; Name:            
; Defined at line: 1
; #Upvalues:       0
; #Parameters:     0
; Is_vararg:       1
; Max Stack Size:  64

       1 [-]: GETIMPORT R0 1; var0 = 0xB009BBC6
       2 [-]: LOADK R1 K2  ; var1 = "/Lotus/Fx/Gameplay/CephalonTear/CephalonTearSpawnAmb"
       3 [-]: CALL R0 2 2  ; var0 = var0(var1)
       4 [-]: GETIMPORT R1 1; var1 = 0xB009BBC6
       5 [-]: LOADK R2 K3  ; var2 = "/Lotus/Fx/Gameplay/CephalonTear/CephalonTearPop"
       6 [-]: CALL R1 2 2  ; var1 = var1(var2)
       7 [-]: GETIMPORT R2 1; var2 = 0xB009BBC6
       8 [-]: LOADK R3 K4  ; var3 = "/Lotus/Sounds/Gameplay/VoidTear/VoidTearOpen"
       9 [-]: CALL R2 2 2  ; var2 = var2(var3)
      10 [-]: GETIMPORT R3 1; var3 = 0xB009BBC6
      11 [-]: LOADK R4 K5  ; var4 = "/Lotus/Sounds/Gameplay/CephalonWeave/CephalonVoidTearOpen"
      12 [-]: CALL R3 2 2  ; var3 = var3(var4)
      13 [-]: GETIMPORT R4 1; var4 = 0xB009BBC6
      14 [-]: LOADK R5 K6  ; var5 = "/Lotus/Sounds/Gameplay/VoidTear/VoidTearClose"
      15 [-]: CALL R4 2 2  ; var4 = var4(var5)
      16 [-]: GETIMPORT R5 1; var5 = 0xB009BBC6
      17 [-]: LOADK R6 K7  ; var6 = "/Lotus/Sounds/Gameplay/CephalonWeave/CephalonVoidTearClose"
      18 [-]: CALL R5 2 2  ; var5 = var5(var6)
      19 [-]: GETIMPORT R6 1; var6 = 0xB009BBC6
      20 [-]: LOADK R7 K8  ; var7 = "/Lotus/Sounds/Gameplay/VoidTear/VoidTearLoopBSeq"
      21 [-]: CALL R6 2 2  ; var6 = var6(var7)
      22 [-]: GETIMPORT R7 1; var7 = 0xB009BBC6
      23 [-]: LOADK R8 K9  ; var8 = "/Lotus/Fx/Gameplay/CephalonTear/CephalonTearCorruptedReplicator"
      24 [-]: CALL R7 2 2  ; var7 = var7(var8)
      25 [-]: GETIMPORT R8 1; var8 = 0xB009BBC6
      26 [-]: LOADK R9 K10 ; var9 = "/Lotus/Fx/Gameplay/CephalonTear/CephalonTearEnemySpawn"
      27 [-]: CALL R8 2 2  ; var8 = var8(var9)
      28 [-]: GETIMPORT R9 1; var9 = 0xB009BBC6
      29 [-]: LOADK R10 K11; var10 = "/Lotus/Fx/Gameplay/CephalonTear/CephalonTearEnemyEscalationProj"
      30 [-]: CALL R9 2 2  ; var9 = var9(var10)
      31 [-]: GETIMPORT R10 1; var10 = 0xB009BBC6
      32 [-]: LOADK R11 K12; var11 = "/Lotus/Fx/Gameplay/CephalonTear/CephalonTearSpawnBeam"
      33 [-]: CALL R10 2 2 ; var10 = var10(var11)
      34 [-]: GETIMPORT R11 1; var11 = 0xB009BBC6
      35 [-]: LOADK R12 K13; var12 = "/Lotus/Sounds/Gameplay/VoidTear/VoidTearTendrilAttach"
      36 [-]: CALL R11 2 2 ; var11 = var11(var12)
      37 [-]: GETIMPORT R12 15; var12 = 0x88EFC25E
      38 [-]: LOADK R13 K16; var13 = "/Lotus/Types/Game/Triggers/CephalonTearTrigger"
      39 [-]: CALL R12 2 2 ; var12 = var12(var13)
      40 [-]: GETIMPORT R13 18; var13 = 0x7ED0A956
      41 [-]: LOADK R14 K19; var14 = "/Lotus/Sounds/Dialog/Nightwave/SeasonThreeGlassmaker/Nora/DGlassFissureDetectNoraNight"
      42 [-]: CALL R13 2 2 ; var13 = var13(var14)
      43 [-]: GETIMPORT R14 18; var14 = 0x7ED0A956
      44 [-]: LOADK R15 K20; var15 = "/Lotus/Sounds/Dialog/Nightwave/SeasonThreeGlassmaker/Nora/DGlassFissureSpawnedNoraNight"
      45 [-]: CALL R14 2 2 ; var14 = var14(var15)
      46 [-]: GETIMPORT R15 18; var15 = 0x7ED0A956
      47 [-]: LOADK R16 K21; var16 = "/Lotus/Sounds/Dialog/Nightwave/SeasonThreeGlassmaker/Nora/DGlassFissureWeakpointNoraNight"
      48 [-]: CALL R15 2 2 ; var15 = var15(var16)
      49 [-]: GETIMPORT R16 15; var16 = 0x88EFC25E
      50 [-]: LOADK R17 K22; var17 = "/Lotus/Types/Enemies/Enhancements/Nightwave/CephalonFissureBipedEnhancement"
      51 [-]: CALL R16 2 2 ; var16 = var16(var17)
      52 [-]: GETIMPORT R17 15; var17 = 0x88EFC25E
      53 [-]: LOADK R18 K23; var18 = "/Lotus/Types/Enemies/Enhancements/Nightwave/CephalonFissureHumanoidEnhancement"
      54 [-]: CALL R17 2 2 ; var17 = var17(var18)
      55 [-]: GETIMPORT R18 15; var18 = 0x88EFC25E
      56 [-]: LOADK R19 K24; var19 = "/Lotus/Types/Enemies/Enhancements/Nightwave/CephalonFissureInfestedEnhancement"
      57 [-]: CALL R18 2 2 ; var18 = var18(var19)
      58 [-]: LOADN R19 3  ; var19 = 3
      59 [-]: LOADN R20 3  ; var20 = 3
      60 [-]: LOADB R21 1  ; var21 = true
      61 [-]: NEWTABLE R22 0 0; var22 = {}
      62 [-]: NEWTABLE R23 0 0; var23 = {}
      63 [-]: LOADN R24 0  ; var24 = 0
      64 [-]: LOADNIL R25  ; var25 = nil
      65 [-]: LOADN R26 0  ; var26 = 0
      66 [-]: LOADN R27 6  ; var27 = 6
      67 [-]: LOADN R28 10 ; var28 = 10
      68 [-]: LOADN R29 0  ; var29 = 0
      69 [-]: LOADN R30 3  ; var30 = 3
      70 [-]: LOADN R31 5  ; var31 = 5
      71 [-]: LOADN R32 0  ; var32 = 0
      72 [-]: LOADNIL R33  ; var33 = nil
      73 [-]: GETIMPORT R34 26; var34 = 0x0469F296
      74 [-]: LOADK R35 K27; var35 = "TENNO"
      75 [-]: CALL R34 2 2 ; var34 = var34(var35)
      76 [-]: GETIMPORT R35 26; var35 = 0x0469F296
      77 [-]: LOADK R36 K28; var36 = "NEUTRAL"
      78 [-]: CALL R35 2 2 ; var35 = var35(var36)
      79 [-]: GETIMPORT R36 26; var36 = 0x0469F296
      80 [-]: LOADK R37 K29; var37 = "VaultPatrol"
      81 [-]: CALL R36 2 2 ; var36 = var36(var37)
      82 [-]: GETIMPORT R37 26; var37 = 0x0469F296
      83 [-]: LOADK R38 K30; var38 = "VoidInvuln"
      84 [-]: CALL R37 2 2 ; var37 = var37(var38)
      85 [-]: GETIMPORT R38 26; var38 = 0x0469F296
      86 [-]: LOADK R39 K31; var39 = "NoGlassTag"
      87 [-]: CALL R38 2 2 ; var38 = var38(var39)
      88 [-]: NEWTABLE R39 0 4; var39 = {}
      89 [-]: GETIMPORT R40 26; var40 = 0x0469F296
      90 [-]: LOADK R41 K32; var41 = "Marine"
      91 [-]: CALL R40 2 2 ; var40 = var40(var41)
      92 [-]: GETIMPORT R41 26; var41 = 0x0469F296
      93 [-]: LOADK R42 K33; var42 = "Spaceman1"
      94 [-]: CALL R41 2 2 ; var41 = var41(var42)
      95 [-]: GETIMPORT R42 26; var42 = 0x0469F296
      96 [-]: LOADK R43 K34; var43 = "GrineerCaptureTarget1"
      97 [-]: CALL R42 2 2 ; var42 = var42(var43)
      98 [-]: GETIMPORT R43 26; var43 = 0x0469F296
      99 [-]: LOADK R44 K35; var44 = "Tenno"
     100 [-]: CALL R43 2 0 ; var43, ... = var43(var44)
     101 [-]: SETLIST R39 R40 -1 [1]; 
     102 [-]: NEWTABLE R40 0 2; var40 = {}
     103 [-]: GETIMPORT R41 26; var41 = 0x0469F296
     104 [-]: LOADK R42 K36; var42 = "BipedPrototype1"
     105 [-]: CALL R41 2 2 ; var41 = var41(var42)
     106 [-]: GETIMPORT R42 26; var42 = 0x0469F296
     107 [-]: LOADK R43 K37; var43 = "RiotBipedPrototype1"
     108 [-]: CALL R42 2 0 ; var42, ... = var42(var43)
     109 [-]: SETLIST R40 R41 -1 [1]; 
     110 [-]: NEWTABLE R41 0 4; var41 = {}
     111 [-]: GETIMPORT R42 26; var42 = 0x0469F296
     112 [-]: LOADK R43 K38; var43 = "Guild"
     113 [-]: CALL R42 2 2 ; var42 = var42(var43)
     114 [-]: GETIMPORT R43 26; var43 = 0x0469F296
     115 [-]: LOADK R44 K39; var44 = "Kubrow"
     116 [-]: CALL R43 2 2 ; var43 = var43(var44)
     117 [-]: GETIMPORT R44 26; var44 = 0x0469F296
     118 [-]: LOADK R45 K40; var45 = "Kavat"
     119 [-]: CALL R44 2 2 ; var44 = var44(var45)
     120 [-]: GETIMPORT R45 26; var45 = 0x0469F296
     121 [-]: LOADK R46 K41; var46 = "QuadrupedPrototype"
     122 [-]: CALL R45 2 0 ; var45, ... = var45(var46)
     123 [-]: SETLIST R41 R42 -1 [1]; 
     124 [-]: GETIMPORT R42 26; var42 = 0x0469F296
     125 [-]: LOADK R43 K42; var43 = "CephalonTearSpawnCycle"
     126 [-]: CALL R42 2 2 ; var42 = var42(var43)
     127 [-]: GETIMPORT R43 26; var43 = 0x0469F296
     128 [-]: LOADK R44 K43; var44 = "CephalonTearRemainingEnemyCount"
     129 [-]: CALL R43 2 2 ; var43 = var43(var44)
     130 [-]: GETIMPORT R44 26; var44 = 0x0469F296
     131 [-]: LOADK R45 K44; var45 = "TearCount"
     132 [-]: CALL R44 2 2 ; var44 = var44(var45)
     133 [-]: GETIMPORT R45 26; var45 = 0x0469F296
     134 [-]: LOADK R46 K45; var46 = "ExcavatorsStarted"
     135 [-]: CALL R45 2 2 ; var45 = var45(var46)
     136 [-]: GETIMPORT R46 47; var46 = 0x2D0FAD09
     137 [-]: LOADK R47 K48; var47 = "Lotus.Scripts.Libs.TableLib"
     138 [-]: CALL R46 2 2 ; var46 = var46(var47)
     139 [-]: GETIMPORT R47 47; var47 = 0x2D0FAD09
     140 [-]: LOADK R48 K49; var48 = "Lotus.Interface.WorldStateUtilities"
     141 [-]: CALL R47 2 2 ; var47 = var47(var48)
     142 [-]: GETIMPORT R48 47; var48 = 0x2D0FAD09
     143 [-]: LOADK R49 K50; var49 = "Lotus.Interface.LotusUtilities"
     144 [-]: CALL R48 2 2 ; var48 = var48(var49)
     145 [-]: GETIMPORT R49 18; var49 = 0x7ED0A956
     146 [-]: LOADK R50 K51; var50 = "/Lotus/Types/Keys/InfestedMicroplanetQuest/InfestedMicroplanetQuestKeyChain"
     147 [-]: CALL R49 2 2 ; var49 = var49(var50)
     148 [-]: GETIMPORT R50 53; var50 = 0x89326C93
     149 [-]: NAMECALL R50 R50 K54; var51 = var50; var50 = var50[0x29EF273D]
     150 [-]: CALL R50 2 2 ; var50 = var50(var51)
     151 [-]: NAMECALL R51 R50 K55; var52 = var50; var51 = var50[0x66905CB0]
     152 [-]: CALL R51 2 2 ; var51 = var51(var52)
     153 [-]: NEWCLOSURE R52 P0; 
     154 [-]: CAPTURE REF R22; 
     155 [-]: SETGLOBAL R52 K56; "OnPlayersChanged" = var52
     156 [-]: DUPCLOSURE R52 K57; 
     157 [-]: CAPTURE VAL R46; 
     158 [-]: CAPTURE VAL R23; 
     159 [-]: DUPCLOSURE R53 K58; 
     160 [-]: CAPTURE VAL R34; 
     161 [-]: CAPTURE VAL R35; 
     162 [-]: CAPTURE VAL R46; 
     163 [-]: CAPTURE VAL R23; 
     164 [-]: CAPTURE VAL R36; 
     165 [-]: CAPTURE VAL R38; 
     166 [-]: CAPTURE VAL R39; 
     167 [-]: CAPTURE VAL R40; 
     168 [-]: CAPTURE VAL R41; 
     169 [-]: DUPCLOSURE R54 K59; 
     170 [-]: CAPTURE VAL R39; 
     171 [-]: CAPTURE VAL R17; 
     172 [-]: CAPTURE VAL R40; 
     173 [-]: CAPTURE VAL R16; 
     174 [-]: CAPTURE VAL R41; 
     175 [-]: CAPTURE VAL R18; 
     176 [-]: NEWCLOSURE R55 P4; 
     177 [-]: CAPTURE VAL R54; 
     178 [-]: CAPTURE VAL R37; 
     179 [-]: CAPTURE REF R24; 
     180 [-]: CAPTURE REF R32; 
     181 [-]: CAPTURE VAL R43; 
     182 [-]: CAPTURE VAL R9; 
     183 [-]: CAPTURE VAL R7; 
     184 [-]: CAPTURE VAL R8; 
     185 [-]: CAPTURE VAL R11; 
     186 [-]: CAPTURE VAL R23; 
     187 [-]: SETGLOBAL R55 K60; "CorruptEnemy" = var55
     188 [-]: DUPCLOSURE R55 K61; 
     189 [-]: CAPTURE VAL R51; 
     190 [-]: CAPTURE VAL R53; 
     191 [-]: NEWCLOSURE R56 P6; 
     192 [-]: CAPTURE VAL R23; 
     193 [-]: CAPTURE REF R24; 
     194 [-]: CAPTURE VAL R43; 
     195 [-]: NEWCLOSURE R57 P7; 
     196 [-]: CAPTURE VAL R56; 
     197 [-]: CAPTURE VAL R23; 
     198 [-]: CAPTURE VAL R13; 
     199 [-]: CAPTURE VAL R47; 
     200 [-]: CAPTURE REF R31; 
     201 [-]: CAPTURE REF R32; 
     202 [-]: DUPCLOSURE R58 K62; 
     203 [-]: CAPTURE VAL R47; 
     204 [-]: NEWCLOSURE R59 P9; 
     205 [-]: CAPTURE REF R25; 
     206 [-]: CAPTURE VAL R42; 
     207 [-]: CAPTURE VAL R57; 
     208 [-]: CAPTURE VAL R58; 
     209 [-]: NEWCLOSURE R60 P10; 
     210 [-]: CAPTURE REF R25; 
     211 [-]: CAPTURE VAL R0; 
     212 [-]: CAPTURE VAL R1; 
     213 [-]: CAPTURE VAL R2; 
     214 [-]: CAPTURE VAL R3; 
     215 [-]: CAPTURE REF R26; 
     216 [-]: CAPTURE REF R21; 
     217 [-]: CAPTURE REF R22; 
     218 [-]: CAPTURE REF R33; 
     219 [-]: CAPTURE VAL R6; 
     220 [-]: CAPTURE REF R24; 
     221 [-]: CAPTURE REF R30; 
     222 [-]: CAPTURE REF R32; 
     223 [-]: CAPTURE REF R31; 
     224 [-]: CAPTURE VAL R53; 
     225 [-]: CAPTURE VAL R10; 
     226 [-]: CAPTURE VAL R43; 
     227 [-]: CAPTURE VAL R44; 
     228 [-]: CAPTURE REF R14; 
     229 [-]: CAPTURE REF R15; 
     230 [-]: DUPCLOSURE R61 K63; 
     231 [-]: SETGLOBAL R61 K64; "OnResourceReady" = var61
     232 [-]: NEWCLOSURE R61 P12; 
     233 [-]: CAPTURE REF R31; 
     234 [-]: CAPTURE REF R30; 
     235 [-]: CAPTURE REF R28; 
     236 [-]: CAPTURE REF R27; 
     237 [-]: CAPTURE REF R19; 
     238 [-]: CAPTURE REF R20; 
     239 [-]: CAPTURE REF R21; 
     240 [-]: CAPTURE VAL R43; 
     241 [-]: CAPTURE VAL R59; 
     242 [-]: DUPCLOSURE R62 K65; 
     243 [-]: NEWCLOSURE R63 P14; 
     244 [-]: CAPTURE VAL R48; 
     245 [-]: CAPTURE VAL R49; 
     246 [-]: CAPTURE VAL R61; 
     247 [-]: CAPTURE VAL R12; 
     248 [-]: CAPTURE REF R25; 
     249 [-]: CAPTURE VAL R0; 
     250 [-]: CAPTURE VAL R59; 
     251 [-]: CAPTURE REF R22; 
     252 [-]: CAPTURE VAL R56; 
     253 [-]: CAPTURE REF R32; 
     254 [-]: CAPTURE REF R31; 
     255 [-]: CAPTURE REF R29; 
     256 [-]: CAPTURE VAL R45; 
     257 [-]: CAPTURE REF R19; 
     258 [-]: CAPTURE REF R28; 
     259 [-]: CAPTURE REF R24; 
     260 [-]: CAPTURE REF R30; 
     261 [-]: CAPTURE VAL R53; 
     262 [-]: CAPTURE VAL R55; 
     263 [-]: CAPTURE VAL R50; 
     264 [-]: CAPTURE VAL R60; 
     265 [-]: CAPTURE REF R26; 
     266 [-]: CAPTURE REF R27; 
     267 [-]: CAPTURE VAL R4; 
     268 [-]: CAPTURE VAL R5; 
     269 [-]: CAPTURE VAL R1; 
     270 [-]: CAPTURE REF R33; 
     271 [-]: CAPTURE REF R20; 
     272 [-]: SETGLOBAL R63 K66; "VoidTear" = var63
     273 [-]: CLOSEUPVALS R14; 
     274 [-]: RETURN R0 0  ; 


; Name:            
; Defined at line: 80
; #Upvalues:       1
; #Parameters:     0
; Is_vararg:       0
; Max Stack Size:  2

       0 [-]: GETIMPORT R0 1; var0 = 0x89326C93
       1 [-]: NAMECALL R0 R0 K2; var1 = var0; var0 = var0[0x7D108DDB]
       2 [-]: CALL R0 2 2  ; var0 = var0(var1)
       3 [-]: SETUPVAL R0 0; upvalues[0] = var0
       4 [-]: RETURN R0 0  ; 


; Name:            
; Defined at line: 84
; #Upvalues:       2
; #Parameters:     1
; Is_vararg:       0
; Max Stack Size:  5

       0 [-]: GETUPVAL R3 0; var3 = upvalues[0]
       1 [-]: GETTABLEKS R2 R3 K0; var2 = var3[0xD16E8ECE]
       2 [-]: GETUPVAL R3 1; var3 = upvalues[1]
       3 [-]: MOVE R4 R0   ; var4 = var0
       4 [-]: CALL R2 3 2  ; var2 = var2(var3, var4)
       5 [-]: LOADN R3 0   ; var3 = 0
       6 [-]: JUMPIFLT R3 R2 L0; goto L0 if var3 < var16777478
       7 [-]: LOADB R1 0 +1; var1 = false
L 0:   8 [-]: LOADB R1 1   ; var1 = true
L 1:   9 [-]: RETURN R1 1  ; 


; Name:            
; Defined at line: 88
; #Upvalues:       9
; #Parameters:     1
; Is_vararg:       0
; Max Stack Size:  9

       0 [-]: FASTCALL1 64 R0 L0; 
       1 [-]: MOVE R2 R0   ; var2 = var0
       2 [-]: GETIMPORT R1 1; var1 = 0x7B998233
       3 [-]: CALL R1 2 2  ; var1 = var1(var2)
L 0:   4 [-]: JUMPIF R1 L22; goto L22 if var1
       5 [-]: NAMECALL R1 R0 K2; var2 = var0; var1 = var0[0x7DAC4C20]
       6 [-]: CALL R1 2 2  ; var1 = var1(var2)
       7 [-]: JUMPIF R1 L22; goto L22 if var1
       8 [-]: NAMECALL R1 R0 K3; var2 = var0; var1 = var0[0x45A0C9E4]
       9 [-]: CALL R1 2 2  ; var1 = var1(var2)
      10 [-]: JUMPIFNOT R1 L22; goto L22 if not var1
      11 [-]: NAMECALL R1 R0 K4; var2 = var0; var1 = var0[0x2047CFE7]
      12 [-]: CALL R1 2 2  ; var1 = var1(var2)
      13 [-]: JUMPIF R1 L22; goto L22 if var1
      14 [-]: NAMECALL R1 R0 K5; var2 = var0; var1 = var0[0xE287C223]
      15 [-]: CALL R1 2 2  ; var1 = var1(var2)
      16 [-]: JUMPIF R1 L22; goto L22 if var1
      17 [-]: NAMECALL R1 R0 K6; var2 = var0; var1 = var0[0x278B099D]
      18 [-]: CALL R1 2 2  ; var1 = var1(var2)
      19 [-]: JUMPIF R1 L22; goto L22 if var1
      20 [-]: NAMECALL R1 R0 K7; var2 = var0; var1 = var0[0x7EF3366A]
      21 [-]: CALL R1 2 2  ; var1 = var1(var2)
      22 [-]: JUMPIF R1 L22; goto L22 if var1
      23 [-]: NAMECALL R1 R0 K8; var2 = var0; var1 = var0[0x2D0A291F]
      24 [-]: CALL R1 2 2  ; var1 = var1(var2)
      25 [-]: GETUPVAL R2 0; var2 = upvalues[0]
      26 [-]: JUMPIFEQ R1 R2 L22; goto L22 if var1 == var520094028
      27 [-]: NAMECALL R1 R0 K8; var2 = var0; var1 = var0[0x2D0A291F]
      28 [-]: CALL R1 2 2  ; var1 = var1(var2)
      29 [-]: GETUPVAL R2 1; var2 = upvalues[1]
      30 [-]: JUMPIFEQ R1 R2 L22; goto L22 if var1 == var-822083252
      31 [-]: NAMECALL R1 R0 K9; var2 = var0; var1 = var0[0x73901ACF]
      32 [-]: CALL R1 2 2  ; var1 = var1(var2)
      33 [-]: JUMPIF R1 L22; goto L22 if var1
      34 [-]: GETUPVAL R3 2; var3 = upvalues[2]
      35 [-]: GETTABLEKS R2 R3 K10; var2 = var3[0xD16E8ECE]
      36 [-]: GETUPVAL R3 3; var3 = upvalues[3]
      37 [-]: MOVE R4 R0   ; var4 = var0
      38 [-]: CALL R2 3 2  ; var2 = var2(var3, var4)
      39 [-]: LOADN R3 0   ; var3 = 0
      40 [-]: JUMPIFLT R3 R2 L1; goto L1 if var3 < var16777478
      41 [-]: LOADB R1 0 +1; var1 = false
L 1:  42 [-]: LOADB R1 1   ; var1 = true
L 2:  43 [-]: JUMPIF R1 L22; goto L22 if var1
      44 [-]: NAMECALL R2 R0 K11; var3 = var0; var2 = var0[0xFA9E477F]
      45 [-]: CALL R2 2 0  ; var2, ... = var2(var3)
      46 [-]: FASTCALL 64 L3; 
      47 [-]: GETIMPORT R1 1; var1 = 0x7B998233
      48 [-]: CALL R1 0 2  ; var1 = var1(var2, ...)
L 3:  49 [-]: JUMPIF R1 L22; goto L22 if var1
      50 [-]: NAMECALL R1 R0 K11; var2 = var0; var1 = var0[0xFA9E477F]
      51 [-]: CALL R1 2 2  ; var1 = var1(var2)
      52 [-]: NAMECALL R1 R1 K12; var2 = var1; var1 = var1[0xAD1E0B4B]
      53 [-]: CALL R1 2 2  ; var1 = var1(var2)
      54 [-]: GETUPVAL R2 4; var2 = upvalues[4]
      55 [-]: JUMPIFNOTEQ R1 R2 L4; goto L4 if var1 ~= var2130706764
      56 [-]: NAMECALL R1 R0 K11; var2 = var0; var1 = var0[0xFA9E477F]
      57 [-]: CALL R1 2 2  ; var1 = var1(var2)
      58 [-]: NAMECALL R1 R1 K13; var2 = var1; var1 = var1[0xEDE38153]
      59 [-]: CALL R1 2 2  ; var1 = var1(var2)
      60 [-]: JUMPIFNOT R1 L22; goto L22 if not var1
L 4:  61 [-]: LOADN R3 1   ; var3 = 1
      62 [-]: GETIMPORT R4 15; var4 = 0x28F30BD5
      63 [-]: LENGTH R1 R4 ; var1 = #var4
      64 [-]: LOADN R2 1   ; var2 = 1
      65 [-]: FORNPREP R1 L7; nforprep start - [escape at L7] -- var1 = iterator
L 5:  66 [-]: GETIMPORT R5 15; var5 = 0x28F30BD5
      67 [-]: GETTABLE R4 R5 R3; var4 = var5[var3]
      68 [-]: JUMPXEQKNIL R4 L6; 
      69 [-]: GETIMPORT R7 15; var7 = 0x28F30BD5
      70 [-]: GETTABLE R6 R7 R3; var6 = var7[var3]
      71 [-]: NAMECALL R4 R0 K16; var5 = var0; var4 = var0[0xF2DEAF69]
      72 [-]: CALL R4 3 2  ; var4 = var4(var5, var6)
      73 [-]: JUMPIFNOT R4 L6; goto L6 if not var4
      74 [-]: LOADB R4 0   ; var4 = false
      75 [-]: RETURN R4 1  ; 
L 6:  76 [-]: FORNLOOP R1 L5; nforloop end - iterate + goto L5
L 7:  77 [-]: NAMECALL R1 R0 K17; var2 = var0; var1 = var0[0x22DA1852]
      78 [-]: CALL R1 2 2  ; var1 = var1(var2)
      79 [-]: GETUPVAL R2 5; var2 = upvalues[5]
      80 [-]: JUMPIFNOTEQ R1 R2 L8; goto L8 if var1 ~= var262
      81 [-]: LOADB R1 0   ; var1 = false
      82 [-]: RETURN R1 1  ; 
L 8:  83 [-]: GETIMPORT R3 19; var3 = gEntityType
      84 [-]: NAMECALL R1 R0 K20; var2 = var0; var1 = var0[0xC1595BD5]
      85 [-]: CALL R1 3 2  ; var1 = var1(var2, var3)
      86 [-]: FASTCALL1 64 R1 L9; 
      87 [-]: MOVE R3 R1   ; var3 = var1
      88 [-]: GETIMPORT R2 1; var2 = 0x7B998233
      89 [-]: CALL R2 2 2  ; var2 = var2(var3)
L 9:  90 [-]: JUMPIF R2 L12; goto L12 if var2
      91 [-]: GETIMPORT R2 22; var2 = 0xC8802016
      92 [-]: MOVE R3 R1   ; var3 = var1
      93 [-]: CALL R2 2 4  ; var2, var3, var4 = var2(var3)
      94 [-]: FORGPREP_INEXT R2 L11; 
L10:  95 [-]: NAMECALL R7 R6 K17; var8 = var6; var7 = var6[0x22DA1852]
      96 [-]: CALL R7 2 2  ; var7 = var7(var8)
      97 [-]: GETUPVAL R8 5; var8 = upvalues[5]
      98 [-]: JUMPIFNOTEQ R7 R8 L11; goto L11 if var7 ~= var1798
      99 [-]: LOADB R7 0   ; var7 = false
     100 [-]: RETURN R7 1  ; 
L11: 101 [-]: FORGLOOP R2 L10 2 [inext]; 
L12: 102 [-]: GETIMPORT R4 24; var4 = gRiotBipedRobotAvatarType
     103 [-]: NAMECALL R2 R0 K16; var3 = var0; var2 = var0[0xF2DEAF69]
     104 [-]: CALL R2 3 2  ; var2 = var2(var3, var4)
     105 [-]: JUMPIFNOT R2 L13; goto L13 if not var2
     106 [-]: LOADB R2 0   ; var2 = false
     107 [-]: RETURN R2 1  ; 
L13: 108 [-]: NAMECALL R2 R0 K25; var3 = var0; var2 = var0[0x61EC8B82]
     109 [-]: CALL R2 2 2  ; var2 = var2(var3)
     110 [-]: LOADN R5 1   ; var5 = 1
     111 [-]: GETUPVAL R6 6; var6 = upvalues[6]
     112 [-]: LENGTH R3 R6 ; var3 = #var6
     113 [-]: LOADN R4 1   ; var4 = 1
     114 [-]: FORNPREP R3 L16; nforprep start - [escape at L16] -- var3 = iterator
L14: 115 [-]: GETUPVAL R7 6; var7 = upvalues[6]
     116 [-]: GETTABLE R6 R7 R5; var6 = var7[var5]
     117 [-]: JUMPIFNOTEQ R2 R6 L15; goto L15 if var2 ~= var67078
     118 [-]: LOADB R6 1   ; var6 = true
     119 [-]: RETURN R6 1  ; 
L15: 120 [-]: FORNLOOP R3 L14; nforloop end - iterate + goto L14
L16: 121 [-]: LOADN R5 1   ; var5 = 1
     122 [-]: GETUPVAL R6 7; var6 = upvalues[7]
     123 [-]: LENGTH R3 R6 ; var3 = #var6
     124 [-]: LOADN R4 1   ; var4 = 1
     125 [-]: FORNPREP R3 L19; nforprep start - [escape at L19] -- var3 = iterator
L17: 126 [-]: GETUPVAL R7 7; var7 = upvalues[7]
     127 [-]: GETTABLE R6 R7 R5; var6 = var7[var5]
     128 [-]: JUMPIFNOTEQ R2 R6 L18; goto L18 if var2 ~= var67078
     129 [-]: LOADB R6 1   ; var6 = true
     130 [-]: RETURN R6 1  ; 
L18: 131 [-]: FORNLOOP R3 L17; nforloop end - iterate + goto L17
L19: 132 [-]: LOADN R5 1   ; var5 = 1
     133 [-]: GETUPVAL R6 8; var6 = upvalues[8]
     134 [-]: LENGTH R3 R6 ; var3 = #var6
     135 [-]: LOADN R4 1   ; var4 = 1
     136 [-]: FORNPREP R3 L22; nforprep start - [escape at L22] -- var3 = iterator
L20: 137 [-]: GETUPVAL R7 8; var7 = upvalues[8]
     138 [-]: GETTABLE R6 R7 R5; var6 = var7[var5]
     139 [-]: JUMPIFNOTEQ R2 R6 L21; goto L21 if var2 ~= var67078
     140 [-]: LOADB R6 1   ; var6 = true
     141 [-]: RETURN R6 1  ; 
L21: 142 [-]: FORNLOOP R3 L20; nforloop end - iterate + goto L20
L22: 143 [-]: LOADB R1 0   ; var1 = false
     144 [-]: RETURN R1 1  ; 


; Name:            
; Defined at line: 154
; #Upvalues:       6
; #Parameters:     1
; Is_vararg:       0
; Max Stack Size:  9

       0 [-]: NAMECALL R1 R0 K0; var2 = var0; var1 = var0[0x61EC8B82]
       1 [-]: CALL R1 2 2  ; var1 = var1(var2)
       2 [-]: LOADN R4 1   ; var4 = 1
       3 [-]: GETUPVAL R5 0; var5 = upvalues[0]
       4 [-]: LENGTH R2 R5 ; var2 = #var5
       5 [-]: LOADN R3 1   ; var3 = 1
       6 [-]: FORNPREP R2 L2; nforprep start - [escape at L2] -- var2 = iterator
L 0:   7 [-]: GETUPVAL R6 0; var6 = upvalues[0]
       8 [-]: GETTABLE R5 R6 R4; var5 = var6[var4]
       9 [-]: JUMPIFNOTEQ R1 R5 L1; goto L1 if var1 ~= var67388
      10 [-]: GETUPVAL R7 1; var7 = upvalues[1]
      11 [-]: LOADB R8 0   ; var8 = false
      12 [-]: NAMECALL R5 R0 K1; var6 = var0; var5 = var0[0x52AE74A4]
      13 [-]: CALL R5 4 1  ; var5(var6, var7, var8)
      14 [-]: RETURN R0 0  ; 
L 1:  15 [-]: FORNLOOP R2 L0; nforloop end - iterate + goto L0
L 2:  16 [-]: LOADN R4 1   ; var4 = 1
      17 [-]: GETUPVAL R5 2; var5 = upvalues[2]
      18 [-]: LENGTH R2 R5 ; var2 = #var5
      19 [-]: LOADN R3 1   ; var3 = 1
      20 [-]: FORNPREP R2 L5; nforprep start - [escape at L5] -- var2 = iterator
L 3:  21 [-]: GETUPVAL R6 2; var6 = upvalues[2]
      22 [-]: GETTABLE R5 R6 R4; var5 = var6[var4]
      23 [-]: JUMPIFNOTEQ R1 R5 L4; goto L4 if var1 ~= var198460
      24 [-]: GETUPVAL R7 3; var7 = upvalues[3]
      25 [-]: LOADB R8 0   ; var8 = false
      26 [-]: NAMECALL R5 R0 K1; var6 = var0; var5 = var0[0x52AE74A4]
      27 [-]: CALL R5 4 1  ; var5(var6, var7, var8)
      28 [-]: RETURN R0 0  ; 
L 4:  29 [-]: FORNLOOP R2 L3; nforloop end - iterate + goto L3
L 5:  30 [-]: LOADN R4 1   ; var4 = 1
      31 [-]: GETUPVAL R5 4; var5 = upvalues[4]
      32 [-]: LENGTH R2 R5 ; var2 = #var5
      33 [-]: LOADN R3 1   ; var3 = 1
      34 [-]: FORNPREP R2 L8; nforprep start - [escape at L8] -- var2 = iterator
L 6:  35 [-]: GETUPVAL R6 4; var6 = upvalues[4]
      36 [-]: GETTABLE R5 R6 R4; var5 = var6[var4]
      37 [-]: JUMPIFNOTEQ R1 R5 L7; goto L7 if var1 ~= var329532
      38 [-]: GETUPVAL R7 5; var7 = upvalues[5]
      39 [-]: LOADB R8 0   ; var8 = false
      40 [-]: NAMECALL R5 R0 K1; var6 = var0; var5 = var0[0x52AE74A4]
      41 [-]: CALL R5 4 1  ; var5(var6, var7, var8)
      42 [-]: RETURN R0 0  ; 
L 7:  43 [-]: FORNLOOP R2 L6; nforloop end - iterate + goto L6
L 8:  44 [-]: RETURN R0 0  ; 


; Name:            
; Defined at line: 178
; #Upvalues:       10
; #Parameters:     1
; Is_vararg:       0
; Max Stack Size:  10

       0 [-]: GETUPVAL R1 0; var1 = upvalues[0]
       1 [-]: MOVE R2 R0   ; var2 = var0
       2 [-]: CALL R1 2 1  ; var1(var2)
       3 [-]: NAMECALL R1 R0 K0; var2 = var0; var1 = var0[0x1AC1655C]
       4 [-]: CALL R1 2 2  ; var1 = var1(var2)
       5 [-]: GETUPVAL R3 1; var3 = upvalues[1]
       6 [-]: LOADN R4 25  ; var4 = 25
       7 [-]: LOADN R5 6   ; var5 = 6
       8 [-]: LOADN R6 0   ; var6 = 0
       9 [-]: NAMECALL R1 R1 K1; var2 = var1; var1 = var1[0xA383DE31]
      10 [-]: CALL R1 6 1  ; var1(var2, var3, var4, var5, var6)
      11 [-]: GETIMPORT R1 3; var1 = 0xCBD666E1
      12 [-]: GETIMPORT R3 6; var3 = 0x55730E1A
      13 [-]: LOADN R4 0   ; var4 = 0
      14 [-]: LOADN R5 1   ; var5 = 1
      15 [-]: CALL R3 3 2  ; var3 = var3(var4, var5)
      16 [-]: MULK R2 R3 K4; var2 = var3 * 0.25
      17 [-]: CALL R1 2 1  ; var1(var2)
      18 [-]: GETIMPORT R1 9; var1 = _T["isStreamingLevel"]
      19 [-]: JUMPIFNOT R1 L0; goto L0 if not var1
      20 [-]: RETURN R0 0  ; 
L 0:  21 [-]: FASTCALL1 64 R0 L1; 
      22 [-]: MOVE R2 R0   ; var2 = var0
      23 [-]: GETIMPORT R1 11; var1 = 0x7B998233
      24 [-]: CALL R1 2 2  ; var1 = var1(var2)
L 1:  25 [-]: JUMPIF R1 L2 ; goto L2 if var1
      26 [-]: NAMECALL R1 R0 K12; var2 = var0; var1 = var0[0x2047CFE7]
      27 [-]: CALL R1 2 2  ; var1 = var1(var2)
      28 [-]: JUMPIFNOT R1 L3; goto L3 if not var1
L 2:  29 [-]: GETUPVAL R2 2; var2 = upvalues[2]
      30 [-]: SUBK R1 R2 K13; var1 = var2 - 1
      31 [-]: SETUPVAL R1 2; upvalues[1] = var2
      32 [-]: GETUPVAL R2 3; var2 = upvalues[3]
      33 [-]: SUBK R1 R2 K13; var1 = var2 - 1
      34 [-]: SETUPVAL R1 3; upvalues[1] = var3
      35 [-]: GETIMPORT R1 15; var1 = 0xBE190284
      36 [-]: GETUPVAL R3 4; var3 = upvalues[4]
      37 [-]: GETUPVAL R4 2; var4 = upvalues[2]
      38 [-]: NAMECALL R1 R1 K16; var2 = var1; var1 = var1[0x751F061D]
      39 [-]: CALL R1 4 1  ; var1(var2, var3, var4)
      40 [-]: RETURN R0 0  ; 
L 3:  41 [-]: GETUPVAL R3 5; var3 = upvalues[5]
      42 [-]: NAMECALL R4 R0 K0; var5 = var0; var4 = var0[0x1AC1655C]
      43 [-]: CALL R4 2 2  ; var4 = var4(var5)
      44 [-]: LOADN R6 0   ; var6 = 0
      45 [-]: NAMECALL R4 R4 K17; var5 = var4; var4 = var4[0x9EB6D632]
      46 [-]: CALL R4 3 0  ; var4, ... = var4(var5, var6)
      47 [-]: NAMECALL R1 R0 K18; var2 = var0; var1 = var0[0x47901F07]
      48 [-]: CALL R1 0 1  ; var1(var2, ...)
      49 [-]: GETUPVAL R4 6; var4 = upvalues[6]
      50 [-]: NAMECALL R2 R0 K19; var3 = var0; var2 = var0[0xC9F6A7D7]
      51 [-]: CALL R2 3 0  ; var2, ... = var2(var3, var4)
      52 [-]: FASTCALL 64 L4; 
      53 [-]: GETIMPORT R1 11; var1 = 0x7B998233
      54 [-]: CALL R1 0 2  ; var1 = var1(var2, ...)
L 4:  55 [-]: JUMPIF R1 L5 ; goto L5 if var1
      56 [-]: GETIMPORT R1 21; var1 = 0x3D106989
      57 [-]: LOADK R2 K22 ; var2 = "Trying to re-corrupt an avatar!"
      58 [-]: CALL R1 2 1  ; var1(var2)
      59 [-]: RETURN R0 0  ; 
L 5:  60 [-]: GETUPVAL R3 6; var3 = upvalues[6]
      61 [-]: GETIMPORT R4 24; var4 = EMPTY_SYMBOL
      62 [-]: NAMECALL R1 R0 K18; var2 = var0; var1 = var0[0x47901F07]
      63 [-]: CALL R1 4 1  ; var1(var2, var3, var4)
      64 [-]: GETUPVAL R3 7; var3 = upvalues[7]
      65 [-]: GETIMPORT R4 24; var4 = EMPTY_SYMBOL
      66 [-]: NAMECALL R1 R0 K18; var2 = var0; var1 = var0[0x47901F07]
      67 [-]: CALL R1 4 1  ; var1(var2, var3, var4)
      68 [-]: GETUPVAL R3 8; var3 = upvalues[8]
      69 [-]: LOADB R4 0   ; var4 = false
      70 [-]: NAMECALL R1 R0 K25; var2 = var0; var1 = var0[0x659D451F]
      71 [-]: CALL R1 4 1  ; var1(var2, var3, var4)
      72 [-]: NAMECALL R1 R0 K0; var2 = var0; var1 = var0[0x1AC1655C]
      73 [-]: CALL R1 2 2  ; var1 = var1(var2)
      74 [-]: NAMECALL R3 R0 K0; var4 = var0; var3 = var0[0x1AC1655C]
      75 [-]: CALL R3 2 2  ; var3 = var3(var4)
      76 [-]: NAMECALL R3 R3 K26; var4 = var3; var3 = var3[0xB87F958D]
      77 [-]: CALL R3 2 0  ; var3, ... = var3(var4)
      78 [-]: NAMECALL R1 R1 K27; var2 = var1; var1 = var1[0x57369B8B]
      79 [-]: CALL R1 0 1  ; var1(var2, ...)
      80 [-]: NAMECALL R3 R0 K28; var4 = var0; var3 = var0[0xB40C191A]
      81 [-]: CALL R3 2 0  ; var3, ... = var3(var4)
      82 [-]: NAMECALL R1 R0 K29; var2 = var0; var1 = var0[0x014DB014]
      83 [-]: CALL R1 0 1  ; var1(var2, ...)
      84 [-]: NAMECALL R1 R0 K0; var2 = var0; var1 = var0[0x1AC1655C]
      85 [-]: CALL R1 2 2  ; var1 = var1(var2)
      86 [-]: LOADB R3 0   ; var3 = false
      87 [-]: NAMECALL R1 R1 K30; var2 = var1; var1 = var1[0x875BAC8F]
      88 [-]: CALL R1 3 1  ; var1(var2, var3)
      89 [-]: GETIMPORT R1 6; var1 = 0x55730E1A
      90 [-]: LOADN R2 0   ; var2 = 0
      91 [-]: LOADN R3 3   ; var3 = 3
      92 [-]: CALL R1 3 2  ; var1 = var1(var2, var3)
      93 [-]: GETIMPORT R4 32; var4 = 0x0469F296
      94 [-]: LOADK R5 K33 ; var5 = "ELECTRIFIED_LOOP"
      95 [-]: CALL R4 2 2  ; var4 = var4(var5)
      96 [-]: LOADB R5 0   ; var5 = false
      97 [-]: LOADN R6 3   ; var6 = 3
      98 [-]: LOADN R7 2   ; var7 = 2
      99 [-]: LOADB R8 1   ; var8 = true
     100 [-]: MOVE R9 R1   ; var9 = var1
     101 [-]: NAMECALL R2 R0 K34; var3 = var0; var2 = var0[0x0F89A4D4]
     102 [-]: CALL R2 8 1  ; var2(var3, var4, var5, var6, var7, var8, var9)
     103 [-]: GETIMPORT R2 3; var2 = 0xCBD666E1
     104 [-]: LOADN R3 1   ; var3 = 1
     105 [-]: CALL R2 2 1  ; var2(var3)
     106 [-]: GETIMPORT R5 32; var5 = 0x0469F296
     107 [-]: LOADK R6 K35 ; var6 = "ELECTRIFIED_END"
     108 [-]: CALL R5 2 2  ; var5 = var5(var6)
     109 [-]: LOADB R6 1   ; var6 = true
     110 [-]: LOADN R7 3   ; var7 = 3
     111 [-]: LOADN R8 1   ; var8 = 1
     112 [-]: LOADB R9 1   ; var9 = true
     113 [-]: NAMECALL R3 R0 K34; var4 = var0; var3 = var0[0x0F89A4D4]
     114 [-]: CALL R3 7 0  ; var3, ... = var3(var4, var5, var6, var7, var8, var9)
     115 [-]: FASTCALL 64 L6; 
     116 [-]: GETIMPORT R2 11; var2 = 0x7B998233
     117 [-]: CALL R2 0 2  ; var2 = var2(var3, ...)
L 6: 118 [-]: JUMPIFNOT R2 L7; goto L7 if not var2
     119 [-]: LOADNIL R4   ; var4 = nil
     120 [-]: LOADB R5 0   ; var5 = false
     121 [-]: LOADN R6 2   ; var6 = 2
     122 [-]: LOADN R7 1   ; var7 = 1
     123 [-]: LOADB R8 0   ; var8 = false
     124 [-]: NAMECALL R2 R0 K36; var3 = var0; var2 = var0[0x5D985C7E]
     125 [-]: CALL R2 7 1  ; var2(var3, var4, var5, var6, var7, var8)
L 7: 126 [-]: NAMECALL R2 R0 K0; var3 = var0; var2 = var0[0x1AC1655C]
     127 [-]: CALL R2 2 2  ; var2 = var2(var3)
     128 [-]: GETUPVAL R4 1; var4 = upvalues[1]
     129 [-]: NAMECALL R2 R2 K37; var3 = var2; var2 = var2[0x8E3E343E]
     130 [-]: CALL R2 3 1  ; var2(var3, var4)
     131 [-]: NAMECALL R2 R0 K38; var3 = var0; var2 = var0[0xFA9E477F]
     132 [-]: CALL R2 2 2  ; var2 = var2(var3)
     133 [-]: FASTCALL1 64 R2 L8; 
     134 [-]: MOVE R4 R2   ; var4 = var2
     135 [-]: GETIMPORT R3 11; var3 = 0x7B998233
     136 [-]: CALL R3 2 2  ; var3 = var3(var4)
L 8: 137 [-]: JUMPIF R3 L9 ; goto L9 if var3
     138 [-]: NAMECALL R3 R2 K39; var4 = var2; var3 = var2[0x9E21E394]
     139 [-]: CALL R3 2 1  ; var3(var4)
L 9: 140 [-]: GETUPVAL R4 9; var4 = upvalues[9]
     141 [-]: FASTCALL2 52 R4 R0 L10; 
     142 [-]: MOVE R5 R0   ; var5 = var0
     143 [-]: GETIMPORT R3 42; var3 = 0x33BDD652[0x23D5322F]
     144 [-]: CALL R3 3 1  ; var3(var4, var5)
L10: 145 [-]: RETURN R0 0  ; 


; Name:            
; Defined at line: 225
; #Upvalues:       2
; #Parameters:     0
; Is_vararg:       0
; Max Stack Size:  11

       0 [-]: GETIMPORT R0 1; var0 = 0x89326C93
       1 [-]: NAMECALL R0 R0 K2; var1 = var0; var0 = var0[0x8B5B1F58]
       2 [-]: CALL R0 2 2  ; var0 = var0(var1)
       3 [-]: GETIMPORT R1 1; var1 = 0x89326C93
       4 [-]: NAMECALL R1 R1 K3; var2 = var1; var1 = var1[0x78298275]
       5 [-]: CALL R1 2 2  ; var1 = var1(var2)
       6 [-]: LOADK R2 K4  ; var2 = 3.4028234663852886e+38
       7 [-]: GETIMPORT R3 6; var3 = 0xC8802016
       8 [-]: MOVE R4 R0   ; var4 = var0
       9 [-]: CALL R3 2 4  ; var3, var4, var5 = var3(var4)
      10 [-]: FORGPREP_INEXT R3 L1; 
L 0:  11 [-]: GETUPVAL R8 0; var8 = upvalues[0]
      12 [-]: MOVE R10 R7  ; var10 = var7
      13 [-]: NAMECALL R8 R8 K7; var9 = var8; var8 = var8[0x038C6583]
      14 [-]: CALL R8 3 2  ; var8 = var8(var9, var10)
      15 [-]: JUMPIFNOTLT R8 R2 L1; goto L1 if var8 >= var524846
      16 [-]: MOVE R2 R8   ; var2 = var8
      17 [-]: MOVE R1 R7   ; var1 = var7
L 1:  18 [-]: FORGLOOP R3 L0 2 [inext]; 
      19 [-]: GETIMPORT R3 1; var3 = 0x89326C93
      20 [-]: GETIMPORT R5 9; var5 = gLotusNpcAvatarType
      21 [-]: NAMECALL R6 R1 K10; var7 = var1; var6 = var1[0xD1586535]
      22 [-]: CALL R6 2 2  ; var6 = var6(var7)
      23 [-]: LOADN R7 0   ; var7 = 0
      24 [-]: LOADN R8 50  ; var8 = 50
      25 [-]: NAMECALL R3 R3 K11; var4 = var3; var3 = var3[0xFB669000]
      26 [-]: CALL R3 6 2  ; var3 = var3(var4, var5, var6, var7, var8)
      27 [-]: LENGTH R6 R3 ; var6 = #var3
      28 [-]: LOADN R4 1   ; var4 = 1
      29 [-]: LOADN R5 -1  ; var5 = -1
      30 [-]: FORNPREP R4 L4; nforprep start - [escape at L4] -- var4 = iterator
L 2:  31 [-]: GETUPVAL R7 1; var7 = upvalues[1]
      32 [-]: GETTABLE R8 R3 R6; var8 = var3[var6]
      33 [-]: CALL R7 2 2  ; var7 = var7(var8)
      34 [-]: JUMPIF R7 L3 ; goto L3 if var7
      35 [-]: GETIMPORT R7 14; var7 = 0x33BDD652[0x9C1F3B5A]
      36 [-]: MOVE R8 R3   ; var8 = var3
      37 [-]: MOVE R9 R6   ; var9 = var6
      38 [-]: CALL R7 3 1  ; var7(var8, var9)
L 3:  39 [-]: FORNLOOP R4 L2; nforloop end - iterate + goto L2
L 4:  40 [-]: RETURN R3 1  ; 


; Name:            
; Defined at line: 246
; #Upvalues:       3
; #Parameters:     0
; Is_vararg:       0
; Max Stack Size:  7

       0 [-]: GETUPVAL R3 0; var3 = upvalues[0]
       1 [-]: LENGTH R2 R3 ; var2 = #var3
       2 [-]: LOADN R0 1   ; var0 = 1
       3 [-]: LOADN R1 -1  ; var1 = -1
       4 [-]: FORNPREP R0 L5; nforprep start - [escape at L5] -- var0 = iterator
L 0:   5 [-]: GETUPVAL R4 0; var4 = upvalues[0]
       6 [-]: GETTABLE R3 R4 R2; var3 = var4[var2]
       7 [-]: FASTCALL1 64 R3 L1; 
       8 [-]: MOVE R5 R3   ; var5 = var3
       9 [-]: GETIMPORT R4 1; var4 = 0x7B998233
      10 [-]: CALL R4 2 2  ; var4 = var4(var5)
L 1:  11 [-]: JUMPIF R4 L2 ; goto L2 if var4
      12 [-]: NAMECALL R4 R3 K2; var5 = var3; var4 = var3[0x2047CFE7]
      13 [-]: CALL R4 2 2  ; var4 = var4(var5)
      14 [-]: JUMPIFNOT R4 L4; goto L4 if not var4
L 2:  15 [-]: GETIMPORT R4 5; var4 = 0x33BDD652[0x9C1F3B5A]
      16 [-]: GETUPVAL R5 0; var5 = upvalues[0]
      17 [-]: MOVE R6 R2   ; var6 = var2
      18 [-]: CALL R4 3 1  ; var4(var5, var6)
      19 [-]: GETUPVAL R6 1; var6 = upvalues[1]
      20 [-]: SUBK R5 R6 K6; var5 = var6 - 1
      21 [-]: FASTCALL2K 18 R5 K7 L3; 
      22 [-]: LOADK R6 K7  ; var6 = 0
      23 [-]: GETIMPORT R4 10; var4 = 0x5BCED4C4[0xB62ECFE0]
      24 [-]: CALL R4 3 2  ; var4 = var4(var5, var6)
L 3:  25 [-]: SETUPVAL R4 1; upvalues[4] = var1
L 4:  26 [-]: FORNLOOP R0 L0; nforloop end - iterate + goto L0
L 5:  27 [-]: GETIMPORT R0 12; var0 = 0x89326C93
      28 [-]: NAMECALL R0 R0 K13; var1 = var0; var0 = var0[0x18D05D30]
      29 [-]: CALL R0 2 2  ; var0 = var0(var1)
      30 [-]: JUMPIFNOT R0 L6; goto L6 if not var0
      31 [-]: GETIMPORT R0 15; var0 = 0xBE190284
      32 [-]: GETUPVAL R2 2; var2 = upvalues[2]
      33 [-]: GETUPVAL R3 1; var3 = upvalues[1]
      34 [-]: NAMECALL R0 R0 K16; var1 = var0; var0 = var0[0x751F061D]
      35 [-]: CALL R0 4 1  ; var0(var1, var2, var3)
L 6:  36 [-]: RETURN R0 0  ; 


; Name:            
; Defined at line: 259
; #Upvalues:       6
; #Parameters:     0
; Is_vararg:       0
; Max Stack Size:  10

       0 [-]: GETUPVAL R0 0; var0 = upvalues[0]
       1 [-]: CALL R0 1 1  ; var0()
       2 [-]: GETUPVAL R1 1; var1 = upvalues[1]
       3 [-]: LENGTH R0 R1 ; var0 = #var1
       4 [-]: LOADN R1 0   ; var1 = 0
       5 [-]: JUMPIFNOTLT R1 R0 L4; goto L4 if var1 >= var65569
       6 [-]: GETIMPORT R0 1; var0 = 0x3D106989
       7 [-]: LOADK R1 K2  ; var1 = "CephalonTear giving up on spawning new Fissures this round, because of the following avatars: "
       8 [-]: CALL R0 2 1  ; var0(var1)
       9 [-]: GETUPVAL R3 1; var3 = upvalues[1]
      10 [-]: LENGTH R2 R3 ; var2 = #var3
      11 [-]: LOADN R0 1   ; var0 = 1
      12 [-]: LOADN R1 -1  ; var1 = -1
      13 [-]: FORNPREP R0 L3; nforprep start - [escape at L3] -- var0 = iterator
L 0:  14 [-]: GETUPVAL R4 1; var4 = upvalues[1]
      15 [-]: GETTABLE R3 R4 R2; var3 = var4[var2]
      16 [-]: FASTCALL1 64 R3 L1; 
      17 [-]: MOVE R5 R3   ; var5 = var3
      18 [-]: GETIMPORT R4 4; var4 = 0x7B998233
      19 [-]: CALL R4 2 2  ; var4 = var4(var5)
L 1:  20 [-]: JUMPIF R4 L2 ; goto L2 if var4
      21 [-]: NAMECALL R4 R3 K5; var5 = var3; var4 = var3[0x2047CFE7]
      22 [-]: CALL R4 2 2  ; var4 = var4(var5)
      23 [-]: JUMPIF R4 L2 ; goto L2 if var4
      24 [-]: GETIMPORT R4 1; var4 = 0x3D106989
      25 [-]: LOADK R6 K6  ; var6 = "CephalonTear live avatars: "
      26 [-]: NAMECALL R7 R3 K7; var8 = var3; var7 = var3[0xED4E0128]
      27 [-]: CALL R7 2 2  ; var7 = var7(var8)
      28 [-]: CONCAT R5 R6 R7; var5 = var6 .. var7
      29 [-]: CALL R4 2 1  ; var4(var5)
L 2:  30 [-]: FORNLOOP R0 L0; nforloop end - iterate + goto L0
L 3:  31 [-]: RETURN R0 0  ; 
L 4:  32 [-]: GETIMPORT R1 9; var1 = 0xBE190284
      33 [-]: FASTCALL1 64 R1 L5; 
      34 [-]: GETIMPORT R0 4; var0 = 0x7B998233
      35 [-]: CALL R0 2 2  ; var0 = var0(var1)
L 5:  36 [-]: JUMPIF R0 L6 ; goto L6 if var0
      37 [-]: GETIMPORT R0 9; var0 = 0xBE190284
      38 [-]: GETUPVAL R2 2; var2 = upvalues[2]
      39 [-]: NAMECALL R0 R0 K10; var1 = var0; var0 = var0[0xC19D05D7]
      40 [-]: CALL R0 3 1  ; var0(var1, var2)
L 6:  41 [-]: GETUPVAL R1 3; var1 = upvalues[3]
      42 [-]: GETTABLEKS R0 R1 K11; var0 = var1[0x8D66EC64]
      43 [-]: LOADK R1 K12 ; var1 = "ctc"
      44 [-]: LOADN R2 5   ; var2 = 5
      45 [-]: CALL R0 3 2  ; var0 = var0(var1, var2)
      46 [-]: GETUPVAL R2 3; var2 = upvalues[3]
      47 [-]: GETTABLEKS R1 R2 K11; var1 = var2[0x8D66EC64]
      48 [-]: LOADK R2 K13 ; var2 = "ctcm"
      49 [-]: LOADN R3 5   ; var3 = 5
      50 [-]: CALL R1 3 2  ; var1 = var1(var2, var3)
      51 [-]: GETIMPORT R2 15; var2 = 0x9BA7909F
      52 [-]: LOADK R4 K16 ; var4 = "LotusGameRules.CephalonTearSpawnInSimulacrum"
      53 [-]: NAMECALL R2 R2 K17; var3 = var2; var2 = var2[0xBF9494FC]
      54 [-]: CALL R2 3 2  ; var2 = var2(var3, var4)
      55 [-]: JUMPIFNOT R2 L7; goto L7 if not var2
      56 [-]: GETIMPORT R2 9; var2 = 0xBE190284
      57 [-]: GETIMPORT R4 19; var4 = 0x7ED0A956
      58 [-]: LOADK R5 K20 ; var5 = "/Lotus/Types/GameRules/LotusDangerRoomGameRules"
      59 [-]: CALL R4 2 0  ; var4, ... = var4(var5)
      60 [-]: NAMECALL R2 R2 K21; var3 = var2; var2 = var2[0xF2DEAF69]
      61 [-]: CALL R2 0 2  ; var2 = var2(var3, ...)
      62 [-]: JUMPIFNOT R2 L7; goto L7 if not var2
      63 [-]: LOADN R2 10000; var2 = 10000
      64 [-]: SETUPVAL R2 4; upvalues[2] = var4
      65 [-]: JUMP L11     ; goto L11
L 7:  66 [-]: LOADN R2 0   ; var2 = 0
      67 [-]: JUMPIFNOTLT R2 R0 L11; goto L11 if var2 >= var196928
      68 [-]: JUMPIFNOTLT R1 R0 L8; goto L8 if var1 >= var262153
      69 [-]: SETUPVAL R0 4; upvalues[0] = var4
      70 [-]: JUMP L11     ; goto L11
L 8:  71 [-]: GETIMPORT R2 9; var2 = 0xBE190284
      72 [-]: NAMECALL R2 R2 K22; var3 = var2; var2 = var2[0xEF893AEC]
      73 [-]: CALL R2 2 2  ; var2 = var2(var3)
      74 [-]: GETTABLEKS R8 R2 K24; var8 = var2["minEnemyLevel"]
      75 [-]: FASTCALL2K 19 R8 K23 L9; 
      76 [-]: LOADK R9 K23 ; var9 = 100
      77 [-]: GETIMPORT R7 27; var7 = 0x5BCED4C4[0xAC1B386A]
      78 [-]: CALL R7 3 2  ; var7 = var7(var8, var9)
L 9:       80 [-]: SUB R7 R1 R0 ; var7 = var1 - var0
      81 [-]: MUL R5 R6 R7 ; var5 = var6 * var7
      82 [-]: ADD R4 R5 R0 ; var4 = var5 + var0
      83 [-]: FASTCALL1 12 R4 L10; 
      84 [-]: GETIMPORT R3 29; var3 = 0x5BCED4C4[0x55F27C30]
      85 [-]: CALL R3 2 2  ; var3 = var3(var4)
L10:  86 [-]: SETUPVAL R3 4; upvalues[3] = var4
L11:  87 [-]: LOADN R2 0   ; var2 = 0
      88 [-]: SETUPVAL R2 5; upvalues[2] = var5
      89 [-]: RETURN R0 0  ; 


; Name:            
; Defined at line: 296
; #Upvalues:       1
; #Parameters:     0
; Is_vararg:       0
; Max Stack Size:  14

       0 [-]: LOADNIL R0   ; var0 = nil
       1 [-]: LOADNIL R1   ; var1 = nil
       2 [-]: GETIMPORT R2 1; var2 = 0x9BA7909F
       3 [-]: LOADK R4 K2  ; var4 = "LotusGameRules.CephalonTearForcedSpawnInterval"
       4 [-]: NAMECALL R2 R2 K3; var3 = var2; var2 = var2[0xD1B7B396]
       5 [-]: CALL R2 3 2  ; var2 = var2(var3, var4)
       6 [-]: LOADN R3 0   ; var3 = 0
       7 [-]: JUMPIFNOTLT R3 R2 L0; goto L0 if var3 >= var67240005
       8 [-]: MULK R0 R2 K4; var0 = var2 * 60
           10 [-]: JUMP L1      ; goto L1
L 0:  11 [-]: GETUPVAL R4 0; var4 = upvalues[0]
      12 [-]: GETTABLEKS R3 R4 K6; var3 = var4[0x8D66EC64]
      13 [-]: LOADK R4 K7  ; var4 = "ctsi"
      14 [-]: LOADN R5 30  ; var5 = 30
      15 [-]: CALL R3 3 2  ; var3 = var3(var4, var5)
      16 [-]: MULK R0 R3 K4; var0 = var3 * 60
      17 [-]: GETUPVAL R4 0; var4 = upvalues[0]
      18 [-]: GETTABLEKS R3 R4 K6; var3 = var4[0x8D66EC64]
      19 [-]: LOADK R4 K8  ; var4 = "ctsb"
      20 [-]: LOADN R5 5   ; var5 = 5
      21 [-]: CALL R3 3 2  ; var3 = var3(var4, var5)
      22 [-]: MULK R1 R3 K4; var1 = var3 * 60
L 1:  23 [-]: GETIMPORT R4 11; var4 = 0x34291F5C[0x397B920F]
      24 [-]: GETIMPORT R7 13; var7 = 0x25D99D89
      25 [-]: NAMECALL R7 R7 K14; var8 = var7; var7 = var7[0x69727E0B]
      26 [-]: CALL R7 2 2  ; var7 = var7(var8)
      27 [-]: GETTABLEKS R6 R7 K15; var6 = var7["mSeasonInfo"]
      28 [-]: GETTABLEKS R5 R6 K16; var5 = var6["mActivation"]
      29 [-]: CALL R4 2 2  ; var4 = var4(var5)
      30 [-]: FASTCALL1 2 R4 L2; 
      31 [-]: GETIMPORT R3 19; var3 = 0x5BCED4C4[0xE4A5B3CA]
      32 [-]: CALL R3 2 2  ; var3 = var3(var4)
L 2:  33 [-]: DIV R5 R3 R0 ; var5 = var3 / var0
      34 [-]: FASTCALL1 12 R5 L3; 
      35 [-]: GETIMPORT R4 21; var4 = 0x5BCED4C4[0x55F27C30]
      36 [-]: CALL R4 2 2  ; var4 = var4(var5)
L 3:  37 [-]: GETIMPORT R5 23; var5 = 0xFFD438AB
      38 [-]: CALL R5 1 2  ; var5 = var5()
      39 [-]: LOADN R6 -1  ; var6 = -1
L 4:  40 [-]: MUL R8 R4 R0 ; var8 = var4 * var0
           42 [-]: ADD R7 R8 R9 ; var7 = var8 + var9
      43 [-]: ADDK R10 R4 K24; var10 = var4 + 1
      44 [-]: MUL R9 R10 R0; var9 = var10 * var0
           46 [-]: SUB R8 R9 R10; var8 = var9 - var10
      47 [-]: GETIMPORT R9 26; var9 = 0x4F6851FF
      48 [-]: GETIMPORT R10 28; var10 = 0x0997DBE6
      49 [-]: LOADK R12 K29; var12 = 71237
      50 [-]: MULK R13 R4 K30; var13 = var4 * 127
      51 [-]: ADD R11 R12 R13; var11 = var12 + var13
      52 [-]: CALL R10 2 0 ; var10, ... = var10(var11)
      53 [-]: CALL R9 0 1  ; var9(var10, ...)
      54 [-]: GETIMPORT R9 32; var9 = 0x0C5E62F9
      55 [-]: MOVE R10 R7  ; var10 = var7
      56 [-]: MOVE R11 R8  ; var11 = var8
      57 [-]: CALL R9 3 2  ; var9 = var9(var10, var11)
      58 [-]: MOVE R6 R9   ; var6 = var9
      59 [-]: JUMPIFNOTLT R6 R3 L6; goto L6 if var6 >= var402916360
      60 [-]: ADDK R4 R4 K24; var4 = var4 + 1
      61 [-]: JUMP L5      ; goto L5
      62 [-]: JUMP L6      ; goto L6
L 5:  63 [-]: JUMPBACK L4  ; goto L4
L 6:  64 [-]: GETIMPORT R7 34; var7 = _T
      65 [-]: SETTABLEKS R4 R7 K35; var4["NextSpawningTearCycle"] = var7
      66 [-]: GETIMPORT R7 26; var7 = 0x4F6851FF
      67 [-]: MOVE R8 R5   ; var8 = var5
      68 [-]: CALL R7 2 1  ; var7(var8)
      69 [-]: SUB R7 R6 R3 ; var7 = var6 - var3
      70 [-]: RETURN R7 1  ; 


; Name:            
; Defined at line: 337
; #Upvalues:       4
; #Parameters:     0
; Is_vararg:       0
; Max Stack Size:  4

       0 [-]: GETIMPORT R0 2; var0 = _T["CephalonTearSpawnTimer"]
       1 [-]: JUMPXEQKNIL R0 L5; 
       2 [-]: GETIMPORT R0 2; var0 = _T["CephalonTearSpawnTimer"]
       3 [-]: LOADN R1 0   ; var1 = 0
       4 [-]: JUMPIFNOTLT R1 R0 L5; goto L5 if var1 >= var196641
       5 [-]: GETIMPORT R0 3; var0 = _T
       6 [-]: GETIMPORT R2 2; var2 = _T["CephalonTearSpawnTimer"]
       7 [-]: GETIMPORT R3 5; var3 = 0xB693B6C1
       8 [-]: CALL R3 1 2  ; var3 = var3()
       9 [-]: SUB R1 R2 R3 ; var1 = var2 - var3
      10 [-]: SETTABLEKS R1 R0 K1; var1["CephalonTearSpawnTimer"] = var0
      11 [-]: GETIMPORT R0 2; var0 = _T["CephalonTearSpawnTimer"]
      12 [-]: LOADN R1 0   ; var1 = 0
      13 [-]: JUMPIFNOTLT R0 R1 L4; goto L4 if var0 >= var131105
      14 [-]: GETIMPORT R0 2; var0 = _T["CephalonTearSpawnTimer"]
      15 [-]: LOADN R1 -60 ; var1 = -60
      16 [-]: JUMPIFNOTLT R1 R0 L4; goto L4 if var1 >= var458785
      17 [-]: GETIMPORT R0 7; var0 = 0xBE190284
      18 [-]: NAMECALL R0 R0 K8; var1 = var0; var0 = var0[0x0AF64C14]
      19 [-]: CALL R0 2 2  ; var0 = var0(var1)
      20 [-]: JUMPIF R0 L3 ; goto L3 if var0
      21 [-]: GETUPVAL R1 0; var1 = upvalues[0]
      22 [-]: FASTCALL1 64 R1 L0; 
      23 [-]: GETIMPORT R0 10; var0 = 0x7B998233
      24 [-]: CALL R0 2 2  ; var0 = var0(var1)
L 0:  25 [-]: JUMPIFNOT R0 L2; goto L2 if not var0
      26 [-]: GETIMPORT R0 12; var0 = 0x14459A1C
      27 [-]: JUMPIFNOT R0 L1; goto L1 if not var0
      28 [-]: GETIMPORT R0 7; var0 = 0xBE190284
      29 [-]: GETUPVAL R2 1; var2 = upvalues[1]
      30 [-]: NAMECALL R0 R0 K13; var1 = var0; var0 = var0[0x0EB34C69]
      31 [-]: CALL R0 3 2  ; var0 = var0(var1, var2)
      32 [-]: GETIMPORT R1 15; var1 = _T["NextSpawningTearCycle"]
      33 [-]: JUMPIFEQ R0 R1 L2; goto L2 if var0 == var131132
L 1:  34 [-]: GETUPVAL R0 2; var0 = upvalues[2]
      35 [-]: CALL R0 1 1  ; var0()
L 2:  36 [-]: GETIMPORT R0 15; var0 = _T["NextSpawningTearCycle"]
      37 [-]: JUMPXEQKNIL R0 L3; 
      38 [-]: GETIMPORT R0 7; var0 = 0xBE190284
      39 [-]: GETUPVAL R2 1; var2 = upvalues[1]
      40 [-]: GETIMPORT R3 15; var3 = _T["NextSpawningTearCycle"]
      41 [-]: NAMECALL R0 R0 K16; var1 = var0; var0 = var0[0x751F061D]
      42 [-]: CALL R0 4 1  ; var0(var1, var2, var3)
L 3:  43 [-]: GETIMPORT R0 3; var0 = _T
      44 [-]: GETUPVAL R1 3; var1 = upvalues[3]
      45 [-]: CALL R1 1 2  ; var1 = var1()
      46 [-]: SETTABLEKS R1 R0 K1; var1["CephalonTearSpawnTimer"] = var0
      47 [-]: RETURN R0 0  ; 
L 4:  48 [-]: GETIMPORT R0 2; var0 = _T["CephalonTearSpawnTimer"]
      49 [-]: LOADN R1 -60 ; var1 = -60
      50 [-]: JUMPIFNOTLT R0 R1 L6; goto L6 if var0 >= var196641
      51 [-]: GETIMPORT R0 3; var0 = _T
      52 [-]: GETUPVAL R1 3; var1 = upvalues[3]
      53 [-]: CALL R1 1 2  ; var1 = var1()
      54 [-]: SETTABLEKS R1 R0 K1; var1["CephalonTearSpawnTimer"] = var0
      55 [-]: RETURN R0 0  ; 
L 5:  56 [-]: GETIMPORT R0 3; var0 = _T
      57 [-]: GETUPVAL R1 3; var1 = upvalues[3]
      58 [-]: CALL R1 1 2  ; var1 = var1()
      59 [-]: SETTABLEKS R1 R0 K1; var1["CephalonTearSpawnTimer"] = var0
L 6:  60 [-]: RETURN R0 0  ; 


; Name:            
; Defined at line: 364
; #Upvalues:       20
; #Parameters:     2
; Is_vararg:       0
; Max Stack Size:  15

       0 [-]: GETIMPORT R2 1; var2 = 0x89326C93
       1 [-]: GETUPVAL R4 1; var4 = upvalues[1]
       2 [-]: MOVE R5 R1   ; var5 = var1
       3 [-]: GETIMPORT R6 3; var6 = ZERO_ROTATION
       4 [-]: NAMECALL R2 R2 K4; var3 = var2; var2 = var2[0x05909209]
       5 [-]: CALL R2 5 2  ; var2 = var2(var3, var4, var5, var6)
       6 [-]: SETUPVAL R2 0; upvalues[2] = var0
       7 [-]: GETIMPORT R2 1; var2 = 0x89326C93
       8 [-]: GETUPVAL R4 2; var4 = upvalues[2]
       9 [-]: MOVE R5 R1   ; var5 = var1
      10 [-]: GETIMPORT R6 3; var6 = ZERO_ROTATION
      11 [-]: NAMECALL R2 R2 K4; var3 = var2; var2 = var2[0x05909209]
      12 [-]: CALL R2 5 1  ; var2(var3, var4, var5, var6)
      13 [-]: GETUPVAL R2 0; var2 = upvalues[0]
      14 [-]: GETUPVAL R4 3; var4 = upvalues[3]
      15 [-]: LOADB R5 0   ; var5 = false
      16 [-]: NAMECALL R2 R2 K5; var3 = var2; var2 = var2[0x659D451F]
      17 [-]: CALL R2 4 1  ; var2(var3, var4, var5)
      18 [-]: GETUPVAL R2 0; var2 = upvalues[0]
      19 [-]: GETUPVAL R4 4; var4 = upvalues[4]
      20 [-]: LOADB R5 0   ; var5 = false
      21 [-]: NAMECALL R2 R2 K5; var3 = var2; var2 = var2[0x659D451F]
      22 [-]: CALL R2 4 1  ; var2(var3, var4, var5)
      23 [-]: LOADN R2 0   ; var2 = 0
      24 [-]: SETUPVAL R2 5; upvalues[2] = var5
      25 [-]: LOADB R2 0   ; var2 = false
      26 [-]: LOADN R3 0   ; var3 = 0
L 0:  27 [-]: GETUPVAL R4 6; var4 = upvalues[6]
      28 [-]: JUMPIFNOT R4 L6; goto L6 if not var4
      29 [-]: JUMPIF R2 L6 ; goto L6 if var2
      30 [-]: LOADN R4 3   ; var4 = 3
      31 [-]: JUMPIFNOTLT R3 R4 L6; goto L6 if var3 >= var1340
      32 [-]: GETUPVAL R5 0; var5 = upvalues[0]
      33 [-]: FASTCALL1 64 R5 L1; 
      34 [-]: GETIMPORT R4 7; var4 = 0x7B998233
      35 [-]: CALL R4 2 2  ; var4 = var4(var5)
L 1:  36 [-]: JUMPIF R4 L6 ; goto L6 if var4
      37 [-]: GETIMPORT R4 9; var4 = 0xC8802016
      38 [-]: GETUPVAL R5 7; var5 = upvalues[7]
      39 [-]: CALL R4 2 4  ; var4, var5, var6 = var4(var5)
      40 [-]: FORGPREP_INEXT R4 L4; 
L 2:  41 [-]: NAMECALL R9 R8 K10; var10 = var8; var9 = var8[0xBB610E5B]
      42 [-]: CALL R9 2 2  ; var9 = var9(var10)
      43 [-]: FASTCALL1 64 R9 L3; 
      44 [-]: MOVE R11 R9  ; var11 = var9
      45 [-]: GETIMPORT R10 7; var10 = 0x7B998233
      46 [-]: CALL R10 2 2 ; var10 = var10(var11)
L 3:  47 [-]: JUMPIF R10 L4; goto L4 if var10
      48 [-]: GETUPVAL R12 0; var12 = upvalues[0]
      49 [-]: NAMECALL R10 R9 K11; var11 = var9; var10 = var9[0x6EE4365D]
      50 [-]: CALL R10 3 2 ; var10 = var10(var11, var12)
      51 [-]: LOADK R11 K12; var11 = 0.10000000149011612
      52 [-]: JUMPIFNOTLT R11 R10 L4; goto L4 if var11 >= var66054
      53 [-]: LOADB R2 1   ; var2 = true
      54 [-]: JUMP L5      ; goto L5
L 4:  55 [-]: FORGLOOP R4 L2 2 [inext]; 
L 5:  56 [-]: GETIMPORT R4 14; var4 = 0xCBD666E1
      57 [-]: LOADN R5 0   ; var5 = 0
      58 [-]: CALL R4 2 1  ; var4(var5)
      59 [-]: GETIMPORT R4 16; var4 = 0x67652851
      60 [-]: CALL R4 1 2  ; var4 = var4()
      61 [-]: ADD R3 R3 R4 ; var3 = var3 + var4
      62 [-]: JUMPBACK L0  ; goto L0
L 6:  63 [-]: GETUPVAL R5 0; var5 = upvalues[0]
      64 [-]: FASTCALL1 64 R5 L7; 
      65 [-]: GETIMPORT R4 7; var4 = 0x7B998233
      66 [-]: CALL R4 2 2  ; var4 = var4(var5)
L 7:  67 [-]: JUMPIFNOT R4 L8; goto L8 if not var4
      68 [-]: RETURN R0 0  ; 
L 8:  69 [-]: GETIMPORT R4 1; var4 = 0x89326C93
      70 [-]: GETUPVAL R6 9; var6 = upvalues[9]
      71 [-]: GETUPVAL R7 0; var7 = upvalues[0]
      72 [-]: NAMECALL R7 R7 K17; var8 = var7; var7 = var7[0xD1586535]
      73 [-]: CALL R7 2 2  ; var7 = var7(var8)
      74 [-]: GETIMPORT R8 3; var8 = ZERO_ROTATION
      75 [-]: GETUPVAL R9 0; var9 = upvalues[0]
      76 [-]: NAMECALL R4 R4 K4; var5 = var4; var4 = var4[0x05909209]
      77 [-]: CALL R4 6 2  ; var4 = var4(var5, var6, var7, var8, var9)
      78 [-]: SETUPVAL R4 8; upvalues[4] = var8
      79 [-]: LOADNIL R4   ; var4 = nil
      80 [-]: GETIMPORT R6 20; var6 = _T["CephalonTearDamageCounterTable"]
      81 [-]: FASTCALL1 64 R6 L9; 
      82 [-]: GETIMPORT R5 7; var5 = 0x7B998233
      83 [-]: CALL R5 2 2  ; var5 = var5(var6)
L 9:  84 [-]: JUMPIFNOT R5 L10; goto L10 if not var5
      85 [-]: GETIMPORT R5 21; var5 = _T
      86 [-]: NEWTABLE R6 0 0; var6 = {}
      87 [-]: SETTABLEKS R6 R5 K19; var6["CephalonTearDamageCounterTable"] = var5
L10:  88 [-]: GETIMPORT R6 23; var6 = _T["CephalonTearDamageFreezeTable"]
      89 [-]: FASTCALL1 64 R6 L11; 
      90 [-]: GETIMPORT R5 7; var5 = 0x7B998233
      91 [-]: CALL R5 2 2  ; var5 = var5(var6)
L11:  92 [-]: JUMPIFNOT R5 L12; goto L12 if not var5
      93 [-]: GETIMPORT R5 21; var5 = _T
      94 [-]: NEWTABLE R6 0 0; var6 = {}
      95 [-]: SETTABLEKS R6 R5 K22; var6["CephalonTearDamageFreezeTable"] = var5
L12:  96 [-]: GETIMPORT R5 9; var5 = 0xC8802016
      97 [-]: MOVE R6 R0   ; var6 = var0
      98 [-]: CALL R5 2 4  ; var5, var6, var7 = var5(var6)
      99 [-]: FORGPREP_INEXT R5 L16; 
L13: 100 [-]: GETUPVAL R10 10; var10 = upvalues[10]
     101 [-]: GETUPVAL R12 11; var12 = upvalues[11]
     102 [-]: GETIMPORT R13 1; var13 = 0x89326C93
     103 [-]: NAMECALL R13 R13 K24; var14 = var13; var13 = var13[0x61BE252A]
     104 [-]: CALL R13 2 2 ; var13 = var13(var14)
     105 [-]: MUL R11 R12 R13; var11 = var12 * var13
     106 [-]: JUMPIFLE R11 R10 L17; goto L17 if var11 <= var789052
     107 [-]: GETUPVAL R10 12; var10 = upvalues[12]
     108 [-]: GETUPVAL R11 13; var11 = upvalues[13]
     109 [-]: JUMPIFLE R11 R10 L17; goto L17 if var11 <= var920124
     110 [-]: GETUPVAL R10 14; var10 = upvalues[14]
     111 [-]: MOVE R11 R9  ; var11 = var9
     112 [-]: CALL R10 2 2 ; var10 = var10(var11)
     113 [-]: JUMPIFNOT R10 L16; goto L16 if not var10
     114 [-]: GETIMPORT R10 1; var10 = 0x89326C93
     115 [-]: GETUPVAL R12 15; var12 = upvalues[15]
     116 [-]: GETUPVAL R13 0; var13 = upvalues[0]
     117 [-]: NAMECALL R13 R13 K17; var14 = var13; var13 = var13[0xD1586535]
     118 [-]: CALL R13 2 2 ; var13 = var13(var14)
     119 [-]: GETIMPORT R14 3; var14 = ZERO_ROTATION
     120 [-]: NAMECALL R10 R10 K4; var11 = var10; var10 = var10[0x05909209]
     121 [-]: CALL R10 5 2 ; var10 = var10(var11, var12, var13, var14)
     122 [-]: NAMECALL R13 R9 K17; var14 = var9; var13 = var9[0xD1586535]
     123 [-]: CALL R13 2 0 ; var13, ... = var13(var14)
     124 [-]: NAMECALL R11 R10 K25; var12 = var10; var11 = var10[0x9E9C67CB]
     125 [-]: CALL R11 0 1 ; var11(var12, ...)
     126 [-]: GETIMPORT R11 20; var11 = _T["CephalonTearDamageCounterTable"]
     127 [-]: NAMECALL R12 R9 K26; var13 = var9; var12 = var9[0x388577D5]
     128 [-]: CALL R12 2 2 ; var12 = var12(var13)
     129 [-]: LOADN R13 0  ; var13 = 0
     130 [-]: SETTABLE R13 R11 R12; var13[var11] = var12
     131 [-]: GETUPVAL R12 10; var12 = upvalues[10]
     132 [-]: ADDK R11 R12 K27; var11 = var12 + 1
     133 [-]: SETUPVAL R11 10; upvalues[11] = var10
     134 [-]: GETUPVAL R12 12; var12 = upvalues[12]
     135 [-]: ADDK R11 R12 K27; var11 = var12 + 1
     136 [-]: SETUPVAL R11 12; upvalues[11] = var12
     137 [-]: GETIMPORT R11 29; var11 = 0xBE190284
     138 [-]: GETUPVAL R13 16; var13 = upvalues[16]
     139 [-]: GETUPVAL R14 10; var14 = upvalues[10]
     140 [-]: NAMECALL R11 R11 K30; var12 = var11; var11 = var11[0x751F061D]
     141 [-]: CALL R11 4 1 ; var11(var12, var13, var14)
     142 [-]: GETIMPORT R13 32; var13 = 0x0469F296
     143 [-]: LOADK R14 K33; var14 = "CorruptEnemy"
     144 [-]: CALL R13 2 2 ; var13 = var13(var14)
     145 [-]: LOADB R14 0  ; var14 = false
     146 [-]: NAMECALL R11 R9 K34; var12 = var9; var11 = var9[0xD5F7912B]
     147 [-]: CALL R11 4 1 ; var11(var12, var13, var14)
     148 [-]: NAMECALL R11 R9 K35; var12 = var9; var11 = var9[0xFA9E477F]
     149 [-]: CALL R11 2 2 ; var11 = var11(var12)
     150 [-]: FASTCALL1 64 R11 L14; 
     151 [-]: MOVE R13 R11 ; var13 = var11
     152 [-]: GETIMPORT R12 7; var12 = 0x7B998233
     153 [-]: CALL R12 2 2 ; var12 = var12(var13)
L14: 154 [-]: JUMPIF R12 L16; goto L16 if var12
     155 [-]: NAMECALL R13 R11 K36; var14 = var11; var13 = var11[0x9ACF9296]
     156 [-]: CALL R13 2 0 ; var13, ... = var13(var14)
     157 [-]: FASTCALL 64 L15; 
     158 [-]: GETIMPORT R12 7; var12 = 0x7B998233
     159 [-]: CALL R12 0 2 ; var12 = var12(var13, ...)
L15: 160 [-]: JUMPIF R12 L16; goto L16 if var12
     161 [-]: NAMECALL R12 R11 K36; var13 = var11; var12 = var11[0x9ACF9296]
     162 [-]: CALL R12 2 2 ; var12 = var12(var13)
     163 [-]: MOVE R4 R12  ; var4 = var12
L16: 164 [-]: FORGLOOP R5 L13 2 [inext]; 
L17: 165 [-]: GETIMPORT R6 29; var6 = 0xBE190284
     166 [-]: GETUPVAL R8 17; var8 = upvalues[17]
     167 [-]: LOADN R9 0   ; var9 = 0
     168 [-]: NAMECALL R6 R6 K37; var7 = var6; var6 = var6[0x0EB34C69]
     169 [-]: CALL R6 4 2  ; var6 = var6(var7, var8, var9)
     170 [-]: ADDK R5 R6 K27; var5 = var6 + 1
     171 [-]: GETUPVAL R7 18; var7 = upvalues[18]
     172 [-]: FASTCALL1 64 R7 L18; 
     173 [-]: GETIMPORT R6 7; var6 = 0x7B998233
     174 [-]: CALL R6 2 2  ; var6 = var6(var7)
L18: 175 [-]: JUMPIF R6 L19; goto L19 if var6
     176 [-]: GETIMPORT R6 29; var6 = 0xBE190284
     177 [-]: GETUPVAL R8 18; var8 = upvalues[18]
     178 [-]: NAMECALL R6 R6 K38; var7 = var6; var6 = var6[0xC19D05D7]
     179 [-]: CALL R6 3 1  ; var6(var7, var8)
     180 [-]: LOADNIL R6   ; var6 = nil
     181 [-]: SETUPVAL R6 18; upvalues[6] = var18
     182 [-]: JUMP L21     ; goto L21
L19: 183 [-]: GETUPVAL R7 19; var7 = upvalues[19]
     184 [-]: FASTCALL1 64 R7 L20; 
     185 [-]: GETIMPORT R6 7; var6 = 0x7B998233
     186 [-]: CALL R6 2 2  ; var6 = var6(var7)
L20: 187 [-]: JUMPIF R6 L21; goto L21 if var6
     188 [-]: GETIMPORT R6 29; var6 = 0xBE190284
     189 [-]: GETUPVAL R8 19; var8 = upvalues[19]
     190 [-]: NAMECALL R6 R6 K38; var7 = var6; var6 = var6[0xC19D05D7]
     191 [-]: CALL R6 3 1  ; var6(var7, var8)
     192 [-]: LOADNIL R6   ; var6 = nil
     193 [-]: SETUPVAL R6 19; upvalues[6] = var19
L21: 194 [-]: GETIMPORT R6 29; var6 = 0xBE190284
     195 [-]: GETUPVAL R8 17; var8 = upvalues[17]
     196 [-]: MOVE R9 R5   ; var9 = var5
     197 [-]: NAMECALL R6 R6 K30; var7 = var6; var6 = var6[0x751F061D]
     198 [-]: CALL R6 4 1  ; var6(var7, var8, var9)
     199 [-]: RETURN R0 0  ; 


; Name:            
; Defined at line: 445
; #Upvalues:       0
; #Parameters:     0
; Is_vararg:       0
; Max Stack Size:  0

       0 [-]: RETURN R0 0  ; 


; Name:            
; Defined at line: 450
; #Upvalues:       9
; #Parameters:     0
; Is_vararg:       0
; Max Stack Size:  8

       0 [-]: GETIMPORT R0 1; var0 = 0xBE190284
       1 [-]: NAMECALL R0 R0 K2; var1 = var0; var0 = var0[0xEF893AEC]
       2 [-]: CALL R0 2 2  ; var0 = var0(var1)
       3 [-]: LOADN R1 1   ; var1 = 1
       4 [-]: GETTABLEKS R2 R0 K3; var2 = var0["activeMissionTag"]
       5 [-]: GETIMPORT R3 5; var3 = EMPTY_SYMBOL
       6 [-]: JUMPIFEQ R2 R3 L1; goto L1 if var2 == var-134216897
       7 [-]: GETTABLEKS R3 R0 K3; var3 = var0["activeMissionTag"]
       8 [-]: FASTCALL1 63 R3 L0; 
       9 [-]: GETIMPORT R2 7; var2 = 0x64FB1586
      10 [-]: CALL R2 2 2  ; var2 = var2(var3)
L 0:  11 [-]: MOVE R1 R2   ; var1 = var2
L 1:  12 [-]: GETIMPORT R2 9; var2 = 0x9BA7909F
      13 [-]: LOADK R4 K10 ; var4 = "LotusGameRules.CephalonTearSpawnInSimulacrum"
      14 [-]: NAMECALL R2 R2 K11; var3 = var2; var2 = var2[0xBF9494FC]
      15 [-]: CALL R2 3 2  ; var2 = var2(var3, var4)
      16 [-]: JUMPIFNOT R2 L2; goto L2 if not var2
      17 [-]: GETIMPORT R2 1; var2 = 0xBE190284
      18 [-]: GETIMPORT R4 13; var4 = 0x7ED0A956
      19 [-]: LOADK R5 K14 ; var5 = "/Lotus/Types/GameRules/LotusDangerRoomGameRules"
      20 [-]: CALL R4 2 0  ; var4, ... = var4(var5)
      21 [-]: NAMECALL R2 R2 K15; var3 = var2; var2 = var2[0xF2DEAF69]
      22 [-]: CALL R2 0 2  ; var2 = var2(var3, ...)
      23 [-]: JUMPIFNOT R2 L2; goto L2 if not var2
      24 [-]: LOADN R2 10000; var2 = 10000
      25 [-]: SETUPVAL R2 0; upvalues[2] = var0
      26 [-]: LOADN R2 10000; var2 = 10000
      27 [-]: SETUPVAL R2 1; upvalues[2] = var1
      28 [-]: LOADN R2 1   ; var2 = 1
      29 [-]: SETUPVAL R2 2; upvalues[2] = var2
      30 [-]: LOADN R2 1   ; var2 = 1
      31 [-]: SETUPVAL R2 3; upvalues[2] = var3
      32 [-]: JUMP L8      ; goto L8
L 2:  33 [-]: GETTABLEKS R2 R0 K16; var2 = var0["missionType"]
      34 [-]: LOADN R3 5   ; var3 = 5
      35 [-]: JUMPIFEQ R2 R3 L3; goto L3 if var2 == var385876543
      36 [-]: GETTABLEKS R2 R0 K16; var2 = var0["missionType"]
      37 [-]: LOADN R3 3   ; var3 = 3
      38 [-]: JUMPIFEQ R2 R3 L3; goto L3 if var2 == var385876543
      39 [-]: GETTABLEKS R2 R0 K16; var2 = var0["missionType"]
      40 [-]: LOADN R3 4   ; var3 = 4
      41 [-]: JUMPIFEQ R2 R3 L3; goto L3 if var2 == var385876543
      42 [-]: GETTABLEKS R2 R0 K16; var2 = var0["missionType"]
      43 [-]: LOADN R3 0   ; var3 = 0
      44 [-]: JUMPIFEQ R2 R3 L3; goto L3 if var2 == var385876543
      45 [-]: GETTABLEKS R2 R0 K16; var2 = var0["missionType"]
      46 [-]: LOADN R3 7   ; var3 = 7
      47 [-]: JUMPIFNOTEQ R2 R3 L4; goto L4 if var2 ~= var66096
L 3:  48 [-]: LOADN R2 1   ; var2 = 1
      49 [-]: SETUPVAL R2 4; upvalues[2] = var4
      50 [-]: LOADN R2 1   ; var2 = 1
      51 [-]: SETUPVAL R2 5; upvalues[2] = var5
      52 [-]: LOADN R2 5   ; var2 = 5
      53 [-]: SETUPVAL R2 3; upvalues[2] = var3
      54 [-]: LOADN R2 8   ; var2 = 8
      55 [-]: SETUPVAL R2 2; upvalues[2] = var2
      56 [-]: JUMP L8      ; goto L8
L 4:  57 [-]: GETTABLEKS R2 R0 K16; var2 = var0["missionType"]
      58 [-]: LOADN R3 1   ; var3 = 1
      59 [-]: JUMPIFNOTEQ R2 R3 L5; goto L5 if var2 ~= var518
      60 [-]: LOADB R2 0   ; var2 = false
      61 [-]: SETUPVAL R2 6; upvalues[2] = var6
      62 [-]: LOADN R2 1   ; var2 = 1
      63 [-]: SETUPVAL R2 4; upvalues[2] = var4
      64 [-]: LOADN R2 1   ; var2 = 1
      65 [-]: SETUPVAL R2 5; upvalues[2] = var5
      66 [-]: LOADN R2 5   ; var2 = 5
      67 [-]: SETUPVAL R2 3; upvalues[2] = var3
      68 [-]: LOADN R2 5   ; var2 = 5
      69 [-]: SETUPVAL R2 2; upvalues[2] = var2
      70 [-]: JUMP L8      ; goto L8
L 5:  71 [-]: GETTABLEKS R2 R0 K16; var2 = var0["missionType"]
      72 [-]: LOADN R3 28  ; var3 = 28
      73 [-]: JUMPIFNOTEQ R2 R3 L6; goto L6 if var2 ~= var131632
      74 [-]: LOADN R2 2   ; var2 = 2
      75 [-]: SETUPVAL R2 4; upvalues[2] = var4
      76 [-]: LOADN R2 2   ; var2 = 2
      77 [-]: SETUPVAL R2 5; upvalues[2] = var5
      78 [-]: LOADN R2 10  ; var2 = 10
      79 [-]: SETUPVAL R2 3; upvalues[2] = var3
      80 [-]: LOADN R2 32  ; var2 = 32
      81 [-]: SETUPVAL R2 2; upvalues[2] = var2
      82 [-]: JUMP L8      ; goto L8
L 6:  83 [-]: GETTABLEKS R2 R0 K16; var2 = var0["missionType"]
      84 [-]: LOADN R3 17  ; var3 = 17
      85 [-]: JUMPIFEQ R2 R3 L7; goto L7 if var2 == var385876543
      86 [-]: GETTABLEKS R2 R0 K16; var2 = var0["missionType"]
      87 [-]: LOADN R3 13  ; var3 = 13
      88 [-]: JUMPIFNOTEQ R2 R3 L8; goto L8 if var2 ~= var518
L 7:  89 [-]: LOADB R2 0   ; var2 = false
      90 [-]: SETUPVAL R2 6; upvalues[2] = var6
L 8:  91 [-]: GETIMPORT R2 18; var2 = 0x14459A1C
      92 [-]: JUMPIFNOT R2 L9; goto L9 if not var2
      93 [-]: GETIMPORT R2 1; var2 = 0xBE190284
      94 [-]: GETUPVAL R4 7; var4 = upvalues[7]
      95 [-]: NAMECALL R2 R2 K19; var3 = var2; var2 = var2[0x0EB34C69]
      96 [-]: CALL R2 3 2  ; var2 = var2(var3, var4)
      97 [-]: SETUPVAL R2 0; upvalues[2] = var0
      98 [-]: GETIMPORT R3 21; var3 = 0x3D106989
      99 [-]: LOADK R5 K22 ; var5 = "CephalonTear found "
     100 [-]: MOVE R6 R2   ; var6 = var2
     101 [-]: LOADK R7 K23 ; var7 = " number of remaining targets carrying over migration!"
     102 [-]: CONCAT R4 R5 R7; var4 = var5 .. var7
     103 [-]: CALL R3 2 1  ; var3(var4)
     104 [-]: JUMP L10     ; goto L10
L 9: 105 [-]: GETIMPORT R2 1; var2 = 0xBE190284
     106 [-]: GETUPVAL R4 7; var4 = upvalues[7]
     107 [-]: LOADN R5 0   ; var5 = 0
     108 [-]: NAMECALL R2 R2 K24; var3 = var2; var2 = var2[0x751F061D]
     109 [-]: CALL R2 4 1  ; var2(var3, var4, var5)
     110 [-]: LOADN R2 0   ; var2 = 0
     111 [-]: SETUPVAL R2 0; upvalues[2] = var0
L10: 112 [-]: GETUPVAL R2 8; var2 = upvalues[8]
     113 [-]: CALL R2 1 1  ; var2()
     114 [-]: RETURN R0 0  ; 


; Name:            
; Defined at line: 507
; #Upvalues:       0
; #Parameters:     0
; Is_vararg:       0
; Max Stack Size:  2

       0 [-]: GETIMPORT R0 2; var0 = _T["EOMOpen"]
       1 [-]: JUMPIFNOT R0 L1; goto L1 if not var0
       2 [-]: GETIMPORT R0 4; var0 = _T["eomScreenMode"]
       3 [-]: JUMPIFNOT R0 L1; goto L1 if not var0
       4 [-]: GETIMPORT R1 4; var1 = _T["eomScreenMode"]
       5 [-]: JUMPXEQKN R1 K5 L0; 
       6 [-]: LOADB R0 0 +1; var0 = false
L 0:   7 [-]: LOADB R0 1   ; var0 = true
L 1:   8 [-]: RETURN R0 1  ; 


; Name:            
; Defined at line: 512
; #Upvalues:       28
; #Parameters:     1
; Is_vararg:       0
; Max Stack Size:  27

       0 [-]: GETIMPORT R1 1; var1 = 0x89326C93
       1 [-]: LOADK R3 K2  ; var3 = "OnPlayersChanged"
       2 [-]: NAMECALL R1 R1 K3; var2 = var1; var1 = var1[0xB7D33840]
       3 [-]: CALL R1 3 1  ; var1(var2, var3)
       4 [-]: GETIMPORT R1 1; var1 = 0x89326C93
       5 [-]: NAMECALL R1 R1 K4; var2 = var1; var1 = var1[0x18D05D30]
       6 [-]: CALL R1 2 2  ; var1 = var1(var2)
       7 [-]: JUMPIF R1 L0 ; goto L0 if var1
       8 [-]: GETIMPORT R1 6; var1 = 0x14459A1C
       9 [-]: JUMPIF R1 L0 ; goto L0 if var1
      10 [-]: RETURN R0 0  ; 
L 0:  11 [-]: GETIMPORT R2 9; var2 = _T["MissionInitReady"]
      12 [-]: FASTCALL1 64 R2 L1; 
      13 [-]: GETIMPORT R1 11; var1 = 0x7B998233
      14 [-]: CALL R1 2 2  ; var1 = var1(var2)
L 1:  15 [-]: JUMPIF R1 L3 ; goto L3 if var1
      16 [-]: GETIMPORT R1 9; var1 = _T["MissionInitReady"]
      17 [-]: JUMPIFNOT R1 L3; goto L3 if not var1
      18 [-]: GETIMPORT R2 13; var2 = 0xBE190284
      19 [-]: FASTCALL1 64 R2 L2; 
      20 [-]: GETIMPORT R1 11; var1 = 0x7B998233
      21 [-]: CALL R1 2 2  ; var1 = var1(var2)
L 2:  22 [-]: JUMPIFNOT R1 L4; goto L4 if not var1
L 3:  23 [-]: GETIMPORT R1 15; var1 = 0xCBD666E1
      24 [-]: LOADN R2 0   ; var2 = 0
      25 [-]: CALL R1 2 1  ; var1(var2)
      26 [-]: JUMPBACK L0  ; goto L0
L 4:  27 [-]: GETIMPORT R1 1; var1 = 0x89326C93
      28 [-]: NAMECALL R1 R1 K4; var2 = var1; var1 = var1[0x18D05D30]
      29 [-]: CALL R1 2 2  ; var1 = var1(var2)
      30 [-]: JUMPIF R1 L5 ; goto L5 if var1
      31 [-]: GETIMPORT R1 6; var1 = 0x14459A1C
      32 [-]: JUMPIF R1 L5 ; goto L5 if var1
      33 [-]: RETURN R0 0  ; 
L 5:  34 [-]: GETIMPORT R1 13; var1 = 0xBE190284
      35 [-]: GETIMPORT R3 17; var3 = gLotusGameRulesType
      36 [-]: NAMECALL R1 R1 K18; var2 = var1; var1 = var1[0xF2DEAF69]
      37 [-]: CALL R1 3 2  ; var1 = var1(var2, var3)
      38 [-]: JUMPIF R1 L6 ; goto L6 if var1
      39 [-]: RETURN R0 0  ; 
L 6:  40 [-]: GETIMPORT R1 13; var1 = 0xBE190284
      41 [-]: NAMECALL R1 R1 K19; var2 = var1; var1 = var1[0xEF893AEC]
      42 [-]: CALL R1 2 2  ; var1 = var1(var2)
      43 [-]: GETTABLEKS R3 R1 K20; var3 = var1["keyChainName"]
      44 [-]: FASTCALL1 64 R3 L7; 
      45 [-]: GETIMPORT R2 11; var2 = 0x7B998233
      46 [-]: CALL R2 2 2  ; var2 = var2(var3)
L 7:  47 [-]: JUMPIF R2 L8 ; goto L8 if var2
      48 [-]: RETURN R0 0  ; 
L 8:  49 [-]: GETUPVAL R3 0; var3 = upvalues[0]
      50 [-]: GETTABLEKS R2 R3 K21; var2 = var3[0x8E7C3B5E]
      51 [-]: GETIMPORT R3 23; var3 = 0x25D99D89
      52 [-]: CALL R2 2 3  ; var2, var3 = var2(var3)
      53 [-]: FASTCALL1 64 R2 L9; 
      54 [-]: MOVE R5 R2   ; var5 = var2
      55 [-]: GETIMPORT R4 11; var4 = 0x7B998233
      56 [-]: CALL R4 2 2  ; var4 = var4(var5)
L 9:  57 [-]: JUMPIF R4 L10; goto L10 if var4
      58 [-]: GETUPVAL R4 1; var4 = upvalues[1]
      59 [-]: JUMPIFNOTEQ R2 R4 L10; goto L10 if var2 ~= var-1140784065
      60 [-]: GETTABLEKS R4 R1 K24; var4 = var1["location"]
      61 [-]: NAMECALL R4 R4 K25; var5 = var4; var4 = var4[0x6D604BA7]
      62 [-]: CALL R4 2 2  ; var4 = var4(var5)
      63 [-]: JUMPXEQKS R4 K26 L10 NOT; 
      64 [-]: RETURN R0 0  ; 
L10:  65 [-]: GETUPVAL R4 2; var4 = upvalues[2]
      66 [-]: CALL R4 1 1  ; var4()
      67 [-]: GETIMPORT R4 1; var4 = 0x89326C93
      68 [-]: GETIMPORT R6 28; var6 = 0x7ED0A956
      69 [-]: LOADK R7 K29 ; var7 = "/Lotus/Types/Game/Waypoints/VoidTearWaypoint"
      70 [-]: CALL R6 2 0  ; var6, ... = var6(var7)
      71 [-]: NAMECALL R4 R4 K30; var5 = var4; var4 = var4[0xFB669000]
      72 [-]: CALL R4 0 2  ; var4 = var4(var5, ...)
      73 [-]: NEWTABLE R5 0 0; var5 = {}
      74 [-]: GETIMPORT R6 32; var6 = 0xC8802016
      75 [-]: MOVE R7 R4   ; var7 = var4
      76 [-]: CALL R6 2 4  ; var6, var7, var8 = var6(var7)
      77 [-]: FORGPREP_INEXT R6 L12; 
L11:  78 [-]: MOVE R12 R5  ; var12 = var5
      79 [-]: GETIMPORT R13 1; var13 = 0x89326C93
      80 [-]: GETUPVAL R15 3; var15 = upvalues[3]
      81 [-]: NAMECALL R16 R10 K33; var17 = var10; var16 = var10[0xD1586535]
      82 [-]: CALL R16 2 2 ; var16 = var16(var17)
      83 [-]: GETIMPORT R17 35; var17 = ZERO_ROTATION
      84 [-]: NAMECALL R13 R13 K36; var14 = var13; var13 = var13[0x05909209]
      85 [-]: CALL R13 5 0 ; var13, ... = var13(var14, var15, var16, var17)
      86 [-]: FASTCALL 52 L12; 
      87 [-]: GETIMPORT R11 39; var11 = 0x33BDD652[0x23D5322F]
      88 [-]: CALL R11 0 1 ; var11(var12, ...)
L12:  89 [-]: FORGLOOP R6 L11 2 [inext]; 
      90 [-]: GETIMPORT R6 6; var6 = 0x14459A1C
      91 [-]: JUMPIFNOT R6 L13; goto L13 if not var6
      92 [-]: GETIMPORT R6 1; var6 = 0x89326C93
      93 [-]: GETUPVAL R8 5; var8 = upvalues[5]
      94 [-]: GETIMPORT R9 41; var9 = 0xA421AF95
      95 [-]: CALL R9 1 2  ; var9 = var9()
      96 [-]: LOADK R10 K42; var10 = 3.4028234663852886e+38
      97 [-]: NAMECALL R6 R6 K43; var7 = var6; var6 = var6[0x4E5939A5]
      98 [-]: CALL R6 5 2  ; var6 = var6(var7, var8, var9, var10)
      99 [-]: SETUPVAL R6 4; upvalues[6] = var4
L13: 100 [-]: GETIMPORT R6 13; var6 = 0xBE190284
     101 [-]: NAMECALL R6 R6 K19; var7 = var6; var6 = var6[0xEF893AEC]
     102 [-]: CALL R6 2 2  ; var6 = var6(var7)
     103 [-]: GETTABLEKS R7 R6 K44; var7 = var6["missionType"]
     104 [-]: LOADB R8 0   ; var8 = false
L14: 105 [-]: GETIMPORT R9 46; var9 = _T["isStreamingLevel"]
     106 [-]: JUMPIFNOT R9 L15; goto L15 if not var9
     107 [-]: NAMECALL R9 R0 K47; var10 = var0; var9 = var0[0xA2880940]
     108 [-]: CALL R9 2 1  ; var9(var10)
     109 [-]: RETURN R0 0  ; 
L15: 110 [-]: GETUPVAL R9 6; var9 = upvalues[6]
     111 [-]: CALL R9 1 1  ; var9()
     112 [-]: GETIMPORT R9 49; var9 = 0x67652851
     113 [-]: CALL R9 1 2  ; var9 = var9()
     114 [-]: GETUPVAL R11 7; var11 = upvalues[7]
     115 [-]: LENGTH R10 R11; var10 = #var11
     116 [-]: JUMPXEQKN R10 K50 L16 NOT; 
     117 [-]: GETIMPORT R10 1; var10 = 0x89326C93
     118 [-]: NAMECALL R10 R10 K51; var11 = var10; var10 = var10[0x7D108DDB]
     119 [-]: CALL R10 2 2 ; var10 = var10(var11)
     120 [-]: SETUPVAL R10 7; upvalues[10] = var7
L16: 121 [-]: GETUPVAL R10 8; var10 = upvalues[8]
     122 [-]: CALL R10 1 1 ; var10()
     123 [-]: GETIMPORT R8 53; var8 = _T["EOMOpen"]
     124 [-]: JUMPIFNOT R8 L18; goto L18 if not var8
     125 [-]: GETIMPORT R8 55; var8 = _T["eomScreenMode"]
     126 [-]: JUMPIFNOT R8 L18; goto L18 if not var8
     127 [-]: GETIMPORT R10 55; var10 = _T["eomScreenMode"]
     128 [-]: JUMPXEQKN R10 K56 L17; 
     129 [-]: LOADB R8 0 +1; var8 = false
L17: 130 [-]: LOADB R8 1   ; var8 = true
L18: 131 [-]: GETUPVAL R11 4; var11 = upvalues[4]
     132 [-]: FASTCALL1 64 R11 L19; 
     133 [-]: GETIMPORT R10 11; var10 = 0x7B998233
     134 [-]: CALL R10 2 2 ; var10 = var10(var11)
L19: 135 [-]: JUMPIFNOT R10 L46; goto L46 if not var10
     136 [-]: GETUPVAL R10 9; var10 = upvalues[9]
     137 [-]: GETUPVAL R11 10; var11 = upvalues[10]
     138 [-]: JUMPIFNOTLT R10 R11 L21; goto L21 if var10 >= var723772
     139 [-]: GETUPVAL R11 11; var11 = upvalues[11]
     140 [-]: ADD R10 R11 R9; var10 = var11 + var9
     141 [-]: SETUPVAL R10 11; upvalues[10] = var11
     142 [-]: LOADN R10 17 ; var10 = 17
     143 [-]: JUMPIFNOTEQ R7 R10 L20; goto L20 if var7 ~= var854561
     144 [-]: GETIMPORT R10 13; var10 = 0xBE190284
     145 [-]: GETUPVAL R12 12; var12 = upvalues[12]
     146 [-]: LOADN R13 0  ; var13 = 0
     147 [-]: NAMECALL R10 R10 K57; var11 = var10; var10 = var10[0x0EB34C69]
     148 [-]: CALL R10 4 2 ; var10 = var10(var11, var12, var13)
     149 [-]: GETUPVAL R12 11; var12 = upvalues[11]
     150 [-]: MUL R13 R10 R9; var13 = var10 * var9
     151 [-]: ADD R11 R12 R13; var11 = var12 + var13
     152 [-]: SETUPVAL R11 11; upvalues[11] = var11
L20: 153 [-]: GETUPVAL R10 11; var10 = upvalues[11]
     154 [-]: LOADN R11 20 ; var11 = 20
     155 [-]: JUMPIFNOTLT R11 R10 L21; goto L21 if var11 >= var68144
     156 [-]: LOADN R10 1  ; var10 = 1
     157 [-]: SETUPVAL R10 13; upvalues[10] = var13
L21: 158 [-]: JUMPIF R8 L50; goto L50 if var8
     159 [-]: GETUPVAL R10 11; var10 = upvalues[11]
     160 [-]: GETUPVAL R11 14; var11 = upvalues[14]
     161 [-]: JUMPIFNOTLT R11 R10 L50; goto L50 if var11 >= var985660
     162 [-]: GETUPVAL R10 15; var10 = upvalues[15]
     163 [-]: GETUPVAL R12 16; var12 = upvalues[16]
     164 [-]: GETIMPORT R13 1; var13 = 0x89326C93
     165 [-]: NAMECALL R13 R13 K58; var14 = var13; var13 = var13[0x61BE252A]
     166 [-]: CALL R13 2 2 ; var13 = var13(var14)
     167 [-]: MUL R11 R12 R13; var11 = var12 * var13
     168 [-]: JUMPIFNOTLT R10 R11 L50; goto L50 if var10 >= var2613
     169 [-]: NEWTABLE R10 0 0; var10 = {}
     170 [-]: LOADNIL R11  ; var11 = nil
     171 [-]: GETIMPORT R12 32; var12 = 0xC8802016
     172 [-]: MOVE R13 R5  ; var13 = var5
     173 [-]: CALL R12 2 4 ; var12, var13, var14 = var12(var13)
     174 [-]: FORGPREP_INEXT R12 L26; 
L22: 175 [-]: NAMECALL R17 R16 K59; var18 = var16; var17 = var16[0x0D09D3C0]
     176 [-]: CALL R17 2 2 ; var17 = var17(var18)
     177 [-]: LENGTH R20 R17; var20 = #var17
     178 [-]: LOADN R18 1  ; var18 = 1
     179 [-]: LOADN R19 -1 ; var19 = -1
     180 [-]: FORNPREP R18 L25; nforprep start - [escape at L25] -- var18 = iterator
L23: 181 [-]: GETTABLE R21 R17 R20; var21 = var17[var20]
     182 [-]: GETUPVAL R22 17; var22 = upvalues[17]
     183 [-]: MOVE R23 R21 ; var23 = var21
     184 [-]: CALL R22 2 2 ; var22 = var22(var23)
     185 [-]: JUMPIF R22 L24; goto L24 if var22
     186 [-]: GETIMPORT R22 61; var22 = 0x33BDD652[0x9C1F3B5A]
     187 [-]: MOVE R23 R17 ; var23 = var17
     188 [-]: MOVE R24 R20 ; var24 = var20
     189 [-]: CALL R22 3 1 ; var22(var23, var24)
L24: 190 [-]: FORNLOOP R18 L23; nforloop end - iterate + goto L23
L25: 191 [-]: LENGTH R18 R17; var18 = #var17
     192 [-]: LENGTH R19 R10; var19 = #var10
     193 [-]: JUMPIFNOTLT R19 R18 L26; goto L26 if var19 >= var1118720
     194 [-]: LENGTH R18 R17; var18 = #var17
     195 [-]: GETUPVAL R19 13; var19 = upvalues[13]
     196 [-]: JUMPIFNOTLE R19 R18 L26; goto L26 if var19 > var1116718
     197 [-]: MOVE R10 R17 ; var10 = var17
     198 [-]: NAMECALL R18 R16 K33; var19 = var16; var18 = var16[0xD1586535]
     199 [-]: CALL R18 2 2 ; var18 = var18(var19)
     200 [-]: GETIMPORT R19 41; var19 = 0xA421AF95
     201 [-]: LOADN R20 0  ; var20 = 0
     202 [-]: LOADN R21 2  ; var21 = 2
     203 [-]: LOADN R22 0  ; var22 = 0
     204 [-]: CALL R19 4 2 ; var19 = var19(var20, var21, var22)
     205 [-]: ADD R11 R18 R19; var11 = var18 + var19
L26: 206 [-]: FORGLOOP R12 L22 2 [inext]; 
     207 [-]: FASTCALL1 64 R11 L27; 
     208 [-]: MOVE R13 R11 ; var13 = var11
     209 [-]: GETIMPORT R12 11; var12 = 0x7B998233
     210 [-]: CALL R12 2 2 ; var12 = var12(var13)
L27: 211 [-]: JUMPIFNOT R12 L28; goto L28 if not var12
     212 [-]: GETUPVAL R12 18; var12 = upvalues[18]
     213 [-]: CALL R12 1 2 ; var12 = var12()
     214 [-]: MOVE R10 R12 ; var10 = var12
     215 [-]: JUMP L33     ; goto L33
L28: 216 [-]: GETTABLEKS R13 R11 K62; var13 = var11["x"]
     217 [-]: FASTCALL1 2 R13 L29; 
     218 [-]: GETIMPORT R12 65; var12 = 0x5BCED4C4[0xE4A5B3CA]
     219 [-]: CALL R12 2 2 ; var12 = var12(var13)
L29: 220 [-]: LOADN R13 5000; var13 = 5000
     221 [-]: JUMPIFLT R13 R12 L32; goto L32 if var13 < var-1744106177
     222 [-]: GETTABLEKS R13 R11 K66; var13 = var11["y"]
     223 [-]: FASTCALL1 2 R13 L30; 
     224 [-]: GETIMPORT R12 65; var12 = 0x5BCED4C4[0xE4A5B3CA]
     225 [-]: CALL R12 2 2 ; var12 = var12(var13)
L30: 226 [-]: LOADN R13 5000; var13 = 5000
     227 [-]: JUMPIFLT R13 R12 L32; goto L32 if var13 < var-1693774529
     228 [-]: GETTABLEKS R13 R11 K67; var13 = var11["z"]
     229 [-]: FASTCALL1 2 R13 L31; 
     230 [-]: GETIMPORT R12 65; var12 = 0x5BCED4C4[0xE4A5B3CA]
     231 [-]: CALL R12 2 2 ; var12 = var12(var13)
L31: 232 [-]: LOADN R13 5000; var13 = 5000
     233 [-]: JUMPIFNOTLT R13 R12 L33; goto L33 if var13 >= var4525089
L32: 234 [-]: GETIMPORT R12 69; var12 = 0x484742B6
     235 [-]: LOADK R13 K70; var13 = "CephalonTear - SpawnPos being found at ridiculous places while looking with trigger pos!"
     236 [-]: CALL R12 2 1 ; var12(var13)
L33: 237 [-]: LENGTH R12 R10; var12 = #var10
     238 [-]: GETUPVAL R13 13; var13 = upvalues[13]
     239 [-]: JUMPIFNOTLE R13 R12 L44; goto L44 if var13 > var51068989
     240 [-]: FASTCALL1 64 R11 L34; 
     241 [-]: MOVE R13 R11 ; var13 = var11
     242 [-]: GETIMPORT R12 11; var12 = 0x7B998233
     243 [-]: CALL R12 2 2 ; var12 = var12(var13)
L34: 244 [-]: JUMPIFNOT R12 L44; goto L44 if not var12
     245 [-]: LENGTH R13 R10; var13 = #var10
          247 [-]: GETIMPORT R14 73; var14 = 0x55730E1A
     248 [-]: LOADN R15 1  ; var15 = 1
     249 [-]: FASTCALL1 7 R12 L35; 
     250 [-]: MOVE R17 R12 ; var17 = var12
     251 [-]: GETIMPORT R16 75; var16 = 0x5BCED4C4[0x99675E23]
     252 [-]: CALL R16 2 2 ; var16 = var16(var17)
L35: 253 [-]: CALL R14 3 2 ; var14 = var14(var15, var16)
     254 [-]: GETTABLE R13 R10 R14; var13 = var10[var14]
     255 [-]: GETIMPORT R15 73; var15 = 0x55730E1A
     256 [-]: ADDK R17 R12 K76; var17 = var12 + 1
     257 [-]: FASTCALL1 12 R17 L36; 
     258 [-]: GETIMPORT R16 78; var16 = 0x5BCED4C4[0x55F27C30]
     259 [-]: CALL R16 2 2 ; var16 = var16(var17)
L36: 260 [-]: LENGTH R17 R10; var17 = #var10
     261 [-]: CALL R15 3 2 ; var15 = var15(var16, var17)
     262 [-]: GETTABLE R14 R10 R15; var14 = var10[var15]
     263 [-]: GETIMPORT R15 80; var15 = 0x5DB3CE80
     264 [-]: NAMECALL R16 R13 K33; var17 = var13; var16 = var13[0xD1586535]
     265 [-]: CALL R16 2 2 ; var16 = var16(var17)
     266 [-]: NAMECALL R17 R14 K33; var18 = var14; var17 = var14[0xD1586535]
     267 [-]: CALL R17 2 2 ; var17 = var17(var18)
     268 [-]: LOADK R18 K81; var18 = 0.5
     269 [-]: CALL R15 4 2 ; var15 = var15(var16, var17, var18)
     270 [-]: GETUPVAL R16 19; var16 = upvalues[19]
     271 [-]: MOVE R18 R15 ; var18 = var15
     272 [-]: LOADN R19 20 ; var19 = 20
     273 [-]: NAMECALL R16 R16 K82; var17 = var16; var16 = var16[0x40F8914B]
     274 [-]: CALL R16 4 2 ; var16 = var16(var17, var18, var19)
     275 [-]: JUMPIF R16 L37; goto L37 if var16
     276 [-]: NAMECALL R17 R13 K33; var18 = var13; var17 = var13[0xD1586535]
     277 [-]: CALL R17 2 2 ; var17 = var17(var18)
     278 [-]: MOVE R15 R17 ; var15 = var17
L37: 279 [-]: GETIMPORT R17 41; var17 = 0xA421AF95
     280 [-]: LOADN R18 0  ; var18 = 0
     281 [-]: LOADN R19 3  ; var19 = 3
     282 [-]: LOADN R20 0  ; var20 = 0
     283 [-]: CALL R17 4 2 ; var17 = var17(var18, var19, var20)
     284 [-]: GETIMPORT R18 41; var18 = 0xA421AF95
     285 [-]: CALL R18 1 2 ; var18 = var18()
     286 [-]: GETIMPORT R19 1; var19 = 0x89326C93
     287 [-]: MOVE R21 R15 ; var21 = var15
     288 [-]: GETIMPORT R23 41; var23 = 0xA421AF95
     289 [-]: LOADN R24 0  ; var24 = 0
     290 [-]: LOADN R25 3  ; var25 = 3
     291 [-]: LOADN R26 0  ; var26 = 0
     292 [-]: CALL R23 4 2 ; var23 = var23(var24, var25, var26)
     293 [-]: ADD R22 R15 R23; var22 = var15 + var23
     294 [-]: LOADNIL R23  ; var23 = nil
     295 [-]: LOADNIL R24  ; var24 = nil
     296 [-]: MOVE R25 R18 ; var25 = var18
     297 [-]: LOADB R26 1  ; var26 = true
     298 [-]: NAMECALL R19 R19 K83; var20 = var19; var19 = var19[0xBD5D0EC1]
     299 [-]: CALL R19 8 2 ; var19 = var19(var20, var21, var22, var23, var24, var25, var26)
     300 [-]: JUMPIFNOT R19 L38; goto L38 if not var19
     301 [-]: GETIMPORT R19 41; var19 = 0xA421AF95
     302 [-]: LOADN R20 0  ; var20 = 0
     303 [-]: LOADN R21 1  ; var21 = 1
     304 [-]: LOADN R22 0  ; var22 = 0
     305 [-]: CALL R19 4 2 ; var19 = var19(var20, var21, var22)
     306 [-]: SUB R11 R18 R19; var11 = var18 - var19
     307 [-]: JUMP L39     ; goto L39
L38: 308 [-]: ADD R11 R15 R17; var11 = var15 + var17
L39: 309 [-]: GETTABLEKS R20 R11 K62; var20 = var11["x"]
     310 [-]: FASTCALL1 2 R20 L40; 
     311 [-]: GETIMPORT R19 65; var19 = 0x5BCED4C4[0xE4A5B3CA]
     312 [-]: CALL R19 2 2 ; var19 = var19(var20)
L40: 313 [-]: LOADN R20 5000; var20 = 5000
     314 [-]: JUMPIFLT R20 R19 L43; goto L43 if var20 < var-1744104385
     315 [-]: GETTABLEKS R20 R11 K66; var20 = var11["y"]
     316 [-]: FASTCALL1 2 R20 L41; 
     317 [-]: GETIMPORT R19 65; var19 = 0x5BCED4C4[0xE4A5B3CA]
     318 [-]: CALL R19 2 2 ; var19 = var19(var20)
L41: 319 [-]: LOADN R20 5000; var20 = 5000
     320 [-]: JUMPIFLT R20 R19 L43; goto L43 if var20 < var-1693772737
     321 [-]: GETTABLEKS R20 R11 K67; var20 = var11["z"]
     322 [-]: FASTCALL1 2 R20 L42; 
     323 [-]: GETIMPORT R19 65; var19 = 0x5BCED4C4[0xE4A5B3CA]
     324 [-]: CALL R19 2 2 ; var19 = var19(var20)
L42: 325 [-]: LOADN R20 5000; var20 = 5000
     326 [-]: JUMPIFNOTLT R20 R19 L44; goto L44 if var20 >= var4526881
L43: 327 [-]: GETIMPORT R19 69; var19 = 0x484742B6
     328 [-]: LOADK R20 K84; var20 = "CephalonTear -  SpawnPos being found at ridiculous places while looking around enemy pos!"
     329 [-]: CALL R19 2 1 ; var19(var20)
L44: 330 [-]: FASTCALL1 64 R11 L45; 
     331 [-]: MOVE R13 R11 ; var13 = var11
     332 [-]: GETIMPORT R12 11; var12 = 0x7B998233
     333 [-]: CALL R12 2 2 ; var12 = var12(var13)
L45: 334 [-]: JUMPIF R12 L50; goto L50 if var12
     335 [-]: GETUPVAL R12 20; var12 = upvalues[20]
     336 [-]: MOVE R13 R10 ; var13 = var10
     337 [-]: MOVE R14 R11 ; var14 = var11
     338 [-]: CALL R12 3 1 ; var12(var13, var14)
     339 [-]: JUMP L50     ; goto L50
L46: 340 [-]: GETUPVAL R11 21; var11 = upvalues[21]
     341 [-]: GETIMPORT R12 49; var12 = 0x67652851
     342 [-]: CALL R12 1 2 ; var12 = var12()
     343 [-]: ADD R10 R11 R12; var10 = var11 + var12
     344 [-]: SETUPVAL R10 21; upvalues[10] = var21
     345 [-]: GETUPVAL R10 21; var10 = upvalues[21]
     346 [-]: GETUPVAL R11 22; var11 = upvalues[22]
     347 [-]: JUMPIFNOTLT R11 R10 L50; goto L50 if var11 >= var264764
     348 [-]: GETUPVAL R10 4; var10 = upvalues[4]
     349 [-]: GETUPVAL R12 23; var12 = upvalues[23]
     350 [-]: LOADB R13 0  ; var13 = false
     351 [-]: NAMECALL R10 R10 K85; var11 = var10; var10 = var10[0x659D451F]
     352 [-]: CALL R10 4 1 ; var10(var11, var12, var13)
     353 [-]: GETUPVAL R10 4; var10 = upvalues[4]
     354 [-]: GETUPVAL R12 24; var12 = upvalues[24]
     355 [-]: LOADB R13 0  ; var13 = false
     356 [-]: NAMECALL R10 R10 K85; var11 = var10; var10 = var10[0x659D451F]
     357 [-]: CALL R10 4 1 ; var10(var11, var12, var13)
     358 [-]: GETUPVAL R10 4; var10 = upvalues[4]
     359 [-]: NAMECALL R10 R10 K47; var11 = var10; var10 = var10[0xA2880940]
     360 [-]: CALL R10 2 1 ; var10(var11)
     361 [-]: GETIMPORT R10 1; var10 = 0x89326C93
     362 [-]: GETUPVAL R12 25; var12 = upvalues[25]
     363 [-]: GETUPVAL R13 4; var13 = upvalues[4]
     364 [-]: NAMECALL R13 R13 K33; var14 = var13; var13 = var13[0xD1586535]
     365 [-]: CALL R13 2 2 ; var13 = var13(var14)
     366 [-]: GETIMPORT R14 35; var14 = ZERO_ROTATION
     367 [-]: NAMECALL R10 R10 K36; var11 = var10; var10 = var10[0x05909209]
     368 [-]: CALL R10 5 1 ; var10(var11, var12, var13, var14)
     369 [-]: GETUPVAL R11 26; var11 = upvalues[26]
     370 [-]: FASTCALL1 64 R11 L47; 
     371 [-]: GETIMPORT R10 11; var10 = 0x7B998233
     372 [-]: CALL R10 2 2 ; var10 = var10(var11)
L47: 373 [-]: JUMPIF R10 L48; goto L48 if var10
     374 [-]: GETUPVAL R10 26; var10 = upvalues[26]
     375 [-]: NAMECALL R10 R10 K47; var11 = var10; var10 = var10[0xA2880940]
     376 [-]: CALL R10 2 1 ; var10(var11)
L48: 377 [-]: GETUPVAL R10 11; var10 = upvalues[11]
     378 [-]: LOADN R11 20 ; var11 = 20
     379 [-]: JUMPIFNOTLT R11 R10 L49; goto L49 if var11 >= var1772092
     380 [-]: GETUPVAL R10 27; var10 = upvalues[27]
     381 [-]: SETUPVAL R10 13; upvalues[10] = var13
L49: 382 [-]: LOADN R10 0  ; var10 = 0
     383 [-]: SETUPVAL R10 11; upvalues[10] = var11
L50: 384 [-]: GETIMPORT R10 15; var10 = 0xCBD666E1
     385 [-]: LOADN R11 0  ; var11 = 0
     386 [-]: CALL R10 2 1 ; var10(var11)
     387 [-]: JUMPBACK L14 ; goto L14
     388 [-]: RETURN R0 0  ; 



