; Name:            
; Defined at line: 1
; #Upvalues:       0
; #Parameters:     0
; Is_vararg:       1
; Max Stack Size:  39

       1 [-]: GETIMPORT R0 1; var0 = 0x7ED0A956
       2 [-]: LOADK R1 K2  ; var1 = "/Lotus/Types/Keys/NewWarQuest/NewWarQuestKeyChain"
       3 [-]: CALL R0 2 2  ; var0 = var0(var1)
       4 [-]: GETIMPORT R1 4; var1 = 0x2D0FAD09
       5 [-]: LOADK R2 K5  ; var2 = "Lotus.Scripts.Libs.CommonGamemodeFunctions"
       6 [-]: CALL R1 2 2  ; var1 = var1(var2)
       7 [-]: GETIMPORT R2 4; var2 = 0x2D0FAD09
       8 [-]: LOADK R3 K6  ; var3 = "Lotus.Scripts.Libs.QuestMissionLib"
       9 [-]: CALL R2 2 2  ; var2 = var2(var3)
      10 [-]: GETIMPORT R3 4; var3 = 0x2D0FAD09
      11 [-]: LOADK R4 K7  ; var4 = "Lotus.Scripts.Libs.TransmissionSet"
      12 [-]: CALL R3 2 2  ; var3 = var3(var4)
      13 [-]: GETIMPORT R4 4; var4 = 0x2D0FAD09
      14 [-]: LOADK R5 K8  ; var5 = "Lotus.Powersuits.Operator.OperatorLib"
      15 [-]: CALL R4 2 2  ; var4 = var4(var5)
      16 [-]: GETIMPORT R5 4; var5 = 0x2D0FAD09
      17 [-]: LOADK R6 K9  ; var6 = "EE.Interface.Utilities"
      18 [-]: CALL R5 2 2  ; var5 = var5(var6)
      19 [-]: GETIMPORT R6 4; var6 = 0x2D0FAD09
      20 [-]: LOADK R7 K10 ; var7 = "Lotus.Interface.LotusUtilities"
      21 [-]: CALL R6 2 2  ; var6 = var6(var7)
      22 [-]: LOADNIL R7   ; var7 = nil
      23 [-]: LOADN R8 0   ; var8 = 0
      24 [-]: LOADNIL R9   ; var9 = nil
      25 [-]: LOADNIL R10  ; var10 = nil
      26 [-]: LOADNIL R11  ; var11 = nil
      27 [-]: LOADNIL R12  ; var12 = nil
      28 [-]: LOADNIL R13  ; var13 = nil
      29 [-]: DUPTABLE R14 13; 
      30 [-]: GETIMPORT R15 15; var15 = 0xA421AF95
      31 [-]: LOADK R16 K16; var16 = -0.106262
      32 [-]: LOADK R17 K17; var17 = 1.18753
      33 [-]: LOADK R18 K18; var18 = -0.026268
      34 [-]: CALL R15 4 2 ; var15 = var15(var16, var17, var18)
      35 [-]: SETTABLEKS R15 R14 K11; var15["pos"] = var14
      36 [-]: GETIMPORT R15 20; var15 = 0x00046924
      37 [-]: LOADK R16 K21; var16 = 2.4959699999999998
      38 [-]: LOADK R17 K22; var17 = 0.36480299999999999
      39 [-]: LOADK R18 K23; var18 = 0.198405
      40 [-]: CALL R15 4 2 ; var15 = var15(var16, var17, var18)
      41 [-]: SETTABLEKS R15 R14 K12; var15["rot"] = var14
      42 [-]: DUPTABLE R15 13; 
      43 [-]: GETIMPORT R16 15; var16 = 0xA421AF95
      44 [-]: LOADK R17 K16; var17 = -0.106262
      45 [-]: LOADK R18 K24; var18 = 1.18784
      46 [-]: LOADK R19 K25; var19 = 0.084747299999999998
      47 [-]: CALL R16 4 2 ; var16 = var16(var17, var18, var19)
      48 [-]: SETTABLEKS R16 R15 K11; var16["pos"] = var15
      49 [-]: GETIMPORT R16 20; var16 = 0x00046924
      50 [-]: LOADK R17 K26; var17 = 4.4350300000000002
      51 [-]: LOADK R18 K27; var18 = 59.537999999999997
      52 [-]: LOADK R19 K28; var19 = 4.0110799999999998
      53 [-]: CALL R16 4 2 ; var16 = var16(var17, var18, var19)
      54 [-]: SETTABLEKS R16 R15 K12; var16["rot"] = var15
      55 [-]: DUPTABLE R16 30; 
      56 [-]: GETIMPORT R17 15; var17 = 0xA421AF95
      57 [-]: LOADK R18 K31; var18 = -0.106256
      58 [-]: LOADK R19 K17; var19 = 1.18753
      59 [-]: LOADK R20 K18; var20 = -0.026268
      60 [-]: CALL R17 4 2 ; var17 = var17(var18, var19, var20)
      61 [-]: SETTABLEKS R17 R16 K11; var17["pos"] = var16
      62 [-]: GETIMPORT R17 20; var17 = 0x00046924
      63 [-]: LOADK R18 K32; var18 = 2.49681
      64 [-]: LOADK R19 K33; var19 = 0.36421999999999999
      65 [-]: LOADK R20 K34; var20 = 0.19839499999999999
      66 [-]: CALL R17 4 2 ; var17 = var17(var18, var19, var20)
      67 [-]: SETTABLEKS R17 R16 K12; var17["rot"] = var16
      68 [-]: LOADK R17 K35; var17 = 39.384990000000002
      69 [-]: SETTABLEKS R17 R16 K29; var17["fov"] = var16
      70 [-]: LOADNIL R17  ; var17 = nil
      71 [-]: LOADB R18 0  ; var18 = false
      72 [-]: LOADB R19 0  ; var19 = false
      73 [-]: DUPTABLE R20 41; 
      74 [-]: LOADN R21 1  ; var21 = 1
      75 [-]: SETTABLEKS R21 R20 K36; var21["SETUP"] = var20
      76 [-]: LOADN R21 2  ; var21 = 2
      77 [-]: SETTABLEKS R21 R20 K37; var21["CINEMATIC_WAIT"] = var20
      78 [-]: LOADN R21 3  ; var21 = 3
      79 [-]: SETTABLEKS R21 R20 K38; var21["LESSON"] = var20
      80 [-]: LOADN R21 4  ; var21 = 4
      81 [-]: SETTABLEKS R21 R20 K39; var21["ANNOUNCEMENT"] = var20
      82 [-]: LOADN R21 5  ; var21 = 5
      83 [-]: SETTABLEKS R21 R20 K40; var21["COMPLETE"] = var20
      84 [-]: NEWTABLE R21 0 4; var21 = {}
      85 [-]: DUPTABLE R22 43; 
      86 [-]: LOADK R23 K44; var23 = "Setup"
      87 [-]: SETTABLEKS R23 R22 K42; var23["name"] = var22
      88 [-]: DUPTABLE R23 43; 
      89 [-]: LOADK R24 K45; var24 = "CinematicWait"
      90 [-]: SETTABLEKS R24 R23 K42; var24["name"] = var23
      91 [-]: DUPTABLE R24 43; 
      92 [-]: LOADK R25 K46; var25 = "Lesson"
      93 [-]: SETTABLEKS R25 R24 K42; var25["name"] = var24
      94 [-]: DUPTABLE R25 43; 
      95 [-]: LOADK R26 K47; var26 = "Annoucement"
      96 [-]: SETTABLEKS R26 R25 K42; var26["name"] = var25
      97 [-]: SETLIST R21 R22 4 [1]; var21[1] = var22; var21[2] = var23; var21[3] = var24; var21[4] = var25; var21[5] = var26; 
      98 [-]: DUPTABLE R22 52; 
      99 [-]: GETIMPORT R23 54; var23 = 0x0469F296
     100 [-]: LOADK R24 K55; var24 = "BallasKillTheDevil"
     101 [-]: CALL R23 2 2 ; var23 = var23(var24)
     102 [-]: SETTABLEKS R23 R22 K48; var23["ballasKillDevil"] = var22
     103 [-]: GETIMPORT R23 54; var23 = 0x0469F296
     104 [-]: LOADK R24 K56; var24 = "AnnouncerStarts"
     105 [-]: CALL R23 2 2 ; var23 = var23(var24)
     106 [-]: SETTABLEKS R23 R22 K49; var23["annoucementStart"] = var22
     107 [-]: GETIMPORT R23 54; var23 = 0x0469F296
     108 [-]: LOADK R24 K57; var24 = "AnnouncerCountdownBegins"
     109 [-]: CALL R23 2 2 ; var23 = var23(var24)
     110 [-]: SETTABLEKS R23 R22 K50; var23["announcementCountdownBegin"] = var22
     111 [-]: GETIMPORT R23 54; var23 = 0x0469F296
     112 [-]: LOADK R24 K58; var24 = "AnnouncerCountdownEnds"
     113 [-]: CALL R23 2 2 ; var23 = var23(var24)
     114 [-]: SETTABLEKS R23 R22 K51; var23["announcementCountdownEnd"] = var22
     115 [-]: DUPTABLE R23 62; 
     116 [-]: GETIMPORT R24 54; var24 = 0x0469F296
     117 [-]: LOADK R25 K63; var25 = "IntroCin"
     118 [-]: CALL R24 2 2 ; var24 = var24(var25)
     119 [-]: SETTABLEKS R24 R23 K59; var24["INTRO"] = var23
     120 [-]: GETIMPORT R24 54; var24 = 0x0469F296
     121 [-]: LOADK R25 K64; var25 = "TabletCin"
     122 [-]: CALL R24 2 2 ; var24 = var24(var25)
     123 [-]: SETTABLEKS R24 R23 K60; var24["TABLET"] = var23
     124 [-]: GETIMPORT R24 54; var24 = 0x0469F296
     125 [-]: LOADK R25 K65; var25 = "LookUpCin"
     126 [-]: CALL R24 2 2 ; var24 = var24(var25)
     127 [-]: SETTABLEKS R24 R23 K61; var24["LOOK_UP"] = var23
     128 [-]: DUPCLOSURE R24 K66; 
     129 [-]: CAPTURE VAL R21; 
     130 [-]: DUPCLOSURE R25 K67; 
     131 [-]: CAPTURE VAL R21; 
     132 [-]: DUPCLOSURE R26 K68; 
     133 [-]: CAPTURE VAL R21; 
     134 [-]: NEWCLOSURE R27 P3; 
     135 [-]: CAPTURE REF R9; 
     136 [-]: DUPCLOSURE R28 K69; 
     137 [-]: DUPCLOSURE R29 K70; 
     138 [-]: NEWCLOSURE R30 P6; 
     139 [-]: CAPTURE VAL R27; 
     140 [-]: CAPTURE REF R9; 
     141 [-]: CAPTURE VAL R29; 
     142 [-]: CAPTURE VAL R4; 
     143 [-]: NEWCLOSURE R31 P7; 
     144 [-]: CAPTURE REF R18; 
     145 [-]: NEWCLOSURE R32 P8; 
     146 [-]: CAPTURE REF R19; 
     147 [-]: CAPTURE REF R7; 
     148 [-]: CAPTURE VAL R20; 
     149 [-]: NEWCLOSURE R33 P9; 
     150 [-]: CAPTURE VAL R3; 
     151 [-]: CAPTURE REF R17; 
     152 [-]: CAPTURE VAL R1; 
     153 [-]: CAPTURE VAL R22; 
     154 [-]: CAPTURE REF R7; 
     155 [-]: CAPTURE VAL R20; 
     156 [-]: SETGLOBAL R33 K71; "AnnouncementFlow" = var33
     157 [-]: DUPCLOSURE R33 K72; 
     158 [-]: SETGLOBAL R33 K73; "VoidEffects" = var33
     159 [-]: DUPCLOSURE R33 K74; 
     160 [-]: CAPTURE VAL R23; 
     161 [-]: CAPTURE VAL R6; 
     162 [-]: SETGLOBAL R33 K75; "OnSkipped" = var33
     163 [-]: DUPCLOSURE R33 K76; 
     164 [-]: NEWCLOSURE R34 P13; 
     165 [-]: CAPTURE VAL R26; 
     166 [-]: CAPTURE VAL R2; 
     167 [-]: CAPTURE REF R17; 
     168 [-]: CAPTURE REF R7; 
     169 [-]: CAPTURE VAL R20; 
     170 [-]: NEWCLOSURE R35 P14; 
     171 [-]: CAPTURE VAL R27; 
     172 [-]: CAPTURE REF R8; 
     173 [-]: CAPTURE VAL R20; 
     174 [-]: CAPTURE REF R7; 
     175 [-]: CAPTURE REF R10; 
     176 [-]: CAPTURE REF R13; 
     177 [-]: CAPTURE VAL R14; 
     178 [-]: CAPTURE REF R11; 
     179 [-]: CAPTURE VAL R15; 
     180 [-]: CAPTURE REF R9; 
     181 [-]: CAPTURE REF R18; 
     182 [-]: CAPTURE REF R19; 
     183 [-]: CAPTURE VAL R23; 
     184 [-]: CAPTURE VAL R32; 
     185 [-]: CAPTURE REF R12; 
     186 [-]: NEWCLOSURE R36 P15; 
     187 [-]: CAPTURE VAL R21; 
     188 [-]: CAPTURE VAL R20; 
     189 [-]: CAPTURE VAL R2; 
     190 [-]: CAPTURE REF R10; 
     191 [-]: CAPTURE VAL R23; 
     192 [-]: CAPTURE VAL R30; 
     193 [-]: CAPTURE REF R13; 
     194 [-]: CAPTURE VAL R5; 
     195 [-]: CAPTURE VAL R3; 
     196 [-]: CAPTURE VAL R22; 
     197 [-]: CAPTURE REF R9; 
     198 [-]: CAPTURE REF R17; 
     199 [-]: CAPTURE VAL R31; 
     200 [-]: CAPTURE REF R12; 
     201 [-]: CAPTURE VAL R16; 
     202 [-]: CAPTURE VAL R0; 
     203 [-]: NEWCLOSURE R37 P16; 
     204 [-]: CAPTURE REF R7; 
     205 [-]: CAPTURE VAL R1; 
     206 [-]: CAPTURE VAL R36; 
     207 [-]: CAPTURE VAL R34; 
     208 [-]: CAPTURE REF R8; 
     209 [-]: CAPTURE VAL R35; 
     210 [-]: SETGLOBAL R37 K77; "Mission" = var37
     211 [-]: DUPCLOSURE R37 K78; 
     212 [-]: SETGLOBAL R37 K79; "BlackBoardTransmission" = var37
     213 [-]: NEWTABLE R37 0 0; var37 = {}
     214 [-]: DUPCLOSURE R38 K80; 
     215 [-]: CAPTURE VAL R37; 
     216 [-]: SETGLOBAL R38 K81; "PlayAnimationThread" = var38
     217 [-]: DUPCLOSURE R38 K82; 
     218 [-]: CAPTURE VAL R37; 
     219 [-]: SETGLOBAL R38 K83; "PlayClassroomAnimation" = var38
     220 [-]: CLOSEUPVALS R7; 
     221 [-]: RETURN R0 0  ; 


; Name:            
; Defined at line: 93
; #Upvalues:       1
; #Parameters:     1
; Is_vararg:       0
; Max Stack Size:  5

       0 [-]: GETUPVAL R3 0; var3 = upvalues[0]
       1 [-]: GETTABLE R2 R3 R0; var2 = var3[var0]
       2 [-]: FASTCALL1 62 R2 L0; 
       3 [-]: GETIMPORT R1 1; var1 = 0x7B998233
       4 [-]: CALL R1 2 2  ; var1 = var1(var2)
L 0:   5 [-]: JUMPIFNOT R1 L1; goto L1 if not var1
       6 [-]: RETURN R0 0  ; 
L 1:   7 [-]: LOADN R1 0   ; var1 = 0
       8 [-]: JUMPIFNOTLT R1 R0 L3; goto L3 if var1 >= var1031
       9 [-]: GETUPVAL R4 0; var4 = upvalues[0]
      10 [-]: GETTABLE R3 R4 R0; var3 = var4[var0]
      11 [-]: GETTABLEKS R2 R3 K2; var2 = var3["startF"]
      12 [-]: FASTCALL1 62 R2 L2; 
      13 [-]: GETIMPORT R1 1; var1 = 0x7B998233
      14 [-]: CALL R1 2 2  ; var1 = var1(var2)
L 2:  15 [-]: JUMPIF R1 L3 ; goto L3 if var1
      16 [-]: GETUPVAL R3 0; var3 = upvalues[0]
      17 [-]: GETTABLE R2 R3 R0; var2 = var3[var0]
      18 [-]: GETTABLEKS R1 R2 K2; var1 = var2["startF"]
      19 [-]: LOADK R3 K3  ; var3 = "TriggerPort"
      20 [-]: NAMECALL R1 R1 K4; var2 = var1; var1 = var1[0x8EB2112D]
      21 [-]: CALL R1 3 1  ; var1(var2, var3)
L 3:  22 [-]: RETURN R0 0  ; 


; Name:            
; Defined at line: 103
; #Upvalues:       1
; #Parameters:     1
; Is_vararg:       0
; Max Stack Size:  5

       0 [-]: GETUPVAL R3 0; var3 = upvalues[0]
       1 [-]: GETTABLE R2 R3 R0; var2 = var3[var0]
       2 [-]: FASTCALL1 62 R2 L0; 
       3 [-]: GETIMPORT R1 1; var1 = 0x7B998233
       4 [-]: CALL R1 2 2  ; var1 = var1(var2)
L 0:   5 [-]: JUMPIFNOT R1 L1; goto L1 if not var1
       6 [-]: RETURN R0 0  ; 
L 1:   7 [-]: LOADN R1 0   ; var1 = 0
       8 [-]: JUMPIFNOTLT R1 R0 L3; goto L3 if var1 >= var1031
       9 [-]: GETUPVAL R4 0; var4 = upvalues[0]
      10 [-]: GETTABLE R3 R4 R0; var3 = var4[var0]
      11 [-]: GETTABLEKS R2 R3 K2; var2 = var3["endF"]
      12 [-]: FASTCALL1 62 R2 L2; 
      13 [-]: GETIMPORT R1 1; var1 = 0x7B998233
      14 [-]: CALL R1 2 2  ; var1 = var1(var2)
L 2:  15 [-]: JUMPIF R1 L3 ; goto L3 if var1
      16 [-]: GETUPVAL R3 0; var3 = upvalues[0]
      17 [-]: GETTABLE R2 R3 R0; var2 = var3[var0]
      18 [-]: GETTABLEKS R1 R2 K2; var1 = var2["endF"]
      19 [-]: LOADK R3 K3  ; var3 = "TriggerPort"
      20 [-]: NAMECALL R1 R1 K4; var2 = var1; var1 = var1[0x8EB2112D]
      21 [-]: CALL R1 3 1  ; var1(var2, var3)
L 3:  22 [-]: RETURN R0 0  ; 


; Name:            
; Defined at line: 113
; #Upvalues:       1
; #Parameters:     0
; Is_vararg:       0
; Max Stack Size:  12

       0 [-]: LOADN R2 1   ; var2 = 1
       1 [-]: GETUPVAL R3 0; var3 = upvalues[0]
       2 [-]: LENGTH R0 R3 ; var0 = #var3
       3 [-]: LOADN R1 1   ; var1 = 1
       4 [-]: FORNPREP R0 L3; nforprep start - [escape at L3] -- var0 = iterator
L 0:   5 [-]: GETUPVAL R5 0; var5 = upvalues[0]
       6 [-]: GETTABLE R4 R5 R2; var4 = var5[var2]
       7 [-]: FASTCALL1 62 R4 L1; 
       8 [-]: GETIMPORT R3 1; var3 = 0x7B998233
       9 [-]: CALL R3 2 2  ; var3 = var3(var4)
L 1:  10 [-]: JUMPIF R3 L2 ; goto L2 if var3
      11 [-]: GETUPVAL R4 0; var4 = upvalues[0]
      12 [-]: GETTABLE R3 R4 R2; var3 = var4[var2]
      13 [-]: GETIMPORT R4 3; var4 = 0x89326C93
      14 [-]: GETIMPORT R6 5; var6 = 0x0469F296
      15 [-]: GETUPVAL R11 0; var11 = upvalues[0]
      16 [-]: GETTABLE R10 R11 R2; var10 = var11[var2]
      17 [-]: GETTABLEKS R8 R10 K6; var8 = var10["name"]
      18 [-]: LOADK R9 K7  ; var9 = "Start"
      19 [-]: CONCAT R7 R8 R9; var7 = var8 .. var9
      20 [-]: CALL R6 2 0  ; var6, ... = var6(var7)
      21 [-]: NAMECALL R4 R4 K8; var5 = var4; var4 = var4[0x46A0EBF5]
      22 [-]: CALL R4 0 2  ; var4 = var4(var5, ...)
      23 [-]: SETTABLEKS R4 R3 K9; var4["startF"] = var3
      24 [-]: GETUPVAL R4 0; var4 = upvalues[0]
      25 [-]: GETTABLE R3 R4 R2; var3 = var4[var2]
      26 [-]: GETIMPORT R4 3; var4 = 0x89326C93
      27 [-]: GETIMPORT R6 5; var6 = 0x0469F296
      28 [-]: GETUPVAL R11 0; var11 = upvalues[0]
      29 [-]: GETTABLE R10 R11 R2; var10 = var11[var2]
      30 [-]: GETTABLEKS R8 R10 K6; var8 = var10["name"]
      31 [-]: LOADK R9 K10 ; var9 = "Ended"
      32 [-]: CONCAT R7 R8 R9; var7 = var8 .. var9
      33 [-]: CALL R6 2 0  ; var6, ... = var6(var7)
      34 [-]: NAMECALL R4 R4 K8; var5 = var4; var4 = var4[0x46A0EBF5]
      35 [-]: CALL R4 0 2  ; var4 = var4(var5, ...)
      36 [-]: SETTABLEKS R4 R3 K11; var4["endF"] = var3
      37 [-]: GETUPVAL R4 0; var4 = upvalues[0]
      38 [-]: GETTABLE R3 R4 R2; var3 = var4[var2]
      39 [-]: GETIMPORT R4 3; var4 = 0x89326C93
      40 [-]: GETIMPORT R6 5; var6 = 0x0469F296
      41 [-]: GETUPVAL R11 0; var11 = upvalues[0]
      42 [-]: GETTABLE R10 R11 R2; var10 = var11[var2]
      43 [-]: GETTABLEKS R8 R10 K6; var8 = var10["name"]
      44 [-]: LOADK R9 K12 ; var9 = "Stop"
      45 [-]: CONCAT R7 R8 R9; var7 = var8 .. var9
      46 [-]: CALL R6 2 0  ; var6, ... = var6(var7)
      47 [-]: NAMECALL R4 R4 K8; var5 = var4; var4 = var4[0x46A0EBF5]
      48 [-]: CALL R4 0 2  ; var4 = var4(var5, ...)
      49 [-]: SETTABLEKS R4 R3 K13; var4["stopC"] = var3
L 2:  50 [-]: FORNLOOP R0 L0; nforloop end - iterate + goto L0
L 3:  51 [-]: RETURN R0 0  ; 


; Name:            
; Defined at line: 123
; #Upvalues:       1
; #Parameters:     1
; Is_vararg:       0
; Max Stack Size:  3

       0 [-]: JUMPIFNOT R0 L3; goto L3 if not var0
L 0:   1 [-]: GETUPVAL R2 0; var2 = upvalues[0]
       2 [-]: FASTCALL1 62 R2 L1; 
       3 [-]: GETIMPORT R1 1; var1 = 0x7B998233
       4 [-]: CALL R1 2 2  ; var1 = var1(var2)
L 1:   5 [-]: JUMPIF R1 L2 ; goto L2 if var1
       6 [-]: GETUPVAL R1 0; var1 = upvalues[0]
       7 [-]: NAMECALL R1 R1 K2; var2 = var1; var1 = var1[0xA5E492D4]
       8 [-]: CALL R1 2 2  ; var1 = var1(var2)
       9 [-]: JUMPIF R1 L6 ; goto L6 if var1
L 2:  10 [-]: GETIMPORT R1 4; var1 = 0x89326C93
      11 [-]: NAMECALL R1 R1 K5; var2 = var1; var1 = var1[0x78298275]
      12 [-]: CALL R1 2 2  ; var1 = var1(var2)
      13 [-]: SETUPVAL R1 0; upvalues[1] = var0
      14 [-]: GETIMPORT R1 7; var1 = 0xCBD666E1
      15 [-]: LOADN R2 0   ; var2 = 0
      16 [-]: CALL R1 2 1  ; var1(var2)
      17 [-]: JUMPBACK L0  ; goto L0
      18 [-]: RETURN R0 0  ; 
L 3:  19 [-]: GETUPVAL R2 0; var2 = upvalues[0]
      20 [-]: FASTCALL1 62 R2 L4; 
      21 [-]: GETIMPORT R1 1; var1 = 0x7B998233
      22 [-]: CALL R1 2 2  ; var1 = var1(var2)
L 4:  23 [-]: JUMPIF R1 L5 ; goto L5 if var1
      24 [-]: GETUPVAL R1 0; var1 = upvalues[0]
      25 [-]: NAMECALL R1 R1 K2; var2 = var1; var1 = var1[0xA5E492D4]
      26 [-]: CALL R1 2 2  ; var1 = var1(var2)
      27 [-]: JUMPIF R1 L6 ; goto L6 if var1
L 5:  28 [-]: GETIMPORT R1 4; var1 = 0x89326C93
      29 [-]: NAMECALL R1 R1 K5; var2 = var1; var1 = var1[0x78298275]
      30 [-]: CALL R1 2 2  ; var1 = var1(var2)
      31 [-]: SETUPVAL R1 0; upvalues[1] = var0
L 6:  32 [-]: RETURN R0 0  ; 


; Name:            
; Defined at line: 138
; #Upvalues:       0
; #Parameters:     0
; Is_vararg:       0
; Max Stack Size:  5

       0 [-]: GETIMPORT R0 1; var0 = 0x0469F296
       1 [-]: LOADK R1 K2  ; var1 = "ActTwoZarimanMusical"
       2 [-]: CALL R0 2 2  ; var0 = var0(var1)
       3 [-]: GETIMPORT R1 4; var1 = 0x7ED0A956
       4 [-]: LOADK R2 K5  ; var2 = "/Lotus/Levels/Proc/TheNewWar/PartTwo/TNWGrineerOceanNarmerLab"
       5 [-]: CALL R1 2 2  ; var1 = var1(var2)
       6 [-]: GETIMPORT R2 7; var2 = 0xBE190284
       7 [-]: NAMECALL R2 R2 K8; var3 = var2; var2 = var2[0xEF893AEC]
       8 [-]: CALL R2 2 2  ; var2 = var2(var3)
       9 [-]: FASTCALL1 62 R2 L0; 
      10 [-]: MOVE R4 R2   ; var4 = var2
      11 [-]: GETIMPORT R3 10; var3 = 0x7B998233
      12 [-]: CALL R3 2 2  ; var3 = var3(var4)
L 0:  13 [-]: JUMPIF R3 L3 ; goto L3 if var3
      14 [-]: GETTABLEKS R4 R2 K11; var4 = var2["levelOverride"]
      15 [-]: FASTCALL1 62 R4 L1; 
      16 [-]: GETIMPORT R3 10; var3 = 0x7B998233
      17 [-]: CALL R3 2 2  ; var3 = var3(var4)
L 1:  18 [-]: JUMPIF R3 L3 ; goto L3 if var3
      19 [-]: GETTABLEKS R3 R2 K11; var3 = var2["levelOverride"]
      20 [-]: JUMPIFNOTEQ R3 R1 L3; goto L3 if var3 ~= var-1493040100
      21 [-]: GETTABLEKS R4 R2 K12; var4 = var2["goalTag"]
      22 [-]: FASTCALL1 62 R4 L2; 
      23 [-]: GETIMPORT R3 10; var3 = 0x7B998233
      24 [-]: CALL R3 2 2  ; var3 = var3(var4)
L 2:  25 [-]: JUMPIF R3 L3 ; goto L3 if var3
      26 [-]: GETTABLEKS R3 R2 K12; var3 = var2["goalTag"]
      27 [-]: JUMPIFEQ R3 R0 L4; goto L4 if var3 == var795
L 3:  28 [-]: LOADB R3 0   ; var3 = false
      29 [-]: RETURN R3 1  ; 
L 4:  30 [-]: LOADB R3 1   ; var3 = true
      31 [-]: RETURN R3 1  ; 


; Name:            
; Defined at line: 153
; #Upvalues:       0
; #Parameters:     2
; Is_vararg:       0
; Max Stack Size:  10

       0 [-]: DUPCLOSURE R2 K0; 
       1 [-]: MOVE R3 R0   ; var3 = var0
       2 [-]: JUMPIF R3 L0 ; goto L0 if var3
       3 [-]: MOVE R3 R2   ; var3 = var2
       4 [-]: CALL R3 1 2  ; var3 = var3()
L 0:   5 [-]: MOVE R0 R3   ; var0 = var3
       6 [-]: MOVE R3 R0   ; var3 = var0
       7 [-]: GETIMPORT R6 2; var6 = 0xEE7500B9
       8 [-]: NAMECALL R4 R3 K3; var5 = var3; var4 = var3[0xF2DEAF69]
       9 [-]: CALL R4 3 2  ; var4 = var4(var5, var6)
      10 [-]: JUMPIF R4 L1 ; goto L1 if var4
      11 [-]: GETIMPORT R6 5; var6 = gTennoAvatarType
      12 [-]: NAMECALL R4 R3 K3; var5 = var3; var4 = var3[0xF2DEAF69]
      13 [-]: CALL R4 3 2  ; var4 = var4(var5, var6)
      14 [-]: JUMPIFNOT R4 L1; goto L1 if not var4
      15 [-]: JUMPIFNOT R1 L4; goto L4 if not var1
L 1:  16 [-]: GETIMPORT R4 7; var4 = 0x89326C93
      17 [-]: NAMECALL R4 R4 K8; var5 = var4; var4 = var4[0xFB64E76C]
      18 [-]: CALL R4 2 2  ; var4 = var4(var5)
      19 [-]: GETIMPORT R5 7; var5 = 0x89326C93
      20 [-]: GETIMPORT R7 10; var7 = 0x0469F296
      21 [-]: LOADK R8 K11 ; var8 = "TNWZarimanOperator"
      22 [-]: CALL R7 2 2  ; var7 = var7(var8)
      23 [-]: NAMECALL R5 R5 K12; var6 = var5; var5 = var5[0x46A0EBF5]
      24 [-]: CALL R5 3 2  ; var5 = var5(var6, var7)
      25 [-]: FASTCALL1 62 R5 L2; 
      26 [-]: MOVE R7 R5   ; var7 = var5
      27 [-]: GETIMPORT R6 14; var6 = 0x7B998233
      28 [-]: CALL R6 2 2  ; var6 = var6(var7)
L 2:  29 [-]: JUMPIFNOT R6 L3; goto L3 if not var6
      30 [-]: RETURN R0 0  ; 
L 3:  31 [-]: LOADB R8 1   ; var8 = true
      32 [-]: NAMECALL R6 R5 K15; var7 = var5; var6 = var5[0x768274D6]
      33 [-]: CALL R6 3 1  ; var6(var7, var8)
      34 [-]: LOADN R8 1   ; var8 = 1
      35 [-]: LOADB R9 1   ; var9 = true
      36 [-]: NAMECALL R6 R5 K16; var7 = var5; var6 = var5[0x2D9BA74F]
      37 [-]: CALL R6 4 1  ; var6(var7, var8, var9)
      38 [-]: MOVE R8 R5   ; var8 = var5
      39 [-]: LOADB R9 1   ; var9 = true
      40 [-]: NAMECALL R6 R4 K17; var7 = var4; var6 = var4[0x480B3AAE]
      41 [-]: CALL R6 4 1  ; var6(var7, var8, var9)
      42 [-]: RETURN R5 1  ; 
L 4:  43 [-]: GETIMPORT R5 19; var5 = 0xBE190284
      44 [-]: FASTCALL1 62 R5 L5; 
      45 [-]: GETIMPORT R4 14; var4 = 0x7B998233
      46 [-]: CALL R4 2 2  ; var4 = var4(var5)
L 5:  47 [-]: JUMPIF R4 L10; goto L10 if var4
      48 [-]: GETIMPORT R4 19; var4 = 0xBE190284
      49 [-]: GETIMPORT R6 21; var6 = gLotusAttractModeGameRulesType
      50 [-]: NAMECALL R4 R4 K3; var5 = var4; var4 = var4[0xF2DEAF69]
      51 [-]: CALL R4 3 2  ; var4 = var4(var5, var6)
      52 [-]: JUMPIFNOT R4 L10; goto L10 if not var4
L 6:  53 [-]: GETIMPORT R5 24; var5 = _T["defaultOperatorRot"]
      54 [-]: FASTCALL1 62 R5 L7; 
      55 [-]: GETIMPORT R4 14; var4 = 0x7B998233
      56 [-]: CALL R4 2 2  ; var4 = var4(var5)
L 7:  57 [-]: JUMPIF R4 L9 ; goto L9 if var4
      58 [-]: GETIMPORT R5 24; var5 = _T["defaultOperatorRot"]
      59 [-]: FASTCALL1 62 R5 L8; 
      60 [-]: GETIMPORT R4 14; var4 = 0x7B998233
      61 [-]: CALL R4 2 2  ; var4 = var4(var5)
L 8:  62 [-]: JUMPIFNOT R4 L10; goto L10 if not var4
L 9:  63 [-]: GETIMPORT R4 26; var4 = 0xCBD666E1
      64 [-]: LOADN R5 0   ; var5 = 0
      65 [-]: CALL R4 2 1  ; var4(var5)
      66 [-]: JUMPBACK L6  ; goto L6
L10:  67 [-]: GETIMPORT R4 27; var4 = _T
      68 [-]: NAMECALL R5 R3 K28; var6 = var3; var5 = var3[0xD1586535]
      69 [-]: CALL R5 2 2  ; var5 = var5(var6)
      70 [-]: SETTABLEKS R5 R4 K29; var5["OverrideTransferencePos"] = var4
      71 [-]: GETIMPORT R4 27; var4 = _T
      72 [-]: LOADB R5 1   ; var5 = true
      73 [-]: SETTABLEKS R5 R4 K30; var5["HideTransferenceFx"] = var4
      74 [-]: NAMECALL R4 R3 K31; var5 = var3; var4 = var3[0x18F03C5D]
      75 [-]: CALL R4 2 1  ; var4(var5)
L11:  76 [-]: FASTCALL1 62 R0 L12; 
      77 [-]: MOVE R5 R0   ; var5 = var0
      78 [-]: GETIMPORT R4 14; var4 = 0x7B998233
      79 [-]: CALL R4 2 2  ; var4 = var4(var5)
L12:  80 [-]: JUMPIF R4 L13; goto L13 if var4
      81 [-]: GETIMPORT R6 33; var6 = gLotusOperatorAvatarType
      82 [-]: NAMECALL R4 R0 K3; var5 = var0; var4 = var0[0xF2DEAF69]
      83 [-]: CALL R4 3 2  ; var4 = var4(var5, var6)
      84 [-]: JUMPIF R4 L16; goto L16 if var4
L13:  85 [-]: GETIMPORT R4 26; var4 = 0xCBD666E1
      86 [-]: LOADN R5 0   ; var5 = 0
      87 [-]: CALL R4 2 1  ; var4(var5)
      88 [-]: MOVE R4 R2   ; var4 = var2
      89 [-]: CALL R4 1 2  ; var4 = var4()
      90 [-]: MOVE R0 R4   ; var0 = var4
      91 [-]: FASTCALL1 62 R3 L14; 
      92 [-]: MOVE R5 R3   ; var5 = var3
      93 [-]: GETIMPORT R4 14; var4 = 0x7B998233
      94 [-]: CALL R4 2 2  ; var4 = var4(var5)
L14:  95 [-]: JUMPIF R4 L15; goto L15 if var4
      96 [-]: NAMECALL R4 R3 K31; var5 = var3; var4 = var3[0x18F03C5D]
      97 [-]: CALL R4 2 1  ; var4(var5)
L15:  98 [-]: JUMPBACK L11 ; goto L11
L16:  99 [-]: GETIMPORT R4 27; var4 = _T
     100 [-]: LOADB R5 1   ; var5 = true
     101 [-]: SETTABLEKS R5 R4 K34; var5["DisableTransferenceToFrame"] = var4
     102 [-]: GETIMPORT R4 27; var4 = _T
     103 [-]: LOADNIL R5   ; var5 = nil
     104 [-]: SETTABLEKS R5 R4 K29; var5["OverrideTransferencePos"] = var4
     105 [-]: FASTCALL1 62 R3 L17; 
     106 [-]: MOVE R5 R3   ; var5 = var3
     107 [-]: GETIMPORT R4 14; var4 = 0x7B998233
     108 [-]: CALL R4 2 2  ; var4 = var4(var5)
L17: 109 [-]: JUMPIF R4 L18; goto L18 if var4
     110 [-]: LOADB R6 0   ; var6 = false
     111 [-]: LOADB R7 1   ; var7 = true
     112 [-]: NAMECALL R4 R3 K15; var5 = var3; var4 = var3[0x768274D6]
     113 [-]: CALL R4 4 1  ; var4(var5, var6, var7)
     114 [-]: RETURN R0 1  ; 
L18: 115 [-]: RETURN R0 0  ; 


; Name:            
; Defined at line: 216
; #Upvalues:       4
; #Parameters:     0
; Is_vararg:       0
; Max Stack Size:  11

       0 [-]: GETUPVAL R0 0; var0 = upvalues[0]
       1 [-]: LOADB R1 1   ; var1 = true
       2 [-]: CALL R0 2 1  ; var0(var1)
       3 [-]: GETUPVAL R0 1; var0 = upvalues[1]
       4 [-]: GETIMPORT R2 1; var2 = 0x0469F296
       5 [-]: LOADK R3 K2  ; var3 = "NotTenno"
       6 [-]: CALL R2 2 0  ; var2, ... = var2(var3)
       7 [-]: NAMECALL R0 R0 K3; var1 = var0; var0 = var0[0x26D544FC]
       8 [-]: CALL R0 0 1  ; var0(var1, ...)
       9 [-]: GETIMPORT R0 5; var0 = 0x89326C93
      10 [-]: GETIMPORT R2 1; var2 = 0x0469F296
      11 [-]: LOADK R3 K6  ; var3 = "DrifterDestination"
      12 [-]: CALL R2 2 0  ; var2, ... = var2(var3)
      13 [-]: NAMECALL R0 R0 K7; var1 = var0; var0 = var0[0x46A0EBF5]
      14 [-]: CALL R0 0 2  ; var0 = var0(var1, ...)
      15 [-]: GETUPVAL R1 1; var1 = upvalues[1]
      16 [-]: NAMECALL R3 R0 K8; var4 = var0; var3 = var0[0xD1586535]
      17 [-]: CALL R3 2 2  ; var3 = var3(var4)
      18 [-]: GETIMPORT R4 10; var4 = ZERO_ROTATION
      19 [-]: LOADB R5 1   ; var5 = true
      20 [-]: NAMECALL R1 R1 K11; var2 = var1; var1 = var1[0x589EF1C1]
      21 [-]: CALL R1 5 1  ; var1(var2, var3, var4, var5)
      22 [-]: GETUPVAL R1 1; var1 = upvalues[1]
      23 [-]: LOADB R3 0   ; var3 = false
      24 [-]: LOADB R4 1   ; var4 = true
      25 [-]: NAMECALL R1 R1 K12; var2 = var1; var1 = var1[0x768274D6]
      26 [-]: CALL R1 4 1  ; var1(var2, var3, var4)
      27 [-]: GETUPVAL R1 2; var1 = upvalues[2]
      28 [-]: GETUPVAL R2 1; var2 = upvalues[1]
      29 [-]: CALL R1 2 2  ; var1 = var1(var2)
      30 [-]: SETUPVAL R1 1; upvalues[1] = var1
      31 [-]: GETUPVAL R2 1; var2 = upvalues[1]
      32 [-]: FASTCALL1 62 R2 L0; 
      33 [-]: GETIMPORT R1 14; var1 = 0x7B998233
      34 [-]: CALL R1 2 2  ; var1 = var1(var2)
L 0:  35 [-]: JUMPIF R1 L5 ; goto L5 if var1
      36 [-]: GETUPVAL R1 1; var1 = upvalues[1]
      37 [-]: GETIMPORT R3 16; var3 = gLotusOperatorAvatarType
      38 [-]: NAMECALL R1 R1 K17; var2 = var1; var1 = var1[0xF2DEAF69]
      39 [-]: CALL R1 3 2  ; var1 = var1(var2, var3)
      40 [-]: JUMPIFNOT R1 L5; goto L5 if not var1
      41 [-]: GETUPVAL R1 1; var1 = upvalues[1]
      42 [-]: GETIMPORT R3 1; var3 = 0x0469F296
      43 [-]: LOADK R4 K18 ; var4 = "Tenno"
      44 [-]: CALL R3 2 0  ; var3, ... = var3(var4)
      45 [-]: NAMECALL R1 R1 K3; var2 = var1; var1 = var1[0x26D544FC]
      46 [-]: CALL R1 0 1  ; var1(var2, ...)
      47 [-]: GETUPVAL R1 1; var1 = upvalues[1]
      48 [-]: NAMECALL R1 R1 K19; var2 = var1; var1 = var1[0xD3A01177]
      49 [-]: CALL R1 2 2  ; var1 = var1(var2)
      50 [-]: LOADB R3 0   ; var3 = false
      51 [-]: NAMECALL R1 R1 K20; var2 = var1; var1 = var1[0x294E7C63]
      52 [-]: CALL R1 3 1  ; var1(var2, var3)
      53 [-]: GETUPVAL R1 1; var1 = upvalues[1]
      54 [-]: NAMECALL R1 R1 K19; var2 = var1; var1 = var1[0xD3A01177]
      55 [-]: CALL R1 2 2  ; var1 = var1(var2)
      56 [-]: LOADB R3 0   ; var3 = false
      57 [-]: NAMECALL R1 R1 K21; var2 = var1; var1 = var1[0x17E9BF45]
      58 [-]: CALL R1 3 1  ; var1(var2, var3)
      59 [-]: GETUPVAL R1 1; var1 = upvalues[1]
      60 [-]: NAMECALL R1 R1 K22; var2 = var1; var1 = var1[0xDE321E6F]
      61 [-]: CALL R1 2 2  ; var1 = var1(var2)
      62 [-]: LOADB R3 0   ; var3 = false
      63 [-]: NAMECALL R1 R1 K23; var2 = var1; var1 = var1[0xC7154A44]
      64 [-]: CALL R1 3 1  ; var1(var2, var3)
      65 [-]: GETUPVAL R1 1; var1 = upvalues[1]
      66 [-]: NAMECALL R1 R1 K22; var2 = var1; var1 = var1[0xDE321E6F]
      67 [-]: CALL R1 2 2  ; var1 = var1(var2)
      68 [-]: LOADB R3 0   ; var3 = false
      69 [-]: NAMECALL R1 R1 K24; var2 = var1; var1 = var1[0x3B832566]
      70 [-]: CALL R1 3 1  ; var1(var2, var3)
      71 [-]: GETUPVAL R1 1; var1 = upvalues[1]
      72 [-]: NAMECALL R1 R1 K22; var2 = var1; var1 = var1[0xDE321E6F]
      73 [-]: CALL R1 2 2  ; var1 = var1(var2)
      74 [-]: LOADN R3 0   ; var3 = 0
      75 [-]: LOADN R4 2   ; var4 = 2
      76 [-]: NAMECALL R1 R1 K25; var2 = var1; var1 = var1[0x4703255B]
      77 [-]: CALL R1 4 1  ; var1(var2, var3, var4)
      78 [-]: GETUPVAL R1 1; var1 = upvalues[1]
      79 [-]: LOADB R3 0   ; var3 = false
      80 [-]: NAMECALL R1 R1 K26; var2 = var1; var1 = var1[0xD9848B59]
      81 [-]: CALL R1 3 1  ; var1(var2, var3)
      82 [-]: GETUPVAL R1 1; var1 = upvalues[1]
      83 [-]: NAMECALL R1 R1 K19; var2 = var1; var1 = var1[0xD3A01177]
      84 [-]: CALL R1 2 2  ; var1 = var1(var2)
      85 [-]: LOADB R3 0   ; var3 = false
      86 [-]: NAMECALL R1 R1 K27; var2 = var1; var1 = var1[0x258E7323]
      87 [-]: CALL R1 3 1  ; var1(var2, var3)
      88 [-]: GETUPVAL R1 1; var1 = upvalues[1]
      89 [-]: LOADB R3 0   ; var3 = false
      90 [-]: NAMECALL R1 R1 K28; var2 = var1; var1 = var1[0xF3CD941B]
      91 [-]: CALL R1 3 1  ; var1(var2, var3)
      92 [-]: GETUPVAL R1 1; var1 = upvalues[1]
      93 [-]: LOADB R3 0   ; var3 = false
      94 [-]: NAMECALL R1 R1 K29; var2 = var1; var1 = var1[0xAB108FBB]
      95 [-]: CALL R1 3 1  ; var1(var2, var3)
      96 [-]: GETUPVAL R1 1; var1 = upvalues[1]
      97 [-]: LOADB R3 0   ; var3 = false
      98 [-]: NAMECALL R1 R1 K30; var2 = var1; var1 = var1[0xA2A052F0]
      99 [-]: CALL R1 3 1  ; var1(var2, var3)
     100 [-]: GETUPVAL R1 1; var1 = upvalues[1]
     101 [-]: GETIMPORT R3 32; var3 = gLotusWeaponAttachmentType
     102 [-]: NAMECALL R1 R1 K33; var2 = var1; var1 = var1[0xC1595BD5]
     103 [-]: CALL R1 3 2  ; var1 = var1(var2, var3)
     104 [-]: GETIMPORT R2 35; var2 = 0xC8802016
     105 [-]: MOVE R3 R1   ; var3 = var1
     106 [-]: CALL R2 2 4  ; var2, var3, var4 = var2(var3)
     107 [-]: FORGPREP_INEXT R2 L3; 
L 1: 108 [-]: NAMECALL R7 R6 K36; var8 = var6; var7 = var6[0x73A8846A]
     109 [-]: CALL R7 2 2  ; var7 = var7(var8)
     110 [-]: FASTCALL1 62 R7 L2; 
     111 [-]: MOVE R9 R7   ; var9 = var7
     112 [-]: GETIMPORT R8 14; var8 = 0x7B998233
     113 [-]: CALL R8 2 2  ; var8 = var8(var9)
L 2: 114 [-]: JUMPIF R8 L3 ; goto L3 if var8
     115 [-]: LOADB R10 1  ; var10 = true
     116 [-]: NAMECALL R8 R6 K37; var9 = var6; var8 = var6[0x014CA753]
     117 [-]: CALL R8 3 1  ; var8(var9, var10)
L 3: 118 [-]: FORGLOOP R2 L1 2 [inext]; 
     119 [-]: GETIMPORT R2 39; var2 = 0xB009BBC6
     120 [-]: LOADK R3 K40 ; var3 = "/Lotus/Upgrades/Skins/Operator/Hoods/HoodA"
     121 [-]: CALL R2 2 2  ; var2 = var2(var3)
     122 [-]: GETUPVAL R4 3; var4 = upvalues[3]
     123 [-]: GETTABLEKS R3 R4 K41; var3 = var4[0xBEC8B821]
     124 [-]: GETUPVAL R4 1; var4 = upvalues[1]
     125 [-]: LOADB R5 1   ; var5 = true
     126 [-]: CALL R3 3 1  ; var3(var4, var5)
     127 [-]: GETIMPORT R3 43; var3 = 0xCBD666E1
     128 [-]: LOADN R4 0   ; var4 = 0
     129 [-]: CALL R3 2 1  ; var3(var4)
     130 [-]: GETUPVAL R4 3; var4 = upvalues[3]
     131 [-]: GETTABLEKS R3 R4 K44; var3 = var4[0x101F906D]
     132 [-]: GETUPVAL R4 1; var4 = upvalues[1]
     133 [-]: LOADB R5 1   ; var5 = true
     134 [-]: CALL R3 3 1  ; var3(var4, var5)
     135 [-]: GETIMPORT R3 43; var3 = 0xCBD666E1
     136 [-]: LOADN R4 0   ; var4 = 0
     137 [-]: CALL R3 2 1  ; var3(var4)
     138 [-]: GETIMPORT R3 5; var3 = 0x89326C93
     139 [-]: GETIMPORT R5 1; var5 = 0x0469F296
     140 [-]: LOADK R6 K45 ; var6 = "WP_ZarimanHighschoolMusical"
     141 [-]: CALL R5 2 0  ; var5, ... = var5(var6)
     142 [-]: NAMECALL R3 R3 K7; var4 = var3; var3 = var3[0x46A0EBF5]
     143 [-]: CALL R3 0 2  ; var3 = var3(var4, ...)
     144 [-]: FASTCALL1 62 R3 L4; 
     145 [-]: MOVE R5 R3   ; var5 = var3
     146 [-]: GETIMPORT R4 14; var4 = 0x7B998233
     147 [-]: CALL R4 2 2  ; var4 = var4(var5)
L 4: 148 [-]: JUMPIF R4 L5 ; goto L5 if var4
     149 [-]: NAMECALL R4 R3 K46; var5 = var3; var4 = var3[0xCB3851B8]
     150 [-]: CALL R4 2 2  ; var4 = var4(var5)
     151 [-]: GETUPVAL R5 1; var5 = upvalues[1]
     152 [-]: NAMECALL R7 R3 K8; var8 = var3; var7 = var3[0xD1586535]
     153 [-]: CALL R7 2 2  ; var7 = var7(var8)
     154 [-]: MOVE R8 R4   ; var8 = var4
     155 [-]: NAMECALL R5 R5 K11; var6 = var5; var5 = var5[0x589EF1C1]
     156 [-]: CALL R5 4 1  ; var5(var6, var7, var8)
     157 [-]: GETUPVAL R5 1; var5 = upvalues[1]
     158 [-]: MOVE R7 R4   ; var7 = var4
     159 [-]: NAMECALL R5 R5 K47; var6 = var5; var5 = var5[0x89C6DBF7]
     160 [-]: CALL R5 3 1  ; var5(var6, var7)
L 5: 161 [-]: GETIMPORT R1 49; var1 = _T
     162 [-]: LOADB R2 1   ; var2 = true
     163 [-]: SETTABLEKS R2 R1 K50; var2["DisableTransferenceToFrame"] = var1
     164 [-]: GETIMPORT R1 49; var1 = _T
     165 [-]: LOADB R2 1   ; var2 = true
     166 [-]: SETTABLEKS R2 R1 K51; var2["HideTransferenceFx"] = var1
     167 [-]: RETURN R0 0  ; 


; Name:            
; Defined at line: 268
; #Upvalues:       1
; #Parameters:     0
; Is_vararg:       0
; Max Stack Size:  7

       0 [-]: GETIMPORT R1 1; var1 = 0x9CC73AEC
       1 [-]: FASTCALL1 62 R1 L0; 
       2 [-]: GETIMPORT R0 3; var0 = 0x7B998233
       3 [-]: CALL R0 2 2  ; var0 = var0(var1)
L 0:   4 [-]: JUMPIFNOT R0 L1; goto L1 if not var0
       5 [-]: RETURN R0 0  ; 
L 1:   6 [-]: LOADB R0 0   ; var0 = false
       7 [-]: SETUPVAL R0 0; upvalues[0] = var0
       8 [-]: GETIMPORT R0 5; var0 = 0x89326C93
       9 [-]: GETIMPORT R2 7; var2 = 0x0469F296
      10 [-]: LOADK R3 K8  ; var3 = "LessonScreen"
      11 [-]: CALL R2 2 0  ; var2, ... = var2(var3)
      12 [-]: NAMECALL R0 R0 K9; var1 = var0; var0 = var0[0x46A0EBF5]
      13 [-]: CALL R0 0 2  ; var0 = var0(var1, ...)
      14 [-]: FASTCALL1 62 R0 L2; 
      15 [-]: MOVE R2 R0   ; var2 = var0
      16 [-]: GETIMPORT R1 3; var1 = 0x7B998233
      17 [-]: CALL R1 2 2  ; var1 = var1(var2)
L 2:  18 [-]: JUMPIF R1 L3 ; goto L3 if var1
      19 [-]: GETIMPORT R1 11; var1 = _T
      20 [-]: DUPTABLE R2 16; 
      21 [-]: SETTABLEKS R0 R2 K12; var0["AttachEntity"] = var2
      22 [-]: GETIMPORT R3 18; var3 = 0xA421AF95
      23 [-]: LOADN R4 0   ; var4 = 0
      24 [-]: LOADK R5 K19 ; var5 = 1.8
      25 [-]: LOADK R6 K20 ; var6 = -0.5
      26 [-]: CALL R3 4 2  ; var3 = var3(var4, var5, var6)
      27 [-]: SETTABLEKS R3 R2 K13; var3["Offset"] = var2
      28 [-]: GETIMPORT R3 22; var3 = 0x00046924
      29 [-]: LOADN R4 -90 ; var4 = -90
      30 [-]: LOADN R5 0   ; var5 = 0
      31 [-]: LOADN R6 0   ; var6 = 0
      32 [-]: CALL R3 4 2  ; var3 = var3(var4, var5, var6)
      33 [-]: SETTABLEKS R3 R2 K14; var3["Rotation"] = var2
      34 [-]: GETIMPORT R3 18; var3 = 0xA421AF95
      35 [-]: LOADK R4 K23 ; var4 = 1.5
      36 [-]: LOADK R5 K23 ; var5 = 1.5
      37 [-]: LOADK R6 K23 ; var6 = 1.5
      38 [-]: CALL R3 4 2  ; var3 = var3(var4, var5, var6)
      39 [-]: SETTABLEKS R3 R2 K15; var3["Scale"] = var2
      40 [-]: SETTABLEKS R2 R1 K24; var2["NewWarLesson_AttachInfo"] = var1
L 3:  41 [-]: GETIMPORT R1 26; var1 = 0x9BA7909F
      42 [-]: GETIMPORT R3 1; var3 = 0x9CC73AEC
      43 [-]: NAMECALL R1 R1 K27; var2 = var1; var1 = var1[0xCFBA257F]
      44 [-]: CALL R1 3 2  ; var1 = var1(var2, var3)
      45 [-]: GETIMPORT R2 11; var2 = _T
      46 [-]: NEWCLOSURE R3 P0; 
      47 [-]: CAPTURE UPVAL U0; 
      48 [-]: SETTABLEKS R3 R2 K28; var3["LessonDone"] = var2
      49 [-]: LOADK R4 K29 ; var4 = "SetCallBack"
      50 [-]: LOADK R5 K28 ; var5 = "LessonDone"
      51 [-]: NAMECALL R2 R1 K30; var3 = var1; var2 = var1[0xE4162EED]
      52 [-]: CALL R2 4 1  ; var2(var3, var4, var5)
      53 [-]: RETURN R0 0  ; 


; Name:            
; Defined at line: 295
; #Upvalues:       3
; #Parameters:     0
; Is_vararg:       0
; Max Stack Size:  7

       0 [-]: GETIMPORT R1 1; var1 = 0x1D683BE5
       1 [-]: FASTCALL1 62 R1 L0; 
       2 [-]: GETIMPORT R0 3; var0 = 0x7B998233
       3 [-]: CALL R0 2 2  ; var0 = var0(var1)
L 0:   4 [-]: JUMPIFNOT R0 L1; goto L1 if not var0
       5 [-]: RETURN R0 0  ; 
L 1:   6 [-]: LOADB R0 1   ; var0 = true
       7 [-]: SETUPVAL R0 0; upvalues[0] = var0
       8 [-]: GETIMPORT R0 5; var0 = 0x89326C93
       9 [-]: GETIMPORT R2 7; var2 = 0x0469F296
      10 [-]: LOADK R3 K8  ; var3 = "PlayerTablet"
      11 [-]: CALL R2 2 0  ; var2, ... = var2(var3)
      12 [-]: NAMECALL R0 R0 K9; var1 = var0; var0 = var0[0x46A0EBF5]
      13 [-]: CALL R0 0 2  ; var0 = var0(var1, ...)
      14 [-]: FASTCALL1 62 R0 L2; 
      15 [-]: MOVE R2 R0   ; var2 = var0
      16 [-]: GETIMPORT R1 3; var1 = 0x7B998233
      17 [-]: CALL R1 2 2  ; var1 = var1(var2)
L 2:  18 [-]: JUMPIF R1 L3 ; goto L3 if var1
      19 [-]: GETIMPORT R1 11; var1 = _T
      20 [-]: DUPTABLE R2 16; 
      21 [-]: SETTABLEKS R0 R2 K12; var0["AttachEntity"] = var2
      22 [-]: GETIMPORT R3 18; var3 = 0xA421AF95
      23 [-]: LOADK R4 K19 ; var4 = 0.02
      24 [-]: LOADK R5 K20 ; var5 = 0.20000000000000001
      25 [-]: LOADK R6 K21 ; var6 = -0.19
      26 [-]: CALL R3 4 2  ; var3 = var3(var4, var5, var6)
      27 [-]: SETTABLEKS R3 R2 K13; var3["Offset"] = var2
      28 [-]: GETIMPORT R3 23; var3 = 0x00046924
      29 [-]: LOADN R4 90  ; var4 = 90
      30 [-]: LOADN R5 90  ; var5 = 90
      31 [-]: LOADN R6 0   ; var6 = 0
      32 [-]: CALL R3 4 2  ; var3 = var3(var4, var5, var6)
      33 [-]: SETTABLEKS R3 R2 K14; var3["Rotation"] = var2
      34 [-]: GETIMPORT R3 18; var3 = 0xA421AF95
      35 [-]: LOADK R4 K24 ; var4 = 0.108
      36 [-]: LOADK R5 K24 ; var5 = 0.108
      37 [-]: LOADK R6 K24 ; var6 = 0.108
      38 [-]: CALL R3 4 2  ; var3 = var3(var4, var5, var6)
      39 [-]: SETTABLEKS R3 R2 K15; var3["Scale"] = var2
      40 [-]: SETTABLEKS R2 R1 K25; var2["NewWarQuiz_AttachInfo"] = var1
L 3:  41 [-]: GETIMPORT R1 27; var1 = 0x9BA7909F
      42 [-]: GETIMPORT R3 1; var3 = 0x1D683BE5
      43 [-]: NAMECALL R1 R1 K28; var2 = var1; var1 = var1[0xCFBA257F]
      44 [-]: CALL R1 3 2  ; var1 = var1(var2, var3)
      45 [-]: GETIMPORT R2 11; var2 = _T
      46 [-]: NEWCLOSURE R3 P0; 
      47 [-]: CAPTURE UPVAL U1; 
      48 [-]: CAPTURE UPVAL U2; 
      49 [-]: SETTABLEKS R3 R2 K29; var3["QuizDone"] = var2
      50 [-]: LOADK R4 K30 ; var4 = "SetCallBack"
      51 [-]: LOADK R5 K29 ; var5 = "QuizDone"
      52 [-]: NAMECALL R2 R1 K31; var3 = var1; var2 = var1[0xE4162EED]
      53 [-]: CALL R2 4 1  ; var2(var3, var4, var5)
      54 [-]: LOADB R4 1   ; var4 = true
      55 [-]: NAMECALL R2 R1 K32; var3 = var1; var2 = var1[0xBED40E9C]
      56 [-]: CALL R2 3 1  ; var2(var3, var4)
      57 [-]: GETIMPORT R2 11; var2 = _T
      58 [-]: SETTABLEKS R1 R2 K33; var1["NewWar_QuizMovie"] = var2
      59 [-]: RETURN R0 0  ; 


; Name:            
; Defined at line: 325
; #Upvalues:       6
; #Parameters:     0
; Is_vararg:       0
; Max Stack Size:  14

       0 [-]: GETUPVAL R1 0; var1 = upvalues[0]
       1 [-]: GETTABLEKS R0 R1 K0; var0 = var1[0xFC87A231]
       2 [-]: CALL R0 1 1  ; var0()
       3 [-]: GETIMPORT R0 2; var0 = 0x89326C93
       4 [-]: GETIMPORT R2 4; var2 = 0x0469F296
       5 [-]: LOADK R3 K5  ; var3 = "CephTeacherInstructive"
       6 [-]: CALL R2 2 0  ; var2, ... = var2(var3)
       7 [-]: NAMECALL R0 R0 K6; var1 = var0; var0 = var0[0x46A0EBF5]
       8 [-]: CALL R0 0 2  ; var0 = var0(var1, ...)
       9 [-]: FASTCALL1 62 R0 L0; 
      10 [-]: MOVE R2 R0   ; var2 = var0
      11 [-]: GETIMPORT R1 8; var1 = 0x7B998233
      12 [-]: CALL R1 2 2  ; var1 = var1(var2)
L 0:  13 [-]: JUMPIF R1 L1 ; goto L1 if var1
      14 [-]: GETUPVAL R1 1; var1 = upvalues[1]
      15 [-]: LOADN R3 0   ; var3 = 0
      16 [-]: GETIMPORT R4 10; var4 = 0x5C49EF67
      17 [-]: NAMECALL R1 R1 K11; var2 = var1; var1 = var1[0xCDDC3ABB]
      18 [-]: CALL R1 4 1  ; var1(var2, var3, var4)
      19 [-]: LOADK R3 K12 ; var3 = "Execute"
      20 [-]: NAMECALL R1 R0 K13; var2 = var0; var1 = var0[0x8EB2112D]
      21 [-]: CALL R1 3 1  ; var1(var2, var3)
      22 [-]: GETIMPORT R1 15; var1 = 0xCBD666E1
      23 [-]: LOADN R2 4   ; var2 = 4
      24 [-]: CALL R1 2 1  ; var1(var2)
      25 [-]: GETUPVAL R2 2; var2 = upvalues[2]
      26 [-]: GETTABLEKS R1 R2 K16; var1 = var2[0xC474A99E]
      27 [-]: GETIMPORT R2 4; var2 = 0x0469F296
      28 [-]: LOADK R3 K17 ; var3 = "ClassroomLookLeft"
      29 [-]: CALL R2 2 2  ; var2 = var2(var3)
      30 [-]: LOADK R3 K12 ; var3 = "Execute"
      31 [-]: CALL R1 3 1  ; var1(var2, var3)
      32 [-]: GETUPVAL R2 0; var2 = upvalues[0]
      33 [-]: GETTABLEKS R1 R2 K0; var1 = var2[0xFC87A231]
      34 [-]: CALL R1 1 1  ; var1()
L 1:  35 [-]: GETUPVAL R1 1; var1 = upvalues[1]
      36 [-]: LOADN R3 0   ; var3 = 0
      37 [-]: GETIMPORT R4 19; var4 = 0xD4D9DCB9
      38 [-]: NAMECALL R1 R1 K11; var2 = var1; var1 = var1[0xCDDC3ABB]
      39 [-]: CALL R1 4 1  ; var1(var2, var3, var4)
      40 [-]: GETUPVAL R2 0; var2 = upvalues[0]
      41 [-]: GETTABLEKS R1 R2 K20; var1 = var2[0x9742B85B]
      42 [-]: GETIMPORT R2 22; var2 = 0xE91D7466
      43 [-]: GETUPVAL R4 3; var4 = upvalues[3]
      44 [-]: GETTABLEKS R3 R4 K23; var3 = var4["announcementCountdownBegin"]
      45 [-]: CALL R1 3 1  ; var1(var2, var3)
      46 [-]: GETIMPORT R1 15; var1 = 0xCBD666E1
      47 [-]: LOADN R2 4   ; var2 = 4
      48 [-]: CALL R1 2 1  ; var1(var2)
      49 [-]: GETIMPORT R1 2; var1 = 0x89326C93
      50 [-]: GETIMPORT R3 4; var3 = 0x0469F296
      51 [-]: LOADK R4 K24 ; var4 = "VoidJumpLights"
      52 [-]: CALL R3 2 0  ; var3, ... = var3(var4)
      53 [-]: NAMECALL R1 R1 K6; var2 = var1; var1 = var1[0x46A0EBF5]
      54 [-]: CALL R1 0 2  ; var1 = var1(var2, ...)
      55 [-]: FASTCALL1 62 R1 L2; 
      56 [-]: MOVE R3 R1   ; var3 = var1
      57 [-]: GETIMPORT R2 8; var2 = 0x7B998233
      58 [-]: CALL R2 2 2  ; var2 = var2(var3)
L 2:  59 [-]: JUMPIF R2 L3 ; goto L3 if var2
      60 [-]: LOADK R4 K12 ; var4 = "Execute"
      61 [-]: NAMECALL R2 R1 K13; var3 = var1; var2 = var1[0x8EB2112D]
      62 [-]: CALL R2 3 1  ; var2(var3, var4)
L 3:  63 [-]: GETIMPORT R2 2; var2 = 0x89326C93
      64 [-]: GETIMPORT R4 4; var4 = 0x0469F296
      65 [-]: LOADK R5 K25 ; var5 = "VoidJumpEffect"
      66 [-]: CALL R4 2 0  ; var4, ... = var4(var5)
      67 [-]: NAMECALL R2 R2 K6; var3 = var2; var2 = var2[0x46A0EBF5]
      68 [-]: CALL R2 0 2  ; var2 = var2(var3, ...)
      69 [-]: FASTCALL1 62 R2 L4; 
      70 [-]: MOVE R4 R2   ; var4 = var2
      71 [-]: GETIMPORT R3 8; var3 = 0x7B998233
      72 [-]: CALL R3 2 2  ; var3 = var3(var4)
L 4:  73 [-]: JUMPIF R3 L5 ; goto L5 if var3
      74 [-]: LOADK R5 K26 ; var5 = "Enable"
      75 [-]: NAMECALL R3 R2 K13; var4 = var2; var3 = var2[0x8EB2112D]
      76 [-]: CALL R3 3 1  ; var3(var4, var5)
L 5:  77 [-]: GETUPVAL R4 2; var4 = upvalues[2]
      78 [-]: GETTABLEKS R3 R4 K16; var3 = var4[0xC474A99E]
      79 [-]: GETIMPORT R4 4; var4 = 0x0469F296
      80 [-]: LOADK R5 K27 ; var5 = "ClassroomReact"
      81 [-]: CALL R4 2 2  ; var4 = var4(var5)
      82 [-]: LOADK R5 K12 ; var5 = "Execute"
      83 [-]: CALL R3 3 1  ; var3(var4, var5)
      84 [-]: GETIMPORT R3 2; var3 = 0x89326C93
      85 [-]: GETIMPORT R5 4; var5 = 0x0469F296
      86 [-]: LOADK R6 K28 ; var6 = "ZarClassroomPostVolume"
      87 [-]: CALL R5 2 0  ; var5, ... = var5(var6)
      88 [-]: NAMECALL R3 R3 K6; var4 = var3; var3 = var3[0x46A0EBF5]
      89 [-]: CALL R3 0 2  ; var3 = var3(var4, ...)
      90 [-]: GETIMPORT R4 2; var4 = 0x89326C93
      91 [-]: GETIMPORT R6 4; var6 = 0x0469F296
      92 [-]: LOADK R7 K29 ; var7 = "FirstPersonCamera"
      93 [-]: CALL R6 2 0  ; var6, ... = var6(var7)
      94 [-]: NAMECALL R4 R4 K6; var5 = var4; var4 = var4[0x46A0EBF5]
      95 [-]: CALL R4 0 2  ; var4 = var4(var5, ...)
      96 [-]: NAMECALL R5 R3 K30; var6 = var3; var5 = var3[0x1D5C4B69]
      97 [-]: CALL R5 2 2  ; var5 = var5(var6)
      98 [-]: LOADN R6 0   ; var6 = 0
      99 [-]: LOADN R7 0   ; var7 = 0
L 6: 100 [-]: LOADN R8 4   ; var8 = 4
     101 [-]: JUMPIFNOTLT R6 R8 L8; goto L8 if var6 >= var2099278
     102 [-]: GETIMPORT R8 32; var8 = 0x42DCC9F5
     103 [-]: GETIMPORT R10 34; var10 = 0x67652851
     104 [-]: CALL R10 1 2 ; var10 = var10()
     105 [-]: ADD R9 R6 R10; var9 = var6 + var10
     106 [-]: LOADN R10 0  ; var10 = 0
     107 [-]: LOADN R11 4  ; var11 = 4
     108 [-]: CALL R8 4 2  ; var8 = var8(var9, var10, var11)
     109 [-]: MOVE R6 R8   ; var6 = var8
     110 [-]: DIVK R9 R6 K35; var9 = var6 / 4
     111 [-]: FASTCALL2K 21 R9 K36 L7; 
     112 [-]: LOADK R10 K36; var10 = 2
     113 [-]: GETIMPORT R8 39; var8 = 0x5BCED4C4[0xA40531D8]
     114 [-]: CALL R8 3 2  ; var8 = var8(var9, var10)
L 7: 115 [-]: MOVE R7 R8   ; var7 = var8
     116 [-]: MULK R10 R7 K40; var10 = var7 * 10
     117 [-]: MOVE R11 R7  ; var11 = var7
     118 [-]: NAMECALL R8 R4 K41; var9 = var4; var8 = var4[0xF3CEFA26]
     119 [-]: CALL R8 4 1  ; var8(var9, var10, var11)
     120 [-]: MULK R8 R7 K36; var8 = var7 * 2
     121 [-]: SETTABLEKS R8 R5 K42; var8["radialBlurStrength"] = var5
     122 [-]: MULK R8 R7 K40; var8 = var7 * 10
     123 [-]: SETTABLEKS R8 R5 K43; var8["bloom"] = var5
     124 [-]: GETIMPORT R8 15; var8 = 0xCBD666E1
     125 [-]: LOADN R9 0   ; var9 = 0
     126 [-]: CALL R8 2 1  ; var8(var9)
     127 [-]: JUMPBACK L6  ; goto L6
L 8: 128 [-]: GETUPVAL R9 0; var9 = upvalues[0]
     129 [-]: GETTABLEKS R8 R9 K0; var8 = var9[0xFC87A231]
     130 [-]: CALL R8 1 1  ; var8()
     131 [-]: GETUPVAL R9 2; var9 = upvalues[2]
     132 [-]: GETTABLEKS R8 R9 K16; var8 = var9[0xC474A99E]
     133 [-]: GETIMPORT R9 4; var9 = 0x0469F296
     134 [-]: LOADK R10 K44; var10 = "ClassroomReactToIdle"
     135 [-]: CALL R9 2 2  ; var9 = var9(var10)
     136 [-]: LOADK R10 K12; var10 = "Execute"
     137 [-]: CALL R8 3 1  ; var8(var9, var10)
     138 [-]: LOADN R6 0   ; var6 = 0
     139 [-]: GETIMPORT R8 2; var8 = 0x89326C93
     140 [-]: NAMECALL R8 R8 K45; var9 = var8; var8 = var8[0x7C1A0374]
     141 [-]: CALL R8 2 2  ; var8 = var8(var9)
L 9: 142 [-]: LOADN R9 8   ; var9 = 8
     143 [-]: JUMPIFNOTLT R6 R9 L10; goto L10 if var6 >= var2230606
     144 [-]: GETIMPORT R9 34; var9 = 0x67652851
     145 [-]: CALL R9 1 2  ; var9 = var9()
     146 [-]: ADD R6 R6 R9 ; var6 = var6 + var9
     147 [-]: GETIMPORT R9 32; var9 = 0x42DCC9F5
     148 [-]: GETIMPORT R10 47; var10 = 0x9BAFFFE3
     149 [-]: LOADN R11 0  ; var11 = 0
     150 [-]: LOADN R12 1  ; var12 = 1
     151 [-]: DIVK R13 R6 K48; var13 = var6 / 8
     152 [-]: CALL R10 4 2 ; var10 = var10(var11, var12, var13)
     153 [-]: LOADN R11 0  ; var11 = 0
     154 [-]: LOADN R12 1  ; var12 = 1
     155 [-]: CALL R9 4 2  ; var9 = var9(var10, var11, var12)
     156 [-]: MINUS R12 R9 ; 
     157 [-]: NAMECALL R10 R8 K49; var11 = var8; var10 = var8[0xB6DF3E50]
     158 [-]: CALL R10 3 1 ; var10(var11, var12)
     159 [-]: GETIMPORT R10 15; var10 = 0xCBD666E1
     160 [-]: LOADN R11 0  ; var11 = 0
     161 [-]: CALL R10 2 1 ; var10(var11)
     162 [-]: JUMPBACK L9  ; goto L9
L10: 163 [-]: GETUPVAL R9 4; var9 = upvalues[4]
     164 [-]: GETUPVAL R12 5; var12 = upvalues[5]
     165 [-]: GETTABLEKS R11 R12 K50; var11 = var12["COMPLETE"]
     166 [-]: NAMECALL R9 R9 K51; var10 = var9; var9 = var9[0x8ABFF40E]
     167 [-]: CALL R9 3 1  ; var9(var10, var11)
     168 [-]: RETURN R0 0  ; 


; Name:            
; Defined at line: 386
; #Upvalues:       0
; #Parameters:     1
; Is_vararg:       0
; Max Stack Size:  16

       0 [-]: GETIMPORT R1 1; var1 = 0x89326C93
       1 [-]: GETIMPORT R3 3; var3 = 0x0469F296
       2 [-]: LOADK R4 K4  ; var4 = "VoidFX"
       3 [-]: CALL R3 2 0  ; var3, ... = var3(var4)
       4 [-]: NAMECALL R1 R1 K5; var2 = var1; var1 = var1[0xC7FCADA9]
       5 [-]: CALL R1 0 2  ; var1 = var1(var2, ...)
       6 [-]: FASTCALL1 62 R1 L0; 
       7 [-]: MOVE R3 R1   ; var3 = var1
       8 [-]: GETIMPORT R2 7; var2 = 0x7B998233
       9 [-]: CALL R2 2 2  ; var2 = var2(var3)
L 0:  10 [-]: JUMPIF R2 L11; goto L11 if var2
      11 [-]: LENGTH R2 R1 ; var2 = #var1
      12 [-]: LOADN R3 0   ; var3 = 0
      13 [-]: JUMPIFNOTLT R3 R2 L11; goto L11 if var3 >= var197198
      14 [-]: GETIMPORT R2 3; var2 = 0x0469F296
      15 [-]: LOADK R3 K8  ; var3 = "UnlitAtten"
      16 [-]: CALL R2 2 2  ; var2 = var2(var3)
      17 [-]: GETIMPORT R3 10; var3 = 0xCBD666E1
      18 [-]: GETIMPORT R4 12; var4 = 0x74B75231
      19 [-]: CALL R3 2 1  ; var3(var4)
      20 [-]: LENGTH R5 R1 ; var5 = #var1
      21 [-]: LOADN R3 1   ; var3 = 1
      22 [-]: LOADN R4 -1  ; var4 = -1
      23 [-]: FORNPREP R3 L5; nforprep start - [escape at L5] -- var3 = iterator
L 1:  24 [-]: GETTABLE R7 R1 R5; var7 = var1[var5]
      25 [-]: FASTCALL1 62 R7 L2; 
      26 [-]: GETIMPORT R6 7; var6 = 0x7B998233
      27 [-]: CALL R6 2 2  ; var6 = var6(var7)
L 2:  28 [-]: JUMPIFNOT R6 L3; goto L3 if not var6
      29 [-]: GETIMPORT R6 15; var6 = 0x33BDD652[0x9C1F3B5A]
      30 [-]: MOVE R7 R1   ; var7 = var1
      31 [-]: MOVE R8 R5   ; var8 = var5
      32 [-]: CALL R6 3 1  ; var6(var7, var8)
      33 [-]: JUMP L4      ; goto L4
L 3:  34 [-]: GETTABLE R6 R1 R5; var6 = var1[var5]
      35 [-]: LOADB R8 1   ; var8 = true
      36 [-]: LOADB R9 1   ; var9 = true
      37 [-]: NAMECALL R6 R6 K16; var7 = var6; var6 = var6[0x768274D6]
      38 [-]: CALL R6 4 1  ; var6(var7, var8, var9)
      39 [-]: GETTABLE R6 R1 R5; var6 = var1[var5]
      40 [-]: LOADK R8 K17 ; var8 = "Show"
      41 [-]: NAMECALL R6 R6 K18; var7 = var6; var6 = var6[0x8EB2112D]
      42 [-]: CALL R6 3 1  ; var6(var7, var8)
L 4:  43 [-]: FORNLOOP R3 L1; nforloop end - iterate + goto L1
L 5:  44 [-]: LOADN R3 0   ; var3 = 0
L 6:  45 [-]: GETIMPORT R4 20; var4 = 0xE15169D2
      46 [-]: JUMPIFNOTLE R3 R4 L9; goto L9 if var3 > var1442894
      47 [-]: GETIMPORT R4 22; var4 = 0x9BAFFFE3
      48 [-]: LOADN R5 0   ; var5 = 0
      49 [-]: LOADN R6 1   ; var6 = 1
      50 [-]: GETIMPORT R7 24; var7 = 0xA533083A
      51 [-]: GETIMPORT R9 20; var9 = 0xE15169D2
      52 [-]: DIV R8 R3 R9 ; var8 = var3 / var9
      53 [-]: CALL R7 2 0  ; var7, ... = var7(var8)
      54 [-]: CALL R4 0 2  ; var4 = var4(var5, ...)
      55 [-]: LOADN R7 1   ; var7 = 1
      56 [-]: LENGTH R5 R1 ; var5 = #var1
      57 [-]: LOADN R6 1   ; var6 = 1
      58 [-]: FORNPREP R5 L8; nforprep start - [escape at L8] -- var5 = iterator
L 7:  59 [-]: GETTABLE R8 R1 R7; var8 = var1[var7]
      60 [-]: MOVE R10 R2  ; var10 = var2
      61 [-]: MOVE R11 R4  ; var11 = var4
      62 [-]: LOADN R12 0  ; var12 = 0
      63 [-]: LOADN R13 0  ; var13 = 0
      64 [-]: LOADN R14 0  ; var14 = 0
      65 [-]: LOADB R15 1  ; var15 = true
      66 [-]: NAMECALL R8 R8 K25; var9 = var8; var8 = var8[0x986D2AB8]
      67 [-]: CALL R8 8 1  ; var8(var9, var10, var11, var12, var13, var14, var15)
      68 [-]: FORNLOOP R5 L7; nforloop end - iterate + goto L7
L 8:  69 [-]: GETIMPORT R5 10; var5 = 0xCBD666E1
      70 [-]: LOADN R6 0   ; var6 = 0
      71 [-]: CALL R5 2 1  ; var5(var6)
      72 [-]: LOADN R6 3   ; var6 = 3
      73 [-]: GETIMPORT R7 27; var7 = 0xFFF641AF
      74 [-]: CALL R7 1 2  ; var7 = var7()
      75 [-]: MUL R5 R6 R7 ; var5 = var6 * var7
      76 [-]: ADD R3 R3 R5 ; var3 = var3 + var5
      77 [-]: JUMPBACK L6  ; goto L6
L 9:  78 [-]: LENGTH R6 R1 ; var6 = #var1
      79 [-]: LOADN R4 1   ; var4 = 1
      80 [-]: LOADN R5 -1  ; var5 = -1
      81 [-]: FORNPREP R4 L11; nforprep start - [escape at L11] -- var4 = iterator
L10:  82 [-]: GETTABLE R7 R1 R6; var7 = var1[var6]
      83 [-]: MOVE R9 R2   ; var9 = var2
      84 [-]: LOADN R10 1  ; var10 = 1
      85 [-]: LOADN R11 0  ; var11 = 0
      86 [-]: LOADN R12 0  ; var12 = 0
      87 [-]: LOADN R13 0  ; var13 = 0
      88 [-]: LOADB R14 1  ; var14 = true
      89 [-]: NAMECALL R7 R7 K25; var8 = var7; var7 = var7[0x986D2AB8]
      90 [-]: CALL R7 8 1  ; var7(var8, var9, var10, var11, var12, var13, var14)
      91 [-]: FORNLOOP R4 L10; nforloop end - iterate + goto L10
L11:  92 [-]: RETURN R0 0  ; 


; Name:            
; Defined at line: 423
; #Upvalues:       2
; #Parameters:     1
; Is_vararg:       0
; Max Stack Size:  4

       0 [-]: FASTCALL1 62 R0 L0; 
       1 [-]: MOVE R2 R0   ; var2 = var0
       2 [-]: GETIMPORT R1 1; var1 = 0x7B998233
       3 [-]: CALL R1 2 2  ; var1 = var1(var2)
L 0:   4 [-]: JUMPIF R1 L1 ; goto L1 if var1
       5 [-]: NAMECALL R1 R0 K2; var2 = var0; var1 = var0[0x22DA1852]
       6 [-]: CALL R1 2 2  ; var1 = var1(var2)
       7 [-]: GETUPVAL R3 0; var3 = upvalues[0]
       8 [-]: GETTABLEKS R2 R3 K3; var2 = var3["INTRO"]
       9 [-]: JUMPIFNOTEQ R1 R2 L1; goto L1 if var1 ~= var66055
      10 [-]: GETUPVAL R2 1; var2 = upvalues[1]
      11 [-]: GETTABLEKS R1 R2 K4; var1 = var2[0xB5C6BBAF]
      12 [-]: LOADB R2 1   ; var2 = true
      13 [-]: CALL R1 2 1  ; var1(var2)
L 1:  14 [-]: RETURN R0 0  ; 


; Name:            
; Defined at line: 429
; #Upvalues:       0
; #Parameters:     0
; Is_vararg:       0
; Max Stack Size:  1

       0 [-]: LOADB R0 0   ; var0 = false
       1 [-]: RETURN R0 1  ; 


; Name:            
; Defined at line: 446
; #Upvalues:       5
; #Parameters:     0
; Is_vararg:       0
; Max Stack Size:  5

       0 [-]: GETUPVAL R0 0; var0 = upvalues[0]
       1 [-]: CALL R0 1 1  ; var0()
       2 [-]: GETUPVAL R1 1; var1 = upvalues[1]
       3 [-]: GETTABLEKS R0 R1 K0; var0 = var1[0xD720831B]
       4 [-]: CALL R0 1 1  ; var0()
       5 [-]: GETUPVAL R1 1; var1 = upvalues[1]
       6 [-]: GETTABLEKS R0 R1 K1; var0 = var1[0x294D5408]
       7 [-]: LOADB R1 1   ; var1 = true
       8 [-]: LOADB R2 1   ; var2 = true
       9 [-]: LOADB R3 1   ; var3 = true
      10 [-]: CALL R0 4 1  ; var0(var1, var2, var3)
      11 [-]: GETIMPORT R0 3; var0 = _T
      12 [-]: LOADB R1 1   ; var1 = true
      13 [-]: SETTABLEKS R1 R0 K4; var1["MinimalHud"] = var0
      14 [-]: GETIMPORT R0 6; var0 = 0x89326C93
      15 [-]: GETIMPORT R2 8; var2 = 0x0469F296
      16 [-]: LOADK R3 K9  ; var3 = "TNWZarimanOperator"
      17 [-]: CALL R2 2 2  ; var2 = var2(var3)
      18 [-]: NAMECALL R0 R0 K10; var1 = var0; var0 = var0[0x46A0EBF5]
      19 [-]: CALL R0 3 2  ; var0 = var0(var1, var2)
      20 [-]: FASTCALL1 62 R0 L0; 
      21 [-]: MOVE R2 R0   ; var2 = var0
      22 [-]: GETIMPORT R1 12; var1 = 0x7B998233
      23 [-]: CALL R1 2 2  ; var1 = var1(var2)
L 0:  24 [-]: JUMPIF R1 L1 ; goto L1 if var1
      25 [-]: LOADB R3 0   ; var3 = false
      26 [-]: NAMECALL R1 R0 K13; var2 = var0; var1 = var0[0x768274D6]
      27 [-]: CALL R1 3 1  ; var1(var2, var3)
L 1:  28 [-]: GETIMPORT R1 6; var1 = 0x89326C93
      29 [-]: GETIMPORT R3 8; var3 = 0x0469F296
      30 [-]: LOADK R4 K14 ; var4 = "CephTeacherScreen"
      31 [-]: CALL R3 2 0  ; var3, ... = var3(var4)
      32 [-]: NAMECALL R1 R1 K10; var2 = var1; var1 = var1[0x46A0EBF5]
      33 [-]: CALL R1 0 2  ; var1 = var1(var2, ...)
      34 [-]: SETUPVAL R1 2; upvalues[1] = var2
      35 [-]: LOADB R1 0   ; var1 = false
      36 [-]: JUMPIF R1 L2 ; goto L2 if var1
      37 [-]: GETUPVAL R1 3; var1 = upvalues[3]
      38 [-]: GETUPVAL R4 4; var4 = upvalues[4]
      39 [-]: GETTABLEKS R3 R4 K15; var3 = var4["SETUP"]
      40 [-]: NAMECALL R1 R1 K16; var2 = var1; var1 = var1[0x8ABFF40E]
      41 [-]: CALL R1 3 1  ; var1(var2, var3)
L 2:  42 [-]: RETURN R0 0  ; 


; Name:            
; Defined at line: 466
; #Upvalues:       15
; #Parameters:     1
; Is_vararg:       0
; Max Stack Size:  10

       0 [-]: GETIMPORT R2 1; var2 = 0xBE190284
       1 [-]: FASTCALL1 62 R2 L0; 
       2 [-]: GETIMPORT R1 3; var1 = 0x7B998233
       3 [-]: CALL R1 2 2  ; var1 = var1(var2)
L 0:   4 [-]: JUMPIFNOT R1 L1; goto L1 if not var1
       5 [-]: RETURN R0 0  ; 
L 1:   6 [-]: GETUPVAL R1 0; var1 = upvalues[0]
       7 [-]: CALL R1 1 1  ; var1()
       8 [-]: GETUPVAL R1 1; var1 = upvalues[1]
       9 [-]: GETUPVAL R3 2; var3 = upvalues[2]
      10 [-]: GETTABLEKS R2 R3 K4; var2 = var3["SETUP"]
      11 [-]: JUMPIFNOTEQ R1 R2 L2; goto L2 if var1 ~= var196871
      12 [-]: GETUPVAL R1 3; var1 = upvalues[3]
      13 [-]: GETUPVAL R4 2; var4 = upvalues[2]
      14 [-]: GETTABLEKS R3 R4 K5; var3 = var4["CINEMATIC_WAIT"]
      15 [-]: NAMECALL R1 R1 K6; var2 = var1; var1 = var1[0x8ABFF40E]
      16 [-]: CALL R1 3 1  ; var1(var2, var3)
      17 [-]: RETURN R0 0  ; 
L 2:  18 [-]: GETUPVAL R1 1; var1 = upvalues[1]
      19 [-]: GETUPVAL R3 2; var3 = upvalues[2]
      20 [-]: GETTABLEKS R2 R3 K5; var2 = var3["CINEMATIC_WAIT"]
      21 [-]: JUMPIFNOTEQ R1 R2 L4; goto L4 if var1 ~= var262663
      22 [-]: GETUPVAL R2 4; var2 = upvalues[4]
      23 [-]: FASTCALL1 62 R2 L3; 
      24 [-]: GETIMPORT R1 3; var1 = 0x7B998233
      25 [-]: CALL R1 2 2  ; var1 = var1(var2)
L 3:  26 [-]: JUMPIF R1 L12; goto L12 if var1
      27 [-]: GETUPVAL R1 4; var1 = upvalues[4]
      28 [-]: NAMECALL R1 R1 K7; var2 = var1; var1 = var1[0x1C84839C]
      29 [-]: CALL R1 2 2  ; var1 = var1(var2)
      30 [-]: JUMPIF R1 L12; goto L12 if var1
      31 [-]: GETUPVAL R1 5; var1 = upvalues[5]
      32 [-]: GETUPVAL R5 6; var5 = upvalues[6]
      33 [-]: GETTABLEKS R4 R5 K8; var4 = var5["pos"]
      34 [-]: GETUPVAL R5 4; var5 = upvalues[4]
      35 [-]: NAMECALL R5 R5 K9; var6 = var5; var5 = var5[0xD1586535]
      36 [-]: CALL R5 2 2  ; var5 = var5(var6)
      37 [-]: ADD R3 R4 R5 ; var3 = var4 + var5
      38 [-]: GETUPVAL R5 6; var5 = upvalues[6]
      39 [-]: GETTABLEKS R4 R5 K10; var4 = var5["rot"]
      40 [-]: NAMECALL R1 R1 K11; var2 = var1; var1 = var1[0x589EF1C1]
      41 [-]: CALL R1 4 1  ; var1(var2, var3, var4)
      42 [-]: GETUPVAL R1 3; var1 = upvalues[3]
      43 [-]: GETUPVAL R4 2; var4 = upvalues[2]
      44 [-]: GETTABLEKS R3 R4 K12; var3 = var4["LESSON"]
      45 [-]: NAMECALL R1 R1 K6; var2 = var1; var1 = var1[0x8ABFF40E]
      46 [-]: CALL R1 3 1  ; var1(var2, var3)
      47 [-]: RETURN R0 0  ; 
L 4:  48 [-]: GETUPVAL R1 1; var1 = upvalues[1]
      49 [-]: GETUPVAL R3 2; var3 = upvalues[2]
      50 [-]: GETTABLEKS R2 R3 K12; var2 = var3["LESSON"]
      51 [-]: JUMPIFNOTEQ R1 R2 L9; goto L9 if var1 ~= var459271
      52 [-]: GETUPVAL R2 7; var2 = upvalues[7]
      53 [-]: FASTCALL1 62 R2 L5; 
      54 [-]: GETIMPORT R1 3; var1 = 0x7B998233
      55 [-]: CALL R1 2 2  ; var1 = var1(var2)
L 5:  56 [-]: JUMPIF R1 L7 ; goto L7 if var1
      57 [-]: GETUPVAL R1 7; var1 = upvalues[7]
      58 [-]: NAMECALL R1 R1 K7; var2 = var1; var1 = var1[0x1C84839C]
      59 [-]: CALL R1 2 2  ; var1 = var1(var2)
      60 [-]: JUMPIF R1 L7 ; goto L7 if var1
      61 [-]: GETUPVAL R1 5; var1 = upvalues[5]
      62 [-]: GETUPVAL R5 8; var5 = upvalues[8]
      63 [-]: GETTABLEKS R4 R5 K8; var4 = var5["pos"]
      64 [-]: GETUPVAL R5 7; var5 = upvalues[7]
      65 [-]: NAMECALL R5 R5 K9; var6 = var5; var5 = var5[0xD1586535]
      66 [-]: CALL R5 2 2  ; var5 = var5(var6)
      67 [-]: ADD R3 R4 R5 ; var3 = var4 + var5
      68 [-]: GETUPVAL R5 8; var5 = upvalues[8]
      69 [-]: GETTABLEKS R4 R5 K10; var4 = var5["rot"]
      70 [-]: NAMECALL R1 R1 K11; var2 = var1; var1 = var1[0x589EF1C1]
      71 [-]: CALL R1 4 1  ; var1(var2, var3, var4)
      72 [-]: LOADNIL R1   ; var1 = nil
      73 [-]: SETUPVAL R1 7; upvalues[1] = var7
      74 [-]: GETUPVAL R1 9; var1 = upvalues[9]
      75 [-]: NAMECALL R1 R1 K13; var2 = var1; var1 = var1[0x0B4BCFB6]
      76 [-]: CALL R1 2 2  ; var1 = var1(var2)
      77 [-]: NAMECALL R2 R1 K14; var3 = var1; var2 = var1[0xA72AFC7E]
      78 [-]: CALL R2 2 2  ; var2 = var2(var3)
      79 [-]: LOADN R5 0   ; var5 = 0
      80 [-]: NAMECALL R3 R1 K15; var4 = var1; var3 = var1[0x68F07B6A]
      81 [-]: CALL R3 3 1  ; var3(var4, var5)
      82 [-]: GETUPVAL R5 5; var5 = upvalues[5]
      83 [-]: LOADN R6 0   ; var6 = 0
      84 [-]: NAMECALL R3 R1 K16; var4 = var1; var3 = var1[0x14C7F7DD]
      85 [-]: CALL R3 4 1  ; var3(var4, var5, var6)
      86 [-]: MOVE R5 R2   ; var5 = var2
      87 [-]: NAMECALL R3 R1 K15; var4 = var1; var3 = var1[0x68F07B6A]
      88 [-]: CALL R3 3 1  ; var3(var4, var5)
      89 [-]: GETUPVAL R3 9; var3 = upvalues[9]
      90 [-]: GETIMPORT R5 18; var5 = 0xAB0D0E73
      91 [-]: LOADB R6 0   ; var6 = false
      92 [-]: LOADN R7 3   ; var7 = 3
      93 [-]: LOADN R8 2   ; var8 = 2
      94 [-]: LOADB R9 1   ; var9 = true
      95 [-]: NAMECALL R3 R3 K19; var4 = var3; var3 = var3[0x5D985C7E]
      96 [-]: CALL R3 7 1  ; var3(var4, var5, var6, var7, var8, var9)
      97 [-]: GETIMPORT R4 22; var4 = _T["NewWar_QuizMovie"]
      98 [-]: FASTCALL1 62 R4 L6; 
      99 [-]: GETIMPORT R3 3; var3 = 0x7B998233
     100 [-]: CALL R3 2 2  ; var3 = var3(var4)
L 6: 101 [-]: JUMPIF R3 L12; goto L12 if var3
     102 [-]: GETIMPORT R3 22; var3 = _T["NewWar_QuizMovie"]
     103 [-]: LOADB R5 0   ; var5 = false
     104 [-]: NAMECALL R3 R3 K23; var4 = var3; var3 = var3[0xBED40E9C]
     105 [-]: CALL R3 3 1  ; var3(var4, var5)
     106 [-]: GETIMPORT R3 22; var3 = _T["NewWar_QuizMovie"]
     107 [-]: LOADK R5 K24 ; var5 = "OnInputReceived"
     108 [-]: LOADK R6 K25 ; var6 = ""
     109 [-]: NAMECALL R3 R3 K26; var4 = var3; var3 = var3[0xE4162EED]
     110 [-]: CALL R3 4 1  ; var3(var4, var5, var6)
     111 [-]: GETIMPORT R3 27; var3 = _T
     112 [-]: LOADNIL R4   ; var4 = nil
     113 [-]: SETTABLEKS R4 R3 K21; var4["NewWar_QuizMovie"] = var3
     114 [-]: RETURN R0 0  ; 
L 7: 115 [-]: GETUPVAL R1 10; var1 = upvalues[10]
     116 [-]: JUMPIFNOT R1 L12; goto L12 if not var1
     117 [-]: GETUPVAL R1 11; var1 = upvalues[11]
     118 [-]: JUMPIF R1 L12; goto L12 if var1
     119 [-]: GETIMPORT R1 29; var1 = 0x89326C93
     120 [-]: GETUPVAL R4 12; var4 = upvalues[12]
     121 [-]: GETTABLEKS R3 R4 K30; var3 = var4["TABLET"]
     122 [-]: NAMECALL R1 R1 K31; var2 = var1; var1 = var1[0x46A0EBF5]
     123 [-]: CALL R1 3 2  ; var1 = var1(var2, var3)
     124 [-]: SETUPVAL R1 7; upvalues[1] = var7
     125 [-]: GETUPVAL R2 7; var2 = upvalues[7]
     126 [-]: FASTCALL1 62 R2 L8; 
     127 [-]: GETIMPORT R1 3; var1 = 0x7B998233
     128 [-]: CALL R1 2 2  ; var1 = var1(var2)
L 8: 129 [-]: JUMPIF R1 L12; goto L12 if var1
     130 [-]: GETUPVAL R1 7; var1 = upvalues[7]
     131 [-]: LOADK R3 K32 ; var3 = "StartPlaying"
     132 [-]: NAMECALL R1 R1 K33; var2 = var1; var1 = var1[0x8EB2112D]
     133 [-]: CALL R1 3 1  ; var1(var2, var3)
     134 [-]: GETUPVAL R1 9; var1 = upvalues[9]
     135 [-]: LOADB R3 1   ; var3 = true
     136 [-]: NAMECALL R1 R1 K34; var2 = var1; var1 = var1[0x768274D6]
     137 [-]: CALL R1 3 1  ; var1(var2, var3)
     138 [-]: GETUPVAL R1 5; var1 = upvalues[5]
     139 [-]: LOADB R3 0   ; var3 = false
     140 [-]: NAMECALL R1 R1 K35; var2 = var1; var1 = var1[0xE7C54CFD]
     141 [-]: CALL R1 3 1  ; var1(var2, var3)
     142 [-]: GETUPVAL R1 5; var1 = upvalues[5]
     143 [-]: GETIMPORT R3 37; var3 = ZERO_ROTATION
     144 [-]: NAMECALL R1 R1 K38; var2 = var1; var1 = var1[0xD5F884A6]
     145 [-]: CALL R1 3 1  ; var1(var2, var3)
     146 [-]: GETIMPORT R1 40; var1 = 0xCBD666E1
     147 [-]: LOADK R2 K41 ; var2 = 3.5
     148 [-]: CALL R1 2 1  ; var1(var2)
     149 [-]: GETUPVAL R1 13; var1 = upvalues[13]
     150 [-]: CALL R1 1 1  ; var1()
     151 [-]: RETURN R0 0  ; 
L 9: 152 [-]: GETUPVAL R1 1; var1 = upvalues[1]
     153 [-]: GETUPVAL R3 2; var3 = upvalues[2]
     154 [-]: GETTABLEKS R2 R3 K42; var2 = var3["ANNOUNCEMENT"]
     155 [-]: JUMPIFNOTEQ R1 R2 L11; goto L11 if var1 ~= var918023
     156 [-]: GETUPVAL R2 14; var2 = upvalues[14]
     157 [-]: FASTCALL1 62 R2 L10; 
     158 [-]: GETIMPORT R1 3; var1 = 0x7B998233
     159 [-]: CALL R1 2 2  ; var1 = var1(var2)
L10: 160 [-]: JUMPIF R1 L12; goto L12 if var1
     161 [-]: GETUPVAL R1 14; var1 = upvalues[14]
     162 [-]: NAMECALL R1 R1 K7; var2 = var1; var1 = var1[0x1C84839C]
     163 [-]: CALL R1 2 2  ; var1 = var1(var2)
     164 [-]: JUMPIF R1 L12; goto L12 if var1
     165 [-]: LOADNIL R1   ; var1 = nil
     166 [-]: SETUPVAL R1 14; upvalues[1] = var14
     167 [-]: GETUPVAL R1 9; var1 = upvalues[9]
     168 [-]: LOADB R3 0   ; var3 = false
     169 [-]: LOADB R4 1   ; var4 = true
     170 [-]: NAMECALL R1 R1 K34; var2 = var1; var1 = var1[0x768274D6]
     171 [-]: CALL R1 4 1  ; var1(var2, var3, var4)
     172 [-]: RETURN R0 0  ; 
L11: 173 [-]: GETUPVAL R1 1; var1 = upvalues[1]
     174 [-]: GETUPVAL R3 2; var3 = upvalues[2]
     175 [-]: GETTABLEKS R2 R3 K43; var2 = var3["COMPLETE"]
     176 [-]: JUMPIFNOTEQ R1 R2 L12; goto L12 if var1 ~= var65581
L12: 177 [-]: RETURN R0 0  ; 


; Name:            
; Defined at line: 523
; #Upvalues:       16
; #Parameters:     1
; Is_vararg:       0
; Max Stack Size:  11

       0 [-]: GETIMPORT R1 1; var1 = 0x3D106989
       1 [-]: LOADK R3 K2  ; var3 = "New Stage: "
       2 [-]: MOVE R4 R0   ; var4 = var0
       3 [-]: LOADK R5 K3  ; var5 = " "
       4 [-]: GETUPVAL R9 0; var9 = upvalues[0]
       5 [-]: GETTABLE R8 R9 R0; var8 = var9[var0]
       6 [-]: FASTCALL1 62 R8 L0; 
       7 [-]: GETIMPORT R7 5; var7 = 0x7B998233
       8 [-]: CALL R7 2 2  ; var7 = var7(var8)
L 0:   9 [-]: JUMPIF R7 L2 ; goto L2 if var7
      10 [-]: GETUPVAL R10 0; var10 = upvalues[0]
      11 [-]: GETTABLE R9 R10 R0; var9 = var10[var0]
      12 [-]: GETTABLEKS R8 R9 K6; var8 = var9["name"]
      13 [-]: FASTCALL1 62 R8 L1; 
      14 [-]: GETIMPORT R7 5; var7 = 0x7B998233
      15 [-]: CALL R7 2 2  ; var7 = var7(var8)
L 1:  16 [-]: JUMPIF R7 L2 ; goto L2 if var7
      17 [-]: GETUPVAL R8 0; var8 = upvalues[0]
      18 [-]: GETTABLE R7 R8 R0; var7 = var8[var0]
      19 [-]: GETTABLEKS R6 R7 K6; var6 = var7["name"]
      20 [-]: JUMPIF R6 L3 ; goto L3 if var6
L 2:  21 [-]: LOADK R6 K7  ; var6 = ""
L 3:  22 [-]: CONCAT R2 R3 R6; var2 = var3 .. var6
      23 [-]: CALL R1 2 1  ; var1(var2)
      24 [-]: SUBK R1 R0 K8; var1 = var0 - 1
      25 [-]: GETUPVAL R4 0; var4 = upvalues[0]
      26 [-]: GETTABLE R3 R4 R1; var3 = var4[var1]
      27 [-]: FASTCALL1 62 R3 L4; 
      28 [-]: GETIMPORT R2 5; var2 = 0x7B998233
      29 [-]: CALL R2 2 2  ; var2 = var2(var3)
L 4:  30 [-]: JUMPIFNOT R2 L5; goto L5 if not var2
      31 [-]: JUMP L7      ; goto L7
L 5:  32 [-]: LOADN R2 0   ; var2 = 0
      33 [-]: JUMPIFNOTLT R2 R1 L7; goto L7 if var2 >= var1287
      34 [-]: GETUPVAL R5 0; var5 = upvalues[0]
      35 [-]: GETTABLE R4 R5 R1; var4 = var5[var1]
      36 [-]: GETTABLEKS R3 R4 K9; var3 = var4["endF"]
      37 [-]: FASTCALL1 62 R3 L6; 
      38 [-]: GETIMPORT R2 5; var2 = 0x7B998233
      39 [-]: CALL R2 2 2  ; var2 = var2(var3)
L 6:  40 [-]: JUMPIF R2 L7 ; goto L7 if var2
      41 [-]: GETUPVAL R4 0; var4 = upvalues[0]
      42 [-]: GETTABLE R3 R4 R1; var3 = var4[var1]
      43 [-]: GETTABLEKS R2 R3 K9; var2 = var3["endF"]
      44 [-]: LOADK R4 K10 ; var4 = "TriggerPort"
      45 [-]: NAMECALL R2 R2 K11; var3 = var2; var2 = var2[0x8EB2112D]
      46 [-]: CALL R2 3 1  ; var2(var3, var4)
L 7:  47 [-]: GETUPVAL R2 1; var2 = upvalues[1]
      48 [-]: GETTABLEKS R1 R2 K12; var1 = var2["SETUP"]
      49 [-]: JUMPIFNOTEQ R0 R1 L11; goto L11 if var0 ~= var131591
      50 [-]: GETUPVAL R2 2; var2 = upvalues[2]
      51 [-]: GETTABLEKS R1 R2 K13; var1 = var2[0x12A41A40]
      52 [-]: LOADB R2 1   ; var2 = true
      53 [-]: LOADK R3 K14 ; var3 = 0.5
      54 [-]: CALL R1 3 1  ; var1(var2, var3)
      55 [-]: GETIMPORT R1 16; var1 = 0x89326C93
      56 [-]: GETUPVAL R4 4; var4 = upvalues[4]
      57 [-]: GETTABLEKS R3 R4 K17; var3 = var4["INTRO"]
      58 [-]: NAMECALL R1 R1 K18; var2 = var1; var1 = var1[0x46A0EBF5]
      59 [-]: CALL R1 3 2  ; var1 = var1(var2, var3)
      60 [-]: SETUPVAL R1 3; upvalues[1] = var3
      61 [-]: GETUPVAL R2 3; var2 = upvalues[3]
      62 [-]: FASTCALL1 62 R2 L8; 
      63 [-]: GETIMPORT R1 5; var1 = 0x7B998233
      64 [-]: CALL R1 2 2  ; var1 = var1(var2)
L 8:  65 [-]: JUMPIFNOT R1 L9; goto L9 if not var1
      66 [-]: GETIMPORT R1 1; var1 = 0x3D106989
      67 [-]: LOADK R2 K19 ; var2 = "Intro cinematic could not be found!"
      68 [-]: CALL R1 2 1  ; var1(var2)
      69 [-]: JUMP L10     ; goto L10
L 9:  70 [-]: GETIMPORT R1 21; var1 = 0x11A19C5E
      71 [-]: GETUPVAL R2 3; var2 = upvalues[3]
      72 [-]: LOADK R3 K22 ; var3 = "OnSkipped"
      73 [-]: CALL R1 3 1  ; var1(var2, var3)
L10:  74 [-]: GETUPVAL R1 5; var1 = upvalues[5]
      75 [-]: CALL R1 1 1  ; var1()
      76 [-]: GETIMPORT R1 16; var1 = 0x89326C93
      77 [-]: GETIMPORT R3 24; var3 = 0x0469F296
      78 [-]: LOADK R4 K25 ; var4 = "FirstPersonCamera"
      79 [-]: CALL R3 2 0  ; var3, ... = var3(var4)
      80 [-]: NAMECALL R1 R1 K18; var2 = var1; var1 = var1[0x46A0EBF5]
      81 [-]: CALL R1 0 2  ; var1 = var1(var2, ...)
      82 [-]: SETUPVAL R1 6; upvalues[1] = var6
      83 [-]: GETUPVAL R2 7; var2 = upvalues[7]
      84 [-]: GETTABLEKS R1 R2 K26; var1 = var2[0x659D451F]
      85 [-]: GETIMPORT R2 28; var2 = 0x39751C29
      86 [-]: CALL R1 2 1  ; var1(var2)
      87 [-]: GETUPVAL R2 8; var2 = upvalues[8]
      88 [-]: GETTABLEKS R1 R2 K29; var1 = var2[0x9742B85B]
      89 [-]: GETIMPORT R2 31; var2 = 0xE91D7466
      90 [-]: GETUPVAL R4 9; var4 = upvalues[9]
      91 [-]: GETTABLEKS R3 R4 K32; var3 = var4["ballasKillDevil"]
      92 [-]: CALL R1 3 1  ; var1(var2, var3)
      93 [-]: GETUPVAL R2 8; var2 = upvalues[8]
      94 [-]: GETTABLEKS R1 R2 K33; var1 = var2[0xFC87A231]
      95 [-]: CALL R1 1 1  ; var1()
      96 [-]: JUMP L23     ; goto L23
L11:  97 [-]: GETUPVAL R2 1; var2 = upvalues[1]
      98 [-]: GETTABLEKS R1 R2 K34; var1 = var2["CINEMATIC_WAIT"]
      99 [-]: JUMPIFNOTEQ R0 R1 L12; goto L12 if var0 ~= var459271
     100 [-]: GETUPVAL R2 7; var2 = upvalues[7]
     101 [-]: GETTABLEKS R1 R2 K26; var1 = var2[0x659D451F]
     102 [-]: GETIMPORT R2 36; var2 = 0xE5895942
     103 [-]: CALL R1 2 1  ; var1(var2)
     104 [-]: GETUPVAL R2 7; var2 = upvalues[7]
     105 [-]: GETTABLEKS R1 R2 K26; var1 = var2[0x659D451F]
     106 [-]: GETIMPORT R2 38; var2 = 0xA13DD623
     107 [-]: CALL R1 2 1  ; var1(var2)
     108 [-]: GETUPVAL R2 2; var2 = upvalues[2]
     109 [-]: GETTABLEKS R1 R2 K13; var1 = var2[0x12A41A40]
     110 [-]: LOADB R2 0   ; var2 = false
     111 [-]: LOADN R3 1   ; var3 = 1
     112 [-]: CALL R1 3 1  ; var1(var2, var3)
     113 [-]: JUMP L23     ; goto L23
L12: 114 [-]: GETUPVAL R2 1; var2 = upvalues[1]
     115 [-]: GETTABLEKS R1 R2 K39; var1 = var2["LESSON"]
     116 [-]: JUMPIFNOTEQ R0 R1 L17; goto L17 if var0 ~= var655623
     117 [-]: GETUPVAL R1 10; var1 = upvalues[10]
     118 [-]: LOADB R3 0   ; var3 = false
     119 [-]: NAMECALL R1 R1 K40; var2 = var1; var1 = var1[0x768274D6]
     120 [-]: CALL R1 3 1  ; var1(var2, var3)
     121 [-]: GETUPVAL R1 10; var1 = upvalues[10]
     122 [-]: NAMECALL R1 R1 K41; var2 = var1; var1 = var1[0x0B4BCFB6]
     123 [-]: CALL R1 2 2  ; var1 = var1(var2)
     124 [-]: NAMECALL R2 R1 K42; var3 = var1; var2 = var1[0xA72AFC7E]
     125 [-]: CALL R2 2 2  ; var2 = var2(var3)
     126 [-]: LOADN R5 0   ; var5 = 0
     127 [-]: NAMECALL R3 R1 K43; var4 = var1; var3 = var1[0x68F07B6A]
     128 [-]: CALL R3 3 1  ; var3(var4, var5)
     129 [-]: GETUPVAL R5 6; var5 = upvalues[6]
     130 [-]: LOADN R6 0   ; var6 = 0
     131 [-]: NAMECALL R3 R1 K44; var4 = var1; var3 = var1[0x14C7F7DD]
     132 [-]: CALL R3 4 1  ; var3(var4, var5, var6)
     133 [-]: MOVE R5 R2   ; var5 = var2
     134 [-]: NAMECALL R3 R1 K43; var4 = var1; var3 = var1[0x68F07B6A]
     135 [-]: CALL R3 3 1  ; var3(var4, var5)
     136 [-]: GETIMPORT R3 16; var3 = 0x89326C93
     137 [-]: GETIMPORT R5 24; var5 = 0x0469F296
     138 [-]: LOADK R6 K45 ; var6 = "CephTeacherIntroLesson"
     139 [-]: CALL R5 2 0  ; var5, ... = var5(var6)
     140 [-]: NAMECALL R3 R3 K18; var4 = var3; var3 = var3[0x46A0EBF5]
     141 [-]: CALL R3 0 2  ; var3 = var3(var4, ...)
     142 [-]: FASTCALL1 62 R3 L13; 
     143 [-]: MOVE R5 R3   ; var5 = var3
     144 [-]: GETIMPORT R4 5; var4 = 0x7B998233
     145 [-]: CALL R4 2 2  ; var4 = var4(var5)
L13: 146 [-]: JUMPIF R4 L14; goto L14 if var4
     147 [-]: GETUPVAL R4 11; var4 = upvalues[11]
     148 [-]: LOADN R6 0   ; var6 = 0
     149 [-]: GETIMPORT R7 47; var7 = 0x5C49EF67
     150 [-]: NAMECALL R4 R4 K48; var5 = var4; var4 = var4[0xCDDC3ABB]
     151 [-]: CALL R4 4 1  ; var4(var5, var6, var7)
     152 [-]: LOADK R6 K49 ; var6 = "Execute"
     153 [-]: NAMECALL R4 R3 K11; var5 = var3; var4 = var3[0x8EB2112D]
     154 [-]: CALL R4 3 1  ; var4(var5, var6)
L14: 155 [-]: GETUPVAL R5 8; var5 = upvalues[8]
     156 [-]: GETTABLEKS R4 R5 K33; var4 = var5[0xFC87A231]
     157 [-]: CALL R4 1 1  ; var4()
     158 [-]: GETIMPORT R4 16; var4 = 0x89326C93
     159 [-]: GETIMPORT R6 24; var6 = 0x0469F296
     160 [-]: LOADK R7 K50 ; var7 = "BlackboardCamera"
     161 [-]: CALL R6 2 0  ; var6, ... = var6(var7)
     162 [-]: NAMECALL R4 R4 K18; var5 = var4; var4 = var4[0x46A0EBF5]
     163 [-]: CALL R4 0 2  ; var4 = var4(var5, ...)
     164 [-]: GETUPVAL R7 6; var7 = upvalues[6]
     165 [-]: NAMECALL R7 R7 K51; var8 = var7; var7 = var7[0xD1586535]
     166 [-]: CALL R7 2 2  ; var7 = var7(var8)
     167 [-]: NAMECALL R8 R4 K52; var9 = var4; var8 = var4[0xCB3851B8]
     168 [-]: CALL R8 2 0  ; var8, ... = var8(var9)
     169 [-]: NAMECALL R5 R4 K53; var6 = var4; var5 = var4[0x589EF1C1]
     170 [-]: CALL R5 0 1  ; var5(var6, ...)
     171 [-]: GETIMPORT R5 55; var5 = 0x00046924
     172 [-]: LOADK R6 K56 ; var6 = 16.978000000000002
     173 [-]: LOADK R7 K57 ; var7 = -6.0999999999999996
     174 [-]: LOADN R8 0   ; var8 = 0
     175 [-]: CALL R5 4 2  ; var5 = var5(var6, var7, var8)
     176 [-]: FASTCALL1 62 R4 L15; 
     177 [-]: MOVE R7 R4   ; var7 = var4
     178 [-]: GETIMPORT R6 5; var6 = 0x7B998233
     179 [-]: CALL R6 2 2  ; var6 = var6(var7)
L15: 180 [-]: JUMPIF R6 L16; goto L16 if var6
     181 [-]: MOVE R8 R4   ; var8 = var4
     182 [-]: NAMECALL R6 R1 K44; var7 = var1; var6 = var1[0x14C7F7DD]
     183 [-]: CALL R6 3 1  ; var6(var7, var8)
     184 [-]: NAMECALL R8 R4 K51; var9 = var4; var8 = var4[0xD1586535]
     185 [-]: CALL R8 2 2  ; var8 = var8(var9)
     186 [-]: MOVE R9 R5   ; var9 = var5
     187 [-]: NAMECALL R6 R4 K53; var7 = var4; var6 = var4[0x589EF1C1]
     188 [-]: CALL R6 4 1  ; var6(var7, var8, var9)
L16: 189 [-]: GETIMPORT R6 59; var6 = 0xCBD666E1
     190 [-]: LOADN R7 1   ; var7 = 1
     191 [-]: CALL R6 2 1  ; var6(var7)
     192 [-]: NAMECALL R8 R4 K51; var9 = var4; var8 = var4[0xD1586535]
     193 [-]: CALL R8 2 2  ; var8 = var8(var9)
     194 [-]: GETIMPORT R9 61; var9 = ZERO_ROTATION
     195 [-]: NAMECALL R6 R4 K53; var7 = var4; var6 = var4[0x589EF1C1]
     196 [-]: CALL R6 4 1  ; var6(var7, var8, var9)
     197 [-]: MOVE R8 R5   ; var8 = var5
     198 [-]: NAMECALL R6 R4 K62; var7 = var4; var6 = var4[0xD5F884A6]
     199 [-]: CALL R6 3 1  ; var6(var7, var8)
     200 [-]: GETUPVAL R6 12; var6 = upvalues[12]
     201 [-]: CALL R6 1 1  ; var6()
     202 [-]: JUMP L23     ; goto L23
L17: 203 [-]: GETUPVAL R2 1; var2 = upvalues[1]
     204 [-]: GETTABLEKS R1 R2 K63; var1 = var2["ANNOUNCEMENT"]
     205 [-]: JUMPIFNOTEQ R0 R1 L22; goto L22 if var0 ~= var1048910
     206 [-]: GETIMPORT R1 16; var1 = 0x89326C93
     207 [-]: GETIMPORT R3 24; var3 = 0x0469F296
     208 [-]: LOADK R4 K64 ; var4 = "StudentExcited"
     209 [-]: CALL R3 2 0  ; var3, ... = var3(var4)
     210 [-]: NAMECALL R1 R1 K18; var2 = var1; var1 = var1[0x46A0EBF5]
     211 [-]: CALL R1 0 2  ; var1 = var1(var2, ...)
     212 [-]: FASTCALL1 62 R1 L18; 
     213 [-]: MOVE R3 R1   ; var3 = var1
     214 [-]: GETIMPORT R2 5; var2 = 0x7B998233
     215 [-]: CALL R2 2 2  ; var2 = var2(var3)
L18: 216 [-]: JUMPIF R2 L19; goto L19 if var2
     217 [-]: NAMECALL R2 R1 K65; var3 = var1; var2 = var1[0x383D2E7D]
     218 [-]: CALL R2 2 1  ; var2(var3)
L19: 219 [-]: GETUPVAL R2 11; var2 = upvalues[11]
     220 [-]: LOADN R4 0   ; var4 = 0
     221 [-]: GETIMPORT R5 67; var5 = 0xD4D9DCB9
     222 [-]: NAMECALL R2 R2 K48; var3 = var2; var2 = var2[0xCDDC3ABB]
     223 [-]: CALL R2 4 1  ; var2(var3, var4, var5)
     224 [-]: GETUPVAL R3 8; var3 = upvalues[8]
     225 [-]: GETTABLEKS R2 R3 K29; var2 = var3[0x9742B85B]
     226 [-]: GETIMPORT R3 31; var3 = 0xE91D7466
     227 [-]: GETUPVAL R5 9; var5 = upvalues[9]
     228 [-]: GETTABLEKS R4 R5 K68; var4 = var5["annoucementStart"]
     229 [-]: CALL R2 3 1  ; var2(var3, var4)
     230 [-]: GETIMPORT R2 16; var2 = 0x89326C93
     231 [-]: GETUPVAL R5 4; var5 = upvalues[4]
     232 [-]: GETTABLEKS R4 R5 K69; var4 = var5["LOOK_UP"]
     233 [-]: NAMECALL R2 R2 K18; var3 = var2; var2 = var2[0x46A0EBF5]
     234 [-]: CALL R2 3 2  ; var2 = var2(var3, var4)
     235 [-]: SETUPVAL R2 13; upvalues[2] = var13
     236 [-]: GETUPVAL R3 13; var3 = upvalues[13]
     237 [-]: FASTCALL1 62 R3 L20; 
     238 [-]: GETIMPORT R2 5; var2 = 0x7B998233
     239 [-]: CALL R2 2 2  ; var2 = var2(var3)
L20: 240 [-]: JUMPIF R2 L21; goto L21 if var2
     241 [-]: GETUPVAL R2 13; var2 = upvalues[13]
     242 [-]: LOADK R4 K70 ; var4 = "StartPlaying"
     243 [-]: NAMECALL R2 R2 K11; var3 = var2; var2 = var2[0x8EB2112D]
     244 [-]: CALL R2 3 1  ; var2(var3, var4)
L21: 245 [-]: GETUPVAL R2 6; var2 = upvalues[6]
     246 [-]: LOADB R4 1   ; var4 = true
     247 [-]: NAMECALL R2 R2 K71; var3 = var2; var2 = var2[0xE7C54CFD]
     248 [-]: CALL R2 3 1  ; var2(var3, var4)
     249 [-]: GETUPVAL R2 6; var2 = upvalues[6]
     250 [-]: GETIMPORT R4 61; var4 = ZERO_ROTATION
     251 [-]: NAMECALL R2 R2 K62; var3 = var2; var2 = var2[0xD5F884A6]
     252 [-]: CALL R2 3 1  ; var2(var3, var4)
     253 [-]: GETUPVAL R2 6; var2 = upvalues[6]
     254 [-]: GETUPVAL R6 14; var6 = upvalues[14]
     255 [-]: GETTABLEKS R5 R6 K72; var5 = var6["pos"]
     256 [-]: GETUPVAL R6 3; var6 = upvalues[3]
     257 [-]: NAMECALL R6 R6 K51; var7 = var6; var6 = var6[0xD1586535]
     258 [-]: CALL R6 2 2  ; var6 = var6(var7)
     259 [-]: ADD R4 R5 R6 ; var4 = var5 + var6
     260 [-]: GETUPVAL R6 14; var6 = upvalues[14]
     261 [-]: GETTABLEKS R5 R6 K73; var5 = var6["rot"]
     262 [-]: NAMECALL R2 R2 K53; var3 = var2; var2 = var2[0x589EF1C1]
     263 [-]: CALL R2 4 1  ; var2(var3, var4, var5)
     264 [-]: GETUPVAL R2 6; var2 = upvalues[6]
     265 [-]: GETUPVAL R5 14; var5 = upvalues[14]
     266 [-]: GETTABLEKS R4 R5 K74; var4 = var5["fov"]
     267 [-]: NAMECALL R2 R2 K75; var3 = var2; var2 = var2[0xACEA6D71]
     268 [-]: CALL R2 3 1  ; var2(var3, var4)
     269 [-]: GETUPVAL R2 10; var2 = upvalues[10]
     270 [-]: GETIMPORT R4 24; var4 = 0x0469F296
     271 [-]: LOADK R5 K76 ; var5 = "AnnouncementFlow"
     272 [-]: CALL R4 2 2  ; var4 = var4(var5)
     273 [-]: LOADB R5 0   ; var5 = false
     274 [-]: NAMECALL R2 R2 K77; var3 = var2; var2 = var2[0xD5F7912B]
     275 [-]: CALL R2 4 1  ; var2(var3, var4, var5)
     276 [-]: JUMP L23     ; goto L23
L22: 277 [-]: GETUPVAL R2 1; var2 = upvalues[1]
     278 [-]: GETTABLEKS R1 R2 K78; var1 = var2["COMPLETE"]
     279 [-]: JUMPIFNOTEQ R0 R1 L23; goto L23 if var0 ~= var131591
     280 [-]: GETUPVAL R2 2; var2 = upvalues[2]
     281 [-]: GETTABLEKS R1 R2 K79; var1 = var2[0x7D717F70]
     282 [-]: GETUPVAL R2 15; var2 = upvalues[15]
     283 [-]: GETIMPORT R3 81; var3 = 0x7DE83207
     284 [-]: CALL R1 3 1  ; var1(var2, var3)
     285 [-]: GETUPVAL R2 2; var2 = upvalues[2]
     286 [-]: GETTABLEKS R1 R2 K82; var1 = var2[0x004C3021]
     287 [-]: CALL R1 1 1  ; var1()
     288 [-]: GETIMPORT R1 84; var1 = 0xBE190284
     289 [-]: LOADB R3 1   ; var3 = true
     290 [-]: NAMECALL R1 R1 K85; var2 = var1; var1 = var1[0xC7C8DAD6]
     291 [-]: CALL R1 3 1  ; var1(var2, var3)
     292 [-]: GETIMPORT R1 88; var1 = 0x34291F5C[0x8EE24660]
     293 [-]: LOADB R2 1   ; var2 = true
     294 [-]: CALL R1 2 1  ; var1(var2)
L23: 295 [-]: GETUPVAL R3 0; var3 = upvalues[0]
     296 [-]: GETTABLE R2 R3 R0; var2 = var3[var0]
     297 [-]: FASTCALL1 62 R2 L24; 
     298 [-]: GETIMPORT R1 5; var1 = 0x7B998233
     299 [-]: CALL R1 2 2  ; var1 = var1(var2)
L24: 300 [-]: JUMPIFNOT R1 L25; goto L25 if not var1
     301 [-]: RETURN R0 0  ; 
L25: 302 [-]: LOADN R1 0   ; var1 = 0
     303 [-]: JUMPIFNOTLT R1 R0 L27; goto L27 if var1 >= var1031
     304 [-]: GETUPVAL R4 0; var4 = upvalues[0]
     305 [-]: GETTABLE R3 R4 R0; var3 = var4[var0]
     306 [-]: GETTABLEKS R2 R3 K89; var2 = var3["startF"]
     307 [-]: FASTCALL1 62 R2 L26; 
     308 [-]: GETIMPORT R1 5; var1 = 0x7B998233
     309 [-]: CALL R1 2 2  ; var1 = var1(var2)
L26: 310 [-]: JUMPIF R1 L27; goto L27 if var1
     311 [-]: GETUPVAL R3 0; var3 = upvalues[0]
     312 [-]: GETTABLE R2 R3 R0; var2 = var3[var0]
     313 [-]: GETTABLEKS R1 R2 K89; var1 = var2["startF"]
     314 [-]: LOADK R3 K10 ; var3 = "TriggerPort"
     315 [-]: NAMECALL R1 R1 K11; var2 = var1; var1 = var1[0x8EB2112D]
     316 [-]: CALL R1 3 1  ; var1(var2, var3)
L27: 317 [-]: RETURN R0 0  ; 


; Name:            
; Defined at line: 619
; #Upvalues:       6
; #Parameters:     1
; Is_vararg:       0
; Max Stack Size:  4

       0 [-]: GETUPVAL R2 1; var2 = upvalues[1]
       1 [-]: GETTABLEKS R1 R2 K0; var1 = var2[0xC9013731]
       2 [-]: GETUPVAL R2 2; var2 = upvalues[2]
       3 [-]: CALL R1 2 2  ; var1 = var1(var2)
       4 [-]: SETUPVAL R1 0; upvalues[1] = var0
       5 [-]: GETUPVAL R1 3; var1 = upvalues[3]
       6 [-]: CALL R1 1 1  ; var1()
L 0:   7 [-]: GETIMPORT R1 2; var1 = 0xCBD666E1
       8 [-]: LOADN R2 0   ; var2 = 0
       9 [-]: CALL R1 2 1  ; var1(var2)
L 1:  10 [-]: GETIMPORT R2 4; var2 = 0xBE190284
      11 [-]: FASTCALL1 62 R2 L2; 
      12 [-]: GETIMPORT R1 6; var1 = 0x7B998233
      13 [-]: CALL R1 2 2  ; var1 = var1(var2)
L 2:  14 [-]: JUMPIFNOT R1 L3; goto L3 if not var1
      15 [-]: GETIMPORT R1 2; var1 = 0xCBD666E1
      16 [-]: LOADN R2 0   ; var2 = 0
      17 [-]: CALL R1 2 1  ; var1(var2)
      18 [-]: JUMPBACK L1  ; goto L1
L 3:  19 [-]: GETUPVAL R1 0; var1 = upvalues[0]
      20 [-]: GETUPVAL R3 4; var3 = upvalues[4]
      21 [-]: NAMECALL R1 R1 K7; var2 = var1; var1 = var1[0x209398C2]
      22 [-]: CALL R1 3 2  ; var1 = var1(var2, var3)
      23 [-]: SETUPVAL R1 4; upvalues[1] = var4
      24 [-]: GETUPVAL R1 5; var1 = upvalues[5]
      25 [-]: GETIMPORT R2 9; var2 = 0x67652851
      26 [-]: CALL R2 1 0  ; var2, ... = var2()
      27 [-]: CALL R1 0 1  ; var1(var2, ...)
      28 [-]: JUMPBACK L0  ; goto L0
      29 [-]: RETURN R0 0  ; 


; Name:            
; Defined at line: 636
; #Upvalues:       0
; #Parameters:     1
; Is_vararg:       0
; Max Stack Size:  8

       0 [-]: LOADN R1 0   ; var1 = 0
       1 [-]: LOADN R2 10  ; var2 = 10
       2 [-]: GETIMPORT R5 1; var5 = 0x0469F296
       3 [-]: LOADK R6 K2  ; var6 = "UnlitAtten"
       4 [-]: CALL R5 2 2  ; var5 = var5(var6)
       5 [-]: LOADN R6 0   ; var6 = 0
       6 [-]: NAMECALL R3 R0 K3; var4 = var0; var3 = var0[0x986D2AB8]
       7 [-]: CALL R3 4 1  ; var3(var4, var5, var6)
L 0:   8 [-]: FASTCALL1 62 R0 L1; 
       9 [-]: MOVE R4 R0   ; var4 = var0
      10 [-]: GETIMPORT R3 5; var3 = 0x7B998233
      11 [-]: CALL R3 2 2  ; var3 = var3(var4)
L 1:  12 [-]: JUMPIF R3 L9 ; goto L9 if var3
      13 [-]: LOADB R3 1   ; var3 = true
      14 [-]: GETIMPORT R5 8; var5 = _T["curTransmission"]
      15 [-]: FASTCALL1 62 R5 L2; 
      16 [-]: GETIMPORT R4 5; var4 = 0x7B998233
      17 [-]: CALL R4 2 2  ; var4 = var4(var5)
L 2:  18 [-]: JUMPIF R4 L4 ; goto L4 if var4
      19 [-]: GETIMPORT R5 8; var5 = _T["curTransmission"]
      20 [-]: NAMECALL R5 R5 K9; var6 = var5; var5 = var5[0x5397D449]
      21 [-]: CALL R5 2 2  ; var5 = var5(var6)
      22 [-]: FASTCALL1 62 R5 L3; 
      23 [-]: GETIMPORT R4 5; var4 = 0x7B998233
      24 [-]: CALL R4 2 2  ; var4 = var4(var5)
L 3:  25 [-]: JUMPIF R4 L5 ; goto L5 if var4
      26 [-]: LOADN R2 0   ; var2 = 0
      27 [-]: JUMP L5      ; goto L5
L 4:  28 [-]: LOADN R2 1   ; var2 = 1
L 5:  29 [-]: LOADN R4 1   ; var4 = 1
      30 [-]: JUMPIFNOTLE R4 R2 L6; goto L6 if var4 > var795
      31 [-]: LOADB R3 0   ; var3 = false
L 6:  32 [-]: JUMPIFNOT R3 L7; goto L7 if not var3
      33 [-]: GETIMPORT R4 11; var4 = 0x42DCC9F5
      34 [-]: GETIMPORT R7 14; var7 = 0x67652851
      35 [-]: CALL R7 1 2  ; var7 = var7()
      36 [-]: MULK R6 R7 K12; var6 = var7 * 4
      37 [-]: ADD R5 R1 R6 ; var5 = var1 + var6
      38 [-]: LOADN R6 0   ; var6 = 0
      39 [-]: LOADN R7 1   ; var7 = 1
      40 [-]: CALL R4 4 2  ; var4 = var4(var5, var6, var7)
      41 [-]: MOVE R1 R4   ; var1 = var4
      42 [-]: JUMP L8      ; goto L8
L 7:  43 [-]: GETIMPORT R4 11; var4 = 0x42DCC9F5
      44 [-]: GETIMPORT R7 14; var7 = 0x67652851
      45 [-]: CALL R7 1 2  ; var7 = var7()
      46 [-]: MULK R6 R7 K12; var6 = var7 * 4
      47 [-]: SUB R5 R1 R6 ; var5 = var1 - var6
      48 [-]: LOADN R6 0   ; var6 = 0
      49 [-]: LOADN R7 1   ; var7 = 1
      50 [-]: CALL R4 4 2  ; var4 = var4(var5, var6, var7)
      51 [-]: MOVE R1 R4   ; var1 = var4
L 8:  52 [-]: GETIMPORT R6 1; var6 = 0x0469F296
      53 [-]: LOADK R7 K2  ; var7 = "UnlitAtten"
      54 [-]: CALL R6 2 2  ; var6 = var6(var7)
      55 [-]: MOVE R7 R1   ; var7 = var1
      56 [-]: NAMECALL R4 R0 K3; var5 = var0; var4 = var0[0x986D2AB8]
      57 [-]: CALL R4 4 1  ; var4(var5, var6, var7)
      58 [-]: GETIMPORT R4 16; var4 = 0xCBD666E1
      59 [-]: LOADN R5 0   ; var5 = 0
      60 [-]: CALL R4 2 1  ; var4(var5)
      61 [-]: JUMPBACK L0  ; goto L0
L 9:  62 [-]: RETURN R0 0  ; 


; Name:            
; Defined at line: 670
; #Upvalues:       1
; #Parameters:     1
; Is_vararg:       0
; Max Stack Size:  17

       0 [-]: NAMECALL R1 R0 K0; var2 = var0; var1 = var0[0x22DA1852]
       1 [-]: CALL R1 2 2  ; var1 = var1(var2)
       2 [-]: NAMECALL R1 R1 K1; var2 = var1; var1 = var1[0x6D604BA7]
       3 [-]: CALL R1 2 2  ; var1 = var1(var2)
       4 [-]: GETIMPORT R2 3; var2 = 0xCFC01047
       5 [-]: GETUPVAL R3 0; var3 = upvalues[0]
       6 [-]: CALL R2 2 4  ; var2, var3, var4 = var2(var3)
       7 [-]: FORGPREP_NEXT R2 L5; 
L 0:   8 [-]: JUMPIFNOTEQ R5 R1 L5; goto L5 if var5 ~= var395045
       9 [-]: GETTABLEN R7 R6 1; var7 = var6[1]
      10 [-]: GETTABLEN R8 R6 2; var8 = var6[2]
      11 [-]: FASTCALL1 62 R7 L1; 
      12 [-]: MOVE R10 R7  ; var10 = var7
      13 [-]: GETIMPORT R9 5; var9 = 0x7B998233
      14 [-]: CALL R9 2 2  ; var9 = var9(var10)
L 1:  15 [-]: JUMPIF R9 L2 ; goto L2 if var9
      16 [-]: MOVE R11 R7  ; var11 = var7
      17 [-]: LOADB R12 1  ; var12 = true
      18 [-]: LOADB R13 0  ; var13 = false
      19 [-]: LOADN R14 0  ; var14 = 0
      20 [-]: GETIMPORT R15 7; var15 = 0x0469F296
      21 [-]: CALL R15 1 2 ; var15 = var15()
      22 [-]: GETIMPORT R16 9; var16 = 0x795A2484
      23 [-]: NAMECALL R9 R0 K10; var10 = var0; var9 = var0[0x5D985C7E]
      24 [-]: CALL R9 8 1  ; var9(var10, var11, var12, var13, var14, var15, var16)
L 2:  25 [-]: FASTCALL1 62 R8 L3; 
      26 [-]: MOVE R10 R8  ; var10 = var8
      27 [-]: GETIMPORT R9 5; var9 = 0x7B998233
      28 [-]: CALL R9 2 2  ; var9 = var9(var10)
L 3:  29 [-]: JUMPIF R9 L4 ; goto L4 if var9
      30 [-]: MOVE R11 R8  ; var11 = var8
      31 [-]: LOADB R12 0  ; var12 = false
      32 [-]: LOADB R13 1  ; var13 = true
      33 [-]: LOADN R14 0  ; var14 = 0
      34 [-]: GETIMPORT R15 7; var15 = 0x0469F296
      35 [-]: CALL R15 1 2 ; var15 = var15()
      36 [-]: GETIMPORT R16 9; var16 = 0x795A2484
      37 [-]: NAMECALL R9 R0 K10; var10 = var0; var9 = var0[0x5D985C7E]
      38 [-]: CALL R9 8 1  ; var9(var10, var11, var12, var13, var14, var15, var16)
L 4:  39 [-]: RETURN R0 0  ; 
L 5:  40 [-]: FORGLOOP R2 L0 2; 
      41 [-]: RETURN R0 0  ; 


; Name:            
; Defined at line: 692
; #Upvalues:       1
; #Parameters:     1
; Is_vararg:       0
; Max Stack Size:  14

       0 [-]: NEWTABLE R1 0 11; var1 = {}
       1 [-]: LOADK R2 K0  ; var2 = "A"
       2 [-]: LOADK R3 K1  ; var3 = "B"
       3 [-]: LOADK R4 K2  ; var4 = "C"
       4 [-]: LOADK R5 K3  ; var5 = "D"
       5 [-]: LOADK R6 K4  ; var6 = "E"
       6 [-]: LOADK R7 K5  ; var7 = "F"
       7 [-]: LOADK R8 K6  ; var8 = "G"
       8 [-]: LOADK R9 K7  ; var9 = "H"
       9 [-]: LOADK R10 K8 ; var10 = "I"
      10 [-]: LOADK R11 K9 ; var11 = "J"
      11 [-]: LOADK R12 K10; var12 = "K"
      12 [-]: SETLIST R1 R2 11 [1]; var1[1] = var2; var1[2] = var3; var1[3] = var4; var1[4] = var5; var1[5] = var6; var1[6] = var7; var1[7] = var8; var1[8] = var9; var1[9] = var10; var1[10] = var11; var1[11] = var12; var1[12] = var13; 
      13 [-]: GETIMPORT R2 12; var2 = 0x0469F296
      14 [-]: LOADK R3 K13 ; var3 = "PlayAnimationThread"
      15 [-]: CALL R2 2 2  ; var2 = var2(var3)
      16 [-]: GETIMPORT R3 15; var3 = 0x3D106989
      17 [-]: LOADK R4 K16 ; var4 = "Starting classroom animations"
      18 [-]: CALL R3 2 1  ; var3(var4)
      19 [-]: NEWCLOSURE R3 P0; 
      20 [-]: CAPTURE UPVAL U0; 
      21 [-]: CAPTURE VAL R2; 
      22 [-]: GETIMPORT R4 18; var4 = 0xC8802016
      23 [-]: MOVE R5 R1   ; var5 = var1
      24 [-]: CALL R4 2 4  ; var4, var5, var6 = var4(var5)
      25 [-]: FORGPREP_INEXT R4 L1; 
L 0:  26 [-]: MOVE R9 R3   ; var9 = var3
      27 [-]: MOVE R10 R7  ; var10 = var7
      28 [-]: LOADK R12 K19; var12 = "Student"
      29 [-]: MOVE R13 R8  ; var13 = var8
      30 [-]: CONCAT R11 R12 R13; var11 = var12 .. var13
      31 [-]: GETIMPORT R12 21; var12 = 0x8CCAE0DA
      32 [-]: GETIMPORT R13 23; var13 = 0x64B6DE32
      33 [-]: CALL R9 5 1  ; var9(var10, var11, var12, var13)
      34 [-]: MOVE R9 R3   ; var9 = var3
      35 [-]: MOVE R10 R7  ; var10 = var7
      36 [-]: LOADK R12 K24; var12 = "Chair"
      37 [-]: MOVE R13 R8  ; var13 = var8
      38 [-]: CONCAT R11 R12 R13; var11 = var12 .. var13
      39 [-]: GETIMPORT R12 26; var12 = 0x06EA1A3C
      40 [-]: GETIMPORT R13 28; var13 = 0xCBB7CA9C
      41 [-]: CALL R9 5 1  ; var9(var10, var11, var12, var13)
L 1:  42 [-]: FORGLOOP R4 L0 2 [inext]; 
      43 [-]: GETIMPORT R4 15; var4 = 0x3D106989
      44 [-]: LOADK R5 K29 ; var5 = "Ended classroom animations"
      45 [-]: CALL R4 2 1  ; var4(var5)
      46 [-]: RETURN R0 0  ; 



