; Name:            
; Defined at line: 1
; #Upvalues:       0
; #Parameters:     0
; Is_vararg:       1
; Max Stack Size:  102

       1 [-]: GETIMPORT R0 1 [0x7ED0A956]
       2 [-]: LOADK R1 K2 ["/Lotus/Types/Vehicles/TNWBalloon/OstBalloonUnmannedAvatar"]
       3 [-]: CALL R0 1 1  
       4 [-]: GETIMPORT R1 1 [0x7ED0A956]
       5 [-]: LOADK R2 K3 ["/Lotus/Types/Enemies/Narmer/NarmerOstronMalePassiveMeleeAvatar"]
       6 [-]: CALL R1 1 1  
       7 [-]: GETIMPORT R2 1 [0x7ED0A956]
       8 [-]: LOADK R3 K4 ["/Lotus/Types/Enemies/NewWar/NarmerOstronWeaponsmithAvatar"]
       9 [-]: CALL R2 1 1  
      10 [-]: GETIMPORT R3 1 [0x7ED0A956]
      11 [-]: LOADK R4 K5 ["/Lotus/Types/Enemies/NewWar/NarmerOstronFishmongerAvatar"]
      12 [-]: CALL R3 1 1  
      13 [-]: GETIMPORT R4 1 [0x7ED0A956]
      14 [-]: LOADK R5 K6 ["/Lotus/Types/Enemies/NewWar/NarmerOstronBeastmasterAvatar"]
      15 [-]: CALL R4 1 1  
      16 [-]: GETIMPORT R5 8 [0xB009BBC6]
      17 [-]: LOADK R6 K9 ["/Lotus/Types/Gameplay/Minigames/Investigation/InvestigationBlockingInputFilter"]
      18 [-]: CALL R5 1 1  
      19 [-]: GETIMPORT R6 11 [0x2D0FAD09]
      20 [-]: LOADK R7 K12 ["Lotus.Scripts.Libs.CommonGamemodeFunctions"]
      21 [-]: CALL R6 1 1  
      22 [-]: GETIMPORT R7 11 [0x2D0FAD09]
      23 [-]: LOADK R8 K13 ["Lotus.Scripts.Libs.ObjectiveText"]
      24 [-]: CALL R7 1 1  
      25 [-]: GETIMPORT R8 11 [0x2D0FAD09]
      26 [-]: LOADK R9 K14 ["Lotus.Interface.Libs.TimerMgr"]
      27 [-]: CALL R8 1 1  
      28 [-]: GETIMPORT R9 11 [0x2D0FAD09]
      29 [-]: LOADK R10 K15 ["Lotus.Scripts.Libs.QuestMissionLib"]
      30 [-]: CALL R9 1 1  
      31 [-]: GETIMPORT R10 11 [0x2D0FAD09]
      32 [-]: LOADK R11 K16 ["Lotus.Scripts.Libs.TransmissionSet"]
      33 [-]: CALL R10 1 1 
      34 [-]: GETIMPORT R11 11 [0x2D0FAD09]
      35 [-]: LOADK R12 K17 ["Lotus.Interface.LotusUtilities"]
      36 [-]: CALL R11 1 1 
      37 [-]: LOADNIL R12  
      38 [-]: LOADNIL R13  
      39 [-]: LOADNIL R14  
      40 [-]: LOADN R15 0  
      41 [-]: LOADNIL R16  
      42 [-]: LOADNIL R17  
      43 [-]: LOADB R18 0  
      44 [-]: LOADN R19 1  
      45 [-]: NEWTABLE R20 0 0
      46 [-]: NEWTABLE R21 0 0
      47 [-]: LOADNIL R22  
      48 [-]: LOADB R23 0  
      49 [-]: LOADB R24 0  
      50 [-]: LOADNIL R25  
      51 [-]: LOADNIL R26  
      52 [-]: LOADNIL R27  
      53 [-]: LOADNIL R28  
      54 [-]: LOADNIL R29  
      55 [-]: LOADN R30 0  
      56 [-]: LOADNIL R31  
      57 [-]: LOADNIL R32  
      58 [-]: LOADN R33 0  
      59 [-]: LOADB R34 0  
      60 [-]: LOADB R35 0  
      61 [-]: LOADNIL R36  
      62 [-]: LOADNIL R37  
      63 [-]: LOADNIL R38  
      64 [-]: LOADB R39 0  
      65 [-]: LOADB R40 0  
      66 [-]: LOADNIL R41  
      67 [-]: LOADNIL R42  
      68 [-]: GETIMPORT R43 19 [0xB7CBD06B]
      69 [-]: LOADN R44 20 
      70 [-]: LOADN R45 30 
      71 [-]: CALL R43 2 1 
      72 [-]: GETIMPORT R44 19 [0xB7CBD06B]
      73 [-]: LOADN R45 5  
      74 [-]: LOADK R46 K20 [7.5]
      75 [-]: CALL R44 2 1 
      76 [-]: LOADNIL R45  
      77 [-]: LOADNIL R46  
      78 [-]: GETIMPORT R47 1 [0x7ED0A956]
      79 [-]: LOADK R48 K21 ["/Lotus/Types/Keys/NewWarQuest/NewWarQuestKeyChain"]
      80 [-]: CALL R47 1 1 
      81 [-]: GETIMPORT R48 1 [0x7ED0A956]
      82 [-]: LOADK R49 K22 ["/Lotus/Types/Keys/NewWarQuest/TNWActThreeBeanstalks"]
      83 [-]: CALL R48 1 1 
      84 [-]: GETIMPORT R49 1 [0x7ED0A956]
      85 [-]: LOADK R50 K23 ["/Lotus/Weapons/Orokin/BallasSword/BallasSwordWeapon"]
      86 [-]: CALL R49 1 1 
      87 [-]: LOADNIL R50  
      88 [-]: LOADNIL R51  
      89 [-]: GETIMPORT R52 25 [0x0469F296]
      90 [-]: LOADK R53 K26 ["isSaved"]
      91 [-]: CALL R52 1 1 
      92 [-]: GETIMPORT R53 25 [0x0469F296]
      93 [-]: LOADK R54 K27 ["EnemyRadarBeanstalks"]
      94 [-]: CALL R53 1 1 
      95 [-]: GETIMPORT R54 25 [0x0469F296]
      96 [-]: LOADK R55 K28 ["DashRadiusBeanstalks"]
      97 [-]: CALL R54 1 1 
      98 [-]: GETIMPORT R55 25 [0x0469F296]
      99 [-]: LOADK R56 K29 ["EnableTowerADevice1Marker"]
     100 [-]: CALL R55 1 1 
     101 [-]: GETIMPORT R56 25 [0x0469F296]
     102 [-]: LOADK R57 K30 ["TimestopTrigger"]
     103 [-]: CALL R56 1 1 
     104 [-]: DUPTABLE R57 43
     105 [-]: LOADN R58 1  
     106 [-]: SETTABLEKS R58 R57 K31 ["INTRO"]
     107 [-]: LOADN R58 2  
     108 [-]: SETTABLEKS R58 R57 K32 ["QUILLS_CAVE"]
     109 [-]: LOADN R58 3  
     110 [-]: SETTABLEKS R58 R57 K33 ["RESCUE_OSTRON"]
     111 [-]: LOADN R58 4  
     112 [-]: SETTABLEKS R58 R57 K34 ["RIDE_BALLOON"]
     113 [-]: LOADN R58 5  
     114 [-]: SETTABLEKS R58 R57 K35 ["ENTER_TOWER"]
     115 [-]: LOADN R58 6  
     116 [-]: SETTABLEKS R58 R57 K36 ["POWER_TOWER_A"]
     117 [-]: LOADN R58 7  
     118 [-]: SETTABLEKS R58 R57 K37 ["POWER_TOWER_B"]
     119 [-]: LOADN R58 8  
     120 [-]: SETTABLEKS R58 R57 K38 ["POWER_TOWER_C"]
     121 [-]: LOADN R58 9  
     122 [-]: SETTABLEKS R58 R57 K39 ["TOWER_ROOF"]
     123 [-]: LOADN R58 10 
     124 [-]: SETTABLEKS R58 R57 K40 ["TIMESTOP"]
     125 [-]: LOADN R58 11 
     126 [-]: SETTABLEKS R58 R57 K41 ["COMPLETE"]
     127 [-]: LOADN R58 999
     128 [-]: SETTABLEKS R58 R57 K42 ["RESPAWN"]
     129 [-]: DUPTABLE R58 55
     130 [-]: LOADK R59 K56 ["/Lotus/Language/NewWar/P3M2RescueKonzu"]
     131 [-]: SETTABLEKS R59 R58 K44 ["rescueKonzu"]
     132 [-]: LOADK R59 K57 ["/Lotus/Language/NewWar/P3M2RescueOstron"]
     133 [-]: SETTABLEKS R59 R58 K45 ["rescueOstron"]
     134 [-]: LOADK R59 K58 ["/Lotus/Language/NewWar/P3M2OptionalRescue"]
     135 [-]: SETTABLEKS R59 R58 K46 ["optionalRescue"]
     136 [-]: LOADK R59 K59 ["/Lotus/Language/NewWar/P3M2RideBalloon"]
     137 [-]: SETTABLEKS R59 R58 K47 ["rideBalloon"]
     138 [-]: LOADK R59 K60 ["/Lotus/Language/NewWar/P3M2AscendTower"]
     139 [-]: SETTABLEKS R59 R58 K48 ["ascendTower"]
     140 [-]: LOADK R59 K61 ["/Lotus/Language/NewWar/P3M2EnterTower"]
     141 [-]: SETTABLEKS R59 R58 K49 ["enterTower"]
     142 [-]: LOADK R59 K62 ["/Lotus/Language/NewWar/P3M2ActivateDevices"]
     143 [-]: SETTABLEKS R59 R58 K50 ["activateDevices"]
     144 [-]: LOADK R59 K63 ["/Lotus/Language/NewWar/P3M2AscendNextLevel"]
     145 [-]: SETTABLEKS R59 R58 K51 ["goToNextLevel"]
     146 [-]: LOADK R59 K64 ["/Lotus/Language/NewWar/P3M2ReachMurex"]
     147 [-]: SETTABLEKS R59 R58 K52 ["reachMurex"]
     148 [-]: LOADK R59 K65 ["/Lotus/Language/NewWar/P3M2FollowLight"]
     149 [-]: SETTABLEKS R59 R58 K53 ["followTheLight"]
     150 [-]: LOADK R59 K66 ["/Lotus/Language/NewWar/P3M2MurexTimeLimit"]
     151 [-]: SETTABLEKS R59 R58 K54 ["murexTimeLeft"]
     152 [-]: DUPTABLE R59 84
     153 [-]: GETIMPORT R60 25 [0x0469F296]
     154 [-]: LOADK R61 K85 ["OrdisIntro"]
     155 [-]: CALL R60 1 1 
     156 [-]: SETTABLEKS R60 R59 K67 ["introOrdis"]
     157 [-]: GETIMPORT R60 25 [0x0469F296]
     158 [-]: LOADK R61 K86 ["KonzuRescued"]
     159 [-]: CALL R60 1 1 
     160 [-]: SETTABLEKS R60 R59 K68 ["konzuRescuedStart"]
     161 [-]: GETIMPORT R60 25 [0x0469F296]
     162 [-]: LOADK R61 K87 ["DTNWPt3M2CetusRescue"]
     163 [-]: CALL R60 1 1 
     164 [-]: SETTABLEKS R60 R59 K69 ["operatorResponseToKonzu"]
     165 [-]: GETIMPORT R60 25 [0x0469F296]
     166 [-]: LOADK R61 K88 ["KonzuSaveTheOthers"]
     167 [-]: CALL R60 1 1 
     168 [-]: SETTABLEKS R60 R59 K70 ["konzuSaveOstrons"]
     169 [-]: GETIMPORT R60 25 [0x0469F296]
     170 [-]: LOADK R61 K89 ["HokThanks"]
     171 [-]: CALL R60 1 1 
     172 [-]: SETTABLEKS R60 R59 K71 ["hokThankYou"]
     173 [-]: GETIMPORT R60 25 [0x0469F296]
     174 [-]: LOADK R61 K90 ["HailukThanks"]
     175 [-]: CALL R60 1 1 
     176 [-]: SETTABLEKS R60 R59 K72 ["hailukThankYou"]
     177 [-]: GETIMPORT R60 25 [0x0469F296]
     178 [-]: LOADK R61 K91 ["TeasonaiThanks"]
     179 [-]: CALL R60 1 1 
     180 [-]: SETTABLEKS R60 R59 K73 ["teasonaiThankYou"]
     181 [-]: GETIMPORT R60 25 [0x0469F296]
     182 [-]: LOADK R61 K92 ["KonzuAirDocs"]
     183 [-]: CALL R60 1 1 
     184 [-]: SETTABLEKS R60 R59 K74 ["konzuGoAirDocs"]
     185 [-]: GETIMPORT R60 25 [0x0469F296]
     186 [-]: LOADK R61 K93 ["KonzuFlyFriend"]
     187 [-]: CALL R60 1 1 
     188 [-]: SETTABLEKS R60 R59 K75 ["konzuFlyTenno"]
     189 [-]: GETIMPORT R60 25 [0x0469F296]
     190 [-]: LOADK R61 K94 ["OrdisAboutUnumTower"]
     191 [-]: CALL R60 1 1 
     192 [-]: SETTABLEKS R60 R59 K76 ["ordisAboutUnumTower"]
     193 [-]: GETIMPORT R60 25 [0x0469F296]
     194 [-]: LOADK R61 K95 ["DTNWPt3M2AscendTower"]
     195 [-]: CALL R60 1 1 
     196 [-]: SETTABLEKS R60 R59 K77 ["operatorResponseUnumTower"]
     197 [-]: GETIMPORT R60 25 [0x0469F296]
     198 [-]: LOADK R61 K96 ["DTNWPt3M2AscendTower2"]
     199 [-]: CALL R60 1 1 
     200 [-]: SETTABLEKS R60 R59 K78 ["operatorReactsWhisper"]
     201 [-]: GETIMPORT R60 25 [0x0469F296]
     202 [-]: LOADK R61 K97 ["OrdisWhisperDialog"]
     203 [-]: CALL R60 1 1 
     204 [-]: SETTABLEKS R60 R59 K79 ["ordisReactsWhisper"]
     205 [-]: GETIMPORT R60 25 [0x0469F296]
     206 [-]: LOADK R61 K98 ["OrdisMurexLaunch"]
     207 [-]: CALL R60 1 1 
     208 [-]: SETTABLEKS R60 R59 K80 ["murexOrbitalLaunch"]
     209 [-]: GETIMPORT R60 25 [0x0469F296]
     210 [-]: LOADK R61 K99 ["UnumWhisper"]
     211 [-]: CALL R60 1 1 
     212 [-]: SETTABLEKS R60 R59 K81 ["unumSpeaks"]
     213 [-]: GETIMPORT R60 25 [0x0469F296]
     214 [-]: LOADK R61 K100 ["OrdisTimeStop"]
     215 [-]: CALL R60 1 1 
     216 [-]: SETTABLEKS R60 R59 K82 ["ordisTimeStop"]
     217 [-]: GETIMPORT R60 25 [0x0469F296]
     218 [-]: LOADK R61 K101 ["DTNWPt3M2AscendTower3"]
     219 [-]: CALL R60 1 1 
     220 [-]: SETTABLEKS R60 R59 K83 ["operatorTimeStop"]
     221 [-]: NEWTABLE R60 0 2
     222 [-]: GETIMPORT R61 25 [0x0469F296]
     223 [-]: LOADK R62 K102 ["KonzuSpawner"]
     224 [-]: CALL R61 1 1 
     225 [-]: GETIMPORT R62 25 [0x0469F296]
     226 [-]: LOADK R63 K103 ["ElderSpawner"]
     227 [-]: CALL R62 1 -1
     228 [-]: SETLIST R60 R61 -1 [1]
     229 [-]: DUPTABLE R61 108
     230 [-]: NEWTABLE R62 0 1
     231 [-]: GETIMPORT R63 25 [0x0469F296]
     232 [-]: LOADK R64 K109 ["TowerADevice1"]
     233 [-]: CALL R63 1 -1
     234 [-]: SETLIST R62 R63 -1 [1]
     235 [-]: SETTABLEKS R62 R61 K104 ["A"]
     236 [-]: NEWTABLE R62 0 2
     237 [-]: GETIMPORT R63 25 [0x0469F296]
     238 [-]: LOADK R64 K110 ["TowerBDevice1"]
     239 [-]: CALL R63 1 1 
     240 [-]: GETIMPORT R64 25 [0x0469F296]
     241 [-]: LOADK R65 K111 ["TowerBDevice2"]
     242 [-]: CALL R64 1 -1
     243 [-]: SETLIST R62 R63 -1 [1]
     244 [-]: SETTABLEKS R62 R61 K105 ["B"]
     245 [-]: NEWTABLE R62 0 4
     246 [-]: GETIMPORT R63 25 [0x0469F296]
     247 [-]: LOADK R64 K112 ["TowerCDevice1"]
     248 [-]: CALL R63 1 1 
     249 [-]: GETIMPORT R64 25 [0x0469F296]
     250 [-]: LOADK R65 K113 ["TowerCDevice2"]
     251 [-]: CALL R64 1 1 
     252 [-]: GETIMPORT R65 25 [0x0469F296]
     253 [-]: LOADK R66 K114 ["TowerCDevice3"]
     254 [-]: CALL R65 1 1 
     255 [-]: GETIMPORT R66 25 [0x0469F296]
     256 [-]: LOADK R67 K115 ["TowerCDevice4"]
     257 [-]: CALL R66 1 -1
     258 [-]: SETLIST R62 R63 -1 [1]
     259 [-]: SETTABLEKS R62 R61 K106 ["C"]
     260 [-]: NEWTABLE R62 0 2
     261 [-]: GETIMPORT R63 25 [0x0469F296]
     262 [-]: LOADK R64 K116 ["TowerRoofDevice1"]
     263 [-]: CALL R63 1 1 
     264 [-]: GETIMPORT R64 25 [0x0469F296]
     265 [-]: LOADK R65 K117 ["TowerRoofDevice2"]
     266 [-]: CALL R64 1 -1
     267 [-]: SETLIST R62 R63 -1 [1]
     268 [-]: SETTABLEKS R62 R61 K107 ["ROOF"]
     269 [-]: DUPTABLE R62 124
     270 [-]: GETIMPORT R63 25 [0x0469F296]
     271 [-]: LOADK R64 K125 ["InnerEnergyBeam"]
     272 [-]: CALL R63 1 1 
     273 [-]: SETTABLEKS R63 R62 K118 ["ENERGY_BEAM_INNER"]
     274 [-]: GETIMPORT R63 25 [0x0469F296]
     275 [-]: LOADK R64 K126 ["OutterEnergyBeam"]
     276 [-]: CALL R63 1 1 
     277 [-]: SETTABLEKS R63 R62 K119 ["ENERGY_BEAM_OUTTER"]
     278 [-]: GETIMPORT R63 25 [0x0469F296]
     279 [-]: LOADK R64 K127 ["RedLight"]
     280 [-]: CALL R63 1 1 
     281 [-]: SETTABLEKS R63 R62 K120 ["RED_LIGHT"]
     282 [-]: GETIMPORT R63 25 [0x0469F296]
     283 [-]: LOADK R64 K128 ["BlueLight"]
     284 [-]: CALL R63 1 1 
     285 [-]: SETTABLEKS R63 R62 K121 ["BLUE_LIGHT"]
     286 [-]: GETIMPORT R63 25 [0x0469F296]
     287 [-]: LOADK R64 K129 ["RedSound"]
     288 [-]: CALL R63 1 1 
     289 [-]: SETTABLEKS R63 R62 K122 ["RED_SOUND"]
     290 [-]: GETIMPORT R63 25 [0x0469F296]
     291 [-]: LOADK R64 K130 ["BlueSound"]
     292 [-]: CALL R63 1 1 
     293 [-]: SETTABLEKS R63 R62 K123 ["BLUE_SOUND"]
     294 [-]: NEWTABLE R63 16 0
     295 [-]: GETTABLEKS R64 R57 K31 ["INTRO"]
     296 [-]: DUPTABLE R65 134
     297 [-]: LOADK R66 K135 ["Intro"]
     298 [-]: SETTABLEKS R66 R65 K131 ["name"]
     299 [-]: GETIMPORT R66 25 [0x0469F296]
     300 [-]: LOADK R67 K136 ["CaveWaypoint"]
     301 [-]: CALL R66 1 1 
     302 [-]: SETTABLEKS R66 R65 K132 ["respawnPt"]
     303 [-]: LOADB R66 1  
     304 [-]: SETTABLEKS R66 R65 K133 ["hasCheckpoint"]
     305 [-]: SETTABLE R65 R63 R64
     306 [-]: GETTABLEKS R64 R57 K32 ["QUILLS_CAVE"]
     307 [-]: DUPTABLE R65 134
     308 [-]: LOADK R66 K137 ["QuillsCave"]
     309 [-]: SETTABLEKS R66 R65 K131 ["name"]
     310 [-]: GETIMPORT R66 25 [0x0469F296]
     311 [-]: LOADK R67 K136 ["CaveWaypoint"]
     312 [-]: CALL R66 1 1 
     313 [-]: SETTABLEKS R66 R65 K132 ["respawnPt"]
     314 [-]: LOADB R66 1  
     315 [-]: SETTABLEKS R66 R65 K133 ["hasCheckpoint"]
     316 [-]: SETTABLE R65 R63 R64
     317 [-]: GETTABLEKS R64 R57 K33 ["RESCUE_OSTRON"]
     318 [-]: DUPTABLE R65 134
     319 [-]: LOADK R66 K138 ["RescueOstron"]
     320 [-]: SETTABLEKS R66 R65 K131 ["name"]
     321 [-]: GETIMPORT R66 25 [0x0469F296]
     322 [-]: LOADK R67 K139 ["QuillsCaveExitWP"]
     323 [-]: CALL R66 1 1 
     324 [-]: SETTABLEKS R66 R65 K132 ["respawnPt"]
     325 [-]: LOADB R66 1  
     326 [-]: SETTABLEKS R66 R65 K133 ["hasCheckpoint"]
     327 [-]: SETTABLE R65 R63 R64
     328 [-]: GETTABLEKS R64 R57 K34 ["RIDE_BALLOON"]
     329 [-]: DUPTABLE R65 134
     330 [-]: LOADK R66 K140 ["RideBalloon"]
     331 [-]: SETTABLEKS R66 R65 K131 ["name"]
     332 [-]: GETIMPORT R66 25 [0x0469F296]
     333 [-]: LOADK R67 K141 ["AfterKonzuCheckpoint"]
     334 [-]: CALL R66 1 1 
     335 [-]: SETTABLEKS R66 R65 K132 ["respawnPt"]
     336 [-]: LOADB R66 1  
     337 [-]: SETTABLEKS R66 R65 K133 ["hasCheckpoint"]
     338 [-]: SETTABLE R65 R63 R64
     339 [-]: GETTABLEKS R64 R57 K35 ["ENTER_TOWER"]
     340 [-]: DUPTABLE R65 142
     341 [-]: LOADK R66 K143 ["EnterTower"]
     342 [-]: SETTABLEKS R66 R65 K131 ["name"]
     343 [-]: GETIMPORT R66 25 [0x0469F296]
     344 [-]: LOADK R67 K144 ["SkipBalloon"]
     345 [-]: CALL R66 1 1 
     346 [-]: SETTABLEKS R66 R65 K132 ["respawnPt"]
     347 [-]: SETTABLE R65 R63 R64
     348 [-]: GETTABLEKS R64 R57 K36 ["POWER_TOWER_A"]
     349 [-]: DUPTABLE R65 134
     350 [-]: LOADK R66 K145 ["PowerTowerA"]
     351 [-]: SETTABLEKS R66 R65 K131 ["name"]
     352 [-]: GETIMPORT R66 25 [0x0469F296]
     353 [-]: LOADK R67 K146 ["UnumTowerA"]
     354 [-]: CALL R66 1 1 
     355 [-]: SETTABLEKS R66 R65 K132 ["respawnPt"]
     356 [-]: LOADB R66 1  
     357 [-]: SETTABLEKS R66 R65 K133 ["hasCheckpoint"]
     358 [-]: SETTABLE R65 R63 R64
     359 [-]: GETTABLEKS R64 R57 K37 ["POWER_TOWER_B"]
     360 [-]: DUPTABLE R65 134
     361 [-]: LOADK R66 K147 ["PowerTowerB"]
     362 [-]: SETTABLEKS R66 R65 K131 ["name"]
     363 [-]: GETIMPORT R66 25 [0x0469F296]
     364 [-]: LOADK R67 K148 ["PowerTowerBSpawnPoint"]
     365 [-]: CALL R66 1 1 
     366 [-]: SETTABLEKS R66 R65 K132 ["respawnPt"]
     367 [-]: LOADB R66 1  
     368 [-]: SETTABLEKS R66 R65 K133 ["hasCheckpoint"]
     369 [-]: SETTABLE R65 R63 R64
     370 [-]: GETTABLEKS R64 R57 K38 ["POWER_TOWER_C"]
     371 [-]: DUPTABLE R65 134
     372 [-]: LOADK R66 K149 ["PowerTowerC"]
     373 [-]: SETTABLEKS R66 R65 K131 ["name"]
     374 [-]: GETIMPORT R66 25 [0x0469F296]
     375 [-]: LOADK R67 K150 ["PowerTowerCSpawnPoint"]
     376 [-]: CALL R66 1 1 
     377 [-]: SETTABLEKS R66 R65 K132 ["respawnPt"]
     378 [-]: LOADB R66 1  
     379 [-]: SETTABLEKS R66 R65 K133 ["hasCheckpoint"]
     380 [-]: SETTABLE R65 R63 R64
     381 [-]: GETTABLEKS R64 R57 K39 ["TOWER_ROOF"]
     382 [-]: DUPTABLE R65 134
     383 [-]: LOADK R66 K151 ["TowerRoof"]
     384 [-]: SETTABLEKS R66 R65 K131 ["name"]
     385 [-]: GETIMPORT R66 25 [0x0469F296]
     386 [-]: LOADK R67 K152 ["TowerRoofTopSpawnPoint"]
     387 [-]: CALL R66 1 1 
     388 [-]: SETTABLEKS R66 R65 K132 ["respawnPt"]
     389 [-]: LOADB R66 1  
     390 [-]: SETTABLEKS R66 R65 K133 ["hasCheckpoint"]
     391 [-]: SETTABLE R65 R63 R64
     392 [-]: GETTABLEKS R64 R57 K40 ["TIMESTOP"]
     393 [-]: DUPTABLE R65 142
     394 [-]: LOADK R66 K153 ["TimeStop"]
     395 [-]: SETTABLEKS R66 R65 K131 ["name"]
     396 [-]: GETIMPORT R66 25 [0x0469F296]
     397 [-]: LOADK R67 K154 ["TimeStopSpawnPoint"]
     398 [-]: CALL R66 1 1 
     399 [-]: SETTABLEKS R66 R65 K132 ["respawnPt"]
     400 [-]: SETTABLE R65 R63 R64
     401 [-]: GETTABLEKS R64 R57 K41 ["COMPLETE"]
     402 [-]: DUPTABLE R65 155
     403 [-]: LOADK R66 K156 ["Complete"]
     404 [-]: SETTABLEKS R66 R65 K131 ["name"]
     405 [-]: SETTABLE R65 R63 R64
     406 [-]: GETTABLEKS R64 R57 K42 ["RESPAWN"]
     407 [-]: DUPTABLE R65 155
     408 [-]: LOADK R66 K157 ["Respawn"]
     409 [-]: SETTABLEKS R66 R65 K131 ["name"]
     410 [-]: SETTABLE R65 R63 R64
     411 [-]: DUPCLOSURE R64 K158 []
     412 [-]: MOVE R0 R63  
     413 [-]: DUPCLOSURE R65 K159 []
     414 [-]: MOVE R0 R63  
     415 [-]: DUPCLOSURE R66 K160 []
     416 [-]: MOVE R0 R63  
     417 [-]: NEWCLOSURE R67 P3
     418 [-]: MOVE R1 R12  
     419 [-]: NEWCLOSURE R68 P4
     420 [-]: MOVE R1 R12  
     421 [-]: NEWCLOSURE R69 P5
     422 [-]: MOVE R1 R12  
     423 [-]: MOVE R1 R17  
     424 [-]: NEWCLOSURE R70 P6
     425 [-]: MOVE R1 R17  
     426 [-]: DUPCLOSURE R71 K161 []
     427 [-]: MOVE R0 R70  
     428 [-]: SETGLOBAL R71 K162 ["ForceRespawn"]
     429 [-]: NEWCLOSURE R71 P8
     430 [-]: MOVE R1 R41  
     431 [-]: MOVE R0 R9   
     432 [-]: MOVE R1 R17  
     433 [-]: MOVE R1 R34  
     434 [-]: MOVE R1 R15  
     435 [-]: MOVE R0 R57  
     436 [-]: MOVE R0 R54  
     437 [-]: MOVE R0 R53  
     438 [-]: MOVE R0 R49  
     439 [-]: DUPCLOSURE R72 K163 []
     440 [-]: DUPCLOSURE R73 K164 []
     441 [-]: MOVE R0 R9   
     442 [-]: MOVE R0 R47  
     443 [-]: MOVE R0 R48  
     444 [-]: NEWCLOSURE R74 P11
     445 [-]: MOVE R0 R71  
     446 [-]: MOVE R1 R17  
     447 [-]: MOVE R1 R18  
     448 [-]: MOVE R0 R9   
     449 [-]: MOVE R0 R49  
     450 [-]: NEWCLOSURE R75 P12
     451 [-]: MOVE R1 R17  
     452 [-]: NEWCLOSURE R76 P13
     453 [-]: MOVE R1 R27  
     454 [-]: MOVE R1 R26  
     455 [-]: MOVE R1 R28  
     456 [-]: DUPCLOSURE R77 K165 []
     457 [-]: MOVE R0 R10  
     458 [-]: MOVE R0 R59  
     459 [-]: SETGLOBAL R77 K166 ["PlayIntroTransmissions"]
     460 [-]: NEWCLOSURE R77 P15
     461 [-]: MOVE R1 R35  
     462 [-]: MOVE R0 R10  
     463 [-]: MOVE R0 R59  
     464 [-]: SETGLOBAL R77 K167 ["PlayBalloonTransmissions"]
     465 [-]: DUPCLOSURE R77 K168 []
     466 [-]: SETGLOBAL R77 K169 ["QuillsCaveEntrance"]
     467 [-]: NEWCLOSURE R77 P17
     468 [-]: MOVE R1 R22  
     469 [-]: NEWCLOSURE R78 P18
     470 [-]: MOVE R1 R20  
     471 [-]: MOVE R1 R21  
     472 [-]: MOVE R0 R52  
     473 [-]: MOVE R1 R19  
     474 [-]: MOVE R0 R77  
     475 [-]: MOVE R1 R22  
     476 [-]: NEWCLOSURE R79 P19
     477 [-]: MOVE R1 R22  
     478 [-]: MOVE R0 R11  
     479 [-]: MOVE R0 R77  
     480 [-]: DUPCLOSURE R80 K170 []
     481 [-]: MOVE R0 R52  
     482 [-]: NEWCLOSURE R81 P21
     483 [-]: MOVE R1 R21  
     484 [-]: NEWCLOSURE R82 P22
     485 [-]: MOVE R1 R22  
     486 [-]: MOVE R0 R79  
     487 [-]: MOVE R0 R78  
     488 [-]: NEWCLOSURE R83 P23
     489 [-]: MOVE R0 R7   
     490 [-]: MOVE R0 R58  
     491 [-]: MOVE R1 R40  
     492 [-]: MOVE R0 R6   
     493 [-]: MOVE R0 R63  
     494 [-]: MOVE R0 R57  
     495 [-]: MOVE R0 R82  
     496 [-]: MOVE R0 R60  
     497 [-]: NEWCLOSURE R84 P24
     498 [-]: MOVE R1 R21  
     499 [-]: MOVE R1 R20  
     500 [-]: MOVE R1 R19  
     501 [-]: MOVE R0 R60  
     502 [-]: MOVE R0 R7   
     503 [-]: MOVE R0 R58  
     504 [-]: MOVE R1 R40  
     505 [-]: MOVE R0 R6   
     506 [-]: MOVE R0 R63  
     507 [-]: MOVE R0 R57  
     508 [-]: MOVE R0 R82  
     509 [-]: MOVE R0 R10  
     510 [-]: MOVE R0 R59  
     511 [-]: SETGLOBAL R84 K171 ["PlayKonzuRescuedTransmissions"]
     512 [-]: NEWCLOSURE R84 P25
     513 [-]: MOVE R1 R15  
     514 [-]: MOVE R0 R57  
     515 [-]: MOVE R0 R78  
     516 [-]: SETGLOBAL R84 K172 ["OnSpawn"]
     517 [-]: DUPCLOSURE R84 K173 []
     518 [-]: MOVE R0 R1   
     519 [-]: SETGLOBAL R84 K174 ["RemoveFinisherFromOstron"]
     520 [-]: DUPCLOSURE R84 K175 []
     521 [-]: DUPCLOSURE R85 K176 []
     522 [-]: MOVE R0 R52  
     523 [-]: MOVE R0 R84  
     524 [-]: SETGLOBAL R85 K177 ["MonitorOstrons"]
     525 [-]: NEWCLOSURE R85 P29
     526 [-]: MOVE R1 R24  
     527 [-]: NEWCLOSURE R86 P30
     528 [-]: MOVE R1 R50  
     529 [-]: DUPCLOSURE R87 K178 []
     530 [-]: SETGLOBAL R87 K179 ["OnDeaconSpawned"]
     531 [-]: NEWCLOSURE R87 P32
     532 [-]: MOVE R1 R17  
     533 [-]: MOVE R1 R45  
     534 [-]: NEWCLOSURE R88 P33
     535 [-]: MOVE R1 R42  
     536 [-]: MOVE R1 R13  
     537 [-]: MOVE R0 R43  
     538 [-]: MOVE R0 R87  
     539 [-]: MOVE R0 R44  
     540 [-]: MOVE R1 R17  
     541 [-]: MOVE R0 R88  
     542 [-]: NEWCLOSURE R89 P34
     543 [-]: MOVE R1 R17  
     544 [-]: MOVE R0 R10  
     545 [-]: MOVE R0 R59  
     546 [-]: MOVE R0 R6   
     547 [-]: SETGLOBAL R89 K180 ["PlayWhisper"]
     548 [-]: NEWCLOSURE R89 P35
     549 [-]: MOVE R1 R31  
     550 [-]: MOVE R1 R30  
     551 [-]: MOVE R0 R7   
     552 [-]: NEWCLOSURE R90 P36
     553 [-]: MOVE R1 R17  
     554 [-]: MOVE R1 R32  
     555 [-]: MOVE R1 R14  
     556 [-]: NEWCLOSURE R91 P37
     557 [-]: MOVE R1 R28  
     558 [-]: MOVE R1 R15  
     559 [-]: MOVE R0 R57  
     560 [-]: MOVE R1 R24  
     561 [-]: MOVE R0 R7   
     562 [-]: MOVE R0 R58  
     563 [-]: MOVE R1 R12  
     564 [-]: MOVE R0 R68  
     565 [-]: SETGLOBAL R91 K181 ["OnActivated"]
     566 [-]: NEWCLOSURE R91 P38
     567 [-]: MOVE R1 R15  
     568 [-]: MOVE R0 R57  
     569 [-]: MOVE R1 R31  
     570 [-]: MOVE R0 R7   
     571 [-]: MOVE R1 R30  
     572 [-]: MOVE R0 R58  
     573 [-]: MOVE R0 R68  
     574 [-]: MOVE R1 R32  
     575 [-]: MOVE R1 R29  
     576 [-]: MOVE R0 R56  
     577 [-]: SETGLOBAL R91 K182 ["FirePort"]
     578 [-]: DUPCLOSURE R91 K183 []
     579 [-]: SETGLOBAL R91 K184 ["OnSentientSpawn"]
     580 [-]: NEWCLOSURE R91 P40
     581 [-]: MOVE R1 R17  
     582 [-]: MOVE R0 R11  
     583 [-]: MOVE R0 R5   
     584 [-]: MOVE R1 R32  
     585 [-]: MOVE R0 R62  
     586 [-]: SETGLOBAL R91 K185 ["BeamElevator"]
     587 [-]: NEWCLOSURE R91 P41
     588 [-]: MOVE R1 R33  
     589 [-]: SETGLOBAL R91 K186 ["OnAgentSpawned"]
     590 [-]: DUPCLOSURE R91 K187 []
     591 [-]: NEWCLOSURE R92 P43
     592 [-]: MOVE R1 R33  
     593 [-]: DUPCLOSURE R93 K188 []
     594 [-]: MOVE R0 R7   
     595 [-]: NEWCLOSURE R94 P45
     596 [-]: MOVE R1 R29  
     597 [-]: MOVE R1 R15  
     598 [-]: MOVE R0 R57  
     599 [-]: MOVE R1 R14  
     600 [-]: MOVE R0 R10  
     601 [-]: MOVE R0 R59  
     602 [-]: MOVE R0 R55  
     603 [-]: MOVE R0 R7   
     604 [-]: MOVE R0 R58  
     605 [-]: MOVE R0 R56  
     606 [-]: MOVE R0 R73  
     607 [-]: SETGLOBAL R94 K189 ["OnTouched"]
     608 [-]: DUPCLOSURE R94 K190 []
     609 [-]: NEWCLOSURE R95 P47
     610 [-]: MOVE R1 R17  
     611 [-]: MOVE R1 R34  
     612 [-]: MOVE R1 R15  
     613 [-]: MOVE R0 R57  
     614 [-]: MOVE R1 R26  
     615 [-]: NEWCLOSURE R96 P48
     616 [-]: MOVE R1 R15  
     617 [-]: MOVE R0 R57  
     618 [-]: MOVE R0 R11  
     619 [-]: MOVE R1 R20  
     620 [-]: MOVE R0 R52  
     621 [-]: MOVE R1 R22  
     622 [-]: MOVE R1 R21  
     623 [-]: MOVE R0 R7   
     624 [-]: MOVE R1 R17  
     625 [-]: NEWCLOSURE R97 P49
     626 [-]: MOVE R1 R15  
     627 [-]: MOVE R0 R57  
     628 [-]: MOVE R1 R17  
     629 [-]: MOVE R0 R71  
     630 [-]: NEWCLOSURE R98 P50
     631 [-]: MOVE R0 R66  
     632 [-]: MOVE R0 R9   
     633 [-]: MOVE R0 R91  
     634 [-]: MOVE R1 R25  
     635 [-]: MOVE R1 R36  
     636 [-]: MOVE R1 R37  
     637 [-]: MOVE R0 R71  
     638 [-]: MOVE R0 R96  
     639 [-]: MOVE R0 R97  
     640 [-]: MOVE R0 R94  
     641 [-]: MOVE R1 R14  
     642 [-]: MOVE R0 R57  
     643 [-]: NEWCLOSURE R99 P51
     644 [-]: MOVE R0 R63  
     645 [-]: MOVE R0 R57  
     646 [-]: MOVE R1 R23  
     647 [-]: MOVE R0 R74  
     648 [-]: MOVE R1 R25  
     649 [-]: MOVE R0 R7   
     650 [-]: MOVE R0 R58  
     651 [-]: MOVE R0 R68  
     652 [-]: MOVE R1 R17  
     653 [-]: MOVE R1 R24  
     654 [-]: MOVE R1 R19  
     655 [-]: MOVE R0 R60  
     656 [-]: MOVE R0 R82  
     657 [-]: MOVE R1 R40  
     658 [-]: MOVE R0 R6   
     659 [-]: MOVE R0 R10  
     660 [-]: MOVE R0 R59  
     661 [-]: MOVE R0 R86  
     662 [-]: MOVE R1 R35  
     663 [-]: MOVE R1 R22  
     664 [-]: MOVE R0 R76  
     665 [-]: MOVE R1 R28  
     666 [-]: MOVE R1 R12  
     667 [-]: MOVE R1 R29  
     668 [-]: MOVE R0 R9   
     669 [-]: MOVE R1 R32  
     670 [-]: MOVE R0 R0   
     671 [-]: MOVE R1 R38  
     672 [-]: MOVE R0 R55  
     673 [-]: MOVE R0 R89  
     674 [-]: MOVE R0 R61  
     675 [-]: MOVE R1 R42  
     676 [-]: MOVE R1 R13  
     677 [-]: MOVE R0 R92  
     678 [-]: MOVE R0 R93  
     679 [-]: MOVE R1 R16  
     680 [-]: MOVE R1 R26  
     681 [-]: MOVE R0 R71  
     682 [-]: MOVE R1 R34  
     683 [-]: NEWCLOSURE R100 P52
     684 [-]: MOVE R0 R95  
     685 [-]: MOVE R1 R16  
     686 [-]: MOVE R1 R15  
     687 [-]: MOVE R1 R14  
     688 [-]: MOVE R0 R57  
     689 [-]: MOVE R0 R71  
     690 [-]: MOVE R1 R41  
     691 [-]: MOVE R1 R45  
     692 [-]: MOVE R1 R17  
     693 [-]: MOVE R1 R42  
     694 [-]: MOVE R1 R13  
     695 [-]: MOVE R0 R43  
     696 [-]: MOVE R0 R88  
     697 [-]: MOVE R1 R36  
     698 [-]: MOVE R1 R38  
     699 [-]: MOVE R1 R37  
     700 [-]: MOVE R1 R39  
     701 [-]: MOVE R1 R25  
     702 [-]: MOVE R1 R12  
     703 [-]: MOVE R0 R85  
     704 [-]: MOVE R1 R21  
     705 [-]: MOVE R1 R20  
     706 [-]: MOVE R0 R80  
     707 [-]: MOVE R1 R19  
     708 [-]: MOVE R1 R22  
     709 [-]: MOVE R0 R2   
     710 [-]: MOVE R0 R10  
     711 [-]: MOVE R0 R59  
     712 [-]: MOVE R0 R3   
     713 [-]: MOVE R0 R4   
     714 [-]: MOVE R1 R40  
     715 [-]: MOVE R1 R51  
     716 [-]: MOVE R0 R58  
     717 [-]: MOVE R1 R50  
     718 [-]: MOVE R0 R7   
     719 [-]: MOVE R1 R35  
     720 [-]: MOVE R0 R63  
     721 [-]: MOVE R1 R32  
     722 [-]: MOVE R1 R46  
     723 [-]: MOVE R1 R23  
     724 [-]: NEWCLOSURE R101 P53
     725 [-]: MOVE R1 R14  
     726 [-]: MOVE R0 R6   
     727 [-]: MOVE R0 R99  
     728 [-]: MOVE R1 R13  
     729 [-]: MOVE R0 R8   
     730 [-]: MOVE R0 R98  
     731 [-]: MOVE R1 R15  
     732 [-]: MOVE R0 R100 
     733 [-]: SETGLOBAL R101 K191 ["Mission"]
     734 [-]: DUPCLOSURE R101 K192 []
     735 [-]: MOVE R0 R72  
     736 [-]: SETGLOBAL R101 K193 ["OnLevelLoaded"]
     737 [-]: DUPCLOSURE R101 K194 []
     738 [-]: MOVE R0 R60  
     739 [-]: MOVE R0 R80  
     740 [-]: SETGLOBAL R101 K195 ["NarmerSaveTutorial"]
     741 [-]: DUPCLOSURE R101 K196 []
     742 [-]: SETGLOBAL R101 K197 ["StopTimeScriptTrigger"]
     743 [-]: DUPCLOSURE R101 K198 []
     744 [-]: SETGLOBAL R101 K199 ["RestartTimeTest"]
     745 [-]: DUPCLOSURE R101 K200 []
     746 [-]: SETGLOBAL R101 K201 ["FreezeDebris"]
     747 [-]: CLOSEUPVALS R12
     748 [-]: RETURN R0 0  


; Name:            
; Defined at line: 227
; #Upvalues:       1
; #Parameters:     1
; Is_vararg:       0
; Max Stack Size:  5

       0 [-]: GETUPVAL R3 0
       1 [-]: GETTABLE R2 R3 R0
       2 [-]: FASTCALL1 62 R2 L0
       3 [-]: GETIMPORT R1 1 [0x7B998233]
       4 [-]: CALL R1 1 1  
L 0:   5 [-]: JUMPIFNOT R1 L1
       6 [-]: RETURN R0 0  
L 1:   7 [-]: LOADN R1 0   
       8 [-]: JUMPIFNOTLT R1 R0 L3
       9 [-]: GETUPVAL R4 0
      10 [-]: GETTABLE R3 R4 R0
      11 [-]: GETTABLEKS R2 R3 K2 ["startF"]
      12 [-]: FASTCALL1 62 R2 L2
      13 [-]: GETIMPORT R1 1 [0x7B998233]
      14 [-]: CALL R1 1 1  
L 2:  15 [-]: JUMPIF R1 L3 
      16 [-]: GETUPVAL R3 0
      17 [-]: GETTABLE R2 R3 R0
      18 [-]: GETTABLEKS R1 R2 K2 ["startF"]
      19 [-]: LOADK R3 K3 ["TriggerPort"]
      20 [-]: NAMECALL R1 R1 K4 [0x8EB2112D]
      21 [-]: CALL R1 2 0  
L 3:  22 [-]: RETURN R0 0  


; Name:            
; Defined at line: 237
; #Upvalues:       1
; #Parameters:     1
; Is_vararg:       0
; Max Stack Size:  5

       0 [-]: GETUPVAL R3 0
       1 [-]: GETTABLE R2 R3 R0
       2 [-]: FASTCALL1 62 R2 L0
       3 [-]: GETIMPORT R1 1 [0x7B998233]
       4 [-]: CALL R1 1 1  
L 0:   5 [-]: JUMPIFNOT R1 L1
       6 [-]: RETURN R0 0  
L 1:   7 [-]: LOADN R1 0   
       8 [-]: JUMPIFNOTLT R1 R0 L3
       9 [-]: GETUPVAL R4 0
      10 [-]: GETTABLE R3 R4 R0
      11 [-]: GETTABLEKS R2 R3 K2 ["endF"]
      12 [-]: FASTCALL1 62 R2 L2
      13 [-]: GETIMPORT R1 1 [0x7B998233]
      14 [-]: CALL R1 1 1  
L 2:  15 [-]: JUMPIF R1 L3 
      16 [-]: GETUPVAL R3 0
      17 [-]: GETTABLE R2 R3 R0
      18 [-]: GETTABLEKS R1 R2 K2 ["endF"]
      19 [-]: LOADK R3 K3 ["TriggerPort"]
      20 [-]: NAMECALL R1 R1 K4 [0x8EB2112D]
      21 [-]: CALL R1 2 0  
L 3:  22 [-]: RETURN R0 0  


; Name:            
; Defined at line: 247
; #Upvalues:       1
; #Parameters:     0
; Is_vararg:       0
; Max Stack Size:  12

       0 [-]: LOADN R2 1   
       1 [-]: GETUPVAL R3 0
       2 [-]: LENGTH R0 R3 
       3 [-]: LOADN R1 1   
       4 [-]: FORNPREP R0 L3
L 0:   5 [-]: GETUPVAL R5 0
       6 [-]: GETTABLE R4 R5 R2
       7 [-]: FASTCALL1 62 R4 L1
       8 [-]: GETIMPORT R3 1 [0x7B998233]
       9 [-]: CALL R3 1 1  
L 1:  10 [-]: JUMPIF R3 L2 
      11 [-]: GETUPVAL R4 0
      12 [-]: GETTABLE R3 R4 R2
      13 [-]: GETIMPORT R4 3 [0x89326C93]
      14 [-]: GETIMPORT R6 5 [0x0469F296]
      15 [-]: GETUPVAL R11 0
      16 [-]: GETTABLE R10 R11 R2
      17 [-]: GETTABLEKS R8 R10 K6 ["name"]
      18 [-]: LOADK R9 K7 ["Start"]
      19 [-]: CONCAT R7 R8 R9
      20 [-]: CALL R6 1 -1 
      21 [-]: NAMECALL R4 R4 K8 [0x46A0EBF5]
      22 [-]: CALL R4 -1 1 
      23 [-]: SETTABLEKS R4 R3 K9 ["startF"]
      24 [-]: GETUPVAL R4 0
      25 [-]: GETTABLE R3 R4 R2
      26 [-]: GETIMPORT R4 3 [0x89326C93]
      27 [-]: GETIMPORT R6 5 [0x0469F296]
      28 [-]: GETUPVAL R11 0
      29 [-]: GETTABLE R10 R11 R2
      30 [-]: GETTABLEKS R8 R10 K6 ["name"]
      31 [-]: LOADK R9 K10 ["Ended"]
      32 [-]: CONCAT R7 R8 R9
      33 [-]: CALL R6 1 -1 
      34 [-]: NAMECALL R4 R4 K8 [0x46A0EBF5]
      35 [-]: CALL R4 -1 1 
      36 [-]: SETTABLEKS R4 R3 K11 ["endF"]
L 2:  37 [-]: FORNLOOP R0 L0
L 3:  38 [-]: RETURN R0 0  


; Name:            
; Defined at line: 257
; #Upvalues:       1
; #Parameters:     1
; Is_vararg:       0
; Max Stack Size:  4

       0 [-]: GETUPVAL R2 0
       1 [-]: FASTCALL1 62 R2 L0
       2 [-]: GETIMPORT R1 1 [0x7B998233]
       3 [-]: CALL R1 1 1  
L 0:   4 [-]: JUMPIF R1 L3 
       5 [-]: JUMPIFNOT R0 L2
       6 [-]: GETUPVAL R1 0
       7 [-]: NAMECALL R1 R1 K2 [0xF37943FF]
       8 [-]: CALL R1 1 1  
       9 [-]: JUMPIFNOT R1 L1
      10 [-]: GETUPVAL R1 0
      11 [-]: LOADK R3 K3 ["Disable"]
      12 [-]: NAMECALL R1 R1 K4 [0x8EB2112D]
      13 [-]: CALL R1 2 0  
L 1:  14 [-]: LOADNIL R1   
      15 [-]: SETUPVAL R1 0
      16 [-]: RETURN R0 0  
L 2:  17 [-]: GETUPVAL R1 0
      18 [-]: NAMECALL R1 R1 K5 [0xA2880940]
      19 [-]: CALL R1 1 0  
L 3:  20 [-]: RETURN R0 0  


; Name:            
; Defined at line: 271
; #Upvalues:       1
; #Parameters:     2
; Is_vararg:       0
; Max Stack Size:  8

       0 [-]: ORK R1 R1 K0 [false]
       1 [-]: GETIMPORT R2 2 [0x89326C93]
       2 [-]: MOVE R4 R0   
       3 [-]: NAMECALL R2 R2 K3 [0x46A0EBF5]
       4 [-]: CALL R2 2 1  
       5 [-]: FASTCALL1 62 R2 L0
       6 [-]: MOVE R4 R2   
       7 [-]: GETIMPORT R3 5 [0x7B998233]
       8 [-]: CALL R3 1 1  
L 0:   9 [-]: JUMPIF R3 L3 
      10 [-]: GETIMPORT R5 7 [0xBB76409B]
      11 [-]: NAMECALL R3 R2 K8 [0xF2DEAF69]
      12 [-]: CALL R3 2 1  
      13 [-]: JUMPIFNOT R3 L1
      14 [-]: SETUPVAL R2 0
      15 [-]: JUMP L2
     
L 1:  16 [-]: GETIMPORT R3 2 [0x89326C93]
      17 [-]: GETIMPORT R5 7 [0xBB76409B]
      18 [-]: NAMECALL R6 R2 K9 [0xD1586535]
      19 [-]: CALL R6 1 1  
      20 [-]: GETIMPORT R7 11 ["ZERO_ROTATION"]
      21 [-]: NAMECALL R3 R3 K12 [0x05909209]
      22 [-]: CALL R3 4 1  
      23 [-]: SETUPVAL R3 0
L 2:  24 [-]: GETUPVAL R3 0
      25 [-]: NAMECALL R3 R3 K13 [0xF37943FF]
      26 [-]: CALL R3 1 1  
      27 [-]: JUMPIF R3 L3 
      28 [-]: JUMPIF R1 L3 
      29 [-]: GETUPVAL R3 0
      30 [-]: LOADK R5 K14 ["Enable"]
      31 [-]: NAMECALL R3 R3 K15 [0x8EB2112D]
      32 [-]: CALL R3 2 0  
L 3:  33 [-]: RETURN R0 0  


; Name:            
; Defined at line: 287
; #Upvalues:       2
; #Parameters:     1
; Is_vararg:       0
; Max Stack Size:  4

       0 [-]: ORK R0 R0 K0 [2]
       1 [-]: GETUPVAL R2 0
       2 [-]: FASTCALL1 62 R2 L0
       3 [-]: GETIMPORT R1 2 [0x7B998233]
       4 [-]: CALL R1 1 1  
L 0:   5 [-]: JUMPIF R1 L2 
       6 [-]: GETUPVAL R2 1
       7 [-]: FASTCALL1 62 R2 L1
       8 [-]: GETIMPORT R1 2 [0x7B998233]
       9 [-]: CALL R1 1 1  
L 1:  10 [-]: JUMPIF R1 L2 
      11 [-]: GETUPVAL R1 1
      12 [-]: GETUPVAL R3 0
      13 [-]: NAMECALL R1 R1 K3 [0xBEBAD19F]
      14 [-]: CALL R1 2 1  
      15 [-]: JUMPIFNOTLE R1 R0 L2
      16 [-]: LOADB R1 1   
      17 [-]: RETURN R1 1  
L 2:  18 [-]: LOADB R1 0   
      19 [-]: RETURN R1 1  


; Name:            
; Defined at line: 297
; #Upvalues:       1
; #Parameters:     0
; Is_vararg:       0
; Max Stack Size:  6

       0 [-]: GETUPVAL R1 0
       1 [-]: FASTCALL1 62 R1 L0
       2 [-]: GETIMPORT R0 1 [0x7B998233]
       3 [-]: CALL R0 1 1  
L 0:   4 [-]: JUMPIF R0 L1 
       5 [-]: GETUPVAL R1 0
       6 [-]: NAMECALL R1 R1 K3 [0xB40C191A]
       7 [-]: CALL R1 1 1  
       8 [-]: MULK R0 R1 K2 [2]
       9 [-]: GETIMPORT R1 6 [0x35C16153]
      10 [-]: CALL R1 0 1  
      11 [-]: GETIMPORT R4 8 [0x7258F36F]
      12 [-]: MOVE R5 R0   
      13 [-]: CALL R4 1 -1 
      14 [-]: NAMECALL R2 R1 K9 [0xF326045F]
      15 [-]: CALL R2 -1 0 
      16 [-]: LOADN R4 17  
      17 [-]: LOADN R5 1   
      18 [-]: NAMECALL R2 R1 K10 [0x1586E35E]
      19 [-]: CALL R2 3 0  
      20 [-]: GETUPVAL R2 0
      21 [-]: MOVE R4 R1   
      22 [-]: NAMECALL R2 R2 K11 [0x479483BB]
      23 [-]: CALL R2 2 0  
L 1:  24 [-]: RETURN R0 0  


; Name:            
; Defined at line: 307
; #Upvalues:       1
; #Parameters:     1
; Is_vararg:       0
; Max Stack Size:  2

       0 [-]: JUMPXEQKN R0 K0 L0 [1]
       1 [-]: RETURN R0 0  
L 0:   2 [-]: GETUPVAL R1 0
       3 [-]: CALL R1 0 0  
       4 [-]: RETURN R0 0  


; Name:            
; Defined at line: 314
; #Upvalues:       9
; #Parameters:     2
; Is_vararg:       0
; Max Stack Size:  8

       0 [-]: GETUPVAL R3 1
       1 [-]: GETTABLEKS R2 R3 K0 [0xD2CED2F7]
       2 [-]: GETUPVAL R3 2
       3 [-]: MOVE R4 R0   
       4 [-]: MOVE R5 R1   
       5 [-]: LOADB R6 1   
       6 [-]: CALL R2 4 1  
       7 [-]: SETUPVAL R2 0
       8 [-]: GETUPVAL R3 0
       9 [-]: GETTABLEKS R2 R3 K1 ["avatar"]
      10 [-]: SETUPVAL R2 2
      11 [-]: GETUPVAL R3 0
      12 [-]: GETTABLEKS R2 R3 K2 ["canRespawn"]
      13 [-]: SETUPVAL R2 3
      14 [-]: GETUPVAL R3 0
      15 [-]: GETTABLEKS R2 R3 K3 ["avatarChanged"]
      16 [-]: JUMPIFNOT R2 L2
      17 [-]: GETUPVAL R2 2
      18 [-]: GETIMPORT R4 5 ["gLotusOperatorAvatarType"]
      19 [-]: NAMECALL R2 R2 K6 [0xF2DEAF69]
      20 [-]: CALL R2 2 1  
      21 [-]: JUMPIFNOT R2 L1
      22 [-]: GETUPVAL R2 4
      23 [-]: GETUPVAL R4 5
      24 [-]: GETTABLEKS R3 R4 K7 ["RESCUE_OSTRON"]
      25 [-]: JUMPIFNOTLE R2 R3 L0
      26 [-]: GETUPVAL R2 2
      27 [-]: NAMECALL R2 R2 K8 [0xDE321E6F]
      28 [-]: CALL R2 1 1  
      29 [-]: GETUPVAL R4 6
      30 [-]: LOADN R5 38  
      31 [-]: LOADN R6 4   
      32 [-]: LOADK R7 K9 [1.5]
      33 [-]: NAMECALL R2 R2 K10 [0xEADE8050]
      34 [-]: CALL R2 5 0  
      35 [-]: GETUPVAL R2 2
      36 [-]: NAMECALL R2 R2 K8 [0xDE321E6F]
      37 [-]: CALL R2 1 1  
      38 [-]: GETUPVAL R4 7
      39 [-]: LOADN R5 47  
      40 [-]: LOADN R6 4   
      41 [-]: LOADN R7 50  
      42 [-]: NAMECALL R2 R2 K10 [0xEADE8050]
      43 [-]: CALL R2 5 0  
      44 [-]: JUMP L2
     
L 0:  45 [-]: GETUPVAL R2 2
      46 [-]: NAMECALL R2 R2 K8 [0xDE321E6F]
      47 [-]: CALL R2 1 1  
      48 [-]: GETUPVAL R4 6
      49 [-]: LOADN R5 38  
      50 [-]: LOADN R6 4   
      51 [-]: LOADK R7 K9 [1.5]
      52 [-]: NAMECALL R2 R2 K11 [0x2722B5C3]
      53 [-]: CALL R2 5 0  
      54 [-]: GETUPVAL R2 2
      55 [-]: NAMECALL R2 R2 K8 [0xDE321E6F]
      56 [-]: CALL R2 1 1  
      57 [-]: GETUPVAL R4 7
      58 [-]: LOADN R5 47  
      59 [-]: LOADN R6 4   
      60 [-]: LOADN R7 50  
      61 [-]: NAMECALL R2 R2 K11 [0x2722B5C3]
      62 [-]: CALL R2 5 0  
      63 [-]: JUMP L2
     
L 1:  64 [-]: GETUPVAL R3 1
      65 [-]: GETTABLEKS R2 R3 K12 [0xA7218ED7]
      66 [-]: GETUPVAL R3 2
      67 [-]: GETIMPORT R4 14 [0x88A5A38E]
      68 [-]: GETUPVAL R5 8
      69 [-]: CALL R2 3 0  
L 2:  70 [-]: GETUPVAL R3 0
      71 [-]: GETTABLEKS R2 R3 K3 ["avatarChanged"]
      72 [-]: RETURN R2 1  


; Name:            
; Defined at line: 339
; #Upvalues:       0
; #Parameters:     0
; Is_vararg:       0
; Max Stack Size:  5

       0 [-]: GETIMPORT R0 1 [0x0469F296]
       1 [-]: LOADK R1 K2 ["ActThreeBeanstalks"]
       2 [-]: CALL R0 1 1  
       3 [-]: GETIMPORT R1 4 [0x7ED0A956]
       4 [-]: LOADK R2 K5 ["/Lotus/Levels/Proc/TheNewWar/PartThree/TNWUnumTower"]
       5 [-]: CALL R1 1 1  
       6 [-]: GETIMPORT R2 7 [0xBE190284]
       7 [-]: NAMECALL R2 R2 K8 [0xEF893AEC]
       8 [-]: CALL R2 1 1  
       9 [-]: FASTCALL1 62 R2 L0
      10 [-]: MOVE R4 R2   
      11 [-]: GETIMPORT R3 10 [0x7B998233]
      12 [-]: CALL R3 1 1  
L 0:  13 [-]: JUMPIF R3 L3 
      14 [-]: GETTABLEKS R4 R2 K11 ["levelOverride"]
      15 [-]: FASTCALL1 62 R4 L1
      16 [-]: GETIMPORT R3 10 [0x7B998233]
      17 [-]: CALL R3 1 1  
L 1:  18 [-]: JUMPIF R3 L3 
      19 [-]: GETTABLEKS R3 R2 K11 ["levelOverride"]
      20 [-]: JUMPIFNOTEQ R3 R1 L3
      21 [-]: GETTABLEKS R4 R2 K12 ["goalTag"]
      22 [-]: FASTCALL1 62 R4 L2
      23 [-]: GETIMPORT R3 10 [0x7B998233]
      24 [-]: CALL R3 1 1  
L 2:  25 [-]: JUMPIF R3 L3 
      26 [-]: GETTABLEKS R3 R2 K12 ["goalTag"]
      27 [-]: JUMPIFEQ R3 R0 L4
L 3:  28 [-]: LOADB R3 0   
      29 [-]: RETURN R3 1  
L 4:  30 [-]: LOADB R3 1   
      31 [-]: RETURN R3 1  


; Name:            
; Defined at line: 353
; #Upvalues:       3
; #Parameters:     0
; Is_vararg:       0
; Max Stack Size:  4

       0 [-]: GETIMPORT R0 1 ["_T"]
       1 [-]: LOADNIL R1   
       2 [-]: SETTABLEKS R1 R0 K2 ["PreCheckpointRespawn"]
       3 [-]: GETIMPORT R0 1 ["_T"]
       4 [-]: LOADNIL R1   
       5 [-]: SETTABLEKS R1 R0 K3 ["PostCheckpointRespawn"]
       6 [-]: GETUPVAL R1 0
       7 [-]: GETTABLEKS R0 R1 K4 [0x7D717F70]
       8 [-]: GETIMPORT R1 6 [0xB009BBC6]
       9 [-]: GETUPVAL R2 1
      10 [-]: CALL R1 1 1  
      11 [-]: GETUPVAL R2 2
      12 [-]: CALL R0 2 0  
      13 [-]: GETIMPORT R0 8 [0x89326C93]
      14 [-]: GETIMPORT R2 10 [0x0469F296]
      15 [-]: LOADK R3 K11 ["LoadNextLevel"]
      16 [-]: CALL R2 1 -1 
      17 [-]: NAMECALL R0 R0 K12 [0x46A0EBF5]
      18 [-]: CALL R0 -1 1 
      19 [-]: FASTCALL1 62 R0 L0
      20 [-]: MOVE R2 R0   
      21 [-]: GETIMPORT R1 14 [0x7B998233]
      22 [-]: CALL R1 1 1  
L 0:  23 [-]: JUMPIF R1 L1 
      24 [-]: GETIMPORT R1 16 [0x3D106989]
      25 [-]: LOADK R2 K17 ["Loading next mission..."]
      26 [-]: CALL R1 1 0  
      27 [-]: LOADK R3 K18 ["Execute"]
      28 [-]: NAMECALL R1 R0 K19 [0x8EB2112D]
      29 [-]: CALL R1 2 0  
L 1:  30 [-]: RETURN R0 0  


; Name:            
; Defined at line: 366
; #Upvalues:       5
; #Parameters:     0
; Is_vararg:       0
; Max Stack Size:  5

       0 [-]: GETUPVAL R0 0
       1 [-]: LOADB R1 1   
       2 [-]: CALL R0 1 0  
       3 [-]: GETUPVAL R0 1
       4 [-]: NAMECALL R0 R0 K0 [0xDE321E6F]
       5 [-]: CALL R0 1 1  
       6 [-]: GETUPVAL R1 2
       7 [-]: JUMPIF R1 L0 
       8 [-]: LOADB R1 1   
       9 [-]: SETUPVAL R1 2
      10 [-]: GETUPVAL R1 1
      11 [-]: NAMECALL R1 R1 K1 [0x5E651723]
      12 [-]: CALL R1 1 1  
      13 [-]: NAMECALL R1 R1 K2 [0x3F256C8B]
      14 [-]: CALL R1 1 1  
      15 [-]: NAMECALL R2 R1 K3 [0x251A4B14]
      16 [-]: CALL R2 1 0  
      17 [-]: MOVE R4 R1   
      18 [-]: NAMECALL R2 R0 K4 [0x1D2DFE4A]
      19 [-]: CALL R2 2 0  
L 0:  20 [-]: GETUPVAL R2 3
      21 [-]: GETTABLEKS R1 R2 K5 [0xA7218ED7]
      22 [-]: GETUPVAL R2 1
      23 [-]: GETIMPORT R3 7 [0x88A5A38E]
      24 [-]: GETUPVAL R4 4
      25 [-]: CALL R1 3 0  
      26 [-]: RETURN R0 0  


; Name:            
; Defined at line: 381
; #Upvalues:       1
; #Parameters:     3
; Is_vararg:       0
; Max Stack Size:  9

       0 [-]: ORK R1 R1 K0 [5]
       1 [-]: MOVE R3 R2   
       2 [-]: JUMPIF R3 L0 
       3 [-]: GETUPVAL R3 0
L 0:   4 [-]: MOVE R2 R3   
       5 [-]: GETIMPORT R3 2 [0x89326C93]
       6 [-]: MOVE R5 R0   
       7 [-]: NAMECALL R3 R3 K3 [0x46A0EBF5]
       8 [-]: CALL R3 2 1  
       9 [-]: FASTCALL1 62 R3 L1
      10 [-]: MOVE R5 R3   
      11 [-]: GETIMPORT R4 5 [0x7B998233]
      12 [-]: CALL R4 1 1  
L 1:  13 [-]: JUMPIF R4 L3 
      14 [-]: FASTCALL1 62 R2 L2
      15 [-]: MOVE R5 R2   
      16 [-]: GETIMPORT R4 5 [0x7B998233]
      17 [-]: CALL R4 1 1  
L 2:  18 [-]: JUMPIF R4 L3 
      19 [-]: MOVE R6 R3   
      20 [-]: NAMECALL R4 R2 K6 [0x9B2E6C87]
      21 [-]: CALL R4 2 1  
      22 [-]: MUL R5 R1 R1 
      23 [-]: JUMPIFNOTLT R5 R4 L3
      24 [-]: NAMECALL R6 R3 K7 [0xD1586535]
      25 [-]: CALL R6 1 1  
      26 [-]: NAMECALL R7 R2 K8 [0xCB3851B8]
      27 [-]: CALL R7 1 -1 
      28 [-]: NAMECALL R4 R2 K9 [0x589EF1C1]
      29 [-]: CALL R4 -1 0 
L 3:  30 [-]: RETURN R0 0  


; Name:            
; Defined at line: 391
; #Upvalues:       3
; #Parameters:     0
; Is_vararg:       0
; Max Stack Size:  8

       0 [-]: GETUPVAL R0 0
       1 [-]: JUMPIF R0 L0 
       2 [-]: GETIMPORT R0 1 [0x89326C93]
       3 [-]: GETIMPORT R2 3 [0x0469F296]
       4 [-]: LOADK R3 K4 ["BalloonSpawner"]
       5 [-]: CALL R2 1 -1 
       6 [-]: NAMECALL R0 R0 K5 [0x46A0EBF5]
       7 [-]: CALL R0 -1 1 
L 0:   8 [-]: SETUPVAL R0 0
       9 [-]: LOADNIL R0   
      10 [-]: SETUPVAL R0 1
L 1:  11 [-]: GETUPVAL R1 1
      12 [-]: FASTCALL1 62 R1 L2
      13 [-]: GETIMPORT R0 7 [0x7B998233]
      14 [-]: CALL R0 1 1  
L 2:  15 [-]: JUMPIFNOT R0 L3
      16 [-]: GETUPVAL R1 0
      17 [-]: NAMECALL R1 R1 K8 [0x90E142BA]
      18 [-]: CALL R1 1 1  
      19 [-]: GETTABLEN R0 R1 1
      20 [-]: NAMECALL R0 R0 K9 [0x1E3535E5]
      21 [-]: CALL R0 1 1  
      22 [-]: SETUPVAL R0 1
      23 [-]: GETIMPORT R0 11 [0xCBD666E1]
      24 [-]: LOADN R1 0   
      25 [-]: CALL R0 1 0  
      26 [-]: JUMPBACK L1  
L 3:  27 [-]: GETUPVAL R0 1
      28 [-]: LOADB R2 0   
      29 [-]: NAMECALL R0 R0 K12 [0xC4759C9F]
      30 [-]: CALL R0 2 0  
      31 [-]: GETUPVAL R0 1
      32 [-]: GETIMPORT R2 14 ["gContextActionType"]
      33 [-]: NAMECALL R0 R0 K15 [0xC1595BD5]
      34 [-]: CALL R0 2 1  
      35 [-]: GETIMPORT R1 17 [0x7ED0A956]
      36 [-]: LOADK R2 K18 ["/Lotus/Types/Vehicles/TNWBalloon/UseBalloon"]
      37 [-]: CALL R1 1 1  
      38 [-]: FASTCALL1 62 R0 L4
      39 [-]: MOVE R3 R0   
      40 [-]: GETIMPORT R2 7 [0x7B998233]
      41 [-]: CALL R2 1 1  
L 4:  42 [-]: JUMPIF R2 L8 
      43 [-]: LOADN R4 1   
      44 [-]: LENGTH R2 R0 
      45 [-]: LOADN R3 1   
      46 [-]: FORNPREP R2 L8
L 5:  47 [-]: GETTABLE R6 R0 R4
      48 [-]: FASTCALL1 62 R6 L6
      49 [-]: GETIMPORT R5 7 [0x7B998233]
      50 [-]: CALL R5 1 1  
L 6:  51 [-]: JUMPIF R5 L7 
      52 [-]: GETTABLE R5 R0 R4
      53 [-]: MOVE R7 R1   
      54 [-]: NAMECALL R5 R5 K19 [0xF2DEAF69]
      55 [-]: CALL R5 2 1  
      56 [-]: JUMPIFNOT R5 L7
      57 [-]: GETTABLE R5 R0 R4
      58 [-]: SETUPVAL R5 2
      59 [-]: GETIMPORT R5 21 [0x11A19C5E]
      60 [-]: GETUPVAL R6 2
      61 [-]: LOADK R7 K22 ["OnActivated"]
      62 [-]: CALL R5 2 0  
      63 [-]: RETURN R0 0  
L 7:  64 [-]: FORNLOOP R2 L5
L 8:  65 [-]: RETURN R0 0  


; Name:            
; Defined at line: 416
; #Upvalues:       2
; #Parameters:     0
; Is_vararg:       0
; Max Stack Size:  4

       0 [-]: GETUPVAL R1 0
       1 [-]: GETTABLEKS R0 R1 K0 [0x9742B85B]
       2 [-]: GETIMPORT R1 2 [0xE91D7466]
       3 [-]: GETUPVAL R3 1
       4 [-]: GETTABLEKS R2 R3 K3 ["introOrdis"]
       5 [-]: CALL R0 2 0  
       6 [-]: RETURN R0 0  


; Name:            
; Defined at line: 420
; #Upvalues:       3
; #Parameters:     0
; Is_vararg:       0
; Max Stack Size:  4

       0 [-]: LOADB R0 1   
       1 [-]: SETUPVAL R0 0
       2 [-]: GETUPVAL R1 1
       3 [-]: GETTABLEKS R0 R1 K0 [0x9742B85B]
       4 [-]: GETIMPORT R1 2 [0xE91D7466]
       5 [-]: GETUPVAL R3 2
       6 [-]: GETTABLEKS R2 R3 K3 ["konzuFlyTenno"]
       7 [-]: CALL R0 2 0  
       8 [-]: RETURN R0 0  


; Name:            
; Defined at line: 425
; #Upvalues:       0
; #Parameters:     2
; Is_vararg:       0
; Max Stack Size:  11

       0 [-]: LOADB R2 0   
L 0:   1 [-]: FASTCALL1 62 R0 L1
       2 [-]: MOVE R4 R0   
       3 [-]: GETIMPORT R3 1 [0x7B998233]
       4 [-]: CALL R3 1 1  
L 1:   5 [-]: JUMPIF R3 L4 
       6 [-]: MOVE R5 R0   
       7 [-]: NAMECALL R3 R1 K2 [0x13D5D3FB]
       8 [-]: CALL R3 2 1  
       9 [-]: JUMPIFNOT R3 L4
      10 [-]: GETIMPORT R5 4 ["gLotusOperatorAvatarType"]
      11 [-]: NAMECALL R3 R0 K5 [0xF2DEAF69]
      12 [-]: CALL R3 2 1  
      13 [-]: JUMPIF R3 L2 
      14 [-]: JUMPIF R2 L2 
      15 [-]: GETIMPORT R3 8 ["ShowImpactMessage"]
      16 [-]: GETIMPORT R4 10 [0x603636AD]
      17 [-]: LOADK R5 K11 ["/Lotus/Language/NewWar/P3M2CaveEntranceHint"]
      18 [-]: NEWTABLE R6 0 0
      19 [-]: CALL R4 2 1  
      20 [-]: LOADN R5 -1  
      21 [-]: LOADB R6 1   
      22 [-]: LOADNIL R7   
      23 [-]: LOADB R8 0   
      24 [-]: LOADNIL R9   
      25 [-]: LOADN R10 3  
      26 [-]: CALL R3 7 0  
      27 [-]: LOADB R2 1   
      28 [-]: JUMP L3
     
L 2:  29 [-]: GETIMPORT R5 4 ["gLotusOperatorAvatarType"]
      30 [-]: NAMECALL R3 R0 K5 [0xF2DEAF69]
      31 [-]: CALL R3 2 1  
      32 [-]: JUMPIFNOT R3 L3
      33 [-]: JUMPIFNOT R2 L3
      34 [-]: GETIMPORT R3 13 ["HideImpactMessage"]
      35 [-]: CALL R3 0 0  
L 3:  36 [-]: GETIMPORT R3 15 [0xCBD666E1]
      37 [-]: LOADN R4 0   
      38 [-]: CALL R3 1 0  
      39 [-]: GETIMPORT R3 17 [0x89326C93]
      40 [-]: NAMECALL R3 R3 K18 [0x78298275]
      41 [-]: CALL R3 1 1  
      42 [-]: MOVE R0 R3   
      43 [-]: JUMPBACK L0  
L 4:  44 [-]: GETIMPORT R3 13 ["HideImpactMessage"]
      45 [-]: CALL R3 0 0  
      46 [-]: RETURN R0 0  


; Name:            
; Defined at line: 450
; #Upvalues:       1
; #Parameters:     1
; Is_vararg:       0
; Max Stack Size:  7

       0 [-]: ORK R0 R0 K0 [""]
       1 [-]: GETUPVAL R2 0
       2 [-]: FASTCALL1 62 R2 L0
       3 [-]: GETIMPORT R1 2 [0x7B998233]
       4 [-]: CALL R1 1 1  
L 0:   5 [-]: JUMPIF R1 L1 
       6 [-]: GETUPVAL R2 0
       7 [-]: GETTABLEKS R1 R2 K3 ["AddIcon"]
       8 [-]: GETIMPORT R2 5 [0xEF1254DE]
       9 [-]: DUPTABLE R3 10
      10 [-]: LOADN R4 24  
      11 [-]: SETTABLEKS R4 R3 K6 ["Width"]
      12 [-]: LOADN R4 24  
      13 [-]: SETTABLEKS R4 R3 K7 ["Height"]
      14 [-]: LOADK R5 K11 ["     "]
      15 [-]: MOVE R6 R0   
      16 [-]: CONCAT R4 R5 R6
      17 [-]: SETTABLEKS R4 R3 K8 ["Label"]
      18 [-]: LOADN R4 38  
      19 [-]: SETTABLEKS R4 R3 K9 ["Color"]
      20 [-]: CALL R1 2 0  
L 1:  21 [-]: RETURN R0 0  


; Name:            
; Defined at line: 457
; #Upvalues:       6
; #Parameters:     1
; Is_vararg:       0
; Max Stack Size:  10

       0 [-]: FASTCALL1 62 R0 L0
       1 [-]: MOVE R2 R0   
       2 [-]: GETIMPORT R1 1 [0x7B998233]
       3 [-]: CALL R1 1 1  
L 0:   4 [-]: JUMPIF R1 L9 
       5 [-]: GETUPVAL R1 0
       6 [-]: JUMPIF R1 L1 
       7 [-]: NEWTABLE R1 0 0
L 1:   8 [-]: SETUPVAL R1 0
       9 [-]: GETUPVAL R1 1
      10 [-]: JUMPIF R1 L2 
      11 [-]: NEWTABLE R1 0 0
L 2:  12 [-]: SETUPVAL R1 1
      13 [-]: GETUPVAL R2 0
      14 [-]: LENGTH R1 R2 
      15 [-]: LOADN R2 0   
      16 [-]: JUMPIFNOTLT R2 R1 L5
      17 [-]: LOADN R3 1   
      18 [-]: GETUPVAL R4 0
      19 [-]: LENGTH R1 R4 
      20 [-]: LOADN R2 1   
      21 [-]: FORNPREP R1 L5
L 3:  22 [-]: GETUPVAL R5 0
      23 [-]: GETTABLE R4 R5 R3
      24 [-]: JUMPIFNOTEQ R4 R0 L4
      25 [-]: GETIMPORT R4 3 [0x3D106989]
      26 [-]: NAMECALL R8 R0 K4 [0xE223E2B1]
      27 [-]: CALL R8 1 1  
      28 [-]: MOVE R6 R8   
      29 [-]: LOADK R7 K5 [" already is on the list! Don't add again"]
      30 [-]: CONCAT R5 R6 R7
      31 [-]: CALL R4 1 0  
      32 [-]: RETURN R0 0  
L 4:  33 [-]: FORNLOOP R1 L3
L 5:  34 [-]: GETUPVAL R2 0
      35 [-]: FASTCALL2 52 R2 R0 L6
      36 [-]: MOVE R3 R0   
      37 [-]: GETIMPORT R1 8 [0x23D5322F]
      38 [-]: CALL R1 2 0  
L 6:  39 [-]: GETUPVAL R2 1
      40 [-]: FASTCALL2K 52 R2 K9 L7 [false]
      41 [-]: LOADK R3 K9 [false]
      42 [-]: GETIMPORT R1 8 [0x23D5322F]
      43 [-]: CALL R1 2 0  
L 7:  44 [-]: GETIMPORT R3 11 [0xBB76409B]
      45 [-]: GETIMPORT R4 13 ["EMPTY_SYMBOL"]
      46 [-]: GETIMPORT R5 15 [0xA421AF95]
      47 [-]: LOADN R6 0   
      48 [-]: LOADN R7 0   
      49 [-]: LOADN R8 0   
      50 [-]: CALL R5 3 1  
      51 [-]: GETIMPORT R6 17 ["ZERO_ROTATION"]
      52 [-]: NAMECALL R1 R0 K18 [0x47901F07]
      53 [-]: CALL R1 5 0  
      54 [-]: GETUPVAL R3 2
      55 [-]: NAMECALL R1 R0 K19 [0xEF77C6EF]
      56 [-]: CALL R1 2 0  
      57 [-]: NAMECALL R1 R0 K20 [0x1AC1655C]
      58 [-]: CALL R1 1 1  
      59 [-]: LOADN R3 15  
      60 [-]: GETIMPORT R4 22 [0x0469F296]
      61 [-]: LOADK R5 K23 ["OstronAntiOperatorProc"]
      62 [-]: CALL R4 1 -1 
      63 [-]: NAMECALL R1 R1 K24 [0xAA0FAA2C]
      64 [-]: CALL R1 -1 0 
      65 [-]: GETUPVAL R1 3
      66 [-]: LOADN R2 1   
      67 [-]: JUMPIFNOTLT R2 R1 L9
      68 [-]: GETUPVAL R1 4
      69 [-]: GETIMPORT R2 26 [0x603636AD]
      70 [-]: GETIMPORT R3 28 [0x64FB1586]
      71 [-]: NAMECALL R4 R0 K29 [0xAF8359C4]
      72 [-]: CALL R4 1 -1 
      73 [-]: CALL R3 -1 1 
      74 [-]: LOADNIL R4   
      75 [-]: CALL R2 2 -1 
      76 [-]: CALL R1 -1 0 
      77 [-]: GETUPVAL R2 5
      78 [-]: FASTCALL1 62 R2 L8
      79 [-]: GETIMPORT R1 1 [0x7B998233]
      80 [-]: CALL R1 1 1  
L 8:  81 [-]: JUMPIF R1 L9 
      82 [-]: GETUPVAL R2 5
      83 [-]: GETTABLEKS R1 R2 K30 ["List"]
      84 [-]: LOADNIL R3   
      85 [-]: LOADB R4 1   
      86 [-]: LOADB R5 1   
      87 [-]: NAMECALL R1 R1 K31 [0x71E9AC81]
      88 [-]: CALL R1 4 0  
L 9:  89 [-]: RETURN R0 0  


; Name:            
; Defined at line: 485
; #Upvalues:       3
; #Parameters:     1
; Is_vararg:       0
; Max Stack Size:  7

       0 [-]: GETIMPORT R1 2 ["AddHudTracker"]
       1 [-]: LOADK R2 K3 ["RescueOstronPanelStatus"]
       2 [-]: GETUPVAL R4 1
       3 [-]: GETTABLEKS R3 R4 K4 ["HT_ICON_BAR"]
       4 [-]: LOADK R4 K5 [0.10000000000000001]
       5 [-]: LOADB R5 0   
       6 [-]: LOADB R6 0   
       7 [-]: CALL R1 5 1  
       8 [-]: SETUPVAL R1 0
       9 [-]: GETUPVAL R2 0
      10 [-]: GETTABLEKS R1 R2 K6 ["List"]
      11 [-]: LOADN R2 20  
      12 [-]: SETTABLEKS R2 R1 K7 ["mForcedVerticalSeparation"]
      13 [-]: GETUPVAL R2 0
      14 [-]: GETTABLEKS R1 R2 K6 ["List"]
      15 [-]: LOADN R2 0   
      16 [-]: SETTABLEKS R2 R1 K8 ["mForcedHorizontalSeparation"]
      17 [-]: GETUPVAL R2 0
      18 [-]: GETTABLEKS R1 R2 K9 ["SetOffset"]
      19 [-]: LOADN R2 0   
      20 [-]: LOADN R3 22  
      21 [-]: CALL R1 2 0  
      22 [-]: LOADN R3 1   
      23 [-]: LENGTH R1 R0 
      24 [-]: LOADN R2 1   
      25 [-]: FORNPREP R1 L1
L 0:  26 [-]: GETUPVAL R4 2
      27 [-]: GETTABLE R5 R0 R3
      28 [-]: CALL R4 1 0  
      29 [-]: FORNLOOP R1 L0
L 1:  30 [-]: GETUPVAL R2 0
      31 [-]: GETTABLEKS R1 R2 K10 ["SetCustomDrawFunction"]
      32 [-]: DUPCLOSURE R2 K11 []
      33 [-]: CALL R1 1 0  
      34 [-]: GETUPVAL R2 0
      35 [-]: GETTABLEKS R1 R2 K6 ["List"]
      36 [-]: NAMECALL R1 R1 K12 [0x71E9AC81]
      37 [-]: CALL R1 1 0  
      38 [-]: RETURN R0 0  


; Name:            
; Defined at line: 507
; #Upvalues:       1
; #Parameters:     1
; Is_vararg:       0
; Max Stack Size:  6

       0 [-]: FASTCALL1 62 R0 L0
       1 [-]: MOVE R2 R0   
       2 [-]: GETIMPORT R1 1 [0x7B998233]
       3 [-]: CALL R1 1 1  
L 0:   4 [-]: JUMPIF R1 L1 
       5 [-]: NAMECALL R1 R0 K2 [0x2047CFE7]
       6 [-]: CALL R1 1 1  
       7 [-]: JUMPIFNOT R1 L5
L 1:   8 [-]: LOADK R1 K3 ["wasn't properly saved. Killed or destroyed!"]
       9 [-]: FASTCALL1 62 R0 L2
      10 [-]: MOVE R5 R0   
      11 [-]: GETIMPORT R4 1 [0x7B998233]
      12 [-]: CALL R4 1 1  
L 2:  13 [-]: JUMPIFNOT R4 L3
      14 [-]: LOADK R2 K4 ["Avatar "]
      15 [-]: JUMP L4
     
L 3:  16 [-]: NAMECALL R4 R0 K5 [0xE223E2B1]
      17 [-]: CALL R4 1 1  
      18 [-]: MOVE R2 R4   
L 4:  19 [-]: MOVE R3 R1   
      20 [-]: CONCAT R1 R2 R3
      21 [-]: GETIMPORT R2 7 [0x3D106989]
      22 [-]: MOVE R3 R1   
      23 [-]: CALL R2 1 0  
      24 [-]: LOADB R2 1   
      25 [-]: RETURN R2 1  
L 5:  26 [-]: GETUPVAL R3 0
      27 [-]: NAMECALL R1 R0 K8 [0xAC99E72C]
      28 [-]: CALL R1 2 1  
      29 [-]: JUMPIF R1 L6 
      30 [-]: LOADB R2 0   
      31 [-]: RETURN R2 1  
L 6:  32 [-]: GETUPVAL R4 0
      33 [-]: NAMECALL R2 R0 K9 [0xA088430F]
      34 [-]: CALL R2 2 1  
      35 [-]: RETURN R2 1  


; Name:            
; Defined at line: 526
; #Upvalues:       1
; #Parameters:     0
; Is_vararg:       0
; Max Stack Size:  5

       0 [-]: LOADN R2 1   
       1 [-]: GETUPVAL R3 0
       2 [-]: LENGTH R0 R3 
       3 [-]: LOADN R1 1   
       4 [-]: FORNPREP R0 L2
L 0:   5 [-]: GETUPVAL R4 0
       6 [-]: GETTABLE R3 R4 R2
       7 [-]: JUMPIF R3 L1 
       8 [-]: LOADB R3 0   
       9 [-]: RETURN R3 1  
L 1:  10 [-]: FORNLOOP R0 L0
L 2:  11 [-]: LOADB R0 1   
      12 [-]: RETURN R0 1  


; Name:            
; Defined at line: 536
; #Upvalues:       3
; #Parameters:     1
; Is_vararg:       0
; Max Stack Size:  10

       0 [-]: GETUPVAL R2 0
       1 [-]: FASTCALL1 62 R2 L0
       2 [-]: GETIMPORT R1 1 [0x7B998233]
       3 [-]: CALL R1 1 1  
L 0:   4 [-]: JUMPIFNOT R1 L1
       5 [-]: GETUPVAL R1 1
       6 [-]: CALL R1 0 0  
L 1:   7 [-]: GETIMPORT R1 3 [0x89326C93]
       8 [-]: MOVE R3 R0   
       9 [-]: NAMECALL R1 R1 K4 [0xC7FCADA9]
      10 [-]: CALL R1 2 1  
      11 [-]: FASTCALL1 62 R1 L2
      12 [-]: MOVE R3 R1   
      13 [-]: GETIMPORT R2 1 [0x7B998233]
      14 [-]: CALL R2 1 1  
L 2:  15 [-]: JUMPIF R2 L5 
      16 [-]: LENGTH R2 R1 
      17 [-]: LOADN R3 0   
      18 [-]: JUMPIFNOTLT R3 R2 L5
      19 [-]: GETIMPORT R2 6 [0xC8802016]
      20 [-]: MOVE R3 R1   
      21 [-]: CALL R2 1 3  
      22 [-]: FORGPREP_INEXT R2 L4
L 3:  23 [-]: GETUPVAL R7 2
      24 [-]: NAMECALL R8 R6 K7 [0x1E3535E5]
      25 [-]: CALL R8 1 -1 
      26 [-]: CALL R7 -1 0 
L 4:  27 [-]: FORGLOOP R2 L3 2 [inext]
L 5:  28 [-]: RETURN R0 0  


; Name:            
; Defined at line: 549
; #Upvalues:       8
; #Parameters:     1
; Is_vararg:       0
; Max Stack Size:  5

       0 [-]: GETUPVAL R2 0
       1 [-]: GETTABLEKS R1 R2 K0 [0xA1DF01D6]
       2 [-]: GETUPVAL R3 1
       3 [-]: GETTABLEKS R2 R3 K1 ["rescueOstron"]
       4 [-]: CALL R1 1 0  
       5 [-]: LOADB R1 1   
       6 [-]: SETUPVAL R1 2
       7 [-]: GETUPVAL R2 3
       8 [-]: GETTABLEKS R1 R2 K2 [0xC474A99E]
       9 [-]: GETIMPORT R2 4 [0x0469F296]
      10 [-]: LOADK R3 K5 ["AfterKonzuEvents"]
      11 [-]: CALL R2 1 1  
      12 [-]: LOADK R3 K6 ["TriggerPort"]
      13 [-]: CALL R1 2 0  
      14 [-]: GETUPVAL R2 4
      15 [-]: GETUPVAL R4 5
      16 [-]: GETTABLEKS R3 R4 K7 ["RESCUE_OSTRON"]
      17 [-]: GETTABLE R1 R2 R3
      18 [-]: GETIMPORT R2 4 [0x0469F296]
      19 [-]: LOADK R3 K8 ["AfterKonzuCheckpoint"]
      20 [-]: CALL R2 1 1  
      21 [-]: SETTABLEKS R2 R1 K9 ["respawnPt"]
      22 [-]: GETUPVAL R1 6
      23 [-]: GETUPVAL R3 7
      24 [-]: GETTABLE R2 R3 R0
      25 [-]: CALL R1 1 0  
      26 [-]: RETURN R0 0  


; Name:            
; Defined at line: 557
; #Upvalues:       13
; #Parameters:     0
; Is_vararg:       0
; Max Stack Size:  5

       0 [-]: GETIMPORT R0 1 [0xCBD666E1]
       1 [-]: LOADK R1 K2 [0.10000000000000001]
       2 [-]: CALL R0 1 0  
       3 [-]: NEWTABLE R0 0 0
       4 [-]: SETUPVAL R0 0
       5 [-]: NEWTABLE R0 0 0
       6 [-]: SETUPVAL R0 1
       7 [-]: GETUPVAL R1 2
       8 [-]: ADDK R0 R1 K3 [1]
       9 [-]: SETUPVAL R0 2
      10 [-]: GETUPVAL R0 2
      11 [-]: GETUPVAL R2 3
      12 [-]: LENGTH R1 R2 
      13 [-]: JUMPIFNOTLE R0 R1 L0
      14 [-]: GETUPVAL R0 2
      15 [-]: GETUPVAL R2 4
      16 [-]: GETTABLEKS R1 R2 K4 [0xA1DF01D6]
      17 [-]: GETUPVAL R3 5
      18 [-]: GETTABLEKS R2 R3 K5 ["rescueOstron"]
      19 [-]: CALL R1 1 0  
      20 [-]: LOADB R1 1   
      21 [-]: SETUPVAL R1 6
      22 [-]: GETUPVAL R2 7
      23 [-]: GETTABLEKS R1 R2 K6 [0xC474A99E]
      24 [-]: GETIMPORT R2 8 [0x0469F296]
      25 [-]: LOADK R3 K9 ["AfterKonzuEvents"]
      26 [-]: CALL R2 1 1  
      27 [-]: LOADK R3 K10 ["TriggerPort"]
      28 [-]: CALL R1 2 0  
      29 [-]: GETUPVAL R2 8
      30 [-]: GETUPVAL R4 9
      31 [-]: GETTABLEKS R3 R4 K11 ["RESCUE_OSTRON"]
      32 [-]: GETTABLE R1 R2 R3
      33 [-]: GETIMPORT R2 8 [0x0469F296]
      34 [-]: LOADK R3 K12 ["AfterKonzuCheckpoint"]
      35 [-]: CALL R2 1 1  
      36 [-]: SETTABLEKS R2 R1 K13 ["respawnPt"]
      37 [-]: GETUPVAL R1 10
      38 [-]: GETUPVAL R3 3
      39 [-]: GETTABLE R2 R3 R0
      40 [-]: CALL R1 1 0  
L 0:  41 [-]: GETIMPORT R0 1 [0xCBD666E1]
      42 [-]: LOADK R1 K14 [1.8999999999999999]
      43 [-]: CALL R0 1 0  
      44 [-]: GETIMPORT R0 17 ["PlayerSpotted"]
      45 [-]: JUMPIF R0 L1 
      46 [-]: GETUPVAL R1 11
      47 [-]: GETTABLEKS R0 R1 K18 [0x9742B85B]
      48 [-]: GETIMPORT R1 20 [0xE91D7466]
      49 [-]: GETUPVAL R3 12
      50 [-]: GETTABLEKS R2 R3 K21 ["konzuRescuedStart"]
      51 [-]: CALL R0 2 0  
      52 [-]: GETUPVAL R1 11
      53 [-]: GETTABLEKS R0 R1 K22 [0xFC87A231]
      54 [-]: CALL R0 0 0  
      55 [-]: GETIMPORT R0 17 ["PlayerSpotted"]
      56 [-]: JUMPIF R0 L1 
      57 [-]: GETUPVAL R1 11
      58 [-]: GETTABLEKS R0 R1 K23 [0x11DCFE97]
      59 [-]: GETUPVAL R2 12
      60 [-]: GETTABLEKS R1 R2 K24 ["operatorResponseToKonzu"]
      61 [-]: CALL R0 1 0  
      62 [-]: GETUPVAL R1 11
      63 [-]: GETTABLEKS R0 R1 K22 [0xFC87A231]
      64 [-]: CALL R0 0 0  
      65 [-]: GETIMPORT R0 17 ["PlayerSpotted"]
      66 [-]: JUMPIF R0 L1 
      67 [-]: GETUPVAL R1 11
      68 [-]: GETTABLEKS R0 R1 K18 [0x9742B85B]
      69 [-]: GETIMPORT R1 20 [0xE91D7466]
      70 [-]: GETUPVAL R3 12
      71 [-]: GETTABLEKS R2 R3 K25 ["konzuSaveOstrons"]
      72 [-]: CALL R0 2 0  
L 1:  73 [-]: RETURN R0 0  


; Name:            
; Defined at line: 582
; #Upvalues:       3
; #Parameters:     1
; Is_vararg:       0
; Max Stack Size:  4

       0 [-]: FASTCALL1 62 R0 L0
       1 [-]: MOVE R2 R0   
       2 [-]: GETIMPORT R1 1 [0x7B998233]
       3 [-]: CALL R1 1 1  
L 0:   4 [-]: JUMPIFNOT R1 L1
       5 [-]: RETURN R0 0  
L 1:   6 [-]: GETIMPORT R3 3 ["gNpcSpawnPointType"]
       7 [-]: NAMECALL R1 R0 K4 [0xF2DEAF69]
       8 [-]: CALL R1 2 1  
       9 [-]: JUMPIFNOT R1 L2
      10 [-]: GETUPVAL R1 0
      11 [-]: GETUPVAL R3 1
      12 [-]: GETTABLEKS R2 R3 K5 ["RESCUE_OSTRON"]
      13 [-]: JUMPIFNOTLE R1 R2 L2
      14 [-]: GETUPVAL R1 2
      15 [-]: NAMECALL R2 R0 K6 [0x1E3535E5]
      16 [-]: CALL R2 1 -1 
      17 [-]: CALL R1 -1 0 
L 2:  18 [-]: RETURN R0 0  


; Name:            
; Defined at line: 593
; #Upvalues:       1
; #Parameters:     1
; Is_vararg:       0
; Max Stack Size:  5

       0 [-]: FASTCALL1 62 R0 L0
       1 [-]: MOVE R2 R0   
       2 [-]: GETIMPORT R1 1 [0x7B998233]
       3 [-]: CALL R1 1 1  
L 0:   4 [-]: JUMPIFNOT R1 L1
       5 [-]: RETURN R0 0  
L 1:   6 [-]: NAMECALL R1 R0 K2 [0xBB610E5B]
       7 [-]: CALL R1 1 1  
       8 [-]: FASTCALL1 62 R1 L2
       9 [-]: MOVE R3 R1   
      10 [-]: GETIMPORT R2 1 [0x7B998233]
      11 [-]: CALL R2 1 1  
L 2:  12 [-]: JUMPIF R2 L3 
      13 [-]: GETUPVAL R4 0
      14 [-]: NAMECALL R2 R1 K3 [0xF2DEAF69]
      15 [-]: CALL R2 2 1  
      16 [-]: JUMPIFNOT R2 L3
      17 [-]: LOADB R4 0   
      18 [-]: NAMECALL R2 R1 K4 [0x8DECB783]
      19 [-]: CALL R2 2 0  
L 3:  20 [-]: RETURN R0 0  


; Name:            
; Defined at line: 604
; #Upvalues:       0
; #Parameters:     1
; Is_vararg:       0
; Max Stack Size:  8

       0 [-]: GETIMPORT R1 2 ["deaconAvatars"]
       1 [-]: JUMPIF R1 L0 
       2 [-]: NEWTABLE R1 0 0
L 0:   3 [-]: FASTCALL1 62 R0 L1
       4 [-]: MOVE R3 R0   
       5 [-]: GETIMPORT R2 4 [0x7B998233]
       6 [-]: CALL R2 1 1  
L 1:   7 [-]: JUMPIF R2 L3 
       8 [-]: LENGTH R2 R1 
       9 [-]: LOADN R3 0   
      10 [-]: JUMPIFNOTLT R3 R2 L3
      11 [-]: GETIMPORT R2 6 [0x89326C93]
      12 [-]: GETTABLEN R4 R1 1
      13 [-]: NAMECALL R4 R4 K7 [0xCDE10C4A]
      14 [-]: CALL R4 1 1  
      15 [-]: NAMECALL R5 R0 K8 [0xD1586535]
      16 [-]: CALL R5 1 1  
      17 [-]: LOADN R6 200 
      18 [-]: NAMECALL R2 R2 K9 [0x4E5939A5]
      19 [-]: CALL R2 4 1  
      20 [-]: FASTCALL1 62 R2 L2
      21 [-]: MOVE R4 R2   
      22 [-]: GETIMPORT R3 4 [0x7B998233]
      23 [-]: CALL R3 1 1  
L 2:  24 [-]: JUMPIF R3 L3 
      25 [-]: NAMECALL R3 R2 K10 [0x2047CFE7]
      26 [-]: CALL R3 1 1  
      27 [-]: JUMPIF R3 L3 
      28 [-]: NAMECALL R3 R2 K11 [0x6F8BABF9]
      29 [-]: CALL R3 1 1  
      30 [-]: JUMPIF R3 L3 
      31 [-]: NAMECALL R3 R2 K12 [0xFA9E477F]
      32 [-]: CALL R3 1 1  
      33 [-]: LOADN R6 2   
      34 [-]: NAMECALL R4 R3 K13 [0xE8A5CFDB]
      35 [-]: CALL R4 2 0  
      36 [-]: NAMECALL R6 R0 K8 [0xD1586535]
      37 [-]: CALL R6 1 -1 
      38 [-]: NAMECALL R4 R3 K14 [0x54CFC0CF]
      39 [-]: CALL R4 -1 0 
L 3:  40 [-]: RETURN R0 0  


; Name:            
; Defined at line: 619
; #Upvalues:       2
; #Parameters:     1
; Is_vararg:       0
; Max Stack Size:  12

       0 [-]: NEWTABLE R1 0 0
       1 [-]: GETIMPORT R3 1 [0x1BE5938D]
       2 [-]: FASTCALL1 62 R3 L0
       3 [-]: GETIMPORT R2 3 [0x7B998233]
       4 [-]: CALL R2 1 1  
L 0:   5 [-]: JUMPIF R2 L10
       6 [-]: NEWTABLE R2 0 0
       7 [-]: LOADN R3 0   
       8 [-]: GETIMPORT R4 1 [0x1BE5938D]
       9 [-]: GETIMPORT R6 5 ["gNpcSpawnControlType"]
      10 [-]: NAMECALL R4 R4 K6 [0xF2DEAF69]
      11 [-]: CALL R4 2 1  
      12 [-]: JUMPIFNOT R4 L1
      13 [-]: GETIMPORT R4 1 [0x1BE5938D]
      14 [-]: NAMECALL R4 R4 K7 [0x90E142BA]
      15 [-]: CALL R4 1 1  
      16 [-]: MOVE R2 R4   
      17 [-]: GETIMPORT R4 1 [0x1BE5938D]
      18 [-]: NAMECALL R4 R4 K8 [0x01F00DE3]
      19 [-]: CALL R4 1 1  
      20 [-]: MOVE R3 R4   
      21 [-]: JUMP L3
     
L 1:  22 [-]: GETIMPORT R4 1 [0x1BE5938D]
      23 [-]: GETIMPORT R6 10 ["gNpcSpawnPointType"]
      24 [-]: NAMECALL R4 R4 K6 [0xF2DEAF69]
      25 [-]: CALL R4 2 1  
      26 [-]: JUMPIFNOT R4 L3
      27 [-]: GETIMPORT R6 1 [0x1BE5938D]
      28 [-]: FASTCALL2 52 R2 R6 L2
      29 [-]: MOVE R5 R2   
      30 [-]: GETIMPORT R4 13 [0x23D5322F]
      31 [-]: CALL R4 2 0  
L 2:  32 [-]: LOADN R3 1   
L 3:  33 [-]: LOADN R4 0   
      34 [-]: JUMPIFNOTLT R4 R3 L10
      35 [-]: FASTCALL1 62 R2 L4
      36 [-]: MOVE R5 R2   
      37 [-]: GETIMPORT R4 3 [0x7B998233]
      38 [-]: CALL R4 1 1  
L 4:  39 [-]: JUMPIF R4 L10
      40 [-]: LENGTH R4 R2 
      41 [-]: LOADN R5 0   
      42 [-]: JUMPIFNOTLT R5 R4 L10
      43 [-]: LOADN R4 5   
L 5:  44 [-]: LENGTH R5 R1 
      45 [-]: JUMPIFNOTLT R5 R3 L10
      46 [-]: LOADN R5 0   
      47 [-]: JUMPIFNOTLT R5 R4 L10
      48 [-]: LOADN R7 1   
      49 [-]: LENGTH R5 R2 
      50 [-]: LOADN R6 1   
      51 [-]: FORNPREP R5 L9
L 6:  52 [-]: GETTABLE R8 R2 R7
      53 [-]: NAMECALL R8 R8 K14 [0x1E3535E5]
      54 [-]: CALL R8 1 1  
      55 [-]: FASTCALL1 62 R8 L7
      56 [-]: MOVE R10 R8  
      57 [-]: GETIMPORT R9 3 [0x7B998233]
      58 [-]: CALL R9 1 1  
L 7:  59 [-]: JUMPIF R9 L8 
      60 [-]: FASTCALL2 52 R1 R8 L8
      61 [-]: MOVE R10 R1  
      62 [-]: MOVE R11 R8  
      63 [-]: GETIMPORT R9 13 [0x23D5322F]
      64 [-]: CALL R9 2 0  
L 8:  65 [-]: FORNLOOP R5 L6
L 9:  66 [-]: GETIMPORT R5 16 [0xCBD666E1]
      67 [-]: LOADN R6 0   
      68 [-]: CALL R5 1 0  
      69 [-]: GETIMPORT R5 18 [0xFFF641AF]
      70 [-]: CALL R5 0 1  
      71 [-]: SUB R4 R4 R5 
      72 [-]: JUMPBACK L5  
L10:  73 [-]: LENGTH R2 R1 
      74 [-]: LOADN R3 0   
      75 [-]: JUMPIFNOTLT R3 R2 L18
      76 [-]: LENGTH R4 R1 
      77 [-]: LOADN R2 1   
      78 [-]: LOADN R3 -1  
      79 [-]: FORNPREP R2 L17
L11:  80 [-]: GETTABLE R5 R1 R4
      81 [-]: FASTCALL1 62 R5 L12
      82 [-]: MOVE R7 R5   
      83 [-]: GETIMPORT R6 3 [0x7B998233]
      84 [-]: CALL R6 1 1  
L12:  85 [-]: JUMPIF R6 L13
      86 [-]: NAMECALL R6 R5 K19 [0x2047CFE7]
      87 [-]: CALL R6 1 1  
      88 [-]: JUMPIFNOT R6 L14
L13:  89 [-]: GETIMPORT R6 21 [0x9C1F3B5A]
      90 [-]: MOVE R7 R1   
      91 [-]: MOVE R8 R4   
      92 [-]: CALL R6 2 0  
      93 [-]: JUMP L16
    
L14:  94 [-]: GETUPVAL R8 0
      95 [-]: NAMECALL R6 R5 K22 [0xAC99E72C]
      96 [-]: CALL R6 2 1  
      97 [-]: JUMPIFNOT R6 L16
      98 [-]: GETUPVAL R9 0
      99 [-]: NAMECALL R7 R5 K23 [0xA088430F]
     100 [-]: CALL R7 2 1  
     101 [-]: JUMPIFNOT R7 L15
     102 [-]: GETIMPORT R8 21 [0x9C1F3B5A]
     103 [-]: MOVE R9 R1   
     104 [-]: MOVE R10 R4  
     105 [-]: CALL R8 2 0  
     106 [-]: JUMP L16
    
L15: 107 [-]: GETIMPORT R8 25 [0x3D106989]
     108 [-]: LOADK R9 K26 ["FAILED TO SAVE"]
     109 [-]: CALL R8 1 0  
     110 [-]: GETUPVAL R8 1
     111 [-]: MOVE R9 R5   
     112 [-]: CALL R8 1 0  
     113 [-]: GETUPVAL R10 0
     114 [-]: NAMECALL R8 R5 K27 [0xEF77C6EF]
     115 [-]: CALL R8 2 0  
L16: 116 [-]: FORNLOOP R2 L11
L17: 117 [-]: GETIMPORT R2 16 [0xCBD666E1]
     118 [-]: LOADN R3 0   
     119 [-]: CALL R2 1 0  
     120 [-]: JUMPBACK L10 
L18: 121 [-]: RETURN R0 0  


; Name:            
; Defined at line: 676
; #Upvalues:       1
; #Parameters:     0
; Is_vararg:       0
; Max Stack Size:  6

       0 [-]: GETUPVAL R0 0
       1 [-]: JUMPIFNOT R0 L4
       2 [-]: GETIMPORT R0 2 ["PlayerSpotted"]
       3 [-]: JUMPIF R0 L4 
       4 [-]: GETIMPORT R3 4 ["deaconAvatars"]
       5 [-]: LENGTH R2 R3 
       6 [-]: LOADN R0 1   
       7 [-]: LOADN R1 -1  
       8 [-]: FORNPREP R0 L4
L 0:   9 [-]: GETIMPORT R5 4 ["deaconAvatars"]
      10 [-]: GETTABLE R4 R5 R2
      11 [-]: FASTCALL1 62 R4 L1
      12 [-]: GETIMPORT R3 6 [0x7B998233]
      13 [-]: CALL R3 1 1  
L 1:  14 [-]: JUMPIF R3 L2 
      15 [-]: GETIMPORT R4 4 ["deaconAvatars"]
      16 [-]: GETTABLE R3 R4 R2
      17 [-]: NAMECALL R3 R3 K7 [0x2047CFE7]
      18 [-]: CALL R3 1 1  
      19 [-]: JUMPIF R3 L2 
      20 [-]: GETIMPORT R4 4 ["deaconAvatars"]
      21 [-]: GETTABLE R3 R4 R2
      22 [-]: NAMECALL R3 R3 K8 [0x6F8BABF9]
      23 [-]: CALL R3 1 1  
      24 [-]: JUMPIFNOT R3 L3
      25 [-]: GETIMPORT R3 10 [0x3D106989]
      26 [-]: LOADK R4 K11 ["You've been spotted"]
      27 [-]: CALL R3 1 0  
      28 [-]: GETIMPORT R3 13 [0xCBD666E1]
      29 [-]: LOADN R4 2   
      30 [-]: CALL R3 1 0  
      31 [-]: GETIMPORT R3 14 ["_T"]
      32 [-]: LOADB R4 1   
      33 [-]: SETTABLEKS R4 R3 K1 ["PlayerSpotted"]
      34 [-]: LOADB R3 1   
      35 [-]: RETURN R3 1  
      36 [-]: JUMP L3
     
L 2:  37 [-]: GETIMPORT R3 17 [0x9C1F3B5A]
      38 [-]: GETIMPORT R4 4 ["deaconAvatars"]
      39 [-]: MOVE R5 R2   
      40 [-]: CALL R3 2 0  
L 3:  41 [-]: FORNLOOP R0 L0
L 4:  42 [-]: LOADB R0 0   
      43 [-]: RETURN R0 1  


; Name:            
; Defined at line: 698
; #Upvalues:       1
; #Parameters:     1
; Is_vararg:       0
; Max Stack Size:  11

       0 [-]: LOADN R1 0   
       1 [-]: SETUPVAL R1 0
       2 [-]: GETIMPORT R1 1 [0x89326C93]
       3 [-]: MOVE R3 R0   
       4 [-]: NAMECALL R1 R1 K2 [0xC7FCADA9]
       5 [-]: CALL R1 2 1  
       6 [-]: GETIMPORT R2 4 [0xC8802016]
       7 [-]: MOVE R3 R1   
       8 [-]: CALL R2 1 3  
       9 [-]: FORGPREP_INEXT R2 L1
L 0:  10 [-]: GETUPVAL R8 0
      11 [-]: NAMECALL R9 R6 K5 [0x74904F84]
      12 [-]: CALL R9 1 1  
      13 [-]: ADD R7 R8 R9 
      14 [-]: SETUPVAL R7 0
L 1:  15 [-]: FORGLOOP R2 L0 2 [inext]
      16 [-]: GETIMPORT R2 7 [0x3D106989]
      17 [-]: LOADK R4 K8 ["Current Hostage Count: "]
      18 [-]: GETUPVAL R5 0
      19 [-]: CONCAT R3 R4 R5
      20 [-]: CALL R2 1 0  
      21 [-]: RETURN R0 0  


; Name:            
; Defined at line: 709
; #Upvalues:       0
; #Parameters:     1
; Is_vararg:       0
; Max Stack Size:  7

       0 [-]: GETIMPORT R2 2 ["deaconAvatars"]
       1 [-]: FASTCALL1 62 R2 L0
       2 [-]: GETIMPORT R1 4 [0x7B998233]
       3 [-]: CALL R1 1 1  
L 0:   4 [-]: JUMPIFNOT R1 L1
       5 [-]: GETIMPORT R1 5 ["_T"]
       6 [-]: NEWTABLE R2 0 0
       7 [-]: SETTABLEKS R2 R1 K1 ["deaconAvatars"]
L 1:   8 [-]: FASTCALL1 62 R0 L2
       9 [-]: MOVE R2 R0   
      10 [-]: GETIMPORT R1 4 [0x7B998233]
      11 [-]: CALL R1 1 1  
L 2:  12 [-]: JUMPIF R1 L5 
      13 [-]: NAMECALL R1 R0 K6 [0xBB610E5B]
      14 [-]: CALL R1 1 1  
      15 [-]: FASTCALL1 62 R1 L3
      16 [-]: MOVE R3 R1   
      17 [-]: GETIMPORT R2 4 [0x7B998233]
      18 [-]: CALL R2 1 1  
L 3:  19 [-]: JUMPIF R2 L5 
      20 [-]: GETIMPORT R3 2 ["deaconAvatars"]
      21 [-]: FASTCALL2 52 R3 R1 L4
      22 [-]: MOVE R4 R1   
      23 [-]: GETIMPORT R2 9 [0x23D5322F]
      24 [-]: CALL R2 2 0  
L 4:  25 [-]: GETIMPORT R2 11 [0x3D106989]
      26 [-]: LOADK R4 K12 ["New deacon spawned: "]
      27 [-]: NAMECALL R5 R1 K13 [0xE223E2B1]
      28 [-]: CALL R5 1 1  
      29 [-]: CONCAT R3 R4 R5
      30 [-]: CALL R2 1 0  
L 5:  31 [-]: RETURN R0 0  


; Name:            
; Defined at line: 724
; #Upvalues:       2
; #Parameters:     0
; Is_vararg:       0
; Max Stack Size:  9

       0 [-]: GETUPVAL R2 0
       1 [-]: FASTCALL1 62 R2 L0
       2 [-]: GETIMPORT R1 1 [0x7B998233]
       3 [-]: CALL R1 1 1  
L 0:   4 [-]: NOT R0 R1    
       5 [-]: JUMPIFNOT R0 L1
       6 [-]: GETUPVAL R1 0
       7 [-]: NAMECALL R1 R1 K2 [0x2047CFE7]
       8 [-]: CALL R1 1 1  
       9 [-]: NOT R0 R1    
      10 [-]: JUMPIFNOT R0 L1
      11 [-]: GETUPVAL R1 0
      12 [-]: NAMECALL R1 R1 K3 [0x73901ACF]
      13 [-]: CALL R1 1 1  
      14 [-]: NOT R0 R1    
      15 [-]: JUMPIFNOT R0 L1
      16 [-]: GETUPVAL R1 0
      17 [-]: NAMECALL R1 R1 K4 [0x6F8BABF9]
      18 [-]: CALL R1 1 1  
      19 [-]: NOT R0 R1    
L 1:  20 [-]: JUMPIFNOT R0 L7
      21 [-]: GETUPVAL R2 1
      22 [-]: FASTCALL1 62 R2 L2
      23 [-]: GETIMPORT R1 1 [0x7B998233]
      24 [-]: CALL R1 1 1  
L 2:  25 [-]: JUMPIF R1 L7 
      26 [-]: GETUPVAL R1 1
      27 [-]: NAMECALL R1 R1 K5 [0x0D09D3C0]
      28 [-]: CALL R1 1 1  
      29 [-]: FASTCALL1 62 R1 L3
      30 [-]: MOVE R3 R1   
      31 [-]: GETIMPORT R2 1 [0x7B998233]
      32 [-]: CALL R2 1 1  
L 3:  33 [-]: JUMPIF R2 L7 
      34 [-]: LENGTH R2 R1 
      35 [-]: LOADN R3 0   
      36 [-]: JUMPIFNOTLT R3 R2 L7
      37 [-]: GETIMPORT R2 7 [0xC8802016]
      38 [-]: MOVE R3 R1   
      39 [-]: CALL R2 1 3  
      40 [-]: FORGPREP_INEXT R2 L6
L 4:  41 [-]: FASTCALL1 62 R6 L5
      42 [-]: MOVE R8 R6   
      43 [-]: GETIMPORT R7 1 [0x7B998233]
      44 [-]: CALL R7 1 1  
L 5:  45 [-]: JUMPIF R7 L6 
      46 [-]: NAMECALL R7 R6 K2 [0x2047CFE7]
      47 [-]: CALL R7 1 1  
      48 [-]: JUMPIF R7 L6 
      49 [-]: NAMECALL R7 R6 K8 [0xCFD0ACBF]
      50 [-]: CALL R7 1 1  
      51 [-]: JUMPIFNOT R7 L6
      52 [-]: LOADB R0 0   
      53 [-]: RETURN R0 1  
L 6:  54 [-]: FORGLOOP R2 L4 2 [inext]
L 7:  55 [-]: RETURN R0 1  


; Name:            
; Defined at line: 754
; #Upvalues:       7
; #Parameters:     0
; Is_vararg:       0
; Max Stack Size:  13

       0 [-]: GETUPVAL R1 0
       1 [-]: FASTCALL1 62 R1 L0
       2 [-]: GETIMPORT R0 1 [0x7B998233]
       3 [-]: CALL R0 1 1  
L 0:   4 [-]: JUMPIF R0 L1 
       5 [-]: GETUPVAL R0 1
       6 [-]: GETUPVAL R2 0
       7 [-]: NAMECALL R0 R0 K2 [0x775C858B]
       8 [-]: CALL R0 2 0  
L 1:   9 [-]: GETIMPORT R0 4 [0xC163F229]
      10 [-]: GETUPVAL R2 2
      11 [-]: GETTABLEKS R1 R2 K5 ["minValue"]
      12 [-]: GETUPVAL R3 2
      13 [-]: GETTABLEKS R2 R3 K6 ["maxValue"]
      14 [-]: CALL R0 2 1  
      15 [-]: GETUPVAL R1 3
      16 [-]: CALL R1 0 1  
      17 [-]: JUMPIF R1 L2 
      18 [-]: GETIMPORT R1 4 [0xC163F229]
      19 [-]: GETUPVAL R3 4
      20 [-]: GETTABLEKS R2 R3 K5 ["minValue"]
      21 [-]: GETUPVAL R4 4
      22 [-]: GETTABLEKS R3 R4 K6 ["maxValue"]
      23 [-]: CALL R1 2 1  
      24 [-]: MOVE R0 R1   
      25 [-]: JUMP L16
    
L 2:  26 [-]: GETIMPORT R1 9 ["IsRandomWhisperActive"]
      27 [-]: JUMPIFNOT R1 L16
      28 [-]: GETUPVAL R1 5
      29 [-]: GETIMPORT R3 11 [0xCD4965D5]
      30 [-]: GETIMPORT R4 13 ["EMPTY_SYMBOL"]
      31 [-]: NAMECALL R1 R1 K14 [0x47901F07]
      32 [-]: CALL R1 3 1  
      33 [-]: GETUPVAL R2 5
      34 [-]: NAMECALL R2 R2 K15 [0x0B4BCFB6]
      35 [-]: CALL R2 1 1  
      36 [-]: FASTCALL1 62 R2 L3
      37 [-]: MOVE R4 R2   
      38 [-]: GETIMPORT R3 1 [0x7B998233]
      39 [-]: CALL R3 1 1  
L 3:  40 [-]: JUMPIF R3 L4 
      41 [-]: GETIMPORT R5 17 [0xE7090A7D]
      42 [-]: LOADK R6 K18 [0.10000000000000001]
      43 [-]: LOADN R7 -1  
      44 [-]: LOADK R8 K18 [0.10000000000000001]
      45 [-]: NAMECALL R3 R2 K19 [0x758C046D]
      46 [-]: CALL R3 5 0  
L 4:  47 [-]: GETUPVAL R3 5
      48 [-]: GETIMPORT R5 21 [0x992245E7]
      49 [-]: LOADB R6 0   
      50 [-]: NAMECALL R3 R3 K22 [0x659D451F]
      51 [-]: CALL R3 3 0  
      52 [-]: GETIMPORT R3 24 [0x89326C93]
      53 [-]: GETIMPORT R5 26 [0x0469F296]
      54 [-]: LOADK R6 K27 ["WhisperLight"]
      55 [-]: CALL R5 1 1  
      56 [-]: GETUPVAL R6 5
      57 [-]: NAMECALL R6 R6 K28 [0xD1586535]
      58 [-]: CALL R6 1 1  
      59 [-]: LOADN R7 0   
      60 [-]: LOADN R8 30  
      61 [-]: NAMECALL R3 R3 K29 [0xF16592C8]
      62 [-]: CALL R3 5 1  
      63 [-]: NEWTABLE R4 0 0
      64 [-]: FASTCALL1 62 R3 L5
      65 [-]: MOVE R6 R3   
      66 [-]: GETIMPORT R5 1 [0x7B998233]
      67 [-]: CALL R5 1 1  
L 5:  68 [-]: JUMPIF R5 L10
      69 [-]: LENGTH R5 R3 
      70 [-]: LOADN R6 0   
      71 [-]: JUMPIFNOTLT R6 R5 L10
      72 [-]: GETIMPORT R5 31 [0xC8802016]
      73 [-]: MOVE R6 R3   
      74 [-]: CALL R5 1 3  
      75 [-]: FORGPREP_INEXT R5 L9
L 6:  76 [-]: FASTCALL1 62 R9 L7
      77 [-]: MOVE R11 R9  
      78 [-]: GETIMPORT R10 1 [0x7B998233]
      79 [-]: CALL R10 1 1 
L 7:  80 [-]: JUMPIF R10 L9
      81 [-]: FASTCALL2 52 R4 R9 L8
      82 [-]: MOVE R11 R4  
      83 [-]: MOVE R12 R9  
      84 [-]: GETIMPORT R10 34 [0x23D5322F]
      85 [-]: CALL R10 2 0 
L 8:  86 [-]: NAMECALL R10 R9 K35 [0xD199E920]
      87 [-]: CALL R10 1 0 
      88 [-]: LENGTH R10 R4
      89 [-]: LOADN R11 4  
      90 [-]: JUMPIFLE R11 R10 L10
L 9:  91 [-]: FORGLOOP R5 L6 2 [inext]
L10:  92 [-]: GETIMPORT R5 37 [0xCBD666E1]
      93 [-]: LOADN R6 5   
      94 [-]: CALL R5 1 0  
      95 [-]: FASTCALL1 62 R1 L11
      96 [-]: MOVE R6 R1   
      97 [-]: GETIMPORT R5 1 [0x7B998233]
      98 [-]: CALL R5 1 1  
L11:  99 [-]: JUMPIF R5 L12
     100 [-]: NAMECALL R5 R1 K38 [0xA2880940]
     101 [-]: CALL R5 1 0  
L12: 102 [-]: FASTCALL1 62 R2 L13
     103 [-]: MOVE R6 R2   
     104 [-]: GETIMPORT R5 1 [0x7B998233]
     105 [-]: CALL R5 1 1  
L13: 106 [-]: JUMPIF R5 L14
     107 [-]: GETIMPORT R7 17 [0xE7090A7D]
     108 [-]: LOADB R8 0   
     109 [-]: NAMECALL R5 R2 K39 [0xBD5007D9]
     110 [-]: CALL R5 3 0  
L14: 111 [-]: LENGTH R5 R4 
     112 [-]: LOADN R6 0   
     113 [-]: JUMPIFNOTLT R6 R5 L16
     114 [-]: LOADN R7 1   
     115 [-]: LENGTH R5 R4 
     116 [-]: LOADN R6 1   
     117 [-]: FORNPREP R5 L16
L15: 118 [-]: GETTABLE R8 R4 R7
     119 [-]: NAMECALL R8 R8 K40 [0x6B5E0C7A]
     120 [-]: CALL R8 1 0  
     121 [-]: FORNLOOP R5 L15
L16: 122 [-]: GETUPVAL R1 1
     123 [-]: MOVE R3 R0   
     124 [-]: GETUPVAL R4 6
     125 [-]: NAMECALL R1 R1 K41 [0xBD2E96EA]
     126 [-]: CALL R1 3 1  
     127 [-]: SETUPVAL R1 0
     128 [-]: RETURN R0 0  


; Name:            
; Defined at line: 811
; #Upvalues:       4
; #Parameters:     1
; Is_vararg:       0
; Max Stack Size:  11

       0 [-]: GETIMPORT R1 1 ["_T"]
       1 [-]: LOADB R2 0   
       2 [-]: SETTABLEKS R2 R1 K2 ["IsRandomWhisperActive"]
       3 [-]: GETIMPORT R2 4 [0x95A557DC]
       4 [-]: FASTCALL1 62 R2 L0
       5 [-]: GETIMPORT R1 6 [0x7B998233]
       6 [-]: CALL R1 1 1  
L 0:   7 [-]: JUMPIF R1 L6 
       8 [-]: GETIMPORT R2 4 [0x95A557DC]
       9 [-]: LENGTH R1 R2 
      10 [-]: LOADN R2 0   
      11 [-]: JUMPIFNOTLT R2 R1 L6
L 1:  12 [-]: LOADN R1 0   
      13 [-]: GETIMPORT R2 8 [0xC8802016]
      14 [-]: GETIMPORT R3 4 [0x95A557DC]
      15 [-]: CALL R2 1 3  
      16 [-]: FORGPREP_INEXT R2 L4
L 2:  17 [-]: FASTCALL1 62 R6 L3
      18 [-]: MOVE R8 R6   
      19 [-]: GETIMPORT R7 6 [0x7B998233]
      20 [-]: CALL R7 1 1  
L 3:  21 [-]: JUMPIF R7 L4 
      22 [-]: NAMECALL R7 R6 K9 [0x01F00DE3]
      23 [-]: CALL R7 1 1  
      24 [-]: ADD R1 R1 R7 
      25 [-]: GETIMPORT R7 11 [0xB78E1C45]
      26 [-]: JUMPIFLT R7 R1 L5
L 4:  27 [-]: FORGLOOP R2 L2 2 [inext]
L 5:  28 [-]: GETIMPORT R2 11 [0xB78E1C45]
      29 [-]: JUMPIFLE R1 R2 L6
      30 [-]: GETIMPORT R2 13 [0xCBD666E1]
      31 [-]: LOADN R3 0   
      32 [-]: CALL R2 1 0  
      33 [-]: JUMPBACK L1  
L 6:  34 [-]: GETIMPORT R1 13 [0xCBD666E1]
      35 [-]: GETIMPORT R2 15 [0x43C1EBBC]
      36 [-]: CALL R1 1 0  
      37 [-]: GETIMPORT R1 17 [0x89326C93]
      38 [-]: NAMECALL R1 R1 K18 [0x78298275]
      39 [-]: CALL R1 1 1  
      40 [-]: SETUPVAL R1 0
L 7:  41 [-]: GETUPVAL R2 0
      42 [-]: FASTCALL1 62 R2 L8
      43 [-]: GETIMPORT R1 6 [0x7B998233]
      44 [-]: CALL R1 1 1  
L 8:  45 [-]: JUMPIFNOT R1 L9
      46 [-]: GETIMPORT R1 13 [0xCBD666E1]
      47 [-]: LOADN R2 0   
      48 [-]: CALL R1 1 0  
      49 [-]: GETIMPORT R1 17 [0x89326C93]
      50 [-]: NAMECALL R1 R1 K18 [0x78298275]
      51 [-]: CALL R1 1 1  
      52 [-]: SETUPVAL R1 0
      53 [-]: JUMPBACK L7  
L 9:  54 [-]: LOADNIL R1   
      55 [-]: LOADNIL R2   
      56 [-]: GETIMPORT R4 20 [0x992245E7]
      57 [-]: FASTCALL1 62 R4 L10
      58 [-]: GETIMPORT R3 6 [0x7B998233]
      59 [-]: CALL R3 1 1  
L10:  60 [-]: JUMPIF R3 L15
      61 [-]: GETUPVAL R3 0
      62 [-]: GETIMPORT R5 22 [0xCD4965D5]
      63 [-]: GETIMPORT R6 24 ["EMPTY_SYMBOL"]
      64 [-]: NAMECALL R3 R3 K25 [0x47901F07]
      65 [-]: CALL R3 3 1  
      66 [-]: MOVE R1 R3   
      67 [-]: GETUPVAL R3 0
      68 [-]: NAMECALL R3 R3 K26 [0x0B4BCFB6]
      69 [-]: CALL R3 1 1  
      70 [-]: MOVE R2 R3   
      71 [-]: FASTCALL1 62 R2 L11
      72 [-]: MOVE R4 R2   
      73 [-]: GETIMPORT R3 6 [0x7B998233]
      74 [-]: CALL R3 1 1  
L11:  75 [-]: JUMPIF R3 L12
      76 [-]: GETIMPORT R5 28 [0xE7090A7D]
      77 [-]: LOADK R6 K29 [0.10000000000000001]
      78 [-]: LOADN R7 -1  
      79 [-]: LOADK R8 K29 [0.10000000000000001]
      80 [-]: NAMECALL R3 R2 K30 [0x758C046D]
      81 [-]: CALL R3 5 0  
L12:  82 [-]: GETUPVAL R4 0
      83 [-]: FASTCALL1 62 R4 L13
      84 [-]: GETIMPORT R3 6 [0x7B998233]
      85 [-]: CALL R3 1 1  
L13:  86 [-]: JUMPIF R3 L14
      87 [-]: GETUPVAL R3 0
      88 [-]: GETIMPORT R5 20 [0x992245E7]
      89 [-]: LOADB R6 0   
      90 [-]: NAMECALL R3 R3 K31 [0x659D451F]
      91 [-]: CALL R3 3 0  
      92 [-]: JUMP L15
    
L14:  93 [-]: GETIMPORT R5 20 [0x992245E7]
      94 [-]: LOADB R6 0   
      95 [-]: NAMECALL R3 R0 K31 [0x659D451F]
      96 [-]: CALL R3 3 0  
L15:  97 [-]: GETIMPORT R4 33 [0xE91D7466]
      98 [-]: FASTCALL1 62 R4 L16
      99 [-]: GETIMPORT R3 6 [0x7B998233]
     100 [-]: CALL R3 1 1  
L16: 101 [-]: JUMPIF R3 L17
     102 [-]: GETIMPORT R3 13 [0xCBD666E1]
     103 [-]: GETIMPORT R4 35 [0xC389E002]
     104 [-]: CALL R3 1 0  
     105 [-]: GETUPVAL R4 1
     106 [-]: GETTABLEKS R3 R4 K36 [0x11DCFE97]
     107 [-]: GETUPVAL R5 2
     108 [-]: GETTABLEKS R4 R5 K37 ["operatorReactsWhisper"]
     109 [-]: CALL R3 1 0  
     110 [-]: GETUPVAL R4 1
     111 [-]: GETTABLEKS R3 R4 K38 [0xFC87A231]
     112 [-]: CALL R3 0 0  
     113 [-]: GETUPVAL R4 1
     114 [-]: GETTABLEKS R3 R4 K39 [0x9742B85B]
     115 [-]: GETIMPORT R4 33 [0xE91D7466]
     116 [-]: GETUPVAL R6 2
     117 [-]: GETTABLEKS R5 R6 K40 ["ordisReactsWhisper"]
     118 [-]: CALL R3 2 0  
L17: 119 [-]: GETIMPORT R3 13 [0xCBD666E1]
     120 [-]: GETIMPORT R4 42 [0x7341A098]
     121 [-]: CALL R3 1 0  
     122 [-]: FASTCALL1 62 R1 L18
     123 [-]: MOVE R4 R1   
     124 [-]: GETIMPORT R3 6 [0x7B998233]
     125 [-]: CALL R3 1 1  
L18: 126 [-]: JUMPIF R3 L19
     127 [-]: NAMECALL R3 R1 K43 [0xA2880940]
     128 [-]: CALL R3 1 0  
L19: 129 [-]: FASTCALL1 62 R2 L20
     130 [-]: MOVE R4 R2   
     131 [-]: GETIMPORT R3 6 [0x7B998233]
     132 [-]: CALL R3 1 1  
L20: 133 [-]: JUMPIF R3 L21
     134 [-]: GETIMPORT R5 28 [0xE7090A7D]
     135 [-]: LOADB R6 0   
     136 [-]: NAMECALL R3 R2 K44 [0xBD5007D9]
     137 [-]: CALL R3 3 0  
L21: 138 [-]: GETIMPORT R4 46 [0x5D7624FC]
     139 [-]: FASTCALL1 62 R4 L22
     140 [-]: GETIMPORT R3 6 [0x7B998233]
     141 [-]: CALL R3 1 1  
L22: 142 [-]: JUMPIF R3 L26
     143 [-]: GETIMPORT R4 46 [0x5D7624FC]
     144 [-]: LENGTH R3 R4 
     145 [-]: LOADN R4 0   
     146 [-]: JUMPIFNOTLT R4 R3 L26
     147 [-]: GETIMPORT R3 8 [0xC8802016]
     148 [-]: GETIMPORT R4 46 [0x5D7624FC]
     149 [-]: CALL R3 1 3  
     150 [-]: FORGPREP_INEXT R3 L25
L23: 151 [-]: FASTCALL1 62 R7 L24
     152 [-]: MOVE R9 R7   
     153 [-]: GETIMPORT R8 6 [0x7B998233]
     154 [-]: CALL R8 1 1  
L24: 155 [-]: JUMPIF R8 L25
     156 [-]: GETUPVAL R9 3
     157 [-]: GETTABLEKS R8 R9 K47 [0xC474A99E]
     158 [-]: MOVE R9 R7   
     159 [-]: LOADK R10 K48 ["TriggerPort"]
     160 [-]: CALL R8 2 0  
L25: 161 [-]: FORGLOOP R3 L23 2 [inext]
L26: 162 [-]: GETIMPORT R3 1 ["_T"]
     163 [-]: LOADB R4 1   
     164 [-]: SETTABLEKS R4 R3 K2 ["IsRandomWhisperActive"]
     165 [-]: RETURN R0 0  


; Name:            
; Defined at line: 888
; #Upvalues:       3
; #Parameters:     3
; Is_vararg:       0
; Max Stack Size:  10

       0 [-]: NEWTABLE R3 0 0
       1 [-]: SETUPVAL R3 0
       2 [-]: LOADN R5 1   
       3 [-]: LENGTH R3 R0 
       4 [-]: LOADN R4 1   
       5 [-]: FORNPREP R3 L4
L 0:   6 [-]: GETIMPORT R6 1 [0x89326C93]
       7 [-]: GETTABLE R8 R0 R5
       8 [-]: NAMECALL R6 R6 K2 [0x46A0EBF5]
       9 [-]: CALL R6 2 1  
      10 [-]: FASTCALL1 62 R6 L1
      11 [-]: MOVE R8 R6   
      12 [-]: GETIMPORT R7 4 [0x7B998233]
      13 [-]: CALL R7 1 1  
L 1:  14 [-]: JUMPIF R7 L3 
      15 [-]: JUMPIF R2 L2 
      16 [-]: GETIMPORT R7 6 [0x11A19C5E]
      17 [-]: MOVE R8 R6   
      18 [-]: LOADK R9 K7 ["FirePort"]
      19 [-]: CALL R7 2 0  
L 2:  20 [-]: GETUPVAL R8 0
      21 [-]: FASTCALL2 52 R8 R6 L3
      22 [-]: MOVE R9 R6   
      23 [-]: GETIMPORT R7 10 [0x23D5322F]
      24 [-]: CALL R7 2 0  
L 3:  25 [-]: FORNLOOP R3 L0
L 4:  26 [-]: GETUPVAL R4 0
      27 [-]: LENGTH R3 R4 
      28 [-]: SETUPVAL R3 1
      29 [-]: JUMPIF R1 L5 
      30 [-]: GETUPVAL R4 2
      31 [-]: GETTABLEKS R3 R4 K11 [0xEA753E99]
      32 [-]: LOADK R4 K12 ["/Lotus/Language/NewWar/P3M2PoweredCrystals"]
      33 [-]: LOADN R5 0   
      34 [-]: GETUPVAL R6 1
      35 [-]: CALL R3 3 0  
L 5:  36 [-]: RETURN R0 0  


; Name:            
; Defined at line: 906
; #Upvalues:       3
; #Parameters:     1
; Is_vararg:       0
; Max Stack Size:  4

       0 [-]: GETUPVAL R2 0
       1 [-]: FASTCALL1 62 R2 L0
       2 [-]: GETIMPORT R1 1 [0x7B998233]
       3 [-]: CALL R1 1 1  
L 0:   4 [-]: JUMPIF R1 L2 
       5 [-]: GETUPVAL R2 1
       6 [-]: FASTCALL1 62 R2 L1
       7 [-]: GETIMPORT R1 1 [0x7B998233]
       8 [-]: CALL R1 1 1  
L 1:   9 [-]: JUMPIF R1 L2 
      10 [-]: GETUPVAL R1 0
      11 [-]: GETUPVAL R3 1
      12 [-]: NAMECALL R1 R1 K2 [0x9B2E6C87]
      13 [-]: CALL R1 2 1  
      14 [-]: LOADN R2 5   
      15 [-]: JUMPIFNOTLT R1 R2 L2
      16 [-]: GETUPVAL R1 2
      17 [-]: MOVE R3 R0   
      18 [-]: NAMECALL R1 R1 K3 [0x8ABFF40E]
      19 [-]: CALL R1 2 0  
L 2:  20 [-]: RETURN R0 0  


; Name:            
; Defined at line: 915
; #Upvalues:       8
; #Parameters:     1
; Is_vararg:       0
; Max Stack Size:  10

       0 [-]: FASTCALL1 62 R0 L0
       1 [-]: MOVE R2 R0   
       2 [-]: GETIMPORT R1 1 [0x7B998233]
       3 [-]: CALL R1 1 1  
L 0:   4 [-]: JUMPIF R1 L7 
       5 [-]: GETIMPORT R3 3 ["gContextActionType"]
       6 [-]: NAMECALL R1 R0 K4 [0xF2DEAF69]
       7 [-]: CALL R1 2 1  
       8 [-]: JUMPIFNOT R1 L7
       9 [-]: GETUPVAL R1 0
      10 [-]: JUMPIFNOTEQ R0 R1 L7
      11 [-]: GETUPVAL R1 1
      12 [-]: GETUPVAL R3 2
      13 [-]: GETTABLEKS R2 R3 K5 ["RIDE_BALLOON"]
      14 [-]: JUMPIFNOTEQ R1 R2 L7
      15 [-]: LOADB R1 0   
      16 [-]: SETUPVAL R1 3
      17 [-]: GETUPVAL R1 0
      18 [-]: LOADK R3 K6 ["Disable"]
      19 [-]: NAMECALL R1 R1 K7 [0x8EB2112D]
      20 [-]: CALL R1 2 0  
      21 [-]: LOADNIL R1   
      22 [-]: SETUPVAL R1 0
      23 [-]: GETUPVAL R2 4
      24 [-]: GETTABLEKS R1 R2 K8 [0xA1DF01D6]
      25 [-]: GETUPVAL R3 5
      26 [-]: GETTABLEKS R2 R3 K9 ["ascendTower"]
      27 [-]: CALL R1 1 0  
      28 [-]: GETUPVAL R2 6
      29 [-]: FASTCALL1 62 R2 L1
      30 [-]: GETIMPORT R1 1 [0x7B998233]
      31 [-]: CALL R1 1 1  
L 1:  32 [-]: JUMPIF R1 L3 
      33 [-]: GETUPVAL R1 6
      34 [-]: NAMECALL R1 R1 K10 [0xF37943FF]
      35 [-]: CALL R1 1 1  
      36 [-]: JUMPIFNOT R1 L2
      37 [-]: GETUPVAL R1 6
      38 [-]: LOADK R3 K6 ["Disable"]
      39 [-]: NAMECALL R1 R1 K7 [0x8EB2112D]
      40 [-]: CALL R1 2 0  
L 2:  41 [-]: LOADNIL R1   
      42 [-]: SETUPVAL R1 6
L 3:  43 [-]: GETUPVAL R1 7
      44 [-]: GETIMPORT R2 12 [0x0469F296]
      45 [-]: LOADK R3 K13 ["Ascend"]
      46 [-]: CALL R2 1 -1 
      47 [-]: CALL R1 -1 0 
      48 [-]: GETIMPORT R1 15 ["_T"]
      49 [-]: LOADB R2 1   
      50 [-]: SETTABLEKS R2 R1 K16 ["ForceShowImpactMessages"]
      51 [-]: GETIMPORT R1 15 ["_T"]
      52 [-]: LOADB R2 1   
      53 [-]: SETTABLEKS R2 R1 K17 ["MinimalHud"]
      54 [-]: GETIMPORT R1 12 [0x0469F296]
      55 [-]: LOADK R2 K18 ["TENNO"]
      56 [-]: CALL R1 1 1  
      57 [-]: LOADN R4 1   
      58 [-]: GETIMPORT R5 20 ["deaconAvatars"]
      59 [-]: LENGTH R2 R5 
      60 [-]: LOADN R3 1   
      61 [-]: FORNPREP R2 L7
L 4:  62 [-]: GETIMPORT R6 20 ["deaconAvatars"]
      63 [-]: GETTABLE R5 R6 R4
      64 [-]: FASTCALL1 62 R5 L5
      65 [-]: MOVE R7 R5   
      66 [-]: GETIMPORT R6 1 [0x7B998233]
      67 [-]: CALL R6 1 1  
L 5:  68 [-]: JUMPIF R6 L6 
      69 [-]: NAMECALL R6 R5 K21 [0xFA9E477F]
      70 [-]: CALL R6 1 1  
      71 [-]: MOVE R9 R1   
      72 [-]: NAMECALL R7 R6 K22 [0xD9CE0673]
      73 [-]: CALL R7 2 0  
L 6:  74 [-]: FORNLOOP R2 L4
L 7:  75 [-]: RETURN R0 0  


; Name:            
; Defined at line: 939
; #Upvalues:       10
; #Parameters:     1
; Is_vararg:       0
; Max Stack Size:  10

       0 [-]: FASTCALL1 62 R0 L0
       1 [-]: MOVE R2 R0   
       2 [-]: GETIMPORT R1 1 [0x7B998233]
       3 [-]: CALL R1 1 1  
L 0:   4 [-]: JUMPIF R1 L13
       5 [-]: GETUPVAL R1 0
       6 [-]: GETUPVAL R3 1
       7 [-]: GETTABLEKS R2 R3 K2 ["POWER_TOWER_A"]
       8 [-]: JUMPIFNOTLE R2 R1 L13
       9 [-]: GETUPVAL R1 0
      10 [-]: GETUPVAL R3 1
      11 [-]: GETTABLEKS R2 R3 K3 ["TIMESTOP"]
      12 [-]: JUMPIFNOTLT R1 R2 L13
      13 [-]: GETUPVAL R2 2
      14 [-]: LENGTH R1 R2 
      15 [-]: LOADN R2 0   
      16 [-]: JUMPIFNOTLT R2 R1 L13
      17 [-]: GETUPVAL R4 2
      18 [-]: LENGTH R3 R4 
      19 [-]: LOADN R1 1   
      20 [-]: LOADN R2 -1  
      21 [-]: FORNPREP R1 L6
L 1:  22 [-]: GETUPVAL R5 2
      23 [-]: GETTABLE R4 R5 R3
      24 [-]: JUMPIFNOTEQ R0 R4 L5
      25 [-]: GETIMPORT R4 6 [0x9C1F3B5A]
      26 [-]: GETUPVAL R5 2
      27 [-]: MOVE R6 R3   
      28 [-]: CALL R4 2 0  
      29 [-]: GETIMPORT R4 8 [0x3D106989]
      30 [-]: LOADK R6 K9 ["Remaining devices: "]
      31 [-]: GETUPVAL R8 2
      32 [-]: LENGTH R7 R8 
      33 [-]: CONCAT R5 R6 R7
      34 [-]: CALL R4 1 0  
      35 [-]: GETIMPORT R4 11 [0x89326C93]
      36 [-]: GETIMPORT R6 13 [0xBB76409B]
      37 [-]: NAMECALL R7 R0 K14 [0xD1586535]
      38 [-]: CALL R7 1 1  
      39 [-]: LOADN R8 2   
      40 [-]: NAMECALL R4 R4 K15 [0x4E5939A5]
      41 [-]: CALL R4 4 1  
      42 [-]: FASTCALL1 62 R4 L2
      43 [-]: MOVE R6 R4   
      44 [-]: GETIMPORT R5 1 [0x7B998233]
      45 [-]: CALL R5 1 1  
L 2:  46 [-]: JUMPIF R5 L3 
      47 [-]: NAMECALL R5 R4 K16 [0xF4E253B6]
      48 [-]: CALL R5 1 0  
L 3:  49 [-]: GETUPVAL R6 3
      50 [-]: GETTABLEKS R5 R6 K17 [0x46749D86]
      51 [-]: CALL R5 0 1  
      52 [-]: FASTCALL1 62 R5 L4
      53 [-]: MOVE R7 R5   
      54 [-]: GETIMPORT R6 1 [0x7B998233]
      55 [-]: CALL R6 1 1  
L 4:  56 [-]: JUMPIF R6 L6 
      57 [-]: GETTABLEKS R6 R5 K18 ["Data"]
      58 [-]: GETTABLEKS R9 R5 K18 ["Data"]
      59 [-]: GETTABLEKS R8 R9 K20 ["Time"]
      60 [-]: ADDK R7 R8 K19 [15]
      61 [-]: SETTABLEKS R7 R6 K20 ["Time"]
      62 [-]: JUMP L6
     
L 5:  63 [-]: FORNLOOP R1 L1
L 6:  64 [-]: GETUPVAL R2 3
      65 [-]: GETTABLEKS R1 R2 K21 [0xF3928F38]
      66 [-]: GETUPVAL R3 4
      67 [-]: GETUPVAL R5 2
      68 [-]: LENGTH R4 R5 
      69 [-]: SUB R2 R3 R4 
      70 [-]: GETUPVAL R3 4
      71 [-]: CALL R1 2 0  
      72 [-]: GETUPVAL R2 2
      73 [-]: LENGTH R1 R2 
      74 [-]: LOADN R2 0   
      75 [-]: JUMPIFNOTLE R1 R2 L13
      76 [-]: GETUPVAL R2 5
      77 [-]: GETTABLEKS R1 R2 K22 ["goToNextLevel"]
      78 [-]: GETUPVAL R2 0
      79 [-]: GETUPVAL R4 1
      80 [-]: GETTABLEKS R3 R4 K2 ["POWER_TOWER_A"]
      81 [-]: JUMPIFNOTEQ R2 R3 L7
      82 [-]: GETUPVAL R2 6
      83 [-]: GETIMPORT R3 24 [0x0469F296]
      84 [-]: LOADK R4 K25 ["TeleportToTowerBMarker"]
      85 [-]: CALL R3 1 1  
      86 [-]: LOADB R4 1   
      87 [-]: CALL R2 2 0  
      88 [-]: GETIMPORT R2 11 [0x89326C93]
      89 [-]: GETIMPORT R4 24 [0x0469F296]
      90 [-]: LOADK R5 K26 ["UnumTowerB"]
      91 [-]: CALL R4 1 -1 
      92 [-]: NAMECALL R2 R2 K27 [0x46A0EBF5]
      93 [-]: CALL R2 -1 1 
      94 [-]: SETUPVAL R2 7
      95 [-]: JUMP L12
    
L 7:  96 [-]: GETUPVAL R2 0
      97 [-]: GETUPVAL R4 1
      98 [-]: GETTABLEKS R3 R4 K28 ["POWER_TOWER_B"]
      99 [-]: JUMPIFNOTEQ R2 R3 L8
     100 [-]: GETUPVAL R2 6
     101 [-]: GETIMPORT R3 24 [0x0469F296]
     102 [-]: LOADK R4 K29 ["TeleportToTowerCMarker"]
     103 [-]: CALL R3 1 1  
     104 [-]: LOADB R4 1   
     105 [-]: CALL R2 2 0  
     106 [-]: GETIMPORT R2 11 [0x89326C93]
     107 [-]: GETIMPORT R4 24 [0x0469F296]
     108 [-]: LOADK R5 K30 ["UnumTowerC"]
     109 [-]: CALL R4 1 -1 
     110 [-]: NAMECALL R2 R2 K27 [0x46A0EBF5]
     111 [-]: CALL R2 -1 1 
     112 [-]: SETUPVAL R2 7
     113 [-]: JUMP L12
    
L 8: 114 [-]: GETUPVAL R2 0
     115 [-]: GETUPVAL R4 1
     116 [-]: GETTABLEKS R3 R4 K31 ["POWER_TOWER_C"]
     117 [-]: JUMPIFNOTEQ R2 R3 L9
     118 [-]: GETUPVAL R2 6
     119 [-]: GETIMPORT R3 24 [0x0469F296]
     120 [-]: LOADK R4 K32 ["TeleportToRoofMarker"]
     121 [-]: CALL R3 1 1  
     122 [-]: LOADB R4 1   
     123 [-]: CALL R2 2 0  
     124 [-]: GETIMPORT R2 11 [0x89326C93]
     125 [-]: GETIMPORT R4 24 [0x0469F296]
     126 [-]: LOADK R5 K33 ["UnumTowerRoof"]
     127 [-]: CALL R4 1 -1 
     128 [-]: NAMECALL R2 R2 K27 [0x46A0EBF5]
     129 [-]: CALL R2 -1 1 
     130 [-]: SETUPVAL R2 7
     131 [-]: JUMP L12
    
L 9: 132 [-]: GETUPVAL R2 0
     133 [-]: GETUPVAL R4 1
     134 [-]: GETTABLEKS R3 R4 K34 ["TOWER_ROOF"]
     135 [-]: JUMPIFNOTEQ R2 R3 L12
     136 [-]: GETUPVAL R2 5
     137 [-]: GETTABLEKS R1 R2 K35 ["reachMurex"]
     138 [-]: GETUPVAL R3 8
     139 [-]: FASTCALL1 62 R3 L10
     140 [-]: GETIMPORT R2 1 [0x7B998233]
     141 [-]: CALL R2 1 1  
L10: 142 [-]: JUMPIF R2 L11
     143 [-]: GETUPVAL R2 8
     144 [-]: NAMECALL R2 R2 K36 [0x22DA1852]
     145 [-]: CALL R2 1 1  
     146 [-]: GETUPVAL R3 9
     147 [-]: JUMPIFEQ R2 R3 L12
L11: 148 [-]: GETIMPORT R2 11 [0x89326C93]
     149 [-]: GETUPVAL R4 9
     150 [-]: NAMECALL R2 R2 K27 [0x46A0EBF5]
     151 [-]: CALL R2 2 1  
     152 [-]: SETUPVAL R2 8
     153 [-]: GETIMPORT R2 38 [0x11A19C5E]
     154 [-]: GETUPVAL R3 8
     155 [-]: LOADK R4 K39 ["OnTouched"]
     156 [-]: CALL R2 2 0  
     157 [-]: GETUPVAL R2 6
     158 [-]: GETIMPORT R3 24 [0x0469F296]
     159 [-]: LOADK R4 K40 ["LightBridgeMarker"]
     160 [-]: CALL R3 1 1  
     161 [-]: LOADB R4 1   
     162 [-]: CALL R2 2 0  
L12: 163 [-]: GETUPVAL R3 3
     164 [-]: GETTABLEKS R2 R3 K41 [0xA1DF01D6]
     165 [-]: MOVE R3 R1   
     166 [-]: CALL R2 1 0  
     167 [-]: LOADNIL R2   
     168 [-]: SETUPVAL R2 2
L13: 169 [-]: RETURN R0 0  


; Name:            
; Defined at line: 997
; #Upvalues:       0
; #Parameters:     1
; Is_vararg:       0
; Max Stack Size:  8

       0 [-]: FASTCALL1 62 R0 L0
       1 [-]: MOVE R2 R0   
       2 [-]: GETIMPORT R1 1 [0x7B998233]
       3 [-]: CALL R1 1 1  
L 0:   4 [-]: JUMPIF R1 L6 
       5 [-]: NAMECALL R1 R0 K2 [0xBB610E5B]
       6 [-]: CALL R1 1 1  
       7 [-]: FASTCALL1 62 R1 L1
       8 [-]: MOVE R3 R1   
       9 [-]: GETIMPORT R2 1 [0x7B998233]
      10 [-]: CALL R2 1 1  
L 1:  11 [-]: JUMPIF R2 L2 
      12 [-]: NAMECALL R2 R1 K3 [0x808B79E6]
      13 [-]: CALL R2 1 1  
      14 [-]: GETIMPORT R3 5 [0x0469F296]
      15 [-]: LOADK R4 K6 ["Sentient"]
      16 [-]: CALL R3 1 1  
      17 [-]: JUMPIFNOTEQ R2 R3 L2
      18 [-]: GETIMPORT R2 8 [0x89326C93]
      19 [-]: GETIMPORT R4 10 [0x74704AF0]
      20 [-]: NAMECALL R5 R1 K11 [0xD1586535]
      21 [-]: CALL R5 1 1  
      22 [-]: GETIMPORT R6 13 ["ZERO_ROTATION"]
      23 [-]: NAMECALL R2 R2 K14 [0x05909209]
      24 [-]: CALL R2 4 0  
      25 [-]: GETIMPORT R4 16 [0x7ED0A956]
      26 [-]: LOADK R5 K17 ["/Lotus/Types/Enemies/Sentients/Clotholyst/SentientClotholystAvatar"]
      27 [-]: CALL R4 1 -1 
      28 [-]: NAMECALL R2 R1 K18 [0xF2DEAF69]
      29 [-]: CALL R2 -1 1 
      30 [-]: JUMPIFNOT R2 L6
      31 [-]: NAMECALL R2 R1 K19 [0x1AC1655C]
      32 [-]: CALL R2 1 1  
      33 [-]: LOADB R5 0   
      34 [-]: NAMECALL R3 R2 K20 [0x35577788]
      35 [-]: CALL R3 2 0  
      36 [-]: RETURN R0 0  
L 2:  37 [-]: GETIMPORT R2 22 [0x3D106989]
      38 [-]: LOADK R4 K23 ["Shouldn't add sentient spawn effect to not-sentients: "]
      39 [-]: FASTCALL1 62 R1 L3
      40 [-]: MOVE R7 R1   
      41 [-]: GETIMPORT R6 1 [0x7B998233]
      42 [-]: CALL R6 1 1  
L 3:  43 [-]: JUMPIF R6 L4 
      44 [-]: NAMECALL R5 R1 K24 [0xE223E2B1]
      45 [-]: CALL R5 1 1  
      46 [-]: JUMPIF R5 L5 
L 4:  47 [-]: LOADK R5 K25 [""]
L 5:  48 [-]: CONCAT R3 R4 R5
      49 [-]: CALL R2 1 0  
L 6:  50 [-]: RETURN R0 0  


; Name:            
; Defined at line: 1012
; #Upvalues:       5
; #Parameters:     2
; Is_vararg:       0
; Max Stack Size:  28

       0 [-]: GETIMPORT R2 1 ["_T"]
       1 [-]: LOADB R3 0   
       2 [-]: SETTABLEKS R3 R2 K2 ["IsRandomWhisperActive"]
       3 [-]: SETUPVAL R1 0
L 0:   4 [-]: GETUPVAL R3 0
       5 [-]: FASTCALL1 62 R3 L1
       6 [-]: GETIMPORT R2 4 [0x7B998233]
       7 [-]: CALL R2 1 1  
L 1:   8 [-]: JUMPIFNOT R2 L2
       9 [-]: GETIMPORT R2 6 [0xCBD666E1]
      10 [-]: LOADN R3 0   
      11 [-]: CALL R2 1 0  
      12 [-]: GETIMPORT R2 8 [0x89326C93]
      13 [-]: NAMECALL R2 R2 K9 [0x78298275]
      14 [-]: CALL R2 1 1  
      15 [-]: SETUPVAL R2 0
      16 [-]: JUMPBACK L0  
L 2:  17 [-]: GETUPVAL R3 0
      18 [-]: FASTCALL1 62 R3 L3
      19 [-]: GETIMPORT R2 4 [0x7B998233]
      20 [-]: CALL R2 1 1  
L 3:  21 [-]: JUMPIF R2 L50
      22 [-]: GETUPVAL R2 0
      23 [-]: NAMECALL R2 R2 K10 [0x2047CFE7]
      24 [-]: CALL R2 1 1  
      25 [-]: JUMPIF R2 L50
      26 [-]: GETUPVAL R3 1
      27 [-]: GETTABLEKS R2 R3 K11 [0x323C12AB]
      28 [-]: GETUPVAL R3 0
      29 [-]: CALL R2 1 1  
      30 [-]: SETUPVAL R2 0
      31 [-]: GETIMPORT R2 13 ["WRAITH_ForceBackToWraith"]
      32 [-]: JUMPIFNOT R2 L5
      33 [-]: GETIMPORT R2 13 ["WRAITH_ForceBackToWraith"]
      34 [-]: GETUPVAL R3 0
      35 [-]: CALL R2 1 1  
      36 [-]: FASTCALL1 62 R2 L4
      37 [-]: MOVE R4 R2   
      38 [-]: GETIMPORT R3 4 [0x7B998233]
      39 [-]: CALL R3 1 1  
L 4:  40 [-]: JUMPIF R3 L5 
      41 [-]: SETUPVAL R2 0
L 5:  42 [-]: GETUPVAL R2 0
      43 [-]: NAMECALL R2 R2 K14 [0xDE321E6F]
      44 [-]: CALL R2 1 1  
      45 [-]: NAMECALL R2 R2 K15 [0xF7D48EE0]
      46 [-]: CALL R2 1 1  
      47 [-]: FASTCALL1 62 R2 L6
      48 [-]: MOVE R4 R2   
      49 [-]: GETIMPORT R3 4 [0x7B998233]
      50 [-]: CALL R3 1 1  
L 6:  51 [-]: JUMPIF R3 L10
      52 [-]: GETIMPORT R5 17 [0x7ED0A956]
      53 [-]: LOADK R6 K18 ["/Lotus/Powersuits/PowersuitAbilities/FairyFlightAbility"]
      54 [-]: CALL R5 1 -1 
      55 [-]: NAMECALL R3 R2 K19 [0x689412A5]
      56 [-]: CALL R3 -1 1 
      57 [-]: FASTCALL1 62 R3 L7
      58 [-]: MOVE R5 R3   
      59 [-]: GETIMPORT R4 4 [0x7B998233]
      60 [-]: CALL R4 1 1  
L 7:  61 [-]: JUMPIF R4 L10
      62 [-]: NAMECALL R4 R3 K20 [0xD8140B94]
      63 [-]: CALL R4 1 1  
      64 [-]: JUMPIFNOT R4 L10
      65 [-]: NAMECALL R4 R3 K21 [0x6FB82A8B]
      66 [-]: CALL R4 1 1  
      67 [-]: JUMPIF R4 L8 
      68 [-]: NAMECALL R4 R3 K22 [0x585FD25A]
      69 [-]: CALL R4 1 0  
L 8:  70 [-]: FASTCALL1 62 R3 L9
      71 [-]: MOVE R5 R3   
      72 [-]: GETIMPORT R4 4 [0x7B998233]
      73 [-]: CALL R4 1 1  
L 9:  74 [-]: JUMPIF R4 L10
      75 [-]: NAMECALL R4 R3 K20 [0xD8140B94]
      76 [-]: CALL R4 1 1  
      77 [-]: JUMPIFNOT R4 L10
      78 [-]: GETUPVAL R4 0
      79 [-]: NAMECALL R4 R4 K23 [0x4094B424]
      80 [-]: CALL R4 1 0  
      81 [-]: GETIMPORT R4 6 [0xCBD666E1]
      82 [-]: LOADN R5 0   
      83 [-]: CALL R4 1 0  
      84 [-]: JUMPBACK L8  
L10:  85 [-]: GETUPVAL R3 0
      86 [-]: NAMECALL R3 R3 K23 [0x4094B424]
      87 [-]: CALL R3 1 0  
      88 [-]: GETUPVAL R3 0
      89 [-]: GETUPVAL R5 2
      90 [-]: NAMECALL R3 R3 K24 [0x89F5ABE4]
      91 [-]: CALL R3 2 0  
      92 [-]: GETUPVAL R3 0
      93 [-]: NAMECALL R3 R3 K25 [0x1AC1655C]
      94 [-]: CALL R3 1 1  
      95 [-]: GETIMPORT R5 27 [0x0469F296]
      96 [-]: LOADK R6 K28 ["UNUM_INVULNERABLE"]
      97 [-]: CALL R5 1 1  
      98 [-]: LOADN R6 25  
      99 [-]: LOADN R7 6   
     100 [-]: LOADN R8 0   
     101 [-]: NAMECALL R3 R3 K29 [0xA383DE31]
     102 [-]: CALL R3 5 0  
     103 [-]: GETUPVAL R4 1
     104 [-]: GETTABLEKS R3 R4 K30 [0x9E3D3434]
     105 [-]: LOADB R4 1   
     106 [-]: CALL R3 1 0  
     107 [-]: GETIMPORT R3 1 ["_T"]
     108 [-]: LOADN R4 0   
     109 [-]: SETTABLEKS R4 R3 K31 ["ForcePostCameraAlpha"]
     110 [-]: GETUPVAL R3 0
     111 [-]: GETIMPORT R5 33 ["gLotusOperatorAvatarType"]
     112 [-]: NAMECALL R3 R3 K34 [0xF2DEAF69]
     113 [-]: CALL R3 2 1  
     114 [-]: JUMPIFNOT R3 L15
     115 [-]: GETUPVAL R3 0
     116 [-]: GETUPVAL R6 2
     117 [-]: NAMECALL R4 R3 K35 [0xAF7C1D8D]
     118 [-]: CALL R4 2 0  
     119 [-]: NAMECALL R4 R3 K25 [0x1AC1655C]
     120 [-]: CALL R4 1 1  
     121 [-]: GETIMPORT R6 27 [0x0469F296]
     122 [-]: LOADK R7 K28 ["UNUM_INVULNERABLE"]
     123 [-]: CALL R6 1 -1 
     124 [-]: NAMECALL R4 R4 K36 [0x8E3E343E]
     125 [-]: CALL R4 -1 0 
     126 [-]: GETIMPORT R4 1 ["_T"]
     127 [-]: LOADB R5 1   
     128 [-]: SETTABLEKS R5 R4 K37 ["HideTransferenceFx"]
     129 [-]: GETUPVAL R4 0
     130 [-]: NAMECALL R4 R4 K38 [0x18F03C5D]
     131 [-]: CALL R4 1 0  
L11: 132 [-]: GETUPVAL R5 0
     133 [-]: FASTCALL1 62 R5 L12
     134 [-]: GETIMPORT R4 4 [0x7B998233]
     135 [-]: CALL R4 1 1  
L12: 136 [-]: JUMPIF R4 L13
     137 [-]: GETUPVAL R4 0
     138 [-]: GETIMPORT R6 33 ["gLotusOperatorAvatarType"]
     139 [-]: NAMECALL R4 R4 K34 [0xF2DEAF69]
     140 [-]: CALL R4 2 1  
     141 [-]: JUMPIFNOT R4 L14
L13: 142 [-]: GETIMPORT R4 6 [0xCBD666E1]
     143 [-]: LOADN R5 0   
     144 [-]: CALL R4 1 0  
     145 [-]: GETIMPORT R4 8 [0x89326C93]
     146 [-]: NAMECALL R4 R4 K9 [0x78298275]
     147 [-]: CALL R4 1 1  
     148 [-]: SETUPVAL R4 0
     149 [-]: JUMPBACK L11 
L14: 150 [-]: GETIMPORT R4 1 ["_T"]
     151 [-]: LOADNIL R5   
     152 [-]: SETTABLEKS R5 R4 K37 ["HideTransferenceFx"]
     153 [-]: GETUPVAL R4 0
     154 [-]: GETUPVAL R6 2
     155 [-]: NAMECALL R4 R4 K24 [0x89F5ABE4]
     156 [-]: CALL R4 2 0  
     157 [-]: GETUPVAL R4 0
     158 [-]: NAMECALL R4 R4 K25 [0x1AC1655C]
     159 [-]: CALL R4 1 1  
     160 [-]: GETIMPORT R6 27 [0x0469F296]
     161 [-]: LOADK R7 K28 ["UNUM_INVULNERABLE"]
     162 [-]: CALL R6 1 1  
     163 [-]: LOADN R7 25  
     164 [-]: LOADN R8 6   
     165 [-]: LOADN R9 0   
     166 [-]: NAMECALL R4 R4 K29 [0xA383DE31]
     167 [-]: CALL R4 5 0  
L15: 168 [-]: GETIMPORT R4 40 [0xE3DE8AFA]
     169 [-]: FASTCALL1 62 R4 L16
     170 [-]: GETIMPORT R3 4 [0x7B998233]
     171 [-]: CALL R3 1 1  
L16: 172 [-]: JUMPIF R3 L18
     173 [-]: GETUPVAL R4 0
     174 [-]: NAMECALL R4 R4 K41 [0x0B4BCFB6]
     175 [-]: CALL R4 1 1  
     176 [-]: FASTCALL1 62 R4 L17
     177 [-]: GETIMPORT R3 4 [0x7B998233]
     178 [-]: CALL R3 1 1  
L17: 179 [-]: JUMPIF R3 L18
     180 [-]: GETUPVAL R3 0
     181 [-]: NAMECALL R3 R3 K41 [0x0B4BCFB6]
     182 [-]: CALL R3 1 1  
     183 [-]: GETIMPORT R5 40 [0xE3DE8AFA]
     184 [-]: LOADN R6 1   
     185 [-]: NAMECALL R3 R3 K42 [0x14C7F7DD]
     186 [-]: CALL R3 3 0  
L18: 187 [-]: GETIMPORT R3 6 [0xCBD666E1]
     188 [-]: GETIMPORT R4 44 [0xDDA7E021]
     189 [-]: CALL R3 1 0  
     190 [-]: NEWCLOSURE R3 P0
     191 [-]: MOVE R2 R0   
     192 [-]: GETIMPORT R4 46 [0xEA84B669]
     193 [-]: JUMPIFNOT R4 L19
     194 [-]: MOVE R4 R3   
     195 [-]: NAMECALL R5 R0 K47 [0xD1586535]
     196 [-]: CALL R5 1 1  
     197 [-]: NAMECALL R6 R0 K48 [0xCB3851B8]
     198 [-]: CALL R6 1 -1 
     199 [-]: CALL R4 -1 0 
     200 [-]: GETIMPORT R4 6 [0xCBD666E1]
     201 [-]: LOADN R5 1   
     202 [-]: CALL R4 1 0  
L19: 203 [-]: GETIMPORT R5 50 [0xA1E4D292]
     204 [-]: FASTCALL1 62 R5 L20
     205 [-]: GETIMPORT R4 4 [0x7B998233]
     206 [-]: CALL R4 1 1  
L20: 207 [-]: JUMPIF R4 L21
     208 [-]: GETUPVAL R4 0
     209 [-]: GETIMPORT R6 50 [0xA1E4D292]
     210 [-]: LOADB R7 0   
     211 [-]: LOADN R8 3   
     212 [-]: LOADN R9 2   
     213 [-]: LOADB R10 1  
     214 [-]: NAMECALL R4 R4 K51 [0x5D985C7E]
     215 [-]: CALL R4 6 0  
L21: 216 [-]: NAMECALL R4 R0 K47 [0xD1586535]
     217 [-]: CALL R4 1 1  
     218 [-]: LOADN R5 0   
     219 [-]: GETUPVAL R6 0
     220 [-]: NAMECALL R6 R6 K52 [0xF6EBD926]
     221 [-]: CALL R6 1 1  
     222 [-]: GETIMPORT R8 54 [0xA421AF95]
     223 [-]: LOADN R9 0   
     224 [-]: GETIMPORT R10 56 [0x939027D4]
     225 [-]: LOADN R11 0  
     226 [-]: CALL R8 3 1  
     227 [-]: ADD R7 R6 R8 
     228 [-]: GETTABLEKS R8 R4 K57 ["x"]
     229 [-]: SETTABLEKS R8 R7 K57 ["x"]
     230 [-]: GETTABLEKS R8 R4 K58 ["z"]
     231 [-]: SETTABLEKS R8 R7 K58 ["z"]
     232 [-]: GETUPVAL R8 0
     233 [-]: NAMECALL R8 R8 K59 [0x5280B883]
     234 [-]: CALL R8 1 1  
L22: 235 [-]: GETIMPORT R9 61 [0xA3D2EB12]
     236 [-]: JUMPIFNOTLT R5 R9 L23
     237 [-]: GETIMPORT R9 63 [0x67652851]
     238 [-]: CALL R9 0 1  
     239 [-]: ADD R5 R5 R9 
     240 [-]: GETIMPORT R9 65 [0x5DB3CE80]
     241 [-]: MOVE R10 R6  
     242 [-]: MOVE R11 R7  
     243 [-]: GETIMPORT R13 61 [0xA3D2EB12]
     244 [-]: DIV R12 R5 R13
     245 [-]: CALL R9 3 1  
     246 [-]: GETUPVAL R10 0
     247 [-]: MOVE R12 R9  
     248 [-]: MOVE R13 R8  
     249 [-]: NAMECALL R10 R10 K66 [0x589EF1C1]
     250 [-]: CALL R10 3 0 
     251 [-]: GETIMPORT R10 6 [0xCBD666E1]
     252 [-]: LOADN R11 0  
     253 [-]: CALL R10 1 0 
     254 [-]: JUMPBACK L22 
L23: 255 [-]: GETUPVAL R9 0
     256 [-]: LOADN R11 27 
     257 [-]: LOADB R12 0  
     258 [-]: NAMECALL R9 R9 K67 [0x30EB0CC3]
     259 [-]: CALL R9 3 0  
     260 [-]: GETIMPORT R11 69 [0x535A567C]
     261 [-]: FASTCALL1 62 R11 L24
     262 [-]: GETIMPORT R10 4 [0x7B998233]
     263 [-]: CALL R10 1 1 
L24: 264 [-]: JUMPIF R10 L25
     265 [-]: GETIMPORT R9 8 [0x89326C93]
     266 [-]: GETIMPORT R11 69 [0x535A567C]
     267 [-]: NAMECALL R9 R9 K70 [0x46A0EBF5]
     268 [-]: CALL R9 2 1  
     269 [-]: JUMPIF R9 L26
L25: 270 [-]: LOADNIL R9   
L26: 271 [-]: GETUPVAL R11 0
     272 [-]: NAMECALL R11 R11 K41 [0x0B4BCFB6]
     273 [-]: CALL R11 1 1 
     274 [-]: FASTCALL1 62 R11 L27
     275 [-]: GETIMPORT R10 4 [0x7B998233]
     276 [-]: CALL R10 1 1 
L27: 277 [-]: JUMPIF R10 L30
     278 [-]: FASTCALL1 62 R9 L28
     279 [-]: MOVE R11 R9  
     280 [-]: GETIMPORT R10 4 [0x7B998233]
     281 [-]: CALL R10 1 1 
L28: 282 [-]: JUMPIF R10 L29
     283 [-]: GETIMPORT R10 72 [0xBBADA53A]
     284 [-]: JUMPIFNOT R10 L29
     285 [-]: LOADK R12 K73 ["Activate"]
     286 [-]: NAMECALL R10 R9 K74 [0x8EB2112D]
     287 [-]: CALL R10 2 0 
     288 [-]: JUMP L30
    
L29: 289 [-]: GETUPVAL R10 0
     290 [-]: NAMECALL R10 R10 K41 [0x0B4BCFB6]
     291 [-]: CALL R10 1 1 
     292 [-]: LOADNIL R12  
     293 [-]: NAMECALL R10 R10 K42 [0x14C7F7DD]
     294 [-]: CALL R10 2 0 
L30: 295 [-]: NAMECALL R10 R0 K75 [0x9BA17154]
     296 [-]: CALL R10 1 1 
     297 [-]: GETIMPORT R12 77 [0x74DB6B8A]
     298 [-]: FASTCALL1 62 R12 L31
     299 [-]: GETIMPORT R11 4 [0x7B998233]
     300 [-]: CALL R11 1 1 
L31: 301 [-]: JUMPIF R11 L33
     302 [-]: GETIMPORT R11 8 [0x89326C93]
     303 [-]: GETIMPORT R13 79 [0x1FD80F7C]
     304 [-]: NAMECALL R11 R11 K70 [0x46A0EBF5]
     305 [-]: CALL R11 2 1 
     306 [-]: SETUPVAL R11 3
     307 [-]: GETUPVAL R12 3
     308 [-]: FASTCALL1 62 R12 L32
     309 [-]: GETIMPORT R11 4 [0x7B998233]
     310 [-]: CALL R11 1 1 
L32: 311 [-]: JUMPIF R11 L33
     312 [-]: GETUPVAL R11 3
     313 [-]: NAMECALL R11 R11 K75 [0x9BA17154]
     314 [-]: CALL R11 1 1 
     315 [-]: MOVE R10 R11 
     316 [-]: GETIMPORT R11 77 [0x74DB6B8A]
     317 [-]: LOADK R13 K80 ["Enable"]
     318 [-]: NAMECALL R11 R11 K74 [0x8EB2112D]
     319 [-]: CALL R11 2 0 
L33: 320 [-]: LOADNIL R11  
     321 [-]: LOADNIL R12  
     322 [-]: LOADNIL R13  
     323 [-]: LOADNIL R14  
     324 [-]: LOADNIL R15  
     325 [-]: LOADNIL R16  
     326 [-]: NEWCLOSURE R17 P1
     327 [-]: MOVE R1 R13  
     328 [-]: MOVE R1 R14  
     329 [-]: MOVE R1 R15  
     330 [-]: MOVE R1 R16  
     331 [-]: MOVE R1 R11  
     332 [-]: MOVE R1 R12  
     333 [-]: GETUPVAL R19 3
     334 [-]: FASTCALL1 62 R19 L34
     335 [-]: GETIMPORT R18 4 [0x7B998233]
     336 [-]: CALL R18 1 1 
L34: 337 [-]: JUMPIF R18 L39
     338 [-]: GETUPVAL R18 3
     339 [-]: NAMECALL R18 R18 K47 [0xD1586535]
     340 [-]: CALL R18 1 1 
     341 [-]: GETIMPORT R19 8 [0x89326C93]
     342 [-]: GETUPVAL R22 4
     343 [-]: GETTABLEKS R21 R22 K81 ["ENERGY_BEAM_INNER"]
     344 [-]: MOVE R22 R18 
     345 [-]: LOADN R23 0  
     346 [-]: LOADN R24 300
     347 [-]: NAMECALL R19 R19 K82 [0xF16592C8]
     348 [-]: CALL R19 5 1 
     349 [-]: MOVE R11 R19 
     350 [-]: GETIMPORT R19 8 [0x89326C93]
     351 [-]: GETUPVAL R22 4
     352 [-]: GETTABLEKS R21 R22 K83 ["ENERGY_BEAM_OUTTER"]
     353 [-]: MOVE R22 R18 
     354 [-]: LOADN R23 0  
     355 [-]: LOADN R24 300
     356 [-]: NAMECALL R19 R19 K82 [0xF16592C8]
     357 [-]: CALL R19 5 1 
     358 [-]: MOVE R12 R19 
     359 [-]: GETIMPORT R19 8 [0x89326C93]
     360 [-]: GETUPVAL R22 4
     361 [-]: GETTABLEKS R21 R22 K84 ["RED_LIGHT"]
     362 [-]: MOVE R22 R18 
     363 [-]: NAMECALL R19 R19 K85 [0xC7B81E8D]
     364 [-]: CALL R19 3 1 
     365 [-]: MOVE R13 R19 
     366 [-]: GETIMPORT R19 8 [0x89326C93]
     367 [-]: GETUPVAL R22 4
     368 [-]: GETTABLEKS R21 R22 K86 ["BLUE_LIGHT"]
     369 [-]: MOVE R22 R18 
     370 [-]: NAMECALL R19 R19 K85 [0xC7B81E8D]
     371 [-]: CALL R19 3 1 
     372 [-]: MOVE R14 R19 
     373 [-]: GETIMPORT R19 8 [0x89326C93]
     374 [-]: GETUPVAL R22 4
     375 [-]: GETTABLEKS R21 R22 K87 ["RED_SOUND"]
     376 [-]: MOVE R22 R18 
     377 [-]: NAMECALL R19 R19 K85 [0xC7B81E8D]
     378 [-]: CALL R19 3 1 
     379 [-]: MOVE R15 R19 
     380 [-]: GETIMPORT R19 8 [0x89326C93]
     381 [-]: GETUPVAL R22 4
     382 [-]: GETTABLEKS R21 R22 K88 ["BLUE_SOUND"]
     383 [-]: MOVE R22 R18 
     384 [-]: NAMECALL R19 R19 K85 [0xC7B81E8D]
     385 [-]: CALL R19 3 1 
     386 [-]: MOVE R16 R19 
     387 [-]: GETIMPORT R19 46 [0xEA84B669]
     388 [-]: JUMPIFNOT R19 L35
     389 [-]: MOVE R19 R17 
     390 [-]: LOADB R20 1  
     391 [-]: CALL R19 1 0 
L35: 392 [-]: GETUPVAL R19 0
     393 [-]: LOADN R21 27 
     394 [-]: LOADB R22 1  
     395 [-]: NAMECALL R19 R19 K67 [0x30EB0CC3]
     396 [-]: CALL R19 3 0 
L36: 397 [-]: GETUPVAL R19 0
     398 [-]: GETUPVAL R21 3
     399 [-]: NAMECALL R19 R19 K89 [0x9B2E6C87]
     400 [-]: CALL R19 2 1 
     401 [-]: LOADN R20 1  
     402 [-]: JUMPIFNOTLT R20 R19 L37
     403 [-]: GETIMPORT R19 6 [0xCBD666E1]
     404 [-]: LOADN R20 0  
     405 [-]: CALL R19 1 0 
     406 [-]: JUMPBACK L36 
L37: 407 [-]: GETIMPORT R19 6 [0xCBD666E1]
     408 [-]: LOADN R20 1  
     409 [-]: CALL R19 1 0 
     410 [-]: GETUPVAL R19 0
     411 [-]: LOADN R21 27 
     412 [-]: LOADB R22 0  
     413 [-]: NAMECALL R19 R19 K67 [0x30EB0CC3]
     414 [-]: CALL R19 3 0 
     415 [-]: GETIMPORT R20 50 [0xA1E4D292]
     416 [-]: FASTCALL1 62 R20 L38
     417 [-]: GETIMPORT R19 4 [0x7B998233]
     418 [-]: CALL R19 1 1 
L38: 419 [-]: JUMPIF R19 L39
     420 [-]: GETUPVAL R19 0
     421 [-]: GETIMPORT R21 50 [0xA1E4D292]
     422 [-]: LOADB R22 0  
     423 [-]: LOADN R23 3  
     424 [-]: LOADN R24 2  
     425 [-]: LOADB R25 1  
     426 [-]: NAMECALL R19 R19 K51 [0x5D985C7E]
     427 [-]: CALL R19 6 0 
L39: 428 [-]: LOADN R5 0   
     429 [-]: GETUPVAL R18 0
     430 [-]: NAMECALL R18 R18 K52 [0xF6EBD926]
     431 [-]: CALL R18 1 1 
     432 [-]: MOVE R6 R18  
     433 [-]: GETIMPORT R18 54 [0xA421AF95]
     434 [-]: LOADN R19 0  
     435 [-]: GETIMPORT R20 91 [0x0EE3FF63]
     436 [-]: LOADN R21 0  
     437 [-]: CALL R18 3 1 
     438 [-]: ADD R7 R6 R18
     439 [-]: GETUPVAL R18 0
     440 [-]: NAMECALL R18 R18 K59 [0x5280B883]
     441 [-]: CALL R18 1 1 
     442 [-]: MOVE R8 R18  
     443 [-]: LOADB R18 0  
     444 [-]: GETIMPORT R19 93 [0x26A3B2DB]
L40: 445 [-]: JUMPIFNOTLT R5 R19 L42
     446 [-]: GETIMPORT R20 63 [0x67652851]
     447 [-]: CALL R20 0 1 
     448 [-]: ADD R5 R5 R20
     449 [-]: GETIMPORT R20 65 [0x5DB3CE80]
     450 [-]: MOVE R21 R6  
     451 [-]: MOVE R22 R7  
     452 [-]: DIV R23 R5 R19
     453 [-]: CALL R20 3 1 
     454 [-]: GETUPVAL R21 0
     455 [-]: MOVE R23 R20 
     456 [-]: MOVE R24 R8  
     457 [-]: NAMECALL R21 R21 K66 [0x589EF1C1]
     458 [-]: CALL R21 3 0 
     459 [-]: GETIMPORT R21 46 [0xEA84B669]
     460 [-]: JUMPIFNOT R21 L41
     461 [-]: JUMPIF R18 L41
     462 [-]: LOADK R22 K94 [0.80000000000000004]
     463 [-]: MUL R21 R22 R19
     464 [-]: JUMPIFNOTLE R21 R5 L41
     465 [-]: LOADB R18 1  
     466 [-]: MOVE R21 R17 
     467 [-]: LOADB R22 0  
     468 [-]: CALL R21 1 0 
L41: 469 [-]: GETIMPORT R21 6 [0xCBD666E1]
     470 [-]: LOADN R22 0  
     471 [-]: CALL R21 1 0 
     472 [-]: JUMPBACK L40 
L42: 473 [-]: GETIMPORT R20 46 [0xEA84B669]
     474 [-]: JUMPIFNOT R20 L43
     475 [-]: JUMPIF R18 L43
     476 [-]: MOVE R20 R17 
     477 [-]: LOADB R21 0  
     478 [-]: CALL R20 1 0 
L43: 479 [-]: GETUPVAL R20 0
     480 [-]: LOADNIL R22  
     481 [-]: LOADB R23 0  
     482 [-]: LOADN R24 0  
     483 [-]: NAMECALL R20 R20 K51 [0x5D985C7E]
     484 [-]: CALL R20 4 0 
     485 [-]: GETIMPORT R20 6 [0xCBD666E1]
     486 [-]: LOADK R21 K95 [0.10000000000000001]
     487 [-]: CALL R20 1 0 
     488 [-]: GETUPVAL R20 0
     489 [-]: GETIMPORT R22 97 [0x6577AF45]
     490 [-]: GETIMPORT R23 99 ["EMPTY_SYMBOL"]
     491 [-]: GETIMPORT R24 54 [0xA421AF95]
     492 [-]: LOADN R25 0  
     493 [-]: LOADN R26 0  
     494 [-]: LOADN R27 0  
     495 [-]: CALL R24 3 1 
     496 [-]: GETIMPORT R25 101 ["ZERO_ROTATION"]
     497 [-]: NAMECALL R20 R20 K102 [0x47901F07]
     498 [-]: CALL R20 5 0 
     499 [-]: FASTCALL1 62 R9 L44
     500 [-]: MOVE R21 R9  
     501 [-]: GETIMPORT R20 4 [0x7B998233]
     502 [-]: CALL R20 1 1 
L44: 503 [-]: JUMPIF R20 L45
     504 [-]: GETIMPORT R20 72 [0xBBADA53A]
     505 [-]: JUMPIF R20 L45
     506 [-]: LOADK R22 K73 ["Activate"]
     507 [-]: NAMECALL R20 R9 K74 [0x8EB2112D]
     508 [-]: CALL R20 2 0 
L45: 509 [-]: GETIMPORT R22 104 [0x1616B06C]
     510 [-]: FASTCALL1 62 R22 L46
     511 [-]: GETIMPORT R21 4 [0x7B998233]
     512 [-]: CALL R21 1 1 
L46: 513 [-]: NOT R20 R21  
     514 [-]: JUMPIFNOT R20 L47
     515 [-]: GETIMPORT R20 8 [0x89326C93]
     516 [-]: GETIMPORT R22 104 [0x1616B06C]
     517 [-]: GETUPVAL R23 0
     518 [-]: NAMECALL R23 R23 K47 [0xD1586535]
     519 [-]: CALL R23 1 -1
     520 [-]: NAMECALL R20 R20 K85 [0xC7B81E8D]
     521 [-]: CALL R20 -1 1
L47: 522 [-]: FASTCALL1 62 R20 L48
     523 [-]: MOVE R22 R20 
     524 [-]: GETIMPORT R21 4 [0x7B998233]
     525 [-]: CALL R21 1 1 
L48: 526 [-]: JUMPIF R21 L49
     527 [-]: GETIMPORT R21 6 [0xCBD666E1]
     528 [-]: LOADK R22 K95 [0.10000000000000001]
     529 [-]: CALL R21 1 0 
     530 [-]: MOVE R21 R3  
     531 [-]: NAMECALL R22 R20 K47 [0xD1586535]
     532 [-]: CALL R22 1 1 
     533 [-]: NAMECALL R23 R20 K48 [0xCB3851B8]
     534 [-]: CALL R23 1 -1
     535 [-]: CALL R21 -1 0
L49: 536 [-]: GETUPVAL R22 1
     537 [-]: GETTABLEKS R21 R22 K30 [0x9E3D3434]
     538 [-]: LOADB R22 0  
     539 [-]: CALL R21 1 0 
     540 [-]: GETIMPORT R21 1 ["_T"]
     541 [-]: LOADNIL R22  
     542 [-]: SETTABLEKS R22 R21 K31 ["ForcePostCameraAlpha"]
     543 [-]: GETUPVAL R21 0
     544 [-]: GETUPVAL R23 2
     545 [-]: NAMECALL R21 R21 K35 [0xAF7C1D8D]
     546 [-]: CALL R21 2 0 
     547 [-]: GETUPVAL R21 0
     548 [-]: NAMECALL R21 R21 K25 [0x1AC1655C]
     549 [-]: CALL R21 1 1 
     550 [-]: GETIMPORT R23 27 [0x0469F296]
     551 [-]: LOADK R24 K28 ["UNUM_INVULNERABLE"]
     552 [-]: CALL R23 1 -1
     553 [-]: NAMECALL R21 R21 K36 [0x8E3E343E]
     554 [-]: CALL R21 -1 0
     555 [-]: GETUPVAL R21 0
     556 [-]: GETUPVAL R23 0
     557 [-]: NAMECALL R23 R23 K47 [0xD1586535]
     558 [-]: CALL R23 1 -1
     559 [-]: NAMECALL R21 R21 K105 [0x5C7A573F]
     560 [-]: CALL R21 -1 0
     561 [-]: GETUPVAL R21 0
     562 [-]: LOADN R23 27 
     563 [-]: LOADB R24 0  
     564 [-]: NAMECALL R21 R21 K67 [0x30EB0CC3]
     565 [-]: CALL R21 3 0 
     566 [-]: CLOSEUPVALS R11
L50: 567 [-]: GETIMPORT R2 1 ["_T"]
     568 [-]: LOADB R3 1   
     569 [-]: SETTABLEKS R3 R2 K2 ["IsRandomWhisperActive"]
     570 [-]: RETURN R0 0  


; Name:            
; Defined at line: 1309
; #Upvalues:       1
; #Parameters:     1
; Is_vararg:       0
; Max Stack Size:  3

       0 [-]: FASTCALL1 62 R0 L0
       1 [-]: MOVE R2 R0   
       2 [-]: GETIMPORT R1 1 [0x7B998233]
       3 [-]: CALL R1 1 1  
L 0:   4 [-]: JUMPIFNOT R1 L1
       5 [-]: RETURN R0 0  
L 1:   6 [-]: GETUPVAL R2 0
       7 [-]: ADDK R1 R2 K2 [1]
       8 [-]: SETUPVAL R1 0
       9 [-]: RETURN R0 0  


; Name:            
; Defined at line: 1318
; #Upvalues:       0
; #Parameters:     0
; Is_vararg:       0
; Max Stack Size:  10

       0 [-]: GETIMPORT R0 1 [0x7ED0A956]
       1 [-]: LOADK R1 K2 ["/Lotus/Types/Player/TennoMainMenuAvatar"]
       2 [-]: CALL R0 1 1  
       3 [-]: GETIMPORT R1 4 [0x89326C93]
       4 [-]: MOVE R3 R0   
       5 [-]: NAMECALL R1 R1 K5 [0xFB669000]
       6 [-]: CALL R1 2 1  
       7 [-]: FASTCALL1 62 R1 L0
       8 [-]: MOVE R3 R1   
       9 [-]: GETIMPORT R2 7 [0x7B998233]
      10 [-]: CALL R2 1 1  
L 0:  11 [-]: JUMPIF R2 L4 
      12 [-]: LENGTH R2 R1 
      13 [-]: LOADN R3 0   
      14 [-]: JUMPIFNOTLT R3 R2 L4
      15 [-]: LENGTH R4 R1 
      16 [-]: LOADN R2 1   
      17 [-]: LOADN R3 -1  
      18 [-]: FORNPREP R2 L4
L 1:  19 [-]: GETTABLE R6 R1 R4
      20 [-]: FASTCALL1 62 R6 L2
      21 [-]: GETIMPORT R5 7 [0x7B998233]
      22 [-]: CALL R5 1 1  
L 2:  23 [-]: JUMPIF R5 L3 
      24 [-]: GETTABLE R5 R1 R4
      25 [-]: NAMECALL R5 R5 K8 [0xA2880940]
      26 [-]: CALL R5 1 0  
L 3:  27 [-]: FORNLOOP R2 L1
L 4:  28 [-]: GETIMPORT R2 4 [0x89326C93]
      29 [-]: GETIMPORT R4 10 [0x0469F296]
      30 [-]: LOADK R5 K11 ["TWNUnumHidden"]
      31 [-]: CALL R4 1 -1 
      32 [-]: NAMECALL R2 R2 K12 [0xC7FCADA9]
      33 [-]: CALL R2 -1 1 
      34 [-]: FASTCALL1 62 R2 L5
      35 [-]: MOVE R4 R2   
      36 [-]: GETIMPORT R3 7 [0x7B998233]
      37 [-]: CALL R3 1 1  
L 5:  38 [-]: JUMPIF R3 L7 
      39 [-]: LENGTH R3 R2 
      40 [-]: LOADN R4 0   
      41 [-]: JUMPIFNOTLT R4 R3 L7
      42 [-]: LOADN R5 1   
      43 [-]: LENGTH R3 R2 
      44 [-]: LOADN R4 1   
      45 [-]: FORNPREP R3 L7
L 6:  46 [-]: GETTABLE R6 R2 R5
      47 [-]: LOADB R8 0   
      48 [-]: LOADB R9 1   
      49 [-]: NAMECALL R6 R6 K13 [0x768274D6]
      50 [-]: CALL R6 3 0  
      51 [-]: FORNLOOP R3 L6
L 7:  52 [-]: RETURN R0 0  


; Name:            
; Defined at line: 1337
; #Upvalues:       1
; #Parameters:     2
; Is_vararg:       0
; Max Stack Size:  12

       0 [-]: LOADN R2 0   
       1 [-]: GETIMPORT R3 1 [0x89326C93]
       2 [-]: MOVE R5 R0   
       3 [-]: NAMECALL R3 R3 K2 [0xC7FCADA9]
       4 [-]: CALL R3 2 1  
       5 [-]: FASTCALL1 62 R3 L0
       6 [-]: MOVE R5 R3   
       7 [-]: GETIMPORT R4 4 [0x7B998233]
       8 [-]: CALL R4 1 1  
L 0:   9 [-]: JUMPIF R4 L5 
      10 [-]: LENGTH R4 R3 
      11 [-]: LOADN R5 0   
      12 [-]: JUMPIFNOTLT R5 R4 L5
      13 [-]: GETIMPORT R4 6 [0xC8802016]
      14 [-]: MOVE R5 R3   
      15 [-]: CALL R4 1 3  
      16 [-]: FORGPREP_INEXT R4 L3
L 1:  17 [-]: FASTCALL1 62 R8 L2
      18 [-]: MOVE R10 R8  
      19 [-]: GETIMPORT R9 4 [0x7B998233]
      20 [-]: CALL R9 1 1  
L 2:  21 [-]: JUMPIF R9 L3 
      22 [-]: NAMECALL R9 R8 K7 [0xF37943FF]
      23 [-]: CALL R9 1 1  
      24 [-]: JUMPIFNOT R9 L3
      25 [-]: GETIMPORT R9 9 [0x11A19C5E]
      26 [-]: MOVE R10 R8  
      27 [-]: LOADK R11 K10 ["OnAgentSpawned"]
      28 [-]: CALL R9 2 0  
      29 [-]: NAMECALL R9 R8 K11 [0x74904F84]
      30 [-]: CALL R9 1 1  
      31 [-]: ADD R2 R2 R9 
      32 [-]: LOADB R11 0  
      33 [-]: NAMECALL R9 R8 K12 [0xA1C833FF]
      34 [-]: CALL R9 2 0  
      35 [-]: NAMECALL R9 R8 K13 [0x36FCC811]
      36 [-]: CALL R9 1 0  
L 3:  37 [-]: FORGLOOP R4 L1 2 [inext]
      38 [-]: ORK R1 R1 K14 [3]
L 4:  39 [-]: GETUPVAL R4 0
      40 [-]: JUMPIFNOTLT R4 R2 L5
      41 [-]: LOADN R4 0   
      42 [-]: JUMPIFNOTLT R4 R1 L5
      43 [-]: GETIMPORT R4 16 [0x67652851]
      44 [-]: CALL R4 0 1  
      45 [-]: SUB R1 R1 R4 
      46 [-]: GETIMPORT R4 18 [0xCBD666E1]
      47 [-]: LOADN R5 0   
      48 [-]: CALL R4 1 0  
      49 [-]: JUMPBACK L4  
L 5:  50 [-]: RETURN R0 0  


; Name:            
; Defined at line: 1360
; #Upvalues:       1
; #Parameters:     0
; Is_vararg:       0
; Max Stack Size:  13

       0 [-]: GETUPVAL R1 0
       1 [-]: GETTABLEKS R0 R1 K0 [0x604F119A]
       2 [-]: LOADB R1 1   
       3 [-]: CALL R0 1 0  
       4 [-]: GETIMPORT R0 2 [0x89326C93]
       5 [-]: NAMECALL R0 R0 K3 [0x29EF273D]
       6 [-]: CALL R0 1 1  
       7 [-]: NAMECALL R0 R0 K4 [0x66905CB0]
       8 [-]: CALL R0 1 1  
       9 [-]: LOADB R3 1   
      10 [-]: NAMECALL R1 R0 K5 [0xB8B90F91]
      11 [-]: CALL R1 2 0  
      12 [-]: LOADB R3 0   
      13 [-]: NAMECALL R1 R0 K6 [0x383D2E7D]
      14 [-]: CALL R1 2 0  
      15 [-]: GETIMPORT R1 2 [0x89326C93]
      16 [-]: NAMECALL R1 R1 K7 [0x21C948F8]
      17 [-]: CALL R1 1 1  
      18 [-]: FASTCALL1 62 R1 L0
      19 [-]: MOVE R3 R1   
      20 [-]: GETIMPORT R2 9 [0x7B998233]
      21 [-]: CALL R2 1 1  
L 0:  22 [-]: JUMPIF R2 L4 
      23 [-]: LENGTH R2 R1 
      24 [-]: LOADN R3 0   
      25 [-]: JUMPIFNOTLT R3 R2 L4
      26 [-]: GETIMPORT R2 11 [0xC8802016]
      27 [-]: MOVE R3 R1   
      28 [-]: CALL R2 1 3  
      29 [-]: FORGPREP_INEXT R2 L3
L 1:  30 [-]: FASTCALL1 62 R6 L2
      31 [-]: MOVE R8 R6   
      32 [-]: GETIMPORT R7 9 [0x7B998233]
      33 [-]: CALL R7 1 1  
L 2:  34 [-]: JUMPIF R7 L3 
      35 [-]: NAMECALL R7 R6 K12 [0x2047CFE7]
      36 [-]: CALL R7 1 1  
      37 [-]: JUMPIF R7 L3 
      38 [-]: NAMECALL R7 R6 K13 [0x808B79E6]
      39 [-]: CALL R7 1 1  
      40 [-]: GETIMPORT R8 15 [0x0469F296]
      41 [-]: LOADK R9 K16 ["TENNO"]
      42 [-]: CALL R8 1 1  
      43 [-]: JUMPIFEQ R7 R8 L3
      44 [-]: NAMECALL R7 R6 K17 [0x1AC1655C]
      45 [-]: CALL R7 1 1  
      46 [-]: GETIMPORT R9 15 [0x0469F296]
      47 [-]: LOADK R10 K18 ["UNUM_INVULNERABLE"]
      48 [-]: CALL R9 1 1  
      49 [-]: LOADN R10 25 
      50 [-]: LOADN R11 6  
      51 [-]: LOADN R12 0  
      52 [-]: NAMECALL R7 R7 K19 [0xA383DE31]
      53 [-]: CALL R7 5 0  
      54 [-]: GETIMPORT R9 21 [0xAB87DDFC]
      55 [-]: GETIMPORT R10 15 [0x0469F296]
      56 [-]: LOADK R11 K22 ["UnumTimeStopEffect"]
      57 [-]: CALL R10 1 -1
      58 [-]: NAMECALL R7 R6 K23 [0x47901F07]
      59 [-]: CALL R7 -1 0 
L 3:  60 [-]: FORGLOOP R2 L1 2 [inext]
L 4:  61 [-]: GETIMPORT R2 2 [0x89326C93]
      62 [-]: GETIMPORT R4 25 ["gProjectileType"]
      63 [-]: NAMECALL R2 R2 K26 [0xFB669000]
      64 [-]: CALL R2 2 1  
      65 [-]: FASTCALL1 62 R2 L5
      66 [-]: MOVE R4 R2   
      67 [-]: GETIMPORT R3 9 [0x7B998233]
      68 [-]: CALL R3 1 1  
L 5:  69 [-]: JUMPIF R3 L9 
      70 [-]: LENGTH R3 R2 
      71 [-]: LOADN R4 0   
      72 [-]: JUMPIFNOTLT R4 R3 L9
      73 [-]: LOADN R5 1   
      74 [-]: LENGTH R3 R2 
      75 [-]: LOADN R4 1   
      76 [-]: FORNPREP R3 L9
L 6:  77 [-]: GETTABLE R7 R2 R5
      78 [-]: FASTCALL1 62 R7 L7
      79 [-]: GETIMPORT R6 9 [0x7B998233]
      80 [-]: CALL R6 1 1  
L 7:  81 [-]: JUMPIF R6 L8 
      82 [-]: GETTABLE R6 R2 R5
      83 [-]: GETIMPORT R8 15 [0x0469F296]
      84 [-]: LOADK R9 K27 ["UnumTimeFreeze"]
      85 [-]: CALL R8 1 1  
      86 [-]: LOADN R9 0   
      87 [-]: NAMECALL R6 R6 K28 [0x9D668F53]
      88 [-]: CALL R6 3 0  
L 8:  89 [-]: FORNLOOP R3 L6
L 9:  90 [-]: RETURN R0 0  


; Name:            
; Defined at line: 1389
; #Upvalues:       11
; #Parameters:     1
; Is_vararg:       0
; Max Stack Size:  5

       0 [-]: FASTCALL1 62 R0 L0
       1 [-]: MOVE R2 R0   
       2 [-]: GETIMPORT R1 1 [0x7B998233]
       3 [-]: CALL R1 1 1  
L 0:   4 [-]: JUMPIF R1 L4 
       5 [-]: GETUPVAL R1 0
       6 [-]: JUMPIFNOTEQ R0 R1 L4
       7 [-]: GETUPVAL R1 1
       8 [-]: GETUPVAL R3 2
       9 [-]: GETTABLEKS R2 R3 K2 ["RIDE_BALLOON"]
      10 [-]: JUMPIFNOTEQ R1 R2 L1
      11 [-]: GETUPVAL R1 3
      12 [-]: GETUPVAL R4 2
      13 [-]: GETTABLEKS R3 R4 K3 ["ENTER_TOWER"]
      14 [-]: NAMECALL R1 R1 K4 [0x8ABFF40E]
      15 [-]: CALL R1 2 0  
      16 [-]: LOADNIL R1   
      17 [-]: SETUPVAL R1 0
      18 [-]: GETUPVAL R2 4
      19 [-]: GETTABLEKS R1 R2 K5 [0x9742B85B]
      20 [-]: GETIMPORT R2 7 [0xE91D7466]
      21 [-]: GETUPVAL R4 5
      22 [-]: GETTABLEKS R3 R4 K8 ["ordisAboutUnumTower"]
      23 [-]: CALL R1 2 0  
      24 [-]: GETUPVAL R2 4
      25 [-]: GETTABLEKS R1 R2 K9 [0xFC87A231]
      26 [-]: CALL R1 0 0  
      27 [-]: GETUPVAL R2 4
      28 [-]: GETTABLEKS R1 R2 K10 [0x11DCFE97]
      29 [-]: GETUPVAL R3 5
      30 [-]: GETTABLEKS R2 R3 K11 ["operatorResponseUnumTower"]
      31 [-]: CALL R1 1 0  
      32 [-]: RETURN R0 0  
L 1:  33 [-]: GETUPVAL R1 1
      34 [-]: GETUPVAL R3 2
      35 [-]: GETTABLEKS R2 R3 K12 ["POWER_TOWER_A"]
      36 [-]: JUMPIFNOTEQ R1 R2 L2
      37 [-]: GETUPVAL R1 0
      38 [-]: NAMECALL R1 R1 K13 [0x22DA1852]
      39 [-]: CALL R1 1 1  
      40 [-]: GETUPVAL R2 6
      41 [-]: JUMPIFNOTEQ R1 R2 L4
      42 [-]: GETUPVAL R2 7
      43 [-]: GETTABLEKS R1 R2 K14 [0xA1DF01D6]
      44 [-]: GETUPVAL R3 8
      45 [-]: GETTABLEKS R2 R3 K15 ["activateDevices"]
      46 [-]: CALL R1 1 0  
      47 [-]: GETUPVAL R1 0
      48 [-]: LOADK R3 K16 ["Disable"]
      49 [-]: NAMECALL R1 R1 K17 [0x8EB2112D]
      50 [-]: CALL R1 2 0  
      51 [-]: LOADNIL R1   
      52 [-]: SETUPVAL R1 0
      53 [-]: RETURN R0 0  
L 2:  54 [-]: GETUPVAL R1 1
      55 [-]: GETUPVAL R3 2
      56 [-]: GETTABLEKS R2 R3 K18 ["TOWER_ROOF"]
      57 [-]: JUMPIFNOTEQ R1 R2 L3
      58 [-]: GETUPVAL R1 0
      59 [-]: NAMECALL R1 R1 K13 [0x22DA1852]
      60 [-]: CALL R1 1 1  
      61 [-]: GETUPVAL R2 9
      62 [-]: JUMPIFNOTEQ R1 R2 L4
      63 [-]: LOADNIL R1   
      64 [-]: SETUPVAL R1 0
      65 [-]: GETUPVAL R1 3
      66 [-]: GETUPVAL R4 2
      67 [-]: GETTABLEKS R3 R4 K19 ["TIMESTOP"]
      68 [-]: NAMECALL R1 R1 K4 [0x8ABFF40E]
      69 [-]: CALL R1 2 0  
      70 [-]: RETURN R0 0  
L 3:  71 [-]: GETUPVAL R1 1
      72 [-]: GETUPVAL R3 2
      73 [-]: GETTABLEKS R2 R3 K19 ["TIMESTOP"]
      74 [-]: JUMPIFNOTEQ R1 R2 L4
      75 [-]: GETUPVAL R1 10
      76 [-]: CALL R1 0 0  
      77 [-]: GETUPVAL R1 3
      78 [-]: GETUPVAL R4 2
      79 [-]: GETTABLEKS R3 R4 K20 ["COMPLETE"]
      80 [-]: NAMECALL R1 R1 K4 [0x8ABFF40E]
      81 [-]: CALL R1 2 0  
      82 [-]: LOADNIL R1   
      83 [-]: SETUPVAL R1 0
L 4:  84 [-]: RETURN R0 0  


; Name:            
; Defined at line: 1423
; #Upvalues:       0
; #Parameters:     0
; Is_vararg:       0
; Max Stack Size:  0

       0 [-]: RETURN R0 0  


; Name:            
; Defined at line: 1508
; #Upvalues:       5
; #Parameters:     0
; Is_vararg:       0
; Max Stack Size:  3

       0 [-]: GETUPVAL R1 0
       1 [-]: FASTCALL1 62 R1 L0
       2 [-]: GETIMPORT R0 1 [0x7B998233]
       3 [-]: CALL R0 1 1  
L 0:   4 [-]: JUMPIF R0 L3 
       5 [-]: GETUPVAL R0 1
       6 [-]: JUMPIFNOT R0 L3
       7 [-]: GETUPVAL R0 0
       8 [-]: NAMECALL R0 R0 K2 [0x73901ACF]
       9 [-]: CALL R0 1 1  
      10 [-]: JUMPIF R0 L1 
      11 [-]: GETUPVAL R0 0
      12 [-]: NAMECALL R0 R0 K3 [0x2047CFE7]
      13 [-]: CALL R0 1 1  
      14 [-]: JUMPIF R0 L1 
      15 [-]: GETIMPORT R0 6 ["PlayerDead"]
      16 [-]: JUMPIFNOT R0 L3
L 1:  17 [-]: GETUPVAL R0 0
      18 [-]: GETIMPORT R2 8 ["gLotusOperatorAvatarType"]
      19 [-]: NAMECALL R0 R0 K9 [0xF2DEAF69]
      20 [-]: CALL R0 2 1  
      21 [-]: JUMPIFNOT R0 L2
      22 [-]: GETUPVAL R0 2
      23 [-]: GETUPVAL R2 3
      24 [-]: GETTABLEKS R1 R2 K10 ["POWER_TOWER_A"]
      25 [-]: JUMPIFNOTLE R1 R0 L2
      26 [-]: LOADB R0 0   
      27 [-]: RETURN R0 1  
L 2:  28 [-]: LOADB R0 1   
      29 [-]: RETURN R0 1  
L 3:  30 [-]: GETUPVAL R0 2
      31 [-]: GETUPVAL R2 3
      32 [-]: GETTABLEKS R1 R2 K11 ["TOWER_ROOF"]
      33 [-]: JUMPIFNOTEQ R0 R1 L4
      34 [-]: GETIMPORT R0 13 ["MurexTimeout"]
      35 [-]: JUMPIFNOT R0 L4
      36 [-]: LOADB R0 1   
      37 [-]: RETURN R0 1  
L 4:  38 [-]: GETUPVAL R0 2
      39 [-]: GETUPVAL R2 3
      40 [-]: GETTABLEKS R1 R2 K14 ["RIDE_BALLOON"]
      41 [-]: JUMPIFNOTEQ R0 R1 L7
      42 [-]: GETUPVAL R1 4
      43 [-]: FASTCALL1 62 R1 L5
      44 [-]: GETIMPORT R0 1 [0x7B998233]
      45 [-]: CALL R0 1 1  
L 5:  46 [-]: JUMPIF R0 L6 
      47 [-]: GETUPVAL R0 4
      48 [-]: NAMECALL R0 R0 K3 [0x2047CFE7]
      49 [-]: CALL R0 1 1  
      50 [-]: JUMPIFNOT R0 L7
L 6:  51 [-]: LOADB R0 1   
      52 [-]: RETURN R0 1  
L 7:  53 [-]: RETURN R0 0  


; Name:            
; Defined at line: 1522
; #Upvalues:       9
; #Parameters:     0
; Is_vararg:       0
; Max Stack Size:  6

       0 [-]: GETUPVAL R0 0
       1 [-]: GETUPVAL R2 1
       2 [-]: GETTABLEKS R1 R2 K0 ["RESCUE_OSTRON"]
       3 [-]: JUMPIFNOTEQ R0 R1 L6
       4 [-]: GETUPVAL R1 2
       5 [-]: GETTABLEKS R0 R1 K1 [0xB5C6BBAF]
       6 [-]: LOADB R1 1   
       7 [-]: CALL R0 1 0  
       8 [-]: GETUPVAL R1 3
       9 [-]: FASTCALL1 62 R1 L0
      10 [-]: GETIMPORT R0 3 [0x7B998233]
      11 [-]: CALL R0 1 1  
L 0:  12 [-]: JUMPIF R0 L4 
      13 [-]: GETUPVAL R1 3
      14 [-]: LENGTH R0 R1 
      15 [-]: LOADN R1 0   
      16 [-]: JUMPIFNOTLT R1 R0 L4
      17 [-]: LOADN R2 1   
      18 [-]: GETUPVAL R3 3
      19 [-]: LENGTH R0 R3 
      20 [-]: LOADN R1 1   
      21 [-]: FORNPREP R0 L4
L 1:  22 [-]: GETUPVAL R5 3
      23 [-]: GETTABLE R4 R5 R2
      24 [-]: FASTCALL1 62 R4 L2
      25 [-]: GETIMPORT R3 3 [0x7B998233]
      26 [-]: CALL R3 1 1  
L 2:  27 [-]: JUMPIF R3 L3 
      28 [-]: GETUPVAL R4 3
      29 [-]: GETTABLE R3 R4 R2
      30 [-]: GETUPVAL R5 4
      31 [-]: NAMECALL R3 R3 K4 [0xEF77C6EF]
      32 [-]: CALL R3 2 0  
      33 [-]: GETUPVAL R4 3
      34 [-]: GETTABLE R3 R4 R2
      35 [-]: NAMECALL R3 R3 K5 [0xA2880940]
      36 [-]: CALL R3 1 0  
L 3:  37 [-]: FORNLOOP R0 L1
L 4:  38 [-]: GETUPVAL R1 5
      39 [-]: FASTCALL1 62 R1 L5
      40 [-]: GETIMPORT R0 3 [0x7B998233]
      41 [-]: CALL R0 1 1  
L 5:  42 [-]: JUMPIF R0 L9 
      43 [-]: LOADNIL R0   
      44 [-]: SETUPVAL R0 3
      45 [-]: LOADNIL R0   
      46 [-]: SETUPVAL R0 6
      47 [-]: GETIMPORT R0 8 ["RemoveHudTracker"]
      48 [-]: GETUPVAL R1 5
      49 [-]: CALL R0 1 0  
      50 [-]: LOADNIL R0   
      51 [-]: SETUPVAL R0 5
      52 [-]: RETURN R0 0  
L 6:  53 [-]: GETUPVAL R0 0
      54 [-]: GETUPVAL R2 1
      55 [-]: GETTABLEKS R1 R2 K9 ["POWER_TOWER_A"]
      56 [-]: JUMPIFNOTLE R1 R0 L9
      57 [-]: GETUPVAL R1 7
      58 [-]: GETTABLEKS R0 R1 K10 [0xBD3CE95D]
      59 [-]: CALL R0 0 0  
      60 [-]: GETUPVAL R0 0
      61 [-]: GETUPVAL R2 1
      62 [-]: GETTABLEKS R1 R2 K11 ["TOWER_ROOF"]
      63 [-]: JUMPIFNOTEQ R0 R1 L9
      64 [-]: GETUPVAL R1 7
      65 [-]: GETTABLEKS R0 R1 K12 [0x46749D86]
      66 [-]: CALL R0 0 1  
      67 [-]: JUMPIFNOT R0 L7
      68 [-]: GETUPVAL R1 7
      69 [-]: GETTABLEKS R0 R1 K13 [0x18DD08AC]
      70 [-]: CALL R0 0 0  
L 7:  71 [-]: GETIMPORT R0 15 ["MurexTimeout"]
      72 [-]: JUMPIFNOT R0 L9
      73 [-]: GETUPVAL R1 8
      74 [-]: FASTCALL1 62 R1 L8
      75 [-]: GETIMPORT R0 3 [0x7B998233]
      76 [-]: CALL R0 1 1  
L 8:  77 [-]: JUMPIF R0 L9 
      78 [-]: GETUPVAL R0 8
      79 [-]: NAMECALL R0 R0 K16 [0x2047CFE7]
      80 [-]: CALL R0 1 1  
      81 [-]: JUMPIFNOT R0 L9
      82 [-]: GETIMPORT R0 18 [0x3D106989]
      83 [-]: LOADK R1 K19 ["Reviving players during PreRespawn as they were dead and time ran out"]
      84 [-]: CALL R0 1 0  
      85 [-]: GETIMPORT R0 21 [0xBE190284]
      86 [-]: GETIMPORT R2 23 [0x89326C93]
      87 [-]: NAMECALL R2 R2 K24 [0xFB64E76C]
      88 [-]: CALL R2 1 1  
      89 [-]: LOADB R3 0   
      90 [-]: NAMECALL R0 R0 K25 [0xE1100F9F]
      91 [-]: CALL R0 3 0  
L 9:  92 [-]: RETURN R0 0  


; Name:            
; Defined at line: 1558
; #Upvalues:       4
; #Parameters:     1
; Is_vararg:       0
; Max Stack Size:  5

       0 [-]: GETUPVAL R1 0
       1 [-]: GETUPVAL R3 1
       2 [-]: GETTABLEKS R2 R3 K0 ["TOWER_ROOF"]
       3 [-]: JUMPIFNOTEQ R1 R2 L6
       4 [-]: GETUPVAL R2 2
       5 [-]: FASTCALL1 62 R2 L0
       6 [-]: GETIMPORT R1 2 [0x7B998233]
       7 [-]: CALL R1 1 1  
L 0:   8 [-]: JUMPIF R1 L5 
       9 [-]: GETUPVAL R1 2
      10 [-]: GETIMPORT R3 4 ["gLotusOperatorAvatarType"]
      11 [-]: NAMECALL R1 R1 K5 [0xF2DEAF69]
      12 [-]: CALL R1 2 1  
      13 [-]: JUMPIFNOT R1 L5
      14 [-]: GETIMPORT R1 7 ["_T"]
      15 [-]: LOADB R2 1   
      16 [-]: SETTABLEKS R2 R1 K8 ["HideTransferenceFx"]
      17 [-]: GETUPVAL R1 2
      18 [-]: LOADB R3 1   
      19 [-]: NAMECALL R1 R1 K9 [0x18F03C5D]
      20 [-]: CALL R1 2 0  
L 1:  21 [-]: GETUPVAL R2 2
      22 [-]: FASTCALL1 62 R2 L2
      23 [-]: GETIMPORT R1 2 [0x7B998233]
      24 [-]: CALL R1 1 1  
L 2:  25 [-]: JUMPIF R1 L3 
      26 [-]: GETUPVAL R1 2
      27 [-]: GETIMPORT R3 4 ["gLotusOperatorAvatarType"]
      28 [-]: NAMECALL R1 R1 K5 [0xF2DEAF69]
      29 [-]: CALL R1 2 1  
      30 [-]: JUMPIFNOT R1 L4
L 3:  31 [-]: GETIMPORT R1 11 [0xCBD666E1]
      32 [-]: LOADN R2 0   
      33 [-]: CALL R1 1 0  
      34 [-]: GETIMPORT R1 13 [0x89326C93]
      35 [-]: NAMECALL R1 R1 K14 [0x78298275]
      36 [-]: CALL R1 1 1  
      37 [-]: SETUPVAL R1 2
      38 [-]: GETIMPORT R1 7 ["_T"]
      39 [-]: GETIMPORT R3 16 ["RespawnTime"]
      40 [-]: GETIMPORT R4 18 [0x67652851]
      41 [-]: CALL R4 0 1  
      42 [-]: ADD R2 R3 R4 
      43 [-]: SETTABLEKS R2 R1 K15 ["RespawnTime"]
      44 [-]: JUMPBACK L1  
L 4:  45 [-]: GETIMPORT R1 7 ["_T"]
      46 [-]: LOADNIL R2   
      47 [-]: SETTABLEKS R2 R1 K8 ["HideTransferenceFx"]
L 5:  48 [-]: GETUPVAL R1 3
      49 [-]: LOADB R2 1   
      50 [-]: CALL R1 1 0  
L 6:  51 [-]: RETURN R0 0  


; Name:            
; Defined at line: 1579
; #Upvalues:       12
; #Parameters:     0
; Is_vararg:       0
; Max Stack Size:  4

       0 [-]: GETUPVAL R0 0
       1 [-]: CALL R0 0 0  
       2 [-]: GETUPVAL R1 1
       3 [-]: GETTABLEKS R0 R1 K0 [0xD720831B]
       4 [-]: CALL R0 0 0  
       5 [-]: GETUPVAL R1 1
       6 [-]: GETTABLEKS R0 R1 K1 [0x294D5408]
       7 [-]: LOADB R1 1   
       8 [-]: LOADB R2 1   
       9 [-]: LOADB R3 1   
      10 [-]: CALL R0 3 0  
      11 [-]: GETIMPORT R0 3 ["_T"]
      12 [-]: LOADN R1 0   
      13 [-]: SETTABLEKS R1 R0 K4 ["OstronHostageRescueCount"]
      14 [-]: GETUPVAL R0 2
      15 [-]: CALL R0 0 0  
      16 [-]: GETIMPORT R0 6 [0x89326C93]
      17 [-]: GETIMPORT R2 8 [0x0469F296]
      18 [-]: LOADK R3 K9 ["OpenCinShort"]
      19 [-]: CALL R2 1 -1 
      20 [-]: NAMECALL R0 R0 K10 [0x46A0EBF5]
      21 [-]: CALL R0 -1 1 
      22 [-]: SETUPVAL R0 3
      23 [-]: GETIMPORT R0 6 [0x89326C93]
      24 [-]: GETIMPORT R2 8 [0x0469F296]
      25 [-]: LOADK R3 K11 ["OrphixVolume"]
      26 [-]: CALL R2 1 -1 
      27 [-]: NAMECALL R0 R0 K10 [0x46A0EBF5]
      28 [-]: CALL R0 -1 1 
      29 [-]: SETUPVAL R0 4
      30 [-]: GETIMPORT R0 6 [0x89326C93]
      31 [-]: GETIMPORT R2 8 [0x0469F296]
      32 [-]: LOADK R3 K12 ["QuillsCaveVolume"]
      33 [-]: CALL R2 1 -1 
      34 [-]: NAMECALL R0 R0 K10 [0x46A0EBF5]
      35 [-]: CALL R0 -1 1 
      36 [-]: SETUPVAL R0 5
      37 [-]: GETUPVAL R0 6
      38 [-]: LOADB R1 1   
      39 [-]: CALL R0 1 0  
      40 [-]: GETIMPORT R0 3 ["_T"]
      41 [-]: GETUPVAL R1 7
      42 [-]: SETTABLEKS R1 R0 K13 ["PreCheckpointRespawn"]
      43 [-]: GETIMPORT R0 3 ["_T"]
      44 [-]: GETUPVAL R1 8
      45 [-]: SETTABLEKS R1 R0 K14 ["PostCheckpointRespawn"]
      46 [-]: GETIMPORT R0 6 [0x89326C93]
      47 [-]: NAMECALL R0 R0 K15 [0x29EF273D]
      48 [-]: CALL R0 1 1  
      49 [-]: GETIMPORT R2 17 [0x531EB85D]
      50 [-]: NAMECALL R0 R0 K18 [0x8955C0B5]
      51 [-]: CALL R0 2 0  
      52 [-]: GETUPVAL R0 9
      53 [-]: CALL R0 0 1  
      54 [-]: JUMPIF R0 L0 
      55 [-]: GETUPVAL R0 10
      56 [-]: GETUPVAL R3 11
      57 [-]: GETTABLEKS R2 R3 K19 ["INTRO"]
      58 [-]: NAMECALL R0 R0 K20 [0x8ABFF40E]
      59 [-]: CALL R0 2 0  
L 0:  60 [-]: RETURN R0 0  


; Name:            
; Defined at line: 1605
; #Upvalues:       39
; #Parameters:     1
; Is_vararg:       0
; Max Stack Size:  13

       0 [-]: GETIMPORT R1 1 [0x3D106989]
       1 [-]: LOADK R3 K2 ["New Stage: "]
       2 [-]: MOVE R4 R0   
       3 [-]: LOADK R5 K3 [" "]
       4 [-]: GETUPVAL R9 0
       5 [-]: GETTABLE R8 R9 R0
       6 [-]: FASTCALL1 62 R8 L0
       7 [-]: GETIMPORT R7 5 [0x7B998233]
       8 [-]: CALL R7 1 1  
L 0:   9 [-]: JUMPIF R7 L2 
      10 [-]: GETUPVAL R10 0
      11 [-]: GETTABLE R9 R10 R0
      12 [-]: GETTABLEKS R8 R9 K6 ["name"]
      13 [-]: FASTCALL1 62 R8 L1
      14 [-]: GETIMPORT R7 5 [0x7B998233]
      15 [-]: CALL R7 1 1  
L 1:  16 [-]: JUMPIF R7 L2 
      17 [-]: GETUPVAL R8 0
      18 [-]: GETTABLE R7 R8 R0
      19 [-]: GETTABLEKS R6 R7 K6 ["name"]
      20 [-]: JUMPIF R6 L3 
L 2:  21 [-]: LOADK R6 K7 [""]
L 3:  22 [-]: CONCAT R2 R3 R6
      23 [-]: CALL R1 1 0  
      24 [-]: SUBK R1 R0 K8 [1]
      25 [-]: GETUPVAL R4 0
      26 [-]: GETTABLE R3 R4 R1
      27 [-]: FASTCALL1 62 R3 L4
      28 [-]: GETIMPORT R2 5 [0x7B998233]
      29 [-]: CALL R2 1 1  
L 4:  30 [-]: JUMPIFNOT R2 L5
      31 [-]: JUMP L7
     
L 5:  32 [-]: LOADN R2 0   
      33 [-]: JUMPIFNOTLT R2 R1 L7
      34 [-]: GETUPVAL R5 0
      35 [-]: GETTABLE R4 R5 R1
      36 [-]: GETTABLEKS R3 R4 K9 ["endF"]
      37 [-]: FASTCALL1 62 R3 L6
      38 [-]: GETIMPORT R2 5 [0x7B998233]
      39 [-]: CALL R2 1 1  
L 6:  40 [-]: JUMPIF R2 L7 
      41 [-]: GETUPVAL R4 0
      42 [-]: GETTABLE R3 R4 R1
      43 [-]: GETTABLEKS R2 R3 K9 ["endF"]
      44 [-]: LOADK R4 K10 ["TriggerPort"]
      45 [-]: NAMECALL R2 R2 K11 [0x8EB2112D]
      46 [-]: CALL R2 2 0  
L 7:  47 [-]: GETUPVAL R2 1
      48 [-]: GETTABLEKS R1 R2 K12 ["POWER_TOWER_A"]
      49 [-]: JUMPIFNOTLT R1 R0 L8
      50 [-]: GETUPVAL R2 1
      51 [-]: GETTABLEKS R1 R2 K13 ["TOWER_ROOF"]
      52 [-]: JUMPIFNOTLT R0 R1 L8
      53 [-]: GETIMPORT R1 16 ["IsRandomWhisperActive"]
      54 [-]: JUMPXEQKNIL R1 L8 NOT
      55 [-]: GETIMPORT R1 17 ["_T"]
      56 [-]: LOADB R2 1   
      57 [-]: SETTABLEKS R2 R1 K15 ["IsRandomWhisperActive"]
L 8:  58 [-]: GETUPVAL R2 1
      59 [-]: GETTABLEKS R1 R2 K12 ["POWER_TOWER_A"]
      60 [-]: JUMPIFNOTLT R0 R1 L9
      61 [-]: GETIMPORT R1 17 ["_T"]
      62 [-]: LOADB R2 1   
      63 [-]: SETTABLEKS R2 R1 K18 ["respawnOperator"]
      64 [-]: JUMP L10
    
L 9:  65 [-]: GETIMPORT R1 17 ["_T"]
      66 [-]: LOADNIL R2   
      67 [-]: SETTABLEKS R2 R1 K18 ["respawnOperator"]
L10:  68 [-]: GETUPVAL R2 1
      69 [-]: GETTABLEKS R1 R2 K19 ["INTRO"]
      70 [-]: JUMPIFNOTEQ R0 R1 L13
      71 [-]: GETUPVAL R1 2
      72 [-]: JUMPIF R1 L12
      73 [-]: GETUPVAL R1 3
      74 [-]: CALL R1 0 0  
      75 [-]: GETIMPORT R1 21 [0xCBD666E1]
      76 [-]: LOADN R2 0   
      77 [-]: CALL R1 1 0  
      78 [-]: GETUPVAL R2 4
      79 [-]: FASTCALL1 62 R2 L11
      80 [-]: GETIMPORT R1 5 [0x7B998233]
      81 [-]: CALL R1 1 1  
L11:  82 [-]: JUMPIF R1 L12
      83 [-]: GETUPVAL R1 4
      84 [-]: LOADK R3 K22 ["StartPlaying"]
      85 [-]: NAMECALL R1 R1 K11 [0x8EB2112D]
      86 [-]: CALL R1 2 0  
L12:  87 [-]: LOADB R1 0   
      88 [-]: SETUPVAL R1 2
      89 [-]: JUMP L116
   
L13:  90 [-]: GETUPVAL R2 1
      91 [-]: GETTABLEKS R1 R2 K23 ["QUILLS_CAVE"]
      92 [-]: JUMPIFNOTEQ R0 R1 L15
      93 [-]: GETUPVAL R2 5
      94 [-]: GETTABLEKS R1 R2 K24 [0xA1DF01D6]
      95 [-]: GETUPVAL R3 6
      96 [-]: GETTABLEKS R2 R3 K25 ["rescueKonzu"]
      97 [-]: CALL R1 1 0  
      98 [-]: GETUPVAL R1 7
      99 [-]: GETIMPORT R2 27 [0x0469F296]
     100 [-]: LOADK R3 K28 ["QuillsCaveWP"]
     101 [-]: CALL R2 1 -1 
     102 [-]: CALL R1 -1 0 
     103 [-]: GETUPVAL R1 2
     104 [-]: JUMPIF R1 L14
     105 [-]: GETUPVAL R1 8
     106 [-]: GETIMPORT R3 27 [0x0469F296]
     107 [-]: LOADK R4 K29 ["PlayIntroTransmissions"]
     108 [-]: CALL R3 1 1  
     109 [-]: LOADB R4 0   
     110 [-]: NAMECALL R1 R1 K30 [0xD5F7912B]
     111 [-]: CALL R1 3 0  
L14: 112 [-]: GETIMPORT R1 32 [0xBE190284]
     113 [-]: LOADB R3 1   
     114 [-]: NAMECALL R1 R1 K33 [0x9DC2A61A]
     115 [-]: CALL R1 2 0  
     116 [-]: JUMP L116
   
L15: 117 [-]: GETUPVAL R2 1
     118 [-]: GETTABLEKS R1 R2 K34 ["RESCUE_OSTRON"]
     119 [-]: JUMPIFNOTEQ R0 R1 L29
     120 [-]: GETIMPORT R1 17 ["_T"]
     121 [-]: LOADN R2 0   
     122 [-]: SETTABLEKS R2 R1 K35 ["OstronHostageRescueCount"]
     123 [-]: LOADB R1 1   
     124 [-]: SETUPVAL R1 9
     125 [-]: GETUPVAL R1 2
     126 [-]: JUMPIF R1 L22
     127 [-]: LOADN R1 1   
     128 [-]: SETUPVAL R1 10
     129 [-]: LOADN R3 1   
     130 [-]: GETUPVAL R4 11
     131 [-]: LENGTH R1 R4 
     132 [-]: LOADN R2 1   
     133 [-]: FORNPREP R1 L22
L16: 134 [-]: GETUPVAL R6 11
     135 [-]: GETTABLE R5 R6 R3
     136 [-]: FASTCALL1 62 R5 L17
     137 [-]: GETIMPORT R4 5 [0x7B998233]
     138 [-]: CALL R4 1 1  
L17: 139 [-]: JUMPIF R4 L21
     140 [-]: GETIMPORT R4 37 [0x89326C93]
     141 [-]: GETUPVAL R7 11
     142 [-]: GETTABLE R6 R7 R3
     143 [-]: NAMECALL R4 R4 K38 [0xC7FCADA9]
     144 [-]: CALL R4 2 1  
     145 [-]: FASTCALL1 62 R4 L18
     146 [-]: MOVE R6 R4   
     147 [-]: GETIMPORT R5 5 [0x7B998233]
     148 [-]: CALL R5 1 1  
L18: 149 [-]: JUMPIF R5 L21
     150 [-]: LENGTH R5 R4 
     151 [-]: LOADN R6 0   
     152 [-]: JUMPIFNOTLT R6 R5 L21
     153 [-]: GETIMPORT R5 40 [0xC8802016]
     154 [-]: MOVE R6 R4   
     155 [-]: CALL R5 1 3  
     156 [-]: FORGPREP_INEXT R5 L20
L19: 157 [-]: GETIMPORT R10 42 [0x11A19C5E]
     158 [-]: MOVE R11 R9  
     159 [-]: LOADK R12 K43 ["OnSpawn"]
     160 [-]: CALL R10 2 0 
L20: 161 [-]: FORGLOOP R5 L19 2 [inext]
L21: 162 [-]: FORNLOOP R1 L16
L22: 163 [-]: LOADB R1 0   
     164 [-]: SETUPVAL R1 2
     165 [-]: GETUPVAL R1 10
     166 [-]: JUMPXEQKN R1 K8 L27 NOT [1]
     167 [-]: GETIMPORT R1 45 ["HideImpactMessage"]
     168 [-]: CALL R1 0 0  
     169 [-]: GETUPVAL R2 1
     170 [-]: GETTABLEKS R1 R2 K34 ["RESCUE_OSTRON"]
     171 [-]: GETUPVAL R4 0
     172 [-]: GETTABLE R3 R4 R1
     173 [-]: FASTCALL1 62 R3 L23
     174 [-]: GETIMPORT R2 5 [0x7B998233]
     175 [-]: CALL R2 1 1  
L23: 176 [-]: JUMPIFNOT R2 L24
     177 [-]: JUMP L26
    
L24: 178 [-]: LOADN R2 0   
     179 [-]: JUMPIFNOTLT R2 R1 L26
     180 [-]: GETUPVAL R5 0
     181 [-]: GETTABLE R4 R5 R1
     182 [-]: GETTABLEKS R3 R4 K46 ["startF"]
     183 [-]: FASTCALL1 62 R3 L25
     184 [-]: GETIMPORT R2 5 [0x7B998233]
     185 [-]: CALL R2 1 1  
L25: 186 [-]: JUMPIF R2 L26
     187 [-]: GETUPVAL R4 0
     188 [-]: GETTABLE R3 R4 R1
     189 [-]: GETTABLEKS R2 R3 K46 ["startF"]
     190 [-]: LOADK R4 K10 ["TriggerPort"]
     191 [-]: NAMECALL R2 R2 K11 [0x8EB2112D]
     192 [-]: CALL R2 2 0  
L26: 193 [-]: GETUPVAL R1 12
     194 [-]: GETUPVAL R3 11
     195 [-]: GETUPVAL R4 10
     196 [-]: GETTABLE R2 R3 R4
     197 [-]: CALL R1 1 0  
     198 [-]: GETUPVAL R2 5
     199 [-]: GETTABLEKS R1 R2 K24 [0xA1DF01D6]
     200 [-]: GETUPVAL R3 6
     201 [-]: GETTABLEKS R2 R3 K25 ["rescueKonzu"]
     202 [-]: CALL R1 1 0  
     203 [-]: JUMP L28
    
L27: 204 [-]: GETUPVAL R1 10
     205 [-]: GETUPVAL R3 5
     206 [-]: GETTABLEKS R2 R3 K24 [0xA1DF01D6]
     207 [-]: GETUPVAL R4 6
     208 [-]: GETTABLEKS R3 R4 K47 ["rescueOstron"]
     209 [-]: CALL R2 1 0  
     210 [-]: LOADB R2 1   
     211 [-]: SETUPVAL R2 13
     212 [-]: GETUPVAL R3 14
     213 [-]: GETTABLEKS R2 R3 K48 [0xC474A99E]
     214 [-]: GETIMPORT R3 27 [0x0469F296]
     215 [-]: LOADK R4 K49 ["AfterKonzuEvents"]
     216 [-]: CALL R3 1 1  
     217 [-]: LOADK R4 K10 ["TriggerPort"]
     218 [-]: CALL R2 2 0  
     219 [-]: GETUPVAL R3 0
     220 [-]: GETUPVAL R5 1
     221 [-]: GETTABLEKS R4 R5 K34 ["RESCUE_OSTRON"]
     222 [-]: GETTABLE R2 R3 R4
     223 [-]: GETIMPORT R3 27 [0x0469F296]
     224 [-]: LOADK R4 K50 ["AfterKonzuCheckpoint"]
     225 [-]: CALL R3 1 1  
     226 [-]: SETTABLEKS R3 R2 K51 ["respawnPt"]
     227 [-]: GETUPVAL R2 12
     228 [-]: GETUPVAL R4 11
     229 [-]: GETTABLE R3 R4 R1
     230 [-]: CALL R2 1 0  
     231 [-]: GETUPVAL R2 15
     232 [-]: GETTABLEKS R1 R2 K52 [0x9742B85B]
     233 [-]: GETIMPORT R2 54 [0xE91D7466]
     234 [-]: GETUPVAL R4 16
     235 [-]: GETTABLEKS R3 R4 K55 ["konzuSaveOstrons"]
     236 [-]: CALL R1 2 0  
L28: 237 [-]: GETUPVAL R1 17
     238 [-]: GETIMPORT R2 27 [0x0469F296]
     239 [-]: LOADK R3 K56 ["NarmerCetusRescueSpawnController"]
     240 [-]: CALL R2 1 -1 
     241 [-]: CALL R1 -1 0 
     242 [-]: JUMP L116
   
L29: 243 [-]: GETUPVAL R2 1
     244 [-]: GETTABLEKS R1 R2 K57 ["RIDE_BALLOON"]
     245 [-]: JUMPIFNOTEQ R0 R1 L42
     246 [-]: LOADB R1 1   
     247 [-]: SETUPVAL R1 9
     248 [-]: LOADB R1 0   
     249 [-]: SETUPVAL R1 18
     250 [-]: GETIMPORT R1 17 ["_T"]
     251 [-]: LOADB R2 0   
     252 [-]: SETTABLEKS R2 R1 K58 ["MinimalHud"]
     253 [-]: GETIMPORT R1 17 ["_T"]
     254 [-]: LOADNIL R2   
     255 [-]: SETTABLEKS R2 R1 K59 ["ForceShowImpactMessages"]
     256 [-]: GETUPVAL R2 19
     257 [-]: FASTCALL1 62 R2 L30
     258 [-]: GETIMPORT R1 5 [0x7B998233]
     259 [-]: CALL R1 1 1  
L30: 260 [-]: JUMPIF R1 L31
     261 [-]: GETIMPORT R1 61 ["RemoveHudTracker"]
     262 [-]: GETUPVAL R2 19
     263 [-]: CALL R1 1 0  
     264 [-]: LOADNIL R1   
     265 [-]: SETUPVAL R1 19
L31: 266 [-]: GETUPVAL R1 20
     267 [-]: CALL R1 0 0  
     268 [-]: GETUPVAL R2 21
     269 [-]: FASTCALL1 62 R2 L32
     270 [-]: GETIMPORT R1 5 [0x7B998233]
     271 [-]: CALL R1 1 1  
L32: 272 [-]: JUMPIF R1 L33
     273 [-]: GETUPVAL R1 21
     274 [-]: LOADK R3 K62 ["Enable"]
     275 [-]: NAMECALL R1 R1 K11 [0x8EB2112D]
     276 [-]: CALL R1 2 0  
L33: 277 [-]: GETUPVAL R2 5
     278 [-]: GETTABLEKS R1 R2 K24 [0xA1DF01D6]
     279 [-]: GETUPVAL R3 6
     280 [-]: GETTABLEKS R2 R3 K63 ["rideBalloon"]
     281 [-]: CALL R1 1 0  
     282 [-]: GETUPVAL R2 22
     283 [-]: FASTCALL1 62 R2 L34
     284 [-]: GETIMPORT R1 5 [0x7B998233]
     285 [-]: CALL R1 1 1  
L34: 286 [-]: JUMPIF R1 L36
     287 [-]: GETUPVAL R1 22
     288 [-]: NAMECALL R1 R1 K64 [0xF37943FF]
     289 [-]: CALL R1 1 1  
     290 [-]: JUMPIFNOT R1 L35
     291 [-]: GETUPVAL R1 22
     292 [-]: LOADK R3 K65 ["Disable"]
     293 [-]: NAMECALL R1 R1 K11 [0x8EB2112D]
     294 [-]: CALL R1 2 0  
L35: 295 [-]: LOADNIL R1   
     296 [-]: SETUPVAL R1 22
L36: 297 [-]: GETUPVAL R1 7
     298 [-]: GETIMPORT R2 27 [0x0469F296]
     299 [-]: LOADK R3 K66 ["BalloonStationMarker"]
     300 [-]: CALL R2 1 -1 
     301 [-]: CALL R1 -1 0 
     302 [-]: GETUPVAL R2 8
     303 [-]: FASTCALL1 62 R2 L37
     304 [-]: GETIMPORT R1 5 [0x7B998233]
     305 [-]: CALL R1 1 1  
L37: 306 [-]: JUMPIF R1 L38
     307 [-]: GETUPVAL R1 8
     308 [-]: GETUPVAL R3 22
     309 [-]: NAMECALL R1 R1 K67 [0xBEBAD19F]
     310 [-]: CALL R1 2 1  
     311 [-]: LOADN R2 20  
     312 [-]: JUMPIFNOTLT R2 R1 L38
     313 [-]: GETUPVAL R2 15
     314 [-]: GETTABLEKS R1 R2 K52 [0x9742B85B]
     315 [-]: GETIMPORT R2 54 [0xE91D7466]
     316 [-]: GETUPVAL R4 16
     317 [-]: GETTABLEKS R3 R4 K68 ["konzuGoAirDocs"]
     318 [-]: CALL R1 2 0  
L38: 319 [-]: GETUPVAL R1 2
     320 [-]: JUMPIF R1 L40
     321 [-]: GETIMPORT R1 37 [0x89326C93]
     322 [-]: GETIMPORT R3 27 [0x0469F296]
     323 [-]: LOADK R4 K69 ["ArrivalDetection"]
     324 [-]: CALL R3 1 -1 
     325 [-]: NAMECALL R1 R1 K70 [0x46A0EBF5]
     326 [-]: CALL R1 -1 1 
     327 [-]: SETUPVAL R1 23
     328 [-]: GETUPVAL R2 23
     329 [-]: FASTCALL1 62 R2 L39
     330 [-]: GETIMPORT R1 5 [0x7B998233]
     331 [-]: CALL R1 1 1  
L39: 332 [-]: JUMPIF R1 L41
     333 [-]: GETUPVAL R1 23
     334 [-]: LOADK R3 K62 ["Enable"]
     335 [-]: NAMECALL R1 R1 K11 [0x8EB2112D]
     336 [-]: CALL R1 2 0  
     337 [-]: GETIMPORT R1 42 [0x11A19C5E]
     338 [-]: GETUPVAL R2 23
     339 [-]: LOADK R3 K71 ["OnTouched"]
     340 [-]: CALL R1 2 0  
     341 [-]: JUMP L41
    
L40: 342 [-]: GETUPVAL R1 17
     343 [-]: GETIMPORT R2 27 [0x0469F296]
     344 [-]: LOADK R3 K56 ["NarmerCetusRescueSpawnController"]
     345 [-]: CALL R2 1 -1 
     346 [-]: CALL R1 -1 0 
L41: 347 [-]: LOADB R1 0   
     348 [-]: SETUPVAL R1 2
     349 [-]: JUMP L116
   
L42: 350 [-]: GETUPVAL R2 1
     351 [-]: GETTABLEKS R1 R2 K72 ["ENTER_TOWER"]
     352 [-]: JUMPIFNOTEQ R0 R1 L57
     353 [-]: GETIMPORT R1 17 ["_T"]
     354 [-]: LOADB R2 0   
     355 [-]: SETTABLEKS R2 R1 K58 ["MinimalHud"]
     356 [-]: GETIMPORT R1 17 ["_T"]
     357 [-]: LOADNIL R2   
     358 [-]: SETTABLEKS R2 R1 K59 ["ForceShowImpactMessages"]
     359 [-]: GETUPVAL R2 22
     360 [-]: FASTCALL1 62 R2 L43
     361 [-]: GETIMPORT R1 5 [0x7B998233]
     362 [-]: CALL R1 1 1  
L43: 363 [-]: JUMPIF R1 L45
     364 [-]: GETUPVAL R1 22
     365 [-]: NAMECALL R1 R1 K64 [0xF37943FF]
     366 [-]: CALL R1 1 1  
     367 [-]: JUMPIFNOT R1 L44
     368 [-]: GETUPVAL R1 22
     369 [-]: LOADK R3 K65 ["Disable"]
     370 [-]: NAMECALL R1 R1 K11 [0x8EB2112D]
     371 [-]: CALL R1 2 0  
L44: 372 [-]: LOADNIL R1   
     373 [-]: SETUPVAL R1 22
L45: 374 [-]: GETUPVAL R1 7
     375 [-]: GETIMPORT R2 27 [0x0469F296]
     376 [-]: LOADK R3 K73 ["EnterTower"]
     377 [-]: CALL R2 1 -1 
     378 [-]: CALL R1 -1 0 
     379 [-]: GETUPVAL R2 5
     380 [-]: GETTABLEKS R1 R2 K24 [0xA1DF01D6]
     381 [-]: GETUPVAL R3 6
     382 [-]: GETTABLEKS R2 R3 K74 ["enterTower"]
     383 [-]: CALL R1 1 0  
     384 [-]: GETUPVAL R2 24
     385 [-]: GETTABLEKS R1 R2 K75 [0x294D5408]
     386 [-]: LOADB R2 0   
     387 [-]: LOADB R3 0   
     388 [-]: LOADB R4 0   
     389 [-]: CALL R1 3 0  
     390 [-]: GETIMPORT R1 37 [0x89326C93]
     391 [-]: GETIMPORT R3 27 [0x0469F296]
     392 [-]: LOADK R4 K76 ["UnumTowerA"]
     393 [-]: CALL R3 1 -1 
     394 [-]: NAMECALL R1 R1 K70 [0x46A0EBF5]
     395 [-]: CALL R1 -1 1 
     396 [-]: SETUPVAL R1 25
     397 [-]: GETUPVAL R2 25
     398 [-]: FASTCALL1 62 R2 L46
     399 [-]: GETIMPORT R1 5 [0x7B998233]
     400 [-]: CALL R1 1 1  
L46: 401 [-]: JUMPIFNOT R1 L48
     402 [-]: GETIMPORT R1 37 [0x89326C93]
     403 [-]: GETIMPORT R3 27 [0x0469F296]
     404 [-]: LOADK R4 K77 ["TeleportInsideTower"]
     405 [-]: CALL R3 1 -1 
     406 [-]: NAMECALL R1 R1 K70 [0x46A0EBF5]
     407 [-]: CALL R1 -1 1 
     408 [-]: FASTCALL1 62 R1 L47
     409 [-]: MOVE R3 R1   
     410 [-]: GETIMPORT R2 5 [0x7B998233]
     411 [-]: CALL R2 1 1  
L47: 412 [-]: JUMPIF R2 L48
     413 [-]: NAMECALL R2 R1 K78 [0xA2880940]
     414 [-]: CALL R2 1 0  
L48: 415 [-]: LOADNIL R1   
     416 [-]: GETUPVAL R3 8
     417 [-]: FASTCALL1 62 R3 L49
     418 [-]: GETIMPORT R2 5 [0x7B998233]
     419 [-]: CALL R2 1 1  
L49: 420 [-]: JUMPIF R2 L50
     421 [-]: GETUPVAL R2 8
     422 [-]: GETUPVAL R4 26
     423 [-]: NAMECALL R2 R2 K79 [0xF2DEAF69]
     424 [-]: CALL R2 2 1  
     425 [-]: JUMPIFNOT R2 L50
     426 [-]: GETUPVAL R1 8
     427 [-]: JUMP L51
    
L50: 428 [-]: GETIMPORT R2 37 [0x89326C93]
     429 [-]: GETUPVAL R4 26
     430 [-]: GETUPVAL R5 8
     431 [-]: NAMECALL R5 R5 K80 [0xD1586535]
     432 [-]: CALL R5 1 1  
     433 [-]: LOADN R6 15  
     434 [-]: NAMECALL R2 R2 K81 [0x4E5939A5]
     435 [-]: CALL R2 4 1  
     436 [-]: MOVE R1 R2   
L51: 437 [-]: FASTCALL1 62 R1 L52
     438 [-]: MOVE R3 R1   
     439 [-]: GETIMPORT R2 5 [0x7B998233]
     440 [-]: CALL R2 1 1  
L52: 441 [-]: JUMPIF R2 L55
     442 [-]: LOADB R4 1   
     443 [-]: NAMECALL R2 R1 K82 [0xC4759C9F]
     444 [-]: CALL R2 2 0  
     445 [-]: NAMECALL R2 R1 K83 [0xFF005826]
     446 [-]: CALL R2 1 1  
     447 [-]: GETIMPORT R4 32 [0xBE190284]
     448 [-]: FASTCALL1 62 R4 L53
     449 [-]: GETIMPORT R3 5 [0x7B998233]
     450 [-]: CALL R3 1 1  
L53: 451 [-]: JUMPIF R3 L54
     452 [-]: GETIMPORT R3 32 [0xBE190284]
     453 [-]: NAMECALL R3 R3 K84 [0xE9D9BC4A]
     454 [-]: CALL R3 1 0  
L54: 455 [-]: MOVE R5 R2   
     456 [-]: NAMECALL R6 R1 K85 [0xF376ADF1]
     457 [-]: CALL R6 1 1  
     458 [-]: LOADB R7 0   
     459 [-]: LOADB R8 0   
     460 [-]: LOADB R9 1   
     461 [-]: NAMECALL R3 R1 K86 [0xCAA5DE6D]
     462 [-]: CALL R3 6 0  
L55: 463 [-]: GETUPVAL R3 27
     464 [-]: FASTCALL1 62 R3 L56
     465 [-]: GETIMPORT R2 5 [0x7B998233]
     466 [-]: CALL R2 1 1  
L56: 467 [-]: JUMPIF R2 L116
     468 [-]: GETUPVAL R2 27
     469 [-]: LOADB R4 0   
     470 [-]: NAMECALL R2 R2 K87 [0xA74EA8AC]
     471 [-]: CALL R2 2 0  
     472 [-]: JUMP L116
   
L57: 473 [-]: GETUPVAL R2 1
     474 [-]: GETTABLEKS R1 R2 K12 ["POWER_TOWER_A"]
     475 [-]: JUMPIFNOTEQ R0 R1 L65
     476 [-]: GETUPVAL R2 22
     477 [-]: FASTCALL1 62 R2 L58
     478 [-]: GETIMPORT R1 5 [0x7B998233]
     479 [-]: CALL R1 1 1  
L58: 480 [-]: JUMPIF R1 L60
     481 [-]: GETUPVAL R1 22
     482 [-]: NAMECALL R1 R1 K64 [0xF37943FF]
     483 [-]: CALL R1 1 1  
     484 [-]: JUMPIFNOT R1 L59
     485 [-]: GETUPVAL R1 22
     486 [-]: LOADK R3 K65 ["Disable"]
     487 [-]: NAMECALL R1 R1 K11 [0x8EB2112D]
     488 [-]: CALL R1 2 0  
L59: 489 [-]: LOADNIL R1   
     490 [-]: SETUPVAL R1 22
L60: 491 [-]: GETIMPORT R1 17 ["_T"]
     492 [-]: LOADB R2 0   
     493 [-]: SETTABLEKS R2 R1 K15 ["IsRandomWhisperActive"]
     494 [-]: GETIMPORT R1 17 ["_T"]
     495 [-]: LOADN R2 0   
     496 [-]: SETTABLEKS R2 R1 K35 ["OstronHostageRescueCount"]
     497 [-]: GETUPVAL R1 2
     498 [-]: JUMPIF R1 L64
     499 [-]: GETUPVAL R2 5
     500 [-]: GETTABLEKS R1 R2 K88 [0xDC3B2033]
     501 [-]: CALL R1 0 0  
     502 [-]: LOADNIL R1   
     503 [-]: SETUPVAL R1 25
     504 [-]: GETIMPORT R1 37 [0x89326C93]
     505 [-]: GETUPVAL R3 28
     506 [-]: NAMECALL R1 R1 K70 [0x46A0EBF5]
     507 [-]: CALL R1 2 1  
     508 [-]: SETUPVAL R1 23
     509 [-]: GETUPVAL R2 23
     510 [-]: FASTCALL1 62 R2 L61
     511 [-]: GETIMPORT R1 5 [0x7B998233]
     512 [-]: CALL R1 1 1  
L61: 513 [-]: JUMPIF R1 L62
     514 [-]: GETIMPORT R1 42 [0x11A19C5E]
     515 [-]: GETUPVAL R2 23
     516 [-]: LOADK R3 K71 ["OnTouched"]
     517 [-]: CALL R1 2 0  
L62: 518 [-]: GETIMPORT R1 37 [0x89326C93]
     519 [-]: GETIMPORT R3 27 [0x0469F296]
     520 [-]: LOADK R4 K89 ["DoorHint"]
     521 [-]: CALL R3 1 1  
     522 [-]: GETUPVAL R4 8
     523 [-]: NAMECALL R4 R4 K80 [0xD1586535]
     524 [-]: CALL R4 1 -1 
     525 [-]: NAMECALL R1 R1 K90 [0xC7B81E8D]
     526 [-]: CALL R1 -1 1 
     527 [-]: FASTCALL1 62 R1 L63
     528 [-]: MOVE R3 R1   
     529 [-]: GETIMPORT R2 5 [0x7B998233]
     530 [-]: CALL R2 1 1  
L63: 531 [-]: JUMPIF R2 L64
     532 [-]: LOADK R4 K91 ["Lock"]
     533 [-]: NAMECALL R2 R1 K11 [0x8EB2112D]
     534 [-]: CALL R2 2 0  
     535 [-]: GETIMPORT R2 21 [0xCBD666E1]
     536 [-]: LOADN R3 0   
     537 [-]: CALL R2 1 0  
     538 [-]: LOADK R4 K92 ["Close"]
     539 [-]: NAMECALL R2 R1 K11 [0x8EB2112D]
     540 [-]: CALL R2 2 0  
L64: 541 [-]: GETUPVAL R1 29
     542 [-]: GETUPVAL R3 30
     543 [-]: GETTABLEKS R2 R3 K93 ["A"]
     544 [-]: LOADB R3 1   
     545 [-]: GETUPVAL R4 2
     546 [-]: CALL R1 3 0  
     547 [-]: LOADB R1 0   
     548 [-]: SETUPVAL R1 2
     549 [-]: GETUPVAL R1 17
     550 [-]: GETIMPORT R2 27 [0x0469F296]
     551 [-]: LOADK R3 K94 ["NarmerRescueUnumTowerA"]
     552 [-]: CALL R2 1 -1 
     553 [-]: CALL R1 -1 0 
     554 [-]: JUMP L116
   
L65: 555 [-]: GETUPVAL R2 1
     556 [-]: GETTABLEKS R1 R2 K95 ["POWER_TOWER_B"]
     557 [-]: JUMPIFNOTEQ R0 R1 L70
     558 [-]: GETUPVAL R1 2
     559 [-]: JUMPIF R1 L66
     560 [-]: LOADNIL R1   
     561 [-]: SETUPVAL R1 25
L66: 562 [-]: GETIMPORT R1 17 ["_T"]
     563 [-]: LOADN R2 0   
     564 [-]: SETTABLEKS R2 R1 K35 ["OstronHostageRescueCount"]
     565 [-]: GETUPVAL R1 29
     566 [-]: GETUPVAL R3 30
     567 [-]: GETTABLEKS R2 R3 K96 ["B"]
     568 [-]: LOADB R3 1   
     569 [-]: GETUPVAL R4 2
     570 [-]: CALL R1 3 0  
     571 [-]: GETUPVAL R2 22
     572 [-]: FASTCALL1 62 R2 L67
     573 [-]: GETIMPORT R1 5 [0x7B998233]
     574 [-]: CALL R1 1 1  
L67: 575 [-]: JUMPIF R1 L69
     576 [-]: GETUPVAL R1 22
     577 [-]: NAMECALL R1 R1 K64 [0xF37943FF]
     578 [-]: CALL R1 1 1  
     579 [-]: JUMPIFNOT R1 L68
     580 [-]: GETUPVAL R1 22
     581 [-]: LOADK R3 K65 ["Disable"]
     582 [-]: NAMECALL R1 R1 K11 [0x8EB2112D]
     583 [-]: CALL R1 2 0  
L68: 584 [-]: LOADNIL R1   
     585 [-]: SETUPVAL R1 22
L69: 586 [-]: GETUPVAL R1 7
     587 [-]: GETIMPORT R2 27 [0x0469F296]
     588 [-]: LOADK R3 K97 ["TowerBDevice1Marker"]
     589 [-]: CALL R2 1 1  
     590 [-]: LOADB R3 1   
     591 [-]: CALL R1 2 0  
     592 [-]: GETUPVAL R2 5
     593 [-]: GETTABLEKS R1 R2 K24 [0xA1DF01D6]
     594 [-]: GETUPVAL R3 6
     595 [-]: GETTABLEKS R2 R3 K98 ["activateDevices"]
     596 [-]: CALL R1 1 0  
     597 [-]: LOADB R1 0   
     598 [-]: SETUPVAL R1 2
     599 [-]: GETUPVAL R1 17
     600 [-]: GETIMPORT R2 27 [0x0469F296]
     601 [-]: LOADK R3 K99 ["NarmerRescueUnumTowerB"]
     602 [-]: CALL R2 1 -1 
     603 [-]: CALL R1 -1 0 
     604 [-]: JUMP L116
   
L70: 605 [-]: GETUPVAL R2 1
     606 [-]: GETTABLEKS R1 R2 K100 ["POWER_TOWER_C"]
     607 [-]: JUMPIFNOTEQ R0 R1 L75
     608 [-]: GETUPVAL R1 2
     609 [-]: JUMPIF R1 L71
     610 [-]: LOADNIL R1   
     611 [-]: SETUPVAL R1 25
L71: 612 [-]: GETIMPORT R1 17 ["_T"]
     613 [-]: LOADN R2 0   
     614 [-]: SETTABLEKS R2 R1 K35 ["OstronHostageRescueCount"]
     615 [-]: GETUPVAL R1 29
     616 [-]: GETUPVAL R3 30
     617 [-]: GETTABLEKS R2 R3 K101 ["C"]
     618 [-]: LOADB R3 1   
     619 [-]: GETUPVAL R4 2
     620 [-]: CALL R1 3 0  
     621 [-]: GETUPVAL R2 22
     622 [-]: FASTCALL1 62 R2 L72
     623 [-]: GETIMPORT R1 5 [0x7B998233]
     624 [-]: CALL R1 1 1  
L72: 625 [-]: JUMPIF R1 L74
     626 [-]: GETUPVAL R1 22
     627 [-]: NAMECALL R1 R1 K64 [0xF37943FF]
     628 [-]: CALL R1 1 1  
     629 [-]: JUMPIFNOT R1 L73
     630 [-]: GETUPVAL R1 22
     631 [-]: LOADK R3 K65 ["Disable"]
     632 [-]: NAMECALL R1 R1 K11 [0x8EB2112D]
     633 [-]: CALL R1 2 0  
L73: 634 [-]: LOADNIL R1   
     635 [-]: SETUPVAL R1 22
L74: 636 [-]: GETUPVAL R1 7
     637 [-]: GETIMPORT R2 27 [0x0469F296]
     638 [-]: LOADK R3 K102 ["TowerCDevice1Marker"]
     639 [-]: CALL R2 1 -1 
     640 [-]: CALL R1 -1 0 
     641 [-]: GETUPVAL R2 5
     642 [-]: GETTABLEKS R1 R2 K24 [0xA1DF01D6]
     643 [-]: GETUPVAL R3 6
     644 [-]: GETTABLEKS R2 R3 K98 ["activateDevices"]
     645 [-]: CALL R1 1 0  
     646 [-]: LOADB R1 0   
     647 [-]: SETUPVAL R1 2
     648 [-]: GETUPVAL R1 17
     649 [-]: GETIMPORT R2 27 [0x0469F296]
     650 [-]: LOADK R3 K103 ["NarmerRescueUnumTowerC"]
     651 [-]: CALL R2 1 -1 
     652 [-]: CALL R1 -1 0 
     653 [-]: JUMP L116
   
L75: 654 [-]: GETUPVAL R2 1
     655 [-]: GETTABLEKS R1 R2 K13 ["TOWER_ROOF"]
     656 [-]: JUMPIFNOTEQ R0 R1 L86
     657 [-]: GETUPVAL R2 1
     658 [-]: GETTABLEKS R1 R2 K13 ["TOWER_ROOF"]
     659 [-]: GETUPVAL R4 0
     660 [-]: GETTABLE R3 R4 R1
     661 [-]: FASTCALL1 62 R3 L76
     662 [-]: GETIMPORT R2 5 [0x7B998233]
     663 [-]: CALL R2 1 1  
L76: 664 [-]: JUMPIFNOT R2 L77
     665 [-]: JUMP L79
    
L77: 666 [-]: LOADN R2 0   
     667 [-]: JUMPIFNOTLT R2 R1 L79
     668 [-]: GETUPVAL R5 0
     669 [-]: GETTABLE R4 R5 R1
     670 [-]: GETTABLEKS R3 R4 K46 ["startF"]
     671 [-]: FASTCALL1 62 R3 L78
     672 [-]: GETIMPORT R2 5 [0x7B998233]
     673 [-]: CALL R2 1 1  
L78: 674 [-]: JUMPIF R2 L79
     675 [-]: GETUPVAL R4 0
     676 [-]: GETTABLE R3 R4 R1
     677 [-]: GETTABLEKS R2 R3 K46 ["startF"]
     678 [-]: LOADK R4 K10 ["TriggerPort"]
     679 [-]: NAMECALL R2 R2 K11 [0x8EB2112D]
     680 [-]: CALL R2 2 0  
L79: 681 [-]: GETUPVAL R2 22
     682 [-]: FASTCALL1 62 R2 L80
     683 [-]: GETIMPORT R1 5 [0x7B998233]
     684 [-]: CALL R1 1 1  
L80: 685 [-]: JUMPIF R1 L82
     686 [-]: GETUPVAL R1 22
     687 [-]: NAMECALL R1 R1 K64 [0xF37943FF]
     688 [-]: CALL R1 1 1  
     689 [-]: JUMPIFNOT R1 L81
     690 [-]: GETUPVAL R1 22
     691 [-]: LOADK R3 K65 ["Disable"]
     692 [-]: NAMECALL R1 R1 K11 [0x8EB2112D]
     693 [-]: CALL R1 2 0  
L81: 694 [-]: LOADNIL R1   
     695 [-]: SETUPVAL R1 22
L82: 696 [-]: GETIMPORT R1 17 ["_T"]
     697 [-]: LOADB R2 0   
     698 [-]: SETTABLEKS R2 R1 K104 ["MurexTimeout"]
     699 [-]: GETUPVAL R1 2
     700 [-]: JUMPIF R1 L85
     701 [-]: GETIMPORT R1 17 ["_T"]
     702 [-]: LOADB R2 0   
     703 [-]: SETTABLEKS R2 R1 K15 ["IsRandomWhisperActive"]
     704 [-]: GETUPVAL R2 31
     705 [-]: FASTCALL1 62 R2 L83
     706 [-]: GETIMPORT R1 5 [0x7B998233]
     707 [-]: CALL R1 1 1  
L83: 708 [-]: JUMPIF R1 L84
     709 [-]: GETUPVAL R1 32
     710 [-]: GETUPVAL R3 31
     711 [-]: NAMECALL R1 R1 K105 [0x775C858B]
     712 [-]: CALL R1 2 0  
L84: 713 [-]: LOADNIL R1   
     714 [-]: SETUPVAL R1 25
L85: 715 [-]: GETUPVAL R2 15
     716 [-]: GETTABLEKS R1 R2 K52 [0x9742B85B]
     717 [-]: GETIMPORT R2 54 [0xE91D7466]
     718 [-]: GETUPVAL R4 16
     719 [-]: GETTABLEKS R3 R4 K106 ["murexOrbitalLaunch"]
     720 [-]: CALL R1 2 0  
     721 [-]: GETUPVAL R2 5
     722 [-]: GETTABLEKS R1 R2 K24 [0xA1DF01D6]
     723 [-]: GETUPVAL R3 6
     724 [-]: GETTABLEKS R2 R3 K98 ["activateDevices"]
     725 [-]: CALL R1 1 0  
     726 [-]: GETUPVAL R2 5
     727 [-]: GETTABLEKS R1 R2 K107 [0xF94B7537]
     728 [-]: CALL R1 0 0  
     729 [-]: GETUPVAL R1 29
     730 [-]: GETUPVAL R3 30
     731 [-]: GETTABLEKS R2 R3 K108 ["ROOF"]
     732 [-]: LOADB R3 0   
     733 [-]: GETUPVAL R4 2
     734 [-]: CALL R1 3 0  
     735 [-]: GETIMPORT R1 110 [0x603636AD]
     736 [-]: LOADK R2 K111 ["/Lotus/Language/NewWar/P3M2MurexTimeLimit"]
     737 [-]: DUPTABLE R3 113
     738 [-]: LOADN R4 60  
     739 [-]: SETTABLEKS R4 R3 K112 ["TIMELEFT"]
     740 [-]: CALL R1 2 1  
     741 [-]: GETUPVAL R3 5
     742 [-]: GETTABLEKS R2 R3 K114 [0xE8FA0E68]
     743 [-]: LOADN R3 60  
     744 [-]: LOADB R4 0   
     745 [-]: LOADB R5 0   
     746 [-]: LOADB R6 0   
     747 [-]: GETUPVAL R8 5
     748 [-]: GETTABLEKS R7 R8 K115 ["TIMELEFT_STRING"]
     749 [-]: MOVE R8 R1   
     750 [-]: LOADN R9 5   
     751 [-]: CALL R2 7 0  
     752 [-]: GETUPVAL R3 24
     753 [-]: GETTABLEKS R2 R3 K116 [0x12A41A40]
     754 [-]: LOADB R3 0   
     755 [-]: LOADN R4 0   
     756 [-]: CALL R2 2 0  
     757 [-]: LOADB R2 0   
     758 [-]: SETUPVAL R2 2
     759 [-]: JUMP L116
   
L86: 760 [-]: GETUPVAL R2 1
     761 [-]: GETTABLEKS R1 R2 K117 ["TIMESTOP"]
     762 [-]: JUMPIFNOTEQ R0 R1 L104
     763 [-]: GETUPVAL R2 1
     764 [-]: GETTABLEKS R1 R2 K117 ["TIMESTOP"]
     765 [-]: GETUPVAL R4 0
     766 [-]: GETTABLE R3 R4 R1
     767 [-]: FASTCALL1 62 R3 L87
     768 [-]: GETIMPORT R2 5 [0x7B998233]
     769 [-]: CALL R2 1 1  
L87: 770 [-]: JUMPIFNOT R2 L88
     771 [-]: JUMP L90
    
L88: 772 [-]: LOADN R2 0   
     773 [-]: JUMPIFNOTLT R2 R1 L90
     774 [-]: GETUPVAL R5 0
     775 [-]: GETTABLE R4 R5 R1
     776 [-]: GETTABLEKS R3 R4 K46 ["startF"]
     777 [-]: FASTCALL1 62 R3 L89
     778 [-]: GETIMPORT R2 5 [0x7B998233]
     779 [-]: CALL R2 1 1  
L89: 780 [-]: JUMPIF R2 L90
     781 [-]: GETUPVAL R4 0
     782 [-]: GETTABLE R3 R4 R1
     783 [-]: GETTABLEKS R2 R3 K46 ["startF"]
     784 [-]: LOADK R4 K10 ["TriggerPort"]
     785 [-]: NAMECALL R2 R2 K11 [0x8EB2112D]
     786 [-]: CALL R2 2 0  
L90: 787 [-]: GETUPVAL R1 33
     788 [-]: GETIMPORT R2 27 [0x0469F296]
     789 [-]: LOADK R3 K118 ["TimeStopNPCSpawn"]
     790 [-]: CALL R2 1 -1 
     791 [-]: CALL R1 -1 0 
     792 [-]: GETUPVAL R2 15
     793 [-]: GETTABLEKS R1 R2 K52 [0x9742B85B]
     794 [-]: GETIMPORT R2 54 [0xE91D7466]
     795 [-]: GETUPVAL R4 16
     796 [-]: GETTABLEKS R3 R4 K119 ["unumSpeaks"]
     797 [-]: CALL R1 2 0  
     798 [-]: LOADNIL R1   
     799 [-]: GETUPVAL R3 8
     800 [-]: FASTCALL1 62 R3 L91
     801 [-]: GETIMPORT R2 5 [0x7B998233]
     802 [-]: CALL R2 1 1  
L91: 803 [-]: JUMPIF R2 L92
     804 [-]: GETUPVAL R2 8
     805 [-]: GETIMPORT R4 121 ["gLotusOperatorAvatarType"]
     806 [-]: NAMECALL R2 R2 K79 [0xF2DEAF69]
     807 [-]: CALL R2 2 1  
     808 [-]: JUMPIFNOT R2 L94
L92: 809 [-]: GETIMPORT R2 37 [0x89326C93]
     810 [-]: NAMECALL R2 R2 K122 [0xFB64E76C]
     811 [-]: CALL R2 1 1  
     812 [-]: FASTCALL1 62 R2 L93
     813 [-]: MOVE R4 R2   
     814 [-]: GETIMPORT R3 5 [0x7B998233]
     815 [-]: CALL R3 1 1  
L93: 816 [-]: JUMPIF R3 L95
     817 [-]: NAMECALL R3 R2 K123 [0xA534C3AC]
     818 [-]: CALL R3 1 1  
     819 [-]: MOVE R1 R3   
     820 [-]: JUMP L95
    
L94: 821 [-]: GETUPVAL R1 8
L95: 822 [-]: FASTCALL1 62 R1 L96
     823 [-]: MOVE R3 R1   
     824 [-]: GETIMPORT R2 5 [0x7B998233]
     825 [-]: CALL R2 1 1  
L96: 826 [-]: JUMPIF R2 L97
     827 [-]: NAMECALL R2 R1 K124 [0x1AC1655C]
     828 [-]: CALL R2 1 1  
     829 [-]: GETIMPORT R4 27 [0x0469F296]
     830 [-]: LOADK R5 K125 ["UNUM_INVULNERABLE"]
     831 [-]: CALL R4 1 1  
     832 [-]: LOADN R5 25  
     833 [-]: LOADN R6 6   
     834 [-]: LOADN R7 0   
     835 [-]: NAMECALL R2 R2 K126 [0xA383DE31]
     836 [-]: CALL R2 5 0  
L97: 837 [-]: GETUPVAL R3 15
     838 [-]: GETTABLEKS R2 R3 K127 [0xFC87A231]
     839 [-]: CALL R2 0 0  
     840 [-]: GETUPVAL R2 8
     841 [-]: GETIMPORT R4 129 [0x14BECE96]
     842 [-]: LOADB R5 0   
     843 [-]: NAMECALL R2 R2 K130 [0x659D451F]
     844 [-]: CALL R2 3 0  
     845 [-]: GETUPVAL R2 8
     846 [-]: NAMECALL R2 R2 K131 [0x0B4BCFB6]
     847 [-]: CALL R2 1 1  
     848 [-]: FASTCALL1 62 R2 L98
     849 [-]: MOVE R4 R2   
     850 [-]: GETIMPORT R3 5 [0x7B998233]
     851 [-]: CALL R3 1 1  
L98: 852 [-]: JUMPIF R3 L99
     853 [-]: GETUPVAL R5 8
     854 [-]: NAMECALL R5 R5 K132 [0xEBFBA9E4]
     855 [-]: CALL R5 1 1  
     856 [-]: LOADN R6 -1  
     857 [-]: LOADN R7 50  
     858 [-]: LOADN R8 0   
     859 [-]: NAMECALL R3 R2 K133 [0xB1C85409]
     860 [-]: CALL R3 5 0  
     861 [-]: GETUPVAL R5 8
     862 [-]: NAMECALL R5 R5 K132 [0xEBFBA9E4]
     863 [-]: CALL R5 1 1  
     864 [-]: LOADN R6 -1  
     865 [-]: LOADN R7 50  
     866 [-]: LOADN R8 3   
     867 [-]: NAMECALL R3 R2 K133 [0xB1C85409]
     868 [-]: CALL R3 5 0  
L99: 869 [-]: GETIMPORT R3 37 [0x89326C93]
     870 [-]: GETIMPORT R5 27 [0x0469F296]
     871 [-]: LOADK R6 K134 ["FreezePortForwarder"]
     872 [-]: CALL R5 1 -1 
     873 [-]: NAMECALL R3 R3 K70 [0x46A0EBF5]
     874 [-]: CALL R3 -1 1 
     875 [-]: FASTCALL1 62 R3 L100
     876 [-]: MOVE R5 R3   
     877 [-]: GETIMPORT R4 5 [0x7B998233]
     878 [-]: CALL R4 1 1  
L100: 879 [-]: JUMPIF R4 L101
     880 [-]: LOADK R6 K10 ["TriggerPort"]
     881 [-]: NAMECALL R4 R3 K11 [0x8EB2112D]
     882 [-]: CALL R4 2 0  
L101: 883 [-]: GETUPVAL R5 5
     884 [-]: GETTABLEKS R4 R5 K135 [0xBD3CE95D]
     885 [-]: CALL R4 0 0  
     886 [-]: GETUPVAL R4 34
     887 [-]: CALL R4 0 0  
     888 [-]: GETIMPORT R4 37 [0x89326C93]
     889 [-]: GETIMPORT R6 27 [0x0469F296]
     890 [-]: LOADK R7 K136 ["BeanstalksLevelExitTrigger"]
     891 [-]: CALL R6 1 -1 
     892 [-]: NAMECALL R4 R4 K70 [0x46A0EBF5]
     893 [-]: CALL R4 -1 1 
     894 [-]: SETUPVAL R4 23
     895 [-]: GETUPVAL R5 23
     896 [-]: FASTCALL1 62 R5 L102
     897 [-]: GETIMPORT R4 5 [0x7B998233]
     898 [-]: CALL R4 1 1  
L102: 899 [-]: JUMPIF R4 L103
     900 [-]: GETIMPORT R4 42 [0x11A19C5E]
     901 [-]: GETUPVAL R5 23
     902 [-]: LOADK R6 K71 ["OnTouched"]
     903 [-]: CALL R4 2 0  
L103: 904 [-]: GETIMPORT R4 21 [0xCBD666E1]
     905 [-]: LOADN R5 3   
     906 [-]: CALL R4 1 0  
     907 [-]: GETUPVAL R5 15
     908 [-]: GETTABLEKS R4 R5 K52 [0x9742B85B]
     909 [-]: GETIMPORT R5 54 [0xE91D7466]
     910 [-]: GETUPVAL R7 16
     911 [-]: GETTABLEKS R6 R7 K137 ["ordisTimeStop"]
     912 [-]: CALL R4 2 0  
     913 [-]: GETUPVAL R5 15
     914 [-]: GETTABLEKS R4 R5 K127 [0xFC87A231]
     915 [-]: CALL R4 0 0  
     916 [-]: GETUPVAL R5 15
     917 [-]: GETTABLEKS R4 R5 K138 [0x11DCFE97]
     918 [-]: GETUPVAL R6 16
     919 [-]: GETTABLEKS R5 R6 K139 ["operatorTimeStop"]
     920 [-]: CALL R4 1 0  
     921 [-]: GETUPVAL R5 5
     922 [-]: GETTABLEKS R4 R5 K24 [0xA1DF01D6]
     923 [-]: GETUPVAL R6 6
     924 [-]: GETTABLEKS R5 R6 K140 ["followTheLight"]
     925 [-]: CALL R4 1 0  
     926 [-]: GETUPVAL R4 22
     927 [-]: LOADK R6 K62 ["Enable"]
     928 [-]: NAMECALL R4 R4 K11 [0x8EB2112D]
     929 [-]: CALL R4 2 0  
     930 [-]: GETUPVAL R5 14
     931 [-]: GETTABLEKS R4 R5 K48 [0xC474A99E]
     932 [-]: GETIMPORT R5 27 [0x0469F296]
     933 [-]: LOADK R6 K141 ["LightBridgeSpawnTrigger"]
     934 [-]: CALL R5 1 1  
     935 [-]: LOADK R6 K62 ["Enable"]
     936 [-]: CALL R4 2 0  
     937 [-]: JUMP L116
   
L104: 938 [-]: GETUPVAL R2 1
     939 [-]: GETTABLEKS R1 R2 K142 ["COMPLETE"]
     940 [-]: JUMPIFNOTEQ R0 R1 L105
     941 [-]: JUMP L116
   
L105: 942 [-]: GETUPVAL R2 1
     943 [-]: GETTABLEKS R1 R2 K143 ["RESPAWN"]
     944 [-]: JUMPIFNOTEQ R0 R1 L116
     945 [-]: GETUPVAL R1 35
     946 [-]: GETUPVAL R3 1
     947 [-]: GETTABLEKS R2 R3 K57 ["RIDE_BALLOON"]
     948 [-]: JUMPIFNOTLE R1 R2 L110
     949 [-]: GETUPVAL R2 8
     950 [-]: FASTCALL1 62 R2 L106
     951 [-]: GETIMPORT R1 5 [0x7B998233]
     952 [-]: CALL R1 1 1  
L106: 953 [-]: JUMPIF R1 L107
     954 [-]: GETUPVAL R1 8
     955 [-]: GETIMPORT R3 145 ["gLotusVehicleAvatarType"]
     956 [-]: NAMECALL R1 R1 K79 [0xF2DEAF69]
     957 [-]: CALL R1 2 1  
     958 [-]: JUMPIFNOT R1 L107
     959 [-]: LOADNIL R1   
     960 [-]: SETUPVAL R1 8
L107: 961 [-]: GETUPVAL R2 36
     962 [-]: FASTCALL1 62 R2 L108
     963 [-]: GETIMPORT R1 5 [0x7B998233]
     964 [-]: CALL R1 1 1  
L108: 965 [-]: JUMPIF R1 L109
     966 [-]: GETUPVAL R1 36
     967 [-]: NAMECALL R1 R1 K146 [0x2047CFE7]
     968 [-]: CALL R1 1 1  
     969 [-]: JUMPIFNOT R1 L109
     970 [-]: GETUPVAL R1 36
     971 [-]: NAMECALL R1 R1 K78 [0xA2880940]
     972 [-]: CALL R1 1 0  
     973 [-]: LOADNIL R1   
     974 [-]: SETUPVAL R1 36
L109: 975 [-]: GETIMPORT R1 21 [0xCBD666E1]
     976 [-]: LOADN R2 1   
     977 [-]: CALL R1 1 0  
     978 [-]: GETUPVAL R2 24
     979 [-]: GETTABLEKS R1 R2 K147 [0x4A6404E4]
     980 [-]: GETUPVAL R2 0
     981 [-]: GETUPVAL R3 35
     982 [-]: GETUPVAL R4 8
     983 [-]: LOADNIL R5   
     984 [-]: LOADNIL R6   
     985 [-]: LOADB R7 1   
     986 [-]: CALL R1 6 1  
     987 [-]: SETUPVAL R1 35
     988 [-]: GETIMPORT R1 17 ["_T"]
     989 [-]: LOADNIL R2   
     990 [-]: SETTABLEKS R2 R1 K148 ["PlayerSpotted"]
     991 [-]: GETIMPORT R1 17 ["_T"]
     992 [-]: LOADNIL R2   
     993 [-]: SETTABLEKS R2 R1 K149 ["deaconList"]
     994 [-]: JUMP L115
   
L110: 995 [-]: GETUPVAL R1 35
     996 [-]: GETUPVAL R3 1
     997 [-]: GETTABLEKS R2 R3 K12 ["POWER_TOWER_A"]
     998 [-]: JUMPIFNOTLE R2 R1 L115
     999 [-]: GETUPVAL R1 35
     1000 [-]: GETUPVAL R3 1
     1001 [-]: GETTABLEKS R2 R3 K13 ["TOWER_ROOF"]
     1002 [-]: JUMPIFNOTEQ R1 R2 L114
     1003 [-]: GETUPVAL R2 8
     1004 [-]: FASTCALL1 62 R2 L111
     1005 [-]: GETIMPORT R1 5 [0x7B998233]
     1006 [-]: CALL R1 1 1  
L111: 1007 [-]: JUMPIF R1 L114
     1008 [-]: GETUPVAL R1 8
     1009 [-]: GETIMPORT R3 121 ["gLotusOperatorAvatarType"]
     1010 [-]: NAMECALL R1 R1 K79 [0xF2DEAF69]
     1011 [-]: CALL R1 2 1  
     1012 [-]: JUMPIFNOT R1 L114
     1013 [-]: GETUPVAL R1 8
     1014 [-]: LOADB R3 1   
     1015 [-]: NAMECALL R1 R1 K150 [0x18F03C5D]
     1016 [-]: CALL R1 2 0  
L112: 1017 [-]: GETUPVAL R2 8
     1018 [-]: FASTCALL1 62 R2 L113
     1019 [-]: GETIMPORT R1 5 [0x7B998233]
     1020 [-]: CALL R1 1 1  
L113: 1021 [-]: JUMPIF R1 L114
     1022 [-]: GETUPVAL R1 8
     1023 [-]: GETIMPORT R3 121 ["gLotusOperatorAvatarType"]
     1024 [-]: NAMECALL R1 R1 K79 [0xF2DEAF69]
     1025 [-]: CALL R1 2 1  
     1026 [-]: JUMPIFNOT R1 L114
     1027 [-]: GETIMPORT R1 21 [0xCBD666E1]
     1028 [-]: LOADN R2 0   
     1029 [-]: CALL R1 1 0  
     1030 [-]: GETUPVAL R1 37
     1031 [-]: CALL R1 0 0  
     1032 [-]: JUMPBACK L112
L114: 1033 [-]: GETUPVAL R2 24
     1034 [-]: GETTABLEKS R1 R2 K147 [0x4A6404E4]
     1035 [-]: GETUPVAL R2 0
     1036 [-]: GETUPVAL R3 35
     1037 [-]: GETUPVAL R4 8
     1038 [-]: LOADNIL R5   
     1039 [-]: LOADNIL R6   
     1040 [-]: LOADB R7 1   
     1041 [-]: CALL R1 6 1  
     1042 [-]: SETUPVAL R1 35
     1043 [-]: GETUPVAL R1 37
     1044 [-]: LOADB R2 1   
     1045 [-]: CALL R1 1 0  
     1046 [-]: GETUPVAL R1 8
     1047 [-]: LOADN R3 0   
     1048 [-]: NAMECALL R1 R1 K151 [0xAEB11A0D]
     1049 [-]: CALL R1 2 0  
     1050 [-]: LOADB R1 0   
     1051 [-]: SETUPVAL R1 38
L115: 1052 [-]: GETUPVAL R1 35
     1053 [-]: GETUPVAL R3 1
     1054 [-]: GETTABLEKS R2 R3 K57 ["RIDE_BALLOON"]
     1055 [-]: JUMPIFNOTEQ R1 R2 L116
     1056 [-]: GETIMPORT R1 17 ["_T"]
     1057 [-]: LOADN R2 0   
     1058 [-]: SETTABLEKS R2 R1 K35 ["OstronHostageRescueCount"]
L116: 1059 [-]: GETUPVAL R1 37
     1060 [-]: LOADB R2 1   
     1061 [-]: CALL R1 1 0  
     1062 [-]: GETUPVAL R2 1
     1063 [-]: GETTABLEKS R1 R2 K34 ["RESCUE_OSTRON"]
     1064 [-]: JUMPIFEQ R0 R1 L120
     1065 [-]: GETUPVAL R2 1
     1066 [-]: GETTABLEKS R1 R2 K13 ["TOWER_ROOF"]
     1067 [-]: JUMPIFEQ R0 R1 L120
     1068 [-]: GETUPVAL R2 1
     1069 [-]: GETTABLEKS R1 R2 K117 ["TIMESTOP"]
     1070 [-]: JUMPIFEQ R0 R1 L120
     1071 [-]: GETUPVAL R3 0
     1072 [-]: GETTABLE R2 R3 R0
     1073 [-]: FASTCALL1 62 R2 L117
     1074 [-]: GETIMPORT R1 5 [0x7B998233]
     1075 [-]: CALL R1 1 1  
L117: 1076 [-]: JUMPIFNOT R1 L118
     1077 [-]: RETURN R0 0  
L118: 1078 [-]: LOADN R1 0   
     1079 [-]: JUMPIFNOTLT R1 R0 L120
     1080 [-]: GETUPVAL R4 0
     1081 [-]: GETTABLE R3 R4 R0
     1082 [-]: GETTABLEKS R2 R3 K46 ["startF"]
     1083 [-]: FASTCALL1 62 R2 L119
     1084 [-]: GETIMPORT R1 5 [0x7B998233]
     1085 [-]: CALL R1 1 1  
L119: 1086 [-]: JUMPIF R1 L120
     1087 [-]: GETUPVAL R3 0
     1088 [-]: GETTABLE R2 R3 R0
     1089 [-]: GETTABLEKS R1 R2 K46 ["startF"]
     1090 [-]: LOADK R3 K10 ["TriggerPort"]
     1091 [-]: NAMECALL R1 R1 K11 [0x8EB2112D]
     1092 [-]: CALL R1 2 0  
L120: 1093 [-]: RETURN R0 0  


; Name:            
; Defined at line: 1948
; #Upvalues:       40
; #Parameters:     1
; Is_vararg:       0
; Max Stack Size:  10

       0 [-]: GETIMPORT R2 1 [0xBE190284]
       1 [-]: FASTCALL1 62 R2 L0
       2 [-]: GETIMPORT R1 3 [0x7B998233]
       3 [-]: CALL R1 1 1  
L 0:   4 [-]: JUMPIFNOT R1 L1
       5 [-]: RETURN R0 0  
L 1:   6 [-]: GETUPVAL R1 0
       7 [-]: CALL R1 0 1  
       8 [-]: JUMPIFNOT R1 L2
       9 [-]: GETUPVAL R1 2
      10 [-]: SETUPVAL R1 1
      11 [-]: GETUPVAL R1 3
      12 [-]: GETUPVAL R4 4
      13 [-]: GETTABLEKS R3 R4 K4 ["RESPAWN"]
      14 [-]: NAMECALL R1 R1 K5 [0x8ABFF40E]
      15 [-]: CALL R1 2 0  
      16 [-]: RETURN R0 0  
L 2:  17 [-]: GETUPVAL R1 5
      18 [-]: CALL R1 0 0  
      19 [-]: GETIMPORT R1 8 ["IsRandomWhisperActive"]
      20 [-]: JUMPIFNOT R1 L9
      21 [-]: GETUPVAL R1 2
      22 [-]: GETUPVAL R3 4
      23 [-]: GETTABLEKS R2 R3 K9 ["POWER_TOWER_A"]
      24 [-]: JUMPIFNOTLE R2 R1 L9
      25 [-]: GETUPVAL R1 2
      26 [-]: GETUPVAL R3 4
      27 [-]: GETTABLEKS R2 R3 K10 ["TOWER_ROOF"]
      28 [-]: JUMPIFNOTLT R1 R2 L9
      29 [-]: GETUPVAL R2 6
      30 [-]: GETTABLEKS R1 R2 K11 ["avatarChanged"]
      31 [-]: JUMPIF R1 L4 
      32 [-]: GETUPVAL R2 7
      33 [-]: FASTCALL1 62 R2 L3
      34 [-]: GETIMPORT R1 3 [0x7B998233]
      35 [-]: CALL R1 1 1  
L 3:  36 [-]: JUMPIF R1 L4 
      37 [-]: GETUPVAL R1 7
      38 [-]: NAMECALL R1 R1 K12 [0x2B54251B]
      39 [-]: CALL R1 1 1  
      40 [-]: GETUPVAL R2 8
      41 [-]: JUMPIFEQ R1 R2 L9
L 4:  42 [-]: GETUPVAL R2 7
      43 [-]: FASTCALL1 62 R2 L5
      44 [-]: GETIMPORT R1 3 [0x7B998233]
      45 [-]: CALL R1 1 1  
L 5:  46 [-]: JUMPIF R1 L6 
      47 [-]: GETUPVAL R1 7
      48 [-]: GETUPVAL R3 8
      49 [-]: GETIMPORT R4 14 ["EMPTY_SYMBOL"]
      50 [-]: NAMECALL R1 R1 K15 [0xB6B094B2]
      51 [-]: CALL R1 3 0  
      52 [-]: JUMP L17
    
L 6:  53 [-]: GETUPVAL R1 8
      54 [-]: GETIMPORT R3 17 [0xC4F53F63]
      55 [-]: GETIMPORT R4 14 ["EMPTY_SYMBOL"]
      56 [-]: NAMECALL R1 R1 K18 [0x47901F07]
      57 [-]: CALL R1 3 1  
      58 [-]: SETUPVAL R1 7
      59 [-]: GETUPVAL R2 9
      60 [-]: FASTCALL1 62 R2 L7
      61 [-]: GETIMPORT R1 3 [0x7B998233]
      62 [-]: CALL R1 1 1  
L 7:  63 [-]: JUMPIF R1 L8 
      64 [-]: GETUPVAL R1 10
      65 [-]: GETUPVAL R3 9
      66 [-]: NAMECALL R1 R1 K19 [0x775C858B]
      67 [-]: CALL R1 2 0  
L 8:  68 [-]: GETIMPORT R1 21 [0xC163F229]
      69 [-]: GETUPVAL R3 11
      70 [-]: GETTABLEKS R2 R3 K22 ["minValue"]
      71 [-]: GETUPVAL R4 11
      72 [-]: GETTABLEKS R3 R4 K23 ["maxValue"]
      73 [-]: CALL R1 2 1  
      74 [-]: GETUPVAL R2 10
      75 [-]: MOVE R4 R1   
      76 [-]: GETUPVAL R5 12
      77 [-]: NAMECALL R2 R2 K24 [0xBD2E96EA]
      78 [-]: CALL R2 3 1  
      79 [-]: SETUPVAL R2 9
      80 [-]: JUMP L17
    
L 9:  81 [-]: GETUPVAL R1 2
      82 [-]: GETUPVAL R3 4
      83 [-]: GETTABLEKS R2 R3 K25 ["INTRO"]
      84 [-]: JUMPIFNOTLE R2 R1 L17
      85 [-]: GETUPVAL R1 2
      86 [-]: GETUPVAL R3 4
      87 [-]: GETTABLEKS R2 R3 K26 ["ENTER_TOWER"]
      88 [-]: JUMPIFNOTLT R1 R2 L17
      89 [-]: GETUPVAL R2 13
      90 [-]: FASTCALL1 62 R2 L10
      91 [-]: GETIMPORT R1 3 [0x7B998233]
      92 [-]: CALL R1 1 1  
L10:  93 [-]: JUMPIF R1 L17
      94 [-]: GETUPVAL R2 8
      95 [-]: FASTCALL1 62 R2 L11
      96 [-]: GETIMPORT R1 3 [0x7B998233]
      97 [-]: CALL R1 1 1  
L11:  98 [-]: JUMPIF R1 L17
      99 [-]: GETUPVAL R1 8
     100 [-]: GETIMPORT R3 28 ["gLotusOperatorAvatarType"]
     101 [-]: NAMECALL R1 R1 K29 [0xF2DEAF69]
     102 [-]: CALL R1 2 1  
     103 [-]: JUMPIFNOT R1 L17
     104 [-]: GETUPVAL R2 14
     105 [-]: FASTCALL1 62 R2 L12
     106 [-]: GETIMPORT R1 3 [0x7B998233]
     107 [-]: CALL R1 1 1  
L12: 108 [-]: JUMPIFNOT R1 L13
     109 [-]: GETUPVAL R1 8
     110 [-]: NAMECALL R1 R1 K30 [0xDE321E6F]
     111 [-]: CALL R1 1 1  
     112 [-]: NAMECALL R1 R1 K31 [0xF7D48EE0]
     113 [-]: CALL R1 1 1  
     114 [-]: LOADN R4 0   
     115 [-]: NAMECALL R2 R1 K32 [0xDADDFB73]
     116 [-]: CALL R2 2 1  
     117 [-]: SETUPVAL R2 14
L13: 118 [-]: GETUPVAL R1 13
     119 [-]: GETUPVAL R3 8
     120 [-]: NAMECALL R1 R1 K33 [0x13D5D3FB]
     121 [-]: CALL R1 2 1  
     122 [-]: GETUPVAL R2 15
     123 [-]: GETUPVAL R4 8
     124 [-]: NAMECALL R2 R2 K33 [0x13D5D3FB]
     125 [-]: CALL R2 2 1  
     126 [-]: JUMPIFNOT R1 L14
     127 [-]: JUMPIF R2 L14
     128 [-]: LOADB R3 1   
     129 [-]: SETUPVAL R3 16
     130 [-]: JUMP L15
    
L14: 131 [-]: JUMPIF R1 L15
     132 [-]: JUMPIFNOT R2 L15
     133 [-]: LOADB R3 0   
     134 [-]: SETUPVAL R3 16
L15: 135 [-]: JUMPIFNOT R1 L16
     136 [-]: GETUPVAL R3 14
     137 [-]: NAMECALL R3 R3 K34 [0x30F46140]
     138 [-]: CALL R3 1 1  
     139 [-]: JUMPIF R3 L16
     140 [-]: GETUPVAL R3 14
     141 [-]: LOADB R5 1   
     142 [-]: NAMECALL R3 R3 K35 [0xA74EA8AC]
     143 [-]: CALL R3 2 0  
     144 [-]: JUMP L17
    
L16: 145 [-]: GETUPVAL R3 14
     146 [-]: NAMECALL R3 R3 K34 [0x30F46140]
     147 [-]: CALL R3 1 1  
     148 [-]: JUMPIFNOT R3 L17
     149 [-]: GETUPVAL R3 16
     150 [-]: JUMPIF R3 L17
     151 [-]: GETUPVAL R3 14
     152 [-]: LOADB R5 0   
     153 [-]: NAMECALL R3 R3 K35 [0xA74EA8AC]
     154 [-]: CALL R3 2 0  
L17: 155 [-]: GETUPVAL R1 2
     156 [-]: GETUPVAL R3 4
     157 [-]: GETTABLEKS R2 R3 K25 ["INTRO"]
     158 [-]: JUMPIFNOTEQ R1 R2 L20
     159 [-]: GETUPVAL R2 17
     160 [-]: FASTCALL1 62 R2 L18
     161 [-]: GETIMPORT R1 3 [0x7B998233]
     162 [-]: CALL R1 1 1  
L18: 163 [-]: JUMPIF R1 L19
     164 [-]: GETUPVAL R1 17
     165 [-]: NAMECALL R1 R1 K36 [0x1C84839C]
     166 [-]: CALL R1 1 1  
     167 [-]: JUMPIF R1 L76
L19: 168 [-]: GETUPVAL R1 3
     169 [-]: GETUPVAL R4 4
     170 [-]: GETTABLEKS R3 R4 K37 ["QUILLS_CAVE"]
     171 [-]: NAMECALL R1 R1 K5 [0x8ABFF40E]
     172 [-]: CALL R1 2 0  
     173 [-]: JUMP L76
    
L20: 174 [-]: GETUPVAL R1 2
     175 [-]: GETUPVAL R3 4
     176 [-]: GETTABLEKS R2 R3 K37 ["QUILLS_CAVE"]
     177 [-]: JUMPIFNOTEQ R1 R2 L28
     178 [-]: GETUPVAL R2 18
     179 [-]: FASTCALL1 62 R2 L21
     180 [-]: GETIMPORT R1 3 [0x7B998233]
     181 [-]: CALL R1 1 1  
L21: 182 [-]: JUMPIF R1 L76
     183 [-]: LOADN R2 5   
     184 [-]: ORK R2 R2 K38 [2]
     185 [-]: GETUPVAL R4 18
     186 [-]: FASTCALL1 62 R4 L22
     187 [-]: GETIMPORT R3 3 [0x7B998233]
     188 [-]: CALL R3 1 1  
L22: 189 [-]: JUMPIF R3 L24
     190 [-]: GETUPVAL R4 8
     191 [-]: FASTCALL1 62 R4 L23
     192 [-]: GETIMPORT R3 3 [0x7B998233]
     193 [-]: CALL R3 1 1  
L23: 194 [-]: JUMPIF R3 L24
     195 [-]: GETUPVAL R3 8
     196 [-]: GETUPVAL R5 18
     197 [-]: NAMECALL R3 R3 K39 [0xBEBAD19F]
     198 [-]: CALL R3 2 1  
     199 [-]: JUMPIFNOTLE R3 R2 L24
     200 [-]: LOADB R1 1   
     201 [-]: JUMP L25
    
L24: 202 [-]: LOADB R1 0   
L25: 203 [-]: JUMPIFNOT R1 L76
     204 [-]: GETUPVAL R2 18
     205 [-]: FASTCALL1 62 R2 L26
     206 [-]: GETIMPORT R1 3 [0x7B998233]
     207 [-]: CALL R1 1 1  
L26: 208 [-]: JUMPIF R1 L27
     209 [-]: GETUPVAL R1 18
     210 [-]: NAMECALL R1 R1 K40 [0xA2880940]
     211 [-]: CALL R1 1 0  
L27: 212 [-]: GETUPVAL R1 3
     213 [-]: GETUPVAL R4 4
     214 [-]: GETTABLEKS R3 R4 K41 ["RESCUE_OSTRON"]
     215 [-]: NAMECALL R1 R1 K5 [0x8ABFF40E]
     216 [-]: CALL R1 2 0  
     217 [-]: JUMP L76
    
L28: 218 [-]: GETUPVAL R1 2
     219 [-]: GETUPVAL R3 4
     220 [-]: GETTABLEKS R2 R3 K41 ["RESCUE_OSTRON"]
     221 [-]: JUMPIFNOTEQ R1 R2 L50
     222 [-]: GETUPVAL R1 19
     223 [-]: CALL R1 0 1  
     224 [-]: JUMPIF R1 L49
     225 [-]: LOADN R4 1   
     226 [-]: GETUPVAL R5 20
     227 [-]: LENGTH R2 R5 
     228 [-]: LOADN R3 1   
     229 [-]: FORNPREP R2 L31
L29: 230 [-]: GETUPVAL R6 20
     231 [-]: GETTABLE R5 R6 R4
     232 [-]: JUMPIF R5 L30
     233 [-]: LOADB R1 0   
     234 [-]: JUMP L32
    
L30: 235 [-]: FORNLOOP R2 L29
L31: 236 [-]: LOADB R1 1   
L32: 237 [-]: JUMPIF R1 L49
     238 [-]: LOADB R1 0   
     239 [-]: GETUPVAL R5 21
     240 [-]: LENGTH R4 R5 
     241 [-]: LOADN R2 1   
     242 [-]: LOADN R3 -1  
     243 [-]: FORNPREP R2 L43
L33: 244 [-]: GETUPVAL R6 20
     245 [-]: GETTABLE R5 R6 R4
     246 [-]: JUMPIF R5 L42
     247 [-]: GETUPVAL R5 22
     248 [-]: GETUPVAL R7 21
     249 [-]: GETTABLE R6 R7 R4
     250 [-]: CALL R5 1 1  
     251 [-]: JUMPIFNOT R5 L42
     252 [-]: GETUPVAL R5 20
     253 [-]: LOADB R6 1   
     254 [-]: SETTABLE R6 R5 R4
     255 [-]: GETUPVAL R7 21
     256 [-]: GETTABLE R6 R7 R4
     257 [-]: FASTCALL1 62 R6 L34
     258 [-]: GETIMPORT R5 3 [0x7B998233]
     259 [-]: CALL R5 1 1  
L34: 260 [-]: JUMPIF R5 L36
     261 [-]: GETUPVAL R6 21
     262 [-]: GETTABLE R5 R6 R4
     263 [-]: GETIMPORT R7 43 [0xBB76409B]
     264 [-]: NAMECALL R5 R5 K44 [0xC9F6A7D7]
     265 [-]: CALL R5 2 1  
     266 [-]: FASTCALL1 62 R5 L35
     267 [-]: MOVE R7 R5   
     268 [-]: GETIMPORT R6 3 [0x7B998233]
     269 [-]: CALL R6 1 1  
L35: 270 [-]: JUMPIF R6 L36
     271 [-]: NAMECALL R6 R5 K40 [0xA2880940]
     272 [-]: CALL R6 1 0  
L36: 273 [-]: GETUPVAL R5 23
     274 [-]: LOADN R6 1   
     275 [-]: JUMPIFNOTLT R6 R5 L41
     276 [-]: GETUPVAL R8 24
     277 [-]: GETTABLEKS R7 R8 K45 ["List"]
     278 [-]: GETTABLEKS R6 R7 K46 ["mElements"]
     279 [-]: GETTABLE R5 R6 R4
     280 [-]: LOADN R6 16  
     281 [-]: SETTABLEKS R6 R5 K47 ["Color"]
     282 [-]: GETIMPORT R6 49 [0x9204B466]
     283 [-]: SETTABLEKS R6 R5 K50 ["Icon"]
     284 [-]: LOADB R1 1   
     285 [-]: GETUPVAL R8 21
     286 [-]: GETTABLE R7 R8 R4
     287 [-]: FASTCALL1 62 R7 L37
     288 [-]: GETIMPORT R6 3 [0x7B998233]
     289 [-]: CALL R6 1 1  
L37: 290 [-]: JUMPIFNOT R6 L38
     291 [-]: JUMP L42
    
L38: 292 [-]: GETUPVAL R7 21
     293 [-]: GETTABLE R6 R7 R4
     294 [-]: GETUPVAL R8 25
     295 [-]: NAMECALL R6 R6 K29 [0xF2DEAF69]
     296 [-]: CALL R6 2 1  
     297 [-]: JUMPIFNOT R6 L39
     298 [-]: GETUPVAL R7 26
     299 [-]: GETTABLEKS R6 R7 K51 [0x9742B85B]
     300 [-]: GETIMPORT R7 53 [0xE91D7466]
     301 [-]: GETUPVAL R9 27
     302 [-]: GETTABLEKS R8 R9 K54 ["hokThankYou"]
     303 [-]: CALL R6 2 0  
     304 [-]: JUMP L42
    
L39: 305 [-]: GETUPVAL R7 21
     306 [-]: GETTABLE R6 R7 R4
     307 [-]: GETUPVAL R8 28
     308 [-]: NAMECALL R6 R6 K29 [0xF2DEAF69]
     309 [-]: CALL R6 2 1  
     310 [-]: JUMPIFNOT R6 L40
     311 [-]: GETUPVAL R7 26
     312 [-]: GETTABLEKS R6 R7 K51 [0x9742B85B]
     313 [-]: GETIMPORT R7 53 [0xE91D7466]
     314 [-]: GETUPVAL R9 27
     315 [-]: GETTABLEKS R8 R9 K55 ["hailukThankYou"]
     316 [-]: CALL R6 2 0  
     317 [-]: JUMP L42
    
L40: 318 [-]: GETUPVAL R7 21
     319 [-]: GETTABLE R6 R7 R4
     320 [-]: GETUPVAL R8 29
     321 [-]: NAMECALL R6 R6 K29 [0xF2DEAF69]
     322 [-]: CALL R6 2 1  
     323 [-]: JUMPIFNOT R6 L42
     324 [-]: GETUPVAL R7 26
     325 [-]: GETTABLEKS R6 R7 K51 [0x9742B85B]
     326 [-]: GETIMPORT R7 53 [0xE91D7466]
     327 [-]: GETUPVAL R9 27
     328 [-]: GETTABLEKS R8 R9 K56 ["teasonaiThankYou"]
     329 [-]: CALL R6 2 0  
     330 [-]: JUMP L42
    
L41: 331 [-]: GETUPVAL R5 8
     332 [-]: GETIMPORT R7 58 [0x0469F296]
     333 [-]: LOADK R8 K59 ["PlayKonzuRescuedTransmissions"]
     334 [-]: CALL R7 1 1  
     335 [-]: LOADB R8 0   
     336 [-]: NAMECALL R5 R5 K60 [0xD5F7912B]
     337 [-]: CALL R5 3 0  
L42: 338 [-]: FORNLOOP R2 L33
L43: 339 [-]: JUMPIFNOT R1 L44
     340 [-]: GETUPVAL R3 24
     341 [-]: GETTABLEKS R2 R3 K45 ["List"]
     342 [-]: LOADNIL R4   
     343 [-]: LOADB R5 1   
     344 [-]: LOADB R6 1   
     345 [-]: NAMECALL R2 R2 K61 [0x71E9AC81]
     346 [-]: CALL R2 4 0  
L44: 347 [-]: LOADN R5 1   
     348 [-]: GETUPVAL R6 20
     349 [-]: LENGTH R3 R6 
     350 [-]: LOADN R4 1   
     351 [-]: FORNPREP R3 L47
L45: 352 [-]: GETUPVAL R7 20
     353 [-]: GETTABLE R6 R7 R5
     354 [-]: JUMPIF R6 L46
     355 [-]: LOADB R2 0   
     356 [-]: JUMP L48
    
L46: 357 [-]: FORNLOOP R3 L45
L47: 358 [-]: LOADB R2 1   
L48: 359 [-]: JUMPIFNOT R2 L49
     360 [-]: GETUPVAL R2 23
     361 [-]: LOADN R3 1   
     362 [-]: JUMPIFNOTLT R3 R2 L49
     363 [-]: NEWTABLE R2 0 0
     364 [-]: SETUPVAL R2 20
     365 [-]: NEWTABLE R2 0 0
     366 [-]: SETUPVAL R2 21
     367 [-]: GETUPVAL R3 23
     368 [-]: ADDK R2 R3 K62 [1]
     369 [-]: SETUPVAL R2 23
     370 [-]: GETUPVAL R2 3
     371 [-]: GETUPVAL R5 4
     372 [-]: GETTABLEKS R4 R5 K63 ["RIDE_BALLOON"]
     373 [-]: NAMECALL R2 R2 K5 [0x8ABFF40E]
     374 [-]: CALL R2 2 0  
L49: 375 [-]: GETUPVAL R1 30
     376 [-]: JUMPIFNOT R1 L76
     377 [-]: GETIMPORT R1 65 [0x603636AD]
     378 [-]: GETUPVAL R3 32
     379 [-]: GETTABLEKS R2 R3 K66 ["optionalRescue"]
     380 [-]: DUPTABLE R3 69
     381 [-]: GETIMPORT R4 71 ["OstronHostageRescueCount"]
     382 [-]: SETTABLEKS R4 R3 K67 ["CURRENT_RESCUE_COUNT"]
     383 [-]: GETUPVAL R4 33
     384 [-]: SETTABLEKS R4 R3 K68 ["TOTAL_RESCUE_COUNT"]
     385 [-]: CALL R1 2 1  
     386 [-]: SETUPVAL R1 31
     387 [-]: GETUPVAL R2 34
     388 [-]: GETTABLEKS R1 R2 K72 [0x118E5C26]
     389 [-]: GETUPVAL R2 31
     390 [-]: CALL R1 1 0  
     391 [-]: JUMP L76
    
L50: 392 [-]: GETUPVAL R1 2
     393 [-]: GETUPVAL R3 4
     394 [-]: GETTABLEKS R2 R3 K63 ["RIDE_BALLOON"]
     395 [-]: JUMPIFNOTEQ R1 R2 L56
     396 [-]: GETUPVAL R1 19
     397 [-]: CALL R1 0 1  
     398 [-]: JUMPIF R1 L55
     399 [-]: GETUPVAL R1 35
     400 [-]: JUMPIF R1 L55
     401 [-]: LOADN R2 5   
     402 [-]: ORK R2 R2 K38 [2]
     403 [-]: GETUPVAL R4 18
     404 [-]: FASTCALL1 62 R4 L51
     405 [-]: GETIMPORT R3 3 [0x7B998233]
     406 [-]: CALL R3 1 1  
L51: 407 [-]: JUMPIF R3 L53
     408 [-]: GETUPVAL R4 8
     409 [-]: FASTCALL1 62 R4 L52
     410 [-]: GETIMPORT R3 3 [0x7B998233]
     411 [-]: CALL R3 1 1  
L52: 412 [-]: JUMPIF R3 L53
     413 [-]: GETUPVAL R3 8
     414 [-]: GETUPVAL R5 18
     415 [-]: NAMECALL R3 R3 K39 [0xBEBAD19F]
     416 [-]: CALL R3 2 1  
     417 [-]: JUMPIFNOTLE R3 R2 L53
     418 [-]: LOADB R1 1   
     419 [-]: JUMP L54
    
L53: 420 [-]: LOADB R1 0   
L54: 421 [-]: JUMPIFNOT R1 L55
     422 [-]: GETUPVAL R2 36
     423 [-]: GETUPVAL R4 4
     424 [-]: GETTABLEKS R3 R4 K63 ["RIDE_BALLOON"]
     425 [-]: GETTABLE R1 R2 R3
     426 [-]: GETIMPORT R2 58 [0x0469F296]
     427 [-]: LOADK R3 K73 ["BalloonStationMarker"]
     428 [-]: CALL R2 1 1  
     429 [-]: SETTABLEKS R2 R1 K74 ["respawnPt"]
     430 [-]: GETUPVAL R1 8
     431 [-]: GETIMPORT R3 58 [0x0469F296]
     432 [-]: LOADK R4 K75 ["PlayBalloonTransmissions"]
     433 [-]: CALL R3 1 1  
     434 [-]: LOADB R4 0   
     435 [-]: NAMECALL R1 R1 K60 [0xD5F7912B]
     436 [-]: CALL R1 3 0  
L55: 437 [-]: GETIMPORT R1 65 [0x603636AD]
     438 [-]: GETUPVAL R3 32
     439 [-]: GETTABLEKS R2 R3 K66 ["optionalRescue"]
     440 [-]: DUPTABLE R3 69
     441 [-]: GETIMPORT R4 71 ["OstronHostageRescueCount"]
     442 [-]: SETTABLEKS R4 R3 K67 ["CURRENT_RESCUE_COUNT"]
     443 [-]: GETUPVAL R4 33
     444 [-]: SETTABLEKS R4 R3 K68 ["TOTAL_RESCUE_COUNT"]
     445 [-]: CALL R1 2 1  
     446 [-]: SETUPVAL R1 31
     447 [-]: GETUPVAL R2 34
     448 [-]: GETTABLEKS R1 R2 K72 [0x118E5C26]
     449 [-]: GETUPVAL R2 31
     450 [-]: CALL R1 1 0  
     451 [-]: JUMP L76
    
L56: 452 [-]: GETUPVAL R1 2
     453 [-]: GETUPVAL R3 4
     454 [-]: GETTABLEKS R2 R3 K26 ["ENTER_TOWER"]
     455 [-]: JUMPIFNOTEQ R1 R2 L59
     456 [-]: GETUPVAL R2 8
     457 [-]: FASTCALL1 62 R2 L57
     458 [-]: GETIMPORT R1 3 [0x7B998233]
     459 [-]: CALL R1 1 1  
L57: 460 [-]: JUMPIF R1 L76
     461 [-]: GETUPVAL R2 37
     462 [-]: FASTCALL1 62 R2 L58
     463 [-]: GETIMPORT R1 3 [0x7B998233]
     464 [-]: CALL R1 1 1  
L58: 465 [-]: JUMPIF R1 L76
     466 [-]: GETUPVAL R1 8
     467 [-]: GETUPVAL R3 37
     468 [-]: NAMECALL R1 R1 K76 [0x9B2E6C87]
     469 [-]: CALL R1 2 1  
     470 [-]: LOADN R2 5   
     471 [-]: JUMPIFNOTLT R1 R2 L76
     472 [-]: GETUPVAL R1 3
     473 [-]: GETUPVAL R4 4
     474 [-]: GETTABLEKS R3 R4 K9 ["POWER_TOWER_A"]
     475 [-]: NAMECALL R1 R1 K5 [0x8ABFF40E]
     476 [-]: CALL R1 2 0  
     477 [-]: JUMP L76
    
L59: 478 [-]: GETUPVAL R1 2
     479 [-]: GETUPVAL R3 4
     480 [-]: GETTABLEKS R2 R3 K9 ["POWER_TOWER_A"]
     481 [-]: JUMPIFNOTEQ R1 R2 L63
     482 [-]: GETUPVAL R2 4
     483 [-]: GETTABLEKS R1 R2 K77 ["POWER_TOWER_B"]
     484 [-]: GETUPVAL R3 8
     485 [-]: FASTCALL1 62 R3 L60
     486 [-]: GETIMPORT R2 3 [0x7B998233]
     487 [-]: CALL R2 1 1  
L60: 488 [-]: JUMPIF R2 L62
     489 [-]: GETUPVAL R3 37
     490 [-]: FASTCALL1 62 R3 L61
     491 [-]: GETIMPORT R2 3 [0x7B998233]
     492 [-]: CALL R2 1 1  
L61: 493 [-]: JUMPIF R2 L62
     494 [-]: GETUPVAL R2 8
     495 [-]: GETUPVAL R4 37
     496 [-]: NAMECALL R2 R2 K76 [0x9B2E6C87]
     497 [-]: CALL R2 2 1  
     498 [-]: LOADN R3 5   
     499 [-]: JUMPIFNOTLT R2 R3 L62
     500 [-]: GETUPVAL R2 3
     501 [-]: MOVE R4 R1   
     502 [-]: NAMECALL R2 R2 K5 [0x8ABFF40E]
     503 [-]: CALL R2 2 0  
L62: 504 [-]: GETIMPORT R1 65 [0x603636AD]
     505 [-]: GETUPVAL R3 32
     506 [-]: GETTABLEKS R2 R3 K66 ["optionalRescue"]
     507 [-]: DUPTABLE R3 69
     508 [-]: GETIMPORT R4 71 ["OstronHostageRescueCount"]
     509 [-]: SETTABLEKS R4 R3 K67 ["CURRENT_RESCUE_COUNT"]
     510 [-]: GETUPVAL R4 33
     511 [-]: SETTABLEKS R4 R3 K68 ["TOTAL_RESCUE_COUNT"]
     512 [-]: CALL R1 2 1  
     513 [-]: SETUPVAL R1 31
     514 [-]: GETUPVAL R2 34
     515 [-]: GETTABLEKS R1 R2 K72 [0x118E5C26]
     516 [-]: GETUPVAL R2 31
     517 [-]: CALL R1 1 0  
     518 [-]: JUMP L76
    
L63: 519 [-]: GETUPVAL R1 2
     520 [-]: GETUPVAL R3 4
     521 [-]: GETTABLEKS R2 R3 K77 ["POWER_TOWER_B"]
     522 [-]: JUMPIFNOTEQ R1 R2 L67
     523 [-]: GETUPVAL R2 4
     524 [-]: GETTABLEKS R1 R2 K78 ["POWER_TOWER_C"]
     525 [-]: GETUPVAL R3 8
     526 [-]: FASTCALL1 62 R3 L64
     527 [-]: GETIMPORT R2 3 [0x7B998233]
     528 [-]: CALL R2 1 1  
L64: 529 [-]: JUMPIF R2 L66
     530 [-]: GETUPVAL R3 37
     531 [-]: FASTCALL1 62 R3 L65
     532 [-]: GETIMPORT R2 3 [0x7B998233]
     533 [-]: CALL R2 1 1  
L65: 534 [-]: JUMPIF R2 L66
     535 [-]: GETUPVAL R2 8
     536 [-]: GETUPVAL R4 37
     537 [-]: NAMECALL R2 R2 K76 [0x9B2E6C87]
     538 [-]: CALL R2 2 1  
     539 [-]: LOADN R3 5   
     540 [-]: JUMPIFNOTLT R2 R3 L66
     541 [-]: GETUPVAL R2 3
     542 [-]: MOVE R4 R1   
     543 [-]: NAMECALL R2 R2 K5 [0x8ABFF40E]
     544 [-]: CALL R2 2 0  
L66: 545 [-]: GETIMPORT R1 65 [0x603636AD]
     546 [-]: GETUPVAL R3 32
     547 [-]: GETTABLEKS R2 R3 K66 ["optionalRescue"]
     548 [-]: DUPTABLE R3 69
     549 [-]: GETIMPORT R4 71 ["OstronHostageRescueCount"]
     550 [-]: SETTABLEKS R4 R3 K67 ["CURRENT_RESCUE_COUNT"]
     551 [-]: GETUPVAL R4 33
     552 [-]: SETTABLEKS R4 R3 K68 ["TOTAL_RESCUE_COUNT"]
     553 [-]: CALL R1 2 1  
     554 [-]: SETUPVAL R1 31
     555 [-]: GETUPVAL R2 34
     556 [-]: GETTABLEKS R1 R2 K72 [0x118E5C26]
     557 [-]: GETUPVAL R2 31
     558 [-]: CALL R1 1 0  
     559 [-]: JUMP L76
    
L67: 560 [-]: GETUPVAL R1 2
     561 [-]: GETUPVAL R3 4
     562 [-]: GETTABLEKS R2 R3 K78 ["POWER_TOWER_C"]
     563 [-]: JUMPIFNOTEQ R1 R2 L71
     564 [-]: GETUPVAL R2 4
     565 [-]: GETTABLEKS R1 R2 K10 ["TOWER_ROOF"]
     566 [-]: GETUPVAL R3 8
     567 [-]: FASTCALL1 62 R3 L68
     568 [-]: GETIMPORT R2 3 [0x7B998233]
     569 [-]: CALL R2 1 1  
L68: 570 [-]: JUMPIF R2 L70
     571 [-]: GETUPVAL R3 37
     572 [-]: FASTCALL1 62 R3 L69
     573 [-]: GETIMPORT R2 3 [0x7B998233]
     574 [-]: CALL R2 1 1  
L69: 575 [-]: JUMPIF R2 L70
     576 [-]: GETUPVAL R2 8
     577 [-]: GETUPVAL R4 37
     578 [-]: NAMECALL R2 R2 K76 [0x9B2E6C87]
     579 [-]: CALL R2 2 1  
     580 [-]: LOADN R3 5   
     581 [-]: JUMPIFNOTLT R2 R3 L70
     582 [-]: GETUPVAL R2 3
     583 [-]: MOVE R4 R1   
     584 [-]: NAMECALL R2 R2 K5 [0x8ABFF40E]
     585 [-]: CALL R2 2 0  
L70: 586 [-]: GETIMPORT R1 65 [0x603636AD]
     587 [-]: GETUPVAL R3 32
     588 [-]: GETTABLEKS R2 R3 K66 ["optionalRescue"]
     589 [-]: DUPTABLE R3 69
     590 [-]: GETIMPORT R4 71 ["OstronHostageRescueCount"]
     591 [-]: SETTABLEKS R4 R3 K67 ["CURRENT_RESCUE_COUNT"]
     592 [-]: GETUPVAL R4 33
     593 [-]: SETTABLEKS R4 R3 K68 ["TOTAL_RESCUE_COUNT"]
     594 [-]: CALL R1 2 1  
     595 [-]: SETUPVAL R1 31
     596 [-]: GETUPVAL R2 34
     597 [-]: GETTABLEKS R1 R2 K72 [0x118E5C26]
     598 [-]: GETUPVAL R2 31
     599 [-]: CALL R1 1 0  
     600 [-]: JUMP L76
    
L71: 601 [-]: GETUPVAL R1 2
     602 [-]: GETUPVAL R3 4
     603 [-]: GETTABLEKS R2 R3 K10 ["TOWER_ROOF"]
     604 [-]: JUMPIFNOTEQ R1 R2 L73
     605 [-]: GETUPVAL R2 34
     606 [-]: GETTABLEKS R1 R2 K79 [0x826F2CA6]
     607 [-]: CALL R1 0 1  
     608 [-]: LOADN R2 0   
     609 [-]: JUMPIFNOTLE R1 R2 L76
     610 [-]: GETUPVAL R1 38
     611 [-]: JUMPIF R1 L72
     612 [-]: LOADK R1 K80 [2.5]
     613 [-]: SETUPVAL R1 38
     614 [-]: JUMP L76
    
L72: 615 [-]: GETUPVAL R2 38
     616 [-]: SUB R1 R2 R0 
     617 [-]: SETUPVAL R1 38
     618 [-]: GETUPVAL R1 38
     619 [-]: LOADN R2 0   
     620 [-]: JUMPIFNOTLE R1 R2 L76
     621 [-]: GETIMPORT R1 81 ["_T"]
     622 [-]: LOADB R2 1   
     623 [-]: SETTABLEKS R2 R1 K82 ["MurexTimeout"]
     624 [-]: GETIMPORT R1 84 [0x3D106989]
     625 [-]: LOADK R2 K85 ["Murex left off timed out! Activate checkpoint!"]
     626 [-]: CALL R1 1 0  
     627 [-]: JUMP L76
    
L73: 628 [-]: GETUPVAL R1 2
     629 [-]: GETUPVAL R3 4
     630 [-]: GETTABLEKS R2 R3 K86 ["TIMESTOP"]
     631 [-]: JUMPIFNOTEQ R1 R2 L74
     632 [-]: JUMP L76
    
L74: 633 [-]: GETUPVAL R1 2
     634 [-]: GETUPVAL R3 4
     635 [-]: GETTABLEKS R2 R3 K87 ["COMPLETE"]
     636 [-]: JUMPIFNOTEQ R1 R2 L75
     637 [-]: JUMP L76
    
L75: 638 [-]: GETUPVAL R1 2
     639 [-]: GETUPVAL R3 4
     640 [-]: GETTABLEKS R2 R3 K4 ["RESPAWN"]
     641 [-]: JUMPIFNOTEQ R1 R2 L76
     642 [-]: LOADB R1 1   
     643 [-]: SETUPVAL R1 39
     644 [-]: GETUPVAL R1 3
     645 [-]: GETUPVAL R3 1
     646 [-]: NAMECALL R1 R1 K5 [0x8ABFF40E]
     647 [-]: CALL R1 2 0  
L76: 648 [-]: GETUPVAL R1 10
     649 [-]: MOVE R3 R0   
     650 [-]: NAMECALL R1 R1 K88 [0xFAA69527]
     651 [-]: CALL R1 2 0  
     652 [-]: RETURN R0 0  


; Name:            
; Defined at line: 2123
; #Upvalues:       8
; #Parameters:     0
; Is_vararg:       0
; Max Stack Size:  3

       0 [-]: GETUPVAL R1 1
       1 [-]: GETTABLEKS R0 R1 K0 [0xC9013731]
       2 [-]: GETUPVAL R1 2
       3 [-]: CALL R0 1 1  
       4 [-]: SETUPVAL R0 0
       5 [-]: GETUPVAL R1 4
       6 [-]: GETTABLEKS R0 R1 K1 [0xDE474187]
       7 [-]: CALL R0 0 1  
       8 [-]: SETUPVAL R0 3
       9 [-]: GETUPVAL R0 5
      10 [-]: CALL R0 0 0  
L 0:  11 [-]: GETIMPORT R0 3 [0xCBD666E1]
      12 [-]: LOADN R1 0   
      13 [-]: CALL R0 1 0  
L 1:  14 [-]: GETIMPORT R1 5 [0xBE190284]
      15 [-]: FASTCALL1 62 R1 L2
      16 [-]: GETIMPORT R0 7 [0x7B998233]
      17 [-]: CALL R0 1 1  
L 2:  18 [-]: JUMPIFNOT R0 L3
      19 [-]: GETIMPORT R0 3 [0xCBD666E1]
      20 [-]: LOADN R1 0   
      21 [-]: CALL R0 1 0  
      22 [-]: JUMPBACK L1  
L 3:  23 [-]: GETUPVAL R0 0
      24 [-]: GETUPVAL R2 6
      25 [-]: NAMECALL R0 R0 K8 [0x209398C2]
      26 [-]: CALL R0 2 1  
      27 [-]: SETUPVAL R0 6
      28 [-]: GETUPVAL R0 7
      29 [-]: GETIMPORT R1 10 [0x67652851]
      30 [-]: CALL R1 0 -1 
      31 [-]: CALL R0 -1 0 
      32 [-]: JUMPBACK L0  
      33 [-]: RETURN R0 0  


; Name:            
; Defined at line: 2140
; #Upvalues:       1
; #Parameters:     1
; Is_vararg:       0
; Max Stack Size:  6

L 0:   0 [-]: GETIMPORT R2 1 [0xBE190284]
       1 [-]: FASTCALL1 62 R2 L1
       2 [-]: GETIMPORT R1 3 [0x7B998233]
       3 [-]: CALL R1 1 1  
L 1:   4 [-]: JUMPIFNOT R1 L2
       5 [-]: GETIMPORT R1 5 [0xCBD666E1]
       6 [-]: LOADN R2 0   
       7 [-]: CALL R1 1 0  
       8 [-]: JUMPBACK L0  
L 2:   9 [-]: GETUPVAL R1 0
      10 [-]: CALL R1 0 1  
      11 [-]: JUMPIF R1 L3 
      12 [-]: RETURN R0 0  
L 3:  13 [-]: GETIMPORT R1 7 [0x0469F296]
      14 [-]: LOADK R2 K8 ["Beanstalks"]
      15 [-]: CALL R1 1 1  
      16 [-]: GETIMPORT R2 10 [0x89326C93]
      17 [-]: MOVE R4 R1   
      18 [-]: NAMECALL R2 R2 K11 [0x46A0EBF5]
      19 [-]: CALL R2 2 1  
      20 [-]: FASTCALL1 62 R2 L4
      21 [-]: MOVE R4 R2   
      22 [-]: GETIMPORT R3 3 [0x7B998233]
      23 [-]: CALL R3 1 1  
L 4:  24 [-]: JUMPIF R3 L5 
      25 [-]: LOADK R5 K12 ["Execute"]
      26 [-]: NAMECALL R3 R2 K13 [0x8EB2112D]
      27 [-]: CALL R3 2 0  
L 5:  28 [-]: RETURN R0 0  


; Name:            
; Defined at line: 2157
; #Upvalues:       2
; #Parameters:     1
; Is_vararg:       0
; Max Stack Size:  12

       0 [-]: LOADN R1 6   
       1 [-]: GETIMPORT R2 1 [0x89326C93]
       2 [-]: GETUPVAL R5 0
       3 [-]: GETTABLEN R4 R5 1
       4 [-]: NAMECALL R2 R2 K2 [0x46A0EBF5]
       5 [-]: CALL R2 2 1  
       6 [-]: FASTCALL1 62 R2 L0
       7 [-]: MOVE R5 R2   
       8 [-]: GETIMPORT R4 4 [0x7B998233]
       9 [-]: CALL R4 1 1  
L 0:  10 [-]: JUMPIF R4 L1 
      11 [-]: NAMECALL R3 R2 K5 [0x1E3535E5]
      12 [-]: CALL R3 1 1  
      13 [-]: JUMPIF R3 L2 
L 1:  14 [-]: LOADNIL R3   
L 2:  15 [-]: FASTCALL1 62 R3 L3
      16 [-]: MOVE R5 R3   
      17 [-]: GETIMPORT R4 4 [0x7B998233]
      18 [-]: CALL R4 1 1  
L 3:  19 [-]: JUMPIF R4 L6 
      20 [-]: LOADN R1 -1  
      21 [-]: GETIMPORT R4 8 ["ShowImpactMessage"]
      22 [-]: GETIMPORT R5 10 [0x603636AD]
      23 [-]: LOADK R6 K11 ["/Lotus/Language/NewWar/P3M2NarmerSaveHint"]
      24 [-]: NEWTABLE R7 0 0
      25 [-]: CALL R5 2 1  
      26 [-]: MOVE R6 R1   
      27 [-]: LOADB R7 1   
      28 [-]: LOADNIL R8   
      29 [-]: LOADB R9 0   
      30 [-]: LOADNIL R10  
      31 [-]: LOADN R11 3  
      32 [-]: CALL R4 7 0  
L 4:  33 [-]: GETUPVAL R4 1
      34 [-]: MOVE R5 R3   
      35 [-]: CALL R4 1 1  
      36 [-]: JUMPIF R4 L5 
      37 [-]: GETIMPORT R4 13 [0xCBD666E1]
      38 [-]: LOADN R5 0   
      39 [-]: CALL R4 1 0  
      40 [-]: JUMPBACK L4  
L 5:  41 [-]: GETIMPORT R4 15 ["HideImpactMessage"]
      42 [-]: CALL R4 0 0  
      43 [-]: RETURN R0 0  
L 6:  44 [-]: GETIMPORT R4 8 ["ShowImpactMessage"]
      45 [-]: GETIMPORT R5 10 [0x603636AD]
      46 [-]: LOADK R6 K11 ["/Lotus/Language/NewWar/P3M2NarmerSaveHint"]
      47 [-]: NEWTABLE R7 0 0
      48 [-]: CALL R5 2 1  
      49 [-]: MOVE R6 R1   
      50 [-]: LOADB R7 1   
      51 [-]: LOADNIL R8   
      52 [-]: LOADB R9 0   
      53 [-]: LOADNIL R10  
      54 [-]: LOADN R11 3  
      55 [-]: CALL R4 7 0  
      56 [-]: GETIMPORT R4 13 [0xCBD666E1]
      57 [-]: LOADN R5 10  
      58 [-]: CALL R4 1 0  
      59 [-]: GETIMPORT R4 15 ["HideImpactMessage"]
      60 [-]: CALL R4 0 0  
      61 [-]: RETURN R0 0  


; Name:            
; Defined at line: 2183
; #Upvalues:       0
; #Parameters:     0
; Is_vararg:       0
; Max Stack Size:  13

       0 [-]: GETIMPORT R0 1 [0x89326C93]
       1 [-]: NAMECALL R0 R0 K2 [0x29EF273D]
       2 [-]: CALL R0 1 1  
       3 [-]: NAMECALL R0 R0 K3 [0x66905CB0]
       4 [-]: CALL R0 1 1  
       5 [-]: LOADB R3 1   
       6 [-]: NAMECALL R1 R0 K4 [0xB8B90F91]
       7 [-]: CALL R1 2 0  
       8 [-]: LOADB R3 0   
       9 [-]: NAMECALL R1 R0 K5 [0x383D2E7D]
      10 [-]: CALL R1 2 0  
      11 [-]: GETIMPORT R1 1 [0x89326C93]
      12 [-]: NAMECALL R1 R1 K6 [0x21C948F8]
      13 [-]: CALL R1 1 1  
      14 [-]: FASTCALL1 62 R1 L0
      15 [-]: MOVE R3 R1   
      16 [-]: GETIMPORT R2 8 [0x7B998233]
      17 [-]: CALL R2 1 1  
L 0:  18 [-]: JUMPIF R2 L4 
      19 [-]: LENGTH R2 R1 
      20 [-]: LOADN R3 0   
      21 [-]: JUMPIFNOTLT R3 R2 L4
      22 [-]: GETIMPORT R2 10 [0xC8802016]
      23 [-]: MOVE R3 R1   
      24 [-]: CALL R2 1 3  
      25 [-]: FORGPREP_INEXT R2 L3
L 1:  26 [-]: FASTCALL1 62 R6 L2
      27 [-]: MOVE R8 R6   
      28 [-]: GETIMPORT R7 8 [0x7B998233]
      29 [-]: CALL R7 1 1  
L 2:  30 [-]: JUMPIF R7 L3 
      31 [-]: NAMECALL R7 R6 K11 [0x2047CFE7]
      32 [-]: CALL R7 1 1  
      33 [-]: JUMPIF R7 L3 
      34 [-]: NAMECALL R7 R6 K12 [0x808B79E6]
      35 [-]: CALL R7 1 1  
      36 [-]: GETIMPORT R8 14 [0x0469F296]
      37 [-]: LOADK R9 K15 ["TENNO"]
      38 [-]: CALL R8 1 1  
      39 [-]: JUMPIFEQ R7 R8 L3
      40 [-]: NAMECALL R7 R6 K16 [0x1AC1655C]
      41 [-]: CALL R7 1 1  
      42 [-]: GETIMPORT R9 14 [0x0469F296]
      43 [-]: LOADK R10 K17 ["UNUM_INVULNERABLE"]
      44 [-]: CALL R9 1 1  
      45 [-]: LOADN R10 25 
      46 [-]: LOADN R11 6  
      47 [-]: LOADN R12 0  
      48 [-]: NAMECALL R7 R7 K18 [0xA383DE31]
      49 [-]: CALL R7 5 0  
      50 [-]: GETIMPORT R9 20 [0xAB87DDFC]
      51 [-]: GETIMPORT R10 14 [0x0469F296]
      52 [-]: LOADK R11 K21 ["UnumTimeStopEffect"]
      53 [-]: CALL R10 1 -1
      54 [-]: NAMECALL R7 R6 K22 [0x47901F07]
      55 [-]: CALL R7 -1 0 
L 3:  56 [-]: FORGLOOP R2 L1 2 [inext]
L 4:  57 [-]: GETIMPORT R2 1 [0x89326C93]
      58 [-]: GETIMPORT R4 24 ["gProjectileType"]
      59 [-]: NAMECALL R2 R2 K25 [0xFB669000]
      60 [-]: CALL R2 2 1  
      61 [-]: FASTCALL1 62 R2 L5
      62 [-]: MOVE R4 R2   
      63 [-]: GETIMPORT R3 8 [0x7B998233]
      64 [-]: CALL R3 1 1  
L 5:  65 [-]: JUMPIF R3 L9 
      66 [-]: LENGTH R3 R2 
      67 [-]: LOADN R4 0   
      68 [-]: JUMPIFNOTLT R4 R3 L9
      69 [-]: LOADN R5 1   
      70 [-]: LENGTH R3 R2 
      71 [-]: LOADN R4 1   
      72 [-]: FORNPREP R3 L9
L 6:  73 [-]: GETTABLE R7 R2 R5
      74 [-]: FASTCALL1 62 R7 L7
      75 [-]: GETIMPORT R6 8 [0x7B998233]
      76 [-]: CALL R6 1 1  
L 7:  77 [-]: JUMPIF R6 L8 
      78 [-]: GETTABLE R6 R2 R5
      79 [-]: GETIMPORT R8 14 [0x0469F296]
      80 [-]: LOADK R9 K26 ["UnumTimeFreeze"]
      81 [-]: CALL R8 1 1  
      82 [-]: LOADN R9 0   
      83 [-]: NAMECALL R6 R6 K27 [0x9D668F53]
      84 [-]: CALL R6 3 0  
L 8:  85 [-]: FORNLOOP R3 L6
L 9:  86 [-]: RETURN R0 0  


; Name:            
; Defined at line: 2212
; #Upvalues:       0
; #Parameters:     0
; Is_vararg:       0
; Max Stack Size:  12

       0 [-]: GETIMPORT R0 1 [0x89326C93]
       1 [-]: NAMECALL R0 R0 K2 [0x29EF273D]
       2 [-]: CALL R0 1 1  
       3 [-]: NAMECALL R0 R0 K3 [0x66905CB0]
       4 [-]: CALL R0 1 1  
       5 [-]: LOADB R3 0   
       6 [-]: NAMECALL R1 R0 K4 [0xB8B90F91]
       7 [-]: CALL R1 2 0  
       8 [-]: LOADB R3 1   
       9 [-]: NAMECALL R1 R0 K5 [0x383D2E7D]
      10 [-]: CALL R1 2 0  
      11 [-]: GETIMPORT R1 1 [0x89326C93]
      12 [-]: NAMECALL R1 R1 K6 [0x21C948F8]
      13 [-]: CALL R1 1 1  
      14 [-]: LOADNIL R2   
      15 [-]: FASTCALL1 62 R1 L0
      16 [-]: MOVE R4 R1   
      17 [-]: GETIMPORT R3 8 [0x7B998233]
      18 [-]: CALL R3 1 1  
L 0:  19 [-]: JUMPIF R3 L5 
      20 [-]: LENGTH R3 R1 
      21 [-]: LOADN R4 0   
      22 [-]: JUMPIFNOTLT R4 R3 L5
      23 [-]: GETIMPORT R3 10 [0xC8802016]
      24 [-]: MOVE R4 R1   
      25 [-]: CALL R3 1 3  
      26 [-]: FORGPREP_INEXT R3 L4
L 1:  27 [-]: FASTCALL1 62 R7 L2
      28 [-]: MOVE R9 R7   
      29 [-]: GETIMPORT R8 8 [0x7B998233]
      30 [-]: CALL R8 1 1  
L 2:  31 [-]: JUMPIF R8 L4 
      32 [-]: NAMECALL R8 R7 K11 [0x2047CFE7]
      33 [-]: CALL R8 1 1  
      34 [-]: JUMPIF R8 L4 
      35 [-]: NAMECALL R8 R7 K12 [0x808B79E6]
      36 [-]: CALL R8 1 1  
      37 [-]: GETIMPORT R9 14 [0x0469F296]
      38 [-]: LOADK R10 K15 ["TENNO"]
      39 [-]: CALL R9 1 1  
      40 [-]: JUMPIFEQ R8 R9 L4
      41 [-]: NAMECALL R8 R7 K16 [0x1AC1655C]
      42 [-]: CALL R8 1 1  
      43 [-]: GETIMPORT R10 14 [0x0469F296]
      44 [-]: LOADK R11 K17 ["UNUM_INVULNERABLE"]
      45 [-]: CALL R10 1 -1
      46 [-]: NAMECALL R8 R8 K18 [0x8E3E343E]
      47 [-]: CALL R8 -1 0 
      48 [-]: GETIMPORT R10 20 [0xAB87DDFC]
      49 [-]: NAMECALL R8 R7 K21 [0xC9F6A7D7]
      50 [-]: CALL R8 2 1  
      51 [-]: MOVE R2 R8   
      52 [-]: FASTCALL1 62 R2 L3
      53 [-]: MOVE R9 R2   
      54 [-]: GETIMPORT R8 8 [0x7B998233]
      55 [-]: CALL R8 1 1  
L 3:  56 [-]: JUMPIF R8 L4 
      57 [-]: NAMECALL R8 R2 K22 [0xA2880940]
      58 [-]: CALL R8 1 0  
L 4:  59 [-]: FORGLOOP R3 L1 2 [inext]
L 5:  60 [-]: GETIMPORT R3 1 [0x89326C93]
      61 [-]: GETIMPORT R5 24 ["gProjectileType"]
      62 [-]: NAMECALL R3 R3 K25 [0xFB669000]
      63 [-]: CALL R3 2 1  
      64 [-]: FASTCALL1 62 R3 L6
      65 [-]: MOVE R5 R3   
      66 [-]: GETIMPORT R4 8 [0x7B998233]
      67 [-]: CALL R4 1 1  
L 6:  68 [-]: JUMPIF R4 L10
      69 [-]: LENGTH R4 R3 
      70 [-]: LOADN R5 0   
      71 [-]: JUMPIFNOTLT R5 R4 L10
      72 [-]: LOADN R6 1   
      73 [-]: LENGTH R4 R3 
      74 [-]: LOADN R5 1   
      75 [-]: FORNPREP R4 L10
L 7:  76 [-]: GETTABLE R8 R3 R6
      77 [-]: FASTCALL1 62 R8 L8
      78 [-]: GETIMPORT R7 8 [0x7B998233]
      79 [-]: CALL R7 1 1  
L 8:  80 [-]: JUMPIF R7 L9 
      81 [-]: GETTABLE R7 R3 R6
      82 [-]: GETIMPORT R9 14 [0x0469F296]
      83 [-]: LOADK R10 K26 ["UnumTimeFreeze"]
      84 [-]: CALL R9 1 -1 
      85 [-]: NAMECALL R7 R7 K27 [0xD8ECECCC]
      86 [-]: CALL R7 -1 0 
L 9:  87 [-]: FORNLOOP R4 L7
L10:  88 [-]: RETURN R0 0  


; Name:            
; Defined at line: 2243
; #Upvalues:       0
; #Parameters:     0
; Is_vararg:       0
; Max Stack Size:  8

       0 [-]: GETIMPORT R0 1 [0x89326C93]
       1 [-]: GETIMPORT R2 3 [0x19F74E67]
       2 [-]: NAMECALL R0 R0 K4 [0xC7FCADA9]
       3 [-]: CALL R0 2 1  
       4 [-]: FASTCALL1 62 R0 L0
       5 [-]: MOVE R2 R0   
       6 [-]: GETIMPORT R1 6 [0x7B998233]
       7 [-]: CALL R1 1 1  
L 0:   8 [-]: JUMPIF R1 L5 
       9 [-]: LENGTH R1 R0 
      10 [-]: LOADN R2 0   
      11 [-]: JUMPIFNOTLT R2 R1 L5
      12 [-]: LOADN R3 1   
      13 [-]: LENGTH R1 R0 
      14 [-]: LOADN R2 1   
      15 [-]: FORNPREP R1 L5
L 1:  16 [-]: GETTABLE R5 R0 R3
      17 [-]: FASTCALL1 62 R5 L2
      18 [-]: GETIMPORT R4 6 [0x7B998233]
      19 [-]: CALL R4 1 1  
L 2:  20 [-]: JUMPIF R4 L4 
      21 [-]: GETIMPORT R4 8 [0x6F48F09E]
      22 [-]: JUMPIFNOT R4 L3
      23 [-]: GETTABLE R4 R0 R3
      24 [-]: GETIMPORT R6 10 [0x0469F296]
      25 [-]: LOADK R7 K11 ["UnumTimeFreeze"]
      26 [-]: CALL R6 1 1  
      27 [-]: LOADN R7 0   
      28 [-]: NAMECALL R4 R4 K12 [0x9D668F53]
      29 [-]: CALL R4 3 0  
      30 [-]: JUMP L4
     
L 3:  31 [-]: GETTABLE R4 R0 R3
      32 [-]: GETIMPORT R6 10 [0x0469F296]
      33 [-]: LOADK R7 K11 ["UnumTimeFreeze"]
      34 [-]: CALL R6 1 -1 
      35 [-]: NAMECALL R4 R4 K13 [0xD8ECECCC]
      36 [-]: CALL R4 -1 0 
L 4:  37 [-]: FORNLOOP R1 L1
L 5:  38 [-]: RETURN R0 0  



