; Name:            
; Defined at line: 1
; #Upvalues:       0
; #Parameters:     0
; Is_vararg:       1
; Max Stack Size:  47

       1 [-]: GETIMPORT R0 1 [0x7ED0A956]
       2 [-]: LOADK R1 K2 ["/Lotus/Characters/Tenno/Lotus/LotusBody_skelDeco"]
       3 [-]: CALL R0 1 1  
       4 [-]: GETIMPORT R1 4 [0xB009BBC6]
       5 [-]: LOADK R2 K5 ["/Lotus/Interface/SaveSpinner.swf"]
       6 [-]: CALL R1 1 1  
       7 [-]: GETIMPORT R2 7 [0x2D0FAD09]
       8 [-]: LOADK R3 K8 ["Lotus.Scripts.Libs.CommonGamemodeFunctions"]
       9 [-]: CALL R2 1 1  
      10 [-]: GETIMPORT R3 7 [0x2D0FAD09]
      11 [-]: LOADK R4 K9 ["Lotus.Scripts.Libs.QuestLib"]
      12 [-]: CALL R3 1 1  
      13 [-]: GETIMPORT R4 7 [0x2D0FAD09]
      14 [-]: LOADK R5 K10 ["Lotus.Scripts.Libs.QuestMissionLib"]
      15 [-]: CALL R4 1 1  
      16 [-]: GETIMPORT R5 7 [0x2D0FAD09]
      17 [-]: LOADK R6 K11 ["Lotus.Scripts.Libs.TransmissionSet"]
      18 [-]: CALL R5 1 1  
      19 [-]: GETIMPORT R6 7 [0x2D0FAD09]
      20 [-]: LOADK R7 K12 ["Lotus.Powersuits.Operator.OperatorLib"]
      21 [-]: CALL R6 1 1  
      22 [-]: DUPTABLE R7 14
      23 [-]: GETIMPORT R8 16 [0x0469F296]
      24 [-]: LOADK R9 K17 ["NewWarEpiloguePlayerStart"]
      25 [-]: CALL R8 1 1  
      26 [-]: SETTABLEKS R8 R7 K13 ["levelStart"]
      27 [-]: DUPTABLE R8 30
      28 [-]: GETIMPORT R9 16 [0x0469F296]
      29 [-]: LOADK R10 K31 ["TNWEpilogueOperatorHowDoYouFeel"]
      30 [-]: CALL R9 1 1  
      31 [-]: SETTABLEKS R9 R8 K18 ["operatorFeel"]
      32 [-]: GETIMPORT R9 16 [0x0469F296]
      33 [-]: LOADK R10 K32 ["TNWEpilogueLotusWasNatah"]
      34 [-]: CALL R9 1 1  
      35 [-]: SETTABLEKS R9 R8 K19 ["lotusWasNatah"]
      36 [-]: GETIMPORT R9 16 [0x0469F296]
      37 [-]: LOADK R10 K33 ["DTNWPt3EpilogueHesGone"]
      38 [-]: CALL R9 1 1  
      39 [-]: SETTABLEKS R9 R8 K20 ["adultOperatorHesGone"]
      40 [-]: GETIMPORT R9 16 [0x0469F296]
      41 [-]: LOADK R10 K34 ["TNWEpilogueLotusThankYou"]
      42 [-]: CALL R9 1 1  
      43 [-]: SETTABLEKS R9 R8 K21 ["lotusThankYou"]
      44 [-]: GETIMPORT R9 16 [0x0469F296]
      45 [-]: LOADK R10 K35 ["DTNWPt3EpilogueWhatSee"]
      46 [-]: CALL R9 1 1  
      47 [-]: SETTABLEKS R9 R8 K22 ["adultOperatorWhatSee"]
      48 [-]: GETIMPORT R9 16 [0x0469F296]
      49 [-]: LOADK R10 K36 ["TNWEpilogueLotusSawNothing"]
      50 [-]: CALL R9 1 1  
      51 [-]: SETTABLEKS R9 R8 K23 ["lotusSawNothing"]
      52 [-]: GETIMPORT R9 16 [0x0469F296]
      53 [-]: LOADK R10 K37 ["TNWEpilogueOperatorWorkToDo"]
      54 [-]: CALL R9 1 1  
      55 [-]: SETTABLEKS R9 R8 K24 ["operatorWorkToDo"]
      56 [-]: GETIMPORT R9 16 [0x0469F296]
      57 [-]: LOADK R10 K38 ["TNWEpilogueLotusConvoVoices"]
      58 [-]: CALL R9 1 1  
      59 [-]: SETTABLEKS R9 R8 K25 ["lotusVoices"]
      60 [-]: GETIMPORT R9 16 [0x0469F296]
      61 [-]: LOADK R10 K39 ["TNWEpilogueOperatorChooseOne"]
      62 [-]: CALL R9 1 1  
      63 [-]: SETTABLEKS R9 R8 K26 ["operatorChooseOne"]
      64 [-]: GETIMPORT R9 16 [0x0469F296]
      65 [-]: LOADK R10 K40 ["TNWEpilogueLotusSun"]
      66 [-]: CALL R9 1 1  
      67 [-]: SETTABLEKS R9 R8 K27 ["lotusSunChoice"]
      68 [-]: GETIMPORT R9 16 [0x0469F296]
      69 [-]: LOADK R10 K41 ["TNWEpilogueLotusBalanced"]
      70 [-]: CALL R9 1 1  
      71 [-]: SETTABLEKS R9 R8 K28 ["lotusBalancedChoice"]
      72 [-]: GETIMPORT R9 16 [0x0469F296]
      73 [-]: LOADK R10 K42 ["TNWEpilogueLotusMoon"]
      74 [-]: CALL R9 1 1  
      75 [-]: SETTABLEKS R9 R8 K29 ["lotusMoonChoice"]
      76 [-]: LOADNIL R9   
      77 [-]: LOADNIL R10  
      78 [-]: LOADN R11 0  
      79 [-]: LOADNIL R12  
      80 [-]: LOADNIL R13  
      81 [-]: LOADNIL R14  
      82 [-]: LOADNIL R15  
      83 [-]: LOADNIL R16  
      84 [-]: LOADNIL R17  
      85 [-]: LOADNIL R18  
      86 [-]: LOADNIL R19  
      87 [-]: LOADNIL R20  
      88 [-]: LOADNIL R21  
      89 [-]: LOADNIL R22  
      90 [-]: LOADNIL R23  
      91 [-]: LOADB R24 0  
      92 [-]: LOADB R25 0  
      93 [-]: LOADNIL R26  
      94 [-]: DUPTABLE R27 46
      95 [-]: LOADN R28 1  
      96 [-]: SETTABLEKS R28 R27 K43 ["INTRO"]
      97 [-]: LOADN R28 2  
      98 [-]: SETTABLEKS R28 R27 K44 ["CONVERSATION"]
      99 [-]: LOADN R28 3  
     100 [-]: SETTABLEKS R28 R27 K45 ["COMPLETE"]
     101 [-]: NEWTABLE R28 4 0
     102 [-]: GETTABLEKS R29 R27 K43 ["INTRO"]
     103 [-]: DUPTABLE R30 49
     104 [-]: LOADK R31 K50 ["Intro"]
     105 [-]: SETTABLEKS R31 R30 K47 ["name"]
     106 [-]: GETTABLEKS R31 R7 K13 ["levelStart"]
     107 [-]: SETTABLEKS R31 R30 K48 ["respawnPt"]
     108 [-]: SETTABLE R30 R28 R29
     109 [-]: GETTABLEKS R29 R27 K44 ["CONVERSATION"]
     110 [-]: DUPTABLE R30 51
     111 [-]: LOADK R31 K52 ["Conversation"]
     112 [-]: SETTABLEKS R31 R30 K47 ["name"]
     113 [-]: SETTABLE R30 R28 R29
     114 [-]: GETTABLEKS R29 R27 K45 ["COMPLETE"]
     115 [-]: DUPTABLE R30 51
     116 [-]: LOADK R31 K53 ["Complete"]
     117 [-]: SETTABLEKS R31 R30 K47 ["name"]
     118 [-]: SETTABLE R30 R28 R29
     119 [-]: DUPCLOSURE R29 K54 []
     120 [-]: MOVE R0 R28  
     121 [-]: NEWCLOSURE R30 P1
     122 [-]: MOVE R1 R12  
     123 [-]: DUPCLOSURE R31 K55 []
     124 [-]: NEWCLOSURE R32 P3
     125 [-]: MOVE R1 R11  
     126 [-]: MOVE R1 R10  
     127 [-]: MOVE R0 R28  
     128 [-]: DUPCLOSURE R33 K56 []
     129 [-]: MOVE R0 R6   
     130 [-]: NEWCLOSURE R34 P5
     131 [-]: MOVE R1 R13  
     132 [-]: MOVE R1 R14  
     133 [-]: NEWCLOSURE R35 P6
     134 [-]: MOVE R1 R12  
     135 [-]: MOVE R1 R13  
     136 [-]: NEWCLOSURE R36 P7
     137 [-]: MOVE R1 R12  
     138 [-]: NEWCLOSURE R37 P8
     139 [-]: MOVE R1 R15  
     140 [-]: MOVE R1 R12  
     141 [-]: MOVE R1 R16  
     142 [-]: MOVE R0 R5   
     143 [-]: NEWCLOSURE R38 P9
     144 [-]: MOVE R1 R17  
     145 [-]: MOVE R1 R12  
     146 [-]: MOVE R0 R5   
     147 [-]: DUPCLOSURE R39 K57 []
     148 [-]: DUPCLOSURE R40 K58 []
     149 [-]: MOVE R0 R39  
     150 [-]: SETGLOBAL R40 K59 ["AlignmentListener"]
     151 [-]: NEWCLOSURE R40 P12
     152 [-]: MOVE R1 R25  
     153 [-]: MOVE R1 R26  
     154 [-]: NEWCLOSURE R41 P13
     155 [-]: MOVE R0 R1   
     156 [-]: MOVE R1 R25  
     157 [-]: MOVE R0 R40  
     158 [-]: NEWCLOSURE R42 P14
     159 [-]: MOVE R1 R22  
     160 [-]: MOVE R0 R3   
     161 [-]: MOVE R0 R4   
     162 [-]: MOVE R1 R24  
     163 [-]: MOVE R1 R13  
     164 [-]: MOVE R1 R12  
     165 [-]: MOVE R1 R18  
     166 [-]: MOVE R1 R16  
     167 [-]: MOVE R0 R35  
     168 [-]: MOVE R0 R37  
     169 [-]: MOVE R0 R8   
     170 [-]: MOVE R1 R17  
     171 [-]: MOVE R0 R5   
     172 [-]: MOVE R0 R41  
     173 [-]: NEWCLOSURE R43 P15
     174 [-]: MOVE R1 R9   
     175 [-]: MOVE R0 R7   
     176 [-]: MOVE R1 R19  
     177 [-]: MOVE R1 R20  
     178 [-]: MOVE R1 R21  
     179 [-]: MOVE R1 R15  
     180 [-]: MOVE R1 R16  
     181 [-]: MOVE R1 R17  
     182 [-]: MOVE R1 R18  
     183 [-]: MOVE R1 R23  
     184 [-]: MOVE R1 R22  
     185 [-]: MOVE R0 R0   
     186 [-]: MOVE R1 R13  
     187 [-]: MOVE R0 R33  
     188 [-]: MOVE R1 R14  
     189 [-]: MOVE R0 R34  
     190 [-]: MOVE R0 R30  
     191 [-]: MOVE R1 R12  
     192 [-]: MOVE R0 R4   
     193 [-]: MOVE R1 R10  
     194 [-]: MOVE R0 R27  
     195 [-]: NEWCLOSURE R44 P16
     196 [-]: MOVE R0 R30  
     197 [-]: MOVE R1 R11  
     198 [-]: MOVE R0 R27  
     199 [-]: MOVE R1 R23  
     200 [-]: MOVE R1 R10  
     201 [-]: MOVE R0 R28  
     202 [-]: MOVE R1 R24  
     203 [-]: MOVE R1 R25  
     204 [-]: MOVE R1 R26  
     205 [-]: MOVE R0 R40  
     206 [-]: NEWCLOSURE R45 P17
     207 [-]: MOVE R1 R11  
     208 [-]: MOVE R0 R27  
     209 [-]: MOVE R1 R23  
     210 [-]: MOVE R1 R12  
     211 [-]: MOVE R1 R22  
     212 [-]: MOVE R0 R42  
     213 [-]: MOVE R1 R18  
     214 [-]: MOVE R0 R4   
     215 [-]: NEWCLOSURE R46 P18
     216 [-]: MOVE R1 R10  
     217 [-]: MOVE R0 R2   
     218 [-]: MOVE R0 R45  
     219 [-]: MOVE R0 R43  
     220 [-]: MOVE R1 R11  
     221 [-]: MOVE R0 R27  
     222 [-]: MOVE R0 R44  
     223 [-]: MOVE R0 R4   
     224 [-]: SETGLOBAL R46 K60 ["Mission"]
     225 [-]: DUPCLOSURE R46 K61 []
     226 [-]: SETGLOBAL R46 K62 ["ToggleLotusEyeFlare"]
     227 [-]: NEWCLOSURE R46 P20
     228 [-]: MOVE R1 R14  
     229 [-]: MOVE R0 R33  
     230 [-]: MOVE R1 R13  
     231 [-]: SETGLOBAL R46 K63 ["DrifterHoodTest"]
     232 [-]: DUPCLOSURE R46 K64 []
     233 [-]: MOVE R0 R39  
     234 [-]: SETGLOBAL R46 K65 ["EndOfQuestDioLotus"]
     235 [-]: CLOSEUPVALS R9
     236 [-]: RETURN R0 0  


; Name:            
; Defined at line: 95
; #Upvalues:       1
; #Parameters:     1
; Is_vararg:       0
; Max Stack Size:  4

       0 [-]: GETUPVAL R3 0
       1 [-]: GETTABLE R2 R3 R0
       2 [-]: GETTABLEKS R1 R2 K0 ["name"]
       3 [-]: RETURN R1 1  


; Name:            
; Defined at line: 101
; #Upvalues:       1
; #Parameters:     1
; Is_vararg:       0
; Max Stack Size:  3

       0 [-]: JUMPIFNOT R0 L2
L 0:   1 [-]: GETUPVAL R2 0
       2 [-]: FASTCALL1 62 R2 L1
       3 [-]: GETIMPORT R1 1 [0x7B998233]
       4 [-]: CALL R1 1 1  
L 1:   5 [-]: JUMPIFNOT R1 L3
       6 [-]: GETIMPORT R1 3 [0x89326C93]
       7 [-]: NAMECALL R1 R1 K4 [0x78298275]
       8 [-]: CALL R1 1 1  
       9 [-]: SETUPVAL R1 0
      10 [-]: GETIMPORT R1 6 [0xCBD666E1]
      11 [-]: LOADN R2 0   
      12 [-]: CALL R1 1 0  
      13 [-]: JUMPBACK L0  
      14 [-]: RETURN R0 0  
L 2:  15 [-]: GETIMPORT R1 3 [0x89326C93]
      16 [-]: NAMECALL R1 R1 K4 [0x78298275]
      17 [-]: CALL R1 1 1  
      18 [-]: SETUPVAL R1 0
L 3:  19 [-]: RETURN R0 0  


; Name:            
; Defined at line: 115
; #Upvalues:       0
; #Parameters:     1
; Is_vararg:       0
; Max Stack Size:  2

       0 [-]: LOADN R1 0   
       1 [-]: ADDK R1 R0 K0 [1]
       2 [-]: RETURN R1 1  


; Name:            
; Defined at line: 121
; #Upvalues:       3
; #Parameters:     1
; Is_vararg:       0
; Max Stack Size:  8

       0 [-]: JUMPIF R0 L0 
       1 [-]: GETUPVAL R1 0
       2 [-]: LOADN R2 0   
       3 [-]: ADDK R2 R1 K0 [1]
       4 [-]: MOVE R0 R2   
L 0:   5 [-]: GETUPVAL R1 1
       6 [-]: MOVE R3 R0   
       7 [-]: NAMECALL R1 R1 K1 [0x8ABFF40E]
       8 [-]: CALL R1 2 0  
       9 [-]: GETIMPORT R1 3 [0xD644C2F1]
      10 [-]: LOADK R3 K4 ["Next state: "]
      11 [-]: MOVE R5 R0   
      12 [-]: GETUPVAL R7 2
      13 [-]: GETTABLE R6 R7 R5
      14 [-]: GETTABLEKS R4 R6 K5 ["name"]
      15 [-]: CONCAT R2 R3 R4
      16 [-]: CALL R1 1 0  
      17 [-]: RETURN R0 1  


; Name:            
; Defined at line: 132
; #Upvalues:       1
; #Parameters:     1
; Is_vararg:       0
; Max Stack Size:  11

       0 [-]: GETIMPORT R1 1 [0xD9AD00FD]
       1 [-]: GETIMPORT R2 3 [0x0469F296]
       2 [-]: LOADK R3 K4 ["childOperator"]
       3 [-]: CALL R2 1 1  
       4 [-]: GETIMPORT R3 3 [0x0469F296]
       5 [-]: LOADK R4 K5 [""]
       6 [-]: CALL R3 1 1  
       7 [-]: JUMPIFNOT R0 L0
       8 [-]: GETIMPORT R4 7 [0x3D106989]
       9 [-]: LOADK R5 K8 ["Creating Adult Operator"]
      10 [-]: CALL R4 1 0  
      11 [-]: GETIMPORT R1 10 [0x16343F1B]
      12 [-]: GETIMPORT R4 3 [0x0469F296]
      13 [-]: LOADK R5 K11 ["adultOperator"]
      14 [-]: CALL R4 1 1  
      15 [-]: MOVE R2 R4   
      16 [-]: GETIMPORT R4 3 [0x0469F296]
      17 [-]: LOADK R5 K12 ["AdultOperator"]
      18 [-]: CALL R4 1 1  
      19 [-]: MOVE R3 R4   
      20 [-]: JUMP L1
     
L 0:  21 [-]: GETIMPORT R4 7 [0x3D106989]
      22 [-]: LOADK R5 K13 ["Creating Child Operator"]
      23 [-]: CALL R4 1 0  
L 1:  24 [-]: GETIMPORT R4 15 [0x89326C93]
      25 [-]: GETIMPORT R6 3 [0x0469F296]
      26 [-]: LOADK R7 K16 ["avatarSpawnPoint"]
      27 [-]: CALL R6 1 -1 
      28 [-]: NAMECALL R4 R4 K17 [0x46A0EBF5]
      29 [-]: CALL R4 -1 1 
      30 [-]: GETIMPORT R5 15 [0x89326C93]
      31 [-]: MOVE R7 R1   
      32 [-]: NAMECALL R8 R4 K18 [0xD1586535]
      33 [-]: CALL R8 1 1  
      34 [-]: GETIMPORT R9 20 ["ZERO_ROTATION"]
      35 [-]: NAMECALL R5 R5 K21 [0x05909209]
      36 [-]: CALL R5 4 1  
      37 [-]: GETIMPORT R6 23 [0xCBD666E1]
      38 [-]: LOADN R7 0   
      39 [-]: CALL R6 1 0  
      40 [-]: GETUPVAL R7 0
      41 [-]: GETTABLEKS R6 R7 K24 [0x222E16F3]
      42 [-]: MOVE R7 R5   
      43 [-]: LOADNIL R8   
      44 [-]: LOADB R9 0   
      45 [-]: MOVE R10 R0  
      46 [-]: CALL R6 4 0  
      47 [-]: GETIMPORT R6 23 [0xCBD666E1]
      48 [-]: LOADN R7 0   
      49 [-]: CALL R6 1 0  
      50 [-]: GETUPVAL R7 0
      51 [-]: GETTABLEKS R6 R7 K25 [0x4A719CAE]
      52 [-]: MOVE R7 R5   
      53 [-]: LOADB R8 0   
      54 [-]: MOVE R9 R0   
      55 [-]: CALL R6 3 0  
      56 [-]: MOVE R8 R2   
      57 [-]: NAMECALL R6 R5 K26 [0x3273BA96]
      58 [-]: CALL R6 2 0  
      59 [-]: LOADB R8 0   
      60 [-]: LOADB R9 1   
      61 [-]: NAMECALL R6 R5 K27 [0x768274D6]
      62 [-]: CALL R6 3 0  
      63 [-]: MOVE R8 R3   
      64 [-]: NAMECALL R6 R5 K28 [0x26D544FC]
      65 [-]: CALL R6 2 0  
      66 [-]: RETURN R5 1  


; Name:            
; Defined at line: 160
; #Upvalues:       2
; #Parameters:     1
; Is_vararg:       0
; Max Stack Size:  11

       0 [-]: GETIMPORT R1 1 [0x89326C93]
       1 [-]: NAMECALL R1 R1 K2 [0xFB64E76C]
       2 [-]: CALL R1 1 1  
       3 [-]: GETIMPORT R2 1 [0x89326C93]
       4 [-]: NAMECALL R2 R2 K3 [0x78298275]
       5 [-]: CALL R2 1 1  
       6 [-]: NAMECALL R3 R2 K4 [0xD1586535]
       7 [-]: CALL R3 1 1  
       8 [-]: NAMECALL R4 R2 K5 [0xCB3851B8]
       9 [-]: CALL R4 1 1  
      10 [-]: GETUPVAL R5 0
      11 [-]: JUMPIFNOT R0 L0
      12 [-]: GETUPVAL R5 1
      13 [-]: GETIMPORT R6 7 [0x3D106989]
      14 [-]: LOADK R8 K8 ["Setting player avatar to adult operator. Avatar is "]
      15 [-]: NAMECALL R9 R5 K9 [0xED4E0128]
      16 [-]: CALL R9 1 1  
      17 [-]: CONCAT R7 R8 R9
      18 [-]: CALL R6 1 0  
      19 [-]: JUMP L1
     
L 0:  20 [-]: GETIMPORT R6 7 [0x3D106989]
      21 [-]: LOADK R8 K10 ["Setting player avatar to child operator. Avatar is "]
      22 [-]: NAMECALL R9 R5 K9 [0xED4E0128]
      23 [-]: CALL R9 1 1  
      24 [-]: CONCAT R7 R8 R9
      25 [-]: CALL R6 1 0  
L 1:  26 [-]: MOVE R8 R3   
      27 [-]: MOVE R9 R4   
      28 [-]: NAMECALL R6 R5 K11 [0x589EF1C1]
      29 [-]: CALL R6 3 0  
      30 [-]: LOADB R8 1   
      31 [-]: LOADB R9 1   
      32 [-]: NAMECALL R6 R5 K12 [0x768274D6]
      33 [-]: CALL R6 3 0  
      34 [-]: MOVE R8 R5   
      35 [-]: LOADB R9 0   
      36 [-]: LOADB R10 1  
      37 [-]: NAMECALL R6 R1 K13 [0x480B3AAE]
      38 [-]: CALL R6 4 0  
      39 [-]: LOADB R8 0   
      40 [-]: LOADB R9 1   
      41 [-]: NAMECALL R6 R2 K12 [0x768274D6]
      42 [-]: CALL R6 3 0  
      43 [-]: RETURN R0 0  


; Name:            
; Defined at line: 180
; #Upvalues:       2
; #Parameters:     1
; Is_vararg:       0
; Max Stack Size:  6

       0 [-]: GETIMPORT R1 1 [0x89326C93]
       1 [-]: NAMECALL R1 R1 K2 [0x78298275]
       2 [-]: CALL R1 1 1  
       3 [-]: SETUPVAL R1 0
       4 [-]: GETUPVAL R1 0
       5 [-]: MOVE R3 R0   
       6 [-]: LOADB R4 1   
       7 [-]: NAMECALL R1 R1 K3 [0x768274D6]
       8 [-]: CALL R1 3 0  
       9 [-]: GETUPVAL R1 1
      10 [-]: NOT R3 R0    
      11 [-]: LOADB R4 1   
      12 [-]: NAMECALL R1 R1 K3 [0x768274D6]
      13 [-]: CALL R1 3 0  
      14 [-]: JUMPIF R0 L0 
      15 [-]: GETIMPORT R1 5 [0x3D106989]
      16 [-]: LOADK R3 K6 ["Fake swapping to child. unhiding avatar "]
      17 [-]: GETUPVAL R4 1
      18 [-]: NAMECALL R4 R4 K7 [0xED4E0128]
      19 [-]: CALL R4 1 1  
      20 [-]: CONCAT R2 R3 R4
      21 [-]: CALL R1 1 0  
      22 [-]: GETUPVAL R1 1
      23 [-]: GETIMPORT R3 9 [0x4B7B290C]
      24 [-]: GETIMPORT R4 11 [0x0469F296]
      25 [-]: LOADK R5 K12 ["GAME_R1_ARM3"]
      26 [-]: CALL R4 1 -1 
      27 [-]: NAMECALL R1 R1 K13 [0x47901F07]
      28 [-]: CALL R1 -1 0 
      29 [-]: RETURN R0 0  
L 0:  30 [-]: GETIMPORT R1 5 [0x3D106989]
      31 [-]: LOADK R2 K14 ["Fake swapping to adult. Hiding child avatar."]
      32 [-]: CALL R1 1 0  
      33 [-]: GETUPVAL R1 0
      34 [-]: GETIMPORT R3 9 [0x4B7B290C]
      35 [-]: GETIMPORT R4 11 [0x0469F296]
      36 [-]: LOADK R5 K12 ["GAME_R1_ARM3"]
      37 [-]: CALL R4 1 -1 
      38 [-]: NAMECALL R1 R1 K13 [0x47901F07]
      39 [-]: CALL R1 -1 0 
      40 [-]: RETURN R0 0  


; Name:            
; Defined at line: 195
; #Upvalues:       1
; #Parameters:     1
; Is_vararg:       0
; Max Stack Size:  5

       0 [-]: GETUPVAL R1 0
       1 [-]: NAMECALL R1 R1 K0 [0x0B4BCFB6]
       2 [-]: CALL R1 1 1  
       3 [-]: MOVE R3 R0   
       4 [-]: LOADK R4 K1 [0.001]
       5 [-]: NAMECALL R1 R1 K2 [0x14C7F7DD]
       6 [-]: CALL R1 3 0  
       7 [-]: RETURN R0 0  


; Name:            
; Defined at line: 199
; #Upvalues:       4
; #Parameters:     2
; Is_vararg:       0
; Max Stack Size:  8

       0 [-]: LOADN R2 3   
       1 [-]: JUMPIFNOT R1 L0
       2 [-]: LOADN R2 4   
       3 [-]: GETUPVAL R3 0
       4 [-]: GETUPVAL R4 1
       5 [-]: NAMECALL R4 R4 K0 [0x0B4BCFB6]
       6 [-]: CALL R4 1 1  
       7 [-]: MOVE R6 R3   
       8 [-]: LOADK R7 K1 [0.001]
       9 [-]: NAMECALL R4 R4 K2 [0x14C7F7DD]
      10 [-]: CALL R4 3 0  
      11 [-]: JUMP L1
     
L 0:  12 [-]: GETUPVAL R3 2
      13 [-]: GETUPVAL R4 1
      14 [-]: NAMECALL R4 R4 K0 [0x0B4BCFB6]
      15 [-]: CALL R4 1 1  
      16 [-]: MOVE R6 R3   
      17 [-]: LOADK R7 K1 [0.001]
      18 [-]: NAMECALL R4 R4 K2 [0x14C7F7DD]
      19 [-]: CALL R4 3 0  
L 1:  20 [-]: GETIMPORT R3 4 [0xCBD666E1]
      21 [-]: LOADK R4 K5 [0.5]
      22 [-]: CALL R3 1 0  
      23 [-]: GETUPVAL R4 3
      24 [-]: GETTABLEKS R3 R4 K6 [0x11DCFE97]
      25 [-]: MOVE R4 R0   
      26 [-]: LOADB R5 0   
      27 [-]: LOADB R6 0   
      28 [-]: MOVE R7 R2   
      29 [-]: CALL R3 4 0  
      30 [-]: GETUPVAL R4 3
      31 [-]: GETTABLEKS R3 R4 K7 [0xFC87A231]
      32 [-]: CALL R3 0 0  
      33 [-]: RETURN R0 0  


; Name:            
; Defined at line: 215
; #Upvalues:       3
; #Parameters:     2
; Is_vararg:       0
; Max Stack Size:  8

       0 [-]: GETUPVAL R2 0
       1 [-]: GETUPVAL R3 1
       2 [-]: NAMECALL R3 R3 K0 [0x0B4BCFB6]
       3 [-]: CALL R3 1 1  
       4 [-]: MOVE R5 R2   
       5 [-]: LOADK R6 K1 [0.001]
       6 [-]: NAMECALL R3 R3 K2 [0x14C7F7DD]
       7 [-]: CALL R3 3 0  
       8 [-]: GETIMPORT R2 4 [0xCBD666E1]
       9 [-]: LOADK R3 K5 [0.5]
      10 [-]: CALL R2 1 0  
      11 [-]: GETGLOBAL R4 K6 [0xE91D7466]
      12 [-]: MOVE R6 R0   
      13 [-]: NAMECALL R4 R4 K7 [0x10C9EEF2]
      14 [-]: CALL R4 2 1  
      15 [-]: LOADNIL R5   
      16 [-]: LOADB R6 0   
      17 [-]: LOADB R7 1   
      18 [-]: NAMECALL R2 R1 K8 [0x68D7CBE0]
      19 [-]: CALL R2 5 0  
      20 [-]: GETUPVAL R3 2
      21 [-]: GETTABLEKS R2 R3 K9 [0xFC87A231]
      22 [-]: CALL R2 0 0  
      23 [-]: RETURN R0 0  


; Name:            
; Defined at line: 222
; #Upvalues:       0
; #Parameters:     2
; Is_vararg:       0
; Max Stack Size:  12

       0 [-]: NAMECALL R2 R0 K0 [0xADBDC520]
       1 [-]: CALL R2 1 1  
       2 [-]: GETIMPORT R5 2 ["gEntityType"]
       3 [-]: NAMECALL R3 R0 K3 [0xC1595BD5]
       4 [-]: CALL R3 2 1  
       5 [-]: LOADN R6 1   
       6 [-]: LENGTH R4 R3 
       7 [-]: LOADN R5 1   
       8 [-]: FORNPREP R4 L2
L 0:   9 [-]: GETTABLE R7 R3 R6
      10 [-]: GETIMPORT R9 5 ["gLotusHubNpcEntityType"]
      11 [-]: NAMECALL R7 R7 K6 [0xF2DEAF69]
      12 [-]: CALL R7 2 1  
      13 [-]: JUMPIF R7 L1 
      14 [-]: GETTABLE R7 R3 R6
      15 [-]: JUMPIFEQ R7 R0 L1
      16 [-]: GETIMPORT R7 8 [0x3D106989]
      17 [-]: LOADK R9 K9 ["Destroying: "]
      18 [-]: GETTABLE R10 R3 R6
      19 [-]: NAMECALL R10 R10 K10 [0xED4E0128]
      20 [-]: CALL R10 1 1 
      21 [-]: CONCAT R8 R9 R10
      22 [-]: CALL R7 1 0  
      23 [-]: GETTABLE R9 R3 R6
      24 [-]: NAMECALL R7 R2 K11 [0x59C96E77]
      25 [-]: CALL R7 2 0  
L 1:  26 [-]: FORNLOOP R4 L0
L 2:  27 [-]: GETIMPORT R6 13 [0x9122BBF3]
      28 [-]: MOVE R7 R0   
      29 [-]: NAMECALL R4 R2 K14 [0x765DAD71]
      30 [-]: CALL R4 3 1  
      31 [-]: MOVE R7 R0   
      32 [-]: NAMECALL R5 R4 K15 [0xD70B80BC]
      33 [-]: CALL R5 2 0  
      34 [-]: GETIMPORT R5 18 [0xAED8235F]
      35 [-]: CALL R5 0 1  
      36 [-]: GETTABLEKS R6 R5 K19 ["mCustomization"]
      37 [-]: MOVE R8 R1   
      38 [-]: LOADN R9 7   
      39 [-]: NAMECALL R6 R6 K20 [0xEDD0B8C3]
      40 [-]: CALL R6 3 0  
      41 [-]: GETTABLEKS R8 R5 K19 ["mCustomization"]
      42 [-]: NAMECALL R6 R4 K21 [0xAA041663]
      43 [-]: CALL R6 2 0  
      44 [-]: GETTABLEKS R8 R5 K19 ["mCustomization"]
      45 [-]: NAMECALL R6 R4 K22 [0xDEFFCEC7]
      46 [-]: CALL R6 2 0  
      47 [-]: NAMECALL R6 R4 K23 [0x8F8353C4]
      48 [-]: CALL R6 1 0  
      49 [-]: GETIMPORT R8 25 [0x4B7B290C]
      50 [-]: GETIMPORT R9 27 [0x0469F296]
      51 [-]: LOADK R10 K28 ["GAME_R1_ARM3"]
      52 [-]: CALL R9 1 -1 
      53 [-]: NAMECALL R6 R0 K29 [0x47901F07]
      54 [-]: CALL R6 -1 0 
      55 [-]: RETURN R0 0  


; Name:            
; Defined at line: 246
; #Upvalues:       1
; #Parameters:     1
; Is_vararg:       0
; Max Stack Size:  5

       0 [-]: LOADN R1 0   
L 0:   1 [-]: FASTCALL1 62 R0 L1
       2 [-]: MOVE R3 R0   
       3 [-]: GETIMPORT R2 1 [0x7B998233]
       4 [-]: CALL R2 1 1  
L 1:   5 [-]: JUMPIF R2 L6 
       6 [-]: GETIMPORT R3 4 ["FocusedAlignmentChoice"]
       7 [-]: FASTCALL1 62 R3 L2
       8 [-]: GETIMPORT R2 1 [0x7B998233]
       9 [-]: CALL R2 1 1  
L 2:  10 [-]: JUMPIF R2 L5 
      11 [-]: GETIMPORT R2 4 ["FocusedAlignmentChoice"]
      12 [-]: JUMPIFEQ R1 R2 L5
      13 [-]: GETIMPORT R1 4 ["FocusedAlignmentChoice"]
      14 [-]: JUMPXEQKN R1 K5 L3 NOT [-1]
      15 [-]: GETUPVAL R2 0
      16 [-]: MOVE R3 R0   
      17 [-]: GETIMPORT R4 7 [0x46A55AD4]
      18 [-]: CALL R2 2 0  
      19 [-]: JUMP L5
     
L 3:  20 [-]: JUMPXEQKN R1 K8 L4 NOT [0]
      21 [-]: GETUPVAL R2 0
      22 [-]: MOVE R3 R0   
      23 [-]: GETIMPORT R4 10 [0xC1D75409]
      24 [-]: CALL R2 2 0  
      25 [-]: JUMP L5
     
L 4:  26 [-]: GETUPVAL R2 0
      27 [-]: MOVE R3 R0   
      28 [-]: GETIMPORT R4 12 [0xE9D518EA]
      29 [-]: CALL R2 2 0  
L 5:  30 [-]: GETIMPORT R2 14 [0xCBD666E1]
      31 [-]: LOADN R3 0   
      32 [-]: CALL R2 1 0  
      33 [-]: JUMPBACK L0  
L 6:  34 [-]: RETURN R0 0  


; Name:            
; Defined at line: 265
; #Upvalues:       2
; #Parameters:     2
; Is_vararg:       0
; Max Stack Size:  7

       0 [-]: JUMPIFNOT R0 L1
       1 [-]: LOADB R2 0   
       2 [-]: SETUPVAL R2 0
       3 [-]: GETIMPORT R3 2 ["LotusLoadoutSaveSpinner"]
       4 [-]: FASTCALL1 62 R3 L0
       5 [-]: GETIMPORT R2 4 [0x7B998233]
       6 [-]: CALL R2 1 1  
L 0:   7 [-]: JUMPIF R2 L2 
       8 [-]: GETIMPORT R2 2 ["LotusLoadoutSaveSpinner"]
       9 [-]: LOADK R4 K5 ["Finished"]
      10 [-]: LOADK R5 K6 [""]
      11 [-]: NAMECALL R2 R2 K7 [0xE4162EED]
      12 [-]: CALL R2 3 0  
      13 [-]: RETURN R0 0  
L 1:  14 [-]: LOADN R2 5   
      15 [-]: SETUPVAL R2 1
      16 [-]: GETIMPORT R2 9 [0x3D106989]
      17 [-]: LOADK R4 K10 ["SaveLoadOut failed: "]
      18 [-]: MOVE R5 R1   
      19 [-]: CONCAT R3 R4 R5
      20 [-]: CALL R2 1 0  
      21 [-]: GETIMPORT R2 9 [0x3D106989]
      22 [-]: LOADK R4 K11 ["Retrying in "]
      23 [-]: GETUPVAL R5 1
      24 [-]: LOADK R6 K12 ["..."]
      25 [-]: CONCAT R3 R4 R6
      26 [-]: CALL R2 1 0  
L 2:  27 [-]: RETURN R0 0  


; Name:            
; Defined at line: 278
; #Upvalues:       3
; #Parameters:     0
; Is_vararg:       0
; Max Stack Size:  4

       0 [-]: GETIMPORT R1 2 ["LotusLoadoutSaveSpinner"]
       1 [-]: FASTCALL1 62 R1 L0
       2 [-]: GETIMPORT R0 4 [0x7B998233]
       3 [-]: CALL R0 1 1  
L 0:   4 [-]: JUMPIFNOT R0 L1
       5 [-]: GETIMPORT R0 5 ["_T"]
       6 [-]: GETIMPORT R1 7 [0x9BA7909F]
       7 [-]: GETUPVAL R3 0
       8 [-]: NAMECALL R1 R1 K8 [0x6DD7AA66]
       9 [-]: CALL R1 2 1  
      10 [-]: SETTABLEKS R1 R0 K1 ["LotusLoadoutSaveSpinner"]
      11 [-]: GETIMPORT R0 2 ["LotusLoadoutSaveSpinner"]
      12 [-]: LOADK R2 K9 ["SetMessage"]
      13 [-]: LOADK R3 K10 ["/Menu/CheckPoint"]
      14 [-]: NAMECALL R0 R0 K11 [0xE4162EED]
      15 [-]: CALL R0 3 0  
      16 [-]: GETIMPORT R0 2 ["LotusLoadoutSaveSpinner"]
      17 [-]: LOADB R2 0   
      18 [-]: NAMECALL R0 R0 K12 [0x85B5D288]
      19 [-]: CALL R0 2 0  
L 1:  20 [-]: LOADB R0 1   
      21 [-]: SETUPVAL R0 1
      22 [-]: GETIMPORT R0 14 [0x25D99D89]
      23 [-]: GETUPVAL R2 2
      24 [-]: NAMECALL R0 R0 K15 [0xB6E2AB0D]
      25 [-]: CALL R0 2 0  
      26 [-]: RETURN R0 0  


; Name:            
; Defined at line: 288
; #Upvalues:       14
; #Parameters:     0
; Is_vararg:       0
; Max Stack Size:  6

       0 [-]: GETUPVAL R1 0
       1 [-]: FASTCALL1 62 R1 L0
       2 [-]: GETIMPORT R0 1 [0x7B998233]
       3 [-]: CALL R0 1 1  
L 0:   4 [-]: JUMPIF R0 L4 
       5 [-]: GETUPVAL R1 1
       6 [-]: GETTABLEKS R0 R1 K2 [0xD3D59A3B]
       7 [-]: GETIMPORT R1 4 [0x7ED0A956]
       8 [-]: LOADK R2 K5 ["/Lotus/Types/Keys/NewWarQuest/NewWarQuestKeyChain"]
       9 [-]: CALL R1 1 -1 
      10 [-]: CALL R0 -1 1 
      11 [-]: LOADNIL R1   
      12 [-]: GETIMPORT R3 7 [0x25D99D89]
      13 [-]: FASTCALL1 62 R3 L1
      14 [-]: GETIMPORT R2 1 [0x7B998233]
      15 [-]: CALL R2 1 1  
L 1:  16 [-]: JUMPIF R2 L2 
      17 [-]: GETIMPORT R2 7 [0x25D99D89]
      18 [-]: NAMECALL R2 R2 K8 [0x25A6E75E]
      19 [-]: CALL R2 1 1  
      20 [-]: MOVE R1 R2   
L 2:  21 [-]: DUPTABLE R2 11
      22 [-]: DUPCLOSURE R3 K12 []
      23 [-]: SETTABLEKS R3 R2 K9 ["mCondition"]
      24 [-]: NEWCLOSURE R3 P1
      25 [-]: MOVE R2 R2   
      26 [-]: MOVE R2 R3   
      27 [-]: SETTABLEKS R3 R2 K10 ["mCallback"]
      28 [-]: GETIMPORT R3 14 ["_T"]
      29 [-]: GETIMPORT R4 16 ["TaggedDialog"]
      30 [-]: JUMPIF R4 L3 
      31 [-]: NEWTABLE R4 0 0
L 3:  32 [-]: SETTABLEKS R4 R3 K15 ["TaggedDialog"]
      33 [-]: GETIMPORT R3 16 ["TaggedDialog"]
      34 [-]: DUPTABLE R4 11
      35 [-]: DUPCLOSURE R5 K17 []
      36 [-]: SETTABLEKS R5 R4 K9 ["mCondition"]
      37 [-]: NEWCLOSURE R5 P3
      38 [-]: MOVE R2 R4   
      39 [-]: MOVE R2 R5   
      40 [-]: MOVE R2 R6   
      41 [-]: MOVE R2 R7   
      42 [-]: MOVE R2 R8   
      43 [-]: MOVE R2 R9   
      44 [-]: MOVE R2 R10  
      45 [-]: MOVE R2 R11  
      46 [-]: MOVE R2 R12  
      47 [-]: MOVE R0 R0   
      48 [-]: MOVE R1 R1   
      49 [-]: MOVE R2 R13  
      50 [-]: MOVE R0 R2   
      51 [-]: SETTABLEKS R5 R4 K10 ["mCallback"]
      52 [-]: SETTABLEKS R4 R3 K18 ["Lotus_StartConversation"]
      53 [-]: CLOSEUPVALS R1
L 4:  54 [-]: RETURN R0 0  


; Name:            
; Defined at line: 459
; #Upvalues:       21
; #Parameters:     1
; Is_vararg:       0
; Max Stack Size:  12

       0 [-]: GETIMPORT R1 1 [0x3D106989]
       1 [-]: LOADK R2 K2 ["Starting New War Epilogue mission"]
       2 [-]: CALL R1 1 0  
       3 [-]: GETIMPORT R1 4 [0x89326C93]
       4 [-]: NAMECALL R1 R1 K5 [0x29EF273D]
       5 [-]: CALL R1 1 1  
       6 [-]: NAMECALL R1 R1 K6 [0x66905CB0]
       7 [-]: CALL R1 1 1  
       8 [-]: SETUPVAL R1 0
       9 [-]: GETIMPORT R1 4 [0x89326C93]
      10 [-]: GETUPVAL R4 1
      11 [-]: GETTABLEKS R3 R4 K7 ["levelStart"]
      12 [-]: NAMECALL R1 R1 K8 [0x46A0EBF5]
      13 [-]: CALL R1 2 1  
L 0:  14 [-]: FASTCALL1 62 R1 L1
      15 [-]: MOVE R3 R1   
      16 [-]: GETIMPORT R2 10 [0x7B998233]
      17 [-]: CALL R2 1 1  
L 1:  18 [-]: JUMPIFNOT R2 L2
      19 [-]: GETIMPORT R2 12 [0xCBD666E1]
      20 [-]: LOADN R3 0   
      21 [-]: CALL R2 1 0  
      22 [-]: GETIMPORT R2 4 [0x89326C93]
      23 [-]: GETUPVAL R5 1
      24 [-]: GETTABLEKS R4 R5 K7 ["levelStart"]
      25 [-]: NAMECALL R2 R2 K8 [0x46A0EBF5]
      26 [-]: CALL R2 2 1  
      27 [-]: MOVE R1 R2   
      28 [-]: JUMPBACK L0  
L 2:  29 [-]: GETIMPORT R2 4 [0x89326C93]
      30 [-]: GETIMPORT R4 14 [0x0469F296]
      31 [-]: LOADK R5 K15 ["Throne"]
      32 [-]: CALL R4 1 -1 
      33 [-]: NAMECALL R2 R2 K8 [0x46A0EBF5]
      34 [-]: CALL R2 -1 1 
      35 [-]: SETUPVAL R2 2
      36 [-]: GETUPVAL R2 2
      37 [-]: NAMECALL R2 R2 K16 [0xD1586535]
      38 [-]: CALL R2 1 1  
      39 [-]: SETUPVAL R2 3
      40 [-]: GETUPVAL R2 2
      41 [-]: NAMECALL R2 R2 K17 [0xCB3851B8]
      42 [-]: CALL R2 1 1  
      43 [-]: SETUPVAL R2 4
      44 [-]: GETIMPORT R2 4 [0x89326C93]
      45 [-]: GETIMPORT R4 14 [0x0469F296]
      46 [-]: LOADK R5 K18 ["OperatorCamera"]
      47 [-]: CALL R4 1 -1 
      48 [-]: NAMECALL R2 R2 K8 [0x46A0EBF5]
      49 [-]: CALL R2 -1 1 
      50 [-]: SETUPVAL R2 5
      51 [-]: GETIMPORT R2 4 [0x89326C93]
      52 [-]: GETIMPORT R4 14 [0x0469F296]
      53 [-]: LOADK R5 K19 ["ChildOperatorCamera"]
      54 [-]: CALL R4 1 -1 
      55 [-]: NAMECALL R2 R2 K8 [0x46A0EBF5]
      56 [-]: CALL R2 -1 1 
      57 [-]: SETUPVAL R2 6
      58 [-]: GETIMPORT R2 4 [0x89326C93]
      59 [-]: GETIMPORT R4 14 [0x0469F296]
      60 [-]: LOADK R5 K20 ["LotusCamera"]
      61 [-]: CALL R4 1 -1 
      62 [-]: NAMECALL R2 R2 K8 [0x46A0EBF5]
      63 [-]: CALL R2 -1 1 
      64 [-]: SETUPVAL R2 7
      65 [-]: GETIMPORT R2 4 [0x89326C93]
      66 [-]: GETIMPORT R4 14 [0x0469F296]
      67 [-]: LOADK R5 K21 ["LotusTalkTrigger"]
      68 [-]: CALL R4 1 -1 
      69 [-]: NAMECALL R2 R2 K8 [0x46A0EBF5]
      70 [-]: CALL R2 -1 1 
      71 [-]: SETUPVAL R2 8
      72 [-]: GETIMPORT R2 4 [0x89326C93]
      73 [-]: GETIMPORT R4 14 [0x0469F296]
      74 [-]: LOADK R5 K22 ["EpilogueCinematic"]
      75 [-]: CALL R4 1 -1 
      76 [-]: NAMECALL R2 R2 K8 [0x46A0EBF5]
      77 [-]: CALL R2 -1 1 
      78 [-]: SETUPVAL R2 9
      79 [-]: GETIMPORT R2 4 [0x89326C93]
      80 [-]: GETIMPORT R4 14 [0x0469F296]
      81 [-]: LOADK R5 K23 ["SittingLotus"]
      82 [-]: CALL R4 1 -1 
      83 [-]: NAMECALL R2 R2 K8 [0x46A0EBF5]
      84 [-]: CALL R2 -1 1 
      85 [-]: SETUPVAL R2 10
      86 [-]: GETUPVAL R2 10
      87 [-]: GETIMPORT R4 14 [0x0469F296]
      88 [-]: LOADK R5 K24 ["AlignmentListener"]
      89 [-]: CALL R4 1 1  
      90 [-]: LOADB R5 0   
      91 [-]: NAMECALL R2 R2 K25 [0xD5F7912B]
      92 [-]: CALL R2 3 0  
      93 [-]: GETIMPORT R2 4 [0x89326C93]
      94 [-]: GETIMPORT R4 27 ["gLotusOperatorAvatarType"]
      95 [-]: NAMECALL R2 R2 K28 [0xFB669000]
      96 [-]: CALL R2 2 1  
      97 [-]: GETIMPORT R3 30 [0xC8802016]
      98 [-]: MOVE R4 R2   
      99 [-]: CALL R3 1 3  
     100 [-]: FORGPREP_INEXT R3 L4
L 3: 101 [-]: LOADB R10 0  
     102 [-]: LOADB R11 1  
     103 [-]: NAMECALL R8 R7 K31 [0x768274D6]
     104 [-]: CALL R8 3 0  
     105 [-]: GETIMPORT R10 33 ["EMPTY_SYMBOL"]
     106 [-]: NAMECALL R8 R7 K34 [0x26D544FC]
     107 [-]: CALL R8 2 0  
     108 [-]: GETIMPORT R10 33 ["EMPTY_SYMBOL"]
     109 [-]: NAMECALL R8 R7 K35 [0x3273BA96]
     110 [-]: CALL R8 2 0  
L 4: 111 [-]: FORGLOOP R3 L3 2 [inext]
     112 [-]: GETIMPORT R3 4 [0x89326C93]
     113 [-]: GETUPVAL R5 11
     114 [-]: NAMECALL R3 R3 K28 [0xFB669000]
     115 [-]: CALL R3 2 1  
     116 [-]: GETIMPORT R4 30 [0xC8802016]
     117 [-]: MOVE R5 R3   
     118 [-]: CALL R4 1 3  
     119 [-]: FORGPREP_INEXT R4 L6
L 5: 120 [-]: GETIMPORT R11 33 ["EMPTY_SYMBOL"]
     121 [-]: NAMECALL R9 R8 K34 [0x26D544FC]
     122 [-]: CALL R9 2 0  
L 6: 123 [-]: FORGLOOP R4 L5 2 [inext]
     124 [-]: GETIMPORT R4 4 [0x89326C93]
     125 [-]: GETIMPORT R6 14 [0x0469F296]
     126 [-]: LOADK R7 K36 ["CarriedLotus"]
     127 [-]: CALL R6 1 -1 
     128 [-]: NAMECALL R4 R4 K8 [0x46A0EBF5]
     129 [-]: CALL R4 -1 1 
     130 [-]: FASTCALL1 62 R4 L7
     131 [-]: MOVE R6 R4   
     132 [-]: GETIMPORT R5 10 [0x7B998233]
     133 [-]: CALL R5 1 1  
L 7: 134 [-]: JUMPIF R5 L8 
     135 [-]: GETIMPORT R7 14 [0x0469F296]
     136 [-]: LOADK R8 K37 ["Lotus"]
     137 [-]: CALL R7 1 -1 
     138 [-]: NAMECALL R5 R4 K34 [0x26D544FC]
     139 [-]: CALL R5 -1 0 
L 8: 140 [-]: GETUPVAL R5 13
     141 [-]: LOADB R6 0   
     142 [-]: CALL R5 1 1  
     143 [-]: SETUPVAL R5 12
     144 [-]: GETUPVAL R5 13
     145 [-]: LOADB R6 1   
     146 [-]: CALL R5 1 1  
     147 [-]: SETUPVAL R5 14
     148 [-]: GETUPVAL R5 15
     149 [-]: LOADB R6 1   
     150 [-]: CALL R5 1 0  
     151 [-]: GETUPVAL R5 16
     152 [-]: LOADB R6 1   
     153 [-]: CALL R5 1 0  
     154 [-]: GETIMPORT R5 4 [0x89326C93]
     155 [-]: NAMECALL R5 R5 K38 [0x78298275]
     156 [-]: CALL R5 1 1  
     157 [-]: NAMECALL R7 R1 K16 [0xD1586535]
     158 [-]: CALL R7 1 1  
     159 [-]: NAMECALL R8 R1 K17 [0xCB3851B8]
     160 [-]: CALL R8 1 -1 
     161 [-]: NAMECALL R5 R5 K39 [0x589EF1C1]
     162 [-]: CALL R5 -1 0 
     163 [-]: GETUPVAL R5 17
     164 [-]: NAMECALL R5 R5 K40 [0xDE321E6F]
     165 [-]: CALL R5 1 1  
     166 [-]: NAMECALL R5 R5 K41 [0xF7D48EE0]
     167 [-]: CALL R5 1 1  
     168 [-]: NAMECALL R5 R5 K42 [0x707CD1F0]
     169 [-]: CALL R5 1 0  
     170 [-]: GETUPVAL R5 17
     171 [-]: NAMECALL R5 R5 K40 [0xDE321E6F]
     172 [-]: CALL R5 1 1  
     173 [-]: NAMECALL R5 R5 K41 [0xF7D48EE0]
     174 [-]: CALL R5 1 1  
     175 [-]: LOADB R7 1   
     176 [-]: NAMECALL R5 R5 K43 [0xD533F1CC]
     177 [-]: CALL R5 2 0  
     178 [-]: GETIMPORT R5 45 ["_T"]
     179 [-]: LOADB R6 1   
     180 [-]: SETTABLEKS R6 R5 K46 ["DisableTransferenceToFrame"]
     181 [-]: GETUPVAL R6 18
     182 [-]: GETTABLEKS R5 R6 K47 [0x294D5408]
     183 [-]: LOADB R6 1   
     184 [-]: LOADB R7 1   
     185 [-]: LOADB R8 1   
     186 [-]: CALL R5 3 0  
     187 [-]: GETUPVAL R6 18
     188 [-]: GETTABLEKS R5 R6 K48 [0x26222032]
     189 [-]: LOADB R6 0   
     190 [-]: CALL R5 1 0  
     191 [-]: GETUPVAL R5 19
     192 [-]: GETUPVAL R8 20
     193 [-]: GETTABLEKS R7 R8 K49 ["INTRO"]
     194 [-]: NAMECALL R5 R5 K50 [0x8ABFF40E]
     195 [-]: CALL R5 2 0  
     196 [-]: RETURN R0 0  


; Name:            
; Defined at line: 520
; #Upvalues:       10
; #Parameters:     1
; Is_vararg:       0
; Max Stack Size:  9

       0 [-]: GETIMPORT R2 1 [0xBE190284]
       1 [-]: FASTCALL1 62 R2 L0
       2 [-]: GETIMPORT R1 3 [0x7B998233]
       3 [-]: CALL R1 1 1  
L 0:   4 [-]: JUMPIFNOT R1 L1
       5 [-]: RETURN R0 0  
L 1:   6 [-]: GETUPVAL R1 0
       7 [-]: CALL R1 0 0  
       8 [-]: GETUPVAL R1 1
       9 [-]: GETUPVAL R3 2
      10 [-]: GETTABLEKS R2 R3 K4 ["INTRO"]
      11 [-]: JUMPIFNOTEQ R1 R2 L3
      12 [-]: GETUPVAL R1 3
      13 [-]: NAMECALL R1 R1 K5 [0x1C84839C]
      14 [-]: CALL R1 1 1  
      15 [-]: JUMPIF R1 L7 
      16 [-]: LOADNIL R1   
      17 [-]: JUMPIF R1 L2 
      18 [-]: GETUPVAL R2 1
      19 [-]: LOADN R3 0   
      20 [-]: ADDK R3 R2 K6 [1]
      21 [-]: MOVE R1 R3   
L 2:  22 [-]: GETUPVAL R2 4
      23 [-]: MOVE R4 R1   
      24 [-]: NAMECALL R2 R2 K7 [0x8ABFF40E]
      25 [-]: CALL R2 2 0  
      26 [-]: GETIMPORT R2 9 [0xD644C2F1]
      27 [-]: LOADK R4 K10 ["Next state: "]
      28 [-]: MOVE R6 R1   
      29 [-]: GETUPVAL R8 5
      30 [-]: GETTABLE R7 R8 R6
      31 [-]: GETTABLEKS R5 R7 K11 ["name"]
      32 [-]: CONCAT R3 R4 R5
      33 [-]: CALL R2 1 0  
      34 [-]: RETURN R0 0  
L 3:  35 [-]: GETUPVAL R1 1
      36 [-]: GETUPVAL R3 2
      37 [-]: GETTABLEKS R2 R3 K12 ["CONVERSATION"]
      38 [-]: JUMPIFNOTEQ R1 R2 L6
      39 [-]: GETUPVAL R1 6
      40 [-]: JUMPIFNOT R1 L7
      41 [-]: GETUPVAL R1 7
      42 [-]: JUMPIF R1 L5 
      43 [-]: LOADNIL R1   
      44 [-]: JUMPIF R1 L4 
      45 [-]: GETUPVAL R2 1
      46 [-]: LOADN R3 0   
      47 [-]: ADDK R3 R2 K6 [1]
      48 [-]: MOVE R1 R3   
L 4:  49 [-]: GETUPVAL R2 4
      50 [-]: MOVE R4 R1   
      51 [-]: NAMECALL R2 R2 K7 [0x8ABFF40E]
      52 [-]: CALL R2 2 0  
      53 [-]: GETIMPORT R2 9 [0xD644C2F1]
      54 [-]: LOADK R4 K10 ["Next state: "]
      55 [-]: MOVE R6 R1   
      56 [-]: GETUPVAL R8 5
      57 [-]: GETTABLE R7 R8 R6
      58 [-]: GETTABLEKS R5 R7 K11 ["name"]
      59 [-]: CONCAT R3 R4 R5
      60 [-]: CALL R2 1 0  
      61 [-]: RETURN R0 0  
L 5:  62 [-]: GETUPVAL R1 8
      63 [-]: JUMPIFNOT R1 L7
      64 [-]: GETUPVAL R2 8
      65 [-]: GETIMPORT R3 14 [0xB693B6C1]
      66 [-]: CALL R3 0 1  
      67 [-]: SUB R1 R2 R3 
      68 [-]: SETUPVAL R1 8
      69 [-]: GETUPVAL R1 8
      70 [-]: LOADN R2 0   
      71 [-]: JUMPIFNOTLT R1 R2 L7
      72 [-]: LOADNIL R1   
      73 [-]: SETUPVAL R1 8
      74 [-]: GETIMPORT R1 16 [0x25D99D89]
      75 [-]: GETUPVAL R3 9
      76 [-]: NAMECALL R1 R1 K17 [0xB6E2AB0D]
      77 [-]: CALL R1 2 0  
      78 [-]: RETURN R0 0  
L 6:  79 [-]: GETUPVAL R1 1
      80 [-]: GETUPVAL R3 2
      81 [-]: GETTABLEKS R2 R3 K18 ["COMPLETE"]
      82 [-]: JUMPIFNOTEQ R1 R2 L7
L 7:  83 [-]: RETURN R0 0  


; Name:            
; Defined at line: 550
; #Upvalues:       8
; #Parameters:     1
; Is_vararg:       0
; Max Stack Size:  8

       0 [-]: SETUPVAL R0 0
       1 [-]: GETUPVAL R1 0
       2 [-]: GETUPVAL R3 1
       3 [-]: GETTABLEKS R2 R3 K0 ["INTRO"]
       4 [-]: JUMPIFNOTEQ R1 R2 L0
       5 [-]: GETIMPORT R1 2 [0x3D106989]
       6 [-]: LOADK R2 K3 ["Playing Carry cinematics"]
       7 [-]: CALL R1 1 0  
       8 [-]: GETUPVAL R1 2
       9 [-]: LOADK R3 K4 ["StartPlaying"]
      10 [-]: NAMECALL R1 R1 K5 [0x8EB2112D]
      11 [-]: CALL R1 2 0  
      12 [-]: GETIMPORT R1 7 ["_T"]
      13 [-]: LOADNIL R2   
      14 [-]: SETTABLEKS R2 R1 K8 ["ForceLoadingScreen"]
      15 [-]: GETIMPORT R1 10 [0x89326C93]
      16 [-]: NAMECALL R1 R1 K11 [0x7C1A0374]
      17 [-]: CALL R1 1 1  
      18 [-]: LOADN R3 -1  
      19 [-]: NAMECALL R1 R1 K12 [0xB6DF3E50]
      20 [-]: CALL R1 2 0  
      21 [-]: GETUPVAL R1 3
      22 [-]: LOADB R3 1   
      23 [-]: NAMECALL R1 R1 K13 [0x8E20FBBB]
      24 [-]: CALL R1 2 0  
      25 [-]: RETURN R0 0  
L 0:  26 [-]: GETUPVAL R1 0
      27 [-]: GETUPVAL R3 1
      28 [-]: GETTABLEKS R2 R3 K14 ["CONVERSATION"]
      29 [-]: JUMPIFNOTEQ R1 R2 L1
      30 [-]: GETIMPORT R1 10 [0x89326C93]
      31 [-]: NAMECALL R1 R1 K11 [0x7C1A0374]
      32 [-]: CALL R1 1 1  
      33 [-]: LOADN R3 -1  
      34 [-]: NAMECALL R1 R1 K12 [0xB6DF3E50]
      35 [-]: CALL R1 2 0  
      36 [-]: GETUPVAL R1 4
      37 [-]: LOADB R3 1   
      38 [-]: LOADB R4 1   
      39 [-]: NAMECALL R1 R1 K15 [0x768274D6]
      40 [-]: CALL R1 3 0  
      41 [-]: GETUPVAL R1 5
      42 [-]: CALL R1 0 0  
      43 [-]: GETUPVAL R1 6
      44 [-]: NAMECALL R1 R1 K16 [0x383D2E7D]
      45 [-]: CALL R1 1 0  
      46 [-]: GETUPVAL R1 3
      47 [-]: GETUPVAL R3 6
      48 [-]: NAMECALL R3 R3 K17 [0xD1586535]
      49 [-]: CALL R3 1 1  
      50 [-]: GETUPVAL R4 6
      51 [-]: NAMECALL R4 R4 K18 [0xCB3851B8]
      52 [-]: CALL R4 1 -1 
      53 [-]: NAMECALL R1 R1 K19 [0x589EF1C1]
      54 [-]: CALL R1 -1 0 
      55 [-]: GETUPVAL R1 3
      56 [-]: GETIMPORT R3 21 [0xAF115F49]
      57 [-]: LOADB R4 0   
      58 [-]: LOADN R5 2   
      59 [-]: LOADN R6 2   
      60 [-]: LOADB R7 1   
      61 [-]: NAMECALL R1 R1 K22 [0x5D985C7E]
      62 [-]: CALL R1 6 0  
      63 [-]: GETUPVAL R2 7
      64 [-]: GETTABLEKS R1 R2 K23 [0xDD1A2C02]
      65 [-]: LOADB R2 0   
      66 [-]: LOADN R3 3   
      67 [-]: CALL R1 2 0  
      68 [-]: RETURN R0 0  
L 1:  69 [-]: GETUPVAL R1 0
      70 [-]: GETUPVAL R3 1
      71 [-]: GETTABLEKS R2 R3 K24 ["COMPLETE"]
      72 [-]: JUMPIFNOTEQ R1 R2 L2
      73 [-]: GETUPVAL R1 3
      74 [-]: LOADB R3 0   
      75 [-]: NAMECALL R1 R1 K13 [0x8E20FBBB]
      76 [-]: CALL R1 2 0  
      77 [-]: GETUPVAL R2 7
      78 [-]: GETTABLEKS R1 R2 K25 [0x7D717F70]
      79 [-]: GETIMPORT R2 27 [0x7ED0A956]
      80 [-]: LOADK R3 K28 ["/Lotus/Types/Keys/NewWarQuest/NewWarQuestKeyChain"]
      81 [-]: CALL R2 1 1  
      82 [-]: GETIMPORT R3 30 [0x7DE83207]
      83 [-]: CALL R1 2 0  
L 2:  84 [-]: RETURN R0 0  


; Name:            
; Defined at line: 579
; #Upvalues:       8
; #Parameters:     1
; Is_vararg:       0
; Max Stack Size:  4

       0 [-]: GETGLOBAL R1 K0 [0xE91D7466]
       1 [-]: SETGLOBAL R1 K0 [0xE91D7466]
       2 [-]: GETUPVAL R2 1
       3 [-]: GETTABLEKS R1 R2 K1 [0xC9013731]
       4 [-]: GETUPVAL R2 2
       5 [-]: CALL R1 1 1  
       6 [-]: SETUPVAL R1 0
       7 [-]: GETUPVAL R1 3
       8 [-]: CALL R1 0 0  
L 0:   9 [-]: GETUPVAL R1 4
      10 [-]: GETUPVAL R3 5
      11 [-]: GETTABLEKS R2 R3 K2 ["COMPLETE"]
      12 [-]: JUMPIFEQ R1 R2 L4
      13 [-]: GETIMPORT R1 4 [0xCBD666E1]
      14 [-]: LOADN R2 0   
      15 [-]: CALL R1 1 0  
L 1:  16 [-]: GETIMPORT R2 6 [0xBE190284]
      17 [-]: FASTCALL1 62 R2 L2
      18 [-]: GETIMPORT R1 8 [0x7B998233]
      19 [-]: CALL R1 1 1  
L 2:  20 [-]: JUMPIFNOT R1 L3
      21 [-]: GETIMPORT R1 4 [0xCBD666E1]
      22 [-]: LOADN R2 0   
      23 [-]: CALL R1 1 0  
      24 [-]: JUMPBACK L1  
L 3:  25 [-]: GETUPVAL R1 0
      26 [-]: GETUPVAL R3 4
      27 [-]: NAMECALL R1 R1 K9 [0x209398C2]
      28 [-]: CALL R1 2 1  
      29 [-]: SETUPVAL R1 4
      30 [-]: GETUPVAL R1 6
      31 [-]: GETIMPORT R2 11 [0x67652851]
      32 [-]: CALL R2 0 -1 
      33 [-]: CALL R1 -1 0 
      34 [-]: JUMPBACK L0  
L 4:  35 [-]: GETIMPORT R1 13 ["_T"]
      36 [-]: LOADB R2 0   
      37 [-]: SETTABLEKS R2 R1 K14 ["EpilogueMissionActive"]
      38 [-]: GETUPVAL R2 7
      39 [-]: GETTABLEKS R1 R2 K15 [0x9C7D6400]
      40 [-]: CALL R1 0 0  
      41 [-]: GETIMPORT R1 18 [0x8EE24660]
      42 [-]: LOADB R2 1   
      43 [-]: CALL R1 1 0  
      44 [-]: RETURN R0 0  


; Name:            
; Defined at line: 599
; #Upvalues:       0
; #Parameters:     0
; Is_vararg:       0
; Max Stack Size:  4

       0 [-]: GETIMPORT R0 1 [0x89326C93]
       1 [-]: GETIMPORT R2 3 [0x0469F296]
       2 [-]: LOADK R3 K4 ["CarriedLotus"]
       3 [-]: CALL R2 1 -1 
       4 [-]: NAMECALL R0 R0 K5 [0x46A0EBF5]
       5 [-]: CALL R0 -1 1 
       6 [-]: GETIMPORT R3 7 [0x022F7F9E]
       7 [-]: NAMECALL R1 R0 K8 [0xC9F6A7D7]
       8 [-]: CALL R1 2 1  
       9 [-]: FASTCALL1 62 R1 L0
      10 [-]: MOVE R3 R1   
      11 [-]: GETIMPORT R2 10 [0x7B998233]
      12 [-]: CALL R2 1 1  
L 0:  13 [-]: JUMPIF R2 L2 
      14 [-]: GETIMPORT R2 12 [0xDB5FE16F]
      15 [-]: JUMPIFNOT R2 L1
      16 [-]: NAMECALL R2 R1 K13 [0x383D2E7D]
      17 [-]: CALL R2 1 0  
      18 [-]: RETURN R0 0  
L 1:  19 [-]: NAMECALL R2 R1 K14 [0xF4E253B6]
      20 [-]: CALL R2 1 0  
L 2:  21 [-]: RETURN R0 0  


; Name:            
; Defined at line: 611
; #Upvalues:       3
; #Parameters:     0
; Is_vararg:       0
; Max Stack Size:  4

       0 [-]: GETUPVAL R0 1
       1 [-]: LOADB R1 1   
       2 [-]: CALL R0 1 1  
       3 [-]: SETUPVAL R0 0
       4 [-]: GETUPVAL R0 0
       5 [-]: LOADB R2 1   
       6 [-]: LOADB R3 1   
       7 [-]: NAMECALL R0 R0 K0 [0x768274D6]
       8 [-]: CALL R0 3 0  
       9 [-]: GETUPVAL R0 1
      10 [-]: LOADB R1 0   
      11 [-]: CALL R0 1 1  
      12 [-]: SETUPVAL R0 2
      13 [-]: GETUPVAL R0 2
      14 [-]: LOADB R2 1   
      15 [-]: LOADB R3 1   
      16 [-]: NAMECALL R0 R0 K0 [0x768274D6]
      17 [-]: CALL R0 3 0  
      18 [-]: RETURN R0 0  


; Name:            
; Defined at line: 619
; #Upvalues:       1
; #Parameters:     1
; Is_vararg:       0
; Max Stack Size:  6

       0 [-]: GETIMPORT R1 1 [0xCBD666E1]
       1 [-]: LOADN R2 1   
       2 [-]: CALL R1 1 0  
       3 [-]: FASTCALL1 62 R0 L0
       4 [-]: MOVE R2 R0   
       5 [-]: GETIMPORT R1 3 [0x7B998233]
       6 [-]: CALL R1 1 1  
L 0:   7 [-]: JUMPIF R1 L5 
       8 [-]: GETIMPORT R2 5 [0x25D99D89]
       9 [-]: FASTCALL1 62 R2 L1
      10 [-]: GETIMPORT R1 3 [0x7B998233]
      11 [-]: CALL R1 1 1  
L 1:  12 [-]: JUMPIF R1 L5 
      13 [-]: GETIMPORT R1 5 [0x25D99D89]
      14 [-]: NAMECALL R1 R1 K6 [0x25A6E75E]
      15 [-]: CALL R1 1 1  
      16 [-]: FASTCALL1 62 R1 L2
      17 [-]: MOVE R3 R1   
      18 [-]: GETIMPORT R2 3 [0x7B998233]
      19 [-]: CALL R2 1 1  
L 2:  20 [-]: JUMPIF R2 L5 
      21 [-]: NAMECALL R2 R1 K7 [0xD297B8B3]
      22 [-]: CALL R2 1 1  
      23 [-]: LOADN R3 0   
      24 [-]: JUMPIFNOTEQ R2 R3 L3
      25 [-]: GETUPVAL R3 0
      26 [-]: MOVE R4 R0   
      27 [-]: GETIMPORT R5 9 [0xE9D518EA]
      28 [-]: CALL R3 2 0  
      29 [-]: RETURN R0 0  
L 3:  30 [-]: LOADN R3 2   
      31 [-]: JUMPIFNOTEQ R2 R3 L4
      32 [-]: GETUPVAL R3 0
      33 [-]: MOVE R4 R0   
      34 [-]: GETIMPORT R5 11 [0x46A55AD4]
      35 [-]: CALL R3 2 0  
      36 [-]: RETURN R0 0  
L 4:  37 [-]: GETUPVAL R3 0
      38 [-]: MOVE R4 R0   
      39 [-]: GETIMPORT R5 13 [0xC1D75409]
      40 [-]: CALL R3 2 0  
L 5:  41 [-]: RETURN R0 0  



