; Name:            
; Defined at line: 1
; #Upvalues:       0
; #Parameters:     0
; Is_vararg:       1
; Max Stack Size:  33

       1 [-]: GETIMPORT R0 1 [0xAEABECDA]
       2 [-]: GETVARARGS R1 1
       3 [-]: GETIMPORT R2 4 ["seeall"]
       4 [-]: CALL R0 2 0  
       5 [-]: LOADN R0 1   
       6 [-]: SETGLOBAL R0 K5 ["INCREMENT"]
       7 [-]: LOADN R0 -1  
       8 [-]: SETGLOBAL R0 K6 ["DECREMENT"]
       9 [-]: LOADN R0 1   
      10 [-]: SETGLOBAL R0 K7 ["RIGHT_ALIGNED"]
      11 [-]: LOADN R0 2   
      12 [-]: SETGLOBAL R0 K8 ["CENTER_ALIGNED"]
      13 [-]: LOADN R0 3   
      14 [-]: SETGLOBAL R0 K9 ["LEFT_ALIGNED"]
      15 [-]: DUPTABLE R0 17
      16 [-]: LOADN R1 0   
      17 [-]: SETTABLEKS R1 R0 K10 ["PC"]
      18 [-]: LOADN R1 1   
      19 [-]: SETTABLEKS R1 R0 K11 ["PS4"]
      20 [-]: LOADN R1 2   
      21 [-]: SETTABLEKS R1 R0 K12 ["XBOX_ONE"]
      22 [-]: LOADN R1 3   
      23 [-]: SETTABLEKS R1 R0 K13 ["SWITCH"]
      24 [-]: LOADN R1 4   
      25 [-]: SETTABLEKS R1 R0 K14 ["PS5"]
      26 [-]: LOADN R1 5   
      27 [-]: SETTABLEKS R1 R0 K15 ["TOUCH"]
      28 [-]: LOADN R1 6   
      29 [-]: SETTABLEKS R1 R0 K16 ["BIG_PIC"]
      30 [-]: SETGLOBAL R0 K18 ["PLATFORM"]
      31 [-]: DUPCLOSURE R0 K19 []
      32 [-]: SETGLOBAL R0 K20 ["Alphanumeric"]
      33 [-]: DUPCLOSURE R0 K21 []
      34 [-]: SETGLOBAL R0 K22 ["ValidChinese"]
      35 [-]: DUPCLOSURE R0 K23 []
      36 [-]: SETGLOBAL R0 K24 ["Punctuation"]
      37 [-]: DUPCLOSURE R0 K25 []
      38 [-]: DUPCLOSURE R1 K26 []
      39 [-]: MOVE R0 R0   
      40 [-]: SETGLOBAL R1 K27 ["PlaySound"]
      41 [-]: DUPCLOSURE R1 K28 []
      42 [-]: DUPCLOSURE R2 K29 []
      43 [-]: SETGLOBAL R2 K30 ["Ternary"]
      44 [-]: DUPCLOSURE R2 K31 []
      45 [-]: SETGLOBAL R2 K32 ["ToggleValue"]
      46 [-]: DUPCLOSURE R2 K33 []
      47 [-]: SETGLOBAL R2 K34 ["ToggleValueNoWrap"]
      48 [-]: DUPCLOSURE R2 K35 []
      49 [-]: DUPCLOSURE R3 K36 []
      50 [-]: SETGLOBAL R3 K37 ["FindInTable"]
      51 [-]: DUPCLOSURE R3 K38 []
      52 [-]: SETGLOBAL R3 K39 ["IsValueInTable"]
      53 [-]: DUPCLOSURE R3 K40 []
      54 [-]: SETGLOBAL R3 K41 ["CopyTable"]
      55 [-]: DUPCLOSURE R3 K42 []
      56 [-]: MOVE R0 R3   
      57 [-]: DUPCLOSURE R4 K43 []
      58 [-]: MOVE R0 R3   
      59 [-]: SETGLOBAL R4 K44 ["CopyTableRecursive"]
      60 [-]: DUPCLOSURE R4 K45 []
      61 [-]: SETGLOBAL R4 K46 ["GetEntityFromTag"]
      62 [-]: DUPCLOSURE R4 K47 []
      63 [-]: SETGLOBAL R4 K48 ["GetNearestEntityFromTag"]
      64 [-]: DUPCLOSURE R4 K49 []
      65 [-]: SETGLOBAL R4 K50 ["ToDeg"]
      66 [-]: DUPCLOSURE R4 K51 []
      67 [-]: DUPCLOSURE R5 K52 []
      68 [-]: SETGLOBAL R5 K53 ["ToRad"]
      69 [-]: DUPCLOSURE R5 K54 []
      70 [-]: SETGLOBAL R5 K55 ["GetSquaredDistanceBetweenPoints"]
      71 [-]: DUPCLOSURE R5 K56 []
      72 [-]: SETGLOBAL R5 K57 ["GetDistanceBetweenPoints"]
      73 [-]: DUPCLOSURE R5 K58 []
      74 [-]: SETGLOBAL R5 K59 ["GetDistanceBetweenPointsEx"]
      75 [-]: DUPCLOSURE R5 K60 []
      76 [-]: SETGLOBAL R5 K61 ["GetAngleBetweenPoints"]
      77 [-]: DUPCLOSURE R5 K62 []
      78 [-]: SETGLOBAL R5 K63 ["IntersectLineToPlane"]
      79 [-]: DUPCLOSURE R5 K64 []
      80 [-]: SETGLOBAL R5 K65 ["GetScreenCursor"]
      81 [-]: DUPCLOSURE R5 K66 []
      82 [-]: DUPCLOSURE R6 K67 []
      83 [-]: DUPCLOSURE R7 K68 []
      84 [-]: SETGLOBAL R7 K69 ["Round"]
      85 [-]: DUPCLOSURE R7 K70 []
      86 [-]: SETGLOBAL R7 K71 ["IsDevicePsMove"]
      87 [-]: DUPCLOSURE R7 K72 []
      88 [-]: DUPCLOSURE R8 K73 []
      89 [-]: SETGLOBAL R8 K74 ["ConvertRGB2HEX"]
      90 [-]: DUPCLOSURE R8 K75 []
      91 [-]: DUPCLOSURE R9 K76 []
      92 [-]: SETGLOBAL R9 K77 ["HEX2RGB"]
      93 [-]: DUPCLOSURE R9 K78 []
      94 [-]: SETGLOBAL R9 K79 ["InterpolateColors"]
      95 [-]: DUPCLOSURE R9 K80 []
      96 [-]: SETGLOBAL R9 K81 ["ConvertHSB2RGB"]
      97 [-]: DUPCLOSURE R9 K82 []
      98 [-]: SETGLOBAL R9 K83 ["RunForAllLocalAvatars"]
      99 [-]: DUPCLOSURE R9 K84 []
     100 [-]: SETGLOBAL R9 K85 ["PrintTable"]
     101 [-]: GETIMPORT R9 88 [0x76960806]
     102 [-]: NEWTABLE R10 0 2
     103 [-]: LOADN R12 194
     104 [-]: FASTCALL1 42 R12 L0
     105 [-]: GETIMPORT R11 91 [0x0DA4ACB2]
     106 [-]: CALL R11 1 1 
L 0: 107 [-]: LOADN R13 160
     108 [-]: FASTCALL1 42 R13 L1
     109 [-]: GETIMPORT R12 91 [0x0DA4ACB2]
     110 [-]: CALL R12 1 1 
L 1: 111 [-]: SETLIST R10 R11 2 [1]
     112 [-]: CALL R9 1 1  
     113 [-]: NEWTABLE R10 0 4
     114 [-]: DUPTABLE R11 94
     115 [-]: LOADK R12 K95 [","]
     116 [-]: SETTABLEKS R12 R11 K92 ["Thousands"]
     117 [-]: LOADK R12 K96 ["."]
     118 [-]: SETTABLEKS R12 R11 K93 ["Decimal"]
     119 [-]: DUPTABLE R12 94
     120 [-]: LOADK R13 K96 ["."]
     121 [-]: SETTABLEKS R13 R12 K92 ["Thousands"]
     122 [-]: LOADK R13 K95 [","]
     123 [-]: SETTABLEKS R13 R12 K93 ["Decimal"]
     124 [-]: DUPTABLE R13 94
     125 [-]: SETTABLEKS R9 R13 K92 ["Thousands"]
     126 [-]: LOADK R14 K95 [","]
     127 [-]: SETTABLEKS R14 R13 K93 ["Decimal"]
     128 [-]: DUPTABLE R14 94
     129 [-]: LOADK R15 K96 ["."]
     130 [-]: SETTABLEKS R15 R14 K92 ["Thousands"]
     131 [-]: LOADK R15 K97 ["'"]
     132 [-]: SETTABLEKS R15 R14 K93 ["Decimal"]
     133 [-]: SETLIST R10 R11 4 [1]
     134 [-]: DUPTABLE R11 113
     135 [-]: LOADN R12 1  
     136 [-]: SETTABLEKS R12 R11 K98 ["_en"]
     137 [-]: LOADN R12 3  
     138 [-]: SETTABLEKS R12 R11 K99 ["_fr"]
     139 [-]: LOADN R12 2  
     140 [-]: SETTABLEKS R12 R11 K100 ["_it"]
     141 [-]: LOADN R12 2  
     142 [-]: SETTABLEKS R12 R11 K101 ["_de"]
     143 [-]: LOADN R12 3  
     144 [-]: SETTABLEKS R12 R11 K102 ["_es"]
     145 [-]: LOADN R12 2  
     146 [-]: SETTABLEKS R12 R11 K103 ["_pt"]
     147 [-]: LOADN R12 3  
     148 [-]: SETTABLEKS R12 R11 K104 ["_ru"]
     149 [-]: LOADN R12 3  
     150 [-]: SETTABLEKS R12 R11 K105 ["_pl"]
     151 [-]: LOADN R12 3  
     152 [-]: SETTABLEKS R12 R11 K106 ["_uk"]
     153 [-]: LOADN R12 2  
     154 [-]: SETTABLEKS R12 R11 K107 ["_tr"]
     155 [-]: LOADN R12 1  
     156 [-]: SETTABLEKS R12 R11 K108 ["_ja"]
     157 [-]: LOADN R12 1  
     158 [-]: SETTABLEKS R12 R11 K109 ["_tc"]
     159 [-]: LOADN R12 1  
     160 [-]: SETTABLEKS R12 R11 K110 ["_zh"]
     161 [-]: LOADN R12 1  
     162 [-]: SETTABLEKS R12 R11 K111 ["_ko"]
     163 [-]: LOADN R12 1  
     164 [-]: SETTABLEKS R12 R11 K112 ["_th"]
     165 [-]: LOADNIL R12  
     166 [-]: NEWCLOSURE R13 P38
     167 [-]: MOVE R1 R12  
     168 [-]: MOVE R0 R11  
     169 [-]: DUPCLOSURE R14 K114 []
     170 [-]: MOVE R0 R13  
     171 [-]: SETGLOBAL R14 K115 ["GetNumericSeparatorsIndex"]
     172 [-]: DUPCLOSURE R14 K116 []
     173 [-]: MOVE R0 R10  
     174 [-]: MOVE R0 R13  
     175 [-]: DUPCLOSURE R15 K117 []
     176 [-]: MOVE R0 R10  
     177 [-]: MOVE R0 R13  
     178 [-]: DUPCLOSURE R16 K118 []
     179 [-]: MOVE R0 R10  
     180 [-]: MOVE R0 R13  
     181 [-]: DUPCLOSURE R17 K119 []
     182 [-]: MOVE R0 R10  
     183 [-]: MOVE R0 R13  
     184 [-]: DUPCLOSURE R18 K120 []
     185 [-]: MOVE R0 R17  
     186 [-]: SETGLOBAL R18 K121 ["SeparateWithCommas"]
     187 [-]: DUPCLOSURE R18 K122 []
     188 [-]: MOVE R0 R6   
     189 [-]: MOVE R0 R17  
     190 [-]: MOVE R0 R10  
     191 [-]: MOVE R0 R13  
     192 [-]: SETGLOBAL R18 K123 ["FormatNumber"]
     193 [-]: DUPCLOSURE R18 K124 []
     194 [-]: SETGLOBAL R18 K125 ["FormatNumberCompact"]
     195 [-]: DUPCLOSURE R18 K126 []
     196 [-]: MOVE R0 R0   
     197 [-]: SETGLOBAL R18 K127 ["AnimateTyping"]
     198 [-]: DUPCLOSURE R18 K128 []
     199 [-]: SETGLOBAL R18 K129 ["CreateObservable"]
     200 [-]: DUPCLOSURE R18 K130 []
     201 [-]: SETGLOBAL R18 K131 ["CreateInputDeviceObservable"]
     202 [-]: DUPCLOSURE R18 K132 []
     203 [-]: SETGLOBAL R18 K133 ["SetFitText"]
     204 [-]: DUPCLOSURE R18 K134 []
     205 [-]: SETGLOBAL R18 K135 ["SetFittedText"]
     206 [-]: DUPCLOSURE R18 K136 []
     207 [-]: SETGLOBAL R18 K137 ["FitTextIntoLines"]
     208 [-]: DUPCLOSURE R18 K138 []
     209 [-]: SETGLOBAL R18 K139 ["FadeBackground"]
     210 [-]: DUPCLOSURE R18 K140 []
     211 [-]: SETGLOBAL R18 K141 ["ShuffleTable"]
     212 [-]: DUPCLOSURE R18 K142 []
     213 [-]: SETGLOBAL R18 K143 ["SeededShuffleTable"]
     214 [-]: DUPCLOSURE R18 K144 []
     215 [-]: SETGLOBAL R18 K145 ["DoOpenWebBrowser"]
     216 [-]: DUPCLOSURE R18 K146 []
     217 [-]: SETGLOBAL R18 K147 ["DoShowPlatformHelp"]
     218 [-]: DUPCLOSURE R18 K148 []
     219 [-]: SETGLOBAL R18 K149 ["DoShowPlatformParty"]
     220 [-]: DUPCLOSURE R18 K150 []
     221 [-]: SETGLOBAL R18 K151 ["DoShowPlatformChallenges"]
     222 [-]: DUPCLOSURE R18 K152 []
     223 [-]: SETGLOBAL R18 K153 ["DoShowPlatformStore"]
     224 [-]: DUPCLOSURE R18 K154 []
     225 [-]: SETGLOBAL R18 K155 ["IsUGCRestricted"]
     226 [-]: DUPCLOSURE R18 K156 []
     227 [-]: SETGLOBAL R18 K157 ["GetChatMovie"]
     228 [-]: DUPCLOSURE R18 K158 []
     229 [-]: DUPCLOSURE R19 K159 []
     230 [-]: MOVE R0 R18  
     231 [-]: SETGLOBAL R19 K160 ["TransformPixelToViewportCoordinates"]
     232 [-]: DUPCLOSURE R19 K161 []
     233 [-]: DUPCLOSURE R20 K162 []
     234 [-]: MOVE R0 R19  
     235 [-]: SETGLOBAL R20 K163 ["TransformViewportToPixelCoordinates"]
     236 [-]: DUPCLOSURE R20 K164 []
     237 [-]: DUPCLOSURE R21 K165 []
     238 [-]: MOVE R0 R20  
     239 [-]: SETGLOBAL R21 K166 ["GetRootBasedPosition"]
     240 [-]: DUPCLOSURE R21 K167 []
     241 [-]: MOVE R0 R18  
     242 [-]: DUPCLOSURE R22 K168 []
     243 [-]: MOVE R0 R21  
     244 [-]: SETGLOBAL R22 K169 ["GetScreenParticlesCoord"]
     245 [-]: DUPCLOSURE R22 K170 []
     246 [-]: MOVE R0 R21  
     247 [-]: DUPCLOSURE R23 K171 []
     248 [-]: MOVE R0 R22  
     249 [-]: SETGLOBAL R23 K172 ["CreateScreenParticles"]
     250 [-]: DUPCLOSURE R23 K173 []
     251 [-]: MOVE R0 R20  
     252 [-]: MOVE R0 R22  
     253 [-]: SETGLOBAL R23 K174 ["CreateParticles"]
     254 [-]: DUPCLOSURE R23 K175 []
     255 [-]: MOVE R0 R22  
     256 [-]: SETGLOBAL R23 K176 ["CreateParticlesOnMouse"]
     257 [-]: DUPCLOSURE R23 K177 []
     258 [-]: MOVE R0 R20  
     259 [-]: MOVE R0 R21  
     260 [-]: SETGLOBAL R23 K178 ["CreateUIParticles"]
     261 [-]: DUPCLOSURE R23 K179 []
     262 [-]: SETGLOBAL R23 K180 ["ShowYesOrNoMessage"]
     263 [-]: DUPCLOSURE R23 K181 []
     264 [-]: SETGLOBAL R23 K182 ["ShowConfirmMessage"]
     265 [-]: DUPCLOSURE R23 K183 []
     266 [-]: DUPCLOSURE R24 K184 []
     267 [-]: MOVE R0 R23  
     268 [-]: SETGLOBAL R24 K185 ["_ShowMessage"]
     269 [-]: DUPCLOSURE R24 K186 []
     270 [-]: SETGLOBAL R24 K187 ["ShowMessage"]
     271 [-]: DUPCLOSURE R24 K188 []
     272 [-]: MOVE R0 R23  
     273 [-]: MOVE R0 R0   
     274 [-]: SETGLOBAL R24 K189 ["ShowErrorMessage"]
     275 [-]: DUPCLOSURE R24 K190 []
     276 [-]: MOVE R0 R23  
     277 [-]: SETGLOBAL R24 K191 ["ShowCustomMessage"]
     278 [-]: DUPCLOSURE R24 K192 []
     279 [-]: SETGLOBAL R24 K193 ["RepositionCallouts"]
     280 [-]: DUPCLOSURE R24 K194 []
     281 [-]: SETGLOBAL R24 K195 ["AttachFunctionToEnvironment"]
     282 [-]: DUPCLOSURE R24 K196 []
     283 [-]: SETGLOBAL R24 K197 ["HookUpEnvironmentCallback"]
     284 [-]: DUPCLOSURE R24 K198 []
     285 [-]: DUPCLOSURE R25 K199 []
     286 [-]: MOVE R0 R24  
     287 [-]: SETGLOBAL R25 K200 ["IsConnectionErrorMsg"]
     288 [-]: DUPCLOSURE R25 K201 []
     289 [-]: MOVE R0 R24  
     290 [-]: DUPCLOSURE R26 K202 []
     291 [-]: MOVE R0 R25  
     292 [-]: SETGLOBAL R26 K203 ["ParseConnectionErrorMsg"]
     293 [-]: DUPCLOSURE R26 K204 []
     294 [-]: MOVE R0 R25  
     295 [-]: SETGLOBAL R26 K205 ["ParseAddFriendErrorMsg"]
     296 [-]: DUPCLOSURE R26 K206 []
     297 [-]: MOVE R0 R25  
     298 [-]: SETGLOBAL R26 K207 ["ParseAddToGuildErrorMsg"]
     299 [-]: DUPCLOSURE R26 K208 []
     300 [-]: SETGLOBAL R26 K209 ["ShouldMoveIntoTitleSafe"]
     301 [-]: DUPCLOSURE R26 K210 []
     302 [-]: DUPCLOSURE R27 K211 []
     303 [-]: MOVE R0 R26  
     304 [-]: SETGLOBAL R27 K212 ["GetInvalidNameCharacters"]
     305 [-]: DUPCLOSURE R27 K213 []
     306 [-]: MOVE R0 R26  
     307 [-]: SETGLOBAL R27 K214 ["ValidateName"]
     308 [-]: DUPCLOSURE R27 K215 []
     309 [-]: SETGLOBAL R27 K216 ["ConvertColorNumberToHex"]
     310 [-]: DUPCLOSURE R27 K217 []
     311 [-]: SETGLOBAL R27 K218 ["ConvertColorNumberToProceduralRGB"]
     312 [-]: DUPCLOSURE R27 K219 []
     313 [-]: SETGLOBAL R27 K220 ["ConvertHEX2RGB255"]
     314 [-]: DUPCLOSURE R27 K221 []
     315 [-]: SETGLOBAL R27 K222 ["StringFindLast"]
     316 [-]: DUPCLOSURE R27 K223 []
     317 [-]: SETGLOBAL R27 K224 ["ConvertToRoman"]
     318 [-]: DUPCLOSURE R27 K225 []
     319 [-]: SETGLOBAL R27 K226 ["RaySphereIntersection"]
     320 [-]: DUPCLOSURE R27 K227 []
     321 [-]: DUPCLOSURE R28 K228 []
     322 [-]: MOVE R0 R27  
     323 [-]: SETGLOBAL R28 K229 ["EscapeMagicCharacters"]
     324 [-]: DUPCLOSURE R28 K230 []
     325 [-]: SETGLOBAL R28 K231 ["SanitizeTextForHTML"]
     326 [-]: DUPCLOSURE R28 K232 []
     327 [-]: DUPCLOSURE R29 K233 []
     328 [-]: MOVE R0 R28  
     329 [-]: SETGLOBAL R29 K234 ["GetStageProp"]
     330 [-]: DUPCLOSURE R29 K235 []
     331 [-]: MOVE R0 R28  
     332 [-]: SETGLOBAL R29 K236 ["GetVisibilitySize"]
     333 [-]: DUPCLOSURE R29 K237 []
     334 [-]: MOVE R0 R28  
     335 [-]: SETGLOBAL R29 K238 ["GetVisibilityCenter"]
     336 [-]: DUPCLOSURE R29 K239 []
     337 [-]: MOVE R0 R28  
     338 [-]: SETGLOBAL R29 K240 ["GetVisibilityFadeSize"]
     339 [-]: DUPCLOSURE R29 K241 []
     340 [-]: SETGLOBAL R29 K242 ["GetScreenDimensions"]
     341 [-]: DUPCLOSURE R29 K243 []
     342 [-]: SETGLOBAL R29 K244 ["GetProportionalScale"]
     343 [-]: DUPCLOSURE R29 K245 []
     344 [-]: SETGLOBAL R29 K246 ["BlinkClip"]
     345 [-]: DUPCLOSURE R29 K247 []
     346 [-]: DUPCLOSURE R30 K248 []
     347 [-]: MOVE R0 R29  
     348 [-]: SETGLOBAL R30 K249 ["GetTransformToGlobal"]
     349 [-]: DUPCLOSURE R30 K250 []
     350 [-]: MOVE R0 R29  
     351 [-]: SETGLOBAL R30 K251 ["TransformPositionToGlobal"]
     352 [-]: DUPCLOSURE R30 K252 []
     353 [-]: DUPCLOSURE R31 K253 []
     354 [-]: MOVE R0 R30  
     355 [-]: SETGLOBAL R31 K254 ["GetTransformToLocal"]
     356 [-]: DUPCLOSURE R31 K255 []
     357 [-]: MOVE R0 R30  
     358 [-]: SETGLOBAL R31 K256 ["TransformPositionToLocal"]
     359 [-]: DUPCLOSURE R31 K257 []
     360 [-]: SETGLOBAL R31 K258 ["SplitChildClipName"]
     361 [-]: DUPCLOSURE R31 K259 []
     362 [-]: DUPCLOSURE R32 K260 []
     363 [-]: MOVE R0 R31  
     364 [-]: SETGLOBAL R32 K261 ["GetPlatform"]
     365 [-]: DUPCLOSURE R32 K262 []
     366 [-]: MOVE R0 R31  
     367 [-]: SETGLOBAL R32 K263 ["GetPlatformString"]
     368 [-]: CLOSEUPVALS R12
     369 [-]: RETURN R0 0  


; Name:            
; Defined at line: 17
; #Upvalues:       0
; #Parameters:     0
; Is_vararg:       0
; Max Stack Size:  1

       0 [-]: LOADK R0 K0 ["A-Za-z0-9"]
       1 [-]: RETURN R0 1  


; Name:            
; Defined at line: 21
; #Upvalues:       0
; #Parameters:     0
; Is_vararg:       0
; Max Stack Size:  1

       0 [-]: LOADK R0 K0 ["\\u4E00-\\u9FCC\\u3400-\\u4DB5"]
       1 [-]: RETURN R0 1  


; Name:            
; Defined at line: 25
; #Upvalues:       0
; #Parameters:     0
; Is_vararg:       0
; Max Stack Size:  1

       0 [-]: LOADK R0 K0 ["!-/:-?@[-`{-~"]
       1 [-]: RETURN R0 1  


; Name:            
; Defined at line: 29
; #Upvalues:       0
; #Parameters:     4
; Is_vararg:       0
; Max Stack Size:  11

       0 [-]: FASTCALL1 62 R0 L0
       1 [-]: MOVE R5 R0   
       2 [-]: GETIMPORT R4 1 [0x7B998233]
       3 [-]: CALL R4 1 1  
L 0:   4 [-]: JUMPIF R4 L6 
       5 [-]: GETIMPORT R5 3 [0x89326C93]
       6 [-]: FASTCALL1 62 R5 L1
       7 [-]: GETIMPORT R4 1 [0x7B998233]
       8 [-]: CALL R4 1 1  
L 1:   9 [-]: JUMPIF R4 L6 
      10 [-]: FASTCALL1 62 R1 L2
      11 [-]: MOVE R5 R1   
      12 [-]: GETIMPORT R4 1 [0x7B998233]
      13 [-]: CALL R4 1 1  
L 2:  14 [-]: JUMPIFNOT R4 L3
      15 [-]: GETIMPORT R4 5 [0xA421AF95]
      16 [-]: CALL R4 0 1  
      17 [-]: MOVE R1 R4   
L 3:  18 [-]: FASTCALL1 62 R2 L4
      19 [-]: MOVE R5 R2   
      20 [-]: GETIMPORT R4 1 [0x7B998233]
      21 [-]: CALL R4 1 1  
L 4:  22 [-]: JUMPIFNOT R4 L5
      23 [-]: LOADB R2 0   
L 5:  24 [-]: GETIMPORT R4 3 [0x89326C93]
      25 [-]: MOVE R6 R0   
      26 [-]: MOVE R7 R1   
      27 [-]: MOVE R8 R2   
      28 [-]: LOADN R9 1   
      29 [-]: MOVE R10 R3  
      30 [-]: NAMECALL R4 R4 K6 [0x659D451F]
      31 [-]: CALL R4 6 1  
      32 [-]: RETURN R4 1  
L 6:  33 [-]: LOADNIL R4   
      34 [-]: RETURN R4 1  


; Name:            
; Defined at line: 42
; #Upvalues:       1
; #Parameters:     4
; Is_vararg:       0
; Max Stack Size:  9

       0 [-]: GETUPVAL R4 0
       1 [-]: MOVE R5 R0   
       2 [-]: MOVE R6 R1   
       3 [-]: MOVE R7 R2   
       4 [-]: MOVE R8 R3   
       5 [-]: CALL R4 4 1  
       6 [-]: RETURN R4 1  


; Name:            
; Defined at line: 46
; #Upvalues:       0
; #Parameters:     3
; Is_vararg:       0
; Max Stack Size:  3

       0 [-]: JUMPIFNOT R0 L0
       1 [-]: RETURN R1 1  
L 0:   2 [-]: RETURN R2 1  


; Name:            
; Defined at line: 54
; #Upvalues:       0
; #Parameters:     3
; Is_vararg:       0
; Max Stack Size:  4

       0 [-]: JUMPIFNOT R0 L0
       1 [-]: MOVE R3 R1   
       2 [-]: RETURN R3 1  
L 0:   3 [-]: MOVE R3 R2   
       4 [-]: RETURN R3 1  
       5 [-]: RETURN R3 1  


; Name:            
; Defined at line: 58
; #Upvalues:       0
; #Parameters:     4
; Is_vararg:       0
; Max Stack Size:  9

       0 [-]: ADD R4 R0 R1 
       1 [-]: GETGLOBAL R5 K0 ["INCREMENT"]
       2 [-]: JUMPIFNOTEQ R1 R5 L0
       3 [-]: JUMPIFNOTLT R3 R4 L0
       4 [-]: MOVE R4 R2   
       5 [-]: JUMP L1
     
L 0:   6 [-]: GETGLOBAL R5 K1 ["DECREMENT"]
       7 [-]: JUMPIFNOTEQ R1 R5 L1
       8 [-]: JUMPIFNOTLT R4 R2 L1
       9 [-]: MOVE R4 R3   
L 1:  10 [-]: GETIMPORT R5 3 [0x42DCC9F5]
      11 [-]: MOVE R6 R4   
      12 [-]: MOVE R7 R2   
      13 [-]: MOVE R8 R3   
      14 [-]: CALL R5 3 1  
      15 [-]: RETURN R5 1  


; Name:            
; Defined at line: 68
; #Upvalues:       0
; #Parameters:     4
; Is_vararg:       0
; Max Stack Size:  9

       0 [-]: ADD R4 R0 R1 
       1 [-]: GETGLOBAL R5 K0 ["INCREMENT"]
       2 [-]: JUMPIFNOTEQ R1 R5 L0
       3 [-]: JUMPIFNOTLT R3 R4 L0
       4 [-]: MOVE R4 R3   
       5 [-]: JUMP L1
     
L 0:   6 [-]: GETGLOBAL R5 K1 ["DECREMENT"]
       7 [-]: JUMPIFNOTEQ R1 R5 L1
       8 [-]: JUMPIFNOTLT R4 R2 L1
       9 [-]: MOVE R4 R2   
L 1:  10 [-]: GETIMPORT R5 3 [0x42DCC9F5]
      11 [-]: MOVE R6 R4   
      12 [-]: MOVE R7 R2   
      13 [-]: MOVE R8 R3   
      14 [-]: CALL R5 3 1  
      15 [-]: RETURN R5 1  


; Name:            
; Defined at line: 78
; #Upvalues:       0
; #Parameters:     2
; Is_vararg:       0
; Max Stack Size:  7

       0 [-]: GETIMPORT R2 1 [0xCFC01047]
       1 [-]: MOVE R3 R0   
       2 [-]: CALL R2 1 3  
       3 [-]: FORGPREP_NEXT R2 L1
L 0:   4 [-]: JUMPIFNOTEQ R6 R1 L1
       5 [-]: RETURN R5 1  
L 1:   6 [-]: FORGLOOP R2 L0 2
       7 [-]: LOADN R2 -1  
       8 [-]: RETURN R2 1  


; Name:            
; Defined at line: 87
; #Upvalues:       0
; #Parameters:     2
; Is_vararg:       0
; Max Stack Size:  8

       0 [-]: GETIMPORT R3 1 [0xCFC01047]
       1 [-]: MOVE R4 R0   
       2 [-]: CALL R3 1 3  
       3 [-]: FORGPREP_NEXT R3 L1
L 0:   4 [-]: JUMPIFNOTEQ R7 R1 L1
       5 [-]: MOVE R2 R6   
       6 [-]: RETURN R2 1  
L 1:   7 [-]: FORGLOOP R3 L0 2
       8 [-]: LOADN R2 -1  
       9 [-]: RETURN R2 1  


; Name:            
; Defined at line: 91
; #Upvalues:       0
; #Parameters:     2
; Is_vararg:       0
; Max Stack Size:  8

       0 [-]: GETIMPORT R2 1 [0xCFC01047]
       1 [-]: MOVE R3 R0   
       2 [-]: CALL R2 1 3  
       3 [-]: FORGPREP_NEXT R2 L1
L 0:   4 [-]: JUMPIFNOTEQ R6 R1 L1
       5 [-]: LOADB R7 1   
       6 [-]: RETURN R7 1  
L 1:   7 [-]: FORGLOOP R2 L0 2
       8 [-]: LOADB R2 0   
       9 [-]: RETURN R2 1  


; Name:            
; Defined at line: 100
; #Upvalues:       0
; #Parameters:     1
; Is_vararg:       0
; Max Stack Size:  7

       0 [-]: NEWTABLE R1 0 0
       1 [-]: GETIMPORT R2 1 [0xCFC01047]
       2 [-]: MOVE R3 R0   
       3 [-]: CALL R2 1 3  
       4 [-]: FORGPREP_NEXT R2 L1
L 0:   5 [-]: SETTABLE R6 R1 R5
L 1:   6 [-]: FORGLOOP R2 L0 2
       7 [-]: RETURN R1 1  


; Name:            
; Defined at line: 108
; #Upvalues:       1
; #Parameters:     1
; Is_vararg:       0
; Max Stack Size:  9

       0 [-]: FASTCALL1 40 R0 L0
       1 [-]: MOVE R2 R0   
       2 [-]: GETIMPORT R1 1 [0x0B96777E]
       3 [-]: CALL R1 1 1  
L 0:   4 [-]: JUMPXEQKS R1 K2 L3 NOT ["table"]
       5 [-]: NEWTABLE R1 0 0
       6 [-]: GETIMPORT R2 4 [0xCFC01047]
       7 [-]: MOVE R3 R0   
       8 [-]: CALL R2 1 3  
       9 [-]: FORGPREP_NEXT R2 L2
L 1:  10 [-]: GETUPVAL R7 0
      11 [-]: MOVE R8 R6   
      12 [-]: CALL R7 1 1  
      13 [-]: SETTABLE R7 R1 R5
L 2:  14 [-]: FORGLOOP R2 L1 2
      15 [-]: RETURN R1 1  
L 3:  16 [-]: RETURN R0 1  


; Name:            
; Defined at line: 120
; #Upvalues:       1
; #Parameters:     1
; Is_vararg:       0
; Max Stack Size:  3

       0 [-]: GETUPVAL R1 0
       1 [-]: MOVE R2 R0   
       2 [-]: CALL R1 1 1  
       3 [-]: RETURN R1 1  


; Name:            
; Defined at line: 124
; #Upvalues:       0
; #Parameters:     2
; Is_vararg:       0
; Max Stack Size:  7

       0 [-]: LOADNIL R2   
       1 [-]: FASTCALL1 62 R0 L0
       2 [-]: MOVE R4 R0   
       3 [-]: GETIMPORT R3 1 [0x7B998233]
       4 [-]: CALL R3 1 1  
L 0:   5 [-]: JUMPIF R3 L3 
       6 [-]: JUMPXEQKS R0 K2 L3 [""]
       7 [-]: JUMPXEQKNIL R1 L1 NOT
       8 [-]: GETIMPORT R1 4 [0x89326C93]
L 1:   9 [-]: FASTCALL1 62 R1 L2
      10 [-]: MOVE R4 R1   
      11 [-]: GETIMPORT R3 1 [0x7B998233]
      12 [-]: CALL R3 1 1  
L 2:  13 [-]: JUMPIF R3 L3 
      14 [-]: GETIMPORT R5 6 [0x0469F296]
      15 [-]: MOVE R6 R0   
      16 [-]: CALL R5 1 -1 
      17 [-]: NAMECALL R3 R1 K7 [0x46A0EBF5]
      18 [-]: CALL R3 -1 1 
      19 [-]: MOVE R2 R3   
L 3:  20 [-]: RETURN R2 1  


; Name:            
; Defined at line: 139
; #Upvalues:       0
; #Parameters:     3
; Is_vararg:       0
; Max Stack Size:  8

       0 [-]: LOADNIL R3   
       1 [-]: JUMPIFNOT R0 L3
       2 [-]: JUMPXEQKS R0 K0 L3 [""]
       3 [-]: JUMPXEQKNIL R2 L0 NOT
       4 [-]: GETIMPORT R2 2 [0x89326C93]
L 0:   5 [-]: FASTCALL1 62 R2 L1
       6 [-]: MOVE R5 R2   
       7 [-]: GETIMPORT R4 4 [0x7B998233]
       8 [-]: CALL R4 1 1  
L 1:   9 [-]: JUMPIF R4 L3 
      10 [-]: JUMPXEQKNIL R1 L2 NOT
      11 [-]: GETIMPORT R6 6 [0x0469F296]
      12 [-]: MOVE R7 R0   
      13 [-]: CALL R6 1 -1 
      14 [-]: NAMECALL R4 R2 K7 [0x46A0EBF5]
      15 [-]: CALL R4 -1 1 
      16 [-]: MOVE R3 R4   
      17 [-]: RETURN R3 1  
L 2:  18 [-]: GETIMPORT R6 6 [0x0469F296]
      19 [-]: MOVE R7 R0   
      20 [-]: CALL R6 1 1  
      21 [-]: MOVE R7 R1   
      22 [-]: NAMECALL R4 R2 K8 [0xC7B81E8D]
      23 [-]: CALL R4 3 1  
      24 [-]: MOVE R3 R4   
L 3:  25 [-]: RETURN R3 1  


; Name:            
; Defined at line: 158
; #Upvalues:       0
; #Parameters:     1
; Is_vararg:       0
; Max Stack Size:  5

       0 [-]: LOADN R3 180 
       1 [-]: LOADK R4 K0 [3.1415927410125732]
       2 [-]: DIV R2 R3 R4 
       3 [-]: MUL R1 R2 R0 
       4 [-]: RETURN R1 1  


; Name:            
; Defined at line: 162
; #Upvalues:       0
; #Parameters:     1
; Is_vararg:       0
; Max Stack Size:  4

       0 [-]: LOADK R3 K1 [3.1415927410125732]
       1 [-]: DIVK R2 R3 K0 [180]
       2 [-]: MODK R3 R0 K2 [360]
       3 [-]: MUL R1 R2 R3 
       4 [-]: RETURN R1 1  


; Name:            
; Defined at line: 166
; #Upvalues:       0
; #Parameters:     1
; Is_vararg:       0
; Max Stack Size:  4

       0 [-]: LOADK R3 K1 [3.1415927410125732]
       1 [-]: DIVK R2 R3 K0 [180]
       2 [-]: MODK R3 R0 K2 [360]
       3 [-]: MUL R1 R2 R3 
       4 [-]: RETURN R1 1  


; Name:            
; Defined at line: 170
; #Upvalues:       0
; #Parameters:     2
; Is_vararg:       0
; Max Stack Size:  7

       0 [-]: GETTABLEKS R3 R1 K0 ["X"]
       1 [-]: GETTABLEKS R4 R0 K0 ["X"]
       2 [-]: SUB R2 R3 R4 
       3 [-]: GETTABLEKS R4 R1 K1 ["Y"]
       4 [-]: GETTABLEKS R5 R0 K1 ["Y"]
       5 [-]: SUB R3 R4 R5 
       6 [-]: MUL R5 R3 R3 
       7 [-]: MUL R6 R2 R2 
       8 [-]: ADD R4 R5 R6 
       9 [-]: RETURN R4 1  


; Name:            
; Defined at line: 176
; #Upvalues:       0
; #Parameters:     2
; Is_vararg:       0
; Max Stack Size:  8

       0 [-]: GETTABLEKS R3 R1 K0 ["X"]
       1 [-]: GETTABLEKS R4 R0 K0 ["X"]
       2 [-]: SUB R2 R3 R4 
       3 [-]: GETTABLEKS R4 R1 K1 ["Y"]
       4 [-]: GETTABLEKS R5 R0 K1 ["Y"]
       5 [-]: SUB R3 R4 R5 
       6 [-]: MUL R6 R3 R3 
       7 [-]: MUL R7 R2 R2 
       8 [-]: ADD R5 R6 R7 
       9 [-]: FASTCALL1 25 R5 L0
      10 [-]: GETIMPORT R4 4 [0x34E9F45C]
      11 [-]: CALL R4 1 1  
L 0:  12 [-]: RETURN R4 1  


; Name:            
; Defined at line: 182
; #Upvalues:       0
; #Parameters:     4
; Is_vararg:       0
; Max Stack Size:  10

       0 [-]: SUB R4 R2 R0 
       1 [-]: SUB R5 R3 R1 
       2 [-]: MUL R8 R5 R5 
       3 [-]: MUL R9 R4 R4 
       4 [-]: ADD R7 R8 R9 
       5 [-]: FASTCALL1 25 R7 L0
       6 [-]: GETIMPORT R6 2 [0x34E9F45C]
       7 [-]: CALL R6 1 1  
L 0:   8 [-]: RETURN R6 1  


; Name:            
; Defined at line: 188
; #Upvalues:       0
; #Parameters:     4
; Is_vararg:       0
; Max Stack Size:  9

       0 [-]: SUB R4 R2 R0 
       1 [-]: SUB R7 R3 R1 
       2 [-]: FASTCALL2 5 R4 R7 L0
       3 [-]: MOVE R6 R4   
       4 [-]: GETIMPORT R5 2 [0x1F2756B6]
       5 [-]: CALL R5 2 1  
L 0:   6 [-]: LOADN R6 0   
       7 [-]: JUMPIFNOTLT R4 R6 L1
       8 [-]: LOADK R7 K4 [3.1415927410125732]
       9 [-]: MULK R6 R7 K3 [2]
      10 [-]: ADD R5 R6 R5 
L 1:  11 [-]: LOADK R8 K4 [3.1415927410125732]
      12 [-]: MULK R7 R8 K3 [2]
      13 [-]: MOD R6 R5 R7 
      14 [-]: RETURN R6 1  


; Name:            
; Defined at line: 197
; #Upvalues:       0
; #Parameters:     4
; Is_vararg:       0
; Max Stack Size:  10

       0 [-]: GETIMPORT R4 1 [0x4FD57545]
       1 [-]: MOVE R5 R2   
       2 [-]: MOVE R6 R1   
       3 [-]: CALL R4 2 1  
       4 [-]: JUMPXEQKN R4 K2 L0 NOT [0]
       5 [-]: GETIMPORT R5 4 [0xA421AF95]
       6 [-]: CALL R5 0 -1 
       7 [-]: RETURN R5 -1 
L 0:   8 [-]: GETIMPORT R7 1 [0x4FD57545]
       9 [-]: MOVE R8 R2   
      10 [-]: MOVE R9 R0   
      11 [-]: CALL R7 2 1  
      12 [-]: SUB R6 R3 R7 
      13 [-]: DIV R5 R6 R4 
      14 [-]: MUL R7 R1 R5 
      15 [-]: ADD R6 R0 R7 
      16 [-]: RETURN R6 1  


; Name:            
; Defined at line: 210
; #Upvalues:       0
; #Parameters:     1
; Is_vararg:       0
; Max Stack Size:  7

       0 [-]: GETIMPORT R1 1 [0xA421AF95]
       1 [-]: LOADK R4 K2 ["_root"]
       2 [-]: LOADN R5 25  
       3 [-]: NAMECALL R2 R0 K3 [0x91A24E4B]
       4 [-]: CALL R2 3 1  
       5 [-]: LOADK R5 K2 ["_root"]
       6 [-]: LOADN R6 26  
       7 [-]: NAMECALL R3 R0 K3 [0x91A24E4B]
       8 [-]: CALL R3 3 1  
       9 [-]: LOADN R4 0   
      10 [-]: CALL R1 3 1  
      11 [-]: RETURN R1 1  


; Name:            
; Defined at line: 214
; #Upvalues:       0
; #Parameters:     2
; Is_vararg:       0
; Max Stack Size:  8

       0 [-]: JUMPIFNOT R1 L1
       1 [-]: LOADN R7 10  
       2 [-]: POW R6 R7 R1 
       3 [-]: MUL R5 R0 R6 
       4 [-]: ADDK R4 R5 K0 [0.5]
       5 [-]: FASTCALL1 12 R4 L0
       6 [-]: GETIMPORT R3 3 [0x55F27C30]
       7 [-]: CALL R3 1 1  
L 0:   8 [-]: LOADN R5 10  
       9 [-]: POW R4 R5 R1 
      10 [-]: DIV R2 R3 R4 
      11 [-]: RETURN R2 1  
L 1:  12 [-]: ADDK R3 R0 K0 [0.5]
      13 [-]: FASTCALL1 12 R3 L2
      14 [-]: GETIMPORT R2 3 [0x55F27C30]
      15 [-]: CALL R2 1 1  
L 2:  16 [-]: RETURN R2 1  


; Name:            
; Defined at line: 222
; #Upvalues:       0
; #Parameters:     2
; Is_vararg:       0
; Max Stack Size:  9

       0 [-]: GETIMPORT R2 1 [0x03F57322]
       1 [-]: MOVE R3 R0   
       2 [-]: CALL R2 1 1  
       3 [-]: LOADK R3 K2 [1000000]
       4 [-]: JUMPIFNOTLT R2 R3 L3
       5 [-]: JUMPIFNOT R1 L1
       6 [-]: LOADN R7 10  
       7 [-]: POW R6 R7 R1 
       8 [-]: MUL R5 R0 R6 
       9 [-]: ADDK R4 R5 K3 [0.5]
      10 [-]: FASTCALL1 12 R4 L0
      11 [-]: GETIMPORT R3 6 [0x55F27C30]
      12 [-]: CALL R3 1 1  
L 0:  13 [-]: LOADN R5 10  
      14 [-]: POW R4 R5 R1 
      15 [-]: DIV R2 R3 R4 
      16 [-]: RETURN R2 1  
L 1:  17 [-]: ADDK R3 R0 K3 [0.5]
      18 [-]: FASTCALL1 12 R3 L2
      19 [-]: GETIMPORT R2 6 [0x55F27C30]
      20 [-]: CALL R2 1 1  
L 2:  21 [-]: RETURN R2 1  
      22 [-]: RETURN R2 1  
L 3:  23 [-]: DIVK R3 R0 K2 [1000000]
      24 [-]: FASTCALL1 12 R3 L4
      25 [-]: GETIMPORT R2 6 [0x55F27C30]
      26 [-]: CALL R2 1 1  
L 4:  27 [-]: MODK R3 R0 K2 [1000000]
      28 [-]: JUMPIFNOT R1 L6
      29 [-]: LOADN R8 10  
      30 [-]: POW R7 R8 R1 
      31 [-]: MUL R6 R3 R7 
      32 [-]: ADDK R5 R6 K3 [0.5]
      33 [-]: FASTCALL1 12 R5 L5
      34 [-]: GETIMPORT R4 6 [0x55F27C30]
      35 [-]: CALL R4 1 1  
L 5:  36 [-]: LOADN R6 10  
      37 [-]: POW R5 R6 R1 
      38 [-]: DIV R3 R4 R5 
      39 [-]: JUMP L8
     
L 6:  40 [-]: ADDK R5 R3 K3 [0.5]
      41 [-]: FASTCALL1 12 R5 L7
      42 [-]: GETIMPORT R4 6 [0x55F27C30]
      43 [-]: CALL R4 1 1  
L 7:  44 [-]: MOVE R3 R4   
L 8:  45 [-]: LOADK R4 K2 [1000000]
      46 [-]: JUMPIFNOTLT R4 R3 L10
      47 [-]: DIVK R5 R3 K2 [1000000]
      48 [-]: FASTCALL1 12 R5 L9
      49 [-]: GETIMPORT R4 6 [0x55F27C30]
      50 [-]: CALL R4 1 1  
L 9:  51 [-]: ADD R2 R2 R4 
      52 [-]: MODK R3 R3 K2 [1000000]
L10:  53 [-]: GETIMPORT R4 9 [0xE8072DED]
      54 [-]: LOADK R5 K10 ["%d%06d"]
      55 [-]: MOVE R6 R2   
      56 [-]: MOVE R7 R3   
      57 [-]: CALL R4 3 1  
      58 [-]: RETURN R4 1  


; Name:            
; Defined at line: 242
; #Upvalues:       0
; #Parameters:     2
; Is_vararg:       0
; Max Stack Size:  8

       0 [-]: JUMPIFNOT R1 L1
       1 [-]: LOADN R7 10  
       2 [-]: POW R6 R7 R1 
       3 [-]: MUL R5 R0 R6 
       4 [-]: ADDK R4 R5 K0 [0.5]
       5 [-]: FASTCALL1 12 R4 L0
       6 [-]: GETIMPORT R3 3 [0x55F27C30]
       7 [-]: CALL R3 1 1  
L 0:   8 [-]: LOADN R5 10  
       9 [-]: POW R4 R5 R1 
      10 [-]: DIV R2 R3 R4 
      11 [-]: RETURN R2 1  
L 1:  12 [-]: ADDK R3 R0 K0 [0.5]
      13 [-]: FASTCALL1 12 R3 L2
      14 [-]: GETIMPORT R2 3 [0x55F27C30]
      15 [-]: CALL R2 1 1  
L 2:  16 [-]: RETURN R2 1  
      17 [-]: RETURN R2 1  


; Name:            
; Defined at line: 246
; #Upvalues:       0
; #Parameters:     1
; Is_vararg:       0
; Max Stack Size:  3

       0 [-]: GETIMPORT R1 1 [0x03F57322]
       1 [-]: MOVE R2 R0   
       2 [-]: CALL R1 1 1  
       3 [-]: MOVE R0 R1   
       4 [-]: LOADB R1 0   
       5 [-]: LOADN R2 7   
       6 [-]: JUMPIFNOTLE R2 R0 L1
       7 [-]: LOADN R2 11  
       8 [-]: JUMPIFLT R0 R2 L0
       9 [-]: LOADB R1 0 +1
L 0:  10 [-]: LOADB R1 1   
L 1:  11 [-]: RETURN R1 1  


; Name:            
; Defined at line: 254
; #Upvalues:       0
; #Parameters:     3
; Is_vararg:       0
; Max Stack Size:  8

       0 [-]: GETIMPORT R3 2 [0xE8072DED]
       1 [-]: LOADK R4 K3 ["%02X%02X%02X"]
       2 [-]: MOVE R5 R0   
       3 [-]: MOVE R6 R1   
       4 [-]: MOVE R7 R2   
       5 [-]: CALL R3 4 -1 
       6 [-]: RETURN R3 -1 


; Name:            
; Defined at line: 258
; #Upvalues:       0
; #Parameters:     3
; Is_vararg:       0
; Max Stack Size:  8

       0 [-]: GETIMPORT R3 2 [0xE8072DED]
       1 [-]: LOADK R4 K3 ["%02X%02X%02X"]
       2 [-]: MOVE R5 R0   
       3 [-]: MOVE R6 R1   
       4 [-]: MOVE R7 R2   
       5 [-]: CALL R3 4 1  
       6 [-]: RETURN R3 1  


; Name:            
; Defined at line: 262
; #Upvalues:       0
; #Parameters:     1
; Is_vararg:       0
; Max Stack Size:  5

       0 [-]: DIVK R2 R0 K1 [65536]
       1 [-]: MODK R1 R2 K0 [256]
       2 [-]: DIVK R3 R0 K0 [256]
       3 [-]: MODK R2 R3 K0 [256]
       4 [-]: DIVK R4 R0 K2 [1]
       5 [-]: MODK R3 R4 K0 [256]
       6 [-]: DUPTABLE R4 6
       7 [-]: SETTABLEKS R1 R4 K3 ["r"]
       8 [-]: SETTABLEKS R2 R4 K4 ["g"]
       9 [-]: SETTABLEKS R3 R4 K5 ["b"]
      10 [-]: RETURN R4 1  


; Name:            
; Defined at line: 269
; #Upvalues:       0
; #Parameters:     1
; Is_vararg:       0
; Max Stack Size:  6

       0 [-]: DIVK R3 R0 K1 [65536]
       1 [-]: MODK R2 R3 K0 [256]
       2 [-]: DIVK R4 R0 K0 [256]
       3 [-]: MODK R3 R4 K0 [256]
       4 [-]: DIVK R5 R0 K2 [1]
       5 [-]: MODK R4 R5 K0 [256]
       6 [-]: DUPTABLE R1 6
       7 [-]: SETTABLEKS R2 R1 K3 ["r"]
       8 [-]: SETTABLEKS R3 R1 K4 ["g"]
       9 [-]: SETTABLEKS R4 R1 K5 ["b"]
      10 [-]: RETURN R1 1  


; Name:            
; Defined at line: 274
; #Upvalues:       0
; #Parameters:     3
; Is_vararg:       0
; Max Stack Size:  20

       0 [-]: DIVK R4 R0 K1 [65536]
       1 [-]: MODK R3 R4 K0 [256]
       2 [-]: DIVK R5 R0 K0 [256]
       3 [-]: MODK R4 R5 K0 [256]
       4 [-]: DIVK R6 R0 K2 [1]
       5 [-]: MODK R5 R6 K0 [256]
       6 [-]: DIVK R7 R1 K1 [65536]
       7 [-]: MODK R6 R7 K0 [256]
       8 [-]: DIVK R8 R1 K0 [256]
       9 [-]: MODK R7 R8 K0 [256]
      10 [-]: DIVK R9 R1 K2 [1]
      11 [-]: MODK R8 R9 K0 [256]
      12 [-]: GETIMPORT R9 4 [0x42DCC9F5]
      13 [-]: SUB R12 R6 R3
      14 [-]: MUL R11 R2 R12
      15 [-]: ADD R10 R3 R11
      16 [-]: LOADN R11 0  
      17 [-]: LOADN R12 255
      18 [-]: CALL R9 3 1  
      19 [-]: GETIMPORT R10 4 [0x42DCC9F5]
      20 [-]: SUB R13 R7 R4
      21 [-]: MUL R12 R2 R13
      22 [-]: ADD R11 R4 R12
      23 [-]: LOADN R12 0  
      24 [-]: LOADN R13 255
      25 [-]: CALL R10 3 1 
      26 [-]: GETIMPORT R11 4 [0x42DCC9F5]
      27 [-]: SUB R14 R8 R5
      28 [-]: MUL R13 R2 R14
      29 [-]: ADD R12 R5 R13
      30 [-]: LOADN R13 0  
      31 [-]: LOADN R14 255
      32 [-]: CALL R11 3 1 
      33 [-]: GETIMPORT R12 6 [0x03F57322]
      34 [-]: LOADK R14 K7 ["0x"]
      35 [-]: GETIMPORT R15 10 [0xE8072DED]
      36 [-]: LOADK R16 K11 ["%02X%02X%02X"]
      37 [-]: MOVE R17 R9  
      38 [-]: MOVE R18 R10 
      39 [-]: MOVE R19 R11 
      40 [-]: CALL R15 4 1 
      41 [-]: CONCAT R13 R14 R15
      42 [-]: CALL R12 1 -1
      43 [-]: RETURN R12 -1


; Name:            
; Defined at line: 290
; #Upvalues:       0
; #Parameters:     3
; Is_vararg:       0
; Max Stack Size:  16

       0 [-]: LOADN R3 0   
       1 [-]: LOADN R4 0   
       2 [-]: LOADN R5 0   
       3 [-]: JUMPXEQKN R1 K0 L0 NOT [0]
       4 [-]: MOVE R3 R2   
       5 [-]: MOVE R4 R2   
       6 [-]: MOVE R5 R2   
       7 [-]: JUMP L9
     
L 0:   8 [-]: JUMPXEQKN R0 K1 L1 NOT [360]
       9 [-]: LOADN R0 0   
L 1:  10 [-]: DIVK R7 R0 K2 [60]
      11 [-]: FASTCALL1 12 R7 L2
      12 [-]: GETIMPORT R6 5 [0x55F27C30]
      13 [-]: CALL R6 1 1  
L 2:  14 [-]: DIVK R8 R0 K2 [60]
      15 [-]: SUB R7 R8 R6 
      16 [-]: LOADN R10 1  
      17 [-]: SUB R9 R10 R1
      18 [-]: MUL R8 R2 R9 
      19 [-]: LOADN R11 1  
      20 [-]: MUL R12 R1 R7
      21 [-]: SUB R10 R11 R12
      22 [-]: MUL R9 R2 R10
      23 [-]: LOADN R12 1  
      24 [-]: LOADN R15 1  
      25 [-]: SUB R14 R15 R7
      26 [-]: MUL R13 R1 R14
      27 [-]: SUB R11 R12 R13
      28 [-]: MUL R10 R2 R11
      29 [-]: JUMPXEQKN R6 K0 L3 NOT [0]
      30 [-]: MOVE R3 R2   
      31 [-]: MOVE R4 R10  
      32 [-]: MOVE R5 R8   
      33 [-]: JUMP L9
     
L 3:  34 [-]: JUMPXEQKN R6 K6 L4 NOT [1]
      35 [-]: MOVE R3 R9   
      36 [-]: MOVE R4 R2   
      37 [-]: MOVE R5 R8   
      38 [-]: JUMP L9
     
L 4:  39 [-]: JUMPXEQKN R6 K7 L5 NOT [2]
      40 [-]: MOVE R3 R8   
      41 [-]: MOVE R4 R2   
      42 [-]: MOVE R5 R10  
      43 [-]: JUMP L9
     
L 5:  44 [-]: JUMPXEQKN R6 K8 L6 NOT [3]
      45 [-]: MOVE R3 R8   
      46 [-]: MOVE R4 R9   
      47 [-]: MOVE R5 R2   
      48 [-]: JUMP L9
     
L 6:  49 [-]: JUMPXEQKN R6 K9 L7 NOT [4]
      50 [-]: MOVE R3 R10  
      51 [-]: MOVE R4 R8   
      52 [-]: MOVE R5 R2   
      53 [-]: JUMP L9
     
L 7:  54 [-]: JUMPXEQKN R6 K10 L8 NOT [5]
      55 [-]: MOVE R3 R2   
      56 [-]: MOVE R4 R8   
      57 [-]: MOVE R5 R9   
      58 [-]: JUMP L9
     
L 8:  59 [-]: LOADN R3 0   
      60 [-]: LOADN R4 0   
      61 [-]: LOADN R5 0   
L 9:  62 [-]: MULK R6 R3 K11 [255]
      63 [-]: MULK R7 R4 K11 [255]
      64 [-]: MULK R8 R5 K11 [255]
      65 [-]: GETIMPORT R9 14 [0xE8072DED]
      66 [-]: LOADK R10 K15 ["%02X%02X%02X"]
      67 [-]: MOVE R11 R6  
      68 [-]: MOVE R12 R7  
      69 [-]: MOVE R13 R8  
      70 [-]: CALL R9 4 1  
      71 [-]: RETURN R9 1  


; Name:            
; Defined at line: 349
; #Upvalues:       0
; #Parameters:     1
; Is_vararg:       0
; Max Stack Size:  9

       0 [-]: GETIMPORT R1 1 [0x89326C93]
       1 [-]: NAMECALL R1 R1 K2 [0x2F57AF72]
       2 [-]: CALL R1 1 1  
       3 [-]: FASTCALL1 62 R1 L0
       4 [-]: MOVE R3 R1   
       5 [-]: GETIMPORT R2 4 [0x7B998233]
       6 [-]: CALL R2 1 1  
L 0:   7 [-]: JUMPIF R2 L4 
       8 [-]: GETIMPORT R2 6 [0xC8802016]
       9 [-]: MOVE R3 R1   
      10 [-]: CALL R2 1 3  
      11 [-]: FORGPREP_INEXT R2 L3
L 1:  12 [-]: FASTCALL1 62 R6 L2
      13 [-]: MOVE R8 R6   
      14 [-]: GETIMPORT R7 4 [0x7B998233]
      15 [-]: CALL R7 1 1  
L 2:  16 [-]: JUMPIF R7 L3 
      17 [-]: MOVE R7 R0   
      18 [-]: MOVE R8 R6   
      19 [-]: CALL R7 1 0  
L 3:  20 [-]: FORGLOOP R2 L1 2 [inext]
L 4:  21 [-]: RETURN R0 0  


; Name:            
; Defined at line: 360
; #Upvalues:       0
; #Parameters:     1
; Is_vararg:       0
; Max Stack Size:  17

       0 [-]: FASTCALL1 62 R0 L0
       1 [-]: MOVE R2 R0   
       2 [-]: GETIMPORT R1 1 [0x7B998233]
       3 [-]: CALL R1 1 1  
L 0:   4 [-]: JUMPIFNOT R1 L1
       5 [-]: GETIMPORT R1 3 [0x3D106989]
       6 [-]: LOADK R2 K4 ["------- Empty Table -----"]
       7 [-]: CALL R1 1 0  
       8 [-]: RETURN R0 0  
L 1:   9 [-]: GETIMPORT R1 3 [0x3D106989]
      10 [-]: LOADK R2 K5 ["-------------------------"]
      11 [-]: CALL R1 1 0  
      12 [-]: GETIMPORT R1 7 [0xCFC01047]
      13 [-]: MOVE R2 R0   
      14 [-]: CALL R1 1 3  
      15 [-]: FORGPREP_NEXT R1 L4
L 2:  16 [-]: GETIMPORT R6 3 [0x3D106989]
      17 [-]: LOADK R8 K8 ["["]
      18 [-]: GETIMPORT R15 10 [0x64FB1586]
      19 [-]: MOVE R16 R4  
      20 [-]: CALL R15 1 1 
      21 [-]: MOVE R9 R15  
      22 [-]: LOADK R10 K11 ["]->"]
      23 [-]: GETIMPORT R15 10 [0x64FB1586]
      24 [-]: MOVE R16 R5  
      25 [-]: CALL R15 1 1 
      26 [-]: MOVE R11 R15 
      27 [-]: LOADK R12 K12 ["("]
      28 [-]: FASTCALL1 40 R5 L3
      29 [-]: MOVE R16 R5  
      30 [-]: GETIMPORT R15 14 [0x0B96777E]
      31 [-]: CALL R15 1 1 
L 3:  32 [-]: MOVE R13 R15 
      33 [-]: LOADK R14 K15 [")"]
      34 [-]: CONCAT R7 R8 R14
      35 [-]: CALL R6 1 0  
L 4:  36 [-]: FORGLOOP R1 L2 2
      37 [-]: GETIMPORT R1 3 [0x3D106989]
      38 [-]: LOADK R2 K5 ["-------------------------"]
      39 [-]: CALL R1 1 0  
      40 [-]: RETURN R0 0  


; Name:            
; Defined at line: 398
; #Upvalues:       2
; #Parameters:     0
; Is_vararg:       0
; Max Stack Size:  4

       0 [-]: GETUPVAL R1 0
       1 [-]: FASTCALL1 62 R1 L0
       2 [-]: GETIMPORT R0 1 [0x7B998233]
       3 [-]: CALL R0 1 1  
L 0:   4 [-]: JUMPIFNOT R0 L2
       5 [-]: GETIMPORT R0 3 [0x76EA806B]
       6 [-]: LOADN R2 0   
       7 [-]: NAMECALL R0 R0 K4 [0x3F3AE64C]
       8 [-]: CALL R0 2 1  
       9 [-]: FASTCALL1 62 R0 L1
      10 [-]: MOVE R2 R0   
      11 [-]: GETIMPORT R1 1 [0x7B998233]
      12 [-]: CALL R1 1 1  
L 1:  13 [-]: JUMPIF R1 L2 
      14 [-]: NAMECALL R1 R0 K5 [0x40E9C32B]
      15 [-]: CALL R1 1 1  
      16 [-]: SETUPVAL R1 0
L 2:  17 [-]: GETUPVAL R1 0
      18 [-]: FASTCALL1 62 R1 L3
      19 [-]: GETIMPORT R0 1 [0x7B998233]
      20 [-]: CALL R0 1 1  
L 3:  21 [-]: JUMPIF R0 L4 
      22 [-]: GETUPVAL R0 0
      23 [-]: NAMECALL R0 R0 K6 [0x2C10B42D]
      24 [-]: CALL R0 1 1  
      25 [-]: JUMPXEQKN R0 K7 L4 [0]
      26 [-]: RETURN R0 1  
L 4:  27 [-]: GETUPVAL R1 1
      28 [-]: GETIMPORT R2 9 [0x67513231]
      29 [-]: CALL R2 0 1  
      30 [-]: NAMECALL R2 R2 K10 [0x6D604BA7]
      31 [-]: CALL R2 1 1  
      32 [-]: GETTABLE R0 R1 R2
      33 [-]: RETURN R0 1  


; Name:            
; Defined at line: 414
; #Upvalues:       1
; #Parameters:     0
; Is_vararg:       0
; Max Stack Size:  1

       0 [-]: GETUPVAL R0 0
       1 [-]: CALL R0 0 1  
       2 [-]: RETURN R0 1  


; Name:            
; Defined at line: 418
; #Upvalues:       2
; #Parameters:     0
; Is_vararg:       0
; Max Stack Size:  3

       0 [-]: GETUPVAL R1 0
       1 [-]: GETUPVAL R2 1
       2 [-]: CALL R2 0 1  
       3 [-]: GETTABLE R0 R1 R2
       4 [-]: RETURN R0 1  


; Name:            
; Defined at line: 422
; #Upvalues:       2
; #Parameters:     0
; Is_vararg:       0
; Max Stack Size:  4

       0 [-]: GETUPVAL R2 0
       1 [-]: GETUPVAL R3 1
       2 [-]: CALL R3 0 1  
       3 [-]: GETTABLE R1 R2 R3
       4 [-]: GETTABLEKS R0 R1 K0 ["Thousands"]
       5 [-]: RETURN R0 1  


; Name:            
; Defined at line: 426
; #Upvalues:       2
; #Parameters:     1
; Is_vararg:       0
; Max Stack Size:  5

       0 [-]: JUMPIFNOT R0 L0
       1 [-]: LOADK R1 K0 ["."]
       2 [-]: RETURN R1 1  
L 0:   3 [-]: GETUPVAL R3 0
       4 [-]: GETUPVAL R4 1
       5 [-]: CALL R4 0 1  
       6 [-]: GETTABLE R2 R3 R4
       7 [-]: GETTABLEKS R1 R2 K1 ["Decimal"]
       8 [-]: RETURN R1 1  


; Name:            
; Defined at line: 433
; #Upvalues:       2
; #Parameters:     2
; Is_vararg:       0
; Max Stack Size:  13

       0 [-]: JUMPIFNOT R1 L0
       1 [-]: RETURN R0 1  
L 0:   2 [-]: LOADNIL R2   
L 1:   3 [-]: GETIMPORT R3 2 [0x66EDF04F]
       4 [-]: MOVE R4 R0   
       5 [-]: LOADK R5 K3 ["^(-?%d+)(%d%d%d)"]
       6 [-]: LOADK R7 K4 ["%1"]
       7 [-]: GETUPVAL R11 0
       8 [-]: GETUPVAL R12 1
       9 [-]: CALL R12 0 1 
      10 [-]: GETTABLE R10 R11 R12
      11 [-]: GETTABLEKS R8 R10 K5 ["Thousands"]
      12 [-]: LOADK R9 K6 ["%2"]
      13 [-]: CONCAT R6 R7 R9
      14 [-]: CALL R3 3 2  
      15 [-]: MOVE R0 R3   
      16 [-]: MOVE R2 R4   
      17 [-]: JUMPXEQKN R2 K7 L2 [0]
      18 [-]: JUMPBACK L1  
L 2:  19 [-]: RETURN R0 1  


; Name:            
; Defined at line: 447
; #Upvalues:       1
; #Parameters:     1
; Is_vararg:       0
; Max Stack Size:  3

       0 [-]: GETUPVAL R1 0
       1 [-]: MOVE R2 R0   
       2 [-]: CALL R1 1 1  
       3 [-]: RETURN R1 1  


; Name:            
; Defined at line: 451
; #Upvalues:       4
; #Parameters:     5
; Is_vararg:       0
; Max Stack Size:  16

       0 [-]: JUMPXEQKNIL R1 L0 NOT
       1 [-]: LOADN R1 0   
L 0:   2 [-]: JUMPXEQKNIL R2 L1 NOT
       3 [-]: LOADB R2 1   
L 1:   4 [-]: JUMPXEQKNIL R3 L2 NOT
       5 [-]: LOADB R3 0   
L 2:   6 [-]: LOADN R5 0   
       7 [-]: JUMPIFNOTLE R1 R5 L3
       8 [-]: GETUPVAL R5 0
       9 [-]: MOVE R6 R0   
      10 [-]: LOADNIL R7   
      11 [-]: CALL R5 2 1  
      12 [-]: GETUPVAL R6 1
      13 [-]: GETIMPORT R7 2 [0xE8072DED]
      14 [-]: LOADK R8 K3 ["%.0f"]
      15 [-]: MOVE R9 R5   
      16 [-]: CALL R7 2 1  
      17 [-]: MOVE R8 R4   
      18 [-]: CALL R6 2 1  
      19 [-]: RETURN R6 1  
L 3:  20 [-]: JUMPIFNOT R3 L5
      21 [-]: LOADN R6 10  
      22 [-]: POW R5 R6 R1 
      23 [-]: MUL R7 R0 R5 
      24 [-]: FASTCALL1 12 R7 L4
      25 [-]: GETIMPORT R6 6 [0x55F27C30]
      26 [-]: CALL R6 1 1  
L 4:  27 [-]: DIV R0 R6 R5 
L 5:  28 [-]: GETIMPORT R5 2 [0xE8072DED]
      29 [-]: LOADK R6 K7 ["%%0.%df"]
      30 [-]: MOVE R7 R1   
      31 [-]: CALL R5 2 1  
      32 [-]: GETIMPORT R6 2 [0xE8072DED]
      33 [-]: MOVE R7 R5   
      34 [-]: MOVE R8 R0   
      35 [-]: CALL R6 2 1  
      36 [-]: GETIMPORT R7 9 [0xA5C556B9]
      37 [-]: MOVE R8 R6   
      38 [-]: LOADK R9 K10 ["%."]
      39 [-]: CALL R7 2 1  
      40 [-]: LOADNIL R8   
      41 [-]: LOADNIL R9   
      42 [-]: JUMPXEQKNIL R7 L6 NOT
      43 [-]: MOVE R8 R6   
      44 [-]: LOADK R9 K11 [""]
      45 [-]: JUMP L9
     
L 6:  46 [-]: MOVE R11 R6  
      47 [-]: LOADN R12 1  
      48 [-]: SUBK R13 R7 K12 [1]
      49 [-]: FASTCALL 45 L7
      50 [-]: GETIMPORT R10 14 [0x1A94C9CC]
      51 [-]: CALL R10 3 1 
L 7:  52 [-]: MOVE R8 R10  
      53 [-]: ADDK R12 R7 K12 [1]
      54 [-]: FASTCALL2 45 R6 R12 L8
      55 [-]: MOVE R11 R6  
      56 [-]: GETIMPORT R10 14 [0x1A94C9CC]
      57 [-]: CALL R10 2 1 
L 8:  58 [-]: MOVE R9 R10  
L 9:  59 [-]: GETUPVAL R10 1
      60 [-]: MOVE R11 R8  
      61 [-]: MOVE R12 R4  
      62 [-]: CALL R10 2 1 
      63 [-]: MOVE R8 R10  
      64 [-]: JUMPXEQKNIL R7 L10
      65 [-]: JUMPIF R2 L10
      66 [-]: GETIMPORT R10 16 [0x66EDF04F]
      67 [-]: MOVE R11 R9  
      68 [-]: LOADK R12 K17 ["0*$"]
      69 [-]: LOADK R13 K11 [""]
      70 [-]: CALL R10 3 1 
      71 [-]: MOVE R9 R10  
L10:  72 [-]: JUMPXEQKS R9 K11 L13 [""]
      73 [-]: MOVE R10 R8  
      74 [-]: JUMPIFNOT R4 L11
      75 [-]: LOADK R11 K18 ["."]
      76 [-]: JUMP L12
    
L11:  77 [-]: GETUPVAL R14 2
      78 [-]: GETUPVAL R15 3
      79 [-]: CALL R15 0 1 
      80 [-]: GETTABLE R13 R14 R15
      81 [-]: GETTABLEKS R11 R13 K19 ["Decimal"]
L12:  82 [-]: MOVE R12 R9  
      83 [-]: CONCAT R6 R10 R12
      84 [-]: RETURN R6 1  
L13:  85 [-]: MOVE R6 R8   
      86 [-]: RETURN R6 1  


; Name:            
; Defined at line: 509
; #Upvalues:       0
; #Parameters:     1
; Is_vararg:       0
; Max Stack Size:  10

       0 [-]: LOADNIL R1   
       1 [-]: LOADNIL R2   
       2 [-]: ADDK R4 R0 K0 [0.5]
       3 [-]: FASTCALL1 12 R4 L0
       4 [-]: GETIMPORT R3 3 [0x55F27C30]
       5 [-]: CALL R3 1 1  
L 0:   6 [-]: LOADN R4 10000
       7 [-]: JUMPIFNOTLT R3 R4 L1
       8 [-]: LOADK R1 K4 ["%.0f"]
       9 [-]: LOADK R2 K5 [""]
      10 [-]: JUMP L3
     
L 1:  11 [-]: MULK R3 R0 K6 [0.001]
      12 [-]: LOADK R4 K7 [999.5]
      13 [-]: JUMPIFNOTLT R3 R4 L2
      14 [-]: LOADK R1 K8 ["%.3g"]
      15 [-]: LOADK R2 K9 ["K"]
      16 [-]: JUMP L3
     
L 2:  17 [-]: MULK R3 R0 K10 [9.9999999999999995e-07]
      18 [-]: LOADK R1 K8 ["%.3g"]
      19 [-]: LOADK R2 K11 ["M"]
L 3:  20 [-]: GETIMPORT R7 14 [0xE8072DED]
      21 [-]: MOVE R8 R1   
      22 [-]: MOVE R9 R3   
      23 [-]: CALL R7 2 1  
      24 [-]: MOVE R5 R7   
      25 [-]: MOVE R6 R2   
      26 [-]: CONCAT R4 R5 R6
      27 [-]: RETURN R4 1  


; Name:            
; Defined at line: 535
; #Upvalues:       1
; #Parameters:     8
; Is_vararg:       0
; Max Stack Size:  21

       0 [-]: FASTCALL1 62 R0 L0
       1 [-]: MOVE R9 R0   
       2 [-]: GETIMPORT R8 1 [0x7B998233]
       3 [-]: CALL R8 1 1  
L 0:   4 [-]: JUMPIFNOT R8 L2
       5 [-]: JUMPIFNOT R4 L1
       6 [-]: MOVE R8 R4   
       7 [-]: CALL R8 0 0  
L 1:   8 [-]: CLOSEUPVALS R5
       9 [-]: RETURN R0 0  
L 2:  10 [-]: JUMPXEQKNIL R5 L3 NOT
      11 [-]: LOADN R5 1   
L 3:  12 [-]: JUMPXEQKNIL R6 L4 NOT
      13 [-]: LOADN R6 0   
L 4:  14 [-]: MOVE R10 R2  
      15 [-]: LOADN R11 68 
      16 [-]: NAMECALL R8 R0 K2 [0x91A24E4B]
      17 [-]: CALL R8 3 1  
      18 [-]: JUMPXEQKNIL R8 L5 NOT
      19 [-]: LOADN R8 0   
L 5:  20 [-]: MOVE R11 R2  
      21 [-]: LOADN R12 29 
      22 [-]: MOVE R13 R3  
      23 [-]: NAMECALL R9 R0 K3 [0x5F56EEAB]
      24 [-]: CALL R9 4 0  
      25 [-]: MOVE R11 R2  
      26 [-]: LOADN R12 33 
      27 [-]: NAMECALL R9 R0 K2 [0x91A24E4B]
      28 [-]: CALL R9 3 1  
      29 [-]: LOADN R10 0  
      30 [-]: JUMPIFNOTLT R10 R5 L6
      31 [-]: MOVE R12 R2  
      32 [-]: LOADN R13 64 
      33 [-]: LOADN R14 0  
      34 [-]: NAMECALL R10 R0 K4 [0x67BC869F]
      35 [-]: CALL R10 4 0 
L 6:  36 [-]: NEWCLOSURE R10 P0
      37 [-]: MOVE R1 R5   
      38 [-]: MOVE R0 R0   
      39 [-]: MOVE R0 R2   
      40 [-]: MOVE R2 R0   
      41 [-]: MOVE R0 R1   
      42 [-]: MOVE R0 R7   
      43 [-]: LOADK R12 K5 [0.34999999999999998]
      44 [-]: LOADK R15 K6 [0.012500000000000001]
      45 [-]: FASTCALL1 2 R5 L7
      46 [-]: MOVE R17 R5  
      47 [-]: GETIMPORT R16 9 [0xE4A5B3CA]
      48 [-]: CALL R16 1 1 
L 7:  49 [-]: MUL R14 R15 R16
      50 [-]: MUL R13 R14 R8
      51 [-]: FASTCALL2 18 R12 R13 L8
      52 [-]: GETIMPORT R11 11 [0xB62ECFE0]
      53 [-]: CALL R11 2 1 
L 8:  54 [-]: GETIMPORT R12 13 [0x25312C9B]
      55 [-]: MOVE R13 R0  
      56 [-]: MOVE R14 R2  
      57 [-]: LOADN R15 0  
      58 [-]: NEWTABLE R16 0 1
      59 [-]: MOVE R17 R10 
      60 [-]: SETLIST R16 R17 1 [1]
      61 [-]: NEWTABLE R17 0 1
      62 [-]: LOADN R18 1  
      63 [-]: SETLIST R17 R18 1 [1]
      64 [-]: MOVE R18 R11 
      65 [-]: MOVE R19 R6  
      66 [-]: MOVE R20 R4  
      67 [-]: CALL R12 8 0 
      68 [-]: CLOSEUPVALS R5
      69 [-]: RETURN R9 1  


; Name:            
; Defined at line: 588
; #Upvalues:       0
; #Parameters:     3
; Is_vararg:       0
; Max Stack Size:  5

       0 [-]: NEWTABLE R3 8 0
       1 [-]: SETTABLEKS R0 R3 K0 ["mValue"]
       2 [-]: SETTABLEKS R1 R3 K1 ["mOnChangeFunc"]
       3 [-]: SETTABLEKS R2 R3 K2 ["mCompareFunc"]
       4 [-]: DUPCLOSURE R4 K3 []
       5 [-]: SETTABLEKS R4 R3 K4 ["Set"]
       6 [-]: DUPCLOSURE R4 K5 []
       7 [-]: SETTABLEKS R4 R3 K6 ["Get"]
       8 [-]: RETURN R3 1  


; Name:            
; Defined at line: 614
; #Upvalues:       0
; #Parameters:     1
; Is_vararg:       0
; Max Stack Size:  3

       0 [-]: NEWTABLE R1 4 0
       1 [-]: GETIMPORT R2 2 [0x1467D5F4]
       2 [-]: CALL R2 0 1  
       3 [-]: SETTABLEKS R2 R1 K3 ["mValue"]
       4 [-]: SETTABLEKS R0 R1 K4 ["mOnChangeFunc"]
       5 [-]: DUPCLOSURE R2 K5 []
       6 [-]: SETTABLEKS R2 R1 K6 ["Update"]
       7 [-]: RETURN R1 1  


; Name:            
; Defined at line: 631
; #Upvalues:       0
; #Parameters:     3
; Is_vararg:       0
; Max Stack Size:  9

       0 [-]: JUMPXEQKNIL R2 L0 NOT
       1 [-]: LOADK R2 K0 [""]
L 0:   2 [-]: MOVE R5 R1   
       3 [-]: LOADN R6 12  
       4 [-]: NAMECALL R3 R0 K1 [0x91A24E4B]
       5 [-]: CALL R3 3 1  
       6 [-]: MOVE R6 R1   
       7 [-]: LOADN R7 82  
       8 [-]: MOVE R8 R2   
       9 [-]: NAMECALL R4 R0 K2 [0x5F56EEAB]
      10 [-]: CALL R4 4 0  
      11 [-]: MOVE R6 R1   
      12 [-]: LOADN R7 79  
      13 [-]: MOVE R8 R3   
      14 [-]: NAMECALL R4 R0 K3 [0x67BC869F]
      15 [-]: CALL R4 4 0  
      16 [-]: RETURN R0 0  


; Name:            
; Defined at line: 644
; #Upvalues:       0
; #Parameters:     4
; Is_vararg:       0
; Max Stack Size:  10

       0 [-]: JUMPXEQKNIL R3 L0 NOT
       1 [-]: LOADK R3 K0 [""]
L 0:   2 [-]: MOVE R6 R1   
       3 [-]: LOADN R7 12  
       4 [-]: NAMECALL R4 R0 K1 [0x91A24E4B]
       5 [-]: CALL R4 3 1  
       6 [-]: MOVE R7 R1   
       7 [-]: LOADN R8 82  
       8 [-]: MOVE R9 R3   
       9 [-]: NAMECALL R5 R0 K2 [0x5F56EEAB]
      10 [-]: CALL R5 4 0  
      11 [-]: MOVE R7 R1   
      12 [-]: LOADN R8 79  
      13 [-]: MOVE R9 R4   
      14 [-]: NAMECALL R5 R0 K3 [0x67BC869F]
      15 [-]: CALL R5 4 0  
      16 [-]: MOVE R7 R1   
      17 [-]: LOADN R8 29  
      18 [-]: MOVE R9 R2   
      19 [-]: NAMECALL R5 R0 K2 [0x5F56EEAB]
      20 [-]: CALL R5 4 0  
      21 [-]: RETURN R0 0  


; Name:            
; Defined at line: 658
; #Upvalues:       0
; #Parameters:     5
; Is_vararg:       0
; Max Stack Size:  10

       0 [-]: JUMPXEQKNIL R4 L0 NOT
       1 [-]: LOADK R4 K0 [""]
L 0:   2 [-]: MOVE R7 R1   
       3 [-]: LOADN R8 78  
       4 [-]: MOVE R9 R2   
       5 [-]: NAMECALL R5 R0 K1 [0x67BC869F]
       6 [-]: CALL R5 4 0  
       7 [-]: MOVE R7 R1   
       8 [-]: LOADN R8 82  
       9 [-]: MOVE R9 R4   
      10 [-]: NAMECALL R5 R0 K2 [0x5F56EEAB]
      11 [-]: CALL R5 4 0  
      12 [-]: MOVE R7 R1   
      13 [-]: LOADN R8 29  
      14 [-]: MOVE R9 R3   
      15 [-]: NAMECALL R5 R0 K2 [0x5F56EEAB]
      16 [-]: CALL R5 4 0  
      17 [-]: RETURN R0 0  


; Name:            
; Defined at line: 671
; #Upvalues:       0
; #Parameters:     5
; Is_vararg:       0
; Max Stack Size:  17

       0 [-]: NAMECALL R5 R0 K0 [0x7B3761D2]
       1 [-]: CALL R5 1 1  
       2 [-]: NEWCLOSURE R6 P0
       3 [-]: MOVE R0 R5   
       4 [-]: MOVE R0 R1   
       5 [-]: MOVE R0 R0   
       6 [-]: NEWCLOSURE R7 P1
       7 [-]: MOVE R0 R0   
       8 [-]: MOVE R0 R1   
       9 [-]: MOVE R0 R4   
      10 [-]: GETIMPORT R8 2 [0x25312C9B]
      11 [-]: MOVE R9 R0   
      12 [-]: LOADK R10 K3 ["_level0"]
      13 [-]: LOADN R11 0  
      14 [-]: NEWTABLE R12 0 1
      15 [-]: MOVE R13 R6  
      16 [-]: SETLIST R12 R13 1 [1]
      17 [-]: NEWTABLE R13 0 1
      18 [-]: LOADN R14 1  
      19 [-]: SETLIST R13 R14 1 [1]
      20 [-]: MOVE R14 R2  
      21 [-]: MOVE R15 R3  
      22 [-]: MOVE R16 R7  
      23 [-]: CALL R8 8 0  
      24 [-]: RETURN R0 0  


; Name:            
; Defined at line: 698
; #Upvalues:       0
; #Parameters:     1
; Is_vararg:       0
; Max Stack Size:  5

       0 [-]: LENGTH R1 R0 
L 0:   1 [-]: LOADN R2 2   
       2 [-]: JUMPIFNOTLE R2 R1 L1
       3 [-]: GETIMPORT R2 2 [0x3630E649]
       4 [-]: MOVE R3 R1   
       5 [-]: CALL R2 1 1  
       6 [-]: GETTABLE R3 R0 R2
       7 [-]: GETTABLE R4 R0 R1
       8 [-]: SETTABLE R3 R0 R1
       9 [-]: SETTABLE R4 R0 R2
      10 [-]: SUBK R1 R1 K3 [1]
      11 [-]: JUMPBACK L0  
L 1:  12 [-]: RETURN R0 1  


; Name:            
; Defined at line: 710
; #Upvalues:       0
; #Parameters:     2
; Is_vararg:       0
; Max Stack Size:  6

       0 [-]: MOVE R2 R1   
       1 [-]: JUMPIF R2 L0 
       2 [-]: GETIMPORT R2 1 [0x0C5E62F9]
L 0:   3 [-]: MOVE R1 R2   
       4 [-]: LENGTH R2 R0 
L 1:   5 [-]: LOADN R3 2   
       6 [-]: JUMPIFNOTLE R3 R2 L2
       7 [-]: MOVE R3 R1   
       8 [-]: LOADN R4 1   
       9 [-]: MOVE R5 R2   
      10 [-]: CALL R3 2 1  
      11 [-]: GETTABLE R4 R0 R3
      12 [-]: GETTABLE R5 R0 R2
      13 [-]: SETTABLE R4 R0 R2
      14 [-]: SETTABLE R5 R0 R3
      15 [-]: SUBK R2 R2 K2 [1]
      16 [-]: JUMPBACK L1  
L 2:  17 [-]: RETURN R0 1  


; Name:            
; Defined at line: 723
; #Upvalues:       0
; #Parameters:     3
; Is_vararg:       0
; Max Stack Size:  14

       0 [-]: JUMPXEQKNIL R1 L0 NOT
       1 [-]: MOVE R1 R0   
L 0:   2 [-]: ORK R2 R2 K0 [false]
       3 [-]: GETIMPORT R3 2 [0x67513231]
       4 [-]: CALL R3 0 1  
       5 [-]: NAMECALL R3 R3 K3 [0x6D604BA7]
       6 [-]: CALL R3 1 1  
       7 [-]: GETIMPORT R4 6 [0x66EDF04F]
       8 [-]: MOVE R5 R3   
       9 [-]: LOADK R6 K7 ["_"]
      10 [-]: LOADK R7 K8 [""]
      11 [-]: CALL R4 3 1  
      12 [-]: MOVE R3 R4   
      13 [-]: JUMPXEQKS R3 K9 L1 NOT ["pt"]
      14 [-]: LOADK R3 K10 ["pt-br"]
      15 [-]: JUMP L4
     
L 1:  16 [-]: JUMPXEQKS R3 K11 L2 NOT ["zh"]
      17 [-]: LOADK R3 K12 ["zh-hans"]
      18 [-]: JUMP L4
     
L 2:  19 [-]: JUMPXEQKS R3 K13 L3 NOT ["tc"]
      20 [-]: LOADK R3 K14 ["zh-hant"]
      21 [-]: JUMP L4
     
L 3:  22 [-]: JUMPXEQKS R3 K15 L4 NOT ["tr"]
      23 [-]: LOADK R3 K16 ["en"]
L 4:  24 [-]: JUMPIFNOT R2 L5
      25 [-]: GETIMPORT R4 18 [0xA5C556B9]
      26 [-]: MOVE R5 R0   
      27 [-]: LOADK R6 K19 ["forums.warframe.com"]
      28 [-]: CALL R4 2 1  
      29 [-]: JUMPXEQKNIL R4 L5 NOT
      30 [-]: GETIMPORT R4 6 [0x66EDF04F]
      31 [-]: MOVE R5 R0   
      32 [-]: LOADK R6 K20 ["warframe.com"]
      33 [-]: LOADK R8 K21 ["warframe.com/"]
      34 [-]: MOVE R9 R3   
      35 [-]: CONCAT R7 R8 R9
      36 [-]: CALL R4 3 1  
      37 [-]: MOVE R0 R4   
L 5:  38 [-]: GETIMPORT R4 23 [0x76EA806B]
      39 [-]: JUMPXEQKNIL R4 L10
      40 [-]: GETIMPORT R4 26 [0xA7A2E381]
      41 [-]: CALL R4 0 1  
      42 [-]: JUMPIF R4 L10
      43 [-]: GETIMPORT R4 28 [0x348C01F7]
      44 [-]: MOVE R5 R0   
      45 [-]: LOADK R6 K29 ["signup?"]
      46 [-]: CALL R4 2 1  
      47 [-]: JUMPIF R4 L10
      48 [-]: GETIMPORT R4 23 [0x76EA806B]
      49 [-]: LOADN R6 0   
      50 [-]: NAMECALL R4 R4 K30 [0x3F3AE64C]
      51 [-]: CALL R4 2 1  
      52 [-]: FASTCALL1 62 R4 L6
      53 [-]: MOVE R6 R4   
      54 [-]: GETIMPORT R5 32 [0x7B998233]
      55 [-]: CALL R5 1 1  
L 6:  56 [-]: JUMPIF R5 L10
      57 [-]: GETIMPORT R5 28 [0x348C01F7]
      58 [-]: MOVE R6 R0   
      59 [-]: LOADK R7 K33 ["https://dev.warframe.com"]
      60 [-]: CALL R5 2 1  
      61 [-]: JUMPIF R5 L7 
      62 [-]: GETIMPORT R5 28 [0x348C01F7]
      63 [-]: MOVE R6 R0   
      64 [-]: LOADK R7 K34 ["https://www.warframe.com"]
      65 [-]: CALL R5 2 1  
      66 [-]: JUMPIF R5 L7 
      67 [-]: GETIMPORT R5 28 [0x348C01F7]
      68 [-]: MOVE R6 R0   
      69 [-]: LOADK R7 K35 ["https://warframe.com"]
      70 [-]: CALL R5 2 1  
      71 [-]: JUMPIF R5 L7 
      72 [-]: GETIMPORT R5 28 [0x348C01F7]
      73 [-]: MOVE R6 R0   
      74 [-]: LOADK R7 K36 ["https://test.warframe.com"]
      75 [-]: CALL R5 2 1  
      76 [-]: JUMPIFNOT R5 L10
L 7:  77 [-]: GETIMPORT R5 6 [0x66EDF04F]
      78 [-]: MOVE R6 R0   
      79 [-]: LOADK R7 K37 ["http.*://.*warframe.com"]
      80 [-]: LOADK R8 K8 [""]
      81 [-]: CALL R5 3 1  
      82 [-]: GETIMPORT R6 6 [0x66EDF04F]
      83 [-]: MOVE R7 R0   
      84 [-]: LOADK R8 K38 ["%.com/.*"]
      85 [-]: LOADK R9 K8 [""]
      86 [-]: CALL R6 3 1  
      87 [-]: NAMECALL R7 R4 K39 [0x1012C7EC]
      88 [-]: CALL R7 1 1  
      89 [-]: MOVE R8 R7   
      90 [-]: NAMECALL R9 R4 K40 [0x37346C0E]
      91 [-]: CALL R9 1 1  
      92 [-]: CONCAT R7 R8 R9
      93 [-]: GETIMPORT R8 18 [0xA5C556B9]
      94 [-]: MOVE R9 R5   
      95 [-]: LOADK R10 K41 ["gameplatinum"]
      96 [-]: CALL R8 2 1  
      97 [-]: JUMPXEQKNIL R8 L9
      98 [-]: GETIMPORT R8 18 [0xA5C556B9]
      99 [-]: MOVE R9 R5   
     100 [-]: LOADK R10 K42 ["?"]
     101 [-]: CALL R8 2 1  
     102 [-]: JUMPXEQKNIL R8 L8
     103 [-]: MOVE R8 R0   
     104 [-]: LOADK R9 K43 ["&"]
     105 [-]: MOVE R10 R7  
     106 [-]: CONCAT R0 R8 R10
     107 [-]: JUMP L10
    
L 8: 108 [-]: MOVE R8 R0   
     109 [-]: LOADK R9 K42 ["?"]
     110 [-]: MOVE R10 R7  
     111 [-]: CONCAT R0 R8 R10
     112 [-]: JUMP L10
    
L 9: 113 [-]: GETIMPORT R8 6 [0x66EDF04F]
     114 [-]: MOVE R9 R5   
     115 [-]: LOADK R10 K44 ["%?"]
     116 [-]: LOADK R11 K45 ["%%3F"]
     117 [-]: CALL R8 3 1  
     118 [-]: MOVE R5 R8   
     119 [-]: GETIMPORT R8 6 [0x66EDF04F]
     120 [-]: MOVE R9 R5   
     121 [-]: LOADK R10 K43 ["&"]
     122 [-]: LOADK R11 K46 ["%%26"]
     123 [-]: CALL R8 3 1  
     124 [-]: MOVE R5 R8   
     125 [-]: GETIMPORT R8 6 [0x66EDF04F]
     126 [-]: MOVE R9 R5   
     127 [-]: LOADK R10 K47 ["="]
     128 [-]: LOADK R11 K48 ["%%3D"]
     129 [-]: CALL R8 3 1  
     130 [-]: MOVE R5 R8   
     131 [-]: LOADK R9 K49 ["&redirect="]
     132 [-]: MOVE R10 R5  
     133 [-]: CONCAT R8 R9 R10
     134 [-]: MOVE R9 R6   
     135 [-]: LOADK R10 K50 [".com/gameplatinum?"]
     136 [-]: MOVE R11 R7  
     137 [-]: LOADK R12 K51 ["&nologin=1"]
     138 [-]: MOVE R13 R8  
     139 [-]: CONCAT R0 R9 R13
L10: 140 [-]: GETIMPORT R4 53 [0x83F4E77C]
     141 [-]: NAMECALL R4 R4 K54 [0x61560C5C]
     142 [-]: CALL R4 1 1  
     143 [-]: NAMECALL R5 R4 K55 [0xBD6257B4]
     144 [-]: CALL R5 1 1  
     145 [-]: GETIMPORT R6 57 [0x0DB48B5B]
     146 [-]: NAMECALL R6 R6 K58 [0x30DFD1DD]
     147 [-]: CALL R6 1 1  
     148 [-]: GETTABLEKS R8 R5 K59 ["currentDisplayMode"]
     149 [-]: GETTABLEKS R7 R8 K60 ["fullScreen"]
     150 [-]: JUMPIF R7 L11
     151 [-]: GETTABLEKS R8 R5 K59 ["currentDisplayMode"]
     152 [-]: GETTABLEKS R7 R8 K61 ["borderless"]
     153 [-]: JUMPIFNOT R7 L12
L11: 154 [-]: GETIMPORT R7 63 [0x49D4C6FC]
     155 [-]: CALL R7 0 1  
     156 [-]: JUMPIFNOT R7 L12
     157 [-]: JUMPIF R6 L12
     158 [-]: GETIMPORT R7 65 [0x1DFCD71A]
     159 [-]: MOVE R8 R0   
     160 [-]: CALL R7 1 0  
     161 [-]: JUMP L13
    
L12: 162 [-]: GETIMPORT R7 67 [0x14CBF4A0]
     163 [-]: MOVE R8 R0   
     164 [-]: CALL R7 1 0  
L13: 165 [-]: GETIMPORT R8 69 [0xCB79539E]
     166 [-]: FASTCALL1 62 R8 L14
     167 [-]: GETIMPORT R7 32 [0x7B998233]
     168 [-]: CALL R7 1 1  
L14: 169 [-]: JUMPIF R7 L15
     170 [-]: GETIMPORT R7 6 [0x66EDF04F]
     171 [-]: MOVE R8 R1   
     172 [-]: LOADK R9 K70 ["%."]
     173 [-]: LOADK R10 K7 ["_"]
     174 [-]: CALL R7 3 1  
     175 [-]: MOVE R1 R7   
     176 [-]: GETIMPORT R7 6 [0x66EDF04F]
     177 [-]: MOVE R8 R1   
     178 [-]: LOADK R9 K71 ["(%/+)$"]
     179 [-]: LOADK R10 K8 [""]
     180 [-]: CALL R7 3 1  
     181 [-]: MOVE R1 R7   
     182 [-]: JUMPXEQKS R1 K8 L15 [""]
     183 [-]: GETIMPORT R7 69 [0xCB79539E]
     184 [-]: GETIMPORT R9 73 [0x0469F296]
     185 [-]: LOADK R10 K74 ["OPENED_BROWSER_LINK"]
     186 [-]: CALL R9 1 1  
     187 [-]: MOVE R10 R1  
     188 [-]: NAMECALL R7 R7 K75 [0x8B8FB8B7]
     189 [-]: CALL R7 3 0  
L15: 190 [-]: RETURN R0 0  


; Name:            
; Defined at line: 789
; #Upvalues:       0
; #Parameters:     0
; Is_vararg:       0
; Max Stack Size:  1

       0 [-]: GETIMPORT R0 1 [0x875CB7BF]
       1 [-]: CALL R0 0 1  
       2 [-]: RETURN R0 1  


; Name:            
; Defined at line: 795
; #Upvalues:       0
; #Parameters:     0
; Is_vararg:       0
; Max Stack Size:  1

       0 [-]: GETIMPORT R0 1 [0xA10122E0]
       1 [-]: CALL R0 0 1  
       2 [-]: RETURN R0 1  


; Name:            
; Defined at line: 801
; #Upvalues:       0
; #Parameters:     0
; Is_vararg:       0
; Max Stack Size:  1

       0 [-]: GETIMPORT R0 1 [0xD49CB88A]
       1 [-]: CALL R0 0 1  
       2 [-]: RETURN R0 1  


; Name:            
; Defined at line: 807
; #Upvalues:       0
; #Parameters:     1
; Is_vararg:       0
; Max Stack Size:  8

       0 [-]: GETIMPORT R1 1 [0x83F4E77C]
       1 [-]: NAMECALL R1 R1 K2 [0x61560C5C]
       2 [-]: CALL R1 1 1  
       3 [-]: NAMECALL R2 R1 K3 [0xBD6257B4]
       4 [-]: CALL R2 1 1  
       5 [-]: LOADB R3 0   
       6 [-]: GETTABLEKS R5 R2 K4 ["currentDisplayMode"]
       7 [-]: GETTABLEKS R4 R5 K5 ["fullScreen"]
       8 [-]: JUMPIF R4 L0 
       9 [-]: GETTABLEKS R5 R2 K4 ["currentDisplayMode"]
      10 [-]: GETTABLEKS R4 R5 K6 ["borderless"]
      11 [-]: JUMPIFNOT R4 L1
L 0:  12 [-]: GETIMPORT R4 9 [0x49D4C6FC]
      13 [-]: CALL R4 0 1  
      14 [-]: JUMPIFNOT R4 L1
      15 [-]: GETIMPORT R4 11 [0x1DFCD71A]
      16 [-]: MOVE R5 R0   
      17 [-]: CALL R4 1 1  
      18 [-]: MOVE R3 R4   
      19 [-]: JUMP L6
     
L 1:  20 [-]: GETIMPORT R4 13 [0xBE190284]
      21 [-]: NAMECALL R4 R4 K14 [0x7926B5DC]
      22 [-]: CALL R4 1 1  
      23 [-]: JUMPIFNOT R4 L5
      24 [-]: GETIMPORT R4 16 [0x9AD21AE9]
      25 [-]: CALL R4 0 1  
      26 [-]: JUMPIFNOT R4 L2
      27 [-]: GETIMPORT R4 18 [0x76EA806B]
      28 [-]: LOADN R6 0   
      29 [-]: NAMECALL R4 R4 K19 [0x3F3AE64C]
      30 [-]: CALL R4 2 1  
      31 [-]: NAMECALL R5 R4 K20 [0x80563238]
      32 [-]: CALL R5 1 1  
      33 [-]: MOVE R7 R0   
      34 [-]: NAMECALL R5 R5 K21 [0xDD741C3B]
      35 [-]: CALL R5 2 1  
      36 [-]: MOVE R3 R5   
      37 [-]: JUMP L6
     
L 2:  38 [-]: GETIMPORT R4 23 [0xC84FA15A]
      39 [-]: CALL R4 0 1  
      40 [-]: JUMPIFNOT R4 L4
      41 [-]: GETIMPORT R4 18 [0x76EA806B]
      42 [-]: MOVE R6 R0   
      43 [-]: NAMECALL R4 R4 K24 [0xC1E0FBAD]
      44 [-]: CALL R4 2 1  
      45 [-]: JUMPIF R4 L3 
      46 [-]: GETGLOBAL R4 K25 ["_ShowMessage"]
      47 [-]: LOADK R5 K26 ["/Lotus/Language/Menu/Store_AlreadyOwned_Switch"]
      48 [-]: CALL R4 1 0  
      49 [-]: JUMP L6
     
L 3:  50 [-]: GETIMPORT R4 28 [0x0AB2AE8D]
      51 [-]: MOVE R5 R0   
      52 [-]: CALL R4 1 1  
      53 [-]: MOVE R3 R4   
      54 [-]: JUMP L6
     
L 4:  55 [-]: GETIMPORT R4 28 [0x0AB2AE8D]
      56 [-]: MOVE R5 R0   
      57 [-]: CALL R4 1 1  
      58 [-]: MOVE R3 R4   
      59 [-]: JUMP L6
     
L 5:  60 [-]: LOADB R4 0   
      61 [-]: LOADK R5 K29 ["/Lotus/Language/Menu/Store_NetworkError_Windows"]
      62 [-]: RETURN R4 2  
L 6:  63 [-]: JUMPIF R3 L7 
      64 [-]: LOADB R4 0   
      65 [-]: LOADK R5 K29 ["/Lotus/Language/Menu/Store_NetworkError_Windows"]
      66 [-]: RETURN R4 2  
L 7:  67 [-]: LOADB R4 1   
      68 [-]: LOADK R5 K30 [""]
      69 [-]: RETURN R4 2  


; Name:            
; Defined at line: 837
; #Upvalues:       0
; #Parameters:     0
; Is_vararg:       0
; Max Stack Size:  4

       0 [-]: GETIMPORT R0 1 [0x76EA806B]
       1 [-]: LOADN R2 0   
       2 [-]: NAMECALL R0 R0 K2 [0x3F3AE64C]
       3 [-]: CALL R0 2 1  
       4 [-]: FASTCALL1 62 R0 L0
       5 [-]: MOVE R3 R0   
       6 [-]: GETIMPORT R2 4 [0x7B998233]
       7 [-]: CALL R2 1 1  
L 0:   8 [-]: NOT R1 R2    
       9 [-]: JUMPIFNOT R1 L1
      10 [-]: NAMECALL R2 R0 K5 [0x300348B9]
      11 [-]: CALL R2 1 1  
      12 [-]: NOT R1 R2    
L 1:  13 [-]: RETURN R1 1  


; Name:            
; Defined at line: 842
; #Upvalues:       0
; #Parameters:     0
; Is_vararg:       0
; Max Stack Size:  2

       0 [-]: GETIMPORT R1 1 [0x0032441C]
       1 [-]: GETTABLEKS R0 R1 K2 ["UIMovie_ChatReduxMovie"]
       2 [-]: RETURN R0 1  


; Name:            
; Defined at line: 846
; #Upvalues:       0
; #Parameters:     3
; Is_vararg:       0
; Max Stack Size:  17

       0 [-]: FASTCALL1 62 R2 L0
       1 [-]: MOVE R4 R2   
       2 [-]: GETIMPORT R3 1 [0x7B998233]
       3 [-]: CALL R3 1 1  
L 0:   4 [-]: JUMPIFNOT R3 L1
       5 [-]: LOADB R2 0   
L 1:   6 [-]: NAMECALL R3 R0 K2 [0x6B837788]
       7 [-]: CALL R3 1 1  
       8 [-]: NAMECALL R4 R0 K3 [0xAF9FDA9F]
       9 [-]: CALL R4 1 1  
      10 [-]: NAMECALL R5 R0 K4 [0x091C120E]
      11 [-]: CALL R5 1 1  
      12 [-]: NAMECALL R6 R0 K5 [0x2CC9D281]
      13 [-]: CALL R6 1 1  
      14 [-]: GETTABLEKS R7 R1 K6 ["x"]
      15 [-]: GETTABLEKS R8 R1 K7 ["y"]
      16 [-]: NAMECALL R9 R0 K8 [0x1AE553AF]
      17 [-]: CALL R9 1 1  
      18 [-]: JUMPIFNOT R9 L13
      19 [-]: NAMECALL R9 R0 K9 [0xC018B56E]
      20 [-]: CALL R9 1 1  
      21 [-]: DIVK R10 R5 K10 [2]
      22 [-]: DIVK R11 R6 K10 [2]
      23 [-]: NAMECALL R12 R0 K11 [0x468B2679]
      24 [-]: CALL R12 1 1 
      25 [-]: LOADN R13 0  
      26 [-]: JUMPIFEQ R12 R13 L2
      27 [-]: LOADN R13 3  
      28 [-]: JUMPIFEQ R12 R13 L2
      29 [-]: LOADN R13 6  
      30 [-]: JUMPIFNOTEQ R12 R13 L3
L 2:  31 [-]: MUL R7 R7 R9 
      32 [-]: JUMP L7
     
L 3:  33 [-]: LOADN R13 1  
      34 [-]: JUMPIFEQ R12 R13 L4
      35 [-]: LOADN R13 4  
      36 [-]: JUMPIFEQ R12 R13 L4
      37 [-]: LOADN R13 7  
      38 [-]: JUMPIFNOTEQ R12 R13 L5
L 4:  39 [-]: SUB R14 R7 R10
      40 [-]: MUL R13 R14 R9
      41 [-]: ADD R7 R10 R13
      42 [-]: JUMP L7
     
L 5:  43 [-]: LOADN R13 2  
      44 [-]: JUMPIFEQ R12 R13 L6
      45 [-]: LOADN R13 5  
      46 [-]: JUMPIFEQ R12 R13 L6
      47 [-]: LOADN R13 8  
      48 [-]: JUMPIFNOTEQ R12 R13 L7
L 6:  49 [-]: SUB R14 R7 R5
      50 [-]: MUL R13 R14 R9
      51 [-]: ADD R7 R5 R13
L 7:  52 [-]: LOADN R13 0  
      53 [-]: JUMPIFEQ R12 R13 L8
      54 [-]: LOADN R13 1  
      55 [-]: JUMPIFEQ R12 R13 L8
      56 [-]: LOADN R13 2  
      57 [-]: JUMPIFNOTEQ R12 R13 L9
L 8:  58 [-]: MUL R8 R8 R9 
      59 [-]: JUMP L13
    
L 9:  60 [-]: LOADN R13 3  
      61 [-]: JUMPIFEQ R12 R13 L10
      62 [-]: LOADN R13 4  
      63 [-]: JUMPIFEQ R12 R13 L10
      64 [-]: LOADN R13 5  
      65 [-]: JUMPIFNOTEQ R12 R13 L11
L10:  66 [-]: SUB R14 R8 R11
      67 [-]: MUL R13 R14 R9
      68 [-]: ADD R8 R11 R13
      69 [-]: JUMP L13
    
L11:  70 [-]: LOADN R13 6  
      71 [-]: JUMPIFEQ R12 R13 L12
      72 [-]: LOADN R13 7  
      73 [-]: JUMPIFEQ R12 R13 L12
      74 [-]: LOADN R13 8  
      75 [-]: JUMPIFNOTEQ R12 R13 L13
L12:  76 [-]: SUB R14 R8 R6
      77 [-]: MUL R13 R14 R9
      78 [-]: ADD R8 R6 R13
L13:  79 [-]: NAMECALL R9 R0 K12 [0x095251AF]
      80 [-]: CALL R9 1 1  
      81 [-]: LOADN R10 0  
      82 [-]: JUMPIFEQ R9 R10 L14
      83 [-]: LOADN R10 2  
      84 [-]: JUMPIFEQ R9 R10 L15
      85 [-]: JUMPIFLT R3 R5 L14
      86 [-]: JUMPIFNOTLT R4 R6 L15
L14:  87 [-]: DIV R7 R7 R5 
      88 [-]: DIV R8 R8 R6 
      89 [-]: JUMP L28
    
L15:  90 [-]: NAMECALL R10 R0 K11 [0x468B2679]
      91 [-]: CALL R10 1 1 
      92 [-]: MOVE R11 R5  
      93 [-]: MOVE R12 R6  
      94 [-]: NAMECALL R13 R0 K12 [0x095251AF]
      95 [-]: CALL R13 1 1 
      96 [-]: LOADN R14 2  
      97 [-]: JUMPIFNOTEQ R13 R14 L16
      98 [-]: MOVE R15 R11 
      99 [-]: MOVE R16 R12 
     100 [-]: NAMECALL R13 R0 K13 [0xBCEE8C15]
     101 [-]: CALL R13 3 2 
     102 [-]: MOVE R11 R13 
     103 [-]: MOVE R12 R14 
     104 [-]: MOVE R15 R7  
     105 [-]: MOVE R16 R8  
     106 [-]: NAMECALL R13 R0 K13 [0xBCEE8C15]
     107 [-]: CALL R13 3 2 
     108 [-]: MOVE R7 R13  
     109 [-]: MOVE R8 R14  
L16: 110 [-]: SUB R13 R3 R11
     111 [-]: SUB R14 R4 R12
     112 [-]: LOADN R15 0  
     113 [-]: JUMPIFEQ R10 R15 L17
     114 [-]: LOADN R15 3  
     115 [-]: JUMPIFEQ R10 R15 L17
     116 [-]: LOADN R15 6  
     117 [-]: JUMPIFNOTEQ R10 R15 L18
L17: 118 [-]: DIV R7 R7 R3 
     119 [-]: JUMP L22
    
L18: 120 [-]: LOADN R15 1  
     121 [-]: JUMPIFEQ R10 R15 L19
     122 [-]: LOADN R15 4  
     123 [-]: JUMPIFEQ R10 R15 L19
     124 [-]: LOADN R15 7  
     125 [-]: JUMPIFNOTEQ R10 R15 L20
L19: 126 [-]: MULK R16 R13 K14 [0.5]
     127 [-]: ADD R15 R7 R16
     128 [-]: DIV R7 R15 R3
     129 [-]: JUMP L22
    
L20: 130 [-]: LOADN R15 2  
     131 [-]: JUMPIFEQ R10 R15 L21
     132 [-]: LOADN R15 5  
     133 [-]: JUMPIFEQ R10 R15 L21
     134 [-]: LOADN R15 8  
     135 [-]: JUMPIFNOTEQ R10 R15 L22
L21: 136 [-]: ADD R15 R7 R13
     137 [-]: DIV R7 R15 R3
L22: 138 [-]: LOADN R15 0  
     139 [-]: JUMPIFEQ R10 R15 L23
     140 [-]: LOADN R15 1  
     141 [-]: JUMPIFEQ R10 R15 L23
     142 [-]: LOADN R15 2  
     143 [-]: JUMPIFNOTEQ R10 R15 L24
L23: 144 [-]: DIV R8 R8 R4 
     145 [-]: JUMP L28
    
L24: 146 [-]: LOADN R15 3  
     147 [-]: JUMPIFEQ R10 R15 L25
     148 [-]: LOADN R15 4  
     149 [-]: JUMPIFEQ R10 R15 L25
     150 [-]: LOADN R15 5  
     151 [-]: JUMPIFNOTEQ R10 R15 L26
L25: 152 [-]: MULK R16 R14 K14 [0.5]
     153 [-]: ADD R15 R8 R16
     154 [-]: DIV R8 R15 R4
     155 [-]: JUMP L28
    
L26: 156 [-]: LOADN R15 6  
     157 [-]: JUMPIFEQ R10 R15 L27
     158 [-]: LOADN R15 7  
     159 [-]: JUMPIFEQ R10 R15 L27
     160 [-]: LOADN R15 8  
     161 [-]: JUMPIFNOTEQ R10 R15 L28
L27: 162 [-]: ADD R15 R8 R14
     163 [-]: DIV R8 R15 R4
L28: 164 [-]: JUMPIFNOT R2 L29
     165 [-]: MULK R10 R7 K10 [2]
     166 [-]: SUBK R7 R10 K15 [1]
     167 [-]: MULK R10 R8 K10 [2]
     168 [-]: SUBK R8 R10 K15 [1]
L29: 169 [-]: GETIMPORT R10 17 [0xA421AF95]
     170 [-]: MOVE R11 R7  
     171 [-]: MOVE R12 R8  
     172 [-]: LOADN R13 5  
     173 [-]: CALL R10 3 1 
     174 [-]: RETURN R10 1 


; Name:            
; Defined at line: 927
; #Upvalues:       1
; #Parameters:     3
; Is_vararg:       0
; Max Stack Size:  7

       0 [-]: GETUPVAL R3 0
       1 [-]: MOVE R4 R0   
       2 [-]: MOVE R5 R1   
       3 [-]: MOVE R6 R2   
       4 [-]: CALL R3 3 1  
       5 [-]: RETURN R3 1  


; Name:            
; Defined at line: 931
; #Upvalues:       0
; #Parameters:     3
; Is_vararg:       0
; Max Stack Size:  19

       0 [-]: FASTCALL1 62 R2 L0
       1 [-]: MOVE R4 R2   
       2 [-]: GETIMPORT R3 1 [0x7B998233]
       3 [-]: CALL R3 1 1  
L 0:   4 [-]: JUMPIFNOT R3 L1
       5 [-]: LOADB R2 0   
L 1:   6 [-]: GETTABLEKS R3 R1 K2 ["x"]
       7 [-]: GETTABLEKS R4 R1 K3 ["y"]
       8 [-]: NAMECALL R5 R0 K4 [0x6B837788]
       9 [-]: CALL R5 1 1  
      10 [-]: NAMECALL R6 R0 K5 [0xAF9FDA9F]
      11 [-]: CALL R6 1 1  
      12 [-]: NAMECALL R7 R0 K6 [0x091C120E]
      13 [-]: CALL R7 1 1  
      14 [-]: NAMECALL R8 R0 K7 [0x2CC9D281]
      15 [-]: CALL R8 1 1  
      16 [-]: JUMPIFNOT R2 L2
      17 [-]: ADDK R9 R3 K9 [1]
      18 [-]: DIVK R3 R9 K8 [2]
      19 [-]: ADDK R9 R4 K9 [1]
      20 [-]: DIVK R4 R9 K8 [2]
L 2:  21 [-]: NAMECALL R9 R0 K10 [0x095251AF]
      22 [-]: CALL R9 1 1  
      23 [-]: LOADN R10 0  
      24 [-]: JUMPIFEQ R9 R10 L3
      25 [-]: LOADN R10 2  
      26 [-]: JUMPIFEQ R9 R10 L4
      27 [-]: JUMPIFLT R5 R7 L3
      28 [-]: JUMPIFNOTLT R6 R8 L4
L 3:  29 [-]: MUL R3 R3 R7 
      30 [-]: MUL R4 R4 R8 
      31 [-]: JUMP L18
    
L 4:  32 [-]: NAMECALL R10 R0 K11 [0x468B2679]
      33 [-]: CALL R10 1 1 
      34 [-]: MOVE R11 R7  
      35 [-]: MOVE R12 R8  
      36 [-]: NAMECALL R13 R0 K10 [0x095251AF]
      37 [-]: CALL R13 1 1 
      38 [-]: LOADN R14 2  
      39 [-]: JUMPIFNOTEQ R13 R14 L5
      40 [-]: MOVE R15 R11 
      41 [-]: MOVE R16 R12 
      42 [-]: NAMECALL R13 R0 K12 [0xBCEE8C15]
      43 [-]: CALL R13 3 2 
      44 [-]: MOVE R11 R13 
      45 [-]: MOVE R12 R14 
L 5:  46 [-]: SUB R13 R5 R11
      47 [-]: SUB R14 R6 R12
      48 [-]: LOADN R15 0  
      49 [-]: JUMPIFEQ R10 R15 L6
      50 [-]: LOADN R15 3  
      51 [-]: JUMPIFEQ R10 R15 L6
      52 [-]: LOADN R15 6  
      53 [-]: JUMPIFNOTEQ R10 R15 L7
L 6:  54 [-]: MUL R3 R3 R5 
      55 [-]: JUMP L11
    
L 7:  56 [-]: LOADN R15 1  
      57 [-]: JUMPIFEQ R10 R15 L8
      58 [-]: LOADN R15 4  
      59 [-]: JUMPIFEQ R10 R15 L8
      60 [-]: LOADN R15 7  
      61 [-]: JUMPIFNOTEQ R10 R15 L9
L 8:  62 [-]: MUL R15 R3 R5
      63 [-]: MULK R16 R13 K13 [0.5]
      64 [-]: SUB R3 R15 R16
      65 [-]: JUMP L11
    
L 9:  66 [-]: LOADN R15 2  
      67 [-]: JUMPIFEQ R10 R15 L10
      68 [-]: LOADN R15 5  
      69 [-]: JUMPIFEQ R10 R15 L10
      70 [-]: LOADN R15 8  
      71 [-]: JUMPIFNOTEQ R10 R15 L11
L10:  72 [-]: MUL R15 R3 R5
      73 [-]: SUB R3 R15 R13
L11:  74 [-]: LOADN R15 0  
      75 [-]: JUMPIFEQ R10 R15 L12
      76 [-]: LOADN R15 1  
      77 [-]: JUMPIFEQ R10 R15 L12
      78 [-]: LOADN R15 2  
      79 [-]: JUMPIFNOTEQ R10 R15 L13
L12:  80 [-]: MUL R4 R4 R6 
      81 [-]: JUMP L17
    
L13:  82 [-]: LOADN R15 3  
      83 [-]: JUMPIFEQ R10 R15 L14
      84 [-]: LOADN R15 4  
      85 [-]: JUMPIFEQ R10 R15 L14
      86 [-]: LOADN R15 5  
      87 [-]: JUMPIFNOTEQ R10 R15 L15
L14:  88 [-]: MUL R15 R4 R6
      89 [-]: MULK R16 R14 K13 [0.5]
      90 [-]: SUB R4 R15 R16
      91 [-]: JUMP L17
    
L15:  92 [-]: LOADN R15 6  
      93 [-]: JUMPIFEQ R10 R15 L16
      94 [-]: LOADN R15 7  
      95 [-]: JUMPIFEQ R10 R15 L16
      96 [-]: LOADN R15 8  
      97 [-]: JUMPIFNOTEQ R10 R15 L17
L16:  98 [-]: MUL R15 R4 R6
      99 [-]: SUB R4 R15 R14
L17: 100 [-]: NAMECALL R15 R0 K10 [0x095251AF]
     101 [-]: CALL R15 1 1 
     102 [-]: LOADN R16 2  
     103 [-]: JUMPIFNOTEQ R15 R16 L18
     104 [-]: MOVE R17 R3  
     105 [-]: MOVE R18 R4  
     106 [-]: NAMECALL R15 R0 K14 [0xBF94C0DA]
     107 [-]: CALL R15 3 2 
     108 [-]: MOVE R3 R15  
     109 [-]: MOVE R4 R16  
L18: 110 [-]: NAMECALL R10 R0 K15 [0x1AE553AF]
     111 [-]: CALL R10 1 1 
     112 [-]: JUMPIFNOT R10 L30
     113 [-]: NAMECALL R10 R0 K16 [0xC018B56E]
     114 [-]: CALL R10 1 1 
     115 [-]: DIVK R11 R7 K8 [2]
     116 [-]: DIVK R12 R8 K8 [2]
     117 [-]: NAMECALL R13 R0 K11 [0x468B2679]
     118 [-]: CALL R13 1 1 
     119 [-]: LOADN R14 0  
     120 [-]: JUMPIFEQ R13 R14 L19
     121 [-]: LOADN R14 3  
     122 [-]: JUMPIFEQ R13 R14 L19
     123 [-]: LOADN R14 6  
     124 [-]: JUMPIFNOTEQ R13 R14 L20
L19: 125 [-]: DIV R3 R3 R10
     126 [-]: JUMP L24
    
L20: 127 [-]: LOADN R14 1  
     128 [-]: JUMPIFEQ R13 R14 L21
     129 [-]: LOADN R14 4  
     130 [-]: JUMPIFEQ R13 R14 L21
     131 [-]: LOADN R14 7  
     132 [-]: JUMPIFNOTEQ R13 R14 L22
L21: 133 [-]: SUB R15 R3 R11
     134 [-]: DIV R14 R15 R10
     135 [-]: ADD R3 R14 R11
     136 [-]: JUMP L24
    
L22: 137 [-]: LOADN R14 2  
     138 [-]: JUMPIFEQ R13 R14 L23
     139 [-]: LOADN R14 5  
     140 [-]: JUMPIFEQ R13 R14 L23
     141 [-]: LOADN R14 8  
     142 [-]: JUMPIFNOTEQ R13 R14 L24
L23: 143 [-]: SUB R15 R3 R7
     144 [-]: DIV R14 R15 R10
     145 [-]: ADD R3 R14 R7
L24: 146 [-]: LOADN R14 0  
     147 [-]: JUMPIFEQ R13 R14 L25
     148 [-]: LOADN R14 1  
     149 [-]: JUMPIFEQ R13 R14 L25
     150 [-]: LOADN R14 2  
     151 [-]: JUMPIFNOTEQ R13 R14 L26
L25: 152 [-]: DIV R4 R4 R10
     153 [-]: JUMP L30
    
L26: 154 [-]: LOADN R14 3  
     155 [-]: JUMPIFEQ R13 R14 L27
     156 [-]: LOADN R14 4  
     157 [-]: JUMPIFEQ R13 R14 L27
     158 [-]: LOADN R14 5  
     159 [-]: JUMPIFNOTEQ R13 R14 L28
L27: 160 [-]: SUB R15 R4 R12
     161 [-]: DIV R14 R15 R10
     162 [-]: ADD R4 R14 R12
     163 [-]: JUMP L30
    
L28: 164 [-]: LOADN R14 6  
     165 [-]: JUMPIFEQ R13 R14 L29
     166 [-]: LOADN R14 7  
     167 [-]: JUMPIFEQ R13 R14 L29
     168 [-]: LOADN R14 8  
     169 [-]: JUMPIFNOTEQ R13 R14 L30
L29: 170 [-]: SUB R15 R4 R8
     171 [-]: DIV R14 R15 R10
     172 [-]: ADD R4 R14 R8
L30: 173 [-]: GETIMPORT R10 18 [0xA421AF95]
     174 [-]: MOVE R11 R3  
     175 [-]: MOVE R12 R4  
     176 [-]: LOADN R13 5  
     177 [-]: CALL R10 3 1 
     178 [-]: RETURN R10 1 


; Name:            
; Defined at line: 1018
; #Upvalues:       1
; #Parameters:     3
; Is_vararg:       0
; Max Stack Size:  7

       0 [-]: GETUPVAL R3 0
       1 [-]: MOVE R4 R0   
       2 [-]: MOVE R5 R1   
       3 [-]: MOVE R6 R2   
       4 [-]: CALL R3 3 1  
       5 [-]: RETURN R3 1  


; Name:            
; Defined at line: 1022
; #Upvalues:       0
; #Parameters:     3
; Is_vararg:       0
; Max Stack Size:  11

       0 [-]: MOVE R5 R1   
       1 [-]: LOADN R6 2   
       2 [-]: NAMECALL R3 R0 K0 [0x91A24E4B]
       3 [-]: CALL R3 3 1  
       4 [-]: MOVE R6 R1   
       5 [-]: LOADN R7 3   
       6 [-]: NAMECALL R4 R0 K0 [0x91A24E4B]
       7 [-]: CALL R4 3 1  
       8 [-]: LOADN R5 0   
       9 [-]: LOADN R6 0   
      10 [-]: JUMPIF R2 L0 
      11 [-]: LOADK R9 K1 ["_root"]
      12 [-]: LOADN R10 0  
      13 [-]: NAMECALL R7 R0 K0 [0x91A24E4B]
      14 [-]: CALL R7 3 1  
      15 [-]: MOVE R5 R7   
      16 [-]: LOADK R9 K1 ["_root"]
      17 [-]: LOADN R10 1  
      18 [-]: NAMECALL R7 R0 K0 [0x91A24E4B]
      19 [-]: CALL R7 3 1  
      20 [-]: MOVE R6 R7   
L 0:  21 [-]: JUMPXEQKNIL R3 L1
      22 [-]: JUMPXEQKNIL R5 L2 NOT
L 1:  23 [-]: LOADN R7 0   
      24 [-]: LOADN R8 0   
      25 [-]: RETURN R7 2  
L 2:  26 [-]: SUB R7 R3 R5 
      27 [-]: SUB R8 R4 R6 
      28 [-]: RETURN R7 2  


; Name:            
; Defined at line: 1038
; #Upvalues:       1
; #Parameters:     3
; Is_vararg:       0
; Max Stack Size:  7

       0 [-]: GETUPVAL R3 0
       1 [-]: MOVE R4 R0   
       2 [-]: MOVE R5 R1   
       3 [-]: MOVE R6 R2   
       4 [-]: CALL R3 3 -1 
       5 [-]: RETURN R3 -1 


; Name:            
; Defined at line: 1042
; #Upvalues:       1
; #Parameters:     4
; Is_vararg:       0
; Max Stack Size:  12

       0 [-]: NAMECALL R4 R3 K0 [0x31050791]
       1 [-]: CALL R4 1 1  
       2 [-]: JUMPXEQKN R4 K1 L0 NOT [0]
       3 [-]: NAMECALL R5 R0 K2 [0x6B837788]
       4 [-]: CALL R5 1 1  
       5 [-]: NAMECALL R6 R0 K3 [0xAF9FDA9F]
       6 [-]: CALL R6 1 1  
       7 [-]: DIV R4 R5 R6 
L 0:   8 [-]: LOADK R8 K6 [3.1415927410125732]
       9 [-]: DIVK R7 R8 K5 [180]
      10 [-]: MULK R6 R7 K4 [10]
      11 [-]: FASTCALL1 27 R6 L1
      12 [-]: GETIMPORT R5 9 [0xD8DA5899]
      13 [-]: CALL R5 1 1  
L 1:  14 [-]: MUL R6 R5 R4 
      15 [-]: GETUPVAL R7 0
      16 [-]: MOVE R8 R0   
      17 [-]: DUPTABLE R9 13
      18 [-]: SETTABLEKS R1 R9 K10 ["x"]
      19 [-]: SETTABLEKS R2 R9 K11 ["y"]
      20 [-]: LOADN R10 0  
      21 [-]: SETTABLEKS R10 R9 K12 ["z"]
      22 [-]: LOADB R10 1  
      23 [-]: CALL R7 3 1  
      24 [-]: GETTABLEKS R9 R7 K10 ["x"]
      25 [-]: MUL R8 R9 R6 
      26 [-]: GETTABLEKS R11 R7 K11 ["y"]
      27 [-]: MINUS R10 R11
      28 [-]: MUL R9 R10 R5
      29 [-]: RETURN R8 2  


; Name:            
; Defined at line: 1058
; #Upvalues:       1
; #Parameters:     4
; Is_vararg:       0
; Max Stack Size:  9

       0 [-]: GETUPVAL R4 0
       1 [-]: MOVE R5 R0   
       2 [-]: MOVE R6 R1   
       3 [-]: MOVE R7 R2   
       4 [-]: MOVE R8 R3   
       5 [-]: CALL R4 4 -1 
       6 [-]: RETURN R4 -1 


; Name:            
; Defined at line: 1062
; #Upvalues:       1
; #Parameters:     8
; Is_vararg:       0
; Max Stack Size:  19

       0 [-]: LOADNIL R8   
       1 [-]: FASTCALL1 62 R1 L0
       2 [-]: MOVE R10 R1  
       3 [-]: GETIMPORT R9 1 [0x7B998233]
       4 [-]: CALL R9 1 1  
L 0:   5 [-]: JUMPIF R9 L4 
       6 [-]: JUMPIF R7 L1 
       7 [-]: LOADK R11 K2 ["_root"]
       8 [-]: LOADN R12 10 
       9 [-]: NAMECALL R9 R0 K3 [0x91A24E4B]
      10 [-]: CALL R9 3 1  
      11 [-]: JUMPXEQKN R9 K4 L4 [0]
      12 [-]: NAMECALL R9 R0 K5 [0xD4CC05B4]
      13 [-]: CALL R9 1 1  
      14 [-]: JUMPIFNOT R9 L4
L 1:  15 [-]: GETIMPORT R10 8 ["BackgroundMovie"]
      16 [-]: FASTCALL1 62 R10 L2
      17 [-]: GETIMPORT R9 1 [0x7B998233]
      18 [-]: CALL R9 1 1  
L 2:  19 [-]: JUMPIFNOT R9 L5
      20 [-]: GETIMPORT R10 10 ["pauseMenuOpen"]
      21 [-]: FASTCALL1 62 R10 L3
      22 [-]: GETIMPORT R9 1 [0x7B998233]
      23 [-]: CALL R9 1 1  
L 3:  24 [-]: JUMPIF R9 L5 
      25 [-]: GETIMPORT R9 10 ["pauseMenuOpen"]
      26 [-]: JUMPIFNOT R9 L5
L 4:  27 [-]: RETURN R8 1  
L 5:  28 [-]: JUMPXEQKNIL R4 L6 NOT
      29 [-]: GETIMPORT R4 12 [0x89326C93]
L 6:  30 [-]: FASTCALL1 62 R4 L7
      31 [-]: MOVE R10 R4  
      32 [-]: GETIMPORT R9 1 [0x7B998233]
      33 [-]: CALL R9 1 1  
L 7:  34 [-]: JUMPIFNOT R9 L8
      35 [-]: RETURN R8 1  
L 8:  36 [-]: NAMECALL R9 R4 K13 [0xB4364067]
      37 [-]: CALL R9 1 1  
      38 [-]: FASTCALL1 62 R9 L9
      39 [-]: MOVE R11 R9  
      40 [-]: GETIMPORT R10 1 [0x7B998233]
      41 [-]: CALL R10 1 1 
L 9:  42 [-]: JUMPIFNOT R10 L10
      43 [-]: RETURN R8 1  
L10:  44 [-]: NAMECALL R10 R0 K14 [0xC7FA728C]
      45 [-]: CALL R10 1 1 
      46 [-]: JUMPIF R10 L12
      47 [-]: NAMECALL R11 R4 K15 [0xDD25E9D1]
      48 [-]: CALL R11 1 1 
      49 [-]: FASTCALL1 62 R11 L11
      50 [-]: GETIMPORT R10 1 [0x7B998233]
      51 [-]: CALL R10 1 1 
L11:  52 [-]: JUMPIF R10 L12
      53 [-]: RETURN R8 1  
L12:  54 [-]: FASTCALL1 62 R0 L13
      55 [-]: MOVE R11 R0  
      56 [-]: GETIMPORT R10 1 [0x7B998233]
      57 [-]: CALL R10 1 1 
L13:  58 [-]: JUMPIF R10 L14
      59 [-]: GETUPVAL R10 0
      60 [-]: MOVE R11 R0  
      61 [-]: MOVE R12 R2  
      62 [-]: MOVE R13 R3  
      63 [-]: MOVE R14 R9  
      64 [-]: CALL R10 4 2 
      65 [-]: MOVE R2 R10  
      66 [-]: MOVE R3 R11  
L14:  67 [-]: JUMPXEQKNIL R5 L15 NOT
      68 [-]: LOADN R5 0   
L15:  69 [-]: MOVE R12 R1  
      70 [-]: GETIMPORT R13 17 ["EMPTY_SYMBOL"]
      71 [-]: GETIMPORT R14 19 [0xA421AF95]
      72 [-]: MOVE R15 R2  
      73 [-]: MOVE R16 R3  
      74 [-]: LOADN R18 1  
      75 [-]: ADD R17 R18 R5
      76 [-]: CALL R14 3 1 
      77 [-]: MOVE R15 R6  
      78 [-]: JUMPIF R15 L16
      79 [-]: GETIMPORT R15 21 [0x00046924]
      80 [-]: CALL R15 0 1 
L16:  81 [-]: NAMECALL R10 R9 K22 [0x47901F07]
      82 [-]: CALL R10 5 1 
      83 [-]: MOVE R8 R10  
      84 [-]: RETURN R8 1  


; Name:            
; Defined at line: 1098
; #Upvalues:       1
; #Parameters:     8
; Is_vararg:       0
; Max Stack Size:  17

       0 [-]: GETUPVAL R8 0
       1 [-]: MOVE R9 R0   
       2 [-]: MOVE R10 R1  
       3 [-]: MOVE R11 R2  
       4 [-]: MOVE R12 R3  
       5 [-]: MOVE R13 R4  
       6 [-]: MOVE R14 R5  
       7 [-]: MOVE R15 R6  
       8 [-]: MOVE R16 R7  
       9 [-]: CALL R8 8 1  
      10 [-]: RETURN R8 1  


; Name:            
; Defined at line: 1102
; #Upvalues:       2
; #Parameters:     9
; Is_vararg:       0
; Max Stack Size:  20

       0 [-]: JUMPXEQKNIL R3 L0 NOT
       1 [-]: LOADN R3 0   
L 0:   2 [-]: JUMPXEQKNIL R4 L1 NOT
       3 [-]: LOADN R4 0   
L 1:   4 [-]: GETUPVAL R9 0
       5 [-]: MOVE R10 R0  
       6 [-]: MOVE R11 R1  
       7 [-]: LOADB R12 1  
       8 [-]: CALL R9 3 2  
       9 [-]: JUMPXEQKNIL R9 L2
      10 [-]: JUMPXEQKNIL R10 L2
      11 [-]: GETUPVAL R11 1
      12 [-]: MOVE R12 R0  
      13 [-]: MOVE R13 R2  
      14 [-]: ADD R14 R9 R3
      15 [-]: ADD R15 R10 R4
      16 [-]: MOVE R16 R5  
      17 [-]: MOVE R17 R6  
      18 [-]: MOVE R18 R7  
      19 [-]: MOVE R19 R8  
      20 [-]: CALL R11 8 1 
      21 [-]: RETURN R11 1 
L 2:  22 [-]: LOADNIL R11  
      23 [-]: RETURN R11 1 


; Name:            
; Defined at line: 1117
; #Upvalues:       1
; #Parameters:     8
; Is_vararg:       0
; Max Stack Size:  17

       0 [-]: JUMPXEQKNIL R2 L0 NOT
       1 [-]: LOADN R2 0   
L 0:   2 [-]: JUMPXEQKNIL R3 L1 NOT
       3 [-]: LOADN R3 0   
L 1:   4 [-]: GETUPVAL R8 0
       5 [-]: MOVE R9 R0   
       6 [-]: MOVE R10 R1  
       7 [-]: LOADK R14 K0 ["_root"]
       8 [-]: LOADN R15 25 
       9 [-]: NAMECALL R12 R0 K1 [0x91A24E4B]
      10 [-]: CALL R12 3 1 
      11 [-]: ADD R11 R12 R2
      12 [-]: LOADK R15 K0 ["_root"]
      13 [-]: LOADN R16 26 
      14 [-]: NAMECALL R13 R0 K1 [0x91A24E4B]
      15 [-]: CALL R13 3 1 
      16 [-]: ADD R12 R13 R3
      17 [-]: MOVE R13 R4  
      18 [-]: MOVE R14 R5  
      19 [-]: MOVE R15 R6  
      20 [-]: MOVE R16 R7  
      21 [-]: CALL R8 8 1  
      22 [-]: RETURN R8 1  


; Name:            
; Defined at line: 1127
; #Upvalues:       2
; #Parameters:     8
; Is_vararg:       0
; Max Stack Size:  14

       0 [-]: FASTCALL1 62 R2 L0
       1 [-]: MOVE R9 R2   
       2 [-]: GETIMPORT R8 1 [0x7B998233]
       3 [-]: CALL R8 1 1  
L 0:   4 [-]: JUMPIF R8 L2 
       5 [-]: LOADK R10 K2 ["_root"]
       6 [-]: LOADN R11 10 
       7 [-]: NAMECALL R8 R0 K3 [0x91A24E4B]
       8 [-]: CALL R8 3 1  
       9 [-]: JUMPXEQKN R8 K4 L1 [0]
      10 [-]: NAMECALL R8 R0 K5 [0xD4CC05B4]
      11 [-]: CALL R8 1 1  
      12 [-]: JUMPIF R8 L3 
L 1:  13 [-]: JUMPIF R6 L3 
L 2:  14 [-]: LOADNIL R8   
      15 [-]: RETURN R8 1  
L 3:  16 [-]: JUMPXEQKNIL R5 L4 NOT
      17 [-]: GETIMPORT R5 7 [0x89326C93]
L 4:  18 [-]: FASTCALL1 62 R5 L5
      19 [-]: MOVE R9 R5   
      20 [-]: GETIMPORT R8 1 [0x7B998233]
      21 [-]: CALL R8 1 1  
L 5:  22 [-]: JUMPIFNOT R8 L6
      23 [-]: LOADNIL R8   
      24 [-]: RETURN R8 1  
L 6:  25 [-]: JUMPXEQKNIL R3 L7 NOT
      26 [-]: LOADN R3 0   
L 7:  27 [-]: JUMPXEQKNIL R4 L8 NOT
      28 [-]: LOADN R4 0   
L 8:  29 [-]: NEWTABLE R8 16 0
      30 [-]: SETTABLEKS R0 R8 K8 ["mMovie"]
      31 [-]: SETTABLEKS R5 R8 K9 ["mRegion"]
      32 [-]: SETTABLEKS R1 R8 K10 ["mClipName"]
      33 [-]: SETTABLEKS R2 R8 K11 ["mFx"]
      34 [-]: SETTABLEKS R3 R8 K12 ["mOffsetX"]
      35 [-]: SETTABLEKS R4 R8 K13 ["mOffsetY"]
      36 [-]: NAMECALL R9 R5 K14 [0xB4364067]
      37 [-]: CALL R9 1 1  
      38 [-]: SETTABLEKS R9 R8 K15 ["CameraEntity"]
      39 [-]: GETTABLEKS R10 R8 K15 ["CameraEntity"]
      40 [-]: FASTCALL1 62 R10 L9
      41 [-]: GETIMPORT R9 1 [0x7B998233]
      42 [-]: CALL R9 1 1  
L 9:  43 [-]: JUMPIFNOT R9 L10
      44 [-]: GETTABLEKS R11 R8 K11 ["mFx"]
      45 [-]: GETIMPORT R12 17 ["ZERO_VECTOR"]
      46 [-]: GETIMPORT R13 19 ["ZERO_ROTATION"]
      47 [-]: NAMECALL R9 R5 K20 [0x05909209]
      48 [-]: CALL R9 4 1  
      49 [-]: SETTABLEKS R9 R8 K21 ["mInstance"]
      50 [-]: JUMP L11
    
L10:  51 [-]: GETTABLEKS R11 R8 K11 ["mFx"]
      52 [-]: GETTABLEKS R12 R8 K15 ["CameraEntity"]
      53 [-]: NAMECALL R12 R12 K22 [0xD1586535]
      54 [-]: CALL R12 1 1 
      55 [-]: GETIMPORT R13 19 ["ZERO_ROTATION"]
      56 [-]: NAMECALL R9 R5 K20 [0x05909209]
      57 [-]: CALL R9 4 1  
      58 [-]: SETTABLEKS R9 R8 K21 ["mInstance"]
L11:  59 [-]: LOADB R9 1   
      60 [-]: SETTABLEKS R9 R8 K23 ["mVisible"]
      61 [-]: GETTABLEKS R10 R8 K21 ["mInstance"]
      62 [-]: FASTCALL1 62 R10 L12
      63 [-]: GETIMPORT R9 1 [0x7B998233]
      64 [-]: CALL R9 1 1  
L12:  65 [-]: JUMPIFNOT R9 L13
      66 [-]: GETIMPORT R9 25 [0x3D106989]
      67 [-]: LOADK R11 K26 ["ERROR: Failed to CreateUIParticles clipname="]
      68 [-]: GETIMPORT R12 28 [0x64FB1586]
      69 [-]: MOVE R13 R1  
      70 [-]: CALL R12 1 1 
      71 [-]: CONCAT R10 R11 R12
      72 [-]: CALL R9 1 0  
      73 [-]: LOADNIL R9   
      74 [-]: RETURN R9 1  
L13:  75 [-]: NEWCLOSURE R9 P0
      76 [-]: MOVE R0 R7   
      77 [-]: MOVE R2 R0   
      78 [-]: MOVE R0 R8   
      79 [-]: MOVE R2 R1   
      80 [-]: SETTABLEKS R9 R8 K29 ["Update"]
      81 [-]: NEWCLOSURE R9 P1
      82 [-]: MOVE R0 R8   
      83 [-]: SETTABLEKS R9 R8 K30 ["SetVisibility"]
      84 [-]: DUPCLOSURE R9 K31 []
      85 [-]: SETTABLEKS R9 R8 K32 ["Destroy"]
      86 [-]: LOADN R11 0  
      87 [-]: NAMECALL R9 R8 K33 [0xFAA69527]
      88 [-]: CALL R9 2 0  
      89 [-]: RETURN R8 1  


; Name:            
; Defined at line: 1237
; #Upvalues:       0
; #Parameters:     2
; Is_vararg:       0
; Max Stack Size:  6

       0 [-]: GETIMPORT R2 2 [0xE27B35BB]
       1 [-]: CALL R2 0 1  
       2 [-]: LOADN R3 1   
       3 [-]: SETTABLEKS R3 R2 K3 ["dialogType"]
       4 [-]: SETTABLEKS R0 R2 K4 ["locString"]
       5 [-]: LOADK R3 K5 ["/Menu/Confirm_Item_Yes"]
       6 [-]: SETTABLEKS R3 R2 K6 ["firstString"]
       7 [-]: LOADK R3 K7 ["/Menu/Confirm_Item_No"]
       8 [-]: SETTABLEKS R3 R2 K8 ["secondString"]
       9 [-]: MOVE R5 R1   
      10 [-]: NAMECALL R3 R2 K9 [0xE6CCC5B9]
      11 [-]: CALL R3 2 0  
      12 [-]: GETIMPORT R3 11 [0x83F4E77C]
      13 [-]: NAMECALL R3 R3 K12 [0x7D63F19C]
      14 [-]: CALL R3 1 1  
      15 [-]: MOVE R5 R2   
      16 [-]: NAMECALL R3 R3 K13 [0x69E5AA4F]
      17 [-]: CALL R3 2 1  
      18 [-]: RETURN R3 1  


; Name:            
; Defined at line: 1247
; #Upvalues:       0
; #Parameters:     3
; Is_vararg:       0
; Max Stack Size:  7

       0 [-]: GETIMPORT R3 2 [0xE27B35BB]
       1 [-]: CALL R3 0 1  
       2 [-]: LOADN R4 1   
       3 [-]: SETTABLEKS R4 R3 K3 ["dialogType"]
       4 [-]: SETTABLEKS R0 R3 K4 ["locString"]
       5 [-]: JUMPIFNOT R2 L0
       6 [-]: SETTABLEKS R2 R3 K5 ["firstDelay"]
L 0:   7 [-]: MOVE R6 R1   
       8 [-]: NAMECALL R4 R3 K6 [0xE6CCC5B9]
       9 [-]: CALL R4 2 0  
      10 [-]: GETIMPORT R4 8 [0x83F4E77C]
      11 [-]: NAMECALL R4 R4 K9 [0x7D63F19C]
      12 [-]: CALL R4 1 1  
      13 [-]: MOVE R6 R3   
      14 [-]: NAMECALL R4 R4 K10 [0x69E5AA4F]
      15 [-]: CALL R4 2 1  
      16 [-]: RETURN R4 1  


; Name:            
; Defined at line: 1258
; #Upvalues:       0
; #Parameters:     1
; Is_vararg:       0
; Max Stack Size:  7

       0 [-]: GETIMPORT R1 2 [0xA5C556B9]
       1 [-]: MOVE R2 R0   
       2 [-]: LOADK R3 K3 ["/"]
       3 [-]: LOADN R4 1   
       4 [-]: LOADB R5 1   
       5 [-]: CALL R1 4 1  
       6 [-]: GETIMPORT R2 2 [0xA5C556B9]
       7 [-]: MOVE R3 R0   
       8 [-]: LOADK R4 K4 [" "]
       9 [-]: LOADN R5 1   
      10 [-]: LOADB R6 0   
      11 [-]: CALL R2 4 1  
      12 [-]: FASTCALL1 62 R1 L0
      13 [-]: MOVE R4 R1   
      14 [-]: GETIMPORT R3 6 [0x7B998233]
      15 [-]: CALL R3 1 1  
L 0:  16 [-]: JUMPIF R3 L3 
      17 [-]: JUMPXEQKN R1 K7 L3 NOT [1]
      18 [-]: FASTCALL1 62 R2 L1
      19 [-]: MOVE R4 R2   
      20 [-]: GETIMPORT R3 6 [0x7B998233]
      21 [-]: CALL R3 1 1  
L 1:  22 [-]: JUMPIFNOT R3 L3
      23 [-]: GETIMPORT R4 9 [0xBE190284]
      24 [-]: FASTCALL1 62 R4 L2
      25 [-]: GETIMPORT R3 6 [0x7B998233]
      26 [-]: CALL R3 1 1  
L 2:  27 [-]: JUMPIF R3 L3 
      28 [-]: GETIMPORT R3 9 [0xBE190284]
      29 [-]: MOVE R5 R0   
      30 [-]: NAMECALL R3 R3 K10 [0x057AE22F]
      31 [-]: CALL R3 2 0  
L 3:  32 [-]: RETURN R0 0  


; Name:            
; Defined at line: 1266
; #Upvalues:       1
; #Parameters:     4
; Is_vararg:       0
; Max Stack Size:  8

       0 [-]: GETUPVAL R4 0
       1 [-]: MOVE R5 R0   
       2 [-]: CALL R4 1 0  
       3 [-]: GETIMPORT R4 2 [0xE27B35BB]
       4 [-]: CALL R4 0 1  
       5 [-]: MOVE R5 R2   
       6 [-]: JUMPIF R5 L0 
       7 [-]: LOADN R5 0   
L 0:   8 [-]: SETTABLEKS R5 R4 K3 ["dialogType"]
       9 [-]: SETTABLEKS R0 R4 K4 ["locString"]
      10 [-]: FASTCALL1 62 R3 L1
      11 [-]: MOVE R6 R3   
      12 [-]: GETIMPORT R5 6 [0x7B998233]
      13 [-]: CALL R5 1 1  
L 1:  14 [-]: JUMPIFNOT R5 L2
      15 [-]: LOADB R3 0   
L 2:  16 [-]: SETTABLEKS R3 R4 K7 ["disableLocalization"]
      17 [-]: JUMPXEQKNIL R1 L3
      18 [-]: MOVE R7 R1   
      19 [-]: NAMECALL R5 R4 K8 [0xE6CCC5B9]
      20 [-]: CALL R5 2 0  
L 3:  21 [-]: GETIMPORT R5 10 [0x83F4E77C]
      22 [-]: NAMECALL R5 R5 K11 [0x7D63F19C]
      23 [-]: CALL R5 1 1  
      24 [-]: MOVE R7 R4   
      25 [-]: NAMECALL R5 R5 K12 [0x69E5AA4F]
      26 [-]: CALL R5 2 1  
      27 [-]: RETURN R5 1  


; Name:            
; Defined at line: 1281
; #Upvalues:       0
; #Parameters:     4
; Is_vararg:       0
; Max Stack Size:  9

       0 [-]: GETGLOBAL R4 K0 ["_ShowMessage"]
       1 [-]: MOVE R5 R0   
       2 [-]: MOVE R6 R1   
       3 [-]: MOVE R7 R2   
       4 [-]: MOVE R8 R3   
       5 [-]: CALL R4 4 1  
       6 [-]: RETURN R4 1  


; Name:            
; Defined at line: 1285
; #Upvalues:       2
; #Parameters:     5
; Is_vararg:       0
; Max Stack Size:  12

       0 [-]: GETUPVAL R5 0
       1 [-]: MOVE R6 R0   
       2 [-]: CALL R5 1 0  
       3 [-]: FASTCALL1 62 R4 L0
       4 [-]: MOVE R7 R4   
       5 [-]: GETIMPORT R6 1 [0x7B998233]
       6 [-]: CALL R6 1 1  
L 0:   7 [-]: GETIMPORT R7 4 ["BackgroundMovie"]
       8 [-]: JUMPIFNOT R6 L1
       9 [-]: MOVE R5 R7   
      10 [-]: JUMP L2
     
L 1:  11 [-]: MOVE R5 R4   
      12 [-]: JUMP L2
     
L 2:  13 [-]: MOVE R6 R0   
      14 [-]: FASTCALL1 62 R5 L3
      15 [-]: MOVE R8 R5   
      16 [-]: GETIMPORT R7 1 [0x7B998233]
      17 [-]: CALL R7 1 1  
L 3:  18 [-]: JUMPIF R7 L5 
      19 [-]: LOADK R9 K5 [" <BIG_PROBLEM> \n\r"]
      20 [-]: LOADB R10 1  
      21 [-]: NAMECALL R7 R5 K6 [0x42B04007]
      22 [-]: CALL R7 3 1  
      23 [-]: MOVE R6 R7   
      24 [-]: JUMPIFNOT R3 L4
      25 [-]: MOVE R7 R6   
      26 [-]: MOVE R8 R0   
      27 [-]: CONCAT R6 R7 R8
      28 [-]: JUMP L5
     
L 4:  29 [-]: MOVE R7 R6   
      30 [-]: MOVE R10 R0  
      31 [-]: LOADB R11 1  
      32 [-]: NAMECALL R8 R5 K6 [0x42B04007]
      33 [-]: CALL R8 3 1  
      34 [-]: CONCAT R6 R7 R8
L 5:  35 [-]: GETUPVAL R7 1
      36 [-]: GETIMPORT R9 8 [0x0032441C]
      37 [-]: GETTABLEKS R8 R9 K9 ["UISound_Error"]
      38 [-]: CALL R7 1 0  
      39 [-]: GETIMPORT R7 12 [0xE27B35BB]
      40 [-]: CALL R7 0 1  
      41 [-]: MOVE R8 R2   
      42 [-]: JUMPIF R8 L6 
      43 [-]: LOADN R8 0   
L 6:  44 [-]: SETTABLEKS R8 R7 K13 ["dialogType"]
      45 [-]: SETTABLEKS R6 R7 K14 ["locString"]
      46 [-]: FASTCALL1 62 R5 L7
      47 [-]: MOVE R10 R5  
      48 [-]: GETIMPORT R9 1 [0x7B998233]
      49 [-]: CALL R9 1 1  
L 7:  50 [-]: NOT R8 R9    
      51 [-]: JUMPIF R8 L9 
      52 [-]: JUMPXEQKB R3 1 L8
      53 [-]: LOADB R8 0 +1
L 8:  54 [-]: LOADB R8 1   
L 9:  55 [-]: SETTABLEKS R8 R7 K15 ["disableLocalization"]
      56 [-]: JUMPXEQKNIL R1 L10
      57 [-]: MOVE R10 R1  
      58 [-]: NAMECALL R8 R7 K16 [0xE6CCC5B9]
      59 [-]: CALL R8 2 0  
L10:  60 [-]: GETIMPORT R8 18 [0x83F4E77C]
      61 [-]: NAMECALL R8 R8 K19 [0x7D63F19C]
      62 [-]: CALL R8 1 1  
      63 [-]: MOVE R10 R7  
      64 [-]: NAMECALL R8 R8 K20 [0x69E5AA4F]
      65 [-]: CALL R8 2 1  
      66 [-]: RETURN R8 1  


; Name:            
; Defined at line: 1310
; #Upvalues:       1
; #Parameters:     1
; Is_vararg:       0
; Max Stack Size:  4

       0 [-]: GETUPVAL R1 0
       1 [-]: GETTABLEKS R2 R0 K0 ["locString"]
       2 [-]: CALL R1 1 0  
       3 [-]: GETIMPORT R1 2 [0x83F4E77C]
       4 [-]: NAMECALL R1 R1 K3 [0x7D63F19C]
       5 [-]: CALL R1 1 1  
       6 [-]: MOVE R3 R0   
       7 [-]: NAMECALL R1 R1 K4 [0x69E5AA4F]
       8 [-]: CALL R1 2 1  
       9 [-]: RETURN R1 1  


; Name:            
; Defined at line: 1315
; #Upvalues:       0
; #Parameters:     2
; Is_vararg:       0
; Max Stack Size:  15

       0 [-]: GETIMPORT R2 2 [0x1467D5F4]
       1 [-]: CALL R2 0 1  
       2 [-]: JUMPIFNOT R2 L1
       3 [-]: GETTABLEN R5 R1 1
       4 [-]: LOADK R6 K3 [".Callout"]
       5 [-]: CONCAT R4 R5 R6
       6 [-]: LOADN R5 0   
       7 [-]: NAMECALL R2 R0 K4 [0x91A24E4B]
       8 [-]: CALL R2 3 1  
       9 [-]: LOADN R5 2   
      10 [-]: LENGTH R3 R1 
      11 [-]: LOADN R4 1   
      12 [-]: FORNPREP R3 L1
L 0:  13 [-]: LOADN R7 10  
      14 [-]: GETIMPORT R8 6 [0x03F57322]
      15 [-]: SUBK R14 R5 K7 [1]
      16 [-]: GETTABLE R12 R1 R14
      17 [-]: LOADK R13 K8 [".Callout.Label"]
      18 [-]: CONCAT R11 R12 R13
      19 [-]: LOADK R12 K9 ["textWidth"]
      20 [-]: NAMECALL R9 R0 K10 [0x5B638CCE]
      21 [-]: CALL R9 3 -1 
      22 [-]: CALL R8 -1 1 
      23 [-]: ADD R6 R7 R8 
      24 [-]: GETTABLE R9 R1 R5
      25 [-]: LOADK R10 K11 ["Callout"]
      26 [-]: LOADN R11 0  
      27 [-]: ADD R12 R2 R6
      28 [-]: NAMECALL R7 R0 K12 [0xF64B7262]
      29 [-]: CALL R7 5 0  
      30 [-]: ADD R2 R2 R6 
      31 [-]: FORNLOOP R3 L0
L 1:  32 [-]: RETURN R0 0  


; Name:            
; Defined at line: 1328
; #Upvalues:       0
; #Parameters:     3
; Is_vararg:       0
; Max Stack Size:  8

       0 [-]: MOVE R3 R1   
L 0:   1 [-]: LOADK R6 K0 ["Prev_"]
       2 [-]: MOVE R7 R3   
       3 [-]: CONCAT R5 R6 R7
       4 [-]: GETTABLE R4 R0 R5
       5 [-]: JUMPXEQKNIL R4 L1
       6 [-]: LOADK R4 K0 ["Prev_"]
       7 [-]: MOVE R5 R3   
       8 [-]: CONCAT R3 R4 R5
       9 [-]: JUMPBACK L0  
L 1:  10 [-]: LOADK R5 K0 ["Prev_"]
      11 [-]: MOVE R6 R3   
      12 [-]: CONCAT R4 R5 R6
      13 [-]: GETTABLE R5 R0 R1
      14 [-]: SETTABLE R5 R0 R4
      15 [-]: LOADK R6 K0 ["Prev_"]
      16 [-]: MOVE R7 R3   
      17 [-]: CONCAT R5 R6 R7
      18 [-]: GETTABLE R4 R0 R5
      19 [-]: JUMPXEQKNIL R4 L2
      20 [-]: NEWCLOSURE R4 P0
      21 [-]: MOVE R0 R0   
      22 [-]: MOVE R1 R3   
      23 [-]: MOVE R0 R2   
      24 [-]: SETTABLE R4 R0 R1
      25 [-]: JUMP L3
     
L 2:  26 [-]: SETTABLE R2 R0 R1
L 3:  27 [-]: CLOSEUPVALS R3
      28 [-]: RETURN R0 0  


; Name:            
; Defined at line: 1345
; #Upvalues:       0
; #Parameters:     4
; Is_vararg:       0
; Max Stack Size:  8

       0 [-]: LOADK R5 K0 ["m"]
       1 [-]: MOVE R6 R2   
       2 [-]: CONCAT R4 R5 R6
       3 [-]: GETTABLE R5 R1 R4
       4 [-]: JUMPXEQKNIL R5 L2 NOT
       5 [-]: NEWTABLE R5 0 0
       6 [-]: SETTABLE R5 R1 R4
       7 [-]: GETTABLE R6 R1 R2
       8 [-]: FASTCALL1 62 R6 L0
       9 [-]: GETIMPORT R5 2 [0x7B998233]
      10 [-]: CALL R5 1 1  
L 0:  11 [-]: JUMPIF R5 L1 
      12 [-]: GETTABLE R5 R1 R4
      13 [-]: NEWTABLE R6 0 1
      14 [-]: GETTABLE R7 R1 R2
      15 [-]: SETLIST R6 R7 1 [1]
      16 [-]: SETTABLE R6 R5 R2
L 1:  17 [-]: NEWCLOSURE R5 P0
      18 [-]: MOVE R0 R1   
      19 [-]: MOVE R0 R4   
      20 [-]: SETTABLE R5 R1 R2
L 2:  21 [-]: GETTABLE R5 R1 R4
      22 [-]: NEWTABLE R6 0 1
      23 [-]: MOVE R7 R3   
      24 [-]: SETLIST R6 R7 1 [1]
      25 [-]: SETTABLE R6 R5 R0
      26 [-]: RETURN R0 0  


; Name:            
; Defined at line: 1362
; #Upvalues:       0
; #Parameters:     1
; Is_vararg:       0
; Max Stack Size:  5

       0 [-]: LOADB R1 1   
       1 [-]: GETIMPORT R2 2 [0xA5C556B9]
       2 [-]: MOVE R3 R0   
       3 [-]: LOADK R4 K3 ["ERROR_INTERNET_"]
       4 [-]: CALL R2 2 1  
       5 [-]: JUMPXEQKNIL R2 L1 NOT
       6 [-]: LOADB R1 1   
       7 [-]: GETIMPORT R2 2 [0xA5C556B9]
       8 [-]: MOVE R3 R0   
       9 [-]: LOADK R4 K4 ["ERROR_HTTP_"]
      10 [-]: CALL R2 2 1  
      11 [-]: JUMPXEQKNIL R2 L1 NOT
      12 [-]: LOADB R1 1   
      13 [-]: GETIMPORT R2 2 [0xA5C556B9]
      14 [-]: MOVE R3 R0   
      15 [-]: LOADK R4 K5 ["HttpSendRequest failed"]
      16 [-]: CALL R2 2 1  
      17 [-]: JUMPXEQKNIL R2 L1 NOT
      18 [-]: LOADB R1 1   
      19 [-]: GETIMPORT R2 2 [0xA5C556B9]
      20 [-]: MOVE R3 R0   
      21 [-]: LOADK R4 K6 ["HTTPRequest wait failed"]
      22 [-]: CALL R2 2 1  
      23 [-]: JUMPXEQKNIL R2 L1 NOT
      24 [-]: LOADB R1 1   
      25 [-]: GETIMPORT R2 2 [0xA5C556B9]
      26 [-]: MOVE R3 R0   
      27 [-]: LOADK R4 K7 ["HTTPRequest::Open failed"]
      28 [-]: CALL R2 2 1  
      29 [-]: JUMPXEQKNIL R2 L1 NOT
      30 [-]: LOADB R1 1   
      31 [-]: GETIMPORT R2 2 [0xA5C556B9]
      32 [-]: MOVE R3 R0   
      33 [-]: LOADK R4 K8 ["HTTPRequest::Send failed"]
      34 [-]: CALL R2 2 1  
      35 [-]: JUMPXEQKNIL R2 L1 NOT
      36 [-]: LOADB R1 1   
      37 [-]: GETIMPORT R2 2 [0xA5C556B9]
      38 [-]: MOVE R3 R0   
      39 [-]: LOADK R4 K9 ["HTTP error"]
      40 [-]: CALL R2 2 1  
      41 [-]: JUMPXEQKNIL R2 L1 NOT
      42 [-]: GETIMPORT R2 2 [0xA5C556B9]
      43 [-]: MOVE R3 R0   
      44 [-]: LOADK R4 K10 ["OpenSSL"]
      45 [-]: CALL R2 2 1  
      46 [-]: JUMPXEQKNIL R2 L0 NOT
      47 [-]: LOADB R1 0 +1
L 0:  48 [-]: LOADB R1 1   
L 1:  49 [-]: RETURN R1 1  


; Name:            
; Defined at line: 1375
; #Upvalues:       1
; #Parameters:     1
; Is_vararg:       0
; Max Stack Size:  3

       0 [-]: GETUPVAL R1 0
       1 [-]: MOVE R2 R0   
       2 [-]: CALL R1 1 1  
       3 [-]: RETURN R1 1  


; Name:            
; Defined at line: 1379
; #Upvalues:       1
; #Parameters:     1
; Is_vararg:       0
; Max Stack Size:  6

       0 [-]: GETIMPORT R1 1 [0x3D106989]
       1 [-]: MOVE R2 R0   
       2 [-]: CALL R1 1 0  
       3 [-]: GETUPVAL R1 0
       4 [-]: MOVE R2 R0   
       5 [-]: CALL R1 1 1  
       6 [-]: LOADNIL R2   
       7 [-]: JUMPIFNOT R1 L0
       8 [-]: LOADK R2 K2 ["/Lotus/Language/Menu/SocialOverlay_NoConnectionError"]
       9 [-]: RETURN R2 1  
L 0:  10 [-]: GETIMPORT R3 5 [0xA5C556B9]
      11 [-]: MOVE R4 R0   
      12 [-]: LOADK R5 K6 ["Authentication failure"]
      13 [-]: CALL R3 2 1  
      14 [-]: JUMPXEQKNIL R3 L1
      15 [-]: LOADK R2 K7 ["/Lotus/Language/Menu/CraftingErrorText_AuthenticationFailed"]
      16 [-]: RETURN R2 1  
L 1:  17 [-]: GETIMPORT R3 5 [0xA5C556B9]
      18 [-]: MOVE R4 R0   
      19 [-]: LOADK R5 K8 ["Log-in expired"]
      20 [-]: CALL R3 2 1  
      21 [-]: JUMPXEQKNIL R3 L2
      22 [-]: LOADK R2 K9 ["/Lotus/Language/Menu/ConnectionError_LoginExpired"]
      23 [-]: RETURN R2 1  
L 2:  24 [-]: GETIMPORT R3 5 [0xA5C556B9]
      25 [-]: MOVE R4 R0   
      26 [-]: LOADK R5 K10 ["Guild does not exist"]
      27 [-]: CALL R3 2 1  
      28 [-]: JUMPXEQKNIL R3 L3
      29 [-]: LOADK R2 K11 ["/Lotus/Language/Menu/SocialOverlay_NonExistentGuildError"]
      30 [-]: RETURN R2 1  
L 3:  31 [-]: GETIMPORT R3 5 [0xA5C556B9]
      32 [-]: MOVE R4 R0   
      33 [-]: LOADK R5 K12 ["does not exist"]
      34 [-]: CALL R3 2 1  
      35 [-]: JUMPXEQKNIL R3 L4
      36 [-]: LOADK R2 K13 ["/Lotus/Language/Menu/SocialOverlay_NonExistentUserError"]
      37 [-]: RETURN R2 1  
L 4:  38 [-]: GETIMPORT R3 5 [0xA5C556B9]
      39 [-]: MOVE R4 R0   
      40 [-]: LOADK R5 K14 ["is ignoring you"]
      41 [-]: CALL R3 2 1  
      42 [-]: JUMPXEQKNIL R3 L5
      43 [-]: LOADK R2 K15 ["/Lotus/Language/Menu/Chat_PlayerIgnoringYou"]
      44 [-]: RETURN R2 1  
L 5:  45 [-]: GETIMPORT R3 5 [0xA5C556B9]
      46 [-]: MOVE R4 R0   
      47 [-]: LOADK R5 K16 ["User is already in a guild"]
      48 [-]: CALL R3 2 1  
      49 [-]: JUMPXEQKNIL R3 L6
      50 [-]: LOADK R2 K17 ["/Lotus/Language/Menu/SocialOverlay_UserAlreadyInGuildError"]
      51 [-]: RETURN R2 1  
L 6:  52 [-]: GETIMPORT R3 5 [0xA5C556B9]
      53 [-]: MOVE R4 R0   
      54 [-]: LOADK R5 K18 ["User already invited to clan"]
      55 [-]: CALL R3 2 1  
      56 [-]: JUMPXEQKNIL R3 L7
      57 [-]: LOADK R2 K17 ["/Lotus/Language/Menu/SocialOverlay_UserAlreadyInGuildError"]
      58 [-]: RETURN R2 1  
L 7:  59 [-]: GETIMPORT R3 5 [0xA5C556B9]
      60 [-]: MOVE R4 R0   
      61 [-]: LOADK R5 K19 ["User is not in a guild"]
      62 [-]: CALL R3 2 1  
      63 [-]: JUMPXEQKNIL R3 L8
      64 [-]: LOADK R2 K20 ["/Lotus/Language/Menu/SocialOverlay_UserNotInGuildError"]
      65 [-]: RETURN R2 1  
L 8:  66 [-]: GETIMPORT R3 5 [0xA5C556B9]
      67 [-]: MOVE R4 R0   
      68 [-]: LOADK R5 K21 ["Invalid permission"]
      69 [-]: CALL R3 2 1  
      70 [-]: JUMPXEQKNIL R3 L9
      71 [-]: LOADK R2 K22 ["/Lotus/Language/Dojo/Generic_INVALID_PERMISSION"]
      72 [-]: RETURN R2 1  
L 9:  73 [-]: GETIMPORT R3 5 [0xA5C556B9]
      74 [-]: MOVE R4 R0   
      75 [-]: LOADK R5 K23 ["Guild has no member with id"]
      76 [-]: CALL R3 2 1  
      77 [-]: JUMPXEQKNIL R3 L10
      78 [-]: LOADK R2 K20 ["/Lotus/Language/Menu/SocialOverlay_UserNotInGuildError"]
      79 [-]: RETURN R2 1  
L10:  80 [-]: GETIMPORT R3 5 [0xA5C556B9]
      81 [-]: MOVE R4 R0   
      82 [-]: LOADK R5 K24 ["Guild name already in use"]
      83 [-]: CALL R3 2 1  
      84 [-]: JUMPXEQKNIL R3 L11
      85 [-]: LOADK R2 K25 ["/Lotus/Language/Menu/SocialOverlay_GuildNameAlreadyInUseError"]
      86 [-]: RETURN R2 1  
L11:  87 [-]: GETIMPORT R3 5 [0xA5C556B9]
      88 [-]: MOVE R4 R0   
      89 [-]: LOADK R5 K26 ["Alliance name already in use"]
      90 [-]: CALL R3 2 1  
      91 [-]: JUMPXEQKNIL R3 L12
      92 [-]: LOADK R2 K27 ["/Lotus/Language/Menu/SocialOverlay_AllianceNameAlreadyInUseError"]
      93 [-]: RETURN R2 1  
L12:  94 [-]: GETIMPORT R3 5 [0xA5C556B9]
      95 [-]: MOVE R4 R0   
      96 [-]: LOADK R5 K28 ["Already invited to alliance"]
      97 [-]: CALL R3 2 1  
      98 [-]: JUMPXEQKNIL R3 L13
      99 [-]: LOADK R2 K29 ["/Lotus/Language/Menu/SocialOverlay_GuildAlreadyInvitedToAllianceError"]
     100 [-]: RETURN R2 1  
L13: 101 [-]: GETIMPORT R3 5 [0xA5C556B9]
     102 [-]: MOVE R4 R0   
     103 [-]: LOADK R5 K30 ["Guild is already in an alliance"]
     104 [-]: CALL R3 2 1  
     105 [-]: JUMPXEQKNIL R3 L14
     106 [-]: LOADK R2 K31 ["/Lotus/Language/Menu/SocialOverlay_GuildAlreadyInAllianceError"]
     107 [-]: RETURN R2 1  
L14: 108 [-]: GETIMPORT R3 5 [0xA5C556B9]
     109 [-]: MOVE R4 R0   
     110 [-]: LOADK R5 K32 ["No pending alliance invitation."]
     111 [-]: CALL R3 2 1  
     112 [-]: JUMPXEQKNIL R3 L15
     113 [-]: LOADK R2 K33 ["/Lotus/Language/Menu/SocialOverlay_NotInAllianceError"]
     114 [-]: RETURN R2 1  
L15: 115 [-]: GETIMPORT R3 5 [0xA5C556B9]
     116 [-]: MOVE R4 R0   
     117 [-]: LOADK R5 K34 ["Service Unavailable"]
     118 [-]: CALL R3 2 1  
     119 [-]: JUMPXEQKNIL R3 L16
     120 [-]: LOADK R2 K35 ["/Lotus/Language/Menu/Profile_FailedToConnect"]
     121 [-]: RETURN R2 1  
L16: 122 [-]: GETIMPORT R3 5 [0xA5C556B9]
     123 [-]: MOVE R4 R0   
     124 [-]: LOADK R5 K36 ["Connection attempt timed out."]
     125 [-]: CALL R3 2 1  
     126 [-]: JUMPXEQKNIL R3 L17
     127 [-]: LOADK R2 K37 ["/Lotus/Language/Game/Connection_attempt_timed_out"]
     128 [-]: RETURN R2 1  
L17: 129 [-]: GETIMPORT R3 5 [0xA5C556B9]
     130 [-]: MOVE R4 R0   
     131 [-]: LOADK R5 K38 ["Bad server port-range"]
     132 [-]: CALL R3 2 1  
     133 [-]: JUMPXEQKNIL R3 L18
     134 [-]: LOADK R2 K39 ["/Lotus/Language/Game/Bad_server_port_range"]
     135 [-]: RETURN R2 1  
L18: 136 [-]: GETIMPORT R3 5 [0xA5C556B9]
     137 [-]: MOVE R4 R0   
     138 [-]: LOADK R5 K40 ["Disconnected"]
     139 [-]: CALL R3 2 1  
     140 [-]: JUMPXEQKNIL R3 L19
     141 [-]: LOADK R2 K41 ["/Lotus/Language/Game/DisconnectedMsg"]
     142 [-]: RETURN R2 1  
L19: 143 [-]: GETIMPORT R3 5 [0xA5C556B9]
     144 [-]: MOVE R4 R0   
     145 [-]: LOADK R5 K42 ["RESTRICTED_CLAN_NAME"]
     146 [-]: CALL R3 2 1  
     147 [-]: JUMPXEQKNIL R3 L20
     148 [-]: LOADK R2 K43 ["/Lotus/Language/Clan/Clan_Name_Profanity_Error"]
     149 [-]: RETURN R2 1  
L20: 150 [-]: LOADK R2 K2 ["/Lotus/Language/Menu/SocialOverlay_NoConnectionError"]
     151 [-]: RETURN R2 1  


; Name:            
; Defined at line: 1437
; #Upvalues:       1
; #Parameters:     1
; Is_vararg:       0
; Max Stack Size:  3

       0 [-]: GETUPVAL R1 0
       1 [-]: MOVE R2 R0   
       2 [-]: CALL R1 1 1  
       3 [-]: RETURN R1 1  


; Name:            
; Defined at line: 1441
; #Upvalues:       1
; #Parameters:     1
; Is_vararg:       0
; Max Stack Size:  5

       0 [-]: LOADNIL R1   
       1 [-]: LENGTH R2 R0 
       2 [-]: JUMPXEQKN R2 K0 L0 NOT [0]
       3 [-]: LOADK R1 K1 ["/Lotus/Language/Menu/SocialOverlay_NonExistentUserError"]
       4 [-]: RETURN R1 1  
L 0:   5 [-]: GETIMPORT R2 4 [0xA5C556B9]
       6 [-]: MOVE R3 R0   
       7 [-]: LOADK R4 K5 ["Friend Invite Restriction"]
       8 [-]: CALL R2 2 1  
       9 [-]: JUMPXEQKNIL R2 L1
      10 [-]: LOADK R1 K6 ["/Lotus/Language/Game/Friend_Invite_Restriction"]
      11 [-]: RETURN R1 1  
L 1:  12 [-]: GETIMPORT R2 4 [0xA5C556B9]
      13 [-]: MOVE R3 R0   
      14 [-]: LOADK R4 K7 ["Player has too many friends"]
      15 [-]: CALL R2 2 1  
      16 [-]: JUMPXEQKNIL R2 L2
      17 [-]: LOADK R1 K8 ["/Lotus/Language/Game/TooManyFriends"]
      18 [-]: RETURN R1 1  
L 2:  19 [-]: GETIMPORT R2 4 [0xA5C556B9]
      20 [-]: MOVE R3 R0   
      21 [-]: LOADK R4 K9 ["Target player has too many friends"]
      22 [-]: CALL R2 2 1  
      23 [-]: JUMPXEQKNIL R2 L3
      24 [-]: LOADK R1 K10 ["/Lotus/Language/Game/TargetTooManyFriends"]
      25 [-]: RETURN R1 1  
L 3:  26 [-]: GETIMPORT R2 4 [0xA5C556B9]
      27 [-]: MOVE R3 R0   
      28 [-]: LOADK R4 K11 ["Account Suspended"]
      29 [-]: CALL R2 2 1  
      30 [-]: JUMPXEQKNIL R2 L4
      31 [-]: LOADK R1 K12 ["/Lotus/Language/CustomerSupport/CompromisedAccountGenericMessage"]
      32 [-]: RETURN R1 1  
L 4:  33 [-]: GETIMPORT R2 4 [0xA5C556B9]
      34 [-]: MOVE R3 R0   
      35 [-]: LOADK R4 K13 ["Already a friend"]
      36 [-]: CALL R2 2 1  
      37 [-]: JUMPXEQKNIL R2 L6
      38 [-]: FASTCALL2K 45 R0 K14 L5 [17]
      39 [-]: MOVE R3 R0   
      40 [-]: LOADK R4 K14 [17]
      41 [-]: GETIMPORT R2 16 [0x1A94C9CC]
      42 [-]: CALL R2 2 1  
L 5:  43 [-]: MOVE R1 R2   
      44 [-]: RETURN R1 1  
L 6:  45 [-]: GETIMPORT R2 4 [0xA5C556B9]
      46 [-]: MOVE R3 R0   
      47 [-]: LOADK R4 K17 ["Added a blocked Xbox player"]
      48 [-]: CALL R2 2 1  
      49 [-]: JUMPXEQKNIL R2 L7
      50 [-]: LOADK R1 K18 ["/Lotus/Language/Menu/SocialOverlay_AddBlockedPlayerError"]
      51 [-]: RETURN R1 1  
L 7:  52 [-]: GETIMPORT R2 4 [0xA5C556B9]
      53 [-]: MOVE R3 R0   
      54 [-]: LOADK R4 K19 ["PLATFORM_MISMATCH"]
      55 [-]: CALL R2 2 1  
      56 [-]: JUMPXEQKNIL R2 L9
      57 [-]: FASTCALL2K 45 R0 K20 L8 [18]
      58 [-]: MOVE R3 R0   
      59 [-]: LOADK R4 K20 [18]
      60 [-]: GETIMPORT R2 16 [0x1A94C9CC]
      61 [-]: CALL R2 2 1  
L 8:  62 [-]: MOVE R1 R2   
      63 [-]: RETURN R1 1  
L 9:  64 [-]: GETUPVAL R2 0
      65 [-]: MOVE R3 R0   
      66 [-]: CALL R2 1 1  
      67 [-]: MOVE R1 R2   
      68 [-]: RETURN R1 1  


; Name:            
; Defined at line: 1466
; #Upvalues:       1
; #Parameters:     1
; Is_vararg:       0
; Max Stack Size:  5

       0 [-]: MOVE R1 R0   
       1 [-]: JUMPXEQKS R0 K0 L0 NOT ["1"]
       2 [-]: LOADK R1 K1 ["/Lotus/Language/Menu/ClanCreationItemRequired"]
       3 [-]: JUMP L14
    
L 0:   4 [-]: JUMPXEQKS R0 K2 L5 NOT ["MAX_SIZE"]
       5 [-]: GETIMPORT R2 4 [0x25D99D89]
       6 [-]: NAMECALL R2 R2 K5 [0x6CA27630]
       7 [-]: CALL R2 1 1  
       8 [-]: LENGTH R3 R2 
       9 [-]: LOADN R4 1000
      10 [-]: JUMPIFNOTLE R4 R3 L1
      11 [-]: LOADK R1 K6 ["/Lotus/Language/Menu/GuildSizeCap5"]
      12 [-]: JUMP L14
    
L 1:  13 [-]: LENGTH R3 R2 
      14 [-]: LOADN R4 300 
      15 [-]: JUMPIFNOTLE R4 R3 L2
      16 [-]: LOADK R1 K7 ["/Lotus/Language/Menu/GuildSizeCap4"]
      17 [-]: JUMP L14
    
L 2:  18 [-]: LENGTH R3 R2 
      19 [-]: LOADN R4 100 
      20 [-]: JUMPIFNOTLE R4 R3 L3
      21 [-]: LOADK R1 K8 ["/Lotus/Language/Menu/GuildSizeCap3"]
      22 [-]: JUMP L14
    
L 3:  23 [-]: LENGTH R3 R2 
      24 [-]: LOADN R4 30  
      25 [-]: JUMPIFNOTLE R4 R3 L4
      26 [-]: LOADK R1 K9 ["/Lotus/Language/Menu/GuildSizeCap2"]
      27 [-]: JUMP L14
    
L 4:  28 [-]: LOADK R1 K10 ["/Lotus/Language/Menu/GuildSizeCap1"]
      29 [-]: JUMP L14
    
L 5:  30 [-]: GETIMPORT R2 13 [0xA5C556B9]
      31 [-]: MOVE R3 R0   
      32 [-]: LOADK R4 K14 ["Invite restricted"]
      33 [-]: CALL R2 2 1  
      34 [-]: JUMPIFNOT R2 L6
      35 [-]: LOADK R1 K15 ["/Lotus/Language/Menu/SocialOverlay_UserGuildInviteRestricted"]
      36 [-]: JUMP L14
    
L 6:  37 [-]: GETIMPORT R2 13 [0xA5C556B9]
      38 [-]: MOVE R3 R0   
      39 [-]: LOADK R4 K16 ["Account Suspended"]
      40 [-]: CALL R2 2 1  
      41 [-]: JUMPIFNOT R2 L7
      42 [-]: LOADK R1 K17 ["/Lotus/Language/CustomerSupport/CompromisedAccountGenericMessage"]
      43 [-]: JUMP L14
    
L 7:  44 [-]: GETIMPORT R2 13 [0xA5C556B9]
      45 [-]: MOVE R3 R0   
      46 [-]: LOADK R4 K18 ["Already requested"]
      47 [-]: CALL R2 2 1  
      48 [-]: JUMPIFNOT R2 L8
      49 [-]: LOADK R1 K19 ["/Lotus/Language/Clan/JoinClanAlreadyRequested"]
      50 [-]: JUMP L14
    
L 8:  51 [-]: GETIMPORT R2 13 [0xA5C556B9]
      52 [-]: MOVE R3 R0   
      53 [-]: LOADK R4 K20 ["Already pending"]
      54 [-]: CALL R2 2 1  
      55 [-]: JUMPIFNOT R2 L9
      56 [-]: LOADK R1 K21 ["/Lotus/Language/Clan/CheckPendingTab"]
      57 [-]: JUMP L14
    
L 9:  58 [-]: GETIMPORT R2 13 [0xA5C556B9]
      59 [-]: MOVE R3 R0   
      60 [-]: LOADK R4 K22 ["Request limit"]
      61 [-]: CALL R2 2 1  
      62 [-]: JUMPIFNOT R2 L10
      63 [-]: LOADK R1 K23 ["/Lotus/Language/Clan/TooManyJoinClanRequests"]
      64 [-]: JUMP L14
    
L10:  65 [-]: GETIMPORT R2 13 [0xA5C556B9]
      66 [-]: MOVE R3 R0   
      67 [-]: LOADK R4 K24 ["Has invite"]
      68 [-]: CALL R2 2 1  
      69 [-]: JUMPIFNOT R2 L11
      70 [-]: LOADK R1 K25 ["/Lotus/Language/Clan/JoinClanHasInvite"]
      71 [-]: JUMP L14
    
L11:  72 [-]: GETIMPORT R2 13 [0xA5C556B9]
      73 [-]: MOVE R3 R0   
      74 [-]: LOADK R4 K26 ["Must be tutored"]
      75 [-]: CALL R2 2 1  
      76 [-]: JUMPIFNOT R2 L12
      77 [-]: LOADK R1 K27 ["/Lotus/Language/Clan/UntutoredAccount"]
      78 [-]: JUMP L14
    
L12:  79 [-]: GETIMPORT R2 13 [0xA5C556B9]
      80 [-]: MOVE R3 R0   
      81 [-]: LOADK R4 K28 ["PLATFORM_MISMATCH"]
      82 [-]: CALL R2 2 1  
      83 [-]: JUMPXEQKNIL R2 L13
      84 [-]: LOADK R1 K29 ["/Lotus/Language/Multiplayer/SocialOverlay_GuildPlatformMismatch"]
      85 [-]: JUMP L14
    
L13:  86 [-]: GETUPVAL R2 0
      87 [-]: MOVE R3 R0   
      88 [-]: CALL R2 1 1  
      89 [-]: MOVE R1 R2   
L14:  90 [-]: JUMPIFNOTEQ R0 R1 L15
      91 [-]: LOADK R1 K30 ["/Lotus/Language/Menu/PurchaseFailure_UnknownError"]
L15:  92 [-]: RETURN R1 1  


; Name:            
; Defined at line: 1510
; #Upvalues:       0
; #Parameters:     0
; Is_vararg:       0
; Max Stack Size:  1

       0 [-]: GETIMPORT R0 2 [0x2A31B96E]
       1 [-]: CALL R0 0 1  
       2 [-]: JUMPIF R0 L0 
       3 [-]: GETIMPORT R0 4 [0x2B31BB01]
       4 [-]: CALL R0 0 1  
       5 [-]: JUMPIF R0 L0 
       6 [-]: GETIMPORT R0 6 [0x9AD21AE9]
       7 [-]: CALL R0 0 1  
       8 [-]: JUMPIF R0 L0 
       9 [-]: GETIMPORT R0 8 [0xC84FA15A]
      10 [-]: CALL R0 0 1  
L 0:  11 [-]: RETURN R0 1  


; Name:            
; Defined at line: 1514
; #Upvalues:       0
; #Parameters:     2
; Is_vararg:       0
; Max Stack Size:  7

       0 [-]: GETIMPORT R2 1 [0x3819560E]
       1 [-]: CALL R2 0 1  
       2 [-]: JUMPIFNOT R2 L0
       3 [-]: LOADN R3 0   
       4 [-]: RETURN R3 1  
L 0:   5 [-]: LOADK R4 K2 ["A-Za-z0-9"]
       6 [-]: LOADK R5 K3 ["_.\\-"]
       7 [-]: CONCAT R3 R4 R5
       8 [-]: JUMPXEQKNIL R1 L1
       9 [-]: MOVE R4 R3   
      10 [-]: MOVE R5 R1   
      11 [-]: CONCAT R3 R4 R5
L 1:  12 [-]: GETIMPORT R4 6 [0x9AD21AE9]
      13 [-]: CALL R4 0 1  
      14 [-]: JUMPIFNOT R4 L3
      15 [-]: JUMPXEQKNIL R1 L2
      16 [-]: GETIMPORT R4 9 [0xA5C556B9]
      17 [-]: MOVE R5 R1   
      18 [-]: LOADK R6 K10 [" "]
      19 [-]: CALL R4 2 1  
      20 [-]: JUMPXEQKNIL R4 L3 NOT
L 2:  21 [-]: MOVE R4 R3   
      22 [-]: LOADK R5 K10 [" "]
      23 [-]: CONCAT R3 R4 R5
L 3:  24 [-]: GETIMPORT R4 12 [0xEB8FDDD7]
      25 [-]: CALL R4 0 1  
      26 [-]: JUMPIFNOT R4 L4
      27 [-]: MOVE R4 R3   
      28 [-]: LOADK R5 K13 ["\\u4E00-\\u9FCC\\u3400-\\u4DB5"]
      29 [-]: CONCAT R3 R4 R5
L 4:  30 [-]: GETIMPORT R4 15 [0x09C87793]
      31 [-]: MOVE R5 R0   
      32 [-]: MOVE R6 R3   
      33 [-]: CALL R4 2 1  
      34 [-]: RETURN R4 1  


; Name:            
; Defined at line: 1539
; #Upvalues:       1
; #Parameters:     2
; Is_vararg:       0
; Max Stack Size:  5

       0 [-]: GETUPVAL R2 0
       1 [-]: MOVE R3 R0   
       2 [-]: MOVE R4 R1   
       3 [-]: CALL R2 2 1  
       4 [-]: RETURN R2 1  


; Name:            
; Defined at line: 1543
; #Upvalues:       1
; #Parameters:     3
; Is_vararg:       0
; Max Stack Size:  11

       0 [-]: LENGTH R3 R0 
       1 [-]: JUMPXEQKN R3 K0 L0 NOT [0]
       2 [-]: LENGTH R3 R2 
       3 [-]: JUMPXEQKN R3 K0 L0 [0]
       4 [-]: GETIMPORT R3 2 [0x603636AD]
       5 [-]: MOVE R4 R2   
       6 [-]: LOADNIL R5   
       7 [-]: CALL R3 2 -1 
       8 [-]: RETURN R3 -1 
L 0:   9 [-]: GETUPVAL R3 0
      10 [-]: MOVE R4 R0   
      11 [-]: LOADK R5 K3 [" &"]
      12 [-]: CALL R3 2 1  
      13 [-]: LOADN R4 0   
      14 [-]: JUMPIFNOTLT R4 R3 L1
      15 [-]: GETIMPORT R8 2 [0x603636AD]
      16 [-]: LOADK R9 K4 ["/Lotus/Language/Menu/SocialOverlay_InvalidCharacter"]
      17 [-]: LOADNIL R10  
      18 [-]: CALL R8 2 1  
      19 [-]: MOVE R5 R8   
      20 [-]: LOADK R6 K5 [" "]
      21 [-]: GETIMPORT R7 7 [0x68B0AFB4]
      22 [-]: MOVE R8 R0   
      23 [-]: MOVE R9 R3   
      24 [-]: MOVE R10 R3  
      25 [-]: CALL R7 3 1  
      26 [-]: CONCAT R4 R5 R7
      27 [-]: RETURN R4 1  
L 1:  28 [-]: GETIMPORT R4 9 [0x09423272]
      29 [-]: MOVE R5 R0   
      30 [-]: LOADN R6 1   
      31 [-]: CALL R4 2 1  
      32 [-]: JUMPIFEQ R4 R0 L2
      33 [-]: GETIMPORT R5 2 [0x603636AD]
      34 [-]: ORK R6 R1 K10 ["/Lotus/Language/Menu/Name_Profanity_Error"]
      35 [-]: LOADNIL R7   
      36 [-]: CALL R5 2 -1 
      37 [-]: RETURN R5 -1 
L 2:  38 [-]: LOADNIL R5   
      39 [-]: RETURN R5 1  


; Name:            
; Defined at line: 1561
; #Upvalues:       0
; #Parameters:     1
; Is_vararg:       0
; Max Stack Size:  6

       0 [-]: LOADK R2 K0 ["#"]
       1 [-]: GETIMPORT R3 3 [0xE8072DED]
       2 [-]: LOADK R4 K4 ["%X"]
       3 [-]: MOVE R5 R0   
       4 [-]: CALL R3 2 1  
       5 [-]: CONCAT R1 R2 R3
       6 [-]: RETURN R1 1  


; Name:            
; Defined at line: 1565
; #Upvalues:       0
; #Parameters:     1
; Is_vararg:       0
; Max Stack Size:  6

       0 [-]: DIVK R3 R0 K1 [65536]
       1 [-]: MODK R2 R3 K0 [256]
       2 [-]: DIVK R4 R0 K0 [256]
       3 [-]: MODK R3 R4 K0 [256]
       4 [-]: DIVK R5 R0 K2 [1]
       5 [-]: MODK R4 R5 K0 [256]
       6 [-]: DUPTABLE R1 6
       7 [-]: SETTABLEKS R2 R1 K3 ["r"]
       8 [-]: SETTABLEKS R3 R1 K4 ["g"]
       9 [-]: SETTABLEKS R4 R1 K5 ["b"]
      10 [-]: DUPTABLE R2 6
      11 [-]: GETTABLEKS R4 R1 K3 ["r"]
      12 [-]: DIVK R3 R4 K7 [255]
      13 [-]: SETTABLEKS R3 R2 K3 ["r"]
      14 [-]: GETTABLEKS R4 R1 K4 ["g"]
      15 [-]: DIVK R3 R4 K7 [255]
      16 [-]: SETTABLEKS R3 R2 K4 ["g"]
      17 [-]: GETTABLEKS R4 R1 K5 ["b"]
      18 [-]: DIVK R3 R4 K7 [255]
      19 [-]: SETTABLEKS R3 R2 K5 ["b"]
      20 [-]: RETURN R2 1  


; Name:            
; Defined at line: 1570
; #Upvalues:       0
; #Parameters:     1
; Is_vararg:       0
; Max Stack Size:  7

       0 [-]: DIVK R3 R0 K1 [65536]
       1 [-]: MODK R2 R3 K0 [256]
       2 [-]: DIVK R4 R0 K0 [256]
       3 [-]: MODK R3 R4 K0 [256]
       4 [-]: DIVK R5 R0 K2 [1]
       5 [-]: MODK R4 R5 K0 [256]
       6 [-]: DUPTABLE R1 6
       7 [-]: SETTABLEKS R2 R1 K3 ["r"]
       8 [-]: SETTABLEKS R3 R1 K4 ["g"]
       9 [-]: SETTABLEKS R4 R1 K5 ["b"]
      10 [-]: GETIMPORT R2 8 [0x60130201]
      11 [-]: GETTABLEKS R3 R1 K3 ["r"]
      12 [-]: GETTABLEKS R4 R1 K4 ["g"]
      13 [-]: GETTABLEKS R5 R1 K5 ["b"]
      14 [-]: LOADN R6 255 
      15 [-]: CALL R2 4 1  
      16 [-]: RETURN R2 1  


; Name:            
; Defined at line: 1575
; #Upvalues:       0
; #Parameters:     2
; Is_vararg:       0
; Max Stack Size:  8

       0 [-]: LOADK R5 K0 [".*"]
       1 [-]: MOVE R6 R1   
       2 [-]: LOADK R7 K1 ["()"]
       3 [-]: CONCAT R4 R5 R7
       4 [-]: NAMECALL R2 R0 K2 [0x348C01F7]
       5 [-]: CALL R2 2 1  
       6 [-]: JUMPXEQKNIL R2 L0 NOT
       7 [-]: LOADNIL R3   
       8 [-]: RETURN R3 1  
L 0:   9 [-]: SUBK R3 R2 K3 [1]
      10 [-]: RETURN R3 1  


; Name:            
; Defined at line: 1584
; #Upvalues:       0
; #Parameters:     1
; Is_vararg:       0
; Max Stack Size:  17

       0 [-]: GETIMPORT R1 1 [0x67513231]
       1 [-]: CALL R1 0 1  
       2 [-]: NAMECALL R1 R1 K2 [0x6D604BA7]
       3 [-]: CALL R1 1 1  
       4 [-]: NEWTABLE R2 0 9
       5 [-]: LOADK R3 K3 ["_en"]
       6 [-]: LOADK R4 K4 ["_fr"]
       7 [-]: LOADK R5 K5 ["_it"]
       8 [-]: LOADK R6 K6 ["_de"]
       9 [-]: LOADK R7 K7 ["_es"]
      10 [-]: LOADK R8 K8 ["_pt"]
      11 [-]: LOADK R9 K9 ["_ru"]
      12 [-]: LOADK R10 K10 ["_pl"]
      13 [-]: LOADK R11 K11 ["_uk"]
      14 [-]: SETLIST R2 R3 9 [1]
      15 [-]: GETIMPORT R4 13 [0xCFC01047]
      16 [-]: MOVE R5 R2   
      17 [-]: CALL R4 1 3  
      18 [-]: FORGPREP_NEXT R4 L1
L 0:  19 [-]: JUMPIFNOTEQ R8 R1 L1
      20 [-]: MOVE R3 R7   
      21 [-]: JUMP L2
     
L 1:  22 [-]: FORGLOOP R4 L0 2
      23 [-]: LOADN R3 -1  
L 2:  24 [-]: JUMPXEQKN R3 K14 L3 NOT [-1]
      25 [-]: RETURN R0 1  
L 3:  26 [-]: LOADK R3 K15 [""]
      27 [-]: NEWTABLE R4 0 10
      28 [-]: LOADK R5 K15 [""]
      29 [-]: LOADK R6 K16 ["C"]
      30 [-]: LOADK R7 K17 ["CC"]
      31 [-]: LOADK R8 K18 ["CCC"]
      32 [-]: LOADK R9 K19 ["CD"]
      33 [-]: LOADK R10 K20 ["D"]
      34 [-]: LOADK R11 K21 ["DC"]
      35 [-]: LOADK R12 K22 ["DCC"]
      36 [-]: LOADK R13 K23 ["DCCC"]
      37 [-]: LOADK R14 K24 ["CM"]
      38 [-]: SETLIST R4 R5 10 [1]
      39 [-]: NEWTABLE R5 0 10
      40 [-]: LOADK R6 K15 [""]
      41 [-]: LOADK R7 K25 ["X"]
      42 [-]: LOADK R8 K26 ["XX"]
      43 [-]: LOADK R9 K27 ["XXX"]
      44 [-]: LOADK R10 K28 ["XL"]
      45 [-]: LOADK R11 K29 ["L"]
      46 [-]: LOADK R12 K30 ["LX"]
      47 [-]: LOADK R13 K31 ["LXX"]
      48 [-]: LOADK R14 K32 ["LXXX"]
      49 [-]: LOADK R15 K33 ["XC"]
      50 [-]: SETLIST R5 R6 10 [1]
      51 [-]: NEWTABLE R6 0 10
      52 [-]: LOADK R7 K15 [""]
      53 [-]: LOADK R8 K34 ["I"]
      54 [-]: LOADK R9 K35 ["II"]
      55 [-]: LOADK R10 K36 ["III"]
      56 [-]: LOADK R11 K37 ["IV"]
      57 [-]: LOADK R12 K38 ["V"]
      58 [-]: LOADK R13 K39 ["VI"]
      59 [-]: LOADK R14 K40 ["VII"]
      60 [-]: LOADK R15 K41 ["VIII"]
      61 [-]: LOADK R16 K42 ["IX"]
      62 [-]: SETLIST R6 R7 10 [1]
L 4:  63 [-]: LOADN R7 1000
      64 [-]: JUMPIFNOTLE R7 R0 L5
      65 [-]: MOVE R7 R3   
      66 [-]: LOADK R8 K43 ["M"]
      67 [-]: CONCAT R3 R7 R8
      68 [-]: SUBK R0 R0 K44 [1000]
      69 [-]: JUMPBACK L4  
L 5:  70 [-]: MOVE R7 R3   
      71 [-]: DIVK R11 R0 K46 [100]
      72 [-]: FASTCALL1 12 R11 L6
      73 [-]: GETIMPORT R10 49 [0x55F27C30]
      74 [-]: CALL R10 1 1 
L 6:  75 [-]: ADDK R9 R10 K45 [1]
      76 [-]: GETTABLE R8 R4 R9
      77 [-]: CONCAT R3 R7 R8
      78 [-]: MODK R0 R0 K46 [100]
      79 [-]: MOVE R7 R3   
      80 [-]: DIVK R11 R0 K50 [10]
      81 [-]: FASTCALL1 12 R11 L7
      82 [-]: GETIMPORT R10 49 [0x55F27C30]
      83 [-]: CALL R10 1 1 
L 7:  84 [-]: ADDK R9 R10 K45 [1]
      85 [-]: GETTABLE R8 R5 R9
      86 [-]: CONCAT R3 R7 R8
      87 [-]: MODK R0 R0 K50 [10]
      88 [-]: MOVE R7 R3   
      89 [-]: ADDK R9 R0 K45 [1]
      90 [-]: GETTABLE R8 R6 R9
      91 [-]: CONCAT R3 R7 R8
      92 [-]: RETURN R3 1  


; Name:            
; Defined at line: 1614
; #Upvalues:       0
; #Parameters:     4
; Is_vararg:       0
; Max Stack Size:  15

       0 [-]: LOADN R5 2   
       1 [-]: GETIMPORT R7 2 [0xAE2294FA]
       2 [-]: MOVE R8 R1   
       3 [-]: CALL R7 1 1  
       4 [-]: POWK R6 R7 K0 [2]
       5 [-]: MUL R4 R5 R6 
       6 [-]: LOADN R6 2   
       7 [-]: GETIMPORT R7 4 [0x4FD57545]
       8 [-]: MOVE R8 R1   
       9 [-]: SUB R9 R0 R2 
      10 [-]: CALL R7 2 1  
      11 [-]: MUL R5 R6 R7 
      12 [-]: GETIMPORT R10 2 [0xAE2294FA]
      13 [-]: MOVE R11 R2  
      14 [-]: CALL R10 1 1 
      15 [-]: POWK R9 R10 K0 [2]
      16 [-]: GETIMPORT R11 2 [0xAE2294FA]
      17 [-]: MOVE R12 R0  
      18 [-]: CALL R11 1 1 
      19 [-]: POWK R10 R11 K0 [2]
      20 [-]: ADD R8 R9 R10
      21 [-]: LOADN R10 2  
      22 [-]: GETIMPORT R11 4 [0x4FD57545]
      23 [-]: MOVE R12 R2  
      24 [-]: MOVE R13 R0  
      25 [-]: CALL R11 2 1 
      26 [-]: MUL R9 R10 R11
      27 [-]: SUB R7 R8 R9 
      28 [-]: POWK R8 R3 K0 [2]
      29 [-]: SUB R6 R7 R8 
      30 [-]: POWK R8 R5 K0 [2]
      31 [-]: LOADN R11 2  
      32 [-]: MUL R10 R11 R4
      33 [-]: MUL R9 R10 R6
      34 [-]: SUB R7 R8 R9 
      35 [-]: LOADN R8 0   
      36 [-]: JUMPIFNOTLE R8 R7 L1
      37 [-]: LOADN R8 0   
      38 [-]: JUMPIFNOTLT R5 R8 L1
      39 [-]: FASTCALL1 25 R7 L0
      40 [-]: MOVE R14 R7  
      41 [-]: GETIMPORT R13 7 [0x34E9F45C]
      42 [-]: CALL R13 1 1 
L 0:  43 [-]: MINUS R12 R13
      44 [-]: SUB R11 R12 R5
      45 [-]: DIV R10 R11 R4
      46 [-]: MUL R9 R1 R10
      47 [-]: ADD R8 R0 R9 
      48 [-]: RETURN R8 1  
L 1:  49 [-]: LOADB R8 0   
      50 [-]: RETURN R8 1  


; Name:            
; Defined at line: 1626
; #Upvalues:       0
; #Parameters:     1
; Is_vararg:       0
; Max Stack Size:  13

       0 [-]: NEWTABLE R1 0 10
       1 [-]: LOADK R2 K0 ["("]
       2 [-]: LOADK R3 K1 [")"]
       3 [-]: LOADK R4 K2 ["."]
       4 [-]: LOADK R5 K3 ["+"]
       5 [-]: LOADK R6 K4 ["-"]
       6 [-]: LOADK R7 K5 ["*"]
       7 [-]: LOADK R8 K6 ["?"]
       8 [-]: LOADK R9 K7 ["["]
       9 [-]: LOADK R10 K8 ["^"]
      10 [-]: LOADK R11 K9 ["$"]
      11 [-]: SETLIST R1 R2 10 [1]
      12 [-]: GETIMPORT R2 11 [0xC8802016]
      13 [-]: MOVE R3 R1   
      14 [-]: CALL R2 1 3  
      15 [-]: FORGPREP_INEXT R2 L1
L 0:  16 [-]: GETIMPORT R7 14 [0x66EDF04F]
      17 [-]: MOVE R8 R0   
      18 [-]: LOADK R10 K15 ["%"]
      19 [-]: MOVE R11 R6  
      20 [-]: CONCAT R9 R10 R11
      21 [-]: LOADK R11 K16 ["%%"]
      22 [-]: MOVE R12 R6  
      23 [-]: CONCAT R10 R11 R12
      24 [-]: CALL R7 3 1  
      25 [-]: MOVE R0 R7   
L 1:  26 [-]: FORGLOOP R2 L0 2 [inext]
      27 [-]: GETIMPORT R2 14 [0x66EDF04F]
      28 [-]: MOVE R3 R0   
      29 [-]: LOADK R4 K16 ["%%"]
      30 [-]: LOADK R5 K17 ["%%%%"]
      31 [-]: CALL R2 3 1  
      32 [-]: MOVE R0 R2   
      33 [-]: RETURN R0 1  


; Name:            
; Defined at line: 1636
; #Upvalues:       1
; #Parameters:     1
; Is_vararg:       0
; Max Stack Size:  3

       0 [-]: GETUPVAL R1 0
       1 [-]: MOVE R2 R0   
       2 [-]: CALL R1 1 1  
       3 [-]: RETURN R1 1  


; Name:            
; Defined at line: 1640
; #Upvalues:       0
; #Parameters:     1
; Is_vararg:       0
; Max Stack Size:  5

       0 [-]: GETIMPORT R1 2 [0x66EDF04F]
       1 [-]: MOVE R2 R0   
       2 [-]: LOADK R3 K3 ["<"]
       3 [-]: LOADK R4 K4 ["&lt;"]
       4 [-]: CALL R1 3 1  
       5 [-]: MOVE R0 R1   
       6 [-]: GETIMPORT R1 2 [0x66EDF04F]
       7 [-]: MOVE R2 R0   
       8 [-]: LOADK R3 K5 [">"]
       9 [-]: LOADK R4 K6 ["&gt;"]
      10 [-]: CALL R1 3 1  
      11 [-]: MOVE R0 R1   
      12 [-]: GETIMPORT R1 2 [0x66EDF04F]
      13 [-]: MOVE R2 R0   
      14 [-]: LOADK R3 K7 ["\r([^\n])"]
      15 [-]: LOADK R4 K8 ["\r\n%1"]
      16 [-]: CALL R1 3 1  
      17 [-]: MOVE R0 R1   
      18 [-]: RETURN R0 1  


; Name:            
; Defined at line: 1648
; #Upvalues:       0
; #Parameters:     1
; Is_vararg:       0
; Max Stack Size:  12

       0 [-]: LOADN R1 1   
       1 [-]: NAMECALL R2 R0 K0 [0x204423D8]
       2 [-]: CALL R2 1 1  
       3 [-]: JUMPIF R2 L0 
       4 [-]: LOADN R2 1   
       5 [-]: NAMECALL R3 R0 K1 [0xC018B56E]
       6 [-]: CALL R3 1 1  
       7 [-]: DIV R1 R2 R3 
L 0:   8 [-]: NAMECALL R3 R0 K2 [0x091C120E]
       9 [-]: CALL R3 1 1  
      10 [-]: MUL R2 R3 R1 
      11 [-]: NAMECALL R4 R0 K3 [0x2CC9D281]
      12 [-]: CALL R4 1 1  
      13 [-]: MUL R3 R4 R1 
      14 [-]: NAMECALL R5 R0 K4 [0x6B837788]
      15 [-]: CALL R5 1 1  
      16 [-]: MUL R4 R5 R1 
      17 [-]: NAMECALL R6 R0 K5 [0xAF9FDA9F]
      18 [-]: CALL R6 1 1  
      19 [-]: MUL R5 R6 R1 
      20 [-]: DIV R6 R4 R2 
      21 [-]: DIV R7 R5 R3 
      22 [-]: LOADN R8 1   
      23 [-]: LOADN R9 1   
      24 [-]: NAMECALL R10 R0 K6 [0x095251AF]
      25 [-]: CALL R10 1 1 
      26 [-]: LOADN R11 2  
      27 [-]: JUMPIFNOTEQ R10 R11 L2
      28 [-]: JUMPIFNOTLT R6 R7 L1
      29 [-]: MUL R11 R3 R6
      30 [-]: DIV R9 R11 R5
      31 [-]: RETURN R8 2  
L 1:  32 [-]: JUMPIFNOTLT R7 R6 L2
      33 [-]: MUL R11 R2 R7
      34 [-]: DIV R8 R11 R4
L 2:  35 [-]: RETURN R8 2  


; Name:            
; Defined at line: 1676
; #Upvalues:       1
; #Parameters:     1
; Is_vararg:       0
; Max Stack Size:  3

       0 [-]: GETUPVAL R1 0
       1 [-]: MOVE R2 R0   
       2 [-]: CALL R1 1 -1 
       3 [-]: RETURN R1 -1 


; Name:            
; Defined at line: 1680
; #Upvalues:       1
; #Parameters:     3
; Is_vararg:       0
; Max Stack Size:  12

       0 [-]: LOADN R3 1   
       1 [-]: NAMECALL R4 R0 K0 [0x204423D8]
       2 [-]: CALL R4 1 1  
       3 [-]: JUMPIF R4 L0 
       4 [-]: LOADN R4 1   
       5 [-]: NAMECALL R5 R0 K1 [0xC018B56E]
       6 [-]: CALL R5 1 1  
       7 [-]: DIV R3 R4 R5 
L 0:   8 [-]: LOADN R4 1   
       9 [-]: GETUPVAL R5 0
      10 [-]: MOVE R6 R0   
      11 [-]: CALL R5 1 2  
      12 [-]: NAMECALL R9 R0 K2 [0x091C120E]
      13 [-]: CALL R9 1 1  
      14 [-]: NAMECALL R10 R0 K3 [0x2CC9D281]
      15 [-]: CALL R10 1 1 
      16 [-]: JUMPIFNOT R2 L1
      17 [-]: MOVE R8 R9   
      18 [-]: JUMP L2
     
L 1:  19 [-]: MOVE R8 R10  
      20 [-]: JUMP L2
     
L 2:  21 [-]: MUL R7 R8 R3 
      22 [-]: DIV R8 R1 R7 
      23 [-]: JUMPIFNOT R2 L3
      24 [-]: MOVE R9 R5   
      25 [-]: JUMP L4
     
L 3:  26 [-]: MOVE R9 R6   
      27 [-]: JUMP L4
     
L 4:  28 [-]: MUL R4 R8 R9 
      29 [-]: RETURN R4 1  


; Name:            
; Defined at line: 1695
; #Upvalues:       1
; #Parameters:     3
; Is_vararg:       0
; Max Stack Size:  12

       0 [-]: LOADN R3 1   
       1 [-]: NAMECALL R4 R0 K0 [0x204423D8]
       2 [-]: CALL R4 1 1  
       3 [-]: JUMPIF R4 L0 
       4 [-]: NAMECALL R4 R0 K1 [0xC018B56E]
       5 [-]: CALL R4 1 1  
       6 [-]: MOVE R3 R4   
L 0:   7 [-]: NAMECALL R5 R0 K2 [0x091C120E]
       8 [-]: CALL R5 1 1  
       9 [-]: NAMECALL R6 R0 K3 [0x2CC9D281]
      10 [-]: CALL R6 1 1  
      11 [-]: JUMPIFNOT R2 L1
      12 [-]: MOVE R4 R5   
      13 [-]: JUMP L2
     
L 1:  14 [-]: MOVE R4 R6   
      15 [-]: JUMP L2
     
L 2:  16 [-]: DIV R1 R1 R4 
      17 [-]: LOADN R4 1   
      18 [-]: NAMECALL R5 R0 K4 [0x468B2679]
      19 [-]: CALL R5 1 1  
      20 [-]: GETUPVAL R6 0
      21 [-]: MOVE R7 R0   
      22 [-]: CALL R6 1 2  
      23 [-]: JUMPIFNOT R2 L8
      24 [-]: LOADN R8 4   
      25 [-]: JUMPIFEQ R5 R8 L3
      26 [-]: LOADN R8 1   
      27 [-]: JUMPIFEQ R5 R8 L3
      28 [-]: LOADN R8 7   
      29 [-]: JUMPIFNOTEQ R5 R8 L4
L 3:  30 [-]: LOADK R8 K5 [0.5]
      31 [-]: SUBK R11 R1 K5 [0.5]
      32 [-]: MUL R10 R11 R3
      33 [-]: MUL R9 R10 R6
      34 [-]: ADD R4 R8 R9 
      35 [-]: RETURN R4 1  
L 4:  36 [-]: LOADN R8 3   
      37 [-]: JUMPIFEQ R5 R8 L5
      38 [-]: LOADN R8 0   
      39 [-]: JUMPIFEQ R5 R8 L5
      40 [-]: LOADN R8 6   
      41 [-]: JUMPIFNOTEQ R5 R8 L6
L 5:  42 [-]: MUL R8 R1 R3 
      43 [-]: MUL R4 R8 R6 
      44 [-]: RETURN R4 1  
L 6:  45 [-]: LOADN R8 5   
      46 [-]: JUMPIFEQ R5 R8 L7
      47 [-]: LOADN R8 2   
      48 [-]: JUMPIFEQ R5 R8 L7
      49 [-]: LOADN R8 8   
      50 [-]: JUMPIFNOTEQ R5 R8 L14
L 7:  51 [-]: LOADN R8 1   
      52 [-]: SUBK R11 R1 K6 [1]
      53 [-]: MUL R10 R11 R3
      54 [-]: MUL R9 R10 R6
      55 [-]: ADD R4 R8 R9 
      56 [-]: RETURN R4 1  
L 8:  57 [-]: LOADN R8 3   
      58 [-]: JUMPIFEQ R5 R8 L9
      59 [-]: LOADN R8 4   
      60 [-]: JUMPIFEQ R5 R8 L9
      61 [-]: LOADN R8 5   
      62 [-]: JUMPIFNOTEQ R5 R8 L10
L 9:  63 [-]: LOADK R8 K5 [0.5]
      64 [-]: SUBK R11 R1 K5 [0.5]
      65 [-]: MUL R10 R11 R3
      66 [-]: MUL R9 R10 R7
      67 [-]: ADD R4 R8 R9 
      68 [-]: RETURN R4 1  
L10:  69 [-]: LOADN R8 0   
      70 [-]: JUMPIFEQ R5 R8 L11
      71 [-]: LOADN R8 1   
      72 [-]: JUMPIFEQ R5 R8 L11
      73 [-]: LOADN R8 2   
      74 [-]: JUMPIFNOTEQ R5 R8 L12
L11:  75 [-]: MUL R8 R1 R3 
      76 [-]: MUL R4 R8 R7 
      77 [-]: RETURN R4 1  
L12:  78 [-]: LOADN R8 6   
      79 [-]: JUMPIFEQ R5 R8 L13
      80 [-]: LOADN R8 7   
      81 [-]: JUMPIFEQ R5 R8 L13
      82 [-]: LOADN R8 8   
      83 [-]: JUMPIFNOTEQ R5 R8 L14
L13:  84 [-]: LOADN R8 1   
      85 [-]: SUBK R11 R1 K6 [1]
      86 [-]: MUL R10 R11 R3
      87 [-]: MUL R9 R10 R7
      88 [-]: ADD R4 R8 R9 
L14:  89 [-]: RETURN R4 1  


; Name:            
; Defined at line: 1727
; #Upvalues:       1
; #Parameters:     2
; Is_vararg:       0
; Max Stack Size:  8

       0 [-]: LOADN R2 1   
       1 [-]: NAMECALL R3 R0 K0 [0x204423D8]
       2 [-]: CALL R3 1 1  
       3 [-]: JUMPIF R3 L0 
       4 [-]: LOADN R3 1   
       5 [-]: NAMECALL R4 R0 K1 [0xC018B56E]
       6 [-]: CALL R4 1 1  
       7 [-]: DIV R2 R3 R4 
L 0:   8 [-]: GETUPVAL R3 0
       9 [-]: MOVE R4 R0   
      10 [-]: CALL R3 1 2  
      11 [-]: NAMECALL R6 R0 K2 [0x2CC9D281]
      12 [-]: CALL R6 1 1  
      13 [-]: MUL R5 R6 R2 
      14 [-]: DIV R7 R1 R5 
      15 [-]: MUL R6 R7 R4 
      16 [-]: RETURN R6 1  


; Name:            
; Defined at line: 1739
; #Upvalues:       0
; #Parameters:     1
; Is_vararg:       0
; Max Stack Size:  13

       0 [-]: NAMECALL R1 R0 K0 [0x095251AF]
       1 [-]: CALL R1 1 1  
       2 [-]: NAMECALL R2 R0 K1 [0x6B837788]
       3 [-]: CALL R2 1 1  
       4 [-]: NAMECALL R3 R0 K2 [0xAF9FDA9F]
       5 [-]: CALL R3 1 1  
       6 [-]: NAMECALL R4 R0 K3 [0x091C120E]
       7 [-]: CALL R4 1 1  
       8 [-]: NAMECALL R5 R0 K4 [0x2CC9D281]
       9 [-]: CALL R5 1 1  
      10 [-]: MOVE R6 R4   
      11 [-]: MOVE R7 R5   
      12 [-]: LOADN R8 2   
      13 [-]: JUMPIFNOTEQ R1 R8 L4
      14 [-]: DIV R8 R2 R4 
      15 [-]: DIV R9 R3 R5 
      16 [-]: JUMPIFNOTLT R8 R9 L1
      17 [-]: MOVE R6 R4   
      18 [-]: LOADN R12 1  
      19 [-]: DIV R11 R12 R8
      20 [-]: MUL R10 R3 R11
      21 [-]: ADDK R12 R10 K5 [0.5]
      22 [-]: FASTCALL1 12 R12 L0
      23 [-]: GETIMPORT R11 8 [0x55F27C30]
      24 [-]: CALL R11 1 1 
L 0:  25 [-]: MOVE R7 R11  
      26 [-]: JUMP L7
     
      27 [-]: JUMP L7
     
L 1:  28 [-]: JUMPIFNOTLT R9 R8 L7
      29 [-]: LOADN R12 1  
      30 [-]: DIV R11 R12 R9
      31 [-]: MUL R10 R2 R11
      32 [-]: ADDK R12 R10 K5 [0.5]
      33 [-]: FASTCALL1 12 R12 L2
      34 [-]: GETIMPORT R11 8 [0x55F27C30]
      35 [-]: CALL R11 1 1 
L 2:  36 [-]: MOVE R6 R11  
      37 [-]: JUMP L3
     
L 3:  38 [-]: MOVE R7 R5   
      39 [-]: JUMP L7
     
L 4:  40 [-]: FASTCALL2 18 R2 R4 L5
      41 [-]: MOVE R9 R2   
      42 [-]: MOVE R10 R4  
      43 [-]: GETIMPORT R8 10 [0xB62ECFE0]
      44 [-]: CALL R8 2 1  
L 5:  45 [-]: MOVE R6 R8   
      46 [-]: FASTCALL2 18 R3 R5 L6
      47 [-]: MOVE R9 R3   
      48 [-]: MOVE R10 R5  
      49 [-]: GETIMPORT R8 10 [0xB62ECFE0]
      50 [-]: CALL R8 2 1  
L 6:  51 [-]: MOVE R7 R8   
L 7:  52 [-]: NAMECALL R8 R0 K11 [0x1AE553AF]
      53 [-]: CALL R8 1 1  
      54 [-]: JUMPIFNOT R8 L8
      55 [-]: LOADN R9 1   
      56 [-]: NAMECALL R10 R0 K12 [0xC018B56E]
      57 [-]: CALL R10 1 1 
      58 [-]: DIV R8 R9 R10
      59 [-]: MUL R6 R6 R8 
      60 [-]: LOADN R9 1   
      61 [-]: NAMECALL R10 R0 K12 [0xC018B56E]
      62 [-]: CALL R10 1 1 
      63 [-]: DIV R8 R9 R10
      64 [-]: MUL R7 R7 R8 
L 8:  65 [-]: RETURN R6 2  


; Name:            
; Defined at line: 1771
; #Upvalues:       0
; #Parameters:     1
; Is_vararg:       0
; Max Stack Size:  12

       0 [-]: NAMECALL R1 R0 K0 [0x091C120E]
       1 [-]: CALL R1 1 1  
       2 [-]: NAMECALL R2 R0 K1 [0x2CC9D281]
       3 [-]: CALL R2 1 1  
       4 [-]: MOVE R5 R1   
       5 [-]: MOVE R6 R2   
       6 [-]: NAMECALL R3 R0 K2 [0xBCEE8C15]
       7 [-]: CALL R3 3 2  
       8 [-]: NAMECALL R6 R0 K3 [0x6B837788]
       9 [-]: CALL R6 1 1  
      10 [-]: DIV R5 R1 R6 
      11 [-]: NAMECALL R7 R0 K4 [0xAF9FDA9F]
      12 [-]: CALL R7 1 1  
      13 [-]: DIV R6 R2 R7 
      14 [-]: DIV R7 R3 R1 
      15 [-]: DIV R8 R4 R2 
      16 [-]: MUL R10 R5 R7
      17 [-]: MULK R9 R10 K5 [100]
      18 [-]: MUL R11 R6 R8
      19 [-]: MULK R10 R11 K5 [100]
      20 [-]: RETURN R9 2  


; Name:            
; Defined at line: 1782
; #Upvalues:       0
; #Parameters:     4
; Is_vararg:       0
; Max Stack Size:  11

       0 [-]: JUMPXEQKNIL R2 L0 NOT
       1 [-]: LOADN R2 1   
L 0:   2 [-]: JUMPXEQKNIL R3 L1 NOT
       3 [-]: LOADN R3 3   
L 1:   4 [-]: GETIMPORT R4 1 [0x25312C9B]
       5 [-]: MOVE R5 R0   
       6 [-]: MOVE R6 R1   
       7 [-]: LOADN R7 0   
       8 [-]: NEWTABLE R8 0 1
       9 [-]: NEWCLOSURE R9 P0
      10 [-]: MOVE R0 R0   
      11 [-]: MOVE R0 R1   
      12 [-]: MOVE R1 R3   
      13 [-]: SETLIST R8 R9 1 [1]
      14 [-]: NEWTABLE R9 0 1
      15 [-]: LOADN R10 1  
      16 [-]: SETLIST R9 R10 1 [1]
      17 [-]: MOVE R10 R2  
      18 [-]: CALL R4 6 0  
      19 [-]: CLOSEUPVALS R3
      20 [-]: RETURN R0 0  


; Name:            
; Defined at line: 1799
; #Upvalues:       0
; #Parameters:     2
; Is_vararg:       0
; Max Stack Size:  18

       0 [-]: DUPTABLE R2 5
       1 [-]: LOADN R3 0   
       2 [-]: SETTABLEKS R3 R2 K0 ["xTranslate"]
       3 [-]: LOADN R3 0   
       4 [-]: SETTABLEKS R3 R2 K1 ["yTranslate"]
       5 [-]: LOADN R3 1   
       6 [-]: SETTABLEKS R3 R2 K2 ["xScale"]
       7 [-]: LOADN R3 1   
       8 [-]: SETTABLEKS R3 R2 K3 ["yScale"]
       9 [-]: DUPCLOSURE R3 K6 []
      10 [-]: SETTABLEKS R3 R2 K4 ["Apply"]
      11 [-]: JUMPXEQKNIL R1 L2
      12 [-]: GETIMPORT R3 8 [0x015284CD]
      13 [-]: LOADK R4 K9 ["."]
      14 [-]: MOVE R5 R1   
      15 [-]: CALL R3 2 1  
      16 [-]: MOVE R4 R1   
      17 [-]: LENGTH R7 R3 
      18 [-]: LOADN R5 1   
      19 [-]: LOADN R6 -1  
      20 [-]: FORNPREP R5 L1
L 0:  21 [-]: MOVE R11 R4  
      22 [-]: LOADN R12 5  
      23 [-]: NAMECALL R9 R0 K11 [0x91A24E4B]
      24 [-]: CALL R9 3 1  
      25 [-]: DIVK R8 R9 K10 [100]
      26 [-]: MOVE R12 R4  
      27 [-]: LOADN R13 6  
      28 [-]: NAMECALL R10 R0 K11 [0x91A24E4B]
      29 [-]: CALL R10 3 1 
      30 [-]: DIVK R9 R10 K10 [100]
      31 [-]: GETTABLEKS R12 R2 K0 ["xTranslate"]
      32 [-]: MUL R11 R12 R8
      33 [-]: MOVE R14 R4  
      34 [-]: LOADN R15 0  
      35 [-]: NAMECALL R12 R0 K11 [0x91A24E4B]
      36 [-]: CALL R12 3 1 
      37 [-]: ADD R10 R11 R12
      38 [-]: SETTABLEKS R10 R2 K0 ["xTranslate"]
      39 [-]: GETTABLEKS R12 R2 K1 ["yTranslate"]
      40 [-]: MUL R11 R12 R9
      41 [-]: MOVE R14 R4  
      42 [-]: LOADN R15 1  
      43 [-]: NAMECALL R12 R0 K11 [0x91A24E4B]
      44 [-]: CALL R12 3 1 
      45 [-]: ADD R10 R11 R12
      46 [-]: SETTABLEKS R10 R2 K1 ["yTranslate"]
      47 [-]: GETTABLEKS R11 R2 K2 ["xScale"]
      48 [-]: MUL R10 R11 R8
      49 [-]: SETTABLEKS R10 R2 K2 ["xScale"]
      50 [-]: GETTABLEKS R11 R2 K3 ["yScale"]
      51 [-]: MUL R10 R11 R9
      52 [-]: SETTABLEKS R10 R2 K3 ["yScale"]
      53 [-]: LOADN R12 1  
      54 [-]: LENGTH R15 R4
      55 [-]: GETTABLE R17 R3 R7
      56 [-]: LENGTH R16 R17
      57 [-]: SUB R14 R15 R16
      58 [-]: SUBK R13 R14 K12 [1]
      59 [-]: NAMECALL R10 R4 K13 [0x1A94C9CC]
      60 [-]: CALL R10 3 1 
      61 [-]: MOVE R4 R10  
      62 [-]: FORNLOOP R5 L0
L 1:  63 [-]: LOADK R8 K14 ["_root"]
      64 [-]: LOADN R9 5   
      65 [-]: NAMECALL R6 R0 K11 [0x91A24E4B]
      66 [-]: CALL R6 3 1  
      67 [-]: DIVK R5 R6 K10 [100]
      68 [-]: LOADK R9 K14 ["_root"]
      69 [-]: LOADN R10 6  
      70 [-]: NAMECALL R7 R0 K11 [0x91A24E4B]
      71 [-]: CALL R7 3 1  
      72 [-]: DIVK R6 R7 K10 [100]
      73 [-]: GETTABLEKS R9 R2 K0 ["xTranslate"]
      74 [-]: MUL R8 R9 R5 
      75 [-]: LOADK R11 K14 ["_root"]
      76 [-]: LOADN R12 0  
      77 [-]: NAMECALL R9 R0 K11 [0x91A24E4B]
      78 [-]: CALL R9 3 1  
      79 [-]: ADD R7 R8 R9 
      80 [-]: SETTABLEKS R7 R2 K0 ["xTranslate"]
      81 [-]: GETTABLEKS R9 R2 K1 ["yTranslate"]
      82 [-]: MUL R8 R9 R6 
      83 [-]: LOADK R11 K14 ["_root"]
      84 [-]: LOADN R12 1  
      85 [-]: NAMECALL R9 R0 K11 [0x91A24E4B]
      86 [-]: CALL R9 3 1  
      87 [-]: ADD R7 R8 R9 
      88 [-]: SETTABLEKS R7 R2 K1 ["yTranslate"]
      89 [-]: GETTABLEKS R8 R2 K2 ["xScale"]
      90 [-]: MUL R7 R8 R5 
      91 [-]: SETTABLEKS R7 R2 K2 ["xScale"]
      92 [-]: GETTABLEKS R8 R2 K3 ["yScale"]
      93 [-]: MUL R7 R8 R6 
      94 [-]: SETTABLEKS R7 R2 K3 ["yScale"]
L 2:  95 [-]: RETURN R2 1  


; Name:            
; Defined at line: 1846
; #Upvalues:       1
; #Parameters:     2
; Is_vararg:       0
; Max Stack Size:  5

       0 [-]: GETUPVAL R2 0
       1 [-]: MOVE R3 R0   
       2 [-]: MOVE R4 R1   
       3 [-]: CALL R2 2 1  
       4 [-]: RETURN R2 1  


; Name:            
; Defined at line: 1851
; #Upvalues:       1
; #Parameters:     4
; Is_vararg:       0
; Max Stack Size:  11

       0 [-]: MOVE R4 R2   
       1 [-]: MOVE R5 R3   
       2 [-]: JUMPXEQKNIL R1 L0
       3 [-]: GETUPVAL R6 0
       4 [-]: MOVE R7 R0   
       5 [-]: MOVE R8 R1   
       6 [-]: CALL R6 2 1  
       7 [-]: MOVE R9 R2   
       8 [-]: MOVE R10 R3  
       9 [-]: NAMECALL R7 R6 K0 [0xF5697F06]
      10 [-]: CALL R7 3 2  
      11 [-]: MOVE R4 R7   
      12 [-]: MOVE R5 R8   
L 0:  13 [-]: RETURN R4 2  


; Name:            
; Defined at line: 1863
; #Upvalues:       0
; #Parameters:     2
; Is_vararg:       0
; Max Stack Size:  19

       0 [-]: DUPTABLE R2 5
       1 [-]: LOADN R3 0   
       2 [-]: SETTABLEKS R3 R2 K0 ["xTranslate"]
       3 [-]: LOADN R3 0   
       4 [-]: SETTABLEKS R3 R2 K1 ["yTranslate"]
       5 [-]: LOADN R3 1   
       6 [-]: SETTABLEKS R3 R2 K2 ["xScale"]
       7 [-]: LOADN R3 1   
       8 [-]: SETTABLEKS R3 R2 K3 ["yScale"]
       9 [-]: DUPCLOSURE R3 K6 []
      10 [-]: SETTABLEKS R3 R2 K4 ["Apply"]
      11 [-]: JUMPXEQKNIL R1 L1
      12 [-]: GETIMPORT R3 8 [0x015284CD]
      13 [-]: LOADK R4 K9 ["."]
      14 [-]: MOVE R5 R1   
      15 [-]: CALL R3 2 1  
      16 [-]: LOADK R4 K10 [""]
      17 [-]: LOADK R8 K12 ["_root"]
      18 [-]: LOADN R9 5   
      19 [-]: NAMECALL R6 R0 K13 [0x91A24E4B]
      20 [-]: CALL R6 3 1  
      21 [-]: DIVK R5 R6 K11 [100]
      22 [-]: LOADK R9 K12 ["_root"]
      23 [-]: LOADN R10 6  
      24 [-]: NAMECALL R7 R0 K13 [0x91A24E4B]
      25 [-]: CALL R7 3 1  
      26 [-]: DIVK R6 R7 K11 [100]
      27 [-]: GETTABLEKS R9 R2 K0 ["xTranslate"]
      28 [-]: MUL R8 R9 R5 
      29 [-]: LOADK R11 K12 ["_root"]
      30 [-]: LOADN R12 0  
      31 [-]: NAMECALL R9 R0 K13 [0x91A24E4B]
      32 [-]: CALL R9 3 1  
      33 [-]: ADD R7 R8 R9 
      34 [-]: SETTABLEKS R7 R2 K0 ["xTranslate"]
      35 [-]: GETTABLEKS R9 R2 K1 ["yTranslate"]
      36 [-]: MUL R8 R9 R6 
      37 [-]: LOADK R11 K12 ["_root"]
      38 [-]: LOADN R12 1  
      39 [-]: NAMECALL R9 R0 K13 [0x91A24E4B]
      40 [-]: CALL R9 3 1  
      41 [-]: ADD R7 R8 R9 
      42 [-]: SETTABLEKS R7 R2 K1 ["yTranslate"]
      43 [-]: GETTABLEKS R8 R2 K2 ["xScale"]
      44 [-]: MUL R7 R8 R5 
      45 [-]: SETTABLEKS R7 R2 K2 ["xScale"]
      46 [-]: LOADN R9 1   
      47 [-]: LENGTH R7 R3 
      48 [-]: LOADN R8 1   
      49 [-]: FORNPREP R7 L1
L 0:  50 [-]: MOVE R10 R4  
      51 [-]: GETTABLE R11 R3 R9
      52 [-]: CONCAT R4 R10 R11
      53 [-]: MOVE R13 R4  
      54 [-]: LOADN R14 5  
      55 [-]: NAMECALL R11 R0 K13 [0x91A24E4B]
      56 [-]: CALL R11 3 1 
      57 [-]: DIVK R10 R11 K11 [100]
      58 [-]: MOVE R14 R4  
      59 [-]: LOADN R15 6  
      60 [-]: NAMECALL R12 R0 K13 [0x91A24E4B]
      61 [-]: CALL R12 3 1 
      62 [-]: DIVK R11 R12 K11 [100]
      63 [-]: GETTABLEKS R14 R2 K0 ["xTranslate"]
      64 [-]: MOVE R17 R4  
      65 [-]: LOADN R18 0  
      66 [-]: NAMECALL R15 R0 K13 [0x91A24E4B]
      67 [-]: CALL R15 3 1 
      68 [-]: ADD R13 R14 R15
      69 [-]: DIV R12 R13 R10
      70 [-]: SETTABLEKS R12 R2 K0 ["xTranslate"]
      71 [-]: GETTABLEKS R14 R2 K1 ["yTranslate"]
      72 [-]: MOVE R17 R4  
      73 [-]: LOADN R18 1  
      74 [-]: NAMECALL R15 R0 K13 [0x91A24E4B]
      75 [-]: CALL R15 3 1 
      76 [-]: ADD R13 R14 R15
      77 [-]: DIV R12 R13 R11
      78 [-]: SETTABLEKS R12 R2 K1 ["yTranslate"]
      79 [-]: GETTABLEKS R13 R2 K2 ["xScale"]
      80 [-]: DIV R12 R13 R10
      81 [-]: SETTABLEKS R12 R2 K2 ["xScale"]
      82 [-]: GETTABLEKS R13 R2 K3 ["yScale"]
      83 [-]: DIV R12 R13 R11
      84 [-]: SETTABLEKS R12 R2 K3 ["yScale"]
      85 [-]: MOVE R12 R4  
      86 [-]: LOADK R13 K9 ["."]
      87 [-]: CONCAT R4 R12 R13
      88 [-]: FORNLOOP R7 L0
L 1:  89 [-]: RETURN R2 1  


; Name:            
; Defined at line: 1910
; #Upvalues:       1
; #Parameters:     2
; Is_vararg:       0
; Max Stack Size:  5

       0 [-]: GETUPVAL R2 0
       1 [-]: MOVE R3 R0   
       2 [-]: MOVE R4 R1   
       3 [-]: CALL R2 2 1  
       4 [-]: RETURN R2 1  


; Name:            
; Defined at line: 1915
; #Upvalues:       1
; #Parameters:     4
; Is_vararg:       0
; Max Stack Size:  11

       0 [-]: MOVE R4 R2   
       1 [-]: MOVE R5 R3   
       2 [-]: JUMPXEQKNIL R1 L0
       3 [-]: GETUPVAL R6 0
       4 [-]: MOVE R7 R0   
       5 [-]: MOVE R8 R1   
       6 [-]: CALL R6 2 1  
       7 [-]: MOVE R9 R2   
       8 [-]: MOVE R10 R3  
       9 [-]: NAMECALL R7 R6 K0 [0xF5697F06]
      10 [-]: CALL R7 3 2  
      11 [-]: MOVE R4 R7   
      12 [-]: MOVE R5 R8   
L 0:  13 [-]: RETURN R4 2  


; Name:            
; Defined at line: 1927
; #Upvalues:       0
; #Parameters:     1
; Is_vararg:       0
; Max Stack Size:  6

       0 [-]: GETIMPORT R1 1 [0x015284CD]
       1 [-]: LOADK R2 K2 ["."]
       2 [-]: MOVE R3 R0   
       3 [-]: CALL R1 2 1  
       4 [-]: GETIMPORT R2 5 [0x9C1F3B5A]
       5 [-]: MOVE R3 R1   
       6 [-]: LENGTH R4 R1 
       7 [-]: CALL R2 2 1  
       8 [-]: GETIMPORT R3 7 [0x76960806]
       9 [-]: MOVE R4 R1   
      10 [-]: LOADK R5 K2 ["."]
      11 [-]: CALL R3 2 -1 
      12 [-]: RETURN R2 -1 


; Name:            
; Defined at line: 1932
; #Upvalues:       0
; #Parameters:     0
; Is_vararg:       0
; Max Stack Size:  2

       0 [-]: GETGLOBAL R1 K0 ["PLATFORM"]
       1 [-]: GETTABLEKS R0 R1 K1 ["PC"]
       2 [-]: GETIMPORT R1 4 [0xE6B41ADB]
       3 [-]: CALL R1 0 1  
       4 [-]: JUMPIFNOT R1 L0
       5 [-]: GETGLOBAL R1 K0 ["PLATFORM"]
       6 [-]: GETTABLEKS R0 R1 K5 ["TOUCH"]
       7 [-]: RETURN R0 1  
L 0:   8 [-]: GETIMPORT R1 7 [0x2A31B96E]
       9 [-]: CALL R1 0 1  
      10 [-]: JUMPIFNOT R1 L1
      11 [-]: GETGLOBAL R1 K0 ["PLATFORM"]
      12 [-]: GETTABLEKS R0 R1 K8 ["PS5"]
      13 [-]: RETURN R0 1  
L 1:  14 [-]: GETIMPORT R1 10 [0x2B31BB01]
      15 [-]: CALL R1 0 1  
      16 [-]: JUMPIFNOT R1 L2
      17 [-]: GETGLOBAL R1 K0 ["PLATFORM"]
      18 [-]: GETTABLEKS R0 R1 K11 ["PS4"]
      19 [-]: RETURN R0 1  
L 2:  20 [-]: GETIMPORT R1 13 [0xC84FA15A]
      21 [-]: CALL R1 0 1  
      22 [-]: JUMPIFNOT R1 L3
      23 [-]: GETGLOBAL R1 K0 ["PLATFORM"]
      24 [-]: GETTABLEKS R0 R1 K14 ["SWITCH"]
      25 [-]: RETURN R0 1  
L 3:  26 [-]: GETIMPORT R1 16 [0x9AD21AE9]
      27 [-]: CALL R1 0 1  
      28 [-]: JUMPIFNOT R1 L4
      29 [-]: GETGLOBAL R1 K0 ["PLATFORM"]
      30 [-]: GETTABLEKS R0 R1 K17 ["XBOX_ONE"]
      31 [-]: RETURN R0 1  
L 4:  32 [-]: GETIMPORT R1 19 [0xFF935E74]
      33 [-]: CALL R1 0 1  
      34 [-]: JUMPIFNOT R1 L5
      35 [-]: GETGLOBAL R1 K0 ["PLATFORM"]
      36 [-]: GETTABLEKS R0 R1 K20 ["BIG_PIC"]
L 5:  37 [-]: RETURN R0 1  


; Name:            
; Defined at line: 1951
; #Upvalues:       1
; #Parameters:     0
; Is_vararg:       0
; Max Stack Size:  1

       0 [-]: GETUPVAL R0 0
       1 [-]: CALL R0 0 1  
       2 [-]: RETURN R0 1  


; Name:            
; Defined at line: 1955
; #Upvalues:       1
; #Parameters:     0
; Is_vararg:       0
; Max Stack Size:  4

       0 [-]: GETUPVAL R0 0
       1 [-]: CALL R0 0 1  
       2 [-]: LOADK R1 K0 [""]
       3 [-]: GETGLOBAL R3 K1 ["PLATFORM"]
       4 [-]: GETTABLEKS R2 R3 K2 ["PC"]
       5 [-]: JUMPIFNOTEQ R0 R2 L0
       6 [-]: LOADK R1 K2 ["PC"]
       7 [-]: RETURN R1 1  
L 0:   8 [-]: GETGLOBAL R3 K1 ["PLATFORM"]
       9 [-]: GETTABLEKS R2 R3 K3 ["TOUCH"]
      10 [-]: JUMPIFNOTEQ R0 R2 L1
      11 [-]: LOADK R1 K4 ["Touch"]
      12 [-]: RETURN R1 1  
L 1:  13 [-]: GETGLOBAL R3 K1 ["PLATFORM"]
      14 [-]: GETTABLEKS R2 R3 K5 ["PS5"]
      15 [-]: JUMPIFNOTEQ R0 R2 L2
      16 [-]: LOADK R1 K5 ["PS5"]
      17 [-]: RETURN R1 1  
L 2:  18 [-]: GETGLOBAL R3 K1 ["PLATFORM"]
      19 [-]: GETTABLEKS R2 R3 K6 ["PS4"]
      20 [-]: JUMPIFNOTEQ R0 R2 L3
      21 [-]: LOADK R1 K6 ["PS4"]
      22 [-]: RETURN R1 1  
L 3:  23 [-]: GETGLOBAL R3 K1 ["PLATFORM"]
      24 [-]: GETTABLEKS R2 R3 K7 ["XBOX_ONE"]
      25 [-]: JUMPIFNOTEQ R0 R2 L4
      26 [-]: LOADK R1 K8 ["XBone"]
      27 [-]: RETURN R1 1  
L 4:  28 [-]: GETGLOBAL R3 K1 ["PLATFORM"]
      29 [-]: GETTABLEKS R2 R3 K9 ["SWITCH"]
      30 [-]: JUMPIFNOTEQ R0 R2 L5
      31 [-]: LOADK R1 K10 ["Switch"]
      32 [-]: RETURN R1 1  
L 5:  33 [-]: GETGLOBAL R3 K1 ["PLATFORM"]
      34 [-]: GETTABLEKS R2 R3 K11 ["BIG_PIC"]
      35 [-]: JUMPIFNOTEQ R0 R2 L6
      36 [-]: LOADK R1 K12 ["BigPic"]
L 6:  37 [-]: RETURN R1 1  



