
main <?:0,0> (94 instructions, 376 bytes at 0000016094B1D1F0)
0+ params, 20 slots, 0 upvalues, 0 locals, 17 constants, 17 functions
	1	[4]	GETGLOBAL	R0 K0 ; R0 := 0x2d0fad09
	2	[4]	LOADK    	R1 K1 ; R1 := "EE.Interface.Utilities"
	3	[4]	CALL     	R0 2 2 ; R0 := R0(R1)
	4	[5]	GETGLOBAL	R1 K0 ; R1 := 0x2d0fad09
	5	[5]	LOADK    	R2 K2 ; R2 := "Lotus.Interface.StoreItemUtilities"
	6	[5]	CALL     	R1 2 2 ; R1 := R1(R2)
	7	[6]	GETGLOBAL	R2 K0 ; R2 := 0x2d0fad09
	8	[6]	LOADK    	R3 K3 ; R3 := "Lotus.Interface.UIStyleUtilities"
	9	[6]	CALL     	R2 2 2 ; R2 := R2(R3)
	10	[7]	GETGLOBAL	R3 K0 ; R3 := 0x2d0fad09
	11	[7]	LOADK    	R4 K4 ; R4 := "Lotus.Interface.UIUtilities"
	12	[7]	CALL     	R3 2 2 ; R3 := R3(R4)
	13	[9]	OP_LOADBOOL	R4 0 0 ; R4 := false
	14	[10]	LOADNIL  	R5 R5 ; R5 := nil
	15	[11]	NEWTABLE 	R6 0 0 ; R6 := {}
	16	[12]	NEWTABLE 	R7 0 0 ; R7 := {}
	17	[14]	LOADNIL  	R8 R9 ; R8 := R9 := nil
	18	[17]	OP_LOADBOOL	R10 0 0 ; R10 := false
	19	[18]	OP_LOADBOOL	R11 0 0 ; R11 := false
	20	[20]	LOADNIL  	R12 R13 ; R12 := R13 := nil
	21	[35]	CLOSURE  	R14 0 ; R14 := closure(Function #1)
	22	[35]	MOVE     	R0 R6 ; R0 := R6
	23	[43]	CLOSURE  	R15 1 ; R15 := closure(Function #2)
	24	[43]	MOVE     	R0 R9 ; R0 := R9
	25	[37]	SETGLOBAL	R15 K5 ; Shutdown := R15
	26	[58]	CLOSURE  	R15 2 ; R15 := closure(Function #3)
	27	[58]	MOVE     	R0 R4 ; R0 := R4
	28	[58]	MOVE     	R0 R0 ; R0 := R0
	29	[58]	MOVE     	R0 R13 ; R0 := R13
	30	[58]	MOVE     	R0 R8 ; R0 := R8
	31	[62]	CLOSURE  	R16 3 ; R16 := closure(Function #4)
	32	[62]	MOVE     	R0 R15 ; R0 := R15
	33	[60]	SETGLOBAL	R16 K6 ; TransitionOut := R16
	34	[198]	CLOSURE  	R16 4 ; R16 := closure(Function #5)
	35	[198]	MOVE     	R0 R5 ; R0 := R5
	36	[198]	MOVE     	R0 R0 ; R0 := R0
	37	[198]	MOVE     	R0 R7 ; R0 := R7
	38	[198]	MOVE     	R0 R3 ; R0 := R3
	39	[198]	MOVE     	R0 R4 ; R0 := R4
	40	[198]	MOVE     	R0 R8 ; R0 := R8
	41	[198]	MOVE     	R0 R15 ; R0 := R15
	42	[198]	MOVE     	R0 R1 ; R0 := R1
	43	[224]	CLOSURE  	R17 5 ; R17 := closure(Function #6)
	44	[224]	MOVE     	R0 R12 ; R0 := R12
	45	[224]	MOVE     	R0 R5 ; R0 := R5
	46	[233]	CLOSURE  	R18 6 ; R18 := closure(Function #7)
	47	[233]	MOVE     	R0 R17 ; R0 := R17
	48	[233]	MOVE     	R0 R4 ; R0 := R4
	49	[271]	CLOSURE  	R19 7 ; R19 := closure(Function #8)
	50	[271]	MOVE     	R0 R4 ; R0 := R4
	51	[271]	MOVE     	R0 R0 ; R0 := R0
	52	[271]	MOVE     	R0 R7 ; R0 := R7
	53	[271]	MOVE     	R0 R2 ; R0 := R2
	54	[271]	MOVE     	R0 R6 ; R0 := R6
	55	[271]	MOVE     	R0 R14 ; R0 := R14
	56	[271]	MOVE     	R0 R16 ; R0 := R16
	57	[271]	MOVE     	R0 R11 ; R0 := R11
	58	[235]	SETGLOBAL	R19 K7 ; Initialize := R19
	59	[288]	CLOSURE  	R19 8 ; R19 := closure(Function #9)
	60	[288]	MOVE     	R0 R11 ; R0 := R11
	61	[288]	MOVE     	R0 R10 ; R0 := R10
	62	[288]	MOVE     	R0 R9 ; R0 := R9
	63	[288]	MOVE     	R0 R12 ; R0 := R12
	64	[288]	MOVE     	R0 R18 ; R0 := R18
	65	[273]	SETGLOBAL	R19 K8 ; Update := R19
	66	[296]	CLOSURE  	R19 9 ; R19 := closure(Function #10)
	67	[296]	MOVE     	R0 R4 ; R0 := R4
	68	[296]	MOVE     	R0 R5 ; R0 := R5
	69	[290]	SETGLOBAL	R19 K9 ; MenuEntryFocused := R19
	70	[304]	CLOSURE  	R19 10 ; R19 := closure(Function #11)
	71	[304]	MOVE     	R0 R4 ; R0 := R4
	72	[304]	MOVE     	R0 R5 ; R0 := R5
	73	[298]	SETGLOBAL	R19 K10 ; MenuEntryUnfocused := R19
	74	[312]	CLOSURE  	R19 11 ; R19 := closure(Function #12)
	75	[312]	MOVE     	R0 R4 ; R0 := R4
	76	[312]	MOVE     	R0 R5 ; R0 := R5
	77	[306]	SETGLOBAL	R19 K11 ; MenuEntryPressed := R19
	78	[318]	CLOSURE  	R19 12 ; R19 := closure(Function #13)
	79	[318]	MOVE     	R0 R4 ; R0 := R4
	80	[318]	MOVE     	R0 R5 ; R0 := R5
	81	[314]	SETGLOBAL	R19 K12 ; onKeyUp_MENU_SELECT := R19
	82	[324]	CLOSURE  	R19 13 ; R19 := closure(Function #14)
	83	[324]	MOVE     	R0 R4 ; R0 := R4
	84	[324]	MOVE     	R0 R6 ; R0 := R6
	85	[320]	SETGLOBAL	R19 K13 ; onKeyUp_MENU_CANCEL := R19
	86	[328]	CLOSURE  	R19 14 ; R19 := closure(Function #15)
	87	[328]	MOVE     	R0 R9 ; R0 := R9
	88	[326]	SETGLOBAL	R19 K14 ; SetActionsInfoFunction := R19
	89	[332]	CLOSURE  	R19 15 ; R19 := closure(Function #16)
	90	[332]	MOVE     	R0 R13 ; R0 := R13
	91	[330]	SETGLOBAL	R19 K15 ; SetCallback := R19
	92	[336]	CLOSURE  	R19 16 ; R19 := closure(Function #17)
	93	[334]	SETGLOBAL	R19 K16 ; SupportsThemes := R19
	94	[336]	RETURN   	R0 1 ; return 


function #1 <?:24,35> (38 instructions, 152 bytes at 0000016094B1D610)
0 params, 11 slots, 1 upvalue, 0 locals, 15 constants, 0 functions
	1	[25]	NEWTABLE 	R0 0 0 ; R0 := {}
	2	[26]	GETUPVAL 	R1 U0 ; R1 := U0
	3	[26]	LEN      	R1 R1 ; R1 := # R1
	4	[26]	LOADK    	R2 := 1.000000
	5	[26]	LOADK    	R3 := -1.000000
	6	[26]	FORPREP  	R1 23 ; R1 -= R3; PC := 23
	7	[27]	GETUPVAL 	R5 U0 ; R5 := U0
	8	[27]	GETTABLE 	R5 R5 R4 ; R5 := R5[R4]
	9	[28]	GETTABLE 	R6 R5 K0 ; R6 := R5["mVisible"]
	10	[28]	TEST     	R6 0 ; if not R6 then PC := 23
	11	[28]	JMP      	23 ; PC := 23
	12	[29]	GETGLOBAL	R6 K1 ; R6 := 0x33bdd652
	13	[29]	GETTABLE 	R6 R6 K2 ; R6 := R6[0x23d5322f]
	14	[29]	MOVE     	R7 R0 ; R7 := R0
	15	[29]	NEWTABLE 	R8 0 3 ; R8 := {}
	16	[29]	GETTABLE 	R9 R5 K4 ; R9 := R5["mLabel"]
	17	[29]	SETTABLE 	R8 K3 R9 ; R8[0xae91e43b] := R9
	18	[29]	GETTABLE 	R9 R5 K6 ; R9 := R5["mCallback"]
	19	[29]	SETTABLE 	R8 K5 R9 ; R8["CallBack"] := R9
	20	[29]	GETTABLE 	R9 R5 K8 ; R9 := R5["mCallout"]
	21	[29]	SETTABLE 	R8 K7 R9 ; R8["CallOut"] := R9
	22	[29]	CALL     	R6 3 1 ; R6(R7,R8)
	23	[26]	FORLOOP  	R1 7 ; R1 += R3; if R1 <= R2 then begin PC := 7; R4 := R1 end
	24	[32]	GETGLOBAL	R6 K9 ; R6 := 0x7b998233
	25	[32]	GETGLOBAL	R7 K10 ; R7 := _T
	26	[32]	GETTABLE 	R7 R7 K11 ; R7 := R7["SetButtons"]
	27	[32]	CALL     	R6 2 2 ; R6 := R6(R7)
	28	[32]	TEST     	R6 1 ; if R6 then PC := 38
	29	[32]	JMP      	38 ; PC := 38
	30	[33]	GETGLOBAL	R6 K10 ; R6 := _T
	31	[33]	GETTABLE 	R6 R6 K12 ; R6 := R6[0x1c5b546f]
	32	[33]	GETGLOBAL	R7 K13 ; R7 := 0xae91e43b
	33	[33]	MOVE     	R8 R0 ; R8 := R0
	34	[33]	GETGLOBAL	R9 K14 ; R9 := 0xcd0165a3
	35	[33]	LOADK    	R10 := 1.000000
	36	[33]	CALL     	R9 2 0 ; R9,... := R9(R10)
	37	[33]	CALL     	R6 0 1 ; R6(R7,...)
	38	[35]	RETURN   	R0 1 ; return 

function #2 <?:37,43> (9 instructions, 36 bytes at 0000016094B1D900)
0 params, 2 slots, 1 upvalue, 0 locals, 3 constants, 0 functions
	1	[38]	GETUPVAL 	R0 U0 ; R0 := U0
	2	[38]	EQ       	1 R0 K0 ; if R0 == nil then PC := 7
	3	[38]	JMP      	7 ; PC := 7
	4	[39]	GETGLOBAL	R0 K1 ; R0 := _T
	5	[39]	GETUPVAL 	R1 U0 ; R1 := U0
	6	[39]	SETTABLE 	R0 R1 K0 ; R0[R1] := nil
	7	[42]	GETGLOBAL	R0 K1 ; R0 := _T
	8	[42]	SETTABLE 	R0 K2 K0 ; R0["InfoPopup_Data"] := nil
	9	[43]	RETURN   	R0 1 ; return 

function #3 <?:45,58> (25 instructions, 100 bytes at 0000016094B1DA50)
0 params, 9 slots, 4 upvalues, 0 locals, 8 constants, 1 function
	1	[46]	OP_LOADBOOL	R0 1 0 ; R0 := true
	2	[46]	SETUPVAL 	R0 U0 ; U0 := R0
	3	[47]	GETGLOBAL	R0 K0 ; R0 := 0x25312c9b
	4	[47]	GETGLOBAL	R1 K1 ; R1 := 0xae91e43b
	5	[47]	LOADK    	R2 K2 ; R2 := "_root"
	6	[47]	LOADK    	R3 := 0.000000
	7	[47]	NEWTABLE 	R4 1 0 ; R4 := {}
	8	[47]	LOADK    	R5 := 10.000000
	9	[47]	SETLIST  	R4 1 1 ; R4[(1-1)*FPF+i] := R(4+i), 1 <= i <= 1
	10	[47]	NEWTABLE 	R5 1 0 ; R5 := {}
	11	[47]	LOADK    	R6 := 0.000000
	12	[47]	SETLIST  	R5 1 1 ; R5[(1-1)*FPF+i] := R(5+i), 1 <= i <= 1
	13	[47]	LOADK    	R6 K4 ; R6 := 0.200000
	14	[47]	LOADK    	R7 := 0.000000
	15	[56]	CLOSURE  	R8 0 ; R8 := closure(Function #1)
	16	[56]	GETUPVAL 	R0 U1 ; R0 := U1
	17	[56]	GETUPVAL 	R0 U2 ; R0 := U2
	18	[56]	GETUPVAL 	R0 U3 ; R0 := U3
	19	[47]	CALL     	R0 9 1 ; R0(R1,R2,R3,R4,R5,R6,R7,R8)
	20	[57]	GETUPVAL 	R0 U1 ; R0 := U1
	21	[57]	GETTABLE 	R0 R0 K5 ; R0 := R0[0x659d451f]
	22	[57]	GETGLOBAL	R1 K6 ; R1 := 0x0032441c
	23	[57]	GETTABLE 	R1 R1 K7 ; R1 := R1["UISound_DialogClose"]
	24	[57]	CALL     	R0 2 1 ; R0(R1)
	25	[58]	RETURN   	R0 1 ; return 

function #4 <?:60,62> (3 instructions, 12 bytes at 0000016094B1DFC0)
0 params, 2 slots, 1 upvalue, 0 locals, 0 constants, 0 functions
	1	[61]	GETUPVAL 	R0 U0 ; R0 := U0
	2	[61]	CALL     	R0 1 1 ; R0()
	3	[62]	RETURN   	R0 1 ; return 

function #5 <?:64,198> (55 instructions, 220 bytes at 0000016094B1E090)
0 params, 7 slots, 8 upvalues, 0 locals, 21 constants, 4 functions
	1	[65]	GETGLOBAL	R0 K0 ; R0 := 0x2d0fad09
	2	[65]	LOADK    	R1 K1 ; R1 := "EE.Interface.Components.Grid"
	3	[65]	CALL     	R0 2 2 ; R0 := R0(R1)
	4	[66]	GETTABLE 	R1 R0 K2 ; R1 := R0[0xda0c93a2]
	5	[66]	GETGLOBAL	R2 K3 ; R2 := 0xae91e43b
	6	[66]	LOADK    	R3 K4 ; R3 := "ActionsMenu.ActionMenuItem"
	7	[66]	LOADNIL  	R4 R4 ; R4 := nil
	8	[66]	LOADK    	R5 := 5.000000
	9	[66]	LOADK    	R6 := 2.000000
	10	[66]	CALL     	R1 6 2 ; R1 := R1(R2,R3,R4,R5,R6)
	11	[66]	SETUPVAL 	R1 U0 ; U0 := R1
	12	[67]	GETUPVAL 	R1 U0 ; R1 := U0
	13	[67]	SELF     	R1 R1 K5 ; R2 := R1; R1 := R1[0x1e5b5cfe]
	14	[67]	LOADK    	R3 K6 ; R3 := "MenuEntryPressed"
	15	[67]	LOADK    	R4 K7 ; R4 := "MenuEntryFocused"
	16	[67]	LOADK    	R5 K8 ; R5 := "MenuEntryUnfocused"
	17	[67]	CALL     	R1 5 1 ; R1(R2,R3,R4,R5)
	18	[68]	GETUPVAL 	R1 U0 ; R1 := U0
	19	[68]	SETTABLE 	R1 K9 K10 ; R1["mColumnSeparation"] := 275.000000
	20	[69]	GETUPVAL 	R1 U0 ; R1 := U0
	21	[69]	SETTABLE 	R1 K11 K10 ; R1["mRowSeparation"] := 275.000000
	22	[70]	GETUPVAL 	R1 U0 ; R1 := U0
	23	[70]	SETTABLE 	R1 K12 K13 ; R1["mElementTransitionTime"] := 0.000000
	24	[71]	GETUPVAL 	R1 U0 ; R1 := U0
	25	[71]	GETGLOBAL	R2 K3 ; R2 := 0xae91e43b
	26	[71]	SELF     	R2 R2 K15 ; R3 := R2; R2 := R2[0x91a24e4b]
	27	[71]	LOADK    	R4 K16 ; R4 := "ActionsMenu.ActionMenuItem.Image"
	28	[71]	LOADK    	R5 := 1.000000
	29	[71]	CALL     	R2 4 2 ; R2 := R2(R3,R4,R5)
	30	[71]	SETTABLE 	R1 K14 R2 ; R1["mOriginalImageYPos"] := R2
	31	[72]	GETUPVAL 	R1 U0 ; R1 := U0
	32	[104]	CLOSURE  	R2 0 ; R2 := closure(Function #1)
	33	[104]	GETUPVAL 	R0 U1 ; R0 := U1
	34	[104]	GETUPVAL 	R0 U2 ; R0 := U2
	35	[104]	GETUPVAL 	R0 U3 ; R0 := U3
	36	[104]	SETTABLE 	R1 K17 R2 ; R1["mOnFocusedCallback"] := R2
	37	[105]	GETUPVAL 	R1 U0 ; R1 := U0
	38	[125]	CLOSURE  	R2 1 ; R2 := closure(Function #2)
	39	[125]	GETUPVAL 	R0 U2 ; R0 := U2
	40	[125]	SETTABLE 	R1 K18 R2 ; R1["mOnUnfocusedCallback"] := R2
	41	[126]	GETUPVAL 	R1 U0 ; R1 := U0
	42	[142]	CLOSURE  	R2 2 ; R2 := closure(Function #3)
	43	[142]	GETUPVAL 	R0 U4 ; R0 := U4
	44	[142]	GETUPVAL 	R0 U1 ; R0 := U1
	45	[142]	GETUPVAL 	R0 U5 ; R0 := U5
	46	[142]	GETUPVAL 	R0 U6 ; R0 := U6
	47	[142]	SETTABLE 	R1 K19 R2 ; R1["mOnSelectedCallback"] := R2
	48	[143]	GETUPVAL 	R1 U0 ; R1 := U0
	49	[197]	CLOSURE  	R2 3 ; R2 := closure(Function #4)
	50	[197]	GETUPVAL 	R0 U0 ; R0 := U0
	51	[197]	GETUPVAL 	R0 U2 ; R0 := U2
	52	[197]	GETUPVAL 	R0 U1 ; R0 := U1
	53	[197]	GETUPVAL 	R0 U7 ; R0 := U7
	54	[197]	SETTABLE 	R1 K20 R2 ; R1["mElementDrawCallback"] := R2
	55	[198]	RETURN   	R0 1 ; return 

function #6 <?:200,224> (86 instructions, 344 bytes at 0000016081E95630)
0 params, 16 slots, 2 upvalues, 0 locals, 21 constants, 0 functions
	1	[201]	LOADK    	R0 := 1.000000
	2	[201]	GETUPVAL 	R1 U0 ; R1 := U0
	3	[201]	LEN      	R1 R1 ; R1 := # R1
	4	[201]	LOADK    	R2 := 1.000000
	5	[201]	FORPREP  	R0 12 ; R0 -= R2; PC := 12
	6	[202]	GETUPVAL 	R4 U1 ; R4 := U1
	7	[202]	SELF     	R4 R4 K0 ; R5 := R4; R4 := R4[0xbad4316f]
	8	[202]	GETUPVAL 	R6 U0 ; R6 := U0
	9	[202]	GETTABLE 	R6 R6 R3 ; R6 := R6[R3]
	10	[202]	OP_LOADBOOL	R7 1 0 ; R7 := true
	11	[202]	CALL     	R4 4 1 ; R4(R5,R6,R7)
	12	[201]	FORLOOP  	R0 6 ; R0 += R2; if R0 <= R1 then begin PC := 6; R3 := R0 end
	13	[204]	GETUPVAL 	R4 U1 ; R4 := U1
	14	[204]	SELF     	R4 R4 K1 ; R5 := R4; R4 := R4[0x71e9ac81]
	15	[204]	CALL     	R4 2 1 ; R4(R5)
	16	[206]	GETGLOBAL	R4 K2 ; R4 := 0x5bced4c4
	17	[206]	GETTABLE 	R4 R4 K3 ; R4 := R4[0x99675e23]
	18	[206]	GETUPVAL 	R5 U1 ; R5 := U1
	19	[206]	SELF     	R5 R5 K4 ; R6 := R5; R5 := R5[0x5fbddc1a]
	20	[206]	CALL     	R5 2 2 ; R5 := R5(R6)
	21	[206]	GETUPVAL 	R6 U1 ; R6 := U1
	22	[206]	GETTABLE 	R6 R6 K5 ; R6 := R6["mColumns"]
	23	[206]	DIV      	R5 R5 R6 ; R5 := R5 / R6
	24	[206]	CALL     	R4 2 2 ; R4 := R4(R5)
	25	[207]	GETUPVAL 	R5 U1 ; R5 := U1
	26	[207]	GETTABLE 	R5 R5 K5 ; R5 := R5["mColumns"]
	27	[208]	EQ       	0 R4 K6 ; if R4 ~= 1.000000 then PC := 33
	28	[208]	JMP      	33 ; PC := 33
	29	[209]	GETUPVAL 	R6 U1 ; R6 := U1
	30	[209]	SELF     	R6 R6 K4 ; R7 := R6; R6 := R6[0x5fbddc1a]
	31	[209]	CALL     	R6 2 2 ; R6 := R6(R7)
	32	[209]	MOVE     	R5 R6 ; R5 := R6
	33	[211]	GETUPVAL 	R6 U1 ; R6 := U1
	34	[211]	GETTABLE 	R6 R6 K7 ; R6 := R6["mColumnSeparation"]
	35	[211]	MUL      	R6 R6 R5 ; R6 := R6 * R5
	36	[211]	SUB      	R6 R6 K8 ; R6 := R6 - 5.000000
	37	[212]	GETUPVAL 	R7 U1 ; R7 := U1
	38	[212]	GETTABLE 	R7 R7 K9 ; R7 := R7["mRowSeparation"]
	39	[212]	MUL      	R7 R7 R4 ; R7 := R7 * R4
	40	[212]	ADD      	R7 R7 K10 ; R7 := R7 + 15.000000
	41	[213]	GETGLOBAL	R8 K11 ; R8 := 0xae91e43b
	42	[213]	SELF     	R8 R8 K12 ; R9 := R8; R8 := R8[0x091c120e]
	43	[213]	CALL     	R8 2 2 ; R8 := R8(R9)
	44	[213]	DIV      	R8 R8 K13 ; R8 := R8 / 2.000000
	45	[214]	GETGLOBAL	R9 K11 ; R9 := 0xae91e43b
	46	[214]	SELF     	R9 R9 K14 ; R10 := R9; R9 := R9[0x67bc869f]
	47	[214]	LOADK    	R11 K15 ; R11 := "ActionsMenu"
	48	[214]	LOADK    	R12 := 0.000000
	49	[214]	DIV      	R13 R6 K13 ; R13 := R6 / 2.000000
	50	[214]	SUB      	R13 R8 R13 ; R13 := R8 - R13
	51	[214]	CALL     	R9 5 1 ; R9(R10,R11,R12,R13)
	52	[216]	GETGLOBAL	R9 K11 ; R9 := 0xae91e43b
	53	[216]	SELF     	R9 R9 K14 ; R10 := R9; R9 := R9[0x67bc869f]
	54	[216]	LOADK    	R11 K16 ; R11 := "FancyBits.LeftLines"
	55	[216]	LOADK    	R12 := 0.000000
	56	[216]	DIV      	R13 R6 K13 ; R13 := R6 / 2.000000
	57	[216]	UNM      	R13 R13 ; R13 := ^ R13
	58	[216]	ADD      	R13 R13 K13 ; R13 := R13 + 2.000000
	59	[216]	CALL     	R9 5 1 ; R9(R10,R11,R12,R13)
	60	[217]	GETGLOBAL	R9 K11 ; R9 := 0xae91e43b
	61	[217]	SELF     	R9 R9 K14 ; R10 := R9; R9 := R9[0x67bc869f]
	62	[217]	LOADK    	R11 K17 ; R11 := "FancyBits.RightLines"
	63	[217]	LOADK    	R12 := 0.000000
	64	[217]	DIV      	R13 R6 K13 ; R13 := R6 / 2.000000
	65	[217]	SUB      	R13 R13 K18 ; R13 := R13 - 4.000000
	66	[217]	CALL     	R9 5 1 ; R9(R10,R11,R12,R13)
	67	[219]	SUB      	R9 R4 K6 ; R9 := R4 - 1.000000
	68	[219]	LT       	0 K19 R9 ; if 0.000000 >= R9 then PC := 86
	69	[219]	JMP      	86 ; PC := 86
	70	[220]	GETGLOBAL	R9 K11 ; R9 := 0xae91e43b
	71	[220]	SELF     	R9 R9 K20 ; R10 := R9; R9 := R9[0x91a24e4b]
	72	[220]	LOADK    	R11 K15 ; R11 := "ActionsMenu"
	73	[220]	LOADK    	R12 := 1.000000
	74	[220]	CALL     	R9 4 2 ; R9 := R9(R10,R11,R12)
	75	[222]	GETGLOBAL	R10 K11 ; R10 := 0xae91e43b
	76	[222]	SELF     	R10 R10 K14 ; R11 := R10; R10 := R10[0x67bc869f]
	77	[222]	LOADK    	R12 K15 ; R12 := "ActionsMenu"
	78	[222]	LOADK    	R13 := 1.000000
	79	[222]	SUB      	R14 R4 K6 ; R14 := R4 - 1.000000
	80	[222]	GETUPVAL 	R15 U1 ; R15 := U1
	81	[222]	GETTABLE 	R15 R15 K9 ; R15 := R15["mRowSeparation"]
	82	[222]	MUL      	R14 R14 R15 ; R14 := R14 * R15
	83	[222]	DIV      	R14 R14 K13 ; R14 := R14 / 2.000000
	84	[222]	SUB      	R14 R9 R14 ; R14 := R9 - R14
	85	[222]	CALL     	R10 5 1 ; R10(R11,R12,R13,R14)
	86	[224]	RETURN   	R0 1 ; return 

function #7 <?:226,233> (20 instructions, 80 bytes at 0000016081E95B40)
0 params, 9 slots, 2 upvalues, 0 locals, 5 constants, 1 function
	1	[227]	GETUPVAL 	R0 U0 ; R0 := U0
	2	[227]	CALL     	R0 1 1 ; R0()
	3	[229]	GETGLOBAL	R0 K0 ; R0 := 0x25312c9b
	4	[229]	GETGLOBAL	R1 K1 ; R1 := 0xae91e43b
	5	[229]	LOADK    	R2 K2 ; R2 := "_root"
	6	[229]	LOADK    	R3 := 4.000000
	7	[229]	NEWTABLE 	R4 2 0 ; R4 := {}
	8	[229]	LOADK    	R5 := 10.000000
	9	[229]	LOADK    	R6 := 4.000000
	10	[229]	SETLIST  	R4 2 1 ; R4[(1-1)*FPF+i] := R(4+i), 1 <= i <= 2
	11	[229]	NEWTABLE 	R5 2 0 ; R5 := {}
	12	[229]	LOADK    	R6 := 100.000000
	13	[229]	LOADK    	R7 := 0.000000
	14	[229]	SETLIST  	R5 2 1 ; R5[(1-1)*FPF+i] := R(5+i), 1 <= i <= 2
	15	[229]	LOADK    	R6 K4 ; R6 := 0.650000
	16	[229]	LOADK    	R7 := 0.000000
	17	[232]	CLOSURE  	R8 0 ; R8 := closure(Function #1)
	18	[232]	GETUPVAL 	R0 U1 ; R0 := U1
	19	[229]	CALL     	R0 9 1 ; R0(R1,R2,R3,R4,R5,R6,R7,R8)
	20	[233]	RETURN   	R0 1 ; return 

function #8 <?:235,271> (132 instructions, 528 bytes at 0000016081E95DE0)
0 params, 6 slots, 8 upvalues, 0 locals, 37 constants, 2 functions
	1	[236]	OP_LOADBOOL	R0 1 0 ; R0 := true
	2	[236]	SETUPVAL 	R0 U0 ; U0 := R0
	3	[238]	GETUPVAL 	R0 U1 ; R0 := U1
	4	[238]	GETTABLE 	R0 R0 K0 ; R0 := R0[0x659d451f]
	5	[238]	GETGLOBAL	R1 K1 ; R1 := 0x0032441c
	6	[238]	GETTABLE 	R1 R1 K2 ; R1 := R1["UISound_DialogOpen"]
	7	[238]	CALL     	R0 2 1 ; R0(R1)
	8	[240]	NEWTABLE 	R0 0 5 ; R0 := {}
	9	[242]	GETUPVAL 	R1 U3 ; R1 := U3
	10	[242]	GETTABLE 	R1 R1 K4 ; R1 := R1[0x5d10207d]
	11	[242]	LOADK    	R2 := 6.000000
	12	[242]	OP_LOADBOOL	R3 1 0 ; R3 := true
	13	[242]	CALL     	R1 3 2 ; R1 := R1(R2,R3)
	14	[242]	SETTABLE 	R0 K3 R1 ; R0["Content"] := R1
	15	[243]	GETUPVAL 	R1 U3 ; R1 := U3
	16	[243]	GETTABLE 	R1 R1 K4 ; R1 := R1[0x5d10207d]
	17	[243]	LOADK    	R2 := 2.000000
	18	[243]	OP_LOADBOOL	R3 1 0 ; R3 := true
	19	[243]	CALL     	R1 3 2 ; R1 := R1(R2,R3)
	20	[243]	SETTABLE 	R0 K6 R1 ; R0["Background1"] := R1
	21	[244]	GETUPVAL 	R1 U3 ; R1 := U3
	22	[244]	GETTABLE 	R1 R1 K4 ; R1 := R1[0x5d10207d]
	23	[244]	LOADK    	R2 := 1.000000
	24	[244]	OP_LOADBOOL	R3 1 0 ; R3 := true
	25	[244]	CALL     	R1 3 2 ; R1 := R1(R2,R3)
	26	[244]	SETTABLE 	R0 K7 R1 ; R0["BackerHighlight"] := R1
	27	[245]	GETUPVAL 	R1 U3 ; R1 := U3
	28	[245]	GETTABLE 	R1 R1 K4 ; R1 := R1[0x5d10207d]
	29	[245]	LOADK    	R2 := 9.000000
	30	[245]	OP_LOADBOOL	R3 1 0 ; R3 := true
	31	[245]	CALL     	R1 3 2 ; R1 := R1(R2,R3)
	32	[245]	SETTABLE 	R0 K8 R1 ; R0["FloatingContent"] := R1
	33	[246]	GETUPVAL 	R1 U3 ; R1 := U3
	34	[246]	GETTABLE 	R1 R1 K4 ; R1 := R1[0x5d10207d]
	35	[246]	LOADK    	R2 := 10.000000
	36	[246]	OP_LOADBOOL	R3 1 0 ; R3 := true
	37	[246]	CALL     	R1 3 2 ; R1 := R1(R2,R3)
	38	[246]	SETTABLE 	R0 K9 R1 ; R0["FloatingContentHighlight"] := R1
	39	[247]	SETUPVAL 	R0 U2 ; U2 := R0
	40	[248]	GETUPVAL 	R0 U2 ; R0 := U2
	41	[248]	GETUPVAL 	R1 U1 ; R1 := U1
	42	[248]	GETTABLE 	R1 R1 K11 ; R1 := R1[0x8bcd12b6]
	43	[248]	GETUPVAL 	R2 U2 ; R2 := U2
	44	[248]	GETTABLE 	R2 R2 K6 ; R2 := R2["Background1"]
	45	[248]	CALL     	R1 2 2 ; R1 := R1(R2)
	46	[248]	SETTABLE 	R0 K10 R1 ; R0["Background1Object"] := R1
	47	[249]	GETUPVAL 	R0 U2 ; R0 := U2
	48	[249]	GETUPVAL 	R1 U1 ; R1 := U1
	49	[249]	GETTABLE 	R1 R1 K11 ; R1 := R1[0x8bcd12b6]
	50	[249]	GETUPVAL 	R2 U2 ; R2 := U2
	51	[249]	GETTABLE 	R2 R2 K7 ; R2 := R2["BackerHighlight"]
	52	[249]	CALL     	R1 2 2 ; R1 := R1(R2)
	53	[249]	SETTABLE 	R0 K12 R1 ; R0["BackerHighlightObject"] := R1
	54	[250]	GETUPVAL 	R0 U2 ; R0 := U2
	55	[250]	GETUPVAL 	R1 U1 ; R1 := U1
	56	[250]	GETTABLE 	R1 R1 K11 ; R1 := R1[0x8bcd12b6]
	57	[250]	GETUPVAL 	R2 U2 ; R2 := U2
	58	[250]	GETTABLE 	R2 R2 K8 ; R2 := R2["FloatingContent"]
	59	[250]	CALL     	R1 2 2 ; R1 := R1(R2)
	60	[250]	SETTABLE 	R0 K13 R1 ; R0["FloatingContentObject"] := R1
	61	[251]	GETUPVAL 	R0 U2 ; R0 := U2
	62	[251]	GETUPVAL 	R1 U1 ; R1 := U1
	63	[251]	GETTABLE 	R1 R1 K11 ; R1 := R1[0x8bcd12b6]
	64	[251]	GETUPVAL 	R2 U2 ; R2 := U2
	65	[251]	GETTABLE 	R2 R2 K9 ; R2 := R2["FloatingContentHighlight"]
	66	[251]	CALL     	R1 2 2 ; R1 := R1(R2)
	67	[251]	SETTABLE 	R0 K14 R1 ; R0["FloatingContentHighlightObject"] := R1
	68	[253]	GETGLOBAL	R0 K15 ; R0 := 0x33bdd652
	69	[253]	GETTABLE 	R0 R0 K16 ; R0 := R0[0x23d5322f]
	70	[253]	GETUPVAL 	R1 U4 ; R1 := U4
	71	[253]	NEWTABLE 	R2 0 4 ; R2 := {}
	72	[253]	SETTABLE 	R2 K17 K18 ; R2["mVisible"] := true
	73	[253]	SETTABLE 	R2 K19 K20 ; R2["mLabel"] := "/Lotus/Language/Menu/Exit"
	74	[253]	CLOSURE  	R3 0 ; R3 := closure(Function #1)
	75	[253]	SETTABLE 	R2 K21 R3 ; R2["mCallback"] := R3
	76	[253]	SETTABLE 	R2 K22 K23 ; R2["mCallout"] := "MENU_CANCEL"
	77	[253]	CALL     	R0 3 1 ; R0(R1,R2)
	78	[254]	GETUPVAL 	R0 U5 ; R0 := U5
	79	[254]	CALL     	R0 1 1 ; R0()
	80	[256]	GETUPVAL 	R0 U6 ; R0 := U6
	81	[256]	CALL     	R0 1 1 ; R0()
	82	[258]	GETGLOBAL	R0 K24 ; R0 := 0xae91e43b
	83	[258]	SELF     	R0 R0 K25 ; R1 := R0; R0 := R0[0xd5181643]
	84	[258]	LOADK    	R2 K26 ; R2 := "FancyBits.LeftLines"
	85	[258]	GETGLOBAL	R3 K27 ; R3 := 0x996808cc
	86	[258]	CALL     	R0 4 1 ; R0(R1,R2,R3)
	87	[259]	GETGLOBAL	R0 K24 ; R0 := 0xae91e43b
	88	[259]	SELF     	R0 R0 K25 ; R1 := R0; R0 := R0[0xd5181643]
	89	[259]	LOADK    	R2 K28 ; R2 := "FancyBits.RightLines"
	90	[259]	GETGLOBAL	R3 K29 ; R3 := 0xc9e06d1b
	91	[259]	CALL     	R0 4 1 ; R0(R1,R2,R3)
	92	[260]	GETGLOBAL	R0 K24 ; R0 := 0xae91e43b
	93	[260]	SELF     	R0 R0 K30 ; R1 := R0; R0 := R0[0x67bc869f]
	94	[260]	LOADK    	R2 K26 ; R2 := "FancyBits.LeftLines"
	95	[260]	LOADK    	R3 := 9.000000
	96	[260]	GETUPVAL 	R4 U2 ; R4 := U2
	97	[260]	GETTABLE 	R4 R4 K8 ; R4 := R4["FloatingContent"]
	98	[260]	CALL     	R0 5 1 ; R0(R1,R2,R3,R4)
	99	[261]	GETGLOBAL	R0 K24 ; R0 := 0xae91e43b
	100	[261]	SELF     	R0 R0 K30 ; R1 := R0; R0 := R0[0x67bc869f]
	101	[261]	LOADK    	R2 K28 ; R2 := "FancyBits.RightLines"
	102	[261]	LOADK    	R3 := 9.000000
	103	[261]	GETUPVAL 	R4 U2 ; R4 := U2
	104	[261]	GETTABLE 	R4 R4 K8 ; R4 := R4["FloatingContent"]
	105	[261]	CALL     	R0 5 1 ; R0(R1,R2,R3,R4)
	106	[263]	GETGLOBAL	R0 K24 ; R0 := 0xae91e43b
	107	[263]	SELF     	R0 R0 K30 ; R1 := R0; R0 := R0[0x67bc869f]
	108	[263]	LOADK    	R2 K31 ; R2 := "_root"
	109	[263]	LOADK    	R3 := 10.000000
	110	[263]	LOADK    	R4 := 0.000000
	111	[263]	CALL     	R0 5 1 ; R0(R1,R2,R3,R4)
	112	[264]	GETGLOBAL	R0 K24 ; R0 := 0xae91e43b
	113	[264]	SELF     	R0 R0 K30 ; R1 := R0; R0 := R0[0x67bc869f]
	114	[264]	LOADK    	R2 K31 ; R2 := "_root"
	115	[264]	LOADK    	R3 := 4.000000
	116	[264]	LOADK    	R4 K32 ; R4 := -15000.000000
	117	[264]	CALL     	R0 5 1 ; R0(R1,R2,R3,R4)
	118	[266]	GETGLOBAL	R0 K24 ; R0 := 0xae91e43b
	119	[266]	SELF     	R0 R0 K33 ; R1 := R0; R0 := R0[0xc6a10ab1]
	120	[266]	GETUPVAL 	R2 U2 ; R2 := U2
	121	[266]	GETTABLE 	R2 R2 K6 ; R2 := R2["Background1"]
	122	[266]	CALL     	R0 3 1 ; R0(R1,R2)
	123	[267]	GETUPVAL 	R0 U1 ; R0 := U1
	124	[267]	GETTABLE 	R0 R0 K34 ; R0 := R0[0x4c232afc]
	125	[267]	GETGLOBAL	R1 K24 ; R1 := 0xae91e43b
	126	[267]	LOADK    	R2 K35 ; R2 := 0.900000
	127	[267]	LOADK    	R3 K36 ; R3 := 0.150000
	128	[267]	LOADK    	R4 := 0.000000
	129	[270]	CLOSURE  	R5 1 ; R5 := closure(Function #2)
	130	[270]	GETUPVAL 	R0 U7 ; R0 := U7
	131	[267]	CALL     	R0 6 1 ; R0(R1,R2,R3,R4,R5)
	132	[271]	RETURN   	R0 1 ; return 

function #9 <?:273,288> (43 instructions, 172 bytes at 0000016081E967A0)
0 params, 3 slots, 5 upvalues, 0 locals, 8 constants, 0 functions
	1	[274]	GETGLOBAL	R0 K0 ; R0 := 0x7b998233
	2	[274]	GETGLOBAL	R1 K1 ; R1 := 0xae91e43b
	3	[274]	CALL     	R0 2 2 ; R0 := R0(R1)
	4	[274]	TEST     	R0 0 ; if not R0 then PC := 7
	5	[274]	JMP      	7 ; PC := 7
	6	[275]	RETURN   	R0 1 ; return 
	7	[278]	GETGLOBAL	R0 K1 ; R0 := 0xae91e43b
	8	[278]	SELF     	R0 R0 K2 ; R1 := R0; R0 := R0[0x368ad758]
	9	[278]	GETGLOBAL	R2 K3 ; R2 := _T
	10	[278]	GETTABLE 	R2 R2 K4 ; R2 := R2["TopMenuOpen"]
	11	[278]	NOT      	R2 R2 ; R2 := not R2
	12	[278]	CALL     	R0 3 1 ; R0(R1,R2)
	13	[280]	GETGLOBAL	R0 K1 ; R0 := 0xae91e43b
	14	[280]	SELF     	R0 R0 K5 ; R1 := R0; R0 := R0[0x8a8c8d5a]
	15	[280]	GETGLOBAL	R2 K6 ; R2 := 0x67652851
	16	[280]	CALL     	R2 1 0 ; R2,... := R2()
	17	[280]	CALL     	R0 0 1 ; R0(R1,...)
	18	[282]	GETUPVAL 	R0 U0 ; R0 := U0
	19	[282]	TEST     	R0 0 ; if not R0 then PC := 43
	20	[282]	JMP      	43 ; PC := 43
	21	[282]	GETUPVAL 	R0 U1 ; R0 := U1
	22	[282]	TEST     	R0 1 ; if R0 then PC := 43
	23	[282]	JMP      	43 ; PC := 43
	24	[282]	GETUPVAL 	R0 U2 ; R0 := U2
	25	[282]	EQ       	1 R0 K7 ; if R0 == nil then PC := 43
	26	[282]	JMP      	43 ; PC := 43
	27	[282]	GETGLOBAL	R0 K0 ; R0 := 0x7b998233
	28	[282]	GETGLOBAL	R1 K3 ; R1 := _T
	29	[282]	GETUPVAL 	R2 U2 ; R2 := U2
	30	[282]	GETTABLE 	R1 R1 R2 ; R1 := R1[R2]
	31	[282]	CALL     	R0 2 2 ; R0 := R0(R1)
	32	[282]	TEST     	R0 1 ; if R0 then PC := 43
	33	[282]	JMP      	43 ; PC := 43
	34	[283]	GETGLOBAL	R0 K3 ; R0 := _T
	35	[283]	GETUPVAL 	R1 U2 ; R1 := U2
	36	[283]	GETTABLE 	R0 R0 R1 ; R0 := R0[R1]
	37	[283]	CALL     	R0 1 2 ; R0 := R0()
	38	[283]	SETUPVAL 	R0 U3 ; U3 := R0
	39	[285]	GETUPVAL 	R0 U4 ; R0 := U4
	40	[285]	CALL     	R0 1 1 ; R0()
	41	[286]	OP_LOADBOOL	R0 1 0 ; R0 := true
	42	[286]	SETUPVAL 	R0 U1 ; U1 := R0
	43	[288]	RETURN   	R0 1 ; return 

function #10 <?:290,296> (14 instructions, 56 bytes at 0000016081E96A40)
1 param, 5 slots, 2 upvalues, 0 locals, 3 constants, 0 functions
	1	[291]	GETUPVAL 	R1 U0 ; R1 := U0
	2	[291]	TEST     	R1 1 ; if R1 then PC := 7
	3	[291]	JMP      	7 ; PC := 7
	4	[291]	GETUPVAL 	R1 U1 ; R1 := U1
	5	[291]	EQ       	0 R1 K0 ; if R1 ~= nil then PC := 8
	6	[291]	JMP      	8 ; PC := 8
	7	[292]	RETURN   	R0 1 ; return 
	8	[295]	GETUPVAL 	R1 U1 ; R1 := U1
	9	[295]	SELF     	R1 R1 K1 ; R2 := R1; R1 := R1[0xdf42446e]
	10	[295]	GETGLOBAL	R3 K2 ; R3 := 0x03f57322
	11	[295]	MOVE     	R4 R0 ; R4 := R0
	12	[295]	CALL     	R3 2 0 ; R3,... := R3(R4)
	13	[295]	CALL     	R1 0 1 ; R1(R2,...)
	14	[296]	RETURN   	R0 1 ; return 

function #11 <?:298,304> (14 instructions, 56 bytes at 0000016081E96BB0)
1 param, 5 slots, 2 upvalues, 0 locals, 3 constants, 0 functions
	1	[299]	GETUPVAL 	R1 U0 ; R1 := U0
	2	[299]	TEST     	R1 1 ; if R1 then PC := 7
	3	[299]	JMP      	7 ; PC := 7
	4	[299]	GETUPVAL 	R1 U1 ; R1 := U1
	5	[299]	EQ       	0 R1 K0 ; if R1 ~= nil then PC := 8
	6	[299]	JMP      	8 ; PC := 8
	7	[300]	RETURN   	R0 1 ; return 
	8	[303]	GETUPVAL 	R1 U1 ; R1 := U1
	9	[303]	SELF     	R1 R1 K1 ; R2 := R1; R1 := R1[0xbce5a201]
	10	[303]	GETGLOBAL	R3 K2 ; R3 := 0x03f57322
	11	[303]	MOVE     	R4 R0 ; R4 := R0
	12	[303]	CALL     	R3 2 0 ; R3,... := R3(R4)
	13	[303]	CALL     	R1 0 1 ; R1(R2,...)
	14	[304]	RETURN   	R0 1 ; return 

function #12 <?:306,312> (14 instructions, 56 bytes at 0000016081E96D20)
1 param, 5 slots, 2 upvalues, 0 locals, 3 constants, 0 functions
	1	[307]	GETUPVAL 	R1 U0 ; R1 := U0
	2	[307]	TEST     	R1 1 ; if R1 then PC := 7
	3	[307]	JMP      	7 ; PC := 7
	4	[307]	GETUPVAL 	R1 U1 ; R1 := U1
	5	[307]	EQ       	0 R1 K0 ; if R1 ~= nil then PC := 8
	6	[307]	JMP      	8 ; PC := 8
	7	[308]	RETURN   	R0 1 ; return 
	8	[311]	GETUPVAL 	R1 U1 ; R1 := U1
	9	[311]	SELF     	R1 R1 K1 ; R2 := R1; R1 := R1[0x070daa5a]
	10	[311]	GETGLOBAL	R3 K2 ; R3 := 0x03f57322
	11	[311]	MOVE     	R4 R0 ; R4 := R0
	12	[311]	CALL     	R3 2 0 ; R3,... := R3(R4)
	13	[311]	CALL     	R1 0 1 ; R1(R2,...)
	14	[312]	RETURN   	R0 1 ; return 

function #13 <?:314,318> (7 instructions, 28 bytes at 0000016081E96E90)
0 params, 2 slots, 2 upvalues, 0 locals, 1 constant, 0 functions
	1	[315]	GETUPVAL 	R0 U0 ; R0 := U0
	2	[315]	TEST     	R0 1 ; if R0 then PC := 7
	3	[315]	JMP      	7 ; PC := 7
	4	[316]	GETUPVAL 	R0 U1 ; R0 := U1
	5	[316]	SELF     	R0 R0 K0 ; R1 := R0; R0 := R0[0x8b24ce41]
	6	[316]	CALL     	R0 2 1 ; R0(R1)
	7	[318]	RETURN   	R0 1 ; return 

function #14 <?:320,324> (12 instructions, 48 bytes at 0000016081E96FA0)
0 params, 2 slots, 2 upvalues, 0 locals, 3 constants, 0 functions
	1	[321]	GETUPVAL 	R0 U0 ; R0 := U0
	2	[321]	TEST     	R0 1 ; if R0 then PC := 12
	3	[321]	JMP      	12 ; PC := 12
	4	[321]	GETUPVAL 	R0 U1 ; R0 := U1
	5	[321]	GETTABLE 	R0 R0 K0 ; R0 := R0[1.000000]
	6	[321]	EQ       	1 R0 K1 ; if R0 == nil then PC := 12
	7	[321]	JMP      	12 ; PC := 12
	8	[322]	GETUPVAL 	R0 U1 ; R0 := U1
	9	[322]	GETTABLE 	R0 R0 K0 ; R0 := R0[1.000000]
	10	[322]	GETTABLE 	R0 R0 K2 ; R0 := R0[0x7ca0d7fa]
	11	[322]	CALL     	R0 1 1 ; R0()
	12	[324]	RETURN   	R0 1 ; return 

function #15 <?:326,328> (2 instructions, 8 bytes at 0000016081E970F0)
1 param, 2 slots, 1 upvalue, 0 locals, 0 constants, 0 functions
	1	[327]	SETUPVAL 	R0 U0 ; U0 := R0
	2	[328]	RETURN   	R0 1 ; return 

function #16 <?:330,332> (2 instructions, 8 bytes at 0000016081E971C0)
1 param, 2 slots, 1 upvalue, 0 locals, 0 constants, 0 functions
	1	[331]	SETUPVAL 	R0 U0 ; U0 := R0
	2	[332]	RETURN   	R0 1 ; return 

function #17 <?:334,336> (3 instructions, 12 bytes at 0000016081E97290)
0 params, 2 slots, 0 upvalues, 0 locals, 0 constants, 0 functions
	1	[335]	OP_LOADBOOL	R0 1 0 ; R0 := true
	2	[335]	RETURN   	R0 2 ; return R0 
	3	[336]	RETURN   	R0 1 ; return 
