; This file has been disassembled using luadec 2.0.2 by sztupy (modified by Reversive)

; Name:            
; Defined at line: 0
; #Upvalues:       0
; #Parameters:     0
; Is_vararg:       2
; Max Stack Size:  21

  1 [-]: CLOSURE   R0 0         ; R0 := closure(Function #1)
  2 [-]: NEWTABLE  R1 7 0       ; R1 := {}
  3 [-]: GETGLOBAL R2 K0        ; R2 := 0xa421af95
  4 [-]: CALL      R2 1 2       ; R2 := R2()
  5 [-]: GETGLOBAL R3 K0        ; R3 := 0xa421af95
  6 [-]: LOADK     R4 0         ; R4 := 0.000000
  7 [-]: LOADK     R5 0         ; R5 := 0.000000
  8 [-]: LOADK     R6 1         ; R6 := 1.000000
  9 [-]: CALL      R3 4 2       ; R3 := R3(R4,R5,R6)
 10 [-]: GETGLOBAL R4 K0        ; R4 := 0xa421af95
 11 [-]: LOADK     R5 0         ; R5 := 0.000000
 12 [-]: LOADK     R6 1         ; R6 := 1.000000
 13 [-]: LOADK     R7 0         ; R7 := 0.000000
 14 [-]: CALL      R4 4 2       ; R4 := R4(R5,R6,R7)
 15 [-]: GETGLOBAL R5 K0        ; R5 := 0xa421af95
 16 [-]: LOADK     R6 0         ; R6 := 0.000000
 17 [-]: LOADK     R7 1         ; R7 := 1.000000
 18 [-]: LOADK     R8 1         ; R8 := 1.000000
 19 [-]: CALL      R5 4 2       ; R5 := R5(R6,R7,R8)
 20 [-]: GETGLOBAL R6 K0        ; R6 := 0xa421af95
 21 [-]: LOADK     R7 1         ; R7 := 1.000000
 22 [-]: LOADK     R8 0         ; R8 := 0.000000
 23 [-]: LOADK     R9 0         ; R9 := 0.000000
 24 [-]: CALL      R6 4 2       ; R6 := R6(R7,R8,R9)
 25 [-]: GETGLOBAL R7 K0        ; R7 := 0xa421af95
 26 [-]: LOADK     R8 1         ; R8 := 1.000000
 27 [-]: LOADK     R9 0         ; R9 := 0.000000
 28 [-]: LOADK     R10 1        ; R10 := 1.000000
 29 [-]: CALL      R7 4 2       ; R7 := R7(R8,R9,R10)
 30 [-]: GETGLOBAL R8 K0        ; R8 := 0xa421af95
 31 [-]: LOADK     R9 1         ; R9 := 1.000000
 32 [-]: LOADK     R10 1        ; R10 := 1.000000
 33 [-]: LOADK     R11 0        ; R11 := 0.000000
 34 [-]: CALL      R8 4 2       ; R8 := R8(R9,R10,R11)
 35 [-]: GETGLOBAL R9 K0        ; R9 := 0xa421af95
 36 [-]: LOADK     R10 1        ; R10 := 1.000000
 37 [-]: LOADK     R11 1        ; R11 := 1.000000
 38 [-]: LOADK     R12 1        ; R12 := 1.000000
 39 [-]: CALL      R9 4 0       ; R9,... := R9(R10,R11,R12)
 40 [-]: SETLIST   R1 0 1       ; R1[(1-1)*FPF+i] := R(1+i), 1 <= i <= 0
 41 [-]: GETGLOBAL R2 K0        ; R2 := 0xa421af95
 42 [-]: LOADK     R3 1         ; R3 := 1.000000
 43 [-]: LOADK     R4 1         ; R4 := 1.000000
 44 [-]: LOADK     R5 1         ; R5 := 1.000000
 45 [-]: CALL      R2 4 2       ; R2 := R2(R3,R4,R5)
 46 [-]: NEWTABLE  R3 4 0       ; R3 := {}
 47 [-]: NEWTABLE  R4 4 0       ; R4 := {}
 48 [-]: LOADK     R5 1         ; R5 := 1.000000
 49 [-]: LOADK     R6 2         ; R6 := 2.000000
 50 [-]: LOADK     R7 3         ; R7 := 3.000000
 51 [-]: LOADK     R8 5         ; R8 := 5.000000
 52 [-]: SETLIST   R4 4 1       ; R4[(1-1)*FPF+i] := R(4+i), 1 <= i <= 4
 53 [-]: NEWTABLE  R5 4 0       ; R5 := {}
 54 [-]: LOADK     R6 6         ; R6 := 6.000000
 55 [-]: LOADK     R7 2         ; R7 := 2.000000
 56 [-]: LOADK     R8 5         ; R8 := 5.000000
 57 [-]: LOADK     R9 8         ; R9 := 8.000000
 58 [-]: SETLIST   R5 4 1       ; R5[(1-1)*FPF+i] := R(5+i), 1 <= i <= 4
 59 [-]: NEWTABLE  R6 4 0       ; R6 := {}
 60 [-]: LOADK     R7 4         ; R7 := 4.000000
 61 [-]: LOADK     R8 3         ; R8 := 3.000000
 62 [-]: LOADK     R9 2         ; R9 := 2.000000
 63 [-]: LOADK     R10 8        ; R10 := 8.000000
 64 [-]: SETLIST   R6 4 1       ; R6[(1-1)*FPF+i] := R(6+i), 1 <= i <= 4
 65 [-]: NEWTABLE  R7 4 0       ; R7 := {}
 66 [-]: LOADK     R8 7         ; R8 := 7.000000
 67 [-]: LOADK     R9 3         ; R9 := 3.000000
 68 [-]: LOADK     R10 8        ; R10 := 8.000000
 69 [-]: LOADK     R11 5        ; R11 := 5.000000
 70 [-]: SETLIST   R7 4 1       ; R7[(1-1)*FPF+i] := R(7+i), 1 <= i <= 4
 71 [-]: SETLIST   R3 4 1       ; R3[(1-1)*FPF+i] := R(3+i), 1 <= i <= 4
 72 [-]: CLOSURE   R4 1         ; R4 := closure(Function #2)
 73 [-]: MOVE      R0 R0        ; R0 := R0
 74 [-]: MOVE      R0 R1        ; R0 := R1
 75 [-]: MOVE      R0 R2        ; R0 := R2
 76 [-]: CLOSURE   R5 2         ; R5 := closure(Function #3)
 77 [-]: MOVE      R0 R4        ; R0 := R4
 78 [-]: MOVE      R0 R3        ; R0 := R3
 79 [-]: CLOSURE   R6 3         ; R6 := closure(Function #4)
 80 [-]: NEWTABLE  R7 0 0       ; R7 := {}
 81 [-]: SETTABLE  R7 K1 R7     ; R7["__index"] := R7
 82 [-]: CLOSURE   R8 4         ; R8 := closure(Function #5)
 83 [-]: SETTABLE  R7 K2 R8     ; R7[true] := R8
 84 [-]: CLOSURE   R8 5         ; R8 := closure(Function #6)
 85 [-]: SETTABLE  R7 K3 R8     ; R7[true] := R8
 86 [-]: CLOSURE   R8 6         ; R8 := closure(Function #7)
 87 [-]: SETTABLE  R7 K4 R8     ; R7[true] := R8
 88 [-]: CLOSURE   R8 7         ; R8 := closure(Function #8)
 89 [-]: MOVE      R0 R7        ; R0 := R7
 90 [-]: SETTABLE  R7 K5 R8     ; R7[true] := R8
 91 [-]: NEWTABLE  R8 0 2       ; R8 := {}
 92 [-]: SETTABLE  R8 K6 K7     ; R8["RESOURCE"] := 1.000000
 93 [-]: SETTABLE  R8 K8 K9     ; R8["CANDIDATE"] := 2.000000
 94 [-]: NEWTABLE  R9 0 0       ; R9 := {}
 95 [-]: SETTABLE  R9 K1 R9     ; R9["__index"] := R9
 96 [-]: CLOSURE   R10 8        ; R10 := closure(Function #9)
 97 [-]: MOVE      R0 R8        ; R0 := R8
 98 [-]: SETTABLE  R9 K10 R10   ; R9[true] := R10
 99 [-]: CLOSURE   R10 9        ; R10 := closure(Function #10)
100 [-]: MOVE      R0 R8        ; R0 := R8
101 [-]: SETTABLE  R9 K11 R10   ; R9[true] := R10
102 [-]: CLOSURE   R10 10       ; R10 := closure(Function #11)
103 [-]: SETTABLE  R9 K12 R10   ; R9[true] := R10
104 [-]: CLOSURE   R10 11       ; R10 := closure(Function #12)
105 [-]: MOVE      R0 R6        ; R0 := R6
106 [-]: SETTABLE  R9 K13 R10   ; R9[true] := R10
107 [-]: GETGLOBAL R10 K14      ; R10 := 0x910f4761
108 [-]: CALL      R10 1 2      ; R10 := R10()
109 [-]: CLOSURE   R11 12       ; R11 := closure(Function #13)
110 [-]: MOVE      R0 R10       ; R0 := R10
111 [-]: SETTABLE  R9 K15 R11   ; R9[true] := R11
112 [-]: CLOSURE   R11 13       ; R11 := closure(Function #14)
113 [-]: MOVE      R0 R8        ; R0 := R8
114 [-]: SETTABLE  R9 K16 R11   ; R9[true] := R11
115 [-]: CLOSURE   R11 14       ; R11 := closure(Function #15)
116 [-]: MOVE      R0 R9        ; R0 := R9
117 [-]: MOVE      R0 R7        ; R0 := R7
118 [-]: SETTABLE  R9 K5 R11    ; R9[true] := R11
119 [-]: NEWTABLE  R11 0 0      ; R11 := {}
120 [-]: SETTABLE  R11 K1 R11   ; R11["__index"] := R11
121 [-]: CLOSURE   R12 15       ; R12 := closure(Function #16)
122 [-]: SETTABLE  R11 K17 R12  ; R11[true] := R12
123 [-]: CLOSURE   R12 16       ; R12 := closure(Function #17)
124 [-]: MOVE      R0 R5        ; R0 := R5
125 [-]: SETTABLE  R11 K16 R12  ; R11[true] := R12
126 [-]: CLOSURE   R12 17       ; R12 := closure(Function #18)
127 [-]: MOVE      R0 R6        ; R0 := R6
128 [-]: SETTABLE  R11 K18 R12  ; R11[true] := R12
129 [-]: CLOSURE   R12 18       ; R12 := closure(Function #19)
130 [-]: SETTABLE  R11 K19 R12  ; R11[true] := R12
131 [-]: CLOSURE   R12 19       ; R12 := closure(Function #20)
132 [-]: SETTABLE  R11 K20 R12  ; R11[true] := R12
133 [-]: CLOSURE   R12 20       ; R12 := closure(Function #21)
134 [-]: SETTABLE  R11 K15 R12  ; R11[true] := R12
135 [-]: CLOSURE   R12 21       ; R12 := closure(Function #22)
136 [-]: SETTABLE  R11 K21 R12  ; R11[true] := R12
137 [-]: CLOSURE   R12 22       ; R12 := closure(Function #23)
138 [-]: MOVE      R0 R11       ; R0 := R11
139 [-]: MOVE      R0 R7        ; R0 := R7
140 [-]: SETTABLE  R11 K5 R12   ; R11[true] := R12
141 [-]: NEWTABLE  R12 0 0      ; R12 := {}
142 [-]: SETTABLE  R12 K1 R12   ; R12["__index"] := R12
143 [-]: CLOSURE   R13 23       ; R13 := closure(Function #24)
144 [-]: SETTABLE  R12 K22 R13  ; R12[true] := R13
145 [-]: CLOSURE   R13 24       ; R13 := closure(Function #25)
146 [-]: SETTABLE  R12 K23 R13  ; R12[true] := R13
147 [-]: CLOSURE   R13 25       ; R13 := closure(Function #26)
148 [-]: SETTABLE  R12 K24 R13  ; R12[true] := R13
149 [-]: CLOSURE   R13 26       ; R13 := closure(Function #27)
150 [-]: SETTABLE  R12 K25 R13  ; R12[true] := R13
151 [-]: CLOSURE   R13 27       ; R13 := closure(Function #28)
152 [-]: SETTABLE  R12 K26 R13  ; R12[true] := R13
153 [-]: CLOSURE   R13 28       ; R13 := closure(Function #29)
154 [-]: SETTABLE  R12 K27 R13  ; R12[true] := R13
155 [-]: CLOSURE   R13 29       ; R13 := closure(Function #30)
156 [-]: SETTABLE  R12 K28 R13  ; R12[true] := R13
157 [-]: CLOSURE   R13 30       ; R13 := closure(Function #31)
158 [-]: SETTABLE  R12 K29 R13  ; R12[true] := R13
159 [-]: CLOSURE   R13 31       ; R13 := closure(Function #32)
160 [-]: SETTABLE  R12 K30 R13  ; R12[true] := R13
161 [-]: CLOSURE   R13 32       ; R13 := closure(Function #33)
162 [-]: SETTABLE  R12 K31 R13  ; R12[true] := R13
163 [-]: CLOSURE   R13 33       ; R13 := closure(Function #34)
164 [-]: SETTABLE  R12 K32 R13  ; R12[true] := R13
165 [-]: CLOSURE   R13 34       ; R13 := closure(Function #35)
166 [-]: SETTABLE  R12 K33 R13  ; R12[true] := R13
167 [-]: CLOSURE   R13 35       ; R13 := closure(Function #36)
168 [-]: SETTABLE  R12 K34 R13  ; R12[true] := R13
169 [-]: CLOSURE   R13 36       ; R13 := closure(Function #37)
170 [-]: SETTABLE  R12 K35 R13  ; R12[true] := R13
171 [-]: CLOSURE   R13 37       ; R13 := closure(Function #38)
172 [-]: MOVE      R0 R9        ; R0 := R9
173 [-]: SETTABLE  R12 K36 R13  ; R12[true] := R13
174 [-]: CLOSURE   R13 38       ; R13 := closure(Function #39)
175 [-]: MOVE      R0 R11       ; R0 := R11
176 [-]: CLOSURE   R14 39       ; R14 := closure(Function #40)
177 [-]: MOVE      R0 R5        ; R0 := R5
178 [-]: CLOSURE   R15 40       ; R15 := closure(Function #41)
179 [-]: CLOSURE   R16 41       ; R16 := closure(Function #42)
180 [-]: CLOSURE   R17 42       ; R17 := closure(Function #43)
181 [-]: CLOSURE   R18 43       ; R18 := closure(Function #44)
182 [-]: CLOSURE   R19 44       ; R19 := closure(Function #45)
183 [-]: MOVE      R0 R17       ; R0 := R17
184 [-]: MOVE      R0 R14       ; R0 := R14
185 [-]: MOVE      R0 R15       ; R0 := R15
186 [-]: MOVE      R0 R16       ; R0 := R16
187 [-]: MOVE      R0 R18       ; R0 := R18
188 [-]: SETTABLE  R12 K15 R19  ; R12[true] := R19
189 [-]: CLOSURE   R19 45       ; R19 := closure(Function #46)
190 [-]: SETTABLE  R12 K37 R19  ; R12[true] := R19
191 [-]: CLOSURE   R19 46       ; R19 := closure(Function #47)
192 [-]: SETTABLE  R12 K38 R19  ; R12[true] := R19
193 [-]: CLOSURE   R19 47       ; R19 := closure(Function #48)
194 [-]: SETTABLE  R12 K39 R19  ; R12[true] := R19
195 [-]: CLOSURE   R19 48       ; R19 := closure(Function #49)
196 [-]: MOVE      R0 R12       ; R0 := R12
197 [-]: MOVE      R0 R13       ; R0 := R13
198 [-]: MOVE      R0 R7        ; R0 := R7
199 [-]: NEWTABLE  R20 0 1      ; R20 := {}
200 [-]: SETTABLE  R20 K40 R19  ; R20["New"] := R19
201 [-]: RETURN    R20 2        ; return R20
202 [-]: RETURN    R0 1         ; return 


; Function #1:
;
; Name:            
; Defined at line: 2
; #Upvalues:       0
; #Parameters:     2
; Is_vararg:       0
; Max Stack Size:  7

  1 [-]: GETGLOBAL R2 K0        ; R2 := 0xa421af95
  2 [-]: GETTABLE  R3 R0 K1     ; R3 := R0["x"]
  3 [-]: GETTABLE  R4 R1 K1     ; R4 := R1["x"]
  4 [-]: MUL       R3 R3 R4     ; R3 := R3 * R4
  5 [-]: GETTABLE  R4 R0 K2     ; R4 := R0["y"]
  6 [-]: GETTABLE  R5 R1 K2     ; R5 := R1["y"]
  7 [-]: MUL       R4 R4 R5     ; R4 := R4 * R5
  8 [-]: GETTABLE  R5 R0 K3     ; R5 := R0["z"]
  9 [-]: GETTABLE  R6 R1 K3     ; R6 := R1["z"]
 10 [-]: MUL       R5 R5 R6     ; R5 := R5 * R6
 11 [-]: TAILCALL  R2 4 0       ; R2,... := R2(R3,R4,R5)
 12 [-]: RETURN    R2 0         ; return R2,...
 13 [-]: RETURN    R0 1         ; return 


; Function #2:
;
; Name:            
; Defined at line: 24
; #Upvalues:       3
; #Parameters:     3
; Is_vararg:       0
; Max Stack Size:  8

  1 [-]: GETUPVAL  R3 U0        ; R3 := U0
  2 [-]: MOVE      R4 R0        ; R4 := R0
  3 [-]: GETUPVAL  R5 U1        ; R5 := U1
  4 [-]: GETTABLE  R5 R5 R2     ; R5 := R5[R2]
  5 [-]: CALL      R3 3 2       ; R3 := R3(R4,R5)
  6 [-]: GETUPVAL  R4 U0        ; R4 := U0
  7 [-]: MOVE      R5 R1        ; R5 := R1
  8 [-]: GETUPVAL  R6 U2        ; R6 := U2
  9 [-]: GETUPVAL  R7 U1        ; R7 := U1
 10 [-]: GETTABLE  R7 R7 R2     ; R7 := R7[R2]
 11 [-]: SUB       R6 R6 R7     ; R6 := R6 - R7
 12 [-]: CALL      R4 3 2       ; R4 := R4(R5,R6)
 13 [-]: ADD       R3 R3 R4     ; R3 := R3 + R4
 14 [-]: RETURN    R3 2         ; return R3
 15 [-]: RETURN    R0 1         ; return 


; Function #3:
;
; Name:            
; Defined at line: 28
; #Upvalues:       2
; #Parameters:     4
; Is_vararg:       0
; Max Stack Size:  24

  1 [-]: NEWTABLE  R4 0 0       ; R4 := {}
  2 [-]: LOADK     R5 1         ; R5 := 1.000000
  3 [-]: LOADK     R6 8         ; R6 := 8.000000
  4 [-]: LOADK     R7 1         ; R7 := 1.000000
  5 [-]: FORPREP   R5 12        ; R5 -= R7; PC := 12
  6 [-]: GETUPVAL  R9 U0        ; R9 := U0
  7 [-]: MOVE      R10 R0       ; R10 := R0
  8 [-]: MOVE      R11 R1       ; R11 := R1
  9 [-]: MOVE      R12 R8       ; R12 := R8
 10 [-]: CALL      R9 4 2       ; R9 := R9(R10,R11,R12)
 11 [-]: SETTABLE  R4 R8 R9     ; R4[R8] := R9
 12 [-]: FORLOOP   R5 6         ; R5 += R7; if R5 <= R6 then begin PC := 6; R8 := R5 end
 13 [-]: LOADK     R9 1         ; R9 := 1.000000
 14 [-]: LOADK     R10 4        ; R10 := 4.000000
 15 [-]: LOADK     R11 1        ; R11 := 1.000000
 16 [-]: FORPREP   R9 35        ; R9 -= R11; PC := 35
 17 [-]: GETUPVAL  R13 U1       ; R13 := U1
 18 [-]: GETTABLE  R13 R13 R12  ; R13 := R13[R12]
 19 [-]: GETTABLE  R13 R13 K0   ; R13 := R13[1.000000]
 20 [-]: LOADK     R14 2        ; R14 := 2.000000
 21 [-]: LOADK     R15 4        ; R15 := 4.000000
 22 [-]: LOADK     R16 1        ; R16 := 1.000000
 23 [-]: FORPREP   R14 34       ; R14 -= R16; PC := 34
 24 [-]: GETGLOBAL R18 K1       ; R18 := 0x89326c93
 25 [-]: SELF      R18 R18 K2   ; R19 := R18; R18 := R18[0x1cecd8f9]
 26 [-]: GETTABLE  R20 R4 R13   ; R20 := R4[R13]
 27 [-]: GETUPVAL  R21 U1       ; R21 := U1
 28 [-]: GETTABLE  R21 R21 R12  ; R21 := R21[R12]
 29 [-]: GETTABLE  R21 R21 R17  ; R21 := R21[R17]
 30 [-]: GETTABLE  R21 R4 R21   ; R21 := R4[R21]
 31 [-]: MOVE      R22 R2       ; R22 := R2
 32 [-]: MOVE      R23 R3       ; R23 := R3
 33 [-]: CALL      R18 6 1      ; R18(R19,R20,R21,R22,R23)
 34 [-]: FORLOOP   R14 24       ; R14 += R16; if R14 <= R15 then begin PC := 24; R17 := R14 end
 35 [-]: FORLOOP   R9 17        ; R9 += R11; if R9 <= R10 then begin PC := 17; R12 := R9 end
 36 [-]: RETURN    R0 1         ; return 


; Function #4:
;
; Name:            
; Defined at line: 43
; #Upvalues:       0
; #Parameters:     1
; Is_vararg:       0
; Max Stack Size:  7

  1 [-]: GETGLOBAL R1 K0        ; R1 := 0xcfc01047
  2 [-]: MOVE      R2 R0        ; R2 := R0
  3 [-]: CALL      R1 2 4       ; R1,R2,R3 := R1(R2)
  4 [-]: JMP       6            ; PC := 6
  5 [-]: SETTABLE  R0 R4 K1     ; R0[R4] := nil
  6 [-]: TFORLOOP  R1 2         ; R4,R5 :=  R1(R2,R3); if R4 ~= nil then begin PC = 5; R3 := R4 end
  7 [-]: JMP       5            ; PC := 5
  8 [-]: RETURN    R0 1         ; return 


; Function #5:
;
; Name:            
; Defined at line: 53
; #Upvalues:       0
; #Parameters:     2
; Is_vararg:       0
; Max Stack Size:  4

  1 [-]: GETTABLE  R2 R0 K0     ; R2 := R0["tail"]
  2 [-]: ADD       R2 R2 K1     ; R2 := R2 + 1.000000
  3 [-]: SETTABLE  R0 K0 R2     ; R0["tail"] := R2
  4 [-]: GETTABLE  R2 R0 K2     ; R2 := R0["data"]
  5 [-]: GETTABLE  R3 R0 K0     ; R3 := R0["tail"]
  6 [-]: SETTABLE  R2 R3 R1     ; R2[R3] := R1
  7 [-]: GETTABLE  R2 R0 K3     ; R2 := R0["length"]
  8 [-]: ADD       R2 R2 K1     ; R2 := R2 + 1.000000
  9 [-]: SETTABLE  R0 K3 R2     ; R0["length"] := R2
 10 [-]: RETURN    R0 1         ; return 


; Function #6:
;
; Name:            
; Defined at line: 59
; #Upvalues:       0
; #Parameters:     2
; Is_vararg:       0
; Max Stack Size:  5

  1 [-]: GETTABLE  R2 R0 K0     ; R2 := R0["length"]
  2 [-]: LT        0 K1 R2      ; if 0.000000 >= R2 then PC := 22
  3 [-]: JMP       22           ; PC := 22
  4 [-]: GETGLOBAL R2 K2        ; R2 := 0x60cce7b4
  5 [-]: GETTABLE  R3 R0 K3     ; R3 := R0["head"]
  6 [-]: GETTABLE  R4 R0 K4     ; R4 := R0["tail"]
  7 [-]: LE        1 R3 R4      ; if R3 <= R4 then PC := 10
  8 [-]: JMP       10           ; PC := 10
  9 [-]: LOADBOOL  R3 0 1       ; R3 := false; PC := 10
 10 [-]: LOADBOOL  R3 1 0       ; R3 := true
 11 [-]: CALL      R2 2 1       ; R2(R3)
 12 [-]: GETTABLE  R2 R0 K3     ; R2 := R0["head"]
 13 [-]: ADD       R2 R2 K5     ; R2 := R2 + 1.000000
 14 [-]: SETTABLE  R0 K3 R2     ; R0["head"] := R2
 15 [-]: GETTABLE  R2 R0 K6     ; R2 := R0["data"]
 16 [-]: GETTABLE  R3 R0 K3     ; R3 := R0["head"]
 17 [-]: GETTABLE  R2 R2 R3     ; R2 := R2[R3]
 18 [-]: GETTABLE  R3 R0 K0     ; R3 := R0["length"]
 19 [-]: SUB       R3 R3 K5     ; R3 := R3 - 1.000000
 20 [-]: SETTABLE  R0 K0 R3     ; R0["length"] := R3
 21 [-]: RETURN    R2 2         ; return R2
 22 [-]: LOADNIL   R3 R3        ; R3 := nil
 23 [-]: RETURN    R3 2         ; return R3
 24 [-]: RETURN    R0 1         ; return 


; Function #7:
;
; Name:            
; Defined at line: 71
; #Upvalues:       0
; #Parameters:     1
; Is_vararg:       0
; Max Stack Size:  2

  1 [-]: SETTABLE  R0 K0 K1     ; R0["head"] := 0.000000
  2 [-]: SETTABLE  R0 K2 K1     ; R0["tail"] := 0.000000
  3 [-]: SETTABLE  R0 K3 K1     ; R0["length"] := 0.000000
  4 [-]: RETURN    R0 1         ; return 


; Function #8:
;
; Name:            
; Defined at line: 77
; #Upvalues:       1
; #Parameters:     0
; Is_vararg:       0
; Max Stack Size:  3

  1 [-]: GETGLOBAL R0 K0        ; R0 := 0x2296a8fd
  2 [-]: NEWTABLE  R1 0 0       ; R1 := {}
  3 [-]: GETUPVAL  R2 U0        ; R2 := U0
  4 [-]: CALL      R0 3 2       ; R0 := R0(R1,R2)
  5 [-]: NEWTABLE  R1 0 0       ; R1 := {}
  6 [-]: SETTABLE  R0 K1 R1     ; R0["data"] := R1
  7 [-]: SELF      R1 R0 K2     ; R2 := R0; R1 := R0[0x36fcc811]
  8 [-]: CALL      R1 2 1       ; R1(R2)
  9 [-]: RETURN    R0 2         ; return R0
 10 [-]: RETURN    R0 1         ; return 


; Function #9:
;
; Name:            
; Defined at line: 93
; #Upvalues:       1
; #Parameters:     4
; Is_vararg:       0
; Max Stack Size:  11

  1 [-]: SELF      R4 R0 K0     ; R5 := R0; R4 := R0[0xcdf11087]
  2 [-]: GETUPVAL  R6 U0        ; R6 := U0
  3 [-]: GETTABLE  R6 R6 K1     ; R6 := R6["RESOURCE"]
  4 [-]: MOVE      R7 R1        ; R7 := R1
  5 [-]: MOVE      R8 R2        ; R8 := R2
  6 [-]: LOADBOOL  R9 0 0       ; R9 := false
  7 [-]: MOVE      R10 R3       ; R10 := R3
  8 [-]: CALL      R4 7 1       ; R4(R5,R6,R7,R8,R9,R10)
  9 [-]: RETURN    R0 1         ; return 


; Function #10:
;
; Name:            
; Defined at line: 97
; #Upvalues:       1
; #Parameters:     5
; Is_vararg:       0
; Max Stack Size:  12

  1 [-]: SELF      R5 R0 K0     ; R6 := R0; R5 := R0[0xcdf11087]
  2 [-]: GETUPVAL  R7 U0        ; R7 := U0
  3 [-]: GETTABLE  R7 R7 K1     ; R7 := R7["CANDIDATE"]
  4 [-]: MOVE      R8 R1        ; R8 := R1
  5 [-]: MOVE      R9 R2        ; R9 := R2
  6 [-]: MOVE      R10 R3       ; R10 := R3
  7 [-]: MOVE      R11 R4       ; R11 := R4
  8 [-]: CALL      R5 7 1       ; R5(R6,R7,R8,R9,R10,R11)
  9 [-]: RETURN    R0 1         ; return 


; Function #11:
;
; Name:            
; Defined at line: 101
; #Upvalues:       0
; #Parameters:     1
; Is_vararg:       0
; Max Stack Size:  2

  1 [-]: GETTABLE  R1 R0 K0     ; R1 := R0["mResultsQueue"]
  2 [-]: RETURN    R1 2         ; return R1
  3 [-]: RETURN    R0 1         ; return 


; Function #12:
;
; Name:            
; Defined at line: 105
; #Upvalues:       1
; #Parameters:     6
; Is_vararg:       0
; Max Stack Size:  14

  1 [-]: SETTABLE  R0 K0 R1     ; R0["mQueryType"] := R1
  2 [-]: GETTABLE  R6 R0 K1     ; R6 := R0["mPosition"]
  3 [-]: GETTABLE  R7 R2 K2     ; R7 := R2["x"]
  4 [-]: SETTABLE  R6 K2 R7     ; R6["x"] := R7
  5 [-]: GETTABLE  R6 R0 K1     ; R6 := R0["mPosition"]
  6 [-]: GETTABLE  R7 R2 K3     ; R7 := R2["y"]
  7 [-]: SETTABLE  R6 K3 R7     ; R6["y"] := R7
  8 [-]: GETTABLE  R6 R0 K1     ; R6 := R0["mPosition"]
  9 [-]: GETTABLE  R7 R2 K4     ; R7 := R2["z"]
 10 [-]: SETTABLE  R6 K4 R7     ; R6["z"] := R7
 11 [-]: SETTABLE  R0 K5 R3     ; R0["mRange"] := R3
 12 [-]: GETTABLE  R6 R0 K6     ; R6 := R0["mResultsQueue"]
 13 [-]: SELF      R6 R6 K7     ; R7 := R6; R6 := R6[0x36fcc811]
 14 [-]: CALL      R6 2 1       ; R6(R7)
 15 [-]: SETTABLE  R0 K8 R4     ; R0["mRemoveResults"] := R4
 16 [-]: SETTABLE  R0 K9 R5     ; R0["mDoDebug"] := R5
 17 [-]: SETTABLE  R0 K10 K11   ; R0["mActiveQuery"] := true
 18 [-]: GETTABLE  R6 R0 K12    ; R6 := R0["mNextCellList"]
 19 [-]: SELF      R6 R6 K7     ; R7 := R6; R6 := R6[0x36fcc811]
 20 [-]: CALL      R6 2 1       ; R6(R7)
 21 [-]: GETTABLE  R6 R0 K12    ; R6 := R0["mNextCellList"]
 22 [-]: SELF      R6 R6 K13    ; R7 := R6; R6 := R6[0xdd2c9860]
 23 [-]: GETTABLE  R8 R0 K14    ; R8 := R0["mGrid"]
 24 [-]: SELF      R8 R8 K15    ; R9 := R8; R8 := R8[0x54c093f8]
 25 [-]: MOVE      R10 R2       ; R10 := R2
 26 [-]: CALL      R8 3 0       ; R8,... := R8(R9,R10)
 27 [-]: CALL      R6 0 1       ; R6(R7,...)
 28 [-]: GETUPVAL  R6 U0        ; R6 := U0
 29 [-]: GETTABLE  R7 R0 K16    ; R7 := R0["mVisitedCells"]
 30 [-]: CALL      R6 2 1       ; R6(R7)
 31 [-]: TEST      R5 0         ; if not R5 then PC := 61
 32 [-]: JMP       61           ; PC := 61
 33 [-]: GETGLOBAL R6 K17       ; R6 := 0x3d106989
 34 [-]: LOADK     R7 K18       ; R7 := "grid query starting"
 35 [-]: CALL      R6 2 1       ; R6(R7)
 36 [-]: GETGLOBAL R6 K19       ; R6 := 0x89326c93
 37 [-]: SELF      R6 R6 K20    ; R7 := R6; R6 := R6[0x9ed3b54e]
 38 [-]: MOVE      R8 R2        ; R8 := R2
 39 [-]: MOVE      R9 R3        ; R9 := R3
 40 [-]: GETGLOBAL R10 K21      ; R10 := 0x60130201
 41 [-]: LOADK     R11 100      ; R11 := 100.000000
 42 [-]: LOADK     R12 100      ; R12 := 100.000000
 43 [-]: LOADK     R13 0        ; R13 := 0.000000
 44 [-]: CALL      R10 4 2      ; R10 := R10(R11,R12,R13)
 45 [-]: LOADK     R11 4        ; R11 := 4.000000
 46 [-]: CALL      R6 6 1       ; R6(R7,R8,R9,R10,R11)
 47 [-]: GETGLOBAL R6 K19       ; R6 := 0x89326c93
 48 [-]: SELF      R6 R6 K20    ; R7 := R6; R6 := R6[0x9ed3b54e]
 49 [-]: GETTABLE  R8 R0 K14    ; R8 := R0["mGrid"]
 50 [-]: SELF      R8 R8 K22    ; R9 := R8; R8 := R8[0x587a454c]
 51 [-]: MOVE      R10 R2       ; R10 := R2
 52 [-]: CALL      R8 3 2       ; R8 := R8(R9,R10)
 53 [-]: LOADK     R9 1         ; R9 := 1.000000
 54 [-]: GETGLOBAL R10 K21      ; R10 := 0x60130201
 55 [-]: LOADK     R11 200      ; R11 := 200.000000
 56 [-]: LOADK     R12 0        ; R12 := 0.000000
 57 [-]: LOADK     R13 0        ; R13 := 0.000000
 58 [-]: CALL      R10 4 2      ; R10 := R10(R11,R12,R13)
 59 [-]: LOADK     R11 4        ; R11 := 4.000000
 60 [-]: CALL      R6 6 1       ; R6(R7,R8,R9,R10,R11)
 61 [-]: GETTABLE  R6 R0 K6     ; R6 := R0["mResultsQueue"]
 62 [-]: RETURN    R6 2         ; return R6
 63 [-]: RETURN    R0 1         ; return 


; Function #13:
;
; Name:            
; Defined at line: 127
; #Upvalues:       1
; #Parameters:     1
; Is_vararg:       0
; Max Stack Size:  6

  1 [-]: GETTABLE  R1 R0 K0     ; R1 := R0["mActiveQuery"]
  2 [-]: TEST      R1 1         ; if R1 then PC := 5
  3 [-]: JMP       5            ; PC := 5
  4 [-]: RETURN    R0 1         ; return 
  5 [-]: GETTABLE  R1 R0 K1     ; R1 := R0["mDoDebug"]
  6 [-]: TEST      R1 0         ; if not R1 then PC := 30
  7 [-]: JMP       30           ; PC := 30
  8 [-]: GETUPVAL  R1 U0        ; R1 := U0
  9 [-]: SELF      R1 R1 K2     ; R2 := R1; R1 := R1[0x36fcc811]
 10 [-]: CALL      R1 2 1       ; R1(R2)
 11 [-]: GETUPVAL  R1 U0        ; R1 := U0
 12 [-]: SELF      R1 R1 K3     ; R2 := R1; R1 := R1[0x44575710]
 13 [-]: CALL      R1 2 1       ; R1(R2)
 14 [-]: SELF      R1 R0 K4     ; R2 := R0; R1 := R0[0xbd5e334b]
 15 [-]: CALL      R1 2 1       ; R1(R2)
 16 [-]: GETUPVAL  R1 U0        ; R1 := U0
 17 [-]: SELF      R1 R1 K5     ; R2 := R1; R1 := R1[0xf33c42c5]
 18 [-]: CALL      R1 2 1       ; R1(R2)
 19 [-]: GETUPVAL  R1 U0        ; R1 := U0
 20 [-]: SELF      R1 R1 K6     ; R2 := R1; R1 := R1[0xaef9485b]
 21 [-]: CALL      R1 2 2       ; R1 := R1(R2)
 22 [-]: MUL       R1 R1 K7     ; R1 := R1 * 1000000.000000
 23 [-]: GETGLOBAL R2 K8        ; R2 := 0x3d106989
 24 [-]: LOADK     R3 K9        ; R3 := "cell search took "
 25 [-]: MOVE      R4 R1        ; R4 := R1
 26 [-]: LOADK     R5 K10       ; R5 := "us"
 27 [-]: CONCAT    R3 R3 R5     ; R3 := R3 .. R4 .. R5
 28 [-]: CALL      R2 2 1       ; R2(R3)
 29 [-]: JMP       32           ; PC := 32
 30 [-]: SELF      R2 R0 K4     ; R3 := R0; R2 := R0[0xbd5e334b]
 31 [-]: CALL      R2 2 1       ; R2(R3)
 32 [-]: RETURN    R0 1         ; return 


; Function #14:
;
; Name:            
; Defined at line: 144
; #Upvalues:       1
; #Parameters:     1
; Is_vararg:       0
; Max Stack Size:  46

  1 [-]: GETTABLE  R1 R0 K0     ; R1 := R0["mNextCellList"]
  2 [-]: SELF      R2 R1 K1     ; R3 := R1; R2 := R1[0xc9c8bcdc]
  3 [-]: CALL      R2 2 2       ; R2 := R2(R3)
  4 [-]: GETTABLE  R3 R0 K2     ; R3 := R0["mVisitedCells"]
  5 [-]: SETTABLE  R3 R2 K3     ; R3[R2] := true
  6 [-]: GETTABLE  R4 R0 K4     ; R4 := R0["mGrid"]
  7 [-]: GETTABLE  R5 R0 K5     ; R5 := R0["mPosition"]
  8 [-]: LOADNIL   R6 R11       ; R6 := R7 := R8 := R9 := R10 := R11 := nil
  9 [-]: GETTABLE  R12 R0 K6    ; R12 := R0["mRange"]
 10 [-]: MUL       R13 R12 R12  ; R13 := R12 * R12
 11 [-]: GETTABLE  R14 R0 K4    ; R14 := R0["mGrid"]
 12 [-]: GETTABLE  R14 R14 K7   ; R14 := R14["mCellWidth"]
 13 [-]: MUL       R14 R14 K8   ; R14 := R14 * 0.500000
 14 [-]: ADD       R15 R14 R12  ; R15 := R14 + R12
 15 [-]: UNM       R16 R15      ; R16 := ^ R15
 16 [-]: GETTABLE  R17 R4 K9    ; R17 := R4["mFullCellCount"]
 17 [-]: MUL       R18 R17 R17  ; R18 := R17 * R17
 18 [-]: GETTABLE  R19 R0 K10   ; R19 := R0["mQueryType"]
 19 [-]: GETUPVAL  R20 U0       ; R20 := U0
 20 [-]: GETTABLE  R20 R20 K11  ; R20 := R20["RESOURCE"]
 21 [-]: EQ        0 R19 R20    ; if R19 ~= R20 then PC := 153
 22 [-]: JMP       153          ; PC := 153
 23 [-]: TEST      R2 0         ; if not R2 then PC := 314
 24 [-]: JMP       314          ; PC := 314
 25 [-]: GETTABLE  R20 R4 R2    ; R20 := R4[R2]
 26 [-]: TEST      R20 0        ; if not R20 then PC := 35
 27 [-]: JMP       35           ; PC := 35
 28 [-]: GETTABLE  R21 R20 K12  ; R21 := R20["mCenter"]
 29 [-]: GETTABLE  R9 R21 K13   ; R9 := R21["x"]
 30 [-]: GETTABLE  R21 R20 K12  ; R21 := R20["mCenter"]
 31 [-]: GETTABLE  R10 R21 K14  ; R10 := R21["y"]
 32 [-]: GETTABLE  R21 R20 K12  ; R21 := R20["mCenter"]
 33 [-]: GETTABLE  R11 R21 K15  ; R11 := R21["z"]
 34 [-]: JMP       41           ; PC := 41
 35 [-]: SELF      R21 R4 K16   ; R22 := R4; R21 := R4[0x3280b40e]
 36 [-]: MOVE      R23 R2       ; R23 := R2
 37 [-]: CALL      R21 3 4      ; R21,R22,R23 := R21(R22,R23)
 38 [-]: MOVE      R11 R23      ; R11 := R23
 39 [-]: MOVE      R10 R22      ; R10 := R22
 40 [-]: MOVE      R9 R21       ; R9 := R21
 41 [-]: GETTABLE  R21 R5 K13   ; R21 := R5["x"]
 42 [-]: SUB       R6 R21 R9    ; R6 := R21 - R9
 43 [-]: GETTABLE  R21 R5 K14   ; R21 := R5["y"]
 44 [-]: SUB       R7 R21 R10   ; R7 := R21 - R10
 45 [-]: GETTABLE  R21 R5 K15   ; R21 := R5["z"]
 46 [-]: SUB       R8 R21 R11   ; R8 := R21 - R11
 47 [-]: LE        0 R6 R15     ; if R6 > R15 then PC := 148
 48 [-]: JMP       148          ; PC := 148
 49 [-]: LE        0 R16 R6     ; if R16 > R6 then PC := 148
 50 [-]: JMP       148          ; PC := 148
 51 [-]: LE        0 R7 R15     ; if R7 > R15 then PC := 148
 52 [-]: JMP       148          ; PC := 148
 53 [-]: LE        0 R16 R7     ; if R16 > R7 then PC := 148
 54 [-]: JMP       148          ; PC := 148
 55 [-]: LE        0 R8 R15     ; if R8 > R15 then PC := 148
 56 [-]: JMP       148          ; PC := 148
 57 [-]: LE        0 R16 R8     ; if R16 > R8 then PC := 148
 58 [-]: JMP       148          ; PC := 148
 59 [-]: TEST      R20 0        ; if not R20 then PC := 99
 60 [-]: JMP       99           ; PC := 99
 61 [-]: LOADK     R21 1        ; R21 := 1.000000
 62 [-]: GETTABLE  R22 R20 K17  ; R22 := R20["resourceEntries"]
 63 [-]: LEN       R22 R22      ; R22 := # R22
 64 [-]: LOADK     R23 1        ; R23 := 1.000000
 65 [-]: MOVE      R24 R22      ; R24 := R22
 66 [-]: LOADK     R25 1        ; R25 := 1.000000
 67 [-]: FORPREP   R23 98       ; R23 -= R25; PC := 98
 68 [-]: GETTABLE  R27 R20 K17  ; R27 := R20["resourceEntries"]
 69 [-]: GETTABLE  R27 R27 R26  ; R27 := R27[R26]
 70 [-]: GETTABLE  R28 R4 K18   ; R28 := R4["mValidateEntity"]
 71 [-]: TEST      R28 0        ; if not R28 then PC := 81
 72 [-]: JMP       81           ; PC := 81
 73 [-]: GETTABLE  R28 R4 K19   ; R28 := R4[0xabbb6050]
 74 [-]: MOVE      R29 R27      ; R29 := R27
 75 [-]: CALL      R28 2 2      ; R28 := R28(R29)
 76 [-]: TEST      R28 1        ; if R28 then PC := 81
 77 [-]: JMP       81           ; PC := 81
 78 [-]: GETTABLE  R28 R20 K17  ; R28 := R20["resourceEntries"]
 79 [-]: SETTABLE  R28 R26 K20  ; R28[R26] := nil
 80 [-]: JMP       98           ; PC := 98
 81 [-]: GETGLOBAL R28 K21      ; R28 := 0xc0da2b81
 82 [-]: MOVE      R29 R5       ; R29 := R5
 83 [-]: GETTABLE  R30 R27 K22  ; R30 := R27["pos"]
 84 [-]: CALL      R28 3 2      ; R28 := R28(R29,R30)
 85 [-]: LE        0 R28 R13    ; if R28 > R13 then PC := 91
 86 [-]: JMP       91           ; PC := 91
 87 [-]: GETTABLE  R28 R0 K23   ; R28 := R0["mResultsQueue"]
 88 [-]: SELF      R28 R28 K24  ; R29 := R28; R28 := R28[0xdd2c9860]
 89 [-]: MOVE      R30 R27      ; R30 := R27
 90 [-]: CALL      R28 3 1      ; R28(R29,R30)
 91 [-]: EQ        1 R21 R26    ; if R21 == R26 then PC := 97
 92 [-]: JMP       97           ; PC := 97
 93 [-]: GETTABLE  R28 R20 K17  ; R28 := R20["resourceEntries"]
 94 [-]: SETTABLE  R28 R26 K20  ; R28[R26] := nil
 95 [-]: GETTABLE  R28 R20 K17  ; R28 := R20["resourceEntries"]
 96 [-]: SETTABLE  R28 R21 R27  ; R28[R21] := R27
 97 [-]: ADD       R21 R21 K25  ; R21 := R21 + 1.000000
 98 [-]: FORLOOP   R23 68       ; R23 += R25; if R23 <= R24 then begin PC := 68; R26 := R23 end
 99 [-]: LOADNIL   R28 R28      ; R28 := nil
100 [-]: ADD       R28 R2 K25   ; R28 := R2 + 1.000000
101 [-]: GETTABLE  R29 R3 R28   ; R29 := R3[R28]
102 [-]: TEST      R29 1        ; if R29 then PC := 108
103 [-]: JMP       108          ; PC := 108
104 [-]: SELF      R29 R1 K24   ; R30 := R1; R29 := R1[0xdd2c9860]
105 [-]: MOVE      R31 R28      ; R31 := R28
106 [-]: CALL      R29 3 1      ; R29(R30,R31)
107 [-]: SETTABLE  R3 R28 K3    ; R3[R28] := true
108 [-]: ADD       R28 R2 R18   ; R28 := R2 + R18
109 [-]: GETTABLE  R29 R3 R28   ; R29 := R3[R28]
110 [-]: TEST      R29 1        ; if R29 then PC := 116
111 [-]: JMP       116          ; PC := 116
112 [-]: SELF      R29 R1 K24   ; R30 := R1; R29 := R1[0xdd2c9860]
113 [-]: MOVE      R31 R28      ; R31 := R28
114 [-]: CALL      R29 3 1      ; R29(R30,R31)
115 [-]: SETTABLE  R3 R28 K3    ; R3[R28] := true
116 [-]: SUB       R28 R2 R18   ; R28 := R2 - R18
117 [-]: GETTABLE  R29 R3 R28   ; R29 := R3[R28]
118 [-]: TEST      R29 1        ; if R29 then PC := 124
119 [-]: JMP       124          ; PC := 124
120 [-]: SELF      R29 R1 K24   ; R30 := R1; R29 := R1[0xdd2c9860]
121 [-]: MOVE      R31 R28      ; R31 := R28
122 [-]: CALL      R29 3 1      ; R29(R30,R31)
123 [-]: SETTABLE  R3 R28 K3    ; R3[R28] := true
124 [-]: SUB       R28 R2 K25   ; R28 := R2 - 1.000000
125 [-]: GETTABLE  R29 R3 R28   ; R29 := R3[R28]
126 [-]: TEST      R29 1        ; if R29 then PC := 132
127 [-]: JMP       132          ; PC := 132
128 [-]: SELF      R29 R1 K24   ; R30 := R1; R29 := R1[0xdd2c9860]
129 [-]: MOVE      R31 R28      ; R31 := R28
130 [-]: CALL      R29 3 1      ; R29(R30,R31)
131 [-]: SETTABLE  R3 R28 K3    ; R3[R28] := true
132 [-]: ADD       R28 R2 R17   ; R28 := R2 + R17
133 [-]: GETTABLE  R29 R3 R28   ; R29 := R3[R28]
134 [-]: TEST      R29 1        ; if R29 then PC := 140
135 [-]: JMP       140          ; PC := 140
136 [-]: SELF      R29 R1 K24   ; R30 := R1; R29 := R1[0xdd2c9860]
137 [-]: MOVE      R31 R28      ; R31 := R28
138 [-]: CALL      R29 3 1      ; R29(R30,R31)
139 [-]: SETTABLE  R3 R28 K3    ; R3[R28] := true
140 [-]: SUB       R28 R2 R17   ; R28 := R2 - R17
141 [-]: GETTABLE  R29 R3 R28   ; R29 := R3[R28]
142 [-]: TEST      R29 1        ; if R29 then PC := 148
143 [-]: JMP       148          ; PC := 148
144 [-]: SELF      R29 R1 K24   ; R30 := R1; R29 := R1[0xdd2c9860]
145 [-]: MOVE      R31 R28      ; R31 := R28
146 [-]: CALL      R29 3 1      ; R29(R30,R31)
147 [-]: SETTABLE  R3 R28 K3    ; R3[R28] := true
148 [-]: SELF      R29 R1 K1    ; R30 := R1; R29 := R1[0xc9c8bcdc]
149 [-]: CALL      R29 2 2      ; R29 := R29(R30)
150 [-]: MOVE      R2 R29       ; R2 := R29
151 [-]: JMP       23           ; PC := 23
152 [-]: JMP       314          ; PC := 314
153 [-]: GETUPVAL  R29 U0       ; R29 := U0
154 [-]: GETTABLE  R29 R29 K26  ; R29 := R29["CANDIDATE"]
155 [-]: EQ        0 R19 R29    ; if R19 ~= R29 then PC := 314
156 [-]: JMP       314          ; PC := 314
157 [-]: TEST      R2 0         ; if not R2 then PC := 314
158 [-]: JMP       314          ; PC := 314
159 [-]: GETTABLE  R29 R4 R2    ; R29 := R4[R2]
160 [-]: TEST      R29 0        ; if not R29 then PC := 169
161 [-]: JMP       169          ; PC := 169
162 [-]: GETTABLE  R30 R29 K12  ; R30 := R29["mCenter"]
163 [-]: GETTABLE  R9 R30 K13   ; R9 := R30["x"]
164 [-]: GETTABLE  R30 R29 K12  ; R30 := R29["mCenter"]
165 [-]: GETTABLE  R10 R30 K14  ; R10 := R30["y"]
166 [-]: GETTABLE  R30 R29 K12  ; R30 := R29["mCenter"]
167 [-]: GETTABLE  R11 R30 K15  ; R11 := R30["z"]
168 [-]: JMP       175          ; PC := 175
169 [-]: SELF      R30 R4 K16   ; R31 := R4; R30 := R4[0x3280b40e]
170 [-]: MOVE      R32 R2       ; R32 := R2
171 [-]: CALL      R30 3 4      ; R30,R31,R32 := R30(R31,R32)
172 [-]: MOVE      R11 R32      ; R11 := R32
173 [-]: MOVE      R10 R31      ; R10 := R31
174 [-]: MOVE      R9 R30       ; R9 := R30
175 [-]: GETTABLE  R30 R5 K13   ; R30 := R5["x"]
176 [-]: SUB       R6 R30 R9    ; R6 := R30 - R9
177 [-]: GETTABLE  R30 R5 K14   ; R30 := R5["y"]
178 [-]: SUB       R7 R30 R10   ; R7 := R30 - R10
179 [-]: GETTABLE  R30 R5 K15   ; R30 := R5["z"]
180 [-]: SUB       R8 R30 R11   ; R8 := R30 - R11
181 [-]: LE        0 R6 R15     ; if R6 > R15 then PC := 310
182 [-]: JMP       310          ; PC := 310
183 [-]: LE        0 R16 R6     ; if R16 > R6 then PC := 310
184 [-]: JMP       310          ; PC := 310
185 [-]: LE        0 R7 R15     ; if R7 > R15 then PC := 310
186 [-]: JMP       310          ; PC := 310
187 [-]: LE        0 R16 R7     ; if R16 > R7 then PC := 310
188 [-]: JMP       310          ; PC := 310
189 [-]: LE        0 R8 R15     ; if R8 > R15 then PC := 310
190 [-]: JMP       310          ; PC := 310
191 [-]: LE        0 R16 R8     ; if R16 > R8 then PC := 310
192 [-]: JMP       310          ; PC := 310
193 [-]: TEST      R29 0        ; if not R29 then PC := 261
194 [-]: JMP       261          ; PC := 261
195 [-]: GETTABLE  R30 R0 K27   ; R30 := R0["mRemoveResults"]
196 [-]: TEST      R30 0        ; if not R30 then PC := 244
197 [-]: JMP       244          ; PC := 244
198 [-]: LOADK     R30 1        ; R30 := 1.000000
199 [-]: GETTABLE  R31 R29 K28  ; R31 := R29["candidates"]
200 [-]: LEN       R31 R31      ; R31 := # R31
201 [-]: LOADK     R32 1        ; R32 := 1.000000
202 [-]: MOVE      R33 R31      ; R33 := R31
203 [-]: LOADK     R34 1        ; R34 := 1.000000
204 [-]: FORPREP   R32 242      ; R32 -= R34; PC := 242
205 [-]: GETTABLE  R36 R29 K28  ; R36 := R29["candidates"]
206 [-]: GETTABLE  R36 R36 R35  ; R36 := R36[R35]
207 [-]: GETGLOBAL R37 K29      ; R37 := 0x7b998233
208 [-]: MOVE      R38 R36      ; R38 := R36
209 [-]: CALL      R37 2 2      ; R37 := R37(R38)
210 [-]: TEST      R37 0        ; if not R37 then PC := 221
211 [-]: JMP       221          ; PC := 221
212 [-]: GETTABLE  R37 R0 K30   ; R37 := R0["mDebugProcessing"]
213 [-]: TEST      R37 0        ; if not R37 then PC := 218
214 [-]: JMP       218          ; PC := 218
215 [-]: GETGLOBAL R37 K31      ; R37 := 0x3d106989
216 [-]: LOADK     R38 K32      ; R38 := "candidate disappeared"
217 [-]: CALL      R37 2 1      ; R37(R38)
218 [-]: GETTABLE  R37 R29 K28  ; R37 := R29["candidates"]
219 [-]: SETTABLE  R37 R35 K20  ; R37[R35] := nil
220 [-]: JMP       242          ; PC := 242
221 [-]: GETGLOBAL R37 K21      ; R37 := 0xc0da2b81
222 [-]: MOVE      R38 R5       ; R38 := R5
223 [-]: SELF      R39 R36 K33  ; R40 := R36; R39 := R36[0xd1586535]
224 [-]: CALL      R39 2 0      ; R39,... := R39(R40)
225 [-]: CALL      R37 0 2      ; R37 := R37(R38,...)
226 [-]: LE        0 R37 R13    ; if R37 > R13 then PC := 235
227 [-]: JMP       235          ; PC := 235
228 [-]: GETTABLE  R37 R0 K23   ; R37 := R0["mResultsQueue"]
229 [-]: SELF      R37 R37 K24  ; R38 := R37; R37 := R37[0xdd2c9860]
230 [-]: MOVE      R39 R36      ; R39 := R36
231 [-]: CALL      R37 3 1      ; R37(R38,R39)
232 [-]: GETTABLE  R37 R29 K28  ; R37 := R29["candidates"]
233 [-]: SETTABLE  R37 R35 K20  ; R37[R35] := nil
234 [-]: JMP       242          ; PC := 242
235 [-]: EQ        1 R30 R35    ; if R30 == R35 then PC := 241
236 [-]: JMP       241          ; PC := 241
237 [-]: GETTABLE  R37 R29 K28  ; R37 := R29["candidates"]
238 [-]: SETTABLE  R37 R35 K20  ; R37[R35] := nil
239 [-]: GETTABLE  R37 R29 K28  ; R37 := R29["candidates"]
240 [-]: SETTABLE  R37 R30 R36  ; R37[R30] := R36
241 [-]: ADD       R30 R30 K25  ; R30 := R30 + 1.000000
242 [-]: FORLOOP   R32 205      ; R32 += R34; if R32 <= R33 then begin PC := 205; R35 := R32 end
243 [-]: JMP       261          ; PC := 261
244 [-]: GETGLOBAL R37 K34      ; R37 := 0xcfc01047
245 [-]: GETTABLE  R38 R29 K28  ; R38 := R29["candidates"]
246 [-]: CALL      R37 2 4      ; R37,R38,R39 := R37(R38)
247 [-]: JMP       259          ; PC := 259
248 [-]: GETGLOBAL R42 K21      ; R42 := 0xc0da2b81
249 [-]: MOVE      R43 R5       ; R43 := R5
250 [-]: SELF      R44 R41 K33  ; R45 := R41; R44 := R41[0xd1586535]
251 [-]: CALL      R44 2 0      ; R44,... := R44(R45)
252 [-]: CALL      R42 0 2      ; R42 := R42(R43,...)
253 [-]: LE        0 R42 R13    ; if R42 > R13 then PC := 259
254 [-]: JMP       259          ; PC := 259
255 [-]: GETTABLE  R42 R0 K23   ; R42 := R0["mResultsQueue"]
256 [-]: SELF      R42 R42 K24  ; R43 := R42; R42 := R42[0xdd2c9860]
257 [-]: MOVE      R44 R41      ; R44 := R41
258 [-]: CALL      R42 3 1      ; R42(R43,R44)
259 [-]: TFORLOOP  R37 2        ; R40,R41 :=  R37(R38,R39); if R40 ~= nil then begin PC = 248; R39 := R40 end
260 [-]: JMP       248          ; PC := 248
261 [-]: LOADNIL   R42 R42      ; R42 := nil
262 [-]: ADD       R42 R2 K25   ; R42 := R2 + 1.000000
263 [-]: GETTABLE  R43 R3 R42   ; R43 := R3[R42]
264 [-]: TEST      R43 1        ; if R43 then PC := 270
265 [-]: JMP       270          ; PC := 270
266 [-]: SELF      R43 R1 K24   ; R44 := R1; R43 := R1[0xdd2c9860]
267 [-]: MOVE      R45 R42      ; R45 := R42
268 [-]: CALL      R43 3 1      ; R43(R44,R45)
269 [-]: SETTABLE  R3 R42 K3    ; R3[R42] := true
270 [-]: ADD       R42 R2 R18   ; R42 := R2 + R18
271 [-]: GETTABLE  R43 R3 R42   ; R43 := R3[R42]
272 [-]: TEST      R43 1        ; if R43 then PC := 278
273 [-]: JMP       278          ; PC := 278
274 [-]: SELF      R43 R1 K24   ; R44 := R1; R43 := R1[0xdd2c9860]
275 [-]: MOVE      R45 R42      ; R45 := R42
276 [-]: CALL      R43 3 1      ; R43(R44,R45)
277 [-]: SETTABLE  R3 R42 K3    ; R3[R42] := true
278 [-]: SUB       R42 R2 R18   ; R42 := R2 - R18
279 [-]: GETTABLE  R43 R3 R42   ; R43 := R3[R42]
280 [-]: TEST      R43 1        ; if R43 then PC := 286
281 [-]: JMP       286          ; PC := 286
282 [-]: SELF      R43 R1 K24   ; R44 := R1; R43 := R1[0xdd2c9860]
283 [-]: MOVE      R45 R42      ; R45 := R42
284 [-]: CALL      R43 3 1      ; R43(R44,R45)
285 [-]: SETTABLE  R3 R42 K3    ; R3[R42] := true
286 [-]: SUB       R42 R2 K25   ; R42 := R2 - 1.000000
287 [-]: GETTABLE  R43 R3 R42   ; R43 := R3[R42]
288 [-]: TEST      R43 1        ; if R43 then PC := 294
289 [-]: JMP       294          ; PC := 294
290 [-]: SELF      R43 R1 K24   ; R44 := R1; R43 := R1[0xdd2c9860]
291 [-]: MOVE      R45 R42      ; R45 := R42
292 [-]: CALL      R43 3 1      ; R43(R44,R45)
293 [-]: SETTABLE  R3 R42 K3    ; R3[R42] := true
294 [-]: ADD       R42 R2 R17   ; R42 := R2 + R17
295 [-]: GETTABLE  R43 R3 R42   ; R43 := R3[R42]
296 [-]: TEST      R43 1        ; if R43 then PC := 302
297 [-]: JMP       302          ; PC := 302
298 [-]: SELF      R43 R1 K24   ; R44 := R1; R43 := R1[0xdd2c9860]
299 [-]: MOVE      R45 R42      ; R45 := R42
300 [-]: CALL      R43 3 1      ; R43(R44,R45)
301 [-]: SETTABLE  R3 R42 K3    ; R3[R42] := true
302 [-]: SUB       R42 R2 R17   ; R42 := R2 - R17
303 [-]: GETTABLE  R43 R3 R42   ; R43 := R3[R42]
304 [-]: TEST      R43 1        ; if R43 then PC := 310
305 [-]: JMP       310          ; PC := 310
306 [-]: SELF      R43 R1 K24   ; R44 := R1; R43 := R1[0xdd2c9860]
307 [-]: MOVE      R45 R42      ; R45 := R42
308 [-]: CALL      R43 3 1      ; R43(R44,R45)
309 [-]: SETTABLE  R3 R42 K3    ; R3[R42] := true
310 [-]: SELF      R43 R1 K1    ; R44 := R1; R43 := R1[0xc9c8bcdc]
311 [-]: CALL      R43 2 2      ; R43 := R43(R44)
312 [-]: MOVE      R2 R43       ; R2 := R43
313 [-]: JMP       157          ; PC := 157
314 [-]: SETTABLE  R0 K35 K36   ; R0["mActiveQuery"] := false
315 [-]: RETURN    R0 1         ; return 


; Function #15:
;
; Name:            
; Defined at line: 352
; #Upvalues:       2
; #Parameters:     2
; Is_vararg:       0
; Max Stack Size:  5

  1 [-]: GETGLOBAL R2 K0        ; R2 := 0x2296a8fd
  2 [-]: NEWTABLE  R3 0 0       ; R3 := {}
  3 [-]: GETUPVAL  R4 U0        ; R4 := U0
  4 [-]: CALL      R2 3 2       ; R2 := R2(R3,R4)
  5 [-]: SETTABLE  R2 K1 R0     ; R2["mGrid"] := R0
  6 [-]: GETGLOBAL R3 K3        ; R3 := 0xa421af95
  7 [-]: CALL      R3 1 2       ; R3 := R3()
  8 [-]: SETTABLE  R2 K2 R3     ; R2["mPosition"] := R3
  9 [-]: TESTSET   R3 R1 1      ; if R1 then PC := 14 else R3 := R1
 10 [-]: JMP       14           ; PC := 14
 11 [-]: GETUPVAL  R3 U1        ; R3 := U1
 12 [-]: GETTABLE  R3 R3 K5     ; R3 := R3[0x7d4d5d68]
 13 [-]: CALL      R3 1 2       ; R3 := R3()
 14 [-]: SETTABLE  R2 K4 R3     ; R2["mResultsQueue"] := R3
 15 [-]: GETUPVAL  R3 U1        ; R3 := U1
 16 [-]: GETTABLE  R3 R3 K5     ; R3 := R3[0x7d4d5d68]
 17 [-]: CALL      R3 1 2       ; R3 := R3()
 18 [-]: SETTABLE  R2 K6 R3     ; R2["mNextCellList"] := R3
 19 [-]: NEWTABLE  R3 0 0       ; R3 := {}
 20 [-]: SETTABLE  R2 K7 R3     ; R2["mVisitedCells"] := R3
 21 [-]: GETGLOBAL R3 K3        ; R3 := 0xa421af95
 22 [-]: CALL      R3 1 2       ; R3 := R3()
 23 [-]: SETTABLE  R2 K8 R3     ; R2["mRelPos"] := R3
 24 [-]: RETURN    R2 2         ; return R2
 25 [-]: RETURN    R0 1         ; return 


; Function #16:
;
; Name:            
; Defined at line: 367
; #Upvalues:       0
; #Parameters:     2
; Is_vararg:       0
; Max Stack Size:  5

  1 [-]: GETTABLE  R2 R0 K0     ; R2 := R0["mGrid"]
  2 [-]: GETTABLE  R2 R2 R1     ; R2 := R2[R1]
  3 [-]: TEST      R2 0         ; if not R2 then PC := 15
  4 [-]: JMP       15           ; PC := 15
  5 [-]: GETTABLE  R2 R0 K1     ; R2 := R0["mVisitedCells"]
  6 [-]: GETTABLE  R2 R2 R1     ; R2 := R2[R1]
  7 [-]: TEST      R2 1         ; if R2 then PC := 15
  8 [-]: JMP       15           ; PC := 15
  9 [-]: GETTABLE  R2 R0 K2     ; R2 := R0["mNextCellList"]
 10 [-]: SELF      R2 R2 K3     ; R3 := R2; R2 := R2[0xdd2c9860]
 11 [-]: MOVE      R4 R1        ; R4 := R1
 12 [-]: CALL      R2 3 1       ; R2(R3,R4)
 13 [-]: GETTABLE  R2 R0 K1     ; R2 := R0["mVisitedCells"]
 14 [-]: SETTABLE  R2 R1 K4     ; R2[R1] := true
 15 [-]: RETURN    R0 1         ; return 


; Function #17:
;
; Name:            
; Defined at line: 374
; #Upvalues:       1
; #Parameters:     1
; Is_vararg:       0
; Max Stack Size:  16

  1 [-]: GETTABLE  R1 R0 K0     ; R1 := R0["mNextCellList"]
  2 [-]: SELF      R1 R1 K1     ; R2 := R1; R1 := R1[0xc9c8bcdc]
  3 [-]: CALL      R1 2 2       ; R1 := R1(R2)
  4 [-]: TEST      R1 1         ; if R1 then PC := 19
  5 [-]: JMP       19           ; PC := 19
  6 [-]: SETTABLE  R0 K2 K3     ; R0["mActiveQuery"] := false
  7 [-]: GETTABLE  R2 R0 K4     ; R2 := R0["mDoDebug"]
  8 [-]: TEST      R2 0         ; if not R2 then PC := 18
  9 [-]: JMP       18           ; PC := 18
 10 [-]: GETGLOBAL R2 K5        ; R2 := 0x3d106989
 11 [-]: LOADK     R3 K6        ; R3 := "active cell query for player "
 12 [-]: GETTABLE  R4 R0 K7     ; R4 := R0["mPlayer"]
 13 [-]: SELF      R4 R4 K8     ; R5 := R4; R4 := R4[0x5ca33548]
 14 [-]: CALL      R4 2 2       ; R4 := R4(R5)
 15 [-]: LOADK     R5 K9        ; R5 := "finished."
 16 [-]: CONCAT    R3 R3 R5     ; R3 := R3 .. R4 .. R5
 17 [-]: CALL      R2 2 1       ; R2(R3)
 18 [-]: RETURN    R0 1         ; return 
 19 [-]: GETTABLE  R2 R0 K10    ; R2 := R0["mGrid"]
 20 [-]: SELF      R3 R2 K11    ; R4 := R2; R3 := R2[0xcabdfd0e]
 21 [-]: MOVE      R5 R1        ; R5 := R1
 22 [-]: CALL      R3 3 2       ; R3 := R3(R4,R5)
 23 [-]: GETTABLE  R4 R0 K12    ; R4 := R0["mVisitedCells"]
 24 [-]: SETTABLE  R4 R1 K13    ; R4[R1] := true
 25 [-]: LOADNIL   R4 R4        ; R4 := nil
 26 [-]: TEST      R3 0         ; if not R3 then PC := 30
 27 [-]: JMP       30           ; PC := 30
 28 [-]: GETTABLE  R4 R3 K14    ; R4 := R3["mCenter"]
 29 [-]: JMP       34           ; PC := 34
 30 [-]: SELF      R5 R2 K15    ; R6 := R2; R5 := R2[0xea7c08de]
 31 [-]: MOVE      R7 R1        ; R7 := R1
 32 [-]: CALL      R5 3 2       ; R5 := R5(R6,R7)
 33 [-]: MOVE      R4 R5        ; R4 := R5
 34 [-]: GETTABLE  R5 R0 K10    ; R5 := R0["mGrid"]
 35 [-]: GETTABLE  R5 R5 K16    ; R5 := R5["mCellWidth"]
 36 [-]: MUL       R5 R5 K17    ; R5 := R5 * 0.500000
 37 [-]: GETTABLE  R6 R0 K18    ; R6 := R0["mRange"]
 38 [-]: GETTABLE  R7 R0 K19    ; R7 := R0["mLastPos"]
 39 [-]: SUB       R8 R7 R4     ; R8 := R7 - R4
 40 [-]: GETTABLE  R9 R8 K20    ; R9 := R8["x"]
 41 [-]: ADD       R10 R5 R6    ; R10 := R5 + R6
 42 [-]: LE        0 R9 R10     ; if R9 > R10 then PC := 99
 43 [-]: JMP       99           ; PC := 99
 44 [-]: GETTABLE  R9 R8 K20    ; R9 := R8["x"]
 45 [-]: UNM       R10 R5       ; R10 := ^ R5
 46 [-]: SUB       R10 R10 R6   ; R10 := R10 - R6
 47 [-]: LE        0 R10 R9     ; if R10 > R9 then PC := 99
 48 [-]: JMP       99           ; PC := 99
 49 [-]: GETTABLE  R9 R8 K21    ; R9 := R8["y"]
 50 [-]: ADD       R10 R5 R6    ; R10 := R5 + R6
 51 [-]: LE        0 R9 R10     ; if R9 > R10 then PC := 99
 52 [-]: JMP       99           ; PC := 99
 53 [-]: GETTABLE  R9 R8 K21    ; R9 := R8["y"]
 54 [-]: UNM       R10 R5       ; R10 := ^ R5
 55 [-]: SUB       R10 R10 R6   ; R10 := R10 - R6
 56 [-]: LE        0 R10 R9     ; if R10 > R9 then PC := 99
 57 [-]: JMP       99           ; PC := 99
 58 [-]: GETTABLE  R9 R8 K22    ; R9 := R8["z"]
 59 [-]: ADD       R10 R5 R6    ; R10 := R5 + R6
 60 [-]: LE        0 R9 R10     ; if R9 > R10 then PC := 99
 61 [-]: JMP       99           ; PC := 99
 62 [-]: GETTABLE  R9 R8 K22    ; R9 := R8["z"]
 63 [-]: UNM       R10 R5       ; R10 := ^ R5
 64 [-]: SUB       R10 R10 R6   ; R10 := R10 - R6
 65 [-]: LE        0 R10 R9     ; if R10 > R9 then PC := 99
 66 [-]: JMP       99           ; PC := 99
 67 [-]: GETTABLE  R9 R0 K23    ; R9 := R0["mActiveCellResults"]
 68 [-]: SELF      R9 R9 K24    ; R10 := R9; R9 := R9[0xdd2c9860]
 69 [-]: MOVE      R11 R1       ; R11 := R1
 70 [-]: CALL      R9 3 1       ; R9(R10,R11)
 71 [-]: GETTABLE  R9 R0 K4     ; R9 := R0["mDoDebug"]
 72 [-]: TEST      R9 0         ; if not R9 then PC := 127
 73 [-]: JMP       127          ; PC := 127
 74 [-]: GETUPVAL  R9 U0        ; R9 := U0
 75 [-]: GETGLOBAL R10 K25      ; R10 := 0xa421af95
 76 [-]: GETTABLE  R11 R4 K20   ; R11 := R4["x"]
 77 [-]: SUB       R11 R11 R5   ; R11 := R11 - R5
 78 [-]: GETTABLE  R12 R4 K21   ; R12 := R4["y"]
 79 [-]: SUB       R12 R12 R5   ; R12 := R12 - R5
 80 [-]: GETTABLE  R13 R4 K22   ; R13 := R4["z"]
 81 [-]: SUB       R13 R13 R5   ; R13 := R13 - R5
 82 [-]: CALL      R10 4 2      ; R10 := R10(R11,R12,R13)
 83 [-]: GETGLOBAL R11 K25      ; R11 := 0xa421af95
 84 [-]: GETTABLE  R12 R4 K20   ; R12 := R4["x"]
 85 [-]: ADD       R12 R12 R5   ; R12 := R12 + R5
 86 [-]: GETTABLE  R13 R4 K21   ; R13 := R4["y"]
 87 [-]: ADD       R13 R13 R5   ; R13 := R13 + R5
 88 [-]: GETTABLE  R14 R4 K22   ; R14 := R4["z"]
 89 [-]: ADD       R14 R14 R5   ; R14 := R14 + R5
 90 [-]: CALL      R11 4 2      ; R11 := R11(R12,R13,R14)
 91 [-]: GETGLOBAL R12 K26      ; R12 := 0x60130201
 92 [-]: LOADK     R13 0        ; R13 := 0.000000
 93 [-]: LOADK     R14 100      ; R14 := 100.000000
 94 [-]: LOADK     R15 100      ; R15 := 100.000000
 95 [-]: CALL      R12 4 2      ; R12 := R12(R13,R14,R15)
 96 [-]: LOADK     R13 4        ; R13 := 4.000000
 97 [-]: CALL      R9 5 1       ; R9(R10,R11,R12,R13)
 98 [-]: JMP       127          ; PC := 127
 99 [-]: GETTABLE  R9 R0 K4     ; R9 := R0["mDoDebug"]
100 [-]: TEST      R9 0         ; if not R9 then PC := 126
101 [-]: JMP       126          ; PC := 126
102 [-]: GETUPVAL  R9 U0        ; R9 := U0
103 [-]: GETGLOBAL R10 K25      ; R10 := 0xa421af95
104 [-]: GETTABLE  R11 R4 K20   ; R11 := R4["x"]
105 [-]: SUB       R11 R11 R5   ; R11 := R11 - R5
106 [-]: GETTABLE  R12 R4 K21   ; R12 := R4["y"]
107 [-]: SUB       R12 R12 R5   ; R12 := R12 - R5
108 [-]: GETTABLE  R13 R4 K22   ; R13 := R4["z"]
109 [-]: SUB       R13 R13 R5   ; R13 := R13 - R5
110 [-]: CALL      R10 4 2      ; R10 := R10(R11,R12,R13)
111 [-]: GETGLOBAL R11 K25      ; R11 := 0xa421af95
112 [-]: GETTABLE  R12 R4 K20   ; R12 := R4["x"]
113 [-]: ADD       R12 R12 R5   ; R12 := R12 + R5
114 [-]: GETTABLE  R13 R4 K21   ; R13 := R4["y"]
115 [-]: ADD       R13 R13 R5   ; R13 := R13 + R5
116 [-]: GETTABLE  R14 R4 K22   ; R14 := R4["z"]
117 [-]: ADD       R14 R14 R5   ; R14 := R14 + R5
118 [-]: CALL      R11 4 2      ; R11 := R11(R12,R13,R14)
119 [-]: GETGLOBAL R12 K26      ; R12 := 0x60130201
120 [-]: LOADK     R13 100      ; R13 := 100.000000
121 [-]: LOADK     R14 0        ; R14 := 0.000000
122 [-]: LOADK     R15 0        ; R15 := 0.000000
123 [-]: CALL      R12 4 2      ; R12 := R12(R13,R14,R15)
124 [-]: LOADK     R13 4        ; R13 := 4.000000
125 [-]: CALL      R9 5 1       ; R9(R10,R11,R12,R13)
126 [-]: RETURN    R0 1         ; return 
127 [-]: SELF      R9 R2 K27    ; R10 := R2; R9 := R2[0x54c093f8]
128 [-]: MOVE      R11 R4       ; R11 := R4
129 [-]: LOADK     R12 0        ; R12 := 0.000000
130 [-]: LOADK     R13 0        ; R13 := 0.000000
131 [-]: LOADK     R14 1        ; R14 := 1.000000
132 [-]: CALL      R9 6 2       ; R9 := R9(R10,R11,R12,R13,R14)
133 [-]: MOVE      R1 R9        ; R1 := R9
134 [-]: SELF      R9 R0 K28    ; R10 := R0; R9 := R0[0xf643a942]
135 [-]: MOVE      R11 R1       ; R11 := R1
136 [-]: CALL      R9 3 1       ; R9(R10,R11)
137 [-]: SELF      R9 R2 K27    ; R10 := R2; R9 := R2[0x54c093f8]
138 [-]: MOVE      R11 R4       ; R11 := R4
139 [-]: LOADK     R12 1        ; R12 := 1.000000
140 [-]: LOADK     R13 0        ; R13 := 0.000000
141 [-]: LOADK     R14 0        ; R14 := 0.000000
142 [-]: CALL      R9 6 2       ; R9 := R9(R10,R11,R12,R13,R14)
143 [-]: MOVE      R1 R9        ; R1 := R9
144 [-]: SELF      R9 R0 K28    ; R10 := R0; R9 := R0[0xf643a942]
145 [-]: MOVE      R11 R1       ; R11 := R1
146 [-]: CALL      R9 3 1       ; R9(R10,R11)
147 [-]: SELF      R9 R2 K27    ; R10 := R2; R9 := R2[0x54c093f8]
148 [-]: MOVE      R11 R4       ; R11 := R4
149 [-]: LOADK     R12 -1       ; R12 := -1.000000
150 [-]: LOADK     R13 0        ; R13 := 0.000000
151 [-]: LOADK     R14 0        ; R14 := 0.000000
152 [-]: CALL      R9 6 2       ; R9 := R9(R10,R11,R12,R13,R14)
153 [-]: MOVE      R1 R9        ; R1 := R9
154 [-]: SELF      R9 R0 K28    ; R10 := R0; R9 := R0[0xf643a942]
155 [-]: MOVE      R11 R1       ; R11 := R1
156 [-]: CALL      R9 3 1       ; R9(R10,R11)
157 [-]: SELF      R9 R2 K27    ; R10 := R2; R9 := R2[0x54c093f8]
158 [-]: MOVE      R11 R4       ; R11 := R4
159 [-]: LOADK     R12 0        ; R12 := 0.000000
160 [-]: LOADK     R13 0        ; R13 := 0.000000
161 [-]: LOADK     R14 -1       ; R14 := -1.000000
162 [-]: CALL      R9 6 2       ; R9 := R9(R10,R11,R12,R13,R14)
163 [-]: MOVE      R1 R9        ; R1 := R9
164 [-]: SELF      R9 R0 K28    ; R10 := R0; R9 := R0[0xf643a942]
165 [-]: MOVE      R11 R1       ; R11 := R1
166 [-]: CALL      R9 3 1       ; R9(R10,R11)
167 [-]: SELF      R9 R2 K27    ; R10 := R2; R9 := R2[0x54c093f8]
168 [-]: MOVE      R11 R4       ; R11 := R4
169 [-]: LOADK     R12 0        ; R12 := 0.000000
170 [-]: LOADK     R13 1        ; R13 := 1.000000
171 [-]: LOADK     R14 0        ; R14 := 0.000000
172 [-]: CALL      R9 6 2       ; R9 := R9(R10,R11,R12,R13,R14)
173 [-]: MOVE      R1 R9        ; R1 := R9
174 [-]: SELF      R9 R0 K28    ; R10 := R0; R9 := R0[0xf643a942]
175 [-]: MOVE      R11 R1       ; R11 := R1
176 [-]: CALL      R9 3 1       ; R9(R10,R11)
177 [-]: SELF      R9 R2 K27    ; R10 := R2; R9 := R2[0x54c093f8]
178 [-]: MOVE      R11 R4       ; R11 := R4
179 [-]: LOADK     R12 0        ; R12 := 0.000000
180 [-]: LOADK     R13 -1       ; R13 := -1.000000
181 [-]: LOADK     R14 0        ; R14 := 0.000000
182 [-]: CALL      R9 6 2       ; R9 := R9(R10,R11,R12,R13,R14)
183 [-]: MOVE      R1 R9        ; R1 := R9
184 [-]: SELF      R9 R0 K28    ; R10 := R0; R9 := R0[0xf643a942]
185 [-]: MOVE      R11 R1       ; R11 := R1
186 [-]: CALL      R9 3 1       ; R9(R10,R11)
187 [-]: RETURN    R0 1         ; return 


; Function #18:
;
; Name:            
; Defined at line: 431
; #Upvalues:       1
; #Parameters:     2
; Is_vararg:       0
; Max Stack Size:  7

  1 [-]: NEWTABLE  R2 0 0       ; R2 := {}
  2 [-]: SETTABLE  R0 K0 R2     ; R0["mNewActiveCells"] := R2
  3 [-]: GETTABLE  R2 R0 K1     ; R2 := R0["mNextCellList"]
  4 [-]: SELF      R2 R2 K2     ; R3 := R2; R2 := R2[0x36fcc811]
  5 [-]: CALL      R2 2 1       ; R2(R3)
  6 [-]: GETTABLE  R2 R0 K1     ; R2 := R0["mNextCellList"]
  7 [-]: SELF      R2 R2 K3     ; R3 := R2; R2 := R2[0xdd2c9860]
  8 [-]: GETTABLE  R4 R0 K4     ; R4 := R0["mGrid"]
  9 [-]: SELF      R4 R4 K5     ; R5 := R4; R4 := R4[0x54c093f8]
 10 [-]: MOVE      R6 R1        ; R6 := R1
 11 [-]: CALL      R4 3 0       ; R4,... := R4(R5,R6)
 12 [-]: CALL      R2 0 1       ; R2(R3,...)
 13 [-]: SETTABLE  R0 K6 K7     ; R0["mActiveQuery"] := true
 14 [-]: GETUPVAL  R2 U0        ; R2 := U0
 15 [-]: GETTABLE  R3 R0 K8     ; R3 := R0["mVisitedCells"]
 16 [-]: CALL      R2 2 1       ; R2(R3)
 17 [-]: SETTABLE  R0 K9 R1     ; R0[0x00000001] := R1
 18 [-]: RETURN    R0 1         ; return 


; Function #19:
;
; Name:            
; Defined at line: 440
; #Upvalues:       0
; #Parameters:     1
; Is_vararg:       0
; Max Stack Size:  9

  1 [-]: GETGLOBAL R1 K0        ; R1 := 0xcfc01047
  2 [-]: GETTABLE  R2 R0 K1     ; R2 := R0["mActiveCells"]
  3 [-]: CALL      R1 2 4       ; R1,R2,R3 := R1(R2)
  4 [-]: JMP       15           ; PC := 15
  5 [-]: GETTABLE  R6 R0 K2     ; R6 := R0["mNewActiveCells"]
  6 [-]: GETTABLE  R6 R6 R4     ; R6 := R6[R4]
  7 [-]: TEST      R6 1         ; if R6 then PC := 15
  8 [-]: JMP       15           ; PC := 15
  9 [-]: GETTABLE  R6 R0 K1     ; R6 := R0["mActiveCells"]
 10 [-]: SETTABLE  R6 R4 K3     ; R6[R4] := nil
 11 [-]: GETTABLE  R6 R0 K4     ; R6 := R0["mActiveCellTable"]
 12 [-]: SELF      R6 R6 K5     ; R7 := R6; R6 := R6[0x1b2cf551]
 13 [-]: MOVE      R8 R4        ; R8 := R4
 14 [-]: CALL      R6 3 1       ; R6(R7,R8)
 15 [-]: TFORLOOP  R1 2         ; R4,R5 :=  R1(R2,R3); if R4 ~= nil then begin PC = 5; R3 := R4 end
 16 [-]: JMP       5            ; PC := 5
 17 [-]: RETURN    R0 1         ; return 


; Function #20:
;
; Name:            
; Defined at line: 450
; #Upvalues:       0
; #Parameters:     1
; Is_vararg:       0
; Max Stack Size:  5

  1 [-]: GETTABLE  R1 R0 K0     ; R1 := R0["mActiveCellResults"]
  2 [-]: SELF      R1 R1 K1     ; R2 := R1; R1 := R1[0xc9c8bcdc]
  3 [-]: CALL      R1 2 2       ; R1 := R1(R2)
  4 [-]: TEST      R1 0         ; if not R1 then PC := 24
  5 [-]: JMP       24           ; PC := 24
  6 [-]: GETTABLE  R2 R0 K2     ; R2 := R0["mNewActiveCells"]
  7 [-]: SETTABLE  R2 R1 K3     ; R2[R1] := true
  8 [-]: GETTABLE  R2 R0 K4     ; R2 := R0["mActiveCells"]
  9 [-]: GETTABLE  R2 R2 R1     ; R2 := R2[R1]
 10 [-]: TEST      R2 0         ; if not R2 then PC := 13
 11 [-]: JMP       13           ; PC := 13
 12 [-]: JMP       19           ; PC := 19
 13 [-]: GETTABLE  R2 R0 K4     ; R2 := R0["mActiveCells"]
 14 [-]: SETTABLE  R2 R1 K3     ; R2[R1] := true
 15 [-]: GETTABLE  R2 R0 K5     ; R2 := R0["mActiveCellTable"]
 16 [-]: SELF      R2 R2 K6     ; R3 := R2; R2 := R2[0xa73fbaa1]
 17 [-]: MOVE      R4 R1        ; R4 := R1
 18 [-]: CALL      R2 3 1       ; R2(R3,R4)
 19 [-]: GETTABLE  R2 R0 K0     ; R2 := R0["mActiveCellResults"]
 20 [-]: SELF      R2 R2 K1     ; R3 := R2; R2 := R2[0xc9c8bcdc]
 21 [-]: CALL      R2 2 2       ; R2 := R2(R3)
 22 [-]: MOVE      R1 R2        ; R1 := R2
 23 [-]: JMP       4            ; PC := 4
 24 [-]: RETURN    R0 1         ; return 


; Function #21:
;
; Name:            
; Defined at line: 465
; #Upvalues:       0
; #Parameters:     1
; Is_vararg:       0
; Max Stack Size:  6

  1 [-]: GETGLOBAL R1 K0        ; R1 := 0x7b998233
  2 [-]: GETTABLE  R2 R0 K1     ; R2 := R0["mPlayer"]
  3 [-]: CALL      R1 2 2       ; R1 := R1(R2)
  4 [-]: TEST      R1 0         ; if not R1 then PC := 20
  5 [-]: JMP       20           ; PC := 20
  6 [-]: GETGLOBAL R1 K2        ; R1 := 0x89326c93
  7 [-]: SELF      R1 R1 K3     ; R2 := R1; R1 := R1[0x7d108ddb]
  8 [-]: CALL      R1 2 2       ; R1 := R1(R2)
  9 [-]: TEST      R1 0         ; if not R1 then PC := 14
 10 [-]: JMP       14           ; PC := 14
 11 [-]: GETTABLE  R2 R0 K4     ; R2 := R0["mPlayerNum"]
 12 [-]: GETTABLE  R2 R1 R2     ; R2 := R1[R2]
 13 [-]: SETTABLE  R0 K1 R2     ; R0["mPlayer"] := R2
 14 [-]: GETGLOBAL R2 K0        ; R2 := 0x7b998233
 15 [-]: GETTABLE  R3 R0 K1     ; R3 := R0["mPlayer"]
 16 [-]: CALL      R2 2 2       ; R2 := R2(R3)
 17 [-]: TEST      R2 0         ; if not R2 then PC := 20
 18 [-]: JMP       20           ; PC := 20
 19 [-]: RETURN    R0 1         ; return 
 20 [-]: GETGLOBAL R2 K0        ; R2 := 0x7b998233
 21 [-]: GETTABLE  R3 R0 K5     ; R3 := R0["mAvatar"]
 22 [-]: CALL      R2 2 2       ; R2 := R2(R3)
 23 [-]: TEST      R2 0         ; if not R2 then PC := 35
 24 [-]: JMP       35           ; PC := 35
 25 [-]: GETTABLE  R2 R0 K1     ; R2 := R0["mPlayer"]
 26 [-]: SELF      R2 R2 K6     ; R3 := R2; R2 := R2[0xbb610e5b]
 27 [-]: CALL      R2 2 2       ; R2 := R2(R3)
 28 [-]: SETTABLE  R0 K5 R2     ; R0["mAvatar"] := R2
 29 [-]: GETGLOBAL R2 K0        ; R2 := 0x7b998233
 30 [-]: GETTABLE  R3 R0 K5     ; R3 := R0["mAvatar"]
 31 [-]: CALL      R2 2 2       ; R2 := R2(R3)
 32 [-]: TEST      R2 0         ; if not R2 then PC := 35
 33 [-]: JMP       35           ; PC := 35
 34 [-]: RETURN    R0 1         ; return 
 35 [-]: GETTABLE  R2 R0 K7     ; R2 := R0["mActiveQuery"]
 36 [-]: TEST      R2 0         ; if not R2 then PC := 48
 37 [-]: JMP       48           ; PC := 48
 38 [-]: SELF      R2 R0 K8     ; R3 := R0; R2 := R0[0xbd5e334b]
 39 [-]: CALL      R2 2 1       ; R2(R3)
 40 [-]: SELF      R2 R0 K9     ; R3 := R0; R2 := R0[0x8be69c0c]
 41 [-]: CALL      R2 2 1       ; R2(R3)
 42 [-]: GETTABLE  R2 R0 K7     ; R2 := R0["mActiveQuery"]
 43 [-]: TEST      R2 1         ; if R2 then PC := 47
 44 [-]: JMP       47           ; PC := 47
 45 [-]: SELF      R2 R0 K10    ; R3 := R0; R2 := R0[0xec221c2f]
 46 [-]: CALL      R2 2 1       ; R2(R3)
 47 [-]: RETURN    R0 1         ; return 
 48 [-]: GETTABLE  R2 R0 K11    ; R2 := R0["mLastPos"]
 49 [-]: EQ        1 R2 K12     ; if R2 == nil then PC := 59
 50 [-]: JMP       59           ; PC := 59
 51 [-]: GETTABLE  R2 R0 K5     ; R2 := R0["mAvatar"]
 52 [-]: SELF      R2 R2 K13    ; R3 := R2; R2 := R2[0x1f420a3a]
 53 [-]: GETTABLE  R4 R0 K11    ; R4 := R0["mLastPos"]
 54 [-]: CALL      R2 3 2       ; R2 := R2(R3,R4)
 55 [-]: GETTABLE  R3 R0 K14    ; R3 := R0["mRange"]
 56 [-]: DIV       R3 R3 K15    ; R3 := R3 / 3.000000
 57 [-]: LT        0 R3 R2      ; if R3 >= R2 then PC := 64
 58 [-]: JMP       64           ; PC := 64
 59 [-]: SELF      R2 R0 K16    ; R3 := R0; R2 := R0[0x2c73974b]
 60 [-]: GETTABLE  R4 R0 K5     ; R4 := R0["mAvatar"]
 61 [-]: SELF      R4 R4 K17    ; R5 := R4; R4 := R4[0xd1586535]
 62 [-]: CALL      R4 2 0       ; R4,... := R4(R5)
 63 [-]: CALL      R2 0 1       ; R2(R3,...)
 64 [-]: RETURN    R0 1         ; return 


; Function #22:
;
; Name:            
; Defined at line: 500
; #Upvalues:       0
; #Parameters:     1
; Is_vararg:       0
; Max Stack Size:  9

  1 [-]: SETTABLE  R0 K0 K1     ; R0["mActiveQuery"] := false
  2 [-]: GETGLOBAL R1 K2        ; R1 := 0xcfc01047
  3 [-]: GETTABLE  R2 R0 K3     ; R2 := R0["mActiveCells"]
  4 [-]: CALL      R1 2 4       ; R1,R2,R3 := R1(R2)
  5 [-]: JMP       12           ; PC := 12
  6 [-]: GETTABLE  R6 R0 K4     ; R6 := R0["mActiveCellTable"]
  7 [-]: SELF      R6 R6 K5     ; R7 := R6; R6 := R6[0x1b2cf551]
  8 [-]: MOVE      R8 R4        ; R8 := R4
  9 [-]: CALL      R6 3 1       ; R6(R7,R8)
 10 [-]: GETTABLE  R6 R0 K3     ; R6 := R0["mActiveCells"]
 11 [-]: SETTABLE  R6 R4 K6     ; R6[R4] := nil
 12 [-]: TFORLOOP  R1 2         ; R4,R5 :=  R1(R2,R3); if R4 ~= nil then begin PC = 6; R3 := R4 end
 13 [-]: JMP       6            ; PC := 6
 14 [-]: SETTABLE  R0 K7 K6     ; R0["mLastPos"] := nil
 15 [-]: RETURN    R0 1         ; return 


; Function #23:
;
; Name:            
; Defined at line: 509
; #Upvalues:       2
; #Parameters:     5
; Is_vararg:       0
; Max Stack Size:  8

  1 [-]: GETGLOBAL R5 K0        ; R5 := 0x2296a8fd
  2 [-]: NEWTABLE  R6 0 0       ; R6 := {}
  3 [-]: GETUPVAL  R7 U0        ; R7 := U0
  4 [-]: CALL      R5 3 2       ; R5 := R5(R6,R7)
  5 [-]: SETTABLE  R5 K1 R0     ; R5["mGrid"] := R0
  6 [-]: NEWTABLE  R6 0 0       ; R6 := {}
  7 [-]: SETTABLE  R5 K2 R6     ; R5["mActiveCells"] := R6
  8 [-]: GETGLOBAL R6 K4        ; R6 := 0x89326c93
  9 [-]: SELF      R6 R6 K5     ; R7 := R6; R6 := R6[0x7d108ddb]
 10 [-]: CALL      R6 2 2       ; R6 := R6(R7)
 11 [-]: GETTABLE  R6 R6 R3     ; R6 := R6[R3]
 12 [-]: SETTABLE  R5 K3 R6     ; R5["mPlayer"] := R6
 13 [-]: SETTABLE  R5 K6 R3     ; R5["mPlayerNum"] := R3
 14 [-]: SETTABLE  R5 K7 R1     ; R5["mRange"] := R1
 15 [-]: GETUPVAL  R6 U1        ; R6 := U1
 16 [-]: GETTABLE  R6 R6 K9     ; R6 := R6[0x7d4d5d68]
 17 [-]: CALL      R6 1 2       ; R6 := R6()
 18 [-]: SETTABLE  R5 K8 R6     ; R5["mNextCellList"] := R6
 19 [-]: GETUPVAL  R6 U1        ; R6 := U1
 20 [-]: GETTABLE  R6 R6 K9     ; R6 := R6[0x7d4d5d68]
 21 [-]: CALL      R6 1 2       ; R6 := R6()
 22 [-]: SETTABLE  R5 K10 R6    ; R5["mActiveCellResults"] := R6
 23 [-]: NEWTABLE  R6 0 0       ; R6 := {}
 24 [-]: SETTABLE  R5 K11 R6    ; R5["mVisitedCells"] := R6
 25 [-]: SETTABLE  R5 K12 R2    ; R5["mActiveCellTable"] := R2
 26 [-]: SETTABLE  R5 K13 R4    ; R5["mDoDebug"] := R4
 27 [-]: RETURN    R5 2         ; return R5
 28 [-]: RETURN    R0 1         ; return 


; Function #24:
;
; Name:            
; Defined at line: 529
; #Upvalues:       0
; #Parameters:     3
; Is_vararg:       0
; Max Stack Size:  5

  1 [-]: SETTABLE  R0 K0 R1     ; R0["mUpdateRange"] := R1
  2 [-]: DIV       R3 R1 K2     ; R3 := R1 / 2.000000
  3 [-]: SETTABLE  R0 K1 R3     ; R0["mCellWidth"] := R3
  4 [-]: SETTABLE  R0 K3 R2     ; R0["mMaxRange"] := R2
  5 [-]: GETGLOBAL R3 K5        ; R3 := 0x5bced4c4
  6 [-]: GETTABLE  R3 R3 K6     ; R3 := R3[0x99675e23]
  7 [-]: GETTABLE  R4 R0 K1     ; R4 := R0["mCellWidth"]
  8 [-]: DIV       R4 R2 R4     ; R4 := R2 / R4
  9 [-]: CALL      R3 2 2       ; R3 := R3(R4)
 10 [-]: SETTABLE  R0 K4 R3     ; R0["mFullCellCount"] := R3
 11 [-]: GETGLOBAL R3 K5        ; R3 := 0x5bced4c4
 12 [-]: GETTABLE  R3 R3 K6     ; R3 := R3[0x99675e23]
 13 [-]: GETTABLE  R4 R0 K4     ; R4 := R0["mFullCellCount"]
 14 [-]: DIV       R4 R4 K2     ; R4 := R4 / 2.000000
 15 [-]: CALL      R3 2 2       ; R3 := R3(R4)
 16 [-]: SETTABLE  R0 K7 R3     ; R0["mHalfCellCount"] := R3
 17 [-]: RETURN    R0 1         ; return 


; Function #25:
;
; Name:            
; Defined at line: 537
; #Upvalues:       0
; #Parameters:     4
; Is_vararg:       0
; Max Stack Size:  7

  1 [-]: GETTABLE  R4 R0 K0     ; R4 := R0["mHalfCellCount"]
  2 [-]: ADD       R4 R1 R4     ; R4 := R1 + R4
  3 [-]: GETTABLE  R5 R0 K1     ; R5 := R0["mFullCellCount"]
  4 [-]: MUL       R4 R4 R5     ; R4 := R4 * R5
  5 [-]: GETTABLE  R5 R0 K1     ; R5 := R0["mFullCellCount"]
  6 [-]: MUL       R4 R4 R5     ; R4 := R4 * R5
  7 [-]: GETTABLE  R5 R0 K0     ; R5 := R0["mHalfCellCount"]
  8 [-]: ADD       R5 R2 R5     ; R5 := R2 + R5
  9 [-]: GETTABLE  R6 R0 K1     ; R6 := R0["mFullCellCount"]
 10 [-]: MUL       R5 R5 R6     ; R5 := R5 * R6
 11 [-]: ADD       R4 R4 R5     ; R4 := R4 + R5
 12 [-]: ADD       R4 R4 R3     ; R4 := R4 + R3
 13 [-]: GETTABLE  R5 R0 K0     ; R5 := R0["mHalfCellCount"]
 14 [-]: ADD       R4 R4 R5     ; R4 := R4 + R5
 15 [-]: RETURN    R4 2         ; return R4
 16 [-]: RETURN    R0 1         ; return 


; Function #26:
;
; Name:            
; Defined at line: 542
; #Upvalues:       0
; #Parameters:     2
; Is_vararg:       0
; Max Stack Size:  10

  1 [-]: GETTABLE  R2 R0 K0     ; R2 := R0["mFullCellCount"]
  2 [-]: MOD       R2 R1 R2     ; R2 := R1 % R2
  3 [-]: GETTABLE  R3 R0 K1     ; R3 := R0["mHalfCellCount"]
  4 [-]: SUB       R2 R2 R3     ; R2 := R2 - R3
  5 [-]: SUB       R3 R1 R2     ; R3 := R1 - R2
  6 [-]: GETTABLE  R4 R0 K1     ; R4 := R0["mHalfCellCount"]
  7 [-]: SUB       R3 R3 R4     ; R3 := R3 - R4
  8 [-]: GETTABLE  R4 R0 K0     ; R4 := R0["mFullCellCount"]
  9 [-]: DIV       R1 R3 R4     ; R1 := R3 / R4
 10 [-]: GETTABLE  R3 R0 K0     ; R3 := R0["mFullCellCount"]
 11 [-]: MOD       R3 R1 R3     ; R3 := R1 % R3
 12 [-]: GETTABLE  R4 R0 K1     ; R4 := R0["mHalfCellCount"]
 13 [-]: SUB       R3 R3 R4     ; R3 := R3 - R4
 14 [-]: SUB       R4 R1 R3     ; R4 := R1 - R3
 15 [-]: GETTABLE  R5 R0 K1     ; R5 := R0["mHalfCellCount"]
 16 [-]: SUB       R4 R4 R5     ; R4 := R4 - R5
 17 [-]: GETTABLE  R5 R0 K0     ; R5 := R0["mFullCellCount"]
 18 [-]: DIV       R4 R4 R5     ; R4 := R4 / R5
 19 [-]: GETTABLE  R5 R0 K1     ; R5 := R0["mHalfCellCount"]
 20 [-]: SUB       R4 R4 R5     ; R4 := R4 - R5
 21 [-]: GETTABLE  R5 R0 K2     ; R5 := R0["mCellWidth"]
 22 [-]: MUL       R5 K3 R5     ; R5 := 0.500000 * R5
 23 [-]: GETGLOBAL R6 K4        ; R6 := 0xa421af95
 24 [-]: GETTABLE  R7 R0 K2     ; R7 := R0["mCellWidth"]
 25 [-]: MUL       R7 R4 R7     ; R7 := R4 * R7
 26 [-]: ADD       R7 R7 R5     ; R7 := R7 + R5
 27 [-]: GETTABLE  R8 R0 K2     ; R8 := R0["mCellWidth"]
 28 [-]: MUL       R8 R3 R8     ; R8 := R3 * R8
 29 [-]: ADD       R8 R8 R5     ; R8 := R8 + R5
 30 [-]: GETTABLE  R9 R0 K2     ; R9 := R0["mCellWidth"]
 31 [-]: MUL       R9 R2 R9     ; R9 := R2 * R9
 32 [-]: ADD       R9 R9 R5     ; R9 := R9 + R5
 33 [-]: TAILCALL  R6 4 0       ; R6,... := R6(R7,R8,R9)
 34 [-]: RETURN    R6 0         ; return R6,...
 35 [-]: RETURN    R0 1         ; return 


; Function #27:
;
; Name:            
; Defined at line: 551
; #Upvalues:       0
; #Parameters:     2
; Is_vararg:       0
; Max Stack Size:  9

  1 [-]: GETTABLE  R2 R0 K0     ; R2 := R0["mFullCellCount"]
  2 [-]: MOD       R2 R1 R2     ; R2 := R1 % R2
  3 [-]: GETTABLE  R3 R0 K1     ; R3 := R0["mHalfCellCount"]
  4 [-]: SUB       R2 R2 R3     ; R2 := R2 - R3
  5 [-]: SUB       R3 R1 R2     ; R3 := R1 - R2
  6 [-]: GETTABLE  R4 R0 K1     ; R4 := R0["mHalfCellCount"]
  7 [-]: SUB       R3 R3 R4     ; R3 := R3 - R4
  8 [-]: GETTABLE  R4 R0 K0     ; R4 := R0["mFullCellCount"]
  9 [-]: DIV       R1 R3 R4     ; R1 := R3 / R4
 10 [-]: GETTABLE  R3 R0 K0     ; R3 := R0["mFullCellCount"]
 11 [-]: MOD       R3 R1 R3     ; R3 := R1 % R3
 12 [-]: GETTABLE  R4 R0 K1     ; R4 := R0["mHalfCellCount"]
 13 [-]: SUB       R3 R3 R4     ; R3 := R3 - R4
 14 [-]: SUB       R4 R1 R3     ; R4 := R1 - R3
 15 [-]: GETTABLE  R5 R0 K1     ; R5 := R0["mHalfCellCount"]
 16 [-]: SUB       R4 R4 R5     ; R4 := R4 - R5
 17 [-]: GETTABLE  R5 R0 K0     ; R5 := R0["mFullCellCount"]
 18 [-]: DIV       R4 R4 R5     ; R4 := R4 / R5
 19 [-]: GETTABLE  R5 R0 K1     ; R5 := R0["mHalfCellCount"]
 20 [-]: SUB       R4 R4 R5     ; R4 := R4 - R5
 21 [-]: GETTABLE  R5 R0 K2     ; R5 := R0["mCellWidth"]
 22 [-]: MUL       R5 K3 R5     ; R5 := 0.500000 * R5
 23 [-]: GETTABLE  R6 R0 K2     ; R6 := R0["mCellWidth"]
 24 [-]: MUL       R6 R4 R6     ; R6 := R4 * R6
 25 [-]: ADD       R6 R6 R5     ; R6 := R6 + R5
 26 [-]: GETTABLE  R7 R0 K2     ; R7 := R0["mCellWidth"]
 27 [-]: MUL       R7 R3 R7     ; R7 := R3 * R7
 28 [-]: ADD       R7 R7 R5     ; R7 := R7 + R5
 29 [-]: GETTABLE  R8 R0 K2     ; R8 := R0["mCellWidth"]
 30 [-]: MUL       R8 R2 R8     ; R8 := R2 * R8
 31 [-]: ADD       R8 R8 R5     ; R8 := R8 + R5
 32 [-]: RETURN    R6 4         ; return R6,R7,R8
 33 [-]: RETURN    R0 1         ; return 


; Function #28:
;
; Name:            
; Defined at line: 560
; #Upvalues:       0
; #Parameters:     4
; Is_vararg:       0
; Max Stack Size:  8

  1 [-]: GETTABLE  R4 R0 R1     ; R4 := R0[R1]
  2 [-]: TEST      R4 1         ; if R4 then PC := 38
  3 [-]: JMP       38           ; PC := 38
  4 [-]: TEST      R3 0         ; if not R3 then PC := 38
  5 [-]: JMP       38           ; PC := 38
  6 [-]: GETTABLE  R4 R0 K0     ; R4 := R0["mDebugProcessing"]
  7 [-]: TEST      R4 0         ; if not R4 then PC := 14
  8 [-]: JMP       14           ; PC := 14
  9 [-]: GETGLOBAL R4 K1        ; R4 := 0x3d106989
 10 [-]: LOADK     R5 K2        ; R5 := "creating fresh cell for "
 11 [-]: MOVE      R6 R1        ; R6 := R1
 12 [-]: CONCAT    R5 R5 R6     ; R5 := R5 .. R6
 13 [-]: CALL      R4 2 1       ; R4(R5)
 14 [-]: NEWTABLE  R4 0 6       ; R4 := {}
 15 [-]: NEWTABLE  R5 0 0       ; R5 := {}
 16 [-]: SETTABLE  R4 K3 R5     ; R4["resourceEntries"] := R5
 17 [-]: NEWTABLE  R5 0 0       ; R5 := {}
 18 [-]: SETTABLE  R4 K4 R5     ; R4["creationInfo"] := R5
 19 [-]: NEWTABLE  R5 0 0       ; R5 := {}
 20 [-]: SETTABLE  R4 K5 R5     ; R4["candidates"] := R5
 21 [-]: SETTABLE  R4 K6 K7     ; R4["mQueried"] := 0.000000
 22 [-]: SETTABLE  R4 K8 K9     ; R4["mCandidatesProcessed"] := false
 23 [-]: SETTABLE  R4 K10 K11   ; R4["mNextCreationId"] := 1.000000
 24 [-]: SETTABLE  R0 R1 R4     ; R0[R1] := R4
 25 [-]: TEST      R2 1         ; if R2 then PC := 33
 26 [-]: JMP       33           ; PC := 33
 27 [-]: GETTABLE  R4 R0 R1     ; R4 := R0[R1]
 28 [-]: SELF      R5 R0 K13    ; R6 := R0; R5 := R0[0xea7c08de]
 29 [-]: MOVE      R7 R1        ; R7 := R1
 30 [-]: CALL      R5 3 2       ; R5 := R5(R6,R7)
 31 [-]: SETTABLE  R4 K12 R5    ; R4["mCenter"] := R5
 32 [-]: JMP       38           ; PC := 38
 33 [-]: GETTABLE  R4 R0 R1     ; R4 := R0[R1]
 34 [-]: SELF      R5 R0 K14    ; R6 := R0; R5 := R0[0x587a454c]
 35 [-]: MOVE      R7 R2        ; R7 := R2
 36 [-]: CALL      R5 3 2       ; R5 := R5(R6,R7)
 37 [-]: SETTABLE  R4 K12 R5    ; R4["mCenter"] := R5
 38 [-]: GETTABLE  R4 R0 R1     ; R4 := R0[R1]
 39 [-]: RETURN    R4 2         ; return R4
 40 [-]: RETURN    R0 1         ; return 


; Function #29:
;
; Name:            
; Defined at line: 582
; #Upvalues:       0
; #Parameters:     5
; Is_vararg:       0
; Max Stack Size:  13

  1 [-]: GETGLOBAL R5 K0        ; R5 := 0x5bced4c4
  2 [-]: GETTABLE  R5 R5 K1     ; R5 := R5[0x55f27c30]
  3 [-]: GETTABLE  R6 R1 K2     ; R6 := R1["x"]
  4 [-]: GETTABLE  R7 R0 K3     ; R7 := R0["mCellWidth"]
  5 [-]: DIV       R6 R6 R7     ; R6 := R6 / R7
  6 [-]: CALL      R5 2 2       ; R5 := R5(R6)
  7 [-]: GETGLOBAL R6 K0        ; R6 := 0x5bced4c4
  8 [-]: GETTABLE  R6 R6 K1     ; R6 := R6[0x55f27c30]
  9 [-]: GETTABLE  R7 R1 K4     ; R7 := R1["y"]
 10 [-]: GETTABLE  R8 R0 K3     ; R8 := R0["mCellWidth"]
 11 [-]: DIV       R7 R7 R8     ; R7 := R7 / R8
 12 [-]: CALL      R6 2 2       ; R6 := R6(R7)
 13 [-]: GETGLOBAL R7 K0        ; R7 := 0x5bced4c4
 14 [-]: GETTABLE  R7 R7 K1     ; R7 := R7[0x55f27c30]
 15 [-]: GETTABLE  R8 R1 K5     ; R8 := R1["z"]
 16 [-]: GETTABLE  R9 R0 K3     ; R9 := R0["mCellWidth"]
 17 [-]: DIV       R8 R8 R9     ; R8 := R8 / R9
 18 [-]: CALL      R7 2 2       ; R7 := R7(R8)
 19 [-]: TEST      R2 0         ; if not R2 then PC := 22
 20 [-]: JMP       22           ; PC := 22
 21 [-]: ADD       R5 R5 R2     ; R5 := R5 + R2
 22 [-]: TEST      R3 0         ; if not R3 then PC := 25
 23 [-]: JMP       25           ; PC := 25
 24 [-]: ADD       R6 R6 R3     ; R6 := R6 + R3
 25 [-]: TEST      R4 0         ; if not R4 then PC := 28
 26 [-]: JMP       28           ; PC := 28
 27 [-]: ADD       R7 R7 R4     ; R7 := R7 + R4
 28 [-]: SELF      R8 R0 K6     ; R9 := R0; R8 := R0[0x8f6bef7b]
 29 [-]: MOVE      R10 R5       ; R10 := R5
 30 [-]: MOVE      R11 R6       ; R11 := R6
 31 [-]: MOVE      R12 R7       ; R12 := R7
 32 [-]: CALL      R8 5 2       ; R8 := R8(R9,R10,R11,R12)
 33 [-]: RETURN    R8 2         ; return R8
 34 [-]: RETURN    R0 1         ; return 


; Function #30:
;
; Name:            
; Defined at line: 599
; #Upvalues:       0
; #Parameters:     7
; Is_vararg:       0
; Max Stack Size:  15

  1 [-]: GETGLOBAL R7 K0        ; R7 := 0x5bced4c4
  2 [-]: GETTABLE  R7 R7 K1     ; R7 := R7[0x55f27c30]
  3 [-]: GETTABLE  R8 R0 K2     ; R8 := R0["mCellWidth"]
  4 [-]: DIV       R8 R1 R8     ; R8 := R1 / R8
  5 [-]: CALL      R7 2 2       ; R7 := R7(R8)
  6 [-]: GETGLOBAL R8 K0        ; R8 := 0x5bced4c4
  7 [-]: GETTABLE  R8 R8 K1     ; R8 := R8[0x55f27c30]
  8 [-]: GETTABLE  R9 R0 K2     ; R9 := R0["mCellWidth"]
  9 [-]: DIV       R9 R2 R9     ; R9 := R2 / R9
 10 [-]: CALL      R8 2 2       ; R8 := R8(R9)
 11 [-]: GETGLOBAL R9 K0        ; R9 := 0x5bced4c4
 12 [-]: GETTABLE  R9 R9 K1     ; R9 := R9[0x55f27c30]
 13 [-]: GETTABLE  R10 R0 K2    ; R10 := R0["mCellWidth"]
 14 [-]: DIV       R10 R3 R10   ; R10 := R3 / R10
 15 [-]: CALL      R9 2 2       ; R9 := R9(R10)
 16 [-]: TEST      R4 0         ; if not R4 then PC := 19
 17 [-]: JMP       19           ; PC := 19
 18 [-]: ADD       R7 R7 R4     ; R7 := R7 + R4
 19 [-]: TEST      R5 0         ; if not R5 then PC := 22
 20 [-]: JMP       22           ; PC := 22
 21 [-]: ADD       R8 R8 R5     ; R8 := R8 + R5
 22 [-]: TEST      R6 0         ; if not R6 then PC := 25
 23 [-]: JMP       25           ; PC := 25
 24 [-]: ADD       R9 R9 R6     ; R9 := R9 + R6
 25 [-]: SELF      R10 R0 K3    ; R11 := R0; R10 := R0[0x8f6bef7b]
 26 [-]: MOVE      R12 R7       ; R12 := R7
 27 [-]: MOVE      R13 R8       ; R13 := R8
 28 [-]: MOVE      R14 R9       ; R14 := R9
 29 [-]: TAILCALL  R10 5 0      ; R10,... := R10(R11,R12,R13,R14)
 30 [-]: RETURN    R10 0        ; return R10,...
 31 [-]: RETURN    R0 1         ; return 


; Function #31:
;
; Name:            
; Defined at line: 615
; #Upvalues:       0
; #Parameters:     2
; Is_vararg:       0
; Max Stack Size:  8

  1 [-]: SELF      R2 R0 K0     ; R3 := R0; R2 := R0[0x54c093f8]
  2 [-]: MOVE      R4 R1        ; R4 := R1
  3 [-]: CALL      R2 3 2       ; R2 := R2(R3,R4)
  4 [-]: SELF      R3 R0 K1     ; R4 := R0; R3 := R0[0xcabdfd0e]
  5 [-]: MOVE      R5 R2        ; R5 := R2
  6 [-]: MOVE      R6 R1        ; R6 := R1
  7 [-]: LOADBOOL  R7 1 0       ; R7 := true
  8 [-]: CALL      R3 5 2       ; R3 := R3(R4,R5,R6,R7)
  9 [-]: SETTABLE  R3 K2 K3     ; R3["mCandidatesProcessed"] := true
 10 [-]: RETURN    R0 1         ; return 


; Function #32:
;
; Name:            
; Defined at line: 621
; #Upvalues:       0
; #Parameters:     4
; Is_vararg:       0
; Max Stack Size:  16

  1 [-]: SELF      R4 R0 K0     ; R5 := R0; R4 := R0[0x54c093f8]
  2 [-]: MOVE      R6 R1        ; R6 := R1
  3 [-]: CALL      R4 3 2       ; R4 := R4(R5,R6)
  4 [-]: SELF      R5 R0 K1     ; R6 := R0; R5 := R0[0xcabdfd0e]
  5 [-]: MOVE      R7 R4        ; R7 := R4
  6 [-]: MOVE      R8 R1        ; R8 := R1
  7 [-]: LOADBOOL  R9 1 0       ; R9 := true
  8 [-]: CALL      R5 5 2       ; R5 := R5(R6,R7,R8,R9)
  9 [-]: GETGLOBAL R6 K2        ; R6 := 0x33bdd652
 10 [-]: GETTABLE  R6 R6 K3     ; R6 := R6[0x23d5322f]
 11 [-]: GETTABLE  R7 R5 K4     ; R7 := R5["resourceEntries"]
 12 [-]: NEWTABLE  R8 0 3       ; R8 := {}
 13 [-]: SETTABLE  R8 K5 R1     ; R8["pos"] := R1
 14 [-]: SETTABLE  R8 K6 R2     ; R8["info"] := R2
 15 [-]: SETTABLE  R8 K7 R3     ; R8["infoId"] := R3
 16 [-]: CALL      R6 3 1       ; R6(R7,R8)
 17 [-]: GETTABLE  R6 R0 K8     ; R6 := R0["mDebugResourcePlacement"]
 18 [-]: TEST      R6 0         ; if not R6 then PC := 32
 19 [-]: JMP       32           ; PC := 32
 20 [-]: GETGLOBAL R6 K9        ; R6 := 0x3d106989
 21 [-]: LOADK     R7 K10       ; R7 := "resource added to "
 22 [-]: MOVE      R8 R4        ; R8 := R4
 23 [-]: LOADK     R9 K11       ; R9 := " at ("
 24 [-]: GETTABLE  R10 R1 K12   ; R10 := R1["x"]
 25 [-]: LOADK     R11 K13      ; R11 := ", "
 26 [-]: GETTABLE  R12 R1 K14   ; R12 := R1["y"]
 27 [-]: LOADK     R13 K13      ; R13 := ", "
 28 [-]: GETTABLE  R14 R1 K15   ; R14 := R1["z"]
 29 [-]: LOADK     R15 K16      ; R15 := ")"
 30 [-]: CONCAT    R7 R7 R15    ; R7 := R7 .. R8 .. R9 .. R10 .. R11 .. R12 .. R13 .. R14 .. R15
 31 [-]: CALL      R6 2 1       ; R6(R7)
 32 [-]: RETURN    R0 1         ; return 


; Function #33:
;
; Name:            
; Defined at line: 631
; #Upvalues:       0
; #Parameters:     3
; Is_vararg:       0
; Max Stack Size:  20

  1 [-]: SELF      R3 R0 K0     ; R4 := R0; R3 := R0[0x54c093f8]
  2 [-]: MOVE      R5 R1        ; R5 := R1
  3 [-]: CALL      R3 3 2       ; R3 := R3(R4,R5)
  4 [-]: SELF      R4 R0 K1     ; R5 := R0; R4 := R0[0xcabdfd0e]
  5 [-]: MOVE      R6 R3        ; R6 := R3
  6 [-]: CALL      R4 3 2       ; R4 := R4(R5,R6)
  7 [-]: LOADBOOL  R5 0 0       ; R5 := false
  8 [-]: GETTABLE  R6 R0 K2     ; R6 := R0["mDebugResourcePlacement"]
  9 [-]: TEST      R6 0         ; if not R6 then PC := 26
 10 [-]: JMP       26           ; PC := 26
 11 [-]: GETGLOBAL R6 K3        ; R6 := 0x3d106989
 12 [-]: LOADK     R7 K4        ; R7 := "trying to remove resource at ("
 13 [-]: GETTABLE  R8 R1 K5     ; R8 := R1["x"]
 14 [-]: LOADK     R9 K6        ; R9 := ", "
 15 [-]: GETTABLE  R10 R1 K7    ; R10 := R1["y"]
 16 [-]: LOADK     R11 K6       ; R11 := ", "
 17 [-]: GETTABLE  R12 R1 K8    ; R12 := R1["z"]
 18 [-]: LOADK     R13 K9       ; R13 := ")"
 19 [-]: CONCAT    R7 R7 R13    ; R7 := R7 .. R8 .. R9 .. R10 .. R11 .. R12 .. R13
 20 [-]: CALL      R6 2 1       ; R6(R7)
 21 [-]: GETGLOBAL R6 K3        ; R6 := 0x3d106989
 22 [-]: LOADK     R7 K10       ; R7 := "cell id determined to be "
 23 [-]: MOVE      R8 R3        ; R8 := R3
 24 [-]: CONCAT    R7 R7 R8     ; R7 := R7 .. R8
 25 [-]: CALL      R6 2 1       ; R6(R7)
 26 [-]: GETGLOBAL R6 K11       ; R6 := 0x7b998233
 27 [-]: MOVE      R7 R4        ; R7 := R4
 28 [-]: CALL      R6 2 2       ; R6 := R6(R7)
 29 [-]: TEST      R6 0         ; if not R6 then PC := 38
 30 [-]: JMP       38           ; PC := 38
 31 [-]: GETGLOBAL R6 K3        ; R6 := 0x3d106989
 32 [-]: LOADK     R7 K12       ; R7 := "No cell for cell id "
 33 [-]: MOVE      R8 R3        ; R8 := R3
 34 [-]: CONCAT    R7 R7 R8     ; R7 := R7 .. R8
 35 [-]: CALL      R6 2 1       ; R6(R7)
 36 [-]: LOADBOOL  R6 0 0       ; R6 := false
 37 [-]: RETURN    R6 2         ; return R6
 38 [-]: GETTABLE  R6 R4 K13    ; R6 := R4["creationInfo"]
 39 [-]: LEN       R7 R6        ; R7 := # R6
 40 [-]: LOADK     R8 1         ; R8 := 1.000000
 41 [-]: GETTABLE  R9 R4 K14    ; R9 := R4["resourceEntries"]
 42 [-]: LEN       R9 R9        ; R9 := # R9
 43 [-]: LOADK     R10 1        ; R10 := 1.000000
 44 [-]: FORPREP   R8 86        ; R8 -= R10; PC := 86
 45 [-]: GETTABLE  R12 R4 K14   ; R12 := R4["resourceEntries"]
 46 [-]: GETTABLE  R12 R12 R11  ; R12 := R12[R11]
 47 [-]: GETTABLE  R13 R0 K15   ; R13 := R0[0x90b5625a]
 48 [-]: MOVE      R14 R2       ; R14 := R2
 49 [-]: MOVE      R15 R12      ; R15 := R12
 50 [-]: CALL      R13 3 2      ; R13 := R13(R14,R15)
 51 [-]: TEST      R13 0        ; if not R13 then PC := 86
 52 [-]: JMP       86           ; PC := 86
 53 [-]: GETTABLE  R13 R0 K16   ; R13 := R0[0x4099a2e1]
 54 [-]: MOVE      R14 R12      ; R14 := R12
 55 [-]: LOADBOOL  R15 1 0      ; R15 := true
 56 [-]: CALL      R13 3 1      ; R13(R14,R15)
 57 [-]: LOADK     R13 1        ; R13 := 1.000000
 58 [-]: MOVE      R14 R7       ; R14 := R7
 59 [-]: LOADK     R15 1        ; R15 := 1.000000
 60 [-]: FORPREP   R13 72       ; R13 -= R15; PC := 72
 61 [-]: GETTABLE  R17 R6 R16   ; R17 := R6[R16]
 62 [-]: GETTABLE  R17 R17 K17  ; R17 := R17["id"]
 63 [-]: GETTABLE  R18 R12 K18  ; R18 := R12["infoId"]
 64 [-]: EQ        0 R17 R18    ; if R17 ~= R18 then PC := 72
 65 [-]: JMP       72           ; PC := 72
 66 [-]: GETGLOBAL R17 K19      ; R17 := 0x33bdd652
 67 [-]: GETTABLE  R17 R17 K20  ; R17 := R17[0x9c1f3b5a]
 68 [-]: GETTABLE  R18 R4 K13   ; R18 := R4["creationInfo"]
 69 [-]: MOVE      R19 R16      ; R19 := R16
 70 [-]: CALL      R17 3 1      ; R17(R18,R19)
 71 [-]: JMP       73           ; PC := 73
 72 [-]: FORLOOP   R13 61       ; R13 += R15; if R13 <= R14 then begin PC := 61; R16 := R13 end
 73 [-]: GETGLOBAL R17 K19      ; R17 := 0x33bdd652
 74 [-]: GETTABLE  R17 R17 K20  ; R17 := R17[0x9c1f3b5a]
 75 [-]: GETTABLE  R18 R4 K14   ; R18 := R4["resourceEntries"]
 76 [-]: MOVE      R19 R11      ; R19 := R11
 77 [-]: CALL      R17 3 1      ; R17(R18,R19)
 78 [-]: LOADBOOL  R5 1 0       ; R5 := true
 79 [-]: GETTABLE  R17 R0 K2    ; R17 := R0["mDebugResourcePlacement"]
 80 [-]: TEST      R17 0        ; if not R17 then PC := 87
 81 [-]: JMP       87           ; PC := 87
 82 [-]: GETGLOBAL R17 K3       ; R17 := 0x3d106989
 83 [-]: LOADK     R18 K21      ; R18 := "removed succesfully"
 84 [-]: CALL      R17 2 1      ; R17(R18)
 85 [-]: JMP       87           ; PC := 87
 86 [-]: FORLOOP   R8 45        ; R8 += R10; if R8 <= R9 then begin PC := 45; R11 := R8 end
 87 [-]: GETTABLE  R17 R0 K2    ; R17 := R0["mDebugResourcePlacement"]
 88 [-]: TEST      R17 0        ; if not R17 then PC := 95
 89 [-]: JMP       95           ; PC := 95
 90 [-]: TEST      R5 1         ; if R5 then PC := 95
 91 [-]: JMP       95           ; PC := 95
 92 [-]: GETGLOBAL R17 K3       ; R17 := 0x3d106989
 93 [-]: LOADK     R18 K22      ; R18 := "couldn't find it!"
 94 [-]: CALL      R17 2 1      ; R17(R18)
 95 [-]: RETURN    R5 2         ; return R5
 96 [-]: RETURN    R0 1         ; return 


; Function #34:
;
; Name:            
; Defined at line: 674
; #Upvalues:       0
; #Parameters:     3
; Is_vararg:       0
; Max Stack Size:  15

  1 [-]: SELF      R3 R0 K0     ; R4 := R0; R3 := R0[0x54c093f8]
  2 [-]: MOVE      R5 R2        ; R5 := R2
  3 [-]: CALL      R3 3 2       ; R3 := R3(R4,R5)
  4 [-]: SELF      R4 R0 K1     ; R5 := R0; R4 := R0[0xcabdfd0e]
  5 [-]: MOVE      R6 R3        ; R6 := R3
  6 [-]: MOVE      R7 R2        ; R7 := R2
  7 [-]: LOADBOOL  R8 1 0       ; R8 := true
  8 [-]: CALL      R4 5 2       ; R4 := R4(R5,R6,R7,R8)
  9 [-]: GETTABLE  R5 R0 K2     ; R5 := R0["mActiveCellTable"]
 10 [-]: GETTABLE  R5 R5 K3     ; R5 := R5["mCells"]
 11 [-]: GETTABLE  R5 R5 R3     ; R5 := R5[R3]
 12 [-]: TEST      R5 0         ; if not R5 then PC := 19
 13 [-]: JMP       19           ; PC := 19
 14 [-]: GETTABLE  R5 R0 K4     ; R5 := R0["mValidationQueue"]
 15 [-]: SELF      R5 R5 K5     ; R6 := R5; R5 := R5[0xdd2c9860]
 16 [-]: MOVE      R7 R1        ; R7 := R1
 17 [-]: CALL      R5 3 1       ; R5(R6,R7)
 18 [-]: JMP       25           ; PC := 25
 19 [-]: GETGLOBAL R5 K6        ; R5 := 0x33bdd652
 20 [-]: GETTABLE  R5 R5 K7     ; R5 := R5[0x23d5322f]
 21 [-]: GETTABLE  R6 R4 K8     ; R6 := R4["candidates"]
 22 [-]: MOVE      R7 R1        ; R7 := R1
 23 [-]: CALL      R5 3 1       ; R5(R6,R7)
 24 [-]: SETTABLE  R4 K9 K10    ; R4["mCandidatesProcessed"] := false
 25 [-]: GETTABLE  R5 R0 K11    ; R5 := R0["mDebugProcessing"]
 26 [-]: TEST      R5 0         ; if not R5 then PC := 40
 27 [-]: JMP       40           ; PC := 40
 28 [-]: GETGLOBAL R5 K12       ; R5 := 0x3d106989
 29 [-]: LOADK     R6 K13       ; R6 := "candidate added to "
 30 [-]: MOVE      R7 R3        ; R7 := R3
 31 [-]: LOADK     R8 K14       ; R8 := " at ("
 32 [-]: GETTABLE  R9 R2 K15    ; R9 := R2["x"]
 33 [-]: LOADK     R10 K16      ; R10 := ", "
 34 [-]: GETTABLE  R11 R2 K17   ; R11 := R2["y"]
 35 [-]: LOADK     R12 K16      ; R12 := ", "
 36 [-]: GETTABLE  R13 R2 K18   ; R13 := R2["z"]
 37 [-]: LOADK     R14 K19      ; R14 := ")"
 38 [-]: CONCAT    R6 R6 R14    ; R6 := R6 .. R7 .. R8 .. R9 .. R10 .. R11 .. R12 .. R13 .. R14
 39 [-]: CALL      R5 2 1       ; R5(R6)
 40 [-]: RETURN    R0 1         ; return 


; Function #35:
;
; Name:            
; Defined at line: 692
; #Upvalues:       0
; #Parameters:     4
; Is_vararg:       0
; Max Stack Size:  16

  1 [-]: SELF      R4 R0 K0     ; R5 := R0; R4 := R0[0x54c093f8]
  2 [-]: MOVE      R6 R1        ; R6 := R1
  3 [-]: CALL      R4 3 2       ; R4 := R4(R5,R6)
  4 [-]: SELF      R5 R0 K1     ; R6 := R0; R5 := R0[0xcabdfd0e]
  5 [-]: MOVE      R7 R4        ; R7 := R4
  6 [-]: MOVE      R8 R1        ; R8 := R1
  7 [-]: LOADBOOL  R9 1 0       ; R9 := true
  8 [-]: CALL      R5 5 2       ; R5 := R5(R6,R7,R8,R9)
  9 [-]: SETTABLE  R2 K2 R4     ; R2["cellId"] := R4
 10 [-]: GETTABLE  R6 R5 K4     ; R6 := R5["mNextCreationId"]
 11 [-]: SETTABLE  R2 K3 R6     ; R2["id"] := R6
 12 [-]: GETTABLE  R6 R5 K4     ; R6 := R5["mNextCreationId"]
 13 [-]: ADD       R6 R6 K5     ; R6 := R6 + 1.000000
 14 [-]: SETTABLE  R5 K4 R6     ; R5["mNextCreationId"] := R6
 15 [-]: GETGLOBAL R6 K6        ; R6 := 0x33bdd652
 16 [-]: GETTABLE  R6 R6 K7     ; R6 := R6[0x23d5322f]
 17 [-]: GETTABLE  R7 R5 K8     ; R7 := R5["creationInfo"]
 18 [-]: MOVE      R8 R2        ; R8 := R2
 19 [-]: CALL      R6 3 1       ; R6(R7,R8)
 20 [-]: TEST      R3 0         ; if not R3 then PC := 26
 21 [-]: JMP       26           ; PC := 26
 22 [-]: GETTABLE  R6 R0 K9     ; R6 := R0["mCreationQueue"]
 23 [-]: SELF      R6 R6 K10    ; R7 := R6; R6 := R6[0xdd2c9860]
 24 [-]: MOVE      R8 R2        ; R8 := R2
 25 [-]: CALL      R6 3 1       ; R6(R7,R8)
 26 [-]: GETTABLE  R6 R0 K11    ; R6 := R0["mDebugProcessing"]
 27 [-]: TEST      R6 0         ; if not R6 then PC := 41
 28 [-]: JMP       41           ; PC := 41
 29 [-]: GETGLOBAL R6 K12       ; R6 := 0x3d106989
 30 [-]: LOADK     R7 K13       ; R7 := "creation info added to "
 31 [-]: MOVE      R8 R4        ; R8 := R4
 32 [-]: LOADK     R9 K14       ; R9 := " at ("
 33 [-]: GETTABLE  R10 R1 K15   ; R10 := R1["x"]
 34 [-]: LOADK     R11 K16      ; R11 := ", "
 35 [-]: GETTABLE  R12 R1 K17   ; R12 := R1["y"]
 36 [-]: LOADK     R13 K16      ; R13 := ", "
 37 [-]: GETTABLE  R14 R1 K18   ; R14 := R1["z"]
 38 [-]: LOADK     R15 K19      ; R15 := ")"
 39 [-]: CONCAT    R7 R7 R15    ; R7 := R7 .. R8 .. R9 .. R10 .. R11 .. R12 .. R13 .. R14 .. R15
 40 [-]: CALL      R6 2 1       ; R6(R7)
 41 [-]: RETURN    R0 1         ; return 


; Function #36:
;
; Name:            
; Defined at line: 709
; #Upvalues:       0
; #Parameters:     2
; Is_vararg:       0
; Max Stack Size:  6

  1 [-]: GETGLOBAL R2 K0        ; R2 := 0xa421af95
  2 [-]: GETTABLE  R3 R1 K1     ; R3 := R1["x"]
  3 [-]: GETTABLE  R4 R1 K2     ; R4 := R1["y"]
  4 [-]: GETTABLE  R5 R1 K3     ; R5 := R1["z"]
  5 [-]: CALL      R2 4 2       ; R2 := R2(R3,R4,R5)
  6 [-]: MUL       R3 R2 K4     ; R3 := R2 * 1.000000
  7 [-]: GETTABLE  R4 R0 K5     ; R4 := R0["mCellWidth"]
  8 [-]: DIV       R2 R3 R4     ; R2 := R3 / R4
  9 [-]: GETGLOBAL R3 K6        ; R3 := 0x5bced4c4
 10 [-]: GETTABLE  R3 R3 K7     ; R3 := R3[0x55f27c30]
 11 [-]: GETTABLE  R4 R2 K1     ; R4 := R2["x"]
 12 [-]: CALL      R3 2 2       ; R3 := R3(R4)
 13 [-]: SETTABLE  R2 K1 R3     ; R2["x"] := R3
 14 [-]: GETGLOBAL R3 K6        ; R3 := 0x5bced4c4
 15 [-]: GETTABLE  R3 R3 K7     ; R3 := R3[0x55f27c30]
 16 [-]: GETTABLE  R4 R2 K2     ; R4 := R2["y"]
 17 [-]: CALL      R3 2 2       ; R3 := R3(R4)
 18 [-]: SETTABLE  R2 K2 R3     ; R2["y"] := R3
 19 [-]: GETGLOBAL R3 K6        ; R3 := 0x5bced4c4
 20 [-]: GETTABLE  R3 R3 K7     ; R3 := R3[0x55f27c30]
 21 [-]: GETTABLE  R4 R2 K3     ; R4 := R2["z"]
 22 [-]: CALL      R3 2 2       ; R3 := R3(R4)
 23 [-]: SETTABLE  R2 K3 R3     ; R2["z"] := R3
 24 [-]: GETTABLE  R3 R0 K5     ; R3 := R0["mCellWidth"]
 25 [-]: MUL       R2 R2 R3     ; R2 := R2 * R3
 26 [-]: GETTABLE  R3 R2 K1     ; R3 := R2["x"]
 27 [-]: GETTABLE  R4 R0 K5     ; R4 := R0["mCellWidth"]
 28 [-]: DIV       R4 R4 K8     ; R4 := R4 / 2.000000
 29 [-]: ADD       R3 R3 R4     ; R3 := R3 + R4
 30 [-]: SETTABLE  R2 K1 R3     ; R2["x"] := R3
 31 [-]: GETTABLE  R3 R2 K2     ; R3 := R2["y"]
 32 [-]: GETTABLE  R4 R0 K5     ; R4 := R0["mCellWidth"]
 33 [-]: DIV       R4 R4 K8     ; R4 := R4 / 2.000000
 34 [-]: ADD       R3 R3 R4     ; R3 := R3 + R4
 35 [-]: SETTABLE  R2 K2 R3     ; R2["y"] := R3
 36 [-]: GETTABLE  R3 R2 K3     ; R3 := R2["z"]
 37 [-]: GETTABLE  R4 R0 K5     ; R4 := R0["mCellWidth"]
 38 [-]: DIV       R4 R4 K8     ; R4 := R4 / 2.000000
 39 [-]: ADD       R3 R3 R4     ; R3 := R3 + R4
 40 [-]: SETTABLE  R2 K3 R3     ; R2["z"] := R3
 41 [-]: RETURN    R2 2         ; return R2
 42 [-]: RETURN    R0 1         ; return 


; Function #37:
;
; Name:            
; Defined at line: 722
; #Upvalues:       0
; #Parameters:     2
; Is_vararg:       0
; Max Stack Size:  11

  1 [-]: SELF      R2 R0 K0     ; R3 := R0; R2 := R0[0x54c093f8]
  2 [-]: GETTABLE  R4 R1 K1     ; R4 := R1["pos"]
  3 [-]: CALL      R2 3 2       ; R2 := R2(R3,R4)
  4 [-]: SELF      R3 R0 K2     ; R4 := R0; R3 := R0[0xcabdfd0e]
  5 [-]: MOVE      R5 R2        ; R5 := R2
  6 [-]: CALL      R3 3 2       ; R3 := R3(R4,R5)
  7 [-]: TEST      R3 0         ; if not R3 then PC := 22
  8 [-]: JMP       22           ; PC := 22
  9 [-]: LOADK     R4 1         ; R4 := 1.000000
 10 [-]: GETTABLE  R5 R3 K3     ; R5 := R3["creationInfo"]
 11 [-]: LEN       R5 R5        ; R5 := # R5
 12 [-]: LOADK     R6 1         ; R6 := 1.000000
 13 [-]: FORPREP   R4 21        ; R4 -= R6; PC := 21
 14 [-]: GETTABLE  R8 R3 K3     ; R8 := R3["creationInfo"]
 15 [-]: GETTABLE  R8 R8 R7     ; R8 := R8[R7]
 16 [-]: GETTABLE  R9 R8 K4     ; R9 := R8["id"]
 17 [-]: GETTABLE  R10 R1 K5    ; R10 := R1["infoId"]
 18 [-]: EQ        0 R9 R10     ; if R9 ~= R10 then PC := 21
 19 [-]: JMP       21           ; PC := 21
 20 [-]: RETURN    R8 2         ; return R8
 21 [-]: FORLOOP   R4 14        ; R4 += R6; if R4 <= R5 then begin PC := 14; R7 := R4 end
 22 [-]: RETURN    R0 1         ; return 


; Function #38:
;
; Name:            
; Defined at line: 735
; #Upvalues:       1
; #Parameters:     2
; Is_vararg:       0
; Max Stack Size:  5

  1 [-]: GETUPVAL  R2 U0        ; R2 := U0
  2 [-]: GETTABLE  R2 R2 K0     ; R2 := R2[0x7d4d5d68]
  3 [-]: MOVE      R3 R0        ; R3 := R0
  4 [-]: MOVE      R4 R1        ; R4 := R1
  5 [-]: TAILCALL  R2 3 0       ; R2,... := R2(R3,R4)
  6 [-]: RETURN    R2 0         ; return R2,...
  7 [-]: RETURN    R0 1         ; return 


; Function #39:
;
; Name:            
; Defined at line: 739
; #Upvalues:       1
; #Parameters:     1
; Is_vararg:       0
; Max Stack Size:  12

  1 [-]: NEWTABLE  R1 0 4       ; R1 := {}
  2 [-]: NEWTABLE  R2 0 0       ; R2 := {}
  3 [-]: SETTABLE  R1 K1 R2     ; R1["mDirty"] := R2
  4 [-]: NEWTABLE  R2 0 0       ; R2 := {}
  5 [-]: SETTABLE  R1 K2 R2     ; R1["mCells"] := R2
  6 [-]: CLOSURE   R2 0         ; R2 := closure(Function #39.1)
  7 [-]: SETTABLE  R1 K3 R2     ; R1["IncrementActive"] := R2
  8 [-]: CLOSURE   R2 1         ; R2 := closure(Function #39.2)
  9 [-]: SETTABLE  R1 K4 R2     ; R1[0x89326c93] := R2
 10 [-]: SETTABLE  R0 K0 R1     ; R0["mActiveCellTable"] := R1
 11 [-]: NEWTABLE  R1 0 0       ; R1 := {}
 12 [-]: SETTABLE  R0 K5 R1     ; R0[0x9ed3b54e] := R1
 13 [-]: LOADK     R1 1         ; R1 := 1.000000
 14 [-]: LOADK     R2 4         ; R2 := 4.000000
 15 [-]: LOADK     R3 1         ; R3 := 1.000000
 16 [-]: FORPREP   R1 27        ; R1 -= R3; PC := 27
 17 [-]: GETTABLE  R5 R0 K5     ; R5 := R0["mActiveCellQueryWorkers"]
 18 [-]: GETUPVAL  R6 U0        ; R6 := U0
 19 [-]: GETTABLE  R6 R6 K6     ; R6 := R6[0x7d4d5d68]
 20 [-]: MOVE      R7 R0        ; R7 := R0
 21 [-]: GETTABLE  R8 R0 K7     ; R8 := R0["mUpdateRange"]
 22 [-]: GETTABLE  R9 R0 K0     ; R9 := R0["mActiveCellTable"]
 23 [-]: MOVE      R10 R4       ; R10 := R4
 24 [-]: GETTABLE  R11 R0 K8    ; R11 := R0["mDebugActiveCells"]
 25 [-]: CALL      R6 6 2       ; R6 := R6(R7,R8,R9,R10,R11)
 26 [-]: SETTABLE  R5 R4 R6     ; R5[R4] := R6
 27 [-]: FORLOOP   R1 17        ; R1 += R3; if R1 <= R2 then begin PC := 17; R4 := R1 end
 28 [-]: SETTABLE  R0 K9 K10    ; R0["mLastNumPlayers"] := 0.000000
 29 [-]: RETURN    R0 1         ; return 


; Function #39.1:
;
; Name:            
; Defined at line: 743
; #Upvalues:       0
; #Parameters:     2
; Is_vararg:       0
; Max Stack Size:  4

  1 [-]: GETTABLE  R2 R0 K0     ; R2 := R0["mCells"]
  2 [-]: GETTABLE  R2 R2 R1     ; R2 := R2[R1]
  3 [-]: EQ        0 R2 K1      ; if R2 ~= nil then PC := 9
  4 [-]: JMP       9            ; PC := 9
  5 [-]: GETTABLE  R2 R0 K2     ; R2 := R0["mDirty"]
  6 [-]: SETTABLE  R2 R1 K3     ; R2[R1] := 1.000000
  7 [-]: GETTABLE  R2 R0 K0     ; R2 := R0["mCells"]
  8 [-]: SETTABLE  R2 R1 K4     ; R2[R1] := 0.000000
  9 [-]: GETTABLE  R2 R0 K0     ; R2 := R0["mCells"]
 10 [-]: GETTABLE  R3 R0 K0     ; R3 := R0["mCells"]
 11 [-]: GETTABLE  R3 R3 R1     ; R3 := R3[R1]
 12 [-]: ADD       R3 R3 K3     ; R3 := R3 + 1.000000
 13 [-]: SETTABLE  R2 R1 R3     ; R2[R1] := R3
 14 [-]: RETURN    R0 1         ; return 


; Function #39.2:
;
; Name:            
; Defined at line: 751
; #Upvalues:       0
; #Parameters:     2
; Is_vararg:       0
; Max Stack Size:  4

  1 [-]: GETTABLE  R2 R0 K0     ; R2 := R0["mCells"]
  2 [-]: GETTABLE  R3 R0 K0     ; R3 := R0["mCells"]
  3 [-]: GETTABLE  R3 R3 R1     ; R3 := R3[R1]
  4 [-]: SUB       R3 R3 K1     ; R3 := R3 - 1.000000
  5 [-]: SETTABLE  R2 R1 R3     ; R2[R1] := R3
  6 [-]: GETTABLE  R2 R0 K0     ; R2 := R0["mCells"]
  7 [-]: GETTABLE  R2 R2 R1     ; R2 := R2[R1]
  8 [-]: EQ        0 R2 K2      ; if R2 ~= 0.000000 then PC := 14
  9 [-]: JMP       14           ; PC := 14
 10 [-]: GETTABLE  R2 R0 K3     ; R2 := R0["mDirty"]
 11 [-]: SETTABLE  R2 R1 K2     ; R2[R1] := 0.000000
 12 [-]: GETTABLE  R2 R0 K0     ; R2 := R0["mCells"]
 13 [-]: SETTABLE  R2 R1 K4     ; R2[R1] := nil
 14 [-]: RETURN    R0 1         ; return 


; Function #40:
;
; Name:            
; Defined at line: 768
; #Upvalues:       1
; #Parameters:     1
; Is_vararg:       0
; Max Stack Size:  27

  1 [-]: GETTABLE  R1 R0 K0     ; R1 := R0["mGenerateForAllPlayers"]
  2 [-]: TEST      R1 0         ; if not R1 then PC := 27
  3 [-]: JMP       27           ; PC := 27
  4 [-]: GETGLOBAL R1 K1        ; R1 := 0x89326c93
  5 [-]: SELF      R1 R1 K2     ; R2 := R1; R1 := R1[0x61be252a]
  6 [-]: CALL      R1 2 2       ; R1 := R1(R2)
  7 [-]: LOADK     R2 1         ; R2 := 1.000000
  8 [-]: MOVE      R3 R1        ; R3 := R1
  9 [-]: LOADK     R4 1         ; R4 := 1.000000
 10 [-]: FORPREP   R2 15        ; R2 -= R4; PC := 15
 11 [-]: GETTABLE  R6 R0 K3     ; R6 := R0["mActiveCellQueryWorkers"]
 12 [-]: GETTABLE  R6 R6 R5     ; R6 := R6[R5]
 13 [-]: SELF      R7 R6 K4     ; R8 := R6; R7 := R6[0xfaa69527]
 14 [-]: CALL      R7 2 1       ; R7(R8)
 15 [-]: FORLOOP   R2 11        ; R2 += R4; if R2 <= R3 then begin PC := 11; R5 := R2 end
 16 [-]: ADD       R7 R1 K5     ; R7 := R1 + 1.000000
 17 [-]: GETTABLE  R8 R0 K6     ; R8 := R0["mLastNumPlayers"]
 18 [-]: LOADK     R9 1         ; R9 := 1.000000
 19 [-]: FORPREP   R7 24        ; R7 -= R9; PC := 24
 20 [-]: GETTABLE  R11 R0 K3    ; R11 := R0["mActiveCellQueryWorkers"]
 21 [-]: GETTABLE  R11 R11 R10  ; R11 := R11[R10]
 22 [-]: SELF      R12 R11 K7   ; R13 := R11; R12 := R11[0xe2e807cc]
 23 [-]: CALL      R12 2 1      ; R12(R13)
 24 [-]: FORLOOP   R7 20        ; R7 += R9; if R7 <= R8 then begin PC := 20; R10 := R7 end
 25 [-]: SETTABLE  R0 K6 R1     ; R0["mLastNumPlayers"] := R1
 26 [-]: JMP       31           ; PC := 31
 27 [-]: GETTABLE  R12 R0 K3    ; R12 := R0["mActiveCellQueryWorkers"]
 28 [-]: GETTABLE  R12 R12 K5   ; R12 := R12[1.000000]
 29 [-]: SELF      R12 R12 K4   ; R13 := R12; R12 := R12[0xfaa69527]
 30 [-]: CALL      R12 2 1      ; R12(R13)
 31 [-]: GETTABLE  R12 R0 K8    ; R12 := R0["mDebugActiveCells"]
 32 [-]: TEST      R12 0        ; if not R12 then PC := 96
 33 [-]: JMP       96           ; PC := 96
 34 [-]: GETTABLE  R12 R0 K9    ; R12 := R0["mCellWidth"]
 35 [-]: DIV       R12 R12 K10  ; R12 := R12 / 2.000000
 36 [-]: GETGLOBAL R13 K11      ; R13 := 0xcfc01047
 37 [-]: GETTABLE  R14 R0 K12   ; R14 := R0["mActiveCellTable"]
 38 [-]: GETTABLE  R14 R14 K13  ; R14 := R14["mCells"]
 39 [-]: CALL      R13 2 4      ; R13,R14,R15 := R13(R14)
 40 [-]: JMP       94           ; PC := 94
 41 [-]: SELF      R18 R0 K14   ; R19 := R0; R18 := R0[0xea7c08de]
 42 [-]: MOVE      R20 R16      ; R20 := R16
 43 [-]: CALL      R18 3 2      ; R18 := R18(R19,R20)
 44 [-]: GETGLOBAL R19 K1       ; R19 := 0x89326c93
 45 [-]: SELF      R19 R19 K15  ; R20 := R19; R19 := R19[0x9ed3b54e]
 46 [-]: MOVE      R21 R18      ; R21 := R18
 47 [-]: LOADK     R22 K16      ; R22 := 0.200000
 48 [-]: GETGLOBAL R23 K17      ; R23 := 0x60130201
 49 [-]: LOADK     R24 0        ; R24 := 0.000000
 50 [-]: LOADK     R25 255      ; R25 := 255.000000
 51 [-]: LOADK     R26 0        ; R26 := 0.000000
 52 [-]: CALL      R23 4 2      ; R23 := R23(R24,R25,R26)
 53 [-]: LOADK     R24 K18      ; R24 := 0.100000
 54 [-]: CALL      R19 6 1      ; R19(R20,R21,R22,R23,R24)
 55 [-]: GETUPVAL  R19 U0       ; R19 := U0
 56 [-]: GETGLOBAL R20 K19      ; R20 := 0xa421af95
 57 [-]: GETTABLE  R21 R18 K20  ; R21 := R18["x"]
 58 [-]: SUB       R21 R21 R12  ; R21 := R21 - R12
 59 [-]: GETTABLE  R22 R18 K21  ; R22 := R18["y"]
 60 [-]: SUB       R22 R22 R12  ; R22 := R22 - R12
 61 [-]: GETTABLE  R23 R18 K22  ; R23 := R18["z"]
 62 [-]: SUB       R23 R23 R12  ; R23 := R23 - R12
 63 [-]: CALL      R20 4 2      ; R20 := R20(R21,R22,R23)
 64 [-]: GETGLOBAL R21 K19      ; R21 := 0xa421af95
 65 [-]: GETTABLE  R22 R18 K20  ; R22 := R18["x"]
 66 [-]: ADD       R22 R22 R12  ; R22 := R22 + R12
 67 [-]: GETTABLE  R23 R18 K21  ; R23 := R18["y"]
 68 [-]: ADD       R23 R23 R12  ; R23 := R23 + R12
 69 [-]: GETTABLE  R24 R18 K22  ; R24 := R18["z"]
 70 [-]: ADD       R24 R24 R12  ; R24 := R24 + R12
 71 [-]: CALL      R21 4 2      ; R21 := R21(R22,R23,R24)
 72 [-]: GETGLOBAL R22 K17      ; R22 := 0x60130201
 73 [-]: LOADK     R23 0        ; R23 := 0.000000
 74 [-]: LOADK     R24 100      ; R24 := 100.000000
 75 [-]: LOADK     R25 100      ; R25 := 100.000000
 76 [-]: CALL      R22 4 2      ; R22 := R22(R23,R24,R25)
 77 [-]: LOADK     R23 K18      ; R23 := 0.100000
 78 [-]: CALL      R19 5 1      ; R19(R20,R21,R22,R23)
 79 [-]: GETGLOBAL R19 K1       ; R19 := 0x89326c93
 80 [-]: SELF      R19 R19 K15  ; R20 := R19; R19 := R19[0x9ed3b54e]
 81 [-]: GETGLOBAL R21 K1       ; R21 := 0x89326c93
 82 [-]: SELF      R21 R21 K23  ; R22 := R21; R21 := R21[0x78298275]
 83 [-]: CALL      R21 2 2      ; R21 := R21(R22)
 84 [-]: SELF      R21 R21 K24  ; R22 := R21; R21 := R21[0xd1586535]
 85 [-]: CALL      R21 2 2      ; R21 := R21(R22)
 86 [-]: GETTABLE  R22 R0 K25   ; R22 := R0["mUpdateRange"]
 87 [-]: GETGLOBAL R23 K17      ; R23 := 0x60130201
 88 [-]: LOADK     R24 100      ; R24 := 100.000000
 89 [-]: LOADK     R25 100      ; R25 := 100.000000
 90 [-]: LOADK     R26 0        ; R26 := 0.000000
 91 [-]: CALL      R23 4 2      ; R23 := R23(R24,R25,R26)
 92 [-]: LOADK     R24 K18      ; R24 := 0.100000
 93 [-]: CALL      R19 6 1      ; R19(R20,R21,R22,R23,R24)
 94 [-]: TFORLOOP  R13 2        ; R16,R17 :=  R13(R14,R15); if R16 ~= nil then begin PC = 41; R15 := R16 end
 95 [-]: JMP       41           ; PC := 41
 96 [-]: RETURN    R0 1         ; return 


; Function #41:
;
; Name:            
; Defined at line: 795
; #Upvalues:       0
; #Parameters:     1
; Is_vararg:       0
; Max Stack Size:  32

  1 [-]: GETGLOBAL R1 K0        ; R1 := 0xcfc01047
  2 [-]: GETTABLE  R2 R0 K1     ; R2 := R0["mActiveCellTable"]
  3 [-]: GETTABLE  R2 R2 K2     ; R2 := R2["mDirty"]
  4 [-]: CALL      R1 2 4       ; R1,R2,R3 := R1(R2)
  5 [-]: JMP       106          ; PC := 106
  6 [-]: SELF      R6 R0 K3     ; R7 := R0; R6 := R0[0xcabdfd0e]
  7 [-]: MOVE      R8 R4        ; R8 := R4
  8 [-]: CALL      R6 3 2       ; R6 := R6(R7,R8)
  9 [-]: TEST      R6 0         ; if not R6 then PC := 103
 10 [-]: JMP       103          ; PC := 103
 11 [-]: EQ        0 R5 K4      ; if R5 ~= 1.000000 then PC := 63
 12 [-]: JMP       63           ; PC := 63
 13 [-]: GETTABLE  R7 R6 K5     ; R7 := R6["mCandidatesProcessed"]
 14 [-]: TEST      R7 1         ; if R7 then PC := 30
 15 [-]: JMP       30           ; PC := 30
 16 [-]: LOADK     R7 1         ; R7 := 1.000000
 17 [-]: GETTABLE  R8 R6 K6     ; R8 := R6["candidates"]
 18 [-]: LEN       R8 R8        ; R8 := # R8
 19 [-]: LOADK     R9 1         ; R9 := 1.000000
 20 [-]: FORPREP   R7 28        ; R7 -= R9; PC := 28
 21 [-]: GETTABLE  R11 R0 K7    ; R11 := R0["mValidationQueue"]
 22 [-]: SELF      R11 R11 K8   ; R12 := R11; R11 := R11[0xdd2c9860]
 23 [-]: GETTABLE  R13 R6 K6    ; R13 := R6["candidates"]
 24 [-]: GETTABLE  R13 R13 R10  ; R13 := R13[R10]
 25 [-]: CALL      R11 3 1      ; R11(R12,R13)
 26 [-]: GETTABLE  R11 R6 K6    ; R11 := R6["candidates"]
 27 [-]: SETTABLE  R11 R10 K9   ; R11[R10] := nil
 28 [-]: FORLOOP   R7 21        ; R7 += R9; if R7 <= R8 then begin PC := 21; R10 := R7 end
 29 [-]: SETTABLE  R6 K5 K10    ; R6["mCandidatesProcessed"] := true
 30 [-]: LOADK     R11 1        ; R11 := 1.000000
 31 [-]: GETTABLE  R12 R6 K11   ; R12 := R6["creationInfo"]
 32 [-]: LEN       R12 R12      ; R12 := # R12
 33 [-]: LOADK     R13 1        ; R13 := 1.000000
 34 [-]: FORPREP   R11 47       ; R11 -= R13; PC := 47
 35 [-]: GETTABLE  R15 R6 K11   ; R15 := R6["creationInfo"]
 36 [-]: GETTABLE  R15 R15 R14  ; R15 := R15[R14]
 37 [-]: GETTABLE  R16 R15 K12  ; R16 := R15["permanent"]
 38 [-]: TEST      R16 0        ; if not R16 then PC := 43
 39 [-]: JMP       43           ; PC := 43
 40 [-]: GETTABLE  R16 R15 K13  ; R16 := R15["permanentlyCreated"]
 41 [-]: TEST      R16 1        ; if R16 then PC := 47
 42 [-]: JMP       47           ; PC := 47
 43 [-]: GETTABLE  R16 R0 K14   ; R16 := R0["mCreationQueue"]
 44 [-]: SELF      R16 R16 K8   ; R17 := R16; R16 := R16[0xdd2c9860]
 45 [-]: MOVE      R18 R15      ; R18 := R15
 46 [-]: CALL      R16 3 1      ; R16(R17,R18)
 47 [-]: FORLOOP   R11 35       ; R11 += R13; if R11 <= R12 then begin PC := 35; R14 := R11 end
 48 [-]: GETTABLE  R16 R0 K15   ; R16 := R0["mDebugActiveCells"]
 49 [-]: TEST      R16 0        ; if not R16 then PC := 103
 50 [-]: JMP       103          ; PC := 103
 51 [-]: GETGLOBAL R16 K16      ; R16 := 0x89326c93
 52 [-]: SELF      R16 R16 K17  ; R17 := R16; R16 := R16[0x9ed3b54e]
 53 [-]: GETTABLE  R18 R6 K18   ; R18 := R6["mCenter"]
 54 [-]: LOADK     R19 2        ; R19 := 2.000000
 55 [-]: GETGLOBAL R20 K19      ; R20 := 0x60130201
 56 [-]: LOADK     R21 0        ; R21 := 0.000000
 57 [-]: LOADK     R22 255      ; R22 := 255.000000
 58 [-]: LOADK     R23 0        ; R23 := 0.000000
 59 [-]: CALL      R20 4 2      ; R20 := R20(R21,R22,R23)
 60 [-]: LOADK     R21 20       ; R21 := 20.000000
 61 [-]: CALL      R16 6 1      ; R16(R17,R18,R19,R20,R21)
 62 [-]: JMP       103          ; PC := 103
 63 [-]: EQ        0 R5 K20     ; if R5 ~= 0.000000 then PC := 103
 64 [-]: JMP       103          ; PC := 103
 65 [-]: LOADK     R16 1        ; R16 := 1.000000
 66 [-]: GETTABLE  R17 R6 K21   ; R17 := R6["resourceEntries"]
 67 [-]: LEN       R18 R17      ; R18 := # R17
 68 [-]: LOADK     R19 1        ; R19 := 1.000000
 69 [-]: MOVE      R20 R18      ; R20 := R18
 70 [-]: LOADK     R21 1        ; R21 := 1.000000
 71 [-]: FORPREP   R19 88       ; R19 -= R21; PC := 88
 72 [-]: GETTABLE  R23 R17 R22  ; R23 := R17[R22]
 73 [-]: GETTABLE  R24 R23 K22  ; R24 := R23["info"]
 74 [-]: GETTABLE  R24 R24 K12  ; R24 := R24["permanent"]
 75 [-]: TEST      R24 1        ; if R24 then PC := 83
 76 [-]: JMP       83           ; PC := 83
 77 [-]: GETTABLE  R24 R0 K23   ; R24 := R0["mDeletionQueue"]
 78 [-]: SELF      R24 R24 K8   ; R25 := R24; R24 := R24[0xdd2c9860]
 79 [-]: MOVE      R26 R23      ; R26 := R23
 80 [-]: CALL      R24 3 1      ; R24(R25,R26)
 81 [-]: SETTABLE  R17 R22 K9   ; R17[R22] := nil
 82 [-]: JMP       88           ; PC := 88
 83 [-]: EQ        1 R16 R22    ; if R16 == R22 then PC := 87
 84 [-]: JMP       87           ; PC := 87
 85 [-]: SETTABLE  R17 R22 K9   ; R17[R22] := nil
 86 [-]: SETTABLE  R17 R16 R23  ; R17[R16] := R23
 87 [-]: ADD       R16 R16 K4   ; R16 := R16 + 1.000000
 88 [-]: FORLOOP   R19 72       ; R19 += R21; if R19 <= R20 then begin PC := 72; R22 := R19 end
 89 [-]: GETTABLE  R24 R0 K15   ; R24 := R0["mDebugActiveCells"]
 90 [-]: TEST      R24 0        ; if not R24 then PC := 103
 91 [-]: JMP       103          ; PC := 103
 92 [-]: GETGLOBAL R24 K16      ; R24 := 0x89326c93
 93 [-]: SELF      R24 R24 K17  ; R25 := R24; R24 := R24[0x9ed3b54e]
 94 [-]: GETTABLE  R26 R6 K18   ; R26 := R6["mCenter"]
 95 [-]: LOADK     R27 2        ; R27 := 2.000000
 96 [-]: GETGLOBAL R28 K19      ; R28 := 0x60130201
 97 [-]: LOADK     R29 255      ; R29 := 255.000000
 98 [-]: LOADK     R30 0        ; R30 := 0.000000
 99 [-]: LOADK     R31 0        ; R31 := 0.000000
100 [-]: CALL      R28 4 2      ; R28 := R28(R29,R30,R31)
101 [-]: LOADK     R29 20       ; R29 := 20.000000
102 [-]: CALL      R24 6 1      ; R24(R25,R26,R27,R28,R29)
103 [-]: GETTABLE  R24 R0 K1    ; R24 := R0["mActiveCellTable"]
104 [-]: GETTABLE  R24 R24 K2   ; R24 := R24["mDirty"]
105 [-]: SETTABLE  R24 R4 K9    ; R24[R4] := nil
106 [-]: TFORLOOP  R1 2         ; R4,R5 :=  R1(R2,R3); if R4 ~= nil then begin PC = 6; R3 := R4 end
107 [-]: JMP       6            ; PC := 6
108 [-]: RETURN    R0 1         ; return 


; Function #42:
;
; Name:            
; Defined at line: 847
; #Upvalues:       0
; #Parameters:     1
; Is_vararg:       0
; Max Stack Size:  12

  1 [-]: GETTABLE  R1 R0 K0     ; R1 := R0["mBudget"]
  2 [-]: LE        0 R1 K1      ; if R1 > 0.000000 then PC := 5
  3 [-]: JMP       5            ; PC := 5
  4 [-]: RETURN    R0 1         ; return 
  5 [-]: GETTABLE  R2 R0 K2     ; R2 := R0["mValidationQueue"]
  6 [-]: GETTABLE  R3 R2 K3     ; R3 := R2["length"]
  7 [-]: LE        0 R3 K1      ; if R3 > 0.000000 then PC := 10
  8 [-]: JMP       10           ; PC := 10
  9 [-]: RETURN    R0 1         ; return 
 10 [-]: GETTABLE  R3 R0 K4     ; R3 := R0["mDebugProcessing"]
 11 [-]: TEST      R3 0         ; if not R3 then PC := 19
 12 [-]: JMP       19           ; PC := 19
 13 [-]: GETGLOBAL R3 K5        ; R3 := 0x3d106989
 14 [-]: LOADK     R4 K6        ; R4 := "processing valid queue  ("
 15 [-]: GETTABLE  R5 R2 K3     ; R5 := R2["length"]
 16 [-]: LOADK     R6 K7        ; R6 := " entries)."
 17 [-]: CONCAT    R4 R4 R6     ; R4 := R4 .. R5 .. R6
 18 [-]: CALL      R3 2 1       ; R3(R4)
 19 [-]: GETTABLE  R3 R0 K8     ; R3 := R0["mClock"]
 20 [-]: SELF      R4 R3 K9     ; R5 := R3; R4 := R3[0x36fcc811]
 21 [-]: CALL      R4 2 1       ; R4(R5)
 22 [-]: SELF      R4 R3 K10    ; R5 := R3; R4 := R3[0x44575710]
 23 [-]: CALL      R4 2 1       ; R4(R5)
 24 [-]: SELF      R4 R2 K11    ; R5 := R2; R4 := R2[0xc9c8bcdc]
 25 [-]: CALL      R4 2 2       ; R4 := R4(R5)
 26 [-]: TEST      R4 1         ; if R4 then PC := 31
 27 [-]: JMP       31           ; PC := 31
 28 [-]: SELF      R5 R3 K12    ; R6 := R3; R5 := R3[0xf33c42c5]
 29 [-]: CALL      R5 2 1       ; R5(R6)
 30 [-]: JMP       61           ; PC := 61
 31 [-]: GETGLOBAL R5 K13       ; R5 := 0x7b998233
 32 [-]: MOVE      R6 R4        ; R6 := R4
 33 [-]: CALL      R5 2 2       ; R5 := R5(R6)
 34 [-]: TEST      R5 1         ; if R5 then PC := 46
 35 [-]: JMP       46           ; PC := 46
 36 [-]: GETTABLE  R5 R0 K14    ; R5 := R0[0xd8625812]
 37 [-]: MOVE      R6 R4        ; R6 := R4
 38 [-]: CALL      R5 2 3       ; R5,R6 := R5(R6)
 39 [-]: TEST      R6 0         ; if not R6 then PC := 46
 40 [-]: JMP       46           ; PC := 46
 41 [-]: SELF      R7 R0 K15    ; R8 := R0; R7 := R0[0x8e4200f0]
 42 [-]: MOVE      R9 R5        ; R9 := R5
 43 [-]: MOVE      R10 R6       ; R10 := R6
 44 [-]: LOADBOOL  R11 1 0      ; R11 := true
 45 [-]: CALL      R7 5 1       ; R7(R8,R9,R10,R11)
 46 [-]: SELF      R7 R3 K12    ; R8 := R3; R7 := R3[0xf33c42c5]
 47 [-]: CALL      R7 2 1       ; R7(R8)
 48 [-]: SELF      R7 R3 K16    ; R8 := R3; R7 := R3[0xaef9485b]
 49 [-]: CALL      R7 2 2       ; R7 := R7(R8)
 50 [-]: MUL       R7 R7 K17    ; R7 := R7 * 1000000.000000
 51 [-]: LE        0 R1 R7      ; if R1 > R7 then PC := 22
 52 [-]: JMP       22           ; PC := 22
 53 [-]: GETTABLE  R7 R0 K4     ; R7 := R0["mDebugProcessing"]
 54 [-]: TEST      R7 0         ; if not R7 then PC := 61
 55 [-]: JMP       61           ; PC := 61
 56 [-]: GETGLOBAL R7 K5        ; R7 := 0x3d106989
 57 [-]: LOADK     R8 K18       ; R8 := "budget blown."
 58 [-]: CALL      R7 2 1       ; R7(R8)
 59 [-]: JMP       61           ; PC := 61
 60 [-]: JMP       22           ; PC := 22
 61 [-]: SELF      R7 R3 K16    ; R8 := R3; R7 := R3[0xaef9485b]
 62 [-]: CALL      R7 2 2       ; R7 := R7(R8)
 63 [-]: MUL       R7 R7 K17    ; R7 := R7 * 1000000.000000
 64 [-]: SUB       R8 R1 R7     ; R8 := R1 - R7
 65 [-]: SETTABLE  R0 K0 R8     ; R0["mBudget"] := R8
 66 [-]: RETURN    R0 1         ; return 


; Function #43:
;
; Name:            
; Defined at line: 892
; #Upvalues:       0
; #Parameters:     1
; Is_vararg:       0
; Max Stack Size:  12

  1 [-]: GETTABLE  R1 R0 K0     ; R1 := R0["mBudget"]
  2 [-]: LE        0 R1 K1      ; if R1 > 0.000000 then PC := 5
  3 [-]: JMP       5            ; PC := 5
  4 [-]: RETURN    R1 2         ; return R1
  5 [-]: GETTABLE  R2 R0 K2     ; R2 := R0["mCreationQueue"]
  6 [-]: GETTABLE  R3 R2 K3     ; R3 := R2["length"]
  7 [-]: LE        0 R3 K1      ; if R3 > 0.000000 then PC := 10
  8 [-]: JMP       10           ; PC := 10
  9 [-]: RETURN    R0 1         ; return 
 10 [-]: GETTABLE  R3 R0 K4     ; R3 := R0["mClock"]
 11 [-]: SELF      R4 R3 K5     ; R5 := R3; R4 := R3[0x36fcc811]
 12 [-]: CALL      R4 2 1       ; R4(R5)
 13 [-]: SELF      R4 R3 K6     ; R5 := R3; R4 := R3[0x44575710]
 14 [-]: CALL      R4 2 1       ; R4(R5)
 15 [-]: SELF      R4 R2 K7     ; R5 := R2; R4 := R2[0xc9c8bcdc]
 16 [-]: CALL      R4 2 2       ; R4 := R4(R5)
 17 [-]: TEST      R4 1         ; if R4 then PC := 22
 18 [-]: JMP       22           ; PC := 22
 19 [-]: SELF      R5 R3 K8     ; R6 := R3; R5 := R3[0xf33c42c5]
 20 [-]: CALL      R5 2 1       ; R5(R6)
 21 [-]: JMP       59           ; PC := 59
 22 [-]: GETTABLE  R5 R0 K9     ; R5 := R0["mActiveCellTable"]
 23 [-]: GETTABLE  R5 R5 K10    ; R5 := R5["mCells"]
 24 [-]: GETTABLE  R6 R4 K11    ; R6 := R4["cellId"]
 25 [-]: GETTABLE  R5 R5 R6     ; R5 := R5[R6]
 26 [-]: TEST      R5 0         ; if not R5 then PC := 44
 27 [-]: JMP       44           ; PC := 44
 28 [-]: GETTABLE  R5 R0 K12    ; R5 := R0[0x67d4920e]
 29 [-]: MOVE      R6 R4        ; R6 := R4
 30 [-]: CALL      R5 2 3       ; R5,R6 := R5(R6)
 31 [-]: TEST      R6 0         ; if not R6 then PC := 44
 32 [-]: JMP       44           ; PC := 44
 33 [-]: GETTABLE  R7 R4 K13    ; R7 := R4["permanent"]
 34 [-]: TEST      R7 0         ; if not R7 then PC := 39
 35 [-]: JMP       39           ; PC := 39
 36 [-]: GETTABLE  R7 R4 K13    ; R7 := R4["permanent"]
 37 [-]: SETTABLE  R6 K13 R7    ; R6["permanent"] := R7
 38 [-]: SETTABLE  R4 K14 K15   ; R4["permanentlyCreated"] := true
 39 [-]: SELF      R7 R0 K16    ; R8 := R0; R7 := R0[0x8a2a6dbd]
 40 [-]: MOVE      R9 R5        ; R9 := R5
 41 [-]: MOVE      R10 R6       ; R10 := R6
 42 [-]: GETTABLE  R11 R4 K17   ; R11 := R4["id"]
 43 [-]: CALL      R7 5 1       ; R7(R8,R9,R10,R11)
 44 [-]: SELF      R7 R3 K8     ; R8 := R3; R7 := R3[0xf33c42c5]
 45 [-]: CALL      R7 2 1       ; R7(R8)
 46 [-]: SELF      R7 R3 K18    ; R8 := R3; R7 := R3[0xaef9485b]
 47 [-]: CALL      R7 2 2       ; R7 := R7(R8)
 48 [-]: MUL       R7 R7 K19    ; R7 := R7 * 1000000.000000
 49 [-]: LE        0 R1 R7      ; if R1 > R7 then PC := 13
 50 [-]: JMP       13           ; PC := 13
 51 [-]: GETTABLE  R7 R0 K20    ; R7 := R0["mDebugProcessing"]
 52 [-]: TEST      R7 0         ; if not R7 then PC := 59
 53 [-]: JMP       59           ; PC := 59
 54 [-]: GETGLOBAL R7 K21       ; R7 := 0x3d106989
 55 [-]: LOADK     R8 K22       ; R8 := "budget blown."
 56 [-]: CALL      R7 2 1       ; R7(R8)
 57 [-]: JMP       59           ; PC := 59
 58 [-]: JMP       13           ; PC := 13
 59 [-]: SELF      R7 R3 K18    ; R8 := R3; R7 := R3[0xaef9485b]
 60 [-]: CALL      R7 2 2       ; R7 := R7(R8)
 61 [-]: MUL       R7 R7 K19    ; R7 := R7 * 1000000.000000
 62 [-]: SUB       R8 R1 R7     ; R8 := R1 - R7
 63 [-]: SETTABLE  R0 K0 R8     ; R0["mBudget"] := R8
 64 [-]: RETURN    R0 1         ; return 


; Function #44:
;
; Name:            
; Defined at line: 937
; #Upvalues:       0
; #Parameters:     1
; Is_vararg:       0
; Max Stack Size:  8

  1 [-]: GETTABLE  R1 R0 K0     ; R1 := R0["mBudget"]
  2 [-]: LE        0 R1 K1      ; if R1 > 0.000000 then PC := 5
  3 [-]: JMP       5            ; PC := 5
  4 [-]: RETURN    R0 1         ; return 
  5 [-]: GETTABLE  R2 R0 K2     ; R2 := R0["mDeletionQueue"]
  6 [-]: GETTABLE  R3 R2 K3     ; R3 := R2["length"]
  7 [-]: LE        0 R3 K1      ; if R3 > 0.000000 then PC := 10
  8 [-]: JMP       10           ; PC := 10
  9 [-]: RETURN    R0 1         ; return 
 10 [-]: GETTABLE  R3 R0 K4     ; R3 := R0["mClock"]
 11 [-]: SELF      R4 R3 K5     ; R5 := R3; R4 := R3[0x36fcc811]
 12 [-]: CALL      R4 2 1       ; R4(R5)
 13 [-]: SELF      R4 R3 K6     ; R5 := R3; R4 := R3[0x44575710]
 14 [-]: CALL      R4 2 1       ; R4(R5)
 15 [-]: SELF      R4 R2 K7     ; R5 := R2; R4 := R2[0xc9c8bcdc]
 16 [-]: CALL      R4 2 2       ; R4 := R4(R5)
 17 [-]: TEST      R4 1         ; if R4 then PC := 22
 18 [-]: JMP       22           ; PC := 22
 19 [-]: SELF      R5 R3 K8     ; R6 := R3; R5 := R3[0xf33c42c5]
 20 [-]: CALL      R5 2 1       ; R5(R6)
 21 [-]: JMP       41           ; PC := 41
 22 [-]: GETTABLE  R5 R0 K9     ; R5 := R0[0x4099a2e1]
 23 [-]: MOVE      R6 R4        ; R6 := R4
 24 [-]: LOADBOOL  R7 0 0       ; R7 := false
 25 [-]: CALL      R5 3 1       ; R5(R6,R7)
 26 [-]: SELF      R5 R3 K8     ; R6 := R3; R5 := R3[0xf33c42c5]
 27 [-]: CALL      R5 2 1       ; R5(R6)
 28 [-]: SELF      R5 R3 K10    ; R6 := R3; R5 := R3[0xaef9485b]
 29 [-]: CALL      R5 2 2       ; R5 := R5(R6)
 30 [-]: MUL       R5 R5 K11    ; R5 := R5 * 1000000.000000
 31 [-]: LE        0 R1 R5      ; if R1 > R5 then PC := 13
 32 [-]: JMP       13           ; PC := 13
 33 [-]: GETTABLE  R5 R0 K12    ; R5 := R0["mDebugProcessing"]
 34 [-]: TEST      R5 0         ; if not R5 then PC := 41
 35 [-]: JMP       41           ; PC := 41
 36 [-]: GETGLOBAL R5 K13       ; R5 := 0x3d106989
 37 [-]: LOADK     R6 K14       ; R6 := "budget blown."
 38 [-]: CALL      R5 2 1       ; R5(R6)
 39 [-]: JMP       41           ; PC := 41
 40 [-]: JMP       13           ; PC := 13
 41 [-]: SELF      R5 R3 K10    ; R6 := R3; R5 := R3[0xaef9485b]
 42 [-]: CALL      R5 2 2       ; R5 := R5(R6)
 43 [-]: MUL       R5 R5 K11    ; R5 := R5 * 1000000.000000
 44 [-]: SUB       R6 R1 R5     ; R6 := R1 - R5
 45 [-]: SETTABLE  R0 K0 R6     ; R0["mBudget"] := R6
 46 [-]: RETURN    R0 1         ; return 


; Function #45:
;
; Name:            
; Defined at line: 972
; #Upvalues:       5
; #Parameters:     1
; Is_vararg:       0
; Max Stack Size:  3

  1 [-]: SETTABLE  R0 K0 K1     ; R0["mBudget"] := 200.000000
  2 [-]: GETUPVAL  R1 U0        ; R1 := U0
  3 [-]: MOVE      R2 R0        ; R2 := R0
  4 [-]: CALL      R1 2 1       ; R1(R2)
  5 [-]: GETUPVAL  R1 U1        ; R1 := U1
  6 [-]: MOVE      R2 R0        ; R2 := R0
  7 [-]: CALL      R1 2 1       ; R1(R2)
  8 [-]: GETUPVAL  R1 U2        ; R1 := U2
  9 [-]: MOVE      R2 R0        ; R2 := R0
 10 [-]: CALL      R1 2 1       ; R1(R2)
 11 [-]: GETUPVAL  R1 U3        ; R1 := U3
 12 [-]: MOVE      R2 R0        ; R2 := R0
 13 [-]: CALL      R1 2 1       ; R1(R2)
 14 [-]: GETUPVAL  R1 U4        ; R1 := U4
 15 [-]: MOVE      R2 R0        ; R2 := R0
 16 [-]: CALL      R1 2 1       ; R1(R2)
 17 [-]: RETURN    R0 1         ; return 


; Function #46:
;
; Name:            
; Defined at line: 981
; #Upvalues:       0
; #Parameters:     2
; Is_vararg:       0
; Max Stack Size:  2

  1 [-]: SETTABLE  R0 K0 R1     ; R0["mGenerateForAllPlayers"] := R1
  2 [-]: RETURN    R0 1         ; return 


; Function #47:
;
; Name:            
; Defined at line: 985
; #Upvalues:       0
; #Parameters:     2
; Is_vararg:       0
; Max Stack Size:  2

  1 [-]: SETTABLE  R0 K0 R1     ; R0["mDebugActiveCells"] := R1
  2 [-]: RETURN    R0 1         ; return 


; Function #48:
;
; Name:            
; Defined at line: 989
; #Upvalues:       0
; #Parameters:     2
; Is_vararg:       0
; Max Stack Size:  2

  1 [-]: SETTABLE  R0 K0 R1     ; R0["mDebugResourcePlacement"] := R1
  2 [-]: RETURN    R0 1         ; return 


; Function #49:
;
; Name:            
; Defined at line: 993
; #Upvalues:       3
; #Parameters:     7
; Is_vararg:       0
; Max Stack Size:  12

  1 [-]: GETGLOBAL R7 K0        ; R7 := 0x2296a8fd
  2 [-]: NEWTABLE  R8 0 0       ; R8 := {}
  3 [-]: GETUPVAL  R9 U0        ; R9 := U0
  4 [-]: CALL      R7 3 2       ; R7 := R7(R8,R9)
  5 [-]: SELF      R8 R7 K1     ; R9 := R7; R8 := R7[0xcbf89887]
  6 [-]: MOVE      R10 R0       ; R10 := R0
  7 [-]: MOVE      R11 R1       ; R11 := R1
  8 [-]: CALL      R8 4 1       ; R8(R9,R10,R11)
  9 [-]: GETUPVAL  R8 U1        ; R8 := U1
 10 [-]: MOVE      R9 R7        ; R9 := R7
 11 [-]: CALL      R8 2 1       ; R8(R9)
 12 [-]: SETTABLE  R7 K2 R2     ; R7["mEntryEquals"] := R2
 13 [-]: SETTABLE  R7 K3 R3     ; R7["mEntryCleanup"] := R3
 14 [-]: SETTABLE  R7 K4 R4     ; R7["mGetCreationInfo"] := R4
 15 [-]: SETTABLE  R7 K5 R5     ; R7["mCreateEntity"] := R5
 16 [-]: SETTABLE  R7 K6 R6     ; R7["mValidateEntity"] := R6
 17 [-]: GETUPVAL  R8 U2        ; R8 := U2
 18 [-]: GETTABLE  R8 R8 K8     ; R8 := R8[0x7d4d5d68]
 19 [-]: CALL      R8 1 2       ; R8 := R8()
 20 [-]: SETTABLE  R7 K7 R8     ; R7["mValidationQueue"] := R8
 21 [-]: GETUPVAL  R8 U2        ; R8 := U2
 22 [-]: GETTABLE  R8 R8 K8     ; R8 := R8[0x7d4d5d68]
 23 [-]: CALL      R8 1 2       ; R8 := R8()
 24 [-]: SETTABLE  R7 K9 R8     ; R7["mCreationQueue"] := R8
 25 [-]: GETUPVAL  R8 U2        ; R8 := U2
 26 [-]: GETTABLE  R8 R8 K8     ; R8 := R8[0x7d4d5d68]
 27 [-]: CALL      R8 1 2       ; R8 := R8()
 28 [-]: SETTABLE  R7 K10 R8    ; R7["mDeletionQueue"] := R8
 29 [-]: GETGLOBAL R8 K12       ; R8 := 0x910f4761
 30 [-]: CALL      R8 1 2       ; R8 := R8()
 31 [-]: SETTABLE  R7 K11 R8    ; R7["mClock"] := R8
 32 [-]: RETURN    R7 2         ; return R7
 33 [-]: RETURN    R0 1         ; return 


