; Name:            
; Defined at line: 1
; #Upvalues:       0
; #Parameters:     0
; Is_vararg:       1
; Max Stack Size:  33

       1 [-]: GETIMPORT R0 1; var0 = 0x0469F296
       2 [-]: LOADK R1 K2  ; var1 = "RiotPercent"
       3 [-]: CALL R0 2 2  ; var0 = var0(var1)
       4 [-]: GETIMPORT R1 1; var1 = 0x0469F296
       5 [-]: LOADK R2 K3  ; var2 = "RiotMoaBonus"
       6 [-]: CALL R1 2 2  ; var1 = var1(var2)
       7 [-]: GETIMPORT R2 1; var2 = 0x0469F296
       8 [-]: LOADK R3 K4  ; var3 = "RiotMoaEventScore"
       9 [-]: CALL R2 2 2  ; var2 = var2(var3)
      10 [-]: GETIMPORT R3 1; var3 = 0x0469F296
      11 [-]: LOADK R4 K5  ; var4 = "RiotShouldPause"
      12 [-]: CALL R3 2 2  ; var3 = var3(var4)
      13 [-]: LOADNIL R4   ; var4 = nil
      14 [-]: LOADNIL R5   ; var5 = nil
      15 [-]: NEWTABLE R6 0 0; var6 = {}
      16 [-]: LOADN R7 0   ; var7 = 0
      17 [-]: LOADN R8 0   ; var8 = 0
      18 [-]: GETIMPORT R9 7; var9 = 0x7ED0A956
      19 [-]: LOADK R10 K8 ; var10 = "/Lotus/Sounds/Dialog/RiotMoaEvent/DOfferingTakenNefAnyo"
      20 [-]: CALL R9 2 2  ; var9 = var9(var10)
      21 [-]: GETIMPORT R10 7; var10 = 0x7ED0A956
      22 [-]: LOADK R11 K9 ; var11 = "/Lotus/Sounds/Dialog/RiotMoaEvent/DTransferFundsLotus"
      23 [-]: CALL R10 2 2 ; var10 = var10(var11)
      24 [-]: GETIMPORT R11 7; var11 = 0x7ED0A956
      25 [-]: LOADK R12 K10; var12 = "/Lotus/Sounds/Dialog/RiotMoaEvent/DVerifyFundsLotus"
      26 [-]: CALL R11 2 2 ; var11 = var11(var12)
      27 [-]: GETIMPORT R12 7; var12 = 0x7ED0A956
      28 [-]: LOADK R13 K11; var13 = "/Lotus/Sounds/Dialog/RiotMoaEvent/DOfferingReceivedNefAnyo"
      29 [-]: CALL R12 2 2 ; var12 = var12(var13)
      30 [-]: GETIMPORT R13 7; var13 = 0x7ED0A956
      31 [-]: LOADK R14 K12; var14 = "/Lotus/Sounds/Dialog/RiotMoaEvent/DHackFailLotus"
      32 [-]: CALL R13 2 2 ; var13 = var13(var14)
      33 [-]: GETIMPORT R14 7; var14 = 0x7ED0A956
      34 [-]: LOADK R15 K13; var15 = "/Lotus/Sounds/Dialog/RiotMoaEvent/DHackSuccessLotus"
      35 [-]: CALL R14 2 2 ; var14 = var14(var15)
      36 [-]: GETIMPORT R15 7; var15 = 0x7ED0A956
      37 [-]: LOADK R16 K14; var16 = "/Lotus/Sounds/Dialog/RiotMoaEvent/DHackSuccessNefAnyo"
      38 [-]: CALL R15 2 2 ; var15 = var15(var16)
      39 [-]: GETIMPORT R16 7; var16 = 0x7ED0A956
      40 [-]: LOADK R17 K15; var17 = "/Lotus/Sounds/Dialog/RiotMoaEvent/DPreachGenericNefAnyo"
      41 [-]: CALL R16 2 2 ; var16 = var16(var17)
      42 [-]: GETIMPORT R17 7; var17 = 0x7ED0A956
      43 [-]: LOADK R18 K16; var18 = "/Lotus/Sounds/Dialog/RiotMoaEvent/DMissionStartLotus"
      44 [-]: CALL R17 2 2 ; var17 = var17(var18)
      45 [-]: GETIMPORT R18 7; var18 = 0x7ED0A956
      46 [-]: LOADK R19 K17; var19 = "/Lotus/Sounds/Dialog/RiotMoaEvent/DPrematureLotus"
      47 [-]: CALL R18 2 2 ; var18 = var18(var19)
      48 [-]: LOADN R19 0  ; var19 = 0
      49 [-]: GETIMPORT R20 7; var20 = 0x7ED0A956
      50 [-]: LOADK R21 K18; var21 = "/Lotus/Types/Enemies/Corpus/BipedRobot/AIWeek/RiotBipedBaseAvatar"
      51 [-]: CALL R20 2 2 ; var20 = var20(var21)
      52 [-]: LOADNIL R21  ; var21 = nil
      53 [-]: GETIMPORT R22 20; var22 = 0x2D0FAD09
      54 [-]: LOADK R23 K21; var23 = "EE.Interface.Utilities"
      55 [-]: CALL R22 2 2 ; var22 = var22(var23)
      56 [-]: DUPTABLE R23 25; 
      57 [-]: NEWTABLE R24 0 4; var24 = {}
      58 [-]: LOADN R25 60 ; var25 = 60
      59 [-]: LOADN R26 105; var26 = 105
      60 [-]: LOADN R27 135; var27 = 135
      61 [-]: LOADN R28 165; var28 = 165
      62 [-]: SETLIST R24 R25 4 [1]; var24[1] = var25; var24[2] = var26; var24[3] = var27; var24[4] = var28; var24[5] = var29; 
      63 [-]: SETTABLEKS R24 R23 K22; var24["SMALL"] = var23
      64 [-]: NEWTABLE R24 0 4; var24 = {}
      65 [-]: LOADN R25 120; var25 = 120
      66 [-]: LOADN R26 180; var26 = 180
      67 [-]: LOADN R27 210; var27 = 210
      68 [-]: LOADN R28 240; var28 = 240
      69 [-]: SETLIST R24 R25 4 [1]; var24[1] = var25; var24[2] = var26; var24[3] = var27; var24[4] = var28; var24[5] = var29; 
      70 [-]: SETTABLEKS R24 R23 K23; var24["MEDIUM"] = var23
      71 [-]: NEWTABLE R24 0 4; var24 = {}
      72 [-]: LOADN R25 180; var25 = 180
      73 [-]: LOADN R26 300; var26 = 300
      74 [-]: LOADN R27 360; var27 = 360
      75 [-]: LOADN R28 420; var28 = 420
      76 [-]: SETLIST R24 R25 4 [1]; var24[1] = var25; var24[2] = var26; var24[3] = var27; var24[4] = var28; var24[5] = var29; 
      77 [-]: SETTABLEKS R24 R23 K24; var24["LARGE"] = var23
      78 [-]: NEWCLOSURE R24 P0; 
      79 [-]: CAPTURE REF R21; 
      80 [-]: NEWCLOSURE R25 P1; 
      81 [-]: CAPTURE REF R5; 
      82 [-]: NEWCLOSURE R26 P2; 
      83 [-]: CAPTURE VAL R6; 
      84 [-]: CAPTURE VAL R24; 
      85 [-]: CAPTURE REF R4; 
      86 [-]: CAPTURE REF R7; 
      87 [-]: NEWCLOSURE R27 P3; 
      88 [-]: CAPTURE REF R5; 
      89 [-]: CAPTURE REF R21; 
      90 [-]: CAPTURE REF R4; 
      91 [-]: CAPTURE VAL R20; 
      92 [-]: CAPTURE REF R8; 
      93 [-]: NEWCLOSURE R28 P4; 
      94 [-]: CAPTURE REF R4; 
      95 [-]: NEWCLOSURE R29 P5; 
      96 [-]: CAPTURE REF R5; 
      97 [-]: CAPTURE VAL R0; 
      98 [-]: CAPTURE VAL R27; 
      99 [-]: CAPTURE REF R4; 
     100 [-]: CAPTURE VAL R26; 
     101 [-]: CAPTURE VAL R3; 
     102 [-]: CAPTURE VAL R22; 
     103 [-]: CAPTURE REF R19; 
     104 [-]: CAPTURE VAL R16; 
     105 [-]: CAPTURE VAL R17; 
     106 [-]: DUPCLOSURE R30 K26; 
     107 [-]: CAPTURE VAL R23; 
     108 [-]: NEWCLOSURE R31 P7; 
     109 [-]: CAPTURE REF R5; 
     110 [-]: CAPTURE VAL R1; 
     111 [-]: NEWCLOSURE R32 P8; 
     112 [-]: CAPTURE REF R4; 
     113 [-]: CAPTURE VAL R20; 
     114 [-]: CAPTURE REF R8; 
     115 [-]: CAPTURE REF R5; 
     116 [-]: CAPTURE VAL R25; 
     117 [-]: CAPTURE VAL R6; 
     118 [-]: CAPTURE REF R7; 
     119 [-]: CAPTURE VAL R30; 
     120 [-]: CAPTURE VAL R9; 
     121 [-]: CAPTURE VAL R27; 
     122 [-]: CAPTURE VAL R10; 
     123 [-]: CAPTURE VAL R29; 
     124 [-]: CAPTURE VAL R18; 
     125 [-]: CAPTURE VAL R11; 
     126 [-]: CAPTURE VAL R24; 
     127 [-]: CAPTURE VAL R0; 
     128 [-]: CAPTURE VAL R1; 
     129 [-]: CAPTURE VAL R2; 
     130 [-]: CAPTURE VAL R14; 
     131 [-]: CAPTURE VAL R15; 
     132 [-]: CAPTURE VAL R12; 
     133 [-]: CAPTURE VAL R13; 
     134 [-]: SETGLOBAL R32 K27; "Start" = var32
     135 [-]: CLOSEUPVALS R4; 
     136 [-]: RETURN R0 0  ; 


; Name:            
; Defined at line: 38
; #Upvalues:       1
; #Parameters:     1
; Is_vararg:       0
; Max Stack Size:  8

       0 [-]: GETUPVAL R2 0; var2 = upvalues[0]
       1 [-]: FASTCALL1 64 R2 L0; 
       2 [-]: GETIMPORT R1 1; var1 = 0x7B998233
       3 [-]: CALL R1 2 2  ; var1 = var1(var2)
L 0:   4 [-]: JUMPIFNOT R1 L1; goto L1 if not var1
       5 [-]: GETIMPORT R1 3; var1 = 0x89326C93
       6 [-]: NAMECALL R1 R1 K4; var2 = var1; var1 = var1[0x7D108DDB]
       7 [-]: CALL R1 2 2  ; var1 = var1(var2)
       8 [-]: SETUPVAL R1 0; upvalues[1] = var0
L 1:   9 [-]: GETIMPORT R1 6; var1 = 0xC8802016
      10 [-]: GETUPVAL R2 0; var2 = upvalues[0]
      11 [-]: CALL R1 2 4  ; var1, var2, var3 = var1(var2)
      12 [-]: FORGPREP_INEXT R1 L4; 
L 2:  13 [-]: FASTCALL1 64 R5 L3; 
      14 [-]: MOVE R7 R5   ; var7 = var5
      15 [-]: GETIMPORT R6 1; var6 = 0x7B998233
      16 [-]: CALL R6 2 2  ; var6 = var6(var7)
L 3:  17 [-]: JUMPIF R6 L4 ; goto L4 if var6
      18 [-]: NAMECALL R6 R5 K7; var7 = var5; var6 = var5[0x5CA33548]
      19 [-]: CALL R6 2 2  ; var6 = var6(var7)
      20 [-]: JUMPIFNOTEQ R6 R0 L4; goto L4 if var6 ~= var132387
      21 [-]: RETURN R5 1  ; 
L 4:  22 [-]: FORGLOOP R1 L2 2 [inext]; 
      23 [-]: LOADNIL R1   ; var1 = nil
      24 [-]: RETURN R1 1  ; 


; Name:            
; Defined at line: 52
; #Upvalues:       1
; #Parameters:     1
; Is_vararg:       0
; Max Stack Size:  12

       0 [-]: LOADN R1 0   ; var1 = 0
       1 [-]: LOADNIL R2   ; var2 = nil
       2 [-]: NAMECALL R3 R0 K0; var4 = var0; var3 = var0[0xDE321E6F]
       3 [-]: CALL R3 2 2  ; var3 = var3(var4)
       4 [-]: LOADN R6 0   ; var6 = 0
       5 [-]: LOADN R9 0   ; var9 = 0
       6 [-]: NAMECALL R7 R3 K2; var8 = var3; var7 = var3[0x4056D183]
       7 [-]: CALL R7 3 2  ; var7 = var7(var8, var9)
       8 [-]: SUBK R4 R7 K1; var4 = var7 - 1
       9 [-]: LOADN R5 1   ; var5 = 1
      10 [-]: FORNPREP R4 L5; nforprep start - [escape at L5] -- var4 = iterator
L 0:  11 [-]: MOVE R9 R6   ; var9 = var6
      12 [-]: LOADN R10 0  ; var10 = 0
      13 [-]: NAMECALL R7 R3 K3; var8 = var3; var7 = var3[0xE6E56442]
      14 [-]: CALL R7 4 2  ; var7 = var7(var8, var9, var10)
      15 [-]: FASTCALL1 64 R7 L1; 
      16 [-]: MOVE R9 R7   ; var9 = var7
      17 [-]: GETIMPORT R8 5; var8 = 0x7B998233
      18 [-]: CALL R8 2 2  ; var8 = var8(var9)
L 1:  19 [-]: JUMPIF R8 L4 ; goto L4 if var8
      20 [-]: GETIMPORT R10 7; var10 = 0x7ED0A956
      21 [-]: LOADK R11 K8 ; var11 = "/Lotus/Types/Restoratives/Consumable/CreditChipLarge"
      22 [-]: CALL R10 2 0 ; var10, ... = var10(var11)
      23 [-]: NAMECALL R8 R7 K9; var9 = var7; var8 = var7[0xF2DEAF69]
      24 [-]: CALL R8 0 2  ; var8 = var8(var9, ...)
      25 [-]: JUMPIFNOT R8 L2; goto L2 if not var8
      26 [-]: LOADK R8 K10 ; var8 = 100000
      27 [-]: JUMPIFNOTLT R1 R8 L4; goto L4 if var1 >= var655687
      28 [-]: LOADK R1 K10 ; var1 = 100000
      29 [-]: MOVE R2 R7   ; var2 = var7
      30 [-]: JUMP L4      ; goto L4
L 2:  31 [-]: GETIMPORT R10 7; var10 = 0x7ED0A956
      32 [-]: LOADK R11 K11; var11 = "/Lotus/Types/Restoratives/Consumable/CreditChipMedium"
      33 [-]: CALL R10 2 0 ; var10, ... = var10(var11)
      34 [-]: NAMECALL R8 R7 K9; var9 = var7; var8 = var7[0xF2DEAF69]
      35 [-]: CALL R8 0 2  ; var8 = var8(var9, ...)
      36 [-]: JUMPIFNOT R8 L3; goto L3 if not var8
      37 [-]: LOADN R8 10000; var8 = 10000
      38 [-]: JUMPIFNOTLT R1 R8 L4; goto L4 if var1 >= var655360304
      39 [-]: LOADN R1 10000; var1 = 10000
      40 [-]: MOVE R2 R7   ; var2 = var7
      41 [-]: JUMP L4      ; goto L4
L 3:  42 [-]: GETIMPORT R10 7; var10 = 0x7ED0A956
      43 [-]: LOADK R11 K12; var11 = "/Lotus/Types/Restoratives/Consumable/CreditChipSmall"
      44 [-]: CALL R10 2 0 ; var10, ... = var10(var11)
      45 [-]: NAMECALL R8 R7 K9; var9 = var7; var8 = var7[0xF2DEAF69]
      46 [-]: CALL R8 0 2  ; var8 = var8(var9, ...)
      47 [-]: JUMPIFNOT R8 L4; goto L4 if not var8
      48 [-]: LOADN R8 1000; var8 = 1000
      49 [-]: JUMPIFNOTLT R1 R8 L4; goto L4 if var1 >= var65536304
      50 [-]: LOADN R1 1000; var1 = 1000
      51 [-]: MOVE R2 R7   ; var2 = var7
L 4:  52 [-]: FORNLOOP R4 L0; nforloop end - iterate + goto L0
L 5:  53 [-]: NAMECALL R4 R0 K13; var5 = var0; var4 = var0[0xA5E492D4]
      54 [-]: CALL R4 2 2  ; var4 = var4(var5)
      55 [-]: JUMPIFNOT R4 L6; goto L6 if not var4
      56 [-]: LOADN R4 0   ; var4 = 0
      57 [-]: JUMPIFNOTLT R4 R1 L6; goto L6 if var4 >= var1084
      58 [-]: GETUPVAL R4 0; var4 = upvalues[0]
      59 [-]: LOADB R6 1   ; var6 = true
      60 [-]: NAMECALL R4 R4 K14; var5 = var4; var4 = var4[0xEBE099B5]
      61 [-]: CALL R4 3 1  ; var4(var5, var6)
L 6:  62 [-]: RETURN R1 2  ; 


; Name:            
; Defined at line: 85
; #Upvalues:       4
; #Parameters:     1
; Is_vararg:       0
; Max Stack Size:  13

       0 [-]: LOADN R1 0   ; var1 = 0
       1 [-]: LOADN R2 0   ; var2 = 0
       2 [-]: GETIMPORT R3 1; var3 = 0xC8802016
       3 [-]: GETUPVAL R4 0; var4 = upvalues[0]
       4 [-]: CALL R3 2 4  ; var3, var4, var5 = var3(var4)
       5 [-]: FORGPREP_INEXT R3 L4; 
L 0:   6 [-]: GETUPVAL R8 1; var8 = upvalues[1]
       7 [-]: GETTABLEKS R9 R7 K2; var9 = var7["playerName"]
       8 [-]: CALL R8 2 2  ; var8 = var8(var9)
       9 [-]: FASTCALL1 64 R8 L1; 
      10 [-]: MOVE R10 R8  ; var10 = var8
      11 [-]: GETIMPORT R9 4; var9 = 0x7B998233
      12 [-]: CALL R9 2 2  ; var9 = var9(var10)
L 1:  13 [-]: JUMPIF R9 L3 ; goto L3 if var9
      14 [-]: NAMECALL R9 R8 K5; var10 = var8; var9 = var8[0xBB610E5B]
      15 [-]: CALL R9 2 2  ; var9 = var9(var10)
      16 [-]: FASTCALL1 64 R9 L2; 
      17 [-]: MOVE R11 R9  ; var11 = var9
      18 [-]: GETIMPORT R10 4; var10 = 0x7B998233
      19 [-]: CALL R10 2 2 ; var10 = var10(var11)
L 2:  20 [-]: JUMPIF R10 L4; goto L4 if var10
      21 [-]: GETUPVAL R12 2; var12 = upvalues[2]
      22 [-]: NAMECALL R10 R9 K6; var11 = var9; var10 = var9[0xBEBAD19F]
      23 [-]: CALL R10 3 2 ; var10 = var10(var11, var12)
      24 [-]: LOADN R11 20 ; var11 = 20
      25 [-]: JUMPIFNOTLT R10 R11 L4; goto L4 if var10 >= var117506312
      26 [-]: ADDK R1 R1 K7; var1 = var1 + 1
      27 [-]: JUMP L4      ; goto L4
L 3:  28 [-]: ADDK R2 R2 K7; var2 = var2 + 1
L 4:  29 [-]: FORGLOOP R3 L0 2 [inext]; 
      30 [-]: GETUPVAL R6 0; var6 = upvalues[0]
      31 [-]: LENGTH R5 R6 ; var5 = #var6
      32 [-]: SUB R4 R5 R2 ; var4 = var5 - var2
           34 [-]: SETUPVAL R3 3; upvalues[3] = var3
      35 [-]: GETUPVAL R3 3; var3 = upvalues[3]
      36 [-]: JUMPIFNOTLE R3 R1 L5; goto L5 if var3 > var328496
      37 [-]: LOADN R3 5   ; var3 = 5
      38 [-]: JUMPIFNOTLT R0 R3 L5; goto L5 if var0 >= var774
      39 [-]: LOADB R3 0   ; var3 = false
      40 [-]: RETURN R3 1  ; 
L 5:  41 [-]: LOADB R3 1   ; var3 = true
      42 [-]: RETURN R3 1  ; 


; Name:            
; Defined at line: 109
; #Upvalues:       5
; #Parameters:     0
; Is_vararg:       0
; Max Stack Size:  6

       0 [-]: LOADB R0 0   ; var0 = false
L 0:   1 [-]: GETUPVAL R2 0; var2 = upvalues[0]
       2 [-]: FASTCALL1 64 R2 L1; 
       3 [-]: GETIMPORT R1 1; var1 = 0x7B998233
       4 [-]: CALL R1 2 2  ; var1 = var1(var2)
L 1:   5 [-]: JUMPIFNOT R1 L2; goto L2 if not var1
       6 [-]: GETIMPORT R1 3; var1 = 0xCBD666E1
       7 [-]: LOADN R2 0   ; var2 = 0
       8 [-]: CALL R1 2 1  ; var1(var2)
       9 [-]: GETIMPORT R1 5; var1 = 0xBE190284
      10 [-]: SETUPVAL R1 0; upvalues[1] = var0
      11 [-]: LOADNIL R1   ; var1 = nil
      12 [-]: SETUPVAL R1 1; upvalues[1] = var1
      13 [-]: LOADB R0 1   ; var0 = true
      14 [-]: GETIMPORT R1 7; var1 = 0x3D106989
      15 [-]: LOADK R2 K8  ; var2 = "Migration, waiting for gameRules"
      16 [-]: CALL R1 2 1  ; var1(var2)
      17 [-]: JUMPBACK L0  ; goto L0
L 2:  18 [-]: JUMPIFNOT R0 L9; goto L9 if not var0
L 3:  19 [-]: GETIMPORT R2 11; var2 = _T["ShowImpactMessage"]
      20 [-]: FASTCALL1 64 R2 L4; 
      21 [-]: GETIMPORT R1 1; var1 = 0x7B998233
      22 [-]: CALL R1 2 2  ; var1 = var1(var2)
L 4:  23 [-]: JUMPIFNOT R1 L5; goto L5 if not var1
      24 [-]: GETIMPORT R1 3; var1 = 0xCBD666E1
      25 [-]: LOADN R2 0   ; var2 = 0
      26 [-]: CALL R1 2 1  ; var1(var2)
      27 [-]: JUMPBACK L3  ; goto L3
L 5:  28 [-]: GETUPVAL R2 2; var2 = upvalues[2]
      29 [-]: FASTCALL1 64 R2 L6; 
      30 [-]: GETIMPORT R1 1; var1 = 0x7B998233
      31 [-]: CALL R1 2 2  ; var1 = var1(var2)
L 6:  32 [-]: JUMPIFNOT R1 L9; goto L9 if not var1
      33 [-]: GETIMPORT R1 3; var1 = 0xCBD666E1
      34 [-]: LOADN R2 0   ; var2 = 0
      35 [-]: CALL R1 2 1  ; var1(var2)
      36 [-]: GETIMPORT R1 13; var1 = 0x89326C93
      37 [-]: GETUPVAL R3 3; var3 = upvalues[3]
      38 [-]: GETIMPORT R4 15; var4 = 0xA421AF95
      39 [-]: CALL R4 1 2  ; var4 = var4()
      40 [-]: LOADK R5 K16 ; var5 = 3.4028234663852886e+38
      41 [-]: NAMECALL R1 R1 K17; var2 = var1; var1 = var1[0x4E5939A5]
      42 [-]: CALL R1 5 2  ; var1 = var1(var2, var3, var4, var5)
      43 [-]: SETUPVAL R1 2; upvalues[1] = var2
      44 [-]: GETUPVAL R2 2; var2 = upvalues[2]
      45 [-]: FASTCALL1 64 R2 L7; 
      46 [-]: GETIMPORT R1 1; var1 = 0x7B998233
      47 [-]: CALL R1 2 2  ; var1 = var1(var2)
L 7:  48 [-]: JUMPIF R1 L8 ; goto L8 if var1
      49 [-]: GETIMPORT R1 13; var1 = 0x89326C93
      50 [-]: NAMECALL R1 R1 K18; var2 = var1; var1 = var1[0x18D05D30]
      51 [-]: CALL R1 2 2  ; var1 = var1(var2)
      52 [-]: JUMPIFNOT R1 L8; goto L8 if not var1
      53 [-]: GETUPVAL R1 2; var1 = upvalues[2]
      54 [-]: NAMECALL R1 R1 K19; var2 = var1; var1 = var1[0xFA9E477F]
      55 [-]: CALL R1 2 2  ; var1 = var1(var2)
      56 [-]: NAMECALL R1 R1 K20; var2 = var1; var1 = var1[0xC45C884B]
      57 [-]: CALL R1 2 2  ; var1 = var1(var2)
      58 [-]: SETUPVAL R1 4; upvalues[1] = var4
L 8:  59 [-]: JUMPBACK L5  ; goto L5
L 9:  60 [-]: RETURN R0 0  ; 


; Name:            
; Defined at line: 134
; #Upvalues:       1
; #Parameters:     0
; Is_vararg:       0
; Max Stack Size:  3

       0 [-]: GETUPVAL R0 0; var0 = upvalues[0]
       1 [-]: NAMECALL R0 R0 K0; var1 = var0; var0 = var0[0xFA9E477F]
       2 [-]: CALL R0 2 2  ; var0 = var0(var1)
       3 [-]: LOADB R2 1   ; var2 = true
       4 [-]: NAMECALL R0 R0 K1; var1 = var0; var0 = var0[0x0223CF08]
       5 [-]: CALL R0 3 2  ; var0 = var0(var1, var2)
       6 [-]: RETURN R0 1  ; 


; Name:            
; Defined at line: 138
; #Upvalues:       10
; #Parameters:     4
; Is_vararg:       0
; Max Stack Size:  14

       0 [-]: LOADN R4 0   ; var4 = 0
       1 [-]: GETUPVAL R5 0; var5 = upvalues[0]
       2 [-]: GETUPVAL R7 1; var7 = upvalues[1]
       3 [-]: LOADN R8 0   ; var8 = 0
       4 [-]: NAMECALL R5 R5 K0; var6 = var5; var5 = var5[0x0EB34C69]
       5 [-]: CALL R5 4 2  ; var5 = var5(var6, var7, var8)
       6 [-]: LOADB R6 0   ; var6 = false
       7 [-]: LOADN R7 0   ; var7 = 0
L 0:   8 [-]: LOADN R8 100 ; var8 = 100
       9 [-]: JUMPIFNOTLT R5 R8 L22; goto L22 if var5 >= var133153
      10 [-]: GETIMPORT R8 2; var8 = 0xCBD666E1
      11 [-]: LOADN R9 0   ; var9 = 0
      12 [-]: CALL R8 2 1  ; var8(var9)
      13 [-]: GETUPVAL R8 2; var8 = upvalues[2]
      14 [-]: CALL R8 1 1  ; var8()
      15 [-]: GETUPVAL R9 3; var9 = upvalues[3]
      16 [-]: FASTCALL1 64 R9 L1; 
      17 [-]: GETIMPORT R8 4; var8 = 0x7B998233
      18 [-]: CALL R8 2 2  ; var8 = var8(var9)
L 1:  19 [-]: JUMPIF R8 L2 ; goto L2 if var8
      20 [-]: GETUPVAL R8 3; var8 = upvalues[3]
      21 [-]: NAMECALL R8 R8 K5; var9 = var8; var8 = var8[0x2047CFE7]
      22 [-]: CALL R8 2 2  ; var8 = var8(var9)
      23 [-]: JUMPIFNOT R8 L3; goto L3 if not var8
L 2:  24 [-]: GETIMPORT R8 7; var8 = 0x3D106989
      25 [-]: LOADK R9 K8  ; var9 = "Event Moa killed"
      26 [-]: CALL R8 2 1  ; var8(var9)
      27 [-]: RETURN R0 0  ; 
L 3:  28 [-]: FASTCALL1 64 R1 L4; 
      29 [-]: MOVE R9 R1   ; var9 = var1
      30 [-]: GETIMPORT R8 4; var8 = 0x7B998233
      31 [-]: CALL R8 2 2  ; var8 = var8(var9)
L 4:  32 [-]: JUMPIF R8 L9 ; goto L9 if var8
      33 [-]: GETIMPORT R8 10; var8 = 0x89326C93
      34 [-]: NAMECALL R8 R8 K11; var9 = var8; var8 = var8[0x18D05D30]
      35 [-]: CALL R8 2 2  ; var8 = var8(var9)
      36 [-]: JUMPIFNOT R8 L6; goto L6 if not var8
      37 [-]: GETUPVAL R8 4; var8 = upvalues[4]
      38 [-]: MOVE R9 R7   ; var9 = var7
      39 [-]: CALL R8 2 2  ; var8 = var8(var9)
      40 [-]: MOVE R6 R8   ; var6 = var8
      41 [-]: JUMPIFNOT R6 L5; goto L5 if not var6
      42 [-]: GETUPVAL R8 0; var8 = upvalues[0]
      43 [-]: GETUPVAL R10 5; var10 = upvalues[5]
      44 [-]: LOADN R11 1  ; var11 = 1
      45 [-]: NAMECALL R8 R8 K12; var9 = var8; var8 = var8[0x751F061D]
      46 [-]: CALL R8 4 1  ; var8(var9, var10, var11)
      47 [-]: JUMP L9      ; goto L9
L 5:  48 [-]: GETUPVAL R8 0; var8 = upvalues[0]
      49 [-]: GETUPVAL R10 5; var10 = upvalues[5]
      50 [-]: LOADN R11 0  ; var11 = 0
      51 [-]: NAMECALL R8 R8 K12; var9 = var8; var8 = var8[0x751F061D]
      52 [-]: CALL R8 4 1  ; var8(var9, var10, var11)
      53 [-]: JUMP L9      ; goto L9
L 6:  54 [-]: GETUPVAL R9 6; var9 = upvalues[6]
      55 [-]: GETTABLEKS R8 R9 K13; var8 = var9[0x06D055F9]
      56 [-]: GETUPVAL R10 0; var10 = upvalues[0]
      57 [-]: GETUPVAL R12 5; var12 = upvalues[5]
      58 [-]: LOADN R13 0  ; var13 = 0
      59 [-]: NAMECALL R10 R10 K0; var11 = var10; var10 = var10[0x0EB34C69]
      60 [-]: CALL R10 4 2 ; var10 = var10(var11, var12, var13)
      61 [-]: LOADN R11 0  ; var11 = 0
      62 [-]: JUMPIFLT R11 R10 L7; goto L7 if var11 < var16779526
      63 [-]: LOADB R9 0 +1; var9 = false
L 7:  64 [-]: LOADB R9 1   ; var9 = true
L 8:  65 [-]: LOADB R10 1  ; var10 = true
      66 [-]: LOADB R11 0  ; var11 = false
      67 [-]: CALL R8 4 2  ; var8 = var8(var9, var10, var11)
      68 [-]: MOVE R6 R8   ; var6 = var8
L 9:  69 [-]: JUMPIF R6 L15; goto L15 if var6
      70 [-]: GETIMPORT R8 10; var8 = 0x89326C93
      71 [-]: NAMECALL R8 R8 K11; var9 = var8; var8 = var8[0x18D05D30]
      72 [-]: CALL R8 2 2  ; var8 = var8(var9)
      73 [-]: JUMPIFNOT R8 L14; goto L14 if not var8
      74 [-]: JUMPXEQKN R4 K14 L10 NOT; 
      75 [-]: LOADN R8 0   ; var8 = 0
      76 [-]: JUMPIFNOTLT R8 R5 L10; goto L10 if var8 >= var50661418
      77 [-]: MUL R8 R5 R3 ; var8 = var5 * var3
     L10:  79 [-]: GETIMPORT R8 17; var8 = 0x67652851
      80 [-]: CALL R8 1 2  ; var8 = var8()
      81 [-]: ADD R4 R4 R8 ; var4 = var4 + var8
      82 [-]: GETUPVAL R8 3; var8 = upvalues[3]
      83 [-]: NAMECALL R8 R8 K18; var9 = var8; var8 = var8[0xFA9E477F]
      84 [-]: CALL R8 2 2  ; var8 = var8(var9)
      85 [-]: LOADB R10 1  ; var10 = true
      86 [-]: NAMECALL R8 R8 K19; var9 = var8; var8 = var8[0x0223CF08]
      87 [-]: CALL R8 3 2  ; var8 = var8(var9, var10)
      88 [-]: JUMPIF R8 L11; goto L11 if var8
      89 [-]: GETIMPORT R8 17; var8 = 0x67652851
      90 [-]: CALL R8 1 2  ; var8 = var8()
      91 [-]: ADD R7 R7 R8 ; var7 = var7 + var8
      92 [-]: JUMP L12     ; goto L12
L11:  93 [-]: LOADN R7 0   ; var7 = 0
L12:  94 [-]: DIV R10 R4 R3; var10 = var4 / var3
      95 [-]: MULK R9 R10 K15; var9 = var10 * 100
      96 [-]: FASTCALL1 12 R9 L13; 
      97 [-]: GETIMPORT R8 22; var8 = 0x5BCED4C4[0x55F27C30]
      98 [-]: CALL R8 2 2  ; var8 = var8(var9)
L13:  99 [-]: MOVE R5 R8   ; var5 = var8
     100 [-]: GETUPVAL R8 0; var8 = upvalues[0]
     101 [-]: GETUPVAL R10 1; var10 = upvalues[1]
     102 [-]: MOVE R11 R5  ; var11 = var5
     103 [-]: NAMECALL R8 R8 K12; var9 = var8; var8 = var8[0x751F061D]
     104 [-]: CALL R8 4 1  ; var8(var9, var10, var11)
     105 [-]: JUMP L15     ; goto L15
L14: 106 [-]: GETUPVAL R8 0; var8 = upvalues[0]
     107 [-]: GETUPVAL R10 1; var10 = upvalues[1]
     108 [-]: MOVE R11 R5  ; var11 = var5
     109 [-]: NAMECALL R8 R8 K0; var9 = var8; var8 = var8[0x0EB34C69]
     110 [-]: CALL R8 4 2  ; var8 = var8(var9, var10, var11)
     111 [-]: MOVE R5 R8   ; var5 = var8
L15: 112 [-]: GETIMPORT R8 10; var8 = 0x89326C93
     113 [-]: NAMECALL R8 R8 K11; var9 = var8; var8 = var8[0x18D05D30]
     114 [-]: CALL R8 2 2  ; var8 = var8(var9)
     115 [-]: JUMPIFNOT R8 L18; goto L18 if not var8
     116 [-]: GETUPVAL R8 7; var8 = upvalues[7]
     117 [-]: LOADN R9 45  ; var9 = 45
     118 [-]: JUMPIFNOTLT R9 R8 L18; goto L18 if var9 >= var5900336
     119 [-]: LOADN R8 90  ; var8 = 90
     120 [-]: JUMPIFNOTLT R5 R8 L18; goto L18 if var5 >= var1574945
     121 [-]: GETIMPORT R8 24; var8 = 0x5BCED4C4[0x3630E649]
     122 [-]: CALL R8 1 2  ; var8 = var8()
     123 [-]: LOADK R9 K25 ; var9 = 0.80000001192092896
     124 [-]: JUMPIFNOTLT R8 R9 L16; goto L16 if var8 >= var2108
     125 [-]: GETUPVAL R8 0; var8 = upvalues[0]
     126 [-]: GETUPVAL R10 8; var10 = upvalues[8]
     127 [-]: NAMECALL R8 R8 K26; var9 = var8; var8 = var8[0xC19D05D7]
     128 [-]: CALL R8 3 1  ; var8(var9, var10)
     129 [-]: JUMP L17     ; goto L17
L16: 130 [-]: GETUPVAL R8 0; var8 = upvalues[0]
     131 [-]: GETUPVAL R10 9; var10 = upvalues[9]
     132 [-]: NAMECALL R8 R8 K26; var9 = var8; var8 = var8[0xC19D05D7]
     133 [-]: CALL R8 3 1  ; var8(var9, var10)
L17: 134 [-]: LOADN R8 0   ; var8 = 0
     135 [-]: SETUPVAL R8 7; upvalues[8] = var7
     136 [-]: JUMP L19     ; goto L19
L18: 137 [-]: GETUPVAL R9 7; var9 = upvalues[7]
     138 [-]: GETIMPORT R10 17; var10 = 0x67652851
     139 [-]: CALL R10 1 2 ; var10 = var10()
     140 [-]: ADD R8 R9 R10; var8 = var9 + var10
     141 [-]: SETUPVAL R8 7; upvalues[8] = var7
L19: 142 [-]: JUMPIFNOT R6 L20; goto L20 if not var6
     143 [-]: GETIMPORT R8 29; var8 = _T["ShowImpactMessage"]
     144 [-]: MOVE R9 R1   ; var9 = var1
     145 [-]: LOADN R10 -1 ; var10 = -1
     146 [-]: MOVE R11 R2  ; var11 = var2
     147 [-]: LOADNIL R12  ; var12 = nil
     148 [-]: LOADB R13 0  ; var13 = false
     149 [-]: CALL R8 6 1  ; var8(var9, var10, var11, var12, var13)
     150 [-]: GETIMPORT R8 10; var8 = 0x89326C93
     151 [-]: NAMECALL R8 R8 K11; var9 = var8; var8 = var8[0x18D05D30]
     152 [-]: CALL R8 2 2  ; var8 = var8(var9)
     153 [-]: JUMPIFNOT R8 L21; goto L21 if not var8
     154 [-]: GETUPVAL R8 3; var8 = upvalues[3]
     155 [-]: NAMECALL R8 R8 K18; var9 = var8; var8 = var8[0xFA9E477F]
     156 [-]: CALL R8 2 2  ; var8 = var8(var9)
     157 [-]: LOADB R10 1  ; var10 = true
     158 [-]: NAMECALL R8 R8 K19; var9 = var8; var8 = var8[0x0223CF08]
     159 [-]: CALL R8 3 2  ; var8 = var8(var9, var10)
     160 [-]: JUMPIFNOT R8 L21; goto L21 if not var8
     161 [-]: LOADN R7 0   ; var7 = 0
     162 [-]: JUMP L21     ; goto L21
L20: 163 [-]: GETIMPORT R8 29; var8 = _T["ShowImpactMessage"]
     164 [-]: GETIMPORT R9 31; var9 = 0x603636AD
     165 [-]: MOVE R10 R0  ; var10 = var0
     166 [-]: DUPTABLE R11 33; 
     167 [-]: SETTABLEKS R5 R11 K32; var5["PERCENT"] = var11
     168 [-]: CALL R9 3 2  ; var9 = var9(var10, var11)
     169 [-]: LOADN R10 -1 ; var10 = -1
     170 [-]: MOVE R11 R2  ; var11 = var2
     171 [-]: LOADNIL R12  ; var12 = nil
     172 [-]: LOADB R13 0  ; var13 = false
     173 [-]: CALL R8 6 1  ; var8(var9, var10, var11, var12, var13)
L21: 174 [-]: JUMPBACK L0  ; goto L0
L22: 175 [-]: RETURN R0 0  ; 


; Name:            
; Defined at line: 204
; #Upvalues:       1
; #Parameters:     1
; Is_vararg:       0
; Max Stack Size:  8

       0 [-]: LOADN R1 0   ; var1 = 0
       1 [-]: GETIMPORT R2 1; var2 = 0xC8802016
       2 [-]: MOVE R3 R0   ; var3 = var0
       3 [-]: CALL R2 2 4  ; var2, var3, var4 = var2(var3)
       4 [-]: FORGPREP_INEXT R2 L1; 
L 0:   5 [-]: GETTABLEKS R7 R6 K2; var7 = var6["value"]
       6 [-]: ADD R1 R1 R7 ; var1 = var1 + var7
L 1:   7 [-]: FORGLOOP R2 L0 2 [inext]; 
       8 [-]: LOADN R2 0   ; var2 = 0
           10 [-]: FASTCALL1 12 R4 L2; 
      11 [-]: GETIMPORT R3 6; var3 = 0x5BCED4C4[0x55F27C30]
      12 [-]: CALL R3 2 2  ; var3 = var3(var4)
L 2:  13 [-]: LOADN R4 0   ; var4 = 0
      14 [-]: JUMPIFNOTLT R4 R3 L3; goto L3 if var4 >= var1596
      15 [-]: GETUPVAL R6 0; var6 = upvalues[0]
      16 [-]: GETTABLEKS R5 R6 K7; var5 = var6["LARGE"]
      17 [-]: GETTABLE R4 R5 R3; var4 = var5[var3]
      18 [-]: ADD R2 R2 R4 ; var2 = var2 + var4
      19 [-]: MULK R4 R3 K3; var4 = var3 * 100000
      20 [-]: SUB R1 R1 R4 ; var1 = var1 - var4
L 3:       22 [-]: FASTCALL1 12 R5 L4; 
      23 [-]: GETIMPORT R4 6; var4 = 0x5BCED4C4[0x55F27C30]
      24 [-]: CALL R4 2 2  ; var4 = var4(var5)
L 4:  25 [-]: MOVE R3 R4   ; var3 = var4
      26 [-]: LOADN R4 0   ; var4 = 0
      27 [-]: JUMPIFNOTLT R4 R3 L5; goto L5 if var4 >= var1596
      28 [-]: GETUPVAL R6 0; var6 = upvalues[0]
      29 [-]: GETTABLEKS R5 R6 K9; var5 = var6["MEDIUM"]
      30 [-]: GETTABLE R4 R5 R3; var4 = var5[var3]
      31 [-]: ADD R2 R2 R4 ; var2 = var2 + var4
      32 [-]: MULK R4 R3 K8; var4 = var3 * 10000
      33 [-]: SUB R1 R1 R4 ; var1 = var1 - var4
L 5:       35 [-]: FASTCALL1 12 R5 L6; 
      36 [-]: GETIMPORT R4 6; var4 = 0x5BCED4C4[0x55F27C30]
      37 [-]: CALL R4 2 2  ; var4 = var4(var5)
L 6:  38 [-]: MOVE R3 R4   ; var3 = var4
      39 [-]: LOADN R4 0   ; var4 = 0
      40 [-]: JUMPIFNOTLT R4 R3 L7; goto L7 if var4 >= var1596
      41 [-]: GETUPVAL R6 0; var6 = upvalues[0]
      42 [-]: GETTABLEKS R5 R6 K11; var5 = var6["SMALL"]
      43 [-]: GETTABLE R4 R5 R3; var4 = var5[var3]
      44 [-]: ADD R2 R2 R4 ; var2 = var2 + var4
      45 [-]: MULK R4 R3 K10; var4 = var3 * 1000
      46 [-]: SUB R1 R1 R4 ; var1 = var1 - var4
L 7:  47 [-]: RETURN R2 1  ; 


; Name:            
; Defined at line: 233
; #Upvalues:       2
; #Parameters:     2
; Is_vararg:       0
; Max Stack Size:  8

       0 [-]: LOADN R2 100 ; var2 = 100
       1 [-]: SUB R1 R2 R1 ; var1 = var2 - var1
       2 [-]: LOADN R2 0   ; var2 = 0
       3 [-]: LOADN R3 66  ; var3 = 66
       4 [-]: JUMPIFNOTLT R3 R1 L0; goto L0 if var3 >= var593
            6 [-]: JUMP L2      ; goto L2
L 0:   7 [-]: LOADN R3 33  ; var3 = 33
       8 [-]: JUMPIFNOTLT R3 R1 L1; goto L1 if var3 >= var16777809
           10 [-]: JUMP L2      ; goto L2
L 1: L 2:  12 [-]: GETUPVAL R3 0; var3 = upvalues[0]
      13 [-]: GETUPVAL R5 1; var5 = upvalues[1]
      14 [-]: FASTCALL1 7 R2 L3; 
      15 [-]: MOVE R7 R2   ; var7 = var2
      16 [-]: GETIMPORT R6 5; var6 = 0x5BCED4C4[0x99675E23]
      17 [-]: CALL R6 2 2  ; var6 = var6(var7)
L 3:  18 [-]: NAMECALL R3 R3 K6; var4 = var3; var3 = var3[0x751F061D]
      19 [-]: CALL R3 4 1  ; var3(var4, var5, var6)
      20 [-]: RETURN R0 0  ; 


; Name:            
; Defined at line: 248
; #Upvalues:       22
; #Parameters:     0
; Is_vararg:       0
; Max Stack Size:  18

       0 [-]: GETIMPORT R0 1; var0 = 0x89326C93
       1 [-]: GETUPVAL R2 1; var2 = upvalues[1]
       2 [-]: GETIMPORT R3 3; var3 = 0xA421AF95
       3 [-]: CALL R3 1 2  ; var3 = var3()
       4 [-]: LOADK R4 K4  ; var4 = 3.4028234663852886e+38
       5 [-]: NAMECALL R0 R0 K5; var1 = var0; var0 = var0[0x4E5939A5]
       6 [-]: CALL R0 5 2  ; var0 = var0(var1, var2, var3, var4)
       7 [-]: SETUPVAL R0 0; upvalues[0] = var0
L 0:   8 [-]: GETUPVAL R1 0; var1 = upvalues[0]
       9 [-]: FASTCALL1 64 R1 L1; 
      10 [-]: GETIMPORT R0 7; var0 = 0x7B998233
      11 [-]: CALL R0 2 2  ; var0 = var0(var1)
L 1:  12 [-]: JUMPIFNOT R0 L2; goto L2 if not var0
      13 [-]: GETIMPORT R0 9; var0 = 0xCBD666E1
      14 [-]: LOADN R1 0   ; var1 = 0
      15 [-]: CALL R0 2 1  ; var0(var1)
      16 [-]: GETIMPORT R0 1; var0 = 0x89326C93
      17 [-]: GETUPVAL R2 1; var2 = upvalues[1]
      18 [-]: GETIMPORT R3 3; var3 = 0xA421AF95
      19 [-]: CALL R3 1 2  ; var3 = var3()
      20 [-]: LOADK R4 K4  ; var4 = 3.4028234663852886e+38
      21 [-]: NAMECALL R0 R0 K5; var1 = var0; var0 = var0[0x4E5939A5]
      22 [-]: CALL R0 5 2  ; var0 = var0(var1, var2, var3, var4)
      23 [-]: SETUPVAL R0 0; upvalues[0] = var0
      24 [-]: JUMPBACK L0  ; goto L0
L 2:  25 [-]: GETIMPORT R0 11; var0 = 0x3D106989
      26 [-]: LOADK R1 K12 ; var1 = "Found riot moa - event logic starting"
      27 [-]: CALL R0 2 1  ; var0(var1)
      28 [-]: GETIMPORT R0 1; var0 = 0x89326C93
      29 [-]: NAMECALL R0 R0 K13; var1 = var0; var0 = var0[0x18D05D30]
      30 [-]: CALL R0 2 2  ; var0 = var0(var1)
      31 [-]: JUMPIFNOT R0 L3; goto L3 if not var0
      32 [-]: GETUPVAL R0 0; var0 = upvalues[0]
      33 [-]: NAMECALL R0 R0 K14; var1 = var0; var0 = var0[0xFA9E477F]
      34 [-]: CALL R0 2 2  ; var0 = var0(var1)
      35 [-]: NAMECALL R0 R0 K15; var1 = var0; var0 = var0[0xC45C884B]
      36 [-]: CALL R0 2 2  ; var0 = var0(var1)
      37 [-]: SETUPVAL R0 2; upvalues[0] = var2
L 3:  38 [-]: GETIMPORT R0 17; var0 = 0xBE190284
      39 [-]: SETUPVAL R0 3; upvalues[0] = var3
      40 [-]: GETUPVAL R0 3; var0 = upvalues[3]
      41 [-]: LOADB R2 1   ; var2 = true
      42 [-]: NAMECALL R0 R0 K18; var1 = var0; var0 = var0[0xD1961230]
      43 [-]: CALL R0 3 1  ; var0(var1, var2)
      44 [-]: GETIMPORT R0 1; var0 = 0x89326C93
      45 [-]: NAMECALL R0 R0 K19; var1 = var0; var0 = var0[0x8B5B1F58]
      46 [-]: CALL R0 2 2  ; var0 = var0(var1)
      47 [-]: GETIMPORT R1 21; var1 = 0xC8802016
      48 [-]: MOVE R2 R0   ; var2 = var0
      49 [-]: CALL R1 2 4  ; var1, var2, var3 = var1(var2)
      50 [-]: FORGPREP_INEXT R1 L6; 
L 4:  51 [-]: GETUPVAL R6 4; var6 = upvalues[4]
      52 [-]: MOVE R7 R5   ; var7 = var5
      53 [-]: CALL R6 2 3  ; var6, var7 = var6(var7)
      54 [-]: FASTCALL1 64 R7 L5; 
      55 [-]: MOVE R9 R7   ; var9 = var7
      56 [-]: GETIMPORT R8 7; var8 = 0x7B998233
      57 [-]: CALL R8 2 2  ; var8 = var8(var9)
L 5:  58 [-]: JUMPIF R8 L6 ; goto L6 if var8
      59 [-]: GETUPVAL R9 5; var9 = upvalues[5]
      60 [-]: DUPTABLE R10 25; 
      61 [-]: NAMECALL R11 R5 K26; var12 = var5; var11 = var5[0x5E651723]
      62 [-]: CALL R11 2 2 ; var11 = var11(var12)
      63 [-]: NAMECALL R11 R11 K27; var12 = var11; var11 = var11[0x5CA33548]
      64 [-]: CALL R11 2 2 ; var11 = var11(var12)
      65 [-]: SETTABLEKS R11 R10 K22; var11["playerName"] = var10
      66 [-]: SETTABLEKS R6 R10 K23; var6["value"] = var10
      67 [-]: SETTABLEKS R7 R10 K24; var7["chip"] = var10
      68 [-]: FASTCALL2 52 R9 R10 L6; 
      69 [-]: GETIMPORT R8 30; var8 = 0x33BDD652[0x23D5322F]
      70 [-]: CALL R8 3 1  ; var8(var9, var10)
L 6:  71 [-]: FORGLOOP R1 L4 2 [inext]; 
      72 [-]: GETUPVAL R4 5; var4 = upvalues[5]
      73 [-]: LENGTH R3 R4 ; var3 = #var4
           75 [-]: FASTCALL1 7 R2 L7; 
      76 [-]: GETIMPORT R1 34; var1 = 0x5BCED4C4[0x99675E23]
      77 [-]: CALL R1 2 2  ; var1 = var1(var2)
L 7:  78 [-]: SETUPVAL R1 6; upvalues[1] = var6
      79 [-]: GETUPVAL R1 7; var1 = upvalues[7]
      80 [-]: GETUPVAL R2 5; var2 = upvalues[5]
      81 [-]: CALL R1 2 2  ; var1 = var1(var2)
      82 [-]: JUMPXEQKN R1 K35 L8 NOT; 
      83 [-]: RETURN R0 0  ; 
L 8:  84 [-]: GETIMPORT R2 1; var2 = 0x89326C93
      85 [-]: NAMECALL R2 R2 K13; var3 = var2; var2 = var2[0x18D05D30]
      86 [-]: CALL R2 2 2  ; var2 = var2(var3)
      87 [-]: JUMPIFNOT R2 L9; goto L9 if not var2
      88 [-]: GETUPVAL R2 3; var2 = upvalues[3]
      89 [-]: GETUPVAL R4 8; var4 = upvalues[8]
      90 [-]: NAMECALL R2 R2 K36; var3 = var2; var2 = var2[0xC19D05D7]
      91 [-]: CALL R2 3 1  ; var2(var3, var4)
      92 [-]: GETIMPORT R2 9; var2 = 0xCBD666E1
      93 [-]: LOADN R3 1   ; var3 = 1
      94 [-]: CALL R2 2 1  ; var2(var3)
      95 [-]: GETUPVAL R2 9; var2 = upvalues[9]
      96 [-]: CALL R2 1 1  ; var2()
      97 [-]: GETUPVAL R2 3; var2 = upvalues[3]
      98 [-]: GETUPVAL R4 10; var4 = upvalues[10]
      99 [-]: NAMECALL R2 R2 K36; var3 = var2; var2 = var2[0xC19D05D7]
     100 [-]: CALL R2 3 1  ; var2(var3, var4)
L 9: 101 [-]: GETIMPORT R2 11; var2 = 0x3D106989
     102 [-]: LOADK R3 K37 ; var3 = "Starting first stage"
     103 [-]: CALL R2 2 1  ; var2(var3)
     104 [-]: GETUPVAL R2 11; var2 = upvalues[11]
     105 [-]: LOADK R3 K38 ; var3 = "/Lotus/Language/Game/CreditChipTransferring"
     106 [-]: LOADK R4 K39 ; var4 = "/Lotus/Language/Game/CreditChipPauseTransfer"
     107 [-]: LOADB R5 1   ; var5 = true
     108 [-]: MOVE R6 R1   ; var6 = var1
     109 [-]: CALL R2 5 1  ; var2(var3, var4, var5, var6)
     110 [-]: GETIMPORT R2 9; var2 = 0xCBD666E1
     111 [-]: LOADN R3 2   ; var3 = 2
     112 [-]: CALL R2 2 1  ; var2(var3)
     113 [-]: GETUPVAL R2 9; var2 = upvalues[9]
     114 [-]: CALL R2 1 1  ; var2()
     115 [-]: GETUPVAL R3 0; var3 = upvalues[0]
     116 [-]: FASTCALL1 64 R3 L10; 
     117 [-]: GETIMPORT R2 7; var2 = 0x7B998233
     118 [-]: CALL R2 2 2  ; var2 = var2(var3)
L10: 119 [-]: JUMPIF R2 L11; goto L11 if var2
     120 [-]: GETUPVAL R2 0; var2 = upvalues[0]
     121 [-]: NAMECALL R2 R2 K40; var3 = var2; var2 = var2[0x2047CFE7]
     122 [-]: CALL R2 2 2  ; var2 = var2(var3)
     123 [-]: JUMPIFNOT R2 L12; goto L12 if not var2
L11: 124 [-]: GETIMPORT R2 43; var2 = _T["ShowImpactMessage"]
     125 [-]: LOADK R3 K44 ; var3 = "/Lotus/Language/Game/CreditChipTransferCancelled"
     126 [-]: LOADN R4 3   ; var4 = 3
     127 [-]: LOADB R5 1   ; var5 = true
     128 [-]: LOADNIL R6   ; var6 = nil
     129 [-]: LOADB R7 0   ; var7 = false
     130 [-]: CALL R2 6 1  ; var2(var3, var4, var5, var6, var7)
     131 [-]: GETUPVAL R2 3; var2 = upvalues[3]
     132 [-]: GETUPVAL R4 12; var4 = upvalues[12]
     133 [-]: NAMECALL R2 R2 K36; var3 = var2; var2 = var2[0xC19D05D7]
     134 [-]: CALL R2 3 1  ; var2(var3, var4)
     135 [-]: RETURN R0 0  ; 
L12: 136 [-]: GETIMPORT R2 1; var2 = 0x89326C93
     137 [-]: NAMECALL R2 R2 K13; var3 = var2; var2 = var2[0x18D05D30]
     138 [-]: CALL R2 2 2  ; var2 = var2(var3)
     139 [-]: JUMPIFNOT R2 L19; goto L19 if not var2
     140 [-]: GETUPVAL R2 3; var2 = upvalues[3]
     141 [-]: GETUPVAL R4 13; var4 = upvalues[13]
     142 [-]: NAMECALL R2 R2 K36; var3 = var2; var2 = var2[0xC19D05D7]
     143 [-]: CALL R2 3 1  ; var2(var3, var4)
     144 [-]: GETIMPORT R2 21; var2 = 0xC8802016
     145 [-]: GETUPVAL R3 5; var3 = upvalues[5]
     146 [-]: CALL R2 2 4  ; var2, var3, var4 = var2(var3)
     147 [-]: FORGPREP_INEXT R2 L18; 
L13: 148 [-]: GETUPVAL R7 14; var7 = upvalues[14]
     149 [-]: GETTABLEKS R8 R6 K22; var8 = var6["playerName"]
     150 [-]: CALL R7 2 2  ; var7 = var7(var8)
     151 [-]: FASTCALL1 64 R7 L14; 
     152 [-]: MOVE R9 R7   ; var9 = var7
     153 [-]: GETIMPORT R8 7; var8 = 0x7B998233
     154 [-]: CALL R8 2 2  ; var8 = var8(var9)
L14: 155 [-]: JUMPIF R8 L18; goto L18 if var8
     156 [-]: NAMECALL R8 R7 K45; var9 = var7; var8 = var7[0xBB610E5B]
     157 [-]: CALL R8 2 2  ; var8 = var8(var9)
     158 [-]: FASTCALL1 64 R8 L15; 
     159 [-]: MOVE R10 R8  ; var10 = var8
     160 [-]: GETIMPORT R9 7; var9 = 0x7B998233
     161 [-]: CALL R9 2 2  ; var9 = var9(var10)
L15: 162 [-]: JUMPIF R9 L18; goto L18 if var9
     163 [-]: GETTABLEKS R10 R6 K24; var10 = var6["chip"]
     164 [-]: FASTCALL1 64 R10 L16; 
     165 [-]: GETIMPORT R9 7; var9 = 0x7B998233
     166 [-]: CALL R9 2 2  ; var9 = var9(var10)
L16: 167 [-]: JUMPIF R9 L17; goto L17 if var9
     168 [-]: GETIMPORT R9 11; var9 = 0x3D106989
     169 [-]: LOADK R11 K46; var11 = "Consuming "
     170 [-]: GETTABLEKS R12 R6 K22; var12 = var6["playerName"]
     171 [-]: LOADK R13 K47; var13 = "'s "
     172 [-]: GETTABLEKS R14 R6 K24; var14 = var6["chip"]
     173 [-]: NAMECALL R14 R14 K48; var15 = var14; var14 = var14[0xED4E0128]
     174 [-]: CALL R14 2 2 ; var14 = var14(var15)
     175 [-]: CONCAT R10 R11 R14; var10 = var11 .. var14
     176 [-]: CALL R9 2 1  ; var9(var10)
     177 [-]: NAMECALL R9 R8 K49; var10 = var8; var9 = var8[0xDE321E6F]
     178 [-]: CALL R9 2 2  ; var9 = var9(var10)
     179 [-]: GETTABLEKS R11 R6 K24; var11 = var6["chip"]
     180 [-]: NAMECALL R9 R9 K50; var10 = var9; var9 = var9[0x40A5B7AF]
     181 [-]: CALL R9 3 1  ; var9(var10, var11)
     182 [-]: JUMP L18     ; goto L18
L17: 183 [-]: GETIMPORT R9 11; var9 = 0x3D106989
     184 [-]: LOADK R11 K51; var11 = "Want to consume chip from "
     185 [-]: GETTABLEKS R12 R6 K22; var12 = var6["playerName"]
     186 [-]: LOADK R13 K52; var13 = " but chip was null"
     187 [-]: CONCAT R10 R11 R13; var10 = var11 .. var13
     188 [-]: CALL R9 2 1  ; var9(var10)
L18: 189 [-]: FORGLOOP R2 L13 2 [inext]; 
     190 [-]: GETUPVAL R2 3; var2 = upvalues[3]
     191 [-]: GETUPVAL R4 15; var4 = upvalues[15]
     192 [-]: LOADN R5 0   ; var5 = 0
     193 [-]: NAMECALL R2 R2 K53; var3 = var2; var2 = var2[0x751F061D]
     194 [-]: CALL R2 4 1  ; var2(var3, var4, var5)
L19: 195 [-]: GETIMPORT R2 43; var2 = _T["ShowImpactMessage"]
     196 [-]: LOADK R3 K54 ; var3 = "/Lotus/Language/Game/CreditChipVerificationStart"
     197 [-]: LOADN R4 3   ; var4 = 3
     198 [-]: LOADB R5 0   ; var5 = false
     199 [-]: LOADNIL R6   ; var6 = nil
     200 [-]: LOADB R7 0   ; var7 = false
     201 [-]: CALL R2 6 1  ; var2(var3, var4, var5, var6, var7)
     202 [-]: GETIMPORT R2 9; var2 = 0xCBD666E1
     203 [-]: LOADN R3 3   ; var3 = 3
     204 [-]: CALL R2 2 1  ; var2(var3)
     205 [-]: GETUPVAL R2 9; var2 = upvalues[9]
     206 [-]: CALL R2 1 1  ; var2()
     207 [-]: GETIMPORT R2 11; var2 = 0x3D106989
     208 [-]: LOADK R3 K55 ; var3 = "Starting second stage"
     209 [-]: CALL R2 2 1  ; var2(var3)
     210 [-]: GETUPVAL R2 11; var2 = upvalues[11]
     211 [-]: LOADK R3 K56 ; var3 = "/Lotus/Language/Game/CreditChipVerifying"
     212 [-]: LOADNIL R4   ; var4 = nil
     213 [-]: LOADB R5 0   ; var5 = false
     214 [-]: LOADN R6 60  ; var6 = 60
     215 [-]: CALL R2 5 1  ; var2(var3, var4, var5, var6)
     216 [-]: GETIMPORT R2 58; var2 = _T["HideImpactMessage"]
     217 [-]: CALL R2 1 1  ; var2()
     218 [-]: GETUPVAL R2 3; var2 = upvalues[3]
     219 [-]: GETUPVAL R4 15; var4 = upvalues[15]
     220 [-]: LOADN R5 0   ; var5 = 0
     221 [-]: NAMECALL R2 R2 K59; var3 = var2; var2 = var2[0x0EB34C69]
     222 [-]: CALL R2 4 2  ; var2 = var2(var3, var4, var5)
     223 [-]: LOADN R3 100 ; var3 = 100
     224 [-]: JUMPIFNOTLT R2 R3 L33; goto L33 if var2 >= var721697
     225 [-]: GETIMPORT R3 11; var3 = 0x3D106989
     226 [-]: LOADK R4 K60 ; var4 = "Event completed - giving rewards"
     227 [-]: CALL R3 2 1  ; var3(var4)
     228 [-]: GETIMPORT R3 1; var3 = 0x89326C93
     229 [-]: NAMECALL R3 R3 K13; var4 = var3; var3 = var3[0x18D05D30]
     230 [-]: CALL R3 2 2  ; var3 = var3(var4)
     231 [-]: JUMPIFNOT R3 L24; goto L24 if not var3
     232 [-]: GETUPVAL R3 2; var3 = upvalues[2]
     233 [-]: MOVE R4 R2   ; var4 = var2
     234 [-]: LOADN R5 100 ; var5 = 100
     235 [-]: SUB R4 R5 R4 ; var4 = var5 - var4
     236 [-]: LOADN R5 0   ; var5 = 0
     237 [-]: LOADN R6 66  ; var6 = 66
     238 [-]: JUMPIFNOTLT R6 R4 L20; goto L20 if var6 >= var520291665
          240 [-]: JUMP L22     ; goto L22
L20: 241 [-]: LOADN R6 33  ; var6 = 33
     242 [-]: JUMPIFNOTLT R6 R4 L21; goto L21 if var6 >= var1023608145
          244 [-]: JUMP L22     ; goto L22
L21: L22: 246 [-]: GETUPVAL R6 3; var6 = upvalues[3]
     247 [-]: GETUPVAL R8 16; var8 = upvalues[16]
     248 [-]: FASTCALL1 7 R5 L23; 
     249 [-]: MOVE R10 R5  ; var10 = var5
     250 [-]: GETIMPORT R9 34; var9 = 0x5BCED4C4[0x99675E23]
     251 [-]: CALL R9 2 2  ; var9 = var9(var10)
L23: 252 [-]: NAMECALL R6 R6 K53; var7 = var6; var6 = var6[0x751F061D]
     253 [-]: CALL R6 4 1  ; var6(var7, var8, var9)
L24: 254 [-]: LOADN R3 0   ; var3 = 0
L25: 255 [-]: JUMPXEQKN R3 K35 L26 NOT; 
     256 [-]: GETIMPORT R4 9; var4 = 0xCBD666E1
     257 [-]: LOADN R5 0   ; var5 = 0
     258 [-]: CALL R4 2 1  ; var4(var5)
     259 [-]: GETUPVAL R4 3; var4 = upvalues[3]
     260 [-]: GETUPVAL R6 16; var6 = upvalues[16]
     261 [-]: LOADN R7 0   ; var7 = 0
     262 [-]: NAMECALL R4 R4 K59; var5 = var4; var4 = var4[0x0EB34C69]
     263 [-]: CALL R4 4 2  ; var4 = var4(var5, var6, var7)
     264 [-]: MOVE R3 R4   ; var3 = var4
     265 [-]: JUMPBACK L25 ; goto L25
L26: 266 [-]: GETIMPORT R4 21; var4 = 0xC8802016
     267 [-]: GETUPVAL R5 5; var5 = upvalues[5]
     268 [-]: CALL R4 2 4  ; var4, var5, var6 = var4(var5)
     269 [-]: FORGPREP_INEXT R4 L32; 
L27: 270 [-]: GETUPVAL R9 14; var9 = upvalues[14]
     271 [-]: GETTABLEKS R10 R8 K22; var10 = var8["playerName"]
     272 [-]: CALL R9 2 2  ; var9 = var9(var10)
     273 [-]: FASTCALL1 64 R9 L28; 
     274 [-]: MOVE R11 R9  ; var11 = var9
     275 [-]: GETIMPORT R10 7; var10 = 0x7B998233
     276 [-]: CALL R10 2 2 ; var10 = var10(var11)
L28: 277 [-]: JUMPIF R10 L32; goto L32 if var10
     278 [-]: NAMECALL R10 R9 K45; var11 = var9; var10 = var9[0xBB610E5B]
     279 [-]: CALL R10 2 2 ; var10 = var10(var11)
     280 [-]: GETTABLEKS R13 R8 K23; var13 = var8["value"]
     281 [-]: LOADN R15 1  ; var15 = 1
          283 [-]: ADD R14 R15 R16; var14 = var15 + var16
     284 [-]: MUL R12 R13 R14; var12 = var13 * var14
     285 [-]: FASTCALL1 12 R12 L29; 
     286 [-]: GETIMPORT R11 65; var11 = 0x5BCED4C4[0x55F27C30]
     287 [-]: CALL R11 2 2 ; var11 = var11(var12)
L29: 288 [-]: FASTCALL1 64 R10 L30; 
     289 [-]: MOVE R13 R10 ; var13 = var10
     290 [-]: GETIMPORT R12 7; var12 = 0x7B998233
     291 [-]: CALL R12 2 2 ; var12 = var12(var13)
L30: 292 [-]: JUMPIF R12 L32; goto L32 if var12
     293 [-]: NAMECALL R12 R10 K66; var13 = var10; var12 = var10[0xA5E492D4]
     294 [-]: CALL R12 2 2 ; var12 = var12(var13)
     295 [-]: JUMPIFNOT R12 L31; goto L31 if not var12
     296 [-]: GETIMPORT R12 43; var12 = _T["ShowImpactMessage"]
     297 [-]: GETIMPORT R13 68; var13 = 0x603636AD
     298 [-]: LOADK R14 K69; var14 = "/Lotus/Language/Game/CreditChipRetrieved"
     299 [-]: DUPTABLE R15 71; 
     300 [-]: SETTABLEKS R11 R15 K70; var11["CREDITS"] = var15
     301 [-]: CALL R13 3 2 ; var13 = var13(var14, var15)
     302 [-]: LOADN R14 5  ; var14 = 5
     303 [-]: LOADB R15 1  ; var15 = true
     304 [-]: LOADNIL R16  ; var16 = nil
     305 [-]: LOADB R17 0  ; var17 = false
     306 [-]: CALL R12 6 1 ; var12(var13, var14, var15, var16, var17)
L31: 307 [-]: GETIMPORT R12 1; var12 = 0x89326C93
     308 [-]: NAMECALL R12 R12 K13; var13 = var12; var12 = var12[0x18D05D30]
     309 [-]: CALL R12 2 2 ; var12 = var12(var13)
     310 [-]: JUMPIFNOT R12 L32; goto L32 if not var12
     311 [-]: NAMECALL R12 R10 K49; var13 = var10; var12 = var10[0xDE321E6F]
     312 [-]: CALL R12 2 2 ; var12 = var12(var13)
     313 [-]: MOVE R14 R11 ; var14 = var11
     314 [-]: NAMECALL R12 R12 K72; var13 = var12; var12 = var12[0x6C26BDB7]
     315 [-]: CALL R12 3 1 ; var12(var13, var14)
L32: 316 [-]: FORGLOOP R4 L27 2 [inext]; 
     317 [-]: GETIMPORT R4 1; var4 = 0x89326C93
     318 [-]: NAMECALL R4 R4 K13; var5 = var4; var4 = var4[0x18D05D30]
     319 [-]: CALL R4 2 2  ; var4 = var4(var5)
     320 [-]: JUMPIFNOT R4 L34; goto L34 if not var4
     321 [-]: GETIMPORT R4 74; var4 = 0xB7CBD06B
     322 [-]: LOADN R5 15  ; var5 = 15
     323 [-]: LOADN R6 100 ; var6 = 100
     324 [-]: CALL R4 3 2  ; var4 = var4(var5, var6)
     325 [-]: GETIMPORT R5 74; var5 = 0xB7CBD06B
     326 [-]: LOADN R6 1   ; var6 = 1
     327 [-]: LOADN R7 4   ; var7 = 4
     328 [-]: CALL R5 3 2  ; var5 = var5(var6, var7)
     329 [-]: GETUPVAL R10 2; var10 = upvalues[2]
     330 [-]: NAMECALL R8 R4 K75; var9 = var4; var8 = var4[0x42DCC9F5]
     331 [-]: CALL R8 3 0  ; var8, ... = var8(var9, var10)
     332 [-]: NAMECALL R6 R4 K76; var7 = var4; var6 = var4[0x3B93153D]
     333 [-]: CALL R6 0 2  ; var6 = var6(var7, ...)
     334 [-]: MOVE R9 R6   ; var9 = var6
     335 [-]: NAMECALL R7 R5 K77; var8 = var5; var7 = var5[0x70596BFE]
     336 [-]: CALL R7 3 2  ; var7 = var7(var8, var9)
     337 [-]: GETUPVAL R8 3; var8 = upvalues[3]
     338 [-]: GETUPVAL R10 17; var10 = upvalues[17]
     339 [-]: LOADN R13 100; var13 = 100
     340 [-]: SUB R12 R13 R2; var12 = var13 - var2
     341 [-]: MUL R11 R12 R7; var11 = var12 * var7
     342 [-]: NAMECALL R8 R8 K53; var9 = var8; var8 = var8[0x751F061D]
     343 [-]: CALL R8 4 1  ; var8(var9, var10, var11)
     344 [-]: GETUPVAL R8 3; var8 = upvalues[3]
     345 [-]: GETUPVAL R10 18; var10 = upvalues[18]
     346 [-]: NAMECALL R8 R8 K36; var9 = var8; var8 = var8[0xC19D05D7]
     347 [-]: CALL R8 3 1  ; var8(var9, var10)
     348 [-]: GETIMPORT R8 9; var8 = 0xCBD666E1
     349 [-]: LOADN R9 3   ; var9 = 3
     350 [-]: CALL R8 2 1  ; var8(var9)
     351 [-]: GETUPVAL R8 3; var8 = upvalues[3]
     352 [-]: GETUPVAL R10 19; var10 = upvalues[19]
     353 [-]: NAMECALL R8 R8 K36; var9 = var8; var8 = var8[0xC19D05D7]
     354 [-]: CALL R8 3 1  ; var8(var9, var10)
     355 [-]: RETURN R0 0  ; 
L33: 356 [-]: GETIMPORT R3 11; var3 = 0x3D106989
     357 [-]: LOADK R4 K78 ; var4 = "Event failed"
     358 [-]: CALL R3 2 1  ; var3(var4)
     359 [-]: GETIMPORT R3 43; var3 = _T["ShowImpactMessage"]
     360 [-]: LOADK R4 K79 ; var4 = "/Lotus/Language/Game/CreditChipLost"
     361 [-]: LOADN R5 5   ; var5 = 5
     362 [-]: LOADB R6 0   ; var6 = false
     363 [-]: LOADNIL R7   ; var7 = nil
     364 [-]: LOADB R8 0   ; var8 = false
     365 [-]: CALL R3 6 1  ; var3(var4, var5, var6, var7, var8)
     366 [-]: GETIMPORT R3 1; var3 = 0x89326C93
     367 [-]: NAMECALL R3 R3 K13; var4 = var3; var3 = var3[0x18D05D30]
     368 [-]: CALL R3 2 2  ; var3 = var3(var4)
     369 [-]: JUMPIFNOT R3 L34; goto L34 if not var3
     370 [-]: GETUPVAL R3 3; var3 = upvalues[3]
     371 [-]: GETUPVAL R5 20; var5 = upvalues[20]
     372 [-]: NAMECALL R3 R3 K36; var4 = var3; var3 = var3[0xC19D05D7]
     373 [-]: CALL R3 3 1  ; var3(var4, var5)
     374 [-]: GETIMPORT R3 9; var3 = 0xCBD666E1
     375 [-]: LOADN R4 3   ; var4 = 3
     376 [-]: CALL R3 2 1  ; var3(var4)
     377 [-]: GETUPVAL R3 9; var3 = upvalues[9]
     378 [-]: CALL R3 1 1  ; var3()
     379 [-]: GETUPVAL R3 3; var3 = upvalues[3]
     380 [-]: GETUPVAL R5 21; var5 = upvalues[21]
     381 [-]: NAMECALL R3 R3 K36; var4 = var3; var3 = var3[0xC19D05D7]
     382 [-]: CALL R3 3 1  ; var3(var4, var5)
L34: 383 [-]: RETURN R0 0  ; 



