; This file has been disassembled using luadec 2.0.2 by sztupy (modified by Reversive)

; Name:            
; Defined at line: 0
; #Upvalues:       0
; #Parameters:     0
; Is_vararg:       2
; Max Stack Size:  35

  1 [-]: GETGLOBAL R0 K0        ; R0 := 0x2d0fad09
  2 [-]: LOADK     R1 K1        ; R1 := "Lotus.Scripts.Libs.TransmissionSet"
  3 [-]: CALL      R0 2 2       ; R0 := R0(R1)
  4 [-]: GETGLOBAL R1 K0        ; R1 := 0x2d0fad09
  5 [-]: LOADK     R2 K2        ; R2 := "Lotus.Interface.LotusUtilities"
  6 [-]: CALL      R1 2 2       ; R1 := R1(R2)
  7 [-]: GETGLOBAL R2 K0        ; R2 := 0x2d0fad09
  8 [-]: LOADK     R3 K3        ; R3 := "EE.Interface.Utilities"
  9 [-]: CALL      R2 2 2       ; R2 := R2(R3)
 10 [-]: LOADK     R3 K4        ; R3 := 1.300000
 11 [-]: GETGLOBAL R4 K5        ; R4 := 0x0469f296
 12 [-]: LOADK     R5 K6        ; R5 := "KahlAlly"
 13 [-]: CALL      R4 2 2       ; R4 := R4(R5)
 14 [-]: GETGLOBAL R5 K5        ; R5 := 0x0469f296
 15 [-]: LOADK     R6 K7        ; R6 := "AllyAvatarsRemainingTime"
 16 [-]: CALL      R5 2 2       ; R5 := R5(R6)
 17 [-]: LOADNIL   R6 R7        ; R6 := R7 := nil
 18 [-]: LOADKB    R8 0 0       ; R8 := false
 19 [-]: GETGLOBAL R9 K0        ; R9 := 0x2d0fad09
 20 [-]: LOADK     R10 K8       ; R10 := "Lotus.Scripts.Libs.PanicLib"
 21 [-]: CALL      R9 2 2       ; R9 := R9(R10)
 22 [-]: GETGLOBAL R10 K0       ; R10 := 0x2d0fad09
 23 [-]: LOADK     R11 K9       ; R11 := "Lotus.Scripts.Libs.AbilitiesLib"
 24 [-]: CALL      R10 2 2      ; R10 := R10(R11)
 25 [-]: CLOSURE   R11 0        ; R11 := closure(Function #1)
 26 [-]: MOVE      R0 R6        ; R0 := R6
 27 [-]: MOVE      R0 R7        ; R0 := R7
 28 [-]: MOVE      R0 R8        ; R0 := R8
 29 [-]: CLOSURE   R12 1        ; R12 := closure(Function #2)
 30 [-]: MOVE      R0 R6        ; R0 := R6
 31 [-]: MOVE      R0 R7        ; R0 := R7
 32 [-]: MOVE      R0 R8        ; R0 := R8
 33 [-]: CLOSURE   R13 2        ; R13 := closure(Function #3)
 34 [-]: CLOSURE   R14 3        ; R14 := closure(Function #4)
 35 [-]: MOVE      R0 R9        ; R0 := R9
 36 [-]: CLOSURE   R15 4        ; R15 := closure(Function #5)
 37 [-]: CLOSURE   R16 5        ; R16 := closure(Function #6)
 38 [-]: MOVE      R0 R6        ; R0 := R6
 39 [-]: MOVE      R0 R1        ; R0 := R1
 40 [-]: MOVE      R0 R3        ; R0 := R3
 41 [-]: MOVE      R0 R12       ; R0 := R12
 42 [-]: CLOSURE   R17 6        ; R17 := closure(Function #7)
 43 [-]: MOVE      R0 R3        ; R0 := R3
 44 [-]: MOVE      R0 R6        ; R0 := R6
 45 [-]: MOVE      R0 R12       ; R0 := R12
 46 [-]: CLOSURE   R18 7        ; R18 := closure(Function #8)
 47 [-]: MOVE      R0 R6        ; R0 := R6
 48 [-]: CLOSURE   R19 8        ; R19 := closure(Function #9)
 49 [-]: MOVE      R0 R6        ; R0 := R6
 50 [-]: MOVE      R0 R18       ; R0 := R18
 51 [-]: MOVE      R0 R12       ; R0 := R12
 52 [-]: MOVE      R0 R16       ; R0 := R16
 53 [-]: MOVE      R0 R17       ; R0 := R17
 54 [-]: MOVE      R0 R7        ; R0 := R7
 55 [-]: MOVE      R0 R15       ; R0 := R15
 56 [-]: CLOSURE   R20 9        ; R20 := closure(Function #10)
 57 [-]: MOVE      R0 R9        ; R0 := R9
 58 [-]: CLOSURE   R21 10       ; R21 := closure(Function #11)
 59 [-]: CLOSURE   R22 11       ; R22 := closure(Function #12)
 60 [-]: CLOSURE   R23 12       ; R23 := closure(Function #13)
 61 [-]: MOVE      R0 R6        ; R0 := R6
 62 [-]: MOVE      R0 R18       ; R0 := R18
 63 [-]: MOVE      R0 R16       ; R0 := R16
 64 [-]: MOVE      R0 R17       ; R0 := R17
 65 [-]: MOVE      R0 R20       ; R0 := R20
 66 [-]: MOVE      R0 R21       ; R0 := R21
 67 [-]: MOVE      R0 R12       ; R0 := R12
 68 [-]: MOVE      R0 R22       ; R0 := R22
 69 [-]: MOVE      R0 R15       ; R0 := R15
 70 [-]: MOVE      R0 R0        ; R0 := R0
 71 [-]: MOVE      R0 R1        ; R0 := R1
 72 [-]: CLOSURE   R24 13       ; R24 := closure(Function #14)
 73 [-]: CLOSURE   R25 14       ; R25 := closure(Function #15)
 74 [-]: MOVE      R0 R6        ; R0 := R6
 75 [-]: MOVE      R0 R18       ; R0 := R18
 76 [-]: MOVE      R0 R16       ; R0 := R16
 77 [-]: MOVE      R0 R17       ; R0 := R17
 78 [-]: MOVE      R0 R7        ; R0 := R7
 79 [-]: MOVE      R0 R24       ; R0 := R24
 80 [-]: CLOSURE   R26 15       ; R26 := closure(Function #16)
 81 [-]: MOVE      R0 R6        ; R0 := R6
 82 [-]: MOVE      R0 R18       ; R0 := R18
 83 [-]: MOVE      R0 R16       ; R0 := R16
 84 [-]: MOVE      R0 R17       ; R0 := R17
 85 [-]: MOVE      R0 R12       ; R0 := R12
 86 [-]: MOVE      R0 R2        ; R0 := R2
 87 [-]: MOVE      R0 R13       ; R0 := R13
 88 [-]: MOVE      R0 R15       ; R0 := R15
 89 [-]: CLOSURE   R27 16       ; R27 := closure(Function #17)
 90 [-]: MOVE      R0 R6        ; R0 := R6
 91 [-]: MOVE      R0 R18       ; R0 := R18
 92 [-]: MOVE      R0 R16       ; R0 := R16
 93 [-]: MOVE      R0 R17       ; R0 := R17
 94 [-]: MOVE      R0 R15       ; R0 := R15
 95 [-]: CLOSURE   R28 17       ; R28 := closure(Function #18)
 96 [-]: MOVE      R0 R18       ; R0 := R18
 97 [-]: MOVE      R0 R6        ; R0 := R6
 98 [-]: MOVE      R0 R16       ; R0 := R16
 99 [-]: MOVE      R0 R17       ; R0 := R17
100 [-]: MOVE      R0 R15       ; R0 := R15
101 [-]: CLOSURE   R29 18       ; R29 := closure(Function #19)
102 [-]: MOVE      R0 R18       ; R0 := R18
103 [-]: MOVE      R0 R6        ; R0 := R6
104 [-]: MOVE      R0 R16       ; R0 := R16
105 [-]: MOVE      R0 R17       ; R0 := R17
106 [-]: MOVE      R0 R15       ; R0 := R15
107 [-]: CLOSURE   R30 19       ; R30 := closure(Function #20)
108 [-]: MOVE      R0 R6        ; R0 := R6
109 [-]: MOVE      R0 R18       ; R0 := R18
110 [-]: MOVE      R0 R16       ; R0 := R16
111 [-]: MOVE      R0 R17       ; R0 := R17
112 [-]: MOVE      R0 R10       ; R0 := R10
113 [-]: CLOSURE   R31 20       ; R31 := closure(Function #21)
114 [-]: MOVE      R0 R4        ; R0 := R4
115 [-]: CLOSURE   R32 21       ; R32 := closure(Function #22)
116 [-]: MOVE      R0 R31       ; R0 := R31
117 [-]: SETGLOBAL R32 K10      ; OnKahlAllyAgentSpawned := R32
118 [-]: CLOSURE   R32 22       ; R32 := closure(Function #23)
119 [-]: SETGLOBAL R32 K11      ; OnKahlAllyDropshipDrop := R32
120 [-]: CLOSURE   R32 23       ; R32 := closure(Function #24)
121 [-]: MOVE      R0 R6        ; R0 := R6
122 [-]: MOVE      R0 R4        ; R0 := R4
123 [-]: MOVE      R0 R7        ; R0 := R7
124 [-]: MOVE      R0 R18       ; R0 := R18
125 [-]: MOVE      R0 R16       ; R0 := R16
126 [-]: MOVE      R0 R17       ; R0 := R17
127 [-]: MOVE      R0 R12       ; R0 := R12
128 [-]: MOVE      R0 R5        ; R0 := R5
129 [-]: MOVE      R0 R13       ; R0 := R13
130 [-]: MOVE      R0 R2        ; R0 := R2
131 [-]: MOVE      R0 R31       ; R0 := R31
132 [-]: CLOSURE   R33 24       ; R33 := closure(Function #25)
133 [-]: SETGLOBAL R33 K12      ; OnPlayersChanged := R33
134 [-]: CLOSURE   R33 25       ; R33 := closure(Function #26)
135 [-]: MOVE      R0 R11       ; R0 := R11
136 [-]: MOVE      R0 R6        ; R0 := R6
137 [-]: MOVE      R0 R19       ; R0 := R19
138 [-]: MOVE      R0 R23       ; R0 := R23
139 [-]: MOVE      R0 R26       ; R0 := R26
140 [-]: MOVE      R0 R27       ; R0 := R27
141 [-]: MOVE      R0 R28       ; R0 := R28
142 [-]: MOVE      R0 R29       ; R0 := R29
143 [-]: MOVE      R0 R25       ; R0 := R25
144 [-]: MOVE      R0 R30       ; R0 := R30
145 [-]: MOVE      R0 R32       ; R0 := R32
146 [-]: SETGLOBAL R33 K13      ; AirSupport := R33
147 [-]: CLOSURE   R33 26       ; R33 := closure(Function #27)
148 [-]: MOVE      R0 R14       ; R0 := R14
149 [-]: CLOSURE   R34 27       ; R34 := closure(Function #28)
150 [-]: MOVE      R0 R33       ; R0 := R33
151 [-]: SETGLOBAL R34 K14      ; Evaluate := R34
152 [-]: RETURN    R0 1         ; return 


; Function #1:
;
; Name:            
; Defined at line: 122
; #Upvalues:       3
; #Parameters:     1
; Is_vararg:       0
; Max Stack Size:  3

  1 [-]: SETUPVAL  R0 U0        ; U82 := R0
  2 [-]: SELF      R1 R0 K0     ; R2 := R0; R1 := R0[0x5b89142c]
  3 [-]: CALL      R1 2 2       ; R1 := R1(R2)
  4 [-]: SETUPVAL  R1 U1        ; U82 := R1
  5 [-]: GETGLOBAL R1 K1        ; R1 := 0x7b998233
  6 [-]: GETUPVAL  R2 U1        ; R2 := U1
  7 [-]: CALL      R1 2 2       ; R1 := R1(R2)
  8 [-]: TEST      R1 0         ; if not R1 then PC := 11
  9 [-]: JMP       11           ; PC := 11
 10 [-]: RETURN    R0 1         ; return 
 11 [-]: GETUPVAL  R1 U1        ; R1 := U1
 12 [-]: SELF      R1 R1 K2     ; R2 := R1; R1 := R1[0xa534c3ac]
 13 [-]: CALL      R1 2 2       ; R1 := R1(R2)
 14 [-]: EQ        0 R1 R0      ; if R1 ~= R0 then PC := 17
 15 [-]: JMP       17           ; PC := 17
 16 [-]: LOADKB    R1 0 1       ; R1 := false; PC := 17
 17 [-]: LOADKB    R1 1 0       ; R1 := true
 18 [-]: SETUPVAL  R1 U2        ; U82 := R2
 19 [-]: RETURN    R0 1         ; return 


; Function #2:
;
; Name:            
; Defined at line: 132
; #Upvalues:       3
; #Parameters:     0
; Is_vararg:       0
; Max Stack Size:  2

  1 [-]: GETGLOBAL R0 K0        ; R0 := 0x7b998233
  2 [-]: GETUPVAL  R1 U0        ; R1 := U0
  3 [-]: CALL      R0 2 2       ; R0 := R0(R1)
  4 [-]: TEST      R0 1         ; if R0 then PC := 7
  5 [-]: JMP       7            ; PC := 7
  6 [-]: RETURN    R0 1         ; return 
  7 [-]: GETGLOBAL R0 K0        ; R0 := 0x7b998233
  8 [-]: GETUPVAL  R1 U1        ; R1 := U1
  9 [-]: CALL      R0 2 2       ; R0 := R0(R1)
 10 [-]: TEST      R0 0         ; if not R0 then PC := 13
 11 [-]: JMP       13           ; PC := 13
 12 [-]: RETURN    R0 1         ; return 
 13 [-]: GETUPVAL  R0 U2        ; R0 := U2
 14 [-]: TEST      R0 0         ; if not R0 then PC := 21
 15 [-]: JMP       21           ; PC := 21
 16 [-]: GETUPVAL  R0 U1        ; R0 := U1
 17 [-]: SELF      R0 R0 K1     ; R1 := R0; R0 := R0[0x5578d98b]
 18 [-]: CALL      R0 2 2       ; R0 := R0(R1)
 19 [-]: SETUPVAL  R0 U0        ; U82 := R0
 20 [-]: JMP       25           ; PC := 25
 21 [-]: GETUPVAL  R0 U1        ; R0 := U1
 22 [-]: SELF      R0 R0 K2     ; R1 := R0; R0 := R0[0xa534c3ac]
 23 [-]: CALL      R0 2 2       ; R0 := R0(R1)
 24 [-]: SETUPVAL  R0 U0        ; U82 := R0
 25 [-]: RETURN    R0 1         ; return 


; Function #3:
;
; Name:            
; Defined at line: 150
; #Upvalues:       0
; #Parameters:     1
; Is_vararg:       0
; Max Stack Size:  8

  1 [-]: MUL       R1 R0 R0     ; R1 := R0 * R0
  2 [-]: GETGLOBAL R2 K0        ; R2 := 0xc163f229
  3 [-]: UNM       R3 R0        ; R3 :=  R0
  4 [-]: MOVE      R4 R0        ; R4 := R0
  5 [-]: CALL      R2 3 2       ; R2 := R2(R3,R4)
  6 [-]: GETGLOBAL R3 K0        ; R3 := 0xc163f229
  7 [-]: CONST     R4 -1        ; R4 := -1.000000
  8 [-]: CONST     R5 1         ; R5 := 1.000000
  9 [-]: CALL      R3 3 2       ; R3 := R3(R4,R5)
 10 [-]: GETGLOBAL R4 K1        ; R4 := 0x5bced4c4
 11 [-]: GETTABLE  R4 R4 K2     ; R4 := R4[0x34e9f45c]
 12 [-]: MUL       R5 R2 R2     ; R5 := R2 * R2
 13 [-]: SUB       R5 R1 R5     ; R5 := R1 - R5
 14 [-]: CALL      R4 2 2       ; R4 := R4(R5)
 15 [-]: MUL       R3 R3 R4     ; R3 := R3 * R4
 16 [-]: GETGLOBAL R4 K3        ; R4 := 0xa421af95
 17 [-]: MOVE      R5 R2        ; R5 := R2
 18 [-]: CONST     R6 0         ; R6 := 0.000000
 19 [-]: MOVE      R7 R3        ; R7 := R3
 20 [-]: CALL      R4 4 2       ; R4 := R4(R5,R6,R7)
 21 [-]: RETURN    R4 2         ; return R4
 22 [-]: RETURN    R0 1         ; return 


; Function #4:
;
; Name:            
; Defined at line: 160
; #Upvalues:       1
; #Parameters:     0
; Is_vararg:       0
; Max Stack Size:  12

  1 [-]: GETGLOBAL R0 K0        ; R0 := 0xbe190284
  2 [-]: GETUPVAL  R1 U0        ; R1 := U0
  3 [-]: GETTABLE  R1 R1 K1     ; R1 := R1[0xe17b82b0]
  4 [-]: CALL      R1 1 2       ; R1 := R1()
  5 [-]: GETUPVAL  R2 U0        ; R2 := U0
  6 [-]: GETTABLE  R2 R2 K2     ; R2 := R2["UNALERT"]
  7 [-]: LT        0 R2 R1      ; if R2 >= R1 then PC := 11
  8 [-]: JMP       11           ; PC := 11
  9 [-]: LOADKB    R1 1 0       ; R1 := true
 10 [-]: RETURN    R1 2         ; return R1
 11 [-]: SELF      R1 R0 K3     ; R2 := R0; R1 := R0[0x5c390f04]
 12 [-]: CALL      R1 2 2       ; R1 := R1(R2)
 13 [-]: EQ        0 R1 K5      ; if R1 ~= 7.000000 then PC := 49
 14 [-]: JMP       49           ; PC := 49
 15 [-]: NEWTABLE  R2 5 0       ; R2 := {}
 16 [-]: GETGLOBAL R3 K6        ; R3 := 0x0469f296
 17 [-]: LOADK     R4 K7        ; R4 := "VaultAStatus"
 18 [-]: CALL      R3 2 2       ; R3 := R3(R4)
 19 [-]: GETGLOBAL R4 K6        ; R4 := 0x0469f296
 20 [-]: LOADK     R5 K8        ; R5 := "VaultBStatus"
 21 [-]: CALL      R4 2 2       ; R4 := R4(R5)
 22 [-]: GETGLOBAL R5 K6        ; R5 := 0x0469f296
 23 [-]: LOADK     R6 K9        ; R6 := "VaultCStatus"
 24 [-]: CALL      R5 2 2       ; R5 := R5(R6)
 25 [-]: GETGLOBAL R6 K6        ; R6 := 0x0469f296
 26 [-]: LOADK     R7 K10       ; R7 := "VaultDStatus"
 27 [-]: CALL      R6 2 2       ; R6 := R6(R7)
 28 [-]: GETGLOBAL R7 K6        ; R7 := 0x0469f296
 29 [-]: LOADK     R8 K11       ; R8 := "VaultEStatus"
 30 [-]: CALL      R7 2 2       ; R7 := R7(R8)
 31 [-]: GETGLOBAL R8 K6        ; R8 := 0x0469f296
 32 [-]: LOADK     R9 K12       ; R9 := "VaultFStatus"
 33 [-]: CALL      R8 2 0       ; R8,... := R8(R9)
 34 [-]: SETLIST   R2 0 1       ; R2[(1-1)*FPF+i] := R(2+i), 1 <= i <= 0
 35 [-]: GETGLOBAL R3 K13       ; R3 := 0xc8802016
 36 [-]: MOVE      R4 R2        ; R4 := R2
 37 [-]: CALL      R3 2 4       ; R3,R4,R5 := R3(R4)
 38 [-]: JMP       46           ; PC := 46
 39 [-]: SELF      R8 R0 K14    ; R9 := R0; R8 := R0[0x0eb34c69]
 40 [-]: MOVE      R10 R7       ; R10 := R7
 41 [-]: CALL      R8 3 2       ; R8 := R8(R9,R10)
 42 [-]: EQ        0 R8 K15     ; if R8 ~= 3.000000 then PC := 46
 43 [-]: JMP       46           ; PC := 46
 44 [-]: LOADKB    R8 1 0       ; R8 := true
 45 [-]: RETURN    R8 2         ; return R8
 46 [-]: TFORLOOP  R3 2         ; R6,R7 :=  R3(R4,R5); if R6 ~= nil then begin PC = 39; R5 := R6 end
 47 [-]: JMP       39           ; PC := 39
 48 [-]: JMP       67           ; PC := 67
 49 [-]: EQ        0 R1 K15     ; if R1 ~= 3.000000 then PC := 61
 50 [-]: JMP       61           ; PC := 61
 51 [-]: SELF      R8 R0 K14    ; R9 := R0; R8 := R0[0x0eb34c69]
 52 [-]: GETGLOBAL R10 K6       ; R10 := 0x0469f296
 53 [-]: LOADK     R11 K16      ; R11 := "RescueTimeLeft"
 54 [-]: CALL      R10 2 0      ; R10,... := R10(R11)
 55 [-]: CALL      R8 0 2       ; R8 := R8(R9,...)
 56 [-]: LT        0 K17 R8     ; if 0.000000 >= R8 then PC := 67
 57 [-]: JMP       67           ; PC := 67
 58 [-]: LOADKB    R8 1 0       ; R8 := true
 59 [-]: RETURN    R8 2         ; return R8
 60 [-]: JMP       67           ; PC := 67
 61 [-]: GETGLOBAL R8 K18       ; R8 := _T
 62 [-]: GETTABLE  R8 R8 K19    ; R8 := R8["LisetHackAvailable"]
 63 [-]: TEST      R8 0         ; if not R8 then PC := 67
 64 [-]: JMP       67           ; PC := 67
 65 [-]: LOADKB    R8 1 0       ; R8 := true
 66 [-]: RETURN    R8 2         ; return R8
 67 [-]: LOADKB    R8 0 0       ; R8 := false
 68 [-]: RETURN    R8 2         ; return R8
 69 [-]: RETURN    R0 1         ; return 


; Function #5:
;
; Name:            
; Defined at line: 187
; #Upvalues:       0
; #Parameters:     1
; Is_vararg:       0
; Max Stack Size:  9

  1 [-]: GETGLOBAL R1 K0        ; R1 := 0xcbd666e1
  2 [-]: CONST     R2 2         ; R2 := 2.500000
  3 [-]: CALL      R1 2 1       ; R1(R2)
  4 [-]: GETGLOBAL R1 K1        ; R1 := 0xbe190284
  5 [-]: SELF      R1 R1 K2     ; R2 := R1; R1 := R1[0x0eb34c69]
  6 [-]: GETGLOBAL R3 K3        ; R3 := 0x0469f296
  7 [-]: LOADK     R4 K4        ; R4 := "StopNormalTransmissions"
  8 [-]: CALL      R3 2 0       ; R3,... := R3(R4)
  9 [-]: CALL      R1 0 2       ; R1 := R1(R2,...)
 10 [-]: EQ        0 R1 K5      ; if R1 ~= 0.000000 then PC := 24
 11 [-]: JMP       24           ; PC := 24
 12 [-]: GETGLOBAL R1 K6        ; R1 := 0x89326c93
 13 [-]: SELF      R1 R1 K7     ; R2 := R1; R1 := R1[0x8b5b1f58]
 14 [-]: CALL      R1 2 2       ; R1 := R1(R2)
 15 [-]: CONST     R2 1         ; R2 := 1.000000
 16 [-]: LEN       R3 R1        ; R3 := # R1
 17 [-]: CONST     R4 1         ; R4 := 1.000000
 18 [-]: FORPREP   R2 23        ; R2 -= R4; PC := 23
 19 [-]: GETTABLE  R6 R1 R5     ; R6 := R1[R5]
 20 [-]: SELF      R6 R6 K8     ; R7 := R6; R6 := R6[0x2a748f85]
 21 [-]: MOVE      R8 R0        ; R8 := R0
 22 [-]: CALL      R6 3 1       ; R6(R7,R8)
 23 [-]: FORLOOP   R2 19        ; R2 += R4; if R2 <= R3 then begin PC := 19; R5 := R2 end
 24 [-]: GETGLOBAL R6 K0        ; R6 := 0xcbd666e1
 25 [-]: CONST     R7 0         ; R7 := 0.000000
 26 [-]: CALL      R6 2 1       ; R6(R7)
 27 [-]: RETURN    R0 1         ; return 


; Function #6:
;
; Name:            
; Defined at line: 200
; #Upvalues:       4
; #Parameters:     1
; Is_vararg:       0
; Max Stack Size:  12

  1 [-]: GETGLOBAL R1 K0        ; R1 := 0xbe190284
  2 [-]: SELF      R1 R1 K1     ; R2 := R1; R1 := R1[0x0eb34c69]
  3 [-]: GETGLOBAL R3 K2        ; R3 := 0x0469f296
  4 [-]: LOADK     R4 K3        ; R4 := "StopNormalTransmissions"
  5 [-]: CALL      R3 2 0       ; R3,... := R3(R4)
  6 [-]: CALL      R1 0 2       ; R1 := R1(R2,...)
  7 [-]: EQ        0 R1 K4      ; if R1 ~= 0.000000 then PC := 120
  8 [-]: JMP       120          ; PC := 120
  9 [-]: GETUPVAL  R1 U0        ; R1 := U0
 10 [-]: SELF      R1 R1 K5     ; R2 := R1; R1 := R1[0xa5e492d4]
 11 [-]: CALL      R1 2 2       ; R1 := R1(R2)
 12 [-]: GETGLOBAL R2 K6        ; R2 := 0x89326c93
 13 [-]: SELF      R2 R2 K7     ; R3 := R2; R2 := R2[0x18d05d30]
 14 [-]: CALL      R2 2 2       ; R2 := R2(R3)
 15 [-]: TEST      R2 0         ; if not R2 then PC := 25
 16 [-]: JMP       25           ; PC := 25
 17 [-]: GETUPVAL  R2 U0        ; R2 := U0
 18 [-]: SELF      R2 R2 K8     ; R3 := R2; R2 := R2[0x2a748f85]
 19 [-]: MOVE      R4 R0        ; R4 := R0
 20 [-]: CALL      R2 3 1       ; R2(R3,R4)
 21 [-]: GETGLOBAL R2 K9        ; R2 := 0xcbd666e1
 22 [-]: CONST     R3 0         ; R3 := 0.000000
 23 [-]: CALL      R2 2 1       ; R2(R3)
 24 [-]: JMP       36           ; PC := 36
 25 [-]: TEST      R1 0         ; if not R1 then PC := 36
 26 [-]: JMP       36           ; PC := 36
 27 [-]: GETUPVAL  R2 U1        ; R2 := U1
 28 [-]: GETTABLE  R2 R2 K10    ; R2 := R2[0x0deacd54]
 29 [-]: CALL      R2 1 2       ; R2 := R2()
 30 [-]: TEST      R2 1         ; if R2 then PC := 36
 31 [-]: JMP       36           ; PC := 36
 32 [-]: GETGLOBAL R2 K9        ; R2 := 0xcbd666e1
 33 [-]: CONST     R3 0         ; R3 := 0.000000
 34 [-]: CALL      R2 2 1       ; R2(R3)
 35 [-]: JMP       27           ; PC := 27
 36 [-]: TEST      R1 1         ; if R1 then PC := 109
 37 [-]: JMP       109          ; PC := 109
 38 [-]: GETGLOBAL R2 K11       ; R2 := 0xbd496aa1
 39 [-]: GETTABLE  R2 R2 K12    ; R2 := R2[0x42645da3]
 40 [-]: NEWTABLE  R3 0 0       ; R3 := {}
 41 [-]: GETGLOBAL R4 K13       ; R4 := 0x64fb1586
 42 [-]: SELF      R5 R0 K14    ; R6 := R0; R5 := R0[0xed4e0128]
 43 [-]: CALL      R5 2 0       ; R5,... := R5(R6)
 44 [-]: CALL      R4 0 0       ; R4,... := R4(R5,...)
 45 [-]: SETLIST   R3 0 1       ; R3[(1-1)*FPF+i] := R(3+i), 1 <= i <= 0
 46 [-]: CALL      R2 2 2       ; R2 := R2(R3)
 47 [-]: GETGLOBAL R3 K9        ; R3 := 0xcbd666e1
 48 [-]: GETUPVAL  R4 U2        ; R4 := U2
 49 [-]: CALL      R3 2 1       ; R3(R4)
 50 [-]: SELF      R3 R2 K15    ; R4 := R2; R3 := R2[0xd2d3875a]
 51 [-]: CALL      R3 2 2       ; R3 := R3(R4)
 52 [-]: TEST      R3 1         ; if R3 then PC := 58
 53 [-]: JMP       58           ; PC := 58
 54 [-]: GETGLOBAL R3 K9        ; R3 := 0xcbd666e1
 55 [-]: CONST     R4 0         ; R4 := 0.000000
 56 [-]: CALL      R3 2 1       ; R3(R4)
 57 [-]: JMP       50           ; PC := 50
 58 [-]: GETUPVAL  R3 U3        ; R3 := U3
 59 [-]: CALL      R3 1 1       ; R3()
 60 [-]: GETGLOBAL R3 K16       ; R3 := 0xb009bbc6
 61 [-]: MOVE      R4 R0        ; R4 := R0
 62 [-]: CALL      R3 2 2       ; R3 := R3(R4)
 63 [-]: SELF      R4 R3 K17    ; R5 := R3; R4 := R3[0xbd368681]
 64 [-]: CALL      R4 2 2       ; R4 := R4(R5)
 65 [-]: LOADNIL   R5 R5        ; R5 := nil
 66 [-]: GETGLOBAL R6 K18       ; R6 := 0x7b998233
 67 [-]: MOVE      R7 R4        ; R7 := R4
 68 [-]: CALL      R6 2 2       ; R6 := R6(R7)
 69 [-]: TEST      R6 1         ; if R6 then PC := 79
 70 [-]: JMP       79           ; PC := 79
 71 [-]: GETUPVAL  R6 U0        ; R6 := U0
 72 [-]: SELF      R6 R6 K19    ; R7 := R6; R6 := R6[0x659d451f]
 73 [-]: MOVE      R8 R4        ; R8 := R4
 74 [-]: LOADKB    R9 0 0       ; R9 := false
 75 [-]: CONST     R10 0        ; R10 := 0.000000
 76 [-]: LOADKB    R11 0 0      ; R11 := false
 77 [-]: CALL      R6 6 2       ; R6 := R6(R7,R8,R9,R10,R11)
 78 [-]: MOVE      R5 R6        ; R5 := R6
 79 [-]: LOADNIL   R6 R6        ; R6 := nil
 80 [-]: GETGLOBAL R7 K18       ; R7 := 0x7b998233
 81 [-]: MOVE      R8 R5        ; R8 := R5
 82 [-]: CALL      R7 2 2       ; R7 := R7(R8)
 83 [-]: TEST      R7 1         ; if R7 then PC := 91
 84 [-]: JMP       91           ; PC := 91
 85 [-]: SELF      R7 R5 K20    ; R8 := R5; R7 := R5[0xa1f65ece]
 86 [-]: CALL      R7 2 2       ; R7 := R7(R8)
 87 [-]: MOVE      R6 R7        ; R6 := R7
 88 [-]: SELF      R7 R5 K21    ; R8 := R5; R7 := R5[0x6cf1e476]
 89 [-]: LOADKB    R9 1 0       ; R9 := true
 90 [-]: CALL      R7 3 1       ; R7(R8,R9)
 91 [-]: GETGLOBAL R7 K18       ; R7 := 0x7b998233
 92 [-]: MOVE      R8 R6        ; R8 := R6
 93 [-]: CALL      R7 2 2       ; R7 := R7(R8)
 94 [-]: TEST      R7 1         ; if R7 then PC := 105
 95 [-]: JMP       105          ; PC := 105
 96 [-]: LT        0 K4 R6      ; if 0.000000 >= R6 then PC := 105
 97 [-]: JMP       105          ; PC := 105
 98 [-]: GETGLOBAL R7 K9        ; R7 := 0xcbd666e1
 99 [-]: CONST     R8 0         ; R8 := 0.000000
100 [-]: CALL      R7 2 1       ; R7(R8)
101 [-]: GETGLOBAL R7 K22       ; R7 := 0x67652851
102 [-]: CALL      R7 1 2       ; R7 := R7()
103 [-]: SUB       R6 R6 R7     ; R6 := R6 - R7
104 [-]: JMP       96           ; PC := 96
105 [-]: GETGLOBAL R7 K9        ; R7 := 0xcbd666e1
106 [-]: GETUPVAL  R8 U2        ; R8 := U2
107 [-]: CALL      R7 2 1       ; R7(R8)
108 [-]: JMP       118          ; PC := 118
109 [-]: GETUPVAL  R7 U1        ; R7 := U1
110 [-]: GETTABLE  R7 R7 K10    ; R7 := R7[0x0deacd54]
111 [-]: CALL      R7 1 2       ; R7 := R7()
112 [-]: TEST      R7 0         ; if not R7 then PC := 118
113 [-]: JMP       118          ; PC := 118
114 [-]: GETGLOBAL R7 K9        ; R7 := 0xcbd666e1
115 [-]: CONST     R8 0         ; R8 := 0.000000
116 [-]: CALL      R7 2 1       ; R7(R8)
117 [-]: JMP       109          ; PC := 109
118 [-]: GETUPVAL  R7 U3        ; R7 := U3
119 [-]: CALL      R7 1 1       ; R7()
120 [-]: RETURN    R0 1         ; return 


; Function #7:
;
; Name:            
; Defined at line: 250
; #Upvalues:       3
; #Parameters:     1
; Is_vararg:       0
; Max Stack Size:  7

  1 [-]: GETGLOBAL R1 K0        ; R1 := 0x89326c93
  2 [-]: SELF      R1 R1 K1     ; R2 := R1; R1 := R1[0x18d05d30]
  3 [-]: CALL      R1 2 2       ; R1 := R1(R2)
  4 [-]: TEST      R1 0         ; if not R1 then PC := 25
  5 [-]: JMP       25           ; PC := 25
  6 [-]: GETGLOBAL R1 K2        ; R1 := 0xcbd666e1
  7 [-]: GETUPVAL  R2 U0        ; R2 := U0
  8 [-]: CALL      R1 2 1       ; R1(R2)
  9 [-]: GETGLOBAL R1 K3        ; R1 := 0x7b998233
 10 [-]: GETUPVAL  R2 U1        ; R2 := U1
 11 [-]: CALL      R1 2 2       ; R1 := R1(R2)
 12 [-]: TEST      R1 1         ; if R1 then PC := 21
 13 [-]: JMP       21           ; PC := 21
 14 [-]: GETUPVAL  R1 U1        ; R1 := U1
 15 [-]: SELF      R1 R1 K4     ; R2 := R1; R1 := R1[0x659d451f]
 16 [-]: MOVE      R3 R0        ; R3 := R0
 17 [-]: LOADKB    R4 0 0       ; R4 := false
 18 [-]: CONST     R5 0         ; R5 := 0.000000
 19 [-]: LOADKB    R6 1 0       ; R6 := true
 20 [-]: CALL      R1 6 1       ; R1(R2,R3,R4,R5,R6)
 21 [-]: GETGLOBAL R1 K2        ; R1 := 0xcbd666e1
 22 [-]: CONST     R2 2         ; R2 := 2.000000
 23 [-]: CALL      R1 2 1       ; R1(R2)
 24 [-]: JMP       31           ; PC := 31
 25 [-]: GETGLOBAL R1 K2        ; R1 := 0xcbd666e1
 26 [-]: GETUPVAL  R2 U0        ; R2 := U0
 27 [-]: CALL      R1 2 1       ; R1(R2)
 28 [-]: GETGLOBAL R1 K2        ; R1 := 0xcbd666e1
 29 [-]: CONST     R2 2         ; R2 := 2.000000
 30 [-]: CALL      R1 2 1       ; R1(R2)
 31 [-]: GETUPVAL  R1 U2        ; R1 := U2
 32 [-]: CALL      R1 1 1       ; R1()
 33 [-]: RETURN    R0 1         ; return 


; Function #8:
;
; Name:            
; Defined at line: 265
; #Upvalues:       1
; #Parameters:     1
; Is_vararg:       0
; Max Stack Size:  7

  1 [-]: GETGLOBAL R1 K0        ; R1 := 0x89326c93
  2 [-]: SELF      R1 R1 K1     ; R2 := R1; R1 := R1[0x18d05d30]
  3 [-]: CALL      R1 2 2       ; R1 := R1(R2)
  4 [-]: TEST      R1 0         ; if not R1 then PC := 18
  5 [-]: JMP       18           ; PC := 18
  6 [-]: GETGLOBAL R1 K2        ; R1 := 0x7b998233
  7 [-]: GETUPVAL  R2 U0        ; R2 := U0
  8 [-]: CALL      R1 2 2       ; R1 := R1(R2)
  9 [-]: TEST      R1 1         ; if R1 then PC := 18
 10 [-]: JMP       18           ; PC := 18
 11 [-]: GETUPVAL  R1 U0        ; R1 := U0
 12 [-]: SELF      R1 R1 K3     ; R2 := R1; R1 := R1[0x659d451f]
 13 [-]: MOVE      R3 R0        ; R3 := R0
 14 [-]: LOADKB    R4 0 0       ; R4 := false
 15 [-]: CONST     R5 0         ; R5 := 0.000000
 16 [-]: LOADKB    R6 1 0       ; R6 := true
 17 [-]: CALL      R1 6 1       ; R1(R2,R3,R4,R5,R6)
 18 [-]: RETURN    R0 1         ; return 


; Function #9:
;
; Name:            
; Defined at line: 271
; #Upvalues:       7
; #Parameters:     1
; Is_vararg:       0
; Max Stack Size:  23

  1 [-]: GETUPVAL  R1 U0        ; R1 := U0
  2 [-]: SELF      R1 R1 K0     ; R2 := R1; R1 := R1[0xcb3851b8]
  3 [-]: CALL      R1 2 2       ; R1 := R1(R2)
  4 [-]: GETUPVAL  R2 U0        ; R2 := U0
  5 [-]: SELF      R2 R2 K1     ; R3 := R2; R2 := R2[0xd1586535]
  6 [-]: CALL      R2 2 2       ; R2 := R2(R3)
  7 [-]: GETUPVAL  R3 U0        ; R3 := U0
  8 [-]: SELF      R3 R3 K2     ; R4 := R3; R3 := R3[0x9ba17154]
  9 [-]: CALL      R3 2 2       ; R3 := R3(R4)
 10 [-]: MUL       R4 R3 K3     ; R4 := R3 * 1.500000
 11 [-]: ADD       R2 R2 R4     ; R2 := R2 + R4
 12 [-]: LOADNIL   R4 R4        ; R4 := nil
 13 [-]: GETGLOBAL R5 K4        ; R5 := 0xa421af95
 14 [-]: CALL      R5 1 2       ; R5 := R5()
 15 [-]: LOADNIL   R6 R9        ; R6 := R7 := R8 := R9 := nil
 16 [-]: GETUPVAL  R10 U1       ; R10 := U1
 17 [-]: GETGLOBAL R11 K5       ; R11 := 0x9c6d95f7
 18 [-]: CALL      R10 2 1      ; R10(R11)
 19 [-]: GETGLOBAL R10 K6       ; R10 := 0x89326c93
 20 [-]: SELF      R10 R10 K7   ; R11 := R10; R10 := R10[0x18d05d30]
 21 [-]: CALL      R10 2 2      ; R10 := R10(R11)
 22 [-]: TEST      R10 0        ; if not R10 then PC := 198
 23 [-]: JMP       198          ; PC := 198
 24 [-]: GETTABLE  R10 R2 K8    ; R10 := R2["y"]
 25 [-]: ADD       R10 R10 K9   ; R10 := R10 + 0.500000
 26 [-]: SETTABLE  R2 K8 R10    ; R2["y"] := R10
 27 [-]: GETGLOBAL R10 K6       ; R10 := 0x89326c93
 28 [-]: SELF      R10 R10 K10  ; R11 := R10; R10 := R10[0xbd5d0ec1]
 29 [-]: GETUPVAL  R12 U0       ; R12 := U0
 30 [-]: SELF      R12 R12 K1   ; R13 := R12; R12 := R12[0xd1586535]
 31 [-]: CALL      R12 2 2      ; R12 := R12(R13)
 32 [-]: MOVE      R13 R2       ; R13 := R2
 33 [-]: GETUPVAL  R14 U0       ; R14 := U0
 34 [-]: MOVE      R15 R6       ; R15 := R6
 35 [-]: MOVE      R16 R5       ; R16 := R5
 36 [-]: CALL      R10 7 2      ; R10 := R10(R11,R12,R13,R14,R15,R16)
 37 [-]: TEST      R10 0        ; if not R10 then PC := 40
 38 [-]: JMP       40           ; PC := 40
 39 [-]: MOVE      R2 R5        ; R2 := R5
 40 [-]: GETTABLE  R10 R2 K8    ; R10 := R2["y"]
 41 [-]: ADD       R10 R10 K11  ; R10 := R10 + 1.000000
 42 [-]: SETTABLE  R2 K8 R10    ; R2["y"] := R10
 43 [-]: GETGLOBAL R10 K4       ; R10 := 0xa421af95
 44 [-]: GETTABLE  R11 R2 K12   ; R11 := R2["x"]
 45 [-]: GETTABLE  R12 R2 K8    ; R12 := R2["y"]
 46 [-]: GETTABLE  R13 R2 K13   ; R13 := R2["z"]
 47 [-]: CALL      R10 4 2      ; R10 := R10(R11,R12,R13)
 48 [-]: GETTABLE  R11 R10 K8   ; R11 := R10["y"]
 49 [-]: SUB       R11 R11 K14  ; R11 := R11 - 100.000000
 50 [-]: SETTABLE  R10 K8 R11   ; R10["y"] := R11
 51 [-]: GETGLOBAL R11 K6       ; R11 := 0x89326c93
 52 [-]: SELF      R11 R11 K10  ; R12 := R11; R11 := R11[0xbd5d0ec1]
 53 [-]: MOVE      R13 R2       ; R13 := R2
 54 [-]: MOVE      R14 R10      ; R14 := R10
 55 [-]: GETUPVAL  R15 U0       ; R15 := U0
 56 [-]: MOVE      R16 R6       ; R16 := R6
 57 [-]: MOVE      R17 R5       ; R17 := R5
 58 [-]: CALL      R11 7 2      ; R11 := R11(R12,R13,R14,R15,R16,R17)
 59 [-]: TEST      R11 0        ; if not R11 then PC := 62
 60 [-]: JMP       62           ; PC := 62
 61 [-]: MOVE      R2 R5        ; R2 := R5
 62 [-]: GETGLOBAL R11 K15      ; R11 := 0x5bced4c4
 63 [-]: GETTABLE  R11 R11 K16  ; R11 := R11[0xe4a5b3ca]
 64 [-]: GETTABLE  R12 R2 K8    ; R12 := R2["y"]
 65 [-]: GETUPVAL  R13 U0       ; R13 := U0
 66 [-]: SELF      R13 R13 K1   ; R14 := R13; R13 := R13[0xd1586535]
 67 [-]: CALL      R13 2 2      ; R13 := R13(R14)
 68 [-]: GETTABLE  R13 R13 K8   ; R13 := R13["y"]
 69 [-]: SUB       R12 R12 R13  ; R12 := R12 - R13
 70 [-]: CALL      R11 2 2      ; R11 := R11(R12)
 71 [-]: LE        0 K17 R11    ; if 5.000000 > R11 then PC := 97
 72 [-]: JMP       97           ; PC := 97
 73 [-]: GETUPVAL  R12 U0       ; R12 := U0
 74 [-]: SELF      R12 R12 K1   ; R13 := R12; R12 := R12[0xd1586535]
 75 [-]: CALL      R12 2 2      ; R12 := R12(R13)
 76 [-]: MOVE      R2 R12       ; R2 := R12
 77 [-]: GETGLOBAL R12 K4       ; R12 := 0xa421af95
 78 [-]: GETTABLE  R13 R2 K12   ; R13 := R2["x"]
 79 [-]: GETTABLE  R14 R2 K8    ; R14 := R2["y"]
 80 [-]: GETTABLE  R15 R2 K13   ; R15 := R2["z"]
 81 [-]: CALL      R12 4 2      ; R12 := R12(R13,R14,R15)
 82 [-]: MOVE      R10 R12      ; R10 := R12
 83 [-]: GETTABLE  R12 R10 K8   ; R12 := R10["y"]
 84 [-]: SUB       R12 R12 K14  ; R12 := R12 - 100.000000
 85 [-]: SETTABLE  R10 K8 R12   ; R10["y"] := R12
 86 [-]: GETGLOBAL R12 K6       ; R12 := 0x89326c93
 87 [-]: SELF      R12 R12 K10  ; R13 := R12; R12 := R12[0xbd5d0ec1]
 88 [-]: MOVE      R14 R2       ; R14 := R2
 89 [-]: MOVE      R15 R10      ; R15 := R10
 90 [-]: GETUPVAL  R16 U0       ; R16 := U0
 91 [-]: MOVE      R17 R6       ; R17 := R6
 92 [-]: MOVE      R18 R5       ; R18 := R5
 93 [-]: CALL      R12 7 2      ; R12 := R12(R13,R14,R15,R16,R17,R18)
 94 [-]: TEST      R12 0        ; if not R12 then PC := 97
 95 [-]: JMP       97           ; PC := 97
 96 [-]: MOVE      R2 R5        ; R2 := R5
 97 [-]: LOADKB    R12 0 0      ; R12 := false
 98 [-]: GETGLOBAL R13 K6       ; R13 := 0x89326c93
 99 [-]: SELF      R13 R13 K18  ; R14 := R13; R13 := R13[0xfb669000]
100 [-]: GETGLOBAL R15 K19      ; R15 := 0x487dd972
101 [-]: MOVE      R16 R2       ; R16 := R2
102 [-]: CONST     R17 0        ; R17 := 0.000000
103 [-]: GETGLOBAL R18 K20      ; R18 := 0xeaa6fd13
104 [-]: CALL      R13 6 2      ; R13 := R13(R14,R15,R16,R17,R18)
105 [-]: LEN       R14 R13      ; R14 := # R13
106 [-]: LT        0 K21 R14    ; if 0.000000 >= R14 then PC := 137
107 [-]: JMP       137          ; PC := 137
108 [-]: GETGLOBAL R14 K22      ; R14 := 0x7b998233
109 [-]: GETTABLE  R15 R13 K11  ; R15 := R13[1.000000]
110 [-]: CALL      R14 2 2      ; R14 := R14(R15)
111 [-]: TEST      R14 1        ; if R14 then PC := 137
112 [-]: JMP       137          ; PC := 137
113 [-]: LOADKB    R12 1 0      ; R12 := true
114 [-]: GETTABLE  R14 R13 K11  ; R14 := R13[1.000000]
115 [-]: SELF      R14 R14 K1   ; R15 := R14; R14 := R14[0xd1586535]
116 [-]: CALL      R14 2 2      ; R14 := R14(R15)
117 [-]: SUB       R14 R14 R2   ; R14 := R14 - R2
118 [-]: SETTABLE  R14 K8 K21   ; R14["y"] := 0.000000
119 [-]: GETGLOBAL R15 K23      ; R15 := 0xc2892f65
120 [-]: MOVE      R16 R14      ; R16 := R14
121 [-]: CALL      R15 2 1      ; R15(R16)
122 [-]: GETGLOBAL R15 K20      ; R15 := 0xeaa6fd13
123 [-]: MUL       R15 R14 R15  ; R15 := R14 * R15
124 [-]: SUB       R2 R2 R15    ; R2 := R2 - R15
125 [-]: GETGLOBAL R15 K6       ; R15 := 0x89326c93
126 [-]: SELF      R15 R15 K18  ; R16 := R15; R15 := R15[0xfb669000]
127 [-]: GETGLOBAL R17 K19      ; R17 := 0x487dd972
128 [-]: MOVE      R18 R2       ; R18 := R2
129 [-]: CONST     R19 0        ; R19 := 0.000000
130 [-]: GETGLOBAL R20 K20      ; R20 := 0xeaa6fd13
131 [-]: CALL      R15 6 2      ; R15 := R15(R16,R17,R18,R19,R20)
132 [-]: MOVE      R13 R15      ; R13 := R15
133 [-]: GETGLOBAL R15 K24      ; R15 := 0xcbd666e1
134 [-]: CONST     R16 0        ; R16 := 0.000000
135 [-]: CALL      R15 2 1      ; R15(R16)
136 [-]: JMP       105          ; PC := 105
137 [-]: GETUPVAL  R15 U2       ; R15 := U2
138 [-]: CALL      R15 1 1      ; R15()
139 [-]: TEST      R12 0        ; if not R12 then PC := 161
140 [-]: JMP       161          ; PC := 161
141 [-]: GETTABLE  R15 R2 K8    ; R15 := R2["y"]
142 [-]: ADD       R15 R15 K11  ; R15 := R15 + 1.000000
143 [-]: SETTABLE  R2 K8 R15    ; R2["y"] := R15
144 [-]: GETGLOBAL R15 K4       ; R15 := 0xa421af95
145 [-]: GETTABLE  R16 R2 K12   ; R16 := R2["x"]
146 [-]: GETTABLE  R17 R2 K8    ; R17 := R2["y"]
147 [-]: SUB       R17 R17 K25  ; R17 := R17 - 10.000000
148 [-]: GETTABLE  R18 R2 K13   ; R18 := R2["z"]
149 [-]: CALL      R15 4 2      ; R15 := R15(R16,R17,R18)
150 [-]: GETGLOBAL R16 K6       ; R16 := 0x89326c93
151 [-]: SELF      R16 R16 K10  ; R17 := R16; R16 := R16[0xbd5d0ec1]
152 [-]: MOVE      R18 R2       ; R18 := R2
153 [-]: MOVE      R19 R15      ; R19 := R15
154 [-]: GETUPVAL  R20 U0       ; R20 := U0
155 [-]: LOADNIL   R21 R21      ; R21 := nil
156 [-]: MOVE      R22 R5       ; R22 := R5
157 [-]: CALL      R16 7 2      ; R16 := R16(R17,R18,R19,R20,R21,R22)
158 [-]: TEST      R16 0        ; if not R16 then PC := 161
159 [-]: JMP       161          ; PC := 161
160 [-]: MOVE      R2 R5        ; R2 := R5
161 [-]: GETTABLE  R16 R1 K26   ; R16 := R1["pitch"]
162 [-]: SUB       R16 R16 K27  ; R16 := R16 - 90.000000
163 [-]: SETTABLE  R1 K26 R16   ; R1["pitch"] := R16
164 [-]: GETUPVAL  R16 U0       ; R16 := U0
165 [-]: SELF      R16 R16 K28  ; R17 := R16; R16 := R16[0xde321e6f]
166 [-]: CALL      R16 2 2      ; R16 := R16(R17)
167 [-]: SELF      R16 R16 K29  ; R17 := R16; R16 := R16[0xf7d48ee0]
168 [-]: CALL      R16 2 2      ; R16 := R16(R17)
169 [-]: MOVE      R7 R16       ; R7 := R16
170 [-]: GETGLOBAL R16 K6       ; R16 := 0x89326c93
171 [-]: SELF      R16 R16 K30  ; R17 := R16; R16 := R16[0x05909209]
172 [-]: GETGLOBAL R18 K31      ; R18 := 0xb367793a
173 [-]: MOVE      R19 R2       ; R19 := R2
174 [-]: MOVE      R20 R1       ; R20 := R1
175 [-]: MOVE      R21 R7       ; R21 := R7
176 [-]: CALL      R16 6 2      ; R16 := R16(R17,R18,R19,R20,R21)
177 [-]: MOVE      R4 R16       ; R4 := R16
178 [-]: GETTABLE  R16 R1 K26   ; R16 := R1["pitch"]
179 [-]: ADD       R16 R16 K27  ; R16 := R16 + 90.000000
180 [-]: SETTABLE  R1 K26 R16   ; R1["pitch"] := R16
181 [-]: GETGLOBAL R16 K4       ; R16 := 0xa421af95
182 [-]: GETTABLE  R17 R2 K12   ; R17 := R2["x"]
183 [-]: GETTABLE  R18 R2 K8    ; R18 := R2["y"]
184 [-]: GETTABLE  R19 R2 K13   ; R19 := R2["z"]
185 [-]: CALL      R16 4 2      ; R16 := R16(R17,R18,R19)
186 [-]: MOVE      R8 R16       ; R8 := R16
187 [-]: GETTABLE  R16 R8 K13   ; R16 := R8["z"]
188 [-]: SUB       R16 R16 K11  ; R16 := R16 - 1.000000
189 [-]: SETTABLE  R8 K13 R16   ; R8["z"] := R16
190 [-]: GETGLOBAL R16 K6       ; R16 := 0x89326c93
191 [-]: SELF      R16 R16 K30  ; R17 := R16; R16 := R16[0x05909209]
192 [-]: GETGLOBAL R18 K32      ; R18 := 0x0f32522b
193 [-]: MOVE      R19 R8       ; R19 := R8
194 [-]: MOVE      R20 R1       ; R20 := R1
195 [-]: GETUPVAL  R21 U0       ; R21 := U0
196 [-]: CALL      R16 6 2      ; R16 := R16(R17,R18,R19,R20,R21)
197 [-]: MOVE      R9 R16       ; R9 := R16
198 [-]: GETUPVAL  R16 U3       ; R16 := U3
199 [-]: GETGLOBAL R17 K33      ; R17 := 0x31643bcd
200 [-]: CALL      R16 2 1      ; R16(R17)
201 [-]: GETUPVAL  R16 U4       ; R16 := U4
202 [-]: GETGLOBAL R17 K34      ; R17 := 0x2bffb364
203 [-]: CALL      R16 2 1      ; R16(R17)
204 [-]: GETGLOBAL R16 K6       ; R16 := 0x89326c93
205 [-]: SELF      R16 R16 K7   ; R17 := R16; R16 := R16[0x18d05d30]
206 [-]: CALL      R16 2 2      ; R16 := R16(R17)
207 [-]: TEST      R16 0        ; if not R16 then PC := 257
208 [-]: JMP       257          ; PC := 257
209 [-]: GETGLOBAL R16 K6       ; R16 := 0x89326c93
210 [-]: SELF      R16 R16 K30  ; R17 := R16; R16 := R16[0x05909209]
211 [-]: GETGLOBAL R18 K35      ; R18 := 0x71f576f7
212 [-]: MOVE      R19 R2       ; R19 := R2
213 [-]: MOVE      R20 R1       ; R20 := R1
214 [-]: MOVE      R21 R7       ; R21 := R7
215 [-]: CALL      R16 6 1      ; R16(R17,R18,R19,R20,R21)
216 [-]: GETGLOBAL R16 K22      ; R16 := 0x7b998233
217 [-]: MOVE      R17 R4       ; R17 := R4
218 [-]: CALL      R16 2 2      ; R16 := R16(R17)
219 [-]: TEST      R16 1        ; if R16 then PC := 225
220 [-]: JMP       225          ; PC := 225
221 [-]: GETGLOBAL R16 K6       ; R16 := 0x89326c93
222 [-]: SELF      R16 R16 K36  ; R17 := R16; R16 := R16[0x59c96e77]
223 [-]: MOVE      R18 R4       ; R18 := R4
224 [-]: CALL      R16 3 1      ; R16(R17,R18)
225 [-]: GETTABLE  R16 R8 K13   ; R16 := R8["z"]
226 [-]: ADD       R16 R16 K11  ; R16 := R16 + 1.000000
227 [-]: SETTABLE  R8 K13 R16   ; R8["z"] := R16
228 [-]: GETGLOBAL R16 K6       ; R16 := 0x89326c93
229 [-]: SELF      R16 R16 K30  ; R17 := R16; R16 := R16[0x05909209]
230 [-]: GETGLOBAL R18 K37      ; R18 := 0x9c948e44
231 [-]: MOVE      R19 R8       ; R19 := R8
232 [-]: MOVE      R20 R1       ; R20 := R1
233 [-]: GETUPVAL  R21 U5       ; R21 := U5
234 [-]: GETUPVAL  R22 U5       ; R22 := U5
235 [-]: CALL      R16 7 1      ; R16(R17,R18,R19,R20,R21,R22)
236 [-]: GETUPVAL  R16 U0       ; R16 := U0
237 [-]: SELF      R16 R16 K28  ; R17 := R16; R16 := R16[0xde321e6f]
238 [-]: CALL      R16 2 2      ; R16 := R16(R17)
239 [-]: SELF      R16 R16 K38  ; R17 := R16; R16 := R16[0x40a5b7af]
240 [-]: SELF      R18 R0 K39   ; R19 := R0; R18 := R0[0x24b019ac]
241 [-]: CALL      R18 2 0      ; R18,... := R18(R19)
242 [-]: CALL      R16 0 1      ; R16(R17,...)
243 [-]: SELF      R16 R0 K40   ; R17 := R0; R16 := R0[0xcc2fcc95]
244 [-]: LOADKB    R18 0 0      ; R18 := false
245 [-]: CALL      R16 3 1      ; R16(R17,R18)
246 [-]: GETGLOBAL R16 K22      ; R16 := 0x7b998233
247 [-]: MOVE      R17 R9       ; R17 := R9
248 [-]: CALL      R16 2 2      ; R16 := R16(R17)
249 [-]: TEST      R16 1        ; if R16 then PC := 253
250 [-]: JMP       253          ; PC := 253
251 [-]: SELF      R16 R9 K41   ; R17 := R9; R16 := R9[0xa2880940]
252 [-]: CALL      R16 2 1      ; R16(R17)
253 [-]: GETUPVAL  R16 U6       ; R16 := U6
254 [-]: GETGLOBAL R17 K42      ; R17 := 0x2b101027
255 [-]: CALL      R16 2 1      ; R16(R17)
256 [-]: JMP       260          ; PC := 260
257 [-]: SELF      R16 R0 K40   ; R17 := R0; R16 := R0[0xcc2fcc95]
258 [-]: LOADKB    R18 0 0      ; R18 := false
259 [-]: CALL      R16 3 1      ; R16(R17,R18)
260 [-]: RETURN    R0 1         ; return 


; Function #10:
;
; Name:            
; Defined at line: 369
; #Upvalues:       1
; #Parameters:     0
; Is_vararg:       0
; Max Stack Size:  3

  1 [-]: GETGLOBAL R0 K0        ; R0 := 0x89326c93
  2 [-]: SELF      R0 R0 K1     ; R1 := R0; R0 := R0[0x18d05d30]
  3 [-]: CALL      R0 2 2       ; R0 := R0(R1)
  4 [-]: TEST      R0 0         ; if not R0 then PC := 37
  5 [-]: JMP       37           ; PC := 37
  6 [-]: GETGLOBAL R0 K2        ; R0 := 0xbe190284
  7 [-]: SELF      R0 R0 K3     ; R1 := R0; R0 := R0[0xef893aec]
  8 [-]: CALL      R0 2 2       ; R0 := R0(R1)
  9 [-]: GETTABLE  R0 R0 K4     ; R0 := R0["missionType"]
 10 [-]: EQ        0 R0 K6      ; if R0 ~= 0.000000 then PC := 18
 11 [-]: JMP       18           ; PC := 18
 12 [-]: GETGLOBAL R0 K2        ; R0 := 0xbe190284
 13 [-]: SELF      R0 R0 K3     ; R1 := R0; R0 := R0[0xef893aec]
 14 [-]: CALL      R0 2 2       ; R0 := R0(R1)
 15 [-]: GETTABLE  R0 R0 K7     ; R0 := R0["maxWaveNum"]
 16 [-]: LT        1 K6 R0      ; if 0.000000 < R0 then PC := 19
 17 [-]: JMP       19           ; PC := 19
 18 [-]: LOADKB    R0 0 1       ; R0 := false; PC := 19
 19 [-]: LOADKB    R0 1 0       ; R0 := true
 20 [-]: GETUPVAL  R1 U0        ; R1 := U0
 21 [-]: GETTABLE  R1 R1 K8     ; R1 := R1[0xe17b82b0]
 22 [-]: CALL      R1 1 2       ; R1 := R1()
 23 [-]: GETUPVAL  R2 U0        ; R2 := U0
 24 [-]: GETTABLE  R2 R2 K9     ; R2 := R2["UNALERT"]
 25 [-]: LT        0 R2 R1      ; if R2 >= R1 then PC := 37
 26 [-]: JMP       37           ; PC := 37
 27 [-]: TEST      R0 1         ; if R0 then PC := 37
 28 [-]: JMP       37           ; PC := 37
 29 [-]: GETUPVAL  R1 U0        ; R1 := U0
 30 [-]: GETTABLE  R1 R1 K10    ; R1 := R1[0x67a78dad]
 31 [-]: GETUPVAL  R2 U0        ; R2 := U0
 32 [-]: GETTABLE  R2 R2 K9     ; R2 := R2["UNALERT"]
 33 [-]: CALL      R1 2 1       ; R1(R2)
 34 [-]: GETUPVAL  R1 U0        ; R1 := U0
 35 [-]: GETTABLE  R1 R1 K11    ; R1 := R1[0x3364d2a5]
 36 [-]: CALL      R1 1 1       ; R1()
 37 [-]: RETURN    R0 1         ; return 


; Function #11:
;
; Name:            
; Defined at line: 379
; #Upvalues:       0
; #Parameters:     1
; Is_vararg:       0
; Max Stack Size:  11

  1 [-]: GETGLOBAL R1 K0        ; R1 := 0x89326c93
  2 [-]: SELF      R1 R1 K1     ; R2 := R1; R1 := R1[0xc7fcada9]
  3 [-]: GETGLOBAL R3 K2        ; R3 := 0x0469f296
  4 [-]: LOADK     R4 K3        ; R4 := "PanicButtonTag"
  5 [-]: CALL      R3 2 0       ; R3,... := R3(R4)
  6 [-]: CALL      R1 0 2       ; R1 := R1(R2,...)
  7 [-]: GETGLOBAL R2 K4        ; R2 := 0x7b998233
  8 [-]: MOVE      R3 R1        ; R3 := R1
  9 [-]: CALL      R2 2 2       ; R2 := R2(R3)
 10 [-]: TEST      R2 1         ; if R2 then PC := 41
 11 [-]: JMP       41           ; PC := 41
 12 [-]: CONST     R2 1         ; R2 := 1.000000
 13 [-]: LEN       R3 R1        ; R3 := # R1
 14 [-]: CONST     R4 1         ; R4 := 1.000000
 15 [-]: FORPREP   R2 40        ; R2 -= R4; PC := 40
 16 [-]: TEST      R0 0         ; if not R0 then PC := 32
 17 [-]: JMP       32           ; PC := 32
 18 [-]: GETTABLE  R6 R1 R5     ; R6 := R1[R5]
 19 [-]: SELF      R6 R6 K5     ; R7 := R6; R6 := R6[0xddafe257]
 20 [-]: CONST     R8 1         ; R8 := 1.000000
 21 [-]: CALL      R6 3 2       ; R6 := R6(R7,R8)
 22 [-]: GETGLOBAL R7 K6        ; R7 := 0x263cbbbd
 23 [-]: EQ        0 R6 R7      ; if R6 ~= R7 then PC := 32
 24 [-]: JMP       32           ; PC := 32
 25 [-]: GETTABLE  R6 R1 R5     ; R6 := R1[R5]
 26 [-]: SELF      R6 R6 K7     ; R7 := R6; R6 := R6[0xcddc3abb]
 27 [-]: CONST     R8 1         ; R8 := 1.000000
 28 [-]: GETGLOBAL R9 K8        ; R9 := 0x175db2a4
 29 [-]: LOADKB    R10 0 0      ; R10 := false
 30 [-]: CALL      R6 5 1       ; R6(R7,R8,R9,R10)
 31 [-]: JMP       40           ; PC := 40
 32 [-]: TEST      R0 1         ; if R0 then PC := 40
 33 [-]: JMP       40           ; PC := 40
 34 [-]: GETTABLE  R6 R1 R5     ; R6 := R1[R5]
 35 [-]: SELF      R6 R6 K7     ; R7 := R6; R6 := R6[0xcddc3abb]
 36 [-]: CONST     R8 1         ; R8 := 1.000000
 37 [-]: GETGLOBAL R9 K6        ; R9 := 0x263cbbbd
 38 [-]: LOADKB    R10 0 0      ; R10 := false
 39 [-]: CALL      R6 5 1       ; R6(R7,R8,R9,R10)
 40 [-]: FORLOOP   R2 16        ; R2 += R4; if R2 <= R3 then begin PC := 16; R5 := R2 end
 41 [-]: RETURN    R0 1         ; return 


; Function #12:
;
; Name:            
; Defined at line: 392
; #Upvalues:       0
; #Parameters:     1
; Is_vararg:       0
; Max Stack Size:  13

  1 [-]: GETGLOBAL R1 K0        ; R1 := 0x89326c93
  2 [-]: SELF      R1 R1 K1     ; R2 := R1; R1 := R1[0xfb669000]
  3 [-]: GETGLOBAL R3 K2        ; R3 := gLotusNpcAvatarType
  4 [-]: SELF      R4 R0 K3     ; R5 := R0; R4 := R0[0xd1586535]
  5 [-]: CALL      R4 2 2       ; R4 := R4(R5)
  6 [-]: CONST     R5 0         ; R5 := 0.000000
  7 [-]: CONST     R6 20        ; R6 := 20.000000
  8 [-]: CALL      R1 6 2       ; R1 := R1(R2,R3,R4,R5,R6)
  9 [-]: GETGLOBAL R2 K4        ; R2 := 0x7ed0a956
 10 [-]: LOADK     R3 K5        ; R3 := "/Lotus/Types/Enemies/Corpus/Turrets/TurretAvatars/SecurityCameraAvatar"
 11 [-]: CALL      R2 2 2       ; R2 := R2(R3)
 12 [-]: CONST     R3 1         ; R3 := 1.000000
 13 [-]: LEN       R4 R1        ; R4 := # R1
 14 [-]: CONST     R5 1         ; R5 := 1.000000
 15 [-]: FORPREP   R3 36        ; R3 -= R5; PC := 36
 16 [-]: GETTABLE  R7 R1 R6     ; R7 := R1[R6]
 17 [-]: SELF      R7 R7 K6     ; R8 := R7; R7 := R7[0xf2deaf69]
 18 [-]: MOVE      R9 R2        ; R9 := R2
 19 [-]: CALL      R7 3 2       ; R7 := R7(R8,R9)
 20 [-]: TEST      R7 0         ; if not R7 then PC := 36
 21 [-]: JMP       36           ; PC := 36
 22 [-]: GETTABLE  R7 R1 R6     ; R7 := R1[R6]
 23 [-]: SELF      R7 R7 K7     ; R8 := R7; R7 := R7[0xfa9e477f]
 24 [-]: CALL      R7 2 2       ; R7 := R7(R8)
 25 [-]: GETGLOBAL R8 K8        ; R8 := 0x7b998233
 26 [-]: MOVE      R9 R7        ; R9 := R7
 27 [-]: CALL      R8 2 2       ; R8 := R8(R9)
 28 [-]: TEST      R8 1         ; if R8 then PC := 36
 29 [-]: JMP       36           ; PC := 36
 30 [-]: SELF      R8 R7 K9     ; R9 := R7; R8 := R7[0x55e9211c]
 31 [-]: LOADKB    R10 1 0      ; R10 := true
 32 [-]: GETGLOBAL R11 K10      ; R11 := 0x0469f296
 33 [-]: LOADK     R12 K11      ; R12 := "HARLEQUIN_CHANGE"
 34 [-]: CALL      R11 2 0      ; R11,... := R11(R12)
 35 [-]: CALL      R8 0 1       ; R8(R9,...)
 36 [-]: FORLOOP   R3 16        ; R3 += R5; if R3 <= R4 then begin PC := 16; R6 := R3 end
 37 [-]: RETURN    R0 1         ; return 


; Function #13:
;
; Name:            
; Defined at line: 405
; #Upvalues:       11
; #Parameters:     1
; Is_vararg:       0
; Max Stack Size:  16

  1 [-]: GETUPVAL  R1 U0        ; R1 := U0
  2 [-]: SELF      R1 R1 K0     ; R2 := R1; R1 := R1[0xde321e6f]
  3 [-]: CALL      R1 2 2       ; R1 := R1(R2)
  4 [-]: SELF      R1 R1 K1     ; R2 := R1; R1 := R1[0xf7d48ee0]
  5 [-]: CALL      R1 2 2       ; R1 := R1(R2)
  6 [-]: GETUPVAL  R2 U0        ; R2 := U0
  7 [-]: SELF      R2 R2 K2     ; R3 := R2; R2 := R2[0xf6ebd926]
  8 [-]: CALL      R2 2 2       ; R2 := R2(R3)
  9 [-]: GETTABLE  R3 R2 K3     ; R3 := R2["y"]
 10 [-]: ADD       R3 R3 K4     ; R3 := R3 + 1.000000
 11 [-]: SETTABLE  R2 K3 R3     ; R2["y"] := R3
 12 [-]: GETUPVAL  R3 U0        ; R3 := U0
 13 [-]: SELF      R3 R3 K5     ; R4 := R3; R3 := R3[0x5280b883]
 14 [-]: CALL      R3 2 2       ; R3 := R3(R4)
 15 [-]: LOADNIL   R4 R5        ; R4 := R5 := nil
 16 [-]: GETGLOBAL R6 K6        ; R6 := 0xa421af95
 17 [-]: CALL      R6 1 2       ; R6 := R6()
 18 [-]: LOADNIL   R7 R7        ; R7 := nil
 19 [-]: GETUPVAL  R8 U1        ; R8 := U1
 20 [-]: GETGLOBAL R9 K7        ; R9 := 0x16fe2d0e
 21 [-]: CALL      R8 2 1       ; R8(R9)
 22 [-]: GETGLOBAL R8 K8        ; R8 := 0x89326c93
 23 [-]: SELF      R8 R8 K9     ; R9 := R8; R8 := R8[0x18d05d30]
 24 [-]: CALL      R8 2 2       ; R8 := R8(R9)
 25 [-]: TEST      R8 0         ; if not R8 then PC := 62
 26 [-]: JMP       62           ; PC := 62
 27 [-]: GETGLOBAL R8 K6        ; R8 := 0xa421af95
 28 [-]: GETTABLE  R9 R2 K10    ; R9 := R2["x"]
 29 [-]: GETTABLE  R10 R2 K3    ; R10 := R2["y"]
 30 [-]: GETTABLE  R11 R2 K11   ; R11 := R2["z"]
 31 [-]: CALL      R8 4 2       ; R8 := R8(R9,R10,R11)
 32 [-]: GETTABLE  R9 R8 K3     ; R9 := R8["y"]
 33 [-]: SUB       R9 R9 K12    ; R9 := R9 - 100.000000
 34 [-]: SETTABLE  R8 K3 R9     ; R8["y"] := R9
 35 [-]: GETGLOBAL R9 K8        ; R9 := 0x89326c93
 36 [-]: SELF      R9 R9 K13    ; R10 := R9; R9 := R9[0xbd5d0ec1]
 37 [-]: MOVE      R11 R2       ; R11 := R2
 38 [-]: MOVE      R12 R8       ; R12 := R8
 39 [-]: GETUPVAL  R13 U0       ; R13 := U0
 40 [-]: MOVE      R14 R7       ; R14 := R7
 41 [-]: MOVE      R15 R6       ; R15 := R6
 42 [-]: CALL      R9 7 2       ; R9 := R9(R10,R11,R12,R13,R14,R15)
 43 [-]: TEST      R9 0         ; if not R9 then PC := 46
 44 [-]: JMP       46           ; PC := 46
 45 [-]: MOVE      R2 R6        ; R2 := R6
 46 [-]: GETGLOBAL R9 K8        ; R9 := 0x89326c93
 47 [-]: SELF      R9 R9 K14    ; R10 := R9; R9 := R9[0x05909209]
 48 [-]: GETGLOBAL R11 K15      ; R11 := 0xb367793a
 49 [-]: MOVE      R12 R2       ; R12 := R2
 50 [-]: MOVE      R13 R3       ; R13 := R3
 51 [-]: MOVE      R14 R1       ; R14 := R1
 52 [-]: CALL      R9 6 2       ; R9 := R9(R10,R11,R12,R13,R14)
 53 [-]: MOVE      R4 R9        ; R4 := R9
 54 [-]: GETGLOBAL R9 K8        ; R9 := 0x89326c93
 55 [-]: SELF      R9 R9 K14    ; R10 := R9; R9 := R9[0x05909209]
 56 [-]: GETGLOBAL R11 K16      ; R11 := 0xe4a9e882
 57 [-]: MOVE      R12 R2       ; R12 := R2
 58 [-]: MOVE      R13 R3       ; R13 := R3
 59 [-]: MOVE      R14 R1       ; R14 := R1
 60 [-]: CALL      R9 6 2       ; R9 := R9(R10,R11,R12,R13,R14)
 61 [-]: MOVE      R5 R9        ; R5 := R9
 62 [-]: GETUPVAL  R9 U2        ; R9 := U2
 63 [-]: GETGLOBAL R10 K17      ; R10 := 0xe64b6090
 64 [-]: CALL      R9 2 1       ; R9(R10)
 65 [-]: GETUPVAL  R9 U3        ; R9 := U3
 66 [-]: GETGLOBAL R10 K18      ; R10 := 0x369155d7
 67 [-]: CALL      R9 2 1       ; R9(R10)
 68 [-]: GETGLOBAL R9 K8        ; R9 := 0x89326c93
 69 [-]: SELF      R9 R9 K9     ; R10 := R9; R9 := R9[0x18d05d30]
 70 [-]: CALL      R9 2 2       ; R9 := R9(R10)
 71 [-]: TEST      R9 0         ; if not R9 then PC := 92
 72 [-]: JMP       92           ; PC := 92
 73 [-]: GETGLOBAL R9 K19       ; R9 := 0x7b998233
 74 [-]: MOVE      R10 R4       ; R10 := R4
 75 [-]: CALL      R9 2 2       ; R9 := R9(R10)
 76 [-]: TEST      R9 1         ; if R9 then PC := 85
 77 [-]: JMP       85           ; PC := 85
 78 [-]: SELF      R9 R4 K20    ; R10 := R4; R9 := R4[0x47901f07]
 79 [-]: GETGLOBAL R11 K21      ; R11 := 0x88e7bb1e
 80 [-]: GETGLOBAL R12 K22      ; R12 := EMPTY_SYMBOL
 81 [-]: GETGLOBAL R13 K23      ; R13 := ZERO_VECTOR
 82 [-]: GETGLOBAL R14 K24      ; R14 := ZERO_ROTATION
 83 [-]: MOVE      R15 R1       ; R15 := R1
 84 [-]: CALL      R9 7 1       ; R9(R10,R11,R12,R13,R14,R15)
 85 [-]: GETGLOBAL R9 K19       ; R9 := 0x7b998233
 86 [-]: MOVE      R10 R5       ; R10 := R5
 87 [-]: CALL      R9 2 2       ; R9 := R9(R10)
 88 [-]: TEST      R9 1         ; if R9 then PC := 92
 89 [-]: JMP       92           ; PC := 92
 90 [-]: SELF      R9 R5 K25    ; R10 := R5; R9 := R5[0xa2880940]
 91 [-]: CALL      R9 2 1       ; R9(R10)
 92 [-]: GETUPVAL  R9 U4        ; R9 := U4
 93 [-]: CALL      R9 1 1       ; R9()
 94 [-]: GETGLOBAL R9 K26       ; R9 := 0xcbd666e1
 95 [-]: CONST     R10 0        ; R10 := 0.000000
 96 [-]: CALL      R9 2 1       ; R9(R10)
 97 [-]: GETUPVAL  R9 U5        ; R9 := U5
 98 [-]: LOADKB    R10 1 0      ; R10 := true
 99 [-]: CALL      R9 2 1       ; R9(R10)
100 [-]: GETUPVAL  R9 U6        ; R9 := U6
101 [-]: CALL      R9 1 1       ; R9()
102 [-]: GETGLOBAL R9 K8        ; R9 := 0x89326c93
103 [-]: SELF      R9 R9 K9     ; R10 := R9; R9 := R9[0x18d05d30]
104 [-]: CALL      R9 2 2       ; R9 := R9(R10)
105 [-]: TEST      R9 0         ; if not R9 then PC := 132
106 [-]: JMP       132          ; PC := 132
107 [-]: GETUPVAL  R9 U7        ; R9 := U7
108 [-]: MOVE      R10 R4       ; R10 := R4
109 [-]: CALL      R9 2 1       ; R9(R10)
110 [-]: GETGLOBAL R9 K27       ; R9 := _T
111 [-]: SETTABLE  R9 K28 K29   ; R9["PauseVaultTimer"] := true
112 [-]: GETGLOBAL R9 K30       ; R9 := 0xbe190284
113 [-]: SELF      R9 R9 K31    ; R10 := R9; R9 := R9[0x0eb34c69]
114 [-]: GETGLOBAL R11 K32      ; R11 := 0x0469f296
115 [-]: LOADK     R12 K33      ; R12 := "StopNormalTransmissions"
116 [-]: CALL      R11 2 0      ; R11,... := R11(R12)
117 [-]: CALL      R9 0 2       ; R9 := R9(R10,...)
118 [-]: EQ        0 R9 K34     ; if R9 ~= 0.000000 then PC := 149
119 [-]: JMP       149          ; PC := 149
120 [-]: GETUPVAL  R9 U8        ; R9 := U8
121 [-]: GETGLOBAL R10 K35      ; R10 := 0x48f3cbc6
122 [-]: CALL      R9 2 1       ; R9(R10)
123 [-]: GETUPVAL  R9 U9        ; R9 := U9
124 [-]: GETTABLE  R9 R9 K36    ; R9 := R9[0x9742b85b]
125 [-]: GETGLOBAL R10 K27      ; R10 := _T
126 [-]: GETTABLE  R10 R10 K37  ; R10 := R10["AmbientMissionTransmissionSet"]
127 [-]: GETGLOBAL R11 K32      ; R11 := 0x0469f296
128 [-]: LOADK     R12 K38      ; R12 := "EnemiesUnalert"
129 [-]: CALL      R11 2 0      ; R11,... := R11(R12)
130 [-]: CALL      R9 0 1       ; R9(R10,...)
131 [-]: JMP       149          ; PC := 149
132 [-]: GETGLOBAL R9 K30       ; R9 := 0xbe190284
133 [-]: SELF      R9 R9 K31    ; R10 := R9; R9 := R9[0x0eb34c69]
134 [-]: GETGLOBAL R11 K32      ; R11 := 0x0469f296
135 [-]: LOADK     R12 K33      ; R12 := "StopNormalTransmissions"
136 [-]: CALL      R11 2 0      ; R11,... := R11(R12)
137 [-]: CALL      R9 0 2       ; R9 := R9(R10,...)
138 [-]: EQ        0 R9 K34     ; if R9 ~= 0.000000 then PC := 149
139 [-]: JMP       149          ; PC := 149
140 [-]: GETUPVAL  R9 U10       ; R9 := U10
141 [-]: GETTABLE  R9 R9 K39    ; R9 := R9[0x0deacd54]
142 [-]: CALL      R9 1 2       ; R9 := R9()
143 [-]: TEST      R9 1         ; if R9 then PC := 149
144 [-]: JMP       149          ; PC := 149
145 [-]: GETGLOBAL R9 K26       ; R9 := 0xcbd666e1
146 [-]: CONST     R10 0        ; R10 := 0.000000
147 [-]: CALL      R9 2 1       ; R9(R10)
148 [-]: JMP       140          ; PC := 140
149 [-]: CONST     R9 0         ; R9 := 0.500000
150 [-]: GETGLOBAL R10 K40      ; R10 := 0xa2e2b25b
151 [-]: LT        0 K34 R10    ; if 0.000000 >= R10 then PC := 165
152 [-]: JMP       165          ; PC := 165
153 [-]: GETUPVAL  R10 U4       ; R10 := U4
154 [-]: CALL      R10 1 1      ; R10()
155 [-]: GETUPVAL  R10 U5       ; R10 := U5
156 [-]: LOADKB    R11 1 0      ; R11 := true
157 [-]: CALL      R10 2 1      ; R10(R11)
158 [-]: GETGLOBAL R10 K26      ; R10 := 0xcbd666e1
159 [-]: MOVE      R11 R9       ; R11 := R9
160 [-]: CALL      R10 2 1      ; R10(R11)
161 [-]: GETGLOBAL R10 K40      ; R10 := 0xa2e2b25b
162 [-]: SUB       R10 R10 R9   ; R10 := R10 - R9
163 [-]: SETGLOBAL R10 K40      ; (0xa2e2b25b) := R10
164 [-]: JMP       150          ; PC := 150
165 [-]: GETUPVAL  R10 U5       ; R10 := U5
166 [-]: LOADKB    R11 0 0      ; R11 := false
167 [-]: CALL      R10 2 1      ; R10(R11)
168 [-]: GETUPVAL  R10 U6       ; R10 := U6
169 [-]: CALL      R10 1 1      ; R10()
170 [-]: GETGLOBAL R10 K8       ; R10 := 0x89326c93
171 [-]: SELF      R10 R10 K9   ; R11 := R10; R10 := R10[0x18d05d30]
172 [-]: CALL      R10 2 2      ; R10 := R10(R11)
173 [-]: TEST      R10 0        ; if not R10 then PC := 199
174 [-]: JMP       199          ; PC := 199
175 [-]: GETUPVAL  R10 U0       ; R10 := U0
176 [-]: SELF      R10 R10 K0   ; R11 := R10; R10 := R10[0xde321e6f]
177 [-]: CALL      R10 2 2      ; R10 := R10(R11)
178 [-]: SELF      R10 R10 K41  ; R11 := R10; R10 := R10[0x40a5b7af]
179 [-]: SELF      R12 R0 K42   ; R13 := R0; R12 := R0[0x24b019ac]
180 [-]: CALL      R12 2 0      ; R12,... := R12(R13)
181 [-]: CALL      R10 0 1      ; R10(R11,...)
182 [-]: GETGLOBAL R10 K27      ; R10 := _T
183 [-]: SETTABLE  R10 K28 K43  ; R10["PauseVaultTimer"] := false
184 [-]: GETGLOBAL R10 K19      ; R10 := 0x7b998233
185 [-]: MOVE      R11 R4       ; R11 := R4
186 [-]: CALL      R10 2 2      ; R10 := R10(R11)
187 [-]: TEST      R10 1        ; if R10 then PC := 199
188 [-]: JMP       199          ; PC := 199
189 [-]: GETGLOBAL R10 K8       ; R10 := 0x89326c93
190 [-]: SELF      R10 R10 K14  ; R11 := R10; R10 := R10[0x05909209]
191 [-]: GETGLOBAL R12 K44      ; R12 := 0x71f576f7
192 [-]: SELF      R13 R4 K45   ; R14 := R4; R13 := R4[0xd1586535]
193 [-]: CALL      R13 2 2      ; R13 := R13(R14)
194 [-]: SELF      R14 R4 K46   ; R15 := R4; R14 := R4[0xcb3851b8]
195 [-]: CALL      R14 2 0      ; R14,... := R14(R15)
196 [-]: CALL      R10 0 1      ; R10(R11,...)
197 [-]: SELF      R10 R4 K25   ; R11 := R4; R10 := R4[0xa2880940]
198 [-]: CALL      R10 2 1      ; R10(R11)
199 [-]: SELF      R10 R0 K47   ; R11 := R0; R10 := R0[0xcc2fcc95]
200 [-]: LOADKB    R12 0 0      ; R12 := false
201 [-]: CALL      R10 3 1      ; R10(R11,R12)
202 [-]: RETURN    R0 1         ; return 


; Function #14:
;
; Name:            
; Defined at line: 483
; #Upvalues:       0
; #Parameters:     2
; Is_vararg:       0
; Max Stack Size:  5

  1 [-]: GETGLOBAL R2 K0        ; R2 := 0x7b998233
  2 [-]: MOVE      R3 R1        ; R3 := R1
  3 [-]: CALL      R2 2 2       ; R2 := R2(R3)
  4 [-]: TEST      R2 1         ; if R2 then PC := 29
  5 [-]: JMP       29           ; PC := 29
  6 [-]: SELF      R2 R1 K1     ; R3 := R1; R2 := R1[0x2047cfe7]
  7 [-]: CALL      R2 2 2       ; R2 := R2(R3)
  8 [-]: TEST      R2 1         ; if R2 then PC := 29
  9 [-]: JMP       29           ; PC := 29
 10 [-]: SELF      R2 R1 K2     ; R3 := R1; R2 := R1[0xc4dff581]
 11 [-]: CONST     R4 0         ; R4 := 0.000000
 12 [-]: CALL      R2 3 2       ; R2 := R2(R3,R4)
 13 [-]: TEST      R2 1         ; if R2 then PC := 29
 14 [-]: JMP       29           ; PC := 29
 15 [-]: SELF      R2 R1 K2     ; R3 := R1; R2 := R1[0xc4dff581]
 16 [-]: CONST     R4 1         ; R4 := 1.000000
 17 [-]: CALL      R2 3 2       ; R2 := R2(R3,R4)
 18 [-]: TEST      R2 1         ; if R2 then PC := 29
 19 [-]: JMP       29           ; PC := 29
 20 [-]: SELF      R2 R1 K4     ; R3 := R1; R2 := R1[0x73901acf]
 21 [-]: CALL      R2 2 2       ; R2 := R2(R3)
 22 [-]: TEST      R2 1         ; if R2 then PC := 29
 23 [-]: JMP       29           ; PC := 29
 24 [-]: SELF      R2 R1 K5     ; R3 := R1; R2 := R1[0xee0bc178]
 25 [-]: MOVE      R4 R0        ; R4 := R0
 26 [-]: CALL      R2 3 2       ; R2 := R2(R3,R4)
 27 [-]: NOT       R2 R2        ; R2 :=  R2
 28 [-]: JMP       31           ; PC := 31
 29 [-]: LOADKB    R2 0 1       ; R2 := false; PC := 30
 30 [-]: LOADKB    R2 1 0       ; R2 := true
 31 [-]: RETURN    R2 2         ; return R2
 32 [-]: RETURN    R0 1         ; return 


; Function #15:
;
; Name:            
; Defined at line: 490
; #Upvalues:       6
; #Parameters:     1
; Is_vararg:       0
; Max Stack Size:  47

  1 [-]: GETUPVAL  R1 U0        ; R1 := U0
  2 [-]: SELF      R1 R1 K0     ; R2 := R1; R1 := R1[0xde321e6f]
  3 [-]: CALL      R1 2 2       ; R1 := R1(R2)
  4 [-]: SELF      R2 R1 K1     ; R3 := R1; R2 := R1[0xf7d48ee0]
  5 [-]: CALL      R2 2 2       ; R2 := R2(R3)
  6 [-]: SELF      R3 R1 K2     ; R4 := R1; R3 := R1[0xefd0fde2]
  7 [-]: CALL      R3 2 2       ; R3 := R3(R4)
  8 [-]: GETUPVAL  R4 U1        ; R4 := U1
  9 [-]: GETGLOBAL R5 K3        ; R5 := 0x9c6d95f7
 10 [-]: CALL      R4 2 1       ; R4(R5)
 11 [-]: LOADNIL   R4 R4        ; R4 := nil
 12 [-]: MOVE      R5 R3        ; R5 := R3
 13 [-]: GETGLOBAL R6 K4        ; R6 := 0x89326c93
 14 [-]: SELF      R6 R6 K5     ; R7 := R6; R6 := R6[0x18d05d30]
 15 [-]: CALL      R6 2 2       ; R6 := R6(R7)
 16 [-]: TEST      R6 0         ; if not R6 then PC := 39
 17 [-]: JMP       39           ; PC := 39
 18 [-]: GETUPVAL  R6 U0        ; R6 := U0
 19 [-]: SELF      R6 R6 K6     ; R7 := R6; R6 := R6[0x5280b883]
 20 [-]: CALL      R6 2 2       ; R6 := R6(R7)
 21 [-]: GETGLOBAL R7 K4        ; R7 := 0x89326c93
 22 [-]: SELF      R7 R7 K7     ; R8 := R7; R7 := R7[0x05909209]
 23 [-]: GETGLOBAL R9 K8        ; R9 := 0xb367793a
 24 [-]: MOVE      R10 R5       ; R10 := R5
 25 [-]: MOVE      R11 R6       ; R11 := R6
 26 [-]: GETUPVAL  R12 U0       ; R12 := U0
 27 [-]: CALL      R7 6 2       ; R7 := R7(R8,R9,R10,R11,R12)
 28 [-]: MOVE      R4 R7        ; R4 := R7
 29 [-]: GETGLOBAL R7 K4        ; R7 := 0x89326c93
 30 [-]: SELF      R7 R7 K7     ; R8 := R7; R7 := R7[0x05909209]
 31 [-]: GETGLOBAL R9 K9        ; R9 := 0x71f576f7
 32 [-]: MOVE      R10 R5       ; R10 := R5
 33 [-]: MOVE      R11 R6       ; R11 := R6
 34 [-]: CALL      R7 5 1       ; R7(R8,R9,R10,R11)
 35 [-]: SELF      R7 R1 K10    ; R8 := R1; R7 := R1[0x40a5b7af]
 36 [-]: SELF      R9 R0 K11    ; R10 := R0; R9 := R0[0x24b019ac]
 37 [-]: CALL      R9 2 0       ; R9,... := R9(R10)
 38 [-]: CALL      R7 0 1       ; R7(R8,...)
 39 [-]: GETUPVAL  R7 U2        ; R7 := U2
 40 [-]: GETGLOBAL R8 K12       ; R8 := 0x3d5a604d
 41 [-]: CALL      R7 2 1       ; R7(R8)
 42 [-]: GETUPVAL  R7 U3        ; R7 := U3
 43 [-]: GETGLOBAL R8 K13       ; R8 := 0x8b9d7e3a
 44 [-]: CALL      R7 2 1       ; R7(R8)
 45 [-]: GETGLOBAL R7 K14       ; R7 := 0xcbd666e1
 46 [-]: CONST     R8 1         ; R8 := 1.000000
 47 [-]: CALL      R7 2 1       ; R7(R8)
 48 [-]: GETGLOBAL R7 K15       ; R7 := 0x7b998233
 49 [-]: MOVE      R8 R4        ; R8 := R4
 50 [-]: CALL      R7 2 2       ; R7 := R7(R8)
 51 [-]: TEST      R7 1         ; if R7 then PC := 65
 52 [-]: JMP       65           ; PC := 65
 53 [-]: GETGLOBAL R7 K4        ; R7 := 0x89326c93
 54 [-]: SELF      R7 R7 K7     ; R8 := R7; R7 := R7[0x05909209]
 55 [-]: GETGLOBAL R9 K9        ; R9 := 0x71f576f7
 56 [-]: SELF      R10 R4 K16   ; R11 := R4; R10 := R4[0xd1586535]
 57 [-]: CALL      R10 2 2      ; R10 := R10(R11)
 58 [-]: SELF      R11 R4 K17   ; R12 := R4; R11 := R4[0xcb3851b8]
 59 [-]: CALL      R11 2 0      ; R11,... := R11(R12)
 60 [-]: CALL      R7 0 1       ; R7(R8,...)
 61 [-]: GETGLOBAL R7 K4        ; R7 := 0x89326c93
 62 [-]: SELF      R7 R7 K18    ; R8 := R7; R7 := R7[0x59c96e77]
 63 [-]: MOVE      R9 R4        ; R9 := R4
 64 [-]: CALL      R7 3 1       ; R7(R8,R9)
 65 [-]: GETGLOBAL R7 K4        ; R7 := 0x89326c93
 66 [-]: SELF      R7 R7 K5     ; R8 := R7; R7 := R7[0x18d05d30]
 67 [-]: CALL      R7 2 2       ; R7 := R7(R8)
 68 [-]: TEST      R7 0         ; if not R7 then PC := 292
 69 [-]: JMP       292          ; PC := 292
 70 [-]: SELF      R7 R0 K19    ; R8 := R0; R7 := R0[0xcc2fcc95]
 71 [-]: LOADKB    R9 0 0       ; R9 := false
 72 [-]: CALL      R7 3 1       ; R7(R8,R9)
 73 [-]: GETTABLE  R7 R5 K20    ; R7 := R5["y"]
 74 [-]: ADD       R7 R7 K21    ; R7 := R7 + 1.000000
 75 [-]: SETTABLE  R5 K20 R7    ; R5["y"] := R7
 76 [-]: GETGLOBAL R7 K22       ; R7 := 0xa421af95
 77 [-]: GETTABLE  R8 R5 K23    ; R8 := R5["x"]
 78 [-]: GETTABLE  R9 R5 K20    ; R9 := R5["y"]
 79 [-]: SUB       R9 R9 K24    ; R9 := R9 - 10.000000
 80 [-]: GETTABLE  R10 R5 K25   ; R10 := R5["z"]
 81 [-]: CALL      R7 4 2       ; R7 := R7(R8,R9,R10)
 82 [-]: GETGLOBAL R8 K22       ; R8 := 0xa421af95
 83 [-]: CALL      R8 1 2       ; R8 := R8()
 84 [-]: GETGLOBAL R9 K4        ; R9 := 0x89326c93
 85 [-]: SELF      R9 R9 K26    ; R10 := R9; R9 := R9[0xbd5d0ec1]
 86 [-]: MOVE      R11 R5       ; R11 := R5
 87 [-]: MOVE      R12 R7       ; R12 := R7
 88 [-]: GETUPVAL  R13 U0       ; R13 := U0
 89 [-]: LOADNIL   R14 R14      ; R14 := nil
 90 [-]: MOVE      R15 R8       ; R15 := R8
 91 [-]: CALL      R9 7 2       ; R9 := R9(R10,R11,R12,R13,R14,R15)
 92 [-]: TEST      R9 0         ; if not R9 then PC := 96
 93 [-]: JMP       96           ; PC := 96
 94 [-]: MOVE      R5 R8        ; R5 := R8
 95 [-]: JMP       99           ; PC := 99
 96 [-]: GETTABLE  R9 R5 K20    ; R9 := R5["y"]
 97 [-]: SUB       R9 R9 K21    ; R9 := R9 - 1.000000
 98 [-]: SETTABLE  R5 K20 R9    ; R5["y"] := R9
 99 [-]: GETGLOBAL R9 K4        ; R9 := 0x89326c93
100 [-]: SELF      R9 R9 K7     ; R10 := R9; R9 := R9[0x05909209]
101 [-]: GETGLOBAL R11 K27      ; R11 := 0x4598d783
102 [-]: GETGLOBAL R12 K28      ; R12 := 0x1a176fb8
103 [-]: ADD       R12 R5 R12   ; R12 := R5 + R12
104 [-]: GETGLOBAL R13 K29      ; R13 := ZERO_ROTATION
105 [-]: GETUPVAL  R14 U4       ; R14 := U4
106 [-]: GETUPVAL  R15 U4       ; R15 := U4
107 [-]: CALL      R9 7 2       ; R9 := R9(R10,R11,R12,R13,R14,R15)
108 [-]: CONST     R10 20       ; R10 := 20.000000
109 [-]: GETGLOBAL R11 K4       ; R11 := 0x89326c93
110 [-]: SELF      R11 R11 K30  ; R12 := R11; R11 := R11[0xfb669000]
111 [-]: GETGLOBAL R13 K31      ; R13 := gLotusNpcAvatarType
112 [-]: MOVE      R14 R3       ; R14 := R3
113 [-]: CONST     R15 0        ; R15 := 0.000000
114 [-]: MOVE      R16 R10      ; R16 := R10
115 [-]: CALL      R11 6 2      ; R11 := R11(R12,R13,R14,R15,R16)
116 [-]: NEWTABLE  R12 0 0      ; R12 := {}
117 [-]: GETGLOBAL R13 K32      ; R13 := 0xc8802016
118 [-]: MOVE      R14 R11      ; R14 := R11
119 [-]: CALL      R13 2 4      ; R13,R14,R15 := R13(R14)
120 [-]: JMP       132          ; PC := 132
121 [-]: GETUPVAL  R18 U5       ; R18 := U5
122 [-]: GETUPVAL  R19 U0       ; R19 := U0
123 [-]: MOVE      R20 R17      ; R20 := R17
124 [-]: CALL      R18 3 2      ; R18 := R18(R19,R20)
125 [-]: TEST      R18 0        ; if not R18 then PC := 132
126 [-]: JMP       132          ; PC := 132
127 [-]: GETGLOBAL R18 K33      ; R18 := 0x33bdd652
128 [-]: GETTABLE  R18 R18 K34  ; R18 := R18[0x23d5322f]
129 [-]: MOVE      R19 R12      ; R19 := R12
130 [-]: MOVE      R20 R17      ; R20 := R17
131 [-]: CALL      R18 3 1      ; R18(R19,R20)
132 [-]: TFORLOOP  R13 2        ; R16,R17 :=  R13(R14,R15); if R16 ~= nil then begin PC = 121; R15 := R16 end
133 [-]: JMP       121          ; PC := 121
134 [-]: CONST     R18 0        ; R18 := 0.000000
135 [-]: GETGLOBAL R19 K35      ; R19 := 0x0469f296
136 [-]: LOADK     R20 K36      ; R20 := "SLEEP_START"
137 [-]: CALL      R19 2 2      ; R19 := R19(R20)
138 [-]: GETGLOBAL R20 K35      ; R20 := 0x0469f296
139 [-]: LOADK     R21 K37      ; R21 := "SLEEP_LOOP"
140 [-]: CALL      R20 2 2      ; R20 := R20(R21)
141 [-]: GETGLOBAL R21 K35      ; R21 := 0x0469f296
142 [-]: LOADK     R22 K38      ; R22 := "SLEEP_END"
143 [-]: CALL      R21 2 2      ; R21 := R21(R22)
144 [-]: GETGLOBAL R22 K32      ; R22 := 0xc8802016
145 [-]: MOVE      R23 R12      ; R23 := R12
146 [-]: CALL      R22 2 4      ; R22,R23,R24 := R22(R23)
147 [-]: JMP       177          ; PC := 177
148 [-]: SELF      R27 R26 K39  ; R28 := R26; R27 := R26[0x30eb0cc3]
149 [-]: CONST     R29 6        ; R29 := 6.000000
150 [-]: LOADKB    R30 1 0      ; R30 := true
151 [-]: CALL      R27 4 1      ; R27(R28,R29,R30)
152 [-]: SELF      R27 R26 K41  ; R28 := R26; R27 := R26[0x47901f07]
153 [-]: GETGLOBAL R29 K42      ; R29 := 0x921afa07
154 [-]: GETGLOBAL R30 K43      ; R30 := EMPTY_SYMBOL
155 [-]: GETGLOBAL R31 K44      ; R31 := ZERO_VECTOR
156 [-]: GETGLOBAL R32 K29      ; R32 := ZERO_ROTATION
157 [-]: MOVE      R33 R2       ; R33 := R2
158 [-]: CALL      R27 7 1      ; R27(R28,R29,R30,R31,R32,R33)
159 [-]: GETGLOBAL R27 K15      ; R27 := 0x7b998233
160 [-]: SELF      R28 R26 K45  ; R29 := R26; R28 := R26[0xfa9e477f]
161 [-]: CALL      R28 2 0      ; R28,... := R28(R29)
162 [-]: CALL      R27 0 2      ; R27 := R27(R28,...)
163 [-]: TEST      R27 1        ; if R27 then PC := 177
164 [-]: JMP       177          ; PC := 177
165 [-]: SELF      R27 R26 K46  ; R28 := R26; R27 := R26[0x444ae2c8]
166 [-]: CALL      R27 2 2      ; R27 := R27(R28)
167 [-]: TEST      R27 1        ; if R27 then PC := 177
168 [-]: JMP       177          ; PC := 177
169 [-]: SELF      R27 R26 K47  ; R28 := R26; R27 := R26[0x0f89a4d4]
170 [-]: MOVE      R29 R19      ; R29 := R19
171 [-]: LOADKB    R30 0 0      ; R30 := false
172 [-]: CONST     R31 4        ; R31 := 4.000000
173 [-]: CONST     R32 3        ; R32 := 3.000000
174 [-]: LOADKB    R33 1 0      ; R33 := true
175 [-]: MOVE      R34 R18      ; R34 := R18
176 [-]: CALL      R27 8 1      ; R27(R28,R29,R30,R31,R32,R33,R34)
177 [-]: TFORLOOP  R22 2        ; R25,R26 :=  R22(R23,R24); if R25 ~= nil then begin PC = 148; R24 := R25 end
178 [-]: JMP       148          ; PC := 148
179 [-]: CONST     R27 20       ; R27 := 20.000000
180 [-]: LT        0 K48 R27    ; if 0.000000 >= R27 then PC := 229
181 [-]: JMP       229          ; PC := 229
182 [-]: GETGLOBAL R28 K32      ; R28 := 0xc8802016
183 [-]: MOVE      R29 R12      ; R29 := R12
184 [-]: CALL      R28 2 4      ; R28,R29,R30 := R28(R29)
185 [-]: JMP       220          ; PC := 220
186 [-]: GETGLOBAL R33 K15      ; R33 := 0x7b998233
187 [-]: MOVE      R34 R32      ; R34 := R32
188 [-]: CALL      R33 2 2      ; R33 := R33(R34)
189 [-]: TEST      R33 1        ; if R33 then PC := 220
190 [-]: JMP       220          ; PC := 220
191 [-]: SELF      R33 R32 K49  ; R34 := R32; R33 := R32[0x2047cfe7]
192 [-]: CALL      R33 2 2      ; R33 := R33(R34)
193 [-]: TEST      R33 1        ; if R33 then PC := 220
194 [-]: JMP       220          ; PC := 220
195 [-]: SELF      R33 R32 K50  ; R34 := R32; R33 := R32[0xc4dff581]
196 [-]: CONST     R35 0        ; R35 := 0.000000
197 [-]: CALL      R33 3 2      ; R33 := R33(R34,R35)
198 [-]: TEST      R33 1        ; if R33 then PC := 220
199 [-]: JMP       220          ; PC := 220
200 [-]: GETGLOBAL R33 K15      ; R33 := 0x7b998233
201 [-]: SELF      R34 R32 K45  ; R35 := R32; R34 := R32[0xfa9e477f]
202 [-]: CALL      R34 2 0      ; R34,... := R34(R35)
203 [-]: CALL      R33 0 2      ; R33 := R33(R34,...)
204 [-]: TEST      R33 1        ; if R33 then PC := 220
205 [-]: JMP       220          ; PC := 220
206 [-]: SELF      R33 R32 K46  ; R34 := R32; R33 := R32[0x444ae2c8]
207 [-]: GETGLOBAL R35 K43      ; R35 := EMPTY_SYMBOL
208 [-]: LOADKB    R36 0 0      ; R36 := false
209 [-]: CALL      R33 4 2      ; R33 := R33(R34,R35,R36)
210 [-]: TEST      R33 1        ; if R33 then PC := 220
211 [-]: JMP       220          ; PC := 220
212 [-]: SELF      R33 R32 K47  ; R34 := R32; R33 := R32[0x0f89a4d4]
213 [-]: MOVE      R35 R20      ; R35 := R20
214 [-]: LOADKB    R36 0 0      ; R36 := false
215 [-]: CONST     R37 4        ; R37 := 4.000000
216 [-]: CONST     R38 2        ; R38 := 2.000000
217 [-]: LOADKB    R39 1 0      ; R39 := true
218 [-]: MOVE      R40 R18      ; R40 := R18
219 [-]: CALL      R33 8 1      ; R33(R34,R35,R36,R37,R38,R39,R40)
220 [-]: TFORLOOP  R28 2        ; R31,R32 :=  R28(R29,R30); if R31 ~= nil then begin PC = 186; R30 := R31 end
221 [-]: JMP       186          ; PC := 186
222 [-]: GETGLOBAL R33 K14      ; R33 := 0xcbd666e1
223 [-]: CONST     R34 0        ; R34 := 0.000000
224 [-]: CALL      R33 2 1      ; R33(R34)
225 [-]: GETGLOBAL R33 K52      ; R33 := 0x67652851
226 [-]: CALL      R33 1 2      ; R33 := R33()
227 [-]: SUB       R27 R27 R33  ; R27 := R27 - R33
228 [-]: JMP       180          ; PC := 180
229 [-]: GETGLOBAL R33 K4       ; R33 := 0x89326c93
230 [-]: SELF      R33 R33 K18  ; R34 := R33; R33 := R33[0x59c96e77]
231 [-]: MOVE      R35 R9       ; R35 := R9
232 [-]: CALL      R33 3 1      ; R33(R34,R35)
233 [-]: GETGLOBAL R33 K32      ; R33 := 0xc8802016
234 [-]: MOVE      R34 R12      ; R34 := R12
235 [-]: CALL      R33 2 4      ; R33,R34,R35 := R33(R34)
236 [-]: JMP       289          ; PC := 289
237 [-]: GETGLOBAL R38 K15      ; R38 := 0x7b998233
238 [-]: MOVE      R39 R37      ; R39 := R37
239 [-]: CALL      R38 2 2      ; R38 := R38(R39)
240 [-]: TEST      R38 1        ; if R38 then PC := 289
241 [-]: JMP       289          ; PC := 289
242 [-]: SELF      R38 R37 K49  ; R39 := R37; R38 := R37[0x2047cfe7]
243 [-]: CALL      R38 2 2      ; R38 := R38(R39)
244 [-]: TEST      R38 1        ; if R38 then PC := 289
245 [-]: JMP       289          ; PC := 289
246 [-]: SELF      R38 R37 K50  ; R39 := R37; R38 := R37[0xc4dff581]
247 [-]: CONST     R40 0        ; R40 := 0.000000
248 [-]: CALL      R38 3 2      ; R38 := R38(R39,R40)
249 [-]: TEST      R38 1        ; if R38 then PC := 289
250 [-]: JMP       289          ; PC := 289
251 [-]: SELF      R38 R37 K53  ; R39 := R37; R38 := R37[0xc9f6a7d7]
252 [-]: GETGLOBAL R40 K42      ; R40 := 0x921afa07
253 [-]: CALL      R38 3 2      ; R38 := R38(R39,R40)
254 [-]: GETGLOBAL R39 K15      ; R39 := 0x7b998233
255 [-]: MOVE      R40 R38      ; R40 := R38
256 [-]: CALL      R39 2 2      ; R39 := R39(R40)
257 [-]: TEST      R39 1        ; if R39 then PC := 261
258 [-]: JMP       261          ; PC := 261
259 [-]: SELF      R39 R38 K54  ; R40 := R38; R39 := R38[0xa2880940]
260 [-]: CALL      R39 2 1      ; R39(R40)
261 [-]: GETGLOBAL R39 K15      ; R39 := 0x7b998233
262 [-]: SELF      R40 R37 K45  ; R41 := R37; R40 := R37[0xfa9e477f]
263 [-]: CALL      R40 2 0      ; R40,... := R40(R41)
264 [-]: CALL      R39 0 2      ; R39 := R39(R40,...)
265 [-]: TEST      R39 1        ; if R39 then PC := 285
266 [-]: JMP       285          ; PC := 285
267 [-]: SELF      R39 R37 K46  ; R40 := R37; R39 := R37[0x444ae2c8]
268 [-]: MOVE      R41 R20      ; R41 := R20
269 [-]: CALL      R39 3 2      ; R39 := R39(R40,R41)
270 [-]: TEST      R39 1        ; if R39 then PC := 277
271 [-]: JMP       277          ; PC := 277
272 [-]: SELF      R39 R37 K46  ; R40 := R37; R39 := R37[0x444ae2c8]
273 [-]: MOVE      R41 R19      ; R41 := R19
274 [-]: CALL      R39 3 2      ; R39 := R39(R40,R41)
275 [-]: TEST      R39 0        ; if not R39 then PC := 285
276 [-]: JMP       285          ; PC := 285
277 [-]: SELF      R39 R37 K47  ; R40 := R37; R39 := R37[0x0f89a4d4]
278 [-]: MOVE      R41 R21      ; R41 := R21
279 [-]: LOADKB    R42 0 0      ; R42 := false
280 [-]: CONST     R43 3        ; R43 := 3.000000
281 [-]: CONST     R44 1        ; R44 := 1.000000
282 [-]: LOADKB    R45 1 0      ; R45 := true
283 [-]: MOVE      R46 R18      ; R46 := R18
284 [-]: CALL      R39 8 1      ; R39(R40,R41,R42,R43,R44,R45,R46)
285 [-]: SELF      R39 R37 K39  ; R40 := R37; R39 := R37[0x30eb0cc3]
286 [-]: CONST     R41 6        ; R41 := 6.000000
287 [-]: LOADKB    R42 0 0      ; R42 := false
288 [-]: CALL      R39 4 1      ; R39(R40,R41,R42)
289 [-]: TFORLOOP  R33 2        ; R36,R37 :=  R33(R34,R35); if R36 ~= nil then begin PC = 237; R35 := R36 end
290 [-]: JMP       237          ; PC := 237
291 [-]: JMP       295          ; PC := 295
292 [-]: SELF      R39 R0 K19   ; R40 := R0; R39 := R0[0xcc2fcc95]
293 [-]: LOADKB    R41 0 0      ; R41 := false
294 [-]: CALL      R39 3 1      ; R39(R40,R41)
295 [-]: RETURN    R0 1         ; return 


; Function #16:
;
; Name:            
; Defined at line: 593
; #Upvalues:       8
; #Parameters:     2
; Is_vararg:       0
; Max Stack Size:  41

  1 [-]: GETUPVAL  R2 U0        ; R2 := U0
  2 [-]: SELF      R2 R2 K0     ; R3 := R2; R2 := R2[0xde321e6f]
  3 [-]: CALL      R2 2 2       ; R2 := R2(R3)
  4 [-]: SELF      R3 R2 K1     ; R4 := R2; R3 := R2[0xf7d48ee0]
  5 [-]: CALL      R3 2 2       ; R3 := R3(R4)
  6 [-]: LOADKB    R4 0 0       ; R4 := false
  7 [-]: GETGLOBAL R5 K2        ; R5 := 0xa421af95
  8 [-]: CALL      R5 1 2       ; R5 := R5()
  9 [-]: CONST     R6 0         ; R6 := 0.000000
 10 [-]: CONST     R7 0         ; R7 := 0.000000
 11 [-]: SELF      R8 R2 K3     ; R9 := R2; R8 := R2[0xefd0fde2]
 12 [-]: CALL      R8 2 2       ; R8 := R8(R9)
 13 [-]: LOADNIL   R9 R9        ; R9 := nil
 14 [-]: GETUPVAL  R10 U0       ; R10 := U0
 15 [-]: SELF      R10 R10 K4   ; R11 := R10; R10 := R10[0xf6ebd926]
 16 [-]: CALL      R10 2 2      ; R10 := R10(R11)
 17 [-]: GETTABLE  R11 R8 K5    ; R11 := R8["x"]
 18 [-]: GETTABLE  R12 R10 K5   ; R12 := R10["x"]
 19 [-]: SUB       R11 R11 R12  ; R11 := R11 - R12
 20 [-]: GETTABLE  R12 R8 K6    ; R12 := R8["z"]
 21 [-]: GETTABLE  R13 R10 K6   ; R13 := R10["z"]
 22 [-]: SUB       R12 R12 R13  ; R12 := R12 - R13
 23 [-]: GETGLOBAL R13 K2       ; R13 := 0xa421af95
 24 [-]: MOVE      R14 R11      ; R14 := R11
 25 [-]: CONST     R15 0        ; R15 := 0.000000
 26 [-]: MOVE      R16 R12      ; R16 := R12
 27 [-]: CALL      R13 4 2      ; R13 := R13(R14,R15,R16)
 28 [-]: GETGLOBAL R14 K7       ; R14 := 0xae2294fa
 29 [-]: MOVE      R15 R13      ; R15 := R13
 30 [-]: CALL      R14 2 2      ; R14 := R14(R15)
 31 [-]: MUL       R14 R14 K8   ; R14 := R14 * 1.500000
 32 [-]: CONST     R15 25       ; R15 := 25.000000
 33 [-]: DIV       R14 R14 R15  ; R14 := R14 / R15
 34 [-]: GETGLOBAL R16 K9       ; R16 := 0xc2892f65
 35 [-]: MOVE      R17 R13      ; R17 := R13
 36 [-]: CALL      R16 2 1      ; R16(R17)
 37 [-]: MUL       R13 R13 R14  ; R13 := R13 * R14
 38 [-]: GETUPVAL  R16 U1       ; R16 := U1
 39 [-]: GETGLOBAL R17 K10      ; R17 := 0x9c6d95f7
 40 [-]: CALL      R16 2 1      ; R16(R17)
 41 [-]: GETGLOBAL R16 K11      ; R16 := 0x89326c93
 42 [-]: SELF      R16 R16 K12  ; R17 := R16; R16 := R16[0x18d05d30]
 43 [-]: CALL      R16 2 2      ; R16 := R16(R17)
 44 [-]: TEST      R16 0        ; if not R16 then PC := 63
 45 [-]: JMP       63           ; PC := 63
 46 [-]: GETUPVAL  R16 U0       ; R16 := U0
 47 [-]: SELF      R16 R16 K13  ; R17 := R16; R16 := R16[0x5280b883]
 48 [-]: CALL      R16 2 2      ; R16 := R16(R17)
 49 [-]: GETGLOBAL R17 K11      ; R17 := 0x89326c93
 50 [-]: SELF      R17 R17 K14  ; R18 := R17; R17 := R17[0x05909209]
 51 [-]: GETGLOBAL R19 K15      ; R19 := 0xb367793a
 52 [-]: MOVE      R20 R8       ; R20 := R8
 53 [-]: MOVE      R21 R16      ; R21 := R16
 54 [-]: GETUPVAL  R22 U0       ; R22 := U0
 55 [-]: CALL      R17 6 2      ; R17 := R17(R18,R19,R20,R21,R22)
 56 [-]: MOVE      R9 R17       ; R9 := R17
 57 [-]: GETGLOBAL R17 K11      ; R17 := 0x89326c93
 58 [-]: SELF      R17 R17 K14  ; R18 := R17; R17 := R17[0x05909209]
 59 [-]: GETGLOBAL R19 K16      ; R19 := 0x71f576f7
 60 [-]: MOVE      R20 R8       ; R20 := R8
 61 [-]: MOVE      R21 R16      ; R21 := R16
 62 [-]: CALL      R17 5 1      ; R17(R18,R19,R20,R21)
 63 [-]: GETUPVAL  R17 U2       ; R17 := U2
 64 [-]: GETGLOBAL R18 K17      ; R18 := 0x25844db3
 65 [-]: CALL      R17 2 1      ; R17(R18)
 66 [-]: GETUPVAL  R17 U3       ; R17 := U3
 67 [-]: GETGLOBAL R18 K18      ; R18 := 0x06fe7d0c
 68 [-]: CALL      R17 2 1      ; R17(R18)
 69 [-]: GETGLOBAL R17 K19      ; R17 := 0xcbd666e1
 70 [-]: CONST     R18 1        ; R18 := 1.000000
 71 [-]: CALL      R17 2 1      ; R17(R18)
 72 [-]: GETUPVAL  R17 U4       ; R17 := U4
 73 [-]: CALL      R17 1 1      ; R17()
 74 [-]: GETGLOBAL R17 K11      ; R17 := 0x89326c93
 75 [-]: SELF      R17 R17 K12  ; R18 := R17; R17 := R17[0x18d05d30]
 76 [-]: CALL      R17 2 2      ; R17 := R17(R18)
 77 [-]: TEST      R17 0        ; if not R17 then PC := 274
 78 [-]: JMP       274          ; PC := 274
 79 [-]: LOADNIL   R17 R17      ; R17 := nil
 80 [-]: TEST      R1 0         ; if not R1 then PC := 89
 81 [-]: JMP       89           ; PC := 89
 82 [-]: GETUPVAL  R18 U0       ; R18 := U0
 83 [-]: SELF      R18 R18 K0   ; R19 := R18; R18 := R18[0xde321e6f]
 84 [-]: CALL      R18 2 2      ; R18 := R18(R19)
 85 [-]: SELF      R18 R18 K20  ; R19 := R18; R18 := R18[0x881b6b90]
 86 [-]: CONST     R20 0        ; R20 := 0.000000
 87 [-]: CALL      R18 3 2      ; R18 := R18(R19,R20)
 88 [-]: MOVE      R17 R18      ; R17 := R18
 89 [-]: CONST     R18 100      ; R18 := 100.000000
 90 [-]: MOVE      R8 R10       ; R8 := R10
 91 [-]: CONST     R19 0        ; R19 := 0.000000
 92 [-]: GETUPVAL  R20 U5       ; R20 := U5
 93 [-]: GETTABLE  R20 R20 K21  ; R20 := R20[0x06d055f9]
 94 [-]: MOVE      R21 R1       ; R21 := R1
 95 [-]: GETGLOBAL R22 K22      ; R22 := 0x8114bf8c
 96 [-]: GETGLOBAL R23 K23      ; R23 := 0x62931c23
 97 [-]: CALL      R20 4 2      ; R20 := R20(R21,R22,R23)
 98 [-]: GETUPVAL  R21 U5       ; R21 := U5
 99 [-]: GETTABLE  R21 R21 K21  ; R21 := R21[0x06d055f9]
100 [-]: MOVE      R22 R1       ; R22 := R1
101 [-]: GETGLOBAL R23 K24      ; R23 := 0x8834b36a
102 [-]: GETGLOBAL R24 K25      ; R24 := 0xcfce0ab7
103 [-]: CALL      R21 4 2      ; R21 := R21(R22,R23,R24)
104 [-]: GETGLOBAL R22 K26      ; R22 := 0x7b998233
105 [-]: GETUPVAL  R23 U0       ; R23 := U0
106 [-]: CALL      R22 2 2      ; R22 := R22(R23)
107 [-]: TEST      R22 1        ; if R22 then PC := 243
108 [-]: JMP       243          ; PC := 243
109 [-]: LT        0 R19 R15    ; if R19 >= R15 then PC := 243
110 [-]: JMP       243          ; PC := 243
111 [-]: LE        0 R6 K27     ; if R6 > 0.000000 then PC := 195
112 [-]: JMP       195          ; PC := 195
113 [-]: GETUPVAL  R22 U6       ; R22 := U6
114 [-]: MOVE      R23 R20      ; R23 := R20
115 [-]: CALL      R22 2 2      ; R22 := R22(R23)
116 [-]: ADD       R22 R8 R22   ; R22 := R8 + R22
117 [-]: GETGLOBAL R23 K2       ; R23 := 0xa421af95
118 [-]: GETTABLE  R24 R22 K5   ; R24 := R22["x"]
119 [-]: GETTABLE  R25 R22 K28  ; R25 := R22["y"]
120 [-]: GETTABLE  R26 R22 K6   ; R26 := R22["z"]
121 [-]: CALL      R23 4 2      ; R23 := R23(R24,R25,R26)
122 [-]: GETTABLE  R24 R23 K28  ; R24 := R23["y"]
123 [-]: SUB       R24 R24 K29  ; R24 := R24 - 50.000000
124 [-]: SETTABLE  R23 K28 R24  ; R23[0xf7d48ee0] := R24
125 [-]: LOADKB    R4 0 0       ; R4 := false
126 [-]: GETGLOBAL R24 K11      ; R24 := 0x89326c93
127 [-]: SELF      R24 R24 K30  ; R25 := R24; R24 := R24[0xbd5d0ec1]
128 [-]: MOVE      R26 R22      ; R26 := R22
129 [-]: MOVE      R27 R23      ; R27 := R23
130 [-]: GETUPVAL  R28 U0       ; R28 := U0
131 [-]: LOADNIL   R29 R29      ; R29 := nil
132 [-]: MOVE      R30 R5       ; R30 := R5
133 [-]: CALL      R24 7 2      ; R24 := R24(R25,R26,R27,R28,R29,R30)
134 [-]: TEST      R24 0        ; if not R24 then PC := 191
135 [-]: JMP       191          ; PC := 191
136 [-]: LOADKB    R4 1 0       ; R4 := true
137 [-]: LOADNIL   R24 R24      ; R24 := nil
138 [-]: TEST      R1 0         ; if not R1 then PC := 159
139 [-]: JMP       159          ; PC := 159
140 [-]: GETTABLE  R25 R5 K28   ; R25 := R5["y"]
141 [-]: ADD       R25 R25 K31  ; R25 := R25 + 0.500000
142 [-]: SETTABLE  R5 K28 R25   ; R5[0xf7d48ee0] := R25
143 [-]: GETGLOBAL R25 K11      ; R25 := 0x89326c93
144 [-]: SELF      R25 R25 K14  ; R26 := R25; R25 := R25[0x05909209]
145 [-]: GETGLOBAL R27 K32      ; R27 := 0x929cdbeb
146 [-]: MOVE      R28 R5       ; R28 := R5
147 [-]: GETGLOBAL R29 K33      ; R29 := ZERO_ROTATION
148 [-]: GETUPVAL  R30 U0       ; R30 := U0
149 [-]: CALL      R25 6 2      ; R25 := R25(R26,R27,R28,R29,R30)
150 [-]: MOVE      R24 R25      ; R24 := R25
151 [-]: GETGLOBAL R25 K11      ; R25 := 0x89326c93
152 [-]: SELF      R25 R25 K14  ; R26 := R25; R25 := R25[0x05909209]
153 [-]: GETGLOBAL R27 K34      ; R27 := 0xbc271130
154 [-]: MOVE      R28 R5       ; R28 := R5
155 [-]: GETGLOBAL R29 K33      ; R29 := ZERO_ROTATION
156 [-]: GETUPVAL  R30 U0       ; R30 := U0
157 [-]: CALL      R25 6 1      ; R25(R26,R27,R28,R29,R30)
158 [-]: JMP       167          ; PC := 167
159 [-]: GETGLOBAL R25 K11      ; R25 := 0x89326c93
160 [-]: SELF      R25 R25 K14  ; R26 := R25; R25 := R25[0x05909209]
161 [-]: GETGLOBAL R27 K34      ; R27 := 0xbc271130
162 [-]: MOVE      R28 R5       ; R28 := R5
163 [-]: GETGLOBAL R29 K33      ; R29 := ZERO_ROTATION
164 [-]: GETUPVAL  R30 U0       ; R30 := U0
165 [-]: CALL      R25 6 2      ; R25 := R25(R26,R27,R28,R29,R30)
166 [-]: MOVE      R24 R25      ; R24 := R25
167 [-]: TEST      R1 0         ; if not R1 then PC := 194
168 [-]: JMP       194          ; PC := 194
169 [-]: GETGLOBAL R25 K26      ; R25 := 0x7b998233
170 [-]: MOVE      R26 R24      ; R26 := R24
171 [-]: CALL      R25 2 2      ; R25 := R25(R26)
172 [-]: TEST      R25 1        ; if R25 then PC := 194
173 [-]: JMP       194          ; PC := 194
174 [-]: ADD       R18 R18 K35  ; R18 := R18 + 1.000000
175 [-]: SELF      R25 R24 K36  ; R26 := R24; R25 := R24[0x263a3cc2]
176 [-]: GETUPVAL  R27 U0       ; R27 := U0
177 [-]: CALL      R25 3 1      ; R25(R26,R27)
178 [-]: SELF      R25 R24 K37  ; R26 := R24; R25 := R24[0xfe447379]
179 [-]: MOVE      R27 R17      ; R27 := R17
180 [-]: CALL      R25 3 1      ; R25(R26,R27)
181 [-]: SELF      R25 R24 K38  ; R26 := R24; R25 := R24[0x1a634741]
182 [-]: MOVE      R27 R18      ; R27 := R18
183 [-]: CALL      R25 3 1      ; R25(R26,R27)
184 [-]: SELF      R25 R24 K39  ; R26 := R24; R25 := R24[0x88bdb569]
185 [-]: LOADKB    R27 1 0      ; R27 := true
186 [-]: CALL      R25 3 1      ; R25(R26,R27)
187 [-]: SELF      R25 R17 K40  ; R26 := R17; R25 := R17[0x9181d90c]
188 [-]: MOVE      R27 R24      ; R27 := R24
189 [-]: CALL      R25 3 1      ; R25(R26,R27)
190 [-]: JMP       194          ; PC := 194
191 [-]: GETTABLE  R25 R8 K28   ; R25 := R8["y"]
192 [-]: ADD       R25 R25 K31  ; R25 := R25 + 0.500000
193 [-]: SETTABLE  R8 K28 R25   ; R8[0xf7d48ee0] := R25
194 [-]: LOADK     R6 K41       ; R6 := 0.050000
195 [-]: GETGLOBAL R25 K19      ; R25 := 0xcbd666e1
196 [-]: CONST     R26 0        ; R26 := 0.000000
197 [-]: CALL      R25 2 1      ; R25(R26)
198 [-]: GETUPVAL  R25 U4       ; R25 := U4
199 [-]: CALL      R25 1 1      ; R25()
200 [-]: GETGLOBAL R25 K42      ; R25 := 0x67652851
201 [-]: CALL      R25 1 2      ; R25 := R25()
202 [-]: SUB       R6 R6 R25    ; R6 := R6 - R25
203 [-]: GETGLOBAL R25 K42      ; R25 := 0x67652851
204 [-]: CALL      R25 1 2      ; R25 := R25()
205 [-]: SUB       R7 R7 R25    ; R7 := R7 - R25
206 [-]: LE        0 R6 K27     ; if R6 > 0.000000 then PC := 237
207 [-]: JMP       237          ; PC := 237
208 [-]: TEST      R4 0         ; if not R4 then PC := 237
209 [-]: JMP       237          ; PC := 237
210 [-]: GETGLOBAL R25 K11      ; R25 := 0x89326c93
211 [-]: SELF      R25 R25 K43  ; R26 := R25; R25 := R25[0x97dcff30]
212 [-]: GETUPVAL  R27 U0       ; R27 := U0
213 [-]: MOVE      R28 R5       ; R28 := R5
214 [-]: MOVE      R29 R21      ; R29 := R21
215 [-]: CONST     R30 10       ; R30 := 10.000000
216 [-]: CONST     R31 300      ; R31 := 300.000000
217 [-]: CONST     R32 0        ; R32 := 0.000000
218 [-]: LOADNIL   R33 R33      ; R33 := nil
219 [-]: MOVE      R34 R3       ; R34 := R3
220 [-]: CONST     R35 20       ; R35 := 20.000000
221 [-]: LOADKB    R36 1 0      ; R36 := true
222 [-]: LOADKB    R37 0 0      ; R37 := false
223 [-]: LOADKB    R38 1 0      ; R38 := true
224 [-]: CONST     R39 0        ; R39 := 0.000000
225 [-]: LOADKB    R40 1 0      ; R40 := true
226 [-]: CALL      R25 16 1     ; R25(R26,R27,R28,R29,R30,R31,R32,R33,R34,R35,R36,R37,R38,R39,R40)
227 [-]: GETTABLE  R25 R5 K28   ; R25 := R5["y"]
228 [-]: ADD       R25 R25 K45  ; R25 := R25 + 0.250000
229 [-]: SETTABLE  R5 K28 R25   ; R5[0xf7d48ee0] := R25
230 [-]: GETGLOBAL R25 K11      ; R25 := 0x89326c93
231 [-]: SELF      R25 R25 K14  ; R26 := R25; R25 := R25[0x05909209]
232 [-]: GETGLOBAL R27 K46      ; R27 := 0x5a74f477
233 [-]: MOVE      R28 R5       ; R28 := R5
234 [-]: GETGLOBAL R29 K33      ; R29 := ZERO_ROTATION
235 [-]: GETUPVAL  R30 U0       ; R30 := U0
236 [-]: CALL      R25 6 1      ; R25(R26,R27,R28,R29,R30)
237 [-]: LE        0 R7 K27     ; if R7 > 0.000000 then PC := 104
238 [-]: JMP       104          ; PC := 104
239 [-]: ADD       R8 R8 R13    ; R8 := R8 + R13
240 [-]: ADD       R19 R19 K35  ; R19 := R19 + 1.000000
241 [-]: LOADK     R7 K41       ; R7 := 0.050000
242 [-]: JMP       104          ; PC := 104
243 [-]: GETUPVAL  R25 U0       ; R25 := U0
244 [-]: SELF      R25 R25 K0   ; R26 := R25; R25 := R25[0xde321e6f]
245 [-]: CALL      R25 2 2      ; R25 := R25(R26)
246 [-]: SELF      R25 R25 K47  ; R26 := R25; R25 := R25[0x40a5b7af]
247 [-]: SELF      R27 R0 K48   ; R28 := R0; R27 := R0[0x24b019ac]
248 [-]: CALL      R27 2 0      ; R27,... := R27(R28)
249 [-]: CALL      R25 0 1      ; R25(R26,...)
250 [-]: SELF      R25 R0 K49   ; R26 := R0; R25 := R0[0xcc2fcc95]
251 [-]: LOADKB    R27 0 0      ; R27 := false
252 [-]: CALL      R25 3 1      ; R25(R26,R27)
253 [-]: GETUPVAL  R25 U7       ; R25 := U7
254 [-]: GETGLOBAL R26 K50      ; R26 := 0x9a4584f5
255 [-]: CALL      R25 2 1      ; R25(R26)
256 [-]: GETGLOBAL R25 K26      ; R25 := 0x7b998233
257 [-]: MOVE      R26 R9       ; R26 := R9
258 [-]: CALL      R25 2 2      ; R25 := R25(R26)
259 [-]: TEST      R25 1        ; if R25 then PC := 277
260 [-]: JMP       277          ; PC := 277
261 [-]: GETGLOBAL R25 K11      ; R25 := 0x89326c93
262 [-]: SELF      R25 R25 K14  ; R26 := R25; R25 := R25[0x05909209]
263 [-]: GETGLOBAL R27 K16      ; R27 := 0x71f576f7
264 [-]: SELF      R28 R9 K51   ; R29 := R9; R28 := R9[0xd1586535]
265 [-]: CALL      R28 2 2      ; R28 := R28(R29)
266 [-]: SELF      R29 R9 K52   ; R30 := R9; R29 := R9[0xcb3851b8]
267 [-]: CALL      R29 2 0      ; R29,... := R29(R30)
268 [-]: CALL      R25 0 1      ; R25(R26,...)
269 [-]: GETGLOBAL R25 K11      ; R25 := 0x89326c93
270 [-]: SELF      R25 R25 K53  ; R26 := R25; R25 := R25[0x59c96e77]
271 [-]: MOVE      R27 R9       ; R27 := R9
272 [-]: CALL      R25 3 1      ; R25(R26,R27)
273 [-]: JMP       277          ; PC := 277
274 [-]: SELF      R25 R0 K49   ; R26 := R0; R25 := R0[0xcc2fcc95]
275 [-]: LOADKB    R27 0 0      ; R27 := false
276 [-]: CALL      R25 3 1      ; R25(R26,R27)
277 [-]: RETURN    R0 1         ; return 


; Function #17:
;
; Name:            
; Defined at line: 707
; #Upvalues:       5
; #Parameters:     1
; Is_vararg:       0
; Max Stack Size:  13

  1 [-]: GETUPVAL  R6 U0        ; R6 := U0
  2 [-]: SELF      R6 R6 K0     ; R7 := R6; R6 := R6[0xde321e6f]
  3 [-]: CALL      R6 2 2       ; R6 := R6(R7)
  4 [-]: SELF      R6 R6 K1     ; R7 := R6; R6 := R6[0xf7d48ee0]
  5 [-]: CALL      R6 2 2       ; R6 := R6(R7)
  6 [-]: GETUPVAL  R7 U1        ; R7 := U1
  7 [-]: GETGLOBAL R8 K2        ; R8 := 0x9c6d95f7
  8 [-]: CALL      R7 2 1       ; R7(R8)
  9 [-]: GETGLOBAL R7 K3        ; R7 := 0x89326c93
 10 [-]: SELF      R7 R7 K4     ; R8 := R7; R7 := R7[0x18d05d30]
 11 [-]: CALL      R7 2 2       ; R7 := R7(R8)
 12 [-]: TEST      R7 0         ; if not R7 then PC := 36
 13 [-]: JMP       36           ; PC := 36
 14 [-]: GETUPVAL  R7 U0        ; R7 := U0
 15 [-]: SELF      R7 R7 K5     ; R8 := R7; R7 := R7[0xf6ebd926]
 16 [-]: CALL      R7 2 2       ; R7 := R7(R8)
 17 [-]: MOVE      R1 R7        ; R1 := R7
 18 [-]: GETUPVAL  R7 U0        ; R7 := U0
 19 [-]: SELF      R7 R7 K6     ; R8 := R7; R7 := R7[0x9ba17154]
 20 [-]: CALL      R7 2 2       ; R7 := R7(R8)
 21 [-]: MOVE      R2 R7        ; R2 := R7
 22 [-]: MUL       R7 R2 K7     ; R7 := R2 * 2.000000
 23 [-]: ADD       R1 R1 R7     ; R1 := R1 + R7
 24 [-]: GETUPVAL  R7 U0        ; R7 := U0
 25 [-]: SELF      R7 R7 K8     ; R8 := R7; R7 := R7[0xcb3851b8]
 26 [-]: CALL      R7 2 2       ; R7 := R7(R8)
 27 [-]: MOVE      R3 R7        ; R3 := R7
 28 [-]: GETGLOBAL R7 K3        ; R7 := 0x89326c93
 29 [-]: SELF      R7 R7 K9     ; R8 := R7; R7 := R7[0x05909209]
 30 [-]: GETGLOBAL R9 K10       ; R9 := 0xb367793a
 31 [-]: MOVE      R10 R1       ; R10 := R1
 32 [-]: MOVE      R11 R3       ; R11 := R3
 33 [-]: GETUPVAL  R12 U0       ; R12 := U0
 34 [-]: CALL      R7 6 2       ; R7 := R7(R8,R9,R10,R11,R12)
 35 [-]: MOVE      R5 R7        ; R5 := R7
 36 [-]: GETUPVAL  R7 U2        ; R7 := U2
 37 [-]: GETGLOBAL R8 K11       ; R8 := 0x31643bcd
 38 [-]: CALL      R7 2 1       ; R7(R8)
 39 [-]: GETUPVAL  R7 U3        ; R7 := U3
 40 [-]: GETGLOBAL R8 K12       ; R8 := 0x369155d7
 41 [-]: CALL      R7 2 1       ; R7(R8)
 42 [-]: GETGLOBAL R7 K3        ; R7 := 0x89326c93
 43 [-]: SELF      R7 R7 K4     ; R8 := R7; R7 := R7[0x18d05d30]
 44 [-]: CALL      R7 2 2       ; R7 := R7(R8)
 45 [-]: TEST      R7 0         ; if not R7 then PC := 144
 46 [-]: JMP       144          ; PC := 144
 47 [-]: GETGLOBAL R7 K3        ; R7 := 0x89326c93
 48 [-]: SELF      R7 R7 K9     ; R8 := R7; R7 := R7[0x05909209]
 49 [-]: GETGLOBAL R9 K13       ; R9 := 0x71f576f7
 50 [-]: MOVE      R10 R1       ; R10 := R1
 51 [-]: MOVE      R11 R3       ; R11 := R3
 52 [-]: MOVE      R12 R6       ; R12 := R6
 53 [-]: CALL      R7 6 1       ; R7(R8,R9,R10,R11,R12)
 54 [-]: GETGLOBAL R7 K3        ; R7 := 0x89326c93
 55 [-]: SELF      R7 R7 K9     ; R8 := R7; R7 := R7[0x05909209]
 56 [-]: GETGLOBAL R9 K14       ; R9 := 0xfdc8601c
 57 [-]: MOVE      R10 R1       ; R10 := R1
 58 [-]: MOVE      R11 R3       ; R11 := R3
 59 [-]: GETUPVAL  R12 U0       ; R12 := U0
 60 [-]: CALL      R7 6 1       ; R7(R8,R9,R10,R11,R12)
 61 [-]: GETTABLE  R7 R3 K15    ; R7 := R3["pitch"]
 62 [-]: GETGLOBAL R8 K16       ; R8 := 0xa06e7419
 63 [-]: ADD       R7 R7 R8     ; R7 := R7 + R8
 64 [-]: SETTABLE  R3 K15 R7    ; R3["pitch"] := R7
 65 [-]: GETGLOBAL R7 K3        ; R7 := 0x89326c93
 66 [-]: SELF      R7 R7 K9     ; R8 := R7; R7 := R7[0x05909209]
 67 [-]: GETGLOBAL R9 K17       ; R9 := 0x279e5f41
 68 [-]: MOVE      R10 R1       ; R10 := R1
 69 [-]: MOVE      R11 R3       ; R11 := R3
 70 [-]: MOVE      R12 R0       ; R12 := R0
 71 [-]: CALL      R7 6 2       ; R7 := R7(R8,R9,R10,R11,R12)
 72 [-]: GETGLOBAL R8 K18       ; R8 := 0x7b998233
 73 [-]: MOVE      R9 R7        ; R9 := R7
 74 [-]: CALL      R8 2 2       ; R8 := R8(R9)
 75 [-]: TEST      R8 1         ; if R8 then PC := 121
 76 [-]: JMP       121          ; PC := 121
 77 [-]: GETUPVAL  R8 U0        ; R8 := U0
 78 [-]: SELF      R8 R8 K0     ; R9 := R8; R8 := R8[0xde321e6f]
 79 [-]: CALL      R8 2 2       ; R8 := R8(R9)
 80 [-]: SELF      R8 R8 K19    ; R9 := R8; R8 := R8[0xac03381f]
 81 [-]: CALL      R8 2 2       ; R8 := R8(R9)
 82 [-]: TEST      R8 0         ; if not R8 then PC := 89
 83 [-]: JMP       89           ; PC := 89
 84 [-]: SELF      R8 R7 K20    ; R9 := R7; R8 := R7[0x2d9ba74f]
 85 [-]: GETUPVAL  R10 U0       ; R10 := U0
 86 [-]: SELF      R10 R10 K21  ; R11 := R10; R10 := R10[0x65d389cb]
 87 [-]: CALL      R10 2 0      ; R10,... := R10(R11)
 88 [-]: CALL      R8 0 1       ; R8(R9,...)
 89 [-]: GETGLOBAL R8 K18       ; R8 := 0x7b998233
 90 [-]: GETUPVAL  R9 U0        ; R9 := U0
 91 [-]: SELF      R9 R9 K22    ; R10 := R9; R9 := R9[0x020d4331]
 92 [-]: CALL      R9 2 2       ; R9 := R9(R10)
 93 [-]: SELF      R9 R9 K23    ; R10 := R9; R9 := R9[0x52892064]
 94 [-]: CALL      R9 2 0       ; R9,... := R9(R10)
 95 [-]: CALL      R8 0 2       ; R8 := R8(R9,...)
 96 [-]: TEST      R8 1         ; if R8 then PC := 121
 97 [-]: JMP       121          ; PC := 121
 98 [-]: SELF      R8 R7 K24    ; R9 := R7; R8 := R7[0xa83b7094]
 99 [-]: GETUPVAL  R10 U0       ; R10 := U0
100 [-]: SELF      R10 R10 K22  ; R11 := R10; R10 := R10[0x020d4331]
101 [-]: CALL      R10 2 2      ; R10 := R10(R11)
102 [-]: SELF      R10 R10 K25  ; R11 := R10; R10 := R10[0x6f59dabf]
103 [-]: CALL      R10 2 2      ; R10 := R10(R11)
104 [-]: GETGLOBAL R11 K26      ; R11 := 0x0469f296
105 [-]: CALL      R11 1 0      ; R11,... := R11()
106 [-]: CALL      R8 0 1       ; R8(R9,...)
107 [-]: GETGLOBAL R8 K18       ; R8 := 0x7b998233
108 [-]: MOVE      R9 R4        ; R9 := R4
109 [-]: CALL      R8 2 2       ; R8 := R8(R9)
110 [-]: TEST      R8 1         ; if R8 then PC := 121
111 [-]: JMP       121          ; PC := 121
112 [-]: SELF      R8 R4 K24    ; R9 := R4; R8 := R4[0xa83b7094]
113 [-]: GETUPVAL  R10 U0       ; R10 := U0
114 [-]: SELF      R10 R10 K22  ; R11 := R10; R10 := R10[0x020d4331]
115 [-]: CALL      R10 2 2      ; R10 := R10(R11)
116 [-]: SELF      R10 R10 K25  ; R11 := R10; R10 := R10[0x6f59dabf]
117 [-]: CALL      R10 2 2      ; R10 := R10(R11)
118 [-]: GETGLOBAL R11 K26      ; R11 := 0x0469f296
119 [-]: CALL      R11 1 0      ; R11,... := R11()
120 [-]: CALL      R8 0 1       ; R8(R9,...)
121 [-]: GETUPVAL  R8 U0        ; R8 := U0
122 [-]: SELF      R8 R8 K0     ; R9 := R8; R8 := R8[0xde321e6f]
123 [-]: CALL      R8 2 2       ; R8 := R8(R9)
124 [-]: SELF      R8 R8 K27    ; R9 := R8; R8 := R8[0x40a5b7af]
125 [-]: SELF      R10 R0 K28   ; R11 := R0; R10 := R0[0x24b019ac]
126 [-]: CALL      R10 2 0      ; R10,... := R10(R11)
127 [-]: CALL      R8 0 1       ; R8(R9,...)
128 [-]: SELF      R8 R0 K29    ; R9 := R0; R8 := R0[0xcc2fcc95]
129 [-]: LOADKB    R10 0 0      ; R10 := false
130 [-]: CALL      R8 3 1       ; R8(R9,R10)
131 [-]: GETGLOBAL R8 K18       ; R8 := 0x7b998233
132 [-]: MOVE      R9 R5        ; R9 := R5
133 [-]: CALL      R8 2 2       ; R8 := R8(R9)
134 [-]: TEST      R8 1         ; if R8 then PC := 140
135 [-]: JMP       140          ; PC := 140
136 [-]: GETGLOBAL R8 K3        ; R8 := 0x89326c93
137 [-]: SELF      R8 R8 K30    ; R9 := R8; R8 := R8[0x59c96e77]
138 [-]: MOVE      R10 R5       ; R10 := R5
139 [-]: CALL      R8 3 1       ; R8(R9,R10)
140 [-]: GETUPVAL  R8 U4        ; R8 := U4
141 [-]: GETGLOBAL R9 K31       ; R9 := 0x2b101027
142 [-]: CALL      R8 2 1       ; R8(R9)
143 [-]: JMP       147          ; PC := 147
144 [-]: SELF      R8 R0 K29    ; R9 := R0; R8 := R0[0xcc2fcc95]
145 [-]: LOADKB    R10 0 0      ; R10 := false
146 [-]: CALL      R8 3 1       ; R8(R9,R10)
147 [-]: RETURN    R0 1         ; return 


; Function #18:
;
; Name:            
; Defined at line: 758
; #Upvalues:       5
; #Parameters:     1
; Is_vararg:       0
; Max Stack Size:  17

  1 [-]: GETUPVAL  R1 U0        ; R1 := U0
  2 [-]: GETGLOBAL R2 K0        ; R2 := 0x9c6d95f7
  3 [-]: CALL      R1 2 1       ; R1(R2)
  4 [-]: GETUPVAL  R1 U1        ; R1 := U1
  5 [-]: SELF      R1 R1 K1     ; R2 := R1; R1 := R1[0xeea7f8c4]
  6 [-]: CALL      R1 2 2       ; R1 := R1(R2)
  7 [-]: GETUPVAL  R2 U1        ; R2 := U1
  8 [-]: SELF      R2 R2 K1     ; R3 := R2; R2 := R2[0xeea7f8c4]
  9 [-]: CALL      R2 2 2       ; R2 := R2(R3)
 10 [-]: GETTABLE  R2 R2 K2     ; R2 := R2["heading"]
 11 [-]: GETUPVAL  R3 U1        ; R3 := U1
 12 [-]: SELF      R3 R3 K1     ; R4 := R3; R3 := R3[0xeea7f8c4]
 13 [-]: CALL      R3 2 2       ; R3 := R3(R4)
 14 [-]: GETTABLE  R3 R3 K3     ; R3 := R3["pitch"]
 15 [-]: GETGLOBAL R4 K4        ; R4 := 0x00046924
 16 [-]: MOVE      R5 R2        ; R5 := R2
 17 [-]: MOVE      R6 R3        ; R6 := R3
 18 [-]: CONST     R7 0         ; R7 := 0.000000
 19 [-]: CALL      R4 4 2       ; R4 := R4(R5,R6,R7)
 20 [-]: GETGLOBAL R5 K5        ; R5 := 0xf6c6e505
 21 [-]: MOVE      R6 R1        ; R6 := R1
 22 [-]: CALL      R5 2 2       ; R5 := R5(R6)
 23 [-]: GETUPVAL  R6 U1        ; R6 := U1
 24 [-]: SELF      R6 R6 K6     ; R7 := R6; R6 := R6[0xf6ebd926]
 25 [-]: CALL      R6 2 2       ; R6 := R6(R7)
 26 [-]: ADD       R6 R5 R6     ; R6 := R5 + R6
 27 [-]: GETTABLE  R7 R6 K7     ; R7 := R6["y"]
 28 [-]: ADD       R7 R7 K8     ; R7 := R7 + 1.100000
 29 [-]: SETTABLE  R6 K7 R7     ; R6[0x24b019ac] := R7
 30 [-]: LOADNIL   R7 R7        ; R7 := nil
 31 [-]: GETGLOBAL R8 K9        ; R8 := 0x89326c93
 32 [-]: SELF      R8 R8 K10    ; R9 := R8; R8 := R8[0x18d05d30]
 33 [-]: CALL      R8 2 2       ; R8 := R8(R9)
 34 [-]: TEST      R8 0         ; if not R8 then PC := 55
 35 [-]: JMP       55           ; PC := 55
 36 [-]: GETUPVAL  R8 U1        ; R8 := U1
 37 [-]: SELF      R8 R8 K6     ; R9 := R8; R8 := R8[0xf6ebd926]
 38 [-]: CALL      R8 2 2       ; R8 := R8(R9)
 39 [-]: GETUPVAL  R9 U1        ; R9 := U1
 40 [-]: SELF      R9 R9 K11    ; R10 := R9; R9 := R9[0x9ba17154]
 41 [-]: CALL      R9 2 2       ; R9 := R9(R10)
 42 [-]: MUL       R10 R9 K12   ; R10 := R9 * 2.000000
 43 [-]: ADD       R8 R8 R10    ; R8 := R8 + R10
 44 [-]: GETUPVAL  R10 U1       ; R10 := U1
 45 [-]: SELF      R10 R10 K13  ; R11 := R10; R10 := R10[0xcb3851b8]
 46 [-]: CALL      R10 2 2      ; R10 := R10(R11)
 47 [-]: GETGLOBAL R11 K9       ; R11 := 0x89326c93
 48 [-]: SELF      R11 R11 K14  ; R12 := R11; R11 := R11[0x05909209]
 49 [-]: GETGLOBAL R13 K15      ; R13 := 0xb367793a
 50 [-]: MOVE      R14 R8       ; R14 := R8
 51 [-]: MOVE      R15 R10      ; R15 := R10
 52 [-]: GETUPVAL  R16 U1       ; R16 := U1
 53 [-]: CALL      R11 6 2      ; R11 := R11(R12,R13,R14,R15,R16)
 54 [-]: MOVE      R7 R11       ; R7 := R11
 55 [-]: GETUPVAL  R11 U2       ; R11 := U2
 56 [-]: GETGLOBAL R12 K16      ; R12 := 0x31643bcd
 57 [-]: CALL      R11 2 1      ; R11(R12)
 58 [-]: GETUPVAL  R11 U3       ; R11 := U3
 59 [-]: GETGLOBAL R12 K17      ; R12 := 0x369155d7
 60 [-]: CALL      R11 2 1      ; R11(R12)
 61 [-]: GETGLOBAL R11 K9       ; R11 := 0x89326c93
 62 [-]: SELF      R11 R11 K10  ; R12 := R11; R11 := R11[0x18d05d30]
 63 [-]: CALL      R11 2 2      ; R11 := R11(R12)
 64 [-]: TEST      R11 0        ; if not R11 then PC := 102
 65 [-]: JMP       102          ; PC := 102
 66 [-]: GETGLOBAL R11 K9       ; R11 := 0x89326c93
 67 [-]: SELF      R11 R11 K14  ; R12 := R11; R11 := R11[0x05909209]
 68 [-]: GETGLOBAL R13 K18      ; R13 := 0x29f34bf3
 69 [-]: MOVE      R14 R6       ; R14 := R6
 70 [-]: MOVE      R15 R4       ; R15 := R4
 71 [-]: GETUPVAL  R16 U1       ; R16 := U1
 72 [-]: CALL      R11 6 1      ; R11(R12,R13,R14,R15,R16)
 73 [-]: GETGLOBAL R11 K9       ; R11 := 0x89326c93
 74 [-]: SELF      R11 R11 K14  ; R12 := R11; R11 := R11[0x05909209]
 75 [-]: GETGLOBAL R13 K19      ; R13 := 0x5a74f477
 76 [-]: MOVE      R14 R6       ; R14 := R6
 77 [-]: GETGLOBAL R15 K20      ; R15 := ZERO_ROTATION
 78 [-]: CALL      R11 5 1      ; R11(R12,R13,R14,R15)
 79 [-]: GETUPVAL  R11 U1       ; R11 := U1
 80 [-]: SELF      R11 R11 K21  ; R12 := R11; R11 := R11[0xde321e6f]
 81 [-]: CALL      R11 2 2      ; R11 := R11(R12)
 82 [-]: SELF      R11 R11 K22  ; R12 := R11; R11 := R11[0x40a5b7af]
 83 [-]: SELF      R13 R0 K23   ; R14 := R0; R13 := R0[0x24b019ac]
 84 [-]: CALL      R13 2 0      ; R13,... := R13(R14)
 85 [-]: CALL      R11 0 1      ; R11(R12,...)
 86 [-]: SELF      R11 R0 K24   ; R12 := R0; R11 := R0[0xcc2fcc95]
 87 [-]: LOADKB    R13 0 0      ; R13 := false
 88 [-]: CALL      R11 3 1      ; R11(R12,R13)
 89 [-]: GETUPVAL  R11 U4       ; R11 := U4
 90 [-]: GETGLOBAL R12 K25      ; R12 := 0x2b101027
 91 [-]: CALL      R11 2 1      ; R11(R12)
 92 [-]: GETGLOBAL R11 K26      ; R11 := 0x7b998233
 93 [-]: MOVE      R12 R7       ; R12 := R7
 94 [-]: CALL      R11 2 2      ; R11 := R11(R12)
 95 [-]: TEST      R11 1        ; if R11 then PC := 105
 96 [-]: JMP       105          ; PC := 105
 97 [-]: GETGLOBAL R11 K9       ; R11 := 0x89326c93
 98 [-]: SELF      R11 R11 K27  ; R12 := R11; R11 := R11[0x59c96e77]
 99 [-]: MOVE      R13 R7       ; R13 := R7
100 [-]: CALL      R11 3 1      ; R11(R12,R13)
101 [-]: JMP       105          ; PC := 105
102 [-]: SELF      R11 R0 K24   ; R12 := R0; R11 := R0[0xcc2fcc95]
103 [-]: LOADKB    R13 0 0      ; R13 := false
104 [-]: CALL      R11 3 1      ; R11(R12,R13)
105 [-]: RETURN    R0 1         ; return 


; Function #19:
;
; Name:            
; Defined at line: 799
; #Upvalues:       5
; #Parameters:     2
; Is_vararg:       0
; Max Stack Size:  22

  1 [-]: GETUPVAL  R9 U0        ; R9 := U0
  2 [-]: GETGLOBAL R10 K0       ; R10 := 0x9c6d95f7
  3 [-]: CALL      R9 2 1       ; R9(R10)
  4 [-]: GETGLOBAL R9 K1        ; R9 := 0x89326c93
  5 [-]: SELF      R9 R9 K2     ; R10 := R9; R9 := R9[0x18d05d30]
  6 [-]: CALL      R9 2 2       ; R9 := R9(R10)
  7 [-]: TEST      R9 0         ; if not R9 then PC := 133
  8 [-]: JMP       133          ; PC := 133
  9 [-]: GETUPVAL  R9 U1        ; R9 := U1
 10 [-]: SELF      R9 R9 K3     ; R10 := R9; R9 := R9[0xde321e6f]
 11 [-]: CALL      R9 2 2       ; R9 := R9(R10)
 12 [-]: MOVE      R2 R9        ; R2 := R9
 13 [-]: SELF      R9 R2 K4     ; R10 := R2; R9 := R2[0xefd0fde2]
 14 [-]: CALL      R9 2 2       ; R9 := R9(R10)
 15 [-]: MOVE      R3 R9        ; R3 := R9
 16 [-]: GETGLOBAL R9 K5        ; R9 := 0xa421af95
 17 [-]: CALL      R9 1 2       ; R9 := R9()
 18 [-]: GETGLOBAL R10 K5       ; R10 := 0xa421af95
 19 [-]: GETTABLE  R11 R3 K6    ; R11 := R3["x"]
 20 [-]: GETTABLE  R12 R3 K7    ; R12 := R3["y"]
 21 [-]: SUB       R12 R12 K8   ; R12 := R12 - 10.000000
 22 [-]: GETTABLE  R13 R3 K9    ; R13 := R3["z"]
 23 [-]: CALL      R10 4 2      ; R10 := R10(R11,R12,R13)
 24 [-]: GETGLOBAL R11 K1       ; R11 := 0x89326c93
 25 [-]: SELF      R11 R11 K10  ; R12 := R11; R11 := R11[0xbd5d0ec1]
 26 [-]: MOVE      R13 R3       ; R13 := R3
 27 [-]: MOVE      R14 R10      ; R14 := R10
 28 [-]: GETUPVAL  R15 U1       ; R15 := U1
 29 [-]: LOADNIL   R16 R16      ; R16 := nil
 30 [-]: MOVE      R17 R9       ; R17 := R9
 31 [-]: CALL      R11 7 2      ; R11 := R11(R12,R13,R14,R15,R16,R17)
 32 [-]: TEST      R11 0        ; if not R11 then PC := 35
 33 [-]: JMP       35           ; PC := 35
 34 [-]: MOVE      R3 R9        ; R3 := R9
 35 [-]: LOADKB    R11 0 0      ; R11 := false
 36 [-]: GETGLOBAL R12 K1       ; R12 := 0x89326c93
 37 [-]: SELF      R12 R12 K11  ; R13 := R12; R12 := R12[0xfb669000]
 38 [-]: GETGLOBAL R14 K12      ; R14 := 0x487dd972
 39 [-]: MOVE      R15 R3       ; R15 := R3
 40 [-]: CONST     R16 0        ; R16 := 0.000000
 41 [-]: GETGLOBAL R17 K13      ; R17 := 0xeaa6fd13
 42 [-]: CALL      R12 6 2      ; R12 := R12(R13,R14,R15,R16,R17)
 43 [-]: LEN       R13 R12      ; R13 := # R12
 44 [-]: LT        0 K14 R13    ; if 0.000000 >= R13 then PC := 75
 45 [-]: JMP       75           ; PC := 75
 46 [-]: GETGLOBAL R13 K15      ; R13 := 0x7b998233
 47 [-]: GETTABLE  R14 R12 K16  ; R14 := R12[1.000000]
 48 [-]: CALL      R13 2 2      ; R13 := R13(R14)
 49 [-]: TEST      R13 1        ; if R13 then PC := 75
 50 [-]: JMP       75           ; PC := 75
 51 [-]: LOADKB    R11 1 0      ; R11 := true
 52 [-]: GETTABLE  R13 R12 K16  ; R13 := R12[1.000000]
 53 [-]: SELF      R13 R13 K17  ; R14 := R13; R13 := R13[0xd1586535]
 54 [-]: CALL      R13 2 2      ; R13 := R13(R14)
 55 [-]: SUB       R13 R13 R3   ; R13 := R13 - R3
 56 [-]: SETTABLE  R13 K7 K14   ; R13["y"] := 0.000000
 57 [-]: GETGLOBAL R14 K18      ; R14 := 0xc2892f65
 58 [-]: MOVE      R15 R13      ; R15 := R13
 59 [-]: CALL      R14 2 1      ; R14(R15)
 60 [-]: GETGLOBAL R14 K13      ; R14 := 0xeaa6fd13
 61 [-]: MUL       R14 R13 R14  ; R14 := R13 * R14
 62 [-]: SUB       R3 R3 R14    ; R3 := R3 - R14
 63 [-]: GETGLOBAL R14 K1       ; R14 := 0x89326c93
 64 [-]: SELF      R14 R14 K11  ; R15 := R14; R14 := R14[0xfb669000]
 65 [-]: GETGLOBAL R16 K12      ; R16 := 0x487dd972
 66 [-]: MOVE      R17 R3       ; R17 := R3
 67 [-]: CONST     R18 0        ; R18 := 0.000000
 68 [-]: GETGLOBAL R19 K13      ; R19 := 0xeaa6fd13
 69 [-]: CALL      R14 6 2      ; R14 := R14(R15,R16,R17,R18,R19)
 70 [-]: MOVE      R12 R14      ; R12 := R14
 71 [-]: GETGLOBAL R14 K19      ; R14 := 0xcbd666e1
 72 [-]: CONST     R15 0        ; R15 := 0.000000
 73 [-]: CALL      R14 2 1      ; R14(R15)
 74 [-]: JMP       43           ; PC := 43
 75 [-]: TEST      R11 0        ; if not R11 then PC := 98
 76 [-]: JMP       98           ; PC := 98
 77 [-]: GETTABLE  R14 R3 K7    ; R14 := R3["y"]
 78 [-]: ADD       R14 R14 K16  ; R14 := R14 + 1.000000
 79 [-]: SETTABLE  R3 K7 R14    ; R3["y"] := R14
 80 [-]: GETGLOBAL R14 K5       ; R14 := 0xa421af95
 81 [-]: GETTABLE  R15 R3 K6    ; R15 := R3["x"]
 82 [-]: GETTABLE  R16 R3 K7    ; R16 := R3["y"]
 83 [-]: SUB       R16 R16 K8   ; R16 := R16 - 10.000000
 84 [-]: GETTABLE  R17 R3 K9    ; R17 := R3["z"]
 85 [-]: CALL      R14 4 2      ; R14 := R14(R15,R16,R17)
 86 [-]: MOVE      R10 R14      ; R10 := R14
 87 [-]: GETGLOBAL R14 K1       ; R14 := 0x89326c93
 88 [-]: SELF      R14 R14 K10  ; R15 := R14; R14 := R14[0xbd5d0ec1]
 89 [-]: MOVE      R16 R3       ; R16 := R3
 90 [-]: MOVE      R17 R10      ; R17 := R10
 91 [-]: GETUPVAL  R18 U1       ; R18 := U1
 92 [-]: LOADNIL   R19 R19      ; R19 := nil
 93 [-]: MOVE      R20 R9       ; R20 := R9
 94 [-]: CALL      R14 7 2      ; R14 := R14(R15,R16,R17,R18,R19,R20)
 95 [-]: TEST      R14 0        ; if not R14 then PC := 98
 96 [-]: JMP       98           ; PC := 98
 97 [-]: MOVE      R3 R9        ; R3 := R9
 98 [-]: GETUPVAL  R14 U1       ; R14 := U1
 99 [-]: SELF      R14 R14 K20  ; R15 := R14; R14 := R14[0xcb3851b8]
100 [-]: CALL      R14 2 2      ; R14 := R14(R15)
101 [-]: MOVE      R4 R14       ; R4 := R14
102 [-]: GETTABLE  R14 R4 K21   ; R14 := R4["pitch"]
103 [-]: SUB       R14 R14 K22  ; R14 := R14 - 90.000000
104 [-]: SETTABLE  R4 K21 R14   ; R4["pitch"] := R14
105 [-]: GETGLOBAL R14 K1       ; R14 := 0x89326c93
106 [-]: SELF      R14 R14 K23  ; R15 := R14; R14 := R14[0x05909209]
107 [-]: GETGLOBAL R16 K24      ; R16 := 0x71f576f7
108 [-]: MOVE      R17 R3       ; R17 := R3
109 [-]: GETGLOBAL R18 K25      ; R18 := ZERO_ROTATION
110 [-]: CALL      R14 5 1      ; R14(R15,R16,R17,R18)
111 [-]: GETGLOBAL R14 K1       ; R14 := 0x89326c93
112 [-]: SELF      R14 R14 K23  ; R15 := R14; R14 := R14[0x05909209]
113 [-]: GETGLOBAL R16 K26      ; R16 := 0xb367793a
114 [-]: MOVE      R17 R3       ; R17 := R3
115 [-]: MOVE      R18 R4       ; R18 := R4
116 [-]: GETUPVAL  R19 U1       ; R19 := U1
117 [-]: CALL      R14 6 2      ; R14 := R14(R15,R16,R17,R18,R19)
118 [-]: MOVE      R5 R14       ; R5 := R14
119 [-]: GETUPVAL  R14 U1       ; R14 := U1
120 [-]: SELF      R14 R14 K27  ; R15 := R14; R14 := R14[0xeea7f8c4]
121 [-]: CALL      R14 2 2      ; R14 := R14(R15)
122 [-]: GETTABLE  R6 R14 K28   ; R6 := R14["heading"]
123 [-]: GETUPVAL  R14 U1       ; R14 := U1
124 [-]: SELF      R14 R14 K27  ; R15 := R14; R14 := R14[0xeea7f8c4]
125 [-]: CALL      R14 2 2      ; R14 := R14(R15)
126 [-]: GETTABLE  R7 R14 K21   ; R7 := R14["pitch"]
127 [-]: GETGLOBAL R14 K29      ; R14 := 0x00046924
128 [-]: MOVE      R15 R6       ; R15 := R6
129 [-]: MOVE      R16 R7       ; R16 := R7
130 [-]: CONST     R17 0        ; R17 := 0.000000
131 [-]: CALL      R14 4 2      ; R14 := R14(R15,R16,R17)
132 [-]: MOVE      R8 R14       ; R8 := R14
133 [-]: GETUPVAL  R14 U2       ; R14 := U2
134 [-]: GETGLOBAL R15 K30      ; R15 := 0xa70e7c37
135 [-]: CALL      R14 2 1      ; R14(R15)
136 [-]: GETUPVAL  R14 U3       ; R14 := U3
137 [-]: GETGLOBAL R15 K31      ; R15 := 0x81dc3453
138 [-]: CALL      R14 2 1      ; R14(R15)
139 [-]: GETGLOBAL R14 K1       ; R14 := 0x89326c93
140 [-]: SELF      R14 R14 K2   ; R15 := R14; R14 := R14[0x18d05d30]
141 [-]: CALL      R14 2 2      ; R14 := R14(R15)
142 [-]: TEST      R14 0        ; if not R14 then PC := 231
143 [-]: JMP       231          ; PC := 231
144 [-]: GETGLOBAL R14 K1       ; R14 := 0x89326c93
145 [-]: SELF      R14 R14 K23  ; R15 := R14; R14 := R14[0x05909209]
146 [-]: GETGLOBAL R16 K24      ; R16 := 0x71f576f7
147 [-]: MOVE      R17 R3       ; R17 := R3
148 [-]: GETGLOBAL R18 K25      ; R18 := ZERO_ROTATION
149 [-]: CALL      R14 5 1      ; R14(R15,R16,R17,R18)
150 [-]: LOADNIL   R14 R14      ; R14 := nil
151 [-]: TEST      R1 0         ; if not R1 then PC := 166
152 [-]: JMP       166          ; PC := 166
153 [-]: GETGLOBAL R15 K1       ; R15 := 0x89326c93
154 [-]: SELF      R15 R15 K32  ; R16 := R15; R15 := R15[0x29ef273d]
155 [-]: CALL      R15 2 2      ; R15 := R15(R16)
156 [-]: SELF      R15 R15 K33  ; R16 := R15; R15 := R15[0x6cd833c5]
157 [-]: GETGLOBAL R17 K34      ; R17 := 0x3a4c411c
158 [-]: MOVE      R18 R3       ; R18 := R3
159 [-]: MOVE      R19 R8       ; R19 := R8
160 [-]: GETGLOBAL R20 K35      ; R20 := 0x0469f296
161 [-]: LOADK     R21 K36      ; R21 := "TENNO"
162 [-]: CALL      R20 2 0      ; R20,... := R20(R21)
163 [-]: CALL      R15 0 2      ; R15 := R15(R16,...)
164 [-]: MOVE      R14 R15      ; R14 := R15
165 [-]: JMP       178          ; PC := 178
166 [-]: GETGLOBAL R15 K1       ; R15 := 0x89326c93
167 [-]: SELF      R15 R15 K32  ; R16 := R15; R15 := R15[0x29ef273d]
168 [-]: CALL      R15 2 2      ; R15 := R15(R16)
169 [-]: SELF      R15 R15 K33  ; R16 := R15; R15 := R15[0x6cd833c5]
170 [-]: GETGLOBAL R17 K37      ; R17 := 0xbbe13559
171 [-]: MOVE      R18 R3       ; R18 := R3
172 [-]: MOVE      R19 R8       ; R19 := R8
173 [-]: GETGLOBAL R20 K35      ; R20 := 0x0469f296
174 [-]: LOADK     R21 K36      ; R21 := "TENNO"
175 [-]: CALL      R20 2 0      ; R20,... := R20(R21)
176 [-]: CALL      R15 0 2      ; R15 := R15(R16,...)
177 [-]: MOVE      R14 R15      ; R14 := R15
178 [-]: GETGLOBAL R15 K15      ; R15 := 0x7b998233
179 [-]: MOVE      R16 R14      ; R16 := R14
180 [-]: CALL      R15 2 2      ; R15 := R15(R16)
181 [-]: TEST      R15 1        ; if R15 then PC := 208
182 [-]: JMP       208          ; PC := 208
183 [-]: SELF      R15 R14 K38  ; R16 := R14; R15 := R14[0xbb610e5b]
184 [-]: CALL      R15 2 2      ; R15 := R15(R16)
185 [-]: SELF      R16 R15 K39  ; R17 := R15; R16 := R15[0x0cca925a]
186 [-]: GETUPVAL  R18 U1       ; R18 := U1
187 [-]: SELF      R18 R18 K40  ; R19 := R18; R18 := R18[0x808b79e6]
188 [-]: CALL      R18 2 0      ; R18,... := R18(R19)
189 [-]: CALL      R16 0 1      ; R16(R17,...)
190 [-]: SELF      R16 R15 K41  ; R17 := R15; R16 := R15[0xc40eed62]
191 [-]: GETUPVAL  R18 U1       ; R18 := U1
192 [-]: CALL      R16 3 1      ; R16(R17,R18)
193 [-]: SELF      R16 R15 K42  ; R17 := R15; R16 := R15[0x74874678]
194 [-]: GETUPVAL  R18 U1       ; R18 := U1
195 [-]: CALL      R16 3 1      ; R16(R17,R18)
196 [-]: GETUPVAL  R16 U1       ; R16 := U1
197 [-]: SELF      R16 R16 K43  ; R17 := R16; R16 := R16[0xf80fae85]
198 [-]: CALL      R16 2 2      ; R16 := R16(R17)
199 [-]: TEST      R16 0        ; if not R16 then PC := 204
200 [-]: JMP       204          ; PC := 204
201 [-]: SELF      R16 R14 K44  ; R17 := R14; R16 := R14[0xa7a16361]
202 [-]: LOADKB    R18 0 0      ; R18 := false
203 [-]: CALL      R16 3 1      ; R16(R17,R18)
204 [-]: GETGLOBAL R16 K1       ; R16 := 0x89326c93
205 [-]: SELF      R16 R16 K45  ; R17 := R16; R16 := R16[0xb7d33840]
206 [-]: LOADK     R18 K46      ; R18 := "OnPlayersChanged"
207 [-]: CALL      R16 3 1      ; R16(R17,R18)
208 [-]: GETUPVAL  R16 U1       ; R16 := U1
209 [-]: SELF      R16 R16 K3   ; R17 := R16; R16 := R16[0xde321e6f]
210 [-]: CALL      R16 2 2      ; R16 := R16(R17)
211 [-]: SELF      R16 R16 K47  ; R17 := R16; R16 := R16[0x40a5b7af]
212 [-]: SELF      R18 R0 K48   ; R19 := R0; R18 := R0[0x24b019ac]
213 [-]: CALL      R18 2 0      ; R18,... := R18(R19)
214 [-]: CALL      R16 0 1      ; R16(R17,...)
215 [-]: SELF      R16 R0 K49   ; R17 := R0; R16 := R0[0xcc2fcc95]
216 [-]: LOADKB    R18 0 0      ; R18 := false
217 [-]: CALL      R16 3 1      ; R16(R17,R18)
218 [-]: GETUPVAL  R16 U4       ; R16 := U4
219 [-]: GETGLOBAL R17 K50      ; R17 := 0x0d301081
220 [-]: CALL      R16 2 1      ; R16(R17)
221 [-]: GETGLOBAL R16 K15      ; R16 := 0x7b998233
222 [-]: MOVE      R17 R5       ; R17 := R5
223 [-]: CALL      R16 2 2      ; R16 := R16(R17)
224 [-]: TEST      R16 1        ; if R16 then PC := 234
225 [-]: JMP       234          ; PC := 234
226 [-]: GETGLOBAL R16 K1       ; R16 := 0x89326c93
227 [-]: SELF      R16 R16 K51  ; R17 := R16; R16 := R16[0x59c96e77]
228 [-]: MOVE      R18 R5       ; R18 := R5
229 [-]: CALL      R16 3 1      ; R16(R17,R18)
230 [-]: JMP       234          ; PC := 234
231 [-]: SELF      R16 R0 K49   ; R17 := R0; R16 := R0[0xcc2fcc95]
232 [-]: LOADKB    R18 0 0      ; R18 := false
233 [-]: CALL      R16 3 1      ; R16(R17,R18)
234 [-]: RETURN    R0 1         ; return 


; Function #20:
;
; Name:            
; Defined at line: 882
; #Upvalues:       5
; #Parameters:     1
; Is_vararg:       0
; Max Stack Size:  30

  1 [-]: GETGLOBAL R5 K0        ; R5 := 0x89326c93
  2 [-]: SELF      R5 R5 K1     ; R6 := R5; R5 := R5[0x18d05d30]
  3 [-]: CALL      R5 2 2       ; R5 := R5(R6)
  4 [-]: TEST      R5 0         ; if not R5 then PC := 28
  5 [-]: JMP       28           ; PC := 28
  6 [-]: GETUPVAL  R5 U0        ; R5 := U0
  7 [-]: SELF      R5 R5 K2     ; R6 := R5; R5 := R5[0xd1586535]
  8 [-]: CALL      R5 2 2       ; R5 := R5(R6)
  9 [-]: MOVE      R1 R5        ; R1 := R5
 10 [-]: GETUPVAL  R5 U0        ; R5 := U0
 11 [-]: SELF      R5 R5 K3     ; R6 := R5; R5 := R5[0xcb3851b8]
 12 [-]: CALL      R5 2 2       ; R5 := R5(R6)
 13 [-]: MOVE      R2 R5        ; R2 := R5
 14 [-]: GETUPVAL  R5 U0        ; R5 := U0
 15 [-]: SELF      R5 R5 K4     ; R6 := R5; R5 := R5[0xde321e6f]
 16 [-]: CALL      R5 2 2       ; R5 := R5(R6)
 17 [-]: SELF      R5 R5 K5     ; R6 := R5; R5 := R5[0xf7d48ee0]
 18 [-]: CALL      R5 2 2       ; R5 := R5(R6)
 19 [-]: MOVE      R4 R5        ; R4 := R5
 20 [-]: GETGLOBAL R5 K0        ; R5 := 0x89326c93
 21 [-]: SELF      R5 R5 K6     ; R6 := R5; R5 := R5[0x05909209]
 22 [-]: GETGLOBAL R7 K7        ; R7 := 0xb367793a
 23 [-]: MOVE      R8 R1        ; R8 := R1
 24 [-]: MOVE      R9 R2        ; R9 := R2
 25 [-]: MOVE      R10 R4       ; R10 := R4
 26 [-]: CALL      R5 6 2       ; R5 := R5(R6,R7,R8,R9,R10)
 27 [-]: MOVE      R3 R5        ; R3 := R5
 28 [-]: GETUPVAL  R5 U1        ; R5 := U1
 29 [-]: GETGLOBAL R6 K8        ; R6 := 0x9c6d95f7
 30 [-]: CALL      R5 2 1       ; R5(R6)
 31 [-]: GETUPVAL  R5 U2        ; R5 := U2
 32 [-]: GETGLOBAL R6 K9        ; R6 := 0x8bc80b84
 33 [-]: CALL      R5 2 1       ; R5(R6)
 34 [-]: GETUPVAL  R5 U3        ; R5 := U3
 35 [-]: GETGLOBAL R6 K10       ; R6 := 0x9b1586f4
 36 [-]: CALL      R5 2 1       ; R5(R6)
 37 [-]: GETGLOBAL R5 K0        ; R5 := 0x89326c93
 38 [-]: SELF      R5 R5 K1     ; R6 := R5; R5 := R5[0x18d05d30]
 39 [-]: CALL      R5 2 2       ; R5 := R5(R6)
 40 [-]: TEST      R5 0         ; if not R5 then PC := 188
 41 [-]: JMP       188          ; PC := 188
 42 [-]: GETGLOBAL R5 K0        ; R5 := 0x89326c93
 43 [-]: SELF      R5 R5 K6     ; R6 := R5; R5 := R5[0x05909209]
 44 [-]: GETGLOBAL R7 K11       ; R7 := 0xd15521f1
 45 [-]: MOVE      R8 R1        ; R8 := R1
 46 [-]: MOVE      R9 R2        ; R9 := R2
 47 [-]: MOVE      R10 R4       ; R10 := R4
 48 [-]: CALL      R5 6 1       ; R5(R6,R7,R8,R9,R10)
 49 [-]: GETUPVAL  R5 U4        ; R5 := U4
 50 [-]: GETTABLE  R5 R5 K12    ; R5 := R5[0x1832af14]
 51 [-]: GETUPVAL  R6 U0        ; R6 := U0
 52 [-]: GETGLOBAL R7 K13       ; R7 := 0x8ed2d97c
 53 [-]: GETUPVAL  R8 U0        ; R8 := U0
 54 [-]: GETGLOBAL R9 K14       ; R9 := 0x1b0d0e51
 55 [-]: GETGLOBAL R10 K15      ; R10 := 0x1b1e1022
 56 [-]: GETGLOBAL R11 K16      ; R11 := 0x63ae2879
 57 [-]: CALL      R5 7 2       ; R5 := R5(R6,R7,R8,R9,R10,R11)
 58 [-]: GETGLOBAL R6 K17       ; R6 := 0x7b998233
 59 [-]: MOVE      R7 R5        ; R7 := R5
 60 [-]: CALL      R6 2 2       ; R6 := R6(R7)
 61 [-]: TEST      R6 1         ; if R6 then PC := 68
 62 [-]: JMP       68           ; PC := 68
 63 [-]: GETGLOBAL R6 K18       ; R6 := 0x4ec73e73
 64 [-]: MOVE      R7 R5        ; R7 := R5
 65 [-]: CALL      R6 2 2       ; R6 := R6(R7)
 66 [-]: EQ        0 R6 K19     ; if R6 ~= nil then PC := 69
 67 [-]: JMP       69           ; PC := 69
 68 [-]: LOADKB    R6 0 1       ; R6 := false; PC := 69
 69 [-]: LOADKB    R6 1 0       ; R6 := true
 70 [-]: TEST      R6 0         ; if not R6 then PC := 180
 71 [-]: JMP       180          ; PC := 180
 72 [-]: GETGLOBAL R7 K20       ; R7 := 0x3d106989
 73 [-]: LOADK     R8 K21       ; R8 := "Liset air support Golden Instinct found "
 74 [-]: GETGLOBAL R9 K22       ; R9 := 0x64fb1586
 75 [-]: LEN       R10 R5       ; R10 := # R5
 76 [-]: CALL      R9 2 2       ; R9 := R9(R10)
 77 [-]: LOADK     R10 K23      ; R10 := " rare pickups in range("
 78 [-]: GETGLOBAL R11 K22      ; R11 := 0x64fb1586
 79 [-]: GETGLOBAL R12 K13      ; R12 := 0x8ed2d97c
 80 [-]: CALL      R11 2 2      ; R11 := R11(R12)
 81 [-]: LOADK     R12 K24      ; R12 := ")"
 82 [-]: CONCAT    R8 R8 R12    ; R8 := R8 .. R9 .. R10 .. R11 .. R12
 83 [-]: CALL      R7 2 1       ; R7(R8)
 84 [-]: GETGLOBAL R7 K25       ; R7 := 0xcbd666e1
 85 [-]: CONST     R8 1         ; R8 := 1.000000
 86 [-]: CALL      R7 2 1       ; R7(R8)
 87 [-]: NEWTABLE  R7 0 0       ; R7 := {}
 88 [-]: GETGLOBAL R8 K17       ; R8 := 0x7b998233
 89 [-]: GETUPVAL  R9 U0        ; R9 := U0
 90 [-]: CALL      R8 2 2       ; R8 := R8(R9)
 91 [-]: TEST      R8 1         ; if R8 then PC := 134
 92 [-]: JMP       134          ; PC := 134
 93 [-]: GETGLOBAL R8 K26       ; R8 := 0xc8802016
 94 [-]: MOVE      R9 R5        ; R9 := R5
 95 [-]: CALL      R8 2 4       ; R8,R9,R10 := R8(R9)
 96 [-]: JMP       132          ; PC := 132
 97 [-]: GETGLOBAL R13 K17      ; R13 := 0x7b998233
 98 [-]: MOVE      R14 R12      ; R14 := R12
 99 [-]: CALL      R13 2 2      ; R13 := R13(R14)
100 [-]: TEST      R13 1        ; if R13 then PC := 132
101 [-]: JMP       132          ; PC := 132
102 [-]: SELF      R13 R12 K27  ; R14 := R12; R13 := R12[0x47901f07]
103 [-]: GETGLOBAL R15 K28      ; R15 := 0x44fec2ed
104 [-]: GETGLOBAL R16 K29      ; R16 := EMPTY_SYMBOL
105 [-]: CALL      R13 4 1      ; R13(R14,R15,R16)
106 [-]: GETGLOBAL R13 K0       ; R13 := 0x89326c93
107 [-]: SELF      R13 R13 K6   ; R14 := R13; R13 := R13[0x05909209]
108 [-]: GETGLOBAL R15 K30      ; R15 := 0x09945ff3
109 [-]: GETUPVAL  R16 U0       ; R16 := U0
110 [-]: SELF      R16 R16 K31  ; R17 := R16; R16 := R16[0xef8e8f7f]
111 [-]: CALL      R16 2 2      ; R16 := R16(R17)
112 [-]: GETGLOBAL R17 K32      ; R17 := ZERO_ROTATION
113 [-]: MOVE      R18 R4       ; R18 := R4
114 [-]: CALL      R13 6 2      ; R13 := R13(R14,R15,R16,R17,R18)
115 [-]: GETUPVAL  R14 U4       ; R14 := U4
116 [-]: GETTABLE  R14 R14 K33  ; R14 := R14[0x08736a59]
117 [-]: GETUPVAL  R15 U0       ; R15 := U0
118 [-]: SELF      R15 R15 K2   ; R16 := R15; R15 := R15[0xd1586535]
119 [-]: CALL      R15 2 2      ; R15 := R15(R16)
120 [-]: SELF      R16 R12 K2   ; R17 := R12; R16 := R12[0xd1586535]
121 [-]: CALL      R16 2 2      ; R16 := R16(R17)
122 [-]: GETGLOBAL R17 K34      ; R17 := 0x5dc20af6
123 [-]: CALL      R14 4 2      ; R14 := R14(R15,R16,R17)
124 [-]: NEWTABLE  R15 0 0      ; R15 := {}
125 [-]: SETTABLE  R15 K35 R13  ; R15[0x5ade0cd5] := R13
126 [-]: SETTABLE  R15 K36 R14  ; R15[0x0469f296] := R14
127 [-]: GETGLOBAL R16 K37      ; R16 := 0x33bdd652
128 [-]: GETTABLE  R16 R16 K38  ; R16 := R16[0x23d5322f]
129 [-]: MOVE      R17 R7       ; R17 := R7
130 [-]: MOVE      R18 R15      ; R18 := R15
131 [-]: CALL      R16 3 1      ; R16(R17,R18)
132 [-]: TFORLOOP  R8 2         ; R11,R12 :=  R8(R9,R10); if R11 ~= nil then begin PC = 97; R10 := R11 end
133 [-]: JMP       97           ; PC := 97
134 [-]: GETGLOBAL R16 K39      ; R16 := 0x1caa79b3
135 [-]: LT        0 K40 R16    ; if 0.000000 >= R16 then PC := 165
136 [-]: JMP       165          ; PC := 165
137 [-]: GETGLOBAL R16 K17      ; R16 := 0x7b998233
138 [-]: GETUPVAL  R17 U0       ; R17 := U0
139 [-]: CALL      R16 2 2      ; R16 := R16(R17)
140 [-]: TEST      R16 1        ; if R16 then PC := 165
141 [-]: JMP       165          ; PC := 165
142 [-]: GETUPVAL  R16 U0       ; R16 := U0
143 [-]: SELF      R16 R16 K41  ; R17 := R16; R16 := R16[0x2047cfe7]
144 [-]: CALL      R16 2 2      ; R16 := R16(R17)
145 [-]: TEST      R16 1        ; if R16 then PC := 165
146 [-]: JMP       165          ; PC := 165
147 [-]: GETGLOBAL R16 K26      ; R16 := 0xc8802016
148 [-]: MOVE      R17 R7       ; R17 := R7
149 [-]: CALL      R16 2 4      ; R16,R17,R18 := R16(R17)
150 [-]: JMP       154          ; PC := 154
151 [-]: GETTABLE  R21 R20 K42  ; R21 := R20[0xd30c589d]
152 [-]: GETTABLE  R22 R20 K35  ; R22 := R20["deco"]
153 [-]: CALL      R21 2 1      ; R21(R22)
154 [-]: TFORLOOP  R16 2        ; R19,R20 :=  R16(R17,R18); if R19 ~= nil then begin PC = 151; R18 := R19 end
155 [-]: JMP       151          ; PC := 151
156 [-]: GETGLOBAL R21 K25      ; R21 := 0xcbd666e1
157 [-]: CONST     R22 0        ; R22 := 0.000000
158 [-]: CALL      R21 2 1      ; R21(R22)
159 [-]: GETGLOBAL R21 K39      ; R21 := 0x1caa79b3
160 [-]: GETGLOBAL R22 K43      ; R22 := 0x67652851
161 [-]: CALL      R22 1 2      ; R22 := R22()
162 [-]: SUB       R21 R21 R22  ; R21 := R21 - R22
163 [-]: SETGLOBAL R21 K39      ; (0x1caa79b3) := R21
164 [-]: JMP       134          ; PC := 134
165 [-]: GETGLOBAL R21 K26      ; R21 := 0xc8802016
166 [-]: MOVE      R22 R7       ; R22 := R7
167 [-]: CALL      R21 2 4      ; R21,R22,R23 := R21(R22)
168 [-]: JMP       177          ; PC := 177
169 [-]: GETGLOBAL R26 K17      ; R26 := 0x7b998233
170 [-]: GETTABLE  R27 R25 K35  ; R27 := R25["deco"]
171 [-]: CALL      R26 2 2      ; R26 := R26(R27)
172 [-]: TEST      R26 1        ; if R26 then PC := 177
173 [-]: JMP       177          ; PC := 177
174 [-]: GETTABLE  R26 R25 K35  ; R26 := R25["deco"]
175 [-]: SELF      R26 R26 K44  ; R27 := R26; R26 := R26[0xa2880940]
176 [-]: CALL      R26 2 1      ; R26(R27)
177 [-]: TFORLOOP  R21 2        ; R24,R25 :=  R21(R22,R23); if R24 ~= nil then begin PC = 169; R23 := R24 end
178 [-]: JMP       169          ; PC := 169
179 [-]: JMP       188          ; PC := 188
180 [-]: GETGLOBAL R26 K20      ; R26 := 0x3d106989
181 [-]: LOADK     R27 K45      ; R27 := "Liset air support Golden Instinct found no rare pickups in range("
182 [-]: GETGLOBAL R28 K22      ; R28 := 0x64fb1586
183 [-]: GETGLOBAL R29 K13      ; R29 := 0x8ed2d97c
184 [-]: CALL      R28 2 2      ; R28 := R28(R29)
185 [-]: LOADK     R29 K24      ; R29 := ")"
186 [-]: CONCAT    R27 R27 R29  ; R27 := R27 .. R28 .. R29
187 [-]: CALL      R26 2 1      ; R26(R27)
188 [-]: GETGLOBAL R26 K0       ; R26 := 0x89326c93
189 [-]: SELF      R26 R26 K46  ; R27 := R26; R26 := R26[0x59c96e77]
190 [-]: MOVE      R28 R3       ; R28 := R3
191 [-]: CALL      R26 3 1      ; R26(R27,R28)
192 [-]: SELF      R26 R0 K47   ; R27 := R0; R26 := R0[0xcc2fcc95]
193 [-]: LOADKB    R28 0 0      ; R28 := false
194 [-]: CALL      R26 3 1      ; R26(R27,R28)
195 [-]: RETURN    R0 1         ; return 


; Function #21:
;
; Name:            
; Defined at line: 954
; #Upvalues:       1
; #Parameters:     3
; Is_vararg:       0
; Max Stack Size:  14

  1 [-]: GETGLOBAL R3 K0        ; R3 := 0x7b998233
  2 [-]: MOVE      R4 R0        ; R4 := R0
  3 [-]: CALL      R3 2 2       ; R3 := R3(R4)
  4 [-]: TEST      R3 0         ; if not R3 then PC := 7
  5 [-]: JMP       7            ; PC := 7
  6 [-]: RETURN    R0 1         ; return 
  7 [-]: SELF      R3 R0 K1     ; R4 := R0; R3 := R0[0xfa9e477f]
  8 [-]: CALL      R3 2 2       ; R3 := R3(R4)
  9 [-]: GETGLOBAL R4 K0        ; R4 := 0x7b998233
 10 [-]: MOVE      R5 R3        ; R5 := R3
 11 [-]: CALL      R4 2 2       ; R4 := R4(R5)
 12 [-]: TEST      R4 0         ; if not R4 then PC := 15
 13 [-]: JMP       15           ; PC := 15
 14 [-]: RETURN    R0 1         ; return 
 15 [-]: GETGLOBAL R4 K0        ; R4 := 0x7b998233
 16 [-]: MOVE      R5 R1        ; R5 := R1
 17 [-]: CALL      R4 2 2       ; R4 := R4(R5)
 18 [-]: TEST      R4 0         ; if not R4 then PC := 21
 19 [-]: JMP       21           ; PC := 21
 20 [-]: RETURN    R0 1         ; return 
 21 [-]: SELF      R4 R1 K2     ; R5 := R1; R4 := R1[0x5b89142c]
 22 [-]: CALL      R4 2 2       ; R4 := R4(R5)
 23 [-]: GETGLOBAL R5 K0        ; R5 := 0x7b998233
 24 [-]: MOVE      R6 R4        ; R6 := R4
 25 [-]: CALL      R5 2 2       ; R5 := R5(R6)
 26 [-]: TEST      R5 0         ; if not R5 then PC := 29
 27 [-]: JMP       29           ; PC := 29
 28 [-]: RETURN    R0 1         ; return 
 29 [-]: SELF      R5 R0 K3     ; R6 := R0; R5 := R0[0x0cca925a]
 30 [-]: SELF      R7 R1 K4     ; R8 := R1; R7 := R1[0x808b79e6]
 31 [-]: CALL      R7 2 0       ; R7,... := R7(R8)
 32 [-]: CALL      R5 0 1       ; R5(R6,...)
 33 [-]: SELF      R5 R0 K5     ; R6 := R0; R5 := R0[0xc40eed62]
 34 [-]: MOVE      R7 R1        ; R7 := R1
 35 [-]: CALL      R5 3 1       ; R5(R6,R7)
 36 [-]: SELF      R5 R0 K6     ; R6 := R0; R5 := R0[0x74874678]
 37 [-]: MOVE      R7 R1        ; R7 := R1
 38 [-]: CALL      R5 3 1       ; R5(R6,R7)
 39 [-]: SELF      R5 R0 K7     ; R6 := R0; R5 := R0[0x8decb783]
 40 [-]: LOADKB    R7 0 0       ; R7 := false
 41 [-]: CALL      R5 3 1       ; R5(R6,R7)
 42 [-]: SELF      R5 R0 K8     ; R6 := R0; R5 := R0[0x3273ba96]
 43 [-]: GETUPVAL  R7 U0        ; R7 := U0
 44 [-]: CALL      R5 3 1       ; R5(R6,R7)
 45 [-]: SELF      R5 R0 K9     ; R6 := R0; R5 := R0[0xfb3ec60f]
 46 [-]: SELF      R7 R4 K10    ; R8 := R4; R7 := R4[0x5ca33548]
 47 [-]: CALL      R7 2 0       ; R7,... := R7(R8)
 48 [-]: CALL      R5 0 1       ; R5(R6,...)
 49 [-]: TEST      R2 1         ; if R2 then PC := 61
 50 [-]: JMP       61           ; PC := 61
 51 [-]: SELF      R5 R0 K11    ; R6 := R0; R5 := R0[0x47901f07]
 52 [-]: GETGLOBAL R7 K12       ; R7 := 0x5ade0cd5
 53 [-]: GETGLOBAL R8 K13       ; R8 := 0x0469f296
 54 [-]: LOADK     R9 K14       ; R9 := "GAME_C1_SPINE2"
 55 [-]: CALL      R8 2 2       ; R8 := R8(R9)
 56 [-]: GETGLOBAL R9 K15       ; R9 := ZERO_VECTOR
 57 [-]: GETGLOBAL R10 K16      ; R10 := ZERO_ROTATION
 58 [-]: MOVE      R11 R1       ; R11 := R1
 59 [-]: CONST     R12 1        ; R12 := 1.000000
 60 [-]: CALL      R5 8 1       ; R5(R6,R7,R8,R9,R10,R11,R12)
 61 [-]: SELF      R5 R1 K18    ; R6 := R1; R5 := R1[0xf80fae85]
 62 [-]: CALL      R5 2 2       ; R5 := R5(R6)
 63 [-]: TEST      R5 0         ; if not R5 then PC := 68
 64 [-]: JMP       68           ; PC := 68
 65 [-]: SELF      R5 R3 K19    ; R6 := R3; R5 := R3[0xa7a16361]
 66 [-]: LOADKB    R7 0 0       ; R7 := false
 67 [-]: CALL      R5 3 1       ; R5(R6,R7)
 68 [-]: GETGLOBAL R5 K0        ; R5 := 0x7b998233
 69 [-]: GETGLOBAL R6 K20       ; R6 := 0x8ebec830
 70 [-]: CALL      R5 2 2       ; R5 := R5(R6)
 71 [-]: TEST      R5 1         ; if R5 then PC := 94
 72 [-]: JMP       94           ; PC := 94
 73 [-]: SELF      R5 R0 K11    ; R6 := R0; R5 := R0[0x47901f07]
 74 [-]: GETGLOBAL R7 K21       ; R7 := 0x88efc25e
 75 [-]: GETGLOBAL R8 K20       ; R8 := 0x8ebec830
 76 [-]: CALL      R7 2 2       ; R7 := R7(R8)
 77 [-]: GETGLOBAL R8 K22       ; R8 := EMPTY_SYMBOL
 78 [-]: CALL      R5 4 1       ; R5(R6,R7,R8)
 79 [-]: SELF      R5 R0 K23    ; R6 := R0; R5 := R0[0xc1595bd5]
 80 [-]: GETGLOBAL R7 K20       ; R7 := 0x8ebec830
 81 [-]: CALL      R5 3 2       ; R5 := R5(R6,R7)
 82 [-]: GETGLOBAL R6 K0        ; R6 := 0x7b998233
 83 [-]: MOVE      R7 R5        ; R7 := R5
 84 [-]: CALL      R6 2 2       ; R6 := R6(R7)
 85 [-]: TEST      R6 1         ; if R6 then PC := 94
 86 [-]: JMP       94           ; PC := 94
 87 [-]: LEN       R6 R5        ; R6 := # R5
 88 [-]: LT        0 K24 R6     ; if 0.000000 >= R6 then PC := 94
 89 [-]: JMP       94           ; PC := 94
 90 [-]: GETTABLE  R6 R5 K25    ; R6 := R5[1.000000]
 91 [-]: SELF      R6 R6 K26    ; R7 := R6; R6 := R6[0xcb62c32f]
 92 [-]: MOVE      R8 R4        ; R8 := R4
 93 [-]: CALL      R6 3 1       ; R6(R7,R8)
 94 [-]: SELF      R6 R3 K27    ; R7 := R3; R6 := R3[0xf2deaf69]
 95 [-]: GETGLOBAL R8 K28       ; R8 := 0xc703b5d3
 96 [-]: CALL      R6 3 2       ; R6 := R6(R7,R8)
 97 [-]: TEST      R6 0         ; if not R6 then PC := 168
 98 [-]: JMP       168          ; PC := 168
 99 [-]: SELF      R6 R0 K29    ; R7 := R0; R6 := R0[0xde321e6f]
100 [-]: CALL      R6 2 2       ; R6 := R6(R7)
101 [-]: GETGLOBAL R7 K0        ; R7 := 0x7b998233
102 [-]: MOVE      R8 R6        ; R8 := R6
103 [-]: CALL      R7 2 2       ; R7 := R7(R8)
104 [-]: TEST      R7 1         ; if R7 then PC := 161
105 [-]: JMP       161          ; PC := 161
106 [-]: SELF      R7 R6 K30    ; R8 := R6; R7 := R6[0xf7d48ee0]
107 [-]: CALL      R7 2 2       ; R7 := R7(R8)
108 [-]: GETGLOBAL R8 K0        ; R8 := 0x7b998233
109 [-]: MOVE      R9 R7        ; R9 := R7
110 [-]: CALL      R8 2 2       ; R8 := R8(R9)
111 [-]: TEST      R8 1         ; if R8 then PC := 153
112 [-]: JMP       153          ; PC := 153
113 [-]: SELF      R8 R4 K31    ; R9 := R4; R8 := R4[0x62c81b76]
114 [-]: CALL      R8 2 2       ; R8 := R8(R9)
115 [-]: GETGLOBAL R9 K0        ; R9 := 0x7b998233
116 [-]: MOVE      R10 R8       ; R10 := R8
117 [-]: CALL      R9 2 2       ; R9 := R9(R10)
118 [-]: TEST      R9 1         ; if R9 then PC := 149
119 [-]: JMP       149          ; PC := 149
120 [-]: GETTABLE  R9 R8 K32    ; R9 := R8["mKahlCustomization"]
121 [-]: GETGLOBAL R10 K0       ; R10 := 0x7b998233
122 [-]: MOVE      R11 R9       ; R11 := R9
123 [-]: CALL      R10 2 2      ; R10 := R10(R11)
124 [-]: TEST      R10 1        ; if R10 then PC := 145
125 [-]: JMP       145          ; PC := 145
126 [-]: GETGLOBAL R10 K0       ; R10 := 0x7b998233
127 [-]: GETTABLE  R11 R9 K33   ; R11 := R9["mCustomization"]
128 [-]: CALL      R10 2 2      ; R10 := R10(R11)
129 [-]: TEST      R10 1        ; if R10 then PC := 141
130 [-]: JMP       141          ; PC := 141
131 [-]: SELF      R10 R7 K34   ; R11 := R7; R10 := R7[0xaa041663]
132 [-]: GETTABLE  R12 R9 K33   ; R12 := R9["mCustomization"]
133 [-]: CALL      R10 3 1      ; R10(R11,R12)
134 [-]: GETGLOBAL R10 K35      ; R10 := 0x3d106989
135 [-]: LOADK     R11 K36      ; R11 := "LisetAirSupport - applied instigator player's Kahl customizations to "
136 [-]: SELF      R12 R0 K37   ; R13 := R0; R12 := R0[0xe223e2b1]
137 [-]: CALL      R12 2 2      ; R12 := R12(R13)
138 [-]: CONCAT    R11 R11 R12  ; R11 := R11 .. R12
139 [-]: CALL      R10 2 1      ; R10(R11)
140 [-]: JMP       168          ; PC := 168
141 [-]: GETGLOBAL R10 K35      ; R10 := 0x3d106989
142 [-]: LOADK     R11 K38      ; R11 := "LisetAirSupport - ERROR: instigator player's loadout.mKahlCustomization.mCustomization is NULL, cannot apply customizations to Kahl NPC"
143 [-]: CALL      R10 2 1      ; R10(R11)
144 [-]: JMP       168          ; PC := 168
145 [-]: GETGLOBAL R10 K35      ; R10 := 0x3d106989
146 [-]: LOADK     R11 K39      ; R11 := "LisetAirSupport - ERROR: instigator player's loadout.mKahlCustomization is NULL, cannot apply customizations to Kahl NPC"
147 [-]: CALL      R10 2 1      ; R10(R11)
148 [-]: JMP       168          ; PC := 168
149 [-]: GETGLOBAL R10 K35      ; R10 := 0x3d106989
150 [-]: LOADK     R11 K40      ; R11 := "LisetAirSupport - ERROR: instigator player's loadout is NULL, cannot apply customizations to Kahl NPC"
151 [-]: CALL      R10 2 1      ; R10(R11)
152 [-]: JMP       168          ; PC := 168
153 [-]: GETGLOBAL R10 K35      ; R10 := 0x3d106989
154 [-]: LOADK     R11 K41      ; R11 := "LisetAirSupport - ERROR: ally Kahl NPC "
155 [-]: SELF      R12 R0 K37   ; R13 := R0; R12 := R0[0xe223e2b1]
156 [-]: CALL      R12 2 2      ; R12 := R12(R13)
157 [-]: LOADK     R13 K42      ; R13 := " has no active power suit, cannot apply customizations"
158 [-]: CONCAT    R11 R11 R13  ; R11 := R11 .. R12 .. R13
159 [-]: CALL      R10 2 1      ; R10(R11)
160 [-]: JMP       168          ; PC := 168
161 [-]: GETGLOBAL R10 K35      ; R10 := 0x3d106989
162 [-]: LOADK     R11 K41      ; R11 := "LisetAirSupport - ERROR: ally Kahl NPC "
163 [-]: SELF      R12 R0 K37   ; R13 := R0; R12 := R0[0xe223e2b1]
164 [-]: CALL      R12 2 2      ; R12 := R12(R13)
165 [-]: LOADK     R13 K43      ; R13 := " has no inventory, cannot apply customizations"
166 [-]: CONCAT    R11 R11 R13  ; R11 := R11 .. R12 .. R13
167 [-]: CALL      R10 2 1      ; R10(R11)
168 [-]: GETGLOBAL R10 K35      ; R10 := 0x3d106989
169 [-]: LOADK     R11 K44      ; R11 := "LisetAirSupport - ally avatar "
170 [-]: SELF      R12 R0 K37   ; R13 := R0; R12 := R0[0xe223e2b1]
171 [-]: CALL      R12 2 2      ; R12 := R12(R13)
172 [-]: LOADK     R13 K45      ; R13 := " initialized"
173 [-]: CONCAT    R11 R11 R13  ; R11 := R11 .. R12 .. R13
174 [-]: CALL      R10 2 1      ; R10(R11)
175 [-]: RETURN    R0 1         ; return 


; Function #22:
;
; Name:            
; Defined at line: 1031
; #Upvalues:       1
; #Parameters:     2
; Is_vararg:       0
; Max Stack Size:  7

  1 [-]: GETGLOBAL R2 K0        ; R2 := 0x7b998233
  2 [-]: MOVE      R3 R0        ; R3 := R0
  3 [-]: CALL      R2 2 2       ; R2 := R2(R3)
  4 [-]: TEST      R2 1         ; if R2 then PC := 18
  5 [-]: JMP       18           ; PC := 18
  6 [-]: GETGLOBAL R2 K0        ; R2 := 0x7b998233
  7 [-]: MOVE      R3 R1        ; R3 := R1
  8 [-]: CALL      R2 2 2       ; R2 := R2(R3)
  9 [-]: TEST      R2 1         ; if R2 then PC := 18
 10 [-]: JMP       18           ; PC := 18
 11 [-]: SELF      R2 R1 K1     ; R3 := R1; R2 := R1[0xd4f67d6e]
 12 [-]: CALL      R2 2 2       ; R2 := R2(R3)
 13 [-]: GETUPVAL  R3 U0        ; R3 := U0
 14 [-]: MOVE      R4 R0        ; R4 := R0
 15 [-]: MOVE      R5 R2        ; R5 := R2
 16 [-]: LOADKB    R6 1 0       ; R6 := true
 17 [-]: CALL      R3 4 1       ; R3(R4,R5,R6)
 18 [-]: RETURN    R0 1         ; return 


; Function #23:
;
; Name:            
; Defined at line: 1039
; #Upvalues:       0
; #Parameters:     2
; Is_vararg:       0
; Max Stack Size:  12

  1 [-]: CONST     R2 3         ; R2 := 3.000000
  2 [-]: CONST     R3 4         ; R3 := 4.000000
  3 [-]: SELF      R4 R0 K0     ; R5 := R0; R4 := R0[0x022561f1]
  4 [-]: CALL      R4 2 2       ; R4 := R4(R5)
  5 [-]: TEST      R4 0         ; if not R4 then PC := 8
  6 [-]: JMP       8            ; PC := 8
  7 [-]: RETURN    R0 1         ; return 
  8 [-]: GETGLOBAL R4 K1        ; R4 := 0x7b998233
  9 [-]: MOVE      R5 R1        ; R5 := R1
 10 [-]: CALL      R4 2 2       ; R4 := R4(R5)
 11 [-]: TEST      R4 1         ; if R4 then PC := 19
 12 [-]: JMP       19           ; PC := 19
 13 [-]: SELF      R4 R0 K2     ; R5 := R0; R4 := R0[0x25f1413e]
 14 [-]: SELF      R6 R1 K3     ; R7 := R1; R6 := R1[0xd1586535]
 15 [-]: CALL      R6 2 2       ; R6 := R6(R7)
 16 [-]: SELF      R7 R1 K4     ; R8 := R1; R7 := R1[0xcb3851b8]
 17 [-]: CALL      R7 2 0       ; R7,... := R7(R8)
 18 [-]: CALL      R4 0 1       ; R4(R5,...)
 19 [-]: SELF      R4 R0 K5     ; R5 := R0; R4 := R0[0xb2532845]
 20 [-]: GETGLOBAL R6 K6        ; R6 := 0x0469f296
 21 [-]: LOADK     R7 K7        ; R7 := "HackPanel"
 22 [-]: CALL      R6 2 0       ; R6,... := R6(R7)
 23 [-]: CALL      R4 0 1       ; R4(R5,...)
 24 [-]: GETGLOBAL R4 K8        ; R4 := 0xcbd666e1
 25 [-]: LOADK     R5 K9        ; R5 := 0.300000
 26 [-]: CALL      R4 2 1       ; R4(R5)
 27 [-]: GETGLOBAL R4 K1        ; R4 := 0x7b998233
 28 [-]: MOVE      R5 R0        ; R5 := R0
 29 [-]: CALL      R4 2 2       ; R4 := R4(R5)
 30 [-]: TEST      R4 1         ; if R4 then PC := 48
 31 [-]: JMP       48           ; PC := 48
 32 [-]: GETGLOBAL R4 K10       ; R4 := 0xae2294fa
 33 [-]: SELF      R5 R0 K11    ; R6 := R0; R5 := R0[0xa0dd18b6]
 34 [-]: CALL      R5 2 0       ; R5,... := R5(R6)
 35 [-]: CALL      R4 0 2       ; R4 := R4(R5,...)
 36 [-]: LT        0 R2 R4      ; if R2 >= R4 then PC := 48
 37 [-]: JMP       48           ; PC := 48
 38 [-]: GETGLOBAL R4 K8        ; R4 := 0xcbd666e1
 39 [-]: CONST     R5 0         ; R5 := 0.000000
 40 [-]: CALL      R4 2 1       ; R4(R5)
 41 [-]: GETGLOBAL R4 K1        ; R4 := 0x7b998233
 42 [-]: MOVE      R5 R0        ; R5 := R0
 43 [-]: CALL      R4 2 2       ; R4 := R4(R5)
 44 [-]: TEST      R4 0         ; if not R4 then PC := 27
 45 [-]: JMP       27           ; PC := 27
 46 [-]: RETURN    R0 1         ; return 
 47 [-]: JMP       27           ; PC := 27
 48 [-]: GETGLOBAL R4 K1        ; R4 := 0x7b998233
 49 [-]: GETGLOBAL R5 K12       ; R5 := 0x26bddb1a
 50 [-]: CALL      R4 2 2       ; R4 := R4(R5)
 51 [-]: TEST      R4 1         ; if R4 then PC := 80
 52 [-]: JMP       80           ; PC := 80
 53 [-]: GETGLOBAL R4 K1        ; R4 := 0x7b998233
 54 [-]: MOVE      R5 R0        ; R5 := R0
 55 [-]: CALL      R4 2 2       ; R4 := R4(R5)
 56 [-]: TEST      R4 1         ; if R4 then PC := 80
 57 [-]: JMP       80           ; PC := 80
 58 [-]: SELF      R4 R0 K13    ; R5 := R0; R4 := R0[0x2047cfe7]
 59 [-]: CALL      R4 2 2       ; R4 := R4(R5)
 60 [-]: TEST      R4 1         ; if R4 then PC := 80
 61 [-]: JMP       80           ; PC := 80
 62 [-]: GETGLOBAL R4 K14       ; R4 := 0x89326c93
 63 [-]: SELF      R4 R4 K15    ; R5 := R4; R4 := R4[0x05909209]
 64 [-]: GETGLOBAL R6 K12       ; R6 := 0x26bddb1a
 65 [-]: GETGLOBAL R7 K16       ; R7 := ZERO_VECTOR
 66 [-]: GETGLOBAL R8 K17       ; R8 := ZERO_ROTATION
 67 [-]: MOVE      R9 R0        ; R9 := R0
 68 [-]: MOVE      R10 R0       ; R10 := R0
 69 [-]: CALL      R4 7 2       ; R4 := R4(R5,R6,R7,R8,R9,R10)
 70 [-]: GETGLOBAL R5 K1        ; R5 := 0x7b998233
 71 [-]: MOVE      R6 R4        ; R6 := R4
 72 [-]: CALL      R5 2 2       ; R5 := R5(R6)
 73 [-]: TEST      R5 1         ; if R5 then PC := 80
 74 [-]: JMP       80           ; PC := 80
 75 [-]: SELF      R5 R4 K18    ; R6 := R4; R5 := R4[0xb6b094b2]
 76 [-]: MOVE      R7 R0        ; R7 := R0
 77 [-]: GETGLOBAL R8 K6        ; R8 := 0x0469f296
 78 [-]: CALL      R8 1 0       ; R8,... := R8()
 79 [-]: CALL      R5 0 1       ; R5(R6,...)
 80 [-]: SELF      R5 R0 K19    ; R6 := R0; R5 := R0[0xa5403422]
 81 [-]: CALL      R5 2 1       ; R5(R6)
 82 [-]: GETGLOBAL R5 K1        ; R5 := 0x7b998233
 83 [-]: MOVE      R6 R0        ; R6 := R0
 84 [-]: CALL      R5 2 2       ; R5 := R5(R6)
 85 [-]: TEST      R5 1         ; if R5 then PC := 95
 86 [-]: JMP       95           ; PC := 95
 87 [-]: SELF      R5 R0 K0     ; R6 := R0; R5 := R0[0x022561f1]
 88 [-]: CALL      R5 2 2       ; R5 := R5(R6)
 89 [-]: TEST      R5 0         ; if not R5 then PC := 95
 90 [-]: JMP       95           ; PC := 95
 91 [-]: GETGLOBAL R5 K8        ; R5 := 0xcbd666e1
 92 [-]: CONST     R6 0         ; R6 := 0.500000
 93 [-]: CALL      R5 2 1       ; R5(R6)
 94 [-]: JMP       82           ; PC := 82
 95 [-]: GETGLOBAL R5 K8        ; R5 := 0xcbd666e1
 96 [-]: MOVE      R6 R3        ; R6 := R3
 97 [-]: CALL      R5 2 1       ; R5(R6)
 98 [-]: GETGLOBAL R5 K1        ; R5 := 0x7b998233
 99 [-]: GETGLOBAL R6 K20       ; R6 := 0xe8deb214
100 [-]: CALL      R5 2 2       ; R5 := R5(R6)
101 [-]: TEST      R5 1         ; if R5 then PC := 130
102 [-]: JMP       130          ; PC := 130
103 [-]: GETGLOBAL R5 K1        ; R5 := 0x7b998233
104 [-]: MOVE      R6 R0        ; R6 := R0
105 [-]: CALL      R5 2 2       ; R5 := R5(R6)
106 [-]: TEST      R5 1         ; if R5 then PC := 130
107 [-]: JMP       130          ; PC := 130
108 [-]: SELF      R5 R0 K13    ; R6 := R0; R5 := R0[0x2047cfe7]
109 [-]: CALL      R5 2 2       ; R5 := R5(R6)
110 [-]: TEST      R5 1         ; if R5 then PC := 130
111 [-]: JMP       130          ; PC := 130
112 [-]: GETGLOBAL R5 K14       ; R5 := 0x89326c93
113 [-]: SELF      R5 R5 K15    ; R6 := R5; R5 := R5[0x05909209]
114 [-]: GETGLOBAL R7 K20       ; R7 := 0xe8deb214
115 [-]: GETGLOBAL R8 K16       ; R8 := ZERO_VECTOR
116 [-]: GETGLOBAL R9 K17       ; R9 := ZERO_ROTATION
117 [-]: MOVE      R10 R0       ; R10 := R0
118 [-]: MOVE      R11 R0       ; R11 := R0
119 [-]: CALL      R5 7 2       ; R5 := R5(R6,R7,R8,R9,R10,R11)
120 [-]: GETGLOBAL R6 K1        ; R6 := 0x7b998233
121 [-]: MOVE      R7 R5        ; R7 := R5
122 [-]: CALL      R6 2 2       ; R6 := R6(R7)
123 [-]: TEST      R6 1         ; if R6 then PC := 130
124 [-]: JMP       130          ; PC := 130
125 [-]: SELF      R6 R5 K18    ; R7 := R5; R6 := R5[0xb6b094b2]
126 [-]: MOVE      R8 R0        ; R8 := R0
127 [-]: GETGLOBAL R9 K6        ; R9 := 0x0469f296
128 [-]: CALL      R9 1 0       ; R9,... := R9()
129 [-]: CALL      R6 0 1       ; R6(R7,...)
130 [-]: RETURN    R0 1         ; return 


; Function #24:
;
; Name:            
; Defined at line: 1086
; #Upvalues:       11
; #Parameters:     1
; Is_vararg:       0
; Max Stack Size:  80

  1 [-]: NEWTABLE  R2 0 0       ; R2 := {}
  2 [-]: NEWTABLE  R3 0 0       ; R3 := {}
  3 [-]: LOADKB    R4 0 0       ; R4 := false
  4 [-]: CONST     R5 0         ; R5 := 0.000000
  5 [-]: LOADNIL   R6 R6        ; R6 := nil
  6 [-]: LOADKB    R7 0 0       ; R7 := false
  7 [-]: CONST     R8 1         ; R8 := 1.000000
  8 [-]: GETGLOBAL R9 K0        ; R9 := 0x7b998233
  9 [-]: GETGLOBAL R10 K1       ; R10 := 0xbe190284
 10 [-]: CALL      R9 2 2       ; R9 := R9(R10)
 11 [-]: TEST      R9 1         ; if R9 then PC := 17
 12 [-]: JMP       17           ; PC := 17
 13 [-]: GETGLOBAL R9 K1        ; R9 := 0xbe190284
 14 [-]: SELF      R9 R9 K2     ; R10 := R9; R9 := R9[0xef893aec]
 15 [-]: CALL      R9 2 2       ; R9 := R9(R10)
 16 [-]: JMP       19           ; PC := 19
 17 [-]: LOADKB    R9 0 1       ; R9 := false; PC := 18
 18 [-]: LOADKB    R9 1 0       ; R9 := true
 19 [-]: GETGLOBAL R10 K0       ; R10 := 0x7b998233
 20 [-]: MOVE      R11 R9       ; R11 := R9
 21 [-]: CALL      R10 2 2      ; R10 := R10(R11)
 22 [-]: TEST      R10 1        ; if R10 then PC := 66
 23 [-]: JMP       66           ; PC := 66
 24 [-]: GETTABLE  R10 R9 K3    ; R10 := R9["missionType"]
 25 [-]: EQ        1 R10 K5     ; if R10 == 28.000000 then PC := 33
 26 [-]: JMP       33           ; PC := 33
 27 [-]: GETGLOBAL R10 K1       ; R10 := 0xbe190284
 28 [-]: SELF      R10 R10 K6   ; R11 := R10; R10 := R10[0xb2cb9941]
 29 [-]: CALL      R10 2 2      ; R10 := R10(R11)
 30 [-]: MOVE      R7 R10       ; R7 := R10
 31 [-]: JMP       34           ; PC := 34
 32 [-]: LOADKB    R7 0 1       ; R7 := false; PC := 33
 33 [-]: LOADKB    R7 1 0       ; R7 := true
 34 [-]: GETGLOBAL R10 K7       ; R10 := 0x89326c93
 35 [-]: SELF      R10 R10 K8   ; R11 := R10; R10 := R10[0x29ef273d]
 36 [-]: CALL      R10 2 2      ; R10 := R10(R11)
 37 [-]: GETGLOBAL R11 K0       ; R11 := 0x7b998233
 38 [-]: MOVE      R12 R10      ; R12 := R10
 39 [-]: CALL      R11 2 2      ; R11 := R11(R12)
 40 [-]: TEST      R11 1        ; if R11 then PC := 66
 41 [-]: JMP       66           ; PC := 66
 42 [-]: SELF      R11 R10 K9   ; R12 := R10; R11 := R10[0x66905cb0]
 43 [-]: CALL      R11 2 2      ; R11 := R11(R12)
 44 [-]: GETGLOBAL R12 K0       ; R12 := 0x7b998233
 45 [-]: MOVE      R13 R11      ; R13 := R11
 46 [-]: CALL      R12 2 2      ; R12 := R12(R13)
 47 [-]: TEST      R12 1        ; if R12 then PC := 66
 48 [-]: JMP       66           ; PC := 66
 49 [-]: GETGLOBAL R12 K10      ; R12 := 0x5bced4c4
 50 [-]: GETTABLE  R12 R12 K11  ; R12 := R12[0xb62ecfe0]
 51 [-]: CONST     R13 1        ; R13 := 1.000000
 52 [-]: GETGLOBAL R14 K10      ; R14 := 0x5bced4c4
 53 [-]: GETTABLE  R14 R14 K12  ; R14 := R14[0xac1b386a]
 54 [-]: SELF      R15 R11 K13  ; R16 := R11; R15 := R11[0xcea36880]
 55 [-]: CALL      R15 2 2      ; R15 := R15(R16)
 56 [-]: GETTABLE  R16 R9 K14   ; R16 := R9["maxEnemyLevel"]
 57 [-]: GETTABLE  R17 R9 K14   ; R17 := R9["maxEnemyLevel"]
 58 [-]: GETTABLE  R18 R9 K15   ; R18 := R9["minEnemyLevel"]
 59 [-]: SUB       R17 R17 R18  ; R17 := R17 - R18
 60 [-]: MUL       R17 K16 R17  ; R17 := 3.000000 * R17
 61 [-]: ADD       R16 R16 R17  ; R16 := R16 + R17
 62 [-]: CALL      R14 3 2      ; R14 := R14(R15,R16)
 63 [-]: ADD       R14 K16 R14  ; R14 := 3.000000 + R14
 64 [-]: CALL      R12 3 2      ; R12 := R12(R13,R14)
 65 [-]: MOVE      R8 R12       ; R8 := R12
 66 [-]: GETGLOBAL R12 K7       ; R12 := 0x89326c93
 67 [-]: SELF      R12 R12 K17  ; R13 := R12; R12 := R12[0x18d05d30]
 68 [-]: CALL      R12 2 2      ; R12 := R12(R13)
 69 [-]: TEST      R12 0        ; if not R12 then PC := 286
 70 [-]: JMP       286          ; PC := 286
 71 [-]: GETUPVAL  R12 U0       ; R12 := U0
 72 [-]: SELF      R12 R12 K18  ; R13 := R12; R12 := R12[0xd1586535]
 73 [-]: CALL      R12 2 2      ; R12 := R12(R13)
 74 [-]: GETUPVAL  R13 U0       ; R13 := U0
 75 [-]: SELF      R13 R13 K19  ; R14 := R13; R13 := R13[0xcb3851b8]
 76 [-]: CALL      R13 2 2      ; R13 := R13(R14)
 77 [-]: GETUPVAL  R14 U0       ; R14 := U0
 78 [-]: SELF      R14 R14 K20  ; R15 := R14; R14 := R14[0xde321e6f]
 79 [-]: CALL      R14 2 2      ; R14 := R14(R15)
 80 [-]: SELF      R14 R14 K21  ; R15 := R14; R14 := R14[0xf7d48ee0]
 81 [-]: CALL      R14 2 2      ; R14 := R14(R15)
 82 [-]: GETGLOBAL R15 K7       ; R15 := 0x89326c93
 83 [-]: SELF      R15 R15 K22  ; R16 := R15; R15 := R15[0x05909209]
 84 [-]: GETGLOBAL R17 K23      ; R17 := 0xb367793a
 85 [-]: MOVE      R18 R12      ; R18 := R12
 86 [-]: MOVE      R19 R13      ; R19 := R13
 87 [-]: MOVE      R20 R14      ; R20 := R14
 88 [-]: CALL      R15 6 2      ; R15 := R15(R16,R17,R18,R19,R20)
 89 [-]: MOVE      R1 R15       ; R1 := R15
 90 [-]: GETGLOBAL R15 K7       ; R15 := 0x89326c93
 91 [-]: SELF      R15 R15 K24  ; R16 := R15; R15 := R15[0xc7fcada9]
 92 [-]: GETUPVAL  R17 U1       ; R17 := U1
 93 [-]: CALL      R15 3 2      ; R15 := R15(R16,R17)
 94 [-]: GETGLOBAL R16 K0       ; R16 := 0x7b998233
 95 [-]: MOVE      R17 R15      ; R17 := R15
 96 [-]: CALL      R16 2 2      ; R16 := R16(R17)
 97 [-]: TEST      R16 1        ; if R16 then PC := 141
 98 [-]: JMP       141          ; PC := 141
 99 [-]: GETGLOBAL R16 K25      ; R16 := 0xc8802016
100 [-]: MOVE      R17 R15      ; R17 := R15
101 [-]: CALL      R16 2 4      ; R16,R17,R18 := R16(R17)
102 [-]: JMP       139          ; PC := 139
103 [-]: GETGLOBAL R21 K0       ; R21 := 0x7b998233
104 [-]: MOVE      R22 R20      ; R22 := R20
105 [-]: CALL      R21 2 2      ; R21 := R21(R22)
106 [-]: TEST      R21 1        ; if R21 then PC := 139
107 [-]: JMP       139          ; PC := 139
108 [-]: SELF      R21 R20 K26  ; R22 := R20; R21 := R20[0x2047cfe7]
109 [-]: CALL      R21 2 2      ; R21 := R21(R22)
110 [-]: TEST      R21 1        ; if R21 then PC := 139
111 [-]: JMP       139          ; PC := 139
112 [-]: GETGLOBAL R21 K27      ; R21 := 0x33bdd652
113 [-]: GETTABLE  R21 R21 K28  ; R21 := R21[0x23d5322f]
114 [-]: MOVE      R22 R3       ; R22 := R3
115 [-]: MOVE      R23 R20      ; R23 := R20
116 [-]: CALL      R21 3 1      ; R21(R22,R23)
117 [-]: SELF      R21 R20 K29  ; R22 := R20; R21 := R20[0xfa9e477f]
118 [-]: CALL      R21 2 2      ; R21 := R21(R22)
119 [-]: GETGLOBAL R22 K0       ; R22 := 0x7b998233
120 [-]: MOVE      R23 R21      ; R23 := R21
121 [-]: CALL      R22 2 2      ; R22 := R22(R23)
122 [-]: TEST      R22 1        ; if R22 then PC := 131
123 [-]: JMP       131          ; PC := 131
124 [-]: SELF      R22 R21 K30  ; R23 := R21; R22 := R21[0xf2deaf69]
125 [-]: GETGLOBAL R24 K31      ; R24 := 0xc703b5d3
126 [-]: CALL      R22 3 2      ; R22 := R22(R23,R24)
127 [-]: TEST      R22 0        ; if not R22 then PC := 131
128 [-]: JMP       131          ; PC := 131
129 [-]: LOADKB    R4 1 0       ; R4 := true
130 [-]: JMP       139          ; PC := 139
131 [-]: SELF      R22 R20 K32  ; R23 := R20; R22 := R20[0xf1aa5903]
132 [-]: CALL      R22 2 2      ; R22 := R22(R23)
133 [-]: GETUPVAL  R23 U2       ; R23 := U2
134 [-]: SELF      R23 R23 K33  ; R24 := R23; R23 := R23[0x5ca33548]
135 [-]: CALL      R23 2 2      ; R23 := R23(R24)
136 [-]: EQ        0 R22 R23    ; if R22 ~= R23 then PC := 139
137 [-]: JMP       139          ; PC := 139
138 [-]: ADD       R5 R5 K34    ; R5 := R5 + 1.000000
139 [-]: TFORLOOP  R16 2        ; R19,R20 :=  R16(R17,R18); if R19 ~= nil then begin PC = 103; R18 := R19 end
140 [-]: JMP       103          ; PC := 103
141 [-]: GETGLOBAL R22 K35      ; R22 := 0x3d106989
142 [-]: LOADK     R23 K36      ; R23 := "LisetAirSupport - found "
143 [-]: GETGLOBAL R24 K37      ; R24 := 0x64fb1586
144 [-]: LEN       R25 R3       ; R25 := # R3
145 [-]: CALL      R24 2 2      ; R24 := R24(R25)
146 [-]: LOADK     R25 K38      ; R25 := " existing ally avatars to be healed, Kahl is alive: "
147 [-]: GETGLOBAL R26 K37      ; R26 := 0x64fb1586
148 [-]: MOVE      R27 R4       ; R27 := R4
149 [-]: CALL      R26 2 2      ; R26 := R26(R27)
150 [-]: LOADK     R27 K39      ; R27 := ", num of grineer agents spawned by "
151 [-]: GETUPVAL  R28 U2       ; R28 := U2
152 [-]: SELF      R28 R28 K33  ; R29 := R28; R28 := R28[0x5ca33548]
153 [-]: CALL      R28 2 2      ; R28 := R28(R29)
154 [-]: LOADK     R29 K40      ; R29 := ": "
155 [-]: GETGLOBAL R30 K37      ; R30 := 0x64fb1586
156 [-]: MOVE      R31 R5       ; R31 := R5
157 [-]: CALL      R30 2 2      ; R30 := R30(R31)
158 [-]: CONCAT    R23 R23 R30  ; R23 := R23 .. R24 .. R25 .. R26 .. R27 .. R28 .. R29 .. R30
159 [-]: CALL      R22 2 1      ; R22(R23)
160 [-]: CONST     R22 0        ; R22 := 0.000000
161 [-]: LOADKB    R23 0 0      ; R23 := false
162 [-]: GETGLOBAL R24 K41      ; R24 := 0x4ec73e73
163 [-]: MOVE      R25 R3       ; R25 := R3
164 [-]: CALL      R24 2 2      ; R24 := R24(R25)
165 [-]: EQ        1 R24 K42    ; if R24 == nil then PC := 176
166 [-]: JMP       176          ; PC := 176
167 [-]: TEST      R4 1         ; if R4 then PC := 171
168 [-]: JMP       171          ; PC := 171
169 [-]: LOADKB    R23 1 0      ; R23 := true
170 [-]: JMP       194          ; PC := 194
171 [-]: GETGLOBAL R24 K43      ; R24 := 0x18f8e474
172 [-]: LT        0 R5 R24     ; if R5 >= R24 then PC := 194
173 [-]: JMP       194          ; PC := 194
174 [-]: CONST     R22 1        ; R22 := 1.000000
175 [-]: JMP       194          ; PC := 194
176 [-]: GETGLOBAL R24 K44      ; R24 := _T
177 [-]: GETTABLE  R24 R24 K45  ; R24 := R24["SpawningKahlAllies"]
178 [-]: TEST      R24 1        ; if R24 then PC := 185
179 [-]: JMP       185          ; PC := 185
180 [-]: GETGLOBAL R24 K44      ; R24 := _T
181 [-]: SETTABLE  R24 K45 K46  ; R24["SpawningKahlAllies"] := true
182 [-]: LOADKB    R23 1 0      ; R23 := true
183 [-]: GETGLOBAL R22 K47      ; R22 := 0x25b5b0e5
184 [-]: JMP       194          ; PC := 194
185 [-]: CONST     R22 1        ; R22 := 1.000000
186 [-]: GETGLOBAL R24 K35      ; R24 := 0x3d106989
187 [-]: LOADK     R25 K48      ; R25 := "LisetAirSupport - Kahl allies are being spawned by another player, "
188 [-]: GETUPVAL  R26 U2       ; R26 := U2
189 [-]: SELF      R26 R26 K33  ; R27 := R26; R26 := R26[0x5ca33548]
190 [-]: CALL      R26 2 2      ; R26 := R26(R27)
191 [-]: LOADK     R27 K49      ; R27 := " only gets 1 additional ally"
192 [-]: CONCAT    R25 R25 R27  ; R25 := R25 .. R26 .. R27
193 [-]: CALL      R24 2 1      ; R24(R25)
194 [-]: GETGLOBAL R24 K35      ; R24 := 0x3d106989
195 [-]: LOADK     R25 K50      ; R25 := "LisetAirSupport - need to spawn Kahl: "
196 [-]: GETGLOBAL R26 K37      ; R26 := 0x64fb1586
197 [-]: MOVE      R27 R23      ; R27 := R23
198 [-]: CALL      R26 2 2      ; R26 := R26(R27)
199 [-]: LOADK     R27 K51      ; R27 := ", num of new grineer agents needed: "
200 [-]: GETGLOBAL R28 K37      ; R28 := 0x64fb1586
201 [-]: MOVE      R29 R22      ; R29 := R22
202 [-]: CALL      R28 2 2      ; R28 := R28(R29)
203 [-]: CONCAT    R25 R25 R28  ; R25 := R25 .. R26 .. R27 .. R28
204 [-]: CALL      R24 2 1      ; R24(R25)
205 [-]: TEST      R23 1        ; if R23 then PC := 209
206 [-]: JMP       209          ; PC := 209
207 [-]: LT        0 K52 R22    ; if 0.000000 >= R22 then PC := 286
208 [-]: JMP       286          ; PC := 286
209 [-]: NEWTABLE  R24 0 0      ; R24 := {}
210 [-]: TEST      R23 0        ; if not R23 then PC := 227
211 [-]: JMP       227          ; PC := 227
212 [-]: GETGLOBAL R25 K27      ; R25 := 0x33bdd652
213 [-]: GETTABLE  R25 R25 K28  ; R25 := R25[0x23d5322f]
214 [-]: MOVE      R26 R2       ; R26 := R2
215 [-]: NEWTABLE  R27 0 2      ; R27 := {}
216 [-]: GETGLOBAL R28 K31      ; R28 := 0xc703b5d3
217 [-]: SETTABLE  R27 K53 R28  ; R27["allyType"] := R28
218 [-]: SETTABLE  R27 K54 R8   ; R27["agentLevel"] := R8
219 [-]: CALL      R25 3 1      ; R25(R26,R27)
220 [-]: GETGLOBAL R25 K27      ; R25 := 0x33bdd652
221 [-]: GETTABLE  R25 R25 K28  ; R25 := R25[0x23d5322f]
222 [-]: MOVE      R26 R24      ; R26 := R24
223 [-]: GETGLOBAL R27 K31      ; R27 := 0xc703b5d3
224 [-]: SELF      R27 R27 K55  ; R28 := R27; R27 := R27[0xed4e0128]
225 [-]: CALL      R27 2 0      ; R27,... := R27(R28)
226 [-]: CALL      R25 0 1      ; R25(R26,...)
227 [-]: LT        0 K52 R22    ; if 0.000000 >= R22 then PC := 267
228 [-]: JMP       267          ; PC := 267
229 [-]: GETGLOBAL R25 K56      ; R25 := 0x0e59f64c
230 [-]: LEN       R25 R25      ; R25 := # R25
231 [-]: LT        0 K52 R25    ; if 0.000000 >= R25 then PC := 259
232 [-]: JMP       259          ; PC := 259
233 [-]: CONST     R25 1        ; R25 := 1.000000
234 [-]: MOVE      R26 R22      ; R26 := R22
235 [-]: CONST     R27 1        ; R27 := 1.000000
236 [-]: FORPREP   R25 257      ; R25 -= R27; PC := 257
237 [-]: GETGLOBAL R29 K57      ; R29 := 0x55730e1a
238 [-]: CONST     R30 1        ; R30 := 1.000000
239 [-]: GETGLOBAL R31 K56      ; R31 := 0x0e59f64c
240 [-]: LEN       R31 R31      ; R31 := # R31
241 [-]: CALL      R29 3 2      ; R29 := R29(R30,R31)
242 [-]: GETGLOBAL R30 K56      ; R30 := 0x0e59f64c
243 [-]: GETTABLE  R30 R30 R29  ; R30 := R30[R29]
244 [-]: GETGLOBAL R31 K27      ; R31 := 0x33bdd652
245 [-]: GETTABLE  R31 R31 K28  ; R31 := R31[0x23d5322f]
246 [-]: MOVE      R32 R2       ; R32 := R2
247 [-]: NEWTABLE  R33 0 2      ; R33 := {}
248 [-]: SETTABLE  R33 K53 R30  ; R33["allyType"] := R30
249 [-]: SETTABLE  R33 K54 R8   ; R33["agentLevel"] := R8
250 [-]: CALL      R31 3 1      ; R31(R32,R33)
251 [-]: GETGLOBAL R31 K27      ; R31 := 0x33bdd652
252 [-]: GETTABLE  R31 R31 K28  ; R31 := R31[0x23d5322f]
253 [-]: MOVE      R32 R24      ; R32 := R24
254 [-]: SELF      R33 R30 K55  ; R34 := R30; R33 := R30[0xed4e0128]
255 [-]: CALL      R33 2 0      ; R33,... := R33(R34)
256 [-]: CALL      R31 0 1      ; R31(R32,...)
257 [-]: FORLOOP   R25 237      ; R25 += R27; if R25 <= R26 then begin PC := 237; R28 := R25 end
258 [-]: JMP       267          ; PC := 267
259 [-]: GETGLOBAL R31 K35      ; R31 := 0x3d106989
260 [-]: LOADK     R32 K58      ; R32 := "LisetAirSupport - trying to spawn "
261 [-]: GETGLOBAL R33 K37      ; R33 := 0x64fb1586
262 [-]: MOVE      R34 R22      ; R34 := R22
263 [-]: CALL      R33 2 2      ; R33 := R33(R34)
264 [-]: LOADK     R34 K59      ; R34 := " grineer agents but grineerAllyAgentTypes is empty"
265 [-]: CONCAT    R32 R32 R34  ; R32 := R32 .. R33 .. R34
266 [-]: CALL      R31 2 1      ; R31(R32)
267 [-]: TEST      R7 0         ; if not R7 then PC := 276
268 [-]: JMP       276          ; PC := 276
269 [-]: GETGLOBAL R31 K27      ; R31 := 0x33bdd652
270 [-]: GETTABLE  R31 R31 K28  ; R31 := R31[0x23d5322f]
271 [-]: MOVE      R32 R24      ; R32 := R24
272 [-]: GETGLOBAL R33 K60      ; R33 := 0x18230fab
273 [-]: SELF      R33 R33 K55  ; R34 := R33; R33 := R33[0xed4e0128]
274 [-]: CALL      R33 2 0      ; R33,... := R33(R34)
275 [-]: CALL      R31 0 1      ; R31(R32,...)
276 [-]: GETGLOBAL R31 K41      ; R31 := 0x4ec73e73
277 [-]: MOVE      R32 R24      ; R32 := R24
278 [-]: CALL      R31 2 2      ; R31 := R31(R32)
279 [-]: EQ        1 R31 K42    ; if R31 == nil then PC := 286
280 [-]: JMP       286          ; PC := 286
281 [-]: GETGLOBAL R31 K1       ; R31 := 0xbe190284
282 [-]: SELF      R31 R31 K61  ; R32 := R31; R31 := R31[0xf91cabaa]
283 [-]: MOVE      R33 R24      ; R33 := R24
284 [-]: CALL      R31 3 2      ; R31 := R31(R32,R33)
285 [-]: MOVE      R6 R31       ; R6 := R31
286 [-]: GETUPVAL  R31 U3       ; R31 := U3
287 [-]: GETGLOBAL R32 K62      ; R32 := 0x9c6d95f7
288 [-]: CALL      R31 2 1      ; R31(R32)
289 [-]: GETUPVAL  R31 U4       ; R31 := U4
290 [-]: GETGLOBAL R32 K63      ; R32 := 0x28e86f09
291 [-]: CALL      R31 2 1      ; R31(R32)
292 [-]: GETUPVAL  R31 U5       ; R31 := U5
293 [-]: GETGLOBAL R32 K64      ; R32 := 0x0bc85972
294 [-]: CALL      R31 2 1      ; R31(R32)
295 [-]: GETUPVAL  R31 U6       ; R31 := U6
296 [-]: CALL      R31 1 1      ; R31()
297 [-]: GETGLOBAL R31 K7       ; R31 := 0x89326c93
298 [-]: SELF      R31 R31 K17  ; R32 := R31; R31 := R31[0x18d05d30]
299 [-]: CALL      R31 2 2      ; R31 := R31(R32)
300 [-]: TEST      R31 0        ; if not R31 then PC := 761
301 [-]: JMP       761          ; PC := 761
302 [-]: GETGLOBAL R31 K0       ; R31 := 0x7b998233
303 [-]: MOVE      R32 R6       ; R32 := R6
304 [-]: CALL      R31 2 2      ; R31 := R31(R32)
305 [-]: TEST      R31 1        ; if R31 then PC := 311
306 [-]: JMP       311          ; PC := 311
307 [-]: GETGLOBAL R31 K1       ; R31 := 0xbe190284
308 [-]: SELF      R31 R31 K65  ; R32 := R31; R31 := R31[0x0a8591ef]
309 [-]: MOVE      R33 R6       ; R33 := R6
310 [-]: CALL      R31 3 1      ; R31(R32,R33)
311 [-]: LOADKB    R31 0 0      ; R31 := false
312 [-]: GETGLOBAL R32 K25      ; R32 := 0xc8802016
313 [-]: MOVE      R33 R3       ; R33 := R3
314 [-]: CALL      R32 2 4      ; R32,R33,R34 := R32(R33)
315 [-]: JMP       341          ; PC := 341
316 [-]: GETGLOBAL R37 K0       ; R37 := 0x7b998233
317 [-]: MOVE      R38 R36      ; R38 := R36
318 [-]: CALL      R37 2 2      ; R37 := R37(R38)
319 [-]: TEST      R37 1        ; if R37 then PC := 341
320 [-]: JMP       341          ; PC := 341
321 [-]: SELF      R37 R36 K26  ; R38 := R36; R37 := R36[0x2047cfe7]
322 [-]: CALL      R37 2 2      ; R37 := R37(R38)
323 [-]: TEST      R37 1        ; if R37 then PC := 341
324 [-]: JMP       341          ; PC := 341
325 [-]: SELF      R37 R36 K66  ; R38 := R36; R37 := R36[0x014db014]
326 [-]: SELF      R39 R36 K67  ; R40 := R36; R39 := R36[0xb40c191a]
327 [-]: CALL      R39 2 0      ; R39,... := R39(R40)
328 [-]: CALL      R37 0 1      ; R37(R38,...)
329 [-]: SELF      R37 R36 K68  ; R38 := R36; R37 := R36[0x47901f07]
330 [-]: GETGLOBAL R39 K69      ; R39 := 0x35fba2e8
331 [-]: GETGLOBAL R40 K70      ; R40 := EMPTY_SYMBOL
332 [-]: CALL      R37 4 1      ; R37(R38,R39,R40)
333 [-]: LOADKB    R31 1 0      ; R31 := true
334 [-]: GETGLOBAL R37 K35      ; R37 := 0x3d106989
335 [-]: LOADK     R38 K71      ; R38 := "LisetAirSupport - ally avatar "
336 [-]: SELF      R39 R36 K72  ; R40 := R36; R39 := R36[0xe223e2b1]
337 [-]: CALL      R39 2 2      ; R39 := R39(R40)
338 [-]: LOADK     R40 K73      ; R40 := " healed"
339 [-]: CONCAT    R38 R38 R40  ; R38 := R38 .. R39 .. R40
340 [-]: CALL      R37 2 1      ; R37(R38)
341 [-]: TFORLOOP  R32 2        ; R35,R36 :=  R32(R33,R34); if R35 ~= nil then begin PC = 316; R34 := R35 end
342 [-]: JMP       316          ; PC := 316
343 [-]: TEST      R31 1        ; if R31 then PC := 348
344 [-]: JMP       348          ; PC := 348
345 [-]: LEN       R37 R2       ; R37 := # R2
346 [-]: LT        0 K52 R37    ; if 0.000000 >= R37 then PC := 384
347 [-]: JMP       384          ; PC := 384
348 [-]: GETGLOBAL R37 K1       ; R37 := 0xbe190284
349 [-]: SELF      R37 R37 K74  ; R38 := R37; R37 := R37[0x751f061d]
350 [-]: GETUPVAL  R39 U7       ; R39 := U7
351 [-]: GETGLOBAL R40 K75      ; R40 := 0x39484872
352 [-]: CALL      R37 4 1      ; R37(R38,R39,R40)
353 [-]: GETGLOBAL R37 K44      ; R37 := _T
354 [-]: GETTABLE  R37 R37 K76  ; R37 := R37["MonitoringAllyNpcs"]
355 [-]: TEST      R37 0        ; if not R37 then PC := 384
356 [-]: JMP       384          ; PC := 384
357 [-]: GETGLOBAL R37 K7       ; R37 := 0x89326c93
358 [-]: SELF      R37 R37 K77  ; R38 := R37; R37 := R37[0x78298275]
359 [-]: CALL      R37 2 2      ; R37 := R37(R38)
360 [-]: GETGLOBAL R38 K0       ; R38 := 0x7b998233
361 [-]: MOVE      R39 R37      ; R39 := R37
362 [-]: CALL      R38 2 2      ; R38 := R38(R39)
363 [-]: TEST      R38 1        ; if R38 then PC := 384
364 [-]: JMP       384          ; PC := 384
365 [-]: GETGLOBAL R38 K4       ; R38 := 0x6c97a788
366 [-]: GETTABLE  R38 R38 K78  ; R38 := R38[0x608bc054]
367 [-]: CALL      R38 1 2      ; R38 := R38()
368 [-]: SETTABLE  R38 K79 K42  ; R38["instigator"] := nil
369 [-]: GETGLOBAL R39 K7       ; R39 := 0x89326c93
370 [-]: SELF      R39 R39 K80  ; R40 := R39; R39 := R39[0x8b5b1f58]
371 [-]: CALL      R39 2 2      ; R39 := R39(R40)
372 [-]: SETTABLE  R38 K81 R39  ; R38["affected"] := R39
373 [-]: SETTABLE  R38 K82 K83  ; R38["forceSquadPanel"] := false
374 [-]: SETTABLE  R38 K84 K34  ; R38["buffType"] := 1.000000
375 [-]: GETGLOBAL R40 K86      ; R40 := 0x69f3932e
376 [-]: SETTABLE  R38 K85 R40  ; R38["abilityType"] := R40
377 [-]: GETGLOBAL R40 K75      ; R40 := 0x39484872
378 [-]: SETTABLE  R38 K87 R40  ; R38["buffData"] := R40
379 [-]: SELF      R40 R37 K88  ; R41 := R37; R40 := R37[0x37e45fb5]
380 [-]: MOVE      R42 R38      ; R42 := R38
381 [-]: LOADKB    R43 1 0      ; R43 := true
382 [-]: LOADKB    R44 1 0      ; R44 := true
383 [-]: CALL      R40 5 1      ; R40(R41,R42,R43,R44)
384 [-]: LEN       R40 R2       ; R40 := # R2
385 [-]: LT        0 K52 R40    ; if 0.000000 >= R40 then PC := 761
386 [-]: JMP       761          ; PC := 761
387 [-]: GETGLOBAL R40 K7       ; R40 := 0x89326c93
388 [-]: SELF      R40 R40 K8   ; R41 := R40; R40 := R40[0x29ef273d]
389 [-]: CALL      R40 2 2      ; R40 := R40(R41)
390 [-]: GETGLOBAL R41 K0       ; R41 := 0x7b998233
391 [-]: MOVE      R42 R40      ; R42 := R40
392 [-]: CALL      R41 2 2      ; R41 := R41(R42)
393 [-]: TEST      R41 1        ; if R41 then PC := 761
394 [-]: JMP       761          ; PC := 761
395 [-]: GETGLOBAL R41 K0       ; R41 := 0x7b998233
396 [-]: GETUPVAL  R42 U0       ; R42 := U0
397 [-]: CALL      R41 2 2      ; R41 := R41(R42)
398 [-]: TEST      R41 1        ; if R41 then PC := 761
399 [-]: JMP       761          ; PC := 761
400 [-]: GETUPVAL  R41 U0       ; R41 := U0
401 [-]: SELF      R41 R41 K18  ; R42 := R41; R41 := R41[0xd1586535]
402 [-]: CALL      R41 2 2      ; R41 := R41(R42)
403 [-]: GETUPVAL  R42 U0       ; R42 := U0
404 [-]: SELF      R42 R42 K20  ; R43 := R42; R42 := R42[0xde321e6f]
405 [-]: CALL      R42 2 2      ; R42 := R42(R43)
406 [-]: SELF      R42 R42 K89  ; R43 := R42; R42 := R42[0xefd0fde2]
407 [-]: CALL      R42 2 2      ; R42 := R42(R43)
408 [-]: TEST      R7 0         ; if not R7 then PC := 703
409 [-]: JMP       703          ; PC := 703
410 [-]: CONST     R43 50       ; R43 := 50.000000
411 [-]: CONST     R44 0        ; R44 := 0.000000
412 [-]: CONST     R45 12       ; R45 := 12.000000
413 [-]: GETUPVAL  R46 U8       ; R46 := U8
414 [-]: CONST     R47 5        ; R47 := 5.000000
415 [-]: CALL      R46 2 2      ; R46 := R46(R47)
416 [-]: ADD       R46 R41 R46  ; R46 := R41 + R46
417 [-]: SELF      R47 R40 K90  ; R48 := R40; R47 := R40[0x40f8914b]
418 [-]: MOVE      R49 R46      ; R49 := R46
419 [-]: CONST     R50 64       ; R50 := 64.000000
420 [-]: CALL      R47 4 1      ; R47(R48,R49,R50)
421 [-]: SELF      R47 R40 K9   ; R48 := R40; R47 := R40[0x66905cb0]
422 [-]: CALL      R47 2 2      ; R47 := R47(R48)
423 [-]: GETGLOBAL R48 K0       ; R48 := 0x7b998233
424 [-]: MOVE      R49 R47      ; R49 := R47
425 [-]: CALL      R48 2 2      ; R48 := R48(R49)
426 [-]: TEST      R48 1        ; if R48 then PC := 755
427 [-]: JMP       755          ; PC := 755
428 [-]: LOADNIL   R48 R49      ; R48 := R49 := nil
429 [-]: SELF      R50 R47 K91  ; R51 := R47; R50 := R47[0x0bd9b68e]
430 [-]: GETUPVAL  R52 U0       ; R52 := U0
431 [-]: CONST     R53 150      ; R53 := 150.000000
432 [-]: CONST     R54 250      ; R54 := 250.000000
433 [-]: CONST     R55 80       ; R55 := 80.000000
434 [-]: CONST     R56 10000    ; R56 := 10000.000000
435 [-]: MOVE      R57 R43      ; R57 := R43
436 [-]: LOADKB    R58 0 0      ; R58 := false
437 [-]: MOVE      R59 R44      ; R59 := R44
438 [-]: CONST     R60 0        ; R60 := 0.000000
439 [-]: CONST     R61 120      ; R61 := 120.000000
440 [-]: CALL      R50 12 2     ; R50 := R50(R51,R52,R53,R54,R55,R56,R57,R58,R59,R60,R61)
441 [-]: LOADNIL   R51 R52      ; R51 := R52 := nil
442 [-]: LEN       R53 R50      ; R53 := # R50
443 [-]: LT        0 K52 R53    ; if 0.000000 >= R53 then PC := 470
444 [-]: JMP       470          ; PC := 470
445 [-]: GETGLOBAL R53 K57      ; R53 := 0x55730e1a
446 [-]: CONST     R54 1        ; R54 := 1.000000
447 [-]: LEN       R55 R50      ; R55 := # R50
448 [-]: CALL      R53 3 2      ; R53 := R53(R54,R55)
449 [-]: GETTABLE  R51 R50 R53  ; R51 := R50[R53]
450 [-]: GETTABLE  R53 R51 K92  ; R53 := R51["y"]
451 [-]: GETTABLE  R54 R46 K92  ; R54 := R46["y"]
452 [-]: LT        0 R53 R54    ; if R53 >= R54 then PC := 457
453 [-]: JMP       457          ; PC := 457
454 [-]: GETTABLE  R53 R46 K92  ; R53 := R46["y"]
455 [-]: ADD       R53 R53 R43  ; R53 := R53 + R43
456 [-]: SETTABLE  R51 K92 R53  ; R51["y"] := R53
457 [-]: GETGLOBAL R53 K57      ; R53 := 0x55730e1a
458 [-]: CONST     R54 1        ; R54 := 1.000000
459 [-]: LEN       R55 R50      ; R55 := # R50
460 [-]: CALL      R53 3 2      ; R53 := R53(R54,R55)
461 [-]: GETTABLE  R52 R50 R53  ; R52 := R50[R53]
462 [-]: GETTABLE  R53 R52 K92  ; R53 := R52["y"]
463 [-]: GETTABLE  R54 R46 K92  ; R54 := R46["y"]
464 [-]: LT        0 R53 R54    ; if R53 >= R54 then PC := 494
465 [-]: JMP       494          ; PC := 494
466 [-]: GETTABLE  R53 R46 K92  ; R53 := R46["y"]
467 [-]: ADD       R53 R53 R43  ; R53 := R53 + R43
468 [-]: SETTABLE  R52 K92 R53  ; R52["y"] := R53
469 [-]: JMP       494          ; PC := 494
470 [-]: GETGLOBAL R53 K93      ; R53 := 0xa421af95
471 [-]: GETGLOBAL R54 K57      ; R54 := 0x55730e1a
472 [-]: CONST     R55 -50      ; R55 := -50.000000
473 [-]: CONST     R56 50       ; R56 := 50.000000
474 [-]: CALL      R54 3 2      ; R54 := R54(R55,R56)
475 [-]: MOVE      R55 R43      ; R55 := R43
476 [-]: GETGLOBAL R56 K57      ; R56 := 0x55730e1a
477 [-]: CONST     R57 -50      ; R57 := -50.000000
478 [-]: CONST     R58 50       ; R58 := 50.000000
479 [-]: CALL      R56 3 0      ; R56,... := R56(R57,R58)
480 [-]: CALL      R53 0 2      ; R53 := R53(R54,...)
481 [-]: ADD       R51 R46 R53  ; R51 := R46 + R53
482 [-]: GETGLOBAL R53 K93      ; R53 := 0xa421af95
483 [-]: GETGLOBAL R54 K57      ; R54 := 0x55730e1a
484 [-]: CONST     R55 -50      ; R55 := -50.000000
485 [-]: CONST     R56 50       ; R56 := 50.000000
486 [-]: CALL      R54 3 2      ; R54 := R54(R55,R56)
487 [-]: MOVE      R55 R43      ; R55 := R43
488 [-]: GETGLOBAL R56 K57      ; R56 := 0x55730e1a
489 [-]: CONST     R57 -50      ; R57 := -50.000000
490 [-]: CONST     R58 50       ; R58 := 50.000000
491 [-]: CALL      R56 3 0      ; R56,... := R56(R57,R58)
492 [-]: CALL      R53 0 2      ; R53 := R53(R54,...)
493 [-]: ADD       R52 R46 R53  ; R52 := R46 + R53
494 [-]: SUB       R53 R46 R51  ; R53 := R46 - R51
495 [-]: GETGLOBAL R54 K94      ; R54 := 0xc2892f65
496 [-]: MOVE      R55 R53      ; R55 := R53
497 [-]: CALL      R54 2 1      ; R54(R55)
498 [-]: GETGLOBAL R54 K10      ; R54 := 0x5bced4c4
499 [-]: GETTABLE  R54 R54 K95  ; R54 := R54[0xbf79b942]
500 [-]: GETGLOBAL R55 K10      ; R55 := 0x5bced4c4
501 [-]: GETTABLE  R55 R55 K96  ; R55 := R55[0x450c9504]
502 [-]: GETGLOBAL R56 K97      ; R56 := 0x42dcc9f5
503 [-]: GETTABLE  R57 R53 K98  ; R57 := R53["z"]
504 [-]: CONST     R58 -1       ; R58 := -1.000000
505 [-]: CONST     R59 1        ; R59 := 1.000000
506 [-]: CALL      R56 4 0      ; R56,... := R56(R57,R58,R59)
507 [-]: CALL      R55 0 0      ; R55,... := R55(R56,...)
508 [-]: CALL      R54 0 2      ; R54 := R54(R55,...)
509 [-]: GETUPVAL  R55 U9       ; R55 := U9
510 [-]: GETTABLE  R55 R55 K99  ; R55 := R55[0x06d055f9]
511 [-]: GETTABLE  R56 R53 K100 ; R56 := R53["x"]
512 [-]: LE        1 K52 R56    ; if 0.000000 <= R56 then PC := 515
513 [-]: JMP       515          ; PC := 515
514 [-]: LOADKB    R56 0 1      ; R56 := false; PC := 515
515 [-]: LOADKB    R56 1 0      ; R56 := true
516 [-]: CONST     R57 1        ; R57 := 1.000000
517 [-]: CONST     R58 -1       ; R58 := -1.000000
518 [-]: CALL      R55 4 2      ; R55 := R55(R56,R57,R58)
519 [-]: MUL       R54 R54 R55  ; R54 := R54 * R55
520 [-]: GETGLOBAL R55 K101     ; R55 := 0x00046924
521 [-]: MOVE      R56 R54      ; R56 := R54
522 [-]: CONST     R57 0        ; R57 := 0.000000
523 [-]: CONST     R58 0        ; R58 := 0.000000
524 [-]: CALL      R55 4 2      ; R55 := R55(R56,R57,R58)
525 [-]: GETGLOBAL R56 K7       ; R56 := 0x89326c93
526 [-]: SELF      R56 R56 K22  ; R57 := R56; R56 := R56[0x05909209]
527 [-]: GETGLOBAL R58 K102     ; R58 := 0x919dc4a0
528 [-]: MOVE      R59 R51      ; R59 := R51
529 [-]: MOVE      R60 R55      ; R60 := R55
530 [-]: CALL      R56 5 2      ; R56 := R56(R57,R58,R59,R60)
531 [-]: MOVE      R48 R56      ; R48 := R56
532 [-]: GETGLOBAL R56 K7       ; R56 := 0x89326c93
533 [-]: SELF      R56 R56 K22  ; R57 := R56; R56 := R56[0x05909209]
534 [-]: GETGLOBAL R58 K102     ; R58 := 0x919dc4a0
535 [-]: MOVE      R59 R52      ; R59 := R52
536 [-]: GETGLOBAL R60 K103     ; R60 := ZERO_ROTATION
537 [-]: CALL      R56 5 2      ; R56 := R56(R57,R58,R59,R60)
538 [-]: MOVE      R49 R56      ; R49 := R56
539 [-]: SELF      R56 R47 K104 ; R57 := R47; R56 := R47[0x33fc842f]
540 [-]: GETGLOBAL R58 K105     ; R58 := 0x88efc25e
541 [-]: GETGLOBAL R59 K60      ; R59 := 0x18230fab
542 [-]: CALL      R58 2 2      ; R58 := R58(R59)
543 [-]: MOVE      R59 R48      ; R59 := R48
544 [-]: GETGLOBAL R60 K106     ; R60 := 0x0469f296
545 [-]: LOADK     R61 K107     ; R61 := "TENNO"
546 [-]: CALL      R60 2 2      ; R60 := R60(R61)
547 [-]: MOVE      R61 R8       ; R61 := R8
548 [-]: LOADNIL   R62 R62      ; R62 := nil
549 [-]: CONST     R63 0        ; R63 := 0.000000
550 [-]: CALL      R56 8 2      ; R56 := R56(R57,R58,R59,R60,R61,R62,R63)
551 [-]: GETGLOBAL R57 K0       ; R57 := 0x7b998233
552 [-]: MOVE      R58 R56      ; R58 := R56
553 [-]: CALL      R57 2 2      ; R57 := R57(R58)
554 [-]: TEST      R57 1        ; if R57 then PC := 685
555 [-]: JMP       685          ; PC := 685
556 [-]: GETGLOBAL R57 K0       ; R57 := 0x7b998233
557 [-]: SELF      R58 R56 K109 ; R59 := R56; R58 := R56[0xbb610e5b]
558 [-]: CALL      R58 2 0      ; R58,... := R58(R59)
559 [-]: CALL      R57 0 2      ; R57 := R57(R58,...)
560 [-]: TEST      R57 1        ; if R57 then PC := 685
561 [-]: JMP       685          ; PC := 685
562 [-]: SELF      R57 R56 K109 ; R58 := R56; R57 := R56[0xbb610e5b]
563 [-]: CALL      R57 2 2      ; R57 := R57(R58)
564 [-]: SELF      R58 R57 K110 ; R59 := R57; R58 := R57[0xc40eed62]
565 [-]: GETUPVAL  R60 U0       ; R60 := U0
566 [-]: CALL      R58 3 1      ; R58(R59,R60)
567 [-]: GETUPVAL  R58 U0       ; R58 := U0
568 [-]: SELF      R58 R58 K111 ; R59 := R58; R58 := R58[0xf80fae85]
569 [-]: CALL      R58 2 2      ; R58 := R58(R59)
570 [-]: TEST      R58 0        ; if not R58 then PC := 575
571 [-]: JMP       575          ; PC := 575
572 [-]: SELF      R58 R56 K112 ; R59 := R56; R58 := R56[0xa7a16361]
573 [-]: LOADKB    R60 0 0      ; R60 := false
574 [-]: CALL      R58 3 1      ; R58(R59,R60)
575 [-]: SELF      R58 R57 K113 ; R59 := R57; R58 := R57[0x73f009e5]
576 [-]: LOADKB    R60 1 0      ; R60 := true
577 [-]: CALL      R58 3 1      ; R58(R59,R60)
578 [-]: GETGLOBAL R58 K25      ; R58 := 0xc8802016
579 [-]: MOVE      R59 R2       ; R59 := R2
580 [-]: CALL      R58 2 4      ; R58,R59,R60 := R58(R59)
581 [-]: JMP       587          ; PC := 587
582 [-]: SELF      R63 R57 K114 ; R64 := R57; R63 := R57[0xb45afc36]
583 [-]: GETGLOBAL R65 K105     ; R65 := 0x88efc25e
584 [-]: GETTABLE  R66 R62 K53  ; R66 := R62["allyType"]
585 [-]: CALL      R65 2 0      ; R65,... := R65(R66)
586 [-]: CALL      R63 0 1      ; R63(R64,...)
587 [-]: TFORLOOP  R58 2        ; R61,R62 :=  R58(R59,R60); if R61 ~= nil then begin PC = 582; R60 := R61 end
588 [-]: JMP       582          ; PC := 582
589 [-]: SELF      R63 R57 K115 ; R64 := R57; R63 := R57[0xe68fe9b4]
590 [-]: LEN       R65 R2       ; R65 := # R2
591 [-]: CALL      R63 3 1      ; R63(R64,R65)
592 [-]: GETGLOBAL R63 K35      ; R63 := 0x3d106989
593 [-]: LOADK     R64 K116     ; R64 := "LisetAirSupport - dropship created, entrance pos: "
594 [-]: GETGLOBAL R65 K37      ; R65 := 0x64fb1586
595 [-]: MOVE      R66 R51      ; R66 := R51
596 [-]: CALL      R65 2 2      ; R65 := R65(R66)
597 [-]: LOADK     R66 K117     ; R66 := ", drop pos: "
598 [-]: GETGLOBAL R67 K37      ; R67 := 0x64fb1586
599 [-]: MOVE      R68 R46      ; R68 := R46
600 [-]: CALL      R67 2 2      ; R67 := R67(R68)
601 [-]: LOADK     R68 K118     ; R68 := ", exit pos: "
602 [-]: GETGLOBAL R69 K37      ; R69 := 0x64fb1586
603 [-]: MOVE      R70 R52      ; R70 := R52
604 [-]: CALL      R69 2 2      ; R69 := R69(R70)
605 [-]: CONCAT    R64 R64 R69  ; R64 := R64 .. R65 .. R66 .. R67 .. R68 .. R69
606 [-]: CALL      R63 2 1      ; R63(R64)
607 [-]: SELF      R63 R56 K119 ; R64 := R56; R63 := R56[0x81b5632f]
608 [-]: GETGLOBAL R65 K106     ; R65 := 0x0469f296
609 [-]: LOADK     R66 K120     ; R66 := "DropshipLeave"
610 [-]: CALL      R65 2 2      ; R65 := R65(R66)
611 [-]: MOVE      R66 R49      ; R66 := R49
612 [-]: MOVE      R67 R45      ; R67 := R45
613 [-]: CALL      R63 5 1      ; R63(R64,R65,R66,R67)
614 [-]: SELF      R63 R56 K121 ; R64 := R56; R63 := R56[0x9a9b0aec]
615 [-]: GETGLOBAL R65 K106     ; R65 := 0x0469f296
616 [-]: LOADK     R66 K122     ; R66 := "DropshipDrop"
617 [-]: CALL      R65 2 2      ; R65 := R65(R66)
618 [-]: MOVE      R66 R46      ; R66 := R46
619 [-]: MOVE      R67 R45      ; R67 := R45
620 [-]: CALL      R63 5 1      ; R63(R64,R65,R66,R67)
621 [-]: GETGLOBAL R63 K35      ; R63 := 0x3d106989
622 [-]: LOADK     R64 K123     ; R64 := "LisetAirSupport - waiting for dropship to deply allies"
623 [-]: CALL      R63 2 1      ; R63(R64)
624 [-]: GETGLOBAL R63 K0       ; R63 := 0x7b998233
625 [-]: MOVE      R64 R57      ; R64 := R57
626 [-]: CALL      R63 2 2      ; R63 := R63(R64)
627 [-]: TEST      R63 1        ; if R63 then PC := 637
628 [-]: JMP       637          ; PC := 637
629 [-]: SELF      R63 R57 K124 ; R64 := R57; R63 := R57[0x34cbb5b6]
630 [-]: CALL      R63 2 2      ; R63 := R63(R64)
631 [-]: TEST      R63 0        ; if not R63 then PC := 639
632 [-]: JMP       639          ; PC := 639
633 [-]: SELF      R63 R57 K125 ; R64 := R57; R63 := R57[0x022561f1]
634 [-]: CALL      R63 2 2      ; R63 := R63(R64)
635 [-]: NOT       R63 R63      ; R63 :=  R63
636 [-]: JMP       639          ; PC := 639
637 [-]: LOADKB    R63 0 1      ; R63 := false; PC := 638
638 [-]: LOADKB    R63 1 0      ; R63 := true
639 [-]: TEST      R63 1        ; if R63 then PC := 669
640 [-]: JMP       669          ; PC := 669
641 [-]: GETGLOBAL R64 K126     ; R64 := 0xcbd666e1
642 [-]: CONST     R65 1        ; R65 := 1.000000
643 [-]: CALL      R64 2 1      ; R64(R65)
644 [-]: GETGLOBAL R64 K0       ; R64 := 0x7b998233
645 [-]: MOVE      R65 R56      ; R65 := R56
646 [-]: CALL      R64 2 2      ; R64 := R64(R65)
647 [-]: TEST      R64 1        ; if R64 then PC := 659
648 [-]: JMP       659          ; PC := 659
649 [-]: GETGLOBAL R64 K0       ; R64 := 0x7b998233
650 [-]: MOVE      R65 R57      ; R65 := R57
651 [-]: CALL      R64 2 2      ; R64 := R64(R65)
652 [-]: TEST      R64 1        ; if R64 then PC := 659
653 [-]: JMP       659          ; PC := 659
654 [-]: GETGLOBAL R64 K0       ; R64 := 0x7b998233
655 [-]: GETUPVAL  R65 U0       ; R65 := U0
656 [-]: CALL      R64 2 2      ; R64 := R64(R65)
657 [-]: TEST      R64 0        ; if not R64 then PC := 661
658 [-]: JMP       661          ; PC := 661
659 [-]: LOADKB    R63 1 0      ; R63 := true
660 [-]: JMP       639          ; PC := 639
661 [-]: SELF      R64 R57 K124 ; R65 := R57; R64 := R57[0x34cbb5b6]
662 [-]: CALL      R64 2 2      ; R64 := R64(R65)
663 [-]: TESTSET   R63 R64 0    ; if not R64 then PC := 668 else R63 := R64
664 [-]: JMP       668          ; PC := 668
665 [-]: SELF      R64 R57 K125 ; R65 := R57; R64 := R57[0x022561f1]
666 [-]: CALL      R64 2 2      ; R64 := R64(R65)
667 [-]: NOT       R63 R64      ; R63 :=  R64
668 [-]: JMP       639          ; PC := 639
669 [-]: GETGLOBAL R64 K35      ; R64 := 0x3d106989
670 [-]: LOADK     R65 K127     ; R65 := "LisetAirSupport - dropship finished deploying agents, waiting for dropship to be destroyed"
671 [-]: CALL      R64 2 1      ; R64(R65)
672 [-]: GETGLOBAL R64 K0       ; R64 := 0x7b998233
673 [-]: MOVE      R65 R56      ; R65 := R56
674 [-]: CALL      R64 2 2      ; R64 := R64(R65)
675 [-]: TEST      R64 1        ; if R64 then PC := 681
676 [-]: JMP       681          ; PC := 681
677 [-]: GETGLOBAL R64 K126     ; R64 := 0xcbd666e1
678 [-]: CONST     R65 1        ; R65 := 1.000000
679 [-]: CALL      R64 2 1      ; R64(R65)
680 [-]: JMP       672          ; PC := 672
681 [-]: GETGLOBAL R64 K35      ; R64 := 0x3d106989
682 [-]: LOADK     R65 K128     ; R65 := "LisetAirSupport - dropship destroyed"
683 [-]: CALL      R64 2 1      ; R64(R65)
684 [-]: JMP       688          ; PC := 688
685 [-]: GETGLOBAL R64 K35      ; R64 := 0x3d106989
686 [-]: LOADK     R65 K129     ; R65 := "LisetAirSupport - spawning Kahl's dropship failed!"
687 [-]: CALL      R64 2 1      ; R64(R65)
688 [-]: GETGLOBAL R64 K0       ; R64 := 0x7b998233
689 [-]: MOVE      R65 R48      ; R65 := R48
690 [-]: CALL      R64 2 2      ; R64 := R64(R65)
691 [-]: TEST      R64 1        ; if R64 then PC := 695
692 [-]: JMP       695          ; PC := 695
693 [-]: SELF      R64 R48 K130 ; R65 := R48; R64 := R48[0xa2880940]
694 [-]: CALL      R64 2 1      ; R64(R65)
695 [-]: GETGLOBAL R64 K0       ; R64 := 0x7b998233
696 [-]: MOVE      R65 R49      ; R65 := R49
697 [-]: CALL      R64 2 2      ; R64 := R64(R65)
698 [-]: TEST      R64 1        ; if R64 then PC := 755
699 [-]: JMP       755          ; PC := 755
700 [-]: SELF      R64 R49 K130 ; R65 := R49; R64 := R49[0xa2880940]
701 [-]: CALL      R64 2 1      ; R64(R65)
702 [-]: JMP       755          ; PC := 755
703 [-]: GETGLOBAL R64 K25      ; R64 := 0xc8802016
704 [-]: MOVE      R65 R2       ; R65 := R2
705 [-]: CALL      R64 2 4      ; R64,R65,R66 := R64(R65)
706 [-]: JMP       753          ; PC := 753
707 [-]: GETUPVAL  R69 U8       ; R69 := U8
708 [-]: CONST     R70 5        ; R70 := 5.000000
709 [-]: CALL      R69 2 2      ; R69 := R69(R70)
710 [-]: ADD       R69 R42 R69  ; R69 := R42 + R69
711 [-]: SELF      R70 R40 K90  ; R71 := R40; R70 := R40[0x40f8914b]
712 [-]: MOVE      R72 R69      ; R72 := R69
713 [-]: CONST     R73 64       ; R73 := 64.000000
714 [-]: CALL      R70 4 1      ; R70(R71,R72,R73)
715 [-]: GETGLOBAL R70 K131     ; R70 := 0x20b7f774
716 [-]: MOVE      R71 R69      ; R71 := R69
717 [-]: MOVE      R72 R41      ; R72 := R41
718 [-]: CALL      R70 3 2      ; R70 := R70(R71,R72)
719 [-]: SETTABLE  R70 K132 K52 ; R70["pitch"] := 0.000000
720 [-]: SELF      R71 R40 K133 ; R72 := R40; R71 := R40[0x6cd833c5]
721 [-]: GETGLOBAL R73 K105     ; R73 := 0x88efc25e
722 [-]: GETTABLE  R74 R68 K53  ; R74 := R68["allyType"]
723 [-]: CALL      R73 2 2      ; R73 := R73(R74)
724 [-]: MOVE      R74 R69      ; R74 := R69
725 [-]: MOVE      R75 R70      ; R75 := R70
726 [-]: GETGLOBAL R76 K106     ; R76 := 0x0469f296
727 [-]: LOADK     R77 K107     ; R77 := "TENNO"
728 [-]: CALL      R76 2 2      ; R76 := R76(R77)
729 [-]: GETTABLE  R77 R68 K54  ; R77 := R68["agentLevel"]
730 [-]: LOADKB    R78 1 0      ; R78 := true
731 [-]: CONST     R79 0        ; R79 := 0.000000
732 [-]: CALL      R71 9 2      ; R71 := R71(R72,R73,R74,R75,R76,R77,R78,R79)
733 [-]: GETGLOBAL R72 K0       ; R72 := 0x7b998233
734 [-]: MOVE      R73 R71      ; R73 := R71
735 [-]: CALL      R72 2 2      ; R72 := R72(R73)
736 [-]: TEST      R72 1        ; if R72 then PC := 745
737 [-]: JMP       745          ; PC := 745
738 [-]: GETUPVAL  R72 U10      ; R72 := U10
739 [-]: SELF      R73 R71 K109 ; R74 := R71; R73 := R71[0xbb610e5b]
740 [-]: CALL      R73 2 2      ; R73 := R73(R74)
741 [-]: GETUPVAL  R74 U0       ; R74 := U0
742 [-]: LOADKB    R75 0 0      ; R75 := false
743 [-]: CALL      R72 4 1      ; R72(R73,R74,R75)
744 [-]: JMP       753          ; PC := 753
745 [-]: GETGLOBAL R72 K35      ; R72 := 0x3d106989
746 [-]: LOADK     R73 K134     ; R73 := "LisetAirSupport - spawning an ally agent of type "
747 [-]: GETTABLE  R74 R68 K53  ; R74 := R68["allyType"]
748 [-]: SELF      R74 R74 K55  ; R75 := R74; R74 := R74[0xed4e0128]
749 [-]: CALL      R74 2 2      ; R74 := R74(R75)
750 [-]: LOADK     R75 K135     ; R75 := " failed"
751 [-]: CONCAT    R73 R73 R75  ; R73 := R73 .. R74 .. R75
752 [-]: CALL      R72 2 1      ; R72(R73)
753 [-]: TFORLOOP  R64 2        ; R67,R68 :=  R64(R65,R66); if R67 ~= nil then begin PC = 707; R66 := R67 end
754 [-]: JMP       707          ; PC := 707
755 [-]: GETGLOBAL R72 K44      ; R72 := _T
756 [-]: GETTABLE  R72 R72 K45  ; R72 := R72["SpawningKahlAllies"]
757 [-]: TEST      R72 0        ; if not R72 then PC := 761
758 [-]: JMP       761          ; PC := 761
759 [-]: GETGLOBAL R72 K44      ; R72 := _T
760 [-]: SETTABLE  R72 K45 K42  ; R72["SpawningKahlAllies"] := nil
761 [-]: GETGLOBAL R72 K7       ; R72 := 0x89326c93
762 [-]: SELF      R72 R72 K136 ; R73 := R72; R72 := R72[0x59c96e77]
763 [-]: MOVE      R74 R1       ; R74 := R1
764 [-]: CALL      R72 3 1      ; R72(R73,R74)
765 [-]: SELF      R72 R0 K137  ; R73 := R0; R72 := R0[0xcc2fcc95]
766 [-]: LOADKB    R74 0 0      ; R74 := false
767 [-]: CALL      R72 3 1      ; R72(R73,R74)
768 [-]: RETURN    R0 1         ; return 


; Function #25:
;
; Name:            
; Defined at line: 1358
; #Upvalues:       0
; #Parameters:     0
; Is_vararg:       0
; Max Stack Size:  14

  1 [-]: GETGLOBAL R0 K0        ; R0 := 0x89326c93
  2 [-]: SELF      R0 R0 K1     ; R1 := R0; R0 := R0[0x7d108ddb]
  3 [-]: CALL      R0 2 2       ; R0 := R0(R1)
  4 [-]: GETGLOBAL R1 K0        ; R1 := 0x89326c93
  5 [-]: SELF      R1 R1 K2     ; R2 := R1; R1 := R1[0xfb669000]
  6 [-]: GETGLOBAL R3 K3        ; R3 := 0x95ff26b1
  7 [-]: CALL      R1 3 2       ; R1 := R1(R2,R3)
  8 [-]: CONST     R2 1         ; R2 := 1.000000
  9 [-]: LEN       R3 R1        ; R3 := # R1
 10 [-]: CONST     R4 1         ; R4 := 1.000000
 11 [-]: FORPREP   R2 44        ; R2 -= R4; PC := 44
 12 [-]: LOADKB    R6 0 0       ; R6 := false
 13 [-]: CONST     R7 1         ; R7 := 1.000000
 14 [-]: LEN       R8 R0        ; R8 := # R0
 15 [-]: CONST     R9 1         ; R9 := 1.000000
 16 [-]: FORPREP   R7 37        ; R7 -= R9; PC := 37
 17 [-]: GETGLOBAL R11 K4       ; R11 := 0x7b998233
 18 [-]: GETTABLE  R12 R1 R5    ; R12 := R1[R5]
 19 [-]: CALL      R11 2 2      ; R11 := R11(R12)
 20 [-]: TEST      R11 1        ; if R11 then PC := 37
 21 [-]: JMP       37           ; PC := 37
 22 [-]: GETGLOBAL R11 K4       ; R11 := 0x7b998233
 23 [-]: GETTABLE  R12 R0 R10   ; R12 := R0[R10]
 24 [-]: CALL      R11 2 2      ; R11 := R11(R12)
 25 [-]: TEST      R11 1        ; if R11 then PC := 37
 26 [-]: JMP       37           ; PC := 37
 27 [-]: GETTABLE  R11 R1 R5    ; R11 := R1[R5]
 28 [-]: SELF      R11 R11 K5   ; R12 := R11; R11 := R11[0xf1aa5903]
 29 [-]: CALL      R11 2 2      ; R11 := R11(R12)
 30 [-]: GETTABLE  R12 R0 R10   ; R12 := R0[R10]
 31 [-]: SELF      R12 R12 K6   ; R13 := R12; R12 := R12[0x5ca33548]
 32 [-]: CALL      R12 2 2      ; R12 := R12(R13)
 33 [-]: EQ        0 R11 R12    ; if R11 ~= R12 then PC := 37
 34 [-]: JMP       37           ; PC := 37
 35 [-]: LOADKB    R6 1 0       ; R6 := true
 36 [-]: JMP       38           ; PC := 38
 37 [-]: FORLOOP   R7 17        ; R7 += R9; if R7 <= R8 then begin PC := 17; R10 := R7 end
 38 [-]: TEST      R6 1         ; if R6 then PC := 44
 39 [-]: JMP       44           ; PC := 44
 40 [-]: GETGLOBAL R11 K0       ; R11 := 0x89326c93
 41 [-]: SELF      R11 R11 K7   ; R12 := R11; R11 := R11[0x59c96e77]
 42 [-]: GETTABLE  R13 R1 R5    ; R13 := R1[R5]
 43 [-]: CALL      R11 3 1      ; R11(R12,R13)
 44 [-]: FORLOOP   R2 12        ; R2 += R4; if R2 <= R3 then begin PC := 12; R5 := R2 end
 45 [-]: RETURN    R0 1         ; return 


; Function #26:
;
; Name:            
; Defined at line: 1377
; #Upvalues:       11
; #Parameters:     2
; Is_vararg:       0
; Max Stack Size:  10

  1 [-]: GETUPVAL  R2 U0        ; R2 := U0
  2 [-]: MOVE      R3 R0        ; R3 := R0
  3 [-]: CALL      R2 2 1       ; R2(R3)
  4 [-]: GETUPVAL  R2 U1        ; R2 := U1
  5 [-]: SELF      R3 R2 K0     ; R4 := R2; R3 := R2[0x5b89142c]
  6 [-]: CALL      R3 2 2       ; R3 := R3(R4)
  7 [-]: GETUPVAL  R4 U1        ; R4 := U1
  8 [-]: SELF      R4 R4 K1     ; R5 := R4; R4 := R4[0xf2deaf69]
  9 [-]: GETGLOBAL R6 K2        ; R6 := gLotusOperatorAvatarType
 10 [-]: CALL      R4 3 2       ; R4 := R4(R5,R6)
 11 [-]: TEST      R4 0         ; if not R4 then PC := 21
 12 [-]: JMP       21           ; PC := 21
 13 [-]: GETGLOBAL R4 K3        ; R4 := 0x7b998233
 14 [-]: MOVE      R5 R3        ; R5 := R3
 15 [-]: CALL      R4 2 2       ; R4 := R4(R5)
 16 [-]: TEST      R4 1         ; if R4 then PC := 21
 17 [-]: JMP       21           ; PC := 21
 18 [-]: SELF      R4 R3 K4     ; R5 := R3; R4 := R3[0xa534c3ac]
 19 [-]: CALL      R4 2 2       ; R4 := R4(R5)
 20 [-]: MOVE      R2 R4        ; R2 := R4
 21 [-]: SELF      R4 R2 K5     ; R5 := R2; R4 := R2[0xde321e6f]
 22 [-]: CALL      R4 2 2       ; R4 := R4(R5)
 23 [-]: SELF      R4 R4 K6     ; R5 := R4; R4 := R4[0x96a422be]
 24 [-]: CALL      R4 2 2       ; R4 := R4(R5)
 25 [-]: GETGLOBAL R5 K3        ; R5 := 0x7b998233
 26 [-]: MOVE      R6 R4        ; R6 := R4
 27 [-]: CALL      R5 2 2       ; R5 := R5(R6)
 28 [-]: TEST      R5 1         ; if R5 then PC := 127
 29 [-]: JMP       127          ; PC := 127
 30 [-]: GETGLOBAL R5 K7        ; R5 := 0xba7dfcd2
 31 [-]: SELF      R5 R5 K8     ; R6 := R5; R5 := R5[0xf056b179]
 32 [-]: MOVE      R7 R3        ; R7 := R3
 33 [-]: GETGLOBAL R8 K9        ; R8 := 0x0469f296
 34 [-]: LOADK     R9 K10       ; R9 := "DEPLOYED_AIR_SUPPORT"
 35 [-]: CALL      R8 2 0       ; R8,... := R8(R9)
 36 [-]: CALL      R5 0 1       ; R5(R6,...)
 37 [-]: SELF      R5 R1 K11    ; R6 := R1; R5 := R1[0xcc2fcc95]
 38 [-]: LOADKB    R7 1 0       ; R7 := true
 39 [-]: CALL      R5 3 1       ; R5(R6,R7)
 40 [-]: GETGLOBAL R5 K12       ; R5 := 0x85c5e424
 41 [-]: EQ        0 R4 R5      ; if R4 ~= R5 then PC := 47
 42 [-]: JMP       47           ; PC := 47
 43 [-]: GETUPVAL  R5 U2        ; R5 := U2
 44 [-]: MOVE      R6 R1        ; R6 := R1
 45 [-]: CALL      R5 2 1       ; R5(R6)
 46 [-]: JMP       127          ; PC := 127
 47 [-]: GETGLOBAL R5 K13       ; R5 := 0x5488586c
 48 [-]: EQ        0 R4 R5      ; if R4 ~= R5 then PC := 54
 49 [-]: JMP       54           ; PC := 54
 50 [-]: GETUPVAL  R5 U3        ; R5 := U3
 51 [-]: MOVE      R6 R1        ; R6 := R1
 52 [-]: CALL      R5 2 1       ; R5(R6)
 53 [-]: JMP       127          ; PC := 127
 54 [-]: GETGLOBAL R5 K14       ; R5 := 0xf533f106
 55 [-]: EQ        0 R4 R5      ; if R4 ~= R5 then PC := 62
 56 [-]: JMP       62           ; PC := 62
 57 [-]: GETUPVAL  R5 U4        ; R5 := U4
 58 [-]: MOVE      R6 R1        ; R6 := R1
 59 [-]: LOADKB    R7 0 0       ; R7 := false
 60 [-]: CALL      R5 3 1       ; R5(R6,R7)
 61 [-]: JMP       127          ; PC := 127
 62 [-]: GETGLOBAL R5 K15       ; R5 := 0xdc6e092f
 63 [-]: EQ        0 R4 R5      ; if R4 ~= R5 then PC := 70
 64 [-]: JMP       70           ; PC := 70
 65 [-]: GETUPVAL  R5 U4        ; R5 := U4
 66 [-]: MOVE      R6 R1        ; R6 := R1
 67 [-]: LOADKB    R7 1 0       ; R7 := true
 68 [-]: CALL      R5 3 1       ; R5(R6,R7)
 69 [-]: JMP       127          ; PC := 127
 70 [-]: GETGLOBAL R5 K16       ; R5 := 0x7bb9b400
 71 [-]: EQ        0 R4 R5      ; if R4 ~= R5 then PC := 77
 72 [-]: JMP       77           ; PC := 77
 73 [-]: GETUPVAL  R5 U5        ; R5 := U5
 74 [-]: MOVE      R6 R1        ; R6 := R1
 75 [-]: CALL      R5 2 1       ; R5(R6)
 76 [-]: JMP       127          ; PC := 127
 77 [-]: GETGLOBAL R5 K17       ; R5 := 0x6776a3ab
 78 [-]: EQ        0 R4 R5      ; if R4 ~= R5 then PC := 84
 79 [-]: JMP       84           ; PC := 84
 80 [-]: GETUPVAL  R5 U6        ; R5 := U6
 81 [-]: MOVE      R6 R1        ; R6 := R1
 82 [-]: CALL      R5 2 1       ; R5(R6)
 83 [-]: JMP       127          ; PC := 127
 84 [-]: GETGLOBAL R5 K18       ; R5 := 0x1e691df0
 85 [-]: EQ        0 R4 R5      ; if R4 ~= R5 then PC := 92
 86 [-]: JMP       92           ; PC := 92
 87 [-]: GETUPVAL  R5 U7        ; R5 := U7
 88 [-]: MOVE      R6 R1        ; R6 := R1
 89 [-]: LOADKB    R7 0 0       ; R7 := false
 90 [-]: CALL      R5 3 1       ; R5(R6,R7)
 91 [-]: JMP       127          ; PC := 127
 92 [-]: GETGLOBAL R5 K19       ; R5 := 0x6473ee0f
 93 [-]: EQ        0 R4 R5      ; if R4 ~= R5 then PC := 100
 94 [-]: JMP       100          ; PC := 100
 95 [-]: GETUPVAL  R5 U7        ; R5 := U7
 96 [-]: MOVE      R6 R1        ; R6 := R1
 97 [-]: LOADKB    R7 1 0       ; R7 := true
 98 [-]: CALL      R5 3 1       ; R5(R6,R7)
 99 [-]: JMP       127          ; PC := 127
100 [-]: GETGLOBAL R5 K20       ; R5 := 0x337a655e
101 [-]: EQ        0 R4 R5      ; if R4 ~= R5 then PC := 107
102 [-]: JMP       107          ; PC := 107
103 [-]: GETUPVAL  R5 U8        ; R5 := U8
104 [-]: MOVE      R6 R1        ; R6 := R1
105 [-]: CALL      R5 2 1       ; R5(R6)
106 [-]: JMP       127          ; PC := 127
107 [-]: GETGLOBAL R5 K21       ; R5 := 0xe2bbba3f
108 [-]: EQ        0 R4 R5      ; if R4 ~= R5 then PC := 114
109 [-]: JMP       114          ; PC := 114
110 [-]: GETUPVAL  R5 U9        ; R5 := U9
111 [-]: MOVE      R6 R1        ; R6 := R1
112 [-]: CALL      R5 2 1       ; R5(R6)
113 [-]: JMP       127          ; PC := 127
114 [-]: GETGLOBAL R5 K22       ; R5 := 0x7dfdb81e
115 [-]: EQ        0 R4 R5      ; if R4 ~= R5 then PC := 121
116 [-]: JMP       121          ; PC := 121
117 [-]: GETUPVAL  R5 U10       ; R5 := U10
118 [-]: MOVE      R6 R1        ; R6 := R1
119 [-]: CALL      R5 2 1       ; R5(R6)
120 [-]: JMP       127          ; PC := 127
121 [-]: GETGLOBAL R5 K23       ; R5 := 0x3d106989
122 [-]: LOADK     R6 K24       ; R6 := "LisetAirSupport - unknown/unhandled air support type: "
123 [-]: SELF      R7 R4 K25    ; R8 := R4; R7 := R4[0xed4e0128]
124 [-]: CALL      R7 2 2       ; R7 := R7(R8)
125 [-]: CONCAT    R6 R6 R7     ; R6 := R6 .. R7
126 [-]: CALL      R5 2 1       ; R5(R6)
127 [-]: RETURN    R0 1         ; return 


; Function #27:
;
; Name:            
; Defined at line: 1420
; #Upvalues:       1
; #Parameters:     2
; Is_vararg:       0
; Max Stack Size:  6

  1 [-]: GETUPVAL  R2 U0        ; R2 := U0
  2 [-]: CALL      R2 1 2       ; R2 := R2()
  3 [-]: TEST      R2 0         ; if not R2 then PC := 7
  4 [-]: JMP       7            ; PC := 7
  5 [-]: LOADKB    R2 1 0       ; R2 := true
  6 [-]: RETURN    R2 2         ; return R2
  7 [-]: GETGLOBAL R2 K0        ; R2 := 0xbe190284
  8 [-]: SELF      R2 R2 K1     ; R3 := R2; R2 := R2[0x0eb34c69]
  9 [-]: GETGLOBAL R4 K2        ; R4 := 0x0469f296
 10 [-]: LOADK     R5 K3        ; R5 := "StopNormalTransmissions"
 11 [-]: CALL      R4 2 0       ; R4,... := R4(R5)
 12 [-]: CALL      R2 0 2       ; R2 := R2(R3,...)
 13 [-]: EQ        0 R2 K4      ; if R2 ~= 0.000000 then PC := 18
 14 [-]: JMP       18           ; PC := 18
 15 [-]: SELF      R2 R0 K5     ; R3 := R0; R2 := R0[0x2a748f85]
 16 [-]: GETGLOBAL R4 K6        ; R4 := 0xacccce14
 17 [-]: CALL      R2 3 1       ; R2(R3,R4)
 18 [-]: LOADKB    R2 0 0       ; R2 := false
 19 [-]: RETURN    R2 2         ; return R2
 20 [-]: RETURN    R0 1         ; return 


; Function #28:
;
; Name:            
; Defined at line: 1432
; #Upvalues:       1
; #Parameters:     2
; Is_vararg:       0
; Max Stack Size:  9

  1 [-]: GETGLOBAL R2 K0        ; R2 := 0xbe190284
  2 [-]: SELF      R3 R0 K1     ; R4 := R0; R3 := R0[0xde321e6f]
  3 [-]: CALL      R3 2 2       ; R3 := R3(R4)
  4 [-]: SELF      R3 R3 K2     ; R4 := R3; R3 := R3[0x890379f5]
  5 [-]: CALL      R3 2 2       ; R3 := R3(R4)
  6 [-]: TEST      R3 1         ; if R3 then PC := 12
  7 [-]: JMP       12           ; PC := 12
  8 [-]: SELF      R3 R2 K3     ; R4 := R2; R3 := R2[0x5c390f04]
  9 [-]: CALL      R3 2 2       ; R3 := R3(R4)
 10 [-]: EQ        0 R3 K5      ; if R3 ~= 18.000000 then PC := 24
 11 [-]: JMP       24           ; PC := 24
 12 [-]: SELF      R3 R2 K6     ; R4 := R2; R3 := R2[0x0eb34c69]
 13 [-]: GETGLOBAL R5 K7        ; R5 := 0x0469f296
 14 [-]: LOADK     R6 K8        ; R6 := "StopNormalTransmissions"
 15 [-]: CALL      R5 2 0       ; R5,... := R5(R6)
 16 [-]: CALL      R3 0 2       ; R3 := R3(R4,...)
 17 [-]: EQ        0 R3 K9      ; if R3 ~= 0.000000 then PC := 22
 18 [-]: JMP       22           ; PC := 22
 19 [-]: SELF      R3 R0 K10    ; R4 := R0; R3 := R0[0x2a748f85]
 20 [-]: GETGLOBAL R5 K11       ; R5 := 0x202cacb8
 21 [-]: CALL      R3 3 1       ; R3(R4,R5)
 22 [-]: LOADKB    R3 0 0       ; R3 := false
 23 [-]: RETURN    R3 2         ; return R3
 24 [-]: MOVE      R3 R0        ; R3 := R0
 25 [-]: SELF      R4 R3 K12    ; R5 := R3; R4 := R3[0xf2deaf69]
 26 [-]: GETGLOBAL R6 K13       ; R6 := gLotusOperatorAvatarType
 27 [-]: CALL      R4 3 2       ; R4 := R4(R5,R6)
 28 [-]: TEST      R4 0         ; if not R4 then PC := 40
 29 [-]: JMP       40           ; PC := 40
 30 [-]: SELF      R4 R3 K14    ; R5 := R3; R4 := R3[0x5b89142c]
 31 [-]: CALL      R4 2 2       ; R4 := R4(R5)
 32 [-]: GETGLOBAL R5 K15       ; R5 := 0x7b998233
 33 [-]: MOVE      R6 R4        ; R6 := R4
 34 [-]: CALL      R5 2 2       ; R5 := R5(R6)
 35 [-]: TEST      R5 1         ; if R5 then PC := 40
 36 [-]: JMP       40           ; PC := 40
 37 [-]: SELF      R5 R4 K16    ; R6 := R4; R5 := R4[0xa534c3ac]
 38 [-]: CALL      R5 2 2       ; R5 := R5(R6)
 39 [-]: MOVE      R3 R5        ; R3 := R5
 40 [-]: SELF      R5 R3 K1     ; R6 := R3; R5 := R3[0xde321e6f]
 41 [-]: CALL      R5 2 2       ; R5 := R5(R6)
 42 [-]: SELF      R5 R5 K17    ; R6 := R5; R5 := R5[0x96a422be]
 43 [-]: CALL      R5 2 2       ; R5 := R5(R6)
 44 [-]: GETGLOBAL R6 K15       ; R6 := 0x7b998233
 45 [-]: MOVE      R7 R5        ; R7 := R5
 46 [-]: CALL      R6 2 2       ; R6 := R6(R7)
 47 [-]: TEST      R6 1         ; if R6 then PC := 63
 48 [-]: JMP       63           ; PC := 63
 49 [-]: GETGLOBAL R6 K18       ; R6 := 0x5488586c
 50 [-]: EQ        0 R5 R6      ; if R5 ~= R6 then PC := 61
 51 [-]: JMP       61           ; PC := 61
 52 [-]: GETUPVAL  R6 U0        ; R6 := U0
 53 [-]: MOVE      R7 R0        ; R7 := R0
 54 [-]: MOVE      R8 R1        ; R8 := R1
 55 [-]: CALL      R6 3 2       ; R6 := R6(R7,R8)
 56 [-]: TEST      R6 1         ; if R6 then PC := 61
 57 [-]: JMP       61           ; PC := 61
 58 [-]: LOADKB    R6 0 0       ; R6 := false
 59 [-]: RETURN    R6 2         ; return R6
 60 [-]: JMP       63           ; PC := 63
 61 [-]: LOADKB    R6 1 0       ; R6 := true
 62 [-]: RETURN    R6 2         ; return R6
 63 [-]: LOADKB    R6 0 0       ; R6 := false
 64 [-]: RETURN    R6 2         ; return R6
 65 [-]: RETURN    R0 1         ; return 


