; Name:            
; Defined at line: 1
; #Upvalues:       0
; #Parameters:     0
; Is_vararg:       1
; Max Stack Size:  41

       1 [-]: GETIMPORT R0 1; var0 = 0x2D0FAD09
       2 [-]: LOADK R1 K2  ; var1 = "EE.Interface.Utilities"
       3 [-]: CALL R0 2 2  ; var0 = var0(var1)
       4 [-]: GETIMPORT R1 1; var1 = 0x2D0FAD09
       5 [-]: LOADK R2 K3  ; var2 = "Lotus.Scripts.Libs.ObjectiveText"
       6 [-]: CALL R1 2 2  ; var1 = var1(var2)
       7 [-]: GETIMPORT R2 1; var2 = 0x2D0FAD09
       8 [-]: LOADK R3 K4  ; var3 = "Lotus.Scripts.Libs.TransmissionSet"
       9 [-]: CALL R2 2 2  ; var2 = var2(var3)
      10 [-]: GETIMPORT R3 1; var3 = 0x2D0FAD09
      11 [-]: LOADK R4 K5  ; var4 = "Lotus.Interface.LotusUtilities"
      12 [-]: CALL R3 2 2  ; var3 = var3(var4)
      13 [-]: GETIMPORT R4 1; var4 = 0x2D0FAD09
      14 [-]: LOADK R5 K6  ; var5 = "Lotus.Scripts.Libs.QuestLib"
      15 [-]: CALL R4 2 2  ; var4 = var4(var5)
      16 [-]: GETIMPORT R5 8; var5 = 0x7ED0A956
      17 [-]: LOADK R6 K9  ; var6 = "/Lotus/Types/Keys/YareliQuest/YareliQuestKeyChain"
      18 [-]: CALL R5 2 2  ; var5 = var5(var6)
      19 [-]: GETIMPORT R6 8; var6 = 0x7ED0A956
      20 [-]: LOADK R7 K10 ; var7 = "/Lotus/Types/Game/HubNpcs/TalkAction"
      21 [-]: CALL R6 2 2  ; var6 = var6(var7)
      22 [-]: GETIMPORT R7 8; var7 = 0x7ED0A956
      23 [-]: LOADK R8 K11 ; var8 = "/Lotus/Types/Game/HubNpcs/HubNpcObjectiveMarker"
      24 [-]: CALL R7 2 2  ; var7 = var7(var8)
      25 [-]: GETIMPORT R8 13; var8 = 0xB009BBC6
      26 [-]: LOADK R9 K14 ; var9 = "/Lotus/Types/Player/TennoAvatarHubTown"
      27 [-]: CALL R8 2 2  ; var8 = var8(var9)
      28 [-]: GETIMPORT R9 16; var9 = 0x0469F296
      29 [-]: LOADK R10 K17; var10 = "HubNpc_Boon"
      30 [-]: CALL R9 2 2  ; var9 = var9(var10)
      31 [-]: GETIMPORT R10 16; var10 = 0x0469F296
      32 [-]: LOADK R11 K18; var11 = "YareliComic"
      33 [-]: CALL R10 2 2 ; var10 = var10(var11)
      34 [-]: GETIMPORT R11 16; var11 = 0x0469F296
      35 [-]: LOADK R12 K19; var12 = "VentKidsMarker"
      36 [-]: CALL R11 2 2 ; var11 = var11(var12)
      37 [-]: GETIMPORT R12 16; var12 = 0x0469F296
      38 [-]: LOADK R13 K20; var13 = "EnterTownMarker"
      39 [-]: CALL R12 2 2 ; var12 = var12(var13)
      40 [-]: LOADNIL R13  ; var13 = nil
      41 [-]: LOADB R14 0  ; var14 = false
      42 [-]: LOADNIL R15  ; var15 = nil
      43 [-]: GETIMPORT R16 1; var16 = 0x2D0FAD09
      44 [-]: LOADK R17 K21; var17 = "Lotus.Interface.Libs.DioramaLoader"
      45 [-]: CALL R16 2 2 ; var16 = var16(var17)
      46 [-]: LOADNIL R17  ; var17 = nil
      47 [-]: LOADNIL R18  ; var18 = nil
      48 [-]: DUPCLOSURE R19 K22; 
      49 [-]: CAPTURE VAL R3; 
      50 [-]: DUPCLOSURE R20 K23; 
      51 [-]: NEWCLOSURE R21 P2; 
      52 [-]: CAPTURE REF R15; 
      53 [-]: CAPTURE VAL R8; 
      54 [-]: DUPCLOSURE R22 K24; 
      55 [-]: CAPTURE VAL R5; 
      56 [-]: DUPCLOSURE R23 K25; 
      57 [-]: DUPCLOSURE R24 K26; 
      58 [-]: CAPTURE VAL R23; 
      59 [-]: NEWCLOSURE R25 P6; 
      60 [-]: CAPTURE VAL R1; 
      61 [-]: CAPTURE REF R13; 
      62 [-]: CAPTURE VAL R5; 
      63 [-]: CAPTURE VAL R7; 
      64 [-]: NEWCLOSURE R26 P7; 
      65 [-]: CAPTURE VAL R0; 
      66 [-]: CAPTURE REF R18; 
      67 [-]: CAPTURE REF R17; 
      68 [-]: CAPTURE VAL R16; 
      69 [-]: DUPCLOSURE R27 K27; 
      70 [-]: SETGLOBAL R27 K28; "CompleteCurrentChallengesCheat" = var27
      71 [-]: DUPCLOSURE R27 K29; 
      72 [-]: CAPTURE VAL R21; 
      73 [-]: CAPTURE VAL R4; 
      74 [-]: CAPTURE VAL R9; 
      75 [-]: CAPTURE VAL R6; 
      76 [-]: SETGLOBAL R27 K30; "SetupRokyAndBoon" = var27
      77 [-]: DUPCLOSURE R27 K31; 
      78 [-]: SETGLOBAL R27 K32; "OnInboxSync" = var27
      79 [-]: DUPCLOSURE R27 K33; 
      80 [-]: DUPCLOSURE R28 K34; 
      81 [-]: CAPTURE VAL R4; 
      82 [-]: CAPTURE VAL R5; 
      83 [-]: CAPTURE VAL R27; 
      84 [-]: SETGLOBAL R28 K35; "ReadRokyMessageStage" = var28
      85 [-]: NEWCLOSURE R28 P13; 
      86 [-]: CAPTURE VAL R3; 
      87 [-]: CAPTURE VAL R20; 
      88 [-]: CAPTURE VAL R21; 
      89 [-]: CAPTURE VAL R9; 
      90 [-]: CAPTURE VAL R6; 
      91 [-]: CAPTURE VAL R25; 
      92 [-]: CAPTURE REF R13; 
      93 [-]: CAPTURE VAL R11; 
      94 [-]: CAPTURE VAL R26; 
      95 [-]: CAPTURE REF R18; 
      96 [-]: CAPTURE VAL R1; 
      97 [-]: CAPTURE VAL R5; 
      98 [-]: CAPTURE VAL R4; 
      99 [-]: SETGLOBAL R28 K36; "GoToFortunaStage" = var28
     100 [-]: NEWCLOSURE R28 P14; 
     101 [-]: CAPTURE REF R14; 
     102 [-]: SETGLOBAL R28 K37; "OnActivated" = var28
     103 [-]: DUPCLOSURE R28 K38; 
     104 [-]: DUPCLOSURE R29 K39; 
     105 [-]: DUPCLOSURE R30 K40; 
     106 [-]: CAPTURE VAL R10; 
     107 [-]: DUPCLOSURE R31 K41; 
     108 [-]: NEWCLOSURE R32 P19; 
     109 [-]: CAPTURE VAL R30; 
     110 [-]: CAPTURE REF R14; 
     111 [-]: NEWCLOSURE R33 P20; 
     112 [-]: CAPTURE VAL R30; 
     113 [-]: CAPTURE VAL R11; 
     114 [-]: CAPTURE REF R14; 
     115 [-]: CAPTURE REF R15; 
     116 [-]: CAPTURE VAL R12; 
     117 [-]: CAPTURE VAL R3; 
     118 [-]: DUPCLOSURE R34 K42; 
     119 [-]: DUPCLOSURE R35 K43; 
     120 [-]: CAPTURE VAL R30; 
     121 [-]: CAPTURE VAL R9; 
     122 [-]: CAPTURE VAL R6; 
     123 [-]: NEWCLOSURE R36 P23; 
     124 [-]: CAPTURE VAL R30; 
     125 [-]: CAPTURE VAL R35; 
     126 [-]: CAPTURE VAL R3; 
     127 [-]: CAPTURE REF R15; 
     128 [-]: NEWCLOSURE R37 P24; 
     129 [-]: CAPTURE VAL R21; 
     130 [-]: CAPTURE VAL R36; 
     131 [-]: CAPTURE VAL R23; 
     132 [-]: CAPTURE VAL R3; 
     133 [-]: CAPTURE VAL R33; 
     134 [-]: CAPTURE VAL R32; 
     135 [-]: CAPTURE REF R18; 
     136 [-]: CAPTURE VAL R4; 
     137 [-]: CAPTURE VAL R5; 
     138 [-]: SETGLOBAL R37 K44; "ReadPage" = var37
     139 [-]: DUPCLOSURE R37 K45; 
     140 [-]: DUPCLOSURE R38 K46; 
     141 [-]: CAPTURE VAL R37; 
     142 [-]: CAPTURE VAL R23; 
     143 [-]: CAPTURE VAL R2; 
     144 [-]: SETGLOBAL R38 K47; "Challenges" = var38
     145 [-]: DUPCLOSURE R38 K48; 
     146 [-]: CAPTURE VAL R26; 
     147 [-]: SETGLOBAL R38 K49; "ComicActionCompleteScript" = var38
     148 [-]: DUPCLOSURE R38 K50; 
     149 [-]: DUPCLOSURE R39 K51; 
     150 [-]: DUPCLOSURE R40 K52; 
     151 [-]: CAPTURE VAL R21; 
     152 [-]: CAPTURE VAL R5; 
     153 [-]: CAPTURE VAL R4; 
     154 [-]: SETGLOBAL R40 K53; "PlacedComic" = var40
     155 [-]: DUPCLOSURE R40 K54; 
     156 [-]: SETGLOBAL R40 K55; "RokyWakeUp" = var40
     157 [-]: NEWCLOSURE R40 P32; 
     158 [-]: CAPTURE VAL R3; 
     159 [-]: CAPTURE VAL R20; 
     160 [-]: CAPTURE VAL R21; 
     161 [-]: CAPTURE VAL R36; 
     162 [-]: CAPTURE VAL R35; 
     163 [-]: CAPTURE VAL R2; 
     164 [-]: CAPTURE VAL R9; 
     165 [-]: CAPTURE VAL R25; 
     166 [-]: CAPTURE REF R13; 
     167 [-]: CAPTURE VAL R11; 
     168 [-]: CAPTURE VAL R4; 
     169 [-]: CAPTURE VAL R5; 
     170 [-]: SETGLOBAL R40 K56; "ReturnToFortunaStage" = var40
     171 [-]: DUPCLOSURE R40 K57; 
     172 [-]: CAPTURE VAL R4; 
     173 [-]: CAPTURE VAL R5; 
     174 [-]: SETGLOBAL R40 K58; "FinalStage" = var40
     175 [-]: CLOSEUPVALS R13; 
     176 [-]: RETURN R0 0  ; 


; Name:            
; Defined at line: 45
; #Upvalues:       1
; #Parameters:     0
; Is_vararg:       0
; Max Stack Size:  4

       0 [-]: GETIMPORT R0 1; var0 = 0xBE190284
       1 [-]: GETIMPORT R2 3; var2 = gLotusHubGameRulesType
       2 [-]: NAMECALL R0 R0 K4; var1 = var0; var0 = var0[0xF2DEAF69]
       3 [-]: CALL R0 3 2  ; var0 = var0(var1, var2)
       4 [-]: JUMPIFNOT R0 L2; goto L2 if not var0
       5 [-]: GETIMPORT R2 1; var2 = 0xBE190284
       6 [-]: NAMECALL R2 R2 K5; var3 = var2; var2 = var2[0xEF893AEC]
       7 [-]: CALL R2 2 2  ; var2 = var2(var3)
       8 [-]: GETTABLEKS R1 R2 K6; var1 = var2["location"]
       9 [-]: GETUPVAL R3 0; var3 = upvalues[0]
      10 [-]: GETTABLEKS R2 R3 K7; var2 = var3["FORTUNA_NODE_TAG"]
      11 [-]: JUMPIFEQ R1 R2 L0; goto L0 if var1 == var16777222
      12 [-]: LOADB R0 0 +1; var0 = false
L 0:  13 [-]: LOADB R0 1   ; var0 = true
L 1:  14 [-]: RETURN R0 1  ; 
L 2:  15 [-]: LOADB R0 0   ; var0 = false
      16 [-]: RETURN R0 1  ; 


; Name:            
; Defined at line: 55
; #Upvalues:       0
; #Parameters:     0
; Is_vararg:       0
; Max Stack Size:  8

       0 [-]: NEWTABLE R0 0 3; var0 = {}
       1 [-]: LOADK R1 K0  ; var1 = "Boon_YareliIntro"
       2 [-]: LOADK R2 K1  ; var2 = "Boon_YareliChallenge"
       3 [-]: LOADK R3 K2  ; var3 = "Boon_YareliChallenge2"
       4 [-]: SETLIST R0 R1 3 [1]; var0[1] = var1; var0[2] = var2; var0[3] = var3; var0[4] = var4; 
       5 [-]: GETIMPORT R1 4; var1 = _T
       6 [-]: GETIMPORT R2 6; var2 = _T["TaggedDialog"]
       7 [-]: JUMPIF R2 L0 ; goto L0 if var2
       8 [-]: NEWTABLE R2 0 0; var2 = {}
L 0:   9 [-]: SETTABLEKS R2 R1 K5; var2["TaggedDialog"] = var1
      10 [-]: GETIMPORT R1 8; var1 = 0xC8802016
      11 [-]: MOVE R2 R0   ; var2 = var0
      12 [-]: CALL R1 2 4  ; var1, var2, var3 = var1(var2)
      13 [-]: FORGPREP_INEXT R1 L2; 
L 1:  14 [-]: GETIMPORT R6 6; var6 = _T["TaggedDialog"]
      15 [-]: LOADNIL R7   ; var7 = nil
      16 [-]: SETTABLE R7 R6 R5; var7[var6] = var5
L 2:  17 [-]: FORGLOOP R1 L1 2 [inext]; 
      18 [-]: RETURN R0 0  ; 


; Name:            
; Defined at line: 68
; #Upvalues:       2
; #Parameters:     0
; Is_vararg:       0
; Max Stack Size:  3

L 0:   0 [-]: GETIMPORT R0 2; var0 = _T["Fortuna_SetupComplete"]
       1 [-]: JUMPIFNOT R0 L3; goto L3 if not var0
       2 [-]: GETIMPORT R1 4; var1 = 0xBE190284
       3 [-]: FASTCALL1 64 R1 L1; 
       4 [-]: GETIMPORT R0 6; var0 = 0x7B998233
       5 [-]: CALL R0 2 2  ; var0 = var0(var1)
L 1:   6 [-]: JUMPIF R0 L3 ; goto L3 if var0
       7 [-]: GETIMPORT R0 4; var0 = 0xBE190284
       8 [-]: GETIMPORT R2 8; var2 = gLotusHubGameRulesType
       9 [-]: NAMECALL R0 R0 K9; var1 = var0; var0 = var0[0xF2DEAF69]
      10 [-]: CALL R0 3 2  ; var0 = var0(var1, var2)
      11 [-]: JUMPIFNOT R0 L3; goto L3 if not var0
      12 [-]: GETIMPORT R1 4; var1 = 0xBE190284
      13 [-]: NAMECALL R1 R1 K10; var2 = var1; var1 = var1[0x33307F92]
      14 [-]: CALL R1 2 0  ; var1, ... = var1(var2)
      15 [-]: FASTCALL 64 L2; 
      16 [-]: GETIMPORT R0 6; var0 = 0x7B998233
      17 [-]: CALL R0 0 2  ; var0 = var0(var1, ...)
L 2:  18 [-]: JUMPIFNOT R0 L4; goto L4 if not var0
L 3:  19 [-]: GETIMPORT R0 12; var0 = 0xCBD666E1
      20 [-]: LOADN R1 0   ; var1 = 0
      21 [-]: CALL R0 2 1  ; var0(var1)
      22 [-]: JUMPBACK L0  ; goto L0
L 4:  23 [-]: GETIMPORT R0 14; var0 = 0x89326C93
      24 [-]: NAMECALL R0 R0 K15; var1 = var0; var0 = var0[0x78298275]
      25 [-]: CALL R0 2 2  ; var0 = var0(var1)
      26 [-]: SETUPVAL R0 0; upvalues[0] = var0
L 5:  27 [-]: GETUPVAL R1 0; var1 = upvalues[0]
      28 [-]: FASTCALL1 64 R1 L6; 
      29 [-]: GETIMPORT R0 6; var0 = 0x7B998233
      30 [-]: CALL R0 2 2  ; var0 = var0(var1)
L 6:  31 [-]: JUMPIF R0 L7 ; goto L7 if var0
      32 [-]: GETUPVAL R0 0; var0 = upvalues[0]
      33 [-]: GETUPVAL R2 1; var2 = upvalues[1]
      34 [-]: NAMECALL R0 R0 K9; var1 = var0; var0 = var0[0xF2DEAF69]
      35 [-]: CALL R0 3 2  ; var0 = var0(var1, var2)
      36 [-]: JUMPIF R0 L8 ; goto L8 if var0
L 7:  37 [-]: GETIMPORT R0 12; var0 = 0xCBD666E1
      38 [-]: LOADN R1 0   ; var1 = 0
      39 [-]: CALL R0 2 1  ; var0(var1)
      40 [-]: GETIMPORT R0 14; var0 = 0x89326C93
      41 [-]: NAMECALL R0 R0 K15; var1 = var0; var0 = var0[0x78298275]
      42 [-]: CALL R0 2 2  ; var0 = var0(var1)
      43 [-]: SETUPVAL R0 0; upvalues[0] = var0
      44 [-]: JUMPBACK L5  ; goto L5
L 8:  45 [-]: RETURN R0 0  ; 


; Name:            
; Defined at line: 82
; #Upvalues:       1
; #Parameters:     0
; Is_vararg:       0
; Max Stack Size:  2

       0 [-]: GETIMPORT R0 1; var0 = 0xB009BBC6
       1 [-]: GETUPVAL R1 0; var1 = upvalues[0]
       2 [-]: CALL R0 2 2  ; var0 = var0(var1)
       3 [-]: NAMECALL R0 R0 K2; var1 = var0; var0 = var0[0xD3A9D01F]
       4 [-]: CALL R0 2 2  ; var0 = var0(var1)
       5 [-]: NAMECALL R0 R0 K3; var1 = var0; var0 = var0[0x6D604BA7]
       6 [-]: CALL R0 2 0  ; var0, ... = var0(var1)
       7 [-]: RETURN R0 -1 ; 


; Name:            
; Defined at line: 86
; #Upvalues:       0
; #Parameters:     0
; Is_vararg:       0
; Max Stack Size:  9

       0 [-]: LOADN R0 0   ; var0 = 0
       1 [-]: GETIMPORT R1 1; var1 = 0xC8802016
       2 [-]: GETIMPORT R2 3; var2 = 0xCDEB224C
       3 [-]: CALL R1 2 4  ; var1, var2, var3 = var1(var2)
       4 [-]: FORGPREP_INEXT R1 L1; 
L 0:   5 [-]: GETIMPORT R6 5; var6 = 0xBA7DFCD2
       6 [-]: MOVE R8 R5   ; var8 = var5
       7 [-]: NAMECALL R6 R6 K6; var7 = var6; var6 = var6[0x4E99844C]
       8 [-]: CALL R6 3 2  ; var6 = var6(var7, var8)
       9 [-]: JUMPIFNOT R6 L1; goto L1 if not var6
      10 [-]: ADDK R0 R0 K7; var0 = var0 + 1
L 1:  11 [-]: FORGLOOP R1 L0 2 [inext]; 
      12 [-]: RETURN R0 1  ; 


; Name:            
; Defined at line: 96
; #Upvalues:       1
; #Parameters:     0
; Is_vararg:       0
; Max Stack Size:  4

       0 [-]: GETUPVAL R1 0; var1 = upvalues[0]
       1 [-]: CALL R1 1 2  ; var1 = var1()
       2 [-]: GETIMPORT R3 1; var3 = 0xCDEB224C
       3 [-]: LENGTH R2 R3 ; var2 = #var3
       4 [-]: JUMPIFLE R2 R1 L0; goto L0 if var2 <= var16777222
       5 [-]: LOADB R0 0 +1; var0 = false
L 0:   6 [-]: LOADB R0 1   ; var0 = true
L 1:   7 [-]: RETURN R0 1  ; 


; Name:            
; Defined at line: 100
; #Upvalues:       4
; #Parameters:     2
; Is_vararg:       0
; Max Stack Size:  5

       0 [-]: FASTCALL1 64 R0 L0; 
       1 [-]: MOVE R3 R0   ; var3 = var0
       2 [-]: GETIMPORT R2 1; var2 = 0x7B998233
       3 [-]: CALL R2 2 2  ; var2 = var2(var3)
L 0:   4 [-]: JUMPIFNOT R2 L2; goto L2 if not var2
       5 [-]: GETUPVAL R3 0; var3 = upvalues[0]
       6 [-]: GETTABLEKS R2 R3 K2; var2 = var3[0xDC3B2033]
       7 [-]: CALL R2 1 1  ; var2()
       8 [-]: GETUPVAL R3 0; var3 = upvalues[0]
       9 [-]: GETTABLEKS R2 R3 K3; var2 = var3[0xF94B7537]
      10 [-]: CALL R2 1 1  ; var2()
      11 [-]: GETUPVAL R3 1; var3 = upvalues[1]
      12 [-]: FASTCALL1 64 R3 L1; 
      13 [-]: GETIMPORT R2 1; var2 = 0x7B998233
      14 [-]: CALL R2 2 2  ; var2 = var2(var3)
L 1:  15 [-]: JUMPIF R2 L7 ; goto L7 if var2
      16 [-]: GETUPVAL R2 1; var2 = upvalues[1]
      17 [-]: NAMECALL R2 R2 K4; var3 = var2; var2 = var2[0xF4E253B6]
      18 [-]: CALL R2 2 1  ; var2(var3)
      19 [-]: LOADNIL R2   ; var2 = nil
      20 [-]: SETUPVAL R2 1; upvalues[2] = var1
      21 [-]: RETURN R0 0  ; 
L 2:  22 [-]: GETUPVAL R3 0; var3 = upvalues[0]
      23 [-]: GETTABLEKS R2 R3 K5; var2 = var3[0xA1DF01D6]
      24 [-]: GETIMPORT R3 7; var3 = 0xB009BBC6
      25 [-]: GETUPVAL R4 2; var4 = upvalues[2]
      26 [-]: CALL R3 2 2  ; var3 = var3(var4)
      27 [-]: NAMECALL R3 R3 K8; var4 = var3; var3 = var3[0xD3A9D01F]
      28 [-]: CALL R3 2 2  ; var3 = var3(var4)
      29 [-]: NAMECALL R3 R3 K9; var4 = var3; var3 = var3[0x6D604BA7]
      30 [-]: CALL R3 2 2  ; var3 = var3(var4)
      31 [-]: LOADN R4 0   ; var4 = 0
      32 [-]: CALL R2 3 1  ; var2(var3, var4)
      33 [-]: GETUPVAL R3 0; var3 = upvalues[0]
      34 [-]: GETTABLEKS R2 R3 K10; var2 = var3[0x118E5C26]
      35 [-]: MOVE R3 R1   ; var3 = var1
      36 [-]: CALL R2 2 1  ; var2(var3)
      37 [-]: GETUPVAL R4 3; var4 = upvalues[3]
      38 [-]: NAMECALL R2 R0 K11; var3 = var0; var2 = var0[0xC9F6A7D7]
      39 [-]: CALL R2 3 2  ; var2 = var2(var3, var4)
      40 [-]: FASTCALL1 64 R2 L3; 
      41 [-]: MOVE R4 R2   ; var4 = var2
      42 [-]: GETIMPORT R3 1; var3 = 0x7B998233
      43 [-]: CALL R3 2 2  ; var3 = var3(var4)
L 3:  44 [-]: JUMPIF R3 L4 ; goto L4 if var3
      45 [-]: NAMECALL R3 R2 K12; var4 = var2; var3 = var2[0x383D2E7D]
      46 [-]: CALL R3 2 1  ; var3(var4)
L 4:  47 [-]: GETUPVAL R3 1; var3 = upvalues[1]
      48 [-]: JUMPIFEQ R2 R3 L6; goto L6 if var2 == var66620
      49 [-]: GETUPVAL R4 1; var4 = upvalues[1]
      50 [-]: FASTCALL1 64 R4 L5; 
      51 [-]: GETIMPORT R3 1; var3 = 0x7B998233
      52 [-]: CALL R3 2 2  ; var3 = var3(var4)
L 5:  53 [-]: JUMPIF R3 L6 ; goto L6 if var3
      54 [-]: GETUPVAL R3 1; var3 = upvalues[1]
      55 [-]: NAMECALL R3 R3 K4; var4 = var3; var3 = var3[0xF4E253B6]
      56 [-]: CALL R3 2 1  ; var3(var4)
L 6:  57 [-]: SETUPVAL R2 1; upvalues[2] = var1
L 7:  58 [-]: RETURN R0 0  ; 


; Name:            
; Defined at line: 126
; #Upvalues:       4
; #Parameters:     0
; Is_vararg:       0
; Max Stack Size:  5

       0 [-]: GETIMPORT R0 1; var0 = _T
       1 [-]: LOADB R1 1   ; var1 = true
       2 [-]: SETTABLEKS R1 R0 K2; var1["BlockAmbientTransmissions"] = var0
       3 [-]: GETIMPORT R0 5; var0 = 0x34291F5C[0xE27B35BB]
       4 [-]: CALL R0 1 2  ; var0 = var0()
       5 [-]: LOADN R1 4   ; var1 = 4
       6 [-]: SETTABLEKS R1 R0 K6; var1["dialogType"] = var0
       7 [-]: LOADK R1 K7  ; var1 = "/Lotus/Language/Menu/Store_PleaseWait"
       8 [-]: SETTABLEKS R1 R0 K8; var1["locString"] = var0
       9 [-]: GETUPVAL R2 0; var2 = upvalues[0]
      10 [-]: GETTABLEKS R1 R2 K9; var1 = var2[0xE99B84E7]
      11 [-]: MOVE R2 R0   ; var2 = var0
      12 [-]: CALL R1 2 2  ; var1 = var1(var2)
      13 [-]: GETIMPORT R2 11; var2 = 0x9BA7909F
      14 [-]: GETIMPORT R4 13; var4 = 0xDA89A091
      15 [-]: NAMECALL R2 R2 K14; var3 = var2; var2 = var2[0xCFBA257F]
      16 [-]: CALL R2 3 2  ; var2 = var2(var3, var4)
      17 [-]: SETUPVAL R2 1; upvalues[2] = var1
      18 [-]: GETUPVAL R2 1; var2 = upvalues[1]
      19 [-]: LOADB R4 0   ; var4 = false
      20 [-]: NAMECALL R2 R2 K15; var3 = var2; var2 = var2[0x368AD758]
      21 [-]: CALL R2 3 1  ; var2(var3, var4)
      22 [-]: GETUPVAL R3 3; var3 = upvalues[3]
      23 [-]: GETTABLEKS R2 R3 K16; var2 = var3[0xBEC1F4EE]
      24 [-]: GETUPVAL R3 1; var3 = upvalues[1]
      25 [-]: CALL R2 2 2  ; var2 = var2(var3)
      26 [-]: SETUPVAL R2 2; upvalues[2] = var2
      27 [-]: GETUPVAL R2 2; var2 = upvalues[2]
      28 [-]: GETIMPORT R4 18; var4 = 0xB03CB71E
      29 [-]: NAMECALL R2 R2 K19; var3 = var2; var2 = var2[0x522B2215]
      30 [-]: CALL R2 3 1  ; var2(var3, var4)
L 0:  31 [-]: GETUPVAL R2 2; var2 = upvalues[2]
      32 [-]: NAMECALL R2 R2 K20; var3 = var2; var2 = var2[0x842BDEF9]
      33 [-]: CALL R2 2 2  ; var2 = var2(var3)
      34 [-]: JUMPIF R2 L1 ; goto L1 if var2
      35 [-]: GETIMPORT R2 22; var2 = 0xCBD666E1
      36 [-]: LOADN R3 0   ; var3 = 0
      37 [-]: CALL R2 2 1  ; var2(var3)
      38 [-]: JUMPBACK L0  ; goto L0
L 1:  39 [-]: NAMECALL R2 R1 K23; var3 = var1; var2 = var1[0x32302B4A]
      40 [-]: CALL R2 2 1  ; var2(var3)
      41 [-]: GETUPVAL R2 2; var2 = upvalues[2]
      42 [-]: NAMECALL R2 R2 K24; var3 = var2; var2 = var2[0xA4497305]
      43 [-]: CALL R2 2 1  ; var2(var3)
      44 [-]: GETUPVAL R2 1; var2 = upvalues[1]
      45 [-]: LOADB R4 1   ; var4 = true
      46 [-]: NAMECALL R2 R2 K15; var3 = var2; var2 = var2[0x368AD758]
      47 [-]: CALL R2 3 1  ; var2(var3, var4)
      48 [-]: RETURN R0 0  ; 


; Name:            
; Defined at line: 147
; #Upvalues:       0
; #Parameters:     0
; Is_vararg:       0
; Max Stack Size:  10

L 0:   0 [-]: GETIMPORT R1 1; var1 = 0x25D99D89
       1 [-]: FASTCALL1 64 R1 L1; 
       2 [-]: GETIMPORT R0 3; var0 = 0x7B998233
       3 [-]: CALL R0 2 2  ; var0 = var0(var1)
L 1:   4 [-]: JUMPIFNOT R0 L2; goto L2 if not var0
       5 [-]: GETIMPORT R0 5; var0 = 0xCBD666E1
       6 [-]: LOADN R1 0   ; var1 = 0
       7 [-]: CALL R0 2 1  ; var0(var1)
       8 [-]: JUMPBACK L0  ; goto L0
L 2:   9 [-]: GETIMPORT R0 7; var0 = 0xBE190284
      10 [-]: NAMECALL R0 R0 K8; var1 = var0; var0 = var0[0x5C390F04]
      11 [-]: CALL R0 2 2  ; var0 = var0(var1)
      12 [-]: LOADN R1 28  ; var1 = 28
      13 [-]: JUMPIFEQ R0 R1 L3; goto L3 if var0 == var655393
      14 [-]: GETIMPORT R0 10; var0 = 0x3D106989
      15 [-]: LOADK R1 K11 ; var1 = "CHEAT INVALID: Completing challenges must be done in a landscape."
      16 [-]: CALL R0 2 1  ; var0(var1)
L 3:  17 [-]: GETIMPORT R0 13; var0 = 0xC8802016
      18 [-]: GETIMPORT R1 16; var1 = _T["CurrentYareliChallenges"]
      19 [-]: CALL R0 2 4  ; var0, var1, var2 = var0(var1)
      20 [-]: FORGPREP_INEXT R0 L5; 
L 4:  21 [-]: GETIMPORT R5 1; var5 = 0x25D99D89
      22 [-]: MOVE R7 R4   ; var7 = var4
      23 [-]: NAMECALL R8 R4 K17; var9 = var4; var8 = var4[0x2F5D21D2]
      24 [-]: CALL R8 2 0  ; var8, ... = var8(var9)
      25 [-]: NAMECALL R5 R5 K18; var6 = var5; var5 = var5[0x9C95EE90]
      26 [-]: CALL R5 0 1  ; var5(var6, ...)
L 5:  27 [-]: FORGLOOP R0 L4 2 [inext]; 
      28 [-]: GETIMPORT R0 1; var0 = 0x25D99D89
      29 [-]: NAMECALL R0 R0 K19; var1 = var0; var0 = var0[0xD723C617]
      30 [-]: CALL R0 2 1  ; var0(var1)
      31 [-]: RETURN R0 0  ; 


; Name:            
; Defined at line: 162
; #Upvalues:       4
; #Parameters:     1
; Is_vararg:       0
; Max Stack Size:  11

       0 [-]: GETUPVAL R1 0; var1 = upvalues[0]
       1 [-]: CALL R1 1 1  ; var1()
       2 [-]: GETUPVAL R2 1; var2 = upvalues[1]
       3 [-]: GETTABLEKS R1 R2 K0; var1 = var2[0x9BD56FD4]
       4 [-]: CALL R1 1 2  ; var1 = var1()
       5 [-]: JUMPIF R1 L0 ; goto L0 if var1
       6 [-]: RETURN R0 0  ; 
L 0:   7 [-]: LOADK R3 K1  ; var3 = "TriggerPort"
       8 [-]: NAMECALL R1 R0 K2; var2 = var0; var1 = var0[0x8EB2112D]
       9 [-]: CALL R1 3 1  ; var1(var2, var3)
      10 [-]: GETIMPORT R1 4; var1 = 0x89326C93
      11 [-]: GETIMPORT R3 6; var3 = 0x0469F296
      12 [-]: LOADK R4 K7  ; var4 = "RokyKDriveVendorNpc"
      13 [-]: CALL R3 2 0  ; var3, ... = var3(var4)
      14 [-]: NAMECALL R1 R1 K8; var2 = var1; var1 = var1[0x46A0EBF5]
      15 [-]: CALL R1 0 2  ; var1 = var1(var2, ...)
      16 [-]: NAMECALL R2 R1 K9; var3 = var1; var2 = var1[0xF4E253B6]
      17 [-]: CALL R2 2 1  ; var2(var3)
      18 [-]: LOADB R4 0   ; var4 = false
      19 [-]: LOADB R5 1   ; var5 = true
      20 [-]: NAMECALL R2 R1 K10; var3 = var1; var2 = var1[0x768274D6]
      21 [-]: CALL R2 4 1  ; var2(var3, var4, var5)
      22 [-]: GETIMPORT R2 4; var2 = 0x89326C93
      23 [-]: GETIMPORT R4 6; var4 = 0x0469F296
      24 [-]: LOADK R5 K11 ; var5 = "KDrive Vendor"
      25 [-]: CALL R4 2 0  ; var4, ... = var4(var5)
      26 [-]: NAMECALL R2 R2 K8; var3 = var2; var2 = var2[0x46A0EBF5]
      27 [-]: CALL R2 0 2  ; var2 = var2(var3, ...)
      28 [-]: NAMECALL R3 R2 K9; var4 = var2; var3 = var2[0xF4E253B6]
      29 [-]: CALL R3 2 1  ; var3(var4)
      30 [-]: GETIMPORT R5 13; var5 = EMPTY_SYMBOL
      31 [-]: NAMECALL R3 R2 K14; var4 = var2; var3 = var2[0x3273BA96]
      32 [-]: CALL R3 3 1  ; var3(var4, var5)
      33 [-]: GETIMPORT R3 4; var3 = 0x89326C93
      34 [-]: GETIMPORT R5 6; var5 = 0x0469F296
      35 [-]: LOADK R6 K15 ; var6 = "RokyBoonDialogTrigger"
      36 [-]: CALL R5 2 0  ; var5, ... = var5(var6)
      37 [-]: NAMECALL R3 R3 K8; var4 = var3; var3 = var3[0x46A0EBF5]
      38 [-]: CALL R3 0 2  ; var3 = var3(var4, ...)
      39 [-]: NAMECALL R4 R3 K9; var5 = var3; var4 = var3[0xF4E253B6]
      40 [-]: CALL R4 2 1  ; var4(var5)
      41 [-]: GETIMPORT R4 4; var4 = 0x89326C93
      42 [-]: GETIMPORT R6 6; var6 = 0x0469F296
      43 [-]: LOADK R7 K16 ; var7 = "BoonDeco"
      44 [-]: CALL R6 2 0  ; var6, ... = var6(var7)
      45 [-]: NAMECALL R4 R4 K8; var5 = var4; var4 = var4[0x46A0EBF5]
      46 [-]: CALL R4 0 2  ; var4 = var4(var5, ...)
      47 [-]: LOADB R7 0   ; var7 = false
      48 [-]: LOADB R8 1   ; var8 = true
      49 [-]: NAMECALL R5 R4 K10; var6 = var4; var5 = var4[0x768274D6]
      50 [-]: CALL R5 4 1  ; var5(var6, var7, var8)
      51 [-]: GETIMPORT R5 4; var5 = 0x89326C93
      52 [-]: GETUPVAL R7 2; var7 = upvalues[2]
      53 [-]: NAMECALL R5 R5 K8; var6 = var5; var5 = var5[0x46A0EBF5]
      54 [-]: CALL R5 3 2  ; var5 = var5(var6, var7)
      55 [-]: GETUPVAL R8 3; var8 = upvalues[3]
      56 [-]: NAMECALL R6 R5 K17; var7 = var5; var6 = var5[0xC9F6A7D7]
      57 [-]: CALL R6 3 2  ; var6 = var6(var7, var8)
      58 [-]: NAMECALL R6 R6 K18; var7 = var6; var6 = var6[0x383D2E7D]
      59 [-]: CALL R6 2 1  ; var6(var7)
      60 [-]: GETUPVAL R8 3; var8 = upvalues[3]
      61 [-]: NAMECALL R6 R5 K17; var7 = var5; var6 = var5[0xC9F6A7D7]
      62 [-]: CALL R6 3 2  ; var6 = var6(var7, var8)
      63 [-]: GETIMPORT R9 6; var9 = 0x0469F296
      64 [-]: LOADK R10 K11; var10 = "KDrive Vendor"
      65 [-]: CALL R9 2 0  ; var9, ... = var9(var10)
      66 [-]: NAMECALL R7 R6 K14; var8 = var6; var7 = var6[0x3273BA96]
      67 [-]: CALL R7 0 1  ; var7(var8, ...)
      68 [-]: GETIMPORT R7 20; var7 = _T
      69 [-]: LOADB R8 1   ; var8 = true
      70 [-]: SETTABLEKS R8 R7 K21; var8["YareliQuestMuteRoky"] = var7
      71 [-]: RETURN R0 0  ; 


; Name:            
; Defined at line: 187
; #Upvalues:       0
; #Parameters:     0
; Is_vararg:       0
; Max Stack Size:  4

       0 [-]: GETIMPORT R0 1; var0 = 0x76EA806B
       1 [-]: LOADN R2 0   ; var2 = 0
       2 [-]: NAMECALL R0 R0 K2; var1 = var0; var0 = var0[0x3F3AE64C]
       3 [-]: CALL R0 3 2  ; var0 = var0(var1, var2)
       4 [-]: FASTCALL1 64 R0 L0; 
       5 [-]: MOVE R2 R0   ; var2 = var0
       6 [-]: GETIMPORT R1 4; var1 = 0x7B998233
       7 [-]: CALL R1 2 2  ; var1 = var1(var2)
L 0:   8 [-]: JUMPIF R1 L2 ; goto L2 if var1
       9 [-]: NAMECALL R1 R0 K5; var2 = var0; var1 = var0[0x22DE02E1]
      10 [-]: CALL R1 2 2  ; var1 = var1(var2)
      11 [-]: JUMPIFNOT R1 L2; goto L2 if not var1
      12 [-]: NAMECALL R1 R0 K6; var2 = var0; var1 = var0[0x80563238]
      13 [-]: CALL R1 2 2  ; var1 = var1(var2)
      14 [-]: FASTCALL1 64 R1 L1; 
      15 [-]: MOVE R3 R1   ; var3 = var1
      16 [-]: GETIMPORT R2 4; var2 = 0x7B998233
      17 [-]: CALL R2 2 2  ; var2 = var2(var3)
L 1:  18 [-]: JUMPIF R2 L2 ; goto L2 if var2
      19 [-]: NAMECALL R2 R1 K7; var3 = var1; var2 = var1[0x1730E16B]
      20 [-]: CALL R2 2 2  ; var2 = var2(var3)
      21 [-]: JUMPIFNOT R2 L2; goto L2 if not var2
      22 [-]: GETIMPORT R2 9; var2 = _T
      23 [-]: LOADB R3 1   ; var3 = true
      24 [-]: SETTABLEKS R3 R2 K10; var3["gQueueMailbox"] = var2
L 2:  25 [-]: RETURN R0 0  ; 


; Name:            
; Defined at line: 199
; #Upvalues:       0
; #Parameters:     0
; Is_vararg:       0
; Max Stack Size:  9

       0 [-]: GETIMPORT R0 1; var0 = 0xC8802016
       1 [-]: GETIMPORT R1 3; var1 = 0xCDEB224C
       2 [-]: CALL R0 2 4  ; var0, var1, var2 = var0(var1)
       3 [-]: FORGPREP_INEXT R0 L1; 
L 0:   4 [-]: GETIMPORT R5 5; var5 = 0x25D99D89
       5 [-]: MOVE R7 R4   ; var7 = var4
       6 [-]: LOADN R8 0   ; var8 = 0
       7 [-]: NAMECALL R5 R5 K6; var6 = var5; var5 = var5[0x9C95EE90]
       8 [-]: CALL R5 4 1  ; var5(var6, var7, var8)
L 1:   9 [-]: FORGLOOP R0 L0 2 [inext]; 
      10 [-]: GETIMPORT R0 5; var0 = 0x25D99D89
      11 [-]: NAMECALL R0 R0 K7; var1 = var0; var0 = var0[0xD723C617]
      12 [-]: CALL R0 2 1  ; var0(var1)
      13 [-]: RETURN R0 0  ; 


; Name:            
; Defined at line: 206
; #Upvalues:       3
; #Parameters:     0
; Is_vararg:       0
; Max Stack Size:  7

L 0:   0 [-]: GETIMPORT R1 1; var1 = 0x25D99D89
       1 [-]: FASTCALL1 64 R1 L1; 
       2 [-]: GETIMPORT R0 3; var0 = 0x7B998233
       3 [-]: CALL R0 2 2  ; var0 = var0(var1)
L 1:   4 [-]: JUMPIFNOT R0 L2; goto L2 if not var0
       5 [-]: GETIMPORT R0 5; var0 = 0xCBD666E1
       6 [-]: LOADN R1 0   ; var1 = 0
       7 [-]: CALL R0 2 1  ; var0(var1)
       8 [-]: JUMPBACK L0  ; goto L0
L 2:   9 [-]: GETUPVAL R1 0; var1 = upvalues[0]
      10 [-]: GETTABLEKS R0 R1 K6; var0 = var1[0xD3D59A3B]
      11 [-]: GETUPVAL R1 1; var1 = upvalues[1]
      12 [-]: CALL R0 2 2  ; var0 = var0(var1)
      13 [-]: JUMPIFNOT R0 L3; goto L3 if not var0
      14 [-]: GETUPVAL R1 0; var1 = upvalues[0]
      15 [-]: GETTABLEKS R0 R1 K7; var0 = var1[0xA26220ED]
      16 [-]: GETIMPORT R1 9; var1 = 0xB009BBC6
      17 [-]: GETUPVAL R2 1; var2 = upvalues[1]
      18 [-]: CALL R1 2 2  ; var1 = var1(var2)
      19 [-]: GETIMPORT R2 11; var2 = 0x1E9E5BC8
      20 [-]: CALL R0 3 1  ; var0(var1, var2)
      21 [-]: GETUPVAL R0 2; var0 = upvalues[2]
      22 [-]: CALL R0 1 1  ; var0()
      23 [-]: RETURN R0 0  ; 
L 3:  24 [-]: GETIMPORT R0 1; var0 = 0x25D99D89
      25 [-]: NAMECALL R0 R0 K12; var1 = var0; var0 = var0[0x42CE212F]
      26 [-]: CALL R0 2 2  ; var0 = var0(var1)
      27 [-]: LOADB R1 0   ; var1 = false
      28 [-]: LOADN R4 1   ; var4 = 1
      29 [-]: LENGTH R2 R0 ; var2 = #var0
      30 [-]: LOADN R3 1   ; var3 = 1
      31 [-]: FORNPREP R2 L6; nforprep start - [escape at L6] -- var2 = iterator
L 4:  32 [-]: GETIMPORT R5 14; var5 = 0xCE225EFA
      33 [-]: CALL R5 1 1  ; var5()
      34 [-]: GETTABLE R6 R0 R4; var6 = var0[var4]
      35 [-]: GETTABLEKS R5 R6 K15; var5 = var6["mSubject"]
      36 [-]: JUMPXEQKS R5 K16 L5 NOT; 
      37 [-]: LOADB R1 1   ; var1 = true
L 5:  38 [-]: FORNLOOP R2 L4; nforloop end - iterate + goto L4
L 6:  39 [-]: JUMPIF R1 L7 ; goto L7 if var1
      40 [-]: GETIMPORT R2 1; var2 = 0x25D99D89
      41 [-]: GETUPVAL R4 1; var4 = upvalues[1]
      42 [-]: GETIMPORT R6 11; var6 = 0x1E9E5BC8
      43 [-]: ADDK R5 R6 K17; var5 = var6 + 1
      44 [-]: NAMECALL R2 R2 K18; var3 = var2; var2 = var2[0xF8CFD9AC]
      45 [-]: CALL R2 4 2  ; var2 = var2(var3, var4, var5)
      46 [-]: JUMPIFNOT R2 L7; goto L7 if not var2
      47 [-]: GETUPVAL R2 2; var2 = upvalues[2]
      48 [-]: CALL R2 1 1  ; var2()
      49 [-]: GETUPVAL R3 0; var3 = upvalues[0]
      50 [-]: GETTABLEKS R2 R3 K7; var2 = var3[0xA26220ED]
      51 [-]: GETIMPORT R3 9; var3 = 0xB009BBC6
      52 [-]: GETUPVAL R4 1; var4 = upvalues[1]
      53 [-]: CALL R3 2 2  ; var3 = var3(var4)
      54 [-]: GETIMPORT R4 11; var4 = 0x1E9E5BC8
      55 [-]: CALL R2 3 1  ; var2(var3, var4)
      56 [-]: RETURN R0 0  ; 
L 7:  57 [-]: GETUPVAL R3 0; var3 = upvalues[0]
      58 [-]: GETTABLEKS R2 R3 K19; var2 = var3[0x02DC6F4F]
      59 [-]: GETUPVAL R3 1; var3 = upvalues[1]
      60 [-]: GETIMPORT R4 11; var4 = 0x1E9E5BC8
      61 [-]: CALL R2 3 1  ; var2(var3, var4)
      62 [-]: GETIMPORT R2 5; var2 = 0xCBD666E1
      63 [-]: LOADN R3 1   ; var3 = 1
      64 [-]: CALL R2 2 1  ; var2(var3)
      65 [-]: GETIMPORT R2 1; var2 = 0x25D99D89
      66 [-]: LOADK R4 K20 ; var4 = "OnInboxSync"
      67 [-]: LOADB R5 1   ; var5 = true
      68 [-]: NAMECALL R2 R2 K21; var3 = var2; var2 = var2[0x24389EC3]
      69 [-]: CALL R2 4 1  ; var2(var3, var4, var5)
      70 [-]: GETUPVAL R2 2; var2 = upvalues[2]
      71 [-]: CALL R2 1 1  ; var2()
L 8:  72 [-]: GETIMPORT R2 24; var2 = _T["curTransmission"]
      73 [-]: GETIMPORT R3 26; var3 = 0x13B4613D
      74 [-]: JUMPIFEQ R2 R3 L9; goto L9 if var2 == var328225
      75 [-]: GETIMPORT R2 5; var2 = 0xCBD666E1
      76 [-]: LOADN R3 0   ; var3 = 0
      77 [-]: CALL R2 2 1  ; var2(var3)
      78 [-]: JUMPBACK L8  ; goto L8
L 9:  79 [-]: GETIMPORT R2 24; var2 = _T["curTransmission"]
      80 [-]: GETIMPORT R3 26; var3 = 0x13B4613D
      81 [-]: JUMPIFNOTEQ R2 R3 L10; goto L10 if var2 ~= var328225
      82 [-]: GETIMPORT R2 5; var2 = 0xCBD666E1
      83 [-]: LOADN R3 0   ; var3 = 0
      84 [-]: CALL R2 2 1  ; var2(var3)
      85 [-]: JUMPBACK L9  ; goto L9
L10:  86 [-]: GETUPVAL R3 0; var3 = upvalues[0]
      87 [-]: GETTABLEKS R2 R3 K7; var2 = var3[0xA26220ED]
      88 [-]: GETIMPORT R3 9; var3 = 0xB009BBC6
      89 [-]: GETUPVAL R4 1; var4 = upvalues[1]
      90 [-]: CALL R3 2 2  ; var3 = var3(var4)
      91 [-]: GETIMPORT R4 11; var4 = 0x1E9E5BC8
      92 [-]: CALL R2 3 1  ; var2(var3, var4)
      93 [-]: RETURN R0 0  ; 


; Name:            
; Defined at line: 252
; #Upvalues:       13
; #Parameters:     0
; Is_vararg:       0
; Max Stack Size:  4

       0 [-]: GETIMPORT R1 1; var1 = 0xBE190284
       1 [-]: GETIMPORT R3 3; var3 = gLotusHubGameRulesType
       2 [-]: NAMECALL R1 R1 K4; var2 = var1; var1 = var1[0xF2DEAF69]
       3 [-]: CALL R1 3 2  ; var1 = var1(var2, var3)
       4 [-]: JUMPIFNOT R1 L2; goto L2 if not var1
       5 [-]: GETIMPORT R2 1; var2 = 0xBE190284
       6 [-]: NAMECALL R2 R2 K5; var3 = var2; var2 = var2[0xEF893AEC]
       7 [-]: CALL R2 2 2  ; var2 = var2(var3)
       8 [-]: GETTABLEKS R1 R2 K6; var1 = var2["location"]
       9 [-]: GETUPVAL R3 0; var3 = upvalues[0]
      10 [-]: GETTABLEKS R2 R3 K7; var2 = var3["FORTUNA_NODE_TAG"]
      11 [-]: JUMPIFEQ R1 R2 L0; goto L0 if var1 == var16777222
      12 [-]: LOADB R0 0 +1; var0 = false
L 0:  13 [-]: LOADB R0 1   ; var0 = true
L 1:  14 [-]: JUMP L3      ; goto L3
L 2:  15 [-]: LOADB R0 0   ; var0 = false
L 3:  16 [-]: JUMPIF R0 L4 ; goto L4 if var0
      17 [-]: RETURN R0 0  ; 
L 4:  18 [-]: GETUPVAL R0 1; var0 = upvalues[1]
      19 [-]: CALL R0 1 1  ; var0()
      20 [-]: GETUPVAL R0 2; var0 = upvalues[2]
      21 [-]: CALL R0 1 1  ; var0()
      22 [-]: GETIMPORT R0 9; var0 = _T
      23 [-]: LOADB R1 0   ; var1 = false
      24 [-]: SETTABLEKS R1 R0 K10; var1["YareliComicReadyOnTable"] = var0
      25 [-]: GETIMPORT R0 9; var0 = _T
      26 [-]: LOADN R1 1   ; var1 = 1
      27 [-]: SETTABLEKS R1 R0 K11; var1["CurrentYareliPage"] = var0
      28 [-]: GETIMPORT R0 13; var0 = 0x89326C93
      29 [-]: GETUPVAL R2 3; var2 = upvalues[3]
      30 [-]: NAMECALL R0 R0 K14; var1 = var0; var0 = var0[0x46A0EBF5]
      31 [-]: CALL R0 3 2  ; var0 = var0(var1, var2)
      32 [-]: GETUPVAL R3 4; var3 = upvalues[4]
      33 [-]: NAMECALL R1 R0 K15; var2 = var0; var1 = var0[0xC9F6A7D7]
      34 [-]: CALL R1 3 2  ; var1 = var1(var2, var3)
      35 [-]: NAMECALL R1 R1 K16; var2 = var1; var1 = var1[0x383D2E7D]
      36 [-]: CALL R1 2 1  ; var1(var2)
      37 [-]: GETUPVAL R1 5; var1 = upvalues[5]
      38 [-]: MOVE R2 R0   ; var2 = var0
      39 [-]: LOADK R3 K17 ; var3 = "/Lotus/Language/YareliQuest/TalkToRoky"
      40 [-]: CALL R1 3 1  ; var1(var2, var3)
      41 [-]: GETIMPORT R1 13; var1 = 0x89326C93
      42 [-]: GETUPVAL R3 7; var3 = upvalues[7]
      43 [-]: NAMECALL R1 R1 K14; var2 = var1; var1 = var1[0x46A0EBF5]
      44 [-]: CALL R1 3 2  ; var1 = var1(var2, var3)
      45 [-]: SETUPVAL R1 6; upvalues[1] = var6
      46 [-]: GETUPVAL R1 6; var1 = upvalues[6]
      47 [-]: NAMECALL R1 R1 K16; var2 = var1; var1 = var1[0x383D2E7D]
      48 [-]: CALL R1 2 1  ; var1(var2)
      49 [-]: GETIMPORT R1 19; var1 = _T["TaggedDialog"]
      50 [-]: GETIMPORT R3 19; var3 = _T["TaggedDialog"]
      51 [-]: GETTABLEKS R2 R3 K20; var2 = var3["Boon_YareliIntro"]
      52 [-]: JUMPIF R2 L5 ; goto L5 if var2
      53 [-]: DUPTABLE R2 23; 
      54 [-]: LOADK R3 K24 ; var3 = "/Lotus/Language/YareliQuest/IntroDialogOption"
      55 [-]: SETTABLEKS R3 R2 K21; var3["mName"] = var2
      56 [-]: NEWCLOSURE R3 P0; 
      57 [-]: CAPTURE UPVAL U5; 
      58 [-]: CAPTURE UPVAL U8; 
      59 [-]: CAPTURE UPVAL U9; 
      60 [-]: SETTABLEKS R3 R2 K22; var3["mCallback"] = var2
L 5:  61 [-]: SETTABLEKS R2 R1 K20; var2["Boon_YareliIntro"] = var1
L 6:  62 [-]: GETIMPORT R1 25; var1 = _T["YareliComicReadyOnTable"]
      63 [-]: JUMPIF R1 L7 ; goto L7 if var1
      64 [-]: GETIMPORT R1 27; var1 = 0xCBD666E1
      65 [-]: LOADN R2 0   ; var2 = 0
      66 [-]: CALL R1 2 1  ; var1(var2)
      67 [-]: JUMPBACK L6  ; goto L6
L 7:  68 [-]: GETUPVAL R2 10; var2 = upvalues[10]
      69 [-]: GETTABLEKS R1 R2 K28; var1 = var2[0xA1DF01D6]
      70 [-]: GETIMPORT R2 30; var2 = 0xB009BBC6
      71 [-]: GETUPVAL R3 11; var3 = upvalues[11]
      72 [-]: CALL R2 2 2  ; var2 = var2(var3)
      73 [-]: NAMECALL R2 R2 K31; var3 = var2; var2 = var2[0xD3A9D01F]
      74 [-]: CALL R2 2 2  ; var2 = var2(var3)
      75 [-]: NAMECALL R2 R2 K32; var3 = var2; var2 = var2[0x6D604BA7]
      76 [-]: CALL R2 2 2  ; var2 = var2(var3)
      77 [-]: LOADN R3 0   ; var3 = 0
      78 [-]: CALL R1 3 1  ; var1(var2, var3)
      79 [-]: GETUPVAL R2 10; var2 = upvalues[10]
      80 [-]: GETTABLEKS R1 R2 K33; var1 = var2[0x118E5C26]
      81 [-]: LOADK R2 K34 ; var2 = "/Lotus/Language/YareliQuest/CompleteChallenges"
      82 [-]: CALL R1 2 1  ; var1(var2)
      83 [-]: GETUPVAL R2 12; var2 = upvalues[12]
      84 [-]: GETTABLEKS R1 R2 K35; var1 = var2[0xA26220ED]
      85 [-]: GETIMPORT R2 30; var2 = 0xB009BBC6
      86 [-]: GETUPVAL R3 11; var3 = upvalues[11]
      87 [-]: CALL R2 2 2  ; var2 = var2(var3)
      88 [-]: GETIMPORT R3 37; var3 = 0x1E9E5BC8
      89 [-]: CALL R1 3 1  ; var1(var2, var3)
      90 [-]: RETURN R0 0  ; 


; Name:            
; Defined at line: 301
; #Upvalues:       1
; #Parameters:     1
; Is_vararg:       0
; Max Stack Size:  2

       0 [-]: LOADB R1 1   ; var1 = true
       1 [-]: SETUPVAL R1 0; upvalues[1] = var0
       2 [-]: RETURN R0 0  ; 


; Name:            
; Defined at line: 305
; #Upvalues:       0
; #Parameters:     2
; Is_vararg:       0
; Max Stack Size:  4

       0 [-]: FASTCALL1 64 R0 L0; 
       1 [-]: MOVE R3 R0   ; var3 = var0
       2 [-]: GETIMPORT R2 1; var2 = 0x7B998233
       3 [-]: CALL R2 2 2  ; var2 = var2(var3)
L 0:   4 [-]: JUMPIFNOT R2 L1; goto L1 if not var2
       5 [-]: RETURN R0 0  ; 
L 1:   6 [-]: JUMPIFNOT R1 L2; goto L2 if not var1
       7 [-]: NAMECALL R2 R0 K2; var3 = var0; var2 = var0[0xF37943FF]
       8 [-]: CALL R2 2 2  ; var2 = var2(var3)
       9 [-]: JUMPIF R2 L2 ; goto L2 if var2
      10 [-]: NAMECALL R2 R0 K3; var3 = var0; var2 = var0[0x383D2E7D]
      11 [-]: CALL R2 2 1  ; var2(var3)
      12 [-]: RETURN R0 0  ; 
L 2:  13 [-]: JUMPIF R1 L3 ; goto L3 if var1
      14 [-]: NAMECALL R2 R0 K2; var3 = var0; var2 = var0[0xF37943FF]
      15 [-]: CALL R2 2 2  ; var2 = var2(var3)
      16 [-]: JUMPIFNOT R2 L3; goto L3 if not var2
      17 [-]: NAMECALL R2 R0 K4; var3 = var0; var2 = var0[0xF4E253B6]
      18 [-]: CALL R2 2 1  ; var2(var3)
L 3:  19 [-]: RETURN R0 0  ; 


; Name:            
; Defined at line: 318
; #Upvalues:       0
; #Parameters:     2
; Is_vararg:       0
; Max Stack Size:  6

       0 [-]: GETIMPORT R4 1; var4 = 0x0469F296
       1 [-]: LOADK R5 K2  ; var5 = "YareliComicMarker"
       2 [-]: CALL R4 2 0  ; var4, ... = var4(var5)
       3 [-]: NAMECALL R2 R1 K3; var3 = var1; var2 = var1[0x3273BA96]
       4 [-]: CALL R2 0 1  ; var2(var3, ...)
       5 [-]: GETIMPORT R4 5; var4 = gContextActionType
       6 [-]: NAMECALL R2 R0 K6; var3 = var0; var2 = var0[0xC9F6A7D7]
       7 [-]: CALL R2 3 2  ; var2 = var2(var3, var4)
       8 [-]: GETIMPORT R3 8; var3 = 0x11A19C5E
       9 [-]: MOVE R4 R2   ; var4 = var2
      10 [-]: LOADK R5 K9  ; var5 = "OnActivated"
      11 [-]: CALL R3 3 1  ; var3(var4, var5)
      12 [-]: RETURN R0 0  ; 


; Name:            
; Defined at line: 324
; #Upvalues:       1
; #Parameters:     0
; Is_vararg:       0
; Max Stack Size:  4

       0 [-]: GETIMPORT R0 1; var0 = 0x89326C93
       1 [-]: GETUPVAL R2 0; var2 = upvalues[0]
       2 [-]: NAMECALL R0 R0 K2; var1 = var0; var0 = var0[0x46A0EBF5]
       3 [-]: CALL R0 3 2  ; var0 = var0(var1, var2)
L 0:   4 [-]: FASTCALL1 64 R0 L1; 
       5 [-]: MOVE R2 R0   ; var2 = var0
       6 [-]: GETIMPORT R1 4; var1 = 0x7B998233
       7 [-]: CALL R1 2 2  ; var1 = var1(var2)
L 1:   8 [-]: JUMPIFNOT R1 L2; goto L2 if not var1
       9 [-]: GETIMPORT R1 6; var1 = 0xCBD666E1
      10 [-]: LOADK R2 K7  ; var2 = 0.20000000298023224
      11 [-]: CALL R1 2 1  ; var1(var2)
      12 [-]: GETIMPORT R1 1; var1 = 0x89326C93
      13 [-]: GETUPVAL R3 0; var3 = upvalues[0]
      14 [-]: NAMECALL R1 R1 K2; var2 = var1; var1 = var1[0x46A0EBF5]
      15 [-]: CALL R1 3 2  ; var1 = var1(var2, var3)
      16 [-]: MOVE R0 R1   ; var0 = var1
      17 [-]: JUMPBACK L0  ; goto L0
L 2:  18 [-]: RETURN R0 1  ; 


; Name:            
; Defined at line: 333
; #Upvalues:       0
; #Parameters:     2
; Is_vararg:       0
; Max Stack Size:  6

       0 [-]: FASTCALL1 64 R0 L0; 
       1 [-]: MOVE R3 R0   ; var3 = var0
       2 [-]: GETIMPORT R2 1; var2 = 0x7B998233
       3 [-]: CALL R2 2 2  ; var2 = var2(var3)
L 0:   4 [-]: JUMPIF R2 L2 ; goto L2 if var2
       5 [-]: FASTCALL1 64 R1 L1; 
       6 [-]: MOVE R3 R1   ; var3 = var1
       7 [-]: GETIMPORT R2 1; var2 = 0x7B998233
       8 [-]: CALL R2 2 2  ; var2 = var2(var3)
L 1:   9 [-]: JUMPIFNOT R2 L3; goto L3 if not var2
L 2:  10 [-]: LOADB R2 0   ; var2 = false
      11 [-]: RETURN R2 1  ; 
L 3:  12 [-]: NAMECALL R3 R0 K2; var4 = var0; var3 = var0[0xE79E7EF4]
      13 [-]: CALL R3 2 2  ; var3 = var3(var4)
      14 [-]: NAMECALL R4 R1 K2; var5 = var1; var4 = var1[0xE79E7EF4]
      15 [-]: CALL R4 2 2  ; var4 = var4(var5)
      16 [-]: JUMPIFEQ R3 R4 L4; goto L4 if var3 == var16777734
      17 [-]: LOADB R2 0 +1; var2 = false
L 4:  18 [-]: LOADB R2 1   ; var2 = true
L 5:  19 [-]: RETURN R2 1  ; 


; Name:            
; Defined at line: 341
; #Upvalues:       2
; #Parameters:     1
; Is_vararg:       0
; Max Stack Size:  7

       0 [-]: GETUPVAL R1 0; var1 = upvalues[0]
       1 [-]: CALL R1 1 2  ; var1 = var1()
       2 [-]: GETIMPORT R4 1; var4 = 0x4C096771
       3 [-]: GETIMPORT R5 3; var5 = EMPTY_SYMBOL
       4 [-]: NAMECALL R2 R1 K4; var3 = var1; var2 = var1[0x47901F07]
       5 [-]: CALL R2 4 2  ; var2 = var2(var3, var4, var5)
       6 [-]: GETIMPORT R5 6; var5 = 0x0469F296
       7 [-]: LOADK R6 K7  ; var6 = "YareliComicMarker"
       8 [-]: CALL R5 2 0  ; var5, ... = var5(var6)
       9 [-]: NAMECALL R3 R2 K8; var4 = var2; var3 = var2[0x3273BA96]
      10 [-]: CALL R3 0 1  ; var3(var4, ...)
      11 [-]: GETIMPORT R5 10; var5 = gContextActionType
      12 [-]: NAMECALL R3 R1 K11; var4 = var1; var3 = var1[0xC9F6A7D7]
      13 [-]: CALL R3 3 2  ; var3 = var3(var4, var5)
      14 [-]: GETIMPORT R4 13; var4 = 0x11A19C5E
      15 [-]: MOVE R5 R3   ; var5 = var3
      16 [-]: LOADK R6 K14 ; var6 = "OnActivated"
      17 [-]: CALL R4 3 1  ; var4(var5, var6)
      18 [-]: FASTCALL1 64 R2 L0; 
      19 [-]: MOVE R4 R2   ; var4 = var2
      20 [-]: GETIMPORT R3 16; var3 = 0x7B998233
      21 [-]: CALL R3 2 2  ; var3 = var3(var4)
L 0:  22 [-]: JUMPIFNOT R3 L1; goto L1 if not var3
      23 [-]: JUMP L2      ; goto L2
L 1:  24 [-]: NAMECALL R3 R2 K17; var4 = var2; var3 = var2[0xF37943FF]
      25 [-]: CALL R3 2 2  ; var3 = var3(var4)
      26 [-]: JUMPIF R3 L2 ; goto L2 if var3
      27 [-]: NAMECALL R3 R2 K18; var4 = var2; var3 = var2[0x383D2E7D]
      28 [-]: CALL R3 2 1  ; var3(var4)
      29 [-]: JUMP L2      ; goto L2
L 2:  30 [-]: GETUPVAL R3 1; var3 = upvalues[1]
      31 [-]: JUMPIF R3 L3 ; goto L3 if var3
      32 [-]: JUMPIFNOT R0 L3; goto L3 if not var0
      33 [-]: GETIMPORT R3 20; var3 = 0xCBD666E1
      34 [-]: LOADN R4 0   ; var4 = 0
      35 [-]: CALL R3 2 1  ; var3(var4)
      36 [-]: JUMPBACK L2  ; goto L2
L 3:  37 [-]: FASTCALL1 64 R2 L4; 
      38 [-]: MOVE R4 R2   ; var4 = var2
      39 [-]: GETIMPORT R3 16; var3 = 0x7B998233
      40 [-]: CALL R3 2 2  ; var3 = var3(var4)
L 4:  41 [-]: JUMPIF R3 L5 ; goto L5 if var3
      42 [-]: NAMECALL R3 R2 K21; var4 = var2; var3 = var2[0xA2880940]
      43 [-]: CALL R3 2 1  ; var3(var4)
L 5:  44 [-]: RETURN R0 0  ; 


; Name:            
; Defined at line: 357
; #Upvalues:       6
; #Parameters:     2
; Is_vararg:       0
; Max Stack Size:  10

       0 [-]: GETUPVAL R2 0; var2 = upvalues[0]
       1 [-]: CALL R2 1 2  ; var2 = var2()
       2 [-]: GETIMPORT R5 1; var5 = 0x4C096771
       3 [-]: GETIMPORT R6 3; var6 = EMPTY_SYMBOL
       4 [-]: NAMECALL R3 R2 K4; var4 = var2; var3 = var2[0x47901F07]
       5 [-]: CALL R3 4 2  ; var3 = var3(var4, var5, var6)
       6 [-]: GETIMPORT R6 6; var6 = 0x0469F296
       7 [-]: LOADK R7 K7  ; var7 = "YareliComicMarker"
       8 [-]: CALL R6 2 0  ; var6, ... = var6(var7)
       9 [-]: NAMECALL R4 R3 K8; var5 = var3; var4 = var3[0x3273BA96]
      10 [-]: CALL R4 0 1  ; var4(var5, ...)
      11 [-]: GETIMPORT R6 10; var6 = gContextActionType
      12 [-]: NAMECALL R4 R2 K11; var5 = var2; var4 = var2[0xC9F6A7D7]
      13 [-]: CALL R4 3 2  ; var4 = var4(var5, var6)
      14 [-]: GETIMPORT R5 13; var5 = 0x11A19C5E
      15 [-]: MOVE R6 R4   ; var6 = var4
      16 [-]: LOADK R7 K14 ; var7 = "OnActivated"
      17 [-]: CALL R5 3 1  ; var5(var6, var7)
      18 [-]: JUMPIFNOT R1 L31; goto L31 if not var1
      19 [-]: GETIMPORT R4 16; var4 = 0x89326C93
      20 [-]: GETUPVAL R6 1; var6 = upvalues[1]
      21 [-]: NAMECALL R4 R4 K17; var5 = var4; var4 = var4[0x46A0EBF5]
      22 [-]: CALL R4 3 2  ; var4 = var4(var5, var6)
L 0:  23 [-]: FASTCALL1 64 R4 L1; 
      24 [-]: MOVE R6 R4   ; var6 = var4
      25 [-]: GETIMPORT R5 19; var5 = 0x7B998233
      26 [-]: CALL R5 2 2  ; var5 = var5(var6)
L 1:  27 [-]: JUMPIFNOT R5 L2; goto L2 if not var5
      28 [-]: GETIMPORT R5 21; var5 = 0xCBD666E1
      29 [-]: LOADN R6 0   ; var6 = 0
      30 [-]: CALL R5 2 1  ; var5(var6)
      31 [-]: GETIMPORT R5 16; var5 = 0x89326C93
      32 [-]: GETUPVAL R7 1; var7 = upvalues[1]
      33 [-]: NAMECALL R5 R5 K17; var6 = var5; var5 = var5[0x46A0EBF5]
      34 [-]: CALL R5 3 2  ; var5 = var5(var6, var7)
      35 [-]: MOVE R4 R5   ; var4 = var5
      36 [-]: JUMPBACK L0  ; goto L0
L 2:  37 [-]: JUMPIFNOT R0 L26; goto L26 if not var0
L 3:  38 [-]: GETUPVAL R5 2; var5 = upvalues[2]
      39 [-]: JUMPIF R5 L26; goto L26 if var5
      40 [-]: FASTCALL1 64 R3 L4; 
      41 [-]: MOVE R6 R3   ; var6 = var3
      42 [-]: GETIMPORT R5 19; var5 = 0x7B998233
      43 [-]: CALL R5 2 2  ; var5 = var5(var6)
L 4:  44 [-]: JUMPIF R5 L26; goto L26 if var5
      45 [-]: FASTCALL1 64 R4 L5; 
      46 [-]: MOVE R6 R4   ; var6 = var4
      47 [-]: GETIMPORT R5 19; var5 = 0x7B998233
      48 [-]: CALL R5 2 2  ; var5 = var5(var6)
L 5:  49 [-]: JUMPIF R5 L26; goto L26 if var5
      50 [-]: GETUPVAL R6 3; var6 = upvalues[3]
      51 [-]: FASTCALL1 64 R6 L6; 
      52 [-]: GETIMPORT R5 19; var5 = 0x7B998233
      53 [-]: CALL R5 2 2  ; var5 = var5(var6)
L 6:  54 [-]: JUMPIF R5 L26; goto L26 if var5
      55 [-]: FASTCALL1 64 R2 L7; 
      56 [-]: MOVE R6 R2   ; var6 = var2
      57 [-]: GETIMPORT R5 19; var5 = 0x7B998233
      58 [-]: CALL R5 2 2  ; var5 = var5(var6)
L 7:  59 [-]: JUMPIF R5 L26; goto L26 if var5
      60 [-]: GETUPVAL R6 3; var6 = upvalues[3]
      61 [-]: FASTCALL1 64 R6 L8; 
      62 [-]: MOVE R8 R6   ; var8 = var6
      63 [-]: GETIMPORT R7 19; var7 = 0x7B998233
      64 [-]: CALL R7 2 2  ; var7 = var7(var8)
L 8:  65 [-]: JUMPIF R7 L10; goto L10 if var7
      66 [-]: FASTCALL1 64 R2 L9; 
      67 [-]: MOVE R8 R2   ; var8 = var2
      68 [-]: GETIMPORT R7 19; var7 = 0x7B998233
      69 [-]: CALL R7 2 2  ; var7 = var7(var8)
L 9:  70 [-]: JUMPIFNOT R7 L11; goto L11 if not var7
L10:  71 [-]: LOADB R5 0   ; var5 = false
      72 [-]: JUMP L13     ; goto L13
L11:  73 [-]: NAMECALL R7 R6 K22; var8 = var6; var7 = var6[0xE79E7EF4]
      74 [-]: CALL R7 2 2  ; var7 = var7(var8)
      75 [-]: NAMECALL R8 R2 K22; var9 = var2; var8 = var2[0xE79E7EF4]
      76 [-]: CALL R8 2 2  ; var8 = var8(var9)
      77 [-]: JUMPIFEQ R7 R8 L12; goto L12 if var7 == var16778502
      78 [-]: LOADB R5 0 +1; var5 = false
L12:  79 [-]: LOADB R5 1   ; var5 = true
L13:  80 [-]: JUMPIFNOT R5 L19; goto L19 if not var5
      81 [-]: FASTCALL1 64 R3 L14; 
      82 [-]: MOVE R6 R3   ; var6 = var3
      83 [-]: GETIMPORT R5 19; var5 = 0x7B998233
      84 [-]: CALL R5 2 2  ; var5 = var5(var6)
L14:  85 [-]: JUMPIFNOT R5 L15; goto L15 if not var5
      86 [-]: JUMP L16     ; goto L16
L15:  87 [-]: NAMECALL R5 R3 K23; var6 = var3; var5 = var3[0xF37943FF]
      88 [-]: CALL R5 2 2  ; var5 = var5(var6)
      89 [-]: JUMPIF R5 L16; goto L16 if var5
      90 [-]: NAMECALL R5 R3 K24; var6 = var3; var5 = var3[0x383D2E7D]
      91 [-]: CALL R5 2 1  ; var5(var6)
      92 [-]: JUMP L16     ; goto L16
L16:  93 [-]: MOVE R5 R4   ; var5 = var4
      94 [-]: FASTCALL1 64 R5 L17; 
      95 [-]: MOVE R7 R5   ; var7 = var5
      96 [-]: GETIMPORT R6 19; var6 = 0x7B998233
      97 [-]: CALL R6 2 2  ; var6 = var6(var7)
L17:  98 [-]: JUMPIFNOT R6 L18; goto L18 if not var6
      99 [-]: JUMP L25     ; goto L25
L18: 100 [-]: NAMECALL R6 R5 K23; var7 = var5; var6 = var5[0xF37943FF]
     101 [-]: CALL R6 2 2  ; var6 = var6(var7)
     102 [-]: JUMPIFNOT R6 L25; goto L25 if not var6
     103 [-]: NAMECALL R6 R5 K25; var7 = var5; var6 = var5[0xF4E253B6]
     104 [-]: CALL R6 2 1  ; var6(var7)
     105 [-]: JUMP L25     ; goto L25
L19: 106 [-]: FASTCALL1 64 R3 L20; 
     107 [-]: MOVE R6 R3   ; var6 = var3
     108 [-]: GETIMPORT R5 19; var5 = 0x7B998233
     109 [-]: CALL R5 2 2  ; var5 = var5(var6)
L20: 110 [-]: JUMPIFNOT R5 L21; goto L21 if not var5
     111 [-]: JUMP L22     ; goto L22
L21: 112 [-]: NAMECALL R5 R3 K23; var6 = var3; var5 = var3[0xF37943FF]
     113 [-]: CALL R5 2 2  ; var5 = var5(var6)
     114 [-]: JUMPIFNOT R5 L22; goto L22 if not var5
     115 [-]: NAMECALL R5 R3 K25; var6 = var3; var5 = var3[0xF4E253B6]
     116 [-]: CALL R5 2 1  ; var5(var6)
L22: 117 [-]: MOVE R5 R4   ; var5 = var4
     118 [-]: FASTCALL1 64 R5 L23; 
     119 [-]: MOVE R7 R5   ; var7 = var5
     120 [-]: GETIMPORT R6 19; var6 = 0x7B998233
     121 [-]: CALL R6 2 2  ; var6 = var6(var7)
L23: 122 [-]: JUMPIFNOT R6 L24; goto L24 if not var6
     123 [-]: JUMP L25     ; goto L25
L24: 124 [-]: NAMECALL R6 R5 K23; var7 = var5; var6 = var5[0xF37943FF]
     125 [-]: CALL R6 2 2  ; var6 = var6(var7)
     126 [-]: JUMPIF R6 L25; goto L25 if var6
     127 [-]: NAMECALL R6 R5 K24; var7 = var5; var6 = var5[0x383D2E7D]
     128 [-]: CALL R6 2 1  ; var6(var7)
     129 [-]: JUMP L25     ; goto L25
L25: 130 [-]: GETIMPORT R5 21; var5 = 0xCBD666E1
     131 [-]: LOADN R6 0   ; var6 = 0
     132 [-]: CALL R5 2 1  ; var5(var6)
     133 [-]: JUMPBACK L3  ; goto L3
L26: 134 [-]: MOVE R5 R4   ; var5 = var4
     135 [-]: FASTCALL1 64 R5 L27; 
     136 [-]: MOVE R7 R5   ; var7 = var5
     137 [-]: GETIMPORT R6 19; var6 = 0x7B998233
     138 [-]: CALL R6 2 2  ; var6 = var6(var7)
L27: 139 [-]: JUMPIFNOT R6 L28; goto L28 if not var6
     140 [-]: JUMP L29     ; goto L29
L28: 141 [-]: NAMECALL R6 R5 K23; var7 = var5; var6 = var5[0xF37943FF]
     142 [-]: CALL R6 2 2  ; var6 = var6(var7)
     143 [-]: JUMPIFNOT R6 L29; goto L29 if not var6
     144 [-]: NAMECALL R6 R5 K25; var7 = var5; var6 = var5[0xF4E253B6]
     145 [-]: CALL R6 2 1  ; var6(var7)
L29: 146 [-]: FASTCALL1 64 R3 L30; 
     147 [-]: MOVE R6 R3   ; var6 = var3
     148 [-]: GETIMPORT R5 19; var5 = 0x7B998233
     149 [-]: CALL R5 2 2  ; var5 = var5(var6)
L30: 150 [-]: JUMPIF R5 L80; goto L80 if var5
     151 [-]: NAMECALL R5 R3 K26; var6 = var3; var5 = var3[0xA2880940]
     152 [-]: CALL R5 2 1  ; var5(var6)
     153 [-]: RETURN R0 0  ; 
L31: 154 [-]: GETIMPORT R4 16; var4 = 0x89326C93
     155 [-]: GETUPVAL R6 4; var6 = upvalues[4]
     156 [-]: NAMECALL R4 R4 K17; var5 = var4; var4 = var4[0x46A0EBF5]
     157 [-]: CALL R4 3 2  ; var4 = var4(var5, var6)
L32: 158 [-]: FASTCALL1 64 R4 L33; 
     159 [-]: MOVE R6 R4   ; var6 = var4
     160 [-]: GETIMPORT R5 19; var5 = 0x7B998233
     161 [-]: CALL R5 2 2  ; var5 = var5(var6)
L33: 162 [-]: JUMPIFNOT R5 L34; goto L34 if not var5
     163 [-]: GETIMPORT R5 21; var5 = 0xCBD666E1
     164 [-]: LOADN R6 0   ; var6 = 0
     165 [-]: CALL R5 2 1  ; var5(var6)
     166 [-]: GETIMPORT R5 16; var5 = 0x89326C93
     167 [-]: GETUPVAL R7 4; var7 = upvalues[4]
     168 [-]: NAMECALL R5 R5 K17; var6 = var5; var5 = var5[0x46A0EBF5]
     169 [-]: CALL R5 3 2  ; var5 = var5(var6, var7)
     170 [-]: MOVE R4 R5   ; var4 = var5
     171 [-]: JUMPBACK L32 ; goto L32
L34: 172 [-]: JUMPIFNOT R0 L58; goto L58 if not var0
L35: 173 [-]: GETUPVAL R5 2; var5 = upvalues[2]
     174 [-]: JUMPIF R5 L58; goto L58 if var5
     175 [-]: FASTCALL1 64 R3 L36; 
     176 [-]: MOVE R6 R3   ; var6 = var3
     177 [-]: GETIMPORT R5 19; var5 = 0x7B998233
     178 [-]: CALL R5 2 2  ; var5 = var5(var6)
L36: 179 [-]: JUMPIF R5 L58; goto L58 if var5
     180 [-]: FASTCALL1 64 R4 L37; 
     181 [-]: MOVE R6 R4   ; var6 = var4
     182 [-]: GETIMPORT R5 19; var5 = 0x7B998233
     183 [-]: CALL R5 2 2  ; var5 = var5(var6)
L37: 184 [-]: JUMPIF R5 L58; goto L58 if var5
     185 [-]: GETUPVAL R6 3; var6 = upvalues[3]
     186 [-]: FASTCALL1 64 R6 L38; 
     187 [-]: GETIMPORT R5 19; var5 = 0x7B998233
     188 [-]: CALL R5 2 2  ; var5 = var5(var6)
L38: 189 [-]: JUMPIF R5 L58; goto L58 if var5
     190 [-]: FASTCALL1 64 R2 L39; 
     191 [-]: MOVE R6 R2   ; var6 = var2
     192 [-]: GETIMPORT R5 19; var5 = 0x7B998233
     193 [-]: CALL R5 2 2  ; var5 = var5(var6)
L39: 194 [-]: JUMPIF R5 L58; goto L58 if var5
     195 [-]: GETUPVAL R6 3; var6 = upvalues[3]
     196 [-]: FASTCALL1 64 R6 L40; 
     197 [-]: MOVE R8 R6   ; var8 = var6
     198 [-]: GETIMPORT R7 19; var7 = 0x7B998233
     199 [-]: CALL R7 2 2  ; var7 = var7(var8)
L40: 200 [-]: JUMPIF R7 L42; goto L42 if var7
     201 [-]: FASTCALL1 64 R2 L41; 
     202 [-]: MOVE R8 R2   ; var8 = var2
     203 [-]: GETIMPORT R7 19; var7 = 0x7B998233
     204 [-]: CALL R7 2 2  ; var7 = var7(var8)
L41: 205 [-]: JUMPIFNOT R7 L43; goto L43 if not var7
L42: 206 [-]: LOADB R5 0   ; var5 = false
     207 [-]: JUMP L45     ; goto L45
L43: 208 [-]: NAMECALL R7 R6 K22; var8 = var6; var7 = var6[0xE79E7EF4]
     209 [-]: CALL R7 2 2  ; var7 = var7(var8)
     210 [-]: NAMECALL R8 R2 K22; var9 = var2; var8 = var2[0xE79E7EF4]
     211 [-]: CALL R8 2 2  ; var8 = var8(var9)
     212 [-]: JUMPIFEQ R7 R8 L44; goto L44 if var7 == var16778502
     213 [-]: LOADB R5 0 +1; var5 = false
L44: 214 [-]: LOADB R5 1   ; var5 = true
L45: 215 [-]: JUMPIFNOT R5 L51; goto L51 if not var5
     216 [-]: FASTCALL1 64 R3 L46; 
     217 [-]: MOVE R6 R3   ; var6 = var3
     218 [-]: GETIMPORT R5 19; var5 = 0x7B998233
     219 [-]: CALL R5 2 2  ; var5 = var5(var6)
L46: 220 [-]: JUMPIFNOT R5 L47; goto L47 if not var5
     221 [-]: JUMP L48     ; goto L48
L47: 222 [-]: NAMECALL R5 R3 K23; var6 = var3; var5 = var3[0xF37943FF]
     223 [-]: CALL R5 2 2  ; var5 = var5(var6)
     224 [-]: JUMPIF R5 L48; goto L48 if var5
     225 [-]: NAMECALL R5 R3 K24; var6 = var3; var5 = var3[0x383D2E7D]
     226 [-]: CALL R5 2 1  ; var5(var6)
     227 [-]: JUMP L48     ; goto L48
L48: 228 [-]: MOVE R5 R4   ; var5 = var4
     229 [-]: FASTCALL1 64 R5 L49; 
     230 [-]: MOVE R7 R5   ; var7 = var5
     231 [-]: GETIMPORT R6 19; var6 = 0x7B998233
     232 [-]: CALL R6 2 2  ; var6 = var6(var7)
L49: 233 [-]: JUMPIFNOT R6 L50; goto L50 if not var6
     234 [-]: JUMP L57     ; goto L57
L50: 235 [-]: NAMECALL R6 R5 K23; var7 = var5; var6 = var5[0xF37943FF]
     236 [-]: CALL R6 2 2  ; var6 = var6(var7)
     237 [-]: JUMPIFNOT R6 L57; goto L57 if not var6
     238 [-]: NAMECALL R6 R5 K25; var7 = var5; var6 = var5[0xF4E253B6]
     239 [-]: CALL R6 2 1  ; var6(var7)
     240 [-]: JUMP L57     ; goto L57
L51: 241 [-]: FASTCALL1 64 R3 L52; 
     242 [-]: MOVE R6 R3   ; var6 = var3
     243 [-]: GETIMPORT R5 19; var5 = 0x7B998233
     244 [-]: CALL R5 2 2  ; var5 = var5(var6)
L52: 245 [-]: JUMPIFNOT R5 L53; goto L53 if not var5
     246 [-]: JUMP L54     ; goto L54
L53: 247 [-]: NAMECALL R5 R3 K23; var6 = var3; var5 = var3[0xF37943FF]
     248 [-]: CALL R5 2 2  ; var5 = var5(var6)
     249 [-]: JUMPIFNOT R5 L54; goto L54 if not var5
     250 [-]: NAMECALL R5 R3 K25; var6 = var3; var5 = var3[0xF4E253B6]
     251 [-]: CALL R5 2 1  ; var5(var6)
L54: 252 [-]: MOVE R5 R4   ; var5 = var4
     253 [-]: FASTCALL1 64 R5 L55; 
     254 [-]: MOVE R7 R5   ; var7 = var5
     255 [-]: GETIMPORT R6 19; var6 = 0x7B998233
     256 [-]: CALL R6 2 2  ; var6 = var6(var7)
L55: 257 [-]: JUMPIFNOT R6 L56; goto L56 if not var6
     258 [-]: JUMP L57     ; goto L57
L56: 259 [-]: NAMECALL R6 R5 K23; var7 = var5; var6 = var5[0xF37943FF]
     260 [-]: CALL R6 2 2  ; var6 = var6(var7)
     261 [-]: JUMPIF R6 L57; goto L57 if var6
     262 [-]: NAMECALL R6 R5 K24; var7 = var5; var6 = var5[0x383D2E7D]
     263 [-]: CALL R6 2 1  ; var6(var7)
     264 [-]: JUMP L57     ; goto L57
L57: 265 [-]: GETIMPORT R5 21; var5 = 0xCBD666E1
     266 [-]: LOADN R6 0   ; var6 = 0
     267 [-]: CALL R5 2 1  ; var5(var6)
     268 [-]: JUMPBACK L35 ; goto L35
L58: 269 [-]: FASTCALL1 64 R3 L59; 
     270 [-]: MOVE R6 R3   ; var6 = var3
     271 [-]: GETIMPORT R5 19; var5 = 0x7B998233
     272 [-]: CALL R5 2 2  ; var5 = var5(var6)
L59: 273 [-]: JUMPIF R5 L60; goto L60 if var5
     274 [-]: NAMECALL R5 R3 K26; var6 = var3; var5 = var3[0xA2880940]
     275 [-]: CALL R5 2 1  ; var5(var6)
L60: 276 [-]: GETIMPORT R6 28; var6 = 0xBE190284
     277 [-]: GETIMPORT R8 30; var8 = gLotusHubGameRulesType
     278 [-]: NAMECALL R6 R6 K31; var7 = var6; var6 = var6[0xF2DEAF69]
     279 [-]: CALL R6 3 2  ; var6 = var6(var7, var8)
     280 [-]: JUMPIFNOT R6 L63; goto L63 if not var6
     281 [-]: GETIMPORT R7 28; var7 = 0xBE190284
     282 [-]: NAMECALL R7 R7 K32; var8 = var7; var7 = var7[0xEF893AEC]
     283 [-]: CALL R7 2 2  ; var7 = var7(var8)
     284 [-]: GETTABLEKS R6 R7 K33; var6 = var7["location"]
     285 [-]: GETUPVAL R8 5; var8 = upvalues[5]
     286 [-]: GETTABLEKS R7 R8 K34; var7 = var8["FORTUNA_NODE_TAG"]
     287 [-]: JUMPIFEQ R6 R7 L61; goto L61 if var6 == var16778502
     288 [-]: LOADB R5 0 +1; var5 = false
L61: 289 [-]: LOADB R5 1   ; var5 = true
L62: 290 [-]: JUMP L64     ; goto L64
L63: 291 [-]: LOADB R5 0   ; var5 = false
L64: 292 [-]: JUMPIFNOT R5 L80; goto L80 if not var5
     293 [-]: FASTCALL1 64 R4 L65; 
     294 [-]: MOVE R6 R4   ; var6 = var4
     295 [-]: GETIMPORT R5 19; var5 = 0x7B998233
     296 [-]: CALL R5 2 2  ; var5 = var5(var6)
L65: 297 [-]: JUMPIF R5 L80; goto L80 if var5
     298 [-]: GETUPVAL R6 3; var6 = upvalues[3]
     299 [-]: FASTCALL1 64 R6 L66; 
     300 [-]: GETIMPORT R5 19; var5 = 0x7B998233
     301 [-]: CALL R5 2 2  ; var5 = var5(var6)
L66: 302 [-]: JUMPIF R5 L80; goto L80 if var5
     303 [-]: FASTCALL1 64 R2 L67; 
     304 [-]: MOVE R6 R2   ; var6 = var2
     305 [-]: GETIMPORT R5 19; var5 = 0x7B998233
     306 [-]: CALL R5 2 2  ; var5 = var5(var6)
L67: 307 [-]: JUMPIF R5 L80; goto L80 if var5
     308 [-]: GETUPVAL R6 3; var6 = upvalues[3]
     309 [-]: FASTCALL1 64 R6 L68; 
     310 [-]: MOVE R8 R6   ; var8 = var6
     311 [-]: GETIMPORT R7 19; var7 = 0x7B998233
     312 [-]: CALL R7 2 2  ; var7 = var7(var8)
L68: 313 [-]: JUMPIF R7 L70; goto L70 if var7
     314 [-]: FASTCALL1 64 R2 L69; 
     315 [-]: MOVE R8 R2   ; var8 = var2
     316 [-]: GETIMPORT R7 19; var7 = 0x7B998233
     317 [-]: CALL R7 2 2  ; var7 = var7(var8)
L69: 318 [-]: JUMPIFNOT R7 L71; goto L71 if not var7
L70: 319 [-]: LOADB R5 0   ; var5 = false
     320 [-]: JUMP L73     ; goto L73
L71: 321 [-]: NAMECALL R7 R6 K22; var8 = var6; var7 = var6[0xE79E7EF4]
     322 [-]: CALL R7 2 2  ; var7 = var7(var8)
     323 [-]: NAMECALL R8 R2 K22; var9 = var2; var8 = var2[0xE79E7EF4]
     324 [-]: CALL R8 2 2  ; var8 = var8(var9)
     325 [-]: JUMPIFEQ R7 R8 L72; goto L72 if var7 == var16778502
     326 [-]: LOADB R5 0 +1; var5 = false
L72: 327 [-]: LOADB R5 1   ; var5 = true
L73: 328 [-]: JUMPIFNOT R5 L76; goto L76 if not var5
     329 [-]: MOVE R5 R4   ; var5 = var4
     330 [-]: FASTCALL1 64 R5 L74; 
     331 [-]: MOVE R7 R5   ; var7 = var5
     332 [-]: GETIMPORT R6 19; var6 = 0x7B998233
     333 [-]: CALL R6 2 2  ; var6 = var6(var7)
L74: 334 [-]: JUMPIFNOT R6 L75; goto L75 if not var6
     335 [-]: JUMP L79     ; goto L79
L75: 336 [-]: NAMECALL R6 R5 K23; var7 = var5; var6 = var5[0xF37943FF]
     337 [-]: CALL R6 2 2  ; var6 = var6(var7)
     338 [-]: JUMPIFNOT R6 L79; goto L79 if not var6
     339 [-]: NAMECALL R6 R5 K25; var7 = var5; var6 = var5[0xF4E253B6]
     340 [-]: CALL R6 2 1  ; var6(var7)
     341 [-]: JUMP L79     ; goto L79
L76: 342 [-]: MOVE R5 R4   ; var5 = var4
     343 [-]: FASTCALL1 64 R5 L77; 
     344 [-]: MOVE R7 R5   ; var7 = var5
     345 [-]: GETIMPORT R6 19; var6 = 0x7B998233
     346 [-]: CALL R6 2 2  ; var6 = var6(var7)
L77: 347 [-]: JUMPIFNOT R6 L78; goto L78 if not var6
     348 [-]: JUMP L79     ; goto L79
L78: 349 [-]: NAMECALL R6 R5 K23; var7 = var5; var6 = var5[0xF37943FF]
     350 [-]: CALL R6 2 2  ; var6 = var6(var7)
     351 [-]: JUMPIF R6 L79; goto L79 if var6
     352 [-]: NAMECALL R6 R5 K24; var7 = var5; var6 = var5[0x383D2E7D]
     353 [-]: CALL R6 2 1  ; var6(var7)
     354 [-]: JUMP L79     ; goto L79
L79: 355 [-]: GETIMPORT R5 21; var5 = 0xCBD666E1
     356 [-]: LOADN R6 0   ; var6 = 0
     357 [-]: CALL R5 2 1  ; var5(var6)
     358 [-]: JUMPBACK L60 ; goto L60
L80: 359 [-]: RETURN R0 0  ; 


; Name:            
; Defined at line: 432
; #Upvalues:       0
; #Parameters:     0
; Is_vararg:       0
; Max Stack Size:  3

       0 [-]: GETIMPORT R2 2; var2 = _T["YareliPagesCompleted"]
       1 [-]: FASTCALL1 64 R2 L0; 
       2 [-]: GETIMPORT R1 4; var1 = 0x7B998233
       3 [-]: CALL R1 2 2  ; var1 = var1(var2)
L 0:   4 [-]: NOT R0 R1    ; var0 = not var1
       5 [-]: JUMPIFNOT R0 L2; goto L2 if not var0
       6 [-]: GETIMPORT R1 2; var1 = _T["YareliPagesCompleted"]
       7 [-]: GETIMPORT R2 6; var2 = 0x52DA7F05
       8 [-]: JUMPIFLE R2 R1 L1; goto L1 if var2 <= var16777222
       9 [-]: LOADB R0 0 +1; var0 = false
L 1:  10 [-]: LOADB R0 1   ; var0 = true
L 2:  11 [-]: RETURN R0 1  ; 


; Name:            
; Defined at line: 436
; #Upvalues:       3
; #Parameters:     1
; Is_vararg:       0
; Max Stack Size:  6

       0 [-]: GETUPVAL R1 0; var1 = upvalues[0]
       1 [-]: CALL R1 1 2  ; var1 = var1()
       2 [-]: GETIMPORT R2 1; var2 = 0x89326C93
       3 [-]: GETUPVAL R4 1; var4 = upvalues[1]
       4 [-]: NAMECALL R2 R2 K2; var3 = var2; var2 = var2[0x46A0EBF5]
       5 [-]: CALL R2 3 2  ; var2 = var2(var3, var4)
       6 [-]: JUMPIFNOT R0 L3; goto L3 if not var0
       7 [-]: FASTCALL1 64 R2 L0; 
       8 [-]: MOVE R4 R2   ; var4 = var2
       9 [-]: GETIMPORT R3 4; var3 = 0x7B998233
      10 [-]: CALL R3 2 2  ; var3 = var3(var4)
L 0:  11 [-]: JUMPIF R3 L1 ; goto L1 if var3
      12 [-]: GETUPVAL R5 2; var5 = upvalues[2]
      13 [-]: NAMECALL R3 R2 K5; var4 = var2; var3 = var2[0xC9F6A7D7]
      14 [-]: CALL R3 3 2  ; var3 = var3(var4, var5)
      15 [-]: NAMECALL R3 R3 K6; var4 = var3; var3 = var3[0x383D2E7D]
      16 [-]: CALL R3 2 1  ; var3(var4)
L 1:  17 [-]: FASTCALL1 64 R1 L2; 
      18 [-]: MOVE R4 R1   ; var4 = var1
      19 [-]: GETIMPORT R3 4; var3 = 0x7B998233
      20 [-]: CALL R3 2 2  ; var3 = var3(var4)
L 2:  21 [-]: JUMPIF R3 L7 ; goto L7 if var3
      22 [-]: GETIMPORT R5 8; var5 = gContextActionType
      23 [-]: NAMECALL R3 R1 K5; var4 = var1; var3 = var1[0xC9F6A7D7]
      24 [-]: CALL R3 3 2  ; var3 = var3(var4, var5)
      25 [-]: NAMECALL R3 R3 K6; var4 = var3; var3 = var3[0x383D2E7D]
      26 [-]: CALL R3 2 1  ; var3(var4)
      27 [-]: RETURN R0 0  ; 
L 3:  28 [-]: FASTCALL1 64 R2 L4; 
      29 [-]: MOVE R4 R2   ; var4 = var2
      30 [-]: GETIMPORT R3 4; var3 = 0x7B998233
      31 [-]: CALL R3 2 2  ; var3 = var3(var4)
L 4:  32 [-]: JUMPIF R3 L5 ; goto L5 if var3
      33 [-]: GETUPVAL R5 2; var5 = upvalues[2]
      34 [-]: NAMECALL R3 R2 K5; var4 = var2; var3 = var2[0xC9F6A7D7]
      35 [-]: CALL R3 3 2  ; var3 = var3(var4, var5)
      36 [-]: NAMECALL R3 R3 K9; var4 = var3; var3 = var3[0xF4E253B6]
      37 [-]: CALL R3 2 1  ; var3(var4)
L 5:  38 [-]: FASTCALL1 64 R1 L6; 
      39 [-]: MOVE R4 R1   ; var4 = var1
      40 [-]: GETIMPORT R3 4; var3 = 0x7B998233
      41 [-]: CALL R3 2 2  ; var3 = var3(var4)
L 6:  42 [-]: JUMPIF R3 L7 ; goto L7 if var3
      43 [-]: GETIMPORT R5 8; var5 = gContextActionType
      44 [-]: NAMECALL R3 R1 K5; var4 = var1; var3 = var1[0xC9F6A7D7]
      45 [-]: CALL R3 3 2  ; var3 = var3(var4, var5)
      46 [-]: NAMECALL R3 R3 K9; var4 = var3; var3 = var3[0xF4E253B6]
      47 [-]: CALL R3 2 1  ; var3(var4)
L 7:  48 [-]: RETURN R0 0  ; 


; Name:            
; Defined at line: 458
; #Upvalues:       4
; #Parameters:     0
; Is_vararg:       0
; Max Stack Size:  6

       0 [-]: GETUPVAL R0 0; var0 = upvalues[0]
       1 [-]: CALL R0 1 2  ; var0 = var0()
       2 [-]: GETUPVAL R1 1; var1 = upvalues[1]
       3 [-]: LOADB R2 0   ; var2 = false
       4 [-]: CALL R1 2 1  ; var1(var2)
       5 [-]: GETIMPORT R1 1; var1 = 0xCBD666E1
       6 [-]: LOADN R2 1   ; var2 = 1
       7 [-]: CALL R1 2 1  ; var1(var2)
L 0:   8 [-]: GETUPVAL R2 2; var2 = upvalues[2]
       9 [-]: GETTABLEKS R1 R2 K2; var1 = var2[0x0DEACD54]
      10 [-]: CALL R1 1 2  ; var1 = var1()
      11 [-]: JUMPIFNOT R1 L8; goto L8 if not var1
      12 [-]: GETIMPORT R1 1; var1 = 0xCBD666E1
      13 [-]: LOADN R2 0   ; var2 = 0
      14 [-]: CALL R1 2 1  ; var1(var2)
      15 [-]: GETUPVAL R2 3; var2 = upvalues[3]
      16 [-]: FASTCALL1 64 R2 L1; 
      17 [-]: MOVE R4 R2   ; var4 = var2
      18 [-]: GETIMPORT R3 4; var3 = 0x7B998233
      19 [-]: CALL R3 2 2  ; var3 = var3(var4)
L 1:  20 [-]: JUMPIF R3 L3 ; goto L3 if var3
      21 [-]: FASTCALL1 64 R0 L2; 
      22 [-]: MOVE R4 R0   ; var4 = var0
      23 [-]: GETIMPORT R3 4; var3 = 0x7B998233
      24 [-]: CALL R3 2 2  ; var3 = var3(var4)
L 2:  25 [-]: JUMPIFNOT R3 L4; goto L4 if not var3
L 3:  26 [-]: LOADB R1 0   ; var1 = false
      27 [-]: JUMP L6      ; goto L6
L 4:  28 [-]: NAMECALL R3 R2 K5; var4 = var2; var3 = var2[0xE79E7EF4]
      29 [-]: CALL R3 2 2  ; var3 = var3(var4)
      30 [-]: NAMECALL R4 R0 K5; var5 = var0; var4 = var0[0xE79E7EF4]
      31 [-]: CALL R4 2 2  ; var4 = var4(var5)
      32 [-]: JUMPIFEQ R3 R4 L5; goto L5 if var3 == var16777478
      33 [-]: LOADB R1 0 +1; var1 = false
L 5:  34 [-]: LOADB R1 1   ; var1 = true
L 6:  35 [-]: JUMPIF R1 L7 ; goto L7 if var1
      36 [-]: GETUPVAL R2 2; var2 = upvalues[2]
      37 [-]: GETTABLEKS R1 R2 K6; var1 = var2[0xFE0D9469]
      38 [-]: CALL R1 1 1  ; var1()
L 7:  39 [-]: JUMPBACK L0  ; goto L0
L 8:  40 [-]: GETUPVAL R1 1; var1 = upvalues[1]
      41 [-]: LOADB R2 1   ; var2 = true
      42 [-]: CALL R1 2 1  ; var1(var2)
      43 [-]: RETURN R0 0  ; 


; Name:            
; Defined at line: 478
; #Upvalues:       9
; #Parameters:     0
; Is_vararg:       0
; Max Stack Size:  11

       0 [-]: GETIMPORT R0 1; var0 = 0x5E34E0F9
       1 [-]: JUMPIFNOT R0 L0; goto L0 if not var0
       2 [-]: GETUPVAL R0 0; var0 = upvalues[0]
       3 [-]: CALL R0 1 1  ; var0()
       4 [-]: GETUPVAL R0 1; var0 = upvalues[1]
       5 [-]: CALL R0 1 1  ; var0()
L 0:   6 [-]: GETIMPORT R0 3; var0 = 0xC8802016
       7 [-]: GETIMPORT R1 5; var1 = 0xCDEB224C
       8 [-]: CALL R0 2 4  ; var0, var1, var2 = var0(var1)
       9 [-]: FORGPREP_INEXT R0 L2; 
L 1:  10 [-]: GETIMPORT R5 7; var5 = 0xBA7DFCD2
      11 [-]: GETIMPORT R7 9; var7 = 0x89326C93
      12 [-]: GETIMPORT R9 11; var9 = 0x88EFC25E
      13 [-]: MOVE R10 R4  ; var10 = var4
      14 [-]: CALL R9 2 0  ; var9, ... = var9(var10)
      15 [-]: NAMECALL R7 R7 K12; var8 = var7; var7 = var7[0x765DAD71]
      16 [-]: CALL R7 0 0  ; var7, ... = var7(var8, ...)
      17 [-]: NAMECALL R5 R5 K13; var6 = var5; var5 = var5[0x9252175F]
      18 [-]: CALL R5 0 1  ; var5(var6, ...)
L 2:  19 [-]: FORGLOOP R0 L1 2 [inext]; 
      20 [-]: GETIMPORT R0 15; var0 = _T
      21 [-]: GETIMPORT R1 5; var1 = 0xCDEB224C
      22 [-]: SETTABLEKS R1 R0 K16; var1["CurrentYareliChallenges"] = var0
      23 [-]: GETIMPORT R0 15; var0 = _T
      24 [-]: GETIMPORT R1 18; var1 = 0x52DA7F05
      25 [-]: SETTABLEKS R1 R0 K19; var1["CurrentYareliPage"] = var0
      26 [-]: GETUPVAL R1 2; var1 = upvalues[2]
      27 [-]: CALL R1 1 2  ; var1 = var1()
      28 [-]: GETIMPORT R3 5; var3 = 0xCDEB224C
      29 [-]: LENGTH R2 R3 ; var2 = #var3
      30 [-]: JUMPIFLE R2 R1 L3; goto L3 if var2 <= var16777222
      31 [-]: LOADB R0 0 +1; var0 = false
L 3:  32 [-]: LOADB R0 1   ; var0 = true
L 4:  33 [-]: MOVE R1 R0   ; var1 = var0
      34 [-]: JUMPIF R1 L7 ; goto L7 if var1
      35 [-]: GETIMPORT R2 21; var2 = _T["YareliPagesCompleted"]
      36 [-]: FASTCALL1 64 R2 L5; 
      37 [-]: GETIMPORT R1 23; var1 = 0x7B998233
      38 [-]: CALL R1 2 2  ; var1 = var1(var2)
L 5:  39 [-]: JUMPIF R1 L7 ; goto L7 if var1
      40 [-]: GETIMPORT R2 18; var2 = 0x52DA7F05
      41 [-]: JUMPXEQKN R2 K24 L6; 
      42 [-]: LOADB R1 0 +1; var1 = false
L 6:  43 [-]: LOADB R1 1   ; var1 = true
L 7:  44 [-]: GETIMPORT R3 26; var3 = 0xBE190284
      45 [-]: GETIMPORT R5 28; var5 = gLotusHubGameRulesType
      46 [-]: NAMECALL R3 R3 K29; var4 = var3; var3 = var3[0xF2DEAF69]
      47 [-]: CALL R3 3 2  ; var3 = var3(var4, var5)
      48 [-]: JUMPIFNOT R3 L10; goto L10 if not var3
      49 [-]: GETIMPORT R4 26; var4 = 0xBE190284
      50 [-]: NAMECALL R4 R4 K30; var5 = var4; var4 = var4[0xEF893AEC]
      51 [-]: CALL R4 2 2  ; var4 = var4(var5)
      52 [-]: GETTABLEKS R3 R4 K31; var3 = var4["location"]
      53 [-]: GETUPVAL R5 3; var5 = upvalues[3]
      54 [-]: GETTABLEKS R4 R5 K32; var4 = var5["FORTUNA_NODE_TAG"]
      55 [-]: JUMPIFEQ R3 R4 L8; goto L8 if var3 == var16777734
      56 [-]: LOADB R2 0 +1; var2 = false
L 8:  57 [-]: LOADB R2 1   ; var2 = true
L 9:  58 [-]: JUMP L11     ; goto L11
L10:  59 [-]: LOADB R2 0   ; var2 = false
L11:  60 [-]: JUMPIFNOT R2 L12; goto L12 if not var2
      61 [-]: GETUPVAL R2 4; var2 = upvalues[4]
      62 [-]: MOVE R3 R1   ; var3 = var1
      63 [-]: MOVE R4 R0   ; var4 = var0
      64 [-]: CALL R2 3 1  ; var2(var3, var4)
      65 [-]: JUMP L13     ; goto L13
L12:  66 [-]: GETUPVAL R2 5; var2 = upvalues[5]
      67 [-]: MOVE R3 R1   ; var3 = var1
      68 [-]: CALL R2 2 1  ; var2(var3)
L13:  69 [-]: JUMPIF R0 L14; goto L14 if var0
      70 [-]: RETURN R0 0  ; 
L14:  71 [-]: GETIMPORT R4 21; var4 = _T["YareliPagesCompleted"]
      72 [-]: FASTCALL1 64 R4 L15; 
      73 [-]: GETIMPORT R3 23; var3 = 0x7B998233
      74 [-]: CALL R3 2 2  ; var3 = var3(var4)
L15:  75 [-]: NOT R2 R3    ; var2 = not var3
      76 [-]: JUMPIFNOT R2 L17; goto L17 if not var2
      77 [-]: GETIMPORT R3 21; var3 = _T["YareliPagesCompleted"]
      78 [-]: GETIMPORT R4 18; var4 = 0x52DA7F05
      79 [-]: JUMPIFLE R4 R3 L16; goto L16 if var4 <= var16777734
      80 [-]: LOADB R2 0 +1; var2 = false
L16:  81 [-]: LOADB R2 1   ; var2 = true
L17:  82 [-]: JUMPIF R2 L18; goto L18 if var2
      83 [-]: GETIMPORT R2 34; var2 = 0xCBD666E1
      84 [-]: LOADN R3 1   ; var3 = 1
      85 [-]: CALL R2 2 1  ; var2(var3)
      86 [-]: JUMPBACK L14 ; goto L14
L18:  87 [-]: GETIMPORT R2 36; var2 = 0x9BA7909F
      88 [-]: GETIMPORT R4 38; var4 = 0xDA89A091
      89 [-]: NAMECALL R2 R2 K39; var3 = var2; var2 = var2[0xBCFB64AB]
      90 [-]: CALL R2 3 2  ; var2 = var2(var3, var4)
      91 [-]: SETUPVAL R2 6; upvalues[2] = var6
L19:  92 [-]: GETUPVAL R3 6; var3 = upvalues[6]
      93 [-]: FASTCALL1 64 R3 L20; 
      94 [-]: GETIMPORT R2 23; var2 = 0x7B998233
      95 [-]: CALL R2 2 2  ; var2 = var2(var3)
L20:  96 [-]: JUMPIF R2 L21; goto L21 if var2
      97 [-]: GETIMPORT R2 34; var2 = 0xCBD666E1
      98 [-]: LOADN R3 0   ; var3 = 0
      99 [-]: CALL R2 2 1  ; var2(var3)
     100 [-]: JUMPBACK L19 ; goto L19
L21: 101 [-]: GETIMPORT R2 41; var2 = 0xE91D7466
     102 [-]: GETIMPORT R4 43; var4 = 0x0469F296
     103 [-]: LOADK R6 K44 ; var6 = "Page"
     104 [-]: GETIMPORT R7 18; var7 = 0x52DA7F05
     105 [-]: LOADK R8 K45 ; var8 = "Viewed"
     106 [-]: CONCAT R5 R6 R8; var5 = var6 .. var8
     107 [-]: CALL R4 2 0  ; var4, ... = var4(var5)
     108 [-]: NAMECALL R2 R2 K46; var3 = var2; var2 = var2[0x10C9EEF2]
     109 [-]: CALL R2 0 2  ; var2 = var2(var3, ...)
     110 [-]: GETIMPORT R4 26; var4 = 0xBE190284
     111 [-]: GETIMPORT R6 28; var6 = gLotusHubGameRulesType
     112 [-]: NAMECALL R4 R4 K29; var5 = var4; var4 = var4[0xF2DEAF69]
     113 [-]: CALL R4 3 2  ; var4 = var4(var5, var6)
     114 [-]: JUMPIFNOT R4 L24; goto L24 if not var4
     115 [-]: GETIMPORT R5 26; var5 = 0xBE190284
     116 [-]: NAMECALL R5 R5 K30; var6 = var5; var5 = var5[0xEF893AEC]
     117 [-]: CALL R5 2 2  ; var5 = var5(var6)
     118 [-]: GETTABLEKS R4 R5 K31; var4 = var5["location"]
     119 [-]: GETUPVAL R6 3; var6 = upvalues[3]
     120 [-]: GETTABLEKS R5 R6 K32; var5 = var6["FORTUNA_NODE_TAG"]
     121 [-]: JUMPIFEQ R4 R5 L22; goto L22 if var4 == var16777990
     122 [-]: LOADB R3 0 +1; var3 = false
L22: 123 [-]: LOADB R3 1   ; var3 = true
L23: 124 [-]: JUMP L25     ; goto L25
L24: 125 [-]: LOADB R3 0   ; var3 = false
L25: 126 [-]: JUMPIFNOT R3 L26; goto L26 if not var3
     127 [-]: GETIMPORT R3 41; var3 = 0xE91D7466
     128 [-]: GETIMPORT R5 43; var5 = 0x0469F296
     129 [-]: LOADK R7 K44 ; var7 = "Page"
     130 [-]: GETIMPORT R8 18; var8 = 0x52DA7F05
     131 [-]: LOADK R9 K47 ; var9 = "Viewed_Vent"
     132 [-]: CONCAT R6 R7 R9; var6 = var7 .. var9
     133 [-]: CALL R5 2 0  ; var5, ... = var5(var6)
     134 [-]: NAMECALL R3 R3 K46; var4 = var3; var3 = var3[0x10C9EEF2]
     135 [-]: CALL R3 0 2  ; var3 = var3(var4, ...)
     136 [-]: MOVE R2 R3   ; var2 = var3
L26: 137 [-]: GETUPVAL R4 3; var4 = upvalues[3]
     138 [-]: GETTABLEKS R3 R4 K48; var3 = var4[0x1F60D532]
     139 [-]: MOVE R4 R2   ; var4 = var2
     140 [-]: CALL R3 2 1  ; var3(var4)
     141 [-]: GETUPVAL R4 7; var4 = upvalues[7]
     142 [-]: GETTABLEKS R3 R4 K49; var3 = var4[0xA26220ED]
     143 [-]: GETIMPORT R4 51; var4 = 0xB009BBC6
     144 [-]: GETUPVAL R5 8; var5 = upvalues[8]
     145 [-]: CALL R4 2 2  ; var4 = var4(var5)
     146 [-]: GETIMPORT R5 53; var5 = 0x1E9E5BC8
     147 [-]: CALL R3 3 1  ; var3(var4, var5)
     148 [-]: RETURN R0 0  ; 


; Name:            
; Defined at line: 527
; #Upvalues:       0
; #Parameters:     1
; Is_vararg:       0
; Max Stack Size:  9

       0 [-]: GETIMPORT R1 1; var1 = 0x7ED0A956
       1 [-]: LOADK R2 K2  ; var2 = "/Lotus/Powersuits/Yareli/YareliBaseSuit"
       2 [-]: CALL R1 2 2  ; var1 = var1(var2)
       3 [-]: GETIMPORT R2 1; var2 = 0x7ED0A956
       4 [-]: LOADK R3 K3  ; var3 = "/Lotus/Powersuits/PowersuitAbilities/YareliBoardAbility"
       5 [-]: CALL R2 2 2  ; var2 = var2(var3)
       6 [-]: FASTCALL1 64 R0 L0; 
       7 [-]: MOVE R4 R0   ; var4 = var0
       8 [-]: GETIMPORT R3 5; var3 = 0x7B998233
       9 [-]: CALL R3 2 2  ; var3 = var3(var4)
L 0:  10 [-]: JUMPIF R3 L4 ; goto L4 if var3
      11 [-]: NAMECALL R3 R0 K6; var4 = var0; var3 = var0[0xDE321E6F]
      12 [-]: CALL R3 2 2  ; var3 = var3(var4)
      13 [-]: FASTCALL1 64 R3 L1; 
      14 [-]: MOVE R5 R3   ; var5 = var3
      15 [-]: GETIMPORT R4 5; var4 = 0x7B998233
      16 [-]: CALL R4 2 2  ; var4 = var4(var5)
L 1:  17 [-]: JUMPIF R4 L4 ; goto L4 if var4
      18 [-]: NAMECALL R4 R3 K7; var5 = var3; var4 = var3[0xF7D48EE0]
      19 [-]: CALL R4 2 2  ; var4 = var4(var5)
      20 [-]: FASTCALL1 64 R4 L2; 
      21 [-]: MOVE R6 R4   ; var6 = var4
      22 [-]: GETIMPORT R5 5; var5 = 0x7B998233
      23 [-]: CALL R5 2 2  ; var5 = var5(var6)
L 2:  24 [-]: JUMPIF R5 L4 ; goto L4 if var5
      25 [-]: MOVE R7 R1   ; var7 = var1
      26 [-]: NAMECALL R5 R4 K8; var6 = var4; var5 = var4[0xF2DEAF69]
      27 [-]: CALL R5 3 2  ; var5 = var5(var6, var7)
      28 [-]: JUMPIFNOT R5 L4; goto L4 if not var5
      29 [-]: MOVE R8 R2   ; var8 = var2
      30 [-]: NAMECALL R6 R4 K9; var7 = var4; var6 = var4[0x689412A5]
      31 [-]: CALL R6 3 0  ; var6, ... = var6(var7, var8)
      32 [-]: FASTCALL 64 L3; 
      33 [-]: GETIMPORT R5 5; var5 = 0x7B998233
      34 [-]: CALL R5 0 2  ; var5 = var5(var6, ...)
L 3:  35 [-]: JUMPIF R5 L4 ; goto L4 if var5
      36 [-]: LOADB R5 1   ; var5 = true
      37 [-]: RETURN R5 1  ; 
L 4:  38 [-]: LOADB R3 0   ; var3 = false
      39 [-]: RETURN R3 1  ; 


; Name:            
; Defined at line: 548
; #Upvalues:       3
; #Parameters:     0
; Is_vararg:       0
; Max Stack Size:  13

L 0:   0 [-]: GETIMPORT R1 1; var1 = 0xBE190284
       1 [-]: FASTCALL1 64 R1 L1; 
       2 [-]: GETIMPORT R0 3; var0 = 0x7B998233
       3 [-]: CALL R0 2 2  ; var0 = var0(var1)
L 1:   4 [-]: JUMPIFNOT R0 L2; goto L2 if not var0
       5 [-]: GETIMPORT R0 5; var0 = 0xCBD666E1
       6 [-]: LOADN R1 0   ; var1 = 0
       7 [-]: CALL R0 2 1  ; var0(var1)
       8 [-]: JUMPBACK L0  ; goto L0
L 2:   9 [-]: GETIMPORT R0 7; var0 = 0x89326C93
      10 [-]: NAMECALL R0 R0 K8; var1 = var0; var0 = var0[0xFB64E76C]
      11 [-]: CALL R0 2 2  ; var0 = var0(var1)
      12 [-]: NAMECALL R1 R0 K9; var2 = var0; var1 = var0[0xBB610E5B]
      13 [-]: CALL R1 2 2  ; var1 = var1(var2)
      14 [-]: GETIMPORT R2 12; var2 = _T["InSimulacrum"]
      15 [-]: JUMPIF R2 L3 ; goto L3 if var2
      16 [-]: GETIMPORT R2 1; var2 = 0xBE190284
      17 [-]: NAMECALL R2 R2 K13; var3 = var2; var2 = var2[0x5C390F04]
      18 [-]: CALL R2 2 2  ; var2 = var2(var3)
      19 [-]: LOADN R3 28  ; var3 = 28
      20 [-]: JUMPIFEQ R2 R3 L4; goto L4 if var2 == var572
      21 [-]: GETUPVAL R2 0; var2 = upvalues[0]
      22 [-]: MOVE R3 R1   ; var3 = var1
      23 [-]: CALL R2 2 2  ; var2 = var2(var3)
      24 [-]: JUMPIF R2 L4 ; goto L4 if var2
L 3:  25 [-]: RETURN R0 0  ; 
L 4:  26 [-]: GETIMPORT R2 14; var2 = _T
      27 [-]: GETIMPORT R3 16; var3 = 0xCDEB224C
      28 [-]: SETTABLEKS R3 R2 K17; var3["CurrentYareliChallenges"] = var2
      29 [-]: GETIMPORT R2 19; var2 = 0xC8802016
      30 [-]: GETIMPORT R3 16; var3 = 0xCDEB224C
      31 [-]: CALL R2 2 4  ; var2, var3, var4 = var2(var3)
      32 [-]: FORGPREP_INEXT R2 L6; 
L 5:  33 [-]: GETIMPORT R7 21; var7 = 0xBA7DFCD2
      34 [-]: GETIMPORT R9 7; var9 = 0x89326C93
      35 [-]: GETIMPORT R11 23; var11 = 0x88EFC25E
      36 [-]: MOVE R12 R6  ; var12 = var6
      37 [-]: CALL R11 2 0 ; var11, ... = var11(var12)
      38 [-]: NAMECALL R9 R9 K24; var10 = var9; var9 = var9[0x765DAD71]
      39 [-]: CALL R9 0 0  ; var9, ... = var9(var10, ...)
      40 [-]: NAMECALL R7 R7 K25; var8 = var7; var7 = var7[0x9252175F]
      41 [-]: CALL R7 0 1  ; var7(var8, ...)
L 6:  42 [-]: FORGLOOP R2 L5 2 [inext]; 
      43 [-]: GETUPVAL R3 1; var3 = upvalues[1]
      44 [-]: CALL R3 1 2  ; var3 = var3()
      45 [-]: GETIMPORT R5 16; var5 = 0xCDEB224C
      46 [-]: LENGTH R4 R5 ; var4 = #var5
      47 [-]: JUMPIFLE R4 R3 L7; goto L7 if var4 <= var16777734
      48 [-]: LOADB R2 0 +1; var2 = false
L 7:  49 [-]: LOADB R2 1   ; var2 = true
L 8:  50 [-]: JUMPIFNOT R2 L9; goto L9 if not var2
      51 [-]: GETIMPORT R2 27; var2 = 0x3D106989
      52 [-]: LOADK R3 K28 ; var3 = "Challenges already complete, not playing completion transmissions"
      53 [-]: CALL R2 2 1  ; var2(var3)
      54 [-]: RETURN R0 0  ; 
L 9:  55 [-]: GETUPVAL R2 1; var2 = upvalues[1]
      56 [-]: CALL R2 1 2  ; var2 = var2()
L10:  57 [-]: GETUPVAL R4 1; var4 = upvalues[1]
      58 [-]: CALL R4 1 2  ; var4 = var4()
      59 [-]: GETIMPORT R6 16; var6 = 0xCDEB224C
      60 [-]: LENGTH R5 R6 ; var5 = #var6
      61 [-]: JUMPIFLE R5 R4 L11; goto L11 if var5 <= var16777990
      62 [-]: LOADB R3 0 +1; var3 = false
L11:  63 [-]: LOADB R3 1   ; var3 = true
L12:  64 [-]: JUMPIF R3 L14; goto L14 if var3
      65 [-]: GETIMPORT R3 5; var3 = 0xCBD666E1
      66 [-]: LOADN R4 3   ; var4 = 3
      67 [-]: CALL R3 2 1  ; var3(var4)
      68 [-]: GETUPVAL R3 1; var3 = upvalues[1]
      69 [-]: CALL R3 1 2  ; var3 = var3()
      70 [-]: JUMPIFNOTLT R2 R3 L13; goto L13 if var2 >= var1049889
      71 [-]: GETIMPORT R5 16; var5 = 0xCDEB224C
      72 [-]: LENGTH R4 R5 ; var4 = #var5
      73 [-]: JUMPIFNOTLT R3 R4 L13; goto L13 if var3 >= var197166
      74 [-]: MOVE R2 R3   ; var2 = var3
      75 [-]: GETIMPORT R4 7; var4 = 0x89326C93
      76 [-]: NAMECALL R4 R4 K29; var5 = var4; var4 = var4[0x78298275]
      77 [-]: CALL R4 2 2  ; var4 = var4(var5)
      78 [-]: GETUPVAL R6 2; var6 = upvalues[2]
      79 [-]: GETTABLEKS R5 R6 K30; var5 = var6[0xF22CFC77]
      80 [-]: GETIMPORT R6 32; var6 = 0xE91D7466
      81 [-]: GETIMPORT R7 34; var7 = 0x0469F296
      82 [-]: LOADK R8 K35 ; var8 = "ChallengeCompleteGeneric"
      83 [-]: CALL R7 2 2  ; var7 = var7(var8)
      84 [-]: MOVE R8 R4   ; var8 = var4
      85 [-]: CALL R5 4 1  ; var5(var6, var7, var8)
L13:  86 [-]: JUMPBACK L10 ; goto L10
L14:  87 [-]: GETIMPORT R3 27; var3 = 0x3D106989
      88 [-]: LOADK R5 K36 ; var5 = "playing Page"
      89 [-]: GETIMPORT R6 38; var6 = 0x52DA7F05
      90 [-]: LOADK R7 K39 ; var7 = "Unlocked transmission"
      91 [-]: CONCAT R4 R5 R7; var4 = var5 .. var7
      92 [-]: CALL R3 2 1  ; var3(var4)
      93 [-]: GETUPVAL R4 2; var4 = upvalues[2]
      94 [-]: GETTABLEKS R3 R4 K30; var3 = var4[0xF22CFC77]
      95 [-]: GETIMPORT R4 32; var4 = 0xE91D7466
      96 [-]: GETIMPORT R5 34; var5 = 0x0469F296
      97 [-]: LOADK R7 K40 ; var7 = "Page"
      98 [-]: GETIMPORT R8 38; var8 = 0x52DA7F05
      99 [-]: LOADK R9 K41 ; var9 = "Unlocked"
     100 [-]: CONCAT R6 R7 R9; var6 = var7 .. var9
     101 [-]: CALL R5 2 2  ; var5 = var5(var6)
     102 [-]: MOVE R6 R1   ; var6 = var1
     103 [-]: CALL R3 4 1  ; var3(var4, var5, var6)
     104 [-]: RETURN R0 0  ; 


; Name:            
; Defined at line: 587
; #Upvalues:       1
; #Parameters:     1
; Is_vararg:       0
; Max Stack Size:  2

       0 [-]: GETUPVAL R1 0; var1 = upvalues[0]
       1 [-]: CALL R1 1 1  ; var1()
       2 [-]: RETURN R0 0  ; 


; Name:            
; Defined at line: 591
; #Upvalues:       0
; #Parameters:     3
; Is_vararg:       0
; Max Stack Size:  7

       0 [-]: MOVE R5 R2   ; var5 = var2
       1 [-]: LOADB R6 1   ; var6 = true
       2 [-]: NAMECALL R3 R0 K0; var4 = var0; var3 = var0[0x768274D6]
       3 [-]: CALL R3 4 1  ; var3(var4, var5, var6)
       4 [-]: JUMPIFNOT R2 L0; goto L0 if not var2
       5 [-]: NAMECALL R3 R1 K1; var4 = var1; var3 = var1[0x383D2E7D]
       6 [-]: CALL R3 2 1  ; var3(var4)
       7 [-]: RETURN R0 0  ; 
L 0:   8 [-]: NAMECALL R3 R1 K2; var4 = var1; var3 = var1[0xF4E253B6]
       9 [-]: CALL R3 2 1  ; var3(var4)
      10 [-]: RETURN R0 0  ; 


; Name:            
; Defined at line: 600
; #Upvalues:       0
; #Parameters:     1
; Is_vararg:       0
; Max Stack Size:  3

       0 [-]: LOADB R1 0   ; var1 = false
       1 [-]: LOADN R2 1   ; var2 = 1
       2 [-]: JUMPIFNOTLT R2 R0 L1; goto L1 if var2 >= var524848
       3 [-]: LOADN R2 8   ; var2 = 8
       4 [-]: JUMPIFLT R0 R2 L0; goto L0 if var0 < var16777478
       5 [-]: LOADB R1 0 +1; var1 = false
L 0:   6 [-]: LOADB R1 1   ; var1 = true
L 1:   7 [-]: RETURN R1 1  ; 


; Name:            
; Defined at line: 604
; #Upvalues:       3
; #Parameters:     1
; Is_vararg:       0
; Max Stack Size:  10

L 0:   0 [-]: GETIMPORT R2 1; var2 = 0x25D99D89
       1 [-]: FASTCALL1 64 R2 L1; 
       2 [-]: GETIMPORT R1 3; var1 = 0x7B998233
       3 [-]: CALL R1 2 2  ; var1 = var1(var2)
L 1:   4 [-]: JUMPIFNOT R1 L2; goto L2 if not var1
       5 [-]: GETIMPORT R1 5; var1 = 0xCBD666E1
       6 [-]: LOADN R2 0   ; var2 = 0
       7 [-]: CALL R1 2 1  ; var1(var2)
       8 [-]: JUMPBACK L0  ; goto L0
L 2:   9 [-]: GETIMPORT R1 7; var1 = 0x5E34E0F9
      10 [-]: JUMPIFNOT R1 L3; goto L3 if not var1
      11 [-]: GETUPVAL R1 0; var1 = upvalues[0]
      12 [-]: CALL R1 1 1  ; var1()
L 3:  13 [-]: GETIMPORT R1 1; var1 = 0x25D99D89
      14 [-]: NAMECALL R1 R1 K8; var2 = var1; var1 = var1[0x25A6E75E]
      15 [-]: CALL R1 2 2  ; var1 = var1(var2)
      16 [-]: NAMECALL R3 R1 K9; var4 = var1; var3 = var1[0x8E7C3B5E]
      17 [-]: CALL R3 2 2  ; var3 = var3(var4)
      18 [-]: GETUPVAL R4 1; var4 = upvalues[1]
      19 [-]: JUMPIFEQ R3 R4 L4; goto L4 if var3 == var16777734
      20 [-]: LOADB R2 0 +1; var2 = false
L 4:  21 [-]: LOADB R2 1   ; var2 = true
L 5:  22 [-]: GETUPVAL R4 2; var4 = upvalues[2]
      23 [-]: GETTABLEKS R3 R4 K10; var3 = var4[0xE77C9F88]
      24 [-]: GETUPVAL R4 1; var4 = upvalues[1]
      25 [-]: CALL R3 2 2  ; var3 = var3(var4)
      26 [-]: GETUPVAL R5 2; var5 = upvalues[2]
      27 [-]: GETTABLEKS R4 R5 K11; var4 = var5[0xBDF58098]
      28 [-]: GETUPVAL R5 1; var5 = upvalues[1]
      29 [-]: CALL R4 2 2  ; var4 = var4(var5)
      30 [-]: JUMPIF R4 L6 ; goto L6 if var4
      31 [-]: RETURN R0 0  ; 
L 6:  32 [-]: GETIMPORT R4 5; var4 = 0xCBD666E1
      33 [-]: LOADN R5 1   ; var5 = 1
      34 [-]: CALL R4 2 1  ; var4(var5)
      35 [-]: GETIMPORT R6 13; var6 = gContextActionType
      36 [-]: NAMECALL R4 R0 K14; var5 = var0; var4 = var0[0xC9F6A7D7]
      37 [-]: CALL R4 3 2  ; var4 = var4(var5, var6)
L 7:  38 [-]: FASTCALL1 64 R4 L8; 
      39 [-]: MOVE R6 R4   ; var6 = var4
      40 [-]: GETIMPORT R5 3; var5 = 0x7B998233
      41 [-]: CALL R5 2 2  ; var5 = var5(var6)
L 8:  42 [-]: JUMPIFNOT R5 L9; goto L9 if not var5
      43 [-]: GETIMPORT R5 5; var5 = 0xCBD666E1
      44 [-]: LOADN R6 0   ; var6 = 0
      45 [-]: CALL R5 2 1  ; var5(var6)
      46 [-]: GETIMPORT R7 13; var7 = gContextActionType
      47 [-]: NAMECALL R5 R0 K14; var6 = var0; var5 = var0[0xC9F6A7D7]
      48 [-]: CALL R5 3 2  ; var5 = var5(var6, var7)
      49 [-]: MOVE R4 R5   ; var4 = var5
      50 [-]: JUMPBACK L7  ; goto L7
L 9:  51 [-]: FASTCALL1 64 R0 L10; 
      52 [-]: MOVE R6 R0   ; var6 = var0
      53 [-]: GETIMPORT R5 3; var5 = 0x7B998233
      54 [-]: CALL R5 2 2  ; var5 = var5(var6)
L10:  55 [-]: JUMPIF R5 L19; goto L19 if var5
      56 [-]: GETIMPORT R6 1; var6 = 0x25D99D89
      57 [-]: FASTCALL1 64 R6 L11; 
      58 [-]: GETIMPORT R5 3; var5 = 0x7B998233
      59 [-]: CALL R5 2 2  ; var5 = var5(var6)
L11:  60 [-]: JUMPIF R5 L19; goto L19 if var5
      61 [-]: FASTCALL1 64 R4 L12; 
      62 [-]: MOVE R6 R4   ; var6 = var4
      63 [-]: GETIMPORT R5 3; var5 = 0x7B998233
      64 [-]: CALL R5 2 2  ; var5 = var5(var6)
L12:  65 [-]: JUMPIF R5 L19; goto L19 if var5
      66 [-]: NAMECALL R5 R1 K9; var6 = var1; var5 = var1[0x8E7C3B5E]
      67 [-]: CALL R5 2 2  ; var5 = var5(var6)
      68 [-]: GETUPVAL R6 1; var6 = upvalues[1]
      69 [-]: JUMPIFEQ R5 R6 L13; goto L13 if var5 == var16777734
      70 [-]: LOADB R2 0 +1; var2 = false
L13:  71 [-]: LOADB R2 1   ; var2 = true
L14:  72 [-]: GETUPVAL R6 2; var6 = upvalues[2]
      73 [-]: GETTABLEKS R5 R6 K10; var5 = var6[0xE77C9F88]
      74 [-]: GETUPVAL R6 1; var6 = upvalues[1]
      75 [-]: CALL R5 2 2  ; var5 = var5(var6)
      76 [-]: MOVE R3 R5   ; var3 = var5
      77 [-]: JUMPIFNOT R2 L17; goto L17 if not var2
      78 [-]: MOVE R6 R3   ; var6 = var3
      79 [-]: LOADB R5 0   ; var5 = false
      80 [-]: LOADN R7 1   ; var7 = 1
      81 [-]: JUMPIFNOTLT R7 R6 L16; goto L16 if var7 >= var526128
      82 [-]: LOADN R7 8   ; var7 = 8
      83 [-]: JUMPIFLT R6 R7 L15; goto L15 if var6 < var16778502
      84 [-]: LOADB R5 0 +1; var5 = false
L15:  85 [-]: LOADB R5 1   ; var5 = true
L16:  86 [-]: JUMPIFNOT R5 L17; goto L17 if not var5
      87 [-]: NAMECALL R5 R0 K15; var6 = var0; var5 = var0[0xD4CC05B4]
      88 [-]: CALL R5 2 2  ; var5 = var5(var6)
      89 [-]: JUMPIF R5 L18; goto L18 if var5
      90 [-]: MOVE R5 R4   ; var5 = var4
      91 [-]: LOADB R8 1   ; var8 = true
      92 [-]: LOADB R9 1   ; var9 = true
      93 [-]: NAMECALL R6 R0 K16; var7 = var0; var6 = var0[0x768274D6]
      94 [-]: CALL R6 4 1  ; var6(var7, var8, var9)
      95 [-]: NAMECALL R6 R5 K17; var7 = var5; var6 = var5[0x383D2E7D]
      96 [-]: CALL R6 2 1  ; var6(var7)
      97 [-]: JUMP L18     ; goto L18
L17:  98 [-]: NAMECALL R5 R0 K15; var6 = var0; var5 = var0[0xD4CC05B4]
      99 [-]: CALL R5 2 2  ; var5 = var5(var6)
     100 [-]: JUMPIFNOT R5 L18; goto L18 if not var5
     101 [-]: MOVE R5 R4   ; var5 = var4
     102 [-]: LOADB R8 0   ; var8 = false
     103 [-]: LOADB R9 1   ; var9 = true
     104 [-]: NAMECALL R6 R0 K16; var7 = var0; var6 = var0[0x768274D6]
     105 [-]: CALL R6 4 1  ; var6(var7, var8, var9)
     106 [-]: NAMECALL R6 R5 K18; var7 = var5; var6 = var5[0xF4E253B6]
     107 [-]: CALL R6 2 1  ; var6(var7)
L18: 108 [-]: GETIMPORT R5 5; var5 = 0xCBD666E1
     109 [-]: LOADN R6 0   ; var6 = 0
     110 [-]: CALL R5 2 1  ; var5(var6)
     111 [-]: JUMPBACK L9  ; goto L9
L19: 112 [-]: RETURN R0 0  ; 


; Name:            
; Defined at line: 645
; #Upvalues:       0
; #Parameters:     1
; Is_vararg:       0
; Max Stack Size:  5

       0 [-]: GETIMPORT R3 1; var3 = 0x3F11767E
       1 [-]: LOADB R4 1   ; var4 = true
       2 [-]: NAMECALL R1 R0 K2; var2 = var0; var1 = var0[0x5D985C7E]
       3 [-]: CALL R1 4 1  ; var1(var2, var3, var4)
       4 [-]: GETIMPORT R3 4; var3 = 0xB7A872FC
       5 [-]: NAMECALL R1 R0 K5; var2 = var0; var1 = var0[0x4C91B5D8]
       6 [-]: CALL R1 3 1  ; var1(var2, var3)
       7 [-]: RETURN R0 0  ; 


; Name:            
; Defined at line: 650
; #Upvalues:       12
; #Parameters:     0
; Is_vararg:       0
; Max Stack Size:  8

       0 [-]: GETIMPORT R1 1; var1 = 0xBE190284
       1 [-]: GETIMPORT R3 3; var3 = gLotusHubGameRulesType
       2 [-]: NAMECALL R1 R1 K4; var2 = var1; var1 = var1[0xF2DEAF69]
       3 [-]: CALL R1 3 2  ; var1 = var1(var2, var3)
       4 [-]: JUMPIFNOT R1 L2; goto L2 if not var1
       5 [-]: GETIMPORT R2 1; var2 = 0xBE190284
       6 [-]: NAMECALL R2 R2 K5; var3 = var2; var2 = var2[0xEF893AEC]
       7 [-]: CALL R2 2 2  ; var2 = var2(var3)
       8 [-]: GETTABLEKS R1 R2 K6; var1 = var2["location"]
       9 [-]: GETUPVAL R3 0; var3 = upvalues[0]
      10 [-]: GETTABLEKS R2 R3 K7; var2 = var3["FORTUNA_NODE_TAG"]
      11 [-]: JUMPIFEQ R1 R2 L0; goto L0 if var1 == var16777222
      12 [-]: LOADB R0 0 +1; var0 = false
L 0:  13 [-]: LOADB R0 1   ; var0 = true
L 1:  14 [-]: JUMP L3      ; goto L3
L 2:  15 [-]: LOADB R0 0   ; var0 = false
L 3:  16 [-]: JUMPIF R0 L4 ; goto L4 if var0
      17 [-]: RETURN R0 0  ; 
L 4:  18 [-]: GETUPVAL R0 1; var0 = upvalues[1]
      19 [-]: CALL R0 1 1  ; var0()
      20 [-]: GETUPVAL R0 2; var0 = upvalues[2]
      21 [-]: CALL R0 1 1  ; var0()
      22 [-]: GETUPVAL R0 3; var0 = upvalues[3]
      23 [-]: CALL R0 1 1  ; var0()
      24 [-]: GETUPVAL R0 4; var0 = upvalues[4]
      25 [-]: LOADB R1 0   ; var1 = false
      26 [-]: CALL R0 2 1  ; var0(var1)
      27 [-]: GETIMPORT R0 9; var0 = 0xCBD666E1
      28 [-]: LOADN R1 1   ; var1 = 1
      29 [-]: CALL R0 2 1  ; var0(var1)
      30 [-]: GETIMPORT R0 11; var0 = 0x89326C93
      31 [-]: NAMECALL R0 R0 K12; var1 = var0; var0 = var0[0xFB64E76C]
      32 [-]: CALL R0 2 2  ; var0 = var0(var1)
      33 [-]: NAMECALL R1 R0 K13; var2 = var0; var1 = var0[0xBB610E5B]
      34 [-]: CALL R1 2 2  ; var1 = var1(var2)
      35 [-]: GETUPVAL R3 5; var3 = upvalues[5]
      36 [-]: GETTABLEKS R2 R3 K14; var2 = var3[0xF22CFC77]
      37 [-]: GETIMPORT R3 16; var3 = 0xE91D7466
      38 [-]: GETIMPORT R4 18; var4 = 0x0469F296
      39 [-]: LOADK R5 K19 ; var5 = "ArriveFortuna"
      40 [-]: CALL R4 2 2  ; var4 = var4(var5)
      41 [-]: MOVE R5 R1   ; var5 = var1
      42 [-]: CALL R2 4 1  ; var2(var3, var4, var5)
      43 [-]: GETIMPORT R2 9; var2 = 0xCBD666E1
      44 [-]: LOADN R3 1   ; var3 = 1
      45 [-]: CALL R2 2 1  ; var2(var3)
L 5:  46 [-]: GETUPVAL R3 0; var3 = upvalues[0]
      47 [-]: GETTABLEKS R2 R3 K20; var2 = var3[0x0DEACD54]
      48 [-]: CALL R2 1 2  ; var2 = var2()
      49 [-]: JUMPIFNOT R2 L6; goto L6 if not var2
      50 [-]: GETIMPORT R2 9; var2 = 0xCBD666E1
      51 [-]: LOADN R3 0   ; var3 = 0
      52 [-]: CALL R2 2 1  ; var2(var3)
      53 [-]: JUMPBACK L5  ; goto L5
L 6:  54 [-]: GETIMPORT R2 11; var2 = 0x89326C93
      55 [-]: GETUPVAL R4 6; var4 = upvalues[6]
      56 [-]: NAMECALL R2 R2 K21; var3 = var2; var2 = var2[0x46A0EBF5]
      57 [-]: CALL R2 3 2  ; var2 = var2(var3, var4)
      58 [-]: GETUPVAL R3 7; var3 = upvalues[7]
      59 [-]: MOVE R4 R2   ; var4 = var2
      60 [-]: LOADK R5 K22 ; var5 = "/Lotus/Language/YareliQuest/TalkToBoon"
      61 [-]: CALL R3 3 1  ; var3(var4, var5)
      62 [-]: GETIMPORT R3 11; var3 = 0x89326C93
      63 [-]: GETUPVAL R5 9; var5 = upvalues[9]
      64 [-]: NAMECALL R3 R3 K21; var4 = var3; var3 = var3[0x46A0EBF5]
      65 [-]: CALL R3 3 2  ; var3 = var3(var4, var5)
      66 [-]: SETUPVAL R3 8; upvalues[3] = var8
      67 [-]: GETUPVAL R3 8; var3 = upvalues[8]
      68 [-]: NAMECALL R3 R3 K23; var4 = var3; var3 = var3[0x383D2E7D]
      69 [-]: CALL R3 2 1  ; var3(var4)
      70 [-]: GETIMPORT R3 11; var3 = 0x89326C93
      71 [-]: NAMECALL R3 R3 K12; var4 = var3; var3 = var3[0xFB64E76C]
      72 [-]: CALL R3 2 2  ; var3 = var3(var4)
      73 [-]: MOVE R0 R3   ; var0 = var3
L 7:  74 [-]: FASTCALL1 64 R2 L8; 
      75 [-]: MOVE R4 R2   ; var4 = var2
      76 [-]: GETIMPORT R3 25; var3 = 0x7B998233
      77 [-]: CALL R3 2 2  ; var3 = var3(var4)
L 8:  78 [-]: JUMPIF R3 L9 ; goto L9 if var3
      79 [-]: NAMECALL R3 R0 K13; var4 = var0; var3 = var0[0xBB610E5B]
      80 [-]: CALL R3 2 2  ; var3 = var3(var4)
      81 [-]: MOVE R5 R2   ; var5 = var2
      82 [-]: NAMECALL R3 R3 K26; var4 = var3; var3 = var3[0xBEBAD19F]
      83 [-]: CALL R3 3 2  ; var3 = var3(var4, var5)
      84 [-]: LOADN R4 10  ; var4 = 10
      85 [-]: JUMPIFNOTLT R4 R3 L9; goto L9 if var4 >= var590625
      86 [-]: GETIMPORT R3 9; var3 = 0xCBD666E1
      87 [-]: LOADK R4 K27 ; var4 = 0.5
      88 [-]: CALL R3 2 1  ; var3(var4)
      89 [-]: JUMPBACK L7  ; goto L7
L 9:  90 [-]: FASTCALL1 64 R2 L10; 
      91 [-]: MOVE R4 R2   ; var4 = var2
      92 [-]: GETIMPORT R3 25; var3 = 0x7B998233
      93 [-]: CALL R3 2 2  ; var3 = var3(var4)
L10:  94 [-]: JUMPIFNOT R3 L11; goto L11 if not var3
      95 [-]: RETURN R0 0  ; 
L11:  96 [-]: GETUPVAL R4 5; var4 = upvalues[5]
      97 [-]: GETTABLEKS R3 R4 K14; var3 = var4[0xF22CFC77]
      98 [-]: GETIMPORT R4 16; var4 = 0xE91D7466
      99 [-]: GETIMPORT R5 18; var5 = 0x0469F296
     100 [-]: LOADK R6 K28 ; var6 = "RokyAwake"
     101 [-]: CALL R5 2 2  ; var5 = var5(var6)
     102 [-]: MOVE R6 R1   ; var6 = var1
     103 [-]: CALL R3 4 1  ; var3(var4, var5, var6)
     104 [-]: GETIMPORT R3 11; var3 = 0x89326C93
     105 [-]: GETIMPORT R5 18; var5 = 0x0469F296
     106 [-]: LOADK R6 K29 ; var6 = "YareliQuestRoky"
     107 [-]: CALL R5 2 0  ; var5, ... = var5(var6)
     108 [-]: NAMECALL R3 R3 K21; var4 = var3; var3 = var3[0x46A0EBF5]
     109 [-]: CALL R3 0 2  ; var3 = var3(var4, ...)
     110 [-]: FASTCALL1 64 R3 L12; 
     111 [-]: MOVE R5 R3   ; var5 = var3
     112 [-]: GETIMPORT R4 25; var4 = 0x7B998233
     113 [-]: CALL R4 2 2  ; var4 = var4(var5)
L12: 114 [-]: JUMPIF R4 L13; goto L13 if var4
     115 [-]: GETIMPORT R6 18; var6 = 0x0469F296
     116 [-]: LOADK R7 K30 ; var7 = "RokyWakeUp"
     117 [-]: CALL R6 2 2  ; var6 = var6(var7)
     118 [-]: LOADB R7 0   ; var7 = false
     119 [-]: NAMECALL R4 R3 K31; var5 = var3; var4 = var3[0xD5F7912B]
     120 [-]: CALL R4 4 1  ; var4(var5, var6, var7)
L13: 121 [-]: GETIMPORT R4 9; var4 = 0xCBD666E1
     122 [-]: LOADN R5 1   ; var5 = 1
     123 [-]: CALL R4 2 1  ; var4(var5)
L14: 124 [-]: GETUPVAL R5 0; var5 = upvalues[0]
     125 [-]: GETTABLEKS R4 R5 K20; var4 = var5[0x0DEACD54]
     126 [-]: CALL R4 1 2  ; var4 = var4()
     127 [-]: JUMPIFNOT R4 L15; goto L15 if not var4
     128 [-]: GETIMPORT R4 9; var4 = 0xCBD666E1
     129 [-]: LOADN R5 0   ; var5 = 0
     130 [-]: CALL R4 2 1  ; var4(var5)
     131 [-]: JUMPBACK L14 ; goto L14
L15: 132 [-]: GETIMPORT R4 33; var4 = _T
     133 [-]: LOADB R5 0   ; var5 = false
     134 [-]: SETTABLEKS R5 R4 K34; var5["CompleteYareliStage"] = var4
     135 [-]: GETIMPORT R4 36; var4 = _T["TaggedDialog"]
     136 [-]: GETIMPORT R6 36; var6 = _T["TaggedDialog"]
     137 [-]: GETTABLEKS R5 R6 K37; var5 = var6["Boon_YareliEnd"]
     138 [-]: JUMPIF R5 L16; goto L16 if var5
     139 [-]: DUPTABLE R5 41; 
     140 [-]: LOADK R6 K42 ; var6 = "/Lotus/Language/YareliQuest/RokyAwakeDialogOption"
     141 [-]: SETTABLEKS R6 R5 K38; var6["mName"] = var5
     142 [-]: LOADB R6 1   ; var6 = true
     143 [-]: SETTABLEKS R6 R5 K39; var6["mAlwaysShow"] = var5
     144 [-]: DUPCLOSURE R6 K43; 
     145 [-]: CAPTURE UPVAL U7; 
     146 [-]: SETTABLEKS R6 R5 K40; var6["mCallback"] = var5
L16: 147 [-]: SETTABLEKS R5 R4 K37; var5["Boon_YareliEnd"] = var4
     148 [-]: GETUPVAL R4 4; var4 = upvalues[4]
     149 [-]: LOADB R5 1   ; var5 = true
     150 [-]: CALL R4 2 1  ; var4(var5)
L17: 151 [-]: GETIMPORT R4 44; var4 = _T["CompleteYareliStage"]
     152 [-]: JUMPIF R4 L18; goto L18 if var4
     153 [-]: GETIMPORT R4 9; var4 = 0xCBD666E1
     154 [-]: LOADN R5 0   ; var5 = 0
     155 [-]: CALL R4 2 1  ; var4(var5)
     156 [-]: JUMPBACK L17 ; goto L17
L18: 157 [-]: GETUPVAL R5 10; var5 = upvalues[10]
     158 [-]: GETTABLEKS R4 R5 K45; var4 = var5[0xA26220ED]
     159 [-]: GETIMPORT R5 47; var5 = 0xB009BBC6
     160 [-]: GETUPVAL R6 11; var6 = upvalues[11]
     161 [-]: CALL R5 2 2  ; var5 = var5(var6)
     162 [-]: GETIMPORT R6 49; var6 = 0x1E9E5BC8
     163 [-]: CALL R4 3 1  ; var4(var5, var6)
     164 [-]: RETURN R0 0  ; 


; Name:            
; Defined at line: 724
; #Upvalues:       2
; #Parameters:     0
; Is_vararg:       0
; Max Stack Size:  4

L 0:   0 [-]: GETIMPORT R1 1; var1 = 0x25D99D89
       1 [-]: FASTCALL1 64 R1 L1; 
       2 [-]: GETIMPORT R0 3; var0 = 0x7B998233
       3 [-]: CALL R0 2 2  ; var0 = var0(var1)
L 1:   4 [-]: JUMPIFNOT R0 L2; goto L2 if not var0
       5 [-]: GETIMPORT R0 5; var0 = 0xCBD666E1
       6 [-]: LOADN R1 0   ; var1 = 0
       7 [-]: CALL R0 2 1  ; var0(var1)
       8 [-]: JUMPBACK L0  ; goto L0
L 2:   9 [-]: GETUPVAL R1 0; var1 = upvalues[0]
      10 [-]: GETTABLEKS R0 R1 K6; var0 = var1[0xD3D59A3B]
      11 [-]: GETUPVAL R1 1; var1 = upvalues[1]
      12 [-]: CALL R0 2 2  ; var0 = var0(var1)
      13 [-]: JUMPIFNOT R0 L3; goto L3 if not var0
      14 [-]: GETUPVAL R1 0; var1 = upvalues[0]
      15 [-]: GETTABLEKS R0 R1 K7; var0 = var1[0xA26220ED]
      16 [-]: GETIMPORT R1 9; var1 = 0xB009BBC6
      17 [-]: GETUPVAL R2 1; var2 = upvalues[1]
      18 [-]: CALL R1 2 2  ; var1 = var1(var2)
      19 [-]: GETIMPORT R2 11; var2 = 0x1E9E5BC8
      20 [-]: CALL R0 3 1  ; var0(var1, var2)
      21 [-]: RETURN R0 0  ; 
L 3:  22 [-]: GETUPVAL R1 0; var1 = upvalues[0]
      23 [-]: GETTABLEKS R0 R1 K12; var0 = var1[0x02DC6F4F]
      24 [-]: GETUPVAL R1 1; var1 = upvalues[1]
      25 [-]: GETIMPORT R2 11; var2 = 0x1E9E5BC8
      26 [-]: CALL R0 3 1  ; var0(var1, var2)
      27 [-]: GETIMPORT R0 5; var0 = 0xCBD666E1
      28 [-]: LOADN R1 1   ; var1 = 1
      29 [-]: CALL R0 2 1  ; var0(var1)
      30 [-]: GETIMPORT R0 1; var0 = 0x25D99D89
      31 [-]: LOADK R2 K13 ; var2 = "OnInboxSync"
      32 [-]: LOADB R3 1   ; var3 = true
      33 [-]: NAMECALL R0 R0 K14; var1 = var0; var0 = var0[0x24389EC3]
      34 [-]: CALL R0 4 1  ; var0(var1, var2, var3)
L 4:  35 [-]: GETIMPORT R0 17; var0 = _T["curTransmission"]
      36 [-]: GETIMPORT R1 19; var1 = 0x13B4613D
      37 [-]: JUMPIFEQ R0 R1 L5; goto L5 if var0 == var327713
      38 [-]: GETIMPORT R0 5; var0 = 0xCBD666E1
      39 [-]: LOADN R1 0   ; var1 = 0
      40 [-]: CALL R0 2 1  ; var0(var1)
      41 [-]: JUMPBACK L4  ; goto L4
L 5:  42 [-]: GETIMPORT R0 17; var0 = _T["curTransmission"]
      43 [-]: GETIMPORT R1 19; var1 = 0x13B4613D
      44 [-]: JUMPIFNOTEQ R0 R1 L6; goto L6 if var0 ~= var327713
      45 [-]: GETIMPORT R0 5; var0 = 0xCBD666E1
      46 [-]: LOADN R1 0   ; var1 = 0
      47 [-]: CALL R0 2 1  ; var0(var1)
      48 [-]: JUMPBACK L5  ; goto L5
L 6:  49 [-]: GETUPVAL R1 0; var1 = upvalues[0]
      50 [-]: GETTABLEKS R0 R1 K7; var0 = var1[0xA26220ED]
      51 [-]: GETIMPORT R1 9; var1 = 0xB009BBC6
      52 [-]: GETUPVAL R2 1; var2 = upvalues[1]
      53 [-]: CALL R1 2 2  ; var1 = var1(var2)
      54 [-]: GETIMPORT R2 11; var2 = 0x1E9E5BC8
      55 [-]: CALL R0 3 1  ; var0(var1, var2)
      56 [-]: RETURN R0 0  ; 



