; Name:            
; Defined at line: 1
; #Upvalues:       0
; #Parameters:     0
; Is_vararg:       1
; Max Stack Size:  3

       1 [-]: GETIMPORT R0 1; var0 = 0xAEABECDA
       2 [-]: GETVARARGS R1 1; var1 = ...
       3 [-]: GETIMPORT R2 4; var2 = package["seeall"]
       4 [-]: CALL R0 3 1  ; var0(var1, var2)
       5 [-]: DUPCLOSURE R0 K5; 
       6 [-]: SETGLOBAL R0 K6; "Create" = var0
       7 [-]: RETURN R0 0  ; 


; Name:            
; Defined at line: 3
; #Upvalues:       0
; #Parameters:     8
; Is_vararg:       0
; Max Stack Size:  22

       0 [-]: GETIMPORT R8 1; var8 = 0x2D0FAD09
       1 [-]: LOADK R9 K2  ; var9 = "EE.Interface.Utilities"
       2 [-]: CALL R8 2 2  ; var8 = var8(var9)
       3 [-]: GETIMPORT R9 1; var9 = 0x2D0FAD09
       4 [-]: LOADK R10 K3 ; var10 = "Lotus.Interface.UIStyleUtilities"
       5 [-]: CALL R9 2 2  ; var9 = var9(var10)
       6 [-]: GETIMPORT R10 1; var10 = 0x2D0FAD09
       7 [-]: LOADK R11 K4 ; var11 = "Lotus.Interface.Components.ThemedButton"
       8 [-]: CALL R10 2 2 ; var10 = var10(var11)
       9 [-]: GETIMPORT R11 1; var11 = 0x2D0FAD09
      10 [-]: LOADK R12 K5 ; var12 = "EE.Interface.Components.List"
      11 [-]: CALL R11 2 2 ; var11 = var11(var12)
      12 [-]: JUMPXEQKNIL R4 L0 NOT; 
      13 [-]: LOADK R4 K6  ; var4 = "<MENU_GENERIC2>"
L 0:  14 [-]: GETTABLEKS R12 R11 K7; var12 = var11[0x9383BC56]
      15 [-]: MOVE R13 R0  ; var13 = var0
      16 [-]: MOVE R15 R1  ; var15 = var1
      17 [-]: LOADK R16 K8 ; var16 = ".Buttons.Button"
      18 [-]: CONCAT R14 R15 R16; var14 = var15 .. var16
      19 [-]: CALL R12 3 2 ; var12 = var12(var13, var14)
      20 [-]: SETTABLEKS R1 R12 K9; var1["mRootClipName"] = var12
      21 [-]: MOVE R14 R1  ; var14 = var1
      22 [-]: LOADK R15 K10; var15 = ".Backer"
      23 [-]: CONCAT R13 R14 R15; var13 = var14 .. var15
      24 [-]: SETTABLEKS R13 R12 K11; var13["mHitboxClipName"] = var12
      25 [-]: LOADK R15 K12; var15 = "SupportsThemes"
      26 [-]: LOADK R16 K13; var16 = ""
      27 [-]: NAMECALL R13 R0 K14; var14 = var0; var13 = var0[0xE4162EED]
      28 [-]: CALL R13 4 2 ; var13 = var13(var14, var15, var16)
      29 [-]: SETTABLEKS R13 R12 K15; var13["mApplyThemes"] = var12
      30 [-]: LOADB R13 0  ; var13 = false
      31 [-]: SETTABLEKS R13 R12 K16; var13["mExpanded"] = var12
      32 [-]: LOADN R13 30 ; var13 = 30
      33 [-]: SETTABLEKS R13 R12 K17; var13["mForcedVerticalSeparation"] = var12
      34 [-]: LOADN R13 370; var13 = 370
      35 [-]: SETTABLEKS R13 R12 K18; var13["mWidth"] = var12
      36 [-]: LOADNIL R13  ; var13 = nil
      37 [-]: SETTABLEKS R13 R12 K19; var13["mSelectedElement"] = var12
      38 [-]: LOADNIL R13  ; var13 = nil
      39 [-]: SETTABLEKS R13 R12 K20; var13["mCustomizeButtonCallback"] = var12
      40 [-]: LOADB R13 1  ; var13 = true
      41 [-]: SETTABLEKS R13 R12 K21; var13["mSelectedIconOnly"] = var12
      42 [-]: GETTABLEKS R13 R10 K22; var13 = var10[0xAE6791BA]
      43 [-]: MOVE R14 R0  ; var14 = var0
      44 [-]: MOVE R16 R1  ; var16 = var1
      45 [-]: LOADK R17 K23; var17 = ".MainButton"
      46 [-]: CONCAT R15 R16 R17; var15 = var16 .. var17
      47 [-]: ORK R16 R2 K24; var16 = var2 or "----"
      48 [-]: MOVE R17 R3  ; var17 = var3
      49 [-]: MOVE R18 R4  ; var18 = var4
      50 [-]: MOVE R19 R5  ; var19 = var5
      51 [-]: MOVE R20 R6  ; var20 = var6
      52 [-]: MOVE R21 R7  ; var21 = var7
      53 [-]: CALL R13 9 2 ; var13 = var13(var14, var15, var16, var17, var18, var19, var20, var21)
      54 [-]: LOADN R14 5  ; var14 = 5
      55 [-]: SETTABLEKS R14 R13 K25; var14["mTextBuffer"] = var13
      56 [-]: LOADB R14 0  ; var14 = false
      57 [-]: SETTABLEKS R14 R13 K26; var14["mPrefixCallout"] = var13
      58 [-]: LOADB R14 1  ; var14 = true
      59 [-]: SETTABLEKS R14 R13 K27; var14["mFlipExpandedIcon"] = var13
      60 [-]: GETTABLEKS R14 R13 K28; var14 = var13["SetFocus"]
      61 [-]: SETTABLEKS R14 R13 K29; var14["ButtonSetFocus"] = var13
      62 [-]: NEWCLOSURE R14 P0; 
      63 [-]: CAPTURE VAL R13; 
      64 [-]: SETTABLEKS R14 R13 K28; var14["SetFocus"] = var13
      65 [-]: GETTABLEKS R14 R13 K30; var14 = var13["Pressed"]
      66 [-]: SETTABLEKS R14 R13 K31; var14["ButtonPressed"] = var13
      67 [-]: NEWCLOSURE R14 P1; 
      68 [-]: CAPTURE VAL R13; 
      69 [-]: CAPTURE VAL R12; 
      70 [-]: SETTABLEKS R14 R13 K30; var14["Pressed"] = var13
      71 [-]: NEWCLOSURE R14 P2; 
      72 [-]: CAPTURE VAL R12; 
      73 [-]: SETTABLEKS R14 R13 K32; var14["SetValue"] = var13
      74 [-]: LOADK R16 K33; var16 = "left"
      75 [-]: NAMECALL R14 R13 K34; var15 = var13; var14 = var13[0x6B2AB44E]
      76 [-]: CALL R14 3 1 ; var14(var15, var16)
      77 [-]: GETTABLEKS R16 R12 K18; var16 = var12["mWidth"]
      78 [-]: NAMECALL R14 R13 K35; var15 = var13; var14 = var13[0x8D77B2B2]
      79 [-]: CALL R14 3 1 ; var14(var15, var16)
      80 [-]: NAMECALL R14 R13 K36; var15 = var13; var14 = var13[0x71E9AC81]
      81 [-]: CALL R14 2 1 ; var14(var15)
      82 [-]: SETTABLEKS R13 R12 K37; var13["mMainButton"] = var12
      83 [-]: DUPCLOSURE R14 K38; 
      84 [-]: SETTABLEKS R14 R12 K39; var14["SetWidth"] = var12
      85 [-]: NEWCLOSURE R14 P4; 
      86 [-]: CAPTURE VAL R9; 
      87 [-]: CAPTURE VAL R8; 
      88 [-]: SETTABLEKS R14 R12 K40; var14["UpdateColors"] = var12
      89 [-]: DUPCLOSURE R14 K41; 
      90 [-]: SETTABLEKS R14 R12 K42; var14["SetVisible"] = var12
      91 [-]: DUPCLOSURE R14 K43; 
      92 [-]: SETTABLEKS R14 R12 K44; var14["IsExpanded"] = var12
      93 [-]: DUPCLOSURE R14 K45; 
      94 [-]: SETTABLEKS R14 R12 K46; var14["SetExpanded"] = var12
      95 [-]: NEWCLOSURE R14 P8; 
      96 [-]: CAPTURE VAL R12; 
      97 [-]: SETTABLEKS R14 R12 K47; var14["UpdateSelectedText"] = var12
      98 [-]: GETTABLEKS R14 R12 K48; var14 = var12["OnSelected"]
      99 [-]: SETTABLEKS R14 R12 K49; var14["ButtonOnSelected"] = var12
     100 [-]: GETTABLEKS R14 R12 K47; var14 = var12["UpdateSelectedText"]
     101 [-]: SETTABLEKS R14 R12 K48; var14["OnSelected"] = var12
     102 [-]: GETTABLEKS R14 R12 K50; var14 = var12["OnDraw"]
     103 [-]: SETTABLEKS R14 R12 K51; var14["ListOnDraw"] = var12
     104 [-]: NEWCLOSURE R14 P9; 
     105 [-]: CAPTURE VAL R10; 
     106 [-]: CAPTURE VAL R12; 
     107 [-]: SETTABLEKS R14 R12 K50; var14["OnDraw"] = var12
     108 [-]: GETTABLEKS R14 R12 K52; var14 = var12["Redraw"]
     109 [-]: SETTABLEKS R14 R12 K53; var14["ListRedraw"] = var12
     110 [-]: DUPCLOSURE R14 K54; 
     111 [-]: SETTABLEKS R14 R12 K52; var14["Redraw"] = var12
     112 [-]: DUPCLOSURE R14 K55; 
     113 [-]: SETTABLEKS R14 R12 K56; var14["MouseOverClip"] = var12
     114 [-]: NEWCLOSURE R14 P12; 
     115 [-]: CAPTURE VAL R1; 
     116 [-]: SETTABLEKS R14 R12 K57; var14["OnMouseClick"] = var12
     117 [-]: DUPCLOSURE R14 K58; 
     118 [-]: SETTABLEKS R14 R12 K59; var14["HookupCallbacks"] = var12
     119 [-]: MOVE R16 R1  ; var16 = var1
     120 [-]: LOADK R17 K60; var17 = "Buttons"
     121 [-]: LOADN R18 1  ; var18 = 1
     122 [-]: GETTABLEKS R19 R12 K17; var19 = var12["mForcedVerticalSeparation"]
     123 [-]: NAMECALL R14 R0 K61; var15 = var0; var14 = var0[0xF64B7262]
     124 [-]: CALL R14 6 1 ; var14(var15, var16, var17, var18, var19)
     125 [-]: MOVE R16 R1  ; var16 = var1
     126 [-]: LOADK R17 K62; var17 = "Backer"
     127 [-]: LOADN R18 1  ; var18 = 1
     128 [-]: GETTABLEKS R19 R12 K17; var19 = var12["mForcedVerticalSeparation"]
     129 [-]: NAMECALL R14 R0 K61; var15 = var0; var14 = var0[0xF64B7262]
     130 [-]: CALL R14 6 1 ; var14(var15, var16, var17, var18, var19)
     131 [-]: MOVE R17 R1  ; var17 = var1
     132 [-]: LOADK R18 K10; var18 = ".Backer"
     133 [-]: CONCAT R16 R17 R18; var16 = var17 .. var18
     134 [-]: GETIMPORT R18 64; var18 = 0x0032441C
     135 [-]: GETTABLEKS R17 R18 K65; var17 = var18["UIMaterial_Button"]
     136 [-]: NAMECALL R14 R0 K66; var15 = var0; var14 = var0[0xD5181643]
     137 [-]: CALL R14 4 1 ; var14(var15, var16, var17)
     138 [-]: LOADB R16 0  ; var16 = false
     139 [-]: NAMECALL R14 R12 K67; var15 = var12; var14 = var12[0xF20F1913]
     140 [-]: CALL R14 3 1 ; var14(var15, var16)
     141 [-]: NAMECALL R14 R12 K68; var15 = var12; var14 = var12[0xA0ED0E4C]
     142 [-]: CALL R14 2 1 ; var14(var15)
     143 [-]: RETURN R12 1 ; 



