; This file has been disassembled using luadec 2.0.2 by sztupy (modified by Reversive)

; Name:            
; Defined at line: 0
; #Upvalues:       0
; #Parameters:     0
; Is_vararg:       2
; Max Stack Size:  58

  1 [-]: GETGLOBAL R0 K0        ; R0 := 0x2d0fad09
  2 [-]: LOADK     R1 K1        ; R1 := "Lotus.Interface.LotusUtilities"
  3 [-]: CALL      R0 2 2       ; R0 := R0(R1)
  4 [-]: GETGLOBAL R1 K0        ; R1 := 0x2d0fad09
  5 [-]: LOADK     R2 K2        ; R2 := "Lotus.Scripts.Libs.LandscapeLib"
  6 [-]: CALL      R1 2 2       ; R1 := R1(R2)
  7 [-]: GETGLOBAL R2 K0        ; R2 := 0x2d0fad09
  8 [-]: LOADK     R3 K3        ; R3 := "Lotus.Scripts.Libs.TransmissionSet"
  9 [-]: CALL      R2 2 2       ; R2 := R2(R3)
 10 [-]: GETGLOBAL R3 K0        ; R3 := 0x2d0fad09
 11 [-]: LOADK     R4 K4        ; R4 := "Lotus.Interface.Libs.TimerMgr"
 12 [-]: CALL      R3 2 2       ; R3 := R3(R4)
 13 [-]: GETGLOBAL R4 K0        ; R4 := 0x2d0fad09
 14 [-]: LOADK     R5 K5        ; R5 := "Lotus.Scripts.Libs.ObjectiveText"
 15 [-]: CALL      R4 2 2       ; R4 := R4(R5)
 16 [-]: LOADK     R5 K6        ; R5 := "/Lotus/Language/InfestedPlainsEvent/EventEncounterDefendConsole"
 17 [-]: LOADK     R6 K7        ; R6 := "/Lotus/Language/InfestedPlainsEvent/EventEncounterMissionTimer"
 18 [-]: LOADK     R7 K8        ; R7 := "/Lotus/Language/InfestedPlainsEvent/EventEncounterOpenVault"
 19 [-]: LOADK     R8 K9        ; R8 := "/Lotus/Language/InfestedPlainsEvent/EventEncounterActivateMixer"
 20 [-]: LOADK     R9 K10       ; R9 := "/Lotus/Language/InfestedPlainsEvent/EventEncounterGetMixture"
 21 [-]: GETGLOBAL R10 K11      ; R10 := 0x0469f296
 22 [-]: LOADK     R11 K12      ; R11 := "MODE_STATE"
 23 [-]: CALL      R10 2 2      ; R10 := R10(R11)
 24 [-]: GETGLOBAL R11 K11      ; R11 := 0x0469f296
 25 [-]: LOADK     R12 K13      ; R12 := "MISSION_TIME"
 26 [-]: CALL      R11 2 2      ; R11 := R11(R12)
 27 [-]: GETGLOBAL R12 K11      ; R12 := 0x0469f296
 28 [-]: LOADK     R13 K14      ; R13 := "NUM_CLAN_ITEMS"
 29 [-]: CALL      R12 2 2      ; R12 := R12(R13)
 30 [-]: GETGLOBAL R13 K11      ; R13 := 0x0469f296
 31 [-]: LOADK     R14 K15      ; R14 := "NUM_EVENT_ITEMS"
 32 [-]: CALL      R13 2 2      ; R13 := R13(R14)
 33 [-]: CONST     R14 180      ; R14 := 180.000000
 34 [-]: LOADNIL   R15 R18      ; R15 := R16 := R17 := R18 := nil
 35 [-]: CONST     R19 0        ; R19 := 0.000000
 36 [-]: CONST     R20 0        ; R20 := 0.000000
 37 [-]: LOADNIL   R21 R22      ; R21 := R22 := nil
 38 [-]: NEWTABLE  R23 0 0      ; R23 := {}
 39 [-]: CONST     R24 0        ; R24 := 0.000000
 40 [-]: CONST     R25 1        ; R25 := 1.000000
 41 [-]: CONST     R26 2        ; R26 := 2.000000
 42 [-]: CONST     R27 3        ; R27 := 3.000000
 43 [-]: CONST     R28 4        ; R28 := 4.000000
 44 [-]: CONST     R29 5        ; R29 := 5.000000
 45 [-]: MOVE      R30 R24      ; R30 := R24
 46 [-]: LOADNIL   R31 R38      ; R31 := R32 := R33 := R34 := R35 := R36 := R37 := R38 := nil
 47 [-]: LOADKB    R39 0 0      ; R39 := false
 48 [-]: LOADNIL   R40 R40      ; R40 := nil
 49 [-]: NEWTABLE  R41 0 0      ; R41 := {}
 50 [-]: LOADNIL   R42 R42      ; R42 := nil
 51 [-]: NEWTABLE  R43 0 0      ; R43 := {}
 52 [-]: LOADNIL   R44 R49      ; R44 := R45 := R46 := R47 := R48 := R49 := nil
 53 [-]: CLOSURE   R50 0        ; R50 := closure(Function #1)
 54 [-]: SETGLOBAL R50 K16      ; Evaluate := R50
 55 [-]: CLOSURE   R50 1        ; R50 := closure(Function #2)
 56 [-]: MOVE      R0 R36       ; R0 := R36
 57 [-]: CLOSURE   R51 2        ; R51 := closure(Function #3)
 58 [-]: MOVE      R0 R15       ; R0 := R15
 59 [-]: MOVE      R0 R11       ; R0 := R11
 60 [-]: MOVE      R0 R4        ; R0 := R4
 61 [-]: CLOSURE   R52 3        ; R52 := closure(Function #4)
 62 [-]: MOVE      R0 R15       ; R0 := R15
 63 [-]: MOVE      R0 R12       ; R0 := R12
 64 [-]: MOVE      R0 R46       ; R0 := R46
 65 [-]: MOVE      R0 R13       ; R0 := R13
 66 [-]: MOVE      R0 R47       ; R0 := R47
 67 [-]: CLOSURE   R53 4        ; R53 := closure(Function #5)
 68 [-]: MOVE      R0 R15       ; R0 := R15
 69 [-]: MOVE      R0 R12       ; R0 := R12
 70 [-]: MOVE      R0 R13       ; R0 := R13
 71 [-]: MOVE      R0 R52       ; R0 := R52
 72 [-]: CLOSURE   R54 5        ; R54 := closure(Function #6)
 73 [-]: MOVE      R0 R2        ; R0 := R2
 74 [-]: MOVE      R0 R22       ; R0 := R22
 75 [-]: CLOSURE   R55 6        ; R55 := closure(Function #7)
 76 [-]: MOVE      R0 R30       ; R0 := R30
 77 [-]: MOVE      R0 R25       ; R0 := R25
 78 [-]: MOVE      R0 R2        ; R0 := R2
 79 [-]: MOVE      R0 R22       ; R0 := R22
 80 [-]: MOVE      R0 R26       ; R0 := R26
 81 [-]: MOVE      R0 R33       ; R0 := R33
 82 [-]: MOVE      R0 R37       ; R0 := R37
 83 [-]: MOVE      R0 R4        ; R0 := R4
 84 [-]: MOVE      R0 R7        ; R0 := R7
 85 [-]: MOVE      R0 R27       ; R0 := R27
 86 [-]: MOVE      R0 R32       ; R0 := R32
 87 [-]: MOVE      R0 R8        ; R0 := R8
 88 [-]: MOVE      R0 R43       ; R0 := R43
 89 [-]: MOVE      R0 R44       ; R0 := R44
 90 [-]: MOVE      R0 R45       ; R0 := R45
 91 [-]: MOVE      R0 R28       ; R0 := R28
 92 [-]: MOVE      R0 R23       ; R0 := R23
 93 [-]: MOVE      R0 R36       ; R0 := R36
 94 [-]: MOVE      R0 R21       ; R0 := R21
 95 [-]: MOVE      R0 R15       ; R0 := R15
 96 [-]: MOVE      R0 R11       ; R0 := R11
 97 [-]: MOVE      R0 R14       ; R0 := R14
 98 [-]: MOVE      R0 R38       ; R0 := R38
 99 [-]: MOVE      R0 R49       ; R0 := R49
100 [-]: MOVE      R0 R51       ; R0 := R51
101 [-]: MOVE      R0 R6        ; R0 := R6
102 [-]: MOVE      R0 R46       ; R0 := R46
103 [-]: MOVE      R0 R0        ; R0 := R0
104 [-]: MOVE      R0 R47       ; R0 := R47
105 [-]: MOVE      R0 R52       ; R0 := R52
106 [-]: MOVE      R0 R5        ; R0 := R5
107 [-]: MOVE      R0 R50       ; R0 := R50
108 [-]: MOVE      R0 R53       ; R0 := R53
109 [-]: MOVE      R0 R54       ; R0 := R54
110 [-]: MOVE      R0 R29       ; R0 := R29
111 [-]: MOVE      R0 R40       ; R0 := R40
112 [-]: MOVE      R0 R9        ; R0 := R9
113 [-]: CLOSURE   R31 7        ; R31 := closure(Function #8)
114 [-]: MOVE      R0 R30       ; R0 := R30
115 [-]: MOVE      R0 R15       ; R0 := R15
116 [-]: MOVE      R0 R10       ; R0 := R10
117 [-]: MOVE      R0 R55       ; R0 := R55
118 [-]: CLOSURE   R56 8        ; R56 := closure(Function #9)
119 [-]: MOVE      R0 R15       ; R0 := R15
120 [-]: MOVE      R0 R21       ; R0 := R21
121 [-]: MOVE      R0 R16       ; R0 := R16
122 [-]: MOVE      R0 R17       ; R0 := R17
123 [-]: MOVE      R0 R18       ; R0 := R18
124 [-]: MOVE      R0 R19       ; R0 := R19
125 [-]: MOVE      R0 R20       ; R0 := R20
126 [-]: MOVE      R0 R22       ; R0 := R22
127 [-]: MOVE      R0 R23       ; R0 := R23
128 [-]: MOVE      R0 R14       ; R0 := R14
129 [-]: MOVE      R0 R33       ; R0 := R33
130 [-]: MOVE      R0 R34       ; R0 := R34
131 [-]: MOVE      R0 R36       ; R0 := R36
132 [-]: MOVE      R0 R42       ; R0 := R42
133 [-]: MOVE      R0 R41       ; R0 := R41
134 [-]: MOVE      R0 R43       ; R0 := R43
135 [-]: MOVE      R0 R44       ; R0 := R44
136 [-]: MOVE      R0 R45       ; R0 := R45
137 [-]: MOVE      R0 R35       ; R0 := R35
138 [-]: MOVE      R0 R50       ; R0 := R50
139 [-]: MOVE      R0 R30       ; R0 := R30
140 [-]: MOVE      R0 R28       ; R0 := R28
141 [-]: MOVE      R0 R32       ; R0 := R32
142 [-]: MOVE      R0 R40       ; R0 := R40
143 [-]: MOVE      R0 R48       ; R0 := R48
144 [-]: MOVE      R0 R1        ; R0 := R1
145 [-]: MOVE      R0 R49       ; R0 := R49
146 [-]: MOVE      R0 R3        ; R0 := R3
147 [-]: MOVE      R0 R31       ; R0 := R31
148 [-]: MOVE      R0 R25       ; R0 := R25
149 [-]: MOVE      R0 R10       ; R0 := R10
150 [-]: MOVE      R0 R26       ; R0 := R26
151 [-]: CLOSURE   R57 9        ; R57 := closure(Function #10)
152 [-]: MOVE      R0 R56       ; R0 := R56
153 [-]: MOVE      R0 R30       ; R0 := R30
154 [-]: MOVE      R0 R25       ; R0 := R25
155 [-]: MOVE      R0 R21       ; R0 := R21
156 [-]: MOVE      R0 R31       ; R0 := R31
157 [-]: MOVE      R0 R26       ; R0 := R26
158 [-]: MOVE      R0 R27       ; R0 := R27
159 [-]: MOVE      R0 R28       ; R0 := R28
160 [-]: MOVE      R0 R48       ; R0 := R48
161 [-]: MOVE      R0 R49       ; R0 := R49
162 [-]: MOVE      R0 R36       ; R0 := R36
163 [-]: MOVE      R0 R4        ; R0 := R4
164 [-]: MOVE      R0 R29       ; R0 := R29
165 [-]: MOVE      R0 R14       ; R0 := R14
166 [-]: MOVE      R0 R39       ; R0 := R39
167 [-]: MOVE      R0 R2        ; R0 := R2
168 [-]: MOVE      R0 R22       ; R0 := R22
169 [-]: MOVE      R0 R37       ; R0 := R37
170 [-]: MOVE      R0 R34       ; R0 := R34
171 [-]: MOVE      R0 R41       ; R0 := R41
172 [-]: MOVE      R0 R43       ; R0 := R43
173 [-]: MOVE      R0 R44       ; R0 := R44
174 [-]: MOVE      R0 R45       ; R0 := R45
175 [-]: MOVE      R0 R16       ; R0 := R16
176 [-]: MOVE      R0 R46       ; R0 := R46
177 [-]: MOVE      R0 R47       ; R0 := R47
178 [-]: MOVE      R0 R1        ; R0 := R1
179 [-]: MOVE      R0 R15       ; R0 := R15
180 [-]: MOVE      R0 R11       ; R0 := R11
181 [-]: SETGLOBAL R57 K17      ; ResourceTheftStart := R57
182 [-]: CLOSURE   R57 10       ; R57 := closure(Function #11)
183 [-]: MOVE      R0 R36       ; R0 := R36
184 [-]: SETGLOBAL R57 K18      ; OnAgentRegistered := R57
185 [-]: CLOSURE   R57 11       ; R57 := closure(Function #12)
186 [-]: MOVE      R0 R23       ; R0 := R23
187 [-]: SETGLOBAL R57 K19      ; OnPlayersChanged := R57
188 [-]: CLOSURE   R57 12       ; R57 := closure(Function #13)
189 [-]: MOVE      R0 R32       ; R0 := R32
190 [-]: MOVE      R0 R31       ; R0 := R31
191 [-]: MOVE      R0 R28       ; R0 := R28
192 [-]: MOVE      R0 R40       ; R0 := R40
193 [-]: MOVE      R0 R17       ; R0 := R17
194 [-]: MOVE      R0 R33       ; R0 := R33
195 [-]: MOVE      R0 R27       ; R0 := R27
196 [-]: SETGLOBAL R57 K20      ; OnActivated := R57
197 [-]: CLOSURE   R57 13       ; R57 := closure(Function #14)
198 [-]: SETGLOBAL R57 K21      ; GetMixtureCompleteScript := R57
199 [-]: CLOSURE   R57 14       ; R57 := closure(Function #15)
200 [-]: SETGLOBAL R57 K22      ; GearItemEval := R57
201 [-]: CLOSURE   R57 15       ; R57 := closure(Function #16)
202 [-]: SETGLOBAL R57 K23      ; GearItemExecute := R57
203 [-]: RETURN    R0 1         ; return 


; Function #1:
;
; Name:            
; Defined at line: 74
; #Upvalues:       0
; #Parameters:     1
; Is_vararg:       0
; Max Stack Size:  11

  1 [-]: GETGLOBAL R1 K0        ; R1 := 0x89326c93
  2 [-]: SELF      R1 R1 K1     ; R2 := R1; R1 := R1[0xc7b81e8d]
  3 [-]: GETGLOBAL R3 K2        ; R3 := 0x0469f296
  4 [-]: LOADK     R4 K3        ; R4 := "LootWagonAction"
  5 [-]: CALL      R3 2 2       ; R3 := R3(R4)
  6 [-]: SELF      R4 R0 K4     ; R5 := R0; R4 := R0[0xd1586535]
  7 [-]: CALL      R4 2 0       ; R4,... := R4(R5)
  8 [-]: CALL      R1 0 2       ; R1 := R1(R2,...)
  9 [-]: SELF      R2 R1 K5     ; R3 := R1; R2 := R1[0xbebad19f]
 10 [-]: MOVE      R4 R0        ; R4 := R0
 11 [-]: CALL      R2 3 2       ; R2 := R2(R3,R4)
 12 [-]: SELF      R3 R0 K6     ; R4 := R0; R3 := R0[0xc5b92518]
 13 [-]: CALL      R3 2 2       ; R3 := R3(R4)
 14 [-]: LT        0 R3 R2      ; if R3 >= R2 then PC := 28
 15 [-]: JMP       28           ; PC := 28
 16 [-]: GETGLOBAL R4 K7        ; R4 := 0x3d106989
 17 [-]: LOADK     R5 K8        ; R5 := "EventDefendMixer.lua Evaluate failed on hint "
 18 [-]: SELF      R6 R0 K9     ; R7 := R0; R6 := R0[0xed4e0128]
 19 [-]: CALL      R6 2 2       ; R6 := R6(R7)
 20 [-]: LOADK     R7 K10       ; R7 := ", action was too far: "
 21 [-]: MOVE      R8 R2        ; R8 := R2
 22 [-]: LOADK     R9 K11       ; R9 := " > "
 23 [-]: MOVE      R10 R3       ; R10 := R3
 24 [-]: CONCAT    R5 R5 R10    ; R5 := R5 .. R6 .. R7 .. R8 .. R9 .. R10
 25 [-]: CALL      R4 2 1       ; R4(R5)
 26 [-]: CONST     R4 0         ; R4 := 0.000000
 27 [-]: RETURN    R4 2         ; return R4
 28 [-]: GETGLOBAL R4 K12       ; R4 := 0x7b998233
 29 [-]: GETGLOBAL R5 K13       ; R5 := _T
 30 [-]: GETTABLE  R5 R5 K14    ; R5 := R5["ActiveJob"]
 31 [-]: CALL      R4 2 2       ; R4 := R4(R5)
 32 [-]: TEST      R4 0         ; if not R4 then PC := 37
 33 [-]: JMP       37           ; PC := 37
 34 [-]: LOADKB    R4 0 0       ; R4 := false
 35 [-]: TEST      R4 0         ; if not R4 then PC := 46
 36 [-]: JMP       46           ; PC := 46
 37 [-]: GETGLOBAL R4 K7        ; R4 := 0x3d106989
 38 [-]: LOADK     R5 K15       ; R5 := "EventDefendMixer.lua Evaluate passed on hint "
 39 [-]: SELF      R6 R0 K9     ; R7 := R0; R6 := R0[0xed4e0128]
 40 [-]: CALL      R6 2 2       ; R6 := R6(R7)
 41 [-]: CONCAT    R5 R5 R6     ; R5 := R5 .. R6
 42 [-]: CALL      R4 2 1       ; R4(R5)
 43 [-]: CONST     R4 1         ; R4 := 1.000000
 44 [-]: RETURN    R4 2         ; return R4
 45 [-]: JMP       54           ; PC := 54
 46 [-]: GETGLOBAL R4 K7        ; R4 := 0x3d106989
 47 [-]: LOADK     R5 K8        ; R5 := "EventDefendMixer.lua Evaluate failed on hint "
 48 [-]: SELF      R6 R0 K9     ; R7 := R0; R6 := R0[0xed4e0128]
 49 [-]: CALL      R6 2 2       ; R6 := R6(R7)
 50 [-]: CONCAT    R5 R5 R6     ; R5 := R5 .. R6
 51 [-]: CALL      R4 2 1       ; R4(R5)
 52 [-]: CONST     R4 0         ; R4 := 0.000000
 53 [-]: RETURN    R4 2         ; return R4
 54 [-]: RETURN    R0 1         ; return 


; Function #2:
;
; Name:            
; Defined at line: 92
; #Upvalues:       1
; #Parameters:     1
; Is_vararg:       0
; Max Stack Size:  7

  1 [-]: GETUPVAL  R1 U0        ; R1 := U0
  2 [-]: SELF      R1 R1 K0     ; R2 := R1; R1 := R1[0x069d881f]
  3 [-]: MOVE      R3 R0        ; R3 := R0
  4 [-]: CALL      R1 3 1       ; R1(R2,R3)
  5 [-]: TEST      R0 0         ; if not R0 then PC := 19
  6 [-]: JMP       19           ; PC := 19
  7 [-]: GETUPVAL  R1 U0        ; R1 := U0
  8 [-]: SELF      R1 R1 K1     ; R2 := R1; R1 := R1[0x1ac1655c]
  9 [-]: CALL      R1 2 2       ; R1 := R1(R2)
 10 [-]: SELF      R1 R1 K2     ; R2 := R1; R1 := R1[0xa383de31]
 11 [-]: GETGLOBAL R3 K3        ; R3 := 0x0469f296
 12 [-]: LOADK     R4 K4        ; R4 := "ResourceTheftInvuln"
 13 [-]: CALL      R3 2 2       ; R3 := R3(R4)
 14 [-]: CONST     R4 25        ; R4 := 25.000000
 15 [-]: CONST     R5 6         ; R5 := 6.000000
 16 [-]: CONST     R6 0         ; R6 := 0.000000
 17 [-]: CALL      R1 6 1       ; R1(R2,R3,R4,R5,R6)
 18 [-]: JMP       27           ; PC := 27
 19 [-]: GETUPVAL  R1 U0        ; R1 := U0
 20 [-]: SELF      R1 R1 K1     ; R2 := R1; R1 := R1[0x1ac1655c]
 21 [-]: CALL      R1 2 2       ; R1 := R1(R2)
 22 [-]: SELF      R1 R1 K6     ; R2 := R1; R1 := R1[0x8e3e343e]
 23 [-]: GETGLOBAL R3 K3        ; R3 := 0x0469f296
 24 [-]: LOADK     R4 K4        ; R4 := "ResourceTheftInvuln"
 25 [-]: CALL      R3 2 0       ; R3,... := R3(R4)
 26 [-]: CALL      R1 0 1       ; R1(R2,...)
 27 [-]: RETURN    R0 1         ; return 


; Function #3:
;
; Name:            
; Defined at line: 101
; #Upvalues:       3
; #Parameters:     0
; Is_vararg:       0
; Max Stack Size:  5

  1 [-]: GETUPVAL  R0 U0        ; R0 := U0
  2 [-]: SELF      R0 R0 K0     ; R1 := R0; R0 := R0[0x751f061d]
  3 [-]: GETUPVAL  R2 U1        ; R2 := U1
  4 [-]: GETGLOBAL R3 K1        ; R3 := 0x5bced4c4
  5 [-]: GETTABLE  R3 R3 K2     ; R3 := R3[0x99675e23]
  6 [-]: GETUPVAL  R4 U2        ; R4 := U2
  7 [-]: GETTABLE  R4 R4 K3     ; R4 := R4[0x826f2ca6]
  8 [-]: CALL      R4 1 0       ; R4,... := R4()
  9 [-]: CALL      R3 0 0       ; R3,... := R3(R4,...)
 10 [-]: CALL      R0 0 1       ; R0(R1,...)
 11 [-]: RETURN    R0 1         ; return 


; Function #4:
;
; Name:            
; Defined at line: 105
; #Upvalues:       5
; #Parameters:     0
; Is_vararg:       0
; Max Stack Size:  6

  1 [-]: GETGLOBAL R0 K0        ; R0 := 0x64fb1586
  2 [-]: GETUPVAL  R1 U0        ; R1 := U0
  3 [-]: SELF      R1 R1 K1     ; R2 := R1; R1 := R1[0x0eb34c69]
  4 [-]: GETUPVAL  R3 U1        ; R3 := U1
  5 [-]: CONST     R4 0         ; R4 := 0.000000
  6 [-]: CALL      R1 4 0       ; R1,... := R1(R2,R3,R4)
  7 [-]: CALL      R0 0 2       ; R0 := R0(R1,...)
  8 [-]: LOADK     R1 K2        ; R1 := "/4 "
  9 [-]: GETUPVAL  R2 U2        ; R2 := U2
 10 [-]: GETTABLE  R2 R2 K3     ; R2 := R2[0x603636ad]
 11 [-]: GETGLOBAL R3 K4        ; R3 := 0xfadf5add
 12 [-]: SELF      R3 R3 K5     ; R4 := R3; R3 := R3[0xd3a9d01f]
 13 [-]: CALL      R3 2 2       ; R3 := R3(R4)
 14 [-]: SELF      R3 R3 K6     ; R4 := R3; R3 := R3[0x6d604ba7]
 15 [-]: CALL      R3 2 0       ; R3,... := R3(R4)
 16 [-]: CALL      R2 0 2       ; R2 := R2(R3,...)
 17 [-]: CONCAT    R0 R0 R2     ; R0 := R0 .. R1 .. R2
 18 [-]: GETUPVAL  R1 U2        ; R1 := U2
 19 [-]: GETTABLE  R1 R1 K7     ; R1 := R1[0x425b8f0d]
 20 [-]: CONST     R2 28        ; R2 := 28.000000
 21 [-]: LOADKB    R3 1 0       ; R3 := true
 22 [-]: CALL      R1 3 1       ; R1(R2,R3)
 23 [-]: GETUPVAL  R1 U2        ; R1 := U2
 24 [-]: GETTABLE  R1 R1 K8     ; R1 := R1[0x3f8a850c]
 25 [-]: MOVE      R2 R0        ; R2 := R0
 26 [-]: CALL      R1 2 1       ; R1(R2)
 27 [-]: GETGLOBAL R1 K0        ; R1 := 0x64fb1586
 28 [-]: GETUPVAL  R2 U0        ; R2 := U0
 29 [-]: SELF      R2 R2 K1     ; R3 := R2; R2 := R2[0x0eb34c69]
 30 [-]: GETUPVAL  R4 U3        ; R4 := U3
 31 [-]: CONST     R5 0         ; R5 := 0.000000
 32 [-]: CALL      R2 4 0       ; R2,... := R2(R3,R4,R5)
 33 [-]: CALL      R1 0 2       ; R1 := R1(R2,...)
 34 [-]: LOADK     R2 K2        ; R2 := "/4 "
 35 [-]: GETUPVAL  R3 U4        ; R3 := U4
 36 [-]: GETTABLE  R3 R3 K3     ; R3 := R3[0x603636ad]
 37 [-]: GETGLOBAL R4 K9        ; R4 := 0xab5dae29
 38 [-]: SELF      R4 R4 K5     ; R5 := R4; R4 := R4[0xd3a9d01f]
 39 [-]: CALL      R4 2 2       ; R4 := R4(R5)
 40 [-]: SELF      R4 R4 K6     ; R5 := R4; R4 := R4[0x6d604ba7]
 41 [-]: CALL      R4 2 0       ; R4,... := R4(R5)
 42 [-]: CALL      R3 0 2       ; R3 := R3(R4,...)
 43 [-]: CONCAT    R0 R1 R3     ; R0 := R1 .. R2 .. R3
 44 [-]: GETUPVAL  R1 U4        ; R1 := U4
 45 [-]: GETTABLE  R1 R1 K7     ; R1 := R1[0x425b8f0d]
 46 [-]: CONST     R2 28        ; R2 := 28.000000
 47 [-]: LOADKB    R3 1 0       ; R3 := true
 48 [-]: CALL      R1 3 1       ; R1(R2,R3)
 49 [-]: GETUPVAL  R1 U4        ; R1 := U4
 50 [-]: GETTABLE  R1 R1 K8     ; R1 := R1[0x3f8a850c]
 51 [-]: MOVE      R2 R0        ; R2 := R0
 52 [-]: CALL      R1 2 1       ; R1(R2)
 53 [-]: RETURN    R0 1         ; return 


; Function #5:
;
; Name:            
; Defined at line: 115
; #Upvalues:       4
; #Parameters:     1
; Is_vararg:       0
; Max Stack Size:  8

  1 [-]: SELF      R1 R0 K0     ; R2 := R0; R1 := R0[0xf2deaf69]
  2 [-]: GETGLOBAL R3 K1        ; R3 := 0xfadf5add
  3 [-]: CALL      R1 3 2       ; R1 := R1(R2,R3)
  4 [-]: TEST      R1 0         ; if not R1 then PC := 24
  5 [-]: JMP       24           ; PC := 24
  6 [-]: GETGLOBAL R1 K2        ; R1 := 0xd644c2f1
  7 [-]: LOADK     R2 K3        ; R2 := "Added Clan event item"
  8 [-]: CALL      R1 2 1       ; R1(R2)
  9 [-]: GETUPVAL  R1 U0        ; R1 := U0
 10 [-]: SELF      R1 R1 K4     ; R2 := R1; R1 := R1[0x751f061d]
 11 [-]: GETUPVAL  R3 U1        ; R3 := U1
 12 [-]: GETUPVAL  R4 U0        ; R4 := U0
 13 [-]: SELF      R4 R4 K5     ; R5 := R4; R4 := R4[0x0eb34c69]
 14 [-]: GETUPVAL  R6 U1        ; R6 := U1
 15 [-]: CONST     R7 0         ; R7 := 0.000000
 16 [-]: CALL      R4 4 2       ; R4 := R4(R5,R6,R7)
 17 [-]: ADD       R4 R4 K6     ; R4 := R4 + 1.000000
 18 [-]: CALL      R1 4 1       ; R1(R2,R3,R4)
 19 [-]: GETUPVAL  R1 U0        ; R1 := U0
 20 [-]: SELF      R1 R1 K7     ; R2 := R1; R1 := R1[0xd3519c8f]
 21 [-]: CONST     R3 250       ; R3 := 250.000000
 22 [-]: CALL      R1 3 1       ; R1(R2,R3)
 23 [-]: JMP       46           ; PC := 46
 24 [-]: SELF      R1 R0 K0     ; R2 := R0; R1 := R0[0xf2deaf69]
 25 [-]: GETGLOBAL R3 K8        ; R3 := 0xab5dae29
 26 [-]: CALL      R1 3 2       ; R1 := R1(R2,R3)
 27 [-]: TEST      R1 0         ; if not R1 then PC := 46
 28 [-]: JMP       46           ; PC := 46
 29 [-]: GETGLOBAL R1 K2        ; R1 := 0xd644c2f1
 30 [-]: LOADK     R2 K9        ; R2 := "Added event item"
 31 [-]: CALL      R1 2 1       ; R1(R2)
 32 [-]: GETUPVAL  R1 U0        ; R1 := U0
 33 [-]: SELF      R1 R1 K4     ; R2 := R1; R1 := R1[0x751f061d]
 34 [-]: GETUPVAL  R3 U2        ; R3 := U2
 35 [-]: GETUPVAL  R4 U0        ; R4 := U0
 36 [-]: SELF      R4 R4 K5     ; R5 := R4; R4 := R4[0x0eb34c69]
 37 [-]: GETUPVAL  R6 U2        ; R6 := U2
 38 [-]: CONST     R7 0         ; R7 := 0.000000
 39 [-]: CALL      R4 4 2       ; R4 := R4(R5,R6,R7)
 40 [-]: ADD       R4 R4 K6     ; R4 := R4 + 1.000000
 41 [-]: CALL      R1 4 1       ; R1(R2,R3,R4)
 42 [-]: GETUPVAL  R1 U0        ; R1 := U0
 43 [-]: SELF      R1 R1 K7     ; R2 := R1; R1 := R1[0xd3519c8f]
 44 [-]: CONST     R3 250       ; R3 := 250.000000
 45 [-]: CALL      R1 3 1       ; R1(R2,R3)
 46 [-]: GETUPVAL  R1 U3        ; R1 := U3
 47 [-]: CALL      R1 1 1       ; R1()
 48 [-]: RETURN    R0 1         ; return 


; Function #6:
;
; Name:            
; Defined at line: 128
; #Upvalues:       2
; #Parameters:     1
; Is_vararg:       0
; Max Stack Size:  4

  1 [-]: GETUPVAL  R1 U0        ; R1 := U0
  2 [-]: GETTABLE  R1 R1 K0     ; R1 := R1[0x9742b85b]
  3 [-]: GETUPVAL  R2 U1        ; R2 := U1
  4 [-]: MOVE      R3 R0        ; R3 := R0
  5 [-]: CALL      R1 3 1       ; R1(R2,R3)
  6 [-]: RETURN    R0 1         ; return 


; Function #7:
;
; Name:            
; Defined at line: 132
; #Upvalues:       37
; #Parameters:     0
; Is_vararg:       0
; Max Stack Size:  32

  1 [-]: GETUPVAL  R0 U0        ; R0 := U0
  2 [-]: GETUPVAL  R1 U1        ; R1 := U1
  3 [-]: EQ        0 R0 R1      ; if R0 ~= R1 then PC := 13
  4 [-]: JMP       13           ; PC := 13
  5 [-]: GETUPVAL  R0 U2        ; R0 := U2
  6 [-]: GETTABLE  R0 R0 K0     ; R0 := R0[0x9742b85b]
  7 [-]: GETUPVAL  R1 U3        ; R1 := U3
  8 [-]: GETGLOBAL R2 K1        ; R2 := 0x0469f296
  9 [-]: LOADK     R3 K2        ; R3 := "Arrived"
 10 [-]: CALL      R2 2 0       ; R2,... := R2(R3)
 11 [-]: CALL      R0 0 1       ; R0(R1,...)
 12 [-]: JMP       307          ; PC := 307
 13 [-]: GETUPVAL  R0 U0        ; R0 := U0
 14 [-]: GETUPVAL  R1 U4        ; R1 := U4
 15 [-]: EQ        0 R0 R1      ; if R0 ~= R1 then PC := 33
 16 [-]: JMP       33           ; PC := 33
 17 [-]: GETUPVAL  R0 U5        ; R0 := U5
 18 [-]: SELF      R0 R0 K3     ; R1 := R0; R0 := R0[0x383d2e7d]
 19 [-]: CALL      R0 2 1       ; R0(R1)
 20 [-]: GETUPVAL  R0 U5        ; R0 := U5
 21 [-]: SELF      R0 R0 K4     ; R1 := R0; R0 := R0[0x47901f07]
 22 [-]: GETGLOBAL R2 K5        ; R2 := 0x656d204c
 23 [-]: GETGLOBAL R3 K6        ; R3 := EMPTY_SYMBOL
 24 [-]: CALL      R0 4 2       ; R0 := R0(R1,R2,R3)
 25 [-]: SETUPVAL  R0 U6        ; U82 := R6
 26 [-]: GETUPVAL  R0 U7        ; R0 := U7
 27 [-]: GETTABLE  R0 R0 K7     ; R0 := R0[0xa1df01d6]
 28 [-]: GETUPVAL  R1 U8        ; R1 := U8
 29 [-]: GETUPVAL  R2 U7        ; R2 := U7
 30 [-]: GETTABLE  R2 R2 K8     ; R2 := R2["GENERIC_ICON"]
 31 [-]: CALL      R0 3 1       ; R0(R1,R2)
 32 [-]: JMP       307          ; PC := 307
 33 [-]: GETUPVAL  R0 U0        ; R0 := U0
 34 [-]: GETUPVAL  R1 U9        ; R1 := U9
 35 [-]: EQ        0 R0 R1      ; if R0 ~= R1 then PC := 86
 36 [-]: JMP       86           ; PC := 86
 37 [-]: GETGLOBAL R0 K9        ; R0 := 0x7b998233
 38 [-]: GETUPVAL  R1 U6        ; R1 := U6
 39 [-]: CALL      R0 2 2       ; R0 := R0(R1)
 40 [-]: TEST      R0 1         ; if R0 then PC := 45
 41 [-]: JMP       45           ; PC := 45
 42 [-]: GETUPVAL  R0 U6        ; R0 := U6
 43 [-]: SELF      R0 R0 K10    ; R1 := R0; R0 := R0[0xa2880940]
 44 [-]: CALL      R0 2 1       ; R0(R1)
 45 [-]: GETUPVAL  R0 U10       ; R0 := U10
 46 [-]: SELF      R0 R0 K3     ; R1 := R0; R0 := R0[0x383d2e7d]
 47 [-]: CALL      R0 2 1       ; R0(R1)
 48 [-]: GETUPVAL  R0 U10       ; R0 := U10
 49 [-]: SELF      R0 R0 K4     ; R1 := R0; R0 := R0[0x47901f07]
 50 [-]: GETGLOBAL R2 K5        ; R2 := 0x656d204c
 51 [-]: GETGLOBAL R3 K6        ; R3 := EMPTY_SYMBOL
 52 [-]: GETGLOBAL R4 K11       ; R4 := 0xa421af95
 53 [-]: CONST     R5 0         ; R5 := 0.000000
 54 [-]: CONST     R6 1         ; R6 := 1.000000
 55 [-]: CONST     R7 0         ; R7 := 0.000000
 56 [-]: CALL      R4 4 0       ; R4,... := R4(R5,R6,R7)
 57 [-]: CALL      R0 0 2       ; R0 := R0(R1,...)
 58 [-]: SETUPVAL  R0 U6        ; U82 := R6
 59 [-]: GETGLOBAL R0 K12       ; R0 := 0x11a19c5e
 60 [-]: GETUPVAL  R1 U10       ; R1 := U10
 61 [-]: LOADK     R2 K13       ; R2 := "OnActivated"
 62 [-]: CALL      R0 3 1       ; R0(R1,R2)
 63 [-]: GETUPVAL  R0 U7        ; R0 := U7
 64 [-]: GETTABLE  R0 R0 K7     ; R0 := R0[0xa1df01d6]
 65 [-]: GETUPVAL  R1 U11       ; R1 := U11
 66 [-]: GETUPVAL  R2 U7        ; R2 := U7
 67 [-]: GETTABLE  R2 R2 K8     ; R2 := R2["GENERIC_ICON"]
 68 [-]: CALL      R0 3 1       ; R0(R1,R2)
 69 [-]: GETGLOBAL R0 K14       ; R0 := 0xc8802016
 70 [-]: GETUPVAL  R1 U12       ; R1 := U12
 71 [-]: CALL      R0 2 4       ; R0,R1,R2 := R0(R1)
 72 [-]: JMP       75           ; PC := 75
 73 [-]: SELF      R5 R4 K15    ; R6 := R4; R5 := R4[0xf4e253b6]
 74 [-]: CALL      R5 2 1       ; R5(R6)
 75 [-]: TFORLOOP  R0 2         ; R3,R4 :=  R0(R1,R2); if R3 ~= nil then begin PC = 73; R2 := R3 end
 76 [-]: JMP       73           ; PC := 73
 77 [-]: GETUPVAL  R5 U13       ; R5 := U13
 78 [-]: SELF      R5 R5 K16    ; R6 := R5; R5 := R5[0x8eb2112d]
 79 [-]: LOADK     R7 K17       ; R7 := "Enable"
 80 [-]: CALL      R5 3 1       ; R5(R6,R7)
 81 [-]: GETUPVAL  R5 U14       ; R5 := U14
 82 [-]: SELF      R5 R5 K16    ; R6 := R5; R5 := R5[0x8eb2112d]
 83 [-]: LOADK     R7 K18       ; R7 := "Disable"
 84 [-]: CALL      R5 3 1       ; R5(R6,R7)
 85 [-]: JMP       307          ; PC := 307
 86 [-]: GETUPVAL  R5 U0        ; R5 := U0
 87 [-]: GETUPVAL  R6 U15       ; R6 := U15
 88 [-]: EQ        0 R5 R6      ; if R5 ~= R6 then PC := 268
 89 [-]: JMP       268          ; PC := 268
 90 [-]: GETUPVAL  R5 U2        ; R5 := U2
 91 [-]: GETTABLE  R5 R5 K0     ; R5 := R5[0x9742b85b]
 92 [-]: GETUPVAL  R6 U3        ; R6 := U3
 93 [-]: GETGLOBAL R7 K1        ; R7 := 0x0469f296
 94 [-]: LOADK     R8 K19       ; R8 := "MixingStarted"
 95 [-]: CALL      R7 2 0       ; R7,... := R7(R8)
 96 [-]: CALL      R5 0 1       ; R5(R6,...)
 97 [-]: GETGLOBAL R5 K14       ; R5 := 0xc8802016
 98 [-]: GETUPVAL  R6 U16       ; R6 := U16
 99 [-]: CALL      R5 2 4       ; R5,R6,R7 := R5(R6)
100 [-]: JMP       152          ; PC := 152
101 [-]: SELF      R10 R9 K20   ; R11 := R9; R10 := R9[0xbb610e5b]
102 [-]: CALL      R10 2 2      ; R10 := R10(R11)
103 [-]: GETGLOBAL R11 K9       ; R11 := 0x7b998233
104 [-]: MOVE      R12 R10      ; R12 := R10
105 [-]: CALL      R11 2 2      ; R11 := R11(R12)
106 [-]: TEST      R11 1        ; if R11 then PC := 152
107 [-]: JMP       152          ; PC := 152
108 [-]: SELF      R11 R10 K21  ; R12 := R10; R11 := R10[0xde321e6f]
109 [-]: CALL      R11 2 2      ; R11 := R11(R12)
110 [-]: CONST     R12 0        ; R12 := 0.000000
111 [-]: SELF      R13 R11 K22  ; R14 := R11; R13 := R11[0x4056d183]
112 [-]: CALL      R13 2 2      ; R13 := R13(R14)
113 [-]: SUB       R13 R13 K23  ; R13 := R13 - 1.000000
114 [-]: CONST     R14 1        ; R14 := 1.000000
115 [-]: FORPREP   R12 151      ; R12 -= R14; PC := 151
116 [-]: SELF      R16 R11 K24  ; R17 := R11; R16 := R11[0xe6e56442]
117 [-]: MOVE      R18 R15      ; R18 := R15
118 [-]: CALL      R16 3 2      ; R16 := R16(R17,R18)
119 [-]: GETGLOBAL R17 K9       ; R17 := 0x7b998233
120 [-]: MOVE      R18 R16      ; R18 := R16
121 [-]: CALL      R17 2 2      ; R17 := R17(R18)
122 [-]: TEST      R17 1        ; if R17 then PC := 151
123 [-]: JMP       151          ; PC := 151
124 [-]: SELF      R17 R16 K25  ; R18 := R16; R17 := R16[0xf2deaf69]
125 [-]: GETGLOBAL R19 K26      ; R19 := 0xab5dae29
126 [-]: CALL      R17 3 2      ; R17 := R17(R18,R19)
127 [-]: TEST      R17 0        ; if not R17 then PC := 138
128 [-]: JMP       138          ; PC := 138
129 [-]: GETUPVAL  R17 U2       ; R17 := U2
130 [-]: GETTABLE  R17 R17 K27  ; R17 := R17[0xf22cfc77]
131 [-]: GETUPVAL  R18 U3       ; R18 := U3
132 [-]: GETGLOBAL R19 K1       ; R19 := 0x0469f296
133 [-]: LOADK     R20 K28      ; R20 := "HasShard"
134 [-]: CALL      R19 2 2      ; R19 := R19(R20)
135 [-]: MOVE      R20 R10      ; R20 := R10
136 [-]: CALL      R17 4 1      ; R17(R18,R19,R20)
137 [-]: JMP       151          ; PC := 151
138 [-]: SELF      R17 R16 K25  ; R18 := R16; R17 := R16[0xf2deaf69]
139 [-]: GETGLOBAL R19 K29      ; R19 := 0xfadf5add
140 [-]: CALL      R17 3 2      ; R17 := R17(R18,R19)
141 [-]: TEST      R17 0        ; if not R17 then PC := 151
142 [-]: JMP       151          ; PC := 151
143 [-]: GETUPVAL  R17 U2       ; R17 := U2
144 [-]: GETTABLE  R17 R17 K27  ; R17 := R17[0xf22cfc77]
145 [-]: GETUPVAL  R18 U3       ; R18 := U3
146 [-]: GETGLOBAL R19 K1       ; R19 := 0x0469f296
147 [-]: LOADK     R20 K30      ; R20 := "HasClanTech"
148 [-]: CALL      R19 2 2      ; R19 := R19(R20)
149 [-]: MOVE      R20 R10      ; R20 := R10
150 [-]: CALL      R17 4 1      ; R17(R18,R19,R20)
151 [-]: FORLOOP   R12 116      ; R12 += R14; if R12 <= R13 then begin PC := 116; R15 := R12 end
152 [-]: TFORLOOP  R5 2         ; R8,R9 :=  R5(R6,R7); if R8 ~= nil then begin PC = 101; R7 := R8 end
153 [-]: JMP       101          ; PC := 101
154 [-]: GETGLOBAL R17 K9       ; R17 := 0x7b998233
155 [-]: GETUPVAL  R18 U6       ; R18 := U6
156 [-]: CALL      R17 2 2      ; R17 := R17(R18)
157 [-]: TEST      R17 1        ; if R17 then PC := 162
158 [-]: JMP       162          ; PC := 162
159 [-]: GETUPVAL  R17 U6       ; R17 := U6
160 [-]: SELF      R17 R17 K10  ; R18 := R17; R17 := R17[0xa2880940]
161 [-]: CALL      R17 2 1      ; R17(R18)
162 [-]: GETUPVAL  R17 U17      ; R17 := U17
163 [-]: SELF      R17 R17 K4   ; R18 := R17; R17 := R17[0x47901f07]
164 [-]: GETGLOBAL R19 K31      ; R19 := 0x30a9fa98
165 [-]: GETGLOBAL R20 K6       ; R20 := EMPTY_SYMBOL
166 [-]: GETGLOBAL R21 K11      ; R21 := 0xa421af95
167 [-]: CONST     R22 0        ; R22 := 0.000000
168 [-]: CONST     R23 2        ; R23 := 2.000000
169 [-]: CONST     R24 0        ; R24 := 0.000000
170 [-]: CALL      R21 4 0      ; R21,... := R21(R22,R23,R24)
171 [-]: CALL      R17 0 2      ; R17 := R17(R18,...)
172 [-]: SETUPVAL  R17 U6       ; U82 := R6
173 [-]: GETUPVAL  R17 U6       ; R17 := U6
174 [-]: SELF      R17 R17 K3   ; R18 := R17; R17 := R17[0x383d2e7d]
175 [-]: CALL      R17 2 1      ; R17(R18)
176 [-]: GETUPVAL  R17 U18      ; R17 := U18
177 [-]: SELF      R17 R17 K32  ; R18 := R17; R17 := R17[0x5b344f44]
178 [-]: LOADK     R19 K33      ; R19 := "OnAgentRegistered"
179 [-]: GETGLOBAL R20 K1       ; R20 := 0x0469f296
180 [-]: LOADK     R21 K34      ; R21 := "CaptureRegistration"
181 [-]: CALL      R20 2 0      ; R20,... := R20(R21)
182 [-]: CALL      R17 0 1      ; R17(R18,...)
183 [-]: GETUPVAL  R17 U19      ; R17 := U19
184 [-]: SELF      R17 R17 K35  ; R18 := R17; R17 := R17[0x0eb34c69]
185 [-]: GETUPVAL  R19 U20      ; R19 := U20
186 [-]: GETUPVAL  R20 U21      ; R20 := U21
187 [-]: CALL      R17 4 2      ; R17 := R17(R18,R19,R20)
188 [-]: GETUPVAL  R18 U23      ; R18 := U23
189 [-]: SELF      R18 R18 K36  ; R19 := R18; R18 := R18[0xbd2e96ea]
190 [-]: CONST     R20 1        ; R20 := 1.000000
191 [-]: GETUPVAL  R21 U24      ; R21 := U24
192 [-]: LOADKB    R22 1 0      ; R22 := true
193 [-]: CALL      R18 5 2      ; R18 := R18(R19,R20,R21,R22)
194 [-]: SETUPVAL  R18 U22      ; U82 := R22
195 [-]: GETUPVAL  R18 U7       ; R18 := U7
196 [-]: GETTABLE  R18 R18 K37  ; R18 := R18[0xe8fa0e68]
197 [-]: MOVE      R19 R17      ; R19 := R17
198 [-]: LOADKB    R20 0 0      ; R20 := false
199 [-]: LOADKB    R21 1 0      ; R21 := true
200 [-]: LOADKB    R22 0 0      ; R22 := false
201 [-]: LOADNIL   R23 R25      ; R23 := R24 := R25 := nil
202 [-]: GETUPVAL  R26 U25      ; R26 := U25
203 [-]: CALL      R18 9 1      ; R18(R19,R20,R21,R22,R23,R24,R25,R26)
204 [-]: GETUPVAL  R18 U7       ; R18 := U7
205 [-]: GETTABLE  R18 R18 K38  ; R18 := R18[0x1551aa65]
206 [-]: GETUPVAL  R19 U17      ; R19 := U17
207 [-]: CALL      R18 2 1      ; R18(R19)
208 [-]: GETGLOBAL R18 K39      ; R18 := _T
209 [-]: GETTABLE  R18 R18 K40  ; R18 := R18[0x8ee923fe]
210 [-]: LOADK     R19 K41      ; R19 := "DefendMixerItems1"
211 [-]: GETUPVAL  R20 U27      ; R20 := U27
212 [-]: GETTABLE  R20 R20 K42  ; R20 := R20["HT_LABEL"]
213 [-]: LOADK     R21 K43      ; R21 := 0.150000
214 [-]: CONST     R22 16       ; R22 := 16.000000
215 [-]: CALL      R18 5 2      ; R18 := R18(R19,R20,R21,R22)
216 [-]: SETUPVAL  R18 U26      ; U82 := R26
217 [-]: GETGLOBAL R18 K39      ; R18 := _T
218 [-]: GETTABLE  R18 R18 K40  ; R18 := R18[0x8ee923fe]
219 [-]: LOADK     R19 K44      ; R19 := "DefendMixerItems2"
220 [-]: GETUPVAL  R20 U27      ; R20 := U27
221 [-]: GETTABLE  R20 R20 K42  ; R20 := R20["HT_LABEL"]
222 [-]: LOADK     R21 K43      ; R21 := 0.150000
223 [-]: CONST     R22 16       ; R22 := 16.000000
224 [-]: CALL      R18 5 2      ; R18 := R18(R19,R20,R21,R22)
225 [-]: SETUPVAL  R18 U28      ; U82 := R28
226 [-]: GETUPVAL  R18 U29      ; R18 := U29
227 [-]: CALL      R18 1 1      ; R18()
228 [-]: GETUPVAL  R18 U7       ; R18 := U7
229 [-]: GETTABLE  R18 R18 K7   ; R18 := R18[0xa1df01d6]
230 [-]: GETUPVAL  R19 U30      ; R19 := U30
231 [-]: GETUPVAL  R20 U7       ; R20 := U7
232 [-]: GETTABLE  R20 R20 K45  ; R20 := R20["DEFEND_ICON"]
233 [-]: CALL      R18 3 1      ; R18(R19,R20)
234 [-]: GETUPVAL  R18 U31      ; R18 := U31
235 [-]: LOADKB    R19 0 0      ; R19 := false
236 [-]: CALL      R18 2 1      ; R18(R19)
237 [-]: GETGLOBAL R18 K39      ; R18 := _T
238 [-]: CLOSURE   R19 0        ; R19 := closure(Function #7.1)
239 [-]: GETUPVAL  R0 U32       ; R0 := U32
240 [-]: SETTABLE  R18 K46 R19  ; R18["AddToMixture"] := R19
241 [-]: CONST     R18 1        ; R18 := 1.000000
242 [-]: CONST     R19 3        ; R19 := 3.000000
243 [-]: CONST     R20 1        ; R20 := 1.000000
244 [-]: FORPREP   R18 266      ; R18 -= R20; PC := 266
245 [-]: GETUPVAL  R22 U21      ; R22 := U21
246 [-]: MUL       R22 R22 R21  ; R22 := R22 * R21
247 [-]: MUL       R22 R22 K47  ; R22 := R22 * 0.250000
248 [-]: GETUPVAL  R23 U21      ; R23 := U21
249 [-]: SUB       R23 R23 R17  ; R23 := R23 - R17
250 [-]: LT        0 R23 R22    ; if R23 >= R22 then PC := 266
251 [-]: JMP       266          ; PC := 266
252 [-]: GETUPVAL  R23 U21      ; R23 := U21
253 [-]: SUB       R23 R23 R17  ; R23 := R23 - R17
254 [-]: SUB       R23 R22 R23  ; R23 := R22 - R23
255 [-]: GETUPVAL  R24 U23      ; R24 := U23
256 [-]: SELF      R24 R24 K36  ; R25 := R24; R24 := R24[0xbd2e96ea]
257 [-]: MOVE      R26 R23      ; R26 := R23
258 [-]: GETUPVAL  R27 U33      ; R27 := U33
259 [-]: LOADKB    R28 0 0      ; R28 := false
260 [-]: GETGLOBAL R29 K1       ; R29 := 0x0469f296
261 [-]: LOADK     R30 K48      ; R30 := "Progress"
262 [-]: MOVE      R31 R21      ; R31 := R21
263 [-]: CONCAT    R30 R30 R31  ; R30 := R30 .. R31
264 [-]: CALL      R29 2 0      ; R29,... := R29(R30)
265 [-]: CALL      R24 0 1      ; R24(R25,...)
266 [-]: FORLOOP   R18 245      ; R18 += R20; if R18 <= R19 then begin PC := 245; R21 := R18 end
267 [-]: JMP       307          ; PC := 307
268 [-]: GETUPVAL  R24 U0       ; R24 := U0
269 [-]: GETUPVAL  R25 U34      ; R25 := U34
270 [-]: EQ        0 R24 R25    ; if R24 ~= R25 then PC := 307
271 [-]: JMP       307          ; PC := 307
272 [-]: GETGLOBAL R24 K9       ; R24 := 0x7b998233
273 [-]: GETUPVAL  R25 U22      ; R25 := U22
274 [-]: CALL      R24 2 2      ; R24 := R24(R25)
275 [-]: TEST      R24 1        ; if R24 then PC := 281
276 [-]: JMP       281          ; PC := 281
277 [-]: GETUPVAL  R24 U23      ; R24 := U23
278 [-]: SELF      R24 R24 K49  ; R25 := R24; R24 := R24[0x775c858b]
279 [-]: GETUPVAL  R26 U22      ; R26 := U22
280 [-]: CALL      R24 3 1      ; R24(R25,R26)
281 [-]: GETUPVAL  R24 U31      ; R24 := U31
282 [-]: LOADKB    R25 1 0      ; R25 := true
283 [-]: CALL      R24 2 1      ; R24(R25)
284 [-]: GETUPVAL  R24 U35      ; R24 := U35
285 [-]: SELF      R24 R24 K3   ; R25 := R24; R24 := R24[0x383d2e7d]
286 [-]: CALL      R24 2 1      ; R24(R25)
287 [-]: GETGLOBAL R24 K12      ; R24 := 0x11a19c5e
288 [-]: GETUPVAL  R25 U35      ; R25 := U35
289 [-]: LOADK     R26 K13      ; R26 := "OnActivated"
290 [-]: CALL      R24 3 1      ; R24(R25,R26)
291 [-]: GETUPVAL  R24 U7       ; R24 := U7
292 [-]: GETTABLE  R24 R24 K7   ; R24 := R24[0xa1df01d6]
293 [-]: GETUPVAL  R25 U36      ; R25 := U36
294 [-]: GETUPVAL  R26 U7       ; R26 := U7
295 [-]: GETTABLE  R26 R26 K8   ; R26 := R26["GENERIC_ICON"]
296 [-]: CALL      R24 3 1      ; R24(R25,R26)
297 [-]: GETGLOBAL R24 K39      ; R24 := _T
298 [-]: GETTABLE  R24 R24 K50  ; R24 := R24[0x1a41a3c1]
299 [-]: GETUPVAL  R25 U26      ; R25 := U26
300 [-]: CALL      R24 2 1      ; R24(R25)
301 [-]: GETGLOBAL R24 K39      ; R24 := _T
302 [-]: GETTABLE  R24 R24 K50  ; R24 := R24[0x1a41a3c1]
303 [-]: GETUPVAL  R25 U28      ; R25 := U28
304 [-]: CALL      R24 2 1      ; R24(R25)
305 [-]: GETGLOBAL R24 K39      ; R24 := _T
306 [-]: SETTABLE  R24 K46 K51  ; R24["AddToMixture"] := nil
307 [-]: RETURN    R0 1         ; return 


; Function #7.1:
;
; Name:            
; Defined at line: 199
; #Upvalues:       1
; #Parameters:     1
; Is_vararg:       0
; Max Stack Size:  3

  1 [-]: GETUPVAL  R1 U0        ; R1 := U0
  2 [-]: MOVE      R2 R0        ; R2 := R0
  3 [-]: CALL      R1 2 1       ; R1(R2)
  4 [-]: RETURN    R0 1         ; return 


; Function #8:
;
; Name:            
; Defined at line: 227
; #Upvalues:       4
; #Parameters:     1
; Is_vararg:       0
; Max Stack Size:  5

  1 [-]: GETUPVAL  R1 U0        ; R1 := U0
  2 [-]: EQ        1 R1 R0      ; if R1 == R0 then PC := 18
  3 [-]: JMP       18           ; PC := 18
  4 [-]: SETUPVAL  R0 U0        ; U82 := R0
  5 [-]: GETUPVAL  R1 U1        ; R1 := U1
  6 [-]: SELF      R1 R1 K0     ; R2 := R1; R1 := R1[0x751f061d]
  7 [-]: GETUPVAL  R3 U2        ; R3 := U2
  8 [-]: MOVE      R4 R0        ; R4 := R0
  9 [-]: CALL      R1 4 1       ; R1(R2,R3,R4)
 10 [-]: GETUPVAL  R1 U3        ; R1 := U3
 11 [-]: CALL      R1 1 1       ; R1()
 12 [-]: GETGLOBAL R1 K1        ; R1 := 0x3d106989
 13 [-]: LOADK     R2 K2        ; R2 := "EventDefendMixer.lua::SetModeState - New State: "
 14 [-]: GETUPVAL  R3 U0        ; R3 := U0
 15 [-]: CONCAT    R2 R2 R3     ; R2 := R2 .. R3
 16 [-]: CALL      R1 2 1       ; R1(R2)
 17 [-]: JMP       21           ; PC := 21
 18 [-]: GETGLOBAL R1 K1        ; R1 := 0x3d106989
 19 [-]: LOADK     R2 K3        ; R2 := "EventDefendMixer.lua::SetModeState - trying to set mode to state we're already in"
 20 [-]: CALL      R1 2 1       ; R1(R2)
 21 [-]: RETURN    R0 1         ; return 


; Function #9:
;
; Name:            
; Defined at line: 238
; #Upvalues:       32
; #Parameters:     1
; Is_vararg:       0
; Max Stack Size:  14

  1 [-]: GETGLOBAL R1 K0        ; R1 := 0xbe190284
  2 [-]: SETUPVAL  R1 U0        ; U82 := R0
  3 [-]: SELF      R1 R0 K1     ; R2 := R0; R1 := R0[0x891629fa]
  4 [-]: CALL      R1 2 2       ; R1 := R1(R2)
  5 [-]: SETUPVAL  R1 U1        ; U82 := R1
  6 [-]: GETGLOBAL R1 K2        ; R1 := 0x89326c93
  7 [-]: SELF      R1 R1 K3     ; R2 := R1; R1 := R1[0x29ef273d]
  8 [-]: CALL      R1 2 2       ; R1 := R1(R2)
  9 [-]: SELF      R1 R1 K4     ; R2 := R1; R1 := R1[0x66905cb0]
 10 [-]: CALL      R1 2 2       ; R1 := R1(R2)
 11 [-]: SETUPVAL  R1 U2        ; U82 := R2
 12 [-]: SETUPVAL  R0 U3        ; U82 := R3
 13 [-]: SELF      R1 R0 K5     ; R2 := R0; R1 := R0[0xd1586535]
 14 [-]: CALL      R1 2 2       ; R1 := R1(R2)
 15 [-]: SETUPVAL  R1 U4        ; U82 := R4
 16 [-]: SELF      R1 R0 K6     ; R2 := R0; R1 := R0[0xc5b92518]
 17 [-]: CALL      R1 2 2       ; R1 := R1(R2)
 18 [-]: SETUPVAL  R1 U5        ; U82 := R5
 19 [-]: SELF      R1 R0 K7     ; R2 := R0; R1 := R0[0x7c97b143]
 20 [-]: CALL      R1 2 2       ; R1 := R1(R2)
 21 [-]: SETUPVAL  R1 U6        ; U82 := R6
 22 [-]: SELF      R1 R0 K8     ; R2 := R0; R1 := R0[0x4c976eda]
 23 [-]: CALL      R1 2 2       ; R1 := R1(R2)
 24 [-]: SELF      R2 R1 K9     ; R3 := R1; R2 := R1[0xe4c355e2]
 25 [-]: CALL      R2 2 2       ; R2 := R2(R3)
 26 [-]: SETUPVAL  R2 U7        ; U82 := R7
 27 [-]: GETUPVAL  R2 U2        ; R2 := U2
 28 [-]: SELF      R2 R2 K10    ; R3 := R2; R2 := R2[0x2d2bdbb8]
 29 [-]: LOADKB    R4 0 0       ; R4 := false
 30 [-]: CALL      R2 3 1       ; R2(R3,R4)
 31 [-]: GETUPVAL  R2 U2        ; R2 := U2
 32 [-]: SELF      R2 R2 K11    ; R3 := R2; R2 := R2[0xe73b6f59]
 33 [-]: LOADKB    R4 0 0       ; R4 := false
 34 [-]: CALL      R2 3 1       ; R2(R3,R4)
 35 [-]: GETGLOBAL R2 K2        ; R2 := 0x89326c93
 36 [-]: SELF      R2 R2 K12    ; R3 := R2; R2 := R2[0xb7d33840]
 37 [-]: LOADK     R4 K13       ; R4 := "OnPlayersChanged"
 38 [-]: CALL      R2 3 1       ; R2(R3,R4)
 39 [-]: GETGLOBAL R2 K2        ; R2 := 0x89326c93
 40 [-]: SELF      R2 R2 K14    ; R3 := R2; R2 := R2[0x7d108ddb]
 41 [-]: CALL      R2 2 2       ; R2 := R2(R3)
 42 [-]: SETUPVAL  R2 U8        ; U82 := R8
 43 [-]: LOADKB    R2 0 0       ; R2 := false
 44 [-]: TEST      R2 0         ; if not R2 then PC := 48
 45 [-]: JMP       48           ; PC := 48
 46 [-]: CONST     R2 10        ; R2 := 10.000000
 47 [-]: SETUPVAL  R2 U9        ; U82 := R9
 48 [-]: GETGLOBAL R2 K2        ; R2 := 0x89326c93
 49 [-]: SELF      R2 R2 K15    ; R3 := R2; R2 := R2[0xc7b81e8d]
 50 [-]: GETGLOBAL R4 K16       ; R4 := 0x0469f296
 51 [-]: LOADK     R5 K17       ; R5 := "LootWagonAction"
 52 [-]: CALL      R4 2 2       ; R4 := R4(R5)
 53 [-]: GETUPVAL  R5 U4        ; R5 := U4
 54 [-]: CALL      R2 4 2       ; R2 := R2(R3,R4,R5)
 55 [-]: SETUPVAL  R2 U10       ; U82 := R10
 56 [-]: GETUPVAL  R2 U10       ; R2 := U10
 57 [-]: SELF      R2 R2 K5     ; R3 := R2; R2 := R2[0xd1586535]
 58 [-]: CALL      R2 2 2       ; R2 := R2(R3)
 59 [-]: GETGLOBAL R3 K2        ; R3 := 0x89326c93
 60 [-]: SELF      R3 R3 K15    ; R4 := R3; R3 := R3[0xc7b81e8d]
 61 [-]: GETGLOBAL R5 K16       ; R5 := 0x0469f296
 62 [-]: LOADK     R6 K18       ; R6 := "MixerConsole"
 63 [-]: CALL      R5 2 2       ; R5 := R5(R6)
 64 [-]: MOVE      R6 R2        ; R6 := R2
 65 [-]: CALL      R3 4 2       ; R3 := R3(R4,R5,R6)
 66 [-]: SETUPVAL  R3 U11       ; U82 := R11
 67 [-]: GETGLOBAL R3 K2        ; R3 := 0x89326c93
 68 [-]: SELF      R3 R3 K19    ; R4 := R3; R3 := R3[0x4e5939a5]
 69 [-]: GETGLOBAL R5 K20       ; R5 := 0xdd794dae
 70 [-]: MOVE      R6 R2        ; R6 := R2
 71 [-]: CONST     R7 10        ; R7 := 10.000000
 72 [-]: CALL      R3 5 2       ; R3 := R3(R4,R5,R6,R7)
 73 [-]: SETUPVAL  R3 U12       ; U82 := R12
 74 [-]: GETGLOBAL R3 K2        ; R3 := 0x89326c93
 75 [-]: SELF      R3 R3 K15    ; R4 := R3; R3 := R3[0xc7b81e8d]
 76 [-]: GETGLOBAL R5 K16       ; R5 := 0x0469f296
 77 [-]: LOADK     R6 K21       ; R6 := "MixerConsoleSpawn"
 78 [-]: CALL      R5 2 2       ; R5 := R5(R6)
 79 [-]: MOVE      R6 R2        ; R6 := R2
 80 [-]: CALL      R3 4 2       ; R3 := R3(R4,R5,R6)
 81 [-]: SETUPVAL  R3 U13       ; U82 := R13
 82 [-]: GETGLOBAL R3 K2        ; R3 := 0x89326c93
 83 [-]: SELF      R3 R3 K22    ; R4 := R3; R3 := R3[0xf16592c8]
 84 [-]: GETGLOBAL R5 K16       ; R5 := 0x0469f296
 85 [-]: LOADK     R6 K23       ; R6 := "MixerBlockingVolume"
 86 [-]: CALL      R5 2 2       ; R5 := R5(R6)
 87 [-]: MOVE      R6 R2        ; R6 := R2
 88 [-]: CONST     R7 0         ; R7 := 0.000000
 89 [-]: CONST     R8 10        ; R8 := 10.000000
 90 [-]: CALL      R3 6 2       ; R3 := R3(R4,R5,R6,R7,R8)
 91 [-]: SETUPVAL  R3 U14       ; U82 := R14
 92 [-]: GETGLOBAL R3 K24       ; R3 := 0xc8802016
 93 [-]: GETUPVAL  R4 U14       ; R4 := U14
 94 [-]: CALL      R3 2 4       ; R3,R4,R5 := R3(R4)
 95 [-]: JMP       99           ; PC := 99
 96 [-]: SELF      R8 R7 K25    ; R9 := R7; R8 := R7[0x8eb2112d]
 97 [-]: LOADK     R10 K26      ; R10 := "Enable"
 98 [-]: CALL      R8 3 1       ; R8(R9,R10)
 99 [-]: TFORLOOP  R3 2         ; R6,R7 :=  R3(R4,R5); if R6 ~= nil then begin PC = 96; R5 := R6 end
100 [-]: JMP       96           ; PC := 96
101 [-]: GETGLOBAL R8 K2        ; R8 := 0x89326c93
102 [-]: SELF      R8 R8 K22    ; R9 := R8; R8 := R8[0xf16592c8]
103 [-]: GETGLOBAL R10 K16      ; R10 := 0x0469f296
104 [-]: LOADK     R11 K27      ; R11 := "MantleUpAction"
105 [-]: CALL      R10 2 2      ; R10 := R10(R11)
106 [-]: GETUPVAL  R11 U13      ; R11 := U13
107 [-]: SELF      R11 R11 K5   ; R12 := R11; R11 := R11[0xd1586535]
108 [-]: CALL      R11 2 2      ; R11 := R11(R12)
109 [-]: CONST     R12 0        ; R12 := 0.000000
110 [-]: CONST     R13 10       ; R13 := 10.000000
111 [-]: CALL      R8 6 2       ; R8 := R8(R9,R10,R11,R12,R13)
112 [-]: SETUPVAL  R8 U15       ; U82 := R15
113 [-]: GETGLOBAL R8 K2        ; R8 := 0x89326c93
114 [-]: SELF      R8 R8 K28    ; R9 := R8; R8 := R8[0x462c251c]
115 [-]: GETGLOBAL R10 K16      ; R10 := 0x0469f296
116 [-]: LOADK     R11 K29      ; R11 := "InteriorLootWagonNavVolume"
117 [-]: CALL      R10 2 2      ; R10 := R10(R11)
118 [-]: GETUPVAL  R11 U13      ; R11 := U13
119 [-]: SELF      R11 R11 K5   ; R12 := R11; R11 := R11[0xd1586535]
120 [-]: CALL      R11 2 2      ; R11 := R11(R12)
121 [-]: CONST     R12 0        ; R12 := 0.000000
122 [-]: CONST     R13 10       ; R13 := 10.000000
123 [-]: CALL      R8 6 2       ; R8 := R8(R9,R10,R11,R12,R13)
124 [-]: SETUPVAL  R8 U16       ; U82 := R16
125 [-]: GETGLOBAL R8 K2        ; R8 := 0x89326c93
126 [-]: SELF      R8 R8 K28    ; R9 := R8; R8 := R8[0x462c251c]
127 [-]: GETGLOBAL R10 K16      ; R10 := 0x0469f296
128 [-]: LOADK     R11 K30      ; R11 := "ExteriorLootWagonNavVolume"
129 [-]: CALL      R10 2 2      ; R10 := R10(R11)
130 [-]: GETUPVAL  R11 U13      ; R11 := U13
131 [-]: SELF      R11 R11 K5   ; R12 := R11; R11 := R11[0xd1586535]
132 [-]: CALL      R11 2 2      ; R11 := R11(R12)
133 [-]: CONST     R12 0        ; R12 := 0.000000
134 [-]: CONST     R13 10       ; R13 := 10.000000
135 [-]: CALL      R8 6 2       ; R8 := R8(R9,R10,R11,R12,R13)
136 [-]: SETUPVAL  R8 U17       ; U82 := R17
137 [-]: GETGLOBAL R8 K31       ; R8 := 0x7b998233
138 [-]: GETUPVAL  R9 U12       ; R9 := U12
139 [-]: CALL      R8 2 2       ; R8 := R8(R9)
140 [-]: TEST      R8 0         ; if not R8 then PC := 162
141 [-]: JMP       162          ; PC := 162
142 [-]: GETUPVAL  R8 U2        ; R8 := U2
143 [-]: SELF      R8 R8 K32    ; R9 := R8; R8 := R8[0x33fc842f]
144 [-]: GETGLOBAL R10 K33      ; R10 := 0x902721c4
145 [-]: GETUPVAL  R11 U13      ; R11 := U13
146 [-]: GETGLOBAL R12 K34      ; R12 := EMPTY_SYMBOL
147 [-]: CALL      R8 5 2       ; R8 := R8(R9,R10,R11,R12)
148 [-]: SETUPVAL  R8 U18       ; U82 := R18
149 [-]: GETGLOBAL R8 K31       ; R8 := 0x7b998233
150 [-]: GETUPVAL  R9 U18       ; R9 := U18
151 [-]: CALL      R8 2 2       ; R8 := R8(R9)
152 [-]: TEST      R8 1         ; if R8 then PC := 173
153 [-]: JMP       173          ; PC := 173
154 [-]: GETUPVAL  R8 U18       ; R8 := U18
155 [-]: SELF      R8 R8 K35    ; R9 := R8; R8 := R8[0xbb610e5b]
156 [-]: CALL      R8 2 2       ; R8 := R8(R9)
157 [-]: SETUPVAL  R8 U12       ; U82 := R12
158 [-]: GETUPVAL  R8 U19       ; R8 := U19
159 [-]: LOADKB    R9 1 0       ; R9 := true
160 [-]: CALL      R8 2 1       ; R8(R9)
161 [-]: JMP       173          ; PC := 173
162 [-]: GETUPVAL  R8 U12       ; R8 := U12
163 [-]: SELF      R8 R8 K36    ; R9 := R8; R8 := R8[0xfa9e477f]
164 [-]: CALL      R8 2 2       ; R8 := R8(R9)
165 [-]: SETUPVAL  R8 U18       ; U82 := R18
166 [-]: GETUPVAL  R8 U20       ; R8 := U20
167 [-]: GETUPVAL  R9 U21       ; R9 := U21
168 [-]: LT        0 R8 R9      ; if R8 >= R9 then PC := 173
169 [-]: JMP       173          ; PC := 173
170 [-]: GETUPVAL  R8 U19       ; R8 := U19
171 [-]: LOADKB    R9 1 0       ; R9 := true
172 [-]: CALL      R8 2 1       ; R8(R9)
173 [-]: GETUPVAL  R8 U12       ; R8 := U12
174 [-]: SELF      R8 R8 K37    ; R9 := R8; R8 := R8[0x9307aa51]
175 [-]: GETUPVAL  R10 U11      ; R10 := U11
176 [-]: SELF      R10 R10 K5   ; R11 := R10; R10 := R10[0xd1586535]
177 [-]: CALL      R10 2 0      ; R10,... := R10(R11)
178 [-]: CALL      R8 0 1       ; R8(R9,...)
179 [-]: GETUPVAL  R8 U12       ; R8 := U12
180 [-]: SELF      R8 R8 K38    ; R9 := R8; R8 := R8[0x020d4331]
181 [-]: CALL      R8 2 2       ; R8 := R8(R9)
182 [-]: SELF      R8 R8 K39    ; R9 := R8; R8 := R8[0x553549e8]
183 [-]: GETUPVAL  R10 U11      ; R10 := U11
184 [-]: SELF      R10 R10 K40  ; R11 := R10; R10 := R10[0xcb3851b8]
185 [-]: CALL      R10 2 0      ; R10,... := R10(R11)
186 [-]: CALL      R8 0 1       ; R8(R9,...)
187 [-]: GETUPVAL  R8 U12       ; R8 := U12
188 [-]: SELF      R8 R8 K41    ; R9 := R8; R8 := R8[0xc9f6a7d7]
189 [-]: GETGLOBAL R10 K42      ; R10 := gContextActionType
190 [-]: CALL      R8 3 2       ; R8 := R8(R9,R10)
191 [-]: SETUPVAL  R8 U22       ; U82 := R22
192 [-]: GETUPVAL  R8 U11       ; R8 := U11
193 [-]: SELF      R8 R8 K41    ; R9 := R8; R8 := R8[0xc9f6a7d7]
194 [-]: GETGLOBAL R10 K42      ; R10 := gContextActionType
195 [-]: CALL      R8 3 2       ; R8 := R8(R9,R10)
196 [-]: SETUPVAL  R8 U23       ; U82 := R23
197 [-]: GETGLOBAL R8 K43       ; R8 := 0x11a19c5e
198 [-]: GETUPVAL  R9 U10       ; R9 := U10
199 [-]: LOADK     R10 K44      ; R10 := "OnActivated"
200 [-]: CALL      R8 3 1       ; R8(R9,R10)
201 [-]: GETUPVAL  R8 U25       ; R8 := U25
202 [-]: GETTABLE  R8 R8 K45    ; R8 := R8[0xa80cf6ff]
203 [-]: GETUPVAL  R9 U2        ; R9 := U2
204 [-]: MOVE      R10 R0       ; R10 := R0
205 [-]: CALL      R8 3 2       ; R8 := R8(R9,R10)
206 [-]: SETUPVAL  R8 U24       ; U82 := R24
207 [-]: GETUPVAL  R8 U27       ; R8 := U27
208 [-]: GETTABLE  R8 R8 K46    ; R8 := R8[0xde474187]
209 [-]: CALL      R8 1 2       ; R8 := R8()
210 [-]: SETUPVAL  R8 U26       ; U82 := R26
211 [-]: GETUPVAL  R8 U3        ; R8 := U3
212 [-]: SELF      R8 R8 K47    ; R9 := R8; R8 := R8[0xabe61691]
213 [-]: CALL      R8 2 2       ; R8 := R8(R9)
214 [-]: EQ        0 R8 K48     ; if R8 ~= 0.000000 then PC := 224
215 [-]: JMP       224          ; PC := 224
216 [-]: GETUPVAL  R8 U3        ; R8 := U3
217 [-]: SELF      R8 R8 K49    ; R9 := R8; R8 := R8[0x5b18bb5d]
218 [-]: CONST     R10 1        ; R10 := 1.000000
219 [-]: CALL      R8 3 1       ; R8(R9,R10)
220 [-]: GETUPVAL  R8 U28       ; R8 := U28
221 [-]: GETUPVAL  R9 U29       ; R9 := U29
222 [-]: CALL      R8 2 1       ; R8(R9)
223 [-]: JMP       231          ; PC := 231
224 [-]: GETUPVAL  R8 U28       ; R8 := U28
225 [-]: GETUPVAL  R9 U0        ; R9 := U0
226 [-]: SELF      R9 R9 K50    ; R10 := R9; R9 := R9[0x0eb34c69]
227 [-]: GETUPVAL  R11 U30      ; R11 := U30
228 [-]: GETUPVAL  R12 U29      ; R12 := U29
229 [-]: CALL      R9 4 0       ; R9,... := R9(R10,R11,R12)
230 [-]: CALL      R8 0 1       ; R8(R9,...)
231 [-]: GETUPVAL  R8 U20       ; R8 := U20
232 [-]: GETUPVAL  R9 U31       ; R9 := U31
233 [-]: LE        0 R8 R9      ; if R8 > R9 then PC := 245
234 [-]: JMP       245          ; PC := 245
235 [-]: GETGLOBAL R8 K2        ; R8 := 0x89326c93
236 [-]: SELF      R8 R8 K15    ; R9 := R8; R8 := R8[0xc7b81e8d]
237 [-]: GETGLOBAL R10 K16      ; R10 := 0x0469f296
238 [-]: LOADK     R11 K51      ; R11 := "CloseLootWagonForwarder"
239 [-]: CALL      R10 2 2      ; R10 := R10(R11)
240 [-]: GETUPVAL  R11 U4       ; R11 := U4
241 [-]: CALL      R8 4 2       ; R8 := R8(R9,R10,R11)
242 [-]: SELF      R9 R8 K25    ; R10 := R8; R9 := R8[0x8eb2112d]
243 [-]: LOADK     R11 K52      ; R11 := "TriggerPort"
244 [-]: CALL      R9 3 1       ; R9(R10,R11)
245 [-]: SELF      R9 R0 K53    ; R10 := R0; R9 := R0[0xfe9dc265]
246 [-]: CONST     R11 2        ; R11 := 2.000000
247 [-]: CALL      R9 3 1       ; R9(R10,R11)
248 [-]: RETURN    R0 1         ; return 


; Function #10:
;
; Name:            
; Defined at line: 313
; #Upvalues:       29
; #Parameters:     1
; Is_vararg:       0
; Max Stack Size:  14

  1 [-]: GETUPVAL  R1 U0        ; R1 := U0
  2 [-]: MOVE      R2 R0        ; R2 := R0
  3 [-]: CALL      R1 2 1       ; R1(R2)
  4 [-]: SELF      R1 R0 K0     ; R2 := R0; R1 := R0[0xefe6cad1]
  5 [-]: CALL      R1 2 2       ; R1 := R1(R2)
  6 [-]: LT        0 R1 K2      ; if R1 >= 4.000000 then PC := 115
  7 [-]: JMP       115          ; PC := 115
  8 [-]: GETUPVAL  R1 U1        ; R1 := U1
  9 [-]: GETUPVAL  R2 U2        ; R2 := U2
 10 [-]: EQ        0 R1 R2      ; if R1 ~= R2 then PC := 26
 11 [-]: JMP       26           ; PC := 26
 12 [-]: GETUPVAL  R1 U3        ; R1 := U3
 13 [-]: SELF      R1 R1 K0     ; R2 := R1; R1 := R1[0xefe6cad1]
 14 [-]: CALL      R1 2 2       ; R1 := R1(R2)
 15 [-]: LE        1 K3 R1      ; if 2.000000 <= R1 then PC := 22
 16 [-]: JMP       22           ; PC := 22
 17 [-]: GETUPVAL  R1 U3        ; R1 := U3
 18 [-]: SELF      R1 R1 K4     ; R2 := R1; R1 := R1[0xd8140b94]
 19 [-]: CALL      R1 2 2       ; R1 := R1(R2)
 20 [-]: TEST      R1 1         ; if R1 then PC := 111
 21 [-]: JMP       111          ; PC := 111
 22 [-]: GETUPVAL  R1 U4        ; R1 := U4
 23 [-]: GETUPVAL  R2 U5        ; R2 := U5
 24 [-]: CALL      R1 2 1       ; R1(R2)
 25 [-]: JMP       111          ; PC := 111
 26 [-]: GETUPVAL  R1 U1        ; R1 := U1
 27 [-]: GETUPVAL  R2 U5        ; R2 := U5
 28 [-]: EQ        0 R1 R2      ; if R1 ~= R2 then PC := 31
 29 [-]: JMP       31           ; PC := 31
 30 [-]: JMP       111          ; PC := 111
 31 [-]: GETUPVAL  R1 U1        ; R1 := U1
 32 [-]: GETUPVAL  R2 U6        ; R2 := U6
 33 [-]: EQ        0 R1 R2      ; if R1 ~= R2 then PC := 36
 34 [-]: JMP       36           ; PC := 36
 35 [-]: JMP       111          ; PC := 111
 36 [-]: GETUPVAL  R1 U1        ; R1 := U1
 37 [-]: GETUPVAL  R2 U7        ; R2 := U7
 38 [-]: EQ        0 R1 R2      ; if R1 ~= R2 then PC := 107
 39 [-]: JMP       107          ; PC := 107
 40 [-]: GETUPVAL  R1 U8        ; R1 := U8
 41 [-]: SELF      R1 R1 K5     ; R2 := R1; R1 := R1[0xfaa69527]
 42 [-]: GETGLOBAL R3 K6        ; R3 := 0x67652851
 43 [-]: CALL      R3 1 0       ; R3,... := R3()
 44 [-]: CALL      R1 0 1       ; R1(R2,...)
 45 [-]: GETUPVAL  R1 U9        ; R1 := U9
 46 [-]: SELF      R1 R1 K5     ; R2 := R1; R1 := R1[0xfaa69527]
 47 [-]: GETGLOBAL R3 K6        ; R3 := 0x67652851
 48 [-]: CALL      R3 1 0       ; R3,... := R3()
 49 [-]: CALL      R1 0 1       ; R1(R2,...)
 50 [-]: GETUPVAL  R1 U10       ; R1 := U10
 51 [-]: SELF      R1 R1 K7     ; R2 := R1; R1 := R1[0x2047cfe7]
 52 [-]: CALL      R1 2 2       ; R1 := R1(R2)
 53 [-]: TEST      R1 0         ; if not R1 then PC := 59
 54 [-]: JMP       59           ; PC := 59
 55 [-]: SELF      R1 R0 K8     ; R2 := R0; R1 := R0[0xfe9dc265]
 56 [-]: CONST     R3 5         ; R3 := 5.000000
 57 [-]: CALL      R1 3 1       ; R1(R2,R3)
 58 [-]: JMP       111          ; PC := 111
 59 [-]: GETGLOBAL R1 K9        ; R1 := 0x7b998233
 60 [-]: GETUPVAL  R2 U11       ; R2 := U11
 61 [-]: GETTABLE  R2 R2 K10    ; R2 := R2[0x46749d86]
 62 [-]: CALL      R2 1 0       ; R2,... := R2()
 63 [-]: CALL      R1 0 2       ; R1 := R1(R2,...)
 64 [-]: TEST      R1 1         ; if R1 then PC := 80
 65 [-]: JMP       80           ; PC := 80
 66 [-]: GETUPVAL  R1 U11       ; R1 := U11
 67 [-]: GETTABLE  R1 R1 K11    ; R1 := R1[0x826f2ca6]
 68 [-]: CALL      R1 1 2       ; R1 := R1()
 69 [-]: LE        0 R1 K12     ; if R1 > 0.000000 then PC := 80
 70 [-]: JMP       80           ; PC := 80
 71 [-]: GETUPVAL  R1 U4        ; R1 := U4
 72 [-]: GETUPVAL  R2 U12       ; R2 := U12
 73 [-]: CALL      R1 2 1       ; R1(R2)
 74 [-]: GETUPVAL  R1 U10       ; R1 := U10
 75 [-]: SELF      R1 R1 K13    ; R2 := R1; R1 := R1[0x659d451f]
 76 [-]: GETGLOBAL R3 K14       ; R3 := 0x55f337f0
 77 [-]: LOADKB    R4 1 0       ; R4 := true
 78 [-]: CALL      R1 4 1       ; R1(R2,R3,R4)
 79 [-]: JMP       111          ; PC := 111
 80 [-]: GETGLOBAL R1 K9        ; R1 := 0x7b998233
 81 [-]: GETUPVAL  R2 U11       ; R2 := U11
 82 [-]: GETTABLE  R2 R2 K10    ; R2 := R2[0x46749d86]
 83 [-]: CALL      R2 1 0       ; R2,... := R2()
 84 [-]: CALL      R1 0 2       ; R1 := R1(R2,...)
 85 [-]: TEST      R1 1         ; if R1 then PC := 111
 86 [-]: JMP       111          ; PC := 111
 87 [-]: GETUPVAL  R1 U11       ; R1 := U11
 88 [-]: GETTABLE  R1 R1 K11    ; R1 := R1[0x826f2ca6]
 89 [-]: CALL      R1 1 2       ; R1 := R1()
 90 [-]: GETUPVAL  R2 U13       ; R2 := U13
 91 [-]: DIV       R2 R2 K3     ; R2 := R2 / 2.000000
 92 [-]: LE        0 R1 R2      ; if R1 > R2 then PC := 111
 93 [-]: JMP       111          ; PC := 111
 94 [-]: GETUPVAL  R1 U14       ; R1 := U14
 95 [-]: TEST      R1 1         ; if R1 then PC := 111
 96 [-]: JMP       111          ; PC := 111
 97 [-]: GETUPVAL  R1 U15       ; R1 := U15
 98 [-]: GETTABLE  R1 R1 K15    ; R1 := R1[0x9742b85b]
 99 [-]: GETUPVAL  R2 U16       ; R2 := U16
100 [-]: GETGLOBAL R3 K16       ; R3 := 0x0469f296
101 [-]: LOADK     R4 K17       ; R4 := "DefendHalfway"
102 [-]: CALL      R3 2 0       ; R3,... := R3(R4)
103 [-]: CALL      R1 0 1       ; R1(R2,...)
104 [-]: LOADKB    R1 1 0       ; R1 := true
105 [-]: SETUPVAL  R1 U14       ; U82 := R14
106 [-]: JMP       111          ; PC := 111
107 [-]: GETUPVAL  R1 U1        ; R1 := U1
108 [-]: GETUPVAL  R2 U12       ; R2 := U12
109 [-]: EQ        0 R1 R2      ; if R1 ~= R2 then PC := 111
110 [-]: JMP       111          ; PC := 111
111 [-]: GETGLOBAL R1 K18       ; R1 := 0xcbd666e1
112 [-]: CONST     R2 0         ; R2 := 0.000000
113 [-]: CALL      R1 2 1       ; R1(R2)
114 [-]: JMP       4            ; PC := 4
115 [-]: GETGLOBAL R1 K9        ; R1 := 0x7b998233
116 [-]: GETUPVAL  R2 U17       ; R2 := U17
117 [-]: CALL      R1 2 2       ; R1 := R1(R2)
118 [-]: TEST      R1 1         ; if R1 then PC := 123
119 [-]: JMP       123          ; PC := 123
120 [-]: GETUPVAL  R1 U17       ; R1 := U17
121 [-]: SELF      R1 R1 K19    ; R2 := R1; R1 := R1[0xa2880940]
122 [-]: CALL      R1 2 1       ; R1(R2)
123 [-]: GETUPVAL  R1 U18       ; R1 := U18
124 [-]: SELF      R1 R1 K20    ; R2 := R1; R1 := R1[0x768274d6]
125 [-]: LOADKB    R3 1 0       ; R3 := true
126 [-]: LOADKB    R4 1 0       ; R4 := true
127 [-]: CALL      R1 4 1       ; R1(R2,R3,R4)
128 [-]: GETUPVAL  R1 U10       ; R1 := U10
129 [-]: SELF      R1 R1 K19    ; R2 := R1; R1 := R1[0xa2880940]
130 [-]: CALL      R1 2 1       ; R1(R2)
131 [-]: GETGLOBAL R1 K21       ; R1 := 0xc8802016
132 [-]: GETUPVAL  R2 U19       ; R2 := U19
133 [-]: CALL      R1 2 4       ; R1,R2,R3 := R1(R2)
134 [-]: JMP       138          ; PC := 138
135 [-]: SELF      R6 R5 K22    ; R7 := R5; R6 := R5[0x8eb2112d]
136 [-]: LOADK     R8 K23       ; R8 := "Disable"
137 [-]: CALL      R6 3 1       ; R6(R7,R8)
138 [-]: TFORLOOP  R1 2         ; R4,R5 :=  R1(R2,R3); if R4 ~= nil then begin PC = 135; R3 := R4 end
139 [-]: JMP       135          ; PC := 135
140 [-]: GETGLOBAL R6 K21       ; R6 := 0xc8802016
141 [-]: GETUPVAL  R7 U20       ; R7 := U20
142 [-]: CALL      R6 2 4       ; R6,R7,R8 := R6(R7)
143 [-]: JMP       146          ; PC := 146
144 [-]: SELF      R11 R10 K24  ; R12 := R10; R11 := R10[0x383d2e7d]
145 [-]: CALL      R11 2 1      ; R11(R12)
146 [-]: TFORLOOP  R6 2         ; R9,R10 :=  R6(R7,R8); if R9 ~= nil then begin PC = 144; R8 := R9 end
147 [-]: JMP       144          ; PC := 144
148 [-]: GETUPVAL  R11 U21      ; R11 := U21
149 [-]: SELF      R11 R11 K22  ; R12 := R11; R11 := R11[0x8eb2112d]
150 [-]: LOADK     R13 K23      ; R13 := "Disable"
151 [-]: CALL      R11 3 1      ; R11(R12,R13)
152 [-]: GETUPVAL  R11 U22      ; R11 := U22
153 [-]: SELF      R11 R11 K22  ; R12 := R11; R11 := R11[0x8eb2112d]
154 [-]: LOADK     R13 K25      ; R13 := "Enable"
155 [-]: CALL      R11 3 1      ; R11(R12,R13)
156 [-]: GETUPVAL  R11 U23      ; R11 := U23
157 [-]: SELF      R11 R11 K26  ; R12 := R11; R11 := R11[0x2d2bdbb8]
158 [-]: LOADKB    R13 1 0      ; R13 := true
159 [-]: CALL      R11 3 1      ; R11(R12,R13)
160 [-]: GETUPVAL  R11 U23      ; R11 := U23
161 [-]: SELF      R11 R11 K27  ; R12 := R11; R11 := R11[0xe73b6f59]
162 [-]: LOADKB    R13 1 0      ; R13 := true
163 [-]: CALL      R11 3 1      ; R11(R12,R13)
164 [-]: GETUPVAL  R11 U11      ; R11 := U11
165 [-]: GETTABLE  R11 R11 K28  ; R11 := R11[0xdc3b2033]
166 [-]: CALL      R11 1 1      ; R11()
167 [-]: GETUPVAL  R11 U11      ; R11 := U11
168 [-]: GETTABLE  R11 R11 K29  ; R11 := R11[0xedf59000]
169 [-]: CALL      R11 1 1      ; R11()
170 [-]: GETUPVAL  R11 U11      ; R11 := U11
171 [-]: GETTABLE  R11 R11 K30  ; R11 := R11[0x18dd08ac]
172 [-]: CALL      R11 1 1      ; R11()
173 [-]: GETGLOBAL R11 K31      ; R11 := _T
174 [-]: GETTABLE  R11 R11 K32  ; R11 := R11[0x1a41a3c1]
175 [-]: GETUPVAL  R12 U24      ; R12 := U24
176 [-]: CALL      R11 2 1      ; R11(R12)
177 [-]: GETGLOBAL R11 K31      ; R11 := _T
178 [-]: GETTABLE  R11 R11 K32  ; R11 := R11[0x1a41a3c1]
179 [-]: GETUPVAL  R12 U25      ; R12 := U25
180 [-]: CALL      R11 2 1      ; R11(R12)
181 [-]: GETUPVAL  R11 U26      ; R11 := U26
182 [-]: GETTABLE  R11 R11 K33  ; R11 := R11[0xe69049eb]
183 [-]: GETUPVAL  R12 U3       ; R12 := U3
184 [-]: CALL      R11 2 1      ; R11(R12)
185 [-]: GETUPVAL  R11 U27      ; R11 := U27
186 [-]: SELF      R11 R11 K34  ; R12 := R11; R11 := R11[0xb9bfd47c]
187 [-]: GETUPVAL  R13 U28      ; R13 := U28
188 [-]: CALL      R11 3 1      ; R11(R12,R13)
189 [-]: RETURN    R0 1         ; return 


; Function #11:
;
; Name:            
; Defined at line: 378
; #Upvalues:       1
; #Parameters:     1
; Is_vararg:       0
; Max Stack Size:  4

  1 [-]: SELF      R1 R0 K0     ; R2 := R0; R1 := R0[0xa64a1f4a]
  2 [-]: GETUPVAL  R3 U0        ; R3 := U0
  3 [-]: CALL      R1 3 1       ; R1(R2,R3)
  4 [-]: RETURN    R0 1         ; return 


; Function #12:
;
; Name:            
; Defined at line: 382
; #Upvalues:       1
; #Parameters:     0
; Is_vararg:       0
; Max Stack Size:  2

  1 [-]: GETGLOBAL R0 K0        ; R0 := 0x89326c93
  2 [-]: SELF      R0 R0 K1     ; R1 := R0; R0 := R0[0x7d108ddb]
  3 [-]: CALL      R0 2 2       ; R0 := R0(R1)
  4 [-]: SETUPVAL  R0 U0        ; U82 := R0
  5 [-]: RETURN    R0 1         ; return 


; Function #13:
;
; Name:            
; Defined at line: 386
; #Upvalues:       7
; #Parameters:     1
; Is_vararg:       0
; Max Stack Size:  4

  1 [-]: GETUPVAL  R1 U0        ; R1 := U0
  2 [-]: EQ        0 R0 R1      ; if R0 ~= R1 then PC := 8
  3 [-]: JMP       8            ; PC := 8
  4 [-]: GETUPVAL  R1 U1        ; R1 := U1
  5 [-]: GETUPVAL  R2 U2        ; R2 := U2
  6 [-]: CALL      R1 2 1       ; R1(R2)
  7 [-]: JMP       22           ; PC := 22
  8 [-]: GETUPVAL  R1 U3        ; R1 := U3
  9 [-]: EQ        0 R0 R1      ; if R0 ~= R1 then PC := 16
 10 [-]: JMP       16           ; PC := 16
 11 [-]: GETUPVAL  R1 U4        ; R1 := U4
 12 [-]: SELF      R1 R1 K0     ; R2 := R1; R1 := R1[0xfe9dc265]
 13 [-]: CONST     R3 4         ; R3 := 4.000000
 14 [-]: CALL      R1 3 1       ; R1(R2,R3)
 15 [-]: JMP       22           ; PC := 22
 16 [-]: GETUPVAL  R1 U5        ; R1 := U5
 17 [-]: EQ        0 R0 R1      ; if R0 ~= R1 then PC := 22
 18 [-]: JMP       22           ; PC := 22
 19 [-]: GETUPVAL  R1 U1        ; R1 := U1
 20 [-]: GETUPVAL  R2 U6        ; R2 := U6
 21 [-]: CALL      R1 2 1       ; R1(R2)
 22 [-]: RETURN    R0 1         ; return 


; Function #14:
;
; Name:            
; Defined at line: 396
; #Upvalues:       0
; #Parameters:     2
; Is_vararg:       0
; Max Stack Size:  8

  1 [-]: GETGLOBAL R2 K0        ; R2 := 0x89326c93
  2 [-]: SELF      R2 R2 K1     ; R3 := R2; R2 := R2[0x18d05d30]
  3 [-]: CALL      R2 2 2       ; R2 := R2(R3)
  4 [-]: TEST      R2 0         ; if not R2 then PC := 20
  5 [-]: JMP       20           ; PC := 20
  6 [-]: SELF      R2 R1 K2     ; R3 := R1; R2 := R1[0xde321e6f]
  7 [-]: CALL      R2 2 2       ; R2 := R2(R3)
  8 [-]: SELF      R3 R2 K3     ; R4 := R2; R3 := R2[0x02a0d8e1]
  9 [-]: CALL      R3 2 2       ; R3 := R3(R4)
 10 [-]: SELF      R4 R2 K4     ; R5 := R2; R4 := R2[0x0b5ec5b5]
 11 [-]: LOADKB    R6 1 0       ; R6 := true
 12 [-]: CALL      R4 3 1       ; R4(R5,R6)
 13 [-]: SELF      R4 R1 K5     ; R5 := R1; R4 := R1[0x511d26b8]
 14 [-]: GETGLOBAL R6 K6        ; R6 := 0x3832bba4
 15 [-]: LOADKB    R7 1 0       ; R7 := true
 16 [-]: CALL      R4 4 1       ; R4(R5,R6,R7)
 17 [-]: SELF      R4 R2 K4     ; R5 := R2; R4 := R2[0x0b5ec5b5]
 18 [-]: MOVE      R6 R3        ; R6 := R3
 19 [-]: CALL      R4 3 1       ; R4(R5,R6)
 20 [-]: RETURN    R0 1         ; return 


; Function #15:
;
; Name:            
; Defined at line: 406
; #Upvalues:       0
; #Parameters:     0
; Is_vararg:       0
; Max Stack Size:  4

  1 [-]: GETGLOBAL R0 K0        ; R0 := 0x7b998233
  2 [-]: GETGLOBAL R1 K1        ; R1 := _T
  3 [-]: GETTABLE  R1 R1 K2     ; R1 := R1["AddToMixture"]
  4 [-]: CALL      R0 2 2       ; R0 := R0(R1)
  5 [-]: TEST      R0 0         ; if not R0 then PC := 10
  6 [-]: JMP       10           ; PC := 10
  7 [-]: LOADKB    R0 0 0       ; R0 := false
  8 [-]: RETURN    R0 2         ; return R0
  9 [-]: JMP       19           ; PC := 19
 10 [-]: GETGLOBAL R0 K3        ; R0 := 0xbe190284
 11 [-]: SELF      R0 R0 K4     ; R1 := R0; R0 := R0[0x0eb34c69]
 12 [-]: GETGLOBAL R2 K5        ; R2 := 0x838eccb2
 13 [-]: CONST     R3 0         ; R3 := 0.000000
 14 [-]: CALL      R0 4 2       ; R0 := R0(R1,R2,R3)
 15 [-]: LT        0 R0 K6      ; if R0 >= 4.000000 then PC := 19
 16 [-]: JMP       19           ; PC := 19
 17 [-]: LOADKB    R0 1 0       ; R0 := true
 18 [-]: RETURN    R0 2         ; return R0
 19 [-]: LOADKB    R0 0 0       ; R0 := false
 20 [-]: RETURN    R0 2         ; return R0
 21 [-]: RETURN    R0 1         ; return 


; Function #16:
;
; Name:            
; Defined at line: 416
; #Upvalues:       0
; #Parameters:     2
; Is_vararg:       0
; Max Stack Size:  6

  1 [-]: SELF      R2 R0 K0     ; R3 := R0; R2 := R0[0x659d451f]
  2 [-]: GETGLOBAL R4 K1        ; R4 := 0x7ab8bed8
  3 [-]: LOADKB    R5 0 0       ; R5 := false
  4 [-]: CALL      R2 4 1       ; R2(R3,R4,R5)
  5 [-]: GETGLOBAL R2 K2        ; R2 := 0x89326c93
  6 [-]: SELF      R2 R2 K3     ; R3 := R2; R2 := R2[0x18d05d30]
  7 [-]: CALL      R2 2 2       ; R2 := R2(R3)
  8 [-]: TEST      R2 0         ; if not R2 then PC := 14
  9 [-]: JMP       14           ; PC := 14
 10 [-]: GETGLOBAL R2 K4        ; R2 := _T
 11 [-]: GETTABLE  R2 R2 K5     ; R2 := R2[0x2de0f140]
 12 [-]: MOVE      R3 R1        ; R3 := R1
 13 [-]: CALL      R2 2 1       ; R2(R3)
 14 [-]: RETURN    R0 1         ; return 


