; This file has been disassembled using luadec 2.0.2 by sztupy (modified by Reversive)

; Name:            
; Defined at line: 0
; #Upvalues:       0
; #Parameters:     0
; Is_vararg:       2
; Max Stack Size:  43

  1 [-]: GETGLOBAL R0 K0        ; R0 := 0x2d0fad09
  2 [-]: LOADK     R1 K1        ; R1 := "Lotus.Interface.UIUtilities"
  3 [-]: CALL      R0 2 2       ; R0 := R0(R1)
  4 [-]: GETGLOBAL R1 K0        ; R1 := 0x2d0fad09
  5 [-]: LOADK     R2 K2        ; R2 := "Lotus.Interface.LotusUtilities"
  6 [-]: CALL      R1 2 2       ; R1 := R1(R2)
  7 [-]: GETGLOBAL R2 K0        ; R2 := 0x2d0fad09
  8 [-]: LOADK     R3 K3        ; R3 := "EE.Interface.Utilities"
  9 [-]: CALL      R2 2 2       ; R2 := R2(R3)
 10 [-]: LOADNIL   R3 R3        ; R3 := nil
 11 [-]: LOADBOOL  R4 0 0       ; R4 := false
 12 [-]: LOADNIL   R5 R5        ; R5 := nil
 13 [-]: NEWTABLE  R6 0 0       ; R6 := {}
 14 [-]: LOADBOOL  R7 0 0       ; R7 := false
 15 [-]: LOADNIL   R8 R12       ; R8 := R9 := R10 := R11 := R12 := nil
 16 [-]: LOADK     R13 0        ; R13 := 0.000000
 17 [-]: LOADK     R14 0        ; R14 := 0.000000
 18 [-]: LOADK     R15 0        ; R15 := 0.000000
 19 [-]: LOADK     R16 0        ; R16 := 0.000000
 20 [-]: LOADK     R17 0        ; R17 := 0.000000
 21 [-]: LOADBOOL  R18 0 0      ; R18 := false
 22 [-]: LOADK     R19 K4       ; R19 := ""
 23 [-]: LOADK     R20 0        ; R20 := 0.000000
 24 [-]: LOADK     R21 0        ; R21 := 0.000000
 25 [-]: LOADBOOL  R22 0 0      ; R22 := false
 26 [-]: LOADNIL   R23 R23      ; R23 := nil
 27 [-]: LOADK     R24 90       ; R24 := 90.000000
 28 [-]: LOADK     R25 5        ; R25 := 5.000000
 29 [-]: LOADK     R26 K5       ; R26 := 0.150000
 30 [-]: MUL       R27 R26 K6   ; R27 := R26 * 0.500000
 31 [-]: LOADK     R28 100      ; R28 := 100.000000
 32 [-]: CLOSURE   R29 0        ; R29 := closure(Function #1)
 33 [-]: CLOSURE   R30 1        ; R30 := closure(Function #2)
 34 [-]: MOVE      R0 R1        ; R0 := R1
 35 [-]: CLOSURE   R31 2        ; R31 := closure(Function #3)
 36 [-]: MOVE      R0 R14       ; R0 := R14
 37 [-]: CLOSURE   R32 3        ; R32 := closure(Function #4)
 38 [-]: MOVE      R0 R13       ; R0 := R13
 39 [-]: MOVE      R0 R28       ; R0 := R28
 40 [-]: CLOSURE   R33 4        ; R33 := closure(Function #5)
 41 [-]: CLOSURE   R34 5        ; R34 := closure(Function #6)
 42 [-]: MOVE      R0 R2        ; R0 := R2
 43 [-]: MOVE      R0 R26       ; R0 := R26
 44 [-]: MOVE      R0 R33       ; R0 := R33
 45 [-]: MOVE      R0 R17       ; R0 := R17
 46 [-]: CLOSURE   R35 6        ; R35 := closure(Function #7)
 47 [-]: MOVE      R0 R28       ; R0 := R28
 48 [-]: CLOSURE   R36 7        ; R36 := closure(Function #8)
 49 [-]: MOVE      R0 R15       ; R0 := R15
 50 [-]: MOVE      R0 R24       ; R0 := R24
 51 [-]: MOVE      R0 R17       ; R0 := R17
 52 [-]: CLOSURE   R37 8        ; R37 := closure(Function #9)
 53 [-]: MOVE      R0 R13       ; R0 := R13
 54 [-]: MOVE      R0 R25       ; R0 := R25
 55 [-]: MOVE      R0 R14       ; R0 := R14
 56 [-]: MOVE      R0 R15       ; R0 := R15
 57 [-]: MOVE      R0 R16       ; R0 := R16
 58 [-]: MOVE      R0 R27       ; R0 := R27
 59 [-]: MOVE      R0 R34       ; R0 := R34
 60 [-]: MOVE      R0 R35       ; R0 := R35
 61 [-]: MOVE      R0 R28       ; R0 := R28
 62 [-]: MOVE      R0 R26       ; R0 := R26
 63 [-]: MOVE      R0 R3        ; R0 := R3
 64 [-]: MOVE      R0 R36       ; R0 := R36
 65 [-]: CLOSURE   R38 9        ; R38 := closure(Function #10)
 66 [-]: MOVE      R0 R4        ; R0 := R4
 67 [-]: MOVE      R0 R3        ; R0 := R3
 68 [-]: MOVE      R0 R5        ; R0 := R5
 69 [-]: MOVE      R0 R7        ; R0 := R7
 70 [-]: MOVE      R0 R6        ; R0 := R6
 71 [-]: MOVE      R0 R12       ; R0 := R12
 72 [-]: MOVE      R0 R18       ; R0 := R18
 73 [-]: MOVE      R0 R20       ; R0 := R20
 74 [-]: MOVE      R0 R2        ; R0 := R2
 75 [-]: MOVE      R0 R30       ; R0 := R30
 76 [-]: MOVE      R0 R29       ; R0 := R29
 77 [-]: MOVE      R0 R8        ; R0 := R8
 78 [-]: MOVE      R0 R10       ; R0 := R10
 79 [-]: MOVE      R0 R11       ; R0 := R11
 80 [-]: MOVE      R0 R23       ; R0 := R23
 81 [-]: MOVE      R0 R31       ; R0 := R31
 82 [-]: MOVE      R0 R32       ; R0 := R32
 83 [-]: MOVE      R0 R28       ; R0 := R28
 84 [-]: MOVE      R0 R37       ; R0 := R37
 85 [-]: MOVE      R0 R22       ; R0 := R22
 86 [-]: MOVE      R0 R0        ; R0 := R0
 87 [-]: MOVE      R0 R21       ; R0 := R21
 88 [-]: MOVE      R0 R9        ; R0 := R9
 89 [-]: SETGLOBAL R38 K7       ; Update := R38
 90 [-]: CLOSURE   R38 10       ; R38 := closure(Function #11)
 91 [-]: MOVE      R0 R7        ; R0 := R7
 92 [-]: MOVE      R0 R6        ; R0 := R6
 93 [-]: CLOSURE   R39 11       ; R39 := closure(Function #12)
 94 [-]: SETGLOBAL R39 K8       ; Shutdown := R39
 95 [-]: CLOSURE   R39 12       ; R39 := closure(Function #13)
 96 [-]: MOVE      R0 R34       ; R0 := R34
 97 [-]: CLOSURE   R40 13       ; R40 := closure(Function #14)
 98 [-]: CLOSURE   R41 14       ; R41 := closure(Function #15)
 99 [-]: CLOSURE   R42 15       ; R42 := closure(Function #16)
100 [-]: MOVE      R0 R3        ; R0 := R3
101 [-]: MOVE      R0 R19       ; R0 := R19
102 [-]: MOVE      R0 R2        ; R0 := R2
103 [-]: MOVE      R0 R20       ; R0 := R20
104 [-]: MOVE      R0 R38       ; R0 := R38
105 [-]: MOVE      R0 R40       ; R0 := R40
106 [-]: MOVE      R0 R41       ; R0 := R41
107 [-]: MOVE      R0 R39       ; R0 := R39
108 [-]: MOVE      R0 R11       ; R0 := R11
109 [-]: MOVE      R0 R28       ; R0 := R28
110 [-]: MOVE      R0 R23       ; R0 := R23
111 [-]: MOVE      R0 R31       ; R0 := R31
112 [-]: MOVE      R0 R32       ; R0 := R32
113 [-]: MOVE      R0 R15       ; R0 := R15
114 [-]: MOVE      R0 R13       ; R0 := R13
115 [-]: MOVE      R0 R25       ; R0 := R25
116 [-]: MOVE      R0 R14       ; R0 := R14
117 [-]: MOVE      R0 R36       ; R0 := R36
118 [-]: MOVE      R0 R35       ; R0 := R35
119 [-]: MOVE      R0 R34       ; R0 := R34
120 [-]: MOVE      R0 R21       ; R0 := R21
121 [-]: MOVE      R0 R8        ; R0 := R8
122 [-]: MOVE      R0 R9        ; R0 := R9
123 [-]: MOVE      R0 R10       ; R0 := R10
124 [-]: MOVE      R0 R4        ; R0 := R4
125 [-]: SETGLOBAL R42 K9       ; Initialize := R42
126 [-]: CLOSURE   R42 16       ; R42 := closure(Function #17)
127 [-]: MOVE      R0 R0        ; R0 := R0
128 [-]: SETGLOBAL R42 K10      ; HandleHudScale := R42
129 [-]: RETURN    R0 1         ; return 


; Function #1:
;
; Name:            
; Defined at line: 46
; #Upvalues:       0
; #Parameters:     0
; Is_vararg:       0
; Max Stack Size:  3

  1 [-]: GETGLOBAL R0 K0        ; R0 := 0xbe190284
  2 [-]: GETGLOBAL R1 K1        ; R1 := 0x7b998233
  3 [-]: MOVE      R2 R0        ; R2 := R0
  4 [-]: CALL      R1 2 2       ; R1 := R1(R2)
  5 [-]: TEST      R1 1         ; if R1 then PC := 13
  6 [-]: JMP       13           ; PC := 13
  7 [-]: SELF      R1 R0 K2     ; R2 := R0; R1 := R0[0x486e5f11]
  8 [-]: CALL      R1 2 2       ; R1 := R1(R2)
  9 [-]: TEST      R1 0         ; if not R1 then PC := 13
 10 [-]: JMP       13           ; PC := 13
 11 [-]: LOADBOOL  R1 1 0       ; R1 := true
 12 [-]: RETURN    R1 2         ; return R1
 13 [-]: LOADBOOL  R1 0 0       ; R1 := false
 14 [-]: RETURN    R1 2         ; return R1
 15 [-]: RETURN    R0 1         ; return 


; Function #2:
;
; Name:            
; Defined at line: 54
; #Upvalues:       1
; #Parameters:     0
; Is_vararg:       0
; Max Stack Size:  2

  1 [-]: GETUPVAL  R0 U0        ; R0 := U0
  2 [-]: GETTABLE  R0 R0 K0     ; R0 := R0[0xb73d420f]
  3 [-]: CALL      R0 1 2       ; R0 := R0()
  4 [-]: GETUPVAL  R1 U0        ; R1 := U0
  5 [-]: GETTABLE  R1 R1 K1     ; R1 := R1["UI_MODE_IN_DOJO"]
  6 [-]: EQ        0 R0 R1      ; if R0 ~= R1 then PC := 10
  7 [-]: JMP       10           ; PC := 10
  8 [-]: LOADBOOL  R0 1 0       ; R0 := true
  9 [-]: RETURN    R0 2         ; return R0
 10 [-]: LOADBOOL  R0 0 0       ; R0 := false
 11 [-]: RETURN    R0 2         ; return R0
 12 [-]: RETURN    R0 1         ; return 


; Function #3:
;
; Name:            
; Defined at line: 61
; #Upvalues:       1
; #Parameters:     1
; Is_vararg:       0
; Max Stack Size:  2

  1 [-]: SETUPVAL  R0 U0        ; U82 := R0
  2 [-]: RETURN    R0 1         ; return 


; Function #4:
;
; Name:            
; Defined at line: 65
; #Upvalues:       2
; #Parameters:     1
; Is_vararg:       0
; Max Stack Size:  4

  1 [-]: GETGLOBAL R1 K0        ; R1 := 0x5bced4c4
  2 [-]: GETTABLE  R1 R1 K1     ; R1 := R1[0xac1b386a]
  3 [-]: MOVE      R2 R0        ; R2 := R0
  4 [-]: GETUPVAL  R3 U1        ; R3 := U1
  5 [-]: CALL      R1 3 2       ; R1 := R1(R2,R3)
  6 [-]: SETUPVAL  R1 U0        ; U82 := R0
  7 [-]: RETURN    R0 1         ; return 


; Function #5:
;
; Name:            
; Defined at line: 69
; #Upvalues:       0
; #Parameters:     1
; Is_vararg:       0
; Max Stack Size:  2

  1 [-]: MUL       R1 R0 K0     ; R1 := R0 * 20.000000
  2 [-]: ADD       R1 K1 R1     ; R1 := 1.000000 + R1
  3 [-]: RETURN    R1 2         ; return R1
  4 [-]: RETURN    R0 1         ; return 


; Function #6:
;
; Name:            
; Defined at line: 73
; #Upvalues:       4
; #Parameters:     5
; Is_vararg:       0
; Max Stack Size:  19

  1 [-]: GETUPVAL  R5 U0        ; R5 := U0
  2 [-]: GETTABLE  R5 R5 K0     ; R5 := R5[0x06d055f9]
  3 [-]: MOVE      R6 R3        ; R6 := R3
  4 [-]: LOADK     R7 0         ; R7 := 0.000000
  5 [-]: GETUPVAL  R8 U1        ; R8 := U1
  6 [-]: CALL      R5 4 2       ; R5 := R5(R6,R7,R8)
  7 [-]: GETUPVAL  R6 U2        ; R6 := U2
  8 [-]: GETUPVAL  R7 U0        ; R7 := U0
  9 [-]: GETTABLE  R7 R7 K0     ; R7 := R7[0x06d055f9]
 10 [-]: MOVE      R8 R1        ; R8 := R1
 11 [-]: SUB       R9 R0 K1     ; R9 := R0 - 1.000000
 12 [-]: MOVE      R10 R0       ; R10 := R0
 13 [-]: CALL      R7 4 0       ; R7,... := R7(R8,R9,R10)
 14 [-]: CALL      R6 0 2       ; R6 := R6(R7,...)
 15 [-]: GETUPVAL  R7 U2        ; R7 := U2
 16 [-]: GETUPVAL  R8 U0        ; R8 := U0
 17 [-]: GETTABLE  R8 R8 K0     ; R8 := R8[0x06d055f9]
 18 [-]: MOVE      R9 R1        ; R9 := R1
 19 [-]: MOVE      R10 R0       ; R10 := R0
 20 [-]: SUB       R11 R0 K1    ; R11 := R0 - 1.000000
 21 [-]: CALL      R8 4 0       ; R8,... := R8(R9,R10,R11)
 22 [-]: CALL      R7 0 2       ; R7 := R7(R8,...)
 23 [-]: LOADNIL   R8 R8        ; R8 := nil
 24 [-]: CLOSURE   R9 0         ; R9 := closure(Function #6.1)
 25 [-]: MOVE      R0 R6        ; R0 := R6
 26 [-]: MOVE      R0 R7        ; R0 := R7
 27 [-]: MOVE      R0 R8        ; R0 := R8
 28 [-]: GETUPVAL  R0 U3        ; R0 := U3
 29 [-]: GETGLOBAL R10 K2       ; R10 := 0x25312c9b
 30 [-]: GETGLOBAL R11 K3       ; R11 := 0xae91e43b
 31 [-]: LOADK     R12 K4       ; R12 := "AdaptationStack.Wheel"
 32 [-]: LOADK     R13 0        ; R13 := 0.000000
 33 [-]: NEWTABLE  R14 1 0      ; R14 := {}
 34 [-]: MOVE      R15 R9       ; R15 := R9
 35 [-]: SETLIST   R14 1 1      ; R14[(1-1)*FPF+i] := R(14+i), 1 <= i <= 1
 36 [-]: NEWTABLE  R15 1 0      ; R15 := {}
 37 [-]: LOADK     R16 1        ; R16 := 1.000000
 38 [-]: SETLIST   R15 1 1      ; R15[(1-1)*FPF+i] := R(15+i), 1 <= i <= 1
 39 [-]: MOVE      R16 R5       ; R16 := R5
 40 [-]: LOADK     R17 0        ; R17 := 0.000000
 41 [-]: MOVE      R18 R2       ; R18 := R2
 42 [-]: CALL      R10 9 1      ; R10(R11,R12,R13,R14,R15,R16,R17,R18)
 43 [-]: RETURN    R0 1         ; return 


; Function #6.1:
;
; Name:            
; Defined at line: 80
; #Upvalues:       4
; #Parameters:     1
; Is_vararg:       0
; Max Stack Size:  12

  1 [-]: GETGLOBAL R1 K0        ; R1 := 0x5bced4c4
  2 [-]: GETTABLE  R1 R1 K1     ; R1 := R1[0x55f27c30]
  3 [-]: GETGLOBAL R2 K2        ; R2 := 0x9bafffe3
  4 [-]: GETUPVAL  R3 U0        ; R3 := U0
  5 [-]: GETUPVAL  R4 U1        ; R4 := U1
  6 [-]: MOVE      R5 R0        ; R5 := R0
  7 [-]: CALL      R2 4 0       ; R2,... := R2(R3,R4,R5)
  8 [-]: CALL      R1 0 2       ; R1 := R1(R2,...)
  9 [-]: GETUPVAL  R2 U2        ; R2 := U2
 10 [-]: EQ        1 R2 R1      ; if R2 == R1 then PC := 48
 11 [-]: JMP       48           ; PC := 48
 12 [-]: SETUPVAL  R1 U2        ; U82 := R2
 13 [-]: GETGLOBAL R2 K3        ; R2 := 0x38f10e85
 14 [-]: GETGLOBAL R3 K4        ; R3 := 0xae91e43b
 15 [-]: LOADK     R4 K5        ; R4 := "AdaptationStack.Wheel.Progress.gotoAndStop"
 16 [-]: LOADK     R5 1         ; R5 := 1.000000
 17 [-]: CALL      R2 4 1       ; R2(R3,R4,R5)
 18 [-]: GETGLOBAL R2 K3        ; R2 := 0x38f10e85
 19 [-]: GETGLOBAL R3 K4        ; R3 := 0xae91e43b
 20 [-]: LOADK     R4 K5        ; R4 := "AdaptationStack.Wheel.Progress.gotoAndStop"
 21 [-]: GETUPVAL  R5 U2        ; R5 := U2
 22 [-]: CALL      R2 4 1       ; R2(R3,R4,R5)
 23 [-]: GETGLOBAL R2 K6        ; R2 := 0xc8802016
 24 [-]: NEWTABLE  R3 2 0       ; R3 := {}
 25 [-]: LOADK     R4 K7        ; R4 := "Right"
 26 [-]: LOADK     R5 K8        ; R5 := "Left"
 27 [-]: SETLIST   R3 2 1       ; R3[(1-1)*FPF+i] := R(3+i), 1 <= i <= 2
 28 [-]: CALL      R2 2 4       ; R2,R3,R4 := R2(R3)
 29 [-]: JMP       46           ; PC := 46
 30 [-]: GETGLOBAL R7 K3        ; R7 := 0x38f10e85
 31 [-]: GETGLOBAL R8 K4        ; R8 := 0xae91e43b
 32 [-]: LOADK     R9 K9        ; R9 := "AdaptationStack.Wheel.Progress."
 33 [-]: MOVE      R10 R6       ; R10 := R6
 34 [-]: LOADK     R11 K10      ; R11 := ".gotoAndStop"
 35 [-]: CONCAT    R9 R9 R11    ; R9 := R9 .. R10 .. R11
 36 [-]: LOADK     R10 1        ; R10 := 1.000000
 37 [-]: CALL      R7 4 1       ; R7(R8,R9,R10)
 38 [-]: GETGLOBAL R7 K3        ; R7 := 0x38f10e85
 39 [-]: GETGLOBAL R8 K4        ; R8 := 0xae91e43b
 40 [-]: LOADK     R9 K9        ; R9 := "AdaptationStack.Wheel.Progress."
 41 [-]: MOVE      R10 R6       ; R10 := R6
 42 [-]: LOADK     R11 K10      ; R11 := ".gotoAndStop"
 43 [-]: CONCAT    R9 R9 R11    ; R9 := R9 .. R10 .. R11
 44 [-]: GETUPVAL  R10 U3       ; R10 := U3
 45 [-]: CALL      R7 4 1       ; R7(R8,R9,R10)
 46 [-]: TFORLOOP  R2 2         ; R5,R6 :=  R2(R3,R4); if R5 ~= nil then begin PC = 30; R4 := R5 end
 47 [-]: JMP       30           ; PC := 30
 48 [-]: RETURN    R0 1         ; return 


; Function #7:
;
; Name:            
; Defined at line: 95
; #Upvalues:       1
; #Parameters:     1
; Is_vararg:       0
; Max Stack Size:  8

  1 [-]: GETUPVAL  R1 U0        ; R1 := U0
  2 [-]: LT        0 R0 R1      ; if R0 >= R1 then PC := 19
  3 [-]: JMP       19           ; PC := 19
  4 [-]: GETGLOBAL R1 K0        ; R1 := 0x38f10e85
  5 [-]: GETGLOBAL R2 K1        ; R2 := 0xae91e43b
  6 [-]: LOADK     R3 K2        ; R3 := "AdaptationStack.Count.setVertexColors"
  7 [-]: LOADK     R4 K3        ; R4 := 16777215.000000
  8 [-]: LOADK     R5 K3        ; R5 := 16777215.000000
  9 [-]: LOADK     R6 K3        ; R6 := 16777215.000000
 10 [-]: LOADK     R7 K3        ; R7 := 16777215.000000
 11 [-]: CALL      R1 7 1       ; R1(R2,R3,R4,R5,R6,R7)
 12 [-]: GETGLOBAL R1 K1        ; R1 := 0xae91e43b
 13 [-]: SELF      R1 R1 K4     ; R2 := R1; R1 := R1[0x5f56eeab]
 14 [-]: LOADK     R3 K5        ; R3 := "AdaptationStack.Count"
 15 [-]: LOADK     R4 29        ; R4 := 29.000000
 16 [-]: MOVE      R5 R0        ; R5 := R0
 17 [-]: CALL      R1 5 1       ; R1(R2,R3,R4,R5)
 18 [-]: JMP       32           ; PC := 32
 19 [-]: GETGLOBAL R1 K0        ; R1 := 0x38f10e85
 20 [-]: GETGLOBAL R2 K1        ; R2 := 0xae91e43b
 21 [-]: LOADK     R3 K2        ; R3 := "AdaptationStack.Count.setVertexColors"
 22 [-]: LOADK     R4 K3        ; R4 := 16777215.000000
 23 [-]: LOADK     R5 K3        ; R5 := 16777215.000000
 24 [-]: LOADK     R6 K6        ; R6 := 12528988.000000
 25 [-]: LOADK     R7 K6        ; R7 := 12528988.000000
 26 [-]: CALL      R1 7 1       ; R1(R2,R3,R4,R5,R6,R7)
 27 [-]: GETGLOBAL R1 K1        ; R1 := 0xae91e43b
 28 [-]: SELF      R1 R1 K7     ; R2 := R1; R1 := R1[0x20b98db3]
 29 [-]: LOADK     R3 K8        ; R3 := "AdaptationStack.Count.text"
 30 [-]: LOADK     R4 K9        ; R4 := "<INFESTED_ADAPTATION>"
 31 [-]: CALL      R1 4 1       ; R1(R2,R3,R4)
 32 [-]: RETURN    R0 1         ; return 


; Function #8:
;
; Name:            
; Defined at line: 105
; #Upvalues:       3
; #Parameters:     0
; Is_vararg:       0
; Max Stack Size:  11

  1 [-]: GETGLOBAL R0 K0        ; R0 := 0x5bced4c4
  2 [-]: GETTABLE  R0 R0 K1     ; R0 := R0[0xac1b386a]
  3 [-]: GETUPVAL  R1 U0        ; R1 := U0
  4 [-]: GETUPVAL  R2 U1        ; R2 := U1
  5 [-]: CALL      R0 3 2       ; R0 := R0(R1,R2)
  6 [-]: ADD       R0 K2 R0     ; R0 := 1.000000 + R0
  7 [-]: GETUPVAL  R1 U2        ; R1 := U2
  8 [-]: EQ        1 R1 R0      ; if R1 == R0 then PC := 36
  9 [-]: JMP       36           ; PC := 36
 10 [-]: SETUPVAL  R0 U2        ; U82 := R2
 11 [-]: GETGLOBAL R1 K3        ; R1 := 0xc8802016
 12 [-]: NEWTABLE  R2 2 0       ; R2 := {}
 13 [-]: LOADK     R3 K4        ; R3 := "Growths"
 14 [-]: LOADK     R4 K5        ; R4 := "Backer"
 15 [-]: SETLIST   R2 2 1       ; R2[(1-1)*FPF+i] := R(2+i), 1 <= i <= 2
 16 [-]: CALL      R1 2 4       ; R1,R2,R3 := R1(R2)
 17 [-]: JMP       34           ; PC := 34
 18 [-]: GETGLOBAL R6 K6        ; R6 := 0x38f10e85
 19 [-]: GETGLOBAL R7 K7        ; R7 := 0xae91e43b
 20 [-]: LOADK     R8 K8        ; R8 := "AdaptationStack.Wheel."
 21 [-]: MOVE      R9 R5        ; R9 := R5
 22 [-]: LOADK     R10 K9       ; R10 := ".gotoAndStop"
 23 [-]: CONCAT    R8 R8 R10    ; R8 := R8 .. R9 .. R10
 24 [-]: LOADK     R9 1         ; R9 := 1.000000
 25 [-]: CALL      R6 4 1       ; R6(R7,R8,R9)
 26 [-]: GETGLOBAL R6 K6        ; R6 := 0x38f10e85
 27 [-]: GETGLOBAL R7 K7        ; R7 := 0xae91e43b
 28 [-]: LOADK     R8 K8        ; R8 := "AdaptationStack.Wheel."
 29 [-]: MOVE      R9 R5        ; R9 := R5
 30 [-]: LOADK     R10 K9       ; R10 := ".gotoAndStop"
 31 [-]: CONCAT    R8 R8 R10    ; R8 := R8 .. R9 .. R10
 32 [-]: GETUPVAL  R9 U2        ; R9 := U2
 33 [-]: CALL      R6 4 1       ; R6(R7,R8,R9)
 34 [-]: TFORLOOP  R1 2         ; R4,R5 :=  R1(R2,R3); if R4 ~= nil then begin PC = 18; R3 := R4 end
 35 [-]: JMP       18           ; PC := 18
 36 [-]: RETURN    R0 1         ; return 


; Function #9:
;
; Name:            
; Defined at line: 116
; #Upvalues:       12
; #Parameters:     1
; Is_vararg:       0
; Max Stack Size:  10

  1 [-]: GETUPVAL  R1 U0        ; R1 := U0
  2 [-]: GETUPVAL  R2 U1        ; R2 := U1
  3 [-]: MUL       R1 R1 R2     ; R1 := R1 * R2
  4 [-]: GETUPVAL  R2 U2        ; R2 := U2
  5 [-]: ADD       R1 R1 R2     ; R1 := R1 + R2
  6 [-]: GETUPVAL  R2 U3        ; R2 := U3
  7 [-]: EQ        1 R1 R2      ; if R1 == R2 then PC := 123
  8 [-]: JMP       123          ; PC := 123
  9 [-]: GETUPVAL  R2 U4        ; R2 := U4
 10 [-]: SUB       R2 R2 R0     ; R2 := R2 - R0
 11 [-]: SETUPVAL  R2 U4        ; U82 := R4
 12 [-]: GETUPVAL  R2 U4        ; R2 := U4
 13 [-]: LE        0 R2 K0      ; if R2 > 0.000000 then PC := 123
 14 [-]: JMP       123          ; PC := 123
 15 [-]: GETUPVAL  R2 U4        ; R2 := U4
 16 [-]: GETUPVAL  R3 U5        ; R3 := U5
 17 [-]: ADD       R2 R2 R3     ; R2 := R2 + R3
 18 [-]: SETUPVAL  R2 U4        ; U82 := R4
 19 [-]: GETGLOBAL R2 K1        ; R2 := 0x5bced4c4
 20 [-]: GETTABLE  R2 R2 K2     ; R2 := R2[0x55f27c30]
 21 [-]: GETUPVAL  R3 U3        ; R3 := U3
 22 [-]: GETUPVAL  R4 U1        ; R4 := U1
 23 [-]: DIV       R3 R3 R4     ; R3 := R3 / R4
 24 [-]: CALL      R2 2 2       ; R2 := R2(R3)
 25 [-]: GETUPVAL  R3 U3        ; R3 := U3
 26 [-]: LT        0 R3 R1      ; if R3 >= R1 then PC := 81
 27 [-]: JMP       81           ; PC := 81
 28 [-]: GETUPVAL  R3 U3        ; R3 := U3
 29 [-]: ADD       R3 R3 K3     ; R3 := R3 + 1.000000
 30 [-]: SETUPVAL  R3 U3        ; U82 := R3
 31 [-]: GETGLOBAL R3 K1        ; R3 := 0x5bced4c4
 32 [-]: GETTABLE  R3 R3 K2     ; R3 := R3[0x55f27c30]
 33 [-]: GETUPVAL  R4 U3        ; R4 := U3
 34 [-]: GETUPVAL  R5 U1        ; R5 := U1
 35 [-]: DIV       R4 R4 R5     ; R4 := R4 / R5
 36 [-]: CALL      R3 2 2       ; R3 := R3(R4)
 37 [-]: GETUPVAL  R4 U3        ; R4 := U3
 38 [-]: GETUPVAL  R5 U1        ; R5 := U1
 39 [-]: MOD       R4 R4 R5     ; R4 := R4 % R5
 40 [-]: LT        0 R2 R3      ; if R2 >= R3 then PC := 75
 41 [-]: JMP       75           ; PC := 75
 42 [-]: GETGLOBAL R5 K4        ; R5 := 0x7b998233
 43 [-]: GETGLOBAL R6 K5        ; R6 := 0xbe190284
 44 [-]: CALL      R5 2 2       ; R5 := R5(R6)
 45 [-]: TEST      R5 1         ; if R5 then PC := 60
 46 [-]: JMP       60           ; PC := 60
 47 [-]: GETGLOBAL R5 K5        ; R5 := 0xbe190284
 48 [-]: SELF      R5 R5 K6     ; R6 := R5; R5 := R5[0xf2deaf69]
 49 [-]: GETGLOBAL R7 K7        ; R7 := gLotusPhotoBoothGameRulesType
 50 [-]: CALL      R5 3 2       ; R5 := R5(R6,R7)
 51 [-]: TEST      R5 1         ; if R5 then PC := 60
 52 [-]: JMP       60           ; PC := 60
 53 [-]: GETGLOBAL R5 K8        ; R5 := 0x89326c93
 54 [-]: SELF      R5 R5 K9     ; R6 := R5; R5 := R5[0x659d451f]
 55 [-]: GETGLOBAL R7 K10       ; R7 := 0xb3561fe2
 56 [-]: GETGLOBAL R8 K11       ; R8 := 0xa421af95
 57 [-]: CALL      R8 1 2       ; R8 := R8()
 58 [-]: LOADBOOL  R9 0 0       ; R9 := false
 59 [-]: CALL      R5 5 1       ; R5(R6,R7,R8,R9)
 60 [-]: GETUPVAL  R5 U4        ; R5 := U4
 61 [-]: GETUPVAL  R6 U5        ; R6 := U5
 62 [-]: MUL       R6 R6 K12    ; R6 := R6 * 3.000000
 63 [-]: ADD       R5 R5 R6     ; R5 := R5 + R6
 64 [-]: SETUPVAL  R5 U4        ; U82 := R4
 65 [-]: GETUPVAL  R5 U6        ; R5 := U6
 66 [-]: GETUPVAL  R6 U1        ; R6 := U1
 67 [-]: LOADBOOL  R7 1 0       ; R7 := true
 68 [-]: CLOSURE   R8 0         ; R8 := closure(Function #9.1)
 69 [-]: GETUPVAL  R0 U7        ; R0 := U7
 70 [-]: MOVE      R0 R3        ; R0 := R3
 71 [-]: GETUPVAL  R0 U8        ; R0 := U8
 72 [-]: GETUPVAL  R0 U9        ; R0 := U9
 73 [-]: CALL      R5 4 1       ; R5(R6,R7,R8)
 74 [-]: JMP       79           ; PC := 79
 75 [-]: GETUPVAL  R5 U6        ; R5 := U6
 76 [-]: MOVE      R6 R4        ; R6 := R4
 77 [-]: LOADBOOL  R7 1 0       ; R7 := true
 78 [-]: CALL      R5 3 1       ; R5(R6,R7)
 79 [-]: CLOSE     R3           ; SAVE R3,...
 80 [-]: JMP       121          ; PC := 121
 81 [-]: GETUPVAL  R3 U3        ; R3 := U3
 82 [-]: SUB       R3 R3 K3     ; R3 := R3 - 1.000000
 83 [-]: SETUPVAL  R3 U3        ; U82 := R3
 84 [-]: GETGLOBAL R3 K1        ; R3 := 0x5bced4c4
 85 [-]: GETTABLE  R3 R3 K2     ; R3 := R3[0x55f27c30]
 86 [-]: GETUPVAL  R4 U3        ; R4 := U3
 87 [-]: GETUPVAL  R5 U1        ; R5 := U1
 88 [-]: DIV       R4 R4 R5     ; R4 := R4 / R5
 89 [-]: CALL      R3 2 2       ; R3 := R3(R4)
 90 [-]: GETUPVAL  R4 U3        ; R4 := U3
 91 [-]: GETUPVAL  R5 U1        ; R5 := U1
 92 [-]: MOD       R4 R4 R5     ; R4 := R4 % R5
 93 [-]: LT        0 R3 R2      ; if R3 >= R2 then PC := 117
 94 [-]: JMP       117          ; PC := 117
 95 [-]: GETUPVAL  R5 U4        ; R5 := U4
 96 [-]: GETUPVAL  R6 U5        ; R6 := U5
 97 [-]: MUL       R6 R6 K13    ; R6 := R6 * 4.000000
 98 [-]: ADD       R5 R5 R6     ; R5 := R5 + R6
 99 [-]: SETUPVAL  R5 U4        ; U82 := R4
100 [-]: GETUPVAL  R5 U7        ; R5 := U7
101 [-]: MOVE      R6 R3        ; R6 := R3
102 [-]: CALL      R5 2 1       ; R5(R6)
103 [-]: GETUPVAL  R5 U10       ; R5 := U10
104 [-]: SELF      R5 R5 K14    ; R6 := R5; R5 := R5[0xbd2e96ea]
105 [-]: GETUPVAL  R7 U9        ; R7 := U9
106 [-]: CLOSURE   R8 1         ; R8 := closure(Function #9.2)
107 [-]: GETUPVAL  R0 U6        ; R0 := U6
108 [-]: GETUPVAL  R0 U1        ; R0 := U1
109 [-]: GETUPVAL  R0 U9        ; R0 := U9
110 [-]: GETUPVAL  R0 U4        ; R0 := U4
111 [-]: CALL      R5 4 1       ; R5(R6,R7,R8)
112 [-]: GETUPVAL  R5 U6        ; R5 := U6
113 [-]: LOADK     R6 0         ; R6 := 0.000000
114 [-]: LOADBOOL  R7 0 0       ; R7 := false
115 [-]: CALL      R5 3 1       ; R5(R6,R7)
116 [-]: JMP       121          ; PC := 121
117 [-]: GETUPVAL  R5 U6        ; R5 := U6
118 [-]: ADD       R6 R4 K3     ; R6 := R4 + 1.000000
119 [-]: LOADBOOL  R7 0 0       ; R7 := false
120 [-]: CALL      R5 3 1       ; R5(R6,R7)
121 [-]: GETUPVAL  R5 U11       ; R5 := U11
122 [-]: CALL      R5 1 1       ; R5()
123 [-]: RETURN    R0 1         ; return 


; Function #9.1:
;
; Name:            
; Defined at line: 134
; #Upvalues:       4
; #Parameters:     0
; Is_vararg:       0
; Max Stack Size:  9

  1 [-]: GETUPVAL  R0 U0        ; R0 := U0
  2 [-]: GETUPVAL  R1 U1        ; R1 := U1
  3 [-]: CALL      R0 2 1       ; R0(R1)
  4 [-]: GETUPVAL  R0 U1        ; R0 := U1
  5 [-]: GETUPVAL  R1 U2        ; R1 := U2
  6 [-]: LT        0 R0 R1      ; if R0 >= R1 then PC := 22
  7 [-]: JMP       22           ; PC := 22
  8 [-]: GETGLOBAL R0 K0        ; R0 := 0x25312c9b
  9 [-]: GETGLOBAL R1 K1        ; R1 := 0xae91e43b
 10 [-]: LOADK     R2 K2        ; R2 := "AdaptationStack.Wheel.Progress"
 11 [-]: LOADK     R3 0         ; R3 := 0.000000
 12 [-]: NEWTABLE  R4 1 0       ; R4 := {}
 13 [-]: LOADK     R5 10        ; R5 := 10.000000
 14 [-]: SETLIST   R4 1 1       ; R4[(1-1)*FPF+i] := R(4+i), 1 <= i <= 1
 15 [-]: NEWTABLE  R5 1 0       ; R5 := {}
 16 [-]: LOADK     R6 0         ; R6 := 0.000000
 17 [-]: SETLIST   R5 1 1       ; R5[(1-1)*FPF+i] := R(5+i), 1 <= i <= 1
 18 [-]: GETUPVAL  R6 U3        ; R6 := U3
 19 [-]: LOADK     R7 0         ; R7 := 0.000000
 20 [-]: CLOSURE   R8 0         ; R8 := closure(Function #9.1.1)
 21 [-]: CALL      R0 9 1       ; R0(R1,R2,R3,R4,R5,R6,R7,R8)
 22 [-]: RETURN    R0 1         ; return 


; Function #9.1.1:
;
; Name:            
; Defined at line: 138
; #Upvalues:       0
; #Parameters:     0
; Is_vararg:       0
; Max Stack Size:  5

  1 [-]: GETGLOBAL R0 K0        ; R0 := 0x38f10e85
  2 [-]: GETGLOBAL R1 K1        ; R1 := 0xae91e43b
  3 [-]: LOADK     R2 K2        ; R2 := "AdaptationStack.Wheel.Progress.gotoAndStop"
  4 [-]: LOADK     R3 1         ; R3 := 1.000000
  5 [-]: CALL      R0 4 1       ; R0(R1,R2,R3)
  6 [-]: GETGLOBAL R0 K1        ; R0 := 0xae91e43b
  7 [-]: SELF      R0 R0 K3     ; R1 := R0; R0 := R0[0x67bc869f]
  8 [-]: LOADK     R2 K4        ; R2 := "AdaptationStack.Wheel.Progress"
  9 [-]: LOADK     R3 10        ; R3 := 10.000000
 10 [-]: LOADK     R4 100       ; R4 := 100.000000
 11 [-]: CALL      R0 5 1       ; R0(R1,R2,R3,R4)
 12 [-]: RETURN    R0 1         ; return 


; Function #9.2:
;
; Name:            
; Defined at line: 155
; #Upvalues:       4
; #Parameters:     0
; Is_vararg:       0
; Max Stack Size:  5

  1 [-]: GETGLOBAL R0 K0        ; R0 := 0xae91e43b
  2 [-]: SELF      R0 R0 K1     ; R1 := R0; R0 := R0[0x67bc869f]
  3 [-]: LOADK     R2 K2        ; R2 := "AdaptationStack.Wheel.Progress"
  4 [-]: LOADK     R3 10        ; R3 := 10.000000
  5 [-]: LOADK     R4 0         ; R4 := 0.000000
  6 [-]: CALL      R0 5 1       ; R0(R1,R2,R3,R4)
  7 [-]: GETUPVAL  R0 U0        ; R0 := U0
  8 [-]: GETUPVAL  R1 U1        ; R1 := U1
  9 [-]: LOADBOOL  R2 1 0       ; R2 := true
 10 [-]: CLOSURE   R3 0         ; R3 := closure(Function #9.2.1)
 11 [-]: GETUPVAL  R0 U2        ; R0 := U2
 12 [-]: GETUPVAL  R0 U0        ; R0 := U0
 13 [-]: GETUPVAL  R0 U1        ; R0 := U1
 14 [-]: GETUPVAL  R0 U3        ; R0 := U3
 15 [-]: LOADBOOL  R4 1 0       ; R4 := true
 16 [-]: CALL      R0 5 1       ; R0(R1,R2,R3,R4)
 17 [-]: RETURN    R0 1         ; return 


; Function #9.2.1:
;
; Name:            
; Defined at line: 158
; #Upvalues:       4
; #Parameters:     0
; Is_vararg:       0
; Max Stack Size:  9

  1 [-]: GETGLOBAL R0 K0        ; R0 := 0x25312c9b
  2 [-]: GETGLOBAL R1 K1        ; R1 := 0xae91e43b
  3 [-]: LOADK     R2 K2        ; R2 := "AdaptationStack.Wheel.Progress"
  4 [-]: LOADK     R3 0         ; R3 := 0.000000
  5 [-]: NEWTABLE  R4 1 0       ; R4 := {}
  6 [-]: LOADK     R5 10        ; R5 := 10.000000
  7 [-]: SETLIST   R4 1 1       ; R4[(1-1)*FPF+i] := R(4+i), 1 <= i <= 1
  8 [-]: NEWTABLE  R5 1 0       ; R5 := {}
  9 [-]: LOADK     R6 100       ; R6 := 100.000000
 10 [-]: SETLIST   R5 1 1       ; R5[(1-1)*FPF+i] := R(5+i), 1 <= i <= 1
 11 [-]: GETUPVAL  R6 U0        ; R6 := U0
 12 [-]: LOADK     R7 0         ; R7 := 0.000000
 13 [-]: CLOSURE   R8 0         ; R8 := closure(Function #9.2.1.1)
 14 [-]: GETUPVAL  R0 U1        ; R0 := U1
 15 [-]: GETUPVAL  R0 U2        ; R0 := U2
 16 [-]: GETUPVAL  R0 U3        ; R0 := U3
 17 [-]: CALL      R0 9 1       ; R0(R1,R2,R3,R4,R5,R6,R7,R8)
 18 [-]: RETURN    R0 1         ; return 


; Function #9.2.1.1:
;
; Name:            
; Defined at line: 160
; #Upvalues:       3
; #Parameters:     0
; Is_vararg:       0
; Max Stack Size:  4

  1 [-]: GETUPVAL  R0 U0        ; R0 := U0
  2 [-]: GETUPVAL  R1 U1        ; R1 := U1
  3 [-]: LOADBOOL  R2 0 0       ; R2 := false
  4 [-]: CLOSURE   R3 0         ; R3 := closure(Function #9.2.1.1.1)
  5 [-]: GETUPVAL  R0 U2        ; R0 := U2
  6 [-]: CALL      R0 4 1       ; R0(R1,R2,R3)
  7 [-]: RETURN    R0 1         ; return 


; Function #9.2.1.1.1:
;
; Name:            
; Defined at line: 162
; #Upvalues:       1
; #Parameters:     0
; Is_vararg:       0
; Max Stack Size:  2

  1 [-]: LOADK     R0 0         ; R0 := 0.000000
  2 [-]: SETUPVAL  R0 U0        ; U82 := R0
  3 [-]: RETURN    R0 1         ; return 


; Function #10:
;
; Name:            
; Defined at line: 179
; #Upvalues:       23
; #Parameters:     0
; Is_vararg:       0
; Max Stack Size:  23

  1 [-]: GETGLOBAL R0 K0        ; R0 := 0x7b998233
  2 [-]: GETGLOBAL R1 K1        ; R1 := 0xae91e43b
  3 [-]: CALL      R0 2 2       ; R0 := R0(R1)
  4 [-]: TEST      R0 1         ; if R0 then PC := 9
  5 [-]: JMP       9            ; PC := 9
  6 [-]: GETUPVAL  R0 U0        ; R0 := U0
  7 [-]: TEST      R0 1         ; if R0 then PC := 10
  8 [-]: JMP       10           ; PC := 10
  9 [-]: RETURN    R0 1         ; return 
 10 [-]: GETGLOBAL R0 K2        ; R0 := 0x67652851
 11 [-]: CALL      R0 1 2       ; R0 := R0()
 12 [-]: GETGLOBAL R1 K0        ; R1 := 0x7b998233
 13 [-]: GETUPVAL  R2 U1        ; R2 := U1
 14 [-]: CALL      R1 2 2       ; R1 := R1(R2)
 15 [-]: TEST      R1 1         ; if R1 then PC := 21
 16 [-]: JMP       21           ; PC := 21
 17 [-]: GETUPVAL  R1 U1        ; R1 := U1
 18 [-]: SELF      R1 R1 K3     ; R2 := R1; R1 := R1[0xfaa69527]
 19 [-]: MOVE      R3 R0        ; R3 := R0
 20 [-]: CALL      R1 3 1       ; R1(R2,R3)
 21 [-]: GETGLOBAL R1 K1        ; R1 := 0xae91e43b
 22 [-]: SELF      R1 R1 K4     ; R2 := R1; R1 := R1[0x8a8c8d5a]
 23 [-]: MOVE      R3 R0        ; R3 := R0
 24 [-]: CALL      R1 3 1       ; R1(R2,R3)
 25 [-]: GETGLOBAL R1 K0        ; R1 := 0x7b998233
 26 [-]: GETUPVAL  R2 U2        ; R2 := U2
 27 [-]: CALL      R1 2 2       ; R1 := R1(R2)
 28 [-]: TEST      R1 0         ; if not R1 then PC := 34
 29 [-]: JMP       34           ; PC := 34
 30 [-]: GETGLOBAL R1 K5        ; R1 := 0xbe190284
 31 [-]: SELF      R1 R1 K6     ; R2 := R1; R1 := R1[0x33307f92]
 32 [-]: CALL      R1 2 2       ; R1 := R1(R2)
 33 [-]: SETUPVAL  R1 U2        ; U82 := R2
 34 [-]: LOADBOOL  R1 1 0       ; R1 := true
 35 [-]: SETUPVAL  R1 U3        ; U82 := R3
 36 [-]: GETUPVAL  R1 U4        ; R1 := U4
 37 [-]: LEN       R1 R1        ; R1 := # R1
 38 [-]: LT        0 K7 R1      ; if 0.000000 >= R1 then PC := 58
 39 [-]: JMP       58           ; PC := 58
 40 [-]: LOADK     R1 1         ; R1 := 1.000000
 41 [-]: GETUPVAL  R2 U4        ; R2 := U4
 42 [-]: LEN       R2 R2        ; R2 := # R2
 43 [-]: LOADK     R3 1         ; R3 := 1.000000
 44 [-]: FORPREP   R1 55        ; R1 -= R3; PC := 55
 45 [-]: GETUPVAL  R5 U4        ; R5 := U4
 46 [-]: GETTABLE  R5 R5 R4     ; R5 := R5[R4]
 47 [-]: GETTABLE  R5 R5 K8     ; R5 := R5[1.000000]
 48 [-]: GETUPVAL  R6 U4        ; R6 := U4
 49 [-]: GETTABLE  R6 R6 R4     ; R6 := R6[R4]
 50 [-]: GETTABLE  R6 R6 K9     ; R6 := R6[2.000000]
 51 [-]: GETUPVAL  R7 U4        ; R7 := U4
 52 [-]: GETTABLE  R7 R7 R4     ; R7 := R7[R4]
 53 [-]: GETTABLE  R7 R7 K10    ; R7 := R7[3.000000]
 54 [-]: CALL      R5 3 1       ; R5(R6,R7)
 55 [-]: FORLOOP   R1 45        ; R1 += R3; if R1 <= R2 then begin PC := 45; R4 := R1 end
 56 [-]: NEWTABLE  R5 0 0       ; R5 := {}
 57 [-]: SETUPVAL  R5 U4        ; U82 := R4
 58 [-]: LOADBOOL  R5 0 0       ; R5 := false
 59 [-]: SETUPVAL  R5 U3        ; U82 := R3
 60 [-]: GETGLOBAL R5 K0        ; R5 := 0x7b998233
 61 [-]: GETUPVAL  R6 U2        ; R6 := U2
 62 [-]: CALL      R5 2 2       ; R5 := R5(R6)
 63 [-]: TEST      R5 1         ; if R5 then PC := 131
 64 [-]: JMP       131          ; PC := 131
 65 [-]: GETUPVAL  R5 U2        ; R5 := U2
 66 [-]: SELF      R5 R5 K11    ; R6 := R5; R5 := R5[0x91a24e4b]
 67 [-]: LOADK     R7 K12       ; R7 := "_root"
 68 [-]: LOADK     R8 10        ; R8 := 10.000000
 69 [-]: CALL      R5 4 2       ; R5 := R5(R6,R7,R8)
 70 [-]: GETUPVAL  R6 U5        ; R6 := U5
 71 [-]: EQ        1 R6 R5      ; if R6 == R5 then PC := 80
 72 [-]: JMP       80           ; PC := 80
 73 [-]: SETUPVAL  R5 U5        ; U82 := R5
 74 [-]: GETGLOBAL R6 K1        ; R6 := 0xae91e43b
 75 [-]: SELF      R6 R6 K13    ; R7 := R6; R6 := R6[0x67bc869f]
 76 [-]: LOADK     R8 K12       ; R8 := "_root"
 77 [-]: LOADK     R9 10        ; R9 := 10.000000
 78 [-]: MOVE      R10 R5       ; R10 := R5
 79 [-]: CALL      R6 5 1       ; R6(R7,R8,R9,R10)
 80 [-]: GETUPVAL  R6 U2        ; R6 := U2
 81 [-]: SELF      R6 R6 K14    ; R7 := R6; R6 := R6[0xd4cc05b4]
 82 [-]: CALL      R6 2 2       ; R6 := R6(R7)
 83 [-]: TEST      R6 0         ; if not R6 then PC := 131
 84 [-]: JMP       131          ; PC := 131
 85 [-]: GETGLOBAL R6 K0        ; R6 := 0x7b998233
 86 [-]: GETGLOBAL R7 K15       ; R7 := _T
 87 [-]: GETTABLE  R7 R7 K16    ; R7 := R7["HUD_GetAnchorMgr"]
 88 [-]: CALL      R6 2 2       ; R6 := R6(R7)
 89 [-]: TEST      R6 1         ; if R6 then PC := 131
 90 [-]: JMP       131          ; PC := 131
 91 [-]: GETUPVAL  R6 U2        ; R6 := U2
 92 [-]: SELF      R6 R6 K17    ; R7 := R6; R6 := R6[0x5b0290d2]
 93 [-]: LOADK     R8 K18       ; R8 := "WeaponFrame.Rage"
 94 [-]: LOADK     R9 11        ; R9 := 11.000000
 95 [-]: CALL      R6 4 2       ; R6 := R6(R7,R8,R9)
 96 [-]: GETUPVAL  R7 U6        ; R7 := U6
 97 [-]: EQ        1 R6 R7      ; if R6 == R7 then PC := 131
 98 [-]: JMP       131          ; PC := 131
 99 [-]: SETUPVAL  R6 U6        ; U82 := R6
100 [-]: GETUPVAL  R7 U7        ; R7 := U7
101 [-]: GETUPVAL  R8 U8        ; R8 := U8
102 [-]: GETTABLE  R8 R8 K19    ; R8 := R8[0x06d055f9]
103 [-]: GETUPVAL  R9 U6        ; R9 := U6
104 [-]: LOADK     R10 -40      ; R10 := -40.000000
105 [-]: LOADK     R11 0        ; R11 := 0.000000
106 [-]: CALL      R8 4 2       ; R8 := R8(R9,R10,R11)
107 [-]: ADD       R7 R7 R8     ; R7 := R7 + R8
108 [-]: GETGLOBAL R8 K15       ; R8 := _T
109 [-]: GETTABLE  R8 R8 K20    ; R8 := R8[0xf6b77431]
110 [-]: CALL      R8 1 2       ; R8 := R8()
111 [-]: SELF      R9 R8 K21    ; R10 := R8; R9 := R8[0x4bc5dc8b]
112 [-]: LOADK     R11 K22      ; R11 := "AdaptationStack"
113 [-]: LOADNIL   R12 R12      ; R12 := nil
114 [-]: MOVE      R13 R7       ; R13 := R7
115 [-]: CALL      R9 5 1       ; R9(R10,R11,R12,R13)
116 [-]: SELF      R9 R8 K3     ; R10 := R8; R9 := R8[0xfaa69527]
117 [-]: GETGLOBAL R11 K1       ; R11 := 0xae91e43b
118 [-]: SELF      R11 R11 K23  ; R12 := R11; R11 := R11[0x6b837788]
119 [-]: CALL      R11 2 2      ; R11 := R11(R12)
120 [-]: GETGLOBAL R12 K1       ; R12 := 0xae91e43b
121 [-]: SELF      R12 R12 K24  ; R13 := R12; R12 := R12[0xaf9fda9f]
122 [-]: CALL      R12 2 2      ; R12 := R12(R13)
123 [-]: LOADBOOL  R13 1 0      ; R13 := true
124 [-]: GETTABLE  R14 R8 K25   ; R14 := R8["mHudScalePadding"]
125 [-]: CALL      R9 6 1       ; R9(R10,R11,R12,R13,R14)
126 [-]: GETGLOBAL R9 K15       ; R9 := _T
127 [-]: GETTABLE  R9 R9 K26    ; R9 := R9[0x71907cb1]
128 [-]: GETGLOBAL R10 K1       ; R10 := 0xae91e43b
129 [-]: LOADK     R11 K22      ; R11 := "AdaptationStack"
130 [-]: CALL      R9 3 1       ; R9(R10,R11)
131 [-]: GETUPVAL  R9 U9        ; R9 := U9
132 [-]: CALL      R9 1 2       ; R9 := R9()
133 [-]: TEST      R9 0         ; if not R9 then PC := 162
134 [-]: JMP       162          ; PC := 162
135 [-]: GETUPVAL  R9 U10       ; R9 := U10
136 [-]: CALL      R9 1 2       ; R9 := R9()
137 [-]: TEST      R9 1         ; if R9 then PC := 149
138 [-]: JMP       149          ; PC := 149
139 [-]: GETGLOBAL R9 K1        ; R9 := 0xae91e43b
140 [-]: SELF      R9 R9 K14    ; R10 := R9; R9 := R9[0xd4cc05b4]
141 [-]: CALL      R9 2 2       ; R9 := R9(R10)
142 [-]: TEST      R9 0         ; if not R9 then PC := 149
143 [-]: JMP       149          ; PC := 149
144 [-]: GETGLOBAL R9 K1        ; R9 := 0xae91e43b
145 [-]: SELF      R9 R9 K27    ; R10 := R9; R9 := R9[0x368ad758]
146 [-]: LOADBOOL  R11 0 0      ; R11 := false
147 [-]: CALL      R9 3 1       ; R9(R10,R11)
148 [-]: JMP       162          ; PC := 162
149 [-]: GETUPVAL  R9 U10       ; R9 := U10
150 [-]: CALL      R9 1 2       ; R9 := R9()
151 [-]: TEST      R9 0         ; if not R9 then PC := 162
152 [-]: JMP       162          ; PC := 162
153 [-]: GETGLOBAL R9 K1        ; R9 := 0xae91e43b
154 [-]: SELF      R9 R9 K14    ; R10 := R9; R9 := R9[0xd4cc05b4]
155 [-]: CALL      R9 2 2       ; R9 := R9(R10)
156 [-]: TEST      R9 1         ; if R9 then PC := 162
157 [-]: JMP       162          ; PC := 162
158 [-]: GETGLOBAL R9 K1        ; R9 := 0xae91e43b
159 [-]: SELF      R9 R9 K27    ; R10 := R9; R9 := R9[0x368ad758]
160 [-]: LOADBOOL  R11 1 0      ; R11 := true
161 [-]: CALL      R9 3 1       ; R9(R10,R11)
162 [-]: GETGLOBAL R9 K0        ; R9 := 0x7b998233
163 [-]: GETUPVAL  R10 U11      ; R10 := U11
164 [-]: CALL      R9 2 2       ; R9 := R9(R10)
165 [-]: TEST      R9 0         ; if not R9 then PC := 180
166 [-]: JMP       180          ; PC := 180
167 [-]: GETGLOBAL R9 K28       ; R9 := 0x89326c93
168 [-]: SELF      R9 R9 K29    ; R10 := R9; R9 := R9[0x78298275]
169 [-]: CALL      R9 2 2       ; R9 := R9(R10)
170 [-]: SETUPVAL  R9 U11       ; U82 := R11
171 [-]: GETGLOBAL R9 K0        ; R9 := 0x7b998233
172 [-]: GETUPVAL  R10 U11      ; R10 := U11
173 [-]: CALL      R9 2 2       ; R9 := R9(R10)
174 [-]: TEST      R9 1         ; if R9 then PC := 180
175 [-]: JMP       180          ; PC := 180
176 [-]: GETUPVAL  R9 U11       ; R9 := U11
177 [-]: SELF      R9 R9 K30    ; R10 := R9; R9 := R9[0xde321e6f]
178 [-]: CALL      R9 2 2       ; R9 := R9(R10)
179 [-]: SETUPVAL  R9 U12       ; U82 := R12
180 [-]: GETGLOBAL R9 K0        ; R9 := 0x7b998233
181 [-]: GETUPVAL  R10 U13      ; R10 := U13
182 [-]: CALL      R9 2 2       ; R9 := R9(R10)
183 [-]: TEST      R9 0         ; if not R9 then PC := 216
184 [-]: JMP       216          ; PC := 216
185 [-]: GETGLOBAL R9 K0        ; R9 := 0x7b998233
186 [-]: GETUPVAL  R10 U11      ; R10 := U11
187 [-]: CALL      R9 2 2       ; R9 := R9(R10)
188 [-]: TEST      R9 1         ; if R9 then PC := 216
189 [-]: JMP       216          ; PC := 216
190 [-]: GETUPVAL  R9 U12       ; R9 := U12
191 [-]: SELF      R9 R9 K31    ; R10 := R9; R9 := R9[0xf7d48ee0]
192 [-]: CALL      R9 2 2       ; R9 := R9(R10)
193 [-]: SETUPVAL  R9 U13       ; U82 := R13
194 [-]: LOADNIL   R9 R9        ; R9 := nil
195 [-]: SETUPVAL  R9 U14       ; U82 := R14
196 [-]: GETGLOBAL R9 K0        ; R9 := 0x7b998233
197 [-]: GETUPVAL  R10 U13      ; R10 := U13
198 [-]: CALL      R9 2 2       ; R9 := R9(R10)
199 [-]: TEST      R9 1         ; if R9 then PC := 216
200 [-]: JMP       216          ; PC := 216
201 [-]: GETUPVAL  R9 U13       ; R9 := U13
202 [-]: SELF      R9 R9 K32    ; R10 := R9; R9 := R9[0x3c88e434]
203 [-]: CALL      R9 2 2       ; R9 := R9(R10)
204 [-]: GETGLOBAL R10 K33      ; R10 := 0xc8802016
205 [-]: MOVE      R11 R9       ; R11 := R9
206 [-]: CALL      R10 2 4      ; R10,R11,R12 := R10(R11)
207 [-]: JMP       214          ; PC := 214
208 [-]: SELF      R15 R14 K34  ; R16 := R14; R15 := R14[0xbffa8848]
209 [-]: CALL      R15 2 2      ; R15 := R15(R16)
210 [-]: TEST      R15 0        ; if not R15 then PC := 214
211 [-]: JMP       214          ; PC := 214
212 [-]: SETUPVAL  R13 U14      ; U82 := R14
213 [-]: JMP       216          ; PC := 216
214 [-]: TFORLOOP  R10 2        ; R13,R14 :=  R10(R11,R12); if R13 ~= nil then begin PC = 208; R12 := R13 end
215 [-]: JMP       208          ; PC := 208
216 [-]: GETGLOBAL R15 K0       ; R15 := 0x7b998233
217 [-]: GETUPVAL  R16 U13      ; R16 := U13
218 [-]: CALL      R15 2 2      ; R15 := R15(R16)
219 [-]: TEST      R15 1        ; if R15 then PC := 273
220 [-]: JMP       273          ; PC := 273
221 [-]: GETGLOBAL R15 K15      ; R15 := _T
222 [-]: GETTABLE  R15 R15 K35  ; R15 := R15["INFESTED_GetHits"]
223 [-]: EQ        1 R15 K36    ; if R15 == nil then PC := 231
224 [-]: JMP       231          ; PC := 231
225 [-]: GETUPVAL  R15 U15      ; R15 := U15
226 [-]: GETGLOBAL R16 K15      ; R16 := _T
227 [-]: GETTABLE  R16 R16 K37  ; R16 := R16[0x39892beb]
228 [-]: GETUPVAL  R17 U13      ; R17 := U13
229 [-]: CALL      R16 2 0      ; R16,... := R16(R17)
230 [-]: CALL      R15 0 1      ; R15(R16,...)
231 [-]: GETGLOBAL R15 K15      ; R15 := _T
232 [-]: GETTABLE  R15 R15 K38  ; R15 := R15["INFESTED_GetStacks"]
233 [-]: EQ        1 R15 K36    ; if R15 == nil then PC := 264
234 [-]: JMP       264          ; PC := 264
235 [-]: GETGLOBAL R15 K15      ; R15 := _T
236 [-]: GETTABLE  R15 R15 K39  ; R15 := R15[0x85ed3714]
237 [-]: GETUPVAL  R16 U13      ; R16 := U13
238 [-]: CALL      R15 2 2      ; R15 := R15(R16)
239 [-]: GETUPVAL  R16 U16      ; R16 := U16
240 [-]: MOVE      R17 R15      ; R17 := R15
241 [-]: CALL      R16 2 1      ; R16(R17)
242 [-]: GETUPVAL  R16 U14      ; R16 := U14
243 [-]: EQ        1 R16 K10    ; if R16 == 3.000000 then PC := 253
244 [-]: JMP       253          ; PC := 253
245 [-]: GETGLOBAL R16 K15      ; R16 := _T
246 [-]: GETTABLE  R16 R16 K40  ; R16 := R16[0x71ddff47]
247 [-]: LOADK     R17 3        ; R17 := 3.000000
248 [-]: LT        1 K7 R15     ; if 0.000000 < R15 then PC := 251
249 [-]: JMP       251          ; PC := 251
250 [-]: LOADBOOL  R18 0 1      ; R18 := false; PC := 251
251 [-]: LOADBOOL  R18 1 0      ; R18 := true
252 [-]: CALL      R16 3 1      ; R16(R17,R18)
253 [-]: GETUPVAL  R16 U14      ; R16 := U14
254 [-]: EQ        1 R16 K41    ; if R16 == 4.000000 then PC := 264
255 [-]: JMP       264          ; PC := 264
256 [-]: GETGLOBAL R16 K15      ; R16 := _T
257 [-]: GETTABLE  R16 R16 K40  ; R16 := R16[0x71ddff47]
258 [-]: LOADK     R17 4        ; R17 := 4.000000
259 [-]: LT        1 K9 R15     ; if 2.000000 < R15 then PC := 262
260 [-]: JMP       262          ; PC := 262
261 [-]: LOADBOOL  R18 0 1      ; R18 := false; PC := 262
262 [-]: LOADBOOL  R18 1 0      ; R18 := true
263 [-]: CALL      R16 3 1      ; R16(R17,R18)
264 [-]: GETGLOBAL R16 K15      ; R16 := _T
265 [-]: GETTABLE  R16 R16 K42  ; R16 := R16["INFESTED_GetMaxStacks"]
266 [-]: EQ        1 R16 K36    ; if R16 == nil then PC := 273
267 [-]: JMP       273          ; PC := 273
268 [-]: GETGLOBAL R16 K15      ; R16 := _T
269 [-]: GETTABLE  R16 R16 K43  ; R16 := R16[0xfdd2de90]
270 [-]: GETUPVAL  R17 U13      ; R17 := U13
271 [-]: CALL      R16 2 2      ; R16 := R16(R17)
272 [-]: SETUPVAL  R16 U17      ; U82 := R17
273 [-]: GETUPVAL  R16 U18      ; R16 := U18
274 [-]: MOVE      R17 R0       ; R17 := R0
275 [-]: CALL      R16 2 1      ; R16(R17)
276 [-]: GETUPVAL  R16 U20      ; R16 := U20
277 [-]: GETTABLE  R16 R16 K44  ; R16 := R16[0x0cad99b9]
278 [-]: GETGLOBAL R17 K1       ; R17 := 0xae91e43b
279 [-]: LOADK     R18 K22      ; R18 := "AdaptationStack"
280 [-]: GETUPVAL  R19 U21      ; R19 := U21
281 [-]: GETUPVAL  R20 U19      ; R20 := U19
282 [-]: GETUPVAL  R21 U22      ; R21 := U22
283 [-]: GETUPVAL  R22 U11      ; R22 := U11
284 [-]: CALL      R16 7 2      ; R16 := R16(R17,R18,R19,R20,R21,R22)
285 [-]: SETUPVAL  R16 U19      ; U82 := R19
286 [-]: RETURN    R0 1         ; return 


; Function #11:
;
; Name:            
; Defined at line: 286
; #Upvalues:       2
; #Parameters:     1
; Is_vararg:       3
; Max Stack Size:  7

  1 [-]: GETUPVAL  R2 U0        ; R2 := U0
  2 [-]: TEST      R2 0         ; if not R2 then PC := 8
  3 [-]: JMP       8            ; PC := 8
  4 [-]: MOVE      R2 R0        ; R2 := R0
  5 [-]: VARARG    R3 0         ; R3 := ...
  6 [-]: CALL      R2 0 1       ; R2(R3,...)
  7 [-]: JMP       16           ; PC := 16
  8 [-]: GETGLOBAL R2 K0        ; R2 := 0x33bdd652
  9 [-]: GETTABLE  R2 R2 K1     ; R2 := R2[0x23d5322f]
 10 [-]: GETUPVAL  R3 U1        ; R3 := U1
 11 [-]: NEWTABLE  R4 1 0       ; R4 := {}
 12 [-]: MOVE      R5 R0        ; R5 := R0
 13 [-]: VARARG    R6 0         ; R6 := ...
 14 [-]: SETLIST   R4 0 1       ; R4[(1-1)*FPF+i] := R(4+i), 1 <= i <= 0
 15 [-]: CALL      R2 3 1       ; R2(R3,R4)
 16 [-]: RETURN    R0 1         ; return 


; Function #12:
;
; Name:            
; Defined at line: 294
; #Upvalues:       0
; #Parameters:     0
; Is_vararg:       0
; Max Stack Size:  5

  1 [-]: GETGLOBAL R0 K0        ; R0 := _T
  2 [-]: SETTABLE  R0 K1 K2     ; R0["INFESTED_ShowNotEnoughStacks"] := nil
  3 [-]: GETGLOBAL R0 K0        ; R0 := _T
  4 [-]: SETTABLE  R0 K3 K2     ; R0["INFESTED_ShowPassiveMessage"] := nil
  5 [-]: GETGLOBAL R0 K4        ; R0 := 0x7b998233
  6 [-]: GETGLOBAL R1 K0        ; R1 := _T
  7 [-]: GETTABLE  R1 R1 K5     ; R1 := R1["HUD_RemoveMotionClip"]
  8 [-]: CALL      R0 2 2       ; R0 := R0(R1)
  9 [-]: TEST      R0 1         ; if R0 then PC := 16
 10 [-]: JMP       16           ; PC := 16
 11 [-]: GETGLOBAL R0 K0        ; R0 := _T
 12 [-]: GETTABLE  R0 R0 K6     ; R0 := R0[0x564984b8]
 13 [-]: GETGLOBAL R1 K7        ; R1 := 0xae91e43b
 14 [-]: LOADK     R2 K8        ; R2 := "AdaptationStack"
 15 [-]: CALL      R0 3 1       ; R0(R1,R2)
 16 [-]: GETGLOBAL R0 K4        ; R0 := 0x7b998233
 17 [-]: GETGLOBAL R1 K0        ; R1 := _T
 18 [-]: GETTABLE  R1 R1 K9     ; R1 := R1["HUD_GetAnchorMgr"]
 19 [-]: CALL      R0 2 2       ; R0 := R0(R1)
 20 [-]: TEST      R0 1         ; if R0 then PC := 35
 21 [-]: JMP       35           ; PC := 35
 22 [-]: GETGLOBAL R0 K0        ; R0 := _T
 23 [-]: GETTABLE  R0 R0 K10    ; R0 := R0[0xf6b77431]
 24 [-]: CALL      R0 1 2       ; R0 := R0()
 25 [-]: EQ        1 R0 K2      ; if R0 == nil then PC := 35
 26 [-]: JMP       35           ; PC := 35
 27 [-]: SELF      R1 R0 K11    ; R2 := R0; R1 := R0[0x7f19c438]
 28 [-]: GETGLOBAL R3 K7        ; R3 := 0xae91e43b
 29 [-]: LOADK     R4 K8        ; R4 := "AdaptationStack"
 30 [-]: CALL      R1 4 1       ; R1(R2,R3,R4)
 31 [-]: SELF      R1 R0 K11    ; R2 := R0; R1 := R0[0x7f19c438]
 32 [-]: GETGLOBAL R3 K7        ; R3 := 0xae91e43b
 33 [-]: LOADK     R4 K12       ; R4 := "Message"
 34 [-]: CALL      R1 4 1       ; R1(R2,R3,R4)
 35 [-]: RETURN    R0 1         ; return 


; Function #13:
;
; Name:            
; Defined at line: 311
; #Upvalues:       1
; #Parameters:     0
; Is_vararg:       0
; Max Stack Size:  5

  1 [-]: GETUPVAL  R0 U0        ; R0 := U0
  2 [-]: LOADK     R1 0         ; R1 := 0.000000
  3 [-]: LOADBOOL  R2 0 0       ; R2 := false
  4 [-]: LOADNIL   R3 R3        ; R3 := nil
  5 [-]: LOADBOOL  R4 1 0       ; R4 := true
  6 [-]: CALL      R0 5 1       ; R0(R1,R2,R3,R4)
  7 [-]: RETURN    R0 1         ; return 


; Function #14:
;
; Name:            
; Defined at line: 324
; #Upvalues:       0
; #Parameters:     0
; Is_vararg:       0
; Max Stack Size:  11

  1 [-]: CLOSURE   R0 0         ; R0 := closure(Function #14.1)
  2 [-]: CLOSURE   R1 1         ; R1 := closure(Function #14.2)
  3 [-]: MOVE      R0 R0        ; R0 := R0
  4 [-]: GETGLOBAL R2 K0        ; R2 := 0x25312c9b
  5 [-]: GETGLOBAL R3 K1        ; R3 := 0xae91e43b
  6 [-]: LOADK     R4 K2        ; R4 := "AdaptationStack.Count"
  7 [-]: LOADK     R5 2         ; R5 := 2.000000
  8 [-]: NEWTABLE  R6 1 0       ; R6 := {}
  9 [-]: MOVE      R7 R1        ; R7 := R1
 10 [-]: SETLIST   R6 1 1       ; R6[(1-1)*FPF+i] := R(6+i), 1 <= i <= 1
 11 [-]: NEWTABLE  R7 1 0       ; R7 := {}
 12 [-]: LOADK     R8 1         ; R8 := 1.000000
 13 [-]: SETLIST   R7 1 1       ; R7[(1-1)*FPF+i] := R(7+i), 1 <= i <= 1
 14 [-]: LOADK     R8 1         ; R8 := 1.000000
 15 [-]: LOADK     R9 0         ; R9 := 0.000000
 16 [-]: CALL      R2 8 1       ; R2(R3,R4,R5,R6,R7,R8,R9)
 17 [-]: GETGLOBAL R2 K0        ; R2 := 0x25312c9b
 18 [-]: GETGLOBAL R3 K1        ; R3 := 0xae91e43b
 19 [-]: LOADK     R4 K4        ; R4 := "AdaptationStack"
 20 [-]: LOADK     R5 2         ; R5 := 2.000000
 21 [-]: NEWTABLE  R6 2 0       ; R6 := {}
 22 [-]: LOADK     R7 5         ; R7 := 5.000000
 23 [-]: LOADK     R8 6         ; R8 := 6.000000
 24 [-]: SETLIST   R6 2 1       ; R6[(1-1)*FPF+i] := R(6+i), 1 <= i <= 2
 25 [-]: NEWTABLE  R7 2 0       ; R7 := {}
 26 [-]: LOADK     R8 150       ; R8 := 150.000000
 27 [-]: LOADK     R9 150       ; R9 := 150.000000
 28 [-]: SETLIST   R7 2 1       ; R7[(1-1)*FPF+i] := R(7+i), 1 <= i <= 2
 29 [-]: LOADK     R8 K5        ; R8 := 0.200000
 30 [-]: LOADK     R9 0         ; R9 := 0.000000
 31 [-]: CLOSURE   R10 2        ; R10 := closure(Function #14.3)
 32 [-]: CALL      R2 9 1       ; R2(R3,R4,R5,R6,R7,R8,R9,R10)
 33 [-]: RETURN    R0 1         ; return 


; Function #14.1:
;
; Name:            
; Defined at line: 326
; #Upvalues:       0
; #Parameters:     1
; Is_vararg:       0
; Max Stack Size:  8

  1 [-]: GETGLOBAL R1 K0        ; R1 := 0x60130201
  2 [-]: LOADK     R2 255       ; R2 := 255.000000
  3 [-]: MUL       R3 R0 K1     ; R3 := R0 * 255.000000
  4 [-]: MUL       R4 R0 K1     ; R4 := R0 * 255.000000
  5 [-]: CALL      R1 4 2       ; R1 := R1(R2,R3,R4)
  6 [-]: GETGLOBAL R2 K2        ; R2 := 0xae91e43b
  7 [-]: SELF      R2 R2 K3     ; R3 := R2; R2 := R2[0x67bc869f]
  8 [-]: LOADK     R4 K4        ; R4 := "AdaptationStack.Count"
  9 [-]: LOADK     R5 36        ; R5 := 36.000000
 10 [-]: SELF      R6 R1 K5     ; R7 := R1; R6 := R1[0xa5d5c8f6]
 11 [-]: CALL      R6 2 0       ; R6,... := R6(R7)
 12 [-]: CALL      R2 0 1       ; R2(R3,...)
 13 [-]: RETURN    R0 1         ; return 


; Function #14.2:
;
; Name:            
; Defined at line: 332
; #Upvalues:       1
; #Parameters:     1
; Is_vararg:       0
; Max Stack Size:  5

  1 [-]: GETUPVAL  R1 U0        ; R1 := U0
  2 [-]: GETGLOBAL R2 K0        ; R2 := 0x5bced4c4
  3 [-]: GETTABLE  R2 R2 K1     ; R2 := R2[0xe4a5b3ca]
  4 [-]: GETGLOBAL R3 K0        ; R3 := 0x5bced4c4
  5 [-]: GETTABLE  R3 R3 K2     ; R3 := R3[0x3eda26fc]
  6 [-]: MUL       R4 R0 K3     ; R4 := R0 * 3.000000
  7 [-]: MUL       R4 R4 K4     ; R4 := R4 * 3.141593
  8 [-]: CALL      R3 2 0       ; R3,... := R3(R4)
  9 [-]: CALL      R2 0 2       ; R2 := R2(R3,...)
 10 [-]: SUB       R2 K5 R2     ; R2 := 1.000000 - R2
 11 [-]: CALL      R1 2 1       ; R1(R2)
 12 [-]: RETURN    R0 1         ; return 


; Function #14.3:
;
; Name:            
; Defined at line: 337
; #Upvalues:       0
; #Parameters:     0
; Is_vararg:       0
; Max Stack Size:  8

  1 [-]: GETGLOBAL R0 K0        ; R0 := 0x25312c9b
  2 [-]: GETGLOBAL R1 K1        ; R1 := 0xae91e43b
  3 [-]: LOADK     R2 K2        ; R2 := "AdaptationStack"
  4 [-]: LOADK     R3 2         ; R3 := 2.000000
  5 [-]: NEWTABLE  R4 2 0       ; R4 := {}
  6 [-]: LOADK     R5 5         ; R5 := 5.000000
  7 [-]: LOADK     R6 6         ; R6 := 6.000000
  8 [-]: SETLIST   R4 2 1       ; R4[(1-1)*FPF+i] := R(4+i), 1 <= i <= 2
  9 [-]: NEWTABLE  R5 2 0       ; R5 := {}
 10 [-]: LOADK     R6 100       ; R6 := 100.000000
 11 [-]: LOADK     R7 100       ; R7 := 100.000000
 12 [-]: SETLIST   R5 2 1       ; R5[(1-1)*FPF+i] := R(5+i), 1 <= i <= 2
 13 [-]: LOADK     R6 K4        ; R6 := 0.100000
 14 [-]: CALL      R0 7 1       ; R0(R1,R2,R3,R4,R5,R6)
 15 [-]: RETURN    R0 1         ; return 


; Function #15:
;
; Name:            
; Defined at line: 342
; #Upvalues:       0
; #Parameters:     1
; Is_vararg:       0
; Max Stack Size:  17

  1 [-]: GETGLOBAL R1 K0        ; R1 := 0x89326c93
  2 [-]: SELF      R1 R1 K1     ; R2 := R1; R1 := R1[0xfb64e76c]
  3 [-]: CALL      R1 2 2       ; R1 := R1(R2)
  4 [-]: GETGLOBAL R2 K2        ; R2 := 0x7b998233
  5 [-]: MOVE      R3 R1        ; R3 := R1
  6 [-]: CALL      R2 2 2       ; R2 := R2(R3)
  7 [-]: TEST      R2 0         ; if not R2 then PC := 10
  8 [-]: JMP       10           ; PC := 10
  9 [-]: RETURN    R0 1         ; return 
 10 [-]: SELF      R2 R1 K3     ; R3 := R1; R2 := R1[0xbb610e5b]
 11 [-]: CALL      R2 2 2       ; R2 := R2(R3)
 12 [-]: GETGLOBAL R3 K2        ; R3 := 0x7b998233
 13 [-]: MOVE      R4 R2        ; R4 := R2
 14 [-]: CALL      R3 2 2       ; R3 := R3(R4)
 15 [-]: TEST      R3 0         ; if not R3 then PC := 18
 16 [-]: JMP       18           ; PC := 18
 17 [-]: RETURN    R0 1         ; return 
 18 [-]: SELF      R3 R1 K4     ; R4 := R1; R3 := R1[0x0b4bcfb6]
 19 [-]: CALL      R3 2 2       ; R3 := R3(R4)
 20 [-]: GETGLOBAL R4 K2        ; R4 := 0x7b998233
 21 [-]: MOVE      R5 R3        ; R5 := R3
 22 [-]: CALL      R4 2 2       ; R4 := R4(R5)
 23 [-]: TEST      R4 0         ; if not R4 then PC := 26
 24 [-]: JMP       26           ; PC := 26
 25 [-]: RETURN    R0 1         ; return 
 26 [-]: GETGLOBAL R4 K5        ; R4 := 0xae91e43b
 27 [-]: SELF      R4 R4 K6     ; R5 := R4; R4 := R4[0x67bc869f]
 28 [-]: LOADK     R6 K7        ; R6 := "Message"
 29 [-]: LOADK     R7 5         ; R7 := 5.000000
 30 [-]: LOADK     R8 200       ; R8 := 200.000000
 31 [-]: CALL      R4 5 1       ; R4(R5,R6,R7,R8)
 32 [-]: GETGLOBAL R4 K5        ; R4 := 0xae91e43b
 33 [-]: SELF      R4 R4 K6     ; R5 := R4; R4 := R4[0x67bc869f]
 34 [-]: LOADK     R6 K7        ; R6 := "Message"
 35 [-]: LOADK     R7 6         ; R7 := 6.000000
 36 [-]: LOADK     R8 200       ; R8 := 200.000000
 37 [-]: CALL      R4 5 1       ; R4(R5,R6,R7,R8)
 38 [-]: LOADNIL   R4 R4        ; R4 := nil
 39 [-]: CLOSURE   R5 0         ; R5 := closure(Function #15.1)
 40 [-]: MOVE      R0 R0        ; R0 := R0
 41 [-]: MOVE      R0 R4        ; R0 := R4
 42 [-]: MOVE      R6 R5        ; R6 := R5
 43 [-]: LOADK     R7 1         ; R7 := 1.000000
 44 [-]: CALL      R6 2 1       ; R6(R7)
 45 [-]: SELF      R6 R3 K8     ; R7 := R3; R6 := R3[0xb1c85409]
 46 [-]: SELF      R8 R2 K9     ; R9 := R2; R8 := R2[0xebfba9e4]
 47 [-]: CALL      R8 2 2       ; R8 := R8(R9)
 48 [-]: LOADK     R9 -1        ; R9 := -1.000000
 49 [-]: LOADK     R10 50       ; R10 := 50.000000
 50 [-]: LOADK     R11 0        ; R11 := 0.000000
 51 [-]: CALL      R6 6 1       ; R6(R7,R8,R9,R10,R11)
 52 [-]: CLOSURE   R6 1         ; R6 := closure(Function #15.2)
 53 [-]: MOVE      R0 R3        ; R0 := R3
 54 [-]: GETGLOBAL R7 K10       ; R7 := 0x25312c9b
 55 [-]: GETGLOBAL R8 K5        ; R8 := 0xae91e43b
 56 [-]: LOADK     R9 K11       ; R9 := "Message.Count.Label"
 57 [-]: LOADK     R10 0        ; R10 := 0.000000
 58 [-]: NEWTABLE  R11 1 0      ; R11 := {}
 59 [-]: CLOSURE   R12 2        ; R12 := closure(Function #15.3)
 60 [-]: MOVE      R0 R5        ; R0 := R5
 61 [-]: SETLIST   R11 1 1      ; R11[(1-1)*FPF+i] := R(11+i), 1 <= i <= 1
 62 [-]: NEWTABLE  R12 1 0      ; R12 := {}
 63 [-]: LOADK     R13 1        ; R13 := 1.000000
 64 [-]: SETLIST   R12 1 1      ; R12[(1-1)*FPF+i] := R(12+i), 1 <= i <= 1
 65 [-]: MOVE      R13 R0       ; R13 := R0
 66 [-]: CALL      R7 7 1       ; R7(R8,R9,R10,R11,R12,R13)
 67 [-]: GETGLOBAL R7 K10       ; R7 := 0x25312c9b
 68 [-]: GETGLOBAL R8 K5        ; R8 := 0xae91e43b
 69 [-]: LOADK     R9 K7        ; R9 := "Message"
 70 [-]: LOADK     R10 2        ; R10 := 2.000000
 71 [-]: NEWTABLE  R11 4 0      ; R11 := {}
 72 [-]: LOADK     R12 K13      ; R12 := "_alpha"
 73 [-]: LOADK     R13 K14      ; R13 := "_xscale"
 74 [-]: LOADK     R14 K15      ; R14 := "_yscale"
 75 [-]: CLOSURE   R15 3        ; R15 := closure(Function #15.4)
 76 [-]: MOVE      R0 R6        ; R0 := R6
 77 [-]: SETLIST   R11 4 1      ; R11[(1-1)*FPF+i] := R(11+i), 1 <= i <= 4
 78 [-]: NEWTABLE  R12 4 0      ; R12 := {}
 79 [-]: LOADK     R13 100      ; R13 := 100.000000
 80 [-]: LOADK     R14 100      ; R14 := 100.000000
 81 [-]: LOADK     R15 100      ; R15 := 100.000000
 82 [-]: LOADK     R16 1        ; R16 := 1.000000
 83 [-]: SETLIST   R12 4 1      ; R12[(1-1)*FPF+i] := R(12+i), 1 <= i <= 4
 84 [-]: LOADK     R13 K16      ; R13 := 0.200000
 85 [-]: LOADK     R14 0        ; R14 := 0.000000
 86 [-]: CLOSURE   R15 4        ; R15 := closure(Function #15.5)
 87 [-]: MOVE      R0 R6        ; R0 := R6
 88 [-]: MOVE      R0 R0        ; R0 := R0
 89 [-]: CALL      R7 9 1       ; R7(R8,R9,R10,R11,R12,R13,R14,R15)
 90 [-]: RETURN    R0 1         ; return 


; Function #15.1:
;
; Name:            
; Defined at line: 362
; #Upvalues:       2
; #Parameters:     1
; Is_vararg:       0
; Max Stack Size:  11

  1 [-]: GETGLOBAL R1 K0        ; R1 := 0x5bced4c4
  2 [-]: GETTABLE  R1 R1 K1     ; R1 := R1[0x99675e23]
  3 [-]: GETUPVAL  R2 U0        ; R2 := U0
  4 [-]: MUL       R2 R2 R0     ; R2 := R2 * R0
  5 [-]: CALL      R1 2 2       ; R1 := R1(R2)
  6 [-]: GETUPVAL  R2 U1        ; R2 := U1
  7 [-]: EQ        1 R2 R1      ; if R2 == R1 then PC := 50
  8 [-]: JMP       50           ; PC := 50
  9 [-]: SETUPVAL  R1 U1        ; U82 := R1
 10 [-]: GETGLOBAL R2 K2        ; R2 := 0xae91e43b
 11 [-]: SELF      R2 R2 K3     ; R3 := R2; R2 := R2[0x67bc869f]
 12 [-]: LOADK     R4 K4        ; R4 := "Message.Count"
 13 [-]: LOADK     R5 10        ; R5 := 10.000000
 14 [-]: LOADK     R6 30        ; R6 := 30.000000
 15 [-]: CALL      R2 5 1       ; R2(R3,R4,R5,R6)
 16 [-]: GETGLOBAL R2 K2        ; R2 := 0xae91e43b
 17 [-]: SELF      R2 R2 K3     ; R3 := R2; R2 := R2[0x67bc869f]
 18 [-]: LOADK     R4 K4        ; R4 := "Message.Count"
 19 [-]: LOADK     R5 5         ; R5 := 5.000000
 20 [-]: LOADK     R6 200       ; R6 := 200.000000
 21 [-]: CALL      R2 5 1       ; R2(R3,R4,R5,R6)
 22 [-]: GETGLOBAL R2 K2        ; R2 := 0xae91e43b
 23 [-]: SELF      R2 R2 K3     ; R3 := R2; R2 := R2[0x67bc869f]
 24 [-]: LOADK     R4 K4        ; R4 := "Message.Count"
 25 [-]: LOADK     R5 6         ; R5 := 6.000000
 26 [-]: LOADK     R6 200       ; R6 := 200.000000
 27 [-]: CALL      R2 5 1       ; R2(R3,R4,R5,R6)
 28 [-]: GETGLOBAL R2 K2        ; R2 := 0xae91e43b
 29 [-]: SELF      R2 R2 K5     ; R3 := R2; R2 := R2[0x5f56eeab]
 30 [-]: LOADK     R4 K6        ; R4 := "Message.Count.Label"
 31 [-]: LOADK     R5 29        ; R5 := 29.000000
 32 [-]: MOVE      R6 R1        ; R6 := R1
 33 [-]: CALL      R2 5 1       ; R2(R3,R4,R5,R6)
 34 [-]: GETGLOBAL R2 K7        ; R2 := 0x25312c9b
 35 [-]: GETGLOBAL R3 K2        ; R3 := 0xae91e43b
 36 [-]: LOADK     R4 K4        ; R4 := "Message.Count"
 37 [-]: LOADK     R5 2         ; R5 := 2.000000
 38 [-]: NEWTABLE  R6 3 0       ; R6 := {}
 39 [-]: LOADK     R7 10        ; R7 := 10.000000
 40 [-]: LOADK     R8 5         ; R8 := 5.000000
 41 [-]: LOADK     R9 6         ; R9 := 6.000000
 42 [-]: SETLIST   R6 3 1       ; R6[(1-1)*FPF+i] := R(6+i), 1 <= i <= 3
 43 [-]: NEWTABLE  R7 3 0       ; R7 := {}
 44 [-]: LOADK     R8 100       ; R8 := 100.000000
 45 [-]: LOADK     R9 100       ; R9 := 100.000000
 46 [-]: LOADK     R10 100      ; R10 := 100.000000
 47 [-]: SETLIST   R7 3 1       ; R7[(1-1)*FPF+i] := R(7+i), 1 <= i <= 3
 48 [-]: LOADK     R8 0         ; R8 := 0.250000
 49 [-]: CALL      R2 7 1       ; R2(R3,R4,R5,R6,R7,R8)
 50 [-]: RETURN    R0 1         ; return 


; Function #15.2:
;
; Name:            
; Defined at line: 378
; #Upvalues:       1
; #Parameters:     1
; Is_vararg:       0
; Max Stack Size:  7

  1 [-]: GETGLOBAL R1 K0        ; R1 := 0x7b998233
  2 [-]: GETUPVAL  R2 U0        ; R2 := U0
  3 [-]: CALL      R1 2 2       ; R1 := R1(R2)
  4 [-]: TEST      R1 1         ; if R1 then PC := 14
  5 [-]: JMP       14           ; PC := 14
  6 [-]: GETUPVAL  R1 U0        ; R1 := U0
  7 [-]: SELF      R1 R1 K1     ; R2 := R1; R1 := R1[0x47de28d6]
  8 [-]: GETGLOBAL R3 K2        ; R3 := 0x9bafffe3
  9 [-]: LOADK     R4 K3        ; R4 := 0.550000
 10 [-]: LOADK     R5 1         ; R5 := 1.000000
 11 [-]: MOVE      R6 R0        ; R6 := R0
 12 [-]: CALL      R3 4 0       ; R3,... := R3(R4,R5,R6)
 13 [-]: CALL      R1 0 1       ; R1(R2,...)
 14 [-]: RETURN    R0 1         ; return 


; Function #15.3:
;
; Name:            
; Defined at line: 384
; #Upvalues:       1
; #Parameters:     1
; Is_vararg:       0
; Max Stack Size:  3

  1 [-]: GETUPVAL  R1 U0        ; R1 := U0
  2 [-]: SUB       R2 K0 R0     ; R2 := 1.000000 - R0
  3 [-]: CALL      R1 2 1       ; R1(R2)
  4 [-]: RETURN    R0 1         ; return 


; Function #15.4:
;
; Name:            
; Defined at line: 385
; #Upvalues:       1
; #Parameters:     1
; Is_vararg:       0
; Max Stack Size:  3

  1 [-]: GETUPVAL  R1 U0        ; R1 := U0
  2 [-]: SUB       R2 K0 R0     ; R2 := 1.000000 - R0
  3 [-]: CALL      R1 2 1       ; R1(R2)
  4 [-]: RETURN    R0 1         ; return 


; Function #15.5:
;
; Name:            
; Defined at line: 386
; #Upvalues:       2
; #Parameters:     0
; Is_vararg:       0
; Max Stack Size:  9

  1 [-]: GETGLOBAL R0 K0        ; R0 := 0x25312c9b
  2 [-]: GETGLOBAL R1 K1        ; R1 := 0xae91e43b
  3 [-]: LOADK     R2 K2        ; R2 := "Message"
  4 [-]: LOADK     R3 0         ; R3 := 0.000000
  5 [-]: NEWTABLE  R4 1 0       ; R4 := {}
  6 [-]: GETUPVAL  R5 U0        ; R5 := U0
  7 [-]: SETLIST   R4 1 1       ; R4[(1-1)*FPF+i] := R(4+i), 1 <= i <= 1
  8 [-]: NEWTABLE  R5 1 0       ; R5 := {}
  9 [-]: LOADK     R6 1         ; R6 := 1.000000
 10 [-]: SETLIST   R5 1 1       ; R5[(1-1)*FPF+i] := R(5+i), 1 <= i <= 1
 11 [-]: GETUPVAL  R6 U1        ; R6 := U1
 12 [-]: SUB       R6 R6 K4     ; R6 := R6 - 0.200000
 13 [-]: LOADK     R7 0         ; R7 := 0.000000
 14 [-]: CLOSURE   R8 0         ; R8 := closure(Function #15.5.1)
 15 [-]: CALL      R0 9 1       ; R0(R1,R2,R3,R4,R5,R6,R7,R8)
 16 [-]: RETURN    R0 1         ; return 


; Function #15.5.1:
;
; Name:            
; Defined at line: 388
; #Upvalues:       0
; #Parameters:     0
; Is_vararg:       0
; Max Stack Size:  9

  1 [-]: GETGLOBAL R0 K0        ; R0 := 0x25312c9b
  2 [-]: GETGLOBAL R1 K1        ; R1 := 0xae91e43b
  3 [-]: LOADK     R2 K2        ; R2 := "Message"
  4 [-]: LOADK     R3 2         ; R3 := 2.000000
  5 [-]: NEWTABLE  R4 3 0       ; R4 := {}
  6 [-]: LOADK     R5 10        ; R5 := 10.000000
  7 [-]: LOADK     R6 5         ; R6 := 5.000000
  8 [-]: LOADK     R7 6         ; R7 := 6.000000
  9 [-]: SETLIST   R4 3 1       ; R4[(1-1)*FPF+i] := R(4+i), 1 <= i <= 3
 10 [-]: NEWTABLE  R5 3 0       ; R5 := {}
 11 [-]: LOADK     R6 0         ; R6 := 0.000000
 12 [-]: LOADK     R7 50        ; R7 := 50.000000
 13 [-]: LOADK     R8 50        ; R8 := 50.000000
 14 [-]: SETLIST   R5 3 1       ; R5[(1-1)*FPF+i] := R(5+i), 1 <= i <= 3
 15 [-]: LOADK     R6 K4        ; R6 := 0.150000
 16 [-]: CALL      R0 7 1       ; R0(R1,R2,R3,R4,R5,R6)
 17 [-]: RETURN    R0 1         ; return 


; Function #16:
;
; Name:            
; Defined at line: 394
; #Upvalues:       25
; #Parameters:     0
; Is_vararg:       0
; Max Stack Size:  19

  1 [-]: GETGLOBAL R0 K0        ; R0 := 0x2d0fad09
  2 [-]: LOADK     R1 K1        ; R1 := "Lotus.Interface.Libs.TimerMgr"
  3 [-]: CALL      R0 2 2       ; R0 := R0(R1)
  4 [-]: GETTABLE  R1 R0 K2     ; R1 := R0[0xde474187]
  5 [-]: CALL      R1 1 2       ; R1 := R1()
  6 [-]: SETUPVAL  R1 U0        ; U82 := R0
  7 [-]: GETGLOBAL R1 K3        ; R1 := 0xae91e43b
  8 [-]: SELF      R1 R1 K4     ; R2 := R1; R1 := R1[0x67bc869f]
  9 [-]: LOADK     R3 K5        ; R3 := "_root"
 10 [-]: LOADK     R4 10        ; R4 := 10.000000
 11 [-]: LOADK     R5 0         ; R5 := 0.000000
 12 [-]: CALL      R1 5 1       ; R1(R2,R3,R4,R5)
 13 [-]: LOADK     R1 K6        ; R1 := "WeaponFrame."
 14 [-]: GETUPVAL  R2 U2        ; R2 := U2
 15 [-]: GETTABLE  R2 R2 K7     ; R2 := R2[0x06d055f9]
 16 [-]: GETGLOBAL R3 K8        ; R3 := 0x9ba7909f
 17 [-]: SELF      R3 R3 K9     ; R4 := R3; R3 := R3[0xbf9494fc]
 18 [-]: LOADK     R5 K10       ; R5 := "Game.EnableNewMelee"
 19 [-]: CALL      R3 3 2       ; R3 := R3(R4,R5)
 20 [-]: LOADK     R4 K11       ; R4 := "Rage"
 21 [-]: LOADK     R5 K12       ; R5 := "ComboTitle"
 22 [-]: CALL      R2 4 2       ; R2 := R2(R3,R4,R5)
 23 [-]: CONCAT    R1 R1 R2     ; R1 := R1 .. R2
 24 [-]: SETUPVAL  R1 U1        ; U82 := R1
 25 [-]: GETGLOBAL R1 K3        ; R1 := 0xae91e43b
 26 [-]: SELF      R1 R1 K13    ; R2 := R1; R1 := R1[0x91a24e4b]
 27 [-]: LOADK     R3 K14       ; R3 := "AdaptationStack"
 28 [-]: LOADK     R4 1         ; R4 := 1.000000
 29 [-]: CALL      R1 4 2       ; R1 := R1(R2,R3,R4)
 30 [-]: SETUPVAL  R1 U3        ; U82 := R3
 31 [-]: GETGLOBAL R1 K15       ; R1 := _T
 32 [-]: GETTABLE  R1 R1 K16    ; R1 := R1[0xf6b77431]
 33 [-]: CALL      R1 1 2       ; R1 := R1()
 34 [-]: SELF      R2 R1 K17    ; R3 := R1; R2 := R1[0x20ff29f7]
 35 [-]: GETGLOBAL R4 K3        ; R4 := 0xae91e43b
 36 [-]: LOADK     R5 K14       ; R5 := "AdaptationStack"
 37 [-]: NEWTABLE  R6 2 0       ; R6 := {}
 38 [-]: GETTABLE  R7 R1 K18    ; R7 := R1["ANCHOR_V_BOTTOM"]
 39 [-]: GETTABLE  R8 R1 K19    ; R8 := R1["ANCHOR_H_RIGHT"]
 40 [-]: SETLIST   R6 2 1       ; R6[(1-1)*FPF+i] := R(6+i), 1 <= i <= 2
 41 [-]: CALL      R2 5 1       ; R2(R3,R4,R5,R6)
 42 [-]: SELF      R2 R1 K17    ; R3 := R1; R2 := R1[0x20ff29f7]
 43 [-]: GETGLOBAL R4 K3        ; R4 := 0xae91e43b
 44 [-]: LOADK     R5 K20       ; R5 := "Message"
 45 [-]: NEWTABLE  R6 2 0       ; R6 := {}
 46 [-]: GETTABLE  R7 R1 K21    ; R7 := R1["ANCHOR_V_TOP"]
 47 [-]: GETTABLE  R8 R1 K22    ; R8 := R1["ANCHOR_H_CENTRE"]
 48 [-]: SETLIST   R6 2 1       ; R6[(1-1)*FPF+i] := R(6+i), 1 <= i <= 2
 49 [-]: CALL      R2 5 1       ; R2(R3,R4,R5,R6)
 50 [-]: SELF      R2 R1 K23    ; R3 := R1; R2 := R1[0xfaa69527]
 51 [-]: GETGLOBAL R4 K3        ; R4 := 0xae91e43b
 52 [-]: SELF      R4 R4 K24    ; R5 := R4; R4 := R4[0x6b837788]
 53 [-]: CALL      R4 2 2       ; R4 := R4(R5)
 54 [-]: GETGLOBAL R5 K3        ; R5 := 0xae91e43b
 55 [-]: SELF      R5 R5 K25    ; R6 := R5; R5 := R5[0xaf9fda9f]
 56 [-]: CALL      R5 2 2       ; R5 := R5(R6)
 57 [-]: LOADBOOL  R6 1 0       ; R6 := true
 58 [-]: GETTABLE  R7 R1 K26    ; R7 := R1["mHudScalePadding"]
 59 [-]: CALL      R2 6 1       ; R2(R3,R4,R5,R6,R7)
 60 [-]: GETGLOBAL R2 K15       ; R2 := _T
 61 [-]: GETTABLE  R2 R2 K27    ; R2 := R2[0x6b23d28b]
 62 [-]: GETGLOBAL R3 K3        ; R3 := 0xae91e43b
 63 [-]: LOADK     R4 K14       ; R4 := "AdaptationStack"
 64 [-]: CALL      R2 3 1       ; R2(R3,R4)
 65 [-]: GETGLOBAL R2 K15       ; R2 := _T
 66 [-]: CLOSURE   R3 0         ; R3 := closure(Function #16.1)
 67 [-]: GETUPVAL  R0 U4        ; R0 := U4
 68 [-]: GETUPVAL  R0 U5        ; R0 := U5
 69 [-]: SETTABLE  R2 K28 R3    ; R2["INFESTED_ShowNotEnoughStacks"] := R3
 70 [-]: GETGLOBAL R2 K15       ; R2 := _T
 71 [-]: CLOSURE   R3 1         ; R3 := closure(Function #16.2)
 72 [-]: GETUPVAL  R0 U4        ; R0 := U4
 73 [-]: GETUPVAL  R0 U6        ; R0 := U6
 74 [-]: SETTABLE  R2 K29 R3    ; R2["INFESTED_ShowPassiveMessage"] := R3
 75 [-]: GETUPVAL  R2 U7        ; R2 := U7
 76 [-]: CALL      R2 1 1       ; R2()
 77 [-]: GETGLOBAL R2 K3        ; R2 := 0xae91e43b
 78 [-]: SELF      R2 R2 K30    ; R3 := R2; R2 := R2[0xaade900e]
 79 [-]: LOADK     R4 K31       ; R4 := "AdaptationStack.Count"
 80 [-]: LOADK     R5 44        ; R5 := 44.000000
 81 [-]: LOADBOOL  R6 0 0       ; R6 := false
 82 [-]: CALL      R2 5 1       ; R2(R3,R4,R5,R6)
 83 [-]: GETGLOBAL R2 K3        ; R2 := 0xae91e43b
 84 [-]: SELF      R2 R2 K30    ; R3 := R2; R2 := R2[0xaade900e]
 85 [-]: LOADK     R4 K31       ; R4 := "AdaptationStack.Count"
 86 [-]: LOADK     R5 75        ; R5 := 75.000000
 87 [-]: LOADBOOL  R6 1 0       ; R6 := true
 88 [-]: CALL      R2 5 1       ; R2(R3,R4,R5,R6)
 89 [-]: GETGLOBAL R2 K3        ; R2 := 0xae91e43b
 90 [-]: SELF      R2 R2 K4     ; R3 := R2; R2 := R2[0x67bc869f]
 91 [-]: LOADK     R4 K20       ; R4 := "Message"
 92 [-]: LOADK     R5 10        ; R5 := 10.000000
 93 [-]: LOADK     R6 0         ; R6 := 0.000000
 94 [-]: CALL      R2 5 1       ; R2(R3,R4,R5,R6)
 95 [-]: GETGLOBAL R2 K3        ; R2 := 0xae91e43b
 96 [-]: SELF      R2 R2 K32    ; R3 := R2; R2 := R2[0x1cb415c1]
 97 [-]: LOADK     R4 K33       ; R4 := "Message.Icon"
 98 [-]: GETGLOBAL R5 K34       ; R5 := 0x9a7150ba
 99 [-]: CALL      R2 4 1       ; R2(R3,R4,R5)
100 [-]: GETGLOBAL R2 K3        ; R2 := 0xae91e43b
101 [-]: SELF      R2 R2 K4     ; R3 := R2; R2 := R2[0x67bc869f]
102 [-]: LOADK     R4 K33       ; R4 := "Message.Icon"
103 [-]: LOADK     R5 10        ; R5 := 10.000000
104 [-]: LOADK     R6 60        ; R6 := 60.000000
105 [-]: CALL      R2 5 1       ; R2(R3,R4,R5,R6)
106 [-]: GETGLOBAL R2 K3        ; R2 := 0xae91e43b
107 [-]: SELF      R2 R2 K4     ; R3 := R2; R2 := R2[0x67bc869f]
108 [-]: LOADK     R4 K33       ; R4 := "Message.Icon"
109 [-]: LOADK     R5 9         ; R5 := 9.000000
110 [-]: LOADK     R6 K35       ; R6 := 12528988.000000
111 [-]: CALL      R2 5 1       ; R2(R3,R4,R5,R6)
112 [-]: GETGLOBAL R2 K3        ; R2 := 0xae91e43b
113 [-]: SELF      R2 R2 K36    ; R3 := R2; R2 := R2[0x20b98db3]
114 [-]: LOADK     R4 K37       ; R4 := "Message.Title.text"
115 [-]: LOADK     R5 K38       ; R5 := "/Lotus/Language/Suits/InfestPassiveAbilityName"
116 [-]: CALL      R2 4 1       ; R2(R3,R4,R5)
117 [-]: LOADK     R2 0         ; R2 := 0.000000
118 [-]: LOADK     R3 0         ; R3 := 0.000000
119 [-]: GETGLOBAL R4 K39       ; R4 := 0x89326c93
120 [-]: SELF      R4 R4 K40    ; R5 := R4; R4 := R4[0x78298275]
121 [-]: CALL      R4 2 2       ; R4 := R4(R5)
122 [-]: GETGLOBAL R5 K41       ; R5 := 0x7b998233
123 [-]: MOVE      R6 R4        ; R6 := R4
124 [-]: CALL      R5 2 2       ; R5 := R5(R6)
125 [-]: TEST      R5 1         ; if R5 then PC := 179
126 [-]: JMP       179          ; PC := 179
127 [-]: SELF      R5 R4 K42    ; R6 := R4; R5 := R4[0xde321e6f]
128 [-]: CALL      R5 2 2       ; R5 := R5(R6)
129 [-]: SELF      R5 R5 K43    ; R6 := R5; R5 := R5[0xf7d48ee0]
130 [-]: CALL      R5 2 2       ; R5 := R5(R6)
131 [-]: SETUPVAL  R5 U8        ; U82 := R8
132 [-]: GETGLOBAL R5 K15       ; R5 := _T
133 [-]: GETTABLE  R5 R5 K44    ; R5 := R5["INFESTED_GetHits"]
134 [-]: EQ        1 R5 K45     ; if R5 == nil then PC := 141
135 [-]: JMP       141          ; PC := 141
136 [-]: GETGLOBAL R5 K15       ; R5 := _T
137 [-]: GETTABLE  R5 R5 K46    ; R5 := R5[0x39892beb]
138 [-]: GETUPVAL  R6 U8        ; R6 := U8
139 [-]: CALL      R5 2 2       ; R5 := R5(R6)
140 [-]: MOVE      R2 R5        ; R2 := R5
141 [-]: GETGLOBAL R5 K15       ; R5 := _T
142 [-]: GETTABLE  R5 R5 K47    ; R5 := R5["INFESTED_GetStacks"]
143 [-]: EQ        1 R5 K45     ; if R5 == nil then PC := 150
144 [-]: JMP       150          ; PC := 150
145 [-]: GETGLOBAL R5 K15       ; R5 := _T
146 [-]: GETTABLE  R5 R5 K48    ; R5 := R5[0x85ed3714]
147 [-]: GETUPVAL  R6 U8        ; R6 := U8
148 [-]: CALL      R5 2 2       ; R5 := R5(R6)
149 [-]: MOVE      R3 R5        ; R3 := R5
150 [-]: GETGLOBAL R5 K15       ; R5 := _T
151 [-]: GETTABLE  R5 R5 K49    ; R5 := R5["INFESTED_GetMaxStacks"]
152 [-]: EQ        1 R5 K45     ; if R5 == nil then PC := 159
153 [-]: JMP       159          ; PC := 159
154 [-]: GETGLOBAL R5 K15       ; R5 := _T
155 [-]: GETTABLE  R5 R5 K50    ; R5 := R5[0xfdd2de90]
156 [-]: GETUPVAL  R6 U8        ; R6 := U8
157 [-]: CALL      R5 2 2       ; R5 := R5(R6)
158 [-]: SETUPVAL  R5 U9        ; U82 := R9
159 [-]: GETGLOBAL R5 K41       ; R5 := 0x7b998233
160 [-]: GETUPVAL  R6 U8        ; R6 := U8
161 [-]: CALL      R5 2 2       ; R5 := R5(R6)
162 [-]: TEST      R5 1         ; if R5 then PC := 179
163 [-]: JMP       179          ; PC := 179
164 [-]: GETUPVAL  R5 U8        ; R5 := U8
165 [-]: SELF      R5 R5 K51    ; R6 := R5; R5 := R5[0x3c88e434]
166 [-]: CALL      R5 2 2       ; R5 := R5(R6)
167 [-]: GETGLOBAL R6 K52       ; R6 := 0xc8802016
168 [-]: MOVE      R7 R5        ; R7 := R5
169 [-]: CALL      R6 2 4       ; R6,R7,R8 := R6(R7)
170 [-]: JMP       177          ; PC := 177
171 [-]: SELF      R11 R10 K53  ; R12 := R10; R11 := R10[0xbffa8848]
172 [-]: CALL      R11 2 2      ; R11 := R11(R12)
173 [-]: TEST      R11 0        ; if not R11 then PC := 177
174 [-]: JMP       177          ; PC := 177
175 [-]: SETUPVAL  R9 U10       ; U82 := R10
176 [-]: JMP       179          ; PC := 179
177 [-]: TFORLOOP  R6 2         ; R9,R10 :=  R6(R7,R8); if R9 ~= nil then begin PC = 171; R8 := R9 end
178 [-]: JMP       171          ; PC := 171
179 [-]: GETUPVAL  R11 U11      ; R11 := U11
180 [-]: MOVE      R12 R2       ; R12 := R2
181 [-]: CALL      R11 2 1      ; R11(R12)
182 [-]: GETUPVAL  R11 U12      ; R11 := U12
183 [-]: MOVE      R12 R3       ; R12 := R3
184 [-]: CALL      R11 2 1      ; R11(R12)
185 [-]: GETUPVAL  R11 U14      ; R11 := U14
186 [-]: GETUPVAL  R12 U15      ; R12 := U15
187 [-]: MUL       R11 R11 R12  ; R11 := R11 * R12
188 [-]: GETUPVAL  R12 U16      ; R12 := U16
189 [-]: ADD       R11 R11 R12  ; R11 := R11 + R12
190 [-]: SETUPVAL  R11 U13      ; U82 := R13
191 [-]: GETUPVAL  R11 U17      ; R11 := U17
192 [-]: CALL      R11 1 1      ; R11()
193 [-]: GETUPVAL  R11 U18      ; R11 := U18
194 [-]: MOVE      R12 R3       ; R12 := R3
195 [-]: CALL      R11 2 1      ; R11(R12)
196 [-]: GETUPVAL  R11 U19      ; R11 := U19
197 [-]: GETUPVAL  R12 U2       ; R12 := U2
198 [-]: GETTABLE  R12 R12 K7   ; R12 := R12[0x06d055f9]
199 [-]: GETUPVAL  R13 U9       ; R13 := U9
200 [-]: EQ        1 R3 R13     ; if R3 == R13 then PC := 203
201 [-]: JMP       203          ; PC := 203
202 [-]: LOADBOOL  R13 0 1      ; R13 := false; PC := 203
203 [-]: LOADBOOL  R13 1 0      ; R13 := true
204 [-]: LOADK     R14 10       ; R14 := 10.000000
205 [-]: MOVE      R15 R2       ; R15 := R2
206 [-]: CALL      R12 4 2      ; R12 := R12(R13,R14,R15)
207 [-]: LOADBOOL  R13 1 0      ; R13 := true
208 [-]: LOADNIL   R14 R14      ; R14 := nil
209 [-]: LOADBOOL  R15 1 0      ; R15 := true
210 [-]: CALL      R11 5 1      ; R11(R12,R13,R14,R15)
211 [-]: SELF      R11 R1 K54   ; R12 := R1; R11 := R1[0x9d1db3eb]
212 [-]: LOADK     R13 K14      ; R13 := "AdaptationStack"
213 [-]: CALL      R11 3 2      ; R11 := R11(R12,R13)
214 [-]: GETTABLE  R11 R11 K55  ; R11 := R11["y"]
215 [-]: SETUPVAL  R11 U20      ; U82 := R20
216 [-]: GETGLOBAL R11 K39      ; R11 := 0x89326c93
217 [-]: SELF      R11 R11 K40  ; R12 := R11; R11 := R11[0x78298275]
218 [-]: CALL      R11 2 2      ; R11 := R11(R12)
219 [-]: SETUPVAL  R11 U21      ; U82 := R21
220 [-]: GETGLOBAL R11 K41      ; R11 := 0x7b998233
221 [-]: GETUPVAL  R12 U21      ; R12 := U21
222 [-]: CALL      R11 2 2      ; R11 := R11(R12)
223 [-]: TEST      R11 1        ; if R11 then PC := 269
224 [-]: JMP       269          ; PC := 269
225 [-]: GETUPVAL  R11 U21      ; R11 := U21
226 [-]: SELF      R11 R11 K56  ; R12 := R11; R11 := R11[0x5e651723]
227 [-]: CALL      R11 2 2      ; R11 := R11(R12)
228 [-]: GETGLOBAL R12 K41      ; R12 := 0x7b998233
229 [-]: MOVE      R13 R11      ; R13 := R11
230 [-]: CALL      R12 2 2      ; R12 := R12(R13)
231 [-]: TEST      R12 1        ; if R12 then PC := 236
232 [-]: JMP       236          ; PC := 236
233 [-]: SELF      R12 R11 K57  ; R13 := R11; R12 := R11[0x0803eee1]
234 [-]: CALL      R12 2 2      ; R12 := R12(R13)
235 [-]: SETUPVAL  R12 U22      ; U82 := R22
236 [-]: GETUPVAL  R12 U21      ; R12 := U21
237 [-]: SELF      R12 R12 K42  ; R13 := R12; R12 := R12[0xde321e6f]
238 [-]: CALL      R12 2 2      ; R12 := R12(R13)
239 [-]: SETUPVAL  R12 U23      ; U82 := R23
240 [-]: GETGLOBAL R12 K41      ; R12 := 0x7b998233
241 [-]: GETUPVAL  R13 U23      ; R13 := U23
242 [-]: CALL      R12 2 2      ; R12 := R12(R13)
243 [-]: TEST      R12 1        ; if R12 then PC := 269
244 [-]: JMP       269          ; PC := 269
245 [-]: GETUPVAL  R12 U23      ; R12 := U23
246 [-]: SELF      R12 R12 K43  ; R13 := R12; R12 := R12[0xf7d48ee0]
247 [-]: CALL      R12 2 2      ; R12 := R12(R13)
248 [-]: GETGLOBAL R13 K41      ; R13 := 0x7b998233
249 [-]: MOVE      R14 R12      ; R14 := R12
250 [-]: CALL      R13 2 2      ; R13 := R13(R14)
251 [-]: TEST      R13 1        ; if R13 then PC := 269
252 [-]: JMP       269          ; PC := 269
253 [-]: SELF      R13 R12 K58  ; R14 := R12; R13 := R12[0x689412a5]
254 [-]: GETGLOBAL R15 K59      ; R15 := 0x7ed0a956
255 [-]: LOADK     R16 K60      ; R16 := "/Lotus/Powersuits/PowersuitAbilities/InfestRuptureAbility"
256 [-]: CALL      R15 2 0      ; R15,... := R15(R16)
257 [-]: CALL      R13 0 2      ; R13 := R13(R14,...)
258 [-]: GETGLOBAL R14 K41      ; R14 := 0x7b998233
259 [-]: MOVE      R15 R13      ; R15 := R13
260 [-]: CALL      R14 2 2      ; R14 := R14(R15)
261 [-]: TEST      R14 0        ; if not R14 then PC := 269
262 [-]: JMP       269          ; PC := 269
263 [-]: GETGLOBAL R14 K3       ; R14 := 0xae91e43b
264 [-]: SELF      R14 R14 K4   ; R15 := R14; R14 := R14[0x67bc869f]
265 [-]: LOADK     R16 K14      ; R16 := "AdaptationStack"
266 [-]: LOADK     R17 10       ; R17 := 10.000000
267 [-]: LOADK     R18 0        ; R18 := 0.000000
268 [-]: CALL      R14 5 1      ; R14(R15,R16,R17,R18)
269 [-]: LOADBOOL  R14 1 0      ; R14 := true
270 [-]: SETUPVAL  R14 U24      ; U82 := R24
271 [-]: RETURN    R0 1         ; return 


; Function #16.1:
;
; Name:            
; Defined at line: 410
; #Upvalues:       2
; #Parameters:     0
; Is_vararg:       3
; Max Stack Size:  4

  1 [-]: GETUPVAL  R1 U0        ; R1 := U0
  2 [-]: GETUPVAL  R2 U1        ; R2 := U1
  3 [-]: VARARG    R3 0         ; R3 := ...
  4 [-]: CALL      R1 0 1       ; R1(R2,...)
  5 [-]: RETURN    R0 1         ; return 


; Function #16.2:
;
; Name:            
; Defined at line: 411
; #Upvalues:       2
; #Parameters:     0
; Is_vararg:       3
; Max Stack Size:  4

  1 [-]: GETUPVAL  R1 U0        ; R1 := U0
  2 [-]: GETUPVAL  R2 U1        ; R2 := U1
  3 [-]: VARARG    R3 0         ; R3 := ...
  4 [-]: CALL      R1 0 1       ; R1(R2,...)
  5 [-]: RETURN    R0 1         ; return 


; Function #17:
;
; Name:            
; Defined at line: 488
; #Upvalues:       1
; #Parameters:     1
; Is_vararg:       0
; Max Stack Size:  5

  1 [-]: GETUPVAL  R1 U0        ; R1 := U0
  2 [-]: GETTABLE  R1 R1 K0     ; R1 := R1[0xfa221145]
  3 [-]: GETGLOBAL R2 K1        ; R2 := 0xae91e43b
  4 [-]: GETGLOBAL R3 K2        ; R3 := 0x03f57322
  5 [-]: MOVE      R4 R0        ; R4 := R0
  6 [-]: CALL      R3 2 0       ; R3,... := R3(R4)
  7 [-]: CALL      R1 0 1       ; R1(R2,...)
  8 [-]: RETURN    R0 1         ; return 


