; Name:            
; Defined at line: 1
; #Upvalues:       0
; #Parameters:     0
; Is_vararg:       1
; Max Stack Size:  34

       1 [-]: GETIMPORT R0 1; var0 = 0x2D0FAD09
       2 [-]: LOADK R1 K2  ; var1 = "Lotus.Interface.UIUtilities"
       3 [-]: CALL R0 2 2  ; var0 = var0(var1)
       4 [-]: GETIMPORT R1 1; var1 = 0x2D0FAD09
       5 [-]: LOADK R2 K3  ; var2 = "Lotus.Interface.LotusUtilities"
       6 [-]: CALL R1 2 2  ; var1 = var1(var2)
       7 [-]: GETIMPORT R2 1; var2 = 0x2D0FAD09
       8 [-]: LOADK R3 K4  ; var3 = "EE.Interface.Utilities"
       9 [-]: CALL R2 2 2  ; var2 = var2(var3)
      10 [-]: GETIMPORT R3 1; var3 = 0x2D0FAD09
      11 [-]: LOADK R4 K5  ; var4 = "Lotus.Powersuits.PowersuitAbilities.PVPLib"
      12 [-]: CALL R3 2 2  ; var3 = var3(var4)
      13 [-]: LOADB R4 0   ; var4 = false
      14 [-]: LOADNIL R5   ; var5 = nil
      15 [-]: NEWTABLE R6 0 0; var6 = {}
      16 [-]: LOADB R7 0   ; var7 = false
      17 [-]: LOADNIL R8   ; var8 = nil
      18 [-]: LOADNIL R9   ; var9 = nil
      19 [-]: LOADNIL R10  ; var10 = nil
      20 [-]: LOADN R11 0  ; var11 = 0
      21 [-]: LOADN R12 1  ; var12 = 1
      22 [-]: LOADN R13 0  ; var13 = 0
      23 [-]: LOADN R14 0  ; var14 = 0
      24 [-]: LOADNIL R15  ; var15 = nil
      25 [-]: LOADNIL R16  ; var16 = nil
      26 [-]: LOADNIL R17  ; var17 = nil
      27 [-]: LOADNIL R18  ; var18 = nil
      28 [-]: LOADB R19 0  ; var19 = false
      29 [-]: LOADB R20 0  ; var20 = false
      30 [-]: LOADN R21 0  ; var21 = 0
      31 [-]: LOADN R22 0  ; var22 = 0
      32 [-]: LOADB R23 0  ; var23 = false
      33 [-]: DUPCLOSURE R24 K6; 
      34 [-]: DUPCLOSURE R25 K7; 
      35 [-]: CAPTURE VAL R1; 
      36 [-]: NEWCLOSURE R26 P2; 
      37 [-]: CAPTURE REF R13; 
      38 [-]: CAPTURE REF R14; 
      39 [-]: DUPCLOSURE R27 K8; 
      40 [-]: CAPTURE VAL R26; 
      41 [-]: SETGLOBAL R27 K9; "onViewportSizeChanged" = var27
      42 [-]: NEWCLOSURE R27 P4; 
      43 [-]: CAPTURE REF R12; 
      44 [-]: CAPTURE REF R11; 
      45 [-]: NEWCLOSURE R28 P5; 
      46 [-]: CAPTURE REF R10; 
      47 [-]: CAPTURE REF R12; 
      48 [-]: CAPTURE VAL R2; 
      49 [-]: CAPTURE REF R13; 
      50 [-]: CAPTURE REF R14; 
      51 [-]: NEWCLOSURE R29 P6; 
      52 [-]: CAPTURE REF R10; 
      53 [-]: CAPTURE REF R11; 
      54 [-]: CAPTURE REF R12; 
      55 [-]: NEWCLOSURE R30 P7; 
      56 [-]: CAPTURE REF R17; 
      57 [-]: CAPTURE REF R18; 
      58 [-]: CAPTURE REF R19; 
      59 [-]: CAPTURE REF R21; 
      60 [-]: CAPTURE REF R20; 
      61 [-]: CAPTURE VAL R2; 
      62 [-]: NEWCLOSURE R31 P8; 
      63 [-]: CAPTURE REF R15; 
      64 [-]: NEWCLOSURE R32 P9; 
      65 [-]: CAPTURE REF R4; 
      66 [-]: CAPTURE REF R15; 
      67 [-]: CAPTURE REF R17; 
      68 [-]: CAPTURE REF R5; 
      69 [-]: CAPTURE REF R7; 
      70 [-]: CAPTURE REF R6; 
      71 [-]: CAPTURE REF R8; 
      72 [-]: CAPTURE REF R9; 
      73 [-]: CAPTURE REF R10; 
      74 [-]: CAPTURE REF R11; 
      75 [-]: CAPTURE REF R12; 
      76 [-]: CAPTURE VAL R30; 
      77 [-]: CAPTURE VAL R1; 
      78 [-]: CAPTURE REF R23; 
      79 [-]: CAPTURE VAL R0; 
      80 [-]: CAPTURE REF R22; 
      81 [-]: CAPTURE REF R16; 
      82 [-]: SETGLOBAL R32 K10; "Update" = var32
      83 [-]: NEWCLOSURE R32 P10; 
      84 [-]: CAPTURE REF R7; 
      85 [-]: CAPTURE REF R6; 
      86 [-]: NEWCLOSURE R33 P11; 
      87 [-]: CAPTURE REF R10; 
      88 [-]: CAPTURE REF R8; 
      89 [-]: SETGLOBAL R33 K11; "Shutdown" = var33
      90 [-]: NEWCLOSURE R33 P12; 
      91 [-]: CAPTURE VAL R26; 
      92 [-]: CAPTURE REF R8; 
      93 [-]: CAPTURE VAL R2; 
      94 [-]: CAPTURE VAL R3; 
      95 [-]: CAPTURE VAL R32; 
      96 [-]: CAPTURE VAL R28; 
      97 [-]: CAPTURE VAL R31; 
      98 [-]: CAPTURE REF R22; 
      99 [-]: CAPTURE REF R15; 
     100 [-]: CAPTURE REF R16; 
     101 [-]: CAPTURE REF R17; 
     102 [-]: CAPTURE REF R4; 
     103 [-]: SETGLOBAL R33 K12; "Initialize" = var33
     104 [-]: DUPCLOSURE R33 K13; 
     105 [-]: CAPTURE VAL R0; 
     106 [-]: SETGLOBAL R33 K14; "HandleHudScale" = var33
     107 [-]: CLOSEUPVALS R4; 
     108 [-]: RETURN R0 0  ; 


; Name:            
; Defined at line: 40
; #Upvalues:       0
; #Parameters:     0
; Is_vararg:       0
; Max Stack Size:  3

       0 [-]: GETIMPORT R0 1; var0 = 0xBE190284
       1 [-]: FASTCALL1 64 R0 L0; 
       2 [-]: MOVE R2 R0   ; var2 = var0
       3 [-]: GETIMPORT R1 3; var1 = 0x7B998233
       4 [-]: CALL R1 2 2  ; var1 = var1(var2)
L 0:   5 [-]: JUMPIF R1 L1 ; goto L1 if var1
       6 [-]: NAMECALL R1 R0 K4; var2 = var0; var1 = var0[0x486E5F11]
       7 [-]: CALL R1 2 2  ; var1 = var1(var2)
       8 [-]: JUMPIFNOT R1 L1; goto L1 if not var1
       9 [-]: LOADB R1 1   ; var1 = true
      10 [-]: RETURN R1 1  ; 
L 1:  11 [-]: LOADB R1 0   ; var1 = false
      12 [-]: RETURN R1 1  ; 


; Name:            
; Defined at line: 48
; #Upvalues:       1
; #Parameters:     0
; Is_vararg:       0
; Max Stack Size:  3

       0 [-]: GETUPVAL R1 0; var1 = upvalues[0]
       1 [-]: GETTABLEKS R0 R1 K0; var0 = var1[0xB73D420F]
       2 [-]: CALL R0 1 2  ; var0 = var0()
       3 [-]: GETUPVAL R2 0; var2 = upvalues[0]
       4 [-]: GETTABLEKS R1 R2 K1; var1 = var2["UI_MODE_IN_DOJO"]
       5 [-]: JUMPIFNOTEQ R0 R1 L0; goto L0 if var0 ~= var65542
       6 [-]: LOADB R0 1   ; var0 = true
       7 [-]: RETURN R0 1  ; 
L 0:   8 [-]: LOADB R0 0   ; var0 = false
       9 [-]: RETURN R0 1  ; 


; Name:            
; Defined at line: 55
; #Upvalues:       2
; #Parameters:     0
; Is_vararg:       0
; Max Stack Size:  4

       0 [-]: GETIMPORT R0 1; var0 = 0xAE91E43B
       1 [-]: NAMECALL R0 R0 K2; var1 = var0; var0 = var0[0x6B837788]
       2 [-]: CALL R0 2 2  ; var0 = var0(var1)
       3 [-]: GETIMPORT R1 1; var1 = 0xAE91E43B
       4 [-]: NAMECALL R1 R1 K3; var2 = var1; var1 = var1[0xAF9FDA9F]
       5 [-]: CALL R1 2 2  ; var1 = var1(var2)
       6 [-]: GETIMPORT R2 1; var2 = 0xAE91E43B
       7 [-]: NAMECALL R2 R2 K4; var3 = var2; var2 = var2[0x091C120E]
       8 [-]: CALL R2 2 2  ; var2 = var2(var3)
       9 [-]: JUMPIFLT R0 R2 L0; goto L0 if var0 < var66081
      10 [-]: GETIMPORT R2 1; var2 = 0xAE91E43B
      11 [-]: NAMECALL R2 R2 K5; var3 = var2; var2 = var2[0x2CC9D281]
      12 [-]: CALL R2 2 2  ; var2 = var2(var3)
      13 [-]: JUMPIFNOTLT R1 R2 L1; goto L1 if var1 >= var524833
L 0:  14 [-]: GETIMPORT R2 8; var2 = 0x34291F5C[0x056BFE8B]
      15 [-]: CALL R2 1 2  ; var2 = var2()
      16 [-]: JUMPIF R2 L1 ; goto L1 if var2
      17 [-]: GETIMPORT R2 1; var2 = 0xAE91E43B
      18 [-]: NAMECALL R2 R2 K4; var3 = var2; var2 = var2[0x091C120E]
      19 [-]: CALL R2 2 2  ; var2 = var2(var3)
      20 [-]: MOVE R0 R2   ; var0 = var2
      21 [-]: GETIMPORT R2 1; var2 = 0xAE91E43B
      22 [-]: NAMECALL R2 R2 K5; var3 = var2; var2 = var2[0x2CC9D281]
      23 [-]: CALL R2 2 2  ; var2 = var2(var3)
      24 [-]: MOVE R1 R2   ; var1 = var2
L 1:  25 [-]: MULK R2 R0 K9; var2 = var0 * 0.5
      26 [-]: SETUPVAL R2 0; upvalues[2] = var0
      27 [-]: MULK R2 R1 K9; var2 = var1 * 0.5
      28 [-]: SETUPVAL R2 1; upvalues[2] = var1
      29 [-]: RETURN R0 0  ; 


; Name:            
; Defined at line: 67
; #Upvalues:       1
; #Parameters:     4
; Is_vararg:       0
; Max Stack Size:  5

       0 [-]: GETUPVAL R4 0; var4 = upvalues[0]
       1 [-]: CALL R4 1 1  ; var4()
       2 [-]: RETURN R0 0  ; 


; Name:            
; Defined at line: 71
; #Upvalues:       2
; #Parameters:     0
; Is_vararg:       0
; Max Stack Size:  8

       0 [-]: LOADK R1 K0  ; var1 = 0.019999999552965164
       1 [-]: GETUPVAL R2 0; var2 = upvalues[0]
       2 [-]: MUL R0 R1 R2 ; var0 = var1 * var2
       3 [-]: GETUPVAL R3 1; var3 = upvalues[1]
       4 [-]: MULK R2 R3 K2; var2 = var3 * 3.1415927410125732
       5 [-]: MULK R1 R2 K1; var1 = var2 * 2
       6 [-]: FASTCALL1 24 R1 L0; 
       7 [-]: MOVE R4 R1   ; var4 = var1
       8 [-]: GETIMPORT R3 5; var3 = 0x5BCED4C4[0x3EDA26FC]
       9 [-]: CALL R3 2 2  ; var3 = var3(var4)
L 0:  10 [-]: MUL R2 R3 R0 ; var2 = var3 * var0
      11 [-]: FASTCALL1 9 R1 L1; 
      12 [-]: MOVE R5 R1   ; var5 = var1
      13 [-]: GETIMPORT R4 7; var4 = 0x5BCED4C4[0x00FA6BF1]
      14 [-]: CALL R4 2 2  ; var4 = var4(var5)
L 1:  15 [-]: MUL R3 R4 R0 ; var3 = var4 * var0
      16 [-]: GETIMPORT R4 9; var4 = 0xA421AF95
      17 [-]: MOVE R5 R2   ; var5 = var2
      18 [-]: MOVE R6 R3   ; var6 = var3
      19 [-]: LOADN R7 0   ; var7 = 0
      20 [-]: CALL R4 4 2  ; var4 = var4(var5, var6, var7)
      21 [-]: RETURN R4 1  ; 


; Name:            
; Defined at line: 79
; #Upvalues:       5
; #Parameters:     1
; Is_vararg:       0
; Max Stack Size:  10

       0 [-]: GETIMPORT R1 1; var1 = 0x3D106989
       1 [-]: LOADK R3 K2  ; var3 = "ShowControlParticles("
       2 [-]: FASTCALL1 63 R0 L0; 
       3 [-]: MOVE R7 R0   ; var7 = var0
       4 [-]: GETIMPORT R6 4; var6 = 0x64FB1586
       5 [-]: CALL R6 2 2  ; var6 = var6(var7)
L 0:   6 [-]: MOVE R4 R6   ; var4 = var6
       7 [-]: LOADK R5 K5  ; var5 = ")"
       8 [-]: CONCAT R2 R3 R5; var2 = var3 .. var5
       9 [-]: CALL R1 2 1  ; var1(var2)
      10 [-]: JUMPIFNOT R0 L2; goto L2 if not var0
      11 [-]: GETUPVAL R2 0; var2 = upvalues[0]
      12 [-]: FASTCALL1 64 R2 L1; 
      13 [-]: GETIMPORT R1 7; var1 = 0x7B998233
      14 [-]: CALL R1 2 2  ; var1 = var1(var2)
L 1:  15 [-]: JUMPIFNOT R1 L2; goto L2 if not var1
      16 [-]: LOADN R1 0   ; var1 = 0
      17 [-]: SETUPVAL R1 1; upvalues[1] = var1
      18 [-]: GETUPVAL R2 2; var2 = upvalues[2]
      19 [-]: GETTABLEKS R1 R2 K8; var1 = var2[0x5A22D251]
      20 [-]: GETIMPORT R2 10; var2 = 0xAE91E43B
      21 [-]: GETIMPORT R3 12; var3 = 0x3253E435
      22 [-]: GETUPVAL R4 3; var4 = upvalues[3]
      23 [-]: GETUPVAL R5 4; var5 = upvalues[4]
      24 [-]: CALL R1 5 2  ; var1 = var1(var2, var3, var4, var5)
      25 [-]: SETUPVAL R1 0; upvalues[1] = var0
      26 [-]: GETIMPORT R1 14; var1 = 0x25312C9B
      27 [-]: GETIMPORT R2 10; var2 = 0xAE91E43B
      28 [-]: LOADK R3 K15 ; var3 = "_root"
      29 [-]: LOADN R4 0   ; var4 = 0
      30 [-]: NEWTABLE R5 0 1; var5 = {}
      31 [-]: NEWCLOSURE R6 P0; 
      32 [-]: CAPTURE UPVAL U1; 
      33 [-]: SETLIST R5 R6 1 [1]; var5[1] = var6; var5[2] = var7; 
      34 [-]: NEWTABLE R6 0 1; var6 = {}
      35 [-]: LOADN R7 1   ; var7 = 1
      36 [-]: SETLIST R6 R7 1 [1]; var6[1] = var7; var6[2] = var8; 
      37 [-]: LOADK R7 K16 ; var7 = 0.5
      38 [-]: LOADK R8 K17 ; var8 = 0.25
      39 [-]: CALL R1 8 1  ; var1(var2, var3, var4, var5, var6, var7, var8)
      40 [-]: RETURN R0 0  ; 
L 2:  41 [-]: JUMPIF R0 L4 ; goto L4 if var0
      42 [-]: GETUPVAL R2 0; var2 = upvalues[0]
      43 [-]: FASTCALL1 64 R2 L3; 
      44 [-]: GETIMPORT R1 7; var1 = 0x7B998233
      45 [-]: CALL R1 2 2  ; var1 = var1(var2)
L 3:  46 [-]: JUMPIF R1 L4 ; goto L4 if var1
      47 [-]: GETUPVAL R1 0; var1 = upvalues[0]
      48 [-]: LOADK R3 K16 ; var3 = 0.5
      49 [-]: NAMECALL R1 R1 K18; var2 = var1; var1 = var1[0x1BFF969C]
      50 [-]: CALL R1 3 1  ; var1(var2, var3)
      51 [-]: GETIMPORT R1 14; var1 = 0x25312C9B
      52 [-]: GETIMPORT R2 10; var2 = 0xAE91E43B
      53 [-]: LOADK R3 K15 ; var3 = "_root"
      54 [-]: LOADN R4 0   ; var4 = 0
      55 [-]: NEWTABLE R5 0 1; var5 = {}
      56 [-]: NEWCLOSURE R6 P1; 
      57 [-]: CAPTURE UPVAL U1; 
      58 [-]: SETLIST R5 R6 1 [1]; var5[1] = var6; var5[2] = var7; 
      59 [-]: NEWTABLE R6 0 1; var6 = {}
      60 [-]: LOADN R7 1   ; var7 = 1
      61 [-]: SETLIST R6 R7 1 [1]; var6[1] = var7; var6[2] = var8; 
      62 [-]: LOADN R7 1   ; var7 = 1
      63 [-]: LOADN R8 0   ; var8 = 0
      64 [-]: NEWCLOSURE R9 P2; 
      65 [-]: CAPTURE UPVAL U0; 
      66 [-]: CAPTURE UPVAL U2; 
      67 [-]: CAPTURE UPVAL U3; 
      68 [-]: CAPTURE UPVAL U4; 
      69 [-]: CALL R1 9 1  ; var1(var2, var3, var4, var5, var6, var7, var8, var9)
L 4:  70 [-]: RETURN R0 0  ; 


; Name:            
; Defined at line: 95
; #Upvalues:       3
; #Parameters:     0
; Is_vararg:       0
; Max Stack Size:  12

       0 [-]: GETUPVAL R1 0; var1 = upvalues[0]
       1 [-]: FASTCALL1 64 R1 L0; 
       2 [-]: GETIMPORT R0 1; var0 = 0x7B998233
       3 [-]: CALL R0 2 2  ; var0 = var0(var1)
L 0:   4 [-]: JUMPIF R0 L4 ; goto L4 if var0
       5 [-]: GETIMPORT R0 3; var0 = 0x89326C93
       6 [-]: NAMECALL R0 R0 K4; var1 = var0; var0 = var0[0xB4364067]
       7 [-]: CALL R0 2 2  ; var0 = var0(var1)
       8 [-]: FASTCALL1 64 R0 L1; 
       9 [-]: MOVE R2 R0   ; var2 = var0
      10 [-]: GETIMPORT R1 1; var1 = 0x7B998233
      11 [-]: CALL R1 2 2  ; var1 = var1(var2)
L 1:  12 [-]: JUMPIF R1 L4 ; goto L4 if var1
      13 [-]: GETUPVAL R2 1; var2 = upvalues[1]
      14 [-]: LOADK R4 K5  ; var4 = 1.75
      15 [-]: GETIMPORT R5 7; var5 = 0x67652851
      16 [-]: CALL R5 1 2  ; var5 = var5()
      17 [-]: MUL R3 R4 R5 ; var3 = var4 * var5
      18 [-]: ADD R1 R2 R3 ; var1 = var2 + var3
      19 [-]: SETUPVAL R1 1; upvalues[1] = var1
      20 [-]: GETUPVAL R1 0; var1 = upvalues[0]
      21 [-]: LOADK R5 K8  ; var5 = 0.019999999552965164
      22 [-]: GETUPVAL R6 2; var6 = upvalues[2]
      23 [-]: MUL R4 R5 R6 ; var4 = var5 * var6
      24 [-]: GETUPVAL R7 1; var7 = upvalues[1]
      25 [-]: MULK R6 R7 K10; var6 = var7 * 3.1415927410125732
      26 [-]: MULK R5 R6 K9; var5 = var6 * 2
      27 [-]: FASTCALL1 24 R5 L2; 
      28 [-]: MOVE R8 R5   ; var8 = var5
      29 [-]: GETIMPORT R7 13; var7 = 0x5BCED4C4[0x3EDA26FC]
      30 [-]: CALL R7 2 2  ; var7 = var7(var8)
L 2:  31 [-]: MUL R6 R7 R4 ; var6 = var7 * var4
      32 [-]: FASTCALL1 9 R5 L3; 
      33 [-]: MOVE R9 R5   ; var9 = var5
      34 [-]: GETIMPORT R8 15; var8 = 0x5BCED4C4[0x00FA6BF1]
      35 [-]: CALL R8 2 2  ; var8 = var8(var9)
L 3:  36 [-]: MUL R7 R8 R4 ; var7 = var8 * var4
      37 [-]: GETIMPORT R8 17; var8 = 0xA421AF95
      38 [-]: MOVE R9 R6   ; var9 = var6
      39 [-]: MOVE R10 R7  ; var10 = var7
      40 [-]: LOADN R11 0  ; var11 = 0
      41 [-]: CALL R8 4 2  ; var8 = var8(var9, var10, var11)
      42 [-]: MOVE R3 R8   ; var3 = var8
      43 [-]: NAMECALL R1 R1 K18; var2 = var1; var1 = var1[0x119B677C]
      44 [-]: CALL R1 3 1  ; var1(var2, var3)
L 4:  45 [-]: RETURN R0 0  ; 


; Name:            
; Defined at line: 106
; #Upvalues:       6
; #Parameters:     0
; Is_vararg:       0
; Max Stack Size:  14

       0 [-]: GETUPVAL R0 0; var0 = upvalues[0]
       1 [-]: LOADN R2 0   ; var2 = 0
       2 [-]: NAMECALL R0 R0 K0; var1 = var0; var0 = var0[0x881B6B90]
       3 [-]: CALL R0 3 2  ; var0 = var0(var1, var2)
       4 [-]: GETUPVAL R1 1; var1 = upvalues[1]
       5 [-]: JUMPIFEQ R1 R0 L2; goto L2 if var1 == var65545
       6 [-]: SETUPVAL R0 1; upvalues[0] = var1
       7 [-]: GETUPVAL R3 1; var3 = upvalues[1]
       8 [-]: FASTCALL1 64 R3 L0; 
       9 [-]: GETIMPORT R2 2; var2 = 0x7B998233
      10 [-]: CALL R2 2 2  ; var2 = var2(var3)
L 0:  11 [-]: NOT R1 R2    ; var1 = not var2
      12 [-]: JUMPIFNOT R1 L1; goto L1 if not var1
      13 [-]: GETUPVAL R1 1; var1 = upvalues[1]
      14 [-]: GETIMPORT R3 4; var3 = 0x49493CF5
      15 [-]: NAMECALL R1 R1 K5; var2 = var1; var1 = var1[0xF2DEAF69]
      16 [-]: CALL R1 3 2  ; var1 = var1(var2, var3)
L 1:  17 [-]: SETUPVAL R1 2; upvalues[1] = var2
L 2:  18 [-]: GETUPVAL R1 0; var1 = upvalues[0]
      19 [-]: NAMECALL R1 R1 K6; var2 = var1; var1 = var1[0xF7D48EE0]
      20 [-]: CALL R1 2 2  ; var1 = var1(var2)
      21 [-]: FASTCALL1 64 R1 L3; 
      22 [-]: MOVE R3 R1   ; var3 = var1
      23 [-]: GETIMPORT R2 2; var2 = 0x7B998233
      24 [-]: CALL R2 2 2  ; var2 = var2(var3)
L 3:  25 [-]: JUMPIF R2 L6 ; goto L6 if var2
      26 [-]: GETIMPORT R4 8; var4 = 0x7ED0A956
      27 [-]: LOADK R5 K9  ; var5 = "/Lotus/Powersuits/PowersuitAbilities/RangerBowAbility"
      28 [-]: CALL R4 2 0  ; var4, ... = var4(var5)
      29 [-]: NAMECALL R2 R1 K10; var3 = var1; var2 = var1[0xA2356091]
      30 [-]: CALL R2 0 2  ; var2 = var2(var3, ...)
      31 [-]: GETUPVAL R3 2; var3 = upvalues[2]
      32 [-]: JUMPIFNOT R3 L5; goto L5 if not var3
      33 [-]: LOADB R3 0   ; var3 = false
      34 [-]: LOADN R4 4   ; var4 = 4
      35 [-]: JUMPIFNOTLT R2 R4 L5; goto L5 if var2 >= var66310
      36 [-]: LOADB R3 1   ; var3 = true
      37 [-]: MOVE R6 R2   ; var6 = var2
      38 [-]: NAMECALL R4 R1 K11; var5 = var1; var4 = var1[0x5063EDC3]
      39 [-]: CALL R4 3 2  ; var4 = var4(var5, var6)
      40 [-]: JUMPXEQKN R4 K12 L5; 
      41 [-]: MOVE R6 R2   ; var6 = var2
      42 [-]: NAMECALL R4 R1 K13; var5 = var1; var4 = var1[0x75ECAF0B]
      43 [-]: CALL R4 3 2  ; var4 = var4(var5, var6)
      44 [-]: LOADN R5 1   ; var5 = 1
      45 [-]: JUMPIFNOTEQ R4 R5 L4; goto L4 if var4 ~= var16777990
      46 [-]: LOADB R3 0 +1; var3 = false
L 4:  47 [-]: LOADB R3 1   ; var3 = true
L 5:  48 [-]: SETUPVAL R3 2; upvalues[3] = var2
L 6:  49 [-]: LOADB R2 0   ; var2 = false
      50 [-]: GETUPVAL R3 3; var3 = upvalues[3]
      51 [-]: GETUPVAL R4 2; var4 = upvalues[2]
      52 [-]: JUMPIFNOT R4 L7; goto L7 if not var4
      53 [-]: GETUPVAL R4 1; var4 = upvalues[1]
      54 [-]: NAMECALL R4 R4 K14; var5 = var4; var4 = var4[0x1403242C]
      55 [-]: CALL R4 2 2  ; var4 = var4(var5)
      56 [-]: JUMPXEQKN R4 K12 L7 NOT; 
      57 [-]: GETUPVAL R4 1; var4 = upvalues[1]
      58 [-]: NAMECALL R4 R4 K15; var5 = var4; var4 = var4[0x6BB20D05]
      59 [-]: CALL R4 2 2  ; var4 = var4(var5)
      60 [-]: MOVE R2 R4   ; var2 = var4
      61 [-]: JUMPIFNOT R2 L7; goto L7 if not var2
      62 [-]: GETUPVAL R4 1; var4 = upvalues[1]
      63 [-]: NAMECALL R4 R4 K16; var5 = var4; var4 = var4[0x46AFA846]
      64 [-]: CALL R4 2 2  ; var4 = var4(var5)
      65 [-]: MOVE R3 R4   ; var3 = var4
L 7:  66 [-]: GETUPVAL R4 4; var4 = upvalues[4]
      67 [-]: JUMPIFEQ R4 R2 L8; goto L8 if var4 == var262665
      68 [-]: SETUPVAL R2 4; upvalues[2] = var4
      69 [-]: GETIMPORT R4 18; var4 = 0x25312C9B
      70 [-]: GETIMPORT R5 20; var5 = 0xAE91E43B
      71 [-]: LOADK R6 K21 ; var6 = "ArrowDirection"
      72 [-]: LOADN R7 0   ; var7 = 0
      73 [-]: NEWTABLE R8 0 1; var8 = {}
      74 [-]: LOADN R9 10  ; var9 = 10
      75 [-]: SETLIST R8 R9 1 [1]; var8[1] = var9; var8[2] = var10; 
      76 [-]: NEWTABLE R9 0 1; var9 = {}
      77 [-]: GETUPVAL R11 5; var11 = upvalues[5]
      78 [-]: GETTABLEKS R10 R11 K22; var10 = var11[0x06D055F9]
      79 [-]: GETUPVAL R11 4; var11 = upvalues[4]
      80 [-]: LOADN R12 30 ; var12 = 30
      81 [-]: LOADN R13 0  ; var13 = 0
      82 [-]: CALL R10 4 0 ; var10, ... = var10(var11, var12, var13)
      83 [-]: SETLIST R9 R10 -1 [1]; 
      84 [-]: LOADK R10 K23; var10 = 0.15000000596046448
      85 [-]: CALL R4 7 1  ; var4(var5, var6, var7, var8, var9, var10)
L 8:  86 [-]: GETUPVAL R4 3; var4 = upvalues[3]
      87 [-]: JUMPIFEQ R4 R3 L9; goto L9 if var4 == var197385
      88 [-]: SETUPVAL R3 3; upvalues[3] = var3
      89 [-]: LOADN R5 -90 ; var5 = -90
      90 [-]: LOADN R7 90  ; var7 = 90
      91 [-]: GETUPVAL R8 3; var8 = upvalues[3]
      92 [-]: MUL R6 R7 R8 ; var6 = var7 * var8
      93 [-]: ADD R4 R5 R6 ; var4 = var5 + var6
      94 [-]: GETIMPORT R5 20; var5 = 0xAE91E43B
      95 [-]: LOADK R7 K21 ; var7 = "ArrowDirection"
      96 [-]: LOADN R8 14  ; var8 = 14
      97 [-]: MOVE R9 R4   ; var9 = var4
      98 [-]: NAMECALL R5 R5 K24; var6 = var5; var5 = var5[0x67BC869F]
      99 [-]: CALL R5 5 1  ; var5(var6, var7, var8, var9)
L 9: 100 [-]: RETURN R0 0  ; 


; Name:            
; Defined at line: 142
; #Upvalues:       1
; #Parameters:     0
; Is_vararg:       0
; Max Stack Size:  6

       0 [-]: GETIMPORT R0 1; var0 = 0x89326C93
       1 [-]: NAMECALL R0 R0 K2; var1 = var0; var0 = var0[0x78298275]
       2 [-]: CALL R0 2 2  ; var0 = var0(var1)
       3 [-]: SETUPVAL R0 0; upvalues[0] = var0
       4 [-]: GETUPVAL R1 0; var1 = upvalues[0]
       5 [-]: FASTCALL1 64 R1 L0; 
       6 [-]: GETIMPORT R0 4; var0 = 0x7B998233
       7 [-]: CALL R0 2 2  ; var0 = var0(var1)
L 0:   8 [-]: JUMPIFNOT R0 L1; goto L1 if not var0
       9 [-]: RETURN R0 0  ; 
L 1:  10 [-]: GETUPVAL R0 0; var0 = upvalues[0]
      11 [-]: NAMECALL R0 R0 K5; var1 = var0; var0 = var0[0x5E651723]
      12 [-]: CALL R0 2 2  ; var0 = var0(var1)
      13 [-]: NAMECALL R0 R0 K6; var1 = var0; var0 = var0[0x8B72B36E]
      14 [-]: CALL R0 2 2  ; var0 = var0(var1)
      15 [-]: LOADN R1 0   ; var1 = 0
      16 [-]: GETIMPORT R3 10; var3 = _T["rangerQuiver"]["domeTimerExpiry"]
      17 [-]: FASTCALL1 64 R3 L2; 
      18 [-]: GETIMPORT R2 4; var2 = 0x7B998233
      19 [-]: CALL R2 2 2  ; var2 = var2(var3)
L 2:  20 [-]: JUMPIF R2 L4 ; goto L4 if var2
      21 [-]: GETIMPORT R4 10; var4 = _T["rangerQuiver"]["domeTimerExpiry"]
      22 [-]: GETTABLE R3 R4 R0; var3 = var4[var0]
      23 [-]: FASTCALL1 64 R3 L3; 
      24 [-]: GETIMPORT R2 4; var2 = 0x7B998233
      25 [-]: CALL R2 2 2  ; var2 = var2(var3)
L 3:  26 [-]: JUMPIF R2 L4 ; goto L4 if var2
      27 [-]: GETIMPORT R3 10; var3 = _T["rangerQuiver"]["domeTimerExpiry"]
      28 [-]: GETTABLE R2 R3 R0; var2 = var3[var0]
      29 [-]: GETIMPORT R3 12; var3 = 0x55156FF7
      30 [-]: CALL R3 1 2  ; var3 = var3()
      31 [-]: SUB R1 R2 R3 ; var1 = var2 - var3
L 4:  32 [-]: LOADN R2 0   ; var2 = 0
      33 [-]: JUMPIFNOTLT R2 R1 L5; goto L5 if var2 >= var918049
      34 [-]: GETIMPORT R2 14; var2 = _T["RANGER_SetArrowTimer"]
      35 [-]: LOADN R3 1   ; var3 = 1
      36 [-]: MOVE R4 R1   ; var4 = var1
      37 [-]: CALL R2 3 1  ; var2(var3, var4)
L 5:  38 [-]: LOADN R2 0   ; var2 = 0
      39 [-]: GETIMPORT R4 16; var4 = _T["rangerQuiver"]["sleepTimerExpiry"]
      40 [-]: FASTCALL1 64 R4 L6; 
      41 [-]: GETIMPORT R3 4; var3 = 0x7B998233
      42 [-]: CALL R3 2 2  ; var3 = var3(var4)
L 6:  43 [-]: JUMPIF R3 L8 ; goto L8 if var3
      44 [-]: GETIMPORT R5 16; var5 = _T["rangerQuiver"]["sleepTimerExpiry"]
      45 [-]: GETTABLE R4 R5 R0; var4 = var5[var0]
      46 [-]: FASTCALL1 64 R4 L7; 
      47 [-]: GETIMPORT R3 4; var3 = 0x7B998233
      48 [-]: CALL R3 2 2  ; var3 = var3(var4)
L 7:  49 [-]: JUMPIF R3 L8 ; goto L8 if var3
      50 [-]: GETIMPORT R4 16; var4 = _T["rangerQuiver"]["sleepTimerExpiry"]
      51 [-]: GETTABLE R3 R4 R0; var3 = var4[var0]
      52 [-]: GETIMPORT R4 12; var4 = 0x55156FF7
      53 [-]: CALL R4 1 2  ; var4 = var4()
      54 [-]: SUB R2 R3 R4 ; var2 = var3 - var4
L 8:  55 [-]: LOADN R3 0   ; var3 = 0
      56 [-]: JUMPIFNOTLT R3 R2 L9; goto L9 if var3 >= var918305
      57 [-]: GETIMPORT R3 14; var3 = _T["RANGER_SetArrowTimer"]
      58 [-]: LOADN R4 4   ; var4 = 4
      59 [-]: MOVE R5 R2   ; var5 = var2
      60 [-]: CALL R3 3 1  ; var3(var4, var5)
L 9:  61 [-]: RETURN R0 0  ; 


; Name:            
; Defined at line: 170
; #Upvalues:       17
; #Parameters:     0
; Is_vararg:       0
; Max Stack Size:  13

       0 [-]: GETIMPORT R1 1; var1 = 0xAE91E43B
       1 [-]: FASTCALL1 64 R1 L0; 
       2 [-]: GETIMPORT R0 3; var0 = 0x7B998233
       3 [-]: CALL R0 2 2  ; var0 = var0(var1)
L 0:   4 [-]: JUMPIF R0 L1 ; goto L1 if var0
       5 [-]: GETUPVAL R0 0; var0 = upvalues[0]
       6 [-]: JUMPIF R0 L2 ; goto L2 if var0
L 1:   7 [-]: RETURN R0 0  ; 
L 2:   8 [-]: GETUPVAL R1 1; var1 = upvalues[1]
       9 [-]: FASTCALL1 64 R1 L3; 
      10 [-]: GETIMPORT R0 3; var0 = 0x7B998233
      11 [-]: CALL R0 2 2  ; var0 = var0(var1)
L 3:  12 [-]: JUMPIFNOT R0 L6; goto L6 if not var0
      13 [-]: GETIMPORT R0 5; var0 = 0x89326C93
      14 [-]: NAMECALL R0 R0 K6; var1 = var0; var0 = var0[0x78298275]
      15 [-]: CALL R0 2 2  ; var0 = var0(var1)
      16 [-]: SETUPVAL R0 1; upvalues[0] = var1
      17 [-]: GETUPVAL R1 1; var1 = upvalues[1]
      18 [-]: FASTCALL1 64 R1 L4; 
      19 [-]: GETIMPORT R0 3; var0 = 0x7B998233
      20 [-]: CALL R0 2 2  ; var0 = var0(var1)
L 4:  21 [-]: JUMPIFNOT R0 L5; goto L5 if not var0
      22 [-]: RETURN R0 0  ; 
L 5:  23 [-]: GETUPVAL R0 1; var0 = upvalues[1]
      24 [-]: NAMECALL R0 R0 K7; var1 = var0; var0 = var0[0xDE321E6F]
      25 [-]: CALL R0 2 2  ; var0 = var0(var1)
      26 [-]: SETUPVAL R0 2; upvalues[0] = var2
L 6:  27 [-]: GETUPVAL R1 2; var1 = upvalues[2]
      28 [-]: FASTCALL1 64 R1 L7; 
      29 [-]: GETIMPORT R0 3; var0 = 0x7B998233
      30 [-]: CALL R0 2 2  ; var0 = var0(var1)
L 7:  31 [-]: JUMPIFNOT R0 L8; goto L8 if not var0
      32 [-]: LOADNIL R0   ; var0 = nil
      33 [-]: SETUPVAL R0 1; upvalues[0] = var1
      34 [-]: RETURN R0 0  ; 
L 8:  35 [-]: GETIMPORT R0 9; var0 = 0x67652851
      36 [-]: CALL R0 1 2  ; var0 = var0()
      37 [-]: GETIMPORT R1 1; var1 = 0xAE91E43B
      38 [-]: MOVE R3 R0   ; var3 = var0
      39 [-]: NAMECALL R1 R1 K10; var2 = var1; var1 = var1[0x8A8C8D5A]
      40 [-]: CALL R1 3 1  ; var1(var2, var3)
      41 [-]: GETUPVAL R2 3; var2 = upvalues[3]
      42 [-]: FASTCALL1 64 R2 L9; 
      43 [-]: GETIMPORT R1 3; var1 = 0x7B998233
      44 [-]: CALL R1 2 2  ; var1 = var1(var2)
L 9:  45 [-]: JUMPIFNOT R1 L10; goto L10 if not var1
      46 [-]: GETIMPORT R1 12; var1 = 0xBE190284
      47 [-]: NAMECALL R1 R1 K13; var2 = var1; var1 = var1[0x33307F92]
      48 [-]: CALL R1 2 2  ; var1 = var1(var2)
      49 [-]: SETUPVAL R1 3; upvalues[1] = var3
L10:  50 [-]: LOADB R1 1   ; var1 = true
      51 [-]: SETUPVAL R1 4; upvalues[1] = var4
      52 [-]: GETUPVAL R2 5; var2 = upvalues[5]
      53 [-]: LENGTH R1 R2 ; var1 = #var2
      54 [-]: LOADN R2 0   ; var2 = 0
      55 [-]: JUMPIFNOTLT R2 R1 L13; goto L13 if var2 >= var66352
      56 [-]: LOADN R3 1   ; var3 = 1
      57 [-]: GETUPVAL R4 5; var4 = upvalues[5]
      58 [-]: LENGTH R1 R4 ; var1 = #var4
      59 [-]: LOADN R2 1   ; var2 = 1
      60 [-]: FORNPREP R1 L12; nforprep start - [escape at L12] -- var1 = iterator
L11:  61 [-]: GETUPVAL R6 5; var6 = upvalues[5]
      62 [-]: GETTABLE R5 R6 R3; var5 = var6[var3]
      63 [-]: GETTABLEN R4 R5 1; var4 = var5[1]
      64 [-]: GETUPVAL R7 5; var7 = upvalues[5]
      65 [-]: GETTABLE R6 R7 R3; var6 = var7[var3]
      66 [-]: GETTABLEN R5 R6 2; var5 = var6[2]
      67 [-]: GETUPVAL R8 5; var8 = upvalues[5]
      68 [-]: GETTABLE R7 R8 R3; var7 = var8[var3]
      69 [-]: GETTABLEN R6 R7 3; var6 = var7[3]
      70 [-]: CALL R4 3 1  ; var4(var5, var6)
      71 [-]: FORNLOOP R1 L11; nforloop end - iterate + goto L11
L12:  72 [-]: NEWTABLE R1 0 0; var1 = {}
      73 [-]: SETUPVAL R1 5; upvalues[1] = var5
L13:  74 [-]: LOADB R1 0   ; var1 = false
      75 [-]: SETUPVAL R1 4; upvalues[1] = var4
      76 [-]: GETUPVAL R2 6; var2 = upvalues[6]
      77 [-]: FASTCALL1 64 R2 L14; 
      78 [-]: GETIMPORT R1 3; var1 = 0x7B998233
      79 [-]: CALL R1 2 2  ; var1 = var1(var2)
L14:  80 [-]: JUMPIF R1 L15; goto L15 if var1
      81 [-]: GETUPVAL R1 6; var1 = upvalues[6]
      82 [-]: MOVE R3 R0   ; var3 = var0
      83 [-]: NAMECALL R1 R1 K14; var2 = var1; var1 = var1[0xFAA69527]
      84 [-]: CALL R1 3 1  ; var1(var2, var3)
L15:  85 [-]: GETUPVAL R2 3; var2 = upvalues[3]
      86 [-]: FASTCALL1 64 R2 L16; 
      87 [-]: GETIMPORT R1 3; var1 = 0x7B998233
      88 [-]: CALL R1 2 2  ; var1 = var1(var2)
L16:  89 [-]: JUMPIF R1 L17; goto L17 if var1
      90 [-]: GETUPVAL R1 3; var1 = upvalues[3]
      91 [-]: LOADK R3 K15 ; var3 = "_root"
      92 [-]: LOADN R4 10  ; var4 = 10
      93 [-]: NAMECALL R1 R1 K16; var2 = var1; var1 = var1[0x91A24E4B]
      94 [-]: CALL R1 4 2  ; var1 = var1(var2, var3, var4)
      95 [-]: GETUPVAL R2 7; var2 = upvalues[7]
      96 [-]: JUMPIFEQ R2 R1 L17; goto L17 if var2 == var459017
      97 [-]: SETUPVAL R1 7; upvalues[1] = var7
      98 [-]: GETIMPORT R2 1; var2 = 0xAE91E43B
      99 [-]: LOADK R4 K15 ; var4 = "_root"
     100 [-]: LOADN R5 10  ; var5 = 10
     101 [-]: MOVE R6 R1   ; var6 = var1
     102 [-]: NAMECALL R2 R2 K17; var3 = var2; var2 = var2[0x67BC869F]
     103 [-]: CALL R2 5 1  ; var2(var3, var4, var5, var6)
L17: 104 [-]: GETUPVAL R2 8; var2 = upvalues[8]
     105 [-]: FASTCALL1 64 R2 L18; 
     106 [-]: GETIMPORT R1 3; var1 = 0x7B998233
     107 [-]: CALL R1 2 2  ; var1 = var1(var2)
L18: 108 [-]: JUMPIF R1 L22; goto L22 if var1
     109 [-]: GETIMPORT R1 5; var1 = 0x89326C93
     110 [-]: NAMECALL R1 R1 K18; var2 = var1; var1 = var1[0xB4364067]
     111 [-]: CALL R1 2 2  ; var1 = var1(var2)
     112 [-]: FASTCALL1 64 R1 L19; 
     113 [-]: MOVE R3 R1   ; var3 = var1
     114 [-]: GETIMPORT R2 3; var2 = 0x7B998233
     115 [-]: CALL R2 2 2  ; var2 = var2(var3)
L19: 116 [-]: JUMPIF R2 L22; goto L22 if var2
     117 [-]: GETUPVAL R3 9; var3 = upvalues[9]
     118 [-]: LOADK R5 K19 ; var5 = 1.75
     119 [-]: GETIMPORT R6 9; var6 = 0x67652851
     120 [-]: CALL R6 1 2  ; var6 = var6()
     121 [-]: MUL R4 R5 R6 ; var4 = var5 * var6
     122 [-]: ADD R2 R3 R4 ; var2 = var3 + var4
     123 [-]: SETUPVAL R2 9; upvalues[2] = var9
     124 [-]: GETUPVAL R2 8; var2 = upvalues[8]
     125 [-]: LOADK R6 K20 ; var6 = 0.019999999552965164
     126 [-]: GETUPVAL R7 10; var7 = upvalues[10]
     127 [-]: MUL R5 R6 R7 ; var5 = var6 * var7
     128 [-]: GETUPVAL R8 9; var8 = upvalues[9]
     129 [-]: MULK R7 R8 K22; var7 = var8 * 3.1415927410125732
     130 [-]: MULK R6 R7 K21; var6 = var7 * 2
     131 [-]: FASTCALL1 24 R6 L20; 
     132 [-]: MOVE R9 R6   ; var9 = var6
     133 [-]: GETIMPORT R8 25; var8 = 0x5BCED4C4[0x3EDA26FC]
     134 [-]: CALL R8 2 2  ; var8 = var8(var9)
L20: 135 [-]: MUL R7 R8 R5 ; var7 = var8 * var5
     136 [-]: FASTCALL1 9 R6 L21; 
     137 [-]: MOVE R10 R6  ; var10 = var6
     138 [-]: GETIMPORT R9 27; var9 = 0x5BCED4C4[0x00FA6BF1]
     139 [-]: CALL R9 2 2  ; var9 = var9(var10)
L21: 140 [-]: MUL R8 R9 R5 ; var8 = var9 * var5
     141 [-]: GETIMPORT R9 29; var9 = 0xA421AF95
     142 [-]: MOVE R10 R7  ; var10 = var7
     143 [-]: MOVE R11 R8  ; var11 = var8
     144 [-]: LOADN R12 0  ; var12 = 0
     145 [-]: CALL R9 4 2  ; var9 = var9(var10, var11, var12)
     146 [-]: MOVE R4 R9   ; var4 = var9
     147 [-]: NAMECALL R2 R2 K30; var3 = var2; var2 = var2[0x119B677C]
     148 [-]: CALL R2 3 1  ; var2(var3, var4)
L22: 149 [-]: GETUPVAL R1 11; var1 = upvalues[11]
     150 [-]: CALL R1 1 1  ; var1()
     151 [-]: GETUPVAL R3 12; var3 = upvalues[12]
     152 [-]: GETTABLEKS R2 R3 K31; var2 = var3[0xB73D420F]
     153 [-]: CALL R2 1 2  ; var2 = var2()
     154 [-]: GETUPVAL R4 12; var4 = upvalues[12]
     155 [-]: GETTABLEKS R3 R4 K32; var3 = var4["UI_MODE_IN_DOJO"]
     156 [-]: JUMPIFNOTEQ R2 R3 L23; goto L23 if var2 ~= var65798
     157 [-]: LOADB R1 1   ; var1 = true
     158 [-]: JUMP L24     ; goto L24
L23: 159 [-]: LOADB R1 0   ; var1 = false
L24: 160 [-]: JUMPIFNOT R1 L32; goto L32 if not var1
     161 [-]: GETIMPORT R2 12; var2 = 0xBE190284
     162 [-]: FASTCALL1 64 R2 L25; 
     163 [-]: MOVE R4 R2   ; var4 = var2
     164 [-]: GETIMPORT R3 3; var3 = 0x7B998233
     165 [-]: CALL R3 2 2  ; var3 = var3(var4)
L25: 166 [-]: JUMPIF R3 L26; goto L26 if var3
     167 [-]: NAMECALL R3 R2 K33; var4 = var2; var3 = var2[0x486E5F11]
     168 [-]: CALL R3 2 2  ; var3 = var3(var4)
     169 [-]: JUMPIFNOT R3 L26; goto L26 if not var3
     170 [-]: LOADB R1 1   ; var1 = true
     171 [-]: JUMP L27     ; goto L27
L26: 172 [-]: LOADB R1 0   ; var1 = false
L27: 173 [-]: JUMPIF R1 L28; goto L28 if var1
     174 [-]: GETIMPORT R1 1; var1 = 0xAE91E43B
     175 [-]: NAMECALL R1 R1 K34; var2 = var1; var1 = var1[0xD4CC05B4]
     176 [-]: CALL R1 2 2  ; var1 = var1(var2)
     177 [-]: JUMPIFNOT R1 L28; goto L28 if not var1
     178 [-]: GETIMPORT R1 1; var1 = 0xAE91E43B
     179 [-]: LOADB R3 0   ; var3 = false
     180 [-]: NAMECALL R1 R1 K35; var2 = var1; var1 = var1[0x368AD758]
     181 [-]: CALL R1 3 1  ; var1(var2, var3)
     182 [-]: JUMP L32     ; goto L32
L28: 183 [-]: GETIMPORT R2 12; var2 = 0xBE190284
     184 [-]: FASTCALL1 64 R2 L29; 
     185 [-]: MOVE R4 R2   ; var4 = var2
     186 [-]: GETIMPORT R3 3; var3 = 0x7B998233
     187 [-]: CALL R3 2 2  ; var3 = var3(var4)
L29: 188 [-]: JUMPIF R3 L30; goto L30 if var3
     189 [-]: NAMECALL R3 R2 K33; var4 = var2; var3 = var2[0x486E5F11]
     190 [-]: CALL R3 2 2  ; var3 = var3(var4)
     191 [-]: JUMPIFNOT R3 L30; goto L30 if not var3
     192 [-]: LOADB R1 1   ; var1 = true
     193 [-]: JUMP L31     ; goto L31
L30: 194 [-]: LOADB R1 0   ; var1 = false
L31: 195 [-]: JUMPIFNOT R1 L32; goto L32 if not var1
     196 [-]: GETIMPORT R1 1; var1 = 0xAE91E43B
     197 [-]: NAMECALL R1 R1 K34; var2 = var1; var1 = var1[0xD4CC05B4]
     198 [-]: CALL R1 2 2  ; var1 = var1(var2)
     199 [-]: JUMPIF R1 L32; goto L32 if var1
     200 [-]: GETIMPORT R1 1; var1 = 0xAE91E43B
     201 [-]: LOADB R3 1   ; var3 = true
     202 [-]: NAMECALL R1 R1 K35; var2 = var1; var1 = var1[0x368AD758]
     203 [-]: CALL R1 3 1  ; var1(var2, var3)
L32: 204 [-]: GETUPVAL R2 14; var2 = upvalues[14]
     205 [-]: GETTABLEKS R1 R2 K36; var1 = var2[0x0CAD99B9]
     206 [-]: GETIMPORT R2 1; var2 = 0xAE91E43B
     207 [-]: LOADK R3 K37 ; var3 = "Quiver"
     208 [-]: GETUPVAL R4 15; var4 = upvalues[15]
     209 [-]: GETUPVAL R5 13; var5 = upvalues[13]
     210 [-]: GETUPVAL R6 16; var6 = upvalues[16]
     211 [-]: GETUPVAL R7 1; var7 = upvalues[1]
     212 [-]: CALL R1 7 2  ; var1 = var1(var2, var3, var4, var5, var6, var7)
     213 [-]: SETUPVAL R1 13; upvalues[1] = var13
     214 [-]: RETURN R0 0  ; 


; Name:            
; Defined at line: 232
; #Upvalues:       2
; #Parameters:     1
; Is_vararg:       1
; Max Stack Size:  6

       1 [-]: GETUPVAL R1 0; var1 = upvalues[0]
       2 [-]: JUMPIFNOT R1 L0; goto L0 if not var1
       3 [-]: MOVE R1 R0   ; var1 = var0
       4 [-]: GETVARARGS R2 -1; var2 = ...
       5 [-]: CALL R1 0 1  ; var1(var2, ...)
       6 [-]: RETURN R0 0  ; 
L 0:   7 [-]: GETUPVAL R2 1; var2 = upvalues[1]
       8 [-]: NEWTABLE R3 0 1; var3 = {}
       9 [-]: MOVE R4 R0   ; var4 = var0
      10 [-]: GETVARARGS R5 -1; var5 = ...
      11 [-]: SETLIST R3 R4 -1 [1]; 
      12 [-]: FASTCALL2 52 R2 R3 L1; 
      13 [-]: GETIMPORT R1 2; var1 = 0x33BDD652[0x23D5322F]
      14 [-]: CALL R1 3 1  ; var1(var2, var3)
L 1:  15 [-]: RETURN R0 0  ; 


; Name:            
; Defined at line: 240
; #Upvalues:       2
; #Parameters:     0
; Is_vararg:       0
; Max Stack Size:  5

       0 [-]: GETIMPORT R0 1; var0 = _T
       1 [-]: LOADNIL R1   ; var1 = nil
       2 [-]: SETTABLEKS R1 R0 K2; var1["RANGER_SetArrowSwitchProp"] = var0
       3 [-]: GETIMPORT R0 1; var0 = _T
       4 [-]: LOADNIL R1   ; var1 = nil
       5 [-]: SETTABLEKS R1 R0 K3; var1["RANGER_SetActiveArrow"] = var0
       6 [-]: GETIMPORT R0 1; var0 = _T
       7 [-]: LOADNIL R1   ; var1 = nil
       8 [-]: SETTABLEKS R1 R0 K4; var1["RANGER_SetArrowTimer"] = var0
       9 [-]: GETIMPORT R0 1; var0 = _T
      10 [-]: LOADNIL R1   ; var1 = nil
      11 [-]: SETTABLEKS R1 R0 K5; var1["RANGER_ShowText"] = var0
      12 [-]: GETIMPORT R0 1; var0 = _T
      13 [-]: LOADNIL R1   ; var1 = nil
      14 [-]: SETTABLEKS R1 R0 K6; var1["RANGER_ShowControlParticles"] = var0
      15 [-]: GETIMPORT R1 8; var1 = _T["HUD_GetAnchorMgr"]
      16 [-]: FASTCALL1 64 R1 L0; 
      17 [-]: GETIMPORT R0 10; var0 = 0x7B998233
      18 [-]: CALL R0 2 2  ; var0 = var0(var1)
L 0:  19 [-]: JUMPIF R0 L1 ; goto L1 if var0
      20 [-]: GETIMPORT R0 8; var0 = _T["HUD_GetAnchorMgr"]
      21 [-]: CALL R0 1 2  ; var0 = var0()
      22 [-]: JUMPXEQKNIL R0 L1; 
      23 [-]: GETIMPORT R3 12; var3 = 0xAE91E43B
      24 [-]: LOADK R4 K13 ; var4 = "ArrowDirection"
      25 [-]: NAMECALL R1 R0 K14; var2 = var0; var1 = var0[0x7F19C438]
      26 [-]: CALL R1 4 1  ; var1(var2, var3, var4)
L 1:  27 [-]: GETUPVAL R1 0; var1 = upvalues[0]
      28 [-]: FASTCALL1 64 R1 L2; 
      29 [-]: GETIMPORT R0 10; var0 = 0x7B998233
      30 [-]: CALL R0 2 2  ; var0 = var0(var1)
L 2:  31 [-]: JUMPIF R0 L3 ; goto L3 if var0
      32 [-]: GETUPVAL R0 0; var0 = upvalues[0]
      33 [-]: NAMECALL R0 R0 K15; var1 = var0; var0 = var0[0xA2880940]
      34 [-]: CALL R0 2 1  ; var0(var1)
L 3:  35 [-]: GETUPVAL R1 1; var1 = upvalues[1]
      36 [-]: FASTCALL1 64 R1 L4; 
      37 [-]: GETIMPORT R0 10; var0 = 0x7B998233
      38 [-]: CALL R0 2 2  ; var0 = var0(var1)
L 4:  39 [-]: JUMPIF R0 L5 ; goto L5 if var0
      40 [-]: GETUPVAL R0 1; var0 = upvalues[1]
      41 [-]: NAMECALL R0 R0 K16; var1 = var0; var0 = var0[0xDB371820]
      42 [-]: CALL R0 2 1  ; var0(var1)
L 5:  43 [-]: RETURN R0 0  ; 


; Name:            
; Defined at line: 263
; #Upvalues:       12
; #Parameters:     0
; Is_vararg:       0
; Max Stack Size:  10

       0 [-]: GETIMPORT R0 2; var0 = _T["HUD_GetAnchorMgr"]
       1 [-]: CALL R0 1 2  ; var0 = var0()
       2 [-]: GETIMPORT R3 4; var3 = 0xAE91E43B
       3 [-]: LOADK R4 K5  ; var4 = "ArrowDirection"
       4 [-]: NEWTABLE R5 0 2; var5 = {}
       5 [-]: GETTABLEKS R6 R0 K6; var6 = var0["ANCHOR_V_CENTRE"]
       6 [-]: GETTABLEKS R7 R0 K7; var7 = var0["ANCHOR_H_CENTRE"]
       7 [-]: SETLIST R5 R6 2 [1]; var5[1] = var6; var5[2] = var7; var5[3] = var8; 
       8 [-]: NAMECALL R1 R0 K8; var2 = var0; var1 = var0[0x20FF29F7]
       9 [-]: CALL R1 5 1  ; var1(var2, var3, var4, var5)
      10 [-]: GETIMPORT R3 4; var3 = 0xAE91E43B
      11 [-]: NAMECALL R3 R3 K9; var4 = var3; var3 = var3[0x6B837788]
      12 [-]: CALL R3 2 2  ; var3 = var3(var4)
      13 [-]: GETIMPORT R4 4; var4 = 0xAE91E43B
      14 [-]: NAMECALL R4 R4 K10; var5 = var4; var4 = var4[0xAF9FDA9F]
      15 [-]: CALL R4 2 2  ; var4 = var4(var5)
      16 [-]: LOADB R5 1   ; var5 = true
      17 [-]: GETTABLEKS R6 R0 K11; var6 = var0["mHudScalePadding"]
      18 [-]: NAMECALL R1 R0 K12; var2 = var0; var1 = var0[0xFAA69527]
      19 [-]: CALL R1 6 1  ; var1(var2, var3, var4, var5, var6)
      20 [-]: GETIMPORT R1 4; var1 = 0xAE91E43B
      21 [-]: LOADK R3 K13 ; var3 = "_root"
      22 [-]: LOADN R4 10  ; var4 = 10
      23 [-]: LOADN R5 0   ; var5 = 0
      24 [-]: NAMECALL R1 R1 K14; var2 = var1; var1 = var1[0x67BC869F]
      25 [-]: CALL R1 5 1  ; var1(var2, var3, var4, var5)
      26 [-]: GETUPVAL R1 0; var1 = upvalues[0]
      27 [-]: CALL R1 1 1  ; var1()
      28 [-]: GETIMPORT R1 4; var1 = 0xAE91E43B
      29 [-]: LOADK R3 K5  ; var3 = "ArrowDirection"
      30 [-]: LOADN R4 10  ; var4 = 10
      31 [-]: LOADN R5 0   ; var5 = 0
      32 [-]: NAMECALL R1 R1 K14; var2 = var1; var1 = var1[0x67BC869F]
      33 [-]: CALL R1 5 1  ; var1(var2, var3, var4, var5)
      34 [-]: GETIMPORT R1 16; var1 = 0x2D0FAD09
      35 [-]: LOADK R2 K17 ; var2 = "Lotus.Interface.PowerSuitCustomHuds.AbilitySelector"
      36 [-]: CALL R1 2 2  ; var1 = var1(var2)
      37 [-]: GETTABLEKS R2 R1 K18; var2 = var1[0xAE6791BA]
      38 [-]: GETIMPORT R3 4; var3 = 0xAE91E43B
      39 [-]: LOADK R4 K19 ; var4 = "Quiver"
      40 [-]: LOADN R5 0   ; var5 = 0
      41 [-]: LOADK R6 K20 ; var6 = "/Lotus/Language/Items/RangerQuiverHoldToSwitch"
      42 [-]: CALL R2 5 2  ; var2 = var2(var3, var4, var5, var6)
      43 [-]: SETUPVAL R2 1; upvalues[2] = var1
      44 [-]: GETUPVAL R2 1; var2 = upvalues[1]
      45 [-]: GETIMPORT R3 22; var3 = 0x9971CC83
      46 [-]: SETTABLEKS R3 R2 K23; var3["mAbilityIcons"] = var2
      47 [-]: GETUPVAL R2 1; var2 = upvalues[1]
      48 [-]: GETUPVAL R4 2; var4 = upvalues[2]
      49 [-]: GETTABLEKS R3 R4 K24; var3 = var4[0x06D055F9]
      50 [-]: GETUPVAL R5 3; var5 = upvalues[3]
      51 [-]: GETTABLEKS R4 R5 K25; var4 = var5[0x32316A21]
      52 [-]: CALL R4 1 2  ; var4 = var4()
      53 [-]: LOADN R5 3   ; var5 = 3
      54 [-]: GETUPVAL R7 1; var7 = upvalues[1]
      55 [-]: GETTABLEKS R6 R7 K26; var6 = var7["MAX_ABILITIES"]
      56 [-]: CALL R3 4 2  ; var3 = var3(var4, var5, var6)
      57 [-]: SETTABLEKS R3 R2 K26; var3["MAX_ABILITIES"] = var2
      58 [-]: GETIMPORT R2 27; var2 = _T
      59 [-]: NEWCLOSURE R3 P0; 
      60 [-]: CAPTURE UPVAL U4; 
      61 [-]: CAPTURE UPVAL U1; 
      62 [-]: SETTABLEKS R3 R2 K28; var3["RANGER_SetArrowSwitchProp"] = var2
      63 [-]: GETIMPORT R2 27; var2 = _T
      64 [-]: NEWCLOSURE R3 P1; 
      65 [-]: CAPTURE UPVAL U4; 
      66 [-]: CAPTURE UPVAL U1; 
      67 [-]: SETTABLEKS R3 R2 K29; var3["RANGER_SetActiveArrow"] = var2
      68 [-]: GETIMPORT R2 27; var2 = _T
      69 [-]: NEWCLOSURE R3 P2; 
      70 [-]: CAPTURE UPVAL U4; 
      71 [-]: CAPTURE UPVAL U1; 
      72 [-]: SETTABLEKS R3 R2 K30; var3["RANGER_SetArrowTimer"] = var2
      73 [-]: GETIMPORT R2 27; var2 = _T
      74 [-]: NEWCLOSURE R3 P3; 
      75 [-]: CAPTURE UPVAL U4; 
      76 [-]: CAPTURE UPVAL U1; 
      77 [-]: SETTABLEKS R3 R2 K31; var3["RANGER_ShowText"] = var2
      78 [-]: GETIMPORT R2 27; var2 = _T
      79 [-]: DUPCLOSURE R3 K32; 
      80 [-]: CAPTURE UPVAL U4; 
      81 [-]: CAPTURE UPVAL U5; 
      82 [-]: SETTABLEKS R3 R2 K33; var3["RANGER_ShowControlParticles"] = var2
      83 [-]: GETIMPORT R2 27; var2 = _T
      84 [-]: GETUPVAL R4 1; var4 = upvalues[1]
      85 [-]: GETTABLEKS R3 R4 K34; var3 = var4["GetAbilityLocTag"]
      86 [-]: SETTABLEKS R3 R2 K35; var3["RANGER_GetArrowLocTag"] = var2
      87 [-]: GETUPVAL R2 1; var2 = upvalues[1]
      88 [-]: NAMECALL R2 R2 K36; var3 = var2; var2 = var2[0x687AE094]
      89 [-]: CALL R2 2 1  ; var2(var3)
      90 [-]: GETUPVAL R4 1; var4 = upvalues[1]
      91 [-]: GETTABLEKS R3 R4 K37; var3 = var4["mAbilityProperties"]
      92 [-]: GETTABLEN R2 R3 1; var2 = var3[1]
      93 [-]: GETIMPORT R3 39; var3 = 0x0469F296
      94 [-]: LOADK R4 K40 ; var4 = "/Lotus/Language/Items/RangerQuiverArrow1Name"
      95 [-]: CALL R3 2 2  ; var3 = var3(var4)
      96 [-]: SETTABLEKS R3 R2 K41; var3["Name"] = var2
      97 [-]: GETUPVAL R4 1; var4 = upvalues[1]
      98 [-]: GETTABLEKS R3 R4 K37; var3 = var4["mAbilityProperties"]
      99 [-]: GETTABLEN R2 R3 2; var2 = var3[2]
     100 [-]: GETIMPORT R3 39; var3 = 0x0469F296
     101 [-]: GETUPVAL R5 2; var5 = upvalues[2]
     102 [-]: GETTABLEKS R4 R5 K24; var4 = var5[0x06D055F9]
     103 [-]: GETUPVAL R6 3; var6 = upvalues[3]
     104 [-]: GETTABLEKS R5 R6 K25; var5 = var6[0x32316A21]
     105 [-]: CALL R5 1 2  ; var5 = var5()
     106 [-]: LOADK R6 K42 ; var6 = "/Lotus/Language/Items/RangerPvpQuiverArrow2Name"
     107 [-]: LOADK R7 K43 ; var7 = "/Lotus/Language/Items/RangerQuiverArrow2Name"
     108 [-]: CALL R4 4 0  ; var4, ... = var4(var5, var6, var7)
     109 [-]: CALL R3 0 2  ; var3 = var3(var4, ...)
     110 [-]: SETTABLEKS R3 R2 K41; var3["Name"] = var2
     111 [-]: GETUPVAL R4 1; var4 = upvalues[1]
     112 [-]: GETTABLEKS R3 R4 K37; var3 = var4["mAbilityProperties"]
     113 [-]: GETTABLEN R2 R3 3; var2 = var3[3]
     114 [-]: GETIMPORT R3 39; var3 = 0x0469F296
     115 [-]: GETUPVAL R5 2; var5 = upvalues[2]
     116 [-]: GETTABLEKS R4 R5 K24; var4 = var5[0x06D055F9]
     117 [-]: GETUPVAL R6 3; var6 = upvalues[3]
     118 [-]: GETTABLEKS R5 R6 K25; var5 = var6[0x32316A21]
     119 [-]: CALL R5 1 2  ; var5 = var5()
     120 [-]: LOADK R6 K44 ; var6 = "/Lotus/Language/Items/RangerPvpQuiverArrow3Name"
     121 [-]: LOADK R7 K45 ; var7 = "/Lotus/Language/Items/RangerQuiverArrow3Name"
     122 [-]: CALL R4 4 0  ; var4, ... = var4(var5, var6, var7)
     123 [-]: CALL R3 0 2  ; var3 = var3(var4, ...)
     124 [-]: SETTABLEKS R3 R2 K41; var3["Name"] = var2
     125 [-]: GETUPVAL R5 1; var5 = upvalues[1]
     126 [-]: GETTABLEKS R4 R5 K37; var4 = var5["mAbilityProperties"]
     127 [-]: GETTABLEN R3 R4 4; var3 = var4[4]
     128 [-]: FASTCALL1 64 R3 L0; 
     129 [-]: GETIMPORT R2 47; var2 = 0x7B998233
     130 [-]: CALL R2 2 2  ; var2 = var2(var3)
L 0: 131 [-]: JUMPIF R2 L1 ; goto L1 if var2
     132 [-]: GETUPVAL R4 1; var4 = upvalues[1]
     133 [-]: GETTABLEKS R3 R4 K37; var3 = var4["mAbilityProperties"]
     134 [-]: GETTABLEN R2 R3 4; var2 = var3[4]
     135 [-]: GETIMPORT R3 39; var3 = 0x0469F296
     136 [-]: LOADK R4 K48 ; var4 = "/Lotus/Language/Items/RangerQuiverArrow4Name"
     137 [-]: CALL R3 2 2  ; var3 = var3(var4)
     138 [-]: SETTABLEKS R3 R2 K41; var3["Name"] = var2
L 1: 139 [-]: GETIMPORT R3 50; var3 = _T["rangerQuiver"]
     140 [-]: FASTCALL1 64 R3 L2; 
     141 [-]: GETIMPORT R2 47; var2 = 0x7B998233
     142 [-]: CALL R2 2 2  ; var2 = var2(var3)
L 2: 143 [-]: JUMPIF R2 L4 ; goto L4 if var2
     144 [-]: GETUPVAL R2 6; var2 = upvalues[6]
     145 [-]: CALL R2 1 1  ; var2()
     146 [-]: GETIMPORT R3 52; var3 = _T["rangerQuiver"]["projIndex"]
     147 [-]: FASTCALL1 64 R3 L3; 
     148 [-]: GETIMPORT R2 47; var2 = 0x7B998233
     149 [-]: CALL R2 2 2  ; var2 = var2(var3)
L 3: 150 [-]: JUMPIF R2 L4 ; goto L4 if var2
     151 [-]: GETIMPORT R2 53; var2 = _T["RANGER_SetActiveArrow"]
     152 [-]: GETIMPORT R5 52; var5 = _T["rangerQuiver"]["projIndex"]
     153 [-]: GETUPVAL R7 1; var7 = upvalues[1]
     154 [-]: GETTABLEKS R6 R7 K26; var6 = var7["MAX_ABILITIES"]
     155 [-]: MOD R4 R5 R6 ; var4 = var5 var6
     156 [-]: ADDK R3 R4 K54; var3 = var4 + 1
     157 [-]: CALL R2 2 1  ; var2(var3)
L 4: 158 [-]: LOADK R5 K19 ; var5 = "Quiver"
     159 [-]: NAMECALL R3 R0 K55; var4 = var0; var3 = var0[0x9D1DB3EB]
     160 [-]: CALL R3 3 2  ; var3 = var3(var4, var5)
     161 [-]: GETTABLEKS R2 R3 K56; var2 = var3["y"]
     162 [-]: SETUPVAL R2 7; upvalues[2] = var7
     163 [-]: GETIMPORT R2 58; var2 = 0x89326C93
     164 [-]: NAMECALL R2 R2 K59; var3 = var2; var2 = var2[0x78298275]
     165 [-]: CALL R2 2 2  ; var2 = var2(var3)
     166 [-]: SETUPVAL R2 8; upvalues[2] = var8
     167 [-]: GETUPVAL R3 8; var3 = upvalues[8]
     168 [-]: FASTCALL1 64 R3 L5; 
     169 [-]: GETIMPORT R2 47; var2 = 0x7B998233
     170 [-]: CALL R2 2 2  ; var2 = var2(var3)
L 5: 171 [-]: JUMPIF R2 L11; goto L11 if var2
     172 [-]: GETUPVAL R2 8; var2 = upvalues[8]
     173 [-]: NAMECALL R2 R2 K60; var3 = var2; var2 = var2[0x5E651723]
     174 [-]: CALL R2 2 2  ; var2 = var2(var3)
     175 [-]: FASTCALL1 64 R2 L6; 
     176 [-]: MOVE R4 R2   ; var4 = var2
     177 [-]: GETIMPORT R3 47; var3 = 0x7B998233
     178 [-]: CALL R3 2 2  ; var3 = var3(var4)
L 6: 179 [-]: JUMPIF R3 L7 ; goto L7 if var3
     180 [-]: NAMECALL R3 R2 K61; var4 = var2; var3 = var2[0x0803EEE1]
     181 [-]: CALL R3 2 2  ; var3 = var3(var4)
     182 [-]: SETUPVAL R3 9; upvalues[3] = var9
L 7: 183 [-]: GETUPVAL R3 8; var3 = upvalues[8]
     184 [-]: NAMECALL R3 R3 K62; var4 = var3; var3 = var3[0xDE321E6F]
     185 [-]: CALL R3 2 2  ; var3 = var3(var4)
     186 [-]: SETUPVAL R3 10; upvalues[3] = var10
     187 [-]: GETUPVAL R4 10; var4 = upvalues[10]
     188 [-]: FASTCALL1 64 R4 L8; 
     189 [-]: GETIMPORT R3 47; var3 = 0x7B998233
     190 [-]: CALL R3 2 2  ; var3 = var3(var4)
L 8: 191 [-]: JUMPIF R3 L11; goto L11 if var3
     192 [-]: GETUPVAL R3 10; var3 = upvalues[10]
     193 [-]: NAMECALL R3 R3 K63; var4 = var3; var3 = var3[0xF7D48EE0]
     194 [-]: CALL R3 2 2  ; var3 = var3(var4)
     195 [-]: FASTCALL1 64 R3 L9; 
     196 [-]: MOVE R5 R3   ; var5 = var3
     197 [-]: GETIMPORT R4 47; var4 = 0x7B998233
     198 [-]: CALL R4 2 2  ; var4 = var4(var5)
L 9: 199 [-]: JUMPIF R4 L11; goto L11 if var4
     200 [-]: GETIMPORT R6 65; var6 = 0x7ED0A956
     201 [-]: LOADK R7 K66 ; var7 = "/Lotus/Powersuits/PowersuitAbilities/RangerQuiverAbility"
     202 [-]: CALL R6 2 0  ; var6, ... = var6(var7)
     203 [-]: NAMECALL R4 R3 K67; var5 = var3; var4 = var3[0x689412A5]
     204 [-]: CALL R4 0 2  ; var4 = var4(var5, ...)
     205 [-]: FASTCALL1 64 R4 L10; 
     206 [-]: MOVE R6 R4   ; var6 = var4
     207 [-]: GETIMPORT R5 47; var5 = 0x7B998233
     208 [-]: CALL R5 2 2  ; var5 = var5(var6)
L10: 209 [-]: JUMPIFNOT R5 L11; goto L11 if not var5
     210 [-]: GETIMPORT R5 4; var5 = 0xAE91E43B
     211 [-]: LOADK R7 K19 ; var7 = "Quiver"
     212 [-]: LOADN R8 10  ; var8 = 10
     213 [-]: LOADN R9 0   ; var9 = 0
     214 [-]: NAMECALL R5 R5 K14; var6 = var5; var5 = var5[0x67BC869F]
     215 [-]: CALL R5 5 1  ; var5(var6, var7, var8, var9)
L11: 216 [-]: LOADB R2 1   ; var2 = true
     217 [-]: SETUPVAL R2 11; upvalues[2] = var11
     218 [-]: RETURN R0 0  ; 


; Name:            
; Defined at line: 329
; #Upvalues:       1
; #Parameters:     1
; Is_vararg:       0
; Max Stack Size:  5

       0 [-]: GETUPVAL R2 0; var2 = upvalues[0]
       1 [-]: GETTABLEKS R1 R2 K0; var1 = var2[0xFA221145]
       2 [-]: GETIMPORT R2 2; var2 = 0xAE91E43B
       3 [-]: FASTCALL1 62 R0 L0; 
       4 [-]: MOVE R4 R0   ; var4 = var0
       5 [-]: GETIMPORT R3 4; var3 = 0x03F57322
       6 [-]: CALL R3 2 2  ; var3 = var3(var4)
L 0:   7 [-]: CALL R1 3 1  ; var1(var2, var3)
       8 [-]: RETURN R0 0  ; 



