; This file has been disassembled using luadec 2.0.2 by sztupy (modified by Reversive)

; Name:            
; Defined at line: 0
; #Upvalues:       0
; #Parameters:     0
; Is_vararg:       2
; Max Stack Size:  43

  1 [-]: GETGLOBAL R0 K0        ; R0 := 0x2d0fad09
  2 [-]: LOADK     R1 K1        ; R1 := "Lotus.Interface.UIUtilities"
  3 [-]: CALL      R0 2 2       ; R0 := R0(R1)
  4 [-]: GETGLOBAL R1 K0        ; R1 := 0x2d0fad09
  5 [-]: LOADK     R2 K2        ; R2 := "Lotus.Interface.LotusUtilities"
  6 [-]: CALL      R1 2 2       ; R1 := R1(R2)
  7 [-]: GETGLOBAL R2 K0        ; R2 := 0x2d0fad09
  8 [-]: LOADK     R3 K3        ; R3 := "EE.Interface.Utilities"
  9 [-]: CALL      R2 2 2       ; R2 := R2(R3)
 10 [-]: GETGLOBAL R3 K0        ; R3 := 0x2d0fad09
 11 [-]: LOADK     R4 K4        ; R4 := "Lotus.Scripts.Effects.EffectsColorUtilities"
 12 [-]: CALL      R3 2 2       ; R3 := R3(R4)
 13 [-]: LOADNIL   R4 R4        ; R4 := nil
 14 [-]: LOADKB    R5 0 0       ; R5 := false
 15 [-]: LOADNIL   R6 R6        ; R6 := nil
 16 [-]: NEWTABLE  R7 0 0       ; R7 := {}
 17 [-]: LOADKB    R8 0 0       ; R8 := false
 18 [-]: LOADNIL   R9 R14       ; R9 := R10 := R11 := R12 := R13 := R14 := nil
 19 [-]: LOADKB    R15 0 0      ; R15 := false
 20 [-]: CONST     R16 0        ; R16 := 0.000000
 21 [-]: LOADKB    R17 0 0      ; R17 := false
 22 [-]: CONST     R18 0        ; R18 := 0.000000
 23 [-]: LOADNIL   R19 R20      ; R19 := R20 := nil
 24 [-]: LOADKB    R21 1 0      ; R21 := true
 25 [-]: LOADNIL   R22 R22      ; R22 := nil
 26 [-]: LOADK     R23 K5       ; R23 := ""
 27 [-]: LOADNIL   R24 R25      ; R24 := R25 := nil
 28 [-]: GETGLOBAL R26 K6       ; R26 := 0x88efc25e
 29 [-]: LOADK     R27 K7       ; R27 := "/Lotus/Types/Game/HealthShieldDisplay"
 30 [-]: CALL      R26 2 2      ; R26 := R26(R27)
 31 [-]: NEWTABLE  R27 0 0      ; R27 := {}
 32 [-]: CLOSURE   R28 0        ; R28 := closure(Function #1)
 33 [-]: CLOSURE   R29 1        ; R29 := closure(Function #2)
 34 [-]: MOVE      R0 R1        ; R0 := R1
 35 [-]: CLOSURE   R30 2        ; R30 := closure(Function #3)
 36 [-]: MOVE      R0 R11       ; R0 := R11
 37 [-]: CLOSURE   R31 3        ; R31 := closure(Function #4)
 38 [-]: MOVE      R0 R12       ; R0 := R12
 39 [-]: MOVE      R0 R30       ; R0 := R30
 40 [-]: MOVE      R0 R11       ; R0 := R11
 41 [-]: MOVE      R0 R3        ; R0 := R3
 42 [-]: MOVE      R0 R13       ; R0 := R13
 43 [-]: CLOSURE   R32 4        ; R32 := closure(Function #5)
 44 [-]: MOVE      R0 R2        ; R0 := R2
 45 [-]: MOVE      R0 R18       ; R0 := R18
 46 [-]: CLOSURE   R33 5        ; R33 := closure(Function #6)
 47 [-]: MOVE      R0 R18       ; R0 := R18
 48 [-]: MOVE      R0 R32       ; R0 := R32
 49 [-]: CLOSURE   R34 6        ; R34 := closure(Function #7)
 50 [-]: CLOSURE   R35 7        ; R35 := closure(Function #8)
 51 [-]: MOVE      R0 R2        ; R0 := R2
 52 [-]: CLOSURE   R36 8        ; R36 := closure(Function #9)
 53 [-]: MOVE      R0 R5        ; R0 := R5
 54 [-]: MOVE      R0 R4        ; R0 := R4
 55 [-]: MOVE      R0 R6        ; R0 := R6
 56 [-]: MOVE      R0 R8        ; R0 := R8
 57 [-]: MOVE      R0 R7        ; R0 := R7
 58 [-]: MOVE      R0 R10       ; R0 := R10
 59 [-]: MOVE      R0 R15       ; R0 := R15
 60 [-]: MOVE      R0 R2        ; R0 := R2
 61 [-]: MOVE      R0 R19       ; R0 := R19
 62 [-]: MOVE      R0 R20       ; R0 := R20
 63 [-]: MOVE      R0 R30       ; R0 := R30
 64 [-]: MOVE      R0 R11       ; R0 := R11
 65 [-]: MOVE      R0 R14       ; R0 := R14
 66 [-]: MOVE      R0 R26       ; R0 := R26
 67 [-]: MOVE      R0 R9        ; R0 := R9
 68 [-]: MOVE      R0 R29       ; R0 := R29
 69 [-]: MOVE      R0 R28       ; R0 := R28
 70 [-]: MOVE      R0 R17       ; R0 := R17
 71 [-]: MOVE      R0 R0        ; R0 := R0
 72 [-]: MOVE      R0 R16       ; R0 := R16
 73 [-]: MOVE      R0 R25       ; R0 := R25
 74 [-]: MOVE      R0 R24       ; R0 := R24
 75 [-]: SETGLOBAL R36 K8       ; Update := R36
 76 [-]: CLOSURE   R36 9        ; R36 := closure(Function #10)
 77 [-]: MOVE      R0 R8        ; R0 := R8
 78 [-]: MOVE      R0 R7        ; R0 := R7
 79 [-]: CLOSURE   R37 10       ; R37 := closure(Function #11)
 80 [-]: MOVE      R0 R14       ; R0 := R14
 81 [-]: SETGLOBAL R37 K9       ; Shutdown := R37
 82 [-]: CLOSURE   R37 11       ; R37 := closure(Function #12)
 83 [-]: MOVE      R0 R21       ; R0 := R21
 84 [-]: MOVE      R0 R2        ; R0 := R2
 85 [-]: CLOSURE   R38 12       ; R38 := closure(Function #13)
 86 [-]: MOVE      R0 R22       ; R0 := R22
 87 [-]: MOVE      R0 R2        ; R0 := R2
 88 [-]: MOVE      R0 R23       ; R0 := R23
 89 [-]: CLOSURE   R39 13       ; R39 := closure(Function #14)
 90 [-]: MOVE      R0 R27       ; R0 := R27
 91 [-]: CLOSURE   R40 14       ; R40 := closure(Function #15)
 92 [-]: MOVE      R0 R2        ; R0 := R2
 93 [-]: MOVE      R0 R12       ; R0 := R12
 94 [-]: MOVE      R0 R13       ; R0 := R13
 95 [-]: CLOSURE   R41 15       ; R41 := closure(Function #16)
 96 [-]: MOVE      R0 R2        ; R0 := R2
 97 [-]: MOVE      R0 R40       ; R0 := R40
 98 [-]: MOVE      R0 R27       ; R0 := R27
 99 [-]: MOVE      R0 R4        ; R0 := R4
100 [-]: MOVE      R0 R12       ; R0 := R12
101 [-]: CLOSURE   R42 16       ; R42 := closure(Function #17)
102 [-]: MOVE      R0 R4        ; R0 := R4
103 [-]: MOVE      R0 R36       ; R0 := R36
104 [-]: MOVE      R0 R33       ; R0 := R33
105 [-]: MOVE      R0 R34       ; R0 := R34
106 [-]: MOVE      R0 R37       ; R0 := R37
107 [-]: MOVE      R0 R38       ; R0 := R38
108 [-]: MOVE      R0 R35       ; R0 := R35
109 [-]: MOVE      R0 R41       ; R0 := R41
110 [-]: MOVE      R0 R24       ; R0 := R24
111 [-]: MOVE      R0 R25       ; R0 := R25
112 [-]: MOVE      R0 R31       ; R0 := R31
113 [-]: MOVE      R0 R39       ; R0 := R39
114 [-]: MOVE      R0 R19       ; R0 := R19
115 [-]: MOVE      R0 R20       ; R0 := R20
116 [-]: MOVE      R0 R2        ; R0 := R2
117 [-]: MOVE      R0 R12       ; R0 := R12
118 [-]: MOVE      R0 R23       ; R0 := R23
119 [-]: MOVE      R0 R16       ; R0 := R16
120 [-]: MOVE      R0 R5        ; R0 := R5
121 [-]: SETGLOBAL R42 K10      ; Initialize := R42
122 [-]: CLOSURE   R42 17       ; R42 := closure(Function #18)
123 [-]: MOVE      R0 R0        ; R0 := R0
124 [-]: SETGLOBAL R42 K11      ; HandleHudScale := R42
125 [-]: RETURN    R0 1         ; return 


; Function #1:
;
; Name:            
; Defined at line: 52
; #Upvalues:       0
; #Parameters:     0
; Is_vararg:       0
; Max Stack Size:  3

  1 [-]: GETGLOBAL R0 K0        ; R0 := 0xbe190284
  2 [-]: GETGLOBAL R1 K1        ; R1 := 0x7b998233
  3 [-]: MOVE      R2 R0        ; R2 := R0
  4 [-]: CALL      R1 2 2       ; R1 := R1(R2)
  5 [-]: TEST      R1 1         ; if R1 then PC := 13
  6 [-]: JMP       13           ; PC := 13
  7 [-]: SELF      R1 R0 K2     ; R2 := R0; R1 := R0[0x486e5f11]
  8 [-]: CALL      R1 2 2       ; R1 := R1(R2)
  9 [-]: TEST      R1 0         ; if not R1 then PC := 13
 10 [-]: JMP       13           ; PC := 13
 11 [-]: LOADKB    R1 1 0       ; R1 := true
 12 [-]: RETURN    R1 2         ; return R1
 13 [-]: LOADKB    R1 0 0       ; R1 := false
 14 [-]: RETURN    R1 2         ; return R1
 15 [-]: RETURN    R0 1         ; return 


; Function #2:
;
; Name:            
; Defined at line: 60
; #Upvalues:       1
; #Parameters:     0
; Is_vararg:       0
; Max Stack Size:  2

  1 [-]: GETUPVAL  R0 U0        ; R0 := U0
  2 [-]: GETTABLE  R0 R0 K0     ; R0 := R0[0xb73d420f]
  3 [-]: CALL      R0 1 2       ; R0 := R0()
  4 [-]: GETUPVAL  R1 U0        ; R1 := U0
  5 [-]: GETTABLE  R1 R1 K1     ; R1 := R1["UI_MODE_IN_DOJO"]
  6 [-]: EQ        0 R0 R1      ; if R0 ~= R1 then PC := 10
  7 [-]: JMP       10           ; PC := 10
  8 [-]: LOADKB    R0 1 0       ; R0 := true
  9 [-]: RETURN    R0 2         ; return R0
 10 [-]: LOADKB    R0 0 0       ; R0 := false
 11 [-]: RETURN    R0 2         ; return R0
 12 [-]: RETURN    R0 1         ; return 


; Function #3:
;
; Name:            
; Defined at line: 67
; #Upvalues:       1
; #Parameters:     0
; Is_vararg:       0
; Max Stack Size:  4

  1 [-]: GETGLOBAL R0 K0        ; R0 := 0x7b998233
  2 [-]: GETUPVAL  R1 U0        ; R1 := U0
  3 [-]: CALL      R0 2 2       ; R0 := R0(R1)
  4 [-]: TEST      R0 0         ; if not R0 then PC := 24
  5 [-]: JMP       24           ; PC := 24
  6 [-]: GETGLOBAL R0 K1        ; R0 := 0x89326c93
  7 [-]: SELF      R0 R0 K2     ; R1 := R0; R0 := R0[0x78298275]
  8 [-]: CALL      R0 2 2       ; R0 := R0(R1)
  9 [-]: GETGLOBAL R1 K0        ; R1 := 0x7b998233
 10 [-]: MOVE      R2 R0        ; R2 := R0
 11 [-]: CALL      R1 2 2       ; R1 := R1(R2)
 12 [-]: TEST      R1 1         ; if R1 then PC := 24
 13 [-]: JMP       24           ; PC := 24
 14 [-]: SELF      R1 R0 K3     ; R2 := R0; R1 := R0[0xde321e6f]
 15 [-]: CALL      R1 2 2       ; R1 := R1(R2)
 16 [-]: GETGLOBAL R2 K0        ; R2 := 0x7b998233
 17 [-]: MOVE      R3 R1        ; R3 := R1
 18 [-]: CALL      R2 2 2       ; R2 := R2(R3)
 19 [-]: TEST      R2 1         ; if R2 then PC := 24
 20 [-]: JMP       24           ; PC := 24
 21 [-]: SELF      R2 R1 K4     ; R3 := R1; R2 := R1[0xf7d48ee0]
 22 [-]: CALL      R2 2 2       ; R2 := R2(R3)
 23 [-]: SETUPVAL  R2 U0        ; U82 := R0
 24 [-]: RETURN    R0 1         ; return 


; Function #4:
;
; Name:            
; Defined at line: 79
; #Upvalues:       5
; #Parameters:     0
; Is_vararg:       0
; Max Stack Size:  13

  1 [-]: GETGLOBAL R0 K0        ; R0 := 0x60130201
  2 [-]: CALL      R0 1 2       ; R0 := R0()
  3 [-]: SETUPVAL  R0 U0        ; U82 := R0
  4 [-]: GETUPVAL  R0 U1        ; R0 := U1
  5 [-]: CALL      R0 1 1       ; R0()
  6 [-]: GETGLOBAL R0 K1        ; R0 := 0x7b998233
  7 [-]: GETUPVAL  R1 U2        ; R1 := U2
  8 [-]: CALL      R0 2 2       ; R0 := R0(R1)
  9 [-]: TEST      R0 1         ; if R0 then PC := 15
 10 [-]: JMP       15           ; PC := 15
 11 [-]: GETUPVAL  R0 U2        ; R0 := U2
 12 [-]: SELF      R0 R0 K2     ; R1 := R0; R0 := R0[0xa3ef5d65]
 13 [-]: GETUPVAL  R2 U0        ; R2 := U0
 14 [-]: CALL      R0 3 1       ; R0(R1,R2)
 15 [-]: GETGLOBAL R0 K1        ; R0 := 0x7b998233
 16 [-]: GETUPVAL  R1 U0        ; R1 := U0
 17 [-]: CALL      R0 2 2       ; R0 := R0(R1)
 18 [-]: TEST      R0 1         ; if R0 then PC := 65
 19 [-]: JMP       65           ; PC := 65
 20 [-]: GETUPVAL  R0 U3        ; R0 := U3
 21 [-]: GETTABLE  R0 R0 K3     ; R0 := R0[0x6bcd0a85]
 22 [-]: GETUPVAL  R1 U0        ; R1 := U0
 23 [-]: CALL      R0 2 4       ; R0,R1,R2 := R0(R1)
 24 [-]: GETUPVAL  R3 U3        ; R3 := U3
 25 [-]: GETTABLE  R3 R3 K4     ; R3 := R3[0x6b70106d]
 26 [-]: MOVE      R4 R0        ; R4 := R0
 27 [-]: MOVE      R5 R1        ; R5 := R1
 28 [-]: LOADK     R6 K5        ; R6 := 0.100000
 29 [-]: CALL      R3 4 2       ; R3 := R3(R4,R5,R6)
 30 [-]: SETUPVAL  R3 U4        ; U82 := R4
 31 [-]: GETUPVAL  R3 U0        ; R3 := U0
 32 [-]: SELF      R3 R3 K6     ; R4 := R3; R3 := R3[0xa5d5c8f6]
 33 [-]: CALL      R3 2 2       ; R3 := R3(R4)
 34 [-]: GETGLOBAL R4 K7        ; R4 := 0xae91e43b
 35 [-]: SELF      R4 R4 K8     ; R5 := R4; R4 := R4[0x67bc869f]
 36 [-]: LOADK     R6 K9        ; R6 := "Container.FuryCounter.Progress"
 37 [-]: CONST     R7 9         ; R7 := 9.000000
 38 [-]: MOVE      R8 R3        ; R8 := R3
 39 [-]: CALL      R4 5 1       ; R4(R5,R6,R7,R8)
 40 [-]: GETGLOBAL R4 K7        ; R4 := 0xae91e43b
 41 [-]: SELF      R4 R4 K8     ; R5 := R4; R4 := R4[0x67bc869f]
 42 [-]: LOADK     R6 K10       ; R6 := "Bonus.Buff.Label"
 43 [-]: CONST     R7 36        ; R7 := 36.000000
 44 [-]: MOVE      R8 R3        ; R8 := R3
 45 [-]: CALL      R4 5 1       ; R4(R5,R6,R7,R8)
 46 [-]: GETGLOBAL R4 K7        ; R4 := 0xae91e43b
 47 [-]: SELF      R4 R4 K8     ; R5 := R4; R4 := R4[0x67bc869f]
 48 [-]: LOADK     R6 K11       ; R6 := "Message.Flare"
 49 [-]: CONST     R7 9         ; R7 := 9.000000
 50 [-]: MOVE      R8 R3        ; R8 := R3
 51 [-]: CALL      R4 5 1       ; R4(R5,R6,R7,R8)
 52 [-]: CONST     R4 1         ; R4 := 1.000000
 53 [-]: CONST     R5 5         ; R5 := 5.000000
 54 [-]: CONST     R6 1         ; R6 := 1.000000
 55 [-]: FORPREP   R4 64        ; R4 -= R6; PC := 64
 56 [-]: GETGLOBAL R8 K7        ; R8 := 0xae91e43b
 57 [-]: SELF      R8 R8 K8     ; R9 := R8; R8 := R8[0x67bc869f]
 58 [-]: LOADK     R10 K12      ; R10 := "Message.Icon"
 59 [-]: MOVE      R11 R7       ; R11 := R7
 60 [-]: CONCAT    R10 R10 R11  ; R10 := R10 .. R11
 61 [-]: CONST     R11 9        ; R11 := 9.000000
 62 [-]: MOVE      R12 R3       ; R12 := R3
 63 [-]: CALL      R8 5 1       ; R8(R9,R10,R11,R12)
 64 [-]: FORLOOP   R4 56        ; R4 += R6; if R4 <= R5 then begin PC := 56; R7 := R4 end
 65 [-]: RETURN    R0 1         ; return 


; Function #5:
;
; Name:            
; Defined at line: 102
; #Upvalues:       2
; #Parameters:     1
; Is_vararg:       0
; Max Stack Size:  9

  1 [-]: GETGLOBAL R1 K0        ; R1 := 0xae91e43b
  2 [-]: SELF      R1 R1 K1     ; R2 := R1; R1 := R1[0x5f56eeab]
  3 [-]: LOADK     R3 K2        ; R3 := "CloudTimer.Timer.Label"
  4 [-]: CONST     R4 29        ; R4 := 29.000000
  5 [-]: GETUPVAL  R5 U0        ; R5 := U0
  6 [-]: GETTABLE  R5 R5 K3     ; R5 := R5[0x1142c7a8]
  7 [-]: GETUPVAL  R6 U1        ; R6 := U1
  8 [-]: GETGLOBAL R7 K4        ; R7 := 0x03f57322
  9 [-]: MOVE      R8 R0        ; R8 := R0
 10 [-]: CALL      R7 2 2       ; R7 := R7(R8)
 11 [-]: SUB       R6 R6 R7     ; R6 := R6 - R7
 12 [-]: CONST     R7 1         ; R7 := 1.000000
 13 [-]: CALL      R5 3 0       ; R5,... := R5(R6,R7)
 14 [-]: CALL      R1 0 1       ; R1(R2,...)
 15 [-]: RETURN    R0 1         ; return 


; Function #6:
;
; Name:            
; Defined at line: 106
; #Upvalues:       2
; #Parameters:     2
; Is_vararg:       0
; Max Stack Size:  11

  1 [-]: GETGLOBAL R2 K0        ; R2 := 0xae91e43b
  2 [-]: SELF      R2 R2 K1     ; R3 := R2; R2 := R2[0x1cb415c1]
  3 [-]: LOADK     R4 K2        ; R4 := "CloudTimer.AbilityIcon"
  4 [-]: MOVE      R5 R1        ; R5 := R1
  5 [-]: CALL      R2 4 1       ; R2(R3,R4,R5)
  6 [-]: GETGLOBAL R2 K0        ; R2 := 0xae91e43b
  7 [-]: SELF      R2 R2 K1     ; R3 := R2; R2 := R2[0x1cb415c1]
  8 [-]: LOADK     R4 K3        ; R4 := "Bonus.AbilityIcon"
  9 [-]: MOVE      R5 R1        ; R5 := R1
 10 [-]: CALL      R2 4 1       ; R2(R3,R4,R5)
 11 [-]: GETGLOBAL R2 K0        ; R2 := 0xae91e43b
 12 [-]: SELF      R2 R2 K4     ; R3 := R2; R2 := R2[0x67bc869f]
 13 [-]: LOADK     R4 K5        ; R4 := "CloudTimer.Focus.Front"
 14 [-]: CONST     R5 5         ; R5 := 5.000000
 15 [-]: CONST     R6 100       ; R6 := 100.000000
 16 [-]: CALL      R2 5 1       ; R2(R3,R4,R5,R6)
 17 [-]: GETGLOBAL R2 K6        ; R2 := 0x25312c9b
 18 [-]: GETGLOBAL R3 K0        ; R3 := 0xae91e43b
 19 [-]: LOADK     R4 K7        ; R4 := "CloudTimer"
 20 [-]: CONST     R5 2         ; R5 := 2.000000
 21 [-]: NEWTABLE  R6 1 0       ; R6 := {}
 22 [-]: CONST     R7 10        ; R7 := 10.000000
 23 [-]: SETLIST   R6 1 1       ; R6[(1-1)*FPF+i] := R(6+i), 1 <= i <= 1
 24 [-]: NEWTABLE  R7 1 0       ; R7 := {}
 25 [-]: CONST     R8 100       ; R8 := 100.000000
 26 [-]: SETLIST   R7 1 1       ; R7[(1-1)*FPF+i] := R(7+i), 1 <= i <= 1
 27 [-]: LOADK     R8 K9        ; R8 := 0.150000
 28 [-]: CALL      R2 7 1       ; R2(R3,R4,R5,R6,R7,R8)
 29 [-]: SETUPVAL  R0 U0        ; U82 := R0
 30 [-]: GETGLOBAL R2 K6        ; R2 := 0x25312c9b
 31 [-]: GETGLOBAL R3 K0        ; R3 := 0xae91e43b
 32 [-]: LOADK     R4 K5        ; R4 := "CloudTimer.Focus.Front"
 33 [-]: CONST     R5 0         ; R5 := 0.000000
 34 [-]: NEWTABLE  R6 2 0       ; R6 := {}
 35 [-]: CONST     R7 5         ; R7 := 5.000000
 36 [-]: GETUPVAL  R8 U1        ; R8 := U1
 37 [-]: SETLIST   R6 2 1       ; R6[(1-1)*FPF+i] := R(6+i), 1 <= i <= 2
 38 [-]: NEWTABLE  R7 2 0       ; R7 := {}
 39 [-]: CONST     R8 0         ; R8 := 0.000000
 40 [-]: MOVE      R9 R0        ; R9 := R0
 41 [-]: SETLIST   R7 2 1       ; R7[(1-1)*FPF+i] := R(7+i), 1 <= i <= 2
 42 [-]: MOVE      R8 R0        ; R8 := R0
 43 [-]: CONST     R9 0         ; R9 := 0.000000
 44 [-]: CLOSURE   R10 0        ; R10 := closure(Function #6.1)
 45 [-]: CALL      R2 9 1       ; R2(R3,R4,R5,R6,R7,R8,R9,R10)
 46 [-]: RETURN    R0 1         ; return 


; Function #6.1:
;
; Name:            
; Defined at line: 114
; #Upvalues:       0
; #Parameters:     0
; Is_vararg:       0
; Max Stack Size:  7

  1 [-]: GETGLOBAL R0 K0        ; R0 := 0x25312c9b
  2 [-]: GETGLOBAL R1 K1        ; R1 := 0xae91e43b
  3 [-]: LOADK     R2 K2        ; R2 := "CloudTimer"
  4 [-]: CONST     R3 2         ; R3 := 2.000000
  5 [-]: NEWTABLE  R4 1 0       ; R4 := {}
  6 [-]: CONST     R5 10        ; R5 := 10.000000
  7 [-]: SETLIST   R4 1 1       ; R4[(1-1)*FPF+i] := R(4+i), 1 <= i <= 1
  8 [-]: NEWTABLE  R5 1 0       ; R5 := {}
  9 [-]: CONST     R6 0         ; R6 := 0.000000
 10 [-]: SETLIST   R5 1 1       ; R5[(1-1)*FPF+i] := R(5+i), 1 <= i <= 1
 11 [-]: LOADK     R6 K4        ; R6 := 0.150000
 12 [-]: CALL      R0 7 1       ; R0(R1,R2,R3,R4,R5,R6)
 13 [-]: RETURN    R0 1         ; return 


; Function #7:
;
; Name:            
; Defined at line: 119
; #Upvalues:       0
; #Parameters:     0
; Is_vararg:       0
; Max Stack Size:  7

  1 [-]: GETGLOBAL R0 K0        ; R0 := 0xae91e43b
  2 [-]: SELF      R0 R0 K1     ; R1 := R0; R0 := R0[0xaf5300dc]
  3 [-]: LOADK     R2 K2        ; R2 := "CloudTimer.Focus.Front"
  4 [-]: CALL      R0 3 1       ; R0(R1,R2)
  5 [-]: GETGLOBAL R0 K3        ; R0 := 0x25312c9b
  6 [-]: GETGLOBAL R1 K0        ; R1 := 0xae91e43b
  7 [-]: LOADK     R2 K4        ; R2 := "CloudTimer"
  8 [-]: CONST     R3 2         ; R3 := 2.000000
  9 [-]: NEWTABLE  R4 1 0       ; R4 := {}
 10 [-]: CONST     R5 10        ; R5 := 10.000000
 11 [-]: SETLIST   R4 1 1       ; R4[(1-1)*FPF+i] := R(4+i), 1 <= i <= 1
 12 [-]: NEWTABLE  R5 1 0       ; R5 := {}
 13 [-]: CONST     R6 0         ; R6 := 0.000000
 14 [-]: SETLIST   R5 1 1       ; R5[(1-1)*FPF+i] := R(5+i), 1 <= i <= 1
 15 [-]: LOADK     R6 K6        ; R6 := 0.150000
 16 [-]: CALL      R0 7 1       ; R0(R1,R2,R3,R4,R5,R6)
 17 [-]: RETURN    R0 1         ; return 


; Function #8:
;
; Name:            
; Defined at line: 124
; #Upvalues:       1
; #Parameters:     5
; Is_vararg:       0
; Max Stack Size:  14

  1 [-]: GETGLOBAL R5 K0        ; R5 := 0xae91e43b
  2 [-]: SELF      R5 R5 K1     ; R6 := R5; R5 := R5[0x67bc869f]
  3 [-]: LOADK     R7 K2        ; R7 := "Bonus.Buff"
  4 [-]: CONST     R8 5         ; R8 := 5.000000
  5 [-]: CONST     R9 100       ; R9 := 100.000000
  6 [-]: CALL      R5 5 1       ; R5(R6,R7,R8,R9)
  7 [-]: GETGLOBAL R5 K0        ; R5 := 0xae91e43b
  8 [-]: SELF      R5 R5 K1     ; R6 := R5; R5 := R5[0x67bc869f]
  9 [-]: LOADK     R7 K2        ; R7 := "Bonus.Buff"
 10 [-]: CONST     R8 6         ; R8 := 6.000000
 11 [-]: CONST     R9 100       ; R9 := 100.000000
 12 [-]: CALL      R5 5 1       ; R5(R6,R7,R8,R9)
 13 [-]: GETGLOBAL R5 K3        ; R5 := 0x25312c9b
 14 [-]: GETGLOBAL R6 K0        ; R6 := 0xae91e43b
 15 [-]: LOADK     R7 K4        ; R7 := "Bonus"
 16 [-]: CONST     R8 2         ; R8 := 2.000000
 17 [-]: NEWTABLE  R9 1 0       ; R9 := {}
 18 [-]: CONST     R10 10       ; R10 := 10.000000
 19 [-]: SETLIST   R9 1 1       ; R9[(1-1)*FPF+i] := R(9+i), 1 <= i <= 1
 20 [-]: NEWTABLE  R10 1 0      ; R10 := {}
 21 [-]: CONST     R11 100      ; R11 := 100.000000
 22 [-]: SETLIST   R10 1 1      ; R10[(1-1)*FPF+i] := R(10+i), 1 <= i <= 1
 23 [-]: LOADK     R11 K6       ; R11 := 0.100000
 24 [-]: CONST     R12 0        ; R12 := 0.000000
 25 [-]: CLOSURE   R13 0        ; R13 := closure(Function #8.1)
 26 [-]: CALL      R5 9 1       ; R5(R6,R7,R8,R9,R10,R11,R12,R13)
 27 [-]: GETGLOBAL R5 K0        ; R5 := 0xae91e43b
 28 [-]: SELF      R5 R5 K1     ; R6 := R5; R5 := R5[0x67bc869f]
 29 [-]: LOADK     R7 K7        ; R7 := "Bonus.Amount"
 30 [-]: CONST     R8 10        ; R8 := 10.000000
 31 [-]: CONST     R9 0         ; R9 := 0.000000
 32 [-]: CALL      R5 5 1       ; R5(R6,R7,R8,R9)
 33 [-]: GETGLOBAL R5 K0        ; R5 := 0xae91e43b
 34 [-]: SELF      R5 R5 K1     ; R6 := R5; R5 := R5[0x67bc869f]
 35 [-]: LOADK     R7 K2        ; R7 := "Bonus.Buff"
 36 [-]: CONST     R8 10        ; R8 := 10.000000
 37 [-]: CONST     R9 0         ; R9 := 0.000000
 38 [-]: CALL      R5 5 1       ; R5(R6,R7,R8,R9)
 39 [-]: GETGLOBAL R5 K0        ; R5 := 0xae91e43b
 40 [-]: SELF      R5 R5 K8     ; R6 := R5; R5 := R5[0x1cb415c1]
 41 [-]: LOADK     R7 K9        ; R7 := "CloudTimer.AbilityIcon"
 42 [-]: MOVE      R8 R4        ; R8 := R4
 43 [-]: CALL      R5 4 1       ; R5(R6,R7,R8)
 44 [-]: GETGLOBAL R5 K0        ; R5 := 0xae91e43b
 45 [-]: SELF      R5 R5 K8     ; R6 := R5; R5 := R5[0x1cb415c1]
 46 [-]: LOADK     R7 K10       ; R7 := "Bonus.AbilityIcon"
 47 [-]: MOVE      R8 R4        ; R8 := R4
 48 [-]: CALL      R5 4 1       ; R5(R6,R7,R8)
 49 [-]: GETGLOBAL R5 K0        ; R5 := 0xae91e43b
 50 [-]: SELF      R5 R5 K11    ; R6 := R5; R5 := R5[0x20b98db3]
 51 [-]: LOADK     R7 K12       ; R7 := "Bonus.Amount.text"
 52 [-]: MOVE      R8 R2        ; R8 := R2
 53 [-]: NEWTABLE  R9 0 1       ; R9 := {}
 54 [-]: GETUPVAL  R10 U0       ; R10 := U0
 55 [-]: GETTABLE  R10 R10 K14  ; R10 := R10[0x1142c7a8]
 56 [-]: MOVE      R11 R0       ; R11 := R0
 57 [-]: CONST     R12 0        ; R12 := 0.000000
 58 [-]: CALL      R10 3 2      ; R10 := R10(R11,R12)
 59 [-]: SETTABLE  R9 K13 R10   ; R9["METERS"] := R10
 60 [-]: CALL      R5 5 1       ; R5(R6,R7,R8,R9)
 61 [-]: GETGLOBAL R5 K0        ; R5 := 0xae91e43b
 62 [-]: SELF      R5 R5 K11    ; R6 := R5; R5 := R5[0x20b98db3]
 63 [-]: LOADK     R7 K15       ; R7 := "Bonus.Buff.Label.text"
 64 [-]: MOVE      R8 R3        ; R8 := R3
 65 [-]: NEWTABLE  R9 0 1       ; R9 := {}
 66 [-]: GETUPVAL  R10 U0       ; R10 := U0
 67 [-]: GETTABLE  R10 R10 K14  ; R10 := R10[0x1142c7a8]
 68 [-]: MOVE      R11 R1       ; R11 := R1
 69 [-]: CONST     R12 0        ; R12 := 0.000000
 70 [-]: CALL      R10 3 2      ; R10 := R10(R11,R12)
 71 [-]: SETTABLE  R9 K16 R10   ; R9["val"] := R10
 72 [-]: CALL      R5 5 1       ; R5(R6,R7,R8,R9)
 73 [-]: GETGLOBAL R5 K3        ; R5 := 0x25312c9b
 74 [-]: GETGLOBAL R6 K0        ; R6 := 0xae91e43b
 75 [-]: LOADK     R7 K7        ; R7 := "Bonus.Amount"
 76 [-]: CONST     R8 2         ; R8 := 2.000000
 77 [-]: NEWTABLE  R9 1 0       ; R9 := {}
 78 [-]: CONST     R10 10       ; R10 := 10.000000
 79 [-]: SETLIST   R9 1 1       ; R9[(1-1)*FPF+i] := R(9+i), 1 <= i <= 1
 80 [-]: NEWTABLE  R10 1 0      ; R10 := {}
 81 [-]: CONST     R11 100      ; R11 := 100.000000
 82 [-]: SETLIST   R10 1 1      ; R10[(1-1)*FPF+i] := R(10+i), 1 <= i <= 1
 83 [-]: LOADK     R11 K6       ; R11 := 0.100000
 84 [-]: LOADK     R12 K6       ; R12 := 0.100000
 85 [-]: CALL      R5 8 1       ; R5(R6,R7,R8,R9,R10,R11,R12)
 86 [-]: GETGLOBAL R5 K3        ; R5 := 0x25312c9b
 87 [-]: GETGLOBAL R6 K0        ; R6 := 0xae91e43b
 88 [-]: LOADK     R7 K2        ; R7 := "Bonus.Buff"
 89 [-]: CONST     R8 2         ; R8 := 2.000000
 90 [-]: NEWTABLE  R9 1 0       ; R9 := {}
 91 [-]: CONST     R10 10       ; R10 := 10.000000
 92 [-]: SETLIST   R9 1 1       ; R9[(1-1)*FPF+i] := R(9+i), 1 <= i <= 1
 93 [-]: NEWTABLE  R10 1 0      ; R10 := {}
 94 [-]: CONST     R11 100      ; R11 := 100.000000
 95 [-]: SETLIST   R10 1 1      ; R10[(1-1)*FPF+i] := R(10+i), 1 <= i <= 1
 96 [-]: LOADK     R11 K17      ; R11 := 0.300000
 97 [-]: LOADK     R12 K18      ; R12 := 0.600000
 98 [-]: CLOSURE   R13 1        ; R13 := closure(Function #8.2)
 99 [-]: CALL      R5 9 1       ; R5(R6,R7,R8,R9,R10,R11,R12,R13)
100 [-]: RETURN    R0 1         ; return 


; Function #8.1:
;
; Name:            
; Defined at line: 128
; #Upvalues:       0
; #Parameters:     0
; Is_vararg:       0
; Max Stack Size:  8

  1 [-]: GETGLOBAL R0 K0        ; R0 := 0x25312c9b
  2 [-]: GETGLOBAL R1 K1        ; R1 := 0xae91e43b
  3 [-]: LOADK     R2 K2        ; R2 := "Bonus"
  4 [-]: CONST     R3 2         ; R3 := 2.000000
  5 [-]: NEWTABLE  R4 1 0       ; R4 := {}
  6 [-]: CONST     R5 10        ; R5 := 10.000000
  7 [-]: SETLIST   R4 1 1       ; R4[(1-1)*FPF+i] := R(4+i), 1 <= i <= 1
  8 [-]: NEWTABLE  R5 1 0       ; R5 := {}
  9 [-]: CONST     R6 0         ; R6 := 0.000000
 10 [-]: SETLIST   R5 1 1       ; R5[(1-1)*FPF+i] := R(5+i), 1 <= i <= 1
 11 [-]: LOADK     R6 K4        ; R6 := 0.200000
 12 [-]: CONST     R7 3         ; R7 := 3.000000
 13 [-]: CALL      R0 8 1       ; R0(R1,R2,R3,R4,R5,R6,R7)
 14 [-]: RETURN    R0 1         ; return 


; Function #8.2:
;
; Name:            
; Defined at line: 141
; #Upvalues:       0
; #Parameters:     0
; Is_vararg:       0
; Max Stack Size:  8

  1 [-]: GETGLOBAL R0 K0        ; R0 := 0x25312c9b
  2 [-]: GETGLOBAL R1 K1        ; R1 := 0xae91e43b
  3 [-]: LOADK     R2 K2        ; R2 := "Bonus.Buff"
  4 [-]: CONST     R3 2         ; R3 := 2.000000
  5 [-]: NEWTABLE  R4 2 0       ; R4 := {}
  6 [-]: CONST     R5 5         ; R5 := 5.000000
  7 [-]: CONST     R6 6         ; R6 := 6.000000
  8 [-]: SETLIST   R4 2 1       ; R4[(1-1)*FPF+i] := R(4+i), 1 <= i <= 2
  9 [-]: NEWTABLE  R5 2 0       ; R5 := {}
 10 [-]: CONST     R6 115       ; R6 := 115.000000
 11 [-]: CONST     R7 115       ; R7 := 115.000000
 12 [-]: SETLIST   R5 2 1       ; R5[(1-1)*FPF+i] := R(5+i), 1 <= i <= 2
 13 [-]: CONST     R6 2         ; R6 := 2.000000
 14 [-]: CALL      R0 7 1       ; R0(R1,R2,R3,R4,R5,R6)
 15 [-]: RETURN    R0 1         ; return 


; Function #9:
;
; Name:            
; Defined at line: 146
; #Upvalues:       22
; #Parameters:     0
; Is_vararg:       0
; Max Stack Size:  20

  1 [-]: GETGLOBAL R0 K0        ; R0 := 0x7b998233
  2 [-]: GETGLOBAL R1 K1        ; R1 := 0xae91e43b
  3 [-]: CALL      R0 2 2       ; R0 := R0(R1)
  4 [-]: TEST      R0 1         ; if R0 then PC := 9
  5 [-]: JMP       9            ; PC := 9
  6 [-]: GETUPVAL  R0 U0        ; R0 := U0
  7 [-]: TEST      R0 1         ; if R0 then PC := 10
  8 [-]: JMP       10           ; PC := 10
  9 [-]: RETURN    R0 1         ; return 
 10 [-]: GETGLOBAL R0 K2        ; R0 := 0x67652851
 11 [-]: CALL      R0 1 2       ; R0 := R0()
 12 [-]: GETGLOBAL R1 K0        ; R1 := 0x7b998233
 13 [-]: GETUPVAL  R2 U1        ; R2 := U1
 14 [-]: CALL      R1 2 2       ; R1 := R1(R2)
 15 [-]: TEST      R1 1         ; if R1 then PC := 21
 16 [-]: JMP       21           ; PC := 21
 17 [-]: GETUPVAL  R1 U1        ; R1 := U1
 18 [-]: SELF      R1 R1 K3     ; R2 := R1; R1 := R1[0xfaa69527]
 19 [-]: MOVE      R3 R0        ; R3 := R0
 20 [-]: CALL      R1 3 1       ; R1(R2,R3)
 21 [-]: GETGLOBAL R1 K1        ; R1 := 0xae91e43b
 22 [-]: SELF      R1 R1 K4     ; R2 := R1; R1 := R1[0x8a8c8d5a]
 23 [-]: MOVE      R3 R0        ; R3 := R0
 24 [-]: CALL      R1 3 1       ; R1(R2,R3)
 25 [-]: GETGLOBAL R1 K0        ; R1 := 0x7b998233
 26 [-]: GETUPVAL  R2 U2        ; R2 := U2
 27 [-]: CALL      R1 2 2       ; R1 := R1(R2)
 28 [-]: TEST      R1 0         ; if not R1 then PC := 34
 29 [-]: JMP       34           ; PC := 34
 30 [-]: GETGLOBAL R1 K5        ; R1 := 0xbe190284
 31 [-]: SELF      R1 R1 K6     ; R2 := R1; R1 := R1[0x33307f92]
 32 [-]: CALL      R1 2 2       ; R1 := R1(R2)
 33 [-]: SETUPVAL  R1 U2        ; U82 := R2
 34 [-]: LOADKB    R1 1 0       ; R1 := true
 35 [-]: SETUPVAL  R1 U3        ; U82 := R3
 36 [-]: GETUPVAL  R1 U4        ; R1 := U4
 37 [-]: LEN       R1 R1        ; R1 := # R1
 38 [-]: LT        0 K7 R1      ; if 0.000000 >= R1 then PC := 59
 39 [-]: JMP       59           ; PC := 59
 40 [-]: CONST     R1 1         ; R1 := 1.000000
 41 [-]: GETUPVAL  R2 U4        ; R2 := U4
 42 [-]: LEN       R2 R2        ; R2 := # R2
 43 [-]: CONST     R3 1         ; R3 := 1.000000
 44 [-]: FORPREP   R1 56        ; R1 -= R3; PC := 56
 45 [-]: GETUPVAL  R5 U4        ; R5 := U4
 46 [-]: GETTABLE  R5 R5 R4     ; R5 := R5[R4]
 47 [-]: GETTABLE  R5 R5 K8     ; R5 := R5[1.000000]
 48 [-]: GETGLOBAL R6 K9        ; R6 := 0x7f896986
 49 [-]: CONST     R7 2         ; R7 := 2.000000
 50 [-]: GETGLOBAL R8 K10       ; R8 := 0x22572a38
 51 [-]: GETUPVAL  R9 U4        ; R9 := U4
 52 [-]: GETTABLE  R9 R9 R4     ; R9 := R9[R4]
 53 [-]: CALL      R8 2 0       ; R8,... := R8(R9)
 54 [-]: CALL      R6 0 0       ; R6,... := R6(R7,...)
 55 [-]: CALL      R5 0 1       ; R5(R6,...)
 56 [-]: FORLOOP   R1 45        ; R1 += R3; if R1 <= R2 then begin PC := 45; R4 := R1 end
 57 [-]: NEWTABLE  R5 0 0       ; R5 := {}
 58 [-]: SETUPVAL  R5 U4        ; U82 := R4
 59 [-]: LOADKB    R5 0 0       ; R5 := false
 60 [-]: SETUPVAL  R5 U3        ; U82 := R3
 61 [-]: LOADNIL   R5 R5        ; R5 := nil
 62 [-]: GETGLOBAL R6 K11       ; R6 := _T
 63 [-]: GETTABLE  R6 R6 K12    ; R6 := R6["monkeyHair"]
 64 [-]: EQ        1 R6 K13     ; if R6 == nil then PC := 92
 65 [-]: JMP       92           ; PC := 92
 66 [-]: GETGLOBAL R6 K14       ; R6 := 0x4ec73e73
 67 [-]: GETGLOBAL R7 K11       ; R7 := _T
 68 [-]: GETTABLE  R7 R7 K12    ; R7 := R7["monkeyHair"]
 69 [-]: CALL      R6 2 2       ; R6 := R6(R7)
 70 [-]: EQ        1 R6 K13     ; if R6 == nil then PC := 92
 71 [-]: JMP       92           ; PC := 92
 72 [-]: GETGLOBAL R6 K15       ; R6 := 0x89326c93
 73 [-]: SELF      R6 R6 K16    ; R7 := R6; R6 := R6[0x78298275]
 74 [-]: CALL      R6 2 2       ; R6 := R6(R7)
 75 [-]: GETGLOBAL R7 K0        ; R7 := 0x7b998233
 76 [-]: MOVE      R8 R6        ; R8 := R6
 77 [-]: CALL      R7 2 2       ; R7 := R7(R8)
 78 [-]: TEST      R7 1         ; if R7 then PC := 92
 79 [-]: JMP       92           ; PC := 92
 80 [-]: SELF      R7 R6 K17    ; R8 := R6; R7 := R6[0x388577d5]
 81 [-]: CALL      R7 2 2       ; R7 := R7(R8)
 82 [-]: GETGLOBAL R8 K0        ; R8 := 0x7b998233
 83 [-]: GETGLOBAL R9 K11       ; R9 := _T
 84 [-]: GETTABLE  R9 R9 K12    ; R9 := R9["monkeyHair"]
 85 [-]: GETTABLE  R9 R9 R7     ; R9 := R9[R7]
 86 [-]: CALL      R8 2 2       ; R8 := R8(R9)
 87 [-]: TEST      R8 1         ; if R8 then PC := 92
 88 [-]: JMP       92           ; PC := 92
 89 [-]: GETGLOBAL R8 K11       ; R8 := _T
 90 [-]: GETTABLE  R8 R8 K12    ; R8 := R8["monkeyHair"]
 91 [-]: GETTABLE  R5 R8 R7     ; R5 := R8[R7]
 92 [-]: GETUPVAL  R8 U5        ; R8 := U5
 93 [-]: EQ        1 R8 R5      ; if R8 == R5 then PC := 210
 94 [-]: JMP       210          ; PC := 210
 95 [-]: SETUPVAL  R5 U5        ; U82 := R5
 96 [-]: GETGLOBAL R8 K0        ; R8 := 0x7b998233
 97 [-]: GETUPVAL  R9 U5        ; R9 := U5
 98 [-]: CALL      R8 2 2       ; R8 := R8(R9)
 99 [-]: NOT       R8 R8        ; R8 :=  R8
100 [-]: SETUPVAL  R8 U6        ; U82 := R6
101 [-]: GETGLOBAL R8 K18       ; R8 := 0x25312c9b
102 [-]: GETGLOBAL R9 K1        ; R9 := 0xae91e43b
103 [-]: LOADK     R10 K19      ; R10 := "Container.HealthDisplay"
104 [-]: CONST     R11 8        ; R11 := 8.000000
105 [-]: NEWTABLE  R12 1 0      ; R12 := {}
106 [-]: CONST     R13 10       ; R13 := 10.000000
107 [-]: SETLIST   R12 1 1      ; R12[(1-1)*FPF+i] := R(12+i), 1 <= i <= 1
108 [-]: NEWTABLE  R13 0 0      ; R13 := {}
109 [-]: GETUPVAL  R14 U7       ; R14 := U7
110 [-]: GETTABLE  R14 R14 K21  ; R14 := R14[0x06d055f9]
111 [-]: GETUPVAL  R15 U6       ; R15 := U6
112 [-]: CONST     R16 100      ; R16 := 100.000000
113 [-]: CONST     R17 0        ; R17 := 0.000000
114 [-]: CALL      R14 4 0      ; R14,... := R14(R15,R16,R17)
115 [-]: SETLIST   R13 0 1      ; R13[(1-1)*FPF+i] := R(13+i), 1 <= i <= 0
116 [-]: LOADK     R14 K22      ; R14 := 0.300000
117 [-]: CALL      R8 7 1       ; R8(R9,R10,R11,R12,R13,R14)
118 [-]: GETGLOBAL R8 K18       ; R8 := 0x25312c9b
119 [-]: GETGLOBAL R9 K1        ; R9 := 0xae91e43b
120 [-]: LOADK     R10 K23      ; R10 := "_root.Container.FuryCounter"
121 [-]: CONST     R11 8        ; R11 := 8.000000
122 [-]: NEWTABLE  R12 2 0      ; R12 := {}
123 [-]: CONST     R13 0        ; R13 := 0.000000
124 [-]: CONST     R14 1        ; R14 := 1.000000
125 [-]: SETLIST   R12 2 1      ; R12[(1-1)*FPF+i] := R(12+i), 1 <= i <= 2
126 [-]: NEWTABLE  R13 2 0      ; R13 := {}
127 [-]: GETUPVAL  R14 U8       ; R14 := U8
128 [-]: GETUPVAL  R15 U7       ; R15 := U7
129 [-]: GETTABLE  R15 R15 K21  ; R15 := R15[0x06d055f9]
130 [-]: GETUPVAL  R16 U6       ; R16 := U6
131 [-]: CONST     R17 -70      ; R17 := -70.000000
132 [-]: CONST     R18 0        ; R18 := 0.000000
133 [-]: CALL      R15 4 2      ; R15 := R15(R16,R17,R18)
134 [-]: ADD       R14 R14 R15  ; R14 := R14 + R15
135 [-]: GETUPVAL  R15 U9       ; R15 := U9
136 [-]: GETUPVAL  R16 U7       ; R16 := U7
137 [-]: GETTABLE  R16 R16 K21  ; R16 := R16[0x06d055f9]
138 [-]: GETUPVAL  R17 U6       ; R17 := U6
139 [-]: CONST     R18 -70      ; R18 := -70.000000
140 [-]: CONST     R19 0        ; R19 := 0.000000
141 [-]: CALL      R16 4 2      ; R16 := R16(R17,R18,R19)
142 [-]: ADD       R15 R15 R16  ; R15 := R15 + R16
143 [-]: SETLIST   R13 2 1      ; R13[(1-1)*FPF+i] := R(13+i), 1 <= i <= 2
144 [-]: LOADK     R14 K22      ; R14 := 0.300000
145 [-]: CALL      R8 7 1       ; R8(R9,R10,R11,R12,R13,R14)
146 [-]: GETUPVAL  R8 U6        ; R8 := U6
147 [-]: TEST      R8 0         ; if not R8 then PC := 210
148 [-]: JMP       210          ; PC := 210
149 [-]: LOADNIL   R8 R8        ; R8 := nil
150 [-]: GETUPVAL  R9 U10       ; R9 := U10
151 [-]: CALL      R9 1 1       ; R9()
152 [-]: GETGLOBAL R9 K0        ; R9 := 0x7b998233
153 [-]: GETUPVAL  R10 U11      ; R10 := U11
154 [-]: CALL      R9 2 2       ; R9 := R9(R10)
155 [-]: TEST      R9 1         ; if R9 then PC := 161
156 [-]: JMP       161          ; PC := 161
157 [-]: GETUPVAL  R9 U11       ; R9 := U11
158 [-]: SELF      R9 R9 K24    ; R10 := R9; R9 := R9[0x056dcf06]
159 [-]: CALL      R9 2 2       ; R9 := R9(R10)
160 [-]: MOVE      R8 R9        ; R8 := R9
161 [-]: GETGLOBAL R9 K1        ; R9 := 0xae91e43b
162 [-]: SELF      R9 R9 K25    ; R10 := R9; R9 := R9[0xaade900e]
163 [-]: LOADK     R11 K26      ; R11 := "Container.HealthDisplay.Icon"
164 [-]: CONST     R12 11       ; R12 := 11.000000
165 [-]: GETGLOBAL R13 K0       ; R13 := 0x7b998233
166 [-]: MOVE      R14 R8       ; R14 := R8
167 [-]: CALL      R13 2 2      ; R13 := R13(R14)
168 [-]: NOT       R13 R13      ; R13 :=  R13
169 [-]: CALL      R9 5 1       ; R9(R10,R11,R12,R13)
170 [-]: GETGLOBAL R9 K0        ; R9 := 0x7b998233
171 [-]: MOVE      R10 R8       ; R10 := R8
172 [-]: CALL      R9 2 2       ; R9 := R9(R10)
173 [-]: TEST      R9 1         ; if R9 then PC := 180
174 [-]: JMP       180          ; PC := 180
175 [-]: GETGLOBAL R9 K1        ; R9 := 0xae91e43b
176 [-]: SELF      R9 R9 K27    ; R10 := R9; R9 := R9[0x1cb415c1]
177 [-]: LOADK     R11 K26      ; R11 := "Container.HealthDisplay.Icon"
178 [-]: MOVE      R12 R8       ; R12 := R8
179 [-]: CALL      R9 4 1       ; R9(R10,R11,R12)
180 [-]: GETGLOBAL R9 K0        ; R9 := 0x7b998233
181 [-]: GETUPVAL  R10 U12      ; R10 := U12
182 [-]: CALL      R9 2 2       ; R9 := R9(R10)
183 [-]: TEST      R9 0         ; if not R9 then PC := 199
184 [-]: JMP       199          ; PC := 199
185 [-]: CONST     R9 3         ; R9 := 3.000000
186 [-]: GETGLOBAL R10 K15      ; R10 := 0x89326c93
187 [-]: SELF      R10 R10 K29  ; R11 := R10; R10 := R10[0x18d05d30]
188 [-]: CALL      R10 2 2      ; R10 := R10(R11)
189 [-]: TEST      R10 1        ; if R10 then PC := 192
190 [-]: JMP       192          ; PC := 192
191 [-]: CONST     R9 4         ; R9 := 4.000000
192 [-]: GETGLOBAL R10 K15      ; R10 := 0x89326c93
193 [-]: SELF      R10 R10 K30  ; R11 := R10; R10 := R10[0x765dad71]
194 [-]: GETUPVAL  R12 U13      ; R12 := U13
195 [-]: LOADNIL   R13 R13      ; R13 := nil
196 [-]: MOVE      R14 R9       ; R14 := R9
197 [-]: CALL      R10 5 2      ; R10 := R10(R11,R12,R13,R14)
198 [-]: SETUPVAL  R10 U12      ; U82 := R12
199 [-]: GETUPVAL  R10 U12      ; R10 := U12
200 [-]: SELF      R10 R10 K31  ; R11 := R10; R10 := R10[0xffbddf1b]
201 [-]: GETGLOBAL R12 K1       ; R12 := 0xae91e43b
202 [-]: GETUPVAL  R13 U5       ; R13 := U5
203 [-]: CONST     R14 160      ; R14 := 160.000000
204 [-]: LOADK     R15 K32      ; R15 := "Container.HealthDisplay.Target"
205 [-]: LOADK     R16 K33      ; R16 := "Container.HealthDisplay.Value"
206 [-]: CALL      R10 7 1      ; R10(R11,R12,R13,R14,R15,R16)
207 [-]: GETUPVAL  R10 U12      ; R10 := U12
208 [-]: SELF      R10 R10 K34  ; R11 := R10; R10 := R10[0x687ae094]
209 [-]: CALL      R10 2 1      ; R10(R11)
210 [-]: GETUPVAL  R10 U6       ; R10 := U6
211 [-]: TEST      R10 0        ; if not R10 then PC := 222
212 [-]: JMP       222          ; PC := 222
213 [-]: GETGLOBAL R10 K0       ; R10 := 0x7b998233
214 [-]: GETUPVAL  R11 U12      ; R11 := U12
215 [-]: CALL      R10 2 2      ; R10 := R10(R11)
216 [-]: TEST      R10 1        ; if R10 then PC := 222
217 [-]: JMP       222          ; PC := 222
218 [-]: GETUPVAL  R10 U12      ; R10 := U12
219 [-]: SELF      R10 R10 K3   ; R11 := R10; R10 := R10[0xfaa69527]
220 [-]: MOVE      R12 R0       ; R12 := R0
221 [-]: CALL      R10 3 1      ; R10(R11,R12)
222 [-]: GETGLOBAL R10 K0       ; R10 := 0x7b998233
223 [-]: GETUPVAL  R11 U2       ; R11 := U2
224 [-]: CALL      R10 2 2      ; R10 := R10(R11)
225 [-]: TEST      R10 1        ; if R10 then PC := 242
226 [-]: JMP       242          ; PC := 242
227 [-]: GETUPVAL  R10 U2       ; R10 := U2
228 [-]: SELF      R10 R10 K35  ; R11 := R10; R10 := R10[0x91a24e4b]
229 [-]: LOADK     R12 K36      ; R12 := "_root"
230 [-]: CONST     R13 10       ; R13 := 10.000000
231 [-]: CALL      R10 4 2      ; R10 := R10(R11,R12,R13)
232 [-]: GETUPVAL  R11 U14      ; R11 := U14
233 [-]: EQ        1 R11 R10    ; if R11 == R10 then PC := 242
234 [-]: JMP       242          ; PC := 242
235 [-]: SETUPVAL  R10 U14      ; U82 := R14
236 [-]: GETGLOBAL R11 K1       ; R11 := 0xae91e43b
237 [-]: SELF      R11 R11 K37  ; R12 := R11; R11 := R11[0x67bc869f]
238 [-]: LOADK     R13 K36      ; R13 := "_root"
239 [-]: CONST     R14 10       ; R14 := 10.000000
240 [-]: MOVE      R15 R10      ; R15 := R10
241 [-]: CALL      R11 5 1      ; R11(R12,R13,R14,R15)
242 [-]: GETUPVAL  R11 U15      ; R11 := U15
243 [-]: CALL      R11 1 2      ; R11 := R11()
244 [-]: TEST      R11 0        ; if not R11 then PC := 273
245 [-]: JMP       273          ; PC := 273
246 [-]: GETUPVAL  R11 U16      ; R11 := U16
247 [-]: CALL      R11 1 2      ; R11 := R11()
248 [-]: TEST      R11 1        ; if R11 then PC := 260
249 [-]: JMP       260          ; PC := 260
250 [-]: GETGLOBAL R11 K1       ; R11 := 0xae91e43b
251 [-]: SELF      R11 R11 K38  ; R12 := R11; R11 := R11[0xd4cc05b4]
252 [-]: CALL      R11 2 2      ; R11 := R11(R12)
253 [-]: TEST      R11 0        ; if not R11 then PC := 260
254 [-]: JMP       260          ; PC := 260
255 [-]: GETGLOBAL R11 K1       ; R11 := 0xae91e43b
256 [-]: SELF      R11 R11 K39  ; R12 := R11; R11 := R11[0x368ad758]
257 [-]: LOADKB    R13 0 0      ; R13 := false
258 [-]: CALL      R11 3 1      ; R11(R12,R13)
259 [-]: JMP       273          ; PC := 273
260 [-]: GETUPVAL  R11 U16      ; R11 := U16
261 [-]: CALL      R11 1 2      ; R11 := R11()
262 [-]: TEST      R11 0        ; if not R11 then PC := 273
263 [-]: JMP       273          ; PC := 273
264 [-]: GETGLOBAL R11 K1       ; R11 := 0xae91e43b
265 [-]: SELF      R11 R11 K38  ; R12 := R11; R11 := R11[0xd4cc05b4]
266 [-]: CALL      R11 2 2      ; R11 := R11(R12)
267 [-]: TEST      R11 1        ; if R11 then PC := 273
268 [-]: JMP       273          ; PC := 273
269 [-]: GETGLOBAL R11 K1       ; R11 := 0xae91e43b
270 [-]: SELF      R11 R11 K39  ; R12 := R11; R11 := R11[0x368ad758]
271 [-]: LOADKB    R13 1 0      ; R13 := true
272 [-]: CALL      R11 3 1      ; R11(R12,R13)
273 [-]: GETUPVAL  R11 U18      ; R11 := U18
274 [-]: GETTABLE  R11 R11 K40  ; R11 := R11[0x0cad99b9]
275 [-]: GETGLOBAL R12 K1       ; R12 := 0xae91e43b
276 [-]: LOADK     R13 K41      ; R13 := "Container"
277 [-]: GETUPVAL  R14 U19      ; R14 := U19
278 [-]: GETUPVAL  R15 U17      ; R15 := U17
279 [-]: GETUPVAL  R16 U20      ; R16 := U20
280 [-]: GETUPVAL  R17 U21      ; R17 := U21
281 [-]: CALL      R11 7 2      ; R11 := R11(R12,R13,R14,R15,R16,R17)
282 [-]: SETUPVAL  R11 U17      ; U82 := R17
283 [-]: RETURN    R0 1         ; return 


; Function #10:
;
; Name:            
; Defined at line: 233
; #Upvalues:       2
; #Parameters:     1
; Is_vararg:       3
; Max Stack Size:  7

  1 [-]: GETUPVAL  R2 U0        ; R2 := U0
  2 [-]: TEST      R2 0         ; if not R2 then PC := 8
  3 [-]: JMP       8            ; PC := 8
  4 [-]: MOVE      R2 R0        ; R2 := R0
  5 [-]: VARARG    R3 0         ; R3 := ...
  6 [-]: CALL      R2 0 1       ; R2(R3,...)
  7 [-]: JMP       16           ; PC := 16
  8 [-]: GETGLOBAL R2 K0        ; R2 := 0x33bdd652
  9 [-]: GETTABLE  R2 R2 K1     ; R2 := R2[0x23d5322f]
 10 [-]: GETUPVAL  R3 U1        ; R3 := U1
 11 [-]: NEWTABLE  R4 1 0       ; R4 := {}
 12 [-]: MOVE      R5 R0        ; R5 := R0
 13 [-]: VARARG    R6 0         ; R6 := ...
 14 [-]: SETLIST   R4 0 1       ; R4[(1-1)*FPF+i] := R(4+i), 1 <= i <= 0
 15 [-]: CALL      R2 3 1       ; R2(R3,R4)
 16 [-]: RETURN    R0 1         ; return 


; Function #11:
;
; Name:            
; Defined at line: 241
; #Upvalues:       1
; #Parameters:     0
; Is_vararg:       0
; Max Stack Size:  5

  1 [-]: GETGLOBAL R0 K0        ; R0 := _T
  2 [-]: SETTABLE  R0 K1 K2     ; R0["WUKONG_StartTimer"] := nil
  3 [-]: GETGLOBAL R0 K0        ; R0 := _T
  4 [-]: SETTABLE  R0 K3 K2     ; R0["WUKONG_OnTimerEnd"] := nil
  5 [-]: GETGLOBAL R0 K0        ; R0 := _T
  6 [-]: SETTABLE  R0 K4 K2     ; R0["WUKONG_SetMeter"] := nil
  7 [-]: GETGLOBAL R0 K0        ; R0 := _T
  8 [-]: SETTABLE  R0 K5 K2     ; R0["WUKONG_SetMeterValue"] := nil
  9 [-]: GETGLOBAL R0 K0        ; R0 := _T
 10 [-]: SETTABLE  R0 K6 K2     ; R0["WUKONG_ShowBonus"] := nil
 11 [-]: GETGLOBAL R0 K0        ; R0 := _T
 12 [-]: SETTABLE  R0 K7 K2     ; R0["WUKONG_ShowPassiveMessage"] := nil
 13 [-]: GETGLOBAL R0 K8        ; R0 := 0x7b998233
 14 [-]: GETUPVAL  R1 U0        ; R1 := U0
 15 [-]: CALL      R0 2 2       ; R0 := R0(R1)
 16 [-]: TEST      R0 1         ; if R0 then PC := 22
 17 [-]: JMP       22           ; PC := 22
 18 [-]: GETGLOBAL R0 K9        ; R0 := 0x89326c93
 19 [-]: SELF      R0 R0 K10    ; R1 := R0; R0 := R0[0x59c96e77]
 20 [-]: GETUPVAL  R2 U0        ; R2 := U0
 21 [-]: CALL      R0 3 1       ; R0(R1,R2)
 22 [-]: GETGLOBAL R0 K8        ; R0 := 0x7b998233
 23 [-]: GETGLOBAL R1 K0        ; R1 := _T
 24 [-]: GETTABLE  R1 R1 K11    ; R1 := R1["HUD_RemoveMotionClip"]
 25 [-]: CALL      R0 2 2       ; R0 := R0(R1)
 26 [-]: TEST      R0 1         ; if R0 then PC := 33
 27 [-]: JMP       33           ; PC := 33
 28 [-]: GETGLOBAL R0 K0        ; R0 := _T
 29 [-]: GETTABLE  R0 R0 K12    ; R0 := R0[0x564984b8]
 30 [-]: GETGLOBAL R1 K13       ; R1 := 0xae91e43b
 31 [-]: LOADK     R2 K14       ; R2 := "Container"
 32 [-]: CALL      R0 3 1       ; R0(R1,R2)
 33 [-]: GETGLOBAL R0 K8        ; R0 := 0x7b998233
 34 [-]: GETGLOBAL R1 K0        ; R1 := _T
 35 [-]: GETTABLE  R1 R1 K15    ; R1 := R1["HUD_GetAnchorMgr"]
 36 [-]: CALL      R0 2 2       ; R0 := R0(R1)
 37 [-]: TEST      R0 1         ; if R0 then PC := 60
 38 [-]: JMP       60           ; PC := 60
 39 [-]: GETGLOBAL R0 K0        ; R0 := _T
 40 [-]: GETTABLE  R0 R0 K16    ; R0 := R0[0xf6b77431]
 41 [-]: CALL      R0 1 2       ; R0 := R0()
 42 [-]: EQ        1 R0 K2      ; if R0 == nil then PC := 60
 43 [-]: JMP       60           ; PC := 60
 44 [-]: SELF      R1 R0 K17    ; R2 := R0; R1 := R0[0x7f19c438]
 45 [-]: GETGLOBAL R3 K13       ; R3 := 0xae91e43b
 46 [-]: LOADK     R4 K14       ; R4 := "Container"
 47 [-]: CALL      R1 4 1       ; R1(R2,R3,R4)
 48 [-]: SELF      R1 R0 K17    ; R2 := R0; R1 := R0[0x7f19c438]
 49 [-]: GETGLOBAL R3 K13       ; R3 := 0xae91e43b
 50 [-]: LOADK     R4 K18       ; R4 := "CloudTimer"
 51 [-]: CALL      R1 4 1       ; R1(R2,R3,R4)
 52 [-]: SELF      R1 R0 K17    ; R2 := R0; R1 := R0[0x7f19c438]
 53 [-]: GETGLOBAL R3 K13       ; R3 := 0xae91e43b
 54 [-]: LOADK     R4 K19       ; R4 := "Bonus"
 55 [-]: CALL      R1 4 1       ; R1(R2,R3,R4)
 56 [-]: SELF      R1 R0 K17    ; R2 := R0; R1 := R0[0x7f19c438]
 57 [-]: GETGLOBAL R3 K13       ; R3 := 0xae91e43b
 58 [-]: LOADK     R4 K20       ; R4 := "Message"
 59 [-]: CALL      R1 4 1       ; R1(R2,R3,R4)
 60 [-]: RETURN    R0 1         ; return 


; Function #12:
;
; Name:            
; Defined at line: 267
; #Upvalues:       2
; #Parameters:     1
; Is_vararg:       0
; Max Stack Size:  11

  1 [-]: GETUPVAL  R1 U0        ; R1 := U0
  2 [-]: LT        1 K0 R0      ; if 0.000000 < R0 then PC := 5
  3 [-]: JMP       5            ; PC := 5
  4 [-]: LOADKB    R2 0 1       ; R2 := false; PC := 5
  5 [-]: LOADKB    R2 1 0       ; R2 := true
  6 [-]: EQ        1 R1 R2      ; if R1 == R2 then PC := 28
  7 [-]: JMP       28           ; PC := 28
  8 [-]: GETUPVAL  R1 U0        ; R1 := U0
  9 [-]: NOT       R1 R1        ; R1 :=  R1
 10 [-]: SETUPVAL  R1 U0        ; U82 := R0
 11 [-]: GETGLOBAL R1 K1        ; R1 := 0x25312c9b
 12 [-]: GETGLOBAL R2 K2        ; R2 := 0xae91e43b
 13 [-]: LOADK     R3 K3        ; R3 := "Container.FuryCounter"
 14 [-]: CONST     R4 2         ; R4 := 2.000000
 15 [-]: NEWTABLE  R5 1 0       ; R5 := {}
 16 [-]: CONST     R6 10        ; R6 := 10.000000
 17 [-]: SETLIST   R5 1 1       ; R5[(1-1)*FPF+i] := R(5+i), 1 <= i <= 1
 18 [-]: NEWTABLE  R6 0 0       ; R6 := {}
 19 [-]: GETUPVAL  R7 U1        ; R7 := U1
 20 [-]: GETTABLE  R7 R7 K5     ; R7 := R7[0x06d055f9]
 21 [-]: GETUPVAL  R8 U0        ; R8 := U0
 22 [-]: CONST     R9 100       ; R9 := 100.000000
 23 [-]: CONST     R10 0        ; R10 := 0.000000
 24 [-]: CALL      R7 4 0       ; R7,... := R7(R8,R9,R10)
 25 [-]: SETLIST   R6 0 1       ; R6[(1-1)*FPF+i] := R(6+i), 1 <= i <= 0
 26 [-]: CONST     R7 0         ; R7 := 0.250000
 27 [-]: CALL      R1 7 1       ; R1(R2,R3,R4,R5,R6,R7)
 28 [-]: MUL       R1 K6 R0     ; R1 := 10.000000 * R0
 29 [-]: ADD       R1 K7 R1     ; R1 := 45.000000 + R1
 30 [-]: GETGLOBAL R2 K2        ; R2 := 0xae91e43b
 31 [-]: SELF      R2 R2 K8     ; R3 := R2; R2 := R2[0x67bc869f]
 32 [-]: LOADK     R4 K9        ; R4 := "Container.FuryCounter.Icon"
 33 [-]: CONST     R5 5         ; R5 := 5.000000
 34 [-]: MOVE      R6 R1        ; R6 := R1
 35 [-]: CALL      R2 5 1       ; R2(R3,R4,R5,R6)
 36 [-]: GETGLOBAL R2 K2        ; R2 := 0xae91e43b
 37 [-]: SELF      R2 R2 K8     ; R3 := R2; R2 := R2[0x67bc869f]
 38 [-]: LOADK     R4 K9        ; R4 := "Container.FuryCounter.Icon"
 39 [-]: CONST     R5 6         ; R5 := 6.000000
 40 [-]: MOVE      R6 R1        ; R6 := R1
 41 [-]: CALL      R2 5 1       ; R2(R3,R4,R5,R6)
 42 [-]: GETGLOBAL R2 K2        ; R2 := 0xae91e43b
 43 [-]: SELF      R2 R2 K10    ; R3 := R2; R2 := R2[0x91e13703]
 44 [-]: LOADK     R4 K11       ; R4 := "Container.FuryCounter.Progress"
 45 [-]: LOADK     R5 K12       ; R5 := "AlphaTestThreshold"
 46 [-]: MOVE      R6 R0        ; R6 := R0
 47 [-]: CONST     R7 0         ; R7 := 0.000000
 48 [-]: CONST     R8 0         ; R8 := 0.000000
 49 [-]: CONST     R9 0         ; R9 := 0.000000
 50 [-]: CALL      R2 8 1       ; R2(R3,R4,R5,R6,R7,R8,R9)
 51 [-]: RETURN    R0 1         ; return 


; Function #13:
;
; Name:            
; Defined at line: 280
; #Upvalues:       3
; #Parameters:     1
; Is_vararg:       0
; Max Stack Size:  7

  1 [-]: GETUPVAL  R1 U0        ; R1 := U0
  2 [-]: EQ        0 R1 R0      ; if R1 ~= R0 then PC := 5
  3 [-]: JMP       5            ; PC := 5
  4 [-]: RETURN    R0 1         ; return 
  5 [-]: SETUPVAL  R0 U0        ; U82 := R0
  6 [-]: LOADK     R1 K0        ; R1 := ""
  7 [-]: LT        0 K1 R0      ; if 0.000000 >= R0 then PC := 19
  8 [-]: JMP       19           ; PC := 19
  9 [-]: LOADK     R2 K2        ; R2 := "<p><font size=\"18\"><b>"
 10 [-]: GETUPVAL  R3 U1        ; R3 := U1
 11 [-]: GETTABLE  R3 R3 K3     ; R3 := R3[0x1142c7a8]
 12 [-]: MOVE      R4 R0        ; R4 := R0
 13 [-]: CONST     R5 0         ; R5 := 0.000000
 14 [-]: CALL      R3 3 2       ; R3 := R3(R4,R5)
 15 [-]: LOADK     R4 K4        ; R4 := "</b><br>"
 16 [-]: GETUPVAL  R5 U2        ; R5 := U2
 17 [-]: LOADK     R6 K5        ; R6 := "</font></p>"
 18 [-]: CONCAT    R1 R2 R6     ; R1 := R2 .. R3 .. R4 .. R5 .. R6
 19 [-]: GETGLOBAL R2 K6        ; R2 := 0xae91e43b
 20 [-]: SELF      R2 R2 K7     ; R3 := R2; R2 := R2[0x5f56eeab]
 21 [-]: LOADK     R4 K8        ; R4 := "Container.FuryCounter.Label"
 22 [-]: CONST     R5 29        ; R5 := 29.000000
 23 [-]: MOVE      R6 R1        ; R6 := R1
 24 [-]: CALL      R2 5 1       ; R2(R3,R4,R5,R6)
 25 [-]: RETURN    R0 1         ; return 


; Function #14:
;
; Name:            
; Defined at line: 294
; #Upvalues:       1
; #Parameters:     0
; Is_vararg:       0
; Max Stack Size:  11

  1 [-]: CONST     R0 1         ; R0 := 1.000000
  2 [-]: CONST     R1 5         ; R1 := 5.000000
  3 [-]: CONST     R2 1         ; R2 := 1.000000
  4 [-]: FORPREP   R0 43        ; R0 -= R2; PC := 43
  5 [-]: LOADK     R4 K0        ; R4 := "Message.Icon"
  6 [-]: MOVE      R5 R3        ; R5 := R3
  7 [-]: CONCAT    R4 R4 R5     ; R4 := R4 .. R5
  8 [-]: GETGLOBAL R5 K1        ; R5 := 0xae91e43b
  9 [-]: SELF      R5 R5 K2     ; R6 := R5; R5 := R5[0xa7ec3e8a]
 10 [-]: MOVE      R7 R4        ; R7 := R4
 11 [-]: CALL      R5 3 2       ; R5 := R5(R6,R7)
 12 [-]: TEST      R5 1         ; if R5 then PC := 25
 13 [-]: JMP       25           ; PC := 25
 14 [-]: GETGLOBAL R5 K3        ; R5 := 0x015284cd
 15 [-]: LOADK     R6 K4        ; R6 := "."
 16 [-]: MOVE      R7 R4        ; R7 := R4
 17 [-]: CALL      R5 3 2       ; R5 := R5(R6,R7)
 18 [-]: GETGLOBAL R6 K5        ; R6 := 0x38f10e85
 19 [-]: GETGLOBAL R7 K1        ; R7 := 0xae91e43b
 20 [-]: LOADK     R8 K6        ; R8 := "Message.Icon1.duplicateMovieClip"
 21 [-]: LEN       R9 R5        ; R9 := # R5
 22 [-]: GETTABLE  R9 R5 R9     ; R9 := R5[R9]
 23 [-]: ADD       R10 K7 R3    ; R10 := 1000.000000 + R3
 24 [-]: CALL      R6 5 1       ; R6(R7,R8,R9,R10)
 25 [-]: GETGLOBAL R6 K1        ; R6 := 0xae91e43b
 26 [-]: SELF      R6 R6 K8     ; R7 := R6; R6 := R6[0xef99134f]
 27 [-]: MOVE      R8 R4        ; R8 := R4
 28 [-]: LOADK     R9 K9        ; R9 := ".Container.IconLeft"
 29 [-]: CONCAT    R8 R8 R9     ; R8 := R8 .. R9
 30 [-]: GETGLOBAL R9 K10       ; R9 := 0xe9622c6b
 31 [-]: GETTABLE  R9 R9 R3     ; R9 := R9[R3]
 32 [-]: GETGLOBAL R10 K11      ; R10 := 0x90921a0f
 33 [-]: CALL      R6 5 1       ; R6(R7,R8,R9,R10)
 34 [-]: GETGLOBAL R6 K1        ; R6 := 0xae91e43b
 35 [-]: SELF      R6 R6 K8     ; R7 := R6; R6 := R6[0xef99134f]
 36 [-]: MOVE      R8 R4        ; R8 := R4
 37 [-]: LOADK     R9 K12       ; R9 := ".Container.IconRight"
 38 [-]: CONCAT    R8 R8 R9     ; R8 := R8 .. R9
 39 [-]: GETGLOBAL R9 K10       ; R9 := 0xe9622c6b
 40 [-]: GETTABLE  R9 R9 R3     ; R9 := R9[R3]
 41 [-]: GETGLOBAL R10 K13      ; R10 := 0x219f3ff2
 42 [-]: CALL      R6 5 1       ; R6(R7,R8,R9,R10)
 43 [-]: FORLOOP   R0 5         ; R0 += R2; if R0 <= R1 then begin PC := 5; R3 := R0 end
 44 [-]: GETGLOBAL R6 K1        ; R6 := 0xae91e43b
 45 [-]: SELF      R6 R6 K14    ; R7 := R6; R6 := R6[0x67bc869f]
 46 [-]: LOADK     R8 K15       ; R8 := "Message"
 47 [-]: CONST     R9 10        ; R9 := 10.000000
 48 [-]: CONST     R10 0        ; R10 := 0.000000
 49 [-]: CALL      R6 5 1       ; R6(R7,R8,R9,R10)
 50 [-]: GETGLOBAL R6 K1        ; R6 := 0xae91e43b
 51 [-]: SELF      R6 R6 K14    ; R7 := R6; R6 := R6[0x67bc869f]
 52 [-]: LOADK     R8 K16       ; R8 := "Message.Flare"
 53 [-]: CONST     R9 10        ; R9 := 10.000000
 54 [-]: CONST     R10 0        ; R10 := 0.000000
 55 [-]: CALL      R6 5 1       ; R6(R7,R8,R9,R10)
 56 [-]: GETGLOBAL R6 K1        ; R6 := 0xae91e43b
 57 [-]: SELF      R6 R6 K17    ; R7 := R6; R6 := R6[0x5f56eeab]
 58 [-]: LOADK     R8 K18       ; R8 := "Message.HowMany"
 59 [-]: CONST     R9 29        ; R9 := 29.000000
 60 [-]: CONST     R10 5        ; R10 := 5.000000
 61 [-]: CALL      R6 5 1       ; R6(R7,R8,R9,R10)
 62 [-]: GETGLOBAL R6 K1        ; R6 := 0xae91e43b
 63 [-]: SELF      R6 R6 K19    ; R7 := R6; R6 := R6[0x20b98db3]
 64 [-]: LOADK     R8 K20       ; R8 := "Message.Title.text"
 65 [-]: LOADK     R9 K21       ; R9 := "/Lotus/Language/Suits/WukongPassiveAbilityName"
 66 [-]: CALL      R6 4 1       ; R6(R7,R8,R9)
 67 [-]: NEWTABLE  R6 0 0       ; R6 := {}
 68 [-]: SETUPVAL  R6 U0        ; U82 := R0
 69 [-]: GETUPVAL  R6 U0        ; R6 := U0
 70 [-]: SETTABLE  R6 K22 K23   ; R6[1.000000] := "/Lotus/Language/Suits/WukongPassiveAbilitySubhuti"
 71 [-]: GETUPVAL  R6 U0        ; R6 := U0
 72 [-]: SETTABLE  R6 K24 K25   ; R6[2.000000] := "/Lotus/Language/Suits/WukongPassiveAbilityBook"
 73 [-]: GETUPVAL  R6 U0        ; R6 := U0
 74 [-]: SETTABLE  R6 K26 K27   ; R6[3.000000] := "/Lotus/Language/Suits/WukongPassiveAbilityPeach"
 75 [-]: GETUPVAL  R6 U0        ; R6 := U0
 76 [-]: SETTABLE  R6 K28 K29   ; R6[4.000000] := "/Lotus/Language/Suits/WukongPassiveAbilityWine"
 77 [-]: GETUPVAL  R6 U0        ; R6 := U0
 78 [-]: SETTABLE  R6 K30 K31   ; R6[5.000000] := "/Lotus/Language/Suits/WukongPassiveAbilityPills"
 79 [-]: RETURN    R0 1         ; return 


; Function #15:
;
; Name:            
; Defined at line: 318
; #Upvalues:       3
; #Parameters:     2
; Is_vararg:       0
; Max Stack Size:  17

  1 [-]: LOADK     R2 K0        ; R2 := "Message.Icon"
  2 [-]: MOVE      R3 R0        ; R3 := R0
  3 [-]: LOADK     R4 K1        ; R4 := ".Container"
  4 [-]: CONCAT    R2 R2 R4     ; R2 := R2 .. R3 .. R4
  5 [-]: GETGLOBAL R3 K2        ; R3 := 0xae91e43b
  6 [-]: SELF      R3 R3 K3     ; R4 := R3; R3 := R3[0xf64b7262]
  7 [-]: MOVE      R5 R2        ; R5 := R2
  8 [-]: LOADK     R6 K4        ; R6 := "IconLeft"
  9 [-]: CONST     R7 0         ; R7 := 0.000000
 10 [-]: CONST     R8 2         ; R8 := 2.000000
 11 [-]: CALL      R3 6 1       ; R3(R4,R5,R6,R7,R8)
 12 [-]: GETGLOBAL R3 K2        ; R3 := 0xae91e43b
 13 [-]: SELF      R3 R3 K3     ; R4 := R3; R3 := R3[0xf64b7262]
 14 [-]: MOVE      R5 R2        ; R5 := R2
 15 [-]: LOADK     R6 K5        ; R6 := "IconRight"
 16 [-]: CONST     R7 0         ; R7 := 0.000000
 17 [-]: CONST     R8 -2        ; R8 := -2.000000
 18 [-]: CALL      R3 6 1       ; R3(R4,R5,R6,R7,R8)
 19 [-]: LT        0 K6 R1      ; if 0.000000 >= R1 then PC := 38
 20 [-]: JMP       38           ; PC := 38
 21 [-]: GETUPVAL  R3 U0        ; R3 := U0
 22 [-]: GETTABLE  R3 R3 K7     ; R3 := R3[0xf76783e5]
 23 [-]: GETGLOBAL R4 K2        ; R4 := 0xae91e43b
 24 [-]: MOVE      R5 R2        ; R5 := R2
 25 [-]: GETGLOBAL R6 K8        ; R6 := 0x1c140aff
 26 [-]: CONST     R7 0         ; R7 := 0.000000
 27 [-]: CONST     R8 0         ; R8 := 0.000000
 28 [-]: CALL      R3 6 2       ; R3 := R3(R4,R5,R6,R7,R8)
 29 [-]: GETGLOBAL R4 K9        ; R4 := 0x7b998233
 30 [-]: MOVE      R5 R3        ; R5 := R3
 31 [-]: CALL      R4 2 2       ; R4 := R4(R5)
 32 [-]: TEST      R4 1         ; if R4 then PC := 38
 33 [-]: JMP       38           ; PC := 38
 34 [-]: SELF      R4 R3 K10    ; R5 := R3; R4 := R3[0x8feccd8b]
 35 [-]: GETUPVAL  R6 U1        ; R6 := U1
 36 [-]: GETUPVAL  R7 U1        ; R7 := U1
 37 [-]: CALL      R4 4 1       ; R4(R5,R6,R7)
 38 [-]: GETGLOBAL R4 K11       ; R4 := 0x25312c9b
 39 [-]: GETGLOBAL R5 K2        ; R5 := 0xae91e43b
 40 [-]: MOVE      R6 R2        ; R6 := R2
 41 [-]: LOADK     R7 K12       ; R7 := ".IconLeft"
 42 [-]: CONCAT    R6 R6 R7     ; R6 := R6 .. R7
 43 [-]: CONST     R7 0         ; R7 := 0.000000
 44 [-]: NEWTABLE  R8 2 0       ; R8 := {}
 45 [-]: CLOSURE   R9 0         ; R9 := closure(Function #15.1)
 46 [-]: MOVE      R0 R2        ; R0 := R2
 47 [-]: LOADK     R10 K14      ; R10 := "_alpha"
 48 [-]: SETLIST   R8 2 1       ; R8[(1-1)*FPF+i] := R(8+i), 1 <= i <= 2
 49 [-]: NEWTABLE  R9 2 0       ; R9 := {}
 50 [-]: CONST     R10 1        ; R10 := 1.000000
 51 [-]: CONST     R11 75       ; R11 := 75.000000
 52 [-]: SETLIST   R9 2 1       ; R9[(1-1)*FPF+i] := R(9+i), 1 <= i <= 2
 53 [-]: MOVE      R10 R1       ; R10 := R1
 54 [-]: MOVE      R11 R1       ; R11 := R1
 55 [-]: CALL      R4 8 1       ; R4(R5,R6,R7,R8,R9,R10,R11)
 56 [-]: GETGLOBAL R4 K11       ; R4 := 0x25312c9b
 57 [-]: GETGLOBAL R5 K2        ; R5 := 0xae91e43b
 58 [-]: MOVE      R6 R2        ; R6 := R2
 59 [-]: LOADK     R7 K15       ; R7 := ".IconRight"
 60 [-]: CONCAT    R6 R6 R7     ; R6 := R6 .. R7
 61 [-]: CONST     R7 0         ; R7 := 0.000000
 62 [-]: NEWTABLE  R8 2 0       ; R8 := {}
 63 [-]: CLOSURE   R9 1         ; R9 := closure(Function #15.2)
 64 [-]: MOVE      R0 R2        ; R0 := R2
 65 [-]: LOADK     R10 K14      ; R10 := "_alpha"
 66 [-]: SETLIST   R8 2 1       ; R8[(1-1)*FPF+i] := R(8+i), 1 <= i <= 2
 67 [-]: NEWTABLE  R9 2 0       ; R9 := {}
 68 [-]: CONST     R10 1        ; R10 := 1.000000
 69 [-]: CONST     R11 75       ; R11 := 75.000000
 70 [-]: SETLIST   R9 2 1       ; R9[(1-1)*FPF+i] := R(9+i), 1 <= i <= 2
 71 [-]: MOVE      R10 R1       ; R10 := R1
 72 [-]: MOVE      R11 R1       ; R11 := R1
 73 [-]: CLOSURE   R12 2        ; R12 := closure(Function #15.3)
 74 [-]: MOVE      R0 R2        ; R0 := R2
 75 [-]: GETUPVAL  R0 U1        ; R0 := U1
 76 [-]: GETUPVAL  R0 U2        ; R0 := U2
 77 [-]: MOVE      R0 R0        ; R0 := R0
 78 [-]: MOVE      R0 R1        ; R0 := R1
 79 [-]: CALL      R4 9 1       ; R4(R5,R6,R7,R8,R9,R10,R11,R12)
 80 [-]: LT        0 K6 R1      ; if 0.000000 >= R1 then PC := 134
 81 [-]: JMP       134          ; PC := 134
 82 [-]: GETUPVAL  R4 U0        ; R4 := U0
 83 [-]: GETTABLE  R4 R4 K16    ; R4 := R4[0xb5be5d4a]
 84 [-]: GETGLOBAL R5 K2        ; R5 := 0xae91e43b
 85 [-]: MOVE      R6 R2        ; R6 := R2
 86 [-]: CALL      R4 3 3       ; R4,R5 := R4(R5,R6)
 87 [-]: GETUPVAL  R6 U0        ; R6 := U0
 88 [-]: GETTABLE  R6 R6 K16    ; R6 := R6[0xb5be5d4a]
 89 [-]: GETGLOBAL R7 K2        ; R7 := 0xae91e43b
 90 [-]: LOADK     R8 K17       ; R8 := "Message"
 91 [-]: CALL      R6 3 3       ; R6,R7 := R6(R7,R8)
 92 [-]: GETGLOBAL R8 K2        ; R8 := 0xae91e43b
 93 [-]: SELF      R8 R8 K18    ; R9 := R8; R8 := R8[0x67bc869f]
 94 [-]: LOADK     R10 K19      ; R10 := "Message.Flare"
 95 [-]: CONST     R11 0        ; R11 := 0.000000
 96 [-]: SUB       R12 R4 R6    ; R12 := R4 - R6
 97 [-]: CALL      R8 5 1       ; R8(R9,R10,R11,R12)
 98 [-]: GETGLOBAL R8 K2        ; R8 := 0xae91e43b
 99 [-]: SELF      R8 R8 K18    ; R9 := R8; R8 := R8[0x67bc869f]
100 [-]: LOADK     R10 K19      ; R10 := "Message.Flare"
101 [-]: CONST     R11 1        ; R11 := 1.000000
102 [-]: SUB       R12 R5 R7    ; R12 := R5 - R7
103 [-]: CALL      R8 5 1       ; R8(R9,R10,R11,R12)
104 [-]: GETGLOBAL R8 K2        ; R8 := 0xae91e43b
105 [-]: SELF      R8 R8 K18    ; R9 := R8; R8 := R8[0x67bc869f]
106 [-]: LOADK     R10 K19      ; R10 := "Message.Flare"
107 [-]: CONST     R11 5        ; R11 := 5.000000
108 [-]: CONST     R12 30       ; R12 := 30.000000
109 [-]: CALL      R8 5 1       ; R8(R9,R10,R11,R12)
110 [-]: GETGLOBAL R8 K2        ; R8 := 0xae91e43b
111 [-]: SELF      R8 R8 K18    ; R9 := R8; R8 := R8[0x67bc869f]
112 [-]: LOADK     R10 K19      ; R10 := "Message.Flare"
113 [-]: CONST     R11 6        ; R11 := 6.000000
114 [-]: CONST     R12 40       ; R12 := 40.000000
115 [-]: CALL      R8 5 1       ; R8(R9,R10,R11,R12)
116 [-]: GETGLOBAL R8 K11       ; R8 := 0x25312c9b
117 [-]: GETGLOBAL R9 K2        ; R9 := 0xae91e43b
118 [-]: LOADK     R10 K19      ; R10 := "Message.Flare"
119 [-]: CONST     R11 2        ; R11 := 2.000000
120 [-]: NEWTABLE  R12 3 0      ; R12 := {}
121 [-]: CONST     R13 5        ; R13 := 5.000000
122 [-]: CONST     R14 6        ; R14 := 6.000000
123 [-]: CONST     R15 10       ; R15 := 10.000000
124 [-]: SETLIST   R12 3 1      ; R12[(1-1)*FPF+i] := R(12+i), 1 <= i <= 3
125 [-]: NEWTABLE  R13 3 0      ; R13 := {}
126 [-]: CONST     R14 50       ; R14 := 50.000000
127 [-]: CONST     R15 50       ; R15 := 50.000000
128 [-]: CONST     R16 100      ; R16 := 100.000000
129 [-]: SETLIST   R13 3 1      ; R13[(1-1)*FPF+i] := R(13+i), 1 <= i <= 3
130 [-]: CONST     R14 0        ; R14 := 0.250000
131 [-]: CONST     R15 0        ; R15 := 0.000000
132 [-]: CLOSURE   R16 3        ; R16 := closure(Function #15.4)
133 [-]: CALL      R8 9 1       ; R8(R9,R10,R11,R12,R13,R14,R15,R16)
134 [-]: RETURN    R0 1         ; return 


; Function #15.1:
;
; Name:            
; Defined at line: 330
; #Upvalues:       1
; #Parameters:     1
; Is_vararg:       0
; Max Stack Size:  10

  1 [-]: GETGLOBAL R1 K0        ; R1 := 0xae91e43b
  2 [-]: SELF      R1 R1 K1     ; R2 := R1; R1 := R1[0xf64b7262]
  3 [-]: GETUPVAL  R3 U0        ; R3 := U0
  4 [-]: LOADK     R4 K2        ; R4 := "IconLeft"
  5 [-]: CONST     R5 0         ; R5 := 0.000000
  6 [-]: GETGLOBAL R6 K3        ; R6 := 0x9bafffe3
  7 [-]: CONST     R7 2         ; R7 := 2.000000
  8 [-]: CONST     R8 10        ; R8 := 10.000000
  9 [-]: MOVE      R9 R0        ; R9 := R0
 10 [-]: CALL      R6 4 0       ; R6,... := R6(R7,R8,R9)
 11 [-]: CALL      R1 0 1       ; R1(R2,...)
 12 [-]: GETGLOBAL R1 K0        ; R1 := 0xae91e43b
 13 [-]: SELF      R1 R1 K1     ; R2 := R1; R1 := R1[0xf64b7262]
 14 [-]: GETUPVAL  R3 U0        ; R3 := U0
 15 [-]: LOADK     R4 K2        ; R4 := "IconLeft"
 16 [-]: CONST     R5 1         ; R5 := 1.000000
 17 [-]: GETGLOBAL R6 K3        ; R6 := 0x9bafffe3
 18 [-]: CONST     R7 0         ; R7 := 0.000000
 19 [-]: CONST     R8 -7        ; R8 := -7.000000
 20 [-]: MOVE      R9 R0        ; R9 := R0
 21 [-]: CALL      R6 4 0       ; R6,... := R6(R7,R8,R9)
 22 [-]: CALL      R1 0 1       ; R1(R2,...)
 23 [-]: RETURN    R0 1         ; return 


; Function #15.2:
;
; Name:            
; Defined at line: 335
; #Upvalues:       1
; #Parameters:     1
; Is_vararg:       0
; Max Stack Size:  10

  1 [-]: GETGLOBAL R1 K0        ; R1 := 0xae91e43b
  2 [-]: SELF      R1 R1 K1     ; R2 := R1; R1 := R1[0xf64b7262]
  3 [-]: GETUPVAL  R3 U0        ; R3 := U0
  4 [-]: LOADK     R4 K2        ; R4 := "IconRight"
  5 [-]: CONST     R5 0         ; R5 := 0.000000
  6 [-]: GETGLOBAL R6 K3        ; R6 := 0x9bafffe3
  7 [-]: CONST     R7 -2        ; R7 := -2.000000
  8 [-]: CONST     R8 -10       ; R8 := -10.000000
  9 [-]: MOVE      R9 R0        ; R9 := R0
 10 [-]: CALL      R6 4 0       ; R6,... := R6(R7,R8,R9)
 11 [-]: CALL      R1 0 1       ; R1(R2,...)
 12 [-]: GETGLOBAL R1 K0        ; R1 := 0xae91e43b
 13 [-]: SELF      R1 R1 K1     ; R2 := R1; R1 := R1[0xf64b7262]
 14 [-]: GETUPVAL  R3 U0        ; R3 := U0
 15 [-]: LOADK     R4 K2        ; R4 := "IconRight"
 16 [-]: CONST     R5 1         ; R5 := 1.000000
 17 [-]: GETGLOBAL R6 K3        ; R6 := 0x9bafffe3
 18 [-]: CONST     R7 0         ; R7 := 0.000000
 19 [-]: CONST     R8 7         ; R8 := 7.000000
 20 [-]: MOVE      R9 R0        ; R9 := R0
 21 [-]: CALL      R6 4 0       ; R6,... := R6(R7,R8,R9)
 22 [-]: CALL      R1 0 1       ; R1(R2,...)
 23 [-]: RETURN    R0 1         ; return 


; Function #15.3:
;
; Name:            
; Defined at line: 339
; #Upvalues:       5
; #Parameters:     0
; Is_vararg:       0
; Max Stack Size:  7

  1 [-]: GETGLOBAL R0 K0        ; R0 := 0x25312c9b
  2 [-]: GETGLOBAL R1 K1        ; R1 := 0xae91e43b
  3 [-]: GETUPVAL  R2 U0        ; R2 := U0
  4 [-]: LOADK     R3 K2        ; R3 := ".IconRight"
  5 [-]: CONCAT    R2 R2 R3     ; R2 := R2 .. R3
  6 [-]: CONST     R3 2         ; R3 := 2.000000
  7 [-]: NEWTABLE  R4 1 0       ; R4 := {}
  8 [-]: CLOSURE   R5 0         ; R5 := closure(Function #15.3.1)
  9 [-]: GETUPVAL  R0 U1        ; R0 := U1
 10 [-]: GETUPVAL  R0 U2        ; R0 := U2
 11 [-]: GETUPVAL  R0 U3        ; R0 := U3
 12 [-]: SETLIST   R4 1 1       ; R4[(1-1)*FPF+i] := R(4+i), 1 <= i <= 1
 13 [-]: NEWTABLE  R5 1 0       ; R5 := {}
 14 [-]: CONST     R6 1         ; R6 := 1.000000
 15 [-]: SETLIST   R5 1 1       ; R5[(1-1)*FPF+i] := R(5+i), 1 <= i <= 1
 16 [-]: GETUPVAL  R6 U4        ; R6 := U4
 17 [-]: CALL      R0 7 1       ; R0(R1,R2,R3,R4,R5,R6)
 18 [-]: RETURN    R0 1         ; return 


; Function #15.3.1:
;
; Name:            
; Defined at line: 341
; #Upvalues:       3
; #Parameters:     1
; Is_vararg:       0
; Max Stack Size:  8

  1 [-]: GETGLOBAL R1 K0        ; R1 := 0x60130201
  2 [-]: GETGLOBAL R2 K1        ; R2 := 0x9bafffe3
  3 [-]: GETUPVAL  R3 U0        ; R3 := U0
  4 [-]: GETTABLE  R3 R3 K2     ; R3 := R3["red"]
  5 [-]: GETUPVAL  R4 U1        ; R4 := U1
  6 [-]: GETTABLE  R4 R4 K2     ; R4 := R4["red"]
  7 [-]: MOVE      R5 R0        ; R5 := R0
  8 [-]: CALL      R2 4 2       ; R2 := R2(R3,R4,R5)
  9 [-]: GETGLOBAL R3 K1        ; R3 := 0x9bafffe3
 10 [-]: GETUPVAL  R4 U0        ; R4 := U0
 11 [-]: GETTABLE  R4 R4 K3     ; R4 := R4["green"]
 12 [-]: GETUPVAL  R5 U1        ; R5 := U1
 13 [-]: GETTABLE  R5 R5 K3     ; R5 := R5["green"]
 14 [-]: MOVE      R6 R0        ; R6 := R0
 15 [-]: CALL      R3 4 2       ; R3 := R3(R4,R5,R6)
 16 [-]: GETGLOBAL R4 K1        ; R4 := 0x9bafffe3
 17 [-]: GETUPVAL  R5 U0        ; R5 := U0
 18 [-]: GETTABLE  R5 R5 K4     ; R5 := R5["blue"]
 19 [-]: GETUPVAL  R6 U1        ; R6 := U1
 20 [-]: GETTABLE  R6 R6 K4     ; R6 := R6["blue"]
 21 [-]: MOVE      R7 R0        ; R7 := R0
 22 [-]: CALL      R4 4 0       ; R4,... := R4(R5,R6,R7)
 23 [-]: CALL      R1 0 2       ; R1 := R1(R2,...)
 24 [-]: GETGLOBAL R2 K5        ; R2 := 0xae91e43b
 25 [-]: SELF      R2 R2 K6     ; R3 := R2; R2 := R2[0x67bc869f]
 26 [-]: LOADK     R4 K7        ; R4 := "Message.Icon"
 27 [-]: GETUPVAL  R5 U2        ; R5 := U2
 28 [-]: CONCAT    R4 R4 R5     ; R4 := R4 .. R5
 29 [-]: CONST     R5 9         ; R5 := 9.000000
 30 [-]: SELF      R6 R1 K8     ; R7 := R1; R6 := R1[0xa5d5c8f6]
 31 [-]: CALL      R6 2 0       ; R6,... := R6(R7)
 32 [-]: CALL      R2 0 1       ; R2(R3,...)
 33 [-]: RETURN    R0 1         ; return 


; Function #15.4:
;
; Name:            
; Defined at line: 355
; #Upvalues:       0
; #Parameters:     0
; Is_vararg:       0
; Max Stack Size:  8

  1 [-]: GETGLOBAL R0 K0        ; R0 := 0x25312c9b
  2 [-]: GETGLOBAL R1 K1        ; R1 := 0xae91e43b
  3 [-]: LOADK     R2 K2        ; R2 := "Message.Flare"
  4 [-]: CONST     R3 0         ; R3 := 0.000000
  5 [-]: NEWTABLE  R4 2 0       ; R4 := {}
  6 [-]: CONST     R5 5         ; R5 := 5.000000
  7 [-]: CONST     R6 10        ; R6 := 10.000000
  8 [-]: SETLIST   R4 2 1       ; R4[(1-1)*FPF+i] := R(4+i), 1 <= i <= 2
  9 [-]: NEWTABLE  R5 2 0       ; R5 := {}
 10 [-]: CONST     R6 80        ; R6 := 80.000000
 11 [-]: CONST     R7 0         ; R7 := 0.000000
 12 [-]: SETLIST   R5 2 1       ; R5[(1-1)*FPF+i] := R(5+i), 1 <= i <= 2
 13 [-]: LOADK     R6 K4        ; R6 := 0.650000
 14 [-]: CALL      R0 7 1       ; R0(R1,R2,R3,R4,R5,R6)
 15 [-]: RETURN    R0 1         ; return 


; Function #16:
;
; Name:            
; Defined at line: 361
; #Upvalues:       5
; #Parameters:     2
; Is_vararg:       0
; Max Stack Size:  24

  1 [-]: GETGLOBAL R2 K0        ; R2 := 0x89326c93
  2 [-]: SELF      R2 R2 K1     ; R3 := R2; R2 := R2[0xfb64e76c]
  3 [-]: CALL      R2 2 2       ; R2 := R2(R3)
  4 [-]: GETGLOBAL R3 K2        ; R3 := 0x7b998233
  5 [-]: MOVE      R4 R2        ; R4 := R2
  6 [-]: CALL      R3 2 2       ; R3 := R3(R4)
  7 [-]: TEST      R3 0         ; if not R3 then PC := 10
  8 [-]: JMP       10           ; PC := 10
  9 [-]: RETURN    R0 1         ; return 
 10 [-]: SELF      R3 R2 K3     ; R4 := R2; R3 := R2[0xbb610e5b]
 11 [-]: CALL      R3 2 2       ; R3 := R3(R4)
 12 [-]: GETGLOBAL R4 K2        ; R4 := 0x7b998233
 13 [-]: MOVE      R5 R3        ; R5 := R3
 14 [-]: CALL      R4 2 2       ; R4 := R4(R5)
 15 [-]: TEST      R4 0         ; if not R4 then PC := 18
 16 [-]: JMP       18           ; PC := 18
 17 [-]: RETURN    R0 1         ; return 
 18 [-]: SELF      R4 R2 K4     ; R5 := R2; R4 := R2[0x0b4bcfb6]
 19 [-]: CALL      R4 2 2       ; R4 := R4(R5)
 20 [-]: GETGLOBAL R5 K2        ; R5 := 0x7b998233
 21 [-]: MOVE      R6 R4        ; R6 := R4
 22 [-]: CALL      R5 2 2       ; R5 := R5(R6)
 23 [-]: TEST      R5 0         ; if not R5 then PC := 26
 24 [-]: JMP       26           ; PC := 26
 25 [-]: RETURN    R0 1         ; return 
 26 [-]: GETUPVAL  R5 U0        ; R5 := U0
 27 [-]: GETTABLE  R5 R5 K5     ; R5 := R5[0x659d451f]
 28 [-]: GETGLOBAL R6 K6        ; R6 := 0x455810e2
 29 [-]: CALL      R5 2 1       ; R5(R6)
 30 [-]: SELF      R5 R4 K7     ; R6 := R4; R5 := R4[0xb1c85409]
 31 [-]: SELF      R7 R3 K8     ; R8 := R3; R7 := R3[0xebfba9e4]
 32 [-]: CALL      R7 2 2       ; R7 := R7(R8)
 33 [-]: CONST     R8 -1        ; R8 := -1.000000
 34 [-]: CONST     R9 50        ; R9 := 50.000000
 35 [-]: CONST     R10 0        ; R10 := 0.000000
 36 [-]: CALL      R5 6 1       ; R5(R6,R7,R8,R9,R10)
 37 [-]: CLOSURE   R5 0         ; R5 := closure(Function #16.1)
 38 [-]: MOVE      R0 R4        ; R0 := R4
 39 [-]: GETGLOBAL R6 K9        ; R6 := 0x25312c9b
 40 [-]: GETGLOBAL R7 K10       ; R7 := 0xae91e43b
 41 [-]: LOADK     R8 K11       ; R8 := "Message"
 42 [-]: CONST     R9 2         ; R9 := 2.000000
 43 [-]: NEWTABLE  R10 2 0      ; R10 := {}
 44 [-]: LOADK     R11 K13      ; R11 := "_alpha"
 45 [-]: CLOSURE   R12 1        ; R12 := closure(Function #16.2)
 46 [-]: MOVE      R0 R5        ; R0 := R5
 47 [-]: SETLIST   R10 2 1      ; R10[(1-1)*FPF+i] := R(10+i), 1 <= i <= 2
 48 [-]: NEWTABLE  R11 2 0      ; R11 := {}
 49 [-]: CONST     R12 100      ; R12 := 100.000000
 50 [-]: CONST     R13 1        ; R13 := 1.000000
 51 [-]: SETLIST   R11 2 1      ; R11[(1-1)*FPF+i] := R(11+i), 1 <= i <= 2
 52 [-]: LOADK     R12 K14      ; R12 := 0.200000
 53 [-]: CONST     R13 0        ; R13 := 0.000000
 54 [-]: CLOSURE   R14 2        ; R14 := closure(Function #16.3)
 55 [-]: MOVE      R0 R5        ; R0 := R5
 56 [-]: GETUPVAL  R0 U0        ; R0 := U0
 57 [-]: CALL      R6 9 1       ; R6(R7,R8,R9,R10,R11,R12,R13,R14)
 58 [-]: LOADNIL   R6 R6        ; R6 := nil
 59 [-]: CONST     R7 15        ; R7 := 15.000000
 60 [-]: UNM       R8 R7        ; R8 :=  R7
 61 [-]: MUL       R8 R8 K15    ; R8 := R8 * 2.000000
 62 [-]: MUL       R8 R8 K16    ; R8 := R8 * 0.500000
 63 [-]: CONST     R9 0         ; R9 := 0.000000
 64 [-]: CONST     R10 0        ; R10 := 0.000000
 65 [-]: CONST     R11 1        ; R11 := 1.000000
 66 [-]: CONST     R12 5        ; R12 := 5.000000
 67 [-]: CONST     R13 1        ; R13 := 1.000000
 68 [-]: FORPREP   R11 137      ; R11 -= R13; PC := 137
 69 [-]: LOADK     R15 K17      ; R15 := "Message.Icon"
 70 [-]: MOVE      R16 R14      ; R16 := R14
 71 [-]: CONCAT    R6 R15 R16   ; R6 := R15 .. R16
 72 [-]: GETTABLE  R15 R1 R14   ; R15 := R1[R14]
 73 [-]: EQ        0 R15 K18    ; if R15 ~= nil then PC := 82
 74 [-]: JMP       82           ; PC := 82
 75 [-]: GETGLOBAL R15 K10      ; R15 := 0xae91e43b
 76 [-]: SELF      R15 R15 K19  ; R16 := R15; R15 := R15[0xaade900e]
 77 [-]: MOVE      R17 R6       ; R17 := R6
 78 [-]: CONST     R18 11       ; R18 := 11.000000
 79 [-]: LOADKB    R19 0 0      ; R19 := false
 80 [-]: CALL      R15 5 1      ; R15(R16,R17,R18,R19)
 81 [-]: JMP       137          ; PC := 137
 82 [-]: ADD       R10 R10 K20  ; R10 := R10 + 1.000000
 83 [-]: GETGLOBAL R15 K10      ; R15 := 0xae91e43b
 84 [-]: SELF      R15 R15 K21  ; R16 := R15; R15 := R15[0x67bc869f]
 85 [-]: MOVE      R17 R6       ; R17 := R6
 86 [-]: CONST     R18 14       ; R18 := 14.000000
 87 [-]: CONST     R19 0        ; R19 := 0.000000
 88 [-]: CALL      R15 5 1      ; R15(R16,R17,R18,R19)
 89 [-]: GETGLOBAL R15 K9       ; R15 := 0x25312c9b
 90 [-]: GETGLOBAL R16 K10      ; R16 := 0xae91e43b
 91 [-]: MOVE      R17 R6       ; R17 := R6
 92 [-]: CONST     R18 4        ; R18 := 4.000000
 93 [-]: NEWTABLE  R19 1 0      ; R19 := {}
 94 [-]: CONST     R20 14       ; R20 := 14.000000
 95 [-]: SETLIST   R19 1 1      ; R19[(1-1)*FPF+i] := R(19+i), 1 <= i <= 1
 96 [-]: NEWTABLE  R20 1 0      ; R20 := {}
 97 [-]: MOVE      R21 R8       ; R21 := R8
 98 [-]: SETLIST   R20 1 1      ; R20[(1-1)*FPF+i] := R(20+i), 1 <= i <= 1
 99 [-]: GETGLOBAL R21 K22      ; R21 := 0x5bced4c4
100 [-]: GETTABLE  R21 R21 K23  ; R21 := R21[0xe4a5b3ca]
101 [-]: SUB       R22 R10 K15  ; R22 := R10 - 2.000000
102 [-]: MUL       R22 K24 R22  ; R22 := 0.600000 * R22
103 [-]: CALL      R21 2 2      ; R21 := R21(R22)
104 [-]: LOADK     R22 K14      ; R22 := 0.200000
105 [-]: CALL      R15 8 1      ; R15(R16,R17,R18,R19,R20,R21,R22)
106 [-]: GETGLOBAL R15 K9       ; R15 := 0x25312c9b
107 [-]: GETGLOBAL R16 K10      ; R16 := 0xae91e43b
108 [-]: MOVE      R17 R6       ; R17 := R6
109 [-]: LOADK     R18 K25      ; R18 := ".Container"
110 [-]: CONCAT    R17 R17 R18  ; R17 := R17 .. R18
111 [-]: CONST     R18 4        ; R18 := 4.000000
112 [-]: NEWTABLE  R19 1 0      ; R19 := {}
113 [-]: CONST     R20 14       ; R20 := 14.000000
114 [-]: SETLIST   R19 1 1      ; R19[(1-1)*FPF+i] := R(19+i), 1 <= i <= 1
115 [-]: NEWTABLE  R20 1 0      ; R20 := {}
116 [-]: UNM       R21 R8       ; R21 :=  R8
117 [-]: SETLIST   R20 1 1      ; R20[(1-1)*FPF+i] := R(20+i), 1 <= i <= 1
118 [-]: GETGLOBAL R21 K22      ; R21 := 0x5bced4c4
119 [-]: GETTABLE  R21 R21 K23  ; R21 := R21[0xe4a5b3ca]
120 [-]: SUB       R22 R10 K15  ; R22 := R10 - 2.000000
121 [-]: MUL       R22 K24 R22  ; R22 := 0.600000 * R22
122 [-]: CALL      R21 2 2      ; R21 := R21(R22)
123 [-]: LOADK     R22 K14      ; R22 := 0.200000
124 [-]: CALL      R15 8 1      ; R15(R16,R17,R18,R19,R20,R21,R22)
125 [-]: ADD       R8 R8 R7     ; R8 := R8 + R7
126 [-]: GETTABLE  R15 R1 R14   ; R15 := R1[R14]
127 [-]: TEST      R15 0        ; if not R15 then PC := 131
128 [-]: JMP       131          ; PC := 131
129 [-]: ADD       R9 R9 K20    ; R9 := R9 + 1.000000
130 [-]: JMP       137          ; PC := 137
131 [-]: EQ        1 R14 R0     ; if R14 == R0 then PC := 137
132 [-]: JMP       137          ; PC := 137
133 [-]: GETUPVAL  R15 U1       ; R15 := U1
134 [-]: MOVE      R16 R14      ; R16 := R14
135 [-]: CONST     R17 0        ; R17 := 0.000000
136 [-]: CALL      R15 3 1      ; R15(R16,R17)
137 [-]: FORLOOP   R11 69       ; R11 += R13; if R11 <= R12 then begin PC := 69; R14 := R11 end
138 [-]: GETGLOBAL R15 K10      ; R15 := 0xae91e43b
139 [-]: SELF      R15 R15 K26  ; R16 := R15; R15 := R15[0x5f56eeab]
140 [-]: LOADK     R17 K27      ; R17 := "Message.HowMany"
141 [-]: CONST     R18 29       ; R18 := 29.000000
142 [-]: ADD       R19 R9 K20   ; R19 := R9 + 1.000000
143 [-]: CALL      R15 5 1      ; R15(R16,R17,R18,R19)
144 [-]: GETGLOBAL R15 K10      ; R15 := 0xae91e43b
145 [-]: SELF      R15 R15 K28  ; R16 := R15; R15 := R15[0x20b98db3]
146 [-]: LOADK     R17 K29      ; R17 := "Message.Effect.text"
147 [-]: GETUPVAL  R18 U2       ; R18 := U2
148 [-]: GETTABLE  R18 R18 R0   ; R18 := R18[R0]
149 [-]: CALL      R15 4 1      ; R15(R16,R17,R18)
150 [-]: GETGLOBAL R15 K10      ; R15 := 0xae91e43b
151 [-]: SELF      R15 R15 K21  ; R16 := R15; R15 := R15[0x67bc869f]
152 [-]: LOADK     R17 K30      ; R17 := "Message.Effect"
153 [-]: CONST     R18 10       ; R18 := 10.000000
154 [-]: CONST     R19 0        ; R19 := 0.000000
155 [-]: CALL      R15 5 1      ; R15(R16,R17,R18,R19)
156 [-]: GETGLOBAL R15 K10      ; R15 := 0xae91e43b
157 [-]: SELF      R15 R15 K21  ; R16 := R15; R15 := R15[0x67bc869f]
158 [-]: LOADK     R17 K27      ; R17 := "Message.HowMany"
159 [-]: CONST     R18 10       ; R18 := 10.000000
160 [-]: CONST     R19 0        ; R19 := 0.000000
161 [-]: CALL      R15 5 1      ; R15(R16,R17,R18,R19)
162 [-]: GETGLOBAL R15 K10      ; R15 := 0xae91e43b
163 [-]: SELF      R15 R15 K21  ; R16 := R15; R15 := R15[0x67bc869f]
164 [-]: LOADK     R17 K31      ; R17 := "Message.Title"
165 [-]: CONST     R18 10       ; R18 := 10.000000
166 [-]: CONST     R19 0        ; R19 := 0.000000
167 [-]: CALL      R15 5 1      ; R15(R16,R17,R18,R19)
168 [-]: GETGLOBAL R15 K9       ; R15 := 0x25312c9b
169 [-]: GETGLOBAL R16 K10      ; R16 := 0xae91e43b
170 [-]: LOADK     R17 K27      ; R17 := "Message.HowMany"
171 [-]: CONST     R18 0        ; R18 := 0.000000
172 [-]: NEWTABLE  R19 1 0      ; R19 := {}
173 [-]: CONST     R20 10       ; R20 := 10.000000
174 [-]: SETLIST   R19 1 1      ; R19[(1-1)*FPF+i] := R(19+i), 1 <= i <= 1
175 [-]: NEWTABLE  R20 1 0      ; R20 := {}
176 [-]: CONST     R21 100      ; R21 := 100.000000
177 [-]: SETLIST   R20 1 1      ; R20[(1-1)*FPF+i] := R(20+i), 1 <= i <= 1
178 [-]: LOADK     R21 K14      ; R21 := 0.200000
179 [-]: LOADK     R22 K32      ; R22 := 0.150000
180 [-]: CALL      R15 8 1      ; R15(R16,R17,R18,R19,R20,R21,R22)
181 [-]: GETGLOBAL R15 K9       ; R15 := 0x25312c9b
182 [-]: GETGLOBAL R16 K10      ; R16 := 0xae91e43b
183 [-]: LOADK     R17 K31      ; R17 := "Message.Title"
184 [-]: CONST     R18 0        ; R18 := 0.000000
185 [-]: NEWTABLE  R19 1 0      ; R19 := {}
186 [-]: CONST     R20 10       ; R20 := 10.000000
187 [-]: SETLIST   R19 1 1      ; R19[(1-1)*FPF+i] := R(19+i), 1 <= i <= 1
188 [-]: NEWTABLE  R20 1 0      ; R20 := {}
189 [-]: CONST     R21 100      ; R21 := 100.000000
190 [-]: SETLIST   R20 1 1      ; R20[(1-1)*FPF+i] := R(20+i), 1 <= i <= 1
191 [-]: LOADK     R21 K14      ; R21 := 0.200000
192 [-]: LOADK     R22 K33      ; R22 := 0.350000
193 [-]: CLOSURE   R23 3        ; R23 := closure(Function #16.4)
194 [-]: GETUPVAL  R0 U3        ; R0 := U3
195 [-]: MOVE      R0 R9        ; R0 := R9
196 [-]: CALL      R15 9 1      ; R15(R16,R17,R18,R19,R20,R21,R22,R23)
197 [-]: GETUPVAL  R15 U3       ; R15 := U3
198 [-]: SELF      R15 R15 K34  ; R16 := R15; R15 := R15[0xbd2e96ea]
199 [-]: CONST     R17 1        ; R17 := 1.500000
200 [-]: CLOSURE   R18 4        ; R18 := closure(Function #16.5)
201 [-]: GETUPVAL  R0 U0        ; R0 := U0
202 [-]: MOVE      R0 R0        ; R0 := R0
203 [-]: GETUPVAL  R0 U4        ; R0 := U4
204 [-]: GETUPVAL  R0 U3        ; R0 := U3
205 [-]: GETUPVAL  R0 U1        ; R0 := U1
206 [-]: CALL      R15 4 1      ; R15(R16,R17,R18)
207 [-]: RETURN    R0 1         ; return 


; Function #16.1:
;
; Name:            
; Defined at line: 382
; #Upvalues:       1
; #Parameters:     1
; Is_vararg:       0
; Max Stack Size:  9

  1 [-]: GETGLOBAL R1 K0        ; R1 := 0x7b998233
  2 [-]: GETUPVAL  R2 U0        ; R2 := U0
  3 [-]: CALL      R1 2 2       ; R1 := R1(R2)
  4 [-]: TEST      R1 1         ; if R1 then PC := 18
  5 [-]: JMP       18           ; PC := 18
  6 [-]: GETUPVAL  R1 U0        ; R1 := U0
  7 [-]: SELF      R1 R1 K1     ; R2 := R1; R1 := R1[0x47de28d6]
  8 [-]: GETGLOBAL R3 K2        ; R3 := 0x9bafffe3
  9 [-]: LOADK     R4 K3        ; R4 := 0.550000
 10 [-]: CONST     R5 1         ; R5 := 1.000000
 11 [-]: GETGLOBAL R6 K4        ; R6 := 0x5bced4c4
 12 [-]: GETTABLE  R6 R6 K5     ; R6 := R6[0xac1b386a]
 13 [-]: MUL       R7 R0 K6     ; R7 := R0 * 2.000000
 14 [-]: CONST     R8 1         ; R8 := 1.000000
 15 [-]: CALL      R6 3 0       ; R6,... := R6(R7,R8)
 16 [-]: CALL      R3 0 0       ; R3,... := R3(R4,...)
 17 [-]: CALL      R1 0 1       ; R1(R2,...)
 18 [-]: RETURN    R0 1         ; return 


; Function #16.2:
;
; Name:            
; Defined at line: 388
; #Upvalues:       1
; #Parameters:     1
; Is_vararg:       0
; Max Stack Size:  3

  1 [-]: GETUPVAL  R1 U0        ; R1 := U0
  2 [-]: SUB       R2 K0 R0     ; R2 := 1.000000 - R0
  3 [-]: CALL      R1 2 1       ; R1(R2)
  4 [-]: RETURN    R0 1         ; return 


; Function #16.3:
;
; Name:            
; Defined at line: 389
; #Upvalues:       2
; #Parameters:     0
; Is_vararg:       0
; Max Stack Size:  9

  1 [-]: GETGLOBAL R0 K0        ; R0 := 0x25312c9b
  2 [-]: GETGLOBAL R1 K1        ; R1 := 0xae91e43b
  3 [-]: LOADK     R2 K2        ; R2 := "Message"
  4 [-]: CONST     R3 0         ; R3 := 0.000000
  5 [-]: NEWTABLE  R4 1 0       ; R4 := {}
  6 [-]: GETUPVAL  R5 U0        ; R5 := U0
  7 [-]: SETLIST   R4 1 1       ; R4[(1-1)*FPF+i] := R(4+i), 1 <= i <= 1
  8 [-]: NEWTABLE  R5 1 0       ; R5 := {}
  9 [-]: CONST     R6 1         ; R6 := 1.000000
 10 [-]: SETLIST   R5 1 1       ; R5[(1-1)*FPF+i] := R(5+i), 1 <= i <= 1
 11 [-]: CONST     R6 6         ; R6 := 6.000000
 12 [-]: CONST     R7 0         ; R7 := 0.000000
 13 [-]: CLOSURE   R8 0         ; R8 := closure(Function #16.3.1)
 14 [-]: GETUPVAL  R0 U1        ; R0 := U1
 15 [-]: CALL      R0 9 1       ; R0(R1,R2,R3,R4,R5,R6,R7,R8)
 16 [-]: RETURN    R0 1         ; return 


; Function #16.3.1:
;
; Name:            
; Defined at line: 391
; #Upvalues:       1
; #Parameters:     0
; Is_vararg:       0
; Max Stack Size:  7

  1 [-]: GETUPVAL  R0 U0        ; R0 := U0
  2 [-]: GETTABLE  R0 R0 K0     ; R0 := R0[0x659d451f]
  3 [-]: GETGLOBAL R1 K1        ; R1 := 0x8888c92a
  4 [-]: CALL      R0 2 1       ; R0(R1)
  5 [-]: GETGLOBAL R0 K2        ; R0 := 0x25312c9b
  6 [-]: GETGLOBAL R1 K3        ; R1 := 0xae91e43b
  7 [-]: LOADK     R2 K4        ; R2 := "Message"
  8 [-]: CONST     R3 0         ; R3 := 0.000000
  9 [-]: NEWTABLE  R4 1 0       ; R4 := {}
 10 [-]: CONST     R5 10        ; R5 := 10.000000
 11 [-]: SETLIST   R4 1 1       ; R4[(1-1)*FPF+i] := R(4+i), 1 <= i <= 1
 12 [-]: NEWTABLE  R5 1 0       ; R5 := {}
 13 [-]: CONST     R6 0         ; R6 := 0.000000
 14 [-]: SETLIST   R5 1 1       ; R5[(1-1)*FPF+i] := R(5+i), 1 <= i <= 1
 15 [-]: LOADK     R6 K6        ; R6 := 0.450000
 16 [-]: CALL      R0 7 1       ; R0(R1,R2,R3,R4,R5,R6)
 17 [-]: RETURN    R0 1         ; return 


; Function #16.4:
;
; Name:            
; Defined at line: 432
; #Upvalues:       2
; #Parameters:     0
; Is_vararg:       0
; Max Stack Size:  4

  1 [-]: GETUPVAL  R0 U0        ; R0 := U0
  2 [-]: SELF      R0 R0 K0     ; R1 := R0; R0 := R0[0xbd2e96ea]
  3 [-]: CONST     R2 1         ; R2 := 1.750000
  4 [-]: CLOSURE   R3 0         ; R3 := closure(Function #16.4.1)
  5 [-]: GETUPVAL  R0 U1        ; R0 := U1
  6 [-]: CALL      R0 4 1       ; R0(R1,R2,R3)
  7 [-]: RETURN    R0 1         ; return 


; Function #16.4.1:
;
; Name:            
; Defined at line: 434
; #Upvalues:       1
; #Parameters:     0
; Is_vararg:       0
; Max Stack Size:  7

  1 [-]: GETGLOBAL R0 K0        ; R0 := 0xae91e43b
  2 [-]: SELF      R0 R0 K1     ; R1 := R0; R0 := R0[0x5f56eeab]
  3 [-]: LOADK     R2 K2        ; R2 := "Message.HowMany"
  4 [-]: CONST     R3 29        ; R3 := 29.000000
  5 [-]: GETUPVAL  R4 U0        ; R4 := U0
  6 [-]: CALL      R0 5 1       ; R0(R1,R2,R3,R4)
  7 [-]: GETGLOBAL R0 K3        ; R0 := 0x25312c9b
  8 [-]: GETGLOBAL R1 K0        ; R1 := 0xae91e43b
  9 [-]: LOADK     R2 K4        ; R2 := "Message.Title"
 10 [-]: CONST     R3 0         ; R3 := 0.000000
 11 [-]: NEWTABLE  R4 1 0       ; R4 := {}
 12 [-]: CONST     R5 10        ; R5 := 10.000000
 13 [-]: SETLIST   R4 1 1       ; R4[(1-1)*FPF+i] := R(4+i), 1 <= i <= 1
 14 [-]: NEWTABLE  R5 1 0       ; R5 := {}
 15 [-]: CONST     R6 0         ; R6 := 0.000000
 16 [-]: SETLIST   R5 1 1       ; R5[(1-1)*FPF+i] := R(5+i), 1 <= i <= 1
 17 [-]: LOADK     R6 K6        ; R6 := 0.200000
 18 [-]: CALL      R0 7 1       ; R0(R1,R2,R3,R4,R5,R6)
 19 [-]: GETGLOBAL R0 K3        ; R0 := 0x25312c9b
 20 [-]: GETGLOBAL R1 K0        ; R1 := 0xae91e43b
 21 [-]: LOADK     R2 K7        ; R2 := "Message.Effect"
 22 [-]: CONST     R3 0         ; R3 := 0.000000
 23 [-]: NEWTABLE  R4 1 0       ; R4 := {}
 24 [-]: CONST     R5 10        ; R5 := 10.000000
 25 [-]: SETLIST   R4 1 1       ; R4[(1-1)*FPF+i] := R(4+i), 1 <= i <= 1
 26 [-]: NEWTABLE  R5 1 0       ; R5 := {}
 27 [-]: CONST     R6 100       ; R6 := 100.000000
 28 [-]: SETLIST   R5 1 1       ; R5[(1-1)*FPF+i] := R(5+i), 1 <= i <= 1
 29 [-]: LOADK     R6 K6        ; R6 := 0.200000
 30 [-]: CALL      R0 7 1       ; R0(R1,R2,R3,R4,R5,R6)
 31 [-]: RETURN    R0 1         ; return 


; Function #16.5:
;
; Name:            
; Defined at line: 443
; #Upvalues:       5
; #Parameters:     0
; Is_vararg:       0
; Max Stack Size:  6

  1 [-]: GETUPVAL  R0 U0        ; R0 := U0
  2 [-]: GETTABLE  R0 R0 K0     ; R0 := R0[0xf76783e5]
  3 [-]: GETGLOBAL R1 K1        ; R1 := 0xae91e43b
  4 [-]: LOADK     R2 K2        ; R2 := "Message.Icon"
  5 [-]: GETUPVAL  R3 U1        ; R3 := U1
  6 [-]: LOADK     R4 K3        ; R4 := ".Container"
  7 [-]: CONCAT    R2 R2 R4     ; R2 := R2 .. R3 .. R4
  8 [-]: GETGLOBAL R3 K4        ; R3 := 0x190188f2
  9 [-]: CONST     R4 0         ; R4 := 0.000000
 10 [-]: CONST     R5 0         ; R5 := 0.000000
 11 [-]: CALL      R0 6 2       ; R0 := R0(R1,R2,R3,R4,R5)
 12 [-]: GETGLOBAL R1 K5        ; R1 := 0x7b998233
 13 [-]: MOVE      R2 R0        ; R2 := R0
 14 [-]: CALL      R1 2 2       ; R1 := R1(R2)
 15 [-]: TEST      R1 1         ; if R1 then PC := 21
 16 [-]: JMP       21           ; PC := 21
 17 [-]: SELF      R1 R0 K6     ; R2 := R0; R1 := R0[0x8feccd8b]
 18 [-]: GETUPVAL  R3 U2        ; R3 := U2
 19 [-]: GETUPVAL  R4 U2        ; R4 := U2
 20 [-]: CALL      R1 4 1       ; R1(R2,R3,R4)
 21 [-]: GETUPVAL  R1 U3        ; R1 := U3
 22 [-]: SELF      R1 R1 K7     ; R2 := R1; R1 := R1[0xbd2e96ea]
 23 [-]: LOADK     R3 K8        ; R3 := 0.650000
 24 [-]: CLOSURE   R4 0         ; R4 := closure(Function #16.5.1)
 25 [-]: GETUPVAL  R0 U0        ; R0 := U0
 26 [-]: GETUPVAL  R0 U1        ; R0 := U1
 27 [-]: GETUPVAL  R0 U4        ; R0 := U4
 28 [-]: CALL      R1 4 1       ; R1(R2,R3,R4)
 29 [-]: RETURN    R0 1         ; return 


; Function #16.5.1:
;
; Name:            
; Defined at line: 449
; #Upvalues:       3
; #Parameters:     0
; Is_vararg:       0
; Max Stack Size:  3

  1 [-]: GETUPVAL  R0 U0        ; R0 := U0
  2 [-]: GETTABLE  R0 R0 K0     ; R0 := R0[0x659d451f]
  3 [-]: GETGLOBAL R1 K1        ; R1 := 0x2d2aa18b
  4 [-]: GETUPVAL  R2 U1        ; R2 := U1
  5 [-]: GETTABLE  R1 R1 R2     ; R1 := R1[R2]
  6 [-]: CALL      R0 2 1       ; R0(R1)
  7 [-]: GETUPVAL  R0 U2        ; R0 := U2
  8 [-]: GETUPVAL  R1 U1        ; R1 := U1
  9 [-]: LOADK     R2 K2        ; R2 := 0.850000
 10 [-]: CALL      R0 3 1       ; R0(R1,R2)
 11 [-]: RETURN    R0 1         ; return 


; Function #17:
;
; Name:            
; Defined at line: 456
; #Upvalues:       19
; #Parameters:     0
; Is_vararg:       0
; Max Stack Size:  10

  1 [-]: GETGLOBAL R0 K0        ; R0 := 0x2d0fad09
  2 [-]: LOADK     R1 K1        ; R1 := "Lotus.Interface.Libs.TimerMgr"
  3 [-]: CALL      R0 2 2       ; R0 := R0(R1)
  4 [-]: GETTABLE  R1 R0 K2     ; R1 := R0[0xde474187]
  5 [-]: CALL      R1 1 2       ; R1 := R1()
  6 [-]: SETUPVAL  R1 U0        ; U82 := R0
  7 [-]: GETGLOBAL R1 K3        ; R1 := _T
  8 [-]: CLOSURE   R2 0         ; R2 := closure(Function #17.1)
  9 [-]: GETUPVAL  R0 U1        ; R0 := U1
 10 [-]: GETUPVAL  R0 U2        ; R0 := U2
 11 [-]: SETTABLE  R1 K4 R2     ; R1["WUKONG_StartTimer"] := R2
 12 [-]: GETGLOBAL R1 K3        ; R1 := _T
 13 [-]: CLOSURE   R2 1         ; R2 := closure(Function #17.2)
 14 [-]: GETUPVAL  R0 U1        ; R0 := U1
 15 [-]: GETUPVAL  R0 U3        ; R0 := U3
 16 [-]: SETTABLE  R1 K5 R2     ; R1["WUKONG_OnTimerEnd"] := R2
 17 [-]: GETGLOBAL R1 K3        ; R1 := _T
 18 [-]: CLOSURE   R2 2         ; R2 := closure(Function #17.3)
 19 [-]: GETUPVAL  R0 U1        ; R0 := U1
 20 [-]: GETUPVAL  R0 U4        ; R0 := U4
 21 [-]: SETTABLE  R1 K6 R2     ; R1["WUKONG_SetMeter"] := R2
 22 [-]: GETGLOBAL R1 K3        ; R1 := _T
 23 [-]: CLOSURE   R2 3         ; R2 := closure(Function #17.4)
 24 [-]: GETUPVAL  R0 U1        ; R0 := U1
 25 [-]: GETUPVAL  R0 U5        ; R0 := U5
 26 [-]: SETTABLE  R1 K7 R2     ; R1["WUKONG_SetMeterValue"] := R2
 27 [-]: GETGLOBAL R1 K3        ; R1 := _T
 28 [-]: CLOSURE   R2 4         ; R2 := closure(Function #17.5)
 29 [-]: GETUPVAL  R0 U1        ; R0 := U1
 30 [-]: GETUPVAL  R0 U6        ; R0 := U6
 31 [-]: SETTABLE  R1 K8 R2     ; R1["WUKONG_ShowBonus"] := R2
 32 [-]: GETGLOBAL R1 K3        ; R1 := _T
 33 [-]: CLOSURE   R2 5         ; R2 := closure(Function #17.6)
 34 [-]: GETUPVAL  R0 U1        ; R0 := U1
 35 [-]: GETUPVAL  R0 U7        ; R0 := U7
 36 [-]: SETTABLE  R1 K9 R2     ; R1["WUKONG_ShowPassiveMessage"] := R2
 37 [-]: GETGLOBAL R1 K10       ; R1 := 0xae91e43b
 38 [-]: SELF      R1 R1 K11    ; R2 := R1; R1 := R1[0x67bc869f]
 39 [-]: LOADK     R3 K12       ; R3 := "CloudTimer"
 40 [-]: CONST     R4 10        ; R4 := 10.000000
 41 [-]: CONST     R5 0         ; R5 := 0.000000
 42 [-]: CALL      R1 5 1       ; R1(R2,R3,R4,R5)
 43 [-]: GETGLOBAL R1 K10       ; R1 := 0xae91e43b
 44 [-]: SELF      R1 R1 K11    ; R2 := R1; R1 := R1[0x67bc869f]
 45 [-]: LOADK     R3 K13       ; R3 := "Bonus"
 46 [-]: CONST     R4 10        ; R4 := 10.000000
 47 [-]: CONST     R5 0         ; R5 := 0.000000
 48 [-]: CALL      R1 5 1       ; R1(R2,R3,R4,R5)
 49 [-]: GETGLOBAL R1 K14       ; R1 := 0x89326c93
 50 [-]: SELF      R1 R1 K15    ; R2 := R1; R1 := R1[0x78298275]
 51 [-]: CALL      R1 2 2       ; R1 := R1(R2)
 52 [-]: SETUPVAL  R1 U8        ; U82 := R8
 53 [-]: GETGLOBAL R1 K16       ; R1 := 0x7b998233
 54 [-]: GETUPVAL  R2 U8        ; R2 := U8
 55 [-]: CALL      R1 2 2       ; R1 := R1(R2)
 56 [-]: TEST      R1 1         ; if R1 then PC := 69
 57 [-]: JMP       69           ; PC := 69
 58 [-]: GETUPVAL  R1 U8        ; R1 := U8
 59 [-]: SELF      R1 R1 K17    ; R2 := R1; R1 := R1[0x5e651723]
 60 [-]: CALL      R1 2 2       ; R1 := R1(R2)
 61 [-]: GETGLOBAL R2 K16       ; R2 := 0x7b998233
 62 [-]: MOVE      R3 R1        ; R3 := R1
 63 [-]: CALL      R2 2 2       ; R2 := R2(R3)
 64 [-]: TEST      R2 1         ; if R2 then PC := 69
 65 [-]: JMP       69           ; PC := 69
 66 [-]: SELF      R2 R1 K18    ; R3 := R1; R2 := R1[0x0803eee1]
 67 [-]: CALL      R2 2 2       ; R2 := R2(R3)
 68 [-]: SETUPVAL  R2 U9        ; U82 := R9
 69 [-]: GETUPVAL  R2 U10       ; R2 := U10
 70 [-]: CALL      R2 1 1       ; R2()
 71 [-]: GETGLOBAL R2 K3        ; R2 := _T
 72 [-]: GETTABLE  R2 R2 K19    ; R2 := R2[0xf6b77431]
 73 [-]: CALL      R2 1 2       ; R2 := R2()
 74 [-]: SELF      R3 R2 K20    ; R4 := R2; R3 := R2[0x20ff29f7]
 75 [-]: GETGLOBAL R5 K10       ; R5 := 0xae91e43b
 76 [-]: LOADK     R6 K21       ; R6 := "Container"
 77 [-]: NEWTABLE  R7 2 0       ; R7 := {}
 78 [-]: GETTABLE  R8 R2 K22    ; R8 := R2["ANCHOR_V_BOTTOM"]
 79 [-]: GETTABLE  R9 R2 K23    ; R9 := R2["ANCHOR_H_RIGHT"]
 80 [-]: SETLIST   R7 2 1       ; R7[(1-1)*FPF+i] := R(7+i), 1 <= i <= 2
 81 [-]: CALL      R3 5 1       ; R3(R4,R5,R6,R7)
 82 [-]: SELF      R3 R2 K20    ; R4 := R2; R3 := R2[0x20ff29f7]
 83 [-]: GETGLOBAL R5 K10       ; R5 := 0xae91e43b
 84 [-]: LOADK     R6 K12       ; R6 := "CloudTimer"
 85 [-]: NEWTABLE  R7 2 0       ; R7 := {}
 86 [-]: GETTABLE  R8 R2 K22    ; R8 := R2["ANCHOR_V_BOTTOM"]
 87 [-]: GETTABLE  R9 R2 K24    ; R9 := R2["ANCHOR_H_CENTRE"]
 88 [-]: SETLIST   R7 2 1       ; R7[(1-1)*FPF+i] := R(7+i), 1 <= i <= 2
 89 [-]: CALL      R3 5 1       ; R3(R4,R5,R6,R7)
 90 [-]: SELF      R3 R2 K20    ; R4 := R2; R3 := R2[0x20ff29f7]
 91 [-]: GETGLOBAL R5 K10       ; R5 := 0xae91e43b
 92 [-]: LOADK     R6 K13       ; R6 := "Bonus"
 93 [-]: NEWTABLE  R7 2 0       ; R7 := {}
 94 [-]: GETTABLE  R8 R2 K22    ; R8 := R2["ANCHOR_V_BOTTOM"]
 95 [-]: GETTABLE  R9 R2 K24    ; R9 := R2["ANCHOR_H_CENTRE"]
 96 [-]: SETLIST   R7 2 1       ; R7[(1-1)*FPF+i] := R(7+i), 1 <= i <= 2
 97 [-]: CALL      R3 5 1       ; R3(R4,R5,R6,R7)
 98 [-]: SELF      R3 R2 K20    ; R4 := R2; R3 := R2[0x20ff29f7]
 99 [-]: GETGLOBAL R5 K10       ; R5 := 0xae91e43b
100 [-]: LOADK     R6 K25       ; R6 := "Message"
101 [-]: NEWTABLE  R7 2 0       ; R7 := {}
102 [-]: GETTABLE  R8 R2 K26    ; R8 := R2["ANCHOR_V_TOP"]
103 [-]: GETTABLE  R9 R2 K24    ; R9 := R2["ANCHOR_H_CENTRE"]
104 [-]: SETLIST   R7 2 1       ; R7[(1-1)*FPF+i] := R(7+i), 1 <= i <= 2
105 [-]: CALL      R3 5 1       ; R3(R4,R5,R6,R7)
106 [-]: SELF      R3 R2 K27    ; R4 := R2; R3 := R2[0xfaa69527]
107 [-]: GETGLOBAL R5 K10       ; R5 := 0xae91e43b
108 [-]: SELF      R5 R5 K28    ; R6 := R5; R5 := R5[0x6b837788]
109 [-]: CALL      R5 2 2       ; R5 := R5(R6)
110 [-]: GETGLOBAL R6 K10       ; R6 := 0xae91e43b
111 [-]: SELF      R6 R6 K29    ; R7 := R6; R6 := R6[0xaf9fda9f]
112 [-]: CALL      R6 2 2       ; R6 := R6(R7)
113 [-]: LOADKB    R7 1 0       ; R7 := true
114 [-]: GETTABLE  R8 R2 K30    ; R8 := R2["mHudScalePadding"]
115 [-]: CALL      R3 6 1       ; R3(R4,R5,R6,R7,R8)
116 [-]: GETGLOBAL R3 K3        ; R3 := _T
117 [-]: GETTABLE  R3 R3 K31    ; R3 := R3[0x6b23d28b]
118 [-]: GETGLOBAL R4 K10       ; R4 := 0xae91e43b
119 [-]: LOADK     R5 K21       ; R5 := "Container"
120 [-]: CALL      R3 3 1       ; R3(R4,R5)
121 [-]: GETUPVAL  R3 U11       ; R3 := U11
122 [-]: CALL      R3 1 1       ; R3()
123 [-]: GETUPVAL  R3 U12       ; R3 := U12
124 [-]: EQ        0 R3 K32     ; if R3 ~= nil then PC := 138
125 [-]: JMP       138          ; PC := 138
126 [-]: GETGLOBAL R3 K10       ; R3 := 0xae91e43b
127 [-]: SELF      R3 R3 K33    ; R4 := R3; R3 := R3[0x91a24e4b]
128 [-]: LOADK     R5 K34       ; R5 := "Container.FuryCounter"
129 [-]: CONST     R6 0         ; R6 := 0.000000
130 [-]: CALL      R3 4 2       ; R3 := R3(R4,R5,R6)
131 [-]: SETUPVAL  R3 U12       ; U82 := R12
132 [-]: GETGLOBAL R3 K10       ; R3 := 0xae91e43b
133 [-]: SELF      R3 R3 K33    ; R4 := R3; R3 := R3[0x91a24e4b]
134 [-]: LOADK     R5 K34       ; R5 := "Container.FuryCounter"
135 [-]: CONST     R6 1         ; R6 := 1.000000
136 [-]: CALL      R3 4 2       ; R3 := R3(R4,R5,R6)
137 [-]: SETUPVAL  R3 U13       ; U82 := R13
138 [-]: LOADNIL   R3 R3        ; R3 := nil
139 [-]: CLOSURE   R3 6         ; R3 := closure(Function #17.7)
140 [-]: GETUPVAL  R0 U14       ; R0 := U14
141 [-]: GETUPVAL  R0 U15       ; R0 := U15
142 [-]: GETUPVAL  R0 U0        ; R0 := U0
143 [-]: MOVE      R0 R3        ; R0 := R3
144 [-]: GETGLOBAL R4 K10       ; R4 := 0xae91e43b
145 [-]: SELF      R4 R4 K11    ; R5 := R4; R4 := R4[0x67bc869f]
146 [-]: LOADK     R6 K35       ; R6 := "_root"
147 [-]: CONST     R7 10        ; R7 := 10.000000
148 [-]: CONST     R8 0         ; R8 := 0.000000
149 [-]: CALL      R4 5 1       ; R4(R5,R6,R7,R8)
150 [-]: GETGLOBAL R4 K10       ; R4 := 0xae91e43b
151 [-]: SELF      R4 R4 K11    ; R5 := R4; R4 := R4[0x67bc869f]
152 [-]: LOADK     R6 K36       ; R6 := "Container.HealthDisplay"
153 [-]: CONST     R7 10        ; R7 := 10.000000
154 [-]: CONST     R8 0         ; R8 := 0.000000
155 [-]: CALL      R4 5 1       ; R4(R5,R6,R7,R8)
156 [-]: GETGLOBAL R4 K10       ; R4 := 0xae91e43b
157 [-]: SELF      R4 R4 K37    ; R5 := R4; R4 := R4[0xd5181643]
158 [-]: LOADK     R6 K38       ; R6 := "Container.FuryCounter.Progress"
159 [-]: GETGLOBAL R7 K39       ; R7 := 0xd3aeedfc
160 [-]: CALL      R4 4 1       ; R4(R5,R6,R7)
161 [-]: GETGLOBAL R4 K10       ; R4 := 0xae91e43b
162 [-]: SELF      R4 R4 K40    ; R5 := R4; R4 := R4[0x42b04007]
163 [-]: LOADK     R6 K41       ; R6 := "/Lotus/Language/Labels/AVATAR_ARMOUR"
164 [-]: LOADKB    R7 0 0       ; R7 := false
165 [-]: CALL      R4 4 2       ; R4 := R4(R5,R6,R7)
166 [-]: SETUPVAL  R4 U16       ; U82 := R16
167 [-]: GETUPVAL  R4 U4        ; R4 := U4
168 [-]: CONST     R5 0         ; R5 := 0.000000
169 [-]: CALL      R4 2 1       ; R4(R5)
170 [-]: GETUPVAL  R4 U5        ; R4 := U5
171 [-]: CONST     R5 0         ; R5 := 0.000000
172 [-]: CALL      R4 2 1       ; R4(R5)
173 [-]: GETGLOBAL R4 K10       ; R4 := 0xae91e43b
174 [-]: SELF      R4 R4 K42    ; R5 := R4; R4 := R4[0xef99134f]
175 [-]: LOADK     R6 K43       ; R6 := "Container.FuryCounter.Icon"
176 [-]: GETGLOBAL R7 K44       ; R7 := 0xc8bd56b6
177 [-]: GETGLOBAL R8 K45       ; R8 := 0x69aa0e52
178 [-]: CALL      R4 5 1       ; R4(R5,R6,R7,R8)
179 [-]: SELF      R4 R2 K46    ; R5 := R2; R4 := R2[0x9d1db3eb]
180 [-]: LOADK     R6 K21       ; R6 := "Container"
181 [-]: CALL      R4 3 2       ; R4 := R4(R5,R6)
182 [-]: GETTABLE  R4 R4 K47    ; R4 := R4["y"]
183 [-]: SETUPVAL  R4 U17       ; U82 := R17
184 [-]: LOADKB    R4 1 0       ; R4 := true
185 [-]: SETUPVAL  R4 U18       ; U82 := R18
186 [-]: RETURN    R0 1         ; return 


; Function #17.1:
;
; Name:            
; Defined at line: 460
; #Upvalues:       2
; #Parameters:     0
; Is_vararg:       3
; Max Stack Size:  4

  1 [-]: GETUPVAL  R1 U0        ; R1 := U0
  2 [-]: GETUPVAL  R2 U1        ; R2 := U1
  3 [-]: VARARG    R3 0         ; R3 := ...
  4 [-]: CALL      R1 0 1       ; R1(R2,...)
  5 [-]: RETURN    R0 1         ; return 


; Function #17.2:
;
; Name:            
; Defined at line: 461
; #Upvalues:       2
; #Parameters:     0
; Is_vararg:       3
; Max Stack Size:  4

  1 [-]: GETUPVAL  R1 U0        ; R1 := U0
  2 [-]: GETUPVAL  R2 U1        ; R2 := U1
  3 [-]: VARARG    R3 0         ; R3 := ...
  4 [-]: CALL      R1 0 1       ; R1(R2,...)
  5 [-]: RETURN    R0 1         ; return 


; Function #17.3:
;
; Name:            
; Defined at line: 463
; #Upvalues:       2
; #Parameters:     0
; Is_vararg:       3
; Max Stack Size:  4

  1 [-]: GETUPVAL  R1 U0        ; R1 := U0
  2 [-]: GETUPVAL  R2 U1        ; R2 := U1
  3 [-]: VARARG    R3 0         ; R3 := ...
  4 [-]: CALL      R1 0 1       ; R1(R2,...)
  5 [-]: RETURN    R0 1         ; return 


; Function #17.4:
;
; Name:            
; Defined at line: 464
; #Upvalues:       2
; #Parameters:     0
; Is_vararg:       3
; Max Stack Size:  4

  1 [-]: GETUPVAL  R1 U0        ; R1 := U0
  2 [-]: GETUPVAL  R2 U1        ; R2 := U1
  3 [-]: VARARG    R3 0         ; R3 := ...
  4 [-]: CALL      R1 0 1       ; R1(R2,...)
  5 [-]: RETURN    R0 1         ; return 


; Function #17.5:
;
; Name:            
; Defined at line: 465
; #Upvalues:       2
; #Parameters:     0
; Is_vararg:       3
; Max Stack Size:  4

  1 [-]: GETUPVAL  R1 U0        ; R1 := U0
  2 [-]: GETUPVAL  R2 U1        ; R2 := U1
  3 [-]: VARARG    R3 0         ; R3 := ...
  4 [-]: CALL      R1 0 1       ; R1(R2,...)
  5 [-]: RETURN    R0 1         ; return 


; Function #17.6:
;
; Name:            
; Defined at line: 467
; #Upvalues:       2
; #Parameters:     0
; Is_vararg:       3
; Max Stack Size:  4

  1 [-]: GETUPVAL  R1 U0        ; R1 := U0
  2 [-]: GETUPVAL  R2 U1        ; R2 := U1
  3 [-]: VARARG    R3 0         ; R3 := ...
  4 [-]: CALL      R1 0 1       ; R1(R2,...)
  5 [-]: RETURN    R0 1         ; return 


; Function #17.7:
;
; Name:            
; Defined at line: 499
; #Upvalues:       4
; #Parameters:     0
; Is_vararg:       0
; Max Stack Size:  6

  1 [-]: GETUPVAL  R0 U0        ; R0 := U0
  2 [-]: GETTABLE  R0 R0 K0     ; R0 := R0[0xf76783e5]
  3 [-]: GETGLOBAL R1 K1        ; R1 := 0xae91e43b
  4 [-]: LOADK     R2 K2        ; R2 := "Message"
  5 [-]: GETGLOBAL R3 K3        ; R3 := 0x190188f2
  6 [-]: CONST     R4 0         ; R4 := 0.000000
  7 [-]: CONST     R5 0         ; R5 := 0.000000
  8 [-]: CALL      R0 6 2       ; R0 := R0(R1,R2,R3,R4,R5)
  9 [-]: SELF      R1 R0 K4     ; R2 := R0; R1 := R0[0x8feccd8b]
 10 [-]: GETUPVAL  R3 U1        ; R3 := U1
 11 [-]: GETUPVAL  R4 U1        ; R4 := U1
 12 [-]: CALL      R1 4 1       ; R1(R2,R3,R4)
 13 [-]: GETUPVAL  R1 U2        ; R1 := U2
 14 [-]: SELF      R1 R1 K5     ; R2 := R1; R1 := R1[0xbd2e96ea]
 15 [-]: CONST     R3 1         ; R3 := 1.000000
 16 [-]: GETUPVAL  R4 U3        ; R4 := U3
 17 [-]: CALL      R1 4 1       ; R1(R2,R3,R4)
 18 [-]: RETURN    R0 1         ; return 


; Function #18:
;
; Name:            
; Defined at line: 521
; #Upvalues:       1
; #Parameters:     1
; Is_vararg:       0
; Max Stack Size:  5

  1 [-]: GETUPVAL  R1 U0        ; R1 := U0
  2 [-]: GETTABLE  R1 R1 K0     ; R1 := R1[0xfa221145]
  3 [-]: GETGLOBAL R2 K1        ; R2 := 0xae91e43b
  4 [-]: GETGLOBAL R3 K2        ; R3 := 0x03f57322
  5 [-]: MOVE      R4 R0        ; R4 := R0
  6 [-]: CALL      R3 2 0       ; R3,... := R3(R4)
  7 [-]: CALL      R1 0 1       ; R1(R2,...)
  8 [-]: RETURN    R0 1         ; return 


