; Name:            
; Defined at line: 1
; #Upvalues:       0
; #Parameters:     0
; Is_vararg:       1
; Max Stack Size:  1

       1 [-]: DUPCLOSURE R0 K0 []
       2 [-]: SETGLOBAL R0 K1 ["OnUpgradeApplied"]
       3 [-]: DUPCLOSURE R0 K2 []
       4 [-]: SETGLOBAL R0 K3 ["OnUpgradeUnapplied"]
       5 [-]: RETURN R0 0  


; Name:            
; Defined at line: 4
; #Upvalues:       0
; #Parameters:     5
; Is_vararg:       0
; Max Stack Size:  11

       0 [-]: NAMECALL R5 R0 K0 [0xDE321E6F]
       1 [-]: CALL R5 1 1  
       2 [-]: LOADN R7 3   
       3 [-]: NAMECALL R5 R5 K1 [0xE85A2361]
       4 [-]: CALL R5 2 1  
       5 [-]: FASTCALL1 62 R5 L0
       6 [-]: MOVE R7 R5   
       7 [-]: GETIMPORT R6 3 [0x7B998233]
       8 [-]: CALL R6 1 1  
L 0:   9 [-]: JUMPIF R6 L1 
      10 [-]: NAMECALL R6 R5 K4 [0xCDE10C4A]
      11 [-]: CALL R6 1 1  
      12 [-]: GETIMPORT R8 6 [0x6DDF8A32]
      13 [-]: NAMECALL R6 R6 K7 [0xF2DEAF69]
      14 [-]: CALL R6 2 1  
      15 [-]: JUMPIFNOT R6 L1
      16 [-]: GETIMPORT R6 10 [0x449A507E]
      17 [-]: CALL R6 0 1  
      18 [-]: LOADN R9 0   
      19 [-]: NAMECALL R7 R6 K11 [0xC670D7F3]
      20 [-]: CALL R7 2 0  
      21 [-]: LOADN R9 71  
      22 [-]: NAMECALL R7 R6 K12 [0x14894DE6]
      23 [-]: CALL R7 2 0  
      24 [-]: GETIMPORT R9 14 [0xE1C42B8B]
      25 [-]: NAMECALL R7 R6 K15 [0x8550D2A7]
      26 [-]: CALL R7 2 0  
      27 [-]: NAMECALL R9 R1 K4 [0xCDE10C4A]
      28 [-]: CALL R9 1 -1 
      29 [-]: NAMECALL R7 R6 K16 [0xD314C0E0]
      30 [-]: CALL R7 -1 0 
      31 [-]: MOVE R9 R1   
      32 [-]: NAMECALL R7 R6 K17 [0x009F88B3]
      33 [-]: CALL R7 2 0  
      34 [-]: LOADN R9 30  
      35 [-]: LOADB R10 1  
      36 [-]: NAMECALL R7 R6 K18 [0x81F914F1]
      37 [-]: CALL R7 3 0  
      38 [-]: NAMECALL R7 R0 K0 [0xDE321E6F]
      39 [-]: CALL R7 1 1  
      40 [-]: MOVE R9 R6   
      41 [-]: NAMECALL R7 R7 K19 [0x5E6704FF]
      42 [-]: CALL R7 2 0  
L 1:  43 [-]: RETURN R0 0  


; Name:            
; Defined at line: 18
; #Upvalues:       0
; #Parameters:     5
; Is_vararg:       0
; Max Stack Size:  11

       0 [-]: NAMECALL R5 R0 K0 [0xDE321E6F]
       1 [-]: CALL R5 1 1  
       2 [-]: LOADN R7 3   
       3 [-]: NAMECALL R5 R5 K1 [0xE85A2361]
       4 [-]: CALL R5 2 1  
       5 [-]: FASTCALL1 62 R5 L0
       6 [-]: MOVE R7 R5   
       7 [-]: GETIMPORT R6 3 [0x7B998233]
       8 [-]: CALL R6 1 1  
L 0:   9 [-]: JUMPIF R6 L1 
      10 [-]: NAMECALL R6 R5 K4 [0xCDE10C4A]
      11 [-]: CALL R6 1 1  
      12 [-]: GETIMPORT R8 6 [0x6DDF8A32]
      13 [-]: NAMECALL R6 R6 K7 [0xF2DEAF69]
      14 [-]: CALL R6 2 1  
      15 [-]: JUMPIFNOT R6 L1
      16 [-]: GETIMPORT R6 10 [0x449A507E]
      17 [-]: CALL R6 0 1  
      18 [-]: LOADN R9 0   
      19 [-]: NAMECALL R7 R6 K11 [0xC670D7F3]
      20 [-]: CALL R7 2 0  
      21 [-]: LOADN R9 71  
      22 [-]: NAMECALL R7 R6 K12 [0x14894DE6]
      23 [-]: CALL R7 2 0  
      24 [-]: GETIMPORT R9 14 [0xE1C42B8B]
      25 [-]: NAMECALL R7 R6 K15 [0x8550D2A7]
      26 [-]: CALL R7 2 0  
      27 [-]: NAMECALL R9 R1 K4 [0xCDE10C4A]
      28 [-]: CALL R9 1 -1 
      29 [-]: NAMECALL R7 R6 K16 [0xD314C0E0]
      30 [-]: CALL R7 -1 0 
      31 [-]: MOVE R9 R1   
      32 [-]: NAMECALL R7 R6 K17 [0x009F88B3]
      33 [-]: CALL R7 2 0  
      34 [-]: LOADN R9 30  
      35 [-]: LOADB R10 1  
      36 [-]: NAMECALL R7 R6 K18 [0x81F914F1]
      37 [-]: CALL R7 3 0  
      38 [-]: NAMECALL R7 R0 K0 [0xDE321E6F]
      39 [-]: CALL R7 1 1  
      40 [-]: MOVE R9 R6   
      41 [-]: NAMECALL R7 R7 K19 [0x12DD9DA2]
      42 [-]: CALL R7 2 0  
L 1:  43 [-]: RETURN R0 0  



