; Name:            
; Defined at line: 1
; #Upvalues:       0
; #Parameters:     0
; Is_vararg:       1
; Max Stack Size:  52

            1 [-]: GETIMPORT R0 1 [nil]
       2 [-]: LOADK R1 K2 ["/Lotus/Types/PickUps/RaidInfestedAntidoteItem"]
       3 [-]: CALL R0 1 1  
       4 [-]: GETIMPORT R1 4 [nil]
       5 [-]: LOADK R2 K5 ["/Lotus/Sounds/Ambience/Infested/GolemTrial/Gameplay/GolemTrialArmourIntegrityFailingLoopSeq"]
       6 [-]: CALL R1 1 1  
       7 [-]: GETIMPORT R2 4 [nil]
       8 [-]: LOADK R3 K6 ["/Lotus/Sounds/UI/J3GolemTrial/InjectAntidote"]
       9 [-]: CALL R2 1 1  
      10 [-]: GETIMPORT R3 8 [nil]
      11 [-]: LOADK R4 K9 ["EE.Interface.Utilities"]
      12 [-]: CALL R3 1 1  
      13 [-]: GETIMPORT R4 8 [nil]
      14 [-]: LOADK R5 K10 ["Lotus.Interface.LotusUtilities"]
      15 [-]: CALL R4 1 1  
      16 [-]: GETIMPORT R5 12 [nil]
      17 [-]: GETIMPORT R6 1 [nil]
      18 [-]: LOADK R7 K13 ["/Lotus/Fx/Raids/J3Golem/InfestedScreenEffect"]
      19 [-]: CALL R6 1 1  
      20 [-]: GETIMPORT R7 15 [nil]
      21 [-]: LOADK R8 K16 ["/Lotus/Types/LevelObjects/Attachments/PurifierArmor"]
      22 [-]: CALL R7 1 1  
      23 [-]: LOADN R8 1   
      24 [-]: LOADNIL R9   
      25 [-]: LOADNIL R10  
      26 [-]: LOADNIL R11  
      27 [-]: LOADNIL R12  
      28 [-]: NEWTABLE R13 0 3
      29 [-]: LOADN R14 0  
      30 [-]: LOADN R15 1  
      31 [-]: LOADN R16 4  
      32 [-]: SETLIST R13 R14 3 [1]
      33 [-]: LOADN R14 1  
      34 [-]: LOADN R15 0  
      35 [-]: LOADN R16 0  
      36 [-]: LOADN R17 0  
      37 [-]: LOADN R18 100
      38 [-]: LOADK R19 K17 [0.5]
      39 [-]: LOADN R20 0  
      40 [-]: LOADN R21 0  
      41 [-]: LOADN R22 0  
      42 [-]: NEWTABLE R23 0 0
      43 [-]: LOADNIL R24  
      44 [-]: LOADNIL R25  
      45 [-]: LOADNIL R26  
      46 [-]: GETIMPORT R27 20 [nil]
      47 [-]: CALL R27 0 1 
      48 [-]: GETIMPORT R30 22 [nil]
      49 [-]: LOADN R31 15 
      50 [-]: CALL R30 1 -1
      51 [-]: NAMECALL R28 R27 K23 [0xF326045F]
      52 [-]: CALL R28 -1 0
      53 [-]: LOADN R30 6  
      54 [-]: LOADN R31 1  
      55 [-]: NAMECALL R28 R27 K24 [0x1586E35E]
      56 [-]: CALL R28 3 0 
      57 [-]: GETIMPORT R28 20 [nil]
      58 [-]: CALL R28 0 1 
      59 [-]: GETIMPORT R31 22 [nil]
      60 [-]: LOADN R32 15 
      61 [-]: CALL R31 1 -1
      62 [-]: NAMECALL R29 R28 K23 [0xF326045F]
      63 [-]: CALL R29 -1 0
      64 [-]: LOADN R31 6  
      65 [-]: LOADN R32 1  
      66 [-]: NAMECALL R29 R28 K24 [0x1586E35E]
      67 [-]: CALL R29 3 0 
      68 [-]: GETIMPORT R29 20 [nil]
      69 [-]: CALL R29 0 1 
      70 [-]: GETIMPORT R32 22 [nil]
      71 [-]: LOADN R33 15 
      72 [-]: CALL R32 1 -1
      73 [-]: NAMECALL R30 R29 K23 [0xF326045F]
      74 [-]: CALL R30 -1 0
      75 [-]: LOADN R32 6  
      76 [-]: LOADN R33 1  
      77 [-]: NAMECALL R30 R29 K24 [0x1586E35E]
      78 [-]: CALL R30 3 0 
      79 [-]: LOADNIL R30  
      80 [-]: LOADN R31 -1 
      81 [-]: LOADN R32 0  
      82 [-]: LOADN R33 0  
      83 [-]: LOADB R34 1  
      84 [-]: LOADNIL R35  
      85 [-]: LOADNIL R36  
      86 [-]: DUPCLOSURE R37 K25 []
      87 [-]: NEWCLOSURE R38 P1
      88 [-]: MOVE R1 R9   
      89 [-]: MOVE R1 R15  
      90 [-]: MOVE R1 R16  
      91 [-]: NEWCLOSURE R39 P2
      92 [-]: MOVE R1 R11  
      93 [-]: MOVE R1 R9   
      94 [-]: MOVE R0 R6   
      95 [-]: MOVE R0 R38  
      96 [-]: MOVE R1 R18  
      97 [-]: MOVE R1 R19  
      98 [-]: MOVE R1 R20  
      99 [-]: MOVE R1 R21  
     100 [-]: MOVE R1 R22  
     101 [-]: MOVE R1 R12  
     102 [-]: NEWCLOSURE R40 P3
     103 [-]: MOVE R1 R35  
     104 [-]: MOVE R0 R4   
     105 [-]: DUPCLOSURE R41 K26 []
     106 [-]: MOVE R0 R0   
     107 [-]: MOVE R0 R13  
     108 [-]: DUPCLOSURE R42 K27 []
     109 [-]: MOVE R0 R13  
     110 [-]: MOVE R0 R41  
     111 [-]: MOVE R0 R0   
     112 [-]: DUPCLOSURE R43 K28 []
     113 [-]: MOVE R0 R13  
     114 [-]: MOVE R0 R0   
     115 [-]: DUPCLOSURE R44 K29 []
     116 [-]: MOVE R0 R23  
     117 [-]: NEWCLOSURE R45 P8
     118 [-]: MOVE R1 R30  
     119 [-]: MOVE R1 R18  
     120 [-]: MOVE R1 R10  
     121 [-]: MOVE R1 R34  
     122 [-]: MOVE R0 R41  
     123 [-]: MOVE R1 R32  
     124 [-]: MOVE R0 R23  
     125 [-]: MOVE R0 R42  
     126 [-]: MOVE R1 R9   
     127 [-]: MOVE R0 R43  
     128 [-]: MOVE R1 R24  
     129 [-]: MOVE R1 R36  
     130 [-]: MOVE R0 R4   
     131 [-]: MOVE R1 R31  
     132 [-]: MOVE R0 R38  
     133 [-]: MOVE R0 R40  
     134 [-]: MOVE R1 R22  
     135 [-]: MOVE R1 R35  
     136 [-]: DUPCLOSURE R46 K30 []
     137 [-]: SETGLOBAL R46 K31 ["EnterNotSafeZone"]
     138 [-]: DUPCLOSURE R46 K32 []
     139 [-]: SETGLOBAL R46 K33 ["ExitNotSafeZone"]
     140 [-]: DUPCLOSURE R46 K34 []
     141 [-]: SETGLOBAL R46 K35 ["EnterSafeZone"]
     142 [-]: DUPCLOSURE R46 K36 []
     143 [-]: SETGLOBAL R46 K37 ["ExitSafeZone"]
     144 [-]: NEWCLOSURE R46 P13
     145 [-]: MOVE R1 R9   
     146 [-]: MOVE R1 R14  
     147 [-]: MOVE R1 R8   
     148 [-]: NEWCLOSURE R47 P14
     149 [-]: MOVE R0 R5   
     150 [-]: MOVE R1 R14  
     151 [-]: NEWCLOSURE R48 P15
     152 [-]: MOVE R1 R9   
     153 [-]: MOVE R1 R18  
     154 [-]: MOVE R0 R38  
     155 [-]: MOVE R0 R3   
     156 [-]: MOVE R0 R5   
     157 [-]: MOVE R1 R14  
     158 [-]: MOVE R1 R17  
     159 [-]: MOVE R1 R25  
     160 [-]: NEWCLOSURE R49 P16
     161 [-]: MOVE R0 R5   
     162 [-]: MOVE R1 R14  
     163 [-]: MOVE R1 R15  
     164 [-]: MOVE R1 R16  
     165 [-]: MOVE R1 R17  
     166 [-]: NEWCLOSURE R50 P17
     167 [-]: MOVE R1 R15  
     168 [-]: MOVE R0 R3   
     169 [-]: MOVE R1 R16  
     170 [-]: MOVE R1 R18  
     171 [-]: MOVE R0 R23  
     172 [-]: MOVE R0 R2   
     173 [-]: MOVE R1 R24  
     174 [-]: MOVE R1 R26  
     175 [-]: MOVE R0 R7   
     176 [-]: MOVE R0 R13  
     177 [-]: MOVE R0 R0   
     178 [-]: MOVE R0 R41  
     179 [-]: MOVE R1 R33  
     180 [-]: MOVE R1 R25  
     181 [-]: MOVE R1 R10  
     182 [-]: MOVE R1 R9   
     183 [-]: MOVE R0 R5   
     184 [-]: MOVE R1 R12  
     185 [-]: MOVE R0 R1   
     186 [-]: MOVE R1 R8   
     187 [-]: NEWCLOSURE R51 P18
     188 [-]: MOVE R0 R50  
     189 [-]: MOVE R0 R5   
     190 [-]: MOVE R1 R10  
     191 [-]: MOVE R1 R15  
     192 [-]: MOVE R1 R16  
     193 [-]: MOVE R1 R18  
     194 [-]: MOVE R1 R14  
     195 [-]: MOVE R0 R46  
     196 [-]: MOVE R1 R9   
     197 [-]: MOVE R0 R48  
     198 [-]: MOVE R0 R38  
     199 [-]: MOVE R1 R22  
     200 [-]: MOVE R0 R29  
     201 [-]: MOVE R1 R24  
     202 [-]: MOVE R0 R27  
     203 [-]: MOVE R0 R28  
     204 [-]: MOVE R0 R45  
     205 [-]: MOVE R0 R39  
     206 [-]: SETGLOBAL R51 K38 ["InfestedMeter"]
     207 [-]: CLOSEUPVALS R8
     208 [-]: RETURN R0 0  


; Name:            
; Defined at line: 86
; #Upvalues:       0
; #Parameters:     0
; Is_vararg:       0
; Max Stack Size:  1

       0 [-]: LOADB R0 0   
       1 [-]: RETURN R0 1  


; Name:            
; Defined at line: 90
; #Upvalues:       3
; #Parameters:     0
; Is_vararg:       0
; Max Stack Size:  6

       0 [-]: GETIMPORT R1 2 [nil]
       1 [-]: FASTCALL1 62 R1 L0
       2 [-]: GETIMPORT R0 4 [nil]
       3 [-]: CALL R0 1 1  
L 0:   4 [-]: JUMPIF R0 L1 
       5 [-]: GETIMPORT R0 2 [nil]
       6 [-]: JUMPIFNOT R0 L1
       7 [-]: LOADB R0 1   
       8 [-]: RETURN R0 1  
L 1:   9 [-]: GETUPVAL R0 0
      10 [-]: NAMECALL R0 R0 K5 [0xBB610E5B]
      11 [-]: CALL R0 1 1  
      12 [-]: FASTCALL1 62 R0 L2
      13 [-]: MOVE R2 R0   
      14 [-]: GETIMPORT R1 4 [nil]
      15 [-]: CALL R1 1 1  
L 2:  16 [-]: JUMPIFNOT R1 L3
      17 [-]: LOADB R1 1   
      18 [-]: RETURN R1 1  
L 3:  19 [-]: NAMECALL R1 R0 K6 [0xE79E7EF4]
      20 [-]: CALL R1 1 1  
      21 [-]: FASTCALL1 62 R1 L4
      22 [-]: MOVE R3 R1   
      23 [-]: GETIMPORT R2 4 [nil]
      24 [-]: CALL R2 1 1  
L 4:  25 [-]: JUMPIFNOT R2 L5
      26 [-]: LOADB R2 1   
      27 [-]: RETURN R2 1  
L 5:  28 [-]: NAMECALL R4 R1 K7 [0x7D05E45F]
      29 [-]: CALL R4 1 1  
      30 [-]: FASTCALL1 62 R4 L6
      31 [-]: GETIMPORT R3 4 [nil]
      32 [-]: CALL R3 1 1  
L 6:  33 [-]: NOT R2 R3    
      34 [-]: JUMPIFNOT R2 L8
      35 [-]: NAMECALL R3 R1 K7 [0x7D05E45F]
      36 [-]: CALL R3 1 1  
      37 [-]: NAMECALL R3 R3 K8 [0x22DA1852]
      38 [-]: CALL R3 1 1  
      39 [-]: GETIMPORT R4 10 [nil]
      40 [-]: LOADK R5 K11 ["InfestedZone"]
      41 [-]: CALL R4 1 1  
      42 [-]: JUMPIFEQ R3 R4 L7
      43 [-]: LOADB R2 0 +1
L 7:  44 [-]: LOADB R2 1   
L 8:  45 [-]: LOADB R3 1   
      46 [-]: GETUPVAL R4 1
      47 [-]: LOADN R5 0   
      48 [-]: JUMPIFLT R5 R4 L10
      49 [-]: NOT R3 R2    
      50 [-]: JUMPIFNOT R3 L10
      51 [-]: GETUPVAL R4 2
      52 [-]: LOADN R5 1   
      53 [-]: JUMPIFLT R4 R5 L9
      54 [-]: LOADB R3 0 +1
L 9:  55 [-]: LOADB R3 1   
L10:  56 [-]: RETURN R3 1  


; Name:            
; Defined at line: 109
; #Upvalues:       10
; #Parameters:     0
; Is_vararg:       0
; Max Stack Size:  8

       0 [-]: GETUPVAL R1 0
       1 [-]: FASTCALL1 62 R1 L0
       2 [-]: GETIMPORT R0 1 [nil]
       3 [-]: CALL R0 1 1  
L 0:   4 [-]: JUMPIFNOT R0 L3
       5 [-]: GETUPVAL R1 1
       6 [-]: NAMECALL R1 R1 K2 [0xBB610E5B]
       7 [-]: CALL R1 1 1  
       8 [-]: FASTCALL1 62 R1 L1
       9 [-]: GETIMPORT R0 1 [nil]
      10 [-]: CALL R0 1 1  
L 1:  11 [-]: JUMPIF R0 L3 
      12 [-]: GETUPVAL R0 1
      13 [-]: NAMECALL R0 R0 K2 [0xBB610E5B]
      14 [-]: CALL R0 1 1  
      15 [-]: GETUPVAL R2 2
      16 [-]: NAMECALL R0 R0 K3 [0xC9F6A7D7]
      17 [-]: CALL R0 2 1  
      18 [-]: SETUPVAL R0 0
      19 [-]: GETUPVAL R1 0
      20 [-]: FASTCALL1 62 R1 L2
      21 [-]: GETIMPORT R0 1 [nil]
      22 [-]: CALL R0 1 1  
L 2:  23 [-]: JUMPIFNOT R0 L3
      24 [-]: GETUPVAL R0 1
      25 [-]: NAMECALL R0 R0 K2 [0xBB610E5B]
      26 [-]: CALL R0 1 1  
      27 [-]: GETUPVAL R2 2
      28 [-]: GETIMPORT R3 5 [nil]
      29 [-]: NAMECALL R0 R0 K6 [0x47901F07]
      30 [-]: CALL R0 3 1  
      31 [-]: SETUPVAL R0 0
      32 [-]: GETUPVAL R0 0
      33 [-]: GETIMPORT R2 9 [nil]
      34 [-]: LOADN R3 0   
      35 [-]: NAMECALL R0 R0 K10 [0x986D2AB8]
      36 [-]: CALL R0 3 0  
      37 [-]: GETUPVAL R0 0
      38 [-]: GETIMPORT R2 12 [nil]
      39 [-]: LOADN R3 0   
      40 [-]: NAMECALL R0 R0 K10 [0x986D2AB8]
      41 [-]: CALL R0 3 0  
L 3:  42 [-]: GETUPVAL R0 3
      43 [-]: CALL R0 0 1  
      44 [-]: GETUPVAL R1 4
      45 [-]: LOADN R2 0   
      46 [-]: JUMPIFLT R2 R1 L4
      47 [-]: JUMPIFNOT R0 L12
L 4:  48 [-]: LOADK R2 K13 [0.34999999999999998]
      49 [-]: LOADN R6 100 
      50 [-]: GETUPVAL R7 4
      51 [-]: SUB R5 R6 R7 
      52 [-]: DIVK R4 R5 K15 [100]
      53 [-]: DIVK R3 R4 K14 [2]
      54 [-]: FASTCALL2 18 R2 R3 L5
      55 [-]: GETIMPORT R1 18 [nil]
      56 [-]: CALL R1 2 1  
L 5:  57 [-]: SETUPVAL R1 5
      58 [-]: LOADB R1 0   
      59 [-]: NOT R2 R0    
      60 [-]: JUMPIFNOT R2 L7
      61 [-]: GETUPVAL R3 6
      62 [-]: GETUPVAL R4 5
      63 [-]: JUMPIFEQ R3 R4 L7
      64 [-]: GETUPVAL R5 7
      65 [-]: GETIMPORT R6 20 [nil]
      66 [-]: CALL R6 0 1  
      67 [-]: ADD R4 R5 R6 
      68 [-]: FASTCALL2K 19 R4 K21 L6 [1]
      69 [-]: LOADK R5 K21 [1]
      70 [-]: GETIMPORT R3 23 [nil]
      71 [-]: CALL R3 2 1  
L 6:  72 [-]: SETUPVAL R3 7
      73 [-]: LOADB R1 1   
      74 [-]: JUMP L9
     
L 7:  75 [-]: JUMPIF R2 L9 
      76 [-]: GETUPVAL R3 6
      77 [-]: JUMPXEQKN R3 K24 L9 [0]
      78 [-]: GETUPVAL R5 7
      79 [-]: GETIMPORT R6 20 [nil]
      80 [-]: CALL R6 0 1  
      81 [-]: SUB R4 R5 R6 
      82 [-]: FASTCALL2K 18 R4 K24 L8 [0]
      83 [-]: LOADK R5 K24 [0]
      84 [-]: GETIMPORT R3 18 [nil]
      85 [-]: CALL R3 2 1  
L 8:  86 [-]: SETUPVAL R3 7
      87 [-]: LOADB R1 1   
L 9:  88 [-]: JUMPIFNOT R1 L11
      89 [-]: GETUPVAL R4 0
      90 [-]: FASTCALL1 62 R4 L10
      91 [-]: GETIMPORT R3 1 [nil]
      92 [-]: CALL R3 1 1  
L10:  93 [-]: JUMPIF R3 L11
      94 [-]: GETIMPORT R3 26 [nil]
      95 [-]: LOADN R4 0   
      96 [-]: GETUPVAL R5 5
      97 [-]: GETUPVAL R7 7
      98 [-]: DIVK R6 R7 K21 [1]
      99 [-]: CALL R3 3 1  
     100 [-]: SETUPVAL R3 6
     101 [-]: GETUPVAL R3 0
     102 [-]: GETIMPORT R5 9 [nil]
     103 [-]: GETUPVAL R6 6
     104 [-]: NAMECALL R3 R3 K10 [0x986D2AB8]
     105 [-]: CALL R3 3 0  
     106 [-]: GETUPVAL R3 0
     107 [-]: GETIMPORT R5 12 [nil]
     108 [-]: GETUPVAL R6 6
     109 [-]: NAMECALL R3 R3 K10 [0x986D2AB8]
     110 [-]: CALL R3 3 0  
L11: 111 [-]: LOADN R3 0   
     112 [-]: SETUPVAL R3 8
     113 [-]: GETUPVAL R3 9
     114 [-]: NAMECALL R3 R3 K27 [0xF37943FF]
     115 [-]: CALL R3 1 1  
     116 [-]: JUMPIFNOT R3 L15
     117 [-]: GETUPVAL R3 9
     118 [-]: NAMECALL R3 R3 K28 [0xF4E253B6]
     119 [-]: CALL R3 1 0  
     120 [-]: RETURN R0 0  
L12: 121 [-]: GETUPVAL R1 8
     122 [-]: LOADK R2 K29 [1.5]
     123 [-]: JUMPIFNOTLT R1 R2 L14
     124 [-]: GETUPVAL R3 8
     125 [-]: GETIMPORT R4 20 [nil]
     126 [-]: CALL R4 0 1  
     127 [-]: ADD R2 R3 R4 
     128 [-]: FASTCALL2K 19 R2 K29 L13 [1.5]
     129 [-]: LOADK R3 K29 [1.5]
     130 [-]: GETIMPORT R1 23 [nil]
     131 [-]: CALL R1 2 1  
L13: 132 [-]: SETUPVAL R1 8
     133 [-]: GETIMPORT R1 26 [nil]
     134 [-]: LOADK R2 K13 [0.34999999999999998]
     135 [-]: LOADN R3 1   
     136 [-]: GETUPVAL R5 8
     137 [-]: DIVK R4 R5 K29 [1.5]
     138 [-]: CALL R1 3 1  
     139 [-]: SETUPVAL R1 6
     140 [-]: GETUPVAL R1 0
     141 [-]: GETIMPORT R3 9 [nil]
     142 [-]: GETUPVAL R4 6
     143 [-]: NAMECALL R1 R1 K10 [0x986D2AB8]
     144 [-]: CALL R1 3 0  
     145 [-]: GETUPVAL R1 0
     146 [-]: GETIMPORT R3 12 [nil]
     147 [-]: GETUPVAL R4 6
     148 [-]: NAMECALL R1 R1 K10 [0x986D2AB8]
     149 [-]: CALL R1 3 0  
L14: 150 [-]: GETUPVAL R1 9
     151 [-]: NAMECALL R1 R1 K27 [0xF37943FF]
     152 [-]: CALL R1 1 1  
     153 [-]: JUMPIF R1 L15
     154 [-]: GETUPVAL R1 9
     155 [-]: NAMECALL R1 R1 K30 [0x383D2E7D]
     156 [-]: CALL R1 1 0  
L15: 157 [-]: RETURN R0 0  


; Name:            
; Defined at line: 158
; #Upvalues:       2
; #Parameters:     9
; Is_vararg:       0
; Max Stack Size:  16

       0 [-]: GETUPVAL R10 0
       1 [-]: FASTCALL1 62 R10 L0
       2 [-]: GETIMPORT R9 1 [nil]
       3 [-]: CALL R9 1 1  
L 0:   4 [-]: JUMPIFNOT R9 L1
       5 [-]: GETIMPORT R9 4 [nil]
       6 [-]: LOADK R10 K5 ["J3ProgressBar"]
       7 [-]: GETUPVAL R12 1
       8 [-]: GETTABLEKS R11 R12 K6 ["HT_PROGRESS_BAR"]
       9 [-]: LOADK R12 K7 [0.20000000000000001]
      10 [-]: LOADB R13 0  
      11 [-]: LOADB R14 0  
      12 [-]: CALL R9 5 1  
      13 [-]: SETUPVAL R9 0
      14 [-]: GETUPVAL R9 0
      15 [-]: LOADN R10 0  
      16 [-]: SETTABLEKS R10 R9 K8 ["BlinkTime"]
      17 [-]: GETUPVAL R9 0
      18 [-]: SETTABLEKS R5 R9 K9 ["DefaultColor"]
L 1:  19 [-]: JUMPIFNOT R4 L2
      20 [-]: GETUPVAL R10 0
      21 [-]: GETTABLEKS R9 R10 K10 ["SetIcon"]
      22 [-]: MOVE R10 R4  
      23 [-]: CALL R9 1 0  
L 2:  24 [-]: LOADN R9 0   
      25 [-]: JUMPIFNOTLT R9 R3 L3
      26 [-]: GETUPVAL R10 0
      27 [-]: GETTABLEKS R9 R10 K11 ["SetLabel"]
      28 [-]: MOVE R10 R0  
      29 [-]: LOADN R11 1  
      30 [-]: CALL R9 2 0  
      31 [-]: GETUPVAL R10 0
      32 [-]: GETTABLEKS R9 R10 K12 ["SetGoalLabel"]
      33 [-]: GETUPVAL R11 0
      34 [-]: GETTABLEKS R10 R11 K13 ["Localize"]
      35 [-]: MOVE R11 R1  
      36 [-]: DUPTABLE R12 16
      37 [-]: SETTABLEKS R2 R12 K14 ["CURRENT"]
      38 [-]: SETTABLEKS R3 R12 K15 ["TOTAL"]
      39 [-]: CALL R10 2 -1
      40 [-]: CALL R9 -1 0 
      41 [-]: GETUPVAL R10 0
      42 [-]: GETTABLEKS R9 R10 K17 ["SetValue"]
      43 [-]: DIV R10 R2 R3
      44 [-]: CALL R9 1 0  
      45 [-]: JUMP L4
     
L 3:  46 [-]: GETUPVAL R10 0
      47 [-]: GETTABLEKS R9 R10 K11 ["SetLabel"]
      48 [-]: LOADK R10 K18 [""]
      49 [-]: CALL R9 1 0  
      50 [-]: GETUPVAL R10 0
      51 [-]: GETTABLEKS R9 R10 K12 ["SetGoalLabel"]
      52 [-]: GETUPVAL R15 0
      53 [-]: GETTABLEKS R14 R15 K13 ["Localize"]
      54 [-]: MOVE R15 R0  
      55 [-]: CALL R14 1 1 
      56 [-]: MOVE R11 R14 
      57 [-]: LOADK R12 K19 [" "]
      58 [-]: MOVE R13 R1  
      59 [-]: CONCAT R10 R11 R13
      60 [-]: CALL R9 1 0  
      61 [-]: GETUPVAL R10 0
      62 [-]: GETTABLEKS R9 R10 K17 ["SetValue"]
      63 [-]: LOADN R10 -1 
      64 [-]: CALL R9 1 0  
L 4:  65 [-]: GETUPVAL R9 0
      66 [-]: SETTABLEKS R6 R9 K20 ["BlinkEnabled"]
      67 [-]: GETUPVAL R9 0
      68 [-]: SETTABLEKS R7 R9 K21 ["BlinkColor"]
      69 [-]: GETUPVAL R9 0
      70 [-]: SETTABLEKS R8 R9 K22 ["BlinkInterval"]
      71 [-]: RETURN R0 0  


; Name:            
; Defined at line: 183
; #Upvalues:       2
; #Parameters:     1
; Is_vararg:       0
; Max Stack Size:  13

       0 [-]: GETIMPORT R1 1 [nil]
       1 [-]: GETUPVAL R2 0
       2 [-]: CALL R1 1 1  
       3 [-]: NAMECALL R2 R0 K2 [0x5B89142C]
       4 [-]: CALL R2 1 1  
       5 [-]: FASTCALL1 62 R2 L0
       6 [-]: MOVE R4 R2   
       7 [-]: GETIMPORT R3 4 [nil]
       8 [-]: CALL R3 1 1  
L 0:   9 [-]: JUMPIFNOT R3 L1
      10 [-]: NAMECALL R3 R0 K5 [0xDE321E6F]
      11 [-]: CALL R3 1 1  
      12 [-]: MOVE R5 R1   
      13 [-]: NAMECALL R3 R3 K6 [0xBADB2A78]
      14 [-]: CALL R3 2 -1 
      15 [-]: RETURN R3 -1 
L 1:  16 [-]: LOADN R3 0   
      17 [-]: GETIMPORT R4 8 [nil]
      18 [-]: GETUPVAL R5 1
      19 [-]: CALL R4 1 3  
      20 [-]: FORGPREP_INEXT R4 L4
L 2:  21 [-]: MOVE R11 R8  
      22 [-]: NAMECALL R9 R2 K9 [0xE3A0BBCA]
      23 [-]: CALL R9 2 1  
      24 [-]: FASTCALL1 62 R9 L3
      25 [-]: MOVE R11 R9  
      26 [-]: GETIMPORT R10 4 [nil]
      27 [-]: CALL R10 1 1 
L 3:  28 [-]: JUMPIF R10 L4
      29 [-]: NAMECALL R10 R9 K5 [0xDE321E6F]
      30 [-]: CALL R10 1 1 
      31 [-]: MOVE R12 R1  
      32 [-]: NAMECALL R10 R10 K6 [0xBADB2A78]
      33 [-]: CALL R10 2 1 
      34 [-]: ADD R3 R3 R10
L 4:  35 [-]: FORGLOOP R4 L2 2 [inext]
      36 [-]: RETURN R3 1  


; Name:            
; Defined at line: 203
; #Upvalues:       3
; #Parameters:     1
; Is_vararg:       0
; Max Stack Size:  12

       0 [-]: NAMECALL R1 R0 K0 [0xA534C3AC]
       1 [-]: CALL R1 1 1  
       2 [-]: FASTCALL1 62 R1 L0
       3 [-]: MOVE R3 R1   
       4 [-]: GETIMPORT R2 2 [nil]
       5 [-]: CALL R2 1 1  
L 0:   6 [-]: JUMPIFNOT R2 L1
       7 [-]: RETURN R0 0  
L 1:   8 [-]: NEWTABLE R2 0 0
       9 [-]: GETIMPORT R3 4 [nil]
      10 [-]: GETUPVAL R4 0
      11 [-]: CALL R3 1 3  
      12 [-]: FORGPREP_INEXT R3 L4
L 2:  13 [-]: MOVE R10 R7  
      14 [-]: NAMECALL R8 R0 K5 [0xE3A0BBCA]
      15 [-]: CALL R8 2 1  
      16 [-]: FASTCALL1 62 R8 L3
      17 [-]: MOVE R10 R8  
      18 [-]: GETIMPORT R9 2 [nil]
      19 [-]: CALL R9 1 1  
L 3:  20 [-]: JUMPIF R9 L4 
      21 [-]: FASTCALL2 52 R2 R8 L4
      22 [-]: MOVE R10 R2  
      23 [-]: MOVE R11 R8  
      24 [-]: GETIMPORT R9 8 [nil]
      25 [-]: CALL R9 2 0  
L 4:  26 [-]: FORGLOOP R3 L2 2 [inext]
      27 [-]: GETIMPORT R3 11 [nil]
      28 [-]: CALL R3 0 1  
      29 [-]: SETTABLEKS R1 R3 K12 ["instigator"]
      30 [-]: SETTABLEKS R2 R3 K13 ["affected"]
      31 [-]: LOADN R4 5   
      32 [-]: SETTABLEKS R4 R3 K14 ["buffType"]
      33 [-]: GETUPVAL R4 1
      34 [-]: MOVE R5 R1   
      35 [-]: CALL R4 1 1  
      36 [-]: SETTABLEKS R4 R3 K15 ["buffData"]
      37 [-]: GETUPVAL R4 2
      38 [-]: SETTABLEKS R4 R3 K16 ["abilityType"]
      39 [-]: MOVE R6 R3   
      40 [-]: LOADB R7 1   
      41 [-]: LOADB R8 0   
      42 [-]: NAMECALL R4 R1 K17 [0x37E45FB5]
      43 [-]: CALL R4 4 0  
      44 [-]: RETURN R0 0  


; Name:            
; Defined at line: 227
; #Upvalues:       2
; #Parameters:     1
; Is_vararg:       0
; Max Stack Size:  12

       0 [-]: NAMECALL R1 R0 K0 [0xA534C3AC]
       1 [-]: CALL R1 1 1  
       2 [-]: FASTCALL1 62 R1 L0
       3 [-]: MOVE R3 R1   
       4 [-]: GETIMPORT R2 2 [nil]
       5 [-]: CALL R2 1 1  
L 0:   6 [-]: JUMPIFNOT R2 L1
       7 [-]: RETURN R0 0  
L 1:   8 [-]: NEWTABLE R2 0 0
       9 [-]: GETIMPORT R3 4 [nil]
      10 [-]: GETUPVAL R4 0
      11 [-]: CALL R3 1 3  
      12 [-]: FORGPREP_INEXT R3 L4
L 2:  13 [-]: MOVE R10 R7  
      14 [-]: NAMECALL R8 R0 K5 [0xE3A0BBCA]
      15 [-]: CALL R8 2 1  
      16 [-]: FASTCALL1 62 R8 L3
      17 [-]: MOVE R10 R8  
      18 [-]: GETIMPORT R9 2 [nil]
      19 [-]: CALL R9 1 1  
L 3:  20 [-]: JUMPIF R9 L4 
      21 [-]: FASTCALL2 52 R2 R8 L4
      22 [-]: MOVE R10 R2  
      23 [-]: MOVE R11 R8  
      24 [-]: GETIMPORT R9 8 [nil]
      25 [-]: CALL R9 2 0  
L 4:  26 [-]: FORGLOOP R3 L2 2 [inext]
      27 [-]: GETIMPORT R3 11 [nil]
      28 [-]: CALL R3 0 1  
      29 [-]: SETTABLEKS R1 R3 K12 ["instigator"]
      30 [-]: SETTABLEKS R2 R3 K13 ["affected"]
      31 [-]: GETUPVAL R4 1
      32 [-]: SETTABLEKS R4 R3 K14 ["abilityType"]
      33 [-]: MOVE R6 R3   
      34 [-]: LOADB R7 0   
      35 [-]: LOADB R8 0   
      36 [-]: NAMECALL R4 R1 K15 [0x37E45FB5]
      37 [-]: CALL R4 4 0  
      38 [-]: RETURN R0 0  


; Name:            
; Defined at line: 249
; #Upvalues:       1
; #Parameters:     2
; Is_vararg:       0
; Max Stack Size:  6

       0 [-]: NEWTABLE R2 2 0
       1 [-]: SETTABLEKS R0 R2 K0 ["Text"]
       2 [-]: SETTABLEKS R1 R2 K1 ["Timer"]
       3 [-]: GETUPVAL R4 0
       4 [-]: LENGTH R3 R4 
       5 [-]: JUMPXEQKN R3 K2 L0 NOT [5]
       6 [-]: GETIMPORT R3 5 [nil]
       7 [-]: GETUPVAL R4 0
       8 [-]: LOADN R5 1   
       9 [-]: CALL R3 2 0  
L 0:  10 [-]: GETUPVAL R4 0
      11 [-]: FASTCALL2 52 R4 R2 L1
      12 [-]: MOVE R5 R2   
      13 [-]: GETIMPORT R3 7 [nil]
      14 [-]: CALL R3 2 0  
L 1:  15 [-]: RETURN R0 0  


; Name:            
; Defined at line: 260
; #Upvalues:       18
; #Parameters:     0
; Is_vararg:       0
; Max Stack Size:  11

       0 [-]: GETIMPORT R0 2 [nil]
       1 [-]: LOADK R1 K3 ["%.1f"]
       2 [-]: GETIMPORT R2 5 [nil]
       3 [-]: GETUPVAL R3 1
       4 [-]: CALL R2 1 -1 
       5 [-]: CALL R0 -1 1 
       6 [-]: SETUPVAL R0 0
       7 [-]: GETUPVAL R1 2
       8 [-]: FASTCALL1 62 R1 L0
       9 [-]: GETIMPORT R0 7 [nil]
      10 [-]: CALL R0 1 1  
L 0:  11 [-]: JUMPIF R0 L9 
      12 [-]: GETUPVAL R0 2
      13 [-]: NAMECALL R0 R0 K8 [0xDE321E6F]
      14 [-]: CALL R0 1 1  
      15 [-]: NAMECALL R0 R0 K9 [0xAC03381F]
      16 [-]: CALL R0 1 1  
      17 [-]: JUMPIFNOT R0 L1
      18 [-]: GETUPVAL R0 3
      19 [-]: JUMPIFNOT R0 L1
      20 [-]: LOADB R0 0   
      21 [-]: SETUPVAL R0 3
      22 [-]: JUMP L2
     
L 1:  23 [-]: GETUPVAL R0 2
      24 [-]: NAMECALL R0 R0 K8 [0xDE321E6F]
      25 [-]: CALL R0 1 1  
      26 [-]: NAMECALL R0 R0 K9 [0xAC03381F]
      27 [-]: CALL R0 1 1  
      28 [-]: JUMPIF R0 L2 
      29 [-]: GETUPVAL R0 3
      30 [-]: JUMPIF R0 L2 
      31 [-]: LOADB R0 1   
      32 [-]: SETUPVAL R0 3
L 2:  33 [-]: GETUPVAL R0 4
      34 [-]: GETUPVAL R1 2
      35 [-]: CALL R0 1 1  
      36 [-]: GETUPVAL R1 5
      37 [-]: JUMPIFNOTLT R1 R0 L5
      38 [-]: GETIMPORT R0 11 [nil]
      39 [-]: LOADK R1 K12 ["/Lotus/Language/Items/RaidInfestedAntidotePickedUp"]
      40 [-]: NEWTABLE R2 0 0
      41 [-]: CALL R0 2 1  
      42 [-]: NEWTABLE R1 2 0
      43 [-]: SETTABLEKS R0 R1 K13 ["Text"]
      44 [-]: LOADN R2 5   
      45 [-]: SETTABLEKS R2 R1 K14 ["Timer"]
      46 [-]: GETUPVAL R3 6
      47 [-]: LENGTH R2 R3 
      48 [-]: JUMPXEQKN R2 K15 L3 NOT [5]
      49 [-]: GETIMPORT R2 18 [nil]
      50 [-]: GETUPVAL R3 6
      51 [-]: LOADN R4 1   
      52 [-]: CALL R2 2 0  
L 3:  53 [-]: GETUPVAL R3 6
      54 [-]: FASTCALL2 52 R3 R1 L4
      55 [-]: MOVE R4 R1   
      56 [-]: GETIMPORT R2 20 [nil]
      57 [-]: CALL R2 2 0  
L 4:  58 [-]: GETUPVAL R1 5
      59 [-]: ADDK R0 R1 K21 [1]
      60 [-]: SETUPVAL R0 5
      61 [-]: JUMP L7
     
L 5:  62 [-]: GETUPVAL R0 4
      63 [-]: GETUPVAL R1 2
      64 [-]: CALL R0 1 1  
      65 [-]: GETUPVAL R1 5
      66 [-]: JUMPIFNOTLT R0 R1 L7
      67 [-]: GETUPVAL R1 5
      68 [-]: SUBK R0 R1 K21 [1]
      69 [-]: SETUPVAL R0 5
      70 [-]: GETIMPORT R0 11 [nil]
      71 [-]: LOADK R1 K22 ["/Lotus/Language/Items/RaidInfestedAntidoteUsed"]
      72 [-]: NEWTABLE R2 0 0
      73 [-]: CALL R0 2 1  
      74 [-]: NEWTABLE R1 2 0
      75 [-]: SETTABLEKS R0 R1 K13 ["Text"]
      76 [-]: LOADN R2 5   
      77 [-]: SETTABLEKS R2 R1 K14 ["Timer"]
      78 [-]: GETUPVAL R3 6
      79 [-]: LENGTH R2 R3 
      80 [-]: JUMPXEQKN R2 K15 L6 NOT [5]
      81 [-]: GETIMPORT R2 18 [nil]
      82 [-]: GETUPVAL R3 6
      83 [-]: LOADN R4 1   
      84 [-]: CALL R2 2 0  
L 6:  85 [-]: GETUPVAL R3 6
      86 [-]: FASTCALL2 52 R3 R1 L7
      87 [-]: MOVE R4 R1   
      88 [-]: GETIMPORT R2 20 [nil]
      89 [-]: CALL R2 2 0  
L 7:  90 [-]: GETUPVAL R0 5
      91 [-]: LOADN R1 0   
      92 [-]: JUMPIFNOTLT R1 R0 L8
      93 [-]: GETUPVAL R0 7
      94 [-]: GETUPVAL R1 8
      95 [-]: CALL R0 1 0  
      96 [-]: JUMP L9
     
L 8:  97 [-]: GETUPVAL R0 9
      98 [-]: GETUPVAL R1 8
      99 [-]: CALL R0 1 0  
L 9: 100 [-]: LOADK R0 K23 [""]
     101 [-]: GETUPVAL R4 6
     102 [-]: LENGTH R3 R4 
     103 [-]: LOADN R1 1   
     104 [-]: LOADN R2 -1  
     105 [-]: FORNPREP R1 L13
L10: 106 [-]: GETUPVAL R5 6
     107 [-]: GETTABLE R4 R5 R3
     108 [-]: GETTABLEKS R6 R4 K14 ["Timer"]
     109 [-]: GETIMPORT R7 25 [nil]
     110 [-]: CALL R7 0 1  
     111 [-]: SUB R5 R6 R7 
     112 [-]: SETTABLEKS R5 R4 K14 ["Timer"]
     113 [-]: GETTABLEKS R5 R4 K14 ["Timer"]
     114 [-]: LOADN R6 0   
     115 [-]: JUMPIFNOTLT R6 R5 L11
     116 [-]: GETTABLEKS R5 R4 K13 ["Text"]
     117 [-]: LOADK R6 K26 ["<br>"]
     118 [-]: MOVE R7 R0   
     119 [-]: CONCAT R0 R5 R7
     120 [-]: JUMP L12
    
L11: 121 [-]: GETIMPORT R5 18 [nil]
     122 [-]: GETUPVAL R6 6
     123 [-]: MOVE R7 R3   
     124 [-]: CALL R5 2 0  
L12: 125 [-]: FORNLOOP R1 L10
L13: 126 [-]: GETUPVAL R1 10
     127 [-]: LOADN R2 21  
     128 [-]: JUMPIFEQ R1 R2 L16
     129 [-]: GETUPVAL R2 11
     130 [-]: FASTCALL1 62 R2 L14
     131 [-]: GETIMPORT R1 7 [nil]
     132 [-]: CALL R1 1 1  
L14: 133 [-]: JUMPIFNOT R1 L15
     134 [-]: GETIMPORT R1 29 [nil]
     135 [-]: LOADK R2 K30 ["J3ObjectiveLabel"]
     136 [-]: GETUPVAL R4 12
     137 [-]: GETTABLEKS R3 R4 K31 ["HT_LABEL"]
     138 [-]: LOADK R4 K32 [0.14999999999999999]
     139 [-]: LOADB R5 0   
     140 [-]: LOADB R6 0   
     141 [-]: CALL R1 5 1  
     142 [-]: SETUPVAL R1 11
L15: 143 [-]: GETUPVAL R2 11
     144 [-]: GETTABLEKS R1 R2 K33 ["SetLabel"]
     145 [-]: LOADK R3 K34 ["<p><font face=\"Noto Sans\">"]
     146 [-]: MOVE R4 R0   
     147 [-]: LOADK R5 K35 ["</font></p>"]
     148 [-]: CONCAT R2 R3 R5
     149 [-]: CALL R1 1 0  
L16: 150 [-]: GETUPVAL R1 3
     151 [-]: JUMPIFNOT R1 L34
     152 [-]: GETUPVAL R1 0
     153 [-]: GETUPVAL R2 13
     154 [-]: JUMPIFNOTEQ R1 R2 L17
     155 [-]: GETUPVAL R1 14
     156 [-]: CALL R1 0 1  
     157 [-]: JUMPIFNOT R1 L22
L17: 158 [-]: GETUPVAL R1 1
     159 [-]: LOADN R2 0   
     160 [-]: JUMPIFNOTLE R2 R1 L19
     161 [-]: GETUPVAL R1 1
     162 [-]: LOADN R2 25  
     163 [-]: JUMPIFNOTLT R1 R2 L19
     164 [-]: GETUPVAL R1 10
     165 [-]: LOADN R2 21  
     166 [-]: JUMPIFNOTEQ R1 R2 L18
     167 [-]: GETIMPORT R1 37 [nil]
     168 [-]: GETIMPORT R7 11 [nil]
     169 [-]: LOADK R8 K38 ["/Lotus/Language/Game/RaidArmorIntegrity"]
     170 [-]: LOADNIL R9   
     171 [-]: CALL R7 2 1  
     172 [-]: MOVE R3 R7   
     173 [-]: LOADK R4 K39 [" "]
     174 [-]: GETUPVAL R5 0
     175 [-]: LOADK R6 K40 ["%"]
     176 [-]: CONCAT R2 R3 R6
     177 [-]: SETTABLEKS R2 R1 K13 ["Text"]
     178 [-]: GETIMPORT R1 37 [nil]
     179 [-]: LOADN R2 34  
     180 [-]: SETTABLEKS R2 R1 K41 ["Color"]
     181 [-]: JUMP L21
    
L18: 182 [-]: GETUPVAL R1 15
     183 [-]: LOADK R2 K38 ["/Lotus/Language/Game/RaidArmorIntegrity"]
     184 [-]: GETUPVAL R4 0
     185 [-]: LOADK R5 K40 ["%"]
     186 [-]: CONCAT R3 R4 R5
     187 [-]: GETUPVAL R4 0
     188 [-]: LOADN R5 100 
     189 [-]: LOADNIL R6   
     190 [-]: LOADN R7 34  
     191 [-]: LOADB R8 0   
     192 [-]: CALL R1 7 0  
     193 [-]: JUMP L21
    
L19: 194 [-]: GETUPVAL R1 10
     195 [-]: LOADN R2 21  
     196 [-]: JUMPIFNOTEQ R1 R2 L20
     197 [-]: GETIMPORT R1 37 [nil]
     198 [-]: GETIMPORT R7 11 [nil]
     199 [-]: LOADK R8 K38 ["/Lotus/Language/Game/RaidArmorIntegrity"]
     200 [-]: LOADNIL R9   
     201 [-]: CALL R7 2 1  
     202 [-]: MOVE R3 R7   
     203 [-]: LOADK R4 K39 [" "]
     204 [-]: GETUPVAL R5 0
     205 [-]: LOADK R6 K40 ["%"]
     206 [-]: CONCAT R2 R3 R6
     207 [-]: SETTABLEKS R2 R1 K13 ["Text"]
     208 [-]: GETIMPORT R1 37 [nil]
     209 [-]: LOADN R2 38  
     210 [-]: SETTABLEKS R2 R1 K41 ["Color"]
     211 [-]: JUMP L21
    
L20: 212 [-]: GETUPVAL R1 15
     213 [-]: LOADK R2 K38 ["/Lotus/Language/Game/RaidArmorIntegrity"]
     214 [-]: GETUPVAL R4 0
     215 [-]: LOADK R5 K40 ["%"]
     216 [-]: CONCAT R3 R4 R5
     217 [-]: GETUPVAL R4 0
     218 [-]: LOADN R5 100 
     219 [-]: LOADNIL R6   
     220 [-]: LOADN R7 38  
     221 [-]: LOADB R8 0   
     222 [-]: CALL R1 7 0  
L21: 223 [-]: GETUPVAL R1 0
     224 [-]: SETUPVAL R1 13
     225 [-]: JUMP L26
    
L22: 226 [-]: GETUPVAL R1 1
     227 [-]: JUMPXEQKN R1 K42 L26 NOT [0]
     228 [-]: GETUPVAL R1 14
     229 [-]: CALL R1 0 1  
     230 [-]: JUMPIF R1 L26
     231 [-]: GETUPVAL R1 16
     232 [-]: LOADK R2 K43 [1.5]
     233 [-]: JUMPIFNOTLE R2 R1 L24
     234 [-]: GETUPVAL R1 10
     235 [-]: LOADN R2 21  
     236 [-]: JUMPIFNOTEQ R1 R2 L23
     237 [-]: GETIMPORT R1 37 [nil]
     238 [-]: GETIMPORT R2 11 [nil]
     239 [-]: LOADK R3 K44 ["/Lotus/Language/Game/RaidVitalsFailing"]
     240 [-]: LOADNIL R4   
     241 [-]: CALL R2 2 1  
     242 [-]: SETTABLEKS R2 R1 K13 ["Text"]
     243 [-]: GETIMPORT R1 37 [nil]
     244 [-]: LOADN R2 34  
     245 [-]: SETTABLEKS R2 R1 K41 ["Color"]
     246 [-]: JUMP L26
    
L23: 247 [-]: GETUPVAL R1 15
     248 [-]: LOADK R2 K44 ["/Lotus/Language/Game/RaidVitalsFailing"]
     249 [-]: LOADK R3 K23 [""]
     250 [-]: GETUPVAL R4 0
     251 [-]: LOADN R5 100 
     252 [-]: LOADNIL R6   
     253 [-]: LOADNIL R7   
     254 [-]: LOADB R8 1   
     255 [-]: LOADN R9 34  
     256 [-]: LOADK R10 K45 [0.25]
     257 [-]: CALL R1 9 0  
     258 [-]: JUMP L26
    
L24: 259 [-]: GETUPVAL R1 10
     260 [-]: LOADN R2 21  
     261 [-]: JUMPIFNOTEQ R1 R2 L25
     262 [-]: GETIMPORT R1 37 [nil]
     263 [-]: GETIMPORT R2 11 [nil]
     264 [-]: LOADK R3 K46 ["/Lotus/Language/Game/RaidLifeSupportFailImminent"]
     265 [-]: LOADNIL R4   
     266 [-]: CALL R2 2 1  
     267 [-]: SETTABLEKS R2 R1 K13 ["Text"]
     268 [-]: GETIMPORT R1 37 [nil]
     269 [-]: LOADN R2 34  
     270 [-]: SETTABLEKS R2 R1 K41 ["Color"]
     271 [-]: JUMP L26
    
L25: 272 [-]: GETUPVAL R1 15
     273 [-]: LOADK R2 K46 ["/Lotus/Language/Game/RaidLifeSupportFailImminent"]
     274 [-]: LOADK R3 K23 [""]
     275 [-]: GETUPVAL R4 0
     276 [-]: LOADN R5 100 
     277 [-]: LOADNIL R6   
     278 [-]: LOADNIL R7   
     279 [-]: LOADB R8 1   
     280 [-]: LOADN R9 34  
     281 [-]: LOADK R10 K45 [0.25]
     282 [-]: CALL R1 9 0  
L26: 283 [-]: GETUPVAL R1 17
     284 [-]: JUMPIFNOT R1 L36
     285 [-]: GETUPVAL R2 17
     286 [-]: GETTABLEKS R1 R2 K47 ["BlinkColor"]
     287 [-]: JUMPIFNOT R1 L31
     288 [-]: LOADNIL R1   
     289 [-]: GETUPVAL R3 17
     290 [-]: GETTABLEKS R2 R3 K48 ["BlinkEnabled"]
     291 [-]: JUMPIFNOT R2 L29
     292 [-]: GETUPVAL R3 17
     293 [-]: GETTABLEKS R2 R3 K49 ["BlinkTime"]
     294 [-]: LOADN R3 0   
     295 [-]: JUMPIFNOTLE R2 R3 L27
     296 [-]: GETUPVAL R2 17
     297 [-]: GETUPVAL R5 17
     298 [-]: GETTABLEKS R4 R5 K51 ["BlinkInterval"]
     299 [-]: MULK R3 R4 K50 [2]
     300 [-]: SETTABLEKS R3 R2 K49 ["BlinkTime"]
     301 [-]: GETUPVAL R2 17
     302 [-]: GETTABLEKS R1 R2 K47 ["BlinkColor"]
L27: 303 [-]: GETUPVAL R3 17
     304 [-]: GETTABLEKS R2 R3 K49 ["BlinkTime"]
     305 [-]: LOADN R3 0   
     306 [-]: JUMPIFNOTLT R3 R2 L28
     307 [-]: GETUPVAL R3 17
     308 [-]: GETTABLEKS R2 R3 K49 ["BlinkTime"]
     309 [-]: GETUPVAL R4 17
     310 [-]: GETTABLEKS R3 R4 K51 ["BlinkInterval"]
     311 [-]: JUMPIFNOTLT R2 R3 L28
     312 [-]: LOADN R1 38  
L28: 313 [-]: GETUPVAL R2 17
     314 [-]: GETUPVAL R5 17
     315 [-]: GETTABLEKS R4 R5 K49 ["BlinkTime"]
     316 [-]: GETIMPORT R5 25 [nil]
     317 [-]: CALL R5 0 1  
     318 [-]: SUB R3 R4 R5 
     319 [-]: SETTABLEKS R3 R2 K49 ["BlinkTime"]
     320 [-]: JUMP L30
    
L29: 321 [-]: GETUPVAL R2 17
     322 [-]: LOADN R3 0   
     323 [-]: SETTABLEKS R3 R2 K49 ["BlinkTime"]
     324 [-]: LOADN R1 38  
L30: 325 [-]: GETUPVAL R2 17
     326 [-]: SETTABLEKS R1 R2 K52 ["BlinkLastColor"]
     327 [-]: JUMPXEQKNIL R1 L36
     328 [-]: GETUPVAL R3 17
     329 [-]: GETTABLEKS R2 R3 K53 ["SetGoalColor"]
     330 [-]: MOVE R3 R1   
     331 [-]: CALL R2 1 0  
     332 [-]: RETURN R0 0  
L31: 333 [-]: GETUPVAL R2 17
     334 [-]: GETTABLEKS R1 R2 K54 ["DefaultColor"]
     335 [-]: JUMPIFNOT R1 L32
     336 [-]: GETUPVAL R2 17
     337 [-]: GETTABLEKS R1 R2 K53 ["SetGoalColor"]
     338 [-]: GETUPVAL R3 17
     339 [-]: GETTABLEKS R2 R3 K54 ["DefaultColor"]
     340 [-]: CALL R1 1 0  
     341 [-]: RETURN R0 0  
L32: 342 [-]: GETUPVAL R2 17
     343 [-]: GETTABLEKS R1 R2 K48 ["BlinkEnabled"]
     344 [-]: JUMPIF R1 L33
     345 [-]: GETUPVAL R2 17
     346 [-]: GETTABLEKS R1 R2 K52 ["BlinkLastColor"]
     347 [-]: LOADN R2 38  
     348 [-]: JUMPIFEQ R1 R2 L36
L33: 349 [-]: GETUPVAL R1 17
     350 [-]: LOADB R2 0   
     351 [-]: SETTABLEKS R2 R1 K48 ["BlinkEnabled"]
     352 [-]: GETUPVAL R1 17
     353 [-]: LOADN R2 38  
     354 [-]: SETTABLEKS R2 R1 K52 ["BlinkLastColor"]
     355 [-]: GETUPVAL R2 17
     356 [-]: GETTABLEKS R1 R2 K53 ["SetGoalColor"]
     357 [-]: LOADN R2 38  
     358 [-]: CALL R1 1 0  
     359 [-]: RETURN R0 0  
L34: 360 [-]: GETUPVAL R1 17
     361 [-]: JUMPIFNOT R1 L35
     362 [-]: GETIMPORT R1 56 [nil]
     363 [-]: GETUPVAL R2 17
     364 [-]: CALL R1 1 0  
     365 [-]: LOADNIL R1   
     366 [-]: SETUPVAL R1 17
L35: 367 [-]: LOADN R1 -1  
     368 [-]: SETUPVAL R1 13
L36: 369 [-]: RETURN R0 0  


; Name:            
; Defined at line: 377
; #Upvalues:       0
; #Parameters:     1
; Is_vararg:       0
; Max Stack Size:  4

       0 [-]: GETIMPORT R2 2 [nil]
       1 [-]: FASTCALL1 62 R2 L0
       2 [-]: GETIMPORT R1 4 [nil]
       3 [-]: CALL R1 1 1  
L 0:   4 [-]: JUMPIF R1 L1 
       5 [-]: GETIMPORT R1 2 [nil]
       6 [-]: LOADB R2 1   
       7 [-]: LOADB R3 0   
       8 [-]: CALL R1 2 0  
L 1:   9 [-]: RETURN R0 0  


; Name:            
; Defined at line: 383
; #Upvalues:       0
; #Parameters:     2
; Is_vararg:       0
; Max Stack Size:  5

       0 [-]: GETIMPORT R3 2 [nil]
       1 [-]: FASTCALL1 62 R3 L0
       2 [-]: GETIMPORT R2 4 [nil]
       3 [-]: CALL R2 1 1  
L 0:   4 [-]: JUMPIF R2 L1 
       5 [-]: GETIMPORT R2 2 [nil]
       6 [-]: LOADB R3 0   
       7 [-]: LOADB R4 0   
       8 [-]: CALL R2 2 0  
L 1:   9 [-]: RETURN R0 0  


; Name:            
; Defined at line: 389
; #Upvalues:       0
; #Parameters:     1
; Is_vararg:       0
; Max Stack Size:  5

       0 [-]: GETIMPORT R1 1 [nil]
       1 [-]: NAMECALL R1 R1 K2 [0xFB64E76C]
       2 [-]: CALL R1 1 1  
       3 [-]: NAMECALL R1 R1 K3 [0xA534C3AC]
       4 [-]: CALL R1 1 1  
       5 [-]: JUMPIFEQ R0 R1 L0
       6 [-]: RETURN R0 0  
L 0:   7 [-]: GETIMPORT R3 6 [nil]
       8 [-]: FASTCALL1 62 R3 L1
       9 [-]: GETIMPORT R2 8 [nil]
      10 [-]: CALL R2 1 1  
L 1:  11 [-]: JUMPIF R2 L2 
      12 [-]: GETIMPORT R2 6 [nil]
      13 [-]: LOADB R3 1   
      14 [-]: LOADB R4 1   
      15 [-]: CALL R2 2 0  
L 2:  16 [-]: RETURN R0 0  


; Name:            
; Defined at line: 400
; #Upvalues:       0
; #Parameters:     2
; Is_vararg:       0
; Max Stack Size:  6

       0 [-]: GETIMPORT R2 1 [nil]
       1 [-]: NAMECALL R2 R2 K2 [0xFB64E76C]
       2 [-]: CALL R2 1 1  
       3 [-]: NAMECALL R2 R2 K3 [0xA534C3AC]
       4 [-]: CALL R2 1 1  
       5 [-]: JUMPIFEQ R1 R2 L0
       6 [-]: RETURN R0 0  
L 0:   7 [-]: GETIMPORT R4 6 [nil]
       8 [-]: FASTCALL1 62 R4 L1
       9 [-]: GETIMPORT R3 8 [nil]
      10 [-]: CALL R3 1 1  
L 1:  11 [-]: JUMPIF R3 L2 
      12 [-]: GETIMPORT R3 6 [nil]
      13 [-]: LOADB R4 0   
      14 [-]: LOADB R5 1   
      15 [-]: CALL R3 2 0  
L 2:  16 [-]: RETURN R0 0  


; Name:            
; Defined at line: 411
; #Upvalues:       3
; #Parameters:     0
; Is_vararg:       0
; Max Stack Size:  12

       0 [-]: GETUPVAL R0 0
       1 [-]: NAMECALL R0 R0 K0 [0xA534C3AC]
       2 [-]: CALL R0 1 1  
       3 [-]: FASTCALL1 62 R0 L0
       4 [-]: MOVE R2 R0   
       5 [-]: GETIMPORT R1 2 [nil]
       6 [-]: CALL R1 1 1  
L 0:   7 [-]: JUMPIFNOT R1 L1
       8 [-]: RETURN R0 0  
L 1:   9 [-]: GETUPVAL R1 0
      10 [-]: NAMECALL R1 R1 K0 [0xA534C3AC]
      11 [-]: CALL R1 1 1  
      12 [-]: NAMECALL R1 R1 K3 [0x1AC1655C]
      13 [-]: CALL R1 1 1  
      14 [-]: NAMECALL R1 R1 K4 [0x76AA1E1B]
      15 [-]: CALL R1 1 1  
      16 [-]: DIVK R3 R1 K5 [50]
      17 [-]: FASTCALL1 12 R3 L2
      18 [-]: GETIMPORT R2 8 [nil]
      19 [-]: CALL R2 1 1  
L 2:  20 [-]: LOADN R3 0   
      21 [-]: LOADN R6 0   
      22 [-]: SUBK R4 R2 K9 [1]
      23 [-]: LOADN R5 1   
      24 [-]: FORNPREP R4 L5
L 3:  25 [-]: LOADK R9 K10 [0.050000000000000003]
      26 [-]: LOADK R11 K11 [0.0050000000000000001]
      27 [-]: MUL R10 R11 R6
      28 [-]: SUB R8 R9 R10
      29 [-]: FASTCALL2K 18 R8 K12 L4 [0.01]
      30 [-]: LOADK R9 K12 [0.01]
      31 [-]: GETIMPORT R7 14 [nil]
      32 [-]: CALL R7 2 1  
L 4:  33 [-]: ADD R3 R3 R7 
      34 [-]: FORNLOOP R4 L3
L 5:  35 [-]: GETUPVAL R5 2
      36 [-]: GETUPVAL R7 2
      37 [-]: MUL R6 R7 R3 
      38 [-]: SUB R4 R5 R6 
      39 [-]: SETUPVAL R4 1
      40 [-]: RETURN R0 0  


; Name:            
; Defined at line: 427
; #Upvalues:       2
; #Parameters:     0
; Is_vararg:       0
; Max Stack Size:  4

       0 [-]: GETUPVAL R0 0
       1 [-]: GETIMPORT R2 1 [nil]
       2 [-]: LOADK R3 K2 ["WipeEvent"]
       3 [-]: CALL R2 1 1  
       4 [-]: LOADN R3 0   
       5 [-]: NAMECALL R0 R0 K3 [0x0EB34C69]
       6 [-]: CALL R0 3 1  
       7 [-]: JUMPXEQKN R0 K4 L0 NOT [1]
       8 [-]: LOADN R0 20  
       9 [-]: RETURN R0 1  
L 0:  10 [-]: GETUPVAL R0 1
      11 [-]: RETURN R0 1  


; Name:            
; Defined at line: 435
; #Upvalues:       8
; #Parameters:     0
; Is_vararg:       0
; Max Stack Size:  14

       0 [-]: GETUPVAL R1 0
       1 [-]: NAMECALL R1 R1 K0 [0xBB610E5B]
       2 [-]: CALL R1 1 1  
       3 [-]: FASTCALL1 62 R1 L0
       4 [-]: GETIMPORT R0 2 [nil]
       5 [-]: CALL R0 1 1  
L 0:   6 [-]: JUMPIF R0 L1 
       7 [-]: GETUPVAL R0 0
       8 [-]: NAMECALL R0 R0 K0 [0xBB610E5B]
       9 [-]: CALL R0 1 1  
      10 [-]: NAMECALL R0 R0 K3 [0x2047CFE7]
      11 [-]: CALL R0 1 1  
      12 [-]: JUMPIFNOT R0 L4
      13 [-]: GETUPVAL R0 1
      14 [-]: LOADN R1 100 
      15 [-]: JUMPIFNOTLT R0 R1 L4
L 1:  16 [-]: LOADN R0 100 
      17 [-]: SETUPVAL R0 1
      18 [-]: GETUPVAL R1 0
      19 [-]: NAMECALL R1 R1 K0 [0xBB610E5B]
      20 [-]: CALL R1 1 1  
      21 [-]: FASTCALL1 62 R1 L2
      22 [-]: GETIMPORT R0 2 [nil]
      23 [-]: CALL R0 1 1  
L 2:  24 [-]: JUMPIFNOT R0 L3
      25 [-]: GETIMPORT R0 5 [nil]
      26 [-]: LOADK R2 K6 ["J3Golem.lua::InfestedMeter() - resetting armor to 100, reason: "]
      27 [-]: LOADK R3 K7 ["localPlayer:GetAvatar() returned nil"]
      28 [-]: CONCAT R1 R2 R3
      29 [-]: CALL R0 1 0  
      30 [-]: RETURN R0 0  
L 3:  31 [-]: GETIMPORT R0 5 [nil]
      32 [-]: LOADK R2 K6 ["J3Golem.lua::InfestedMeter() - resetting armor to 100, reason: "]
      33 [-]: LOADK R3 K8 ["localPlayer:GetAvatar():IsKilled() and armor < 100"]
      34 [-]: CONCAT R1 R2 R3
      35 [-]: CALL R0 1 0  
      36 [-]: RETURN R0 0  
L 4:  37 [-]: GETUPVAL R0 2
      38 [-]: GETUPVAL R1 0
      39 [-]: CALL R0 1 1  
      40 [-]: JUMPIFNOT R0 L6
      41 [-]: GETUPVAL R0 1
      42 [-]: LOADN R1 25  
      43 [-]: JUMPIFNOTLT R0 R1 L11
      44 [-]: LOADN R1 25  
      45 [-]: GETUPVAL R3 1
      46 [-]: GETIMPORT R5 11 [nil]
      47 [-]: CALL R5 0 1  
      48 [-]: MULK R4 R5 K9 [0]
      49 [-]: ADD R2 R3 R4 
      50 [-]: FASTCALL2 19 R1 R2 L5
      51 [-]: GETIMPORT R0 14 [nil]
      52 [-]: CALL R0 2 1  
L 5:  53 [-]: SETUPVAL R0 1
      54 [-]: JUMP L11
    
L 6:  55 [-]: GETUPVAL R1 0
      56 [-]: NAMECALL R1 R1 K0 [0xBB610E5B]
      57 [-]: CALL R1 1 1  
      58 [-]: FASTCALL1 62 R1 L7
      59 [-]: GETIMPORT R0 2 [nil]
      60 [-]: CALL R0 1 1  
L 7:  61 [-]: JUMPIF R0 L11
      62 [-]: GETUPVAL R0 0
      63 [-]: NAMECALL R0 R0 K0 [0xBB610E5B]
      64 [-]: CALL R0 1 1  
      65 [-]: NAMECALL R0 R0 K15 [0x73901ACF]
      66 [-]: CALL R0 1 1  
      67 [-]: JUMPIF R0 L11
      68 [-]: GETUPVAL R2 3
      69 [-]: GETTABLEKS R1 R2 K16 [0x06D055F9]
      70 [-]: LOADB R2 0   
      71 [-]: LOADN R3 1   
      72 [-]: LOADN R4 0   
      73 [-]: CALL R1 3 1  
      74 [-]: GETUPVAL R3 1
      75 [-]: GETIMPORT R5 11 [nil]
      76 [-]: CALL R5 0 1  
      77 [-]: GETUPVAL R7 4
      78 [-]: GETIMPORT R9 18 [nil]
      79 [-]: LOADK R10 K19 ["WipeEvent"]
      80 [-]: CALL R9 1 1  
      81 [-]: LOADN R10 0  
      82 [-]: NAMECALL R7 R7 K20 [0x0EB34C69]
      83 [-]: CALL R7 3 1  
      84 [-]: JUMPXEQKN R7 K21 L8 NOT [1]
      85 [-]: LOADN R6 20  
      86 [-]: JUMP L9
     
L 8:  87 [-]: GETUPVAL R6 5
      88 [-]: JUMP L9
     
L 9:  89 [-]: MUL R4 R5 R6 
      90 [-]: SUB R2 R3 R4 
      91 [-]: FASTCALL2 18 R1 R2 L10
      92 [-]: GETIMPORT R0 23 [nil]
      93 [-]: CALL R0 2 1  
L10:  94 [-]: SETUPVAL R0 1
L11:  95 [-]: LOADN R1 20  
      96 [-]: GETUPVAL R4 1
      97 [-]: DIVK R3 R4 K24 [5]
      98 [-]: FASTCALL1 7 R3 L12
      99 [-]: GETIMPORT R2 26 [nil]
     100 [-]: CALL R2 1 1  
L12: 101 [-]: SUB R0 R1 R2 
     102 [-]: GETUPVAL R1 6
     103 [-]: JUMPIFEQ R0 R1 L14
     104 [-]: GETUPVAL R1 0
     105 [-]: NAMECALL R1 R1 K0 [0xBB610E5B]
     106 [-]: CALL R1 1 1  
     107 [-]: NAMECALL R1 R1 K27 [0xDE321E6F]
     108 [-]: CALL R1 1 1  
     109 [-]: GETUPVAL R2 6
     110 [-]: LOADN R3 0   
     111 [-]: JUMPIFNOTLT R3 R2 L13
     112 [-]: LOADN R4 15  
     113 [-]: LOADN R5 2   
     114 [-]: LOADN R8 100 
     115 [-]: GETUPVAL R10 6
     116 [-]: MULK R9 R10 K24 [5]
     117 [-]: SUB R7 R8 R9 
     118 [-]: DIVK R6 R7 K28 [100]
     119 [-]: LOADNIL R7   
     120 [-]: LOADNIL R8   
     121 [-]: LOADN R9 25  
     122 [-]: GETIMPORT R10 18 [nil]
     123 [-]: CALL R10 0 1 
     124 [-]: GETIMPORT R12 30 [nil]
     125 [-]: NAMECALL R12 R12 K31 [0x18D05D30]
     126 [-]: CALL R12 1 1 
     127 [-]: NOT R11 R12  
     128 [-]: NAMECALL R2 R1 K32 [0x12DD9DA2]
     129 [-]: CALL R2 9 0  
L13: 130 [-]: SETUPVAL R0 6
     131 [-]: LOADN R2 0   
     132 [-]: JUMPIFNOTLT R2 R0 L14
     133 [-]: LOADN R4 15  
     134 [-]: LOADN R5 2   
     135 [-]: LOADN R8 100 
     136 [-]: MULK R9 R0 K24 [5]
     137 [-]: SUB R7 R8 R9 
     138 [-]: DIVK R6 R7 K28 [100]
     139 [-]: LOADNIL R7   
     140 [-]: LOADNIL R8   
     141 [-]: LOADN R9 25  
     142 [-]: GETIMPORT R10 18 [nil]
     143 [-]: CALL R10 0 1 
     144 [-]: GETIMPORT R12 30 [nil]
     145 [-]: NAMECALL R12 R12 K31 [0x18D05D30]
     146 [-]: CALL R12 1 1 
     147 [-]: NOT R11 R12  
     148 [-]: NAMECALL R2 R1 K33 [0x5E6704FF]
     149 [-]: CALL R2 9 0  
L14: 150 [-]: GETUPVAL R2 7
     151 [-]: FASTCALL1 62 R2 L15
     152 [-]: GETIMPORT R1 2 [nil]
     153 [-]: CALL R1 1 1  
L15: 154 [-]: JUMPIF R1 L16
     155 [-]: GETUPVAL R1 1
     156 [-]: GETUPVAL R3 7
     157 [-]: GETTABLEKS R2 R3 K34 ["Value"]
     158 [-]: JUMPIFNOTLE R1 R2 L16
     159 [-]: GETUPVAL R2 7
     160 [-]: GETTABLEKS R1 R2 K35 ["Callback"]
     161 [-]: CALL R1 0 0  
     162 [-]: LOADNIL R1   
     163 [-]: SETUPVAL R1 7
L16: 164 [-]: RETURN R0 0  


; Name:            
; Defined at line: 474
; #Upvalues:       5
; #Parameters:     0
; Is_vararg:       0
; Max Stack Size:  5

       0 [-]: GETUPVAL R0 0
       1 [-]: GETIMPORT R2 1 [nil]
       2 [-]: LOADK R3 K2 ["Infested Rate"]
       3 [-]: CALL R2 1 1  
       4 [-]: GETIMPORT R3 4 [nil]
       5 [-]: GETUPVAL R4 1
       6 [-]: CALL R3 1 -1 
       7 [-]: NAMECALL R0 R0 K5 [0xC7A98999]
       8 [-]: CALL R0 -1 0 
       9 [-]: GETUPVAL R0 0
      10 [-]: GETIMPORT R2 1 [nil]
      11 [-]: LOADK R3 K6 ["Safe Counter"]
      12 [-]: CALL R2 1 1  
      13 [-]: GETIMPORT R3 4 [nil]
      14 [-]: GETUPVAL R4 2
      15 [-]: CALL R3 1 -1 
      16 [-]: NAMECALL R0 R0 K5 [0xC7A98999]
      17 [-]: CALL R0 -1 0 
      18 [-]: GETUPVAL R0 0
      19 [-]: GETIMPORT R2 1 [nil]
      20 [-]: LOADK R3 K7 ["Infest Counter"]
      21 [-]: CALL R2 1 1  
      22 [-]: GETIMPORT R3 4 [nil]
      23 [-]: GETUPVAL R4 3
      24 [-]: CALL R3 1 -1 
      25 [-]: NAMECALL R0 R0 K5 [0xC7A98999]
      26 [-]: CALL R0 -1 0 
      27 [-]: GETUPVAL R0 0
      28 [-]: GETIMPORT R2 1 [nil]
      29 [-]: LOADK R3 K8 ["Armor Stage"]
      30 [-]: CALL R2 1 1  
      31 [-]: GETIMPORT R3 4 [nil]
      32 [-]: GETUPVAL R4 4
      33 [-]: CALL R3 1 -1 
      34 [-]: NAMECALL R0 R0 K5 [0xC7A98999]
      35 [-]: CALL R0 -1 0 
      36 [-]: RETURN R0 0  


; Name:            
; Defined at line: 481
; #Upvalues:       20
; #Parameters:     0
; Is_vararg:       0
; Max Stack Size:  6

       0 [-]: GETIMPORT R0 1 [nil]
       1 [-]: NEWCLOSURE R1 P0
       2 [-]: MOVE R2 R0   
       3 [-]: MOVE R2 R1   
       4 [-]: MOVE R2 R2   
       5 [-]: SETTABLEKS R1 R0 K2 ["RaidPlayerZone"]
       6 [-]: GETIMPORT R0 1 [nil]
       7 [-]: NEWCLOSURE R1 P1
       8 [-]: MOVE R2 R1   
       9 [-]: MOVE R2 R3   
      10 [-]: MOVE R2 R4   
      11 [-]: MOVE R2 R5   
      12 [-]: MOVE R2 R6   
      13 [-]: MOVE R2 R7   
      14 [-]: MOVE R2 R8   
      15 [-]: MOVE R2 R9   
      16 [-]: MOVE R2 R10  
      17 [-]: SETTABLEKS R1 R0 K3 ["RaidUsedSyringe"]
      18 [-]: GETIMPORT R0 1 [nil]
      19 [-]: DUPCLOSURE R1 K4 []
      20 [-]: MOVE R2 R11  
      21 [-]: SETTABLEKS R1 R0 K5 ["RaidHasAntidote"]
      22 [-]: GETIMPORT R0 1 [nil]
      23 [-]: NEWCLOSURE R1 P3
      24 [-]: MOVE R2 R12  
      25 [-]: SETTABLEKS R1 R0 K6 ["RaidSetBuffTimer"]
      26 [-]: GETIMPORT R0 1 [nil]
      27 [-]: NEWCLOSURE R1 P4
      28 [-]: MOVE R2 R13  
      29 [-]: SETTABLEKS R1 R0 K7 ["SetArmorIntegrityCallback"]
      30 [-]: GETIMPORT R0 9 [nil]
      31 [-]: NAMECALL R0 R0 K10 [0x78298275]
      32 [-]: CALL R0 1 1  
      33 [-]: SETUPVAL R0 14
L 0:  34 [-]: GETUPVAL R1 14
      35 [-]: FASTCALL1 62 R1 L1
      36 [-]: GETIMPORT R0 12 [nil]
      37 [-]: CALL R0 1 1  
L 1:  38 [-]: JUMPIFNOT R0 L2
      39 [-]: GETIMPORT R0 14 [nil]
      40 [-]: LOADN R1 0   
      41 [-]: CALL R0 1 0  
      42 [-]: GETIMPORT R0 9 [nil]
      43 [-]: NAMECALL R0 R0 K10 [0x78298275]
      44 [-]: CALL R0 1 1  
      45 [-]: SETUPVAL R0 14
      46 [-]: JUMPBACK L0  
L 2:  47 [-]: GETUPVAL R0 14
      48 [-]: NAMECALL R0 R0 K15 [0x5E651723]
      49 [-]: CALL R0 1 1  
      50 [-]: SETUPVAL R0 15
L 3:  51 [-]: GETUPVAL R1 15
      52 [-]: FASTCALL1 62 R1 L4
      53 [-]: GETIMPORT R0 12 [nil]
      54 [-]: CALL R0 1 1  
L 4:  55 [-]: JUMPIFNOT R0 L5
      56 [-]: GETIMPORT R0 14 [nil]
      57 [-]: LOADN R1 0   
      58 [-]: CALL R0 1 0  
      59 [-]: GETUPVAL R0 14
      60 [-]: NAMECALL R0 R0 K15 [0x5E651723]
      61 [-]: CALL R0 1 1  
      62 [-]: SETUPVAL R0 15
      63 [-]: JUMPBACK L3  
L 5:  64 [-]: GETUPVAL R0 16
      65 [-]: NAMECALL R0 R0 K16 [0x33307F92]
      66 [-]: CALL R0 1 1  
L 6:  67 [-]: FASTCALL1 62 R0 L7
      68 [-]: MOVE R2 R0   
      69 [-]: GETIMPORT R1 12 [nil]
      70 [-]: CALL R1 1 1  
L 7:  71 [-]: JUMPIFNOT R1 L8
      72 [-]: GETIMPORT R1 14 [nil]
      73 [-]: LOADN R2 0   
      74 [-]: CALL R1 1 0  
      75 [-]: GETUPVAL R1 16
      76 [-]: NAMECALL R1 R1 K16 [0x33307F92]
      77 [-]: CALL R1 1 1  
      78 [-]: MOVE R0 R1   
      79 [-]: JUMPBACK L6  
L 8:  80 [-]: GETUPVAL R2 17
      81 [-]: FASTCALL1 62 R2 L9
      82 [-]: GETIMPORT R1 12 [nil]
      83 [-]: CALL R1 1 1  
L 9:  84 [-]: JUMPIFNOT R1 L10
      85 [-]: GETIMPORT R1 9 [nil]
      86 [-]: GETUPVAL R3 18
      87 [-]: GETIMPORT R4 18 [nil]
      88 [-]: GETIMPORT R5 20 [nil]
      89 [-]: NAMECALL R1 R1 K21 [0x05909209]
      90 [-]: CALL R1 4 1  
      91 [-]: SETUPVAL R1 17
L10:  92 [-]: GETUPVAL R1 16
      93 [-]: NAMECALL R1 R1 K22 [0x5C390F04]
      94 [-]: CALL R1 1 1  
      95 [-]: SETUPVAL R1 6
      96 [-]: GETUPVAL R1 6
      97 [-]: LOADN R2 21  
      98 [-]: JUMPIFNOTEQ R1 R2 L11
      99 [-]: LOADK R1 K23 [1.5]
     100 [-]: SETUPVAL R1 19
     101 [-]: JUMP L12
    
L11: 102 [-]: LOADN R1 1   
     103 [-]: SETUPVAL R1 19
L12: 104 [-]: GETIMPORT R1 1 [nil]
     105 [-]: NEWTABLE R2 0 0
     106 [-]: SETTABLEKS R2 R1 K24 ["InfestedMeterInfo"]
     107 [-]: RETURN R0 0  


; Name:            
; Defined at line: 580
; #Upvalues:       18
; #Parameters:     0
; Is_vararg:       0
; Max Stack Size:  6

       0 [-]: GETUPVAL R0 0
       1 [-]: CALL R0 0 0  
       2 [-]: GETIMPORT R0 1 [nil]
       3 [-]: LOADB R1 1   
       4 [-]: SETTABLEKS R1 R0 K2 ["InfestedMeterInitialized"]
       5 [-]: LOADN R0 1   
       6 [-]: GETIMPORT R1 4 [nil]
       7 [-]: LOADK R2 K5 ["WipeEvent"]
       8 [-]: CALL R1 1 1  
L 0:   9 [-]: GETUPVAL R3 1
      10 [-]: FASTCALL1 62 R3 L1
      11 [-]: GETIMPORT R2 7 [nil]
      12 [-]: CALL R2 1 1  
L 1:  13 [-]: JUMPIF R2 L12
      14 [-]: GETUPVAL R3 2
      15 [-]: FASTCALL1 62 R3 L2
      16 [-]: GETIMPORT R2 7 [nil]
      17 [-]: CALL R2 1 1  
L 2:  18 [-]: JUMPIF R2 L10
      19 [-]: GETUPVAL R2 2
      20 [-]: NAMECALL R2 R2 K8 [0x2047CFE7]
      21 [-]: CALL R2 1 1  
      22 [-]: JUMPIFNOT R2 L3
      23 [-]: LOADN R2 0   
      24 [-]: SETUPVAL R2 3
      25 [-]: LOADN R2 0   
      26 [-]: SETUPVAL R2 4
      27 [-]: LOADN R2 100 
      28 [-]: SETUPVAL R2 5
      29 [-]: JUMP L11
    
L 3:  30 [-]: GETUPVAL R2 6
      31 [-]: JUMPXEQKN R2 K9 L4 NOT [1]
      32 [-]: GETUPVAL R2 7
      33 [-]: GETUPVAL R3 8
      34 [-]: CALL R2 1 0  
L 4:  35 [-]: GETUPVAL R2 9
      36 [-]: CALL R2 0 0  
      37 [-]: GETUPVAL R2 5
      38 [-]: JUMPXEQKN R2 K10 L11 NOT [0]
      39 [-]: GETUPVAL R2 10
      40 [-]: CALL R2 0 1  
      41 [-]: JUMPIF R2 L11
      42 [-]: GETUPVAL R2 11
      43 [-]: LOADK R3 K11 [1.5]
      44 [-]: JUMPIFNOTLE R3 R2 L11
      45 [-]: GETUPVAL R3 2
      46 [-]: FASTCALL1 62 R3 L5
      47 [-]: GETIMPORT R2 7 [nil]
      48 [-]: CALL R2 1 1  
L 5:  49 [-]: JUMPIF R2 L9 
      50 [-]: LOADN R2 0   
      51 [-]: JUMPIFNOTLE R0 R2 L9
      52 [-]: GETUPVAL R2 2
      53 [-]: NAMECALL R2 R2 K12 [0x73901ACF]
      54 [-]: CALL R2 1 1  
      55 [-]: JUMPIF R2 L9 
      56 [-]: GETUPVAL R2 1
      57 [-]: MOVE R4 R1   
      58 [-]: LOADN R5 0   
      59 [-]: NAMECALL R2 R2 K13 [0x0EB34C69]
      60 [-]: CALL R2 3 1  
      61 [-]: JUMPXEQKN R2 K9 L6 NOT [1]
      62 [-]: GETUPVAL R2 2
      63 [-]: GETUPVAL R4 12
      64 [-]: NAMECALL R2 R2 K14 [0x479483BB]
      65 [-]: CALL R2 2 0  
      66 [-]: LOADN R0 1   
      67 [-]: JUMP L11
    
L 6:  68 [-]: GETUPVAL R2 13
      69 [-]: LOADN R3 21  
      70 [-]: JUMPIFNOTEQ R2 R3 L7
      71 [-]: GETUPVAL R2 2
      72 [-]: GETIMPORT R3 16 [nil]
      73 [-]: NAMECALL R3 R3 K17 [0xFB64E76C]
      74 [-]: CALL R3 1 1  
      75 [-]: NAMECALL R3 R3 K18 [0xA534C3AC]
      76 [-]: CALL R3 1 1  
      77 [-]: JUMPIFNOTEQ R2 R3 L8
      78 [-]: GETUPVAL R2 2
      79 [-]: GETUPVAL R4 14
      80 [-]: NAMECALL R2 R2 K14 [0x479483BB]
      81 [-]: CALL R2 2 0  
      82 [-]: JUMP L8
     
L 7:  83 [-]: GETUPVAL R2 2
      84 [-]: GETUPVAL R4 15
      85 [-]: NAMECALL R2 R2 K14 [0x479483BB]
      86 [-]: CALL R2 2 0  
L 8:  87 [-]: LOADN R0 1   
      88 [-]: JUMP L11
    
L 9:  89 [-]: GETUPVAL R2 2
      90 [-]: NAMECALL R2 R2 K12 [0x73901ACF]
      91 [-]: CALL R2 1 1  
      92 [-]: JUMPIF R2 L11
      93 [-]: GETIMPORT R2 20 [nil]
      94 [-]: CALL R2 0 1  
      95 [-]: SUB R0 R0 R2 
      96 [-]: JUMP L11
    
L10:  97 [-]: GETIMPORT R2 16 [nil]
      98 [-]: NAMECALL R2 R2 K21 [0x78298275]
      99 [-]: CALL R2 1 1  
     100 [-]: SETUPVAL R2 2
L11: 101 [-]: GETUPVAL R2 16
     102 [-]: CALL R2 0 0  
     103 [-]: GETUPVAL R2 17
     104 [-]: CALL R2 0 0  
     105 [-]: GETIMPORT R2 23 [nil]
     106 [-]: LOADN R3 0   
     107 [-]: CALL R2 1 0  
     108 [-]: JUMPBACK L0  
L12: 109 [-]: RETURN R0 0  



