; Name:            
; Defined at line: 1
; #Upvalues:       0
; #Parameters:     0
; Is_vararg:       1
; Max Stack Size:  18

            1 [-]: GETIMPORT R0 1 [nil]
       2 [-]: LOADK R1 K2 ["/Lotus/Interface/EndOfMatch.swf"]
       3 [-]: CALL R0 1 1  
       4 [-]: GETIMPORT R1 4 [nil]
       5 [-]: NAMECALL R1 R1 K5 [0x29EF273D]
       6 [-]: CALL R1 1 1  
       7 [-]: GETIMPORT R2 7 [nil]
       8 [-]: GETIMPORT R3 9 [nil]
       9 [-]: LOADK R4 K10 ["DoPerch"]
      10 [-]: CALL R3 1 1  
      11 [-]: GETIMPORT R4 9 [nil]
      12 [-]: LOADK R5 K11 ["ExitPerch"]
      13 [-]: CALL R4 1 1  
      14 [-]: GETIMPORT R5 9 [nil]
      15 [-]: LOADK R6 K12 ["RechargeTimer"]
      16 [-]: CALL R5 1 1  
      17 [-]: GETIMPORT R6 9 [nil]
      18 [-]: LOADK R7 K13 ["RechargeLimit"]
      19 [-]: CALL R6 1 1  
      20 [-]: GETIMPORT R7 9 [nil]
      21 [-]: LOADK R8 K14 ["SpaceGolemStage"]
      22 [-]: CALL R7 1 1  
      23 [-]: DUPCLOSURE R8 K15 []
      24 [-]: SETGLOBAL R8 K16 ["ToggleGolemImmunity"]
      25 [-]: DUPCLOSURE R8 K17 []
      26 [-]: DUPCLOSURE R9 K18 []
      27 [-]: DUPCLOSURE R10 K19 []
      28 [-]: MOVE R0 R2   
      29 [-]: MOVE R0 R5   
      30 [-]: MOVE R0 R6   
      31 [-]: SETGLOBAL R10 K20 ["EnginesHUD"]
      32 [-]: DUPCLOSURE R10 K21 []
      33 [-]: DUPCLOSURE R11 K22 []
      34 [-]: DUPCLOSURE R12 K23 []
      35 [-]: MOVE R0 R11  
      36 [-]: MOVE R0 R10  
      37 [-]: SETGLOBAL R12 K24 ["TeleportAndFade"]
      38 [-]: DUPCLOSURE R12 K25 []
      39 [-]: SETGLOBAL R12 K26 ["ExitGauntlet"]
      40 [-]: DUPCLOSURE R12 K27 []
      41 [-]: DUPCLOSURE R13 K28 []
      42 [-]: DUPCLOSURE R14 K29 []
      43 [-]: MOVE R0 R12  
      44 [-]: SETGLOBAL R14 K30 ["InsideTimer"]
      45 [-]: DUPCLOSURE R14 K31 []
      46 [-]: SETGLOBAL R14 K32 ["EnterGolem"]
      47 [-]: DUPCLOSURE R14 K33 []
      48 [-]: MOVE R0 R2   
      49 [-]: MOVE R0 R7   
      50 [-]: SETGLOBAL R14 K34 ["WeakpointDestroyed"]
      51 [-]: DUPCLOSURE R14 K35 []
      52 [-]: DUPCLOSURE R15 K36 []
      53 [-]: MOVE R0 R2   
      54 [-]: MOVE R0 R5   
      55 [-]: MOVE R0 R6   
      56 [-]: MOVE R0 R1   
      57 [-]: MOVE R0 R7   
      58 [-]: MOVE R0 R3   
      59 [-]: MOVE R0 R9   
      60 [-]: MOVE R0 R13  
      61 [-]: MOVE R0 R4   
      62 [-]: MOVE R0 R0   
      63 [-]: SETGLOBAL R15 K37 ["SpaceMonitor"]
      64 [-]: DUPCLOSURE R15 K38 []
      65 [-]: SETGLOBAL R15 K39 ["FadeAtStart"]
      66 [-]: DUPCLOSURE R15 K40 []
      67 [-]: SETGLOBAL R15 K41 ["Destroy"]
      68 [-]: DUPCLOSURE R15 K42 []
      69 [-]: MOVE R0 R2   
      70 [-]: MOVE R0 R6   
      71 [-]: MOVE R0 R5   
      72 [-]: SETGLOBAL R15 K43 ["PerchLights"]
      73 [-]: DUPCLOSURE R15 K44 []
      74 [-]: SETGLOBAL R15 K45 ["SetThreat"]
      75 [-]: DUPCLOSURE R15 K46 []
      76 [-]: SETGLOBAL R15 K47 ["ModifyThreat"]
      77 [-]: DUPCLOSURE R15 K48 []
      78 [-]: MOVE R0 R2   
      79 [-]: SETGLOBAL R15 K49 ["GolemCombatTaunts"]
      80 [-]: DUPCLOSURE R15 K50 []
      81 [-]: SETGLOBAL R15 K51 ["PlayTauntsOnAvatar"]
      82 [-]: DUPCLOSURE R15 K52 []
      83 [-]: SETGLOBAL R15 K53 ["GolemInteriorTaunts"]
      84 [-]: DUPCLOSURE R15 K54 []
      85 [-]: SETGLOBAL R15 K55 ["SpaceDebrisTaunts"]
      86 [-]: DUPCLOSURE R15 K56 []
      87 [-]: SETGLOBAL R15 K57 ["MinionFlood"]
      88 [-]: DUPCLOSURE R15 K58 []
      89 [-]: DUPCLOSURE R16 K59 []
      90 [-]: DUPCLOSURE R17 K60 []
      91 [-]: MOVE R0 R15  
      92 [-]: MOVE R0 R16  
      93 [-]: MOVE R0 R3   
      94 [-]: MOVE R0 R4   
      95 [-]: SETGLOBAL R17 K61 ["GolemTest"]
      96 [-]: DUPCLOSURE R17 K62 []
      97 [-]: MOVE R0 R15  
      98 [-]: MOVE R0 R16  
      99 [-]: MOVE R0 R4   
     100 [-]: SETGLOBAL R17 K63 ["PerchTest"]
     101 [-]: DUPCLOSURE R17 K64 []
     102 [-]: SETGLOBAL R17 K65 ["DebugKillWeakpoint"]
     103 [-]: DUPCLOSURE R17 K66 []
     104 [-]: SETGLOBAL R17 K67 ["WeakpointCallout"]
     105 [-]: DUPCLOSURE R17 K68 []
     106 [-]: MOVE R0 R2   
     107 [-]: SETGLOBAL R17 K69 ["ProgressTagManager"]
     108 [-]: DUPCLOSURE R17 K70 []
     109 [-]: SETGLOBAL R17 K71 ["DisableWeakpointHitProxy"]
     110 [-]: DUPCLOSURE R17 K72 []
     111 [-]: SETGLOBAL R17 K73 ["ToggleWeakpointHitProxy"]
     112 [-]: DUPCLOSURE R17 K74 []
     113 [-]: SETGLOBAL R17 K75 ["DisableDevourerHitProxy"]
     114 [-]: DUPCLOSURE R17 K76 []
     115 [-]: SETGLOBAL R17 K77 ["ToggleDevourerHitProxy"]
     116 [-]: DUPCLOSURE R17 K78 []
     117 [-]: SETGLOBAL R17 K79 ["SimpleDisableDevProxy"]
     118 [-]: DUPCLOSURE R17 K80 []
     119 [-]: SETGLOBAL R17 K81 ["OnSpawned"]
     120 [-]: DUPCLOSURE R17 K82 []
     121 [-]: SETGLOBAL R17 K83 ["SetSpawn"]
     122 [-]: RETURN R0 0  


; Name:            
; Defined at line: 90
; #Upvalues:       0
; #Parameters:     0
; Is_vararg:       0
; Max Stack Size:  7

       0 [-]: GETIMPORT R0 1 [nil]
       1 [-]: GETIMPORT R2 3 [nil]
       2 [-]: GETIMPORT R3 5 [nil]
       3 [-]: CALL R3 0 1  
       4 [-]: LOADK R4 K6 [3.4028234663852886e+38]
       5 [-]: NAMECALL R0 R0 K7 [0x4E5939A5]
       6 [-]: CALL R0 4 1  
       7 [-]: FASTCALL1 62 R0 L0
       8 [-]: MOVE R2 R0   
       9 [-]: GETIMPORT R1 9 [nil]
      10 [-]: CALL R1 1 1  
L 0:  11 [-]: JUMPIF R1 L2 
      12 [-]: GETIMPORT R1 11 [nil]
      13 [-]: JUMPIFNOT R1 L1
      14 [-]: NAMECALL R1 R0 K12 [0x1AC1655C]
      15 [-]: CALL R1 1 1  
      16 [-]: GETIMPORT R3 14 [nil]
      17 [-]: LOADK R4 K15 ["GolemImmune"]
      18 [-]: CALL R3 1 1  
      19 [-]: LOADN R4 25  
      20 [-]: LOADN R5 6   
      21 [-]: LOADN R6 0   
      22 [-]: NAMECALL R1 R1 K16 [0xA383DE31]
      23 [-]: CALL R1 5 0  
      24 [-]: RETURN R0 0  
L 1:  25 [-]: NAMECALL R1 R0 K12 [0x1AC1655C]
      26 [-]: CALL R1 1 1  
      27 [-]: GETIMPORT R3 14 [nil]
      28 [-]: LOADK R4 K15 ["GolemImmune"]
      29 [-]: CALL R3 1 -1 
      30 [-]: NAMECALL R1 R1 K17 [0x8E3E343E]
      31 [-]: CALL R1 -1 0 
L 2:  32 [-]: RETURN R0 0  


; Name:            
; Defined at line: 101
; #Upvalues:       0
; #Parameters:     1
; Is_vararg:       0
; Max Stack Size:  4

       0 [-]: GETIMPORT R2 1 [nil]
       1 [-]: GETTABLE R1 R2 R0
       2 [-]: GETIMPORT R3 3 [nil]
       3 [-]: NAMECALL R1 R1 K4 [0xC9F6A7D7]
       4 [-]: CALL R1 2 1  
       5 [-]: FASTCALL1 62 R1 L0
       6 [-]: MOVE R3 R1   
       7 [-]: GETIMPORT R2 6 [nil]
       8 [-]: CALL R2 1 1  
L 0:   9 [-]: JUMPIF R2 L1 
      10 [-]: NAMECALL R2 R1 K7 [0xA2880940]
      11 [-]: CALL R2 1 0  
L 1:  12 [-]: RETURN R0 0  


; Name:            
; Defined at line: 108
; #Upvalues:       0
; #Parameters:     2
; Is_vararg:       0
; Max Stack Size:  9

       0 [-]: LOADNIL R2   
       1 [-]: GETIMPORT R3 1 [nil]
       2 [-]: GETIMPORT R5 3 [nil]
       3 [-]: LOADK R6 K4 ["GolemPerch"]
       4 [-]: CALL R5 1 1  
       5 [-]: NAMECALL R6 R0 K5 [0xD1586535]
       6 [-]: CALL R6 1 -1 
       7 [-]: NAMECALL R3 R3 K6 [0xC7B81E8D]
       8 [-]: CALL R3 -1 1 
       9 [-]: LOADN R6 1   
      10 [-]: GETIMPORT R7 8 [nil]
      11 [-]: LENGTH R4 R7 
      12 [-]: LOADN R5 1   
      13 [-]: FORNPREP R4 L2
L 0:  14 [-]: GETIMPORT R8 8 [nil]
      15 [-]: GETTABLE R7 R8 R6
      16 [-]: JUMPIFNOTEQ R3 R7 L1
      17 [-]: GETIMPORT R7 10 [nil]
      18 [-]: GETTABLE R2 R7 R6
L 1:  19 [-]: FORNLOOP R4 L0
L 2:  20 [-]: FASTCALL1 62 R2 L3
      21 [-]: MOVE R5 R2   
      22 [-]: GETIMPORT R4 12 [nil]
      23 [-]: CALL R4 1 1  
L 3:  24 [-]: JUMPIF R4 L5 
      25 [-]: JUMPIFNOT R1 L4
      26 [-]: NAMECALL R4 R2 K13 [0x383D2E7D]
      27 [-]: CALL R4 1 0  
      28 [-]: RETURN R0 0  
L 4:  29 [-]: NAMECALL R4 R2 K14 [0xF4E253B6]
      30 [-]: CALL R4 1 0  
L 5:  31 [-]: RETURN R0 0  


; Name:            
; Defined at line: 127
; #Upvalues:       3
; #Parameters:     0
; Is_vararg:       0
; Max Stack Size:  13

       0 [-]: GETIMPORT R0 1 [nil]
       1 [-]: GETIMPORT R2 3 [nil]
       2 [-]: GETIMPORT R3 5 [nil]
       3 [-]: CALL R3 0 1  
       4 [-]: LOADK R4 K6 [3.4028234663852886e+38]
       5 [-]: NAMECALL R0 R0 K7 [0x4E5939A5]
       6 [-]: CALL R0 4 1  
L 0:   7 [-]: FASTCALL1 62 R0 L1
       8 [-]: MOVE R2 R0   
       9 [-]: GETIMPORT R1 9 [nil]
      10 [-]: CALL R1 1 1  
L 1:  11 [-]: JUMPIFNOT R1 L2
      12 [-]: GETIMPORT R1 1 [nil]
      13 [-]: GETIMPORT R3 3 [nil]
      14 [-]: GETIMPORT R4 5 [nil]
      15 [-]: CALL R4 0 1  
      16 [-]: LOADK R5 K6 [3.4028234663852886e+38]
      17 [-]: NAMECALL R1 R1 K7 [0x4E5939A5]
      18 [-]: CALL R1 4 1  
      19 [-]: MOVE R0 R1   
      20 [-]: GETIMPORT R1 11 [nil]
      21 [-]: LOADN R2 0   
      22 [-]: CALL R1 1 0  
      23 [-]: JUMPBACK L0  
L 2:  24 [-]: GETIMPORT R1 11 [nil]
      25 [-]: LOADN R2 2   
      26 [-]: CALL R1 1 0  
      27 [-]: LOADNIL R1   
      28 [-]: LOADNIL R2   
      29 [-]: LOADNIL R3   
      30 [-]: LOADNIL R4   
L 3:  31 [-]: GETUPVAL R6 0
      32 [-]: FASTCALL1 62 R6 L4
      33 [-]: GETIMPORT R5 9 [nil]
      34 [-]: CALL R5 1 1  
L 4:  35 [-]: JUMPIF R5 L12
      36 [-]: FASTCALL1 62 R0 L5
      37 [-]: MOVE R6 R0   
      38 [-]: GETIMPORT R5 9 [nil]
      39 [-]: CALL R5 1 1  
L 5:  40 [-]: JUMPIF R5 L12
      41 [-]: NAMECALL R5 R0 K12 [0x5E8B6A40]
      42 [-]: CALL R5 1 1  
      43 [-]: JUMPIF R5 L9 
      44 [-]: GETUPVAL R5 0
      45 [-]: GETIMPORT R7 14 [nil]
      46 [-]: LOADK R8 K15 ["WipeEvent"]
      47 [-]: CALL R7 1 -1 
      48 [-]: NAMECALL R5 R5 K16 [0x0EB34C69]
      49 [-]: CALL R5 -1 1 
      50 [-]: JUMPXEQKN R5 K17 L8 NOT [1]
      51 [-]: LOADN R4 15  
L 6:  52 [-]: LOADN R5 0   
      53 [-]: JUMPIFNOTLT R5 R4 L7
      54 [-]: GETIMPORT R7 19 [nil]
      55 [-]: LOADK R8 K20 ["/Lotus/Language/Game/RaidEnginesPurge"]
      56 [-]: DUPTABLE R9 22
      57 [-]: SETTABLEKS R4 R9 K21 ["PERCENT"]
      58 [-]: CALL R7 2 1  
      59 [-]: MOVE R5 R7   
      60 [-]: LOADK R6 K23 [" "]
      61 [-]: CONCAT R1 R5 R6
      62 [-]: GETIMPORT R5 26 [nil]
      63 [-]: MOVE R6 R1   
      64 [-]: LOADN R7 -1  
      65 [-]: LOADB R8 1   
      66 [-]: LOADNIL R9   
      67 [-]: LOADB R10 0  
      68 [-]: CALL R5 5 0  
      69 [-]: SUBK R4 R4 K17 [1]
      70 [-]: GETIMPORT R5 11 [nil]
      71 [-]: LOADN R6 1   
      72 [-]: CALL R5 1 0  
      73 [-]: JUMPBACK L6  
L 7:  74 [-]: GETUPVAL R5 0
      75 [-]: GETIMPORT R7 14 [nil]
      76 [-]: LOADK R8 K15 ["WipeEvent"]
      77 [-]: CALL R7 1 -1 
      78 [-]: NAMECALL R5 R5 K16 [0x0EB34C69]
      79 [-]: CALL R5 -1 1 
      80 [-]: JUMPXEQKN R5 K17 L8 NOT [1]
      81 [-]: GETIMPORT R5 11 [nil]
      82 [-]: LOADN R6 0   
      83 [-]: CALL R5 1 0  
      84 [-]: JUMPBACK L7  
L 8:  85 [-]: GETIMPORT R5 26 [nil]
      86 [-]: LOADK R6 K27 ["/Lotus/Language/Game/RaidEnginesEngaged"]
      87 [-]: LOADN R7 -1  
      88 [-]: LOADB R8 1   
      89 [-]: LOADNIL R9   
      90 [-]: LOADB R10 0  
      91 [-]: CALL R5 5 0  
      92 [-]: JUMP L11
    
L 9:  93 [-]: MOVE R3 R2   
      94 [-]: GETUPVAL R8 0
      95 [-]: GETUPVAL R10 1
      96 [-]: LOADN R11 0  
      97 [-]: NAMECALL R8 R8 K16 [0x0EB34C69]
      98 [-]: CALL R8 3 1  
      99 [-]: GETUPVAL R9 0
     100 [-]: GETUPVAL R11 2
     101 [-]: LOADN R12 180
     102 [-]: NAMECALL R9 R9 K16 [0x0EB34C69]
     103 [-]: CALL R9 3 1  
     104 [-]: DIV R7 R8 R9 
     105 [-]: MULK R6 R7 K28 [100]
     106 [-]: FASTCALL1 12 R6 L10
     107 [-]: GETIMPORT R5 31 [nil]
     108 [-]: CALL R5 1 1  
L10: 109 [-]: MOVE R2 R5   
     110 [-]: GETIMPORT R7 19 [nil]
     111 [-]: LOADK R8 K32 ["/Lotus/Language/Game/RaidEnginesProgress"]
     112 [-]: DUPTABLE R9 22
     113 [-]: SETTABLEKS R2 R9 K21 ["PERCENT"]
     114 [-]: CALL R7 2 1  
     115 [-]: MOVE R5 R7   
     116 [-]: LOADK R6 K23 [" "]
     117 [-]: CONCAT R1 R5 R6
     118 [-]: GETIMPORT R5 26 [nil]
     119 [-]: MOVE R6 R1   
     120 [-]: LOADN R7 -1  
     121 [-]: LOADB R8 1   
     122 [-]: LOADNIL R9   
     123 [-]: LOADB R10 0  
     124 [-]: CALL R5 5 0  
L11: 125 [-]: GETIMPORT R5 11 [nil]
     126 [-]: LOADN R6 0   
     127 [-]: CALL R5 1 0  
     128 [-]: JUMPBACK L3  
L12: 129 [-]: GETIMPORT R5 34 [nil]
     130 [-]: CALL R5 0 0  
     131 [-]: RETURN R0 0  


; Name:            
; Defined at line: 166
; #Upvalues:       0
; #Parameters:     2
; Is_vararg:       0
; Max Stack Size:  14

       0 [-]: GETIMPORT R2 1 [nil]
       1 [-]: LOADK R3 K2 ["         Start Teleport"]
       2 [-]: CALL R2 1 0  
       3 [-]: LOADNIL R2   
       4 [-]: GETIMPORT R3 4 [nil]
       5 [-]: CALL R3 0 1  
       6 [-]: FASTCALL1 62 R0 L0
       7 [-]: MOVE R6 R0   
       8 [-]: GETIMPORT R5 6 [nil]
       9 [-]: CALL R5 1 1  
L 0:  10 [-]: NOT R4 R5    
      11 [-]: JUMPIFNOT R4 L1
      12 [-]: GETIMPORT R6 8 [nil]
      13 [-]: NAMECALL R4 R0 K9 [0xF2DEAF69]
      14 [-]: CALL R4 2 1  
L 1:  15 [-]: FASTCALL1 62 R0 L2
      16 [-]: MOVE R7 R0   
      17 [-]: GETIMPORT R6 6 [nil]
      18 [-]: CALL R6 1 1  
L 2:  19 [-]: NOT R5 R6    
      20 [-]: JUMPIFNOT R5 L3
      21 [-]: GETIMPORT R7 11 [nil]
      22 [-]: LOADK R8 K12 ["/EE/Types/Game/PickUp"]
      23 [-]: CALL R7 1 -1 
      24 [-]: NAMECALL R5 R0 K9 [0xF2DEAF69]
      25 [-]: CALL R5 -1 1 
L 3:  26 [-]: GETIMPORT R6 14 [nil]
      27 [-]: JUMPIF R6 L5 
      28 [-]: JUMPIFNOT R4 L5
      29 [-]: NAMECALL R7 R0 K15 [0x5E651723]
      30 [-]: CALL R7 1 1  
      31 [-]: FASTCALL1 62 R7 L4
      32 [-]: GETIMPORT R6 6 [nil]
      33 [-]: CALL R6 1 1  
L 4:  34 [-]: JUMPIF R6 L5 
      35 [-]: NAMECALL R6 R0 K16 [0xA22E9F03]
      36 [-]: CALL R6 1 1  
      37 [-]: MOVE R2 R6   
      38 [-]: GETIMPORT R6 4 [nil]
      39 [-]: CALL R6 0 1  
      40 [-]: MOVE R3 R6   
      41 [-]: JUMP L9
     
L 5:  42 [-]: JUMPIFNOT R5 L6
      43 [-]: NAMECALL R6 R0 K17 [0x859EA8E2]
      44 [-]: CALL R6 1 1  
      45 [-]: JUMPIFNOT R6 L6
      46 [-]: NAMECALL R6 R0 K18 [0x5F4FB08A]
      47 [-]: CALL R6 1 1  
      48 [-]: GETIMPORT R7 20 [nil]
      49 [-]: LOADN R8 0   
      50 [-]: LOADN R9 1   
      51 [-]: LOADN R10 0  
      52 [-]: CALL R7 3 1  
      53 [-]: ADD R2 R6 R7 
      54 [-]: JUMP L9
     
L 6:  55 [-]: FASTCALL1 62 R1 L7
      56 [-]: MOVE R7 R1   
      57 [-]: GETIMPORT R6 6 [nil]
      58 [-]: CALL R6 1 1  
L 7:  59 [-]: JUMPIF R6 L9 
      60 [-]: NAMECALL R6 R1 K21 [0xD1586535]
      61 [-]: CALL R6 1 1  
      62 [-]: MOVE R2 R6   
      63 [-]: GETTABLEKS R7 R2 K22 ["x"]
      64 [-]: GETIMPORT R8 24 [nil]
      65 [-]: LOADN R9 -10 
      66 [-]: LOADN R10 10 
      67 [-]: CALL R8 2 1  
      68 [-]: ADD R6 R7 R8 
      69 [-]: SETTABLEKS R6 R2 K22 ["x"]
      70 [-]: GETTABLEKS R7 R2 K25 ["z"]
      71 [-]: GETIMPORT R8 24 [nil]
      72 [-]: LOADN R9 -10 
      73 [-]: LOADN R10 10 
      74 [-]: CALL R8 2 1  
      75 [-]: ADD R6 R7 R8 
      76 [-]: SETTABLEKS R6 R2 K25 ["z"]
      77 [-]: NAMECALL R6 R1 K26 [0xCB3851B8]
      78 [-]: CALL R6 1 1  
      79 [-]: MOVE R3 R6   
      80 [-]: JUMPIF R4 L8 
      81 [-]: JUMPIFNOT R5 L9
L 8:  82 [-]: GETIMPORT R6 1 [nil]
      83 [-]: LOADK R8 K27 ["Script Teleport and Fade: "]
      84 [-]: NAMECALL R12 R0 K28 [0xED4E0128]
      85 [-]: CALL R12 1 1 
      86 [-]: MOVE R9 R12  
      87 [-]: LOADK R10 K29 [" to: "]
      88 [-]: NAMECALL R11 R1 K28 [0xED4E0128]
      89 [-]: CALL R11 1 1 
      90 [-]: CONCAT R7 R8 R11
      91 [-]: CALL R6 1 0  
L 9:  92 [-]: JUMPXEQKNIL R2 L22
      93 [-]: MOVE R8 R2   
      94 [-]: MOVE R9 R3   
      95 [-]: NAMECALL R6 R0 K30 [0x589EF1C1]
      96 [-]: CALL R6 3 0  
      97 [-]: JUMPIFNOT R4 L13
      98 [-]: NAMECALL R7 R0 K15 [0x5E651723]
      99 [-]: CALL R7 1 1  
     100 [-]: FASTCALL1 62 R7 L10
     101 [-]: GETIMPORT R6 6 [nil]
     102 [-]: CALL R6 1 1  
L10: 103 [-]: JUMPIF R6 L13
     104 [-]: GETIMPORT R6 32 [nil]
     105 [-]: JUMPIFNOT R6 L11
     106 [-]: GETIMPORT R8 34 [nil]
     107 [-]: LOADB R9 0   
     108 [-]: LOADN R10 2  
     109 [-]: LOADN R11 1  
     110 [-]: LOADB R12 1  
     111 [-]: NAMECALL R6 R0 K35 [0x5D985C7E]
     112 [-]: CALL R6 6 0  
L11: 113 [-]: NAMECALL R6 R0 K36 [0xDE321E6F]
     114 [-]: CALL R6 1 1  
     115 [-]: NAMECALL R6 R6 K37 [0x7F6EBE4E]
     116 [-]: CALL R6 1 0  
     117 [-]: NAMECALL R6 R0 K36 [0xDE321E6F]
     118 [-]: CALL R6 1 1  
     119 [-]: LOADN R8 5   
     120 [-]: NAMECALL R6 R6 K38 [0xE85A2361]
     121 [-]: CALL R6 2 1  
     122 [-]: FASTCALL1 62 R6 L12
     123 [-]: MOVE R8 R6   
     124 [-]: GETIMPORT R7 6 [nil]
     125 [-]: CALL R7 1 1  
L12: 126 [-]: JUMPIF R7 L13
     127 [-]: NAMECALL R7 R6 K39 [0x41BF4B5D]
     128 [-]: CALL R7 1 1  
     129 [-]: LOADN R8 0   
     130 [-]: JUMPIFEQ R7 R8 L13
     131 [-]: NAMECALL R7 R0 K36 [0xDE321E6F]
     132 [-]: CALL R7 1 1  
     133 [-]: LOADB R9 1   
     134 [-]: LOADB R10 1  
     135 [-]: NAMECALL R7 R7 K40 [0xC5E0C516]
     136 [-]: CALL R7 3 0  
L13: 137 [-]: GETIMPORT R8 20 [nil]
     138 [-]: CALL R8 0 -1 
     139 [-]: NAMECALL R6 R0 K41 [0xC5B6A2D5]
     140 [-]: CALL R6 -1 0 
     141 [-]: GETIMPORT R7 43 [nil]
     142 [-]: FASTCALL1 62 R7 L14
     143 [-]: GETIMPORT R6 6 [nil]
     144 [-]: CALL R6 1 1  
L14: 145 [-]: JUMPIF R6 L15
     146 [-]: GETIMPORT R6 45 [nil]
     147 [-]: GETIMPORT R8 43 [nil]
     148 [-]: MOVE R9 R2   
     149 [-]: MOVE R10 R3  
     150 [-]: NAMECALL R6 R6 K46 [0x05909209]
     151 [-]: CALL R6 4 0  
L15: 152 [-]: GETIMPORT R7 48 [nil]
     153 [-]: FASTCALL1 62 R7 L16
     154 [-]: GETIMPORT R6 6 [nil]
     155 [-]: CALL R6 1 1  
L16: 156 [-]: JUMPIF R6 L17
     157 [-]: GETIMPORT R8 48 [nil]
     158 [-]: GETIMPORT R9 50 [nil]
     159 [-]: NAMECALL R6 R0 K51 [0x47901F07]
     160 [-]: CALL R6 3 0  
L17: 161 [-]: JUMPIFNOT R4 L21
     162 [-]: GETIMPORT R6 53 [nil]
     163 [-]: JUMPIFNOT R6 L18
     164 [-]: MOVE R8 R3   
     165 [-]: NAMECALL R6 R0 K54 [0xB41A4158]
     166 [-]: CALL R6 2 0  
     167 [-]: NAMECALL R6 R0 K55 [0x020D4331]
     168 [-]: CALL R6 1 1  
     169 [-]: MOVE R8 R3   
     170 [-]: NAMECALL R6 R6 K56 [0x553549E8]
     171 [-]: CALL R6 2 0  
L18: 172 [-]: NAMECALL R6 R0 K57 [0xB1FBB0A7]
     173 [-]: CALL R6 1 0  
     174 [-]: NAMECALL R6 R0 K58 [0x283A8730]
     175 [-]: CALL R6 1 0  
     176 [-]: NAMECALL R7 R0 K15 [0x5E651723]
     177 [-]: CALL R7 1 1  
     178 [-]: FASTCALL1 62 R7 L19
     179 [-]: GETIMPORT R6 6 [nil]
     180 [-]: CALL R6 1 1  
L19: 181 [-]: JUMPIF R6 L21
     182 [-]: NAMECALL R6 R0 K36 [0xDE321E6F]
     183 [-]: CALL R6 1 1  
     184 [-]: NAMECALL R6 R6 K37 [0x7F6EBE4E]
     185 [-]: CALL R6 1 0  
     186 [-]: NAMECALL R6 R0 K36 [0xDE321E6F]
     187 [-]: CALL R6 1 1  
     188 [-]: LOADN R8 5   
     189 [-]: NAMECALL R6 R6 K38 [0xE85A2361]
     190 [-]: CALL R6 2 1  
     191 [-]: FASTCALL1 62 R6 L20
     192 [-]: MOVE R8 R6   
     193 [-]: GETIMPORT R7 6 [nil]
     194 [-]: CALL R7 1 1  
L20: 195 [-]: JUMPIF R7 L21
     196 [-]: NAMECALL R7 R6 K39 [0x41BF4B5D]
     197 [-]: CALL R7 1 1  
     198 [-]: LOADN R8 0   
     199 [-]: JUMPIFEQ R7 R8 L21
     200 [-]: NAMECALL R7 R0 K36 [0xDE321E6F]
     201 [-]: CALL R7 1 1  
     202 [-]: LOADB R9 1   
     203 [-]: LOADB R10 1  
     204 [-]: NAMECALL R7 R7 K40 [0xC5E0C516]
     205 [-]: CALL R7 3 0  
L21: 206 [-]: GETIMPORT R6 60 [nil]
     207 [-]: LOADK R7 K61 [0.10000000000000001]
     208 [-]: CALL R6 1 0  
     209 [-]: MOVE R8 R2   
     210 [-]: MOVE R9 R3   
     211 [-]: NAMECALL R6 R0 K30 [0x589EF1C1]
     212 [-]: CALL R6 3 0  
     213 [-]: GETIMPORT R8 20 [nil]
     214 [-]: CALL R8 0 -1 
     215 [-]: NAMECALL R6 R0 K41 [0xC5B6A2D5]
     216 [-]: CALL R6 -1 0 
     217 [-]: GETIMPORT R6 60 [nil]
     218 [-]: LOADK R7 K61 [0.10000000000000001]
     219 [-]: CALL R6 1 0  
     220 [-]: MOVE R8 R2   
     221 [-]: MOVE R9 R3   
     222 [-]: NAMECALL R6 R0 K30 [0x589EF1C1]
     223 [-]: CALL R6 3 0  
     224 [-]: GETIMPORT R8 20 [nil]
     225 [-]: CALL R8 0 -1 
     226 [-]: NAMECALL R6 R0 K41 [0xC5B6A2D5]
     227 [-]: CALL R6 -1 0 
     228 [-]: JUMP L25
    
L22: 229 [-]: GETIMPORT R6 1 [nil]
     230 [-]: LOADK R8 K62 ["ERROR: SpaceGolem.lua: "]
     231 [-]: NAMECALL R11 R0 K28 [0xED4E0128]
     232 [-]: CALL R11 1 1 
     233 [-]: MOVE R9 R11  
     234 [-]: LOADK R10 K63 [" Was not teleported to a waypoint because the waypoint was null"]
     235 [-]: CONCAT R7 R8 R10
     236 [-]: CALL R6 1 0  
     237 [-]: GETIMPORT R6 45 [nil]
     238 [-]: NAMECALL R6 R6 K64 [0x1CF711C9]
     239 [-]: CALL R6 1 1  
     240 [-]: FASTCALL1 62 R6 L23
     241 [-]: MOVE R8 R6   
     242 [-]: GETIMPORT R7 6 [nil]
     243 [-]: CALL R7 1 1  
L23: 244 [-]: JUMPIF R7 L24
     245 [-]: GETIMPORT R7 1 [nil]
     246 [-]: LOADK R8 K65 ["Defaulting to putting them at the initial spawn point"]
     247 [-]: CALL R7 1 0  
     248 [-]: MOVE R9 R6   
     249 [-]: NAMECALL R10 R0 K26 [0xCB3851B8]
     250 [-]: CALL R10 1 -1
     251 [-]: NAMECALL R7 R0 K30 [0x589EF1C1]
     252 [-]: CALL R7 -1 0 
     253 [-]: JUMP L25
    
L24: 254 [-]: GETIMPORT R7 1 [nil]
     255 [-]: LOADK R9 K66 ["Cannot find initial spawn "]
     256 [-]: NAMECALL R12 R0 K28 [0xED4E0128]
     257 [-]: CALL R12 1 1 
     258 [-]: MOVE R10 R12 
     259 [-]: LOADK R11 K67 [" Is probably going to fall out of the world"]
     260 [-]: CONCAT R8 R9 R11
     261 [-]: CALL R7 1 0  
L25: 262 [-]: JUMPIFNOT R4 L28
     263 [-]: LOADB R8 1   
     264 [-]: NAMECALL R6 R0 K68 [0x2C13654D]
     265 [-]: CALL R6 2 0  
     266 [-]: NAMECALL R6 R0 K36 [0xDE321E6F]
     267 [-]: CALL R6 1 1  
     268 [-]: FASTCALL1 62 R6 L26
     269 [-]: MOVE R8 R6   
     270 [-]: GETIMPORT R7 6 [nil]
     271 [-]: CALL R7 1 1  
L26: 272 [-]: JUMPIF R7 L28
     273 [-]: GETIMPORT R9 70 [nil]
     274 [-]: NAMECALL R7 R6 K9 [0xF2DEAF69]
     275 [-]: CALL R7 2 1  
     276 [-]: JUMPIFNOT R7 L28
     277 [-]: NAMECALL R7 R6 K71 [0xF7D48EE0]
     278 [-]: CALL R7 1 1  
     279 [-]: FASTCALL1 62 R7 L27
     280 [-]: MOVE R9 R7   
     281 [-]: GETIMPORT R8 6 [nil]
     282 [-]: CALL R8 1 1  
L27: 283 [-]: JUMPIF R8 L28
     284 [-]: NAMECALL R8 R7 K72 [0x707CD1F0]
     285 [-]: CALL R8 1 0  
L28: 286 [-]: RETURN R0 0  


; Name:            
; Defined at line: 258
; #Upvalues:       0
; #Parameters:     3
; Is_vararg:       0
; Max Stack Size:  11

       0 [-]: GETIMPORT R3 1 [nil]
       1 [-]: LOADK R4 K2 ["         start fade"]
       2 [-]: CALL R3 1 0  
       3 [-]: GETIMPORT R3 4 [nil]
       4 [-]: LOADK R4 K5 [0.01]
       5 [-]: CALL R3 1 0  
       6 [-]: GETIMPORT R3 7 [nil]
       7 [-]: NAMECALL R3 R3 K8 [0x7C1A0374]
       8 [-]: CALL R3 1 1  
       9 [-]: NAMECALL R4 R3 K9 [0x65C7544C]
      10 [-]: CALL R4 1 1  
      11 [-]: JUMPXEQKN R1 K10 L0 NOT [0]
      12 [-]: MOVE R7 R2   
      13 [-]: NAMECALL R5 R3 K11 [0xB6DF3E50]
      14 [-]: CALL R5 2 0  
      15 [-]: GETIMPORT R5 4 [nil]
      16 [-]: LOADN R6 0   
      17 [-]: CALL R5 1 0  
      18 [-]: RETURN R0 0  
L 0:  19 [-]: LOADN R5 0   
      20 [-]: LOADNIL R6   
L 1:  21 [-]: LOADN R7 1   
      22 [-]: JUMPIFNOTLT R5 R7 L2
      23 [-]: GETIMPORT R7 13 [nil]
      24 [-]: MOVE R8 R4   
      25 [-]: MOVE R9 R2   
      26 [-]: MOVE R10 R5  
      27 [-]: CALL R7 3 1  
      28 [-]: MOVE R6 R7   
      29 [-]: MOVE R9 R6   
      30 [-]: NAMECALL R7 R3 K11 [0xB6DF3E50]
      31 [-]: CALL R7 2 0  
      32 [-]: GETIMPORT R8 15 [nil]
      33 [-]: CALL R8 0 1  
      34 [-]: DIV R7 R8 R1 
      35 [-]: ADD R5 R5 R7 
      36 [-]: GETIMPORT R7 4 [nil]
      37 [-]: LOADN R8 0   
      38 [-]: CALL R7 1 0  
      39 [-]: JUMPBACK L1  
L 2:  40 [-]: MOVE R9 R2   
      41 [-]: NAMECALL R7 R3 K11 [0xB6DF3E50]
      42 [-]: CALL R7 2 0  
      43 [-]: GETIMPORT R7 4 [nil]
      44 [-]: LOADN R8 0   
      45 [-]: CALL R7 1 0  
      46 [-]: RETURN R0 0  


; Name:            
; Defined at line: 286
; #Upvalues:       2
; #Parameters:     1
; Is_vararg:       0
; Max Stack Size:  9

       0 [-]: GETIMPORT R1 1 [nil]
       1 [-]: LOADK R2 K2 ["start teleport and fade"]
       2 [-]: CALL R1 1 0  
       3 [-]: FASTCALL1 62 R0 L0
       4 [-]: MOVE R2 R0   
       5 [-]: GETIMPORT R1 4 [nil]
       6 [-]: CALL R1 1 1  
L 0:   7 [-]: JUMPIFNOT R1 L1
       8 [-]: RETURN R0 0  
L 1:   9 [-]: GETIMPORT R1 6 [nil]
      10 [-]: NAMECALL R1 R1 K7 [0x18D05D30]
      11 [-]: CALL R1 1 1  
      12 [-]: GETIMPORT R2 6 [nil]
      13 [-]: GETIMPORT R4 9 [nil]
      14 [-]: LOADK R5 K10 ["OutsideGolem"]
      15 [-]: CALL R4 1 -1 
      16 [-]: NAMECALL R2 R2 K11 [0x46A0EBF5]
      17 [-]: CALL R2 -1 1 
      18 [-]: GETIMPORT R5 13 [nil]
      19 [-]: NAMECALL R3 R0 K14 [0xF2DEAF69]
      20 [-]: CALL R3 2 1  
      21 [-]: JUMPIFNOT R3 L9
      22 [-]: NAMECALL R4 R0 K15 [0x5E651723]
      23 [-]: CALL R4 1 1  
      24 [-]: FASTCALL1 62 R4 L2
      25 [-]: GETIMPORT R3 4 [nil]
      26 [-]: CALL R3 1 1  
L 2:  27 [-]: JUMPIF R3 L6 
      28 [-]: GETIMPORT R3 1 [nil]
      29 [-]: LOADK R4 K16 ["Teleport Player"]
      30 [-]: CALL R3 1 0  
      31 [-]: NAMECALL R3 R0 K17 [0xA5E492D4]
      32 [-]: CALL R3 1 1  
      33 [-]: JUMPIFNOT R3 L5
      34 [-]: LOADB R6 0   
      35 [-]: NAMECALL R4 R0 K18 [0x2C13654D]
      36 [-]: CALL R4 2 0  
      37 [-]: GETIMPORT R4 6 [nil]
      38 [-]: NAMECALL R4 R4 K19 [0xDD25E9D1]
      39 [-]: CALL R4 1 1  
      40 [-]: JUMPIF R4 L3 
      41 [-]: GETIMPORT R4 21 [nil]
      42 [-]: GETIMPORT R5 23 [nil]
      43 [-]: CALL R4 1 0  
      44 [-]: GETUPVAL R4 0
      45 [-]: MOVE R5 R0   
      46 [-]: GETIMPORT R6 25 [nil]
      47 [-]: GETIMPORT R7 27 [nil]
      48 [-]: CALL R4 3 0  
L 3:  49 [-]: GETUPVAL R4 1
      50 [-]: MOVE R5 R0   
      51 [-]: MOVE R6 R2   
      52 [-]: CALL R4 2 0  
      53 [-]: GETIMPORT R4 21 [nil]
      54 [-]: GETIMPORT R5 29 [nil]
      55 [-]: CALL R4 1 0  
      56 [-]: GETIMPORT R4 31 [nil]
      57 [-]: JUMPIFNOT R4 L4
      58 [-]: NAMECALL R7 R0 K33 [0xB40C191A]
      59 [-]: CALL R7 1 1  
      60 [-]: ADDK R6 R7 K32 [1]
      61 [-]: LOADN R7 20  
      62 [-]: NAMECALL R4 R0 K34 [0x6E9719EB]
      63 [-]: CALL R4 3 0  
L 4:  64 [-]: GETIMPORT R4 6 [nil]
      65 [-]: NAMECALL R4 R4 K19 [0xDD25E9D1]
      66 [-]: CALL R4 1 1  
      67 [-]: JUMPIF R4 L12
      68 [-]: GETUPVAL R4 0
      69 [-]: MOVE R5 R0   
      70 [-]: GETIMPORT R6 36 [nil]
      71 [-]: GETIMPORT R7 38 [nil]
      72 [-]: CALL R4 3 0  
      73 [-]: RETURN R0 0  
L 5:  74 [-]: JUMPIFNOT R1 L12
      75 [-]: GETIMPORT R4 40 [nil]
      76 [-]: JUMPIFNOT R4 L12
      77 [-]: GETIMPORT R4 21 [nil]
      78 [-]: GETIMPORT R6 23 [nil]
      79 [-]: GETIMPORT R7 25 [nil]
      80 [-]: ADD R5 R6 R7 
      81 [-]: CALL R4 1 0  
      82 [-]: GETUPVAL R4 1
      83 [-]: MOVE R5 R0   
      84 [-]: MOVE R6 R2   
      85 [-]: CALL R4 2 0  
      86 [-]: GETIMPORT R4 31 [nil]
      87 [-]: JUMPIFNOT R4 L12
      88 [-]: NAMECALL R7 R0 K33 [0xB40C191A]
      89 [-]: CALL R7 1 1  
      90 [-]: ADDK R6 R7 K32 [1]
      91 [-]: LOADN R7 20  
      92 [-]: NAMECALL R4 R0 K34 [0x6E9719EB]
      93 [-]: CALL R4 3 0  
      94 [-]: RETURN R0 0  
L 6:  95 [-]: NAMECALL R4 R0 K41 [0xFA9E477F]
      96 [-]: CALL R4 1 1  
      97 [-]: FASTCALL1 62 R4 L7
      98 [-]: GETIMPORT R3 4 [nil]
      99 [-]: CALL R3 1 1  
L 7: 100 [-]: JUMPIF R3 L12
     101 [-]: JUMPIFNOT R1 L8
     102 [-]: GETUPVAL R3 1
     103 [-]: MOVE R4 R0   
     104 [-]: CALL R3 1 0  
L 8: 105 [-]: RETURN R0 0  
     106 [-]: RETURN R0 0  
L 9: 107 [-]: GETIMPORT R5 43 [nil]
     108 [-]: LOADK R6 K44 ["/EE/Types/Game/PickUp"]
     109 [-]: CALL R5 1 -1 
     110 [-]: NAMECALL R3 R0 K14 [0xF2DEAF69]
     111 [-]: CALL R3 -1 1 
     112 [-]: JUMPIFNOT R3 L12
     113 [-]: NAMECALL R4 R0 K45 [0x2B54251B]
     114 [-]: CALL R4 1 1  
     115 [-]: FASTCALL1 62 R4 L10
     116 [-]: GETIMPORT R3 4 [nil]
     117 [-]: CALL R3 1 1  
L10: 118 [-]: JUMPIF R3 L11
     119 [-]: NAMECALL R3 R0 K46 [0x467C327C]
     120 [-]: CALL R3 1 0  
L11: 121 [-]: GETUPVAL R3 1
     122 [-]: MOVE R4 R0   
     123 [-]: CALL R3 1 0  
L12: 124 [-]: RETURN R0 0  


; Name:            
; Defined at line: 346
; #Upvalues:       0
; #Parameters:     1
; Is_vararg:       0
; Max Stack Size:  11

       0 [-]: FASTCALL1 62 R0 L0
       1 [-]: MOVE R2 R0   
       2 [-]: GETIMPORT R1 1 [nil]
       3 [-]: CALL R1 1 1  
L 0:   4 [-]: JUMPIF R1 L1 
       5 [-]: GETIMPORT R3 3 [nil]
       6 [-]: NAMECALL R1 R0 K4 [0xF2DEAF69]
       7 [-]: CALL R1 2 1  
       8 [-]: JUMPIF R1 L2 
L 1:   9 [-]: RETURN R0 0  
L 2:  10 [-]: NAMECALL R1 R0 K5 [0x5E651723]
      11 [-]: CALL R1 1 1  
      12 [-]: FASTCALL1 62 R1 L3
      13 [-]: MOVE R3 R1   
      14 [-]: GETIMPORT R2 1 [nil]
      15 [-]: CALL R2 1 1  
L 3:  16 [-]: JUMPIFNOT R2 L4
      17 [-]: RETURN R0 0  
L 4:  18 [-]: GETIMPORT R2 7 [nil]
      19 [-]: LOADK R3 K8 ["     Exit Gaunlet"]
      20 [-]: CALL R2 1 0  
      21 [-]: NAMECALL R2 R1 K9 [0x5CA33548]
      22 [-]: CALL R2 1 1  
      23 [-]: FASTCALL1 62 R2 L5
      24 [-]: MOVE R4 R2   
      25 [-]: GETIMPORT R3 1 [nil]
      26 [-]: CALL R3 1 1  
L 5:  27 [-]: JUMPIF R3 L6 
      28 [-]: GETIMPORT R3 7 [nil]
      29 [-]: LOADK R5 K10 ["         Player "]
      30 [-]: MOVE R6 R2   
      31 [-]: LOADK R7 K11 [" has reached the end of the speedrun!"]
      32 [-]: CONCAT R4 R5 R7
      33 [-]: CALL R3 1 0  
L 6:  34 [-]: LOADN R5 1   
      35 [-]: GETIMPORT R6 14 [nil]
      36 [-]: LENGTH R3 R6 
      37 [-]: LOADN R4 1   
      38 [-]: FORNPREP R3 L9
L 7:  39 [-]: GETIMPORT R7 14 [nil]
      40 [-]: GETTABLE R6 R7 R5
      41 [-]: JUMPIFNOTEQ R6 R0 L8
      42 [-]: GETIMPORT R6 17 [nil]
      43 [-]: GETIMPORT R7 14 [nil]
      44 [-]: MOVE R8 R5   
      45 [-]: CALL R6 2 0  
      46 [-]: NAMECALL R6 R0 K18 [0xDE321E6F]
      47 [-]: CALL R6 1 1  
      48 [-]: LOADN R8 135 
      49 [-]: LOADN R9 2   
      50 [-]: LOADK R10 K19 [0.75]
      51 [-]: NAMECALL R6 R6 K20 [0x12DD9DA2]
      52 [-]: CALL R6 4 0  
L 8:  53 [-]: FORNLOOP R3 L7
L 9:  54 [-]: RETURN R0 0  


; Name:            
; Defined at line: 371
; #Upvalues:       0
; #Parameters:     1
; Is_vararg:       0
; Max Stack Size:  9

       0 [-]: GETIMPORT R1 1 [nil]
       1 [-]: LOADK R3 K2 ["         Player "]
       2 [-]: NAMECALL R6 R0 K3 [0x5E651723]
       3 [-]: CALL R6 1 1  
       4 [-]: NAMECALL R6 R6 K4 [0x5CA33548]
       5 [-]: CALL R6 1 1  
       6 [-]: MOVE R4 R6   
       7 [-]: LOADK R5 K5 [" has failed the speedrun!"]
       8 [-]: CONCAT R2 R3 R5
       9 [-]: CALL R1 1 0  
      10 [-]: LOADN R3 1   
      11 [-]: GETIMPORT R4 8 [nil]
      12 [-]: LENGTH R1 R4 
      13 [-]: LOADN R2 1   
      14 [-]: FORNPREP R1 L2
L 0:  15 [-]: GETIMPORT R5 8 [nil]
      16 [-]: GETTABLE R4 R5 R3
      17 [-]: JUMPIFNOTEQ R4 R0 L1
      18 [-]: GETIMPORT R4 11 [nil]
      19 [-]: GETIMPORT R5 8 [nil]
      20 [-]: MOVE R6 R3   
      21 [-]: CALL R4 2 0  
      22 [-]: NAMECALL R4 R0 K12 [0xDE321E6F]
      23 [-]: CALL R4 1 1  
      24 [-]: LOADN R6 135 
      25 [-]: LOADN R7 2   
      26 [-]: LOADK R8 K13 [0.75]
      27 [-]: NAMECALL R4 R4 K14 [0x12DD9DA2]
      28 [-]: CALL R4 4 0  
L 1:  29 [-]: FORNLOOP R1 L0
L 2:  30 [-]: RETURN R0 0  


; Name:            
; Defined at line: 382
; #Upvalues:       0
; #Parameters:     1
; Is_vararg:       0
; Max Stack Size:  16

       0 [-]: GETIMPORT R1 1 [nil]
       1 [-]: GETIMPORT R3 3 [nil]
       2 [-]: GETIMPORT R4 5 [nil]
       3 [-]: CALL R4 0 1  
       4 [-]: LOADK R5 K6 [3.4028234663852886e+38]
       5 [-]: NAMECALL R1 R1 K7 [0x4E5939A5]
       6 [-]: CALL R1 4 1  
       7 [-]: FASTCALL1 62 R1 L0
       8 [-]: MOVE R3 R1   
       9 [-]: GETIMPORT R2 9 [nil]
      10 [-]: CALL R2 1 1  
L 0:  11 [-]: JUMPIFNOT R2 L1
      12 [-]: RETURN R0 0  
L 1:  13 [-]: GETIMPORT R2 1 [nil]
      14 [-]: GETIMPORT R4 11 [nil]
      15 [-]: LOADK R5 K12 ["OutsideSpawn"]
      16 [-]: CALL R4 1 -1 
      17 [-]: NAMECALL R2 R2 K13 [0xC7FCADA9]
      18 [-]: CALL R2 -1 1 
      19 [-]: GETIMPORT R3 1 [nil]
      20 [-]: NAMECALL R3 R3 K14 [0x7D108DDB]
      21 [-]: CALL R3 1 1  
      22 [-]: LOADNIL R4   
      23 [-]: LOADN R7 1   
      24 [-]: LENGTH R5 R3 
      25 [-]: LOADN R6 1   
      26 [-]: FORNPREP R5 L9
L 2:  27 [-]: GETTABLE R8 R3 R7
      28 [-]: NAMECALL R8 R8 K15 [0xBB610E5B]
      29 [-]: CALL R8 1 1  
      30 [-]: MOVE R4 R8   
      31 [-]: FASTCALL1 62 R4 L3
      32 [-]: MOVE R9 R4   
      33 [-]: GETIMPORT R8 9 [nil]
      34 [-]: CALL R8 1 1  
L 3:  35 [-]: JUMPIF R8 L8 
      36 [-]: NAMECALL R8 R4 K16 [0xE79E7EF4]
      37 [-]: CALL R8 1 1  
      38 [-]: JUMPIFEQ R8 R0 L8
      39 [-]: NAMECALL R8 R4 K17 [0xDE321E6F]
      40 [-]: CALL R8 1 1  
      41 [-]: NAMECALL R8 R8 K18 [0xF7D48EE0]
      42 [-]: CALL R8 1 1  
      43 [-]: FASTCALL1 62 R8 L4
      44 [-]: MOVE R10 R8  
      45 [-]: GETIMPORT R9 9 [nil]
      46 [-]: CALL R9 1 1  
L 4:  47 [-]: JUMPIF R9 L5 
      48 [-]: NAMECALL R9 R8 K19 [0x1BA58C7F]
      49 [-]: CALL R9 1 1  
      50 [-]: JUMPIFNOT R9 L5
      51 [-]: GETTABLE R9 R3 R7
      52 [-]: NAMECALL R9 R9 K20 [0xA534C3AC]
      53 [-]: CALL R9 1 1  
      54 [-]: NAMECALL R10 R9 K17 [0xDE321E6F]
      55 [-]: CALL R10 1 1 
      56 [-]: NAMECALL R10 R10 K18 [0xF7D48EE0]
      57 [-]: CALL R10 1 1 
      58 [-]: MOVE R8 R10  
      59 [-]: NAMECALL R10 R4 K21 [0x18F03C5D]
      60 [-]: CALL R10 1 0 
L 5:  61 [-]: GETIMPORT R11 23 [nil]
      62 [-]: LOADK R12 K24 ["/Lotus/Powersuits/PowersuitAbilities/OperatorTransferenceAbility"]
      63 [-]: CALL R11 1 -1
      64 [-]: NAMECALL R9 R8 K25 [0x689412A5]
      65 [-]: CALL R9 -1 1 
      66 [-]: FASTCALL1 62 R9 L6
      67 [-]: MOVE R11 R9  
      68 [-]: GETIMPORT R10 9 [nil]
      69 [-]: CALL R10 1 1 
L 6:  70 [-]: JUMPIF R10 L7
      71 [-]: LOADB R12 1  
      72 [-]: NAMECALL R10 R9 K26 [0xA74EA8AC]
      73 [-]: CALL R10 2 0 
L 7:  74 [-]: NAMECALL R13 R4 K28 [0xB40C191A]
      75 [-]: CALL R13 1 1 
      76 [-]: ADDK R12 R13 K27 [1]
      77 [-]: LOADN R13 20 
      78 [-]: NAMECALL R10 R4 K29 [0x6E9719EB]
      79 [-]: CALL R10 3 0 
      80 [-]: GETTABLE R10 R3 R7
      81 [-]: GETIMPORT R13 31 [nil]
      82 [-]: LOADN R14 1  
      83 [-]: LENGTH R15 R2
      84 [-]: CALL R13 2 1 
      85 [-]: GETTABLE R12 R2 R13
      86 [-]: NAMECALL R10 R10 K32 [0x3D89C6AA]
      87 [-]: CALL R10 2 0 
L 8:  88 [-]: FORNLOOP R5 L2
L 9:  89 [-]: RETURN R0 0  


; Name:            
; Defined at line: 416
; #Upvalues:       1
; #Parameters:     1
; Is_vararg:       0
; Max Stack Size:  20

       0 [-]: GETIMPORT R1 1 [nil]
       1 [-]: LOADK R2 K2 ["             Tenno is inside, start shield drain"]
       2 [-]: CALL R1 1 0  
       3 [-]: GETIMPORT R1 5 [nil]
       4 [-]: LOADB R2 0   
       5 [-]: FASTCALL1 62 R1 L0
       6 [-]: MOVE R4 R1   
       7 [-]: GETIMPORT R3 7 [nil]
       8 [-]: CALL R3 1 1  
L 0:   9 [-]: JUMPIFNOT R3 L4
      10 [-]: GETIMPORT R3 9 [nil]
      11 [-]: GETIMPORT R5 11 [nil]
      12 [-]: LOADK R6 K12 ["/EE/Types/Npc/Waypoint"]
      13 [-]: CALL R5 1 1  
      14 [-]: NAMECALL R6 R0 K13 [0xD1586535]
      15 [-]: CALL R6 1 1  
      16 [-]: LOADN R7 100 
      17 [-]: NAMECALL R3 R3 K14 [0x4E5939A5]
      18 [-]: CALL R3 4 1  
      19 [-]: NAMECALL R4 R3 K15 [0x22DA1852]
      20 [-]: CALL R4 1 1  
      21 [-]: GETIMPORT R5 17 [nil]
      22 [-]: LOADK R6 K18 ["SpeedRunA"]
      23 [-]: CALL R5 1 1  
      24 [-]: JUMPIFNOTEQ R4 R5 L1
      25 [-]: LOADN R1 1   
      26 [-]: LOADB R2 1   
      27 [-]: GETIMPORT R4 1 [nil]
      28 [-]: LOADK R6 K19 ["             TEST RUN == SPEEDRUN A. TIMER == "]
      29 [-]: GETIMPORT R8 21 [nil]
      30 [-]: GETTABLE R7 R8 R1
      31 [-]: CONCAT R5 R6 R7
      32 [-]: CALL R4 1 0  
      33 [-]: JUMP L5
     
L 1:  34 [-]: NAMECALL R4 R3 K15 [0x22DA1852]
      35 [-]: CALL R4 1 1  
      36 [-]: GETIMPORT R5 17 [nil]
      37 [-]: LOADK R6 K22 ["SpeedRunB"]
      38 [-]: CALL R5 1 1  
      39 [-]: JUMPIFNOTEQ R4 R5 L2
      40 [-]: LOADN R1 3   
      41 [-]: LOADB R2 1   
      42 [-]: GETIMPORT R4 1 [nil]
      43 [-]: LOADK R6 K23 ["             TEST RUN == SPEEDRUN B. TIMER == "]
      44 [-]: GETIMPORT R8 21 [nil]
      45 [-]: GETTABLE R7 R8 R1
      46 [-]: CONCAT R5 R6 R7
      47 [-]: CALL R4 1 0  
      48 [-]: JUMP L5
     
L 2:  49 [-]: NAMECALL R4 R3 K15 [0x22DA1852]
      50 [-]: CALL R4 1 1  
      51 [-]: GETIMPORT R5 17 [nil]
      52 [-]: LOADK R6 K24 ["SpeedRunC"]
      53 [-]: CALL R5 1 1  
      54 [-]: JUMPIFNOTEQ R4 R5 L3
      55 [-]: LOADN R1 5   
      56 [-]: LOADB R2 1   
      57 [-]: GETIMPORT R4 1 [nil]
      58 [-]: LOADK R6 K25 ["             TEST RUN == SPEEDRUN C. TIMER == "]
      59 [-]: GETIMPORT R8 21 [nil]
      60 [-]: GETTABLE R7 R8 R1
      61 [-]: CONCAT R5 R6 R7
      62 [-]: CALL R4 1 0  
      63 [-]: JUMP L5
     
L 3:  64 [-]: GETIMPORT R4 1 [nil]
      65 [-]: LOADK R5 K26 ["     COULDN'T FIND WAYPOINT. EXITING INSIDETIMER"]
      66 [-]: CALL R4 1 0  
      67 [-]: RETURN R0 0  
      68 [-]: JUMP L5
     
L 4:  69 [-]: GETIMPORT R3 1 [nil]
      70 [-]: LOADK R5 K27 ["     This run is for real! Stage == "]
      71 [-]: MOVE R6 R1   
      72 [-]: LOADK R7 K28 [" and timer == "]
      73 [-]: GETIMPORT R9 21 [nil]
      74 [-]: GETTABLE R8 R9 R1
      75 [-]: CONCAT R4 R5 R8
      76 [-]: CALL R3 1 0  
L 5:  77 [-]: GETIMPORT R3 9 [nil]
      78 [-]: GETIMPORT R5 17 [nil]
      79 [-]: LOADK R6 K29 ["SpaceGolem"]
      80 [-]: CALL R5 1 -1 
      81 [-]: NAMECALL R3 R3 K30 [0x46A0EBF5]
      82 [-]: CALL R3 -1 1 
      83 [-]: MOVE R4 R1   
      84 [-]: NAMECALL R5 R0 K31 [0x1AC1655C]
      85 [-]: CALL R5 1 1  
      86 [-]: NAMECALL R5 R5 K32 [0xB87F958D]
      87 [-]: CALL R5 1 1  
      88 [-]: NAMECALL R6 R0 K31 [0x1AC1655C]
      89 [-]: CALL R6 1 1  
      90 [-]: MOVE R8 R5   
      91 [-]: NAMECALL R6 R6 K33 [0x57369B8B]
      92 [-]: CALL R6 2 0  
      93 [-]: NAMECALL R6 R0 K31 [0x1AC1655C]
      94 [-]: CALL R6 1 1  
      95 [-]: NAMECALL R6 R6 K34 [0xF456C2D7]
      96 [-]: CALL R6 1 1  
      97 [-]: GETIMPORT R8 21 [nil]
      98 [-]: GETTABLE R7 R8 R1
      99 [-]: DIV R8 R5 R7 
     100 [-]: LOADB R9 1   
     101 [-]: LOADN R11 1  
     102 [-]: FASTCALL2 18 R11 R8 L6
     103 [-]: MOVE R12 R8  
     104 [-]: GETIMPORT R10 37 [nil]
     105 [-]: CALL R10 2 1 
L 6: 106 [-]: MOVE R8 R10  
     107 [-]: GETIMPORT R10 39 [nil]
     108 [-]: GETIMPORT R11 41 [nil]
     109 [-]: LOADN R12 1  
     110 [-]: CALL R11 1 0 
     111 [-]: GETIMPORT R14 43 [nil]
     112 [-]: GETTABLEN R13 R14 1
     113 [-]: NAMECALL R11 R0 K44 [0x2A748F85]
     114 [-]: CALL R11 2 0 
     115 [-]: LOADN R11 0  
     116 [-]: LOADB R12 0  
     117 [-]: LOADB R13 0  
L 7: 118 [-]: JUMPIFNOT R9 L19
     119 [-]: LOADN R14 0  
     120 [-]: JUMPIFNOTLT R14 R6 L19
     121 [-]: JUMPIFNOTEQ R1 R4 L19
     122 [-]: JUMPIF R2 L9 
     123 [-]: FASTCALL1 62 R3 L8
     124 [-]: MOVE R15 R3  
     125 [-]: GETIMPORT R14 7 [nil]
     126 [-]: CALL R14 1 1 
L 8: 127 [-]: JUMPIF R14 L19
     128 [-]: NAMECALL R14 R3 K45 [0x5E8B6A40]
     129 [-]: CALL R14 1 1 
     130 [-]: JUMPIFNOT R14 L19
L 9: 131 [-]: LOADB R9 0   
     132 [-]: LOADN R16 1  
     133 [-]: GETIMPORT R17 47 [nil]
     134 [-]: LENGTH R14 R17
     135 [-]: LOADN R15 1  
     136 [-]: FORNPREP R14 L12
L10: 137 [-]: GETIMPORT R18 47 [nil]
     138 [-]: GETTABLE R17 R18 R16
     139 [-]: JUMPIFNOTEQ R17 R0 L11
     140 [-]: LOADB R9 1   
L11: 141 [-]: FORNLOOP R14 L10
L12: 142 [-]: GETIMPORT R14 49 [nil]
     143 [-]: CALL R14 0 1 
     144 [-]: SUB R10 R10 R14
     145 [-]: LOADN R14 0  
     146 [-]: JUMPIFNOTLE R10 R14 L13
     147 [-]: GETIMPORT R14 51 [nil]
     148 [-]: JUMPIFNOT R14 L13
     149 [-]: JUMPIFNOT R9 L13
     150 [-]: GETIMPORT R14 54 [nil]
     151 [-]: CALL R14 0 1 
     152 [-]: SETTABLEKS R8 R14 K55 ["baseAmount"]
     153 [-]: GETIMPORT R17 57 [nil]
     154 [-]: LOADN R18 1  
     155 [-]: NAMECALL R15 R14 K58 [0x1586E35E]
     156 [-]: CALL R15 3 0 
     157 [-]: LOADNIL R17  
     158 [-]: NAMECALL R15 R14 K59 [0xF4DC3420]
     159 [-]: CALL R15 2 0 
     160 [-]: LOADN R17 0  
     161 [-]: NAMECALL R15 R14 K60 [0xCA73DD2A]
     162 [-]: CALL R15 2 0 
     163 [-]: MOVE R17 R14 
     164 [-]: NAMECALL R15 R0 K61 [0x479483BB]
     165 [-]: CALL R15 2 0 
     166 [-]: GETIMPORT R10 39 [nil]
     167 [-]: ADDK R11 R11 K62 [1]
L13: 168 [-]: DIV R14 R6 R5
     169 [-]: LOADK R15 K63 [0.5]
     170 [-]: JUMPIFNOTLE R14 R15 L14
     171 [-]: JUMPIF R12 L14
     172 [-]: GETIMPORT R17 43 [nil]
     173 [-]: GETTABLEN R16 R17 2
     174 [-]: NAMECALL R14 R0 K44 [0x2A748F85]
     175 [-]: CALL R14 2 0 
     176 [-]: LOADB R12 1  
L14: 177 [-]: DIV R14 R6 R5
     178 [-]: LOADK R15 K64 [0.10000000000000001]
     179 [-]: JUMPIFNOTLE R14 R15 L15
     180 [-]: JUMPIF R13 L15
     181 [-]: LOADB R13 1  
     182 [-]: GETIMPORT R16 66 [nil]
     183 [-]: LOADB R17 0  
     184 [-]: LOADN R18 0  
     185 [-]: LOADB R19 0  
     186 [-]: NAMECALL R14 R0 K67 [0x659D451F]
     187 [-]: CALL R14 5 0 
L15: 188 [-]: GETIMPORT R14 69 [nil]
     189 [-]: JUMPIFNOT R14 L16
     190 [-]: JUMPIFNOT R9 L16
     191 [-]: NAMECALL R14 R0 K31 [0x1AC1655C]
     192 [-]: CALL R14 1 1 
     193 [-]: NAMECALL R14 R14 K34 [0xF456C2D7]
     194 [-]: CALL R14 1 1 
     195 [-]: MOVE R6 R14  
     196 [-]: JUMP L17
    
L16: 197 [-]: LOADN R6 1   
L17: 198 [-]: JUMPIF R2 L18
     199 [-]: GETIMPORT R1 5 [nil]
L18: 200 [-]: GETIMPORT R14 41 [nil]
     201 [-]: LOADN R15 0  
     202 [-]: CALL R14 1 0 
     203 [-]: JUMPBACK L7  
L19: 204 [-]: LOADN R14 0  
     205 [-]: JUMPIFLE R6 R14 L20
     206 [-]: JUMPIFEQ R1 R4 L21
L20: 207 [-]: GETUPVAL R14 0
     208 [-]: MOVE R15 R0  
     209 [-]: CALL R14 1 0 
     210 [-]: GETIMPORT R16 17 [nil]
     211 [-]: LOADK R17 K70 ["TeleportAndFade"]
     212 [-]: CALL R16 1 1 
     213 [-]: LOADB R17 0  
     214 [-]: NAMECALL R14 R0 K71 [0xD5F7912B]
     215 [-]: CALL R14 3 0 
L21: 216 [-]: RETURN R0 0  


; Name:            
; Defined at line: 527
; #Upvalues:       0
; #Parameters:     1
; Is_vararg:       0
; Max Stack Size:  7

       0 [-]: NAMECALL R1 R0 K0 [0xCD73323E]
       1 [-]: CALL R1 1 1  
       2 [-]: GETIMPORT R3 3 [nil]
       3 [-]: FASTCALL1 62 R3 L0
       4 [-]: GETIMPORT R2 5 [nil]
       5 [-]: CALL R2 1 1  
L 0:   6 [-]: JUMPIFNOT R2 L1
       7 [-]: GETIMPORT R2 6 [nil]
       8 [-]: NEWTABLE R3 0 0
       9 [-]: SETTABLEKS R3 R2 K2 ["PlayersInGauntlet"]
L 1:  10 [-]: LOADN R4 1   
      11 [-]: GETIMPORT R5 3 [nil]
      12 [-]: LENGTH R2 R5 
      13 [-]: LOADN R3 1   
      14 [-]: FORNPREP R2 L4
L 2:  15 [-]: GETIMPORT R6 3 [nil]
      16 [-]: GETTABLE R5 R6 R4
      17 [-]: JUMPIFNOTEQ R5 R1 L3
      18 [-]: RETURN R0 0  
L 3:  19 [-]: FORNLOOP R2 L2
L 4:  20 [-]: NAMECALL R2 R1 K7 [0xDE321E6F]
      21 [-]: CALL R2 1 1  
      22 [-]: LOADN R4 135 
      23 [-]: LOADN R5 2   
      24 [-]: LOADK R6 K8 [0.75]
      25 [-]: NAMECALL R2 R2 K9 [0x5E6704FF]
      26 [-]: CALL R2 4 0  
      27 [-]: GETIMPORT R3 3 [nil]
      28 [-]: FASTCALL2 52 R3 R1 L5
      29 [-]: MOVE R4 R1   
      30 [-]: GETIMPORT R2 12 [nil]
      31 [-]: CALL R2 2 0  
L 5:  32 [-]: GETIMPORT R4 14 [nil]
      33 [-]: LOADK R5 K15 ["InsideTimer"]
      34 [-]: CALL R4 1 1  
      35 [-]: LOADB R5 0   
      36 [-]: NAMECALL R2 R1 K16 [0xD5F7912B]
      37 [-]: CALL R2 3 0  
      38 [-]: RETURN R0 0  


; Name:            
; Defined at line: 548
; #Upvalues:       2
; #Parameters:     0
; Is_vararg:       0
; Max Stack Size:  13

       0 [-]: GETIMPORT R0 1 [nil]
       1 [-]: LOADK R1 K2 ["     Weakpoint has been destroyed"]
       2 [-]: CALL R0 1 0  
       3 [-]: GETIMPORT R0 4 [nil]
       4 [-]: LOADN R1 1   
       5 [-]: CALL R0 1 0  
       6 [-]: GETUPVAL R0 0
       7 [-]: GETIMPORT R2 6 [nil]
       8 [-]: NAMECALL R0 R0 K7 [0xC19D05D7]
       9 [-]: CALL R0 2 0  
      10 [-]: GETIMPORT R0 9 [nil]
      11 [-]: GETIMPORT R2 11 [nil]
      12 [-]: LOADK R3 K12 ["GolemWeakpointDestroyedVocal"]
      13 [-]: CALL R2 1 -1 
      14 [-]: NAMECALL R0 R0 K13 [0x46A0EBF5]
      15 [-]: CALL R0 -1 1 
      16 [-]: GETIMPORT R1 9 [nil]
      17 [-]: GETIMPORT R3 15 [nil]
      18 [-]: GETIMPORT R4 17 [nil]
      19 [-]: CALL R4 0 1  
      20 [-]: LOADK R5 K18 [3.4028234663852886e+38]
      21 [-]: NAMECALL R1 R1 K19 [0x4E5939A5]
      22 [-]: CALL R1 4 1  
L 0:  23 [-]: FASTCALL1 62 R1 L1
      24 [-]: MOVE R3 R1   
      25 [-]: GETIMPORT R2 21 [nil]
      26 [-]: CALL R2 1 1  
L 1:  27 [-]: JUMPIFNOT R2 L2
      28 [-]: GETIMPORT R2 9 [nil]
      29 [-]: GETIMPORT R4 15 [nil]
      30 [-]: GETIMPORT R5 17 [nil]
      31 [-]: CALL R5 0 1  
      32 [-]: LOADK R6 K18 [3.4028234663852886e+38]
      33 [-]: NAMECALL R2 R2 K19 [0x4E5939A5]
      34 [-]: CALL R2 4 1  
      35 [-]: MOVE R1 R2   
      36 [-]: GETIMPORT R2 4 [nil]
      37 [-]: LOADN R3 1   
      38 [-]: CALL R2 1 0  
      39 [-]: JUMPBACK L0  
L 2:  40 [-]: GETIMPORT R2 9 [nil]
      41 [-]: NAMECALL R2 R2 K22 [0x18D05D30]
      42 [-]: CALL R2 1 1  
      43 [-]: JUMPIFNOT R2 L12
      44 [-]: GETIMPORT R2 4 [nil]
      45 [-]: LOADN R3 3   
      46 [-]: CALL R2 1 0  
      47 [-]: GETIMPORT R2 9 [nil]
      48 [-]: GETIMPORT R4 24 [nil]
      49 [-]: NAMECALL R2 R2 K25 [0xFB669000]
      50 [-]: CALL R2 2 1  
      51 [-]: LOADB R3 0   
L 3:  52 [-]: JUMPXEQKB R3 0 L7 NOT
      53 [-]: LOADB R4 0   
      54 [-]: GETIMPORT R5 27 [nil]
      55 [-]: MOVE R6 R2   
      56 [-]: CALL R5 1 3  
      57 [-]: FORGPREP_NEXT R5 L6
L 4:  58 [-]: JUMPIF R4 L5 
      59 [-]: NAMECALL R10 R9 K28 [0x1DC7376B]
      60 [-]: CALL R10 1 1 
      61 [-]: JUMPXEQKB R10 1 L5 NOT
      62 [-]: LOADB R4 1   
L 5:  63 [-]: LOADN R12 5  
      64 [-]: NAMECALL R10 R9 K29 [0x1206721E]
      65 [-]: CALL R10 2 0 
L 6:  66 [-]: FORGLOOP R5 L4 2
      67 [-]: NOT R3 R4    
      68 [-]: GETIMPORT R5 4 [nil]
      69 [-]: LOADK R6 K30 [0.20000000000000001]
      70 [-]: CALL R5 1 0  
      71 [-]: JUMPBACK L3  
L 7:  72 [-]: GETIMPORT R4 9 [nil]
      73 [-]: GETIMPORT R6 32 [nil]
      74 [-]: NAMECALL R4 R4 K13 [0x46A0EBF5]
      75 [-]: CALL R4 2 1  
      76 [-]: FASTCALL1 62 R4 L8
      77 [-]: MOVE R6 R4   
      78 [-]: GETIMPORT R5 21 [nil]
      79 [-]: CALL R5 1 1  
L 8:  80 [-]: JUMPIF R5 L9 
      81 [-]: LOADK R7 K33 ["TriggerPort"]
      82 [-]: NAMECALL R5 R4 K34 [0x8EB2112D]
      83 [-]: CALL R5 2 0  
L 9:  84 [-]: LOADB R7 0   
      85 [-]: NAMECALL R5 R1 K35 [0x113A6664]
      86 [-]: CALL R5 2 0  
      87 [-]: FASTCALL1 62 R0 L10
      88 [-]: MOVE R6 R0   
      89 [-]: GETIMPORT R5 21 [nil]
      90 [-]: CALL R5 1 1  
L10:  91 [-]: JUMPIF R5 L11
      92 [-]: LOADK R7 K36 ["Enable"]
      93 [-]: NAMECALL R5 R0 K34 [0x8EB2112D]
      94 [-]: CALL R5 2 0  
L11:  95 [-]: GETIMPORT R5 38 [nil]
      96 [-]: GETIMPORT R7 41 [nil]
      97 [-]: ADDK R6 R7 K39 [1]
      98 [-]: SETTABLEKS R6 R5 K40 ["SpaceGolemStage"]
      99 [-]: GETUPVAL R5 0
     100 [-]: GETUPVAL R7 1
     101 [-]: GETIMPORT R8 41 [nil]
     102 [-]: NAMECALL R5 R5 K42 [0x751F061D]
     103 [-]: CALL R5 3 0  
     104 [-]: GETIMPORT R5 38 [nil]
     105 [-]: LOADB R6 0   
     106 [-]: SETTABLEKS R6 R5 K43 ["GolemAttached"]
L12: 107 [-]: RETURN R0 0  


; Name:            
; Defined at line: 596
; #Upvalues:       0
; #Parameters:     2
; Is_vararg:       0
; Max Stack Size:  4

       0 [-]: SUB R2 R0 R1 
       1 [-]: LOADN R3 180 
       2 [-]: JUMPIFNOTLT R3 R2 L0
       3 [-]: SUBK R0 R0 K0 [360]
L 0:   4 [-]: SUB R2 R0 R1 
       5 [-]: LOADN R3 -180
       6 [-]: JUMPIFNOTLT R2 R3 L1
       7 [-]: ADDK R0 R0 K0 [360]
L 1:   8 [-]: SUB R2 R0 R1 
       9 [-]: RETURN R2 1  


; Name:            
; Defined at line: 608
; #Upvalues:       10
; #Parameters:     1
; Is_vararg:       0
; Max Stack Size:  30

       0 [-]: GETUPVAL R1 0
       1 [-]: GETUPVAL R3 1
       2 [-]: LOADN R4 0   
       3 [-]: NAMECALL R1 R1 K0 [0x751F061D]
       4 [-]: CALL R1 3 0  
       5 [-]: GETUPVAL R1 0
       6 [-]: GETUPVAL R3 2
       7 [-]: LOADN R4 180 
       8 [-]: NAMECALL R1 R1 K0 [0x751F061D]
       9 [-]: CALL R1 3 0  
L 0:  10 [-]: GETIMPORT R2 3 [nil]
      11 [-]: FASTCALL1 62 R2 L1
      12 [-]: GETIMPORT R1 5 [nil]
      13 [-]: CALL R1 1 1  
L 1:  14 [-]: JUMPIFNOT R1 L2
      15 [-]: GETIMPORT R1 7 [nil]
      16 [-]: LOADK R2 K8 [0.10000000000000001]
      17 [-]: CALL R1 1 0  
      18 [-]: JUMPBACK L0  
L 2:  19 [-]: GETUPVAL R1 3
      20 [-]: NAMECALL R1 R1 K9 [0x66905CB0]
      21 [-]: CALL R1 1 1  
      22 [-]: GETIMPORT R2 11 [nil]
      23 [-]: GETIMPORT R4 13 [nil]
      24 [-]: LOADK R5 K14 ["GolemWaypoint"]
      25 [-]: CALL R4 1 -1 
      26 [-]: NAMECALL R2 R2 K15 [0xC7FCADA9]
      27 [-]: CALL R2 -1 1 
      28 [-]: GETIMPORT R3 11 [nil]
      29 [-]: GETIMPORT R5 13 [nil]
      30 [-]: LOADK R6 K16 ["ExteriorSpawning"]
      31 [-]: CALL R5 1 -1 
      32 [-]: NAMECALL R3 R3 K17 [0x46A0EBF5]
      33 [-]: CALL R3 -1 1 
      34 [-]: LOADN R6 1   
      35 [-]: LENGTH R4 R2 
      36 [-]: LOADN R5 1   
      37 [-]: FORNPREP R4 L6
L 3:  38 [-]: GETTABLE R8 R2 R6
      39 [-]: FASTCALL1 62 R8 L4
      40 [-]: GETIMPORT R7 5 [nil]
      41 [-]: CALL R7 1 1  
L 4:  42 [-]: JUMPIF R7 L5 
      43 [-]: GETTABLE R7 R2 R6
      44 [-]: LOADK R9 K18 ["Disable"]
      45 [-]: NAMECALL R7 R7 K19 [0x8EB2112D]
      46 [-]: CALL R7 2 0  
L 5:  47 [-]: FORNLOOP R4 L3
L 6:  48 [-]: GETIMPORT R4 20 [nil]
      49 [-]: NEWTABLE R5 0 0
      50 [-]: SETTABLEKS R5 R4 K21 ["PlayersInGauntlet"]
      51 [-]: GETIMPORT R4 20 [nil]
      52 [-]: LOADB R5 1   
      53 [-]: SETTABLEKS R5 R4 K22 ["GolemAttached"]
      54 [-]: GETIMPORT R4 20 [nil]
      55 [-]: LOADN R5 1   
      56 [-]: SETTABLEKS R5 R4 K23 ["SpaceGolemStage"]
      57 [-]: GETUPVAL R4 0
      58 [-]: GETUPVAL R6 4
      59 [-]: GETIMPORT R7 24 [nil]
      60 [-]: NAMECALL R4 R4 K0 [0x751F061D]
      61 [-]: CALL R4 3 0  
      62 [-]: GETIMPORT R4 7 [nil]
      63 [-]: GETIMPORT R5 26 [nil]
      64 [-]: CALL R4 1 0  
      65 [-]: GETIMPORT R6 28 [nil]
      66 [-]: GETIMPORT R7 30 [nil]
      67 [-]: GETIMPORT R8 13 [nil]
      68 [-]: LOADK R9 K31 ["RandomTeam"]
      69 [-]: CALL R8 1 1  
      70 [-]: LOADN R9 100 
      71 [-]: NAMECALL R4 R1 K32 [0x33FC842F]
      72 [-]: CALL R4 5 1  
      73 [-]: NAMECALL R5 R4 K33 [0xBB610E5B]
      74 [-]: CALL R5 1 1  
      75 [-]: GETIMPORT R6 20 [nil]
      76 [-]: SETTABLEKS R5 R6 K34 ["vipAvatar"]
      77 [-]: NAMECALL R6 R5 K35 [0xB40C191A]
      78 [-]: CALL R6 1 1  
      79 [-]: MOVE R7 R6   
      80 [-]: LOADNIL R8   
      81 [-]: GETIMPORT R10 37 [nil]
      82 [-]: GETTABLEN R9 R10 1
      83 [-]: LOADK R11 K38 ["Enable"]
      84 [-]: NAMECALL R9 R9 K19 [0x8EB2112D]
      85 [-]: CALL R9 2 0  
      86 [-]: GETIMPORT R9 11 [nil]
      87 [-]: GETIMPORT R11 13 [nil]
      88 [-]: LOADK R12 K39 ["ExhaustOn"]
      89 [-]: CALL R11 1 1 
      90 [-]: NAMECALL R12 R5 K40 [0xD1586535]
      91 [-]: CALL R12 1 -1
      92 [-]: NAMECALL R9 R9 K41 [0xC7B81E8D]
      93 [-]: CALL R9 -1 1 
      94 [-]: FASTCALL1 62 R9 L7
      95 [-]: MOVE R11 R9  
      96 [-]: GETIMPORT R10 5 [nil]
      97 [-]: CALL R10 1 1 
L 7:  98 [-]: JUMPIF R10 L8
      99 [-]: LOADK R12 K42 ["TriggerPort"]
     100 [-]: NAMECALL R10 R9 K19 [0x8EB2112D]
     101 [-]: CALL R10 2 0 
L 8: 102 [-]: GETUPVAL R12 5
     103 [-]: NAMECALL R10 R5 K43 [0xB2532845]
     104 [-]: CALL R10 2 0 
     105 [-]: GETIMPORT R13 37 [nil]
     106 [-]: GETTABLEN R12 R13 1
     107 [-]: NAMECALL R12 R12 K40 [0xD1586535]
     108 [-]: CALL R12 1 1 
     109 [-]: GETIMPORT R14 37 [nil]
     110 [-]: GETTABLEN R13 R14 1
     111 [-]: NAMECALL R13 R13 K44 [0xCB3851B8]
     112 [-]: CALL R13 1 -1
     113 [-]: NAMECALL R10 R5 K45 [0x589EF1C1]
     114 [-]: CALL R10 -1 0
     115 [-]: GETIMPORT R11 47 [nil]
     116 [-]: FASTCALL1 62 R11 L9
     117 [-]: GETIMPORT R10 5 [nil]
     118 [-]: CALL R10 1 1 
L 9: 119 [-]: JUMPIF R10 L11
     120 [-]: GETIMPORT R10 47 [nil]
     121 [-]: LOADK R12 K48 ["StartPlaying"]
     122 [-]: NAMECALL R10 R10 K19 [0x8EB2112D]
     123 [-]: CALL R10 2 0 
     124 [-]: GETIMPORT R10 7 [nil]
     125 [-]: LOADN R11 0  
     126 [-]: CALL R10 1 0 
L10: 127 [-]: GETIMPORT R10 47 [nil]
     128 [-]: NAMECALL R10 R10 K49 [0x1C84839C]
     129 [-]: CALL R10 1 1 
     130 [-]: JUMPIFNOT R10 L11
     131 [-]: GETIMPORT R10 7 [nil]
     132 [-]: LOADN R11 0  
     133 [-]: CALL R10 1 0 
     134 [-]: JUMPBACK L10 
L11: 135 [-]: GETIMPORT R13 37 [nil]
     136 [-]: GETTABLEN R12 R13 1
     137 [-]: NAMECALL R12 R12 K40 [0xD1586535]
     138 [-]: CALL R12 1 1 
     139 [-]: GETIMPORT R14 37 [nil]
     140 [-]: GETTABLEN R13 R14 1
     141 [-]: NAMECALL R13 R13 K44 [0xCB3851B8]
     142 [-]: CALL R13 1 -1
     143 [-]: NAMECALL R10 R5 K45 [0x589EF1C1]
     144 [-]: CALL R10 -1 0
     145 [-]: GETIMPORT R11 51 [nil]
     146 [-]: GETTABLEN R10 R11 1
     147 [-]: LOADK R12 K52 ["Execute"]
     148 [-]: NAMECALL R10 R10 K19 [0x8EB2112D]
     149 [-]: CALL R10 2 0 
     150 [-]: GETIMPORT R10 54 [nil]
     151 [-]: LOADK R12 K52 ["Execute"]
     152 [-]: NAMECALL R10 R10 K19 [0x8EB2112D]
     153 [-]: CALL R10 2 0 
     154 [-]: GETUPVAL R10 0
     155 [-]: GETIMPORT R12 56 [nil]
     156 [-]: NAMECALL R10 R10 K57 [0xC19D05D7]
     157 [-]: CALL R10 2 0 
     158 [-]: NAMECALL R10 R5 K58 [0xE79E7EF4]
     159 [-]: CALL R10 1 1 
     160 [-]: LOADB R11 0  
     161 [-]: GETIMPORT R12 11 [nil]
     162 [-]: GETIMPORT R14 13 [nil]
     163 [-]: LOADK R15 K59 ["ExhaustOff"]
     164 [-]: CALL R14 1 1 
     165 [-]: NAMECALL R15 R5 K40 [0xD1586535]
     166 [-]: CALL R15 1 -1
     167 [-]: NAMECALL R12 R12 K41 [0xC7B81E8D]
     168 [-]: CALL R12 -1 1
     169 [-]: GETIMPORT R13 11 [nil]
     170 [-]: GETIMPORT R15 13 [nil]
     171 [-]: LOADK R16 K39 ["ExhaustOn"]
     172 [-]: CALL R15 1 1 
     173 [-]: NAMECALL R16 R5 K40 [0xD1586535]
     174 [-]: CALL R16 1 -1
     175 [-]: NAMECALL R13 R13 K41 [0xC7B81E8D]
     176 [-]: CALL R13 -1 1
     177 [-]: GETIMPORT R14 11 [nil]
     178 [-]: GETIMPORT R16 13 [nil]
     179 [-]: LOADK R17 K60 ["GolemHeartWarningVocal"]
     180 [-]: CALL R16 1 -1
     181 [-]: NAMECALL R14 R14 K17 [0x46A0EBF5]
     182 [-]: CALL R14 -1 1
     183 [-]: LOADNIL R15  
     184 [-]: GETIMPORT R16 62 [nil]
     185 [-]: LOADK R18 K52 ["Execute"]
     186 [-]: NAMECALL R16 R16 K19 [0x8EB2112D]
     187 [-]: CALL R16 2 0 
     188 [-]: LOADB R16 1  
     189 [-]: GETIMPORT R17 64 [nil]
     190 [-]: LOADK R19 K65 ["Start"]
     191 [-]: NAMECALL R17 R17 K19 [0x8EB2112D]
     192 [-]: CALL R17 2 0 
     193 [-]: LOADN R17 10 
L12: 194 [-]: FASTCALL1 62 R5 L13
     195 [-]: MOVE R19 R5  
     196 [-]: GETIMPORT R18 5 [nil]
     197 [-]: CALL R18 1 1 
L13: 198 [-]: JUMPIF R18 L74
     199 [-]: NAMECALL R18 R5 K66 [0x2047CFE7]
     200 [-]: CALL R18 1 1 
     201 [-]: JUMPIF R18 L74
     202 [-]: NAMECALL R18 R5 K67 [0x5E8B6A40]
     203 [-]: CALL R18 1 1 
     204 [-]: JUMPIFNOT R18 L14
     205 [-]: JUMPIF R11 L14
     206 [-]: LOADB R11 1  
     207 [-]: GETIMPORT R18 69 [nil]
     208 [-]: LOADK R20 K18 ["Disable"]
     209 [-]: NAMECALL R18 R18 K19 [0x8EB2112D]
     210 [-]: CALL R18 2 0 
     211 [-]: GETUPVAL R18 6
     212 [-]: MOVE R19 R5  
     213 [-]: LOADB R20 1  
     214 [-]: CALL R18 2 0 
     215 [-]: LOADN R20 1  
     216 [-]: NAMECALL R18 R1 K70 [0xD5BF651F]
     217 [-]: CALL R18 2 0 
     218 [-]: JUMP L19
    
L14: 219 [-]: NAMECALL R18 R5 K67 [0x5E8B6A40]
     220 [-]: CALL R18 1 1 
     221 [-]: JUMPIF R18 L19
     222 [-]: JUMPIFNOT R11 L19
     223 [-]: LOADB R11 0  
     224 [-]: GETIMPORT R18 69 [nil]
     225 [-]: LOADK R20 K38 ["Enable"]
     226 [-]: NAMECALL R18 R18 K19 [0x8EB2112D]
     227 [-]: CALL R18 2 0 
     228 [-]: GETUPVAL R18 6
     229 [-]: MOVE R19 R5  
     230 [-]: LOADB R20 0  
     231 [-]: CALL R18 2 0 
     232 [-]: LOADN R20 0  
     233 [-]: NAMECALL R18 R1 K70 [0xD5BF651F]
     234 [-]: CALL R18 2 0 
     235 [-]: GETIMPORT R18 72 [nil]
     236 [-]: LOADK R19 K73 ["Golem is no longer purified. Engaging engines and kicking players outside"]
     237 [-]: CALL R18 1 0 
     238 [-]: FASTCALL1 62 R14 L15
     239 [-]: MOVE R19 R14 
     240 [-]: GETIMPORT R18 5 [nil]
     241 [-]: CALL R18 1 1 
L15: 242 [-]: JUMPIF R18 L16
     243 [-]: LOADK R20 K38 ["Enable"]
     244 [-]: NAMECALL R18 R14 K19 [0x8EB2112D]
     245 [-]: CALL R18 2 0 
L16: 246 [-]: FASTCALL1 62 R3 L17
     247 [-]: MOVE R19 R3  
     248 [-]: GETIMPORT R18 5 [nil]
     249 [-]: CALL R18 1 1 
L17: 250 [-]: JUMPIF R18 L18
     251 [-]: LOADK R20 K52 ["Execute"]
     252 [-]: NAMECALL R18 R3 K19 [0x8EB2112D]
     253 [-]: CALL R18 2 0 
L18: 254 [-]: GETUPVAL R18 0
     255 [-]: GETIMPORT R20 13 [nil]
     256 [-]: LOADK R21 K74 ["WipeEvent"]
     257 [-]: CALL R20 1 1 
     258 [-]: LOADN R21 1  
     259 [-]: NAMECALL R18 R18 K0 [0x751F061D]
     260 [-]: CALL R18 3 0 
     261 [-]: GETIMPORT R18 7 [nil]
     262 [-]: LOADN R19 15 
     263 [-]: CALL R18 1 0 
     264 [-]: GETUPVAL R18 0
     265 [-]: GETIMPORT R20 13 [nil]
     266 [-]: LOADK R21 K74 ["WipeEvent"]
     267 [-]: CALL R20 1 1 
     268 [-]: LOADN R21 0  
     269 [-]: NAMECALL R18 R18 K0 [0x751F061D]
     270 [-]: CALL R18 3 0 
     271 [-]: GETIMPORT R18 69 [nil]
     272 [-]: LOADK R20 K18 ["Disable"]
     273 [-]: NAMECALL R18 R18 K19 [0x8EB2112D]
     274 [-]: CALL R18 2 0 
L19: 275 [-]: NAMECALL R18 R5 K67 [0x5E8B6A40]
     276 [-]: CALL R18 1 1 
     277 [-]: JUMPIF R18 L20
     278 [-]: GETUPVAL R18 7
     279 [-]: MOVE R19 R10 
     280 [-]: CALL R18 1 0 
L20: 281 [-]: GETIMPORT R18 75 [nil]
     282 [-]: JUMPIF R18 L34
     283 [-]: GETUPVAL R20 5
     284 [-]: NAMECALL R18 R5 K76 [0xB6A7C46E]
     285 [-]: CALL R18 2 1 
     286 [-]: JUMPIFNOT R18 L34
     287 [-]: NAMECALL R18 R5 K40 [0xD1586535]
     288 [-]: CALL R18 1 1 
L21: 289 [-]: FASTCALL1 62 R5 L22
     290 [-]: MOVE R20 R5  
     291 [-]: GETIMPORT R19 5 [nil]
     292 [-]: CALL R19 1 1 
L22: 293 [-]: JUMPIF R19 L23
     294 [-]: LOADN R21 16 
     295 [-]: NAMECALL R19 R5 K77 [0x0E46E45B]
     296 [-]: CALL R19 2 1 
     297 [-]: JUMPIFNOT R19 L23
     298 [-]: GETIMPORT R19 72 [nil]
     299 [-]: LOADK R20 K78 ["                         won't leave perch until MENACE posture modifier is cleared!"]
     300 [-]: CALL R19 1 0 
     301 [-]: GETIMPORT R19 7 [nil]
     302 [-]: LOADK R20 K79 [0.050000000000000003]
     303 [-]: CALL R19 1 0 
     304 [-]: JUMPBACK L21 
L23: 305 [-]: FASTCALL1 62 R5 L24
     306 [-]: MOVE R20 R5  
     307 [-]: GETIMPORT R19 5 [nil]
     308 [-]: CALL R19 1 1 
L24: 309 [-]: JUMPIF R19 L25
     310 [-]: NAMECALL R19 R5 K40 [0xD1586535]
     311 [-]: CALL R19 1 1 
     312 [-]: MOVE R18 R19 
L25: 313 [-]: GETIMPORT R19 64 [nil]
     314 [-]: LOADK R21 K80 ["Stop"]
     315 [-]: NAMECALL R19 R19 K19 [0x8EB2112D]
     316 [-]: CALL R19 2 0 
     317 [-]: GETIMPORT R19 11 [nil]
     318 [-]: GETIMPORT R21 82 [nil]
     319 [-]: MOVE R22 R18 
     320 [-]: LOADN R23 100
     321 [-]: NAMECALL R19 R19 K83 [0x4E5939A5]
     322 [-]: CALL R19 4 1 
     323 [-]: MOVE R15 R19 
     324 [-]: FASTCALL1 62 R15 L26
     325 [-]: MOVE R20 R15 
     326 [-]: GETIMPORT R19 5 [nil]
     327 [-]: CALL R19 1 1 
L26: 328 [-]: JUMPIF R19 L27
     329 [-]: NAMECALL R19 R15 K84 [0xA2880940]
     330 [-]: CALL R19 1 0 
L27: 331 [-]: LOADN R21 1  
     332 [-]: GETIMPORT R22 37 [nil]
     333 [-]: LENGTH R19 R22
     334 [-]: LOADN R20 1  
     335 [-]: FORNPREP R19 L29
L28: 336 [-]: GETIMPORT R23 37 [nil]
     337 [-]: GETTABLE R22 R23 R21
     338 [-]: LOADK R24 K18 ["Disable"]
     339 [-]: NAMECALL R22 R22 K19 [0x8EB2112D]
     340 [-]: CALL R22 2 0 
     341 [-]: FORNLOOP R19 L28
L29: 342 [-]: FASTCALL1 62 R5 L30
     343 [-]: MOVE R20 R5  
     344 [-]: GETIMPORT R19 5 [nil]
     345 [-]: CALL R19 1 1 
L30: 346 [-]: JUMPIF R19 L31
     347 [-]: GETUPVAL R21 8
     348 [-]: NAMECALL R19 R5 K43 [0xB2532845]
     349 [-]: CALL R19 2 0 
     350 [-]: LOADB R21 0  
     351 [-]: NAMECALL R19 R5 K85 [0x113A6664]
     352 [-]: CALL R19 2 0 
L31: 353 [-]: LOADB R11 0  
     354 [-]: GETIMPORT R19 11 [nil]
     355 [-]: GETIMPORT R21 13 [nil]
     356 [-]: LOADK R22 K59 ["ExhaustOff"]
     357 [-]: CALL R21 1 1 
     358 [-]: MOVE R22 R18 
     359 [-]: NAMECALL R19 R19 K41 [0xC7B81E8D]
     360 [-]: CALL R19 3 1 
     361 [-]: MOVE R12 R19 
     362 [-]: LOADK R21 K42 ["TriggerPort"]
     363 [-]: NAMECALL R19 R12 K19 [0x8EB2112D]
     364 [-]: CALL R19 2 0 
     365 [-]: GETIMPORT R20 87 [nil]
     366 [-]: FASTCALL1 62 R20 L32
     367 [-]: GETIMPORT R19 5 [nil]
     368 [-]: CALL R19 1 1 
L32: 369 [-]: JUMPIF R19 L33
     370 [-]: GETIMPORT R19 87 [nil]
     371 [-]: LOADK R21 K38 ["Enable"]
     372 [-]: NAMECALL R19 R19 K19 [0x8EB2112D]
     373 [-]: CALL R19 2 0 
L33: 374 [-]: JUMPIFNOT R16 L73
     375 [-]: GETIMPORT R19 89 [nil]
     376 [-]: LOADK R21 K52 ["Execute"]
     377 [-]: NAMECALL R19 R19 K19 [0x8EB2112D]
     378 [-]: CALL R19 2 0 
     379 [-]: LOADB R16 0  
     380 [-]: JUMP L73
    
L34: 381 [-]: GETIMPORT R18 75 [nil]
     382 [-]: JUMPIFNOT R18 L42
     383 [-]: GETUPVAL R20 5
     384 [-]: NAMECALL R18 R5 K76 [0xB6A7C46E]
     385 [-]: CALL R18 2 1 
     386 [-]: JUMPIF R18 L42
     387 [-]: LOADN R17 10 
     388 [-]: GETIMPORT R18 24 [nil]
     389 [-]: JUMPXEQKN R18 K90 L35 NOT [1]
     390 [-]: GETIMPORT R19 37 [nil]
     391 [-]: GETTABLEN R18 R19 1
     392 [-]: LOADK R20 K38 ["Enable"]
     393 [-]: NAMECALL R18 R18 K19 [0x8EB2112D]
     394 [-]: CALL R18 2 0 
     395 [-]: JUMP L41
    
L35: 396 [-]: GETIMPORT R18 24 [nil]
     397 [-]: JUMPXEQKN R18 K91 L38 NOT [3]
     398 [-]: GETIMPORT R19 37 [nil]
     399 [-]: GETTABLEN R18 R19 2
     400 [-]: LOADK R20 K38 ["Enable"]
     401 [-]: NAMECALL R18 R18 K19 [0x8EB2112D]
     402 [-]: CALL R18 2 0 
     403 [-]: GETIMPORT R19 93 [nil]
     404 [-]: GETTABLEN R18 R19 1
     405 [-]: GETIMPORT R20 95 [nil]
     406 [-]: NAMECALL R18 R18 K96 [0xC9F6A7D7]
     407 [-]: CALL R18 2 1 
     408 [-]: FASTCALL1 62 R18 L36
     409 [-]: MOVE R20 R18 
     410 [-]: GETIMPORT R19 5 [nil]
     411 [-]: CALL R19 1 1 
L36: 412 [-]: JUMPIF R19 L37
     413 [-]: NAMECALL R19 R18 K84 [0xA2880940]
     414 [-]: CALL R19 1 0 
L37: 415 [-]: GETIMPORT R19 51 [nil]
     416 [-]: GETTABLEN R18 R19 2
     417 [-]: LOADK R20 K52 ["Execute"]
     418 [-]: NAMECALL R18 R18 K19 [0x8EB2112D]
     419 [-]: CALL R18 2 0 
     420 [-]: JUMP L41
    
L38: 421 [-]: GETIMPORT R18 24 [nil]
     422 [-]: JUMPXEQKN R18 K97 L41 NOT [5]
     423 [-]: GETIMPORT R19 37 [nil]
     424 [-]: GETTABLEN R18 R19 3
     425 [-]: LOADK R20 K38 ["Enable"]
     426 [-]: NAMECALL R18 R18 K19 [0x8EB2112D]
     427 [-]: CALL R18 2 0 
     428 [-]: GETIMPORT R19 93 [nil]
     429 [-]: GETTABLEN R18 R19 2
     430 [-]: GETIMPORT R20 95 [nil]
     431 [-]: NAMECALL R18 R18 K96 [0xC9F6A7D7]
     432 [-]: CALL R18 2 1 
     433 [-]: FASTCALL1 62 R18 L39
     434 [-]: MOVE R20 R18 
     435 [-]: GETIMPORT R19 5 [nil]
     436 [-]: CALL R19 1 1 
L39: 437 [-]: JUMPIF R19 L40
     438 [-]: NAMECALL R19 R18 K84 [0xA2880940]
     439 [-]: CALL R19 1 0 
L40: 440 [-]: GETIMPORT R19 51 [nil]
     441 [-]: GETTABLEN R18 R19 3
     442 [-]: LOADK R20 K52 ["Execute"]
     443 [-]: NAMECALL R18 R18 K19 [0x8EB2112D]
     444 [-]: CALL R18 2 0 
L41: 445 [-]: GETIMPORT R18 64 [nil]
     446 [-]: LOADK R20 K65 ["Start"]
     447 [-]: NAMECALL R18 R18 K19 [0x8EB2112D]
     448 [-]: CALL R18 2 0 
     449 [-]: JUMP L73
    
L42: 450 [-]: GETIMPORT R18 75 [nil]
     451 [-]: JUMPIFNOT R18 L66
     452 [-]: GETUPVAL R20 5
     453 [-]: NAMECALL R18 R5 K76 [0xB6A7C46E]
     454 [-]: CALL R18 2 1 
     455 [-]: JUMPIFNOT R18 L66
     456 [-]: NAMECALL R18 R5 K98 [0xD2715720]
     457 [-]: CALL R18 1 1 
     458 [-]: MOVE R7 R18  
     459 [-]: GETIMPORT R18 24 [nil]
     460 [-]: JUMPXEQKN R18 K90 L43 NOT [1]
     461 [-]: MOVE R8 R6   
     462 [-]: JUMP L45
    
L43: 463 [-]: GETIMPORT R18 24 [nil]
     464 [-]: JUMPXEQKN R18 K91 L44 NOT [3]
     465 [-]: GETIMPORT R19 100 [nil]
     466 [-]: GETTABLEN R18 R19 1
     467 [-]: MUL R8 R18 R6
     468 [-]: JUMP L45
    
L44: 469 [-]: GETIMPORT R18 24 [nil]
     470 [-]: JUMPXEQKN R18 K97 L45 NOT [5]
     471 [-]: GETIMPORT R19 100 [nil]
     472 [-]: GETTABLEN R18 R19 2
     473 [-]: MUL R8 R18 R6
L45: 474 [-]: JUMPIFNOTLT R7 R8 L46
     475 [-]: GETIMPORT R22 102 [nil]
     476 [-]: MUL R21 R6 R22
     477 [-]: ADD R20 R7 R21
     478 [-]: LOADB R21 0  
     479 [-]: NAMECALL R18 R5 K103 [0x014DB014]
     480 [-]: CALL R18 3 0 
     481 [-]: NAMECALL R18 R5 K98 [0xD2715720]
     482 [-]: CALL R18 1 1 
     483 [-]: JUMPIFNOTLT R8 R18 L46
     484 [-]: MOVE R20 R8  
     485 [-]: NAMECALL R18 R5 K103 [0x014DB014]
     486 [-]: CALL R18 2 0 
L46: 487 [-]: SUBK R17 R17 K90 [1]
     488 [-]: LOADN R18 0  
     489 [-]: JUMPIFNOTLE R17 R18 L73
     490 [-]: NAMECALL R18 R5 K104 [0xE75AF8CF]
     491 [-]: CALL R18 1 1 
     492 [-]: JUMPIF R18 L73
     493 [-]: LOADN R17 10 
     494 [-]: LOADK R18 K105 [999999999]
     495 [-]: LOADNIL R19  
     496 [-]: LOADN R22 1  
     497 [-]: GETIMPORT R23 37 [nil]
     498 [-]: LENGTH R20 R23
     499 [-]: LOADN R21 1  
     500 [-]: FORNPREP R20 L49
L47: 501 [-]: GETIMPORT R26 37 [nil]
     502 [-]: GETTABLE R25 R26 R22
     503 [-]: NAMECALL R23 R5 K106 [0xBEBAD19F]
     504 [-]: CALL R23 2 1 
     505 [-]: JUMPIFNOTLT R23 R18 L48
     506 [-]: GETIMPORT R24 37 [nil]
     507 [-]: GETTABLE R19 R24 R22
     508 [-]: MOVE R18 R23 
L48: 509 [-]: FORNLOOP R20 L47
L49: 510 [-]: FASTCALL1 62 R19 L50
     511 [-]: MOVE R21 R19 
     512 [-]: GETIMPORT R20 5 [nil]
     513 [-]: CALL R20 1 1 
L50: 514 [-]: JUMPIF R20 L73
     515 [-]: NAMECALL R20 R19 K44 [0xCB3851B8]
     516 [-]: CALL R20 1 1 
     517 [-]: NAMECALL R21 R19 K40 [0xD1586535]
     518 [-]: CALL R21 1 1 
     519 [-]: NAMECALL R23 R5 K40 [0xD1586535]
     520 [-]: CALL R23 1 1 
     521 [-]: SUB R22 R21 R23
     522 [-]: GETTABLEKS R24 R22 K107 ["x"]
     523 [-]: FASTCALL1 2 R24 L51
     524 [-]: GETIMPORT R23 110 [nil]
     525 [-]: CALL R23 1 1 
L51: 526 [-]: LOADN R24 1  
     527 [-]: JUMPIFLT R24 R23 L54
     528 [-]: GETTABLEKS R24 R22 K111 ["y"]
     529 [-]: FASTCALL1 2 R24 L52
     530 [-]: GETIMPORT R23 110 [nil]
     531 [-]: CALL R23 1 1 
L52: 532 [-]: LOADN R24 1  
     533 [-]: JUMPIFLT R24 R23 L54
     534 [-]: GETTABLEKS R24 R22 K112 ["z"]
     535 [-]: FASTCALL1 2 R24 L53
     536 [-]: GETIMPORT R23 110 [nil]
     537 [-]: CALL R23 1 1 
L53: 538 [-]: LOADN R24 1  
     539 [-]: JUMPIFNOTLT R24 R23 L55
L54: 540 [-]: MOVE R25 R21 
     541 [-]: MOVE R26 R20 
     542 [-]: NAMECALL R23 R5 K45 [0x589EF1C1]
     543 [-]: CALL R23 3 0 
     544 [-]: JUMP L73
    
L55: 545 [-]: NAMECALL R23 R5 K44 [0xCB3851B8]
     546 [-]: CALL R23 1 1 
     547 [-]: GETIMPORT R24 114 [nil]
     548 [-]: CALL R24 0 1 
     549 [-]: GETTABLEKS R26 R20 K115 ["heading"]
     550 [-]: GETTABLEKS R27 R23 K115 ["heading"]
     551 [-]: SUB R28 R26 R27
     552 [-]: LOADN R29 180
     553 [-]: JUMPIFNOTLT R29 R28 L56
     554 [-]: SUBK R26 R26 K116 [360]
L56: 555 [-]: SUB R28 R26 R27
     556 [-]: LOADN R29 -180
     557 [-]: JUMPIFNOTLT R28 R29 L57
     558 [-]: ADDK R26 R26 K116 [360]
L57: 559 [-]: SUB R25 R26 R27
     560 [-]: SETTABLEKS R25 R24 K115 ["heading"]
     561 [-]: GETTABLEKS R26 R20 K117 ["pitch"]
     562 [-]: GETTABLEKS R27 R23 K117 ["pitch"]
     563 [-]: SUB R28 R26 R27
     564 [-]: LOADN R29 180
     565 [-]: JUMPIFNOTLT R29 R28 L58
     566 [-]: SUBK R26 R26 K116 [360]
L58: 567 [-]: SUB R28 R26 R27
     568 [-]: LOADN R29 -180
     569 [-]: JUMPIFNOTLT R28 R29 L59
     570 [-]: ADDK R26 R26 K116 [360]
L59: 571 [-]: SUB R25 R26 R27
     572 [-]: SETTABLEKS R25 R24 K117 ["pitch"]
     573 [-]: GETTABLEKS R26 R20 K118 ["bank"]
     574 [-]: GETTABLEKS R27 R23 K118 ["bank"]
     575 [-]: SUB R28 R26 R27
     576 [-]: LOADN R29 180
     577 [-]: JUMPIFNOTLT R29 R28 L60
     578 [-]: SUBK R26 R26 K116 [360]
L60: 579 [-]: SUB R28 R26 R27
     580 [-]: LOADN R29 -180
     581 [-]: JUMPIFNOTLT R28 R29 L61
     582 [-]: ADDK R26 R26 K116 [360]
L61: 583 [-]: SUB R25 R26 R27
     584 [-]: SETTABLEKS R25 R24 K118 ["bank"]
     585 [-]: GETIMPORT R25 114 [nil]
     586 [-]: CALL R25 0 1 
     587 [-]: GETTABLEKS R27 R25 K115 ["heading"]
     588 [-]: FASTCALL1 2 R27 L62
     589 [-]: GETIMPORT R26 110 [nil]
     590 [-]: CALL R26 1 1 
L62: 591 [-]: LOADN R27 1  
     592 [-]: JUMPIFLT R27 R26 L65
     593 [-]: GETTABLEKS R27 R25 K117 ["pitch"]
     594 [-]: FASTCALL1 2 R27 L63
     595 [-]: GETIMPORT R26 110 [nil]
     596 [-]: CALL R26 1 1 
L63: 597 [-]: LOADN R27 1  
     598 [-]: JUMPIFLT R27 R26 L65
     599 [-]: GETTABLEKS R27 R25 K118 ["bank"]
     600 [-]: FASTCALL1 2 R27 L64
     601 [-]: GETIMPORT R26 110 [nil]
     602 [-]: CALL R26 1 1 
L64: 603 [-]: LOADN R27 1  
     604 [-]: JUMPIFNOTLT R27 R26 L73
L65: 605 [-]: MOVE R28 R21 
     606 [-]: MOVE R29 R20 
     607 [-]: NAMECALL R26 R5 K45 [0x589EF1C1]
     608 [-]: CALL R26 3 0 
     609 [-]: JUMP L73
    
L66: 610 [-]: GETIMPORT R18 24 [nil]
     611 [-]: JUMPXEQKN R18 K119 L67 NOT [2]
     612 [-]: GETIMPORT R19 100 [nil]
     613 [-]: GETTABLEN R18 R19 1
     614 [-]: MUL R8 R18 R6
     615 [-]: JUMP L69
    
L67: 616 [-]: GETIMPORT R18 24 [nil]
     617 [-]: JUMPXEQKN R18 K120 L68 NOT [4]
     618 [-]: GETIMPORT R19 100 [nil]
     619 [-]: GETTABLEN R18 R19 2
     620 [-]: MUL R8 R18 R6
     621 [-]: JUMP L69
    
L68: 622 [-]: LOADN R8 0   
L69: 623 [-]: FASTCALL1 62 R5 L70
     624 [-]: MOVE R19 R5  
     625 [-]: GETIMPORT R18 5 [nil]
     626 [-]: CALL R18 1 1 
L70: 627 [-]: JUMPIF R18 L71
     628 [-]: NAMECALL R18 R5 K98 [0xD2715720]
     629 [-]: CALL R18 1 1 
     630 [-]: JUMPIFNOTLE R8 R18 L71
     631 [-]: GETIMPORT R18 7 [nil]
     632 [-]: LOADN R19 0  
     633 [-]: CALL R18 1 0 
     634 [-]: JUMPBACK L69 
L71: 635 [-]: FASTCALL1 62 R5 L72
     636 [-]: MOVE R19 R5  
     637 [-]: GETIMPORT R18 5 [nil]
     638 [-]: CALL R18 1 1 
L72: 639 [-]: JUMPIF R18 L73
     640 [-]: NAMECALL R18 R5 K98 [0xD2715720]
     641 [-]: CALL R18 1 1 
     642 [-]: LOADN R19 0  
     643 [-]: JUMPIFNOTLT R19 R18 L73
     644 [-]: GETIMPORT R18 62 [nil]
     645 [-]: LOADK R20 K52 ["Execute"]
     646 [-]: NAMECALL R18 R18 K19 [0x8EB2112D]
     647 [-]: CALL R18 2 0 
     648 [-]: MOVE R20 R8  
     649 [-]: NAMECALL R18 R5 K103 [0x014DB014]
     650 [-]: CALL R18 2 0 
     651 [-]: LOADB R16 1  
     652 [-]: GETIMPORT R18 20 [nil]
     653 [-]: GETIMPORT R20 24 [nil]
     654 [-]: ADDK R19 R20 K90 [1]
     655 [-]: SETTABLEKS R19 R18 K23 ["SpaceGolemStage"]
     656 [-]: GETUPVAL R18 0
     657 [-]: GETUPVAL R20 4
     658 [-]: GETIMPORT R21 24 [nil]
     659 [-]: NAMECALL R18 R18 K0 [0x751F061D]
     660 [-]: CALL R18 3 0 
     661 [-]: GETIMPORT R18 20 [nil]
     662 [-]: LOADB R19 1  
     663 [-]: SETTABLEKS R19 R18 K22 ["GolemAttached"]
L73: 664 [-]: GETIMPORT R18 7 [nil]
     665 [-]: LOADN R19 1  
     666 [-]: CALL R18 1 0 
     667 [-]: JUMPBACK L12 
L74: 668 [-]: GETIMPORT R18 64 [nil]
     669 [-]: LOADK R20 K121 ["Kill Agents"]
     670 [-]: NAMECALL R18 R18 K19 [0x8EB2112D]
     671 [-]: CALL R18 2 0 
     672 [-]: GETIMPORT R18 64 [nil]
     673 [-]: LOADK R20 K80 ["Stop"]
     674 [-]: NAMECALL R18 R18 K19 [0x8EB2112D]
     675 [-]: CALL R18 2 0 
     676 [-]: GETUPVAL R18 0
     677 [-]: GETIMPORT R20 123 [nil]
     678 [-]: NAMECALL R18 R18 K57 [0xC19D05D7]
     679 [-]: CALL R18 2 0 
     680 [-]: GETIMPORT R18 7 [nil]
     681 [-]: LOADN R19 8  
     682 [-]: CALL R18 1 0 
     683 [-]: GETIMPORT R18 125 [nil]
     684 [-]: LOADK R20 K48 ["StartPlaying"]
     685 [-]: NAMECALL R18 R18 K19 [0x8EB2112D]
     686 [-]: CALL R18 2 0 
L75: 687 [-]: GETIMPORT R18 125 [nil]
     688 [-]: NAMECALL R18 R18 K49 [0x1C84839C]
     689 [-]: CALL R18 1 1 
     690 [-]: JUMPIFNOT R18 L76
     691 [-]: GETIMPORT R18 7 [nil]
     692 [-]: LOADN R19 0  
     693 [-]: CALL R18 1 0 
     694 [-]: JUMPBACK L75 
L76: 695 [-]: GETIMPORT R18 7 [nil]
     696 [-]: LOADN R19 10 
     697 [-]: CALL R18 1 0 
     698 [-]: GETIMPORT R18 127 [nil]
     699 [-]: LOADK R20 K128 ["Open"]
     700 [-]: NAMECALL R18 R18 K19 [0x8EB2112D]
     701 [-]: CALL R18 2 0 
     702 [-]: GETIMPORT R18 130 [nil]
     703 [-]: GETUPVAL R20 9
     704 [-]: NAMECALL R18 R18 K131 [0xBCFB64AB]
     705 [-]: CALL R18 2 1 
L77: 706 [-]: FASTCALL1 62 R18 L78
     707 [-]: MOVE R20 R18 
     708 [-]: GETIMPORT R19 5 [nil]
     709 [-]: CALL R19 1 1 
L78: 710 [-]: JUMPIFNOT R19 L79
     711 [-]: GETIMPORT R19 7 [nil]
     712 [-]: LOADN R20 0  
     713 [-]: CALL R19 1 0 
     714 [-]: GETIMPORT R19 130 [nil]
     715 [-]: CALL R19 0 1 
     716 [-]: GETUPVAL R21 9
     717 [-]: NAMECALL R19 R19 K131 [0xBCFB64AB]
     718 [-]: CALL R19 2 1 
     719 [-]: MOVE R18 R19 
     720 [-]: JUMPBACK L77 
L79: 721 [-]: LOADK R21 K132 ["AutoClose"]
     722 [-]: LOADN R22 10 
     723 [-]: NAMECALL R19 R18 K133 [0xE4162EED]
     724 [-]: CALL R19 3 0 
     725 [-]: RETURN R0 0  


; Name:            
; Defined at line: 894
; #Upvalues:       0
; #Parameters:     1
; Is_vararg:       0
; Max Stack Size:  10

       0 [-]: GETIMPORT R1 1 [nil]
       1 [-]: LOADK R2 K2 ["         start fade"]
       2 [-]: CALL R1 1 0  
       3 [-]: GETIMPORT R1 4 [nil]
       4 [-]: GETIMPORT R3 6 [nil]
       5 [-]: NAMECALL R4 R0 K7 [0xD1586535]
       6 [-]: CALL R4 1 1  
       7 [-]: LOADN R5 0   
       8 [-]: LOADK R6 K8 [3.4028234663852886e+38]
       9 [-]: NAMECALL R1 R1 K9 [0xFB669000]
      10 [-]: CALL R1 5 1  
      11 [-]: LOADN R4 1   
      12 [-]: LENGTH R2 R1 
      13 [-]: LOADN R3 1   
      14 [-]: FORNPREP R2 L2
L 0:  15 [-]: GETTABLE R5 R1 R4
      16 [-]: NAMECALL R5 R5 K10 [0x1C84839C]
      17 [-]: CALL R5 1 1  
      18 [-]: JUMPIFNOT R5 L1
      19 [-]: GETIMPORT R5 12 [nil]
      20 [-]: LOADN R6 0   
      21 [-]: CALL R5 1 0  
      22 [-]: JUMPBACK L0  
L 1:  23 [-]: FORNLOOP R2 L0
L 2:  24 [-]: GETIMPORT R2 12 [nil]
      25 [-]: LOADK R3 K13 [0.01]
      26 [-]: CALL R2 1 0  
      27 [-]: GETIMPORT R2 4 [nil]
      28 [-]: NAMECALL R2 R2 K14 [0x7C1A0374]
      29 [-]: CALL R2 1 1  
      30 [-]: NAMECALL R3 R2 K15 [0x65C7544C]
      31 [-]: CALL R3 1 1  
      32 [-]: GETIMPORT R4 12 [nil]
      33 [-]: GETIMPORT R5 17 [nil]
      34 [-]: CALL R4 1 0  
      35 [-]: GETIMPORT R4 19 [nil]
      36 [-]: JUMPXEQKN R4 K20 L3 NOT [0]
      37 [-]: GETIMPORT R6 22 [nil]
      38 [-]: NAMECALL R4 R2 K23 [0xB6DF3E50]
      39 [-]: CALL R4 2 0  
      40 [-]: GETIMPORT R4 12 [nil]
      41 [-]: LOADN R5 0   
      42 [-]: CALL R4 1 0  
      43 [-]: RETURN R0 0  
L 3:  44 [-]: LOADN R4 0   
      45 [-]: LOADNIL R5   
L 4:  46 [-]: LOADN R6 1   
      47 [-]: JUMPIFNOTLT R4 R6 L5
      48 [-]: GETIMPORT R6 25 [nil]
      49 [-]: MOVE R7 R3   
      50 [-]: GETIMPORT R8 22 [nil]
      51 [-]: MOVE R9 R4   
      52 [-]: CALL R6 3 1  
      53 [-]: MOVE R5 R6   
      54 [-]: MOVE R8 R5   
      55 [-]: NAMECALL R6 R2 K23 [0xB6DF3E50]
      56 [-]: CALL R6 2 0  
      57 [-]: GETIMPORT R7 27 [nil]
      58 [-]: CALL R7 0 1  
      59 [-]: GETIMPORT R8 19 [nil]
      60 [-]: DIV R6 R7 R8 
      61 [-]: ADD R4 R4 R6 
      62 [-]: GETIMPORT R6 12 [nil]
      63 [-]: LOADN R7 0   
      64 [-]: CALL R6 1 0  
      65 [-]: JUMPBACK L4  
L 5:  66 [-]: GETIMPORT R8 22 [nil]
      67 [-]: NAMECALL R6 R2 K23 [0xB6DF3E50]
      68 [-]: CALL R6 2 0  
      69 [-]: GETIMPORT R6 12 [nil]
      70 [-]: LOADN R7 0   
      71 [-]: CALL R6 1 0  
      72 [-]: RETURN R0 0  


; Name:            
; Defined at line: 932
; #Upvalues:       0
; #Parameters:     1
; Is_vararg:       0
; Max Stack Size:  6

       0 [-]: NAMECALL R1 R0 K0 [0xCD73323E]
       1 [-]: CALL R1 1 1  
       2 [-]: LOADNIL R2   
       3 [-]: FASTCALL1 62 R1 L0
       4 [-]: MOVE R4 R1   
       5 [-]: GETIMPORT R3 2 [nil]
       6 [-]: CALL R3 1 1  
L 0:   7 [-]: JUMPIF R3 L1 
       8 [-]: NAMECALL R3 R1 K3 [0xB40C191A]
       9 [-]: CALL R3 1 1  
      10 [-]: MOVE R2 R3   
      11 [-]: MULK R5 R2 K4 [2]
      12 [-]: NAMECALL R3 R1 K5 [0x6E9719EB]
      13 [-]: CALL R3 2 0  
L 1:  14 [-]: RETURN R0 0  


; Name:            
; Defined at line: 941
; #Upvalues:       3
; #Parameters:     0
; Is_vararg:       0
; Max Stack Size:  12

       0 [-]: GETIMPORT R0 1 [nil]
       1 [-]: GETIMPORT R2 3 [nil]
       2 [-]: GETIMPORT R3 5 [nil]
       3 [-]: CALL R3 0 1  
       4 [-]: LOADK R4 K6 [3.4028234663852886e+38]
       5 [-]: NAMECALL R0 R0 K7 [0x4E5939A5]
       6 [-]: CALL R0 4 1  
L 0:   7 [-]: FASTCALL1 62 R0 L1
       8 [-]: MOVE R2 R0   
       9 [-]: GETIMPORT R1 9 [nil]
      10 [-]: CALL R1 1 1  
L 1:  11 [-]: JUMPIFNOT R1 L2
      12 [-]: GETIMPORT R1 1 [nil]
      13 [-]: GETIMPORT R3 3 [nil]
      14 [-]: GETIMPORT R4 5 [nil]
      15 [-]: CALL R4 0 1  
      16 [-]: LOADK R5 K6 [3.4028234663852886e+38]
      17 [-]: NAMECALL R1 R1 K7 [0x4E5939A5]
      18 [-]: CALL R1 4 1  
      19 [-]: MOVE R0 R1   
      20 [-]: GETIMPORT R1 11 [nil]
      21 [-]: LOADN R2 0   
      22 [-]: CALL R1 1 0  
      23 [-]: JUMPBACK L0  
L 2:  24 [-]: GETIMPORT R1 13 [nil]
      25 [-]: LOADK R2 K14 ["DoPerch"]
      26 [-]: CALL R1 1 1  
      27 [-]: GETIMPORT R3 16 [nil]
      28 [-]: LENGTH R2 R3 
      29 [-]: GETUPVAL R4 0
      30 [-]: GETUPVAL R6 1
      31 [-]: LOADN R7 0   
      32 [-]: NAMECALL R4 R4 K17 [0x0EB34C69]
      33 [-]: CALL R4 3 1  
      34 [-]: DIV R3 R4 R2 
      35 [-]: LOADB R4 1   
L 3:  36 [-]: FASTCALL1 62 R0 L4
      37 [-]: MOVE R6 R0   
      38 [-]: GETIMPORT R5 9 [nil]
      39 [-]: CALL R5 1 1  
L 4:  40 [-]: JUMPIF R5 L5 
      41 [-]: MOVE R7 R1   
      42 [-]: NAMECALL R5 R0 K18 [0xB6A7C46E]
      43 [-]: CALL R5 2 1  
      44 [-]: JUMPIF R5 L5 
      45 [-]: GETIMPORT R5 11 [nil]
      46 [-]: LOADN R6 1   
      47 [-]: CALL R5 1 0  
      48 [-]: JUMPBACK L3  
L 5:  49 [-]: GETIMPORT R5 11 [nil]
      50 [-]: GETIMPORT R6 20 [nil]
      51 [-]: CALL R5 1 0  
L 6:  52 [-]: FASTCALL1 62 R0 L7
      53 [-]: MOVE R6 R0   
      54 [-]: GETIMPORT R5 9 [nil]
      55 [-]: CALL R5 1 1  
L 7:  56 [-]: JUMPIF R5 L16
      57 [-]: MOVE R7 R1   
      58 [-]: NAMECALL R5 R0 K18 [0xB6A7C46E]
      59 [-]: CALL R5 2 1  
      60 [-]: JUMPIFNOT R5 L16
      61 [-]: NAMECALL R5 R0 K21 [0x5E8B6A40]
      62 [-]: CALL R5 1 1  
      63 [-]: JUMPIF R5 L9 
      64 [-]: JUMPIFNOT R4 L9
      65 [-]: LOADB R4 0   
      66 [-]: LOADN R7 1   
      67 [-]: MOVE R5 R2   
      68 [-]: LOADN R6 1   
      69 [-]: FORNPREP R5 L9
L 8:  70 [-]: GETIMPORT R9 16 [nil]
      71 [-]: GETTABLE R8 R9 R7
      72 [-]: LOADK R10 K22 ["Show"]
      73 [-]: NAMECALL R8 R8 K23 [0x8EB2112D]
      74 [-]: CALL R8 2 0  
      75 [-]: GETIMPORT R9 25 [nil]
      76 [-]: GETTABLE R8 R9 R7
      77 [-]: LOADK R10 K22 ["Show"]
      78 [-]: NAMECALL R8 R8 K23 [0x8EB2112D]
      79 [-]: CALL R8 2 0  
      80 [-]: GETIMPORT R9 27 [nil]
      81 [-]: GETTABLE R8 R9 R7
      82 [-]: LOADK R10 K28 ["Hide"]
      83 [-]: NAMECALL R8 R8 K23 [0x8EB2112D]
      84 [-]: CALL R8 2 0  
      85 [-]: GETIMPORT R9 30 [nil]
      86 [-]: GETTABLE R8 R9 R7
      87 [-]: LOADK R10 K28 ["Hide"]
      88 [-]: NAMECALL R8 R8 K23 [0x8EB2112D]
      89 [-]: CALL R8 2 0  
      90 [-]: FORNLOOP R5 L8
L 9:  91 [-]: NAMECALL R5 R0 K21 [0x5E8B6A40]
      92 [-]: CALL R5 1 1  
      93 [-]: JUMPIFNOT R5 L11
      94 [-]: GETUPVAL R5 0
      95 [-]: GETUPVAL R7 2
      96 [-]: LOADN R8 0   
      97 [-]: NAMECALL R5 R5 K17 [0x0EB34C69]
      98 [-]: CALL R5 3 1  
      99 [-]: JUMPIFNOTLE R5 R3 L11
     100 [-]: LOADB R4 1   
     101 [-]: LOADN R7 1   
     102 [-]: MOVE R5 R2   
     103 [-]: LOADN R6 1   
     104 [-]: FORNPREP R5 L15
L10: 105 [-]: GETIMPORT R9 16 [nil]
     106 [-]: GETTABLE R8 R9 R7
     107 [-]: LOADK R10 K28 ["Hide"]
     108 [-]: NAMECALL R8 R8 K23 [0x8EB2112D]
     109 [-]: CALL R8 2 0  
     110 [-]: GETIMPORT R9 25 [nil]
     111 [-]: GETTABLE R8 R9 R7
     112 [-]: LOADK R10 K28 ["Hide"]
     113 [-]: NAMECALL R8 R8 K23 [0x8EB2112D]
     114 [-]: CALL R8 2 0  
     115 [-]: GETIMPORT R9 27 [nil]
     116 [-]: GETTABLE R8 R9 R7
     117 [-]: LOADK R10 K22 ["Show"]
     118 [-]: NAMECALL R8 R8 K23 [0x8EB2112D]
     119 [-]: CALL R8 2 0  
     120 [-]: GETIMPORT R9 30 [nil]
     121 [-]: GETTABLE R8 R9 R7
     122 [-]: LOADK R10 K22 ["Show"]
     123 [-]: NAMECALL R8 R8 K23 [0x8EB2112D]
     124 [-]: CALL R8 2 0  
     125 [-]: FORNLOOP R5 L10
     126 [-]: JUMP L15
    
L11: 127 [-]: NAMECALL R5 R0 K21 [0x5E8B6A40]
     128 [-]: CALL R5 1 1  
     129 [-]: JUMPIFNOT R5 L15
     130 [-]: LOADB R4 1   
     131 [-]: LOADN R7 1   
     132 [-]: MOVE R5 R2   
     133 [-]: LOADN R6 1   
     134 [-]: FORNPREP R5 L15
L12: 135 [-]: GETUPVAL R8 0
     136 [-]: GETUPVAL R10 2
     137 [-]: LOADN R11 0  
     138 [-]: NAMECALL R8 R8 K17 [0x0EB34C69]
     139 [-]: CALL R8 3 1  
     140 [-]: MUL R9 R7 R3 
     141 [-]: JUMPIFNOTLT R9 R8 L13
     142 [-]: GETIMPORT R9 16 [nil]
     143 [-]: GETTABLE R8 R9 R7
     144 [-]: LOADK R10 K22 ["Show"]
     145 [-]: NAMECALL R8 R8 K23 [0x8EB2112D]
     146 [-]: CALL R8 2 0  
     147 [-]: GETIMPORT R9 25 [nil]
     148 [-]: GETTABLE R8 R9 R7
     149 [-]: LOADK R10 K22 ["Show"]
     150 [-]: NAMECALL R8 R8 K23 [0x8EB2112D]
     151 [-]: CALL R8 2 0  
     152 [-]: GETIMPORT R9 27 [nil]
     153 [-]: GETTABLE R8 R9 R7
     154 [-]: LOADK R10 K28 ["Hide"]
     155 [-]: NAMECALL R8 R8 K23 [0x8EB2112D]
     156 [-]: CALL R8 2 0  
     157 [-]: GETIMPORT R9 30 [nil]
     158 [-]: GETTABLE R8 R9 R7
     159 [-]: LOADK R10 K28 ["Hide"]
     160 [-]: NAMECALL R8 R8 K23 [0x8EB2112D]
     161 [-]: CALL R8 2 0  
     162 [-]: JUMP L14
    
L13: 163 [-]: GETIMPORT R9 16 [nil]
     164 [-]: GETTABLE R8 R9 R7
     165 [-]: LOADK R10 K28 ["Hide"]
     166 [-]: NAMECALL R8 R8 K23 [0x8EB2112D]
     167 [-]: CALL R8 2 0  
     168 [-]: GETIMPORT R9 25 [nil]
     169 [-]: GETTABLE R8 R9 R7
     170 [-]: LOADK R10 K28 ["Hide"]
     171 [-]: NAMECALL R8 R8 K23 [0x8EB2112D]
     172 [-]: CALL R8 2 0  
     173 [-]: GETIMPORT R9 27 [nil]
     174 [-]: GETTABLE R8 R9 R7
     175 [-]: LOADK R10 K22 ["Show"]
     176 [-]: NAMECALL R8 R8 K23 [0x8EB2112D]
     177 [-]: CALL R8 2 0  
     178 [-]: GETIMPORT R9 30 [nil]
     179 [-]: GETTABLE R8 R9 R7
     180 [-]: LOADK R10 K22 ["Show"]
     181 [-]: NAMECALL R8 R8 K23 [0x8EB2112D]
     182 [-]: CALL R8 2 0  
L14: 183 [-]: FORNLOOP R5 L12
L15: 184 [-]: GETIMPORT R5 11 [nil]
     185 [-]: LOADK R6 K31 [0.10000000000000001]
     186 [-]: CALL R5 1 0  
     187 [-]: JUMPBACK L6  
L16: 188 [-]: LOADN R7 1   
     189 [-]: LOADN R5 5   
     190 [-]: LOADN R6 1   
     191 [-]: FORNPREP R5 L18
L17: 192 [-]: GETIMPORT R9 16 [nil]
     193 [-]: GETTABLE R8 R9 R7
     194 [-]: LOADK R10 K28 ["Hide"]
     195 [-]: NAMECALL R8 R8 K23 [0x8EB2112D]
     196 [-]: CALL R8 2 0  
     197 [-]: GETIMPORT R9 25 [nil]
     198 [-]: GETTABLE R8 R9 R7
     199 [-]: LOADK R10 K28 ["Hide"]
     200 [-]: NAMECALL R8 R8 K23 [0x8EB2112D]
     201 [-]: CALL R8 2 0  
     202 [-]: GETIMPORT R9 27 [nil]
     203 [-]: GETTABLE R8 R9 R7
     204 [-]: LOADK R10 K22 ["Show"]
     205 [-]: NAMECALL R8 R8 K23 [0x8EB2112D]
     206 [-]: CALL R8 2 0  
     207 [-]: GETIMPORT R9 30 [nil]
     208 [-]: GETTABLE R8 R9 R7
     209 [-]: LOADK R10 K22 ["Show"]
     210 [-]: NAMECALL R8 R8 K23 [0x8EB2112D]
     211 [-]: CALL R8 2 0  
     212 [-]: FORNLOOP R5 L17
L18: 213 [-]: RETURN R0 0  


; Name:            
; Defined at line: 1012
; #Upvalues:       0
; #Parameters:     1
; Is_vararg:       0
; Max Stack Size:  5

       0 [-]: FASTCALL1 62 R0 L0
       1 [-]: MOVE R2 R0   
       2 [-]: GETIMPORT R1 1 [nil]
       3 [-]: CALL R1 1 1  
L 0:   4 [-]: JUMPIFNOT R1 L1
       5 [-]: RETURN R0 0  
L 1:   6 [-]: NAMECALL R1 R0 K2 [0xBB610E5B]
       7 [-]: CALL R1 1 1  
       8 [-]: LOADN R4 0   
       9 [-]: NAMECALL R2 R1 K3 [0x8DDEFF60]
      10 [-]: CALL R2 2 0  
      11 [-]: RETURN R0 0  


; Name:            
; Defined at line: 1020
; #Upvalues:       0
; #Parameters:     1
; Is_vararg:       0
; Max Stack Size:  4

       0 [-]: FASTCALL1 62 R0 L0
       1 [-]: MOVE R2 R0   
       2 [-]: GETIMPORT R1 1 [nil]
       3 [-]: CALL R1 1 1  
L 0:   4 [-]: JUMPIF R1 L2 
       5 [-]: GETIMPORT R3 3 [nil]
       6 [-]: NAMECALL R1 R0 K4 [0xF2DEAF69]
       7 [-]: CALL R1 2 1  
       8 [-]: JUMPIFNOT R1 L2
       9 [-]: GETIMPORT R1 6 [nil]
      10 [-]: LOADK R2 K7 ["modify threat of avatar"]
      11 [-]: CALL R1 1 0  
      12 [-]: LOADN R3 -10 
      13 [-]: NAMECALL R1 R0 K8 [0x1FEDCBCF]
      14 [-]: CALL R1 2 0  
      15 [-]: GETIMPORT R1 10 [nil]
      16 [-]: LOADN R2 8   
      17 [-]: CALL R1 1 0  
      18 [-]: FASTCALL1 62 R0 L1
      19 [-]: MOVE R2 R0   
      20 [-]: GETIMPORT R1 1 [nil]
      21 [-]: CALL R1 1 1  
L 1:  22 [-]: JUMPIF R1 L2 
      23 [-]: GETIMPORT R1 6 [nil]
      24 [-]: LOADK R2 K11 ["removing threat modifier"]
      25 [-]: CALL R1 1 0  
      26 [-]: LOADN R3 0   
      27 [-]: NAMECALL R1 R0 K8 [0x1FEDCBCF]
      28 [-]: CALL R1 2 0  
L 2:  29 [-]: RETURN R0 0  


; Name:            
; Defined at line: 1032
; #Upvalues:       1
; #Parameters:     0
; Is_vararg:       0
; Max Stack Size:  9

       0 [-]: GETIMPORT R0 1 [nil]
       1 [-]: GETIMPORT R2 3 [nil]
       2 [-]: GETIMPORT R3 5 [nil]
       3 [-]: CALL R3 0 1  
       4 [-]: LOADK R4 K6 [3.4028234663852886e+38]
       5 [-]: NAMECALL R0 R0 K7 [0x4E5939A5]
       6 [-]: CALL R0 4 1  
L 0:   7 [-]: FASTCALL1 62 R0 L1
       8 [-]: MOVE R2 R0   
       9 [-]: GETIMPORT R1 9 [nil]
      10 [-]: CALL R1 1 1  
L 1:  11 [-]: JUMPIFNOT R1 L2
      12 [-]: GETIMPORT R1 1 [nil]
      13 [-]: GETIMPORT R3 3 [nil]
      14 [-]: GETIMPORT R4 5 [nil]
      15 [-]: CALL R4 0 1  
      16 [-]: LOADK R5 K6 [3.4028234663852886e+38]
      17 [-]: NAMECALL R1 R1 K7 [0x4E5939A5]
      18 [-]: CALL R1 4 1  
      19 [-]: MOVE R0 R1   
      20 [-]: GETIMPORT R1 11 [nil]
      21 [-]: LOADN R2 0   
      22 [-]: CALL R1 1 0  
      23 [-]: JUMPBACK L0  
L 2:  24 [-]: GETIMPORT R1 11 [nil]
      25 [-]: LOADN R2 2   
      26 [-]: CALL R1 1 0  
L 3:  27 [-]: GETIMPORT R1 13 [nil]
      28 [-]: NAMECALL R1 R1 K14 [0x1C84839C]
      29 [-]: CALL R1 1 1  
      30 [-]: JUMPIFNOT R1 L4
      31 [-]: GETIMPORT R1 11 [nil]
      32 [-]: LOADN R2 0   
      33 [-]: CALL R1 1 0  
      34 [-]: JUMPBACK L3  
L 4:  35 [-]: FASTCALL1 62 R0 L5
      36 [-]: MOVE R2 R0   
      37 [-]: GETIMPORT R1 9 [nil]
      38 [-]: CALL R1 1 1  
L 5:  39 [-]: JUMPIF R1 L6 
      40 [-]: NAMECALL R1 R0 K15 [0x2047CFE7]
      41 [-]: CALL R1 1 1  
      42 [-]: JUMPIF R1 L6 
      43 [-]: GETIMPORT R1 11 [nil]
      44 [-]: GETIMPORT R2 17 [nil]
      45 [-]: LOADN R3 45  
      46 [-]: LOADN R4 75  
      47 [-]: CALL R2 2 -1 
      48 [-]: CALL R1 -1 0 
      49 [-]: GETUPVAL R1 0
      50 [-]: GETIMPORT R4 19 [nil]
      51 [-]: GETIMPORT R5 21 [nil]
      52 [-]: LOADN R6 1   
      53 [-]: GETIMPORT R8 19 [nil]
      54 [-]: LENGTH R7 R8 
      55 [-]: CALL R5 2 1  
      56 [-]: GETTABLE R3 R4 R5
      57 [-]: NAMECALL R1 R1 K22 [0xC19D05D7]
      58 [-]: CALL R1 2 0  
      59 [-]: JUMPBACK L4  
L 6:  60 [-]: RETURN R0 0  


; Name:            
; Defined at line: 1051
; #Upvalues:       0
; #Parameters:     1
; Is_vararg:       0
; Max Stack Size:  8

       0 [-]: GETIMPORT R1 1 [nil]
       1 [-]: GETIMPORT R3 3 [nil]
       2 [-]: GETIMPORT R4 5 [nil]
       3 [-]: CALL R4 0 1  
       4 [-]: LOADK R5 K6 [3.4028234663852886e+38]
       5 [-]: NAMECALL R1 R1 K7 [0x4E5939A5]
       6 [-]: CALL R1 4 1  
       7 [-]: FASTCALL1 62 R1 L0
       8 [-]: MOVE R3 R1   
       9 [-]: GETIMPORT R2 9 [nil]
      10 [-]: CALL R2 1 1  
L 0:  11 [-]: JUMPIFNOT R2 L1
      12 [-]: RETURN R0 0  
L 1:  13 [-]: NAMECALL R2 R1 K10 [0xE79E7EF4]
      14 [-]: CALL R2 1 1  
      15 [-]: LOADN R3 1   
      16 [-]: GETIMPORT R4 12 [nil]
      17 [-]: LOADN R5 5   
      18 [-]: CALL R4 1 0  
L 2:  19 [-]: FASTCALL1 62 R0 L3
      20 [-]: MOVE R5 R0   
      21 [-]: GETIMPORT R4 9 [nil]
      22 [-]: CALL R4 1 1  
L 3:  23 [-]: JUMPIF R4 L5 
      24 [-]: NAMECALL R4 R0 K10 [0xE79E7EF4]
      25 [-]: CALL R4 1 1  
      26 [-]: JUMPIFEQ R4 R2 L5
      27 [-]: GETIMPORT R7 14 [nil]
      28 [-]: GETTABLE R6 R7 R3
      29 [-]: NAMECALL R4 R0 K15 [0x2A748F85]
      30 [-]: CALL R4 2 0  
      31 [-]: ADDK R3 R3 K16 [1]
      32 [-]: GETIMPORT R5 14 [nil]
      33 [-]: LENGTH R4 R5 
      34 [-]: JUMPIFNOTLT R4 R3 L4
      35 [-]: RETURN R0 0  
L 4:  36 [-]: GETIMPORT R4 12 [nil]
      37 [-]: GETIMPORT R5 18 [nil]
      38 [-]: LOADN R6 30  
      39 [-]: LOADN R7 60  
      40 [-]: CALL R5 2 -1 
      41 [-]: CALL R4 -1 0 
      42 [-]: JUMPBACK L2  
L 5:  43 [-]: RETURN R0 0  


; Name:            
; Defined at line: 1072
; #Upvalues:       0
; #Parameters:     1
; Is_vararg:       0
; Max Stack Size:  6

       0 [-]: NAMECALL R1 R0 K0 [0xCD73323E]
       1 [-]: CALL R1 1 1  
       2 [-]: FASTCALL1 62 R1 L0
       3 [-]: MOVE R3 R1   
       4 [-]: GETIMPORT R2 2 [nil]
       5 [-]: CALL R2 1 1  
L 0:   6 [-]: JUMPIF R2 L1 
       7 [-]: GETIMPORT R4 4 [nil]
       8 [-]: LOADK R5 K5 ["PlayTauntsOnAvatar"]
       9 [-]: CALL R4 1 1  
      10 [-]: LOADB R5 0   
      11 [-]: NAMECALL R2 R1 K6 [0xD5F7912B]
      12 [-]: CALL R2 3 0  
L 1:  13 [-]: RETURN R0 0  


; Name:            
; Defined at line: 1079
; #Upvalues:       0
; #Parameters:     1
; Is_vararg:       0
; Max Stack Size:  12

       0 [-]: NAMECALL R1 R0 K0 [0xCD73323E]
       1 [-]: CALL R1 1 1  
       2 [-]: LOADB R2 0   
       3 [-]: GETIMPORT R3 2 [nil]
       4 [-]: LOADN R4 0   
       5 [-]: LOADN R5 1   
       6 [-]: CALL R3 2 1  
       7 [-]: GETIMPORT R5 5 [nil]
       8 [-]: FASTCALL1 62 R5 L0
       9 [-]: GETIMPORT R4 7 [nil]
      10 [-]: CALL R4 1 1  
L 0:  11 [-]: JUMPIFNOT R4 L2
      12 [-]: GETIMPORT R4 8 [nil]
      13 [-]: NEWTABLE R5 0 0
      14 [-]: SETTABLEKS R5 R4 K4 ["DebrisTransList"]
      15 [-]: GETIMPORT R5 5 [nil]
      16 [-]: FASTCALL2 52 R5 R1 L1
      17 [-]: MOVE R6 R1   
      18 [-]: GETIMPORT R4 11 [nil]
      19 [-]: CALL R4 2 0  
L 1:  20 [-]: GETIMPORT R7 13 [nil]
      21 [-]: GETIMPORT R8 15 [nil]
      22 [-]: LOADN R9 1   
      23 [-]: GETIMPORT R11 13 [nil]
      24 [-]: LENGTH R10 R11
      25 [-]: CALL R8 2 1  
      26 [-]: GETTABLE R6 R7 R8
      27 [-]: NAMECALL R4 R1 K16 [0x2A748F85]
      28 [-]: CALL R4 2 0  
      29 [-]: JUMP L5
     
L 2:  30 [-]: LOADN R6 1   
      31 [-]: GETIMPORT R7 5 [nil]
      32 [-]: LENGTH R4 R7 
      33 [-]: LOADN R5 1   
      34 [-]: FORNPREP R4 L5
L 3:  35 [-]: GETIMPORT R8 5 [nil]
      36 [-]: GETTABLE R7 R8 R6
      37 [-]: JUMPIFNOTEQ R7 R1 L4
      38 [-]: LOADB R2 1   
L 4:  39 [-]: FORNLOOP R4 L3
L 5:  40 [-]: JUMPIFNOT R2 L6
      41 [-]: LOADK R4 K17 [0.050000000000000003]
      42 [-]: JUMPIFNOTLT R3 R4 L6
      43 [-]: GETIMPORT R7 13 [nil]
      44 [-]: GETIMPORT R8 15 [nil]
      45 [-]: LOADN R9 1   
      46 [-]: GETIMPORT R11 13 [nil]
      47 [-]: LENGTH R10 R11
      48 [-]: CALL R8 2 1  
      49 [-]: GETTABLE R6 R7 R8
      50 [-]: NAMECALL R4 R1 K16 [0x2A748F85]
      51 [-]: CALL R4 2 0  
L 6:  52 [-]: RETURN R0 0  


; Name:            
; Defined at line: 1104
; #Upvalues:       0
; #Parameters:     0
; Is_vararg:       0
; Max Stack Size:  18

       0 [-]: GETIMPORT R0 1 [nil]
       1 [-]: GETIMPORT R2 3 [nil]
       2 [-]: LOADK R3 K4 ["MinionSource"]
       3 [-]: CALL R2 1 -1 
       4 [-]: NAMECALL R0 R0 K5 [0xC7FCADA9]
       5 [-]: CALL R0 -1 1 
       6 [-]: GETIMPORT R1 1 [nil]
       7 [-]: GETIMPORT R3 7 [nil]
       8 [-]: GETIMPORT R4 9 [nil]
       9 [-]: CALL R4 0 1  
      10 [-]: LOADK R5 K10 [3.4028234663852886e+38]
      11 [-]: NAMECALL R1 R1 K11 [0x4E5939A5]
      12 [-]: CALL R1 4 1  
      13 [-]: NAMECALL R2 R1 K12 [0xD1586535]
      14 [-]: CALL R2 1 1  
      15 [-]: NAMECALL R3 R1 K13 [0xE79E7EF4]
      16 [-]: CALL R3 1 1  
      17 [-]: LOADNIL R4   
      18 [-]: LOADNIL R5   
      19 [-]: LOADNIL R6   
      20 [-]: LOADNIL R7   
      21 [-]: LOADB R8 0   
      22 [-]: FASTCALL1 62 R0 L0
      23 [-]: MOVE R10 R0  
      24 [-]: GETIMPORT R9 15 [nil]
      25 [-]: CALL R9 1 1  
L 0:  26 [-]: JUMPIFNOT R9 L1
      27 [-]: RETURN R0 0  
L 1:  28 [-]: FASTCALL1 62 R1 L2
      29 [-]: MOVE R10 R1  
      30 [-]: GETIMPORT R9 15 [nil]
      31 [-]: CALL R9 1 1  
L 2:  32 [-]: JUMPIF R9 L17
      33 [-]: NAMECALL R9 R1 K16 [0x2047CFE7]
      34 [-]: CALL R9 1 1  
      35 [-]: JUMPIF R9 L17
      36 [-]: NAMECALL R9 R1 K17 [0x5E8B6A40]
      37 [-]: CALL R9 1 1  
      38 [-]: JUMPIF R9 L3 
      39 [-]: GETIMPORT R9 20 [nil]
      40 [-]: JUMPIF R9 L17
L 3:  41 [-]: GETIMPORT R9 1 [nil]
      42 [-]: NAMECALL R9 R9 K21 [0x8B5B1F58]
      43 [-]: CALL R9 1 1  
      44 [-]: MOVE R6 R9   
      45 [-]: LOADB R8 0   
      46 [-]: LOADN R11 1  
      47 [-]: LENGTH R9 R6 
      48 [-]: LOADN R10 1  
      49 [-]: FORNPREP R9 L6
L 4:  50 [-]: GETTABLE R12 R6 R11
      51 [-]: NAMECALL R12 R12 K13 [0xE79E7EF4]
      52 [-]: CALL R12 1 1 
      53 [-]: JUMPIFNOTEQ R12 R3 L5
      54 [-]: LOADB R8 1   
L 5:  55 [-]: FORNLOOP R9 L4
L 6:  56 [-]: LOADN R11 1  
      57 [-]: LENGTH R9 R0 
      58 [-]: LOADN R10 1  
      59 [-]: FORNPREP R9 L14
L 7:  60 [-]: GETTABLE R12 R0 R11
      61 [-]: NAMECALL R12 R12 K12 [0xD1586535]
      62 [-]: CALL R12 1 1 
      63 [-]: MOVE R7 R12  
      64 [-]: NAMECALL R12 R1 K12 [0xD1586535]
      65 [-]: CALL R12 1 1 
      66 [-]: MOVE R2 R12  
      67 [-]: GETIMPORT R12 23 [nil]
      68 [-]: MOVE R13 R7  
      69 [-]: MOVE R14 R2  
      70 [-]: CALL R12 2 1 
      71 [-]: LOADN R13 100
      72 [-]: JUMPIFNOTLT R13 R12 L13
      73 [-]: JUMPIFNOT R8 L13
      74 [-]: GETIMPORT R12 1 [nil]
      75 [-]: GETIMPORT R14 25 [nil]
      76 [-]: MOVE R15 R7  
      77 [-]: GETTABLE R16 R0 R11
      78 [-]: NAMECALL R16 R16 K26 [0xCB3851B8]
      79 [-]: CALL R16 1 -1
      80 [-]: NAMECALL R12 R12 K27 [0x05909209]
      81 [-]: CALL R12 -1 1
      82 [-]: MOVE R4 R12  
      83 [-]: GETIMPORT R12 1 [nil]
      84 [-]: GETIMPORT R14 29 [nil]
      85 [-]: MOVE R15 R7  
      86 [-]: GETIMPORT R16 31 [nil]
      87 [-]: NAMECALL R12 R12 K27 [0x05909209]
      88 [-]: CALL R12 4 0 
      89 [-]: MOVE R14 R1  
      90 [-]: NAMECALL R12 R4 K32 [0x263A3CC2]
      91 [-]: CALL R12 2 0 
      92 [-]: GETIMPORT R12 34 [nil]
      93 [-]: LOADN R13 1  
      94 [-]: LENGTH R14 R6
      95 [-]: CALL R12 2 1 
      96 [-]: GETTABLE R5 R6 R12
L 8:  97 [-]: FASTCALL1 62 R5 L9
      98 [-]: MOVE R13 R5  
      99 [-]: GETIMPORT R12 15 [nil]
     100 [-]: CALL R12 1 1 
L 9: 101 [-]: JUMPIF R12 L10
     102 [-]: NAMECALL R12 R5 K13 [0xE79E7EF4]
     103 [-]: CALL R12 1 1 
     104 [-]: JUMPIFEQ R12 R3 L11
L10: 105 [-]: GETIMPORT R12 34 [nil]
     106 [-]: LOADN R13 1  
     107 [-]: LENGTH R14 R6
     108 [-]: CALL R12 2 1 
     109 [-]: GETTABLE R5 R6 R12
     110 [-]: GETIMPORT R12 36 [nil]
     111 [-]: LOADN R13 0  
     112 [-]: CALL R12 1 0 
     113 [-]: JUMPBACK L8  
L11: 114 [-]: FASTCALL1 62 R4 L12
     115 [-]: MOVE R13 R4  
     116 [-]: GETIMPORT R12 15 [nil]
     117 [-]: CALL R12 1 1 
L12: 118 [-]: JUMPIF R12 L13
     119 [-]: MOVE R14 R5  
     120 [-]: NAMECALL R12 R4 K37 [0x419785D7]
     121 [-]: CALL R12 2 0 
L13: 122 [-]: GETIMPORT R12 36 [nil]
     123 [-]: LOADN R13 3  
     124 [-]: CALL R12 1 0 
     125 [-]: FORNLOOP R9 L7
L14: 126 [-]: GETIMPORT R9 36 [nil]
     127 [-]: LOADN R10 0  
     128 [-]: CALL R9 1 0  
     129 [-]: NAMECALL R9 R1 K17 [0x5E8B6A40]
     130 [-]: CALL R9 1 1  
     131 [-]: JUMPIFNOT R9 L15
     132 [-]: GETIMPORT R9 36 [nil]
     133 [-]: LOADN R10 5  
     134 [-]: CALL R9 1 0  
     135 [-]: JUMP L16
    
L15: 136 [-]: GETIMPORT R9 36 [nil]
     137 [-]: LOADN R10 10 
     138 [-]: CALL R9 1 0  
L16: 139 [-]: JUMPBACK L1  
L17: 140 [-]: RETURN R0 0  


; Name:            
; Defined at line: 1156
; #Upvalues:       0
; #Parameters:     1
; Is_vararg:       0
; Max Stack Size:  7

       0 [-]: LOADN R3 1   
       1 [-]: LENGTH R1 R0 
       2 [-]: LOADN R2 1   
       3 [-]: FORNPREP R1 L3
L 0:   4 [-]: GETTABLE R5 R0 R3
       5 [-]: FASTCALL1 62 R5 L1
       6 [-]: GETIMPORT R4 1 [nil]
       7 [-]: CALL R4 1 1  
L 1:   8 [-]: JUMPIF R4 L2 
       9 [-]: GETTABLE R4 R0 R3
      10 [-]: LOADK R6 K2 ["Enable"]
      11 [-]: NAMECALL R4 R4 K3 [0x8EB2112D]
      12 [-]: CALL R4 2 0  
L 2:  13 [-]: FORNLOOP R1 L0
L 3:  14 [-]: RETURN R0 0  


; Name:            
; Defined at line: 1164
; #Upvalues:       0
; #Parameters:     1
; Is_vararg:       0
; Max Stack Size:  7

       0 [-]: LOADN R3 1   
       1 [-]: LENGTH R1 R0 
       2 [-]: LOADN R2 1   
       3 [-]: FORNPREP R1 L3
L 0:   4 [-]: GETTABLE R5 R0 R3
       5 [-]: FASTCALL1 62 R5 L1
       6 [-]: GETIMPORT R4 1 [nil]
       7 [-]: CALL R4 1 1  
L 1:   8 [-]: JUMPIF R4 L2 
       9 [-]: GETTABLE R4 R0 R3
      10 [-]: LOADK R6 K2 ["Disable"]
      11 [-]: NAMECALL R4 R4 K3 [0x8EB2112D]
      12 [-]: CALL R4 2 0  
L 2:  13 [-]: FORNLOOP R1 L0
L 3:  14 [-]: RETURN R0 0  


; Name:            
; Defined at line: 1172
; #Upvalues:       4
; #Parameters:     0
; Is_vararg:       0
; Max Stack Size:  8

       0 [-]: GETIMPORT R0 1 [nil]
       1 [-]: GETIMPORT R2 3 [nil]
       2 [-]: GETIMPORT R3 5 [nil]
       3 [-]: CALL R3 0 1  
       4 [-]: LOADK R4 K6 [3.4028234663852886e+38]
       5 [-]: NAMECALL R0 R0 K7 [0x4E5939A5]
       6 [-]: CALL R0 4 1  
L 0:   7 [-]: FASTCALL1 62 R0 L1
       8 [-]: MOVE R2 R0   
       9 [-]: GETIMPORT R1 9 [nil]
      10 [-]: CALL R1 1 1  
L 1:  11 [-]: JUMPIFNOT R1 L2
      12 [-]: GETIMPORT R1 1 [nil]
      13 [-]: GETIMPORT R3 3 [nil]
      14 [-]: GETIMPORT R4 5 [nil]
      15 [-]: CALL R4 0 1  
      16 [-]: LOADK R5 K6 [3.4028234663852886e+38]
      17 [-]: NAMECALL R1 R1 K7 [0x4E5939A5]
      18 [-]: CALL R1 4 1  
      19 [-]: MOVE R0 R1   
      20 [-]: GETIMPORT R1 11 [nil]
      21 [-]: LOADN R2 0   
      22 [-]: CALL R1 1 0  
      23 [-]: JUMPBACK L0  
L 2:  24 [-]: GETIMPORT R1 1 [nil]
      25 [-]: GETIMPORT R3 13 [nil]
      26 [-]: LOADK R4 K14 ["GolemWaypoint"]
      27 [-]: CALL R3 1 -1 
      28 [-]: NAMECALL R1 R1 K15 [0xC7FCADA9]
      29 [-]: CALL R1 -1 1 
      30 [-]: GETIMPORT R2 1 [nil]
      31 [-]: GETIMPORT R4 13 [nil]
      32 [-]: LOADK R5 K16 ["GolemPerch"]
      33 [-]: CALL R4 1 -1 
      34 [-]: NAMECALL R2 R2 K15 [0xC7FCADA9]
      35 [-]: CALL R2 -1 1 
      36 [-]: GETIMPORT R3 18 [nil]
      37 [-]: JUMPIFNOT R3 L3
      38 [-]: GETIMPORT R3 20 [nil]
      39 [-]: LOADK R4 K21 ["     Set Golem to perched"]
      40 [-]: CALL R3 1 0  
      41 [-]: GETUPVAL R3 0
      42 [-]: MOVE R4 R2   
      43 [-]: CALL R3 1 0  
      44 [-]: GETUPVAL R3 1
      45 [-]: MOVE R4 R1   
      46 [-]: CALL R3 1 0  
      47 [-]: GETUPVAL R5 2
      48 [-]: NAMECALL R3 R0 K22 [0xB2532845]
      49 [-]: CALL R3 2 0  
      50 [-]: GETTABLEN R5 R2 1
      51 [-]: NAMECALL R5 R5 K23 [0xD1586535]
      52 [-]: CALL R5 1 1  
      53 [-]: GETTABLEN R6 R2 1
      54 [-]: NAMECALL R6 R6 K24 [0xCB3851B8]
      55 [-]: CALL R6 1 -1 
      56 [-]: NAMECALL R3 R0 K25 [0x589EF1C1]
      57 [-]: CALL R3 -1 0 
      58 [-]: RETURN R0 0  
L 3:  59 [-]: GETIMPORT R3 20 [nil]
      60 [-]: LOADK R4 K26 ["     Set Golem to not perched"]
      61 [-]: CALL R3 1 0  
      62 [-]: GETUPVAL R3 0
      63 [-]: MOVE R4 R1   
      64 [-]: CALL R3 1 0  
      65 [-]: GETUPVAL R3 1
      66 [-]: MOVE R4 R2   
      67 [-]: CALL R3 1 0  
      68 [-]: GETUPVAL R5 3
      69 [-]: NAMECALL R3 R0 K22 [0xB2532845]
      70 [-]: CALL R3 2 0  
      71 [-]: RETURN R0 0  


; Name:            
; Defined at line: 1196
; #Upvalues:       3
; #Parameters:     0
; Is_vararg:       0
; Max Stack Size:  8

       0 [-]: GETIMPORT R0 1 [nil]
       1 [-]: GETIMPORT R2 3 [nil]
       2 [-]: LOADK R3 K4 ["GolemWaypoint"]
       3 [-]: CALL R2 1 -1 
       4 [-]: NAMECALL R0 R0 K5 [0xC7FCADA9]
       5 [-]: CALL R0 -1 1 
       6 [-]: GETIMPORT R1 1 [nil]
       7 [-]: GETIMPORT R3 3 [nil]
       8 [-]: LOADK R4 K6 ["GolemPerch"]
       9 [-]: CALL R3 1 -1 
      10 [-]: NAMECALL R1 R1 K5 [0xC7FCADA9]
      11 [-]: CALL R1 -1 1 
      12 [-]: GETUPVAL R2 0
      13 [-]: MOVE R3 R0   
      14 [-]: CALL R2 1 0  
      15 [-]: GETUPVAL R2 1
      16 [-]: MOVE R3 R1   
      17 [-]: CALL R2 1 0  
      18 [-]: GETIMPORT R2 1 [nil]
      19 [-]: GETIMPORT R4 8 [nil]
      20 [-]: GETIMPORT R5 10 [nil]
      21 [-]: CALL R5 0 1  
      22 [-]: LOADK R6 K11 [3.4028234663852886e+38]
      23 [-]: NAMECALL R2 R2 K12 [0x4E5939A5]
      24 [-]: CALL R2 4 1  
L 0:  25 [-]: FASTCALL1 62 R2 L1
      26 [-]: MOVE R4 R2   
      27 [-]: GETIMPORT R3 14 [nil]
      28 [-]: CALL R3 1 1  
L 1:  29 [-]: JUMPIFNOT R3 L2
      30 [-]: GETIMPORT R3 1 [nil]
      31 [-]: GETIMPORT R5 8 [nil]
      32 [-]: GETIMPORT R6 10 [nil]
      33 [-]: CALL R6 0 1  
      34 [-]: LOADK R7 K11 [3.4028234663852886e+38]
      35 [-]: NAMECALL R3 R3 K12 [0x4E5939A5]
      36 [-]: CALL R3 4 1  
      37 [-]: MOVE R2 R3   
      38 [-]: GETIMPORT R3 16 [nil]
      39 [-]: LOADN R4 0   
      40 [-]: CALL R3 1 0  
      41 [-]: JUMPBACK L0  
L 2:  42 [-]: LOADN R3 1   
L 3:  43 [-]: FASTCALL1 62 R2 L4
      44 [-]: MOVE R5 R2   
      45 [-]: GETIMPORT R4 14 [nil]
      46 [-]: CALL R4 1 1  
L 4:  47 [-]: JUMPIF R4 L7 
      48 [-]: NAMECALL R4 R2 K17 [0x2047CFE7]
      49 [-]: CALL R4 1 1  
      50 [-]: JUMPIF R4 L7 
      51 [-]: GETUPVAL R4 0
      52 [-]: MOVE R5 R0   
      53 [-]: CALL R4 1 0  
      54 [-]: GETUPVAL R4 1
      55 [-]: MOVE R5 R1   
      56 [-]: CALL R4 1 0  
      57 [-]: GETUPVAL R6 2
      58 [-]: NAMECALL R4 R2 K18 [0xB2532845]
      59 [-]: CALL R4 2 0  
      60 [-]: GETIMPORT R4 16 [nil]
      61 [-]: LOADN R5 15  
      62 [-]: CALL R4 1 0  
      63 [-]: GETUPVAL R4 1
      64 [-]: MOVE R5 R0   
      65 [-]: CALL R4 1 0  
      66 [-]: GETIMPORT R4 20 [nil]
      67 [-]: JUMPIFNOT R4 L5
      68 [-]: GETIMPORT R4 22 [nil]
      69 [-]: LOADK R6 K23 ["Enable"]
      70 [-]: NAMECALL R4 R4 K24 [0x8EB2112D]
      71 [-]: CALL R4 2 0  
      72 [-]: JUMP L6
     
L 5:  73 [-]: GETTABLE R4 R1 R3
      74 [-]: LOADK R6 K23 ["Enable"]
      75 [-]: NAMECALL R4 R4 K24 [0x8EB2112D]
      76 [-]: CALL R4 2 0  
      77 [-]: ADDK R3 R3 K25 [1]
      78 [-]: LENGTH R4 R1 
      79 [-]: JUMPIFNOTLT R4 R3 L6
      80 [-]: LOADN R3 1   
L 6:  81 [-]: GETIMPORT R4 16 [nil]
      82 [-]: LOADN R5 30  
      83 [-]: CALL R4 1 0  
      84 [-]: JUMPBACK L3  
L 7:  85 [-]: RETURN R0 0  


; Name:            
; Defined at line: 1231
; #Upvalues:       0
; #Parameters:     0
; Is_vararg:       0
; Max Stack Size:  6

       0 [-]: NEWTABLE R0 0 0
       1 [-]: GETIMPORT R1 1 [nil]
       2 [-]: GETIMPORT R3 3 [nil]
       3 [-]: LOADK R4 K4 ["WeakpointOne"]
       4 [-]: CALL R3 1 -1 
       5 [-]: NAMECALL R1 R1 K5 [0xC7FCADA9]
       6 [-]: CALL R1 -1 1 
       7 [-]: FASTCALL2 52 R0 R1 L0
       8 [-]: MOVE R3 R0   
       9 [-]: MOVE R4 R1   
      10 [-]: GETIMPORT R2 8 [nil]
      11 [-]: CALL R2 2 0  
L 0:  12 [-]: GETIMPORT R2 1 [nil]
      13 [-]: GETIMPORT R4 3 [nil]
      14 [-]: LOADK R5 K9 ["WeakpointTwo"]
      15 [-]: CALL R4 1 -1 
      16 [-]: NAMECALL R2 R2 K5 [0xC7FCADA9]
      17 [-]: CALL R2 -1 1 
      18 [-]: MOVE R1 R2   
      19 [-]: FASTCALL2 52 R0 R1 L1
      20 [-]: MOVE R3 R0   
      21 [-]: MOVE R4 R1   
      22 [-]: GETIMPORT R2 8 [nil]
      23 [-]: CALL R2 2 0  
L 1:  24 [-]: GETIMPORT R2 1 [nil]
      25 [-]: GETIMPORT R4 3 [nil]
      26 [-]: LOADK R5 K10 ["WeakpointThree"]
      27 [-]: CALL R4 1 -1 
      28 [-]: NAMECALL R2 R2 K5 [0xC7FCADA9]
      29 [-]: CALL R2 -1 1 
      30 [-]: MOVE R1 R2   
      31 [-]: FASTCALL2 52 R0 R1 L2
      32 [-]: MOVE R3 R0   
      33 [-]: MOVE R4 R1   
      34 [-]: GETIMPORT R2 8 [nil]
      35 [-]: CALL R2 2 0  
L 2:  36 [-]: FASTCALL1 62 R0 L3
      37 [-]: MOVE R3 R0   
      38 [-]: GETIMPORT R2 12 [nil]
      39 [-]: CALL R2 1 1  
L 3:  40 [-]: JUMPIF R2 L4 
      41 [-]: GETTABLEN R2 R0 1
      42 [-]: NAMECALL R2 R2 K13 [0xA2880940]
      43 [-]: CALL R2 1 0  
L 4:  44 [-]: RETURN R0 0  


; Name:            
; Defined at line: 1247
; #Upvalues:       0
; #Parameters:     1
; Is_vararg:       0
; Max Stack Size:  6

       0 [-]: GETIMPORT R1 1 [nil]
       1 [-]: JUMPXEQKN R1 K2 L7 NOT [1]
       2 [-]: GETIMPORT R2 5 [nil]
       3 [-]: FASTCALL1 62 R2 L0
       4 [-]: GETIMPORT R1 7 [nil]
       5 [-]: CALL R1 1 1  
L 0:   6 [-]: JUMPIFNOT R1 L2
       7 [-]: GETIMPORT R1 8 [nil]
       8 [-]: NEWTABLE R2 0 0
       9 [-]: SETTABLEKS R2 R1 K4 ["NerveOneCalloutReceived"]
      10 [-]: GETIMPORT R2 5 [nil]
      11 [-]: FASTCALL2 52 R2 R0 L1
      12 [-]: MOVE R3 R0   
      13 [-]: GETIMPORT R1 11 [nil]
      14 [-]: CALL R1 2 0  
L 1:  15 [-]: GETIMPORT R3 13 [nil]
      16 [-]: NAMECALL R1 R0 K14 [0x2A748F85]
      17 [-]: CALL R1 2 0  
      18 [-]: RETURN R0 0  
L 2:  19 [-]: LOADN R3 1   
      20 [-]: GETIMPORT R4 5 [nil]
      21 [-]: LENGTH R1 R4 
      22 [-]: LOADN R2 1   
      23 [-]: FORNPREP R1 L5
L 3:  24 [-]: GETIMPORT R5 5 [nil]
      25 [-]: GETTABLE R4 R5 R3
      26 [-]: JUMPIFNOTEQ R0 R4 L4
      27 [-]: RETURN R0 0  
L 4:  28 [-]: FORNLOOP R1 L3
L 5:  29 [-]: GETIMPORT R2 5 [nil]
      30 [-]: FASTCALL2 52 R2 R0 L6
      31 [-]: MOVE R3 R0   
      32 [-]: GETIMPORT R1 11 [nil]
      33 [-]: CALL R1 2 0  
L 6:  34 [-]: GETIMPORT R3 13 [nil]
      35 [-]: NAMECALL R1 R0 K14 [0x2A748F85]
      36 [-]: CALL R1 2 0  
      37 [-]: RETURN R0 0  
L 7:  38 [-]: GETIMPORT R1 1 [nil]
      39 [-]: JUMPXEQKN R1 K15 L15 NOT [2]
      40 [-]: GETIMPORT R2 17 [nil]
      41 [-]: FASTCALL1 62 R2 L8
      42 [-]: GETIMPORT R1 7 [nil]
      43 [-]: CALL R1 1 1  
L 8:  44 [-]: JUMPIFNOT R1 L10
      45 [-]: GETIMPORT R1 8 [nil]
      46 [-]: NEWTABLE R2 0 0
      47 [-]: SETTABLEKS R2 R1 K16 ["NerveTwoCalloutReceived"]
      48 [-]: GETIMPORT R2 17 [nil]
      49 [-]: FASTCALL2 52 R2 R0 L9
      50 [-]: MOVE R3 R0   
      51 [-]: GETIMPORT R1 11 [nil]
      52 [-]: CALL R1 2 0  
L 9:  53 [-]: GETIMPORT R3 13 [nil]
      54 [-]: NAMECALL R1 R0 K14 [0x2A748F85]
      55 [-]: CALL R1 2 0  
      56 [-]: RETURN R0 0  
L10:  57 [-]: LOADN R3 1   
      58 [-]: GETIMPORT R4 17 [nil]
      59 [-]: LENGTH R1 R4 
      60 [-]: LOADN R2 1   
      61 [-]: FORNPREP R1 L13
L11:  62 [-]: GETIMPORT R5 17 [nil]
      63 [-]: GETTABLE R4 R5 R3
      64 [-]: JUMPIFNOTEQ R0 R4 L12
      65 [-]: RETURN R0 0  
L12:  66 [-]: FORNLOOP R1 L11
L13:  67 [-]: GETIMPORT R2 17 [nil]
      68 [-]: FASTCALL2 52 R2 R0 L14
      69 [-]: MOVE R3 R0   
      70 [-]: GETIMPORT R1 11 [nil]
      71 [-]: CALL R1 2 0  
L14:  72 [-]: GETIMPORT R3 13 [nil]
      73 [-]: NAMECALL R1 R0 K14 [0x2A748F85]
      74 [-]: CALL R1 2 0  
      75 [-]: RETURN R0 0  
L15:  76 [-]: GETIMPORT R1 1 [nil]
      77 [-]: JUMPXEQKN R1 K18 L23 NOT [3]
      78 [-]: GETIMPORT R2 20 [nil]
      79 [-]: FASTCALL1 62 R2 L16
      80 [-]: GETIMPORT R1 7 [nil]
      81 [-]: CALL R1 1 1  
L16:  82 [-]: JUMPIFNOT R1 L18
      83 [-]: GETIMPORT R1 8 [nil]
      84 [-]: NEWTABLE R2 0 0
      85 [-]: SETTABLEKS R2 R1 K19 ["NerveThreeCalloutReceived"]
      86 [-]: GETIMPORT R2 20 [nil]
      87 [-]: FASTCALL2 52 R2 R0 L17
      88 [-]: MOVE R3 R0   
      89 [-]: GETIMPORT R1 11 [nil]
      90 [-]: CALL R1 2 0  
L17:  91 [-]: GETIMPORT R3 13 [nil]
      92 [-]: NAMECALL R1 R0 K14 [0x2A748F85]
      93 [-]: CALL R1 2 0  
      94 [-]: RETURN R0 0  
L18:  95 [-]: LOADN R3 1   
      96 [-]: GETIMPORT R4 20 [nil]
      97 [-]: LENGTH R1 R4 
      98 [-]: LOADN R2 1   
      99 [-]: FORNPREP R1 L21
L19: 100 [-]: GETIMPORT R5 20 [nil]
     101 [-]: GETTABLE R4 R5 R3
     102 [-]: JUMPIFNOTEQ R0 R4 L20
     103 [-]: RETURN R0 0  
L20: 104 [-]: FORNLOOP R1 L19
L21: 105 [-]: GETIMPORT R2 20 [nil]
     106 [-]: FASTCALL2 52 R2 R0 L22
     107 [-]: MOVE R3 R0   
     108 [-]: GETIMPORT R1 11 [nil]
     109 [-]: CALL R1 2 0  
L22: 110 [-]: GETIMPORT R3 13 [nil]
     111 [-]: NAMECALL R1 R0 K14 [0x2A748F85]
     112 [-]: CALL R1 2 0  
L23: 113 [-]: RETURN R0 0  


; Name:            
; Defined at line: 1296
; #Upvalues:       1
; #Parameters:     0
; Is_vararg:       0
; Max Stack Size:  6

       0 [-]: GETIMPORT R0 1 [nil]
       1 [-]: GETIMPORT R2 3 [nil]
       2 [-]: GETIMPORT R3 5 [nil]
       3 [-]: CALL R3 0 1  
       4 [-]: LOADK R4 K6 [3.4028234663852886e+38]
       5 [-]: NAMECALL R0 R0 K7 [0x4E5939A5]
       6 [-]: CALL R0 4 1  
L 0:   7 [-]: FASTCALL1 62 R0 L1
       8 [-]: MOVE R2 R0   
       9 [-]: GETIMPORT R1 9 [nil]
      10 [-]: CALL R1 1 1  
L 1:  11 [-]: JUMPIFNOT R1 L2
      12 [-]: GETIMPORT R1 1 [nil]
      13 [-]: GETIMPORT R3 3 [nil]
      14 [-]: GETIMPORT R4 5 [nil]
      15 [-]: CALL R4 0 1  
      16 [-]: LOADK R5 K6 [3.4028234663852886e+38]
      17 [-]: NAMECALL R1 R1 K7 [0x4E5939A5]
      18 [-]: CALL R1 4 1  
      19 [-]: MOVE R0 R1   
      20 [-]: GETIMPORT R1 11 [nil]
      21 [-]: LOADN R2 1   
      22 [-]: CALL R1 1 0  
      23 [-]: JUMPBACK L0  
L 2:  24 [-]: GETUPVAL R1 0
      25 [-]: LOADK R3 K12 ["Golem Encountered"]
      26 [-]: NAMECALL R1 R1 K13 [0xABBFDA4A]
      27 [-]: CALL R1 2 0  
L 3:  28 [-]: GETIMPORT R1 16 [nil]
      29 [-]: JUMPXEQKN R1 K17 L4 NOT [1]
      30 [-]: GETIMPORT R1 11 [nil]
      31 [-]: LOADN R2 1   
      32 [-]: CALL R1 1 0  
      33 [-]: JUMPBACK L3  
L 4:  34 [-]: GETUPVAL R1 0
      35 [-]: LOADK R3 K18 ["First Golem Nerve Destroyed"]
      36 [-]: NAMECALL R1 R1 K13 [0xABBFDA4A]
      37 [-]: CALL R1 2 0  
L 5:  38 [-]: GETIMPORT R1 16 [nil]
      39 [-]: JUMPXEQKN R1 K19 L6 NOT [2]
      40 [-]: GETIMPORT R1 11 [nil]
      41 [-]: LOADN R2 1   
      42 [-]: CALL R1 1 0  
      43 [-]: JUMPBACK L5  
L 6:  44 [-]: GETUPVAL R1 0
      45 [-]: LOADK R3 K20 ["Golem damaged to 66%"]
      46 [-]: NAMECALL R1 R1 K13 [0xABBFDA4A]
      47 [-]: CALL R1 2 0  
L 7:  48 [-]: GETIMPORT R1 16 [nil]
      49 [-]: JUMPXEQKN R1 K21 L8 NOT [3]
      50 [-]: GETIMPORT R1 11 [nil]
      51 [-]: LOADN R2 1   
      52 [-]: CALL R1 1 0  
      53 [-]: JUMPBACK L7  
L 8:  54 [-]: GETUPVAL R1 0
      55 [-]: LOADK R3 K22 ["Second Golem Nerve Destroyed"]
      56 [-]: NAMECALL R1 R1 K13 [0xABBFDA4A]
      57 [-]: CALL R1 2 0  
L 9:  58 [-]: GETIMPORT R1 16 [nil]
      59 [-]: JUMPXEQKN R1 K23 L10 NOT [4]
      60 [-]: GETIMPORT R1 11 [nil]
      61 [-]: LOADN R2 1   
      62 [-]: CALL R1 1 0  
      63 [-]: JUMPBACK L9  
L10:  64 [-]: GETUPVAL R1 0
      65 [-]: LOADK R3 K24 ["Golem damaged to 33%"]
      66 [-]: NAMECALL R1 R1 K13 [0xABBFDA4A]
      67 [-]: CALL R1 2 0  
L11:  68 [-]: GETIMPORT R1 16 [nil]
      69 [-]: JUMPXEQKN R1 K25 L12 NOT [5]
      70 [-]: GETIMPORT R1 11 [nil]
      71 [-]: LOADN R2 1   
      72 [-]: CALL R1 1 0  
      73 [-]: JUMPBACK L11 
L12:  74 [-]: GETUPVAL R1 0
      75 [-]: LOADK R3 K26 ["Third Golem Nerve Destroyed"]
      76 [-]: NAMECALL R1 R1 K13 [0xABBFDA4A]
      77 [-]: CALL R1 2 0  
L13:  78 [-]: FASTCALL1 62 R0 L14
      79 [-]: MOVE R2 R0   
      80 [-]: GETIMPORT R1 9 [nil]
      81 [-]: CALL R1 1 1  
L14:  82 [-]: JUMPIF R1 L15
      83 [-]: NAMECALL R1 R0 K27 [0x2047CFE7]
      84 [-]: CALL R1 1 1  
      85 [-]: JUMPIF R1 L15
      86 [-]: GETIMPORT R1 11 [nil]
      87 [-]: LOADN R2 1   
      88 [-]: CALL R1 1 0  
      89 [-]: JUMPBACK L13 
L15:  90 [-]: GETUPVAL R1 0
      91 [-]: LOADK R3 K28 ["Golem defeated!"]
      92 [-]: NAMECALL R1 R1 K13 [0xABBFDA4A]
      93 [-]: CALL R1 2 0  
      94 [-]: RETURN R0 0  


; Name:            
; Defined at line: 1337
; #Upvalues:       0
; #Parameters:     0
; Is_vararg:       0
; Max Stack Size:  6

       0 [-]: GETIMPORT R0 1 [nil]
       1 [-]: LOADB R1 0   
       2 [-]: SETTABLEKS R1 R0 K2 ["WeakpointEnabled"]
       3 [-]: GETIMPORT R1 4 [nil]
       4 [-]: FASTCALL1 62 R1 L0
       5 [-]: GETIMPORT R0 6 [nil]
       6 [-]: CALL R0 1 1  
L 0:   7 [-]: JUMPIFNOT R0 L1
       8 [-]: RETURN R0 0  
L 1:   9 [-]: GETIMPORT R0 4 [nil]
      10 [-]: GETIMPORT R2 8 [nil]
      11 [-]: NAMECALL R0 R0 K9 [0xC9F6A7D7]
      12 [-]: CALL R0 2 1  
L 2:  13 [-]: FASTCALL1 62 R0 L3
      14 [-]: MOVE R2 R0   
      15 [-]: GETIMPORT R1 6 [nil]
      16 [-]: CALL R1 1 1  
L 3:  17 [-]: JUMPIFNOT R1 L4
      18 [-]: GETIMPORT R1 11 [nil]
      19 [-]: LOADN R2 0   
      20 [-]: CALL R1 1 0  
      21 [-]: GETIMPORT R1 4 [nil]
      22 [-]: GETIMPORT R3 8 [nil]
      23 [-]: NAMECALL R1 R1 K9 [0xC9F6A7D7]
      24 [-]: CALL R1 2 1  
      25 [-]: MOVE R0 R1   
      26 [-]: JUMPBACK L2  
L 4:  27 [-]: GETIMPORT R1 13 [nil]
      28 [-]: GETIMPORT R3 15 [nil]
      29 [-]: LOADK R4 K16 ["PurifierTrig"]
      30 [-]: CALL R3 1 1  
      31 [-]: GETIMPORT R4 4 [nil]
      32 [-]: NAMECALL R4 R4 K17 [0xD1586535]
      33 [-]: CALL R4 1 -1 
      34 [-]: NAMECALL R1 R1 K18 [0xC7B81E8D]
      35 [-]: CALL R1 -1 1 
      36 [-]: GETIMPORT R4 4 [nil]
      37 [-]: NAMECALL R2 R1 K19 [0xBEBAD19F]
      38 [-]: CALL R2 2 1  
L 5:  39 [-]: GETIMPORT R4 4 [nil]
      40 [-]: FASTCALL1 62 R4 L6
      41 [-]: GETIMPORT R3 6 [nil]
      42 [-]: CALL R3 1 1  
L 6:  43 [-]: JUMPIF R3 L12
      44 [-]: FASTCALL1 62 R0 L7
      45 [-]: MOVE R4 R0   
      46 [-]: GETIMPORT R3 6 [nil]
      47 [-]: CALL R3 1 1  
L 7:  48 [-]: JUMPIFNOT R3 L8
      49 [-]: RETURN R0 0  
L 8:  50 [-]: FASTCALL1 62 R1 L9
      51 [-]: MOVE R4 R1   
      52 [-]: GETIMPORT R3 6 [nil]
      53 [-]: CALL R3 1 1  
L 9:  54 [-]: JUMPIF R3 L11
      55 [-]: GETIMPORT R3 20 [nil]
      56 [-]: JUMPIF R3 L10
      57 [-]: NAMECALL R3 R1 K21 [0xDE89CF48]
      58 [-]: CALL R3 1 1  
      59 [-]: JUMPIFNOTLT R2 R3 L10
      60 [-]: NAMECALL R3 R0 K22 [0xF4E253B6]
      61 [-]: CALL R3 1 0  
      62 [-]: GETIMPORT R3 4 [nil]
      63 [-]: NAMECALL R3 R3 K23 [0xE92524C3]
      64 [-]: CALL R3 1 0  
      65 [-]: JUMP L11
    
L10:  66 [-]: GETIMPORT R3 20 [nil]
      67 [-]: JUMPIFNOT R3 L11
      68 [-]: NAMECALL R3 R1 K21 [0xDE89CF48]
      69 [-]: CALL R3 1 1  
      70 [-]: JUMPIFNOTLT R2 R3 L11
      71 [-]: NAMECALL R3 R0 K24 [0x383D2E7D]
      72 [-]: CALL R3 1 0  
      73 [-]: GETIMPORT R3 4 [nil]
      74 [-]: NAMECALL R3 R3 K25 [0x04347778]
      75 [-]: CALL R3 1 0  
L11:  76 [-]: GETIMPORT R3 11 [nil]
      77 [-]: LOADN R4 0   
      78 [-]: CALL R3 1 0  
      79 [-]: JUMPBACK L5  
L12:  80 [-]: RETURN R0 0  


; Name:            
; Defined at line: 1373
; #Upvalues:       0
; #Parameters:     0
; Is_vararg:       0
; Max Stack Size:  2

       0 [-]: GETIMPORT R0 1 [nil]
       1 [-]: JUMPIFNOT R0 L0
       2 [-]: GETIMPORT R0 3 [nil]
       3 [-]: LOADB R1 1   
       4 [-]: SETTABLEKS R1 R0 K4 ["WeakpointEnabled"]
       5 [-]: RETURN R0 0  
L 0:   6 [-]: GETIMPORT R0 3 [nil]
       7 [-]: LOADB R1 0   
       8 [-]: SETTABLEKS R1 R0 K4 ["WeakpointEnabled"]
       9 [-]: RETURN R0 0  


; Name:            
; Defined at line: 1381
; #Upvalues:       0
; #Parameters:     0
; Is_vararg:       0
; Max Stack Size:  4

       0 [-]: GETIMPORT R0 1 [nil]
       1 [-]: LOADB R1 0   
       2 [-]: SETTABLEKS R1 R0 K2 ["DevourerEnabled"]
       3 [-]: GETIMPORT R1 4 [nil]
       4 [-]: FASTCALL1 62 R1 L0
       5 [-]: GETIMPORT R0 6 [nil]
       6 [-]: CALL R0 1 1  
L 0:   7 [-]: JUMPIFNOT R0 L1
       8 [-]: RETURN R0 0  
L 1:   9 [-]: GETIMPORT R0 4 [nil]
      10 [-]: GETIMPORT R2 8 [nil]
      11 [-]: NAMECALL R0 R0 K9 [0xC9F6A7D7]
      12 [-]: CALL R0 2 1  
L 2:  13 [-]: FASTCALL1 62 R0 L3
      14 [-]: MOVE R2 R0   
      15 [-]: GETIMPORT R1 6 [nil]
      16 [-]: CALL R1 1 1  
L 3:  17 [-]: JUMPIFNOT R1 L4
      18 [-]: GETIMPORT R1 11 [nil]
      19 [-]: LOADN R2 0   
      20 [-]: CALL R1 1 0  
      21 [-]: GETIMPORT R1 4 [nil]
      22 [-]: GETIMPORT R3 8 [nil]
      23 [-]: NAMECALL R1 R1 K9 [0xC9F6A7D7]
      24 [-]: CALL R1 2 1  
      25 [-]: MOVE R0 R1   
      26 [-]: JUMPBACK L2  
L 4:  27 [-]: FASTCALL1 62 R0 L5
      28 [-]: MOVE R2 R0   
      29 [-]: GETIMPORT R1 6 [nil]
      30 [-]: CALL R1 1 1  
L 5:  31 [-]: JUMPIF R1 L7 
      32 [-]: GETIMPORT R2 4 [nil]
      33 [-]: FASTCALL1 62 R2 L6
      34 [-]: GETIMPORT R1 6 [nil]
      35 [-]: CALL R1 1 1  
L 6:  36 [-]: JUMPIFNOT R1 L8
L 7:  37 [-]: RETURN R0 0  
L 8:  38 [-]: GETIMPORT R1 12 [nil]
      39 [-]: JUMPIF R1 L9 
      40 [-]: GETIMPORT R1 4 [nil]
      41 [-]: LOADB R3 0   
      42 [-]: NAMECALL R1 R1 K13 [0x7668FD38]
      43 [-]: CALL R1 2 0  
      44 [-]: NAMECALL R1 R0 K14 [0xF4E253B6]
      45 [-]: CALL R1 1 0  
      46 [-]: JUMP L10
    
L 9:  47 [-]: GETIMPORT R1 4 [nil]
      48 [-]: LOADB R3 1   
      49 [-]: NAMECALL R1 R1 K13 [0x7668FD38]
      50 [-]: CALL R1 2 0  
      51 [-]: NAMECALL R1 R0 K15 [0x383D2E7D]
      52 [-]: CALL R1 1 0  
L10:  53 [-]: GETIMPORT R1 11 [nil]
      54 [-]: LOADN R2 0   
      55 [-]: CALL R1 1 0  
      56 [-]: JUMPBACK L4  
      57 [-]: RETURN R0 0  


; Name:            
; Defined at line: 1411
; #Upvalues:       0
; #Parameters:     0
; Is_vararg:       0
; Max Stack Size:  2

       0 [-]: GETIMPORT R0 1 [nil]
       1 [-]: JUMPIFNOT R0 L0
       2 [-]: GETIMPORT R0 3 [nil]
       3 [-]: LOADB R1 1   
       4 [-]: SETTABLEKS R1 R0 K4 ["DevourerEnabled"]
       5 [-]: RETURN R0 0  
L 0:   6 [-]: GETIMPORT R0 3 [nil]
       7 [-]: LOADB R1 0   
       8 [-]: SETTABLEKS R1 R0 K4 ["DevourerEnabled"]
       9 [-]: RETURN R0 0  


; Name:            
; Defined at line: 1419
; #Upvalues:       0
; #Parameters:     0
; Is_vararg:       0
; Max Stack Size:  4

       0 [-]: GETIMPORT R1 1 [nil]
       1 [-]: FASTCALL1 62 R1 L0
       2 [-]: GETIMPORT R0 3 [nil]
       3 [-]: CALL R0 1 1  
L 0:   4 [-]: JUMPIFNOT R0 L1
       5 [-]: RETURN R0 0  
L 1:   6 [-]: GETIMPORT R0 1 [nil]
       7 [-]: GETIMPORT R2 5 [nil]
       8 [-]: NAMECALL R0 R0 K6 [0xC9F6A7D7]
       9 [-]: CALL R0 2 1  
L 2:  10 [-]: FASTCALL1 62 R0 L3
      11 [-]: MOVE R2 R0   
      12 [-]: GETIMPORT R1 3 [nil]
      13 [-]: CALL R1 1 1  
L 3:  14 [-]: JUMPIFNOT R1 L4
      15 [-]: GETIMPORT R1 8 [nil]
      16 [-]: LOADN R2 0   
      17 [-]: CALL R1 1 0  
      18 [-]: GETIMPORT R1 1 [nil]
      19 [-]: GETIMPORT R3 5 [nil]
      20 [-]: NAMECALL R1 R1 K6 [0xC9F6A7D7]
      21 [-]: CALL R1 2 1  
      22 [-]: MOVE R0 R1   
      23 [-]: JUMPBACK L2  
L 4:  24 [-]: GETIMPORT R1 10 [nil]
      25 [-]: JUMPIFNOT R1 L5
      26 [-]: GETIMPORT R1 1 [nil]
      27 [-]: LOADB R3 1   
      28 [-]: NAMECALL R1 R1 K11 [0x7668FD38]
      29 [-]: CALL R1 2 0  
      30 [-]: NAMECALL R1 R0 K12 [0x383D2E7D]
      31 [-]: CALL R1 1 0  
      32 [-]: RETURN R0 0  
L 5:  33 [-]: GETIMPORT R1 1 [nil]
      34 [-]: LOADB R3 0   
      35 [-]: NAMECALL R1 R1 K11 [0x7668FD38]
      36 [-]: CALL R1 2 0  
      37 [-]: NAMECALL R1 R0 K13 [0xF4E253B6]
      38 [-]: CALL R1 1 0  
      39 [-]: RETURN R0 0  


; Name:            
; Defined at line: 1441
; #Upvalues:       0
; #Parameters:     1
; Is_vararg:       0
; Max Stack Size:  9

       0 [-]: GETIMPORT R1 1 [nil]
       1 [-]: GETIMPORT R3 3 [nil]
       2 [-]: NAMECALL R4 R0 K4 [0xD1586535]
       3 [-]: CALL R4 1 1  
       4 [-]: LOADN R5 0   
       5 [-]: LOADN R6 5   
       6 [-]: NAMECALL R1 R1 K5 [0xFB669000]
       7 [-]: CALL R1 5 1  
       8 [-]: LOADNIL R2   
       9 [-]: FASTCALL1 62 R1 L0
      10 [-]: MOVE R4 R1   
      11 [-]: GETIMPORT R3 7 [nil]
      12 [-]: CALL R3 1 1  
L 0:  13 [-]: JUMPIF R3 L4 
      14 [-]: LOADN R5 1   
      15 [-]: LENGTH R3 R1 
      16 [-]: LOADN R4 1   
      17 [-]: FORNPREP R3 L4
L 1:  18 [-]: GETTABLE R6 R1 R5
      19 [-]: NAMECALL R6 R6 K8 [0x5E651723]
      20 [-]: CALL R6 1 1  
      21 [-]: MOVE R2 R6   
      22 [-]: NAMECALL R7 R2 K9 [0x1770A2A6]
      23 [-]: CALL R7 1 1  
      24 [-]: FASTCALL1 62 R7 L2
      25 [-]: GETIMPORT R6 7 [nil]
      26 [-]: CALL R6 1 1  
L 2:  27 [-]: JUMPIF R6 L3 
      28 [-]: LOADNIL R8   
      29 [-]: NAMECALL R6 R2 K10 [0x3D89C6AA]
      30 [-]: CALL R6 2 0  
L 3:  31 [-]: FORNLOOP R3 L1
L 4:  32 [-]: RETURN R0 0  


; Name:            
; Defined at line: 1455
; #Upvalues:       0
; #Parameters:     1
; Is_vararg:       0
; Max Stack Size:  4

       0 [-]: GETIMPORT R1 1 [nil]
       1 [-]: MOVE R2 R0   
       2 [-]: LOADK R3 K2 ["OnSpawned"]
       3 [-]: CALL R1 2 0  
L 0:   4 [-]: GETIMPORT R1 4 [nil]
       5 [-]: LOADN R2 0   
       6 [-]: CALL R1 1 0  
       7 [-]: JUMPBACK L0  
       8 [-]: RETURN R0 0  



