; This file has been disassembled using luadec 2.0.2 by sztupy (modified by Reversive)

; Name:            
; Defined at line: 0
; #Upvalues:       0
; #Parameters:     0
; Is_vararg:       2
; Max Stack Size:  46

  1 [-]: GETGLOBAL R0 K0        ; R0 := 0x2d0fad09
  2 [-]: LOADK     R1 K1        ; R1 := "Lotus.Scripts.Libs.PlayerSkillsLib"
  3 [-]: CALL      R0 2 2       ; R0 := R0(R1)
  4 [-]: GETGLOBAL R1 K0        ; R1 := 0x2d0fad09
  5 [-]: LOADK     R2 K2        ; R2 := "Lotus.Scripts.Libs.RailjackUtilities"
  6 [-]: CALL      R1 2 2       ; R1 := R1(R2)
  7 [-]: LOADNIL   R2 R3        ; R2 := R3 := nil
  8 [-]: LOADBOOL  R4 0 0       ; R4 := false
  9 [-]: LOADNIL   R5 R7        ; R5 := R6 := R7 := nil
 10 [-]: LOADK     R8 K3        ; R8 := 0.010000
 11 [-]: LOADK     R9 K4        ; R9 := 0.040000
 12 [-]: LOADK     R10 0        ; R10 := 0.000000
 13 [-]: LOADBOOL  R11 0 0      ; R11 := false
 14 [-]: LOADBOOL  R12 0 0      ; R12 := false
 15 [-]: LOADBOOL  R13 0 0      ; R13 := false
 16 [-]: LOADBOOL  R14 0 0      ; R14 := false
 17 [-]: LOADBOOL  R15 0 0      ; R15 := false
 18 [-]: LOADNIL   R16 R18      ; R16 := R17 := R18 := nil
 19 [-]: GETGLOBAL R19 K5       ; R19 := 0x0469f296
 20 [-]: LOADK     R20 K6       ; R20 := "/Lotus/Language/Railjack/TacCallRepair"
 21 [-]: CALL      R19 2 2      ; R19 := R19(R20)
 22 [-]: GETGLOBAL R20 K5       ; R20 := 0x0469f296
 23 [-]: LOADK     R21 K7       ; R21 := "EmissiveMapAtten"
 24 [-]: CALL      R20 2 2      ; R20 := R20(R21)
 25 [-]: GETGLOBAL R21 K5       ; R21 := 0x0469f296
 26 [-]: LOADK     R22 K8       ; R22 := "EmissiveTintColor"
 27 [-]: CALL      R21 2 2      ; R21 := R21(R22)
 28 [-]: LOADNIL   R22 R23      ; R22 := R23 := nil
 29 [-]: LOADK     R24 0        ; R24 := 0.500000
 30 [-]: LOADK     R25 1        ; R25 := 1.000000
 31 [-]: CLOSURE   R26 0        ; R26 := closure(Function #1)
 32 [-]: CLOSURE   R27 1        ; R27 := closure(Function #2)
 33 [-]: MOVE      R0 R3        ; R0 := R3
 34 [-]: MOVE      R0 R5        ; R0 := R5
 35 [-]: CLOSURE   R28 2        ; R28 := closure(Function #3)
 36 [-]: CLOSURE   R29 3        ; R29 := closure(Function #4)
 37 [-]: CLOSURE   R30 4        ; R30 := closure(Function #5)
 38 [-]: CLOSURE   R31 5        ; R31 := closure(Function #6)
 39 [-]: MOVE      R0 R30       ; R0 := R30
 40 [-]: CLOSURE   R32 6        ; R32 := closure(Function #7)
 41 [-]: MOVE      R0 R4        ; R0 := R4
 42 [-]: CLOSURE   R33 7        ; R33 := closure(Function #8)
 43 [-]: MOVE      R0 R32       ; R0 := R32
 44 [-]: CLOSURE   R34 8        ; R34 := closure(Function #9)
 45 [-]: MOVE      R0 R33       ; R0 := R33
 46 [-]: MOVE      R0 R28       ; R0 := R28
 47 [-]: CLOSURE   R35 9        ; R35 := closure(Function #10)
 48 [-]: MOVE      R0 R26       ; R0 := R26
 49 [-]: CLOSURE   R36 10       ; R36 := closure(Function #11)
 50 [-]: CLOSURE   R37 11       ; R37 := closure(Function #12)
 51 [-]: CLOSURE   R38 12       ; R38 := closure(Function #13)
 52 [-]: MOVE      R0 R4        ; R0 := R4
 53 [-]: MOVE      R0 R37       ; R0 := R37
 54 [-]: MOVE      R0 R16       ; R0 := R16
 55 [-]: CLOSURE   R39 13       ; R39 := closure(Function #14)
 56 [-]: MOVE      R0 R36       ; R0 := R36
 57 [-]: MOVE      R0 R38       ; R0 := R38
 58 [-]: CLOSURE   R40 14       ; R40 := closure(Function #15)
 59 [-]: MOVE      R0 R12       ; R0 := R12
 60 [-]: MOVE      R0 R11       ; R0 := R11
 61 [-]: MOVE      R0 R15       ; R0 := R15
 62 [-]: MOVE      R0 R18       ; R0 := R18
 63 [-]: MOVE      R0 R23       ; R0 := R23
 64 [-]: MOVE      R0 R7        ; R0 := R7
 65 [-]: MOVE      R0 R9        ; R0 := R9
 66 [-]: MOVE      R0 R39       ; R0 := R39
 67 [-]: MOVE      R0 R6        ; R0 := R6
 68 [-]: MOVE      R0 R14       ; R0 := R14
 69 [-]: MOVE      R0 R2        ; R0 := R2
 70 [-]: MOVE      R0 R20       ; R0 := R20
 71 [-]: MOVE      R0 R21       ; R0 := R21
 72 [-]: CLOSURE   R41 15       ; R41 := closure(Function #16)
 73 [-]: MOVE      R0 R24       ; R0 := R24
 74 [-]: MOVE      R0 R4        ; R0 := R4
 75 [-]: MOVE      R0 R25       ; R0 := R25
 76 [-]: MOVE      R0 R11       ; R0 := R11
 77 [-]: MOVE      R0 R12       ; R0 := R12
 78 [-]: MOVE      R0 R15       ; R0 := R15
 79 [-]: MOVE      R0 R13       ; R0 := R13
 80 [-]: MOVE      R0 R30       ; R0 := R30
 81 [-]: MOVE      R0 R26       ; R0 := R26
 82 [-]: MOVE      R0 R22       ; R0 := R22
 83 [-]: MOVE      R0 R32       ; R0 := R32
 84 [-]: MOVE      R0 R31       ; R0 := R31
 85 [-]: CLOSURE   R23 16       ; R23 := closure(Function #17)
 86 [-]: MOVE      R0 R5        ; R0 := R5
 87 [-]: MOVE      R0 R8        ; R0 := R8
 88 [-]: MOVE      R0 R3        ; R0 := R3
 89 [-]: MOVE      R0 R10       ; R0 := R10
 90 [-]: CLOSURE   R42 17       ; R42 := closure(Function #18)
 91 [-]: MOVE      R0 R5        ; R0 := R5
 92 [-]: MOVE      R0 R3        ; R0 := R3
 93 [-]: MOVE      R0 R23       ; R0 := R23
 94 [-]: MOVE      R0 R10       ; R0 := R10
 95 [-]: CLOSURE   R43 18       ; R43 := closure(Function #19)
 96 [-]: MOVE      R0 R18       ; R0 := R18
 97 [-]: MOVE      R0 R20       ; R0 := R20
 98 [-]: MOVE      R0 R26       ; R0 := R26
 99 [-]: MOVE      R0 R17       ; R0 := R17
100 [-]: MOVE      R0 R34       ; R0 := R34
101 [-]: MOVE      R0 R28       ; R0 := R28
102 [-]: MOVE      R0 R35       ; R0 := R35
103 [-]: MOVE      R0 R16       ; R0 := R16
104 [-]: CLOSURE   R22 19       ; R22 := closure(Function #20)
105 [-]: MOVE      R0 R26       ; R0 := R26
106 [-]: MOVE      R0 R17       ; R0 := R17
107 [-]: MOVE      R0 R43       ; R0 := R43
108 [-]: MOVE      R0 R1        ; R0 := R1
109 [-]: MOVE      R0 R3        ; R0 := R3
110 [-]: CLOSURE   R44 20       ; R44 := closure(Function #21)
111 [-]: MOVE      R0 R6        ; R0 := R6
112 [-]: MOVE      R0 R3        ; R0 := R3
113 [-]: MOVE      R0 R5        ; R0 := R5
114 [-]: MOVE      R0 R2        ; R0 := R2
115 [-]: MOVE      R0 R16       ; R0 := R16
116 [-]: MOVE      R0 R42       ; R0 := R42
117 [-]: MOVE      R0 R26       ; R0 := R26
118 [-]: MOVE      R0 R43       ; R0 := R43
119 [-]: MOVE      R0 R12       ; R0 := R12
120 [-]: MOVE      R0 R13       ; R0 := R13
121 [-]: MOVE      R0 R14       ; R0 := R14
122 [-]: MOVE      R0 R11       ; R0 := R11
123 [-]: MOVE      R0 R17       ; R0 := R17
124 [-]: MOVE      R0 R15       ; R0 := R15
125 [-]: MOVE      R0 R27       ; R0 := R27
126 [-]: MOVE      R0 R28       ; R0 := R28
127 [-]: MOVE      R0 R40       ; R0 := R40
128 [-]: MOVE      R0 R41       ; R0 := R41
129 [-]: MOVE      R0 R22       ; R0 := R22
130 [-]: CLOSURE   R45 21       ; R45 := closure(Function #22)
131 [-]: MOVE      R0 R26       ; R0 := R26
132 [-]: MOVE      R0 R29       ; R0 := R29
133 [-]: MOVE      R0 R2        ; R0 := R2
134 [-]: MOVE      R0 R3        ; R0 := R3
135 [-]: MOVE      R0 R4        ; R0 := R4
136 [-]: MOVE      R0 R0        ; R0 := R0
137 [-]: MOVE      R0 R5        ; R0 := R5
138 [-]: MOVE      R0 R10       ; R0 := R10
139 [-]: MOVE      R0 R44       ; R0 := R44
140 [-]: SETGLOBAL R45 K9       ; OnEquipped := R45
141 [-]: CLOSURE   R45 22       ; R45 := closure(Function #23)
142 [-]: MOVE      R0 R19       ; R0 := R19
143 [-]: SETGLOBAL R45 K10      ; ConsumeRepairMaterialsAndRewardXP := R45
144 [-]: CLOSURE   R45 23       ; R45 := closure(Function #24)
145 [-]: SETGLOBAL R45 K11      ; RepairToolAdditionalInventory := R45
146 [-]: RETURN    R0 1         ; return 


; Function #1:
;
; Name:            
; Defined at line: 57
; #Upvalues:       0
; #Parameters:     1
; Is_vararg:       0
; Max Stack Size:  2

  1 [-]: RETURN    R0 1         ; return 


; Function #2:
;
; Name:            
; Defined at line: 65
; #Upvalues:       2
; #Parameters:     0
; Is_vararg:       0
; Max Stack Size:  5

  1 [-]: GETGLOBAL R0 K0        ; R0 := 0x9ba7909f
  2 [-]: SELF      R0 R0 K1     ; R1 := R0; R0 := R0[0xbf9494fc]
  3 [-]: LOADK     R2 K2        ; R2 := "Client.InfiniteAmmo"
  4 [-]: CALL      R0 3 2       ; R0 := R0(R1,R2)
  5 [-]: TEST      R0 1         ; if R0 then PC := 51
  6 [-]: JMP       51           ; PC := 51
  7 [-]: GETGLOBAL R0 K3        ; R0 := 0x7b998233
  8 [-]: GETUPVAL  R1 U0        ; R1 := U0
  9 [-]: CALL      R0 2 2       ; R0 := R0(R1)
 10 [-]: TEST      R0 1         ; if R0 then PC := 53
 11 [-]: JMP       53           ; PC := 53
 12 [-]: GETUPVAL  R0 U0        ; R0 := U0
 13 [-]: SELF      R0 R0 K4     ; R1 := R0; R0 := R0[0xf2deaf69]
 14 [-]: GETGLOBAL R2 K5        ; R2 := gLotusOperatorAvatarType
 15 [-]: CALL      R0 3 2       ; R0 := R0(R1,R2)
 16 [-]: TEST      R0 1         ; if R0 then PC := 29
 17 [-]: JMP       29           ; PC := 29
 18 [-]: GETGLOBAL R0 K3        ; R0 := 0x7b998233
 19 [-]: GETUPVAL  R1 U1        ; R1 := U1
 20 [-]: CALL      R0 2 2       ; R0 := R0(R1)
 21 [-]: TEST      R0 1         ; if R0 then PC := 53
 22 [-]: JMP       53           ; PC := 53
 23 [-]: GETUPVAL  R0 U1        ; R0 := U1
 24 [-]: SELF      R0 R0 K6     ; R1 := R0; R0 := R0[0x4e434800]
 25 [-]: GETGLOBAL R2 K7        ; R2 := 0x186b715b
 26 [-]: TAILCALL  R0 3 0       ; R0,... := R0(R1,R2)
 27 [-]: RETURN    R0 0         ; return R0,...
 28 [-]: JMP       53           ; PC := 53
 29 [-]: GETUPVAL  R0 U0        ; R0 := U0
 30 [-]: SELF      R0 R0 K8     ; R1 := R0; R0 := R0[0x5b89142c]
 31 [-]: CALL      R0 2 2       ; R0 := R0(R1)
 32 [-]: GETGLOBAL R1 K3        ; R1 := 0x7b998233
 33 [-]: MOVE      R2 R0        ; R2 := R0
 34 [-]: CALL      R1 2 2       ; R1 := R1(R2)
 35 [-]: TEST      R1 1         ; if R1 then PC := 53
 36 [-]: JMP       53           ; PC := 53
 37 [-]: SELF      R1 R0 K9     ; R2 := R0; R1 := R0[0xa534c3ac]
 38 [-]: CALL      R1 2 2       ; R1 := R1(R2)
 39 [-]: GETGLOBAL R2 K3        ; R2 := 0x7b998233
 40 [-]: MOVE      R3 R1        ; R3 := R1
 41 [-]: CALL      R2 2 2       ; R2 := R2(R3)
 42 [-]: TEST      R2 1         ; if R2 then PC := 53
 43 [-]: JMP       53           ; PC := 53
 44 [-]: SELF      R2 R1 K10    ; R3 := R1; R2 := R1[0xde321e6f]
 45 [-]: CALL      R2 2 2       ; R2 := R2(R3)
 46 [-]: SELF      R2 R2 K6     ; R3 := R2; R2 := R2[0x4e434800]
 47 [-]: GETGLOBAL R4 K7        ; R4 := 0x186b715b
 48 [-]: TAILCALL  R2 3 0       ; R2,... := R2(R3,R4)
 49 [-]: RETURN    R2 0         ; return R2,...
 50 [-]: JMP       53           ; PC := 53
 51 [-]: LOADK     R2 999       ; R2 := 999.000000
 52 [-]: RETURN    R2 2         ; return R2
 53 [-]: RETURN    R0 1         ; return 


; Function #3:
;
; Name:            
; Defined at line: 89
; #Upvalues:       0
; #Parameters:     1
; Is_vararg:       0
; Max Stack Size:  4

  1 [-]: GETGLOBAL R1 K0        ; R1 := 0x7b998233
  2 [-]: MOVE      R2 R0        ; R2 := R0
  3 [-]: CALL      R1 2 2       ; R1 := R1(R2)
  4 [-]: TEST      R1 1         ; if R1 then PC := 18
  5 [-]: JMP       18           ; PC := 18
  6 [-]: SELF      R1 R0 K1     ; R2 := R0; R1 := R0[0xf2deaf69]
  7 [-]: GETGLOBAL R3 K2        ; R3 := 0x392a88f7
  8 [-]: CALL      R1 3 2       ; R1 := R1(R2,R3)
  9 [-]: TEST      R1 1         ; if R1 then PC := 16
 10 [-]: JMP       16           ; PC := 16
 11 [-]: SELF      R1 R0 K1     ; R2 := R0; R1 := R0[0xf2deaf69]
 12 [-]: GETGLOBAL R3 K3        ; R3 := 0xa5dc8da5
 13 [-]: CALL      R1 3 2       ; R1 := R1(R2,R3)
 14 [-]: TEST      R1 0         ; if not R1 then PC := 18
 15 [-]: JMP       18           ; PC := 18
 16 [-]: LOADBOOL  R1 1 0       ; R1 := true
 17 [-]: RETURN    R1 2         ; return R1
 18 [-]: LOADBOOL  R1 0 0       ; R1 := false
 19 [-]: RETURN    R1 2         ; return R1
 20 [-]: RETURN    R0 1         ; return 


; Function #4:
;
; Name:            
; Defined at line: 99
; #Upvalues:       0
; #Parameters:     0
; Is_vararg:       0
; Max Stack Size:  2

  1 [-]: GETGLOBAL R0 K0        ; R0 := 0x7b998233
  2 [-]: GETGLOBAL R1 K1        ; R1 := _T
  3 [-]: GETTABLE  R1 R1 K2     ; R1 := R1["MultiTool"]
  4 [-]: CALL      R0 2 2       ; R0 := R0(R1)
  5 [-]: TEST      R0 0         ; if not R0 then PC := 10
  6 [-]: JMP       10           ; PC := 10
  7 [-]: GETGLOBAL R0 K1        ; R0 := _T
  8 [-]: NEWTABLE  R1 0 0       ; R1 := {}
  9 [-]: SETTABLE  R0 K2 R1     ; R0["MultiTool"] := R1
 10 [-]: GETGLOBAL R0 K0        ; R0 := 0x7b998233
 11 [-]: GETGLOBAL R1 K1        ; R1 := _T
 12 [-]: GETTABLE  R1 R1 K2     ; R1 := R1["MultiTool"]
 13 [-]: GETTABLE  R1 R1 K3     ; R1 := R1["ActiveRepairsInfo"]
 14 [-]: CALL      R0 2 2       ; R0 := R0(R1)
 15 [-]: TEST      R0 0         ; if not R0 then PC := 24
 16 [-]: JMP       24           ; PC := 24
 17 [-]: GETGLOBAL R0 K1        ; R0 := _T
 18 [-]: GETTABLE  R0 R0 K2     ; R0 := R0["MultiTool"]
 19 [-]: NEWTABLE  R1 0 0       ; R1 := {}
 20 [-]: SETTABLE  R0 K3 R1     ; R0["ActiveRepairsInfo"] := R1
 21 [-]: GETGLOBAL R0 K1        ; R0 := _T
 22 [-]: GETTABLE  R0 R0 K2     ; R0 := R0["MultiTool"]
 23 [-]: SETTABLE  R0 K4 K5     ; R0["ActiveRepairsCount"] := 0.000000
 24 [-]: RETURN    R0 1         ; return 


; Function #5:
;
; Name:            
; Defined at line: 110
; #Upvalues:       0
; #Parameters:     2
; Is_vararg:       0
; Max Stack Size:  6

  1 [-]: LOADK     R2 K0        ; R2 := 0.015000
  2 [-]: GETGLOBAL R3 K1        ; R3 := 0x5bced4c4
  3 [-]: GETTABLE  R3 R3 K2     ; R3 := R3[0xac1b386a]
  4 [-]: ADD       R4 R1 R2     ; R4 := R1 + R2
  5 [-]: LOADK     R5 1         ; R5 := 1.000000
  6 [-]: CALL      R3 3 2       ; R3 := R3(R4,R5)
  7 [-]: GETTABLE  R4 R0 K3     ; R4 := R0["START"]
  8 [-]: LT        1 K4 R4      ; if 0.000000 < R4 then PC := 13
  9 [-]: JMP       13           ; PC := 13
 10 [-]: GETTABLE  R4 R0 K5     ; R4 := R0["END"]
 11 [-]: LT        0 K4 R4      ; if 0.000000 >= R4 then PC := 23
 12 [-]: JMP       23           ; PC := 23
 13 [-]: GETTABLE  R4 R0 K5     ; R4 := R0["END"]
 14 [-]: GETTABLE  R5 R0 K3     ; R5 := R0["START"]
 15 [-]: LT        0 R5 R4      ; if R5 >= R4 then PC := 23
 16 [-]: JMP       23           ; PC := 23
 17 [-]: GETTABLE  R4 R0 K3     ; R4 := R0["START"]
 18 [-]: LE        0 R4 R3      ; if R4 > R3 then PC := 23
 19 [-]: JMP       23           ; PC := 23
 20 [-]: GETTABLE  R4 R0 K5     ; R4 := R0["END"]
 21 [-]: LE        1 R3 R4      ; if R3 <= R4 then PC := 24
 22 [-]: JMP       24           ; PC := 24
 23 [-]: LOADBOOL  R4 0 1       ; R4 := false; PC := 24
 24 [-]: LOADBOOL  R4 1 0       ; R4 := true
 25 [-]: RETURN    R4 2         ; return R4
 26 [-]: RETURN    R0 1         ; return 


; Function #6:
;
; Name:            
; Defined at line: 122
; #Upvalues:       1
; #Parameters:     3
; Is_vararg:       0
; Max Stack Size:  6

  1 [-]: GETUPVAL  R3 U0        ; R3 := U0
  2 [-]: MOVE      R4 R0        ; R4 := R0
  3 [-]: MOVE      R5 R1        ; R5 := R1
  4 [-]: CALL      R3 3 2       ; R3 := R3(R4,R5)
  5 [-]: TEST      R3 1         ; if R3 then PC := 12
  6 [-]: JMP       12           ; PC := 12
  7 [-]: GETUPVAL  R3 U0        ; R3 := U0
  8 [-]: MOVE      R4 R0        ; R4 := R0
  9 [-]: MOVE      R5 R2        ; R5 := R2
 10 [-]: CALL      R3 3 2       ; R3 := R3(R4,R5)
 11 [-]: JMP       14           ; PC := 14
 12 [-]: LOADBOOL  R3 0 1       ; R3 := false; PC := 13
 13 [-]: LOADBOOL  R3 1 0       ; R3 := true
 14 [-]: RETURN    R3 2         ; return R3
 15 [-]: RETURN    R0 1         ; return 


; Function #7:
;
; Name:            
; Defined at line: 126
; #Upvalues:       1
; #Parameters:     0
; Is_vararg:       0
; Max Stack Size:  8

  1 [-]: GETUPVAL  R0 U0        ; R0 := U0
  2 [-]: TEST      R0 0         ; if not R0 then PC := 22
  3 [-]: JMP       22           ; PC := 22
  4 [-]: LOADK     R0 K0        ; R0 := 0.300000
  5 [-]: LOADK     R1 K1        ; R1 := 0.030000
  6 [-]: LOADK     R2 K2        ; R2 := 0.050000
  7 [-]: SUB       R3 K3 R0     ; R3 := 1.000000 - R0
  8 [-]: ADD       R4 R1 R2     ; R4 := R1 + R2
  9 [-]: SUB       R3 R3 R4     ; R3 := R3 - R4
 10 [-]: GETGLOBAL R4 K4        ; R4 := 0xc163f229
 11 [-]: LOADK     R5 0         ; R5 := 0.000000
 12 [-]: MOVE      R6 R3        ; R6 := R3
 13 [-]: CALL      R4 3 2       ; R4 := R4(R5,R6)
 14 [-]: ADD       R4 R0 R4     ; R4 := R0 + R4
 15 [-]: GETGLOBAL R5 K4        ; R5 := 0xc163f229
 16 [-]: MOVE      R6 R1        ; R6 := R1
 17 [-]: ADD       R7 R1 R2     ; R7 := R1 + R2
 18 [-]: CALL      R5 3 2       ; R5 := R5(R6,R7)
 19 [-]: MOVE      R6 R4        ; R6 := R4
 20 [-]: ADD       R7 R4 R5     ; R7 := R4 + R5
 21 [-]: RETURN    R6 3         ; return R6,R7
 22 [-]: LOADK     R6 0         ; R6 := 0.000000
 23 [-]: LOADK     R7 0         ; R7 := 0.000000
 24 [-]: RETURN    R6 3         ; return R6,R7
 25 [-]: RETURN    R0 1         ; return 


; Function #8:
;
; Name:            
; Defined at line: 142
; #Upvalues:       1
; #Parameters:     2
; Is_vararg:       0
; Max Stack Size:  6

  1 [-]: NEWTABLE  R2 0 0       ; R2 := {}
  2 [-]: SETTABLE  R2 K0 R0     ; R2["target"] := R0
  3 [-]: SETTABLE  R2 K1 K2     ; R2["lastUpdateTime"] := nil
  4 [-]: SETTABLE  R2 K3 K4     ; R2["progression"] := 0.000000
  5 [-]: SETTABLE  R2 K5 K6     ; R2["progressionDirection"] := 1.000000
  6 [-]: NEWTABLE  R3 0 2       ; R3 := {}
  7 [-]: SETTABLE  R3 K8 K4     ; R3["START"] := 0.000000
  8 [-]: SETTABLE  R3 K9 K4     ; R3["END"] := 0.000000
  9 [-]: SETTABLE  R2 K7 R3     ; R2["baseSweetSpot"] := R3
 10 [-]: NEWTABLE  R3 0 2       ; R3 := {}
 11 [-]: SETTABLE  R3 K8 K4     ; R3["START"] := 0.000000
 12 [-]: SETTABLE  R3 K9 K4     ; R3["END"] := 0.000000
 13 [-]: SETTABLE  R2 K10 R3    ; R2[0x89326c93] := R3
 14 [-]: SETTABLE  R2 K11 K12   ; R2["enteredSweetSpot"] := false
 15 [-]: TEST      R1 0         ; if not R1 then PC := 27
 16 [-]: JMP       27           ; PC := 27
 17 [-]: GETUPVAL  R3 U0        ; R3 := U0
 18 [-]: CALL      R3 1 3       ; R3,R4 := R3()
 19 [-]: NEWTABLE  R5 0 2       ; R5 := {}
 20 [-]: SETTABLE  R5 K8 R3     ; R5[0xed4e0128] := R3
 21 [-]: SETTABLE  R5 K9 R4     ; R5[0x9808fb37] := R4
 22 [-]: SETTABLE  R2 K7 R5     ; R2["baseSweetSpot"] := R5
 23 [-]: NEWTABLE  R5 0 2       ; R5 := {}
 24 [-]: SETTABLE  R5 K8 R3     ; R5[0xed4e0128] := R3
 25 [-]: SETTABLE  R5 K9 R4     ; R5[0x9808fb37] := R4
 26 [-]: SETTABLE  R2 K10 R5    ; R2[0x89326c93] := R5
 27 [-]: SETTABLE  R2 K13 K4    ; R2["gemSpot"] := 0.000000
 28 [-]: RETURN    R2 2         ; return R2
 29 [-]: RETURN    R0 1         ; return 


; Function #9:
;
; Name:            
; Defined at line: 164
; #Upvalues:       2
; #Parameters:     1
; Is_vararg:       0
; Max Stack Size:  10

  1 [-]: GETGLOBAL R1 K0        ; R1 := 0x7b998233
  2 [-]: MOVE      R2 R0        ; R2 := R0
  3 [-]: CALL      R1 2 2       ; R1 := R1(R2)
  4 [-]: TEST      R1 1         ; if R1 then PC := 78
  5 [-]: JMP       78           ; PC := 78
  6 [-]: LOADK     R1 -1        ; R1 := -1.000000
  7 [-]: LOADK     R2 1         ; R2 := 1.000000
  8 [-]: GETGLOBAL R3 K1        ; R3 := _T
  9 [-]: GETTABLE  R3 R3 K2     ; R3 := R3["MultiTool"]
 10 [-]: GETTABLE  R3 R3 K3     ; R3 := R3["ActiveRepairsCount"]
 11 [-]: LOADK     R4 1         ; R4 := 1.000000
 12 [-]: FORPREP   R2 48        ; R2 -= R4; PC := 48
 13 [-]: GETGLOBAL R6 K0        ; R6 := 0x7b998233
 14 [-]: GETGLOBAL R7 K1        ; R7 := _T
 15 [-]: GETTABLE  R7 R7 K2     ; R7 := R7["MultiTool"]
 16 [-]: GETTABLE  R7 R7 K4     ; R7 := R7["ActiveRepairsInfo"]
 17 [-]: GETTABLE  R7 R7 R5     ; R7 := R7[R5]
 18 [-]: CALL      R6 2 2       ; R6 := R6(R7)
 19 [-]: TEST      R6 1         ; if R6 then PC := 30
 20 [-]: JMP       30           ; PC := 30
 21 [-]: GETGLOBAL R6 K0        ; R6 := 0x7b998233
 22 [-]: GETGLOBAL R7 K1        ; R7 := _T
 23 [-]: GETTABLE  R7 R7 K2     ; R7 := R7["MultiTool"]
 24 [-]: GETTABLE  R7 R7 K4     ; R7 := R7["ActiveRepairsInfo"]
 25 [-]: GETTABLE  R7 R7 R5     ; R7 := R7[R5]
 26 [-]: GETTABLE  R7 R7 K5     ; R7 := R7["target"]
 27 [-]: CALL      R6 2 2       ; R6 := R6(R7)
 28 [-]: TEST      R6 0         ; if not R6 then PC := 36
 29 [-]: JMP       36           ; PC := 36
 30 [-]: MOVE      R1 R5        ; R1 := R5
 31 [-]: GETGLOBAL R6 K1        ; R6 := _T
 32 [-]: GETTABLE  R6 R6 K2     ; R6 := R6["MultiTool"]
 33 [-]: GETTABLE  R6 R6 K4     ; R6 := R6["ActiveRepairsInfo"]
 34 [-]: SETTABLE  R6 R1 K6     ; R6[R1] := nil
 35 [-]: JMP       48           ; PC := 48
 36 [-]: GETGLOBAL R6 K1        ; R6 := _T
 37 [-]: GETTABLE  R6 R6 K2     ; R6 := R6["MultiTool"]
 38 [-]: GETTABLE  R6 R6 K4     ; R6 := R6["ActiveRepairsInfo"]
 39 [-]: GETTABLE  R6 R6 R5     ; R6 := R6[R5]
 40 [-]: GETTABLE  R6 R6 K5     ; R6 := R6["target"]
 41 [-]: EQ        0 R0 R6      ; if R0 ~= R6 then PC := 48
 42 [-]: JMP       48           ; PC := 48
 43 [-]: GETGLOBAL R6 K1        ; R6 := _T
 44 [-]: GETTABLE  R6 R6 K2     ; R6 := R6["MultiTool"]
 45 [-]: GETTABLE  R6 R6 K4     ; R6 := R6["ActiveRepairsInfo"]
 46 [-]: GETTABLE  R6 R6 R5     ; R6 := R6[R5]
 47 [-]: RETURN    R6 2         ; return R6
 48 [-]: FORLOOP   R2 13        ; R2 += R4; if R2 <= R3 then begin PC := 13; R5 := R2 end
 49 [-]: GETUPVAL  R6 U0        ; R6 := U0
 50 [-]: MOVE      R7 R0        ; R7 := R0
 51 [-]: GETUPVAL  R8 U1        ; R8 := U1
 52 [-]: MOVE      R9 R0        ; R9 := R0
 53 [-]: CALL      R8 2 2       ; R8 := R8(R9)
 54 [-]: NOT       R8 R8        ; R8 := not R8
 55 [-]: CALL      R6 3 2       ; R6 := R6(R7,R8)
 56 [-]: LT        0 R1 K7      ; if R1 >= 0.000000 then PC := 73
 57 [-]: JMP       73           ; PC := 73
 58 [-]: GETGLOBAL R7 K8        ; R7 := 0x33bdd652
 59 [-]: GETTABLE  R7 R7 K9     ; R7 := R7[0x23d5322f]
 60 [-]: GETGLOBAL R8 K1        ; R8 := _T
 61 [-]: GETTABLE  R8 R8 K2     ; R8 := R8["MultiTool"]
 62 [-]: GETTABLE  R8 R8 K4     ; R8 := R8["ActiveRepairsInfo"]
 63 [-]: MOVE      R9 R6        ; R9 := R6
 64 [-]: CALL      R7 3 1       ; R7(R8,R9)
 65 [-]: GETGLOBAL R7 K1        ; R7 := _T
 66 [-]: GETTABLE  R7 R7 K2     ; R7 := R7["MultiTool"]
 67 [-]: GETGLOBAL R8 K1        ; R8 := _T
 68 [-]: GETTABLE  R8 R8 K2     ; R8 := R8["MultiTool"]
 69 [-]: GETTABLE  R8 R8 K3     ; R8 := R8["ActiveRepairsCount"]
 70 [-]: ADD       R8 R8 K10    ; R8 := R8 + 1.000000
 71 [-]: SETTABLE  R7 K3 R8     ; R7["ActiveRepairsCount"] := R8
 72 [-]: JMP       77           ; PC := 77
 73 [-]: GETGLOBAL R7 K1        ; R7 := _T
 74 [-]: GETTABLE  R7 R7 K2     ; R7 := R7["MultiTool"]
 75 [-]: GETTABLE  R7 R7 K4     ; R7 := R7["ActiveRepairsInfo"]
 76 [-]: SETTABLE  R7 R1 R6     ; R7[R1] := R6
 77 [-]: RETURN    R6 2         ; return R6
 78 [-]: RETURN    R0 1         ; return 


; Function #10:
;
; Name:            
; Defined at line: 195
; #Upvalues:       1
; #Parameters:     1
; Is_vararg:       0
; Max Stack Size:  15

  1 [-]: GETUPVAL  R1 U0        ; R1 := U0
  2 [-]: LOADK     R2 K0        ; R2 := "FetchTargetBreachInfo"
  3 [-]: CALL      R1 2 1       ; R1(R2)
  4 [-]: GETGLOBAL R1 K1        ; R1 := 0x7b998233
  5 [-]: GETGLOBAL R2 K2        ; R2 := _T
  6 [-]: GETTABLE  R2 R2 K3     ; R2 := R2["WallBreaches"]
  7 [-]: CALL      R1 2 2       ; R1 := R1(R2)
  8 [-]: TEST      R1 1         ; if R1 then PC := 51
  9 [-]: JMP       51           ; PC := 51
 10 [-]: GETUPVAL  R1 U0        ; R1 := U0
 11 [-]: LOADK     R2 K4        ; R2 := "not IsNull(_T.WallBreaches)"
 12 [-]: CALL      R1 2 1       ; R1(R2)
 13 [-]: GETGLOBAL R1 K5        ; R1 := 0xcfc01047
 14 [-]: GETGLOBAL R2 K2        ; R2 := _T
 15 [-]: GETTABLE  R2 R2 K3     ; R2 := R2["WallBreaches"]
 16 [-]: CALL      R1 2 4       ; R1,R2,R3 := R1(R2)
 17 [-]: JMP       48           ; PC := 48
 18 [-]: GETGLOBAL R6 K1        ; R6 := 0x7b998233
 19 [-]: MOVE      R7 R4        ; R7 := R4
 20 [-]: CALL      R6 2 2       ; R6 := R6(R7)
 21 [-]: TEST      R6 1         ; if R6 then PC := 48
 22 [-]: JMP       48           ; PC := 48
 23 [-]: EQ        0 R4 R0      ; if R4 ~= R0 then PC := 48
 24 [-]: JMP       48           ; PC := 48
 25 [-]: GETUPVAL  R6 U0        ; R6 := U0
 26 [-]: LOADK     R7 K6        ; R7 := "Found breach info for "
 27 [-]: SELF      R8 R0 K7     ; R9 := R0; R8 := R0[0xed4e0128]
 28 [-]: CALL      R8 2 2       ; R8 := R8(R9)
 29 [-]: CONCAT    R7 R7 R8     ; R7 := R7 .. R8
 30 [-]: CALL      R6 2 1       ; R6(R7)
 31 [-]: GETGLOBAL R6 K8        ; R6 := 0x9808fb37
 32 [-]: TEST      R6 0         ; if not R6 then PC := 47
 33 [-]: JMP       47           ; PC := 47
 34 [-]: GETGLOBAL R6 K9        ; R6 := 0x89326c93
 35 [-]: SELF      R6 R6 K10    ; R7 := R6; R6 := R6[0x9ed3b54e]
 36 [-]: SELF      R8 R0 K11    ; R9 := R0; R8 := R0[0xd1586535]
 37 [-]: CALL      R8 2 2       ; R8 := R8(R9)
 38 [-]: LOADK     R9 K12       ; R9 := 0.400000
 39 [-]: GETGLOBAL R10 K13      ; R10 := 0x60130201
 40 [-]: LOADK     R11 0        ; R11 := 0.000000
 41 [-]: LOADK     R12 100      ; R12 := 100.000000
 42 [-]: LOADK     R13 100      ; R13 := 100.000000
 43 [-]: LOADK     R14 255      ; R14 := 255.000000
 44 [-]: CALL      R10 5 2      ; R10 := R10(R11,R12,R13,R14)
 45 [-]: LOADK     R11 2        ; R11 := 2.000000
 46 [-]: CALL      R6 6 1       ; R6(R7,R8,R9,R10,R11)
 47 [-]: RETURN    R5 2         ; return R5
 48 [-]: TFORLOOP  R1 2         ; R4,R5 :=  R1(R2,R3); if R4 ~= nil then begin PC = 18; R3 := R4 end
 49 [-]: JMP       18           ; PC := 18
 50 [-]: JMP       57           ; PC := 57
 51 [-]: GETGLOBAL R6 K14       ; R6 := 0x3d106989
 52 [-]: LOADK     R7 K15       ; R7 := "ERROR: _T.WallBreaches not found. Information not created for "
 53 [-]: SELF      R8 R0 K7     ; R9 := R0; R8 := R0[0xed4e0128]
 54 [-]: CALL      R8 2 2       ; R8 := R8(R9)
 55 [-]: CONCAT    R7 R7 R8     ; R7 := R7 .. R8
 56 [-]: CALL      R6 2 1       ; R6(R7)
 57 [-]: RETURN    R0 1         ; return 


; Function #11:
;
; Name:            
; Defined at line: 214
; #Upvalues:       0
; #Parameters:     3
; Is_vararg:       0
; Max Stack Size:  5

  1 [-]: GETTABLE  R3 R1 K0     ; R3 := R1["x"]
  2 [-]: GETTABLE  R4 R0 K0     ; R4 := R0["x"]
  3 [-]: LE        0 R3 R4      ; if R3 > R4 then PC := 25
  4 [-]: JMP       25           ; PC := 25
  5 [-]: GETTABLE  R3 R0 K0     ; R3 := R0["x"]
  6 [-]: GETTABLE  R4 R2 K0     ; R4 := R2["x"]
  7 [-]: LE        0 R3 R4      ; if R3 > R4 then PC := 25
  8 [-]: JMP       25           ; PC := 25
  9 [-]: GETTABLE  R3 R1 K1     ; R3 := R1["y"]
 10 [-]: GETTABLE  R4 R0 K1     ; R4 := R0["y"]
 11 [-]: LE        0 R3 R4      ; if R3 > R4 then PC := 25
 12 [-]: JMP       25           ; PC := 25
 13 [-]: GETTABLE  R3 R0 K1     ; R3 := R0["y"]
 14 [-]: GETTABLE  R4 R2 K1     ; R4 := R2["y"]
 15 [-]: LE        0 R3 R4      ; if R3 > R4 then PC := 25
 16 [-]: JMP       25           ; PC := 25
 17 [-]: GETTABLE  R3 R1 K2     ; R3 := R1["z"]
 18 [-]: GETTABLE  R4 R0 K2     ; R4 := R0["z"]
 19 [-]: LE        0 R3 R4      ; if R3 > R4 then PC := 25
 20 [-]: JMP       25           ; PC := 25
 21 [-]: GETTABLE  R3 R0 K2     ; R3 := R0["z"]
 22 [-]: GETTABLE  R4 R2 K2     ; R4 := R2["z"]
 23 [-]: LE        1 R3 R4      ; if R3 <= R4 then PC := 26
 24 [-]: JMP       26           ; PC := 26
 25 [-]: LOADBOOL  R3 0 1       ; R3 := false; PC := 26
 26 [-]: LOADBOOL  R3 1 0       ; R3 := true
 27 [-]: RETURN    R3 2         ; return R3
 28 [-]: RETURN    R0 1         ; return 


; Function #12:
;
; Name:            
; Defined at line: 222
; #Upvalues:       0
; #Parameters:     1
; Is_vararg:       0
; Max Stack Size:  7

  1 [-]: LOADK     R1 5         ; R1 := 5.000000
  2 [-]: LOADK     R2 3         ; R2 := 3.000000
  3 [-]: GETGLOBAL R3 K0        ; R3 := 0x42dcc9f5
  4 [-]: GETGLOBAL R4 K1        ; R4 := 0x5bced4c4
  5 [-]: GETTABLE  R4 R4 K2     ; R4 := R4[0xb62ecfe0]
  6 [-]: SUB       R5 R0 K3     ; R5 := R0 - 1.000000
  7 [-]: LOADK     R6 0         ; R6 := 0.000000
  8 [-]: CALL      R4 3 2       ; R4 := R4(R5,R6)
  9 [-]: DIV       R4 R4 R1     ; R4 := R4 / R1
 10 [-]: LOADK     R5 0         ; R5 := 0.000000
 11 [-]: LOADK     R6 1         ; R6 := 1.000000
 12 [-]: CALL      R3 4 2       ; R3 := R3(R4,R5,R6)
 13 [-]: SUB       R4 K3 R3     ; R4 := 1.000000 - R3
 14 [-]: MUL       R4 R2 R4     ; R4 := R2 * R4
 15 [-]: RETURN    R4 2         ; return R4
 16 [-]: RETURN    R0 1         ; return 


; Function #13:
;
; Name:            
; Defined at line: 229
; #Upvalues:       3
; #Parameters:     3
; Is_vararg:       0
; Max Stack Size:  29

  1 [-]: GETTABLE  R3 R0 K0     ; R3 := R0["points"]
  2 [-]: GETGLOBAL R4 K1        ; R4 := 0xf03431cc
  3 [-]: GETUPVAL  R5 U0        ; R5 := U0
  4 [-]: TEST      R5 0         ; if not R5 then PC := 7
  5 [-]: JMP       7            ; PC := 7
  6 [-]: GETGLOBAL R4 K2        ; R4 := 0x13aa510d
  7 [-]: GETUPVAL  R5 U1        ; R5 := U1
  8 [-]: LEN       R6 R3        ; R6 := # R3
  9 [-]: CALL      R5 2 2       ; R5 := R5(R6)
 10 [-]: MUL       R6 R4 R5     ; R6 := R4 * R5
 11 [-]: ADD       R6 R4 R6     ; R6 := R4 + R6
 12 [-]: GETGLOBAL R7 K3        ; R7 := 0xc8802016
 13 [-]: MOVE      R8 R3        ; R8 := R3
 14 [-]: CALL      R7 2 4       ; R7,R8,R9 := R7(R8)
 15 [-]: JMP       109          ; PC := 109
 16 [-]: GETGLOBAL R12 K4       ; R12 := 0x9808fb37
 17 [-]: TEST      R12 0        ; if not R12 then PC := 31
 18 [-]: JMP       31           ; PC := 31
 19 [-]: GETGLOBAL R12 K5       ; R12 := 0x89326c93
 20 [-]: SELF      R12 R12 K6   ; R13 := R12; R12 := R12[0x9ed3b54e]
 21 [-]: MOVE      R14 R11      ; R14 := R11
 22 [-]: MOVE      R15 R6       ; R15 := R6
 23 [-]: GETGLOBAL R16 K7       ; R16 := 0x60130201
 24 [-]: LOADK     R17 200      ; R17 := 200.000000
 25 [-]: LOADK     R18 0        ; R18 := 0.000000
 26 [-]: LOADK     R19 50       ; R19 := 50.000000
 27 [-]: LOADK     R20 255      ; R20 := 255.000000
 28 [-]: CALL      R16 5 2      ; R16 := R16(R17,R18,R19,R20)
 29 [-]: GETGLOBAL R17 K8       ; R17 := 0xf062bfa1
 30 [-]: CALL      R12 6 1      ; R12(R13,R14,R15,R16,R17)
 31 [-]: GETGLOBAL R12 K9       ; R12 := 0xb6489516
 32 [-]: MOVE      R13 R1       ; R13 := R1
 33 [-]: ADD       R14 R1 R2    ; R14 := R1 + R2
 34 [-]: MOVE      R15 R11      ; R15 := R11
 35 [-]: CALL      R12 4 2      ; R12 := R12(R13,R14,R15)
 36 [-]: LE        0 R12 R6     ; if R12 > R6 then PC := 109
 37 [-]: JMP       109          ; PC := 109
 38 [-]: GETGLOBAL R13 K10      ; R13 := 0x33bdd652
 39 [-]: GETTABLE  R13 R13 K11  ; R13 := R13[0x9c1f3b5a]
 40 [-]: GETTABLE  R14 R0 K0    ; R14 := R0["points"]
 41 [-]: MOVE      R15 R10      ; R15 := R10
 42 [-]: CALL      R13 3 1      ; R13(R14,R15)
 43 [-]: GETTABLE  R13 R0 K12   ; R13 := R0["pointDecos"]
 44 [-]: LEN       R13 R13      ; R13 := # R13
 45 [-]: LT        0 K13 R13    ; if 0.000000 >= R13 then PC := 65
 46 [-]: JMP       65           ; PC := 65
 47 [-]: GETTABLE  R13 R0 K12   ; R13 := R0["pointDecos"]
 48 [-]: LEN       R13 R13      ; R13 := # R13
 49 [-]: LE        0 R10 R13    ; if R10 > R13 then PC := 65
 50 [-]: JMP       65           ; PC := 65
 51 [-]: GETTABLE  R13 R0 K12   ; R13 := R0["pointDecos"]
 52 [-]: GETTABLE  R13 R13 R10  ; R13 := R13[R10]
 53 [-]: GETGLOBAL R14 K10      ; R14 := 0x33bdd652
 54 [-]: GETTABLE  R14 R14 K11  ; R14 := R14[0x9c1f3b5a]
 55 [-]: GETTABLE  R15 R0 K12   ; R15 := R0["pointDecos"]
 56 [-]: MOVE      R16 R10      ; R16 := R10
 57 [-]: CALL      R14 3 1      ; R14(R15,R16)
 58 [-]: GETGLOBAL R14 K14      ; R14 := 0x7b998233
 59 [-]: MOVE      R15 R13      ; R15 := R13
 60 [-]: CALL      R14 2 2      ; R14 := R14(R15)
 61 [-]: TEST      R14 1        ; if R14 then PC := 65
 62 [-]: JMP       65           ; PC := 65
 63 [-]: SELF      R14 R13 K15  ; R15 := R13; R14 := R13[0xa2880940]
 64 [-]: CALL      R14 2 1      ; R14(R15)
 65 [-]: GETGLOBAL R14 K10      ; R14 := 0x33bdd652
 66 [-]: GETTABLE  R14 R14 K16  ; R14 := R14[0x23d5322f]
 67 [-]: GETTABLE  R15 R0 K17   ; R15 := R0["repairedPoints"]
 68 [-]: MOVE      R16 R11      ; R16 := R11
 69 [-]: CALL      R14 3 1      ; R14(R15,R16)
 70 [-]: GETGLOBAL R14 K14      ; R14 := 0x7b998233
 71 [-]: GETTABLE  R15 R0 K18   ; R15 := R0["repairedPointDecoType"]
 72 [-]: CALL      R14 2 2      ; R14 := R14(R15)
 73 [-]: TEST      R14 1        ; if R14 then PC := 109
 74 [-]: JMP       109          ; PC := 109
 75 [-]: GETGLOBAL R14 K5       ; R14 := 0x89326c93
 76 [-]: SELF      R14 R14 K19  ; R15 := R14; R14 := R14[0x05909209]
 77 [-]: GETTABLE  R16 R0 K18   ; R16 := R0["repairedPointDecoType"]
 78 [-]: MOVE      R17 R11      ; R17 := R11
 79 [-]: GETGLOBAL R18 K20      ; R18 := 0x00046924
 80 [-]: GETGLOBAL R19 K21      ; R19 := 0x5bced4c4
 81 [-]: GETTABLE  R19 R19 K22  ; R19 := R19[0x3630e649]
 82 [-]: LOADK     R20 -180     ; R20 := -180.000000
 83 [-]: LOADK     R21 180      ; R21 := 180.000000
 84 [-]: CALL      R19 3 2      ; R19 := R19(R20,R21)
 85 [-]: GETGLOBAL R20 K21      ; R20 := 0x5bced4c4
 86 [-]: GETTABLE  R20 R20 K22  ; R20 := R20[0x3630e649]
 87 [-]: LOADK     R21 -180     ; R21 := -180.000000
 88 [-]: LOADK     R22 180      ; R22 := 180.000000
 89 [-]: CALL      R20 3 2      ; R20 := R20(R21,R22)
 90 [-]: GETGLOBAL R21 K21      ; R21 := 0x5bced4c4
 91 [-]: GETTABLE  R21 R21 K22  ; R21 := R21[0x3630e649]
 92 [-]: LOADK     R22 -180     ; R22 := -180.000000
 93 [-]: LOADK     R23 180      ; R23 := 180.000000
 94 [-]: CALL      R21 3 0      ; R21,... := R21(R22,R23)
 95 [-]: CALL      R18 0 2      ; R18 := R18(R19,...)
 96 [-]: GETUPVAL  R19 U2       ; R19 := U2
 97 [-]: GETUPVAL  R20 U2       ; R20 := U2
 98 [-]: CALL      R14 7 2      ; R14 := R14(R15,R16,R17,R18,R19,R20)
 99 [-]: GETGLOBAL R15 K14      ; R15 := 0x7b998233
100 [-]: MOVE      R16 R14      ; R16 := R14
101 [-]: CALL      R15 2 2      ; R15 := R15(R16)
102 [-]: TEST      R15 1        ; if R15 then PC := 109
103 [-]: JMP       109          ; PC := 109
104 [-]: GETGLOBAL R15 K10      ; R15 := 0x33bdd652
105 [-]: GETTABLE  R15 R15 K16  ; R15 := R15[0x23d5322f]
106 [-]: GETTABLE  R16 R0 K23   ; R16 := R0["repairedPointDecos"]
107 [-]: MOVE      R17 R14      ; R17 := R14
108 [-]: CALL      R15 3 1      ; R15(R16,R17)
109 [-]: TFORLOOP  R7 2         ; R10,R11 :=  R7(R8,R9); if R10 ~= nil then begin PC = 16; R9 := R10 end
110 [-]: JMP       16           ; PC := 16
111 [-]: GETGLOBAL R15 K4       ; R15 := 0x9808fb37
112 [-]: TEST      R15 0        ; if not R15 then PC := 144
113 [-]: JMP       144          ; PC := 144
114 [-]: GETGLOBAL R15 K5       ; R15 := 0x89326c93
115 [-]: SELF      R15 R15 K6   ; R16 := R15; R15 := R15[0x9ed3b54e]
116 [-]: MOVE      R17 R1       ; R17 := R1
117 [-]: LOADK     R18 K24      ; R18 := 0.030000
118 [-]: GETGLOBAL R19 K7       ; R19 := 0x60130201
119 [-]: LOADK     R20 0        ; R20 := 0.000000
120 [-]: LOADK     R21 100      ; R21 := 100.000000
121 [-]: LOADK     R22 100      ; R22 := 100.000000
122 [-]: LOADK     R23 255      ; R23 := 255.000000
123 [-]: CALL      R19 5 2      ; R19 := R19(R20,R21,R22,R23)
124 [-]: GETGLOBAL R20 K8       ; R20 := 0xf062bfa1
125 [-]: CALL      R15 6 1      ; R15(R16,R17,R18,R19,R20)
126 [-]: GETGLOBAL R15 K3       ; R15 := 0xc8802016
127 [-]: GETTABLE  R16 R0 K17   ; R16 := R0["repairedPoints"]
128 [-]: CALL      R15 2 4      ; R15,R16,R17 := R15(R16)
129 [-]: JMP       142          ; PC := 142
130 [-]: GETGLOBAL R20 K5       ; R20 := 0x89326c93
131 [-]: SELF      R20 R20 K6   ; R21 := R20; R20 := R20[0x9ed3b54e]
132 [-]: MOVE      R22 R19      ; R22 := R19
133 [-]: MOVE      R23 R4       ; R23 := R4
134 [-]: GETGLOBAL R24 K7       ; R24 := 0x60130201
135 [-]: LOADK     R25 0        ; R25 := 0.000000
136 [-]: LOADK     R26 200      ; R26 := 200.000000
137 [-]: LOADK     R27 50       ; R27 := 50.000000
138 [-]: LOADK     R28 255      ; R28 := 255.000000
139 [-]: CALL      R24 5 2      ; R24 := R24(R25,R26,R27,R28)
140 [-]: GETGLOBAL R25 K8       ; R25 := 0xf062bfa1
141 [-]: CALL      R20 6 1      ; R20(R21,R22,R23,R24,R25)
142 [-]: TFORLOOP  R15 2        ; R18,R19 :=  R15(R16,R17); if R18 ~= nil then begin PC = 130; R17 := R18 end
143 [-]: JMP       130          ; PC := 130
144 [-]: RETURN    R0 1         ; return 


; Function #14:
;
; Name:            
; Defined at line: 272
; #Upvalues:       2
; #Parameters:     3
; Is_vararg:       0
; Max Stack Size:  7

  1 [-]: GETUPVAL  R3 U0        ; R3 := U0
  2 [-]: MOVE      R4 R1        ; R4 := R1
  3 [-]: GETTABLE  R5 R0 K0     ; R5 := R0["boundsMin"]
  4 [-]: GETTABLE  R6 R0 K1     ; R6 := R0["boundsMax"]
  5 [-]: CALL      R3 4 2       ; R3 := R3(R4,R5,R6)
  6 [-]: TEST      R3 0         ; if not R3 then PC := 13
  7 [-]: JMP       13           ; PC := 13
  8 [-]: GETUPVAL  R3 U1        ; R3 := U1
  9 [-]: MOVE      R4 R0        ; R4 := R0
 10 [-]: MOVE      R5 R1        ; R5 := R1
 11 [-]: MOVE      R6 R2        ; R6 := R2
 12 [-]: CALL      R3 4 1       ; R3(R4,R5,R6)
 13 [-]: RETURN    R0 1         ; return 


; Function #15:
;
; Name:            
; Defined at line: 279
; #Upvalues:       13
; #Parameters:     1
; Is_vararg:       0
; Max Stack Size:  13

  1 [-]: GETUPVAL  R1 U0        ; R1 := U0
  2 [-]: TEST      R1 0         ; if not R1 then PC := 53
  3 [-]: JMP       53           ; PC := 53
  4 [-]: GETUPVAL  R1 U1        ; R1 := U1
  5 [-]: TEST      R1 0         ; if not R1 then PC := 53
  6 [-]: JMP       53           ; PC := 53
  7 [-]: GETUPVAL  R1 U2        ; R1 := U2
  8 [-]: TEST      R1 0         ; if not R1 then PC := 53
  9 [-]: JMP       53           ; PC := 53
 10 [-]: GETGLOBAL R1 K0        ; R1 := 0x7b998233
 11 [-]: GETUPVAL  R2 U3        ; R2 := U3
 12 [-]: CALL      R1 2 2       ; R1 := R1(R2)
 13 [-]: TEST      R1 1         ; if R1 then PC := 53
 14 [-]: JMP       53           ; PC := 53
 15 [-]: GETUPVAL  R1 U4        ; R1 := U4
 16 [-]: CALL      R1 1 2       ; R1 := R1()
 17 [-]: GETUPVAL  R2 U5        ; R2 := U5
 18 [-]: TEST      R2 0         ; if not R2 then PC := 27
 19 [-]: JMP       27           ; PC := 27
 20 [-]: GETGLOBAL R2 K1        ; R2 := 0x03ea2485
 21 [-]: GETUPVAL  R3 U5        ; R3 := U5
 22 [-]: MOVE      R4 R1        ; R4 := R1
 23 [-]: CALL      R2 3 2       ; R2 := R2(R3,R4)
 24 [-]: GETUPVAL  R3 U6        ; R3 := U6
 25 [-]: LE        0 R3 R2      ; if R3 > R2 then PC := 53
 26 [-]: JMP       53           ; PC := 53
 27 [-]: GETUPVAL  R2 U7        ; R2 := U7
 28 [-]: GETUPVAL  R3 U3        ; R3 := U3
 29 [-]: MOVE      R4 R1        ; R4 := R1
 30 [-]: GETUPVAL  R5 U8        ; R5 := U8
 31 [-]: SELF      R5 R5 K2     ; R6 := R5; R5 := R5[0xd1cbfc3e]
 32 [-]: CALL      R5 2 0       ; R5,... := R5(R6)
 33 [-]: CALL      R2 0 1       ; R2(R3,...)
 34 [-]: SETUPVAL  R1 U5        ; U82 := R5
 35 [-]: GETUPVAL  R2 U3        ; R2 := U3
 36 [-]: GETTABLE  R2 R2 K3     ; R2 := R2["points"]
 37 [-]: LEN       R2 R2        ; R2 := # R2
 38 [-]: GETUPVAL  R3 U3        ; R3 := U3
 39 [-]: GETTABLE  R3 R3 K4     ; R3 := R3["repairedPoints"]
 40 [-]: LEN       R3 R3        ; R3 := # R3
 41 [-]: ADD       R2 R2 R3     ; R2 := R2 + R3
 42 [-]: GETUPVAL  R3 U3        ; R3 := U3
 43 [-]: GETTABLE  R3 R3 K4     ; R3 := R3["repairedPoints"]
 44 [-]: LEN       R3 R3        ; R3 := # R3
 45 [-]: DIV       R3 R3 R2     ; R3 := R3 / R2
 46 [-]: GETGLOBAL R4 K6        ; R4 := 0x5bced4c4
 47 [-]: GETTABLE  R4 R4 K7     ; R4 := R4[0xac1b386a]
 48 [-]: GETGLOBAL R5 K8        ; R5 := 0xce2eda5c
 49 [-]: DIV       R5 R3 R5     ; R5 := R3 / R5
 50 [-]: LOADK     R6 1         ; R6 := 1.000000
 51 [-]: CALL      R4 3 2       ; R4 := R4(R5,R6)
 52 [-]: SETTABLE  R0 K5 R4     ; R0["progression"] := R4
 53 [-]: GETUPVAL  R4 U0        ; R4 := U0
 54 [-]: TEST      R4 1         ; if R4 then PC := 59
 55 [-]: JMP       59           ; PC := 59
 56 [-]: GETUPVAL  R4 U9        ; R4 := U9
 57 [-]: TEST      R4 0         ; if not R4 then PC := 115
 58 [-]: JMP       115          ; PC := 115
 59 [-]: GETUPVAL  R4 U10       ; R4 := U10
 60 [-]: SELF      R4 R4 K9     ; R5 := R4; R4 := R4[0x9519a807]
 61 [-]: CALL      R4 2 2       ; R4 := R4(R5)
 62 [-]: TEST      R4 0         ; if not R4 then PC := 115
 63 [-]: JMP       115          ; PC := 115
 64 [-]: GETGLOBAL R4 K0        ; R4 := 0x7b998233
 65 [-]: GETUPVAL  R5 U3        ; R5 := U3
 66 [-]: CALL      R4 2 2       ; R4 := R4(R5)
 67 [-]: TEST      R4 1         ; if R4 then PC := 141
 68 [-]: JMP       141          ; PC := 141
 69 [-]: GETGLOBAL R4 K0        ; R4 := 0x7b998233
 70 [-]: GETUPVAL  R5 U3        ; R5 := U3
 71 [-]: GETTABLE  R5 R5 K10    ; R5 := R5["projector"]
 72 [-]: CALL      R4 2 2       ; R4 := R4(R5)
 73 [-]: TEST      R4 1         ; if R4 then PC := 141
 74 [-]: JMP       141          ; PC := 141
 75 [-]: GETUPVAL  R4 U3        ; R4 := U3
 76 [-]: GETTABLE  R4 R4 K3     ; R4 := R4["points"]
 77 [-]: LEN       R4 R4        ; R4 := # R4
 78 [-]: GETUPVAL  R5 U3        ; R5 := U3
 79 [-]: GETTABLE  R5 R5 K4     ; R5 := R5["repairedPoints"]
 80 [-]: LEN       R5 R5        ; R5 := # R5
 81 [-]: ADD       R4 R4 R5     ; R4 := R4 + R5
 82 [-]: LT        0 K11 R4     ; if 0.000000 >= R4 then PC := 141
 83 [-]: JMP       141          ; PC := 141
 84 [-]: GETUPVAL  R5 U3        ; R5 := U3
 85 [-]: GETTABLE  R5 R5 K3     ; R5 := R5["points"]
 86 [-]: LEN       R5 R5        ; R5 := # R5
 87 [-]: DIV       R5 R5 R4     ; R5 := R5 / R4
 88 [-]: GETUPVAL  R6 U3        ; R6 := U3
 89 [-]: GETTABLE  R6 R6 K10    ; R6 := R6["projector"]
 90 [-]: SELF      R6 R6 K12    ; R7 := R6; R6 := R6[0x986d2ab8]
 91 [-]: GETUPVAL  R8 U11       ; R8 := U11
 92 [-]: MUL       R9 K13 R5    ; R9 := 40.000000 * R5
 93 [-]: CALL      R6 4 1       ; R6(R7,R8,R9)
 94 [-]: GETUPVAL  R6 U3        ; R6 := U3
 95 [-]: GETTABLE  R6 R6 K10    ; R6 := R6["projector"]
 96 [-]: SELF      R6 R6 K12    ; R7 := R6; R6 := R6[0x986d2ab8]
 97 [-]: GETUPVAL  R8 U12       ; R8 := U12
 98 [-]: MUL       R9 K14 R5    ; R9 := 1.820000 * R5
 99 [-]: ADD       R9 K15 R9    ; R9 := 0.320000 + R9
100 [-]: MUL       R10 K16 R5   ; R10 := 0.300000 * R5
101 [-]: MUL       R11 K17 R5   ; R11 := 0.030000 * R5
102 [-]: LOADK     R12 1        ; R12 := 1.000000
103 [-]: CALL      R6 7 1       ; R6(R7,R8,R9,R10,R11,R12)
104 [-]: GETUPVAL  R6 U3        ; R6 := U3
105 [-]: GETTABLE  R6 R6 K10    ; R6 := R6["projector"]
106 [-]: SELF      R6 R6 K18    ; R7 := R6; R6 := R6[0x66472bf5]
107 [-]: GETGLOBAL R8 K6        ; R8 := 0x5bced4c4
108 [-]: GETTABLE  R8 R8 K19    ; R8 := R8[0xb62ecfe0]
109 [-]: LOADK     R9 0         ; R9 := 0.000000
110 [-]: SUB       R10 K20 R5   ; R10 := 0.400000 - R5
111 [-]: CALL      R8 3 2       ; R8 := R8(R9,R10)
112 [-]: MUL       R8 K21 R8    ; R8 := 2.500000 * R8
113 [-]: CALL      R6 3 1       ; R6(R7,R8)
114 [-]: JMP       141          ; PC := 141
115 [-]: GETGLOBAL R6 K0        ; R6 := 0x7b998233
116 [-]: GETUPVAL  R7 U3        ; R7 := U3
117 [-]: CALL      R6 2 2       ; R6 := R6(R7)
118 [-]: TEST      R6 1         ; if R6 then PC := 141
119 [-]: JMP       141          ; PC := 141
120 [-]: GETGLOBAL R6 K0        ; R6 := 0x7b998233
121 [-]: GETUPVAL  R7 U3        ; R7 := U3
122 [-]: GETTABLE  R7 R7 K10    ; R7 := R7["projector"]
123 [-]: CALL      R6 2 2       ; R6 := R6(R7)
124 [-]: TEST      R6 1         ; if R6 then PC := 141
125 [-]: JMP       141          ; PC := 141
126 [-]: GETUPVAL  R6 U3        ; R6 := U3
127 [-]: GETTABLE  R6 R6 K10    ; R6 := R6["projector"]
128 [-]: SELF      R6 R6 K12    ; R7 := R6; R6 := R6[0x986d2ab8]
129 [-]: GETUPVAL  R8 U11       ; R8 := U11
130 [-]: LOADK     R9 1         ; R9 := 1.000000
131 [-]: CALL      R6 4 1       ; R6(R7,R8,R9)
132 [-]: GETUPVAL  R6 U3        ; R6 := U3
133 [-]: GETTABLE  R6 R6 K10    ; R6 := R6["projector"]
134 [-]: SELF      R6 R6 K12    ; R7 := R6; R6 := R6[0x986d2ab8]
135 [-]: GETUPVAL  R8 U12       ; R8 := U12
136 [-]: LOADK     R9 K15       ; R9 := 0.320000
137 [-]: LOADK     R10 0        ; R10 := 0.000000
138 [-]: LOADK     R11 0        ; R11 := 0.000000
139 [-]: LOADK     R12 1        ; R12 := 1.000000
140 [-]: CALL      R6 7 1       ; R6(R7,R8,R9,R10,R11,R12)
141 [-]: RETURN    R0 2         ; return R0
142 [-]: RETURN    R0 1         ; return 


; Function #16:
;
; Name:            
; Defined at line: 318
; #Upvalues:       12
; #Parameters:     1
; Is_vararg:       0
; Max Stack Size:  16

  1 [-]: GETGLOBAL R1 K0        ; R1 := 0x67652851
  2 [-]: CALL      R1 1 2       ; R1 := R1()
  3 [-]: GETGLOBAL R2 K1        ; R2 := 0x7b998233
  4 [-]: GETTABLE  R3 R0 K2     ; R3 := R0["lastUpdateTime"]
  5 [-]: CALL      R2 2 2       ; R2 := R2(R3)
  6 [-]: TEST      R2 1         ; if R2 then PC := 19
  7 [-]: JMP       19           ; PC := 19
  8 [-]: GETTABLE  R2 R0 K3     ; R2 := R0["progressionDirection"]
  9 [-]: LT        0 R2 K4      ; if R2 >= 0.000000 then PC := 19
 10 [-]: JMP       19           ; PC := 19
 11 [-]: GETGLOBAL R2 K5        ; R2 := 0x55156ff7
 12 [-]: CALL      R2 1 2       ; R2 := R2()
 13 [-]: GETGLOBAL R3 K5        ; R3 := 0x55156ff7
 14 [-]: CALL      R3 1 2       ; R3 := R3()
 15 [-]: GETTABLE  R4 R0 K2     ; R4 := R0["lastUpdateTime"]
 16 [-]: SUB       R1 R3 R4     ; R1 := R3 - R4
 17 [-]: SETTABLE  R0 K2 R2     ; R0["lastUpdateTime"] := R2
 18 [-]: JMP       22           ; PC := 22
 19 [-]: GETGLOBAL R3 K5        ; R3 := 0x55156ff7
 20 [-]: CALL      R3 1 2       ; R3 := R3()
 21 [-]: SETTABLE  R0 K2 R3     ; R0["lastUpdateTime"] := R3
 22 [-]: GETUPVAL  R3 U0        ; R3 := U0
 23 [-]: GETUPVAL  R4 U1        ; R4 := U1
 24 [-]: TEST      R4 0         ; if not R4 then PC := 27
 25 [-]: JMP       27           ; PC := 27
 26 [-]: GETUPVAL  R3 U2        ; R3 := U2
 27 [-]: MUL       R4 R3 R1     ; R4 := R3 * R1
 28 [-]: GETTABLE  R5 R0 K3     ; R5 := R0["progressionDirection"]
 29 [-]: GETUPVAL  R6 U3        ; R6 := U3
 30 [-]: TEST      R6 0         ; if not R6 then PC := 36
 31 [-]: JMP       36           ; PC := 36
 32 [-]: GETUPVAL  R6 U4        ; R6 := U4
 33 [-]: TEST      R6 0         ; if not R6 then PC := 36
 34 [-]: JMP       36           ; PC := 36
 35 [-]: GETUPVAL  R6 U5        ; R6 := U5
 36 [-]: GETTABLE  R7 R0 K6     ; R7 := R0["progression"]
 37 [-]: TEST      R6 0         ; if not R6 then PC := 57
 38 [-]: JMP       57           ; PC := 57
 39 [-]: LT        0 K4 R5      ; if 0.000000 >= R5 then PC := 57
 40 [-]: JMP       57           ; PC := 57
 41 [-]: LOADK     R8 K7        ; R8 := 0.050000
 42 [-]: GETGLOBAL R9 K8        ; R9 := 0x5bced4c4
 43 [-]: GETTABLE  R9 R9 K9     ; R9 := R9[0xb62ecfe0]
 44 [-]: GETTABLE  R10 R0 K6    ; R10 := R0["progression"]
 45 [-]: SUB       R10 K10 R10  ; R10 := 1.000000 - R10
 46 [-]: MOVE      R11 R8       ; R11 := R8
 47 [-]: CALL      R9 3 2       ; R9 := R9(R10,R11)
 48 [-]: MUL       R4 R4 R9     ; R4 := R4 * R9
 49 [-]: GETGLOBAL R10 K8       ; R10 := 0x5bced4c4
 50 [-]: GETTABLE  R10 R10 K11  ; R10 := R10[0xac1b386a]
 51 [-]: GETTABLE  R11 R0 K6    ; R11 := R0["progression"]
 52 [-]: ADD       R11 R11 R4   ; R11 := R11 + R4
 53 [-]: LOADK     R12 1        ; R12 := 1.000000
 54 [-]: CALL      R10 3 2      ; R10 := R10(R11,R12)
 55 [-]: SETTABLE  R0 K6 R10    ; R0["progression"] := R10
 56 [-]: JMP       120          ; PC := 120
 57 [-]: GETUPVAL  R10 U6       ; R10 := U6
 58 [-]: TEST      R10 0        ; if not R10 then PC := 82
 59 [-]: JMP       82           ; PC := 82
 60 [-]: GETUPVAL  R10 U4       ; R10 := U4
 61 [-]: TEST      R10 1        ; if R10 then PC := 82
 62 [-]: JMP       82           ; PC := 82
 63 [-]: LT        0 K4 R5      ; if 0.000000 >= R5 then PC := 82
 64 [-]: JMP       82           ; PC := 82
 65 [-]: GETUPVAL  R10 U7       ; R10 := U7
 66 [-]: GETTABLE  R11 R0 K12   ; R11 := R0["sweetSpot"]
 67 [-]: GETTABLE  R12 R0 K6    ; R12 := R0["progression"]
 68 [-]: CALL      R10 3 2      ; R10 := R10(R11,R12)
 69 [-]: TEST      R10 0        ; if not R10 then PC := 77
 70 [-]: JMP       77           ; PC := 77
 71 [-]: GETUPVAL  R10 U8       ; R10 := U8
 72 [-]: LOADK     R11 K13      ; R11 := "Hit sweet spot."
 73 [-]: CALL      R10 2 1      ; R10(R11)
 74 [-]: GETUPVAL  R10 U9       ; R10 := U9
 75 [-]: CALL      R10 1 1      ; R10()
 76 [-]: JMP       120          ; PC := 120
 77 [-]: GETUPVAL  R10 U8       ; R10 := U8
 78 [-]: LOADK     R11 K14      ; R11 := "Retreat progress."
 79 [-]: CALL      R10 2 1      ; R10(R11)
 80 [-]: SETTABLE  R0 K3 K15    ; R0["progressionDirection"] := -1.000000
 81 [-]: JMP       120          ; PC := 120
 82 [-]: LT        0 K4 R5      ; if 0.000000 >= R5 then PC := 94
 83 [-]: JMP       94           ; PC := 94
 84 [-]: GETTABLE  R10 R0 K6    ; R10 := R0["progression"]
 85 [-]: LT        0 K4 R10     ; if 0.000000 >= R10 then PC := 94
 86 [-]: JMP       94           ; PC := 94
 87 [-]: TEST      R6 1         ; if R6 then PC := 94
 88 [-]: JMP       94           ; PC := 94
 89 [-]: GETUPVAL  R10 U8       ; R10 := U8
 90 [-]: LOADK     R11 K14      ; R11 := "Retreat progress."
 91 [-]: CALL      R10 2 1      ; R10(R11)
 92 [-]: SETTABLE  R0 K3 K15    ; R0["progressionDirection"] := -1.000000
 93 [-]: JMP       120          ; PC := 120
 94 [-]: LT        0 R5 K4      ; if R5 >= 0.000000 then PC := 120
 95 [-]: JMP       120          ; PC := 120
 96 [-]: GETGLOBAL R10 K8       ; R10 := 0x5bced4c4
 97 [-]: GETTABLE  R10 R10 K9   ; R10 := R10[0xb62ecfe0]
 98 [-]: GETTABLE  R11 R0 K6    ; R11 := R0["progression"]
 99 [-]: SUB       R11 R11 R4   ; R11 := R11 - R4
100 [-]: LOADK     R12 0        ; R12 := 0.000000
101 [-]: CALL      R10 3 2      ; R10 := R10(R11,R12)
102 [-]: SETTABLE  R0 K6 R10    ; R0["progression"] := R10
103 [-]: GETTABLE  R10 R0 K6    ; R10 := R0["progression"]
104 [-]: LE        0 R10 K4     ; if R10 > 0.000000 then PC := 120
105 [-]: JMP       120          ; PC := 120
106 [-]: GETUPVAL  R10 U8       ; R10 := U8
107 [-]: LOADK     R11 K16      ; R11 := "Reset direction."
108 [-]: CALL      R10 2 1      ; R10(R11)
109 [-]: GETUPVAL  R10 U10      ; R10 := U10
110 [-]: CALL      R10 1 3      ; R10,R11 := R10()
111 [-]: NEWTABLE  R12 0 2      ; R12 := {}
112 [-]: SETTABLE  R12 K18 R10  ; R12["START"] := R10
113 [-]: SETTABLE  R12 K19 R11  ; R12["END"] := R11
114 [-]: SETTABLE  R0 K17 R12   ; R0["baseSweetSpot"] := R12
115 [-]: NEWTABLE  R12 0 2      ; R12 := {}
116 [-]: SETTABLE  R12 K18 R10  ; R12["START"] := R10
117 [-]: SETTABLE  R12 K19 R11  ; R12["END"] := R11
118 [-]: SETTABLE  R0 K12 R12   ; R0["sweetSpot"] := R12
119 [-]: SETTABLE  R0 K3 K10    ; R0["progressionDirection"] := 1.000000
120 [-]: GETUPVAL  R12 U11      ; R12 := U11
121 [-]: GETTABLE  R13 R0 K12   ; R13 := R0["sweetSpot"]
122 [-]: MOVE      R14 R7       ; R14 := R7
123 [-]: GETTABLE  R15 R0 K6    ; R15 := R0["progression"]
124 [-]: CALL      R12 4 2      ; R12 := R12(R13,R14,R15)
125 [-]: SETTABLE  R0 K20 R12   ; R0["enteredSweetSpot"] := R12
126 [-]: RETURN    R0 2         ; return R0
127 [-]: RETURN    R0 1         ; return 


; Function #17:
;
; Name:            
; Defined at line: 372
; #Upvalues:       4
; #Parameters:     0
; Is_vararg:       0
; Max Stack Size:  13

  1 [-]: GETUPVAL  R0 U0        ; R0 := U0
  2 [-]: SELF      R0 R0 K0     ; R1 := R0; R0 := R0[0x7c09e541]
  3 [-]: CALL      R0 2 2       ; R0 := R0(R1)
  4 [-]: GETUPVAL  R1 U0        ; R1 := U0
  5 [-]: SELF      R1 R1 K1     ; R2 := R1; R1 := R1[0x20149084]
  6 [-]: GETUPVAL  R3 U1        ; R3 := U1
  7 [-]: CALL      R1 3 2       ; R1 := R1(R2,R3)
  8 [-]: GETGLOBAL R2 K2        ; R2 := 0x7b998233
  9 [-]: MOVE      R3 R0        ; R3 := R0
 10 [-]: CALL      R2 2 2       ; R2 := R2(R3)
 11 [-]: TEST      R2 1         ; if R2 then PC := 50
 12 [-]: JMP       50           ; PC := 50
 13 [-]: SELF      R2 R0 K3     ; R3 := R0; R2 := R0[0xf2deaf69]
 14 [-]: GETGLOBAL R4 K4        ; R4 := 0xdb331825
 15 [-]: CALL      R2 3 2       ; R2 := R2(R3,R4)
 16 [-]: TEST      R2 0         ; if not R2 then PC := 50
 17 [-]: JMP       50           ; PC := 50
 18 [-]: NEWTABLE  R2 4 0       ; R2 := {}
 19 [-]: GETGLOBAL R3 K5        ; R3 := gBaseAvatarType
 20 [-]: GETGLOBAL R4 K6        ; R4 := gPickUpType
 21 [-]: GETGLOBAL R5 K7        ; R5 := gRagdollType
 22 [-]: GETGLOBAL R6 K8        ; R6 := gHitProxyType
 23 [-]: SETLIST   R2 4 1       ; R2[(1-1)*FPF+i] := R(2+i), 1 <= i <= 4
 24 [-]: GETUPVAL  R3 U2        ; R3 := U2
 25 [-]: SELF      R3 R3 K9     ; R4 := R3; R3 := R3[0xd3a01177]
 26 [-]: CALL      R3 2 2       ; R3 := R3(R4)
 27 [-]: SELF      R3 R3 K10    ; R4 := R3; R3 := R3[0xd1cbfc3e]
 28 [-]: CALL      R3 2 2       ; R3 := R3(R4)
 29 [-]: GETGLOBAL R4 K11       ; R4 := 0xc2892f65
 30 [-]: MOVE      R5 R3        ; R5 := R3
 31 [-]: CALL      R4 2 1       ; R4(R5)
 32 [-]: GETUPVAL  R4 U3        ; R4 := U3
 33 [-]: MUL       R4 R3 R4     ; R4 := R3 * R4
 34 [-]: ADD       R4 R1 R4     ; R4 := R1 + R4
 35 [-]: GETGLOBAL R5 K12       ; R5 := 0xa421af95
 36 [-]: CALL      R5 1 2       ; R5 := R5()
 37 [-]: GETGLOBAL R6 K13       ; R6 := 0x89326c93
 38 [-]: SELF      R6 R6 K14    ; R7 := R6; R6 := R6[0x722cd32c]
 39 [-]: MOVE      R8 R1        ; R8 := R1
 40 [-]: MOVE      R9 R4        ; R9 := R4
 41 [-]: MOVE      R10 R2       ; R10 := R2
 42 [-]: LOADNIL   R11 R11      ; R11 := nil
 43 [-]: MOVE      R12 R5       ; R12 := R5
 44 [-]: CALL      R6 7 2       ; R6 := R6(R7,R8,R9,R10,R11,R12)
 45 [-]: TEST      R6 0         ; if not R6 then PC := 49
 46 [-]: JMP       49           ; PC := 49
 47 [-]: RETURN    R5 2         ; return R5
 48 [-]: JMP       50           ; PC := 50
 49 [-]: RETURN    R1 2         ; return R1
 50 [-]: RETURN    R1 2         ; return R1
 51 [-]: RETURN    R0 1         ; return 


; Function #18:
;
; Name:            
; Defined at line: 392
; #Upvalues:       4
; #Parameters:     0
; Is_vararg:       0
; Max Stack Size:  6

  1 [-]: GETGLOBAL R0 K0        ; R0 := 0x7b998233
  2 [-]: GETUPVAL  R1 U0        ; R1 := U0
  3 [-]: CALL      R0 2 2       ; R0 := R0(R1)
  4 [-]: TEST      R0 1         ; if R0 then PC := 41
  5 [-]: JMP       41           ; PC := 41
  6 [-]: GETGLOBAL R0 K0        ; R0 := 0x7b998233
  7 [-]: GETUPVAL  R1 U1        ; R1 := U1
  8 [-]: CALL      R0 2 2       ; R0 := R0(R1)
  9 [-]: TEST      R0 1         ; if R0 then PC := 41
 10 [-]: JMP       41           ; PC := 41
 11 [-]: GETUPVAL  R0 U0        ; R0 := U0
 12 [-]: SELF      R0 R0 K1     ; R1 := R0; R0 := R0[0x7c09e541]
 13 [-]: CALL      R0 2 2       ; R0 := R0(R1)
 14 [-]: GETGLOBAL R1 K0        ; R1 := 0x7b998233
 15 [-]: MOVE      R2 R0        ; R2 := R0
 16 [-]: CALL      R1 2 2       ; R1 := R1(R2)
 17 [-]: TEST      R1 1         ; if R1 then PC := 41
 18 [-]: JMP       41           ; PC := 41
 19 [-]: SELF      R1 R0 K2     ; R2 := R0; R1 := R0[0xf2deaf69]
 20 [-]: GETGLOBAL R3 K3        ; R3 := 0xdb331825
 21 [-]: CALL      R1 3 2       ; R1 := R1(R2,R3)
 22 [-]: TEST      R1 0         ; if not R1 then PC := 41
 23 [-]: JMP       41           ; PC := 41
 24 [-]: SELF      R1 R0 K4     ; R2 := R0; R1 := R0[0x2b54251b]
 25 [-]: CALL      R1 2 2       ; R1 := R1(R2)
 26 [-]: GETUPVAL  R2 U2        ; R2 := U2
 27 [-]: CALL      R2 1 2       ; R2 := R2()
 28 [-]: GETGLOBAL R3 K0        ; R3 := 0x7b998233
 29 [-]: MOVE      R4 R1        ; R4 := R1
 30 [-]: CALL      R3 2 2       ; R3 := R3(R4)
 31 [-]: TEST      R3 1         ; if R3 then PC := 41
 32 [-]: JMP       41           ; PC := 41
 33 [-]: GETUPVAL  R3 U1        ; R3 := U1
 34 [-]: SELF      R3 R3 K5     ; R4 := R3; R3 := R3[0x1f420a3a]
 35 [-]: MOVE      R5 R2        ; R5 := R2
 36 [-]: CALL      R3 3 2       ; R3 := R3(R4,R5)
 37 [-]: GETUPVAL  R4 U3        ; R4 := U3
 38 [-]: LE        0 R3 R4      ; if R3 > R4 then PC := 41
 39 [-]: JMP       41           ; PC := 41
 40 [-]: RETURN    R1 2         ; return R1
 41 [-]: LOADNIL   R3 R3        ; R3 := nil
 42 [-]: RETURN    R3 2         ; return R3
 43 [-]: RETURN    R0 1         ; return 


; Function #19:
;
; Name:            
; Defined at line: 406
; #Upvalues:       8
; #Parameters:     1
; Is_vararg:       0
; Max Stack Size:  5

  1 [-]: GETGLOBAL R1 K0        ; R1 := 0x7b998233
  2 [-]: GETUPVAL  R2 U0        ; R2 := U0
  3 [-]: CALL      R1 2 2       ; R1 := R1(R2)
  4 [-]: TEST      R1 1         ; if R1 then PC := 18
  5 [-]: JMP       18           ; PC := 18
  6 [-]: GETGLOBAL R1 K0        ; R1 := 0x7b998233
  7 [-]: GETUPVAL  R2 U0        ; R2 := U0
  8 [-]: GETTABLE  R2 R2 K1     ; R2 := R2["projector"]
  9 [-]: CALL      R1 2 2       ; R1 := R1(R2)
 10 [-]: TEST      R1 1         ; if R1 then PC := 18
 11 [-]: JMP       18           ; PC := 18
 12 [-]: GETUPVAL  R1 U0        ; R1 := U0
 13 [-]: GETTABLE  R1 R1 K1     ; R1 := R1["projector"]
 14 [-]: SELF      R1 R1 K2     ; R2 := R1; R1 := R1[0x986d2ab8]
 15 [-]: GETUPVAL  R3 U1        ; R3 := U1
 16 [-]: LOADK     R4 1         ; R4 := 1.000000
 17 [-]: CALL      R1 4 1       ; R1(R2,R3,R4)
 18 [-]: GETGLOBAL R1 K0        ; R1 := 0x7b998233
 19 [-]: MOVE      R2 R0        ; R2 := R0
 20 [-]: CALL      R1 2 2       ; R1 := R1(R2)
 21 [-]: TEST      R1 1         ; if R1 then PC := 46
 22 [-]: JMP       46           ; PC := 46
 23 [-]: GETUPVAL  R1 U2        ; R1 := U2
 24 [-]: LOADK     R2 K3        ; R2 := "Get new target info"
 25 [-]: CALL      R1 2 1       ; R1(R2)
 26 [-]: GETUPVAL  R1 U4        ; R1 := U4
 27 [-]: MOVE      R2 R0        ; R2 := R0
 28 [-]: CALL      R1 2 2       ; R1 := R1(R2)
 29 [-]: SETUPVAL  R1 U3        ; U82 := R3
 30 [-]: GETUPVAL  R1 U5        ; R1 := U5
 31 [-]: MOVE      R2 R0        ; R2 := R0
 32 [-]: CALL      R1 2 2       ; R1 := R1(R2)
 33 [-]: TEST      R1 0         ; if not R1 then PC := 43
 34 [-]: JMP       43           ; PC := 43
 35 [-]: GETUPVAL  R1 U2        ; R1 := U2
 36 [-]: LOADK     R2 K4        ; R2 := "Get new TargettedWallBreachInfo"
 37 [-]: CALL      R1 2 1       ; R1(R2)
 38 [-]: GETUPVAL  R1 U6        ; R1 := U6
 39 [-]: GETUPVAL  R2 U7        ; R2 := U7
 40 [-]: CALL      R1 2 2       ; R1 := R1(R2)
 41 [-]: SETUPVAL  R1 U0        ; U82 := R0
 42 [-]: JMP       48           ; PC := 48
 43 [-]: LOADNIL   R1 R1        ; R1 := nil
 44 [-]: SETUPVAL  R1 U0        ; U82 := R0
 45 [-]: JMP       48           ; PC := 48
 46 [-]: LOADNIL   R1 R1        ; R1 := nil
 47 [-]: SETUPVAL  R1 U3        ; U82 := R3
 48 [-]: RETURN    R0 1         ; return 


; Function #20:
;
; Name:            
; Defined at line: 424
; #Upvalues:       5
; #Parameters:     0
; Is_vararg:       0
; Max Stack Size:  7

  1 [-]: GETUPVAL  R0 U0        ; R0 := U0
  2 [-]: LOADK     R1 K0        ; R1 := "FinishRepair"
  3 [-]: CALL      R0 2 1       ; R0(R1)
  4 [-]: GETGLOBAL R0 K1        ; R0 := 0x7b998233
  5 [-]: GETUPVAL  R1 U1        ; R1 := U1
  6 [-]: CALL      R0 2 2       ; R0 := R0(R1)
  7 [-]: TEST      R0 1         ; if R0 then PC := 56
  8 [-]: JMP       56           ; PC := 56
  9 [-]: GETUPVAL  R0 U1        ; R0 := U1
 10 [-]: GETTABLE  R0 R0 K2     ; R0 := R0["target"]
 11 [-]: GETGLOBAL R1 K1        ; R1 := 0x7b998233
 12 [-]: MOVE      R2 R0        ; R2 := R0
 13 [-]: CALL      R1 2 2       ; R1 := R1(R2)
 14 [-]: TEST      R1 1         ; if R1 then PC := 56
 15 [-]: JMP       56           ; PC := 56
 16 [-]: SELF      R1 R0 K3     ; R2 := R0; R1 := R0[0xed4e0128]
 17 [-]: CALL      R1 2 2       ; R1 := R1(R2)
 18 [-]: GETGLOBAL R2 K1        ; R2 := 0x7b998233
 19 [-]: GETGLOBAL R3 K4        ; R3 := 0xcb79539e
 20 [-]: CALL      R2 2 2       ; R2 := R2(R3)
 21 [-]: TEST      R2 1         ; if R2 then PC := 30
 22 [-]: JMP       30           ; PC := 30
 23 [-]: GETGLOBAL R2 K4        ; R2 := 0xcb79539e
 24 [-]: SELF      R2 R2 K5     ; R3 := R2; R2 := R2[0x8b8fb8b7]
 25 [-]: GETGLOBAL R4 K6        ; R4 := 0x0469f296
 26 [-]: LOADK     R5 K7        ; R5 := "RAILJACK_REPAIRS"
 27 [-]: CALL      R4 2 2       ; R4 := R4(R5)
 28 [-]: MOVE      R5 R1        ; R5 := R1
 29 [-]: CALL      R2 4 1       ; R2(R3,R4,R5)
 30 [-]: SELF      R2 R0 K8     ; R3 := R0; R2 := R0[0xf2deaf69]
 31 [-]: GETGLOBAL R4 K9        ; R4 := 0xa5dc8da5
 32 [-]: CALL      R2 3 2       ; R2 := R2(R3,R4)
 33 [-]: TEST      R2 0         ; if not R2 then PC := 41
 34 [-]: JMP       41           ; PC := 41
 35 [-]: SELF      R2 R0 K10    ; R3 := R0; R2 := R0[0xa2880940]
 36 [-]: CALL      R2 2 1       ; R2(R3)
 37 [-]: GETUPVAL  R2 U2        ; R2 := U2
 38 [-]: LOADNIL   R3 R3        ; R3 := nil
 39 [-]: CALL      R2 2 1       ; R2(R3)
 40 [-]: JMP       56           ; PC := 56
 41 [-]: GETUPVAL  R2 U3        ; R2 := U3
 42 [-]: GETTABLE  R2 R2 K11    ; R2 := R2[0x81e6c00c]
 43 [-]: CALL      R2 1 2       ; R2 := R2()
 44 [-]: GETGLOBAL R3 K1        ; R3 := 0x7b998233
 45 [-]: MOVE      R4 R2        ; R4 := R2
 46 [-]: CALL      R3 2 2       ; R3 := R3(R4)
 47 [-]: TEST      R3 1         ; if R3 then PC := 56
 48 [-]: JMP       56           ; PC := 56
 49 [-]: SELF      R3 R2 K12    ; R4 := R2; R3 := R2[0xaa0a8cef]
 50 [-]: MOVE      R5 R0        ; R5 := R0
 51 [-]: GETUPVAL  R6 U4        ; R6 := U4
 52 [-]: CALL      R3 4 1       ; R3(R4,R5,R6)
 53 [-]: GETUPVAL  R3 U2        ; R3 := U2
 54 [-]: LOADNIL   R4 R4        ; R4 := nil
 55 [-]: CALL      R3 2 1       ; R3(R4)
 56 [-]: LOADNIL   R3 R3        ; R3 := nil
 57 [-]: SETUPVAL  R3 U1        ; U82 := R1
 58 [-]: RETURN    R0 1         ; return 


; Function #21:
;
; Name:            
; Defined at line: 449
; #Upvalues:       19
; #Parameters:     0
; Is_vararg:       0
; Max Stack Size:  7

  1 [-]: GETGLOBAL R0 K0        ; R0 := 0x7b998233
  2 [-]: GETUPVAL  R1 U0        ; R1 := U0
  3 [-]: CALL      R0 2 2       ; R0 := R0(R1)
  4 [-]: TEST      R0 0         ; if not R0 then PC := 10
  5 [-]: JMP       10           ; PC := 10
  6 [-]: GETUPVAL  R0 U1        ; R0 := U1
  7 [-]: SELF      R0 R0 K1     ; R1 := R0; R0 := R0[0xd3a01177]
  8 [-]: CALL      R0 2 2       ; R0 := R0(R1)
  9 [-]: SETUPVAL  R0 U0        ; U82 := R0
 10 [-]: GETGLOBAL R0 K0        ; R0 := 0x7b998233
 11 [-]: GETUPVAL  R1 U0        ; R1 := U0
 12 [-]: CALL      R0 2 2       ; R0 := R0(R1)
 13 [-]: TEST      R0 1         ; if R0 then PC := 30
 14 [-]: JMP       30           ; PC := 30
 15 [-]: GETGLOBAL R0 K0        ; R0 := 0x7b998233
 16 [-]: GETUPVAL  R1 U2        ; R1 := U2
 17 [-]: CALL      R0 2 2       ; R0 := R0(R1)
 18 [-]: TEST      R0 1         ; if R0 then PC := 30
 19 [-]: JMP       30           ; PC := 30
 20 [-]: GETGLOBAL R0 K0        ; R0 := 0x7b998233
 21 [-]: GETUPVAL  R1 U3        ; R1 := U3
 22 [-]: CALL      R0 2 2       ; R0 := R0(R1)
 23 [-]: TEST      R0 1         ; if R0 then PC := 30
 24 [-]: JMP       30           ; PC := 30
 25 [-]: GETGLOBAL R0 K0        ; R0 := 0x7b998233
 26 [-]: GETUPVAL  R1 U1        ; R1 := U1
 27 [-]: CALL      R0 2 2       ; R0 := R0(R1)
 28 [-]: TEST      R0 0         ; if not R0 then PC := 31
 29 [-]: JMP       31           ; PC := 31
 30 [-]: RETURN    R0 1         ; return 
 31 [-]: GETUPVAL  R0 U4        ; R0 := U4
 32 [-]: GETUPVAL  R1 U5        ; R1 := U5
 33 [-]: CALL      R1 1 2       ; R1 := R1()
 34 [-]: SETUPVAL  R1 U4        ; U82 := R4
 35 [-]: GETUPVAL  R1 U4        ; R1 := U4
 36 [-]: EQ        0 R1 R0      ; if R1 ~= R0 then PC := 39
 37 [-]: JMP       39           ; PC := 39
 38 [-]: LOADBOOL  R1 0 1       ; R1 := false; PC := 39
 39 [-]: LOADBOOL  R1 1 0       ; R1 := true
 40 [-]: TEST      R1 0         ; if not R1 then PC := 54
 41 [-]: JMP       54           ; PC := 54
 42 [-]: GETUPVAL  R2 U6        ; R2 := U6
 43 [-]: LOADK     R3 K2        ; R3 := "New Target on MultiTool IsNull? "
 44 [-]: GETGLOBAL R4 K3        ; R4 := 0x64fb1586
 45 [-]: GETGLOBAL R5 K0        ; R5 := 0x7b998233
 46 [-]: GETUPVAL  R6 U4        ; R6 := U4
 47 [-]: CALL      R5 2 0       ; R5,... := R5(R6)
 48 [-]: CALL      R4 0 2       ; R4 := R4(R5,...)
 49 [-]: CONCAT    R3 R3 R4     ; R3 := R3 .. R4
 50 [-]: CALL      R2 2 1       ; R2(R3)
 51 [-]: GETUPVAL  R2 U7        ; R2 := U7
 52 [-]: GETUPVAL  R3 U4        ; R3 := U4
 53 [-]: CALL      R2 2 1       ; R2(R3)
 54 [-]: GETUPVAL  R2 U8        ; R2 := U8
 55 [-]: GETUPVAL  R3 U3        ; R3 := U3
 56 [-]: SELF      R3 R3 K4     ; R4 := R3; R3 := R3[0x7d4b71b1]
 57 [-]: CALL      R3 2 2       ; R3 := R3(R4)
 58 [-]: SETUPVAL  R3 U8        ; U82 := R8
 59 [-]: GETUPVAL  R3 U8        ; R3 := U8
 60 [-]: EQ        0 R3 R2      ; if R3 ~= R2 then PC := 63
 61 [-]: JMP       63           ; PC := 63
 62 [-]: LOADBOOL  R3 0 1       ; R3 := false; PC := 63
 63 [-]: LOADBOOL  R3 1 0       ; R3 := true
 64 [-]: SETUPVAL  R3 U9        ; U82 := R9
 65 [-]: GETUPVAL  R3 U1        ; R3 := U1
 66 [-]: SELF      R3 R3 K5     ; R4 := R3; R3 := R3[0x0e46e45b]
 67 [-]: LOADK     R5 0         ; R5 := 0.000000
 68 [-]: CALL      R3 3 2       ; R3 := R3(R4,R5)
 69 [-]: SETUPVAL  R3 U10       ; U82 := R10
 70 [-]: LOADBOOL  R3 0 0       ; R3 := false
 71 [-]: SETUPVAL  R3 U11       ; U82 := R11
 72 [-]: GETGLOBAL R3 K0        ; R3 := 0x7b998233
 73 [-]: GETUPVAL  R4 U4        ; R4 := U4
 74 [-]: CALL      R3 2 2       ; R3 := R3(R4)
 75 [-]: TEST      R3 1         ; if R3 then PC := 79
 76 [-]: JMP       79           ; PC := 79
 77 [-]: LOADBOOL  R3 1 0       ; R3 := true
 78 [-]: SETUPVAL  R3 U11       ; U82 := R11
 79 [-]: GETGLOBAL R3 K0        ; R3 := 0x7b998233
 80 [-]: GETUPVAL  R4 U4        ; R4 := U4
 81 [-]: CALL      R3 2 2       ; R3 := R3(R4)
 82 [-]: TEST      R3 1         ; if R3 then PC := 132
 83 [-]: JMP       132          ; PC := 132
 84 [-]: GETGLOBAL R3 K0        ; R3 := 0x7b998233
 85 [-]: GETUPVAL  R4 U12       ; R4 := U12
 86 [-]: CALL      R3 2 2       ; R3 := R3(R4)
 87 [-]: TEST      R3 1         ; if R3 then PC := 132
 88 [-]: JMP       132          ; PC := 132
 89 [-]: GETUPVAL  R3 U4        ; R3 := U4
 90 [-]: SELF      R3 R3 K7     ; R4 := R3; R3 := R3[0x0454650e]
 91 [-]: CALL      R3 2 2       ; R3 := R3(R4)
 92 [-]: GETGLOBAL R4 K0        ; R4 := 0x7b998233
 93 [-]: GETGLOBAL R5 K8        ; R5 := _T
 94 [-]: GETTABLE  R5 R5 K9     ; R5 := R5["multiToolAmmoReduction"]
 95 [-]: CALL      R4 2 2       ; R4 := R4(R5)
 96 [-]: TEST      R4 1         ; if R4 then PC := 101
 97 [-]: JMP       101          ; PC := 101
 98 [-]: GETGLOBAL R4 K8        ; R4 := _T
 99 [-]: GETTABLE  R4 R4 K9     ; R4 := R4["multiToolAmmoReduction"]
100 [-]: MUL       R3 R3 R4     ; R3 := R3 * R4
101 [-]: GETUPVAL  R4 U14       ; R4 := U14
102 [-]: CALL      R4 1 2       ; R4 := R4()
103 [-]: LE        1 R3 R4      ; if R3 <= R4 then PC := 106
104 [-]: JMP       106          ; PC := 106
105 [-]: LOADBOOL  R4 0 1       ; R4 := false; PC := 106
106 [-]: LOADBOOL  R4 1 0       ; R4 := true
107 [-]: SETUPVAL  R4 U13       ; U82 := R13
108 [-]: GETUPVAL  R4 U15       ; R4 := U15
109 [-]: GETUPVAL  R5 U4        ; R5 := U4
110 [-]: CALL      R4 2 2       ; R4 := R4(R5)
111 [-]: TEST      R4 0         ; if not R4 then PC := 118
112 [-]: JMP       118          ; PC := 118
113 [-]: GETUPVAL  R4 U16       ; R4 := U16
114 [-]: GETUPVAL  R5 U12       ; R5 := U12
115 [-]: CALL      R4 2 2       ; R4 := R4(R5)
116 [-]: SETUPVAL  R4 U12       ; U82 := R12
117 [-]: JMP       122          ; PC := 122
118 [-]: GETUPVAL  R4 U17       ; R4 := U17
119 [-]: GETUPVAL  R5 U12       ; R5 := U12
120 [-]: CALL      R4 2 2       ; R4 := R4(R5)
121 [-]: SETUPVAL  R4 U12       ; U82 := R12
122 [-]: GETUPVAL  R4 U12       ; R4 := U12
123 [-]: GETTABLE  R4 R4 K10    ; R4 := R4["progression"]
124 [-]: LE        0 K11 R4     ; if 1.000000 > R4 then PC := 136
125 [-]: JMP       136          ; PC := 136
126 [-]: GETUPVAL  R4 U6        ; R4 := U6
127 [-]: LOADK     R5 K12       ; R5 := "mCurrentTargetRepairInfo.progression >= 1.0"
128 [-]: CALL      R4 2 1       ; R4(R5)
129 [-]: GETUPVAL  R4 U18       ; R4 := U18
130 [-]: CALL      R4 1 1       ; R4()
131 [-]: JMP       136          ; PC := 136
132 [-]: LOADNIL   R4 R4        ; R4 := nil
133 [-]: SETUPVAL  R4 U12       ; U82 := R12
134 [-]: LOADBOOL  R4 0 0       ; R4 := false
135 [-]: SETUPVAL  R4 U13       ; U82 := R13
136 [-]: GETGLOBAL R4 K8        ; R4 := _T
137 [-]: GETTABLE  R4 R4 K13    ; R4 := R4["MultiTool"]
138 [-]: GETUPVAL  R5 U12       ; R5 := U12
139 [-]: SETTABLE  R4 K14 R5    ; R4["CurrentTargetRepairInfo"] := R5
140 [-]: GETGLOBAL R4 K8        ; R4 := _T
141 [-]: GETTABLE  R4 R4 K13    ; R4 := R4["MultiTool"]
142 [-]: GETUPVAL  R5 U14       ; R5 := U14
143 [-]: CALL      R5 1 2       ; R5 := R5()
144 [-]: SETTABLE  R4 K15 R5    ; R4["Revolite"] := R5
145 [-]: GETGLOBAL R4 K8        ; R4 := _T
146 [-]: GETTABLE  R4 R4 K13    ; R4 := R4["MultiTool"]
147 [-]: GETUPVAL  R5 U13       ; R5 := U13
148 [-]: SETTABLE  R4 K16 R5    ; R4["HasEnoughRevolite"] := R5
149 [-]: RETURN    R0 1         ; return 


; Function #22:
;
; Name:            
; Defined at line: 503
; #Upvalues:       9
; #Parameters:     1
; Is_vararg:       0
; Max Stack Size:  6

  1 [-]: GETUPVAL  R1 U0        ; R1 := U0
  2 [-]: LOADK     R2 K0        ; R2 := "OnEquipped master? "
  3 [-]: GETGLOBAL R3 K1        ; R3 := 0x64fb1586
  4 [-]: GETGLOBAL R4 K2        ; R4 := 0x89326c93
  5 [-]: SELF      R4 R4 K3     ; R5 := R4; R4 := R4[0x18d05d30]
  6 [-]: CALL      R4 2 0       ; R4,... := R4(R5)
  7 [-]: CALL      R3 0 2       ; R3 := R3(R4,...)
  8 [-]: CONCAT    R2 R2 R3     ; R2 := R2 .. R3
  9 [-]: CALL      R1 2 1       ; R1(R2)
 10 [-]: GETUPVAL  R1 U1        ; R1 := U1
 11 [-]: CALL      R1 1 1       ; R1()
 12 [-]: SETUPVAL  R0 U2        ; U82 := R2
 13 [-]: GETUPVAL  R1 U2        ; R1 := U2
 14 [-]: SELF      R1 R1 K4     ; R2 := R1; R1 := R1[0x20833f15]
 15 [-]: CALL      R1 2 2       ; R1 := R1(R2)
 16 [-]: SETUPVAL  R1 U3        ; U82 := R3
 17 [-]: GETGLOBAL R1 K5        ; R1 := 0x7b998233
 18 [-]: GETUPVAL  R2 U3        ; R2 := U3
 19 [-]: CALL      R1 2 2       ; R1 := R1(R2)
 20 [-]: TEST      R1 1         ; if R1 then PC := 59
 21 [-]: JMP       59           ; PC := 59
 22 [-]: GETUPVAL  R1 U3        ; R1 := U3
 23 [-]: SELF      R1 R1 K6     ; R2 := R1; R1 := R1[0xf7028472]
 24 [-]: GETUPVAL  R3 U5        ; R3 := U5
 25 [-]: GETTABLE  R3 R3 K7     ; R3 := R3["sSkillMultiToolExpert"]
 26 [-]: CALL      R1 3 2       ; R1 := R1(R2,R3)
 27 [-]: SETUPVAL  R1 U4        ; U82 := R4
 28 [-]: GETUPVAL  R1 U3        ; R1 := U3
 29 [-]: SELF      R1 R1 K8     ; R2 := R1; R1 := R1[0xde321e6f]
 30 [-]: CALL      R1 2 2       ; R1 := R1(R2)
 31 [-]: SETUPVAL  R1 U6        ; U82 := R6
 32 [-]: GETUPVAL  R1 U2        ; R1 := U2
 33 [-]: SELF      R1 R1 K9     ; R2 := R1; R1 := R1[0x870e163a]
 34 [-]: CALL      R1 2 2       ; R1 := R1(R2)
 35 [-]: SELF      R1 R1 K10    ; R2 := R1; R1 := R1[0xd60b781a]
 36 [-]: CALL      R1 2 2       ; R1 := R1(R2)
 37 [-]: SETUPVAL  R1 U7        ; U82 := R7
 38 [-]: GETGLOBAL R1 K5        ; R1 := 0x7b998233
 39 [-]: GETUPVAL  R2 U2        ; R2 := U2
 40 [-]: CALL      R1 2 2       ; R1 := R1(R2)
 41 [-]: TEST      R1 1         ; if R1 then PC := 59
 42 [-]: JMP       59           ; PC := 59
 43 [-]: GETGLOBAL R1 K5        ; R1 := 0x7b998233
 44 [-]: GETUPVAL  R2 U3        ; R2 := U3
 45 [-]: CALL      R1 2 2       ; R1 := R1(R2)
 46 [-]: TEST      R1 1         ; if R1 then PC := 59
 47 [-]: JMP       59           ; PC := 59
 48 [-]: GETUPVAL  R1 U3        ; R1 := U3
 49 [-]: SELF      R1 R1 K11    ; R2 := R1; R1 := R1[0x4accf179]
 50 [-]: CALL      R1 2 2       ; R1 := R1(R2)
 51 [-]: TEST      R1 0         ; if not R1 then PC := 59
 52 [-]: JMP       59           ; PC := 59
 53 [-]: GETUPVAL  R1 U8        ; R1 := U8
 54 [-]: CALL      R1 1 1       ; R1()
 55 [-]: GETGLOBAL R1 K12       ; R1 := 0xcbd666e1
 56 [-]: LOADK     R2 0         ; R2 := 0.000000
 57 [-]: CALL      R1 2 1       ; R1(R2)
 58 [-]: JMP       38           ; PC := 38
 59 [-]: RETURN    R0 1         ; return 


; Function #23:
;
; Name:            
; Defined at line: 526
; #Upvalues:       1
; #Parameters:     2
; Is_vararg:       0
; Max Stack Size:  14

  1 [-]: GETGLOBAL R2 K0        ; R2 := 0x89326c93
  2 [-]: SELF      R2 R2 K1     ; R3 := R2; R2 := R2[0x18d05d30]
  3 [-]: CALL      R2 2 2       ; R2 := R2(R3)
  4 [-]: TEST      R2 0         ; if not R2 then PC := 138
  5 [-]: JMP       138          ; PC := 138
  6 [-]: SELF      R2 R0 K2     ; R3 := R0; R2 := R0[0x0454650e]
  7 [-]: CALL      R2 2 2       ; R2 := R2(R3)
  8 [-]: GETGLOBAL R3 K3        ; R3 := 0x7b998233
  9 [-]: GETGLOBAL R4 K4        ; R4 := _T
 10 [-]: GETTABLE  R4 R4 K5     ; R4 := R4["multiToolAmmoReduction"]
 11 [-]: CALL      R3 2 2       ; R3 := R3(R4)
 12 [-]: TEST      R3 1         ; if R3 then PC := 17
 13 [-]: JMP       17           ; PC := 17
 14 [-]: GETGLOBAL R3 K4        ; R3 := _T
 15 [-]: GETTABLE  R3 R3 K5     ; R3 := R3["multiToolAmmoReduction"]
 16 [-]: MUL       R2 R2 R3     ; R2 := R2 * R3
 17 [-]: GETGLOBAL R3 K3        ; R3 := 0x7b998233
 18 [-]: MOVE      R4 R1        ; R4 := R1
 19 [-]: CALL      R3 2 2       ; R3 := R3(R4)
 20 [-]: TEST      R3 1         ; if R3 then PC := 67
 21 [-]: JMP       67           ; PC := 67
 22 [-]: GETGLOBAL R3 K6        ; R3 := 0xb5a654de
 23 [-]: TEST      R3 0         ; if not R3 then PC := 30
 24 [-]: JMP       30           ; PC := 30
 25 [-]: SELF      R3 R1 K7     ; R4 := R1; R3 := R1[0xf2deaf69]
 26 [-]: GETGLOBAL R5 K8        ; R5 := gLotusNpcAvatarType
 27 [-]: CALL      R3 3 2       ; R3 := R3(R4,R5)
 28 [-]: TEST      R3 1         ; if R3 then PC := 67
 29 [-]: JMP       67           ; PC := 67
 30 [-]: SELF      R3 R1 K7     ; R4 := R1; R3 := R1[0xf2deaf69]
 31 [-]: GETGLOBAL R5 K9        ; R5 := gLotusOperatorAvatarType
 32 [-]: CALL      R3 3 2       ; R3 := R3(R4,R5)
 33 [-]: TEST      R3 0         ; if not R3 then PC := 56
 34 [-]: JMP       56           ; PC := 56
 35 [-]: SELF      R3 R1 K10    ; R4 := R1; R3 := R1[0x5b89142c]
 36 [-]: CALL      R3 2 2       ; R3 := R3(R4)
 37 [-]: GETGLOBAL R4 K3        ; R4 := 0x7b998233
 38 [-]: MOVE      R5 R3        ; R5 := R3
 39 [-]: CALL      R4 2 2       ; R4 := R4(R5)
 40 [-]: TEST      R4 1         ; if R4 then PC := 67
 41 [-]: JMP       67           ; PC := 67
 42 [-]: SELF      R4 R3 K11    ; R5 := R3; R4 := R3[0xa534c3ac]
 43 [-]: CALL      R4 2 2       ; R4 := R4(R5)
 44 [-]: GETGLOBAL R5 K3        ; R5 := 0x7b998233
 45 [-]: MOVE      R6 R4        ; R6 := R4
 46 [-]: CALL      R5 2 2       ; R5 := R5(R6)
 47 [-]: TEST      R5 1         ; if R5 then PC := 67
 48 [-]: JMP       67           ; PC := 67
 49 [-]: SELF      R5 R4 K12    ; R6 := R4; R5 := R4[0xde321e6f]
 50 [-]: CALL      R5 2 2       ; R5 := R5(R6)
 51 [-]: SELF      R5 R5 K13    ; R6 := R5; R5 := R5[0x936fc1c2]
 52 [-]: GETGLOBAL R7 K14       ; R7 := 0x186b715b
 53 [-]: MOVE      R8 R2        ; R8 := R2
 54 [-]: CALL      R5 4 1       ; R5(R6,R7,R8)
 55 [-]: JMP       67           ; PC := 67
 56 [-]: SELF      R5 R1 K12    ; R6 := R1; R5 := R1[0xde321e6f]
 57 [-]: CALL      R5 2 2       ; R5 := R5(R6)
 58 [-]: GETGLOBAL R6 K3        ; R6 := 0x7b998233
 59 [-]: MOVE      R7 R5        ; R7 := R5
 60 [-]: CALL      R6 2 2       ; R6 := R6(R7)
 61 [-]: TEST      R6 1         ; if R6 then PC := 67
 62 [-]: JMP       67           ; PC := 67
 63 [-]: SELF      R6 R5 K13    ; R7 := R5; R6 := R5[0x936fc1c2]
 64 [-]: GETGLOBAL R8 K14       ; R8 := 0x186b715b
 65 [-]: MOVE      R9 R2        ; R9 := R2
 66 [-]: CALL      R6 4 1       ; R6(R7,R8,R9)
 67 [-]: GETGLOBAL R6 K3        ; R6 := 0x7b998233
 68 [-]: MOVE      R7 R1        ; R7 := R1
 69 [-]: CALL      R6 2 2       ; R6 := R6(R7)
 70 [-]: TEST      R6 1         ; if R6 then PC := 138
 71 [-]: JMP       138          ; PC := 138
 72 [-]: SELF      R6 R1 K12    ; R7 := R1; R6 := R1[0xde321e6f]
 73 [-]: CALL      R6 2 2       ; R6 := R6(R7)
 74 [-]: GETGLOBAL R7 K3        ; R7 := 0x7b998233
 75 [-]: MOVE      R8 R6        ; R8 := R6
 76 [-]: CALL      R7 2 2       ; R7 := R7(R8)
 77 [-]: TEST      R7 1         ; if R7 then PC := 118
 78 [-]: JMP       118          ; PC := 118
 79 [-]: SELF      R7 R0 K15    ; R8 := R0; R7 := R0[0xea969abd]
 80 [-]: CALL      R7 2 2       ; R7 := R7(R8)
 81 [-]: GETGLOBAL R8 K4        ; R8 := _T
 82 [-]: GETTABLE  R8 R8 K16    ; R8 := R8["NpcRepairXPRewarded"]
 83 [-]: EQ        0 R8 K17     ; if R8 ~= nil then PC := 87
 84 [-]: JMP       87           ; PC := 87
 85 [-]: GETGLOBAL R8 K4        ; R8 := _T
 86 [-]: SETTABLE  R8 K16 K18   ; R8["NpcRepairXPRewarded"] := 0.000000
 87 [-]: SELF      R8 R1 K19    ; R9 := R1; R8 := R1[0x35844cf2]
 88 [-]: CALL      R8 2 2       ; R8 := R8(R9)
 89 [-]: TEST      R8 1         ; if R8 then PC := 96
 90 [-]: JMP       96           ; PC := 96
 91 [-]: GETGLOBAL R8 K4        ; R8 := _T
 92 [-]: GETTABLE  R8 R8 K16    ; R8 := R8["NpcRepairXPRewarded"]
 93 [-]: GETGLOBAL R9 K20       ; R9 := 0x5fa5788e
 94 [-]: LT        0 R8 R9      ; if R8 >= R9 then PC := 118
 95 [-]: JMP       118          ; PC := 118
 96 [-]: SELF      R8 R1 K19    ; R9 := R1; R8 := R1[0x35844cf2]
 97 [-]: CALL      R8 2 2       ; R8 := R8(R9)
 98 [-]: TEST      R8 1         ; if R8 then PC := 105
 99 [-]: JMP       105          ; PC := 105
100 [-]: GETGLOBAL R8 K4        ; R8 := _T
101 [-]: GETGLOBAL R9 K4        ; R9 := _T
102 [-]: GETTABLE  R9 R9 K16    ; R9 := R9["NpcRepairXPRewarded"]
103 [-]: ADD       R9 R9 K21    ; R9 := R9 + 1.000000
104 [-]: SETTABLE  R8 K16 R9    ; R8["NpcRepairXPRewarded"] := R9
105 [-]: SELF      R8 R6 K22    ; R9 := R6; R8 := R6[0x8db2624f]
106 [-]: MOVE      R10 R7       ; R10 := R7
107 [-]: MOVE      R11 R1       ; R11 := R1
108 [-]: GETUPVAL  R12 U0       ; R12 := U0
109 [-]: LOADBOOL  R13 0 0      ; R13 := false
110 [-]: CALL      R8 6 1       ; R8(R9,R10,R11,R12,R13)
111 [-]: SELF      R8 R6 K23    ; R9 := R6; R8 := R6[0x2bfc9e36]
112 [-]: MOVE      R10 R7       ; R10 := R7
113 [-]: MOVE      R11 R1       ; R11 := R1
114 [-]: SELF      R12 R1 K24   ; R13 := R1; R12 := R1[0xcde10c4a]
115 [-]: CALL      R12 2 2      ; R12 := R12(R13)
116 [-]: GETUPVAL  R13 U0       ; R13 := U0
117 [-]: CALL      R8 6 1       ; R8(R9,R10,R11,R12,R13)
118 [-]: SELF      R8 R1 K25    ; R9 := R1; R8 := R1[0x5e651723]
119 [-]: CALL      R8 2 2       ; R8 := R8(R9)
120 [-]: GETGLOBAL R9 K3        ; R9 := 0x7b998233
121 [-]: MOVE      R10 R8       ; R10 := R8
122 [-]: CALL      R9 2 2       ; R9 := R9(R10)
123 [-]: TEST      R9 1         ; if R9 then PC := 138
124 [-]: JMP       138          ; PC := 138
125 [-]: SELF      R9 R1 K19    ; R10 := R1; R9 := R1[0x35844cf2]
126 [-]: CALL      R9 2 2       ; R9 := R9(R10)
127 [-]: TEST      R9 0         ; if not R9 then PC := 138
128 [-]: JMP       138          ; PC := 138
129 [-]: SELF      R9 R8 K26    ; R10 := R8; R9 := R8[0x61c34fa9]
130 [-]: CALL      R9 2 2       ; R9 := R9(R10)
131 [-]: GETGLOBAL R10 K3       ; R10 := 0x7b998233
132 [-]: MOVE      R11 R9       ; R11 := R9
133 [-]: CALL      R10 2 2      ; R10 := R10(R11)
134 [-]: TEST      R10 1        ; if R10 then PC := 138
135 [-]: JMP       138          ; PC := 138
136 [-]: SELF      R10 R9 K27   ; R11 := R9; R10 := R9[0xd1372c89]
137 [-]: CALL      R10 2 1      ; R10(R11)
138 [-]: RETURN    R0 1         ; return 


; Function #24:
;
; Name:            
; Defined at line: 580
; #Upvalues:       0
; #Parameters:     2
; Is_vararg:       0
; Max Stack Size:  2

  1 [-]: RETURN    R0 1         ; return 


