; Name:            
; Defined at line: 1
; #Upvalues:       0
; #Parameters:     0
; Is_vararg:       1
; Max Stack Size:  3

            1 [-]: GETIMPORT R0 1 [nil]
       2 [-]: LOADK R1 K2 ["/Lotus/Powersuits/Harlequin/IllusionMirrorAvatar"]
       3 [-]: CALL R0 1 1  
       4 [-]: GETIMPORT R1 4 [nil]
       5 [-]: LOADK R2 K5 ["impactPoint"]
       6 [-]: CALL R1 1 1  
       7 [-]: DUPCLOSURE R2 K6 []
       8 [-]: SETGLOBAL R2 K7 ["KillAttached"]
       9 [-]: DUPCLOSURE R2 K8 []
      10 [-]: SETGLOBAL R2 K9 ["KillAttachedOnSelf"]
      11 [-]: DUPCLOSURE R2 K10 []
      12 [-]: SETGLOBAL R2 K11 ["KillAttachedToGameCamera"]
      13 [-]: DUPCLOSURE R2 K12 []
      14 [-]: SETGLOBAL R2 K13 ["KillThisAttachedToParent"]
      15 [-]: DUPCLOSURE R2 K14 []
      16 [-]: SETGLOBAL R2 K15 ["KillArrayAttachedToParent"]
      17 [-]: DUPCLOSURE R2 K16 []
      18 [-]: SETGLOBAL R2 K17 ["KillArrayAttachedToSelf"]
      19 [-]: DUPCLOSURE R2 K18 []
      20 [-]: SETGLOBAL R2 K19 ["KillThisAttachedToParentOnBone"]
      21 [-]: DUPCLOSURE R2 K20 []
      22 [-]: SETGLOBAL R2 K21 ["KillAttachedArray"]
      23 [-]: DUPCLOSURE R2 K22 []
      24 [-]: SETGLOBAL R2 K23 ["Attach"]
      25 [-]: DUPCLOSURE R2 K24 []
      26 [-]: SETGLOBAL R2 K25 ["AttachArray"]
      27 [-]: DUPCLOSURE R2 K26 []
      28 [-]: SETGLOBAL R2 K27 ["AttachProjector"]
      29 [-]: DUPCLOSURE R2 K28 []
      30 [-]: SETGLOBAL R2 K29 ["KillParent"]
      31 [-]: DUPCLOSURE R2 K30 []
      32 [-]: SETGLOBAL R2 K31 ["AttachToMe"]
      33 [-]: DUPCLOSURE R2 K32 []
      34 [-]: SETGLOBAL R2 K33 ["AttachToTouchingAvatar"]
      35 [-]: DUPCLOSURE R2 K34 []
      36 [-]: SETGLOBAL R2 K35 ["AttachToAvatarFromBehavior"]
      37 [-]: DUPCLOSURE R2 K36 []
      38 [-]: MOVE R0 R0   
      39 [-]: SETGLOBAL R2 K37 ["KillParticleCenterTypeIfIllusionAvatar"]
      40 [-]: DUPCLOSURE R2 K38 []
      41 [-]: SETGLOBAL R2 K39 ["EnableDisableAttachment"]
      42 [-]: DUPCLOSURE R2 K40 []
      43 [-]: SETGLOBAL R2 K41 ["EnableDisableAttachmentOnParent"]
      44 [-]: DUPCLOSURE R2 K42 []
      45 [-]: SETGLOBAL R2 K43 ["SwapParentMesh"]
      46 [-]: DUPCLOSURE R2 K44 []
      47 [-]: MOVE R0 R1   
      48 [-]: SETGLOBAL R2 K45 ["ProjUpdateWorldPos"]
      49 [-]: DUPCLOSURE R2 K46 []
      50 [-]: SETGLOBAL R2 K47 ["SleepToDisable"]
      51 [-]: DUPCLOSURE R2 K48 []
      52 [-]: SETGLOBAL R2 K49 ["ApplyToParentIfLocal"]
      53 [-]: DUPCLOSURE R2 K50 []
      54 [-]: SETGLOBAL R2 K51 ["AttachBeamsToThis"]
      55 [-]: DUPCLOSURE R2 K52 []
      56 [-]: SETGLOBAL R2 K53 ["BeamEndPoint"]
      57 [-]: DUPCLOSURE R2 K54 []
      58 [-]: SETGLOBAL R2 K55 ["UnattachMe"]
      59 [-]: RETURN R0 0  


; Name:            
; Defined at line: 26
; #Upvalues:       0
; #Parameters:     0
; Is_vararg:       0
; Max Stack Size:  3

       0 [-]: GETIMPORT R1 1 [nil]
       1 [-]: FASTCALL1 62 R1 L0
       2 [-]: GETIMPORT R0 3 [nil]
       3 [-]: CALL R0 1 1  
L 0:   4 [-]: JUMPIF R0 L2 
       5 [-]: GETIMPORT R0 5 [nil]
       6 [-]: GETIMPORT R2 1 [nil]
       7 [-]: NAMECALL R0 R0 K6 [0xC9F6A7D7]
       8 [-]: CALL R0 2 1  
       9 [-]: FASTCALL1 62 R0 L1
      10 [-]: MOVE R2 R0   
      11 [-]: GETIMPORT R1 3 [nil]
      12 [-]: CALL R1 1 1  
L 1:  13 [-]: JUMPIF R1 L2 
      14 [-]: NAMECALL R1 R0 K7 [0xA2880940]
      15 [-]: CALL R1 1 0  
L 2:  16 [-]: RETURN R0 0  


; Name:            
; Defined at line: 35
; #Upvalues:       0
; #Parameters:     1
; Is_vararg:       0
; Max Stack Size:  4

       0 [-]: GETIMPORT R2 1 [nil]
       1 [-]: FASTCALL1 62 R2 L0
       2 [-]: GETIMPORT R1 3 [nil]
       3 [-]: CALL R1 1 1  
L 0:   4 [-]: JUMPIF R1 L2 
       5 [-]: GETIMPORT R3 1 [nil]
       6 [-]: NAMECALL R1 R0 K4 [0xC9F6A7D7]
       7 [-]: CALL R1 2 1  
       8 [-]: FASTCALL1 62 R1 L1
       9 [-]: MOVE R3 R1   
      10 [-]: GETIMPORT R2 3 [nil]
      11 [-]: CALL R2 1 1  
L 1:  12 [-]: JUMPIF R2 L2 
      13 [-]: NAMECALL R2 R1 K5 [0xA2880940]
      14 [-]: CALL R2 1 0  
L 2:  15 [-]: RETURN R0 0  


; Name:            
; Defined at line: 44
; #Upvalues:       0
; #Parameters:     0
; Is_vararg:       0
; Max Stack Size:  4

       0 [-]: GETIMPORT R0 1 [nil]
       1 [-]: GETIMPORT R1 3 [nil]
       2 [-]: CALL R0 1 0  
       3 [-]: GETIMPORT R0 5 [nil]
       4 [-]: NAMECALL R0 R0 K6 [0xB4364067]
       5 [-]: CALL R0 1 1  
       6 [-]: GETIMPORT R2 8 [nil]
       7 [-]: FASTCALL1 62 R2 L0
       8 [-]: GETIMPORT R1 10 [nil]
       9 [-]: CALL R1 1 1  
L 0:  10 [-]: JUMPIF R1 L3 
      11 [-]: FASTCALL1 62 R0 L1
      12 [-]: MOVE R2 R0   
      13 [-]: GETIMPORT R1 10 [nil]
      14 [-]: CALL R1 1 1  
L 1:  15 [-]: JUMPIF R1 L3 
      16 [-]: GETIMPORT R3 8 [nil]
      17 [-]: NAMECALL R1 R0 K11 [0xC9F6A7D7]
      18 [-]: CALL R1 2 1  
      19 [-]: FASTCALL1 62 R1 L2
      20 [-]: MOVE R3 R1   
      21 [-]: GETIMPORT R2 10 [nil]
      22 [-]: CALL R2 1 1  
L 2:  23 [-]: JUMPIF R2 L3 
      24 [-]: NAMECALL R2 R1 K12 [0xA2880940]
      25 [-]: CALL R2 1 0  
L 3:  26 [-]: RETURN R0 0  


; Name:            
; Defined at line: 55
; #Upvalues:       0
; #Parameters:     1
; Is_vararg:       0
; Max Stack Size:  8

       0 [-]: NAMECALL R1 R0 K0 [0x2B54251B]
       1 [-]: CALL R1 1 1  
       2 [-]: FASTCALL1 62 R1 L0
       3 [-]: MOVE R3 R1   
       4 [-]: GETIMPORT R2 2 [nil]
       5 [-]: CALL R2 1 1  
L 0:   6 [-]: JUMPIF R2 L4 
       7 [-]: GETIMPORT R3 4 [nil]
       8 [-]: FASTCALL1 62 R3 L1
       9 [-]: GETIMPORT R2 2 [nil]
      10 [-]: CALL R2 1 1  
L 1:  11 [-]: JUMPIF R2 L4 
      12 [-]: GETIMPORT R4 4 [nil]
      13 [-]: NAMECALL R2 R1 K5 [0xC9F6A7D7]
      14 [-]: CALL R2 2 1  
      15 [-]: FASTCALL1 62 R2 L2
      16 [-]: MOVE R4 R2   
      17 [-]: GETIMPORT R3 2 [nil]
      18 [-]: CALL R3 1 1  
L 2:  19 [-]: JUMPIF R3 L4 
      20 [-]: GETIMPORT R3 7 [nil]
      21 [-]: JUMPIFNOT R3 L3
      22 [-]: LOADN R5 0   
      23 [-]: LOADN R6 0   
      24 [-]: LOADB R7 0   
      25 [-]: NAMECALL R3 R2 K8 [0x052A3A7C]
      26 [-]: CALL R3 4 0  
      27 [-]: RETURN R0 0  
L 3:  28 [-]: NAMECALL R3 R2 K9 [0xA2880940]
      29 [-]: CALL R3 1 0  
L 4:  30 [-]: RETURN R0 0  


; Name:            
; Defined at line: 70
; #Upvalues:       0
; #Parameters:     1
; Is_vararg:       0
; Max Stack Size:  11

       0 [-]: NAMECALL R1 R0 K0 [0x2B54251B]
       1 [-]: CALL R1 1 1  
       2 [-]: FASTCALL1 62 R1 L0
       3 [-]: MOVE R3 R1   
       4 [-]: GETIMPORT R2 2 [nil]
       5 [-]: CALL R2 1 1  
L 0:   6 [-]: JUMPIF R2 L6 
       7 [-]: GETIMPORT R3 4 [nil]
       8 [-]: FASTCALL1 62 R3 L1
       9 [-]: GETIMPORT R2 2 [nil]
      10 [-]: CALL R2 1 1  
L 1:  11 [-]: JUMPIF R2 L6 
      12 [-]: LOADN R4 1   
      13 [-]: GETIMPORT R5 4 [nil]
      14 [-]: LENGTH R2 R5 
      15 [-]: LOADN R3 1   
      16 [-]: FORNPREP R2 L6
L 2:  17 [-]: GETIMPORT R8 4 [nil]
      18 [-]: GETTABLE R7 R8 R4
      19 [-]: NAMECALL R5 R1 K5 [0xC9F6A7D7]
      20 [-]: CALL R5 2 1  
      21 [-]: FASTCALL1 62 R5 L3
      22 [-]: MOVE R7 R5   
      23 [-]: GETIMPORT R6 2 [nil]
      24 [-]: CALL R6 1 1  
L 3:  25 [-]: JUMPIF R6 L5 
      26 [-]: GETIMPORT R6 7 [nil]
      27 [-]: JUMPIFNOT R6 L4
      28 [-]: LOADN R8 0   
      29 [-]: LOADN R9 0   
      30 [-]: LOADB R10 0  
      31 [-]: NAMECALL R6 R5 K8 [0x052A3A7C]
      32 [-]: CALL R6 4 0  
      33 [-]: JUMP L5
     
L 4:  34 [-]: NAMECALL R6 R5 K9 [0xA2880940]
      35 [-]: CALL R6 1 0  
L 5:  36 [-]: FORNLOOP R2 L2
L 6:  37 [-]: RETURN R0 0  


; Name:            
; Defined at line: 86
; #Upvalues:       0
; #Parameters:     1
; Is_vararg:       0
; Max Stack Size:  10

       0 [-]: FASTCALL1 62 R0 L0
       1 [-]: MOVE R2 R0   
       2 [-]: GETIMPORT R1 1 [nil]
       3 [-]: CALL R1 1 1  
L 0:   4 [-]: JUMPIF R1 L6 
       5 [-]: GETIMPORT R2 3 [nil]
       6 [-]: FASTCALL1 62 R2 L1
       7 [-]: GETIMPORT R1 1 [nil]
       8 [-]: CALL R1 1 1  
L 1:   9 [-]: JUMPIF R1 L6 
      10 [-]: LOADN R3 1   
      11 [-]: GETIMPORT R4 3 [nil]
      12 [-]: LENGTH R1 R4 
      13 [-]: LOADN R2 1   
      14 [-]: FORNPREP R1 L6
L 2:  15 [-]: GETIMPORT R7 3 [nil]
      16 [-]: GETTABLE R6 R7 R3
      17 [-]: NAMECALL R4 R0 K4 [0xC9F6A7D7]
      18 [-]: CALL R4 2 1  
      19 [-]: FASTCALL1 62 R4 L3
      20 [-]: MOVE R6 R4   
      21 [-]: GETIMPORT R5 1 [nil]
      22 [-]: CALL R5 1 1  
L 3:  23 [-]: JUMPIF R5 L5 
      24 [-]: GETIMPORT R5 6 [nil]
      25 [-]: JUMPIFNOT R5 L4
      26 [-]: LOADN R7 0   
      27 [-]: LOADN R8 0   
      28 [-]: LOADB R9 0   
      29 [-]: NAMECALL R5 R4 K7 [0x052A3A7C]
      30 [-]: CALL R5 4 0  
      31 [-]: JUMP L5
     
L 4:  32 [-]: NAMECALL R5 R4 K8 [0xA2880940]
      33 [-]: CALL R5 1 0  
L 5:  34 [-]: FORNLOOP R1 L2
L 6:  35 [-]: RETURN R0 0  


; Name:            
; Defined at line: 101
; #Upvalues:       0
; #Parameters:     1
; Is_vararg:       0
; Max Stack Size:  8

       0 [-]: GETIMPORT R2 1 [nil]
       1 [-]: FASTCALL1 62 R2 L0
       2 [-]: GETIMPORT R1 3 [nil]
       3 [-]: CALL R1 1 1  
L 0:   4 [-]: JUMPIF R1 L1 
       5 [-]: GETIMPORT R1 1 [nil]
       6 [-]: GETIMPORT R2 5 [nil]
       7 [-]: JUMPIFNOTEQ R1 R2 L2
L 1:   8 [-]: RETURN R0 0  
L 2:   9 [-]: NAMECALL R1 R0 K6 [0x2B54251B]
      10 [-]: CALL R1 1 1  
      11 [-]: FASTCALL1 62 R1 L3
      12 [-]: MOVE R3 R1   
      13 [-]: GETIMPORT R2 3 [nil]
      14 [-]: CALL R2 1 1  
L 3:  15 [-]: JUMPIF R2 L9 
      16 [-]: GETIMPORT R3 8 [nil]
      17 [-]: FASTCALL1 62 R3 L4
      18 [-]: GETIMPORT R2 3 [nil]
      19 [-]: CALL R2 1 1  
L 4:  20 [-]: JUMPIF R2 L9 
      21 [-]: GETIMPORT R4 8 [nil]
      22 [-]: NAMECALL R2 R1 K9 [0xC1595BD5]
      23 [-]: CALL R2 2 1  
      24 [-]: FASTCALL1 62 R2 L5
      25 [-]: MOVE R4 R2   
      26 [-]: GETIMPORT R3 3 [nil]
      27 [-]: CALL R3 1 1  
L 5:  28 [-]: JUMPIF R3 L9 
      29 [-]: LOADN R5 1   
      30 [-]: LENGTH R3 R2 
      31 [-]: LOADN R4 1   
      32 [-]: FORNPREP R3 L9
L 6:  33 [-]: GETTABLE R7 R2 R5
      34 [-]: FASTCALL1 62 R7 L7
      35 [-]: GETIMPORT R6 3 [nil]
      36 [-]: CALL R6 1 1  
L 7:  37 [-]: JUMPIF R6 L8 
      38 [-]: GETTABLE R6 R2 R5
      39 [-]: NAMECALL R6 R6 K10 [0x6162D901]
      40 [-]: CALL R6 1 1  
      41 [-]: GETIMPORT R7 1 [nil]
      42 [-]: JUMPIFNOTEQ R6 R7 L8
      43 [-]: GETTABLE R6 R2 R5
      44 [-]: NAMECALL R6 R6 K11 [0xA2880940]
      45 [-]: CALL R6 1 0  
L 8:  46 [-]: FORNLOOP R3 L6
L 9:  47 [-]: RETURN R0 0  


; Name:            
; Defined at line: 119
; #Upvalues:       0
; #Parameters:     0
; Is_vararg:       0
; Max Stack Size:  6

       0 [-]: GETIMPORT R1 1 [nil]
       1 [-]: FASTCALL1 62 R1 L0
       2 [-]: GETIMPORT R0 3 [nil]
       3 [-]: CALL R0 1 1  
L 0:   4 [-]: JUMPIF R0 L5 
       5 [-]: GETIMPORT R1 5 [nil]
       6 [-]: FASTCALL1 62 R1 L1
       7 [-]: GETIMPORT R0 3 [nil]
       8 [-]: CALL R0 1 1  
L 1:   9 [-]: JUMPIF R0 L5 
      10 [-]: LOADN R2 1   
      11 [-]: GETIMPORT R3 1 [nil]
      12 [-]: LENGTH R0 R3 
      13 [-]: LOADN R1 1   
      14 [-]: FORNPREP R0 L5
L 2:  15 [-]: GETIMPORT R4 1 [nil]
      16 [-]: GETTABLE R3 R4 R2
      17 [-]: GETIMPORT R5 5 [nil]
      18 [-]: NAMECALL R3 R3 K6 [0xC9F6A7D7]
      19 [-]: CALL R3 2 1  
      20 [-]: FASTCALL1 62 R3 L3
      21 [-]: MOVE R5 R3   
      22 [-]: GETIMPORT R4 3 [nil]
      23 [-]: CALL R4 1 1  
L 3:  24 [-]: JUMPIF R4 L4 
      25 [-]: NAMECALL R4 R3 K7 [0xA2880940]
      26 [-]: CALL R4 1 0  
L 4:  27 [-]: FORNLOOP R0 L2
L 5:  28 [-]: RETURN R0 0  


; Name:            
; Defined at line: 130
; #Upvalues:       0
; #Parameters:     0
; Is_vararg:       0
; Max Stack Size:  6

       0 [-]: GETIMPORT R0 1 [nil]
       1 [-]: GETIMPORT R1 3 [nil]
       2 [-]: CALL R0 1 0  
       3 [-]: GETIMPORT R1 5 [nil]
       4 [-]: FASTCALL1 62 R1 L0
       5 [-]: GETIMPORT R0 7 [nil]
       6 [-]: CALL R0 1 1  
L 0:   7 [-]: JUMPIF R0 L2 
       8 [-]: GETIMPORT R1 9 [nil]
       9 [-]: FASTCALL1 62 R1 L1
      10 [-]: GETIMPORT R0 7 [nil]
      11 [-]: CALL R0 1 1  
L 1:  12 [-]: JUMPIF R0 L2 
      13 [-]: GETIMPORT R0 5 [nil]
      14 [-]: GETIMPORT R2 9 [nil]
      15 [-]: GETIMPORT R3 11 [nil]
      16 [-]: GETIMPORT R4 13 [nil]
      17 [-]: GETIMPORT R5 15 [nil]
      18 [-]: NAMECALL R0 R0 K16 [0x47901F07]
      19 [-]: CALL R0 5 0  
L 2:  20 [-]: RETURN R0 0  


; Name:            
; Defined at line: 137
; #Upvalues:       0
; #Parameters:     0
; Is_vararg:       0
; Max Stack Size:  9

       0 [-]: GETIMPORT R1 1 [nil]
       1 [-]: FASTCALL1 62 R1 L0
       2 [-]: GETIMPORT R0 3 [nil]
       3 [-]: CALL R0 1 1  
L 0:   4 [-]: JUMPIF R0 L3 
       5 [-]: GETIMPORT R1 5 [nil]
       6 [-]: FASTCALL1 62 R1 L1
       7 [-]: GETIMPORT R0 3 [nil]
       8 [-]: CALL R0 1 1  
L 1:   9 [-]: JUMPIF R0 L3 
      10 [-]: LOADN R2 1   
      11 [-]: GETIMPORT R3 1 [nil]
      12 [-]: LENGTH R0 R3 
      13 [-]: LOADN R1 1   
      14 [-]: FORNPREP R0 L3
L 2:  15 [-]: GETIMPORT R4 1 [nil]
      16 [-]: GETTABLE R3 R4 R2
      17 [-]: GETIMPORT R5 5 [nil]
      18 [-]: GETIMPORT R6 7 [nil]
      19 [-]: GETIMPORT R7 9 [nil]
      20 [-]: GETIMPORT R8 11 [nil]
      21 [-]: NAMECALL R3 R3 K12 [0x47901F07]
      22 [-]: CALL R3 5 0  
      23 [-]: FORNLOOP R0 L2
L 3:  24 [-]: RETURN R0 0  


; Name:            
; Defined at line: 145
; #Upvalues:       0
; #Parameters:     1
; Is_vararg:       0
; Max Stack Size:  9

       0 [-]: GETIMPORT R1 1 [nil]
       1 [-]: LOADN R2 0   
       2 [-]: CALL R1 1 0  
       3 [-]: NAMECALL R1 R0 K2 [0x2B54251B]
       4 [-]: CALL R1 1 1  
       5 [-]: FASTCALL1 62 R1 L0
       6 [-]: MOVE R3 R1   
       7 [-]: GETIMPORT R2 4 [nil]
       8 [-]: CALL R2 1 1  
L 0:   9 [-]: JUMPIF R2 L2 
      10 [-]: GETIMPORT R3 6 [nil]
      11 [-]: FASTCALL1 62 R3 L1
      12 [-]: GETIMPORT R2 4 [nil]
      13 [-]: CALL R2 1 1  
L 1:  14 [-]: JUMPIF R2 L2 
      15 [-]: GETIMPORT R4 6 [nil]
      16 [-]: GETIMPORT R5 8 [nil]
      17 [-]: GETIMPORT R6 10 [nil]
      18 [-]: GETIMPORT R7 12 [nil]
      19 [-]: LOADB R8 1   
      20 [-]: NAMECALL R2 R1 K13 [0x09B0C239]
      21 [-]: CALL R2 6 0  
L 2:  22 [-]: RETURN R0 0  


; Name:            
; Defined at line: 153
; #Upvalues:       0
; #Parameters:     1
; Is_vararg:       0
; Max Stack Size:  4

       0 [-]: NAMECALL R1 R0 K0 [0x2B54251B]
       1 [-]: CALL R1 1 1  
       2 [-]: FASTCALL1 62 R1 L0
       3 [-]: MOVE R3 R1   
       4 [-]: GETIMPORT R2 2 [nil]
       5 [-]: CALL R2 1 1  
L 0:   6 [-]: JUMPIF R2 L1 
       7 [-]: NAMECALL R2 R1 K3 [0xA2880940]
       8 [-]: CALL R2 1 0  
L 1:   9 [-]: RETURN R0 0  


; Name:            
; Defined at line: 160
; #Upvalues:       0
; #Parameters:     1
; Is_vararg:       0
; Max Stack Size:  8

       0 [-]: GETIMPORT R1 1 [nil]
       1 [-]: JUMPIFNOT R1 L0
       2 [-]: GETIMPORT R1 3 [nil]
       3 [-]: NAMECALL R1 R1 K4 [0x18D05D30]
       4 [-]: CALL R1 1 1  
       5 [-]: JUMPIF R1 L0 
       6 [-]: RETURN R0 0  
L 0:   7 [-]: GETIMPORT R2 6 [nil]
       8 [-]: FASTCALL1 62 R2 L1
       9 [-]: GETIMPORT R1 8 [nil]
      10 [-]: CALL R1 1 1  
L 1:  11 [-]: JUMPIF R1 L2 
      12 [-]: GETIMPORT R3 6 [nil]
      13 [-]: GETIMPORT R4 10 [nil]
      14 [-]: GETIMPORT R5 12 [nil]
      15 [-]: GETIMPORT R6 14 [nil]
      16 [-]: MOVE R7 R0   
      17 [-]: NAMECALL R1 R0 K15 [0x47901F07]
      18 [-]: CALL R1 6 0  
L 2:  19 [-]: RETURN R0 0  


; Name:            
; Defined at line: 169
; #Upvalues:       0
; #Parameters:     2
; Is_vararg:       0
; Max Stack Size:  6

       0 [-]: FASTCALL1 62 R1 L0
       1 [-]: MOVE R3 R1   
       2 [-]: GETIMPORT R2 1 [nil]
       3 [-]: CALL R2 1 1  
L 0:   4 [-]: JUMPIF R2 L3 
       5 [-]: GETIMPORT R2 3 [nil]
       6 [-]: JUMPIFNOT R2 L1
       7 [-]: GETIMPORT R4 5 [nil]
       8 [-]: NAMECALL R2 R1 K6 [0x0542D42B]
       9 [-]: CALL R2 2 1  
      10 [-]: JUMPIF R2 L3 
      11 [-]: GETIMPORT R4 5 [nil]
      12 [-]: GETIMPORT R5 8 [nil]
      13 [-]: NAMECALL R2 R1 K9 [0x47901F07]
      14 [-]: CALL R2 3 0  
      15 [-]: RETURN R0 0  
L 1:  16 [-]: GETIMPORT R4 5 [nil]
      17 [-]: NAMECALL R2 R1 K10 [0xC9F6A7D7]
      18 [-]: CALL R2 2 1  
      19 [-]: FASTCALL1 62 R2 L2
      20 [-]: MOVE R4 R2   
      21 [-]: GETIMPORT R3 1 [nil]
      22 [-]: CALL R3 1 1  
L 2:  23 [-]: JUMPIF R3 L3 
      24 [-]: NAMECALL R3 R2 K11 [0xA2880940]
      25 [-]: CALL R3 1 0  
L 3:  26 [-]: RETURN R0 0  


; Name:            
; Defined at line: 184
; #Upvalues:       0
; #Parameters:     1
; Is_vararg:       0
; Max Stack Size:  6

       0 [-]: NAMECALL R1 R0 K0 [0xBB610E5B]
       1 [-]: CALL R1 1 1  
       2 [-]: FASTCALL1 62 R1 L0
       3 [-]: MOVE R3 R1   
       4 [-]: GETIMPORT R2 2 [nil]
       5 [-]: CALL R2 1 1  
L 0:   6 [-]: JUMPIF R2 L2 
       7 [-]: GETIMPORT R3 4 [nil]
       8 [-]: FASTCALL1 62 R3 L1
       9 [-]: GETIMPORT R2 2 [nil]
      10 [-]: CALL R2 1 1  
L 1:  11 [-]: JUMPIF R2 L2 
      12 [-]: GETIMPORT R4 4 [nil]
      13 [-]: GETIMPORT R5 6 [nil]
      14 [-]: NAMECALL R2 R1 K7 [0x47901F07]
      15 [-]: CALL R2 3 0  
L 2:  16 [-]: RETURN R0 0  


; Name:            
; Defined at line: 193
; #Upvalues:       1
; #Parameters:     1
; Is_vararg:       0
; Max Stack Size:  6

       0 [-]: NAMECALL R1 R0 K0 [0xED324116]
       1 [-]: CALL R1 1 1  
       2 [-]: FASTCALL1 62 R1 L0
       3 [-]: MOVE R3 R1   
       4 [-]: GETIMPORT R2 2 [nil]
       5 [-]: CALL R2 1 1  
L 0:   6 [-]: JUMPIFNOT R2 L1
       7 [-]: RETURN R0 0  
L 1:   8 [-]: NAMECALL R2 R1 K3 [0x28E744CF]
       9 [-]: CALL R2 1 1  
      10 [-]: FASTCALL1 62 R2 L2
      11 [-]: MOVE R4 R2   
      12 [-]: GETIMPORT R3 2 [nil]
      13 [-]: CALL R3 1 1  
L 2:  14 [-]: JUMPIFNOT R3 L3
      15 [-]: RETURN R0 0  
L 3:  16 [-]: GETUPVAL R5 0
      17 [-]: NAMECALL R3 R2 K4 [0xF2DEAF69]
      18 [-]: CALL R3 2 1  
      19 [-]: JUMPIFNOT R3 L5
      20 [-]: GETIMPORT R5 6 [nil]
      21 [-]: NAMECALL R3 R0 K4 [0xF2DEAF69]
      22 [-]: CALL R3 2 1  
      23 [-]: JUMPIFNOT R3 L4
      24 [-]: NAMECALL R3 R0 K7 [0x6B5E0C7A]
      25 [-]: CALL R3 1 0  
      26 [-]: RETURN R0 0  
L 4:  27 [-]: NAMECALL R3 R0 K8 [0xA2880940]
      28 [-]: CALL R3 1 0  
L 5:  29 [-]: RETURN R0 0  


; Name:            
; Defined at line: 211
; #Upvalues:       0
; #Parameters:     0
; Is_vararg:       0
; Max Stack Size:  8

       0 [-]: GETIMPORT R0 1 [nil]
       1 [-]: GETIMPORT R2 3 [nil]
       2 [-]: NAMECALL R0 R0 K4 [0xC1595BD5]
       3 [-]: CALL R0 2 1  
       4 [-]: FASTCALL1 62 R0 L0
       5 [-]: MOVE R2 R0   
       6 [-]: GETIMPORT R1 6 [nil]
       7 [-]: CALL R1 1 1  
L 0:   8 [-]: JUMPIF R1 L4 
       9 [-]: GETIMPORT R1 8 [nil]
      10 [-]: MOVE R2 R0   
      11 [-]: CALL R1 1 3  
      12 [-]: FORGPREP_INEXT R1 L3
L 1:  13 [-]: GETIMPORT R6 10 [nil]
      14 [-]: JUMPIFNOT R6 L2
      15 [-]: NAMECALL R6 R5 K11 [0x383D2E7D]
      16 [-]: CALL R6 1 0  
      17 [-]: JUMP L3
     
L 2:  18 [-]: NAMECALL R6 R5 K12 [0xF4E253B6]
      19 [-]: CALL R6 1 0  
L 3:  20 [-]: FORGLOOP R1 L1 2 [inext]
L 4:  21 [-]: RETURN R0 0  


; Name:            
; Defined at line: 224
; #Upvalues:       0
; #Parameters:     1
; Is_vararg:       0
; Max Stack Size:  10

       0 [-]: NAMECALL R1 R0 K0 [0x2B54251B]
       1 [-]: CALL R1 1 1  
       2 [-]: FASTCALL1 62 R1 L0
       3 [-]: MOVE R3 R1   
       4 [-]: GETIMPORT R2 2 [nil]
       5 [-]: CALL R2 1 1  
L 0:   6 [-]: JUMPIFNOT R2 L1
       7 [-]: RETURN R0 0  
L 1:   8 [-]: GETIMPORT R4 4 [nil]
       9 [-]: NAMECALL R2 R1 K5 [0xC1595BD5]
      10 [-]: CALL R2 2 1  
      11 [-]: FASTCALL1 62 R2 L2
      12 [-]: MOVE R4 R2   
      13 [-]: GETIMPORT R3 2 [nil]
      14 [-]: CALL R3 1 1  
L 2:  15 [-]: JUMPIF R3 L6 
      16 [-]: GETIMPORT R3 7 [nil]
      17 [-]: MOVE R4 R2   
      18 [-]: CALL R3 1 3  
      19 [-]: FORGPREP_INEXT R3 L5
L 3:  20 [-]: GETIMPORT R8 9 [nil]
      21 [-]: JUMPIFNOT R8 L4
      22 [-]: NAMECALL R8 R7 K10 [0x383D2E7D]
      23 [-]: CALL R8 1 0  
      24 [-]: JUMP L5
     
L 4:  25 [-]: NAMECALL R8 R7 K11 [0xF4E253B6]
      26 [-]: CALL R8 1 0  
L 5:  27 [-]: FORGLOOP R3 L3 2 [inext]
L 6:  28 [-]: RETURN R0 0  


; Name:            
; Defined at line: 241
; #Upvalues:       0
; #Parameters:     1
; Is_vararg:       0
; Max Stack Size:  7

       0 [-]: NAMECALL R1 R0 K0 [0x2B54251B]
       1 [-]: CALL R1 1 1  
       2 [-]: FASTCALL1 62 R1 L0
       3 [-]: MOVE R3 R1   
       4 [-]: GETIMPORT R2 2 [nil]
       5 [-]: CALL R2 1 1  
L 0:   6 [-]: JUMPIF R2 L1 
       7 [-]: GETIMPORT R4 4 [nil]
       8 [-]: LOADB R5 0   
       9 [-]: LOADB R6 0   
      10 [-]: NAMECALL R2 R1 K5 [0x2970F52F]
      11 [-]: CALL R2 4 0  
L 1:  12 [-]: RETURN R0 0  


; Name:            
; Defined at line: 248
; #Upvalues:       1
; #Parameters:     1
; Is_vararg:       0
; Max Stack Size:  8

L 0:   0 [-]: FASTCALL1 62 R0 L1
       1 [-]: MOVE R2 R0   
       2 [-]: GETIMPORT R1 1 [nil]
       3 [-]: CALL R1 1 1  
L 1:   4 [-]: JUMPIF R1 L2 
       5 [-]: NAMECALL R1 R0 K2 [0xF6EBD926]
       6 [-]: CALL R1 1 1  
       7 [-]: GETUPVAL R4 0
       8 [-]: GETTABLEKS R5 R1 K3 ["x"]
       9 [-]: GETTABLEKS R6 R1 K4 ["y"]
      10 [-]: GETTABLEKS R7 R1 K5 ["z"]
      11 [-]: NAMECALL R2 R0 K6 [0x986D2AB8]
      12 [-]: CALL R2 5 0  
      13 [-]: GETIMPORT R2 8 [nil]
      14 [-]: LOADN R3 0   
      15 [-]: CALL R2 1 0  
      16 [-]: JUMPBACK L0  
L 2:  17 [-]: RETURN R0 0  


; Name:            
; Defined at line: 256
; #Upvalues:       0
; #Parameters:     1
; Is_vararg:       0
; Max Stack Size:  3

       0 [-]: GETIMPORT R1 1 [nil]
       1 [-]: GETIMPORT R2 3 [nil]
       2 [-]: CALL R1 1 0  
       3 [-]: FASTCALL1 62 R0 L0
       4 [-]: MOVE R2 R0   
       5 [-]: GETIMPORT R1 5 [nil]
       6 [-]: CALL R1 1 1  
L 0:   7 [-]: JUMPIF R1 L1 
       8 [-]: NAMECALL R1 R0 K6 [0xF4E253B6]
       9 [-]: CALL R1 1 0  
L 1:  10 [-]: RETURN R0 0  


; Name:            
; Defined at line: 263
; #Upvalues:       0
; #Parameters:     1
; Is_vararg:       0
; Max Stack Size:  6

       0 [-]: GETIMPORT R1 1 [nil]
       1 [-]: GETIMPORT R2 3 [nil]
       2 [-]: CALL R1 1 0  
       3 [-]: FASTCALL1 62 R0 L0
       4 [-]: MOVE R2 R0   
       5 [-]: GETIMPORT R1 5 [nil]
       6 [-]: CALL R1 1 1  
L 0:   7 [-]: JUMPIF R1 L3 
       8 [-]: NAMECALL R1 R0 K6 [0x2B54251B]
       9 [-]: CALL R1 1 1  
      10 [-]: FASTCALL1 62 R1 L1
      11 [-]: MOVE R3 R1   
      12 [-]: GETIMPORT R2 5 [nil]
      13 [-]: CALL R2 1 1  
L 1:  14 [-]: JUMPIF R2 L3 
      15 [-]: GETIMPORT R4 8 [nil]
      16 [-]: NAMECALL R2 R1 K9 [0xF2DEAF69]
      17 [-]: CALL R2 2 1  
      18 [-]: JUMPIFNOT R2 L3
      19 [-]: NAMECALL R2 R1 K10 [0xA5E492D4]
      20 [-]: CALL R2 1 1  
      21 [-]: JUMPIFNOT R2 L2
      22 [-]: GETIMPORT R4 12 [nil]
      23 [-]: GETIMPORT R5 14 [nil]
      24 [-]: NAMECALL R2 R1 K15 [0x47901F07]
      25 [-]: CALL R2 3 0  
      26 [-]: RETURN R0 0  
L 2:  27 [-]: GETIMPORT R2 17 [nil]
      28 [-]: JUMPIFNOT R2 L3
      29 [-]: NAMECALL R2 R0 K18 [0xA2880940]
      30 [-]: CALL R2 1 0  
L 3:  31 [-]: RETURN R0 0  


; Name:            
; Defined at line: 277
; #Upvalues:       0
; #Parameters:     1
; Is_vararg:       0
; Max Stack Size:  10

       0 [-]: GETIMPORT R1 1 [nil]
       1 [-]: GETIMPORT R2 3 [nil]
       2 [-]: CALL R1 1 0  
       3 [-]: FASTCALL1 62 R0 L0
       4 [-]: MOVE R2 R0   
       5 [-]: GETIMPORT R1 5 [nil]
       6 [-]: CALL R1 1 1  
L 0:   7 [-]: JUMPIF R1 L6 
       8 [-]: GETIMPORT R2 7 [nil]
       9 [-]: FASTCALL1 62 R2 L1
      10 [-]: GETIMPORT R1 5 [nil]
      11 [-]: CALL R1 1 1  
L 1:  12 [-]: JUMPIF R1 L6 
      13 [-]: GETIMPORT R2 9 [nil]
      14 [-]: FASTCALL1 62 R2 L2
      15 [-]: GETIMPORT R1 5 [nil]
      16 [-]: CALL R1 1 1  
L 2:  17 [-]: JUMPIF R1 L6 
      18 [-]: GETIMPORT R2 7 [nil]
      19 [-]: LENGTH R1 R2 
      20 [-]: GETIMPORT R3 9 [nil]
      21 [-]: LENGTH R2 R3 
      22 [-]: JUMPIFNOTEQ R1 R2 L6
      23 [-]: LOADN R3 1   
      24 [-]: GETIMPORT R4 7 [nil]
      25 [-]: LENGTH R1 R4 
      26 [-]: LOADN R2 1   
      27 [-]: FORNPREP R1 L6
L 3:  28 [-]: GETIMPORT R6 11 [nil]
      29 [-]: GETIMPORT R8 7 [nil]
      30 [-]: GETTABLE R7 R8 R3
      31 [-]: NAMECALL R4 R0 K12 [0x47901F07]
      32 [-]: CALL R4 3 1  
      33 [-]: FASTCALL1 62 R4 L4
      34 [-]: MOVE R6 R4   
      35 [-]: GETIMPORT R5 5 [nil]
      36 [-]: CALL R5 1 1  
L 4:  37 [-]: JUMPIF R5 L5 
      38 [-]: MOVE R7 R0   
      39 [-]: GETIMPORT R9 9 [nil]
      40 [-]: GETTABLE R8 R9 R3
      41 [-]: NAMECALL R5 R4 K13 [0xB94B0AB4]
      42 [-]: CALL R5 3 0  
L 5:  43 [-]: FORNLOOP R1 L3
L 6:  44 [-]: RETURN R0 0  


; Name:            
; Defined at line: 289
; #Upvalues:       0
; #Parameters:     1
; Is_vararg:       0
; Max Stack Size:  4

       0 [-]: GETIMPORT R1 1 [nil]
       1 [-]: GETIMPORT R2 3 [nil]
       2 [-]: CALL R1 1 0  
       3 [-]: FASTCALL1 62 R0 L0
       4 [-]: MOVE R2 R0   
       5 [-]: GETIMPORT R1 5 [nil]
       6 [-]: CALL R1 1 1  
L 0:   7 [-]: JUMPIF R1 L1 
       8 [-]: GETIMPORT R3 7 [nil]
       9 [-]: NAMECALL R1 R0 K8 [0x9E9C67CB]
      10 [-]: CALL R1 2 0  
L 1:  11 [-]: RETURN R0 0  


; Name:            
; Defined at line: 296
; #Upvalues:       0
; #Parameters:     1
; Is_vararg:       0
; Max Stack Size:  3

       0 [-]: GETIMPORT R1 1 [nil]
       1 [-]: LOADN R2 0   
       2 [-]: JUMPIFNOTLE R2 R1 L0
       3 [-]: GETIMPORT R1 3 [nil]
       4 [-]: GETIMPORT R2 1 [nil]
       5 [-]: CALL R1 1 0  
L 0:   6 [-]: NAMECALL R1 R0 K4 [0x467C327C]
       7 [-]: CALL R1 1 0  
       8 [-]: RETURN R0 0  



