; Name:            
; Defined at line: 1
; #Upvalues:       0
; #Parameters:     0
; Is_vararg:       1
; Max Stack Size:  92

       1 [-]: NEWTABLE R0 0 4; var0 = {}
       2 [-]: LOADN R1 0   ; var1 = 0
       3 [-]: LOADN R2 250 ; var2 = 250
       4 [-]: LOADN R3 400 ; var3 = 400
       5 [-]: LOADN R4 600 ; var4 = 600
       6 [-]: SETLIST R0 R1 4 [1]; var0[1] = var1; var0[2] = var2; var0[3] = var3; var0[4] = var4; var0[5] = var5; 
       7 [-]: NEWTABLE R1 0 4; var1 = {}
       8 [-]: LOADN R2 3   ; var2 = 3
       9 [-]: LOADN R3 4   ; var3 = 4
      10 [-]: LOADN R4 5   ; var4 = 5
      11 [-]: LOADN R5 6   ; var5 = 6
      12 [-]: SETLIST R1 R2 4 [1]; var1[1] = var2; var1[2] = var3; var1[3] = var4; var1[4] = var5; var1[5] = var6; 
      13 [-]: NEWTABLE R2 0 4; var2 = {}
      14 [-]: LOADN R3 12  ; var3 = 12
      15 [-]: LOADN R4 14  ; var4 = 14
      16 [-]: LOADN R5 15  ; var5 = 15
      17 [-]: LOADN R6 20  ; var6 = 20
      18 [-]: SETLIST R2 R3 4 [1]; var2[1] = var3; var2[2] = var4; var2[3] = var5; var2[4] = var6; var2[5] = var7; 
      19 [-]: NEWTABLE R3 0 4; var3 = {}
      20 [-]: LOADN R4 6   ; var4 = 6
      21 [-]: LOADN R5 8   ; var5 = 8
      22 [-]: LOADN R6 12  ; var6 = 12
      23 [-]: LOADN R7 16  ; var7 = 16
      24 [-]: SETLIST R3 R4 4 [1]; var3[1] = var4; var3[2] = var5; var3[3] = var6; var3[4] = var7; var3[5] = var8; 
      25 [-]: NEWTABLE R4 0 4; var4 = {}
      26 [-]: LOADN R5 10  ; var5 = 10
      27 [-]: LOADN R6 12  ; var6 = 12
      28 [-]: LOADN R7 17  ; var7 = 17
      29 [-]: LOADN R8 20  ; var8 = 20
      30 [-]: SETLIST R4 R5 4 [1]; var4[1] = var5; var4[2] = var6; var4[3] = var7; var4[4] = var8; var4[5] = var9; 
      31 [-]: NEWTABLE R5 0 4; var5 = {}
      32 [-]: LOADN R6 8   ; var6 = 8
      33 [-]: LOADN R7 8   ; var7 = 8
      34 [-]: LOADN R8 8   ; var8 = 8
      35 [-]: LOADN R9 8   ; var9 = 8
      36 [-]: SETLIST R5 R6 4 [1]; var5[1] = var6; var5[2] = var7; var5[3] = var8; var5[4] = var9; var5[5] = var10; 
      37 [-]: NEWTABLE R6 0 4; var6 = {}
      38 [-]: LOADN R7 12  ; var7 = 12
      39 [-]: LOADN R8 12  ; var8 = 12
      40 [-]: LOADN R9 12  ; var9 = 12
      41 [-]: LOADN R10 12 ; var10 = 12
      42 [-]: SETLIST R6 R7 4 [1]; var6[1] = var7; var6[2] = var8; var6[3] = var9; var6[4] = var10; var6[5] = var11; 
      43 [-]: GETIMPORT R7 1; var7 = 0x2D0FAD09
      44 [-]: LOADK R8 K2  ; var8 = "EE.Interface.Utilities"
      45 [-]: CALL R7 2 2  ; var7 = var7(var8)
      46 [-]: GETIMPORT R8 1; var8 = 0x2D0FAD09
      47 [-]: LOADK R9 K3  ; var9 = "Lotus.Interface.LotusUtilities"
      48 [-]: CALL R8 2 2  ; var8 = var8(var9)
      49 [-]: GETIMPORT R9 1; var9 = 0x2D0FAD09
      50 [-]: LOADK R10 K4 ; var10 = "Lotus.Scripts.Libs.LandscapeLib"
      51 [-]: CALL R9 2 2  ; var9 = var9(var10)
      52 [-]: GETIMPORT R10 1; var10 = 0x2D0FAD09
      53 [-]: LOADK R11 K5 ; var11 = "Lotus.Scripts.Libs.TransmissionSet"
      54 [-]: CALL R10 2 2 ; var10 = var10(var11)
      55 [-]: GETIMPORT R11 1; var11 = 0x2D0FAD09
      56 [-]: LOADK R12 K6 ; var12 = "Lotus.Interface.Libs.TimerMgr"
      57 [-]: CALL R11 2 2 ; var11 = var11(var12)
      58 [-]: GETIMPORT R12 1; var12 = 0x2D0FAD09
      59 [-]: LOADK R13 K7 ; var13 = "Lotus.Scripts.Libs.ObjectiveText"
      60 [-]: CALL R12 2 2 ; var12 = var12(var13)
      61 [-]: GETIMPORT R13 1; var13 = 0x2D0FAD09
      62 [-]: LOADK R14 K8 ; var14 = "Lotus.Scripts.Libs.SpawnObjectsOnTerrain"
      63 [-]: CALL R13 2 2 ; var13 = var13(var14)
      64 [-]: GETIMPORT R14 1; var14 = 0x2D0FAD09
      65 [-]: LOADK R15 K9 ; var15 = "Lotus.Scripts.Libs.CommonGamemodeFunctions"
      66 [-]: CALL R14 2 2 ; var14 = var14(var15)
      67 [-]: GETIMPORT R15 11; var15 = 0x7ED0A956
      68 [-]: LOADK R16 K12; var16 = "/Lotus/Types/PickUps/ExcavatorCellItem"
      69 [-]: CALL R15 2 2 ; var15 = var15(var16)
      70 [-]: GETIMPORT R16 14; var16 = 0x88EFC25E
      71 [-]: LOADK R17 K15; var17 = "/Lotus/Types/PickUps/ExcavatorCellPickup"
      72 [-]: CALL R16 2 2 ; var16 = var16(var17)
      73 [-]: GETIMPORT R17 14; var17 = 0x88EFC25E
      74 [-]: LOADK R18 K16; var18 = "/Lotus/Types/Game/MarkerInfos/VenusObjectiveAMarkerInfo"
      75 [-]: CALL R17 2 2 ; var17 = var17(var18)
      76 [-]: GETIMPORT R18 14; var18 = 0x88EFC25E
      77 [-]: LOADK R19 K17; var19 = "/Lotus/Types/Game/MarkerInfos/VenusObjectiveBMarkerInfo"
      78 [-]: CALL R18 2 2 ; var18 = var18(var19)
      79 [-]: GETIMPORT R19 14; var19 = 0x88EFC25E
      80 [-]: LOADK R20 K18; var20 = "/Lotus/Types/Game/MarkerInfos/VenusObjectiveCMarkerInfo"
      81 [-]: CALL R19 2 2 ; var19 = var19(var20)
      82 [-]: GETIMPORT R20 14; var20 = 0x88EFC25E
      83 [-]: LOADK R21 K19; var21 = "/Lotus/Types/Game/MarkerInfos/VenusObjectiveDMarkerInfo"
      84 [-]: CALL R20 2 2 ; var20 = var20(var21)
      85 [-]: GETIMPORT R21 14; var21 = 0x88EFC25E
      86 [-]: LOADK R22 K20; var22 = "/Lotus/Types/Game/MarkerInfos/VenusObjectiveEMarkerInfo"
      87 [-]: CALL R21 2 2 ; var21 = var21(var22)
      88 [-]: NEWTABLE R22 0 5; var22 = {}
      89 [-]: MOVE R23 R17 ; var23 = var17
      90 [-]: MOVE R24 R18 ; var24 = var18
      91 [-]: MOVE R25 R19 ; var25 = var19
      92 [-]: MOVE R26 R20 ; var26 = var20
      93 [-]: MOVE R27 R21 ; var27 = var21
      94 [-]: SETLIST R22 R23 5 [1]; var22[1] = var23; var22[2] = var24; var22[3] = var25; var22[4] = var26; var22[5] = var27; var22[6] = var28; 
      95 [-]: GETIMPORT R23 22; var23 = 0x0469F296
      96 [-]: LOADK R24 K23; var24 = "EidolonObjectiveMarker"
      97 [-]: CALL R23 2 2 ; var23 = var23(var24)
      98 [-]: GETIMPORT R24 22; var24 = 0x0469F296
      99 [-]: LOADK R25 K24; var25 = "VenusObjectiveMarkerInfo"
     100 [-]: CALL R24 2 2 ; var24 = var24(var25)
     101 [-]: GETIMPORT R25 22; var25 = 0x0469F296
     102 [-]: LOADK R26 K25; var26 = "DynamicExcavatorAvatar"
     103 [-]: CALL R25 2 2 ; var25 = var25(var26)
     104 [-]: GETIMPORT R26 22; var26 = 0x0469F296
     105 [-]: LOADK R27 K26; var27 = "LeavingCB"
     106 [-]: CALL R26 2 2 ; var26 = var26(var27)
     107 [-]: GETIMPORT R27 22; var27 = 0x0469F296
     108 [-]: LOADK R28 K27; var28 = "ReturningCB"
     109 [-]: CALL R27 2 2 ; var27 = var27(var28)
     110 [-]: GETIMPORT R28 14; var28 = 0x88EFC25E
     111 [-]: LOADK R29 K28; var29 = "/Lotus/Types/Friendly/Venus/LotusDynamicExcavationState"
     112 [-]: CALL R28 2 2 ; var28 = var28(var29)
     113 [-]: GETIMPORT R29 11; var29 = 0x7ED0A956
     114 [-]: LOADK R30 K29; var30 = "/Lotus/Types/Enemies/Corpus/Venus/Avatars/VenusCarrierSpacemanAvatar"
     115 [-]: CALL R29 2 2 ; var29 = var29(var30)
     116 [-]: GETIMPORT R30 11; var30 = 0x7ED0A956
     117 [-]: LOADK R31 K30; var31 = "/Lotus/Types/Enemies/Corpus/Dropship/Venus/VenusDropshipAvatar"
     118 [-]: CALL R30 2 2 ; var30 = var30(var31)
     119 [-]: GETIMPORT R31 11; var31 = 0x7ED0A956
     120 [-]: LOADK R32 K31; var32 = "/EE/Types/Engine/Terrain"
     121 [-]: CALL R31 2 2 ; var31 = var31(var32)
     122 [-]: GETIMPORT R32 11; var32 = 0x7ED0A956
     123 [-]: LOADK R33 K32; var33 = "/EE/Types/Effects/Landscape"
     124 [-]: CALL R32 2 2 ; var32 = var32(var33)
     125 [-]: GETIMPORT R33 22; var33 = 0x0469F296
     126 [-]: LOADK R34 K33; var34 = "DYNAMIC_EXCAVATION_SITES_EXCAVATED"
     127 [-]: CALL R33 2 2 ; var33 = var33(var34)
     128 [-]: GETIMPORT R34 22; var34 = 0x0469F296
     129 [-]: LOADK R35 K34; var35 = "DYNAMIC_EXCAVATION_NUM_EXCAVATORS_DROPPED"
     130 [-]: CALL R34 2 2 ; var34 = var34(var35)
     131 [-]: GETIMPORT R35 22; var35 = 0x0469F296
     132 [-]: LOADK R36 K35; var36 = "DYNAMIC_EXCAVATION_TIME_ELAPSED"
     133 [-]: CALL R35 2 2 ; var35 = var35(var36)
     134 [-]: GETIMPORT R36 22; var36 = 0x0469F296
     135 [-]: LOADK R37 K36; var37 = "DYNAMIC_EXCAVATION_DIGS_COMPLETED"
     136 [-]: CALL R36 2 2 ; var36 = var36(var37)
     137 [-]: GETIMPORT R37 22; var37 = 0x0469F296
     138 [-]: LOADK R38 K37; var38 = "DYNAMIC_EXCAVATION_EXCAVATORS_DESTROYED"
     139 [-]: CALL R37 2 2 ; var37 = var37(var38)
     140 [-]: GETIMPORT R38 22; var38 = 0x0469F296
     141 [-]: LOADK R39 K38; var39 = "DynamicExcavationHiddenTimer"
     142 [-]: CALL R38 2 2 ; var38 = var38(var39)
     143 [-]: GETIMPORT R39 22; var39 = 0x0469F296
     144 [-]: LOADK R40 K39; var40 = "DynamicExcavationState"
     145 [-]: CALL R39 2 2 ; var39 = var39(var40)
     146 [-]: GETIMPORT R40 22; var40 = 0x0469F296
     147 [-]: LOADK R41 K40; var41 = "ExcavatorLandingPoint"
     148 [-]: CALL R40 2 2 ; var40 = var40(var41)
     149 [-]: LOADN R41 0  ; var41 = 0
     150 [-]: LOADNIL R42  ; var42 = nil
     151 [-]: LOADNIL R43  ; var43 = nil
     152 [-]: LOADNIL R44  ; var44 = nil
     153 [-]: LOADN R45 0  ; var45 = 0
     154 [-]: LOADN R46 0  ; var46 = 0
     155 [-]: LOADNIL R47  ; var47 = nil
     156 [-]: LOADNIL R48  ; var48 = nil
     157 [-]: LOADNIL R49  ; var49 = nil
     158 [-]: LOADNIL R50  ; var50 = nil
     159 [-]: NEWTABLE R51 0 0; var51 = {}
     160 [-]: LOADNIL R52  ; var52 = nil
     161 [-]: NEWTABLE R53 0 0; var53 = {}
     162 [-]: NEWTABLE R54 0 0; var54 = {}
     163 [-]: LOADN R55 0  ; var55 = 0
     164 [-]: LOADN R56 0  ; var56 = 0
     165 [-]: LOADN R57 0  ; var57 = 0
     166 [-]: LOADK R58 K41; var58 = 0.5
     167 [-]: LOADN R59 60 ; var59 = 60
     168 [-]: NEWTABLE R60 0 0; var60 = {}
     169 [-]: LOADNIL R61  ; var61 = nil
     170 [-]: NEWTABLE R62 0 5; var62 = {}
     171 [-]: LOADK R63 K42; var63 = "<MISSION_MARKER_A>"
     172 [-]: LOADK R64 K43; var64 = "<MISSION_MARKER_B>"
     173 [-]: LOADK R65 K44; var65 = "<MISSION_MARKER_C>"
     174 [-]: LOADK R66 K45; var66 = "<MISSION_MARKER_D>"
     175 [-]: LOADK R67 K46; var67 = "<MISSION_MARKER_E>"
     176 [-]: SETLIST R62 R63 5 [1]; var62[1] = var63; var62[2] = var64; var62[3] = var65; var62[4] = var66; var62[5] = var67; var62[6] = var68; 
     177 [-]: LOADNIL R63  ; var63 = nil
     178 [-]: LOADN R64 0  ; var64 = 0
     179 [-]: DUPCLOSURE R65 K47; 
     180 [-]: DUPCLOSURE R66 K48; 
     181 [-]: NEWCLOSURE R67 P2; 
     182 [-]: CAPTURE VAL R8; 
     183 [-]: CAPTURE VAL R62; 
     184 [-]: CAPTURE VAL R7; 
     185 [-]: CAPTURE VAL R66; 
     186 [-]: CAPTURE REF R61; 
     187 [-]: CAPTURE VAL R14; 
     188 [-]: DUPCLOSURE R68 K49; 
     189 [-]: NEWCLOSURE R69 P4; 
     190 [-]: CAPTURE VAL R40; 
     191 [-]: CAPTURE REF R42; 
     192 [-]: CAPTURE VAL R13; 
     193 [-]: CAPTURE VAL R31; 
     194 [-]: CAPTURE VAL R32; 
     195 [-]: NEWCLOSURE R70 P5; 
     196 [-]: CAPTURE VAL R34; 
     197 [-]: CAPTURE REF R60; 
     198 [-]: NEWCLOSURE R71 P6; 
     199 [-]: CAPTURE VAL R70; 
     200 [-]: CAPTURE REF R56; 
     201 [-]: DUPCLOSURE R72 K50; 
     202 [-]: DUPCLOSURE R73 K51; 
     203 [-]: DUPCLOSURE R74 K52; 
     204 [-]: DUPCLOSURE R75 K53; 
     205 [-]: CAPTURE VAL R15; 
     206 [-]: DUPCLOSURE R76 K54; 
     207 [-]: CAPTURE VAL R25; 
     208 [-]: DUPCLOSURE R77 K55; 
     209 [-]: CAPTURE VAL R37; 
     210 [-]: CAPTURE VAL R10; 
     211 [-]: CAPTURE VAL R24; 
     212 [-]: CAPTURE VAL R76; 
     213 [-]: DUPCLOSURE R78 K56; 
     214 [-]: DUPCLOSURE R79 K57; 
     215 [-]: CAPTURE VAL R36; 
     216 [-]: CAPTURE VAL R78; 
     217 [-]: NEWCLOSURE R80 P15; 
     218 [-]: CAPTURE VAL R75; 
     219 [-]: CAPTURE VAL R7; 
     220 [-]: CAPTURE VAL R36; 
     221 [-]: CAPTURE VAL R78; 
     222 [-]: CAPTURE VAL R73; 
     223 [-]: CAPTURE VAL R15; 
     224 [-]: CAPTURE REF R59; 
     225 [-]: CAPTURE VAL R10; 
     226 [-]: CAPTURE REF R48; 
     227 [-]: CAPTURE VAL R67; 
     228 [-]: NEWCLOSURE R81 P16; 
     229 [-]: CAPTURE REF R49; 
     230 [-]: CAPTURE VAL R12; 
     231 [-]: CAPTURE REF R51; 
     232 [-]: NEWCLOSURE R82 P17; 
     233 [-]: CAPTURE VAL R22; 
     234 [-]: CAPTURE REF R63; 
     235 [-]: DUPCLOSURE R83 K58; 
     236 [-]: DUPCLOSURE R84 K59; 
     237 [-]: CAPTURE VAL R13; 
     238 [-]: CAPTURE VAL R0; 
     239 [-]: CAPTURE VAL R25; 
     240 [-]: CAPTURE VAL R34; 
     241 [-]: CAPTURE VAL R39; 
     242 [-]: CAPTURE VAL R83; 
     243 [-]: CAPTURE VAL R82; 
     244 [-]: NEWCLOSURE R85 P20; 
     245 [-]: CAPTURE VAL R34; 
     246 [-]: CAPTURE VAL R69; 
     247 [-]: CAPTURE REF R47; 
     248 [-]: CAPTURE VAL R84; 
     249 [-]: SETGLOBAL R85 K60; "DropExcavator" = var85
     250 [-]: NEWCLOSURE R85 P21; 
     251 [-]: CAPTURE REF R42; 
     252 [-]: CAPTURE REF R52; 
     253 [-]: CAPTURE REF R47; 
     254 [-]: CAPTURE VAL R7; 
     255 [-]: CAPTURE REF R43; 
     256 [-]: CAPTURE REF R44; 
     257 [-]: CAPTURE REF R45; 
     258 [-]: CAPTURE REF R46; 
     259 [-]: CAPTURE REF R48; 
     260 [-]: CAPTURE REF R63; 
     261 [-]: CAPTURE REF R51; 
     262 [-]: CAPTURE REF R53; 
     263 [-]: CAPTURE VAL R3; 
     264 [-]: CAPTURE REF R54; 
     265 [-]: CAPTURE VAL R4; 
     266 [-]: CAPTURE VAL R1; 
     267 [-]: CAPTURE VAL R2; 
     268 [-]: CAPTURE VAL R12; 
     269 [-]: CAPTURE REF R49; 
     270 [-]: CAPTURE VAL R9; 
     271 [-]: CAPTURE VAL R81; 
     272 [-]: CAPTURE VAL R26; 
     273 [-]: CAPTURE VAL R27; 
     274 [-]: CAPTURE REF R50; 
     275 [-]: CAPTURE VAL R11; 
     276 [-]: CAPTURE VAL R24; 
     277 [-]: CAPTURE VAL R25; 
     278 [-]: CAPTURE VAL R28; 
     279 [-]: CAPTURE VAL R82; 
     280 [-]: CAPTURE VAL R39; 
     281 [-]: CAPTURE VAL R34; 
     282 [-]: CAPTURE REF R55; 
     283 [-]: CAPTURE VAL R35; 
     284 [-]: CAPTURE VAL R38; 
     285 [-]: CAPTURE REF R64; 
     286 [-]: CAPTURE VAL R33; 
     287 [-]: CAPTURE REF R61; 
     288 [-]: NEWCLOSURE R86 P22; 
     289 [-]: CAPTURE REF R47; 
     290 [-]: CAPTURE REF R58; 
     291 [-]: CAPTURE REF R57; 
     292 [-]: CAPTURE VAL R29; 
     293 [-]: CAPTURE REF R44; 
     294 [-]: CAPTURE REF R46; 
     295 [-]: CAPTURE REF R51; 
     296 [-]: CAPTURE REF R41; 
     297 [-]: CAPTURE VAL R5; 
     298 [-]: CAPTURE VAL R6; 
     299 [-]: CAPTURE REF R54; 
     300 [-]: CAPTURE VAL R25; 
     301 [-]: CAPTURE REF R60; 
     302 [-]: CAPTURE REF R42; 
     303 [-]: CAPTURE REF R43; 
     304 [-]: NEWCLOSURE R87 P23; 
     305 [-]: CAPTURE VAL R36; 
     306 [-]: CAPTURE VAL R12; 
     307 [-]: CAPTURE REF R51; 
     308 [-]: NEWCLOSURE R88 P24; 
     309 [-]: CAPTURE REF R51; 
     310 [-]: CAPTURE VAL R36; 
     311 [-]: CAPTURE VAL R37; 
     312 [-]: CAPTURE VAL R34; 
     313 [-]: CAPTURE REF R49; 
     314 [-]: CAPTURE REF R43; 
     315 [-]: NEWCLOSURE R89 P25; 
     316 [-]: CAPTURE REF R60; 
     317 [-]: CAPTURE VAL R80; 
     318 [-]: NEWCLOSURE R90 P26; 
     319 [-]: CAPTURE VAL R28; 
     320 [-]: CAPTURE REF R44; 
     321 [-]: CAPTURE REF R47; 
     322 [-]: NEWCLOSURE R91 P27; 
     323 [-]: CAPTURE VAL R85; 
     324 [-]: CAPTURE REF R60; 
     325 [-]: CAPTURE VAL R39; 
     326 [-]: CAPTURE REF R49; 
     327 [-]: CAPTURE VAL R10; 
     328 [-]: CAPTURE REF R48; 
     329 [-]: CAPTURE REF R51; 
     330 [-]: CAPTURE VAL R90; 
     331 [-]: CAPTURE REF R55; 
     332 [-]: CAPTURE VAL R35; 
     333 [-]: CAPTURE VAL R38; 
     334 [-]: CAPTURE VAL R25; 
     335 [-]: CAPTURE VAL R37; 
     336 [-]: CAPTURE VAL R36; 
     337 [-]: CAPTURE VAL R24; 
     338 [-]: CAPTURE VAL R34; 
     339 [-]: CAPTURE VAL R88; 
     340 [-]: CAPTURE VAL R70; 
     341 [-]: CAPTURE REF R56; 
     342 [-]: CAPTURE VAL R86; 
     343 [-]: CAPTURE VAL R80; 
     344 [-]: CAPTURE VAL R12; 
     345 [-]: CAPTURE REF R59; 
     346 [-]: CAPTURE REF R50; 
     347 [-]: CAPTURE VAL R9; 
     348 [-]: CAPTURE VAL R15; 
     349 [-]: CAPTURE VAL R22; 
     350 [-]: CAPTURE REF R45; 
     351 [-]: CAPTURE VAL R78; 
     352 [-]: CAPTURE VAL R23; 
     353 [-]: CAPTURE REF R46; 
     354 [-]: CAPTURE VAL R30; 
     355 [-]: CAPTURE VAL R16; 
     356 [-]: CAPTURE REF R44; 
     357 [-]: CAPTURE VAL R29; 
     358 [-]: CAPTURE REF R47; 
     359 [-]: CAPTURE REF R43; 
     360 [-]: CAPTURE VAL R26; 
     361 [-]: CAPTURE VAL R27; 
     362 [-]: CAPTURE VAL R33; 
     363 [-]: SETGLOBAL R91 K61; "ExcavationStart" = var91
     364 [-]: DUPCLOSURE R91 K62; 
     365 [-]: SETGLOBAL R91 K63; "OnKilled" = var91
     366 [-]: DUPCLOSURE R91 K64; 
     367 [-]: CAPTURE VAL R29; 
     368 [-]: CAPTURE VAL R25; 
     369 [-]: SETGLOBAL R91 K65; "OnAgentRegistered" = var91
     370 [-]: DUPCLOSURE R91 K66; 
     371 [-]: SETGLOBAL R91 K67; "OnExcavatorDeployed" = var91
     372 [-]: DUPCLOSURE R91 K68; 
     373 [-]: CAPTURE VAL R39; 
     374 [-]: CAPTURE VAL R77; 
     375 [-]: SETGLOBAL R91 K69; "OnExcavatorDestroyed" = var91
     376 [-]: NEWCLOSURE R91 P32; 
     377 [-]: CAPTURE REF R51; 
     378 [-]: CAPTURE VAL R39; 
     379 [-]: CAPTURE VAL R36; 
     380 [-]: CAPTURE VAL R37; 
     381 [-]: SETGLOBAL R91 K70; "OnPlayersChanged" = var91
     382 [-]: NEWCLOSURE R91 P33; 
     383 [-]: CAPTURE VAL R9; 
     384 [-]: CAPTURE REF R43; 
     385 [-]: SETGLOBAL R91 K71; "PlayersLeaving" = var91
     386 [-]: NEWCLOSURE R91 P34; 
     387 [-]: CAPTURE VAL R9; 
     388 [-]: CAPTURE REF R43; 
     389 [-]: SETGLOBAL R91 K72; "PlayersReturning" = var91
     390 [-]: CLOSEUPVALS R41; 
     391 [-]: RETURN R0 0  ; 


; Name:            
; Defined at line: 123
; #Upvalues:       0
; #Parameters:     1
; Is_vararg:       0
; Max Stack Size:  3

       0 [-]: GETIMPORT R1 1; var1 = 0xD644C2F1
       1 [-]: MOVE R2 R0   ; var2 = var0
       2 [-]: CALL R1 2 1  ; var1(var2)
       3 [-]: GETIMPORT R1 3; var1 = 0x3D106989
       4 [-]: MOVE R2 R0   ; var2 = var0
       5 [-]: CALL R1 2 1  ; var1(var2)
       6 [-]: RETURN R0 0  ; 


; Name:            
; Defined at line: 128
; #Upvalues:       0
; #Parameters:     3
; Is_vararg:       0
; Max Stack Size:  11

       0 [-]: LOADK R3 K0  ; var3 = ""
       1 [-]: FASTCALL1 62 R2 L0; 
       2 [-]: MOVE R5 R2   ; var5 = var2
       3 [-]: GETIMPORT R4 2; var4 = 0x7B998233
       4 [-]: CALL R4 2 2  ; var4 = var4(var5)
L 0:   5 [-]: JUMPIF R4 L6 ; goto L6 if var4
       6 [-]: LOADN R4 0   ; var4 = 0
       7 [-]: JUMPIFNOTLE R0 R4 L1; goto L1 if var0 > var328782
       8 [-]: GETIMPORT R4 5; var4 = 0x7F5022CF[0xE8072DED]
       9 [-]: LOADK R5 K6  ; var5 = "<font color=\"%s\"><b>%s</b></font>"
      10 [-]: GETTABLEKS R6 R2 K7; var6 = var2["ColorizeBlink"]
      11 [-]: LOADN R7 38  ; var7 = 38
      12 [-]: LOADN R8 34  ; var8 = 34
      13 [-]: CALL R6 3 2  ; var6 = var6(var7, var8)
      14 [-]: LOADK R8 K8  ; var8 = "0% "
      15 [-]: GETTABLEKS R9 R2 K9; var9 = var2["Localize"]
      16 [-]: LOADK R10 K10; var10 = "<PROBLEM>"
      17 [-]: CALL R9 2 2  ; var9 = var9(var10)
      18 [-]: CONCAT R7 R8 R9; var7 = var8 .. var9
      19 [-]: CALL R4 4 2  ; var4 = var4(var5, var6, var7)
      20 [-]: MOVE R3 R4   ; var3 = var4
      21 [-]: RETURN R3 1  ; 
L 1:  22 [-]: LOADN R4 25  ; var4 = 25
      23 [-]: JUMPIFNOTLE R0 R4 L3; goto L3 if var0 > var50400331
      24 [-]: FASTCALL1 12 R1 L2; 
      25 [-]: MOVE R5 R1   ; var5 = var1
      26 [-]: GETIMPORT R4 13; var4 = 0x5BCED4C4[0x55F27C30]
      27 [-]: CALL R4 2 2  ; var4 = var4(var5)
L 2:  28 [-]: JUMPIFNOTLT R0 R4 L3; goto L3 if var0 >= var328782
      29 [-]: GETIMPORT R4 5; var4 = 0x7F5022CF[0xE8072DED]
      30 [-]: LOADK R5 K6  ; var5 = "<font color=\"%s\"><b>%s</b></font>"
      31 [-]: GETTABLEKS R6 R2 K7; var6 = var2["ColorizeBlink"]
      32 [-]: LOADN R7 38  ; var7 = 38
      33 [-]: LOADN R8 34  ; var8 = 34
      34 [-]: CALL R6 3 2  ; var6 = var6(var7, var8)
      35 [-]: MOVE R8 R0   ; var8 = var0
      36 [-]: LOADK R9 K14 ; var9 = "%"
      37 [-]: CONCAT R7 R8 R9; var7 = var8 .. var9
      38 [-]: CALL R4 4 2  ; var4 = var4(var5, var6, var7)
      39 [-]: MOVE R3 R4   ; var3 = var4
      40 [-]: RETURN R3 1  ; 
L 3:  41 [-]: FASTCALL1 12 R1 L4; 
      42 [-]: MOVE R5 R1   ; var5 = var1
      43 [-]: GETIMPORT R4 13; var4 = 0x5BCED4C4[0x55F27C30]
      44 [-]: CALL R4 2 2  ; var4 = var4(var5)
L 4:  45 [-]: JUMPIFNOTLE R4 R0 L5; goto L5 if var4 > var328782
      46 [-]: GETIMPORT R4 5; var4 = 0x7F5022CF[0xE8072DED]
      47 [-]: LOADK R5 K6  ; var5 = "<font color=\"%s\"><b>%s</b></font>"
      48 [-]: GETTABLEKS R6 R2 K15; var6 = var2["Colorize"]
      49 [-]: LOADN R7 10  ; var7 = 10
      50 [-]: CALL R6 2 2  ; var6 = var6(var7)
      51 [-]: GETTABLEKS R7 R2 K9; var7 = var2["Localize"]
      52 [-]: LOADK R8 K16 ; var8 = "/Lotus/Language/Objectives/ExcavPowerFull"
      53 [-]: CALL R7 2 0  ; var7, ... = var7(var8)
      54 [-]: CALL R4 0 2  ; var4 = var4(var5, ...)
      55 [-]: MOVE R3 R4   ; var3 = var4
      56 [-]: RETURN R3 1  ; 
L 5:  57 [-]: GETIMPORT R4 5; var4 = 0x7F5022CF[0xE8072DED]
      58 [-]: LOADK R5 K6  ; var5 = "<font color=\"%s\"><b>%s</b></font>"
      59 [-]: GETTABLEKS R6 R2 K15; var6 = var2["Colorize"]
      60 [-]: LOADN R7 38  ; var7 = 38
      61 [-]: CALL R6 2 2  ; var6 = var6(var7)
      62 [-]: MOVE R8 R0   ; var8 = var0
      63 [-]: LOADK R9 K14 ; var9 = "%"
      64 [-]: CONCAT R7 R8 R9; var7 = var8 .. var9
      65 [-]: CALL R4 4 2  ; var4 = var4(var5, var6, var7)
      66 [-]: MOVE R3 R4   ; var3 = var4
L 6:  67 [-]: RETURN R3 1  ; 


; Name:            
; Defined at line: 145
; #Upvalues:       6
; #Parameters:     1
; Is_vararg:       0
; Max Stack Size:  16

       0 [-]: GETIMPORT R1 1; var1 = 0xBE190284
       1 [-]: NAMECALL R1 R1 K2; var2 = var1; var1 = var1[0x33307F92]
       2 [-]: CALL R1 2 2  ; var1 = var1(var2)
       3 [-]: FASTCALL1 62 R0 L0; 
       4 [-]: MOVE R3 R0   ; var3 = var0
       5 [-]: GETIMPORT R2 4; var2 = 0x7B998233
       6 [-]: CALL R2 2 2  ; var2 = var2(var3)
L 0:   7 [-]: JUMPIF R2 L9 ; goto L9 if var2
       8 [-]: NAMECALL R2 R0 K5; var3 = var0; var2 = var0[0xBB610E5B]
       9 [-]: CALL R2 2 2  ; var2 = var2(var3)
      10 [-]: NAMECALL R3 R0 K6; var4 = var0; var3 = var0[0x08E5889B]
      11 [-]: CALL R3 2 2  ; var3 = var3(var4)
      12 [-]: FASTCALL1 12 R3 L1; 
      13 [-]: MOVE R5 R3   ; var5 = var3
      14 [-]: GETIMPORT R4 9; var4 = 0x5BCED4C4[0x55F27C30]
      15 [-]: CALL R4 2 2  ; var4 = var4(var5)
L 1:  16 [-]: MOVE R3 R4   ; var3 = var4
      17 [-]: NAMECALL R4 R0 K10; var5 = var0; var4 = var0[0x17DD42BB]
      18 [-]: CALL R4 2 2  ; var4 = var4(var5)
      19 [-]: NAMECALL R5 R0 K11; var6 = var0; var5 = var0[0xF329A790]
      20 [-]: CALL R5 2 2  ; var5 = var5(var6)
      21 [-]: LOADK R7 K12 ; var7 = "DynamicExcavationInfo"
      22 [-]: MOVE R8 R5   ; var8 = var5
      23 [-]: CONCAT R6 R7 R8; var6 = var7 .. var8
      24 [-]: LOADNIL R7   ; var7 = nil
      25 [-]: GETIMPORT R10 15; var10 = _T["DynamicExcavationHudInfo"]
      26 [-]: GETTABLE R9 R10 R5; var9 = var10[var5]
      27 [-]: FASTCALL1 62 R9 L2; 
      28 [-]: GETIMPORT R8 4; var8 = 0x7B998233
      29 [-]: CALL R8 2 2  ; var8 = var8(var9)
L 2:  30 [-]: JUMPIFNOT R8 L3; goto L3 if not var8
      31 [-]: NEWTABLE R7 0 0; var7 = {}
      32 [-]: GETIMPORT R8 17; var8 = _T["AddHudTracker"]
      33 [-]: MOVE R10 R6  ; var10 = var6
      34 [-]: LOADK R11 K18; var11 = "health"
      35 [-]: CONCAT R9 R10 R11; var9 = var10 .. var11
      36 [-]: GETUPVAL R11 0; var11 = upvalues[0]
      37 [-]: GETTABLEKS R10 R11 K19; var10 = var11["HT_HEALTH_TRACKER"]
      38 [-]: LOADK R11 K20; var11 = 0.14999999999999999
      39 [-]: LOADN R12 10 ; var12 = 10
      40 [-]: LOADB R13 1  ; var13 = true
      41 [-]: CALL R8 6 2  ; var8 = var8(var9, var10, var11, var12, var13)
      42 [-]: SETTABLEN R8 R7 1; SETTABLEN R8 R7 1
      43 [-]: GETTABLEN R9 R7 1; var9 = var7[1]
      44 [-]: GETTABLEKS R8 R9 K21; var8 = var9["SetOffset"]
      45 [-]: LOADN R9 5   ; var9 = 5
      46 [-]: LOADN R10 0  ; var10 = 0
      47 [-]: CALL R8 3 1  ; var8(var9, var10)
      48 [-]: GETTABLEN R9 R7 1; var9 = var7[1]
      49 [-]: GETTABLEKS R8 R9 K22; var8 = var9["SetTarget"]
      50 [-]: MOVE R9 R2   ; var9 = var2
      51 [-]: CALL R8 2 1  ; var8(var9)
      52 [-]: GETTABLEN R9 R7 1; var9 = var7[1]
      53 [-]: GETTABLEKS R8 R9 K23; var8 = var9["SetHealthWarningThreshold"]
      54 [-]: LOADN R9 20  ; var9 = 20
      55 [-]: LOADB R10 0  ; var10 = false
      56 [-]: CALL R8 3 1  ; var8(var9, var10)
      57 [-]: GETTABLEN R9 R7 1; var9 = var7[1]
      58 [-]: GETTABLEKS R8 R9 K24; var8 = var9["SetNameOverride"]
      59 [-]: LOADK R9 K25 ; var9 = "/Lotus/Language/Game/ExcavatorObject"
      60 [-]: CALL R8 2 1  ; var8(var9)
      61 [-]: GETTABLEN R9 R7 1; var9 = var7[1]
      62 [-]: GETTABLEKS R8 R9 K26; var8 = var9["SetNameFormat"]
      63 [-]: GETUPVAL R12 1; var12 = upvalues[1]
      64 [-]: GETTABLE R10 R12 R5; var10 = var12[var5]
      65 [-]: LOADK R11 K27; var11 = " |NAME|"
      66 [-]: CONCAT R9 R10 R11; var9 = var10 .. var11
      67 [-]: CALL R8 2 1  ; var8(var9)
      68 [-]: GETIMPORT R8 17; var8 = _T["AddHudTracker"]
      69 [-]: MOVE R10 R6  ; var10 = var6
      70 [-]: LOADK R11 K28; var11 = "label"
      71 [-]: CONCAT R9 R10 R11; var9 = var10 .. var11
      72 [-]: GETUPVAL R11 0; var11 = upvalues[0]
      73 [-]: GETTABLEKS R10 R11 K29; var10 = var11["HT_LABEL"]
      74 [-]: LOADK R11 K20; var11 = 0.14999999999999999
      75 [-]: LOADN R12 10 ; var12 = 10
      76 [-]: LOADB R13 1  ; var13 = true
      77 [-]: CALL R8 6 2  ; var8 = var8(var9, var10, var11, var12, var13)
      78 [-]: SETTABLEN R8 R7 2; SETTABLEN R8 R7 2
      79 [-]: GETTABLEN R9 R7 2; var9 = var7[2]
      80 [-]: GETTABLEKS R8 R9 K21; var8 = var9["SetOffset"]
      81 [-]: LOADN R9 -20 ; var9 = -20
      82 [-]: LOADN R10 -34; var10 = -34
      83 [-]: CALL R8 3 1  ; var8(var9, var10)
      84 [-]: GETIMPORT R8 15; var8 = _T["DynamicExcavationHudInfo"]
      85 [-]: SETTABLE R7 R8 R5; var7[var8] = var5
      86 [-]: JUMP L4      ; goto L4
L 3:  87 [-]: GETIMPORT R8 15; var8 = _T["DynamicExcavationHudInfo"]
      88 [-]: GETTABLE R7 R8 R5; var7 = var8[var5]
L 4:  89 [-]: FASTCALL1 62 R7 L5; 
      90 [-]: MOVE R9 R7   ; var9 = var7
      91 [-]: GETIMPORT R8 4; var8 = 0x7B998233
      92 [-]: CALL R8 2 2  ; var8 = var8(var9)
L 5:  93 [-]: JUMPIF R8 L9 ; goto L9 if var8
      94 [-]: GETUPVAL R9 2; var9 = upvalues[2]
      95 [-]: GETTABLEKS R8 R9 K30; var8 = var9[0x1142C7A8]
      96 [-]: DIVK R9 R4 K31; var9 = var4 / 1
      97 [-]: LOADN R10 1  ; var10 = 1
      98 [-]: LOADNIL R11  ; var11 = nil
      99 [-]: LOADNIL R12  ; var12 = nil
     100 [-]: LOADB R13 1  ; var13 = true
     101 [-]: CALL R8 6 2  ; var8 = var8(var9, var10, var11, var12, var13)
     102 [-]: GETUPVAL R9 3; var9 = upvalues[3]
     103 [-]: MOVE R10 R3  ; var10 = var3
     104 [-]: MOVE R11 R4  ; var11 = var4
     105 [-]: GETTABLEN R12 R7 2; var12 = var7[2]
     106 [-]: CALL R9 4 2  ; var9 = var9(var10, var11, var12)
     107 [-]: GETTABLEN R11 R7 2; var11 = var7[2]
     108 [-]: GETTABLEKS R10 R11 K32; var10 = var11["Localize"]
     109 [-]: LOADK R11 K33; var11 = "/Lotus/Language/Game/ExcavationTime"
     110 [-]: CALL R10 2 1 ; var10(var11)
     111 [-]: GETTABLEN R11 R7 2; var11 = var7[2]
     112 [-]: GETTABLEKS R10 R11 K32; var10 = var11["Localize"]
     113 [-]: LOADK R11 K34; var11 = "/Lotus/Language/Game/ExcavationPower"
     114 [-]: CALL R10 2 1 ; var10(var11)
     115 [-]: GETTABLEN R11 R7 2; var11 = var7[2]
     116 [-]: GETTABLEKS R10 R11 K35; var10 = var11["Colorize"]
     117 [-]: LOADN R11 38 ; var11 = 38
     118 [-]: CALL R10 2 1 ; var10(var11)
     119 [-]: GETTABLEN R11 R7 2; var11 = var7[2]
     120 [-]: GETTABLEKS R10 R11 K36; var10 = var11["SetLabel"]
     121 [-]: GETIMPORT R11 39; var11 = 0x7F5022CF[0xE8072DED]
     122 [-]: GETUPVAL R12 4; var12 = upvalues[4]
     123 [-]: GETUPVAL R14 5; var14 = upvalues[5]
     124 [-]: GETTABLEKS R13 R14 K40; var13 = var14[0xC70DAAAC]
     125 [-]: MOVE R14 R8  ; var14 = var8
     126 [-]: CALL R13 2 2 ; var13 = var13(var14)
     127 [-]: MOVE R14 R9  ; var14 = var9
     128 [-]: CALL R11 4 0 ; var11, ... = var11(var12, var13, var14)
     129 [-]: CALL R10 0 1 ; var10(var11, ...)
     130 [-]: GETTABLEN R11 R7 2; var11 = var7[2]
     131 [-]: GETTABLEKS R10 R11 K41; var10 = var11["NeedsInit"]
     132 [-]: JUMPIF R10 L9; goto L9 if var10
     133 [-]: FASTCALL1 62 R1 L6; 
     134 [-]: MOVE R11 R1  ; var11 = var1
     135 [-]: GETIMPORT R10 4; var10 = 0x7B998233
     136 [-]: CALL R10 2 2 ; var10 = var10(var11)
L 6: 137 [-]: JUMPIF R10 L9; goto L9 if var10
     138 [-]: GETTABLEN R15 R7 2; var15 = var7[2]
     139 [-]: GETTABLEKS R13 R15 K42; var13 = var15["ClipName"]
     140 [-]: LOADK R14 K43; var14 = ".Label"
     141 [-]: CONCAT R12 R13 R14; var12 = var13 .. var14
     142 [-]: LOADN R13 34 ; var13 = 34
     143 [-]: NAMECALL R10 R1 K44; var11 = var1; var10 = var1[0x91A24E4B]
     144 [-]: CALL R10 4 2 ; var10 = var10(var11, var12, var13)
     145 [-]: FASTCALL1 62 R10 L7; 
     146 [-]: MOVE R12 R10 ; var12 = var10
     147 [-]: GETIMPORT R11 4; var11 = 0x7B998233
     148 [-]: CALL R11 2 2 ; var11 = var11(var12)
L 7: 149 [-]: JUMPIF R11 L9; goto L9 if var11
     150 [-]: GETIMPORT R12 46; var12 = 0x03F57322
     151 [-]: MOVE R13 R10 ; var13 = var10
     152 [-]: CALL R12 2 2 ; var12 = var12(var13)
     153 [-]: FASTCALL1 62 R12 L8; 
     154 [-]: GETIMPORT R11 4; var11 = 0x7B998233
     155 [-]: CALL R11 2 2 ; var11 = var11(var12)
L 8: 156 [-]: JUMPIF R11 L9; goto L9 if var11
     157 [-]: GETTABLEN R12 R7 2; var12 = var7[2]
     158 [-]: GETTABLEKS R11 R12 K47; var11 = var12["SetHeight"]
     159 [-]: GETIMPORT R13 46; var13 = 0x03F57322
     160 [-]: MOVE R14 R10 ; var14 = var10
     161 [-]: CALL R13 2 2 ; var13 = var13(var14)
     162 [-]: ADDK R12 R13 K48; var12 = var13 + 25
     163 [-]: CALL R11 2 1 ; var11(var12)
L 9: 164 [-]: RETURN R0 0  ; 


; Name:            
; Defined at line: 192
; #Upvalues:       0
; #Parameters:     3
; Is_vararg:       0
; Max Stack Size:  3

       0 [-]: RETURN R0 0  ; 


; Name:            
; Defined at line: 202
; #Upvalues:       5
; #Parameters:     5
; Is_vararg:       0
; Max Stack Size:  30

       0 [-]: MUL R5 R3 R3 ; var5 = var3 * var3
       1 [-]: MUL R6 R4 R4 ; var6 = var4 * var4
       2 [-]: LOADB R7 0   ; var7 = false
       3 [-]: LOADN R8 200 ; var8 = 200
       4 [-]: GETIMPORT R9 1; var9 = 0xA421AF95
       5 [-]: LOADN R10 0  ; var10 = 0
       6 [-]: LOADN R11 300; var11 = 300
       7 [-]: LOADN R12 0  ; var12 = 0
       8 [-]: CALL R9 4 2  ; var9 = var9(var10, var11, var12)
       9 [-]: GETIMPORT R10 3; var10 = 0x89326C93
      10 [-]: GETUPVAL R12 0; var12 = upvalues[0]
      11 [-]: MOVE R13 R0  ; var13 = var0
      12 [-]: LOADN R14 0  ; var14 = 0
      13 [-]: MOVE R15 R2  ; var15 = var2
      14 [-]: NAMECALL R10 R10 K4; var11 = var10; var10 = var10[0xF16592C8]
      15 [-]: CALL R10 6 2 ; var10 = var10(var11, var12, var13, var14, var15)
      16 [-]: LENGTH R11 R10; var11 = #var10
      17 [-]: LOADN R12 1  ; var12 = 1
      18 [-]: JUMPIFNOTLT R12 R11 L1; goto L1 if var12 >= var68935
      19 [-]: LOADN R13 1  ; var13 = 1
      20 [-]: LENGTH R11 R10; var11 = #var10
      21 [-]: LOADN R12 1  ; var12 = 1
      22 [-]: FORNPREP R11 L1; nforprep start - [escape at L1] -- var11 = iterator
L 0:  23 [-]: GETTABLE R14 R10 R13; var14 = var10[var13]
      24 [-]: GETIMPORT R15 6; var15 = 0x55730E1A
      25 [-]: LOADN R16 1  ; var16 = 1
      26 [-]: LENGTH R17 R10; var17 = #var10
      27 [-]: CALL R15 3 2 ; var15 = var15(var16, var17)
      28 [-]: GETTABLE R16 R10 R15; var16 = var10[var15]
      29 [-]: SETTABLE R16 R10 R13; var16[var10] = var13
      30 [-]: SETTABLE R14 R10 R15; var14[var10] = var15
      31 [-]: FORNLOOP R11 L0; nforloop end - iterate + goto L0
L 1:  32 [-]: LOADN R11 0  ; var11 = 0
L 2:  33 [-]: JUMPIF R7 L25; goto L25 if var7
      34 [-]: LOADN R12 0  ; var12 = 0
      35 [-]: JUMPIFNOTLT R12 R8 L25; goto L25 if var12 >= var3086
      36 [-]: LOADNIL R12  ; var12 = nil
      37 [-]: LOADN R15 1  ; var15 = 1
      38 [-]: LOADN R13 10 ; var13 = 10
      39 [-]: LOADN R14 1  ; var14 = 1
      40 [-]: FORNPREP R13 L23; nforprep start - [escape at L23] -- var13 = iterator
L 3:  41 [-]: SUBK R8 R8 K7; var8 = var8 - 1
      42 [-]: LENGTH R16 R10; var16 = #var10
      43 [-]: LOADN R17 0  ; var17 = 0
      44 [-]: JUMPIFNOTLT R17 R16 L4; goto L4 if var17 >= var118165544
      45 [-]: ADDK R16 R11 K7; var16 = var11 + 1
      46 [-]: LENGTH R17 R10; var17 = #var10
      47 [-]: JUMPIFNOTLE R16 R17 L4; goto L4 if var16 > var118164264
      48 [-]: ADDK R11 R11 K7; var11 = var11 + 1
      49 [-]: GETTABLE R16 R10 R11; var16 = var10[var11]
      50 [-]: NAMECALL R16 R16 K8; var17 = var16; var16 = var16[0xD1586535]
      51 [-]: CALL R16 2 2 ; var16 = var16(var17)
      52 [-]: MOVE R12 R16 ; var12 = var16
      53 [-]: JUMP L7      ; goto L7
L 4:  54 [-]: MOVE R12 R0  ; var12 = var0
      55 [-]: GETIMPORT R18 12; var18 = 0x5BCED4C4[0x3630E649]
      56 [-]: CALL R18 1 2 ; var18 = var18()
      57 [-]: MULK R17 R18 K9; var17 = var18 * 2
      58 [-]: LOADK R18 K13; var18 = 3.1415927410125732
      59 [-]: MUL R16 R17 R18; var16 = var17 * var18
      60 [-]: GETIMPORT R17 1; var17 = 0xA421AF95
      61 [-]: FASTCALL1 9 R16 L5; 
      62 [-]: MOVE R19 R16 ; var19 = var16
      63 [-]: GETIMPORT R18 15; var18 = 0x5BCED4C4[0x00FA6BF1]
      64 [-]: CALL R18 2 2 ; var18 = var18(var19)
L 5:  65 [-]: LOADN R19 0  ; var19 = 0
      66 [-]: FASTCALL1 24 R16 L6; 
      67 [-]: MOVE R21 R16 ; var21 = var16
      68 [-]: GETIMPORT R20 17; var20 = 0x5BCED4C4[0x3EDA26FC]
      69 [-]: CALL R20 2 2 ; var20 = var20(var21)
L 6:  70 [-]: CALL R17 4 2 ; var17 = var17(var18, var19, var20)
      71 [-]: GETIMPORT R19 12; var19 = 0x5BCED4C4[0x3630E649]
      72 [-]: MOVE R20 R1  ; var20 = var1
      73 [-]: MOVE R21 R2  ; var21 = var2
      74 [-]: CALL R19 3 2 ; var19 = var19(var20, var21)
      75 [-]: MUL R18 R17 R19; var18 = var17 * var19
      76 [-]: ADD R12 R12 R18; var12 = var12 + var18
      77 [-]: GETUPVAL R18 1; var18 = upvalues[1]
      78 [-]: MOVE R20 R12 ; var20 = var12
      79 [-]: MOVE R21 R2  ; var21 = var2
      80 [-]: LOADB R22 1  ; var22 = true
      81 [-]: LOADN R23 10 ; var23 = 10
      82 [-]: NAMECALL R18 R18 K18; var19 = var18; var18 = var18[0xACFAB10E]
      83 [-]: CALL R18 6 2 ; var18 = var18(var19, var20, var21, var22, var23)
      84 [-]: MOVE R12 R18 ; var12 = var18
      85 [-]: GETUPVAL R19 2; var19 = upvalues[2]
      86 [-]: GETTABLEKS R18 R19 K19; var18 = var19[0x29595BA9]
      87 [-]: MOVE R19 R12 ; var19 = var12
      88 [-]: LOADN R20 40 ; var20 = 40
      89 [-]: LOADB R21 1  ; var21 = true
      90 [-]: LOADN R22 2  ; var22 = 2
      91 [-]: CALL R18 5 2 ; var18 = var18(var19, var20, var21, var22)
      92 [-]: MOVE R12 R18 ; var12 = var18
L 7:  93 [-]: LOADB R16 1  ; var16 = true
      94 [-]: LOADB R17 0  ; var17 = false
      95 [-]: LOADN R18 0  ; var18 = 0
      96 [-]: FASTCALL1 62 R12 L8; 
      97 [-]: MOVE R20 R12 ; var20 = var12
      98 [-]: GETIMPORT R19 21; var19 = 0x7B998233
      99 [-]: CALL R19 2 2 ; var19 = var19(var20)
L 8: 100 [-]: JUMPIF R19 L21; goto L21 if var19
     101 [-]: ADD R19 R12 R9; var19 = var12 + var9
     102 [-]: SUB R20 R12 R9; var20 = var12 - var9
     103 [-]: GETIMPORT R21 1; var21 = 0xA421AF95
     104 [-]: CALL R21 1 2 ; var21 = var21()
     105 [-]: GETIMPORT R22 23; var22 = 0x467EAF6A
     106 [-]: CALL R22 1 2 ; var22 = var22()
     107 [-]: GETIMPORT R23 3; var23 = 0x89326C93
     108 [-]: MOVE R25 R19 ; var25 = var19
     109 [-]: MOVE R26 R20 ; var26 = var20
     110 [-]: LOADNIL R27  ; var27 = nil
     111 [-]: MOVE R28 R22 ; var28 = var22
     112 [-]: MOVE R29 R21 ; var29 = var21
     113 [-]: NAMECALL R23 R23 K24; var24 = var23; var23 = var23[0xBD5D0EC1]
     114 [-]: CALL R23 7 1 ; var23(var24, var25, var26, var27, var28, var29)
     115 [-]: NAMECALL R23 R22 K25; var24 = var22; var23 = var22[0xEF3A99CA]
     116 [-]: CALL R23 2 2 ; var23 = var23(var24)
     117 [-]: MOVE R22 R23 ; var22 = var23
     118 [-]: FASTCALL1 62 R22 L9; 
     119 [-]: MOVE R24 R22 ; var24 = var22
     120 [-]: GETIMPORT R23 21; var23 = 0x7B998233
     121 [-]: CALL R23 2 2 ; var23 = var23(var24)
L 9: 122 [-]: JUMPIF R23 L20; goto L20 if var23
     123 [-]: GETUPVAL R25 3; var25 = upvalues[3]
     124 [-]: NAMECALL R23 R22 K26; var24 = var22; var23 = var22[0xF2DEAF69]
     125 [-]: CALL R23 3 2 ; var23 = var23(var24, var25)
     126 [-]: JUMPIF R23 L10; goto L10 if var23
     127 [-]: GETUPVAL R25 4; var25 = upvalues[4]
     128 [-]: NAMECALL R23 R22 K26; var24 = var22; var23 = var22[0xF2DEAF69]
     129 [-]: CALL R23 3 2 ; var23 = var23(var24, var25)
     130 [-]: JUMPIFNOT R23 L20; goto L20 if not var23
L10: 131 [-]: MOVE R12 R21 ; var12 = var21
     132 [-]: LOADN R25 1  ; var25 = 1
     133 [-]: GETIMPORT R26 29; var26 = _T["DynamicExcavatorSpawnPoints"]
     134 [-]: LENGTH R23 R26; var23 = #var26
     135 [-]: LOADN R24 1  ; var24 = 1
     136 [-]: FORNPREP R23 L16; nforprep start - [escape at L16] -- var23 = iterator
L11: 137 [-]: GETIMPORT R26 31; var26 = 0xC0DA2B81
     138 [-]: GETIMPORT R28 29; var28 = _T["DynamicExcavatorSpawnPoints"]
     139 [-]: GETTABLE R27 R28 R25; var27 = var28[var25]
     140 [-]: MOVE R28 R12 ; var28 = var12
     141 [-]: CALL R26 3 2 ; var26 = var26(var27, var28)
     142 [-]: MOVE R18 R26 ; var18 = var26
     143 [-]: MOVE R26 R16 ; var26 = var16
     144 [-]: JUMPIFNOT R26 L13; goto L13 if not var26
     145 [-]: JUMPIFLE R5 R18 L12; goto L12 if var5 <= var16783899
     146 [-]: LOADB R26 0 +1; var26 = false
L12: 147 [-]: LOADB R26 1  ; var26 = true
L13: 148 [-]: MOVE R16 R26 ; var16 = var26
     149 [-]: MOVE R26 R17 ; var26 = var17
     150 [-]: JUMPIF R26 L15; goto L15 if var26
     151 [-]: JUMPIFLE R18 R6 L14; goto L14 if var18 <= var16783899
     152 [-]: LOADB R26 0 +1; var26 = false
L14: 153 [-]: LOADB R26 1  ; var26 = true
L15: 154 [-]: MOVE R17 R26 ; var17 = var26
     155 [-]: JUMPIFNOT R16 L16; goto L16 if not var16
     156 [-]: FORNLOOP R23 L11; nforloop end - iterate + goto L11
L16: 157 [-]: JUMPIFNOT R16 L17; goto L17 if not var16
     158 [-]: MOVE R23 R17 ; var23 = var17
     159 [-]: JUMPIF R23 L19; goto L19 if var23
L17: 160 [-]: GETIMPORT R25 29; var25 = _T["DynamicExcavatorSpawnPoints"]
     161 [-]: LENGTH R24 R25; var24 = #var25
     162 [-]: JUMPXEQKN R24 K32 L18; 
     163 [-]: LOADB R23 0 +1; var23 = false
L18: 164 [-]: LOADB R23 1  ; var23 = true
L19: 165 [-]: MOVE R7 R23  ; var7 = var23
     166 [-]: JUMPIFNOT R7 L22; goto L22 if not var7
     167 [-]: GETIMPORT R23 34; var23 = 0xD644C2F1
     168 [-]: LOADK R24 K35; var24 = "DynamicExcavation: Spawn point found"
     169 [-]: CALL R23 2 1 ; var23(var24)
     170 [-]: GETIMPORT R23 37; var23 = 0x3D106989
     171 [-]: LOADK R24 K35; var24 = "DynamicExcavation: Spawn point found"
     172 [-]: CALL R23 2 1 ; var23(var24)
     173 [-]: MOVE R23 R12 ; var23 = var12
     174 [-]: GETIMPORT R25 1; var25 = 0xA421AF95
     175 [-]: LOADN R26 0  ; var26 = 0
     176 [-]: LOADN R27 100; var27 = 100
     177 [-]: LOADN R28 0  ; var28 = 0
     178 [-]: CALL R25 4 2 ; var25 = var25(var26, var27, var28)
     179 [-]: ADD R24 R12 R25; var24 = var12 + var25
     180 [-]: GETIMPORT R25 39; var25 = 0x60130201
     181 [-]: LOADN R26 0  ; var26 = 0
     182 [-]: LOADN R27 255; var27 = 255
     183 [-]: LOADN R28 0  ; var28 = 0
     184 [-]: CALL R25 4 2 ; var25 = var25(var26, var27, var28)
     185 [-]: RETURN R12 1 ; 
     186 [-]: JUMP L22     ; goto L22
L20: 187 [-]: GETIMPORT R23 34; var23 = 0xD644C2F1
     188 [-]: LOADK R24 K40; var24 = "DynamicExcavation: Rejecting location since drop position is not on landscape"
     189 [-]: CALL R23 2 1 ; var23(var24)
     190 [-]: GETIMPORT R23 37; var23 = 0x3D106989
     191 [-]: LOADK R24 K40; var24 = "DynamicExcavation: Rejecting location since drop position is not on landscape"
     192 [-]: CALL R23 2 1 ; var23(var24)
     193 [-]: JUMP L22     ; goto L22
L21: 194 [-]: LOADB R16 0  ; var16 = false
     195 [-]: LOADB R17 0  ; var17 = false
L22: 196 [-]: FORNLOOP R13 L3; nforloop end - iterate + goto L3
L23: 197 [-]: JUMPIF R7 L24; goto L24 if var7
     198 [-]: GETIMPORT R13 42; var13 = 0xCBD666E1
     199 [-]: LOADN R14 0  ; var14 = 0
     200 [-]: CALL R13 2 1 ; var13(var14)
L24: 201 [-]: JUMPBACK L2  ; goto L2
L25: 202 [-]: GETIMPORT R12 34; var12 = 0xD644C2F1
     203 [-]: LOADK R13 K43; var13 = "DynamicExcavation: Couldn't find spawn point: reverting to hint pos"
     204 [-]: CALL R12 2 1 ; var12(var13)
     205 [-]: GETIMPORT R12 37; var12 = 0x3D106989
     206 [-]: LOADK R13 K43; var13 = "DynamicExcavation: Couldn't find spawn point: reverting to hint pos"
     207 [-]: CALL R12 2 1 ; var12(var13)
     208 [-]: RETURN R0 1  ; 


; Name:            
; Defined at line: 286
; #Upvalues:       2
; #Parameters:     0
; Is_vararg:       0
; Max Stack Size:  12

       0 [-]: LOADN R0 0   ; var0 = 0
       1 [-]: GETIMPORT R1 1; var1 = 0xBE190284
       2 [-]: GETUPVAL R3 0; var3 = upvalues[0]
       3 [-]: LOADN R4 0   ; var4 = 0
       4 [-]: NAMECALL R1 R1 K2; var2 = var1; var1 = var1[0x0EB34C69]
       5 [-]: CALL R1 4 2  ; var1 = var1(var2, var3, var4)
       6 [-]: LOADN R2 0   ; var2 = 0
       7 [-]: GETIMPORT R3 4; var3 = 0xCFC01047
       8 [-]: GETUPVAL R4 1; var4 = upvalues[1]
       9 [-]: CALL R3 2 4  ; var3, var4, var5 = var3(var4)
      10 [-]: FORGPREP_NEXT R3 L2; 
L 0:  11 [-]: FASTCALL1 62 R7 L1; 
      12 [-]: MOVE R9 R7   ; var9 = var7
      13 [-]: GETIMPORT R8 6; var8 = 0x7B998233
      14 [-]: CALL R8 2 2  ; var8 = var8(var9)
L 1:  15 [-]: JUMPIF R8 L2 ; goto L2 if var8
      16 [-]: LOADN R9 100 ; var9 = 100
      17 [-]: NAMECALL R10 R7 K7; var11 = var7; var10 = var7[0x17DD42BB]
      18 [-]: CALL R10 2 2 ; var10 = var10(var11)
      19 [-]: SUB R8 R9 R10; var8 = var9 - var10
      20 [-]: ADD R2 R2 R8 ; var2 = var2 + var8
L 2:  21 [-]: FORGLOOP R3 L0 2; 
      22 [-]: MULK R3 R1 K8; var3 = var1 * 100
      23 [-]: DIV R0 R2 R3 ; var0 = var2 / var3
      24 [-]: RETURN R0 1  ; 


; Name:            
; Defined at line: 300
; #Upvalues:       2
; #Parameters:     0
; Is_vararg:       0
; Max Stack Size:  2

       0 [-]: GETUPVAL R0 0; var0 = upvalues[0]
       1 [-]: CALL R0 1 2  ; var0 = var0()
       2 [-]: MUL R1 R0 R0 ; var1 = var0 * var0
       3 [-]: SETUPVAL R1 1; upvalues[1] = var1
       4 [-]: RETURN R0 0  ; 


; Name:            
; Defined at line: 305
; #Upvalues:       0
; #Parameters:     1
; Is_vararg:       0
; Max Stack Size:  6

       0 [-]: GETIMPORT R1 1; var1 = 0xBE190284
       1 [-]: MOVE R3 R0   ; var3 = var0
       2 [-]: LOADN R4 0   ; var4 = 0
       3 [-]: NAMECALL R1 R1 K2; var2 = var1; var1 = var1[0x0EB34C69]
       4 [-]: CALL R1 4 2  ; var1 = var1(var2, var3, var4)
       5 [-]: ADDK R1 R1 K3; var1 = var1 + 1
       6 [-]: GETIMPORT R2 1; var2 = 0xBE190284
       7 [-]: MOVE R4 R0   ; var4 = var0
       8 [-]: MOVE R5 R1   ; var5 = var1
       9 [-]: NAMECALL R2 R2 K4; var3 = var2; var2 = var2[0x751F061D]
      10 [-]: CALL R2 4 1  ; var2(var3, var4, var5)
      11 [-]: RETURN R0 0  ; 


; Name:            
; Defined at line: 311
; #Upvalues:       0
; #Parameters:     4
; Is_vararg:       0
; Max Stack Size:  11

       0 [-]: JUMPIFNOT R3 L8; goto L8 if not var3
       1 [-]: FASTCALL1 62 R0 L0; 
       2 [-]: MOVE R5 R0   ; var5 = var0
       3 [-]: GETIMPORT R4 1; var4 = 0x7B998233
       4 [-]: CALL R4 2 2  ; var4 = var4(var5)
L 0:   5 [-]: JUMPIF R4 L1 ; goto L1 if var4
       6 [-]: LOADB R6 1   ; var6 = true
       7 [-]: LOADB R7 0   ; var7 = false
       8 [-]: NAMECALL R4 R0 K2; var5 = var0; var4 = var0[0x768274D6]
       9 [-]: CALL R4 4 1  ; var4(var5, var6, var7)
L 1:  10 [-]: GETIMPORT R4 4; var4 = 0xC8802016
      11 [-]: MOVE R5 R1   ; var5 = var1
      12 [-]: CALL R4 2 4  ; var4, var5, var6 = var4(var5)
      13 [-]: FORGPREP_INEXT R4 L4; 
L 2:  14 [-]: FASTCALL1 62 R8 L3; 
      15 [-]: MOVE R10 R8  ; var10 = var8
      16 [-]: GETIMPORT R9 1; var9 = 0x7B998233
      17 [-]: CALL R9 2 2  ; var9 = var9(var10)
L 3:  18 [-]: JUMPIF R9 L4 ; goto L4 if var9
      19 [-]: NAMECALL R9 R8 K5; var10 = var8; var9 = var8[0x383D2E7D]
      20 [-]: CALL R9 2 1  ; var9(var10)
L 4:  21 [-]: FORGLOOP R4 L2 2 [inext]; 
      22 [-]: GETIMPORT R4 4; var4 = 0xC8802016
      23 [-]: MOVE R5 R2   ; var5 = var2
      24 [-]: CALL R4 2 4  ; var4, var5, var6 = var4(var5)
      25 [-]: FORGPREP_INEXT R4 L7; 
L 5:  26 [-]: FASTCALL1 62 R8 L6; 
      27 [-]: MOVE R10 R8  ; var10 = var8
      28 [-]: GETIMPORT R9 1; var9 = 0x7B998233
      29 [-]: CALL R9 2 2  ; var9 = var9(var10)
L 6:  30 [-]: JUMPIF R9 L7 ; goto L7 if var9
      31 [-]: NAMECALL R9 R8 K5; var10 = var8; var9 = var8[0x383D2E7D]
      32 [-]: CALL R9 2 1  ; var9(var10)
L 7:  33 [-]: FORGLOOP R4 L5 2 [inext]; 
      34 [-]: RETURN R0 0  ; 
L 8:  35 [-]: FASTCALL1 62 R0 L9; 
      36 [-]: MOVE R5 R0   ; var5 = var0
      37 [-]: GETIMPORT R4 1; var4 = 0x7B998233
      38 [-]: CALL R4 2 2  ; var4 = var4(var5)
L 9:  39 [-]: JUMPIF R4 L10; goto L10 if var4
      40 [-]: LOADB R6 0   ; var6 = false
      41 [-]: LOADB R7 0   ; var7 = false
      42 [-]: NAMECALL R4 R0 K2; var5 = var0; var4 = var0[0x768274D6]
      43 [-]: CALL R4 4 1  ; var4(var5, var6, var7)
L10:  44 [-]: GETIMPORT R4 4; var4 = 0xC8802016
      45 [-]: MOVE R5 R1   ; var5 = var1
      46 [-]: CALL R4 2 4  ; var4, var5, var6 = var4(var5)
      47 [-]: FORGPREP_INEXT R4 L13; 
L11:  48 [-]: FASTCALL1 62 R8 L12; 
      49 [-]: MOVE R10 R8  ; var10 = var8
      50 [-]: GETIMPORT R9 1; var9 = 0x7B998233
      51 [-]: CALL R9 2 2  ; var9 = var9(var10)
L12:  52 [-]: JUMPIF R9 L13; goto L13 if var9
      53 [-]: NAMECALL R9 R8 K6; var10 = var8; var9 = var8[0xF4E253B6]
      54 [-]: CALL R9 2 1  ; var9(var10)
L13:  55 [-]: FORGLOOP R4 L11 2 [inext]; 
      56 [-]: GETIMPORT R4 4; var4 = 0xC8802016
      57 [-]: MOVE R5 R2   ; var5 = var2
      58 [-]: CALL R4 2 4  ; var4, var5, var6 = var4(var5)
      59 [-]: FORGPREP_INEXT R4 L16; 
L14:  60 [-]: FASTCALL1 62 R8 L15; 
      61 [-]: MOVE R10 R8  ; var10 = var8
      62 [-]: GETIMPORT R9 1; var9 = 0x7B998233
      63 [-]: CALL R9 2 2  ; var9 = var9(var10)
L15:  64 [-]: JUMPIF R9 L16; goto L16 if var9
      65 [-]: NAMECALL R9 R8 K6; var10 = var8; var9 = var8[0xF4E253B6]
      66 [-]: CALL R9 2 1  ; var9(var10)
L16:  67 [-]: FORGLOOP R4 L14 2 [inext]; 
      68 [-]: RETURN R0 0  ; 


; Name:            
; Defined at line: 343
; #Upvalues:       0
; #Parameters:     1
; Is_vararg:       0
; Max Stack Size:  6

       0 [-]: NAMECALL R1 R0 K0; var2 = var0; var1 = var0[0x08E5889B]
       1 [-]: CALL R1 2 2  ; var1 = var1(var2)
       2 [-]: NAMECALL R2 R0 K1; var3 = var0; var2 = var0[0x17DD42BB]
       3 [-]: CALL R2 2 2  ; var2 = var2(var3)
       4 [-]: FASTCALL1 12 R2 L0; 
       5 [-]: MOVE R5 R2   ; var5 = var2
       6 [-]: GETIMPORT R4 4; var4 = 0x5BCED4C4[0x55F27C30]
       7 [-]: CALL R4 2 2  ; var4 = var4(var5)
L 0:   8 [-]: JUMPIFLE R4 R1 L1; goto L1 if var4 <= var16778011
       9 [-]: LOADB R3 0 +1; var3 = false
L 1:  10 [-]: LOADB R3 1   ; var3 = true
L 2:  11 [-]: RETURN R3 1  ; 


; Name:            
; Defined at line: 350
; #Upvalues:       1
; #Parameters:     1
; Is_vararg:       0
; Max Stack Size:  16

       0 [-]: GETIMPORT R1 1; var1 = 0x89326C93
       1 [-]: NAMECALL R1 R1 K2; var2 = var1; var1 = var1[0x8B5B1F58]
       2 [-]: CALL R1 2 2  ; var1 = var1(var2)
       3 [-]: NAMECALL R2 R0 K3; var3 = var0; var2 = var0[0xBB610E5B]
       4 [-]: CALL R2 2 2  ; var2 = var2(var3)
       5 [-]: LOADN R3 0   ; var3 = 0
       6 [-]: FASTCALL1 62 R2 L0; 
       7 [-]: MOVE R5 R2   ; var5 = var2
       8 [-]: GETIMPORT R4 5; var4 = 0x7B998233
       9 [-]: CALL R4 2 2  ; var4 = var4(var5)
L 0:  10 [-]: JUMPIF R4 L10; goto L10 if var4
      11 [-]: LOADN R6 1   ; var6 = 1
      12 [-]: LENGTH R4 R1 ; var4 = #var1
      13 [-]: LOADN R5 1   ; var5 = 1
      14 [-]: FORNPREP R4 L10; nforprep start - [escape at L10] -- var4 = iterator
L 1:  15 [-]: GETTABLE R7 R1 R6; var7 = var1[var6]
      16 [-]: FASTCALL1 62 R2 L2; 
      17 [-]: MOVE R9 R2   ; var9 = var2
      18 [-]: GETIMPORT R8 5; var8 = 0x7B998233
      19 [-]: CALL R8 2 2  ; var8 = var8(var9)
L 2:  20 [-]: JUMPIF R8 L9 ; goto L9 if var8
      21 [-]: GETUPVAL R10 0; var10 = upvalues[0]
      22 [-]: NAMECALL R8 R7 K6; var9 = var7; var8 = var7[0x0866B4BD]
      23 [-]: CALL R8 3 2  ; var8 = var8(var9, var10)
      24 [-]: JUMPIFNOT R8 L9; goto L9 if not var8
      25 [-]: MOVE R11 R2  ; var11 = var2
      26 [-]: NAMECALL R9 R7 K7; var10 = var7; var9 = var7[0xBEBAD19F]
      27 [-]: CALL R9 3 2  ; var9 = var9(var10, var11)
      28 [-]: LOADN R10 5  ; var10 = 5
      29 [-]: JUMPIFLT R9 R10 L3; goto L3 if var9 < var16779291
      30 [-]: LOADB R8 0 +1; var8 = false
L 3:  31 [-]: LOADB R8 1   ; var8 = true
L 4:  32 [-]: NAMECALL R9 R2 K8; var10 = var2; var9 = var2[0x1AC1655C]
      33 [-]: CALL R9 2 2  ; var9 = var9(var10)
      34 [-]: NAMECALL R9 R9 K9; var10 = var9; var9 = var9[0xB87F958D]
      35 [-]: CALL R9 2 2  ; var9 = var9(var10)
      36 [-]: NAMECALL R10 R2 K8; var11 = var2; var10 = var2[0x1AC1655C]
      37 [-]: CALL R10 2 2 ; var10 = var10(var11)
      38 [-]: NAMECALL R10 R10 K10; var11 = var10; var10 = var10[0xD127117D]
      39 [-]: CALL R10 2 2 ; var10 = var10(var11)
      40 [-]: JUMPIFNOT R8 L9; goto L9 if not var8
      41 [-]: NAMECALL R12 R0 K11; var13 = var0; var12 = var0[0x08E5889B]
      42 [-]: CALL R12 2 2 ; var12 = var12(var13)
      43 [-]: NAMECALL R13 R0 K12; var14 = var0; var13 = var0[0x17DD42BB]
      44 [-]: CALL R13 2 2 ; var13 = var13(var14)
      45 [-]: FASTCALL1 12 R13 L5; 
      46 [-]: MOVE R15 R13 ; var15 = var13
      47 [-]: GETIMPORT R14 15; var14 = 0x5BCED4C4[0x55F27C30]
      48 [-]: CALL R14 2 2 ; var14 = var14(var15)
L 5:  49 [-]: JUMPIFLE R14 R12 L6; goto L6 if var14 <= var16780059
      50 [-]: LOADB R11 0 +1; var11 = false
L 6:  51 [-]: LOADB R11 1  ; var11 = true
L 7:  52 [-]: JUMPIFNOT R11 L8; goto L8 if not var11
      53 [-]: JUMPIFNOTLT R10 R9 L9; goto L9 if var10 >= var3335
L 8:  54 [-]: GETUPVAL R13 0; var13 = upvalues[0]
      55 [-]: NAMECALL R11 R7 K16; var12 = var7; var11 = var7[0x35B09371]
      56 [-]: CALL R11 3 1 ; var11(var12, var13)
      57 [-]: GETIMPORT R13 18; var13 = 0xEF8F0445
      58 [-]: LOADB R14 0  ; var14 = false
      59 [-]: NAMECALL R11 R7 K19; var12 = var7; var11 = var7[0x659D451F]
      60 [-]: CALL R11 4 1 ; var11(var12, var13, var14)
      61 [-]: ADDK R3 R3 K20; var3 = var3 + 1
L 9:  62 [-]: FORNLOOP R4 L1; nforloop end - iterate + goto L1
L10:  63 [-]: RETURN R3 1  ; 


; Name:            
; Defined at line: 374
; #Upvalues:       1
; #Parameters:     1
; Is_vararg:       0
; Max Stack Size:  13

       0 [-]: NAMECALL R1 R0 K0; var2 = var0; var1 = var0[0x22DF603C]
       1 [-]: CALL R1 2 2  ; var1 = var1(var2)
       2 [-]: GETIMPORT R2 2; var2 = 0xD644C2F1
       3 [-]: LOADK R3 K3  ; var3 = "Reassigning all agents to storm other excavators"
       4 [-]: CALL R2 2 1  ; var2(var3)
       5 [-]: GETIMPORT R2 5; var2 = 0x3D106989
       6 [-]: LOADK R3 K3  ; var3 = "Reassigning all agents to storm other excavators"
       7 [-]: CALL R2 2 1  ; var2(var3)
       8 [-]: GETIMPORT R2 7; var2 = 0xC8802016
       9 [-]: MOVE R3 R1   ; var3 = var1
      10 [-]: CALL R2 2 4  ; var2, var3, var4 = var2(var3)
      11 [-]: FORGPREP_INEXT R2 L2; 
L 0:  12 [-]: NAMECALL R7 R6 K8; var8 = var6; var7 = var6[0xBB610E5B]
      13 [-]: CALL R7 2 2  ; var7 = var7(var8)
      14 [-]: GETIMPORT R8 10; var8 = 0x89326C93
      15 [-]: GETUPVAL R10 0; var10 = upvalues[0]
      16 [-]: NAMECALL R11 R7 K11; var12 = var7; var11 = var7[0xD1586535]
      17 [-]: CALL R11 2 0 ; var11, ... = var11(var12)
      18 [-]: NAMECALL R8 R8 K12; var9 = var8; var8 = var8[0xC7B81E8D]
      19 [-]: CALL R8 0 2  ; var8 = var8(var9, ...)
      20 [-]: FASTCALL1 62 R8 L1; 
      21 [-]: MOVE R10 R8  ; var10 = var8
      22 [-]: GETIMPORT R9 14; var9 = 0x7B998233
      23 [-]: CALL R9 2 2  ; var9 = var9(var10)
L 1:  24 [-]: JUMPIF R9 L2 ; goto L2 if var9
      25 [-]: MOVE R11 R8  ; var11 = var8
      26 [-]: NAMECALL R9 R6 K15; var10 = var6; var9 = var6[0xA64A1F4A]
      27 [-]: CALL R9 3 1  ; var9(var10, var11)
L 2:  28 [-]: FORGLOOP R2 L0 2 [inext]; 
      29 [-]: RETURN R0 0  ; 


; Name:            
; Defined at line: 386
; #Upvalues:       4
; #Parameters:     1
; Is_vararg:       0
; Max Stack Size:  12

       0 [-]: FASTCALL1 62 R0 L0; 
       1 [-]: MOVE R2 R0   ; var2 = var0
       2 [-]: GETIMPORT R1 1; var1 = 0x7B998233
       3 [-]: CALL R1 2 2  ; var1 = var1(var2)
L 0:   4 [-]: JUMPIF R1 L13; goto L13 if var1
       5 [-]: NAMECALL R1 R0 K2; var2 = var0; var1 = var0[0xF329A790]
       6 [-]: CALL R1 2 2  ; var1 = var1(var2)
       7 [-]: NAMECALL R2 R0 K3; var3 = var0; var2 = var0[0xBB610E5B]
       8 [-]: CALL R2 2 2  ; var2 = var2(var3)
       9 [-]: NAMECALL R3 R2 K4; var4 = var2; var3 = var2[0xD1586535]
      10 [-]: CALL R3 2 2  ; var3 = var3(var4)
      11 [-]: GETIMPORT R4 6; var4 = 0x89326C93
      12 [-]: GETIMPORT R6 8; var6 = 0xD02846B9
      13 [-]: MOVE R7 R3   ; var7 = var3
      14 [-]: GETIMPORT R8 10; var8 = ZERO_ROTATION
      15 [-]: LOADNIL R9   ; var9 = nil
      16 [-]: LOADNIL R10  ; var10 = nil
      17 [-]: NAMECALL R4 R4 K11; var5 = var4; var4 = var4[0x05909209]
      18 [-]: CALL R4 7 1  ; var4(var5, var6, var7, var8, var9, var10)
      19 [-]: LOADNIL R4   ; var4 = nil
      20 [-]: FASTCALL1 62 R2 L1; 
      21 [-]: MOVE R6 R2   ; var6 = var2
      22 [-]: GETIMPORT R5 1; var5 = 0x7B998233
      23 [-]: CALL R5 2 2  ; var5 = var5(var6)
L 1:  24 [-]: JUMPIF R5 L3 ; goto L3 if var5
      25 [-]: NAMECALL R5 R2 K12; var6 = var2; var5 = var2[0xFA9E477F]
      26 [-]: CALL R5 2 2  ; var5 = var5(var6)
      27 [-]: FASTCALL1 62 R5 L2; 
      28 [-]: MOVE R7 R5   ; var7 = var5
      29 [-]: GETIMPORT R6 1; var6 = 0x7B998233
      30 [-]: CALL R6 2 2  ; var6 = var6(var7)
L 2:  31 [-]: JUMPIF R6 L3 ; goto L3 if var6
      32 [-]: NAMECALL R6 R5 K13; var7 = var5; var6 = var5[0x96A5DCEB]
      33 [-]: CALL R6 2 2  ; var6 = var6(var7)
      34 [-]: MOVE R4 R6   ; var4 = var6
L 3:  35 [-]: NAMECALL R5 R0 K14; var6 = var0; var5 = var0[0x17DD42BB]
      36 [-]: CALL R5 2 2  ; var5 = var5(var6)
      37 [-]: SUBK R6 R5 K15; var6 = var5 - 0.01
      38 [-]: LOADN R7 0   ; var7 = 0
      39 [-]: JUMPIFNOTLT R7 R6 L4; goto L4 if var7 >= var1543
      40 [-]: GETUPVAL R6 0; var6 = upvalues[0]
      41 [-]: GETIMPORT R7 17; var7 = 0xBE190284
      42 [-]: MOVE R9 R6   ; var9 = var6
      43 [-]: LOADN R10 0  ; var10 = 0
      44 [-]: NAMECALL R7 R7 K18; var8 = var7; var7 = var7[0x0EB34C69]
      45 [-]: CALL R7 4 2  ; var7 = var7(var8, var9, var10)
      46 [-]: ADDK R7 R7 K19; var7 = var7 + 1
      47 [-]: GETIMPORT R8 17; var8 = 0xBE190284
      48 [-]: MOVE R10 R6  ; var10 = var6
      49 [-]: MOVE R11 R7  ; var11 = var7
      50 [-]: NAMECALL R8 R8 K20; var9 = var8; var8 = var8[0x751F061D]
      51 [-]: CALL R8 4 1  ; var8(var9, var10, var11)
      52 [-]: GETIMPORT R6 17; var6 = 0xBE190284
      53 [-]: GETUPVAL R8 0; var8 = upvalues[0]
      54 [-]: LOADN R9 0   ; var9 = 0
      55 [-]: NAMECALL R6 R6 K18; var7 = var6; var6 = var6[0x0EB34C69]
      56 [-]: CALL R6 4 2  ; var6 = var6(var7, var8, var9)
      57 [-]: GETIMPORT R7 6; var7 = 0x89326C93
      58 [-]: NAMECALL R7 R7 K21; var8 = var7; var7 = var7[0x8B5B1F58]
      59 [-]: CALL R7 2 2  ; var7 = var7(var8)
      60 [-]: LENGTH R9 R7 ; var9 = #var7
      61 [-]: ADDK R8 R9 K19; var8 = var9 + 1
      62 [-]: JUMPIFNOTLT R6 R8 L4; goto L4 if var6 >= var67847
      63 [-]: GETUPVAL R9 1; var9 = upvalues[1]
      64 [-]: GETTABLEKS R8 R9 K22; var8 = var9[0x9742B85B]
      65 [-]: GETIMPORT R9 25; var9 = _T["TransmissionSet"]
      66 [-]: GETIMPORT R10 27; var10 = 0x0469F296
      67 [-]: LOADK R11 K28; var11 = "DynamicExcavation_ExcavatorDestroyed"
      68 [-]: CALL R10 2 0 ; var10, ... = var10(var11)
      69 [-]: CALL R8 0 1  ; var8(var9, ...)
L 4:  70 [-]: GETIMPORT R7 30; var7 = _T["DynamicExcavationHudInfo"]
      71 [-]: FASTCALL1 62 R7 L5; 
      72 [-]: GETIMPORT R6 1; var6 = 0x7B998233
      73 [-]: CALL R6 2 2  ; var6 = var6(var7)
L 5:  74 [-]: JUMPIF R6 L7 ; goto L7 if var6
      75 [-]: GETIMPORT R8 30; var8 = _T["DynamicExcavationHudInfo"]
      76 [-]: GETTABLE R7 R8 R1; var7 = var8[var1]
      77 [-]: FASTCALL1 62 R7 L6; 
      78 [-]: GETIMPORT R6 1; var6 = 0x7B998233
      79 [-]: CALL R6 2 2  ; var6 = var6(var7)
L 6:  80 [-]: JUMPIF R6 L7 ; goto L7 if var6
      81 [-]: GETIMPORT R6 32; var6 = _T["RemoveHudTracker"]
      82 [-]: GETIMPORT R9 30; var9 = _T["DynamicExcavationHudInfo"]
      83 [-]: GETTABLE R8 R9 R1; var8 = var9[var1]
      84 [-]: GETTABLEN R7 R8 1; var7 = var8[1]
      85 [-]: CALL R6 2 1  ; var6(var7)
      86 [-]: GETIMPORT R6 32; var6 = _T["RemoveHudTracker"]
      87 [-]: GETIMPORT R9 30; var9 = _T["DynamicExcavationHudInfo"]
      88 [-]: GETTABLE R8 R9 R1; var8 = var9[var1]
      89 [-]: GETTABLEN R7 R8 2; var7 = var8[2]
      90 [-]: CALL R6 2 1  ; var6(var7)
      91 [-]: GETIMPORT R6 30; var6 = _T["DynamicExcavationHudInfo"]
      92 [-]: LOADNIL R7   ; var7 = nil
      93 [-]: SETTABLE R7 R6 R1; var7[var6] = var1
L 7:  94 [-]: FASTCALL1 62 R0 L8; 
      95 [-]: MOVE R7 R0   ; var7 = var0
      96 [-]: GETIMPORT R6 1; var6 = 0x7B998233
      97 [-]: CALL R6 2 2  ; var6 = var6(var7)
L 8:  98 [-]: JUMPIF R6 L9 ; goto L9 if var6
      99 [-]: NAMECALL R6 R0 K33; var7 = var0; var6 = var0[0xA2880940]
     100 [-]: CALL R6 2 1  ; var6(var7)
L 9: 101 [-]: GETIMPORT R6 6; var6 = 0x89326C93
     102 [-]: GETUPVAL R8 2; var8 = upvalues[2]
     103 [-]: MOVE R9 R3   ; var9 = var3
     104 [-]: NAMECALL R6 R6 K34; var7 = var6; var6 = var6[0xC7B81E8D]
     105 [-]: CALL R6 4 2  ; var6 = var6(var7, var8, var9)
     106 [-]: FASTCALL1 62 R6 L10; 
     107 [-]: MOVE R8 R6   ; var8 = var6
     108 [-]: GETIMPORT R7 1; var7 = 0x7B998233
     109 [-]: CALL R7 2 2  ; var7 = var7(var8)
L10: 110 [-]: JUMPIF R7 L11; goto L11 if var7
     111 [-]: NAMECALL R7 R6 K33; var8 = var6; var7 = var6[0xA2880940]
     112 [-]: CALL R7 2 1  ; var7(var8)
L11: 113 [-]: FASTCALL1 62 R4 L12; 
     114 [-]: MOVE R8 R4   ; var8 = var4
     115 [-]: GETIMPORT R7 1; var7 = 0x7B998233
     116 [-]: CALL R7 2 2  ; var7 = var7(var8)
L12: 117 [-]: JUMPIF R7 L13; goto L13 if var7
     118 [-]: GETUPVAL R7 3; var7 = upvalues[3]
     119 [-]: MOVE R8 R4   ; var8 = var4
     120 [-]: CALL R7 2 1  ; var7(var8)
L13: 121 [-]: RETURN R0 0  ; 


; Name:            
; Defined at line: 430
; #Upvalues:       0
; #Parameters:     1
; Is_vararg:       0
; Max Stack Size:  7

       0 [-]: FASTCALL1 62 R0 L0; 
       1 [-]: MOVE R2 R0   ; var2 = var0
       2 [-]: GETIMPORT R1 1; var1 = 0x7B998233
       3 [-]: CALL R1 2 2  ; var1 = var1(var2)
L 0:   4 [-]: JUMPIF R1 L2 ; goto L2 if var1
       5 [-]: NAMECALL R1 R0 K2; var2 = var0; var1 = var0[0xBB610E5B]
       6 [-]: CALL R1 2 2  ; var1 = var1(var2)
       7 [-]: FASTCALL1 62 R1 L1; 
       8 [-]: MOVE R3 R1   ; var3 = var1
       9 [-]: GETIMPORT R2 1; var2 = 0x7B998233
      10 [-]: CALL R2 2 2  ; var2 = var2(var3)
L 1:  11 [-]: JUMPIF R2 L2 ; goto L2 if var2
      12 [-]: GETIMPORT R2 5; var2 = 0x34291F5C[0x35C16153]
      13 [-]: CALL R2 1 2  ; var2 = var2()
      14 [-]: LOADN R5 0   ; var5 = 0
      15 [-]: LOADN R6 1   ; var6 = 1
      16 [-]: NAMECALL R3 R2 K6; var4 = var2; var3 = var2[0x1586E35E]
      17 [-]: CALL R3 4 1  ; var3(var4, var5, var6)
      18 [-]: LOADK R3 K7  ; var3 = 9999999
      19 [-]: SETTABLEKS R3 R2 K8; var3["baseAmount"] = var2
      20 [-]: GETGLOBAL R5 K9; var5 = 0x5AA2084E
      21 [-]: NAMECALL R3 R1 K10; var4 = var1; var3 = var1[0x0CCA925A]
      22 [-]: CALL R3 3 1  ; var3(var4, var5)
      23 [-]: MOVE R5 R2   ; var5 = var2
      24 [-]: NAMECALL R3 R1 K11; var4 = var1; var3 = var1[0x479483BB]
      25 [-]: CALL R3 3 1  ; var3(var4, var5)
L 2:  26 [-]: RETURN R0 0  ; 


; Name:            
; Defined at line: 444
; #Upvalues:       2
; #Parameters:     1
; Is_vararg:       0
; Max Stack Size:  7

       0 [-]: FASTCALL1 62 R0 L0; 
       1 [-]: MOVE R2 R0   ; var2 = var0
       2 [-]: GETIMPORT R1 1; var1 = 0x7B998233
       3 [-]: CALL R1 2 2  ; var1 = var1(var2)
L 0:   4 [-]: JUMPIF R1 L1 ; goto L1 if var1
       5 [-]: GETUPVAL R1 0; var1 = upvalues[0]
       6 [-]: GETIMPORT R2 3; var2 = 0xBE190284
       7 [-]: MOVE R4 R1   ; var4 = var1
       8 [-]: LOADN R5 0   ; var5 = 0
       9 [-]: NAMECALL R2 R2 K4; var3 = var2; var2 = var2[0x0EB34C69]
      10 [-]: CALL R2 4 2  ; var2 = var2(var3, var4, var5)
      11 [-]: ADDK R2 R2 K5; var2 = var2 + 1
      12 [-]: GETIMPORT R3 3; var3 = 0xBE190284
      13 [-]: MOVE R5 R1   ; var5 = var1
      14 [-]: MOVE R6 R2   ; var6 = var2
      15 [-]: NAMECALL R3 R3 K6; var4 = var3; var3 = var3[0x751F061D]
      16 [-]: CALL R3 4 1  ; var3(var4, var5, var6)
      17 [-]: GETUPVAL R1 1; var1 = upvalues[1]
      18 [-]: MOVE R2 R0   ; var2 = var0
      19 [-]: CALL R1 2 1  ; var1(var2)
L 1:  20 [-]: RETURN R0 0  ; 


; Name:            
; Defined at line: 451
; #Upvalues:       10
; #Parameters:     1
; Is_vararg:       0
; Max Stack Size:  16

       0 [-]: FASTCALL1 62 R0 L0; 
       1 [-]: MOVE R2 R0   ; var2 = var0
       2 [-]: GETIMPORT R1 1; var1 = 0x7B998233
       3 [-]: CALL R1 2 2  ; var1 = var1(var2)
L 0:   4 [-]: JUMPIF R1 L16; goto L16 if var1
       5 [-]: FASTCALL1 62 R0 L1; 
       6 [-]: MOVE R2 R0   ; var2 = var0
       7 [-]: GETIMPORT R1 1; var1 = 0x7B998233
       8 [-]: CALL R1 2 2  ; var1 = var1(var2)
L 1:   9 [-]: JUMPIF R1 L16; goto L16 if var1
      10 [-]: NAMECALL R1 R0 K2; var2 = var0; var1 = var0[0xBB610E5B]
      11 [-]: CALL R1 2 2  ; var1 = var1(var2)
      12 [-]: FASTCALL1 62 R1 L2; 
      13 [-]: MOVE R3 R1   ; var3 = var1
      14 [-]: GETIMPORT R2 1; var2 = 0x7B998233
      15 [-]: CALL R2 2 2  ; var2 = var2(var3)
L 2:  16 [-]: JUMPIFNOT R2 L3; goto L3 if not var2
      17 [-]: RETURN R0 0  ; 
L 3:  18 [-]: GETUPVAL R2 0; var2 = upvalues[0]
      19 [-]: MOVE R3 R0   ; var3 = var0
      20 [-]: CALL R2 2 2  ; var2 = var2(var3)
      21 [-]: NAMECALL R3 R0 K3; var4 = var0; var3 = var0[0x08E5889B]
      22 [-]: CALL R3 2 2  ; var3 = var3(var4)
      23 [-]: LOADN R4 0   ; var4 = 0
      24 [-]: JUMPIFNOTLT R4 R2 L5; goto L5 if var4 >= var66823
      25 [-]: GETUPVAL R5 1; var5 = upvalues[1]
      26 [-]: GETTABLEKS R4 R5 K4; var4 = var5[0x74A11EC6]
      27 [-]: LOADN R7 20  ; var7 = 20
      28 [-]: MUL R6 R7 R2 ; var6 = var7 * var2
      29 [-]: LOADN R8 100 ; var8 = 100
      30 [-]: SUB R7 R8 R3 ; var7 = var8 - var3
      31 [-]: FASTCALL2 19 R6 R7 L4; 
      32 [-]: GETIMPORT R5 7; var5 = 0x5BCED4C4[0xAC1B386A]
      33 [-]: CALL R5 3 2  ; var5 = var5(var6, var7)
L 4:  34 [-]: CALL R4 2 2  ; var4 = var4(var5)
      35 [-]: ADD R3 R3 R4 ; var3 = var3 + var4
      36 [-]: NAMECALL R5 R1 K8; var6 = var1; var5 = var1[0x1AC1655C]
      37 [-]: CALL R5 2 2  ; var5 = var5(var6)
      38 [-]: NAMECALL R5 R5 K9; var6 = var5; var5 = var5[0xB87F958D]
      39 [-]: CALL R5 2 2  ; var5 = var5(var6)
      40 [-]: NAMECALL R6 R1 K8; var7 = var1; var6 = var1[0x1AC1655C]
      41 [-]: CALL R6 2 2  ; var6 = var6(var7)
      42 [-]: MOVE R8 R5   ; var8 = var5
      43 [-]: NAMECALL R6 R6 K10; var7 = var6; var6 = var6[0x57369B8B]
      44 [-]: CALL R6 3 1  ; var6(var7, var8)
L 5:  45 [-]: NAMECALL R4 R0 K11; var5 = var0; var4 = var0[0x17DD42BB]
      46 [-]: CALL R4 2 2  ; var4 = var4(var5)
      47 [-]: LOADN R5 0   ; var5 = 0
      48 [-]: JUMPIFNOTLT R5 R3 L8; goto L8 if var5 >= var1351
      49 [-]: LOADN R5 0   ; var5 = 0
      50 [-]: JUMPIFNOTLT R5 R4 L8; goto L8 if var5 >= var919118
      51 [-]: GETIMPORT R6 14; var6 = 0xFFF641AF
      52 [-]: CALL R6 1 2  ; var6 = var6()
      53 [-]: MULK R5 R6 K12; var5 = var6 * 1
      54 [-]: SUB R3 R3 R5 ; var3 = var3 - var5
      55 [-]: MOVE R8 R3   ; var8 = var3
      56 [-]: NAMECALL R6 R0 K15; var7 = var0; var6 = var0[0x8061B6D7]
      57 [-]: CALL R6 3 1  ; var6(var7, var8)
      58 [-]: SUB R4 R4 R5 ; var4 = var4 - var5
      59 [-]: MOVE R8 R4   ; var8 = var4
      60 [-]: NAMECALL R6 R0 K16; var7 = var0; var6 = var0[0x2F5F5657]
      61 [-]: CALL R6 3 1  ; var6(var7, var8)
      62 [-]: SUBK R6 R4 K17; var6 = var4 - 0.01
      63 [-]: LOADN R7 0   ; var7 = 0
      64 [-]: JUMPIFNOTLE R6 R7 L8; goto L8 if var6 > var50347595
      65 [-]: FASTCALL1 62 R0 L6; 
      66 [-]: MOVE R7 R0   ; var7 = var0
      67 [-]: GETIMPORT R6 1; var6 = 0x7B998233
      68 [-]: CALL R6 2 2  ; var6 = var6(var7)
L 6:  69 [-]: JUMPIF R6 L7 ; goto L7 if var6
      70 [-]: GETUPVAL R6 2; var6 = upvalues[2]
      71 [-]: GETIMPORT R7 19; var7 = 0xBE190284
      72 [-]: MOVE R9 R6   ; var9 = var6
      73 [-]: LOADN R10 0  ; var10 = 0
      74 [-]: NAMECALL R7 R7 K20; var8 = var7; var7 = var7[0x0EB34C69]
      75 [-]: CALL R7 4 2  ; var7 = var7(var8, var9, var10)
      76 [-]: ADDK R7 R7 K12; var7 = var7 + 1
      77 [-]: GETIMPORT R8 19; var8 = 0xBE190284
      78 [-]: MOVE R10 R6  ; var10 = var6
      79 [-]: MOVE R11 R7  ; var11 = var7
      80 [-]: NAMECALL R8 R8 K21; var9 = var8; var8 = var8[0x751F061D]
      81 [-]: CALL R8 4 1  ; var8(var9, var10, var11)
      82 [-]: GETUPVAL R6 3; var6 = upvalues[3]
      83 [-]: MOVE R7 R0   ; var7 = var0
      84 [-]: CALL R6 2 1  ; var6(var7)
L 7:  85 [-]: RETURN R0 0  ; 
L 8:  86 [-]: GETIMPORT R7 23; var7 = gParticleSysType
      87 [-]: NAMECALL R5 R1 K24; var6 = var1; var5 = var1[0xC1595BD5]
      88 [-]: CALL R5 3 2  ; var5 = var5(var6, var7)
      89 [-]: GETIMPORT R8 26; var8 = gSequencerType
      90 [-]: NAMECALL R6 R1 K24; var7 = var1; var6 = var1[0xC1595BD5]
      91 [-]: CALL R6 3 2  ; var6 = var6(var7, var8)
      92 [-]: GETIMPORT R9 28; var9 = 0xB1D7E36F
      93 [-]: NAMECALL R7 R1 K29; var8 = var1; var7 = var1[0xC9F6A7D7]
      94 [-]: CALL R7 3 2  ; var7 = var7(var8, var9)
      95 [-]: GETUPVAL R8 4; var8 = upvalues[4]
      96 [-]: MOVE R9 R7   ; var9 = var7
      97 [-]: MOVE R10 R5  ; var10 = var5
      98 [-]: MOVE R11 R6  ; var11 = var6
      99 [-]: LOADN R13 0  ; var13 = 0
     100 [-]: JUMPIFLT R13 R3 L9; goto L9 if var13 < var16780315
     101 [-]: LOADB R12 0 +1; var12 = false
L 9: 102 [-]: LOADB R12 1  ; var12 = true
L10: 103 [-]: CALL R8 5 1  ; var8(var9, var10, var11, var12)
     104 [-]: LOADNIL R8   ; var8 = nil
     105 [-]: LOADN R9 0   ; var9 = 0
     106 [-]: JUMPIFNOTLT R9 R3 L11; goto L11 if var9 >= var2033742
     107 [-]: GETIMPORT R8 31; var8 = 0xDDB2A096
     108 [-]: JUMP L15     ; goto L15
L11: 109 [-]: GETIMPORT R9 33; var9 = 0x89326C93
     110 [-]: NAMECALL R9 R9 K34; var10 = var9; var9 = var9[0x8B5B1F58]
     111 [-]: CALL R9 2 2  ; var9 = var9(var10)
     112 [-]: LOADN R12 1  ; var12 = 1
     113 [-]: LENGTH R10 R9; var10 = #var9
     114 [-]: LOADN R11 1  ; var11 = 1
     115 [-]: FORNPREP R10 L14; nforprep start - [escape at L14] -- var10 = iterator
L12: 116 [-]: GETTABLE R13 R9 R12; var13 = var9[var12]
     117 [-]: GETUPVAL R15 5; var15 = upvalues[5]
     118 [-]: NAMECALL R13 R13 K35; var14 = var13; var13 = var13[0x0866B4BD]
     119 [-]: CALL R13 3 2 ; var13 = var13(var14, var15)
     120 [-]: JUMPIFNOT R13 L13; goto L13 if not var13
     121 [-]: LOADN R13 0  ; var13 = 0
     122 [-]: SETUPVAL R13 6; upvalues[13] = var6
L13: 123 [-]: FORNLOOP R10 L12; nforloop end - iterate + goto L12
L14: 124 [-]: GETUPVAL R10 6; var10 = upvalues[6]
     125 [-]: LOADN R11 60 ; var11 = 60
     126 [-]: JUMPIFNOTLT R11 R10 L15; goto L15 if var11 >= var461575
     127 [-]: GETUPVAL R11 7; var11 = upvalues[7]
     128 [-]: GETTABLEKS R10 R11 K36; var10 = var11[0x9742B85B]
     129 [-]: GETUPVAL R11 8; var11 = upvalues[8]
     130 [-]: GETIMPORT R12 38; var12 = 0x0469F296
     131 [-]: LOADK R13 K39; var13 = "DynamicExcavation_ExcavatorUnpoweredShield"
     132 [-]: CALL R12 2 0 ; var12, ... = var12(var13)
     133 [-]: CALL R10 0 1 ; var10(var11, ...)
     134 [-]: LOADN R10 0  ; var10 = 0
     135 [-]: SETUPVAL R10 6; upvalues[10] = var6
L15: 136 [-]: MOVE R11 R8  ; var11 = var8
     137 [-]: LOADB R12 0  ; var12 = false
     138 [-]: LOADN R13 2  ; var13 = 2
     139 [-]: LOADN R14 2  ; var14 = 2
     140 [-]: NAMECALL R9 R1 K40; var10 = var1; var9 = var1[0x5D985C7E]
     141 [-]: CALL R9 6 1  ; var9(var10, var11, var12, var13, var14)
     142 [-]: GETUPVAL R9 9; var9 = upvalues[9]
     143 [-]: MOVE R10 R0  ; var10 = var0
     144 [-]: CALL R9 2 1  ; var9(var10)
L16: 145 [-]: RETURN R0 0  ; 


; Name:            
; Defined at line: 510
; #Upvalues:       3
; #Parameters:     0
; Is_vararg:       0
; Max Stack Size:  6

       0 [-]: GETUPVAL R0 0; var0 = upvalues[0]
       1 [-]: NAMECALL R0 R0 K0; var1 = var0; var0 = var0[0x209398C2]
       2 [-]: CALL R0 2 2  ; var0 = var0(var1)
       3 [-]: JUMPXEQKN R0 K1 L1 NOT; 
       4 [-]: GETIMPORT R0 3; var0 = 0xBE190284
       5 [-]: NAMECALL R0 R0 K4; var1 = var0; var0 = var0[0xABF50B1C]
       6 [-]: CALL R0 2 2  ; var0 = var0(var1)
       7 [-]: FASTCALL1 62 R0 L0; 
       8 [-]: MOVE R2 R0   ; var2 = var0
       9 [-]: GETIMPORT R1 6; var1 = 0x7B998233
      10 [-]: CALL R1 2 2  ; var1 = var1(var2)
L 0:  11 [-]: JUMPIF R1 L11; goto L11 if var1
      12 [-]: LOADN R3 0   ; var3 = 0
      13 [-]: NAMECALL R1 R0 K7; var2 = var0; var1 = var0[0x8CFF1D7A]
      14 [-]: CALL R1 3 1  ; var1(var2, var3)
      15 [-]: LOADB R3 0   ; var3 = false
      16 [-]: NAMECALL R1 R0 K8; var2 = var0; var1 = var0[0x543A0B5E]
      17 [-]: CALL R1 3 1  ; var1(var2, var3)
      18 [-]: RETURN R0 0  ; 
L 1:  19 [-]: GETUPVAL R0 0; var0 = upvalues[0]
      20 [-]: NAMECALL R0 R0 K0; var1 = var0; var0 = var0[0x209398C2]
      21 [-]: CALL R0 2 2  ; var0 = var0(var1)
      22 [-]: JUMPXEQKN R0 K9 L5 NOT; 
      23 [-]: GETIMPORT R0 11; var0 = 0x1AC7975A
      24 [-]: JUMPIFNOT R0 L2; goto L2 if not var0
      25 [-]: GETUPVAL R1 1; var1 = upvalues[1]
      26 [-]: GETTABLEKS R0 R1 K12; var0 = var1[0xEA753E99]
      27 [-]: LOADK R1 K13 ; var1 = "/Lotus/Language/Objectives/ExcavDigsComplete"
      28 [-]: LOADN R2 0   ; var2 = 0
      29 [-]: GETUPVAL R4 2; var4 = upvalues[2]
      30 [-]: LENGTH R3 R4 ; var3 = #var4
      31 [-]: CALL R0 4 1  ; var0(var1, var2, var3)
      32 [-]: JUMP L4      ; goto L4
L 2:  33 [-]: GETUPVAL R1 1; var1 = upvalues[1]
      34 [-]: GETTABLEKS R0 R1 K12; var0 = var1[0xEA753E99]
      35 [-]: LOADK R1 K13 ; var1 = "/Lotus/Language/Objectives/ExcavDigsComplete"
      36 [-]: LOADN R2 0   ; var2 = 0
      37 [-]: GETUPVAL R5 2; var5 = upvalues[2]
      38 [-]: LENGTH R4 R5 ; var4 = #var5
      39 [-]: FASTCALL2K 19 R4 K14 L3; 
      40 [-]: LOADK R5 K14 ; var5 = 3
      41 [-]: GETIMPORT R3 17; var3 = 0x5BCED4C4[0xAC1B386A]
      42 [-]: CALL R3 3 2  ; var3 = var3(var4, var5)
L 3:  43 [-]: CALL R0 4 1  ; var0(var1, var2, var3)
L 4:  44 [-]: GETUPVAL R1 1; var1 = upvalues[1]
      45 [-]: GETTABLEKS R0 R1 K18; var0 = var1[0xA8FBEA61]
      46 [-]: LOADK R1 K19 ; var1 = "/Lotus/Language/SolarisJobs/DynamicExcavationBonusObj"
      47 [-]: CALL R0 2 1  ; var0(var1)
      48 [-]: RETURN R0 0  ; 
L 5:  49 [-]: GETUPVAL R0 0; var0 = upvalues[0]
      50 [-]: NAMECALL R0 R0 K0; var1 = var0; var0 = var0[0x209398C2]
      51 [-]: CALL R0 2 2  ; var0 = var0(var1)
      52 [-]: JUMPXEQKN R0 K14 L9 NOT; 
      53 [-]: GETIMPORT R0 22; var0 = _T["QualifiedForBountyBonus"]
      54 [-]: JUMPIFNOT R0 L6; goto L6 if not var0
      55 [-]: GETUPVAL R1 1; var1 = upvalues[1]
      56 [-]: GETTABLEKS R0 R1 K23; var0 = var1[0x0A8ECC31]
      57 [-]: LOADK R1 K19 ; var1 = "/Lotus/Language/SolarisJobs/DynamicExcavationBonusObj"
      58 [-]: CALL R0 2 1  ; var0(var1)
      59 [-]: JUMP L7      ; goto L7
L 6:  60 [-]: GETUPVAL R1 1; var1 = upvalues[1]
      61 [-]: GETTABLEKS R0 R1 K24; var0 = var1[0x37317859]
      62 [-]: LOADK R1 K19 ; var1 = "/Lotus/Language/SolarisJobs/DynamicExcavationBonusObj"
      63 [-]: CALL R0 2 1  ; var0(var1)
L 7:  64 [-]: GETIMPORT R0 3; var0 = 0xBE190284
      65 [-]: NAMECALL R0 R0 K4; var1 = var0; var0 = var0[0xABF50B1C]
      66 [-]: CALL R0 2 2  ; var0 = var0(var1)
      67 [-]: FASTCALL1 62 R0 L8; 
      68 [-]: MOVE R2 R0   ; var2 = var0
      69 [-]: GETIMPORT R1 6; var1 = 0x7B998233
      70 [-]: CALL R1 2 2  ; var1 = var1(var2)
L 8:  71 [-]: JUMPIF R1 L11; goto L11 if var1
      72 [-]: LOADN R3 0   ; var3 = 0
      73 [-]: NAMECALL R1 R0 K7; var2 = var0; var1 = var0[0x8CFF1D7A]
      74 [-]: CALL R1 3 1  ; var1(var2, var3)
      75 [-]: LOADB R3 1   ; var3 = true
      76 [-]: NAMECALL R1 R0 K8; var2 = var0; var1 = var0[0x543A0B5E]
      77 [-]: CALL R1 3 1  ; var1(var2, var3)
      78 [-]: RETURN R0 0  ; 
L 9:  79 [-]: GETUPVAL R0 0; var0 = upvalues[0]
      80 [-]: NAMECALL R0 R0 K0; var1 = var0; var0 = var0[0x209398C2]
      81 [-]: CALL R0 2 2  ; var0 = var0(var1)
      82 [-]: JUMPXEQKN R0 K25 L11 NOT; 
      83 [-]: GETIMPORT R0 3; var0 = 0xBE190284
      84 [-]: NAMECALL R0 R0 K4; var1 = var0; var0 = var0[0xABF50B1C]
      85 [-]: CALL R0 2 2  ; var0 = var0(var1)
      86 [-]: FASTCALL1 62 R0 L10; 
      87 [-]: MOVE R2 R0   ; var2 = var0
      88 [-]: GETIMPORT R1 6; var1 = 0x7B998233
      89 [-]: CALL R1 2 2  ; var1 = var1(var2)
L10:  90 [-]: JUMPIF R1 L11; goto L11 if var1
      91 [-]: LOADN R3 0   ; var3 = 0
      92 [-]: NAMECALL R1 R0 K7; var2 = var0; var1 = var0[0x8CFF1D7A]
      93 [-]: CALL R1 3 1  ; var1(var2, var3)
      94 [-]: LOADB R3 1   ; var3 = true
      95 [-]: NAMECALL R1 R0 K8; var2 = var0; var1 = var0[0x543A0B5E]
      96 [-]: CALL R1 3 1  ; var1(var2, var3)
L11:  97 [-]: RETURN R0 0  ; 


; Name:            
; Defined at line: 553
; #Upvalues:       2
; #Parameters:     2
; Is_vararg:       0
; Max Stack Size:  10

       0 [-]: NAMECALL R2 R0 K0; var3 = var0; var2 = var0[0xD1586535]
       1 [-]: CALL R2 2 2  ; var2 = var2(var3)
       2 [-]: GETUPVAL R4 0; var4 = upvalues[0]
       3 [-]: LENGTH R3 R4 ; var3 = #var4
       4 [-]: JUMPIFNOTLE R1 R3 L0; goto L0 if var1 > var131918
       5 [-]: GETIMPORT R3 2; var3 = 0x89326C93
       6 [-]: GETUPVAL R6 0; var6 = upvalues[0]
       7 [-]: GETTABLE R5 R6 R1; var5 = var6[var1]
       8 [-]: MOVE R6 R2   ; var6 = var2
       9 [-]: GETIMPORT R7 4; var7 = ZERO_ROTATION
      10 [-]: NAMECALL R3 R3 K5; var4 = var3; var3 = var3[0x05909209]
      11 [-]: CALL R3 5 2  ; var3 = var3(var4, var5, var6, var7)
      12 [-]: GETIMPORT R4 2; var4 = 0x89326C93
      13 [-]: GETUPVAL R6 1; var6 = upvalues[1]
      14 [-]: MOVE R7 R2   ; var7 = var2
      15 [-]: GETIMPORT R8 4; var8 = ZERO_ROTATION
      16 [-]: NAMECALL R4 R4 K5; var5 = var4; var4 = var4[0x05909209]
      17 [-]: CALL R4 5 2  ; var4 = var4(var5, var6, var7, var8)
      18 [-]: LOADN R7 100 ; var7 = 100
      19 [-]: NAMECALL R5 R4 K6; var6 = var4; var5 = var4[0x5004BE24]
      20 [-]: CALL R5 3 1  ; var5(var6, var7)
      21 [-]: GETIMPORT R7 8; var7 = 0xB7CBD06B
      22 [-]: LOADN R8 5   ; var8 = 5
      23 [-]: LOADN R9 5000; var9 = 5000
      24 [-]: CALL R7 3 0  ; var7, ... = var7(var8, var9)
      25 [-]: NAMECALL R5 R3 K9; var6 = var3; var5 = var3[0x53BC0559]
      26 [-]: CALL R5 0 1  ; var5(var6, ...)
L 0:  27 [-]: RETURN R0 0  ; 


; Name:            
; Defined at line: 564
; #Upvalues:       0
; #Parameters:     3
; Is_vararg:       0
; Max Stack Size:  8

       0 [-]: NAMECALL R5 R2 K0; var6 = var2; var5 = var2[0xD1586535]
       1 [-]: CALL R5 2 0  ; var5, ... = var5(var6)
       2 [-]: NAMECALL R3 R0 K1; var4 = var0; var3 = var0[0x9307AA51]
       3 [-]: CALL R3 0 1  ; var3(var4, ...)
       4 [-]: LOADN R5 20  ; var5 = 20
       5 [-]: NAMECALL R3 R0 K2; var4 = var0; var3 = var0[0x8061B6D7]
       6 [-]: CALL R3 3 1  ; var3(var4, var5)
       7 [-]: LOADN R5 100 ; var5 = 100
       8 [-]: NAMECALL R3 R0 K3; var4 = var0; var3 = var0[0x2F5F5657]
       9 [-]: CALL R3 3 1  ; var3(var4, var5)
      10 [-]: MOVE R5 R2   ; var5 = var2
      11 [-]: NAMECALL R3 R0 K4; var4 = var0; var3 = var0[0x00F85B37]
      12 [-]: CALL R3 3 1  ; var3(var4, var5)
      13 [-]: MOVE R5 R1   ; var5 = var1
      14 [-]: NAMECALL R3 R0 K5; var4 = var0; var3 = var0[0xD95ACD2C]
      15 [-]: CALL R3 3 1  ; var3(var4, var5)
      16 [-]: GETIMPORT R3 7; var3 = 0x3D106989
      17 [-]: LOADK R5 K8  ; var5 = "State: "
      18 [-]: NAMECALL R6 R0 K9; var7 = var0; var6 = var0[0xED4E0128]
      19 [-]: CALL R6 2 2  ; var6 = var6(var7)
      20 [-]: CONCAT R4 R5 R6; var4 = var5 .. var6
      21 [-]: CALL R3 2 1  ; var3(var4)
      22 [-]: GETIMPORT R3 7; var3 = 0x3D106989
      23 [-]: LOADK R5 K10 ; var5 = "Instance number: "
      24 [-]: MOVE R6 R1   ; var6 = var1
      25 [-]: CONCAT R4 R5 R6; var4 = var5 .. var6
      26 [-]: CALL R3 2 1  ; var3(var4)
      27 [-]: GETIMPORT R3 7; var3 = 0x3D106989
      28 [-]: LOADK R5 K11 ; var5 = "Avatar: "
      29 [-]: NAMECALL R6 R2 K9; var7 = var2; var6 = var2[0xED4E0128]
      30 [-]: CALL R6 2 2  ; var6 = var6(var7)
      31 [-]: CONCAT R4 R5 R6; var4 = var5 .. var6
      32 [-]: CALL R3 2 1  ; var3(var4)
      33 [-]: RETURN R0 0  ; 


; Name:            
; Defined at line: 576
; #Upvalues:       7
; #Parameters:     2
; Is_vararg:       0
; Max Stack Size:  26

       0 [-]: GETIMPORT R2 1; var2 = 0x3D106989
       1 [-]: LOADK R3 K2  ; var3 = "CreateExcavator()"
       2 [-]: CALL R2 2 1  ; var2(var3)
       3 [-]: GETIMPORT R2 4; var2 = 0xA421AF95
       4 [-]: LOADN R3 0   ; var3 = 0
       5 [-]: LOADN R4 10  ; var4 = 10
       6 [-]: LOADN R5 0   ; var5 = 0
       7 [-]: CALL R2 4 2  ; var2 = var2(var3, var4, var5)
       8 [-]: ADD R3 R0 R2 ; var3 = var0 + var2
       9 [-]: SUB R4 R0 R2 ; var4 = var0 - var2
      10 [-]: GETIMPORT R5 6; var5 = 0x89326C93
      11 [-]: NAMECALL R5 R5 K7; var6 = var5; var5 = var5[0x5D971903]
      12 [-]: CALL R5 2 2  ; var5 = var5(var6)
      13 [-]: GETUPVAL R7 0; var7 = upvalues[0]
      14 [-]: GETTABLEKS R6 R7 K8; var6 = var7[0x29595BA9]
      15 [-]: MOVE R7 R0   ; var7 = var0
      16 [-]: LOADN R8 4   ; var8 = 4
      17 [-]: LOADB R9 1   ; var9 = true
      18 [-]: LOADK R10 K9 ; var10 = 0.25
      19 [-]: CALL R6 5 3  ; var6, var7 = var6(var7, var8, var9, var10)
      20 [-]: GETUPVAL R9 1; var9 = upvalues[1]
      21 [-]: GETTABLE R8 R9 R5; var8 = var9[var5]
      22 [-]: GETIMPORT R9 6; var9 = 0x89326C93
      23 [-]: NAMECALL R9 R9 K10; var10 = var9; var9 = var9[0x29EF273D]
      24 [-]: CALL R9 2 2  ; var9 = var9(var10)
      25 [-]: NAMECALL R9 R9 K11; var10 = var9; var9 = var9[0x66905CB0]
      26 [-]: CALL R9 2 2  ; var9 = var9(var10)
      27 [-]: MOVE R11 R0  ; var11 = var0
      28 [-]: NAMECALL R9 R9 K12; var10 = var9; var9 = var9[0xC1088746]
      29 [-]: CALL R9 3 2  ; var9 = var9(var10, var11)
      30 [-]: FASTCALL1 62 R6 L0; 
      31 [-]: MOVE R11 R6  ; var11 = var6
      32 [-]: GETIMPORT R10 14; var10 = 0x7B998233
      33 [-]: CALL R10 2 2 ; var10 = var10(var11)
L 0:  34 [-]: JUMPIFNOT R10 L1; goto L1 if not var10
      35 [-]: GETIMPORT R10 4; var10 = 0xA421AF95
      36 [-]: CALL R10 1 2 ; var10 = var10()
      37 [-]: MOVE R6 R10  ; var6 = var10
      38 [-]: GETIMPORT R10 6; var10 = 0x89326C93
      39 [-]: MOVE R12 R3  ; var12 = var3
      40 [-]: MOVE R13 R4  ; var13 = var4
      41 [-]: LOADNIL R14  ; var14 = nil
      42 [-]: LOADNIL R15  ; var15 = nil
      43 [-]: MOVE R16 R6  ; var16 = var6
      44 [-]: NAMECALL R10 R10 K15; var11 = var10; var10 = var10[0xBD5D0EC1]
      45 [-]: CALL R10 7 1 ; var10(var11, var12, var13, var14, var15, var16)
L 1:  46 [-]: FASTCALL1 62 R7 L2; 
      47 [-]: MOVE R11 R7  ; var11 = var7
      48 [-]: GETIMPORT R10 14; var10 = 0x7B998233
      49 [-]: CALL R10 2 2 ; var10 = var10(var11)
L 2:  50 [-]: JUMPIFNOT R10 L3; goto L3 if not var10
      51 [-]: GETIMPORT R10 17; var10 = 0x00046924
      52 [-]: CALL R10 1 2 ; var10 = var10()
      53 [-]: MOVE R7 R10  ; var7 = var10
L 3:  54 [-]: GETIMPORT R10 6; var10 = 0x89326C93
      55 [-]: NAMECALL R10 R10 K10; var11 = var10; var10 = var10[0x29EF273D]
      56 [-]: CALL R10 2 2 ; var10 = var10(var11)
      57 [-]: GETIMPORT R12 19; var12 = 0x872A2DDC
      58 [-]: MOVE R13 R6  ; var13 = var6
      59 [-]: MOVE R14 R7  ; var14 = var7
      60 [-]: GETIMPORT R15 21; var15 = 0x0469F296
      61 [-]: CALL R15 1 2 ; var15 = var15()
      62 [-]: MOVE R16 R9  ; var16 = var9
      63 [-]: LOADB R17 1  ; var17 = true
      64 [-]: NAMECALL R10 R10 K22; var11 = var10; var10 = var10[0x6CD833C5]
      65 [-]: CALL R10 8 2 ; var10 = var10(var11, var12, var13, var14, var15, var16, var17)
      66 [-]: NAMECALL R11 R10 K23; var12 = var10; var11 = var10[0xBB610E5B]
      67 [-]: CALL R11 2 2 ; var11 = var11(var12)
      68 [-]: NAMECALL R13 R11 K24; var14 = var11; var13 = var11[0xD2715720]
      69 [-]: CALL R13 2 2 ; var13 = var13(var14)
      70 [-]: ADD R12 R13 R8; var12 = var13 + var8
      71 [-]: MOVE R15 R12 ; var15 = var12
      72 [-]: LOADB R16 0  ; var16 = false
      73 [-]: NAMECALL R13 R11 K25; var14 = var11; var13 = var11[0xA31BA7EE]
      74 [-]: CALL R13 4 1 ; var13(var14, var15, var16)
      75 [-]: MOVE R15 R12 ; var15 = var12
      76 [-]: LOADB R16 1  ; var16 = true
      77 [-]: NAMECALL R13 R11 K26; var14 = var11; var13 = var11[0x014DB014]
      78 [-]: CALL R13 4 1 ; var13(var14, var15, var16)
      79 [-]: GETUPVAL R15 2; var15 = upvalues[2]
      80 [-]: NAMECALL R13 R11 K27; var14 = var11; var13 = var11[0x3273BA96]
      81 [-]: CALL R13 3 1 ; var13(var14, var15)
      82 [-]: GETIMPORT R13 29; var13 = _T
      83 [-]: GETIMPORT R15 32; var15 = _T["DynExcavNumRequested"]
      84 [-]: SUBK R14 R15 K30; var14 = var15 - 1
      85 [-]: SETTABLEKS R14 R13 K31; var14["DynExcavNumRequested"] = var13
      86 [-]: GETUPVAL R13 3; var13 = upvalues[3]
      87 [-]: GETIMPORT R14 34; var14 = 0xBE190284
      88 [-]: MOVE R16 R13 ; var16 = var13
      89 [-]: LOADN R17 0  ; var17 = 0
      90 [-]: NAMECALL R14 R14 K35; var15 = var14; var14 = var14[0x0EB34C69]
      91 [-]: CALL R14 4 2 ; var14 = var14(var15, var16, var17)
      92 [-]: ADDK R14 R14 K30; var14 = var14 + 1
      93 [-]: GETIMPORT R15 34; var15 = 0xBE190284
      94 [-]: MOVE R17 R13 ; var17 = var13
      95 [-]: MOVE R18 R14 ; var18 = var14
      96 [-]: NAMECALL R15 R15 K36; var16 = var15; var15 = var15[0x751F061D]
      97 [-]: CALL R15 4 1 ; var15(var16, var17, var18)
      98 [-]: LOADN R13 0  ; var13 = 0
      99 [-]: LOADN R16 1  ; var16 = 1
     100 [-]: LOADN R14 3  ; var14 = 3
     101 [-]: LOADN R15 1  ; var15 = 1
     102 [-]: FORNPREP R14 L11; nforprep start - [escape at L11] -- var14 = iterator
L 4: 103 [-]: LOADB R17 0  ; var17 = false
     104 [-]: GETIMPORT R18 6; var18 = 0x89326C93
     105 [-]: GETUPVAL R20 4; var20 = upvalues[4]
     106 [-]: NAMECALL R18 R18 K37; var19 = var18; var18 = var18[0xC7FCADA9]
     107 [-]: CALL R18 3 2 ; var18 = var18(var19, var20)
     108 [-]: GETIMPORT R19 1; var19 = 0x3D106989
     109 [-]: LOADK R21 K38; var21 = "Found "
     110 [-]: LENGTH R22 R18; var22 = #var18
     111 [-]: LOADK R23 K39; var23 = " states"
     112 [-]: CONCAT R20 R21 R23; var20 = var21 .. var23
     113 [-]: CALL R19 2 1 ; var19(var20)
     114 [-]: GETIMPORT R19 41; var19 = 0xCFC01047
     115 [-]: MOVE R20 R18 ; var20 = var18
     116 [-]: CALL R19 2 4 ; var19, var20, var21 = var19(var20)
     117 [-]: FORGPREP_NEXT R19 L8; 
L 5: 118 [-]: NAMECALL R24 R23 K42; var25 = var23; var24 = var23[0xF329A790]
     119 [-]: CALL R24 2 2 ; var24 = var24(var25)
     120 [-]: JUMPIFEQ R24 R16 L6; goto L6 if var24 == var16781595
     121 [-]: LOADB R17 0 +1; var17 = false
L 6: 122 [-]: LOADB R17 1  ; var17 = true
L 7: 123 [-]: JUMPIF R17 L9; goto L9 if var17
L 8: 124 [-]: FORGLOOP R19 L5 2; 
L 9: 125 [-]: JUMPIF R17 L10; goto L10 if var17
     126 [-]: MOVE R13 R16 ; var13 = var16
     127 [-]: JUMP L11     ; goto L11
L10: 128 [-]: FORNLOOP R14 L4; nforloop end - iterate + goto L4
L11: 129 [-]: LOADK R15 K43; var15 = "Created Excavator "
     130 [-]: MOVE R16 R13 ; var16 = var13
     131 [-]: CONCAT R14 R15 R16; var14 = var15 .. var16
     132 [-]: GETIMPORT R15 45; var15 = 0xD644C2F1
     133 [-]: MOVE R16 R14 ; var16 = var14
     134 [-]: CALL R15 2 1 ; var15(var16)
     135 [-]: GETIMPORT R15 1; var15 = 0x3D106989
     136 [-]: MOVE R16 R14 ; var16 = var14
     137 [-]: CALL R15 2 1 ; var15(var16)
     138 [-]: GETUPVAL R14 5; var14 = upvalues[5]
     139 [-]: MOVE R15 R1  ; var15 = var1
     140 [-]: MOVE R16 R13 ; var16 = var13
     141 [-]: MOVE R17 R11 ; var17 = var11
     142 [-]: CALL R14 4 1 ; var14(var15, var16, var17)
     143 [-]: GETUPVAL R14 6; var14 = upvalues[6]
     144 [-]: MOVE R15 R11 ; var15 = var11
     145 [-]: MOVE R16 R13 ; var16 = var13
     146 [-]: CALL R14 3 1 ; var14(var15, var16)
     147 [-]: RETURN R0 0  ; 


; Name:            
; Defined at line: 627
; #Upvalues:       4
; #Parameters:     1
; Is_vararg:       0
; Max Stack Size:  25

       0 [-]: GETIMPORT R1 1; var1 = 0x3D106989
       1 [-]: LOADK R3 K2  ; var3 = "DropExcavator "
       2 [-]: NAMECALL R4 R0 K3; var5 = var0; var4 = var0[0xED4E0128]
       3 [-]: CALL R4 2 2  ; var4 = var4(var5)
       4 [-]: CONCAT R2 R3 R4; var2 = var3 .. var4
       5 [-]: CALL R1 2 1  ; var1(var2)
       6 [-]: GETIMPORT R2 6; var2 = _T["DynamicExcavatorSpawnPoints"]
       7 [-]: LENGTH R1 R2 ; var1 = #var2
       8 [-]: GETIMPORT R3 8; var3 = 0xBE190284
       9 [-]: GETUPVAL R5 0; var5 = upvalues[0]
      10 [-]: LOADN R6 0   ; var6 = 0
      11 [-]: NAMECALL R3 R3 K9; var4 = var3; var3 = var3[0x0EB34C69]
      12 [-]: CALL R3 4 2  ; var3 = var3(var4, var5, var6)
      13 [-]: GETIMPORT R4 11; var4 = _T["DynExcavNumRequested"]
      14 [-]: ADD R2 R3 R4 ; var2 = var3 + var4
      15 [-]: LOADNIL R3   ; var3 = nil
      16 [-]: ADDK R4 R2 K12; var4 = var2 + 1
      17 [-]: JUMPIFNOTLT R1 R4 L1; goto L1 if var1 >= var66567
      18 [-]: GETUPVAL R4 1; var4 = upvalues[1]
      19 [-]: NAMECALL R5 R0 K13; var6 = var0; var5 = var0[0xD1586535]
      20 [-]: CALL R5 2 2  ; var5 = var5(var6)
      21 [-]: GETIMPORT R6 15; var6 = 0xE242BD4B
      22 [-]: GETUPVAL R7 2; var7 = upvalues[2]
      23 [-]: NAMECALL R7 R7 K16; var8 = var7; var7 = var7[0xF6CF204F]
      24 [-]: CALL R7 2 2  ; var7 = var7(var8)
      25 [-]: GETIMPORT R8 18; var8 = 0x2F080179
      26 [-]: GETIMPORT R9 20; var9 = 0xE1ACC7B7
      27 [-]: CALL R4 6 2  ; var4 = var4(var5, var6, var7, var8, var9)
      28 [-]: MOVE R3 R4   ; var3 = var4
      29 [-]: GETIMPORT R5 6; var5 = _T["DynamicExcavatorSpawnPoints"]
      30 [-]: FASTCALL2 52 R5 R3 L0; 
      31 [-]: MOVE R6 R3   ; var6 = var3
      32 [-]: GETIMPORT R4 23; var4 = 0x33BDD652[0x23D5322F]
      33 [-]: CALL R4 3 1  ; var4(var5, var6)
L 0:  34 [-]: JUMP L2      ; goto L2
L 1:  35 [-]: GETIMPORT R4 6; var4 = _T["DynamicExcavatorSpawnPoints"]
      36 [-]: ADDK R5 R2 K12; var5 = var2 + 1
      37 [-]: GETTABLE R3 R4 R5; var3 = var4[var5]
L 2:  38 [-]: FASTCALL1 62 R3 L3; 
      39 [-]: MOVE R5 R3   ; var5 = var3
      40 [-]: GETIMPORT R4 25; var4 = 0x7B998233
      41 [-]: CALL R4 2 2  ; var4 = var4(var5)
L 3:  42 [-]: JUMPIF R4 L4 ; goto L4 if var4
      43 [-]: GETIMPORT R4 1; var4 = 0x3D106989
      44 [-]: LOADK R6 K26 ; var6 = "Spawn point is "
      45 [-]: GETIMPORT R7 28; var7 = 0x64FB1586
      46 [-]: MOVE R8 R3   ; var8 = var3
      47 [-]: CALL R7 2 2  ; var7 = var7(var8)
      48 [-]: CONCAT R5 R6 R7; var5 = var6 .. var7
      49 [-]: CALL R4 2 1  ; var4(var5)
L 4:  50 [-]: GETIMPORT R4 1; var4 = 0x3D106989
      51 [-]: LOADK R5 K29 ; var5 = "DynamicExcavatorSpawnPoints:"
      52 [-]: CALL R4 2 1  ; var4(var5)
      53 [-]: GETIMPORT R4 31; var4 = 0xCFC01047
      54 [-]: GETIMPORT R5 6; var5 = _T["DynamicExcavatorSpawnPoints"]
      55 [-]: CALL R4 2 4  ; var4, var5, var6 = var4(var5)
      56 [-]: FORGPREP_NEXT R4 L7; 
L 5:  57 [-]: FASTCALL1 62 R8 L6; 
      58 [-]: MOVE R10 R8  ; var10 = var8
      59 [-]: GETIMPORT R9 25; var9 = 0x7B998233
      60 [-]: CALL R9 2 2  ; var9 = var9(var10)
L 6:  61 [-]: JUMPIF R9 L7 ; goto L7 if var9
      62 [-]: GETIMPORT R9 1; var9 = 0x3D106989
      63 [-]: MOVE R11 R7  ; var11 = var7
      64 [-]: LOADK R12 K32; var12 = ": "
      65 [-]: GETIMPORT R13 28; var13 = 0x64FB1586
      66 [-]: MOVE R14 R8  ; var14 = var8
      67 [-]: CALL R13 2 2 ; var13 = var13(var14)
      68 [-]: CONCAT R10 R11 R13; var10 = var11 .. var13
      69 [-]: CALL R9 2 1  ; var9(var10)
L 7:  70 [-]: FORGLOOP R4 L5 2; 
      71 [-]: GETIMPORT R5 34; var5 = 0xA421AF95
      72 [-]: LOADN R6 0   ; var6 = 0
      73 [-]: LOADN R7 38  ; var7 = 38
      74 [-]: LOADN R8 0   ; var8 = 0
      75 [-]: CALL R5 4 2  ; var5 = var5(var6, var7, var8)
      76 [-]: ADD R4 R3 R5 ; var4 = var3 + var5
      77 [-]: GETIMPORT R5 34; var5 = 0xA421AF95
      78 [-]: CALL R5 1 2  ; var5 = var5()
      79 [-]: GETIMPORT R6 36; var6 = 0x00046924
      80 [-]: CALL R6 1 2  ; var6 = var6()
      81 [-]: GETIMPORT R7 38; var7 = 0x89326C93
      82 [-]: MOVE R9 R4   ; var9 = var4
      83 [-]: GETIMPORT R11 34; var11 = 0xA421AF95
      84 [-]: LOADN R12 0  ; var12 = 0
      85 [-]: LOADN R13 10 ; var13 = 10
      86 [-]: LOADN R14 0  ; var14 = 0
      87 [-]: CALL R11 4 2 ; var11 = var11(var12, var13, var14)
      88 [-]: SUB R10 R3 R11; var10 = var3 - var11
      89 [-]: LOADNIL R11  ; var11 = nil
      90 [-]: LOADNIL R12  ; var12 = nil
      91 [-]: LOADNIL R13  ; var13 = nil
      92 [-]: MOVE R14 R5  ; var14 = var5
      93 [-]: MOVE R15 R6  ; var15 = var6
      94 [-]: LOADB R16 1  ; var16 = true
      95 [-]: NAMECALL R7 R7 K39; var8 = var7; var7 = var7[0xDB88E2D9]
      96 [-]: CALL R7 10 1 ; var7(var8, var9, var10, var11, var12, var13, var14, var15, var16)
      97 [-]: GETIMPORT R7 41; var7 = ZERO_VECTOR
      98 [-]: JUMPIFEQ R5 R7 L21; goto L21 if var5 == var2819918
      99 [-]: GETIMPORT R7 43; var7 = 0x4FD57545
     100 [-]: GETIMPORT R8 45; var8 = 0x492C7F2A
     101 [-]: GETIMPORT R9 34; var9 = 0xA421AF95
     102 [-]: LOADN R10 0  ; var10 = 0
     103 [-]: LOADN R11 0  ; var11 = 0
     104 [-]: LOADN R12 1  ; var12 = 1
     105 [-]: CALL R9 4 2  ; var9 = var9(var10, var11, var12)
     106 [-]: MOVE R10 R6  ; var10 = var6
     107 [-]: CALL R8 3 2  ; var8 = var8(var9, var10)
     108 [-]: GETIMPORT R9 34; var9 = 0xA421AF95
     109 [-]: LOADN R10 0  ; var10 = 0
     110 [-]: LOADN R11 1  ; var11 = 1
     111 [-]: LOADN R12 0  ; var12 = 0
     112 [-]: CALL R9 4 0  ; var9, ... = var9(var10, var11, var12)
     113 [-]: CALL R7 0 2  ; var7 = var7(var8, ...)
     114 [-]: LOADK R8 K46 ; var8 = 0.34202014332566882
     115 [-]: JUMPIFLT R7 R8 L21; goto L21 if var7 < var67406
     116 [-]: GETIMPORT R7 1; var7 = 0x3D106989
     117 [-]: LOADK R9 K47 ; var9 = "hitPoint is valid: "
     118 [-]: GETIMPORT R10 28; var10 = 0x64FB1586
     119 [-]: MOVE R11 R5  ; var11 = var5
     120 [-]: CALL R10 2 2 ; var10 = var10(var11)
     121 [-]: CONCAT R8 R9 R10; var8 = var9 .. var10
     122 [-]: CALL R7 2 1  ; var7(var8)
     123 [-]: GETIMPORT R7 1; var7 = 0x3D106989
     124 [-]: LOADK R9 K48 ; var9 = "hitAngle is valid: "
     125 [-]: GETIMPORT R10 28; var10 = 0x64FB1586
     126 [-]: MOVE R11 R6  ; var11 = var6
     127 [-]: CALL R10 2 2 ; var10 = var10(var11)
     128 [-]: CONCAT R8 R9 R10; var8 = var9 .. var10
     129 [-]: CALL R7 2 1  ; var7(var8)
     130 [-]: GETIMPORT R7 38; var7 = 0x89326C93
     131 [-]: GETIMPORT R9 50; var9 = 0x8C4D3FB7
     132 [-]: GETIMPORT R11 34; var11 = 0xA421AF95
     133 [-]: LOADN R12 0  ; var12 = 0
     134 [-]: LOADN R13 300; var13 = 300
     135 [-]: LOADN R14 0  ; var14 = 0
     136 [-]: CALL R11 4 2 ; var11 = var11(var12, var13, var14)
     137 [-]: ADD R10 R5 R11; var10 = var5 + var11
     138 [-]: GETIMPORT R11 52; var11 = 0x02CB8FD1
     139 [-]: NAMECALL R7 R7 K53; var8 = var7; var7 = var7[0x05909209]
     140 [-]: CALL R7 5 2  ; var7 = var7(var8, var9, var10, var11)
     141 [-]: NAMECALL R8 R7 K13; var9 = var7; var8 = var7[0xD1586535]
     142 [-]: CALL R8 2 2  ; var8 = var8(var9)
     143 [-]: GETIMPORT R10 34; var10 = 0xA421AF95
     144 [-]: LOADN R11 0  ; var11 = 0
     145 [-]: LOADN R12 299; var12 = 299
     146 [-]: LOADN R13 0  ; var13 = 0
     147 [-]: CALL R10 4 2 ; var10 = var10(var11, var12, var13)
     148 [-]: SUB R9 R8 R10; var9 = var8 - var10
     149 [-]: LOADN R10 0  ; var10 = 0
     150 [-]: NAMECALL R11 R7 K13; var12 = var7; var11 = var7[0xD1586535]
     151 [-]: CALL R11 2 2 ; var11 = var11(var12)
     152 [-]: NAMECALL R12 R7 K54; var13 = var7; var12 = var7[0x65D389CB]
     153 [-]: CALL R12 2 2 ; var12 = var12(var13)
     154 [-]: LOADK R14 K55; var14 = 0.040000000000000001
     155 [-]: MUL R13 R14 R12; var13 = var14 * var12
     156 [-]: LOADK R16 K56; var16 = 0.01
     157 [-]: NAMECALL R14 R7 K57; var15 = var7; var14 = var7[0x2D9BA74F]
     158 [-]: CALL R14 3 1 ; var14(var15, var16)
L 8: 159 [-]: FASTCALL1 62 R0 L9; 
     160 [-]: MOVE R15 R0  ; var15 = var0
     161 [-]: GETIMPORT R14 25; var14 = 0x7B998233
     162 [-]: CALL R14 2 2 ; var14 = var14(var15)
L 9: 163 [-]: JUMPIF R14 L10; goto L10 if var14
     164 [-]: NAMECALL R14 R0 K58; var15 = var0; var14 = var0[0xF329A790]
     165 [-]: CALL R14 2 2 ; var14 = var14(var15)
     166 [-]: JUMPXEQKN R14 K59 L10; 
     167 [-]: GETTABLEKS R14 R11 K60; var14 = var11["y"]
     168 [-]: GETTABLEKS R15 R9 K60; var15 = var9["y"]
     169 [-]: JUMPIFNOTLT R15 R14 L10; goto L10 if var15 >= var1024069121
     170 [-]: DIVK R14 R10 K61; var14 = var10 / 2
     171 [-]: MUL R15 R14 R14; var15 = var14 * var14
     172 [-]: GETIMPORT R18 63; var18 = 0x5DB3CE80
     173 [-]: MOVE R19 R8  ; var19 = var8
     174 [-]: MOVE R20 R9  ; var20 = var9
     175 [-]: MOVE R21 R15 ; var21 = var15
     176 [-]: CALL R18 4 2 ; var18 = var18(var19, var20, var21)
     177 [-]: GETIMPORT R19 52; var19 = 0x02CB8FD1
     178 [-]: NAMECALL R16 R7 K64; var17 = var7; var16 = var7[0x589EF1C1]
     179 [-]: CALL R16 4 1 ; var16(var17, var18, var19)
     180 [-]: GETIMPORT R18 66; var18 = 0x9BAFFFE3
     181 [-]: MOVE R19 R13 ; var19 = var13
     182 [-]: MOVE R20 R12 ; var20 = var12
     183 [-]: MOVE R21 R15 ; var21 = var15
     184 [-]: CALL R18 4 0 ; var18, ... = var18(var19, var20, var21)
     185 [-]: NAMECALL R16 R7 K57; var17 = var7; var16 = var7[0x2D9BA74F]
     186 [-]: CALL R16 0 1 ; var16(var17, ...)
     187 [-]: GETIMPORT R16 68; var16 = 0xCBD666E1
     188 [-]: LOADN R17 0  ; var17 = 0
     189 [-]: CALL R16 2 1 ; var16(var17)
     190 [-]: GETIMPORT R16 70; var16 = 0x67652851
     191 [-]: CALL R16 1 2 ; var16 = var16()
     192 [-]: ADD R10 R10 R16; var10 = var10 + var16
     193 [-]: NAMECALL R16 R7 K13; var17 = var7; var16 = var7[0xD1586535]
     194 [-]: CALL R16 2 2 ; var16 = var16(var17)
     195 [-]: MOVE R11 R16 ; var11 = var16
     196 [-]: JUMPBACK L8  ; goto L8
L10: 197 [-]: FASTCALL1 62 R0 L11; 
     198 [-]: MOVE R15 R0  ; var15 = var0
     199 [-]: GETIMPORT R14 25; var14 = 0x7B998233
     200 [-]: CALL R14 2 2 ; var14 = var14(var15)
L11: 201 [-]: JUMPIF R14 L12; goto L12 if var14
     202 [-]: NAMECALL R14 R0 K58; var15 = var0; var14 = var0[0xF329A790]
     203 [-]: CALL R14 2 2 ; var14 = var14(var15)
     204 [-]: JUMPXEQKN R14 K59 L17 NOT; 
L12: 205 [-]: GETIMPORT R14 1; var14 = 0x3D106989
     206 [-]: LOADK R15 K71; var15 = "State was canceled while being dropped, destroying pod and state"
     207 [-]: CALL R14 2 1 ; var14(var15)
     208 [-]: FASTCALL1 62 R7 L13; 
     209 [-]: MOVE R15 R7  ; var15 = var7
     210 [-]: GETIMPORT R14 25; var14 = 0x7B998233
     211 [-]: CALL R14 2 2 ; var14 = var14(var15)
L13: 212 [-]: JUMPIF R14 L14; goto L14 if var14
     213 [-]: NAMECALL R14 R7 K72; var15 = var7; var14 = var7[0xA2880940]
     214 [-]: CALL R14 2 1 ; var14(var15)
L14: 215 [-]: FASTCALL1 62 R0 L15; 
     216 [-]: MOVE R15 R0  ; var15 = var0
     217 [-]: GETIMPORT R14 25; var14 = 0x7B998233
     218 [-]: CALL R14 2 2 ; var14 = var14(var15)
L15: 219 [-]: JUMPIF R14 L16; goto L16 if var14
     220 [-]: NAMECALL R14 R0 K72; var15 = var0; var14 = var0[0xA2880940]
     221 [-]: CALL R14 2 1 ; var14(var15)
L16: 222 [-]: RETURN R0 0  ; 
L17: 223 [-]: GETIMPORT R14 1; var14 = 0x3D106989
     224 [-]: LOADK R15 K73; var15 = "Pod landed, creating avatar..."
     225 [-]: CALL R14 2 1 ; var14(var15)
     226 [-]: GETIMPORT R14 34; var14 = 0xA421AF95
     227 [-]: CALL R14 1 2 ; var14 = var14()
     228 [-]: GETIMPORT R15 36; var15 = 0x00046924
     229 [-]: CALL R15 1 2 ; var15 = var15()
     230 [-]: MOVE R6 R15  ; var6 = var15
     231 [-]: GETIMPORT R15 38; var15 = 0x89326C93
     232 [-]: GETIMPORT R18 34; var18 = 0xA421AF95
     233 [-]: LOADN R19 0  ; var19 = 0
     234 [-]: LOADN R20 2  ; var20 = 2
     235 [-]: LOADN R21 0  ; var21 = 0
     236 [-]: CALL R18 4 2 ; var18 = var18(var19, var20, var21)
     237 [-]: ADD R17 R9 R18; var17 = var9 + var18
     238 [-]: GETIMPORT R19 34; var19 = 0xA421AF95
     239 [-]: LOADN R20 0  ; var20 = 0
     240 [-]: LOADN R21 -10; var21 = -10
     241 [-]: LOADN R22 0  ; var22 = 0
     242 [-]: CALL R19 4 2 ; var19 = var19(var20, var21, var22)
     243 [-]: ADD R18 R9 R19; var18 = var9 + var19
     244 [-]: LOADNIL R19  ; var19 = nil
     245 [-]: LOADNIL R20  ; var20 = nil
     246 [-]: LOADNIL R21  ; var21 = nil
     247 [-]: MOVE R22 R14 ; var22 = var14
     248 [-]: MOVE R23 R6  ; var23 = var6
     249 [-]: LOADB R24 1  ; var24 = true
     250 [-]: NAMECALL R15 R15 K39; var16 = var15; var15 = var15[0xDB88E2D9]
     251 [-]: CALL R15 10 2; var15 = var15(var16, var17, var18, var19, var20, var21, var22, var23, var24)
     252 [-]: JUMPIF R15 L18; goto L18 if var15
     253 [-]: MOVE R14 R9  ; var14 = var9
L18: 254 [-]: LOADN R17 1  ; var17 = 1
     255 [-]: GETIMPORT R18 75; var18 = 0xC4B0E911
     256 [-]: LENGTH R15 R18; var15 = #var18
     257 [-]: LOADN R16 1  ; var16 = 1
     258 [-]: FORNPREP R15 L20; nforprep start - [escape at L20] -- var15 = iterator
L19: 259 [-]: GETIMPORT R18 38; var18 = 0x89326C93
     260 [-]: GETIMPORT R21 75; var21 = 0xC4B0E911
     261 [-]: GETTABLE R20 R21 R17; var20 = var21[var17]
     262 [-]: MOVE R21 R14 ; var21 = var14
     263 [-]: GETIMPORT R22 77; var22 = 0x20E8CA12
     264 [-]: MOVE R23 R6  ; var23 = var6
     265 [-]: GETIMPORT R24 52; var24 = 0x02CB8FD1
     266 [-]: CALL R22 3 2 ; var22 = var22(var23, var24)
     267 [-]: GETUPVAL R23 2; var23 = upvalues[2]
     268 [-]: GETUPVAL R24 2; var24 = upvalues[2]
     269 [-]: NAMECALL R18 R18 K53; var19 = var18; var18 = var18[0x05909209]
     270 [-]: CALL R18 7 1 ; var18(var19, var20, var21, var22, var23, var24)
     271 [-]: FORNLOOP R15 L19; nforloop end - iterate + goto L19
L20: 272 [-]: NAMECALL R15 R7 K72; var16 = var7; var15 = var7[0xA2880940]
     273 [-]: CALL R15 2 1 ; var15(var16)
     274 [-]: GETUPVAL R15 3; var15 = upvalues[3]
     275 [-]: MOVE R16 R14 ; var16 = var14
     276 [-]: MOVE R17 R0  ; var17 = var0
     277 [-]: CALL R15 3 1 ; var15(var16, var17)
     278 [-]: RETURN R0 0  ; 
L21: 279 [-]: GETIMPORT R7 1; var7 = 0x3D106989
     280 [-]: LOADK R8 K78 ; var8 = "something went wrong, excavator avatar was not created"
     281 [-]: CALL R7 2 1  ; var7(var8)
     282 [-]: FASTCALL1 62 R5 L22; 
     283 [-]: MOVE R8 R5   ; var8 = var5
     284 [-]: GETIMPORT R7 25; var7 = 0x7B998233
     285 [-]: CALL R7 2 2  ; var7 = var7(var8)
L22: 286 [-]: JUMPIF R7 L23; goto L23 if var7
     287 [-]: GETIMPORT R7 1; var7 = 0x3D106989
     288 [-]: LOADK R9 K79 ; var9 = "hit point is "
     289 [-]: GETIMPORT R10 28; var10 = 0x64FB1586
     290 [-]: MOVE R11 R5  ; var11 = var5
     291 [-]: CALL R10 2 2 ; var10 = var10(var11)
     292 [-]: CONCAT R8 R9 R10; var8 = var9 .. var10
     293 [-]: CALL R7 2 1  ; var7(var8)
L23: 294 [-]: FASTCALL1 62 R6 L24; 
     295 [-]: MOVE R8 R6   ; var8 = var6
     296 [-]: GETIMPORT R7 25; var7 = 0x7B998233
     297 [-]: CALL R7 2 2  ; var7 = var7(var8)
L24: 298 [-]: JUMPIF R7 L25; goto L25 if var7
     299 [-]: GETIMPORT R7 1; var7 = 0x3D106989
     300 [-]: LOADK R9 K80 ; var9 = "hit angle is "
     301 [-]: GETIMPORT R10 28; var10 = 0x64FB1586
     302 [-]: MOVE R11 R6  ; var11 = var6
     303 [-]: CALL R10 2 2 ; var10 = var10(var11)
     304 [-]: CONCAT R8 R9 R10; var8 = var9 .. var10
     305 [-]: CALL R7 2 1  ; var7(var8)
L25: 306 [-]: RETURN R0 0  ; 


; Name:            
; Defined at line: 713
; #Upvalues:       37
; #Parameters:     1
; Is_vararg:       0
; Max Stack Size:  18

       0 [-]: GETIMPORT R1 1; var1 = 0x89326C93
       1 [-]: NAMECALL R1 R1 K2; var2 = var1; var1 = var1[0x29EF273D]
       2 [-]: CALL R1 2 2  ; var1 = var1(var2)
       3 [-]: NAMECALL R1 R1 K3; var2 = var1; var1 = var1[0x66905CB0]
       4 [-]: CALL R1 2 2  ; var1 = var1(var2)
       5 [-]: SETUPVAL R1 0; upvalues[1] = var0
L 0:   6 [-]: GETUPVAL R1 0; var1 = upvalues[0]
       7 [-]: NAMECALL R1 R1 K4; var2 = var1; var1 = var1[0xA2D83ED4]
       8 [-]: CALL R1 2 2  ; var1 = var1(var2)
       9 [-]: JUMPIF R1 L1 ; goto L1 if var1
      10 [-]: GETIMPORT R1 6; var1 = 0xCBD666E1
      11 [-]: LOADN R2 0   ; var2 = 0
      12 [-]: CALL R1 2 1  ; var1(var2)
      13 [-]: JUMPBACK L0  ; goto L0
L 1:  14 [-]: GETIMPORT R2 8; var2 = 0x83F4E77C
      15 [-]: FASTCALL1 62 R2 L2; 
      16 [-]: GETIMPORT R1 10; var1 = 0x7B998233
      17 [-]: CALL R1 2 2  ; var1 = var1(var2)
L 2:  18 [-]: JUMPIF R1 L5 ; goto L5 if var1
L 3:  19 [-]: GETUPVAL R2 1; var2 = upvalues[1]
      20 [-]: FASTCALL1 62 R2 L4; 
      21 [-]: GETIMPORT R1 10; var1 = 0x7B998233
      22 [-]: CALL R1 2 2  ; var1 = var1(var2)
L 4:  23 [-]: JUMPIFNOT R1 L5; goto L5 if not var1
      24 [-]: GETIMPORT R1 12; var1 = 0xBE190284
      25 [-]: NAMECALL R1 R1 K13; var2 = var1; var1 = var1[0x33307F92]
      26 [-]: CALL R1 2 2  ; var1 = var1(var2)
      27 [-]: SETUPVAL R1 1; upvalues[1] = var1
      28 [-]: GETIMPORT R1 6; var1 = 0xCBD666E1
      29 [-]: LOADN R2 0   ; var2 = 0
      30 [-]: CALL R1 2 1  ; var1(var2)
      31 [-]: JUMPBACK L3  ; goto L3
L 5:  32 [-]: GETIMPORT R1 15; var1 = 0x8C4D3FB7
      33 [-]: GETIMPORT R1 17; var1 = 0x02CB8FD1
      34 [-]: GETIMPORT R1 19; var1 = 0xC4B0E911
      35 [-]: GETIMPORT R1 21; var1 = 0x872A2DDC
      36 [-]: GETIMPORT R1 23; var1 = 0xE242BD4B
      37 [-]: GETIMPORT R1 25; var1 = 0x2F080179
      38 [-]: GETIMPORT R1 27; var1 = 0xE1ACC7B7
      39 [-]: NAMECALL R2 R0 K28; var3 = var0; var2 = var0[0x891629FA]
      40 [-]: CALL R2 2 2  ; var2 = var2(var3)
      41 [-]: SETUPVAL R2 2; upvalues[2] = var2
      42 [-]: GETUPVAL R3 2; var3 = upvalues[2]
      43 [-]: FASTCALL1 62 R3 L6; 
      44 [-]: GETIMPORT R2 10; var2 = 0x7B998233
      45 [-]: CALL R2 2 2  ; var2 = var2(var3)
L 6:  46 [-]: JUMPIF R2 L8 ; goto L8 if var2
      47 [-]: GETUPVAL R3 2; var3 = upvalues[2]
      48 [-]: NAMECALL R3 R3 K29; var4 = var3; var3 = var3[0x4C976EDA]
      49 [-]: CALL R3 2 2  ; var3 = var3(var4)
      50 [-]: FASTCALL1 62 R3 L7; 
      51 [-]: GETIMPORT R2 10; var2 = 0x7B998233
      52 [-]: CALL R2 2 2  ; var2 = var2(var3)
L 7:  53 [-]: JUMPIF R2 L8 ; goto L8 if var2
      54 [-]: GETUPVAL R2 2; var2 = upvalues[2]
      55 [-]: NAMECALL R2 R2 K30; var3 = var2; var2 = var2[0x18F05C50]
      56 [-]: CALL R2 2 2  ; var2 = var2(var3)
      57 [-]: GETUPVAL R4 3; var4 = upvalues[3]
      58 [-]: GETTABLEKS R3 R4 K31; var3 = var4[0x06D055F9]
      59 [-]: NAMECALL R4 R2 K32; var5 = var2; var4 = var2[0x56C01834]
      60 [-]: CALL R4 2 2  ; var4 = var4(var5)
      61 [-]: MOVE R5 R2   ; var5 = var2
      62 [-]: GETGLOBAL R6 K33; var6 = 0x5AA2084E
      63 [-]: CALL R3 4 2  ; var3 = var3(var4, var5, var6)
      64 [-]: SETGLOBAL R3 K33; 0x5AA2084E = var3
L 8:  65 [-]: SETUPVAL R0 4; upvalues[0] = var4
      66 [-]: NAMECALL R2 R0 K34; var3 = var0; var2 = var0[0xD1586535]
      67 [-]: CALL R2 2 2  ; var2 = var2(var3)
      68 [-]: SETUPVAL R2 5; upvalues[2] = var5
      69 [-]: GETUPVAL R2 2; var2 = upvalues[2]
      70 [-]: NAMECALL R2 R2 K35; var3 = var2; var2 = var2[0xF6CF204F]
      71 [-]: CALL R2 2 2  ; var2 = var2(var3)
      72 [-]: SETUPVAL R2 6; upvalues[2] = var6
      73 [-]: GETUPVAL R2 2; var2 = upvalues[2]
      74 [-]: NAMECALL R2 R2 K36; var3 = var2; var2 = var2[0x7C97B143]
      75 [-]: CALL R2 2 2  ; var2 = var2(var3)
      76 [-]: SETUPVAL R2 7; upvalues[2] = var7
      77 [-]: NAMECALL R2 R0 K29; var3 = var0; var2 = var0[0x4C976EDA]
      78 [-]: CALL R2 2 2  ; var2 = var2(var3)
      79 [-]: NAMECALL R3 R2 K37; var4 = var2; var3 = var2[0xE4C355E2]
      80 [-]: CALL R3 2 2  ; var3 = var3(var4)
      81 [-]: SETUPVAL R3 8; upvalues[3] = var8
      82 [-]: NAMECALL R3 R2 K38; var4 = var2; var3 = var2[0xAA1950D4]
      83 [-]: CALL R3 2 2  ; var3 = var3(var4)
      84 [-]: SETUPVAL R3 9; upvalues[3] = var9
      85 [-]: GETIMPORT R3 1; var3 = 0x89326C93
      86 [-]: LOADK R5 K39 ; var5 = "OnPlayersChanged"
      87 [-]: NAMECALL R3 R3 K40; var4 = var3; var3 = var3[0xB7D33840]
      88 [-]: CALL R3 3 1  ; var3(var4, var5)
      89 [-]: GETIMPORT R3 1; var3 = 0x89326C93
      90 [-]: NAMECALL R3 R3 K41; var4 = var3; var3 = var3[0x7D108DDB]
      91 [-]: CALL R3 2 2  ; var3 = var3(var4)
      92 [-]: SETUPVAL R3 10; upvalues[3] = var10
      93 [-]: GETIMPORT R3 44; var3 = 0x34291F5C[0x056BFE8B]
      94 [-]: CALL R3 1 2  ; var3 = var3()
      95 [-]: JUMPIFNOT R3 L9; goto L9 if not var3
      96 [-]: GETUPVAL R3 12; var3 = upvalues[12]
      97 [-]: SETUPVAL R3 11; upvalues[3] = var11
      98 [-]: GETUPVAL R3 14; var3 = upvalues[14]
      99 [-]: SETUPVAL R3 13; upvalues[3] = var13
     100 [-]: JUMP L10     ; goto L10
L 9: 101 [-]: GETUPVAL R3 15; var3 = upvalues[15]
     102 [-]: SETUPVAL R3 11; upvalues[3] = var11
     103 [-]: GETUPVAL R3 16; var3 = upvalues[16]
     104 [-]: SETUPVAL R3 13; upvalues[3] = var13
L10: 105 [-]: GETIMPORT R3 46; var3 = 0x1AC7975A
     106 [-]: JUMPIFNOT R3 L11; goto L11 if not var3
     107 [-]: NEWTABLE R3 0 4; var3 = {}
     108 [-]: LOADN R4 8   ; var4 = 8
     109 [-]: LOADN R5 8   ; var5 = 8
     110 [-]: LOADN R6 8   ; var6 = 8
     111 [-]: LOADN R7 8   ; var7 = 8
     112 [-]: SETLIST R3 R4 4 [1]; var3[1] = var4; var3[2] = var5; var3[3] = var6; var3[4] = var7; var3[5] = var8; 
     113 [-]: SETUPVAL R3 13; upvalues[3] = var13
L11: 114 [-]: GETUPVAL R4 17; var4 = upvalues[17]
     115 [-]: GETTABLEKS R3 R4 K47; var3 = var4[0xA1DF01D6]
     116 [-]: LOADK R4 K48 ; var4 = "/Lotus/Language/Game/ExcavationLocateAndProtect"
     117 [-]: GETUPVAL R6 17; var6 = upvalues[17]
     118 [-]: GETTABLEKS R5 R6 K49; var5 = var6["GENERIC_ICON"]
     119 [-]: CALL R3 3 1  ; var3(var4, var5)
     120 [-]: GETUPVAL R3 4; var3 = upvalues[4]
     121 [-]: NAMECALL R3 R3 K50; var4 = var3; var3 = var3[0xABE61691]
     122 [-]: CALL R3 2 2  ; var3 = var3(var4)
     123 [-]: GETUPVAL R5 19; var5 = upvalues[19]
     124 [-]: GETTABLEKS R4 R5 K51; var4 = var5[0xC9013731]
     125 [-]: GETUPVAL R5 20; var5 = upvalues[20]
     126 [-]: GETUPVAL R6 4; var6 = upvalues[4]
     127 [-]: NEWTABLE R7 0 0; var7 = {}
     128 [-]: CALL R4 4 2  ; var4 = var4(var5, var6, var7)
     129 [-]: SETUPVAL R4 18; upvalues[4] = var18
     130 [-]: GETUPVAL R4 18; var4 = upvalues[18]
     131 [-]: GETUPVAL R7 3; var7 = upvalues[3]
     132 [-]: GETTABLEKS R6 R7 K31; var6 = var7[0x06D055F9]
     133 [-]: JUMPXEQKN R3 K52 L12; 
     134 [-]: LOADB R7 0 +1; var7 = false
L12: 135 [-]: LOADB R7 1   ; var7 = true
L13: 136 [-]: LOADN R8 1   ; var8 = 1
     137 [-]: MOVE R9 R3   ; var9 = var3
     138 [-]: CALL R6 4 0  ; var6, ... = var6(var7, var8, var9)
     139 [-]: NAMECALL R4 R4 K53; var5 = var4; var4 = var4[0x8ABFF40E]
     140 [-]: CALL R4 0 1  ; var4(var5, ...)
     141 [-]: GETUPVAL R4 4; var4 = upvalues[4]
     142 [-]: LOADK R6 K54 ; var6 = "PlayersLeaving"
     143 [-]: GETUPVAL R7 21; var7 = upvalues[21]
     144 [-]: NAMECALL R4 R4 K55; var5 = var4; var4 = var4[0xE19C3F44]
     145 [-]: CALL R4 4 1  ; var4(var5, var6, var7)
     146 [-]: GETUPVAL R4 4; var4 = upvalues[4]
     147 [-]: LOADK R6 K56 ; var6 = "PlayersReturning"
     148 [-]: GETUPVAL R7 22; var7 = upvalues[22]
     149 [-]: NAMECALL R4 R4 K57; var5 = var4; var4 = var4[0x3F86F5A0]
     150 [-]: CALL R4 4 1  ; var4(var5, var6, var7)
     151 [-]: GETUPVAL R5 24; var5 = upvalues[24]
     152 [-]: GETTABLEKS R4 R5 K58; var4 = var5[0xDE474187]
     153 [-]: CALL R4 1 2  ; var4 = var4()
     154 [-]: SETUPVAL R4 23; upvalues[4] = var23
     155 [-]: GETUPVAL R4 2; var4 = upvalues[2]
     156 [-]: LOADK R6 K59 ; var6 = "OnAgentRegistered"
     157 [-]: GETIMPORT R7 61; var7 = 0x0469F296
     158 [-]: LOADK R8 K62 ; var8 = "DynamicExcavationRegistration"
     159 [-]: CALL R7 2 0  ; var7, ... = var7(var8)
     160 [-]: NAMECALL R4 R4 K63; var5 = var4; var4 = var4[0x5B344F44]
     161 [-]: CALL R4 0 1  ; var4(var5, ...)
     162 [-]: GETIMPORT R5 66; var5 = _T["DynamicExcavatorSpawnPoints"]
     163 [-]: FASTCALL1 62 R5 L14; 
     164 [-]: GETIMPORT R4 10; var4 = 0x7B998233
     165 [-]: CALL R4 2 2  ; var4 = var4(var5)
L14: 166 [-]: JUMPIFNOT R4 L15; goto L15 if not var4
     167 [-]: GETIMPORT R4 67; var4 = _T
     168 [-]: NEWTABLE R5 0 0; var5 = {}
     169 [-]: SETTABLEKS R5 R4 K65; var5["DynamicExcavatorSpawnPoints"] = var4
L15: 170 [-]: GETIMPORT R5 69; var5 = _T["DynamicExcavationHudInfo"]
     171 [-]: FASTCALL1 62 R5 L16; 
     172 [-]: GETIMPORT R4 10; var4 = 0x7B998233
     173 [-]: CALL R4 2 2  ; var4 = var4(var5)
L16: 174 [-]: JUMPIFNOT R4 L17; goto L17 if not var4
     175 [-]: GETIMPORT R4 67; var4 = _T
     176 [-]: NEWTABLE R5 0 0; var5 = {}
     177 [-]: SETTABLEKS R5 R4 K68; var5["DynamicExcavationHudInfo"] = var4
L17: 178 [-]: GETIMPORT R5 71; var5 = _T["DynExcavNumRequested"]
     179 [-]: FASTCALL1 62 R5 L18; 
     180 [-]: GETIMPORT R4 10; var4 = 0x7B998233
     181 [-]: CALL R4 2 2  ; var4 = var4(var5)
L18: 182 [-]: JUMPIFNOT R4 L19; goto L19 if not var4
     183 [-]: GETIMPORT R4 67; var4 = _T
     184 [-]: LOADN R5 0   ; var5 = 0
     185 [-]: SETTABLEKS R5 R4 K70; var5["DynExcavNumRequested"] = var4
L19: 186 [-]: GETIMPORT R5 73; var5 = _T["DynExcavNumExpectedEnemy"]
     187 [-]: FASTCALL1 62 R5 L20; 
     188 [-]: GETIMPORT R4 10; var4 = 0x7B998233
     189 [-]: CALL R4 2 2  ; var4 = var4(var5)
L20: 190 [-]: JUMPIFNOT R4 L21; goto L21 if not var4
     191 [-]: GETIMPORT R4 67; var4 = _T
     192 [-]: LOADN R5 0   ; var5 = 0
     193 [-]: SETTABLEKS R5 R4 K72; var5["DynExcavNumExpectedEnemy"] = var4
L21: 194 [-]: GETIMPORT R5 75; var5 = _T["DynamicOverrideAgentCount"]
     195 [-]: FASTCALL1 62 R5 L22; 
     196 [-]: GETIMPORT R4 10; var4 = 0x7B998233
     197 [-]: CALL R4 2 2  ; var4 = var4(var5)
L22: 198 [-]: JUMPIFNOT R4 L23; goto L23 if not var4
     199 [-]: GETIMPORT R4 67; var4 = _T
     200 [-]: LOADN R5 0   ; var5 = 0
     201 [-]: SETTABLEKS R5 R4 K74; var5["DynamicOverrideAgentCount"] = var4
L23: 202 [-]: GETIMPORT R4 1; var4 = 0x89326C93
     203 [-]: GETUPVAL R6 25; var6 = upvalues[25]
     204 [-]: NAMECALL R4 R4 K76; var5 = var4; var4 = var4[0xC7FCADA9]
     205 [-]: CALL R4 3 2  ; var4 = var4(var5, var6)
     206 [-]: FASTCALL1 62 R4 L24; 
     207 [-]: MOVE R6 R4   ; var6 = var4
     208 [-]: GETIMPORT R5 10; var5 = 0x7B998233
     209 [-]: CALL R5 2 2  ; var5 = var5(var6)
L24: 210 [-]: JUMPIF R5 L26; goto L26 if var5
     211 [-]: LOADN R7 1   ; var7 = 1
     212 [-]: LENGTH R5 R4 ; var5 = #var4
     213 [-]: LOADN R6 1   ; var6 = 1
     214 [-]: FORNPREP R5 L26; nforprep start - [escape at L26] -- var5 = iterator
L25: 215 [-]: GETTABLE R8 R4 R7; var8 = var4[var7]
     216 [-]: NAMECALL R8 R8 K77; var9 = var8; var8 = var8[0xA2880940]
     217 [-]: CALL R8 2 1  ; var8(var9)
     218 [-]: FORNLOOP R5 L25; nforloop end - iterate + goto L25
L26: 219 [-]: GETIMPORT R5 1; var5 = 0x89326C93
     220 [-]: GETUPVAL R7 26; var7 = upvalues[26]
     221 [-]: NAMECALL R5 R5 K76; var6 = var5; var5 = var5[0xC7FCADA9]
     222 [-]: CALL R5 3 2  ; var5 = var5(var6, var7)
     223 [-]: LENGTH R6 R5 ; var6 = #var5
     224 [-]: FASTCALL1 62 R5 L27; 
     225 [-]: MOVE R8 R5   ; var8 = var5
     226 [-]: GETIMPORT R7 10; var7 = 0x7B998233
     227 [-]: CALL R7 2 2  ; var7 = var7(var8)
L27: 228 [-]: JUMPIF R7 L33; goto L33 if var7
     229 [-]: LOADN R9 1   ; var9 = 1
     230 [-]: MOVE R7 R6   ; var7 = var6
     231 [-]: LOADN R8 1   ; var8 = 1
     232 [-]: FORNPREP R7 L33; nforprep start - [escape at L33] -- var7 = iterator
L28: 233 [-]: GETIMPORT R10 1; var10 = 0x89326C93
     234 [-]: GETUPVAL R12 27; var12 = upvalues[27]
     235 [-]: GETTABLE R13 R5 R9; var13 = var5[var9]
     236 [-]: NAMECALL R13 R13 K34; var14 = var13; var13 = var13[0xD1586535]
     237 [-]: CALL R13 2 2 ; var13 = var13(var14)
     238 [-]: LOADN R14 1  ; var14 = 1
     239 [-]: NAMECALL R10 R10 K78; var11 = var10; var10 = var10[0x4E5939A5]
     240 [-]: CALL R10 5 2 ; var10 = var10(var11, var12, var13, var14)
     241 [-]: FASTCALL1 62 R10 L29; 
     242 [-]: MOVE R12 R10 ; var12 = var10
     243 [-]: GETIMPORT R11 10; var11 = 0x7B998233
     244 [-]: CALL R11 2 2 ; var11 = var11(var12)
L29: 245 [-]: JUMPIF R11 L31; goto L31 if var11
     246 [-]: GETUPVAL R11 28; var11 = upvalues[28]
     247 [-]: GETTABLE R12 R5 R9; var12 = var5[var9]
     248 [-]: NAMECALL R13 R10 K79; var14 = var10; var13 = var10[0xF329A790]
     249 [-]: CALL R13 2 0 ; var13, ... = var13(var14)
     250 [-]: CALL R11 0 1 ; var11(var12, ...)
     251 [-]: GETTABLE R13 R5 R9; var13 = var5[var9]
     252 [-]: NAMECALL R11 R10 K80; var12 = var10; var11 = var10[0x00F85B37]
     253 [-]: CALL R11 3 1 ; var11(var12, var13)
     254 [-]: GETIMPORT R12 66; var12 = _T["DynamicExcavatorSpawnPoints"]
     255 [-]: NAMECALL R13 R10 K34; var14 = var10; var13 = var10[0xD1586535]
     256 [-]: CALL R13 2 0 ; var13, ... = var13(var14)
     257 [-]: FASTCALL 52 L30; 
     258 [-]: GETIMPORT R11 83; var11 = 0x33BDD652[0x23D5322F]
     259 [-]: CALL R11 0 1 ; var11(var12, ...)
L30: 260 [-]: JUMP L32     ; goto L32
L31: 261 [-]: GETTABLE R11 R5 R9; var11 = var5[var9]
     262 [-]: NAMECALL R11 R11 K77; var12 = var11; var11 = var11[0xA2880940]
     263 [-]: CALL R11 2 1 ; var11(var12)
     264 [-]: SUBK R6 R6 K84; var6 = var6 - 1
L32: 265 [-]: FORNLOOP R7 L28; nforloop end - iterate + goto L28
L33: 266 [-]: GETIMPORT R7 1; var7 = 0x89326C93
     267 [-]: GETUPVAL R9 29; var9 = upvalues[29]
     268 [-]: NAMECALL R7 R7 K76; var8 = var7; var7 = var7[0xC7FCADA9]
     269 [-]: CALL R7 3 2  ; var7 = var7(var8, var9)
     270 [-]: LOADB R8 0   ; var8 = false
     271 [-]: GETIMPORT R9 86; var9 = 0xCFC01047
     272 [-]: MOVE R10 R7  ; var10 = var7
     273 [-]: CALL R9 2 4  ; var9, var10, var11 = var9(var10)
     274 [-]: FORGPREP_NEXT R9 L36; 
L34: 275 [-]: NAMECALL R15 R13 K87; var16 = var13; var15 = var13[0xBB610E5B]
     276 [-]: CALL R15 2 2 ; var15 = var15(var16)
     277 [-]: FASTCALL1 62 R15 L35; 
     278 [-]: GETIMPORT R14 10; var14 = 0x7B998233
     279 [-]: CALL R14 2 2 ; var14 = var14(var15)
L35: 280 [-]: JUMPIFNOT R14 L36; goto L36 if not var14
     281 [-]: NAMECALL R14 R13 K77; var15 = var13; var14 = var13[0xA2880940]
     282 [-]: CALL R14 2 1 ; var14(var15)
     283 [-]: LOADB R8 1   ; var8 = true
L36: 284 [-]: FORGLOOP R9 L34 2; 
     285 [-]: JUMPIFNOT R8 L37; goto L37 if not var8
     286 [-]: GETIMPORT R9 6; var9 = 0xCBD666E1
     287 [-]: LOADN R10 0  ; var10 = 0
     288 [-]: CALL R9 2 1  ; var9(var10)
     289 [-]: GETIMPORT R9 1; var9 = 0x89326C93
     290 [-]: GETUPVAL R11 29; var11 = upvalues[29]
     291 [-]: NAMECALL R9 R9 K76; var10 = var9; var9 = var9[0xC7FCADA9]
     292 [-]: CALL R9 3 2  ; var9 = var9(var10, var11)
     293 [-]: MOVE R7 R9   ; var7 = var9
L37: 294 [-]: GETIMPORT R9 12; var9 = 0xBE190284
     295 [-]: GETUPVAL R11 30; var11 = upvalues[30]
     296 [-]: MOVE R12 R6  ; var12 = var6
     297 [-]: NAMECALL R9 R9 K88; var10 = var9; var9 = var9[0x751F061D]
     298 [-]: CALL R9 4 1  ; var9(var10, var11, var12)
     299 [-]: JUMPXEQKN R3 K89 L38 NOT; 
     300 [-]: GETIMPORT R9 12; var9 = 0xBE190284
     301 [-]: GETUPVAL R11 32; var11 = upvalues[32]
     302 [-]: LOADN R12 0  ; var12 = 0
     303 [-]: NAMECALL R9 R9 K90; var10 = var9; var9 = var9[0x0EB34C69]
     304 [-]: CALL R9 4 2  ; var9 = var9(var10, var11, var12)
     305 [-]: SETUPVAL R9 31; upvalues[9] = var31
     306 [-]: GETIMPORT R9 12; var9 = 0xBE190284
     307 [-]: GETUPVAL R11 33; var11 = upvalues[33]
     308 [-]: GETIMPORT R12 92; var12 = EMPTY_SYMBOL
     309 [-]: LOADN R13 0  ; var13 = 0
     310 [-]: LOADB R14 0  ; var14 = false
     311 [-]: LOADB R15 0  ; var15 = false
     312 [-]: LOADB R16 1  ; var16 = true
     313 [-]: NAMECALL R9 R9 K93; var10 = var9; var9 = var9[0xFE23FE59]
     314 [-]: CALL R9 8 1  ; var9(var10, var11, var12, var13, var14, var15, var16)
     315 [-]: GETIMPORT R9 12; var9 = 0xBE190284
     316 [-]: GETUPVAL R11 33; var11 = upvalues[33]
     317 [-]: GETUPVAL R12 31; var12 = upvalues[31]
     318 [-]: NAMECALL R9 R9 K94; var10 = var9; var9 = var9[0x39A80406]
     319 [-]: CALL R9 4 1  ; var9(var10, var11, var12)
L38: 320 [-]: GETIMPORT R9 12; var9 = 0xBE190284
     321 [-]: GETUPVAL R11 35; var11 = upvalues[35]
     322 [-]: LOADN R12 0  ; var12 = 0
     323 [-]: NAMECALL R9 R9 K90; var10 = var9; var9 = var9[0x0EB34C69]
     324 [-]: CALL R9 4 2  ; var9 = var9(var10, var11, var12)
     325 [-]: SETUPVAL R9 34; upvalues[9] = var34
     326 [-]: GETIMPORT R9 97; var9 = 0x7F5022CF[0xE8072DED]
     327 [-]: LOADK R10 K98; var10 = "<Color%u>"
     328 [-]: LOADN R11 38 ; var11 = 38
     329 [-]: CALL R9 3 2  ; var9 = var9(var10, var11)
     330 [-]: LOADK R11 K99; var11 = "<p><font color=\""
     331 [-]: MOVE R12 R9  ; var12 = var9
     332 [-]: LOADK R13 K100; var13 = "\"><br>      "
     333 [-]: LOADK R14 K101; var14 = "/Lotus/Language/Game/ExcavationTime"
     334 [-]: LOADK R15 K102; var15 = "</font><font color=\""
     335 [-]: MOVE R16 R9  ; var16 = var9
     336 [-]: LOADK R17 K103; var17 = "\"><b> %s</b></font>"
     337 [-]: CONCAT R10 R11 R17; var10 = var11 .. var17
     338 [-]: SETUPVAL R10 36; upvalues[10] = var36
     339 [-]: GETUPVAL R11 36; var11 = upvalues[36]
     340 [-]: LOADK R12 K104; var12 = "<font color=\""
     341 [-]: MOVE R13 R9  ; var13 = var9
     342 [-]: LOADK R14 K105; var14 = "\">  "
     343 [-]: LOADK R15 K106; var15 = "/Lotus/Language/Game/ExcavationPower"
     344 [-]: LOADK R16 K107; var16 = "</font>%s"
     345 [-]: CONCAT R10 R11 R16; var10 = var11 .. var16
     346 [-]: SETUPVAL R10 36; upvalues[10] = var36
     347 [-]: GETUPVAL R11 36; var11 = upvalues[36]
     348 [-]: LOADK R12 K108; var12 = "</p>"
     349 [-]: CONCAT R10 R11 R12; var10 = var11 .. var12
     350 [-]: SETUPVAL R10 36; upvalues[10] = var36
     351 [-]: LOADN R12 2  ; var12 = 2
     352 [-]: NAMECALL R10 R0 K109; var11 = var0; var10 = var0[0xFE9DC265]
     353 [-]: CALL R10 3 1 ; var10(var11, var12)
     354 [-]: GETIMPORT R10 67; var10 = _T
     355 [-]: GETUPVAL R11 8; var11 = upvalues[8]
     356 [-]: SETTABLEKS R11 R10 K110; var11["TransmissionSet"] = var10
     357 [-]: RETURN R0 0  ; 


; Name:            
; Defined at line: 852
; #Upvalues:       15
; #Parameters:     0
; Is_vararg:       0
; Max Stack Size:  17

       0 [-]: GETUPVAL R0 0; var0 = upvalues[0]
       1 [-]: NAMECALL R0 R0 K0; var1 = var0; var0 = var0[0x22DF603C]
       2 [-]: CALL R0 2 2  ; var0 = var0(var1)
       3 [-]: LOADN R1 0   ; var1 = 0
       4 [-]: FASTCALL1 62 R0 L0; 
       5 [-]: MOVE R3 R0   ; var3 = var0
       6 [-]: GETIMPORT R2 2; var2 = 0x7B998233
       7 [-]: CALL R2 2 2  ; var2 = var2(var3)
L 0:   8 [-]: JUMPIF R2 L1 ; goto L1 if var2
       9 [-]: LENGTH R1 R0 ; var1 = #var0
L 1:  10 [-]: GETUPVAL R3 1; var3 = upvalues[1]
      11 [-]: GETIMPORT R4 4; var4 = 0xFFF641AF
      12 [-]: CALL R4 1 2  ; var4 = var4()
      13 [-]: ADD R2 R3 R4 ; var2 = var3 + var4
      14 [-]: SETUPVAL R2 1; upvalues[2] = var1
      15 [-]: GETUPVAL R3 2; var3 = upvalues[2]
      16 [-]: GETIMPORT R4 4; var4 = 0xFFF641AF
      17 [-]: CALL R4 1 2  ; var4 = var4()
      18 [-]: ADD R2 R3 R4 ; var2 = var3 + var4
      19 [-]: SETUPVAL R2 2; upvalues[2] = var2
      20 [-]: GETUPVAL R2 1; var2 = upvalues[1]
      21 [-]: LOADK R3 K5  ; var3 = 0.5
      22 [-]: JUMPIFNOTLT R3 R2 L2; goto L2 if var3 >= var66311
      23 [-]: GETUPVAL R3 1; var3 = upvalues[1]
      24 [-]: SUBK R2 R3 K5; var2 = var3 - 0.5
      25 [-]: SETUPVAL R2 1; upvalues[2] = var1
      26 [-]: JUMP L3      ; goto L3
L 2:  27 [-]: RETURN R0 0  ; 
L 3:  28 [-]: GETIMPORT R2 7; var2 = 0x89326C93
      29 [-]: GETUPVAL R4 3; var4 = upvalues[3]
      30 [-]: GETUPVAL R5 4; var5 = upvalues[4]
      31 [-]: LOADN R6 0   ; var6 = 0
      32 [-]: GETUPVAL R8 5; var8 = upvalues[5]
      33 [-]: MULK R7 R8 K8; var7 = var8 * 2
      34 [-]: NAMECALL R2 R2 K9; var3 = var2; var2 = var2[0xFB669000]
      35 [-]: CALL R2 6 2  ; var2 = var2(var3, var4, var5, var6, var7)
      36 [-]: GETIMPORT R4 11; var4 = 0x229AE792
      37 [-]: GETIMPORT R5 13; var5 = 0x42DCC9F5
      38 [-]: GETUPVAL R7 6; var7 = upvalues[6]
      39 [-]: LENGTH R6 R7 ; var6 = #var7
      40 [-]: LOADN R7 1   ; var7 = 1
      41 [-]: LOADN R8 4   ; var8 = 4
      42 [-]: CALL R5 4 2  ; var5 = var5(var6, var7, var8)
      43 [-]: GETTABLE R3 R4 R5; var3 = var4[var5]
      44 [-]: GETUPVAL R4 2; var4 = upvalues[2]
      45 [-]: GETUPVAL R5 7; var5 = upvalues[7]
      46 [-]: JUMPIFNOTLE R5 R4 L10; goto L10 if var5 > var132359
      47 [-]: GETUPVAL R5 2; var5 = upvalues[2]
      48 [-]: GETUPVAL R6 7; var6 = upvalues[7]
      49 [-]: SUB R4 R5 R6 ; var4 = var5 - var6
      50 [-]: SETUPVAL R4 2; upvalues[4] = var2
      51 [-]: LOADN R4 0   ; var4 = 0
      52 [-]: GETIMPORT R6 16; var6 = _T["DynamicOverrideAgent"]
      53 [-]: FASTCALL1 62 R6 L4; 
      54 [-]: GETIMPORT R5 2; var5 = 0x7B998233
      55 [-]: CALL R5 2 2  ; var5 = var5(var6)
L 4:  56 [-]: JUMPIF R5 L6 ; goto L6 if var5
      57 [-]: GETIMPORT R5 16; var5 = _T["DynamicOverrideAgent"]
      58 [-]: GETIMPORT R6 18; var6 = 0x2FB3EF3B
      59 [-]: JUMPIFNOTEQ R5 R6 L6; goto L6 if var5 ~= var1312334
      60 [-]: GETIMPORT R6 20; var6 = _T["DynamicOverrideAgentCount"]
      61 [-]: FASTCALL2K 18 R6 K21 L5; 
      62 [-]: LOADK R7 K21 ; var7 = 0
      63 [-]: GETIMPORT R5 24; var5 = 0x5BCED4C4[0xB62ECFE0]
      64 [-]: CALL R5 3 2  ; var5 = var5(var6, var7)
L 5:  65 [-]: MOVE R4 R5   ; var4 = var5
L 6:  66 [-]: LENGTH R6 R2 ; var6 = #var2
      67 [-]: ADD R5 R6 R4 ; var5 = var6 + var4
      68 [-]: FASTCALL1 62 R2 L7; 
      69 [-]: MOVE R7 R2   ; var7 = var2
      70 [-]: GETIMPORT R6 2; var6 = 0x7B998233
      71 [-]: CALL R6 2 2  ; var6 = var6(var7)
L 7:  72 [-]: JUMPIF R6 L8 ; goto L8 if var6
      73 [-]: JUMPIFNOTLT R5 R3 L10; goto L10 if var5 >= var1050446
L 8:  74 [-]: GETIMPORT R7 16; var7 = _T["DynamicOverrideAgent"]
      75 [-]: FASTCALL1 62 R7 L9; 
      76 [-]: GETIMPORT R6 2; var6 = 0x7B998233
      77 [-]: CALL R6 2 2  ; var6 = var6(var7)
L 9:  78 [-]: JUMPIFNOT R6 L10; goto L10 if not var6
      79 [-]: GETIMPORT R6 26; var6 = 0x5BCED4C4[0x3630E649]
      80 [-]: GETUPVAL R8 8; var8 = upvalues[8]
      81 [-]: GETIMPORT R9 13; var9 = 0x42DCC9F5
      82 [-]: GETUPVAL R11 6; var11 = upvalues[6]
      83 [-]: LENGTH R10 R11; var10 = #var11
      84 [-]: LOADN R11 1  ; var11 = 1
      85 [-]: LOADN R12 4  ; var12 = 4
      86 [-]: CALL R9 4 2  ; var9 = var9(var10, var11, var12)
      87 [-]: GETTABLE R7 R8 R9; var7 = var8[var9]
      88 [-]: GETUPVAL R9 9; var9 = upvalues[9]
      89 [-]: GETIMPORT R10 13; var10 = 0x42DCC9F5
      90 [-]: GETUPVAL R12 6; var12 = upvalues[6]
      91 [-]: LENGTH R11 R12; var11 = #var12
      92 [-]: LOADN R12 1  ; var12 = 1
      93 [-]: LOADN R13 4  ; var13 = 4
      94 [-]: CALL R10 4 2 ; var10 = var10(var11, var12, var13)
      95 [-]: GETTABLE R8 R9 R10; var8 = var9[var10]
      96 [-]: CALL R6 3 2  ; var6 = var6(var7, var8)
      97 [-]: SETUPVAL R6 7; upvalues[6] = var7
      98 [-]: GETIMPORT R6 27; var6 = _T
      99 [-]: GETIMPORT R7 18; var7 = 0x2FB3EF3B
     100 [-]: SETTABLEKS R7 R6 K15; var7["DynamicOverrideAgent"] = var6
     101 [-]: LENGTH R7 R2 ; var7 = #var2
     102 [-]: SUB R6 R3 R7 ; var6 = var3 - var7
     103 [-]: LOADK R8 K28 ; var8 = "Queueing up "
     104 [-]: MOVE R9 R6   ; var9 = var6
     105 [-]: LOADK R10 K29; var10 = " cell carriers for reinforcements"
     106 [-]: CONCAT R7 R8 R10; var7 = var8 .. var10
     107 [-]: GETIMPORT R8 31; var8 = 0xD644C2F1
     108 [-]: MOVE R9 R7   ; var9 = var7
     109 [-]: CALL R8 2 1  ; var8(var9)
     110 [-]: GETIMPORT R8 33; var8 = 0x3D106989
     111 [-]: MOVE R9 R7   ; var9 = var7
     112 [-]: CALL R8 2 1  ; var8(var9)
     113 [-]: GETIMPORT R7 27; var7 = _T
     114 [-]: SETTABLEKS R6 R7 K19; var6["DynamicOverrideAgentCount"] = var7
L10: 115 [-]: GETIMPORT R4 35; var4 = 0xE77FE59F
     116 [-]: JUMPIFNOT R4 L12; goto L12 if not var4
     117 [-]: GETIMPORT R5 16; var5 = _T["DynamicOverrideAgent"]
     118 [-]: FASTCALL1 62 R5 L11; 
     119 [-]: GETIMPORT R4 2; var4 = 0x7B998233
     120 [-]: CALL R4 2 2  ; var4 = var4(var5)
L11: 121 [-]: JUMPIFNOT R4 L13; goto L13 if not var4
L12: 122 [-]: LENGTH R4 R0 ; var4 = #var0
     123 [-]: GETUPVAL R6 10; var6 = upvalues[10]
     124 [-]: GETUPVAL R8 6; var8 = upvalues[6]
     125 [-]: LENGTH R7 R8 ; var7 = #var8
     126 [-]: GETTABLE R5 R6 R7; var5 = var6[var7]
     127 [-]: JUMPIFNOTLT R4 R5 L22; goto L22 if var4 >= var459854
L13: 128 [-]: GETIMPORT R4 7; var4 = 0x89326C93
     129 [-]: GETUPVAL R6 11; var6 = upvalues[11]
     130 [-]: NAMECALL R4 R4 K36; var5 = var4; var4 = var4[0xC7FCADA9]
     131 [-]: CALL R4 3 2  ; var4 = var4(var5, var6)
     132 [-]: GETUPVAL R5 4; var5 = upvalues[4]
     133 [-]: FASTCALL1 62 R4 L14; 
     134 [-]: MOVE R7 R4   ; var7 = var4
     135 [-]: GETIMPORT R6 2; var6 = 0x7B998233
     136 [-]: CALL R6 2 2  ; var6 = var6(var7)
L14: 137 [-]: JUMPIFNOT R6 L15; goto L15 if not var6
     138 [-]: RETURN R0 0  ; 
L15: 139 [-]: GETUPVAL R7 12; var7 = upvalues[12]
     140 [-]: FASTCALL1 62 R7 L16; 
     141 [-]: GETIMPORT R6 2; var6 = 0x7B998233
     142 [-]: CALL R6 2 2  ; var6 = var6(var7)
L16: 143 [-]: JUMPIF R6 L18; goto L18 if var6
     144 [-]: GETUPVAL R7 12; var7 = upvalues[12]
     145 [-]: LENGTH R6 R7 ; var6 = #var7
     146 [-]: LOADN R7 0   ; var7 = 0
     147 [-]: JUMPIFNOTLT R7 R6 L18; goto L18 if var7 >= var788231
     148 [-]: GETUPVAL R7 12; var7 = upvalues[12]
     149 [-]: GETIMPORT R8 38; var8 = 0x55730E1A
     150 [-]: LOADN R9 1   ; var9 = 1
     151 [-]: GETUPVAL R11 12; var11 = upvalues[12]
     152 [-]: LENGTH R10 R11; var10 = #var11
     153 [-]: CALL R8 3 2  ; var8 = var8(var9, var10)
     154 [-]: GETTABLE R6 R7 R8; var6 = var7[var8]
     155 [-]: NAMECALL R6 R6 K39; var7 = var6; var6 = var6[0xBB610E5B]
     156 [-]: CALL R6 2 2  ; var6 = var6(var7)
     157 [-]: FASTCALL1 62 R6 L17; 
     158 [-]: MOVE R8 R6   ; var8 = var6
     159 [-]: GETIMPORT R7 2; var7 = 0x7B998233
     160 [-]: CALL R7 2 2  ; var7 = var7(var8)
L17: 161 [-]: JUMPIF R7 L18; goto L18 if var7
     162 [-]: NAMECALL R7 R6 K40; var8 = var6; var7 = var6[0xD1586535]
     163 [-]: CALL R7 2 2  ; var7 = var7(var8)
     164 [-]: MOVE R5 R7   ; var5 = var7
L18: 165 [-]: GETUPVAL R6 13; var6 = upvalues[13]
     166 [-]: MOVE R8 R5   ; var8 = var5
     167 [-]: LOADN R9 0   ; var9 = 0
     168 [-]: LOADN R10 20 ; var10 = 20
     169 [-]: GETIMPORT R12 42; var12 = 0x7496783E
     170 [-]: GETIMPORT R13 38; var13 = 0x55730E1A
     171 [-]: LOADN R14 1  ; var14 = 1
     172 [-]: GETIMPORT R16 42; var16 = 0x7496783E
     173 [-]: LENGTH R15 R16; var15 = #var16
     174 [-]: CALL R13 3 2 ; var13 = var13(var14, var15)
     175 [-]: GETTABLE R11 R12 R13; var11 = var12[var13]
     176 [-]: LOADN R12 2  ; var12 = 2
     177 [-]: LOADN R13 2  ; var13 = 2
     178 [-]: GETUPVAL R14 14; var14 = upvalues[14]
     179 [-]: NAMECALL R6 R6 K43; var7 = var6; var6 = var6[0xA3871690]
     180 [-]: CALL R6 9 1  ; var6(var7, var8, var9, var10, var11, var12, var13, var14)
     181 [-]: GETIMPORT R6 33; var6 = 0x3D106989
     182 [-]: LOADK R7 K44 ; var7 = "             Dynamic Excavation spawned another Reinforcement Encounter"
     183 [-]: CALL R6 2 1  ; var6(var7)
     184 [-]: GETIMPORT R6 27; var6 = _T
     185 [-]: GETIMPORT R8 47; var8 = _T["DynExcavNumExpectedEnemy"]
     186 [-]: ADDK R7 R8 K45; var7 = var8 + 5
     187 [-]: SETTABLEKS R7 R6 K46; var7["DynExcavNumExpectedEnemy"] = var6
     188 [-]: LENGTH R7 R0 ; var7 = #var0
     189 [-]: GETIMPORT R8 47; var8 = _T["DynExcavNumExpectedEnemy"]
     190 [-]: ADD R6 R7 R8 ; var6 = var7 + var8
     191 [-]: GETUPVAL R8 10; var8 = upvalues[10]
     192 [-]: GETUPVAL R10 6; var10 = upvalues[6]
     193 [-]: LENGTH R9 R10; var9 = #var10
     194 [-]: GETTABLE R7 R8 R9; var7 = var8[var9]
     195 [-]: JUMPIFNOTLT R7 R6 L19; goto L19 if var7 >= var67335
     196 [-]: GETUPVAL R7 1; var7 = upvalues[1]
     197 [-]: SUBK R6 R7 K48; var6 = var7 - 13
     198 [-]: SETUPVAL R6 1; upvalues[6] = var1
L19: 199 [-]: GETIMPORT R7 16; var7 = _T["DynamicOverrideAgent"]
     200 [-]: FASTCALL1 62 R7 L20; 
     201 [-]: GETIMPORT R6 2; var6 = 0x7B998233
     202 [-]: CALL R6 2 2  ; var6 = var6(var7)
L20: 203 [-]: JUMPIF R6 L21; goto L21 if var6
     204 [-]: LOADK R7 K49 ; var7 = "     EXCAVATION bringing in a Carrier. There are "
     205 [-]: LENGTH R8 R0 ; var8 = #var0
     206 [-]: LOADK R9 K50 ; var9 = " registered agents"
     207 [-]: CONCAT R6 R7 R9; var6 = var7 .. var9
     208 [-]: GETIMPORT R7 31; var7 = 0xD644C2F1
     209 [-]: MOVE R8 R6   ; var8 = var6
     210 [-]: CALL R7 2 1  ; var7(var8)
     211 [-]: GETIMPORT R7 33; var7 = 0x3D106989
     212 [-]: MOVE R8 R6   ; var8 = var6
     213 [-]: CALL R7 2 1  ; var7(var8)
     214 [-]: RETURN R0 0  ; 
L21: 215 [-]: LENGTH R6 R0 ; var6 = #var0
     216 [-]: GETUPVAL R8 10; var8 = upvalues[10]
     217 [-]: GETUPVAL R10 6; var10 = upvalues[6]
     218 [-]: LENGTH R9 R10; var9 = #var10
     219 [-]: GETTABLE R7 R8 R9; var7 = var8[var9]
     220 [-]: JUMPIFNOTLT R7 R6 L22; goto L22 if var7 >= var3344133
     221 [-]: LOADK R7 K51 ; var7 = "     EXCAVATION registered agent count == "
     222 [-]: LENGTH R8 R0 ; var8 = #var0
     223 [-]: LOADK R9 K52 ; var9 = " which is more than "
     224 [-]: GETUPVAL R11 10; var11 = upvalues[10]
     225 [-]: GETUPVAL R13 6; var13 = upvalues[6]
     226 [-]: LENGTH R12 R13; var12 = #var13
     227 [-]: GETTABLE R10 R11 R12; var10 = var11[var12]
     228 [-]: CONCAT R6 R7 R10; var6 = var7 .. var10
     229 [-]: GETIMPORT R7 31; var7 = 0xD644C2F1
     230 [-]: MOVE R8 R6   ; var8 = var6
     231 [-]: CALL R7 2 1  ; var7(var8)
     232 [-]: GETIMPORT R7 33; var7 = 0x3D106989
     233 [-]: MOVE R8 R6   ; var8 = var6
     234 [-]: CALL R7 2 1  ; var7(var8)
L22: 235 [-]: RETURN R0 0  ; 


; Name:            
; Defined at line: 924
; #Upvalues:       3
; #Parameters:     0
; Is_vararg:       0
; Max Stack Size:  6

       0 [-]: GETIMPORT R0 1; var0 = 0xBE190284
       1 [-]: GETUPVAL R2 0; var2 = upvalues[0]
       2 [-]: LOADN R3 0   ; var3 = 0
       3 [-]: NAMECALL R0 R0 K2; var1 = var0; var0 = var0[0x0EB34C69]
       4 [-]: CALL R0 4 2  ; var0 = var0(var1, var2, var3)
       5 [-]: GETIMPORT R1 4; var1 = 0x1AC7975A
       6 [-]: JUMPIFNOT R1 L0; goto L0 if not var1
       7 [-]: GETUPVAL R2 1; var2 = upvalues[1]
       8 [-]: GETTABLEKS R1 R2 K5; var1 = var2[0xF3928F38]
       9 [-]: MOVE R2 R0   ; var2 = var0
      10 [-]: GETUPVAL R4 2; var4 = upvalues[2]
      11 [-]: LENGTH R3 R4 ; var3 = #var4
      12 [-]: CALL R1 3 1  ; var1(var2, var3)
      13 [-]: RETURN R0 0  ; 
L 0:  14 [-]: GETUPVAL R2 1; var2 = upvalues[1]
      15 [-]: GETTABLEKS R1 R2 K5; var1 = var2[0xF3928F38]
      16 [-]: MOVE R2 R0   ; var2 = var0
      17 [-]: GETUPVAL R5 2; var5 = upvalues[2]
      18 [-]: LENGTH R4 R5 ; var4 = #var5
      19 [-]: FASTCALL2K 19 R4 K6 L1; 
      20 [-]: LOADK R5 K6  ; var5 = 3
      21 [-]: GETIMPORT R3 9; var3 = 0x5BCED4C4[0xAC1B386A]
      22 [-]: CALL R3 3 2  ; var3 = var3(var4, var5)
L 1:  23 [-]: CALL R1 3 1  ; var1(var2, var3)
      24 [-]: RETURN R0 0  ; 


; Name:            
; Defined at line: 933
; #Upvalues:       6
; #Parameters:     0
; Is_vararg:       0
; Max Stack Size:  13

       0 [-]: GETIMPORT R1 1; var1 = 0x1AC7975A
       1 [-]: JUMPIFNOT R1 L0; goto L0 if not var1
       2 [-]: GETUPVAL R1 0; var1 = upvalues[0]
       3 [-]: LENGTH R0 R1 ; var0 = #var1
       4 [-]: JUMPIF R0 L1 ; goto L1 if var0
L 0:   5 [-]: GETUPVAL R2 0; var2 = upvalues[0]
       6 [-]: LENGTH R1 R2 ; var1 = #var2
       7 [-]: FASTCALL2K 19 R1 K2 L1; 
       8 [-]: LOADK R2 K2  ; var2 = 3
       9 [-]: GETIMPORT R0 5; var0 = 0x5BCED4C4[0xAC1B386A]
      10 [-]: CALL R0 3 2  ; var0 = var0(var1, var2)
L 1:  11 [-]: GETIMPORT R1 7; var1 = 0xBE190284
      12 [-]: GETUPVAL R3 1; var3 = upvalues[1]
      13 [-]: LOADN R4 0   ; var4 = 0
      14 [-]: NAMECALL R1 R1 K8; var2 = var1; var1 = var1[0x0EB34C69]
      15 [-]: CALL R1 4 2  ; var1 = var1(var2, var3, var4)
      16 [-]: GETIMPORT R2 7; var2 = 0xBE190284
      17 [-]: GETUPVAL R4 2; var4 = upvalues[2]
      18 [-]: LOADN R5 0   ; var5 = 0
      19 [-]: NAMECALL R2 R2 K8; var3 = var2; var2 = var2[0x0EB34C69]
      20 [-]: CALL R2 4 2  ; var2 = var2(var3, var4, var5)
      21 [-]: GETIMPORT R3 7; var3 = 0xBE190284
      22 [-]: GETUPVAL R5 3; var5 = upvalues[3]
      23 [-]: LOADN R6 0   ; var6 = 0
      24 [-]: NAMECALL R3 R3 K8; var4 = var3; var3 = var3[0x0EB34C69]
      25 [-]: CALL R3 4 2  ; var3 = var3(var4, var5, var6)
      26 [-]: ADD R5 R1 R2 ; var5 = var1 + var2
      27 [-]: JUMPIFLE R0 R5 L2; goto L2 if var0 <= var16778267
      28 [-]: LOADB R4 0 +1; var4 = false
L 2:  29 [-]: LOADB R4 1   ; var4 = true
L 3:  30 [-]: MOVE R5 R4   ; var5 = var4
      31 [-]: JUMPIFNOT R5 L5; goto L5 if not var5
      32 [-]: LOADN R6 0   ; var6 = 0
      33 [-]: JUMPIFLT R6 R1 L4; goto L4 if var6 < var16778523
      34 [-]: LOADB R5 0 +1; var5 = false
L 4:  35 [-]: LOADB R5 1   ; var5 = true
L 5:  36 [-]: JUMPIFLE R0 R2 L6; goto L6 if var0 <= var16778779
      37 [-]: LOADB R6 0 +1; var6 = false
L 6:  38 [-]: LOADB R6 1   ; var6 = true
L 7:  39 [-]: JUMPIFLE R0 R1 L8; goto L8 if var0 <= var16779035
      40 [-]: LOADB R7 0 +1; var7 = false
L 8:  41 [-]: LOADB R7 1   ; var7 = true
L 9:  42 [-]: JUMPIFNOT R4 L13; goto L13 if not var4
      43 [-]: GETIMPORT R8 10; var8 = 0x3D106989
      44 [-]: LOADK R10 K11; var10 = "num players: "
      45 [-]: GETUPVAL R12 0; var12 = upvalues[0]
      46 [-]: LENGTH R11 R12; var11 = #var12
      47 [-]: CONCAT R9 R10 R11; var9 = var10 .. var11
      48 [-]: CALL R8 2 1  ; var8(var9)
      49 [-]: GETIMPORT R8 10; var8 = 0x3D106989
      50 [-]: LOADK R10 K12; var10 = "digsCompleted: "
      51 [-]: MOVE R11 R1  ; var11 = var1
      52 [-]: CONCAT R9 R10 R11; var9 = var10 .. var11
      53 [-]: CALL R8 2 1  ; var8(var9)
      54 [-]: GETIMPORT R8 10; var8 = 0x3D106989
      55 [-]: LOADK R10 K13; var10 = "excavatorsDestroyed: "
      56 [-]: MOVE R11 R2  ; var11 = var2
      57 [-]: CONCAT R9 R10 R11; var9 = var10 .. var11
      58 [-]: CALL R8 2 1  ; var8(var9)
      59 [-]: GETIMPORT R8 10; var8 = 0x3D106989
      60 [-]: LOADK R10 K14; var10 = "excavatorsDeployed: "
      61 [-]: MOVE R11 R3  ; var11 = var3
      62 [-]: CONCAT R9 R10 R11; var9 = var10 .. var11
      63 [-]: CALL R8 2 1  ; var8(var9)
      64 [-]: GETIMPORT R8 10; var8 = 0x3D106989
      65 [-]: LOADK R10 K15; var10 = "numDigsCompleteForBonus: "
      66 [-]: MOVE R11 R0  ; var11 = var0
      67 [-]: CONCAT R9 R10 R11; var9 = var10 .. var11
      68 [-]: CALL R8 2 1  ; var8(var9)
      69 [-]: GETIMPORT R8 10; var8 = 0x3D106989
      70 [-]: LOADK R10 K16; var10 = "encounterFailed: "
      71 [-]: GETIMPORT R11 18; var11 = 0x64FB1586
      72 [-]: MOVE R12 R6  ; var12 = var6
      73 [-]: CALL R11 2 2 ; var11 = var11(var12)
      74 [-]: CONCAT R9 R10 R11; var9 = var10 .. var11
      75 [-]: CALL R8 2 1  ; var8(var9)
      76 [-]: GETIMPORT R8 10; var8 = 0x3D106989
      77 [-]: LOADK R10 K19; var10 = "bonusSuceeded: "
      78 [-]: GETIMPORT R11 18; var11 = 0x64FB1586
      79 [-]: MOVE R12 R7  ; var12 = var7
      80 [-]: CALL R11 2 2 ; var11 = var11(var12)
      81 [-]: CONCAT R9 R10 R11; var9 = var10 .. var11
      82 [-]: CALL R8 2 1  ; var8(var9)
      83 [-]: GETIMPORT R8 10; var8 = 0x3D106989
      84 [-]: LOADK R10 K20; var10 = "encounterSuceeded: "
      85 [-]: GETIMPORT R11 18; var11 = 0x64FB1586
      86 [-]: MOVE R12 R5  ; var12 = var5
      87 [-]: CALL R11 2 2 ; var11 = var11(var12)
      88 [-]: CONCAT R9 R10 R11; var9 = var10 .. var11
      89 [-]: CALL R8 2 1  ; var8(var9)
      90 [-]: GETIMPORT R8 10; var8 = 0x3D106989
      91 [-]: LOADK R10 K21; var10 = "encounterCompleted: "
      92 [-]: GETIMPORT R11 18; var11 = 0x64FB1586
      93 [-]: MOVE R12 R4  ; var12 = var4
      94 [-]: CALL R11 2 2 ; var11 = var11(var12)
      95 [-]: CONCAT R9 R10 R11; var9 = var10 .. var11
      96 [-]: CALL R8 2 1  ; var8(var9)
      97 [-]: JUMPIFNOT R5 L12; goto L12 if not var5
      98 [-]: JUMPIFNOT R7 L10; goto L10 if not var7
      99 [-]: GETIMPORT R8 23; var8 = 0xD644C2F1
     100 [-]: LOADK R9 K24 ; var9 = "Encounter: SUCCESS Bonus: SUCCESS"
     101 [-]: CALL R8 2 1  ; var8(var9)
     102 [-]: GETIMPORT R8 10; var8 = 0x3D106989
     103 [-]: LOADK R9 K24 ; var9 = "Encounter: SUCCESS Bonus: SUCCESS"
     104 [-]: CALL R8 2 1  ; var8(var9)
     105 [-]: JUMP L11     ; goto L11
L10: 106 [-]: GETIMPORT R8 23; var8 = 0xD644C2F1
     107 [-]: LOADK R9 K25 ; var9 = "Encounter: SUCCESS Bonus: FAIL"
     108 [-]: CALL R8 2 1  ; var8(var9)
     109 [-]: GETIMPORT R8 10; var8 = 0x3D106989
     110 [-]: LOADK R9 K25 ; var9 = "Encounter: SUCCESS Bonus: FAIL"
     111 [-]: CALL R8 2 1  ; var8(var9)
L11: 112 [-]: GETIMPORT R8 27; var8 = _T
     113 [-]: SETTABLEKS R7 R8 K28; var7["QualifiedForBountyBonus"] = var8
     114 [-]: GETUPVAL R8 4; var8 = upvalues[4]
     115 [-]: LOADN R10 3  ; var10 = 3
     116 [-]: NAMECALL R8 R8 K29; var9 = var8; var8 = var8[0x8ABFF40E]
     117 [-]: CALL R8 3 1  ; var8(var9, var10)
     118 [-]: GETUPVAL R8 5; var8 = upvalues[5]
     119 [-]: LOADN R10 4  ; var10 = 4
     120 [-]: NAMECALL R8 R8 K30; var9 = var8; var8 = var8[0xFE9DC265]
     121 [-]: CALL R8 3 1  ; var8(var9, var10)
     122 [-]: LOADB R8 1   ; var8 = true
     123 [-]: RETURN R8 1  ; 
L12: 124 [-]: JUMPIFNOT R6 L14; goto L14 if not var6
     125 [-]: GETIMPORT R8 23; var8 = 0xD644C2F1
     126 [-]: LOADK R9 K31 ; var9 = "Encounter: FAIL Bonus: FAIL"
     127 [-]: CALL R8 2 1  ; var8(var9)
     128 [-]: GETIMPORT R8 10; var8 = 0x3D106989
     129 [-]: LOADK R9 K31 ; var9 = "Encounter: FAIL Bonus: FAIL"
     130 [-]: CALL R8 2 1  ; var8(var9)
     131 [-]: GETUPVAL R8 4; var8 = upvalues[4]
     132 [-]: LOADN R10 4  ; var10 = 4
     133 [-]: NAMECALL R8 R8 K29; var9 = var8; var8 = var8[0x8ABFF40E]
     134 [-]: CALL R8 3 1  ; var8(var9, var10)
     135 [-]: GETUPVAL R8 5; var8 = upvalues[5]
     136 [-]: LOADN R10 5  ; var10 = 5
     137 [-]: NAMECALL R8 R8 K30; var9 = var8; var8 = var8[0xFE9DC265]
     138 [-]: CALL R8 3 1  ; var8(var9, var10)
     139 [-]: LOADB R8 1   ; var8 = true
     140 [-]: RETURN R8 1  ; 
     141 [-]: RETURN R0 0  ; 
L13: 142 [-]: LOADB R8 0   ; var8 = false
     143 [-]: RETURN R8 1  ; 
L14: 144 [-]: RETURN R0 0  ; 


; Name:            
; Defined at line: 977
; #Upvalues:       2
; #Parameters:     0
; Is_vararg:       0
; Max Stack Size:  7

       0 [-]: GETIMPORT R0 1; var0 = 0xCFC01047
       1 [-]: GETUPVAL R1 0; var1 = upvalues[0]
       2 [-]: CALL R0 2 4  ; var0, var1, var2 = var0(var1)
       3 [-]: FORGPREP_NEXT R0 L1; 
L 0:   4 [-]: GETUPVAL R5 1; var5 = upvalues[1]
       5 [-]: MOVE R6 R4   ; var6 = var4
       6 [-]: CALL R5 2 1  ; var5(var6)
L 1:   7 [-]: FORGLOOP R0 L0 2; 
       8 [-]: RETURN R0 0  ; 


; Name:            
; Defined at line: 983
; #Upvalues:       3
; #Parameters:     1
; Is_vararg:       0
; Max Stack Size:  8

       0 [-]: GETIMPORT R2 2; var2 = _T["DynExcavNumRequested"]
       1 [-]: FASTCALL1 62 R2 L0; 
       2 [-]: GETIMPORT R1 4; var1 = 0x7B998233
       3 [-]: CALL R1 2 2  ; var1 = var1(var2)
L 0:   4 [-]: JUMPIFNOT R1 L1; goto L1 if not var1
       5 [-]: GETIMPORT R1 5; var1 = _T
       6 [-]: LOADN R2 1   ; var2 = 1
       7 [-]: SETTABLEKS R2 R1 K1; var2["DynExcavNumRequested"] = var1
       8 [-]: JUMP L2      ; goto L2
L 1:   9 [-]: GETIMPORT R1 5; var1 = _T
      10 [-]: GETIMPORT R3 2; var3 = _T["DynExcavNumRequested"]
      11 [-]: ADDK R2 R3 K6; var2 = var3 + 1
      12 [-]: SETTABLEKS R2 R1 K1; var2["DynExcavNumRequested"] = var1
L 2:  13 [-]: FASTCALL1 62 R0 L3; 
      14 [-]: MOVE R2 R0   ; var2 = var0
      15 [-]: GETIMPORT R1 4; var1 = 0x7B998233
      16 [-]: CALL R1 2 2  ; var1 = var1(var2)
L 3:  17 [-]: JUMPIFNOT R1 L4; goto L4 if not var1
      18 [-]: GETIMPORT R1 8; var1 = 0x89326C93
      19 [-]: GETUPVAL R3 0; var3 = upvalues[0]
      20 [-]: GETUPVAL R4 1; var4 = upvalues[1]
      21 [-]: GETIMPORT R5 10; var5 = ZERO_ROTATION
      22 [-]: GETUPVAL R6 2; var6 = upvalues[2]
      23 [-]: GETUPVAL R7 2; var7 = upvalues[2]
      24 [-]: NAMECALL R1 R1 K11; var2 = var1; var1 = var1[0x05909209]
      25 [-]: CALL R1 7 2  ; var1 = var1(var2, var3, var4, var5, var6, var7)
      26 [-]: MOVE R0 R1   ; var0 = var1
L 4:  27 [-]: GETIMPORT R3 13; var3 = 0x0469F296
      28 [-]: LOADK R4 K14 ; var4 = "DropExcavator"
      29 [-]: CALL R3 2 2  ; var3 = var3(var4)
      30 [-]: LOADB R4 0   ; var4 = false
      31 [-]: NAMECALL R1 R0 K15; var2 = var0; var1 = var0[0xD5F7912B]
      32 [-]: CALL R1 4 1  ; var1(var2, var3, var4)
      33 [-]: RETURN R0 0  ; 


; Name:            
; Defined at line: 995
; #Upvalues:       40
; #Parameters:     1
; Is_vararg:       0
; Max Stack Size:  23

       0 [-]: GETUPVAL R1 0; var1 = upvalues[0]
       1 [-]: MOVE R2 R0   ; var2 = var0
       2 [-]: CALL R1 2 1  ; var1(var2)
L 0:   3 [-]: NAMECALL R1 R0 K0; var2 = var0; var1 = var0[0xEFE6CAD1]
       4 [-]: CALL R1 2 2  ; var1 = var1(var2)
       5 [-]: LOADN R2 4   ; var2 = 4
       6 [-]: JUMPIFNOTLT R1 R2 L29; goto L29 if var1 >= var131406
       7 [-]: GETIMPORT R1 2; var1 = 0x89326C93
       8 [-]: GETUPVAL R3 2; var3 = upvalues[2]
       9 [-]: NAMECALL R1 R1 K3; var2 = var1; var1 = var1[0xC7FCADA9]
      10 [-]: CALL R1 3 2  ; var1 = var1(var2, var3)
      11 [-]: SETUPVAL R1 1; upvalues[1] = var1
      12 [-]: GETUPVAL R1 3; var1 = upvalues[3]
      13 [-]: NAMECALL R1 R1 K4; var2 = var1; var1 = var1[0x209398C2]
      14 [-]: CALL R1 2 2  ; var1 = var1(var2)
      15 [-]: JUMPXEQKN R1 K5 L6 NOT; 
      16 [-]: GETUPVAL R2 1; var2 = upvalues[1]
      17 [-]: LENGTH R1 R2 ; var1 = #var2
      18 [-]: GETUPVAL R3 4; var3 = upvalues[4]
      19 [-]: GETTABLEKS R2 R3 K6; var2 = var3[0x9742B85B]
      20 [-]: GETUPVAL R3 5; var3 = upvalues[5]
      21 [-]: GETIMPORT R4 8; var4 = 0x0469F296
      22 [-]: LOADK R5 K9  ; var5 = "DynamicExcavation_ExcavatorDeploy"
      23 [-]: CALL R4 2 0  ; var4, ... = var4(var5)
      24 [-]: CALL R2 0 1  ; var2(var3, ...)
      25 [-]: GETUPVAL R4 6; var4 = upvalues[6]
      26 [-]: LENGTH R3 R4 ; var3 = #var4
      27 [-]: GETIMPORT R4 11; var4 = 0x9BA7909F
      28 [-]: LOADK R6 K12 ; var6 = "Server.NumVirtualTestClients"
      29 [-]: NAMECALL R4 R4 K13; var5 = var4; var4 = var4[0x8151451D]
      30 [-]: CALL R4 3 2  ; var4 = var4(var5, var6)
      31 [-]: ADD R2 R3 R4 ; var2 = var3 + var4
      32 [-]: GETIMPORT R3 15; var3 = 0x1AC7975A
      33 [-]: JUMPIFNOT R3 L2; goto L2 if not var3
      34 [-]: ADDK R5 R1 K5; var5 = var1 + 1
      35 [-]: MOVE R3 R2   ; var3 = var2
      36 [-]: LOADN R4 1   ; var4 = 1
      37 [-]: FORNPREP R3 L5; nforprep start - [escape at L5] -- var3 = iterator
L 1:  38 [-]: GETUPVAL R6 7; var6 = upvalues[7]
      39 [-]: CALL R6 1 1  ; var6()
      40 [-]: FORNLOOP R3 L1; nforloop end - iterate + goto L1
      41 [-]: JUMP L5      ; goto L5
L 2:  42 [-]: ADDK R5 R1 K5; var5 = var1 + 1
      43 [-]: FASTCALL2K 19 R2 K16 L3; 
      44 [-]: MOVE R7 R2   ; var7 = var2
      45 [-]: LOADK R8 K16 ; var8 = 3
      46 [-]: GETIMPORT R6 19; var6 = 0x5BCED4C4[0xAC1B386A]
      47 [-]: CALL R6 3 2  ; var6 = var6(var7, var8)
L 3:  48 [-]: MOVE R3 R6   ; var3 = var6
      49 [-]: LOADN R4 1   ; var4 = 1
      50 [-]: FORNPREP R3 L5; nforprep start - [escape at L5] -- var3 = iterator
L 4:  51 [-]: GETUPVAL R6 7; var6 = upvalues[7]
      52 [-]: CALL R6 1 1  ; var6()
      53 [-]: FORNLOOP R3 L4; nforloop end - iterate + goto L4
L 5:  54 [-]: GETUPVAL R3 3; var3 = upvalues[3]
      55 [-]: LOADN R5 2   ; var5 = 2
      56 [-]: NAMECALL R3 R3 K20; var4 = var3; var3 = var3[0x8ABFF40E]
      57 [-]: CALL R3 3 1  ; var3(var4, var5)
      58 [-]: GETIMPORT R3 22; var3 = 0xBE190284
      59 [-]: GETUPVAL R5 9; var5 = upvalues[9]
      60 [-]: LOADN R6 0   ; var6 = 0
      61 [-]: NAMECALL R3 R3 K23; var4 = var3; var3 = var3[0x0EB34C69]
      62 [-]: CALL R3 4 2  ; var3 = var3(var4, var5, var6)
      63 [-]: SETUPVAL R3 8; upvalues[3] = var8
      64 [-]: GETIMPORT R3 22; var3 = 0xBE190284
      65 [-]: GETUPVAL R5 10; var5 = upvalues[10]
      66 [-]: GETIMPORT R6 25; var6 = EMPTY_SYMBOL
      67 [-]: LOADN R7 0   ; var7 = 0
      68 [-]: LOADB R8 0   ; var8 = false
      69 [-]: LOADB R9 0   ; var9 = false
      70 [-]: LOADB R10 1  ; var10 = true
      71 [-]: NAMECALL R3 R3 K26; var4 = var3; var3 = var3[0xFE23FE59]
      72 [-]: CALL R3 8 1  ; var3(var4, var5, var6, var7, var8, var9, var10)
      73 [-]: GETIMPORT R3 22; var3 = 0xBE190284
      74 [-]: GETUPVAL R5 10; var5 = upvalues[10]
      75 [-]: GETUPVAL R6 8; var6 = upvalues[8]
      76 [-]: NAMECALL R3 R3 K27; var4 = var3; var3 = var3[0x39A80406]
      77 [-]: CALL R3 4 1  ; var3(var4, var5, var6)
      78 [-]: JUMP L27     ; goto L27
L 6:  79 [-]: GETUPVAL R1 3; var1 = upvalues[3]
      80 [-]: NAMECALL R1 R1 K4; var2 = var1; var1 = var1[0x209398C2]
      81 [-]: CALL R1 2 2  ; var1 = var1(var2)
      82 [-]: JUMPXEQKN R1 K28 L27 NOT; 
      83 [-]: GETIMPORT R1 22; var1 = 0xBE190284
      84 [-]: GETUPVAL R3 10; var3 = upvalues[10]
      85 [-]: NAMECALL R1 R1 K29; var2 = var1; var1 = var1[0xFFDDF768]
      86 [-]: CALL R1 3 2  ; var1 = var1(var2, var3)
      87 [-]: SETUPVAL R1 8; upvalues[1] = var8
      88 [-]: GETIMPORT R1 22; var1 = 0xBE190284
      89 [-]: GETUPVAL R3 9; var3 = upvalues[9]
      90 [-]: GETUPVAL R5 8; var5 = upvalues[8]
      91 [-]: FASTCALL1 7 R5 L7; 
      92 [-]: GETIMPORT R4 31; var4 = 0x5BCED4C4[0x99675E23]
      93 [-]: CALL R4 2 2  ; var4 = var4(var5)
L 7:  94 [-]: NAMECALL R1 R1 K32; var2 = var1; var1 = var1[0x751F061D]
      95 [-]: CALL R1 4 1  ; var1(var2, var3, var4)
      96 [-]: GETIMPORT R1 2; var1 = 0x89326C93
      97 [-]: GETUPVAL R3 11; var3 = upvalues[11]
      98 [-]: NAMECALL R1 R1 K3; var2 = var1; var1 = var1[0xC7FCADA9]
      99 [-]: CALL R1 3 2  ; var1 = var1(var2, var3)
     100 [-]: LOADN R2 0   ; var2 = 0
     101 [-]: FASTCALL1 62 R1 L8; 
     102 [-]: MOVE R4 R1   ; var4 = var1
     103 [-]: GETIMPORT R3 34; var3 = 0x7B998233
     104 [-]: CALL R3 2 2  ; var3 = var3(var4)
L 8: 105 [-]: JUMPIF R3 L9 ; goto L9 if var3
     106 [-]: LENGTH R2 R1 ; var2 = #var1
L 9: 107 [-]: GETIMPORT R3 22; var3 = 0xBE190284
     108 [-]: GETUPVAL R5 12; var5 = upvalues[12]
     109 [-]: LOADN R6 0   ; var6 = 0
     110 [-]: NAMECALL R3 R3 K23; var4 = var3; var3 = var3[0x0EB34C69]
     111 [-]: CALL R3 4 2  ; var3 = var3(var4, var5, var6)
     112 [-]: GETIMPORT R4 22; var4 = 0xBE190284
     113 [-]: GETUPVAL R6 13; var6 = upvalues[13]
     114 [-]: LOADN R7 0   ; var7 = 0
     115 [-]: NAMECALL R4 R4 K23; var5 = var4; var4 = var4[0x0EB34C69]
     116 [-]: CALL R4 4 2  ; var4 = var4(var5, var6, var7)
     117 [-]: ADD R6 R2 R3 ; var6 = var2 + var3
     118 [-]: ADD R5 R6 R4 ; var5 = var6 + var4
     119 [-]: GETIMPORT R6 15; var6 = 0x1AC7975A
     120 [-]: JUMPIFNOT R6 L10; goto L10 if not var6
     121 [-]: GETUPVAL R7 6; var7 = upvalues[6]
     122 [-]: LENGTH R6 R7 ; var6 = #var7
     123 [-]: GETIMPORT R8 37; var8 = _T["DynExcavNumRequested"]
     124 [-]: ADD R7 R5 R8 ; var7 = var5 + var8
     125 [-]: JUMPIFNOTLT R7 R6 L10; goto L10 if var7 >= var2557518
     126 [-]: GETIMPORT R6 39; var6 = 0x3D106989
     127 [-]: LOADK R7 K40 ; var7 = "More players than excavators, creating new excavator"
     128 [-]: CALL R6 2 1  ; var6(var7)
     129 [-]: GETUPVAL R6 7; var6 = upvalues[7]
     130 [-]: CALL R6 1 1  ; var6()
     131 [-]: JUMP L12     ; goto L12
L10: 132 [-]: GETIMPORT R6 15; var6 = 0x1AC7975A
     133 [-]: JUMPIF R6 L12; goto L12 if var6
     134 [-]: GETUPVAL R8 6; var8 = upvalues[6]
     135 [-]: LENGTH R7 R8 ; var7 = #var8
     136 [-]: FASTCALL2K 19 R7 K16 L11; 
     137 [-]: LOADK R8 K16 ; var8 = 3
     138 [-]: GETIMPORT R6 19; var6 = 0x5BCED4C4[0xAC1B386A]
     139 [-]: CALL R6 3 2  ; var6 = var6(var7, var8)
L11: 140 [-]: GETIMPORT R8 37; var8 = _T["DynExcavNumRequested"]
     141 [-]: ADD R7 R5 R8 ; var7 = var5 + var8
     142 [-]: JUMPIFNOTLT R7 R6 L12; goto L12 if var7 >= var2557518
     143 [-]: GETIMPORT R6 39; var6 = 0x3D106989
     144 [-]: LOADK R7 K40 ; var7 = "More players than excavators, creating new excavator"
     145 [-]: CALL R6 2 1  ; var6(var7)
     146 [-]: GETUPVAL R6 7; var6 = upvalues[7]
     147 [-]: CALL R6 1 1  ; var6()
L12: 148 [-]: GETUPVAL R8 6; var8 = upvalues[6]
     149 [-]: LENGTH R7 R8 ; var7 = #var8
     150 [-]: FASTCALL2K 19 R7 K16 L13; 
     151 [-]: LOADK R8 K16 ; var8 = 3
     152 [-]: GETIMPORT R6 19; var6 = 0x5BCED4C4[0xAC1B386A]
     153 [-]: CALL R6 3 2  ; var6 = var6(var7, var8)
L13: 154 [-]: GETIMPORT R7 15; var7 = 0x1AC7975A
     155 [-]: JUMPIFNOT R7 L14; goto L14 if not var7
     156 [-]: GETUPVAL R7 6; var7 = upvalues[6]
     157 [-]: LENGTH R6 R7 ; var6 = #var7
L14: 158 [-]: GETIMPORT R7 37; var7 = _T["DynExcavNumRequested"]
     159 [-]: JUMPXEQKN R7 K41 L21 NOT; 
     160 [-]: LOADN R7 0   ; var7 = 0
     161 [-]: JUMPIFNOTLT R7 R2 L21; goto L21 if var7 >= var7407116
     162 [-]: JUMPIFNOTLT R6 R5 L21; goto L21 if var6 >= var2885454
     163 [-]: GETIMPORT R7 44; var7 = 0x33BDD652[0xF21B1D8E]
     164 [-]: GETUPVAL R8 1; var8 = upvalues[1]
     165 [-]: DUPCLOSURE R9 K45; 
     166 [-]: CALL R7 3 1  ; var7(var8, var9)
     167 [-]: LOADN R9 1   ; var9 = 1
     168 [-]: SUB R7 R2 R6 ; var7 = var2 - var6
     169 [-]: LOADN R8 1   ; var8 = 1
     170 [-]: FORNPREP R7 L20; nforprep start - [escape at L20] -- var7 = iterator
L15: 171 [-]: GETUPVAL R11 1; var11 = upvalues[1]
     172 [-]: GETTABLE R10 R11 R9; var10 = var11[var9]
     173 [-]: NAMECALL R11 R10 K46; var12 = var10; var11 = var10[0xBB610E5B]
     174 [-]: CALL R11 2 2 ; var11 = var11(var12)
     175 [-]: NAMECALL R12 R10 K47; var13 = var10; var12 = var10[0xF329A790]
     176 [-]: CALL R12 2 2 ; var12 = var12(var13)
     177 [-]: GETIMPORT R13 2; var13 = 0x89326C93
     178 [-]: GETUPVAL R15 14; var15 = upvalues[14]
     179 [-]: NAMECALL R16 R11 K48; var17 = var11; var16 = var11[0xD1586535]
     180 [-]: CALL R16 2 0 ; var16, ... = var16(var17)
     181 [-]: NAMECALL R13 R13 K49; var14 = var13; var13 = var13[0xC7B81E8D]
     182 [-]: CALL R13 0 2 ; var13 = var13(var14, ...)
     183 [-]: GETIMPORT R14 39; var14 = 0x3D106989
     184 [-]: LOADK R16 K50; var16 = "Removing excavator"
     185 [-]: MOVE R17 R12 ; var17 = var12
     186 [-]: LOADK R18 K51; var18 = "since it was extra"
     187 [-]: CONCAT R15 R16 R18; var15 = var16 .. var18
     188 [-]: CALL R14 2 1 ; var14(var15)
     189 [-]: NAMECALL R14 R13 K52; var15 = var13; var14 = var13[0xA2880940]
     190 [-]: CALL R14 2 1 ; var14(var15)
     191 [-]: NAMECALL R14 R11 K52; var15 = var11; var14 = var11[0xA2880940]
     192 [-]: CALL R14 2 1 ; var14(var15)
     193 [-]: NAMECALL R14 R10 K52; var15 = var10; var14 = var10[0xA2880940]
     194 [-]: CALL R14 2 1 ; var14(var15)
     195 [-]: GETIMPORT R16 54; var16 = _T["DynamicExcavationHudInfo"]
     196 [-]: GETTABLE R15 R16 R12; var15 = var16[var12]
     197 [-]: FASTCALL1 62 R15 L16; 
     198 [-]: GETIMPORT R14 34; var14 = 0x7B998233
     199 [-]: CALL R14 2 2 ; var14 = var14(var15)
L16: 200 [-]: JUMPIF R14 L17; goto L17 if var14
     201 [-]: GETIMPORT R14 56; var14 = _T["RemoveHudTracker"]
     202 [-]: GETIMPORT R17 54; var17 = _T["DynamicExcavationHudInfo"]
     203 [-]: GETTABLE R16 R17 R12; var16 = var17[var12]
     204 [-]: GETTABLEN R15 R16 1; var15 = var16[1]
     205 [-]: CALL R14 2 1 ; var14(var15)
     206 [-]: GETIMPORT R14 56; var14 = _T["RemoveHudTracker"]
     207 [-]: GETIMPORT R17 54; var17 = _T["DynamicExcavationHudInfo"]
     208 [-]: GETTABLE R16 R17 R12; var16 = var17[var12]
     209 [-]: GETTABLEN R15 R16 2; var15 = var16[2]
     210 [-]: CALL R14 2 1 ; var14(var15)
     211 [-]: GETIMPORT R14 54; var14 = _T["DynamicExcavationHudInfo"]
     212 [-]: LOADNIL R15  ; var15 = nil
     213 [-]: SETTABLE R15 R14 R12; var15[var14] = var12
L17: 214 [-]: GETIMPORT R14 58; var14 = 0xCBD666E1
     215 [-]: LOADN R15 0  ; var15 = 0
     216 [-]: CALL R14 2 1 ; var14(var15)
     217 [-]: GETIMPORT R14 2; var14 = 0x89326C93
     218 [-]: GETUPVAL R16 2; var16 = upvalues[2]
     219 [-]: NAMECALL R14 R14 K3; var15 = var14; var14 = var14[0xC7FCADA9]
     220 [-]: CALL R14 3 2 ; var14 = var14(var15, var16)
     221 [-]: SETUPVAL R14 1; upvalues[14] = var1
     222 [-]: GETIMPORT R14 59; var14 = _T
     223 [-]: NEWTABLE R15 0 0; var15 = {}
     224 [-]: SETTABLEKS R15 R14 K60; var15["DynamicExcavatorSpawnPoints"] = var14
     225 [-]: GETIMPORT R14 62; var14 = 0xCFC01047
     226 [-]: GETUPVAL R15 1; var15 = upvalues[1]
     227 [-]: CALL R14 2 4 ; var14, var15, var16 = var14(var15)
     228 [-]: FORGPREP_NEXT R14 L19; 
L18: 229 [-]: GETIMPORT R20 63; var20 = _T["DynamicExcavatorSpawnPoints"]
     230 [-]: NAMECALL R21 R18 K46; var22 = var18; var21 = var18[0xBB610E5B]
     231 [-]: CALL R21 2 2 ; var21 = var21(var22)
     232 [-]: NAMECALL R21 R21 K48; var22 = var21; var21 = var21[0xD1586535]
     233 [-]: CALL R21 2 0 ; var21, ... = var21(var22)
     234 [-]: FASTCALL 52 L19; 
     235 [-]: GETIMPORT R19 65; var19 = 0x33BDD652[0x23D5322F]
     236 [-]: CALL R19 0 1 ; var19(var20, ...)
L19: 237 [-]: FORGLOOP R14 L18 2; 
     238 [-]: FORNLOOP R7 L15; nforloop end - iterate + goto L15
L20: 239 [-]: GETIMPORT R7 22; var7 = 0xBE190284
     240 [-]: GETUPVAL R9 15; var9 = upvalues[15]
     241 [-]: MOVE R10 R6  ; var10 = var6
     242 [-]: NAMECALL R7 R7 K32; var8 = var7; var7 = var7[0x751F061D]
     243 [-]: CALL R7 4 1  ; var7(var8, var9, var10)
L21: 244 [-]: GETUPVAL R7 16; var7 = upvalues[16]
     245 [-]: CALL R7 1 2  ; var7 = var7()
     246 [-]: JUMPIF R7 L24; goto L24 if var7
     247 [-]: GETUPVAL R7 17; var7 = upvalues[17]
     248 [-]: CALL R7 1 2  ; var7 = var7()
     249 [-]: MUL R8 R7 R7 ; var8 = var7 * var7
     250 [-]: SETUPVAL R8 18; upvalues[8] = var18
     251 [-]: GETUPVAL R7 19; var7 = upvalues[19]
     252 [-]: CALL R7 1 1  ; var7()
     253 [-]: GETIMPORT R7 62; var7 = 0xCFC01047
     254 [-]: GETUPVAL R8 1; var8 = upvalues[1]
     255 [-]: CALL R7 2 4  ; var7, var8, var9 = var7(var8)
     256 [-]: FORGPREP_NEXT R7 L23; 
L22: 257 [-]: GETUPVAL R12 20; var12 = upvalues[20]
     258 [-]: MOVE R13 R11 ; var13 = var11
     259 [-]: CALL R12 2 1 ; var12(var13)
L23: 260 [-]: FORGLOOP R7 L22 2; 
L24: 261 [-]: GETIMPORT R7 22; var7 = 0xBE190284
     262 [-]: GETUPVAL R9 13; var9 = upvalues[13]
     263 [-]: LOADN R10 0  ; var10 = 0
     264 [-]: NAMECALL R7 R7 K23; var8 = var7; var7 = var7[0x0EB34C69]
     265 [-]: CALL R7 4 2  ; var7 = var7(var8, var9, var10)
     266 [-]: GETIMPORT R8 15; var8 = 0x1AC7975A
     267 [-]: JUMPIFNOT R8 L25; goto L25 if not var8
     268 [-]: GETUPVAL R9 21; var9 = upvalues[21]
     269 [-]: GETTABLEKS R8 R9 K66; var8 = var9[0xF3928F38]
     270 [-]: MOVE R9 R7   ; var9 = var7
     271 [-]: GETUPVAL R11 6; var11 = upvalues[6]
     272 [-]: LENGTH R10 R11; var10 = #var11
     273 [-]: CALL R8 3 1  ; var8(var9, var10)
     274 [-]: JUMP L27     ; goto L27
L25: 275 [-]: GETUPVAL R9 21; var9 = upvalues[21]
     276 [-]: GETTABLEKS R8 R9 K66; var8 = var9[0xF3928F38]
     277 [-]: MOVE R9 R7   ; var9 = var7
     278 [-]: GETUPVAL R12 6; var12 = upvalues[6]
     279 [-]: LENGTH R11 R12; var11 = #var12
     280 [-]: FASTCALL2K 19 R11 K16 L26; 
     281 [-]: LOADK R12 K16; var12 = 3
     282 [-]: GETIMPORT R10 19; var10 = 0x5BCED4C4[0xAC1B386A]
     283 [-]: CALL R10 3 2 ; var10 = var10(var11, var12)
L26: 284 [-]: CALL R8 3 1  ; var8(var9, var10)
L27: 285 [-]: GETUPVAL R2 22; var2 = upvalues[22]
     286 [-]: GETIMPORT R3 68; var3 = 0xFFF641AF
     287 [-]: CALL R3 1 2  ; var3 = var3()
     288 [-]: ADD R1 R2 R3 ; var1 = var2 + var3
     289 [-]: SETUPVAL R1 22; upvalues[1] = var22
     290 [-]: GETUPVAL R1 23; var1 = upvalues[23]
     291 [-]: GETIMPORT R3 68; var3 = 0xFFF641AF
     292 [-]: CALL R3 1 0  ; var3, ... = var3()
     293 [-]: NAMECALL R1 R1 K69; var2 = var1; var1 = var1[0xFAA69527]
     294 [-]: CALL R1 0 1  ; var1(var2, ...)
     295 [-]: NAMECALL R1 R0 K70; var2 = var0; var1 = var0[0xD9531187]
     296 [-]: CALL R1 2 2  ; var1 = var1(var2)
     297 [-]: JUMPIFNOT R1 L28; goto L28 if not var1
     298 [-]: GETUPVAL R2 24; var2 = upvalues[24]
     299 [-]: GETTABLEKS R1 R2 K71; var1 = var2[0xD712B9DB]
     300 [-]: CALL R1 1 1  ; var1()
     301 [-]: LOADN R3 5   ; var3 = 5
     302 [-]: NAMECALL R1 R0 K72; var2 = var0; var1 = var0[0xFE9DC265]
     303 [-]: CALL R1 3 1  ; var1(var2, var3)
L28: 304 [-]: GETIMPORT R1 58; var1 = 0xCBD666E1
     305 [-]: LOADN R2 0   ; var2 = 0
     306 [-]: CALL R1 2 1  ; var1(var2)
     307 [-]: JUMPBACK L0  ; goto L0
L29: 308 [-]: GETIMPORT R1 2; var1 = 0x89326C93
     309 [-]: NAMECALL R1 R1 K73; var2 = var1; var1 = var1[0x8B5B1F58]
     310 [-]: CALL R1 2 2  ; var1 = var1(var2)
     311 [-]: GETIMPORT R2 75; var2 = 0xC8802016
     312 [-]: MOVE R3 R1   ; var3 = var1
     313 [-]: CALL R2 2 4  ; var2, var3, var4 = var2(var3)
     314 [-]: FORGPREP_INEXT R2 L31; 
L30: 315 [-]: GETUPVAL R9 25; var9 = upvalues[25]
     316 [-]: NAMECALL R7 R6 K76; var8 = var6; var7 = var6[0x0866B4BD]
     317 [-]: CALL R7 3 2  ; var7 = var7(var8, var9)
     318 [-]: JUMPIFNOT R7 L31; goto L31 if not var7
     319 [-]: GETUPVAL R9 25; var9 = upvalues[25]
     320 [-]: NAMECALL R7 R6 K77; var8 = var6; var7 = var6[0x35B09371]
     321 [-]: CALL R7 3 1  ; var7(var8, var9)
L31: 322 [-]: FORGLOOP R2 L30 2 [inext]; 
     323 [-]: GETIMPORT R2 2; var2 = 0x89326C93
     324 [-]: GETUPVAL R4 2; var4 = upvalues[2]
     325 [-]: NAMECALL R2 R2 K3; var3 = var2; var2 = var2[0xC7FCADA9]
     326 [-]: CALL R2 3 2  ; var2 = var2(var3, var4)
     327 [-]: GETIMPORT R3 39; var3 = 0x3D106989
     328 [-]: LOADK R5 K78 ; var5 = "Found "
     329 [-]: LENGTH R6 R2 ; var6 = #var2
     330 [-]: LOADK R7 K79 ; var7 = " states"
     331 [-]: CONCAT R4 R5 R7; var4 = var5 .. var7
     332 [-]: CALL R3 2 1  ; var3(var4)
     333 [-]: GETIMPORT R3 62; var3 = 0xCFC01047
     334 [-]: MOVE R4 R2   ; var4 = var2
     335 [-]: CALL R3 2 4  ; var3, var4, var5 = var3(var4)
     336 [-]: FORGPREP_NEXT R3 L39; 
L32: 337 [-]: NAMECALL R8 R7 K47; var9 = var7; var8 = var7[0xF329A790]
     338 [-]: CALL R8 2 2  ; var8 = var8(var9)
     339 [-]: JUMPXEQKN R8 K41 L33; 
     340 [-]: GETUPVAL R10 26; var10 = upvalues[26]
     341 [-]: LENGTH R9 R10; var9 = #var10
     342 [-]: JUMPIFNOTLT R9 R8 L34; goto L34 if var9 >= var2558286
L33: 343 [-]: GETIMPORT R9 39; var9 = 0x3D106989
     344 [-]: LOADK R11 K80; var11 = "Invalid marker index for "
     345 [-]: GETIMPORT R15 82; var15 = 0x64FB1586
     346 [-]: NAMECALL R16 R7 K83; var17 = var7; var16 = var7[0xED4E0128]
     347 [-]: CALL R16 2 0 ; var16, ... = var16(var17)
     348 [-]: CALL R15 0 2 ; var15 = var15(var16, ...)
     349 [-]: MOVE R12 R15 ; var12 = var15
     350 [-]: LOADK R13 K84; var13 = ", index="
     351 [-]: GETIMPORT R14 82; var14 = 0x64FB1586
     352 [-]: MOVE R15 R8  ; var15 = var8
     353 [-]: CALL R14 2 2 ; var14 = var14(var15)
     354 [-]: CONCAT R10 R11 R14; var10 = var11 .. var14
     355 [-]: CALL R9 2 1  ; var9(var10)
L34: 356 [-]: GETIMPORT R9 2; var9 = 0x89326C93
     357 [-]: GETUPVAL R12 26; var12 = upvalues[26]
     358 [-]: GETTABLE R11 R12 R8; var11 = var12[var8]
     359 [-]: NAMECALL R12 R0 K48; var13 = var0; var12 = var0[0xD1586535]
     360 [-]: CALL R12 2 2 ; var12 = var12(var13)
     361 [-]: GETUPVAL R13 27; var13 = upvalues[27]
     362 [-]: NAMECALL R9 R9 K85; var10 = var9; var9 = var9[0x4E5939A5]
     363 [-]: CALL R9 5 2  ; var9 = var9(var10, var11, var12, var13)
     364 [-]: FASTCALL1 62 R9 L35; 
     365 [-]: MOVE R11 R9  ; var11 = var9
     366 [-]: GETIMPORT R10 34; var10 = 0x7B998233
     367 [-]: CALL R10 2 2 ; var10 = var10(var11)
L35: 368 [-]: JUMPIF R10 L36; goto L36 if var10
     369 [-]: NAMECALL R10 R9 K52; var11 = var9; var10 = var9[0xA2880940]
     370 [-]: CALL R10 2 1 ; var10(var11)
L36: 371 [-]: GETIMPORT R12 54; var12 = _T["DynamicExcavationHudInfo"]
     372 [-]: GETTABLE R11 R12 R8; var11 = var12[var8]
     373 [-]: FASTCALL1 62 R11 L37; 
     374 [-]: GETIMPORT R10 34; var10 = 0x7B998233
     375 [-]: CALL R10 2 2 ; var10 = var10(var11)
L37: 376 [-]: JUMPIF R10 L38; goto L38 if var10
     377 [-]: GETIMPORT R10 56; var10 = _T["RemoveHudTracker"]
     378 [-]: GETIMPORT R13 54; var13 = _T["DynamicExcavationHudInfo"]
     379 [-]: GETTABLE R12 R13 R8; var12 = var13[var8]
     380 [-]: GETTABLEN R11 R12 1; var11 = var12[1]
     381 [-]: CALL R10 2 1 ; var10(var11)
     382 [-]: GETIMPORT R10 56; var10 = _T["RemoveHudTracker"]
     383 [-]: GETIMPORT R13 54; var13 = _T["DynamicExcavationHudInfo"]
     384 [-]: GETTABLE R12 R13 R8; var12 = var13[var8]
     385 [-]: GETTABLEN R11 R12 2; var11 = var12[2]
     386 [-]: CALL R10 2 1 ; var10(var11)
     387 [-]: GETIMPORT R10 54; var10 = _T["DynamicExcavationHudInfo"]
     388 [-]: LOADNIL R11  ; var11 = nil
     389 [-]: SETTABLE R11 R10 R8; var11[var10] = var8
L38: 390 [-]: GETUPVAL R10 28; var10 = upvalues[28]
     391 [-]: MOVE R11 R7  ; var11 = var7
     392 [-]: CALL R10 2 1 ; var10(var11)
L39: 393 [-]: FORGLOOP R3 L32 2; 
     394 [-]: GETIMPORT R3 2; var3 = 0x89326C93
     395 [-]: GETUPVAL R5 29; var5 = upvalues[29]
     396 [-]: NAMECALL R6 R0 K48; var7 = var0; var6 = var0[0xD1586535]
     397 [-]: CALL R6 2 2  ; var6 = var6(var7)
     398 [-]: LOADN R7 0   ; var7 = 0
     399 [-]: GETUPVAL R8 30; var8 = upvalues[30]
     400 [-]: NAMECALL R3 R3 K86; var4 = var3; var3 = var3[0xF16592C8]
     401 [-]: CALL R3 6 2  ; var3 = var3(var4, var5, var6, var7, var8)
     402 [-]: GETIMPORT R4 75; var4 = 0xC8802016
     403 [-]: MOVE R5 R3   ; var5 = var3
     404 [-]: CALL R4 2 4  ; var4, var5, var6 = var4(var5)
     405 [-]: FORGPREP_INEXT R4 L42; 
L40: 406 [-]: FASTCALL1 62 R8 L41; 
     407 [-]: MOVE R10 R8  ; var10 = var8
     408 [-]: GETIMPORT R9 34; var9 = 0x7B998233
     409 [-]: CALL R9 2 2  ; var9 = var9(var10)
L41: 410 [-]: JUMPIF R9 L42; goto L42 if var9
     411 [-]: NAMECALL R9 R8 K52; var10 = var8; var9 = var8[0xA2880940]
     412 [-]: CALL R9 2 1  ; var9(var10)
L42: 413 [-]: FORGLOOP R4 L40 2 [inext]; 
     414 [-]: GETIMPORT R4 2; var4 = 0x89326C93
     415 [-]: GETUPVAL R6 31; var6 = upvalues[31]
     416 [-]: NAMECALL R4 R4 K87; var5 = var4; var4 = var4[0xFB669000]
     417 [-]: CALL R4 3 2  ; var4 = var4(var5, var6)
     418 [-]: GETIMPORT R5 62; var5 = 0xCFC01047
     419 [-]: MOVE R6 R4   ; var6 = var4
     420 [-]: CALL R5 2 4  ; var5, var6, var7 = var5(var6)
     421 [-]: FORGPREP_NEXT R5 L44; 
L43: 422 [-]: NAMECALL R10 R9 K88; var11 = var9; var10 = var9[0x785853D5]
     423 [-]: CALL R10 2 1 ; var10(var11)
L44: 424 [-]: FORGLOOP R5 L43 2; 
     425 [-]: GETIMPORT R5 2; var5 = 0x89326C93
     426 [-]: GETUPVAL R7 32; var7 = upvalues[32]
     427 [-]: GETUPVAL R8 33; var8 = upvalues[33]
     428 [-]: LOADN R9 0   ; var9 = 0
     429 [-]: GETUPVAL R10 30; var10 = upvalues[30]
     430 [-]: NAMECALL R5 R5 K87; var6 = var5; var5 = var5[0xFB669000]
     431 [-]: CALL R5 6 2  ; var5 = var5(var6, var7, var8, var9, var10)
     432 [-]: GETIMPORT R6 75; var6 = 0xC8802016
     433 [-]: MOVE R7 R5   ; var7 = var5
     434 [-]: CALL R6 2 4  ; var6, var7, var8 = var6(var7)
     435 [-]: FORGPREP_INEXT R6 L46; 
L45: 436 [-]: NAMECALL R11 R10 K52; var12 = var10; var11 = var10[0xA2880940]
     437 [-]: CALL R11 2 1 ; var11(var12)
L46: 438 [-]: FORGLOOP R6 L45 2 [inext]; 
     439 [-]: GETIMPORT R6 2; var6 = 0x89326C93
     440 [-]: GETUPVAL R8 34; var8 = upvalues[34]
     441 [-]: GETUPVAL R9 33; var9 = upvalues[33]
     442 [-]: LOADN R10 0  ; var10 = 0
     443 [-]: GETUPVAL R11 30; var11 = upvalues[30]
     444 [-]: NAMECALL R6 R6 K87; var7 = var6; var6 = var6[0xFB669000]
     445 [-]: CALL R6 6 2  ; var6 = var6(var7, var8, var9, var10, var11)
     446 [-]: GETIMPORT R7 75; var7 = 0xC8802016
     447 [-]: MOVE R8 R6   ; var8 = var6
     448 [-]: CALL R7 2 4  ; var7, var8, var9 = var7(var8)
     449 [-]: FORGPREP_INEXT R7 L48; 
L47: 450 [-]: NAMECALL R12 R11 K52; var13 = var11; var12 = var11[0xA2880940]
     451 [-]: CALL R12 2 1 ; var12(var13)
L48: 452 [-]: FORGLOOP R7 L47 2 [inext]; 
     453 [-]: GETIMPORT R7 59; var7 = _T
     454 [-]: LOADNIL R8   ; var8 = nil
     455 [-]: SETTABLEKS R8 R7 K53; var8["DynamicExcavationHudInfo"] = var7
     456 [-]: GETIMPORT R7 59; var7 = _T
     457 [-]: LOADNIL R8   ; var8 = nil
     458 [-]: SETTABLEKS R8 R7 K60; var8["DynamicExcavatorSpawnPoints"] = var7
     459 [-]: GETIMPORT R7 59; var7 = _T
     460 [-]: LOADNIL R8   ; var8 = nil
     461 [-]: SETTABLEKS R8 R7 K89; var8["TransmissionSet"] = var7
     462 [-]: GETIMPORT R7 59; var7 = _T
     463 [-]: LOADNIL R8   ; var8 = nil
     464 [-]: SETTABLEKS R8 R7 K36; var8["DynExcavNumRequested"] = var7
     465 [-]: GETIMPORT R7 59; var7 = _T
     466 [-]: LOADN R8 0   ; var8 = 0
     467 [-]: SETTABLEKS R8 R7 K90; var8["DynExcavNumExpectedEnemy"] = var7
     468 [-]: GETIMPORT R7 59; var7 = _T
     469 [-]: LOADNIL R8   ; var8 = nil
     470 [-]: SETTABLEKS R8 R7 K91; var8["DynamicOverrideAgent"] = var7
     471 [-]: GETIMPORT R7 59; var7 = _T
     472 [-]: LOADN R8 0   ; var8 = 0
     473 [-]: SETTABLEKS R8 R7 K92; var8["DynamicOverrideAgentCount"] = var7
     474 [-]: GETUPVAL R8 24; var8 = upvalues[24]
     475 [-]: GETTABLEKS R7 R8 K93; var7 = var8[0xE69049EB]
     476 [-]: GETUPVAL R8 35; var8 = upvalues[35]
     477 [-]: CALL R7 2 1  ; var7(var8)
     478 [-]: GETUPVAL R7 35; var7 = upvalues[35]
     479 [-]: GETIMPORT R9 8; var9 = 0x0469F296
     480 [-]: LOADK R10 K94; var10 = "OnAgentRegistered"
     481 [-]: CALL R9 2 0  ; var9, ... = var9(var10)
     482 [-]: NAMECALL R7 R7 K95; var8 = var7; var7 = var7[0x11D6DE31]
     483 [-]: CALL R7 0 1  ; var7(var8, ...)
     484 [-]: GETUPVAL R7 36; var7 = upvalues[36]
     485 [-]: GETUPVAL R9 37; var9 = upvalues[37]
     486 [-]: NAMECALL R7 R7 K96; var8 = var7; var7 = var7[0x3D412E0D]
     487 [-]: CALL R7 3 1  ; var7(var8, var9)
     488 [-]: GETUPVAL R7 36; var7 = upvalues[36]
     489 [-]: GETUPVAL R9 38; var9 = upvalues[38]
     490 [-]: NAMECALL R7 R7 K97; var8 = var7; var7 = var7[0x136A027D]
     491 [-]: CALL R7 3 1  ; var7(var8, var9)
     492 [-]: GETIMPORT R7 22; var7 = 0xBE190284
     493 [-]: GETUPVAL R9 39; var9 = upvalues[39]
     494 [-]: NAMECALL R7 R7 K98; var8 = var7; var7 = var7[0xB9BFD47C]
     495 [-]: CALL R7 3 1  ; var7(var8, var9)
     496 [-]: GETIMPORT R7 22; var7 = 0xBE190284
     497 [-]: GETUPVAL R9 13; var9 = upvalues[13]
     498 [-]: NAMECALL R7 R7 K98; var8 = var7; var7 = var7[0xB9BFD47C]
     499 [-]: CALL R7 3 1  ; var7(var8, var9)
     500 [-]: GETIMPORT R7 22; var7 = 0xBE190284
     501 [-]: GETUPVAL R9 12; var9 = upvalues[12]
     502 [-]: NAMECALL R7 R7 K98; var8 = var7; var7 = var7[0xB9BFD47C]
     503 [-]: CALL R7 3 1  ; var7(var8, var9)
     504 [-]: GETIMPORT R7 22; var7 = 0xBE190284
     505 [-]: GETUPVAL R9 15; var9 = upvalues[15]
     506 [-]: NAMECALL R7 R7 K98; var8 = var7; var7 = var7[0xB9BFD47C]
     507 [-]: CALL R7 3 1  ; var7(var8, var9)
     508 [-]: GETIMPORT R7 22; var7 = 0xBE190284
     509 [-]: GETUPVAL R9 39; var9 = upvalues[39]
     510 [-]: NAMECALL R7 R7 K98; var8 = var7; var7 = var7[0xB9BFD47C]
     511 [-]: CALL R7 3 1  ; var7(var8, var9)
     512 [-]: GETIMPORT R7 22; var7 = 0xBE190284
     513 [-]: GETUPVAL R9 9; var9 = upvalues[9]
     514 [-]: NAMECALL R7 R7 K98; var8 = var7; var7 = var7[0xB9BFD47C]
     515 [-]: CALL R7 3 1  ; var7(var8, var9)
     516 [-]: GETIMPORT R7 58; var7 = 0xCBD666E1
     517 [-]: LOADN R8 2   ; var8 = 2
     518 [-]: CALL R7 2 1  ; var7(var8)
     519 [-]: GETUPVAL R8 21; var8 = upvalues[21]
     520 [-]: GETTABLEKS R7 R8 K99; var7 = var8[0xDC3B2033]
     521 [-]: CALL R7 1 1  ; var7()
     522 [-]: GETUPVAL R8 21; var8 = upvalues[21]
     523 [-]: GETTABLEKS R7 R8 K100; var7 = var8[0xBD3CE95D]
     524 [-]: CALL R7 1 1  ; var7()
     525 [-]: GETUPVAL R8 21; var8 = upvalues[21]
     526 [-]: GETTABLEKS R7 R8 K101; var7 = var8[0xF7EBDDC8]
     527 [-]: CALL R7 1 1  ; var7()
     528 [-]: RETURN R0 0  ; 


; Name:            
; Defined at line: 1168
; #Upvalues:       0
; #Parameters:     1
; Is_vararg:       0
; Max Stack Size:  1

       0 [-]: RETURN R0 0  ; 


; Name:            
; Defined at line: 1171
; #Upvalues:       2
; #Parameters:     1
; Is_vararg:       0
; Max Stack Size:  7

       0 [-]: GETIMPORT R1 1; var1 = 0x11A19C5E
       1 [-]: NAMECALL R2 R0 K2; var3 = var0; var2 = var0[0xBB610E5B]
       2 [-]: CALL R2 2 2  ; var2 = var2(var3)
       3 [-]: LOADK R3 K3  ; var3 = "OnKilled"
       4 [-]: CALL R1 3 1  ; var1(var2, var3)
       5 [-]: NAMECALL R1 R0 K2; var2 = var0; var1 = var0[0xBB610E5B]
       6 [-]: CALL R1 2 2  ; var1 = var1(var2)
       7 [-]: FASTCALL1 62 R1 L0; 
       8 [-]: MOVE R3 R1   ; var3 = var1
       9 [-]: GETIMPORT R2 5; var2 = 0x7B998233
      10 [-]: CALL R2 2 2  ; var2 = var2(var3)
L 0:  11 [-]: JUMPIF R2 L4 ; goto L4 if var2
      12 [-]: GETIMPORT R4 7; var4 = gDropshipAvatarType
      13 [-]: NAMECALL R2 R1 K8; var3 = var1; var2 = var1[0xF2DEAF69]
      14 [-]: CALL R2 3 2  ; var2 = var2(var3, var4)
      15 [-]: JUMPIF R2 L4 ; goto L4 if var2
      16 [-]: GETIMPORT R4 10; var4 = gLotusVehicleAvatarType
      17 [-]: NAMECALL R2 R1 K8; var3 = var1; var2 = var1[0xF2DEAF69]
      18 [-]: CALL R2 3 2  ; var2 = var2(var3, var4)
      19 [-]: JUMPIF R2 L4 ; goto L4 if var2
      20 [-]: GETUPVAL R4 0; var4 = upvalues[0]
      21 [-]: NAMECALL R2 R1 K8; var3 = var1; var2 = var1[0xF2DEAF69]
      22 [-]: CALL R2 3 2  ; var2 = var2(var3, var4)
      23 [-]: JUMPIFNOT R2 L1; goto L1 if not var2
      24 [-]: GETIMPORT R2 12; var2 = 0xD644C2F1
      25 [-]: LOADK R3 K13 ; var3 = "Cell carrier created"
      26 [-]: CALL R2 2 1  ; var2(var3)
      27 [-]: GETIMPORT R2 15; var2 = 0x3D106989
      28 [-]: LOADK R3 K13 ; var3 = "Cell carrier created"
      29 [-]: CALL R2 2 1  ; var2(var3)
L 1:  30 [-]: GETIMPORT R2 17; var2 = 0x89326C93
      31 [-]: GETUPVAL R4 1; var4 = upvalues[1]
      32 [-]: NAMECALL R5 R1 K18; var6 = var1; var5 = var1[0xD1586535]
      33 [-]: CALL R5 2 0  ; var5, ... = var5(var6)
      34 [-]: NAMECALL R2 R2 K19; var3 = var2; var2 = var2[0xC7B81E8D]
      35 [-]: CALL R2 0 2  ; var2 = var2(var3, ...)
      36 [-]: FASTCALL1 62 R2 L2; 
      37 [-]: MOVE R4 R2   ; var4 = var2
      38 [-]: GETIMPORT R3 5; var3 = 0x7B998233
      39 [-]: CALL R3 2 2  ; var3 = var3(var4)
L 2:  40 [-]: JUMPIF R3 L3 ; goto L3 if var3
      41 [-]: MOVE R5 R2   ; var5 = var2
      42 [-]: NAMECALL R3 R0 K20; var4 = var0; var3 = var0[0xA64A1F4A]
      43 [-]: CALL R3 3 1  ; var3(var4, var5)
L 3:  44 [-]: GETIMPORT R3 22; var3 = _T
      45 [-]: GETIMPORT R5 25; var5 = _T["DynExcavNumExpectedEnemy"]
      46 [-]: SUBK R4 R5 K23; var4 = var5 - 1
      47 [-]: SETTABLEKS R4 R3 K24; var4["DynExcavNumExpectedEnemy"] = var3
L 4:  48 [-]: RETURN R0 0  ; 


; Name:            
; Defined at line: 1189
; #Upvalues:       0
; #Parameters:     1
; Is_vararg:       0
; Max Stack Size:  6

       0 [-]: NAMECALL R4 R0 K0; var5 = var0; var4 = var0[0xE223E2B1]
       1 [-]: CALL R4 2 2  ; var4 = var4(var5)
       2 [-]: MOVE R2 R4   ; var2 = var4
       3 [-]: LOADK R3 K1  ; var3 = " deployed"
       4 [-]: CONCAT R1 R2 R3; var1 = var2 .. var3
       5 [-]: GETIMPORT R2 3; var2 = 0xD644C2F1
       6 [-]: MOVE R3 R1   ; var3 = var1
       7 [-]: CALL R2 2 1  ; var2(var3)
       8 [-]: GETIMPORT R2 5; var2 = 0x3D106989
       9 [-]: MOVE R3 R1   ; var3 = var1
      10 [-]: CALL R2 2 1  ; var2(var3)
      11 [-]: RETURN R0 0  ; 


; Name:            
; Defined at line: 1193
; #Upvalues:       2
; #Parameters:     1
; Is_vararg:       0
; Max Stack Size:  10

       0 [-]: GETIMPORT R1 1; var1 = 0x89326C93
       1 [-]: GETUPVAL R3 0; var3 = upvalues[0]
       2 [-]: NAMECALL R1 R1 K2; var2 = var1; var1 = var1[0xC7FCADA9]
       3 [-]: CALL R1 3 2  ; var1 = var1(var2, var3)
       4 [-]: GETIMPORT R2 4; var2 = 0xCFC01047
       5 [-]: MOVE R3 R1   ; var3 = var1
       6 [-]: CALL R2 2 4  ; var2, var3, var4 = var2(var3)
       7 [-]: FORGPREP_NEXT R2 L2; 
L 0:   8 [-]: FASTCALL1 62 R6 L1; 
       9 [-]: MOVE R8 R6   ; var8 = var6
      10 [-]: GETIMPORT R7 6; var7 = 0x7B998233
      11 [-]: CALL R7 2 2  ; var7 = var7(var8)
L 1:  12 [-]: JUMPIF R7 L2 ; goto L2 if var7
      13 [-]: NAMECALL R7 R6 K7; var8 = var6; var7 = var6[0xBB610E5B]
      14 [-]: CALL R7 2 2  ; var7 = var7(var8)
      15 [-]: JUMPIFNOTEQ R7 R0 L2; goto L2 if var7 ~= var67591
      16 [-]: GETUPVAL R8 1; var8 = upvalues[1]
      17 [-]: MOVE R9 R6   ; var9 = var6
      18 [-]: CALL R8 2 1  ; var8(var9)
      19 [-]: NAMECALL R8 R7 K8; var9 = var7; var8 = var7[0xA2880940]
      20 [-]: CALL R8 2 1  ; var8(var9)
      21 [-]: RETURN R0 0  ; 
L 2:  22 [-]: FORGLOOP R2 L0 2; 
      23 [-]: RETURN R0 0  ; 


; Name:            
; Defined at line: 1207
; #Upvalues:       4
; #Parameters:     0
; Is_vararg:       0
; Max Stack Size:  12

       0 [-]: GETIMPORT R0 1; var0 = 0x89326C93
       1 [-]: NAMECALL R0 R0 K2; var1 = var0; var0 = var0[0x7D108DDB]
       2 [-]: CALL R0 2 2  ; var0 = var0(var1)
       3 [-]: SETUPVAL R0 0; upvalues[0] = var0
       4 [-]: GETUPVAL R1 0; var1 = upvalues[0]
       5 [-]: LENGTH R0 R1 ; var0 = #var1
       6 [-]: LOADN R1 0   ; var1 = 0
       7 [-]: JUMPIFNOTLE R0 R1 L0; goto L0 if var0 > var65581
       8 [-]: RETURN R0 0  ; 
L 0:   9 [-]: GETIMPORT R0 1; var0 = 0x89326C93
      10 [-]: GETUPVAL R2 1; var2 = upvalues[1]
      11 [-]: NAMECALL R0 R0 K3; var1 = var0; var0 = var0[0xC7FCADA9]
      12 [-]: CALL R0 3 2  ; var0 = var0(var1, var2)
      13 [-]: GETIMPORT R1 5; var1 = 0xBE190284
      14 [-]: GETUPVAL R3 2; var3 = upvalues[2]
      15 [-]: LOADN R4 0   ; var4 = 0
      16 [-]: NAMECALL R1 R1 K6; var2 = var1; var1 = var1[0x0EB34C69]
      17 [-]: CALL R1 4 2  ; var1 = var1(var2, var3, var4)
      18 [-]: GETIMPORT R2 5; var2 = 0xBE190284
      19 [-]: GETUPVAL R4 3; var4 = upvalues[3]
      20 [-]: LOADN R5 0   ; var5 = 0
      21 [-]: NAMECALL R2 R2 K6; var3 = var2; var2 = var2[0x0EB34C69]
      22 [-]: CALL R2 4 2  ; var2 = var2(var3, var4, var5)
      23 [-]: GETUPVAL R5 0; var5 = upvalues[0]
      24 [-]: LENGTH R4 R5 ; var4 = #var5
      25 [-]: FASTCALL2K 19 R4 K7 L1; 
      26 [-]: LOADK R5 K7  ; var5 = 3
      27 [-]: GETIMPORT R3 10; var3 = 0x5BCED4C4[0xAC1B386A]
      28 [-]: CALL R3 3 2  ; var3 = var3(var4, var5)
L 1:  29 [-]: LENGTH R6 R0 ; var6 = #var0
      30 [-]: ADD R5 R6 R1 ; var5 = var6 + var1
      31 [-]: ADD R4 R5 R2 ; var4 = var5 + var2
      32 [-]: JUMPIFNOTLT R3 R4 L6; goto L6 if var3 >= var787278
      33 [-]: GETIMPORT R3 12; var3 = 0x3D106989
      34 [-]: LOADK R4 K13 ; var4 = "A player left while potentially one of the excavators was falling and we no longer need it"
      35 [-]: CALL R3 2 1  ; var3(var4)
      36 [-]: LENGTH R5 R0 ; var5 = #var0
      37 [-]: LOADN R3 1   ; var3 = 1
      38 [-]: LOADN R4 -1  ; var4 = -1
      39 [-]: FORNPREP R3 L4; nforprep start - [escape at L4] -- var3 = iterator
L 2:  40 [-]: GETTABLE R6 R0 R5; var6 = var0[var5]
      41 [-]: NAMECALL R7 R6 K14; var8 = var6; var7 = var6[0xF329A790]
      42 [-]: CALL R7 2 2  ; var7 = var7(var8)
      43 [-]: JUMPXEQKN R7 K15 L3 NOT; 
      44 [-]: GETIMPORT R7 12; var7 = 0x3D106989
      45 [-]: LOADK R9 K16 ; var9 = "Marking for destroy "
      46 [-]: NAMECALL R10 R6 K17; var11 = var6; var10 = var6[0xED4E0128]
      47 [-]: CALL R10 2 2 ; var10 = var10(var11)
      48 [-]: CONCAT R8 R9 R10; var8 = var9 .. var10
      49 [-]: CALL R7 2 1  ; var7(var8)
      50 [-]: LOADN R9 -1  ; var9 = -1
      51 [-]: NAMECALL R7 R6 K18; var8 = var6; var7 = var6[0xD95ACD2C]
      52 [-]: CALL R7 3 1  ; var7(var8, var9)
      53 [-]: GETIMPORT R7 21; var7 = 0x33BDD652[0x9C1F3B5A]
      54 [-]: MOVE R8 R0   ; var8 = var0
      55 [-]: MOVE R9 R5   ; var9 = var5
      56 [-]: CALL R7 3 1  ; var7(var8, var9)
L 3:  57 [-]: FORNLOOP R3 L2; nforloop end - iterate + goto L2
L 4:  58 [-]: GETUPVAL R5 0; var5 = upvalues[0]
      59 [-]: LENGTH R4 R5 ; var4 = #var5
      60 [-]: FASTCALL2K 19 R4 K7 L5; 
      61 [-]: LOADK R5 K7  ; var5 = 3
      62 [-]: GETIMPORT R3 10; var3 = 0x5BCED4C4[0xAC1B386A]
      63 [-]: CALL R3 3 2  ; var3 = var3(var4, var5)
L 5:  64 [-]: LENGTH R6 R0 ; var6 = #var0
      65 [-]: ADD R5 R6 R1 ; var5 = var6 + var1
      66 [-]: ADD R4 R5 R2 ; var4 = var5 + var2
      67 [-]: JUMPIFNOTLT R3 R4 L6; goto L6 if var3 >= var787278
      68 [-]: GETIMPORT R3 12; var3 = 0x3D106989
      69 [-]: LOADK R4 K22 ; var4 = "After removing uninitialized states, we still have too many of them!"
      70 [-]: CALL R3 2 1  ; var3(var4)
L 6:  71 [-]: RETURN R0 0  ; 


; Name:            
; Defined at line: 1233
; #Upvalues:       2
; #Parameters:     0
; Is_vararg:       0
; Max Stack Size:  3

       0 [-]: GETUPVAL R1 0; var1 = upvalues[0]
       1 [-]: GETTABLEKS R0 R1 K0; var0 = var1[0x7E8A976A]
       2 [-]: GETUPVAL R1 1; var1 = upvalues[1]
       3 [-]: LOADB R2 1   ; var2 = true
       4 [-]: CALL R0 3 1  ; var0(var1, var2)
       5 [-]: RETURN R0 0  ; 


; Name:            
; Defined at line: 1237
; #Upvalues:       2
; #Parameters:     0
; Is_vararg:       0
; Max Stack Size:  3

       0 [-]: GETUPVAL R1 0; var1 = upvalues[0]
       1 [-]: GETTABLEKS R0 R1 K0; var0 = var1[0x7E8A976A]
       2 [-]: GETUPVAL R1 1; var1 = upvalues[1]
       3 [-]: LOADB R2 0   ; var2 = false
       4 [-]: CALL R0 3 1  ; var0(var1, var2)
       5 [-]: RETURN R0 0  ; 



