; Name:            
; Defined at line: 1
; #Upvalues:       0
; #Parameters:     0
; Is_vararg:       1
; Max Stack Size:  66

       1 [-]: NEWTABLE R0 0 4
       2 [-]: LOADN R1 1   
       3 [-]: LOADN R2 2   
       4 [-]: LOADN R3 3   
       5 [-]: LOADN R4 4   
       6 [-]: SETLIST R0 R1 4 [1]
       7 [-]: NEWTABLE R1 0 4
       8 [-]: LOADN R2 10  
       9 [-]: LOADN R3 13  
      10 [-]: LOADN R4 18  
      11 [-]: LOADN R5 23  
      12 [-]: SETLIST R1 R2 4 [1]
      13 [-]: NEWTABLE R2 0 4
      14 [-]: LOADN R3 5   
      15 [-]: LOADN R4 13  
      16 [-]: LOADN R5 16  
      17 [-]: LOADN R6 18  
      18 [-]: SETLIST R2 R3 4 [1]
      19 [-]: NEWTABLE R3 0 4
      20 [-]: LOADN R4 12  
      21 [-]: LOADN R5 15  
      22 [-]: LOADN R6 17  
      23 [-]: LOADN R7 20  
      24 [-]: SETLIST R3 R4 4 [1]
      25 [-]: GETIMPORT R4 1 [0xA421AF95]
      26 [-]: LOADN R5 0   
      27 [-]: LOADK R6 K2 [-0.10000000000000001]
      28 [-]: LOADN R7 0   
      29 [-]: CALL R4 3 1  
      30 [-]: GETIMPORT R5 4 [0x2D0FAD09]
      31 [-]: LOADK R6 K5 ["EE.Interface.Utilities"]
      32 [-]: CALL R5 1 1  
      33 [-]: GETIMPORT R6 4 [0x2D0FAD09]
      34 [-]: LOADK R7 K6 ["Lotus.Scripts.Libs.LandscapeLib"]
      35 [-]: CALL R6 1 1  
      36 [-]: GETIMPORT R7 4 [0x2D0FAD09]
      37 [-]: LOADK R8 K7 ["Lotus.Scripts.Libs.TransmissionSet"]
      38 [-]: CALL R7 1 1  
      39 [-]: GETIMPORT R8 4 [0x2D0FAD09]
      40 [-]: LOADK R9 K8 ["Lotus.Interface.Libs.TimerMgr"]
      41 [-]: CALL R8 1 1  
      42 [-]: GETIMPORT R9 4 [0x2D0FAD09]
      43 [-]: LOADK R10 K9 ["Lotus.Scripts.Libs.ObjectiveText"]
      44 [-]: CALL R9 1 1  
      45 [-]: GETIMPORT R10 11 [0x7ED0A956]
      46 [-]: LOADK R11 K12 ["/EE/Types/Engine/Terrain"]
      47 [-]: CALL R10 1 1 
      48 [-]: GETIMPORT R11 11 [0x7ED0A956]
      49 [-]: LOADK R12 K13 ["/EE/Types/Effects/Landscape"]
      50 [-]: CALL R11 1 1 
      51 [-]: GETIMPORT R12 15 [0x0469F296]
      52 [-]: LOADK R13 K16 ["DynamicAmbushBeginHackContextAction"]
      53 [-]: CALL R12 1 1 
      54 [-]: GETIMPORT R13 15 [0x0469F296]
      55 [-]: LOADK R14 K17 ["DynamicAmbushConsoleDeco"]
      56 [-]: CALL R13 1 1 
      57 [-]: GETIMPORT R14 15 [0x0469F296]
      58 [-]: LOADK R15 K18 ["DynamicAmbushTrapDeco"]
      59 [-]: CALL R14 1 1 
      60 [-]: GETIMPORT R15 15 [0x0469F296]
      61 [-]: LOADK R16 K19 ["DynamicAmbushWaypoint"]
      62 [-]: CALL R15 1 1 
      63 [-]: GETIMPORT R16 15 [0x0469F296]
      64 [-]: LOADK R17 K20 ["LoboWheelCarDropshipAvatar"]
      65 [-]: CALL R16 1 1 
      66 [-]: GETIMPORT R17 15 [0x0469F296]
      67 [-]: LOADK R18 K21 ["VenusObjectiveMarkerInfo"]
      68 [-]: CALL R17 1 1 
      69 [-]: GETIMPORT R18 15 [0x0469F296]
      70 [-]: LOADK R19 K22 ["TrapInvincible"]
      71 [-]: CALL R18 1 1 
      72 [-]: GETIMPORT R19 15 [0x0469F296]
      73 [-]: LOADK R20 K23 ["RandomTeam"]
      74 [-]: CALL R19 1 1 
      75 [-]: GETIMPORT R20 15 [0x0469F296]
      76 [-]: LOADK R21 K24 ["DYNAMIC_AMBUSH_TRAP_ACTIVATED"]
      77 [-]: CALL R20 1 1 
      78 [-]: GETIMPORT R21 15 [0x0469F296]
      79 [-]: LOADK R22 K25 ["DYNAMIC_AMBUSH_TIME_ELAPSED"]
      80 [-]: CALL R21 1 1 
      81 [-]: GETIMPORT R22 15 [0x0469F296]
      82 [-]: LOADK R23 K26 ["DynamicAmbushTimer"]
      83 [-]: CALL R22 1 1 
      84 [-]: GETIMPORT R23 15 [0x0469F296]
      85 [-]: LOADK R24 K27 ["OpenDoor"]
      86 [-]: CALL R23 1 1 
      87 [-]: GETIMPORT R24 15 [0x0469F296]
      88 [-]: LOADK R25 K28 ["DynamicAmbushCoilDriveTrapped"]
      89 [-]: CALL R24 1 1 
      90 [-]: GETIMPORT R25 15 [0x0469F296]
      91 [-]: LOADK R26 K29 ["TENNO"]
      92 [-]: CALL R25 1 1 
      93 [-]: GETIMPORT R26 15 [0x0469F296]
      94 [-]: LOADK R27 K30 ["LeavingCB"]
      95 [-]: CALL R26 1 1 
      96 [-]: GETIMPORT R27 15 [0x0469F296]
      97 [-]: LOADK R28 K31 ["ReturningCB"]
      98 [-]: CALL R27 1 1 
      99 [-]: GETIMPORT R28 1 [0xA421AF95]
     100 [-]: CALL R28 0 1 
     101 [-]: LOADNIL R29  
     102 [-]: LOADNIL R30  
     103 [-]: LOADNIL R31  
     104 [-]: LOADNIL R32  
     105 [-]: LOADNIL R33  
     106 [-]: LOADNIL R34  
     107 [-]: LOADNIL R35  
     108 [-]: LOADNIL R36  
     109 [-]: LOADN R37 0  
     110 [-]: LOADN R38 0  
     111 [-]: LOADNIL R39  
     112 [-]: LOADNIL R40  
     113 [-]: LOADNIL R41  
     114 [-]: LOADNIL R42  
     115 [-]: NEWTABLE R43 0 0
     116 [-]: LOADNIL R44  
     117 [-]: LOADNIL R45  
     118 [-]: LOADB R46 0  
     119 [-]: LOADB R47 0  
     120 [-]: LOADB R48 0  
     121 [-]: LOADN R49 0  
     122 [-]: LOADB R50 0  
     123 [-]: NEWTABLE R51 0 0
     124 [-]: LOADNIL R52  
     125 [-]: LOADNIL R53  
     126 [-]: DUPCLOSURE R54 K32 []
     127 [-]: DUPCLOSURE R55 K33 []
     128 [-]: NEWCLOSURE R56 P2
     129 [-]: MOVE R1 R41  
     130 [-]: MOVE R0 R9   
     131 [-]: MOVE R1 R53  
     132 [-]: MOVE R1 R32  
     133 [-]: MOVE R0 R13  
     134 [-]: NEWCLOSURE R57 P3
     135 [-]: MOVE R1 R32  
     136 [-]: MOVE R0 R9   
     137 [-]: MOVE R0 R22  
     138 [-]: DUPCLOSURE R58 K34 []
     139 [-]: DUPCLOSURE R59 K35 []
     140 [-]: MOVE R0 R10  
     141 [-]: MOVE R0 R11  
     142 [-]: DUPCLOSURE R60 K36 []
     143 [-]: DUPCLOSURE R61 K37 []
     144 [-]: NEWCLOSURE R62 P8
     145 [-]: MOVE R1 R32  
     146 [-]: NEWCLOSURE R63 P9
     147 [-]: MOVE R1 R34  
     148 [-]: MOVE R1 R45  
     149 [-]: MOVE R1 R39  
     150 [-]: MOVE R1 R35  
     151 [-]: MOVE R1 R36  
     152 [-]: MOVE R1 R37  
     153 [-]: MOVE R1 R38  
     154 [-]: MOVE R1 R40  
     155 [-]: MOVE R1 R33  
     156 [-]: MOVE R1 R43  
     157 [-]: MOVE R1 R41  
     158 [-]: MOVE R0 R6   
     159 [-]: MOVE R0 R56  
     160 [-]: MOVE R0 R5   
     161 [-]: MOVE R0 R26  
     162 [-]: MOVE R0 R27  
     163 [-]: MOVE R1 R42  
     164 [-]: MOVE R0 R8   
     165 [-]: MOVE R1 R44  
     166 [-]: MOVE R0 R2   
     167 [-]: MOVE R0 R3   
     168 [-]: MOVE R0 R0   
     169 [-]: MOVE R0 R1   
     170 [-]: MOVE R1 R28  
     171 [-]: MOVE R0 R59  
     172 [-]: MOVE R1 R31  
     173 [-]: MOVE R1 R29  
     174 [-]: MOVE R0 R61  
     175 [-]: MOVE R0 R16  
     176 [-]: MOVE R1 R32  
     177 [-]: MOVE R1 R30  
     178 [-]: MOVE R0 R14  
     179 [-]: MOVE R1 R48  
     180 [-]: MOVE R0 R17  
     181 [-]: MOVE R0 R62  
     182 [-]: MOVE R0 R12  
     183 [-]: MOVE R0 R22  
     184 [-]: MOVE R0 R25  
     185 [-]: MOVE R0 R21  
     186 [-]: MOVE R1 R52  
     187 [-]: NEWCLOSURE R64 P10
     188 [-]: MOVE R1 R34  
     189 [-]: MOVE R1 R35  
     190 [-]: MOVE R1 R32  
     191 [-]: MOVE R1 R29  
     192 [-]: MOVE R0 R19  
     193 [-]: MOVE R1 R39  
     194 [-]: MOVE R1 R31  
     195 [-]: MOVE R0 R18  
     196 [-]: MOVE R1 R53  
     197 [-]: MOVE R0 R58  
     198 [-]: MOVE R0 R7   
     199 [-]: MOVE R1 R40  
     200 [-]: NEWCLOSURE R65 P11
     201 [-]: MOVE R0 R63  
     202 [-]: MOVE R1 R41  
     203 [-]: MOVE R1 R48  
     204 [-]: MOVE R1 R28  
     205 [-]: MOVE R1 R30  
     206 [-]: MOVE R0 R4   
     207 [-]: MOVE R1 R49  
     208 [-]: MOVE R1 R50  
     209 [-]: MOVE R0 R7   
     210 [-]: MOVE R1 R40  
     211 [-]: MOVE R0 R20  
     212 [-]: MOVE R0 R64  
     213 [-]: MOVE R1 R32  
     214 [-]: MOVE R1 R44  
     215 [-]: MOVE R0 R62  
     216 [-]: MOVE R1 R39  
     217 [-]: MOVE R0 R22  
     218 [-]: MOVE R1 R46  
     219 [-]: MOVE R0 R9   
     220 [-]: MOVE R1 R35  
     221 [-]: MOVE R0 R23  
     222 [-]: MOVE R1 R47  
     223 [-]: MOVE R0 R21  
     224 [-]: MOVE R1 R42  
     225 [-]: MOVE R0 R57  
     226 [-]: MOVE R0 R6   
     227 [-]: MOVE R0 R15  
     228 [-]: MOVE R0 R14  
     229 [-]: MOVE R1 R31  
     230 [-]: MOVE R0 R17  
     231 [-]: MOVE R0 R51  
     232 [-]: MOVE R0 R26  
     233 [-]: MOVE R0 R27  
     234 [-]: MOVE R1 R53  
     235 [-]: SETGLOBAL R65 K38 ["AmbushStart"]
     236 [-]: DUPCLOSURE R65 K39 []
     237 [-]: MOVE R0 R16  
     238 [-]: SETGLOBAL R65 K40 ["OnKilled"]
     239 [-]: DUPCLOSURE R65 K41 []
     240 [-]: MOVE R0 R16  
     241 [-]: SETGLOBAL R65 K42 ["OnAgentRegistered"]
     242 [-]: NEWCLOSURE R65 P14
     243 [-]: MOVE R1 R43  
     244 [-]: SETGLOBAL R65 K43 ["OnPlayersChanged"]
     245 [-]: NEWCLOSURE R65 P15
     246 [-]: MOVE R0 R6   
     247 [-]: MOVE R1 R35  
     248 [-]: SETGLOBAL R65 K44 ["PlayersLeaving"]
     249 [-]: NEWCLOSURE R65 P16
     250 [-]: MOVE R0 R6   
     251 [-]: MOVE R1 R35  
     252 [-]: SETGLOBAL R65 K45 ["PlayersReturning"]
     253 [-]: DUPCLOSURE R65 K46 []
     254 [-]: MOVE R0 R18  
     255 [-]: MOVE R0 R24  
     256 [-]: SETGLOBAL R65 K47 ["DestroyVehicle"]
     257 [-]: DUPCLOSURE R65 K48 []
     258 [-]: MOVE R0 R7   
     259 [-]: MOVE R0 R9   
     260 [-]: MOVE R0 R20  
     261 [-]: SETGLOBAL R65 K49 ["ActivateTrap"]
     262 [-]: DUPCLOSURE R65 K50 []
     263 [-]: MOVE R0 R13  
     264 [-]: MOVE R0 R16  
     265 [-]: MOVE R0 R25  
     266 [-]: MOVE R0 R18  
     267 [-]: MOVE R0 R22  
     268 [-]: SETGLOBAL R65 K51 ["CipherResult"]
     269 [-]: DUPCLOSURE R65 K52 []
     270 [-]: MOVE R0 R25  
     271 [-]: MOVE R0 R7   
     272 [-]: SETGLOBAL R65 K53 ["OnVehicleDamage"]
     273 [-]: CLOSEUPVALS R28
     274 [-]: RETURN R0 0  


; Name:            
; Defined at line: 112
; #Upvalues:       0
; #Parameters:     1
; Is_vararg:       0
; Max Stack Size:  1

       0 [-]: RETURN R0 0  


; Name:            
; Defined at line: 118
; #Upvalues:       0
; #Parameters:     4
; Is_vararg:       0
; Max Stack Size:  4

       0 [-]: RETURN R0 0  


; Name:            
; Defined at line: 130
; #Upvalues:       5
; #Parameters:     0
; Is_vararg:       0
; Max Stack Size:  11

       0 [-]: GETUPVAL R0 0
       1 [-]: NAMECALL R0 R0 K0 [0x209398C2]
       2 [-]: CALL R0 1 1  
       3 [-]: JUMPXEQKN R0 K1 L0 NOT [1]
       4 [-]: GETUPVAL R2 1
       5 [-]: GETTABLEKS R1 R2 K2 [0xA1DF01D6]
       6 [-]: LOADK R2 K3 ["/Lotus/Language/SolarisJobs/DynamicAmbushActivateTrapObj"]
       7 [-]: GETUPVAL R4 1
       8 [-]: GETTABLEKS R3 R4 K4 ["GENERIC_ICON"]
       9 [-]: CALL R1 2 0  
      10 [-]: RETURN R0 0  
L 0:  11 [-]: JUMPXEQKN R0 K5 L1 NOT [2]
      12 [-]: GETUPVAL R2 1
      13 [-]: GETTABLEKS R1 R2 K2 [0xA1DF01D6]
      14 [-]: LOADK R2 K6 ["/Lotus/Language/SolarisJobs/DynamicAmbushWaitForTrapObj"]
      15 [-]: GETUPVAL R4 1
      16 [-]: GETTABLEKS R3 R4 K4 ["GENERIC_ICON"]
      17 [-]: CALL R1 2 0  
      18 [-]: RETURN R0 0  
L 1:  19 [-]: JUMPXEQKN R0 K7 L6 NOT [3]
      20 [-]: GETUPVAL R2 1
      21 [-]: GETTABLEKS R1 R2 K2 [0xA1DF01D6]
      22 [-]: LOADK R2 K8 ["/Lotus/Language/SolarisJobs/DynamicAmbushHackVehicleObj"]
      23 [-]: GETUPVAL R4 1
      24 [-]: GETTABLEKS R3 R4 K4 ["GENERIC_ICON"]
      25 [-]: CALL R1 2 0  
      26 [-]: GETUPVAL R2 2
      27 [-]: FASTCALL1 62 R2 L2
      28 [-]: GETIMPORT R1 10 [0x7B998233]
      29 [-]: CALL R1 1 1  
L 2:  30 [-]: JUMPIF R1 L3 
      31 [-]: GETUPVAL R1 2
      32 [-]: NAMECALL R1 R1 K11 [0xA2880940]
      33 [-]: CALL R1 1 0  
L 3:  34 [-]: GETUPVAL R2 3
      35 [-]: FASTCALL1 62 R2 L4
      36 [-]: GETIMPORT R1 10 [0x7B998233]
      37 [-]: CALL R1 1 1  
L 4:  38 [-]: JUMPIF R1 L14
      39 [-]: GETIMPORT R1 13 [0x89326C93]
      40 [-]: GETUPVAL R3 4
      41 [-]: NAMECALL R1 R1 K14 [0x46A0EBF5]
      42 [-]: CALL R1 2 1  
      43 [-]: FASTCALL1 62 R1 L5
      44 [-]: MOVE R3 R1   
      45 [-]: GETIMPORT R2 10 [0x7B998233]
      46 [-]: CALL R2 1 1  
L 5:  47 [-]: JUMPIF R2 L14
      48 [-]: GETIMPORT R4 16 [0x282E65D7]
      49 [-]: GETIMPORT R5 18 ["EMPTY_SYMBOL"]
      50 [-]: GETIMPORT R6 20 [0xA421AF95]
      51 [-]: LOADN R7 0   
      52 [-]: LOADN R8 1   
      53 [-]: LOADN R9 0   
      54 [-]: CALL R6 3 -1 
      55 [-]: NAMECALL R2 R1 K21 [0x47901F07]
      56 [-]: CALL R2 -1 1 
      57 [-]: SETUPVAL R2 2
      58 [-]: RETURN R0 0  
L 6:  59 [-]: JUMPXEQKN R0 K22 L11 NOT [4]
      60 [-]: GETUPVAL R2 1
      61 [-]: GETTABLEKS R1 R2 K2 [0xA1DF01D6]
      62 [-]: LOADK R2 K23 ["/Lotus/Language/SolarisJobs/DynamicAmbushDefendVehicleObj"]
      63 [-]: GETUPVAL R4 1
      64 [-]: GETTABLEKS R3 R4 K24 ["DEFEND_ICON"]
      65 [-]: CALL R1 2 0  
      66 [-]: GETUPVAL R2 1
      67 [-]: GETTABLEKS R1 R2 K25 [0xA8FBEA61]
      68 [-]: LOADK R2 K26 ["/Lotus/Language/SolarisJobs/DynamicAmbushBonusObj"]
      69 [-]: CALL R1 1 0  
      70 [-]: GETUPVAL R2 2
      71 [-]: FASTCALL1 62 R2 L7
      72 [-]: GETIMPORT R1 10 [0x7B998233]
      73 [-]: CALL R1 1 1  
L 7:  74 [-]: JUMPIF R1 L8 
      75 [-]: GETUPVAL R1 2
      76 [-]: NAMECALL R1 R1 K11 [0xA2880940]
      77 [-]: CALL R1 1 0  
L 8:  78 [-]: GETUPVAL R2 3
      79 [-]: FASTCALL1 62 R2 L9
      80 [-]: GETIMPORT R1 10 [0x7B998233]
      81 [-]: CALL R1 1 1  
L 9:  82 [-]: JUMPIF R1 L14
      83 [-]: GETUPVAL R1 3
      84 [-]: NAMECALL R1 R1 K27 [0xBB610E5B]
      85 [-]: CALL R1 1 1  
      86 [-]: FASTCALL1 62 R1 L10
      87 [-]: MOVE R3 R1   
      88 [-]: GETIMPORT R2 10 [0x7B998233]
      89 [-]: CALL R2 1 1  
L10:  90 [-]: JUMPIF R2 L14
      91 [-]: GETIMPORT R2 13 [0x89326C93]
      92 [-]: GETIMPORT R4 29 [0x30A9FA98]
      93 [-]: NAMECALL R6 R1 K30 [0xD1586535]
      94 [-]: CALL R6 1 1  
      95 [-]: GETIMPORT R7 20 [0xA421AF95]
      96 [-]: LOADN R8 0   
      97 [-]: LOADN R9 3   
      98 [-]: LOADN R10 0  
      99 [-]: CALL R7 3 1  
     100 [-]: ADD R5 R6 R7 
     101 [-]: GETIMPORT R6 32 ["ZERO_ROTATION"]
     102 [-]: NAMECALL R2 R2 K33 [0x05909209]
     103 [-]: CALL R2 4 1  
     104 [-]: SETUPVAL R2 2
     105 [-]: RETURN R0 0  
L11: 106 [-]: JUMPXEQKN R0 K34 L13 NOT [5]
     107 [-]: GETIMPORT R1 37 ["QualifiedForBountyBonus"]
     108 [-]: JUMPIFNOT R1 L12
     109 [-]: GETUPVAL R2 1
     110 [-]: GETTABLEKS R1 R2 K38 [0x0A8ECC31]
     111 [-]: LOADK R2 K26 ["/Lotus/Language/SolarisJobs/DynamicAmbushBonusObj"]
     112 [-]: CALL R1 1 0  
     113 [-]: RETURN R0 0  
L12: 114 [-]: GETUPVAL R2 1
     115 [-]: GETTABLEKS R1 R2 K39 [0x37317859]
     116 [-]: LOADK R2 K26 ["/Lotus/Language/SolarisJobs/DynamicAmbushBonusObj"]
     117 [-]: CALL R1 1 0  
     118 [-]: RETURN R0 0  
L13: 119 [-]: JUMPXEQKN R0 K40 L14 NOT [6]
L14: 120 [-]: RETURN R0 0  


; Name:            
; Defined at line: 173
; #Upvalues:       3
; #Parameters:     0
; Is_vararg:       0
; Max Stack Size:  8

       0 [-]: GETUPVAL R1 0
       1 [-]: FASTCALL1 62 R1 L0
       2 [-]: GETIMPORT R0 1 [0x7B998233]
       3 [-]: CALL R0 1 1  
L 0:   4 [-]: JUMPIF R0 L1 
       5 [-]: GETUPVAL R1 1
       6 [-]: GETTABLEKS R0 R1 K2 [0x0395E519]
       7 [-]: CALL R0 0 1  
       8 [-]: JUMPXEQKNIL R0 L2 NOT
       9 [-]: GETUPVAL R1 1
      10 [-]: GETTABLEKS R0 R1 K3 [0x1551AA65]
      11 [-]: GETUPVAL R1 0
      12 [-]: NAMECALL R1 R1 K4 [0xBB610E5B]
      13 [-]: CALL R1 1 -1 
      14 [-]: CALL R0 -1 0 
      15 [-]: JUMP L2
     
L 1:  16 [-]: GETUPVAL R1 1
      17 [-]: GETTABLEKS R0 R1 K2 [0x0395E519]
      18 [-]: CALL R0 0 1  
      19 [-]: JUMPXEQKNIL R0 L2
      20 [-]: GETUPVAL R1 1
      21 [-]: GETTABLEKS R0 R1 K5 [0xEDF59000]
      22 [-]: CALL R0 0 0  
L 2:  23 [-]: GETIMPORT R0 7 [0xBE190284]
      24 [-]: GETUPVAL R2 2
      25 [-]: NAMECALL R0 R0 K8 [0x0F823E41]
      26 [-]: CALL R0 2 1  
      27 [-]: JUMPIFNOT R0 L4
      28 [-]: GETIMPORT R0 7 [0xBE190284]
      29 [-]: GETUPVAL R2 2
      30 [-]: NAMECALL R0 R0 K9 [0xFFDDF768]
      31 [-]: CALL R0 2 1  
      32 [-]: FASTCALL2K 18 R0 K10 L3 [0]
      33 [-]: MOVE R2 R0   
      34 [-]: LOADK R3 K10 [0]
      35 [-]: GETIMPORT R1 13 [0xB62ECFE0]
      36 [-]: CALL R1 2 1  
L 3:  37 [-]: MOVE R0 R1   
      38 [-]: GETUPVAL R2 1
      39 [-]: GETTABLEKS R1 R2 K14 [0x46749D86]
      40 [-]: CALL R1 0 1  
      41 [-]: JUMPXEQKNIL R1 L5 NOT
      42 [-]: GETUPVAL R2 1
      43 [-]: GETTABLEKS R1 R2 K15 [0xE8FA0E68]
      44 [-]: MOVE R2 R0   
      45 [-]: LOADB R3 0   
      46 [-]: LOADB R4 0   
      47 [-]: LOADB R5 0   
      48 [-]: GETUPVAL R7 1
      49 [-]: GETTABLEKS R6 R7 K16 ["TIMELEFT_STRING"]
      50 [-]: CALL R1 5 0  
      51 [-]: RETURN R0 0  
L 4:  52 [-]: GETUPVAL R1 1
      53 [-]: GETTABLEKS R0 R1 K14 [0x46749D86]
      54 [-]: CALL R0 0 1  
      55 [-]: JUMPXEQKNIL R0 L5
      56 [-]: GETUPVAL R1 1
      57 [-]: GETTABLEKS R0 R1 K17 [0x18DD08AC]
      58 [-]: CALL R0 0 0  
L 5:  59 [-]: RETURN R0 0  


; Name:            
; Defined at line: 224
; #Upvalues:       0
; #Parameters:     5
; Is_vararg:       0
; Max Stack Size:  15

       0 [-]: NAMECALL R5 R1 K0 [0xD1586535]
       1 [-]: CALL R5 1 1  
       2 [-]: GETIMPORT R6 2 [0x89326C93]
       3 [-]: MOVE R8 R0   
       4 [-]: MOVE R9 R5   
       5 [-]: GETIMPORT R10 4 ["ZERO_ROTATION"]
       6 [-]: NAMECALL R6 R6 K5 [0x05909209]
       7 [-]: CALL R6 4 1  
       8 [-]: JUMPIFNOT R3 L0
       9 [-]: MOVE R9 R6   
      10 [-]: GETIMPORT R10 7 ["EMPTY_SYMBOL"]
      11 [-]: GETIMPORT R11 9 [0xA421AF95]
      12 [-]: LOADN R12 0  
      13 [-]: LOADN R13 3  
      14 [-]: LOADN R14 0  
      15 [-]: CALL R11 3 1 
      16 [-]: GETIMPORT R12 4 ["ZERO_ROTATION"]
      17 [-]: NAMECALL R7 R1 K10 [0x3BB4F460]
      18 [-]: CALL R7 5 0  
L 0:  19 [-]: JUMPIFNOT R4 L1
      20 [-]: MOVE R9 R4   
      21 [-]: NAMECALL R7 R6 K11 [0x5004BE24]
      22 [-]: CALL R7 2 0  
L 1:  23 [-]: GETIMPORT R9 13 [0xB7CBD06B]
      24 [-]: LOADN R10 5  
      25 [-]: LOADN R11 5000
      26 [-]: CALL R9 2 -1 
      27 [-]: NAMECALL R7 R6 K14 [0x53BC0559]
      28 [-]: CALL R7 -1 0 
      29 [-]: RETURN R6 1  


; Name:            
; Defined at line: 237
; #Upvalues:       2
; #Parameters:     1
; Is_vararg:       0
; Max Stack Size:  15

       0 [-]: GETIMPORT R1 1 [0xA421AF95]
       1 [-]: LOADN R2 0   
       2 [-]: LOADN R3 10  
       3 [-]: LOADN R4 0   
       4 [-]: CALL R1 3 1  
       5 [-]: ADD R2 R0 R1 
       6 [-]: SUB R3 R0 R1 
       7 [-]: GETIMPORT R4 1 [0xA421AF95]
       8 [-]: CALL R4 0 1  
       9 [-]: GETIMPORT R5 3 [0x467EAF6A]
      10 [-]: CALL R5 0 1  
      11 [-]: LOADNIL R8   
      12 [-]: NAMECALL R6 R5 K4 [0xC63157A6]
      13 [-]: CALL R6 2 0  
      14 [-]: LOADNIL R6   
      15 [-]: LOADB R7 0   
L 0:  16 [-]: JUMPIF R7 L8 
      17 [-]: GETIMPORT R8 6 [0x89326C93]
      18 [-]: MOVE R10 R2  
      19 [-]: MOVE R11 R3  
      20 [-]: LOADNIL R12  
      21 [-]: MOVE R13 R5  
      22 [-]: MOVE R14 R4  
      23 [-]: NAMECALL R8 R8 K7 [0xBD5D0EC1]
      24 [-]: CALL R8 6 1  
      25 [-]: JUMPIFNOT R8 L6
      26 [-]: FASTCALL1 62 R5 L1
      27 [-]: MOVE R9 R5   
      28 [-]: GETIMPORT R8 9 [0x7B998233]
      29 [-]: CALL R8 1 1  
L 1:  30 [-]: JUMPIF R8 L2 
      31 [-]: NAMECALL R8 R5 K10 [0xEF3A99CA]
      32 [-]: CALL R8 1 1  
      33 [-]: MOVE R6 R8   
L 2:  34 [-]: FASTCALL1 62 R6 L3
      35 [-]: MOVE R9 R6   
      36 [-]: GETIMPORT R8 9 [0x7B998233]
      37 [-]: CALL R8 1 1  
L 3:  38 [-]: JUMPIF R8 L5 
      39 [-]: GETUPVAL R10 0
      40 [-]: NAMECALL R8 R6 K11 [0xF2DEAF69]
      41 [-]: CALL R8 2 1  
      42 [-]: JUMPIF R8 L4 
      43 [-]: GETUPVAL R10 1
      44 [-]: NAMECALL R8 R6 K11 [0xF2DEAF69]
      45 [-]: CALL R8 2 1  
      46 [-]: JUMPIFNOT R8 L5
L 4:  47 [-]: MOVE R0 R4   
      48 [-]: LOADB R7 1   
      49 [-]: JUMP L7
     
L 5:  50 [-]: GETIMPORT R8 13 [0xCBD666E1]
      51 [-]: LOADN R9 1   
      52 [-]: CALL R8 1 0  
      53 [-]: JUMP L7
     
L 6:  54 [-]: ADD R2 R2 R1 
      55 [-]: SUB R3 R3 R1 
L 7:  56 [-]: JUMPBACK L0  
L 8:  57 [-]: RETURN R0 1  


; Name:            
; Defined at line: 267
; #Upvalues:       0
; #Parameters:     3
; Is_vararg:       0
; Max Stack Size:  8

       0 [-]: GETIMPORT R4 1 [0xA421AF95]
       1 [-]: LOADN R5 0   
       2 [-]: LOADN R6 1000
       3 [-]: LOADN R7 0   
       4 [-]: CALL R4 3 1  
       5 [-]: ADD R3 R0 R4 
       6 [-]: MOVE R4 R1   
       7 [-]: MOVE R5 R2   
       8 [-]: RETURN R0 0  


; Name:            
; Defined at line: 271
; #Upvalues:       0
; #Parameters:     4
; Is_vararg:       0
; Max Stack Size:  21

       0 [-]: GETIMPORT R4 1 [0xA421AF95]
       1 [-]: CALL R4 0 1  
       2 [-]: GETIMPORT R5 3 [0x89326C93]
       3 [-]: NAMECALL R5 R5 K4 [0x29EF273D]
       4 [-]: CALL R5 1 1  
       5 [-]: MUL R6 R2 R2 
       6 [-]: MUL R7 R3 R3 
       7 [-]: LOADN R8 0   
       8 [-]: LOADB R9 0   
       9 [-]: NEWTABLE R10 0 0
      10 [-]: GETIMPORT R11 1 [0xA421AF95]
      11 [-]: CALL R11 0 1 
      12 [-]: LOADN R14 1  
      13 [-]: LENGTH R12 R0
      14 [-]: LOADN R13 1  
      15 [-]: FORNPREP R12 L3
L 0:  16 [-]: GETTABLE R17 R0 R14
      17 [-]: MOVE R18 R11 
      18 [-]: NAMECALL R15 R5 K5 [0x9B3A6C3C]
      19 [-]: CALL R15 3 0 
      20 [-]: GETIMPORT R15 7 [0x60130201]
      21 [-]: LOADN R16 24 
      22 [-]: LOADN R17 240
      23 [-]: LOADN R18 200
      24 [-]: CALL R15 3 1 
      25 [-]: GETIMPORT R17 1 [0xA421AF95]
      26 [-]: LOADN R18 0  
      27 [-]: LOADN R19 1000
      28 [-]: LOADN R20 0  
      29 [-]: CALL R17 3 1 
      30 [-]: ADD R16 R11 R17
      31 [-]: MOVE R17 R15 
      32 [-]: LOADN R18 600
      33 [-]: GETIMPORT R15 9 [0xC0DA2B81]
      34 [-]: MOVE R16 R11 
      35 [-]: MOVE R17 R1  
      36 [-]: CALL R15 2 1 
      37 [-]: JUMPIFNOTLE R6 R15 L1
      38 [-]: JUMPIFNOTLE R15 R7 L1
      39 [-]: LOADB R9 1   
      40 [-]: FASTCALL2 52 R10 R11 L1
      41 [-]: MOVE R17 R10 
      42 [-]: MOVE R18 R11 
      43 [-]: GETIMPORT R16 12 [0x23D5322F]
      44 [-]: CALL R16 2 0 
L 1:  45 [-]: JUMPIFNOTLT R8 R15 L2
      46 [-]: MOVE R4 R11  
      47 [-]: MOVE R8 R15  
L 2:  48 [-]: FORNLOOP R12 L0
L 3:  49 [-]: LOADK R13 K13 ["Choosing from "]
      50 [-]: LENGTH R14 R0
      51 [-]: LOADK R15 K14 [" vehicle start points"]
      52 [-]: CONCAT R12 R13 R15
      53 [-]: LOADK R13 K15 ["Maxdist: "]
      54 [-]: MOVE R14 R8  
      55 [-]: CONCAT R12 R13 R14
      56 [-]: LOADK R13 K16 ["Vehicle Start Point found: "]
      57 [-]: GETIMPORT R14 18 [0x64FB1586]
      58 [-]: MOVE R15 R9  
      59 [-]: CALL R14 1 1 
      60 [-]: CONCAT R12 R13 R14
      61 [-]: JUMPIFNOT R9 L4
      62 [-]: RETURN R10 1 
L 4:  63 [-]: NEWTABLE R12 0 1
      64 [-]: MOVE R13 R4  
      65 [-]: SETLIST R12 R13 1 [1]
      66 [-]: RETURN R12 1 


; Name:            
; Defined at line: 303
; #Upvalues:       1
; #Parameters:     1
; Is_vararg:       0
; Max Stack Size:  15

       0 [-]: GETUPVAL R2 0
       1 [-]: FASTCALL1 62 R2 L0
       2 [-]: GETIMPORT R1 1 [0x7B998233]
       3 [-]: CALL R1 1 1  
L 0:   4 [-]: JUMPIFNOT R1 L1
       5 [-]: GETIMPORT R1 3 [0x3D106989]
       6 [-]: LOADK R2 K4 ["ShowVehicleFx: mAmbushedAgent is null"]
       7 [-]: CALL R1 1 0  
       8 [-]: RETURN R0 0  
L 1:   9 [-]: GETUPVAL R1 0
      10 [-]: NAMECALL R1 R1 K5 [0xBB610E5B]
      11 [-]: CALL R1 1 1  
      12 [-]: GETIMPORT R4 7 ["gLotusEffectDecorationType"]
      13 [-]: NAMECALL R2 R1 K8 [0xC1595BD5]
      14 [-]: CALL R2 2 1  
      15 [-]: GETIMPORT R5 10 ["gParticleSysType"]
      16 [-]: NAMECALL R3 R1 K8 [0xC1595BD5]
      17 [-]: CALL R3 2 1  
      18 [-]: GETIMPORT R6 12 ["gSequencerType"]
      19 [-]: NAMECALL R4 R1 K8 [0xC1595BD5]
      20 [-]: CALL R4 2 1  
      21 [-]: GETIMPORT R7 14 ["gEffectType"]
      22 [-]: NAMECALL R5 R1 K8 [0xC1595BD5]
      23 [-]: CALL R5 2 1  
      24 [-]: JUMPIFNOT R0 L14
      25 [-]: GETIMPORT R6 16 [0xC8802016]
      26 [-]: MOVE R7 R2   
      27 [-]: CALL R6 1 3  
      28 [-]: FORGPREP_INEXT R6 L4
L 2:  29 [-]: FASTCALL1 62 R10 L3
      30 [-]: MOVE R12 R10 
      31 [-]: GETIMPORT R11 1 [0x7B998233]
      32 [-]: CALL R11 1 1 
L 3:  33 [-]: JUMPIF R11 L4
      34 [-]: LOADB R13 1  
      35 [-]: LOADB R14 0  
      36 [-]: NAMECALL R11 R10 K17 [0x768274D6]
      37 [-]: CALL R11 3 0 
L 4:  38 [-]: FORGLOOP R6 L2 2 [inext]
      39 [-]: GETIMPORT R6 16 [0xC8802016]
      40 [-]: MOVE R7 R3   
      41 [-]: CALL R6 1 3  
      42 [-]: FORGPREP_INEXT R6 L7
L 5:  43 [-]: FASTCALL1 62 R10 L6
      44 [-]: MOVE R12 R10 
      45 [-]: GETIMPORT R11 1 [0x7B998233]
      46 [-]: CALL R11 1 1 
L 6:  47 [-]: JUMPIF R11 L7
      48 [-]: NAMECALL R11 R10 K18 [0x383D2E7D]
      49 [-]: CALL R11 1 0 
L 7:  50 [-]: FORGLOOP R6 L5 2 [inext]
      51 [-]: GETIMPORT R6 16 [0xC8802016]
      52 [-]: MOVE R7 R4   
      53 [-]: CALL R6 1 3  
      54 [-]: FORGPREP_INEXT R6 L10
L 8:  55 [-]: FASTCALL1 62 R10 L9
      56 [-]: MOVE R12 R10 
      57 [-]: GETIMPORT R11 1 [0x7B998233]
      58 [-]: CALL R11 1 1 
L 9:  59 [-]: JUMPIF R11 L10
      60 [-]: NAMECALL R11 R10 K18 [0x383D2E7D]
      61 [-]: CALL R11 1 0 
L10:  62 [-]: FORGLOOP R6 L8 2 [inext]
      63 [-]: GETIMPORT R6 16 [0xC8802016]
      64 [-]: MOVE R7 R5   
      65 [-]: CALL R6 1 3  
      66 [-]: FORGPREP_INEXT R6 L13
L11:  67 [-]: FASTCALL1 62 R10 L12
      68 [-]: MOVE R12 R10 
      69 [-]: GETIMPORT R11 1 [0x7B998233]
      70 [-]: CALL R11 1 1 
L12:  71 [-]: JUMPIF R11 L13
      72 [-]: LOADB R13 1  
      73 [-]: LOADB R14 0  
      74 [-]: NAMECALL R11 R10 K17 [0x768274D6]
      75 [-]: CALL R11 3 0 
L13:  76 [-]: FORGLOOP R6 L11 2 [inext]
      77 [-]: RETURN R0 0  
L14:  78 [-]: GETIMPORT R6 16 [0xC8802016]
      79 [-]: MOVE R7 R2   
      80 [-]: CALL R6 1 3  
      81 [-]: FORGPREP_INEXT R6 L17
L15:  82 [-]: FASTCALL1 62 R10 L16
      83 [-]: MOVE R12 R10 
      84 [-]: GETIMPORT R11 1 [0x7B998233]
      85 [-]: CALL R11 1 1 
L16:  86 [-]: JUMPIF R11 L17
      87 [-]: LOADB R13 0  
      88 [-]: LOADB R14 0  
      89 [-]: NAMECALL R11 R10 K17 [0x768274D6]
      90 [-]: CALL R11 3 0 
L17:  91 [-]: FORGLOOP R6 L15 2 [inext]
      92 [-]: GETIMPORT R6 16 [0xC8802016]
      93 [-]: MOVE R7 R3   
      94 [-]: CALL R6 1 3  
      95 [-]: FORGPREP_INEXT R6 L20
L18:  96 [-]: FASTCALL1 62 R10 L19
      97 [-]: MOVE R12 R10 
      98 [-]: GETIMPORT R11 1 [0x7B998233]
      99 [-]: CALL R11 1 1 
L19: 100 [-]: JUMPIF R11 L20
     101 [-]: NAMECALL R11 R10 K19 [0xF4E253B6]
     102 [-]: CALL R11 1 0 
L20: 103 [-]: FORGLOOP R6 L18 2 [inext]
     104 [-]: GETIMPORT R6 16 [0xC8802016]
     105 [-]: MOVE R7 R4   
     106 [-]: CALL R6 1 3  
     107 [-]: FORGPREP_INEXT R6 L23
L21: 108 [-]: FASTCALL1 62 R10 L22
     109 [-]: MOVE R12 R10 
     110 [-]: GETIMPORT R11 1 [0x7B998233]
     111 [-]: CALL R11 1 1 
L22: 112 [-]: JUMPIF R11 L23
     113 [-]: NAMECALL R11 R10 K19 [0xF4E253B6]
     114 [-]: CALL R11 1 0 
L23: 115 [-]: FORGLOOP R6 L21 2 [inext]
     116 [-]: GETIMPORT R6 16 [0xC8802016]
     117 [-]: MOVE R7 R5   
     118 [-]: CALL R6 1 3  
     119 [-]: FORGPREP_INEXT R6 L26
L24: 120 [-]: FASTCALL1 62 R10 L25
     121 [-]: MOVE R12 R10 
     122 [-]: GETIMPORT R11 1 [0x7B998233]
     123 [-]: CALL R11 1 1 
L25: 124 [-]: JUMPIF R11 L26
     125 [-]: LOADB R13 0  
     126 [-]: LOADB R14 0  
     127 [-]: NAMECALL R11 R10 K17 [0x768274D6]
     128 [-]: CALL R11 3 0 
L26: 129 [-]: FORGLOOP R6 L24 2 [inext]
     130 [-]: RETURN R0 0  


; Name:            
; Defined at line: 358
; #Upvalues:       40
; #Parameters:     1
; Is_vararg:       0
; Max Stack Size:  16

       0 [-]: GETIMPORT R1 1 [0x89326C93]
       1 [-]: NAMECALL R1 R1 K2 [0x29EF273D]
       2 [-]: CALL R1 1 1  
       3 [-]: NAMECALL R1 R1 K3 [0x66905CB0]
       4 [-]: CALL R1 1 1  
       5 [-]: SETUPVAL R1 0
L 0:   6 [-]: GETUPVAL R1 0
       7 [-]: NAMECALL R1 R1 K4 [0xA2D83ED4]
       8 [-]: CALL R1 1 1  
       9 [-]: JUMPIF R1 L1 
      10 [-]: GETIMPORT R1 6 [0xCBD666E1]
      11 [-]: LOADN R2 0   
      12 [-]: CALL R1 1 0  
      13 [-]: JUMPBACK L0  
L 1:  14 [-]: GETIMPORT R2 8 [0x83F4E77C]
      15 [-]: FASTCALL1 62 R2 L2
      16 [-]: GETIMPORT R1 10 [0x7B998233]
      17 [-]: CALL R1 1 1  
L 2:  18 [-]: JUMPIF R1 L5 
L 3:  19 [-]: GETUPVAL R2 1
      20 [-]: FASTCALL1 62 R2 L4
      21 [-]: GETIMPORT R1 10 [0x7B998233]
      22 [-]: CALL R1 1 1  
L 4:  23 [-]: JUMPIFNOT R1 L5
      24 [-]: GETIMPORT R1 12 [0xBE190284]
      25 [-]: NAMECALL R1 R1 K13 [0x33307F92]
      26 [-]: CALL R1 1 1  
      27 [-]: SETUPVAL R1 1
      28 [-]: GETIMPORT R1 6 [0xCBD666E1]
      29 [-]: LOADN R2 0   
      30 [-]: CALL R1 1 0  
      31 [-]: JUMPBACK L3  
L 5:  32 [-]: NAMECALL R1 R0 K14 [0x891629FA]
      33 [-]: CALL R1 1 1  
      34 [-]: SETUPVAL R1 2
      35 [-]: SETUPVAL R0 3
      36 [-]: NAMECALL R1 R0 K15 [0xD1586535]
      37 [-]: CALL R1 1 1  
      38 [-]: SETUPVAL R1 4
      39 [-]: NAMECALL R1 R0 K16 [0xF6CF204F]
      40 [-]: CALL R1 1 1  
      41 [-]: SETUPVAL R1 5
      42 [-]: NAMECALL R1 R0 K17 [0x7C97B143]
      43 [-]: CALL R1 1 1  
      44 [-]: SETUPVAL R1 6
      45 [-]: NAMECALL R1 R0 K18 [0x4C976EDA]
      46 [-]: CALL R1 1 1  
      47 [-]: NAMECALL R2 R1 K19 [0xE4C355E2]
      48 [-]: CALL R2 1 1  
      49 [-]: SETUPVAL R2 7
      50 [-]: NAMECALL R2 R1 K20 [0xAA1950D4]
      51 [-]: CALL R2 1 1  
      52 [-]: SETUPVAL R2 8
      53 [-]: GETIMPORT R2 1 [0x89326C93]
      54 [-]: LOADK R4 K21 ["OnPlayersChanged"]
      55 [-]: NAMECALL R2 R2 K22 [0xB7D33840]
      56 [-]: CALL R2 2 0  
      57 [-]: GETIMPORT R2 1 [0x89326C93]
      58 [-]: NAMECALL R2 R2 K23 [0x8B5B1F58]
      59 [-]: CALL R2 1 1  
      60 [-]: SETUPVAL R2 9
      61 [-]: GETUPVAL R2 3
      62 [-]: NAMECALL R2 R2 K24 [0xABE61691]
      63 [-]: CALL R2 1 1  
      64 [-]: GETUPVAL R4 11
      65 [-]: GETTABLEKS R3 R4 K25 [0xC9013731]
      66 [-]: GETUPVAL R4 12
      67 [-]: GETUPVAL R5 3
      68 [-]: NEWTABLE R6 0 0
      69 [-]: CALL R3 3 1  
      70 [-]: SETUPVAL R3 10
      71 [-]: GETUPVAL R3 10
      72 [-]: GETUPVAL R6 13
      73 [-]: GETTABLEKS R5 R6 K26 [0x06D055F9]
      74 [-]: JUMPXEQKN R2 K27 L6 [0]
      75 [-]: LOADB R6 0 +1
L 6:  76 [-]: LOADB R6 1   
L 7:  77 [-]: LOADN R7 1   
      78 [-]: MOVE R8 R2   
      79 [-]: CALL R5 3 -1 
      80 [-]: NAMECALL R3 R3 K28 [0x8ABFF40E]
      81 [-]: CALL R3 -1 0 
      82 [-]: GETUPVAL R3 3
      83 [-]: LOADK R5 K29 ["PlayersLeaving"]
      84 [-]: GETUPVAL R6 14
      85 [-]: NAMECALL R3 R3 K30 [0xE19C3F44]
      86 [-]: CALL R3 3 0  
      87 [-]: GETUPVAL R3 3
      88 [-]: LOADK R5 K31 ["PlayersReturning"]
      89 [-]: GETUPVAL R6 15
      90 [-]: NAMECALL R3 R3 K32 [0x3F86F5A0]
      91 [-]: CALL R3 3 0  
      92 [-]: GETUPVAL R4 17
      93 [-]: GETTABLEKS R3 R4 K33 [0xDE474187]
      94 [-]: CALL R3 0 1  
      95 [-]: SETUPVAL R3 16
      96 [-]: GETUPVAL R4 11
      97 [-]: GETTABLEKS R3 R4 K34 [0xA80CF6FF]
      98 [-]: GETUPVAL R4 0
      99 [-]: MOVE R5 R0   
     100 [-]: CALL R3 2 1  
     101 [-]: SETUPVAL R3 18
     102 [-]: GETUPVAL R3 18
     103 [-]: GETIMPORT R4 36 [0x7496783E]
     104 [-]: SETTABLEKS R4 R3 K37 ["mSpecificEncounterTypes"]
     105 [-]: GETUPVAL R3 18
     106 [-]: GETUPVAL R5 11
     107 [-]: GETTABLEKS R4 R5 K38 ["AS_SPECIFIC_ENCOUNTER_TYPE"]
     108 [-]: SETTABLEKS R4 R3 K39 ["mActivationStyle"]
     109 [-]: GETUPVAL R3 18
     110 [-]: GETIMPORT R4 41 [0x9014786D]
     111 [-]: SETTABLEKS R4 R3 K42 ["mRandomActivationFaction"]
     112 [-]: GETUPVAL R3 18
     113 [-]: GETUPVAL R5 3
     114 [-]: NAMECALL R5 R5 K16 [0xF6CF204F]
     115 [-]: CALL R5 1 1  
     116 [-]: MULK R4 R5 K43 [0.40000000000000002]
     117 [-]: SETTABLEKS R4 R3 K44 ["mHintRadius"]
     118 [-]: GETUPVAL R3 18
     119 [-]: LOADN R4 8   
     120 [-]: SETTABLEKS R4 R3 K45 ["mReinforceDelay"]
     121 [-]: GETIMPORT R3 48 [0x056BFE8B]
     122 [-]: CALL R3 0 1  
     123 [-]: JUMPIFNOT R3 L8
     124 [-]: GETUPVAL R3 18
     125 [-]: GETUPVAL R4 19
     126 [-]: SETTABLEKS R4 R3 K49 ["mMinNumAgents"]
     127 [-]: GETUPVAL R3 18
     128 [-]: GETUPVAL R4 20
     129 [-]: SETTABLEKS R4 R3 K50 ["mMaxNumAgents"]
     130 [-]: JUMP L9
     
L 8: 131 [-]: GETUPVAL R3 18
     132 [-]: GETUPVAL R4 21
     133 [-]: SETTABLEKS R4 R3 K49 ["mMinNumAgents"]
     134 [-]: GETUPVAL R3 18
     135 [-]: GETUPVAL R4 22
     136 [-]: SETTABLEKS R4 R3 K50 ["mMaxNumAgents"]
L 9: 137 [-]: GETUPVAL R3 2
     138 [-]: LOADK R5 K51 ["OnAgentRegistered"]
     139 [-]: GETIMPORT R6 53 [0x0469F296]
     140 [-]: LOADK R7 K54 ["DynamicAmbushRegistration"]
     141 [-]: CALL R6 1 -1 
     142 [-]: NAMECALL R3 R3 K55 [0x5B344F44]
     143 [-]: CALL R3 -1 0 
     144 [-]: GETIMPORT R3 1 [0x89326C93]
     145 [-]: NAMECALL R3 R3 K2 [0x29EF273D]
     146 [-]: CALL R3 1 1  
     147 [-]: GETUPVAL R6 4
     148 [-]: GETUPVAL R7 23
     149 [-]: NAMECALL R4 R3 K56 [0x9B3A6C3C]
     150 [-]: CALL R4 3 0  
     151 [-]: GETUPVAL R4 24
     152 [-]: GETUPVAL R5 23
     153 [-]: CALL R4 1 1  
     154 [-]: SETUPVAL R4 23
     155 [-]: GETUPVAL R5 25
     156 [-]: FASTCALL1 62 R5 L10
     157 [-]: GETIMPORT R4 10 [0x7B998233]
     158 [-]: CALL R4 1 1  
L10: 159 [-]: JUMPIFNOT R4 L11
     160 [-]: GETIMPORT R4 1 [0x89326C93]
     161 [-]: GETIMPORT R6 58 [0x78EB7099]
     162 [-]: GETUPVAL R7 23
     163 [-]: GETIMPORT R8 60 ["ZERO_ROTATION"]
     164 [-]: NAMECALL R4 R4 K61 [0x05909209]
     165 [-]: CALL R4 4 1  
     166 [-]: SETUPVAL R4 25
L11: 167 [-]: GETUPVAL R4 23
     168 [-]: SETUPVAL R4 26
     169 [-]: GETUPVAL R5 11
     170 [-]: GETTABLEKS R4 R5 K62 [0xEA7690E3]
     171 [-]: GETUPVAL R5 2
     172 [-]: GETIMPORT R6 64 ["gWaypointType"]
     173 [-]: CALL R4 2 1  
     174 [-]: FASTCALL1 62 R4 L12
     175 [-]: MOVE R6 R4   
     176 [-]: GETIMPORT R5 10 [0x7B998233]
     177 [-]: CALL R5 1 1  
L12: 178 [-]: JUMPIFNOT R5 L13
     179 [-]: GETUPVAL R5 0
     180 [-]: MOVE R7 R0   
     181 [-]: LOADN R8 100 
     182 [-]: LOADN R9 300 
     183 [-]: LOADN R10 80 
     184 [-]: LOADN R11 10000
     185 [-]: LOADB R12 1  
     186 [-]: LOADN R13 0  
     187 [-]: LOADN R14 120
     188 [-]: LOADB R15 1  
     189 [-]: NAMECALL R5 R5 K65 [0x0D7B12A1]
     190 [-]: CALL R5 10 1 
     191 [-]: GETUPVAL R6 27
     192 [-]: MOVE R7 R5   
     193 [-]: GETUPVAL R8 23
     194 [-]: LOADN R9 100 
     195 [-]: LOADN R10 300
     196 [-]: CALL R6 4 1  
     197 [-]: GETIMPORT R8 67 [0x55730E1A]
     198 [-]: LOADN R9 1   
     199 [-]: LENGTH R10 R6
     200 [-]: CALL R8 2 1  
     201 [-]: GETTABLE R7 R6 R8
     202 [-]: SETUPVAL R7 26
     203 [-]: JUMP L14
    
L13: 204 [-]: GETIMPORT R6 67 [0x55730E1A]
     205 [-]: LOADN R7 1   
     206 [-]: LENGTH R8 R4 
     207 [-]: CALL R6 2 1  
     208 [-]: GETTABLE R5 R4 R6
     209 [-]: NAMECALL R5 R5 K15 [0xD1586535]
     210 [-]: CALL R5 1 1  
     211 [-]: SETUPVAL R5 26
L14: 212 [-]: GETUPVAL R5 23
     213 [-]: GETUPVAL R6 26
     214 [-]: GETIMPORT R7 69 [0x60130201]
     215 [-]: LOADN R8 255 
     216 [-]: LOADN R9 255 
     217 [-]: LOADN R10 255
     218 [-]: CALL R7 3 1  
     219 [-]: LOADN R8 600 
     220 [-]: GETUPVAL R5 23
     221 [-]: GETIMPORT R6 69 [0x60130201]
     222 [-]: LOADN R7 255 
     223 [-]: LOADN R8 0   
     224 [-]: LOADN R9 0   
     225 [-]: CALL R6 3 1  
     226 [-]: GETIMPORT R8 71 [0xA421AF95]
     227 [-]: LOADN R9 0   
     228 [-]: LOADN R10 1000
     229 [-]: LOADN R11 0  
     230 [-]: CALL R8 3 1  
     231 [-]: ADD R7 R5 R8 
     232 [-]: MOVE R8 R6   
     233 [-]: LOADN R9 600 
     234 [-]: GETUPVAL R5 26
     235 [-]: GETIMPORT R6 69 [0x60130201]
     236 [-]: LOADN R7 0   
     237 [-]: LOADN R8 255 
     238 [-]: LOADN R9 0   
     239 [-]: CALL R6 3 1  
     240 [-]: GETIMPORT R8 71 [0xA421AF95]
     241 [-]: LOADN R9 0   
     242 [-]: LOADN R10 1000
     243 [-]: LOADN R11 0  
     244 [-]: CALL R8 3 1  
     245 [-]: ADD R7 R5 R8 
     246 [-]: MOVE R8 R6   
     247 [-]: LOADN R9 600 
     248 [-]: JUMPXEQKN R2 K27 L15 NOT [0]
     249 [-]: GETUPVAL R5 10
     250 [-]: LOADN R7 1   
     251 [-]: NAMECALL R5 R5 K28 [0x8ABFF40E]
     252 [-]: CALL R5 2 0  
     253 [-]: JUMP L33
    
L15: 254 [-]: LOADN R5 1   
     255 [-]: JUMPIFNOTLT R5 R2 L33
     256 [-]: GETIMPORT R5 1 [0x89326C93]
     257 [-]: GETUPVAL R7 28
     258 [-]: NAMECALL R5 R5 K72 [0x46A0EBF5]
     259 [-]: CALL R5 2 1  
     260 [-]: FASTCALL1 62 R5 L16
     261 [-]: MOVE R7 R5   
     262 [-]: GETIMPORT R6 10 [0x7B998233]
     263 [-]: CALL R6 1 1  
L16: 264 [-]: JUMPIF R6 L18
     265 [-]: NAMECALL R6 R5 K73 [0xFA9E477F]
     266 [-]: CALL R6 1 1  
     267 [-]: SETUPVAL R6 29
     268 [-]: LOADN R6 3   
     269 [-]: JUMPIFNOTLT R2 R6 L17
     270 [-]: GETUPVAL R6 29
     271 [-]: GETUPVAL R8 25
     272 [-]: LOADB R9 1   
     273 [-]: LOADB R10 1  
     274 [-]: LOADB R11 0  
     275 [-]: NAMECALL R6 R6 K74 [0x748DF3EF]
     276 [-]: CALL R6 5 0  
     277 [-]: JUMP L18
    
L17: 278 [-]: GETUPVAL R6 29
     279 [-]: NAMECALL R6 R6 K75 [0x4094B424]
     280 [-]: CALL R6 1 0  
     281 [-]: GETUPVAL R6 29
     282 [-]: NAMECALL R6 R6 K76 [0xBB610E5B]
     283 [-]: CALL R6 1 1  
     284 [-]: LOADB R8 1   
     285 [-]: NAMECALL R6 R6 K77 [0xEC1EE87F]
     286 [-]: CALL R6 2 0  
L18: 287 [-]: GETIMPORT R6 1 [0x89326C93]
     288 [-]: GETUPVAL R8 31
     289 [-]: NAMECALL R6 R6 K72 [0x46A0EBF5]
     290 [-]: CALL R6 2 1  
     291 [-]: SETUPVAL R6 30
     292 [-]: GETUPVAL R7 30
     293 [-]: FASTCALL1 62 R7 L19
     294 [-]: GETIMPORT R6 10 [0x7B998233]
     295 [-]: CALL R6 1 1  
L19: 296 [-]: JUMPIF R6 L20
     297 [-]: LOADB R6 1   
     298 [-]: SETUPVAL R6 32
     299 [-]: GETUPVAL R6 30
     300 [-]: GETIMPORT R8 79 [0x282E65D7]
     301 [-]: GETIMPORT R9 81 ["EMPTY_SYMBOL"]
     302 [-]: NAMECALL R6 R6 K82 [0x47901F07]
     303 [-]: CALL R6 3 0  
L20: 304 [-]: GETIMPORT R6 1 [0x89326C93]
     305 [-]: GETUPVAL R8 33
     306 [-]: NAMECALL R6 R6 K72 [0x46A0EBF5]
     307 [-]: CALL R6 2 1  
     308 [-]: FASTCALL1 62 R6 L21
     309 [-]: MOVE R8 R6   
     310 [-]: GETIMPORT R7 10 [0x7B998233]
     311 [-]: CALL R7 1 1  
L21: 312 [-]: JUMPIF R7 L23
     313 [-]: FASTCALL1 62 R5 L22
     314 [-]: MOVE R8 R5   
     315 [-]: GETIMPORT R7 10 [0x7B998233]
     316 [-]: CALL R7 1 1  
L22: 317 [-]: JUMPIF R7 L23
     318 [-]: MOVE R9 R6   
     319 [-]: GETIMPORT R10 81 ["EMPTY_SYMBOL"]
     320 [-]: GETIMPORT R11 84 ["ZERO_VECTOR"]
     321 [-]: GETIMPORT R12 60 ["ZERO_ROTATION"]
     322 [-]: NAMECALL R7 R5 K85 [0x3BB4F460]
     323 [-]: CALL R7 5 0  
L23: 324 [-]: JUMPXEQKN R2 K86 L27 NOT [3]
     325 [-]: GETUPVAL R7 18
     326 [-]: GETUPVAL R8 23
     327 [-]: SETTABLEKS R8 R7 K87 ["mActivationPos"]
     328 [-]: GETUPVAL R7 18
     329 [-]: MOVE R9 R5   
     330 [-]: NAMECALL R7 R7 K88 [0xEB80A36F]
     331 [-]: CALL R7 2 0  
     332 [-]: GETUPVAL R7 34
     333 [-]: LOADB R8 0   
     334 [-]: CALL R7 1 0  
     335 [-]: GETUPVAL R8 29
     336 [-]: FASTCALL1 62 R8 L24
     337 [-]: GETIMPORT R7 10 [0x7B998233]
     338 [-]: CALL R7 1 1  
L24: 339 [-]: JUMPIF R7 L25
     340 [-]: GETUPVAL R7 29
     341 [-]: LOADB R9 0   
     342 [-]: NAMECALL R7 R7 K89 [0xF433D122]
     343 [-]: CALL R7 2 0  
     344 [-]: GETUPVAL R7 29
     345 [-]: NAMECALL R7 R7 K90 [0x77AB4573]
     346 [-]: CALL R7 1 0  
     347 [-]: GETUPVAL R7 29
     348 [-]: LOADB R9 0   
     349 [-]: NAMECALL R7 R7 K91 [0x999901AF]
     350 [-]: CALL R7 2 0  
L25: 351 [-]: GETIMPORT R7 1 [0x89326C93]
     352 [-]: GETUPVAL R9 35
     353 [-]: NAMECALL R7 R7 K72 [0x46A0EBF5]
     354 [-]: CALL R7 2 1  
     355 [-]: GETIMPORT R8 12 [0xBE190284]
     356 [-]: GETUPVAL R10 36
     357 [-]: NAMECALL R8 R8 K92 [0x0F823E41]
     358 [-]: CALL R8 2 1  
     359 [-]: JUMPIF R8 L27
     360 [-]: FASTCALL1 62 R7 L26
     361 [-]: MOVE R9 R7   
     362 [-]: GETIMPORT R8 10 [0x7B998233]
     363 [-]: CALL R8 1 1  
L26: 364 [-]: JUMPIF R8 L27
     365 [-]: LOADK R10 K93 ["Enable"]
     366 [-]: NAMECALL R8 R7 K94 [0x8EB2112D]
     367 [-]: CALL R8 2 0  
L27: 368 [-]: JUMPXEQKN R2 K95 L33 NOT [4]
     369 [-]: FASTCALL1 62 R5 L28
     370 [-]: MOVE R8 R5   
     371 [-]: GETIMPORT R7 10 [0x7B998233]
     372 [-]: CALL R7 1 1  
L28: 373 [-]: JUMPIFNOT R7 L29
     374 [-]: GETIMPORT R7 1 [0x89326C93]
     375 [-]: GETUPVAL R9 28
     376 [-]: NAMECALL R7 R7 K72 [0x46A0EBF5]
     377 [-]: CALL R7 2 1  
     378 [-]: MOVE R5 R7   
L29: 379 [-]: FASTCALL1 62 R5 L30
     380 [-]: MOVE R8 R5   
     381 [-]: GETIMPORT R7 10 [0x7B998233]
     382 [-]: CALL R7 1 1  
L30: 383 [-]: JUMPIF R7 L31
     384 [-]: GETUPVAL R9 37
     385 [-]: NAMECALL R7 R5 K96 [0x0CCA925A]
     386 [-]: CALL R7 2 0  
L31: 387 [-]: GETIMPORT R7 12 [0xBE190284]
     388 [-]: GETUPVAL R9 38
     389 [-]: LOADN R10 150
     390 [-]: NAMECALL R7 R7 K97 [0x0EB34C69]
     391 [-]: CALL R7 3 1  
     392 [-]: GETIMPORT R8 12 [0xBE190284]
     393 [-]: GETUPVAL R10 36
     394 [-]: GETIMPORT R11 81 ["EMPTY_SYMBOL"]
     395 [-]: MOVE R12 R7  
     396 [-]: LOADB R13 0  
     397 [-]: NAMECALL R8 R8 K98 [0xFE23FE59]
     398 [-]: CALL R8 5 0  
     399 [-]: GETIMPORT R8 1 [0x89326C93]
     400 [-]: GETUPVAL R10 35
     401 [-]: NAMECALL R8 R8 K72 [0x46A0EBF5]
     402 [-]: CALL R8 2 1  
     403 [-]: FASTCALL1 62 R8 L32
     404 [-]: MOVE R10 R8  
     405 [-]: GETIMPORT R9 10 [0x7B998233]
     406 [-]: CALL R9 1 1  
L32: 407 [-]: JUMPIF R9 L33
     408 [-]: NAMECALL R9 R8 K99 [0xA2880940]
     409 [-]: CALL R9 1 0  
L33: 410 [-]: LOADK R6 K100 ["<p><font color=\"#"]
     411 [-]: GETIMPORT R11 103 [0xE8072DED]
     412 [-]: LOADK R12 K104 ["%X"]
     413 [-]: GETIMPORT R14 106 [0x0032441C]
     414 [-]: GETTABLEKS R13 R14 K107 ["UIColor_White"]
     415 [-]: CALL R11 2 1 
     416 [-]: MOVE R7 R11  
     417 [-]: LOADK R8 K108 ["\"><br>      "]
     418 [-]: LOADK R9 K109 ["/Lotus/Language/SolarisJobs/DynamicAmbushHackTimeLeft"]
     419 [-]: LOADK R10 K110 ["</font> %s</p>"]
     420 [-]: CONCAT R5 R6 R10
     421 [-]: SETUPVAL R5 39
     422 [-]: GETIMPORT R5 112 ["_T"]
     423 [-]: GETUPVAL R6 7
     424 [-]: SETTABLEKS R6 R5 K113 ["DynAmbushTransmissionSet"]
     425 [-]: GETIMPORT R5 112 ["_T"]
     426 [-]: LOADNIL R6   
     427 [-]: SETTABLEKS R6 R5 K114 ["DynAmbushVehicleDamageWarn"]
     428 [-]: LOADN R7 2   
     429 [-]: NAMECALL R5 R0 K115 [0xFE9DC265]
     430 [-]: CALL R5 2 0  
     431 [-]: RETURN R0 0  


; Name:            
; Defined at line: 498
; #Upvalues:       12
; #Parameters:     0
; Is_vararg:       0
; Max Stack Size:  9

       0 [-]: GETIMPORT R1 1 [0xFAE1F50F]
       1 [-]: FASTCALL1 62 R1 L0
       2 [-]: GETIMPORT R0 3 [0x7B998233]
       3 [-]: CALL R0 1 1  
L 0:   4 [-]: JUMPIF R0 L3 
       5 [-]: GETUPVAL R0 0
       6 [-]: GETUPVAL R2 1
       7 [-]: NAMECALL R2 R2 K4 [0xD1586535]
       8 [-]: CALL R2 1 -1 
       9 [-]: NAMECALL R0 R0 K5 [0xC1088746]
      10 [-]: CALL R0 -1 1 
      11 [-]: GETIMPORT R1 7 [0x89326C93]
      12 [-]: NAMECALL R1 R1 K8 [0x29EF273D]
      13 [-]: CALL R1 1 1  
      14 [-]: GETIMPORT R3 1 [0xFAE1F50F]
      15 [-]: GETUPVAL R4 3
      16 [-]: GETIMPORT R5 10 ["ZERO_ROTATION"]
      17 [-]: GETUPVAL R6 4
      18 [-]: MOVE R7 R0   
      19 [-]: NAMECALL R1 R1 K11 [0x6CD833C5]
      20 [-]: CALL R1 6 1  
      21 [-]: SETUPVAL R1 2
      22 [-]: GETUPVAL R1 5
      23 [-]: GETUPVAL R3 2
      24 [-]: NAMECALL R1 R1 K12 [0x2FB0041C]
      25 [-]: CALL R1 2 0  
      26 [-]: GETUPVAL R1 2
      27 [-]: GETUPVAL R3 6
      28 [-]: LOADB R4 1   
      29 [-]: LOADB R5 1   
      30 [-]: LOADB R6 0   
      31 [-]: NAMECALL R1 R1 K13 [0x748DF3EF]
      32 [-]: CALL R1 5 0  
      33 [-]: GETIMPORT R1 15 [0xA421AF95]
      34 [-]: CALL R1 0 1  
L 1:  35 [-]: GETUPVAL R2 2
      36 [-]: MOVE R4 R1   
      37 [-]: NAMECALL R2 R2 K16 [0x0F38BB6E]
      38 [-]: CALL R2 2 1  
      39 [-]: JUMPIF R2 L2 
      40 [-]: GETIMPORT R2 18 [0xCBD666E1]
      41 [-]: LOADN R3 0   
      42 [-]: CALL R2 1 0  
      43 [-]: JUMPBACK L1  
L 2:  44 [-]: GETUPVAL R2 2
      45 [-]: NAMECALL R2 R2 K19 [0xBB610E5B]
      46 [-]: CALL R2 1 1  
      47 [-]: NAMECALL R3 R2 K20 [0x1AC1655C]
      48 [-]: CALL R3 1 1  
      49 [-]: GETUPVAL R5 7
      50 [-]: LOADN R6 25  
      51 [-]: LOADN R7 6   
      52 [-]: LOADN R8 0   
      53 [-]: NAMECALL R3 R3 K21 [0xA383DE31]
      54 [-]: CALL R3 5 0  
      55 [-]: GETIMPORT R5 23 [0x20B7F774]
      56 [-]: NAMECALL R6 R2 K4 [0xD1586535]
      57 [-]: CALL R6 1 1  
      58 [-]: MOVE R7 R1   
      59 [-]: CALL R5 2 -1 
      60 [-]: NAMECALL R3 R2 K24 [0x70B8836C]
      61 [-]: CALL R3 -1 0 
      62 [-]: LOADB R5 1   
      63 [-]: NAMECALL R3 R2 K25 [0x069D881F]
      64 [-]: CALL R3 2 0  
      65 [-]: GETUPVAL R3 9
      66 [-]: GETIMPORT R4 27 [0x8E5D721A]
      67 [-]: MOVE R5 R2   
      68 [-]: LOADNIL R6   
      69 [-]: LOADB R7 1   
      70 [-]: CALL R3 4 1  
      71 [-]: SETUPVAL R3 8
      72 [-]: GETUPVAL R4 10
      73 [-]: GETTABLEKS R3 R4 K28 [0x9742B85B]
      74 [-]: GETUPVAL R4 11
      75 [-]: GETIMPORT R5 30 [0x0469F296]
      76 [-]: LOADK R6 K31 ["DynamicAmbush_CoilDriveSpawned"]
      77 [-]: CALL R5 1 -1 
      78 [-]: CALL R3 -1 0 
L 3:  79 [-]: RETURN R0 0  


; Name:            
; Defined at line: 522
; #Upvalues:       34
; #Parameters:     1
; Is_vararg:       0
; Max Stack Size:  13

       0 [-]: GETUPVAL R1 0
       1 [-]: MOVE R2 R0   
       2 [-]: CALL R1 1 0  
L 0:   3 [-]: NAMECALL R1 R0 K0 [0xEFE6CAD1]
       4 [-]: CALL R1 1 1  
       5 [-]: LOADN R2 4   
       6 [-]: JUMPIFNOTLT R1 R2 L31
       7 [-]: GETUPVAL R1 1
       8 [-]: NAMECALL R1 R1 K1 [0x209398C2]
       9 [-]: CALL R1 1 1  
      10 [-]: JUMPXEQKN R1 K2 L6 NOT [1]
      11 [-]: GETUPVAL R1 2
      12 [-]: JUMPIF R1 L1 
      13 [-]: LOADB R1 1   
      14 [-]: SETUPVAL R1 2
      15 [-]: GETIMPORT R1 4 [0xA421AF95]
      16 [-]: CALL R1 0 1  
      17 [-]: GETIMPORT R2 6 [0x00046924]
      18 [-]: CALL R2 0 1  
      19 [-]: GETIMPORT R3 8 [0x89326C93]
      20 [-]: GETUPVAL R6 3
      21 [-]: GETIMPORT R7 4 [0xA421AF95]
      22 [-]: LOADN R8 0   
      23 [-]: LOADN R9 10  
      24 [-]: LOADN R10 0  
      25 [-]: CALL R7 3 1  
      26 [-]: ADD R5 R6 R7 
      27 [-]: GETUPVAL R7 3
      28 [-]: GETIMPORT R8 4 [0xA421AF95]
      29 [-]: LOADN R9 0   
      30 [-]: LOADN R10 10 
      31 [-]: LOADN R11 0  
      32 [-]: CALL R8 3 1  
      33 [-]: SUB R6 R7 R8 
      34 [-]: LOADNIL R7   
      35 [-]: LOADNIL R8   
      36 [-]: LOADNIL R9   
      37 [-]: MOVE R10 R1  
      38 [-]: MOVE R11 R2  
      39 [-]: LOADB R12 1  
      40 [-]: NAMECALL R3 R3 K9 [0xDB88E2D9]
      41 [-]: CALL R3 9 0  
      42 [-]: GETIMPORT R3 12 [0x3630E649]
      43 [-]: LOADN R4 0   
      44 [-]: LOADN R5 360 
      45 [-]: CALL R3 2 1  
      46 [-]: GETIMPORT R4 14 [0x20E8CA12]
      47 [-]: MOVE R5 R2   
      48 [-]: GETIMPORT R6 6 [0x00046924]
      49 [-]: LOADN R7 0   
      50 [-]: LOADN R8 0   
      51 [-]: MOVE R9 R3   
      52 [-]: CALL R6 3 -1 
      53 [-]: CALL R4 -1 1 
      54 [-]: MOVE R2 R4   
      55 [-]: GETIMPORT R4 14 [0x20E8CA12]
      56 [-]: MOVE R5 R2   
      57 [-]: GETIMPORT R6 6 [0x00046924]
      58 [-]: LOADN R7 0   
      59 [-]: LOADN R8 90  
      60 [-]: LOADN R9 0   
      61 [-]: CALL R6 3 -1 
      62 [-]: CALL R4 -1 1 
      63 [-]: MOVE R2 R4   
      64 [-]: GETIMPORT R4 8 [0x89326C93]
      65 [-]: GETIMPORT R6 16 [0x6D85CA74]
      66 [-]: GETUPVAL R8 3
      67 [-]: GETUPVAL R9 5
      68 [-]: ADD R7 R8 R9 
      69 [-]: MOVE R8 R2   
      70 [-]: NAMECALL R4 R4 K17 [0x05909209]
      71 [-]: CALL R4 4 1  
      72 [-]: SETUPVAL R4 4
      73 [-]: GETUPVAL R4 4
      74 [-]: GETIMPORT R6 19 [0x282E65D7]
      75 [-]: GETIMPORT R7 21 ["EMPTY_SYMBOL"]
      76 [-]: NAMECALL R4 R4 K22 [0x47901F07]
      77 [-]: CALL R4 3 0  
L 1:  78 [-]: GETUPVAL R2 6
      79 [-]: GETIMPORT R3 24 [0xFFF641AF]
      80 [-]: CALL R3 0 1  
      81 [-]: ADD R1 R2 R3 
      82 [-]: SETUPVAL R1 6
      83 [-]: GETUPVAL R1 7
      84 [-]: JUMPIF R1 L5 
      85 [-]: GETUPVAL R1 6
      86 [-]: GETIMPORT R2 26 [0x0E1AF509]
      87 [-]: JUMPIFNOTLE R2 R1 L5
      88 [-]: GETIMPORT R1 8 [0x89326C93]
      89 [-]: NAMECALL R1 R1 K27 [0x8B5B1F58]
      90 [-]: CALL R1 1 1  
      91 [-]: LOADB R2 0   
      92 [-]: GETIMPORT R3 29 [0xC8802016]
      93 [-]: MOVE R4 R1   
      94 [-]: CALL R3 1 3  
      95 [-]: FORGPREP_INEXT R3 L3
L 2:  96 [-]: GETIMPORT R8 31 [0xC0DA2B81]
      97 [-]: NAMECALL R9 R7 K32 [0xD1586535]
      98 [-]: CALL R9 1 1  
      99 [-]: GETUPVAL R10 3
     100 [-]: CALL R8 2 1  
     101 [-]: GETIMPORT R10 34 [0x701A3ACB]
     102 [-]: GETIMPORT R11 34 [0x701A3ACB]
     103 [-]: MUL R9 R10 R11
     104 [-]: JUMPIFNOTLT R8 R9 L3
     105 [-]: LOADB R2 1   
     106 [-]: JUMP L4
     
L 3: 107 [-]: FORGLOOP R3 L2 2 [inext]
L 4: 108 [-]: JUMPIF R2 L5 
     109 [-]: LOADB R3 1   
     110 [-]: SETUPVAL R3 7
     111 [-]: GETUPVAL R4 8
     112 [-]: GETTABLEKS R3 R4 K35 [0x9742B85B]
     113 [-]: GETUPVAL R4 9
     114 [-]: GETIMPORT R5 37 [0x0469F296]
     115 [-]: LOADK R6 K38 ["DynamicAmbush_Reminder"]
     116 [-]: CALL R5 1 -1 
     117 [-]: CALL R3 -1 0 
L 5: 118 [-]: GETIMPORT R1 40 [0xBE190284]
     119 [-]: GETUPVAL R3 10
     120 [-]: LOADN R4 0   
     121 [-]: NAMECALL R1 R1 K41 [0x0EB34C69]
     122 [-]: CALL R1 3 1  
     123 [-]: JUMPXEQKN R1 K2 L19 NOT [1]
     124 [-]: GETIMPORT R2 43 [0xCBD666E1]
     125 [-]: LOADN R3 3   
     126 [-]: CALL R2 1 0  
     127 [-]: GETUPVAL R2 11
     128 [-]: CALL R2 0 0  
     129 [-]: GETUPVAL R2 1
     130 [-]: LOADN R4 2   
     131 [-]: NAMECALL R2 R2 K44 [0x8ABFF40E]
     132 [-]: CALL R2 2 0  
     133 [-]: JUMP L19
    
L 6: 134 [-]: GETUPVAL R1 1
     135 [-]: NAMECALL R1 R1 K1 [0x209398C2]
     136 [-]: CALL R1 1 1  
     137 [-]: JUMPXEQKN R1 K45 L11 NOT [2]
     138 [-]: GETUPVAL R2 12
     139 [-]: FASTCALL1 62 R2 L7
     140 [-]: GETIMPORT R1 47 [0x7B998233]
     141 [-]: CALL R1 1 1  
L 7: 142 [-]: JUMPIF R1 L19
     143 [-]: GETUPVAL R1 12
     144 [-]: NAMECALL R1 R1 K48 [0xBB610E5B]
     145 [-]: CALL R1 1 1  
     146 [-]: FASTCALL1 62 R1 L8
     147 [-]: MOVE R3 R1   
     148 [-]: GETIMPORT R2 47 [0x7B998233]
     149 [-]: CALL R2 1 1  
L 8: 150 [-]: JUMPIF R2 L19
     151 [-]: GETIMPORT R2 31 [0xC0DA2B81]
     152 [-]: NAMECALL R3 R1 K32 [0xD1586535]
     153 [-]: CALL R3 1 1  
     154 [-]: GETUPVAL R4 3
     155 [-]: CALL R2 2 1  
     156 [-]: LOADN R3 25  
     157 [-]: JUMPIFNOTLT R2 R3 L19
     158 [-]: GETIMPORT R2 50 ["_T"]
     159 [-]: LOADB R3 1   
     160 [-]: SETTABLEKS R3 R2 K51 ["DynAmbushVehicleDamageWarn"]
     161 [-]: GETUPVAL R3 8
     162 [-]: GETTABLEKS R2 R3 K35 [0x9742B85B]
     163 [-]: GETUPVAL R3 9
     164 [-]: GETIMPORT R4 37 [0x0469F296]
     165 [-]: LOADK R5 K52 ["DynamicAmbush_CoilDriveDisabled"]
     166 [-]: CALL R4 1 -1 
     167 [-]: CALL R2 -1 0 
     168 [-]: GETUPVAL R2 13
     169 [-]: GETUPVAL R3 3
     170 [-]: SETTABLEKS R3 R2 K53 ["mActivationPos"]
     171 [-]: GETUPVAL R2 13
     172 [-]: MOVE R4 R1   
     173 [-]: NAMECALL R2 R2 K54 [0xEB80A36F]
     174 [-]: CALL R2 2 0  
     175 [-]: GETUPVAL R2 14
     176 [-]: LOADB R3 0   
     177 [-]: CALL R2 1 0  
     178 [-]: LOADN R4 1   
     179 [-]: GETIMPORT R5 56 [0x42D2CE14]
     180 [-]: LENGTH R2 R5 
     181 [-]: LOADN R3 1   
     182 [-]: FORNPREP R2 L10
L 9: 183 [-]: GETIMPORT R8 56 [0x42D2CE14]
     184 [-]: GETTABLE R7 R8 R4
     185 [-]: GETIMPORT R8 21 ["EMPTY_SYMBOL"]
     186 [-]: GETIMPORT R9 58 ["ZERO_VECTOR"]
     187 [-]: GETIMPORT R10 60 ["ZERO_ROTATION"]
     188 [-]: GETUPVAL R11 15
     189 [-]: NAMECALL R5 R1 K22 [0x47901F07]
     190 [-]: CALL R5 6 0  
     191 [-]: FORNLOOP R2 L9
L10: 192 [-]: GETUPVAL R2 1
     193 [-]: LOADN R4 3   
     194 [-]: NAMECALL R2 R2 K44 [0x8ABFF40E]
     195 [-]: CALL R2 2 0  
     196 [-]: GETUPVAL R2 12
     197 [-]: NAMECALL R2 R2 K61 [0x4094B424]
     198 [-]: CALL R2 1 0  
     199 [-]: LOADB R4 1   
     200 [-]: NAMECALL R2 R1 K62 [0xEC1EE87F]
     201 [-]: CALL R2 2 0  
     202 [-]: GETUPVAL R2 4
     203 [-]: NAMECALL R2 R2 K63 [0xA2880940]
     204 [-]: CALL R2 1 0  
     205 [-]: GETUPVAL R2 12
     206 [-]: LOADB R4 0   
     207 [-]: NAMECALL R2 R2 K64 [0xF433D122]
     208 [-]: CALL R2 2 0  
     209 [-]: GETUPVAL R2 12
     210 [-]: NAMECALL R2 R2 K65 [0x77AB4573]
     211 [-]: CALL R2 1 0  
     212 [-]: GETUPVAL R2 12
     213 [-]: LOADB R4 0   
     214 [-]: NAMECALL R2 R2 K66 [0x999901AF]
     215 [-]: CALL R2 2 0  
     216 [-]: JUMP L19
    
L11: 217 [-]: GETUPVAL R1 1
     218 [-]: NAMECALL R1 R1 K1 [0x209398C2]
     219 [-]: CALL R1 1 1  
     220 [-]: JUMPXEQKN R1 K67 L12 NOT [3]
     221 [-]: GETIMPORT R1 40 [0xBE190284]
     222 [-]: GETUPVAL R3 16
     223 [-]: NAMECALL R1 R1 K68 [0x0F823E41]
     224 [-]: CALL R1 2 1  
     225 [-]: JUMPIFNOT R1 L19
     226 [-]: GETUPVAL R1 1
     227 [-]: LOADN R3 4   
     228 [-]: NAMECALL R1 R1 K44 [0x8ABFF40E]
     229 [-]: CALL R1 2 0  
     230 [-]: JUMP L19
    
L12: 231 [-]: GETUPVAL R1 1
     232 [-]: NAMECALL R1 R1 K1 [0x209398C2]
     233 [-]: CALL R1 1 1  
     234 [-]: JUMPXEQKN R1 K69 L19 NOT [4]
     235 [-]: GETIMPORT R1 40 [0xBE190284]
     236 [-]: GETUPVAL R3 16
     237 [-]: NAMECALL R1 R1 K70 [0xFFDDF768]
     238 [-]: CALL R1 2 1  
     239 [-]: GETUPVAL R2 17
     240 [-]: JUMPIF R2 L13
     241 [-]: LOADN R2 45  
     242 [-]: JUMPIFNOTLT R1 R2 L13
     243 [-]: GETUPVAL R3 8
     244 [-]: GETTABLEKS R2 R3 K35 [0x9742B85B]
     245 [-]: GETUPVAL R3 9
     246 [-]: GETIMPORT R4 37 [0x0469F296]
     247 [-]: LOADK R5 K71 ["DynamicAmbush_HackProgress"]
     248 [-]: CALL R4 1 -1 
     249 [-]: CALL R2 -1 0 
     250 [-]: LOADB R2 1   
     251 [-]: SETUPVAL R2 17
L13: 252 [-]: LOADNIL R2   
     253 [-]: GETUPVAL R4 12
     254 [-]: FASTCALL1 62 R4 L14
     255 [-]: GETIMPORT R3 47 [0x7B998233]
     256 [-]: CALL R3 1 1  
L14: 257 [-]: JUMPIF R3 L17
     258 [-]: GETUPVAL R3 12
     259 [-]: NAMECALL R3 R3 K48 [0xBB610E5B]
     260 [-]: CALL R3 1 1  
     261 [-]: MOVE R2 R3   
     262 [-]: FASTCALL1 62 R2 L15
     263 [-]: MOVE R4 R2   
     264 [-]: GETIMPORT R3 47 [0x7B998233]
     265 [-]: CALL R3 1 1  
L15: 266 [-]: JUMPIF R3 L17
     267 [-]: NAMECALL R4 R2 K72 [0xD2715720]
     268 [-]: CALL R4 1 1  
     269 [-]: NAMECALL R5 R2 K73 [0xB40C191A]
     270 [-]: CALL R5 1 1  
     271 [-]: DIV R3 R4 R5 
     272 [-]: LOADK R4 K74 [0.69999999999999996]
     273 [-]: JUMPIFNOTLT R3 R4 L16
     274 [-]: GETIMPORT R4 76 ["QualifiedForBountyBonus"]
     275 [-]: JUMPIFNOT R4 L17
     276 [-]: GETUPVAL R5 18
     277 [-]: GETTABLEKS R4 R5 K77 [0x37317859]
     278 [-]: LOADK R5 K78 ["/Lotus/Language/SolarisJobs/DynamicAmbushBonusObj"]
     279 [-]: CALL R4 1 0  
     280 [-]: GETIMPORT R4 50 ["_T"]
     281 [-]: LOADB R5 0   
     282 [-]: SETTABLEKS R5 R4 K75 ["QualifiedForBountyBonus"]
     283 [-]: JUMP L17
    
L16: 284 [-]: GETIMPORT R4 50 ["_T"]
     285 [-]: LOADB R5 1   
     286 [-]: SETTABLEKS R5 R4 K75 ["QualifiedForBountyBonus"]
L17: 287 [-]: LOADN R3 -1  
     288 [-]: JUMPIFNOTLT R3 R1 L19
     289 [-]: LOADN R3 0   
     290 [-]: JUMPIFNOTLE R1 R3 L19
     291 [-]: FASTCALL1 62 R2 L18
     292 [-]: MOVE R4 R2   
     293 [-]: GETIMPORT R3 47 [0x7B998233]
     294 [-]: CALL R3 1 1  
L18: 295 [-]: JUMPIF R3 L19
     296 [-]: GETUPVAL R3 1
     297 [-]: LOADN R5 5   
     298 [-]: NAMECALL R3 R3 K44 [0x8ABFF40E]
     299 [-]: CALL R3 2 0  
     300 [-]: GETUPVAL R3 19
     301 [-]: LOADN R5 4   
     302 [-]: NAMECALL R3 R3 K79 [0xFE9DC265]
     303 [-]: CALL R3 2 0  
     304 [-]: GETUPVAL R5 20
     305 [-]: NAMECALL R3 R2 K80 [0xB2532845]
     306 [-]: CALL R3 2 0  
     307 [-]: GETIMPORT R3 82 [0xFBD1CEA7]
     308 [-]: MOVE R5 R2   
     309 [-]: GETIMPORT R6 84 [0x9014786D]
     310 [-]: GETIMPORT R7 86 [0x09E8FD75]
     311 [-]: GETIMPORT R8 88 [0xEF8D33E2]
     312 [-]: NAMECALL R3 R3 K89 [0xE4C98581]
     313 [-]: CALL R3 5 0  
L19: 314 [-]: GETUPVAL R1 1
     315 [-]: NAMECALL R1 R1 K1 [0x209398C2]
     316 [-]: CALL R1 1 1  
     317 [-]: LOADN R2 2   
     318 [-]: JUMPIFNOTLE R2 R1 L23
     319 [-]: GETUPVAL R2 12
     320 [-]: FASTCALL1 62 R2 L20
     321 [-]: GETIMPORT R1 47 [0x7B998233]
     322 [-]: CALL R1 1 1  
L20: 323 [-]: JUMPIF R1 L22
     324 [-]: GETUPVAL R2 12
     325 [-]: NAMECALL R2 R2 K48 [0xBB610E5B]
     326 [-]: CALL R2 1 1  
     327 [-]: FASTCALL1 62 R2 L21
     328 [-]: GETIMPORT R1 47 [0x7B998233]
     329 [-]: CALL R1 1 1  
L21: 330 [-]: JUMPIFNOT R1 L23
L22: 331 [-]: GETUPVAL R1 1
     332 [-]: LOADN R3 6   
     333 [-]: NAMECALL R1 R1 K44 [0x8ABFF40E]
     334 [-]: CALL R1 2 0  
     335 [-]: GETUPVAL R1 19
     336 [-]: LOADN R3 5   
     337 [-]: NAMECALL R1 R1 K79 [0xFE9DC265]
     338 [-]: CALL R1 2 0  
L23: 339 [-]: GETUPVAL R1 21
     340 [-]: JUMPIF R1 L26
     341 [-]: GETUPVAL R1 1
     342 [-]: NAMECALL R1 R1 K1 [0x209398C2]
     343 [-]: CALL R1 1 1  
     344 [-]: LOADN R2 4   
     345 [-]: JUMPIFNOTLE R2 R1 L26
     346 [-]: GETUPVAL R2 12
     347 [-]: FASTCALL1 62 R2 L24
     348 [-]: GETIMPORT R1 47 [0x7B998233]
     349 [-]: CALL R1 1 1  
L24: 350 [-]: JUMPIF R1 L26
     351 [-]: GETUPVAL R2 12
     352 [-]: NAMECALL R2 R2 K48 [0xBB610E5B]
     353 [-]: CALL R2 1 1  
     354 [-]: FASTCALL1 62 R2 L25
     355 [-]: GETIMPORT R1 47 [0x7B998233]
     356 [-]: CALL R1 1 1  
L25: 357 [-]: JUMPIF R1 L26
     358 [-]: GETUPVAL R1 12
     359 [-]: NAMECALL R1 R1 K48 [0xBB610E5B]
     360 [-]: CALL R1 1 1  
     361 [-]: NAMECALL R3 R1 K72 [0xD2715720]
     362 [-]: CALL R3 1 1  
     363 [-]: NAMECALL R4 R1 K73 [0xB40C191A]
     364 [-]: CALL R4 1 1  
     365 [-]: DIV R2 R3 R4 
     366 [-]: LOADK R3 K90 [0.5]
     367 [-]: JUMPIFNOTLT R2 R3 L26
     368 [-]: LOADB R3 1   
     369 [-]: SETUPVAL R3 21
     370 [-]: GETUPVAL R4 8
     371 [-]: GETTABLEKS R3 R4 K35 [0x9742B85B]
     372 [-]: GETUPVAL R4 9
     373 [-]: GETIMPORT R5 37 [0x0469F296]
     374 [-]: LOADK R6 K91 ["DynamicAmbush_CoilDriveInjured"]
     375 [-]: CALL R5 1 -1 
     376 [-]: CALL R3 -1 0 
L26: 377 [-]: GETUPVAL R1 1
     378 [-]: NAMECALL R1 R1 K1 [0x209398C2]
     379 [-]: CALL R1 1 1  
     380 [-]: LOADN R2 3   
     381 [-]: JUMPIFNOTLE R2 R1 L27
     382 [-]: GETUPVAL R1 13
     383 [-]: GETIMPORT R3 24 [0xFFF641AF]
     384 [-]: CALL R3 0 -1 
     385 [-]: NAMECALL R1 R1 K92 [0xFAA69527]
     386 [-]: CALL R1 -1 0 
L27: 387 [-]: GETIMPORT R1 40 [0xBE190284]
     388 [-]: GETUPVAL R3 16
     389 [-]: NAMECALL R1 R1 K68 [0x0F823E41]
     390 [-]: CALL R1 2 1  
     391 [-]: JUMPIFNOT R1 L29
     392 [-]: GETIMPORT R1 40 [0xBE190284]
     393 [-]: GETUPVAL R3 16
     394 [-]: NAMECALL R1 R1 K70 [0xFFDDF768]
     395 [-]: CALL R1 2 1  
     396 [-]: GETIMPORT R2 40 [0xBE190284]
     397 [-]: GETUPVAL R4 22
     398 [-]: GETIMPORT R6 94 [0x42DCC9F5]
     399 [-]: MOVE R7 R1   
     400 [-]: LOADN R8 0   
     401 [-]: LOADN R9 150 
     402 [-]: CALL R6 3 1  
     403 [-]: FASTCALL1 12 R6 L28
     404 [-]: GETIMPORT R5 96 [0x55F27C30]
     405 [-]: CALL R5 1 1  
L28: 406 [-]: NAMECALL R2 R2 K97 [0x751F061D]
     407 [-]: CALL R2 3 0  
L29: 408 [-]: GETUPVAL R1 23
     409 [-]: GETIMPORT R3 24 [0xFFF641AF]
     410 [-]: CALL R3 0 -1 
     411 [-]: NAMECALL R1 R1 K92 [0xFAA69527]
     412 [-]: CALL R1 -1 0 
     413 [-]: GETUPVAL R1 24
     414 [-]: CALL R1 0 0  
     415 [-]: NAMECALL R1 R0 K98 [0xD9531187]
     416 [-]: CALL R1 1 1  
     417 [-]: JUMPIFNOT R1 L30
     418 [-]: GETUPVAL R2 25
     419 [-]: GETTABLEKS R1 R2 K99 [0xD712B9DB]
     420 [-]: CALL R1 0 0  
     421 [-]: LOADN R3 5   
     422 [-]: NAMECALL R1 R0 K79 [0xFE9DC265]
     423 [-]: CALL R1 2 0  
L30: 424 [-]: GETIMPORT R1 43 [0xCBD666E1]
     425 [-]: LOADN R2 0   
     426 [-]: CALL R1 1 0  
     427 [-]: JUMPBACK L0  
L31: 428 [-]: GETUPVAL R2 12
     429 [-]: FASTCALL1 62 R2 L32
     430 [-]: GETIMPORT R1 47 [0x7B998233]
     431 [-]: CALL R1 1 1  
L32: 432 [-]: JUMPIF R1 L34
     433 [-]: GETUPVAL R1 12
     434 [-]: NAMECALL R1 R1 K48 [0xBB610E5B]
     435 [-]: CALL R1 1 1  
     436 [-]: FASTCALL1 62 R1 L33
     437 [-]: MOVE R3 R1   
     438 [-]: GETIMPORT R2 47 [0x7B998233]
     439 [-]: CALL R2 1 1  
L33: 440 [-]: JUMPIF R2 L34
     441 [-]: GETIMPORT R4 37 [0x0469F296]
     442 [-]: LOADK R5 K100 ["DestroyVehicle"]
     443 [-]: CALL R4 1 1  
     444 [-]: LOADB R5 0   
     445 [-]: NAMECALL R2 R1 K101 [0xD5F7912B]
     446 [-]: CALL R2 3 0  
L34: 447 [-]: GETIMPORT R1 40 [0xBE190284]
     448 [-]: GETUPVAL R3 16
     449 [-]: NAMECALL R1 R1 K102 [0xBFC566BD]
     450 [-]: CALL R1 2 0  
     451 [-]: GETIMPORT R1 8 [0x89326C93]
     452 [-]: GETUPVAL R3 26
     453 [-]: NAMECALL R1 R1 K103 [0x46A0EBF5]
     454 [-]: CALL R1 2 1  
     455 [-]: FASTCALL1 62 R1 L35
     456 [-]: MOVE R3 R1   
     457 [-]: GETIMPORT R2 47 [0x7B998233]
     458 [-]: CALL R2 1 1  
L35: 459 [-]: JUMPIF R2 L36
     460 [-]: NAMECALL R2 R1 K63 [0xA2880940]
     461 [-]: CALL R2 1 0  
L36: 462 [-]: GETIMPORT R2 8 [0x89326C93]
     463 [-]: GETUPVAL R4 27
     464 [-]: NAMECALL R2 R2 K103 [0x46A0EBF5]
     465 [-]: CALL R2 2 1  
     466 [-]: FASTCALL1 62 R2 L37
     467 [-]: MOVE R4 R2   
     468 [-]: GETIMPORT R3 47 [0x7B998233]
     469 [-]: CALL R3 1 1  
L37: 470 [-]: JUMPIF R3 L38
     471 [-]: NAMECALL R3 R2 K63 [0xA2880940]
     472 [-]: CALL R3 1 0  
L38: 473 [-]: GETUPVAL R4 28
     474 [-]: FASTCALL1 62 R4 L39
     475 [-]: GETIMPORT R3 47 [0x7B998233]
     476 [-]: CALL R3 1 1  
L39: 477 [-]: JUMPIF R3 L40
     478 [-]: GETUPVAL R3 28
     479 [-]: NAMECALL R3 R3 K63 [0xA2880940]
     480 [-]: CALL R3 1 0  
L40: 481 [-]: GETIMPORT R3 8 [0x89326C93]
     482 [-]: GETUPVAL R5 29
     483 [-]: NAMECALL R3 R3 K103 [0x46A0EBF5]
     484 [-]: CALL R3 2 1  
     485 [-]: FASTCALL1 62 R3 L41
     486 [-]: MOVE R5 R3   
     487 [-]: GETIMPORT R4 47 [0x7B998233]
     488 [-]: CALL R4 1 1  
L41: 489 [-]: JUMPIF R4 L42
     490 [-]: NAMECALL R4 R3 K63 [0xA2880940]
     491 [-]: CALL R4 1 0  
L42: 492 [-]: GETUPVAL R5 25
     493 [-]: GETTABLEKS R4 R5 K104 [0xE69049EB]
     494 [-]: GETUPVAL R5 15
     495 [-]: CALL R4 1 0  
     496 [-]: GETUPVAL R6 30
     497 [-]: GETTABLEN R5 R6 1
     498 [-]: FASTCALL1 62 R5 L43
     499 [-]: GETIMPORT R4 47 [0x7B998233]
     500 [-]: CALL R4 1 1  
L43: 501 [-]: JUMPIF R4 L44
     502 [-]: GETIMPORT R4 106 ["RemoveHudTracker"]
     503 [-]: GETUPVAL R6 30
     504 [-]: GETTABLEN R5 R6 1
     505 [-]: CALL R4 1 0  
L44: 506 [-]: GETUPVAL R6 30
     507 [-]: GETTABLEN R5 R6 2
     508 [-]: FASTCALL1 62 R5 L45
     509 [-]: GETIMPORT R4 47 [0x7B998233]
     510 [-]: CALL R4 1 1  
L45: 511 [-]: JUMPIF R4 L46
     512 [-]: GETIMPORT R4 106 ["RemoveHudTracker"]
     513 [-]: GETUPVAL R6 30
     514 [-]: GETTABLEN R5 R6 2
     515 [-]: CALL R4 1 0  
L46: 516 [-]: GETIMPORT R4 40 [0xBE190284]
     517 [-]: GETUPVAL R6 10
     518 [-]: NAMECALL R4 R4 K107 [0xB9BFD47C]
     519 [-]: CALL R4 2 0  
     520 [-]: GETIMPORT R4 40 [0xBE190284]
     521 [-]: GETUPVAL R6 22
     522 [-]: NAMECALL R4 R4 K107 [0xB9BFD47C]
     523 [-]: CALL R4 2 0  
     524 [-]: GETIMPORT R4 50 ["_T"]
     525 [-]: LOADNIL R5   
     526 [-]: SETTABLEKS R5 R4 K108 ["DynAmbushTransmissionSet"]
     527 [-]: GETIMPORT R4 50 ["_T"]
     528 [-]: LOADNIL R5   
     529 [-]: SETTABLEKS R5 R4 K51 ["DynAmbushVehicleDamageWarn"]
     530 [-]: GETUPVAL R4 15
     531 [-]: GETIMPORT R6 37 [0x0469F296]
     532 [-]: LOADK R7 K109 ["OnAgentRegistered"]
     533 [-]: CALL R6 1 -1 
     534 [-]: NAMECALL R4 R4 K110 [0x11D6DE31]
     535 [-]: CALL R4 -1 0 
     536 [-]: GETUPVAL R4 19
     537 [-]: GETUPVAL R6 31
     538 [-]: NAMECALL R4 R4 K111 [0x3D412E0D]
     539 [-]: CALL R4 2 0  
     540 [-]: GETUPVAL R4 19
     541 [-]: GETUPVAL R6 32
     542 [-]: NAMECALL R4 R4 K112 [0x136A027D]
     543 [-]: CALL R4 2 0  
     544 [-]: GETUPVAL R5 33
     545 [-]: FASTCALL1 62 R5 L47
     546 [-]: GETIMPORT R4 47 [0x7B998233]
     547 [-]: CALL R4 1 1  
L47: 548 [-]: JUMPIF R4 L48
     549 [-]: GETUPVAL R4 33
     550 [-]: NAMECALL R4 R4 K63 [0xA2880940]
     551 [-]: CALL R4 1 0  
L48: 552 [-]: GETIMPORT R4 43 [0xCBD666E1]
     553 [-]: LOADN R5 2   
     554 [-]: CALL R4 1 0  
     555 [-]: GETUPVAL R5 18
     556 [-]: GETTABLEKS R4 R5 K113 [0xDC3B2033]
     557 [-]: CALL R4 0 0  
     558 [-]: GETUPVAL R5 18
     559 [-]: GETTABLEKS R4 R5 K114 [0xF94B7537]
     560 [-]: CALL R4 0 0  
     561 [-]: GETUPVAL R5 18
     562 [-]: GETTABLEKS R4 R5 K115 [0xBD3CE95D]
     563 [-]: CALL R4 0 0  
     564 [-]: GETUPVAL R5 18
     565 [-]: GETTABLEKS R4 R5 K116 [0xF7EBDDC8]
     566 [-]: CALL R4 0 0  
     567 [-]: GETUPVAL R5 18
     568 [-]: GETTABLEKS R4 R5 K117 [0x18DD08AC]
     569 [-]: CALL R4 0 0  
     570 [-]: GETUPVAL R5 18
     571 [-]: GETTABLEKS R4 R5 K118 [0xEDF59000]
     572 [-]: CALL R4 0 0  
     573 [-]: RETURN R0 0  


; Name:            
; Defined at line: 711
; #Upvalues:       1
; #Parameters:     1
; Is_vararg:       0
; Max Stack Size:  5

       0 [-]: LOADK R2 K0 ["Killed"]
       1 [-]: NAMECALL R3 R0 K1 [0xE223E2B1]
       2 [-]: CALL R3 1 1  
       3 [-]: CONCAT R1 R2 R3
       4 [-]: NAMECALL R1 R0 K2 [0x22DA1852]
       5 [-]: CALL R1 1 1  
       6 [-]: GETUPVAL R2 0
       7 [-]: JUMPIFNOTEQ R1 R2 L0
L 0:   8 [-]: RETURN R0 0  


; Name:            
; Defined at line: 717
; #Upvalues:       1
; #Parameters:     1
; Is_vararg:       0
; Max Stack Size:  6

       0 [-]: GETIMPORT R1 1 [0x89326C93]
       1 [-]: GETUPVAL R3 0
       2 [-]: NAMECALL R1 R1 K2 [0x46A0EBF5]
       3 [-]: CALL R1 2 1  
       4 [-]: FASTCALL1 62 R1 L0
       5 [-]: MOVE R3 R1   
       6 [-]: GETIMPORT R2 4 [0x7B998233]
       7 [-]: CALL R2 1 1  
L 0:   8 [-]: JUMPIF R2 L1 
       9 [-]: MOVE R4 R1   
      10 [-]: NAMECALL R2 R0 K5 [0xA64A1F4A]
      11 [-]: CALL R2 2 0  
L 1:  12 [-]: LOADK R3 K6 ["Registered"]
      13 [-]: NAMECALL R4 R0 K7 [0xBB610E5B]
      14 [-]: CALL R4 1 1  
      15 [-]: NAMECALL R4 R4 K8 [0xE223E2B1]
      16 [-]: CALL R4 1 1  
      17 [-]: CONCAT R2 R3 R4
      18 [-]: GETIMPORT R2 10 [0x11A19C5E]
      19 [-]: NAMECALL R3 R0 K7 [0xBB610E5B]
      20 [-]: CALL R3 1 1  
      21 [-]: LOADK R4 K11 ["OnKilled"]
      22 [-]: CALL R2 2 0  
      23 [-]: RETURN R0 0  


; Name:            
; Defined at line: 726
; #Upvalues:       1
; #Parameters:     0
; Is_vararg:       0
; Max Stack Size:  2

       0 [-]: GETIMPORT R0 1 [0x89326C93]
       1 [-]: NAMECALL R0 R0 K2 [0x8B5B1F58]
       2 [-]: CALL R0 1 1  
       3 [-]: SETUPVAL R0 0
       4 [-]: RETURN R0 0  


; Name:            
; Defined at line: 730
; #Upvalues:       2
; #Parameters:     0
; Is_vararg:       0
; Max Stack Size:  3

       0 [-]: GETUPVAL R1 0
       1 [-]: GETTABLEKS R0 R1 K0 [0x7E8A976A]
       2 [-]: GETUPVAL R1 1
       3 [-]: LOADB R2 1   
       4 [-]: CALL R0 2 0  
       5 [-]: RETURN R0 0  


; Name:            
; Defined at line: 734
; #Upvalues:       2
; #Parameters:     0
; Is_vararg:       0
; Max Stack Size:  3

       0 [-]: GETUPVAL R1 0
       1 [-]: GETTABLEKS R0 R1 K0 [0x7E8A976A]
       2 [-]: GETUPVAL R1 1
       3 [-]: LOADB R2 0   
       4 [-]: CALL R0 2 0  
       5 [-]: RETURN R0 0  


; Name:            
; Defined at line: 738
; #Upvalues:       2
; #Parameters:     1
; Is_vararg:       0
; Max Stack Size:  9

       0 [-]: GETIMPORT R1 1 [0xCBD666E1]
       1 [-]: LOADN R2 10  
       2 [-]: CALL R1 1 0  
       3 [-]: FASTCALL1 62 R0 L0
       4 [-]: MOVE R2 R0   
       5 [-]: GETIMPORT R1 3 [0x7B998233]
       6 [-]: CALL R1 1 1  
L 0:   7 [-]: JUMPIF R1 L3 
       8 [-]: NAMECALL R1 R0 K4 [0x1AC1655C]
       9 [-]: CALL R1 1 1  
      10 [-]: GETUPVAL R3 0
      11 [-]: NAMECALL R1 R1 K5 [0x8E3E343E]
      12 [-]: CALL R1 2 0  
      13 [-]: GETIMPORT R3 7 [0x9014786D]
      14 [-]: NAMECALL R1 R0 K8 [0x0CCA925A]
      15 [-]: CALL R1 2 0  
      16 [-]: NAMECALL R1 R0 K9 [0xFB3BBA96]
      17 [-]: CALL R1 1 0  
      18 [-]: GETIMPORT R1 11 [0x89326C93]
      19 [-]: GETUPVAL R3 1
      20 [-]: NAMECALL R1 R1 K12 [0xC7FCADA9]
      21 [-]: CALL R1 2 1  
      22 [-]: GETIMPORT R2 14 [0xCFC01047]
      23 [-]: MOVE R3 R1   
      24 [-]: CALL R2 1 3  
      25 [-]: FORGPREP_NEXT R2 L2
L 1:  26 [-]: NAMECALL R7 R6 K15 [0xA2880940]
      27 [-]: CALL R7 1 0  
L 2:  28 [-]: FORGLOOP R2 L1 2
L 3:  29 [-]: RETURN R0 0  


; Name:            
; Defined at line: 754
; #Upvalues:       3
; #Parameters:     1
; Is_vararg:       0
; Max Stack Size:  10

       0 [-]: NAMECALL R1 R0 K0 [0x2B54251B]
       1 [-]: CALL R1 1 1  
       2 [-]: FASTCALL1 62 R1 L0
       3 [-]: MOVE R3 R1   
       4 [-]: GETIMPORT R2 2 [0x7B998233]
       5 [-]: CALL R2 1 1  
L 0:   6 [-]: JUMPIFNOT R2 L1
       7 [-]: RETURN R0 0  
L 1:   8 [-]: GETUPVAL R3 0
       9 [-]: GETTABLEKS R2 R3 K3 [0x9742B85B]
      10 [-]: GETIMPORT R3 6 ["DynAmbushTransmissionSet"]
      11 [-]: GETIMPORT R4 8 [0x0469F296]
      12 [-]: LOADK R5 K9 ["DynamicAmbush_TrapActivated"]
      13 [-]: CALL R4 1 -1 
      14 [-]: CALL R2 -1 0 
      15 [-]: GETUPVAL R3 1
      16 [-]: GETTABLEKS R2 R3 K10 [0xA1DF01D6]
      17 [-]: LOADK R3 K11 ["/Lotus/Language/SolarisJobs/DynamicAmbushWaitForTrapObj"]
      18 [-]: GETUPVAL R5 1
      19 [-]: GETTABLEKS R4 R5 K12 ["GENERIC_ICON"]
      20 [-]: CALL R2 2 0  
      21 [-]: GETIMPORT R4 14 [0x657F4DA9]
      22 [-]: LOADB R5 1   
      23 [-]: LOADB R6 0   
      24 [-]: LOADN R7 0   
      25 [-]: GETIMPORT R8 16 ["EMPTY_SYMBOL"]
      26 [-]: LOADN R9 1   
      27 [-]: NAMECALL R2 R1 K17 [0x5D985C7E]
      28 [-]: CALL R2 7 0  
      29 [-]: GETIMPORT R4 19 [0x91BD67D3]
      30 [-]: NAMECALL R2 R1 K20 [0x4C91B5D8]
      31 [-]: CALL R2 2 0  
      32 [-]: GETIMPORT R4 22 [0x2B059C63]
      33 [-]: NAMECALL R2 R1 K23 [0xC9F6A7D7]
      34 [-]: CALL R2 2 1  
      35 [-]: FASTCALL1 62 R2 L2
      36 [-]: MOVE R4 R2   
      37 [-]: GETIMPORT R3 2 [0x7B998233]
      38 [-]: CALL R3 1 1  
L 2:  39 [-]: JUMPIF R3 L3 
      40 [-]: NAMECALL R3 R2 K24 [0x383D2E7D]
      41 [-]: CALL R3 1 0  
L 3:  42 [-]: GETIMPORT R3 26 [0xBE190284]
      43 [-]: GETUPVAL R5 2
      44 [-]: LOADN R6 1   
      45 [-]: NAMECALL R3 R3 K27 [0x751F061D]
      46 [-]: CALL R3 3 0  
      47 [-]: RETURN R0 0  


; Name:            
; Defined at line: 772
; #Upvalues:       5
; #Parameters:     3
; Is_vararg:       0
; Max Stack Size:  12

       0 [-]: FASTCALL1 62 R0 L0
       1 [-]: MOVE R4 R0   
       2 [-]: GETIMPORT R3 1 [0x7B998233]
       3 [-]: CALL R3 1 1  
L 0:   4 [-]: JUMPIFNOT R3 L1
       5 [-]: RETURN R0 0  
L 1:   6 [-]: NAMECALL R4 R0 K2 [0xFA9E477F]
       7 [-]: CALL R4 1 1  
       8 [-]: FASTCALL1 62 R4 L2
       9 [-]: GETIMPORT R3 1 [0x7B998233]
      10 [-]: CALL R3 1 1  
L 2:  11 [-]: JUMPIF R3 L3 
      12 [-]: LOADN R1 1   
L 3:  13 [-]: JUMPXEQKNIL R1 L4 NOT
      14 [-]: LOADN R1 1   
L 4:  15 [-]: JUMPXEQKN R1 K3 L12 NOT [1]
      16 [-]: GETIMPORT R3 5 [0x89326C93]
      17 [-]: GETUPVAL R5 0
      18 [-]: NAMECALL R3 R3 K6 [0x46A0EBF5]
      19 [-]: CALL R3 2 1  
      20 [-]: FASTCALL1 62 R3 L5
      21 [-]: MOVE R5 R3   
      22 [-]: GETIMPORT R4 1 [0x7B998233]
      23 [-]: CALL R4 1 1  
L 5:  24 [-]: JUMPIF R4 L7 
      25 [-]: LOADN R6 1   
      26 [-]: GETIMPORT R7 8 [0x226934B5]
      27 [-]: LENGTH R4 R7 
      28 [-]: LOADN R5 1   
      29 [-]: FORNPREP R4 L7
L 6:  30 [-]: SUBK R9 R6 K3 [1]
      31 [-]: GETIMPORT R11 8 [0x226934B5]
      32 [-]: GETTABLE R10 R11 R6
      33 [-]: NAMECALL R7 R3 K9 [0xCDDC3ABB]
      34 [-]: CALL R7 3 0  
      35 [-]: FORNLOOP R4 L6
L 7:  36 [-]: GETIMPORT R4 5 [0x89326C93]
      37 [-]: NAMECALL R4 R4 K10 [0x18D05D30]
      38 [-]: CALL R4 1 1  
      39 [-]: JUMPIFNOT R4 L12
      40 [-]: GETIMPORT R4 5 [0x89326C93]
      41 [-]: GETUPVAL R6 1
      42 [-]: NAMECALL R4 R4 K6 [0x46A0EBF5]
      43 [-]: CALL R4 2 1  
      44 [-]: FASTCALL1 62 R4 L8
      45 [-]: MOVE R6 R4   
      46 [-]: GETIMPORT R5 1 [0x7B998233]
      47 [-]: CALL R5 1 1  
L 8:  48 [-]: JUMPIF R5 L9 
      49 [-]: GETIMPORT R7 12 [0x5FEE017F]
      50 [-]: LOADB R8 0   
      51 [-]: NAMECALL R5 R4 K13 [0x659D451F]
      52 [-]: CALL R5 3 0  
      53 [-]: GETUPVAL R7 2
      54 [-]: NAMECALL R5 R4 K14 [0x0CCA925A]
      55 [-]: CALL R5 2 0  
      56 [-]: LOADB R7 0   
      57 [-]: NAMECALL R5 R4 K15 [0x069D881F]
      58 [-]: CALL R5 2 0  
      59 [-]: NAMECALL R5 R4 K16 [0x1AC1655C]
      60 [-]: CALL R5 1 1  
      61 [-]: GETUPVAL R7 3
      62 [-]: NAMECALL R5 R5 K17 [0x8E3E343E]
      63 [-]: CALL R5 2 0  
L 9:  64 [-]: FASTCALL1 62 R2 L10
      65 [-]: MOVE R6 R2   
      66 [-]: GETIMPORT R5 1 [0x7B998233]
      67 [-]: CALL R5 1 1  
L10:  68 [-]: JUMPIF R5 L11
      69 [-]: NAMECALL R5 R2 K18 [0xA2880940]
      70 [-]: CALL R5 1 0  
L11:  71 [-]: GETIMPORT R5 20 [0xBE190284]
      72 [-]: GETUPVAL R7 4
      73 [-]: GETIMPORT R8 22 ["EMPTY_SYMBOL"]
      74 [-]: LOADN R9 150 
      75 [-]: LOADB R10 0  
      76 [-]: NAMECALL R5 R5 K23 [0xFE23FE59]
      77 [-]: CALL R5 5 0  
L12:  78 [-]: RETURN R0 0  


; Name:            
; Defined at line: 812
; #Upvalues:       2
; #Parameters:     1
; Is_vararg:       0
; Max Stack Size:  5

       0 [-]: GETIMPORT R2 2 ["DynAmbushVehicleDamageWarn"]
       1 [-]: FASTCALL1 62 R2 L0
       2 [-]: GETIMPORT R1 4 [0x7B998233]
       3 [-]: CALL R1 1 1  
L 0:   4 [-]: JUMPIF R1 L1 
       5 [-]: GETIMPORT R1 2 ["DynAmbushVehicleDamageWarn"]
       6 [-]: JUMPIF R1 L2 
L 1:   7 [-]: NAMECALL R1 R0 K5 [0x808B79E6]
       8 [-]: CALL R1 1 1  
       9 [-]: GETUPVAL R2 0
      10 [-]: JUMPIFEQ R1 R2 L2
      11 [-]: GETUPVAL R2 1
      12 [-]: GETTABLEKS R1 R2 K6 [0x9742B85B]
      13 [-]: GETIMPORT R2 8 ["DynAmbushTransmissionSet"]
      14 [-]: GETIMPORT R3 10 [0x0469F296]
      15 [-]: LOADK R4 K11 ["DynamicAmbush_CoilDriveDamage"]
      16 [-]: CALL R3 1 -1 
      17 [-]: CALL R1 -1 0 
      18 [-]: GETIMPORT R1 12 ["_T"]
      19 [-]: LOADB R2 1   
      20 [-]: SETTABLEKS R2 R1 K1 ["DynAmbushVehicleDamageWarn"]
L 2:  21 [-]: RETURN R0 0  



