; Name:            
; Defined at line: 1
; #Upvalues:       0
; #Parameters:     0
; Is_vararg:       1
; Max Stack Size:  44

       1 [-]: GETIMPORT R0 1; var0 = 0x2D0FAD09
       2 [-]: LOADK R1 K2  ; var1 = "Lotus.Scripts.Libs.LandscapeLib"
       3 [-]: CALL R0 2 2  ; var0 = var0(var1)
       4 [-]: GETIMPORT R1 1; var1 = 0x2D0FAD09
       5 [-]: LOADK R2 K3  ; var2 = "Lotus.Scripts.Libs.TransmissionSet"
       6 [-]: CALL R1 2 2  ; var1 = var1(var2)
       7 [-]: GETIMPORT R2 1; var2 = 0x2D0FAD09
       8 [-]: LOADK R3 K4  ; var3 = "Lotus.Interface.Libs.TimerMgr"
       9 [-]: CALL R2 2 2  ; var2 = var2(var3)
      10 [-]: GETIMPORT R3 1; var3 = 0x2D0FAD09
      11 [-]: LOADK R4 K5  ; var4 = "Lotus.Scripts.Libs.ObjectiveText"
      12 [-]: CALL R3 2 2  ; var3 = var3(var4)
      13 [-]: GETIMPORT R4 1; var4 = 0x2D0FAD09
      14 [-]: LOADK R5 K6  ; var5 = "EE.Interface.Utilities"
      15 [-]: CALL R4 2 2  ; var4 = var4(var5)
      16 [-]: GETIMPORT R5 1; var5 = 0x2D0FAD09
      17 [-]: LOADK R6 K7  ; var6 = "Lotus.Scripts.Libs.StoryLib"
      18 [-]: CALL R5 2 2  ; var5 = var5(var6)
      19 [-]: GETIMPORT R6 9; var6 = 0x88EFC25E
      20 [-]: LOADK R7 K10 ; var7 = "/Lotus/Types/Game/MarkerInfos/DefendMarkerInfo"
      21 [-]: CALL R6 2 2  ; var6 = var6(var7)
      22 [-]: GETIMPORT R7 9; var7 = 0x88EFC25E
      23 [-]: LOADK R8 K11 ; var8 = "/Lotus/Types/Game/MarkerInfos/KillMarkerLongRange"
      24 [-]: CALL R7 2 2  ; var7 = var7(var8)
      25 [-]: GETIMPORT R8 13; var8 = 0x7ED0A956
      26 [-]: LOADK R9 K14 ; var9 = "/Lotus/Types/Keys/SolarisQuest/SolarisQuestKeyChain"
      27 [-]: CALL R8 2 2  ; var8 = var8(var9)
      28 [-]: GETIMPORT R9 13; var9 = 0x7ED0A956
      29 [-]: LOADK R10 K15; var10 = "/Lotus/Types/PickUps/SolarisDatamassPickup"
      30 [-]: CALL R9 2 2  ; var9 = var9(var10)
      31 [-]: GETIMPORT R10 17; var10 = 0x0469F296
      32 [-]: LOADK R11 K18; var11 = "MISSION_TIME"
      33 [-]: CALL R10 2 2 ; var10 = var10(var11)
      34 [-]: GETIMPORT R11 17; var11 = 0x0469F296
      35 [-]: LOADK R12 K19; var12 = "REINFORCEMENTS_CALLED"
      36 [-]: CALL R11 2 2 ; var11 = var11(var12)
      37 [-]: GETIMPORT R12 17; var12 = 0x0469F296
      38 [-]: LOADK R13 K20; var13 = "SOLARIS_ENEMIES_TOTAL"
      39 [-]: CALL R12 2 2 ; var12 = var12(var13)
      40 [-]: GETIMPORT R13 17; var13 = 0x0469F296
      41 [-]: LOADK R14 K21; var14 = "SOLARIS_ENEMIES_KILLED"
      42 [-]: CALL R13 2 2 ; var13 = var13(var14)
      43 [-]: GETIMPORT R14 17; var14 = 0x0469F296
      44 [-]: LOADK R15 K22; var15 = "SolarisDefendDM"
      45 [-]: CALL R14 2 2 ; var14 = var14(var15)
      46 [-]: GETIMPORT R15 17; var15 = 0x0469F296
      47 [-]: LOADK R16 K23; var16 = "SolarisOccupied"
      48 [-]: CALL R15 2 2 ; var15 = var15(var16)
      49 [-]: LOADNIL R16  ; var16 = nil
      50 [-]: LOADNIL R17  ; var17 = nil
      51 [-]: LOADNIL R18  ; var18 = nil
      52 [-]: LOADNIL R19  ; var19 = nil
      53 [-]: LOADN R20 0  ; var20 = 0
      54 [-]: LOADNIL R21  ; var21 = nil
      55 [-]: LOADNIL R22  ; var22 = nil
      56 [-]: LOADNIL R23  ; var23 = nil
      57 [-]: LOADNIL R24  ; var24 = nil
      58 [-]: LOADNIL R25  ; var25 = nil
      59 [-]: LOADN R26 30 ; var26 = 30
      60 [-]: NEWTABLE R27 0 0; var27 = {}
      61 [-]: LOADNIL R28  ; var28 = nil
      62 [-]: NEWTABLE R29 0 0; var29 = {}
      63 [-]: LOADNIL R30  ; var30 = nil
      64 [-]: LOADNIL R31  ; var31 = nil
      65 [-]: LOADNIL R32  ; var32 = nil
      66 [-]: LOADNIL R33  ; var33 = nil
      67 [-]: LOADNIL R34  ; var34 = nil
      68 [-]: LOADNIL R35  ; var35 = nil
      69 [-]: LOADNIL R36  ; var36 = nil
      70 [-]: DUPCLOSURE R37 K24; 
      71 [-]: NEWCLOSURE R38 P1; 
      72 [-]: CAPTURE REF R26; 
      73 [-]: CAPTURE REF R17; 
      74 [-]: CAPTURE REF R19; 
      75 [-]: CAPTURE REF R18; 
      76 [-]: CAPTURE REF R28; 
      77 [-]: CAPTURE VAL R27; 
      78 [-]: NEWCLOSURE R39 P2; 
      79 [-]: CAPTURE REF R19; 
      80 [-]: NEWCLOSURE R40 P3; 
      81 [-]: CAPTURE REF R34; 
      82 [-]: CAPTURE VAL R3; 
      83 [-]: CAPTURE VAL R1; 
      84 [-]: CAPTURE REF R22; 
      85 [-]: CAPTURE REF R21; 
      86 [-]: CAPTURE REF R28; 
      87 [-]: CAPTURE REF R33; 
      88 [-]: CAPTURE REF R17; 
      89 [-]: CAPTURE VAL R14; 
      90 [-]: CAPTURE REF R23; 
      91 [-]: CAPTURE VAL R6; 
      92 [-]: CAPTURE REF R18; 
      93 [-]: CAPTURE REF R35; 
      94 [-]: CAPTURE REF R36; 
      95 [-]: CAPTURE VAL R39; 
      96 [-]: CAPTURE VAL R7; 
      97 [-]: CAPTURE REF R16; 
      98 [-]: CAPTURE VAL R12; 
      99 [-]: CAPTURE REF R32; 
     100 [-]: CAPTURE VAL R15; 
     101 [-]: CAPTURE REF R31; 
     102 [-]: CAPTURE REF R30; 
     103 [-]: CAPTURE VAL R0; 
     104 [-]: CAPTURE REF R19; 
     105 [-]: NEWCLOSURE R41 P4; 
     106 [-]: CAPTURE REF R17; 
     107 [-]: CAPTURE REF R16; 
     108 [-]: CAPTURE REF R18; 
     109 [-]: CAPTURE REF R21; 
     110 [-]: CAPTURE REF R31; 
     111 [-]: CAPTURE REF R19; 
     112 [-]: CAPTURE REF R20; 
     113 [-]: CAPTURE REF R22; 
     114 [-]: CAPTURE REF R29; 
     115 [-]: CAPTURE REF R30; 
     116 [-]: CAPTURE REF R35; 
     117 [-]: CAPTURE REF R32; 
     118 [-]: CAPTURE VAL R15; 
     119 [-]: CAPTURE REF R24; 
     120 [-]: CAPTURE VAL R0; 
     121 [-]: CAPTURE REF R34; 
     122 [-]: CAPTURE VAL R40; 
     123 [-]: CAPTURE VAL R10; 
     124 [-]: CAPTURE VAL R11; 
     125 [-]: CAPTURE VAL R12; 
     126 [-]: CAPTURE VAL R13; 
     127 [-]: CAPTURE REF R25; 
     128 [-]: CAPTURE VAL R2; 
     129 [-]: CAPTURE REF R33; 
     130 [-]: CAPTURE REF R28; 
     131 [-]: CAPTURE VAL R4; 
     132 [-]: NEWCLOSURE R42 P5; 
     133 [-]: CAPTURE VAL R41; 
     134 [-]: CAPTURE REF R34; 
     135 [-]: CAPTURE REF R24; 
     136 [-]: CAPTURE VAL R38; 
     137 [-]: CAPTURE REF R28; 
     138 [-]: CAPTURE VAL R3; 
     139 [-]: CAPTURE REF R16; 
     140 [-]: CAPTURE VAL R10; 
     141 [-]: CAPTURE REF R17; 
     142 [-]: CAPTURE VAL R1; 
     143 [-]: CAPTURE REF R22; 
     144 [-]: CAPTURE REF R33; 
     145 [-]: CAPTURE VAL R13; 
     146 [-]: CAPTURE VAL R12; 
     147 [-]: CAPTURE REF R36; 
     148 [-]: CAPTURE REF R25; 
     149 [-]: CAPTURE REF R18; 
     150 [-]: SETGLOBAL R42 K25; "DefendStart" = var42
     151 [-]: NEWCLOSURE R42 P6; 
     152 [-]: CAPTURE REF R29; 
     153 [-]: SETGLOBAL R42 K26; "OnPlayersChanged" = var42
     154 [-]: DUPCLOSURE R42 K27; 
     155 [-]: CAPTURE VAL R12; 
     156 [-]: CAPTURE VAL R13; 
     157 [-]: CAPTURE VAL R3; 
     158 [-]: SETGLOBAL R42 K28; "OnKilled" = var42
     159 [-]: NEWCLOSURE R42 P8; 
     160 [-]: CAPTURE REF R18; 
     161 [-]: SETGLOBAL R42 K29; "OnAgentRegistered" = var42
     162 [-]: NEWCLOSURE R42 P9; 
     163 [-]: CAPTURE VAL R0; 
     164 [-]: CAPTURE REF R18; 
     165 [-]: SETGLOBAL R42 K30; "PlayersLeaving" = var42
     166 [-]: NEWCLOSURE R42 P10; 
     167 [-]: CAPTURE VAL R0; 
     168 [-]: CAPTURE REF R18; 
     169 [-]: SETGLOBAL R42 K31; "PlayersReturning" = var42
     170 [-]: DUPCLOSURE R42 K32; 
     171 [-]: SETGLOBAL R42 K33; "StartCapture" = var42
     172 [-]: DUPCLOSURE R42 K34; 
     173 [-]: DUPCLOSURE R43 K35; 
     174 [-]: CAPTURE VAL R5; 
     175 [-]: CAPTURE VAL R8; 
     176 [-]: CAPTURE VAL R0; 
     177 [-]: CAPTURE VAL R42; 
     178 [-]: CAPTURE VAL R9; 
     179 [-]: SETGLOBAL R43 K36; "VenusCampBeacon" = var43
     180 [-]: DUPCLOSURE R43 K37; 
     181 [-]: CAPTURE VAL R1; 
     182 [-]: SETGLOBAL R43 K38; "DataMassPickedUp" = var43
     183 [-]: CLOSEUPVALS R16; 
     184 [-]: RETURN R0 0  ; 


; Name:            
; Defined at line: 70
; #Upvalues:       0
; #Parameters:     1
; Is_vararg:       0
; Max Stack Size:  6

       0 [-]: LOADN R2 20  ; var2 = 20
       1 [-]: LOADN R5 15  ; var5 = 15
       2 [-]: MUL R4 R5 R0 ; var4 = var5 * var0
       3 [-]: DIVK R3 R4 K0; var3 = var4 / 150
       4 [-]: SUB R1 R2 R3 ; var1 = var2 - var3
       5 [-]: RETURN R1 1  ; 


; Name:            
; Defined at line: 74
; #Upvalues:       6
; #Parameters:     0
; Is_vararg:       0
; Max Stack Size:  8

       0 [-]: GETUPVAL R0 0; var0 = upvalues[0]
       1 [-]: LOADN R1 0   ; var1 = 0
       2 [-]: JUMPIFNOTLE R0 R1 L3; goto L3 if var0 > var65543
       3 [-]: GETUPVAL R0 1; var0 = upvalues[1]
       4 [-]: GETUPVAL R2 2; var2 = upvalues[2]
       5 [-]: LOADN R3 0   ; var3 = 0
       6 [-]: LOADN R4 70  ; var4 = 70
       7 [-]: LOADN R5 2   ; var5 = 2
       8 [-]: LOADN R6 2   ; var6 = 2
       9 [-]: GETUPVAL R7 3; var7 = upvalues[3]
      10 [-]: NAMECALL R0 R0 K0; var1 = var0; var0 = var0[0xFA25307F]
      11 [-]: CALL R0 8 2  ; var0 = var0(var1, var2, var3, var4, var5, var6, var7)
      12 [-]: FASTCALL1 62 R0 L0; 
      13 [-]: MOVE R2 R0   ; var2 = var0
      14 [-]: GETIMPORT R1 2; var1 = 0x7B998233
      15 [-]: CALL R1 2 2  ; var1 = var1(var2)
L 0:  16 [-]: JUMPIFNOT R1 L1; goto L1 if not var1
      17 [-]: RETURN R0 0  ; 
L 1:  18 [-]: LOADN R3 150 ; var3 = 150
      19 [-]: GETUPVAL R4 4; var4 = upvalues[4]
      20 [-]: SUB R2 R3 R4 ; var2 = var3 - var4
      21 [-]: LOADN R3 20  ; var3 = 20
      22 [-]: LOADN R6 15  ; var6 = 15
      23 [-]: MUL R5 R6 R2 ; var5 = var6 * var2
      24 [-]: DIVK R4 R5 K3; var4 = var5 / 150
      25 [-]: SUB R1 R3 R4 ; var1 = var3 - var4
      26 [-]: SETUPVAL R1 0; upvalues[1] = var0
      27 [-]: GETUPVAL R2 5; var2 = upvalues[5]
      28 [-]: FASTCALL2 52 R2 R0 L2; 
      29 [-]: MOVE R3 R0   ; var3 = var0
      30 [-]: GETIMPORT R1 6; var1 = 0x33BDD652[0x23D5322F]
      31 [-]: CALL R1 3 1  ; var1(var2, var3)
L 2:  32 [-]: RETURN R0 0  ; 
L 3:  33 [-]: GETUPVAL R1 5; var1 = upvalues[5]
      34 [-]: LENGTH R0 R1 ; var0 = #var1
      35 [-]: LOADN R1 1   ; var1 = 1
      36 [-]: JUMPIFNOTLT R0 R1 L4; goto L4 if var0 >= var263
      37 [-]: GETUPVAL R1 0; var1 = upvalues[0]
      38 [-]: GETIMPORT R2 8; var2 = 0xFFF641AF
      39 [-]: CALL R2 1 2  ; var2 = var2()
      40 [-]: SUB R0 R1 R2 ; var0 = var1 - var2
      41 [-]: SETUPVAL R0 0; upvalues[0] = var0
      42 [-]: RETURN R0 0  ; 
L 4:  43 [-]: GETUPVAL R3 5; var3 = upvalues[5]
      44 [-]: LENGTH R2 R3 ; var2 = #var3
      45 [-]: LOADN R0 1   ; var0 = 1
      46 [-]: LOADN R1 -1  ; var1 = -1
      47 [-]: FORNPREP R0 L9; nforprep start - [escape at L9] -- var0 = iterator
L 5:  48 [-]: GETUPVAL R5 5; var5 = upvalues[5]
      49 [-]: GETTABLE R4 R5 R2; var4 = var5[var2]
      50 [-]: FASTCALL1 62 R4 L6; 
      51 [-]: GETIMPORT R3 2; var3 = 0x7B998233
      52 [-]: CALL R3 2 2  ; var3 = var3(var4)
L 6:  53 [-]: JUMPIF R3 L7 ; goto L7 if var3
      54 [-]: GETUPVAL R4 5; var4 = upvalues[5]
      55 [-]: GETTABLE R3 R4 R2; var3 = var4[var2]
      56 [-]: NAMECALL R3 R3 K9; var4 = var3; var3 = var3[0xEFE6CAD1]
      57 [-]: CALL R3 2 2  ; var3 = var3(var4)
      58 [-]: LOADN R4 3   ; var4 = 3
      59 [-]: JUMPIFNOTEQ R3 R4 L8; goto L8 if var3 ~= var721742
L 7:  60 [-]: GETIMPORT R3 11; var3 = 0x33BDD652[0x9C1F3B5A]
      61 [-]: GETUPVAL R4 5; var4 = upvalues[5]
      62 [-]: MOVE R5 R2   ; var5 = var2
      63 [-]: CALL R3 3 1  ; var3(var4, var5)
L 8:  64 [-]: FORNLOOP R0 L5; nforloop end - iterate + goto L5
L 9:  65 [-]: RETURN R0 0  ; 


; Name:            
; Defined at line: 94
; #Upvalues:       1
; #Parameters:     1
; Is_vararg:       0
; Max Stack Size:  12

       0 [-]: NEWTABLE R1 0 0; var1 = {}
       1 [-]: GETIMPORT R2 1; var2 = 0x89326C93
       2 [-]: GETIMPORT R4 3; var4 = gLotusNpcAvatarType
       3 [-]: GETUPVAL R5 0; var5 = upvalues[0]
       4 [-]: LOADN R6 0   ; var6 = 0
       5 [-]: MOVE R7 R0   ; var7 = var0
       6 [-]: NAMECALL R2 R2 K4; var3 = var2; var2 = var2[0xFB669000]
       7 [-]: CALL R2 6 2  ; var2 = var2(var3, var4, var5, var6, var7)
       8 [-]: GETIMPORT R3 6; var3 = 0xC8802016
       9 [-]: MOVE R4 R2   ; var4 = var2
      10 [-]: CALL R3 2 4  ; var3, var4, var5 = var3(var4)
      11 [-]: FORGPREP_INEXT R3 L2; 
L 0:  12 [-]: NAMECALL R8 R7 K7; var9 = var7; var8 = var7[0xFA9E477F]
      13 [-]: CALL R8 2 2  ; var8 = var8(var9)
      14 [-]: FASTCALL1 62 R8 L1; 
      15 [-]: MOVE R10 R8  ; var10 = var8
      16 [-]: GETIMPORT R9 9; var9 = 0x7B998233
      17 [-]: CALL R9 2 2  ; var9 = var9(var10)
L 1:  18 [-]: JUMPIF R9 L2 ; goto L2 if var9
      19 [-]: GETIMPORT R11 11; var11 = 0x8FA43E5B
      20 [-]: NAMECALL R9 R8 K12; var10 = var8; var9 = var8[0xF2DEAF69]
      21 [-]: CALL R9 3 2  ; var9 = var9(var10, var11)
      22 [-]: JUMPIFNOT R9 L2; goto L2 if not var9
      23 [-]: NAMECALL R9 R7 K13; var10 = var7; var9 = var7[0x808B79E6]
      24 [-]: CALL R9 2 2  ; var9 = var9(var10)
      25 [-]: GETIMPORT R10 15; var10 = 0x0469F296
      26 [-]: LOADK R11 K16; var11 = "TENNO"
      27 [-]: CALL R10 2 2 ; var10 = var10(var11)
      28 [-]: JUMPIFEQ R9 R10 L2; goto L2 if var9 == var83964941
      29 [-]: FASTCALL2 52 R1 R7 L2; 
      30 [-]: MOVE R10 R1  ; var10 = var1
      31 [-]: MOVE R11 R7  ; var11 = var7
      32 [-]: GETIMPORT R9 19; var9 = 0x33BDD652[0x23D5322F]
      33 [-]: CALL R9 3 1  ; var9(var10, var11)
L 2:  34 [-]: FORGLOOP R3 L0 2 [inext]; 
      35 [-]: RETURN R1 1  ; 


; Name:            
; Defined at line: 106
; #Upvalues:       24
; #Parameters:     0
; Is_vararg:       0
; Max Stack Size:  12

       0 [-]: GETUPVAL R0 0; var0 = upvalues[0]
       1 [-]: NAMECALL R0 R0 K0; var1 = var0; var0 = var0[0x209398C2]
       2 [-]: CALL R0 2 2  ; var0 = var0(var1)
       3 [-]: GETUPVAL R2 1; var2 = upvalues[1]
       4 [-]: GETTABLEKS R1 R2 K1; var1 = var2[0x2BEB71D2]
       5 [-]: LOADK R2 K2  ; var2 = "DEBUG STAGE: "
       6 [-]: GETIMPORT R3 4; var3 = 0x64FB1586
       7 [-]: MOVE R4 R0   ; var4 = var0
       8 [-]: CALL R3 2 0  ; var3, ... = var3(var4)
       9 [-]: CALL R1 0 1  ; var1(var2, ...)
      10 [-]: JUMPXEQKN R0 K5 L0 NOT; 
      11 [-]: GETIMPORT R1 7; var1 = 0x3D106989
      12 [-]: LOADK R2 K8  ; var2 = "Encounter: Solaris Base: STARTUP"
      13 [-]: CALL R1 2 1  ; var1(var2)
      14 [-]: GETUPVAL R2 2; var2 = upvalues[2]
      15 [-]: GETTABLEKS R1 R2 K9; var1 = var2[0x9742B85B]
      16 [-]: GETUPVAL R2 3; var2 = upvalues[3]
      17 [-]: GETIMPORT R3 11; var3 = 0x0469F296
      18 [-]: LOADK R4 K12 ; var4 = "BaseCaptureStarted"
      19 [-]: CALL R3 2 0  ; var3, ... = var3(var4)
      20 [-]: CALL R1 0 1  ; var1(var2, ...)
      21 [-]: GETUPVAL R1 0; var1 = upvalues[0]
      22 [-]: LOADN R3 2   ; var3 = 2
      23 [-]: NAMECALL R1 R1 K13; var2 = var1; var1 = var1[0x8ABFF40E]
      24 [-]: CALL R1 3 1  ; var1(var2, var3)
      25 [-]: JUMP L28     ; goto L28
L 0:  26 [-]: JUMPXEQKN R0 K14 L7 NOT; 
      27 [-]: GETIMPORT R1 7; var1 = 0x3D106989
      28 [-]: LOADK R2 K15 ; var2 = "Encounter: Solaris Base: WAIT_FOR_TIMER"
      29 [-]: CALL R1 2 1  ; var1(var2)
      30 [-]: GETUPVAL R1 4; var1 = upvalues[4]
      31 [-]: LOADK R3 K16 ; var3 = "OnAgentRegistered"
      32 [-]: GETIMPORT R4 11; var4 = 0x0469F296
      33 [-]: LOADK R5 K17 ; var5 = "DefendRegistration"
      34 [-]: CALL R4 2 0  ; var4, ... = var4(var5)
      35 [-]: NAMECALL R1 R1 K18; var2 = var1; var1 = var1[0x5B344F44]
      36 [-]: CALL R1 0 1  ; var1(var2, ...)
      37 [-]: GETUPVAL R2 1; var2 = upvalues[1]
      38 [-]: GETTABLEKS R1 R2 K19; var1 = var2[0xE8FA0E68]
      39 [-]: GETUPVAL R2 5; var2 = upvalues[5]
      40 [-]: LOADB R3 0   ; var3 = false
      41 [-]: LOADB R4 1   ; var4 = true
      42 [-]: LOADB R5 0   ; var5 = false
      43 [-]: GETUPVAL R7 1; var7 = upvalues[1]
      44 [-]: GETTABLEKS R6 R7 K20; var6 = var7["TIMELEFT_STRING"]
      45 [-]: CALL R1 6 1  ; var1(var2, var3, var4, var5, var6)
      46 [-]: GETUPVAL R2 1; var2 = upvalues[1]
      47 [-]: GETTABLEKS R1 R2 K21; var1 = var2[0xA1DF01D6]
      48 [-]: LOADK R2 K22 ; var2 = "/Lotus/Language/SolarisJobs/SolarisBaseCaptureDefend"
      49 [-]: LOADN R3 5   ; var3 = 5
      50 [-]: CALL R1 3 1  ; var1(var2, var3)
      51 [-]: GETUPVAL R2 1; var2 = upvalues[1]
      52 [-]: GETTABLEKS R1 R2 K23; var1 = var2[0x1551AA65]
      53 [-]: GETUPVAL R2 6; var2 = upvalues[6]
      54 [-]: CALL R1 2 1  ; var1(var2)
      55 [-]: GETUPVAL R1 7; var1 = upvalues[7]
      56 [-]: GETUPVAL R3 6; var3 = upvalues[6]
      57 [-]: NAMECALL R1 R1 K24; var2 = var1; var1 = var1[0xCC6AA982]
      58 [-]: CALL R1 3 1  ; var1(var2, var3)
      59 [-]: GETUPVAL R1 6; var1 = upvalues[6]
      60 [-]: LOADN R3 2   ; var3 = 2
      61 [-]: NAMECALL R1 R1 K25; var2 = var1; var1 = var1[0x1FEDCBCF]
      62 [-]: CALL R1 3 1  ; var1(var2, var3)
      63 [-]: GETUPVAL R1 6; var1 = upvalues[6]
      64 [-]: NAMECALL R1 R1 K26; var2 = var1; var1 = var1[0x1AC1655C]
      65 [-]: CALL R1 2 2  ; var1 = var1(var2)
      66 [-]: GETUPVAL R3 8; var3 = upvalues[8]
      67 [-]: NAMECALL R1 R1 K27; var2 = var1; var1 = var1[0x8E3E343E]
      68 [-]: CALL R1 3 1  ; var1(var2, var3)
      69 [-]: GETUPVAL R1 6; var1 = upvalues[6]
      70 [-]: LOADB R3 0   ; var3 = false
      71 [-]: NAMECALL R1 R1 K28; var2 = var1; var1 = var1[0x069D881F]
      72 [-]: CALL R1 3 1  ; var1(var2, var3)
      73 [-]: GETUPVAL R2 6; var2 = upvalues[6]
      74 [-]: NAMECALL R2 R2 K29; var3 = var2; var2 = var2[0xD1586535]
      75 [-]: CALL R2 2 2  ; var2 = var2(var3)
      76 [-]: GETIMPORT R3 31; var3 = 0xA421AF95
      77 [-]: LOADN R4 0   ; var4 = 0
      78 [-]: LOADN R5 1   ; var5 = 1
      79 [-]: LOADN R6 0   ; var6 = 0
      80 [-]: CALL R3 4 2  ; var3 = var3(var4, var5, var6)
      81 [-]: ADD R1 R2 R3 ; var1 = var2 + var3
      82 [-]: GETIMPORT R2 33; var2 = 0x89326C93
      83 [-]: GETUPVAL R4 10; var4 = upvalues[10]
      84 [-]: MOVE R5 R1   ; var5 = var1
      85 [-]: GETIMPORT R6 35; var6 = ZERO_ROTATION
      86 [-]: GETUPVAL R7 11; var7 = upvalues[11]
      87 [-]: NAMECALL R2 R2 K36; var3 = var2; var2 = var2[0x05909209]
      88 [-]: CALL R2 6 2  ; var2 = var2(var3, var4, var5, var6, var7)
      89 [-]: SETUPVAL R2 9; upvalues[2] = var9
      90 [-]: GETIMPORT R4 39; var4 = _T["BaseReinforcements"]
      91 [-]: GETUPVAL R5 12; var5 = upvalues[12]
      92 [-]: GETTABLE R3 R4 R5; var3 = var4[var5]
      93 [-]: FASTCALL1 62 R3 L1; 
      94 [-]: GETIMPORT R2 41; var2 = 0x7B998233
      95 [-]: CALL R2 2 2  ; var2 = var2(var3)
L 1:  96 [-]: JUMPIFNOT R2 L5; goto L5 if not var2
      97 [-]: GETUPVAL R2 4; var2 = upvalues[4]
      98 [-]: NAMECALL R2 R2 K42; var3 = var2; var2 = var2[0xD8140B94]
      99 [-]: CALL R2 2 2  ; var2 = var2(var3)
     100 [-]: JUMPIF R2 L5 ; goto L5 if var2
     101 [-]: GETUPVAL R2 4; var2 = upvalues[4]
     102 [-]: NAMECALL R2 R2 K43; var3 = var2; var2 = var2[0xBE21D4F6]
     103 [-]: CALL R2 2 2  ; var2 = var2(var3)
     104 [-]: JUMPIF R2 L2 ; goto L2 if var2
     105 [-]: GETUPVAL R2 4; var2 = upvalues[4]
     106 [-]: NAMECALL R2 R2 K44; var3 = var2; var2 = var2[0x1E0AEEEC]
     107 [-]: CALL R2 2 2  ; var2 = var2(var3)
     108 [-]: JUMPIFNOT R2 L5; goto L5 if not var2
L 2: 109 [-]: GETUPVAL R2 7; var2 = upvalues[7]
     110 [-]: GETUPVAL R5 4; var5 = upvalues[4]
     111 [-]: NAMECALL R5 R5 K29; var6 = var5; var5 = var5[0xD1586535]
     112 [-]: CALL R5 2 2  ; var5 = var5(var6)
     113 [-]: GETIMPORT R6 31; var6 = 0xA421AF95
     114 [-]: LOADN R7 0   ; var7 = 0
     115 [-]: LOADN R8 1   ; var8 = 1
     116 [-]: LOADN R9 0   ; var9 = 0
     117 [-]: CALL R6 4 2  ; var6 = var6(var7, var8, var9)
     118 [-]: ADD R4 R5 R6 ; var4 = var5 + var6
     119 [-]: GETIMPORT R5 46; var5 = 0x1A40EDD1
     120 [-]: GETUPVAL R6 4; var6 = upvalues[4]
     121 [-]: NAMECALL R2 R2 K47; var3 = var2; var2 = var2[0x44C55B21]
     122 [-]: CALL R2 5 1  ; var2(var3, var4, var5, var6)
     123 [-]: LOADN R2 10  ; var2 = 10
L 3: 124 [-]: GETIMPORT R5 39; var5 = _T["BaseReinforcements"]
     125 [-]: GETUPVAL R6 12; var6 = upvalues[12]
     126 [-]: GETTABLE R4 R5 R6; var4 = var5[var6]
     127 [-]: FASTCALL1 62 R4 L4; 
     128 [-]: GETIMPORT R3 41; var3 = 0x7B998233
     129 [-]: CALL R3 2 2  ; var3 = var3(var4)
L 4: 130 [-]: JUMPIFNOT R3 L5; goto L5 if not var3
     131 [-]: LOADN R3 0   ; var3 = 0
     132 [-]: JUMPIFNOTLT R3 R2 L5; goto L5 if var3 >= var3212110
     133 [-]: GETIMPORT R3 49; var3 = 0xFFF641AF
     134 [-]: CALL R3 1 2  ; var3 = var3()
     135 [-]: SUB R2 R2 R3 ; var2 = var2 - var3
     136 [-]: GETIMPORT R3 51; var3 = 0xCBD666E1
     137 [-]: LOADN R4 0   ; var4 = 0
     138 [-]: CALL R3 2 1  ; var3(var4)
     139 [-]: JUMPBACK L3  ; goto L3
L 5: 140 [-]: GETIMPORT R4 39; var4 = _T["BaseReinforcements"]
     141 [-]: GETUPVAL R5 12; var5 = upvalues[12]
     142 [-]: GETTABLE R3 R4 R5; var3 = var4[var5]
     143 [-]: FASTCALL1 62 R3 L6; 
     144 [-]: GETIMPORT R2 41; var2 = 0x7B998233
     145 [-]: CALL R2 2 2  ; var2 = var2(var3)
L 6: 146 [-]: JUMPIF R2 L28; goto L28 if var2
     147 [-]: GETIMPORT R4 39; var4 = _T["BaseReinforcements"]
     148 [-]: GETUPVAL R5 12; var5 = upvalues[12]
     149 [-]: GETTABLE R3 R4 R5; var3 = var4[var5]
     150 [-]: GETTABLEKS R2 R3 K52; var2 = var3["Start"]
     151 [-]: CALL R2 1 1  ; var2()
     152 [-]: JUMP L28     ; goto L28
L 7: 153 [-]: JUMPXEQKN R0 K53 L16 NOT; 
     154 [-]: GETIMPORT R1 7; var1 = 0x3D106989
     155 [-]: LOADK R2 K54 ; var2 = "Encounter: Solaris Base: WAIT_FOR_KILLS"
     156 [-]: CALL R1 2 1  ; var1(var2)
     157 [-]: GETUPVAL R2 9; var2 = upvalues[9]
     158 [-]: FASTCALL1 62 R2 L8; 
     159 [-]: GETIMPORT R1 41; var1 = 0x7B998233
     160 [-]: CALL R1 2 2  ; var1 = var1(var2)
L 8: 161 [-]: JUMPIF R1 L9 ; goto L9 if var1
     162 [-]: GETUPVAL R1 9; var1 = upvalues[9]
     163 [-]: NAMECALL R1 R1 K55; var2 = var1; var1 = var1[0xA2880940]
     164 [-]: CALL R1 2 1  ; var1(var2)
L 9: 165 [-]: GETUPVAL R2 1; var2 = upvalues[1]
     166 [-]: GETTABLEKS R1 R2 K56; var1 = var2[0xEDF59000]
     167 [-]: CALL R1 1 1  ; var1()
     168 [-]: GETUPVAL R2 6; var2 = upvalues[6]
     169 [-]: FASTCALL1 62 R2 L10; 
     170 [-]: GETIMPORT R1 41; var1 = 0x7B998233
     171 [-]: CALL R1 2 2  ; var1 = var1(var2)
L10: 172 [-]: JUMPIF R1 L11; goto L11 if var1
     173 [-]: GETUPVAL R1 6; var1 = upvalues[6]
     174 [-]: NAMECALL R1 R1 K26; var2 = var1; var1 = var1[0x1AC1655C]
     175 [-]: CALL R1 2 2  ; var1 = var1(var2)
     176 [-]: GETUPVAL R3 8; var3 = upvalues[8]
     177 [-]: LOADN R4 25  ; var4 = 25
     178 [-]: LOADN R5 6   ; var5 = 6
     179 [-]: LOADN R6 0   ; var6 = 0
     180 [-]: NAMECALL R1 R1 K57; var2 = var1; var1 = var1[0xA383DE31]
     181 [-]: CALL R1 6 1  ; var1(var2, var3, var4, var5, var6)
     182 [-]: GETUPVAL R1 6; var1 = upvalues[6]
     183 [-]: LOADN R3 -5  ; var3 = -5
     184 [-]: NAMECALL R1 R1 K25; var2 = var1; var1 = var1[0x1FEDCBCF]
     185 [-]: CALL R1 3 1  ; var1(var2, var3)
     186 [-]: GETUPVAL R1 6; var1 = upvalues[6]
     187 [-]: LOADB R3 1   ; var3 = true
     188 [-]: NAMECALL R1 R1 K28; var2 = var1; var1 = var1[0x069D881F]
     189 [-]: CALL R1 3 1  ; var1(var2, var3)
L11: 190 [-]: GETUPVAL R1 7; var1 = upvalues[7]
     191 [-]: LOADN R3 0   ; var3 = 0
     192 [-]: NAMECALL R1 R1 K58; var2 = var1; var1 = var1[0x27D04ADD]
     193 [-]: CALL R1 3 1  ; var1(var2, var3)
     194 [-]: GETIMPORT R3 39; var3 = _T["BaseReinforcements"]
     195 [-]: GETUPVAL R4 12; var4 = upvalues[12]
     196 [-]: GETTABLE R2 R3 R4; var2 = var3[var4]
     197 [-]: FASTCALL1 62 R2 L12; 
     198 [-]: GETIMPORT R1 41; var1 = 0x7B998233
     199 [-]: CALL R1 2 2  ; var1 = var1(var2)
L12: 200 [-]: JUMPIF R1 L13; goto L13 if var1
     201 [-]: GETIMPORT R3 39; var3 = _T["BaseReinforcements"]
     202 [-]: GETUPVAL R4 12; var4 = upvalues[12]
     203 [-]: GETTABLE R2 R3 R4; var2 = var3[var4]
     204 [-]: GETTABLEKS R1 R2 K59; var1 = var2["Stop"]
     205 [-]: CALL R1 1 1  ; var1()
L13: 206 [-]: GETIMPORT R1 51; var1 = 0xCBD666E1
     207 [-]: LOADN R2 1   ; var2 = 1
     208 [-]: CALL R1 2 1  ; var1(var2)
     209 [-]: GETUPVAL R1 14; var1 = upvalues[14]
     210 [-]: LOADN R2 100 ; var2 = 100
     211 [-]: CALL R1 2 2  ; var1 = var1(var2)
     212 [-]: SETUPVAL R1 13; upvalues[1] = var13
     213 [-]: GETIMPORT R1 61; var1 = 0xC8802016
     214 [-]: GETUPVAL R2 13; var2 = upvalues[13]
     215 [-]: CALL R1 2 4  ; var1, var2, var3 = var1(var2)
     216 [-]: FORGPREP_INEXT R1 L15; 
L14: 217 [-]: NAMECALL R6 R5 K62; var7 = var5; var6 = var5[0xFA9E477F]
     218 [-]: CALL R6 2 2  ; var6 = var6(var7)
     219 [-]: NAMECALL R7 R6 K63; var8 = var6; var7 = var6[0x9E21E394]
     220 [-]: CALL R7 2 1  ; var7(var8)
     221 [-]: GETUPVAL R9 6; var9 = upvalues[6]
     222 [-]: NAMECALL R7 R6 K64; var8 = var6; var7 = var6[0xA64A1F4A]
     223 [-]: CALL R7 3 1  ; var7(var8, var9)
     224 [-]: GETUPVAL R9 15; var9 = upvalues[15]
     225 [-]: GETIMPORT R10 11; var10 = 0x0469F296
     226 [-]: LOADK R11 K65; var11 = "GAME_C1_SPINE3"
     227 [-]: CALL R10 2 0 ; var10, ... = var10(var11)
     228 [-]: NAMECALL R7 R5 K66; var8 = var5; var7 = var5[0x47901F07]
     229 [-]: CALL R7 0 1  ; var7(var8, ...)
     230 [-]: GETIMPORT R7 68; var7 = 0x11A19C5E
     231 [-]: MOVE R8 R5   ; var8 = var5
     232 [-]: LOADK R9 K69 ; var9 = "OnKilled"
     233 [-]: CALL R7 3 1  ; var7(var8, var9)
L15: 234 [-]: FORGLOOP R1 L14 2 [inext]; 
     235 [-]: GETUPVAL R1 16; var1 = upvalues[16]
     236 [-]: GETUPVAL R3 17; var3 = upvalues[17]
     237 [-]: GETUPVAL R5 13; var5 = upvalues[13]
     238 [-]: LENGTH R4 R5 ; var4 = #var5
     239 [-]: NAMECALL R1 R1 K70; var2 = var1; var1 = var1[0x751F061D]
     240 [-]: CALL R1 4 1  ; var1(var2, var3, var4)
     241 [-]: GETUPVAL R2 1; var2 = upvalues[1]
     242 [-]: GETTABLEKS R1 R2 K21; var1 = var2[0xA1DF01D6]
     243 [-]: LOADK R2 K71 ; var2 = "/Lotus/Language/Objectives/KillRemainingEnemies"
     244 [-]: LOADN R3 2   ; var3 = 2
     245 [-]: CALL R1 3 1  ; var1(var2, var3)
     246 [-]: GETUPVAL R2 1; var2 = upvalues[1]
     247 [-]: GETTABLEKS R1 R2 K72; var1 = var2[0xEA753E99]
     248 [-]: LOADK R2 K73 ; var2 = "/Lotus/Language/SolarisJobs/DynamicExterminateStatus"
     249 [-]: LOADN R3 0   ; var3 = 0
     250 [-]: GETUPVAL R5 13; var5 = upvalues[13]
     251 [-]: LENGTH R4 R5 ; var4 = #var5
     252 [-]: CALL R1 4 1  ; var1(var2, var3, var4)
     253 [-]: JUMP L28     ; goto L28
L16: 254 [-]: JUMPXEQKN R0 K74 L26 NOT; 
     255 [-]: GETIMPORT R1 7; var1 = 0x3D106989
     256 [-]: LOADK R2 K75 ; var2 = "Encounter: Solaris Base: COMPLETED"
     257 [-]: CALL R1 2 1  ; var1(var2)
     258 [-]: GETUPVAL R2 18; var2 = upvalues[18]
     259 [-]: FASTCALL1 62 R2 L17; 
     260 [-]: GETIMPORT R1 41; var1 = 0x7B998233
     261 [-]: CALL R1 2 2  ; var1 = var1(var2)
L17: 262 [-]: JUMPIF R1 L20; goto L20 if var1
     263 [-]: GETIMPORT R1 61; var1 = 0xC8802016
     264 [-]: GETUPVAL R2 18; var2 = upvalues[18]
     265 [-]: CALL R1 2 4  ; var1, var2, var3 = var1(var2)
     266 [-]: FORGPREP_INEXT R1 L19; 
L18: 267 [-]: GETUPVAL R8 19; var8 = upvalues[19]
     268 [-]: NAMECALL R6 R5 K76; var7 = var5; var6 = var5[0xFA1A049A]
     269 [-]: CALL R6 3 1  ; var6(var7, var8)
L19: 270 [-]: FORGLOOP R1 L18 2 [inext]; 
L20: 271 [-]: GETIMPORT R2 78; var2 = _T["CapturedCamp"]
     272 [-]: FASTCALL1 62 R2 L21; 
     273 [-]: GETIMPORT R1 41; var1 = 0x7B998233
     274 [-]: CALL R1 2 2  ; var1 = var1(var2)
L21: 275 [-]: JUMPIF R1 L24; goto L24 if var1
     276 [-]: GETIMPORT R1 78; var1 = _T["CapturedCamp"]
     277 [-]: NAMECALL R1 R1 K79; var2 = var1; var1 = var1[0x5252E77D]
     278 [-]: CALL R1 2 2  ; var1 = var1(var2)
     279 [-]: GETIMPORT R2 61; var2 = 0xC8802016
     280 [-]: MOVE R3 R1   ; var3 = var1
     281 [-]: CALL R2 2 4  ; var2, var3, var4 = var2(var3)
     282 [-]: FORGPREP_INEXT R2 L23; 
L22: 283 [-]: GETUPVAL R9 19; var9 = upvalues[19]
     284 [-]: NAMECALL R7 R6 K80; var8 = var6; var7 = var6[0x3E58DFE0]
     285 [-]: CALL R7 3 1  ; var7(var8, var9)
L23: 286 [-]: FORGLOOP R2 L22 2 [inext]; 
L24: 287 [-]: GETIMPORT R1 81; var1 = _T
     288 [-]: GETUPVAL R2 20; var2 = upvalues[20]
     289 [-]: SETTABLEKS R2 R1 K77; var2["CapturedCamp"] = var1
     290 [-]: GETUPVAL R1 21; var1 = upvalues[21]
     291 [-]: NAMECALL R1 R1 K82; var2 = var1; var1 = var1[0x383D2E7D]
     292 [-]: CALL R1 2 1  ; var1(var2)
     293 [-]: GETIMPORT R2 84; var2 = _T["ActiveJob"]
     294 [-]: FASTCALL1 62 R2 L25; 
     295 [-]: GETIMPORT R1 41; var1 = 0x7B998233
     296 [-]: CALL R1 2 2  ; var1 = var1(var2)
L25: 297 [-]: JUMPIFNOT R1 L28; goto L28 if not var1
     298 [-]: GETUPVAL R2 2; var2 = upvalues[2]
     299 [-]: GETTABLEKS R1 R2 K9; var1 = var2[0x9742B85B]
     300 [-]: GETUPVAL R2 3; var2 = upvalues[3]
     301 [-]: GETIMPORT R3 11; var3 = 0x0469F296
     302 [-]: LOADK R4 K85 ; var4 = "BaseCaptureDone"
     303 [-]: CALL R3 2 0  ; var3, ... = var3(var4)
     304 [-]: CALL R1 0 1  ; var1(var2, ...)
     305 [-]: JUMP L28     ; goto L28
L26: 306 [-]: LOADN R1 5   ; var1 = 5
     307 [-]: JUMPIFNOTLE R1 R0 L28; goto L28 if var1 > var459086
     308 [-]: GETIMPORT R1 7; var1 = 0x3D106989
     309 [-]: LOADK R2 K86 ; var2 = "Encounter: Solaris Base: FAILED"
     310 [-]: CALL R1 2 1  ; var1(var2)
     311 [-]: GETUPVAL R2 2; var2 = upvalues[2]
     312 [-]: GETTABLEKS R1 R2 K9; var1 = var2[0x9742B85B]
     313 [-]: GETUPVAL R2 3; var2 = upvalues[3]
     314 [-]: GETIMPORT R3 11; var3 = 0x0469F296
     315 [-]: LOADK R4 K87 ; var4 = "BaseCaptureFail"
     316 [-]: CALL R3 2 0  ; var3, ... = var3(var4)
     317 [-]: CALL R1 0 1  ; var1(var2, ...)
     318 [-]: JUMPXEQKN R0 K88 L27 NOT; 
     319 [-]: GETUPVAL R2 22; var2 = upvalues[22]
     320 [-]: GETTABLEKS R1 R2 K89; var1 = var2[0xD712B9DB]
     321 [-]: CALL R1 1 1  ; var1()
     322 [-]: GETIMPORT R1 33; var1 = 0x89326C93
     323 [-]: GETIMPORT R3 11; var3 = 0x0469F296
     324 [-]: LOADK R4 K90 ; var4 = "SolarisConsoleAbandonedForwarder"
     325 [-]: CALL R3 2 2  ; var3 = var3(var4)
     326 [-]: GETUPVAL R4 23; var4 = upvalues[23]
     327 [-]: NAMECALL R1 R1 K91; var2 = var1; var1 = var1[0xC7B81E8D]
     328 [-]: CALL R1 4 2  ; var1 = var1(var2, var3, var4)
     329 [-]: LOADK R4 K92 ; var4 = "TriggerPort"
     330 [-]: NAMECALL R2 R1 K93; var3 = var1; var2 = var1[0x8EB2112D]
     331 [-]: CALL R2 3 1  ; var2(var3, var4)
L27: 332 [-]: GETUPVAL R1 11; var1 = upvalues[11]
     333 [-]: LOADN R3 5   ; var3 = 5
     334 [-]: NAMECALL R1 R1 K94; var2 = var1; var1 = var1[0xFE9DC265]
     335 [-]: CALL R1 3 1  ; var1(var2, var3)
L28: 336 [-]: LOADN R1 4   ; var1 = 4
     337 [-]: JUMPIFNOTLE R1 R0 L36; goto L36 if var1 > var459086
     338 [-]: GETIMPORT R1 7; var1 = 0x3D106989
     339 [-]: LOADK R2 K95 ; var2 = "Encounter: Solaris Base: Shutting down..."
     340 [-]: CALL R1 2 1  ; var1(var2)
     341 [-]: GETUPVAL R2 9; var2 = upvalues[9]
     342 [-]: FASTCALL1 62 R2 L29; 
     343 [-]: GETIMPORT R1 41; var1 = 0x7B998233
     344 [-]: CALL R1 2 2  ; var1 = var1(var2)
L29: 345 [-]: JUMPIF R1 L30; goto L30 if var1
     346 [-]: GETUPVAL R1 9; var1 = upvalues[9]
     347 [-]: NAMECALL R1 R1 K55; var2 = var1; var1 = var1[0xA2880940]
     348 [-]: CALL R1 2 1  ; var1(var2)
L30: 349 [-]: GETIMPORT R1 97; var1 = _T["EnableStores"]
     350 [-]: CALL R1 1 1  ; var1()
     351 [-]: GETUPVAL R1 14; var1 = upvalues[14]
     352 [-]: LOADN R2 200 ; var2 = 200
     353 [-]: CALL R1 2 2  ; var1 = var1(var2)
     354 [-]: SETUPVAL R1 13; upvalues[1] = var13
     355 [-]: GETIMPORT R1 61; var1 = 0xC8802016
     356 [-]: GETUPVAL R2 13; var2 = upvalues[13]
     357 [-]: CALL R1 2 4  ; var1, var2, var3 = var1(var2)
     358 [-]: FORGPREP_INEXT R1 L33; 
L31: 359 [-]: GETUPVAL R8 15; var8 = upvalues[15]
     360 [-]: NAMECALL R6 R5 K98; var7 = var5; var6 = var5[0xC9F6A7D7]
     361 [-]: CALL R6 3 2  ; var6 = var6(var7, var8)
     362 [-]: FASTCALL1 62 R6 L32; 
     363 [-]: MOVE R8 R6   ; var8 = var6
     364 [-]: GETIMPORT R7 41; var7 = 0x7B998233
     365 [-]: CALL R7 2 2  ; var7 = var7(var8)
L32: 366 [-]: JUMPIF R7 L33; goto L33 if var7
     367 [-]: NAMECALL R7 R6 K55; var8 = var6; var7 = var6[0xA2880940]
     368 [-]: CALL R7 2 1  ; var7(var8)
L33: 369 [-]: FORGLOOP R1 L31 2 [inext]; 
     370 [-]: GETUPVAL R2 6; var2 = upvalues[6]
     371 [-]: FASTCALL1 62 R2 L34; 
     372 [-]: GETIMPORT R1 41; var1 = 0x7B998233
     373 [-]: CALL R1 2 2  ; var1 = var1(var2)
L34: 374 [-]: JUMPIF R1 L35; goto L35 if var1
     375 [-]: GETUPVAL R1 7; var1 = upvalues[7]
     376 [-]: GETUPVAL R3 6; var3 = upvalues[6]
     377 [-]: NAMECALL R1 R1 K99; var2 = var1; var1 = var1[0x996C2CAB]
     378 [-]: CALL R1 3 1  ; var1(var2, var3)
     379 [-]: GETUPVAL R1 6; var1 = upvalues[6]
     380 [-]: NAMECALL R1 R1 K55; var2 = var1; var1 = var1[0xA2880940]
     381 [-]: CALL R1 2 1  ; var1(var2)
L35: 382 [-]: GETUPVAL R1 7; var1 = upvalues[7]
     383 [-]: LOADB R3 1   ; var3 = true
     384 [-]: NAMECALL R1 R1 K100; var2 = var1; var1 = var1[0x2D2BDBB8]
     385 [-]: CALL R1 3 1  ; var1(var2, var3)
     386 [-]: GETUPVAL R2 1; var2 = upvalues[1]
     387 [-]: GETTABLEKS R1 R2 K101; var1 = var2[0x18DD08AC]
     388 [-]: CALL R1 1 1  ; var1()
     389 [-]: GETIMPORT R1 51; var1 = 0xCBD666E1
     390 [-]: LOADN R2 3   ; var2 = 3
     391 [-]: CALL R1 2 1  ; var1(var2)
     392 [-]: GETUPVAL R2 1; var2 = upvalues[1]
     393 [-]: GETTABLEKS R1 R2 K102; var1 = var2[0xDC3B2033]
     394 [-]: CALL R1 1 1  ; var1()
     395 [-]: GETUPVAL R2 1; var2 = upvalues[1]
     396 [-]: GETTABLEKS R1 R2 K103; var1 = var2[0xBD3CE95D]
     397 [-]: CALL R1 1 1  ; var1()
     398 [-]: GETUPVAL R2 1; var2 = upvalues[1]
     399 [-]: GETTABLEKS R1 R2 K56; var1 = var2[0xEDF59000]
     400 [-]: CALL R1 1 1  ; var1()
     401 [-]: GETUPVAL R2 1; var2 = upvalues[1]
     402 [-]: GETTABLEKS R1 R2 K104; var1 = var2[0xF158D74D]
     403 [-]: CALL R1 1 1  ; var1()
     404 [-]: GETUPVAL R1 0; var1 = upvalues[0]
     405 [-]: NAMECALL R1 R1 K105; var2 = var1; var1 = var1[0x588ED000]
     406 [-]: CALL R1 2 1  ; var1(var2)
     407 [-]: GETUPVAL R2 22; var2 = upvalues[22]
     408 [-]: GETTABLEKS R1 R2 K106; var1 = var2[0xE69049EB]
     409 [-]: GETUPVAL R2 4; var2 = upvalues[4]
     410 [-]: CALL R1 2 1  ; var1(var2)
L36: 411 [-]: RETURN R0 0  ; 


; Name:            
; Defined at line: 255
; #Upvalues:       26
; #Parameters:     1
; Is_vararg:       0
; Max Stack Size:  11

       0 [-]: GETIMPORT R1 1; var1 = 0x3D106989
       1 [-]: LOADK R2 K2  ; var2 = "Encounter: Solaris Base: Initializing..."
       2 [-]: CALL R1 2 1  ; var1(var2)
       3 [-]: GETIMPORT R1 4; var1 = 0x89326C93
       4 [-]: NAMECALL R1 R1 K5; var2 = var1; var1 = var1[0x29EF273D]
       5 [-]: CALL R1 2 2  ; var1 = var1(var2)
       6 [-]: NAMECALL R1 R1 K6; var2 = var1; var1 = var1[0x66905CB0]
       7 [-]: CALL R1 2 2  ; var1 = var1(var2)
       8 [-]: SETUPVAL R1 0; upvalues[1] = var0
L 0:   9 [-]: GETUPVAL R1 0; var1 = upvalues[0]
      10 [-]: NAMECALL R1 R1 K7; var2 = var1; var1 = var1[0xA2D83ED4]
      11 [-]: CALL R1 2 2  ; var1 = var1(var2)
      12 [-]: JUMPIF R1 L1 ; goto L1 if var1
      13 [-]: GETIMPORT R1 9; var1 = 0xCBD666E1
      14 [-]: LOADN R2 0   ; var2 = 0
      15 [-]: CALL R1 2 1  ; var1(var2)
      16 [-]: JUMPBACK L0  ; goto L0
L 1:  17 [-]: GETIMPORT R1 11; var1 = 0xBE190284
      18 [-]: SETUPVAL R1 1; upvalues[1] = var1
      19 [-]: SETUPVAL R0 2; upvalues[0] = var2
      20 [-]: NAMECALL R1 R0 K12; var2 = var0; var1 = var0[0x891629FA]
      21 [-]: CALL R1 2 2  ; var1 = var1(var2)
      22 [-]: SETUPVAL R1 3; upvalues[1] = var3
      23 [-]: GETUPVAL R1 3; var1 = upvalues[3]
      24 [-]: NAMECALL R1 R1 K13; var2 = var1; var1 = var1[0x32DE3AB1]
      25 [-]: CALL R1 2 2  ; var1 = var1(var2)
      26 [-]: SETUPVAL R1 4; upvalues[1] = var4
      27 [-]: NAMECALL R1 R0 K14; var2 = var0; var1 = var0[0xD1586535]
      28 [-]: CALL R1 2 2  ; var1 = var1(var2)
      29 [-]: SETUPVAL R1 5; upvalues[1] = var5
      30 [-]: NAMECALL R1 R0 K15; var2 = var0; var1 = var0[0x7C97B143]
      31 [-]: CALL R1 2 2  ; var1 = var1(var2)
      32 [-]: SETUPVAL R1 6; upvalues[1] = var6
      33 [-]: NAMECALL R1 R0 K16; var2 = var0; var1 = var0[0x4C976EDA]
      34 [-]: CALL R1 2 2  ; var1 = var1(var2)
      35 [-]: NAMECALL R1 R1 K17; var2 = var1; var1 = var1[0xE4C355E2]
      36 [-]: CALL R1 2 2  ; var1 = var1(var2)
      37 [-]: SETUPVAL R1 7; upvalues[1] = var7
      38 [-]: GETIMPORT R1 4; var1 = 0x89326C93
      39 [-]: NAMECALL R1 R1 K18; var2 = var1; var1 = var1[0x7D108DDB]
      40 [-]: CALL R1 2 2  ; var1 = var1(var2)
      41 [-]: SETUPVAL R1 8; upvalues[1] = var8
      42 [-]: GETIMPORT R1 4; var1 = 0x89326C93
      43 [-]: GETIMPORT R3 20; var3 = 0x0469F296
      44 [-]: LOADK R4 K21 ; var4 = "SolarisCaptureTalkAction"
      45 [-]: CALL R3 2 2  ; var3 = var3(var4)
      46 [-]: GETUPVAL R4 5; var4 = upvalues[5]
      47 [-]: NAMECALL R1 R1 K22; var2 = var1; var1 = var1[0xC7B81E8D]
      48 [-]: CALL R1 4 2  ; var1 = var1(var2, var3, var4)
      49 [-]: SETUPVAL R1 9; upvalues[1] = var9
      50 [-]: GETUPVAL R1 3; var1 = upvalues[3]
      51 [-]: NAMECALL R1 R1 K23; var2 = var1; var1 = var1[0xED4E0128]
      52 [-]: CALL R1 2 2  ; var1 = var1(var2)
      53 [-]: SETUPVAL R1 10; upvalues[1] = var10
      54 [-]: GETUPVAL R2 4; var2 = upvalues[4]
      55 [-]: FASTCALL1 62 R2 L2; 
      56 [-]: GETIMPORT R1 25; var1 = 0x7B998233
      57 [-]: CALL R1 2 2  ; var1 = var1(var2)
L 2:  58 [-]: JUMPIF R1 L3 ; goto L3 if var1
      59 [-]: GETUPVAL R1 4; var1 = upvalues[4]
      60 [-]: NAMECALL R1 R1 K26; var2 = var1; var1 = var1[0x5252E77D]
      61 [-]: CALL R1 2 2  ; var1 = var1(var2)
      62 [-]: SETUPVAL R1 11; upvalues[1] = var11
L 3:  63 [-]: GETUPVAL R1 0; var1 = upvalues[0]
      64 [-]: GETUPVAL R3 12; var3 = upvalues[12]
      65 [-]: NAMECALL R1 R1 K27; var2 = var1; var1 = var1[0x4CB79046]
      66 [-]: CALL R1 3 1  ; var1(var2, var3)
      67 [-]: GETUPVAL R1 0; var1 = upvalues[0]
      68 [-]: LOADB R3 0   ; var3 = false
      69 [-]: NAMECALL R1 R1 K28; var2 = var1; var1 = var1[0x2D2BDBB8]
      70 [-]: CALL R1 3 1  ; var1(var2, var3)
      71 [-]: GETIMPORT R1 4; var1 = 0x89326C93
      72 [-]: LOADK R3 K29 ; var3 = "OnPlayersChanged"
      73 [-]: NAMECALL R1 R1 K30; var2 = var1; var1 = var1[0xB7D33840]
      74 [-]: CALL R1 3 1  ; var1(var2, var3)
      75 [-]: LOADK R3 K31 ; var3 = "PlayersLeaving"
      76 [-]: GETIMPORT R4 20; var4 = 0x0469F296
      77 [-]: LOADK R5 K32 ; var5 = "LeavingCB"
      78 [-]: CALL R4 2 0  ; var4, ... = var4(var5)
      79 [-]: NAMECALL R1 R0 K33; var2 = var0; var1 = var0[0xE19C3F44]
      80 [-]: CALL R1 0 1  ; var1(var2, ...)
      81 [-]: LOADK R3 K34 ; var3 = "PlayersReturning"
      82 [-]: GETIMPORT R4 20; var4 = 0x0469F296
      83 [-]: LOADK R5 K35 ; var5 = "ReturningCB"
      84 [-]: CALL R4 2 0  ; var4, ... = var4(var5)
      85 [-]: NAMECALL R1 R0 K36; var2 = var0; var1 = var0[0x3F86F5A0]
      86 [-]: CALL R1 0 1  ; var1(var2, ...)
      87 [-]: GETUPVAL R2 14; var2 = upvalues[14]
      88 [-]: GETTABLEKS R1 R2 K37; var1 = var2[0xA80CF6FF]
      89 [-]: GETUPVAL R2 0; var2 = upvalues[0]
      90 [-]: MOVE R3 R0   ; var3 = var0
      91 [-]: CALL R1 3 2  ; var1 = var1(var2, var3)
      92 [-]: SETUPVAL R1 13; upvalues[1] = var13
      93 [-]: GETUPVAL R1 13; var1 = upvalues[13]
      94 [-]: LOADN R2 10  ; var2 = 10
      95 [-]: SETTABLEKS R2 R1 K38; var2["mReinforceDelay"] = var1
      96 [-]: GETUPVAL R2 14; var2 = upvalues[14]
      97 [-]: GETTABLEKS R1 R2 K39; var1 = var2[0xC9013731]
      98 [-]: GETUPVAL R2 16; var2 = upvalues[16]
      99 [-]: GETUPVAL R3 2; var3 = upvalues[2]
     100 [-]: NEWTABLE R4 0 4; var4 = {}
     101 [-]: GETUPVAL R5 17; var5 = upvalues[17]
     102 [-]: GETUPVAL R6 18; var6 = upvalues[18]
     103 [-]: GETUPVAL R7 19; var7 = upvalues[19]
     104 [-]: GETUPVAL R8 20; var8 = upvalues[20]
     105 [-]: SETLIST R4 R5 4 [1]; var4[1] = var5; var4[2] = var6; var4[3] = var7; var4[4] = var8; var4[5] = var9; 
     106 [-]: CALL R1 4 2  ; var1 = var1(var2, var3, var4)
     107 [-]: SETUPVAL R1 15; upvalues[1] = var15
     108 [-]: GETUPVAL R2 22; var2 = upvalues[22]
     109 [-]: GETTABLEKS R1 R2 K40; var1 = var2[0xDE474187]
     110 [-]: CALL R1 1 2  ; var1 = var1()
     111 [-]: SETUPVAL R1 21; upvalues[1] = var21
     112 [-]: GETIMPORT R1 4; var1 = 0x89326C93
     113 [-]: GETIMPORT R3 20; var3 = 0x0469F296
     114 [-]: LOADK R4 K41 ; var4 = "SolarisDefenseSpawn"
     115 [-]: CALL R3 2 2  ; var3 = var3(var4)
     116 [-]: GETUPVAL R4 5; var4 = upvalues[5]
     117 [-]: NAMECALL R1 R1 K22; var2 = var1; var1 = var1[0xC7B81E8D]
     118 [-]: CALL R1 4 2  ; var1 = var1(var2, var3, var4)
     119 [-]: NAMECALL R3 R1 K42; var4 = var1; var3 = var1[0x90E142BA]
     120 [-]: CALL R3 2 2  ; var3 = var3(var4)
     121 [-]: GETTABLEN R2 R3 1; var2 = var3[1]
     122 [-]: NAMECALL R3 R2 K43; var4 = var2; var3 = var2[0x1E3535E5]
     123 [-]: CALL R3 2 2  ; var3 = var3(var4)
     124 [-]: SETUPVAL R3 23; upvalues[3] = var23
     125 [-]: GETUPVAL R4 23; var4 = upvalues[23]
     126 [-]: FASTCALL1 62 R4 L4; 
     127 [-]: GETIMPORT R3 25; var3 = 0x7B998233
     128 [-]: CALL R3 2 2  ; var3 = var3(var4)
L 4: 129 [-]: JUMPIFNOT R3 L5; goto L5 if not var3
     130 [-]: GETUPVAL R3 0; var3 = upvalues[0]
     131 [-]: GETIMPORT R5 45; var5 = 0x7C8D6307
     132 [-]: MOVE R6 R2   ; var6 = var2
     133 [-]: GETIMPORT R7 20; var7 = 0x0469F296
     134 [-]: LOADK R8 K46 ; var8 = "BaseDefendAvatar"
     135 [-]: CALL R7 2 0  ; var7, ... = var7(var8)
     136 [-]: NAMECALL R3 R3 K47; var4 = var3; var3 = var3[0x33FC842F]
     137 [-]: CALL R3 0 2  ; var3 = var3(var4, ...)
     138 [-]: NAMECALL R4 R3 K48; var5 = var3; var4 = var3[0xBB610E5B]
     139 [-]: CALL R4 2 2  ; var4 = var4(var5)
     140 [-]: SETUPVAL R4 23; upvalues[4] = var23
L 5: 141 [-]: GETIMPORT R3 51; var3 = _T["DisableStores"]
     142 [-]: CALL R3 1 1  ; var3()
     143 [-]: GETUPVAL R3 1; var3 = upvalues[1]
     144 [-]: GETUPVAL R5 17; var5 = upvalues[17]
     145 [-]: LOADN R6 9999; var6 = 9999
     146 [-]: NAMECALL R3 R3 K52; var4 = var3; var3 = var3[0x0EB34C69]
     147 [-]: CALL R3 4 2  ; var3 = var3(var4, var5, var6)
     148 [-]: JUMPXEQKN R3 K53 L6 NOT; 
     149 [-]: LOADN R4 150 ; var4 = 150
     150 [-]: SETUPVAL R4 24; upvalues[4] = var24
     151 [-]: JUMP L7      ; goto L7
L 6: 152 [-]: SETUPVAL R3 24; upvalues[3] = var24
L 7: 153 [-]: GETIMPORT R5 55; var5 = _T["BaseReinforcements"]
     154 [-]: FASTCALL1 62 R5 L8; 
     155 [-]: GETIMPORT R4 25; var4 = 0x7B998233
     156 [-]: CALL R4 2 2  ; var4 = var4(var5)
L 8: 157 [-]: JUMPIFNOT R4 L9; goto L9 if not var4
     158 [-]: GETIMPORT R4 56; var4 = _T
     159 [-]: NEWTABLE R5 0 0; var5 = {}
     160 [-]: SETTABLEKS R5 R4 K54; var5["BaseReinforcements"] = var4
L 9: 161 [-]: GETUPVAL R4 2; var4 = upvalues[2]
     162 [-]: NAMECALL R4 R4 K57; var5 = var4; var4 = var4[0xABE61691]
     163 [-]: CALL R4 2 2  ; var4 = var4(var5)
     164 [-]: JUMPXEQKN R4 K58 L10 NOT; 
     165 [-]: GETUPVAL R5 2; var5 = upvalues[2]
     166 [-]: LOADN R7 1   ; var7 = 1
     167 [-]: NAMECALL R5 R5 K59; var6 = var5; var5 = var5[0x5B18BB5D]
     168 [-]: CALL R5 3 1  ; var5(var6, var7)
L10: 169 [-]: GETUPVAL R5 15; var5 = upvalues[15]
     170 [-]: GETUPVAL R8 25; var8 = upvalues[25]
     171 [-]: GETTABLEKS R7 R8 K60; var7 = var8[0x06D055F9]
     172 [-]: JUMPXEQKN R4 K58 L11; 
     173 [-]: LOADB R8 0 +1; var8 = false
L11: 174 [-]: LOADB R8 1   ; var8 = true
L12: 175 [-]: LOADN R9 1   ; var9 = 1
     176 [-]: MOVE R10 R4  ; var10 = var4
     177 [-]: CALL R7 4 0  ; var7, ... = var7(var8, var9, var10)
     178 [-]: NAMECALL R5 R5 K61; var6 = var5; var5 = var5[0x8ABFF40E]
     179 [-]: CALL R5 0 1  ; var5(var6, ...)
     180 [-]: NAMECALL R5 R0 K62; var6 = var0; var5 = var0[0xEFE6CAD1]
     181 [-]: CALL R5 2 2  ; var5 = var5(var6)
     182 [-]: LOADN R6 1   ; var6 = 1
     183 [-]: JUMPIFNOTEQ R5 R6 L13; goto L13 if var5 ~= var132935
     184 [-]: LOADN R7 2   ; var7 = 2
     185 [-]: NAMECALL R5 R0 K63; var6 = var0; var5 = var0[0xFE9DC265]
     186 [-]: CALL R5 3 1  ; var5(var6, var7)
L13: 187 [-]: GETIMPORT R5 1; var5 = 0x3D106989
     188 [-]: LOADK R6 K64 ; var6 = "Encounter: Solaris Base: Initialize complete"
     189 [-]: CALL R5 2 1  ; var5(var6)
     190 [-]: RETURN R0 0  ; 


; Name:            
; Defined at line: 328
; #Upvalues:       17
; #Parameters:     1
; Is_vararg:       0
; Max Stack Size:  13

       0 [-]: GETUPVAL R1 0; var1 = upvalues[0]
       1 [-]: MOVE R2 R0   ; var2 = var0
       2 [-]: CALL R1 2 1  ; var1(var2)
       3 [-]: LOADN R1 0   ; var1 = 0
       4 [-]: LOADNIL R2   ; var2 = nil
       5 [-]: LOADB R3 0   ; var3 = false
L 0:   6 [-]: NAMECALL R4 R0 K0; var5 = var0; var4 = var0[0xEFE6CAD1]
       7 [-]: CALL R4 2 2  ; var4 = var4(var5)
       8 [-]: LOADN R5 4   ; var5 = 4
       9 [-]: JUMPIFNOTLT R4 R5 L17; goto L17 if var4 >= var132174
      10 [-]: GETIMPORT R4 2; var4 = 0xFFF641AF
      11 [-]: CALL R4 1 2  ; var4 = var4()
      12 [-]: MOVE R1 R4   ; var1 = var4
      13 [-]: GETUPVAL R4 1; var4 = upvalues[1]
      14 [-]: NAMECALL R4 R4 K3; var5 = var4; var4 = var4[0x209398C2]
      15 [-]: CALL R4 2 2  ; var4 = var4(var5)
      16 [-]: MOVE R2 R4   ; var2 = var4
      17 [-]: JUMPXEQKN R2 K4 L9 NOT; 
      18 [-]: GETUPVAL R4 2; var4 = upvalues[2]
      19 [-]: MOVE R6 R1   ; var6 = var1
      20 [-]: NAMECALL R4 R4 K5; var5 = var4; var4 = var4[0xFAA69527]
      21 [-]: CALL R4 3 1  ; var4(var5, var6)
      22 [-]: GETUPVAL R4 3; var4 = upvalues[3]
      23 [-]: CALL R4 1 1  ; var4()
      24 [-]: GETUPVAL R6 5; var6 = upvalues[5]
      25 [-]: GETTABLEKS R5 R6 K6; var5 = var6[0x826F2CA6]
      26 [-]: CALL R5 1 2  ; var5 = var5()
      27 [-]: FASTCALL2K 18 R5 K7 L1; 
      28 [-]: LOADK R6 K7  ; var6 = 0
      29 [-]: GETIMPORT R4 10; var4 = 0x5BCED4C4[0xB62ECFE0]
      30 [-]: CALL R4 3 2  ; var4 = var4(var5, var6)
L 1:  31 [-]: SETUPVAL R4 4; upvalues[4] = var4
      32 [-]: GETUPVAL R4 6; var4 = upvalues[6]
      33 [-]: GETUPVAL R6 7; var6 = upvalues[7]
      34 [-]: GETUPVAL R8 4; var8 = upvalues[4]
      35 [-]: FASTCALL1 12 R8 L2; 
      36 [-]: GETIMPORT R7 12; var7 = 0x5BCED4C4[0x55F27C30]
      37 [-]: CALL R7 2 2  ; var7 = var7(var8)
L 2:  38 [-]: NAMECALL R4 R4 K13; var5 = var4; var4 = var4[0x751F061D]
      39 [-]: CALL R4 4 1  ; var4(var5, var6, var7)
      40 [-]: LOADN R6 150 ; var6 = 150
      41 [-]: GETUPVAL R7 4; var7 = upvalues[4]
      42 [-]: SUB R5 R6 R7 ; var5 = var6 - var7
      43 [-]: DIVK R4 R5 K14; var4 = var5 / 150
      44 [-]: GETUPVAL R5 4; var5 = upvalues[4]
      45 [-]: LOADN R6 0   ; var6 = 0
      46 [-]: JUMPIFNOTLE R5 R6 L3; goto L3 if var5 > var66823
      47 [-]: GETUPVAL R5 1; var5 = upvalues[1]
      48 [-]: LOADN R7 3   ; var7 = 3
      49 [-]: NAMECALL R5 R5 K15; var6 = var5; var5 = var5[0x8ABFF40E]
      50 [-]: CALL R5 3 1  ; var5(var6, var7)
      51 [-]: JUMP L7      ; goto L7
L 3:  52 [-]: GETIMPORT R6 18; var6 = _T["MaxAlertLevel"]
      53 [-]: FASTCALL1 62 R6 L4; 
      54 [-]: GETIMPORT R5 20; var5 = 0x7B998233
      55 [-]: CALL R5 2 2  ; var5 = var5(var6)
L 4:  56 [-]: JUMPIF R5 L7 ; goto L7 if var5
      57 [-]: GETUPVAL R5 8; var5 = upvalues[8]
      58 [-]: NAMECALL R5 R5 K21; var6 = var5; var5 = var5[0x78072CA1]
      59 [-]: CALL R5 2 2  ; var5 = var5(var6)
      60 [-]: GETIMPORT R9 23; var9 = 0x9BAFFFE3
      61 [-]: LOADN R10 1  ; var10 = 1
      62 [-]: GETIMPORT R11 18; var11 = _T["MaxAlertLevel"]
      63 [-]: MOVE R12 R4  ; var12 = var4
      64 [-]: CALL R9 4 2  ; var9 = var9(var10, var11, var12)
      65 [-]: FASTCALL1 7 R9 L5; 
      66 [-]: GETIMPORT R8 25; var8 = 0x5BCED4C4[0x99675E23]
      67 [-]: CALL R8 2 2  ; var8 = var8(var9)
L 5:  68 [-]: FASTCALL2 18 R5 R8 L6; 
      69 [-]: MOVE R7 R5   ; var7 = var5
      70 [-]: GETIMPORT R6 10; var6 = 0x5BCED4C4[0xB62ECFE0]
      71 [-]: CALL R6 3 2  ; var6 = var6(var7, var8)
L 6:  72 [-]: JUMPIFNOTLT R5 R6 L7; goto L7 if var5 >= var526087
      73 [-]: GETUPVAL R7 8; var7 = upvalues[8]
      74 [-]: MOVE R9 R6   ; var9 = var6
      75 [-]: NAMECALL R7 R7 K26; var8 = var7; var7 = var7[0x27D04ADD]
      76 [-]: CALL R7 3 1  ; var7(var8, var9)
      77 [-]: GETIMPORT R7 28; var7 = 0xD644C2F1
      78 [-]: LOADK R9 K29 ; var9 = "Base Capture: Alert level increased to "
      79 [-]: MOVE R10 R6  ; var10 = var6
      80 [-]: CONCAT R8 R9 R10; var8 = var9 .. var10
      81 [-]: CALL R7 2 1  ; var7(var8)
L 7:  82 [-]: JUMPIF R3 L8 ; goto L8 if var3
      83 [-]: LOADK R5 K30 ; var5 = 0.5
      84 [-]: JUMPIFNOTLE R5 R4 L8; goto L8 if var5 > var591367
      85 [-]: GETUPVAL R6 9; var6 = upvalues[9]
      86 [-]: GETTABLEKS R5 R6 K31; var5 = var6[0x9742B85B]
      87 [-]: GETUPVAL R6 10; var6 = upvalues[10]
      88 [-]: GETIMPORT R7 33; var7 = 0x0469F296
      89 [-]: LOADK R8 K34 ; var8 = "BaseCaptureHalf"
      90 [-]: CALL R7 2 0  ; var7, ... = var7(var8)
      91 [-]: CALL R5 0 1  ; var5(var6, ...)
      92 [-]: LOADB R3 1   ; var3 = true
L 8:  93 [-]: GETUPVAL R5 11; var5 = upvalues[11]
      94 [-]: NAMECALL R5 R5 K35; var6 = var5; var5 = var5[0xD2715720]
      95 [-]: CALL R5 2 2  ; var5 = var5(var6)
      96 [-]: LOADN R6 0   ; var6 = 0
      97 [-]: JUMPIFNOTLE R5 R6 L15; goto L15 if var5 > var66823
      98 [-]: GETUPVAL R5 1; var5 = upvalues[1]
      99 [-]: LOADN R7 5   ; var7 = 5
     100 [-]: NAMECALL R5 R5 K15; var6 = var5; var5 = var5[0x8ABFF40E]
     101 [-]: CALL R5 3 1  ; var5(var6, var7)
     102 [-]: JUMP L17     ; goto L17
     103 [-]: JUMP L15     ; goto L15
L 9: 104 [-]: JUMPXEQKN R2 K36 L15 NOT; 
     105 [-]: GETUPVAL R4 6; var4 = upvalues[6]
     106 [-]: GETUPVAL R6 12; var6 = upvalues[12]
     107 [-]: NAMECALL R4 R4 K37; var5 = var4; var4 = var4[0x0EB34C69]
     108 [-]: CALL R4 3 2  ; var4 = var4(var5, var6)
     109 [-]: GETUPVAL R5 6; var5 = upvalues[6]
     110 [-]: GETUPVAL R7 13; var7 = upvalues[13]
     111 [-]: NAMECALL R5 R5 K37; var6 = var5; var5 = var5[0x0EB34C69]
     112 [-]: CALL R5 3 2  ; var5 = var5(var6, var7)
     113 [-]: JUMPIFNOTLE R5 R4 L10; goto L10 if var5 > var67079
     114 [-]: GETUPVAL R6 1; var6 = upvalues[1]
     115 [-]: LOADN R8 4   ; var8 = 4
     116 [-]: NAMECALL R6 R6 K15; var7 = var6; var6 = var6[0x8ABFF40E]
     117 [-]: CALL R6 3 1  ; var6(var7, var8)
     118 [-]: JUMP L17     ; goto L17
L10: 119 [-]: GETUPVAL R9 14; var9 = upvalues[14]
     120 [-]: LENGTH R8 R9 ; var8 = #var9
     121 [-]: LOADN R6 1   ; var6 = 1
     122 [-]: LOADN R7 -1  ; var7 = -1
     123 [-]: FORNPREP R6 L14; nforprep start - [escape at L14] -- var6 = iterator
L11: 124 [-]: GETUPVAL R11 14; var11 = upvalues[14]
     125 [-]: GETTABLE R10 R11 R8; var10 = var11[var8]
     126 [-]: FASTCALL1 62 R10 L12; 
     127 [-]: GETIMPORT R9 20; var9 = 0x7B998233
     128 [-]: CALL R9 2 2  ; var9 = var9(var10)
L12: 129 [-]: JUMPIFNOT R9 L13; goto L13 if not var9
     130 [-]: GETIMPORT R9 40; var9 = 0x33BDD652[0x9C1F3B5A]
     131 [-]: GETUPVAL R10 14; var10 = upvalues[14]
     132 [-]: MOVE R11 R8  ; var11 = var8
     133 [-]: CALL R9 3 1  ; var9(var10, var11)
L13: 134 [-]: FORNLOOP R6 L11; nforloop end - iterate + goto L11
L14: 135 [-]: GETUPVAL R8 14; var8 = upvalues[14]
     136 [-]: LENGTH R7 R8 ; var7 = #var8
     137 [-]: ADD R6 R7 R4 ; var6 = var7 + var4
     138 [-]: JUMPIFNOTLT R6 R5 L15; goto L15 if var6 >= var394759
     139 [-]: GETUPVAL R6 6; var6 = upvalues[6]
     140 [-]: GETUPVAL R8 13; var8 = upvalues[13]
     141 [-]: GETUPVAL R10 14; var10 = upvalues[14]
     142 [-]: LENGTH R9 R10; var9 = #var10
     143 [-]: NAMECALL R6 R6 K37; var7 = var6; var6 = var6[0x0EB34C69]
     144 [-]: CALL R6 4 1  ; var6(var7, var8, var9)
     145 [-]: GETUPVAL R7 5; var7 = upvalues[5]
     146 [-]: GETTABLEKS R6 R7 K41; var6 = var7[0xF3928F38]
     147 [-]: MOVE R7 R4   ; var7 = var4
     148 [-]: GETUPVAL R9 14; var9 = upvalues[14]
     149 [-]: LENGTH R8 R9 ; var8 = #var9
     150 [-]: CALL R6 3 1  ; var6(var7, var8)
L15: 151 [-]: NAMECALL R4 R0 K42; var5 = var0; var4 = var0[0xD9531187]
     152 [-]: CALL R4 2 2  ; var4 = var4(var5)
     153 [-]: JUMPIFNOT R4 L16; goto L16 if not var4
     154 [-]: GETUPVAL R4 1; var4 = upvalues[1]
     155 [-]: LOADN R6 5   ; var6 = 5
     156 [-]: NAMECALL R4 R4 K15; var5 = var4; var4 = var4[0x8ABFF40E]
     157 [-]: CALL R4 3 1  ; var4(var5, var6)
     158 [-]: JUMP L17     ; goto L17
L16: 159 [-]: GETUPVAL R4 15; var4 = upvalues[15]
     160 [-]: MOVE R6 R1   ; var6 = var1
     161 [-]: NAMECALL R4 R4 K5; var5 = var4; var4 = var4[0xFAA69527]
     162 [-]: CALL R4 3 1  ; var4(var5, var6)
     163 [-]: GETIMPORT R4 44; var4 = 0xCBD666E1
     164 [-]: LOADN R5 0   ; var5 = 0
     165 [-]: CALL R4 2 1  ; var4(var5)
     166 [-]: JUMPBACK L0  ; goto L0
L17: 167 [-]: GETUPVAL R4 1; var4 = upvalues[1]
     168 [-]: NAMECALL R4 R4 K3; var5 = var4; var4 = var4[0x209398C2]
     169 [-]: CALL R4 2 2  ; var4 = var4(var5)
     170 [-]: MOVE R2 R4   ; var2 = var4
     171 [-]: JUMPXEQKN R2 K45 L18 NOT; 
     172 [-]: GETUPVAL R4 16; var4 = upvalues[16]
     173 [-]: LOADN R6 4   ; var6 = 4
     174 [-]: NAMECALL R4 R4 K46; var5 = var4; var4 = var4[0xFE9DC265]
     175 [-]: CALL R4 3 1  ; var4(var5, var6)
     176 [-]: JUMP L19     ; goto L19
L18: 177 [-]: JUMPXEQKN R2 K47 L19 NOT; 
     178 [-]: GETUPVAL R4 16; var4 = upvalues[16]
     179 [-]: LOADN R6 5   ; var6 = 5
     180 [-]: NAMECALL R4 R4 K46; var5 = var4; var4 = var4[0xFE9DC265]
     181 [-]: CALL R4 3 1  ; var4(var5, var6)
L19: 182 [-]: GETIMPORT R6 33; var6 = 0x0469F296
     183 [-]: LOADK R7 K48 ; var7 = "LeavingCB"
     184 [-]: CALL R6 2 0  ; var6, ... = var6(var7)
     185 [-]: NAMECALL R4 R0 K49; var5 = var0; var4 = var0[0x3D412E0D]
     186 [-]: CALL R4 0 1  ; var4(var5, ...)
     187 [-]: GETIMPORT R6 33; var6 = 0x0469F296
     188 [-]: LOADK R7 K50 ; var7 = "ReturningCB"
     189 [-]: CALL R6 2 0  ; var6, ... = var6(var7)
     190 [-]: NAMECALL R4 R0 K51; var5 = var0; var4 = var0[0x136A027D]
     191 [-]: CALL R4 0 1  ; var4(var5, ...)
     192 [-]: GETIMPORT R4 53; var4 = 0x3D106989
     193 [-]: LOADK R5 K54 ; var5 = "Encounter: Solaris Base: Shutdown complete"
     194 [-]: CALL R4 2 1  ; var4(var5)
     195 [-]: RETURN R0 0  ; 


; Name:            
; Defined at line: 412
; #Upvalues:       1
; #Parameters:     0
; Is_vararg:       0
; Max Stack Size:  2

       0 [-]: GETIMPORT R0 1; var0 = 0x89326C93
       1 [-]: NAMECALL R0 R0 K2; var1 = var0; var0 = var0[0x7D108DDB]
       2 [-]: CALL R0 2 2  ; var0 = var0(var1)
       3 [-]: SETUPVAL R0 0; upvalues[0] = var0
       4 [-]: RETURN R0 0  ; 


; Name:            
; Defined at line: 416
; #Upvalues:       3
; #Parameters:     1
; Is_vararg:       0
; Max Stack Size:  7

       0 [-]: GETIMPORT R1 1; var1 = 0xBE190284
       1 [-]: GETUPVAL R3 0; var3 = upvalues[0]
       2 [-]: NAMECALL R1 R1 K2; var2 = var1; var1 = var1[0x0EB34C69]
       3 [-]: CALL R1 3 2  ; var1 = var1(var2, var3)
       4 [-]: LOADN R2 0   ; var2 = 0
       5 [-]: JUMPIFNOTLT R2 R1 L0; goto L0 if var2 >= var66126
       6 [-]: GETIMPORT R2 1; var2 = 0xBE190284
       7 [-]: GETUPVAL R4 1; var4 = upvalues[1]
       8 [-]: NAMECALL R2 R2 K2; var3 = var2; var2 = var2[0x0EB34C69]
       9 [-]: CALL R2 3 2  ; var2 = var2(var3, var4)
      10 [-]: GETIMPORT R3 1; var3 = 0xBE190284
      11 [-]: GETUPVAL R5 1; var5 = upvalues[1]
      12 [-]: ADDK R6 R2 K3; var6 = var2 + 1
      13 [-]: NAMECALL R3 R3 K4; var4 = var3; var3 = var3[0x751F061D]
      14 [-]: CALL R3 4 1  ; var3(var4, var5, var6)
      15 [-]: GETUPVAL R4 2; var4 = upvalues[2]
      16 [-]: GETTABLEKS R3 R4 K5; var3 = var4[0xF3928F38]
      17 [-]: ADDK R4 R2 K3; var4 = var2 + 1
      18 [-]: MOVE R5 R1   ; var5 = var1
      19 [-]: CALL R3 3 1  ; var3(var4, var5)
L 0:  20 [-]: RETURN R0 0  ; 


; Name:            
; Defined at line: 425
; #Upvalues:       1
; #Parameters:     1
; Is_vararg:       0
; Max Stack Size:  4

       0 [-]: GETIMPORT R1 1; var1 = 0x11A19C5E
       1 [-]: NAMECALL R2 R0 K2; var3 = var0; var2 = var0[0xBB610E5B]
       2 [-]: CALL R2 2 2  ; var2 = var2(var3)
       3 [-]: LOADK R3 K3  ; var3 = "OnKilled"
       4 [-]: CALL R1 3 1  ; var1(var2, var3)
       5 [-]: GETUPVAL R3 0; var3 = upvalues[0]
       6 [-]: NAMECALL R1 R0 K4; var2 = var0; var1 = var0[0xA64A1F4A]
       7 [-]: CALL R1 3 1  ; var1(var2, var3)
       8 [-]: RETURN R0 0  ; 


; Name:            
; Defined at line: 430
; #Upvalues:       2
; #Parameters:     0
; Is_vararg:       0
; Max Stack Size:  3

       0 [-]: GETUPVAL R1 0; var1 = upvalues[0]
       1 [-]: GETTABLEKS R0 R1 K0; var0 = var1[0x7E8A976A]
       2 [-]: GETUPVAL R1 1; var1 = upvalues[1]
       3 [-]: LOADB R2 1   ; var2 = true
       4 [-]: CALL R0 3 1  ; var0(var1, var2)
       5 [-]: RETURN R0 0  ; 


; Name:            
; Defined at line: 434
; #Upvalues:       2
; #Parameters:     0
; Is_vararg:       0
; Max Stack Size:  3

       0 [-]: GETUPVAL R1 0; var1 = upvalues[0]
       1 [-]: GETTABLEKS R0 R1 K0; var0 = var1[0x7E8A976A]
       2 [-]: GETUPVAL R1 1; var1 = upvalues[1]
       3 [-]: LOADB R2 0   ; var2 = false
       4 [-]: CALL R0 3 1  ; var0(var1, var2)
       5 [-]: RETURN R0 0  ; 


; Name:            
; Defined at line: 438
; #Upvalues:       0
; #Parameters:     1
; Is_vararg:       0
; Max Stack Size:  8

       0 [-]: GETIMPORT R1 1; var1 = 0x89326C93
       1 [-]: NAMECALL R1 R1 K2; var2 = var1; var1 = var1[0x18D05D30]
       2 [-]: CALL R1 2 2  ; var1 = var1(var2)
       3 [-]: JUMPIFNOT R1 L0; goto L0 if not var1
       4 [-]: GETIMPORT R1 1; var1 = 0x89326C93
       5 [-]: NAMECALL R1 R1 K3; var2 = var1; var1 = var1[0x29EF273D]
       6 [-]: CALL R1 2 2  ; var1 = var1(var2)
       7 [-]: NAMECALL R1 R1 K4; var2 = var1; var1 = var1[0x66905CB0]
       8 [-]: CALL R1 2 2  ; var1 = var1(var2)
       9 [-]: GETIMPORT R2 1; var2 = 0x89326C93
      10 [-]: GETIMPORT R4 6; var4 = 0x0469F296
      11 [-]: LOADK R5 K7  ; var5 = "CapturableCampHint"
      12 [-]: CALL R4 2 2  ; var4 = var4(var5)
      13 [-]: NAMECALL R5 R0 K8; var6 = var0; var5 = var0[0xD1586535]
      14 [-]: CALL R5 2 0  ; var5, ... = var5(var6)
      15 [-]: NAMECALL R2 R2 K9; var3 = var2; var2 = var2[0xC7B81E8D]
      16 [-]: CALL R2 0 2  ; var2 = var2(var3, ...)
      17 [-]: NAMECALL R5 R0 K8; var6 = var0; var5 = var0[0xD1586535]
      18 [-]: CALL R5 2 2  ; var5 = var5(var6)
      19 [-]: GETIMPORT R6 11; var6 = 0xF7B712E9
      20 [-]: MOVE R7 R2   ; var7 = var2
      21 [-]: NAMECALL R3 R1 K12; var4 = var1; var3 = var1[0x44C55B21]
      22 [-]: CALL R3 5 1  ; var3(var4, var5, var6, var7)
      23 [-]: NAMECALL R3 R0 K13; var4 = var0; var3 = var0[0x2B54251B]
      24 [-]: CALL R3 2 2  ; var3 = var3(var4)
      25 [-]: NAMECALL R4 R3 K14; var5 = var3; var4 = var3[0x5710748F]
      26 [-]: CALL R4 2 1  ; var4(var5)
L 0:  27 [-]: RETURN R0 0  ; 


; Name:            
; Defined at line: 448
; #Upvalues:       0
; #Parameters:     3
; Is_vararg:       0
; Max Stack Size:  13

       0 [-]: GETIMPORT R3 1; var3 = 0xC8802016
       1 [-]: MOVE R4 R1   ; var4 = var1
       2 [-]: CALL R3 2 4  ; var3, var4, var5 = var3(var4)
       3 [-]: FORGPREP_INEXT R3 L2; 
L 0:   4 [-]: NAMECALL R8 R7 K2; var9 = var7; var8 = var7[0x1E3535E5]
       5 [-]: CALL R8 2 2  ; var8 = var8(var9)
       6 [-]: FASTCALL1 62 R8 L1; 
       7 [-]: MOVE R10 R8  ; var10 = var8
       8 [-]: GETIMPORT R9 4; var9 = 0x7B998233
       9 [-]: CALL R9 2 2  ; var9 = var9(var10)
L 1:  10 [-]: JUMPIF R9 L2 ; goto L2 if var9
      11 [-]: MOVE R11 R0  ; var11 = var0
      12 [-]: MOVE R12 R2  ; var12 = var2
      13 [-]: NAMECALL R9 R8 K5; var10 = var8; var9 = var8[0xFAF7BD22]
      14 [-]: CALL R9 4 1  ; var9(var10, var11, var12)
L 2:  15 [-]: FORGLOOP R3 L0 2 [inext]; 
      16 [-]: RETURN R0 0  ; 


; Name:            
; Defined at line: 458
; #Upvalues:       5
; #Parameters:     1
; Is_vararg:       0
; Max Stack Size:  26

       0 [-]: GETIMPORT R1 1; var1 = 0x3D106989
       1 [-]: LOADK R2 K2  ; var2 = "Encounter: Camp Beacon: Starting..."
       2 [-]: CALL R1 2 1  ; var1(var2)
       3 [-]: GETIMPORT R1 4; var1 = 0x89326C93
       4 [-]: NAMECALL R1 R1 K5; var2 = var1; var1 = var1[0x29EF273D]
       5 [-]: CALL R1 2 2  ; var1 = var1(var2)
       6 [-]: NAMECALL R1 R1 K6; var2 = var1; var1 = var1[0x66905CB0]
       7 [-]: CALL R1 2 2  ; var1 = var1(var2)
L 0:   8 [-]: NAMECALL R2 R1 K7; var3 = var1; var2 = var1[0xA2D83ED4]
       9 [-]: CALL R2 2 2  ; var2 = var2(var3)
      10 [-]: JUMPIF R2 L1 ; goto L1 if var2
      11 [-]: GETIMPORT R2 9; var2 = 0xCBD666E1
      12 [-]: LOADN R3 0   ; var3 = 0
      13 [-]: CALL R2 2 1  ; var2(var3)
      14 [-]: JUMPBACK L0  ; goto L0
L 1:  15 [-]: GETUPVAL R3 0; var3 = upvalues[0]
      16 [-]: GETTABLEKS R2 R3 K10; var2 = var3[0x200054F6]
      17 [-]: GETUPVAL R3 1; var3 = upvalues[1]
      18 [-]: CALL R2 2 2  ; var2 = var2(var3)
      19 [-]: JUMPIF R2 L2 ; goto L2 if var2
      20 [-]: GETIMPORT R2 1; var2 = 0x3D106989
      21 [-]: LOADK R3 K11 ; var3 = "Encounter: Camp Beacon: Requires Solaris quest completion, shutting down."
      22 [-]: CALL R2 2 1  ; var2(var3)
      23 [-]: RETURN R0 0  ; 
L 2:  24 [-]: GETIMPORT R2 1; var2 = 0x3D106989
      25 [-]: LOADK R3 K12 ; var3 = "Encounter: Camp Beacon: Started"
      26 [-]: CALL R2 2 1  ; var2(var3)
      27 [-]: GETIMPORT R2 14; var2 = 0x0469F296
      28 [-]: LOADK R3 K15 ; var3 = "SolarisCamp"
      29 [-]: CALL R2 2 2  ; var2 = var2(var3)
      30 [-]: GETUPVAL R4 2; var4 = upvalues[2]
      31 [-]: GETTABLEKS R3 R4 K16; var3 = var4[0xBD9A0502]
      32 [-]: MOVE R4 R0   ; var4 = var0
      33 [-]: LOADNIL R5   ; var5 = nil
      34 [-]: GETIMPORT R6 14; var6 = 0x0469F296
      35 [-]: LOADK R7 K17 ; var7 = "SolarisConsoleActiveForwarder"
      36 [-]: CALL R6 2 0  ; var6, ... = var6(var7)
      37 [-]: CALL R3 0 2  ; var3 = var3(var4, ...)
      38 [-]: GETUPVAL R5 2; var5 = upvalues[2]
      39 [-]: GETTABLEKS R4 R5 K16; var4 = var5[0xBD9A0502]
      40 [-]: MOVE R5 R0   ; var5 = var0
      41 [-]: LOADNIL R6   ; var6 = nil
      42 [-]: GETIMPORT R7 14; var7 = 0x0469F296
      43 [-]: LOADK R8 K18 ; var8 = "SolarisConsoleCapturedForwarder"
      44 [-]: CALL R7 2 0  ; var7, ... = var7(var8)
      45 [-]: CALL R4 0 2  ; var4 = var4(var5, ...)
      46 [-]: GETUPVAL R6 2; var6 = upvalues[2]
      47 [-]: GETTABLEKS R5 R6 K16; var5 = var6[0xBD9A0502]
      48 [-]: MOVE R6 R0   ; var6 = var0
      49 [-]: LOADNIL R7   ; var7 = nil
      50 [-]: GETIMPORT R8 14; var8 = 0x0469F296
      51 [-]: LOADK R9 K19 ; var9 = "SolarisConsoleResetForwarder"
      52 [-]: CALL R8 2 0  ; var8, ... = var8(var9)
      53 [-]: CALL R5 0 2  ; var5 = var5(var6, ...)
      54 [-]: GETUPVAL R7 2; var7 = upvalues[2]
      55 [-]: GETTABLEKS R6 R7 K16; var6 = var7[0xBD9A0502]
      56 [-]: MOVE R7 R0   ; var7 = var0
      57 [-]: LOADNIL R8   ; var8 = nil
      58 [-]: GETIMPORT R9 14; var9 = 0x0469F296
      59 [-]: LOADK R10 K20; var10 = "CapturedCampMarker"
      60 [-]: CALL R9 2 0  ; var9, ... = var9(var10)
      61 [-]: CALL R6 0 2  ; var6 = var6(var7, ...)
      62 [-]: FASTCALL1 62 R3 L3; 
      63 [-]: MOVE R8 R3   ; var8 = var3
      64 [-]: GETIMPORT R7 22; var7 = 0x7B998233
      65 [-]: CALL R7 2 2  ; var7 = var7(var8)
L 3:  66 [-]: JUMPIF R7 L6 ; goto L6 if var7
      67 [-]: FASTCALL1 62 R4 L4; 
      68 [-]: MOVE R8 R4   ; var8 = var4
      69 [-]: GETIMPORT R7 22; var7 = 0x7B998233
      70 [-]: CALL R7 2 2  ; var7 = var7(var8)
L 4:  71 [-]: JUMPIF R7 L6 ; goto L6 if var7
      72 [-]: FASTCALL1 62 R5 L5; 
      73 [-]: MOVE R8 R5   ; var8 = var5
      74 [-]: GETIMPORT R7 22; var7 = 0x7B998233
      75 [-]: CALL R7 2 2  ; var7 = var7(var8)
L 5:  76 [-]: JUMPIFNOT R7 L7; goto L7 if not var7
L 6:  77 [-]: RETURN R0 0  ; 
L 7:  78 [-]: GETIMPORT R7 4; var7 = 0x89326C93
      79 [-]: GETIMPORT R9 14; var9 = 0x0469F296
      80 [-]: LOADK R10 K23; var10 = "CapturableCampHint"
      81 [-]: CALL R9 2 2  ; var9 = var9(var10)
      82 [-]: NAMECALL R10 R0 K24; var11 = var0; var10 = var0[0xD1586535]
      83 [-]: CALL R10 2 2 ; var10 = var10(var11)
      84 [-]: LOADN R11 0  ; var11 = 0
      85 [-]: LOADN R12 200; var12 = 200
      86 [-]: NAMECALL R7 R7 K25; var8 = var7; var7 = var7[0x462C251C]
      87 [-]: CALL R7 6 2  ; var7 = var7(var8, var9, var10, var11, var12)
      88 [-]: FASTCALL1 62 R7 L8; 
      89 [-]: MOVE R9 R7   ; var9 = var7
      90 [-]: GETIMPORT R8 22; var8 = 0x7B998233
      91 [-]: CALL R8 2 2  ; var8 = var8(var9)
L 8:  92 [-]: JUMPIFNOT R8 L9; goto L9 if not var8
      93 [-]: RETURN R0 0  ; 
L 9:  94 [-]: NAMECALL R8 R7 K26; var9 = var7; var8 = var7[0x891629FA]
      95 [-]: CALL R8 2 2  ; var8 = var8(var9)
      96 [-]: MOVE R9 R8   ; var9 = var8
      97 [-]: LOADN R10 0  ; var10 = 0
      98 [-]: NAMECALL R11 R8 K24; var12 = var8; var11 = var8[0xD1586535]
      99 [-]: CALL R11 2 2 ; var11 = var11(var12)
     100 [-]: NAMECALL R12 R8 K27; var13 = var8; var12 = var8[0xC5B92518]
     101 [-]: CALL R12 2 2 ; var12 = var12(var13)
     102 [-]: GETIMPORT R13 4; var13 = 0x89326C93
     103 [-]: GETIMPORT R15 14; var15 = 0x0469F296
     104 [-]: LOADK R16 K28; var16 = "BountyGiverEnable"
     105 [-]: CALL R15 2 2 ; var15 = var15(var16)
     106 [-]: MOVE R16 R11 ; var16 = var11
     107 [-]: NAMECALL R13 R13 K29; var14 = var13; var13 = var13[0xC7B81E8D]
     108 [-]: CALL R13 4 2 ; var13 = var13(var14, var15, var16)
     109 [-]: GETIMPORT R14 4; var14 = 0x89326C93
     110 [-]: GETIMPORT R16 14; var16 = 0x0469F296
     111 [-]: LOADK R17 K30; var17 = "BountyGiverDisable"
     112 [-]: CALL R16 2 2 ; var16 = var16(var17)
     113 [-]: MOVE R17 R11 ; var17 = var11
     114 [-]: NAMECALL R14 R14 K29; var15 = var14; var14 = var14[0xC7B81E8D]
     115 [-]: CALL R14 4 2 ; var14 = var14(var15, var16, var17)
     116 [-]: GETIMPORT R15 4; var15 = 0x89326C93
     117 [-]: GETIMPORT R17 14; var17 = 0x0469F296
     118 [-]: LOADK R18 K31; var18 = "SmallTurretSpawn"
     119 [-]: CALL R17 2 2 ; var17 = var17(var18)
     120 [-]: MOVE R18 R11 ; var18 = var11
     121 [-]: LOADN R19 0  ; var19 = 0
     122 [-]: MOVE R20 R12 ; var20 = var12
     123 [-]: NAMECALL R15 R15 K32; var16 = var15; var15 = var15[0xF16592C8]
     124 [-]: CALL R15 6 2 ; var15 = var15(var16, var17, var18, var19, var20)
     125 [-]: NAMECALL R16 R8 K33; var17 = var8; var16 = var8[0x32DE3AB1]
     126 [-]: CALL R16 2 2 ; var16 = var16(var17)
     127 [-]: FASTCALL1 62 R16 L10; 
     128 [-]: MOVE R18 R16 ; var18 = var16
     129 [-]: GETIMPORT R17 22; var17 = 0x7B998233
     130 [-]: CALL R17 2 2 ; var17 = var17(var18)
L10: 131 [-]: JUMPIF R17 L14; goto L14 if var17
     132 [-]: NAMECALL R17 R16 K34; var18 = var16; var17 = var16[0x5252E77D]
     133 [-]: CALL R17 2 2 ; var17 = var17(var18)
     134 [-]: GETIMPORT R18 36; var18 = 0xC8802016
     135 [-]: MOVE R19 R17 ; var19 = var17
     136 [-]: CALL R18 2 4 ; var18, var19, var20 = var18(var19)
     137 [-]: FORGPREP_INEXT R18 L13; 
L11: 138 [-]: FASTCALL1 62 R22 L12; 
     139 [-]: MOVE R24 R22 ; var24 = var22
     140 [-]: GETIMPORT R23 22; var23 = 0x7B998233
     141 [-]: CALL R23 2 2 ; var23 = var23(var24)
L12: 142 [-]: JUMPIF R23 L13; goto L13 if var23
     143 [-]: MOVE R25 R11 ; var25 = var11
     144 [-]: NAMECALL R23 R22 K37; var24 = var22; var23 = var22[0x1F420A3A]
     145 [-]: CALL R23 3 2 ; var23 = var23(var24, var25)
     146 [-]: JUMPIFNOTLT R10 R23 L13; goto L13 if var10 >= var1509910
     147 [-]: MOVE R10 R23 ; var10 = var23
     148 [-]: MOVE R9 R22  ; var9 = var22
L13: 149 [-]: FORGLOOP R18 L11 2 [inext]; 
L14: 150 [-]: FASTCALL1 62 R6 L15; 
     151 [-]: MOVE R18 R6  ; var18 = var6
     152 [-]: GETIMPORT R17 22; var17 = 0x7B998233
     153 [-]: CALL R17 2 2 ; var17 = var17(var18)
L15: 154 [-]: JUMPIF R17 L17; goto L17 if var17
     155 [-]: NAMECALL R20 R9 K38; var21 = var9; var20 = var9[0xF6CF204F]
     156 [-]: CALL R20 2 2 ; var20 = var20(var21)
     157 [-]: ADD R19 R10 R20; var19 = var10 + var20
     158 [-]: FASTCALL2 18 R12 R19 L16; 
     159 [-]: MOVE R18 R12 ; var18 = var12
     160 [-]: GETIMPORT R17 41; var17 = 0x5BCED4C4[0xB62ECFE0]
     161 [-]: CALL R17 3 2 ; var17 = var17(var18, var19)
L16: 162 [-]: MOVE R20 R11 ; var20 = var11
     163 [-]: NAMECALL R18 R6 K42; var19 = var6; var18 = var6[0x9307AA51]
     164 [-]: CALL R18 3 1 ; var18(var19, var20)
     165 [-]: MOVE R20 R17 ; var20 = var17
     166 [-]: NAMECALL R18 R6 K43; var19 = var6; var18 = var6[0x5004BE24]
     167 [-]: CALL R18 3 1 ; var18(var19, var20)
     168 [-]: GETIMPORT R20 45; var20 = 0xB7CBD06B
     169 [-]: MOVE R21 R17 ; var21 = var17
     170 [-]: LOADN R22 5000; var22 = 5000
     171 [-]: CALL R20 3 0 ; var20, ... = var20(var21, var22)
     172 [-]: NAMECALL R18 R6 K46; var19 = var6; var18 = var6[0x53BC0559]
     173 [-]: CALL R18 0 1 ; var18(var19, ...)
L17: 174 [-]: LOADN R17 0  ; var17 = 0
     175 [-]: LOADNIL R18  ; var18 = nil
     176 [-]: GETIMPORT R19 1; var19 = 0x3D106989
     177 [-]: LOADK R20 K12; var20 = "Encounter: Camp Beacon: Started"
     178 [-]: CALL R19 2 1 ; var19(var20)
L18: 179 [-]: NAMECALL R19 R0 K47; var20 = var0; var19 = var0[0xD9531187]
     180 [-]: CALL R19 2 2 ; var19 = var19(var20)
     181 [-]: JUMPIF R19 L32; goto L32 if var19
     182 [-]: GETUPVAL R20 2; var20 = upvalues[2]
     183 [-]: GETTABLEKS R19 R20 K48; var19 = var20[0xE2E65329]
     184 [-]: MOVE R20 R8  ; var20 = var8
     185 [-]: CALL R19 2 2 ; var19 = var19(var20)
     186 [-]: JUMPIFNOT R19 L19; goto L19 if not var19
     187 [-]: LOADN R17 2  ; var17 = 2
     188 [-]: JUMP L25     ; goto L25
L19: 189 [-]: GETIMPORT R20 51; var20 = _T["DynamicMission"]
     190 [-]: FASTCALL1 62 R20 L20; 
     191 [-]: GETIMPORT R19 22; var19 = 0x7B998233
     192 [-]: CALL R19 2 2 ; var19 = var19(var20)
L20: 193 [-]: JUMPIFNOT R19 L22; goto L22 if not var19
     194 [-]: GETIMPORT R20 53; var20 = _T["ActiveJob"]
     195 [-]: FASTCALL1 62 R20 L21; 
     196 [-]: GETIMPORT R19 22; var19 = 0x7B998233
     197 [-]: CALL R19 2 2 ; var19 = var19(var20)
L21: 198 [-]: JUMPIF R19 L23; goto L23 if var19
L22: 199 [-]: GETIMPORT R19 55; var19 = _T["BaseCaptureObjectiveHint"]
     200 [-]: JUMPIFNOTEQ R19 R8 L24; goto L24 if var19 ~= var69959
L23: 201 [-]: LOADN R17 1  ; var17 = 1
     202 [-]: JUMP L25     ; goto L25
L24: 203 [-]: LOADN R17 0  ; var17 = 0
L25: 204 [-]: JUMPIFEQ R17 R18 L31; goto L31 if var17 == var1446192
     205 [-]: JUMPXEQKN R17 K56 L26 NOT; 
     206 [-]: LOADK R21 K57; var21 = "TriggerPort"
     207 [-]: NAMECALL R19 R4 K58; var20 = var4; var19 = var4[0x8EB2112D]
     208 [-]: CALL R19 3 1 ; var19(var20, var21)
     209 [-]: LOADK R21 K57; var21 = "TriggerPort"
     210 [-]: NAMECALL R19 R13 K58; var20 = var13; var19 = var13[0x8EB2112D]
     211 [-]: CALL R19 3 1 ; var19(var20, var21)
     212 [-]: GETUPVAL R19 3; var19 = upvalues[3]
     213 [-]: MOVE R20 R2  ; var20 = var2
     214 [-]: MOVE R21 R15 ; var21 = var15
     215 [-]: GETIMPORT R22 14; var22 = 0x0469F296
     216 [-]: LOADK R23 K59; var23 = "TENNO"
     217 [-]: CALL R22 2 0 ; var22, ... = var22(var23)
     218 [-]: CALL R19 0 1 ; var19(var20, ...)
     219 [-]: GETIMPORT R19 1; var19 = 0x3D106989
     220 [-]: LOADK R20 K60; var20 = "Encounter: Camp Beacon: AREA_CAPTURED"
     221 [-]: CALL R19 2 1 ; var19(var20)
     222 [-]: JUMP L31     ; goto L31
L26: 223 [-]: JUMPXEQKN R17 K61 L30 NOT; 
     224 [-]: LOADK R21 K57; var21 = "TriggerPort"
     225 [-]: NAMECALL R19 R3 K58; var20 = var3; var19 = var3[0x8EB2112D]
     226 [-]: CALL R19 3 1 ; var19(var20, var21)
     227 [-]: LOADK R21 K57; var21 = "TriggerPort"
     228 [-]: NAMECALL R19 R14 K58; var20 = var14; var19 = var14[0x8EB2112D]
     229 [-]: CALL R19 3 1 ; var19(var20, var21)
     230 [-]: GETUPVAL R19 3; var19 = upvalues[3]
     231 [-]: MOVE R20 R2  ; var20 = var2
     232 [-]: MOVE R21 R15 ; var21 = var15
     233 [-]: GETIMPORT R22 63; var22 = 0x5AA2084E
     234 [-]: CALL R19 4 1 ; var19(var20, var21, var22)
     235 [-]: GETIMPORT R19 1; var19 = 0x3D106989
     236 [-]: LOADK R20 K64; var20 = "Encounter: Camp Beacon: AREA_ACTIVE"
     237 [-]: CALL R19 2 1 ; var19(var20)
     238 [-]: FASTCALL1 62 R18 L27; 
     239 [-]: MOVE R20 R18 ; var20 = var18
     240 [-]: GETIMPORT R19 22; var19 = 0x7B998233
     241 [-]: CALL R19 2 2 ; var19 = var19(var20)
L27: 242 [-]: JUMPIFNOT R19 L29; goto L29 if not var19
     243 [-]: FASTCALL1 62 R18 L28; 
     244 [-]: MOVE R20 R18 ; var20 = var18
     245 [-]: GETIMPORT R19 22; var19 = 0x7B998233
     246 [-]: CALL R19 2 2 ; var19 = var19(var20)
L28: 247 [-]: JUMPIFNOT R19 L31; goto L31 if not var19
     248 [-]: NAMECALL R19 R8 K65; var20 = var8; var19 = var8[0x1E0AEEEC]
     249 [-]: CALL R19 2 2 ; var19 = var19(var20)
     250 [-]: JUMPIF R19 L29; goto L29 if var19
     251 [-]: NAMECALL R19 R8 K66; var20 = var8; var19 = var8[0xBE21D4F6]
     252 [-]: CALL R19 2 2 ; var19 = var19(var20)
     253 [-]: JUMPIFNOT R19 L31; goto L31 if not var19
L29: 254 [-]: NAMECALL R21 R0 K24; var22 = var0; var21 = var0[0xD1586535]
     255 [-]: CALL R21 2 2 ; var21 = var21(var22)
     256 [-]: GETIMPORT R22 68; var22 = 0xCD06F26B
     257 [-]: MOVE R23 R0  ; var23 = var0
     258 [-]: LOADN R24 5  ; var24 = 5
     259 [-]: NAMECALL R19 R1 K69; var20 = var1; var19 = var1[0x44C55B21]
     260 [-]: CALL R19 6 1 ; var19(var20, var21, var22, var23, var24)
     261 [-]: JUMP L31     ; goto L31
L30: 262 [-]: JUMPXEQKN R17 K70 L31 NOT; 
     263 [-]: LOADK R21 K57; var21 = "TriggerPort"
     264 [-]: NAMECALL R19 R5 K58; var20 = var5; var19 = var5[0x8EB2112D]
     265 [-]: CALL R19 3 1 ; var19(var20, var21)
     266 [-]: LOADK R21 K57; var21 = "TriggerPort"
     267 [-]: NAMECALL R19 R14 K58; var20 = var14; var19 = var14[0x8EB2112D]
     268 [-]: CALL R19 3 1 ; var19(var20, var21)
     269 [-]: GETUPVAL R19 3; var19 = upvalues[3]
     270 [-]: MOVE R20 R2  ; var20 = var2
     271 [-]: MOVE R21 R15 ; var21 = var15
     272 [-]: GETIMPORT R22 63; var22 = 0x5AA2084E
     273 [-]: CALL R19 4 1 ; var19(var20, var21, var22)
     274 [-]: GETIMPORT R19 1; var19 = 0x3D106989
     275 [-]: LOADK R20 K71; var20 = "Encounter: Camp Beacon: AREA_INACTIVE"
     276 [-]: CALL R19 2 1 ; var19(var20)
L31: 277 [-]: MOVE R18 R17 ; var18 = var17
     278 [-]: GETIMPORT R19 9; var19 = 0xCBD666E1
     279 [-]: LOADN R20 0  ; var20 = 0
     280 [-]: CALL R19 2 1 ; var19(var20)
     281 [-]: JUMPBACK L18 ; goto L18
L32: 282 [-]: GETIMPORT R19 4; var19 = 0x89326C93
     283 [-]: GETUPVAL R21 4; var21 = upvalues[4]
     284 [-]: MOVE R22 R11 ; var22 = var11
     285 [-]: MULK R23 R12 K56; var23 = var12 * 2
     286 [-]: NAMECALL R19 R19 K72; var20 = var19; var19 = var19[0x4E5939A5]
     287 [-]: CALL R19 5 2 ; var19 = var19(var20, var21, var22, var23)
     288 [-]: FASTCALL1 62 R19 L33; 
     289 [-]: MOVE R21 R19 ; var21 = var19
     290 [-]: GETIMPORT R20 22; var20 = 0x7B998233
     291 [-]: CALL R20 2 2 ; var20 = var20(var21)
L33: 292 [-]: JUMPIF R20 L34; goto L34 if var20
     293 [-]: NAMECALL R20 R19 K73; var21 = var19; var20 = var19[0xA2880940]
     294 [-]: CALL R20 2 1 ; var20(var21)
L34: 295 [-]: LOADK R22 K57; var22 = "TriggerPort"
     296 [-]: NAMECALL R20 R5 K58; var21 = var5; var20 = var5[0x8EB2112D]
     297 [-]: CALL R20 3 1 ; var20(var21, var22)
     298 [-]: LOADK R22 K57; var22 = "TriggerPort"
     299 [-]: NAMECALL R20 R14 K58; var21 = var14; var20 = var14[0x8EB2112D]
     300 [-]: CALL R20 3 1 ; var20(var21, var22)
     301 [-]: GETUPVAL R20 3; var20 = upvalues[3]
     302 [-]: MOVE R21 R2  ; var21 = var2
     303 [-]: MOVE R22 R15 ; var22 = var15
     304 [-]: GETIMPORT R23 63; var23 = 0x5AA2084E
     305 [-]: CALL R20 4 1 ; var20(var21, var22, var23)
     306 [-]: GETIMPORT R20 1; var20 = 0x3D106989
     307 [-]: LOADK R21 K74; var21 = "Encounter: Camp Beacon: Shutdown"
     308 [-]: CALL R20 2 1 ; var20(var21)
     309 [-]: RETURN R0 0  ; 


; Name:            
; Defined at line: 581
; #Upvalues:       1
; #Parameters:     0
; Is_vararg:       0
; Max Stack Size:  4

       0 [-]: GETIMPORT R1 2; var1 = _T["CapturedCamp"]
       1 [-]: FASTCALL1 62 R1 L0; 
       2 [-]: GETIMPORT R0 4; var0 = 0x7B998233
       3 [-]: CALL R0 2 2  ; var0 = var0(var1)
L 0:   4 [-]: JUMPIFNOT R0 L1; goto L1 if not var0
       5 [-]: GETUPVAL R1 0; var1 = upvalues[0]
       6 [-]: GETTABLEKS R0 R1 K5; var0 = var1[0x9742B85B]
       7 [-]: GETIMPORT R1 7; var1 = 0xE91D7466
       8 [-]: GETIMPORT R2 9; var2 = 0x0469F296
       9 [-]: LOADK R3 K10 ; var3 = "BaseCaptureDatamass"
      10 [-]: CALL R2 2 0  ; var2, ... = var2(var3)
      11 [-]: CALL R0 0 1  ; var0(var1, ...)
      12 [-]: RETURN R0 0  ; 
L 1:  13 [-]: GETUPVAL R1 0; var1 = upvalues[0]
      14 [-]: GETTABLEKS R0 R1 K5; var0 = var1[0x9742B85B]
      15 [-]: GETIMPORT R1 7; var1 = 0xE91D7466
      16 [-]: GETIMPORT R2 9; var2 = 0x0469F296
      17 [-]: LOADK R3 K11 ; var3 = "BaseCaptureDatamass_Alt"
      18 [-]: CALL R2 2 0  ; var2, ... = var2(var3)
      19 [-]: CALL R0 0 1  ; var0(var1, ...)
      20 [-]: RETURN R0 0  ; 



