; Name:            
; Defined at line: 1
; #Upvalues:       0
; #Parameters:     0
; Is_vararg:       1
; Max Stack Size:  87

       1 [-]: GETIMPORT R0 1 [0x2D0FAD09]
       2 [-]: LOADK R1 K2 ["Lotus.Scripts.Libs.TransmissionSet"]
       3 [-]: CALL R0 1 1  
       4 [-]: GETIMPORT R1 1 [0x2D0FAD09]
       5 [-]: LOADK R2 K3 ["Lotus.Scripts.Libs.CommonGamemodeFunctions"]
       6 [-]: CALL R1 1 1  
       7 [-]: GETIMPORT R2 1 [0x2D0FAD09]
       8 [-]: LOADK R3 K4 ["Lotus.Scripts.Libs.LandscapeLib"]
       9 [-]: CALL R2 1 1  
      10 [-]: GETIMPORT R3 1 [0x2D0FAD09]
      11 [-]: LOADK R4 K5 ["Lotus.Scripts.Libs.ObjectiveText"]
      12 [-]: CALL R3 1 1  
      13 [-]: GETIMPORT R4 1 [0x2D0FAD09]
      14 [-]: LOADK R5 K6 ["Lotus.Interface.Libs.TimerMgr"]
      15 [-]: CALL R4 1 1  
      16 [-]: GETIMPORT R5 1 [0x2D0FAD09]
      17 [-]: LOADK R6 K7 ["Lotus.Scripts.Libs.QuestMissionLib"]
      18 [-]: CALL R5 1 1  
      19 [-]: GETIMPORT R6 1 [0x2D0FAD09]
      20 [-]: LOADK R7 K8 ["Lotus.Powersuits.Operator.OperatorLib"]
      21 [-]: CALL R6 1 1  
      22 [-]: GETIMPORT R7 1 [0x2D0FAD09]
      23 [-]: LOADK R8 K9 ["EE.Interface.Utilities"]
      24 [-]: CALL R7 1 1  
      25 [-]: GETIMPORT R8 1 [0x2D0FAD09]
      26 [-]: LOADK R9 K10 ["Lotus.Scripts.Libs.DuviriStoryQuestLib"]
      27 [-]: CALL R8 1 1  
      28 [-]: GETIMPORT R9 1 [0x2D0FAD09]
      29 [-]: LOADK R10 K11 ["Lotus.Scripts.Libs.StoryLib"]
      30 [-]: CALL R9 1 1  
      31 [-]: GETIMPORT R10 1 [0x2D0FAD09]
      32 [-]: LOADK R11 K12 ["Lotus.Scripts.Quests.DuviriQuest.ParadoxQuestUtil"]
      33 [-]: CALL R10 1 1 
      34 [-]: GETIMPORT R11 1 [0x2D0FAD09]
      35 [-]: LOADK R12 K13 ["Lotus.Scripts.Libs.DuviriActivityLib"]
      36 [-]: CALL R11 1 1 
      37 [-]: LOADNIL R12  
      38 [-]: LOADNIL R13  
      39 [-]: LOADNIL R14  
      40 [-]: LOADNIL R15  
      41 [-]: LOADNIL R16  
      42 [-]: LOADNIL R17  
      43 [-]: LOADNIL R18  
      44 [-]: LOADNIL R19  
      45 [-]: LOADN R20 0  
      46 [-]: LOADNIL R21  
      47 [-]: LOADNIL R22  
      48 [-]: LOADNIL R23  
      49 [-]: LOADNIL R24  
      50 [-]: LOADNIL R25  
      51 [-]: LOADNIL R26  
      52 [-]: LOADNIL R27  
      53 [-]: LOADNIL R28  
      54 [-]: LOADNIL R29  
      55 [-]: LOADNIL R30  
      56 [-]: LOADNIL R31  
      57 [-]: LOADNIL R32  
      58 [-]: LOADNIL R33  
      59 [-]: LOADNIL R34  
      60 [-]: LOADNIL R35  
      61 [-]: LOADNIL R36  
      62 [-]: LOADB R37 0  
      63 [-]: DUPTABLE R38 25
      64 [-]: LOADK R39 K26 ["/Lotus/Language/Duviri/DuviriQuest/StageFourApproachTeshinObj"]
      65 [-]: SETTABLEKS R39 R38 K14 ["TESHIN_APPROACH_OBJ"]
      66 [-]: LOADK R39 K27 ["/Lotus/Language/Duviri/DuviriQuest/StageFourFreeRoamObj"]
      67 [-]: SETTABLEKS R39 R38 K15 ["FREE_ROAM_OBJ"]
      68 [-]: LOADK R39 K28 ["/Lotus/Language/Duviri/DuviriQuest/StageFourFreeRoamWeaponsObj"]
      69 [-]: SETTABLEKS R39 R38 K16 ["FREE_ROAM_WEAPONS_OBJ"]
      70 [-]: LOADK R39 K29 ["/Lotus/Language/Duviri/DuviriQuest/StageFourTalkTeshinObj"]
      71 [-]: SETTABLEKS R39 R38 K17 ["TALK_TESHIN_OBJ"]
      72 [-]: LOADK R39 K30 ["/Lotus/Language/Duviri/DuviriQuest/StageFourGoToMainlandObj"]
      73 [-]: SETTABLEKS R39 R38 K18 ["GO_TO_MAINLAND_OBJ"]
      74 [-]: LOADK R39 K31 ["/Lotus/Language/Duviri/DuviriQuest/StageFourCollectFigurineObj"]
      75 [-]: SETTABLEKS R39 R38 K19 ["COLLECT_FIGURINE_OBJ"]
      76 [-]: LOADK R39 K32 ["/Lotus/Language/Duviri/DuviriQuest/StageFourReturnToCaveObj"]
      77 [-]: SETTABLEKS R39 R38 K20 ["RETURN_TO_CAVE_OBJ"]
      78 [-]: LOADK R39 K33 ["/Lotus/Language/Duviri/DuviriQuest/StageFourAssembleFigurineObj"]
      79 [-]: SETTABLEKS R39 R38 K21 ["ASSEMBLE_FIGURINE_OBJ"]
      80 [-]: LOADK R39 K34 ["/Lotus/Language/Duviri/DuviriQuest/StageFourRestByFireObj"]
      81 [-]: SETTABLEKS R39 R38 K22 ["REST_BY_FIRE_OBJ"]
      82 [-]: LOADK R39 K35 ["/Lotus/Language/Duviri/DuviriQuest/StageFourWhatsNext"]
      83 [-]: SETTABLEKS R39 R38 K23 ["FINALDIALOG_NEXT"]
      84 [-]: LOADK R39 K36 ["/Lotus/Language/Duviri/DuviriQuest/StageFourExplain"]
      85 [-]: SETTABLEKS R39 R38 K24 ["FINALDIALOG_EXPLAIN"]
      86 [-]: DUPTABLE R39 51
      87 [-]: LOADN R40 1  
      88 [-]: SETTABLEKS R40 R39 K37 ["TESHIN_APPROACH"]
      89 [-]: LOADN R40 2  
      90 [-]: SETTABLEKS R40 R39 K38 ["FREE_ROAM"]
      91 [-]: LOADN R40 3  
      92 [-]: SETTABLEKS R40 R39 K39 ["GO_TO_MAINLAND"]
      93 [-]: LOADN R40 4  
      94 [-]: SETTABLEKS R40 R39 K40 ["REACH_ANGRY_STORY"]
      95 [-]: LOADN R40 5  
      96 [-]: SETTABLEKS R40 R39 K41 ["ANGRY_STORY"]
      97 [-]: LOADN R40 6  
      98 [-]: SETTABLEKS R40 R39 K42 ["COLLECT_FIGURINE_PART"]
      99 [-]: LOADN R40 7  
     100 [-]: SETTABLEKS R40 R39 K43 ["RETURN_TO_CAVE"]
     101 [-]: LOADN R40 8  
     102 [-]: SETTABLEKS R40 R39 K44 ["REASSEMBLE_FIGURE"]
     103 [-]: LOADN R40 9  
     104 [-]: SETTABLEKS R40 R39 K45 ["DIORAMA"]
     105 [-]: LOADN R40 10 
     106 [-]: SETTABLEKS R40 R39 K46 ["CUTSCENE"]
     107 [-]: LOADN R40 11 
     108 [-]: SETTABLEKS R40 R39 K47 ["CONVERSATION"]
     109 [-]: LOADN R40 12 
     110 [-]: SETTABLEKS R40 R39 K48 ["REST_BY_FIRE"]
     111 [-]: LOADN R40 13 
     112 [-]: SETTABLEKS R40 R39 K49 ["COMPLETE"]
     113 [-]: LOADN R40 99 
     114 [-]: SETTABLEKS R40 R39 K50 ["RESPAWN"]
     115 [-]: NEWTABLE R40 16 0
     116 [-]: GETTABLEKS R41 R39 K37 ["TESHIN_APPROACH"]
     117 [-]: DUPTABLE R42 55
     118 [-]: LOADK R43 K56 ["Teshin Approach"]
     119 [-]: SETTABLEKS R43 R42 K52 ["name"]
     120 [-]: GETIMPORT R43 58 [0x0469F296]
     121 [-]: LOADK R44 K59 ["DormizoneSpawnPoint"]
     122 [-]: CALL R43 1 1 
     123 [-]: SETTABLEKS R43 R42 K53 ["respawnPt"]
     124 [-]: LOADB R43 1  
     125 [-]: SETTABLEKS R43 R42 K54 ["hasCheckpoint"]
     126 [-]: SETTABLE R42 R40 R41
     127 [-]: GETTABLEKS R41 R39 K38 ["FREE_ROAM"]
     128 [-]: DUPTABLE R42 60
     129 [-]: LOADK R43 K61 ["Free Roam"]
     130 [-]: SETTABLEKS R43 R42 K52 ["name"]
     131 [-]: SETTABLE R42 R40 R41
     132 [-]: GETTABLEKS R41 R39 K39 ["GO_TO_MAINLAND"]
     133 [-]: DUPTABLE R42 60
     134 [-]: LOADK R43 K62 ["Go To Mainland"]
     135 [-]: SETTABLEKS R43 R42 K52 ["name"]
     136 [-]: SETTABLE R42 R40 R41
     137 [-]: GETTABLEKS R41 R39 K40 ["REACH_ANGRY_STORY"]
     138 [-]: DUPTABLE R42 60
     139 [-]: LOADK R43 K63 ["Reach Angry Story"]
     140 [-]: SETTABLEKS R43 R42 K52 ["name"]
     141 [-]: SETTABLE R42 R40 R41
     142 [-]: GETTABLEKS R41 R39 K41 ["ANGRY_STORY"]
     143 [-]: DUPTABLE R42 55
     144 [-]: LOADK R43 K64 ["Angry Story"]
     145 [-]: SETTABLEKS R43 R42 K52 ["name"]
     146 [-]: GETIMPORT R43 58 [0x0469F296]
     147 [-]: LOADK R44 K65 ["StoryCheckpointWp"]
     148 [-]: CALL R43 1 1 
     149 [-]: SETTABLEKS R43 R42 K53 ["respawnPt"]
     150 [-]: LOADB R43 1  
     151 [-]: SETTABLEKS R43 R42 K54 ["hasCheckpoint"]
     152 [-]: SETTABLE R42 R40 R41
     153 [-]: GETTABLEKS R41 R39 K42 ["COLLECT_FIGURINE_PART"]
     154 [-]: DUPTABLE R42 55
     155 [-]: LOADK R43 K66 ["Collect Figurine Part"]
     156 [-]: SETTABLEKS R43 R42 K52 ["name"]
     157 [-]: GETIMPORT R43 58 [0x0469F296]
     158 [-]: LOADK R44 K65 ["StoryCheckpointWp"]
     159 [-]: CALL R43 1 1 
     160 [-]: SETTABLEKS R43 R42 K53 ["respawnPt"]
     161 [-]: LOADB R43 1  
     162 [-]: SETTABLEKS R43 R42 K54 ["hasCheckpoint"]
     163 [-]: SETTABLE R42 R40 R41
     164 [-]: GETTABLEKS R41 R39 K43 ["RETURN_TO_CAVE"]
     165 [-]: DUPTABLE R42 55
     166 [-]: LOADK R43 K67 ["Return To Cave"]
     167 [-]: SETTABLEKS R43 R42 K52 ["name"]
     168 [-]: GETIMPORT R43 58 [0x0469F296]
     169 [-]: LOADK R44 K65 ["StoryCheckpointWp"]
     170 [-]: CALL R43 1 1 
     171 [-]: SETTABLEKS R43 R42 K53 ["respawnPt"]
     172 [-]: LOADB R43 1  
     173 [-]: SETTABLEKS R43 R42 K54 ["hasCheckpoint"]
     174 [-]: SETTABLE R42 R40 R41
     175 [-]: GETTABLEKS R41 R39 K44 ["REASSEMBLE_FIGURE"]
     176 [-]: DUPTABLE R42 55
     177 [-]: LOADK R43 K68 ["ReAssemble Figure"]
     178 [-]: SETTABLEKS R43 R42 K52 ["name"]
     179 [-]: GETIMPORT R43 58 [0x0469F296]
     180 [-]: LOADK R44 K69 ["WfCavePlayerSpawn"]
     181 [-]: CALL R43 1 1 
     182 [-]: SETTABLEKS R43 R42 K53 ["respawnPt"]
     183 [-]: LOADB R43 1  
     184 [-]: SETTABLEKS R43 R42 K54 ["hasCheckpoint"]
     185 [-]: SETTABLE R42 R40 R41
     186 [-]: GETTABLEKS R41 R39 K45 ["DIORAMA"]
     187 [-]: DUPTABLE R42 60
     188 [-]: LOADK R43 K70 ["Diorama"]
     189 [-]: SETTABLEKS R43 R42 K52 ["name"]
     190 [-]: SETTABLE R42 R40 R41
     191 [-]: GETTABLEKS R41 R39 K46 ["CUTSCENE"]
     192 [-]: DUPTABLE R42 60
     193 [-]: LOADK R43 K71 ["Cutscene"]
     194 [-]: SETTABLEKS R43 R42 K52 ["name"]
     195 [-]: SETTABLE R42 R40 R41
     196 [-]: GETTABLEKS R41 R39 K47 ["CONVERSATION"]
     197 [-]: DUPTABLE R42 60
     198 [-]: LOADK R43 K72 ["Conversation"]
     199 [-]: SETTABLEKS R43 R42 K52 ["name"]
     200 [-]: SETTABLE R42 R40 R41
     201 [-]: GETTABLEKS R41 R39 K48 ["REST_BY_FIRE"]
     202 [-]: DUPTABLE R42 60
     203 [-]: LOADK R43 K73 ["Rest By Fire"]
     204 [-]: SETTABLEKS R43 R42 K52 ["name"]
     205 [-]: SETTABLE R42 R40 R41
     206 [-]: GETTABLEKS R41 R39 K49 ["COMPLETE"]
     207 [-]: DUPTABLE R42 60
     208 [-]: LOADK R43 K74 ["Complete"]
     209 [-]: SETTABLEKS R43 R42 K52 ["name"]
     210 [-]: SETTABLE R42 R40 R41
     211 [-]: GETTABLEKS R41 R39 K50 ["RESPAWN"]
     212 [-]: DUPTABLE R42 60
     213 [-]: LOADK R43 K75 ["Respawn"]
     214 [-]: SETTABLEKS R43 R42 K52 ["name"]
     215 [-]: SETTABLE R42 R40 R41
     216 [-]: NEWCLOSURE R41 P0
     217 [-]: MOVE R1 R17  
     218 [-]: MOVE R0 R10  
     219 [-]: MOVE R1 R18  
     220 [-]: NEWCLOSURE R42 P1
     221 [-]: MOVE R1 R17  
     222 [-]: MOVE R0 R10  
     223 [-]: MOVE R1 R18  
     224 [-]: NEWCLOSURE R43 P2
     225 [-]: MOVE R0 R10  
     226 [-]: MOVE R1 R17  
     227 [-]: DUPCLOSURE R44 K76 []
     228 [-]: SETGLOBAL R44 K77 ["ForceRespawn"]
     229 [-]: DUPCLOSURE R44 K78 []
     230 [-]: SETGLOBAL R44 K79 ["TempInteractionComplete"]
     231 [-]: NEWCLOSURE R44 P5
     232 [-]: MOVE R1 R27  
     233 [-]: MOVE R0 R7   
     234 [-]: MOVE R0 R1   
     235 [-]: MOVE R0 R0   
     236 [-]: MOVE R1 R15  
     237 [-]: NEWCLOSURE R45 P6
     238 [-]: MOVE R1 R22  
     239 [-]: MOVE R0 R8   
     240 [-]: MOVE R1 R35  
     241 [-]: MOVE R1 R27  
     242 [-]: LOADB R46 0  
     243 [-]: NEWCLOSURE R47 P7
     244 [-]: MOVE R1 R25  
     245 [-]: MOVE R1 R22  
     246 [-]: MOVE R1 R46  
     247 [-]: NEWCLOSURE R48 P8
     248 [-]: MOVE R0 R3   
     249 [-]: MOVE R0 R38  
     250 [-]: MOVE R1 R25  
     251 [-]: MOVE R1 R17  
     252 [-]: MOVE R0 R10  
     253 [-]: MOVE R1 R18  
     254 [-]: MOVE R1 R46  
     255 [-]: MOVE R0 R0   
     256 [-]: MOVE R1 R15  
     257 [-]: MOVE R1 R19  
     258 [-]: MOVE R0 R39  
     259 [-]: SETGLOBAL R48 K80 ["TeshinApproach_StateEvents"]
     260 [-]: LOADB R48 0  
     261 [-]: LOADB R49 0  
     262 [-]: LOADB R50 0  
     263 [-]: GETIMPORT R51 82 [0xA421AF95]
     264 [-]: LOADN R52 0  
     265 [-]: LOADK R53 K83 [0.5]
     266 [-]: LOADN R54 0  
     267 [-]: CALL R51 3 1 
     268 [-]: DUPTABLE R52 87
     269 [-]: LOADN R53 1  
     270 [-]: SETTABLEKS R53 R52 K84 ["FIGURINE"]
     271 [-]: LOADN R53 2  
     272 [-]: SETTABLEKS R53 R52 K85 ["SECONDARYWEAPON"]
     273 [-]: LOADN R53 3  
     274 [-]: SETTABLEKS R53 R52 K86 ["MASK"]
     275 [-]: DUPTABLE R53 91
     276 [-]: LOADN R54 0  
     277 [-]: SETTABLEKS R54 R53 K88 ["PRIMARY"]
     278 [-]: LOADN R54 0  
     279 [-]: SETTABLEKS R54 R53 K89 ["SECONDARY"]
     280 [-]: LOADN R54 0  
     281 [-]: SETTABLEKS R54 R53 K90 ["MELEE"]
     282 [-]: NEWCLOSURE R54 P9
     283 [-]: MOVE R1 R17  
     284 [-]: MOVE R0 R10  
     285 [-]: MOVE R1 R18  
     286 [-]: DUPCLOSURE R55 K92 []
     287 [-]: MOVE R0 R54  
     288 [-]: DUPCLOSURE R56 K93 []
     289 [-]: MOVE R0 R54  
     290 [-]: MOVE R0 R51  
     291 [-]: DUPCLOSURE R57 K94 []
     292 [-]: MOVE R0 R54  
     293 [-]: DUPCLOSURE R58 K95 []
     294 [-]: NEWCLOSURE R59 P14
     295 [-]: MOVE R1 R21  
     296 [-]: DUPCLOSURE R60 K96 []
     297 [-]: MOVE R0 R10  
     298 [-]: MOVE R0 R59  
     299 [-]: MOVE R0 R0   
     300 [-]: NEWCLOSURE R61 P16
     301 [-]: MOVE R0 R0   
     302 [-]: MOVE R1 R15  
     303 [-]: MOVE R0 R60  
     304 [-]: LOADN R62 0  
     305 [-]: LOADN R63 -1 
     306 [-]: DUPCLOSURE R64 K97 []
     307 [-]: DUPCLOSURE R65 K98 []
     308 [-]: DUPCLOSURE R66 K99 []
     309 [-]: MOVE R0 R64  
     310 [-]: MOVE R0 R65  
     311 [-]: DUPCLOSURE R67 K100 []
     312 [-]: MOVE R0 R65  
     313 [-]: NEWCLOSURE R68 P21
     314 [-]: MOVE R0 R67  
     315 [-]: MOVE R1 R28  
     316 [-]: MOVE R0 R53  
     317 [-]: MOVE R1 R29  
     318 [-]: MOVE R1 R30  
     319 [-]: NEWCLOSURE R69 P22
     320 [-]: MOVE R0 R67  
     321 [-]: MOVE R1 R28  
     322 [-]: MOVE R0 R53  
     323 [-]: MOVE R1 R29  
     324 [-]: MOVE R1 R30  
     325 [-]: MOVE R0 R0   
     326 [-]: MOVE R1 R15  
     327 [-]: MOVE R1 R63  
     328 [-]: MOVE R0 R3   
     329 [-]: MOVE R0 R38  
     330 [-]: MOVE R0 R54  
     331 [-]: MOVE R0 R51  
     332 [-]: MOVE R0 R58  
     333 [-]: NEWCLOSURE R70 P23
     334 [-]: MOVE R0 R0   
     335 [-]: MOVE R1 R15  
     336 [-]: MOVE R0 R60  
     337 [-]: NEWCLOSURE R71 P24
     338 [-]: MOVE R1 R35  
     339 [-]: LOADB R72 0  
     340 [-]: NEWCLOSURE R73 P25
     341 [-]: MOVE R1 R62  
     342 [-]: MOVE R0 R52  
     343 [-]: MOVE R0 R53  
     344 [-]: MOVE R1 R63  
     345 [-]: MOVE R1 R72  
     346 [-]: SETGLOBAL R73 K101 ["OnActivated"]
     347 [-]: NEWCLOSURE R73 P26
     348 [-]: MOVE R0 R10  
     349 [-]: MOVE R1 R28  
     350 [-]: MOVE R0 R64  
     351 [-]: MOVE R0 R65  
     352 [-]: MOVE R1 R29  
     353 [-]: MOVE R1 R30  
     354 [-]: MOVE R1 R48  
     355 [-]: MOVE R0 R54  
     356 [-]: MOVE R1 R49  
     357 [-]: MOVE R0 R56  
     358 [-]: MOVE R1 R50  
     359 [-]: MOVE R0 R3   
     360 [-]: MOVE R0 R38  
     361 [-]: MOVE R1 R62  
     362 [-]: MOVE R0 R58  
     363 [-]: MOVE R0 R52  
     364 [-]: MOVE R0 R61  
     365 [-]: MOVE R0 R69  
     366 [-]: MOVE R0 R0   
     367 [-]: MOVE R1 R15  
     368 [-]: MOVE R0 R60  
     369 [-]: MOVE R1 R19  
     370 [-]: MOVE R0 R39  
     371 [-]: SETGLOBAL R73 K102 ["FreeRoam_StateEvents"]
     372 [-]: NEWCLOSURE R73 P27
     373 [-]: MOVE R0 R10  
     374 [-]: MOVE R1 R13  
     375 [-]: MOVE R0 R0   
     376 [-]: MOVE R1 R15  
     377 [-]: MOVE R0 R3   
     378 [-]: MOVE R0 R38  
     379 [-]: MOVE R1 R17  
     380 [-]: MOVE R1 R18  
     381 [-]: MOVE R1 R33  
     382 [-]: MOVE R0 R8   
     383 [-]: MOVE R0 R5   
     384 [-]: MOVE R0 R7   
     385 [-]: MOVE R1 R19  
     386 [-]: MOVE R0 R39  
     387 [-]: SETGLOBAL R73 K103 ["GoToMainLand_StateEvents"]
     388 [-]: NEWCLOSURE R73 P28
     389 [-]: MOVE R1 R19  
     390 [-]: MOVE R0 R39  
     391 [-]: MOVE R0 R0   
     392 [-]: MOVE R1 R15  
     393 [-]: SETGLOBAL R73 K104 ["ReachAngryStory_StateEvents"]
     394 [-]: LOADN R73 -1 
     395 [-]: LOADN R74 -1 
     396 [-]: NEWCLOSURE R75 P29
     397 [-]: MOVE R1 R74  
     398 [-]: NEWCLOSURE R76 P30
     399 [-]: MOVE R1 R74  
     400 [-]: MOVE R1 R73  
     401 [-]: MOVE R0 R75  
     402 [-]: NEWCLOSURE R77 P31
     403 [-]: MOVE R1 R35  
     404 [-]: MOVE R1 R74  
     405 [-]: MOVE R1 R73  
     406 [-]: MOVE R0 R75  
     407 [-]: MOVE R0 R11  
     408 [-]: MOVE R1 R19  
     409 [-]: MOVE R0 R39  
     410 [-]: SETGLOBAL R77 K105 ["AngryStory_StateEvents"]
     411 [-]: DUPCLOSURE R77 K106 []
     412 [-]: SETGLOBAL R77 K107 ["OnCollectPart"]
     413 [-]: NEWCLOSURE R77 P33
     414 [-]: MOVE R1 R34  
     415 [-]: MOVE R0 R0   
     416 [-]: MOVE R1 R15  
     417 [-]: MOVE R0 R3   
     418 [-]: MOVE R0 R38  
     419 [-]: MOVE R1 R17  
     420 [-]: MOVE R0 R10  
     421 [-]: MOVE R1 R18  
     422 [-]: MOVE R1 R19  
     423 [-]: MOVE R0 R39  
     424 [-]: SETGLOBAL R77 K108 ["CollectFigurinePart_StateEvents"]
     425 [-]: LOADB R77 0  
     426 [-]: NEWCLOSURE R78 P34
     427 [-]: MOVE R0 R3   
     428 [-]: MOVE R0 R38  
     429 [-]: MOVE R1 R77  
     430 [-]: MOVE R0 R10  
     431 [-]: MOVE R1 R17  
     432 [-]: MOVE R1 R18  
     433 [-]: MOVE R1 R33  
     434 [-]: MOVE R0 R5   
     435 [-]: MOVE R1 R25  
     436 [-]: MOVE R0 R8   
     437 [-]: MOVE R1 R19  
     438 [-]: MOVE R0 R39  
     439 [-]: SETGLOBAL R78 K109 ["ReturnToCave_StateEvents"]
     440 [-]: NEWCLOSURE R78 P35
     441 [-]: MOVE R1 R32  
     442 [-]: MOVE R0 R10  
     443 [-]: MOVE R0 R38  
     444 [-]: MOVE R1 R18  
     445 [-]: MOVE R1 R19  
     446 [-]: MOVE R0 R39  
     447 [-]: SETGLOBAL R78 K110 ["ReassembleFigure_StateEvents"]
     448 [-]: NEWCLOSURE R78 P36
     449 [-]: MOVE R0 R9   
     450 [-]: MOVE R1 R32  
     451 [-]: MOVE R1 R19  
     452 [-]: MOVE R0 R39  
     453 [-]: SETGLOBAL R78 K111 ["Diorama_StateEvents"]
     454 [-]: NEWCLOSURE R78 P37
     455 [-]: MOVE R1 R31  
     456 [-]: MOVE R0 R10  
     457 [-]: MOVE R1 R22  
     458 [-]: NEWCLOSURE R79 P38
     459 [-]: MOVE R0 R78  
     460 [-]: MOVE R1 R19  
     461 [-]: MOVE R0 R39  
     462 [-]: SETGLOBAL R79 K112 ["Cutscene_StateEvents"]
     463 [-]: DUPCLOSURE R79 K113 []
     464 [-]: MOVE R0 R10  
     465 [-]: MOVE R0 R1   
     466 [-]: NEWCLOSURE R80 P40
     467 [-]: MOVE R1 R26  
     468 [-]: MOVE R0 R10  
     469 [-]: MOVE R0 R6   
     470 [-]: MOVE R1 R22  
     471 [-]: MOVE R1 R17  
     472 [-]: MOVE R1 R31  
     473 [-]: MOVE R1 R15  
     474 [-]: MOVE R0 R38  
     475 [-]: MOVE R1 R18  
     476 [-]: MOVE R1 R19  
     477 [-]: MOVE R0 R39  
     478 [-]: SETGLOBAL R80 K114 ["Conversation_StateEvents"]
     479 [-]: GETIMPORT R80 116 [0xB009BBC6]
     480 [-]: LOADK R81 K117 ["/Lotus/Animations/Tenno/Emotes/Generic/StandToKneel_anim.fbx"]
     481 [-]: CALL R80 1 1 
     482 [-]: GETIMPORT R81 116 [0xB009BBC6]
     483 [-]: LOADK R82 K118 ["/Lotus/Animations/Tenno/Emotes/Generic/KneelIdle_anim.fbx"]
     484 [-]: CALL R81 1 1 
     485 [-]: NEWCLOSURE R82 P41
     486 [-]: MOVE R1 R72  
     487 [-]: MOVE R0 R3   
     488 [-]: MOVE R0 R38  
     489 [-]: MOVE R1 R17  
     490 [-]: MOVE R0 R10  
     491 [-]: MOVE R1 R18  
     492 [-]: MOVE R1 R22  
     493 [-]: MOVE R0 R80  
     494 [-]: MOVE R0 R81  
     495 [-]: MOVE R0 R5   
     496 [-]: MOVE R1 R31  
     497 [-]: MOVE R1 R26  
     498 [-]: MOVE R1 R19  
     499 [-]: MOVE R0 R39  
     500 [-]: SETGLOBAL R82 K119 ["RestByFire_StateEvents"]
     501 [-]: NEWCLOSURE R82 P42
     502 [-]: MOVE R1 R37  
     503 [-]: MOVE R0 R10  
     504 [-]: SETGLOBAL R82 K120 ["RespawnWarframe"]
     505 [-]: NEWCLOSURE R82 P43
     506 [-]: MOVE R0 R39  
     507 [-]: MOVE R1 R24  
     508 [-]: MOVE R0 R10  
     509 [-]: MOVE R1 R33  
     510 [-]: MOVE R0 R40  
     511 [-]: MOVE R1 R14  
     512 [-]: MOVE R1 R35  
     513 [-]: MOVE R1 R23  
     514 [-]: MOVE R0 R5   
     515 [-]: MOVE R1 R22  
     516 [-]: MOVE R0 R1   
     517 [-]: NEWCLOSURE R83 P44
     518 [-]: MOVE R1 R24  
     519 [-]: MOVE R1 R19  
     520 [-]: MOVE R1 R23  
     521 [-]: MOVE R1 R20  
     522 [-]: MOVE R0 R39  
     523 [-]: MOVE R1 R16  
     524 [-]: MOVE R1 R46  
     525 [-]: MOVE R1 R25  
     526 [-]: MOVE R1 R22  
     527 [-]: MOVE R1 R36  
     528 [-]: MOVE R1 R13  
     529 [-]: MOVE R1 R35  
     530 [-]: MOVE R1 R21  
     531 [-]: MOVE R1 R37  
     532 [-]: MOVE R1 R14  
     533 [-]: NEWCLOSURE R84 P45
     534 [-]: MOVE R1 R24  
     535 [-]: MOVE R0 R39  
     536 [-]: NEWCLOSURE R85 P46
     537 [-]: MOVE R1 R14  
     538 [-]: MOVE R1 R12  
     539 [-]: MOVE R1 R18  
     540 [-]: MOVE R1 R15  
     541 [-]: MOVE R1 R13  
     542 [-]: MOVE R1 R16  
     543 [-]: MOVE R0 R4   
     544 [-]: MOVE R1 R19  
     545 [-]: MOVE R0 R2   
     546 [-]: MOVE R0 R82  
     547 [-]: MOVE R1 R21  
     548 [-]: MOVE R1 R22  
     549 [-]: MOVE R0 R5   
     550 [-]: MOVE R0 R10  
     551 [-]: MOVE R1 R31  
     552 [-]: MOVE R1 R25  
     553 [-]: MOVE R1 R26  
     554 [-]: MOVE R0 R44  
     555 [-]: MOVE R0 R45  
     556 [-]: MOVE R0 R1   
     557 [-]: MOVE R0 R39  
     558 [-]: MOVE R0 R84  
     559 [-]: NEWCLOSURE R86 P47
     560 [-]: MOVE R0 R85  
     561 [-]: MOVE R1 R14  
     562 [-]: MOVE R1 R20  
     563 [-]: MOVE R1 R19  
     564 [-]: MOVE R0 R83  
     565 [-]: SETGLOBAL R86 K121 ["StartEncounter"]
     566 [-]: DUPCLOSURE R86 K122 []
     567 [-]: MOVE R0 R0   
     568 [-]: SETGLOBAL R86 K123 ["DioramaTransmission"]
     569 [-]: CLOSEUPVALS R12
     570 [-]: RETURN R0 0  


; Name:            
; Defined at line: 156
; #Upvalues:       3
; #Parameters:     3
; Is_vararg:       0
; Max Stack Size:  11

       0 [-]: GETUPVAL R4 1
       1 [-]: GETTABLEKS R3 R4 K0 [0x7C676590]
       2 [-]: GETUPVAL R4 2
       3 [-]: MOVE R5 R0   
       4 [-]: MOVE R6 R1   
       5 [-]: MOVE R7 R2   
       6 [-]: GETIMPORT R8 2 [0xB7CBD06B]
       7 [-]: LOADN R9 2   
       8 [-]: LOADN R10 100
       9 [-]: CALL R8 2 -1 
      10 [-]: CALL R3 -1 1 
      11 [-]: SETUPVAL R3 0
      12 [-]: GETUPVAL R3 0
      13 [-]: RETURN R3 1  


; Name:            
; Defined at line: 161
; #Upvalues:       3
; #Parameters:     4
; Is_vararg:       0
; Max Stack Size:  10

       0 [-]: GETUPVAL R5 1
       1 [-]: GETTABLEKS R4 R5 K0 [0x3C599C25]
       2 [-]: GETUPVAL R5 2
       3 [-]: MOVE R6 R0   
       4 [-]: MOVE R7 R1   
       5 [-]: MOVE R8 R2   
       6 [-]: MOVE R9 R3   
       7 [-]: CALL R4 5 1  
       8 [-]: SETUPVAL R4 0
       9 [-]: GETUPVAL R4 0
      10 [-]: RETURN R4 1  


; Name:            
; Defined at line: 166
; #Upvalues:       2
; #Parameters:     0
; Is_vararg:       0
; Max Stack Size:  2

       0 [-]: GETUPVAL R1 0
       1 [-]: GETTABLEKS R0 R1 K0 [0x4949D0BA]
       2 [-]: GETUPVAL R1 1
       3 [-]: CALL R0 1 0  
       4 [-]: RETURN R0 0  


; Name:            
; Defined at line: 170
; #Upvalues:       0
; #Parameters:     0
; Is_vararg:       0
; Max Stack Size:  7

       0 [-]: GETIMPORT R0 1 [0x89326C93]
       1 [-]: NAMECALL R0 R0 K2 [0x78298275]
       2 [-]: CALL R0 1 1  
       3 [-]: FASTCALL1 62 R0 L0
       4 [-]: MOVE R2 R0   
       5 [-]: GETIMPORT R1 4 [0x7B998233]
       6 [-]: CALL R1 1 1  
L 0:   7 [-]: JUMPIF R1 L2 
       8 [-]: GETIMPORT R3 6 ["gLotusVehicleAvatarType"]
       9 [-]: NAMECALL R1 R0 K7 [0xF2DEAF69]
      10 [-]: CALL R1 2 1  
      11 [-]: JUMPIFNOT R1 L1
      12 [-]: NAMECALL R1 R0 K8 [0xFF005826]
      13 [-]: CALL R1 1 1  
      14 [-]: MOVE R0 R1   
L 1:  15 [-]: GETIMPORT R3 10 [0x0469F296]
      16 [-]: LOADK R4 K11 ["AdultOperator"]
      17 [-]: CALL R3 1 -1 
      18 [-]: NAMECALL R1 R0 K12 [0x26D544FC]
      19 [-]: CALL R1 -1 0 
      20 [-]: NAMECALL R2 R0 K14 [0xB40C191A]
      21 [-]: CALL R2 1 1  
      22 [-]: MULK R1 R2 K13 [2]
      23 [-]: GETIMPORT R2 17 [0x35C16153]
      24 [-]: CALL R2 0 1  
      25 [-]: GETIMPORT R5 19 [0x7258F36F]
      26 [-]: MOVE R6 R1   
      27 [-]: CALL R5 1 -1 
      28 [-]: NAMECALL R3 R2 K20 [0xF326045F]
      29 [-]: CALL R3 -1 0 
      30 [-]: LOADN R5 17  
      31 [-]: LOADN R6 1   
      32 [-]: NAMECALL R3 R2 K21 [0x1586E35E]
      33 [-]: CALL R3 3 0  
      34 [-]: MOVE R5 R2   
      35 [-]: NAMECALL R3 R0 K22 [0x479483BB]
      36 [-]: CALL R3 2 0  
L 2:  37 [-]: RETURN R0 0  


; Name:            
; Defined at line: 185
; #Upvalues:       0
; #Parameters:     0
; Is_vararg:       0
; Max Stack Size:  2

       0 [-]: GETIMPORT R0 1 ["_T"]
       1 [-]: LOADB R1 1   
       2 [-]: SETTABLEKS R1 R0 K2 ["DuviriAngryTempInteraction"]
       3 [-]: RETURN R0 0  


; Name:            
; Defined at line: 189
; #Upvalues:       5
; #Parameters:     0
; Is_vararg:       0
; Max Stack Size:  4

       0 [-]: LOADNIL R0   
       1 [-]: SETUPVAL R0 0
       2 [-]: GETIMPORT R1 1 [0xB227841D]
       3 [-]: FASTCALL1 62 R1 L0
       4 [-]: GETIMPORT R0 3 [0x7B998233]
       5 [-]: CALL R0 1 1  
L 0:   6 [-]: JUMPIF R0 L1 
       7 [-]: GETUPVAL R0 0
       8 [-]: JUMPXEQKNIL R0 L1 NOT
       9 [-]: GETUPVAL R1 1
      10 [-]: GETTABLEKS R0 R1 K4 [0x659D451F]
      11 [-]: GETIMPORT R1 1 [0xB227841D]
      12 [-]: CALL R0 1 1  
      13 [-]: SETUPVAL R0 0
L 1:  14 [-]: GETUPVAL R1 2
      15 [-]: GETTABLEKS R0 R1 K5 [0xC474A99E]
      16 [-]: GETIMPORT R1 7 [0x0469F296]
      17 [-]: LOADK R2 K8 ["DuviriMusicTownCombat"]
      18 [-]: CALL R1 1 1  
      19 [-]: LOADK R2 K9 ["Disable"]
      20 [-]: CALL R0 2 0  
      21 [-]: GETUPVAL R1 2
      22 [-]: GETTABLEKS R0 R1 K5 [0xC474A99E]
      23 [-]: GETIMPORT R1 7 [0x0469F296]
      24 [-]: LOADK R2 K10 ["DuviriTownSoundSeqDisable"]
      25 [-]: CALL R1 1 1  
      26 [-]: LOADK R2 K9 ["Disable"]
      27 [-]: CALL R0 2 0  
      28 [-]: GETIMPORT R0 12 ["_T"]
      29 [-]: LOADB R1 1   
      30 [-]: SETTABLEKS R1 R0 K13 ["PlayRespawnTransmission"]
      31 [-]: GETUPVAL R1 3
      32 [-]: GETTABLEKS R0 R1 K14 [0x9742B85B]
      33 [-]: GETUPVAL R1 4
      34 [-]: GETIMPORT R2 7 [0x0469F296]
      35 [-]: LOADK R3 K15 ["ThraxFistSlam"]
      36 [-]: CALL R2 1 -1 
      37 [-]: CALL R0 -1 0 
      38 [-]: GETUPVAL R1 3
      39 [-]: GETTABLEKS R0 R1 K16 [0xFC87A231]
      40 [-]: CALL R0 0 0  
      41 [-]: GETIMPORT R0 12 ["_T"]
      42 [-]: LOADB R1 0   
      43 [-]: SETTABLEKS R1 R0 K13 ["PlayRespawnTransmission"]
      44 [-]: RETURN R0 0  


; Name:            
; Defined at line: 209
; #Upvalues:       4
; #Parameters:     0
; Is_vararg:       0
; Max Stack Size:  5

       0 [-]: GETIMPORT R0 1 [0x89326C93]
       1 [-]: NAMECALL R0 R0 K2 [0x78298275]
       2 [-]: CALL R0 1 1  
       3 [-]: SETUPVAL R0 0
       4 [-]: GETUPVAL R1 1
       5 [-]: GETTABLEKS R0 R1 K3 [0x3DF1EF0C]
       6 [-]: LOADB R1 0   
       7 [-]: GETUPVAL R2 0
       8 [-]: GETUPVAL R3 0
       9 [-]: CALL R0 3 1  
      10 [-]: SETUPVAL R0 0
      11 [-]: GETUPVAL R1 2
      12 [-]: FASTCALL1 62 R1 L0
      13 [-]: GETIMPORT R0 5 [0x7B998233]
      14 [-]: CALL R0 1 1  
L 0:  15 [-]: JUMPIF R0 L1 
      16 [-]: GETUPVAL R0 0
      17 [-]: GETUPVAL R2 2
      18 [-]: NAMECALL R2 R2 K6 [0xD1586535]
      19 [-]: CALL R2 1 1  
      20 [-]: GETUPVAL R3 2
      21 [-]: NAMECALL R3 R3 K7 [0xCB3851B8]
      22 [-]: CALL R3 1 -1 
      23 [-]: NAMECALL R0 R0 K8 [0x589EF1C1]
      24 [-]: CALL R0 -1 0 
L 1:  25 [-]: GETUPVAL R1 3
      26 [-]: FASTCALL1 62 R1 L2
      27 [-]: GETIMPORT R0 5 [0x7B998233]
      28 [-]: CALL R0 1 1  
L 2:  29 [-]: JUMPIF R0 L3 
      30 [-]: GETUPVAL R0 3
      31 [-]: LOADB R2 0   
      32 [-]: NAMECALL R0 R0 K9 [0x6CF1E476]
      33 [-]: CALL R0 2 0  
L 3:  34 [-]: GETIMPORT R0 11 ["_T"]
      35 [-]: LOADN R1 999 
      36 [-]: SETTABLEKS R1 R0 K12 ["RespawnTime"]
      37 [-]: RETURN R0 0  


; Name:            
; Defined at line: 226
; #Upvalues:       3
; #Parameters:     0
; Is_vararg:       0
; Max Stack Size:  4

       0 [-]: GETUPVAL R1 0
       1 [-]: FASTCALL1 62 R1 L0
       2 [-]: GETIMPORT R0 1 [0x7B998233]
       3 [-]: CALL R0 1 1  
L 0:   4 [-]: JUMPIF R0 L2 
       5 [-]: GETUPVAL R1 1
       6 [-]: FASTCALL1 62 R1 L1
       7 [-]: GETIMPORT R0 1 [0x7B998233]
       8 [-]: CALL R0 1 1  
L 1:   9 [-]: JUMPIFNOT R0 L3
L 2:  10 [-]: RETURN R0 0  
L 3:  11 [-]: GETUPVAL R0 0
      12 [-]: NAMECALL R0 R0 K2 [0xD1586535]
      13 [-]: CALL R0 1 1  
      14 [-]: GETUPVAL R1 1
      15 [-]: MOVE R3 R0   
      16 [-]: NAMECALL R1 R1 K3 [0x1F420A3A]
      17 [-]: CALL R1 2 1  
      18 [-]: LOADN R2 5   
      19 [-]: JUMPIFNOTLT R1 R2 L4
      20 [-]: LOADB R1 1   
      21 [-]: SETUPVAL R1 2
L 4:  22 [-]: RETURN R0 0  


; Name:            
; Defined at line: 241
; #Upvalues:       11
; #Parameters:     0
; Is_vararg:       0
; Max Stack Size:  9

       0 [-]: GETUPVAL R1 0
       1 [-]: GETTABLEKS R0 R1 K0 [0xA1DF01D6]
       2 [-]: GETUPVAL R2 1
       3 [-]: GETTABLEKS R1 R2 K1 ["TESHIN_APPROACH_OBJ"]
       4 [-]: CALL R0 1 0  
       5 [-]: GETUPVAL R0 2
       6 [-]: GETUPVAL R2 4
       7 [-]: GETTABLEKS R1 R2 K2 [0x7C676590]
       8 [-]: GETUPVAL R2 5
       9 [-]: MOVE R3 R0   
      10 [-]: LOADNIL R4   
      11 [-]: LOADNIL R5   
      12 [-]: GETIMPORT R6 4 [0xB7CBD06B]
      13 [-]: LOADN R7 2   
      14 [-]: LOADN R8 100 
      15 [-]: CALL R6 2 -1 
      16 [-]: CALL R1 -1 1 
      17 [-]: SETUPVAL R1 3
      18 [-]: GETUPVAL R1 3
      19 [-]: LOADB R0 0   
      20 [-]: SETUPVAL R0 6
      21 [-]: GETUPVAL R1 7
      22 [-]: GETTABLEKS R0 R1 K5 [0x9742B85B]
      23 [-]: GETUPVAL R1 8
      24 [-]: GETIMPORT R2 7 [0x0469F296]
      25 [-]: LOADK R3 K8 ["DDuvParQDormCave0850"]
      26 [-]: CALL R2 1 1  
      27 [-]: LOADB R3 0   
      28 [-]: LOADB R4 0   
      29 [-]: CALL R0 4 0  
L 0:  30 [-]: GETUPVAL R0 6
      31 [-]: JUMPIF R0 L1 
      32 [-]: GETIMPORT R0 10 [0xCBD666E1]
      33 [-]: LOADN R1 0   
      34 [-]: CALL R0 1 0  
      35 [-]: JUMPBACK L0  
L 1:  36 [-]: GETUPVAL R1 7
      37 [-]: GETTABLEKS R0 R1 K11 [0xED8F83F8]
      38 [-]: CALL R0 0 1  
      39 [-]: JUMPIFNOT R0 L2
      40 [-]: GETUPVAL R1 7
      41 [-]: GETTABLEKS R0 R1 K5 [0x9742B85B]
      42 [-]: GETUPVAL R1 8
      43 [-]: GETIMPORT R2 7 [0x0469F296]
      44 [-]: LOADK R3 K12 [""]
      45 [-]: CALL R2 1 1  
      46 [-]: LOADB R3 1   
      47 [-]: LOADB R4 0   
      48 [-]: CALL R0 4 0  
L 2:  49 [-]: GETUPVAL R1 4
      50 [-]: GETTABLEKS R0 R1 K13 [0x4949D0BA]
      51 [-]: GETUPVAL R1 3
      52 [-]: CALL R0 1 0  
      53 [-]: GETUPVAL R1 0
      54 [-]: GETTABLEKS R0 R1 K14 [0xDC3B2033]
      55 [-]: CALL R0 0 0  
      56 [-]: GETIMPORT R0 10 [0xCBD666E1]
      57 [-]: LOADK R1 K15 [0.5]
      58 [-]: CALL R0 1 0  
      59 [-]: GETUPVAL R1 7
      60 [-]: GETTABLEKS R0 R1 K5 [0x9742B85B]
      61 [-]: GETUPVAL R1 8
      62 [-]: GETIMPORT R2 7 [0x0469F296]
      63 [-]: LOADK R3 K16 ["DDuvParQDormCave0860"]
      64 [-]: CALL R2 1 1  
      65 [-]: LOADB R3 0   
      66 [-]: LOADB R4 1   
      67 [-]: CALL R0 4 0  
      68 [-]: GETUPVAL R1 7
      69 [-]: GETTABLEKS R0 R1 K17 [0x11DCFE97]
      70 [-]: GETIMPORT R1 7 [0x0469F296]
      71 [-]: LOADK R2 K18 ["DDuvParQDormCave0870"]
      72 [-]: CALL R1 1 1  
      73 [-]: LOADB R2 0   
      74 [-]: LOADB R3 1   
      75 [-]: LOADN R4 4   
      76 [-]: CALL R0 4 0  
      77 [-]: GETUPVAL R1 7
      78 [-]: GETTABLEKS R0 R1 K5 [0x9742B85B]
      79 [-]: GETUPVAL R1 8
      80 [-]: GETIMPORT R2 7 [0x0469F296]
      81 [-]: LOADK R3 K19 ["DDuvParQDormCave0880"]
      82 [-]: CALL R2 1 1  
      83 [-]: LOADB R3 0   
      84 [-]: LOADB R4 1   
      85 [-]: CALL R0 4 0  
      86 [-]: GETUPVAL R0 9
      87 [-]: GETUPVAL R3 10
      88 [-]: GETTABLEKS R2 R3 K20 ["FREE_ROAM"]
      89 [-]: NAMECALL R0 R0 K21 [0x8ABFF40E]
      90 [-]: CALL R0 2 0  
      91 [-]: RETURN R0 0  


; Name:            
; Defined at line: 293
; #Upvalues:       3
; #Parameters:     3
; Is_vararg:       0
; Max Stack Size:  16

       0 [-]: NEWTABLE R3 2 0
       1 [-]: GETIMPORT R4 1 [0x89326C93]
       2 [-]: MOVE R6 R0   
       3 [-]: NAMECALL R4 R4 K2 [0x46A0EBF5]
       4 [-]: CALL R4 2 1  
       5 [-]: MOVE R5 R4   
       6 [-]: JUMPIFNOT R1 L1
       7 [-]: GETIMPORT R6 1 [0x89326C93]
       8 [-]: MOVE R8 R1   
       9 [-]: NAMECALL R6 R6 K2 [0x46A0EBF5]
      10 [-]: CALL R6 2 1  
      11 [-]: FASTCALL1 62 R6 L0
      12 [-]: MOVE R8 R6   
      13 [-]: GETIMPORT R7 4 [0x7B998233]
      14 [-]: CALL R7 1 1  
L 0:  15 [-]: JUMPIF R7 L1 
      16 [-]: MOVE R5 R6   
L 1:  17 [-]: NAMECALL R6 R4 K5 [0x383D2E7D]
      18 [-]: CALL R6 1 0  
      19 [-]: MOVE R7 R5   
      20 [-]: GETUPVAL R9 1
      21 [-]: GETTABLEKS R8 R9 K6 [0x7C676590]
      22 [-]: GETUPVAL R9 2
      23 [-]: MOVE R10 R7  
      24 [-]: LOADNIL R11  
      25 [-]: MOVE R12 R2  
      26 [-]: GETIMPORT R13 8 [0xB7CBD06B]
      27 [-]: LOADN R14 2  
      28 [-]: LOADN R15 100
      29 [-]: CALL R13 2 -1
      30 [-]: CALL R8 -1 1 
      31 [-]: SETUPVAL R8 0
      32 [-]: GETUPVAL R6 0
      33 [-]: SETTABLEKS R4 R3 K9 ["trigger"]
      34 [-]: SETTABLEKS R6 R3 K10 ["marker"]
      35 [-]: RETURN R3 1  


; Name:            
; Defined at line: 309
; #Upvalues:       1
; #Parameters:     0
; Is_vararg:       0
; Max Stack Size:  3

       0 [-]: GETUPVAL R0 0
       1 [-]: GETIMPORT R1 1 [0x7FB428F8]
       2 [-]: GETIMPORT R2 3 [0xA364E08E]
       3 [-]: CALL R0 2 1  
       4 [-]: RETURN R0 1  


; Name:            
; Defined at line: 313
; #Upvalues:       2
; #Parameters:     0
; Is_vararg:       0
; Max Stack Size:  7

       0 [-]: NEWTABLE R0 0 0
       1 [-]: GETUPVAL R3 0
       2 [-]: GETIMPORT R4 1 [0xB2C5BE14]
       3 [-]: LOADNIL R5   
       4 [-]: GETUPVAL R6 1
       5 [-]: CALL R3 3 1  
       6 [-]: FASTCALL2 52 R0 R3 L0
       7 [-]: MOVE R2 R0   
       8 [-]: GETIMPORT R1 4 [0x23D5322F]
       9 [-]: CALL R1 2 0  
L 0:  10 [-]: GETUPVAL R3 0
      11 [-]: GETIMPORT R4 6 [0xBC9AC9DC]
      12 [-]: LOADNIL R5   
      13 [-]: GETUPVAL R6 1
      14 [-]: CALL R3 3 1  
      15 [-]: FASTCALL2 52 R0 R3 L1
      16 [-]: MOVE R2 R0   
      17 [-]: GETIMPORT R1 4 [0x23D5322F]
      18 [-]: CALL R1 2 0  
L 1:  19 [-]: GETUPVAL R3 0
      20 [-]: GETIMPORT R4 8 [0x4E2F5D3A]
      21 [-]: LOADNIL R5   
      22 [-]: GETUPVAL R6 1
      23 [-]: CALL R3 3 1  
      24 [-]: FASTCALL2 52 R0 R3 L2
      25 [-]: MOVE R2 R0   
      26 [-]: GETIMPORT R1 4 [0x23D5322F]
      27 [-]: CALL R1 2 0  
L 2:  28 [-]: RETURN R0 1  


; Name:            
; Defined at line: 321
; #Upvalues:       1
; #Parameters:     0
; Is_vararg:       0
; Max Stack Size:  3

       0 [-]: GETUPVAL R0 0
       1 [-]: GETIMPORT R1 1 [0xF752C275]
       2 [-]: GETIMPORT R2 3 [0xFF699EA9]
       3 [-]: CALL R0 2 1  
       4 [-]: RETURN R0 1  


; Name:            
; Defined at line: 325
; #Upvalues:       0
; #Parameters:     1
; Is_vararg:       0
; Max Stack Size:  10

       0 [-]: GETIMPORT R1 1 [0xC8802016]
       1 [-]: MOVE R2 R0   
       2 [-]: CALL R1 1 3  
       3 [-]: FORGPREP_INEXT R1 L4
L 0:   4 [-]: GETTABLEKS R6 R5 K2 ["trigger"]
       5 [-]: FASTCALL1 62 R6 L1
       6 [-]: MOVE R8 R6   
       7 [-]: GETIMPORT R7 4 [0x7B998233]
       8 [-]: CALL R7 1 1  
L 1:   9 [-]: JUMPIF R7 L2 
      10 [-]: NAMECALL R7 R6 K5 [0xF4E253B6]
      11 [-]: CALL R7 1 0  
L 2:  12 [-]: GETTABLEKS R7 R5 K6 ["marker"]
      13 [-]: FASTCALL1 62 R7 L3
      14 [-]: MOVE R9 R7   
      15 [-]: GETIMPORT R8 4 [0x7B998233]
      16 [-]: CALL R8 1 1  
L 3:  17 [-]: JUMPIF R8 L4 
      18 [-]: NAMECALL R8 R7 K7 [0xA2880940]
      19 [-]: CALL R8 1 0  
L 4:  20 [-]: FORGLOOP R1 L0 2 [inext]
      21 [-]: RETURN R0 0  


; Name:            
; Defined at line: 338
; #Upvalues:       1
; #Parameters:     2
; Is_vararg:       0
; Max Stack Size:  9

       0 [-]: LOADN R2 0   
       1 [-]: GETUPVAL R3 0
       2 [-]: LOADN R5 8   
       3 [-]: NAMECALL R3 R3 K0 [0xE3A0BBCA]
       4 [-]: CALL R3 2 1  
       5 [-]: FASTCALL1 62 R3 L0
       6 [-]: MOVE R5 R3   
       7 [-]: GETIMPORT R4 2 [0x7B998233]
       8 [-]: CALL R4 1 1  
L 0:   9 [-]: JUMPIFNOT R4 L1
      10 [-]: GETIMPORT R4 4 [0x89326C93]
      11 [-]: NAMECALL R4 R4 K5 [0x78298275]
      12 [-]: CALL R4 1 1  
      13 [-]: MOVE R3 R4   
L 1:  14 [-]: LOADN R4 1   
      15 [-]: FASTCALL1 62 R1 L2
      16 [-]: MOVE R6 R1   
      17 [-]: GETIMPORT R5 2 [0x7B998233]
      18 [-]: CALL R5 1 1  
L 2:  19 [-]: JUMPIF R5 L4 
      20 [-]: JUMPXEQKB R1 1 L3 NOT
      21 [-]: LOADN R4 0   
      22 [-]: JUMP L4
     
L 3:  23 [-]: LOADB R7 1   
      24 [-]: LOADB R8 1   
      25 [-]: NAMECALL R5 R3 K6 [0x768274D6]
      26 [-]: CALL R5 3 0  
L 4:  27 [-]: JUMPIFNOTLT R2 R0 L6
      28 [-]: GETIMPORT R5 8 [0x67652851]
      29 [-]: CALL R5 0 1  
      30 [-]: ADD R2 R2 R5 
      31 [-]: DIV R7 R2 R0 
      32 [-]: SUB R6 R4 R7 
      33 [-]: FASTCALL1 2 R6 L5
      34 [-]: GETIMPORT R5 11 [0xE4A5B3CA]
      35 [-]: CALL R5 1 1  
L 5:  36 [-]: MOVE R8 R5   
      37 [-]: NAMECALL R6 R3 K12 [0x66472BF5]
      38 [-]: CALL R6 2 0  
      39 [-]: GETIMPORT R6 14 [0xCBD666E1]
      40 [-]: LOADN R7 0   
      41 [-]: CALL R6 1 0  
      42 [-]: JUMPBACK L4  
L 6:  43 [-]: FASTCALL1 62 R1 L7
      44 [-]: MOVE R6 R1   
      45 [-]: GETIMPORT R5 2 [0x7B998233]
      46 [-]: CALL R5 1 1  
L 7:  47 [-]: JUMPIF R5 L8 
      48 [-]: JUMPXEQKB R1 1 L8 NOT
      49 [-]: LOADB R7 0   
      50 [-]: LOADB R8 1   
      51 [-]: NAMECALL R5 R3 K6 [0x768274D6]
      52 [-]: CALL R5 3 0  
      53 [-]: RETURN R0 0  
L 8:  54 [-]: LOADN R7 0   
      55 [-]: NAMECALL R5 R3 K12 [0x66472BF5]
      56 [-]: CALL R5 2 0  
      57 [-]: RETURN R0 0  


; Name:            
; Defined at line: 369
; #Upvalues:       3
; #Parameters:     3
; Is_vararg:       0
; Max Stack Size:  7

       0 [-]: GETUPVAL R4 0
       1 [-]: GETTABLEKS R3 R4 K0 [0x217A3A95]
       2 [-]: LOADB R4 0   
       3 [-]: CALL R3 1 0  
       4 [-]: GETIMPORT R3 2 [0x89326C93]
       5 [-]: MOVE R5 R0   
       6 [-]: NAMECALL R3 R3 K3 [0x46A0EBF5]
       7 [-]: CALL R3 2 1  
       8 [-]: FASTCALL1 62 R3 L0
       9 [-]: MOVE R5 R3   
      10 [-]: GETIMPORT R4 5 [0x7B998233]
      11 [-]: CALL R4 1 1  
L 0:  12 [-]: JUMPIF R4 L1 
      13 [-]: GETIMPORT R4 7 [0xCBD666E1]
      14 [-]: LOADN R5 0   
      15 [-]: CALL R4 1 0  
      16 [-]: LOADK R6 K8 ["Activate"]
      17 [-]: NAMECALL R4 R3 K9 [0x8EB2112D]
      18 [-]: CALL R4 2 0  
L 1:  19 [-]: JUMPIFNOT R2 L2
      20 [-]: GETUPVAL R4 1
      21 [-]: LOADN R5 1   
      22 [-]: LOADB R6 1   
      23 [-]: CALL R4 2 0  
      24 [-]: JUMP L3
     
L 2:  25 [-]: GETIMPORT R4 7 [0xCBD666E1]
      26 [-]: LOADN R5 1   
      27 [-]: CALL R4 1 0  
L 3:  28 [-]: MOVE R4 R1   
      29 [-]: CALL R4 0 0  
L 4:  30 [-]: NAMECALL R4 R3 K10 [0xD8140B94]
      31 [-]: CALL R4 1 1  
      32 [-]: JUMPIFNOT R4 L5
      33 [-]: GETIMPORT R4 7 [0xCBD666E1]
      34 [-]: LOADN R5 0   
      35 [-]: CALL R4 1 0  
      36 [-]: JUMPBACK L4  
L 5:  37 [-]: GETUPVAL R5 0
      38 [-]: GETTABLEKS R4 R5 K0 [0x217A3A95]
      39 [-]: LOADB R5 1   
      40 [-]: CALL R4 1 0  
      41 [-]: JUMPIFNOT R2 L6
      42 [-]: GETUPVAL R4 1
      43 [-]: LOADN R5 1   
      44 [-]: LOADB R6 0   
      45 [-]: CALL R4 2 0  
L 6:  46 [-]: GETUPVAL R5 2
      47 [-]: GETTABLEKS R4 R5 K11 [0xED8F83F8]
      48 [-]: CALL R4 0 1  
      49 [-]: JUMPIFNOT R4 L7
      50 [-]: GETIMPORT R4 7 [0xCBD666E1]
      51 [-]: LOADN R5 0   
      52 [-]: CALL R4 1 0  
      53 [-]: JUMPBACK L6  
L 7:  54 [-]: RETURN R0 0  


; Name:            
; Defined at line: 411
; #Upvalues:       3
; #Parameters:     0
; Is_vararg:       0
; Max Stack Size:  5

       0 [-]: NEWCLOSURE R0 P0
       1 [-]: MOVE R2 R0   
       2 [-]: MOVE R2 R1   
       3 [-]: GETUPVAL R1 2
       4 [-]: GETIMPORT R2 1 [0x69F43E88]
       5 [-]: MOVE R3 R0   
       6 [-]: CALL R1 2 0  
       7 [-]: GETIMPORT R1 3 [0x89326C93]
       8 [-]: GETIMPORT R3 5 [0x0469F296]
       9 [-]: LOADK R4 K6 ["ThraxDollLightTurnOff"]
      10 [-]: CALL R3 1 -1 
      11 [-]: NAMECALL R1 R1 K7 [0x46A0EBF5]
      12 [-]: CALL R1 -1 1 
      13 [-]: FASTCALL1 62 R1 L0
      14 [-]: MOVE R3 R1   
      15 [-]: GETIMPORT R2 9 [0x7B998233]
      16 [-]: CALL R2 1 1  
L 0:  17 [-]: JUMPIF R2 L1 
      18 [-]: LOADK R4 K10 ["Execute"]
      19 [-]: NAMECALL R2 R1 K11 [0x8EB2112D]
      20 [-]: CALL R2 2 0  
L 1:  21 [-]: RETURN R0 0  


; Name:            
; Defined at line: 434
; #Upvalues:       0
; #Parameters:     3
; Is_vararg:       0
; Max Stack Size:  20

       0 [-]: GETIMPORT R4 2 ["DuviriQuestWeapons"]
       1 [-]: GETTABLE R3 R4 R1
       2 [-]: GETTABLEKS R5 R0 K3 ["Equipment"]
       3 [-]: GETTABLE R4 R5 R1
       4 [-]: GETIMPORT R5 5 [0xB009BBC6]
       5 [-]: GETTABLE R6 R3 R4
       6 [-]: NAMECALL R6 R6 K6 [0xED4E0128]
       7 [-]: CALL R6 1 -1 
       8 [-]: CALL R5 -1 1 
       9 [-]: NAMECALL R6 R5 K7 [0x16D81B57]
      10 [-]: CALL R6 1 1  
      11 [-]: GETIMPORT R7 9 [0x89326C93]
      12 [-]: GETIMPORT R9 11 [0x0469F296]
      13 [-]: LOADK R10 K12 ["WeaponSpawnWp"]
      14 [-]: CALL R9 1 1  
      15 [-]: NAMECALL R10 R2 K13 [0xD1586535]
      16 [-]: CALL R10 1 -1
      17 [-]: NAMECALL R7 R7 K14 [0xC7B81E8D]
      18 [-]: CALL R7 -1 1 
      19 [-]: LOADNIL R8   
      20 [-]: JUMPXEQKN R1 K15 L0 NOT [0]
      21 [-]: JUMPXEQKN R4 K16 L1 [3]
L 0:  22 [-]: JUMPXEQKN R1 K17 L4 NOT [5]
      23 [-]: JUMPXEQKN R4 K18 L4 NOT [2]
L 1:  24 [-]: GETIMPORT R9 9 [0x89326C93]
      25 [-]: GETIMPORT R11 20 [0x43C04BB9]
      26 [-]: NAMECALL R12 R7 K13 [0xD1586535]
      27 [-]: CALL R12 1 1 
      28 [-]: GETIMPORT R13 22 [0x20E8CA12]
      29 [-]: NAMECALL R14 R7 K23 [0xCB3851B8]
      30 [-]: CALL R14 1 1 
      31 [-]: GETIMPORT R15 25 [0x00046924]
      32 [-]: LOADN R16 0  
      33 [-]: LOADN R17 180
      34 [-]: LOADN R18 0  
      35 [-]: CALL R15 3 -1
      36 [-]: CALL R13 -1 -1
      37 [-]: NAMECALL R9 R9 K26 [0x05909209]
      38 [-]: CALL R9 -1 1 
      39 [-]: MOVE R8 R9   
      40 [-]: MOVE R11 R6  
      41 [-]: LOADB R12 1  
      42 [-]: LOADB R13 0  
      43 [-]: NAMECALL R9 R8 K27 [0x2970F52F]
      44 [-]: CALL R9 4 0  
      45 [-]: NAMECALL R9 R8 K28 [0x905BB2BD]
      46 [-]: CALL R9 1 1  
      47 [-]: GETIMPORT R10 30 [0xC8802016]
      48 [-]: MOVE R11 R9  
      49 [-]: CALL R10 1 3 
      50 [-]: FORGPREP_INEXT R10 L3
L 2:  51 [-]: MOVE R17 R6  
      52 [-]: LOADB R18 1  
      53 [-]: LOADB R19 0  
      54 [-]: NAMECALL R15 R14 K27 [0x2970F52F]
      55 [-]: CALL R15 4 0 
L 3:  56 [-]: FORGLOOP R10 L2 2 [inext]
      57 [-]: RETURN R8 1  
L 4:  58 [-]: GETIMPORT R9 9 [0x89326C93]
      59 [-]: GETIMPORT R11 32 [0x9748BAD3]
      60 [-]: NAMECALL R12 R7 K13 [0xD1586535]
      61 [-]: CALL R12 1 1 
      62 [-]: NAMECALL R13 R7 K23 [0xCB3851B8]
      63 [-]: CALL R13 1 -1
      64 [-]: NAMECALL R9 R9 K26 [0x05909209]
      65 [-]: CALL R9 -1 1 
      66 [-]: MOVE R8 R9   
      67 [-]: MOVE R11 R6  
      68 [-]: LOADB R12 1  
      69 [-]: LOADB R13 0  
      70 [-]: NAMECALL R9 R8 K27 [0x2970F52F]
      71 [-]: CALL R9 4 0  
      72 [-]: RETURN R8 1  


; Name:            
; Defined at line: 457
; #Upvalues:       0
; #Parameters:     2
; Is_vararg:       0
; Max Stack Size:  8

       0 [-]: LOADNIL R2   
       1 [-]: JUMPIFNOT R1 L0
       2 [-]: GETIMPORT R3 1 [0x89326C93]
       3 [-]: GETIMPORT R5 3 [0x0469F296]
       4 [-]: LOADK R6 K4 ["LightsOn"]
       5 [-]: CALL R5 1 1  
       6 [-]: NAMECALL R6 R0 K5 [0xD1586535]
       7 [-]: CALL R6 1 -1 
       8 [-]: NAMECALL R3 R3 K6 [0xC7B81E8D]
       9 [-]: CALL R3 -1 1 
      10 [-]: MOVE R2 R3   
      11 [-]: JUMP L1
     
L 0:  12 [-]: GETIMPORT R3 1 [0x89326C93]
      13 [-]: GETIMPORT R5 3 [0x0469F296]
      14 [-]: LOADK R6 K7 ["LightsOut"]
      15 [-]: CALL R5 1 1  
      16 [-]: NAMECALL R6 R0 K5 [0xD1586535]
      17 [-]: CALL R6 1 -1 
      18 [-]: NAMECALL R3 R3 K6 [0xC7B81E8D]
      19 [-]: CALL R3 -1 1 
      20 [-]: MOVE R2 R3   
L 1:  21 [-]: LOADK R5 K8 ["TriggerPort"]
      22 [-]: NAMECALL R3 R2 K9 [0x8EB2112D]
      23 [-]: CALL R3 2 0  
      24 [-]: RETURN R0 0  


; Name:            
; Defined at line: 467
; #Upvalues:       2
; #Parameters:     4
; Is_vararg:       0
; Max Stack Size:  8

       0 [-]: JUMPIF R0 L0 
       1 [-]: GETUPVAL R4 0
       2 [-]: MOVE R5 R1   
       3 [-]: MOVE R6 R2   
       4 [-]: MOVE R7 R3   
       5 [-]: CALL R4 3 1  
       6 [-]: MOVE R0 R4   
       7 [-]: JUMP L1
     
L 0:   8 [-]: LOADB R6 1   
       9 [-]: LOADB R7 1   
      10 [-]: NAMECALL R4 R0 K0 [0x768274D6]
      11 [-]: CALL R4 3 0  
L 1:  12 [-]: GETUPVAL R4 1
      13 [-]: MOVE R5 R3   
      14 [-]: LOADB R6 1   
      15 [-]: CALL R4 2 0  
      16 [-]: RETURN R0 1  


; Name:            
; Defined at line: 477
; #Upvalues:       1
; #Parameters:     2
; Is_vararg:       0
; Max Stack Size:  6

       0 [-]: NAMECALL R2 R0 K0 [0xD4CC05B4]
       1 [-]: CALL R2 1 1  
       2 [-]: JUMPIFNOT R2 L0
       3 [-]: JUMPXEQKN R1 K1 L0 NOT [1]
       4 [-]: LOADB R4 0   
       5 [-]: LOADB R5 1   
       6 [-]: NAMECALL R2 R0 K2 [0x768274D6]
       7 [-]: CALL R2 3 0  
       8 [-]: GETUPVAL R2 0
       9 [-]: MOVE R3 R0   
      10 [-]: LOADB R4 0   
      11 [-]: CALL R2 2 0  
      12 [-]: RETURN R0 0  
L 0:  13 [-]: NAMECALL R2 R0 K0 [0xD4CC05B4]
      14 [-]: CALL R2 1 1  
      15 [-]: JUMPIF R2 L1 
      16 [-]: JUMPXEQKN R1 K3 L1 NOT [0]
      17 [-]: LOADB R4 1   
      18 [-]: LOADB R5 1   
      19 [-]: NAMECALL R2 R0 K2 [0x768274D6]
      20 [-]: CALL R2 3 0  
      21 [-]: GETUPVAL R2 0
      22 [-]: MOVE R3 R0   
      23 [-]: LOADB R4 1   
      24 [-]: CALL R2 2 0  
L 1:  25 [-]: RETURN R0 0  


; Name:            
; Defined at line: 487
; #Upvalues:       5
; #Parameters:     0
; Is_vararg:       0
; Max Stack Size:  4

       0 [-]: GETUPVAL R0 0
       1 [-]: GETUPVAL R1 1
       2 [-]: GETUPVAL R3 2
       3 [-]: GETTABLEKS R2 R3 K0 ["PRIMARY"]
       4 [-]: CALL R0 2 0  
       5 [-]: GETUPVAL R0 0
       6 [-]: GETUPVAL R1 3
       7 [-]: GETUPVAL R3 2
       8 [-]: GETTABLEKS R2 R3 K1 ["SECONDARY"]
       9 [-]: CALL R0 2 0  
      10 [-]: GETUPVAL R0 0
      11 [-]: GETUPVAL R1 4
      12 [-]: GETUPVAL R3 2
      13 [-]: GETTABLEKS R2 R3 K2 ["MELEE"]
      14 [-]: CALL R0 2 0  
      15 [-]: RETURN R0 0  


; Name:            
; Defined at line: 493
; #Upvalues:       13
; #Parameters:     0
; Is_vararg:       0
; Max Stack Size:  8

       0 [-]: GETUPVAL R0 0
       1 [-]: GETUPVAL R1 1
       2 [-]: GETUPVAL R3 2
       3 [-]: GETTABLEKS R2 R3 K0 ["PRIMARY"]
       4 [-]: CALL R0 2 0  
       5 [-]: GETUPVAL R0 0
       6 [-]: GETUPVAL R1 3
       7 [-]: GETUPVAL R3 2
       8 [-]: GETTABLEKS R2 R3 K1 ["SECONDARY"]
       9 [-]: CALL R0 2 0  
      10 [-]: GETUPVAL R0 0
      11 [-]: GETUPVAL R1 4
      12 [-]: GETUPVAL R3 2
      13 [-]: GETTABLEKS R2 R3 K2 ["MELEE"]
      14 [-]: CALL R0 2 0  
      15 [-]: GETUPVAL R1 5
      16 [-]: GETTABLEKS R0 R1 K3 [0x9742B85B]
      17 [-]: GETUPVAL R1 6
      18 [-]: GETIMPORT R2 5 [0x0469F296]
      19 [-]: LOADK R3 K6 ["DDuvParQDormCave0890"]
      20 [-]: CALL R2 1 1  
      21 [-]: LOADB R3 0   
      22 [-]: LOADB R4 0   
      23 [-]: CALL R0 4 0  
      24 [-]: LOADN R0 -1  
      25 [-]: SETUPVAL R0 7
      26 [-]: GETUPVAL R1 8
      27 [-]: GETTABLEKS R0 R1 K7 [0xDC3B2033]
      28 [-]: CALL R0 0 0  
      29 [-]: GETIMPORT R0 9 [0xCBD666E1]
      30 [-]: LOADN R1 1   
      31 [-]: CALL R0 1 0  
      32 [-]: GETUPVAL R1 8
      33 [-]: GETTABLEKS R0 R1 K10 [0xA1DF01D6]
      34 [-]: GETUPVAL R2 9
      35 [-]: GETTABLEKS R1 R2 K11 ["FREE_ROAM_WEAPONS_OBJ"]
      36 [-]: CALL R0 1 0  
      37 [-]: LOADB R0 1   
      38 [-]: NEWTABLE R1 0 0
L 0:  39 [-]: JUMPIFNOT R0 L7
      40 [-]: GETUPVAL R2 7
      41 [-]: JUMPXEQKN R2 K12 L5 NOT [-1]
      42 [-]: NEWTABLE R1 0 0
      43 [-]: GETUPVAL R3 2
      44 [-]: GETTABLEKS R2 R3 K0 ["PRIMARY"]
      45 [-]: JUMPXEQKN R2 K13 L1 NOT [0]
      46 [-]: GETUPVAL R4 10
      47 [-]: GETIMPORT R5 15 [0xB2C5BE14]
      48 [-]: LOADNIL R6   
      49 [-]: GETUPVAL R7 11
      50 [-]: CALL R4 3 1  
      51 [-]: FASTCALL2 52 R1 R4 L1
      52 [-]: MOVE R3 R1   
      53 [-]: GETIMPORT R2 18 [0x23D5322F]
      54 [-]: CALL R2 2 0  
L 1:  55 [-]: GETUPVAL R3 2
      56 [-]: GETTABLEKS R2 R3 K1 ["SECONDARY"]
      57 [-]: JUMPXEQKN R2 K13 L2 NOT [0]
      58 [-]: GETUPVAL R4 10
      59 [-]: GETIMPORT R5 20 [0xBC9AC9DC]
      60 [-]: LOADNIL R6   
      61 [-]: GETUPVAL R7 11
      62 [-]: CALL R4 3 1  
      63 [-]: FASTCALL2 52 R1 R4 L2
      64 [-]: MOVE R3 R1   
      65 [-]: GETIMPORT R2 18 [0x23D5322F]
      66 [-]: CALL R2 2 0  
L 2:  67 [-]: GETUPVAL R3 2
      68 [-]: GETTABLEKS R2 R3 K2 ["MELEE"]
      69 [-]: JUMPXEQKN R2 K13 L3 NOT [0]
      70 [-]: GETUPVAL R4 10
      71 [-]: GETIMPORT R5 22 [0x4E2F5D3A]
      72 [-]: LOADNIL R6   
      73 [-]: GETUPVAL R7 11
      74 [-]: CALL R4 3 1  
      75 [-]: FASTCALL2 52 R1 R4 L3
      76 [-]: MOVE R3 R1   
      77 [-]: GETIMPORT R2 18 [0x23D5322F]
      78 [-]: CALL R2 2 0  
L 3:  79 [-]: LENGTH R2 R1 
      80 [-]: JUMPXEQKN R2 K13 L4 NOT [0]
      81 [-]: LOADB R0 0   
L 4:  82 [-]: LOADN R2 0   
      83 [-]: SETUPVAL R2 7
L 5:  84 [-]: GETUPVAL R2 7
      85 [-]: JUMPXEQKN R2 K23 L6 NOT [1]
      86 [-]: GETUPVAL R2 12
      87 [-]: MOVE R3 R1   
      88 [-]: CALL R2 1 0  
      89 [-]: GETUPVAL R2 0
      90 [-]: GETUPVAL R3 1
      91 [-]: GETUPVAL R5 2
      92 [-]: GETTABLEKS R4 R5 K0 ["PRIMARY"]
      93 [-]: CALL R2 2 0  
      94 [-]: GETUPVAL R2 0
      95 [-]: GETUPVAL R3 3
      96 [-]: GETUPVAL R5 2
      97 [-]: GETTABLEKS R4 R5 K1 ["SECONDARY"]
      98 [-]: CALL R2 2 0  
      99 [-]: GETUPVAL R2 0
     100 [-]: GETUPVAL R3 4
     101 [-]: GETUPVAL R5 2
     102 [-]: GETTABLEKS R4 R5 K2 ["MELEE"]
     103 [-]: CALL R2 2 0  
     104 [-]: LOADN R2 -1  
     105 [-]: SETUPVAL R2 7
     106 [-]: GETIMPORT R2 9 [0xCBD666E1]
     107 [-]: LOADN R3 1   
     108 [-]: CALL R2 1 0  
L 6: 109 [-]: GETIMPORT R2 9 [0xCBD666E1]
     110 [-]: LOADN R3 0   
     111 [-]: CALL R2 1 0  
     112 [-]: JUMPBACK L0  
L 7: 113 [-]: GETUPVAL R3 8
     114 [-]: GETTABLEKS R2 R3 K7 [0xDC3B2033]
     115 [-]: CALL R2 0 0  
L 8: 116 [-]: GETUPVAL R3 5
     117 [-]: GETTABLEKS R2 R3 K24 [0xED8F83F8]
     118 [-]: CALL R2 0 1  
     119 [-]: JUMPIFNOT R2 L9
     120 [-]: GETIMPORT R2 9 [0xCBD666E1]
     121 [-]: LOADN R3 0   
     122 [-]: CALL R2 1 0  
     123 [-]: JUMPBACK L8  
L 9: 124 [-]: RETURN R0 0  


; Name:            
; Defined at line: 543
; #Upvalues:       3
; #Parameters:     0
; Is_vararg:       0
; Max Stack Size:  5

       0 [-]: NEWCLOSURE R0 P0
       1 [-]: MOVE R2 R0   
       2 [-]: MOVE R2 R1   
       3 [-]: GETUPVAL R1 2
       4 [-]: GETIMPORT R2 1 [0x0469F296]
       5 [-]: LOADK R3 K2 ["AngryQuestMaskCamera"]
       6 [-]: CALL R2 1 1  
       7 [-]: MOVE R3 R0   
       8 [-]: LOADB R4 1   
       9 [-]: CALL R1 3 0  
      10 [-]: RETURN R0 0  


; Name:            
; Defined at line: 557
; #Upvalues:       1
; #Parameters:     2
; Is_vararg:       0
; Max Stack Size:  7

       0 [-]: GETUPVAL R2 0
       1 [-]: JUMPIFNOT R2 L0
       2 [-]: GETUPVAL R2 0
       3 [-]: NAMECALL R2 R2 K0 [0xA2880940]
       4 [-]: CALL R2 1 0  
L 0:   5 [-]: GETIMPORT R2 2 [0x89326C93]
       6 [-]: GETIMPORT R4 4 [0x78EB7099]
       7 [-]: MOVE R5 R0   
       8 [-]: MOVE R6 R1   
       9 [-]: NAMECALL R2 R2 K5 [0x05909209]
      10 [-]: CALL R2 4 1  
      11 [-]: SETUPVAL R2 0
      12 [-]: GETUPVAL R2 0
      13 [-]: GETIMPORT R4 7 [0x0469F296]
      14 [-]: LOADK R5 K8 ["StoryCheckpointWp"]
      15 [-]: CALL R4 1 -1 
      16 [-]: NAMECALL R2 R2 K9 [0x3273BA96]
      17 [-]: CALL R2 -1 0 
      18 [-]: RETURN R0 0  


; Name:            
; Defined at line: 567
; #Upvalues:       5
; #Parameters:     1
; Is_vararg:       0
; Max Stack Size:  4

       0 [-]: NAMECALL R1 R0 K0 [0x22DA1852]
       1 [-]: CALL R1 1 1  
       2 [-]: GETIMPORT R2 2 [0x0469F296]
       3 [-]: LOADK R3 K3 ["FigurineCollectTrigger"]
       4 [-]: CALL R2 1 1  
       5 [-]: JUMPIFNOTEQ R1 R2 L0
       6 [-]: NAMECALL R2 R0 K4 [0xA2880940]
       7 [-]: CALL R2 1 0  
       8 [-]: RETURN R0 0  
L 0:   9 [-]: GETIMPORT R2 6 [0x7FB428F8]
      10 [-]: JUMPIFNOTEQ R1 R2 L1
      11 [-]: GETUPVAL R3 1
      12 [-]: GETTABLEKS R2 R3 K7 ["FIGURINE"]
      13 [-]: SETUPVAL R2 0
      14 [-]: GETIMPORT R2 9 ["_T"]
      15 [-]: LOADB R3 1   
      16 [-]: SETTABLEKS R3 R2 K10 ["FigurineInteract"]
      17 [-]: JUMP L6
     
L 1:  18 [-]: GETIMPORT R2 12 [0xF752C275]
      19 [-]: JUMPIFNOTEQ R1 R2 L2
      20 [-]: GETUPVAL R3 1
      21 [-]: GETTABLEKS R2 R3 K13 ["MASK"]
      22 [-]: SETUPVAL R2 0
      23 [-]: JUMP L6
     
L 2:  24 [-]: GETIMPORT R2 15 [0xB2C5BE14]
      25 [-]: JUMPIFNOTEQ R1 R2 L3
      26 [-]: GETUPVAL R3 1
      27 [-]: GETTABLEKS R2 R3 K16 ["SECONDARYWEAPON"]
      28 [-]: SETUPVAL R2 0
      29 [-]: GETUPVAL R2 2
      30 [-]: LOADN R3 1   
      31 [-]: SETTABLEKS R3 R2 K17 ["PRIMARY"]
      32 [-]: LOADN R2 1   
      33 [-]: SETUPVAL R2 3
      34 [-]: JUMP L6
     
L 3:  35 [-]: GETIMPORT R2 19 [0xBC9AC9DC]
      36 [-]: JUMPIFNOTEQ R1 R2 L4
      37 [-]: GETUPVAL R3 1
      38 [-]: GETTABLEKS R2 R3 K16 ["SECONDARYWEAPON"]
      39 [-]: SETUPVAL R2 0
      40 [-]: GETUPVAL R2 2
      41 [-]: LOADN R3 1   
      42 [-]: SETTABLEKS R3 R2 K20 ["SECONDARY"]
      43 [-]: LOADN R2 1   
      44 [-]: SETUPVAL R2 3
      45 [-]: JUMP L6
     
L 4:  46 [-]: GETIMPORT R2 22 [0x4E2F5D3A]
      47 [-]: JUMPIFNOTEQ R1 R2 L5
      48 [-]: GETUPVAL R3 1
      49 [-]: GETTABLEKS R2 R3 K16 ["SECONDARYWEAPON"]
      50 [-]: SETUPVAL R2 0
      51 [-]: GETUPVAL R2 2
      52 [-]: LOADN R3 1   
      53 [-]: SETTABLEKS R3 R2 K23 ["MELEE"]
      54 [-]: LOADN R2 1   
      55 [-]: SETUPVAL R2 3
      56 [-]: JUMP L6
     
L 5:  57 [-]: GETIMPORT R2 2 [0x0469F296]
      58 [-]: LOADK R3 K24 ["SitByFireAction"]
      59 [-]: CALL R2 1 1  
      60 [-]: JUMPIFNOTEQ R1 R2 L6
      61 [-]: LOADB R2 1   
      62 [-]: SETUPVAL R2 4
L 6:  63 [-]: NAMECALL R2 R0 K25 [0xF4E253B6]
      64 [-]: CALL R2 1 0  
      65 [-]: RETURN R0 0  


; Name:            
; Defined at line: 597
; #Upvalues:       23
; #Parameters:     0
; Is_vararg:       0
; Max Stack Size:  18

       0 [-]: GETIMPORT R0 1 [0x89326C93]
       1 [-]: GETIMPORT R2 3 [0x7FB428F8]
       2 [-]: NAMECALL R0 R0 K4 [0x46A0EBF5]
       3 [-]: CALL R0 2 1  
       4 [-]: GETIMPORT R1 6 [0x11A19C5E]
       5 [-]: MOVE R2 R0   
       6 [-]: LOADK R3 K7 ["OnActivated"]
       7 [-]: CALL R1 2 0  
       8 [-]: GETIMPORT R1 1 [0x89326C93]
       9 [-]: GETIMPORT R3 9 [0xF752C275]
      10 [-]: NAMECALL R1 R1 K4 [0x46A0EBF5]
      11 [-]: CALL R1 2 1  
      12 [-]: GETIMPORT R2 6 [0x11A19C5E]
      13 [-]: MOVE R3 R1   
      14 [-]: LOADK R4 K7 ["OnActivated"]
      15 [-]: CALL R2 2 0  
      16 [-]: GETIMPORT R2 1 [0x89326C93]
      17 [-]: GETIMPORT R4 11 [0xB2C5BE14]
      18 [-]: NAMECALL R2 R2 K4 [0x46A0EBF5]
      19 [-]: CALL R2 2 1  
      20 [-]: GETIMPORT R3 6 [0x11A19C5E]
      21 [-]: MOVE R4 R2   
      22 [-]: LOADK R5 K7 ["OnActivated"]
      23 [-]: CALL R3 2 0  
      24 [-]: GETIMPORT R3 1 [0x89326C93]
      25 [-]: GETIMPORT R5 13 [0xBC9AC9DC]
      26 [-]: NAMECALL R3 R3 K4 [0x46A0EBF5]
      27 [-]: CALL R3 2 1  
      28 [-]: GETIMPORT R4 6 [0x11A19C5E]
      29 [-]: MOVE R5 R3   
      30 [-]: LOADK R6 K7 ["OnActivated"]
      31 [-]: CALL R4 2 0  
      32 [-]: GETIMPORT R4 1 [0x89326C93]
      33 [-]: GETIMPORT R6 15 [0x4E2F5D3A]
      34 [-]: NAMECALL R4 R4 K4 [0x46A0EBF5]
      35 [-]: CALL R4 2 1  
      36 [-]: GETIMPORT R5 6 [0x11A19C5E]
      37 [-]: MOVE R6 R4   
      38 [-]: LOADK R7 K7 ["OnActivated"]
      39 [-]: CALL R5 2 0  
      40 [-]: GETUPVAL R6 0
      41 [-]: GETTABLEKS R5 R6 K16 [0x1CF754D5]
      42 [-]: CALL R5 0 1  
      43 [-]: GETUPVAL R7 1
      44 [-]: LOADN R8 1   
      45 [-]: JUMPIF R7 L0 
      46 [-]: GETUPVAL R9 2
      47 [-]: MOVE R10 R5  
      48 [-]: MOVE R11 R8  
      49 [-]: MOVE R12 R2  
      50 [-]: CALL R9 3 1  
      51 [-]: MOVE R7 R9   
      52 [-]: JUMP L1
     
L 0:  53 [-]: LOADB R11 1  
      54 [-]: LOADB R12 1  
      55 [-]: NAMECALL R9 R7 K17 [0x768274D6]
      56 [-]: CALL R9 3 0  
L 1:  57 [-]: GETUPVAL R9 3
      58 [-]: MOVE R10 R2  
      59 [-]: LOADB R11 1  
      60 [-]: CALL R9 2 0  
      61 [-]: MOVE R6 R7   
      62 [-]: SETUPVAL R6 1
      63 [-]: GETUPVAL R7 4
      64 [-]: LOADN R8 0   
      65 [-]: JUMPIF R7 L2 
      66 [-]: GETUPVAL R9 2
      67 [-]: MOVE R10 R5  
      68 [-]: MOVE R11 R8  
      69 [-]: MOVE R12 R3  
      70 [-]: CALL R9 3 1  
      71 [-]: MOVE R7 R9   
      72 [-]: JUMP L3
     
L 2:  73 [-]: LOADB R11 1  
      74 [-]: LOADB R12 1  
      75 [-]: NAMECALL R9 R7 K17 [0x768274D6]
      76 [-]: CALL R9 3 0  
L 3:  77 [-]: GETUPVAL R9 3
      78 [-]: MOVE R10 R3  
      79 [-]: LOADB R11 1  
      80 [-]: CALL R9 2 0  
      81 [-]: MOVE R6 R7   
      82 [-]: SETUPVAL R6 4
      83 [-]: GETUPVAL R7 5
      84 [-]: LOADN R8 5   
      85 [-]: JUMPIF R7 L4 
      86 [-]: GETUPVAL R9 2
      87 [-]: MOVE R10 R5  
      88 [-]: MOVE R11 R8  
      89 [-]: MOVE R12 R4  
      90 [-]: CALL R9 3 1  
      91 [-]: MOVE R7 R9   
      92 [-]: JUMP L5
     
L 4:  93 [-]: LOADB R11 1  
      94 [-]: LOADB R12 1  
      95 [-]: NAMECALL R9 R7 K17 [0x768274D6]
      96 [-]: CALL R9 3 0  
L 5:  97 [-]: GETUPVAL R9 3
      98 [-]: MOVE R10 R4  
      99 [-]: LOADB R11 1  
     100 [-]: CALL R9 2 0  
     101 [-]: MOVE R6 R7   
     102 [-]: SETUPVAL R6 5
     103 [-]: LOADB R6 1   
     104 [-]: NEWTABLE R7 0 0
     105 [-]: LOADN R8 3   
L 6: 106 [-]: LOADN R9 0   
     107 [-]: JUMPIFNOTLT R9 R8 L18
     108 [-]: JUMPIFNOT R6 L13
     109 [-]: NEWTABLE R7 0 0
     110 [-]: GETUPVAL R9 6
     111 [-]: JUMPIF R9 L7 
     112 [-]: GETUPVAL R11 7
     113 [-]: GETIMPORT R12 3 [0x7FB428F8]
     114 [-]: GETIMPORT R13 19 [0xA364E08E]
     115 [-]: CALL R11 2 1 
     116 [-]: FASTCALL2 52 R7 R11 L7
     117 [-]: MOVE R10 R7  
     118 [-]: GETIMPORT R9 22 [0x23D5322F]
     119 [-]: CALL R9 2 0  
L 7: 120 [-]: GETUPVAL R9 8
     121 [-]: JUMPIF R9 L10
     122 [-]: GETUPVAL R9 9
     123 [-]: CALL R9 0 1  
     124 [-]: GETIMPORT R10 24 [0xC8802016]
     125 [-]: MOVE R11 R9  
     126 [-]: CALL R10 1 3 
     127 [-]: FORGPREP_INEXT R10 L9
L 8: 128 [-]: FASTCALL2 52 R7 R14 L9
     129 [-]: MOVE R16 R7  
     130 [-]: MOVE R17 R14 
     131 [-]: GETIMPORT R15 22 [0x23D5322F]
     132 [-]: CALL R15 2 0 
L 9: 133 [-]: FORGLOOP R10 L8 2 [inext]
L10: 134 [-]: GETUPVAL R9 10
     135 [-]: JUMPIF R9 L11
     136 [-]: GETUPVAL R11 7
     137 [-]: GETIMPORT R12 9 [0xF752C275]
     138 [-]: GETIMPORT R13 26 [0xFF699EA9]
     139 [-]: CALL R11 2 1 
     140 [-]: FASTCALL2 52 R7 R11 L11
     141 [-]: MOVE R10 R7  
     142 [-]: GETIMPORT R9 22 [0x23D5322F]
     143 [-]: CALL R9 2 0  
L11: 144 [-]: LENGTH R9 R7 
     145 [-]: LOADN R10 0  
     146 [-]: JUMPIFNOTLT R10 R9 L12
     147 [-]: GETUPVAL R10 11
     148 [-]: GETTABLEKS R9 R10 K27 [0xA1DF01D6]
     149 [-]: GETUPVAL R11 12
     150 [-]: GETTABLEKS R10 R11 K28 ["FREE_ROAM_OBJ"]
     151 [-]: CALL R9 1 0  
L12: 152 [-]: LOADB R6 0   
     153 [-]: JUMP L17
    
L13: 154 [-]: GETUPVAL R9 13
     155 [-]: JUMPXEQKN R9 K29 L17 [0]
     156 [-]: GETUPVAL R10 11
     157 [-]: GETTABLEKS R9 R10 K30 [0xDC3B2033]
     158 [-]: CALL R9 0 0  
     159 [-]: GETUPVAL R9 14
     160 [-]: MOVE R10 R7  
     161 [-]: CALL R9 1 0  
     162 [-]: GETUPVAL R9 13
     163 [-]: GETUPVAL R11 15
     164 [-]: GETTABLEKS R10 R11 K31 ["FIGURINE"]
     165 [-]: JUMPIFNOTEQ R9 R10 L14
     166 [-]: GETUPVAL R9 16
     167 [-]: CALL R9 0 0  
     168 [-]: LOADB R9 1   
     169 [-]: SETUPVAL R9 6
     170 [-]: JUMP L16
    
L14: 171 [-]: GETUPVAL R9 13
     172 [-]: GETUPVAL R11 15
     173 [-]: GETTABLEKS R10 R11 K32 ["SECONDARYWEAPON"]
     174 [-]: JUMPIFNOTEQ R9 R10 L15
     175 [-]: GETUPVAL R9 17
     176 [-]: CALL R9 0 0  
     177 [-]: LOADB R9 1   
     178 [-]: SETUPVAL R9 8
     179 [-]: JUMP L16
    
L15: 180 [-]: GETUPVAL R9 13
     181 [-]: GETUPVAL R11 15
     182 [-]: GETTABLEKS R10 R11 K33 ["MASK"]
     183 [-]: JUMPIFNOTEQ R9 R10 L16
     184 [-]: NEWCLOSURE R9 P0
     185 [-]: MOVE R2 R18  
     186 [-]: MOVE R2 R19  
     187 [-]: GETUPVAL R10 20
     188 [-]: GETIMPORT R11 35 [0x0469F296]
     189 [-]: LOADK R12 K36 ["AngryQuestMaskCamera"]
     190 [-]: CALL R11 1 1 
     191 [-]: MOVE R12 R9  
     192 [-]: LOADB R13 1  
     193 [-]: CALL R10 3 0 
     194 [-]: LOADB R9 1   
     195 [-]: SETUPVAL R9 10
L16: 196 [-]: SUBK R8 R8 K37 [1]
     197 [-]: LOADN R9 0   
     198 [-]: SETUPVAL R9 13
     199 [-]: LOADB R6 1   
     200 [-]: GETIMPORT R9 39 [0xCBD666E1]
     201 [-]: LOADN R10 1  
     202 [-]: CALL R9 1 0  
L17: 203 [-]: GETIMPORT R9 39 [0xCBD666E1]
     204 [-]: LOADN R10 0  
     205 [-]: CALL R9 1 0  
     206 [-]: JUMPBACK L6  
L18: 207 [-]: LOADN R9 0   
     208 [-]: SETUPVAL R9 13
     209 [-]: GETUPVAL R10 11
     210 [-]: GETTABLEKS R9 R10 K30 [0xDC3B2033]
     211 [-]: CALL R9 0 0  
     212 [-]: GETUPVAL R9 21
     213 [-]: GETUPVAL R12 22
     214 [-]: GETTABLEKS R11 R12 K40 ["GO_TO_MAINLAND"]
     215 [-]: NAMECALL R9 R9 K41 [0x8ABFF40E]
     216 [-]: CALL R9 2 0  
     217 [-]: RETURN R0 0  


; Name:            
; Defined at line: 679
; #Upvalues:       14
; #Parameters:     0
; Is_vararg:       0
; Max Stack Size:  10

       0 [-]: GETUPVAL R1 0
       1 [-]: GETTABLEKS R0 R1 K0 [0x948125AB]
       2 [-]: GETIMPORT R1 2 [0xDDBB3ADA]
       3 [-]: GETIMPORT R2 4 [0xF40E7C8B]
       4 [-]: GETIMPORT R3 6 [0x9397F349]
       5 [-]: GETUPVAL R4 1
       6 [-]: CALL R0 4 0  
       7 [-]: GETUPVAL R1 2
       8 [-]: GETTABLEKS R0 R1 K7 [0x9742B85B]
       9 [-]: GETUPVAL R1 3
      10 [-]: GETIMPORT R2 9 [0x0469F296]
      11 [-]: LOADK R3 K10 ["DDuvParQDormCave0950"]
      12 [-]: CALL R2 1 1  
      13 [-]: LOADB R3 0   
      14 [-]: LOADB R4 1   
      15 [-]: CALL R0 4 0  
L 0:  16 [-]: GETIMPORT R1 13 ["StartStoryEncounter"]
      17 [-]: FASTCALL1 62 R1 L1
      18 [-]: GETIMPORT R0 15 [0x7B998233]
      19 [-]: CALL R0 1 1  
L 1:  20 [-]: JUMPIFNOT R0 L2
      21 [-]: GETIMPORT R0 17 [0xCBD666E1]
      22 [-]: LOADN R1 0   
      23 [-]: CALL R0 1 0  
      24 [-]: JUMPBACK L0  
L 2:  25 [-]: GETUPVAL R1 4
      26 [-]: GETTABLEKS R0 R1 K18 [0xA1DF01D6]
      27 [-]: GETUPVAL R2 5
      28 [-]: GETTABLEKS R1 R2 K19 ["GO_TO_MAINLAND_OBJ"]
      29 [-]: CALL R0 1 0  
      30 [-]: GETIMPORT R0 9 [0x0469F296]
      31 [-]: LOADK R1 K20 ["PortalDecoration"]
      32 [-]: CALL R0 1 2  
      33 [-]: GETUPVAL R3 0
      34 [-]: GETTABLEKS R2 R3 K21 [0x7C676590]
      35 [-]: GETUPVAL R3 7
      36 [-]: LOADNIL R4   
      37 [-]: MOVE R5 R0   
      38 [-]: MOVE R6 R1   
      39 [-]: GETIMPORT R7 23 [0xB7CBD06B]
      40 [-]: LOADN R8 2   
      41 [-]: LOADN R9 100 
      42 [-]: CALL R7 2 -1 
      43 [-]: CALL R2 -1 1 
      44 [-]: SETUPVAL R2 6
      45 [-]: GETUPVAL R2 6
      46 [-]: GETUPVAL R1 0
      47 [-]: GETTABLEKS R0 R1 K24 [0xD9337924]
      48 [-]: GETIMPORT R1 26 [0xBCAE77F6]
      49 [-]: LOADB R2 1   
      50 [-]: CALL R0 2 1  
      51 [-]: SETUPVAL R0 8
L 3:  52 [-]: GETUPVAL R1 9
      53 [-]: GETTABLEKS R0 R1 K27 [0xF3401BFF]
      54 [-]: CALL R0 0 1  
      55 [-]: JUMPIF R0 L4 
      56 [-]: GETIMPORT R0 17 [0xCBD666E1]
      57 [-]: LOADN R1 0   
      58 [-]: CALL R0 1 0  
      59 [-]: JUMPBACK L3  
L 4:  60 [-]: GETUPVAL R1 10
      61 [-]: GETTABLEKS R0 R1 K28 [0xBDD9801D]
      62 [-]: LOADB R1 1   
      63 [-]: CALL R0 1 0  
      64 [-]: GETUPVAL R1 0
      65 [-]: GETTABLEKS R0 R1 K29 [0x663D839C]
      66 [-]: LOADB R1 1   
      67 [-]: CALL R0 1 0  
      68 [-]: GETUPVAL R1 0
      69 [-]: GETTABLEKS R0 R1 K30 [0x4949D0BA]
      70 [-]: GETUPVAL R1 6
      71 [-]: CALL R0 1 0  
      72 [-]: GETUPVAL R1 4
      73 [-]: GETTABLEKS R0 R1 K31 [0xDC3B2033]
      74 [-]: CALL R0 0 0  
      75 [-]: GETUPVAL R1 9
      76 [-]: GETTABLEKS R0 R1 K32 [0xA2080540]
      77 [-]: GETUPVAL R1 8
      78 [-]: CALL R0 1 0  
      79 [-]: GETUPVAL R1 11
      80 [-]: GETTABLEKS R0 R1 K33 [0x659D451F]
      81 [-]: GETIMPORT R1 35 [0x29AF4E34]
      82 [-]: CALL R0 1 0  
      83 [-]: GETUPVAL R0 12
      84 [-]: GETUPVAL R3 13
      85 [-]: GETTABLEKS R2 R3 K36 ["REACH_ANGRY_STORY"]
      86 [-]: NAMECALL R0 R0 K37 [0x8ABFF40E]
      87 [-]: CALL R0 2 0  
      88 [-]: RETURN R0 0  


; Name:            
; Defined at line: 728
; #Upvalues:       4
; #Parameters:     0
; Is_vararg:       0
; Max Stack Size:  5

       0 [-]: GETUPVAL R0 0
       1 [-]: GETUPVAL R3 1
       2 [-]: GETTABLEKS R2 R3 K0 ["ANGRY_STORY"]
       3 [-]: NAMECALL R0 R0 K1 [0x8ABFF40E]
       4 [-]: CALL R0 2 0  
       5 [-]: GETUPVAL R1 2
       6 [-]: GETTABLEKS R0 R1 K2 [0x9742B85B]
       7 [-]: GETUPVAL R1 3
       8 [-]: GETIMPORT R2 4 [0x0469F296]
       9 [-]: LOADK R3 K5 ["DDuvParQAnger0960"]
      10 [-]: CALL R2 1 1  
      11 [-]: LOADB R3 0   
      12 [-]: LOADB R4 1   
      13 [-]: CALL R0 4 0  
      14 [-]: GETUPVAL R1 2
      15 [-]: GETTABLEKS R0 R1 K2 [0x9742B85B]
      16 [-]: GETUPVAL R1 3
      17 [-]: GETIMPORT R2 4 [0x0469F296]
      18 [-]: LOADK R3 K6 ["DDuvParQAnger0980"]
      19 [-]: CALL R2 1 1  
      20 [-]: LOADB R3 0   
      21 [-]: LOADB R4 1   
      22 [-]: CALL R0 4 0  
      23 [-]: GETIMPORT R0 8 [0xCBD666E1]
      24 [-]: LOADN R1 1   
      25 [-]: CALL R0 1 0  
      26 [-]: GETIMPORT R1 11 ["StartStoryEncounter"]
      27 [-]: FASTCALL1 62 R1 L0
      28 [-]: GETIMPORT R0 13 [0x7B998233]
      29 [-]: CALL R0 1 1  
L 0:  30 [-]: JUMPIF R0 L1 
      31 [-]: GETIMPORT R0 11 ["StartStoryEncounter"]
      32 [-]: CALL R0 0 0  
L 1:  33 [-]: RETURN R0 0  


; Name:            
; Defined at line: 760
; #Upvalues:       1
; #Parameters:     2
; Is_vararg:       0
; Max Stack Size:  10

       0 [-]: GETIMPORT R2 1 [0x3D106989]
       1 [-]: LOADK R4 K2 ["Job State Changed, old stage = "]
       2 [-]: GETIMPORT R8 4 [0x64FB1586]
       3 [-]: MOVE R9 R0   
       4 [-]: CALL R8 1 1  
       5 [-]: MOVE R5 R8   
       6 [-]: LOADK R6 K5 [", new stage = "]
       7 [-]: GETIMPORT R7 4 [0x64FB1586]
       8 [-]: MOVE R8 R1   
       9 [-]: CALL R7 1 1  
      10 [-]: CONCAT R3 R4 R7
      11 [-]: CALL R2 1 0  
      12 [-]: SUBK R2 R1 K6 [1]
      13 [-]: LOADN R3 1   
      14 [-]: JUMPIFNOTLE R3 R2 L0
      15 [-]: GETUPVAL R3 0
      16 [-]: JUMPIFNOTLE R2 R3 L0
      17 [-]: LOADK R4 K7 ["Encounter#"]
      18 [-]: GETIMPORT R5 4 [0x64FB1586]
      19 [-]: MOVE R6 R2   
      20 [-]: CALL R5 1 1  
      21 [-]: CONCAT R3 R4 R5
      22 [-]: GETIMPORT R4 1 [0x3D106989]
      23 [-]: LOADK R6 K8 ["Starting "]
      24 [-]: MOVE R7 R3   
      25 [-]: CONCAT R5 R6 R7
      26 [-]: CALL R4 1 0  
L 0:  27 [-]: SUBK R3 R0 K6 [1]
      28 [-]: LOADN R4 1   
      29 [-]: JUMPIFNOTLE R4 R3 L1
      30 [-]: GETUPVAL R4 0
      31 [-]: JUMPIFNOTLE R3 R4 L1
      32 [-]: LOADK R5 K7 ["Encounter#"]
      33 [-]: GETIMPORT R6 4 [0x64FB1586]
      34 [-]: MOVE R7 R3   
      35 [-]: CALL R6 1 1  
      36 [-]: CONCAT R4 R5 R6
      37 [-]: GETIMPORT R5 1 [0x3D106989]
      38 [-]: LOADK R7 K9 ["Ending "]
      39 [-]: MOVE R8 R4   
      40 [-]: CONCAT R6 R7 R8
      41 [-]: CALL R5 1 0  
L 1:  42 [-]: RETURN R0 0  


; Name:            
; Defined at line: 775
; #Upvalues:       3
; #Parameters:     0
; Is_vararg:       0
; Max Stack Size:  4

       0 [-]: GETUPVAL R0 0
       1 [-]: JUMPXEQKN R0 K0 L0 NOT [-1]
       2 [-]: GETIMPORT R2 5 ["stages"]
       3 [-]: LENGTH R1 R2 
       4 [-]: SUBK R0 R1 K1 [1]
       5 [-]: SETUPVAL R0 0
L 0:   6 [-]: GETIMPORT R0 7 [0xBE190284]
       7 [-]: GETIMPORT R2 9 [0x0469F296]
       8 [-]: LOADK R3 K10 ["JobStage"]
       9 [-]: CALL R2 1 1  
      10 [-]: LOADN R3 9999
      11 [-]: NAMECALL R0 R0 K11 [0x0EB34C69]
      12 [-]: CALL R0 3 1  
      13 [-]: GETUPVAL R1 1
      14 [-]: JUMPIFEQ R0 R1 L1
      15 [-]: GETUPVAL R1 2
      16 [-]: GETUPVAL R2 1
      17 [-]: MOVE R3 R0   
      18 [-]: CALL R1 2 0  
      19 [-]: SETUPVAL R0 1
L 1:  20 [-]: RETURN R0 0  


; Name:            
; Defined at line: 786
; #Upvalues:       7
; #Parameters:     0
; Is_vararg:       0
; Max Stack Size:  8

       0 [-]: GETUPVAL R0 0
       1 [-]: JUMPIF R0 L1 
       2 [-]: GETIMPORT R0 1 [0x89326C93]
       3 [-]: GETIMPORT R2 3 [0xBCAE77F6]
       4 [-]: NAMECALL R0 R0 K4 [0x46A0EBF5]
       5 [-]: CALL R0 2 1  
       6 [-]: NAMECALL R1 R0 K5 [0xD1586535]
       7 [-]: CALL R1 1 1  
       8 [-]: NAMECALL R2 R0 K6 [0xCB3851B8]
       9 [-]: CALL R2 1 1  
      10 [-]: GETUPVAL R3 0
      11 [-]: JUMPIFNOT R3 L0
      12 [-]: GETUPVAL R3 0
      13 [-]: NAMECALL R3 R3 K7 [0xA2880940]
      14 [-]: CALL R3 1 0  
L 0:  15 [-]: GETIMPORT R3 1 [0x89326C93]
      16 [-]: GETIMPORT R5 9 [0x78EB7099]
      17 [-]: MOVE R6 R1   
      18 [-]: MOVE R7 R2   
      19 [-]: NAMECALL R3 R3 K10 [0x05909209]
      20 [-]: CALL R3 4 1  
      21 [-]: SETUPVAL R3 0
      22 [-]: GETUPVAL R3 0
      23 [-]: GETIMPORT R5 12 [0x0469F296]
      24 [-]: LOADK R6 K13 ["StoryCheckpointWp"]
      25 [-]: CALL R5 1 -1 
      26 [-]: NAMECALL R3 R3 K14 [0x3273BA96]
      27 [-]: CALL R3 -1 0 
L 1:  28 [-]: GETIMPORT R1 17 ["ActiveJob"]
      29 [-]: FASTCALL1 62 R1 L2
      30 [-]: GETIMPORT R0 19 [0x7B998233]
      31 [-]: CALL R0 1 1  
L 2:  32 [-]: JUMPIF R0 L5 
      33 [-]: GETUPVAL R0 1
      34 [-]: JUMPXEQKN R0 K20 L3 NOT [-1]
      35 [-]: GETIMPORT R2 23 ["stages"]
      36 [-]: LENGTH R1 R2 
      37 [-]: SUBK R0 R1 K21 [1]
      38 [-]: SETUPVAL R0 1
L 3:  39 [-]: GETIMPORT R0 25 [0xBE190284]
      40 [-]: GETIMPORT R2 12 [0x0469F296]
      41 [-]: LOADK R3 K26 ["JobStage"]
      42 [-]: CALL R2 1 1  
      43 [-]: LOADN R3 9999
      44 [-]: NAMECALL R0 R0 K27 [0x0EB34C69]
      45 [-]: CALL R0 3 1  
      46 [-]: GETUPVAL R1 2
      47 [-]: JUMPIFEQ R0 R1 L4
      48 [-]: GETUPVAL R1 3
      49 [-]: GETUPVAL R2 2
      50 [-]: MOVE R3 R0   
      51 [-]: CALL R1 2 0  
      52 [-]: SETUPVAL R0 2
L 4:  53 [-]: GETIMPORT R0 29 [0xCBD666E1]
      54 [-]: LOADN R1 0   
      55 [-]: CALL R0 1 0  
      56 [-]: JUMPBACK L1  
L 5:  57 [-]: GETUPVAL R1 4
      58 [-]: GETTABLEKS R0 R1 K30 [0xFEA395B0]
      59 [-]: CALL R0 0 0  
      60 [-]: GETUPVAL R1 4
      61 [-]: GETTABLEKS R0 R1 K31 [0x914FF6EB]
      62 [-]: CALL R0 0 0  
      63 [-]: GETUPVAL R1 4
      64 [-]: GETTABLEKS R0 R1 K32 [0x032483A6]
      65 [-]: CALL R0 0 0  
      66 [-]: GETIMPORT R0 1 [0x89326C93]
      67 [-]: GETIMPORT R2 12 [0x0469F296]
      68 [-]: LOADK R3 K33 ["AngryDragonLoop"]
      69 [-]: CALL R2 1 -1 
      70 [-]: NAMECALL R0 R0 K4 [0x46A0EBF5]
      71 [-]: CALL R0 -1 1 
      72 [-]: JUMPIFNOT R0 L6
      73 [-]: LOADK R3 K34 ["TriggerPort"]
      74 [-]: NAMECALL R1 R0 K35 [0x8EB2112D]
      75 [-]: CALL R1 2 0  
L 6:  76 [-]: GETIMPORT R1 36 ["_T"]
      77 [-]: LOADB R2 1   
      78 [-]: SETTABLEKS R2 R1 K37 ["DragonActive"]
      79 [-]: GETUPVAL R1 5
      80 [-]: GETUPVAL R4 6
      81 [-]: GETTABLEKS R3 R4 K38 ["COLLECT_FIGURINE_PART"]
      82 [-]: NAMECALL R1 R1 K39 [0x8ABFF40E]
      83 [-]: CALL R1 2 0  
      84 [-]: RETURN R0 0  


; Name:            
; Defined at line: 814
; #Upvalues:       0
; #Parameters:     1
; Is_vararg:       0
; Max Stack Size:  3

       0 [-]: NAMECALL R1 R0 K0 [0xA2880940]
       1 [-]: CALL R1 1 0  
       2 [-]: RETURN R0 0  


; Name:            
; Defined at line: 818
; #Upvalues:       10
; #Parameters:     0
; Is_vararg:       0
; Max Stack Size:  7

       0 [-]: GETUPVAL R1 0
       1 [-]: FASTCALL1 62 R1 L0
       2 [-]: GETIMPORT R0 1 [0x7B998233]
       3 [-]: CALL R0 1 1  
L 0:   4 [-]: JUMPIFNOT R0 L1
       5 [-]: GETUPVAL R1 1
       6 [-]: GETTABLEKS R0 R1 K2 [0x9742B85B]
       7 [-]: GETUPVAL R1 2
       8 [-]: GETIMPORT R2 4 [0x0469F296]
       9 [-]: LOADK R3 K5 ["DDuvParQAnger0990"]
      10 [-]: CALL R2 1 1  
      11 [-]: LOADB R3 0   
      12 [-]: LOADB R4 1   
      13 [-]: CALL R0 4 0  
      14 [-]: GETIMPORT R0 7 [0xCBD666E1]
      15 [-]: LOADN R1 1   
      16 [-]: CALL R0 1 0  
      17 [-]: GETUPVAL R1 3
      18 [-]: GETTABLEKS R0 R1 K8 [0xA1DF01D6]
      19 [-]: GETUPVAL R2 4
      20 [-]: GETTABLEKS R1 R2 K9 ["COLLECT_FIGURINE_OBJ"]
      21 [-]: CALL R0 1 0  
      22 [-]: GETIMPORT R0 11 [0xA421AF95]
      23 [-]: LOADK R1 K12 [-32.832000000000001]
      24 [-]: LOADK R2 K13 [651.5]
      25 [-]: LOADK R3 K14 [-72.361000000000004]
      26 [-]: CALL R0 3 1  
      27 [-]: GETUPVAL R2 6
      28 [-]: GETTABLEKS R1 R2 K15 [0x3C599C25]
      29 [-]: GETUPVAL R2 7
      30 [-]: LOADNIL R3   
      31 [-]: LOADNIL R4   
      32 [-]: MOVE R5 R0   
      33 [-]: LOADNIL R6   
      34 [-]: CALL R1 5 1  
      35 [-]: SETUPVAL R1 5
      36 [-]: GETUPVAL R1 5
      37 [-]: GETUPVAL R2 6
      38 [-]: GETTABLEKS R1 R2 K16 [0x4229860B]
      39 [-]: LOADNIL R2   
      40 [-]: MOVE R3 R0   
      41 [-]: GETIMPORT R4 18 [0xEA42AB6F]
      42 [-]: CALL R1 3 1  
      43 [-]: SETUPVAL R1 0
L 1:  44 [-]: GETUPVAL R1 0
      45 [-]: FASTCALL1 62 R1 L2
      46 [-]: GETIMPORT R0 1 [0x7B998233]
      47 [-]: CALL R0 1 1  
L 2:  48 [-]: JUMPIF R0 L6 
L 3:  49 [-]: GETUPVAL R2 0
      50 [-]: GETTABLEKS R1 R2 K19 ["trig"]
      51 [-]: FASTCALL1 62 R1 L4
      52 [-]: GETIMPORT R0 1 [0x7B998233]
      53 [-]: CALL R0 1 1  
L 4:  54 [-]: JUMPIF R0 L5 
      55 [-]: GETIMPORT R0 7 [0xCBD666E1]
      56 [-]: LOADN R1 0   
      57 [-]: CALL R0 1 0  
      58 [-]: JUMPBACK L3  
L 5:  59 [-]: GETUPVAL R1 6
      60 [-]: GETTABLEKS R0 R1 K20 [0xB6EB8014]
      61 [-]: GETUPVAL R1 0
      62 [-]: CALL R0 1 0  
      63 [-]: GETUPVAL R1 6
      64 [-]: GETTABLEKS R0 R1 K21 [0x4949D0BA]
      65 [-]: GETUPVAL R1 5
      66 [-]: CALL R0 1 0  
      67 [-]: GETUPVAL R1 3
      68 [-]: GETTABLEKS R0 R1 K22 [0xDC3B2033]
      69 [-]: CALL R0 0 0  
      70 [-]: GETUPVAL R1 1
      71 [-]: GETTABLEKS R0 R1 K2 [0x9742B85B]
      72 [-]: GETUPVAL R1 2
      73 [-]: GETIMPORT R2 4 [0x0469F296]
      74 [-]: LOADK R3 K23 ["DDuvParQAnger1000"]
      75 [-]: CALL R2 1 1  
      76 [-]: LOADB R3 0   
      77 [-]: LOADB R4 0   
      78 [-]: CALL R0 4 0  
      79 [-]: GETIMPORT R0 11 [0xA421AF95]
      80 [-]: LOADK R1 K24 [-0.029999999999999999]
      81 [-]: LOADK R2 K25 [0.089999999999999997]
      82 [-]: LOADK R3 K26 [-0.01]
      83 [-]: CALL R0 3 1  
      84 [-]: GETIMPORT R1 28 [0x00046924]
      85 [-]: LOADN R2 90  
      86 [-]: LOADN R3 5   
      87 [-]: LOADN R4 -5  
      88 [-]: CALL R1 3 1  
      89 [-]: GETUPVAL R3 6
      90 [-]: GETTABLEKS R2 R3 K29 [0x45C27941]
      91 [-]: GETIMPORT R3 18 [0xEA42AB6F]
      92 [-]: MOVE R4 R0   
      93 [-]: MOVE R5 R1   
      94 [-]: CALL R2 3 0  
      95 [-]: LOADNIL R2   
      96 [-]: SETUPVAL R2 0
L 6:  97 [-]: GETUPVAL R1 1
      98 [-]: GETTABLEKS R0 R1 K30 [0xED8F83F8]
      99 [-]: CALL R0 0 1  
     100 [-]: JUMPIFNOT R0 L7
     101 [-]: GETIMPORT R0 7 [0xCBD666E1]
     102 [-]: LOADN R1 0   
     103 [-]: CALL R0 1 0  
     104 [-]: JUMPBACK L6  
L 7: 105 [-]: GETUPVAL R0 8
     106 [-]: GETUPVAL R3 9
     107 [-]: GETTABLEKS R2 R3 K31 ["RETURN_TO_CAVE"]
     108 [-]: NAMECALL R0 R0 K32 [0x8ABFF40E]
     109 [-]: CALL R0 2 0  
     110 [-]: RETURN R0 0  


; Name:            
; Defined at line: 871
; #Upvalues:       12
; #Parameters:     0
; Is_vararg:       0
; Max Stack Size:  8

       0 [-]: GETUPVAL R1 0
       1 [-]: GETTABLEKS R0 R1 K0 [0xA1DF01D6]
       2 [-]: GETUPVAL R2 1
       3 [-]: GETTABLEKS R1 R2 K1 ["RETURN_TO_CAVE_OBJ"]
       4 [-]: CALL R0 1 0  
       5 [-]: GETUPVAL R0 2
       6 [-]: JUMPIF R0 L0 
       7 [-]: GETUPVAL R1 3
       8 [-]: GETTABLEKS R0 R1 K2 [0x725AD21C]
       9 [-]: LOADK R1 K3 ["ending"]
      10 [-]: GETIMPORT R2 5 [0x910E4893]
      11 [-]: CALL R0 2 1  
      12 [-]: GETIMPORT R1 7 [0x89326C93]
      13 [-]: MOVE R3 R0   
      14 [-]: NAMECALL R1 R1 K8 [0x46A0EBF5]
      15 [-]: CALL R1 2 1  
      16 [-]: GETUPVAL R3 3
      17 [-]: GETTABLEKS R2 R3 K9 [0x3C599C25]
      18 [-]: GETUPVAL R3 5
      19 [-]: MOVE R4 R1   
      20 [-]: LOADNIL R5   
      21 [-]: LOADNIL R6   
      22 [-]: LOADNIL R7   
      23 [-]: CALL R2 5 1  
      24 [-]: SETUPVAL R2 4
      25 [-]: GETUPVAL R2 4
      26 [-]: GETUPVAL R3 3
      27 [-]: GETTABLEKS R2 R3 K10 [0xE298E362]
      28 [-]: MOVE R3 R1   
      29 [-]: CALL R2 1 1  
      30 [-]: SETUPVAL R2 6
      31 [-]: LOADB R2 1   
      32 [-]: SETUPVAL R2 2
L 0:  33 [-]: GETUPVAL R1 3
      34 [-]: GETTABLEKS R0 R1 K11 [0xFFEA66F0]
      35 [-]: CALL R0 0 1  
L 1:  36 [-]: JUMPIF R0 L2 
      37 [-]: GETUPVAL R2 3
      38 [-]: GETTABLEKS R1 R2 K11 [0xFFEA66F0]
      39 [-]: CALL R1 0 1  
      40 [-]: MOVE R0 R1   
      41 [-]: GETIMPORT R1 13 [0xCBD666E1]
      42 [-]: LOADN R2 0   
      43 [-]: CALL R1 1 0  
      44 [-]: JUMPBACK L1  
L 2:  45 [-]: FASTCALL1 62 R0 L3
      46 [-]: MOVE R2 R0   
      47 [-]: GETIMPORT R1 15 [0x7B998233]
      48 [-]: CALL R1 1 1  
L 3:  49 [-]: JUMPIFNOT R1 L4
      50 [-]: RETURN R0 0  
L 4:  51 [-]: GETUPVAL R2 3
      52 [-]: GETTABLEKS R1 R2 K16 [0x3C1B3308]
      53 [-]: CALL R1 0 0  
      54 [-]: GETUPVAL R2 3
      55 [-]: GETTABLEKS R1 R2 K17 [0x69DDAB85]
      56 [-]: LOADB R2 1   
      57 [-]: CALL R1 1 0  
      58 [-]: GETUPVAL R2 3
      59 [-]: GETTABLEKS R1 R2 K18 [0x663D839C]
      60 [-]: LOADB R2 0   
      61 [-]: CALL R1 1 0  
      62 [-]: GETUPVAL R2 7
      63 [-]: GETTABLEKS R1 R2 K19 [0xBDD9801D]
      64 [-]: LOADB R2 0   
      65 [-]: CALL R1 1 0  
      66 [-]: GETUPVAL R1 8
      67 [-]: LOADB R3 0   
      68 [-]: LOADB R4 1   
      69 [-]: NAMECALL R1 R1 K20 [0x768274D6]
      70 [-]: CALL R1 3 0  
      71 [-]: GETIMPORT R1 7 [0x89326C93]
      72 [-]: GETIMPORT R3 22 [0x0469F296]
      73 [-]: LOADK R4 K23 ["TeshinFireRabbitSFX"]
      74 [-]: CALL R3 1 -1 
      75 [-]: NAMECALL R1 R1 K8 [0x46A0EBF5]
      76 [-]: CALL R1 -1 1 
      77 [-]: JUMPIFNOT R1 L5
      78 [-]: NAMECALL R2 R1 K24 [0xF4E253B6]
      79 [-]: CALL R2 1 0  
L 5:  80 [-]: GETIMPORT R2 7 [0x89326C93]
      81 [-]: GETIMPORT R4 22 [0x0469F296]
      82 [-]: LOADK R5 K25 ["ShowDollTeshin"]
      83 [-]: CALL R4 1 -1 
      84 [-]: NAMECALL R2 R2 K8 [0x46A0EBF5]
      85 [-]: CALL R2 -1 1 
      86 [-]: JUMPIFNOT R2 L6
      87 [-]: LOADK R5 K26 ["TriggerPort"]
      88 [-]: NAMECALL R3 R2 K27 [0x8EB2112D]
      89 [-]: CALL R3 2 0  
L 6:  90 [-]: GETIMPORT R3 7 [0x89326C93]
      91 [-]: GETIMPORT R5 22 [0x0469F296]
      92 [-]: LOADK R6 K28 ["AngryDragonEnd"]
      93 [-]: CALL R5 1 -1 
      94 [-]: NAMECALL R3 R3 K8 [0x46A0EBF5]
      95 [-]: CALL R3 -1 1 
      96 [-]: JUMPIFNOT R3 L7
      97 [-]: LOADK R6 K26 ["TriggerPort"]
      98 [-]: NAMECALL R4 R3 K27 [0x8EB2112D]
      99 [-]: CALL R4 2 0  
L 7: 100 [-]: GETIMPORT R4 30 ["_T"]
     101 [-]: LOADNIL R5   
     102 [-]: SETTABLEKS R5 R4 K31 ["DragonActive"]
     103 [-]: GETUPVAL R5 9
     104 [-]: GETTABLEKS R4 R5 K32 [0xA2080540]
     105 [-]: GETUPVAL R5 6
     106 [-]: CALL R4 1 0  
     107 [-]: GETUPVAL R5 3
     108 [-]: GETTABLEKS R4 R5 K33 [0x4949D0BA]
     109 [-]: GETUPVAL R5 4
     110 [-]: CALL R4 1 0  
     111 [-]: GETUPVAL R5 0
     112 [-]: GETTABLEKS R4 R5 K34 [0xDC3B2033]
     113 [-]: CALL R4 0 0  
     114 [-]: GETIMPORT R4 13 [0xCBD666E1]
     115 [-]: LOADN R5 1   
     116 [-]: CALL R4 1 0  
     117 [-]: GETUPVAL R5 3
     118 [-]: GETTABLEKS R4 R5 K35 [0xE453D7FE]
     119 [-]: CALL R4 0 0  
     120 [-]: GETUPVAL R4 10
     121 [-]: GETUPVAL R7 11
     122 [-]: GETTABLEKS R6 R7 K36 ["REASSEMBLE_FIGURE"]
     123 [-]: NAMECALL R4 R4 K37 [0x8ABFF40E]
     124 [-]: CALL R4 2 0  
     125 [-]: RETURN R0 0  


; Name:            
; Defined at line: 931
; #Upvalues:       6
; #Parameters:     0
; Is_vararg:       0
; Max Stack Size:  4

       0 [-]: GETUPVAL R1 1
       1 [-]: GETTABLEKS R0 R1 K0 [0xBF2BF492]
       2 [-]: GETUPVAL R2 2
       3 [-]: GETTABLEKS R1 R2 K1 ["ASSEMBLE_FIGURINE_OBJ"]
       4 [-]: GETUPVAL R2 3
       5 [-]: GETIMPORT R3 3 [0x0187F259]
       6 [-]: CALL R0 3 1  
       7 [-]: SETUPVAL R0 0
       8 [-]: GETUPVAL R0 4
       9 [-]: GETUPVAL R3 5
      10 [-]: GETTABLEKS R2 R3 K4 ["DIORAMA"]
      11 [-]: NAMECALL R0 R0 K5 [0x8ABFF40E]
      12 [-]: CALL R0 2 0  
      13 [-]: RETURN R0 0  


; Name:            
; Defined at line: 936
; #Upvalues:       4
; #Parameters:     0
; Is_vararg:       0
; Max Stack Size:  4

       0 [-]: GETUPVAL R1 0
       1 [-]: GETTABLEKS R0 R1 K0 [0xC2019EF5]
       2 [-]: GETIMPORT R1 2 [0xF27B46D8]
       3 [-]: LOADNIL R2   
       4 [-]: LOADB R3 1   
       5 [-]: CALL R0 3 0  
       6 [-]: GETUPVAL R0 1
       7 [-]: JUMPIFNOT R0 L0
       8 [-]: GETUPVAL R0 1
       9 [-]: NAMECALL R0 R0 K3 [0x6CF1E476]
      10 [-]: CALL R0 1 0  
L 0:  11 [-]: GETUPVAL R0 2
      12 [-]: GETUPVAL R3 3
      13 [-]: GETTABLEKS R2 R3 K4 ["CUTSCENE"]
      14 [-]: NAMECALL R0 R0 K5 [0x8ABFF40E]
      15 [-]: CALL R0 2 0  
      16 [-]: RETURN R0 0  


; Name:            
; Defined at line: 944
; #Upvalues:       3
; #Parameters:     0
; Is_vararg:       0
; Max Stack Size:  5

       0 [-]: GETUPVAL R0 0
       1 [-]: LOADB R2 1   
       2 [-]: LOADB R3 1   
       3 [-]: NAMECALL R0 R0 K0 [0x768274D6]
       4 [-]: CALL R0 3 0  
       5 [-]: GETIMPORT R0 2 [0x89326C93]
       6 [-]: GETIMPORT R2 4 [0x0469F296]
       7 [-]: LOADK R3 K5 ["HideDollTeshin"]
       8 [-]: CALL R2 1 -1 
       9 [-]: NAMECALL R0 R0 K6 [0x46A0EBF5]
      10 [-]: CALL R0 -1 1 
      11 [-]: JUMPIFNOT R0 L0
      12 [-]: LOADK R3 K7 ["TriggerPort"]
      13 [-]: NAMECALL R1 R0 K8 [0x8EB2112D]
      14 [-]: CALL R1 2 0  
L 0:  15 [-]: GETIMPORT R1 2 [0x89326C93]
      16 [-]: GETIMPORT R3 4 [0x0469F296]
      17 [-]: LOADK R4 K9 ["TeshinsStaffFire"]
      18 [-]: CALL R3 1 -1 
      19 [-]: NAMECALL R1 R1 K6 [0x46A0EBF5]
      20 [-]: CALL R1 -1 1 
      21 [-]: FASTCALL1 62 R1 L1
      22 [-]: MOVE R3 R1   
      23 [-]: GETIMPORT R2 11 [0x7B998233]
      24 [-]: CALL R2 1 1  
L 1:  25 [-]: JUMPIF R2 L2 
      26 [-]: LOADK R4 K7 ["TriggerPort"]
      27 [-]: NAMECALL R2 R1 K8 [0x8EB2112D]
      28 [-]: CALL R2 2 0  
L 2:  29 [-]: GETUPVAL R3 1
      30 [-]: GETTABLEKS R2 R3 K12 [0xD92F6872]
      31 [-]: GETUPVAL R3 2
      32 [-]: GETIMPORT R4 14 [0xEF992D0C]
      33 [-]: CALL R2 2 0  
      34 [-]: RETURN R0 0  


; Name:            
; Defined at line: 960
; #Upvalues:       3
; #Parameters:     0
; Is_vararg:       0
; Max Stack Size:  4

       0 [-]: GETUPVAL R0 0
       1 [-]: CALL R0 0 0  
       2 [-]: GETUPVAL R0 1
       3 [-]: GETUPVAL R3 2
       4 [-]: GETTABLEKS R2 R3 K0 ["CONVERSATION"]
       5 [-]: NAMECALL R0 R0 K1 [0x8ABFF40E]
       6 [-]: CALL R0 2 0  
       7 [-]: RETURN R0 0  


; Name:            
; Defined at line: 965
; #Upvalues:       2
; #Parameters:     0
; Is_vararg:       0
; Max Stack Size:  6

       0 [-]: GETUPVAL R1 0
       1 [-]: GETTABLEKS R0 R1 K0 [0x958E23C4]
       2 [-]: CALL R0 0 1  
       3 [-]: JUMPIFNOT R0 L2
       4 [-]: LOADN R0 -1  
       5 [-]: DUPTABLE R1 2
       6 [-]: LOADN R2 1   
       7 [-]: SETTABLEKS R2 R1 K1 ["CompleteLevel"]
       8 [-]: NEWCLOSURE R2 P0
       9 [-]: MOVE R1 R0   
      10 [-]: GETUPVAL R4 1
      11 [-]: GETTABLEKS R3 R4 K3 [0x01566DB3]
      12 [-]: MOVE R4 R1   
      13 [-]: MOVE R5 R2   
      14 [-]: CALL R3 2 0  
L 0:  15 [-]: JUMPXEQKN R0 K4 L1 NOT [-1]
      16 [-]: GETIMPORT R3 6 [0xCBD666E1]
      17 [-]: LOADN R4 0   
      18 [-]: CALL R3 1 0  
      19 [-]: JUMPBACK L0  
L 1:  20 [-]: CLOSEUPVALS R0
L 2:  21 [-]: RETURN R0 0  


; Name:            
; Defined at line: 982
; #Upvalues:       11
; #Parameters:     0
; Is_vararg:       0
; Max Stack Size:  10

       0 [-]: GETUPVAL R0 0
       1 [-]: LOADK R2 K0 ["Enable"]
       2 [-]: NAMECALL R0 R0 K1 [0x8EB2112D]
       3 [-]: CALL R0 2 0  
       4 [-]: GETUPVAL R1 1
       5 [-]: GETTABLEKS R0 R1 K2 [0x8EB2CA40]
       6 [-]: LOADB R1 1   
       7 [-]: CALL R0 1 0  
       8 [-]: GETUPVAL R1 1
       9 [-]: GETTABLEKS R0 R1 K3 [0xF009BF4B]
      10 [-]: LOADN R1 2   
      11 [-]: CALL R0 1 0  
      12 [-]: LOADB R0 1   
      13 [-]: GETIMPORT R1 5 ["_T"]
      14 [-]: GETIMPORT R2 7 ["TaggedDialog"]
      15 [-]: JUMPIF R2 L0 
      16 [-]: NEWTABLE R2 0 0
L 0:  17 [-]: SETTABLEKS R2 R1 K6 ["TaggedDialog"]
      18 [-]: GETIMPORT R1 7 ["TaggedDialog"]
      19 [-]: DUPTABLE R2 10
      20 [-]: LOADK R3 K11 [""]
      21 [-]: SETTABLEKS R3 R2 K8 ["mName"]
      22 [-]: NEWCLOSURE R3 P0
      23 [-]: MOVE R2 R2   
      24 [-]: MOVE R2 R3   
      25 [-]: MOVE R2 R1   
      26 [-]: MOVE R2 R4   
      27 [-]: MOVE R2 R5   
      28 [-]: MOVE R2 R6   
      29 [-]: MOVE R2 R7   
      30 [-]: MOVE R1 R0   
      31 [-]: SETTABLEKS R3 R2 K9 ["mCallback"]
      32 [-]: SETTABLEKS R2 R1 K12 ["Angry_FinalDialog"]
      33 [-]: GETIMPORT R1 14 [0x89326C93]
      34 [-]: GETIMPORT R3 16 [0x0469F296]
      35 [-]: LOADK R4 K17 ["PostCineTeshinInteractTrigger"]
      36 [-]: CALL R3 1 -1 
      37 [-]: NAMECALL R1 R1 K18 [0x46A0EBF5]
      38 [-]: CALL R1 -1 1 
      39 [-]: NAMECALL R2 R1 K19 [0x383D2E7D]
      40 [-]: CALL R2 1 0  
      41 [-]: GETUPVAL R3 1
      42 [-]: GETTABLEKS R2 R3 K20 [0x7C676590]
      43 [-]: GETUPVAL R3 8
      44 [-]: MOVE R4 R1   
      45 [-]: LOADNIL R5   
      46 [-]: LOADNIL R6   
      47 [-]: GETIMPORT R7 22 [0xB7CBD06B]
      48 [-]: LOADN R8 2   
      49 [-]: LOADN R9 100 
      50 [-]: CALL R7 2 -1 
      51 [-]: CALL R2 -1 1 
      52 [-]: SETUPVAL R2 4
      53 [-]: GETUPVAL R2 4
L 1:  54 [-]: JUMPIFNOT R0 L2
      55 [-]: GETIMPORT R2 24 [0xCBD666E1]
      56 [-]: LOADN R3 0   
      57 [-]: CALL R2 1 0  
      58 [-]: JUMPBACK L1  
L 2:  59 [-]: NAMECALL R2 R1 K25 [0xF4E253B6]
      60 [-]: CALL R2 1 0  
      61 [-]: GETUPVAL R3 1
      62 [-]: GETTABLEKS R2 R3 K2 [0x8EB2CA40]
      63 [-]: LOADB R3 1   
      64 [-]: CALL R2 1 0  
      65 [-]: GETUPVAL R2 9
      66 [-]: GETUPVAL R5 10
      67 [-]: GETTABLEKS R4 R5 K26 ["REST_BY_FIRE"]
      68 [-]: NAMECALL R2 R2 K27 [0x8ABFF40E]
      69 [-]: CALL R2 2 0  
      70 [-]: CLOSEUPVALS R0
      71 [-]: RETURN R0 0  


; Name:            
; Defined at line: 1088
; #Upvalues:       14
; #Parameters:     0
; Is_vararg:       0
; Max Stack Size:  17

       0 [-]: LOADB R0 0   
       1 [-]: SETUPVAL R0 0
       2 [-]: GETUPVAL R1 1
       3 [-]: GETTABLEKS R0 R1 K0 [0xA1DF01D6]
       4 [-]: GETUPVAL R2 2
       5 [-]: GETTABLEKS R1 R2 K1 ["REST_BY_FIRE_OBJ"]
       6 [-]: CALL R0 1 0  
       7 [-]: GETIMPORT R0 3 [0x89326C93]
       8 [-]: GETIMPORT R2 5 [0x0469F296]
       9 [-]: LOADK R3 K6 ["SitByFireAction"]
      10 [-]: CALL R2 1 -1 
      11 [-]: NAMECALL R0 R0 K7 [0x46A0EBF5]
      12 [-]: CALL R0 -1 1 
      13 [-]: NAMECALL R1 R0 K8 [0x383D2E7D]
      14 [-]: CALL R1 1 0  
      15 [-]: GETIMPORT R1 10 [0x11A19C5E]
      16 [-]: MOVE R2 R0   
      17 [-]: LOADK R3 K11 ["OnActivated"]
      18 [-]: CALL R1 2 0  
      19 [-]: GETIMPORT R1 3 [0x89326C93]
      20 [-]: GETIMPORT R3 5 [0x0469F296]
      21 [-]: LOADK R4 K12 ["RestFirePit"]
      22 [-]: CALL R3 1 -1 
      23 [-]: NAMECALL R1 R1 K7 [0x46A0EBF5]
      24 [-]: CALL R1 -1 1 
      25 [-]: FASTCALL1 62 R1 L0
      26 [-]: MOVE R3 R1   
      27 [-]: GETIMPORT R2 14 [0x7B998233]
      28 [-]: CALL R2 1 1  
L 0:  29 [-]: JUMPIFNOT R2 L1
      30 [-]: MOVE R1 R0   
L 1:  31 [-]: MOVE R2 R1   
      32 [-]: GETUPVAL R4 4
      33 [-]: GETTABLEKS R3 R4 K15 [0x7C676590]
      34 [-]: GETUPVAL R4 5
      35 [-]: MOVE R5 R2   
      36 [-]: LOADNIL R6   
      37 [-]: LOADNIL R7   
      38 [-]: GETIMPORT R8 17 [0xB7CBD06B]
      39 [-]: LOADN R9 2   
      40 [-]: LOADN R10 100
      41 [-]: CALL R8 2 -1 
      42 [-]: CALL R3 -1 1 
      43 [-]: SETUPVAL R3 3
      44 [-]: GETUPVAL R3 3
L 2:  45 [-]: GETUPVAL R2 0
      46 [-]: JUMPIF R2 L3 
      47 [-]: GETIMPORT R2 19 [0xCBD666E1]
      48 [-]: LOADN R3 0   
      49 [-]: CALL R2 1 0  
      50 [-]: JUMPBACK L2  
L 3:  51 [-]: GETUPVAL R3 1
      52 [-]: GETTABLEKS R2 R3 K20 [0xDC3B2033]
      53 [-]: CALL R2 0 0  
      54 [-]: GETUPVAL R3 4
      55 [-]: GETTABLEKS R2 R3 K21 [0x4949D0BA]
      56 [-]: GETUPVAL R3 3
      57 [-]: CALL R2 1 0  
      58 [-]: GETUPVAL R3 4
      59 [-]: GETTABLEKS R2 R3 K22 [0x8EB2CA40]
      60 [-]: LOADB R3 0   
      61 [-]: CALL R2 1 0  
      62 [-]: GETUPVAL R3 4
      63 [-]: GETTABLEKS R2 R3 K23 [0x217A3A95]
      64 [-]: LOADB R3 0   
      65 [-]: CALL R2 1 0  
      66 [-]: LOADN R2 0   
      67 [-]: GETUPVAL R3 6
      68 [-]: NAMECALL R3 R3 K24 [0xF6EBD926]
      69 [-]: CALL R3 1 1  
      70 [-]: GETUPVAL R4 6
      71 [-]: NAMECALL R4 R4 K25 [0x5280B883]
      72 [-]: CALL R4 1 1  
      73 [-]: GETIMPORT R5 3 [0x89326C93]
      74 [-]: GETIMPORT R7 5 [0x0469F296]
      75 [-]: LOADK R8 K26 ["SitByFireWP"]
      76 [-]: CALL R7 1 -1 
      77 [-]: NAMECALL R5 R5 K7 [0x46A0EBF5]
      78 [-]: CALL R5 -1 1 
      79 [-]: NAMECALL R6 R5 K27 [0xD1586535]
      80 [-]: CALL R6 1 1  
      81 [-]: NAMECALL R7 R5 K28 [0xCB3851B8]
      82 [-]: CALL R7 1 1  
      83 [-]: GETUPVAL R8 6
      84 [-]: GETUPVAL R10 7
      85 [-]: LOADB R11 0  
      86 [-]: LOADN R12 3  
      87 [-]: LOADN R13 1  
      88 [-]: NAMECALL R8 R8 K29 [0x5D985C7E]
      89 [-]: CALL R8 5 1  
      90 [-]: GETIMPORT R9 3 [0x89326C93]
      91 [-]: GETIMPORT R11 5 [0x0469F296]
      92 [-]: LOADK R12 K30 ["SitByFireCamera"]
      93 [-]: CALL R11 1 -1
      94 [-]: NAMECALL R9 R9 K7 [0x46A0EBF5]
      95 [-]: CALL R9 -1 1 
      96 [-]: LOADK R12 K31 ["Activate"]
      97 [-]: NAMECALL R10 R9 K32 [0x8EB2112D]
      98 [-]: CALL R10 2 0 
L 4:  99 [-]: JUMPIFNOTLT R2 R8 L6
     100 [-]: GETIMPORT R10 34 [0x67652851]
     101 [-]: CALL R10 0 1 
     102 [-]: ADD R2 R2 R10
     103 [-]: DIV R11 R2 R8
     104 [-]: FASTCALL2K 19 R11 K35 L5 [1]
     105 [-]: LOADK R12 K35 [1]
     106 [-]: GETIMPORT R10 38 [0xAC1B386A]
     107 [-]: CALL R10 2 1 
L 5: 108 [-]: GETIMPORT R11 40 [0x5DB3CE80]
     109 [-]: MOVE R12 R3  
     110 [-]: MOVE R13 R6  
     111 [-]: MOVE R14 R10 
     112 [-]: CALL R11 3 1 
     113 [-]: GETIMPORT R12 42 [0x5E223E7D]
     114 [-]: MOVE R13 R4  
     115 [-]: MOVE R14 R7  
     116 [-]: MOVE R15 R10 
     117 [-]: CALL R12 3 1 
     118 [-]: GETUPVAL R13 6
     119 [-]: MOVE R15 R11 
     120 [-]: MOVE R16 R12 
     121 [-]: NAMECALL R13 R13 K43 [0x589EF1C1]
     122 [-]: CALL R13 3 0 
     123 [-]: GETIMPORT R13 19 [0xCBD666E1]
     124 [-]: LOADN R14 0  
     125 [-]: CALL R13 1 0 
     126 [-]: JUMPBACK L4  
L 6: 127 [-]: GETUPVAL R10 6
     128 [-]: GETUPVAL R12 8
     129 [-]: LOADB R13 0  
     130 [-]: LOADN R14 3  
     131 [-]: LOADN R15 2  
     132 [-]: NAMECALL R10 R10 K29 [0x5D985C7E]
     133 [-]: CALL R10 5 0 
     134 [-]: GETIMPORT R10 19 [0xCBD666E1]
     135 [-]: LOADN R11 2  
     136 [-]: CALL R10 1 0 
     137 [-]: GETUPVAL R11 9
     138 [-]: GETTABLEKS R10 R11 K44 [0x12A41A40]
     139 [-]: LOADB R11 1  
     140 [-]: LOADN R12 1  
     141 [-]: CALL R10 2 0 
     142 [-]: GETUPVAL R10 10
     143 [-]: LOADB R12 0  
     144 [-]: LOADB R13 1  
     145 [-]: NAMECALL R10 R10 K45 [0x768274D6]
     146 [-]: CALL R10 3 0 
     147 [-]: GETUPVAL R10 11
     148 [-]: LOADK R12 K46 ["Disable"]
     149 [-]: NAMECALL R10 R10 K32 [0x8EB2112D]
     150 [-]: CALL R10 2 0 
     151 [-]: GETIMPORT R10 19 [0xCBD666E1]
     152 [-]: LOADN R11 0  
     153 [-]: CALL R10 1 0 
     154 [-]: GETUPVAL R10 12
     155 [-]: GETUPVAL R13 13
     156 [-]: GETTABLEKS R12 R13 K47 ["COMPLETE"]
     157 [-]: NAMECALL R10 R10 K48 [0x8ABFF40E]
     158 [-]: CALL R10 2 0 
     159 [-]: RETURN R0 0  


; Name:            
; Defined at line: 1150
; #Upvalues:       2
; #Parameters:     0
; Is_vararg:       0
; Max Stack Size:  2

       0 [-]: LOADB R0 1   
       1 [-]: SETUPVAL R0 0
       2 [-]: GETUPVAL R1 1
       3 [-]: GETTABLEKS R0 R1 K0 [0x1CD67745]
       4 [-]: CALL R0 0 0  
       5 [-]: LOADB R0 0   
       6 [-]: SETUPVAL R0 0
       7 [-]: RETURN R0 0  


; Name:            
; Defined at line: 1157
; #Upvalues:       11
; #Parameters:     1
; Is_vararg:       0
; Max Stack Size:  8

       0 [-]: GETIMPORT R2 1 [0xCB79539E]
       1 [-]: FASTCALL1 62 R2 L0
       2 [-]: GETIMPORT R1 3 [0x7B998233]
       3 [-]: CALL R1 1 1  
L 0:   4 [-]: JUMPIF R1 L4 
       5 [-]: GETUPVAL R2 0
       6 [-]: GETTABLEKS R1 R2 K4 ["RESPAWN"]
       7 [-]: JUMPIFEQ R0 R1 L4
       8 [-]: GETUPVAL R2 0
       9 [-]: GETTABLEKS R1 R2 K5 ["TESHIN_APPROACH"]
      10 [-]: JUMPIFNOTEQ R0 R1 L1
      11 [-]: GETIMPORT R1 1 [0xCB79539E]
      12 [-]: GETIMPORT R3 7 [0x0469F296]
      13 [-]: LOADK R4 K8 ["DUVIRI_TUTORIAL_STAGE_TIME"]
      14 [-]: CALL R3 1 1  
      15 [-]: LOADK R4 K9 ["5_DormizoneIntro_1"]
      16 [-]: NAMECALL R1 R1 K10 [0xA9188A47]
      17 [-]: CALL R1 3 0  
      18 [-]: JUMP L2
     
L 1:  19 [-]: GETIMPORT R1 1 [0xCB79539E]
      20 [-]: GETIMPORT R3 7 [0x0469F296]
      21 [-]: LOADK R4 K8 ["DUVIRI_TUTORIAL_STAGE_TIME"]
      22 [-]: CALL R3 1 1  
      23 [-]: LOADK R5 K11 ["6_AngryEncounter_"]
      24 [-]: SUBK R6 R0 K12 [1]
      25 [-]: CONCAT R4 R5 R6
      26 [-]: NAMECALL R1 R1 K10 [0xA9188A47]
      27 [-]: CALL R1 3 0  
L 2:  28 [-]: GETUPVAL R2 0
      29 [-]: GETTABLEKS R1 R2 K13 ["COMPLETE"]
      30 [-]: JUMPIFEQ R0 R1 L3
      31 [-]: GETIMPORT R1 1 [0xCB79539E]
      32 [-]: GETIMPORT R3 7 [0x0469F296]
      33 [-]: LOADK R4 K8 ["DUVIRI_TUTORIAL_STAGE_TIME"]
      34 [-]: CALL R3 1 1  
      35 [-]: LOADK R5 K11 ["6_AngryEncounter_"]
      36 [-]: MOVE R6 R0   
      37 [-]: CONCAT R4 R5 R6
      38 [-]: NAMECALL R1 R1 K14 [0xA9136B2F]
      39 [-]: CALL R1 3 0  
L 3:  40 [-]: GETIMPORT R1 1 [0xCB79539E]
      41 [-]: GETIMPORT R3 7 [0x0469F296]
      42 [-]: LOADK R4 K15 ["DUVIRI_TUTORIAL_STAGE"]
      43 [-]: CALL R3 1 1  
      44 [-]: LOADK R5 K11 ["6_AngryEncounter_"]
      45 [-]: MOVE R6 R0   
      46 [-]: CONCAT R4 R5 R6
      47 [-]: NAMECALL R1 R1 K16 [0x8B8FB8B7]
      48 [-]: CALL R1 3 0  
L 4:  49 [-]: GETUPVAL R1 1
      50 [-]: JUMPIFNOT R1 L7
      51 [-]: GETUPVAL R2 0
      52 [-]: GETTABLEKS R1 R2 K17 ["FREE_ROAM"]
      53 [-]: JUMPIFNOTLT R1 R0 L5
      54 [-]: GETUPVAL R2 2
      55 [-]: GETTABLEKS R1 R2 K18 [0xE989BB26]
      56 [-]: CALL R1 0 0  
L 5:  57 [-]: GETUPVAL R2 0
      58 [-]: GETTABLEKS R1 R2 K19 ["GO_TO_MAINLAND"]
      59 [-]: JUMPIFNOTLT R1 R0 L7
      60 [-]: GETUPVAL R2 0
      61 [-]: GETTABLEKS R1 R2 K20 ["ANGRY_STORY"]
      62 [-]: JUMPIFNOTLE R0 R1 L6
      63 [-]: GETUPVAL R2 2
      64 [-]: GETTABLEKS R1 R2 K21 [0x948125AB]
      65 [-]: GETIMPORT R2 23 [0xDDBB3ADA]
      66 [-]: GETIMPORT R3 25 [0xF40E7C8B]
      67 [-]: GETIMPORT R4 27 [0x9397F349]
      68 [-]: CALL R1 3 0  
L 6:  69 [-]: GETUPVAL R2 2
      70 [-]: GETTABLEKS R1 R2 K28 [0xD9337924]
      71 [-]: GETIMPORT R2 30 [0xBCAE77F6]
      72 [-]: LOADB R3 1   
      73 [-]: CALL R1 2 1  
      74 [-]: SETUPVAL R1 3
L 7:  75 [-]: GETUPVAL R2 2
      76 [-]: GETTABLEKS R1 R2 K31 [0xC3899E6B]
      77 [-]: GETUPVAL R2 4
      78 [-]: MOVE R3 R0   
      79 [-]: CALL R1 2 0  
      80 [-]: GETUPVAL R2 0
      81 [-]: GETTABLEKS R1 R2 K5 ["TESHIN_APPROACH"]
      82 [-]: JUMPIFNOTEQ R0 R1 L8
      83 [-]: GETUPVAL R1 5
      84 [-]: GETIMPORT R3 7 [0x0469F296]
      85 [-]: LOADK R4 K32 ["TeshinApproach_StateEvents"]
      86 [-]: CALL R3 1 1  
      87 [-]: LOADB R4 0   
      88 [-]: NAMECALL R1 R1 K33 [0xD5F7912B]
      89 [-]: CALL R1 3 0  
      90 [-]: JUMP L22
    
L 8:  91 [-]: GETUPVAL R2 0
      92 [-]: GETTABLEKS R1 R2 K17 ["FREE_ROAM"]
      93 [-]: JUMPIFNOTEQ R0 R1 L9
      94 [-]: GETUPVAL R1 5
      95 [-]: GETIMPORT R3 7 [0x0469F296]
      96 [-]: LOADK R4 K34 ["FreeRoam_StateEvents"]
      97 [-]: CALL R3 1 1  
      98 [-]: LOADB R4 0   
      99 [-]: NAMECALL R1 R1 K33 [0xD5F7912B]
     100 [-]: CALL R1 3 0  
     101 [-]: JUMP L22
    
L 9: 102 [-]: GETUPVAL R2 0
     103 [-]: GETTABLEKS R1 R2 K19 ["GO_TO_MAINLAND"]
     104 [-]: JUMPIFNOTEQ R0 R1 L10
     105 [-]: GETUPVAL R1 5
     106 [-]: GETIMPORT R3 7 [0x0469F296]
     107 [-]: LOADK R4 K35 ["GoToMainLand_StateEvents"]
     108 [-]: CALL R3 1 1  
     109 [-]: LOADB R4 0   
     110 [-]: NAMECALL R1 R1 K33 [0xD5F7912B]
     111 [-]: CALL R1 3 0  
     112 [-]: JUMP L22
    
L10: 113 [-]: GETUPVAL R2 0
     114 [-]: GETTABLEKS R1 R2 K36 ["REACH_ANGRY_STORY"]
     115 [-]: JUMPIFNOTEQ R0 R1 L11
     116 [-]: GETUPVAL R1 5
     117 [-]: GETIMPORT R3 7 [0x0469F296]
     118 [-]: LOADK R4 K37 ["ReachAngryStory_StateEvents"]
     119 [-]: CALL R3 1 1  
     120 [-]: LOADB R4 0   
     121 [-]: NAMECALL R1 R1 K33 [0xD5F7912B]
     122 [-]: CALL R1 3 0  
     123 [-]: JUMP L22
    
L11: 124 [-]: GETUPVAL R2 0
     125 [-]: GETTABLEKS R1 R2 K20 ["ANGRY_STORY"]
     126 [-]: JUMPIFNOTEQ R0 R1 L12
     127 [-]: GETUPVAL R1 5
     128 [-]: GETIMPORT R3 7 [0x0469F296]
     129 [-]: LOADK R4 K38 ["AngryStory_StateEvents"]
     130 [-]: CALL R3 1 1  
     131 [-]: LOADB R4 0   
     132 [-]: NAMECALL R1 R1 K33 [0xD5F7912B]
     133 [-]: CALL R1 3 0  
     134 [-]: JUMP L22
    
L12: 135 [-]: GETUPVAL R2 0
     136 [-]: GETTABLEKS R1 R2 K39 ["COLLECT_FIGURINE_PART"]
     137 [-]: JUMPIFNOTEQ R0 R1 L13
     138 [-]: GETUPVAL R1 5
     139 [-]: GETIMPORT R3 7 [0x0469F296]
     140 [-]: LOADK R4 K40 ["CollectFigurinePart_StateEvents"]
     141 [-]: CALL R3 1 1  
     142 [-]: LOADB R4 0   
     143 [-]: NAMECALL R1 R1 K33 [0xD5F7912B]
     144 [-]: CALL R1 3 0  
     145 [-]: JUMP L22
    
L13: 146 [-]: GETUPVAL R2 0
     147 [-]: GETTABLEKS R1 R2 K41 ["RETURN_TO_CAVE"]
     148 [-]: JUMPIFNOTEQ R0 R1 L14
     149 [-]: GETUPVAL R1 5
     150 [-]: GETIMPORT R3 7 [0x0469F296]
     151 [-]: LOADK R4 K42 ["ReturnToCave_StateEvents"]
     152 [-]: CALL R3 1 1  
     153 [-]: LOADB R4 0   
     154 [-]: NAMECALL R1 R1 K33 [0xD5F7912B]
     155 [-]: CALL R1 3 0  
     156 [-]: JUMP L22
    
L14: 157 [-]: GETUPVAL R2 0
     158 [-]: GETTABLEKS R1 R2 K43 ["REASSEMBLE_FIGURE"]
     159 [-]: JUMPIFNOTEQ R0 R1 L15
     160 [-]: GETUPVAL R1 5
     161 [-]: GETIMPORT R3 7 [0x0469F296]
     162 [-]: LOADK R4 K44 ["ReassembleFigure_StateEvents"]
     163 [-]: CALL R3 1 1  
     164 [-]: LOADB R4 0   
     165 [-]: NAMECALL R1 R1 K33 [0xD5F7912B]
     166 [-]: CALL R1 3 0  
     167 [-]: JUMP L22
    
L15: 168 [-]: GETUPVAL R2 0
     169 [-]: GETTABLEKS R1 R2 K45 ["DIORAMA"]
     170 [-]: JUMPIFNOTEQ R0 R1 L16
     171 [-]: GETUPVAL R1 5
     172 [-]: GETIMPORT R3 7 [0x0469F296]
     173 [-]: LOADK R4 K46 ["Diorama_StateEvents"]
     174 [-]: CALL R3 1 1  
     175 [-]: LOADB R4 0   
     176 [-]: NAMECALL R1 R1 K33 [0xD5F7912B]
     177 [-]: CALL R1 3 0  
     178 [-]: JUMP L22
    
L16: 179 [-]: GETUPVAL R2 0
     180 [-]: GETTABLEKS R1 R2 K47 ["CUTSCENE"]
     181 [-]: JUMPIFNOTEQ R0 R1 L17
     182 [-]: GETUPVAL R1 5
     183 [-]: GETIMPORT R3 7 [0x0469F296]
     184 [-]: LOADK R4 K48 ["Cutscene_StateEvents"]
     185 [-]: CALL R3 1 1  
     186 [-]: LOADB R4 0   
     187 [-]: NAMECALL R1 R1 K33 [0xD5F7912B]
     188 [-]: CALL R1 3 0  
     189 [-]: JUMP L22
    
L17: 190 [-]: GETUPVAL R2 0
     191 [-]: GETTABLEKS R1 R2 K49 ["CONVERSATION"]
     192 [-]: JUMPIFNOTEQ R0 R1 L18
     193 [-]: GETUPVAL R1 5
     194 [-]: GETIMPORT R3 7 [0x0469F296]
     195 [-]: LOADK R4 K50 ["Conversation_StateEvents"]
     196 [-]: CALL R3 1 1  
     197 [-]: LOADB R4 0   
     198 [-]: NAMECALL R1 R1 K33 [0xD5F7912B]
     199 [-]: CALL R1 3 0  
     200 [-]: JUMP L22
    
L18: 201 [-]: GETUPVAL R2 0
     202 [-]: GETTABLEKS R1 R2 K51 ["REST_BY_FIRE"]
     203 [-]: JUMPIFNOTEQ R0 R1 L19
     204 [-]: GETUPVAL R1 5
     205 [-]: GETIMPORT R3 7 [0x0469F296]
     206 [-]: LOADK R4 K52 ["RestByFire_StateEvents"]
     207 [-]: CALL R3 1 1  
     208 [-]: LOADB R4 0   
     209 [-]: NAMECALL R1 R1 K33 [0xD5F7912B]
     210 [-]: CALL R1 3 0  
     211 [-]: JUMP L22
    
L19: 212 [-]: GETUPVAL R2 0
     213 [-]: GETTABLEKS R1 R2 K13 ["COMPLETE"]
     214 [-]: JUMPIFNOTEQ R0 R1 L21
     215 [-]: GETUPVAL R1 6
     216 [-]: JUMPIFNOT R1 L20
     217 [-]: GETUPVAL R1 6
     218 [-]: NAMECALL R1 R1 K53 [0xA2880940]
     219 [-]: CALL R1 1 0  
L20: 220 [-]: GETUPVAL R1 5
     221 [-]: LOADN R3 4   
     222 [-]: NAMECALL R1 R1 K54 [0xFE9DC265]
     223 [-]: CALL R1 2 0  
     224 [-]: JUMP L22
    
L21: 225 [-]: GETUPVAL R2 0
     226 [-]: GETTABLEKS R1 R2 K4 ["RESPAWN"]
     227 [-]: JUMPIFNOTEQ R0 R1 L22
     228 [-]: GETUPVAL R2 8
     229 [-]: GETTABLEKS R1 R2 K55 [0x4A6404E4]
     230 [-]: GETUPVAL R2 4
     231 [-]: GETUPVAL R3 7
     232 [-]: GETUPVAL R4 9
     233 [-]: LOADNIL R5   
     234 [-]: LOADNIL R6   
     235 [-]: LOADB R7 1   
     236 [-]: CALL R1 6 1  
     237 [-]: SETUPVAL R1 7
L22: 238 [-]: GETUPVAL R1 1
     239 [-]: JUMPIFNOT R1 L23
     240 [-]: GETUPVAL R2 10
     241 [-]: GETTABLEKS R1 R2 K56 [0x76247E4F]
     242 [-]: GETUPVAL R2 1
     243 [-]: GETUPVAL R3 4
     244 [-]: CALL R1 2 0  
L23: 245 [-]: RETURN R0 0  


; Name:            
; Defined at line: 1257
; #Upvalues:       15
; #Parameters:     1
; Is_vararg:       0
; Max Stack Size:  9

       0 [-]: GETUPVAL R1 0
       1 [-]: JUMPIFNOT R1 L0
       2 [-]: GETUPVAL R1 1
       3 [-]: GETUPVAL R3 0
       4 [-]: NAMECALL R1 R1 K0 [0x8ABFF40E]
       5 [-]: CALL R1 2 0  
       6 [-]: LOADNIL R1   
       7 [-]: SETUPVAL R1 0
       8 [-]: RETURN R0 0  
L 0:   9 [-]: GETIMPORT R1 3 ["PlayerDead"]
      10 [-]: JUMPIFNOT R1 L1
      11 [-]: GETUPVAL R1 3
      12 [-]: SETUPVAL R1 2
      13 [-]: GETUPVAL R1 1
      14 [-]: GETUPVAL R4 4
      15 [-]: GETTABLEKS R3 R4 K4 ["RESPAWN"]
      16 [-]: NAMECALL R1 R1 K0 [0x8ABFF40E]
      17 [-]: CALL R1 2 0  
      18 [-]: RETURN R0 0  
L 1:  19 [-]: GETUPVAL R1 5
      20 [-]: MOVE R3 R0   
      21 [-]: NAMECALL R1 R1 K5 [0xFAA69527]
      22 [-]: CALL R1 2 0  
      23 [-]: GETUPVAL R1 3
      24 [-]: GETUPVAL R3 4
      25 [-]: GETTABLEKS R2 R3 K6 ["TESHIN_APPROACH"]
      26 [-]: JUMPIFNOTEQ R1 R2 L5
      27 [-]: GETUPVAL R1 6
      28 [-]: JUMPIF R1 L15
      29 [-]: GETUPVAL R2 7
      30 [-]: FASTCALL1 62 R2 L2
      31 [-]: GETIMPORT R1 8 [0x7B998233]
      32 [-]: CALL R1 1 1  
L 2:  33 [-]: JUMPIF R1 L15
      34 [-]: GETUPVAL R2 8
      35 [-]: FASTCALL1 62 R2 L3
      36 [-]: GETIMPORT R1 8 [0x7B998233]
      37 [-]: CALL R1 1 1  
L 3:  38 [-]: JUMPIFNOT R1 L4
      39 [-]: RETURN R0 0  
L 4:  40 [-]: GETUPVAL R1 7
      41 [-]: NAMECALL R1 R1 K9 [0xD1586535]
      42 [-]: CALL R1 1 1  
      43 [-]: GETUPVAL R2 8
      44 [-]: MOVE R4 R1   
      45 [-]: NAMECALL R2 R2 K10 [0x1F420A3A]
      46 [-]: CALL R2 2 1  
      47 [-]: LOADN R3 5   
      48 [-]: JUMPIFNOTLT R2 R3 L15
      49 [-]: LOADB R2 1   
      50 [-]: SETUPVAL R2 6
      51 [-]: RETURN R0 0  
L 5:  52 [-]: GETUPVAL R1 3
      53 [-]: GETUPVAL R3 4
      54 [-]: GETTABLEKS R2 R3 K11 ["ANGRY_STORY"]
      55 [-]: JUMPIFNOTEQ R1 R2 L14
      56 [-]: GETIMPORT R1 13 ["DynamicMission"]
      57 [-]: JUMPIFNOT R1 L11
      58 [-]: GETIMPORT R1 15 ["Hint"]
      59 [-]: GETUPVAL R2 9
      60 [-]: JUMPIFEQ R1 R2 L11
      61 [-]: GETUPVAL R2 9
      62 [-]: FASTCALL1 62 R2 L6
      63 [-]: GETIMPORT R1 8 [0x7B998233]
      64 [-]: CALL R1 1 1  
L 6:  65 [-]: JUMPIF R1 L9 
      66 [-]: GETUPVAL R2 9
      67 [-]: NAMECALL R2 R2 K16 [0xC4FD01FA]
      68 [-]: CALL R2 1 1  
      69 [-]: LENGTH R1 R2 
      70 [-]: LOADN R2 0   
      71 [-]: JUMPIFNOTLT R2 R1 L9
      72 [-]: GETUPVAL R1 10
      73 [-]: GETUPVAL R3 9
      74 [-]: NAMECALL R3 R3 K9 [0xD1586535]
      75 [-]: CALL R3 1 -1 
      76 [-]: NAMECALL R1 R1 K17 [0x0E8C38E5]
      77 [-]: CALL R1 -1 1 
      78 [-]: GETIMPORT R2 19 ["ZERO_ROTATION"]
      79 [-]: GETIMPORT R3 15 ["Hint"]
      80 [-]: JUMPIFNOT R3 L7
      81 [-]: GETIMPORT R3 21 [0x20B7F774]
      82 [-]: MOVE R4 R1   
      83 [-]: GETIMPORT R5 15 ["Hint"]
      84 [-]: NAMECALL R5 R5 K9 [0xD1586535]
      85 [-]: CALL R5 1 -1 
      86 [-]: CALL R3 -1 1 
      87 [-]: MOVE R2 R3   
L 7:  88 [-]: MOVE R3 R2   
      89 [-]: GETUPVAL R4 11
      90 [-]: JUMPIFNOT R4 L8
      91 [-]: GETUPVAL R4 11
      92 [-]: NAMECALL R4 R4 K22 [0xA2880940]
      93 [-]: CALL R4 1 0  
L 8:  94 [-]: GETIMPORT R4 24 [0x89326C93]
      95 [-]: GETIMPORT R6 26 [0x78EB7099]
      96 [-]: MOVE R7 R1   
      97 [-]: MOVE R8 R3   
      98 [-]: NAMECALL R4 R4 K27 [0x05909209]
      99 [-]: CALL R4 4 1  
     100 [-]: SETUPVAL R4 11
     101 [-]: GETUPVAL R4 11
     102 [-]: GETIMPORT R6 29 [0x0469F296]
     103 [-]: LOADK R7 K30 ["StoryCheckpointWp"]
     104 [-]: CALL R6 1 -1 
     105 [-]: NAMECALL R4 R4 K31 [0x3273BA96]
     106 [-]: CALL R4 -1 0 
     107 [-]: JUMP L10
    
L 9: 108 [-]: GETIMPORT R1 33 [0x3D106989]
     109 [-]: LOADK R2 K34 ["mCurStoryHint is null or no encounter tags"]
     110 [-]: CALL R1 1 0  
L10: 111 [-]: GETIMPORT R1 15 ["Hint"]
     112 [-]: SETUPVAL R1 9
L11: 113 [-]: GETUPVAL R2 12
     114 [-]: FASTCALL1 62 R2 L12
     115 [-]: GETIMPORT R1 8 [0x7B998233]
     116 [-]: CALL R1 1 1  
L12: 117 [-]: JUMPIF R1 L15
     118 [-]: GETUPVAL R1 12
     119 [-]: LOADN R3 0   
     120 [-]: NAMECALL R1 R1 K35 [0xE3A0BBCA]
     121 [-]: CALL R1 2 1  
     122 [-]: FASTCALL1 62 R1 L13
     123 [-]: MOVE R3 R1   
     124 [-]: GETIMPORT R2 8 [0x7B998233]
     125 [-]: CALL R2 1 1  
L13: 126 [-]: JUMPIF R2 L15
     127 [-]: NAMECALL R2 R1 K36 [0x2047CFE7]
     128 [-]: CALL R2 1 1  
     129 [-]: JUMPIFNOT R2 L15
     130 [-]: GETUPVAL R2 13
     131 [-]: JUMPIF R2 L15
     132 [-]: GETUPVAL R2 14
     133 [-]: GETIMPORT R4 29 [0x0469F296]
     134 [-]: LOADK R5 K37 ["RespawnWarframe"]
     135 [-]: CALL R4 1 1  
     136 [-]: LOADB R5 0   
     137 [-]: NAMECALL R2 R2 K38 [0xD5F7912B]
     138 [-]: CALL R2 3 0  
     139 [-]: RETURN R0 0  
L14: 140 [-]: GETUPVAL R1 3
     141 [-]: GETUPVAL R3 4
     142 [-]: GETTABLEKS R2 R3 K4 ["RESPAWN"]
     143 [-]: JUMPIFNOTEQ R1 R2 L15
     144 [-]: GETUPVAL R1 1
     145 [-]: GETUPVAL R3 2
     146 [-]: NAMECALL R1 R1 K0 [0x8ABFF40E]
     147 [-]: CALL R1 2 0  
L15: 148 [-]: RETURN R0 0  


; Name:            
; Defined at line: 1312
; #Upvalues:       2
; #Parameters:     1
; Is_vararg:       0
; Max Stack Size:  3

       0 [-]: JUMPXEQKS R0 K0 L0 NOT ["Cancel"]
       1 [-]: GETUPVAL R2 1
       2 [-]: GETTABLEKS R1 R2 K1 ["TESHIN_APPROACH"]
       3 [-]: SETUPVAL R1 0
       4 [-]: RETURN R0 0  
L 0:   5 [-]: GETUPVAL R2 1
       6 [-]: GETTABLE R1 R2 R0
       7 [-]: SETUPVAL R1 0
       8 [-]: RETURN R0 0  


; Name:            
; Defined at line: 1321
; #Upvalues:       22
; #Parameters:     1
; Is_vararg:       0
; Max Stack Size:  15

       0 [-]: SETUPVAL R0 0
       1 [-]: GETUPVAL R1 0
       2 [-]: NAMECALL R1 R1 K0 [0x4C976EDA]
       3 [-]: CALL R1 1 1  
       4 [-]: SETUPVAL R1 1
       5 [-]: GETUPVAL R2 1
       6 [-]: FASTCALL1 62 R2 L0
       7 [-]: GETIMPORT R1 2 [0x7B998233]
       8 [-]: CALL R1 1 1  
L 0:   9 [-]: JUMPIF R1 L1 
      10 [-]: GETUPVAL R1 1
      11 [-]: NAMECALL R1 R1 K3 [0xAA1950D4]
      12 [-]: CALL R1 1 1  
      13 [-]: SETUPVAL R1 2
      14 [-]: GETUPVAL R1 1
      15 [-]: NAMECALL R1 R1 K4 [0xE4C355E2]
      16 [-]: CALL R1 1 1  
      17 [-]: SETUPVAL R1 3
L 1:  18 [-]: GETIMPORT R1 6 [0x89326C93]
      19 [-]: NAMECALL R1 R1 K7 [0x29EF273D]
      20 [-]: CALL R1 1 1  
      21 [-]: NAMECALL R1 R1 K8 [0x66905CB0]
      22 [-]: CALL R1 1 1  
      23 [-]: SETUPVAL R1 4
      24 [-]: GETUPVAL R2 6
      25 [-]: GETTABLEKS R1 R2 K9 [0xDE474187]
      26 [-]: CALL R1 0 1  
      27 [-]: SETUPVAL R1 5
      28 [-]: GETUPVAL R2 8
      29 [-]: GETTABLEKS R1 R2 K10 [0xC9013731]
      30 [-]: GETUPVAL R2 9
      31 [-]: GETUPVAL R3 0
      32 [-]: NEWTABLE R4 0 0
      33 [-]: CALL R1 3 1  
      34 [-]: SETUPVAL R1 7
      35 [-]: GETIMPORT R1 6 [0x89326C93]
      36 [-]: NAMECALL R1 R1 K11 [0xFB64E76C]
      37 [-]: CALL R1 1 1  
      38 [-]: SETUPVAL R1 10
      39 [-]: GETIMPORT R1 6 [0x89326C93]
      40 [-]: NAMECALL R1 R1 K12 [0x78298275]
      41 [-]: CALL R1 1 1  
      42 [-]: SETUPVAL R1 11
      43 [-]: GETUPVAL R2 12
      44 [-]: GETTABLEKS R1 R2 K13 [0xD2CED2F7]
      45 [-]: GETUPVAL R2 11
      46 [-]: LOADB R3 1   
      47 [-]: LOADNIL R4   
      48 [-]: LOADB R5 1   
      49 [-]: CALL R1 4 0  
      50 [-]: GETUPVAL R2 13
      51 [-]: GETTABLEKS R1 R2 K14 [0x05E250F3]
      52 [-]: CALL R1 0 0  
      53 [-]: GETIMPORT R1 6 [0x89326C93]
      54 [-]: GETIMPORT R3 16 [0x0469F296]
      55 [-]: LOADK R4 K17 ["OldManTeshin"]
      56 [-]: CALL R3 1 -1 
      57 [-]: NAMECALL R1 R1 K18 [0x46A0EBF5]
      58 [-]: CALL R1 -1 1 
      59 [-]: FASTCALL1 62 R1 L2
      60 [-]: MOVE R3 R1   
      61 [-]: GETIMPORT R2 2 [0x7B998233]
      62 [-]: CALL R2 1 1  
L 2:  63 [-]: JUMPIF R2 L3 
      64 [-]: LOADB R4 0   
      65 [-]: LOADB R5 1   
      66 [-]: NAMECALL R2 R1 K19 [0x768274D6]
      67 [-]: CALL R2 3 0  
      68 [-]: GETIMPORT R4 16 [0x0469F296]
      69 [-]: LOADK R5 K20 ["NotAnimated"]
      70 [-]: CALL R4 1 -1 
      71 [-]: NAMECALL R2 R1 K21 [0x26D544FC]
      72 [-]: CALL R2 -1 0 
L 3:  73 [-]: GETIMPORT R2 6 [0x89326C93]
      74 [-]: GETIMPORT R4 16 [0x0469F296]
      75 [-]: LOADK R5 K22 ["TeshinApproachCutscene"]
      76 [-]: CALL R4 1 -1 
      77 [-]: NAMECALL R2 R2 K18 [0x46A0EBF5]
      78 [-]: CALL R2 -1 1 
      79 [-]: FASTCALL1 62 R2 L4
      80 [-]: MOVE R4 R2   
      81 [-]: GETIMPORT R3 2 [0x7B998233]
      82 [-]: CALL R3 1 1  
L 4:  83 [-]: JUMPIF R3 L5 
      84 [-]: LOADB R5 0   
      85 [-]: LOADB R6 1   
      86 [-]: NAMECALL R3 R2 K19 [0x768274D6]
      87 [-]: CALL R3 3 0  
      88 [-]: GETIMPORT R5 16 [0x0469F296]
      89 [-]: LOADK R6 K20 ["NotAnimated"]
      90 [-]: CALL R5 1 -1 
      91 [-]: NAMECALL R3 R2 K21 [0x26D544FC]
      92 [-]: CALL R3 -1 0 
L 5:  93 [-]: GETIMPORT R3 6 [0x89326C93]
      94 [-]: GETIMPORT R5 16 [0x0469F296]
      95 [-]: LOADK R6 K23 ["OldManTeshinHappyCinematic"]
      96 [-]: CALL R5 1 -1 
      97 [-]: NAMECALL R3 R3 K18 [0x46A0EBF5]
      98 [-]: CALL R3 -1 1 
      99 [-]: FASTCALL1 62 R3 L6
     100 [-]: MOVE R5 R3   
     101 [-]: GETIMPORT R4 2 [0x7B998233]
     102 [-]: CALL R4 1 1  
L 6: 103 [-]: JUMPIF R4 L7 
     104 [-]: LOADB R6 0   
     105 [-]: LOADB R7 1   
     106 [-]: NAMECALL R4 R3 K19 [0x768274D6]
     107 [-]: CALL R4 3 0  
     108 [-]: GETIMPORT R6 16 [0x0469F296]
     109 [-]: LOADK R7 K20 ["NotAnimated"]
     110 [-]: CALL R6 1 -1 
     111 [-]: NAMECALL R4 R3 K21 [0x26D544FC]
     112 [-]: CALL R4 -1 0 
L 7: 113 [-]: GETIMPORT R4 6 [0x89326C93]
     114 [-]: GETIMPORT R6 16 [0x0469F296]
     115 [-]: LOADK R7 K24 ["OldManTeshinConvo"]
     116 [-]: CALL R6 1 -1 
     117 [-]: NAMECALL R4 R4 K18 [0x46A0EBF5]
     118 [-]: CALL R4 -1 1 
     119 [-]: FASTCALL1 62 R4 L8
     120 [-]: MOVE R6 R4   
     121 [-]: GETIMPORT R5 2 [0x7B998233]
     122 [-]: CALL R5 1 1  
L 8: 123 [-]: JUMPIF R5 L9 
     124 [-]: SETUPVAL R4 14
     125 [-]: GETUPVAL R5 14
     126 [-]: LOADB R7 0   
     127 [-]: LOADB R8 1   
     128 [-]: NAMECALL R5 R5 K19 [0x768274D6]
     129 [-]: CALL R5 3 0  
L 9: 130 [-]: GETIMPORT R5 6 [0x89326C93]
     131 [-]: GETIMPORT R7 16 [0x0469F296]
     132 [-]: LOADK R8 K25 ["OldManTeshinFire"]
     133 [-]: CALL R7 1 -1 
     134 [-]: NAMECALL R5 R5 K18 [0x46A0EBF5]
     135 [-]: CALL R5 -1 1 
     136 [-]: FASTCALL1 62 R5 L10
     137 [-]: MOVE R7 R5   
     138 [-]: GETIMPORT R6 2 [0x7B998233]
     139 [-]: CALL R6 1 1  
L10: 140 [-]: JUMPIF R6 L11
     141 [-]: SETUPVAL R5 15
     142 [-]: GETUPVAL R6 15
     143 [-]: LOADB R8 1   
     144 [-]: LOADB R9 1   
     145 [-]: NAMECALL R6 R6 K19 [0x768274D6]
     146 [-]: CALL R6 3 0  
L11: 147 [-]: GETIMPORT R6 6 [0x89326C93]
     148 [-]: GETIMPORT R8 16 [0x0469F296]
     149 [-]: LOADK R9 K26 ["TeshinsFire"]
     150 [-]: CALL R8 1 -1 
     151 [-]: NAMECALL R6 R6 K18 [0x46A0EBF5]
     152 [-]: CALL R6 -1 1 
     153 [-]: FASTCALL1 62 R6 L12
     154 [-]: MOVE R8 R6   
     155 [-]: GETIMPORT R7 2 [0x7B998233]
     156 [-]: CALL R7 1 1  
L12: 157 [-]: JUMPIF R7 L13
     158 [-]: LOADK R9 K27 ["TriggerPort"]
     159 [-]: NAMECALL R7 R6 K28 [0x8EB2112D]
     160 [-]: CALL R7 2 0  
L13: 161 [-]: GETIMPORT R7 6 [0x89326C93]
     162 [-]: GETIMPORT R9 16 [0x0469F296]
     163 [-]: LOADK R10 K29 ["OldManTeshinCinematicBV"]
     164 [-]: CALL R9 1 -1 
     165 [-]: NAMECALL R7 R7 K18 [0x46A0EBF5]
     166 [-]: CALL R7 -1 1 
     167 [-]: FASTCALL1 62 R7 L14
     168 [-]: MOVE R9 R7   
     169 [-]: GETIMPORT R8 2 [0x7B998233]
     170 [-]: CALL R8 1 1  
L14: 171 [-]: JUMPIF R8 L15
     172 [-]: SETUPVAL R7 16
L15: 173 [-]: GETIMPORT R8 6 [0x89326C93]
     174 [-]: GETIMPORT R10 16 [0x0469F296]
     175 [-]: LOADK R11 K30 ["TeshinBarkTrigger"]
     176 [-]: CALL R10 1 -1
     177 [-]: NAMECALL R8 R8 K18 [0x46A0EBF5]
     178 [-]: CALL R8 -1 1 
     179 [-]: FASTCALL1 62 R8 L16
     180 [-]: MOVE R10 R8  
     181 [-]: GETIMPORT R9 2 [0x7B998233]
     182 [-]: CALL R9 1 1  
L16: 183 [-]: JUMPIF R9 L17
     184 [-]: NAMECALL R9 R8 K31 [0xF4E253B6]
     185 [-]: CALL R9 1 0  
L17: 186 [-]: GETIMPORT R9 6 [0x89326C93]
     187 [-]: GETIMPORT R11 16 [0x0469F296]
     188 [-]: LOADK R12 K32 ["DormizoneSpawnPoint"]
     189 [-]: CALL R11 1 -1
     190 [-]: NAMECALL R9 R9 K18 [0x46A0EBF5]
     191 [-]: CALL R9 -1 1 
     192 [-]: FASTCALL1 62 R9 L18
     193 [-]: MOVE R11 R9  
     194 [-]: GETIMPORT R10 2 [0x7B998233]
     195 [-]: CALL R10 1 1 
L18: 196 [-]: JUMPIF R10 L19
     197 [-]: GETUPVAL R10 11
     198 [-]: NAMECALL R12 R9 K33 [0xD1586535]
     199 [-]: CALL R12 1 1 
     200 [-]: NAMECALL R13 R9 K34 [0xCB3851B8]
     201 [-]: CALL R13 1 -1
     202 [-]: NAMECALL R10 R10 K35 [0x589EF1C1]
     203 [-]: CALL R10 -1 0
L19: 204 [-]: GETUPVAL R11 13
     205 [-]: GETTABLEKS R10 R11 K36 [0x3C1B3308]
     206 [-]: CALL R10 0 0 
     207 [-]: GETUPVAL R11 13
     208 [-]: GETTABLEKS R10 R11 K37 [0xE453D7FE]
     209 [-]: CALL R10 0 0 
     210 [-]: GETUPVAL R11 13
     211 [-]: GETTABLEKS R10 R11 K38 [0x59CAB14B]
     212 [-]: CALL R10 0 0 
     213 [-]: GETUPVAL R11 13
     214 [-]: GETTABLEKS R10 R11 K39 [0xF009BF4B]
     215 [-]: LOADN R11 1  
     216 [-]: CALL R10 1 0 
     217 [-]: GETUPVAL R11 13
     218 [-]: GETTABLEKS R10 R11 K40 [0xCFE9FDF7]
     219 [-]: CALL R10 0 0 
     220 [-]: GETUPVAL R11 13
     221 [-]: GETTABLEKS R10 R11 K41 [0x663D839C]
     222 [-]: LOADB R11 0  
     223 [-]: CALL R10 1 0 
     224 [-]: GETIMPORT R10 43 ["_T"]
     225 [-]: GETUPVAL R11 17
     226 [-]: SETTABLEKS R11 R10 K44 ["PreCheckpointRespawn"]
     227 [-]: GETIMPORT R10 43 ["_T"]
     228 [-]: GETUPVAL R11 18
     229 [-]: SETTABLEKS R11 R10 K45 ["PostCheckpointRespawn"]
     230 [-]: GETUPVAL R11 13
     231 [-]: GETTABLEKS R10 R11 K46 [0xC7CEABE5]
     232 [-]: CALL R10 0 0 
     233 [-]: GETUPVAL R11 12
     234 [-]: GETTABLEKS R10 R11 K47 [0xBDD9801D]
     235 [-]: LOADB R11 0  
     236 [-]: CALL R10 1 0 
     237 [-]: GETUPVAL R11 12
     238 [-]: GETTABLEKS R10 R11 K48 [0x12A41A40]
     239 [-]: LOADB R11 0  
     240 [-]: LOADN R12 1  
     241 [-]: CALL R10 2 0 
     242 [-]: GETUPVAL R11 13
     243 [-]: GETTABLEKS R10 R11 K49 [0x958E23C4]
     244 [-]: CALL R10 0 1 
     245 [-]: JUMPIFNOT R10 L20
     246 [-]: GETUPVAL R11 19
     247 [-]: GETTABLEKS R10 R11 K50 [0x01566DB3]
     248 [-]: GETUPVAL R11 20
     249 [-]: GETUPVAL R12 21
     250 [-]: CALL R10 2 0 
     251 [-]: RETURN R0 0  
L20: 252 [-]: GETUPVAL R10 7
     253 [-]: GETUPVAL R13 20
     254 [-]: GETTABLEKS R12 R13 K51 ["TESHIN_APPROACH"]
     255 [-]: NAMECALL R10 R10 K52 [0x8ABFF40E]
     256 [-]: CALL R10 2 0 
     257 [-]: RETURN R0 0  


; Name:            
; Defined at line: 1416
; #Upvalues:       5
; #Parameters:     1
; Is_vararg:       0
; Max Stack Size:  4

       0 [-]: GETUPVAL R1 0
       1 [-]: MOVE R2 R0   
       2 [-]: CALL R1 1 0  
L 0:   3 [-]: GETUPVAL R1 1
       4 [-]: NAMECALL R1 R1 K0 [0xEFE6CAD1]
       5 [-]: CALL R1 1 1  
       6 [-]: LOADN R2 4   
       7 [-]: JUMPIFNOTLT R1 R2 L1
       8 [-]: GETUPVAL R1 3
       9 [-]: GETUPVAL R3 2
      10 [-]: NAMECALL R1 R1 K1 [0x209398C2]
      11 [-]: CALL R1 2 1  
      12 [-]: SETUPVAL R1 2
      13 [-]: GETUPVAL R1 4
      14 [-]: GETIMPORT R2 3 [0xFFF641AF]
      15 [-]: CALL R2 0 -1 
      16 [-]: CALL R1 -1 0 
      17 [-]: GETIMPORT R1 5 [0xCBD666E1]
      18 [-]: LOADN R2 0   
      19 [-]: CALL R1 1 0  
      20 [-]: JUMPBACK L0  
L 1:  21 [-]: RETURN R0 0  


; Name:            
; Defined at line: 1425
; #Upvalues:       1
; #Parameters:     0
; Is_vararg:       0
; Max Stack Size:  5

       0 [-]: GETUPVAL R1 0
       1 [-]: GETTABLEKS R0 R1 K0 [0x11DCFE97]
       2 [-]: GETIMPORT R1 2 [0x0469F296]
       3 [-]: LOADK R2 K3 ["DDuvParQAngerMem1010"]
       4 [-]: CALL R1 1 1  
       5 [-]: LOADB R2 0   
       6 [-]: LOADB R3 0   
       7 [-]: LOADN R4 4   
       8 [-]: CALL R0 4 0  
       9 [-]: RETURN R0 0  



