; Name:            
; Defined at line: 1
; #Upvalues:       0
; #Parameters:     0
; Is_vararg:       1
; Max Stack Size:  87

       1 [-]: GETIMPORT R0 1; var0 = 0x2D0FAD09
       2 [-]: LOADK R1 K2  ; var1 = "Lotus.Scripts.Libs.TableLib"
       3 [-]: CALL R0 2 2  ; var0 = var0(var1)
       4 [-]: GETIMPORT R1 1; var1 = 0x2D0FAD09
       5 [-]: LOADK R2 K3  ; var2 = "Lotus.Scripts.Libs.TransmissionSet"
       6 [-]: CALL R1 2 2  ; var1 = var1(var2)
       7 [-]: GETIMPORT R2 1; var2 = 0x2D0FAD09
       8 [-]: LOADK R3 K4  ; var3 = "Lotus.Scripts.Libs.CommonGamemodeFunctions"
       9 [-]: CALL R2 2 2  ; var2 = var2(var3)
      10 [-]: GETIMPORT R3 1; var3 = 0x2D0FAD09
      11 [-]: LOADK R4 K5  ; var4 = "Lotus.Scripts.Libs.LandscapeLib"
      12 [-]: CALL R3 2 2  ; var3 = var3(var4)
      13 [-]: GETIMPORT R4 1; var4 = 0x2D0FAD09
      14 [-]: LOADK R5 K6  ; var5 = "Lotus.Scripts.Libs.ObjectiveText"
      15 [-]: CALL R4 2 2  ; var4 = var4(var5)
      16 [-]: GETIMPORT R5 1; var5 = 0x2D0FAD09
      17 [-]: LOADK R6 K7  ; var6 = "Lotus.Interface.Libs.TimerMgr"
      18 [-]: CALL R5 2 2  ; var5 = var5(var6)
      19 [-]: GETIMPORT R6 1; var6 = 0x2D0FAD09
      20 [-]: LOADK R7 K8  ; var7 = "Lotus.Scripts.Libs.QuestMissionLib"
      21 [-]: CALL R6 2 2  ; var6 = var6(var7)
      22 [-]: GETIMPORT R7 1; var7 = 0x2D0FAD09
      23 [-]: LOADK R8 K9  ; var8 = "Lotus.Interface.LotusUtilities"
      24 [-]: CALL R7 2 2  ; var7 = var7(var8)
      25 [-]: GETIMPORT R8 1; var8 = 0x2D0FAD09
      26 [-]: LOADK R9 K10 ; var9 = "EE.Interface.Utilities"
      27 [-]: CALL R8 2 2  ; var8 = var8(var9)
      28 [-]: GETIMPORT R9 1; var9 = 0x2D0FAD09
      29 [-]: LOADK R10 K11; var10 = "Lotus.Scripts.Libs.DuviriStoryQuestLib"
      30 [-]: CALL R9 2 2  ; var9 = var9(var10)
      31 [-]: GETIMPORT R10 1; var10 = 0x2D0FAD09
      32 [-]: LOADK R11 K12; var11 = "Lotus.Scripts.Quests.DuviriQuest.ParadoxQuestUtil"
      33 [-]: CALL R10 2 2 ; var10 = var10(var11)
      34 [-]: GETIMPORT R11 1; var11 = 0x2D0FAD09
      35 [-]: LOADK R12 K13; var12 = "Lotus.Powersuits.Operator.OperatorLib"
      36 [-]: CALL R11 2 2 ; var11 = var11(var12)
      37 [-]: LOADNIL R12  ; var12 = nil
      38 [-]: LOADNIL R13  ; var13 = nil
      39 [-]: LOADNIL R14  ; var14 = nil
      40 [-]: LOADNIL R15  ; var15 = nil
      41 [-]: LOADNIL R16  ; var16 = nil
      42 [-]: LOADNIL R17  ; var17 = nil
      43 [-]: LOADN R18 0  ; var18 = 0
      44 [-]: LOADNIL R19  ; var19 = nil
      45 [-]: LOADNIL R20  ; var20 = nil
      46 [-]: LOADNIL R21  ; var21 = nil
      47 [-]: LOADNIL R22  ; var22 = nil
      48 [-]: LOADNIL R23  ; var23 = nil
      49 [-]: LOADNIL R24  ; var24 = nil
      50 [-]: LOADNIL R25  ; var25 = nil
      51 [-]: LOADNIL R26  ; var26 = nil
      52 [-]: LOADNIL R27  ; var27 = nil
      53 [-]: LOADN R28 0  ; var28 = 0
      54 [-]: LOADN R29 0  ; var29 = 0
      55 [-]: LOADNIL R30  ; var30 = nil
      56 [-]: LOADNIL R31  ; var31 = nil
      57 [-]: LOADNIL R32  ; var32 = nil
      58 [-]: LOADNIL R33  ; var33 = nil
      59 [-]: LOADB R34 0  ; var34 = false
      60 [-]: LOADNIL R35  ; var35 = nil
      61 [-]: LOADNIL R36  ; var36 = nil
      62 [-]: LOADB R37 0  ; var37 = false
      63 [-]: LOADB R38 0  ; var38 = false
      64 [-]: LOADNIL R39  ; var39 = nil
      65 [-]: LOADB R40 0  ; var40 = false
      66 [-]: NEWTABLE R41 0 0; var41 = {}
      67 [-]: LOADNIL R42  ; var42 = nil
      68 [-]: NEWTABLE R43 4 0; var43 = {}
      69 [-]: LOADN R44 0  ; var44 = 0
      70 [-]: LOADNIL R45  ; var45 = nil
      71 [-]: SETTABLE R45 R43 R44; var45[var43] = var44
      72 [-]: LOADN R44 1  ; var44 = 1
      73 [-]: LOADNIL R45  ; var45 = nil
      74 [-]: SETTABLE R45 R43 R44; var45[var43] = var44
      75 [-]: LOADN R44 3  ; var44 = 3
      76 [-]: LOADNIL R45  ; var45 = nil
      77 [-]: SETTABLE R45 R43 R44; var45[var43] = var44
      78 [-]: LOADN R44 5  ; var44 = 5
      79 [-]: LOADNIL R45  ; var45 = nil
      80 [-]: SETTABLE R45 R43 R44; var45[var43] = var44
      81 [-]: LOADNIL R44  ; var44 = nil
      82 [-]: LOADNIL R45  ; var45 = nil
      83 [-]: LOADB R46 0  ; var46 = false
      84 [-]: GETIMPORT R47 15; var47 = 0x0469F296
      85 [-]: LOADK R48 K16; var48 = "Orokin"
      86 [-]: CALL R47 2 2 ; var47 = var47(var48)
      87 [-]: GETIMPORT R48 15; var48 = 0x0469F296
      88 [-]: LOADK R49 K17; var49 = "StatueBV"
      89 [-]: CALL R48 2 2 ; var48 = var48(var49)
      90 [-]: GETIMPORT R49 15; var49 = 0x0469F296
      91 [-]: LOADK R50 K18; var50 = "OPERATOR_TRANSFERENCE"
      92 [-]: CALL R49 2 2 ; var49 = var49(var50)
      93 [-]: LOADN R50 5  ; var50 = 5
      94 [-]: LOADN R51 0  ; var51 = 0
      95 [-]: LOADN R52 0  ; var52 = 0
      96 [-]: LOADN R53 0  ; var53 = 0
      97 [-]: DUPTABLE R54 35; 
      98 [-]: LOADK R55 K36; var55 = "/Lotus/Language/Duviri/DuviriQuest/StageTwoSelectWarframeObj"
      99 [-]: SETTABLEKS R55 R54 K19; var55["SELECT_WARFRAME_OBJ"] = var54
     100 [-]: LOADK R55 K37; var55 = "/Lotus/Language/Duviri/DuviriQuest/StageTwoEnterPortalObj"
     101 [-]: SETTABLEKS R55 R54 K20; var55["ENTER_POTAL_OBJ"] = var54
     102 [-]: LOADK R55 K38; var55 = "/Lotus/Language/Duviri/DuviriQuest/StageTwoMovementTutorialObj"
     103 [-]: SETTABLEKS R55 R54 K21; var55["MOVEMENT_TUTORIAL_OBJ"] = var54
     104 [-]: LOADK R55 K39; var55 = "/Lotus/Language/Duviri/DuviriQuest/StageTwoTestSuitObj"
     105 [-]: SETTABLEKS R55 R54 K22; var55["TEST_SUIT_OBJ"] = var54
     106 [-]: LOADK R55 K40; var55 = "/Lotus/Language/Duviri/DuviriQuest/StageTwoSelectSecondaryObj"
     107 [-]: SETTABLEKS R55 R54 K23; var55["SELECT_SECONDARY_OBJ"] = var54
     108 [-]: LOADK R55 K41; var55 = "/Lotus/Language/Duviri/DuviriQuest/StageTwoTestSecondaryObj"
     109 [-]: SETTABLEKS R55 R54 K24; var55["TEST_SECONDARY_OBJ"] = var54
     110 [-]: LOADK R55 K42; var55 = "/Lotus/Language/Duviri/DuviriQuest/StageTwoSelectPrimaryObj"
     111 [-]: SETTABLEKS R55 R54 K25; var55["SELECT_PRIMARY_OBJ"] = var54
     112 [-]: LOADK R55 K43; var55 = "/Lotus/Language/Duviri/DuviriQuest/StageTwoTestPrimaryObj"
     113 [-]: SETTABLEKS R55 R54 K26; var55["TEST_PRIMARY_OBJ"] = var54
     114 [-]: LOADK R55 K44; var55 = "/Lotus/Language/Duviri/DuviriQuest/StageTwoSelectMeleeObj"
     115 [-]: SETTABLEKS R55 R54 K27; var55["SELECT_MELEE_OBJ"] = var54
     116 [-]: LOADK R55 K45; var55 = "/Lotus/Language/Duviri/DuviriQuest/StageTwoTestMeleeObj"
     117 [-]: SETTABLEKS R55 R54 K28; var55["TEST_MELEE_OBJ"] = var54
     118 [-]: LOADK R55 K46; var55 = "/Lotus/Language/Duviri/DuviriQuest/StageTwoTestProgressBar"
     119 [-]: SETTABLEKS R55 R54 K29; var55["BATTLE_PROGRESS_BAR"] = var54
     120 [-]: LOADK R55 K47; var55 = "/Lotus/Language/Duviri/DuviriQuest/StageTwoSelectSecondaryAction"
     121 [-]: SETTABLEKS R55 R54 K30; var55["SELECT_SECONDARY_ACTION"] = var54
     122 [-]: LOADK R55 K48; var55 = "/Lotus/Language/Duviri/DuviriQuest/StageTwoEnergyTutorial"
     123 [-]: SETTABLEKS R55 R54 K31; var55["ENERGY_TUTORIAL"] = var54
     124 [-]: LOADK R55 K49; var55 = "/Lotus/Language/Duviri/DuviriQuest/StageTwoHealthTutorial"
     125 [-]: SETTABLEKS R55 R54 K32; var55["HEALTH_TUTORIAL"] = var54
     126 [-]: LOADK R55 K50; var55 = "/Lotus/Language/Duviri/DuviriQuest/StageTwoAmmoTutorial"
     127 [-]: SETTABLEKS R55 R54 K33; var55["AMMO_TUTORIAL"] = var54
     128 [-]: LOADK R55 K51; var55 = "/Lotus/Language/Duviri/DuviriQuest/StageTwoStayOrLeaveObj"
     129 [-]: SETTABLEKS R55 R54 K34; var55["SELECT_SECONDARY_EXIT_AVAILABLE_OBJ"] = var54
     130 [-]: DUPTABLE R55 65; 
     131 [-]: LOADN R56 1  ; var56 = 1
     132 [-]: SETTABLEKS R56 R55 K52; var56["SELECT_WARFRAME"] = var55
     133 [-]: LOADN R56 2  ; var56 = 2
     134 [-]: SETTABLEKS R56 R55 K53; var56["WARFRAME_SELECTED"] = var55
     135 [-]: LOADN R56 3  ; var56 = 3
     136 [-]: SETTABLEKS R56 R55 K54; var56["MOVEMENT_TUTORIAL"] = var55
     137 [-]: LOADN R56 4  ; var56 = 4
     138 [-]: SETTABLEKS R56 R55 K55; var56["TEST_SUIT"] = var55
     139 [-]: LOADN R56 5  ; var56 = 5
     140 [-]: SETTABLEKS R56 R55 K56; var56["SELECT_SECONDARY"] = var55
     141 [-]: LOADN R56 6  ; var56 = 6
     142 [-]: SETTABLEKS R56 R55 K57; var56["TEST_SECONDARY"] = var55
     143 [-]: LOADN R56 7  ; var56 = 7
     144 [-]: SETTABLEKS R56 R55 K58; var56["SELECT_PRIMARY"] = var55
     145 [-]: LOADN R56 8  ; var56 = 8
     146 [-]: SETTABLEKS R56 R55 K59; var56["TEST_PRIMARY"] = var55
     147 [-]: LOADN R56 9  ; var56 = 9
     148 [-]: SETTABLEKS R56 R55 K60; var56["SELECT_MELEE"] = var55
     149 [-]: LOADN R56 10 ; var56 = 10
     150 [-]: SETTABLEKS R56 R55 K61; var56["TEST_MELEE"] = var55
     151 [-]: LOADN R56 11 ; var56 = 11
     152 [-]: SETTABLEKS R56 R55 K62; var56["STAY_OR_LEAVE"] = var55
     153 [-]: LOADN R56 12 ; var56 = 12
     154 [-]: SETTABLEKS R56 R55 K63; var56["COMPLETE"] = var55
     155 [-]: LOADN R56 99 ; var56 = 99
     156 [-]: SETTABLEKS R56 R55 K64; var56["RESPAWN"] = var55
     157 [-]: NEWTABLE R56 16 0; var56 = {}
     158 [-]: GETTABLEKS R57 R55 K52; var57 = var55["SELECT_WARFRAME"]
     159 [-]: DUPTABLE R58 69; 
     160 [-]: LOADK R59 K70; var59 = "SelectWarframe"
     161 [-]: SETTABLEKS R59 R58 K66; var59["name"] = var58
     162 [-]: GETTABLEKS R59 R10 K71; var59 = var10["CAVE_SPAWN_TAG"]
     163 [-]: SETTABLEKS R59 R58 K67; var59["respawnPt"] = var58
     164 [-]: LOADB R59 1  ; var59 = true
     165 [-]: SETTABLEKS R59 R58 K68; var59["hasCheckpoint"] = var58
     166 [-]: SETTABLE R58 R56 R57; var58[var56] = var57
     167 [-]: GETTABLEKS R57 R55 K53; var57 = var55["WARFRAME_SELECTED"]
     168 [-]: DUPTABLE R58 72; 
     169 [-]: LOADK R59 K73; var59 = "WarframeSelected"
     170 [-]: SETTABLEKS R59 R58 K66; var59["name"] = var58
     171 [-]: SETTABLE R58 R56 R57; var58[var56] = var57
     172 [-]: GETTABLEKS R57 R55 K54; var57 = var55["MOVEMENT_TUTORIAL"]
     173 [-]: DUPTABLE R58 72; 
     174 [-]: LOADK R59 K74; var59 = "MovementTutorial"
     175 [-]: SETTABLEKS R59 R58 K66; var59["name"] = var58
     176 [-]: SETTABLE R58 R56 R57; var58[var56] = var57
     177 [-]: GETTABLEKS R57 R55 K55; var57 = var55["TEST_SUIT"]
     178 [-]: DUPTABLE R58 69; 
     179 [-]: LOADK R59 K75; var59 = "TestSuit"
     180 [-]: SETTABLEKS R59 R58 K66; var59["name"] = var58
     181 [-]: GETTABLEKS R59 R10 K76; var59 = var10["ARENA_SPAWN_TAG"]
     182 [-]: SETTABLEKS R59 R58 K67; var59["respawnPt"] = var58
     183 [-]: LOADB R59 1  ; var59 = true
     184 [-]: SETTABLEKS R59 R58 K68; var59["hasCheckpoint"] = var58
     185 [-]: SETTABLE R58 R56 R57; var58[var56] = var57
     186 [-]: GETTABLEKS R57 R55 K56; var57 = var55["SELECT_SECONDARY"]
     187 [-]: DUPTABLE R58 72; 
     188 [-]: LOADK R59 K77; var59 = "ChooseSecondary"
     189 [-]: SETTABLEKS R59 R58 K66; var59["name"] = var58
     190 [-]: SETTABLE R58 R56 R57; var58[var56] = var57
     191 [-]: GETTABLEKS R57 R55 K57; var57 = var55["TEST_SECONDARY"]
     192 [-]: DUPTABLE R58 72; 
     193 [-]: LOADK R59 K78; var59 = "TestSecondary"
     194 [-]: SETTABLEKS R59 R58 K66; var59["name"] = var58
     195 [-]: SETTABLE R58 R56 R57; var58[var56] = var57
     196 [-]: GETTABLEKS R57 R55 K58; var57 = var55["SELECT_PRIMARY"]
     197 [-]: DUPTABLE R58 72; 
     198 [-]: LOADK R59 K79; var59 = "ChoosePrimary"
     199 [-]: SETTABLEKS R59 R58 K66; var59["name"] = var58
     200 [-]: SETTABLE R58 R56 R57; var58[var56] = var57
     201 [-]: GETTABLEKS R57 R55 K59; var57 = var55["TEST_PRIMARY"]
     202 [-]: DUPTABLE R58 72; 
     203 [-]: LOADK R59 K80; var59 = "TestPrimary"
     204 [-]: SETTABLEKS R59 R58 K66; var59["name"] = var58
     205 [-]: SETTABLE R58 R56 R57; var58[var56] = var57
     206 [-]: GETTABLEKS R57 R55 K60; var57 = var55["SELECT_MELEE"]
     207 [-]: DUPTABLE R58 72; 
     208 [-]: LOADK R59 K81; var59 = "ChooseMelee"
     209 [-]: SETTABLEKS R59 R58 K66; var59["name"] = var58
     210 [-]: SETTABLE R58 R56 R57; var58[var56] = var57
     211 [-]: GETTABLEKS R57 R55 K61; var57 = var55["TEST_MELEE"]
     212 [-]: DUPTABLE R58 72; 
     213 [-]: LOADK R59 K82; var59 = "TestMelee"
     214 [-]: SETTABLEKS R59 R58 K66; var59["name"] = var58
     215 [-]: SETTABLE R58 R56 R57; var58[var56] = var57
     216 [-]: GETTABLEKS R57 R55 K62; var57 = var55["STAY_OR_LEAVE"]
     217 [-]: DUPTABLE R58 72; 
     218 [-]: LOADK R59 K83; var59 = "StayOrLeave"
     219 [-]: SETTABLEKS R59 R58 K66; var59["name"] = var58
     220 [-]: SETTABLE R58 R56 R57; var58[var56] = var57
     221 [-]: GETTABLEKS R57 R55 K63; var57 = var55["COMPLETE"]
     222 [-]: DUPTABLE R58 72; 
     223 [-]: LOADK R59 K84; var59 = "Complete"
     224 [-]: SETTABLEKS R59 R58 K66; var59["name"] = var58
     225 [-]: SETTABLE R58 R56 R57; var58[var56] = var57
     226 [-]: GETTABLEKS R57 R55 K64; var57 = var55["RESPAWN"]
     227 [-]: DUPTABLE R58 72; 
     228 [-]: LOADK R59 K85; var59 = "Respawn"
     229 [-]: SETTABLEKS R59 R58 K66; var59["name"] = var58
     230 [-]: SETTABLE R58 R56 R57; var58[var56] = var57
     231 [-]: NEWTABLE R57 8 0; var57 = {}
     232 [-]: GETTABLEKS R58 R55 K55; var58 = var55["TEST_SUIT"]
     233 [-]: LOADK R59 K86; var59 = "/Lotus/Language/Duviri/DuviriQuest/StageTwoSuitTutorial"
     234 [-]: SETTABLE R59 R57 R58; var59[var57] = var58
     235 [-]: GETTABLEKS R58 R55 K57; var58 = var55["TEST_SECONDARY"]
     236 [-]: LOADK R59 K87; var59 = "/Lotus/Language/Duviri/DuviriQuest/StageTwoSecondaryTutorial"
     237 [-]: SETTABLE R59 R57 R58; var59[var57] = var58
     238 [-]: GETTABLEKS R58 R55 K59; var58 = var55["TEST_PRIMARY"]
     239 [-]: LOADK R59 K88; var59 = "/Lotus/Language/Duviri/DuviriQuest/StageTwoPrimaryTutorial"
     240 [-]: SETTABLE R59 R57 R58; var59[var57] = var58
     241 [-]: GETTABLEKS R58 R55 K61; var58 = var55["TEST_MELEE"]
     242 [-]: LOADK R59 K89; var59 = "/Lotus/Language/Duviri/DuviriQuest/StageTwoMeleeTutorial"
     243 [-]: SETTABLE R59 R57 R58; var59[var57] = var58
     244 [-]: LOADK R58 K90; var58 = "/Lotus/Language/Duviri/DuviriQuest/StageTwoExcalTutorial"
     245 [-]: SETTABLEKS R58 R57 K91; var58["Excalibur"] = var57
     246 [-]: LOADK R58 K92; var58 = "/Lotus/Language/Duviri/DuviriQuest/StageTwoVoltTutorial"
     247 [-]: SETTABLEKS R58 R57 K93; var58["Volt"] = var57
     248 [-]: LOADK R58 K94; var58 = "/Lotus/Language/Duviri/DuviriQuest/StageTwoMagTutorial"
     249 [-]: SETTABLEKS R58 R57 K95; var58["Mag"] = var57
     250 [-]: NEWTABLE R58 8 0; var58 = {}
     251 [-]: GETTABLEKS R59 R55 K55; var59 = var55["TEST_SUIT"]
     252 [-]: LOADK R60 K96; var60 = "/Lotus/Language/Duviri/DuviriQuest/StageTwoSuitControllerTutorial"
     253 [-]: SETTABLE R60 R58 R59; var60[var58] = var59
     254 [-]: GETTABLEKS R59 R55 K57; var59 = var55["TEST_SECONDARY"]
     255 [-]: LOADK R60 K87; var60 = "/Lotus/Language/Duviri/DuviriQuest/StageTwoSecondaryTutorial"
     256 [-]: SETTABLE R60 R58 R59; var60[var58] = var59
     257 [-]: GETTABLEKS R59 R55 K59; var59 = var55["TEST_PRIMARY"]
     258 [-]: LOADK R60 K88; var60 = "/Lotus/Language/Duviri/DuviriQuest/StageTwoPrimaryTutorial"
     259 [-]: SETTABLE R60 R58 R59; var60[var58] = var59
     260 [-]: GETTABLEKS R59 R55 K61; var59 = var55["TEST_MELEE"]
     261 [-]: LOADK R60 K89; var60 = "/Lotus/Language/Duviri/DuviriQuest/StageTwoMeleeTutorial"
     262 [-]: SETTABLE R60 R58 R59; var60[var58] = var59
     263 [-]: LOADK R59 K97; var59 = "/Lotus/Language/Duviri/DuviriQuest/StageTwoExcalControllerTutorial"
     264 [-]: SETTABLEKS R59 R58 K91; var59["Excalibur"] = var58
     265 [-]: LOADK R59 K98; var59 = "/Lotus/Language/Duviri/DuviriQuest/StageTwoVoltControllerTutorial"
     266 [-]: SETTABLEKS R59 R58 K93; var59["Volt"] = var58
     267 [-]: LOADK R59 K99; var59 = "/Lotus/Language/Duviri/DuviriQuest/StageTwoMagControllerTutorial"
     268 [-]: SETTABLEKS R59 R58 K95; var59["Mag"] = var58
     269 [-]: DUPCLOSURE R59 K100; 
     270 [-]: DUPCLOSURE R60 K101; 
     271 [-]: CAPTURE VAL R56; 
     272 [-]: NEWCLOSURE R61 P2; 
     273 [-]: CAPTURE REF R18; 
     274 [-]: CAPTURE VAL R56; 
     275 [-]: NEWCLOSURE R62 P3; 
     276 [-]: CAPTURE REF R23; 
     277 [-]: CAPTURE VAL R55; 
     278 [-]: DUPCLOSURE R63 K102; 
     279 [-]: SETGLOBAL R63 K103; "ForceRespawn" = var63
     280 [-]: NEWCLOSURE R63 P5; 
     281 [-]: CAPTURE REF R22; 
     282 [-]: CAPTURE VAL R8; 
     283 [-]: CAPTURE VAL R2; 
     284 [-]: NEWCLOSURE R64 P6; 
     285 [-]: CAPTURE REF R21; 
     286 [-]: CAPTURE VAL R55; 
     287 [-]: CAPTURE REF R20; 
     288 [-]: CAPTURE VAL R9; 
     289 [-]: CAPTURE REF R25; 
     290 [-]: CAPTURE REF R22; 
     291 [-]: NEWCLOSURE R65 P7; 
     292 [-]: CAPTURE REF R34; 
     293 [-]: SETGLOBAL R65 K104; "OnTouched" = var65
     294 [-]: DUPCLOSURE R65 K105; 
     295 [-]: CAPTURE VAL R9; 
     296 [-]: SETGLOBAL R65 K106; "LoadAiSpec" = var65
     297 [-]: NEWCLOSURE R65 P9; 
     298 [-]: CAPTURE REF R28; 
     299 [-]: CAPTURE VAL R4; 
     300 [-]: SETGLOBAL R65 K107; "OnKilled" = var65
     301 [-]: DUPCLOSURE R65 K108; 
     302 [-]: NEWCLOSURE R66 P11; 
     303 [-]: CAPTURE REF R37; 
     304 [-]: CAPTURE REF R20; 
     305 [-]: CAPTURE REF R52; 
     306 [-]: NEWCLOSURE R67 P12; 
     307 [-]: CAPTURE REF R18; 
     308 [-]: CAPTURE VAL R55; 
     309 [-]: CAPTURE VAL R8; 
     310 [-]: CAPTURE VAL R58; 
     311 [-]: CAPTURE VAL R57; 
     312 [-]: CAPTURE VAL R43; 
     313 [-]: CAPTURE VAL R0; 
     314 [-]: NEWCLOSURE R68 P13; 
     315 [-]: CAPTURE REF R35; 
     316 [-]: NEWCLOSURE R69 P14; 
     317 [-]: CAPTURE REF R51; 
     318 [-]: CAPTURE VAL R67; 
     319 [-]: CAPTURE VAL R54; 
     320 [-]: CAPTURE REF R30; 
     321 [-]: CAPTURE REF R35; 
     322 [-]: CAPTURE VAL R66; 
     323 [-]: SETGLOBAL R69 K109; "EnergyTutorial" = var69
     324 [-]: NEWCLOSURE R69 P15; 
     325 [-]: CAPTURE REF R52; 
     326 [-]: CAPTURE VAL R1; 
     327 [-]: CAPTURE REF R15; 
     328 [-]: CAPTURE REF R20; 
     329 [-]: CAPTURE VAL R67; 
     330 [-]: CAPTURE VAL R54; 
     331 [-]: CAPTURE REF R31; 
     332 [-]: CAPTURE REF R35; 
     333 [-]: CAPTURE VAL R66; 
     334 [-]: CAPTURE REF R18; 
     335 [-]: CAPTURE VAL R55; 
     336 [-]: SETGLOBAL R69 K110; "HealthTutorial" = var69
     337 [-]: NEWCLOSURE R69 P16; 
     338 [-]: CAPTURE REF R53; 
     339 [-]: CAPTURE VAL R67; 
     340 [-]: CAPTURE VAL R54; 
     341 [-]: CAPTURE VAL R8; 
     342 [-]: CAPTURE REF R36; 
     343 [-]: CAPTURE REF R32; 
     344 [-]: CAPTURE REF R35; 
     345 [-]: CAPTURE VAL R66; 
     346 [-]: SETGLOBAL R69 K111; "AmmoTutorial" = var69
     347 [-]: NEWCLOSURE R69 P17; 
     348 [-]: CAPTURE REF R13; 
     349 [-]: CAPTURE REF R25; 
     350 [-]: CAPTURE REF R20; 
     351 [-]: NEWCLOSURE R70 P18; 
     352 [-]: CAPTURE REF R29; 
     353 [-]: CAPTURE REF R50; 
     354 [-]: CAPTURE REF R13; 
     355 [-]: CAPTURE VAL R47; 
     356 [-]: CAPTURE REF R41; 
     357 [-]: NEWCLOSURE R71 P19; 
     358 [-]: CAPTURE REF R20; 
     359 [-]: CAPTURE VAL R65; 
     360 [-]: CAPTURE REF R51; 
     361 [-]: CAPTURE REF R14; 
     362 [-]: CAPTURE REF R30; 
     363 [-]: CAPTURE REF R35; 
     364 [-]: NEWCLOSURE R72 P20; 
     365 [-]: CAPTURE REF R20; 
     366 [-]: CAPTURE REF R52; 
     367 [-]: CAPTURE REF R14; 
     368 [-]: CAPTURE REF R31; 
     369 [-]: CAPTURE REF R35; 
     370 [-]: NEWCLOSURE R73 P21; 
     371 [-]: CAPTURE REF R20; 
     372 [-]: CAPTURE REF R36; 
     373 [-]: CAPTURE REF R53; 
     374 [-]: CAPTURE REF R14; 
     375 [-]: CAPTURE REF R32; 
     376 [-]: CAPTURE VAL R8; 
     377 [-]: CAPTURE REF R35; 
     378 [-]: NEWCLOSURE R74 P22; 
     379 [-]: CAPTURE REF R30; 
     380 [-]: CAPTURE REF R31; 
     381 [-]: CAPTURE REF R32; 
     382 [-]: NEWCLOSURE R75 P23; 
     383 [-]: CAPTURE VAL R10; 
     384 [-]: CAPTURE VAL R8; 
     385 [-]: CAPTURE VAL R54; 
     386 [-]: CAPTURE VAL R11; 
     387 [-]: CAPTURE REF R20; 
     388 [-]: CAPTURE REF R15; 
     389 [-]: CAPTURE VAL R6; 
     390 [-]: CAPTURE REF R27; 
     391 [-]: CAPTURE VAL R1; 
     392 [-]: CAPTURE REF R24; 
     393 [-]: CAPTURE VAL R43; 
     394 [-]: CAPTURE REF R42; 
     395 [-]: CAPTURE REF R17; 
     396 [-]: CAPTURE VAL R55; 
     397 [-]: SETGLOBAL R75 K70; "SelectWarframe" = var75
     398 [-]: DUPCLOSURE R75 K112; 
     399 [-]: NEWCLOSURE R76 P25; 
     400 [-]: CAPTURE VAL R75; 
     401 [-]: CAPTURE REF R14; 
     402 [-]: CAPTURE REF R25; 
     403 [-]: CAPTURE VAL R10; 
     404 [-]: CAPTURE REF R35; 
     405 [-]: CAPTURE VAL R69; 
     406 [-]: NEWCLOSURE R77 P26; 
     407 [-]: CAPTURE VAL R4; 
     408 [-]: CAPTURE VAL R43; 
     409 [-]: CAPTURE VAL R48; 
     410 [-]: CAPTURE REF R24; 
     411 [-]: CAPTURE REF R20; 
     412 [-]: CAPTURE VAL R9; 
     413 [-]: CAPTURE REF R39; 
     414 [-]: CAPTURE VAL R6; 
     415 [-]: CAPTURE REF R26; 
     416 [-]: CAPTURE VAL R10; 
     417 [-]: CAPTURE REF R27; 
     418 [-]: CAPTURE VAL R54; 
     419 [-]: CAPTURE VAL R3; 
     420 [-]: CAPTURE REF R19; 
     421 [-]: CAPTURE REF R17; 
     422 [-]: CAPTURE VAL R55; 
     423 [-]: SETGLOBAL R77 K73; "WarframeSelected" = var77
     424 [-]: DUPCLOSURE R77 K113; 
     425 [-]: CAPTURE VAL R49; 
     426 [-]: NEWCLOSURE R78 P28; 
     427 [-]: CAPTURE VAL R77; 
     428 [-]: CAPTURE VAL R4; 
     429 [-]: CAPTURE VAL R54; 
     430 [-]: CAPTURE VAL R76; 
     431 [-]: CAPTURE REF R34; 
     432 [-]: CAPTURE VAL R1; 
     433 [-]: CAPTURE REF R15; 
     434 [-]: CAPTURE VAL R10; 
     435 [-]: CAPTURE REF R26; 
     436 [-]: CAPTURE VAL R9; 
     437 [-]: CAPTURE VAL R3; 
     438 [-]: CAPTURE REF R19; 
     439 [-]: CAPTURE REF R17; 
     440 [-]: CAPTURE VAL R55; 
     441 [-]: SETGLOBAL R78 K74; "MovementTutorial" = var78
     442 [-]: NEWCLOSURE R78 P29; 
     443 [-]: CAPTURE REF R46; 
     444 [-]: CAPTURE VAL R10; 
     445 [-]: CAPTURE VAL R77; 
     446 [-]: CAPTURE REF R20; 
     447 [-]: SETGLOBAL R78 K114; "RespawnWarframe" = var78
     448 [-]: NEWCLOSURE R78 P30; 
     449 [-]: CAPTURE REF R41; 
     450 [-]: NEWCLOSURE R79 P31; 
     451 [-]: CAPTURE REF R38; 
     452 [-]: CAPTURE REF R27; 
     453 [-]: CAPTURE REF R26; 
     454 [-]: CAPTURE VAL R9; 
     455 [-]: CAPTURE REF R20; 
     456 [-]: CAPTURE VAL R1; 
     457 [-]: CAPTURE REF R15; 
     458 [-]: CAPTURE VAL R4; 
     459 [-]: CAPTURE VAL R54; 
     460 [-]: CAPTURE REF R40; 
     461 [-]: CAPTURE VAL R67; 
     462 [-]: CAPTURE REF R28; 
     463 [-]: CAPTURE VAL R70; 
     464 [-]: CAPTURE VAL R71; 
     465 [-]: CAPTURE VAL R72; 
     466 [-]: CAPTURE REF R37; 
     467 [-]: CAPTURE VAL R78; 
     468 [-]: CAPTURE REF R17; 
     469 [-]: CAPTURE VAL R55; 
     470 [-]: SETGLOBAL R79 K75; "TestSuit" = var79
     471 [-]: NEWCLOSURE R79 P32; 
     472 [-]: CAPTURE VAL R43; 
     473 [-]: CAPTURE REF R44; 
     474 [-]: CAPTURE VAL R10; 
     475 [-]: DUPCLOSURE R80 K115; 
     476 [-]: CAPTURE VAL R54; 
     477 [-]: CAPTURE VAL R8; 
     478 [-]: SETGLOBAL R80 K116; "SetupWeaponSelection" = var80
     479 [-]: NEWCLOSURE R80 P34; 
     480 [-]: CAPTURE REF R27; 
     481 [-]: NEWCLOSURE R81 P35; 
     482 [-]: CAPTURE VAL R1; 
     483 [-]: CAPTURE REF R15; 
     484 [-]: CAPTURE VAL R4; 
     485 [-]: CAPTURE VAL R54; 
     486 [-]: CAPTURE VAL R80; 
     487 [-]: CAPTURE REF R44; 
     488 [-]: CAPTURE REF R27; 
     489 [-]: CAPTURE REF R17; 
     490 [-]: CAPTURE VAL R55; 
     491 [-]: SETGLOBAL R81 K117; "SelectSecondary" = var81
     492 [-]: NEWCLOSURE R81 P36; 
     493 [-]: CAPTURE VAL R4; 
     494 [-]: CAPTURE VAL R54; 
     495 [-]: CAPTURE VAL R80; 
     496 [-]: CAPTURE REF R44; 
     497 [-]: CAPTURE REF R27; 
     498 [-]: CAPTURE REF R17; 
     499 [-]: CAPTURE VAL R55; 
     500 [-]: SETGLOBAL R81 K118; "SelectPrimary" = var81
     501 [-]: NEWCLOSURE R81 P37; 
     502 [-]: CAPTURE VAL R4; 
     503 [-]: CAPTURE VAL R54; 
     504 [-]: CAPTURE VAL R80; 
     505 [-]: CAPTURE REF R44; 
     506 [-]: CAPTURE REF R27; 
     507 [-]: CAPTURE REF R17; 
     508 [-]: CAPTURE VAL R55; 
     509 [-]: SETGLOBAL R81 K119; "SelectMelee" = var81
     510 [-]: NEWCLOSURE R81 P38; 
     511 [-]: CAPTURE VAL R4; 
     512 [-]: CAPTURE VAL R54; 
     513 [-]: CAPTURE REF R18; 
     514 [-]: CAPTURE VAL R55; 
     515 [-]: CAPTURE VAL R67; 
     516 [-]: CAPTURE REF R28; 
     517 [-]: CAPTURE VAL R70; 
     518 [-]: CAPTURE REF R20; 
     519 [-]: CAPTURE VAL R73; 
     520 [-]: CAPTURE VAL R72; 
     521 [-]: CAPTURE REF R37; 
     522 [-]: CAPTURE REF R30; 
     523 [-]: CAPTURE REF R31; 
     524 [-]: CAPTURE REF R32; 
     525 [-]: CAPTURE VAL R78; 
     526 [-]: NEWCLOSURE R82 P39; 
     527 [-]: CAPTURE VAL R4; 
     528 [-]: CAPTURE VAL R54; 
     529 [-]: CAPTURE VAL R81; 
     530 [-]: CAPTURE REF R17; 
     531 [-]: CAPTURE VAL R55; 
     532 [-]: SETGLOBAL R82 K78; "TestSecondary" = var82
     533 [-]: NEWCLOSURE R82 P40; 
     534 [-]: CAPTURE VAL R4; 
     535 [-]: CAPTURE VAL R54; 
     536 [-]: CAPTURE REF R53; 
     537 [-]: CAPTURE VAL R81; 
     538 [-]: CAPTURE REF R17; 
     539 [-]: CAPTURE VAL R55; 
     540 [-]: SETGLOBAL R82 K80; "TestPrimary" = var82
     541 [-]: NEWCLOSURE R82 P41; 
     542 [-]: CAPTURE VAL R4; 
     543 [-]: CAPTURE VAL R54; 
     544 [-]: CAPTURE VAL R81; 
     545 [-]: CAPTURE VAL R1; 
     546 [-]: CAPTURE REF R15; 
     547 [-]: CAPTURE REF R17; 
     548 [-]: CAPTURE VAL R55; 
     549 [-]: SETGLOBAL R82 K82; "TestMelee" = var82
     550 [-]: NEWCLOSURE R82 P42; 
     551 [-]: CAPTURE VAL R10; 
     552 [-]: CAPTURE REF R26; 
     553 [-]: CAPTURE VAL R9; 
     554 [-]: CAPTURE REF R33; 
     555 [-]: CAPTURE VAL R8; 
     556 [-]: NEWCLOSURE R83 P43; 
     557 [-]: CAPTURE VAL R4; 
     558 [-]: CAPTURE VAL R54; 
     559 [-]: CAPTURE VAL R82; 
     560 [-]: CAPTURE REF R44; 
     561 [-]: CAPTURE REF R45; 
     562 [-]: CAPTURE REF R17; 
     563 [-]: CAPTURE VAL R55; 
     564 [-]: CAPTURE REF R33; 
     565 [-]: CAPTURE VAL R9; 
     566 [-]: CAPTURE REF R26; 
     567 [-]: CAPTURE VAL R81; 
     568 [-]: SETGLOBAL R83 K83; "StayOrLeave" = var83
     569 [-]: NEWCLOSURE R83 P44; 
     570 [-]: CAPTURE VAL R43; 
     571 [-]: CAPTURE REF R14; 
     572 [-]: SETGLOBAL R83 K84; "Complete" = var83
     573 [-]: DUPCLOSURE R83 K120; 
     574 [-]: CAPTURE VAL R48; 
     575 [-]: SETGLOBAL R83 K121; "SetupWarframes" = var83
     576 [-]: NEWCLOSURE R83 P46; 
     577 [-]: CAPTURE VAL R55; 
     578 [-]: CAPTURE REF R18; 
     579 [-]: CAPTURE VAL R56; 
     580 [-]: CAPTURE REF R23; 
     581 [-]: CAPTURE VAL R76; 
     582 [-]: CAPTURE REF R20; 
     583 [-]: CAPTURE VAL R9; 
     584 [-]: CAPTURE REF R25; 
     585 [-]: CAPTURE VAL R6; 
     586 [-]: CAPTURE REF R24; 
     587 [-]: CAPTURE VAL R43; 
     588 [-]: CAPTURE VAL R10; 
     589 [-]: CAPTURE REF R44; 
     590 [-]: CAPTURE VAL R77; 
     591 [-]: CAPTURE REF R14; 
     592 [-]: CAPTURE REF R42; 
     593 [-]: CAPTURE VAL R4; 
     594 [-]: CAPTURE REF R21; 
     595 [-]: CAPTURE VAL R2; 
     596 [-]: NEWCLOSURE R84 P47; 
     597 [-]: CAPTURE REF R21; 
     598 [-]: CAPTURE REF R18; 
     599 [-]: CAPTURE REF R17; 
     600 [-]: CAPTURE VAL R55; 
     601 [-]: CAPTURE REF R23; 
     602 [-]: CAPTURE REF R16; 
     603 [-]: CAPTURE REF R46; 
     604 [-]: CAPTURE REF R19; 
     605 [-]: CAPTURE REF R14; 
     606 [-]: CAPTURE REF R51; 
     607 [-]: CAPTURE REF R52; 
     608 [-]: CAPTURE REF R40; 
     609 [-]: CAPTURE REF R38; 
     610 [-]: CAPTURE VAL R67; 
     611 [-]: NEWCLOSURE R85 P48; 
     612 [-]: CAPTURE REF R14; 
     613 [-]: CAPTURE REF R12; 
     614 [-]: CAPTURE REF R15; 
     615 [-]: CAPTURE REF R13; 
     616 [-]: CAPTURE REF R16; 
     617 [-]: CAPTURE VAL R5; 
     618 [-]: CAPTURE REF R17; 
     619 [-]: CAPTURE VAL R3; 
     620 [-]: CAPTURE VAL R83; 
     621 [-]: CAPTURE REF R19; 
     622 [-]: CAPTURE REF R20; 
     623 [-]: CAPTURE VAL R6; 
     624 [-]: CAPTURE VAL R63; 
     625 [-]: CAPTURE VAL R64; 
     626 [-]: CAPTURE REF R42; 
     627 [-]: CAPTURE VAL R10; 
     628 [-]: CAPTURE REF R45; 
     629 [-]: CAPTURE REF R39; 
     630 [-]: CAPTURE VAL R79; 
     631 [-]: CAPTURE VAL R75; 
     632 [-]: CAPTURE VAL R43; 
     633 [-]: CAPTURE REF R24; 
     634 [-]: CAPTURE VAL R2; 
     635 [-]: CAPTURE VAL R55; 
     636 [-]: CAPTURE VAL R62; 
     637 [-]: NEWCLOSURE R86 P49; 
     638 [-]: CAPTURE VAL R85; 
     639 [-]: CAPTURE REF R14; 
     640 [-]: CAPTURE REF R18; 
     641 [-]: CAPTURE REF R17; 
     642 [-]: CAPTURE VAL R84; 
     643 [-]: SETGLOBAL R86 K122; "StartEncounter" = var86
     644 [-]: NEWCLOSURE R86 P50; 
     645 [-]: CAPTURE REF R18; 
     646 [-]: CAPTURE VAL R55; 
     647 [-]: CAPTURE VAL R43; 
     648 [-]: CAPTURE REF R24; 
     649 [-]: CAPTURE VAL R10; 
     650 [-]: CAPTURE REF R17; 
     651 [-]: CAPTURE VAL R77; 
     652 [-]: SETGLOBAL R86 K123; "OnActivated" = var86
     653 [-]: DUPCLOSURE R86 K124; 
     654 [-]: SETGLOBAL R86 K125; "OnWeaponSelected" = var86
     655 [-]: CLOSEUPVALS R12; 
     656 [-]: RETURN R0 0  ; 


; Name:            
; Defined at line: 210
; #Upvalues:       0
; #Parameters:     0
; Is_vararg:       0
; Max Stack Size:  1

       0 [-]: LOADB R0 0   ; var0 = false
       1 [-]: RETURN R0 1  ; 


; Name:            
; Defined at line: 214
; #Upvalues:       1
; #Parameters:     1
; Is_vararg:       0
; Max Stack Size:  4

       0 [-]: GETUPVAL R3 0; var3 = upvalues[0]
       1 [-]: GETTABLE R2 R3 R0; var2 = var3[var0]
       2 [-]: GETTABLEKS R1 R2 K0; var1 = var2["name"]
       3 [-]: RETURN R1 1  ; 


; Name:            
; Defined at line: 218
; #Upvalues:       2
; #Parameters:     1
; Is_vararg:       0
; Max Stack Size:  9

       0 [-]: MOVE R1 R0   ; var1 = var0
       1 [-]: JUMPIF R1 L0 ; goto L0 if var1
       2 [-]: GETUPVAL R1 0; var1 = upvalues[0]
L 0:   3 [-]: MOVE R0 R1   ; var0 = var1
       4 [-]: JUMPXEQKN R0 K0 L1 NOT; 
       5 [-]: RETURN R0 0  ; 
L 1:   6 [-]: LOADK R2 K1  ; var2 = "[DEBUG] Stage: "
       7 [-]: MOVE R3 R0   ; var3 = var0
       8 [-]: LOADK R4 K2  ; var4 = " "
       9 [-]: MOVE R6 R0   ; var6 = var0
      10 [-]: GETUPVAL R8 1; var8 = upvalues[1]
      11 [-]: GETTABLE R7 R8 R6; var7 = var8[var6]
      12 [-]: GETTABLEKS R5 R7 K3; var5 = var7["name"]
      13 [-]: CONCAT R1 R2 R5; var1 = var2 .. var5
      14 [-]: GETIMPORT R2 5; var2 = 0x3D106989
      15 [-]: MOVE R3 R1   ; var3 = var1
      16 [-]: CALL R2 2 1  ; var2(var3)
      17 [-]: RETURN R0 0  ; 


; Name:            
; Defined at line: 227
; #Upvalues:       2
; #Parameters:     1
; Is_vararg:       0
; Max Stack Size:  3

       0 [-]: JUMPXEQKS R0 K0 L0 NOT; 
       1 [-]: GETUPVAL R2 1; var2 = upvalues[1]
       2 [-]: GETTABLEKS R1 R2 K1; var1 = var2["SELECT_WARFRAME"]
       3 [-]: SETUPVAL R1 0; upvalues[1] = var0
       4 [-]: RETURN R0 0  ; 
L 0:   5 [-]: GETUPVAL R2 1; var2 = upvalues[1]
       6 [-]: GETTABLE R1 R2 R0; var1 = var2[var0]
       7 [-]: SETUPVAL R1 0; upvalues[1] = var0
       8 [-]: RETURN R0 0  ; 


; Name:            
; Defined at line: 236
; #Upvalues:       0
; #Parameters:     0
; Is_vararg:       0
; Max Stack Size:  7

       0 [-]: GETIMPORT R0 1; var0 = 0x89326C93
       1 [-]: NAMECALL R0 R0 K2; var1 = var0; var0 = var0[0x78298275]
       2 [-]: CALL R0 2 2  ; var0 = var0(var1)
       3 [-]: FASTCALL1 64 R0 L0; 
       4 [-]: MOVE R2 R0   ; var2 = var0
       5 [-]: GETIMPORT R1 4; var1 = 0x7B998233
       6 [-]: CALL R1 2 2  ; var1 = var1(var2)
L 0:   7 [-]: JUMPIF R1 L2 ; goto L2 if var1
       8 [-]: GETIMPORT R3 6; var3 = gLotusVehicleAvatarType
       9 [-]: NAMECALL R1 R0 K7; var2 = var0; var1 = var0[0xF2DEAF69]
      10 [-]: CALL R1 3 2  ; var1 = var1(var2, var3)
      11 [-]: JUMPIFNOT R1 L1; goto L1 if not var1
      12 [-]: NAMECALL R1 R0 K8; var2 = var0; var1 = var0[0xFF005826]
      13 [-]: CALL R1 2 2  ; var1 = var1(var2)
      14 [-]: MOVE R0 R1   ; var0 = var1
L 1:  15 [-]: GETIMPORT R3 10; var3 = 0x0469F296
      16 [-]: LOADK R4 K11 ; var4 = "AdultOperator"
      17 [-]: CALL R3 2 0  ; var3, ... = var3(var4)
      18 [-]: NAMECALL R1 R0 K12; var2 = var0; var1 = var0[0x26D544FC]
      19 [-]: CALL R1 0 1  ; var1(var2, ...)
      20 [-]: NAMECALL R2 R0 K14; var3 = var0; var2 = var0[0xB40C191A]
      21 [-]: CALL R2 2 2  ; var2 = var2(var3)
      22 [-]: MULK R1 R2 K13; var1 = var2 * 2
      23 [-]: GETIMPORT R2 17; var2 = 0x34291F5C[0x35C16153]
      24 [-]: CALL R2 1 2  ; var2 = var2()
      25 [-]: GETIMPORT R5 19; var5 = 0x34291F5C[0x7258F36F]
      26 [-]: MOVE R6 R1   ; var6 = var1
      27 [-]: CALL R5 2 0  ; var5, ... = var5(var6)
      28 [-]: NAMECALL R3 R2 K20; var4 = var2; var3 = var2[0xF326045F]
      29 [-]: CALL R3 0 1  ; var3(var4, ...)
      30 [-]: LOADN R5 17  ; var5 = 17
      31 [-]: LOADN R6 1   ; var6 = 1
      32 [-]: NAMECALL R3 R2 K21; var4 = var2; var3 = var2[0x1586E35E]
      33 [-]: CALL R3 4 1  ; var3(var4, var5, var6)
      34 [-]: MOVE R5 R2   ; var5 = var2
      35 [-]: NAMECALL R3 R0 K22; var4 = var0; var3 = var0[0x479483BB]
      36 [-]: CALL R3 3 1  ; var3(var4, var5)
L 2:  37 [-]: RETURN R0 0  ; 


; Name:            
; Defined at line: 251
; #Upvalues:       3
; #Parameters:     0
; Is_vararg:       0
; Max Stack Size:  3

       0 [-]: LOADNIL R0   ; var0 = nil
       1 [-]: SETUPVAL R0 0; upvalues[0] = var0
       2 [-]: GETIMPORT R1 1; var1 = 0xB227841D
       3 [-]: FASTCALL1 64 R1 L0; 
       4 [-]: GETIMPORT R0 3; var0 = 0x7B998233
       5 [-]: CALL R0 2 2  ; var0 = var0(var1)
L 0:   6 [-]: JUMPIF R0 L1 ; goto L1 if var0
       7 [-]: GETUPVAL R0 0; var0 = upvalues[0]
       8 [-]: JUMPXEQKNIL R0 L1 NOT; 
       9 [-]: GETUPVAL R1 1; var1 = upvalues[1]
      10 [-]: GETTABLEKS R0 R1 K4; var0 = var1[0x659D451F]
      11 [-]: GETIMPORT R1 1; var1 = 0xB227841D
      12 [-]: CALL R0 2 2  ; var0 = var0(var1)
      13 [-]: SETUPVAL R0 0; upvalues[0] = var0
L 1:  14 [-]: GETUPVAL R1 2; var1 = upvalues[2]
      15 [-]: GETTABLEKS R0 R1 K5; var0 = var1[0xC474A99E]
      16 [-]: GETIMPORT R1 7; var1 = 0x0469F296
      17 [-]: LOADK R2 K8  ; var2 = "DuviriMusicTownCombat"
      18 [-]: CALL R1 2 2  ; var1 = var1(var2)
      19 [-]: LOADK R2 K9  ; var2 = "Disable"
      20 [-]: CALL R0 3 1  ; var0(var1, var2)
      21 [-]: GETUPVAL R1 2; var1 = upvalues[2]
      22 [-]: GETTABLEKS R0 R1 K5; var0 = var1[0xC474A99E]
      23 [-]: GETIMPORT R1 7; var1 = 0x0469F296
      24 [-]: LOADK R2 K10 ; var2 = "DuviriTownSoundSeqDisable"
      25 [-]: CALL R1 2 2  ; var1 = var1(var2)
      26 [-]: LOADK R2 K9  ; var2 = "Disable"
      27 [-]: CALL R0 3 1  ; var0(var1, var2)
      28 [-]: RETURN R0 0  ; 


; Name:            
; Defined at line: 266
; #Upvalues:       6
; #Parameters:     0
; Is_vararg:       0
; Max Stack Size:  5

       0 [-]: GETUPVAL R0 0; var0 = upvalues[0]
       1 [-]: GETUPVAL R2 1; var2 = upvalues[1]
       2 [-]: GETTABLEKS R1 R2 K0; var1 = var2["TEST_SUIT"]
       3 [-]: JUMPIFNOTLE R1 R0 L0; goto L0 if var1 > var196924
       4 [-]: GETUPVAL R1 3; var1 = upvalues[3]
       5 [-]: GETTABLEKS R0 R1 K1; var0 = var1[0x3DF1EF0C]
       6 [-]: LOADB R1 1   ; var1 = true
       7 [-]: GETUPVAL R2 4; var2 = upvalues[4]
       8 [-]: GETIMPORT R3 3; var3 = 0x89326C93
       9 [-]: NAMECALL R3 R3 K4; var4 = var3; var3 = var3[0x78298275]
      10 [-]: CALL R3 2 0  ; var3, ... = var3(var4)
      11 [-]: CALL R0 0 2  ; var0 = var0(var1, ...)
      12 [-]: SETUPVAL R0 2; upvalues[0] = var2
L 0:  13 [-]: GETUPVAL R1 5; var1 = upvalues[5]
      14 [-]: FASTCALL1 64 R1 L1; 
      15 [-]: GETIMPORT R0 6; var0 = 0x7B998233
      16 [-]: CALL R0 2 2  ; var0 = var0(var1)
L 1:  17 [-]: JUMPIF R0 L2 ; goto L2 if var0
      18 [-]: GETUPVAL R0 5; var0 = upvalues[5]
      19 [-]: LOADB R2 0   ; var2 = false
      20 [-]: NAMECALL R0 R0 K7; var1 = var0; var0 = var0[0x6CF1E476]
      21 [-]: CALL R0 3 1  ; var0(var1, var2)
L 2:  22 [-]: GETIMPORT R0 9; var0 = _T
      23 [-]: LOADN R1 999 ; var1 = 999
      24 [-]: SETTABLEKS R1 R0 K10; var1["RespawnTime"] = var0
      25 [-]: RETURN R0 0  ; 


; Name:            
; Defined at line: 279
; #Upvalues:       1
; #Parameters:     1
; Is_vararg:       0
; Max Stack Size:  2

       0 [-]: LOADB R1 1   ; var1 = true
       1 [-]: SETUPVAL R1 0; upvalues[1] = var0
       2 [-]: RETURN R0 0  ; 


; Name:            
; Defined at line: 284
; #Upvalues:       1
; #Parameters:     0
; Is_vararg:       0
; Max Stack Size:  3

       0 [-]: GETUPVAL R1 0; var1 = upvalues[0]
       1 [-]: GETTABLEKS R0 R1 K0; var0 = var1[0x81192D1F]
       2 [-]: GETIMPORT R1 2; var1 = 0x57121901
       3 [-]: LOADB R2 1   ; var2 = true
       4 [-]: CALL R0 3 1  ; var0(var1, var2)
       5 [-]: RETURN R0 0  ; 


; Name:            
; Defined at line: 288
; #Upvalues:       2
; #Parameters:     1
; Is_vararg:       0
; Max Stack Size:  4

       0 [-]: GETUPVAL R2 0; var2 = upvalues[0]
       1 [-]: ADDK R1 R2 K0; var1 = var2 + 1
       2 [-]: SETUPVAL R1 0; upvalues[1] = var0
       3 [-]: GETUPVAL R2 1; var2 = upvalues[1]
       4 [-]: GETTABLEKS R1 R2 K1; var1 = var2[0xF3928F38]
       5 [-]: GETUPVAL R2 0; var2 = upvalues[0]
       6 [-]: LOADN R3 5   ; var3 = 5
       7 [-]: CALL R1 3 1  ; var1(var2, var3)
       8 [-]: RETURN R0 0  ; 


; Name:            
; Defined at line: 293
; #Upvalues:       0
; #Parameters:     1
; Is_vararg:       0
; Max Stack Size:  11

       0 [-]: FASTCALL1 64 R0 L0; 
       1 [-]: MOVE R2 R0   ; var2 = var0
       2 [-]: GETIMPORT R1 1; var1 = 0x7B998233
       3 [-]: CALL R1 2 2  ; var1 = var1(var2)
L 0:   4 [-]: JUMPIFNOT R1 L1; goto L1 if not var1
       5 [-]: LOADN R1 0   ; var1 = 0
       6 [-]: RETURN R1 1  ; 
L 1:   7 [-]: NAMECALL R1 R0 K2; var2 = var0; var1 = var0[0x3C88E434]
       8 [-]: CALL R1 2 2  ; var1 = var1(var2)
       9 [-]: LOADN R2 0   ; var2 = 0
      10 [-]: GETIMPORT R3 4; var3 = 0xC8802016
      11 [-]: MOVE R4 R1   ; var4 = var1
      12 [-]: CALL R3 2 4  ; var3, var4, var5 = var3(var4)
      13 [-]: FORGPREP_INEXT R3 L3; 
L 2:  14 [-]: NAMECALL R8 R0 K5; var9 = var0; var8 = var0[0x58A4D5AC]
      15 [-]: CALL R8 2 2  ; var8 = var8(var9)
      16 [-]: NAMECALL R9 R7 K6; var10 = var7; var9 = var7[0x7E627183]
      17 [-]: CALL R9 2 2  ; var9 = var9(var10)
      18 [-]: JUMPIFNOTLE R9 R8 L3; goto L3 if var9 > var117572104
      19 [-]: ADDK R2 R2 K7; var2 = var2 + 1
L 3:  20 [-]: FORGLOOP R3 L2 2 [inext]; 
      21 [-]: RETURN R2 1  ; 


; Name:            
; Defined at line: 310
; #Upvalues:       3
; #Parameters:     1
; Is_vararg:       0
; Max Stack Size:  3

L 0:   0 [-]: FASTCALL1 64 R0 L1; 
       1 [-]: MOVE R2 R0   ; var2 = var0
       2 [-]: GETIMPORT R1 1; var1 = 0x7B998233
       3 [-]: CALL R1 2 2  ; var1 = var1(var2)
L 1:   4 [-]: JUMPIF R1 L5 ; goto L5 if var1
       5 [-]: GETUPVAL R1 0; var1 = upvalues[0]
       6 [-]: JUMPIF R1 L3 ; goto L3 if var1
       7 [-]: GETUPVAL R2 1; var2 = upvalues[1]
       8 [-]: FASTCALL1 64 R2 L2; 
       9 [-]: GETIMPORT R1 1; var1 = 0x7B998233
      10 [-]: CALL R1 2 2  ; var1 = var1(var2)
L 2:  11 [-]: JUMPIF R1 L3 ; goto L3 if var1
      12 [-]: GETUPVAL R1 2; var1 = upvalues[2]
      13 [-]: JUMPXEQKN R1 K2 L4 NOT; 
      14 [-]: GETUPVAL R1 1; var1 = upvalues[1]
      15 [-]: NAMECALL R1 R1 K3; var2 = var1; var1 = var1[0xC8442850]
      16 [-]: CALL R1 2 2  ; var1 = var1(var2)
      17 [-]: LOADN R2 1   ; var2 = 1
      18 [-]: JUMPIFNOTLE R2 R1 L4; goto L4 if var2 > var262
L 3:  19 [-]: LOADB R1 0   ; var1 = false
      20 [-]: SETUPVAL R1 0; upvalues[1] = var0
      21 [-]: GETIMPORT R1 6; var1 = _T["HideImpactMessage"]
      22 [-]: CALL R1 1 1  ; var1()
      23 [-]: NAMECALL R1 R0 K7; var2 = var0; var1 = var0[0xA2880940]
      24 [-]: CALL R1 2 1  ; var1(var2)
      25 [-]: LOADB R1 0   ; var1 = false
      26 [-]: RETURN R1 1  ; 
L 4:  27 [-]: GETIMPORT R1 9; var1 = 0xCBD666E1
      28 [-]: LOADN R2 0   ; var2 = 0
      29 [-]: CALL R1 2 1  ; var1(var2)
      30 [-]: JUMPBACK L0  ; goto L0
L 5:  31 [-]: LOADB R1 1   ; var1 = true
      32 [-]: RETURN R1 1  ; 


; Name:            
; Defined at line: 324
; #Upvalues:       7
; #Parameters:     1
; Is_vararg:       0
; Max Stack Size:  8

       0 [-]: LOADNIL R1   ; var1 = nil
       1 [-]: GETUPVAL R2 0; var2 = upvalues[0]
       2 [-]: GETUPVAL R4 1; var4 = upvalues[1]
       3 [-]: GETTABLEKS R3 R4 K0; var3 = var4["TEST_SUIT"]
       4 [-]: JUMPIFNOTLT R3 R2 L1; goto L1 if var3 >= var558
       5 [-]: MOVE R2 R0   ; var2 = var0
       6 [-]: JUMPIF R2 L0 ; goto L0 if var2
       7 [-]: GETUPVAL R3 2; var3 = upvalues[2]
       8 [-]: GETTABLEKS R2 R3 K1; var2 = var3[0x06D055F9]
       9 [-]: GETIMPORT R3 4; var3 = 0x34291F5C[0x1467D5F4]
      10 [-]: CALL R3 1 2  ; var3 = var3()
      11 [-]: GETUPVAL R5 3; var5 = upvalues[3]
      12 [-]: GETUPVAL R6 0; var6 = upvalues[0]
      13 [-]: GETTABLE R4 R5 R6; var4 = var5[var6]
      14 [-]: GETUPVAL R6 4; var6 = upvalues[4]
      15 [-]: GETUPVAL R7 0; var7 = upvalues[0]
      16 [-]: GETTABLE R5 R6 R7; var5 = var6[var7]
      17 [-]: CALL R2 4 2  ; var2 = var2(var3, var4, var5)
L 0:  18 [-]: MOVE R1 R2   ; var1 = var2
      19 [-]: JUMP L2      ; goto L2
L 1:  20 [-]: GETUPVAL R3 5; var3 = upvalues[5]
      21 [-]: LOADN R4 3   ; var4 = 3
      22 [-]: GETTABLE R2 R3 R4; var2 = var3[var4]
      23 [-]: NAMECALL R2 R2 K5; var3 = var2; var2 = var2[0xE223E2B1]
      24 [-]: CALL R2 2 2  ; var2 = var2(var3)
      25 [-]: GETUPVAL R4 2; var4 = upvalues[2]
      26 [-]: GETTABLEKS R3 R4 K1; var3 = var4[0x06D055F9]
      27 [-]: GETIMPORT R4 4; var4 = 0x34291F5C[0x1467D5F4]
      28 [-]: CALL R4 1 2  ; var4 = var4()
      29 [-]: GETUPVAL R6 3; var6 = upvalues[3]
      30 [-]: GETTABLE R5 R6 R2; var5 = var6[var2]
      31 [-]: GETUPVAL R7 4; var7 = upvalues[4]
      32 [-]: GETTABLE R6 R7 R2; var6 = var7[var2]
      33 [-]: CALL R3 4 2  ; var3 = var3(var4, var5, var6)
      34 [-]: MOVE R1 R3   ; var1 = var3
L 2:  35 [-]: JUMPIF R1 L4 ; goto L4 if var1
      36 [-]: GETUPVAL R3 6; var3 = upvalues[6]
      37 [-]: GETTABLEKS R2 R3 K6; var2 = var3[0x8025D8E6]
      38 [-]: GETUPVAL R3 0; var3 = upvalues[0]
      39 [-]: GETUPVAL R4 1; var4 = upvalues[1]
      40 [-]: CALL R2 3 2  ; var2 = var2(var3, var4)
      41 [-]: JUMPIF R2 L3 ; goto L3 if var2
      42 [-]: LOADK R1 K7  ; var1 = "Missing tag"
      43 [-]: JUMP L4      ; goto L4
L 3:  44 [-]: LOADK R3 K8  ; var3 = "Missing tag for "
      45 [-]: MOVE R4 R2   ; var4 = var2
      46 [-]: CONCAT R1 R3 R4; var1 = var3 .. var4
L 4:  47 [-]: GETIMPORT R2 11; var2 = _T["ShowImpactMessage"]
      48 [-]: MOVE R3 R1   ; var3 = var1
      49 [-]: LOADN R4 -1  ; var4 = -1
      50 [-]: CALL R2 3 1  ; var2(var3, var4)
      51 [-]: GETUPVAL R3 2; var3 = upvalues[2]
      52 [-]: GETTABLEKS R2 R3 K12; var2 = var3[0x659D451F]
      53 [-]: GETIMPORT R3 14; var3 = 0x97698087
      54 [-]: CALL R2 2 1  ; var2(var3)
      55 [-]: RETURN R0 0  ; 


; Name:            
; Defined at line: 344
; #Upvalues:       1
; #Parameters:     1
; Is_vararg:       0
; Max Stack Size:  10

       0 [-]: GETIMPORT R1 1; var1 = 0x89326C93
       1 [-]: MOVE R3 R0   ; var3 = var0
       2 [-]: GETUPVAL R4 0; var4 = upvalues[0]
       3 [-]: NAMECALL R4 R4 K2; var5 = var4; var4 = var4[0xD1586535]
       4 [-]: CALL R4 2 2  ; var4 = var4(var5)
       5 [-]: GETIMPORT R5 4; var5 = ZERO_ROTATION
       6 [-]: NAMECALL R1 R1 K5; var2 = var1; var1 = var1[0x05909209]
       7 [-]: CALL R1 5 2  ; var1 = var1(var2, var3, var4, var5)
       8 [-]: GETIMPORT R4 7; var4 = 0xBB76409B
       9 [-]: GETIMPORT R5 9; var5 = EMPTY_SYMBOL
      10 [-]: GETIMPORT R6 11; var6 = 0xA421AF95
      11 [-]: LOADN R7 0   ; var7 = 0
      12 [-]: LOADK R8 K12 ; var8 = 0.5
      13 [-]: LOADN R9 0   ; var9 = 0
      14 [-]: CALL R6 4 2  ; var6 = var6(var7, var8, var9)
      15 [-]: GETIMPORT R7 4; var7 = ZERO_ROTATION
      16 [-]: NAMECALL R2 R1 K13; var3 = var1; var2 = var1[0x47901F07]
      17 [-]: CALL R2 6 1  ; var2(var3, var4, var5, var6, var7)
      18 [-]: RETURN R1 1  ; 


; Name:            
; Defined at line: 350
; #Upvalues:       6
; #Parameters:     0
; Is_vararg:       0
; Max Stack Size:  11

       0 [-]: LOADN R0 1   ; var0 = 1
       1 [-]: SETUPVAL R0 0; upvalues[0] = var0
       2 [-]: GETUPVAL R0 1; var0 = upvalues[1]
       3 [-]: GETUPVAL R2 2; var2 = upvalues[2]
       4 [-]: GETTABLEKS R1 R2 K0; var1 = var2["ENERGY_TUTORIAL"]
       5 [-]: CALL R0 2 1  ; var0(var1)
       6 [-]: GETIMPORT R1 2; var1 = 0xBE6CF0D2
       7 [-]: GETIMPORT R2 4; var2 = 0x89326C93
       8 [-]: MOVE R4 R1   ; var4 = var1
       9 [-]: GETUPVAL R5 4; var5 = upvalues[4]
      10 [-]: NAMECALL R5 R5 K5; var6 = var5; var5 = var5[0xD1586535]
      11 [-]: CALL R5 2 2  ; var5 = var5(var6)
      12 [-]: GETIMPORT R6 7; var6 = ZERO_ROTATION
      13 [-]: NAMECALL R2 R2 K8; var3 = var2; var2 = var2[0x05909209]
      14 [-]: CALL R2 5 2  ; var2 = var2(var3, var4, var5, var6)
      15 [-]: GETIMPORT R5 10; var5 = 0xBB76409B
      16 [-]: GETIMPORT R6 12; var6 = EMPTY_SYMBOL
      17 [-]: GETIMPORT R7 14; var7 = 0xA421AF95
      18 [-]: LOADN R8 0   ; var8 = 0
      19 [-]: LOADK R9 K15 ; var9 = 0.5
      20 [-]: LOADN R10 0  ; var10 = 0
      21 [-]: CALL R7 4 2  ; var7 = var7(var8, var9, var10)
      22 [-]: GETIMPORT R8 7; var8 = ZERO_ROTATION
      23 [-]: NAMECALL R3 R2 K16; var4 = var2; var3 = var2[0x47901F07]
      24 [-]: CALL R3 6 1  ; var3(var4, var5, var6, var7, var8)
      25 [-]: MOVE R0 R2   ; var0 = var2
      26 [-]: SETUPVAL R0 3; upvalues[0] = var3
      27 [-]: GETUPVAL R0 5; var0 = upvalues[5]
      28 [-]: GETUPVAL R1 3; var1 = upvalues[3]
      29 [-]: CALL R0 2 2  ; var0 = var0(var1)
      30 [-]: JUMPIF R0 L0 ; goto L0 if var0
      31 [-]: LOADN R0 2   ; var0 = 2
      32 [-]: SETUPVAL R0 0; upvalues[0] = var0
      33 [-]: RETURN R0 0  ; 
L 0:  34 [-]: GETUPVAL R0 1; var0 = upvalues[1]
      35 [-]: GETUPVAL R2 2; var2 = upvalues[2]
      36 [-]: GETTABLEKS R1 R2 K17; var1 = var2["ABILITY_TUTORIAL"]
      37 [-]: CALL R0 2 1  ; var0(var1)
      38 [-]: LOADN R0 2   ; var0 = 2
      39 [-]: SETUPVAL R0 0; upvalues[0] = var0
      40 [-]: RETURN R0 0  ; 


; Name:            
; Defined at line: 365
; #Upvalues:       11
; #Parameters:     0
; Is_vararg:       0
; Max Stack Size:  11

       0 [-]: LOADN R0 1   ; var0 = 1
       1 [-]: SETUPVAL R0 0; upvalues[0] = var0
       2 [-]: GETUPVAL R1 1; var1 = upvalues[1]
       3 [-]: GETTABLEKS R0 R1 K0; var0 = var1[0x11DCFE97]
       4 [-]: GETIMPORT R1 2; var1 = 0x0469F296
       5 [-]: LOADK R2 K3  ; var2 = "DDuvParQUndercroft0760"
       6 [-]: CALL R1 2 2  ; var1 = var1(var2)
       7 [-]: LOADB R2 0   ; var2 = false
       8 [-]: LOADB R3 0   ; var3 = false
       9 [-]: LOADN R4 4   ; var4 = 4
      10 [-]: CALL R0 5 1  ; var0(var1, var2, var3, var4)
      11 [-]: GETUPVAL R1 1; var1 = upvalues[1]
      12 [-]: GETTABLEKS R0 R1 K4; var0 = var1[0x9742B85B]
      13 [-]: GETUPVAL R1 2; var1 = upvalues[2]
      14 [-]: GETIMPORT R2 2; var2 = 0x0469F296
      15 [-]: LOADK R3 K5  ; var3 = "DDuvParQUndercroft0770"
      16 [-]: CALL R2 2 0  ; var2, ... = var2(var3)
      17 [-]: CALL R0 0 1  ; var0(var1, ...)
      18 [-]: GETUPVAL R1 1; var1 = upvalues[1]
      19 [-]: GETTABLEKS R0 R1 K6; var0 = var1[0xFC87A231]
      20 [-]: CALL R0 1 1  ; var0()
      21 [-]: GETUPVAL R0 3; var0 = upvalues[3]
      22 [-]: NAMECALL R0 R0 K7; var1 = var0; var0 = var0[0xC8442850]
      23 [-]: CALL R0 2 2  ; var0 = var0(var1)
      24 [-]: LOADN R1 1   ; var1 = 1
      25 [-]: JUMPIFNOTLE R1 R0 L0; goto L0 if var1 > var131120
      26 [-]: LOADN R0 2   ; var0 = 2
      27 [-]: SETUPVAL R0 0; upvalues[0] = var0
      28 [-]: RETURN R0 0  ; 
L 0:  29 [-]: GETUPVAL R0 4; var0 = upvalues[4]
      30 [-]: GETUPVAL R2 5; var2 = upvalues[5]
      31 [-]: GETTABLEKS R1 R2 K8; var1 = var2["HEALTH_TUTORIAL"]
      32 [-]: CALL R0 2 1  ; var0(var1)
      33 [-]: GETIMPORT R1 10; var1 = 0x0CC88278
      34 [-]: GETIMPORT R2 12; var2 = 0x89326C93
      35 [-]: MOVE R4 R1   ; var4 = var1
      36 [-]: GETUPVAL R5 7; var5 = upvalues[7]
      37 [-]: NAMECALL R5 R5 K13; var6 = var5; var5 = var5[0xD1586535]
      38 [-]: CALL R5 2 2  ; var5 = var5(var6)
      39 [-]: GETIMPORT R6 15; var6 = ZERO_ROTATION
      40 [-]: NAMECALL R2 R2 K16; var3 = var2; var2 = var2[0x05909209]
      41 [-]: CALL R2 5 2  ; var2 = var2(var3, var4, var5, var6)
      42 [-]: GETIMPORT R5 18; var5 = 0xBB76409B
      43 [-]: GETIMPORT R6 20; var6 = EMPTY_SYMBOL
      44 [-]: GETIMPORT R7 22; var7 = 0xA421AF95
      45 [-]: LOADN R8 0   ; var8 = 0
      46 [-]: LOADK R9 K23 ; var9 = 0.5
      47 [-]: LOADN R10 0  ; var10 = 0
      48 [-]: CALL R7 4 2  ; var7 = var7(var8, var9, var10)
      49 [-]: GETIMPORT R8 15; var8 = ZERO_ROTATION
      50 [-]: NAMECALL R3 R2 K24; var4 = var2; var3 = var2[0x47901F07]
      51 [-]: CALL R3 6 1  ; var3(var4, var5, var6, var7, var8)
      52 [-]: MOVE R0 R2   ; var0 = var2
      53 [-]: SETUPVAL R0 6; upvalues[0] = var6
      54 [-]: GETUPVAL R0 8; var0 = upvalues[8]
      55 [-]: GETUPVAL R1 6; var1 = upvalues[6]
      56 [-]: CALL R0 2 2  ; var0 = var0(var1)
      57 [-]: JUMPIF R0 L1 ; goto L1 if var0
      58 [-]: LOADN R0 2   ; var0 = 2
      59 [-]: SETUPVAL R0 0; upvalues[0] = var0
      60 [-]: RETURN R0 0  ; 
L 1:  61 [-]: GETUPVAL R0 9; var0 = upvalues[9]
      62 [-]: GETUPVAL R2 10; var2 = upvalues[10]
      63 [-]: GETTABLEKS R1 R2 K25; var1 = var2["TEST_SUIT"]
      64 [-]: JUMPIFNOTEQ R0 R1 L2; goto L2 if var0 ~= var262204
      65 [-]: GETUPVAL R0 4; var0 = upvalues[4]
      66 [-]: GETUPVAL R2 5; var2 = upvalues[5]
      67 [-]: GETTABLEKS R1 R2 K26; var1 = var2["ABILITY_TUTORIAL"]
      68 [-]: CALL R0 2 1  ; var0(var1)
      69 [-]: JUMP L3      ; goto L3
L 2:  70 [-]: GETUPVAL R0 4; var0 = upvalues[4]
      71 [-]: CALL R0 1 1  ; var0()
L 3:  72 [-]: LOADN R0 2   ; var0 = 2
      73 [-]: SETUPVAL R0 0; upvalues[0] = var0
      74 [-]: RETURN R0 0  ; 


; Name:            
; Defined at line: 393
; #Upvalues:       8
; #Parameters:     0
; Is_vararg:       0
; Max Stack Size:  11

       0 [-]: LOADN R0 1   ; var0 = 1
       1 [-]: SETUPVAL R0 0; upvalues[0] = var0
       2 [-]: GETUPVAL R0 1; var0 = upvalues[1]
       3 [-]: GETUPVAL R2 2; var2 = upvalues[2]
       4 [-]: GETTABLEKS R1 R2 K0; var1 = var2["AMMO_TUTORIAL"]
       5 [-]: CALL R0 2 1  ; var0(var1)
       6 [-]: GETUPVAL R1 3; var1 = upvalues[3]
       7 [-]: GETTABLEKS R0 R1 K1; var0 = var1[0x06D055F9]
       8 [-]: GETUPVAL R2 4; var2 = upvalues[4]
       9 [-]: GETIMPORT R3 3; var3 = 0x7ED0A956
      10 [-]: LOADK R4 K4  ; var4 = "/Lotus/Weapons/Ammo/PistolAmmoEx"
      11 [-]: CALL R3 2 2  ; var3 = var3(var4)
      12 [-]: JUMPIFEQ R2 R3 L0; goto L0 if var2 == var16777478
      13 [-]: LOADB R1 0 +1; var1 = false
L 0:  14 [-]: LOADB R1 1   ; var1 = true
L 1:  15 [-]: GETIMPORT R2 6; var2 = 0x8947A1FA
      16 [-]: GETIMPORT R3 8; var3 = 0x9A5E37EA
      17 [-]: CALL R0 4 2  ; var0 = var0(var1, var2, var3)
      18 [-]: GETIMPORT R2 10; var2 = 0x89326C93
      19 [-]: MOVE R4 R0   ; var4 = var0
      20 [-]: GETUPVAL R5 6; var5 = upvalues[6]
      21 [-]: NAMECALL R5 R5 K11; var6 = var5; var5 = var5[0xD1586535]
      22 [-]: CALL R5 2 2  ; var5 = var5(var6)
      23 [-]: GETIMPORT R6 13; var6 = ZERO_ROTATION
      24 [-]: NAMECALL R2 R2 K14; var3 = var2; var2 = var2[0x05909209]
      25 [-]: CALL R2 5 2  ; var2 = var2(var3, var4, var5, var6)
      26 [-]: GETIMPORT R5 16; var5 = 0xBB76409B
      27 [-]: GETIMPORT R6 18; var6 = EMPTY_SYMBOL
      28 [-]: GETIMPORT R7 20; var7 = 0xA421AF95
      29 [-]: LOADN R8 0   ; var8 = 0
      30 [-]: LOADK R9 K21 ; var9 = 0.5
      31 [-]: LOADN R10 0  ; var10 = 0
      32 [-]: CALL R7 4 2  ; var7 = var7(var8, var9, var10)
      33 [-]: GETIMPORT R8 13; var8 = ZERO_ROTATION
      34 [-]: NAMECALL R3 R2 K22; var4 = var2; var3 = var2[0x47901F07]
      35 [-]: CALL R3 6 1  ; var3(var4, var5, var6, var7, var8)
      36 [-]: MOVE R1 R2   ; var1 = var2
      37 [-]: SETUPVAL R1 5; upvalues[1] = var5
      38 [-]: GETUPVAL R1 7; var1 = upvalues[7]
      39 [-]: GETUPVAL R2 5; var2 = upvalues[5]
      40 [-]: CALL R1 2 2  ; var1 = var1(var2)
      41 [-]: JUMPIF R1 L2 ; goto L2 if var1
      42 [-]: LOADN R1 2   ; var1 = 2
      43 [-]: SETUPVAL R1 0; upvalues[1] = var0
      44 [-]: RETURN R0 0  ; 
L 2:  45 [-]: GETUPVAL R1 1; var1 = upvalues[1]
      46 [-]: CALL R1 1 1  ; var1()
      47 [-]: LOADN R1 2   ; var1 = 2
      48 [-]: SETUPVAL R1 0; upvalues[1] = var0
      49 [-]: RETURN R0 0  ; 


; Name:            
; Defined at line: 409
; #Upvalues:       3
; #Parameters:     0
; Is_vararg:       0
; Max Stack Size:  9

       0 [-]: GETUPVAL R0 0; var0 = upvalues[0]
       1 [-]: GETIMPORT R2 1; var2 = 0x0469F296
       2 [-]: LOADK R3 K2  ; var3 = "UndercroftSpec"
       3 [-]: CALL R2 2 2  ; var2 = var2(var3)
       4 [-]: GETIMPORT R3 4; var3 = 0x57121901
       5 [-]: NAMECALL R0 R0 K5; var1 = var0; var0 = var0[0xA86E04ED]
       6 [-]: CALL R0 4 1  ; var0(var1, var2, var3)
       7 [-]: GETUPVAL R0 0; var0 = upvalues[0]
       8 [-]: LOADN R2 250 ; var2 = 250
       9 [-]: LOADN R3 250 ; var3 = 250
      10 [-]: LOADB R4 0   ; var4 = false
      11 [-]: LOADB R5 0   ; var5 = false
      12 [-]: NAMECALL R0 R0 K6; var1 = var0; var0 = var0[0x2B39CBDE]
      13 [-]: CALL R0 6 1  ; var0(var1, var2, var3, var4, var5)
      14 [-]: GETUPVAL R0 0; var0 = upvalues[0]
      15 [-]: LOADN R2 20  ; var2 = 20
      16 [-]: LOADN R3 250 ; var3 = 250
      17 [-]: LOADN R4 0   ; var4 = 0
      18 [-]: LOADN R5 3   ; var5 = 3
      19 [-]: LOADB R6 0   ; var6 = false
      20 [-]: LOADB R7 1   ; var7 = true
      21 [-]: LOADB R8 0   ; var8 = false
      22 [-]: NAMECALL R0 R0 K7; var1 = var0; var0 = var0[0xA2367658]
      23 [-]: CALL R0 9 1  ; var0(var1, var2, var3, var4, var5, var6, var7, var8)
      24 [-]: GETUPVAL R0 0; var0 = upvalues[0]
      25 [-]: LOADB R2 1   ; var2 = true
      26 [-]: NAMECALL R0 R0 K8; var1 = var0; var0 = var0[0x1A82855B]
      27 [-]: CALL R0 3 1  ; var0(var1, var2)
      28 [-]: GETUPVAL R0 0; var0 = upvalues[0]
      29 [-]: NAMECALL R0 R0 K9; var1 = var0; var0 = var0[0x54E453D2]
      30 [-]: CALL R0 2 1  ; var0(var1)
      31 [-]: GETUPVAL R0 0; var0 = upvalues[0]
      32 [-]: GETUPVAL R2 1; var2 = upvalues[1]
      33 [-]: NAMECALL R0 R0 K10; var1 = var0; var0 = var0[0xE2871589]
      34 [-]: CALL R0 3 1  ; var0(var1, var2)
      35 [-]: GETUPVAL R0 0; var0 = upvalues[0]
      36 [-]: LOADN R2 20  ; var2 = 20
      37 [-]: LOADN R3 20  ; var3 = 20
      38 [-]: NAMECALL R0 R0 K11; var1 = var0; var0 = var0[0xCE01CCC2]
      39 [-]: CALL R0 4 1  ; var0(var1, var2, var3)
      40 [-]: GETUPVAL R0 0; var0 = upvalues[0]
      41 [-]: GETUPVAL R2 2; var2 = upvalues[2]
      42 [-]: LOADN R3 20  ; var3 = 20
      43 [-]: NAMECALL R0 R0 K12; var1 = var0; var0 = var0[0xCC6AA982]
      44 [-]: CALL R0 4 1  ; var0(var1, var2, var3)
      45 [-]: GETUPVAL R0 0; var0 = upvalues[0]
      46 [-]: LOADN R2 0   ; var2 = 0
      47 [-]: NAMECALL R0 R0 K13; var1 = var0; var0 = var0[0x3EA76F0C]
      48 [-]: CALL R0 3 1  ; var0(var1, var2)
      49 [-]: RETURN R0 0  ; 


; Name:            
; Defined at line: 425
; #Upvalues:       5
; #Parameters:     1
; Is_vararg:       0
; Max Stack Size:  12

       0 [-]: GETUPVAL R1 0; var1 = upvalues[0]
       1 [-]: GETUPVAL R2 1; var2 = upvalues[1]
       2 [-]: JUMPIFNOTLT R1 R2 L0; goto L0 if var1 >= var572
       3 [-]: GETUPVAL R2 0; var2 = upvalues[0]
       4 [-]: ADD R1 R2 R0 ; var1 = var2 + var0
       5 [-]: SETUPVAL R1 0; upvalues[1] = var0
       6 [-]: RETURN R0 0  ; 
L 0:   7 [-]: GETUPVAL R1 2; var1 = upvalues[2]
       8 [-]: GETIMPORT R3 2; var3 = _T["ArenaStreamingLayerIndex"]
       9 [-]: NAMECALL R1 R1 K3; var2 = var1; var1 = var1[0xE3A763FE]
      10 [-]: CALL R1 3 2  ; var1 = var1(var2, var3)
      11 [-]: LOADN R2 3   ; var2 = 3
      12 [-]: JUMPIFNOTLT R1 R2 L8; goto L8 if var1 >= var327969
      13 [-]: GETIMPORT R1 5; var1 = 0x3D106989
      14 [-]: LOADK R3 K6  ; var3 = "Attempting to spawn an agent, Enemy Count: "
      15 [-]: GETUPVAL R4 2; var4 = upvalues[2]
      16 [-]: GETIMPORT R6 2; var6 = _T["ArenaStreamingLayerIndex"]
      17 [-]: NAMECALL R4 R4 K3; var5 = var4; var4 = var4[0xE3A763FE]
      18 [-]: CALL R4 3 2  ; var4 = var4(var5, var6)
      19 [-]: CONCAT R2 R3 R4; var2 = var3 .. var4
      20 [-]: CALL R1 2 1  ; var1(var2)
      21 [-]: GETUPVAL R1 2; var1 = upvalues[2]
      22 [-]: GETIMPORT R3 8; var3 = 0x57121901
      23 [-]: GETUPVAL R4 3; var4 = upvalues[3]
      24 [-]: NAMECALL R1 R1 K9; var2 = var1; var1 = var1[0xD1B469E9]
      25 [-]: CALL R1 4 2  ; var1 = var1(var2, var3, var4)
      26 [-]: GETUPVAL R2 2; var2 = upvalues[2]
      27 [-]: MOVE R4 R1   ; var4 = var1
      28 [-]: LOADNIL R5   ; var5 = nil
      29 [-]: NAMECALL R2 R2 K10; var3 = var2; var2 = var2[0x33FC842F]
      30 [-]: CALL R2 4 2  ; var2 = var2(var3, var4, var5)
      31 [-]: FASTCALL1 64 R2 L1; 
      32 [-]: MOVE R4 R2   ; var4 = var2
      33 [-]: GETIMPORT R3 12; var3 = 0x7B998233
      34 [-]: CALL R3 2 2  ; var3 = var3(var4)
L 1:  35 [-]: JUMPIF R3 L3 ; goto L3 if var3
      36 [-]: NAMECALL R3 R2 K13; var4 = var2; var3 = var2[0xBB610E5B]
      37 [-]: CALL R3 2 2  ; var3 = var3(var4)
      38 [-]: GETIMPORT R6 15; var6 = 0xBA3D59B8
      39 [-]: GETIMPORT R7 17; var7 = EMPTY_SYMBOL
      40 [-]: GETIMPORT R8 19; var8 = 0xA421AF95
      41 [-]: LOADN R9 0   ; var9 = 0
      42 [-]: LOADN R10 2  ; var10 = 2
      43 [-]: LOADN R11 0  ; var11 = 0
      44 [-]: CALL R8 4 2  ; var8 = var8(var9, var10, var11)
      45 [-]: GETIMPORT R9 21; var9 = ZERO_ROTATION
      46 [-]: NAMECALL R4 R3 K22; var5 = var3; var4 = var3[0x47901F07]
      47 [-]: CALL R4 6 1  ; var4(var5, var6, var7, var8, var9)
      48 [-]: GETIMPORT R4 24; var4 = 0x11A19C5E
      49 [-]: MOVE R5 R3   ; var5 = var3
      50 [-]: LOADK R6 K25 ; var6 = "OnKilled"
      51 [-]: CALL R4 3 1  ; var4(var5, var6)
      52 [-]: GETUPVAL R5 4; var5 = upvalues[4]
      53 [-]: FASTCALL2 52 R5 R3 L2; 
      54 [-]: MOVE R6 R3   ; var6 = var3
      55 [-]: GETIMPORT R4 28; var4 = 0x33BDD652[0x23D5322F]
      56 [-]: CALL R4 3 1  ; var4(var5, var6)
L 2:  57 [-]: JUMP L7      ; goto L7
L 3:  58 [-]: LOADNIL R3   ; var3 = nil
      59 [-]: FASTCALL1 64 R1 L4; 
      60 [-]: MOVE R5 R1   ; var5 = var1
      61 [-]: GETIMPORT R4 12; var4 = 0x7B998233
      62 [-]: CALL R4 2 2  ; var4 = var4(var5)
L 4:  63 [-]: JUMPIFNOT R4 L5; goto L5 if not var4
      64 [-]: LOADK R3 K29 ; var3 = "Null agent type"
      65 [-]: JUMP L6      ; goto L6
L 5:  66 [-]: LOADK R4 K30 ; var4 = "Failed to spawn "
      67 [-]: NAMECALL R5 R1 K31; var6 = var1; var5 = var1[0xED4E0128]
      68 [-]: CALL R5 2 2  ; var5 = var5(var6)
      69 [-]: CONCAT R3 R4 R5; var3 = var4 .. var5
L 6:  70 [-]: GETIMPORT R4 5; var4 = 0x3D106989
      71 [-]: LOADK R6 K32 ; var6 = "Unable to spawn enemy: "
      72 [-]: MOVE R7 R3   ; var7 = var3
      73 [-]: CONCAT R5 R6 R7; var5 = var6 .. var7
      74 [-]: CALL R4 2 1  ; var4(var5)
L 7:  75 [-]: LOADN R3 0   ; var3 = 0
      76 [-]: SETUPVAL R3 0; upvalues[3] = var0
      77 [-]: RETURN R0 0  ; 
L 8:  78 [-]: GETIMPORT R1 5; var1 = 0x3D106989
      79 [-]: LOADK R3 K33 ; var3 = "Reached MAX_SIM, Enemy Count: "
      80 [-]: GETUPVAL R4 2; var4 = upvalues[2]
      81 [-]: GETIMPORT R6 2; var6 = _T["ArenaStreamingLayerIndex"]
      82 [-]: NAMECALL R4 R4 K3; var5 = var4; var4 = var4[0xE3A763FE]
      83 [-]: CALL R4 3 2  ; var4 = var4(var5, var6)
      84 [-]: CONCAT R2 R3 R4; var2 = var3 .. var4
      85 [-]: CALL R1 2 1  ; var1(var2)
      86 [-]: LOADN R1 0   ; var1 = 0
      87 [-]: SETUPVAL R1 0; upvalues[1] = var0
      88 [-]: RETURN R0 0  ; 


; Name:            
; Defined at line: 453
; #Upvalues:       6
; #Parameters:     0
; Is_vararg:       0
; Max Stack Size:  13

       0 [-]: GETUPVAL R0 0; var0 = upvalues[0]
       1 [-]: NAMECALL R0 R0 K0; var1 = var0; var0 = var0[0xDE321E6F]
       2 [-]: CALL R0 2 2  ; var0 = var0(var1)
       3 [-]: NAMECALL R0 R0 K1; var1 = var0; var0 = var0[0xF7D48EE0]
       4 [-]: CALL R0 2 2  ; var0 = var0(var1)
       5 [-]: GETUPVAL R1 1; var1 = upvalues[1]
       6 [-]: MOVE R2 R0   ; var2 = var0
       7 [-]: CALL R1 2 2  ; var1 = var1(var2)
       8 [-]: LOADN R2 0   ; var2 = 0
       9 [-]: JUMPIFNOTLE R1 R2 L0; goto L0 if var1 > var131644
      10 [-]: GETUPVAL R2 2; var2 = upvalues[2]
      11 [-]: JUMPXEQKN R2 K2 L0 NOT; 
      12 [-]: GETUPVAL R2 3; var2 = upvalues[3]
      13 [-]: GETIMPORT R4 4; var4 = 0x0469F296
      14 [-]: LOADK R5 K5  ; var5 = "EnergyTutorial"
      15 [-]: CALL R4 2 2  ; var4 = var4(var5)
      16 [-]: LOADB R5 0   ; var5 = false
      17 [-]: NAMECALL R2 R2 K6; var3 = var2; var2 = var2[0xD5F7912B]
      18 [-]: CALL R2 4 1  ; var2(var3, var4, var5)
      19 [-]: RETURN R0 0  ; 
L 0:  20 [-]: LOADN R2 0   ; var2 = 0
      21 [-]: JUMPIFNOTLE R1 R2 L2; goto L2 if var1 > var131644
      22 [-]: GETUPVAL R2 2; var2 = upvalues[2]
      23 [-]: JUMPXEQKN R2 K7 L2 NOT; 
      24 [-]: GETUPVAL R3 4; var3 = upvalues[4]
      25 [-]: FASTCALL1 64 R3 L1; 
      26 [-]: GETIMPORT R2 9; var2 = 0x7B998233
      27 [-]: CALL R2 2 2  ; var2 = var2(var3)
L 1:  28 [-]: JUMPIFNOT R2 L2; goto L2 if not var2
      29 [-]: GETIMPORT R3 11; var3 = 0xBE6CF0D2
      30 [-]: GETIMPORT R4 13; var4 = 0x89326C93
      31 [-]: MOVE R6 R3   ; var6 = var3
      32 [-]: GETUPVAL R7 5; var7 = upvalues[5]
      33 [-]: NAMECALL R7 R7 K14; var8 = var7; var7 = var7[0xD1586535]
      34 [-]: CALL R7 2 2  ; var7 = var7(var8)
      35 [-]: GETIMPORT R8 16; var8 = ZERO_ROTATION
      36 [-]: NAMECALL R4 R4 K17; var5 = var4; var4 = var4[0x05909209]
      37 [-]: CALL R4 5 2  ; var4 = var4(var5, var6, var7, var8)
      38 [-]: GETIMPORT R7 19; var7 = 0xBB76409B
      39 [-]: GETIMPORT R8 21; var8 = EMPTY_SYMBOL
      40 [-]: GETIMPORT R9 23; var9 = 0xA421AF95
      41 [-]: LOADN R10 0  ; var10 = 0
      42 [-]: LOADK R11 K24; var11 = 0.5
      43 [-]: LOADN R12 0  ; var12 = 0
      44 [-]: CALL R9 4 2  ; var9 = var9(var10, var11, var12)
      45 [-]: GETIMPORT R10 16; var10 = ZERO_ROTATION
      46 [-]: NAMECALL R5 R4 K25; var6 = var4; var5 = var4[0x47901F07]
      47 [-]: CALL R5 6 1  ; var5(var6, var7, var8, var9, var10)
      48 [-]: MOVE R2 R4   ; var2 = var4
      49 [-]: SETUPVAL R2 4; upvalues[2] = var4
L 2:  50 [-]: RETURN R0 0  ; 


; Name:            
; Defined at line: 467
; #Upvalues:       5
; #Parameters:     0
; Is_vararg:       0
; Max Stack Size:  12

       0 [-]: GETUPVAL R0 0; var0 = upvalues[0]
       1 [-]: NAMECALL R0 R0 K0; var1 = var0; var0 = var0[0xC8442850]
       2 [-]: CALL R0 2 2  ; var0 = var0(var1)
       3 [-]: LOADN R1 1   ; var1 = 1
       4 [-]: JUMPIFNOTLT R0 R1 L0; goto L0 if var0 >= var65852
       5 [-]: GETUPVAL R1 1; var1 = upvalues[1]
       6 [-]: JUMPXEQKN R1 K1 L0 NOT; 
       7 [-]: GETUPVAL R1 2; var1 = upvalues[2]
       8 [-]: GETIMPORT R3 3; var3 = 0x0469F296
       9 [-]: LOADK R4 K4  ; var4 = "HealthTutorial"
      10 [-]: CALL R3 2 2  ; var3 = var3(var4)
      11 [-]: LOADB R4 0   ; var4 = false
      12 [-]: NAMECALL R1 R1 K5; var2 = var1; var1 = var1[0xD5F7912B]
      13 [-]: CALL R1 4 1  ; var1(var2, var3, var4)
      14 [-]: RETURN R0 0  ; 
L 0:  15 [-]: LOADN R1 1   ; var1 = 1
      16 [-]: JUMPIFNOTLT R0 R1 L2; goto L2 if var0 >= var65852
      17 [-]: GETUPVAL R1 1; var1 = upvalues[1]
      18 [-]: JUMPXEQKN R1 K6 L2 NOT; 
      19 [-]: GETUPVAL R2 3; var2 = upvalues[3]
      20 [-]: FASTCALL1 64 R2 L1; 
      21 [-]: GETIMPORT R1 8; var1 = 0x7B998233
      22 [-]: CALL R1 2 2  ; var1 = var1(var2)
L 1:  23 [-]: JUMPIFNOT R1 L2; goto L2 if not var1
      24 [-]: GETIMPORT R2 10; var2 = 0x0CC88278
      25 [-]: GETIMPORT R3 12; var3 = 0x89326C93
      26 [-]: MOVE R5 R2   ; var5 = var2
      27 [-]: GETUPVAL R6 4; var6 = upvalues[4]
      28 [-]: NAMECALL R6 R6 K13; var7 = var6; var6 = var6[0xD1586535]
      29 [-]: CALL R6 2 2  ; var6 = var6(var7)
      30 [-]: GETIMPORT R7 15; var7 = ZERO_ROTATION
      31 [-]: NAMECALL R3 R3 K16; var4 = var3; var3 = var3[0x05909209]
      32 [-]: CALL R3 5 2  ; var3 = var3(var4, var5, var6, var7)
      33 [-]: GETIMPORT R6 18; var6 = 0xBB76409B
      34 [-]: GETIMPORT R7 20; var7 = EMPTY_SYMBOL
      35 [-]: GETIMPORT R8 22; var8 = 0xA421AF95
      36 [-]: LOADN R9 0   ; var9 = 0
      37 [-]: LOADK R10 K23; var10 = 0.5
      38 [-]: LOADN R11 0  ; var11 = 0
      39 [-]: CALL R8 4 2  ; var8 = var8(var9, var10, var11)
      40 [-]: GETIMPORT R9 15; var9 = ZERO_ROTATION
      41 [-]: NAMECALL R4 R3 K24; var5 = var3; var4 = var3[0x47901F07]
      42 [-]: CALL R4 6 1  ; var4(var5, var6, var7, var8, var9)
      43 [-]: MOVE R1 R3   ; var1 = var3
      44 [-]: SETUPVAL R1 3; upvalues[1] = var3
L 2:  45 [-]: RETURN R0 0  ; 


; Name:            
; Defined at line: 479
; #Upvalues:       7
; #Parameters:     1
; Is_vararg:       0
; Max Stack Size:  16

       0 [-]: LOADN R1 5   ; var1 = 5
       1 [-]: JUMPIFNOTEQ R0 R1 L0; goto L0 if var0 ~= var65571
       2 [-]: RETURN R0 0  ; 
L 0:   3 [-]: GETUPVAL R1 0; var1 = upvalues[0]
       4 [-]: NAMECALL R1 R1 K0; var2 = var1; var1 = var1[0xDE321E6F]
       5 [-]: CALL R1 2 2  ; var1 = var1(var2)
       6 [-]: MOVE R3 R0   ; var3 = var0
       7 [-]: NAMECALL R1 R1 K1; var2 = var1; var1 = var1[0xE85A2361]
       8 [-]: CALL R1 3 2  ; var1 = var1(var2, var3)
       9 [-]: FASTCALL1 64 R1 L1; 
      10 [-]: MOVE R3 R1   ; var3 = var1
      11 [-]: GETIMPORT R2 3; var2 = 0x7B998233
      12 [-]: CALL R2 2 2  ; var2 = var2(var3)
L 1:  13 [-]: JUMPIF R2 L9 ; goto L9 if var2
      14 [-]: NAMECALL R2 R1 K4; var3 = var1; var2 = var1[0x4C7FFB31]
      15 [-]: CALL R2 2 2  ; var2 = var2(var3)
      16 [-]: SETUPVAL R2 1; upvalues[2] = var1
      17 [-]: GETUPVAL R3 1; var3 = upvalues[1]
      18 [-]: FASTCALL1 64 R3 L2; 
      19 [-]: GETIMPORT R2 3; var2 = 0x7B998233
      20 [-]: CALL R2 2 2  ; var2 = var2(var3)
L 2:  21 [-]: JUMPIF R2 L9 ; goto L9 if var2
      22 [-]: NAMECALL R2 R1 K5; var3 = var1; var2 = var1[0x7A7373F5]
      23 [-]: CALL R2 2 2  ; var2 = var2(var3)
      24 [-]: NAMECALL R3 R1 K6; var4 = var1; var3 = var1[0x094B3A83]
      25 [-]: CALL R3 2 2  ; var3 = var3(var4)
      26 [-]: LOADB R4 0   ; var4 = false
      27 [-]: LOADN R5 0   ; var5 = 0
      28 [-]: JUMPIFNOTLE R2 R5 L4; goto L4 if var2 > var1328
      29 [-]: LOADN R5 0   ; var5 = 0
      30 [-]: JUMPIFLE R3 R5 L3; goto L3 if var3 <= var16778246
      31 [-]: LOADB R4 0 +1; var4 = false
L 3:  32 [-]: LOADB R4 1   ; var4 = true
L 4:  33 [-]: JUMPIFNOT R4 L5; goto L5 if not var4
      34 [-]: GETUPVAL R5 2; var5 = upvalues[2]
      35 [-]: JUMPXEQKN R5 K7 L5 NOT; 
      36 [-]: GETUPVAL R5 3; var5 = upvalues[3]
      37 [-]: GETIMPORT R7 9; var7 = 0x0469F296
      38 [-]: LOADK R8 K10 ; var8 = "AmmoTutorial"
      39 [-]: CALL R7 2 2  ; var7 = var7(var8)
      40 [-]: LOADB R8 0   ; var8 = false
      41 [-]: NAMECALL R5 R5 K11; var6 = var5; var5 = var5[0xD5F7912B]
      42 [-]: CALL R5 4 1  ; var5(var6, var7, var8)
      43 [-]: RETURN R0 0  ; 
L 5:  44 [-]: JUMPIFNOT R4 L9; goto L9 if not var4
      45 [-]: GETUPVAL R5 2; var5 = upvalues[2]
      46 [-]: JUMPXEQKN R5 K12 L9 NOT; 
      47 [-]: GETUPVAL R6 4; var6 = upvalues[4]
      48 [-]: FASTCALL1 64 R6 L6; 
      49 [-]: GETIMPORT R5 3; var5 = 0x7B998233
      50 [-]: CALL R5 2 2  ; var5 = var5(var6)
L 6:  51 [-]: JUMPIFNOT R5 L9; goto L9 if not var5
      52 [-]: GETUPVAL R6 5; var6 = upvalues[5]
      53 [-]: GETTABLEKS R5 R6 K13; var5 = var6[0x06D055F9]
      54 [-]: GETUPVAL R7 1; var7 = upvalues[1]
      55 [-]: GETIMPORT R8 15; var8 = 0x7ED0A956
      56 [-]: LOADK R9 K16 ; var9 = "/Lotus/Weapons/Ammo/PistolAmmoEx"
      57 [-]: CALL R8 2 2  ; var8 = var8(var9)
      58 [-]: JUMPIFEQ R7 R8 L7; goto L7 if var7 == var16778758
      59 [-]: LOADB R6 0 +1; var6 = false
L 7:  60 [-]: LOADB R6 1   ; var6 = true
L 8:  61 [-]: GETIMPORT R7 18; var7 = 0x8947A1FA
      62 [-]: GETIMPORT R8 20; var8 = 0x9A5E37EA
      63 [-]: CALL R5 4 2  ; var5 = var5(var6, var7, var8)
      64 [-]: GETIMPORT R7 22; var7 = 0x89326C93
      65 [-]: MOVE R9 R5   ; var9 = var5
      66 [-]: GETUPVAL R10 6; var10 = upvalues[6]
      67 [-]: NAMECALL R10 R10 K23; var11 = var10; var10 = var10[0xD1586535]
      68 [-]: CALL R10 2 2 ; var10 = var10(var11)
      69 [-]: GETIMPORT R11 25; var11 = ZERO_ROTATION
      70 [-]: NAMECALL R7 R7 K26; var8 = var7; var7 = var7[0x05909209]
      71 [-]: CALL R7 5 2  ; var7 = var7(var8, var9, var10, var11)
      72 [-]: GETIMPORT R10 28; var10 = 0xBB76409B
      73 [-]: GETIMPORT R11 30; var11 = EMPTY_SYMBOL
      74 [-]: GETIMPORT R12 32; var12 = 0xA421AF95
      75 [-]: LOADN R13 0  ; var13 = 0
      76 [-]: LOADK R14 K33; var14 = 0.5
      77 [-]: LOADN R15 0  ; var15 = 0
      78 [-]: CALL R12 4 2 ; var12 = var12(var13, var14, var15)
      79 [-]: GETIMPORT R13 25; var13 = ZERO_ROTATION
      80 [-]: NAMECALL R8 R7 K34; var9 = var7; var8 = var7[0x47901F07]
      81 [-]: CALL R8 6 1  ; var8(var9, var10, var11, var12, var13)
      82 [-]: MOVE R6 R7   ; var6 = var7
      83 [-]: SETUPVAL R6 4; upvalues[6] = var4
L 9:  84 [-]: RETURN R0 0  ; 


; Name:            
; Defined at line: 509
; #Upvalues:       3
; #Parameters:     0
; Is_vararg:       0
; Max Stack Size:  2

       0 [-]: GETUPVAL R1 0; var1 = upvalues[0]
       1 [-]: FASTCALL1 64 R1 L0; 
       2 [-]: GETIMPORT R0 1; var0 = 0x7B998233
       3 [-]: CALL R0 2 2  ; var0 = var0(var1)
L 0:   4 [-]: JUMPIF R0 L1 ; goto L1 if var0
       5 [-]: GETUPVAL R0 0; var0 = upvalues[0]
       6 [-]: NAMECALL R0 R0 K2; var1 = var0; var0 = var0[0xA2880940]
       7 [-]: CALL R0 2 1  ; var0(var1)
L 1:   8 [-]: GETUPVAL R1 1; var1 = upvalues[1]
       9 [-]: FASTCALL1 64 R1 L2; 
      10 [-]: GETIMPORT R0 1; var0 = 0x7B998233
      11 [-]: CALL R0 2 2  ; var0 = var0(var1)
L 2:  12 [-]: JUMPIF R0 L3 ; goto L3 if var0
      13 [-]: GETUPVAL R0 1; var0 = upvalues[1]
      14 [-]: NAMECALL R0 R0 K2; var1 = var0; var0 = var0[0xA2880940]
      15 [-]: CALL R0 2 1  ; var0(var1)
L 3:  16 [-]: GETUPVAL R1 2; var1 = upvalues[2]
      17 [-]: FASTCALL1 64 R1 L4; 
      18 [-]: GETIMPORT R0 1; var0 = 0x7B998233
      19 [-]: CALL R0 2 2  ; var0 = var0(var1)
L 4:  20 [-]: JUMPIF R0 L5 ; goto L5 if var0
      21 [-]: GETUPVAL R0 2; var0 = upvalues[2]
      22 [-]: NAMECALL R0 R0 K2; var1 = var0; var0 = var0[0xA2880940]
      23 [-]: CALL R0 2 1  ; var0(var1)
L 5:  24 [-]: RETURN R0 0  ; 


; Name:            
; Defined at line: 523
; #Upvalues:       14
; #Parameters:     0
; Is_vararg:       0
; Max Stack Size:  7

       0 [-]: GETUPVAL R1 0; var1 = upvalues[0]
       1 [-]: GETTABLEKS R0 R1 K0; var0 = var1[0xE453D7FE]
       2 [-]: CALL R0 1 1  ; var0()
       3 [-]: GETIMPORT R1 2; var1 = 0x3BDDD011
       4 [-]: FASTCALL1 64 R1 L0; 
       5 [-]: GETIMPORT R0 4; var0 = 0x7B998233
       6 [-]: CALL R0 2 2  ; var0 = var0(var1)
L 0:   7 [-]: JUMPIF R0 L1 ; goto L1 if var0
       8 [-]: GETUPVAL R1 1; var1 = upvalues[1]
       9 [-]: GETTABLEKS R0 R1 K5; var0 = var1[0x659D451F]
      10 [-]: GETIMPORT R1 2; var1 = 0x3BDDD011
      11 [-]: CALL R0 2 1  ; var0(var1)
L 1:  12 [-]: GETIMPORT R0 7; var0 = _T
      13 [-]: GETIMPORT R1 9; var1 = _T["TaggedDialog"]
      14 [-]: JUMPIF R1 L2 ; goto L2 if var1
      15 [-]: NEWTABLE R1 0 0; var1 = {}
L 2:  16 [-]: SETTABLEKS R1 R0 K8; var1["TaggedDialog"] = var0
      17 [-]: GETIMPORT R0 9; var0 = _T["TaggedDialog"]
      18 [-]: DUPTABLE R1 12; 
      19 [-]: GETUPVAL R3 2; var3 = upvalues[2]
      20 [-]: GETTABLEKS R2 R3 K13; var2 = var3["NAME_RABBIT"]
      21 [-]: SETTABLEKS R2 R1 K10; var2["mName"] = var1
      22 [-]: NEWCLOSURE R2 P0; 
      23 [-]: CAPTURE UPVAL U3; 
      24 [-]: CAPTURE UPVAL U4; 
      25 [-]: CAPTURE UPVAL U5; 
      26 [-]: SETTABLEKS R2 R1 K11; var2["mCallback"] = var1
      27 [-]: SETTABLEKS R1 R0 K14; var1["SelectWarframe"] = var0
      28 [-]: GETUPVAL R1 4; var1 = upvalues[4]
      29 [-]: FASTCALL1 64 R1 L3; 
      30 [-]: GETIMPORT R0 4; var0 = 0x7B998233
      31 [-]: CALL R0 2 2  ; var0 = var0(var1)
L 3:  32 [-]: JUMPIFNOT R0 L4; goto L4 if not var0
      33 [-]: RETURN R0 0  ; 
L 4:  34 [-]: GETIMPORT R0 16; var0 = 0x89326C93
      35 [-]: GETIMPORT R2 18; var2 = 0x0469F296
      36 [-]: LOADK R3 K19 ; var3 = "DrifterTalkPosition"
      37 [-]: CALL R2 2 0  ; var2, ... = var2(var3)
      38 [-]: NAMECALL R0 R0 K20; var1 = var0; var0 = var0[0x46A0EBF5]
      39 [-]: CALL R0 0 2  ; var0 = var0(var1, ...)
      40 [-]: GETUPVAL R1 4; var1 = upvalues[4]
      41 [-]: NAMECALL R3 R0 K21; var4 = var0; var3 = var0[0xD1586535]
      42 [-]: CALL R3 2 2  ; var3 = var3(var4)
      43 [-]: NAMECALL R4 R0 K22; var5 = var0; var4 = var0[0xCB3851B8]
      44 [-]: CALL R4 2 0  ; var4, ... = var4(var5)
      45 [-]: NAMECALL R1 R1 K23; var2 = var1; var1 = var1[0x589EF1C1]
      46 [-]: CALL R1 0 1  ; var1(var2, ...)
      47 [-]: GETIMPORT R1 25; var1 = 0xCBD666E1
      48 [-]: LOADN R2 1   ; var2 = 1
      49 [-]: CALL R1 2 1  ; var1(var2)
      50 [-]: GETIMPORT R1 16; var1 = 0x89326C93
      51 [-]: GETIMPORT R3 18; var3 = 0x0469F296
      52 [-]: LOADK R4 K26 ; var4 = "TeshinTalkAction"
      53 [-]: CALL R3 2 0  ; var3, ... = var3(var4)
      54 [-]: NAMECALL R1 R1 K20; var2 = var1; var1 = var1[0x46A0EBF5]
      55 [-]: CALL R1 0 2  ; var1 = var1(var2, ...)
      56 [-]: GETUPVAL R2 4; var2 = upvalues[4]
      57 [-]: NAMECALL R2 R2 K27; var3 = var2; var2 = var2[0x59E42E1B]
      58 [-]: CALL R2 2 2  ; var2 = var2(var3)
      59 [-]: MOVE R4 R1   ; var4 = var1
      60 [-]: NAMECALL R2 R2 K28; var3 = var2; var2 = var2[0x98852CF7]
      61 [-]: CALL R2 3 1  ; var2(var3, var4)
      62 [-]: GETUPVAL R3 6; var3 = upvalues[6]
      63 [-]: GETTABLEKS R2 R3 K29; var2 = var3[0x12A41A40]
      64 [-]: LOADB R3 0   ; var3 = false
      65 [-]: LOADN R4 3   ; var4 = 3
      66 [-]: CALL R2 3 1  ; var2(var3, var4)
L 5:  67 [-]: GETIMPORT R3 9; var3 = _T["TaggedDialog"]
      68 [-]: GETTABLEKS R2 R3 K14; var2 = var3["SelectWarframe"]
      69 [-]: JUMPIFNOT R2 L6; goto L6 if not var2
      70 [-]: GETIMPORT R2 25; var2 = 0xCBD666E1
      71 [-]: LOADN R3 0   ; var3 = 0
      72 [-]: CALL R2 2 1  ; var2(var3)
      73 [-]: JUMPBACK L5  ; goto L5
L 6:  74 [-]: GETIMPORT R2 16; var2 = 0x89326C93
      75 [-]: GETIMPORT R4 18; var4 = 0x0469F296
      76 [-]: LOADK R5 K30 ; var5 = "SelectWarframeMarker"
      77 [-]: CALL R4 2 0  ; var4, ... = var4(var5)
      78 [-]: NAMECALL R2 R2 K20; var3 = var2; var2 = var2[0x46A0EBF5]
      79 [-]: CALL R2 0 2  ; var2 = var2(var3, ...)
      80 [-]: SETUPVAL R2 7; upvalues[2] = var7
      81 [-]: GETUPVAL R2 7; var2 = upvalues[7]
      82 [-]: NAMECALL R2 R2 K31; var3 = var2; var2 = var2[0x383D2E7D]
      83 [-]: CALL R2 2 1  ; var2(var3)
      84 [-]: GETIMPORT R2 25; var2 = 0xCBD666E1
      85 [-]: LOADN R3 2   ; var3 = 2
      86 [-]: CALL R2 2 1  ; var2(var3)
      87 [-]: GETUPVAL R3 8; var3 = upvalues[8]
      88 [-]: GETTABLEKS R2 R3 K32; var2 = var3[0x9742B85B]
      89 [-]: GETUPVAL R3 5; var3 = upvalues[5]
      90 [-]: GETIMPORT R4 18; var4 = 0x0469F296
      91 [-]: LOADK R5 K33 ; var5 = "DDuvParQWF0690"
      92 [-]: CALL R4 2 0  ; var4, ... = var4(var5)
      93 [-]: CALL R2 0 1  ; var2(var3, ...)
      94 [-]: GETUPVAL R3 8; var3 = upvalues[8]
      95 [-]: GETTABLEKS R2 R3 K34; var2 = var3[0xFC87A231]
      96 [-]: CALL R2 1 1  ; var2()
L 7:  97 [-]: GETUPVAL R3 4; var3 = upvalues[4]
      98 [-]: FASTCALL1 64 R3 L8; 
      99 [-]: GETIMPORT R2 4; var2 = 0x7B998233
     100 [-]: CALL R2 2 2  ; var2 = var2(var3)
L 8: 101 [-]: JUMPIF R2 L9 ; goto L9 if var2
     102 [-]: GETUPVAL R2 4; var2 = upvalues[4]
     103 [-]: GETUPVAL R4 7; var4 = upvalues[7]
     104 [-]: NAMECALL R2 R2 K35; var3 = var2; var2 = var2[0x68D0CBED]
     105 [-]: CALL R2 3 2  ; var2 = var2(var3, var4)
     106 [-]: LOADN R3 10  ; var3 = 10
     107 [-]: JUMPIFNOTLT R3 R2 L12; goto L12 if var3 >= var1638945
L 9: 108 [-]: GETIMPORT R2 25; var2 = 0xCBD666E1
     109 [-]: LOADN R3 0   ; var3 = 0
     110 [-]: CALL R2 2 1  ; var2(var3)
     111 [-]: GETUPVAL R3 4; var3 = upvalues[4]
     112 [-]: FASTCALL1 64 R3 L10; 
     113 [-]: GETIMPORT R2 4; var2 = 0x7B998233
     114 [-]: CALL R2 2 2  ; var2 = var2(var3)
L10: 115 [-]: JUMPIFNOT R2 L11; goto L11 if not var2
     116 [-]: GETIMPORT R2 16; var2 = 0x89326C93
     117 [-]: NAMECALL R2 R2 K36; var3 = var2; var2 = var2[0x78298275]
     118 [-]: CALL R2 2 2  ; var2 = var2(var3)
     119 [-]: SETUPVAL R2 4; upvalues[2] = var4
L11: 120 [-]: JUMPBACK L7  ; goto L7
L12: 121 [-]: GETIMPORT R2 38; var2 = 0xBE190284
     122 [-]: NAMECALL R2 R2 K39; var3 = var2; var2 = var2[0x9C1CC518]
     123 [-]: CALL R2 2 2  ; var2 = var2(var3)
     124 [-]: JUMPIFNOT R2 L13; goto L13 if not var2
     125 [-]: RETURN R0 0  ; 
L13: 126 [-]: GETUPVAL R2 4; var2 = upvalues[4]
     127 [-]: NAMECALL R2 R2 K40; var3 = var2; var2 = var2[0xDE321E6F]
     128 [-]: CALL R2 2 2  ; var2 = var2(var3)
     129 [-]: LOADN R4 0   ; var4 = 0
     130 [-]: LOADN R5 0   ; var5 = 0
     131 [-]: NAMECALL R2 R2 K41; var3 = var2; var2 = var2[0x54732CC7]
     132 [-]: CALL R2 4 1  ; var2(var3, var4, var5)
     133 [-]: GETUPVAL R2 7; var2 = upvalues[7]
     134 [-]: NAMECALL R2 R2 K42; var3 = var2; var2 = var2[0xF4E253B6]
     135 [-]: CALL R2 2 1  ; var2(var3)
     136 [-]: GETIMPORT R2 44; var2 = 0x9BA7909F
     137 [-]: GETIMPORT R4 46; var4 = 0x771B530B
     138 [-]: NAMECALL R2 R2 K47; var3 = var2; var2 = var2[0x6DD7AA66]
     139 [-]: CALL R2 3 2  ; var2 = var2(var3, var4)
L14: 140 [-]: GETUPVAL R4 9; var4 = upvalues[9]
     141 [-]: FASTCALL1 64 R4 L15; 
     142 [-]: GETIMPORT R3 4; var3 = 0x7B998233
     143 [-]: CALL R3 2 2  ; var3 = var3(var4)
L15: 144 [-]: JUMPIFNOT R3 L17; goto L17 if not var3
     145 [-]: GETIMPORT R3 25; var3 = 0xCBD666E1
     146 [-]: LOADN R4 0   ; var4 = 0
     147 [-]: CALL R3 2 1  ; var3(var4)
     148 [-]: GETIMPORT R3 38; var3 = 0xBE190284
     149 [-]: NAMECALL R3 R3 K39; var4 = var3; var3 = var3[0x9C1CC518]
     150 [-]: CALL R3 2 2  ; var3 = var3(var4)
     151 [-]: JUMPIFNOT R3 L16; goto L16 if not var3
     152 [-]: NAMECALL R3 R2 K48; var4 = var2; var3 = var2[0x32302B4A]
     153 [-]: CALL R3 2 1  ; var3(var4)
     154 [-]: RETURN R0 0  ; 
L16: 155 [-]: JUMPBACK L14 ; goto L14
L17: 156 [-]: GETUPVAL R4 0; var4 = upvalues[0]
     157 [-]: GETTABLEKS R3 R4 K49; var3 = var4[0x94B054B1]
     158 [-]: GETUPVAL R5 10; var5 = upvalues[10]
     159 [-]: LOADN R6 3   ; var6 = 3
     160 [-]: GETTABLE R4 R5 R6; var4 = var5[var6]
     161 [-]: LOADN R5 3   ; var5 = 3
     162 [-]: CALL R3 3 1  ; var3(var4, var5)
     163 [-]: GETUPVAL R3 11; var3 = upvalues[11]
     164 [-]: NAMECALL R3 R3 K42; var4 = var3; var3 = var3[0xF4E253B6]
     165 [-]: CALL R3 2 1  ; var3(var4)
     166 [-]: GETUPVAL R3 12; var3 = upvalues[12]
     167 [-]: GETUPVAL R6 13; var6 = upvalues[13]
     168 [-]: GETTABLEKS R5 R6 K50; var5 = var6["WARFRAME_SELECTED"]
     169 [-]: NAMECALL R3 R3 K51; var4 = var3; var3 = var3[0x8ABFF40E]
     170 [-]: CALL R3 3 1  ; var3(var4, var5)
     171 [-]: RETURN R0 0  ; 


; Name:            
; Defined at line: 668
; #Upvalues:       0
; #Parameters:     0
; Is_vararg:       0
; Max Stack Size:  2

L 0:   0 [-]: GETIMPORT R0 2; var0 = _T["isStreamingLevel"]
       1 [-]: JUMPIF R0 L1 ; goto L1 if var0
       2 [-]: GETIMPORT R0 4; var0 = 0xCBD666E1
       3 [-]: LOADN R1 0   ; var1 = 0
       4 [-]: CALL R0 2 1  ; var0(var1)
       5 [-]: JUMPBACK L0  ; goto L0
L 1:   6 [-]: GETIMPORT R0 2; var0 = _T["isStreamingLevel"]
       7 [-]: JUMPIFNOT R0 L2; goto L2 if not var0
       8 [-]: GETIMPORT R0 4; var0 = 0xCBD666E1
       9 [-]: LOADN R1 0   ; var1 = 0
      10 [-]: CALL R0 2 1  ; var0(var1)
      11 [-]: JUMPBACK L1  ; goto L1
L 2:  12 [-]: RETURN R0 0  ; 


; Name:            
; Defined at line: 678
; #Upvalues:       6
; #Parameters:     0
; Is_vararg:       0
; Max Stack Size:  4

       0 [-]: GETIMPORT R0 1; var0 = _T
       1 [-]: LOADB R1 1   ; var1 = true
       2 [-]: SETTABLEKS R1 R0 K2; var1["ArenaNextLevel"] = var0
       3 [-]: GETUPVAL R0 0; var0 = upvalues[0]
       4 [-]: CALL R0 1 1  ; var0()
       5 [-]: GETUPVAL R0 1; var0 = upvalues[1]
       6 [-]: GETIMPORT R2 4; var2 = 0x0469F296
       7 [-]: LOADK R3 K5  ; var3 = "LoadAiSpec"
       8 [-]: CALL R2 2 2  ; var2 = var2(var3)
       9 [-]: LOADB R3 1   ; var3 = true
      10 [-]: NAMECALL R0 R0 K6; var1 = var0; var0 = var0[0xD5F7912B]
      11 [-]: CALL R0 4 1  ; var0(var1, var2, var3)
      12 [-]: GETIMPORT R0 8; var0 = 0x89326C93
      13 [-]: GETUPVAL R3 3; var3 = upvalues[3]
      14 [-]: GETTABLEKS R2 R3 K9; var2 = var3["ARENA_SPAWN_TAG"]
      15 [-]: NAMECALL R0 R0 K10; var1 = var0; var0 = var0[0x46A0EBF5]
      16 [-]: CALL R0 3 2  ; var0 = var0(var1, var2)
      17 [-]: SETUPVAL R0 2; upvalues[0] = var2
      18 [-]: GETIMPORT R0 8; var0 = 0x89326C93
      19 [-]: GETIMPORT R2 4; var2 = 0x0469F296
      20 [-]: LOADK R3 K11 ; var3 = "TutorialPickupWp"
      21 [-]: CALL R2 2 0  ; var2, ... = var2(var3)
      22 [-]: NAMECALL R0 R0 K10; var1 = var0; var0 = var0[0x46A0EBF5]
      23 [-]: CALL R0 0 2  ; var0 = var0(var1, ...)
      24 [-]: SETUPVAL R0 4; upvalues[0] = var4
      25 [-]: GETUPVAL R0 5; var0 = upvalues[5]
      26 [-]: CALL R0 1 1  ; var0()
      27 [-]: RETURN R0 0  ; 


; Name:            
; Defined at line: 691
; #Upvalues:       16
; #Parameters:     0
; Is_vararg:       0
; Max Stack Size:  14

       0 [-]: GETUPVAL R1 0; var1 = upvalues[0]
       1 [-]: GETTABLEKS R0 R1 K0; var0 = var1[0xDC3B2033]
       2 [-]: CALL R0 1 1  ; var0()
       3 [-]: GETIMPORT R0 2; var0 = 0x89326C93
       4 [-]: GETIMPORT R2 4; var2 = 0x0469F296
       5 [-]: LOADK R3 K5  ; var3 = "MenuSuit"
       6 [-]: CALL R2 2 0  ; var2, ... = var2(var3)
       7 [-]: NAMECALL R0 R0 K6; var1 = var0; var0 = var0[0xC7FCADA9]
       8 [-]: CALL R0 0 2  ; var0 = var0(var1, ...)
       9 [-]: GETIMPORT R1 8; var1 = 0xC8802016
      10 [-]: MOVE R2 R0   ; var2 = var0
      11 [-]: CALL R1 2 4  ; var1, var2, var3 = var1(var2)
      12 [-]: FORGPREP_INEXT R1 L2; 
L 0:  13 [-]: NAMECALL R6 R5 K9; var7 = var5; var6 = var5[0xDE321E6F]
      14 [-]: CALL R6 2 2  ; var6 = var6(var7)
      15 [-]: NAMECALL R6 R6 K10; var7 = var6; var6 = var6[0xF7D48EE0]
      16 [-]: CALL R6 2 2  ; var6 = var6(var7)
      17 [-]: GETUPVAL R10 1; var10 = upvalues[1]
      18 [-]: LOADN R11 3  ; var11 = 3
      19 [-]: GETTABLE R9 R10 R11; var9 = var10[var11]
      20 [-]: NAMECALL R7 R6 K11; var8 = var6; var7 = var6[0xF2DEAF69]
      21 [-]: CALL R7 3 2  ; var7 = var7(var8, var9)
      22 [-]: JUMPIFNOT R7 L2; goto L2 if not var7
      23 [-]: LOADB R9 0   ; var9 = false
      24 [-]: LOADB R10 1  ; var10 = true
      25 [-]: NAMECALL R7 R5 K12; var8 = var5; var7 = var5[0x768274D6]
      26 [-]: CALL R7 4 1  ; var7(var8, var9, var10)
      27 [-]: GETIMPORT R7 2; var7 = 0x89326C93
      28 [-]: GETUPVAL R9 2; var9 = upvalues[2]
      29 [-]: NAMECALL R10 R5 K13; var11 = var5; var10 = var5[0xD1586535]
      30 [-]: CALL R10 2 0 ; var10, ... = var10(var11)
      31 [-]: NAMECALL R7 R7 K14; var8 = var7; var7 = var7[0xC7B81E8D]
      32 [-]: CALL R7 0 2  ; var7 = var7(var8, ...)
      33 [-]: LOADK R10 K15; var10 = "Disable"
      34 [-]: NAMECALL R8 R7 K16; var9 = var7; var8 = var7[0x8EB2112D]
      35 [-]: CALL R8 3 1  ; var8(var9, var10)
      36 [-]: GETIMPORT R8 2; var8 = 0x89326C93
      37 [-]: GETIMPORT R10 4; var10 = 0x0469F296
      38 [-]: LOADK R11 K17; var11 = "WarframeEmptyStandEffect"
      39 [-]: CALL R10 2 2 ; var10 = var10(var11)
      40 [-]: NAMECALL R11 R5 K13; var12 = var5; var11 = var5[0xD1586535]
      41 [-]: CALL R11 2 0 ; var11, ... = var11(var12)
      42 [-]: NAMECALL R8 R8 K14; var9 = var8; var8 = var8[0xC7B81E8D]
      43 [-]: CALL R8 0 2  ; var8 = var8(var9, ...)
      44 [-]: FASTCALL1 64 R8 L1; 
      45 [-]: MOVE R10 R8  ; var10 = var8
      46 [-]: GETIMPORT R9 19; var9 = 0x7B998233
      47 [-]: CALL R9 2 2  ; var9 = var9(var10)
L 1:  48 [-]: JUMPIF R9 L2 ; goto L2 if var9
      49 [-]: LOADB R11 0  ; var11 = false
      50 [-]: LOADB R12 1  ; var12 = true
      51 [-]: NAMECALL R9 R8 K12; var10 = var8; var9 = var8[0x768274D6]
      52 [-]: CALL R9 4 1  ; var9(var10, var11, var12)
L 2:  53 [-]: FORGLOOP R1 L0 2 [inext]; 
      54 [-]: GETUPVAL R1 3; var1 = upvalues[3]
      55 [-]: LOADK R3 K20 ; var3 = "StartPlaying"
      56 [-]: NAMECALL R1 R1 K16; var2 = var1; var1 = var1[0x8EB2112D]
      57 [-]: CALL R1 3 1  ; var1(var2, var3)
L 3:  58 [-]: GETUPVAL R1 3; var1 = upvalues[3]
      59 [-]: NAMECALL R1 R1 K21; var2 = var1; var1 = var1[0x1C84839C]
      60 [-]: CALL R1 2 2  ; var1 = var1(var2)
      61 [-]: JUMPIFNOT R1 L4; goto L4 if not var1
      62 [-]: GETIMPORT R1 23; var1 = 0xCBD666E1
      63 [-]: LOADN R2 0   ; var2 = 0
      64 [-]: CALL R1 2 1  ; var1(var2)
      65 [-]: JUMPBACK L3  ; goto L3
L 4:  66 [-]: GETIMPORT R1 2; var1 = 0x89326C93
      67 [-]: GETIMPORT R3 4; var3 = 0x0469F296
      68 [-]: LOADK R4 K24 ; var4 = "MagFrame"
      69 [-]: CALL R3 2 0  ; var3, ... = var3(var4)
      70 [-]: NAMECALL R1 R1 K25; var2 = var1; var1 = var1[0x46A0EBF5]
      71 [-]: CALL R1 0 2  ; var1 = var1(var2, ...)
      72 [-]: GETIMPORT R2 2; var2 = 0x89326C93
      73 [-]: GETIMPORT R4 4; var4 = 0x0469F296
      74 [-]: LOADK R5 K26 ; var5 = "ExcaliburFrame"
      75 [-]: CALL R4 2 0  ; var4, ... = var4(var5)
      76 [-]: NAMECALL R2 R2 K25; var3 = var2; var2 = var2[0x46A0EBF5]
      77 [-]: CALL R2 0 2  ; var2 = var2(var3, ...)
      78 [-]: GETIMPORT R3 2; var3 = 0x89326C93
      79 [-]: GETIMPORT R5 4; var5 = 0x0469F296
      80 [-]: LOADK R6 K27 ; var6 = "VoltFrame"
      81 [-]: CALL R5 2 0  ; var5, ... = var5(var6)
      82 [-]: NAMECALL R3 R3 K25; var4 = var3; var3 = var3[0x46A0EBF5]
      83 [-]: CALL R3 0 2  ; var3 = var3(var4, ...)
      84 [-]: LOADB R6 0   ; var6 = false
      85 [-]: LOADB R7 1   ; var7 = true
      86 [-]: NAMECALL R4 R1 K12; var5 = var1; var4 = var1[0x768274D6]
      87 [-]: CALL R4 4 1  ; var4(var5, var6, var7)
      88 [-]: LOADB R6 0   ; var6 = false
      89 [-]: LOADB R7 1   ; var7 = true
      90 [-]: NAMECALL R4 R2 K12; var5 = var2; var4 = var2[0x768274D6]
      91 [-]: CALL R4 4 1  ; var4(var5, var6, var7)
      92 [-]: LOADB R6 0   ; var6 = false
      93 [-]: LOADB R7 1   ; var7 = true
      94 [-]: NAMECALL R4 R3 K12; var5 = var3; var4 = var3[0x768274D6]
      95 [-]: CALL R4 4 1  ; var4(var5, var6, var7)
      96 [-]: GETUPVAL R5 5; var5 = upvalues[5]
      97 [-]: GETTABLEKS R4 R5 K28; var4 = var5[0x3DF1EF0C]
      98 [-]: LOADB R5 1   ; var5 = true
      99 [-]: GETUPVAL R6 6; var6 = upvalues[6]
     100 [-]: GETUPVAL R7 4; var7 = upvalues[4]
     101 [-]: CALL R4 4 2  ; var4 = var4(var5, var6, var7)
     102 [-]: SETUPVAL R4 4; upvalues[4] = var4
     103 [-]: GETIMPORT R4 23; var4 = 0xCBD666E1
     104 [-]: LOADN R5 0   ; var5 = 0
     105 [-]: CALL R4 2 1  ; var4(var5)
     106 [-]: GETUPVAL R4 4; var4 = upvalues[4]
     107 [-]: GETUPVAL R6 4; var6 = upvalues[4]
     108 [-]: NAMECALL R6 R6 K29; var7 = var6; var6 = var6[0x5280B883]
     109 [-]: CALL R6 2 0  ; var6, ... = var6(var7)
     110 [-]: NAMECALL R4 R4 K30; var5 = var4; var4 = var4[0x89C6DBF7]
     111 [-]: CALL R4 0 1  ; var4(var5, ...)
     112 [-]: GETUPVAL R5 7; var5 = upvalues[7]
     113 [-]: GETTABLEKS R4 R5 K31; var4 = var5[0xDD1A2C02]
     114 [-]: LOADB R5 0   ; var5 = false
     115 [-]: LOADN R6 3   ; var6 = 3
     116 [-]: CALL R4 3 1  ; var4(var5, var6)
     117 [-]: GETIMPORT R4 2; var4 = 0x89326C93
     118 [-]: GETIMPORT R6 4; var6 = 0x0469F296
     119 [-]: LOADK R7 K32 ; var7 = "QuestTeshinCaveExit"
     120 [-]: CALL R6 2 0  ; var6, ... = var6(var7)
     121 [-]: NAMECALL R4 R4 K25; var5 = var4; var4 = var4[0x46A0EBF5]
     122 [-]: CALL R4 0 2  ; var4 = var4(var5, ...)
     123 [-]: GETUPVAL R6 9; var6 = upvalues[9]
     124 [-]: GETTABLEKS R5 R6 K33; var5 = var6[0xD9337924]
     125 [-]: GETIMPORT R6 4; var6 = 0x0469F296
     126 [-]: LOADK R7 K34 ; var7 = "ParkourTutorialSpawn"
     127 [-]: CALL R6 2 2  ; var6 = var6(var7)
     128 [-]: LOADB R7 1   ; var7 = true
     129 [-]: LOADN R8 0   ; var8 = 0
     130 [-]: CALL R5 4 2  ; var5 = var5(var6, var7, var8)
     131 [-]: SETUPVAL R5 8; upvalues[5] = var8
     132 [-]: GETIMPORT R5 2; var5 = 0x89326C93
     133 [-]: GETIMPORT R7 36; var7 = 0xBB76409B
     134 [-]: NAMECALL R9 R4 K13; var10 = var4; var9 = var4[0xD1586535]
     135 [-]: CALL R9 2 2  ; var9 = var9(var10)
     136 [-]: GETIMPORT R10 38; var10 = 0xA421AF95
     137 [-]: LOADN R11 0  ; var11 = 0
     138 [-]: LOADN R12 2  ; var12 = 2
     139 [-]: LOADN R13 0  ; var13 = 0
     140 [-]: CALL R10 4 2 ; var10 = var10(var11, var12, var13)
     141 [-]: ADD R8 R9 R10; var8 = var9 + var10
     142 [-]: NAMECALL R9 R4 K39; var10 = var4; var9 = var4[0xCB3851B8]
     143 [-]: CALL R9 2 0  ; var9, ... = var9(var10)
     144 [-]: NAMECALL R5 R5 K40; var6 = var5; var5 = var5[0x05909209]
     145 [-]: CALL R5 0 2  ; var5 = var5(var6, ...)
     146 [-]: SETUPVAL R5 10; upvalues[5] = var10
     147 [-]: GETUPVAL R6 0; var6 = upvalues[0]
     148 [-]: GETTABLEKS R5 R6 K41; var5 = var6[0xA1DF01D6]
     149 [-]: GETUPVAL R7 11; var7 = upvalues[11]
     150 [-]: GETTABLEKS R6 R7 K42; var6 = var7["ENTER_POTAL_OBJ"]
     151 [-]: CALL R5 2 1  ; var5(var6)
L 5: 152 [-]: GETUPVAL R6 12; var6 = upvalues[12]
     153 [-]: GETTABLEKS R5 R6 K43; var5 = var6[0x440B780E]
     154 [-]: GETUPVAL R6 13; var6 = upvalues[13]
     155 [-]: LOADN R8 0   ; var8 = 0
     156 [-]: NAMECALL R6 R6 K44; var7 = var6; var6 = var6[0xE3A0BBCA]
     157 [-]: CALL R6 3 2  ; var6 = var6(var7, var8)
     158 [-]: GETIMPORT R8 48; var8 = _T["ArenaStreamingLayerIndex"]
     159 [-]: ADDK R7 R8 K45; var7 = var8 + 1
     160 [-]: CALL R5 3 2  ; var5 = var5(var6, var7)
     161 [-]: JUMPIF R5 L6 ; goto L6 if var5
     162 [-]: GETIMPORT R5 23; var5 = 0xCBD666E1
     163 [-]: LOADN R6 0   ; var6 = 0
     164 [-]: CALL R5 2 1  ; var5(var6)
     165 [-]: JUMPBACK L5  ; goto L5
L 6: 166 [-]: GETUPVAL R5 14; var5 = upvalues[14]
     167 [-]: GETUPVAL R8 15; var8 = upvalues[15]
     168 [-]: GETTABLEKS R7 R8 K49; var7 = var8["MOVEMENT_TUTORIAL"]
     169 [-]: NAMECALL R5 R5 K50; var6 = var5; var5 = var5[0x8ABFF40E]
     170 [-]: CALL R5 3 1  ; var5(var6, var7)
     171 [-]: RETURN R0 0  ; 


; Name:            
; Defined at line: 740
; #Upvalues:       1
; #Parameters:     0
; Is_vararg:       0
; Max Stack Size:  8

       0 [-]: GETIMPORT R0 1; var0 = 0x7ED0A956
       1 [-]: LOADK R1 K2  ; var1 = "/Lotus/Powersuits/PowersuitAbilities/OperatorTransferenceAbility"
       2 [-]: CALL R0 2 2  ; var0 = var0(var1)
       3 [-]: LOADN R1 0   ; var1 = 0
L 0:   4 [-]: LOADN R2 2   ; var2 = 2
       5 [-]: JUMPIFNOTLT R1 R2 L4; goto L4 if var1 >= var262689
       6 [-]: GETIMPORT R2 4; var2 = 0x89326C93
       7 [-]: NAMECALL R2 R2 K5; var3 = var2; var2 = var2[0xFB64E76C]
       8 [-]: CALL R2 2 2  ; var2 = var2(var3)
       9 [-]: LOADN R4 0   ; var4 = 0
      10 [-]: NAMECALL R2 R2 K6; var3 = var2; var2 = var2[0xE3A0BBCA]
      11 [-]: CALL R2 3 2  ; var2 = var2(var3, var4)
      12 [-]: NAMECALL R2 R2 K7; var3 = var2; var2 = var2[0xDE321E6F]
      13 [-]: CALL R2 2 2  ; var2 = var2(var3)
      14 [-]: NAMECALL R2 R2 K8; var3 = var2; var2 = var2[0xF7D48EE0]
      15 [-]: CALL R2 2 2  ; var2 = var2(var3)
      16 [-]: FASTCALL1 64 R2 L1; 
      17 [-]: MOVE R4 R2   ; var4 = var2
      18 [-]: GETIMPORT R3 10; var3 = 0x7B998233
      19 [-]: CALL R3 2 2  ; var3 = var3(var4)
L 1:  20 [-]: JUMPIF R3 L3 ; goto L3 if var3
      21 [-]: MOVE R5 R0   ; var5 = var0
      22 [-]: NAMECALL R3 R2 K11; var4 = var2; var3 = var2[0x689412A5]
      23 [-]: CALL R3 3 2  ; var3 = var3(var4, var5)
      24 [-]: FASTCALL1 64 R3 L2; 
      25 [-]: MOVE R5 R3   ; var5 = var3
      26 [-]: GETIMPORT R4 10; var4 = 0x7B998233
      27 [-]: CALL R4 2 2  ; var4 = var4(var5)
L 2:  28 [-]: JUMPIF R4 L3 ; goto L3 if var4
      29 [-]: NAMECALL R4 R3 K12; var5 = var3; var4 = var3[0x30F46140]
      30 [-]: CALL R4 2 2  ; var4 = var4(var5)
      31 [-]: JUMPIF R4 L3 ; goto L3 if var4
      32 [-]: LOADB R6 1   ; var6 = true
      33 [-]: GETUPVAL R7 0; var7 = upvalues[0]
      34 [-]: NAMECALL R4 R2 K13; var5 = var2; var4 = var2[0x83DF59E9]
      35 [-]: CALL R4 4 1  ; var4(var5, var6, var7)
      36 [-]: RETURN R0 0  ; 
L 3:  37 [-]: GETIMPORT R3 15; var3 = 0xCBD666E1
      38 [-]: LOADN R4 0   ; var4 = 0
      39 [-]: CALL R3 2 1  ; var3(var4)
      40 [-]: GETIMPORT R3 17; var3 = 0xFFF641AF
      41 [-]: CALL R3 1 2  ; var3 = var3()
      42 [-]: ADD R1 R1 R3 ; var1 = var1 + var3
      43 [-]: JUMPBACK L0  ; goto L0
L 4:  44 [-]: RETURN R0 0  ; 


; Name:            
; Defined at line: 757
; #Upvalues:       14
; #Parameters:     0
; Is_vararg:       0
; Max Stack Size:  12

       0 [-]: GETUPVAL R0 0; var0 = upvalues[0]
       1 [-]: CALL R0 1 1  ; var0()
       2 [-]: GETUPVAL R1 1; var1 = upvalues[1]
       3 [-]: GETTABLEKS R0 R1 K0; var0 = var1[0xA1DF01D6]
       4 [-]: GETUPVAL R2 2; var2 = upvalues[2]
       5 [-]: GETTABLEKS R1 R2 K1; var1 = var2["MOVEMENT_TUTORIAL_OBJ"]
       6 [-]: CALL R0 2 1  ; var0(var1)
       7 [-]: GETUPVAL R0 3; var0 = upvalues[3]
       8 [-]: CALL R0 1 1  ; var0()
       9 [-]: GETIMPORT R0 3; var0 = 0x89326C93
      10 [-]: GETIMPORT R2 5; var2 = 0x0469F296
      11 [-]: LOADK R3 K6  ; var3 = "DuviriCompleteTutorialTrigger"
      12 [-]: CALL R2 2 0  ; var2, ... = var2(var3)
      13 [-]: NAMECALL R0 R0 K7; var1 = var0; var0 = var0[0x46A0EBF5]
      14 [-]: CALL R0 0 2  ; var0 = var0(var1, ...)
      15 [-]: NAMECALL R1 R0 K8; var2 = var0; var1 = var0[0x383D2E7D]
      16 [-]: CALL R1 2 1  ; var1(var2)
      17 [-]: GETIMPORT R1 10; var1 = 0x11A19C5E
      18 [-]: MOVE R2 R0   ; var2 = var0
      19 [-]: LOADK R3 K11 ; var3 = "OnTouched"
      20 [-]: CALL R1 3 1  ; var1(var2, var3)
L 0:  21 [-]: GETUPVAL R1 4; var1 = upvalues[4]
      22 [-]: JUMPIF R1 L1 ; goto L1 if var1
      23 [-]: GETIMPORT R1 13; var1 = 0xCBD666E1
      24 [-]: LOADN R2 0   ; var2 = 0
      25 [-]: CALL R1 2 1  ; var1(var2)
      26 [-]: JUMPBACK L0  ; goto L0
L 1:  27 [-]: GETUPVAL R2 5; var2 = upvalues[5]
      28 [-]: GETTABLEKS R1 R2 K14; var1 = var2[0x11DCFE97]
      29 [-]: GETIMPORT R2 5; var2 = 0x0469F296
      30 [-]: LOADK R3 K15 ; var3 = "DDuvParQWF0710"
      31 [-]: CALL R2 2 2  ; var2 = var2(var3)
      32 [-]: LOADB R3 0   ; var3 = false
      33 [-]: LOADB R4 0   ; var4 = false
      34 [-]: LOADN R5 4   ; var5 = 4
      35 [-]: CALL R1 5 1  ; var1(var2, var3, var4, var5)
      36 [-]: GETUPVAL R2 5; var2 = upvalues[5]
      37 [-]: GETTABLEKS R1 R2 K16; var1 = var2[0xFC87A231]
      38 [-]: CALL R1 1 1  ; var1()
      39 [-]: GETUPVAL R2 5; var2 = upvalues[5]
      40 [-]: GETTABLEKS R1 R2 K17; var1 = var2[0x9742B85B]
      41 [-]: GETUPVAL R2 6; var2 = upvalues[6]
      42 [-]: GETIMPORT R3 5; var3 = 0x0469F296
      43 [-]: LOADK R4 K18 ; var4 = "DDuvParQWF0720"
      44 [-]: CALL R3 2 0  ; var3, ... = var3(var4)
      45 [-]: CALL R1 0 1  ; var1(var2, ...)
      46 [-]: GETIMPORT R1 3; var1 = 0x89326C93
      47 [-]: GETIMPORT R3 5; var3 = 0x0469F296
      48 [-]: LOADK R4 K19 ; var4 = "PortalWp"
      49 [-]: CALL R3 2 0  ; var3, ... = var3(var4)
      50 [-]: NAMECALL R1 R1 K7; var2 = var1; var1 = var1[0x46A0EBF5]
      51 [-]: CALL R1 0 2  ; var1 = var1(var2, ...)
      52 [-]: GETIMPORT R2 3; var2 = 0x89326C93
      53 [-]: GETUPVAL R5 7; var5 = upvalues[7]
      54 [-]: GETTABLEKS R4 R5 K20; var4 = var5["ARENA_SPAWN_TAG"]
      55 [-]: NAMECALL R2 R2 K7; var3 = var2; var2 = var2[0x46A0EBF5]
      56 [-]: CALL R2 3 2  ; var2 = var2(var3, var4)
      57 [-]: GETUPVAL R4 9; var4 = upvalues[9]
      58 [-]: GETTABLEKS R3 R4 K21; var3 = var4[0x17AB718C]
      59 [-]: GETIMPORT R4 23; var4 = 0xC61B9FC4
      60 [-]: NAMECALL R5 R1 K24; var6 = var1; var5 = var1[0xD1586535]
      61 [-]: CALL R5 2 2  ; var5 = var5(var6)
      62 [-]: NAMECALL R6 R1 K25; var7 = var1; var6 = var1[0xCB3851B8]
      63 [-]: CALL R6 2 2  ; var6 = var6(var7)
      64 [-]: NAMECALL R7 R2 K24; var8 = var2; var7 = var2[0xD1586535]
      65 [-]: CALL R7 2 2  ; var7 = var7(var8)
      66 [-]: NAMECALL R8 R2 K25; var9 = var2; var8 = var2[0xCB3851B8]
      67 [-]: CALL R8 2 2  ; var8 = var8(var9)
      68 [-]: LOADN R9 0   ; var9 = 0
      69 [-]: CALL R3 7 2  ; var3 = var3(var4, var5, var6, var7, var8, var9)
      70 [-]: SETUPVAL R3 8; upvalues[3] = var8
      71 [-]: GETIMPORT R3 3; var3 = 0x89326C93
      72 [-]: GETIMPORT R5 27; var5 = 0xED313964
      73 [-]: NAMECALL R7 R1 K24; var8 = var1; var7 = var1[0xD1586535]
      74 [-]: CALL R7 2 2  ; var7 = var7(var8)
      75 [-]: GETIMPORT R8 29; var8 = 0xA421AF95
      76 [-]: LOADN R9 0   ; var9 = 0
      77 [-]: LOADN R10 1  ; var10 = 1
      78 [-]: LOADN R11 0  ; var11 = 0
      79 [-]: CALL R8 4 2  ; var8 = var8(var9, var10, var11)
      80 [-]: ADD R6 R7 R8 ; var6 = var7 + var8
      81 [-]: GETIMPORT R7 31; var7 = ZERO_ROTATION
      82 [-]: NAMECALL R3 R3 K32; var4 = var3; var3 = var3[0x05909209]
      83 [-]: CALL R3 5 2  ; var3 = var3(var4, var5, var6, var7)
      84 [-]: NAMECALL R4 R3 K8; var5 = var3; var4 = var3[0x383D2E7D]
      85 [-]: CALL R4 2 1  ; var4(var5)
      86 [-]: NAMECALL R4 R0 K33; var5 = var0; var4 = var0[0xE79E7EF4]
      87 [-]: CALL R4 2 2  ; var4 = var4(var5)
      88 [-]: NAMECALL R4 R4 K34; var5 = var4; var4 = var4[0xB06572DA]
      89 [-]: CALL R4 2 2  ; var4 = var4(var5)
L 2:  90 [-]: GETUPVAL R6 10; var6 = upvalues[10]
      91 [-]: GETTABLEKS R5 R6 K35; var5 = var6[0x440B780E]
      92 [-]: GETUPVAL R6 11; var6 = upvalues[11]
      93 [-]: LOADN R8 0   ; var8 = 0
      94 [-]: NAMECALL R6 R6 K36; var7 = var6; var6 = var6[0xE3A0BBCA]
      95 [-]: CALL R6 3 2  ; var6 = var6(var7, var8)
      96 [-]: MOVE R7 R4   ; var7 = var4
      97 [-]: CALL R5 3 2  ; var5 = var5(var6, var7)
      98 [-]: JUMPIFNOT R5 L3; goto L3 if not var5
      99 [-]: GETIMPORT R5 13; var5 = 0xCBD666E1
     100 [-]: LOADN R6 0   ; var6 = 0
     101 [-]: CALL R5 2 1  ; var5(var6)
     102 [-]: JUMPBACK L2  ; goto L2
L 3: 103 [-]: NAMECALL R5 R3 K37; var6 = var3; var5 = var3[0xA2880940]
     104 [-]: CALL R5 2 1  ; var5(var6)
     105 [-]: GETIMPORT R5 39; var5 = _T
     106 [-]: LOADB R6 1   ; var6 = true
     107 [-]: SETTABLEKS R6 R5 K40; var6["ArenaDestroyLevel"] = var5
     108 [-]: GETUPVAL R5 12; var5 = upvalues[12]
     109 [-]: GETUPVAL R8 13; var8 = upvalues[13]
     110 [-]: GETTABLEKS R7 R8 K41; var7 = var8["TEST_SUIT"]
     111 [-]: NAMECALL R5 R5 K42; var6 = var5; var5 = var5[0x8ABFF40E]
     112 [-]: CALL R5 3 1  ; var5(var6, var7)
     113 [-]: RETURN R0 0  ; 


; Name:            
; Defined at line: 795
; #Upvalues:       4
; #Parameters:     0
; Is_vararg:       0
; Max Stack Size:  2

       0 [-]: LOADB R0 1   ; var0 = true
       1 [-]: SETUPVAL R0 0; upvalues[0] = var0
       2 [-]: GETUPVAL R1 1; var1 = upvalues[1]
       3 [-]: GETTABLEKS R0 R1 K0; var0 = var1[0x1CD67745]
       4 [-]: GETUPVAL R1 2; var1 = upvalues[2]
       5 [-]: CALL R0 2 1  ; var0(var1)
       6 [-]: GETIMPORT R0 2; var0 = 0x89326C93
       7 [-]: NAMECALL R0 R0 K3; var1 = var0; var0 = var0[0x78298275]
       8 [-]: CALL R0 2 2  ; var0 = var0(var1)
       9 [-]: SETUPVAL R0 3; upvalues[0] = var3
      10 [-]: LOADB R0 0   ; var0 = false
      11 [-]: SETUPVAL R0 0; upvalues[0] = var0
      12 [-]: RETURN R0 0  ; 


; Name:            
; Defined at line: 802
; #Upvalues:       1
; #Parameters:     0
; Is_vararg:       0
; Max Stack Size:  8

       0 [-]: GETIMPORT R0 1; var0 = 0xC8802016
       1 [-]: GETUPVAL R1 0; var1 = upvalues[0]
       2 [-]: CALL R0 2 4  ; var0, var1, var2 = var0(var1)
       3 [-]: FORGPREP_INEXT R0 L4; 
L 0:   4 [-]: FASTCALL1 64 R4 L1; 
       5 [-]: MOVE R6 R4   ; var6 = var4
       6 [-]: GETIMPORT R5 3; var5 = 0x7B998233
       7 [-]: CALL R5 2 2  ; var5 = var5(var6)
L 1:   8 [-]: JUMPIF R5 L4 ; goto L4 if var5
       9 [-]: NAMECALL R5 R4 K4; var6 = var4; var5 = var4[0x2047CFE7]
      10 [-]: CALL R5 2 2  ; var5 = var5(var6)
      11 [-]: JUMPIF R5 L4 ; goto L4 if var5
      12 [-]: GETIMPORT R7 6; var7 = gBaseMarkerInfoType
      13 [-]: NAMECALL R5 R4 K7; var6 = var4; var5 = var4[0xC9F6A7D7]
      14 [-]: CALL R5 3 2  ; var5 = var5(var6, var7)
      15 [-]: FASTCALL1 64 R5 L2; 
      16 [-]: MOVE R7 R5   ; var7 = var5
      17 [-]: GETIMPORT R6 3; var6 = 0x7B998233
      18 [-]: CALL R6 2 2  ; var6 = var6(var7)
L 2:  19 [-]: JUMPIF R6 L3 ; goto L3 if var6
      20 [-]: NAMECALL R6 R5 K8; var7 = var5; var6 = var5[0xA2880940]
      21 [-]: CALL R6 2 1  ; var6(var7)
L 3:  22 [-]: NAMECALL R6 R4 K9; var7 = var4; var6 = var4[0xFB3BBA96]
      23 [-]: CALL R6 2 1  ; var6(var7)
L 4:  24 [-]: FORGLOOP R0 L0 2 [inext]; 
      25 [-]: NEWTABLE R0 0 0; var0 = {}
      26 [-]: SETUPVAL R0 0; upvalues[0] = var0
      27 [-]: RETURN R0 0  ; 


; Name:            
; Defined at line: 815
; #Upvalues:       19
; #Parameters:     0
; Is_vararg:       0
; Max Stack Size:  6

       0 [-]: GETIMPORT R0 2; var0 = 0x34291F5C[0x1467D5F4]
       1 [-]: CALL R0 1 2  ; var0 = var0()
       2 [-]: SETUPVAL R0 0; upvalues[0] = var0
       3 [-]: GETUPVAL R1 1; var1 = upvalues[1]
       4 [-]: FASTCALL1 64 R1 L0; 
       5 [-]: GETIMPORT R0 4; var0 = 0x7B998233
       6 [-]: CALL R0 2 2  ; var0 = var0(var1)
L 0:   7 [-]: JUMPIF R0 L1 ; goto L1 if var0
       8 [-]: GETUPVAL R0 1; var0 = upvalues[1]
       9 [-]: NAMECALL R0 R0 K5; var1 = var0; var0 = var0[0xA2880940]
      10 [-]: CALL R0 2 1  ; var0(var1)
L 1:  11 [-]: GETUPVAL R1 2; var1 = upvalues[2]
      12 [-]: FASTCALL1 64 R1 L2; 
      13 [-]: GETIMPORT R0 4; var0 = 0x7B998233
      14 [-]: CALL R0 2 2  ; var0 = var0(var1)
L 2:  15 [-]: JUMPIF R0 L3 ; goto L3 if var0
      16 [-]: GETUPVAL R1 3; var1 = upvalues[3]
      17 [-]: GETTABLEKS R0 R1 K6; var0 = var1[0xA2080540]
      18 [-]: GETUPVAL R1 2; var1 = upvalues[2]
      19 [-]: CALL R0 2 1  ; var0(var1)
L 3:  20 [-]: GETUPVAL R0 4; var0 = upvalues[4]
      21 [-]: GETIMPORT R2 8; var2 = 0xA3A6D0C9
      22 [-]: LOADB R3 0   ; var3 = false
      23 [-]: NAMECALL R0 R0 K9; var1 = var0; var0 = var0[0x659D451F]
      24 [-]: CALL R0 4 1  ; var0(var1, var2, var3)
      25 [-]: GETIMPORT R0 11; var0 = 0x89326C93
      26 [-]: NAMECALL R0 R0 K12; var1 = var0; var0 = var0[0x78298275]
      27 [-]: CALL R0 2 2  ; var0 = var0(var1)
      28 [-]: SETUPVAL R0 4; upvalues[0] = var4
      29 [-]: GETUPVAL R0 4; var0 = upvalues[4]
      30 [-]: NAMECALL R0 R0 K13; var1 = var0; var0 = var0[0xDE321E6F]
      31 [-]: CALL R0 2 2  ; var0 = var0(var1)
      32 [-]: NAMECALL R0 R0 K14; var1 = var0; var0 = var0[0xF7D48EE0]
      33 [-]: CALL R0 2 2  ; var0 = var0(var1)
      34 [-]: NAMECALL R3 R0 K15; var4 = var0; var3 = var0[0xDED54C60]
      35 [-]: CALL R3 2 0  ; var3, ... = var3(var4)
      36 [-]: NAMECALL R1 R0 K16; var2 = var0; var1 = var0[0x6E19D3FE]
      37 [-]: CALL R1 0 1  ; var1(var2, ...)
      38 [-]: GETUPVAL R2 5; var2 = upvalues[5]
      39 [-]: GETTABLEKS R1 R2 K17; var1 = var2[0x9742B85B]
      40 [-]: GETUPVAL R2 6; var2 = upvalues[6]
      41 [-]: GETIMPORT R3 19; var3 = 0x0469F296
      42 [-]: LOADK R4 K20 ; var4 = "DDuvParQUndercroft0730"
      43 [-]: CALL R3 2 0  ; var3, ... = var3(var4)
      44 [-]: CALL R1 0 1  ; var1(var2, ...)
      45 [-]: GETUPVAL R2 5; var2 = upvalues[5]
      46 [-]: GETTABLEKS R1 R2 K21; var1 = var2[0x11DCFE97]
      47 [-]: GETIMPORT R2 19; var2 = 0x0469F296
      48 [-]: LOADK R3 K22 ; var3 = "DDuvParQUndercroft0740"
      49 [-]: CALL R2 2 2  ; var2 = var2(var3)
      50 [-]: LOADB R3 0   ; var3 = false
      51 [-]: LOADB R4 0   ; var4 = false
      52 [-]: LOADN R5 4   ; var5 = 4
      53 [-]: CALL R1 5 1  ; var1(var2, var3, var4, var5)
      54 [-]: GETUPVAL R2 5; var2 = upvalues[5]
      55 [-]: GETTABLEKS R1 R2 K17; var1 = var2[0x9742B85B]
      56 [-]: GETUPVAL R2 6; var2 = upvalues[6]
      57 [-]: GETIMPORT R3 19; var3 = 0x0469F296
      58 [-]: LOADK R4 K23 ; var4 = "DDuvParQUndercroft0750"
      59 [-]: CALL R3 2 0  ; var3, ... = var3(var4)
      60 [-]: CALL R1 0 1  ; var1(var2, ...)
      61 [-]: GETUPVAL R2 5; var2 = upvalues[5]
      62 [-]: GETTABLEKS R1 R2 K24; var1 = var2[0xFC87A231]
      63 [-]: CALL R1 1 1  ; var1()
      64 [-]: GETUPVAL R2 7; var2 = upvalues[7]
      65 [-]: GETTABLEKS R1 R2 K25; var1 = var2[0xA1DF01D6]
      66 [-]: GETUPVAL R3 8; var3 = upvalues[8]
      67 [-]: GETTABLEKS R2 R3 K26; var2 = var3["TEST_SUIT_OBJ"]
      68 [-]: CALL R1 2 1  ; var1(var2)
      69 [-]: GETUPVAL R2 7; var2 = upvalues[7]
      70 [-]: GETTABLEKS R1 R2 K27; var1 = var2[0xEA753E99]
      71 [-]: GETUPVAL R3 8; var3 = upvalues[8]
      72 [-]: GETTABLEKS R2 R3 K28; var2 = var3["BATTLE_PROGRESS_BAR"]
      73 [-]: LOADN R3 0   ; var3 = 0
      74 [-]: LOADN R4 5   ; var4 = 5
      75 [-]: CALL R1 4 1  ; var1(var2, var3, var4)
      76 [-]: LOADB R1 1   ; var1 = true
      77 [-]: SETUPVAL R1 9; upvalues[1] = var9
      78 [-]: GETUPVAL R1 10; var1 = upvalues[10]
      79 [-]: GETUPVAL R3 8; var3 = upvalues[8]
      80 [-]: GETTABLEKS R2 R3 K29; var2 = var3["ABILITY_TUTORIAL"]
      81 [-]: CALL R1 2 1  ; var1(var2)
      82 [-]: GETIMPORT R1 31; var1 = 0x3D106989
      83 [-]: LOADK R2 K32 ; var2 = "Spawning Enemies"
      84 [-]: CALL R1 2 1  ; var1(var2)
      85 [-]: LOADN R1 0   ; var1 = 0
      86 [-]: SETUPVAL R1 11; upvalues[1] = var11
L 4:  87 [-]: GETUPVAL R1 11; var1 = upvalues[11]
      88 [-]: LOADN R2 5   ; var2 = 5
      89 [-]: JUMPIFNOTLT R1 R2 L7; goto L7 if var1 >= var786748
      90 [-]: GETUPVAL R1 12; var1 = upvalues[12]
      91 [-]: GETIMPORT R2 34; var2 = 0xFFF641AF
      92 [-]: CALL R2 1 0  ; var2, ... = var2()
      93 [-]: CALL R1 0 1  ; var1(var2, ...)
      94 [-]: GETUPVAL R2 4; var2 = upvalues[4]
      95 [-]: FASTCALL1 64 R2 L5; 
      96 [-]: GETIMPORT R1 4; var1 = 0x7B998233
      97 [-]: CALL R1 2 2  ; var1 = var1(var2)
L 5:  98 [-]: JUMPIF R1 L6 ; goto L6 if var1
      99 [-]: GETUPVAL R1 4; var1 = upvalues[4]
     100 [-]: NAMECALL R1 R1 K35; var2 = var1; var1 = var1[0x2047CFE7]
     101 [-]: CALL R1 2 2  ; var1 = var1(var2)
     102 [-]: JUMPIF R1 L6 ; goto L6 if var1
     103 [-]: GETUPVAL R1 13; var1 = upvalues[13]
     104 [-]: CALL R1 1 1  ; var1()
     105 [-]: GETUPVAL R1 14; var1 = upvalues[14]
     106 [-]: CALL R1 1 1  ; var1()
L 6: 107 [-]: GETIMPORT R1 37; var1 = 0xCBD666E1
     108 [-]: LOADN R2 0   ; var2 = 0
     109 [-]: CALL R1 2 1  ; var1(var2)
     110 [-]: JUMPBACK L4  ; goto L4
L 7: 111 [-]: LOADB R1 1   ; var1 = true
     112 [-]: SETUPVAL R1 15; upvalues[1] = var15
     113 [-]: GETIMPORT R1 40; var1 = _T["HideImpactMessage"]
     114 [-]: CALL R1 1 1  ; var1()
     115 [-]: GETUPVAL R2 7; var2 = upvalues[7]
     116 [-]: GETTABLEKS R1 R2 K41; var1 = var2[0xBD3CE95D]
     117 [-]: CALL R1 1 1  ; var1()
     118 [-]: GETUPVAL R2 7; var2 = upvalues[7]
     119 [-]: GETTABLEKS R1 R2 K42; var1 = var2[0xDC3B2033]
     120 [-]: CALL R1 1 1  ; var1()
     121 [-]: GETUPVAL R1 16; var1 = upvalues[16]
     122 [-]: CALL R1 1 1  ; var1()
     123 [-]: GETUPVAL R1 17; var1 = upvalues[17]
     124 [-]: GETUPVAL R4 18; var4 = upvalues[18]
     125 [-]: GETTABLEKS R3 R4 K43; var3 = var4["SELECT_SECONDARY"]
     126 [-]: NAMECALL R1 R1 K44; var2 = var1; var1 = var1[0x8ABFF40E]
     127 [-]: CALL R1 3 1  ; var1(var2, var3)
     128 [-]: RETURN R0 0  ; 


; Name:            
; Defined at line: 864
; #Upvalues:       3
; #Parameters:     2
; Is_vararg:       0
; Max Stack Size:  6

       0 [-]: GETUPVAL R2 0; var2 = upvalues[0]
       1 [-]: GETIMPORT R5 2; var5 = _T["DuviriQuestWeapons"]
       2 [-]: GETTABLE R4 R5 R0; var4 = var5[var0]
       3 [-]: GETTABLE R3 R4 R1; var3 = var4[var1]
       4 [-]: SETTABLE R3 R2 R0; var3[var2] = var0
       5 [-]: SETUPVAL R0 1; upvalues[0] = var1
       6 [-]: GETUPVAL R3 2; var3 = upvalues[2]
       7 [-]: GETTABLEKS R2 R3 K3; var2 = var3[0x94B054B1]
       8 [-]: GETUPVAL R4 0; var4 = upvalues[0]
       9 [-]: GETTABLE R3 R4 R0; var3 = var4[var0]
      10 [-]: MOVE R4 R0   ; var4 = var0
      11 [-]: CALL R2 3 1  ; var2(var3, var4)
      12 [-]: RETURN R0 0  ; 


; Name:            
; Defined at line: 874
; #Upvalues:       2
; #Parameters:     1
; Is_vararg:       0
; Max Stack Size:  25

       0 [-]: GETIMPORT R2 2; var2 = _T["DuviriQuestWeapons"]
       1 [-]: GETIMPORT R3 4; var3 = 0x37847D3A
       2 [-]: GETTABLE R1 R2 R3; var1 = var2[var3]
       3 [-]: GETIMPORT R2 6; var2 = _T["DuviriCaveWeaponSpawns"]
       4 [-]: JUMPXEQKNIL R2 L0 NOT; 
       5 [-]: GETIMPORT R2 7; var2 = _T
       6 [-]: NEWTABLE R3 0 0; var3 = {}
       7 [-]: SETTABLEKS R3 R2 K5; var3["DuviriCaveWeaponSpawns"] = var2
L 0:   8 [-]: GETIMPORT R2 9; var2 = 0xC8802016
       9 [-]: GETIMPORT R3 11; var3 = 0xB6509A7F
      10 [-]: CALL R2 2 4  ; var2, var3, var4 = var2(var3)
      11 [-]: FORGPREP_INEXT R2 L5; 
L 1:  12 [-]: LOADB R9 1   ; var9 = true
      13 [-]: LOADB R10 1  ; var10 = true
      14 [-]: NAMECALL R7 R6 K12; var8 = var6; var7 = var6[0x768274D6]
      15 [-]: CALL R7 4 1  ; var7(var8, var9, var10)
      16 [-]: GETIMPORT R7 14; var7 = 0xB009BBC6
      17 [-]: GETTABLE R8 R1 R5; var8 = var1[var5]
      18 [-]: NAMECALL R8 R8 K15; var9 = var8; var8 = var8[0xED4E0128]
      19 [-]: CALL R8 2 0  ; var8, ... = var8(var9)
      20 [-]: CALL R7 0 2  ; var7 = var7(var8, ...)
      21 [-]: GETIMPORT R10 17; var10 = gContextActionType
      22 [-]: NAMECALL R8 R6 K18; var9 = var6; var8 = var6[0xC9F6A7D7]
      23 [-]: CALL R8 3 2  ; var8 = var8(var9, var10)
      24 [-]: NAMECALL R9 R8 K19; var10 = var8; var9 = var8[0x2B54251B]
      25 [-]: CALL R9 2 2  ; var9 = var9(var10)
      26 [-]: LOADB R12 1  ; var12 = true
      27 [-]: LOADB R13 1  ; var13 = true
      28 [-]: NAMECALL R10 R9 K12; var11 = var9; var10 = var9[0x768274D6]
      29 [-]: CALL R10 4 1 ; var10(var11, var12, var13)
      30 [-]: NAMECALL R10 R8 K20; var11 = var8; var10 = var8[0x383D2E7D]
      31 [-]: CALL R10 2 1 ; var10(var11)
      32 [-]: GETIMPORT R10 22; var10 = 0x11A19C5E
      33 [-]: MOVE R11 R8  ; var11 = var8
      34 [-]: LOADK R12 K23; var12 = "OnActivated"
      35 [-]: CALL R10 3 1 ; var10(var11, var12)
      36 [-]: GETIMPORT R10 25; var10 = 0x603636AD
      37 [-]: GETUPVAL R12 0; var12 = upvalues[0]
      38 [-]: GETTABLEKS R11 R12 K26; var11 = var12["SELECT_SECONDARY_ACTION"]
      39 [-]: DUPTABLE R12 28; 
      40 [-]: GETIMPORT R13 25; var13 = 0x603636AD
      41 [-]: NAMECALL R14 R7 K29; var15 = var7; var14 = var7[0xD3A9D01F]
      42 [-]: CALL R14 2 2 ; var14 = var14(var15)
      43 [-]: NAMECALL R14 R14 K30; var15 = var14; var14 = var14[0x6D604BA7]
      44 [-]: CALL R14 2 2 ; var14 = var14(var15)
      45 [-]: NEWTABLE R15 0 0; var15 = {}
      46 [-]: CALL R13 3 2 ; var13 = var13(var14, var15)
      47 [-]: SETTABLEKS R13 R12 K27; var13["NAME"] = var12
      48 [-]: CALL R10 3 2 ; var10 = var10(var11, var12)
      49 [-]: MOVE R13 R10 ; var13 = var10
      50 [-]: NAMECALL R11 R8 K31; var12 = var8; var11 = var8[0x3961202B]
      51 [-]: CALL R11 3 1 ; var11(var12, var13)
      52 [-]: NAMECALL R11 R7 K32; var12 = var7; var11 = var7[0x16D81B57]
      53 [-]: CALL R11 2 2 ; var11 = var11(var12)
      54 [-]: GETIMPORT R14 34; var14 = 0x7ED0A956
      55 [-]: LOADK R15 K35; var15 = "/Lotus/Weapons/Tenno/Melee/Tonfa/TonfaContestWinner/TennoTonfa"
      56 [-]: CALL R14 2 0 ; var14, ... = var14(var15)
      57 [-]: NAMECALL R12 R7 K36; var13 = var7; var12 = var7[0xF2DEAF69]
      58 [-]: CALL R12 0 2 ; var12 = var12(var13, ...)
      59 [-]: LOADNIL R13  ; var13 = nil
      60 [-]: NAMECALL R14 R7 K37; var15 = var7; var14 = var7[0xC9A26F04]
      61 [-]: CALL R14 2 2 ; var14 = var14(var15)
      62 [-]: LOADN R15 1  ; var15 = 1
      63 [-]: JUMPIFEQ R14 R15 L2; goto L2 if var14 == var5835796
      64 [-]: JUMPIFNOT R12 L3; goto L3 if not var12
L 2:  65 [-]: GETIMPORT R14 39; var14 = 0x89326C93
      66 [-]: GETIMPORT R16 41; var16 = 0x20640DF6
      67 [-]: NAMECALL R18 R6 K42; var19 = var6; var18 = var6[0xD1586535]
      68 [-]: CALL R18 2 2 ; var18 = var18(var19)
      69 [-]: GETIMPORT R19 44; var19 = 0xA421AF95
      70 [-]: LOADN R20 0  ; var20 = 0
      71 [-]: GETUPVAL R22 1; var22 = upvalues[1]
      72 [-]: GETTABLEKS R21 R22 K45; var21 = var22[0x06D055F9]
      73 [-]: MOVE R22 R12 ; var22 = var12
      74 [-]: LOADK R23 K46; var23 = 1.2000000476837158
      75 [-]: LOADN R24 1  ; var24 = 1
      76 [-]: CALL R21 4 2 ; var21 = var21(var22, var23, var24)
      77 [-]: LOADN R22 0  ; var22 = 0
      78 [-]: CALL R19 4 2 ; var19 = var19(var20, var21, var22)
      79 [-]: ADD R17 R18 R19; var17 = var18 + var19
      80 [-]: GETIMPORT R18 48; var18 = ZERO_ROTATION
      81 [-]: NAMECALL R14 R14 K49; var15 = var14; var14 = var14[0x05909209]
      82 [-]: CALL R14 5 2 ; var14 = var14(var15, var16, var17, var18)
      83 [-]: LOADB R17 1  ; var17 = true
      84 [-]: NAMECALL R15 R14 K50; var16 = var14; var15 = var14[0x1A06FB6D]
      85 [-]: CALL R15 3 1 ; var15(var16, var17)
      86 [-]: GETIMPORT R17 52; var17 = 0x9748BAD3
      87 [-]: GETIMPORT R18 54; var18 = EMPTY_SYMBOL
      88 [-]: GETIMPORT R19 44; var19 = 0xA421AF95
      89 [-]: LOADK R20 K55; var20 = -0.10000000149011612
      90 [-]: LOADN R21 0  ; var21 = 0
      91 [-]: LOADN R22 0  ; var22 = 0
      92 [-]: CALL R19 4 2 ; var19 = var19(var20, var21, var22)
      93 [-]: GETIMPORT R20 48; var20 = ZERO_ROTATION
      94 [-]: NAMECALL R15 R14 K56; var16 = var14; var15 = var14[0x47901F07]
      95 [-]: CALL R15 6 2 ; var15 = var15(var16, var17, var18, var19, var20)
      96 [-]: MOVE R13 R15 ; var13 = var15
      97 [-]: MOVE R17 R11 ; var17 = var11
      98 [-]: LOADB R18 1  ; var18 = true
      99 [-]: LOADB R19 0  ; var19 = false
     100 [-]: NAMECALL R15 R13 K57; var16 = var13; var15 = var13[0x2970F52F]
     101 [-]: CALL R15 5 1 ; var15(var16, var17, var18, var19)
     102 [-]: LOADB R17 0  ; var17 = false
     103 [-]: NAMECALL R15 R13 K50; var16 = var13; var15 = var13[0x1A06FB6D]
     104 [-]: CALL R15 3 1 ; var15(var16, var17)
     105 [-]: LOADB R17 0  ; var17 = false
     106 [-]: NAMECALL R15 R13 K58; var16 = var13; var15 = var13[0x47C04419]
     107 [-]: CALL R15 3 1 ; var15(var16, var17)
     108 [-]: GETIMPORT R17 52; var17 = 0x9748BAD3
     109 [-]: GETIMPORT R18 54; var18 = EMPTY_SYMBOL
     110 [-]: GETIMPORT R19 44; var19 = 0xA421AF95
     111 [-]: LOADK R20 K59; var20 = 0.10000000149011612
     112 [-]: LOADN R21 0  ; var21 = 0
     113 [-]: LOADN R22 0  ; var22 = 0
     114 [-]: CALL R19 4 2 ; var19 = var19(var20, var21, var22)
     115 [-]: GETIMPORT R20 48; var20 = ZERO_ROTATION
     116 [-]: NAMECALL R15 R14 K56; var16 = var14; var15 = var14[0x47901F07]
     117 [-]: CALL R15 6 2 ; var15 = var15(var16, var17, var18, var19, var20)
     118 [-]: MOVE R18 R11 ; var18 = var11
     119 [-]: LOADB R19 1  ; var19 = true
     120 [-]: LOADB R20 0  ; var20 = false
     121 [-]: NAMECALL R16 R15 K57; var17 = var15; var16 = var15[0x2970F52F]
     122 [-]: CALL R16 5 1 ; var16(var17, var18, var19, var20)
     123 [-]: LOADB R18 0  ; var18 = false
     124 [-]: NAMECALL R16 R15 K50; var17 = var15; var16 = var15[0x1A06FB6D]
     125 [-]: CALL R16 3 1 ; var16(var17, var18)
     126 [-]: LOADB R18 0  ; var18 = false
     127 [-]: NAMECALL R16 R15 K58; var17 = var15; var16 = var15[0x47C04419]
     128 [-]: CALL R16 3 1 ; var16(var17, var18)
     129 [-]: JUMP L4      ; goto L4
L 3: 130 [-]: GETIMPORT R14 39; var14 = 0x89326C93
     131 [-]: GETIMPORT R16 52; var16 = 0x9748BAD3
     132 [-]: NAMECALL R18 R6 K42; var19 = var6; var18 = var6[0xD1586535]
     133 [-]: CALL R18 2 2 ; var18 = var18(var19)
     134 [-]: GETIMPORT R19 44; var19 = 0xA421AF95
     135 [-]: LOADN R20 0  ; var20 = 0
     136 [-]: LOADN R21 1  ; var21 = 1
     137 [-]: LOADN R22 0  ; var22 = 0
     138 [-]: CALL R19 4 2 ; var19 = var19(var20, var21, var22)
     139 [-]: ADD R17 R18 R19; var17 = var18 + var19
     140 [-]: GETIMPORT R18 48; var18 = ZERO_ROTATION
     141 [-]: NAMECALL R14 R14 K49; var15 = var14; var14 = var14[0x05909209]
     142 [-]: CALL R14 5 2 ; var14 = var14(var15, var16, var17, var18)
     143 [-]: MOVE R13 R14 ; var13 = var14
     144 [-]: MOVE R16 R11 ; var16 = var11
     145 [-]: LOADB R17 1  ; var17 = true
     146 [-]: LOADB R18 0  ; var18 = false
     147 [-]: NAMECALL R14 R13 K57; var15 = var13; var14 = var13[0x2970F52F]
     148 [-]: CALL R14 5 1 ; var14(var15, var16, var17, var18)
L 4: 149 [-]: GETIMPORT R14 39; var14 = 0x89326C93
     150 [-]: GETIMPORT R16 61; var16 = 0x803FC943
     151 [-]: NAMECALL R18 R6 K42; var19 = var6; var18 = var6[0xD1586535]
     152 [-]: CALL R18 2 2 ; var18 = var18(var19)
     153 [-]: GETIMPORT R19 44; var19 = 0xA421AF95
     154 [-]: LOADN R20 0  ; var20 = 0
     155 [-]: LOADN R21 1  ; var21 = 1
     156 [-]: LOADN R22 0  ; var22 = 0
     157 [-]: CALL R19 4 2 ; var19 = var19(var20, var21, var22)
     158 [-]: ADD R17 R18 R19; var17 = var18 + var19
     159 [-]: GETIMPORT R18 48; var18 = ZERO_ROTATION
     160 [-]: NAMECALL R14 R14 K49; var15 = var14; var14 = var14[0x05909209]
     161 [-]: CALL R14 5 2 ; var14 = var14(var15, var16, var17, var18)
     162 [-]: LOADB R17 1  ; var17 = true
     163 [-]: NAMECALL R15 R14 K62; var16 = var14; var15 = var14[0x7D76533A]
     164 [-]: CALL R15 3 1 ; var15(var16, var17)
     165 [-]: MOVE R17 R6  ; var17 = var6
     166 [-]: GETIMPORT R18 54; var18 = EMPTY_SYMBOL
     167 [-]: NAMECALL R15 R14 K63; var16 = var14; var15 = var14[0xA83B7094]
     168 [-]: CALL R15 4 1 ; var15(var16, var17, var18)
     169 [-]: GETIMPORT R16 6; var16 = _T["DuviriCaveWeaponSpawns"]
     170 [-]: DUPTABLE R17 66; 
     171 [-]: SETTABLEKS R6 R17 K64; var6["deco"] = var17
     172 [-]: SETTABLEKS R7 R17 K65; var7["weapon"] = var17
     173 [-]: FASTCALL2 52 R16 R17 L5; 
     174 [-]: GETIMPORT R15 69; var15 = 0x33BDD652[0x23D5322F]
     175 [-]: CALL R15 3 1 ; var15(var16, var17)
L 5: 176 [-]: FORGLOOP R2 L1 2 [inext]; 
     177 [-]: GETIMPORT R2 71; var2 = 0x9BA7909F
     178 [-]: GETIMPORT R4 34; var4 = 0x7ED0A956
     179 [-]: GETIMPORT R5 73; var5 = 0xC1807141
     180 [-]: CALL R4 2 0  ; var4, ... = var4(var5)
     181 [-]: NAMECALL R2 R2 K74; var3 = var2; var2 = var2[0xBCFB64AB]
     182 [-]: CALL R2 0 2  ; var2 = var2(var3, ...)
     183 [-]: FASTCALL1 64 R2 L6; 
     184 [-]: MOVE R4 R2   ; var4 = var2
     185 [-]: GETIMPORT R3 76; var3 = 0x7B998233
     186 [-]: CALL R3 2 2  ; var3 = var3(var4)
L 6: 187 [-]: JUMPIFNOT R3 L7; goto L7 if not var3
     188 [-]: GETIMPORT R3 71; var3 = 0x9BA7909F
     189 [-]: GETIMPORT R5 73; var5 = 0xC1807141
     190 [-]: NAMECALL R3 R3 K77; var4 = var3; var3 = var3[0x6DD7AA66]
     191 [-]: CALL R3 3 2  ; var3 = var3(var4, var5)
     192 [-]: MOVE R2 R3   ; var2 = var3
L 7: 193 [-]: FASTCALL1 64 R0 L8; 
     194 [-]: MOVE R4 R0   ; var4 = var0
     195 [-]: GETIMPORT R3 76; var3 = 0x7B998233
     196 [-]: CALL R3 2 2  ; var3 = var3(var4)
L 8: 197 [-]: JUMPIF R3 L9 ; goto L9 if var3
     198 [-]: GETIMPORT R3 79; var3 = 0xCBD666E1
     199 [-]: LOADN R4 0   ; var4 = 0
     200 [-]: CALL R3 2 1  ; var3(var4)
     201 [-]: JUMPBACK L7  ; goto L7
L 9: 202 [-]: RETURN R0 0  ; 


; Name:            
; Defined at line: 931
; #Upvalues:       1
; #Parameters:     1
; Is_vararg:       0
; Max Stack Size:  7

       0 [-]: GETIMPORT R1 1; var1 = 0x89326C93
       1 [-]: GETIMPORT R3 3; var3 = 0x0469F296
       2 [-]: MOVE R4 R0   ; var4 = var0
       3 [-]: CALL R3 2 0  ; var3, ... = var3(var4)
       4 [-]: NAMECALL R1 R1 K4; var2 = var1; var1 = var1[0x46A0EBF5]
       5 [-]: CALL R1 0 2  ; var1 = var1(var2, ...)
       6 [-]: LOADK R4 K5  ; var4 = "Execute"
       7 [-]: NAMECALL R2 R1 K6; var3 = var1; var2 = var1[0x8EB2112D]
       8 [-]: CALL R2 3 1  ; var2(var3, var4)
       9 [-]: GETIMPORT R2 1; var2 = 0x89326C93
      10 [-]: GETIMPORT R4 3; var4 = 0x0469F296
      11 [-]: LOADK R5 K7  ; var5 = "WeaponSelectMarker"
      12 [-]: CALL R4 2 2  ; var4 = var4(var5)
      13 [-]: NAMECALL R5 R1 K8; var6 = var1; var5 = var1[0xD1586535]
      14 [-]: CALL R5 2 0  ; var5, ... = var5(var6)
      15 [-]: NAMECALL R2 R2 K9; var3 = var2; var2 = var2[0xC7B81E8D]
      16 [-]: CALL R2 0 2  ; var2 = var2(var3, ...)
      17 [-]: SETUPVAL R2 0; upvalues[2] = var0
      18 [-]: GETUPVAL R2 0; var2 = upvalues[0]
      19 [-]: NAMECALL R2 R2 K10; var3 = var2; var2 = var2[0x383D2E7D]
      20 [-]: CALL R2 2 1  ; var2(var3)
      21 [-]: GETUPVAL R2 0; var2 = upvalues[0]
      22 [-]: GETIMPORT R4 12; var4 = 0xD2C04602
      23 [-]: LOADB R5 0   ; var5 = false
      24 [-]: NAMECALL R2 R2 K13; var3 = var2; var2 = var2[0x659D451F]
      25 [-]: CALL R2 4 1  ; var2(var3, var4, var5)
      26 [-]: RETURN R0 0  ; 


; Name:            
; Defined at line: 939
; #Upvalues:       9
; #Parameters:     0
; Is_vararg:       0
; Max Stack Size:  5

       0 [-]: GETUPVAL R1 0; var1 = upvalues[0]
       1 [-]: GETTABLEKS R0 R1 K0; var0 = var1[0x11DCFE97]
       2 [-]: GETIMPORT R1 2; var1 = 0x0469F296
       3 [-]: LOADK R2 K3  ; var2 = "DDuvParQUndercroft0780"
       4 [-]: CALL R1 2 2  ; var1 = var1(var2)
       5 [-]: LOADB R2 0   ; var2 = false
       6 [-]: LOADB R3 0   ; var3 = false
       7 [-]: LOADN R4 4   ; var4 = 4
       8 [-]: CALL R0 5 1  ; var0(var1, var2, var3, var4)
       9 [-]: GETUPVAL R1 0; var1 = upvalues[0]
      10 [-]: GETTABLEKS R0 R1 K4; var0 = var1[0x9742B85B]
      11 [-]: GETUPVAL R1 1; var1 = upvalues[1]
      12 [-]: GETIMPORT R2 2; var2 = 0x0469F296
      13 [-]: LOADK R3 K5  ; var3 = "DDuvParQUndercroft0790"
      14 [-]: CALL R2 2 0  ; var2, ... = var2(var3)
      15 [-]: CALL R0 0 1  ; var0(var1, ...)
      16 [-]: GETUPVAL R1 0; var1 = upvalues[0]
      17 [-]: GETTABLEKS R0 R1 K6; var0 = var1[0xFC87A231]
      18 [-]: CALL R0 1 1  ; var0()
      19 [-]: GETUPVAL R1 2; var1 = upvalues[2]
      20 [-]: GETTABLEKS R0 R1 K7; var0 = var1[0xA1DF01D6]
      21 [-]: GETUPVAL R2 3; var2 = upvalues[3]
      22 [-]: GETTABLEKS R1 R2 K8; var1 = var2["SELECT_SECONDARY_OBJ"]
      23 [-]: CALL R0 2 1  ; var0(var1)
      24 [-]: GETUPVAL R0 4; var0 = upvalues[4]
      25 [-]: GETIMPORT R1 2; var1 = 0x0469F296
      26 [-]: LOADK R2 K9  ; var2 = "SetupSecondariesTrigger"
      27 [-]: CALL R1 2 0  ; var1, ... = var1(var2)
      28 [-]: CALL R0 0 1  ; var0(var1, ...)
L 0:  29 [-]: GETUPVAL R0 5; var0 = upvalues[5]
      30 [-]: LOADN R1 0   ; var1 = 0
      31 [-]: JUMPIFEQ R0 R1 L1; goto L1 if var0 == var720929
      32 [-]: GETIMPORT R0 11; var0 = 0xCBD666E1
      33 [-]: LOADN R1 0   ; var1 = 0
      34 [-]: CALL R0 2 1  ; var0(var1)
      35 [-]: JUMPBACK L0  ; goto L0
L 1:  36 [-]: GETUPVAL R0 6; var0 = upvalues[6]
      37 [-]: NAMECALL R0 R0 K12; var1 = var0; var0 = var0[0xF4E253B6]
      38 [-]: CALL R0 2 1  ; var0(var1)
      39 [-]: GETUPVAL R1 0; var1 = upvalues[0]
      40 [-]: GETTABLEKS R0 R1 K4; var0 = var1[0x9742B85B]
      41 [-]: GETUPVAL R1 1; var1 = upvalues[1]
      42 [-]: GETIMPORT R2 2; var2 = 0x0469F296
      43 [-]: LOADK R3 K13 ; var3 = "DDuvParQUndercroft0800"
      44 [-]: CALL R2 2 0  ; var2, ... = var2(var3)
      45 [-]: CALL R0 0 1  ; var0(var1, ...)
      46 [-]: GETUPVAL R0 7; var0 = upvalues[7]
      47 [-]: GETUPVAL R3 8; var3 = upvalues[8]
      48 [-]: GETTABLEKS R2 R3 K14; var2 = var3["TEST_SECONDARY"]
      49 [-]: NAMECALL R0 R0 K15; var1 = var0; var0 = var0[0x8ABFF40E]
      50 [-]: CALL R0 3 1  ; var0(var1, var2)
      51 [-]: RETURN R0 0  ; 


; Name:            
; Defined at line: 959
; #Upvalues:       7
; #Parameters:     0
; Is_vararg:       0
; Max Stack Size:  4

       0 [-]: GETUPVAL R1 0; var1 = upvalues[0]
       1 [-]: GETTABLEKS R0 R1 K0; var0 = var1[0xA1DF01D6]
       2 [-]: GETUPVAL R2 1; var2 = upvalues[1]
       3 [-]: GETTABLEKS R1 R2 K1; var1 = var2["SELECT_PRIMARY_OBJ"]
       4 [-]: CALL R0 2 1  ; var0(var1)
       5 [-]: GETUPVAL R0 2; var0 = upvalues[2]
       6 [-]: GETIMPORT R1 3; var1 = 0x0469F296
       7 [-]: LOADK R2 K4  ; var2 = "SetupPrimariesTrigger"
       8 [-]: CALL R1 2 0  ; var1, ... = var1(var2)
       9 [-]: CALL R0 0 1  ; var0(var1, ...)
L 0:  10 [-]: GETUPVAL R0 3; var0 = upvalues[3]
      11 [-]: LOADN R1 1   ; var1 = 1
      12 [-]: JUMPIFEQ R0 R1 L1; goto L1 if var0 == var393249
      13 [-]: GETIMPORT R0 6; var0 = 0xCBD666E1
      14 [-]: LOADN R1 0   ; var1 = 0
      15 [-]: CALL R0 2 1  ; var0(var1)
      16 [-]: JUMPBACK L0  ; goto L0
L 1:  17 [-]: GETUPVAL R0 4; var0 = upvalues[4]
      18 [-]: NAMECALL R0 R0 K7; var1 = var0; var0 = var0[0xF4E253B6]
      19 [-]: CALL R0 2 1  ; var0(var1)
      20 [-]: GETUPVAL R0 5; var0 = upvalues[5]
      21 [-]: GETUPVAL R3 6; var3 = upvalues[6]
      22 [-]: GETTABLEKS R2 R3 K8; var2 = var3["TEST_PRIMARY"]
      23 [-]: NAMECALL R0 R0 K9; var1 = var0; var0 = var0[0x8ABFF40E]
      24 [-]: CALL R0 3 1  ; var0(var1, var2)
      25 [-]: RETURN R0 0  ; 


; Name:            
; Defined at line: 973
; #Upvalues:       7
; #Parameters:     0
; Is_vararg:       0
; Max Stack Size:  4

       0 [-]: GETUPVAL R1 0; var1 = upvalues[0]
       1 [-]: GETTABLEKS R0 R1 K0; var0 = var1[0xA1DF01D6]
       2 [-]: GETUPVAL R2 1; var2 = upvalues[1]
       3 [-]: GETTABLEKS R1 R2 K1; var1 = var2["SELECT_MELEE_OBJ"]
       4 [-]: CALL R0 2 1  ; var0(var1)
       5 [-]: GETUPVAL R0 2; var0 = upvalues[2]
       6 [-]: GETIMPORT R1 3; var1 = 0x0469F296
       7 [-]: LOADK R2 K4  ; var2 = "SetupMeleeTrigger"
       8 [-]: CALL R1 2 0  ; var1, ... = var1(var2)
       9 [-]: CALL R0 0 1  ; var0(var1, ...)
L 0:  10 [-]: GETUPVAL R0 3; var0 = upvalues[3]
      11 [-]: LOADN R1 5   ; var1 = 5
      12 [-]: JUMPIFEQ R0 R1 L1; goto L1 if var0 == var393249
      13 [-]: GETIMPORT R0 6; var0 = 0xCBD666E1
      14 [-]: LOADN R1 0   ; var1 = 0
      15 [-]: CALL R0 2 1  ; var0(var1)
      16 [-]: JUMPBACK L0  ; goto L0
L 1:  17 [-]: GETUPVAL R0 4; var0 = upvalues[4]
      18 [-]: NAMECALL R0 R0 K7; var1 = var0; var0 = var0[0xF4E253B6]
      19 [-]: CALL R0 2 1  ; var0(var1)
      20 [-]: GETUPVAL R0 5; var0 = upvalues[5]
      21 [-]: GETUPVAL R3 6; var3 = upvalues[6]
      22 [-]: GETTABLEKS R2 R3 K8; var2 = var3["TEST_MELEE"]
      23 [-]: NAMECALL R0 R0 K9; var1 = var0; var0 = var0[0x8ABFF40E]
      24 [-]: CALL R0 3 1  ; var0(var1, var2)
      25 [-]: RETURN R0 0  ; 


; Name:            
; Defined at line: 987
; #Upvalues:       15
; #Parameters:     1
; Is_vararg:       0
; Max Stack Size:  5

       0 [-]: GETUPVAL R2 0; var2 = upvalues[0]
       1 [-]: GETTABLEKS R1 R2 K0; var1 = var2[0xEA753E99]
       2 [-]: GETUPVAL R3 1; var3 = upvalues[1]
       3 [-]: GETTABLEKS R2 R3 K1; var2 = var3["BATTLE_PROGRESS_BAR"]
       4 [-]: LOADN R3 0   ; var3 = 0
       5 [-]: LOADN R4 5   ; var4 = 5
       6 [-]: CALL R1 4 1  ; var1(var2, var3, var4)
       7 [-]: GETUPVAL R1 2; var1 = upvalues[2]
       8 [-]: GETUPVAL R3 3; var3 = upvalues[3]
       9 [-]: GETTABLEKS R2 R3 K2; var2 = var3["STAY_OR_LEAVE"]
      10 [-]: JUMPIFNOTLT R1 R2 L0; goto L0 if var1 >= var262460
      11 [-]: GETUPVAL R1 4; var1 = upvalues[4]
      12 [-]: CALL R1 1 1  ; var1()
L 0:  13 [-]: GETIMPORT R1 4; var1 = 0x3D106989
      14 [-]: LOADK R2 K5  ; var2 = "Spawning Enemies"
      15 [-]: CALL R1 2 1  ; var1(var2)
      16 [-]: LOADN R1 0   ; var1 = 0
      17 [-]: SETUPVAL R1 5; upvalues[1] = var5
L 1:  18 [-]: GETUPVAL R1 5; var1 = upvalues[5]
      19 [-]: LOADN R2 5   ; var2 = 5
      20 [-]: JUMPIFNOTLT R1 R2 L4; goto L4 if var1 >= var393532
      21 [-]: GETUPVAL R1 6; var1 = upvalues[6]
      22 [-]: GETIMPORT R2 7; var2 = 0xFFF641AF
      23 [-]: CALL R2 1 0  ; var2, ... = var2()
      24 [-]: CALL R1 0 1  ; var1(var2, ...)
      25 [-]: GETUPVAL R2 7; var2 = upvalues[7]
      26 [-]: FASTCALL1 64 R2 L2; 
      27 [-]: GETIMPORT R1 9; var1 = 0x7B998233
      28 [-]: CALL R1 2 2  ; var1 = var1(var2)
L 2:  29 [-]: JUMPIF R1 L3 ; goto L3 if var1
      30 [-]: GETUPVAL R1 7; var1 = upvalues[7]
      31 [-]: NAMECALL R1 R1 K10; var2 = var1; var1 = var1[0x2047CFE7]
      32 [-]: CALL R1 2 2  ; var1 = var1(var2)
      33 [-]: JUMPIF R1 L3 ; goto L3 if var1
      34 [-]: GETUPVAL R1 8; var1 = upvalues[8]
      35 [-]: MOVE R2 R0   ; var2 = var0
      36 [-]: CALL R1 2 1  ; var1(var2)
      37 [-]: GETUPVAL R1 9; var1 = upvalues[9]
      38 [-]: CALL R1 1 1  ; var1()
L 3:  39 [-]: GETIMPORT R1 12; var1 = 0xCBD666E1
      40 [-]: LOADN R2 0   ; var2 = 0
      41 [-]: CALL R1 2 1  ; var1(var2)
      42 [-]: JUMPBACK L1  ; goto L1
L 4:  43 [-]: LOADB R1 1   ; var1 = true
      44 [-]: SETUPVAL R1 10; upvalues[1] = var10
      45 [-]: GETUPVAL R2 11; var2 = upvalues[11]
      46 [-]: FASTCALL1 64 R2 L5; 
      47 [-]: GETIMPORT R1 9; var1 = 0x7B998233
      48 [-]: CALL R1 2 2  ; var1 = var1(var2)
L 5:  49 [-]: JUMPIF R1 L6 ; goto L6 if var1
      50 [-]: GETUPVAL R1 11; var1 = upvalues[11]
      51 [-]: NAMECALL R1 R1 K13; var2 = var1; var1 = var1[0xA2880940]
      52 [-]: CALL R1 2 1  ; var1(var2)
L 6:  53 [-]: GETUPVAL R2 12; var2 = upvalues[12]
      54 [-]: FASTCALL1 64 R2 L7; 
      55 [-]: GETIMPORT R1 9; var1 = 0x7B998233
      56 [-]: CALL R1 2 2  ; var1 = var1(var2)
L 7:  57 [-]: JUMPIF R1 L8 ; goto L8 if var1
      58 [-]: GETUPVAL R1 12; var1 = upvalues[12]
      59 [-]: NAMECALL R1 R1 K13; var2 = var1; var1 = var1[0xA2880940]
      60 [-]: CALL R1 2 1  ; var1(var2)
L 8:  61 [-]: GETUPVAL R2 13; var2 = upvalues[13]
      62 [-]: FASTCALL1 64 R2 L9; 
      63 [-]: GETIMPORT R1 9; var1 = 0x7B998233
      64 [-]: CALL R1 2 2  ; var1 = var1(var2)
L 9:  65 [-]: JUMPIF R1 L10; goto L10 if var1
      66 [-]: GETUPVAL R1 13; var1 = upvalues[13]
      67 [-]: NAMECALL R1 R1 K13; var2 = var1; var1 = var1[0xA2880940]
      68 [-]: CALL R1 2 1  ; var1(var2)
L10:  69 [-]: GETUPVAL R1 14; var1 = upvalues[14]
      70 [-]: CALL R1 1 1  ; var1()
      71 [-]: GETIMPORT R1 16; var1 = _T["HideImpactMessage"]
      72 [-]: CALL R1 1 1  ; var1()
      73 [-]: GETUPVAL R2 0; var2 = upvalues[0]
      74 [-]: GETTABLEKS R1 R2 K17; var1 = var2[0xBD3CE95D]
      75 [-]: CALL R1 1 1  ; var1()
      76 [-]: LOADB R1 1   ; var1 = true
      77 [-]: RETURN R1 1  ; 


; Name:            
; Defined at line: 1017
; #Upvalues:       5
; #Parameters:     0
; Is_vararg:       0
; Max Stack Size:  4

       0 [-]: GETUPVAL R1 0; var1 = upvalues[0]
       1 [-]: GETTABLEKS R0 R1 K0; var0 = var1[0xA1DF01D6]
       2 [-]: GETUPVAL R2 1; var2 = upvalues[1]
       3 [-]: GETTABLEKS R1 R2 K1; var1 = var2["TEST_SECONDARY_OBJ"]
       4 [-]: CALL R0 2 1  ; var0(var1)
       5 [-]: GETIMPORT R0 3; var0 = 0x89326C93
       6 [-]: NAMECALL R0 R0 K4; var1 = var0; var0 = var0[0x29EF273D]
       7 [-]: CALL R0 2 2  ; var0 = var0(var1)
       8 [-]: GETIMPORT R2 6; var2 = 0xE26A8747
       9 [-]: NAMECALL R0 R0 K7; var1 = var0; var0 = var0[0x8955C0B5]
      10 [-]: CALL R0 3 1  ; var0(var1, var2)
      11 [-]: GETUPVAL R0 2; var0 = upvalues[2]
      12 [-]: LOADN R1 0   ; var1 = 0
      13 [-]: CALL R0 2 2  ; var0 = var0(var1)
      14 [-]: JUMPIF R0 L0 ; goto L0 if var0
      15 [-]: RETURN R0 0  ; 
L 0:  16 [-]: GETUPVAL R0 3; var0 = upvalues[3]
      17 [-]: GETUPVAL R3 4; var3 = upvalues[4]
      18 [-]: GETTABLEKS R2 R3 K8; var2 = var3["SELECT_PRIMARY"]
      19 [-]: NAMECALL R0 R0 K9; var1 = var0; var0 = var0[0x8ABFF40E]
      20 [-]: CALL R0 3 1  ; var0(var1, var2)
      21 [-]: RETURN R0 0  ; 


; Name:            
; Defined at line: 1028
; #Upvalues:       6
; #Parameters:     0
; Is_vararg:       0
; Max Stack Size:  4

       0 [-]: GETUPVAL R1 0; var1 = upvalues[0]
       1 [-]: GETTABLEKS R0 R1 K0; var0 = var1[0xA1DF01D6]
       2 [-]: GETUPVAL R2 1; var2 = upvalues[1]
       3 [-]: GETTABLEKS R1 R2 K1; var1 = var2["TEST_PRIMARY_OBJ"]
       4 [-]: CALL R0 2 1  ; var0(var1)
       5 [-]: LOADN R0 0   ; var0 = 0
       6 [-]: SETUPVAL R0 2; upvalues[0] = var2
       7 [-]: GETUPVAL R0 3; var0 = upvalues[3]
       8 [-]: LOADN R1 1   ; var1 = 1
       9 [-]: CALL R0 2 2  ; var0 = var0(var1)
      10 [-]: JUMPIF R0 L0 ; goto L0 if var0
      11 [-]: RETURN R0 0  ; 
L 0:  12 [-]: GETUPVAL R0 4; var0 = upvalues[4]
      13 [-]: GETUPVAL R3 5; var3 = upvalues[5]
      14 [-]: GETTABLEKS R2 R3 K2; var2 = var3["SELECT_MELEE"]
      15 [-]: NAMECALL R0 R0 K3; var1 = var0; var0 = var0[0x8ABFF40E]
      16 [-]: CALL R0 3 1  ; var0(var1, var2)
      17 [-]: RETURN R0 0  ; 


; Name:            
; Defined at line: 1039
; #Upvalues:       7
; #Parameters:     0
; Is_vararg:       0
; Max Stack Size:  5

       0 [-]: GETUPVAL R1 0; var1 = upvalues[0]
       1 [-]: GETTABLEKS R0 R1 K0; var0 = var1[0xA1DF01D6]
       2 [-]: GETUPVAL R2 1; var2 = upvalues[1]
       3 [-]: GETTABLEKS R1 R2 K1; var1 = var2["TEST_MELEE_OBJ"]
       4 [-]: CALL R0 2 1  ; var0(var1)
       5 [-]: GETIMPORT R0 3; var0 = 0x89326C93
       6 [-]: NAMECALL R0 R0 K4; var1 = var0; var0 = var0[0x29EF273D]
       7 [-]: CALL R0 2 2  ; var0 = var0(var1)
       8 [-]: GETIMPORT R2 6; var2 = 0x88431D72
       9 [-]: NAMECALL R0 R0 K7; var1 = var0; var0 = var0[0x8955C0B5]
      10 [-]: CALL R0 3 1  ; var0(var1, var2)
      11 [-]: GETUPVAL R0 2; var0 = upvalues[2]
      12 [-]: LOADN R1 5   ; var1 = 5
      13 [-]: CALL R0 2 2  ; var0 = var0(var1)
      14 [-]: JUMPIF R0 L0 ; goto L0 if var0
      15 [-]: RETURN R0 0  ; 
L 0:  16 [-]: GETUPVAL R1 0; var1 = upvalues[0]
      17 [-]: GETTABLEKS R0 R1 K8; var0 = var1[0xDC3B2033]
      18 [-]: CALL R0 1 1  ; var0()
      19 [-]: GETUPVAL R1 3; var1 = upvalues[3]
      20 [-]: GETTABLEKS R0 R1 K9; var0 = var1[0x9742B85B]
      21 [-]: GETUPVAL R1 4; var1 = upvalues[4]
      22 [-]: GETIMPORT R2 11; var2 = 0x0469F296
      23 [-]: LOADK R3 K12 ; var3 = "DDuvParQUndercroft0810"
      24 [-]: CALL R2 2 0  ; var2, ... = var2(var3)
      25 [-]: CALL R0 0 1  ; var0(var1, ...)
      26 [-]: GETUPVAL R1 3; var1 = upvalues[3]
      27 [-]: GETTABLEKS R0 R1 K13; var0 = var1[0x11DCFE97]
      28 [-]: GETIMPORT R1 11; var1 = 0x0469F296
      29 [-]: LOADK R2 K14 ; var2 = "DDuvParQUndercroft0820"
      30 [-]: CALL R1 2 2  ; var1 = var1(var2)
      31 [-]: LOADB R2 0   ; var2 = false
      32 [-]: LOADB R3 0   ; var3 = false
      33 [-]: LOADN R4 4   ; var4 = 4
      34 [-]: CALL R0 5 1  ; var0(var1, var2, var3, var4)
      35 [-]: GETUPVAL R1 3; var1 = upvalues[3]
      36 [-]: GETTABLEKS R0 R1 K9; var0 = var1[0x9742B85B]
      37 [-]: GETUPVAL R1 4; var1 = upvalues[4]
      38 [-]: GETIMPORT R2 11; var2 = 0x0469F296
      39 [-]: LOADK R3 K15 ; var3 = "DDuvParQUndercroft0830"
      40 [-]: CALL R2 2 0  ; var2, ... = var2(var3)
      41 [-]: CALL R0 0 1  ; var0(var1, ...)
      42 [-]: GETUPVAL R1 3; var1 = upvalues[3]
      43 [-]: GETTABLEKS R0 R1 K16; var0 = var1[0xFC87A231]
      44 [-]: CALL R0 1 1  ; var0()
      45 [-]: GETUPVAL R0 5; var0 = upvalues[5]
      46 [-]: GETUPVAL R3 6; var3 = upvalues[6]
      47 [-]: GETTABLEKS R2 R3 K17; var2 = var3["STAY_OR_LEAVE"]
      48 [-]: NAMECALL R0 R0 K18; var1 = var0; var0 = var0[0x8ABFF40E]
      49 [-]: CALL R0 3 1  ; var0(var1, var2)
      50 [-]: RETURN R0 0  ; 


; Name:            
; Defined at line: 1057
; #Upvalues:       5
; #Parameters:     0
; Is_vararg:       0
; Max Stack Size:  9

       0 [-]: GETIMPORT R0 1; var0 = 0x89326C93
       1 [-]: GETIMPORT R2 3; var2 = 0x0469F296
       2 [-]: LOADK R3 K4  ; var3 = "DuviriQuestArenaPortal"
       3 [-]: CALL R2 2 0  ; var2, ... = var2(var3)
       4 [-]: NAMECALL R0 R0 K5; var1 = var0; var0 = var0[0x46A0EBF5]
       5 [-]: CALL R0 0 2  ; var0 = var0(var1, ...)
       6 [-]: GETIMPORT R1 1; var1 = 0x89326C93
       7 [-]: GETUPVAL R4 0; var4 = upvalues[0]
       8 [-]: GETTABLEKS R3 R4 K6; var3 = var4["CAVE_SPAWN_TAG"]
       9 [-]: NAMECALL R1 R1 K5; var2 = var1; var1 = var1[0x46A0EBF5]
      10 [-]: CALL R1 3 2  ; var1 = var1(var2, var3)
      11 [-]: GETUPVAL R3 2; var3 = upvalues[2]
      12 [-]: GETTABLEKS R2 R3 K7; var2 = var3[0x17AB718C]
      13 [-]: GETIMPORT R3 9; var3 = 0xC61B9FC4
      14 [-]: NAMECALL R4 R0 K10; var5 = var0; var4 = var0[0xD1586535]
      15 [-]: CALL R4 2 2  ; var4 = var4(var5)
      16 [-]: NAMECALL R5 R0 K11; var6 = var0; var5 = var0[0xCB3851B8]
      17 [-]: CALL R5 2 2  ; var5 = var5(var6)
      18 [-]: NAMECALL R6 R1 K10; var7 = var1; var6 = var1[0xD1586535]
      19 [-]: CALL R6 2 2  ; var6 = var6(var7)
      20 [-]: NAMECALL R7 R1 K11; var8 = var1; var7 = var1[0xCB3851B8]
      21 [-]: CALL R7 2 2  ; var7 = var7(var8)
      22 [-]: LOADN R8 8   ; var8 = 8
      23 [-]: CALL R2 7 2  ; var2 = var2(var3, var4, var5, var6, var7, var8)
      24 [-]: SETUPVAL R2 1; upvalues[2] = var1
      25 [-]: GETIMPORT R2 1; var2 = 0x89326C93
      26 [-]: GETIMPORT R4 13; var4 = 0xED313964
      27 [-]: NAMECALL R5 R0 K10; var6 = var0; var5 = var0[0xD1586535]
      28 [-]: CALL R5 2 2  ; var5 = var5(var6)
      29 [-]: GETIMPORT R6 15; var6 = ZERO_ROTATION
      30 [-]: NAMECALL R2 R2 K16; var3 = var2; var2 = var2[0x05909209]
      31 [-]: CALL R2 5 2  ; var2 = var2(var3, var4, var5, var6)
      32 [-]: SETUPVAL R2 3; upvalues[2] = var3
      33 [-]: GETUPVAL R2 3; var2 = upvalues[3]
      34 [-]: NAMECALL R2 R2 K17; var3 = var2; var2 = var2[0x383D2E7D]
      35 [-]: CALL R2 2 1  ; var2(var3)
      36 [-]: GETUPVAL R2 1; var2 = upvalues[1]
      37 [-]: GETIMPORT R4 19; var4 = 0xCF3496E5
      38 [-]: LOADB R5 0   ; var5 = false
      39 [-]: NAMECALL R2 R2 K20; var3 = var2; var2 = var2[0x659D451F]
      40 [-]: CALL R2 4 1  ; var2(var3, var4, var5)
      41 [-]: GETUPVAL R3 4; var3 = upvalues[4]
      42 [-]: GETTABLEKS R2 R3 K20; var2 = var3[0x659D451F]
      43 [-]: GETIMPORT R3 22; var3 = 0x9CFF77E6
      44 [-]: CALL R2 2 1  ; var2(var3)
      45 [-]: GETIMPORT R2 1; var2 = 0x89326C93
      46 [-]: GETIMPORT R4 24; var4 = 0xA4767BA1
      47 [-]: GETUPVAL R5 3; var5 = upvalues[3]
      48 [-]: NAMECALL R5 R5 K10; var6 = var5; var5 = var5[0xD1586535]
      49 [-]: CALL R5 2 2  ; var5 = var5(var6)
      50 [-]: GETIMPORT R6 15; var6 = ZERO_ROTATION
      51 [-]: NAMECALL R2 R2 K16; var3 = var2; var2 = var2[0x05909209]
      52 [-]: CALL R2 5 2  ; var2 = var2(var3, var4, var5, var6)
      53 [-]: NAMECALL R3 R2 K17; var4 = var2; var3 = var2[0x383D2E7D]
      54 [-]: CALL R3 2 1  ; var3(var4)
      55 [-]: RETURN R0 0  ; 


; Name:            
; Defined at line: 1069
; #Upvalues:       11
; #Parameters:     0
; Is_vararg:       0
; Max Stack Size:  4

       0 [-]: GETUPVAL R1 0; var1 = upvalues[0]
       1 [-]: GETTABLEKS R0 R1 K0; var0 = var1[0xA1DF01D6]
       2 [-]: GETUPVAL R2 1; var2 = upvalues[1]
       3 [-]: GETTABLEKS R1 R2 K1; var1 = var2["SELECT_SECONDARY_EXIT_AVAILABLE_OBJ"]
       4 [-]: CALL R0 2 1  ; var0(var1)
       5 [-]: GETUPVAL R0 2; var0 = upvalues[2]
       6 [-]: CALL R0 1 1  ; var0()
       7 [-]: GETIMPORT R0 3; var0 = _T
       8 [-]: LOADB R1 1   ; var1 = true
       9 [-]: SETTABLEKS R1 R0 K4; var1["SkipTeleportFadeIn"] = var0
      10 [-]: LOADNIL R0   ; var0 = nil
      11 [-]: SETUPVAL R0 3; upvalues[0] = var3
L 0:  12 [-]: GETUPVAL R0 4; var0 = upvalues[4]
      13 [-]: NAMECALL R0 R0 K5; var1 = var0; var0 = var0[0xA5E492D4]
      14 [-]: CALL R0 2 2  ; var0 = var0(var1)
      15 [-]: JUMPIFNOT R0 L1; goto L1 if not var0
      16 [-]: GETUPVAL R0 5; var0 = upvalues[5]
      17 [-]: GETUPVAL R3 6; var3 = upvalues[6]
      18 [-]: GETTABLEKS R2 R3 K6; var2 = var3["COMPLETE"]
      19 [-]: NAMECALL R0 R0 K7; var1 = var0; var0 = var0[0x8ABFF40E]
      20 [-]: CALL R0 3 1  ; var0(var1, var2)
      21 [-]: RETURN R0 0  ; 
L 1:  22 [-]: GETUPVAL R0 3; var0 = upvalues[3]
      23 [-]: JUMPIFNOT R0 L2; goto L2 if not var0
      24 [-]: GETUPVAL R0 7; var0 = upvalues[7]
      25 [-]: NAMECALL R0 R0 K8; var1 = var0; var0 = var0[0xA2880940]
      26 [-]: CALL R0 2 1  ; var0(var1)
      27 [-]: GETUPVAL R1 8; var1 = upvalues[8]
      28 [-]: GETTABLEKS R0 R1 K9; var0 = var1[0xA2080540]
      29 [-]: GETUPVAL R1 9; var1 = upvalues[9]
      30 [-]: CALL R0 2 1  ; var0(var1)
      31 [-]: GETUPVAL R0 10; var0 = upvalues[10]
      32 [-]: GETUPVAL R1 3; var1 = upvalues[3]
      33 [-]: CALL R0 2 1  ; var0(var1)
      34 [-]: LOADNIL R0   ; var0 = nil
      35 [-]: SETUPVAL R0 3; upvalues[0] = var3
      36 [-]: GETUPVAL R0 2; var0 = upvalues[2]
      37 [-]: CALL R0 1 1  ; var0()
L 2:  38 [-]: GETIMPORT R0 11; var0 = 0xCBD666E1
      39 [-]: LOADN R1 0   ; var1 = 0
      40 [-]: CALL R0 2 1  ; var0(var1)
      41 [-]: JUMPBACK L0  ; goto L0
      42 [-]: RETURN R0 0  ; 


; Name:            
; Defined at line: 1095
; #Upvalues:       2
; #Parameters:     0
; Is_vararg:       0
; Max Stack Size:  8

L 0:   0 [-]: GETIMPORT R0 2; var0 = _T["ActiveQuestLoaded"]
       1 [-]: JUMPIF R0 L1 ; goto L1 if var0
       2 [-]: GETIMPORT R0 4; var0 = 0xCBD666E1
       3 [-]: LOADN R1 0   ; var1 = 0
       4 [-]: CALL R0 2 1  ; var0(var1)
       5 [-]: JUMPBACK L0  ; goto L0
L 1:   6 [-]: GETIMPORT R0 7; var0 = 0x33BDD652[0xA5C556B9]
       7 [-]: GETIMPORT R2 9; var2 = _T["DuviriQuestWeapons"]
       8 [-]: LOADN R3 0   ; var3 = 0
       9 [-]: GETTABLE R1 R2 R3; var1 = var2[var3]
      10 [-]: GETUPVAL R3 0; var3 = upvalues[0]
      11 [-]: LOADN R4 0   ; var4 = 0
      12 [-]: GETTABLE R2 R3 R4; var2 = var3[var4]
      13 [-]: CALL R0 3 2  ; var0 = var0(var1, var2)
      14 [-]: GETIMPORT R1 7; var1 = 0x33BDD652[0xA5C556B9]
      15 [-]: GETIMPORT R3 9; var3 = _T["DuviriQuestWeapons"]
      16 [-]: LOADN R4 1   ; var4 = 1
      17 [-]: GETTABLE R2 R3 R4; var2 = var3[var4]
      18 [-]: GETUPVAL R4 0; var4 = upvalues[0]
      19 [-]: LOADN R5 1   ; var5 = 1
      20 [-]: GETTABLE R3 R4 R5; var3 = var4[var5]
      21 [-]: CALL R1 3 2  ; var1 = var1(var2, var3)
      22 [-]: GETIMPORT R2 7; var2 = 0x33BDD652[0xA5C556B9]
      23 [-]: GETIMPORT R4 9; var4 = _T["DuviriQuestWeapons"]
      24 [-]: LOADN R5 3   ; var5 = 3
      25 [-]: GETTABLE R3 R4 R5; var3 = var4[var5]
      26 [-]: GETUPVAL R5 0; var5 = upvalues[0]
      27 [-]: LOADN R6 3   ; var6 = 3
      28 [-]: GETTABLE R4 R5 R6; var4 = var5[var6]
      29 [-]: CALL R2 3 2  ; var2 = var2(var3, var4)
      30 [-]: GETIMPORT R3 7; var3 = 0x33BDD652[0xA5C556B9]
      31 [-]: GETIMPORT R5 9; var5 = _T["DuviriQuestWeapons"]
      32 [-]: LOADN R6 5   ; var6 = 5
      33 [-]: GETTABLE R4 R5 R6; var4 = var5[var6]
      34 [-]: GETUPVAL R6 0; var6 = upvalues[0]
      35 [-]: LOADN R7 5   ; var7 = 5
      36 [-]: GETTABLE R5 R6 R7; var5 = var6[var7]
      37 [-]: CALL R3 3 2  ; var3 = var3(var4, var5)
      38 [-]: GETIMPORT R4 10; var4 = _T
      39 [-]: DUPTABLE R5 12; 
      40 [-]: NEWTABLE R6 4 0; var6 = {}
      41 [-]: LOADN R7 0   ; var7 = 0
      42 [-]: SETTABLE R0 R6 R7; var0[var6] = var7
      43 [-]: LOADN R7 1   ; var7 = 1
      44 [-]: SETTABLE R1 R6 R7; var1[var6] = var7
      45 [-]: LOADN R7 3   ; var7 = 3
      46 [-]: SETTABLE R2 R6 R7; var2[var6] = var7
      47 [-]: LOADN R7 5   ; var7 = 5
      48 [-]: SETTABLE R3 R6 R7; var3[var6] = var7
      49 [-]: SETTABLEKS R6 R5 K11; var6["Equipment"] = var5
      50 [-]: SETTABLEKS R5 R4 K13; var5["DuviriQuestCustomData"] = var4
      51 [-]: GETUPVAL R4 1; var4 = upvalues[1]
      52 [-]: LOADN R6 4   ; var6 = 4
      53 [-]: NAMECALL R4 R4 K14; var5 = var4; var4 = var4[0xFE9DC265]
      54 [-]: CALL R4 3 1  ; var4(var5, var6)
      55 [-]: RETURN R0 0  ; 


; Name:            
; Defined at line: 1121
; #Upvalues:       1
; #Parameters:     1
; Is_vararg:       0
; Max Stack Size:  20

       0 [-]: NEWTABLE R1 0 0; var1 = {}
       1 [-]: GETIMPORT R2 1; var2 = 0xC8802016
       2 [-]: GETIMPORT R3 3; var3 = 0x6CBCB2C6
       3 [-]: CALL R2 2 4  ; var2, var3, var4 = var2(var3)
       4 [-]: FORGPREP_INEXT R2 L5; 
L 0:   5 [-]: NAMECALL R7 R6 K4; var8 = var6; var7 = var6[0xD1586535]
       6 [-]: CALL R7 2 2  ; var7 = var7(var8)
       7 [-]: NAMECALL R8 R6 K5; var9 = var6; var8 = var6[0xCB3851B8]
       8 [-]: CALL R8 2 2  ; var8 = var8(var9)
       9 [-]: GETIMPORT R9 7; var9 = 0x89326C93
      10 [-]: GETIMPORT R11 9; var11 = 0xBC12E9CB
      11 [-]: MOVE R12 R7  ; var12 = var7
      12 [-]: MOVE R13 R8  ; var13 = var8
      13 [-]: NAMECALL R9 R9 K10; var10 = var9; var9 = var9[0x05909209]
      14 [-]: CALL R9 5 2  ; var9 = var9(var10, var11, var12, var13)
      15 [-]: GETIMPORT R10 7; var10 = 0x89326C93
      16 [-]: GETIMPORT R12 12; var12 = 0x803FC943
      17 [-]: MOVE R13 R7  ; var13 = var7
      18 [-]: MOVE R14 R8  ; var14 = var8
      19 [-]: NAMECALL R10 R10 K10; var11 = var10; var10 = var10[0x05909209]
      20 [-]: CALL R10 5 2 ; var10 = var10(var11, var12, var13, var14)
      21 [-]: MOVE R13 R9  ; var13 = var9
      22 [-]: GETIMPORT R14 14; var14 = EMPTY_SYMBOL
      23 [-]: NAMECALL R11 R10 K15; var12 = var10; var11 = var10[0xB6B094B2]
      24 [-]: CALL R11 4 1 ; var11(var12, var13, var14)
      25 [-]: GETIMPORT R11 7; var11 = 0x89326C93
      26 [-]: GETUPVAL R13 0; var13 = upvalues[0]
      27 [-]: NAMECALL R14 R9 K4; var15 = var9; var14 = var9[0xD1586535]
      28 [-]: CALL R14 2 0 ; var14, ... = var14(var15)
      29 [-]: NAMECALL R11 R11 K16; var12 = var11; var11 = var11[0xC7B81E8D]
      30 [-]: CALL R11 0 2 ; var11 = var11(var12, ...)
      31 [-]: FASTCALL1 64 R11 L1; 
      32 [-]: MOVE R13 R11 ; var13 = var11
      33 [-]: GETIMPORT R12 18; var12 = 0x7B998233
      34 [-]: CALL R12 2 2 ; var12 = var12(var13)
L 1:  35 [-]: JUMPIF R12 L2; goto L2 if var12
      36 [-]: LOADK R14 K19; var14 = "Enable"
      37 [-]: NAMECALL R12 R11 K20; var13 = var11; var12 = var11[0x8EB2112D]
      38 [-]: CALL R12 3 1 ; var12(var13, var14)
L 2:  39 [-]: GETIMPORT R12 7; var12 = 0x89326C93
      40 [-]: GETIMPORT R14 22; var14 = 0x0469F296
      41 [-]: LOADK R15 K23; var15 = "WarframeEmptyStandEffect"
      42 [-]: CALL R14 2 2 ; var14 = var14(var15)
      43 [-]: MOVE R15 R7  ; var15 = var7
      44 [-]: NAMECALL R12 R12 K16; var13 = var12; var12 = var12[0xC7B81E8D]
      45 [-]: CALL R12 4 2 ; var12 = var12(var13, var14, var15)
      46 [-]: FASTCALL1 64 R12 L3; 
      47 [-]: MOVE R14 R12 ; var14 = var12
      48 [-]: GETIMPORT R13 18; var13 = 0x7B998233
      49 [-]: CALL R13 2 2 ; var13 = var13(var14)
L 3:  50 [-]: JUMPIF R13 L4; goto L4 if var13
      51 [-]: LOADB R15 1  ; var15 = true
      52 [-]: LOADB R16 1  ; var16 = true
      53 [-]: NAMECALL R13 R12 K24; var14 = var12; var13 = var12[0x768274D6]
      54 [-]: CALL R13 4 1 ; var13(var14, var15, var16)
L 4:  55 [-]: GETIMPORT R15 26; var15 = 0x62B46842
      56 [-]: LOADB R16 0  ; var16 = false
      57 [-]: LOADN R17 3  ; var17 = 3
      58 [-]: LOADN R18 2  ; var18 = 2
      59 [-]: LOADB R19 1  ; var19 = true
      60 [-]: NAMECALL R13 R9 K27; var14 = var9; var13 = var9[0x5D985C7E]
      61 [-]: CALL R13 7 1 ; var13(var14, var15, var16, var17, var18, var19)
      62 [-]: GETIMPORT R17 30; var17 = _T["DuviriQuestWeapons"]
      63 [-]: LOADN R18 3  ; var18 = 3
      64 [-]: GETTABLE R16 R17 R18; var16 = var17[var18]
      65 [-]: GETTABLE R15 R16 R5; var15 = var16[var5]
      66 [-]: LOADB R16 1  ; var16 = true
      67 [-]: NAMECALL R13 R9 K31; var14 = var9; var13 = var9[0x511D26B8]
      68 [-]: CALL R13 4 1 ; var13(var14, var15, var16)
      69 [-]: FASTCALL2 52 R1 R9 L5; 
      70 [-]: MOVE R14 R1  ; var14 = var1
      71 [-]: MOVE R15 R9  ; var15 = var9
      72 [-]: GETIMPORT R13 34; var13 = 0x33BDD652[0x23D5322F]
      73 [-]: CALL R13 3 1 ; var13(var14, var15)
L 5:  74 [-]: FORGLOOP R2 L0 2 [inext]; 
L 6:  75 [-]: NAMECALL R2 R0 K35; var3 = var0; var2 = var0[0xF37943FF]
      76 [-]: CALL R2 2 2  ; var2 = var2(var3)
      77 [-]: JUMPIFNOT R2 L7; goto L7 if not var2
      78 [-]: GETIMPORT R2 37; var2 = 0xCBD666E1
      79 [-]: LOADN R3 0   ; var3 = 0
      80 [-]: CALL R2 2 1  ; var2(var3)
      81 [-]: JUMPBACK L6  ; goto L6
L 7:  82 [-]: RETURN R0 0  ; 


; Name:            
; Defined at line: 1153
; #Upvalues:       19
; #Parameters:     1
; Is_vararg:       0
; Max Stack Size:  17

       0 [-]: GETIMPORT R2 1; var2 = 0xCB79539E
       1 [-]: FASTCALL1 64 R2 L0; 
       2 [-]: GETIMPORT R1 3; var1 = 0x7B998233
       3 [-]: CALL R1 2 2  ; var1 = var1(var2)
L 0:   4 [-]: JUMPIF R1 L4 ; goto L4 if var1
       5 [-]: GETUPVAL R2 0; var2 = upvalues[0]
       6 [-]: GETTABLEKS R1 R2 K4; var1 = var2["RESPAWN"]
       7 [-]: JUMPIFEQ R0 R1 L4; goto L4 if var0 == var572
       8 [-]: GETUPVAL R2 0; var2 = upvalues[0]
       9 [-]: GETTABLEKS R1 R2 K5; var1 = var2["SELECT_WARFRAME"]
      10 [-]: JUMPIFNOTEQ R0 R1 L1; goto L1 if var0 ~= var65825
      11 [-]: GETIMPORT R1 1; var1 = 0xCB79539E
      12 [-]: GETIMPORT R3 7; var3 = 0x0469F296
      13 [-]: LOADK R4 K8  ; var4 = "DUVIRI_TUTORIAL_STAGE_TIME"
      14 [-]: CALL R3 2 2  ; var3 = var3(var4)
      15 [-]: LOADK R4 K9  ; var4 = "3_CaveIntroEncounter_9"
      16 [-]: NAMECALL R1 R1 K10; var2 = var1; var1 = var1[0xA9188A47]
      17 [-]: CALL R1 4 1  ; var1(var2, var3, var4)
      18 [-]: JUMP L2      ; goto L2
L 1:  19 [-]: GETIMPORT R1 1; var1 = 0xCB79539E
      20 [-]: GETIMPORT R3 7; var3 = 0x0469F296
      21 [-]: LOADK R4 K8  ; var4 = "DUVIRI_TUTORIAL_STAGE_TIME"
      22 [-]: CALL R3 2 2  ; var3 = var3(var4)
      23 [-]: LOADK R5 K11 ; var5 = "4_UndercroftEncounter_"
      24 [-]: SUBK R6 R0 K12; var6 = var0 - 1
      25 [-]: CONCAT R4 R5 R6; var4 = var5 .. var6
      26 [-]: NAMECALL R1 R1 K10; var2 = var1; var1 = var1[0xA9188A47]
      27 [-]: CALL R1 4 1  ; var1(var2, var3, var4)
L 2:  28 [-]: GETUPVAL R2 0; var2 = upvalues[0]
      29 [-]: GETTABLEKS R1 R2 K13; var1 = var2["COMPLETE"]
      30 [-]: JUMPIFEQ R0 R1 L3; goto L3 if var0 == var65825
      31 [-]: GETIMPORT R1 1; var1 = 0xCB79539E
      32 [-]: GETIMPORT R3 7; var3 = 0x0469F296
      33 [-]: LOADK R4 K8  ; var4 = "DUVIRI_TUTORIAL_STAGE_TIME"
      34 [-]: CALL R3 2 2  ; var3 = var3(var4)
      35 [-]: LOADK R5 K11 ; var5 = "4_UndercroftEncounter_"
      36 [-]: MOVE R6 R0   ; var6 = var0
      37 [-]: CONCAT R4 R5 R6; var4 = var5 .. var6
      38 [-]: NAMECALL R1 R1 K14; var2 = var1; var1 = var1[0xA9136B2F]
      39 [-]: CALL R1 4 1  ; var1(var2, var3, var4)
L 3:  40 [-]: GETIMPORT R1 1; var1 = 0xCB79539E
      41 [-]: GETIMPORT R3 7; var3 = 0x0469F296
      42 [-]: LOADK R4 K15 ; var4 = "DUVIRI_TUTORIAL_STAGE"
      43 [-]: CALL R3 2 2  ; var3 = var3(var4)
      44 [-]: LOADK R5 K11 ; var5 = "4_UndercroftEncounter_"
      45 [-]: MOVE R6 R0   ; var6 = var0
      46 [-]: CONCAT R4 R5 R6; var4 = var5 .. var6
      47 [-]: NAMECALL R1 R1 K16; var2 = var1; var1 = var1[0x8B8FB8B7]
      48 [-]: CALL R1 4 1  ; var1(var2, var3, var4)
L 4:  49 [-]: SETUPVAL R0 1; upvalues[0] = var1
      50 [-]: MOVE R1 R0   ; var1 = var0
      51 [-]: MOVE R2 R1   ; var2 = var1
      52 [-]: JUMPIF R2 L5 ; goto L5 if var2
      53 [-]: GETUPVAL R2 1; var2 = upvalues[1]
L 5:  54 [-]: MOVE R1 R2   ; var1 = var2
      55 [-]: JUMPXEQKN R1 K17 L6 NOT; 
      56 [-]: JUMP L7      ; goto L7
L 6:  57 [-]: LOADK R3 K18 ; var3 = "[DEBUG] Stage: "
      58 [-]: MOVE R4 R1   ; var4 = var1
      59 [-]: LOADK R5 K19 ; var5 = " "
      60 [-]: MOVE R7 R1   ; var7 = var1
      61 [-]: GETUPVAL R9 2; var9 = upvalues[2]
      62 [-]: GETTABLE R8 R9 R7; var8 = var9[var7]
      63 [-]: GETTABLEKS R6 R8 K20; var6 = var8["name"]
      64 [-]: CONCAT R2 R3 R6; var2 = var3 .. var6
      65 [-]: GETIMPORT R3 22; var3 = 0x3D106989
      66 [-]: MOVE R4 R2   ; var4 = var2
      67 [-]: CALL R3 2 1  ; var3(var4)
L 7:  68 [-]: GETUPVAL R1 3; var1 = upvalues[3]
      69 [-]: JUMPIFNOT R1 L16; goto L16 if not var1
      70 [-]: GETUPVAL R1 3; var1 = upvalues[3]
      71 [-]: GETUPVAL R3 0; var3 = upvalues[0]
      72 [-]: GETTABLEKS R2 R3 K23; var2 = var3["WARFRAME_SELECTED"]
      73 [-]: JUMPIFNOTLE R2 R1 L16; goto L16 if var2 > var196924
      74 [-]: GETUPVAL R1 3; var1 = upvalues[3]
      75 [-]: GETUPVAL R3 0; var3 = upvalues[0]
      76 [-]: GETTABLEKS R2 R3 K13; var2 = var3["COMPLETE"]
      77 [-]: JUMPIFNOTLT R1 R2 L16; goto L16 if var1 >= var196924
      78 [-]: GETUPVAL R1 3; var1 = upvalues[3]
      79 [-]: GETUPVAL R3 0; var3 = upvalues[0]
      80 [-]: GETTABLEKS R2 R3 K24; var2 = var3["TEST_SUIT"]
      81 [-]: JUMPIFNOTLE R2 R1 L8; goto L8 if var2 > var196924
      82 [-]: GETUPVAL R1 3; var1 = upvalues[3]
      83 [-]: GETUPVAL R3 0; var3 = upvalues[0]
      84 [-]: GETTABLEKS R2 R3 K13; var2 = var3["COMPLETE"]
      85 [-]: JUMPIFNOTLT R1 R2 L8; goto L8 if var1 >= var262460
      86 [-]: GETUPVAL R1 4; var1 = upvalues[4]
      87 [-]: CALL R1 1 1  ; var1()
      88 [-]: GETUPVAL R2 6; var2 = upvalues[6]
      89 [-]: GETTABLEKS R1 R2 K25; var1 = var2[0x3DF1EF0C]
      90 [-]: LOADB R2 1   ; var2 = true
      91 [-]: GETUPVAL R3 7; var3 = upvalues[7]
      92 [-]: GETUPVAL R4 5; var4 = upvalues[5]
      93 [-]: CALL R1 4 2  ; var1 = var1(var2, var3, var4)
      94 [-]: SETUPVAL R1 5; upvalues[1] = var5
      95 [-]: GETIMPORT R1 27; var1 = 0x89326C93
      96 [-]: NAMECALL R1 R1 K28; var2 = var1; var1 = var1[0x29EF273D]
      97 [-]: CALL R1 2 2  ; var1 = var1(var2)
      98 [-]: GETIMPORT R3 30; var3 = 0x88431D72
      99 [-]: NAMECALL R1 R1 K31; var2 = var1; var1 = var1[0x8955C0B5]
     100 [-]: CALL R1 3 1  ; var1(var2, var3)
L 8: 101 [-]: GETUPVAL R1 3; var1 = upvalues[3]
     102 [-]: GETUPVAL R3 0; var3 = upvalues[0]
     103 [-]: GETTABLEKS R2 R3 K23; var2 = var3["WARFRAME_SELECTED"]
     104 [-]: JUMPIFNOTLE R2 R1 L9; goto L9 if var2 > var524860
     105 [-]: GETUPVAL R2 8; var2 = upvalues[8]
     106 [-]: GETTABLEKS R1 R2 K32; var1 = var2[0x12A41A40]
     107 [-]: LOADB R2 0   ; var2 = false
     108 [-]: LOADN R3 0   ; var3 = 0
     109 [-]: CALL R1 3 1  ; var1(var2, var3)
     110 [-]: GETIMPORT R1 27; var1 = 0x89326C93
     111 [-]: GETIMPORT R3 7; var3 = 0x0469F296
     112 [-]: LOADK R4 K33 ; var4 = "ChooseExcalCin"
     113 [-]: CALL R3 2 0  ; var3, ... = var3(var4)
     114 [-]: NAMECALL R1 R1 K34; var2 = var1; var1 = var1[0x46A0EBF5]
     115 [-]: CALL R1 0 2  ; var1 = var1(var2, ...)
     116 [-]: SETUPVAL R1 9; upvalues[1] = var9
     117 [-]: GETUPVAL R1 10; var1 = upvalues[10]
     118 [-]: LOADN R2 3   ; var2 = 3
     119 [-]: GETIMPORT R5 37; var5 = _T["DuviriQuestWeapons"]
     120 [-]: LOADN R6 3   ; var6 = 3
     121 [-]: GETTABLE R4 R5 R6; var4 = var5[var6]
     122 [-]: GETTABLEN R3 R4 1; var3 = var4[1]
     123 [-]: SETTABLE R3 R1 R2; var3[var1] = var2
     124 [-]: GETUPVAL R2 11; var2 = upvalues[11]
     125 [-]: GETTABLEKS R1 R2 K38; var1 = var2[0x94B054B1]
     126 [-]: GETUPVAL R3 10; var3 = upvalues[10]
     127 [-]: LOADN R4 3   ; var4 = 3
     128 [-]: GETTABLE R2 R3 R4; var2 = var3[var4]
     129 [-]: LOADN R3 3   ; var3 = 3
     130 [-]: CALL R1 3 1  ; var1(var2, var3)
L 9: 131 [-]: GETUPVAL R1 3; var1 = upvalues[3]
     132 [-]: GETUPVAL R3 0; var3 = upvalues[0]
     133 [-]: GETTABLEKS R2 R3 K39; var2 = var3["TEST_SECONDARY"]
     134 [-]: JUMPIFNOTLE R2 R1 L10; goto L10 if var2 > var655676
     135 [-]: GETUPVAL R1 10; var1 = upvalues[10]
     136 [-]: LOADN R2 0   ; var2 = 0
     137 [-]: GETIMPORT R5 37; var5 = _T["DuviriQuestWeapons"]
     138 [-]: LOADN R6 0   ; var6 = 0
     139 [-]: GETTABLE R4 R5 R6; var4 = var5[var6]
     140 [-]: GETTABLEN R3 R4 1; var3 = var4[1]
     141 [-]: SETTABLE R3 R1 R2; var3[var1] = var2
     142 [-]: GETIMPORT R1 27; var1 = 0x89326C93
     143 [-]: GETIMPORT R3 7; var3 = 0x0469F296
     144 [-]: LOADK R4 K40 ; var4 = "SetupSecondariesTrigger"
     145 [-]: CALL R3 2 0  ; var3, ... = var3(var4)
     146 [-]: NAMECALL R1 R1 K34; var2 = var1; var1 = var1[0x46A0EBF5]
     147 [-]: CALL R1 0 2  ; var1 = var1(var2, ...)
     148 [-]: LOADK R4 K41 ; var4 = "Execute"
     149 [-]: NAMECALL R2 R1 K42; var3 = var1; var2 = var1[0x8EB2112D]
     150 [-]: CALL R2 3 1  ; var2(var3, var4)
     151 [-]: LOADN R2 0   ; var2 = 0
     152 [-]: GETUPVAL R3 10; var3 = upvalues[10]
     153 [-]: GETIMPORT R6 37; var6 = _T["DuviriQuestWeapons"]
     154 [-]: GETTABLE R5 R6 R2; var5 = var6[var2]
     155 [-]: GETTABLEN R4 R5 1; var4 = var5[1]
     156 [-]: SETTABLE R4 R3 R2; var4[var3] = var2
     157 [-]: SETUPVAL R2 12; upvalues[2] = var12
     158 [-]: GETUPVAL R4 11; var4 = upvalues[11]
     159 [-]: GETTABLEKS R3 R4 K38; var3 = var4[0x94B054B1]
     160 [-]: GETUPVAL R5 10; var5 = upvalues[10]
     161 [-]: GETTABLE R4 R5 R2; var4 = var5[var2]
     162 [-]: MOVE R5 R2   ; var5 = var2
     163 [-]: CALL R3 3 1  ; var3(var4, var5)
L10: 164 [-]: GETUPVAL R1 3; var1 = upvalues[3]
     165 [-]: GETUPVAL R3 0; var3 = upvalues[0]
     166 [-]: GETTABLEKS R2 R3 K43; var2 = var3["TEST_PRIMARY"]
     167 [-]: JUMPIFNOTLE R2 R1 L11; goto L11 if var2 > var655676
     168 [-]: GETUPVAL R1 10; var1 = upvalues[10]
     169 [-]: LOADN R2 1   ; var2 = 1
     170 [-]: GETIMPORT R5 37; var5 = _T["DuviriQuestWeapons"]
     171 [-]: LOADN R6 1   ; var6 = 1
     172 [-]: GETTABLE R4 R5 R6; var4 = var5[var6]
     173 [-]: GETTABLEN R3 R4 1; var3 = var4[1]
     174 [-]: SETTABLE R3 R1 R2; var3[var1] = var2
     175 [-]: GETIMPORT R1 27; var1 = 0x89326C93
     176 [-]: GETIMPORT R3 7; var3 = 0x0469F296
     177 [-]: LOADK R4 K44 ; var4 = "SetupPrimariesTrigger"
     178 [-]: CALL R3 2 0  ; var3, ... = var3(var4)
     179 [-]: NAMECALL R1 R1 K34; var2 = var1; var1 = var1[0x46A0EBF5]
     180 [-]: CALL R1 0 2  ; var1 = var1(var2, ...)
     181 [-]: LOADK R4 K41 ; var4 = "Execute"
     182 [-]: NAMECALL R2 R1 K42; var3 = var1; var2 = var1[0x8EB2112D]
     183 [-]: CALL R2 3 1  ; var2(var3, var4)
     184 [-]: LOADN R2 1   ; var2 = 1
     185 [-]: GETUPVAL R3 10; var3 = upvalues[10]
     186 [-]: GETIMPORT R6 37; var6 = _T["DuviriQuestWeapons"]
     187 [-]: GETTABLE R5 R6 R2; var5 = var6[var2]
     188 [-]: GETTABLEN R4 R5 1; var4 = var5[1]
     189 [-]: SETTABLE R4 R3 R2; var4[var3] = var2
     190 [-]: SETUPVAL R2 12; upvalues[2] = var12
     191 [-]: GETUPVAL R4 11; var4 = upvalues[11]
     192 [-]: GETTABLEKS R3 R4 K38; var3 = var4[0x94B054B1]
     193 [-]: GETUPVAL R5 10; var5 = upvalues[10]
     194 [-]: GETTABLE R4 R5 R2; var4 = var5[var2]
     195 [-]: MOVE R5 R2   ; var5 = var2
     196 [-]: CALL R3 3 1  ; var3(var4, var5)
L11: 197 [-]: GETUPVAL R1 3; var1 = upvalues[3]
     198 [-]: GETUPVAL R3 0; var3 = upvalues[0]
     199 [-]: GETTABLEKS R2 R3 K45; var2 = var3["TEST_MELEE"]
     200 [-]: JUMPIFNOTLE R2 R1 L12; goto L12 if var2 > var655676
     201 [-]: GETUPVAL R1 10; var1 = upvalues[10]
     202 [-]: LOADN R2 5   ; var2 = 5
     203 [-]: GETIMPORT R5 37; var5 = _T["DuviriQuestWeapons"]
     204 [-]: LOADN R6 5   ; var6 = 5
     205 [-]: GETTABLE R4 R5 R6; var4 = var5[var6]
     206 [-]: GETTABLEN R3 R4 1; var3 = var4[1]
     207 [-]: SETTABLE R3 R1 R2; var3[var1] = var2
     208 [-]: GETIMPORT R1 27; var1 = 0x89326C93
     209 [-]: GETIMPORT R3 7; var3 = 0x0469F296
     210 [-]: LOADK R4 K46 ; var4 = "SetupMeleeTrigger"
     211 [-]: CALL R3 2 0  ; var3, ... = var3(var4)
     212 [-]: NAMECALL R1 R1 K34; var2 = var1; var1 = var1[0x46A0EBF5]
     213 [-]: CALL R1 0 2  ; var1 = var1(var2, ...)
     214 [-]: LOADK R4 K41 ; var4 = "Execute"
     215 [-]: NAMECALL R2 R1 K42; var3 = var1; var2 = var1[0x8EB2112D]
     216 [-]: CALL R2 3 1  ; var2(var3, var4)
     217 [-]: LOADN R2 5   ; var2 = 5
     218 [-]: GETUPVAL R3 10; var3 = upvalues[10]
     219 [-]: GETIMPORT R6 37; var6 = _T["DuviriQuestWeapons"]
     220 [-]: GETTABLE R5 R6 R2; var5 = var6[var2]
     221 [-]: GETTABLEN R4 R5 1; var4 = var5[1]
     222 [-]: SETTABLE R4 R3 R2; var4[var3] = var2
     223 [-]: SETUPVAL R2 12; upvalues[2] = var12
     224 [-]: GETUPVAL R4 11; var4 = upvalues[11]
     225 [-]: GETTABLEKS R3 R4 K38; var3 = var4[0x94B054B1]
     226 [-]: GETUPVAL R5 10; var5 = upvalues[10]
     227 [-]: GETTABLE R4 R5 R2; var4 = var5[var2]
     228 [-]: MOVE R5 R2   ; var5 = var2
     229 [-]: CALL R3 3 1  ; var3(var4, var5)
L12: 230 [-]: LOADNIL R1   ; var1 = nil
L13: 231 [-]: FASTCALL1 64 R1 L14; 
     232 [-]: MOVE R3 R1   ; var3 = var1
     233 [-]: GETIMPORT R2 3; var2 = 0x7B998233
     234 [-]: CALL R2 2 2  ; var2 = var2(var3)
L14: 235 [-]: JUMPIFNOT R2 L15; goto L15 if not var2
     236 [-]: GETIMPORT R2 48; var2 = 0xCBD666E1
     237 [-]: LOADN R3 0   ; var3 = 0
     238 [-]: CALL R2 2 1  ; var2(var3)
     239 [-]: GETUPVAL R2 5; var2 = upvalues[5]
     240 [-]: NAMECALL R2 R2 K49; var3 = var2; var2 = var2[0xDE321E6F]
     241 [-]: CALL R2 2 2  ; var2 = var2(var3)
     242 [-]: NAMECALL R2 R2 K50; var3 = var2; var2 = var2[0xF7D48EE0]
     243 [-]: CALL R2 2 2  ; var2 = var2(var3)
     244 [-]: MOVE R1 R2   ; var1 = var2
     245 [-]: JUMPBACK L13 ; goto L13
L15: 246 [-]: GETUPVAL R2 3; var2 = upvalues[3]
     247 [-]: GETUPVAL R4 0; var4 = upvalues[0]
     248 [-]: GETTABLEKS R3 R4 K24; var3 = var4["TEST_SUIT"]
     249 [-]: JUMPIFNOTLE R3 R2 L16; goto L16 if var3 > var852540
     250 [-]: GETUPVAL R2 13; var2 = upvalues[13]
     251 [-]: CALL R2 1 1  ; var2()
L16: 252 [-]: GETUPVAL R2 0; var2 = upvalues[0]
     253 [-]: GETTABLEKS R1 R2 K5; var1 = var2["SELECT_WARFRAME"]
     254 [-]: JUMPIFNOTEQ R0 R1 L23; goto L23 if var0 ~= var327996
     255 [-]: GETUPVAL R1 5; var1 = upvalues[5]
     256 [-]: NAMECALL R1 R1 K51; var2 = var1; var1 = var1[0x1AC1655C]
     257 [-]: CALL R1 2 2  ; var1 = var1(var2)
     258 [-]: GETIMPORT R3 7; var3 = 0x0469F296
     259 [-]: LOADK R4 K52 ; var4 = "DragonCinInvuln"
     260 [-]: CALL R3 2 0  ; var3, ... = var3(var4)
     261 [-]: NAMECALL R1 R1 K53; var2 = var1; var1 = var1[0x8E3E343E]
     262 [-]: CALL R1 0 1  ; var1(var2, ...)
     263 [-]: GETUPVAL R1 14; var1 = upvalues[14]
     264 [-]: GETIMPORT R3 7; var3 = 0x0469F296
     265 [-]: LOADK R4 K54 ; var4 = "SelectWarframe"
     266 [-]: CALL R3 2 2  ; var3 = var3(var4)
     267 [-]: LOADB R4 0   ; var4 = false
     268 [-]: NAMECALL R1 R1 K55; var2 = var1; var1 = var1[0xD5F7912B]
     269 [-]: CALL R1 4 1  ; var1(var2, var3, var4)
     270 [-]: GETIMPORT R1 27; var1 = 0x89326C93
     271 [-]: GETIMPORT R3 7; var3 = 0x0469F296
     272 [-]: LOADK R4 K56 ; var4 = "HideWarframes"
     273 [-]: CALL R3 2 0  ; var3, ... = var3(var4)
     274 [-]: NAMECALL R1 R1 K34; var2 = var1; var1 = var1[0x46A0EBF5]
     275 [-]: CALL R1 0 2  ; var1 = var1(var2, ...)
     276 [-]: LOADK R4 K57 ; var4 = "TriggerPort"
     277 [-]: NAMECALL R2 R1 K42; var3 = var1; var2 = var1[0x8EB2112D]
     278 [-]: CALL R2 3 1  ; var2(var3, var4)
     279 [-]: GETIMPORT R2 37; var2 = _T["DuviriQuestWeapons"]
     280 [-]: JUMPIFNOT R2 L22; goto L22 if not var2
     281 [-]: GETIMPORT R3 37; var3 = _T["DuviriQuestWeapons"]
     282 [-]: LOADN R4 3   ; var4 = 3
     283 [-]: GETTABLE R2 R3 R4; var2 = var3[var4]
     284 [-]: JUMPIFNOT R2 L22; goto L22 if not var2
     285 [-]: NEWTABLE R2 0 0; var2 = {}
     286 [-]: GETIMPORT R3 59; var3 = 0xC8802016
     287 [-]: GETIMPORT R6 37; var6 = _T["DuviriQuestWeapons"]
     288 [-]: LOADN R7 3   ; var7 = 3
     289 [-]: GETTABLE R4 R6 R7; var4 = var6[var7]
     290 [-]: CALL R3 2 4  ; var3, var4, var5 = var3(var4)
     291 [-]: FORGPREP_INEXT R3 L20; 
L17: 292 [-]: GETIMPORT R8 61; var8 = 0x25D99D89
     293 [-]: MOVE R10 R7  ; var10 = var7
     294 [-]: NAMECALL R8 R8 K62; var9 = var8; var8 = var8[0xAF0B6EB6]
     295 [-]: CALL R8 3 2  ; var8 = var8(var9, var10)
     296 [-]: GETIMPORT R9 59; var9 = 0xC8802016
     297 [-]: MOVE R10 R8  ; var10 = var8
     298 [-]: CALL R9 2 4  ; var9, var10, var11 = var9(var10)
     299 [-]: FORGPREP_INEXT R9 L19; 
L18: 300 [-]: FASTCALL2 52 R2 R13 L19; 
     301 [-]: MOVE R15 R2  ; var15 = var2
     302 [-]: MOVE R16 R13 ; var16 = var13
     303 [-]: GETIMPORT R14 65; var14 = 0x33BDD652[0x23D5322F]
     304 [-]: CALL R14 3 1 ; var14(var15, var16)
L19: 305 [-]: FORGLOOP R9 L18 2 [inext]; 
L20: 306 [-]: FORGLOOP R3 L17 2 [inext]; 
     307 [-]: LENGTH R3 R2 ; var3 = #var2
     308 [-]: LOADN R4 0   ; var4 = 0
     309 [-]: JUMPIFNOTLT R4 R3 L22; goto L22 if var4 >= var4457249
     310 [-]: GETIMPORT R3 68; var3 = 0xBD496AA1[0x42645DA3]
     311 [-]: MOVE R4 R2   ; var4 = var2
     312 [-]: CALL R3 2 2  ; var3 = var3(var4)
L21: 313 [-]: NAMECALL R4 R3 K69; var5 = var3; var4 = var3[0xD2D3875A]
     314 [-]: CALL R4 2 2  ; var4 = var4(var5)
     315 [-]: JUMPIF R4 L22; goto L22 if var4
     316 [-]: GETIMPORT R4 48; var4 = 0xCBD666E1
     317 [-]: LOADN R5 0   ; var5 = 0
     318 [-]: CALL R4 2 1  ; var4(var5)
     319 [-]: JUMPBACK L21 ; goto L21
L22: 320 [-]: GETUPVAL R2 15; var2 = upvalues[15]
     321 [-]: LOADK R4 K41 ; var4 = "Execute"
     322 [-]: NAMECALL R2 R2 K42; var3 = var2; var2 = var2[0x8EB2112D]
     323 [-]: CALL R2 3 1  ; var2(var3, var4)
     324 [-]: JUMP L35     ; goto L35
L23: 325 [-]: GETUPVAL R2 0; var2 = upvalues[0]
     326 [-]: GETTABLEKS R1 R2 K23; var1 = var2["WARFRAME_SELECTED"]
     327 [-]: JUMPIFNOTEQ R0 R1 L24; goto L24 if var0 ~= var917820
     328 [-]: GETUPVAL R1 14; var1 = upvalues[14]
     329 [-]: GETIMPORT R3 7; var3 = 0x0469F296
     330 [-]: LOADK R4 K70 ; var4 = "WarframeSelected"
     331 [-]: CALL R3 2 2  ; var3 = var3(var4)
     332 [-]: LOADB R4 0   ; var4 = false
     333 [-]: NAMECALL R1 R1 K55; var2 = var1; var1 = var1[0xD5F7912B]
     334 [-]: CALL R1 4 1  ; var1(var2, var3, var4)
     335 [-]: JUMP L35     ; goto L35
L24: 336 [-]: GETUPVAL R2 0; var2 = upvalues[0]
     337 [-]: GETTABLEKS R1 R2 K71; var1 = var2["MOVEMENT_TUTORIAL"]
     338 [-]: JUMPIFNOTEQ R0 R1 L25; goto L25 if var0 ~= var917820
     339 [-]: GETUPVAL R1 14; var1 = upvalues[14]
     340 [-]: GETIMPORT R3 7; var3 = 0x0469F296
     341 [-]: LOADK R4 K72 ; var4 = "MovementTutorial"
     342 [-]: CALL R3 2 2  ; var3 = var3(var4)
     343 [-]: LOADB R4 0   ; var4 = false
     344 [-]: NAMECALL R1 R1 K55; var2 = var1; var1 = var1[0xD5F7912B]
     345 [-]: CALL R1 4 1  ; var1(var2, var3, var4)
     346 [-]: JUMP L35     ; goto L35
L25: 347 [-]: GETUPVAL R2 0; var2 = upvalues[0]
     348 [-]: GETTABLEKS R1 R2 K24; var1 = var2["TEST_SUIT"]
     349 [-]: JUMPIFNOTEQ R0 R1 L26; goto L26 if var0 ~= var917820
     350 [-]: GETUPVAL R1 14; var1 = upvalues[14]
     351 [-]: GETIMPORT R3 7; var3 = 0x0469F296
     352 [-]: LOADK R4 K73 ; var4 = "TestSuit"
     353 [-]: CALL R3 2 2  ; var3 = var3(var4)
     354 [-]: LOADB R4 0   ; var4 = false
     355 [-]: NAMECALL R1 R1 K55; var2 = var1; var1 = var1[0xD5F7912B]
     356 [-]: CALL R1 4 1  ; var1(var2, var3, var4)
     357 [-]: JUMP L35     ; goto L35
L26: 358 [-]: GETUPVAL R2 0; var2 = upvalues[0]
     359 [-]: GETTABLEKS R1 R2 K74; var1 = var2["SELECT_SECONDARY"]
     360 [-]: JUMPIFNOTEQ R0 R1 L27; goto L27 if var0 ~= var917820
     361 [-]: GETUPVAL R1 14; var1 = upvalues[14]
     362 [-]: GETIMPORT R3 7; var3 = 0x0469F296
     363 [-]: LOADK R4 K75 ; var4 = "SelectSecondary"
     364 [-]: CALL R3 2 2  ; var3 = var3(var4)
     365 [-]: LOADB R4 0   ; var4 = false
     366 [-]: NAMECALL R1 R1 K55; var2 = var1; var1 = var1[0xD5F7912B]
     367 [-]: CALL R1 4 1  ; var1(var2, var3, var4)
     368 [-]: JUMP L35     ; goto L35
L27: 369 [-]: GETUPVAL R2 0; var2 = upvalues[0]
     370 [-]: GETTABLEKS R1 R2 K39; var1 = var2["TEST_SECONDARY"]
     371 [-]: JUMPIFNOTEQ R0 R1 L28; goto L28 if var0 ~= var917820
     372 [-]: GETUPVAL R1 14; var1 = upvalues[14]
     373 [-]: GETIMPORT R3 7; var3 = 0x0469F296
     374 [-]: LOADK R4 K76 ; var4 = "TestSecondary"
     375 [-]: CALL R3 2 2  ; var3 = var3(var4)
     376 [-]: LOADB R4 0   ; var4 = false
     377 [-]: NAMECALL R1 R1 K55; var2 = var1; var1 = var1[0xD5F7912B]
     378 [-]: CALL R1 4 1  ; var1(var2, var3, var4)
     379 [-]: JUMP L35     ; goto L35
L28: 380 [-]: GETUPVAL R2 0; var2 = upvalues[0]
     381 [-]: GETTABLEKS R1 R2 K77; var1 = var2["SELECT_PRIMARY"]
     382 [-]: JUMPIFNOTEQ R0 R1 L29; goto L29 if var0 ~= var917820
     383 [-]: GETUPVAL R1 14; var1 = upvalues[14]
     384 [-]: GETIMPORT R3 7; var3 = 0x0469F296
     385 [-]: LOADK R4 K78 ; var4 = "SelectPrimary"
     386 [-]: CALL R3 2 2  ; var3 = var3(var4)
     387 [-]: LOADB R4 0   ; var4 = false
     388 [-]: NAMECALL R1 R1 K55; var2 = var1; var1 = var1[0xD5F7912B]
     389 [-]: CALL R1 4 1  ; var1(var2, var3, var4)
     390 [-]: JUMP L35     ; goto L35
L29: 391 [-]: GETUPVAL R2 0; var2 = upvalues[0]
     392 [-]: GETTABLEKS R1 R2 K43; var1 = var2["TEST_PRIMARY"]
     393 [-]: JUMPIFNOTEQ R0 R1 L30; goto L30 if var0 ~= var917820
     394 [-]: GETUPVAL R1 14; var1 = upvalues[14]
     395 [-]: GETIMPORT R3 7; var3 = 0x0469F296
     396 [-]: LOADK R4 K79 ; var4 = "TestPrimary"
     397 [-]: CALL R3 2 2  ; var3 = var3(var4)
     398 [-]: LOADB R4 0   ; var4 = false
     399 [-]: NAMECALL R1 R1 K55; var2 = var1; var1 = var1[0xD5F7912B]
     400 [-]: CALL R1 4 1  ; var1(var2, var3, var4)
     401 [-]: JUMP L35     ; goto L35
L30: 402 [-]: GETUPVAL R2 0; var2 = upvalues[0]
     403 [-]: GETTABLEKS R1 R2 K80; var1 = var2["SELECT_MELEE"]
     404 [-]: JUMPIFNOTEQ R0 R1 L31; goto L31 if var0 ~= var917820
     405 [-]: GETUPVAL R1 14; var1 = upvalues[14]
     406 [-]: GETIMPORT R3 7; var3 = 0x0469F296
     407 [-]: LOADK R4 K81 ; var4 = "SelectMelee"
     408 [-]: CALL R3 2 2  ; var3 = var3(var4)
     409 [-]: LOADB R4 0   ; var4 = false
     410 [-]: NAMECALL R1 R1 K55; var2 = var1; var1 = var1[0xD5F7912B]
     411 [-]: CALL R1 4 1  ; var1(var2, var3, var4)
     412 [-]: JUMP L35     ; goto L35
L31: 413 [-]: GETUPVAL R2 0; var2 = upvalues[0]
     414 [-]: GETTABLEKS R1 R2 K45; var1 = var2["TEST_MELEE"]
     415 [-]: JUMPIFNOTEQ R0 R1 L32; goto L32 if var0 ~= var917820
     416 [-]: GETUPVAL R1 14; var1 = upvalues[14]
     417 [-]: GETIMPORT R3 7; var3 = 0x0469F296
     418 [-]: LOADK R4 K82 ; var4 = "TestMelee"
     419 [-]: CALL R3 2 2  ; var3 = var3(var4)
     420 [-]: LOADB R4 0   ; var4 = false
     421 [-]: NAMECALL R1 R1 K55; var2 = var1; var1 = var1[0xD5F7912B]
     422 [-]: CALL R1 4 1  ; var1(var2, var3, var4)
     423 [-]: JUMP L35     ; goto L35
L32: 424 [-]: GETUPVAL R2 0; var2 = upvalues[0]
     425 [-]: GETTABLEKS R1 R2 K83; var1 = var2["STAY_OR_LEAVE"]
     426 [-]: JUMPIFNOTEQ R0 R1 L33; goto L33 if var0 ~= var917820
     427 [-]: GETUPVAL R1 14; var1 = upvalues[14]
     428 [-]: GETIMPORT R3 7; var3 = 0x0469F296
     429 [-]: LOADK R4 K84 ; var4 = "StayOrLeave"
     430 [-]: CALL R3 2 2  ; var3 = var3(var4)
     431 [-]: LOADB R4 0   ; var4 = false
     432 [-]: NAMECALL R1 R1 K55; var2 = var1; var1 = var1[0xD5F7912B]
     433 [-]: CALL R1 4 1  ; var1(var2, var3, var4)
     434 [-]: JUMP L35     ; goto L35
L33: 435 [-]: GETUPVAL R2 0; var2 = upvalues[0]
     436 [-]: GETTABLEKS R1 R2 K13; var1 = var2["COMPLETE"]
     437 [-]: JUMPIFNOTEQ R0 R1 L34; goto L34 if var0 ~= var1049148
     438 [-]: GETUPVAL R2 16; var2 = upvalues[16]
     439 [-]: GETTABLEKS R1 R2 K85; var1 = var2[0xDC3B2033]
     440 [-]: CALL R1 1 1  ; var1()
     441 [-]: GETUPVAL R1 14; var1 = upvalues[14]
     442 [-]: GETIMPORT R3 7; var3 = 0x0469F296
     443 [-]: LOADK R4 K86 ; var4 = "Complete"
     444 [-]: CALL R3 2 2  ; var3 = var3(var4)
     445 [-]: LOADB R4 0   ; var4 = false
     446 [-]: NAMECALL R1 R1 K55; var2 = var1; var1 = var1[0xD5F7912B]
     447 [-]: CALL R1 4 1  ; var1(var2, var3, var4)
     448 [-]: JUMP L35     ; goto L35
L34: 449 [-]: GETUPVAL R2 0; var2 = upvalues[0]
     450 [-]: GETTABLEKS R1 R2 K4; var1 = var2["RESPAWN"]
     451 [-]: JUMPIFNOTEQ R0 R1 L35; goto L35 if var0 ~= var524860
     452 [-]: GETUPVAL R2 8; var2 = upvalues[8]
     453 [-]: GETTABLEKS R1 R2 K87; var1 = var2[0x4A6404E4]
     454 [-]: GETUPVAL R2 2; var2 = upvalues[2]
     455 [-]: GETUPVAL R3 17; var3 = upvalues[17]
     456 [-]: GETUPVAL R4 5; var4 = upvalues[5]
     457 [-]: LOADNIL R5   ; var5 = nil
     458 [-]: LOADNIL R6   ; var6 = nil
     459 [-]: LOADB R7 1   ; var7 = true
     460 [-]: CALL R1 7 2  ; var1 = var1(var2, var3, var4, var5, var6, var7)
     461 [-]: SETUPVAL R1 17; upvalues[1] = var17
L35: 462 [-]: GETUPVAL R1 3; var1 = upvalues[3]
     463 [-]: JUMPIFNOT R1 L36; goto L36 if not var1
     464 [-]: GETUPVAL R2 18; var2 = upvalues[18]
     465 [-]: GETTABLEKS R1 R2 K88; var1 = var2[0x76247E4F]
     466 [-]: GETUPVAL R2 3; var2 = upvalues[3]
     467 [-]: GETUPVAL R3 2; var3 = upvalues[2]
     468 [-]: CALL R1 3 1  ; var1(var2, var3)
L36: 469 [-]: RETURN R0 0  ; 


; Name:            
; Defined at line: 1299
; #Upvalues:       14
; #Parameters:     1
; Is_vararg:       0
; Max Stack Size:  5

       0 [-]: GETIMPORT R1 2; var1 = _T["PlayerDead"]
       1 [-]: JUMPIFNOT R1 L0; goto L0 if not var1
       2 [-]: GETUPVAL R1 1; var1 = upvalues[1]
       3 [-]: SETUPVAL R1 0; upvalues[1] = var0
       4 [-]: GETUPVAL R1 2; var1 = upvalues[2]
       5 [-]: GETUPVAL R4 3; var4 = upvalues[3]
       6 [-]: GETTABLEKS R3 R4 K3; var3 = var4["RESPAWN"]
       7 [-]: NAMECALL R1 R1 K4; var2 = var1; var1 = var1[0x8ABFF40E]
       8 [-]: CALL R1 3 1  ; var1(var2, var3)
       9 [-]: RETURN R0 0  ; 
L 0:  10 [-]: GETUPVAL R1 4; var1 = upvalues[4]
      11 [-]: JUMPIFNOT R1 L1; goto L1 if not var1
      12 [-]: GETUPVAL R1 2; var1 = upvalues[2]
      13 [-]: GETUPVAL R3 4; var3 = upvalues[4]
      14 [-]: NAMECALL R1 R1 K4; var2 = var1; var1 = var1[0x8ABFF40E]
      15 [-]: CALL R1 3 1  ; var1(var2, var3)
      16 [-]: LOADNIL R1   ; var1 = nil
      17 [-]: SETUPVAL R1 4; upvalues[1] = var4
      18 [-]: RETURN R0 0  ; 
L 1:  19 [-]: GETUPVAL R1 5; var1 = upvalues[5]
      20 [-]: MOVE R3 R0   ; var3 = var0
      21 [-]: NAMECALL R1 R1 K5; var2 = var1; var1 = var1[0xFAA69527]
      22 [-]: CALL R1 3 1  ; var1(var2, var3)
      23 [-]: GETUPVAL R1 6; var1 = upvalues[6]
      24 [-]: JUMPIF R1 L2 ; goto L2 if var1
      25 [-]: GETUPVAL R1 7; var1 = upvalues[7]
      26 [-]: LOADN R3 0   ; var3 = 0
      27 [-]: NAMECALL R1 R1 K6; var2 = var1; var1 = var1[0xE3A0BBCA]
      28 [-]: CALL R1 3 2  ; var1 = var1(var2, var3)
      29 [-]: NAMECALL R1 R1 K7; var2 = var1; var1 = var1[0x2047CFE7]
      30 [-]: CALL R1 2 2  ; var1 = var1(var2)
      31 [-]: JUMPIFNOT R1 L2; goto L2 if not var1
      32 [-]: GETUPVAL R1 8; var1 = upvalues[8]
      33 [-]: GETIMPORT R3 9; var3 = 0x0469F296
      34 [-]: LOADK R4 K10 ; var4 = "RespawnWarframe"
      35 [-]: CALL R3 2 2  ; var3 = var3(var4)
      36 [-]: LOADB R4 0   ; var4 = false
      37 [-]: NAMECALL R1 R1 K11; var2 = var1; var1 = var1[0xD5F7912B]
      38 [-]: CALL R1 4 1  ; var1(var2, var3, var4)
L 2:  39 [-]: GETUPVAL R1 1; var1 = upvalues[1]
      40 [-]: GETUPVAL R3 3; var3 = upvalues[3]
      41 [-]: GETTABLEKS R2 R3 K12; var2 = var3["SELECT_WARFRAME"]
      42 [-]: JUMPIFNOTEQ R1 R2 L3; goto L3 if var1 ~= var65571
      43 [-]: RETURN R0 0  ; 
L 3:  44 [-]: GETUPVAL R1 1; var1 = upvalues[1]
      45 [-]: GETUPVAL R3 3; var3 = upvalues[3]
      46 [-]: GETTABLEKS R2 R3 K13; var2 = var3["WARFRAME_SELECTED"]
      47 [-]: JUMPIFNOTEQ R1 R2 L4; goto L4 if var1 ~= var65571
      48 [-]: RETURN R0 0  ; 
L 4:  49 [-]: GETUPVAL R1 1; var1 = upvalues[1]
      50 [-]: GETUPVAL R3 3; var3 = upvalues[3]
      51 [-]: GETTABLEKS R2 R3 K14; var2 = var3["MOVEMENT_TUTORIAL"]
      52 [-]: JUMPIFNOTEQ R1 R2 L5; goto L5 if var1 ~= var65571
      53 [-]: RETURN R0 0  ; 
L 5:  54 [-]: GETUPVAL R1 1; var1 = upvalues[1]
      55 [-]: GETUPVAL R3 3; var3 = upvalues[3]
      56 [-]: GETTABLEKS R2 R3 K15; var2 = var3["TEST_SUIT"]
      57 [-]: JUMPIFNOTEQ R1 R2 L7; goto L7 if var1 ~= var590140
      58 [-]: GETUPVAL R1 9; var1 = upvalues[9]
      59 [-]: JUMPXEQKN R1 K16 L10; 
      60 [-]: GETUPVAL R1 10; var1 = upvalues[10]
      61 [-]: JUMPXEQKN R1 K16 L10; 
      62 [-]: GETUPVAL R1 11; var1 = upvalues[11]
      63 [-]: JUMPIFNOT R1 L10; goto L10 if not var1
      64 [-]: GETUPVAL R1 12; var1 = upvalues[12]
      65 [-]: JUMPIF R1 L6 ; goto L6 if var1
      66 [-]: GETIMPORT R1 19; var1 = 0x34291F5C[0x1467D5F4]
      67 [-]: CALL R1 1 2  ; var1 = var1()
      68 [-]: JUMPIFNOT R1 L6; goto L6 if not var1
      69 [-]: LOADB R1 1   ; var1 = true
      70 [-]: SETUPVAL R1 12; upvalues[1] = var12
      71 [-]: GETUPVAL R1 13; var1 = upvalues[13]
      72 [-]: CALL R1 1 1  ; var1()
      73 [-]: RETURN R0 0  ; 
L 6:  74 [-]: GETUPVAL R1 12; var1 = upvalues[12]
      75 [-]: JUMPIFNOT R1 L10; goto L10 if not var1
      76 [-]: GETIMPORT R1 19; var1 = 0x34291F5C[0x1467D5F4]
      77 [-]: CALL R1 1 2  ; var1 = var1()
      78 [-]: JUMPIF R1 L10; goto L10 if var1
      79 [-]: LOADB R1 0   ; var1 = false
      80 [-]: SETUPVAL R1 12; upvalues[1] = var12
      81 [-]: GETUPVAL R1 13; var1 = upvalues[13]
      82 [-]: CALL R1 1 1  ; var1()
      83 [-]: RETURN R0 0  ; 
L 7:  84 [-]: GETUPVAL R1 1; var1 = upvalues[1]
      85 [-]: GETUPVAL R3 3; var3 = upvalues[3]
      86 [-]: GETTABLEKS R2 R3 K20; var2 = var3["SELECT_SECONDARY"]
      87 [-]: JUMPIFNOTEQ R1 R2 L8; goto L8 if var1 ~= var65571
      88 [-]: RETURN R0 0  ; 
L 8:  89 [-]: GETUPVAL R1 1; var1 = upvalues[1]
      90 [-]: GETUPVAL R3 3; var3 = upvalues[3]
      91 [-]: GETTABLEKS R2 R3 K21; var2 = var3["TEST_SECONDARY"]
      92 [-]: JUMPIFNOTEQ R1 R2 L9; goto L9 if var1 ~= var65571
      93 [-]: RETURN R0 0  ; 
L 9:  94 [-]: GETUPVAL R1 1; var1 = upvalues[1]
      95 [-]: GETUPVAL R3 3; var3 = upvalues[3]
      96 [-]: GETTABLEKS R2 R3 K3; var2 = var3["RESPAWN"]
      97 [-]: JUMPIFNOTEQ R1 R2 L10; goto L10 if var1 ~= var131388
      98 [-]: GETUPVAL R1 2; var1 = upvalues[2]
      99 [-]: GETUPVAL R3 0; var3 = upvalues[0]
     100 [-]: NAMECALL R1 R1 K4; var2 = var1; var1 = var1[0x8ABFF40E]
     101 [-]: CALL R1 3 1  ; var1(var2, var3)
L10: 102 [-]: RETURN R0 0  ; 


; Name:            
; Defined at line: 1347
; #Upvalues:       25
; #Parameters:     1
; Is_vararg:       0
; Max Stack Size:  9

       0 [-]: SETUPVAL R0 0; upvalues[0] = var0
       1 [-]: GETUPVAL R1 0; var1 = upvalues[0]
       2 [-]: NAMECALL R1 R1 K0; var2 = var1; var1 = var1[0x4C976EDA]
       3 [-]: CALL R1 2 2  ; var1 = var1(var2)
       4 [-]: SETUPVAL R1 1; upvalues[1] = var1
       5 [-]: GETUPVAL R1 1; var1 = upvalues[1]
       6 [-]: NAMECALL R1 R1 K1; var2 = var1; var1 = var1[0xE4C355E2]
       7 [-]: CALL R1 2 2  ; var1 = var1(var2)
       8 [-]: SETUPVAL R1 2; upvalues[1] = var2
       9 [-]: GETIMPORT R1 3; var1 = 0x89326C93
      10 [-]: NAMECALL R1 R1 K4; var2 = var1; var1 = var1[0x29EF273D]
      11 [-]: CALL R1 2 2  ; var1 = var1(var2)
      12 [-]: NAMECALL R1 R1 K5; var2 = var1; var1 = var1[0x66905CB0]
      13 [-]: CALL R1 2 2  ; var1 = var1(var2)
      14 [-]: SETUPVAL R1 3; upvalues[1] = var3
      15 [-]: GETUPVAL R2 5; var2 = upvalues[5]
      16 [-]: GETTABLEKS R1 R2 K6; var1 = var2[0xDE474187]
      17 [-]: CALL R1 1 2  ; var1 = var1()
      18 [-]: SETUPVAL R1 4; upvalues[1] = var4
      19 [-]: GETUPVAL R2 7; var2 = upvalues[7]
      20 [-]: GETTABLEKS R1 R2 K7; var1 = var2[0xC9013731]
      21 [-]: GETUPVAL R2 8; var2 = upvalues[8]
      22 [-]: GETUPVAL R3 0; var3 = upvalues[0]
      23 [-]: NEWTABLE R4 0 0; var4 = {}
      24 [-]: CALL R1 4 2  ; var1 = var1(var2, var3, var4)
      25 [-]: SETUPVAL R1 6; upvalues[1] = var6
      26 [-]: GETIMPORT R1 3; var1 = 0x89326C93
      27 [-]: NAMECALL R1 R1 K8; var2 = var1; var1 = var1[0xFB64E76C]
      28 [-]: CALL R1 2 2  ; var1 = var1(var2)
      29 [-]: SETUPVAL R1 9; upvalues[1] = var9
      30 [-]: GETIMPORT R1 3; var1 = 0x89326C93
      31 [-]: NAMECALL R1 R1 K9; var2 = var1; var1 = var1[0x78298275]
      32 [-]: CALL R1 2 2  ; var1 = var1(var2)
      33 [-]: SETUPVAL R1 10; upvalues[1] = var10
      34 [-]: GETUPVAL R2 11; var2 = upvalues[11]
      35 [-]: GETTABLEKS R1 R2 K10; var1 = var2[0xD2CED2F7]
      36 [-]: GETUPVAL R2 10; var2 = upvalues[10]
      37 [-]: LOADB R3 1   ; var3 = true
      38 [-]: LOADNIL R4   ; var4 = nil
      39 [-]: LOADB R5 1   ; var5 = true
      40 [-]: CALL R1 5 1  ; var1(var2, var3, var4, var5)
      41 [-]: GETIMPORT R1 3; var1 = 0x89326C93
      42 [-]: GETIMPORT R3 12; var3 = 0x0469F296
      43 [-]: LOADK R4 K13 ; var4 = "ApproachTrigger"
      44 [-]: CALL R3 2 0  ; var3, ... = var3(var4)
      45 [-]: NAMECALL R1 R1 K14; var2 = var1; var1 = var1[0xC7FCADA9]
      46 [-]: CALL R1 0 2  ; var1 = var1(var2, ...)
      47 [-]: GETIMPORT R2 16; var2 = 0xC8802016
      48 [-]: MOVE R3 R1   ; var3 = var1
      49 [-]: CALL R2 2 4  ; var2, var3, var4 = var2(var3)
      50 [-]: FORGPREP_INEXT R2 L1; 
L 0:  51 [-]: NAMECALL R7 R6 K17; var8 = var6; var7 = var6[0xF4E253B6]
      52 [-]: CALL R7 2 1  ; var7(var8)
L 1:  53 [-]: FORGLOOP R2 L0 2 [inext]; 
      54 [-]: GETIMPORT R2 19; var2 = _T
      55 [-]: GETUPVAL R3 12; var3 = upvalues[12]
      56 [-]: SETTABLEKS R3 R2 K20; var3["PreCheckpointRespawn"] = var2
      57 [-]: GETIMPORT R2 19; var2 = _T
      58 [-]: GETUPVAL R3 13; var3 = upvalues[13]
      59 [-]: SETTABLEKS R3 R2 K21; var3["PostCheckpointRespawn"] = var2
      60 [-]: GETIMPORT R2 3; var2 = 0x89326C93
      61 [-]: GETIMPORT R4 12; var4 = 0x0469F296
      62 [-]: LOADK R5 K22 ; var5 = "SetupWarframes"
      63 [-]: CALL R4 2 0  ; var4, ... = var4(var5)
      64 [-]: NAMECALL R2 R2 K23; var3 = var2; var2 = var2[0x46A0EBF5]
      65 [-]: CALL R2 0 2  ; var2 = var2(var3, ...)
      66 [-]: SETUPVAL R2 14; upvalues[2] = var14
      67 [-]: GETUPVAL R3 15; var3 = upvalues[15]
      68 [-]: GETTABLEKS R2 R3 K24; var2 = var3[0x59CAB14B]
      69 [-]: CALL R2 1 1  ; var2()
      70 [-]: GETUPVAL R2 10; var2 = upvalues[10]
      71 [-]: SETUPVAL R2 16; upvalues[2] = var16
      72 [-]: GETUPVAL R2 10; var2 = upvalues[10]
      73 [-]: NAMECALL R2 R2 K25; var3 = var2; var2 = var2[0xDE321E6F]
      74 [-]: CALL R2 2 2  ; var2 = var2(var3)
      75 [-]: LOADB R4 0   ; var4 = false
      76 [-]: NAMECALL R2 R2 K26; var3 = var2; var2 = var2[0xC7154A44]
      77 [-]: CALL R2 3 1  ; var2(var3, var4)
      78 [-]: GETIMPORT R2 3; var2 = 0x89326C93
      79 [-]: GETUPVAL R5 15; var5 = upvalues[15]
      80 [-]: GETTABLEKS R4 R5 K27; var4 = var5["CAVE_SPAWN_TAG"]
      81 [-]: NAMECALL R2 R2 K23; var3 = var2; var2 = var2[0x46A0EBF5]
      82 [-]: CALL R2 3 2  ; var2 = var2(var3, var4)
      83 [-]: SETUPVAL R2 17; upvalues[2] = var17
      84 [-]: GETUPVAL R2 10; var2 = upvalues[10]
      85 [-]: GETUPVAL R4 17; var4 = upvalues[17]
      86 [-]: NAMECALL R4 R4 K28; var5 = var4; var4 = var4[0xD1586535]
      87 [-]: CALL R4 2 2  ; var4 = var4(var5)
      88 [-]: GETUPVAL R5 17; var5 = upvalues[17]
      89 [-]: NAMECALL R5 R5 K29; var6 = var5; var5 = var5[0xCB3851B8]
      90 [-]: CALL R5 2 0  ; var5, ... = var5(var6)
      91 [-]: NAMECALL R2 R2 K30; var3 = var2; var2 = var2[0x589EF1C1]
      92 [-]: CALL R2 0 1  ; var2(var3, ...)
      93 [-]: GETIMPORT R2 19; var2 = _T
      94 [-]: GETUPVAL R3 18; var3 = upvalues[18]
      95 [-]: SETTABLEKS R3 R2 K31; var3["SelectWeapon"] = var2
      96 [-]: GETIMPORT R2 19; var2 = _T
      97 [-]: LOADB R3 1   ; var3 = true
      98 [-]: SETTABLEKS R3 R2 K32; var3["ArenaUseSequence"] = var2
      99 [-]: GETIMPORT R2 3; var2 = 0x89326C93
     100 [-]: GETIMPORT R4 12; var4 = 0x0469F296
     101 [-]: LOADK R5 K33 ; var5 = "StreamUndercroft"
     102 [-]: CALL R4 2 0  ; var4, ... = var4(var5)
     103 [-]: NAMECALL R2 R2 K23; var3 = var2; var2 = var2[0x46A0EBF5]
     104 [-]: CALL R2 0 2  ; var2 = var2(var3, ...)
     105 [-]: LOADK R5 K34 ; var5 = "Execute"
     106 [-]: NAMECALL R3 R2 K35; var4 = var2; var3 = var2[0x8EB2112D]
     107 [-]: CALL R3 3 1  ; var3(var4, var5)
     108 [-]: GETUPVAL R4 15; var4 = upvalues[15]
     109 [-]: GETTABLEKS R3 R4 K36; var3 = var4[0x3BD749F0]
     110 [-]: CALL R3 1 1  ; var3()
     111 [-]: GETUPVAL R4 15; var4 = upvalues[15]
     112 [-]: GETTABLEKS R3 R4 K37; var3 = var4[0xA21EF799]
     113 [-]: CALL R3 1 1  ; var3()
     114 [-]: GETUPVAL R3 19; var3 = upvalues[19]
     115 [-]: CALL R3 1 1  ; var3()
     116 [-]: GETIMPORT R3 19; var3 = _T
     117 [-]: NEWCLOSURE R4 P0; 
     118 [-]: CAPTURE UPVAL U20; 
     119 [-]: CAPTURE UPVAL U21; 
     120 [-]: SETTABLEKS R4 R3 K38; var4["SelectSuit"] = var3
     121 [-]: GETIMPORT R3 3; var3 = 0x89326C93
     122 [-]: NAMECALL R3 R3 K4; var4 = var3; var3 = var3[0x29EF273D]
     123 [-]: CALL R3 2 2  ; var3 = var3(var4)
     124 [-]: GETIMPORT R5 40; var5 = 0xB1044E5E
     125 [-]: NAMECALL R3 R3 K41; var4 = var3; var3 = var3[0x8955C0B5]
     126 [-]: CALL R3 3 1  ; var3(var4, var5)
     127 [-]: LOADB R3 0   ; var3 = false
     128 [-]: JUMPIFNOT R3 L2; goto L2 if not var3
     129 [-]: GETUPVAL R4 22; var4 = upvalues[22]
     130 [-]: GETTABLEKS R3 R4 K42; var3 = var4[0x01566DB3]
     131 [-]: GETUPVAL R4 23; var4 = upvalues[23]
     132 [-]: GETUPVAL R5 24; var5 = upvalues[24]
     133 [-]: CALL R3 3 1  ; var3(var4, var5)
     134 [-]: RETURN R0 0  ; 
L 2: 135 [-]: GETUPVAL R3 6; var3 = upvalues[6]
     136 [-]: GETUPVAL R6 23; var6 = upvalues[23]
     137 [-]: GETTABLEKS R5 R6 K43; var5 = var6["SELECT_WARFRAME"]
     138 [-]: NAMECALL R3 R3 K44; var4 = var3; var3 = var3[0x8ABFF40E]
     139 [-]: CALL R3 3 1  ; var3(var4, var5)
     140 [-]: RETURN R0 0  ; 


; Name:            
; Defined at line: 1413
; #Upvalues:       5
; #Parameters:     1
; Is_vararg:       0
; Max Stack Size:  4

       0 [-]: GETIMPORT R1 1; var1 = 0x3D106989
       1 [-]: LOADK R2 K2  ; var2 = "Encounter started"
       2 [-]: CALL R1 2 1  ; var1(var2)
       3 [-]: GETUPVAL R1 0; var1 = upvalues[0]
       4 [-]: MOVE R2 R0   ; var2 = var0
       5 [-]: CALL R1 2 1  ; var1(var2)
L 0:   6 [-]: GETUPVAL R2 1; var2 = upvalues[1]
       7 [-]: FASTCALL1 64 R2 L1; 
       8 [-]: GETIMPORT R1 4; var1 = 0x7B998233
       9 [-]: CALL R1 2 2  ; var1 = var1(var2)
L 1:  10 [-]: JUMPIF R1 L2 ; goto L2 if var1
      11 [-]: GETUPVAL R1 1; var1 = upvalues[1]
      12 [-]: NAMECALL R1 R1 K5; var2 = var1; var1 = var1[0xEFE6CAD1]
      13 [-]: CALL R1 2 2  ; var1 = var1(var2)
      14 [-]: LOADN R2 4   ; var2 = 4
      15 [-]: JUMPIFNOTLT R1 R2 L2; goto L2 if var1 >= var196924
      16 [-]: GETUPVAL R1 3; var1 = upvalues[3]
      17 [-]: GETUPVAL R3 2; var3 = upvalues[2]
      18 [-]: NAMECALL R1 R1 K6; var2 = var1; var1 = var1[0x209398C2]
      19 [-]: CALL R1 3 2  ; var1 = var1(var2, var3)
      20 [-]: SETUPVAL R1 2; upvalues[1] = var2
      21 [-]: GETUPVAL R1 4; var1 = upvalues[4]
      22 [-]: GETIMPORT R2 8; var2 = 0xFFF641AF
      23 [-]: CALL R2 1 0  ; var2, ... = var2()
      24 [-]: CALL R1 0 1  ; var1(var2, ...)
      25 [-]: GETIMPORT R1 10; var1 = 0xCBD666E1
      26 [-]: LOADN R2 0   ; var2 = 0
      27 [-]: CALL R1 2 1  ; var1(var2)
      28 [-]: JUMPBACK L0  ; goto L0
L 2:  29 [-]: RETURN R0 0  ; 


; Name:            
; Defined at line: 1423
; #Upvalues:       7
; #Parameters:     1
; Is_vararg:       0
; Max Stack Size:  11

       0 [-]: GETUPVAL R1 0; var1 = upvalues[0]
       1 [-]: GETUPVAL R3 1; var3 = upvalues[1]
       2 [-]: GETTABLEKS R2 R3 K0; var2 = var3["SELECT_WARFRAME"]
       3 [-]: JUMPIFNOTEQ R1 R2 L3; goto L3 if var1 ~= var334
       4 [-]: LOADNIL R1   ; var1 = nil
       5 [-]: NAMECALL R1 R1 K1; var2 = var1; var1 = var1[0xF4E253B6]
       6 [-]: CALL R1 2 1  ; var1(var2)
       7 [-]: LOADNIL R1   ; var1 = nil
       8 [-]: NAMECALL R1 R1 K1; var2 = var1; var1 = var1[0xF4E253B6]
       9 [-]: CALL R1 2 1  ; var1(var2)
      10 [-]: LOADNIL R1   ; var1 = nil
      11 [-]: NAMECALL R1 R1 K1; var2 = var1; var1 = var1[0xF4E253B6]
      12 [-]: CALL R1 2 1  ; var1(var2)
      13 [-]: JUMPXEQKNIL R0 L0 NOT; 
      14 [-]: GETUPVAL R1 2; var1 = upvalues[2]
      15 [-]: LOADN R2 3   ; var2 = 3
      16 [-]: GETIMPORT R5 4; var5 = _T["DuviriQuestWeapons"]
      17 [-]: LOADN R6 3   ; var6 = 3
      18 [-]: GETTABLE R4 R5 R6; var4 = var5[var6]
      19 [-]: GETTABLEN R3 R4 1; var3 = var4[1]
      20 [-]: SETTABLE R3 R1 R2; var3[var1] = var2
      21 [-]: GETIMPORT R1 6; var1 = 0x89326C93
      22 [-]: GETIMPORT R3 8; var3 = 0x0469F296
      23 [-]: LOADK R4 K9  ; var4 = "ChooseExcalCin"
      24 [-]: CALL R3 2 0  ; var3, ... = var3(var4)
      25 [-]: NAMECALL R1 R1 K10; var2 = var1; var1 = var1[0x46A0EBF5]
      26 [-]: CALL R1 0 2  ; var1 = var1(var2, ...)
      27 [-]: SETUPVAL R1 3; upvalues[1] = var3
      28 [-]: JUMP L2      ; goto L2
L 0:  29 [-]: JUMPXEQKNIL R0 L1 NOT; 
      30 [-]: GETUPVAL R1 2; var1 = upvalues[2]
      31 [-]: LOADN R2 3   ; var2 = 3
      32 [-]: GETIMPORT R5 4; var5 = _T["DuviriQuestWeapons"]
      33 [-]: LOADN R6 3   ; var6 = 3
      34 [-]: GETTABLE R4 R5 R6; var4 = var5[var6]
      35 [-]: GETTABLEN R3 R4 2; var3 = var4[2]
      36 [-]: SETTABLE R3 R1 R2; var3[var1] = var2
      37 [-]: GETIMPORT R1 6; var1 = 0x89326C93
      38 [-]: GETIMPORT R3 8; var3 = 0x0469F296
      39 [-]: LOADK R4 K11 ; var4 = "ChooseMagCin"
      40 [-]: CALL R3 2 0  ; var3, ... = var3(var4)
      41 [-]: NAMECALL R1 R1 K10; var2 = var1; var1 = var1[0x46A0EBF5]
      42 [-]: CALL R1 0 2  ; var1 = var1(var2, ...)
      43 [-]: SETUPVAL R1 3; upvalues[1] = var3
      44 [-]: JUMP L2      ; goto L2
L 1:  45 [-]: GETUPVAL R1 2; var1 = upvalues[2]
      46 [-]: LOADN R2 3   ; var2 = 3
      47 [-]: GETIMPORT R5 4; var5 = _T["DuviriQuestWeapons"]
      48 [-]: LOADN R6 3   ; var6 = 3
      49 [-]: GETTABLE R4 R5 R6; var4 = var5[var6]
      50 [-]: GETTABLEN R3 R4 3; var3 = var4[3]
      51 [-]: SETTABLE R3 R1 R2; var3[var1] = var2
      52 [-]: GETIMPORT R1 6; var1 = 0x89326C93
      53 [-]: GETIMPORT R3 8; var3 = 0x0469F296
      54 [-]: LOADK R4 K12 ; var4 = "ChooseVoltCin"
      55 [-]: CALL R3 2 0  ; var3, ... = var3(var4)
      56 [-]: NAMECALL R1 R1 K10; var2 = var1; var1 = var1[0x46A0EBF5]
      57 [-]: CALL R1 0 2  ; var1 = var1(var2, ...)
      58 [-]: SETUPVAL R1 3; upvalues[1] = var3
L 2:  59 [-]: GETUPVAL R2 4; var2 = upvalues[4]
      60 [-]: GETTABLEKS R1 R2 K13; var1 = var2[0x94B054B1]
      61 [-]: GETUPVAL R3 2; var3 = upvalues[2]
      62 [-]: LOADN R4 3   ; var4 = 3
      63 [-]: GETTABLE R2 R3 R4; var2 = var3[var4]
      64 [-]: LOADN R3 3   ; var3 = 3
      65 [-]: CALL R1 3 1  ; var1(var2, var3)
      66 [-]: GETUPVAL R1 5; var1 = upvalues[5]
      67 [-]: GETUPVAL R4 1; var4 = upvalues[1]
      68 [-]: GETTABLEKS R3 R4 K14; var3 = var4["WARFRAME_SELECTED"]
      69 [-]: NAMECALL R1 R1 K15; var2 = var1; var1 = var1[0x8ABFF40E]
      70 [-]: CALL R1 3 1  ; var1(var2, var3)
      71 [-]: RETURN R0 0  ; 
L 3:  72 [-]: NAMECALL R1 R0 K1; var2 = var0; var1 = var0[0xF4E253B6]
      73 [-]: CALL R1 2 1  ; var1(var2)
      74 [-]: GETIMPORT R1 6; var1 = 0x89326C93
      75 [-]: NAMECALL R1 R1 K16; var2 = var1; var1 = var1[0x78298275]
      76 [-]: CALL R1 2 2  ; var1 = var1(var2)
      77 [-]: NAMECALL R1 R1 K17; var2 = var1; var1 = var1[0xDE321E6F]
      78 [-]: CALL R1 2 2  ; var1 = var1(var2)
      79 [-]: NAMECALL R1 R1 K18; var2 = var1; var1 = var1[0xF7D48EE0]
      80 [-]: CALL R1 2 2  ; var1 = var1(var2)
      81 [-]: NAMECALL R2 R1 K19; var3 = var1; var2 = var1[0x4B305D6A]
      82 [-]: CALL R2 2 1  ; var2(var3)
      83 [-]: LOADN R2 0   ; var2 = 0
L 4:  84 [-]: NAMECALL R3 R1 K20; var4 = var1; var3 = var1[0x74055260]
      85 [-]: CALL R3 2 2  ; var3 = var3(var4)
      86 [-]: JUMPIFNOT R3 L7; goto L7 if not var3
      87 [-]: GETIMPORT R3 22; var3 = 0xCBD666E1
      88 [-]: LOADN R4 0   ; var4 = 0
      89 [-]: CALL R3 2 1  ; var3(var4)
      90 [-]: FASTCALL1 64 R1 L5; 
      91 [-]: MOVE R4 R1   ; var4 = var1
      92 [-]: GETIMPORT R3 24; var3 = 0x7B998233
      93 [-]: CALL R3 2 2  ; var3 = var3(var4)
L 5:  94 [-]: JUMPIFNOT R3 L6; goto L6 if not var3
      95 [-]: RETURN R0 0  ; 
L 6:  96 [-]: GETIMPORT R3 26; var3 = 0xFFF641AF
      97 [-]: CALL R3 1 2  ; var3 = var3()
      98 [-]: ADD R2 R2 R3 ; var2 = var2 + var3
      99 [-]: LOADN R3 5   ; var3 = 5
     100 [-]: JUMPIFLT R3 R2 L7; goto L7 if var3 < var-1507258
     101 [-]: JUMPBACK L4  ; goto L4
L 7: 102 [-]: GETIMPORT R3 28; var3 = 0xC8802016
     103 [-]: GETIMPORT R4 30; var4 = 0xB6509A7F
     104 [-]: CALL R3 2 4  ; var3, var4, var5 = var3(var4)
     105 [-]: FORGPREP_INEXT R3 L9; 
L 8: 106 [-]: GETIMPORT R10 32; var10 = gContextActionType
     107 [-]: NAMECALL R8 R7 K33; var9 = var7; var8 = var7[0xC9F6A7D7]
     108 [-]: CALL R8 3 2  ; var8 = var8(var9, var10)
     109 [-]: JUMPIFNOTEQ R8 R0 L9; goto L9 if var8 ~= var2295841
     110 [-]: GETIMPORT R8 35; var8 = _T["SelectWeapon"]
     111 [-]: GETIMPORT R9 37; var9 = 0x37847D3A
     112 [-]: MOVE R10 R6  ; var10 = var6
     113 [-]: CALL R8 3 1  ; var8(var9, var10)
L 9: 114 [-]: FORGLOOP R3 L8 2 [inext]; 
     115 [-]: GETIMPORT R3 22; var3 = 0xCBD666E1
     116 [-]: LOADN R4 0   ; var4 = 0
     117 [-]: CALL R3 2 1  ; var3(var4)
     118 [-]: GETUPVAL R3 6; var3 = upvalues[6]
     119 [-]: CALL R3 1 1  ; var3()
     120 [-]: NAMECALL R3 R0 K38; var4 = var0; var3 = var0[0x383D2E7D]
     121 [-]: CALL R3 2 1  ; var3(var4)
     122 [-]: RETURN R0 0  ; 


; Name:            
; Defined at line: 1472
; #Upvalues:       0
; #Parameters:     1
; Is_vararg:       0
; Max Stack Size:  7

       0 [-]: GETIMPORT R1 1; var1 = 0x89326C93
       1 [-]: GETIMPORT R3 3; var3 = 0x0469F296
       2 [-]: LOADK R4 K4  ; var4 = "WeaponDeco"
       3 [-]: CALL R3 2 2  ; var3 = var3(var4)
       4 [-]: NAMECALL R4 R0 K5; var5 = var0; var4 = var0[0xD1586535]
       5 [-]: CALL R4 2 0  ; var4, ... = var4(var5)
       6 [-]: NAMECALL R1 R1 K6; var2 = var1; var1 = var1[0xC7B81E8D]
       7 [-]: CALL R1 0 2  ; var1 = var1(var2, ...)
       8 [-]: GETIMPORT R2 1; var2 = 0x89326C93
       9 [-]: GETIMPORT R4 8; var4 = 0xD11C33D0
      10 [-]: NAMECALL R5 R1 K5; var6 = var1; var5 = var1[0xD1586535]
      11 [-]: CALL R5 2 2  ; var5 = var5(var6)
      12 [-]: GETIMPORT R6 10; var6 = ZERO_ROTATION
      13 [-]: NAMECALL R2 R2 K11; var3 = var2; var2 = var2[0x05909209]
      14 [-]: CALL R2 5 1  ; var2(var3, var4, var5, var6)
      15 [-]: RETURN R0 0  ; 



