; This file has been disassembled using luadec 2.0.2 by sztupy (modified by Reversive)

; Name:            
; Defined at line: 0
; #Upvalues:       0
; #Parameters:     0
; Is_vararg:       2
; Max Stack Size:  81

  1 [-]: GETGLOBAL R0 K0        ; R0 := 0x2d0fad09
  2 [-]: LOADK     R1 K1        ; R1 := "EE.Interface.Utilities"
  3 [-]: CALL      R0 2 2       ; R0 := R0(R1)
  4 [-]: GETGLOBAL R1 K0        ; R1 := 0x2d0fad09
  5 [-]: LOADK     R2 K2        ; R2 := "Lotus.Interface.LotusUtilities"
  6 [-]: CALL      R1 2 2       ; R1 := R1(R2)
  7 [-]: GETGLOBAL R2 K0        ; R2 := 0x2d0fad09
  8 [-]: LOADK     R3 K3        ; R3 := "Lotus.Interface.SequencerUtilities"
  9 [-]: CALL      R2 2 2       ; R2 := R2(R3)
 10 [-]: GETGLOBAL R3 K0        ; R3 := 0x2d0fad09
 11 [-]: LOADK     R4 K4        ; R4 := "Lotus.Interface.Libs.JukeBoxMgr"
 12 [-]: CALL      R3 2 2       ; R3 := R3(R4)
 13 [-]: GETGLOBAL R4 K0        ; R4 := 0x2d0fad09
 14 [-]: LOADK     R5 K5        ; R5 := "Lotus.Interface.Components.ThemedCustomizationButton"
 15 [-]: CALL      R4 2 2       ; R4 := R4(R5)
 16 [-]: GETGLOBAL R5 K6        ; R5 := 0x0469f296
 17 [-]: LOADK     R6 K7        ; R6 := "HiddenShipDeco"
 18 [-]: CALL      R5 2 2       ; R5 := R5(R6)
 19 [-]: LOADNIL   R6 R7        ; R6 := R7 := nil
 20 [-]: LOADBOOL  R8 0 0       ; R8 := false
 21 [-]: LOADNIL   R9 R11       ; R9 := R10 := R11 := nil
 22 [-]: LOADK     R12 16       ; R12 := 16.000000
 23 [-]: MUL       R13 R12 K8   ; R13 := R12 * 4.000000
 24 [-]: LOADNIL   R14 R17      ; R14 := R15 := R16 := R17 := nil
 25 [-]: LOADK     R18 0        ; R18 := 0.000000
 26 [-]: LOADBOOL  R19 0 0      ; R19 := false
 27 [-]: NEWTABLE  R20 0 0      ; R20 := {}
 28 [-]: LOADK     R21 1        ; R21 := 1.000000
 29 [-]: LOADNIL   R22 R22      ; R22 := nil
 30 [-]: NEWTABLE  R23 0 0      ; R23 := {}
 31 [-]: LOADNIL   R24 R24      ; R24 := nil
 32 [-]: LOADK     R25 K10      ; R25 := ""
 33 [-]: NEWTABLE  R26 0 0      ; R26 := {}
 34 [-]: LOADNIL   R27 R34      ; R27 := R28 := R29 := R30 := R31 := R32 := R33 := R34 := nil
 35 [-]: LOADBOOL  R35 0 0      ; R35 := false
 36 [-]: LOADBOOL  R36 0 0      ; R36 := false
 37 [-]: LOADBOOL  R37 0 0      ; R37 := false
 38 [-]: LOADBOOL  R38 0 0      ; R38 := false
 39 [-]: LOADBOOL  R39 0 0      ; R39 := false
 40 [-]: CLOSURE   R40 0        ; R40 := closure(Function #1)
 41 [-]: MOVE      R0 R22       ; R0 := R22
 42 [-]: MOVE      R0 R27       ; R0 := R27
 43 [-]: MOVE      R0 R4        ; R0 := R4
 44 [-]: MOVE      R0 R28       ; R0 := R28
 45 [-]: MOVE      R0 R29       ; R0 := R29
 46 [-]: MOVE      R0 R30       ; R0 := R30
 47 [-]: CLOSURE   R41 1        ; R41 := closure(Function #2)
 48 [-]: MOVE      R0 R27       ; R0 := R27
 49 [-]: MOVE      R0 R4        ; R0 := R4
 50 [-]: MOVE      R0 R22       ; R0 := R22
 51 [-]: MOVE      R0 R0        ; R0 := R0
 52 [-]: MOVE      R0 R20       ; R0 := R20
 53 [-]: CLOSURE   R42 2        ; R42 := closure(Function #3)
 54 [-]: MOVE      R0 R16       ; R0 := R16
 55 [-]: MOVE      R0 R22       ; R0 := R22
 56 [-]: MOVE      R0 R12       ; R0 := R12
 57 [-]: MOVE      R0 R13       ; R0 := R13
 58 [-]: CLOSURE   R43 3        ; R43 := closure(Function #4)
 59 [-]: MOVE      R0 R22       ; R0 := R22
 60 [-]: CLOSURE   R44 4        ; R44 := closure(Function #5)
 61 [-]: MOVE      R0 R43       ; R0 := R43
 62 [-]: CLOSURE   R45 5        ; R45 := closure(Function #6)
 63 [-]: MOVE      R0 R43       ; R0 := R43
 64 [-]: CLOSURE   R46 6        ; R46 := closure(Function #7)
 65 [-]: MOVE      R0 R43       ; R0 := R43
 66 [-]: CLOSURE   R47 7        ; R47 := closure(Function #8)
 67 [-]: MOVE      R0 R16       ; R0 := R16
 68 [-]: MOVE      R0 R27       ; R0 := R27
 69 [-]: MOVE      R0 R34       ; R0 := R34
 70 [-]: CLOSURE   R31 8        ; R31 := closure(Function #9)
 71 [-]: MOVE      R0 R22       ; R0 := R22
 72 [-]: MOVE      R0 R20       ; R0 := R20
 73 [-]: MOVE      R0 R47       ; R0 := R47
 74 [-]: CLOSURE   R48 9        ; R48 := closure(Function #10)
 75 [-]: MOVE      R0 R31       ; R0 := R31
 76 [-]: CLOSURE   R49 10       ; R49 := closure(Function #11)
 77 [-]: MOVE      R0 R31       ; R0 := R31
 78 [-]: CLOSURE   R50 11       ; R50 := closure(Function #12)
 79 [-]: MOVE      R0 R31       ; R0 := R31
 80 [-]: CLOSURE   R51 12       ; R51 := closure(Function #13)
 81 [-]: MOVE      R0 R6        ; R0 := R6
 82 [-]: MOVE      R0 R2        ; R0 := R2
 83 [-]: MOVE      R0 R16       ; R0 := R16
 84 [-]: CLOSURE   R52 13       ; R52 := closure(Function #14)
 85 [-]: MOVE      R0 R2        ; R0 := R2
 86 [-]: MOVE      R0 R6        ; R0 := R6
 87 [-]: MOVE      R0 R22       ; R0 := R22
 88 [-]: MOVE      R0 R47       ; R0 := R47
 89 [-]: MOVE      R0 R24       ; R0 := R24
 90 [-]: MOVE      R0 R41       ; R0 := R41
 91 [-]: MOVE      R0 R16       ; R0 := R16
 92 [-]: MOVE      R0 R11       ; R0 := R11
 93 [-]: MOVE      R0 R42       ; R0 := R42
 94 [-]: MOVE      R0 R40       ; R0 := R40
 95 [-]: CLOSURE   R53 14       ; R53 := closure(Function #15)
 96 [-]: MOVE      R0 R16       ; R0 := R16
 97 [-]: MOVE      R0 R47       ; R0 := R47
 98 [-]: MOVE      R0 R15       ; R0 := R15
 99 [-]: MOVE      R0 R22       ; R0 := R22
100 [-]: MOVE      R0 R24       ; R0 := R24
101 [-]: MOVE      R0 R23       ; R0 := R23
102 [-]: CLOSURE   R54 15       ; R54 := closure(Function #16)
103 [-]: MOVE      R0 R3        ; R0 := R3
104 [-]: SETGLOBAL R54 K11      ; OnStepSequencerUpdated := R54
105 [-]: LOADNIL   R54 R54      ; R54 := nil
106 [-]: CLOSURE   R55 16       ; R55 := closure(Function #17)
107 [-]: MOVE      R0 R54       ; R0 := R54
108 [-]: MOVE      R0 R0        ; R0 := R0
109 [-]: MOVE      R0 R7        ; R0 := R7
110 [-]: CLOSURE   R56 17       ; R56 := closure(Function #18)
111 [-]: MOVE      R0 R55       ; R0 := R55
112 [-]: MOVE      R0 R16       ; R0 := R16
113 [-]: MOVE      R0 R54       ; R0 := R54
114 [-]: SETGLOBAL R56 K12      ; SaveSongNamed := R56
115 [-]: CLOSURE   R56 18       ; R56 := closure(Function #19)
116 [-]: MOVE      R0 R55       ; R0 := R55
117 [-]: MOVE      R0 R16       ; R0 := R16
118 [-]: MOVE      R0 R54       ; R0 := R54
119 [-]: SETGLOBAL R56 K13      ; OSKSaveSongNamed := R56
120 [-]: CLOSURE   R56 19       ; R56 := closure(Function #20)
121 [-]: MOVE      R0 R53       ; R0 := R53
122 [-]: MOVE      R0 R22       ; R0 := R22
123 [-]: MOVE      R0 R1        ; R0 := R1
124 [-]: MOVE      R0 R54       ; R0 := R54
125 [-]: MOVE      R0 R16       ; R0 := R16
126 [-]: MOVE      R0 R7        ; R0 := R7
127 [-]: CLOSURE   R57 20       ; R57 := closure(Function #21)
128 [-]: MOVE      R0 R56       ; R0 := R56
129 [-]: MOVE      R0 R54       ; R0 := R54
130 [-]: SETGLOBAL R57 K14      ; SaveSong := R57
131 [-]: CLOSURE   R57 21       ; R57 := closure(Function #22)
132 [-]: MOVE      R0 R16       ; R0 := R16
133 [-]: MOVE      R0 R9        ; R0 := R9
134 [-]: MOVE      R0 R22       ; R0 := R22
135 [-]: MOVE      R0 R6        ; R0 := R6
136 [-]: MOVE      R0 R54       ; R0 := R54
137 [-]: MOVE      R0 R2        ; R0 := R2
138 [-]: MOVE      R0 R7        ; R0 := R7
139 [-]: MOVE      R0 R51       ; R0 := R51
140 [-]: MOVE      R0 R15       ; R0 := R15
141 [-]: MOVE      R0 R23       ; R0 := R23
142 [-]: MOVE      R0 R0        ; R0 := R0
143 [-]: CLOSURE   R58 22       ; R58 := closure(Function #23)
144 [-]: MOVE      R0 R15       ; R0 := R15
145 [-]: MOVE      R0 R23       ; R0 := R23
146 [-]: MOVE      R0 R22       ; R0 := R22
147 [-]: MOVE      R0 R24       ; R0 := R24
148 [-]: MOVE      R0 R11       ; R0 := R11
149 [-]: MOVE      R0 R41       ; R0 := R41
150 [-]: MOVE      R0 R40       ; R0 := R40
151 [-]: MOVE      R0 R42       ; R0 := R42
152 [-]: MOVE      R0 R16       ; R0 := R16
153 [-]: MOVE      R0 R47       ; R0 := R47
154 [-]: CLOSURE   R59 23       ; R59 := closure(Function #24)
155 [-]: MOVE      R0 R58       ; R0 := R58
156 [-]: SETGLOBAL R59 K15      ; ConfirmReload := R59
157 [-]: CLOSURE   R34 24       ; R34 := closure(Function #25)
158 [-]: MOVE      R0 R16       ; R0 := R16
159 [-]: MOVE      R0 R0        ; R0 := R0
160 [-]: CLOSURE   R59 25       ; R59 := closure(Function #26)
161 [-]: MOVE      R0 R51       ; R0 := R51
162 [-]: MOVE      R0 R22       ; R0 := R22
163 [-]: MOVE      R0 R7        ; R0 := R7
164 [-]: MOVE      R0 R0        ; R0 := R0
165 [-]: MOVE      R0 R11       ; R0 := R11
166 [-]: MOVE      R0 R41       ; R0 := R41
167 [-]: MOVE      R0 R40       ; R0 := R40
168 [-]: MOVE      R0 R42       ; R0 := R42
169 [-]: MOVE      R0 R16       ; R0 := R16
170 [-]: MOVE      R0 R47       ; R0 := R47
171 [-]: CLOSURE   R60 26       ; R60 := closure(Function #27)
172 [-]: MOVE      R0 R16       ; R0 := R16
173 [-]: MOVE      R0 R9        ; R0 := R9
174 [-]: MOVE      R0 R22       ; R0 := R22
175 [-]: MOVE      R0 R6        ; R0 := R6
176 [-]: MOVE      R0 R59       ; R0 := R59
177 [-]: MOVE      R0 R7        ; R0 := R7
178 [-]: MOVE      R0 R2        ; R0 := R2
179 [-]: MOVE      R0 R51       ; R0 := R51
180 [-]: CLOSURE   R61 27       ; R61 := closure(Function #28)
181 [-]: MOVE      R0 R36       ; R0 := R36
182 [-]: MOVE      R0 R15       ; R0 := R15
183 [-]: MOVE      R0 R38       ; R0 := R38
184 [-]: MOVE      R0 R21       ; R0 := R21
185 [-]: MOVE      R0 R11       ; R0 := R11
186 [-]: MOVE      R0 R22       ; R0 := R22
187 [-]: CLOSURE   R62 28       ; R62 := closure(Function #29)
188 [-]: MOVE      R0 R16       ; R0 := R16
189 [-]: MOVE      R0 R61       ; R0 := R61
190 [-]: MOVE      R0 R8        ; R0 := R8
191 [-]: CLOSURE   R63 29       ; R63 := closure(Function #30)
192 [-]: MOVE      R0 R53       ; R0 := R53
193 [-]: MOVE      R0 R62       ; R0 := R62
194 [-]: SETGLOBAL R63 K16      ; ConfirmClose := R63
195 [-]: CLOSURE   R63 30       ; R63 := closure(Function #31)
196 [-]: MOVE      R0 R16       ; R0 := R16
197 [-]: MOVE      R0 R22       ; R0 := R22
198 [-]: MOVE      R0 R23       ; R0 := R23
199 [-]: CLOSURE   R64 31       ; R64 := closure(Function #32)
200 [-]: CLOSURE   R65 32       ; R65 := closure(Function #33)
201 [-]: MOVE      R0 R16       ; R0 := R16
202 [-]: MOVE      R0 R27       ; R0 := R27
203 [-]: MOVE      R0 R64       ; R0 := R64
204 [-]: MOVE      R0 R25       ; R0 := R25
205 [-]: MOVE      R0 R0        ; R0 := R0
206 [-]: MOVE      R0 R62       ; R0 := R62
207 [-]: CLOSURE   R66 33       ; R66 := closure(Function #34)
208 [-]: MOVE      R0 R65       ; R0 := R65
209 [-]: SETGLOBAL R66 K17      ; Close := R66
210 [-]: CLOSURE   R66 34       ; R66 := closure(Function #35)
211 [-]: CLOSURE   R67 35       ; R67 := closure(Function #36)
212 [-]: MOVE      R0 R42       ; R0 := R42
213 [-]: CLOSURE   R68 36       ; R68 := closure(Function #37)
214 [-]: MOVE      R0 R4        ; R0 := R4
215 [-]: MOVE      R0 R30       ; R0 := R30
216 [-]: MOVE      R0 R29       ; R0 := R29
217 [-]: MOVE      R0 R28       ; R0 := R28
218 [-]: MOVE      R0 R48       ; R0 := R48
219 [-]: MOVE      R0 R49       ; R0 := R49
220 [-]: MOVE      R0 R50       ; R0 := R50
221 [-]: MOVE      R0 R44       ; R0 := R44
222 [-]: MOVE      R0 R45       ; R0 := R45
223 [-]: MOVE      R0 R46       ; R0 := R46
224 [-]: MOVE      R0 R66       ; R0 := R66
225 [-]: MOVE      R0 R67       ; R0 := R67
226 [-]: MOVE      R0 R11       ; R0 := R11
227 [-]: MOVE      R0 R57       ; R0 := R57
228 [-]: MOVE      R0 R34       ; R0 := R34
229 [-]: MOVE      R0 R60       ; R0 := R60
230 [-]: MOVE      R0 R27       ; R0 := R27
231 [-]: MOVE      R0 R26       ; R0 := R26
232 [-]: CLOSURE   R69 37       ; R69 := closure(Function #38)
233 [-]: MOVE      R0 R27       ; R0 := R27
234 [-]: MOVE      R0 R26       ; R0 := R26
235 [-]: MOVE      R0 R0        ; R0 := R0
236 [-]: MOVE      R0 R68       ; R0 := R68
237 [-]: MOVE      R0 R40       ; R0 := R40
238 [-]: MOVE      R0 R41       ; R0 := R41
239 [-]: CLOSURE   R70 38       ; R70 := closure(Function #39)
240 [-]: MOVE      R0 R11       ; R0 := R11
241 [-]: CLOSURE   R71 39       ; R71 := closure(Function #40)
242 [-]: MOVE      R0 R9        ; R0 := R9
243 [-]: MOVE      R0 R22       ; R0 := R22
244 [-]: MOVE      R0 R51       ; R0 := R51
245 [-]: MOVE      R0 R16       ; R0 := R16
246 [-]: MOVE      R0 R7        ; R0 := R7
247 [-]: CLOSURE   R28 40       ; R28 := closure(Function #41)
248 [-]: MOVE      R0 R71       ; R0 := R71
249 [-]: CLOSURE   R29 41       ; R29 := closure(Function #42)
250 [-]: MOVE      R0 R71       ; R0 := R71
251 [-]: CLOSURE   R30 42       ; R30 := closure(Function #43)
252 [-]: MOVE      R0 R71       ; R0 := R71
253 [-]: CLOSURE   R72 43       ; R72 := closure(Function #44)
254 [-]: MOVE      R0 R22       ; R0 := R22
255 [-]: MOVE      R0 R16       ; R0 := R16
256 [-]: MOVE      R0 R33       ; R0 := R33
257 [-]: CLOSURE   R73 44       ; R73 := closure(Function #45)
258 [-]: MOVE      R0 R72       ; R0 := R72
259 [-]: SETGLOBAL R73 K18      ; TogglePause := R73
260 [-]: CLOSURE   R73 45       ; R73 := closure(Function #46)
261 [-]: MOVE      R0 R11       ; R0 := R11
262 [-]: CLOSURE   R74 46       ; R74 := closure(Function #47)
263 [-]: MOVE      R0 R73       ; R0 := R73
264 [-]: SETGLOBAL R74 K19      ; ConfirmClearNotes := R74
265 [-]: CLOSURE   R32 47       ; R32 := closure(Function #48)
266 [-]: MOVE      R0 R73       ; R0 := R73
267 [-]: MOVE      R0 R16       ; R0 := R16
268 [-]: MOVE      R0 R0        ; R0 := R0
269 [-]: CLOSURE   R74 48       ; R74 := closure(Function #49)
270 [-]: MOVE      R0 R32       ; R0 := R32
271 [-]: SETGLOBAL R74 K20      ; ClearNotes := R74
272 [-]: CLOSURE   R33 49       ; R33 := closure(Function #50)
273 [-]: MOVE      R0 R0        ; R0 := R0
274 [-]: MOVE      R0 R16       ; R0 := R16
275 [-]: MOVE      R0 R25       ; R0 := R25
276 [-]: MOVE      R0 R19       ; R0 := R19
277 [-]: CLOSURE   R74 50       ; R74 := closure(Function #51)
278 [-]: MOVE      R0 R20       ; R0 := R20
279 [-]: CLOSURE   R75 51       ; R75 := closure(Function #52)
280 [-]: MOVE      R0 R10       ; R0 := R10
281 [-]: CLOSURE   R76 52       ; R76 := closure(Function #53)
282 [-]: MOVE      R0 R26       ; R0 := R26
283 [-]: MOVE      R0 R0        ; R0 := R0
284 [-]: MOVE      R0 R11       ; R0 := R11
285 [-]: CLOSURE   R77 53       ; R77 := closure(Function #54)
286 [-]: MOVE      R0 R25       ; R0 := R25
287 [-]: MOVE      R0 R26       ; R0 := R26
288 [-]: MOVE      R0 R16       ; R0 := R16
289 [-]: CLOSURE   R78 54       ; R78 := closure(Function #55)
290 [-]: MOVE      R0 R37       ; R0 := R37
291 [-]: MOVE      R0 R15       ; R0 := R15
292 [-]: MOVE      R0 R1        ; R0 := R1
293 [-]: MOVE      R0 R14       ; R0 := R14
294 [-]: MOVE      R0 R7        ; R0 := R7
295 [-]: MOVE      R0 R39       ; R0 := R39
296 [-]: MOVE      R0 R3        ; R0 := R3
297 [-]: MOVE      R0 R23       ; R0 := R23
298 [-]: MOVE      R0 R0        ; R0 := R0
299 [-]: MOVE      R0 R22       ; R0 := R22
300 [-]: MOVE      R0 R8        ; R0 := R8
301 [-]: MOVE      R0 R24       ; R0 := R24
302 [-]: MOVE      R0 R63       ; R0 := R63
303 [-]: MOVE      R0 R33       ; R0 := R33
304 [-]: MOVE      R0 R21       ; R0 := R21
305 [-]: MOVE      R0 R75       ; R0 := R75
306 [-]: MOVE      R0 R74       ; R0 := R74
307 [-]: MOVE      R0 R69       ; R0 := R69
308 [-]: MOVE      R0 R70       ; R0 := R70
309 [-]: MOVE      R0 R76       ; R0 := R76
310 [-]: MOVE      R0 R42       ; R0 := R42
311 [-]: MOVE      R0 R16       ; R0 := R16
312 [-]: SETGLOBAL R78 K21      ; Initialize := R78
313 [-]: CLOSURE   R78 55       ; R78 := closure(Function #56)
314 [-]: MOVE      R0 R10       ; R0 := R10
315 [-]: MOVE      R0 R15       ; R0 := R15
316 [-]: MOVE      R0 R61       ; R0 := R61
317 [-]: MOVE      R0 R5        ; R0 := R5
318 [-]: MOVE      R0 R39       ; R0 := R39
319 [-]: MOVE      R0 R3        ; R0 := R3
320 [-]: SETGLOBAL R78 K22      ; Shutdown := R78
321 [-]: CLOSURE   R78 56       ; R78 := closure(Function #57)
322 [-]: MOVE      R0 R15       ; R0 := R15
323 [-]: MOVE      R0 R65       ; R0 := R65
324 [-]: CLOSURE   R79 57       ; R79 := closure(Function #58)
325 [-]: MOVE      R0 R27       ; R0 := R27
326 [-]: MOVE      R0 R8        ; R0 := R8
327 [-]: MOVE      R0 R0        ; R0 := R0
328 [-]: MOVE      R0 R35       ; R0 := R35
329 [-]: MOVE      R0 R7        ; R0 := R7
330 [-]: MOVE      R0 R22       ; R0 := R22
331 [-]: MOVE      R0 R51       ; R0 := R51
332 [-]: MOVE      R0 R77       ; R0 := R77
333 [-]: MOVE      R0 R52       ; R0 := R52
334 [-]: MOVE      R0 R14       ; R0 := R14
335 [-]: MOVE      R0 R1        ; R0 := R1
336 [-]: MOVE      R0 R78       ; R0 := R78
337 [-]: SETGLOBAL R79 K23      ; Update := R79
338 [-]: CLOSURE   R79 58       ; R79 := closure(Function #59)
339 [-]: SETGLOBAL R79 K24      ; SupportsThemes := R79
340 [-]: CLOSURE   R79 59       ; R79 := closure(Function #60)
341 [-]: MOVE      R0 R16       ; R0 := R16
342 [-]: SETGLOBAL R79 K25      ; IsInputBlocked := R79
343 [-]: CLOSURE   R79 60       ; R79 := closure(Function #61)
344 [-]: MOVE      R0 R76       ; R0 := R76
345 [-]: MOVE      R0 R27       ; R0 := R27
346 [-]: SETGLOBAL R79 K26      ; onViewportSizeChanged := R79
347 [-]: CLOSURE   R79 61       ; R79 := closure(Function #62)
348 [-]: MOVE      R0 R15       ; R0 := R15
349 [-]: SETGLOBAL R79 K27      ; ScrubRollOver := R79
350 [-]: CLOSURE   R79 62       ; R79 := closure(Function #63)
351 [-]: MOVE      R0 R22       ; R0 := R22
352 [-]: MOVE      R0 R27       ; R0 := R27
353 [-]: MOVE      R0 R43       ; R0 := R43
354 [-]: CLOSURE   R80 63       ; R80 := closure(Function #64)
355 [-]: MOVE      R0 R79       ; R0 := R79
356 [-]: SETGLOBAL R80 K28      ; Mute0 := R80
357 [-]: CLOSURE   R80 64       ; R80 := closure(Function #65)
358 [-]: MOVE      R0 R79       ; R0 := R79
359 [-]: SETGLOBAL R80 K29      ; Mute1 := R80
360 [-]: CLOSURE   R80 65       ; R80 := closure(Function #66)
361 [-]: MOVE      R0 R79       ; R0 := R79
362 [-]: SETGLOBAL R80 K30      ; Mute2 := R80
363 [-]: CLOSURE   R80 66       ; R80 := closure(Function #67)
364 [-]: MOVE      R0 R57       ; R0 := R57
365 [-]: SETGLOBAL R80 K31      ; Save := R80
366 [-]: CLOSURE   R80 67       ; R80 := closure(Function #68)
367 [-]: MOVE      R0 R34       ; R0 := R34
368 [-]: SETGLOBAL R80 K32      ; Reload := R80
369 [-]: CLOSURE   R80 68       ; R80 := closure(Function #69)
370 [-]: MOVE      R0 R60       ; R0 := R60
371 [-]: SETGLOBAL R80 K33      ; Default := R80
372 [-]: CLOSURE   R80 69       ; R80 := closure(Function #70)
373 [-]: MOVE      R0 R25       ; R0 := R25
374 [-]: MOVE      R0 R22       ; R0 := R22
375 [-]: MOVE      R0 R73       ; R0 := R73
376 [-]: MOVE      R0 R42       ; R0 := R42
377 [-]: MOVE      R0 R17       ; R0 := R17
378 [-]: MOVE      R0 R18       ; R0 := R18
379 [-]: MOVE      R0 R33       ; R0 := R33
380 [-]: SETGLOBAL R80 K34      ; PuzzleMode := R80
381 [-]: CLOSURE   R80 70       ; R80 := closure(Function #71)
382 [-]: MOVE      R0 R19       ; R0 := R19
383 [-]: MOVE      R0 R33       ; R0 := R33
384 [-]: SETGLOBAL R80 K35      ; PuzzleShowHide := R80
385 [-]: CLOSURE   R80 71       ; R80 := closure(Function #72)
386 [-]: MOVE      R0 R22       ; R0 := R22
387 [-]: SETGLOBAL R80 K36      ; PuzzleSync := R80
388 [-]: CLOSURE   R80 72       ; R80 := closure(Function #73)
389 [-]: MOVE      R0 R16       ; R0 := R16
390 [-]: MOVE      R0 R65       ; R0 := R65
391 [-]: SETGLOBAL R80 K37      ; onKeyDown_HIDE_PAUSE_MENU := R80
392 [-]: CLOSURE   R80 73       ; R80 := closure(Function #74)
393 [-]: MOVE      R0 R26       ; R0 := R26
394 [-]: MOVE      R0 R27       ; R0 := R27
395 [-]: MOVE      R0 R25       ; R0 := R25
396 [-]: SETGLOBAL R80 K38      ; onKeyDown_MENU_MOUSE_Z := R80
397 [-]: CLOSURE   R80 74       ; R80 := closure(Function #75)
398 [-]: MOVE      R0 R37       ; R0 := R37
399 [-]: MOVE      R0 R25       ; R0 := R25
400 [-]: MOVE      R0 R1        ; R0 := R1
401 [-]: MOVE      R0 R72       ; R0 := R72
402 [-]: SETGLOBAL R80 K39      ; onRawInputEvent := R80
403 [-]: RETURN    R0 1         ; return 


; Function #1:
;
; Name:            
; Defined at line: 69
; #Upvalues:       6
; #Parameters:     0
; Is_vararg:       0
; Max Stack Size:  15

  1 [-]: GETGLOBAL R0 K0        ; R0 := 0x7b998233
  2 [-]: GETUPVAL  R1 U0        ; R1 := U0
  3 [-]: CALL      R0 2 2       ; R0 := R0(R1)
  4 [-]: TEST      R0 0         ; if not R0 then PC := 7
  5 [-]: JMP       7            ; PC := 7
  6 [-]: RETURN    R0 1         ; return 
  7 [-]: GETUPVAL  R0 U0        ; R0 := U0
  8 [-]: SELF      R0 R0 K1     ; R1 := R0; R0 := R0[0x4d7a0caf]
  9 [-]: LOADK     R2 0         ; R2 := 0.000000
 10 [-]: CALL      R0 3 2       ; R0 := R0(R1,R2)
 11 [-]: LOADK     R1 K3        ; R1 := ""
 12 [-]: GETUPVAL  R2 U0        ; R2 := U0
 13 [-]: SELF      R2 R2 K1     ; R3 := R2; R2 := R2[0x4d7a0caf]
 14 [-]: LOADK     R4 1         ; R4 := 1.000000
 15 [-]: CALL      R2 3 2       ; R2 := R2(R3,R4)
 16 [-]: LOADK     R3 K3        ; R3 := ""
 17 [-]: GETUPVAL  R4 U0        ; R4 := U0
 18 [-]: SELF      R4 R4 K1     ; R5 := R4; R4 := R4[0x4d7a0caf]
 19 [-]: LOADK     R6 2         ; R6 := 2.000000
 20 [-]: CALL      R4 3 2       ; R4 := R4(R5,R6)
 21 [-]: LOADK     R5 K3        ; R5 := ""
 22 [-]: GETGLOBAL R6 K0        ; R6 := 0x7b998233
 23 [-]: MOVE      R7 R0        ; R7 := R0
 24 [-]: CALL      R6 2 2       ; R6 := R6(R7)
 25 [-]: TEST      R6 1         ; if R6 then PC := 43
 26 [-]: JMP       43           ; PC := 43
 27 [-]: GETGLOBAL R6 K4        ; R6 := 0xae91e43b
 28 [-]: SELF      R6 R6 K5     ; R7 := R6; R6 := R6[0x42b04007]
 29 [-]: LOADK     R8 K6        ; R8 := "/Lotus/Language/Menu/Composition_MelodyPack"
 30 [-]: LOADBOOL  R9 0 0       ; R9 := false
 31 [-]: NEWTABLE  R10 0 1      ; R10 := {}
 32 [-]: GETGLOBAL R11 K4       ; R11 := 0xae91e43b
 33 [-]: SELF      R11 R11 K5   ; R12 := R11; R11 := R11[0x42b04007]
 34 [-]: SELF      R13 R0 K8    ; R14 := R0; R13 := R0[0xd3a9d01f]
 35 [-]: CALL      R13 2 2      ; R13 := R13(R14)
 36 [-]: SELF      R13 R13 K9   ; R14 := R13; R13 := R13[0x6d604ba7]
 37 [-]: CALL      R13 2 2      ; R13 := R13(R14)
 38 [-]: LOADBOOL  R14 0 0      ; R14 := false
 39 [-]: CALL      R11 4 2      ; R11 := R11(R12,R13,R14)
 40 [-]: SETTABLE  R10 K7 R11   ; R10["NAME"] := R11
 41 [-]: CALL      R6 5 2       ; R6 := R6(R7,R8,R9,R10)
 42 [-]: MOVE      R1 R6        ; R1 := R6
 43 [-]: GETGLOBAL R6 K0        ; R6 := 0x7b998233
 44 [-]: MOVE      R7 R2        ; R7 := R2
 45 [-]: CALL      R6 2 2       ; R6 := R6(R7)
 46 [-]: TEST      R6 1         ; if R6 then PC := 64
 47 [-]: JMP       64           ; PC := 64
 48 [-]: GETGLOBAL R6 K4        ; R6 := 0xae91e43b
 49 [-]: SELF      R6 R6 K5     ; R7 := R6; R6 := R6[0x42b04007]
 50 [-]: LOADK     R8 K10       ; R8 := "/Lotus/Language/Menu/Composition_BassPack"
 51 [-]: LOADBOOL  R9 0 0       ; R9 := false
 52 [-]: NEWTABLE  R10 0 1      ; R10 := {}
 53 [-]: GETGLOBAL R11 K4       ; R11 := 0xae91e43b
 54 [-]: SELF      R11 R11 K5   ; R12 := R11; R11 := R11[0x42b04007]
 55 [-]: SELF      R13 R2 K8    ; R14 := R2; R13 := R2[0xd3a9d01f]
 56 [-]: CALL      R13 2 2      ; R13 := R13(R14)
 57 [-]: SELF      R13 R13 K9   ; R14 := R13; R13 := R13[0x6d604ba7]
 58 [-]: CALL      R13 2 2      ; R13 := R13(R14)
 59 [-]: LOADBOOL  R14 0 0      ; R14 := false
 60 [-]: CALL      R11 4 2      ; R11 := R11(R12,R13,R14)
 61 [-]: SETTABLE  R10 K7 R11   ; R10["NAME"] := R11
 62 [-]: CALL      R6 5 2       ; R6 := R6(R7,R8,R9,R10)
 63 [-]: MOVE      R3 R6        ; R3 := R6
 64 [-]: GETGLOBAL R6 K0        ; R6 := 0x7b998233
 65 [-]: MOVE      R7 R4        ; R7 := R4
 66 [-]: CALL      R6 2 2       ; R6 := R6(R7)
 67 [-]: TEST      R6 1         ; if R6 then PC := 85
 68 [-]: JMP       85           ; PC := 85
 69 [-]: GETGLOBAL R6 K4        ; R6 := 0xae91e43b
 70 [-]: SELF      R6 R6 K5     ; R7 := R6; R6 := R6[0x42b04007]
 71 [-]: LOADK     R8 K11       ; R8 := "/Lotus/Language/Menu/Composition_PercussionPack"
 72 [-]: LOADBOOL  R9 0 0       ; R9 := false
 73 [-]: NEWTABLE  R10 0 1      ; R10 := {}
 74 [-]: GETGLOBAL R11 K4       ; R11 := 0xae91e43b
 75 [-]: SELF      R11 R11 K5   ; R12 := R11; R11 := R11[0x42b04007]
 76 [-]: SELF      R13 R4 K8    ; R14 := R4; R13 := R4[0xd3a9d01f]
 77 [-]: CALL      R13 2 2      ; R13 := R13(R14)
 78 [-]: SELF      R13 R13 K9   ; R14 := R13; R13 := R13[0x6d604ba7]
 79 [-]: CALL      R13 2 2      ; R13 := R13(R14)
 80 [-]: LOADBOOL  R14 0 0      ; R14 := false
 81 [-]: CALL      R11 4 2      ; R11 := R11(R12,R13,R14)
 82 [-]: SETTABLE  R10 K7 R11   ; R10["NAME"] := R11
 83 [-]: CALL      R6 5 2       ; R6 := R6(R7,R8,R9,R10)
 84 [-]: MOVE      R5 R6        ; R5 := R6
 85 [-]: GETGLOBAL R6 K4        ; R6 := 0xae91e43b
 86 [-]: SELF      R6 R6 K5     ; R7 := R6; R6 := R6[0x42b04007]
 87 [-]: LOADK     R8 K12       ; R8 := "<MELODY>"
 88 [-]: LOADBOOL  R9 1 0       ; R9 := true
 89 [-]: CALL      R6 4 2       ; R6 := R6(R7,R8,R9)
 90 [-]: MOVE      R7 R1        ; R7 := R1
 91 [-]: CONCAT    R1 R6 R7     ; R1 := R6 .. R7
 92 [-]: GETGLOBAL R6 K4        ; R6 := 0xae91e43b
 93 [-]: SELF      R6 R6 K5     ; R7 := R6; R6 := R6[0x42b04007]
 94 [-]: LOADK     R8 K13       ; R8 := "<BASS>"
 95 [-]: LOADBOOL  R9 1 0       ; R9 := true
 96 [-]: CALL      R6 4 2       ; R6 := R6(R7,R8,R9)
 97 [-]: MOVE      R7 R3        ; R7 := R3
 98 [-]: CONCAT    R3 R6 R7     ; R3 := R6 .. R7
 99 [-]: GETGLOBAL R6 K4        ; R6 := 0xae91e43b
100 [-]: SELF      R6 R6 K5     ; R7 := R6; R6 := R6[0x42b04007]
101 [-]: LOADK     R8 K14       ; R8 := "<PERCUSSION>"
102 [-]: LOADBOOL  R9 1 0       ; R9 := true
103 [-]: CALL      R6 4 2       ; R6 := R6(R7,R8,R9)
104 [-]: MOVE      R7 R5        ; R7 := R5
105 [-]: CONCAT    R5 R6 R7     ; R5 := R6 .. R7
106 [-]: GETGLOBAL R6 K0        ; R6 := 0x7b998233
107 [-]: GETUPVAL  R7 U1        ; R7 := U1
108 [-]: CALL      R6 2 2       ; R6 := R6(R7)
109 [-]: TEST      R6 1         ; if R6 then PC := 124
110 [-]: JMP       124          ; PC := 124
111 [-]: GETUPVAL  R6 U1        ; R6 := U1
112 [-]: GETTABLE  R6 R6 K15    ; R6 := R6["CustomizationList"]
113 [-]: SELF      R6 R6 K16    ; R7 := R6; R6 := R6[0xea061e98]
114 [-]: CLOSURE   R8 0         ; R8 := closure(Function #1.1)
115 [-]: GETUPVAL  R0 U2        ; R0 := U2
116 [-]: GETUPVAL  R0 U3        ; R0 := U3
117 [-]: MOVE      R0 R1        ; R0 := R1
118 [-]: GETUPVAL  R0 U1        ; R0 := U1
119 [-]: GETUPVAL  R0 U4        ; R0 := U4
120 [-]: MOVE      R0 R3        ; R0 := R3
121 [-]: GETUPVAL  R0 U5        ; R0 := U5
122 [-]: MOVE      R0 R5        ; R0 := R5
123 [-]: CALL      R6 3 1       ; R6(R7,R8)
124 [-]: RETURN    R0 1         ; return 


; Function #1.1:
;
; Name:            
; Defined at line: 99
; #Upvalues:       8
; #Parameters:     1
; Is_vararg:       0
; Max Stack Size:  3

  1 [-]: GETTABLE  R1 R0 K0     ; R1 := R0["Type"]
  2 [-]: GETUPVAL  R2 U0        ; R2 := U0
  3 [-]: GETTABLE  R2 R2 K1     ; R2 := R2["Types"]
  4 [-]: GETTABLE  R2 R2 K2     ; R2 := R2["BUTTON"]
  5 [-]: EQ        0 R1 R2      ; if R1 ~= R2 then PC := 47
  6 [-]: JMP       47           ; PC := 47
  7 [-]: GETGLOBAL R1 K3        ; R1 := 0x7b998233
  8 [-]: GETTABLE  R2 R0 K4     ; R2 := R0["CallBack"]
  9 [-]: CALL      R1 2 2       ; R1 := R1(R2)
 10 [-]: TEST      R1 1         ; if R1 then PC := 47
 11 [-]: JMP       47           ; PC := 47
 12 [-]: GETTABLE  R1 R0 K4     ; R1 := R0["CallBack"]
 13 [-]: GETUPVAL  R2 U1        ; R2 := U1
 14 [-]: EQ        0 R1 R2      ; if R1 ~= R2 then PC := 24
 15 [-]: JMP       24           ; PC := 24
 16 [-]: GETUPVAL  R1 U2        ; R1 := U2
 17 [-]: SETTABLE  R0 K5 R1     ; R0["NameTag"] := R1
 18 [-]: GETUPVAL  R1 U3        ; R1 := U3
 19 [-]: GETTABLE  R1 R1 K6     ; R1 := R1["CustomizationList"]
 20 [-]: GETTABLE  R1 R1 K7     ; R82 := R1[0xb15e6aca]
 21 [-]: MOVE      R2 R0        ; R2 := R0
 22 [-]: CALL      R1 2 1       ; R1(R2)
 23 [-]: JMP       47           ; PC := 47
 24 [-]: GETTABLE  R1 R0 K4     ; R1 := R0["CallBack"]
 25 [-]: GETUPVAL  R2 U4        ; R2 := U4
 26 [-]: EQ        0 R1 R2      ; if R1 ~= R2 then PC := 36
 27 [-]: JMP       36           ; PC := 36
 28 [-]: GETUPVAL  R1 U5        ; R1 := U5
 29 [-]: SETTABLE  R0 K5 R1     ; R0["NameTag"] := R1
 30 [-]: GETUPVAL  R1 U3        ; R1 := U3
 31 [-]: GETTABLE  R1 R1 K6     ; R1 := R1["CustomizationList"]
 32 [-]: GETTABLE  R1 R1 K7     ; R82 := R1[0xb15e6aca]
 33 [-]: MOVE      R2 R0        ; R2 := R0
 34 [-]: CALL      R1 2 1       ; R1(R2)
 35 [-]: JMP       47           ; PC := 47
 36 [-]: GETTABLE  R1 R0 K4     ; R1 := R0["CallBack"]
 37 [-]: GETUPVAL  R2 U6        ; R2 := U6
 38 [-]: EQ        0 R1 R2      ; if R1 ~= R2 then PC := 47
 39 [-]: JMP       47           ; PC := 47
 40 [-]: GETUPVAL  R1 U7        ; R1 := U7
 41 [-]: SETTABLE  R0 K5 R1     ; R0["NameTag"] := R1
 42 [-]: GETUPVAL  R1 U3        ; R1 := U3
 43 [-]: GETTABLE  R1 R1 K6     ; R1 := R1["CustomizationList"]
 44 [-]: GETTABLE  R1 R1 K7     ; R82 := R1[0xb15e6aca]
 45 [-]: MOVE      R2 R0        ; R2 := R0
 46 [-]: CALL      R1 2 1       ; R1(R2)
 47 [-]: RETURN    R0 1         ; return 


; Function #2:
;
; Name:            
; Defined at line: 116
; #Upvalues:       5
; #Parameters:     0
; Is_vararg:       0
; Max Stack Size:  3

  1 [-]: GETGLOBAL R0 K0        ; R0 := 0x7b998233
  2 [-]: GETUPVAL  R1 U0        ; R1 := U0
  3 [-]: CALL      R0 2 2       ; R0 := R0(R1)
  4 [-]: TEST      R0 1         ; if R0 then PC := 16
  5 [-]: JMP       16           ; PC := 16
  6 [-]: GETUPVAL  R0 U0        ; R0 := U0
  7 [-]: GETTABLE  R0 R0 K1     ; R0 := R0["CustomizationList"]
  8 [-]: SELF      R0 R0 K2     ; R1 := R0; R0 := R0[0xea061e98]
  9 [-]: CLOSURE   R2 0         ; R2 := closure(Function #2.1)
 10 [-]: GETUPVAL  R0 U1        ; R0 := U1
 11 [-]: GETUPVAL  R0 U2        ; R0 := U2
 12 [-]: GETUPVAL  R0 U3        ; R0 := U3
 13 [-]: GETUPVAL  R0 U4        ; R0 := U4
 14 [-]: GETUPVAL  R0 U0        ; R0 := U0
 15 [-]: CALL      R0 3 1       ; R0(R1,R2)
 16 [-]: RETURN    R0 1         ; return 


; Function #2.1:
;
; Name:            
; Defined at line: 119
; #Upvalues:       5
; #Parameters:     1
; Is_vararg:       0
; Max Stack Size:  9

  1 [-]: GETTABLE  R1 R0 K0     ; R1 := R0["Type"]
  2 [-]: GETUPVAL  R2 U0        ; R2 := U0
  3 [-]: GETTABLE  R2 R2 K1     ; R2 := R2["Types"]
  4 [-]: GETTABLE  R2 R2 K2     ; R2 := R2["VALUE_SELECTOR"]
  5 [-]: EQ        0 R1 R2      ; if R1 ~= R2 then PC := 46
  6 [-]: JMP       46           ; PC := 46
  7 [-]: GETGLOBAL R1 K3        ; R1 := 0x7b998233
  8 [-]: GETTABLE  R2 R0 K4     ; R2 := R0["mValueChangedCallback"]
  9 [-]: CALL      R1 2 2       ; R1 := R1(R2)
 10 [-]: TEST      R1 1         ; if R1 then PC := 46
 11 [-]: JMP       46           ; PC := 46
 12 [-]: GETGLOBAL R1 K3        ; R1 := 0x7b998233
 13 [-]: GETTABLE  R2 R0 K5     ; R2 := R0["NoteType"]
 14 [-]: CALL      R1 2 2       ; R1 := R1(R2)
 15 [-]: TEST      R1 1         ; if R1 then PC := 46
 16 [-]: JMP       46           ; PC := 46
 17 [-]: GETGLOBAL R1 K6        ; R1 := 0xe10c64de
 18 [-]: GETUPVAL  R2 U1        ; R2 := U1
 19 [-]: SELF      R2 R2 K7     ; R3 := R2; R2 := R2[0xfeab5fb6]
 20 [-]: GETTABLE  R4 R0 K5     ; R4 := R0["NoteType"]
 21 [-]: CALL      R2 3 0       ; R2,... := R2(R3,R4)
 22 [-]: CALL      R1 0 2       ; R1 := R1(R2,...)
 23 [-]: GETTABLE  R2 R0 K8     ; R2 := R0["mButton"]
 24 [-]: GETTABLE  R2 R2 K9     ; R2 := R2["mSlider"]
 25 [-]: GETUPVAL  R3 U2        ; R3 := U2
 26 [-]: GETTABLE  R3 R3 K11    ; R82 := R3[0x74a11ec6]
 27 [-]: GETUPVAL  R4 U3        ; R4 := U3
 28 [-]: GETTABLE  R5 R0 K5     ; R5 := R0["NoteType"]
 29 [-]: GETTABLE  R4 R4 R5     ; R4 := R4[R5]
 30 [-]: SELF      R4 R4 K12    ; R5 := R4; R4 := R4[0x3b93153d]
 31 [-]: GETUPVAL  R6 U3        ; R6 := U3
 32 [-]: GETTABLE  R7 R0 K5     ; R7 := R0["NoteType"]
 33 [-]: GETTABLE  R6 R6 R7     ; R6 := R6[R7]
 34 [-]: SELF      R6 R6 K13    ; R7 := R6; R6 := R6[0x42dcc9f5]
 35 [-]: MOVE      R8 R1        ; R8 := R1
 36 [-]: CALL      R6 3 0       ; R6,... := R6(R7,R8)
 37 [-]: CALL      R4 0 2       ; R4 := R4(R5,...)
 38 [-]: MUL       R4 R4 K14    ; R4 := R4 * 100.000000
 39 [-]: CALL      R3 2 2       ; R3 := R3(R4)
 40 [-]: SETTABLE  R2 K10 R3    ; R2["mLabel"] := R3
 41 [-]: GETUPVAL  R2 U4        ; R2 := U4
 42 [-]: GETTABLE  R2 R2 K15    ; R2 := R2["CustomizationList"]
 43 [-]: GETTABLE  R2 R2 K16    ; R82 := R2[0xb15e6aca]
 44 [-]: MOVE      R3 R0        ; R3 := R0
 45 [-]: CALL      R2 2 1       ; R2(R3)
 46 [-]: RETURN    R0 1         ; return 


; Function #3:
;
; Name:            
; Defined at line: 129
; #Upvalues:       4
; #Parameters:     1
; Is_vararg:       0
; Max Stack Size:  5

  1 [-]: GETUPVAL  R1 U0        ; R1 := U0
  2 [-]: SETTABLE  R1 K0 R0     ; R1["looping"] := R0
  3 [-]: GETGLOBAL R1 K1        ; R1 := 0x7b998233
  4 [-]: GETUPVAL  R2 U1        ; R2 := U1
  5 [-]: CALL      R1 2 2       ; R1 := R1(R2)
  6 [-]: TEST      R1 1         ; if R1 then PC := 24
  7 [-]: JMP       24           ; PC := 24
  8 [-]: EQ        1 R0 K2      ; if R0 == nil then PC := 19
  9 [-]: JMP       19           ; PC := 19
 10 [-]: GETUPVAL  R1 U1        ; R1 := U1
 11 [-]: SELF      R1 R1 K3     ; R2 := R1; R1 := R1[0x34dd4a58]
 12 [-]: SUB       R3 R0 K4     ; R3 := R0 - 1.000000
 13 [-]: GETUPVAL  R4 U2        ; R4 := U2
 14 [-]: MUL       R3 R3 R4     ; R3 := R3 * R4
 15 [-]: GETUPVAL  R4 U2        ; R4 := U2
 16 [-]: MUL       R4 R0 R4     ; R4 := R0 * R4
 17 [-]: CALL      R1 4 1       ; R1(R2,R3,R4)
 18 [-]: JMP       24           ; PC := 24
 19 [-]: GETUPVAL  R1 U1        ; R1 := U1
 20 [-]: SELF      R1 R1 K3     ; R2 := R1; R1 := R1[0x34dd4a58]
 21 [-]: LOADK     R3 0         ; R3 := 0.000000
 22 [-]: GETUPVAL  R4 U3        ; R4 := U3
 23 [-]: CALL      R1 4 1       ; R1(R2,R3,R4)
 24 [-]: RETURN    R0 1         ; return 


; Function #4:
;
; Name:            
; Defined at line: 143
; #Upvalues:       1
; #Parameters:     2
; Is_vararg:       0
; Max Stack Size:  6

  1 [-]: GETGLOBAL R2 K0        ; R2 := 0x7b998233
  2 [-]: GETUPVAL  R3 U0        ; R3 := U0
  3 [-]: CALL      R2 2 2       ; R2 := R2(R3)
  4 [-]: TEST      R2 0         ; if not R2 then PC := 7
  5 [-]: JMP       7            ; PC := 7
  6 [-]: RETURN    R0 1         ; return 
  7 [-]: GETUPVAL  R2 U0        ; R2 := U0
  8 [-]: SELF      R2 R2 K1     ; R3 := R2; R2 := R2[0x3ee1feb7]
  9 [-]: MOVE      R4 R0        ; R4 := R0
 10 [-]: MOVE      R5 R1        ; R5 := R1
 11 [-]: CALL      R2 4 1       ; R2(R3,R4,R5)
 12 [-]: RETURN    R0 1         ; return 


; Function #5:
;
; Name:            
; Defined at line: 151
; #Upvalues:       1
; #Parameters:     1
; Is_vararg:       0
; Max Stack Size:  4

  1 [-]: GETUPVAL  R1 U0        ; R1 := U0
  2 [-]: LOADK     R2 2         ; R2 := 2.000000
  3 [-]: GETTABLE  R3 R0 K1     ; R3 := R0["mChecked"]
  4 [-]: NOT       R3 R3        ; R3 := not R3
  5 [-]: CALL      R1 3 1       ; R1(R2,R3)
  6 [-]: RETURN    R0 1         ; return 


; Function #6:
;
; Name:            
; Defined at line: 155
; #Upvalues:       1
; #Parameters:     1
; Is_vararg:       0
; Max Stack Size:  4

  1 [-]: GETUPVAL  R1 U0        ; R1 := U0
  2 [-]: LOADK     R2 1         ; R2 := 1.000000
  3 [-]: GETTABLE  R3 R0 K1     ; R3 := R0["mChecked"]
  4 [-]: NOT       R3 R3        ; R3 := not R3
  5 [-]: CALL      R1 3 1       ; R1(R2,R3)
  6 [-]: RETURN    R0 1         ; return 


; Function #7:
;
; Name:            
; Defined at line: 159
; #Upvalues:       1
; #Parameters:     1
; Is_vararg:       0
; Max Stack Size:  4

  1 [-]: GETUPVAL  R1 U0        ; R1 := U0
  2 [-]: LOADK     R2 0         ; R2 := 0.000000
  3 [-]: GETTABLE  R3 R0 K1     ; R3 := R0["mChecked"]
  4 [-]: NOT       R3 R3        ; R3 := not R3
  5 [-]: CALL      R1 3 1       ; R1(R2,R3)
  6 [-]: RETURN    R0 1         ; return 


; Function #8:
;
; Name:            
; Defined at line: 163
; #Upvalues:       3
; #Parameters:     1
; Is_vararg:       0
; Max Stack Size:  4

  1 [-]: GETUPVAL  R1 U0        ; R1 := U0
  2 [-]: GETTABLE  R1 R1 K0     ; R1 := R1["dirty"]
  3 [-]: EQ        1 R1 R0      ; if R1 == R0 then PC := 7
  4 [-]: JMP       7            ; PC := 7
  5 [-]: GETUPVAL  R1 U0        ; R1 := U0
  6 [-]: SETTABLE  R1 K0 R0     ; R1["dirty"] := R0
  7 [-]: GETUPVAL  R1 U1        ; R1 := U1
  8 [-]: GETTABLE  R1 R1 K1     ; R1 := R1["CustomizationList"]
  9 [-]: SELF      R1 R1 K2     ; R2 := R1; R1 := R1[0xea061e98]
 10 [-]: CLOSURE   R3 0         ; R3 := closure(Function #8.1)
 11 [-]: GETUPVAL  R0 U2        ; R0 := U2
 12 [-]: GETUPVAL  R0 U0        ; R0 := U0
 13 [-]: GETUPVAL  R0 U1        ; R0 := U1
 14 [-]: CALL      R1 3 1       ; R1(R2,R3)
 15 [-]: RETURN    R0 1         ; return 


; Function #8.1:
;
; Name:            
; Defined at line: 168
; #Upvalues:       3
; #Parameters:     1
; Is_vararg:       0
; Max Stack Size:  3

  1 [-]: GETTABLE  R1 R0 K0     ; R1 := R0["CallBack"]
  2 [-]: EQ        1 R1 K1      ; if R1 == nil then PC := 16
  3 [-]: JMP       16           ; PC := 16
  4 [-]: GETTABLE  R1 R0 K0     ; R1 := R0["CallBack"]
  5 [-]: GETUPVAL  R2 U0        ; R2 := U0
  6 [-]: EQ        0 R1 R2      ; if R1 ~= R2 then PC := 16
  7 [-]: JMP       16           ; PC := 16
  8 [-]: GETUPVAL  R1 U1        ; R1 := U1
  9 [-]: GETTABLE  R1 R1 K3     ; R1 := R1["dirty"]
 10 [-]: SETTABLE  R0 K2 R1     ; R0["Enabled"] := R1
 11 [-]: GETUPVAL  R1 U2        ; R1 := U2
 12 [-]: GETTABLE  R1 R1 K4     ; R1 := R1["CustomizationList"]
 13 [-]: GETTABLE  R1 R1 K5     ; R82 := R1[0xb15e6aca]
 14 [-]: MOVE      R2 R0        ; R2 := R0
 15 [-]: CALL      R1 2 1       ; R1(R2)
 16 [-]: RETURN    R0 1         ; return 


; Function #9:
;
; Name:            
; Defined at line: 176
; #Upvalues:       3
; #Parameters:     2
; Is_vararg:       0
; Max Stack Size:  7

  1 [-]: GETGLOBAL R2 K0        ; R2 := 0x7b998233
  2 [-]: GETUPVAL  R3 U0        ; R3 := U0
  3 [-]: CALL      R2 2 2       ; R2 := R2(R3)
  4 [-]: TEST      R2 1         ; if R2 then PC := 28
  5 [-]: JMP       28           ; PC := 28
  6 [-]: GETGLOBAL R2 K1        ; R2 := 0x58b0509e
  7 [-]: GETUPVAL  R3 U1        ; R3 := U1
  8 [-]: GETTABLE  R3 R3 R1     ; R3 := R3[R1]
  9 [-]: SELF      R3 R3 K2     ; R4 := R3; R3 := R3[0x70596bfe]
 10 [-]: GETTABLE  R5 R0 K3     ; R5 := R0["mLabel"]
 11 [-]: DIV       R5 R5 K4     ; R5 := R5 / 100.000000
 12 [-]: CALL      R3 3 0       ; R3,... := R3(R4,R5)
 13 [-]: CALL      R2 0 2       ; R2 := R2(R3,...)
 14 [-]: GETUPVAL  R3 U0        ; R3 := U0
 15 [-]: SELF      R3 R3 K5     ; R4 := R3; R3 := R3[0xfeab5fb6]
 16 [-]: MOVE      R5 R1        ; R5 := R1
 17 [-]: CALL      R3 3 2       ; R3 := R3(R4,R5)
 18 [-]: EQ        1 R3 R2      ; if R3 == R2 then PC := 28
 19 [-]: JMP       28           ; PC := 28
 20 [-]: GETUPVAL  R3 U0        ; R3 := U0
 21 [-]: SELF      R3 R3 K6     ; R4 := R3; R3 := R3[0xe7883e4a]
 22 [-]: MOVE      R5 R1        ; R5 := R1
 23 [-]: MOVE      R6 R2        ; R6 := R2
 24 [-]: CALL      R3 4 1       ; R3(R4,R5,R6)
 25 [-]: GETUPVAL  R3 U2        ; R3 := U2
 26 [-]: LOADBOOL  R4 1 0       ; R4 := true
 27 [-]: CALL      R3 2 1       ; R3(R4)
 28 [-]: RETURN    R0 1         ; return 


; Function #10:
;
; Name:            
; Defined at line: 186
; #Upvalues:       1
; #Parameters:     1
; Is_vararg:       0
; Max Stack Size:  4

  1 [-]: GETUPVAL  R1 U0        ; R1 := U0
  2 [-]: MOVE      R2 R0        ; R2 := R0
  3 [-]: LOADK     R3 2         ; R3 := 2.000000
  4 [-]: CALL      R1 3 1       ; R1(R2,R3)
  5 [-]: RETURN    R0 1         ; return 


; Function #11:
;
; Name:            
; Defined at line: 190
; #Upvalues:       1
; #Parameters:     1
; Is_vararg:       0
; Max Stack Size:  4

  1 [-]: GETUPVAL  R1 U0        ; R1 := U0
  2 [-]: MOVE      R2 R0        ; R2 := R0
  3 [-]: LOADK     R3 1         ; R3 := 1.000000
  4 [-]: CALL      R1 3 1       ; R1(R2,R3)
  5 [-]: RETURN    R0 1         ; return 


; Function #12:
;
; Name:            
; Defined at line: 194
; #Upvalues:       1
; #Parameters:     1
; Is_vararg:       0
; Max Stack Size:  4

  1 [-]: GETUPVAL  R1 U0        ; R1 := U0
  2 [-]: MOVE      R2 R0        ; R2 := R0
  3 [-]: LOADK     R3 0         ; R3 := 0.000000
  4 [-]: CALL      R1 3 1       ; R1(R2,R3)
  5 [-]: RETURN    R0 1         ; return 


; Function #13:
;
; Name:            
; Defined at line: 198
; #Upvalues:       3
; #Parameters:     3
; Is_vararg:       0
; Max Stack Size:  11

  1 [-]: GETUPVAL  R3 U0        ; R3 := U0
  2 [-]: EQ        0 R3 K0      ; if R3 ~= nil then PC := 8
  3 [-]: JMP       8            ; PC := 8
  4 [-]: GETUPVAL  R3 U1        ; R3 := U1
  5 [-]: GETTABLE  R3 R3 K1     ; R82 := R3[0x21ea49b2]
  6 [-]: CALL      R3 1 2       ; R3 := R3()
  7 [-]: SETUPVAL  R3 U0        ; U82 := 
  8 [-]: GETUPVAL  R3 U0        ; R3 := U0
  9 [-]: SETTABLE  R3 K2 R0     ; R3["StepSequencer"] := R0
 10 [-]: GETUPVAL  R3 U0        ; R3 := U0
 11 [-]: NEWTABLE  R4 0 0       ; R4 := {}
 12 [-]: SETTABLE  R3 K3 R4     ; R3["OldNotePackInfo"] := R4
 13 [-]: GETGLOBAL R3 K4        ; R3 := 0x7b998233
 14 [-]: MOVE      R4 R0        ; R4 := R0
 15 [-]: CALL      R3 2 2       ; R3 := R3(R4)
 16 [-]: TEST      R3 1         ; if R3 then PC := 29
 17 [-]: JMP       29           ; PC := 29
 18 [-]: LOADK     R3 0         ; R3 := 0.000000
 19 [-]: LOADK     R4 2         ; R4 := 2.000000
 20 [-]: LOADK     R5 1         ; R5 := 1.000000
 21 [-]: FORPREP   R3 28        ; R3 -= R5; PC := 28
 22 [-]: GETUPVAL  R7 U0        ; R7 := U0
 23 [-]: GETTABLE  R7 R7 K3     ; R7 := R7["OldNotePackInfo"]
 24 [-]: SELF      R8 R0 K6     ; R9 := R0; R8 := R0[0x4d7a0caf]
 25 [-]: MOVE      R10 R6       ; R10 := R6
 26 [-]: CALL      R8 3 2       ; R8 := R8(R9,R10)
 27 [-]: SETTABLE  R7 R6 R8     ; R7[R6] := R8
 28 [-]: FORLOOP   R3 22        ; R3 += R5; if R3 <= R4 then begin PC := 22; R6 := R3 end
 29 [-]: GETUPVAL  R7 U1        ; R7 := U1
 30 [-]: GETTABLE  R7 R7 K7     ; R82 := R7[0xfd3b438e]
 31 [-]: GETUPVAL  R8 U0        ; R8 := U0
 32 [-]: MOVE      R9 R1        ; R9 := R1
 33 [-]: MOVE      R10 R2       ; R10 := R2
 34 [-]: CALL      R7 4 1       ; R7(R8,R9,R10)
 35 [-]: GETUPVAL  R7 U2        ; R7 := U2
 36 [-]: SETTABLE  R7 K8 K9     ; R7["inputBlocked"] := true
 37 [-]: RETURN    R0 1         ; return 


; Function #14:
;
; Name:            
; Defined at line: 222
; #Upvalues:       10
; #Parameters:     0
; Is_vararg:       0
; Max Stack Size:  18

  1 [-]: GETUPVAL  R0 U0        ; R0 := U0
  2 [-]: GETTABLE  R0 R0 K0     ; R82 := R0[0x2fb43a9e]
  3 [-]: GETUPVAL  R1 U1        ; R1 := U1
  4 [-]: CALL      R0 2 2       ; R0 := R0(R1)
  5 [-]: EQ        0 R0 K1      ; if R0 ~= true then PC := 130
  6 [-]: JMP       130          ; PC := 130
  7 [-]: GETUPVAL  R0 U1        ; R0 := U1
  8 [-]: GETTABLE  R0 R0 K2     ; R0 := R0["StepSequencer"]
  9 [-]: GETUPVAL  R1 U2        ; R1 := U2
 10 [-]: EQ        0 R0 R1      ; if R0 ~= R1 then PC := 119
 11 [-]: JMP       119          ; PC := 119
 12 [-]: GETGLOBAL R1 K3        ; R1 := 0xc8802016
 13 [-]: GETUPVAL  R2 U1        ; R2 := U1
 14 [-]: GETTABLE  R2 R2 K4     ; R2 := R2["NotePackRes"]
 15 [-]: CALL      R1 2 4       ; R1,R2,R3 := R1(R2)
 16 [-]: JMP       77           ; PC := 77
 17 [-]: GETTABLE  R6 R5 K5     ; R6 := R5["NoteType"]
 18 [-]: GETTABLE  R7 R5 K6     ; R7 := R5["NotePack"]
 19 [-]: GETGLOBAL R8 K7        ; R8 := 0x7b998233
 20 [-]: MOVE      R9 R7        ; R9 := R7
 21 [-]: CALL      R8 2 2       ; R8 := R8(R9)
 22 [-]: TEST      R8 1         ; if R8 then PC := 77
 23 [-]: JMP       77           ; PC := 77
 24 [-]: GETUPVAL  R8 U1        ; R8 := U1
 25 [-]: GETTABLE  R8 R8 K8     ; R8 := R8["OldNotePackInfo"]
 26 [-]: GETTABLE  R8 R8 R6     ; R8 := R8[R6]
 27 [-]: EQ        1 R7 R8      ; if R7 == R8 then PC := 77
 28 [-]: JMP       77           ; PC := 77
 29 [-]: GETUPVAL  R9 U3        ; R9 := U3
 30 [-]: LOADBOOL  R10 1 0      ; R10 := true
 31 [-]: CALL      R9 2 1       ; R9(R10)
 32 [-]: EQ        0 R6 K10     ; if R6 ~= 3.000000 then PC := 77
 33 [-]: JMP       77           ; PC := 77
 34 [-]: GETUPVAL  R9 U1        ; R9 := U1
 35 [-]: GETTABLE  R9 R9 K11    ; R9 := R9["FingerPrint"]
 36 [-]: EQ        0 R9 K12     ; if R9 ~= nil then PC := 77
 37 [-]: JMP       77           ; PC := 77
 38 [-]: GETGLOBAL R9 K13       ; R9 := 0x3d106989
 39 [-]: LOADK     R10 K14      ; R10 := "CompositionTool::UpdateResLoader - MAX_NoteType and nil FingerPrint"
 40 [-]: CALL      R9 2 1       ; R9(R10)
 41 [-]: LOADNIL   R9 R9        ; R9 := nil
 42 [-]: GETUPVAL  R10 U2       ; R10 := U2
 43 [-]: SELF      R10 R10 K15  ; R11 := R10; R10 := R10[0x61294cb8]
 44 [-]: CALL      R10 2 2      ; R10 := R10(R11)
 45 [-]: GETGLOBAL R11 K16      ; R11 := 0xb009bbc6
 46 [-]: GETGLOBAL R12 K17      ; R12 := 0x53b33231
 47 [-]: CALL      R11 2 2      ; R11 := R11(R12)
 48 [-]: SELF      R12 R11 K18  ; R13 := R11; R12 := R11[0x4d7a0caf]
 49 [-]: LOADK     R14 3        ; R14 := 3.000000
 50 [-]: CALL      R12 3 2      ; R12 := R12(R13,R14)
 51 [-]: EQ        0 R8 R12     ; if R8 ~= R12 then PC := 60
 52 [-]: JMP       60           ; PC := 60
 53 [-]: GETUPVAL  R12 U2       ; R12 := U2
 54 [-]: SELF      R12 R12 K19  ; R13 := R12; R12 := R12[0x4dc40cc1]
 55 [-]: CALL      R12 2 2      ; R12 := R12(R13)
 56 [-]: EQ        0 R10 R12    ; if R10 ~= R12 then PC := 67
 57 [-]: JMP       67           ; PC := 67
 58 [-]: MOVE      R9 R12       ; R9 := R12
 59 [-]: JMP       67           ; PC := 67
 60 [-]: SELF      R13 R8 K20   ; R14 := R8; R13 := R8[0x7b0c20c2]
 61 [-]: CALL      R13 2 2      ; R13 := R13(R14)
 62 [-]: SELF      R13 R13 K21  ; R14 := R13; R13 := R13[0x6d604ba7]
 63 [-]: CALL      R13 2 2      ; R13 := R13(R14)
 64 [-]: EQ        0 R10 R13    ; if R10 ~= R13 then PC := 67
 65 [-]: JMP       67           ; PC := 67
 66 [-]: MOVE      R9 R13       ; R9 := R13
 67 [-]: EQ        1 R9 K12     ; if R9 == nil then PC := 79
 68 [-]: JMP       79           ; PC := 79
 69 [-]: SETUPVAL  R9 U4        ; U82 := 	
 70 [-]: GETUPVAL  R14 U2       ; R14 := U2
 71 [-]: SELF      R14 R14 K22  ; R15 := R14; R14 := R14[0x4148785c]
 72 [-]: GETUPVAL  R16 U4       ; R16 := U4
 73 [-]: CALL      R14 3 1      ; R14(R15,R16)
 74 [-]: GETUPVAL  R14 U5       ; R14 := U5
 75 [-]: CALL      R14 1 1      ; R14()
 76 [-]: JMP       79           ; PC := 79
 77 [-]: TFORLOOP  R1 2         ; R4,R5 :=  R1(R2,R3); if R4 ~= nil then begin PC = 17; R3 := R4 end
 78 [-]: JMP       17           ; PC := 17
 79 [-]: GETUPVAL  R14 U6       ; R14 := U6
 80 [-]: GETTABLE  R14 R14 K23  ; R14 := R14["dirty"]
 81 [-]: TEST      R14 1        ; if R14 then PC := 92
 82 [-]: JMP       92           ; PC := 92
 83 [-]: GETUPVAL  R14 U2       ; R14 := U2
 84 [-]: SELF      R14 R14 K15  ; R15 := R14; R14 := R14[0x61294cb8]
 85 [-]: CALL      R14 2 2      ; R14 := R14(R15)
 86 [-]: GETUPVAL  R15 U4       ; R15 := U4
 87 [-]: EQ        1 R14 R15    ; if R14 == R15 then PC := 92
 88 [-]: JMP       92           ; PC := 92
 89 [-]: GETUPVAL  R14 U3       ; R14 := U3
 90 [-]: LOADBOOL  R15 1 0      ; R15 := true
 91 [-]: CALL      R14 2 1      ; R14(R15)
 92 [-]: GETUPVAL  R14 U1       ; R14 := U1
 93 [-]: GETTABLE  R14 R14 K11  ; R14 := R14["FingerPrint"]
 94 [-]: EQ        1 R14 K12    ; if R14 == nil then PC := 108
 95 [-]: JMP       108          ; PC := 108
 96 [-]: GETGLOBAL R14 K7       ; R14 := 0x7b998233
 97 [-]: GETUPVAL  R15 U7       ; R15 := U7
 98 [-]: CALL      R14 2 2      ; R14 := R14(R15)
 99 [-]: TEST      R14 1        ; if R14 then PC := 106
100 [-]: JMP       106          ; PC := 106
101 [-]: GETUPVAL  R14 U7       ; R14 := U7
102 [-]: SELF      R14 R14 K24  ; R15 := R14; R14 := R14[0xe4162eed]
103 [-]: LOADK     R16 K25      ; R16 := "RedrawNotes"
104 [-]: LOADK     R17 K26      ; R17 := ""
105 [-]: CALL      R14 4 1      ; R14(R15,R16,R17)
106 [-]: GETUPVAL  R14 U5       ; R14 := U5
107 [-]: CALL      R14 1 1      ; R14()
108 [-]: GETUPVAL  R14 U8       ; R14 := U8
109 [-]: GETUPVAL  R15 U6       ; R15 := U6
110 [-]: GETTABLE  R15 R15 K27  ; R15 := R15["looping"]
111 [-]: CALL      R14 2 1      ; R14(R15)
112 [-]: SELF      R14 R0 K28   ; R15 := R0; R14 := R0[0x55e9211c]
113 [-]: GETUPVAL  R16 U6       ; R16 := U6
114 [-]: GETTABLE  R16 R16 K29  ; R16 := R16["paused"]
115 [-]: CALL      R14 3 1      ; R14(R15,R16)
116 [-]: GETUPVAL  R14 U9       ; R14 := U9
117 [-]: CALL      R14 1 1      ; R14()
118 [-]: JMP       122          ; PC := 122
119 [-]: SELF      R14 R0 K28   ; R15 := R0; R14 := R0[0x55e9211c]
120 [-]: LOADBOOL  R16 0 0      ; R16 := false
121 [-]: CALL      R14 3 1      ; R14(R15,R16)
122 [-]: GETUPVAL  R14 U6       ; R14 := U6
123 [-]: SETTABLE  R14 K30 K31  ; R14["inputBlocked"] := false
124 [-]: GETGLOBAL R14 K32      ; R14 := _T
125 [-]: GETTABLE  R14 R14 K33  ; R14 := R14["BackgroundMovie"]
126 [-]: SELF      R14 R14 K24  ; R15 := R14; R14 := R14[0xe4162eed]
127 [-]: LOADK     R16 K34      ; R16 := "ShowBlockingMessage"
128 [-]: LOADK     R17 K35      ; R17 := "0"
129 [-]: CALL      R14 4 1      ; R14(R15,R16,R17)
130 [-]: RETURN    R0 1         ; return 


; Function #15:
;
; Name:            
; Defined at line: 294
; #Upvalues:       6
; #Parameters:     0
; Is_vararg:       0
; Max Stack Size:  18

  1 [-]: GETUPVAL  R0 U0        ; R0 := U0
  2 [-]: GETTABLE  R0 R0 K0     ; R0 := R0["dirty"]
  3 [-]: TEST      R0 1         ; if R0 then PC := 6
  4 [-]: JMP       6            ; PC := 6
  5 [-]: RETURN    R0 1         ; return 
  6 [-]: GETUPVAL  R0 U1        ; R0 := U1
  7 [-]: LOADBOOL  R1 0 0       ; R1 := false
  8 [-]: CALL      R0 2 1       ; R0(R1)
  9 [-]: GETGLOBAL R0 K1        ; R0 := 0x7b998233
 10 [-]: GETUPVAL  R1 U2        ; R1 := U2
 11 [-]: CALL      R0 2 2       ; R0 := R0(R1)
 12 [-]: TEST      R0 1         ; if R0 then PC := 128
 13 [-]: JMP       128          ; PC := 128
 14 [-]: GETUPVAL  R0 U2        ; R0 := U2
 15 [-]: SELF      R0 R0 K2     ; R1 := R0; R0 := R0[0xde321e6f]
 16 [-]: CALL      R0 2 2       ; R0 := R0(R1)
 17 [-]: GETGLOBAL R1 K1        ; R1 := 0x7b998233
 18 [-]: MOVE      R2 R0        ; R2 := R0
 19 [-]: CALL      R1 2 2       ; R1 := R1(R2)
 20 [-]: TEST      R1 1         ; if R1 then PC := 128
 21 [-]: JMP       128          ; PC := 128
 22 [-]: GETGLOBAL R1 K1        ; R1 := 0x7b998233
 23 [-]: GETUPVAL  R2 U3        ; R2 := U3
 24 [-]: CALL      R1 2 2       ; R1 := R1(R2)
 25 [-]: TEST      R1 1         ; if R1 then PC := 128
 26 [-]: JMP       128          ; PC := 128
 27 [-]: GETUPVAL  R1 U3        ; R1 := U3
 28 [-]: SELF      R1 R1 K3     ; R2 := R1; R1 := R1[0x61294cb8]
 29 [-]: CALL      R1 2 2       ; R1 := R1(R2)
 30 [-]: GETGLOBAL R2 K4        ; R2 := 0x3d106989
 31 [-]: LOADK     R3 K5        ; R3 := "StepSequencer fingerprint: "
 32 [-]: MOVE      R4 R1        ; R4 := R1
 33 [-]: CONCAT    R3 R3 R4     ; R3 := R3 .. R4
 34 [-]: CALL      R2 2 1       ; R2(R3)
 35 [-]: SETUPVAL  R1 U4        ; U82 := 
 36 [-]: SELF      R2 R0 K6     ; R3 := R0; R2 := R0[0xf7d48ee0]
 37 [-]: CALL      R2 2 2       ; R2 := R2(R3)
 38 [-]: GETGLOBAL R3 K1        ; R3 := 0x7b998233
 39 [-]: MOVE      R4 R2        ; R4 := R2
 40 [-]: CALL      R3 2 2       ; R3 := R3(R4)
 41 [-]: TEST      R3 1         ; if R3 then PC := 128
 42 [-]: JMP       128          ; PC := 128
 43 [-]: GETUPVAL  R3 U5        ; R3 := U5
 44 [-]: EQ        1 R3 K7      ; if R3 == nil then PC := 128
 45 [-]: JMP       128          ; PC := 128
 46 [-]: GETUPVAL  R3 U5        ; R3 := U5
 47 [-]: GETTABLE  R3 R3 K8     ; R3 := R3["abilityIndex"]
 48 [-]: EQ        1 R3 K7      ; if R3 == nil then PC := 128
 49 [-]: JMP       128          ; PC := 128
 50 [-]: GETGLOBAL R3 K9        ; R3 := 0xb009bbc6
 51 [-]: GETGLOBAL R4 K10       ; R4 := 0x53b33231
 52 [-]: CALL      R3 2 2       ; R3 := R3(R4)
 53 [-]: GETGLOBAL R4 K11       ; R4 := 0x6c97a788
 54 [-]: GETTABLE  R4 R4 K12    ; R82 := R4[0x9e3cf712]
 55 [-]: CALL      R4 1 2       ; R4 := R4()
 56 [-]: LOADK     R5 0         ; R5 := 0.000000
 57 [-]: LOADK     R6 2         ; R6 := 2.000000
 58 [-]: LOADK     R7 1         ; R7 := 1.000000
 59 [-]: FORPREP   R5 82        ; R5 -= R7; PC := 82
 60 [-]: GETUPVAL  R9 U3        ; R9 := U3
 61 [-]: SELF      R9 R9 K13    ; R10 := R9; R9 := R9[0x4d7a0caf]
 62 [-]: MOVE      R11 R8       ; R11 := R8
 63 [-]: CALL      R9 3 2       ; R9 := R9(R10,R11)
 64 [-]: SELF      R10 R3 K13   ; R11 := R3; R10 := R3[0x4d7a0caf]
 65 [-]: MOVE      R12 R8       ; R12 := R8
 66 [-]: CALL      R10 3 2      ; R10 := R10(R11,R12)
 67 [-]: EQ        1 R9 R10     ; if R9 == R10 then PC := 82
 68 [-]: JMP       82           ; PC := 82
 69 [-]: GETGLOBAL R10 K1       ; R10 := 0x7b998233
 70 [-]: MOVE      R11 R9       ; R11 := R9
 71 [-]: CALL      R10 2 2      ; R10 := R10(R11)
 72 [-]: TEST      R10 1        ; if R10 then PC := 82
 73 [-]: JMP       82           ; PC := 82
 74 [-]: SELF      R10 R4 K14   ; R11 := R4; R10 := R4[0x3546d52b]
 75 [-]: MOVE      R12 R8       ; R12 := R8
 76 [-]: LOADBOOL  R13 1 0      ; R13 := true
 77 [-]: CALL      R10 4 1      ; R10(R11,R12,R13)
 78 [-]: SELF      R10 R4 K15   ; R11 := R4; R10 := R4[0x6caac40b]
 79 [-]: MOVE      R12 R8       ; R12 := R8
 80 [-]: MOVE      R13 R9       ; R13 := R9
 81 [-]: CALL      R10 4 1      ; R10(R11,R12,R13)
 82 [-]: FORLOOP   R5 60        ; R5 += R7; if R5 <= R6 then begin PC := 60; R8 := R5 end
 83 [-]: SELF      R10 R3 K16   ; R11 := R3; R10 := R3[0x4dc40cc1]
 84 [-]: CALL      R10 2 2      ; R10 := R10(R11)
 85 [-]: EQ        1 R1 R10     ; if R1 == R10 then PC := 89
 86 [-]: JMP       89           ; PC := 89
 87 [-]: SETTABLE  R4 K17 K18   ; R4["mHasFingerPrint"] := true
 88 [-]: SETTABLE  R4 K19 R1    ; R4["mFingerPrint"] := R1
 89 [-]: SELF      R10 R2 K20   ; R11 := R2; R10 := R2[0x68d708a7]
 90 [-]: CALL      R10 2 2      ; R10 := R10(R11)
 91 [-]: SELF      R11 R10 K21  ; R12 := R10; R11 := R10[0x202cdc77]
 92 [-]: MOVE      R13 R4       ; R13 := R4
 93 [-]: GETUPVAL  R14 U5       ; R14 := U5
 94 [-]: GETTABLE  R14 R14 K8   ; R14 := R14["abilityIndex"]
 95 [-]: CALL      R11 4 1      ; R11(R12,R13,R14)
 96 [-]: SELF      R11 R2 K22   ; R12 := R2; R11 := R2[0xaa041663]
 97 [-]: MOVE      R13 R10      ; R13 := R10
 98 [-]: LOADBOOL  R14 0 0      ; R14 := false
 99 [-]: CALL      R11 4 1      ; R11(R12,R13,R14)
100 [-]: GETUPVAL  R11 U5       ; R11 := U5
101 [-]: GETTABLE  R11 R11 K23  ; R11 := R11["weaponId"]
102 [-]: EQ        1 R11 K7     ; if R11 == nil then PC := 128
103 [-]: JMP       128          ; PC := 128
104 [-]: GETUPVAL  R11 U5       ; R11 := U5
105 [-]: GETTABLE  R11 R11 K24  ; R11 := R11["configId"]
106 [-]: EQ        1 R11 K7     ; if R11 == nil then PC := 128
107 [-]: JMP       128          ; PC := 128
108 [-]: GETGLOBAL R11 K25      ; R11 := 0x76ea806b
109 [-]: SELF      R11 R11 K26  ; R12 := R11; R11 := R11[0x3f3ae64c]
110 [-]: LOADK     R13 0        ; R13 := 0.000000
111 [-]: CALL      R11 3 2      ; R11 := R11(R12,R13)
112 [-]: GETGLOBAL R12 K1       ; R12 := 0x7b998233
113 [-]: MOVE      R13 R11      ; R13 := R11
114 [-]: CALL      R12 2 2      ; R12 := R12(R13)
115 [-]: TEST      R12 1        ; if R12 then PC := 128
116 [-]: JMP       128          ; PC := 128
117 [-]: SELF      R12 R11 K27  ; R13 := R11; R12 := R11[0x80563238]
118 [-]: CALL      R12 2 2      ; R12 := R12(R13)
119 [-]: SELF      R12 R12 K28  ; R13 := R12; R12 := R12[0x25a6e75e]
120 [-]: CALL      R12 2 2      ; R12 := R12(R13)
121 [-]: SELF      R13 R12 K29  ; R14 := R12; R13 := R12[0x9b051033]
122 [-]: GETUPVAL  R15 U5       ; R15 := U5
123 [-]: GETTABLE  R15 R15 K23  ; R15 := R15["weaponId"]
124 [-]: GETUPVAL  R16 U5       ; R16 := U5
125 [-]: GETTABLE  R16 R16 K24  ; R16 := R16["configId"]
126 [-]: MOVE      R17 R10      ; R17 := R10
127 [-]: CALL      R13 5 1      ; R13(R14,R15,R16,R17)
128 [-]: RETURN    R0 1         ; return 


; Function #16:
;
; Name:            
; Defined at line: 347
; #Upvalues:       1
; #Parameters:     2
; Is_vararg:       0
; Max Stack Size:  4

  1 [-]: GETGLOBAL R2 K0        ; R2 := _T
  2 [-]: GETTABLE  R2 R2 K1     ; R2 := R2["Jukebox"]
  3 [-]: EQ        1 R2 K2      ; if R2 == nil then PC := 9
  4 [-]: JMP       9            ; PC := 9
  5 [-]: GETUPVAL  R2 U0        ; R2 := U0
  6 [-]: GETTABLE  R2 R2 K3     ; R82 := R2[0x284a8fad]
  7 [-]: GETGLOBAL R3 K4        ; R3 := 0xae91e43b
  8 [-]: CALL      R2 2 1       ; R2(R3)
  9 [-]: RETURN    R0 1         ; return 


; Function #17:
;
; Name:            
; Defined at line: 354
; #Upvalues:       3
; #Parameters:     1
; Is_vararg:       0
; Max Stack Size:  9

  1 [-]: GETUPVAL  R1 U0        ; R1 := U0
  2 [-]: EQ        0 R1 K0      ; if R1 ~= nil then PC := 5
  3 [-]: JMP       5            ; PC := 5
  4 [-]: RETURN    R0 1         ; return 
  5 [-]: GETUPVAL  R1 U1        ; R1 := U1
  6 [-]: GETTABLE  R1 R1 K1     ; R82 := R1[0x5d3d561a]
  7 [-]: MOVE      R2 R0        ; R2 := R0
  8 [-]: LOADK     R3 K2        ; R3 := " "
  9 [-]: CALL      R1 3 2       ; R1 := R1(R2,R3)
 10 [-]: LT        0 K3 R1      ; if 0.000000 >= R1 then PC := 28
 11 [-]: JMP       28           ; PC := 28
 12 [-]: GETUPVAL  R2 U1        ; R2 := U1
 13 [-]: GETTABLE  R2 R2 K4     ; R82 := R2[0xe0cba3ca]
 14 [-]: GETGLOBAL R3 K5        ; R3 := 0xae91e43b
 15 [-]: SELF      R3 R3 K6     ; R4 := R3; R3 := R3[0x42b04007]
 16 [-]: LOADK     R5 K7        ; R5 := "/Lotus/Language/Menu/SocialOverlay_InvalidCharacter"
 17 [-]: LOADBOOL  R6 0 0       ; R6 := false
 18 [-]: CALL      R3 4 2       ; R3 := R3(R4,R5,R6)
 19 [-]: LOADK     R4 K2        ; R4 := " "
 20 [-]: GETGLOBAL R5 K8        ; R5 := 0x68b0afb4
 21 [-]: MOVE      R6 R0        ; R6 := R0
 22 [-]: MOVE      R7 R1        ; R7 := R1
 23 [-]: MOVE      R8 R1        ; R8 := R1
 24 [-]: CALL      R5 4 2       ; R5 := R5(R6,R7,R8)
 25 [-]: CONCAT    R3 R3 R5     ; R3 := R3 .. R4 .. R5
 26 [-]: CALL      R2 2 1       ; R2(R3)
 27 [-]: RETURN    R0 1         ; return 
 28 [-]: GETGLOBAL R2 K9        ; R2 := 0x09423272
 29 [-]: MOVE      R3 R0        ; R3 := R0
 30 [-]: LOADK     R4 1         ; R4 := 1.000000
 31 [-]: CALL      R2 3 2       ; R2 := R2(R3,R4)
 32 [-]: EQ        1 R2 R0      ; if R2 == R0 then PC := 43
 33 [-]: JMP       43           ; PC := 43
 34 [-]: GETUPVAL  R3 U1        ; R3 := U1
 35 [-]: GETTABLE  R3 R3 K4     ; R82 := R3[0xe0cba3ca]
 36 [-]: GETGLOBAL R4 K5        ; R4 := 0xae91e43b
 37 [-]: SELF      R4 R4 K6     ; R5 := R4; R4 := R4[0x42b04007]
 38 [-]: LOADK     R6 K11       ; R6 := "/Lotus/Language/Menu/Composition_ProfanityError"
 39 [-]: LOADBOOL  R7 0 0       ; R7 := false
 40 [-]: CALL      R4 4 0       ; R4,... := R4(R5,R6,R7)
 41 [-]: CALL      R3 0 1       ; R3(R4,...)
 42 [-]: RETURN    R0 1         ; return 
 43 [-]: GETUPVAL  R3 U0        ; R3 := U0
 44 [-]: SETTABLE  R3 K12 R0    ; R3["mName"] := R0
 45 [-]: GETUPVAL  R3 U2        ; R3 := U2
 46 [-]: SELF      R3 R3 K13    ; R4 := R3; R3 := R3[0x2fb43a9e]
 47 [-]: GETUPVAL  R5 U0        ; R5 := U0
 48 [-]: LOADK     R6 K14       ; R6 := "OnStepSequencerUpdated"
 49 [-]: CALL      R3 4 1       ; R3(R4,R5,R6)
 50 [-]: RETURN    R0 1         ; return 


; Function #18:
;
; Name:            
; Defined at line: 376
; #Upvalues:       3
; #Parameters:     3
; Is_vararg:       0
; Max Stack Size:  5

  1 [-]: GETGLOBAL R3 K0        ; R3 := 0x03f57322
  2 [-]: MOVE      R4 R2        ; R4 := R2
  3 [-]: CALL      R3 2 2       ; R3 := R3(R4)
  4 [-]: EQ        0 R3 K2      ; if R3 ~= 4.000000 then PC := 9
  5 [-]: JMP       9            ; PC := 9
  6 [-]: GETUPVAL  R3 U0        ; R3 := U0
  7 [-]: MOVE      R4 R0        ; R4 := R0
  8 [-]: CALL      R3 2 1       ; R3(R4)
  9 [-]: GETUPVAL  R3 U1        ; R3 := U1
 10 [-]: SETTABLE  R3 K3 K4     ; R3["inputBlocked"] := false
 11 [-]: LOADNIL   R3 R3        ; R3 := nil
 12 [-]: SETUPVAL  R3 U2        ; U82 := 
 13 [-]: RETURN    R0 1         ; return 


; Function #19:
;
; Name:            
; Defined at line: 385
; #Upvalues:       3
; #Parameters:     2
; Is_vararg:       0
; Max Stack Size:  4

  1 [-]: TEST      R0 1         ; if R0 then PC := 6
  2 [-]: JMP       6            ; PC := 6
  3 [-]: GETUPVAL  R2 U0        ; R2 := U0
  4 [-]: MOVE      R3 R1        ; R3 := R1
  5 [-]: CALL      R2 2 1       ; R2(R3)
  6 [-]: GETUPVAL  R2 U1        ; R2 := U1
  7 [-]: SETTABLE  R2 K0 K1     ; R2["inputBlocked"] := false
  8 [-]: LOADNIL   R2 R2        ; R2 := nil
  9 [-]: SETUPVAL  R2 U2        ; U82 := 
 10 [-]: RETURN    R0 1         ; return 


; Function #20:
;
; Name:            
; Defined at line: 394
; #Upvalues:       6
; #Parameters:     1
; Is_vararg:       0
; Max Stack Size:  12

  1 [-]: EQ        0 R0 K0      ; if R0 ~= nil then PC := 6
  2 [-]: JMP       6            ; PC := 6
  3 [-]: GETUPVAL  R1 U0        ; R1 := U0
  4 [-]: CALL      R1 1 1       ; R1()
  5 [-]: JMP       48           ; PC := 48
  6 [-]: GETUPVAL  R1 U1        ; R1 := U1
  7 [-]: SELF      R1 R1 K2     ; R2 := R1; R1 := R1[0x61294cb8]
  8 [-]: CALL      R1 2 2       ; R1 := R1(R2)
  9 [-]: SETTABLE  R0 K1 R1     ; R0["mFingerPrint"] := R1
 10 [-]: LOADK     R1 0         ; R1 := 0.000000
 11 [-]: LOADK     R2 2         ; R2 := 2.000000
 12 [-]: LOADK     R3 1         ; R3 := 1.000000
 13 [-]: FORPREP   R1 21        ; R1 -= R3; PC := 21
 14 [-]: SELF      R5 R0 K4     ; R6 := R0; R5 := R0[0x6caac40b]
 15 [-]: MOVE      R7 R4        ; R7 := R4
 16 [-]: GETUPVAL  R8 U1        ; R8 := U1
 17 [-]: SELF      R8 R8 K5     ; R9 := R8; R8 := R8[0x4d7a0caf]
 18 [-]: MOVE      R10 R4       ; R10 := R4
 19 [-]: CALL      R8 3 0       ; R8,... := R8(R9,R10)
 20 [-]: CALL      R5 0 1       ; R5(R6,...)
 21 [-]: FORLOOP   R1 14        ; R1 += R3; if R1 <= R2 then begin PC := 14; R4 := R1 end
 22 [-]: GETUPVAL  R5 U2        ; R5 := U2
 23 [-]: GETTABLE  R5 R5 K6     ; R82 := R5[0xef3e3165]
 24 [-]: GETGLOBAL R6 K7        ; R6 := 0xae91e43b
 25 [-]: GETGLOBAL R7 K7        ; R7 := 0xae91e43b
 26 [-]: SELF      R7 R7 K8     ; R8 := R7; R7 := R7[0x42b04007]
 27 [-]: LOADK     R9 K9        ; R9 := "/Lotus/Language/Menu/Composition_SetName"
 28 [-]: LOADBOOL  R10 0 0      ; R10 := false
 29 [-]: CALL      R7 4 2       ; R7 := R7(R8,R9,R10)
 30 [-]: GETTABLE  R8 R0 K10    ; R8 := R0["mName"]
 31 [-]: LOADK     R9 24        ; R9 := 24.000000
 32 [-]: LOADK     R10 K11      ; R10 := "SaveSongNamed"
 33 [-]: LOADK     R11 K12      ; R11 := "OSKSaveSongNamed"
 34 [-]: CALL      R5 7 2       ; R5 := R5(R6,R7,R8,R9,R10,R11)
 35 [-]: TEST      R5 0         ; if not R5 then PC := 41
 36 [-]: JMP       41           ; PC := 41
 37 [-]: SETUPVAL  R0 U3        ; U82 := 
 38 [-]: GETUPVAL  R5 U4        ; R5 := U4
 39 [-]: SETTABLE  R5 K13 K14   ; R5["inputBlocked"] := true
 40 [-]: JMP       48           ; PC := 48
 41 [-]: GETUPVAL  R5 U5        ; R5 := U5
 42 [-]: SELF      R5 R5 K15    ; R6 := R5; R5 := R5[0x2fb43a9e]
 43 [-]: MOVE      R7 R0        ; R7 := R0
 44 [-]: LOADK     R8 K16       ; R8 := "OnStepSequencerUpdated"
 45 [-]: CALL      R5 4 1       ; R5(R6,R7,R8)
 46 [-]: LOADNIL   R5 R5        ; R5 := nil
 47 [-]: SETUPVAL  R5 U3        ; U82 := 
 48 [-]: RETURN    R0 1         ; return 


; Function #21:
;
; Name:            
; Defined at line: 422
; #Upvalues:       2
; #Parameters:     0
; Is_vararg:       0
; Max Stack Size:  2

  1 [-]: GETUPVAL  R0 U0        ; R0 := U0
  2 [-]: GETUPVAL  R1 U1        ; R1 := U1
  3 [-]: CALL      R0 2 1       ; R0(R1)
  4 [-]: RETURN    R0 1         ; return 


; Function #22:
;
; Name:            
; Defined at line: 426
; #Upvalues:       11
; #Parameters:     0
; Is_vararg:       0
; Max Stack Size:  5

  1 [-]: GETUPVAL  R0 U0        ; R0 := U0
  2 [-]: GETTABLE  R0 R0 K0     ; R0 := R0["inputBlocked"]
  3 [-]: TEST      R0 0         ; if not R0 then PC := 6
  4 [-]: JMP       6            ; PC := 6
  5 [-]: RETURN    R0 1         ; return 
  6 [-]: GETGLOBAL R0 K1        ; R0 := 0x7b998233
  7 [-]: GETGLOBAL R1 K2        ; R1 := 0x08a5afb4
  8 [-]: CALL      R0 2 2       ; R0 := R0(R1)
  9 [-]: TEST      R0 0         ; if not R0 then PC := 12
 10 [-]: JMP       12           ; PC := 12
 11 [-]: RETURN    R0 1         ; return 
 12 [-]: GETGLOBAL R0 K1        ; R0 := 0x7b998233
 13 [-]: GETUPVAL  R1 U1        ; R1 := U1
 14 [-]: CALL      R0 2 2       ; R0 := R0(R1)
 15 [-]: TEST      R0 1         ; if R0 then PC := 20
 16 [-]: JMP       20           ; PC := 20
 17 [-]: GETUPVAL  R0 U1        ; R0 := U1
 18 [-]: SELF      R0 R0 K3     ; R1 := R0; R0 := R0[0x32302b4a]
 19 [-]: CALL      R0 2 1       ; R0(R1)
 20 [-]: GETGLOBAL R0 K4        ; R0 := 0xae91e43b
 21 [-]: SELF      R0 R0 K5     ; R1 := R0; R0 := R0[0x1fd6abd0]
 22 [-]: GETGLOBAL R2 K2        ; R2 := 0x08a5afb4
 23 [-]: CALL      R0 3 2       ; R0 := R0(R1,R2)
 24 [-]: SETUPVAL  R0 U1        ; U82 := 
 25 [-]: GETGLOBAL R0 K1        ; R0 := 0x7b998233
 26 [-]: GETUPVAL  R1 U1        ; R1 := U1
 27 [-]: CALL      R0 2 2       ; R0 := R0(R1)
 28 [-]: TEST      R0 0         ; if not R0 then PC := 31
 29 [-]: JMP       31           ; PC := 31
 30 [-]: RETURN    R0 1         ; return 
 31 [-]: GETUPVAL  R0 U1        ; R0 := U1
 32 [-]: SELF      R0 R0 K6     ; R1 := R0; R0 := R0[0xe4162eed]
 33 [-]: LOADK     R2 K7        ; R2 := "SetTitle"
 34 [-]: LOADK     R3 K8        ; R3 := "/Lotus/Language/Menu/Composition_Save"
 35 [-]: CALL      R0 4 1       ; R0(R1,R2,R3)
 36 [-]: GETUPVAL  R0 U2        ; R0 := U2
 37 [-]: SELF      R0 R0 K9     ; R1 := R0; R0 := R0[0x55e9211c]
 38 [-]: LOADBOOL  R2 1 0       ; R2 := true
 39 [-]: CALL      R0 3 1       ; R0(R1,R2)
 40 [-]: LOADNIL   R0 R0        ; R0 := nil
 41 [-]: GETGLOBAL R1 K10       ; R1 := _T
 42 [-]: CLOSURE   R2 0         ; R2 := closure(Function #22.1)
 43 [-]: MOVE      R0 R0        ; R0 := R0
 44 [-]: GETUPVAL  R0 U3        ; R0 := U3
 45 [-]: GETUPVAL  R0 U2        ; R0 := U2
 46 [-]: GETUPVAL  R0 U0        ; R0 := U0
 47 [-]: GETUPVAL  R0 U4        ; R0 := U4
 48 [-]: SETTABLE  R1 K11 R2    ; R1["SongSelectionDone"] := R2
 49 [-]: GETUPVAL  R1 U1        ; R1 := U1
 50 [-]: SELF      R1 R1 K6     ; R2 := R1; R1 := R1[0xe4162eed]
 51 [-]: LOADK     R3 K12       ; R3 := "SetCallBack"
 52 [-]: LOADK     R4 K11       ; R4 := "SongSelectionDone"
 53 [-]: CALL      R1 4 1       ; R1(R2,R3,R4)
 54 [-]: GETGLOBAL R1 K10       ; R1 := _T
 55 [-]: CLOSURE   R2 1         ; R2 := closure(Function #22.2)
 56 [-]: GETUPVAL  R0 U0        ; R0 := U0
 57 [-]: GETUPVAL  R0 U5        ; R0 := U5
 58 [-]: GETUPVAL  R0 U6        ; R0 := U6
 59 [-]: SETTABLE  R1 K13 R2    ; R1["GetSongList"] := R2
 60 [-]: GETUPVAL  R1 U1        ; R1 := U1
 61 [-]: SELF      R1 R1 K6     ; R2 := R1; R1 := R1[0xe4162eed]
 62 [-]: LOADK     R3 K14       ; R3 := "SetElementsFunction"
 63 [-]: LOADK     R4 K13       ; R4 := "GetSongList"
 64 [-]: CALL      R1 4 1       ; R1(R2,R3,R4)
 65 [-]: GETGLOBAL R1 K10       ; R1 := _T
 66 [-]: CLOSURE   R2 2         ; R2 := closure(Function #22.3)
 67 [-]: MOVE      R0 R0        ; R0 := R0
 68 [-]: GETUPVAL  R0 U7        ; R0 := U7
 69 [-]: GETUPVAL  R0 U8        ; R0 := U8
 70 [-]: GETUPVAL  R0 U9        ; R0 := U9
 71 [-]: GETUPVAL  R0 U10       ; R0 := U10
 72 [-]: GETUPVAL  R0 U1        ; R0 := U1
 73 [-]: SETTABLE  R1 K15 R2    ; R1["OnSongFocused"] := R2
 74 [-]: GETUPVAL  R1 U1        ; R1 := U1
 75 [-]: SELF      R1 R1 K6     ; R2 := R1; R1 := R1[0xe4162eed]
 76 [-]: LOADK     R3 K16       ; R3 := "SetOnFocusedCallback"
 77 [-]: LOADK     R4 K15       ; R4 := "OnSongFocused"
 78 [-]: CALL      R1 4 1       ; R1(R2,R3,R4)
 79 [-]: GETGLOBAL R1 K10       ; R1 := _T
 80 [-]: CLOSURE   R2 3         ; R2 := closure(Function #22.4)
 81 [-]: MOVE      R0 R0        ; R0 := R0
 82 [-]: GETUPVAL  R0 U1        ; R0 := U1
 83 [-]: GETUPVAL  R0 U3        ; R0 := U3
 84 [-]: SETTABLE  R1 K17 R2    ; R1["OnSongUnfocused"] := R2
 85 [-]: GETUPVAL  R1 U1        ; R1 := U1
 86 [-]: SELF      R1 R1 K6     ; R2 := R1; R1 := R1[0xe4162eed]
 87 [-]: LOADK     R3 K18       ; R3 := "SetOnUnfocusedCallback"
 88 [-]: LOADK     R4 K17       ; R4 := "OnSongUnfocused"
 89 [-]: CALL      R1 4 1       ; R1(R2,R3,R4)
 90 [-]: RETURN    R0 1         ; return 


; Function #22.1:
;
; Name:            
; Defined at line: 450
; #Upvalues:       5
; #Parameters:     1
; Is_vararg:       0
; Max Stack Size:  5

  1 [-]: GETGLOBAL R1 K0        ; R1 := _T
  2 [-]: SETTABLE  R1 K1 K2     ; R1["SongSelectionDone"] := nil
  3 [-]: GETGLOBAL R1 K0        ; R1 := _T
  4 [-]: SETTABLE  R1 K3 K2     ; R1["GetSongList"] := nil
  5 [-]: GETGLOBAL R1 K0        ; R1 := _T
  6 [-]: SETTABLE  R1 K4 K2     ; R1["OnSongFocused"] := nil
  7 [-]: GETGLOBAL R1 K0        ; R1 := _T
  8 [-]: SETTABLE  R1 K5 K2     ; R1["OnSongUnfocused"] := nil
  9 [-]: GETGLOBAL R1 K6        ; R1 := 0x7b998233
 10 [-]: GETUPVAL  R2 U0        ; R2 := U0
 11 [-]: CALL      R1 2 2       ; R1 := R1(R2)
 12 [-]: TEST      R1 1         ; if R1 then PC := 31
 13 [-]: JMP       31           ; PC := 31
 14 [-]: GETUPVAL  R1 U0        ; R1 := U0
 15 [-]: SELF      R1 R1 K7     ; R2 := R1; R1 := R1[0xa2880940]
 16 [-]: CALL      R1 2 1       ; R1(R2)
 17 [-]: GETUPVAL  R1 U1        ; R1 := U1
 18 [-]: EQ        1 R1 K2      ; if R1 == nil then PC := 31
 19 [-]: JMP       31           ; PC := 31
 20 [-]: GETUPVAL  R1 U1        ; R1 := U1
 21 [-]: GETTABLE  R1 R1 K8     ; R1 := R1["IsLoading"]
 22 [-]: TEST      R1 0         ; if not R1 then PC := 31
 23 [-]: JMP       31           ; PC := 31
 24 [-]: GETUPVAL  R1 U1        ; R1 := U1
 25 [-]: GETTABLE  R1 R1 K9     ; R1 := R1["StepSequencer"]
 26 [-]: GETUPVAL  R2 U0        ; R2 := U0
 27 [-]: EQ        0 R1 R2      ; if R1 ~= R2 then PC := 31
 28 [-]: JMP       31           ; PC := 31
 29 [-]: LOADNIL   R1 R1        ; R1 := nil
 30 [-]: SETUPVAL  R1 U1        ; U82 := 
 31 [-]: GETUPVAL  R1 U2        ; R1 := U2
 32 [-]: SELF      R1 R1 K10    ; R2 := R1; R1 := R1[0x55e9211c]
 33 [-]: GETUPVAL  R3 U3        ; R3 := U3
 34 [-]: GETTABLE  R3 R3 K11    ; R3 := R3["paused"]
 35 [-]: CALL      R1 3 1       ; R1(R2,R3)
 36 [-]: GETUPVAL  R1 U3        ; R1 := U3
 37 [-]: SETTABLE  R1 K12 K13   ; R1["inputBlocked"] := false
 38 [-]: GETTABLE  R1 R0 K14    ; R1 := R0[1.000000]
 39 [-]: EQ        1 R1 K2      ; if R1 == nil then PC := 49
 40 [-]: JMP       49           ; PC := 49
 41 [-]: GETTABLE  R1 R0 K14    ; R1 := R0[1.000000]
 42 [-]: GETTABLE  R1 R1 K15    ; R1 := R1["mSong"]
 43 [-]: SETUPVAL  R1 U4        ; U82 := 
 44 [-]: GETGLOBAL R1 K16       ; R1 := 0xae91e43b
 45 [-]: SELF      R1 R1 K17    ; R2 := R1; R1 := R1[0xe4162eed]
 46 [-]: LOADK     R3 K18       ; R3 := "SaveSong"
 47 [-]: LOADK     R4 K19       ; R4 := ""
 48 [-]: CALL      R1 4 1       ; R1(R2,R3,R4)
 49 [-]: RETURN    R0 1         ; return 


; Function #22.2:
;
; Name:            
; Defined at line: 475
; #Upvalues:       3
; #Parameters:     0
; Is_vararg:       0
; Max Stack Size:  18

  1 [-]: NEWTABLE  R0 0 0       ; R0 := {}
  2 [-]: GETUPVAL  R1 U0        ; R1 := U0
  3 [-]: GETTABLE  R1 R1 K0     ; R1 := R1["dirty"]
  4 [-]: TEST      R1 0         ; if not R1 then PC := 18
  5 [-]: JMP       18           ; PC := 18
  6 [-]: GETGLOBAL R1 K1        ; R1 := 0x33bdd652
  7 [-]: GETTABLE  R1 R1 K2     ; R82 := R1[0x23d5322f]
  8 [-]: MOVE      R2 R0        ; R2 := R0
  9 [-]: NEWTABLE  R3 0 2       ; R3 := {}
 10 [-]: GETGLOBAL R4 K4        ; R4 := 0xae91e43b
 11 [-]: SELF      R4 R4 K5     ; R5 := R4; R4 := R4[0x42b04007]
 12 [-]: LOADK     R6 K6        ; R6 := "/Lotus/Language/Menu/Composition_SaveCustomization"
 13 [-]: LOADBOOL  R7 0 0       ; R7 := false
 14 [-]: CALL      R4 4 2       ; R4 := R4(R5,R6,R7)
 15 [-]: SETTABLE  R3 K3 R4     ; R3["mName"] := R4
 16 [-]: SETTABLE  R3 K7 K8     ; R3["mTintIcons"] := true
 17 [-]: CALL      R1 3 1       ; R1(R2,R3)
 18 [-]: GETUPVAL  R1 U1        ; R1 := U1
 19 [-]: GETTABLE  R1 R1 K9     ; R82 := R1[0x1be8b875]
 20 [-]: GETGLOBAL R2 K10       ; R2 := 0x639ad296
 21 [-]: CALL      R1 2 2       ; R1 := R1(R2)
 22 [-]: GETUPVAL  R2 U2        ; R2 := U2
 23 [-]: SELF      R2 R2 K11    ; R3 := R2; R2 := R2[0x25a6e75e]
 24 [-]: CALL      R2 2 2       ; R2 := R2(R3)
 25 [-]: SELF      R2 R2 K12    ; R3 := R2; R2 := R2[0xb139c962]
 26 [-]: CALL      R2 2 2       ; R2 := R2(R3)
 27 [-]: GETGLOBAL R3 K13       ; R3 := 0xc8802016
 28 [-]: MOVE      R4 R2        ; R4 := R2
 29 [-]: CALL      R3 2 4       ; R3,R4,R5 := R3(R4)
 30 [-]: JMP       55           ; PC := 55
 31 [-]: LT        0 R1 R6      ; if R1 >= R6 then PC := 34
 32 [-]: JMP       34           ; PC := 34
 33 [-]: JMP       57           ; PC := 57
 34 [-]: GETTABLE  R8 R7 K3     ; R8 := R7["mName"]
 35 [-]: EQ        1 R8 K14     ; if R8 == nil then PC := 39
 36 [-]: JMP       39           ; PC := 39
 37 [-]: EQ        0 R8 K15     ; if R8 ~= "" then PC := 47
 38 [-]: JMP       47           ; PC := 47
 39 [-]: GETGLOBAL R9 K4        ; R9 := 0xae91e43b
 40 [-]: SELF      R9 R9 K5     ; R10 := R9; R9 := R9[0x42b04007]
 41 [-]: LOADK     R11 K16      ; R11 := "/Lotus/Language/Menu/Composition_SaveSong"
 42 [-]: LOADBOOL  R12 0 0      ; R12 := false
 43 [-]: NEWTABLE  R13 0 1      ; R13 := {}
 44 [-]: SETTABLE  R13 K17 R6   ; R13["INDEX"] := R6
 45 [-]: CALL      R9 5 2       ; R9 := R9(R10,R11,R12,R13)
 46 [-]: MOVE      R8 R9        ; R8 := R9
 47 [-]: GETGLOBAL R9 K1        ; R9 := 0x33bdd652
 48 [-]: GETTABLE  R9 R9 K2     ; R82 := R9[0x23d5322f]
 49 [-]: MOVE      R10 R0       ; R10 := R0
 50 [-]: NEWTABLE  R11 0 3      ; R11 := {}
 51 [-]: SETTABLE  R11 K3 R8    ; R11["mName"] := R8
 52 [-]: SETTABLE  R11 K18 R7   ; R11["mSong"] := R7
 53 [-]: SETTABLE  R11 K7 K8    ; R11["mTintIcons"] := true
 54 [-]: CALL      R9 3 1       ; R9(R10,R11)
 55 [-]: TFORLOOP  R3 2         ; R6,R7 :=  R3(R4,R5); if R6 ~= nil then begin PC = 31; R5 := R6 end
 56 [-]: JMP       31           ; PC := 31
 57 [-]: LEN       R9 R2        ; R9 := # R2
 58 [-]: LT        0 R9 R1      ; if R9 >= R1 then PC := 79
 59 [-]: JMP       79           ; PC := 79
 60 [-]: GETGLOBAL R9 K1        ; R9 := 0x33bdd652
 61 [-]: GETTABLE  R9 R9 K2     ; R82 := R9[0x23d5322f]
 62 [-]: MOVE      R10 R0       ; R10 := R0
 63 [-]: NEWTABLE  R11 0 2      ; R11 := {}
 64 [-]: GETGLOBAL R12 K4       ; R12 := 0xae91e43b
 65 [-]: SELF      R12 R12 K5   ; R13 := R12; R12 := R12[0x42b04007]
 66 [-]: LOADK     R14 K19      ; R14 := "/Lotus/Language/Menu/Composition_SaveSlot"
 67 [-]: LOADBOOL  R15 0 0      ; R15 := false
 68 [-]: NEWTABLE  R16 0 1      ; R16 := {}
 69 [-]: LEN       R17 R2       ; R17 := # R2
 70 [-]: SUB       R17 R1 R17   ; R17 := R1 - R17
 71 [-]: SETTABLE  R16 K20 R17  ; R16["COUNT"] := R17
 72 [-]: CALL      R12 5 2      ; R12 := R12(R13,R14,R15,R16)
 73 [-]: SETTABLE  R11 K3 R12   ; R11["mName"] := R12
 74 [-]: GETGLOBAL R12 K21      ; R12 := 0x6c97a788
 75 [-]: GETTABLE  R12 R12 K22  ; R82 := R12[0xeca1b641]
 76 [-]: CALL      R12 1 2      ; R12 := R12()
 77 [-]: SETTABLE  R11 K18 R12  ; R11["mSong"] := R12
 78 [-]: CALL      R9 3 1       ; R9(R10,R11)
 79 [-]: RETURN    R0 2         ; return R0
 80 [-]: RETURN    R0 1         ; return 


; Function #22.3:
;
; Name:            
; Defined at line: 507
; #Upvalues:       6
; #Parameters:     1
; Is_vararg:       0
; Max Stack Size:  28

  1 [-]: GETGLOBAL R1 K0        ; R1 := 0x7b998233
  2 [-]: GETUPVAL  R2 U0        ; R2 := U0
  3 [-]: CALL      R1 2 2       ; R1 := R1(R2)
  4 [-]: TEST      R1 0         ; if not R1 then PC := 22
  5 [-]: JMP       22           ; PC := 22
  6 [-]: GETGLOBAL R1 K1        ; R1 := 0x89326c93
  7 [-]: SELF      R1 R1 K2     ; R2 := R1; R1 := R1[0x05909209]
  8 [-]: GETGLOBAL R3 K3        ; R3 := 0x53b33231
  9 [-]: GETGLOBAL R4 K4        ; R4 := ZERO_VECTOR
 10 [-]: GETGLOBAL R5 K5        ; R5 := ZERO_ROTATION
 11 [-]: CALL      R1 5 2       ; R1 := R1(R2,R3,R4,R5)
 12 [-]: SETUPVAL  R1 U0        ; U82 := 
 13 [-]: GETGLOBAL R1 K0        ; R1 := 0x7b998233
 14 [-]: GETUPVAL  R2 U0        ; R2 := U0
 15 [-]: CALL      R1 2 2       ; R1 := R1(R2)
 16 [-]: TEST      R1 1         ; if R1 then PC := 22
 17 [-]: JMP       22           ; PC := 22
 18 [-]: GETUPVAL  R1 U0        ; R1 := U0
 19 [-]: SELF      R1 R1 K6     ; R2 := R1; R1 := R1[0x55e9211c]
 20 [-]: LOADBOOL  R3 1 0       ; R3 := true
 21 [-]: CALL      R1 3 1       ; R1(R2,R3)
 22 [-]: GETGLOBAL R1 K0        ; R1 := 0x7b998233
 23 [-]: GETUPVAL  R2 U0        ; R2 := U0
 24 [-]: CALL      R1 2 2       ; R1 := R1(R2)
 25 [-]: TEST      R1 1         ; if R1 then PC := 153
 26 [-]: JMP       153          ; PC := 153
 27 [-]: GETTABLE  R1 R0 K7     ; R1 := R0["mSong"]
 28 [-]: EQ        1 R1 K8      ; if R1 == nil then PC := 66
 29 [-]: JMP       66           ; PC := 66
 30 [-]: GETTABLE  R1 R0 K7     ; R1 := R0["mSong"]
 31 [-]: GETTABLE  R1 R1 K9     ; R1 := R1["mItemId"]
 32 [-]: SELF      R1 R1 K10    ; R2 := R1; R1 := R1[0x262a8b80]
 33 [-]: CALL      R1 2 2       ; R1 := R1(R2)
 34 [-]: TEST      R1 0         ; if not R1 then PC := 37
 35 [-]: JMP       37           ; PC := 37
 36 [-]: RETURN    R0 1         ; return 
 37 [-]: NEWTABLE  R1 0 0       ; R1 := {}
 38 [-]: LOADK     R2 0         ; R2 := 0.000000
 39 [-]: LOADK     R3 2         ; R3 := 2.000000
 40 [-]: LOADK     R4 1         ; R4 := 1.000000
 41 [-]: FORPREP   R2 58        ; R2 -= R4; PC := 58
 42 [-]: GETTABLE  R6 R0 K7     ; R6 := R0["mSong"]
 43 [-]: SELF      R6 R6 K12    ; R7 := R6; R6 := R6[0x4d7a0caf]
 44 [-]: MOVE      R8 R5        ; R8 := R5
 45 [-]: CALL      R6 3 2       ; R6 := R6(R7,R8)
 46 [-]: GETGLOBAL R7 K0        ; R7 := 0x7b998233
 47 [-]: MOVE      R8 R6        ; R8 := R6
 48 [-]: CALL      R7 2 2       ; R7 := R7(R8)
 49 [-]: TEST      R7 1         ; if R7 then PC := 58
 50 [-]: JMP       58           ; PC := 58
 51 [-]: GETGLOBAL R7 K13       ; R7 := 0x33bdd652
 52 [-]: GETTABLE  R7 R7 K14    ; R82 := R7[0x23d5322f]
 53 [-]: MOVE      R8 R1        ; R8 := R1
 54 [-]: NEWTABLE  R9 0 2       ; R9 := {}
 55 [-]: SETTABLE  R9 K15 R5    ; R9["NoteType"] := R5
 56 [-]: SETTABLE  R9 K16 R6    ; R9["NotePack"] := R6
 57 [-]: CALL      R7 3 1       ; R7(R8,R9)
 58 [-]: FORLOOP   R2 42        ; R2 += R4; if R2 <= R3 then begin PC := 42; R5 := R2 end
 59 [-]: GETUPVAL  R7 U1        ; R7 := U1
 60 [-]: GETUPVAL  R8 U0        ; R8 := U0
 61 [-]: MOVE      R9 R1        ; R9 := R1
 62 [-]: GETTABLE  R10 R0 K7    ; R10 := R0["mSong"]
 63 [-]: GETTABLE  R10 R10 K17  ; R10 := R10["mFingerPrint"]
 64 [-]: CALL      R7 4 1       ; R7(R8,R9,R10)
 65 [-]: JMP       135          ; PC := 135
 66 [-]: GETGLOBAL R7 K0        ; R7 := 0x7b998233
 67 [-]: GETUPVAL  R8 U2        ; R8 := U2
 68 [-]: CALL      R7 2 2       ; R7 := R7(R8)
 69 [-]: TEST      R7 0         ; if not R7 then PC := 72
 70 [-]: JMP       72           ; PC := 72
 71 [-]: RETURN    R0 1         ; return 
 72 [-]: GETUPVAL  R7 U2        ; R7 := U2
 73 [-]: SELF      R7 R7 K18    ; R8 := R7; R7 := R7[0xde321e6f]
 74 [-]: CALL      R7 2 2       ; R7 := R7(R8)
 75 [-]: GETGLOBAL R8 K0        ; R8 := 0x7b998233
 76 [-]: MOVE      R9 R7        ; R9 := R7
 77 [-]: CALL      R8 2 2       ; R8 := R8(R9)
 78 [-]: TEST      R8 0         ; if not R8 then PC := 81
 79 [-]: JMP       81           ; PC := 81
 80 [-]: RETURN    R0 1         ; return 
 81 [-]: SELF      R8 R7 K19    ; R9 := R7; R8 := R7[0xf7d48ee0]
 82 [-]: CALL      R8 2 2       ; R8 := R8(R9)
 83 [-]: GETGLOBAL R9 K0        ; R9 := 0x7b998233
 84 [-]: MOVE      R10 R8       ; R10 := R8
 85 [-]: CALL      R9 2 2       ; R9 := R9(R10)
 86 [-]: TEST      R9 0         ; if not R9 then PC := 89
 87 [-]: JMP       89           ; PC := 89
 88 [-]: RETURN    R0 1         ; return 
 89 [-]: SELF      R9 R8 K20    ; R10 := R8; R9 := R8[0x68d708a7]
 90 [-]: CALL      R9 2 2       ; R9 := R9(R10)
 91 [-]: SELF      R9 R9 K21    ; R10 := R9; R9 := R9[0xce6f9f03]
 92 [-]: GETUPVAL  R11 U3       ; R11 := U3
 93 [-]: GETTABLE  R11 R11 K22  ; R11 := R11["abilityIndex"]
 94 [-]: CALL      R9 3 2       ; R9 := R9(R10,R11)
 95 [-]: GETGLOBAL R10 K23      ; R10 := 0xb009bbc6
 96 [-]: GETGLOBAL R11 K3       ; R11 := 0x53b33231
 97 [-]: CALL      R10 2 2      ; R10 := R10(R11)
 98 [-]: GETUPVAL  R11 U4       ; R11 := U4
 99 [-]: GETTABLE  R11 R11 K24  ; R82 := R11[0x06d055f9]
100 [-]: GETTABLE  R12 R9 K25   ; R12 := R9["mHasFingerPrint"]
101 [-]: GETTABLE  R13 R9 K17   ; R13 := R9["mFingerPrint"]
102 [-]: SELF      R14 R10 K26  ; R15 := R10; R14 := R10[0x4dc40cc1]
103 [-]: CALL      R14 2 0      ; R14,... := R14(R15)
104 [-]: CALL      R11 0 2      ; R11 := R11(R12,...)
105 [-]: NEWTABLE  R12 0 0      ; R12 := {}
106 [-]: LOADK     R13 0        ; R13 := 0.000000
107 [-]: LOADK     R14 2        ; R14 := 2.000000
108 [-]: LOADK     R15 1        ; R15 := 1.000000
109 [-]: FORPREP   R13 129      ; R13 -= R15; PC := 129
110 [-]: GETGLOBAL R17 K13      ; R17 := 0x33bdd652
111 [-]: GETTABLE  R17 R17 K14  ; R82 := R17[0x23d5322f]
112 [-]: MOVE      R18 R12      ; R18 := R12
113 [-]: NEWTABLE  R19 0 2      ; R19 := {}
114 [-]: SETTABLE  R19 K15 R16  ; R19["NoteType"] := R16
115 [-]: GETUPVAL  R20 U4       ; R20 := U4
116 [-]: GETTABLE  R20 R20 K24  ; R82 := R20[0x06d055f9]
117 [-]: SELF      R21 R9 K27   ; R22 := R9; R21 := R9[0x017b5873]
118 [-]: MOVE      R23 R16      ; R23 := R16
119 [-]: CALL      R21 3 2      ; R21 := R21(R22,R23)
120 [-]: SELF      R22 R9 K12   ; R23 := R9; R22 := R9[0x4d7a0caf]
121 [-]: MOVE      R24 R16      ; R24 := R16
122 [-]: CALL      R22 3 2      ; R22 := R22(R23,R24)
123 [-]: SELF      R23 R10 K12  ; R24 := R10; R23 := R10[0x4d7a0caf]
124 [-]: MOVE      R25 R16      ; R25 := R16
125 [-]: CALL      R23 3 0      ; R23,... := R23(R24,R25)
126 [-]: CALL      R20 0 2      ; R20 := R20(R21,...)
127 [-]: SETTABLE  R19 K16 R20  ; R19["NotePack"] := R20
128 [-]: CALL      R17 3 1      ; R17(R18,R19)
129 [-]: FORLOOP   R13 110      ; R13 += R15; if R13 <= R14 then begin PC := 110; R16 := R13 end
130 [-]: GETUPVAL  R17 U1       ; R17 := U1
131 [-]: GETUPVAL  R18 U0       ; R18 := U0
132 [-]: MOVE      R19 R12      ; R19 := R12
133 [-]: MOVE      R20 R11      ; R20 := R11
134 [-]: CALL      R17 4 1      ; R17(R18,R19,R20)
135 [-]: GETUPVAL  R17 U5       ; R17 := U5
136 [-]: SELF      R17 R17 K28  ; R18 := R17; R17 := R17[0xe261aa96]
137 [-]: GETTABLE  R19 R0 K29   ; R19 := R0["mClipName"]
138 [-]: LOADK     R20 K30      ; R20 := "Label"
139 [-]: LOADK     R21 29       ; R21 := 29.000000
140 [-]: GETTABLE  R22 R0 K31   ; R22 := R0["mName"]
141 [-]: LOADK     R23 K32      ; R23 := "  "
142 [-]: GETGLOBAL R24 K33      ; R24 := 0xae91e43b
143 [-]: SELF      R24 R24 K34  ; R25 := R24; R24 := R24[0x42b04007]
144 [-]: LOADK     R26 K35      ; R26 := "<SPEAKER>"
145 [-]: LOADBOOL  R27 1 0      ; R27 := true
146 [-]: CALL      R24 4 2      ; R24 := R24(R25,R26,R27)
147 [-]: CONCAT    R22 R22 R24  ; R22 := R22 .. R23 .. R24
148 [-]: CALL      R17 6 1      ; R17(R18,R19,R20,R21,R22)
149 [-]: GETUPVAL  R17 U0       ; R17 := U0
150 [-]: SELF      R17 R17 K36  ; R18 := R17; R17 := R17[0x458592ad]
151 [-]: LOADK     R19 0        ; R19 := 0.000000
152 [-]: CALL      R17 3 1      ; R17(R18,R19)
153 [-]: RETURN    R0 1         ; return 


; Function #22.4:
;
; Name:            
; Defined at line: 567
; #Upvalues:       3
; #Parameters:     1
; Is_vararg:       0
; Max Stack Size:  7

  1 [-]: GETGLOBAL R1 K0        ; R1 := 0x7b998233
  2 [-]: GETUPVAL  R2 U0        ; R2 := U0
  3 [-]: CALL      R1 2 2       ; R1 := R1(R2)
  4 [-]: TEST      R1 1         ; if R1 then PC := 34
  5 [-]: JMP       34           ; PC := 34
  6 [-]: GETUPVAL  R1 U0        ; R1 := U0
  7 [-]: SELF      R1 R1 K1     ; R2 := R1; R1 := R1[0x55e9211c]
  8 [-]: LOADBOOL  R3 1 0       ; R3 := true
  9 [-]: CALL      R1 3 1       ; R1(R2,R3)
 10 [-]: GETTABLE  R1 R0 K2     ; R1 := R0["mClipName"]
 11 [-]: EQ        1 R1 K3      ; if R1 == nil then PC := 20
 12 [-]: JMP       20           ; PC := 20
 13 [-]: GETUPVAL  R1 U1        ; R1 := U1
 14 [-]: SELF      R1 R1 K4     ; R2 := R1; R1 := R1[0xe261aa96]
 15 [-]: GETTABLE  R3 R0 K2     ; R3 := R0["mClipName"]
 16 [-]: LOADK     R4 K5        ; R4 := "Label"
 17 [-]: LOADK     R5 29        ; R5 := 29.000000
 18 [-]: GETTABLE  R6 R0 K6     ; R6 := R0["mName"]
 19 [-]: CALL      R1 6 1       ; R1(R2,R3,R4,R5,R6)
 20 [-]: GETUPVAL  R1 U2        ; R1 := U2
 21 [-]: EQ        1 R1 K3      ; if R1 == nil then PC := 34
 22 [-]: JMP       34           ; PC := 34
 23 [-]: GETUPVAL  R1 U2        ; R1 := U2
 24 [-]: GETTABLE  R1 R1 K7     ; R1 := R1["IsLoading"]
 25 [-]: TEST      R1 0         ; if not R1 then PC := 34
 26 [-]: JMP       34           ; PC := 34
 27 [-]: GETUPVAL  R1 U2        ; R1 := U2
 28 [-]: GETTABLE  R1 R1 K8     ; R1 := R1["StepSequencer"]
 29 [-]: GETUPVAL  R2 U0        ; R2 := U0
 30 [-]: EQ        0 R1 R2      ; if R1 ~= R2 then PC := 34
 31 [-]: JMP       34           ; PC := 34
 32 [-]: LOADNIL   R1 R1        ; R1 := nil
 33 [-]: SETUPVAL  R1 U2        ; U82 := 
 34 [-]: RETURN    R0 1         ; return 


; Function #23:
;
; Name:            
; Defined at line: 583
; #Upvalues:       10
; #Parameters:     0
; Is_vararg:       0
; Max Stack Size:  14

  1 [-]: GETUPVAL  R0 U0        ; R0 := U0
  2 [-]: SELF      R0 R0 K0     ; R1 := R0; R0 := R0[0xde321e6f]
  3 [-]: CALL      R0 2 2       ; R0 := R0(R1)
  4 [-]: GETGLOBAL R1 K1        ; R1 := 0x7b998233
  5 [-]: MOVE      R2 R0        ; R2 := R0
  6 [-]: CALL      R1 2 2       ; R1 := R1(R2)
  7 [-]: TEST      R1 1         ; if R1 then PC := 54
  8 [-]: JMP       54           ; PC := 54
  9 [-]: SELF      R1 R0 K2     ; R2 := R0; R1 := R0[0xf7d48ee0]
 10 [-]: CALL      R1 2 2       ; R1 := R1(R2)
 11 [-]: GETGLOBAL R2 K1        ; R2 := 0x7b998233
 12 [-]: MOVE      R3 R1        ; R3 := R1
 13 [-]: CALL      R2 2 2       ; R2 := R2(R3)
 14 [-]: TEST      R2 1         ; if R2 then PC := 54
 15 [-]: JMP       54           ; PC := 54
 16 [-]: SELF      R2 R1 K3     ; R3 := R1; R2 := R1[0x68d708a7]
 17 [-]: CALL      R2 2 2       ; R2 := R2(R3)
 18 [-]: SELF      R2 R2 K4     ; R3 := R2; R2 := R2[0xce6f9f03]
 19 [-]: GETUPVAL  R4 U1        ; R4 := U1
 20 [-]: GETTABLE  R4 R4 K5     ; R4 := R4["abilityIndex"]
 21 [-]: CALL      R2 3 2       ; R2 := R2(R3,R4)
 22 [-]: LOADK     R3 0         ; R3 := 0.000000
 23 [-]: LOADK     R4 2         ; R4 := 2.000000
 24 [-]: LOADK     R5 1         ; R5 := 1.000000
 25 [-]: FORPREP   R3 53        ; R3 -= R5; PC := 53
 26 [-]: SELF      R7 R2 K7     ; R8 := R2; R7 := R2[0x017b5873]
 27 [-]: MOVE      R9 R6        ; R9 := R6
 28 [-]: CALL      R7 3 2       ; R7 := R7(R8,R9)
 29 [-]: TEST      R7 0         ; if not R7 then PC := 41
 30 [-]: JMP       41           ; PC := 41
 31 [-]: GETUPVAL  R7 U2        ; R7 := U2
 32 [-]: SELF      R7 R7 K8     ; R8 := R7; R7 := R7[0x6caac40b]
 33 [-]: MOVE      R9 R6        ; R9 := R6
 34 [-]: GETGLOBAL R10 K9       ; R10 := 0xb009bbc6
 35 [-]: SELF      R11 R2 K10   ; R12 := R2; R11 := R2[0x4d7a0caf]
 36 [-]: MOVE      R13 R6       ; R13 := R6
 37 [-]: CALL      R11 3 0      ; R11,... := R11(R12,R13)
 38 [-]: CALL      R10 0 0      ; R10,... := R10(R11,...)
 39 [-]: CALL      R7 0 1       ; R7(R8,...)
 40 [-]: JMP       53           ; PC := 53
 41 [-]: GETUPVAL  R7 U2        ; R7 := U2
 42 [-]: SELF      R7 R7 K8     ; R8 := R7; R7 := R7[0x6caac40b]
 43 [-]: MOVE      R9 R6        ; R9 := R6
 44 [-]: GETGLOBAL R10 K9       ; R10 := 0xb009bbc6
 45 [-]: GETUPVAL  R11 U2       ; R11 := U2
 46 [-]: SELF      R11 R11 K11  ; R12 := R11; R11 := R11[0xcde10c4a]
 47 [-]: CALL      R11 2 0      ; R11,... := R11(R12)
 48 [-]: CALL      R10 0 2      ; R10 := R10(R11,...)
 49 [-]: SELF      R10 R10 K10  ; R11 := R10; R10 := R10[0x4d7a0caf]
 50 [-]: MOVE      R12 R6       ; R12 := R6
 51 [-]: CALL      R10 3 0      ; R10,... := R10(R11,R12)
 52 [-]: CALL      R7 0 1       ; R7(R8,...)
 53 [-]: FORLOOP   R3 26        ; R3 += R5; if R3 <= R4 then begin PC := 26; R6 := R3 end
 54 [-]: GETUPVAL  R7 U2        ; R7 := U2
 55 [-]: SELF      R7 R7 K12    ; R8 := R7; R7 := R7[0x4148785c]
 56 [-]: GETUPVAL  R9 U3        ; R9 := U3
 57 [-]: CALL      R7 3 1       ; R7(R8,R9)
 58 [-]: GETGLOBAL R7 K1        ; R7 := 0x7b998233
 59 [-]: GETUPVAL  R8 U4        ; R8 := U4
 60 [-]: CALL      R7 2 2       ; R7 := R7(R8)
 61 [-]: TEST      R7 1         ; if R7 then PC := 68
 62 [-]: JMP       68           ; PC := 68
 63 [-]: GETUPVAL  R7 U4        ; R7 := U4
 64 [-]: SELF      R7 R7 K13    ; R8 := R7; R7 := R7[0xe4162eed]
 65 [-]: LOADK     R9 K14       ; R9 := "RedrawNotes"
 66 [-]: LOADK     R10 K15      ; R10 := ""
 67 [-]: CALL      R7 4 1       ; R7(R8,R9,R10)
 68 [-]: GETUPVAL  R7 U5        ; R7 := U5
 69 [-]: CALL      R7 1 1       ; R7()
 70 [-]: GETUPVAL  R7 U6        ; R7 := U6
 71 [-]: CALL      R7 1 1       ; R7()
 72 [-]: GETUPVAL  R7 U7        ; R7 := U7
 73 [-]: GETUPVAL  R8 U8        ; R8 := U8
 74 [-]: GETTABLE  R8 R8 K16    ; R8 := R8["looping"]
 75 [-]: CALL      R7 2 1       ; R7(R8)
 76 [-]: GETUPVAL  R7 U9        ; R7 := U9
 77 [-]: LOADBOOL  R8 0 0       ; R8 := false
 78 [-]: CALL      R7 2 1       ; R7(R8)
 79 [-]: RETURN    R0 1         ; return 


; Function #24:
;
; Name:            
; Defined at line: 611
; #Upvalues:       1
; #Parameters:     1
; Is_vararg:       0
; Max Stack Size:  3

  1 [-]: GETGLOBAL R1 K0        ; R1 := 0x03f57322
  2 [-]: MOVE      R2 R0        ; R2 := R0
  3 [-]: CALL      R1 2 2       ; R1 := R1(R2)
  4 [-]: EQ        0 R1 K2      ; if R1 ~= 4.000000 then PC := 8
  5 [-]: JMP       8            ; PC := 8
  6 [-]: GETUPVAL  R1 U0        ; R1 := U0
  7 [-]: CALL      R1 1 1       ; R1()
  8 [-]: RETURN    R0 1         ; return 


; Function #25:
;
; Name:            
; Defined at line: 617
; #Upvalues:       2
; #Parameters:     0
; Is_vararg:       0
; Max Stack Size:  3

  1 [-]: GETUPVAL  R0 U0        ; R0 := U0
  2 [-]: GETTABLE  R0 R0 K0     ; R0 := R0["inputBlocked"]
  3 [-]: TEST      R0 0         ; if not R0 then PC := 6
  4 [-]: JMP       6            ; PC := 6
  5 [-]: RETURN    R0 1         ; return 
  6 [-]: GETUPVAL  R0 U0        ; R0 := U0
  7 [-]: GETTABLE  R0 R0 K1     ; R0 := R0["dirty"]
  8 [-]: TEST      R0 0         ; if not R0 then PC := 15
  9 [-]: JMP       15           ; PC := 15
 10 [-]: GETUPVAL  R0 U1        ; R0 := U1
 11 [-]: GETTABLE  R0 R0 K2     ; R82 := R0[0xdedfded7]
 12 [-]: LOADK     R1 K3        ; R1 := "/Lotus/Language/Menu/Composition_ConfirmReload"
 13 [-]: LOADK     R2 K4        ; R2 := "ConfirmReload"
 14 [-]: CALL      R0 3 1       ; R0(R1,R2)
 15 [-]: RETURN    R0 1         ; return 


; Function #26:
;
; Name:            
; Defined at line: 627
; #Upvalues:       10
; #Parameters:     2
; Is_vararg:       0
; Max Stack Size:  36

  1 [-]: GETGLOBAL R2 K0        ; R2 := 0x7b998233
  2 [-]: MOVE      R3 R1        ; R3 := R1
  3 [-]: CALL      R2 2 2       ; R2 := R2(R3)
  4 [-]: TEST      R2 1         ; if R2 then PC := 16
  5 [-]: JMP       16           ; PC := 16
  6 [-]: GETUPVAL  R2 U0        ; R2 := U0
  7 [-]: GETUPVAL  R3 U1        ; R3 := U1
  8 [-]: NEWTABLE  R4 1 0       ; R4 := {}
  9 [-]: NEWTABLE  R5 0 2       ; R5 := {}
 10 [-]: SETTABLE  R5 K1 K3     ; R5["NoteType"] := 3.000000
 11 [-]: SETTABLE  R5 K4 R1     ; R5["NotePack"] := R1
 12 [-]: SETLIST   R4 1 1       ; R4[(1-1)*FPF+i] := R(4+i), 1 <= i <= 1
 13 [-]: MOVE      R5 R1        ; R5 := R1
 14 [-]: CALL      R2 4 1       ; R2(R3,R4,R5)
 15 [-]: JMP       179          ; PC := 179
 16 [-]: GETGLOBAL R2 K0        ; R2 := 0x7b998233
 17 [-]: MOVE      R3 R0        ; R3 := R0
 18 [-]: CALL      R2 2 2       ; R2 := R2(R3)
 19 [-]: TEST      R2 1         ; if R2 then PC := 128
 20 [-]: JMP       128          ; PC := 128
 21 [-]: NEWTABLE  R2 0 0       ; R2 := {}
 22 [-]: GETUPVAL  R3 U2        ; R3 := U2
 23 [-]: SELF      R3 R3 K5     ; R4 := R3; R3 := R3[0x25a6e75e]
 24 [-]: CALL      R3 2 2       ; R3 := R3(R4)
 25 [-]: SELF      R3 R3 K6     ; R4 := R3; R3 := R3[0xd8dfa041]
 26 [-]: CALL      R3 2 2       ; R3 := R3(R4)
 27 [-]: LOADK     R4 1         ; R4 := 1.000000
 28 [-]: LEN       R5 R3        ; R5 := # R3
 29 [-]: LOADK     R6 1         ; R6 := 1.000000
 30 [-]: FORPREP   R4 44        ; R4 -= R6; PC := 44
 31 [-]: GETTABLE  R8 R3 R7     ; R8 := R3[R7]
 32 [-]: GETTABLE  R8 R8 K7     ; R8 := R8["mItemType"]
 33 [-]: SELF      R8 R8 K8     ; R9 := R8; R8 := R8[0xf2deaf69]
 34 [-]: GETGLOBAL R10 K9       ; R10 := gNotePackType
 35 [-]: CALL      R8 3 2       ; R8 := R8(R9,R10)
 36 [-]: TEST      R8 0         ; if not R8 then PC := 44
 37 [-]: JMP       44           ; PC := 44
 38 [-]: GETGLOBAL R8 K10       ; R8 := 0x33bdd652
 39 [-]: GETTABLE  R8 R8 K11    ; R82 := R8[0x23d5322f]
 40 [-]: MOVE      R9 R2        ; R9 := R2
 41 [-]: GETTABLE  R10 R3 R7    ; R10 := R3[R7]
 42 [-]: GETTABLE  R10 R10 K7   ; R10 := R10["mItemType"]
 43 [-]: CALL      R8 3 1       ; R8(R9,R10)
 44 [-]: FORLOOP   R4 31        ; R4 += R6; if R4 <= R5 then begin PC := 31; R7 := R4 end
 45 [-]: GETGLOBAL R8 K12       ; R8 := 0xb009bbc6
 46 [-]: GETUPVAL  R9 U1        ; R9 := U1
 47 [-]: SELF      R9 R9 K13    ; R10 := R9; R9 := R9[0xcde10c4a]
 48 [-]: CALL      R9 2 0       ; R9,... := R9(R10)
 49 [-]: CALL      R8 0 2       ; R8 := R8(R9,...)
 50 [-]: NEWTABLE  R9 0 0       ; R9 := {}
 51 [-]: LOADBOOL  R10 0 0      ; R10 := false
 52 [-]: LOADK     R11 0        ; R11 := 0.000000
 53 [-]: LOADK     R12 2        ; R12 := 2.000000
 54 [-]: LOADK     R13 1        ; R13 := 1.000000
 55 [-]: FORPREP   R11 96       ; R11 -= R13; PC := 96
 56 [-]: SELF      R15 R0 K14   ; R16 := R0; R15 := R0[0x4d7a0caf]
 57 [-]: MOVE      R17 R14      ; R17 := R14
 58 [-]: CALL      R15 3 2      ; R15 := R15(R16,R17)
 59 [-]: GETGLOBAL R16 K0       ; R16 := 0x7b998233
 60 [-]: MOVE      R17 R15      ; R17 := R15
 61 [-]: CALL      R16 2 2      ; R16 := R16(R17)
 62 [-]: TEST      R16 1        ; if R16 then PC := 96
 63 [-]: JMP       96           ; PC := 96
 64 [-]: SELF      R16 R8 K14   ; R17 := R8; R16 := R8[0x4d7a0caf]
 65 [-]: MOVE      R18 R14      ; R18 := R14
 66 [-]: CALL      R16 3 2      ; R16 := R16(R17,R18)
 67 [-]: SELF      R16 R16 K13  ; R17 := R16; R16 := R16[0xcde10c4a]
 68 [-]: CALL      R16 2 2      ; R16 := R16(R17)
 69 [-]: EQ        1 R15 R16    ; if R15 == R16 then PC := 72
 70 [-]: JMP       72           ; PC := 72
 71 [-]: LOADBOOL  R16 0 1      ; R16 := false; PC := 72
 72 [-]: LOADBOOL  R16 1 0      ; R16 := true
 73 [-]: TEST      R16 1        ; if R16 then PC := 85
 74 [-]: JMP       85           ; PC := 85
 75 [-]: GETGLOBAL R17 K15      ; R17 := 0xc8802016
 76 [-]: MOVE      R18 R2       ; R18 := R2
 77 [-]: CALL      R17 2 4      ; R17,R18,R19 := R17(R18)
 78 [-]: JMP       83           ; PC := 83
 79 [-]: EQ        0 R15 R21    ; if R15 ~= R21 then PC := 83
 80 [-]: JMP       83           ; PC := 83
 81 [-]: LOADBOOL  R16 1 0      ; R16 := true
 82 [-]: JMP       85           ; PC := 85
 83 [-]: TFORLOOP  R17 2        ; R20,R21 :=  R17(R18,R19); if R20 ~= nil then begin PC = 79; R19 := R20 end
 84 [-]: JMP       79           ; PC := 79
 85 [-]: TEST      R16 0        ; if not R16 then PC := 95
 86 [-]: JMP       95           ; PC := 95
 87 [-]: GETGLOBAL R22 K10      ; R22 := 0x33bdd652
 88 [-]: GETTABLE  R22 R22 K11  ; R82 := R22[0x23d5322f]
 89 [-]: MOVE      R23 R9       ; R23 := R9
 90 [-]: NEWTABLE  R24 0 2      ; R24 := {}
 91 [-]: SETTABLE  R24 K1 R14   ; R24["NoteType"] := R14
 92 [-]: SETTABLE  R24 K4 R15   ; R24["NotePack"] := R15
 93 [-]: CALL      R22 3 1      ; R22(R23,R24)
 94 [-]: JMP       96           ; PC := 96
 95 [-]: LOADBOOL  R10 1 0      ; R10 := true
 96 [-]: FORLOOP   R11 56       ; R11 += R13; if R11 <= R12 then begin PC := 56; R14 := R11 end
 97 [-]: TEST      R10 0        ; if not R10 then PC := 103
 98 [-]: JMP       103          ; PC := 103
 99 [-]: GETUPVAL  R22 U3       ; R22 := U3
100 [-]: GETTABLE  R22 R22 K16  ; R82 := R22[0xe0cba3ca]
101 [-]: LOADK     R23 K17      ; R23 := "/Lotus/Language/Menu/Composition_NotePacksNotOwnedError"
102 [-]: CALL      R22 2 1      ; R22(R23)
103 [-]: LEN       R22 R9       ; R22 := # R9
104 [-]: EQ        0 R22 K18    ; if R22 ~= 0.000000 then PC := 122
105 [-]: JMP       122          ; PC := 122
106 [-]: LOADK     R22 0        ; R22 := 0.000000
107 [-]: LOADK     R23 2        ; R23 := 2.000000
108 [-]: LOADK     R24 1        ; R24 := 1.000000
109 [-]: FORPREP   R22 121      ; R22 -= R24; PC := 121
110 [-]: GETGLOBAL R26 K10      ; R26 := 0x33bdd652
111 [-]: GETTABLE  R26 R26 K11  ; R82 := R26[0x23d5322f]
112 [-]: MOVE      R27 R9       ; R27 := R9
113 [-]: NEWTABLE  R28 0 2      ; R28 := {}
114 [-]: SETTABLE  R28 K1 R25   ; R28["NoteType"] := R25
115 [-]: GETUPVAL  R29 U1       ; R29 := U1
116 [-]: SELF      R29 R29 K14  ; R30 := R29; R29 := R29[0x4d7a0caf]
117 [-]: MOVE      R31 R25      ; R31 := R25
118 [-]: CALL      R29 3 2      ; R29 := R29(R30,R31)
119 [-]: SETTABLE  R28 K4 R29   ; R28["NotePack"] := R29
120 [-]: CALL      R26 3 1      ; R26(R27,R28)
121 [-]: FORLOOP   R22 110      ; R22 += R24; if R22 <= R23 then begin PC := 110; R25 := R22 end
122 [-]: GETUPVAL  R26 U0       ; R26 := U0
123 [-]: GETUPVAL  R27 U1       ; R27 := U1
124 [-]: MOVE      R28 R9       ; R28 := R9
125 [-]: GETTABLE  R29 R0 K19   ; R29 := R0["mFingerPrint"]
126 [-]: CALL      R26 4 1      ; R26(R27,R28,R29)
127 [-]: JMP       179          ; PC := 179
128 [-]: GETGLOBAL R26 K12      ; R26 := 0xb009bbc6
129 [-]: GETUPVAL  R27 U1       ; R27 := U1
130 [-]: SELF      R27 R27 K13  ; R28 := R27; R27 := R27[0xcde10c4a]
131 [-]: CALL      R27 2 0      ; R27,... := R27(R28)
132 [-]: CALL      R26 0 2      ; R26 := R26(R27,...)
133 [-]: LOADK     R27 0        ; R27 := 0.000000
134 [-]: LOADK     R28 2        ; R28 := 2.000000
135 [-]: LOADK     R29 1        ; R29 := 1.000000
136 [-]: FORPREP   R27 150      ; R27 -= R29; PC := 150
137 [-]: SELF      R31 R26 K14  ; R32 := R26; R31 := R26[0x4d7a0caf]
138 [-]: MOVE      R33 R30      ; R33 := R30
139 [-]: CALL      R31 3 2      ; R31 := R31(R32,R33)
140 [-]: GETGLOBAL R32 K0       ; R32 := 0x7b998233
141 [-]: MOVE      R33 R31      ; R33 := R31
142 [-]: CALL      R32 2 2      ; R32 := R32(R33)
143 [-]: TEST      R32 1        ; if R32 then PC := 150
144 [-]: JMP       150          ; PC := 150
145 [-]: GETUPVAL  R32 U1       ; R32 := U1
146 [-]: SELF      R32 R32 K20  ; R33 := R32; R32 := R32[0x6caac40b]
147 [-]: MOVE      R34 R30      ; R34 := R30
148 [-]: MOVE      R35 R31      ; R35 := R31
149 [-]: CALL      R32 4 1      ; R32(R33,R34,R35)
150 [-]: FORLOOP   R27 137      ; R27 += R29; if R27 <= R28 then begin PC := 137; R30 := R27 end
151 [-]: GETUPVAL  R32 U1       ; R32 := U1
152 [-]: SELF      R32 R32 K21  ; R33 := R32; R32 := R32[0x4148785c]
153 [-]: GETUPVAL  R34 U1       ; R34 := U1
154 [-]: SELF      R34 R34 K22  ; R35 := R34; R34 := R34[0x4dc40cc1]
155 [-]: CALL      R34 2 0      ; R34,... := R34(R35)
156 [-]: CALL      R32 0 1      ; R32(R33,...)
157 [-]: GETUPVAL  R32 U1       ; R32 := U1
158 [-]: SELF      R32 R32 K23  ; R33 := R32; R32 := R32[0x458592ad]
159 [-]: LOADK     R34 0        ; R34 := 0.000000
160 [-]: CALL      R32 3 1      ; R32(R33,R34)
161 [-]: GETGLOBAL R32 K0       ; R32 := 0x7b998233
162 [-]: GETUPVAL  R33 U4       ; R33 := U4
163 [-]: CALL      R32 2 2      ; R32 := R32(R33)
164 [-]: TEST      R32 1        ; if R32 then PC := 171
165 [-]: JMP       171          ; PC := 171
166 [-]: GETUPVAL  R32 U4       ; R32 := U4
167 [-]: SELF      R32 R32 K24  ; R33 := R32; R32 := R32[0xe4162eed]
168 [-]: LOADK     R34 K25      ; R34 := "RedrawNotes"
169 [-]: LOADK     R35 K26      ; R35 := ""
170 [-]: CALL      R32 4 1      ; R32(R33,R34,R35)
171 [-]: GETUPVAL  R32 U5       ; R32 := U5
172 [-]: CALL      R32 1 1      ; R32()
173 [-]: GETUPVAL  R32 U6       ; R32 := U6
174 [-]: CALL      R32 1 1      ; R32()
175 [-]: GETUPVAL  R32 U7       ; R32 := U7
176 [-]: GETUPVAL  R33 U8       ; R33 := U8
177 [-]: GETTABLE  R33 R33 K27  ; R33 := R33["looping"]
178 [-]: CALL      R32 2 1      ; R32(R33)
179 [-]: GETUPVAL  R32 U9       ; R32 := U9
180 [-]: LOADBOOL  R33 1 0      ; R33 := true
181 [-]: CALL      R32 2 1      ; R32(R33)
182 [-]: RETURN    R0 1         ; return 


; Function #27:
;
; Name:            
; Defined at line: 701
; #Upvalues:       8
; #Parameters:     0
; Is_vararg:       0
; Max Stack Size:  5

  1 [-]: GETUPVAL  R0 U0        ; R0 := U0
  2 [-]: GETTABLE  R0 R0 K0     ; R0 := R0["inputBlocked"]
  3 [-]: TEST      R0 0         ; if not R0 then PC := 6
  4 [-]: JMP       6            ; PC := 6
  5 [-]: RETURN    R0 1         ; return 
  6 [-]: GETGLOBAL R0 K1        ; R0 := 0x7b998233
  7 [-]: GETGLOBAL R1 K2        ; R1 := 0x08a5afb4
  8 [-]: CALL      R0 2 2       ; R0 := R0(R1)
  9 [-]: TEST      R0 0         ; if not R0 then PC := 12
 10 [-]: JMP       12           ; PC := 12
 11 [-]: RETURN    R0 1         ; return 
 12 [-]: GETGLOBAL R0 K1        ; R0 := 0x7b998233
 13 [-]: GETUPVAL  R1 U1        ; R1 := U1
 14 [-]: CALL      R0 2 2       ; R0 := R0(R1)
 15 [-]: TEST      R0 1         ; if R0 then PC := 20
 16 [-]: JMP       20           ; PC := 20
 17 [-]: GETUPVAL  R0 U1        ; R0 := U1
 18 [-]: SELF      R0 R0 K3     ; R1 := R0; R0 := R0[0x32302b4a]
 19 [-]: CALL      R0 2 1       ; R0(R1)
 20 [-]: GETGLOBAL R0 K4        ; R0 := 0xae91e43b
 21 [-]: SELF      R0 R0 K5     ; R1 := R0; R0 := R0[0x1fd6abd0]
 22 [-]: GETGLOBAL R2 K2        ; R2 := 0x08a5afb4
 23 [-]: CALL      R0 3 2       ; R0 := R0(R1,R2)
 24 [-]: SETUPVAL  R0 U1        ; U82 := 
 25 [-]: GETGLOBAL R0 K1        ; R0 := 0x7b998233
 26 [-]: GETUPVAL  R1 U1        ; R1 := U1
 27 [-]: CALL      R0 2 2       ; R0 := R0(R1)
 28 [-]: TEST      R0 0         ; if not R0 then PC := 31
 29 [-]: JMP       31           ; PC := 31
 30 [-]: RETURN    R0 1         ; return 
 31 [-]: GETUPVAL  R0 U1        ; R0 := U1
 32 [-]: SELF      R0 R0 K6     ; R1 := R0; R0 := R0[0xe4162eed]
 33 [-]: LOADK     R2 K7        ; R2 := "SetTitle"
 34 [-]: LOADK     R3 K8        ; R3 := "/Lotus/Language/Menu/Composition_LoadSong"
 35 [-]: CALL      R0 4 1       ; R0(R1,R2,R3)
 36 [-]: GETUPVAL  R0 U2        ; R0 := U2
 37 [-]: SELF      R0 R0 K9     ; R1 := R0; R0 := R0[0x55e9211c]
 38 [-]: LOADBOOL  R2 1 0       ; R2 := true
 39 [-]: CALL      R0 3 1       ; R0(R1,R2)
 40 [-]: LOADNIL   R0 R0        ; R0 := nil
 41 [-]: GETGLOBAL R1 K10       ; R1 := _T
 42 [-]: CLOSURE   R2 0         ; R2 := closure(Function #27.1)
 43 [-]: MOVE      R0 R0        ; R0 := R0
 44 [-]: GETUPVAL  R0 U3        ; R0 := U3
 45 [-]: GETUPVAL  R0 U2        ; R0 := U2
 46 [-]: GETUPVAL  R0 U0        ; R0 := U0
 47 [-]: GETUPVAL  R0 U4        ; R0 := U4
 48 [-]: SETTABLE  R1 K11 R2    ; R1["SongSelectionDone"] := R2
 49 [-]: GETUPVAL  R1 U1        ; R1 := U1
 50 [-]: SELF      R1 R1 K6     ; R2 := R1; R1 := R1[0xe4162eed]
 51 [-]: LOADK     R3 K12       ; R3 := "SetCallBack"
 52 [-]: LOADK     R4 K11       ; R4 := "SongSelectionDone"
 53 [-]: CALL      R1 4 1       ; R1(R2,R3,R4)
 54 [-]: GETGLOBAL R1 K10       ; R1 := _T
 55 [-]: CLOSURE   R2 1         ; R2 := closure(Function #27.2)
 56 [-]: GETUPVAL  R0 U5        ; R0 := U5
 57 [-]: GETUPVAL  R0 U6        ; R0 := U6
 58 [-]: SETTABLE  R1 K13 R2    ; R1["GetSongList"] := R2
 59 [-]: GETUPVAL  R1 U1        ; R1 := U1
 60 [-]: SELF      R1 R1 K6     ; R2 := R1; R1 := R1[0xe4162eed]
 61 [-]: LOADK     R3 K14       ; R3 := "SetElementsFunction"
 62 [-]: LOADK     R4 K13       ; R4 := "GetSongList"
 63 [-]: CALL      R1 4 1       ; R1(R2,R3,R4)
 64 [-]: GETGLOBAL R1 K10       ; R1 := _T
 65 [-]: CLOSURE   R2 2         ; R2 := closure(Function #27.3)
 66 [-]: MOVE      R0 R0        ; R0 := R0
 67 [-]: GETUPVAL  R0 U7        ; R0 := U7
 68 [-]: GETUPVAL  R0 U2        ; R0 := U2
 69 [-]: GETUPVAL  R0 U1        ; R0 := U1
 70 [-]: SETTABLE  R1 K15 R2    ; R1["OnSongFocused"] := R2
 71 [-]: GETUPVAL  R1 U1        ; R1 := U1
 72 [-]: SELF      R1 R1 K6     ; R2 := R1; R1 := R1[0xe4162eed]
 73 [-]: LOADK     R3 K16       ; R3 := "SetOnFocusedCallback"
 74 [-]: LOADK     R4 K15       ; R4 := "OnSongFocused"
 75 [-]: CALL      R1 4 1       ; R1(R2,R3,R4)
 76 [-]: GETGLOBAL R1 K10       ; R1 := _T
 77 [-]: CLOSURE   R2 3         ; R2 := closure(Function #27.4)
 78 [-]: MOVE      R0 R0        ; R0 := R0
 79 [-]: GETUPVAL  R0 U1        ; R0 := U1
 80 [-]: GETUPVAL  R0 U3        ; R0 := U3
 81 [-]: SETTABLE  R1 K17 R2    ; R1["OnSongUnfocused"] := R2
 82 [-]: GETUPVAL  R1 U1        ; R1 := U1
 83 [-]: SELF      R1 R1 K6     ; R2 := R1; R1 := R1[0xe4162eed]
 84 [-]: LOADK     R3 K18       ; R3 := "SetOnUnfocusedCallback"
 85 [-]: LOADK     R4 K17       ; R4 := "OnSongUnfocused"
 86 [-]: CALL      R1 4 1       ; R1(R2,R3,R4)
 87 [-]: RETURN    R0 1         ; return 


; Function #27.1:
;
; Name:            
; Defined at line: 725
; #Upvalues:       5
; #Parameters:     1
; Is_vararg:       0
; Max Stack Size:  4

  1 [-]: GETGLOBAL R1 K0        ; R1 := _T
  2 [-]: SETTABLE  R1 K1 K2     ; R1["SongSelectionDone"] := nil
  3 [-]: GETGLOBAL R1 K0        ; R1 := _T
  4 [-]: SETTABLE  R1 K3 K2     ; R1["GetSongList"] := nil
  5 [-]: GETGLOBAL R1 K0        ; R1 := _T
  6 [-]: SETTABLE  R1 K4 K2     ; R1["OnSongFocused"] := nil
  7 [-]: GETGLOBAL R1 K0        ; R1 := _T
  8 [-]: SETTABLE  R1 K5 K2     ; R1["OnSongUnfocused"] := nil
  9 [-]: GETGLOBAL R1 K6        ; R1 := 0x7b998233
 10 [-]: GETUPVAL  R2 U0        ; R2 := U0
 11 [-]: CALL      R1 2 2       ; R1 := R1(R2)
 12 [-]: TEST      R1 1         ; if R1 then PC := 31
 13 [-]: JMP       31           ; PC := 31
 14 [-]: GETUPVAL  R1 U0        ; R1 := U0
 15 [-]: SELF      R1 R1 K7     ; R2 := R1; R1 := R1[0xa2880940]
 16 [-]: CALL      R1 2 1       ; R1(R2)
 17 [-]: GETUPVAL  R1 U1        ; R1 := U1
 18 [-]: EQ        1 R1 K2      ; if R1 == nil then PC := 31
 19 [-]: JMP       31           ; PC := 31
 20 [-]: GETUPVAL  R1 U1        ; R1 := U1
 21 [-]: GETTABLE  R1 R1 K8     ; R1 := R1["IsLoading"]
 22 [-]: TEST      R1 0         ; if not R1 then PC := 31
 23 [-]: JMP       31           ; PC := 31
 24 [-]: GETUPVAL  R1 U1        ; R1 := U1
 25 [-]: GETTABLE  R1 R1 K9     ; R1 := R1["StepSequencer"]
 26 [-]: GETUPVAL  R2 U0        ; R2 := U0
 27 [-]: EQ        0 R1 R2      ; if R1 ~= R2 then PC := 31
 28 [-]: JMP       31           ; PC := 31
 29 [-]: LOADNIL   R1 R1        ; R1 := nil
 30 [-]: SETUPVAL  R1 U1        ; U82 := 
 31 [-]: GETUPVAL  R1 U2        ; R1 := U2
 32 [-]: SELF      R1 R1 K10    ; R2 := R1; R1 := R1[0x55e9211c]
 33 [-]: GETUPVAL  R3 U3        ; R3 := U3
 34 [-]: GETTABLE  R3 R3 K11    ; R3 := R3["paused"]
 35 [-]: CALL      R1 3 1       ; R1(R2,R3)
 36 [-]: GETUPVAL  R1 U3        ; R1 := U3
 37 [-]: SETTABLE  R1 K12 K13   ; R1["inputBlocked"] := false
 38 [-]: GETTABLE  R1 R0 K14    ; R1 := R0[1.000000]
 39 [-]: EQ        1 R1 K2      ; if R1 == nil then PC := 47
 40 [-]: JMP       47           ; PC := 47
 41 [-]: GETUPVAL  R1 U4        ; R1 := U4
 42 [-]: GETTABLE  R2 R0 K14    ; R2 := R0[1.000000]
 43 [-]: GETTABLE  R2 R2 K15    ; R2 := R2["mSong"]
 44 [-]: GETTABLE  R3 R0 K14    ; R3 := R0[1.000000]
 45 [-]: GETTABLE  R3 R3 K16    ; R3 := R3["mNotePack"]
 46 [-]: CALL      R1 3 1       ; R1(R2,R3)
 47 [-]: RETURN    R0 1         ; return 


; Function #27.2:
;
; Name:            
; Defined at line: 749
; #Upvalues:       2
; #Parameters:     0
; Is_vararg:       0
; Max Stack Size:  29

  1 [-]: NEWTABLE  R0 0 0       ; R0 := {}
  2 [-]: GETGLOBAL R1 K0        ; R1 := 0xb009bbc6
  3 [-]: GETGLOBAL R2 K1        ; R2 := 0x53b33231
  4 [-]: CALL      R1 2 2       ; R1 := R1(R2)
  5 [-]: SELF      R1 R1 K2     ; R2 := R1; R1 := R1[0x4d7a0caf]
  6 [-]: LOADK     R3 3         ; R3 := 3.000000
  7 [-]: CALL      R1 3 2       ; R1 := R1(R2,R3)
  8 [-]: GETGLOBAL R2 K4        ; R2 := 0x7b998233
  9 [-]: MOVE      R3 R1        ; R3 := R1
 10 [-]: CALL      R2 2 2       ; R2 := R2(R3)
 11 [-]: TEST      R2 1         ; if R2 then PC := 24
 12 [-]: JMP       24           ; PC := 24
 13 [-]: GETGLOBAL R2 K5        ; R2 := 0x33bdd652
 14 [-]: GETTABLE  R2 R2 K6     ; R82 := R2[0x23d5322f]
 15 [-]: MOVE      R3 R0        ; R3 := R0
 16 [-]: NEWTABLE  R4 0 2       ; R4 := {}
 17 [-]: SELF      R5 R1 K8     ; R6 := R1; R5 := R1[0xd3a9d01f]
 18 [-]: CALL      R5 2 2       ; R5 := R5(R6)
 19 [-]: SELF      R5 R5 K9     ; R6 := R5; R5 := R5[0x6d604ba7]
 20 [-]: CALL      R5 2 2       ; R5 := R5(R6)
 21 [-]: SETTABLE  R4 K7 R5     ; R4["mName"] := R5
 22 [-]: SETTABLE  R4 K10 R1    ; R4["mNotePack"] := R1
 23 [-]: CALL      R2 3 1       ; R2(R3,R4)
 24 [-]: GETGLOBAL R2 K11       ; R2 := 0x639ad296
 25 [-]: SELF      R2 R2 K12    ; R3 := R2; R2 := R2[0x06ad312d]
 26 [-]: CALL      R2 2 2       ; R2 := R2(R3)
 27 [-]: GETUPVAL  R3 U0        ; R3 := U0
 28 [-]: SELF      R3 R3 K13    ; R4 := R3; R3 := R3[0x25a6e75e]
 29 [-]: CALL      R3 2 2       ; R3 := R3(R4)
 30 [-]: SELF      R3 R3 K14    ; R4 := R3; R3 := R3[0xd8dfa041]
 31 [-]: CALL      R3 2 2       ; R3 := R3(R4)
 32 [-]: LOADK     R4 1         ; R4 := 1.000000
 33 [-]: LEN       R5 R3        ; R5 := # R3
 34 [-]: LOADK     R6 1         ; R6 := 1.000000
 35 [-]: FORPREP   R4 73        ; R4 -= R6; PC := 73
 36 [-]: GETTABLE  R8 R3 R7     ; R8 := R3[R7]
 37 [-]: GETTABLE  R8 R8 K15    ; R8 := R8["mItemType"]
 38 [-]: SELF      R8 R8 K16    ; R9 := R8; R8 := R8[0xf2deaf69]
 39 [-]: GETGLOBAL R10 K17      ; R10 := gNotePackType
 40 [-]: CALL      R8 3 2       ; R8 := R8(R9,R10)
 41 [-]: TEST      R8 0         ; if not R8 then PC := 73
 42 [-]: JMP       73           ; PC := 73
 43 [-]: GETTABLE  R8 R3 R7     ; R8 := R3[R7]
 44 [-]: GETTABLE  R8 R8 K15    ; R8 := R8["mItemType"]
 45 [-]: EQ        1 R8 R1      ; if R8 == R1 then PC := 73
 46 [-]: JMP       73           ; PC := 73
 47 [-]: LOADK     R8 1         ; R8 := 1.000000
 48 [-]: LEN       R9 R2        ; R9 := # R2
 49 [-]: LOADK     R10 1        ; R10 := 1.000000
 50 [-]: FORPREP   R8 72        ; R8 -= R10; PC := 72
 51 [-]: GETTABLE  R12 R2 R11   ; R12 := R2[R11]
 52 [-]: SELF      R12 R12 K18  ; R13 := R12; R12 := R12[0xf278f8a1]
 53 [-]: CALL      R12 2 2      ; R12 := R12(R13)
 54 [-]: GETTABLE  R13 R3 R7    ; R13 := R3[R7]
 55 [-]: GETTABLE  R13 R13 K15  ; R13 := R13["mItemType"]
 56 [-]: EQ        0 R12 R13    ; if R12 ~= R13 then PC := 72
 57 [-]: JMP       72           ; PC := 72
 58 [-]: GETGLOBAL R12 K5       ; R12 := 0x33bdd652
 59 [-]: GETTABLE  R12 R12 K6   ; R82 := R12[0x23d5322f]
 60 [-]: MOVE      R13 R0       ; R13 := R0
 61 [-]: NEWTABLE  R14 0 2      ; R14 := {}
 62 [-]: GETTABLE  R15 R2 R11   ; R15 := R2[R11]
 63 [-]: SELF      R15 R15 K8   ; R16 := R15; R15 := R15[0xd3a9d01f]
 64 [-]: CALL      R15 2 2      ; R15 := R15(R16)
 65 [-]: SELF      R15 R15 K9   ; R16 := R15; R15 := R15[0x6d604ba7]
 66 [-]: CALL      R15 2 2      ; R15 := R15(R16)
 67 [-]: SETTABLE  R14 K7 R15   ; R14["mName"] := R15
 68 [-]: GETTABLE  R15 R3 R7    ; R15 := R3[R7]
 69 [-]: GETTABLE  R15 R15 K15  ; R15 := R15["mItemType"]
 70 [-]: SETTABLE  R14 K10 R15  ; R14["mNotePack"] := R15
 71 [-]: CALL      R12 3 1      ; R12(R13,R14)
 72 [-]: FORLOOP   R8 51        ; R8 += R10; if R8 <= R9 then begin PC := 51; R11 := R8 end
 73 [-]: FORLOOP   R4 36        ; R4 += R6; if R4 <= R5 then begin PC := 36; R7 := R4 end
 74 [-]: GETGLOBAL R12 K5       ; R12 := 0x33bdd652
 75 [-]: GETTABLE  R12 R12 K19  ; R82 := R12[0xf21b1d8e]
 76 [-]: MOVE      R13 R0       ; R13 := R0
 77 [-]: CLOSURE   R14 0        ; R14 := closure(Function #27.2.1)
 78 [-]: CALL      R12 3 1      ; R12(R13,R14)
 79 [-]: GETGLOBAL R12 K5       ; R12 := 0x33bdd652
 80 [-]: GETTABLE  R12 R12 K6   ; R82 := R12[0x23d5322f]
 81 [-]: MOVE      R13 R0       ; R13 := R0
 82 [-]: LOADK     R14 1        ; R14 := 1.000000
 83 [-]: NEWTABLE  R15 0 2      ; R15 := {}
 84 [-]: SETTABLE  R15 K7 K20   ; R15["mName"] := "/Lotus/Language/Menu/Composition_SoundPack"
 85 [-]: SETTABLE  R15 K21 K22  ; R15["mEnabled"] := false
 86 [-]: CALL      R12 4 1      ; R12(R13,R14,R15)
 87 [-]: GETUPVAL  R12 U1       ; R12 := U1
 88 [-]: GETTABLE  R12 R12 K23  ; R82 := R12[0x1be8b875]
 89 [-]: GETGLOBAL R13 K11      ; R13 := 0x639ad296
 90 [-]: CALL      R12 2 2      ; R12 := R12(R13)
 91 [-]: GETUPVAL  R13 U0       ; R13 := U0
 92 [-]: SELF      R13 R13 K13  ; R14 := R13; R13 := R13[0x25a6e75e]
 93 [-]: CALL      R13 2 2      ; R13 := R13(R14)
 94 [-]: SELF      R13 R13 K24  ; R14 := R13; R13 := R13[0xb139c962]
 95 [-]: CALL      R13 2 2      ; R13 := R13(R14)
 96 [-]: GETGLOBAL R14 K25      ; R14 := 0xc8802016
 97 [-]: MOVE      R15 R13      ; R15 := R13
 98 [-]: CALL      R14 2 4      ; R14,R15,R16 := R14(R15)
 99 [-]: JMP       124          ; PC := 124
100 [-]: LT        0 R12 R17    ; if R12 >= R17 then PC := 103
101 [-]: JMP       103          ; PC := 103
102 [-]: JMP       126          ; PC := 126
103 [-]: GETTABLE  R19 R18 K7   ; R19 := R18["mName"]
104 [-]: EQ        1 R19 K26    ; if R19 == nil then PC := 108
105 [-]: JMP       108          ; PC := 108
106 [-]: EQ        0 R19 K27    ; if R19 ~= "" then PC := 116
107 [-]: JMP       116          ; PC := 116
108 [-]: GETGLOBAL R20 K28      ; R20 := 0xae91e43b
109 [-]: SELF      R20 R20 K29  ; R21 := R20; R20 := R20[0x42b04007]
110 [-]: LOADK     R22 K30      ; R22 := "/Lotus/Language/Menu/Composition_SaveSong"
111 [-]: LOADBOOL  R23 0 0      ; R23 := false
112 [-]: NEWTABLE  R24 0 1      ; R24 := {}
113 [-]: SETTABLE  R24 K31 R17  ; R24["INDEX"] := R17
114 [-]: CALL      R20 5 2      ; R20 := R20(R21,R22,R23,R24)
115 [-]: MOVE      R19 R20      ; R19 := R20
116 [-]: GETGLOBAL R20 K5       ; R20 := 0x33bdd652
117 [-]: GETTABLE  R20 R20 K6   ; R82 := R20[0x23d5322f]
118 [-]: MOVE      R21 R0       ; R21 := R0
119 [-]: MOVE      R22 R17      ; R22 := R17
120 [-]: NEWTABLE  R23 0 2      ; R23 := {}
121 [-]: SETTABLE  R23 K7 R19   ; R23["mName"] := R19
122 [-]: SETTABLE  R23 K32 R18  ; R23["mSong"] := R18
123 [-]: CALL      R20 4 1      ; R20(R21,R22,R23)
124 [-]: TFORLOOP  R14 2        ; R17,R18 :=  R14(R15,R16); if R17 ~= nil then begin PC = 100; R16 := R17 end
125 [-]: JMP       100          ; PC := 100
126 [-]: GETGLOBAL R20 K5       ; R20 := 0x33bdd652
127 [-]: GETTABLE  R20 R20 K6   ; R82 := R20[0x23d5322f]
128 [-]: MOVE      R21 R0       ; R21 := R0
129 [-]: LOADK     R22 1        ; R22 := 1.000000
130 [-]: NEWTABLE  R23 0 1      ; R23 := {}
131 [-]: SETTABLE  R23 K7 K33   ; R23["mName"] := "/Lotus/Language/Menu/Composition_Default"
132 [-]: CALL      R20 4 1      ; R20(R21,R22,R23)
133 [-]: GETGLOBAL R20 K5       ; R20 := 0x33bdd652
134 [-]: GETTABLE  R20 R20 K6   ; R82 := R20[0x23d5322f]
135 [-]: MOVE      R21 R0       ; R21 := R0
136 [-]: LOADK     R22 1        ; R22 := 1.000000
137 [-]: NEWTABLE  R23 0 2      ; R23 := {}
138 [-]: SETTABLE  R23 K7 K34   ; R23["mName"] := "/Lotus/Language/Menu/Composition_Songs"
139 [-]: SETTABLE  R23 K21 K22  ; R23["mEnabled"] := false
140 [-]: CALL      R20 4 1      ; R20(R21,R22,R23)
141 [-]: GETGLOBAL R20 K25      ; R20 := 0xc8802016
142 [-]: MOVE      R21 R0       ; R21 := R0
143 [-]: CALL      R20 2 4      ; R20,R21,R22 := R20(R21)
144 [-]: JMP       152          ; PC := 152
145 [-]: GETGLOBAL R25 K28      ; R25 := 0xae91e43b
146 [-]: SELF      R25 R25 K29  ; R26 := R25; R25 := R25[0x42b04007]
147 [-]: GETTABLE  R27 R24 K7   ; R27 := R24["mName"]
148 [-]: LOADBOOL  R28 1 0      ; R28 := true
149 [-]: CALL      R25 4 2      ; R25 := R25(R26,R27,R28)
150 [-]: SETTABLE  R24 K7 R25   ; R24["mName"] := R25
151 [-]: SETTABLE  R24 K35 K36  ; R24["mTintIcons"] := true
152 [-]: TFORLOOP  R20 2        ; R23,R24 :=  R20(R21,R22); if R23 ~= nil then begin PC = 145; R22 := R23 end
153 [-]: JMP       145          ; PC := 145
154 [-]: RETURN    R0 2         ; return R0
155 [-]: RETURN    R0 1         ; return 


; Function #27.2.1:
;
; Name:            
; Defined at line: 768
; #Upvalues:       0
; #Parameters:     2
; Is_vararg:       0
; Max Stack Size:  4

  1 [-]: GETTABLE  R2 R0 K0     ; R2 := R0["mName"]
  2 [-]: GETTABLE  R3 R1 K0     ; R3 := R1["mName"]
  3 [-]: LT        1 R2 R3      ; if R2 < R3 then PC := 6
  4 [-]: JMP       6            ; PC := 6
  5 [-]: LOADBOOL  R2 0 1       ; R2 := false; PC := 6
  6 [-]: LOADBOOL  R2 1 0       ; R2 := true
  7 [-]: RETURN    R2 2         ; return R2
  8 [-]: RETURN    R0 1         ; return 


; Function #27.3:
;
; Name:            
; Defined at line: 801
; #Upvalues:       4
; #Parameters:     1
; Is_vararg:       0
; Max Stack Size:  23

  1 [-]: GETGLOBAL R1 K0        ; R1 := 0x7b998233
  2 [-]: GETUPVAL  R2 U0        ; R2 := U0
  3 [-]: CALL      R1 2 2       ; R1 := R1(R2)
  4 [-]: TEST      R1 0         ; if not R1 then PC := 22
  5 [-]: JMP       22           ; PC := 22
  6 [-]: GETGLOBAL R1 K1        ; R1 := 0x89326c93
  7 [-]: SELF      R1 R1 K2     ; R2 := R1; R1 := R1[0x05909209]
  8 [-]: GETGLOBAL R3 K3        ; R3 := 0x53b33231
  9 [-]: GETGLOBAL R4 K4        ; R4 := ZERO_VECTOR
 10 [-]: GETGLOBAL R5 K5        ; R5 := ZERO_ROTATION
 11 [-]: CALL      R1 5 2       ; R1 := R1(R2,R3,R4,R5)
 12 [-]: SETUPVAL  R1 U0        ; U82 := 
 13 [-]: GETGLOBAL R1 K0        ; R1 := 0x7b998233
 14 [-]: GETUPVAL  R2 U0        ; R2 := U0
 15 [-]: CALL      R1 2 2       ; R1 := R1(R2)
 16 [-]: TEST      R1 1         ; if R1 then PC := 22
 17 [-]: JMP       22           ; PC := 22
 18 [-]: GETUPVAL  R1 U0        ; R1 := U0
 19 [-]: SELF      R1 R1 K6     ; R2 := R1; R1 := R1[0x55e9211c]
 20 [-]: LOADBOOL  R3 1 0       ; R3 := true
 21 [-]: CALL      R1 3 1       ; R1(R2,R3)
 22 [-]: GETGLOBAL R1 K0        ; R1 := 0x7b998233
 23 [-]: GETUPVAL  R2 U0        ; R2 := U0
 24 [-]: CALL      R1 2 2       ; R1 := R1(R2)
 25 [-]: TEST      R1 1         ; if R1 then PC := 116
 26 [-]: JMP       116          ; PC := 116
 27 [-]: GETTABLE  R1 R0 K7     ; R1 := R0["mNotePack"]
 28 [-]: EQ        1 R1 K8      ; if R1 == nil then PC := 41
 29 [-]: JMP       41           ; PC := 41
 30 [-]: GETUPVAL  R1 U1        ; R1 := U1
 31 [-]: GETUPVAL  R2 U0        ; R2 := U0
 32 [-]: NEWTABLE  R3 1 0       ; R3 := {}
 33 [-]: NEWTABLE  R4 0 2       ; R4 := {}
 34 [-]: SETTABLE  R4 K9 K11    ; R4["NoteType"] := 3.000000
 35 [-]: GETTABLE  R5 R0 K7     ; R5 := R0["mNotePack"]
 36 [-]: SETTABLE  R4 K12 R5    ; R4["NotePack"] := R5
 37 [-]: SETLIST   R3 1 1       ; R3[(1-1)*FPF+i] := R(3+i), 1 <= i <= 1
 38 [-]: GETTABLE  R4 R0 K7     ; R4 := R0["mNotePack"]
 39 [-]: CALL      R1 4 1       ; R1(R2,R3,R4)
 40 [-]: JMP       98           ; PC := 98
 41 [-]: GETTABLE  R1 R0 K13    ; R1 := R0["mSong"]
 42 [-]: EQ        1 R1 K8      ; if R1 == nil then PC := 73
 43 [-]: JMP       73           ; PC := 73
 44 [-]: NEWTABLE  R1 0 0       ; R1 := {}
 45 [-]: LOADK     R2 0         ; R2 := 0.000000
 46 [-]: LOADK     R3 2         ; R3 := 2.000000
 47 [-]: LOADK     R4 1         ; R4 := 1.000000
 48 [-]: FORPREP   R2 65        ; R2 -= R4; PC := 65
 49 [-]: GETTABLE  R6 R0 K13    ; R6 := R0["mSong"]
 50 [-]: SELF      R6 R6 K14    ; R7 := R6; R6 := R6[0x4d7a0caf]
 51 [-]: MOVE      R8 R5        ; R8 := R5
 52 [-]: CALL      R6 3 2       ; R6 := R6(R7,R8)
 53 [-]: GETGLOBAL R7 K0        ; R7 := 0x7b998233
 54 [-]: MOVE      R8 R6        ; R8 := R6
 55 [-]: CALL      R7 2 2       ; R7 := R7(R8)
 56 [-]: TEST      R7 1         ; if R7 then PC := 65
 57 [-]: JMP       65           ; PC := 65
 58 [-]: GETGLOBAL R7 K15       ; R7 := 0x33bdd652
 59 [-]: GETTABLE  R7 R7 K16    ; R82 := R7[0x23d5322f]
 60 [-]: MOVE      R8 R1        ; R8 := R1
 61 [-]: NEWTABLE  R9 0 2       ; R9 := {}
 62 [-]: SETTABLE  R9 K9 R5     ; R9["NoteType"] := R5
 63 [-]: SETTABLE  R9 K12 R6    ; R9["NotePack"] := R6
 64 [-]: CALL      R7 3 1       ; R7(R8,R9)
 65 [-]: FORLOOP   R2 49        ; R2 += R4; if R2 <= R3 then begin PC := 49; R5 := R2 end
 66 [-]: GETUPVAL  R7 U1        ; R7 := U1
 67 [-]: GETUPVAL  R8 U0        ; R8 := U0
 68 [-]: MOVE      R9 R1        ; R9 := R1
 69 [-]: GETTABLE  R10 R0 K13   ; R10 := R0["mSong"]
 70 [-]: GETTABLE  R10 R10 K17  ; R10 := R10["mFingerPrint"]
 71 [-]: CALL      R7 4 1       ; R7(R8,R9,R10)
 72 [-]: JMP       98           ; PC := 98
 73 [-]: GETGLOBAL R7 K18       ; R7 := 0xb009bbc6
 74 [-]: GETGLOBAL R8 K3        ; R8 := 0x53b33231
 75 [-]: CALL      R7 2 2       ; R7 := R7(R8)
 76 [-]: LOADK     R8 0         ; R8 := 0.000000
 77 [-]: LOADK     R9 2         ; R9 := 2.000000
 78 [-]: LOADK     R10 1        ; R10 := 1.000000
 79 [-]: FORPREP   R8 87        ; R8 -= R10; PC := 87
 80 [-]: GETUPVAL  R12 U0       ; R12 := U0
 81 [-]: SELF      R12 R12 K19  ; R13 := R12; R12 := R12[0x6caac40b]
 82 [-]: MOVE      R14 R11      ; R14 := R11
 83 [-]: SELF      R15 R7 K14   ; R16 := R7; R15 := R7[0x4d7a0caf]
 84 [-]: MOVE      R17 R11      ; R17 := R11
 85 [-]: CALL      R15 3 0      ; R15,... := R15(R16,R17)
 86 [-]: CALL      R12 0 1      ; R12(R13,...)
 87 [-]: FORLOOP   R8 80        ; R8 += R10; if R8 <= R9 then begin PC := 80; R11 := R8 end
 88 [-]: GETUPVAL  R12 U0       ; R12 := U0
 89 [-]: SELF      R12 R12 K20  ; R13 := R12; R12 := R12[0x4148785c]
 90 [-]: GETUPVAL  R14 U2       ; R14 := U2
 91 [-]: SELF      R14 R14 K21  ; R15 := R14; R14 := R14[0x4dc40cc1]
 92 [-]: CALL      R14 2 0      ; R14,... := R14(R15)
 93 [-]: CALL      R12 0 1      ; R12(R13,...)
 94 [-]: GETUPVAL  R12 U0       ; R12 := U0
 95 [-]: SELF      R12 R12 K6   ; R13 := R12; R12 := R12[0x55e9211c]
 96 [-]: LOADBOOL  R14 0 0      ; R14 := false
 97 [-]: CALL      R12 3 1      ; R12(R13,R14)
 98 [-]: GETUPVAL  R12 U3       ; R12 := U3
 99 [-]: SELF      R12 R12 K22  ; R13 := R12; R12 := R12[0xe261aa96]
100 [-]: GETTABLE  R14 R0 K23   ; R14 := R0["mClipName"]
101 [-]: LOADK     R15 K24      ; R15 := "Label"
102 [-]: LOADK     R16 29       ; R16 := 29.000000
103 [-]: GETTABLE  R17 R0 K25   ; R17 := R0["mName"]
104 [-]: LOADK     R18 K26      ; R18 := "  "
105 [-]: GETGLOBAL R19 K27      ; R19 := 0xae91e43b
106 [-]: SELF      R19 R19 K28  ; R20 := R19; R19 := R19[0x42b04007]
107 [-]: LOADK     R21 K29      ; R21 := "<SPEAKER>"
108 [-]: LOADBOOL  R22 1 0      ; R22 := true
109 [-]: CALL      R19 4 2      ; R19 := R19(R20,R21,R22)
110 [-]: CONCAT    R17 R17 R19  ; R17 := R17 .. R18 .. R19
111 [-]: CALL      R12 6 1      ; R12(R13,R14,R15,R16,R17)
112 [-]: GETUPVAL  R12 U0       ; R12 := U0
113 [-]: SELF      R12 R12 K30  ; R13 := R12; R12 := R12[0x458592ad]
114 [-]: LOADK     R14 0        ; R14 := 0.000000
115 [-]: CALL      R12 3 1      ; R12(R13,R14)
116 [-]: RETURN    R0 1         ; return 


; Function #27.4:
;
; Name:            
; Defined at line: 839
; #Upvalues:       3
; #Parameters:     1
; Is_vararg:       0
; Max Stack Size:  7

  1 [-]: GETGLOBAL R1 K0        ; R1 := 0x7b998233
  2 [-]: GETUPVAL  R2 U0        ; R2 := U0
  3 [-]: CALL      R1 2 2       ; R1 := R1(R2)
  4 [-]: TEST      R1 1         ; if R1 then PC := 34
  5 [-]: JMP       34           ; PC := 34
  6 [-]: GETUPVAL  R1 U0        ; R1 := U0
  7 [-]: SELF      R1 R1 K1     ; R2 := R1; R1 := R1[0x55e9211c]
  8 [-]: LOADBOOL  R3 1 0       ; R3 := true
  9 [-]: CALL      R1 3 1       ; R1(R2,R3)
 10 [-]: GETTABLE  R1 R0 K2     ; R1 := R0["mClipName"]
 11 [-]: EQ        1 R1 K3      ; if R1 == nil then PC := 20
 12 [-]: JMP       20           ; PC := 20
 13 [-]: GETUPVAL  R1 U1        ; R1 := U1
 14 [-]: SELF      R1 R1 K4     ; R2 := R1; R1 := R1[0xe261aa96]
 15 [-]: GETTABLE  R3 R0 K2     ; R3 := R0["mClipName"]
 16 [-]: LOADK     R4 K5        ; R4 := "Label"
 17 [-]: LOADK     R5 29        ; R5 := 29.000000
 18 [-]: GETTABLE  R6 R0 K6     ; R6 := R0["mName"]
 19 [-]: CALL      R1 6 1       ; R1(R2,R3,R4,R5,R6)
 20 [-]: GETUPVAL  R1 U2        ; R1 := U2
 21 [-]: EQ        1 R1 K3      ; if R1 == nil then PC := 34
 22 [-]: JMP       34           ; PC := 34
 23 [-]: GETUPVAL  R1 U2        ; R1 := U2
 24 [-]: GETTABLE  R1 R1 K7     ; R1 := R1["IsLoading"]
 25 [-]: TEST      R1 0         ; if not R1 then PC := 34
 26 [-]: JMP       34           ; PC := 34
 27 [-]: GETUPVAL  R1 U2        ; R1 := U2
 28 [-]: GETTABLE  R1 R1 K8     ; R1 := R1["StepSequencer"]
 29 [-]: GETUPVAL  R2 U0        ; R2 := U0
 30 [-]: EQ        0 R1 R2      ; if R1 ~= R2 then PC := 34
 31 [-]: JMP       34           ; PC := 34
 32 [-]: LOADNIL   R1 R1        ; R1 := nil
 33 [-]: SETUPVAL  R1 U2        ; U82 := 
 34 [-]: RETURN    R0 1         ; return 


; Function #28:
;
; Name:            
; Defined at line: 855
; #Upvalues:       6
; #Parameters:     0
; Is_vararg:       0
; Max Stack Size:  6

  1 [-]: GETUPVAL  R0 U0        ; R0 := U0
  2 [-]: TEST      R0 0         ; if not R0 then PC := 5
  3 [-]: JMP       5            ; PC := 5
  4 [-]: RETURN    R0 1         ; return 
  5 [-]: GETGLOBAL R0 K0        ; R0 := 0x7b998233
  6 [-]: GETUPVAL  R1 U1        ; R1 := U1
  7 [-]: CALL      R0 2 2       ; R0 := R0(R1)
  8 [-]: TEST      R0 1         ; if R0 then PC := 42
  9 [-]: JMP       42           ; PC := 42
 10 [-]: GETUPVAL  R0 U1        ; R0 := U1
 11 [-]: SELF      R0 R0 K1     ; R1 := R0; R0 := R0[0x7027c544]
 12 [-]: LOADNIL   R2 R2        ; R2 := nil
 13 [-]: LOADBOOL  R3 0 0       ; R3 := false
 14 [-]: LOADK     R4 2         ; R4 := 2.000000
 15 [-]: LOADK     R5 2         ; R5 := 2.000000
 16 [-]: CALL      R0 6 1       ; R0(R1,R2,R3,R4,R5)
 17 [-]: GETUPVAL  R0 U1        ; R0 := U1
 18 [-]: SELF      R0 R0 K3     ; R1 := R0; R0 := R0[0x986d2ab8]
 19 [-]: GETGLOBAL R2 K4        ; R2 := 0x0469f296
 20 [-]: LOADK     R3 K5        ; R3 := "PanGlobalScale"
 21 [-]: CALL      R2 2 2       ; R2 := R2(R3)
 22 [-]: LOADK     R3 1         ; R3 := 1.000000
 23 [-]: LOADK     R4 0         ; R4 := 0.000000
 24 [-]: LOADK     R5 0         ; R5 := 0.000000
 25 [-]: CALL      R0 6 1       ; R0(R1,R2,R3,R4,R5)
 26 [-]: GETUPVAL  R0 U1        ; R0 := U1
 27 [-]: SELF      R0 R0 K6     ; R1 := R0; R0 := R0[0x044b7be8]
 28 [-]: GETUPVAL  R2 U2        ; R2 := U2
 29 [-]: CALL      R0 3 1       ; R0(R1,R2)
 30 [-]: GETUPVAL  R0 U1        ; R0 := U1
 31 [-]: SELF      R0 R0 K7     ; R1 := R0; R0 := R0[0xde321e6f]
 32 [-]: CALL      R0 2 2       ; R0 := R0(R1)
 33 [-]: GETGLOBAL R1 K0        ; R1 := 0x7b998233
 34 [-]: MOVE      R2 R0        ; R2 := R0
 35 [-]: CALL      R1 2 2       ; R1 := R1(R2)
 36 [-]: TEST      R1 1         ; if R1 then PC := 42
 37 [-]: JMP       42           ; PC := 42
 38 [-]: SELF      R1 R0 K8     ; R2 := R0; R1 := R0[0x4d29b3a5]
 39 [-]: LOADK     R3 0         ; R3 := 0.000000
 40 [-]: GETUPVAL  R4 U3        ; R4 := U3
 41 [-]: CALL      R1 4 1       ; R1(R2,R3,R4)
 42 [-]: GETGLOBAL R1 K0        ; R1 := 0x7b998233
 43 [-]: GETUPVAL  R2 U4        ; R2 := U4
 44 [-]: CALL      R1 2 2       ; R1 := R1(R2)
 45 [-]: TEST      R1 1         ; if R1 then PC := 50
 46 [-]: JMP       50           ; PC := 50
 47 [-]: GETUPVAL  R1 U4        ; R1 := U4
 48 [-]: SELF      R1 R1 K9     ; R2 := R1; R1 := R1[0x32302b4a]
 49 [-]: CALL      R1 2 1       ; R1(R2)
 50 [-]: GETGLOBAL R1 K0        ; R1 := 0x7b998233
 51 [-]: GETUPVAL  R2 U5        ; R2 := U5
 52 [-]: CALL      R1 2 2       ; R1 := R1(R2)
 53 [-]: TEST      R1 1         ; if R1 then PC := 58
 54 [-]: JMP       58           ; PC := 58
 55 [-]: GETUPVAL  R1 U5        ; R1 := U5
 56 [-]: SELF      R1 R1 K10    ; R2 := R1; R1 := R1[0xa2880940]
 57 [-]: CALL      R1 2 1       ; R1(R2)
 58 [-]: RETURN    R0 1         ; return 


; Function #29:
;
; Name:            
; Defined at line: 880
; #Upvalues:       3
; #Parameters:     0
; Is_vararg:       0
; Max Stack Size:  9

  1 [-]: GETUPVAL  R0 U0        ; R0 := U0
  2 [-]: SETTABLE  R0 K0 K1     ; R0["inputBlocked"] := true
  3 [-]: GETUPVAL  R0 U1        ; R0 := U1
  4 [-]: CALL      R0 1 1       ; R0()
  5 [-]: GETGLOBAL R0 K2        ; R0 := 0x25312c9b
  6 [-]: GETGLOBAL R1 K3        ; R1 := 0xae91e43b
  7 [-]: LOADK     R2 K4        ; R2 := "_root"
  8 [-]: LOADK     R3 0         ; R3 := 0.000000
  9 [-]: NEWTABLE  R4 1 0       ; R4 := {}
 10 [-]: LOADK     R5 10        ; R5 := 10.000000
 11 [-]: SETLIST   R4 1 1       ; R4[(1-1)*FPF+i] := R(4+i), 1 <= i <= 1
 12 [-]: NEWTABLE  R5 1 0       ; R5 := {}
 13 [-]: LOADK     R6 0         ; R6 := 0.000000
 14 [-]: SETLIST   R5 1 1       ; R5[(1-1)*FPF+i] := R(5+i), 1 <= i <= 1
 15 [-]: LOADK     R6 K6        ; R6 := 0.200000
 16 [-]: LOADK     R7 0         ; R7 := 0.000000
 17 [-]: CLOSURE   R8 0         ; R8 := closure(Function #29.1)
 18 [-]: GETUPVAL  R0 U2        ; R0 := U2
 19 [-]: CALL      R0 9 1       ; R0(R1,R2,R3,R4,R5,R6,R7,R8)
 20 [-]: RETURN    R0 1         ; return 


; Function #29.1:
;
; Name:            
; Defined at line: 885
; #Upvalues:       1
; #Parameters:     0
; Is_vararg:       0
; Max Stack Size:  2

  1 [-]: LOADBOOL  R0 1 0       ; R0 := true
  2 [-]: SETUPVAL  R0 U0        ; U82 := 
  3 [-]: RETURN    R0 1         ; return 


; Function #30:
;
; Name:            
; Defined at line: 888
; #Upvalues:       2
; #Parameters:     1
; Is_vararg:       0
; Max Stack Size:  3

  1 [-]: GETGLOBAL R1 K0        ; R1 := 0x03f57322
  2 [-]: MOVE      R2 R0        ; R2 := R0
  3 [-]: CALL      R1 2 2       ; R1 := R1(R2)
  4 [-]: EQ        0 R1 K2      ; if R1 ~= 4.000000 then PC := 11
  5 [-]: JMP       11           ; PC := 11
  6 [-]: GETUPVAL  R1 U0        ; R1 := U0
  7 [-]: CALL      R1 1 1       ; R1()
  8 [-]: GETUPVAL  R1 U1        ; R1 := U1
  9 [-]: CALL      R1 1 1       ; R1()
 10 [-]: JMP       18           ; PC := 18
 11 [-]: GETGLOBAL R1 K0        ; R1 := 0x03f57322
 12 [-]: MOVE      R2 R0        ; R2 := R0
 13 [-]: CALL      R1 2 2       ; R1 := R1(R2)
 14 [-]: EQ        0 R1 K3      ; if R1 ~= 6.000000 then PC := 18
 15 [-]: JMP       18           ; PC := 18
 16 [-]: GETUPVAL  R1 U1        ; R1 := U1
 17 [-]: CALL      R1 1 1       ; R1()
 18 [-]: RETURN    R0 1         ; return 


; Function #31:
;
; Name:            
; Defined at line: 897
; #Upvalues:       3
; #Parameters:     0
; Is_vararg:       0
; Max Stack Size:  2

  1 [-]: NEWTABLE  R0 0 0       ; R0 := {}
  2 [-]: SETUPVAL  R0 U0        ; U82 := 
  3 [-]: GETUPVAL  R0 U0        ; R0 := U0
  4 [-]: SETTABLE  R0 K0 K1     ; R0["paused"] := false
  5 [-]: GETUPVAL  R0 U0        ; R0 := U0
  6 [-]: SETTABLE  R0 K2 K3     ; R0["looping"] := nil
  7 [-]: GETUPVAL  R0 U0        ; R0 := U0
  8 [-]: SETTABLE  R0 K4 K1     ; R0["dirty"] := false
  9 [-]: GETUPVAL  R0 U0        ; R0 := U0
 10 [-]: SETTABLE  R0 K5 K1     ; R0["mouseOverList"] := false
 11 [-]: GETUPVAL  R0 U0        ; R0 := U0
 12 [-]: GETUPVAL  R1 U1        ; R1 := U1
 13 [-]: SETTABLE  R0 K6 R1     ; R0["stepSequencer"] := R1
 14 [-]: GETUPVAL  R0 U0        ; R0 := U0
 15 [-]: GETUPVAL  R1 U2        ; R1 := U2
 16 [-]: SETTABLE  R0 K7 R1     ; R0["composeTool"] := R1
 17 [-]: GETGLOBAL R0 K8        ; R0 := _T
 18 [-]: GETUPVAL  R1 U0        ; R1 := U0
 19 [-]: SETTABLE  R0 K9 R1     ; R0["SharedCompositionResources"] := R1
 20 [-]: RETURN    R0 1         ; return 


; Function #32:
;
; Name:            
; Defined at line: 908
; #Upvalues:       0
; #Parameters:     0
; Is_vararg:       0
; Max Stack Size:  2

  1 [-]: GETGLOBAL R0 K0        ; R0 := _T
  2 [-]: SETTABLE  R0 K1 K2     ; R0["SharedCompositionResources"] := nil
  3 [-]: RETURN    R0 1         ; return 


; Function #33:
;
; Name:            
; Defined at line: 912
; #Upvalues:       6
; #Parameters:     0
; Is_vararg:       0
; Max Stack Size:  4

  1 [-]: GETUPVAL  R0 U0        ; R0 := U0
  2 [-]: GETTABLE  R0 R0 K0     ; R0 := R0["inputBlocked"]
  3 [-]: TEST      R0 0         ; if not R0 then PC := 6
  4 [-]: JMP       6            ; PC := 6
  5 [-]: RETURN    R0 1         ; return 
  6 [-]: GETGLOBAL R0 K1        ; R0 := 0x7b998233
  7 [-]: GETUPVAL  R1 U1        ; R1 := U1
  8 [-]: CALL      R0 2 2       ; R0 := R0(R1)
  9 [-]: TEST      R0 1         ; if R0 then PC := 17
 10 [-]: JMP       17           ; PC := 17
 11 [-]: GETUPVAL  R0 U1        ; R0 := U1
 12 [-]: SELF      R0 R0 K2     ; R1 := R0; R0 := R0[0x09c8a77d]
 13 [-]: CALL      R0 2 2       ; R0 := R0(R1)
 14 [-]: TEST      R0 0         ; if not R0 then PC := 17
 15 [-]: JMP       17           ; PC := 17
 16 [-]: RETURN    R0 1         ; return 
 17 [-]: GETUPVAL  R0 U2        ; R0 := U2
 18 [-]: CALL      R0 1 1       ; R0()
 19 [-]: GETUPVAL  R0 U0        ; R0 := U0
 20 [-]: GETTABLE  R0 R0 K3     ; R0 := R0["dirty"]
 21 [-]: TEST      R0 0         ; if not R0 then PC := 42
 22 [-]: JMP       42           ; PC := 42
 23 [-]: GETUPVAL  R0 U3        ; R0 := U3
 24 [-]: EQ        0 R0 K4      ; if R0 ~= "" then PC := 42
 25 [-]: JMP       42           ; PC := 42
 26 [-]: GETGLOBAL R0 K5        ; R0 := 0x34291f5c
 27 [-]: GETTABLE  R0 R0 K6     ; R82 := R0[0xe27b35bb]
 28 [-]: CALL      R0 1 2       ; R0 := R0()
 29 [-]: SETTABLE  R0 K7 K8     ; R0["dialogType"] := 5.000000
 30 [-]: SETTABLE  R0 K9 K10    ; R0["locString"] := "/Lotus/Language/Menu/Composition_UnsavedChanges"
 31 [-]: SETTABLE  R0 K11 K12   ; R0["firstString"] := "/Menu/Confirm_Item_Yes"
 32 [-]: SETTABLE  R0 K13 K14   ; R0["secondString"] := "/Menu/Confirm_Item_No"
 33 [-]: SETTABLE  R0 K15 K16   ; R0["thirdString"] := "/Menu/Confirm_Item_Cancel"
 34 [-]: SELF      R1 R0 K17    ; R2 := R0; R1 := R0[0xe6ccc5b9]
 35 [-]: LOADK     R3 K18       ; R3 := "ConfirmClose"
 36 [-]: CALL      R1 3 1       ; R1(R2,R3)
 37 [-]: GETUPVAL  R1 U4        ; R1 := U4
 38 [-]: GETTABLE  R1 R1 K19    ; R82 := R1[0xe99b84e7]
 39 [-]: MOVE      R2 R0        ; R2 := R0
 40 [-]: CALL      R1 2 1       ; R1(R2)
 41 [-]: JMP       44           ; PC := 44
 42 [-]: GETUPVAL  R1 U5        ; R1 := U5
 43 [-]: CALL      R1 1 1       ; R1()
 44 [-]: RETURN    R0 1         ; return 


; Function #34:
;
; Name:            
; Defined at line: 937
; #Upvalues:       1
; #Parameters:     0
; Is_vararg:       0
; Max Stack Size:  2

  1 [-]: GETUPVAL  R0 U0        ; R0 := U0
  2 [-]: CALL      R0 1 1       ; R0()
  3 [-]: RETURN    R0 1         ; return 


; Function #35:
;
; Name:            
; Defined at line: 941
; #Upvalues:       0
; #Parameters:     0
; Is_vararg:       0
; Max Stack Size:  10

  1 [-]: NEWTABLE  R0 5 0       ; R0 := {}
  2 [-]: NEWTABLE  R1 0 2       ; R1 := {}
  3 [-]: GETGLOBAL R2 K1        ; R2 := 0xae91e43b
  4 [-]: SELF      R2 R2 K2     ; R3 := R2; R2 := R2[0x42b04007]
  5 [-]: LOADK     R4 K3        ; R4 := "/Lotus/Language/Menu/Composition_BarFull"
  6 [-]: LOADBOOL  R5 0 0       ; R5 := false
  7 [-]: CALL      R2 4 2       ; R2 := R2(R3,R4,R5)
  8 [-]: SETTABLE  R1 K0 R2     ; R1["Name"] := R2
  9 [-]: SETTABLE  R1 K4 K5     ; R1["Bar"] := nil
 10 [-]: NEWTABLE  R2 0 2       ; R2 := {}
 11 [-]: GETGLOBAL R3 K1        ; R3 := 0xae91e43b
 12 [-]: SELF      R3 R3 K2     ; R4 := R3; R3 := R3[0x42b04007]
 13 [-]: LOADK     R5 K6        ; R5 := "/Lotus/Language/Menu/Composition_Bar1"
 14 [-]: LOADBOOL  R6 0 0       ; R6 := false
 15 [-]: CALL      R3 4 2       ; R3 := R3(R4,R5,R6)
 16 [-]: SETTABLE  R2 K0 R3     ; R2["Name"] := R3
 17 [-]: SETTABLE  R2 K4 K7     ; R2["Bar"] := 1.000000
 18 [-]: NEWTABLE  R3 0 2       ; R3 := {}
 19 [-]: GETGLOBAL R4 K1        ; R4 := 0xae91e43b
 20 [-]: SELF      R4 R4 K2     ; R5 := R4; R4 := R4[0x42b04007]
 21 [-]: LOADK     R6 K8        ; R6 := "/Lotus/Language/Menu/Composition_Bar2"
 22 [-]: LOADBOOL  R7 0 0       ; R7 := false
 23 [-]: CALL      R4 4 2       ; R4 := R4(R5,R6,R7)
 24 [-]: SETTABLE  R3 K0 R4     ; R3["Name"] := R4
 25 [-]: SETTABLE  R3 K4 K9     ; R3["Bar"] := 2.000000
 26 [-]: NEWTABLE  R4 0 2       ; R4 := {}
 27 [-]: GETGLOBAL R5 K1        ; R5 := 0xae91e43b
 28 [-]: SELF      R5 R5 K2     ; R6 := R5; R5 := R5[0x42b04007]
 29 [-]: LOADK     R7 K10       ; R7 := "/Lotus/Language/Menu/Composition_Bar3"
 30 [-]: LOADBOOL  R8 0 0       ; R8 := false
 31 [-]: CALL      R5 4 2       ; R5 := R5(R6,R7,R8)
 32 [-]: SETTABLE  R4 K0 R5     ; R4["Name"] := R5
 33 [-]: SETTABLE  R4 K4 K11    ; R4["Bar"] := 3.000000
 34 [-]: NEWTABLE  R5 0 2       ; R5 := {}
 35 [-]: GETGLOBAL R6 K1        ; R6 := 0xae91e43b
 36 [-]: SELF      R6 R6 K2     ; R7 := R6; R6 := R6[0x42b04007]
 37 [-]: LOADK     R8 K12       ; R8 := "/Lotus/Language/Menu/Composition_Bar4"
 38 [-]: LOADBOOL  R9 0 0       ; R9 := false
 39 [-]: CALL      R6 4 2       ; R6 := R6(R7,R8,R9)
 40 [-]: SETTABLE  R5 K0 R6     ; R5["Name"] := R6
 41 [-]: SETTABLE  R5 K4 K13    ; R5["Bar"] := 4.000000
 42 [-]: SETLIST   R0 5 1       ; R0[(1-1)*FPF+i] := R(0+i), 1 <= i <= 5
 43 [-]: RETURN    R0 2         ; return R0
 44 [-]: RETURN    R0 1         ; return 


; Function #36:
;
; Name:            
; Defined at line: 954
; #Upvalues:       1
; #Parameters:     1
; Is_vararg:       0
; Max Stack Size:  3

  1 [-]: GETGLOBAL R1 K0        ; R1 := 0x7b998233
  2 [-]: MOVE      R2 R0        ; R2 := R0
  3 [-]: CALL      R1 2 2       ; R1 := R1(R2)
  4 [-]: TEST      R1 0         ; if not R1 then PC := 7
  5 [-]: JMP       7            ; PC := 7
  6 [-]: RETURN    R0 1         ; return 
  7 [-]: GETUPVAL  R1 U0        ; R1 := U0
  8 [-]: GETTABLE  R2 R0 K1     ; R2 := R0["Bar"]
  9 [-]: CALL      R1 2 1       ; R1(R2)
 10 [-]: RETURN    R0 1         ; return 


; Function #37:
;
; Name:            
; Defined at line: 962
; #Upvalues:       18
; #Parameters:     0
; Is_vararg:       0
; Max Stack Size:  22

  1 [-]: NEWTABLE  R0 18 0      ; R0 := {}
  2 [-]: NEWTABLE  R1 0 4       ; R1 := {}
  3 [-]: GETUPVAL  R2 U0        ; R2 := U0
  4 [-]: GETTABLE  R2 R2 K1     ; R2 := R2["Types"]
  5 [-]: GETTABLE  R2 R2 K2     ; R2 := R2["TITLE"]
  6 [-]: SETTABLE  R1 K0 R2     ; R1["Type"] := R2
  7 [-]: SETTABLE  R1 K3 K4     ; R1["NameTag"] := "/Lotus/Language/Menu/Composition_SoundPack"
  8 [-]: SETTABLE  R1 K5 K6     ; R1["UseBookends"] := true
  9 [-]: SETTABLE  R1 K7 K8     ; R1["BackerAlphaOverride"] := 100.000000
 10 [-]: NEWTABLE  R2 0 6       ; R2 := {}
 11 [-]: GETUPVAL  R3 U0        ; R3 := U0
 12 [-]: GETTABLE  R3 R3 K1     ; R3 := R3["Types"]
 13 [-]: GETTABLE  R3 R3 K9     ; R3 := R3["BUTTON"]
 14 [-]: SETTABLE  R2 K0 R3     ; R2["Type"] := R3
 15 [-]: SETTABLE  R2 K3 K10    ; R2["NameTag"] := "/Lotus/Language/Menu/Composition_Percussion"
 16 [-]: GETUPVAL  R3 U1        ; R3 := U1
 17 [-]: SETTABLE  R2 K11 R3    ; R2["mOnReleasedCallback"] := R3
 18 [-]: GETGLOBAL R3 K13       ; R3 := 0x0032441c
 19 [-]: GETTABLE  R3 R3 K14    ; R3 := R3["UITexture_SettingsIcons"]
 20 [-]: GETUPVAL  R4 U0        ; R4 := U0
 21 [-]: GETTABLE  R4 R4 K15    ; R4 := R4["IconTypes"]
 22 [-]: GETTABLE  R4 R4 K16    ; R4 := R4["OPEN_GRID"]
 23 [-]: GETTABLE  R3 R3 R4     ; R3 := R3[R4]
 24 [-]: SETTABLE  R2 K12 R3    ; R2["DefaultIcon"] := R3
 25 [-]: SETTABLE  R2 K7 K8     ; R2["BackerAlphaOverride"] := 100.000000
 26 [-]: SETTABLE  R2 K17 K18   ; R2["mTextYOffset"] := -4.500000
 27 [-]: NEWTABLE  R3 0 6       ; R3 := {}
 28 [-]: GETUPVAL  R4 U0        ; R4 := U0
 29 [-]: GETTABLE  R4 R4 K1     ; R4 := R4["Types"]
 30 [-]: GETTABLE  R4 R4 K9     ; R4 := R4["BUTTON"]
 31 [-]: SETTABLE  R3 K0 R4     ; R3["Type"] := R4
 32 [-]: SETTABLE  R3 K3 K19    ; R3["NameTag"] := "/Lotus/Language/Menu/Composition_Bass"
 33 [-]: GETUPVAL  R4 U2        ; R4 := U2
 34 [-]: SETTABLE  R3 K11 R4    ; R3["mOnReleasedCallback"] := R4
 35 [-]: GETGLOBAL R4 K13       ; R4 := 0x0032441c
 36 [-]: GETTABLE  R4 R4 K14    ; R4 := R4["UITexture_SettingsIcons"]
 37 [-]: GETUPVAL  R5 U0        ; R5 := U0
 38 [-]: GETTABLE  R5 R5 K15    ; R5 := R5["IconTypes"]
 39 [-]: GETTABLE  R5 R5 K16    ; R5 := R5["OPEN_GRID"]
 40 [-]: GETTABLE  R4 R4 R5     ; R4 := R4[R5]
 41 [-]: SETTABLE  R3 K12 R4    ; R3["DefaultIcon"] := R4
 42 [-]: SETTABLE  R3 K7 K8     ; R3["BackerAlphaOverride"] := 100.000000
 43 [-]: SETTABLE  R3 K17 K18   ; R3["mTextYOffset"] := -4.500000
 44 [-]: NEWTABLE  R4 0 6       ; R4 := {}
 45 [-]: GETUPVAL  R5 U0        ; R5 := U0
 46 [-]: GETTABLE  R5 R5 K1     ; R5 := R5["Types"]
 47 [-]: GETTABLE  R5 R5 K9     ; R5 := R5["BUTTON"]
 48 [-]: SETTABLE  R4 K0 R5     ; R4["Type"] := R5
 49 [-]: SETTABLE  R4 K3 K20    ; R4["NameTag"] := "/Lotus/Language/Menu/Composition_Melody"
 50 [-]: GETGLOBAL R5 K13       ; R5 := 0x0032441c
 51 [-]: GETTABLE  R5 R5 K14    ; R5 := R5["UITexture_SettingsIcons"]
 52 [-]: GETUPVAL  R6 U0        ; R6 := U0
 53 [-]: GETTABLE  R6 R6 K15    ; R6 := R6["IconTypes"]
 54 [-]: GETTABLE  R6 R6 K16    ; R6 := R6["OPEN_GRID"]
 55 [-]: GETTABLE  R5 R5 R6     ; R5 := R5[R6]
 56 [-]: SETTABLE  R4 K12 R5    ; R4["DefaultIcon"] := R5
 57 [-]: GETUPVAL  R5 U3        ; R5 := U3
 58 [-]: SETTABLE  R4 K11 R5    ; R4["mOnReleasedCallback"] := R5
 59 [-]: SETTABLE  R4 K7 K8     ; R4["BackerAlphaOverride"] := 100.000000
 60 [-]: SETTABLE  R4 K17 K18   ; R4["mTextYOffset"] := -4.500000
 61 [-]: NEWTABLE  R5 0 4       ; R5 := {}
 62 [-]: GETUPVAL  R6 U0        ; R6 := U0
 63 [-]: GETTABLE  R6 R6 K1     ; R6 := R6["Types"]
 64 [-]: GETTABLE  R6 R6 K2     ; R6 := R6["TITLE"]
 65 [-]: SETTABLE  R5 K0 R6     ; R5["Type"] := R6
 66 [-]: SETTABLE  R5 K3 K21    ; R5["NameTag"] := "/Lotus/Language/Menu/Composition_Volume"
 67 [-]: SETTABLE  R5 K5 K6     ; R5["UseBookends"] := true
 68 [-]: SETTABLE  R5 K7 K8     ; R5["BackerAlphaOverride"] := 100.000000
 69 [-]: NEWTABLE  R6 0 9       ; R6 := {}
 70 [-]: GETUPVAL  R7 U0        ; R7 := U0
 71 [-]: GETTABLE  R7 R7 K1     ; R7 := R7["Types"]
 72 [-]: GETTABLE  R7 R7 K22    ; R7 := R7["VALUE_SELECTOR"]
 73 [-]: SETTABLE  R6 K0 R7     ; R6["Type"] := R7
 74 [-]: SETTABLE  R6 K3 K10    ; R6["NameTag"] := "/Lotus/Language/Menu/Composition_Percussion"
 75 [-]: SETTABLE  R6 K17 K18   ; R6["mTextYOffset"] := -4.500000
 76 [-]: SETTABLE  R6 K23 K24   ; R6["mDefaultValue"] := 0.000000
 77 [-]: SETTABLE  R6 K25 K24   ; R6["mMinValue"] := 0.000000
 78 [-]: SETTABLE  R6 K26 K8    ; R6["mMaxValue"] := 100.000000
 79 [-]: SETTABLE  R6 K27 K29   ; R6["NoteType"] := 2.000000
 80 [-]: GETUPVAL  R7 U4        ; R7 := U4
 81 [-]: SETTABLE  R6 K30 R7    ; R6["mValueChangedCallback"] := R7
 82 [-]: SETTABLE  R6 K7 K8     ; R6["BackerAlphaOverride"] := 100.000000
 83 [-]: NEWTABLE  R7 0 9       ; R7 := {}
 84 [-]: GETUPVAL  R8 U0        ; R8 := U0
 85 [-]: GETTABLE  R8 R8 K1     ; R8 := R8["Types"]
 86 [-]: GETTABLE  R8 R8 K22    ; R8 := R8["VALUE_SELECTOR"]
 87 [-]: SETTABLE  R7 K0 R8     ; R7["Type"] := R8
 88 [-]: SETTABLE  R7 K3 K19    ; R7["NameTag"] := "/Lotus/Language/Menu/Composition_Bass"
 89 [-]: SETTABLE  R7 K17 K18   ; R7["mTextYOffset"] := -4.500000
 90 [-]: SETTABLE  R7 K23 K24   ; R7["mDefaultValue"] := 0.000000
 91 [-]: SETTABLE  R7 K25 K24   ; R7["mMinValue"] := 0.000000
 92 [-]: SETTABLE  R7 K26 K8    ; R7["mMaxValue"] := 100.000000
 93 [-]: SETTABLE  R7 K27 K31   ; R7["NoteType"] := 1.000000
 94 [-]: GETUPVAL  R8 U5        ; R8 := U5
 95 [-]: SETTABLE  R7 K30 R8    ; R7["mValueChangedCallback"] := R8
 96 [-]: SETTABLE  R7 K7 K8     ; R7["BackerAlphaOverride"] := 100.000000
 97 [-]: NEWTABLE  R8 0 9       ; R8 := {}
 98 [-]: GETUPVAL  R9 U0        ; R9 := U0
 99 [-]: GETTABLE  R9 R9 K1     ; R9 := R9["Types"]
100 [-]: GETTABLE  R9 R9 K22    ; R9 := R9["VALUE_SELECTOR"]
101 [-]: SETTABLE  R8 K0 R9     ; R8["Type"] := R9
102 [-]: SETTABLE  R8 K3 K20    ; R8["NameTag"] := "/Lotus/Language/Menu/Composition_Melody"
103 [-]: SETTABLE  R8 K17 K18   ; R8["mTextYOffset"] := -4.500000
104 [-]: SETTABLE  R8 K23 K24   ; R8["mDefaultValue"] := 0.000000
105 [-]: SETTABLE  R8 K25 K24   ; R8["mMinValue"] := 0.000000
106 [-]: SETTABLE  R8 K26 K8    ; R8["mMaxValue"] := 100.000000
107 [-]: SETTABLE  R8 K27 K24   ; R8["NoteType"] := 0.000000
108 [-]: GETUPVAL  R9 U6        ; R9 := U6
109 [-]: SETTABLE  R8 K30 R9    ; R8["mValueChangedCallback"] := R9
110 [-]: SETTABLE  R8 K7 K8     ; R8["BackerAlphaOverride"] := 100.000000
111 [-]: NEWTABLE  R9 0 4       ; R9 := {}
112 [-]: GETUPVAL  R10 U0       ; R10 := U0
113 [-]: GETTABLE  R10 R10 K1   ; R10 := R10["Types"]
114 [-]: GETTABLE  R10 R10 K2   ; R10 := R10["TITLE"]
115 [-]: SETTABLE  R9 K0 R10    ; R9["Type"] := R10
116 [-]: SETTABLE  R9 K3 K32    ; R9["NameTag"] := "/Lotus/Language/Menu/Composition_Mute"
117 [-]: SETTABLE  R9 K5 K6     ; R9["UseBookends"] := true
118 [-]: SETTABLE  R9 K7 K8     ; R9["BackerAlphaOverride"] := 100.000000
119 [-]: NEWTABLE  R10 0 7      ; R10 := {}
120 [-]: GETUPVAL  R11 U0       ; R11 := U0
121 [-]: GETTABLE  R11 R11 K1   ; R11 := R11["Types"]
122 [-]: GETTABLE  R11 R11 K33  ; R11 := R11["CHECKBOX"]
123 [-]: SETTABLE  R10 K0 R11   ; R10["Type"] := R11
124 [-]: SETTABLE  R10 K3 K10   ; R10["NameTag"] := "/Lotus/Language/Menu/Composition_Percussion"
125 [-]: SETTABLE  R10 K17 K18  ; R10["mTextYOffset"] := -4.500000
126 [-]: SETTABLE  R10 K34 K6   ; R10["mInitialValue"] := true
127 [-]: SETTABLE  R10 K27 K29  ; R10["NoteType"] := 2.000000
128 [-]: GETUPVAL  R11 U7       ; R11 := U7
129 [-]: SETTABLE  R10 K30 R11  ; R10["mValueChangedCallback"] := R11
130 [-]: SETTABLE  R10 K7 K8    ; R10["BackerAlphaOverride"] := 100.000000
131 [-]: NEWTABLE  R11 0 7      ; R11 := {}
132 [-]: GETUPVAL  R12 U0       ; R12 := U0
133 [-]: GETTABLE  R12 R12 K1   ; R12 := R12["Types"]
134 [-]: GETTABLE  R12 R12 K33  ; R12 := R12["CHECKBOX"]
135 [-]: SETTABLE  R11 K0 R12   ; R11["Type"] := R12
136 [-]: SETTABLE  R11 K3 K19   ; R11["NameTag"] := "/Lotus/Language/Menu/Composition_Bass"
137 [-]: SETTABLE  R11 K17 K18  ; R11["mTextYOffset"] := -4.500000
138 [-]: SETTABLE  R11 K34 K6   ; R11["mInitialValue"] := true
139 [-]: SETTABLE  R11 K27 K31  ; R11["NoteType"] := 1.000000
140 [-]: GETUPVAL  R12 U8       ; R12 := U8
141 [-]: SETTABLE  R11 K30 R12  ; R11["mValueChangedCallback"] := R12
142 [-]: SETTABLE  R11 K7 K8    ; R11["BackerAlphaOverride"] := 100.000000
143 [-]: NEWTABLE  R12 0 7      ; R12 := {}
144 [-]: GETUPVAL  R13 U0       ; R13 := U0
145 [-]: GETTABLE  R13 R13 K1   ; R13 := R13["Types"]
146 [-]: GETTABLE  R13 R13 K33  ; R13 := R13["CHECKBOX"]
147 [-]: SETTABLE  R12 K0 R13   ; R12["Type"] := R13
148 [-]: SETTABLE  R12 K3 K20   ; R12["NameTag"] := "/Lotus/Language/Menu/Composition_Melody"
149 [-]: SETTABLE  R12 K17 K18  ; R12["mTextYOffset"] := -4.500000
150 [-]: SETTABLE  R12 K34 K6   ; R12["mInitialValue"] := true
151 [-]: SETTABLE  R12 K27 K24  ; R12["NoteType"] := 0.000000
152 [-]: GETUPVAL  R13 U9       ; R13 := U9
153 [-]: SETTABLE  R12 K30 R13  ; R12["mValueChangedCallback"] := R13
154 [-]: SETTABLE  R12 K7 K8    ; R12["BackerAlphaOverride"] := 100.000000
155 [-]: NEWTABLE  R13 0 4      ; R13 := {}
156 [-]: GETUPVAL  R14 U0       ; R14 := U0
157 [-]: GETTABLE  R14 R14 K1   ; R14 := R14["Types"]
158 [-]: GETTABLE  R14 R14 K2   ; R14 := R14["TITLE"]
159 [-]: SETTABLE  R13 K0 R14   ; R13["Type"] := R14
160 [-]: SETTABLE  R13 K3 K35   ; R13["NameTag"] := "/Lotus/Language/Menu/Composition_Loop"
161 [-]: SETTABLE  R13 K5 K6    ; R13["UseBookends"] := true
162 [-]: SETTABLE  R13 K7 K8    ; R13["BackerAlphaOverride"] := 100.000000
163 [-]: NEWTABLE  R14 0 6      ; R14 := {}
164 [-]: GETUPVAL  R15 U0       ; R15 := U0
165 [-]: GETTABLE  R15 R15 K1   ; R15 := R15["Types"]
166 [-]: GETTABLE  R15 R15 K36  ; R15 := R15["DROP_DOWN"]
167 [-]: SETTABLE  R14 K0 R15   ; R14["Type"] := R15
168 [-]: SETTABLE  R14 K3 K35   ; R14["NameTag"] := "/Lotus/Language/Menu/Composition_Loop"
169 [-]: GETUPVAL  R15 U10      ; R15 := U10
170 [-]: CALL      R15 1 2      ; R15 := R15()
171 [-]: SETTABLE  R14 K37 R15  ; R14["mOptions"] := R15
172 [-]: SETTABLE  R14 K23 K31  ; R14["mDefaultValue"] := 1.000000
173 [-]: GETUPVAL  R15 U11      ; R15 := U11
174 [-]: SETTABLE  R14 K30 R15  ; R14["mValueChangedCallback"] := R15
175 [-]: SETTABLE  R14 K7 K8    ; R14["BackerAlphaOverride"] := 100.000000
176 [-]: NEWTABLE  R15 0 5      ; R15 := {}
177 [-]: GETUPVAL  R16 U0       ; R16 := U0
178 [-]: GETTABLE  R16 R16 K1   ; R16 := R16["Types"]
179 [-]: GETTABLE  R16 R16 K9   ; R16 := R16["BUTTON"]
180 [-]: SETTABLE  R15 K0 R16   ; R15["Type"] := R16
181 [-]: SETTABLE  R15 K3 K38   ; R15["NameTag"] := "/Lotus/Language/Menu/Composition_CopyNotes"
182 [-]: CLOSURE   R16 0        ; R16 := closure(Function #37.1)
183 [-]: GETUPVAL  R0 U12       ; R0 := U12
184 [-]: SETTABLE  R15 K11 R16  ; R15["mOnReleasedCallback"] := R16
185 [-]: SETTABLE  R15 K39 K6   ; R15["ShowCopyIcon"] := true
186 [-]: SETTABLE  R15 K7 K8    ; R15["BackerAlphaOverride"] := 100.000000
187 [-]: NEWTABLE  R16 0 5      ; R16 := {}
188 [-]: GETUPVAL  R17 U0       ; R17 := U0
189 [-]: GETTABLE  R17 R17 K1   ; R17 := R17["Types"]
190 [-]: GETTABLE  R17 R17 K9   ; R17 := R17["BUTTON"]
191 [-]: SETTABLE  R16 K0 R17   ; R16["Type"] := R17
192 [-]: SETTABLE  R16 K3 K40   ; R16["NameTag"] := "/Lotus/Language/Menu/Composition_ClearNotes"
193 [-]: CLOSURE   R17 1        ; R17 := closure(Function #37.2)
194 [-]: GETUPVAL  R0 U12       ; R0 := U12
195 [-]: SETTABLE  R16 K11 R17  ; R16["mOnReleasedCallback"] := R17
196 [-]: GETGLOBAL R17 K42      ; R17 := 0x76bd2728
197 [-]: SETTABLE  R16 K41 R17  ; R16["CustomIcon"] := R17
198 [-]: SETTABLE  R16 K7 K8    ; R16["BackerAlphaOverride"] := 100.000000
199 [-]: NEWTABLE  R17 0 4      ; R17 := {}
200 [-]: GETUPVAL  R18 U0       ; R18 := U0
201 [-]: GETTABLE  R18 R18 K1   ; R18 := R18["Types"]
202 [-]: GETTABLE  R18 R18 K2   ; R18 := R18["TITLE"]
203 [-]: SETTABLE  R17 K0 R18   ; R17["Type"] := R18
204 [-]: SETTABLE  R17 K3 K43   ; R17["NameTag"] := "/Lotus/Language/Menu/Composition_Composition"
205 [-]: SETTABLE  R17 K5 K6    ; R17["UseBookends"] := true
206 [-]: SETTABLE  R17 K7 K8    ; R17["BackerAlphaOverride"] := 100.000000
207 [-]: NEWTABLE  R18 0 4      ; R18 := {}
208 [-]: GETUPVAL  R19 U0       ; R19 := U0
209 [-]: GETTABLE  R19 R19 K1   ; R19 := R19["Types"]
210 [-]: GETTABLE  R19 R19 K9   ; R19 := R19["BUTTON"]
211 [-]: SETTABLE  R18 K0 R19   ; R18["Type"] := R19
212 [-]: SETTABLE  R18 K3 K44   ; R18["NameTag"] := "/Lotus/Language/Menu/Composition_Save"
213 [-]: GETUPVAL  R19 U13      ; R19 := U13
214 [-]: SETTABLE  R18 K11 R19  ; R18["mOnReleasedCallback"] := R19
215 [-]: SETTABLE  R18 K7 K8    ; R18["BackerAlphaOverride"] := 100.000000
216 [-]: NEWTABLE  R19 0 5      ; R19 := {}
217 [-]: GETUPVAL  R20 U0       ; R20 := U0
218 [-]: GETTABLE  R20 R20 K1   ; R20 := R20["Types"]
219 [-]: GETTABLE  R20 R20 K9   ; R20 := R20["BUTTON"]
220 [-]: SETTABLE  R19 K0 R20   ; R19["Type"] := R20
221 [-]: SETTABLE  R19 K3 K45   ; R19["NameTag"] := "/Lotus/Language/Menu/Composition_Reload"
222 [-]: SETTABLE  R19 K46 K47  ; R19["Enabled"] := false
223 [-]: GETUPVAL  R20 U14      ; R20 := U14
224 [-]: SETTABLE  R19 K11 R20  ; R19["mOnReleasedCallback"] := R20
225 [-]: SETTABLE  R19 K7 K8    ; R19["BackerAlphaOverride"] := 100.000000
226 [-]: NEWTABLE  R20 0 4      ; R20 := {}
227 [-]: GETUPVAL  R21 U0       ; R21 := U0
228 [-]: GETTABLE  R21 R21 K1   ; R21 := R21["Types"]
229 [-]: GETTABLE  R21 R21 K9   ; R21 := R21["BUTTON"]
230 [-]: SETTABLE  R20 K0 R21   ; R20["Type"] := R21
231 [-]: SETTABLE  R20 K3 K48   ; R20["NameTag"] := "/Lotus/Language/Menu/Composition_LoadSong"
232 [-]: GETUPVAL  R21 U15      ; R21 := U15
233 [-]: SETTABLE  R20 K11 R21  ; R20["mOnReleasedCallback"] := R21
234 [-]: SETTABLE  R20 K7 K8    ; R20["BackerAlphaOverride"] := 100.000000
235 [-]: SETLIST   R0 20 1      ; R0[(1-1)*FPF+i] := R(0+i), 1 <= i <= 20
236 [-]: GETGLOBAL R1 K49       ; R1 := 0xc8802016
237 [-]: MOVE      R2 R0        ; R2 := R0
238 [-]: CALL      R1 2 4       ; R1,R2,R3 := R1(R2)
239 [-]: JMP       262          ; PC := 262
240 [-]: GETTABLE  R6 R5 K50    ; R6 := R5["ShouldRemove"]
241 [-]: EQ        1 R6 K51     ; if R6 == nil then PC := 247
242 [-]: JMP       247          ; PC := 247
243 [-]: SELF      R6 R5 K52    ; R7 := R5; R6 := R5[0x061e5391]
244 [-]: CALL      R6 2 2       ; R6 := R6(R7)
245 [-]: TEST      R6 1         ; if R6 then PC := 262
246 [-]: JMP       262          ; PC := 262
247 [-]: GETTABLE  R6 R5 K0     ; R6 := R5["Type"]
248 [-]: GETUPVAL  R7 U0        ; R7 := U0
249 [-]: GETTABLE  R7 R7 K1     ; R7 := R7["Types"]
250 [-]: GETTABLE  R7 R7 K22    ; R7 := R7["VALUE_SELECTOR"]
251 [-]: EQ        0 R6 R7      ; if R6 ~= R7 then PC := 256
252 [-]: JMP       256          ; PC := 256
253 [-]: SETTABLE  R5 K53 K24   ; R5["ValueChange"] := 0.000000
254 [-]: SETTABLE  R5 K54 K47   ; R5["SliderActive"] := false
255 [-]: SETTABLE  R5 K55 K24   ; R5["SliderX"] := 0.000000
256 [-]: GETUPVAL  R6 U16       ; R6 := U16
257 [-]: GETTABLE  R6 R6 K56    ; R6 := R6["CustomizationList"]
258 [-]: SELF      R6 R6 K57    ; R7 := R6; R6 := R6[0xbad4316f]
259 [-]: MOVE      R8 R5        ; R8 := R5
260 [-]: LOADBOOL  R9 1 0       ; R9 := true
261 [-]: CALL      R6 4 1       ; R6(R7,R8,R9)
262 [-]: TFORLOOP  R1 2         ; R4,R5 :=  R1(R2,R3); if R4 ~= nil then begin PC = 240; R3 := R4 end
263 [-]: JMP       240          ; PC := 240
264 [-]: GETUPVAL  R6 U16       ; R6 := U16
265 [-]: GETTABLE  R6 R6 K56    ; R6 := R6["CustomizationList"]
266 [-]: SELF      R6 R6 K58    ; R7 := R6; R6 := R6[0x71e9ac81]
267 [-]: CALL      R6 2 1       ; R6(R7)
268 [-]: GETUPVAL  R6 U17       ; R6 := U17
269 [-]: GETGLOBAL R7 K60       ; R7 := 0xae91e43b
270 [-]: SELF      R7 R7 K61    ; R8 := R7; R7 := R7[0x91a24e4b]
271 [-]: LOADK     R9 K62       ; R9 := "AreaPicker.CustomizationPanel.List"
272 [-]: LOADK     R10 12       ; R10 := 12.000000
273 [-]: CALL      R7 4 2       ; R7 := R7(R8,R9,R10)
274 [-]: SETTABLE  R6 K59 R7    ; R6["width"] := R7
275 [-]: GETUPVAL  R6 U17       ; R6 := U17
276 [-]: GETGLOBAL R7 K60       ; R7 := 0xae91e43b
277 [-]: SELF      R7 R7 K61    ; R8 := R7; R7 := R7[0x91a24e4b]
278 [-]: LOADK     R9 K62       ; R9 := "AreaPicker.CustomizationPanel.List"
279 [-]: LOADK     R10 13       ; R10 := 13.000000
280 [-]: CALL      R7 4 2       ; R7 := R7(R8,R9,R10)
281 [-]: SETTABLE  R6 K63 R7    ; R6["height"] := R7
282 [-]: RETURN    R0 1         ; return 


; Function #37.1:
;
; Name:            
; Defined at line: 1084
; #Upvalues:       1
; #Parameters:     0
; Is_vararg:       0
; Max Stack Size:  4

  1 [-]: GETGLOBAL R0 K0        ; R0 := 0x7b998233
  2 [-]: GETUPVAL  R1 U0        ; R1 := U0
  3 [-]: CALL      R0 2 2       ; R0 := R0(R1)
  4 [-]: TEST      R0 1         ; if R0 then PC := 11
  5 [-]: JMP       11           ; PC := 11
  6 [-]: GETUPVAL  R0 U0        ; R0 := U0
  7 [-]: SELF      R0 R0 K1     ; R1 := R0; R0 := R0[0xe4162eed]
  8 [-]: LOADK     R2 K2        ; R2 := "ShowCopyNotesTool"
  9 [-]: LOADK     R3 K3        ; R3 := ""
 10 [-]: CALL      R0 4 1       ; R0(R1,R2,R3)
 11 [-]: RETURN    R0 1         ; return 


; Function #37.2:
;
; Name:            
; Defined at line: 1095
; #Upvalues:       1
; #Parameters:     0
; Is_vararg:       0
; Max Stack Size:  4

  1 [-]: GETGLOBAL R0 K0        ; R0 := 0x7b998233
  2 [-]: GETUPVAL  R1 U0        ; R1 := U0
  3 [-]: CALL      R0 2 2       ; R0 := R0(R1)
  4 [-]: TEST      R0 1         ; if R0 then PC := 11
  5 [-]: JMP       11           ; PC := 11
  6 [-]: GETUPVAL  R0 U0        ; R0 := U0
  7 [-]: SELF      R0 R0 K1     ; R1 := R0; R0 := R0[0xe4162eed]
  8 [-]: LOADK     R2 K2        ; R2 := "ClearNotes"
  9 [-]: LOADK     R3 K3        ; R3 := ""
 10 [-]: CALL      R0 4 1       ; R0(R1,R2,R3)
 11 [-]: RETURN    R0 1         ; return 


; Function #38:
;
; Name:            
; Defined at line: 1147
; #Upvalues:       6
; #Parameters:     0
; Is_vararg:       0
; Max Stack Size:  6

  1 [-]: GETGLOBAL R0 K0        ; R0 := 0x2d0fad09
  2 [-]: LOADK     R1 K1        ; R1 := "Lotus.Interface.Components.ThemedCustomizationList"
  3 [-]: CALL      R0 2 2       ; R0 := R0(R1)
  4 [-]: GETTABLE  R1 R0 K2     ; R82 := R1[0xae6791ba]
  5 [-]: GETGLOBAL R2 K3        ; R2 := 0xae91e43b
  6 [-]: LOADK     R3 K4        ; R3 := "AreaPicker"
  7 [-]: CALL      R1 3 2       ; R1 := R1(R2,R3)
  8 [-]: SETUPVAL  R1 U0        ; U82 := 
  9 [-]: GETUPVAL  R1 U0        ; R1 := U0
 10 [-]: SETTABLE  R1 K5 K6     ; R1["ScrollRemainderOnFocus"] := false
 11 [-]: GETUPVAL  R1 U0        ; R1 := U0
 12 [-]: GETTABLE  R1 R1 K7     ; R1 := R1["CustomizationList"]
 13 [-]: SETTABLE  R1 K8 K9     ; R1["mMaxVisibleHeight"] := 700.000000
 14 [-]: GETUPVAL  R1 U0        ; R1 := U0
 15 [-]: GETTABLE  R1 R1 K7     ; R1 := R1["CustomizationList"]
 16 [-]: SETTABLE  R1 K10 K11   ; R1["mElementHeight"] := 42.000000
 17 [-]: GETUPVAL  R1 U0        ; R1 := U0
 18 [-]: GETTABLE  R1 R1 K7     ; R1 := R1["CustomizationList"]
 19 [-]: SETTABLE  R1 K12 K13   ; R1["mElementWidth"] := 375.000000
 20 [-]: GETUPVAL  R1 U0        ; R1 := U0
 21 [-]: GETTABLE  R1 R1 K7     ; R1 := R1["CustomizationList"]
 22 [-]: SETTABLE  R1 K14 K15   ; R1["mForcedVerticalSeparation"] := 45.000000
 23 [-]: GETUPVAL  R1 U0        ; R1 := U0
 24 [-]: GETTABLE  R1 R1 K7     ; R1 := R1["CustomizationList"]
 25 [-]: SETTABLE  R1 K16 K17   ; R1["mNoneTextOverride"] := "/Lotus/Language/Menu/Cosmetics_None"
 26 [-]: GETUPVAL  R1 U0        ; R1 := U0
 27 [-]: GETTABLE  R1 R1 K18    ; R1 := R1["ItemSelectionGrid"]
 28 [-]: SELF      R1 R1 K19    ; R2 := R1; R1 := R1[0xa0ed0e4c]
 29 [-]: CALL      R1 2 1       ; R1(R2)
 30 [-]: NEWTABLE  R1 0 0       ; R1 := {}
 31 [-]: SETUPVAL  R1 U1        ; U82 := 
 32 [-]: GETUPVAL  R1 U1        ; R1 := U1
 33 [-]: GETUPVAL  R2 U1        ; R2 := U1
 34 [-]: GETUPVAL  R3 U2        ; R3 := U2
 35 [-]: GETTABLE  R3 R3 K22    ; R82 := R3[0xb5be5d4a]
 36 [-]: GETGLOBAL R4 K3        ; R4 := 0xae91e43b
 37 [-]: LOADK     R5 K23       ; R5 := "AreaPicker.CustomizationPanel.List"
 38 [-]: CALL      R3 3 3       ; R3,R4 := R3(R4,R5)
 39 [-]: SETTABLE  R2 K21 R4    ; R2["y"] := R4
 40 [-]: SETTABLE  R1 K20 R3    ; R1["x"] := R3
 41 [-]: GETUPVAL  R1 U0        ; R1 := U0
 42 [-]: GETTABLE  R1 R1 K7     ; R1 := R1["CustomizationList"]
 43 [-]: GETGLOBAL R2 K25       ; R2 := 0x5c4aee66
 44 [-]: SETTABLE  R1 K24 R2    ; R1["VisibleRangeMaterial"] := R2
 45 [-]: GETUPVAL  R1 U0        ; R1 := U0
 46 [-]: GETTABLE  R1 R1 K7     ; R1 := R1["CustomizationList"]
 47 [-]: GETGLOBAL R2 K27       ; R2 := 0xde244639
 48 [-]: SETTABLE  R1 K26 R2    ; R1["TextVisibleRangeMaterial"] := R2
 49 [-]: GETUPVAL  R1 U0        ; R1 := U0
 50 [-]: GETTABLE  R1 R1 K7     ; R1 := R1["CustomizationList"]
 51 [-]: GETGLOBAL R2 K29       ; R2 := 0xd8549545
 52 [-]: SETTABLE  R1 K28 R2    ; R1["RectangleVisibleRangeMaterial"] := R2
 53 [-]: GETUPVAL  R1 U0        ; R1 := U0
 54 [-]: GETTABLE  R1 R1 K7     ; R1 := R1["CustomizationList"]
 55 [-]: SELF      R1 R1 K30    ; R2 := R1; R1 := R1[0x4859e88d]
 56 [-]: CALL      R1 2 1       ; R1(R2)
 57 [-]: GETUPVAL  R1 U3        ; R1 := U3
 58 [-]: CALL      R1 1 1       ; R1()
 59 [-]: GETUPVAL  R1 U4        ; R1 := U4
 60 [-]: CALL      R1 1 1       ; R1()
 61 [-]: GETUPVAL  R1 U5        ; R1 := U5
 62 [-]: CALL      R1 1 1       ; R1()
 63 [-]: RETURN    R0 1         ; return 


; Function #39:
;
; Name:            
; Defined at line: 1173
; #Upvalues:       1
; #Parameters:     0
; Is_vararg:       0
; Max Stack Size:  3

  1 [-]: GETGLOBAL R0 K0        ; R0 := 0x9ba7909f
  2 [-]: SELF      R0 R0 K1     ; R1 := R0; R0 := R0[0xbcfb64ab]
  3 [-]: GETGLOBAL R2 K2        ; R2 := 0x1091d481
  4 [-]: CALL      R0 3 1       ; R0(R1,R2)
  5 [-]: GETGLOBAL R0 K3        ; R0 := 0x7b998233
  6 [-]: GETUPVAL  R1 U0        ; R1 := U0
  7 [-]: CALL      R0 2 2       ; R0 := R0(R1)
  8 [-]: TEST      R0 0         ; if not R0 then PC := 15
  9 [-]: JMP       15           ; PC := 15
 10 [-]: GETGLOBAL R0 K0        ; R0 := 0x9ba7909f
 11 [-]: SELF      R0 R0 K4     ; R1 := R0; R0 := R0[0xcfba257f]
 12 [-]: GETGLOBAL R2 K2        ; R2 := 0x1091d481
 13 [-]: CALL      R0 3 2       ; R0 := R0(R1,R2)
 14 [-]: SETUPVAL  R0 U0        ; U82 := 
 15 [-]: GETGLOBAL R0 K3        ; R0 := 0x7b998233
 16 [-]: GETUPVAL  R1 U0        ; R1 := U0
 17 [-]: CALL      R0 2 2       ; R0 := R0(R1)
 18 [-]: TEST      R0 1         ; if R0 then PC := 20
 19 [-]: JMP       20           ; PC := 20
 20 [-]: RETURN    R0 1         ; return 


; Function #40:
;
; Name:            
; Defined at line: 1183
; #Upvalues:       5
; #Parameters:     1
; Is_vararg:       0
; Max Stack Size:  10

  1 [-]: GETGLOBAL R1 K0        ; R1 := 0x7b998233
  2 [-]: GETUPVAL  R2 U0        ; R2 := U0
  3 [-]: CALL      R1 2 2       ; R1 := R1(R2)
  4 [-]: TEST      R1 0         ; if not R1 then PC := 16
  5 [-]: JMP       16           ; PC := 16
  6 [-]: GETGLOBAL R1 K0        ; R1 := 0x7b998233
  7 [-]: GETUPVAL  R2 U1        ; R2 := U1
  8 [-]: CALL      R1 2 2       ; R1 := R1(R2)
  9 [-]: TEST      R1 1         ; if R1 then PC := 16
 10 [-]: JMP       16           ; PC := 16
 11 [-]: GETGLOBAL R1 K0        ; R1 := 0x7b998233
 12 [-]: GETGLOBAL R2 K1        ; R2 := 0x639ad296
 13 [-]: CALL      R1 2 2       ; R1 := R1(R2)
 14 [-]: TEST      R1 0         ; if not R1 then PC := 19
 15 [-]: JMP       19           ; PC := 19
 16 [-]: GETUPVAL  R1 U0        ; R1 := U0
 17 [-]: SELF      R1 R1 K2     ; R2 := R1; R1 := R1[0x32302b4a]
 18 [-]: CALL      R1 2 1       ; R1(R2)
 19 [-]: GETUPVAL  R1 U1        ; R1 := U1
 20 [-]: SELF      R1 R1 K3     ; R2 := R1; R1 := R1[0x4d7a0caf]
 21 [-]: MOVE      R3 R0        ; R3 := R0
 22 [-]: CALL      R1 3 2       ; R1 := R1(R2,R3)
 23 [-]: GETGLOBAL R2 K4        ; R2 := 0xae91e43b
 24 [-]: SELF      R2 R2 K5     ; R3 := R2; R2 := R2[0x1fd6abd0]
 25 [-]: GETGLOBAL R4 K6        ; R4 := 0x0032441c
 26 [-]: GETTABLE  R4 R4 K7     ; R4 := R4["UIMovie_ItemBrowsingMovie"]
 27 [-]: CALL      R2 3 2       ; R2 := R2(R3,R4)
 28 [-]: SETUPVAL  R2 U0        ; U82 := 
 29 [-]: GETGLOBAL R2 K0        ; R2 := 0x7b998233
 30 [-]: GETUPVAL  R3 U0        ; R3 := U0
 31 [-]: CALL      R2 2 2       ; R2 := R2(R3)
 32 [-]: TEST      R2 1         ; if R2 then PC := 96
 33 [-]: JMP       96           ; PC := 96
 34 [-]: LOADK     R2 K8        ; R2 := "/Lotus/Language/Menu/Composition_SwapMelodyPack"
 35 [-]: EQ        0 R0 K10     ; if R0 ~= 1.000000 then PC := 39
 36 [-]: JMP       39           ; PC := 39
 37 [-]: LOADK     R2 K11       ; R2 := "/Lotus/Language/Menu/Composition_SwapBassPack"
 38 [-]: JMP       42           ; PC := 42
 39 [-]: EQ        0 R0 K12     ; if R0 ~= 2.000000 then PC := 42
 40 [-]: JMP       42           ; PC := 42
 41 [-]: LOADK     R2 K13       ; R2 := "/Lotus/Language/Menu/Composition_SwapPercussionPack"
 42 [-]: GETUPVAL  R3 U0        ; R3 := U0
 43 [-]: SELF      R3 R3 K14    ; R4 := R3; R3 := R3[0xe4162eed]
 44 [-]: LOADK     R5 K15       ; R5 := "SetTitle"
 45 [-]: GETGLOBAL R6 K4        ; R6 := 0xae91e43b
 46 [-]: SELF      R6 R6 K16    ; R7 := R6; R6 := R6[0x42b04007]
 47 [-]: MOVE      R8 R2        ; R8 := R2
 48 [-]: LOADBOOL  R9 0 0       ; R9 := false
 49 [-]: CALL      R6 4 0       ; R6,... := R6(R7,R8,R9)
 50 [-]: CALL      R3 0 1       ; R3(R4,...)
 51 [-]: GETUPVAL  R3 U0        ; R3 := U0
 52 [-]: SELF      R3 R3 K14    ; R4 := R3; R3 := R3[0xe4162eed]
 53 [-]: LOADK     R5 K17       ; R5 := "SetRequiredSelections"
 54 [-]: LOADK     R6 1         ; R6 := 1.000000
 55 [-]: CALL      R3 4 1       ; R3(R4,R5,R6)
 56 [-]: GETUPVAL  R3 U0        ; R3 := U0
 57 [-]: SELF      R3 R3 K14    ; R4 := R3; R3 := R3[0xe4162eed]
 58 [-]: LOADK     R5 K18       ; R5 := "SetHideCountThreshold"
 59 [-]: LOADK     R6 0         ; R6 := 0.000000
 60 [-]: CALL      R3 4 1       ; R3(R4,R5,R6)
 61 [-]: GETGLOBAL R3 K19       ; R3 := _T
 62 [-]: CLOSURE   R4 0         ; R4 := closure(Function #40.1)
 63 [-]: SETTABLE  R3 K20 R4    ; R3["ValidateNotePack"] := R4
 64 [-]: GETUPVAL  R3 U0        ; R3 := U0
 65 [-]: SELF      R3 R3 K14    ; R4 := R3; R3 := R3[0xe4162eed]
 66 [-]: LOADK     R5 K21       ; R5 := "SetValidationFunction"
 67 [-]: LOADK     R6 K20       ; R6 := "ValidateNotePack"
 68 [-]: CALL      R3 4 1       ; R3(R4,R5,R6)
 69 [-]: GETGLOBAL R3 K19       ; R3 := _T
 70 [-]: CLOSURE   R4 1         ; R4 := closure(Function #40.2)
 71 [-]: GETUPVAL  R0 U2        ; R0 := U2
 72 [-]: GETUPVAL  R0 U1        ; R0 := U1
 73 [-]: MOVE      R0 R0        ; R0 := R0
 74 [-]: GETUPVAL  R0 U3        ; R0 := U3
 75 [-]: SETTABLE  R3 K22 R4    ; R3["BrowseDone"] := R4
 76 [-]: GETUPVAL  R3 U0        ; R3 := U0
 77 [-]: SELF      R3 R3 K14    ; R4 := R3; R3 := R3[0xe4162eed]
 78 [-]: LOADK     R5 K23       ; R5 := "SetCallBack"
 79 [-]: LOADK     R6 K22       ; R6 := "BrowseDone"
 80 [-]: CALL      R3 4 1       ; R3(R4,R5,R6)
 81 [-]: GETGLOBAL R3 K19       ; R3 := _T
 82 [-]: CLOSURE   R4 2         ; R4 := closure(Function #40.3)
 83 [-]: GETUPVAL  R0 U4        ; R0 := U4
 84 [-]: MOVE      R0 R1        ; R0 := R1
 85 [-]: MOVE      R0 R0        ; R0 := R0
 86 [-]: SETTABLE  R3 K24 R4    ; R3["GetAllNotePacks"] := R4
 87 [-]: GETUPVAL  R3 U0        ; R3 := U0
 88 [-]: SELF      R3 R3 K14    ; R4 := R3; R3 := R3[0xe4162eed]
 89 [-]: LOADK     R5 K25       ; R5 := "SetElementsFunction"
 90 [-]: LOADK     R6 K24       ; R6 := "GetAllNotePacks"
 91 [-]: CALL      R3 4 1       ; R3(R4,R5,R6)
 92 [-]: GETUPVAL  R3 U1        ; R3 := U1
 93 [-]: SELF      R3 R3 K26    ; R4 := R3; R3 := R3[0x55e9211c]
 94 [-]: LOADBOOL  R5 1 0       ; R5 := true
 95 [-]: CALL      R3 3 1       ; R3(R4,R5)
 96 [-]: RETURN    R0 1         ; return 


; Function #40.1:
;
; Name:            
; Defined at line: 1203
; #Upvalues:       0
; #Parameters:     1
; Is_vararg:       0
; Max Stack Size:  3

  1 [-]: EQ        1 R0 K0      ; if R0 == nil then PC := 6
  2 [-]: JMP       6            ; PC := 6
  3 [-]: GETTABLE  R1 R0 K1     ; R1 := R0[1.000000]
  4 [-]: EQ        0 R1 K0      ; if R1 ~= nil then PC := 9
  5 [-]: JMP       9            ; PC := 9
  6 [-]: LOADBOOL  R1 0 0       ; R1 := false
  7 [-]: LOADK     R2 K2        ; R2 := ""
  8 [-]: RETURN    R1 3         ; return R1,R2
  9 [-]: GETTABLE  R1 R0 K1     ; R1 := R0[1.000000]
 10 [-]: GETTABLE  R1 R1 K3     ; R1 := R1["Locked"]
 11 [-]: TEST      R1 0         ; if not R1 then PC := 17
 12 [-]: JMP       17           ; PC := 17
 13 [-]: LOADBOOL  R1 0 0       ; R1 := false
 14 [-]: GETTABLE  R2 R0 K1     ; R2 := R0[1.000000]
 15 [-]: GETTABLE  R2 R2 K4     ; R2 := R2["LockedMsg"]
 16 [-]: RETURN    R1 3         ; return R1,R2
 17 [-]: LOADBOOL  R1 1 0       ; R1 := true
 18 [-]: RETURN    R1 2         ; return R1
 19 [-]: RETURN    R0 1         ; return 


; Function #40.2:
;
; Name:            
; Defined at line: 1217
; #Upvalues:       4
; #Parameters:     1
; Is_vararg:       0
; Max Stack Size:  6

  1 [-]: GETGLOBAL R1 K0        ; R1 := _T
  2 [-]: SETTABLE  R1 K1 K2     ; R1["BrowseDone"] := nil
  3 [-]: GETGLOBAL R1 K0        ; R1 := _T
  4 [-]: SETTABLE  R1 K3 K2     ; R1["GetAllNotePacks"] := nil
  5 [-]: GETGLOBAL R1 K0        ; R1 := _T
  6 [-]: SETTABLE  R1 K4 K2     ; R1["ValidateNotePack"] := nil
  7 [-]: EQ        1 R0 K2      ; if R0 == nil then PC := 24
  8 [-]: JMP       24           ; PC := 24
  9 [-]: GETTABLE  R1 R0 K5     ; R1 := R0[1.000000]
 10 [-]: EQ        1 R1 K2      ; if R1 == nil then PC := 24
 11 [-]: JMP       24           ; PC := 24
 12 [-]: GETUPVAL  R1 U0        ; R1 := U0
 13 [-]: GETUPVAL  R2 U1        ; R2 := U1
 14 [-]: NEWTABLE  R3 1 0       ; R3 := {}
 15 [-]: NEWTABLE  R4 0 2       ; R4 := {}
 16 [-]: GETUPVAL  R5 U2        ; R5 := U2
 17 [-]: SETTABLE  R4 K6 R5     ; R4["NoteType"] := R5
 18 [-]: GETTABLE  R5 R0 K5     ; R5 := R0[1.000000]
 19 [-]: GETTABLE  R5 R5 K8     ; R5 := R5["Type"]
 20 [-]: SETTABLE  R4 K7 R5     ; R4["NotePack"] := R5
 21 [-]: SETLIST   R3 1 1       ; R3[(1-1)*FPF+i] := R(3+i), 1 <= i <= 1
 22 [-]: CALL      R1 3 1       ; R1(R2,R3)
 23 [-]: JMP       34           ; PC := 34
 24 [-]: GETGLOBAL R1 K9        ; R1 := 0x7b998233
 25 [-]: GETUPVAL  R2 U1        ; R2 := U1
 26 [-]: CALL      R1 2 2       ; R1 := R1(R2)
 27 [-]: TEST      R1 1         ; if R1 then PC := 34
 28 [-]: JMP       34           ; PC := 34
 29 [-]: GETUPVAL  R1 U1        ; R1 := U1
 30 [-]: SELF      R1 R1 K10    ; R2 := R1; R1 := R1[0x55e9211c]
 31 [-]: GETUPVAL  R3 U3        ; R3 := U3
 32 [-]: GETTABLE  R3 R3 K11    ; R3 := R3["paused"]
 33 [-]: CALL      R1 3 1       ; R1(R2,R3)
 34 [-]: RETURN    R0 1         ; return 


; Function #40.3:
;
; Name:            
; Defined at line: 1231
; #Upvalues:       3
; #Parameters:     0
; Is_vararg:       0
; Max Stack Size:  26

  1 [-]: NEWTABLE  R0 0 0       ; R0 := {}
  2 [-]: GETGLOBAL R1 K0        ; R1 := 0x639ad296
  3 [-]: SELF      R1 R1 K1     ; R2 := R1; R1 := R1[0x06ad312d]
  4 [-]: CALL      R1 2 2       ; R1 := R1(R2)
  5 [-]: NEWTABLE  R2 0 0       ; R2 := {}
  6 [-]: GETUPVAL  R3 U0        ; R3 := U0
  7 [-]: SELF      R3 R3 K2     ; R4 := R3; R3 := R3[0x25a6e75e]
  8 [-]: CALL      R3 2 2       ; R3 := R3(R4)
  9 [-]: SELF      R3 R3 K3     ; R4 := R3; R3 := R3[0xd8dfa041]
 10 [-]: CALL      R3 2 2       ; R3 := R3(R4)
 11 [-]: LOADK     R4 1         ; R4 := 1.000000
 12 [-]: LEN       R5 R3        ; R5 := # R3
 13 [-]: LOADK     R6 1         ; R6 := 1.000000
 14 [-]: FORPREP   R4 27        ; R4 -= R6; PC := 27
 15 [-]: GETTABLE  R8 R3 R7     ; R8 := R3[R7]
 16 [-]: GETTABLE  R8 R8 K4     ; R8 := R8["mItemType"]
 17 [-]: SELF      R8 R8 K5     ; R9 := R8; R8 := R8[0xf2deaf69]
 18 [-]: GETGLOBAL R10 K6       ; R10 := gNotePackType
 19 [-]: CALL      R8 3 2       ; R8 := R8(R9,R10)
 20 [-]: TEST      R8 0         ; if not R8 then PC := 27
 21 [-]: JMP       27           ; PC := 27
 22 [-]: GETGLOBAL R8 K7        ; R8 := 0x33bdd652
 23 [-]: GETTABLE  R8 R8 K8     ; R82 := R8[0x23d5322f]
 24 [-]: MOVE      R9 R2        ; R9 := R2
 25 [-]: GETTABLE  R10 R3 R7    ; R10 := R3[R7]
 26 [-]: CALL      R8 3 1       ; R8(R9,R10)
 27 [-]: FORLOOP   R4 15        ; R4 += R6; if R4 <= R5 then begin PC := 15; R7 := R4 end
 28 [-]: LOADK     R8 1         ; R8 := 1.000000
 29 [-]: LEN       R9 R1        ; R9 := # R1
 30 [-]: LOADK     R10 1        ; R10 := 1.000000
 31 [-]: FORPREP   R8 92        ; R8 -= R10; PC := 92
 32 [-]: GETTABLE  R12 R1 R11   ; R12 := R1[R11]
 33 [-]: SELF      R13 R12 K9   ; R14 := R12; R13 := R12[0xf278f8a1]
 34 [-]: CALL      R13 2 2      ; R13 := R13(R14)
 35 [-]: LOADBOOL  R14 0 0      ; R14 := false
 36 [-]: LOADNIL   R15 R15      ; R15 := nil
 37 [-]: LOADK     R16 0        ; R16 := 0.000000
 38 [-]: GETUPVAL  R17 U1       ; R17 := U1
 39 [-]: EQ        1 R17 K10    ; if R17 == nil then PC := 46
 40 [-]: JMP       46           ; PC := 46
 41 [-]: GETGLOBAL R17 K11      ; R17 := 0x7ed0a956
 42 [-]: GETUPVAL  R18 U1       ; R18 := U1
 43 [-]: CALL      R17 2 2      ; R17 := R17(R18)
 44 [-]: EQ        1 R13 R17    ; if R13 == R17 then PC := 47
 45 [-]: JMP       47           ; PC := 47
 46 [-]: LOADBOOL  R17 0 1      ; R17 := false; PC := 47
 47 [-]: LOADBOOL  R17 1 0      ; R17 := true
 48 [-]: SELF      R18 R12 K12  ; R19 := R12; R18 := R12[0x31e559d2]
 49 [-]: CALL      R18 2 2      ; R18 := R18(R19)
 50 [-]: TEST      R18 0        ; if not R18 then PC := 55
 51 [-]: JMP       55           ; PC := 55
 52 [-]: LOADBOOL  R14 1 0      ; R14 := true
 53 [-]: LOADK     R16 1        ; R16 := 1.000000
 54 [-]: JMP       67           ; PC := 67
 55 [-]: LOADK     R18 1        ; R18 := 1.000000
 56 [-]: LEN       R19 R2       ; R19 := # R2
 57 [-]: LOADK     R20 1        ; R20 := 1.000000
 58 [-]: FORPREP   R18 66       ; R18 -= R20; PC := 66
 59 [-]: GETTABLE  R22 R2 R21   ; R22 := R2[R21]
 60 [-]: GETTABLE  R22 R22 K4   ; R22 := R22["mItemType"]
 61 [-]: EQ        0 R13 R22    ; if R13 ~= R22 then PC := 66
 62 [-]: JMP       66           ; PC := 66
 63 [-]: LOADBOOL  R14 1 0      ; R14 := true
 64 [-]: LOADK     R16 1        ; R16 := 1.000000
 65 [-]: JMP       67           ; PC := 67
 66 [-]: FORLOOP   R18 59       ; R18 += R20; if R18 <= R19 then begin PC := 59; R21 := R18 end
 67 [-]: TEST      R14 1        ; if R14 then PC := 72
 68 [-]: JMP       72           ; PC := 72
 69 [-]: SELF      R22 R12 K13  ; R23 := R12; R22 := R12[0x2ce719d4]
 70 [-]: CALL      R22 2 2      ; R22 := R22(R23)
 71 [-]: MOVE      R15 R22      ; R15 := R22
 72 [-]: TEST      R14 1        ; if R14 then PC := 78
 73 [-]: JMP       78           ; PC := 78
 74 [-]: SELF      R22 R12 K14  ; R23 := R12; R22 := R12[0xc055cef8]
 75 [-]: CALL      R22 2 2      ; R22 := R22(R23)
 76 [-]: TEST      R22 0        ; if not R22 then PC := 92
 77 [-]: JMP       92           ; PC := 92
 78 [-]: NEWTABLE  R22 0 7      ; R22 := {}
 79 [-]: SETTABLE  R22 K15 R13  ; R22["Type"] := R13
 80 [-]: SETTABLE  R22 K16 R12  ; R22["StoreItem"] := R12
 81 [-]: SETTABLE  R22 K17 R16  ; R22["Count"] := R16
 82 [-]: SETTABLE  R22 K18 R15  ; R22["PremiumPrice"] := R15
 83 [-]: GETUPVAL  R23 U2       ; R23 := U2
 84 [-]: SETTABLE  R22 K19 R23  ; R22["NoteType"] := R23
 85 [-]: SETTABLE  R22 K20 R17  ; R22["Locked"] := R17
 86 [-]: SETTABLE  R22 K21 K22  ; R22["LockedTag"] := "/Lotus/Language/Menu/ShipSelection_ShipSelected"
 87 [-]: GETGLOBAL R23 K7       ; R23 := 0x33bdd652
 88 [-]: GETTABLE  R23 R23 K8   ; R82 := R23[0x23d5322f]
 89 [-]: MOVE      R24 R0       ; R24 := R0
 90 [-]: MOVE      R25 R22      ; R25 := R22
 91 [-]: CALL      R23 3 1      ; R23(R24,R25)
 92 [-]: FORLOOP   R8 32        ; R8 += R10; if R8 <= R9 then begin PC := 32; R11 := R8 end
 93 [-]: RETURN    R0 2         ; return R0
 94 [-]: RETURN    R0 1         ; return 


; Function #41:
;
; Name:            
; Defined at line: 1292
; #Upvalues:       1
; #Parameters:     0
; Is_vararg:       0
; Max Stack Size:  2

  1 [-]: GETUPVAL  R0 U0        ; R0 := U0
  2 [-]: LOADK     R1 0         ; R1 := 0.000000
  3 [-]: CALL      R0 2 1       ; R0(R1)
  4 [-]: RETURN    R0 1         ; return 


; Function #42:
;
; Name:            
; Defined at line: 1296
; #Upvalues:       1
; #Parameters:     0
; Is_vararg:       0
; Max Stack Size:  2

  1 [-]: GETUPVAL  R0 U0        ; R0 := U0
  2 [-]: LOADK     R1 1         ; R1 := 1.000000
  3 [-]: CALL      R0 2 1       ; R0(R1)
  4 [-]: RETURN    R0 1         ; return 


; Function #43:
;
; Name:            
; Defined at line: 1300
; #Upvalues:       1
; #Parameters:     0
; Is_vararg:       0
; Max Stack Size:  2

  1 [-]: GETUPVAL  R0 U0        ; R0 := U0
  2 [-]: LOADK     R1 2         ; R1 := 2.000000
  3 [-]: CALL      R0 2 1       ; R0(R1)
  4 [-]: RETURN    R0 1         ; return 


; Function #44:
;
; Name:            
; Defined at line: 1304
; #Upvalues:       3
; #Parameters:     0
; Is_vararg:       0
; Max Stack Size:  3

  1 [-]: GETGLOBAL R0 K0        ; R0 := 0x7b998233
  2 [-]: GETUPVAL  R1 U0        ; R1 := U0
  3 [-]: CALL      R0 2 2       ; R0 := R0(R1)
  4 [-]: TEST      R0 0         ; if not R0 then PC := 7
  5 [-]: JMP       7            ; PC := 7
  6 [-]: RETURN    R0 1         ; return 
  7 [-]: GETUPVAL  R0 U1        ; R0 := U1
  8 [-]: GETUPVAL  R1 U0        ; R1 := U0
  9 [-]: SELF      R1 R1 K2     ; R2 := R1; R1 := R1[0x5e81fe30]
 10 [-]: CALL      R1 2 2       ; R1 := R1(R2)
 11 [-]: NOT       R1 R1        ; R1 := not R1
 12 [-]: SETTABLE  R0 K1 R1     ; R0["paused"] := R1
 13 [-]: GETUPVAL  R0 U0        ; R0 := U0
 14 [-]: SELF      R0 R0 K3     ; R1 := R0; R0 := R0[0x55e9211c]
 15 [-]: GETUPVAL  R2 U1        ; R2 := U1
 16 [-]: GETTABLE  R2 R2 K1     ; R2 := R2["paused"]
 17 [-]: CALL      R0 3 1       ; R0(R1,R2)
 18 [-]: GETUPVAL  R0 U2        ; R0 := U2
 19 [-]: CALL      R0 1 1       ; R0()
 20 [-]: RETURN    R0 1         ; return 


; Function #45:
;
; Name:            
; Defined at line: 1314
; #Upvalues:       1
; #Parameters:     0
; Is_vararg:       0
; Max Stack Size:  2

  1 [-]: GETUPVAL  R0 U0        ; R0 := U0
  2 [-]: CALL      R0 1 1       ; R0()
  3 [-]: RETURN    R0 1         ; return 


; Function #46:
;
; Name:            
; Defined at line: 1318
; #Upvalues:       1
; #Parameters:     0
; Is_vararg:       0
; Max Stack Size:  4

  1 [-]: GETGLOBAL R0 K0        ; R0 := 0x7b998233
  2 [-]: GETUPVAL  R1 U0        ; R1 := U0
  3 [-]: CALL      R0 2 2       ; R0 := R0(R1)
  4 [-]: TEST      R0 1         ; if R0 then PC := 11
  5 [-]: JMP       11           ; PC := 11
  6 [-]: GETUPVAL  R0 U0        ; R0 := U0
  7 [-]: SELF      R0 R0 K1     ; R1 := R0; R0 := R0[0xe4162eed]
  8 [-]: LOADK     R2 K2        ; R2 := "ClearNotes"
  9 [-]: LOADK     R3 K3        ; R3 := ""
 10 [-]: CALL      R0 4 1       ; R0(R1,R2,R3)
 11 [-]: RETURN    R0 1         ; return 


; Function #47:
;
; Name:            
; Defined at line: 1324
; #Upvalues:       1
; #Parameters:     1
; Is_vararg:       0
; Max Stack Size:  3

  1 [-]: GETGLOBAL R1 K0        ; R1 := 0x03f57322
  2 [-]: MOVE      R2 R0        ; R2 := R0
  3 [-]: CALL      R1 2 2       ; R1 := R1(R2)
  4 [-]: EQ        0 R1 K2      ; if R1 ~= 4.000000 then PC := 8
  5 [-]: JMP       8            ; PC := 8
  6 [-]: GETUPVAL  R1 U0        ; R1 := U0
  7 [-]: CALL      R1 1 1       ; R1()
  8 [-]: RETURN    R0 1         ; return 


; Function #48:
;
; Name:            
; Defined at line: 1330
; #Upvalues:       3
; #Parameters:     1
; Is_vararg:       0
; Max Stack Size:  8

  1 [-]: GETGLOBAL R1 K0        ; R1 := 0x03f57322
  2 [-]: MOVE      R2 R0        ; R2 := R0
  3 [-]: CALL      R1 2 2       ; R1 := R1(R2)
  4 [-]: EQ        0 R1 K1      ; if R1 ~= 1.000000 then PC := 9
  5 [-]: JMP       9            ; PC := 9
  6 [-]: GETUPVAL  R1 U0        ; R1 := U0
  7 [-]: CALL      R1 1 1       ; R1()
  8 [-]: RETURN    R0 1         ; return 
  9 [-]: LOADK     R1 K2        ; R1 := ""
 10 [-]: GETUPVAL  R2 U1        ; R2 := U1
 11 [-]: GETTABLE  R2 R2 K3     ; R2 := R2["looping"]
 12 [-]: EQ        0 R2 K4      ; if R2 ~= nil then PC := 21
 13 [-]: JMP       21           ; PC := 21
 14 [-]: GETGLOBAL R2 K5        ; R2 := 0xae91e43b
 15 [-]: SELF      R2 R2 K6     ; R3 := R2; R2 := R2[0x42b04007]
 16 [-]: LOADK     R4 K7        ; R4 := "/Lotus/Language/Menu/Composition_ClearNotesConfirmation"
 17 [-]: LOADBOOL  R5 0 0       ; R5 := false
 18 [-]: CALL      R2 4 2       ; R2 := R2(R3,R4,R5)
 19 [-]: MOVE      R1 R2        ; R1 := R2
 20 [-]: JMP       31           ; PC := 31
 21 [-]: GETGLOBAL R2 K5        ; R2 := 0xae91e43b
 22 [-]: SELF      R2 R2 K6     ; R3 := R2; R2 := R2[0x42b04007]
 23 [-]: LOADK     R4 K8        ; R4 := "/Lotus/Language/Menu/Composition_ClearNotesInBarConfirmation"
 24 [-]: LOADBOOL  R5 0 0       ; R5 := false
 25 [-]: NEWTABLE  R6 0 1       ; R6 := {}
 26 [-]: GETUPVAL  R7 U1        ; R7 := U1
 27 [-]: GETTABLE  R7 R7 K3     ; R7 := R7["looping"]
 28 [-]: SETTABLE  R6 K9 R7     ; R6["BAR"] := R7
 29 [-]: CALL      R2 5 2       ; R2 := R2(R3,R4,R5,R6)
 30 [-]: MOVE      R1 R2        ; R1 := R2
 31 [-]: GETUPVAL  R2 U2        ; R2 := U2
 32 [-]: GETTABLE  R2 R2 K10    ; R82 := R2[0xf616a184]
 33 [-]: MOVE      R3 R1        ; R3 := R1
 34 [-]: LOADK     R4 K11       ; R4 := "ConfirmClearNotes"
 35 [-]: CALL      R2 3 1       ; R2(R3,R4)
 36 [-]: RETURN    R0 1         ; return 


; Function #49:
;
; Name:            
; Defined at line: 1345
; #Upvalues:       1
; #Parameters:     1
; Is_vararg:       0
; Max Stack Size:  3

  1 [-]: GETUPVAL  R1 U0        ; R1 := U0
  2 [-]: MOVE      R2 R0        ; R2 := R0
  3 [-]: CALL      R1 2 1       ; R1(R2)
  4 [-]: RETURN    R0 1         ; return 


; Function #50:
;
; Name:            
; Defined at line: 1349
; #Upvalues:       4
; #Parameters:     0
; Is_vararg:       0
; Max Stack Size:  9

  1 [-]: NEWTABLE  R0 0 0       ; R0 := {}
  2 [-]: GETGLOBAL R1 K0        ; R1 := 0xae91e43b
  3 [-]: SELF      R1 R1 K1     ; R2 := R1; R1 := R1[0x42b04007]
  4 [-]: LOADK     R3 K2        ; R3 := "/Lotus/Language/Menu/Composition_Pause"
  5 [-]: LOADBOOL  R4 0 0       ; R4 := false
  6 [-]: CALL      R1 4 2       ; R1 := R1(R2,R3,R4)
  7 [-]: LOADK     R2 K3        ; R2 := " "
  8 [-]: GETGLOBAL R3 K0        ; R3 := 0xae91e43b
  9 [-]: SELF      R3 R3 K1     ; R4 := R3; R3 := R3[0x42b04007]
 10 [-]: GETUPVAL  R5 U0        ; R5 := U0
 11 [-]: GETTABLE  R5 R5 K4     ; R82 := R5[0x06d055f9]
 12 [-]: GETUPVAL  R6 U1        ; R6 := U1
 13 [-]: GETTABLE  R6 R6 K5     ; R6 := R6["paused"]
 14 [-]: LOADK     R7 K6        ; R7 := "<CHECKMARK>"
 15 [-]: LOADK     R8 K7        ; R8 := "<CHECKMARK_OUTLINE>"
 16 [-]: CALL      R5 4 2       ; R5 := R5(R6,R7,R8)
 17 [-]: LOADBOOL  R6 1 0       ; R6 := true
 18 [-]: CALL      R3 4 2       ; R3 := R3(R4,R5,R6)
 19 [-]: CONCAT    R1 R1 R3     ; R1 := R1 .. R2 .. R3
 20 [-]: GETUPVAL  R2 U2        ; R2 := U2
 21 [-]: EQ        0 R2 K8      ; if R2 ~= "" then PC := 37
 22 [-]: JMP       37           ; PC := 37
 23 [-]: GETGLOBAL R2 K9        ; R2 := 0x33bdd652
 24 [-]: GETTABLE  R2 R2 K10    ; R82 := R2[0x23d5322f]
 25 [-]: MOVE      R3 R0        ; R3 := R0
 26 [-]: NEWTABLE  R4 0 4       ; R4 := {}
 27 [-]: SETTABLE  R4 K11 R1    ; R4["Label"] := R1
 28 [-]: CLOSURE   R5 0         ; R5 := closure(Function #50.1)
 29 [-]: SETTABLE  R4 K12 R5    ; R4["CallBack"] := R5
 30 [-]: SETTABLE  R4 K13 K14   ; R4["CallOut"] := "MENU_GENERIC1"
 31 [-]: GETUPVAL  R5 U1        ; R5 := U1
 32 [-]: GETTABLE  R5 R5 K5     ; R5 := R5["paused"]
 33 [-]: NOT       R5 R5        ; R5 := not R5
 34 [-]: SETTABLE  R4 K15 R5    ; R4["OverrideTintIcons"] := R5
 35 [-]: CALL      R2 3 1       ; R2(R3,R4)
 36 [-]: JMP       52           ; PC := 52
 37 [-]: GETGLOBAL R2 K9        ; R2 := 0x33bdd652
 38 [-]: GETTABLE  R2 R2 K10    ; R82 := R2[0x23d5322f]
 39 [-]: MOVE      R3 R0        ; R3 := R0
 40 [-]: NEWTABLE  R4 0 3       ; R4 := {}
 41 [-]: GETUPVAL  R5 U0        ; R5 := U0
 42 [-]: GETTABLE  R5 R5 K4     ; R82 := R5[0x06d055f9]
 43 [-]: GETUPVAL  R6 U3        ; R6 := U3
 44 [-]: LOADK     R7 K16       ; R7 := "/Lotus/Language/Menu/Composition_Show"
 45 [-]: LOADK     R8 K17       ; R8 := "/Lotus/Language/Menu/Composition_Hide"
 46 [-]: CALL      R5 4 2       ; R5 := R5(R6,R7,R8)
 47 [-]: SETTABLE  R4 K11 R5    ; R4["Label"] := R5
 48 [-]: CLOSURE   R5 1         ; R5 := closure(Function #50.2)
 49 [-]: SETTABLE  R4 K12 R5    ; R4["CallBack"] := R5
 50 [-]: SETTABLE  R4 K13 K18   ; R4["CallOut"] := "MENU_GENERIC2"
 51 [-]: CALL      R2 3 1       ; R2(R3,R4)
 52 [-]: GETGLOBAL R2 K9        ; R2 := 0x33bdd652
 53 [-]: GETTABLE  R2 R2 K10    ; R82 := R2[0x23d5322f]
 54 [-]: MOVE      R3 R0        ; R3 := R0
 55 [-]: NEWTABLE  R4 0 3       ; R4 := {}
 56 [-]: SETTABLE  R4 K11 K19   ; R4["Label"] := "/Lotus/Language/Menu/Exit"
 57 [-]: CLOSURE   R5 2         ; R5 := closure(Function #50.3)
 58 [-]: SETTABLE  R4 K12 R5    ; R4["CallBack"] := R5
 59 [-]: SETTABLE  R4 K13 K20   ; R4["CallOut"] := "MENU_CANCEL"
 60 [-]: CALL      R2 3 1       ; R2(R3,R4)
 61 [-]: GETGLOBAL R2 K21       ; R2 := _T
 62 [-]: GETTABLE  R2 R2 K22    ; R82 := R2[0x1c5b546f]
 63 [-]: GETGLOBAL R3 K0        ; R3 := 0xae91e43b
 64 [-]: MOVE      R4 R0        ; R4 := R0
 65 [-]: GETGLOBAL R5 K23       ; R5 := 0xcd0165a3
 66 [-]: LOADK     R6 1         ; R6 := 1.000000
 67 [-]: CALL      R5 2 0       ; R5,... := R5(R6)
 68 [-]: CALL      R2 0 1       ; R2(R3,...)
 69 [-]: RETURN    R0 1         ; return 


; Function #50.1:
;
; Name:            
; Defined at line: 1354
; #Upvalues:       0
; #Parameters:     0
; Is_vararg:       0
; Max Stack Size:  4

  1 [-]: GETGLOBAL R0 K0        ; R0 := 0xae91e43b
  2 [-]: SELF      R0 R0 K1     ; R1 := R0; R0 := R0[0xe4162eed]
  3 [-]: LOADK     R2 K2        ; R2 := "TogglePause"
  4 [-]: LOADK     R3 K3        ; R3 := ""
  5 [-]: CALL      R0 4 1       ; R0(R1,R2,R3)
  6 [-]: RETURN    R0 1         ; return 


; Function #50.2:
;
; Name:            
; Defined at line: 1356
; #Upvalues:       0
; #Parameters:     0
; Is_vararg:       0
; Max Stack Size:  4

  1 [-]: GETGLOBAL R0 K0        ; R0 := 0xae91e43b
  2 [-]: SELF      R0 R0 K1     ; R1 := R0; R0 := R0[0xe4162eed]
  3 [-]: LOADK     R2 K2        ; R2 := "PuzzleShowHide"
  4 [-]: LOADK     R3 K3        ; R3 := ""
  5 [-]: CALL      R0 4 1       ; R0(R1,R2,R3)
  6 [-]: RETURN    R0 1         ; return 


; Function #50.3:
;
; Name:            
; Defined at line: 1358
; #Upvalues:       0
; #Parameters:     0
; Is_vararg:       0
; Max Stack Size:  4

  1 [-]: GETGLOBAL R0 K0        ; R0 := 0xae91e43b
  2 [-]: SELF      R0 R0 K1     ; R1 := R0; R0 := R0[0xe4162eed]
  3 [-]: LOADK     R2 K2        ; R2 := "Close"
  4 [-]: LOADK     R3 K3        ; R3 := ""
  5 [-]: CALL      R0 4 1       ; R0(R1,R2,R3)
  6 [-]: RETURN    R0 1         ; return 


; Function #51:
;
; Name:            
; Defined at line: 1363
; #Upvalues:       1
; #Parameters:     0
; Is_vararg:       0
; Max Stack Size:  4

  1 [-]: GETGLOBAL R0 K0        ; R0 := 0xb7cbd06b
  2 [-]: GETGLOBAL R1 K1        ; R1 := 0xe10c64de
  3 [-]: LOADK     R2 -48       ; R2 := -48.000000
  4 [-]: CALL      R1 2 2       ; R1 := R1(R2)
  5 [-]: GETGLOBAL R2 K1        ; R2 := 0xe10c64de
  6 [-]: LOADK     R3 0         ; R3 := 0.000000
  7 [-]: CALL      R2 2 0       ; R2,... := R2(R3)
  8 [-]: CALL      R0 0 2       ; R0 := R0(R1,...)
  9 [-]: GETUPVAL  R1 U0        ; R1 := U0
 10 [-]: SETTABLE  R1 K3 R0     ; R1[0.000000] := R0
 11 [-]: GETUPVAL  R1 U0        ; R1 := U0
 12 [-]: SETTABLE  R1 K4 R0     ; R1[1.000000] := R0
 13 [-]: GETUPVAL  R1 U0        ; R1 := U0
 14 [-]: SETTABLE  R1 K5 R0     ; R1[2.000000] := R0
 15 [-]: RETURN    R0 1         ; return 


; Function #52:
;
; Name:            
; Defined at line: 1370
; #Upvalues:       1
; #Parameters:     0
; Is_vararg:       0
; Max Stack Size:  4

  1 [-]: GETGLOBAL R0 K0        ; R0 := 0x9ba7909f
  2 [-]: SELF      R0 R0 K1     ; R1 := R0; R0 := R0[0xbcfb64ab]
  3 [-]: GETGLOBAL R2 K2        ; R2 := 0x6e48c770
  4 [-]: CALL      R0 3 2       ; R0 := R0(R1,R2)
  5 [-]: SETUPVAL  R0 U0        ; U82 := 
  6 [-]: GETGLOBAL R0 K3        ; R0 := 0x7b998233
  7 [-]: GETUPVAL  R1 U0        ; R1 := U0
  8 [-]: CALL      R0 2 2       ; R0 := R0(R1)
  9 [-]: TEST      R0 0         ; if not R0 then PC := 16
 10 [-]: JMP       16           ; PC := 16
 11 [-]: GETGLOBAL R0 K0        ; R0 := 0x9ba7909f
 12 [-]: SELF      R0 R0 K4     ; R1 := R0; R0 := R0[0xcfba257f]
 13 [-]: GETGLOBAL R2 K2        ; R2 := 0x6e48c770
 14 [-]: CALL      R0 3 2       ; R0 := R0(R1,R2)
 15 [-]: SETUPVAL  R0 U0        ; U82 := 
 16 [-]: GETGLOBAL R0 K3        ; R0 := 0x7b998233
 17 [-]: GETUPVAL  R1 U0        ; R1 := U0
 18 [-]: CALL      R0 2 2       ; R0 := R0(R1)
 19 [-]: TEST      R0 1         ; if R0 then PC := 46
 20 [-]: JMP       46           ; PC := 46
 21 [-]: GETUPVAL  R0 U0        ; R0 := U0
 22 [-]: SELF      R0 R0 K5     ; R1 := R0; R0 := R0[0xe4162eed]
 23 [-]: LOADK     R2 K6        ; R2 := "EnableColorCorrection"
 24 [-]: LOADK     R3 K7        ; R3 := "false"
 25 [-]: CALL      R0 4 1       ; R0(R1,R2,R3)
 26 [-]: GETUPVAL  R0 U0        ; R0 := U0
 27 [-]: SELF      R0 R0 K5     ; R1 := R0; R0 := R0[0xe4162eed]
 28 [-]: LOADK     R2 K8        ; R2 := "SetHideHud"
 29 [-]: LOADK     R3 K7        ; R3 := "false"
 30 [-]: CALL      R0 4 1       ; R0(R1,R2,R3)
 31 [-]: GETUPVAL  R0 U0        ; R0 := U0
 32 [-]: SELF      R0 R0 K5     ; R1 := R0; R0 := R0[0xe4162eed]
 33 [-]: LOADK     R2 K9        ; R2 := "EnableBackgroundFade"
 34 [-]: LOADK     R3 K10       ; R3 := "true"
 35 [-]: CALL      R0 4 1       ; R0(R1,R2,R3)
 36 [-]: GETUPVAL  R0 U0        ; R0 := U0
 37 [-]: SELF      R0 R0 K5     ; R1 := R0; R0 := R0[0xe4162eed]
 38 [-]: LOADK     R2 K11       ; R2 := "EnableBackgroundBlur"
 39 [-]: LOADK     R3 K7        ; R3 := "false"
 40 [-]: CALL      R0 4 1       ; R0(R1,R2,R3)
 41 [-]: GETUPVAL  R0 U0        ; R0 := U0
 42 [-]: SELF      R0 R0 K5     ; R1 := R0; R0 := R0[0xe4162eed]
 43 [-]: LOADK     R2 K12       ; R2 := "SetAlpha"
 44 [-]: LOADK     R3 K13       ; R3 := "100, 100"
 45 [-]: CALL      R0 4 1       ; R0(R1,R2,R3)
 46 [-]: RETURN    R0 1         ; return 


; Function #53:
;
; Name:            
; Defined at line: 1384
; #Upvalues:       3
; #Parameters:     0
; Is_vararg:       0
; Max Stack Size:  8

  1 [-]: GETUPVAL  R0 U0        ; R0 := U0
  2 [-]: GETGLOBAL R1 K1        ; R1 := 0xae91e43b
  3 [-]: SELF      R1 R1 K2     ; R2 := R1; R1 := R1[0x91a24e4b]
  4 [-]: LOADK     R3 K3        ; R3 := "AreaPicker.CustomizationPanel.List"
  5 [-]: LOADK     R4 12        ; R4 := 12.000000
  6 [-]: CALL      R1 4 2       ; R1 := R1(R2,R3,R4)
  7 [-]: SETTABLE  R0 K0 R1     ; R0["width"] := R1
  8 [-]: GETUPVAL  R0 U0        ; R0 := U0
  9 [-]: GETGLOBAL R1 K1        ; R1 := 0xae91e43b
 10 [-]: SELF      R1 R1 K2     ; R2 := R1; R1 := R1[0x91a24e4b]
 11 [-]: LOADK     R3 K3        ; R3 := "AreaPicker.CustomizationPanel.List"
 12 [-]: LOADK     R4 13        ; R4 := 13.000000
 13 [-]: CALL      R1 4 2       ; R1 := R1(R2,R3,R4)
 14 [-]: SETTABLE  R0 K4 R1     ; R0["height"] := R1
 15 [-]: GETUPVAL  R0 U0        ; R0 := U0
 16 [-]: GETUPVAL  R1 U0        ; R1 := U0
 17 [-]: GETUPVAL  R2 U1        ; R2 := U1
 18 [-]: GETTABLE  R2 R2 K7     ; R82 := R2[0xb5be5d4a]
 19 [-]: GETGLOBAL R3 K1        ; R3 := 0xae91e43b
 20 [-]: LOADK     R4 K3        ; R4 := "AreaPicker.CustomizationPanel.List"
 21 [-]: CALL      R2 3 3       ; R2,R3 := R2(R3,R4)
 22 [-]: SETTABLE  R1 K6 R3     ; R1["y"] := R3
 23 [-]: SETTABLE  R0 K5 R2     ; R0["x"] := R2
 24 [-]: GETGLOBAL R0 K8        ; R0 := 0x7b998233
 25 [-]: GETUPVAL  R1 U2        ; R1 := U2
 26 [-]: CALL      R0 2 2       ; R0 := R0(R1)
 27 [-]: TEST      R0 1         ; if R0 then PC := 54
 28 [-]: JMP       54           ; PC := 54
 29 [-]: GETGLOBAL R0 K9        ; R0 := 0x64fb1586
 30 [-]: GETUPVAL  R1 U0        ; R1 := U0
 31 [-]: GETTABLE  R1 R1 K5     ; R1 := R1["x"]
 32 [-]: CALL      R0 2 2       ; R0 := R0(R1)
 33 [-]: LOADK     R1 K10       ; R1 := ","
 34 [-]: GETGLOBAL R2 K9        ; R2 := 0x64fb1586
 35 [-]: GETUPVAL  R3 U0        ; R3 := U0
 36 [-]: GETTABLE  R3 R3 K6     ; R3 := R3["y"]
 37 [-]: CALL      R2 2 2       ; R2 := R2(R3)
 38 [-]: LOADK     R3 K10       ; R3 := ","
 39 [-]: GETGLOBAL R4 K9        ; R4 := 0x64fb1586
 40 [-]: GETUPVAL  R5 U0        ; R5 := U0
 41 [-]: GETTABLE  R5 R5 K0     ; R5 := R5["width"]
 42 [-]: CALL      R4 2 2       ; R4 := R4(R5)
 43 [-]: LOADK     R5 K10       ; R5 := ","
 44 [-]: GETGLOBAL R6 K9        ; R6 := 0x64fb1586
 45 [-]: GETUPVAL  R7 U0        ; R7 := U0
 46 [-]: GETTABLE  R7 R7 K4     ; R7 := R7["height"]
 47 [-]: CALL      R6 2 2       ; R6 := R6(R7)
 48 [-]: CONCAT    R0 R0 R6     ; R0 := R0 .. R1 .. R2 .. R3 .. R4 .. R5 .. R6
 49 [-]: GETUPVAL  R1 U2        ; R1 := U2
 50 [-]: SELF      R1 R1 K11    ; R2 := R1; R1 := R1[0xe4162eed]
 51 [-]: LOADK     R3 K12       ; R3 := "SetListBounds"
 52 [-]: MOVE      R4 R0        ; R4 := R0
 53 [-]: CALL      R1 4 1       ; R1(R2,R3,R4)
 54 [-]: RETURN    R0 1         ; return 


; Function #54:
;
; Name:            
; Defined at line: 1395
; #Upvalues:       3
; #Parameters:     0
; Is_vararg:       0
; Max Stack Size:  5

  1 [-]: GETGLOBAL R0 K0        ; R0 := 0xae91e43b
  2 [-]: SELF      R0 R0 K1     ; R1 := R0; R0 := R0[0x91a24e4b]
  3 [-]: LOADK     R2 K2        ; R2 := "_root"
  4 [-]: LOADK     R3 25        ; R3 := 25.000000
  5 [-]: CALL      R0 4 2       ; R0 := R0(R1,R2,R3)
  6 [-]: GETGLOBAL R1 K0        ; R1 := 0xae91e43b
  7 [-]: SELF      R1 R1 K1     ; R2 := R1; R1 := R1[0x91a24e4b]
  8 [-]: LOADK     R3 K2        ; R3 := "_root"
  9 [-]: LOADK     R4 26        ; R4 := 26.000000
 10 [-]: CALL      R1 4 2       ; R1 := R1(R2,R3,R4)
 11 [-]: GETUPVAL  R2 U0        ; R2 := U0
 12 [-]: EQ        0 R2 K3      ; if R2 ~= "" then PC := 36
 13 [-]: JMP       36           ; PC := 36
 14 [-]: GETUPVAL  R2 U1        ; R2 := U1
 15 [-]: GETTABLE  R2 R2 K4     ; R2 := R2["x"]
 16 [-]: LE        0 R2 R0      ; if R2 > R0 then PC := 36
 17 [-]: JMP       36           ; PC := 36
 18 [-]: GETUPVAL  R2 U1        ; R2 := U1
 19 [-]: GETTABLE  R2 R2 K4     ; R2 := R2["x"]
 20 [-]: GETUPVAL  R3 U1        ; R3 := U1
 21 [-]: GETTABLE  R3 R3 K5     ; R3 := R3["width"]
 22 [-]: ADD       R2 R2 R3     ; R2 := R2 + R3
 23 [-]: LE        0 R0 R2      ; if R0 > R2 then PC := 36
 24 [-]: JMP       36           ; PC := 36
 25 [-]: GETUPVAL  R2 U1        ; R2 := U1
 26 [-]: GETTABLE  R2 R2 K6     ; R2 := R2["y"]
 27 [-]: LE        0 R2 R1      ; if R2 > R1 then PC := 36
 28 [-]: JMP       36           ; PC := 36
 29 [-]: GETUPVAL  R2 U1        ; R2 := U1
 30 [-]: GETTABLE  R2 R2 K6     ; R2 := R2["y"]
 31 [-]: GETUPVAL  R3 U1        ; R3 := U1
 32 [-]: GETTABLE  R3 R3 K7     ; R3 := R3["height"]
 33 [-]: ADD       R2 R2 R3     ; R2 := R2 + R3
 34 [-]: LE        1 R1 R2      ; if R1 <= R2 then PC := 37
 35 [-]: JMP       37           ; PC := 37
 36 [-]: LOADBOOL  R2 0 1       ; R2 := false; PC := 37
 37 [-]: LOADBOOL  R2 1 0       ; R2 := true
 38 [-]: GETUPVAL  R3 U2        ; R3 := U2
 39 [-]: SETTABLE  R3 K8 R2     ; R3["mouseOverList"] := R2
 40 [-]: RETURN    R0 1         ; return 


; Function #55:
;
; Name:            
; Defined at line: 1407
; #Upvalues:       22
; #Parameters:     0
; Is_vararg:       0
; Max Stack Size:  26

  1 [-]: LOADBOOL  R0 0 0       ; R0 := false
  2 [-]: SETUPVAL  R0 U0        ; U82 := 
  3 [-]: GETGLOBAL R0 K0        ; R0 := 0x7b998233
  4 [-]: GETGLOBAL R1 K1        ; R1 := _T
  5 [-]: GETTABLE  R1 R1 K2     ; R1 := R1["SetSquadOverlayTitle"]
  6 [-]: CALL      R0 2 2       ; R0 := R0(R1)
  7 [-]: TEST      R0 1         ; if R0 then PC := 17
  8 [-]: JMP       17           ; PC := 17
  9 [-]: GETGLOBAL R0 K1        ; R0 := _T
 10 [-]: GETTABLE  R0 R0 K3     ; R82 := R0[0xdf29a9d6]
 11 [-]: GETGLOBAL R1 K4        ; R1 := 0xae91e43b
 12 [-]: SELF      R1 R1 K5     ; R2 := R1; R1 := R1[0x42b04007]
 13 [-]: LOADK     R3 K6        ; R3 := "/Lotus/Language/BardQuest/BardQuestSequencer"
 14 [-]: LOADBOOL  R4 0 0       ; R4 := false
 15 [-]: CALL      R1 4 0       ; R1,... := R1(R2,R3,R4)
 16 [-]: CALL      R0 0 1       ; R0(R1,...)
 17 [-]: GETGLOBAL R0 K1        ; R0 := _T
 18 [-]: GETTABLE  R0 R0 K7     ; R0 := R0["MenuSuitAvatar"]
 19 [-]: SETUPVAL  R0 U1        ; U82 := 
 20 [-]: GETGLOBAL R0 K0        ; R0 := 0x7b998233
 21 [-]: GETUPVAL  R1 U1        ; R1 := U1
 22 [-]: CALL      R0 2 2       ; R0 := R0(R1)
 23 [-]: TEST      R0 0         ; if not R0 then PC := 29
 24 [-]: JMP       29           ; PC := 29
 25 [-]: GETUPVAL  R0 U2        ; R0 := U2
 26 [-]: GETTABLE  R0 R0 K8     ; R82 := R0[0x6ef45ebc]
 27 [-]: CALL      R0 1 2       ; R0 := R0()
 28 [-]: SETUPVAL  R0 U1        ; U82 := 
 29 [-]: GETUPVAL  R0 U2        ; R0 := U2
 30 [-]: GETTABLE  R0 R0 K9     ; R82 := R0[0xb73d420f]
 31 [-]: CALL      R0 1 2       ; R0 := R0()
 32 [-]: SETUPVAL  R0 U3        ; U82 := 
 33 [-]: GETGLOBAL R0 K1        ; R0 := _T
 34 [-]: GETTABLE  R0 R0 K10    ; R0 := R0["InSimulacrum"]
 35 [-]: TEST      R0 0         ; if not R0 then PC := 47
 36 [-]: JMP       47           ; PC := 47
 37 [-]: GETGLOBAL R0 K1        ; R0 := _T
 38 [-]: GETTABLE  R0 R0 K7     ; R0 := R0["MenuSuitAvatar"]
 39 [-]: SELF      R0 R0 K11    ; R1 := R0; R0 := R0[0x2abc8ecd]
 40 [-]: LOADBOOL  R2 0 0       ; R2 := false
 41 [-]: CALL      R0 3 1       ; R0(R1,R2)
 42 [-]: GETUPVAL  R0 U1        ; R0 := U1
 43 [-]: SELF      R0 R0 K12    ; R1 := R0; R0 := R0[0x768274d6]
 44 [-]: LOADBOOL  R2 1 0       ; R2 := true
 45 [-]: LOADBOOL  R3 1 0       ; R3 := true
 46 [-]: CALL      R0 4 1       ; R0(R1,R2,R3)
 47 [-]: GETGLOBAL R0 K4        ; R0 := 0xae91e43b
 48 [-]: SELF      R0 R0 K13    ; R1 := R0; R0 := R0[0x767c0947]
 49 [-]: LOADBOOL  R2 1 0       ; R2 := true
 50 [-]: CALL      R0 3 1       ; R0(R1,R2)
 51 [-]: GETGLOBAL R0 K1        ; R0 := _T
 52 [-]: SETTABLE  R0 K14 K15   ; R0["BlockAmbientTransmissions"] := true
 53 [-]: GETGLOBAL R0 K1        ; R0 := _T
 54 [-]: SETTABLE  R0 K16 K15   ; R0["ComposeToolOpen"] := true
 55 [-]: GETGLOBAL R0 K0        ; R0 := 0x7b998233
 56 [-]: GETGLOBAL R1 K17       ; R1 := 0x76ea806b
 57 [-]: SELF      R1 R1 K18    ; R2 := R1; R1 := R1[0x3f3ae64c]
 58 [-]: LOADK     R3 0         ; R3 := 0.000000
 59 [-]: CALL      R1 3 0       ; R1,... := R1(R2,R3)
 60 [-]: CALL      R0 0 2       ; R0 := R0(R1,...)
 61 [-]: TEST      R0 1         ; if R0 then PC := 70
 62 [-]: JMP       70           ; PC := 70
 63 [-]: GETGLOBAL R0 K17       ; R0 := 0x76ea806b
 64 [-]: SELF      R0 R0 K18    ; R1 := R0; R0 := R0[0x3f3ae64c]
 65 [-]: LOADK     R2 0         ; R2 := 0.000000
 66 [-]: CALL      R0 3 2       ; R0 := R0(R1,R2)
 67 [-]: SELF      R0 R0 K19    ; R1 := R0; R0 := R0[0x80563238]
 68 [-]: CALL      R0 2 2       ; R0 := R0(R1)
 69 [-]: SETUPVAL  R0 U4        ; U82 := 
 70 [-]: GETGLOBAL R0 K1        ; R0 := _T
 71 [-]: GETTABLE  R0 R0 K20    ; R0 := R0["Jukebox"]
 72 [-]: EQ        1 R0 K21     ; if R0 == nil then PC := 96
 73 [-]: JMP       96           ; PC := 96
 74 [-]: GETUPVAL  R0 U6        ; R0 := U6
 75 [-]: GETTABLE  R0 R0 K22    ; R82 := R0[0xc9270fc5]
 76 [-]: CALL      R0 1 2       ; R0 := R0()
 77 [-]: TEST      R0 1         ; if R0 then PC := 86
 78 [-]: JMP       86           ; PC := 86
 79 [-]: GETUPVAL  R0 U6        ; R0 := U6
 80 [-]: GETTABLE  R0 R0 K23    ; R82 := R0[0x81a90acb]
 81 [-]: CALL      R0 1 2       ; R0 := R0()
 82 [-]: EQ        1 R0 K21     ; if R0 == nil then PC := 85
 83 [-]: JMP       85           ; PC := 85
 84 [-]: LOADBOOL  R0 0 1       ; R0 := false; PC := 85
 85 [-]: LOADBOOL  R0 1 0       ; R0 := true
 86 [-]: SETUPVAL  R0 U5        ; U82 := 
 87 [-]: GETUPVAL  R0 U5        ; R0 := U5
 88 [-]: TEST      R0 1         ; if R0 then PC := 96
 89 [-]: JMP       96           ; PC := 96
 90 [-]: GETUPVAL  R0 U6        ; R0 := U6
 91 [-]: GETTABLE  R0 R0 K24    ; R82 := R0[0x6e1aeeb7]
 92 [-]: GETUPVAL  R1 U6        ; R1 := U6
 93 [-]: GETTABLE  R1 R1 K23    ; R82 := R1[0x81a90acb]
 94 [-]: CALL      R1 1 0       ; R1,... := R1()
 95 [-]: CALL      R0 0 1       ; R0(R1,...)
 96 [-]: GETGLOBAL R0 K25       ; R0 := 0x89326c93
 97 [-]: SELF      R0 R0 K26    ; R1 := R0; R0 := R0[0xfb669000]
 98 [-]: GETGLOBAL R2 K27       ; R2 := 0x53b33231
 99 [-]: CALL      R0 3 2       ; R0 := R0(R1,R2)
100 [-]: GETGLOBAL R1 K28       ; R1 := 0x0469f296
101 [-]: LOADK     R2 K29       ; R2 := "JukeboxSequencer"
102 [-]: CALL      R1 2 2       ; R1 := R1(R2)
103 [-]: GETGLOBAL R2 K30       ; R2 := 0xc8802016
104 [-]: MOVE      R3 R0        ; R3 := R0
105 [-]: CALL      R2 2 4       ; R2,R3,R4 := R2(R3)
106 [-]: JMP       115          ; PC := 115
107 [-]: SELF      R7 R6 K31    ; R8 := R6; R7 := R6[0x22da1852]
108 [-]: CALL      R7 2 2       ; R7 := R7(R8)
109 [-]: EQ        1 R7 R1      ; if R7 == R1 then PC := 115
110 [-]: JMP       115          ; PC := 115
111 [-]: GETGLOBAL R7 K25       ; R7 := 0x89326c93
112 [-]: SELF      R7 R7 K32    ; R8 := R7; R7 := R7[0x59c96e77]
113 [-]: MOVE      R9 R6        ; R9 := R6
114 [-]: CALL      R7 3 1       ; R7(R8,R9)
115 [-]: TFORLOOP  R2 2         ; R5,R6 :=  R2(R3,R4); if R5 ~= nil then begin PC = 107; R4 := R5 end
116 [-]: JMP       107          ; PC := 107
117 [-]: GETGLOBAL R7 K1        ; R7 := _T
118 [-]: GETTABLE  R7 R7 K33    ; R7 := R7["ComposeTool"]
119 [-]: EQ        1 R7 K21     ; if R7 == nil then PC := 126
120 [-]: JMP       126          ; PC := 126
121 [-]: GETGLOBAL R7 K1        ; R7 := _T
122 [-]: GETTABLE  R7 R7 K33    ; R7 := R7["ComposeTool"]
123 [-]: SETUPVAL  R7 U7        ; U82 := 
124 [-]: GETGLOBAL R7 K1        ; R7 := _T
125 [-]: SETTABLE  R7 K33 K21   ; R7["ComposeTool"] := nil
126 [-]: GETUPVAL  R7 U8        ; R7 := U8
127 [-]: GETTABLE  R7 R7 K34    ; R82 := R7[0xa9882367]
128 [-]: LOADK     R8 K35       ; R8 := "LisetSoundsFadeOut"
129 [-]: CALL      R7 2 2       ; R7 := R7(R8)
130 [-]: GETGLOBAL R8 K0        ; R8 := 0x7b998233
131 [-]: MOVE      R9 R7        ; R9 := R7
132 [-]: CALL      R8 2 2       ; R8 := R8(R9)
133 [-]: TEST      R8 1         ; if R8 then PC := 138
134 [-]: JMP       138          ; PC := 138
135 [-]: SELF      R8 R7 K36    ; R9 := R7; R8 := R7[0x8eb2112d]
136 [-]: LOADK     R10 K37      ; R10 := "Execute"
137 [-]: CALL      R8 3 1       ; R8(R9,R10)
138 [-]: GETGLOBAL R8 K25       ; R8 := 0x89326c93
139 [-]: SELF      R8 R8 K38    ; R9 := R8; R8 := R8[0x05909209]
140 [-]: GETGLOBAL R10 K27      ; R10 := 0x53b33231
141 [-]: GETUPVAL  R11 U1       ; R11 := U1
142 [-]: SELF      R11 R11 K39  ; R12 := R11; R11 := R11[0xd1586535]
143 [-]: CALL      R11 2 2      ; R11 := R11(R12)
144 [-]: GETGLOBAL R12 K40      ; R12 := ZERO_ROTATION
145 [-]: CALL      R8 5 2       ; R8 := R8(R9,R10,R11,R12)
146 [-]: SETUPVAL  R8 U9        ; U82 := 
147 [-]: GETGLOBAL R8 K0        ; R8 := 0x7b998233
148 [-]: GETUPVAL  R9 U9        ; R9 := U9
149 [-]: CALL      R8 2 2       ; R8 := R8(R9)
150 [-]: TEST      R8 0         ; if not R8 then PC := 155
151 [-]: JMP       155          ; PC := 155
152 [-]: LOADBOOL  R8 1 0       ; R8 := true
153 [-]: SETUPVAL  R8 U10       ; U82 := 
154 [-]: JMP       218          ; PC := 218
155 [-]: GETGLOBAL R8 K0        ; R8 := 0x7b998233
156 [-]: GETUPVAL  R9 U1        ; R9 := U1
157 [-]: CALL      R8 2 2       ; R8 := R8(R9)
158 [-]: TEST      R8 1         ; if R8 then PC := 211
159 [-]: JMP       211          ; PC := 211
160 [-]: GETUPVAL  R8 U7        ; R8 := U7
161 [-]: GETTABLE  R8 R8 K41    ; R8 := R8["abilityIndex"]
162 [-]: EQ        1 R8 K21     ; if R8 == nil then PC := 211
163 [-]: JMP       211          ; PC := 211
164 [-]: GETUPVAL  R8 U1        ; R8 := U1
165 [-]: SELF      R8 R8 K42    ; R9 := R8; R8 := R8[0xde321e6f]
166 [-]: CALL      R8 2 2       ; R8 := R8(R9)
167 [-]: GETGLOBAL R9 K0        ; R9 := 0x7b998233
168 [-]: MOVE      R10 R8       ; R10 := R8
169 [-]: CALL      R9 2 2       ; R9 := R9(R10)
170 [-]: TEST      R9 1         ; if R9 then PC := 211
171 [-]: JMP       211          ; PC := 211
172 [-]: SELF      R9 R8 K43    ; R10 := R8; R9 := R8[0xf7d48ee0]
173 [-]: CALL      R9 2 2       ; R9 := R9(R10)
174 [-]: GETGLOBAL R10 K0       ; R10 := 0x7b998233
175 [-]: MOVE      R11 R9       ; R11 := R9
176 [-]: CALL      R10 2 2      ; R10 := R10(R11)
177 [-]: TEST      R10 1        ; if R10 then PC := 211
178 [-]: JMP       211          ; PC := 211
179 [-]: SELF      R10 R9 K44   ; R11 := R9; R10 := R9[0x68d708a7]
180 [-]: CALL      R10 2 2      ; R10 := R10(R11)
181 [-]: SELF      R10 R10 K45  ; R11 := R10; R10 := R10[0xce6f9f03]
182 [-]: GETUPVAL  R12 U7       ; R12 := U7
183 [-]: GETTABLE  R12 R12 K41  ; R12 := R12["abilityIndex"]
184 [-]: CALL      R10 3 2      ; R10 := R10(R11,R12)
185 [-]: LOADK     R11 0        ; R11 := 0.000000
186 [-]: LOADK     R12 2        ; R12 := 2.000000
187 [-]: LOADK     R13 1        ; R13 := 1.000000
188 [-]: FORPREP   R11 203      ; R11 -= R13; PC := 203
189 [-]: SELF      R15 R10 K47  ; R16 := R10; R15 := R10[0x017b5873]
190 [-]: MOVE      R17 R14      ; R17 := R14
191 [-]: CALL      R15 3 2      ; R15 := R15(R16,R17)
192 [-]: TEST      R15 0        ; if not R15 then PC := 203
193 [-]: JMP       203          ; PC := 203
194 [-]: GETUPVAL  R15 U9       ; R15 := U9
195 [-]: SELF      R15 R15 K48  ; R16 := R15; R15 := R15[0x6caac40b]
196 [-]: MOVE      R17 R14      ; R17 := R14
197 [-]: GETGLOBAL R18 K49      ; R18 := 0xb009bbc6
198 [-]: SELF      R19 R10 K50  ; R20 := R10; R19 := R10[0x4d7a0caf]
199 [-]: MOVE      R21 R14      ; R21 := R14
200 [-]: CALL      R19 3 0      ; R19,... := R19(R20,R21)
201 [-]: CALL      R18 0 0      ; R18,... := R18(R19,...)
202 [-]: CALL      R15 0 1      ; R15(R16,...)
203 [-]: FORLOOP   R11 189      ; R11 += R13; if R11 <= R12 then begin PC := 189; R14 := R11 end
204 [-]: GETTABLE  R15 R10 K51  ; R15 := R10["mHasFingerPrint"]
205 [-]: TEST      R15 0        ; if not R15 then PC := 211
206 [-]: JMP       211          ; PC := 211
207 [-]: GETUPVAL  R15 U9       ; R15 := U9
208 [-]: SELF      R15 R15 K52  ; R16 := R15; R15 := R15[0x4148785c]
209 [-]: GETTABLE  R17 R10 K53  ; R17 := R10["mFingerPrint"]
210 [-]: CALL      R15 3 1      ; R15(R16,R17)
211 [-]: GETUPVAL  R15 U9       ; R15 := U9
212 [-]: SELF      R15 R15 K54  ; R16 := R15; R15 := R15[0x687ae094]
213 [-]: CALL      R15 2 1      ; R15(R16)
214 [-]: GETUPVAL  R15 U9       ; R15 := U9
215 [-]: SELF      R15 R15 K55  ; R16 := R15; R15 := R15[0x61294cb8]
216 [-]: CALL      R15 2 2      ; R15 := R15(R16)
217 [-]: SETUPVAL  R15 U11      ; U82 := 
218 [-]: GETUPVAL  R15 U12      ; R15 := U12
219 [-]: CALL      R15 1 1      ; R15()
220 [-]: GETGLOBAL R15 K4       ; R15 := 0xae91e43b
221 [-]: SELF      R15 R15 K56  ; R16 := R15; R15 := R15[0x1e5b5cfe]
222 [-]: LOADK     R17 K57      ; R17 := "ScrubBtn"
223 [-]: LOADK     R18 K58      ; R18 := "ScrubRollOver"
224 [-]: LOADK     R19 K59      ; R19 := "ScrubRollOut"
225 [-]: LOADK     R20 K60      ; R20 := "ScrubRelease"
226 [-]: LOADK     R21 K61      ; R21 := "ScrubPress"
227 [-]: CALL      R15 7 1      ; R15(R16,R17,R18,R19,R20,R21)
228 [-]: GETGLOBAL R15 K4       ; R15 := 0xae91e43b
229 [-]: SELF      R15 R15 K62  ; R16 := R15; R15 := R15[0x337dac6d]
230 [-]: LOADK     R17 K57      ; R17 := "ScrubBtn"
231 [-]: LOADK     R18 K60      ; R18 := "ScrubRelease"
232 [-]: CALL      R15 4 1      ; R15(R16,R17,R18)
233 [-]: GETUPVAL  R15 U13      ; R15 := U13
234 [-]: CALL      R15 1 1      ; R15()
235 [-]: GETGLOBAL R15 K0       ; R15 := 0x7b998233
236 [-]: GETUPVAL  R16 U1       ; R16 := U1
237 [-]: CALL      R15 2 2      ; R15 := R15(R16)
238 [-]: TEST      R15 1        ; if R15 then PC := 256
239 [-]: JMP       256          ; PC := 256
240 [-]: GETUPVAL  R15 U1       ; R15 := U1
241 [-]: SELF      R15 R15 K42  ; R16 := R15; R15 := R15[0xde321e6f]
242 [-]: CALL      R15 2 2      ; R15 := R15(R16)
243 [-]: GETGLOBAL R16 K0       ; R16 := 0x7b998233
244 [-]: MOVE      R17 R15      ; R17 := R15
245 [-]: CALL      R16 2 2      ; R16 := R16(R17)
246 [-]: TEST      R16 1        ; if R16 then PC := 256
247 [-]: JMP       256          ; PC := 256
248 [-]: SELF      R16 R15 K63  ; R17 := R15; R16 := R15[0x19c82309]
249 [-]: LOADK     R18 0        ; R18 := 0.000000
250 [-]: CALL      R16 3 2      ; R16 := R16(R17,R18)
251 [-]: SETUPVAL  R16 U14      ; U82 := 
252 [-]: SELF      R16 R15 K65  ; R17 := R15; R16 := R15[0x4d29b3a5]
253 [-]: LOADK     R18 0        ; R18 := 0.000000
254 [-]: LOADK     R19 1        ; R19 := 1.000000
255 [-]: CALL      R16 4 1      ; R16(R17,R18,R19)
256 [-]: GETUPVAL  R16 U15      ; R16 := U15
257 [-]: CALL      R16 1 1      ; R16()
258 [-]: GETUPVAL  R16 U16      ; R16 := U16
259 [-]: CALL      R16 1 1      ; R16()
260 [-]: GETUPVAL  R16 U17      ; R16 := U17
261 [-]: CALL      R16 1 1      ; R16()
262 [-]: GETUPVAL  R16 U18      ; R16 := U18
263 [-]: CALL      R16 1 1      ; R16()
264 [-]: GETUPVAL  R16 U19      ; R16 := U19
265 [-]: CALL      R16 1 1      ; R16()
266 [-]: GETUPVAL  R16 U20      ; R16 := U20
267 [-]: LOADNIL   R17 R17      ; R17 := nil
268 [-]: CALL      R16 2 1      ; R16(R17)
269 [-]: GETGLOBAL R16 K66      ; R16 := 0x25312c9b
270 [-]: GETGLOBAL R17 K4       ; R17 := 0xae91e43b
271 [-]: LOADK     R18 K67      ; R18 := "_root"
272 [-]: LOADK     R19 0        ; R19 := 0.000000
273 [-]: NEWTABLE  R20 1 0      ; R20 := {}
274 [-]: LOADK     R21 10       ; R21 := 10.000000
275 [-]: SETLIST   R20 1 1      ; R20[(1-1)*FPF+i] := R(20+i), 1 <= i <= 1
276 [-]: NEWTABLE  R21 1 0      ; R21 := {}
277 [-]: LOADK     R22 100      ; R22 := 100.000000
278 [-]: SETLIST   R21 1 1      ; R21[(1-1)*FPF+i] := R(21+i), 1 <= i <= 1
279 [-]: LOADK     R22 K69      ; R22 := 0.200000
280 [-]: LOADK     R23 0        ; R23 := 0.000000
281 [-]: CLOSURE   R24 0        ; R24 := closure(Function #55.1)
282 [-]: GETUPVAL  R0 U21       ; R0 := U21
283 [-]: CALL      R16 9 1      ; R16(R17,R18,R19,R20,R21,R22,R23,R24)
284 [-]: GETGLOBAL R16 K25      ; R16 := 0x89326c93
285 [-]: SELF      R16 R16 K26  ; R17 := R16; R16 := R16[0xfb669000]
286 [-]: GETGLOBAL R18 K70      ; R18 := gDojoPlaceableDecorationType
287 [-]: CALL      R16 3 2      ; R16 := R16(R17,R18)
288 [-]: GETGLOBAL R17 K30      ; R17 := 0xc8802016
289 [-]: MOVE      R18 R16      ; R18 := R16
290 [-]: CALL      R17 2 4      ; R17,R18,R19 := R17(R18)
291 [-]: JMP       296          ; PC := 296
292 [-]: SELF      R22 R21 K12  ; R23 := R21; R22 := R21[0x768274d6]
293 [-]: LOADBOOL  R24 0 0      ; R24 := false
294 [-]: LOADBOOL  R25 1 0      ; R25 := true
295 [-]: CALL      R22 4 1      ; R22(R23,R24,R25)
296 [-]: TFORLOOP  R17 2        ; R20,R21 :=  R17(R18,R19); if R20 ~= nil then begin PC = 292; R19 := R20 end
297 [-]: JMP       292          ; PC := 292
298 [-]: GETGLOBAL R22 K0       ; R22 := 0x7b998233
299 [-]: GETGLOBAL R23 K71      ; R23 := 0xcb79539e
300 [-]: CALL      R22 2 2      ; R22 := R22(R23)
301 [-]: TEST      R22 1        ; if R22 then PC := 317
302 [-]: JMP       317          ; PC := 317
303 [-]: GETGLOBAL R22 K71      ; R22 := 0xcb79539e
304 [-]: SELF      R22 R22 K72  ; R23 := R22; R22 := R22[0xa9136b2f]
305 [-]: GETGLOBAL R24 K28      ; R24 := 0x0469f296
306 [-]: LOADK     R25 K73      ; R25 := "IN_SHIP_VIEW_TIME"
307 [-]: CALL      R24 2 2      ; R24 := R24(R25)
308 [-]: LOADK     R25 K74      ; R25 := "EQUIPMENT_ARSENAL_MANDACHORD"
309 [-]: CALL      R22 4 1      ; R22(R23,R24,R25)
310 [-]: GETGLOBAL R22 K71      ; R22 := 0xcb79539e
311 [-]: SELF      R22 R22 K75  ; R23 := R22; R22 := R22[0xa9188a47]
312 [-]: GETGLOBAL R24 K28      ; R24 := 0x0469f296
313 [-]: LOADK     R25 K73      ; R25 := "IN_SHIP_VIEW_TIME"
314 [-]: CALL      R24 2 2      ; R24 := R24(R25)
315 [-]: LOADK     R25 K76      ; R25 := "EQUIPMENT_ARSENAL_APPEARANCE"
316 [-]: CALL      R22 4 1      ; R22(R23,R24,R25)
317 [-]: RETURN    R0 1         ; return 


; Function #55.1:
;
; Name:            
; Defined at line: 1510
; #Upvalues:       1
; #Parameters:     0
; Is_vararg:       0
; Max Stack Size:  2

  1 [-]: GETUPVAL  R0 U0        ; R0 := U0
  2 [-]: SETTABLE  R0 K0 K1     ; R0["inputBlocked"] := false
  3 [-]: RETURN    R0 1         ; return 


; Function #56:
;
; Name:            
; Defined at line: 1525
; #Upvalues:       6
; #Parameters:     0
; Is_vararg:       0
; Max Stack Size:  10

  1 [-]: GETGLOBAL R0 K0        ; R0 := 0x7b998233
  2 [-]: GETGLOBAL R1 K1        ; R1 := _T
  3 [-]: GETTABLE  R1 R1 K2     ; R1 := R1["ClearSquadOverlayTitle"]
  4 [-]: CALL      R0 2 2       ; R0 := R0(R1)
  5 [-]: TEST      R0 1         ; if R0 then PC := 10
  6 [-]: JMP       10           ; PC := 10
  7 [-]: GETGLOBAL R0 K1        ; R0 := _T
  8 [-]: GETTABLE  R0 R0 K3     ; R82 := R0[0xfed37ac5]
  9 [-]: CALL      R0 1 1       ; R0()
 10 [-]: GETGLOBAL R0 K0        ; R0 := 0x7b998233
 11 [-]: GETUPVAL  R1 U0        ; R1 := U0
 12 [-]: CALL      R0 2 2       ; R0 := R0(R1)
 13 [-]: TEST      R0 0         ; if not R0 then PC := 20
 14 [-]: JMP       20           ; PC := 20
 15 [-]: GETGLOBAL R0 K4        ; R0 := 0x9ba7909f
 16 [-]: SELF      R0 R0 K5     ; R1 := R0; R0 := R0[0xbcfb64ab]
 17 [-]: GETGLOBAL R2 K6        ; R2 := 0x6e48c770
 18 [-]: CALL      R0 3 2       ; R0 := R0(R1,R2)
 19 [-]: SETUPVAL  R0 U0        ; U82 := 
 20 [-]: GETGLOBAL R0 K0        ; R0 := 0x7b998233
 21 [-]: GETUPVAL  R1 U0        ; R1 := U0
 22 [-]: CALL      R0 2 2       ; R0 := R0(R1)
 23 [-]: TEST      R0 1         ; if R0 then PC := 33
 24 [-]: JMP       33           ; PC := 33
 25 [-]: GETUPVAL  R0 U0        ; R0 := U0
 26 [-]: SELF      R0 R0 K7     ; R1 := R0; R0 := R0[0xf56f3887]
 27 [-]: LOADK     R2 K8        ; R2 := "TransitionOut"
 28 [-]: NEWTABLE  R3 2 0       ; R3 := {}
 29 [-]: LOADK     R4 K9        ; R4 := ""
 30 [-]: LOADK     R5 K10       ; R5 := "false"
 31 [-]: SETLIST   R3 2 1       ; R3[(1-1)*FPF+i] := R(3+i), 1 <= i <= 2
 32 [-]: CALL      R0 4 1       ; R0(R1,R2,R3)
 33 [-]: GETGLOBAL R0 K1        ; R0 := _T
 34 [-]: GETTABLE  R0 R0 K11    ; R0 := R0["InSimulacrum"]
 35 [-]: TEST      R0 0         ; if not R0 then PC := 73
 36 [-]: JMP       73           ; PC := 73
 37 [-]: GETGLOBAL R0 K0        ; R0 := 0x7b998233
 38 [-]: GETGLOBAL R1 K12       ; R1 := 0x89326c93
 39 [-]: CALL      R0 2 2       ; R0 := R0(R1)
 40 [-]: TEST      R0 1         ; if R0 then PC := 73
 41 [-]: JMP       73           ; PC := 73
 42 [-]: GETGLOBAL R0 K0        ; R0 := 0x7b998233
 43 [-]: GETUPVAL  R1 U1        ; R1 := U1
 44 [-]: CALL      R0 2 2       ; R0 := R0(R1)
 45 [-]: TEST      R0 1         ; if R0 then PC := 73
 46 [-]: JMP       73           ; PC := 73
 47 [-]: GETGLOBAL R0 K0        ; R0 := 0x7b998233
 48 [-]: GETGLOBAL R1 K1        ; R1 := _T
 49 [-]: GETTABLE  R1 R1 K13    ; R1 := R1["MenuSuitAvatar"]
 50 [-]: CALL      R0 2 2       ; R0 := R0(R1)
 51 [-]: TEST      R0 1         ; if R0 then PC := 58
 52 [-]: JMP       58           ; PC := 58
 53 [-]: GETGLOBAL R0 K1        ; R0 := _T
 54 [-]: GETTABLE  R0 R0 K13    ; R0 := R0["MenuSuitAvatar"]
 55 [-]: SELF      R0 R0 K14    ; R1 := R0; R0 := R0[0x2abc8ecd]
 56 [-]: LOADBOOL  R2 1 0       ; R2 := true
 57 [-]: CALL      R0 3 1       ; R0(R1,R2)
 58 [-]: GETGLOBAL R0 K12       ; R0 := 0x89326c93
 59 [-]: SELF      R0 R0 K15    ; R1 := R0; R0 := R0[0x18d05d30]
 60 [-]: CALL      R0 2 2       ; R0 := R0(R1)
 61 [-]: TEST      R0 0         ; if not R0 then PC := 68
 62 [-]: JMP       68           ; PC := 68
 63 [-]: GETUPVAL  R0 U1        ; R0 := U1
 64 [-]: SELF      R0 R0 K14    ; R1 := R0; R0 := R0[0x2abc8ecd]
 65 [-]: LOADBOOL  R2 0 0       ; R2 := false
 66 [-]: CALL      R0 3 1       ; R0(R1,R2)
 67 [-]: JMP       73           ; PC := 73
 68 [-]: GETUPVAL  R0 U1        ; R0 := U1
 69 [-]: SELF      R0 R0 K16    ; R1 := R0; R0 := R0[0x768274d6]
 70 [-]: LOADBOOL  R2 0 0       ; R2 := false
 71 [-]: LOADBOOL  R3 1 0       ; R3 := true
 72 [-]: CALL      R0 4 1       ; R0(R1,R2,R3)
 73 [-]: GETUPVAL  R0 U2        ; R0 := U2
 74 [-]: CALL      R0 1 1       ; R0()
 75 [-]: GETGLOBAL R0 K0        ; R0 := 0x7b998233
 76 [-]: GETGLOBAL R1 K12       ; R1 := 0x89326c93
 77 [-]: CALL      R0 2 2       ; R0 := R0(R1)
 78 [-]: TEST      R0 1         ; if R0 then PC := 99
 79 [-]: JMP       99           ; PC := 99
 80 [-]: GETGLOBAL R0 K12       ; R0 := 0x89326c93
 81 [-]: SELF      R0 R0 K17    ; R1 := R0; R0 := R0[0xfb669000]
 82 [-]: GETGLOBAL R2 K18       ; R2 := gDojoPlaceableDecorationType
 83 [-]: CALL      R0 3 2       ; R0 := R0(R1,R2)
 84 [-]: GETGLOBAL R1 K19       ; R1 := 0xc8802016
 85 [-]: MOVE      R2 R0        ; R2 := R0
 86 [-]: CALL      R1 2 4       ; R1,R2,R3 := R1(R2)
 87 [-]: JMP       97           ; PC := 97
 88 [-]: SELF      R6 R5 K20    ; R7 := R5; R6 := R5[0x22da1852]
 89 [-]: CALL      R6 2 2       ; R6 := R6(R7)
 90 [-]: GETUPVAL  R7 U3        ; R7 := U3
 91 [-]: EQ        1 R6 R7      ; if R6 == R7 then PC := 97
 92 [-]: JMP       97           ; PC := 97
 93 [-]: SELF      R6 R5 K16    ; R7 := R5; R6 := R5[0x768274d6]
 94 [-]: LOADBOOL  R8 1 0       ; R8 := true
 95 [-]: LOADBOOL  R9 1 0       ; R9 := true
 96 [-]: CALL      R6 4 1       ; R6(R7,R8,R9)
 97 [-]: TFORLOOP  R1 2         ; R4,R5 :=  R1(R2,R3); if R4 ~= nil then begin PC = 88; R3 := R4 end
 98 [-]: JMP       88           ; PC := 88
 99 [-]: GETGLOBAL R6 K1        ; R6 := _T
100 [-]: GETTABLE  R6 R6 K21    ; R6 := R6["Jukebox"]
101 [-]: EQ        1 R6 K22     ; if R6 == nil then PC := 112
102 [-]: JMP       112          ; PC := 112
103 [-]: GETUPVAL  R6 U4        ; R6 := U4
104 [-]: TEST      R6 1         ; if R6 then PC := 112
105 [-]: JMP       112          ; PC := 112
106 [-]: GETUPVAL  R6 U5        ; R6 := U5
107 [-]: GETTABLE  R6 R6 K23    ; R82 := R6[0x6e1aeeb7]
108 [-]: GETUPVAL  R7 U5        ; R7 := U5
109 [-]: GETTABLE  R7 R7 K24    ; R82 := R7[0x81a90acb]
110 [-]: CALL      R7 1 0       ; R7,... := R7()
111 [-]: CALL      R6 0 1       ; R6(R7,...)
112 [-]: GETGLOBAL R6 K1        ; R6 := _T
113 [-]: SETTABLE  R6 K25 K26   ; R6["BlockAmbientTransmissions"] := false
114 [-]: GETGLOBAL R6 K1        ; R6 := _T
115 [-]: SETTABLE  R6 K27 K22   ; R6["ComposeToolOpen"] := nil
116 [-]: GETGLOBAL R6 K1        ; R6 := _T
117 [-]: SETTABLE  R6 K28 K22   ; R6["ComposeToolRequest"] := nil
118 [-]: GETGLOBAL R6 K0        ; R6 := 0x7b998233
119 [-]: GETGLOBAL R7 K29       ; R7 := 0xcb79539e
120 [-]: CALL      R6 2 2       ; R6 := R6(R7)
121 [-]: TEST      R6 1         ; if R6 then PC := 137
122 [-]: JMP       137          ; PC := 137
123 [-]: GETGLOBAL R6 K29       ; R6 := 0xcb79539e
124 [-]: SELF      R6 R6 K30    ; R7 := R6; R6 := R6[0xa9188a47]
125 [-]: GETGLOBAL R8 K31       ; R8 := 0x0469f296
126 [-]: LOADK     R9 K32       ; R9 := "IN_SHIP_VIEW_TIME"
127 [-]: CALL      R8 2 2       ; R8 := R8(R9)
128 [-]: LOADK     R9 K33       ; R9 := "EQUIPMENT_ARSENAL_MANDACHORD"
129 [-]: CALL      R6 4 1       ; R6(R7,R8,R9)
130 [-]: GETGLOBAL R6 K29       ; R6 := 0xcb79539e
131 [-]: SELF      R6 R6 K34    ; R7 := R6; R6 := R6[0xa9136b2f]
132 [-]: GETGLOBAL R8 K31       ; R8 := 0x0469f296
133 [-]: LOADK     R9 K32       ; R9 := "IN_SHIP_VIEW_TIME"
134 [-]: CALL      R8 2 2       ; R8 := R8(R9)
135 [-]: LOADK     R9 K35       ; R9 := "EQUIPMENT_ARSENAL_APPEARANCE"
136 [-]: CALL      R6 4 1       ; R6(R7,R8,R9)
137 [-]: RETURN    R0 1         ; return 


; Function #57:
;
; Name:            
; Defined at line: 1576
; #Upvalues:       2
; #Parameters:     0
; Is_vararg:       0
; Max Stack Size:  5

  1 [-]: GETGLOBAL R0 K0        ; R0 := _T
  2 [-]: GETTABLE  R0 R0 K1     ; R0 := R0["ArsenalOpen"]
  3 [-]: TEST      R0 1         ; if R0 then PC := 42
  4 [-]: JMP       42           ; PC := 42
  5 [-]: GETGLOBAL R0 K2        ; R0 := 0x7b998233
  6 [-]: GETUPVAL  R1 U0        ; R1 := U0
  7 [-]: CALL      R0 2 2       ; R0 := R0(R1)
  8 [-]: TEST      R0 1         ; if R0 then PC := 42
  9 [-]: JMP       42           ; PC := 42
 10 [-]: GETUPVAL  R0 U0        ; R0 := U0
 11 [-]: SELF      R0 R0 K3     ; R1 := R0; R0 := R0[0x5e651723]
 12 [-]: CALL      R0 2 2       ; R0 := R0(R1)
 13 [-]: GETGLOBAL R1 K2        ; R1 := 0x7b998233
 14 [-]: MOVE      R2 R0        ; R2 := R0
 15 [-]: CALL      R1 2 2       ; R1 := R1(R2)
 16 [-]: TEST      R1 0         ; if not R1 then PC := 42
 17 [-]: JMP       42           ; PC := 42
 18 [-]: GETUPVAL  R1 U0        ; R1 := U0
 19 [-]: SELF      R1 R1 K4     ; R2 := R1; R1 := R1[0x5b89142c]
 20 [-]: CALL      R1 2 2       ; R1 := R1(R2)
 21 [-]: GETGLOBAL R2 K2        ; R2 := 0x7b998233
 22 [-]: MOVE      R3 R1        ; R3 := R1
 23 [-]: CALL      R2 2 2       ; R2 := R2(R3)
 24 [-]: TEST      R2 1         ; if R2 then PC := 42
 25 [-]: JMP       42           ; PC := 42
 26 [-]: SELF      R2 R1 K5     ; R3 := R1; R2 := R1[0xbb610e5b]
 27 [-]: CALL      R2 2 2       ; R2 := R2(R3)
 28 [-]: SETUPVAL  R2 U0        ; U82 := 
 29 [-]: GETGLOBAL R2 K2        ; R2 := 0x7b998233
 30 [-]: GETUPVAL  R3 U0        ; R3 := U0
 31 [-]: CALL      R2 2 2       ; R2 := R2(R3)
 32 [-]: TEST      R2 1         ; if R2 then PC := 42
 33 [-]: JMP       42           ; PC := 42
 34 [-]: GETUPVAL  R2 U0        ; R2 := U0
 35 [-]: SELF      R2 R2 K6     ; R3 := R2; R2 := R2[0xf2deaf69]
 36 [-]: GETGLOBAL R4 K7        ; R4 := gLotusOperatorAvatarType
 37 [-]: CALL      R2 3 2       ; R2 := R2(R3,R4)
 38 [-]: TEST      R2 0         ; if not R2 then PC := 42
 39 [-]: JMP       42           ; PC := 42
 40 [-]: GETUPVAL  R2 U1        ; R2 := U1
 41 [-]: CALL      R2 1 1       ; R2()
 42 [-]: GETGLOBAL R2 K2        ; R2 := 0x7b998233
 43 [-]: GETUPVAL  R3 U0        ; R3 := U0
 44 [-]: CALL      R2 2 2       ; R2 := R2(R3)
 45 [-]: TEST      R2 0         ; if not R2 then PC := 51
 46 [-]: JMP       51           ; PC := 51
 47 [-]: GETGLOBAL R2 K8        ; R2 := 0x89326c93
 48 [-]: SELF      R2 R2 K9     ; R3 := R2; R2 := R2[0x78298275]
 49 [-]: CALL      R2 2 2       ; R2 := R2(R3)
 50 [-]: SETUPVAL  R2 U0        ; U82 := 
 51 [-]: RETURN    R0 1         ; return 


; Function #58:
;
; Name:            
; Defined at line: 1595
; #Upvalues:       12
; #Parameters:     0
; Is_vararg:       0
; Max Stack Size:  33

  1 [-]: GETGLOBAL R0 K0        ; R0 := 0x7b998233
  2 [-]: GETGLOBAL R1 K1        ; R1 := 0xae91e43b
  3 [-]: CALL      R0 2 2       ; R0 := R0(R1)
  4 [-]: TEST      R0 0         ; if not R0 then PC := 7
  5 [-]: JMP       7            ; PC := 7
  6 [-]: RETURN    R0 1         ; return 
  7 [-]: GETGLOBAL R0 K1        ; R0 := 0xae91e43b
  8 [-]: SELF      R0 R0 K2     ; R1 := R0; R0 := R0[0x8a8c8d5a]
  9 [-]: GETGLOBAL R2 K3        ; R2 := 0xb693b6c1
 10 [-]: CALL      R2 1 0       ; R2,... := R2()
 11 [-]: CALL      R0 0 1       ; R0(R1,...)
 12 [-]: GETGLOBAL R0 K0        ; R0 := 0x7b998233
 13 [-]: GETUPVAL  R1 U0        ; R1 := U0
 14 [-]: CALL      R0 2 2       ; R0 := R0(R1)
 15 [-]: TEST      R0 1         ; if R0 then PC := 23
 16 [-]: JMP       23           ; PC := 23
 17 [-]: GETUPVAL  R0 U0        ; R0 := U0
 18 [-]: GETTABLE  R0 R0 K4     ; R0 := R0["CustomizationList"]
 19 [-]: SELF      R0 R0 K5     ; R1 := R0; R0 := R0[0xfaa69527]
 20 [-]: GETGLOBAL R2 K3        ; R2 := 0xb693b6c1
 21 [-]: CALL      R2 1 0       ; R2,... := R2()
 22 [-]: CALL      R0 0 1       ; R0(R1,...)
 23 [-]: GETUPVAL  R0 U1        ; R0 := U1
 24 [-]: TEST      R0 0         ; if not R0 then PC := 42
 25 [-]: JMP       42           ; PC := 42
 26 [-]: GETUPVAL  R0 U2        ; R0 := U2
 27 [-]: GETTABLE  R0 R0 K6     ; R82 := R0[0xa9882367]
 28 [-]: LOADK     R1 K7        ; R1 := "LisetSoundsFadeIn"
 29 [-]: CALL      R0 2 2       ; R0 := R0(R1)
 30 [-]: GETGLOBAL R1 K0        ; R1 := 0x7b998233
 31 [-]: MOVE      R2 R0        ; R2 := R0
 32 [-]: CALL      R1 2 2       ; R1 := R1(R2)
 33 [-]: TEST      R1 1         ; if R1 then PC := 38
 34 [-]: JMP       38           ; PC := 38
 35 [-]: SELF      R1 R0 K8     ; R2 := R0; R1 := R0[0x8eb2112d]
 36 [-]: LOADK     R3 K9        ; R3 := "Execute"
 37 [-]: CALL      R1 3 1       ; R1(R2,R3)
 38 [-]: GETGLOBAL R1 K1        ; R1 := 0xae91e43b
 39 [-]: SELF      R1 R1 K10    ; R2 := R1; R1 := R1[0x32302b4a]
 40 [-]: CALL      R1 2 1       ; R1(R2)
 41 [-]: RETURN    R0 1         ; return 
 42 [-]: GETGLOBAL R1 K11       ; R1 := _T
 43 [-]: GETTABLE  R1 R1 K12    ; R82 := R1[0x8e6a7b4e]
 44 [-]: LOADK     R2 K13       ; R2 := "Menu"
 45 [-]: CALL      R1 2 2       ; R1 := R1(R2)
 46 [-]: GETUPVAL  R2 U3        ; R2 := U3
 47 [-]: EQ        1 R2 R1      ; if R2 == R1 then PC := 67
 48 [-]: JMP       67           ; PC := 67
 49 [-]: SETUPVAL  R1 U3        ; U82 := 
 50 [-]: GETGLOBAL R2 K14       ; R2 := 0x25312c9b
 51 [-]: GETGLOBAL R3 K1        ; R3 := 0xae91e43b
 52 [-]: LOADK     R4 K15       ; R4 := "_level0"
 53 [-]: LOADK     R5 0         ; R5 := 0.000000
 54 [-]: NEWTABLE  R6 1 0       ; R6 := {}
 55 [-]: LOADK     R7 10        ; R7 := 10.000000
 56 [-]: SETLIST   R6 1 1       ; R6[(1-1)*FPF+i] := R(6+i), 1 <= i <= 1
 57 [-]: NEWTABLE  R7 0 0       ; R7 := {}
 58 [-]: GETUPVAL  R8 U2        ; R8 := U2
 59 [-]: GETTABLE  R8 R8 K17    ; R82 := R8[0x06d055f9]
 60 [-]: MOVE      R9 R1        ; R9 := R1
 61 [-]: LOADK     R10 0        ; R10 := 0.000000
 62 [-]: LOADK     R11 100      ; R11 := 100.000000
 63 [-]: CALL      R8 4 0       ; R8,... := R8(R9,R10,R11)
 64 [-]: SETLIST   R7 0 1       ; R7[(1-1)*FPF+i] := R(7+i), 1 <= i <= 0
 65 [-]: LOADK     R8 K18       ; R8 := 0.200000
 66 [-]: CALL      R2 7 1       ; R2(R3,R4,R5,R6,R7,R8)
 67 [-]: GETGLOBAL R2 K11       ; R2 := _T
 68 [-]: GETTABLE  R2 R2 K19    ; R2 := R2["ComposeToolRequest"]
 69 [-]: EQ        1 R2 K20     ; if R2 == nil then PC := 178
 70 [-]: JMP       178          ; PC := 178
 71 [-]: NEWTABLE  R2 0 0       ; R2 := {}
 72 [-]: GETUPVAL  R3 U4        ; R3 := U4
 73 [-]: SELF      R3 R3 K21    ; R4 := R3; R3 := R3[0x25a6e75e]
 74 [-]: CALL      R3 2 2       ; R3 := R3(R4)
 75 [-]: SELF      R3 R3 K22    ; R4 := R3; R3 := R3[0xd8dfa041]
 76 [-]: CALL      R3 2 2       ; R3 := R3(R4)
 77 [-]: LOADK     R4 1         ; R4 := 1.000000
 78 [-]: LEN       R5 R3        ; R5 := # R3
 79 [-]: LOADK     R6 1         ; R6 := 1.000000
 80 [-]: FORPREP   R4 94        ; R4 -= R6; PC := 94
 81 [-]: GETTABLE  R8 R3 R7     ; R8 := R3[R7]
 82 [-]: GETTABLE  R8 R8 K23    ; R8 := R8["mItemType"]
 83 [-]: SELF      R8 R8 K24    ; R9 := R8; R8 := R8[0xf2deaf69]
 84 [-]: GETGLOBAL R10 K25      ; R10 := gNotePackType
 85 [-]: CALL      R8 3 2       ; R8 := R8(R9,R10)
 86 [-]: TEST      R8 0         ; if not R8 then PC := 94
 87 [-]: JMP       94           ; PC := 94
 88 [-]: GETGLOBAL R8 K26       ; R8 := 0x33bdd652
 89 [-]: GETTABLE  R8 R8 K27    ; R82 := R8[0x23d5322f]
 90 [-]: MOVE      R9 R2        ; R9 := R2
 91 [-]: GETTABLE  R10 R3 R7    ; R10 := R3[R7]
 92 [-]: GETTABLE  R10 R10 K23  ; R10 := R10["mItemType"]
 93 [-]: CALL      R8 3 1       ; R8(R9,R10)
 94 [-]: FORLOOP   R4 81        ; R4 += R6; if R4 <= R5 then begin PC := 81; R7 := R4 end
 95 [-]: GETGLOBAL R8 K28       ; R8 := 0xb009bbc6
 96 [-]: GETGLOBAL R9 K29       ; R9 := 0x53b33231
 97 [-]: CALL      R8 2 2       ; R8 := R8(R9)
 98 [-]: NEWTABLE  R9 0 0       ; R9 := {}
 99 [-]: LOADBOOL  R10 0 0      ; R10 := false
100 [-]: GETGLOBAL R11 K30      ; R11 := 0xc8802016
101 [-]: GETGLOBAL R12 K11      ; R12 := _T
102 [-]: GETTABLE  R12 R12 K19  ; R12 := R12["ComposeToolRequest"]
103 [-]: GETTABLE  R12 R12 K31  ; R12 := R12["NotePackInfo"]
104 [-]: CALL      R11 2 4      ; R11,R12,R13 := R11(R12)
105 [-]: JMP       142          ; PC := 142
106 [-]: GETTABLE  R16 R15 K32  ; R16 := R15["NotePack"]
107 [-]: GETGLOBAL R17 K0       ; R17 := 0x7b998233
108 [-]: MOVE      R18 R16      ; R18 := R16
109 [-]: CALL      R17 2 2      ; R17 := R17(R18)
110 [-]: TEST      R17 1        ; if R17 then PC := 142
111 [-]: JMP       142          ; PC := 142
112 [-]: SELF      R17 R8 K33   ; R18 := R8; R17 := R8[0x4d7a0caf]
113 [-]: MOVE      R19 R14      ; R19 := R14
114 [-]: CALL      R17 3 2      ; R17 := R17(R18,R19)
115 [-]: SELF      R17 R17 K34  ; R18 := R17; R17 := R17[0xcde10c4a]
116 [-]: CALL      R17 2 2      ; R17 := R17(R18)
117 [-]: EQ        1 R16 R17    ; if R16 == R17 then PC := 120
118 [-]: JMP       120          ; PC := 120
119 [-]: LOADBOOL  R17 0 1      ; R17 := false; PC := 120
120 [-]: LOADBOOL  R17 1 0      ; R17 := true
121 [-]: TEST      R17 1        ; if R17 then PC := 133
122 [-]: JMP       133          ; PC := 133
123 [-]: GETGLOBAL R18 K30      ; R18 := 0xc8802016
124 [-]: MOVE      R19 R2       ; R19 := R2
125 [-]: CALL      R18 2 4      ; R18,R19,R20 := R18(R19)
126 [-]: JMP       131          ; PC := 131
127 [-]: EQ        0 R16 R22    ; if R16 ~= R22 then PC := 131
128 [-]: JMP       131          ; PC := 131
129 [-]: LOADBOOL  R17 1 0      ; R17 := true
130 [-]: JMP       133          ; PC := 133
131 [-]: TFORLOOP  R18 2        ; R21,R22 :=  R18(R19,R20); if R21 ~= nil then begin PC = 127; R20 := R21 end
132 [-]: JMP       127          ; PC := 127
133 [-]: TEST      R17 0        ; if not R17 then PC := 141
134 [-]: JMP       141          ; PC := 141
135 [-]: GETGLOBAL R23 K26      ; R23 := 0x33bdd652
136 [-]: GETTABLE  R23 R23 K27  ; R82 := R23[0x23d5322f]
137 [-]: MOVE      R24 R9       ; R24 := R9
138 [-]: MOVE      R25 R15      ; R25 := R15
139 [-]: CALL      R23 3 1      ; R23(R24,R25)
140 [-]: JMP       142          ; PC := 142
141 [-]: LOADBOOL  R10 1 0      ; R10 := true
142 [-]: TFORLOOP  R11 2        ; R14,R15 :=  R11(R12,R13); if R14 ~= nil then begin PC = 106; R13 := R14 end
143 [-]: JMP       106          ; PC := 106
144 [-]: TEST      R10 0        ; if not R10 then PC := 150
145 [-]: JMP       150          ; PC := 150
146 [-]: GETUPVAL  R23 U2       ; R23 := U2
147 [-]: GETTABLE  R23 R23 K35  ; R82 := R23[0xe0cba3ca]
148 [-]: LOADK     R24 K36      ; R24 := "/Lotus/Language/Menu/Composition_NotePacksNotOwnedError"
149 [-]: CALL      R23 2 1      ; R23(R24)
150 [-]: LEN       R23 R9       ; R23 := # R9
151 [-]: EQ        0 R23 K37    ; if R23 ~= 0.000000 then PC := 169
152 [-]: JMP       169          ; PC := 169
153 [-]: LOADK     R23 0        ; R23 := 0.000000
154 [-]: LOADK     R24 2        ; R24 := 2.000000
155 [-]: LOADK     R25 1        ; R25 := 1.000000
156 [-]: FORPREP   R23 168      ; R23 -= R25; PC := 168
157 [-]: GETGLOBAL R27 K26      ; R27 := 0x33bdd652
158 [-]: GETTABLE  R27 R27 K27  ; R82 := R27[0x23d5322f]
159 [-]: MOVE      R28 R9       ; R28 := R9
160 [-]: NEWTABLE  R29 0 2      ; R29 := {}
161 [-]: SETTABLE  R29 K39 R26  ; R29["NoteType"] := R26
162 [-]: GETUPVAL  R30 U5       ; R30 := U5
163 [-]: SELF      R30 R30 K33  ; R31 := R30; R30 := R30[0x4d7a0caf]
164 [-]: MOVE      R32 R26      ; R32 := R26
165 [-]: CALL      R30 3 2      ; R30 := R30(R31,R32)
166 [-]: SETTABLE  R29 K32 R30  ; R29["NotePack"] := R30
167 [-]: CALL      R27 3 1      ; R27(R28,R29)
168 [-]: FORLOOP   R23 157      ; R23 += R25; if R23 <= R24 then begin PC := 157; R26 := R23 end
169 [-]: GETUPVAL  R27 U6       ; R27 := U6
170 [-]: GETUPVAL  R28 U5       ; R28 := U5
171 [-]: MOVE      R29 R9       ; R29 := R9
172 [-]: GETGLOBAL R30 K11      ; R30 := _T
173 [-]: GETTABLE  R30 R30 K19  ; R30 := R30["ComposeToolRequest"]
174 [-]: GETTABLE  R30 R30 K40  ; R30 := R30["FingerPrint"]
175 [-]: CALL      R27 4 1      ; R27(R28,R29,R30)
176 [-]: GETGLOBAL R27 K11      ; R27 := _T
177 [-]: SETTABLE  R27 K19 K20  ; R27["ComposeToolRequest"] := nil
178 [-]: GETUPVAL  R27 U7       ; R27 := U7
179 [-]: CALL      R27 1 1      ; R27()
180 [-]: GETUPVAL  R27 U8       ; R27 := U8
181 [-]: CALL      R27 1 1      ; R27()
182 [-]: GETUPVAL  R27 U9       ; R27 := U9
183 [-]: GETUPVAL  R28 U10      ; R28 := U10
184 [-]: GETTABLE  R28 R28 K41  ; R28 := R28["UI_MODE_IN_GAME"]
185 [-]: EQ        0 R27 R28    ; if R27 ~= R28 then PC := 189
186 [-]: JMP       189          ; PC := 189
187 [-]: GETUPVAL  R27 U11      ; R27 := U11
188 [-]: CALL      R27 1 1      ; R27()
189 [-]: RETURN    R0 1         ; return 


; Function #59:
;
; Name:            
; Defined at line: 1678
; #Upvalues:       0
; #Parameters:     0
; Is_vararg:       0
; Max Stack Size:  2

  1 [-]: LOADBOOL  R0 1 0       ; R0 := true
  2 [-]: RETURN    R0 2         ; return R0
  3 [-]: RETURN    R0 1         ; return 


; Function #60:
;
; Name:            
; Defined at line: 1682
; #Upvalues:       1
; #Parameters:     0
; Is_vararg:       0
; Max Stack Size:  2

  1 [-]: GETUPVAL  R0 U0        ; R0 := U0
  2 [-]: GETTABLE  R0 R0 K0     ; R0 := R0["inputBlocked"]
  3 [-]: RETURN    R0 2         ; return R0
  4 [-]: RETURN    R0 1         ; return 


; Function #61:
;
; Name:            
; Defined at line: 1686
; #Upvalues:       2
; #Parameters:     4
; Is_vararg:       0
; Max Stack Size:  6

  1 [-]: GETUPVAL  R4 U0        ; R4 := U0
  2 [-]: CALL      R4 1 1       ; R4()
  3 [-]: GETGLOBAL R4 K0        ; R4 := 0x7b998233
  4 [-]: GETUPVAL  R5 U1        ; R5 := U1
  5 [-]: CALL      R4 2 2       ; R4 := R4(R5)
  6 [-]: TEST      R4 1         ; if R4 then PC := 12
  7 [-]: JMP       12           ; PC := 12
  8 [-]: GETUPVAL  R4 U1        ; R4 := U1
  9 [-]: GETTABLE  R4 R4 K1     ; R4 := R4["CustomizationList"]
 10 [-]: SELF      R4 R4 K2     ; R5 := R4; R4 := R4[0x4859e88d]
 11 [-]: CALL      R4 2 1       ; R4(R5)
 12 [-]: RETURN    R0 1         ; return 


; Function #62:
;
; Name:            
; Defined at line: 1694
; #Upvalues:       1
; #Parameters:     0
; Is_vararg:       0
; Max Stack Size:  7

  1 [-]: GETUPVAL  R0 U0        ; R0 := U0
  2 [-]: SELF      R0 R0 K0     ; R1 := R0; R0 := R0[0x986d2ab8]
  3 [-]: GETGLOBAL R2 K1        ; R2 := 0x0469f296
  4 [-]: LOADK     R3 K2        ; R3 := "UnlitAtten"
  5 [-]: CALL      R2 2 2       ; R2 := R2(R3)
  6 [-]: LOADK     R3 2         ; R3 := 2.250000
  7 [-]: LOADK     R4 0         ; R4 := 0.000000
  8 [-]: LOADK     R5 0         ; R5 := 0.000000
  9 [-]: CALL      R0 6 1       ; R0(R1,R2,R3,R4,R5)
 10 [-]: GETGLOBAL R0 K3        ; R0 := 0x25312c9b
 11 [-]: GETGLOBAL R1 K4        ; R1 := 0xae91e43b
 12 [-]: LOADK     R2 K5        ; R2 := "ScrubCallout"
 13 [-]: LOADK     R3 2         ; R3 := 2.000000
 14 [-]: NEWTABLE  R4 1 0       ; R4 := {}
 15 [-]: LOADK     R5 10        ; R5 := 10.000000
 16 [-]: SETLIST   R4 1 1       ; R4[(1-1)*FPF+i] := R(4+i), 1 <= i <= 1
 17 [-]: NEWTABLE  R5 1 0       ; R5 := {}
 18 [-]: LOADK     R6 100       ; R6 := 100.000000
 19 [-]: SETLIST   R5 1 1       ; R5[(1-1)*FPF+i] := R(5+i), 1 <= i <= 1
 20 [-]: LOADK     R6 K7        ; R6 := 0.150000
 21 [-]: CALL      R0 7 1       ; R0(R1,R2,R3,R4,R5,R6)
 22 [-]: RETURN    R0 1         ; return 


; Function #63:
;
; Name:            
; Defined at line: 1710
; #Upvalues:       3
; #Parameters:     0
; Is_vararg:       0
; Max Stack Size:  5

  1 [-]: GETGLOBAL R0 K0        ; R0 := 0x7b998233
  2 [-]: GETUPVAL  R1 U0        ; R1 := U0
  3 [-]: CALL      R0 2 2       ; R0 := R0(R1)
  4 [-]: TEST      R0 1         ; if R0 then PC := 27
  5 [-]: JMP       27           ; PC := 27
  6 [-]: GETGLOBAL R0 K0        ; R0 := 0x7b998233
  7 [-]: GETUPVAL  R1 U1        ; R1 := U1
  8 [-]: GETTABLE  R1 R1 K1     ; R1 := R1["CustomizationList"]
  9 [-]: GETTABLE  R1 R1 K2     ; R1 := R1["mSelectedElement"]
 10 [-]: CALL      R0 2 2       ; R0 := R0(R1)
 11 [-]: TEST      R0 1         ; if R0 then PC := 27
 12 [-]: JMP       27           ; PC := 27
 13 [-]: GETUPVAL  R0 U2        ; R0 := U2
 14 [-]: GETUPVAL  R1 U1        ; R1 := U1
 15 [-]: GETTABLE  R1 R1 K1     ; R1 := R1["CustomizationList"]
 16 [-]: GETTABLE  R1 R1 K2     ; R1 := R1["mSelectedElement"]
 17 [-]: GETTABLE  R1 R1 K3     ; R1 := R1["NoteType"]
 18 [-]: GETUPVAL  R2 U0        ; R2 := U0
 19 [-]: SELF      R2 R2 K4     ; R3 := R2; R2 := R2[0x10e0b4a3]
 20 [-]: GETUPVAL  R4 U1        ; R4 := U1
 21 [-]: GETTABLE  R4 R4 K1     ; R4 := R4["CustomizationList"]
 22 [-]: GETTABLE  R4 R4 K2     ; R4 := R4["mSelectedElement"]
 23 [-]: GETTABLE  R4 R4 K3     ; R4 := R4["NoteType"]
 24 [-]: CALL      R2 3 2       ; R2 := R2(R3,R4)
 25 [-]: NOT       R2 R2        ; R2 := not R2
 26 [-]: CALL      R0 3 1       ; R0(R1,R2)
 27 [-]: RETURN    R0 1         ; return 


; Function #64:
;
; Name:            
; Defined at line: 1716
; #Upvalues:       1
; #Parameters:     0
; Is_vararg:       0
; Max Stack Size:  2

  1 [-]: GETUPVAL  R0 U0        ; R0 := U0
  2 [-]: LOADK     R1 0         ; R1 := 0.000000
  3 [-]: CALL      R0 2 1       ; R0(R1)
  4 [-]: RETURN    R0 1         ; return 


; Function #65:
;
; Name:            
; Defined at line: 1720
; #Upvalues:       1
; #Parameters:     0
; Is_vararg:       0
; Max Stack Size:  2

  1 [-]: GETUPVAL  R0 U0        ; R0 := U0
  2 [-]: LOADK     R1 1         ; R1 := 1.000000
  3 [-]: CALL      R0 2 1       ; R0(R1)
  4 [-]: RETURN    R0 1         ; return 


; Function #66:
;
; Name:            
; Defined at line: 1724
; #Upvalues:       1
; #Parameters:     0
; Is_vararg:       0
; Max Stack Size:  2

  1 [-]: GETUPVAL  R0 U0        ; R0 := U0
  2 [-]: LOADK     R1 2         ; R1 := 2.000000
  3 [-]: CALL      R0 2 1       ; R0(R1)
  4 [-]: RETURN    R0 1         ; return 


; Function #67:
;
; Name:            
; Defined at line: 1728
; #Upvalues:       1
; #Parameters:     0
; Is_vararg:       0
; Max Stack Size:  2

  1 [-]: GETUPVAL  R0 U0        ; R0 := U0
  2 [-]: CALL      R0 1 1       ; R0()
  3 [-]: RETURN    R0 1         ; return 


; Function #68:
;
; Name:            
; Defined at line: 1732
; #Upvalues:       1
; #Parameters:     0
; Is_vararg:       0
; Max Stack Size:  2

  1 [-]: GETUPVAL  R0 U0        ; R0 := U0
  2 [-]: CALL      R0 1 1       ; R0()
  3 [-]: RETURN    R0 1         ; return 


; Function #69:
;
; Name:            
; Defined at line: 1736
; #Upvalues:       1
; #Parameters:     0
; Is_vararg:       0
; Max Stack Size:  2

  1 [-]: GETUPVAL  R0 U0        ; R0 := U0
  2 [-]: CALL      R0 1 1       ; R0()
  3 [-]: RETURN    R0 1         ; return 


; Function #70:
;
; Name:            
; Defined at line: 1740
; #Upvalues:       7
; #Parameters:     3
; Is_vararg:       0
; Max Stack Size:  17

  1 [-]: ADD       R3 K1 R0     ; R3 := 0.000000 + R0
  2 [-]: GETGLOBAL R4 K2        ; R4 := 0x64fb1586
  3 [-]: MOVE      R5 R1        ; R5 := R1
  4 [-]: CALL      R4 2 2       ; R4 := R4(R5)
  5 [-]: SETUPVAL  R4 U0        ; U82 := 
  6 [-]: GETGLOBAL R4 K3        ; R4 := 0xae91e43b
  7 [-]: SELF      R4 R4 K4     ; R5 := R4; R4 := R4[0xaade900e]
  8 [-]: LOADK     R6 K5        ; R6 := "ScrubBtn"
  9 [-]: LOADK     R7 59        ; R7 := 59.000000
 10 [-]: LOADBOOL  R8 0 0       ; R8 := false
 11 [-]: CALL      R4 5 1       ; R4(R5,R6,R7,R8)
 12 [-]: GETGLOBAL R4 K3        ; R4 := 0xae91e43b
 13 [-]: SELF      R4 R4 K4     ; R5 := R4; R4 := R4[0xaade900e]
 14 [-]: LOADK     R6 K6        ; R6 := "AreaPicker"
 15 [-]: LOADK     R7 11        ; R7 := 11.000000
 16 [-]: LOADBOOL  R8 0 0       ; R8 := false
 17 [-]: CALL      R4 5 1       ; R4(R5,R6,R7,R8)
 18 [-]: GETGLOBAL R4 K3        ; R4 := 0xae91e43b
 19 [-]: SELF      R4 R4 K4     ; R5 := R4; R4 := R4[0xaade900e]
 20 [-]: LOADK     R6 K6        ; R6 := "AreaPicker"
 21 [-]: LOADK     R7 59        ; R7 := 59.000000
 22 [-]: LOADBOOL  R8 0 0       ; R8 := false
 23 [-]: CALL      R4 5 1       ; R4(R5,R6,R7,R8)
 24 [-]: GETGLOBAL R4 K3        ; R4 := 0xae91e43b
 25 [-]: SELF      R4 R4 K4     ; R5 := R4; R4 := R4[0xaade900e]
 26 [-]: LOADK     R6 K7        ; R6 := "Tip"
 27 [-]: LOADK     R7 11        ; R7 := 11.000000
 28 [-]: LOADBOOL  R8 0 0       ; R8 := false
 29 [-]: CALL      R4 5 1       ; R4(R5,R6,R7,R8)
 30 [-]: GETGLOBAL R4 K3        ; R4 := 0xae91e43b
 31 [-]: SELF      R4 R4 K4     ; R5 := R4; R4 := R4[0xaade900e]
 32 [-]: LOADK     R6 K8        ; R6 := "AbilityIcons"
 33 [-]: LOADK     R7 11        ; R7 := 11.000000
 34 [-]: LOADBOOL  R8 0 0       ; R8 := false
 35 [-]: CALL      R4 5 1       ; R4(R5,R6,R7,R8)
 36 [-]: GETGLOBAL R4 K3        ; R4 := 0xae91e43b
 37 [-]: SELF      R4 R4 K4     ; R5 := R4; R4 := R4[0xaade900e]
 38 [-]: LOADK     R6 K8        ; R6 := "AbilityIcons"
 39 [-]: LOADK     R7 59        ; R7 := 59.000000
 40 [-]: LOADBOOL  R8 0 0       ; R8 := false
 41 [-]: CALL      R4 5 1       ; R4(R5,R6,R7,R8)
 42 [-]: LOADK     R4 1         ; R4 := 1.000000
 43 [-]: LOADK     R5 16        ; R5 := 16.000000
 44 [-]: LOADK     R6 1         ; R6 := 1.000000
 45 [-]: FORPREP   R4 64        ; R4 -= R6; PC := 64
 46 [-]: GETGLOBAL R8 K3        ; R8 := 0xae91e43b
 47 [-]: SELF      R8 R8 K9     ; R9 := R8; R8 := R8[0xf64b7262]
 48 [-]: LOADK     R10 K10      ; R10 := "Grid.FourthLine"
 49 [-]: MOVE      R11 R7       ; R11 := R7
 50 [-]: CONCAT    R10 R10 R11  ; R10 := R10 .. R11
 51 [-]: LOADK     R11 K11      ; R11 := "Delimiter"
 52 [-]: LOADK     R12 10       ; R12 := 10.000000
 53 [-]: LOADK     R13 30       ; R13 := 30.000000
 54 [-]: CALL      R8 6 1       ; R8(R9,R10,R11,R12,R13)
 55 [-]: GETGLOBAL R8 K3        ; R8 := 0xae91e43b
 56 [-]: SELF      R8 R8 K9     ; R9 := R8; R8 := R8[0xf64b7262]
 57 [-]: LOADK     R10 K10      ; R10 := "Grid.FourthLine"
 58 [-]: MOVE      R11 R7       ; R11 := R7
 59 [-]: CONCAT    R10 R10 R11  ; R10 := R10 .. R11
 60 [-]: LOADK     R11 K12      ; R11 := "Delimiter2"
 61 [-]: LOADK     R12 10       ; R12 := 10.000000
 62 [-]: LOADK     R13 30       ; R13 := 30.000000
 63 [-]: CALL      R8 6 1       ; R8(R9,R10,R11,R12,R13)
 64 [-]: FORLOOP   R4 46        ; R4 += R6; if R4 <= R5 then begin PC := 46; R7 := R4 end
 65 [-]: LOADK     R8 1         ; R8 := 1.000000
 66 [-]: LOADK     R9 4         ; R9 := 4.000000
 67 [-]: LOADK     R10 1        ; R10 := 1.000000
 68 [-]: FORPREP   R8 77        ; R8 -= R10; PC := 77
 69 [-]: GETGLOBAL R12 K3       ; R12 := 0xae91e43b
 70 [-]: SELF      R12 R12 K4   ; R13 := R12; R12 := R12[0xaade900e]
 71 [-]: LOADK     R14 K13      ; R14 := "Grid.Marker"
 72 [-]: MOVE      R15 R11      ; R15 := R11
 73 [-]: CONCAT    R14 R14 R15  ; R14 := R14 .. R15
 74 [-]: LOADK     R15 11       ; R15 := 11.000000
 75 [-]: LOADBOOL  R16 0 0      ; R16 := false
 76 [-]: CALL      R12 5 1      ; R12(R13,R14,R15,R16)
 77 [-]: FORLOOP   R8 69        ; R8 += R10; if R8 <= R9 then begin PC := 69; R11 := R8 end
 78 [-]: GETUPVAL  R12 U1       ; R12 := U1
 79 [-]: SELF      R12 R12 K14  ; R13 := R12; R12 := R12[0x6caac40b]
 80 [-]: LOADK     R14 2        ; R14 := 2.000000
 81 [-]: GETGLOBAL R15 K15      ; R15 := _T
 82 [-]: GETTABLE  R15 R15 R2   ; R15 := R15[R2]
 83 [-]: CALL      R12 4 1      ; R12(R13,R14,R15)
 84 [-]: GETUPVAL  R12 U1       ; R12 := U1
 85 [-]: SELF      R12 R12 K14  ; R13 := R12; R12 := R12[0x6caac40b]
 86 [-]: LOADK     R14 1        ; R14 := 1.000000
 87 [-]: GETGLOBAL R15 K15      ; R15 := _T
 88 [-]: GETTABLE  R15 R15 R2   ; R15 := R15[R2]
 89 [-]: CALL      R12 4 1      ; R12(R13,R14,R15)
 90 [-]: GETUPVAL  R12 U1       ; R12 := U1
 91 [-]: SELF      R12 R12 K14  ; R13 := R12; R12 := R12[0x6caac40b]
 92 [-]: LOADK     R14 0        ; R14 := 0.000000
 93 [-]: GETGLOBAL R15 K15      ; R15 := _T
 94 [-]: GETTABLE  R15 R15 R2   ; R15 := R15[R2]
 95 [-]: CALL      R12 4 1      ; R12(R13,R14,R15)
 96 [-]: GETUPVAL  R12 U1       ; R12 := U1
 97 [-]: SELF      R12 R12 K16  ; R13 := R12; R12 := R12[0x687ae094]
 98 [-]: CALL      R12 2 1      ; R12(R13)
 99 [-]: GETUPVAL  R12 U2       ; R12 := U2
100 [-]: CALL      R12 1 1      ; R12()
101 [-]: GETUPVAL  R12 U3       ; R12 := U3
102 [-]: LOADK     R13 1        ; R13 := 1.000000
103 [-]: CALL      R12 2 1      ; R12(R13)
104 [-]: SETUPVAL  R3 U4        ; U82 := 
105 [-]: LOADK     R12 1        ; R12 := 1.000000
106 [-]: SETUPVAL  R12 U5       ; U82 := 
107 [-]: GETUPVAL  R12 U6       ; R12 := U6
108 [-]: CALL      R12 1 1      ; R12()
109 [-]: RETURN    R0 1         ; return 


; Function #71:
;
; Name:            
; Defined at line: 1776
; #Upvalues:       2
; #Parameters:     0
; Is_vararg:       0
; Max Stack Size:  8

  1 [-]: GETUPVAL  R0 U0        ; R0 := U0
  2 [-]: TEST      R0 0         ; if not R0 then PC := 18
  3 [-]: JMP       18           ; PC := 18
  4 [-]: GETGLOBAL R0 K0        ; R0 := 0x25312c9b
  5 [-]: GETGLOBAL R1 K1        ; R1 := 0xae91e43b
  6 [-]: LOADK     R2 K2        ; R2 := "_root"
  7 [-]: LOADK     R3 0         ; R3 := 0.000000
  8 [-]: NEWTABLE  R4 1 0       ; R4 := {}
  9 [-]: LOADK     R5 10        ; R5 := 10.000000
 10 [-]: SETLIST   R4 1 1       ; R4[(1-1)*FPF+i] := R(4+i), 1 <= i <= 1
 11 [-]: NEWTABLE  R5 1 0       ; R5 := {}
 12 [-]: LOADK     R6 100       ; R6 := 100.000000
 13 [-]: SETLIST   R5 1 1       ; R5[(1-1)*FPF+i] := R(5+i), 1 <= i <= 1
 14 [-]: LOADK     R6 K4        ; R6 := 0.300000
 15 [-]: LOADK     R7 0         ; R7 := 0.000000
 16 [-]: CALL      R0 8 1       ; R0(R1,R2,R3,R4,R5,R6,R7)
 17 [-]: JMP       31           ; PC := 31
 18 [-]: GETGLOBAL R0 K0        ; R0 := 0x25312c9b
 19 [-]: GETGLOBAL R1 K1        ; R1 := 0xae91e43b
 20 [-]: LOADK     R2 K2        ; R2 := "_root"
 21 [-]: LOADK     R3 0         ; R3 := 0.000000
 22 [-]: NEWTABLE  R4 1 0       ; R4 := {}
 23 [-]: LOADK     R5 10        ; R5 := 10.000000
 24 [-]: SETLIST   R4 1 1       ; R4[(1-1)*FPF+i] := R(4+i), 1 <= i <= 1
 25 [-]: NEWTABLE  R5 1 0       ; R5 := {}
 26 [-]: LOADK     R6 0         ; R6 := 0.000000
 27 [-]: SETLIST   R5 1 1       ; R5[(1-1)*FPF+i] := R(5+i), 1 <= i <= 1
 28 [-]: LOADK     R6 K4        ; R6 := 0.300000
 29 [-]: LOADK     R7 0         ; R7 := 0.000000
 30 [-]: CALL      R0 8 1       ; R0(R1,R2,R3,R4,R5,R6,R7)
 31 [-]: GETUPVAL  R0 U0        ; R0 := U0
 32 [-]: NOT       R0 R0        ; R0 := not R0
 33 [-]: SETUPVAL  R0 U0        ; U82 := 
 34 [-]: GETGLOBAL R0 K5        ; R0 := _T
 35 [-]: GETUPVAL  R1 U0        ; R1 := U0
 36 [-]: SETTABLE  R0 K6 R1     ; R0["CompositionToolPuzzleHidden"] := R1
 37 [-]: GETUPVAL  R0 U1        ; R0 := U1
 38 [-]: CALL      R0 1 1       ; R0()
 39 [-]: RETURN    R0 1         ; return 


; Function #72:
;
; Name:            
; Defined at line: 1787
; #Upvalues:       1
; #Parameters:     0
; Is_vararg:       0
; Max Stack Size:  3

  1 [-]: GETGLOBAL R0 K0        ; R0 := 0x7b998233
  2 [-]: GETUPVAL  R1 U0        ; R1 := U0
  3 [-]: CALL      R0 2 2       ; R0 := R0(R1)
  4 [-]: TEST      R0 1         ; if R0 then PC := 10
  5 [-]: JMP       10           ; PC := 10
  6 [-]: GETUPVAL  R0 U0        ; R0 := U0
  7 [-]: SELF      R0 R0 K1     ; R1 := R0; R0 := R0[0x458592ad]
  8 [-]: LOADK     R2 0         ; R2 := 0.000000
  9 [-]: CALL      R0 3 1       ; R0(R1,R2)
 10 [-]: RETURN    R0 1         ; return 


; Function #73:
;
; Name:            
; Defined at line: 1793
; #Upvalues:       2
; #Parameters:     0
; Is_vararg:       0
; Max Stack Size:  2

  1 [-]: GETUPVAL  R0 U0        ; R0 := U0
  2 [-]: GETTABLE  R0 R0 K0     ; R0 := R0["inputBlocked"]
  3 [-]: TEST      R0 1         ; if R0 then PC := 9
  4 [-]: JMP       9            ; PC := 9
  5 [-]: GETUPVAL  R0 U1        ; R0 := U1
  6 [-]: CALL      R0 1 1       ; R0()
  7 [-]: LOADBOOL  R0 1 0       ; R0 := true
  8 [-]: RETURN    R0 2         ; return R0
  9 [-]: RETURN    R0 1         ; return 


; Function #74:
;
; Name:            
; Defined at line: 1800
; #Upvalues:       3
; #Parameters:     2
; Is_vararg:       0
; Max Stack Size:  8

  1 [-]: GETGLOBAL R2 K0        ; R2 := 0xae91e43b
  2 [-]: SELF      R2 R2 K1     ; R3 := R2; R2 := R2[0x91a24e4b]
  3 [-]: LOADK     R4 K2        ; R4 := "_root"
  4 [-]: LOADK     R5 25        ; R5 := 25.000000
  5 [-]: CALL      R2 4 2       ; R2 := R2(R3,R4,R5)
  6 [-]: GETUPVAL  R3 U0        ; R3 := U0
  7 [-]: GETTABLE  R3 R3 K3     ; R3 := R3["x"]
  8 [-]: GETUPVAL  R4 U0        ; R4 := U0
  9 [-]: GETTABLE  R4 R4 K4     ; R4 := R4["width"]
 10 [-]: ADD       R3 R3 R4     ; R3 := R3 + R4
 11 [-]: GETUPVAL  R4 U0        ; R4 := U0
 12 [-]: GETTABLE  R4 R4 K3     ; R4 := R4["x"]
 13 [-]: LT        0 R4 R2      ; if R4 >= R2 then PC := 26
 14 [-]: JMP       26           ; PC := 26
 15 [-]: LT        0 R2 R3      ; if R2 >= R3 then PC := 26
 16 [-]: JMP       26           ; PC := 26
 17 [-]: GETUPVAL  R4 U1        ; R4 := U1
 18 [-]: SELF      R4 R4 K5     ; R5 := R4; R4 := R4[0x8a8eba7f]
 19 [-]: GETGLOBAL R6 K6        ; R6 := 0x03f57322
 20 [-]: MOVE      R7 R1        ; R7 := R1
 21 [-]: CALL      R6 2 0       ; R6,... := R6(R7)
 22 [-]: CALL      R4 0 1       ; R4(R5,...)
 23 [-]: LOADBOOL  R4 1 0       ; R4 := true
 24 [-]: RETURN    R4 2         ; return R4
 25 [-]: JMP       31           ; PC := 31
 26 [-]: GETUPVAL  R4 U2        ; R4 := U2
 27 [-]: EQ        1 R4 K7      ; if R4 == "" then PC := 31
 28 [-]: JMP       31           ; PC := 31
 29 [-]: LOADBOOL  R4 0 0       ; R4 := false
 30 [-]: RETURN    R4 2         ; return R4
 31 [-]: RETURN    R0 1         ; return 


; Function #75:
;
; Name:            
; Defined at line: 1813
; #Upvalues:       4
; #Parameters:     3
; Is_vararg:       0
; Max Stack Size:  6

  1 [-]: GETUPVAL  R3 U0        ; R3 := U0
  2 [-]: TEST      R3 0         ; if not R3 then PC := 8
  3 [-]: JMP       8            ; PC := 8
  4 [-]: EQ        0 R1 K0      ; if R1 ~= "EN_ENTER" then PC := 8
  5 [-]: JMP       8            ; PC := 8
  6 [-]: GETGLOBAL R3 K1        ; R3 := _T
  7 [-]: SETTABLE  R3 K2 K3     ; R3["CompositionToolPuzzleSolved"] := true
  8 [-]: GETUPVAL  R3 U1        ; R3 := U1
  9 [-]: EQ        0 R3 K4      ; if R3 ~= "" then PC := 16
 10 [-]: JMP       16           ; PC := 16
 11 [-]: GETUPVAL  R3 U2        ; R3 := U2
 12 [-]: GETTABLE  R3 R3 K5     ; R82 := R3[0x87ca1105]
 13 [-]: CALL      R3 1 2       ; R3 := R3()
 14 [-]: TEST      R3 0         ; if not R3 then PC := 17
 15 [-]: JMP       17           ; PC := 17
 16 [-]: RETURN    R0 1         ; return 
 17 [-]: GETGLOBAL R3 K6        ; R3 := 0x7f5022cf
 18 [-]: GETTABLE  R3 R3 K7     ; R82 := R3[0xa5c556b9]
 19 [-]: MOVE      R4 R1        ; R4 := R1
 20 [-]: LOADK     R5 K8        ; R5 := "_SPACE"
 21 [-]: CALL      R3 3 2       ; R3 := R3(R4,R5)
 22 [-]: TEST      R3 0         ; if not R3 then PC := 28
 23 [-]: JMP       28           ; PC := 28
 24 [-]: EQ        0 R2 K9      ; if R2 ~= "0" then PC := 28
 25 [-]: JMP       28           ; PC := 28
 26 [-]: GETUPVAL  R3 U3        ; R3 := U3
 27 [-]: CALL      R3 1 1       ; R3()
 28 [-]: RETURN    R0 1         ; return 


