; Name:            
; Defined at line: 1
; #Upvalues:       0
; #Parameters:     0
; Is_vararg:       1
; Max Stack Size:  59

       1 [-]: GETIMPORT R0 1; var0 = 0xBE190284
       2 [-]: GETIMPORT R1 3; var1 = 0x89326C93
       3 [-]: NAMECALL R1 R1 K4; var2 = var1; var1 = var1[0x29EF273D]
       4 [-]: CALL R1 2 2  ; var1 = var1(var2)
       5 [-]: NAMECALL R1 R1 K5; var2 = var1; var1 = var1[0x66905CB0]
       6 [-]: CALL R1 2 2  ; var1 = var1(var2)
       7 [-]: GETIMPORT R2 7; var2 = 0x2D0FAD09
       8 [-]: LOADK R3 K8  ; var3 = "Lotus.Scripts.Libs.TableLib"
       9 [-]: CALL R2 2 2  ; var2 = var2(var3)
      10 [-]: GETIMPORT R3 7; var3 = 0x2D0FAD09
      11 [-]: LOADK R4 K9  ; var4 = "Lotus.Interface.LotusUtilities"
      12 [-]: CALL R3 2 2  ; var3 = var3(var4)
      13 [-]: GETIMPORT R4 7; var4 = 0x2D0FAD09
      14 [-]: LOADK R5 K10 ; var5 = "Lotus.Scripts.Libs.TransmissionSet"
      15 [-]: CALL R4 2 2  ; var4 = var4(var5)
      16 [-]: GETIMPORT R5 7; var5 = 0x2D0FAD09
      17 [-]: LOADK R6 K11 ; var6 = "Lotus.Scripts.Libs.GameplayUtilities"
      18 [-]: CALL R5 2 2  ; var5 = var5(var6)
      19 [-]: GETIMPORT R6 7; var6 = 0x2D0FAD09
      20 [-]: LOADK R7 K12 ; var7 = "Lotus.Scripts.Libs.ObjectiveText"
      21 [-]: CALL R6 2 2  ; var6 = var6(var7)
      22 [-]: GETIMPORT R7 14; var7 = 0x0469F296
      23 [-]: LOADK R8 K15 ; var8 = "GhostsDestroyed"
      24 [-]: CALL R7 2 2  ; var7 = var7(var8)
      25 [-]: LOADNIL R8   ; var8 = nil
      26 [-]: LOADNIL R9   ; var9 = nil
      27 [-]: GETIMPORT R10 17; var10 = 0xB009BBC6
      28 [-]: LOADK R11 K18; var11 = "/Lotus/Sounds/Gameplay/VoidTower/VoidTowerCaptureDisrupted"
      29 [-]: CALL R10 2 2 ; var10 = var10(var11)
      30 [-]: GETIMPORT R11 17; var11 = 0xB009BBC6
      31 [-]: CALL R11 1 2 ; var11 = var11()
      32 [-]: GETIMPORT R12 17; var12 = 0xB009BBC6
      33 [-]: CALL R12 1 2 ; var12 = var12()
      34 [-]: GETIMPORT R13 20; var13 = 0x7ED0A956
      35 [-]: LOADK R14 K21; var14 = "/Lotus/Types/Enemies/Grineer/Vip/GrineerRoyalGuard/GrineerRoyalGuardAvatar"
      36 [-]: CALL R13 2 2 ; var13 = var13(var14)
      37 [-]: GETIMPORT R14 17; var14 = 0xB009BBC6
      38 [-]: LOADK R15 K22; var15 = "/Lotus/Fx/Enemies/CaptainVor/CptVorAddsTeleportIn"
      39 [-]: CALL R14 2 2 ; var14 = var14(var15)
      40 [-]: GETIMPORT R15 20; var15 = 0x7ED0A956
      41 [-]: LOADK R16 K23; var16 = "/Lotus/Types/Game/GhostTower/GhostSpawnWaypoint"
      42 [-]: CALL R15 2 2 ; var15 = var15(var16)
      43 [-]: GETIMPORT R16 20; var16 = 0x7ED0A956
      44 [-]: LOADK R17 K24; var17 = "/Lotus/Types/Game/GhostTower/GhostTowerWaypoint"
      45 [-]: CALL R16 2 2 ; var16 = var16(var17)
      46 [-]: GETIMPORT R17 17; var17 = 0xB009BBC6
      47 [-]: LOADK R18 K25; var18 = "/Lotus/Types/Items/MiscItems/Kuva"
      48 [-]: CALL R17 2 2 ; var17 = var17(var18)
      49 [-]: GETIMPORT R18 20; var18 = 0x7ED0A956
      50 [-]: LOADK R19 K26; var19 = "/Lotus/Types/Enemies/Grineer/GhostTower/GhostAvatar"
      51 [-]: CALL R18 2 2 ; var18 = var18(var19)
      52 [-]: GETIMPORT R19 28; var19 = 0x88EFC25E
      53 [-]: LOADK R20 K29; var20 = "/Lotus/Fx/Gameplay/NegationTower/NegTowerPlayerAttachSpawner"
      54 [-]: CALL R19 2 2 ; var19 = var19(var20)
      55 [-]: GETIMPORT R20 17; var20 = 0xB009BBC6
      56 [-]: LOADK R21 K30; var21 = "/Lotus/Interface/Icons/GameModes/KuvaSiphonIcon.png"
      57 [-]: CALL R20 2 2 ; var20 = var20(var21)
      58 [-]: LOADB R21 0  ; var21 = false
      59 [-]: LOADB R22 0  ; var22 = false
      60 [-]: NEWTABLE R23 0 0; var23 = {}
      61 [-]: LOADN R24 0  ; var24 = 0
      62 [-]: LOADNIL R25  ; var25 = nil
      63 [-]: LOADNIL R26  ; var26 = nil
      64 [-]: LOADNIL R27  ; var27 = nil
      65 [-]: NEWTABLE R28 0 0; var28 = {}
      66 [-]: LOADN R29 2  ; var29 = 2
      67 [-]: LOADN R30 8  ; var30 = 8
      68 [-]: LOADN R31 0  ; var31 = 0
      69 [-]: NEWTABLE R32 0 0; var32 = {}
      70 [-]: NEWTABLE R33 0 0; var33 = {}
      71 [-]: NEWCLOSURE R34 P0; 
      72 [-]: CAPTURE REF R29; 
      73 [-]: CAPTURE REF R23; 
      74 [-]: CAPTURE REF R30; 
      75 [-]: DUPCLOSURE R35 K31; 
      76 [-]: DUPCLOSURE R36 K32; 
      77 [-]: DUPCLOSURE R37 K33; 
      78 [-]: NEWCLOSURE R38 P4; 
      79 [-]: CAPTURE VAL R28; 
      80 [-]: CAPTURE REF R27; 
      81 [-]: NEWCLOSURE R39 P5; 
      82 [-]: CAPTURE REF R27; 
      83 [-]: CAPTURE VAL R28; 
      84 [-]: CAPTURE VAL R2; 
      85 [-]: CAPTURE VAL R38; 
      86 [-]: CAPTURE VAL R33; 
      87 [-]: CAPTURE VAL R1; 
      88 [-]: CAPTURE VAL R12; 
      89 [-]: NEWCLOSURE R40 P6; 
      90 [-]: CAPTURE REF R27; 
      91 [-]: CAPTURE VAL R33; 
      92 [-]: NEWCLOSURE R41 P7; 
      93 [-]: CAPTURE REF R31; 
      94 [-]: CAPTURE VAL R40; 
      95 [-]: CAPTURE VAL R33; 
      96 [-]: CAPTURE VAL R1; 
      97 [-]: CAPTURE VAL R14; 
      98 [-]: DUPCLOSURE R42 K34; 
      99 [-]: CAPTURE VAL R33; 
     100 [-]: NEWCLOSURE R43 P9; 
     101 [-]: CAPTURE VAL R1; 
     102 [-]: CAPTURE VAL R33; 
     103 [-]: CAPTURE REF R30; 
     104 [-]: CAPTURE VAL R40; 
     105 [-]: CAPTURE VAL R32; 
     106 [-]: CAPTURE VAL R14; 
     107 [-]: NEWCLOSURE R44 P10; 
     108 [-]: CAPTURE VAL R10; 
     109 [-]: CAPTURE REF R27; 
     110 [-]: CAPTURE VAL R19; 
     111 [-]: CAPTURE VAL R4; 
     112 [-]: SETGLOBAL R44 K35; "OnDamaged" = var44
     113 [-]: NEWCLOSURE R44 P11; 
     114 [-]: CAPTURE REF R27; 
     115 [-]: CAPTURE VAL R28; 
     116 [-]: CAPTURE REF R11; 
     117 [-]: CAPTURE REF R0; 
     118 [-]: CAPTURE VAL R7; 
     119 [-]: CAPTURE VAL R4; 
     120 [-]: CAPTURE VAL R2; 
     121 [-]: SETGLOBAL R44 K36; "UpdateGhost" = var44
     122 [-]: NEWCLOSURE R44 P12; 
     123 [-]: CAPTURE REF R23; 
     124 [-]: CAPTURE REF R29; 
     125 [-]: CAPTURE REF R30; 
     126 [-]: CAPTURE VAL R32; 
     127 [-]: CAPTURE REF R25; 
     128 [-]: CAPTURE VAL R16; 
     129 [-]: CAPTURE REF R27; 
     130 [-]: CAPTURE REF R26; 
     131 [-]: CAPTURE VAL R4; 
     132 [-]: CAPTURE REF R24; 
     133 [-]: CAPTURE VAL R33; 
     134 [-]: CAPTURE VAL R35; 
     135 [-]: CAPTURE VAL R15; 
     136 [-]: CAPTURE VAL R18; 
     137 [-]: CAPTURE VAL R13; 
     138 [-]: CAPTURE REF R8; 
     139 [-]: CAPTURE VAL R41; 
     140 [-]: CAPTURE REF R31; 
     141 [-]: CAPTURE REF R9; 
     142 [-]: CAPTURE VAL R39; 
     143 [-]: CAPTURE VAL R43; 
     144 [-]: DUPCLOSURE R45 K37; 
     145 [-]: CAPTURE VAL R33; 
     146 [-]: NEWCLOSURE R46 P14; 
     147 [-]: CAPTURE VAL R33; 
     148 [-]: CAPTURE REF R0; 
     149 [-]: NEWCLOSURE R47 P15; 
     150 [-]: CAPTURE REF R27; 
     151 [-]: CAPTURE REF R0; 
     152 [-]: CAPTURE VAL R7; 
     153 [-]: NEWTABLE R48 0 0; var48 = {}
     154 [-]: NEWTABLE R49 0 0; var49 = {}
     155 [-]: DUPCLOSURE R50 K38; 
     156 [-]: CAPTURE VAL R48; 
     157 [-]: CAPTURE VAL R49; 
     158 [-]: LOADNIL R51  ; var51 = nil
     159 [-]: NEWCLOSURE R51 P17; 
     160 [-]: CAPTURE REF R27; 
     161 [-]: CAPTURE VAL R4; 
     162 [-]: CAPTURE REF R8; 
     163 [-]: CAPTURE REF R51; 
     164 [-]: NEWCLOSURE R52 P18; 
     165 [-]: CAPTURE REF R8; 
     166 [-]: CAPTURE VAL R20; 
     167 [-]: CAPTURE REF R27; 
     168 [-]: CAPTURE VAL R47; 
     169 [-]: CAPTURE REF R0; 
     170 [-]: CAPTURE VAL R44; 
     171 [-]: CAPTURE REF R51; 
     172 [-]: CAPTURE REF R21; 
     173 [-]: CAPTURE REF R22; 
     174 [-]: CAPTURE VAL R46; 
     175 [-]: CAPTURE VAL R6; 
     176 [-]: CAPTURE VAL R4; 
     177 [-]: CAPTURE VAL R33; 
     178 [-]: CAPTURE REF R31; 
     179 [-]: CAPTURE REF R29; 
     180 [-]: CAPTURE VAL R41; 
     181 [-]: CAPTURE VAL R7; 
     182 [-]: CAPTURE REF R23; 
     183 [-]: CAPTURE VAL R17; 
     184 [-]: CAPTURE REF R9; 
     185 [-]: SETGLOBAL R52 K39; "GhostEvent" = var52
     186 [-]: NEWCLOSURE R52 P19; 
     187 [-]: CAPTURE REF R23; 
     188 [-]: CAPTURE REF R29; 
     189 [-]: CAPTURE REF R30; 
     190 [-]: SETGLOBAL R52 K40; "OnPlayersChanged" = var52
     191 [-]: DUPCLOSURE R52 K41; 
     192 [-]: DUPCLOSURE R53 K42; 
     193 [-]: DUPCLOSURE R54 K43; 
     194 [-]: LOADB R55 0  ; var55 = false
     195 [-]: NEWCLOSURE R56 P23; 
     196 [-]: CAPTURE REF R55; 
     197 [-]: CAPTURE VAL R54; 
     198 [-]: SETGLOBAL R56 K44; "OnPlayersChangedSiphonTrigger" = var56
     199 [-]: NEWCLOSURE R56 P24; 
     200 [-]: CAPTURE VAL R5; 
     201 [-]: CAPTURE REF R0; 
     202 [-]: CAPTURE REF R25; 
     203 [-]: CAPTURE VAL R16; 
     204 [-]: CAPTURE REF R26; 
     205 [-]: CAPTURE REF R27; 
     206 [-]: CAPTURE VAL R1; 
     207 [-]: CAPTURE REF R55; 
     208 [-]: CAPTURE VAL R54; 
     209 [-]: CAPTURE VAL R50; 
     210 [-]: CAPTURE VAL R53; 
     211 [-]: SETGLOBAL R56 K45; "GhostTower" = var56
     212 [-]: LOADNIL R56  ; var56 = nil
     213 [-]: LOADB R57 0  ; var57 = false
     214 [-]: NEWCLOSURE R58 P25; 
     215 [-]: CAPTURE REF R56; 
     216 [-]: CAPTURE REF R57; 
     217 [-]: SETGLOBAL R58 K46; "OnTouched" = var58
     218 [-]: NEWCLOSURE R58 P26; 
     219 [-]: CAPTURE REF R56; 
     220 [-]: CAPTURE REF R57; 
     221 [-]: SETGLOBAL R58 K47; "OnUntouched" = var58
     222 [-]: NEWCLOSURE R58 P27; 
     223 [-]: CAPTURE VAL R3; 
     224 [-]: CAPTURE REF R56; 
     225 [-]: CAPTURE REF R57; 
     226 [-]: SETGLOBAL R58 K48; "TransferenceTrigger" = var58
     227 [-]: CLOSEUPVALS R0; 
     228 [-]: RETURN R0 0  ; 


; Name:            
; Defined at line: 70
; #Upvalues:       3
; #Parameters:     0
; Is_vararg:       0
; Max Stack Size:  6

       0 [-]: GETUPVAL R2 1; var2 = upvalues[1]
       1 [-]: LENGTH R1 R2 ; var1 = #var2
       2 [-]: ADDK R0 R1 K0; var0 = var1 + 1
       3 [-]: SETUPVAL R0 0; upvalues[0] = var0
       4 [-]: GETUPVAL R2 1; var2 = upvalues[1]
       5 [-]: LENGTH R1 R2 ; var1 = #var2
       6 [-]: LOADN R3 2   ; var3 = 2
       7 [-]: GETUPVAL R5 1; var5 = upvalues[1]
       8 [-]: LENGTH R4 R5 ; var4 = #var5
       9 [-]: MUL R2 R3 R4 ; var2 = var3 * var4
      10 [-]: ADD R0 R1 R2 ; var0 = var1 + var2
      11 [-]: SETUPVAL R0 2; upvalues[0] = var2
      12 [-]: RETURN R0 0  ; 


; Name:            
; Defined at line: 75
; #Upvalues:       0
; #Parameters:     2
; Is_vararg:       0
; Max Stack Size:  10

       0 [-]: FASTCALL1 62 R0 L0; 
       1 [-]: MOVE R3 R0   ; var3 = var0
       2 [-]: GETIMPORT R2 1; var2 = 0x7B998233
       3 [-]: CALL R2 2 2  ; var2 = var2(var3)
L 0:   4 [-]: JUMPIF R2 L2 ; goto L2 if var2
       5 [-]: FASTCALL1 62 R1 L1; 
       6 [-]: MOVE R3 R1   ; var3 = var1
       7 [-]: GETIMPORT R2 1; var2 = 0x7B998233
       8 [-]: CALL R2 2 2  ; var2 = var2(var3)
L 1:   9 [-]: JUMPIFNOT R2 L3; goto L3 if not var2
L 2:  10 [-]: LOADN R2 0   ; var2 = 0
      11 [-]: RETURN R2 1  ; 
L 3:  12 [-]: NAMECALL R3 R0 K2; var4 = var0; var3 = var0[0x020D4331]
      13 [-]: CALL R3 2 2  ; var3 = var3(var4)
      14 [-]: NAMECALL R3 R3 K3; var4 = var3; var3 = var3[0xDDD5B6EB]
      15 [-]: CALL R3 2 2  ; var3 = var3(var4)
      16 [-]: GETTABLEKS R2 R3 K4; var2 = var3["heading"]
      17 [-]: NAMECALL R3 R0 K5; var4 = var0; var3 = var0[0xD1586535]
      18 [-]: CALL R3 2 2  ; var3 = var3(var4)
      19 [-]: GETIMPORT R6 7; var6 = 0x20B7F774
      20 [-]: MOVE R7 R3   ; var7 = var3
      21 [-]: NAMECALL R8 R1 K5; var9 = var1; var8 = var1[0xD1586535]
      22 [-]: CALL R8 2 0  ; var8, ... = var8(var9)
      23 [-]: CALL R6 0 2  ; var6 = var6(var7, ...)
      24 [-]: GETTABLEKS R5 R6 K4; var5 = var6["heading"]
      25 [-]: SUB R4 R5 R2 ; var4 = var5 - var2
      26 [-]: LOADN R5 0   ; var5 = 0
      27 [-]: JUMPIFNOTLE R4 R5 L4; goto L4 if var4 > var134480936
      28 [-]: ADDK R4 R4 K8; var4 = var4 + 360
L 4:  29 [-]: DIVK R6 R4 K9; var6 = var4 / 90
      30 [-]: FASTCALL1 7 R6 L5; 
      31 [-]: GETIMPORT R5 12; var5 = 0x5BCED4C4[0x99675E23]
      32 [-]: CALL R5 2 2  ; var5 = var5(var6)
L 5:  33 [-]: RETURN R5 1  ; 


; Name:            
; Defined at line: 90
; #Upvalues:       0
; #Parameters:     1
; Is_vararg:       0
; Max Stack Size:  3

       0 [-]: SUBK R1 R0 K0; var1 = var0 - 1
       1 [-]: LOADN R2 0   ; var2 = 0
       2 [-]: JUMPIFNOTLE R1 R2 L0; goto L0 if var1 > var262471
       3 [-]: LOADN R1 4   ; var1 = 4
L 0:   4 [-]: RETURN R1 1  ; 


; Name:            
; Defined at line: 98
; #Upvalues:       0
; #Parameters:     1
; Is_vararg:       0
; Max Stack Size:  3

       0 [-]: ADDK R1 R0 K0; var1 = var0 + 1
       1 [-]: LOADN R2 4   ; var2 = 4
       2 [-]: JUMPIFNOTLT R2 R1 L0; goto L0 if var2 >= var65863
       3 [-]: LOADN R1 1   ; var1 = 1
L 0:   4 [-]: RETURN R1 1  ; 


; Name:            
; Defined at line: 106
; #Upvalues:       2
; #Parameters:     1
; Is_vararg:       0
; Max Stack Size:  9

       0 [-]: GETIMPORT R1 1; var1 = 0xC8802016
       1 [-]: GETUPVAL R2 0; var2 = upvalues[0]
       2 [-]: CALL R1 2 4  ; var1, var2, var3 = var1(var2)
       3 [-]: FORGPREP_INEXT R1 L1; 
L 0:   4 [-]: GETUPVAL R6 1; var6 = upvalues[1]
       5 [-]: MOVE R8 R5   ; var8 = var5
       6 [-]: NAMECALL R6 R6 K2; var7 = var6; var6 = var6[0xA206852D]
       7 [-]: CALL R6 3 2  ; var6 = var6(var7, var8)
       8 [-]: JUMPIFNOTEQ R6 R0 L1; goto L1 if var6 ~= var67099
       9 [-]: LOADB R6 1   ; var6 = true
      10 [-]: RETURN R6 1  ; 
L 1:  11 [-]: FORGLOOP R1 L0 2 [inext]; 
      12 [-]: LOADB R1 0   ; var1 = false
      13 [-]: RETURN R1 1  ; 


; Name:            
; Defined at line: 116
; #Upvalues:       7
; #Parameters:     0
; Is_vararg:       0
; Max Stack Size:  14

       0 [-]: GETUPVAL R1 0; var1 = upvalues[0]
       1 [-]: FASTCALL1 62 R1 L0; 
       2 [-]: GETIMPORT R0 1; var0 = 0x7B998233
       3 [-]: CALL R0 2 2  ; var0 = var0(var1)
L 0:   4 [-]: JUMPIF R0 L1 ; goto L1 if var0
       5 [-]: GETUPVAL R0 0; var0 = upvalues[0]
       6 [-]: NAMECALL R0 R0 K2; var1 = var0; var0 = var0[0x2047CFE7]
       7 [-]: CALL R0 2 2  ; var0 = var0(var1)
       8 [-]: JUMPIFNOT R0 L2; goto L2 if not var0
L 1:   9 [-]: RETURN R0 0  ; 
L 2:  10 [-]: NEWTABLE R0 0 0; var0 = {}
      11 [-]: GETIMPORT R1 4; var1 = 0xC8802016
      12 [-]: GETUPVAL R2 1; var2 = upvalues[1]
      13 [-]: CALL R1 2 4  ; var1, var2, var3 = var1(var2)
      14 [-]: FORGPREP_INEXT R1 L4; 
L 3:  15 [-]: MOVE R7 R0   ; var7 = var0
      16 [-]: GETUPVAL R8 0; var8 = upvalues[0]
      17 [-]: MOVE R10 R5  ; var10 = var5
      18 [-]: NAMECALL R8 R8 K5; var9 = var8; var8 = var8[0xA206852D]
      19 [-]: CALL R8 3 0  ; var8, ... = var8(var9, var10)
      20 [-]: FASTCALL 52 L4; 
      21 [-]: GETIMPORT R6 8; var6 = 0x33BDD652[0x23D5322F]
      22 [-]: CALL R6 0 1  ; var6(var7, ...)
L 4:  23 [-]: FORGLOOP R1 L3 2 [inext]; 
      24 [-]: NEWTABLE R1 0 0; var1 = {}
      25 [-]: LOADN R4 1   ; var4 = 1
      26 [-]: LOADN R2 4   ; var2 = 4
      27 [-]: LOADN R3 1   ; var3 = 1
      28 [-]: FORNPREP R2 L7; nforprep start - [escape at L7] -- var2 = iterator
L 5:  29 [-]: GETUPVAL R6 2; var6 = upvalues[2]
      30 [-]: GETTABLEKS R5 R6 K9; var5 = var6[0xD16E8ECE]
      31 [-]: MOVE R6 R0   ; var6 = var0
      32 [-]: MOVE R7 R4   ; var7 = var4
      33 [-]: CALL R5 3 2  ; var5 = var5(var6, var7)
      34 [-]: LOADN R6 0   ; var6 = 0
      35 [-]: JUMPIFNOTLE R5 R6 L6; goto L6 if var5 > var1287
      36 [-]: GETUPVAL R5 0; var5 = upvalues[0]
      37 [-]: MOVE R7 R4   ; var7 = var4
      38 [-]: NAMECALL R5 R5 K10; var6 = var5; var5 = var5[0xBF39B623]
      39 [-]: CALL R5 3 2  ; var5 = var5(var6, var7)
      40 [-]: JUMPIF R5 L6 ; goto L6 if var5
      41 [-]: GETUPVAL R5 0; var5 = upvalues[0]
      42 [-]: MOVE R7 R4   ; var7 = var4
      43 [-]: NAMECALL R5 R5 K11; var6 = var5; var5 = var5[0x2E1DD58A]
      44 [-]: CALL R5 3 2  ; var5 = var5(var6, var7)
      45 [-]: JUMPIFNOT R5 L6; goto L6 if not var5
      46 [-]: GETUPVAL R5 3; var5 = upvalues[3]
      47 [-]: MOVE R6 R4   ; var6 = var4
      48 [-]: CALL R5 2 2  ; var5 = var5(var6)
      49 [-]: JUMPIF R5 L6 ; goto L6 if var5
      50 [-]: FASTCALL2 52 R1 R4 L6; 
      51 [-]: MOVE R6 R1   ; var6 = var1
      52 [-]: MOVE R7 R4   ; var7 = var4
      53 [-]: GETIMPORT R5 8; var5 = 0x33BDD652[0x23D5322F]
      54 [-]: CALL R5 3 1  ; var5(var6, var7)
L 6:  55 [-]: FORNLOOP R2 L5; nforloop end - iterate + goto L5
L 7:  56 [-]: LENGTH R2 R1 ; var2 = #var1
      57 [-]: JUMPXEQKN R2 K12 L8 NOT; 
      58 [-]: RETURN R0 0  ; 
L 8:  59 [-]: GETIMPORT R3 14; var3 = 0x55730E1A
      60 [-]: LOADN R4 1   ; var4 = 1
      61 [-]: LENGTH R5 R1 ; var5 = #var1
      62 [-]: CALL R3 3 2  ; var3 = var3(var4, var5)
      63 [-]: GETTABLE R2 R1 R3; var2 = var1[var3]
      64 [-]: GETUPVAL R5 4; var5 = upvalues[4]
      65 [-]: GETTABLE R4 R5 R2; var4 = var5[var2]
      66 [-]: GETTABLEKS R3 R4 K15; var3 = var4["GhostSpawns"]
      67 [-]: GETIMPORT R4 14; var4 = 0x55730E1A
      68 [-]: LOADN R5 1   ; var5 = 1
      69 [-]: LENGTH R6 R3 ; var6 = #var3
      70 [-]: CALL R4 3 2  ; var4 = var4(var5, var6)
      71 [-]: GETTABLE R5 R3 R4; var5 = var3[var4]
      72 [-]: FASTCALL1 62 R5 L9; 
      73 [-]: MOVE R7 R5   ; var7 = var5
      74 [-]: GETIMPORT R6 1; var6 = 0x7B998233
      75 [-]: CALL R6 2 2  ; var6 = var6(var7)
L 9:  76 [-]: JUMPIFNOT R6 L14; goto L14 if not var6
      77 [-]: SUBK R7 R2 K16; var7 = var2 - 1
      78 [-]: LOADN R8 0   ; var8 = 0
      79 [-]: JUMPIFNOTLE R7 R8 L10; goto L10 if var7 > var264007
      80 [-]: LOADN R7 4   ; var7 = 4
L10:  81 [-]: MOVE R6 R7   ; var6 = var7
      82 [-]: GETUPVAL R8 4; var8 = upvalues[4]
      83 [-]: GETTABLE R7 R8 R6; var7 = var8[var6]
      84 [-]: GETTABLEKS R3 R7 K15; var3 = var7["GhostSpawns"]
      85 [-]: LENGTH R7 R3 ; var7 = #var3
      86 [-]: LOADN R8 0   ; var8 = 0
      87 [-]: JUMPIFNOTLT R8 R7 L11; goto L11 if var8 >= var919374
      88 [-]: GETIMPORT R7 14; var7 = 0x55730E1A
      89 [-]: LOADN R8 1   ; var8 = 1
      90 [-]: LENGTH R9 R3 ; var9 = #var3
      91 [-]: CALL R7 3 2  ; var7 = var7(var8, var9)
      92 [-]: GETTABLE R5 R3 R7; var5 = var3[var7]
      93 [-]: JUMP L14     ; goto L14
L11:  94 [-]: ADDK R8 R2 K16; var8 = var2 + 1
      95 [-]: LOADN R9 4   ; var9 = 4
      96 [-]: JUMPIFNOTLT R9 R8 L12; goto L12 if var9 >= var67655
      97 [-]: LOADN R8 1   ; var8 = 1
L12:  98 [-]: MOVE R7 R8   ; var7 = var8
      99 [-]: GETUPVAL R9 4; var9 = upvalues[4]
     100 [-]: GETTABLE R8 R9 R7; var8 = var9[var7]
     101 [-]: GETTABLEKS R3 R8 K15; var3 = var8["GhostSpawns"]
     102 [-]: LENGTH R8 R3 ; var8 = #var3
     103 [-]: LOADN R9 0   ; var9 = 0
     104 [-]: JUMPIFNOTLT R9 R8 L13; goto L13 if var9 >= var919630
     105 [-]: GETIMPORT R8 14; var8 = 0x55730E1A
     106 [-]: LOADN R9 1   ; var9 = 1
     107 [-]: LENGTH R10 R3; var10 = #var3
     108 [-]: CALL R8 3 2  ; var8 = var8(var9, var10)
     109 [-]: GETTABLE R5 R3 R8; var5 = var3[var8]
     110 [-]: JUMP L14     ; goto L14
L13: 111 [-]: GETIMPORT R8 18; var8 = 0x3D106989
     112 [-]: LOADK R9 K19 ; var9 = "Couldn't find ghost spawns in next or prev quadrants"
     113 [-]: CALL R8 2 1  ; var8(var9)
     114 [-]: RETURN R0 0  ; 
L14: 115 [-]: NAMECALL R7 R5 K20; var8 = var5; var7 = var5[0xD1586535]
     116 [-]: CALL R7 2 2  ; var7 = var7(var8)
     117 [-]: GETIMPORT R8 22; var8 = 0xA421AF95
     118 [-]: LOADN R9 0   ; var9 = 0
     119 [-]: LOADN R10 1  ; var10 = 1
     120 [-]: LOADN R11 0  ; var11 = 0
     121 [-]: CALL R8 4 2  ; var8 = var8(var9, var10, var11)
     122 [-]: ADD R6 R7 R8 ; var6 = var7 + var8
     123 [-]: GETIMPORT R7 24; var7 = 0x20B7F774
     124 [-]: MOVE R8 R6   ; var8 = var6
     125 [-]: GETUPVAL R9 0; var9 = upvalues[0]
     126 [-]: NAMECALL R9 R9 K20; var10 = var9; var9 = var9[0xD1586535]
     127 [-]: CALL R9 2 0  ; var9, ... = var9(var10)
     128 [-]: CALL R7 0 2  ; var7 = var7(var8, ...)
     129 [-]: LOADN R8 0   ; var8 = 0
     130 [-]: SETTABLEKS R8 R7 K25; var8["bank"] = var7
     131 [-]: LOADN R8 0   ; var8 = 0
     132 [-]: SETTABLEKS R8 R7 K26; var8["pitch"] = var7
     133 [-]: GETUPVAL R8 5; var8 = upvalues[5]
     134 [-]: GETIMPORT R10 28; var10 = 0xEEAE74D6
     135 [-]: MOVE R11 R6  ; var11 = var6
     136 [-]: MOVE R12 R7  ; var12 = var7
     137 [-]: GETIMPORT R13 30; var13 = 0x0469F296
     138 [-]: CALL R13 1 0 ; var13, ... = var13()
     139 [-]: NAMECALL R8 R8 K31; var9 = var8; var8 = var8[0x6CD833C5]
     140 [-]: CALL R8 0 2  ; var8 = var8(var9, ...)
     141 [-]: NAMECALL R9 R8 K32; var10 = var8; var9 = var8[0xBB610E5B]
     142 [-]: CALL R9 2 2  ; var9 = var9(var10)
     143 [-]: GETUPVAL R12 6; var12 = upvalues[6]
     144 [-]: LOADB R13 0  ; var13 = false
     145 [-]: NAMECALL R10 R9 K33; var11 = var9; var10 = var9[0x659D451F]
     146 [-]: CALL R10 4 1 ; var10(var11, var12, var13)
     147 [-]: GETUPVAL R10 0; var10 = upvalues[0]
     148 [-]: MOVE R12 R9  ; var12 = var9
     149 [-]: MOVE R13 R2  ; var13 = var2
     150 [-]: NAMECALL R10 R10 K34; var11 = var10; var10 = var10[0x587702D8]
     151 [-]: CALL R10 4 1 ; var10(var11, var12, var13)
     152 [-]: GETIMPORT R12 30; var12 = 0x0469F296
     153 [-]: LOADK R13 K35; var13 = "UpdateGhost"
     154 [-]: CALL R12 2 2 ; var12 = var12(var13)
     155 [-]: LOADB R13 0  ; var13 = false
     156 [-]: NAMECALL R10 R9 K36; var11 = var9; var10 = var9[0xD5F7912B]
     157 [-]: CALL R10 4 1 ; var10(var11, var12, var13)
     158 [-]: RETURN R0 0  ; 


; Name:            
; Defined at line: 177
; #Upvalues:       2
; #Parameters:     1
; Is_vararg:       0
; Max Stack Size:  11

       0 [-]: GETUPVAL R2 0; var2 = upvalues[0]
       1 [-]: FASTCALL1 62 R2 L0; 
       2 [-]: GETIMPORT R1 1; var1 = 0x7B998233
       3 [-]: CALL R1 2 2  ; var1 = var1(var2)
L 0:   4 [-]: JUMPIFNOT R1 L1; goto L1 if not var1
       5 [-]: GETIMPORT R1 3; var1 = 0x3D106989
       6 [-]: LOADK R2 K4  ; var2 = "GhostTower.lua::FindAvailableQuadrant - mGhostTowerAvatar is null"
       7 [-]: CALL R1 2 1  ; var1(var2)
       8 [-]: LOADN R1 0   ; var1 = 0
       9 [-]: RETURN R1 1  ; 
L 1:  10 [-]: LOADN R1 0   ; var1 = 0
      11 [-]: GETIMPORT R2 6; var2 = 0xC8802016
      12 [-]: GETUPVAL R3 1; var3 = upvalues[1]
      13 [-]: CALL R2 2 4  ; var2, var3, var4 = var2(var3)
      14 [-]: FORGPREP_INEXT R2 L4; 
L 2:  15 [-]: GETTABLEKS R8 R6 K7; var8 = var6["Spawns"]
      16 [-]: LENGTH R7 R8 ; var7 = #var8
      17 [-]: LOADN R8 0   ; var8 = 0
      18 [-]: JUMPIFNOTLT R8 R7 L4; goto L4 if var8 >= var67591
      19 [-]: GETUPVAL R8 1; var8 = upvalues[1]
      20 [-]: GETTABLE R7 R8 R1; var7 = var8[var1]
      21 [-]: GETUPVAL R8 0; var8 = upvalues[0]
      22 [-]: MOVE R10 R5  ; var10 = var5
      23 [-]: NAMECALL R8 R8 K8; var9 = var8; var8 = var8[0x2E1DD58A]
      24 [-]: CALL R8 3 2  ; var8 = var8(var9, var10)
      25 [-]: JUMPIFNOT R8 L4; goto L4 if not var8
      26 [-]: JUMPXEQKN R1 K9 L3; 
      27 [-]: GETTABLE R9 R6 R0; var9 = var6[var0]
      28 [-]: LENGTH R8 R9 ; var8 = #var9
      29 [-]: GETTABLE R10 R7 R0; var10 = var7[var0]
      30 [-]: LENGTH R9 R10; var9 = #var10
      31 [-]: JUMPIFNOTLT R8 R9 L4; goto L4 if var8 >= var327958
L 3:  32 [-]: MOVE R1 R5   ; var1 = var5
L 4:  33 [-]: FORGLOOP R2 L2 2 [inext]; 
      34 [-]: RETURN R1 1  ; 


; Name:            
; Defined at line: 196
; #Upvalues:       5
; #Parameters:     0
; Is_vararg:       0
; Max Stack Size:  12

       0 [-]: GETUPVAL R1 0; var1 = upvalues[0]
       1 [-]: SUBK R0 R1 K0; var0 = var1 - 1
       2 [-]: SETUPVAL R0 0; upvalues[0] = var0
       3 [-]: GETUPVAL R0 1; var0 = upvalues[1]
       4 [-]: LOADK R1 K1  ; var1 = "Guards"
       5 [-]: CALL R0 2 2  ; var0 = var0(var1)
       6 [-]: JUMPXEQKN R0 K2 L0 NOT; 
       7 [-]: RETURN R0 0  ; 
L 0:   8 [-]: GETUPVAL R3 2; var3 = upvalues[2]
       9 [-]: GETTABLE R2 R3 R0; var2 = var3[var0]
      10 [-]: GETTABLEKS R1 R2 K3; var1 = var2["Spawns"]
      11 [-]: GETUPVAL R2 3; var2 = upvalues[3]
      12 [-]: GETIMPORT R4 5; var4 = 0xF4C088C4
      13 [-]: GETIMPORT R6 7; var6 = 0x55730E1A
      14 [-]: LOADN R7 1   ; var7 = 1
      15 [-]: LENGTH R8 R1 ; var8 = #var1
      16 [-]: CALL R6 3 2  ; var6 = var6(var7, var8)
      17 [-]: GETTABLE R5 R1 R6; var5 = var1[var6]
      18 [-]: GETIMPORT R6 9; var6 = 0x0469F296
      19 [-]: LOADK R7 K10 ; var7 = "Team"
      20 [-]: CALL R6 2 0  ; var6, ... = var6(var7)
      21 [-]: NAMECALL R2 R2 K11; var3 = var2; var2 = var2[0x33FC842F]
      22 [-]: CALL R2 0 2  ; var2 = var2(var3, ...)
      23 [-]: FASTCALL1 62 R2 L1; 
      24 [-]: MOVE R4 R2   ; var4 = var2
      25 [-]: GETIMPORT R3 13; var3 = 0x7B998233
      26 [-]: CALL R3 2 2  ; var3 = var3(var4)
L 1:  27 [-]: JUMPIF R3 L4 ; goto L4 if var3
      28 [-]: GETIMPORT R4 16; var4 = _T["UseAiDirectorPopulationSpawnCount"]
      29 [-]: FASTCALL1 62 R4 L2; 
      30 [-]: GETIMPORT R3 13; var3 = 0x7B998233
      31 [-]: CALL R3 2 2  ; var3 = var3(var4)
L 2:  32 [-]: JUMPIF R3 L3 ; goto L3 if var3
      33 [-]: GETIMPORT R3 16; var3 = _T["UseAiDirectorPopulationSpawnCount"]
      34 [-]: JUMPIFNOT R3 L3; goto L3 if not var3
      35 [-]: GETUPVAL R3 3; var3 = upvalues[3]
      36 [-]: LOADN R5 1   ; var5 = 1
      37 [-]: NAMECALL R3 R3 K17; var4 = var3; var3 = var3[0xF2D6020E]
      38 [-]: CALL R3 3 1  ; var3(var4, var5)
L 3:  39 [-]: NAMECALL R3 R2 K18; var4 = var2; var3 = var2[0xBB610E5B]
      40 [-]: CALL R3 2 2  ; var3 = var3(var4)
      41 [-]: NAMECALL R4 R3 K19; var5 = var3; var4 = var3[0xDE321E6F]
      42 [-]: CALL R4 2 2  ; var4 = var4(var5)
      43 [-]: LOADN R6 35  ; var6 = 35
      44 [-]: LOADN R7 2   ; var7 = 2
      45 [-]: LOADK R8 K20 ; var8 = 0.20000000000000001
      46 [-]: LOADNIL R9   ; var9 = nil
      47 [-]: LOADNIL R10  ; var10 = nil
      48 [-]: LOADN R11 13 ; var11 = 13
      49 [-]: NAMECALL R4 R4 K21; var5 = var4; var4 = var4[0x5E6704FF]
      50 [-]: CALL R4 8 1  ; var4(var5, var6, var7, var8, var9, var10, var11)
      51 [-]: GETIMPORT R4 23; var4 = 0x89326C93
      52 [-]: GETUPVAL R6 4; var6 = upvalues[4]
      53 [-]: NAMECALL R7 R3 K24; var8 = var3; var7 = var3[0xD1586535]
      54 [-]: CALL R7 2 2  ; var7 = var7(var8)
      55 [-]: NAMECALL R8 R3 K25; var9 = var3; var8 = var3[0xCB3851B8]
      56 [-]: CALL R8 2 0  ; var8, ... = var8(var9)
      57 [-]: NAMECALL R4 R4 K26; var5 = var4; var4 = var4[0x05909209]
      58 [-]: CALL R4 0 1  ; var4(var5, ...)
      59 [-]: GETUPVAL R7 2; var7 = upvalues[2]
      60 [-]: GETTABLE R6 R7 R0; var6 = var7[var0]
      61 [-]: GETTABLEKS R5 R6 K1; var5 = var6["Guards"]
      62 [-]: FASTCALL2 52 R5 R2 L4; 
      63 [-]: MOVE R6 R2   ; var6 = var2
      64 [-]: GETIMPORT R4 29; var4 = 0x33BDD652[0x23D5322F]
      65 [-]: CALL R4 3 1  ; var4(var5, var6)
L 4:  66 [-]: RETURN R0 0  ; 


; Name:            
; Defined at line: 217
; #Upvalues:       1
; #Parameters:     0
; Is_vararg:       0
; Max Stack Size:  8

       0 [-]: LOADN R0 0   ; var0 = 0
       1 [-]: GETIMPORT R1 1; var1 = 0xC8802016
       2 [-]: GETUPVAL R2 0; var2 = upvalues[0]
       3 [-]: CALL R1 2 4  ; var1, var2, var3 = var1(var2)
       4 [-]: FORGPREP_INEXT R1 L1; 
L 0:   5 [-]: GETTABLEKS R7 R5 K2; var7 = var5["Enemies"]
       6 [-]: LENGTH R6 R7 ; var6 = #var7
       7 [-]: ADD R0 R0 R6 ; var0 = var0 + var6
L 1:   8 [-]: FORGLOOP R1 L0 2 [inext]; 
       9 [-]: RETURN R0 1  ; 


; Name:            
; Defined at line: 226
; #Upvalues:       6
; #Parameters:     0
; Is_vararg:       0
; Max Stack Size:  10

       0 [-]: GETUPVAL R0 0; var0 = upvalues[0]
       1 [-]: NAMECALL R0 R0 K0; var1 = var0; var0 = var0[0xE2E98521]
       2 [-]: CALL R0 2 2  ; var0 = var0(var1)
       3 [-]: GETUPVAL R1 0; var1 = upvalues[0]
       4 [-]: NAMECALL R1 R1 K1; var2 = var1; var1 = var1[0x9A49D00C]
       5 [-]: CALL R1 2 2  ; var1 = var1(var2)
       6 [-]: JUMPIFLT R1 R0 L2; goto L2 if var1 < var327
       7 [-]: LOADN R1 0   ; var1 = 0
       8 [-]: GETIMPORT R2 3; var2 = 0xC8802016
       9 [-]: GETUPVAL R3 1; var3 = upvalues[1]
      10 [-]: CALL R2 2 4  ; var2, var3, var4 = var2(var3)
      11 [-]: FORGPREP_INEXT R2 L1; 
L 0:  12 [-]: GETTABLEKS R8 R6 K4; var8 = var6["Enemies"]
      13 [-]: LENGTH R7 R8 ; var7 = #var8
      14 [-]: ADD R1 R1 R7 ; var1 = var1 + var7
L 1:  15 [-]: FORGLOOP R2 L0 2 [inext]; 
      16 [-]: MOVE R0 R1   ; var0 = var1
      17 [-]: GETUPVAL R1 2; var1 = upvalues[2]
      18 [-]: JUMPIFNOTLE R1 R0 L3; goto L3 if var1 > var65581
L 2:  19 [-]: RETURN R0 0  ; 
L 3:  20 [-]: GETUPVAL R0 3; var0 = upvalues[3]
      21 [-]: LOADK R1 K4  ; var1 = "Enemies"
      22 [-]: CALL R0 2 2  ; var0 = var0(var1)
      23 [-]: JUMPXEQKN R0 K5 L4 NOT; 
      24 [-]: RETURN R0 0  ; 
L 4:  25 [-]: GETUPVAL R3 1; var3 = upvalues[1]
      26 [-]: GETTABLE R2 R3 R0; var2 = var3[var0]
      27 [-]: GETTABLEKS R1 R2 K6; var1 = var2["Spawns"]
      28 [-]: GETUPVAL R2 0; var2 = upvalues[0]
      29 [-]: GETUPVAL R5 4; var5 = upvalues[4]
      30 [-]: GETIMPORT R6 8; var6 = 0x55730E1A
      31 [-]: LOADN R7 1   ; var7 = 1
      32 [-]: GETUPVAL R9 4; var9 = upvalues[4]
      33 [-]: LENGTH R8 R9 ; var8 = #var9
      34 [-]: CALL R6 3 2  ; var6 = var6(var7, var8)
      35 [-]: GETTABLE R4 R5 R6; var4 = var5[var6]
      36 [-]: GETIMPORT R6 8; var6 = 0x55730E1A
      37 [-]: LOADN R7 1   ; var7 = 1
      38 [-]: LENGTH R8 R1 ; var8 = #var1
      39 [-]: CALL R6 3 2  ; var6 = var6(var7, var8)
      40 [-]: GETTABLE R5 R1 R6; var5 = var1[var6]
      41 [-]: GETIMPORT R6 10; var6 = 0x0469F296
      42 [-]: LOADK R7 K11 ; var7 = "Team"
      43 [-]: CALL R6 2 0  ; var6, ... = var6(var7)
      44 [-]: NAMECALL R2 R2 K12; var3 = var2; var2 = var2[0x33FC842F]
      45 [-]: CALL R2 0 2  ; var2 = var2(var3, ...)
      46 [-]: FASTCALL1 62 R2 L5; 
      47 [-]: MOVE R4 R2   ; var4 = var2
      48 [-]: GETIMPORT R3 14; var3 = 0x7B998233
      49 [-]: CALL R3 2 2  ; var3 = var3(var4)
L 5:  50 [-]: JUMPIF R3 L8 ; goto L8 if var3
      51 [-]: GETIMPORT R4 17; var4 = _T["UseAiDirectorPopulationSpawnCount"]
      52 [-]: FASTCALL1 62 R4 L6; 
      53 [-]: GETIMPORT R3 14; var3 = 0x7B998233
      54 [-]: CALL R3 2 2  ; var3 = var3(var4)
L 6:  55 [-]: JUMPIF R3 L7 ; goto L7 if var3
      56 [-]: GETIMPORT R3 17; var3 = _T["UseAiDirectorPopulationSpawnCount"]
      57 [-]: JUMPIFNOT R3 L7; goto L7 if not var3
      58 [-]: GETUPVAL R3 0; var3 = upvalues[0]
      59 [-]: LOADN R5 1   ; var5 = 1
      60 [-]: NAMECALL R3 R3 K18; var4 = var3; var3 = var3[0xF2D6020E]
      61 [-]: CALL R3 3 1  ; var3(var4, var5)
L 7:  62 [-]: NAMECALL R3 R2 K19; var4 = var2; var3 = var2[0xBB610E5B]
      63 [-]: CALL R3 2 2  ; var3 = var3(var4)
      64 [-]: GETIMPORT R4 21; var4 = 0x89326C93
      65 [-]: GETUPVAL R6 5; var6 = upvalues[5]
      66 [-]: NAMECALL R7 R3 K22; var8 = var3; var7 = var3[0xD1586535]
      67 [-]: CALL R7 2 2  ; var7 = var7(var8)
      68 [-]: NAMECALL R8 R3 K23; var9 = var3; var8 = var3[0xCB3851B8]
      69 [-]: CALL R8 2 0  ; var8, ... = var8(var9)
      70 [-]: NAMECALL R4 R4 K24; var5 = var4; var4 = var4[0x05909209]
      71 [-]: CALL R4 0 1  ; var4(var5, ...)
      72 [-]: GETUPVAL R7 1; var7 = upvalues[1]
      73 [-]: GETTABLE R6 R7 R0; var6 = var7[var0]
      74 [-]: GETTABLEKS R5 R6 K4; var5 = var6["Enemies"]
      75 [-]: FASTCALL2 52 R5 R2 L8; 
      76 [-]: MOVE R6 R2   ; var6 = var2
      77 [-]: GETIMPORT R4 27; var4 = 0x33BDD652[0x23D5322F]
      78 [-]: CALL R4 3 1  ; var4(var5, var6)
L 8:  79 [-]: RETURN R0 0  ; 


; Name:            
; Defined at line: 248
; #Upvalues:       4
; #Parameters:     1
; Is_vararg:       0
; Max Stack Size:  10

       0 [-]: GETIMPORT R1 1; var1 = 0x89326C93
       1 [-]: NAMECALL R1 R1 K2; var2 = var1; var1 = var1[0x18D05D30]
       2 [-]: CALL R1 2 2  ; var1 = var1(var2)
       3 [-]: JUMPIF R1 L0 ; goto L0 if var1
       4 [-]: RETURN R0 0  ; 
L 0:   5 [-]: NAMECALL R1 R0 K3; var2 = var0; var1 = var0[0xBD1405A3]
       6 [-]: CALL R1 2 2  ; var1 = var1(var2)
       7 [-]: FASTCALL1 62 R1 L1; 
       8 [-]: MOVE R3 R1   ; var3 = var1
       9 [-]: GETIMPORT R2 5; var2 = 0x7B998233
      10 [-]: CALL R2 2 2  ; var2 = var2(var3)
L 1:  11 [-]: JUMPIFNOT R2 L2; goto L2 if not var2
      12 [-]: RETURN R0 0  ; 
L 2:  13 [-]: NAMECALL R2 R1 K6; var3 = var1; var2 = var1[0x52DE0ED7]
      14 [-]: CALL R2 2 2  ; var2 = var2(var3)
      15 [-]: NAMECALL R3 R1 K7; var4 = var1; var3 = var1[0x14A55974]
      16 [-]: CALL R3 2 2  ; var3 = var3(var4)
      17 [-]: FASTCALL1 62 R2 L3; 
      18 [-]: MOVE R5 R2   ; var5 = var2
      19 [-]: GETIMPORT R4 5; var4 = 0x7B998233
      20 [-]: CALL R4 2 2  ; var4 = var4(var5)
L 3:  21 [-]: JUMPIF R4 L5 ; goto L5 if var4
      22 [-]: GETIMPORT R6 9; var6 = gLotusOperatorAvatarType
      23 [-]: NAMECALL R4 R2 K10; var5 = var2; var4 = var2[0xF2DEAF69]
      24 [-]: CALL R4 3 2  ; var4 = var4(var5, var6)
      25 [-]: JUMPIFNOT R4 L5; goto L5 if not var4
      26 [-]: FASTCALL1 62 R3 L4; 
      27 [-]: MOVE R5 R3   ; var5 = var3
      28 [-]: GETIMPORT R4 5; var4 = 0x7B998233
      29 [-]: CALL R4 2 2  ; var4 = var4(var5)
L 4:  30 [-]: JUMPIF R4 L6 ; goto L6 if var4
      31 [-]: GETIMPORT R6 12; var6 = 0x7ED0A956
      32 [-]: LOADK R7 K13 ; var7 = "/Lotus/Types/Friendly/Tenno/OperatorBeamWeapon"
      33 [-]: CALL R6 2 0  ; var6, ... = var6(var7)
      34 [-]: NAMECALL R4 R3 K10; var5 = var3; var4 = var3[0xF2DEAF69]
      35 [-]: CALL R4 0 2  ; var4 = var4(var5, ...)
      36 [-]: JUMPIFNOT R4 L6; goto L6 if not var4
L 5:  37 [-]: RETURN R0 0  ; 
L 6:  38 [-]: GETUPVAL R6 0; var6 = upvalues[0]
      39 [-]: LOADB R7 0   ; var7 = false
      40 [-]: NAMECALL R4 R0 K14; var5 = var0; var4 = var0[0x659D451F]
      41 [-]: CALL R4 4 1  ; var4(var5, var6, var7)
      42 [-]: GETIMPORT R6 16; var6 = gPortCounterType
      43 [-]: NAMECALL R4 R0 K17; var5 = var0; var4 = var0[0xC9F6A7D7]
      44 [-]: CALL R4 3 2  ; var4 = var4(var5, var6)
      45 [-]: LOADN R6 1   ; var6 = 1
      46 [-]: NAMECALL R4 R4 K18; var5 = var4; var4 = var4[0xB35F65B4]
      47 [-]: CALL R4 3 1  ; var4(var5, var6)
      48 [-]: LOADN R6 0   ; var6 = 0
      49 [-]: NAMECALL R4 R0 K19; var5 = var0; var4 = var0[0x014DB014]
      50 [-]: CALL R4 3 1  ; var4(var5, var6)
      51 [-]: GETUPVAL R4 1; var4 = upvalues[1]
      52 [-]: MOVE R6 R0   ; var6 = var0
      53 [-]: NAMECALL R4 R4 K20; var5 = var4; var4 = var4[0xA206852D]
      54 [-]: CALL R4 3 2  ; var4 = var4(var5, var6)
      55 [-]: GETUPVAL R5 1; var5 = upvalues[1]
      56 [-]: MOVE R7 R4   ; var7 = var4
      57 [-]: NAMECALL R5 R5 K21; var6 = var5; var5 = var5[0xF2249C4C]
      58 [-]: CALL R5 3 1  ; var5(var6, var7)
      59 [-]: NAMECALL R5 R1 K6; var6 = var1; var5 = var1[0x52DE0ED7]
      60 [-]: CALL R5 2 2  ; var5 = var5(var6)
      61 [-]: FASTCALL1 62 R5 L7; 
      62 [-]: MOVE R7 R5   ; var7 = var5
      63 [-]: GETIMPORT R6 5; var6 = 0x7B998233
      64 [-]: CALL R6 2 2  ; var6 = var6(var7)
L 7:  65 [-]: JUMPIF R6 L8 ; goto L8 if var6
      66 [-]: GETUPVAL R8 2; var8 = upvalues[2]
      67 [-]: GETIMPORT R9 23; var9 = EMPTY_SYMBOL
      68 [-]: NAMECALL R6 R5 K24; var7 = var5; var6 = var5[0x47901F07]
      69 [-]: CALL R6 4 1  ; var6(var7, var8, var9)
L 8:  70 [-]: GETUPVAL R6 1; var6 = upvalues[1]
      71 [-]: NAMECALL R6 R6 K25; var7 = var6; var6 = var6[0xEFF44F5B]
      72 [-]: CALL R6 2 2  ; var6 = var6(var7)
      73 [-]: LOADN R7 3   ; var7 = 3
      74 [-]: JUMPIFNOTLE R6 R7 L9; goto L9 if var6 > var1771086
      75 [-]: GETIMPORT R6 27; var6 = 0xBE190284
      76 [-]: LOADB R8 1   ; var8 = true
      77 [-]: NAMECALL R6 R6 K28; var7 = var6; var6 = var6[0xD1961230]
      78 [-]: CALL R6 3 1  ; var6(var7, var8)
L 9:  79 [-]: GETUPVAL R6 1; var6 = upvalues[1]
      80 [-]: NAMECALL R6 R6 K25; var7 = var6; var6 = var6[0xEFF44F5B]
      81 [-]: CALL R6 2 2  ; var6 = var6(var7)
      82 [-]: LOADN R7 1   ; var7 = 1
      83 [-]: JUMPIFNOTLE R6 R7 L10; goto L10 if var6 > var65581
      84 [-]: RETURN R0 0  ; 
L10:  85 [-]: GETIMPORT R6 31; var6 = 0x5BCED4C4[0x3630E649]
      86 [-]: CALL R6 1 2  ; var6 = var6()
      87 [-]: LOADK R7 K32 ; var7 = 0.5
      88 [-]: JUMPIFNOTLT R6 R7 L11; goto L11 if var6 >= var198407
      89 [-]: GETUPVAL R7 3; var7 = upvalues[3]
      90 [-]: GETTABLEKS R6 R7 K33; var6 = var7[0x9742B85B]
      91 [-]: GETIMPORT R7 35; var7 = 0xE91D7466
      92 [-]: GETIMPORT R8 37; var8 = 0x0469F296
      93 [-]: LOADK R9 K38 ; var9 = "DKSBraidDestroyedLotus"
      94 [-]: CALL R8 2 0  ; var8, ... = var8(var9)
      95 [-]: CALL R6 0 1  ; var6(var7, ...)
      96 [-]: RETURN R0 0  ; 
L11:  97 [-]: GETIMPORT R6 31; var6 = 0x5BCED4C4[0x3630E649]
      98 [-]: CALL R6 1 2  ; var6 = var6()
      99 [-]: LOADK R7 K32 ; var7 = 0.5
     100 [-]: JUMPIFNOTLT R6 R7 L12; goto L12 if var6 >= var198407
     101 [-]: GETUPVAL R7 3; var7 = upvalues[3]
     102 [-]: GETTABLEKS R6 R7 K33; var6 = var7[0x9742B85B]
     103 [-]: GETIMPORT R7 35; var7 = 0xE91D7466
     104 [-]: GETIMPORT R8 37; var8 = 0x0469F296
     105 [-]: LOADK R9 K39 ; var9 = "DKSBraidDestroyedWormQueen"
     106 [-]: CALL R8 2 0  ; var8, ... = var8(var9)
     107 [-]: CALL R6 0 1  ; var6(var7, ...)
     108 [-]: RETURN R0 0  ; 
L12: 109 [-]: GETUPVAL R7 3; var7 = upvalues[3]
     110 [-]: GETTABLEKS R6 R7 K33; var6 = var7[0x9742B85B]
     111 [-]: GETIMPORT R7 35; var7 = 0xE91D7466
     112 [-]: GETIMPORT R8 37; var8 = 0x0469F296
     113 [-]: LOADK R9 K40 ; var9 = "DKSDashThroughWormQueen"
     114 [-]: CALL R8 2 0  ; var8, ... = var8(var9)
     115 [-]: CALL R6 0 1  ; var6(var7, ...)
     116 [-]: RETURN R0 0  ; 


; Name:            
; Defined at line: 302
; #Upvalues:       7
; #Parameters:     1
; Is_vararg:       0
; Max Stack Size:  11

       0 [-]: GETUPVAL R2 0; var2 = upvalues[0]
       1 [-]: FASTCALL1 62 R2 L0; 
       2 [-]: GETIMPORT R1 1; var1 = 0x7B998233
       3 [-]: CALL R1 2 2  ; var1 = var1(var2)
L 0:   4 [-]: JUMPIFNOT R1 L1; goto L1 if not var1
       5 [-]: NAMECALL R1 R0 K2; var2 = var0; var1 = var0[0xA2880940]
       6 [-]: CALL R1 2 1  ; var1(var2)
       7 [-]: RETURN R0 0  ; 
L 1:   8 [-]: GETIMPORT R3 4; var3 = gPortCounterType
       9 [-]: NAMECALL R1 R0 K5; var2 = var0; var1 = var0[0xC9F6A7D7]
      10 [-]: CALL R1 3 2  ; var1 = var1(var2, var3)
      11 [-]: GETIMPORT R2 7; var2 = 0x14459A1C
      12 [-]: JUMPIFNOT R2 L2; goto L2 if not var2
      13 [-]: NAMECALL R2 R1 K8; var3 = var1; var2 = var1[0x2E333568]
      14 [-]: CALL R2 2 2  ; var2 = var2(var3)
      15 [-]: JUMPXEQKN R2 K9 L2; 
      16 [-]: LOADB R4 0   ; var4 = false
      17 [-]: LOADB R5 1   ; var5 = true
      18 [-]: NAMECALL R2 R0 K10; var3 = var0; var2 = var0[0x768274D6]
      19 [-]: CALL R2 4 1  ; var2(var3, var4, var5)
      20 [-]: RETURN R0 0  ; 
L 2:  21 [-]: GETUPVAL R3 1; var3 = upvalues[1]
      22 [-]: FASTCALL2 52 R3 R0 L3; 
      23 [-]: MOVE R4 R0   ; var4 = var0
      24 [-]: GETIMPORT R2 13; var2 = 0x33BDD652[0x23D5322F]
      25 [-]: CALL R2 3 1  ; var2(var3, var4)
L 3:  26 [-]: LOADK R4 K14 ; var4 = "OnDamaged"
      27 [-]: NAMECALL R2 R0 K15; var3 = var0; var2 = var0[0x05B9ABD3]
      28 [-]: CALL R2 3 1  ; var2(var3, var4)
      29 [-]: NAMECALL R2 R0 K16; var3 = var0; var2 = var0[0xFA9E477F]
      30 [-]: CALL R2 2 2  ; var2 = var2(var3)
      31 [-]: GETIMPORT R4 18; var4 = 0x0469F296
      32 [-]: LOADK R5 K19 ; var5 = "StormTarget"
      33 [-]: CALL R4 2 2  ; var4 = var4(var5)
      34 [-]: GETUPVAL R5 0; var5 = upvalues[0]
      35 [-]: LOADK R6 K20 ; var6 = 0.10000000000000001
      36 [-]: NAMECALL R2 R2 K21; var3 = var2; var2 = var2[0x81B5632F]
      37 [-]: CALL R2 5 1  ; var2(var3, var4, var5, var6)
      38 [-]: GETUPVAL R3 0; var3 = upvalues[0]
      39 [-]: NAMECALL R3 R3 K22; var4 = var3; var3 = var3[0xD1586535]
      40 [-]: CALL R3 2 2  ; var3 = var3(var4)
      41 [-]: GETIMPORT R4 24; var4 = 0xA421AF95
      42 [-]: LOADN R5 0   ; var5 = 0
      43 [-]: LOADN R6 1   ; var6 = 1
      44 [-]: LOADN R7 0   ; var7 = 0
      45 [-]: CALL R4 4 2  ; var4 = var4(var5, var6, var7)
      46 [-]: ADD R2 R3 R4 ; var2 = var3 + var4
L 4:  47 [-]: NAMECALL R3 R1 K8; var4 = var1; var3 = var1[0x2E333568]
      48 [-]: CALL R3 2 2  ; var3 = var3(var4)
      49 [-]: JUMPXEQKN R3 K9 L9 NOT; 
      50 [-]: GETIMPORT R3 26; var3 = 0xCBD666E1
      51 [-]: LOADN R4 0   ; var4 = 0
      52 [-]: CALL R3 2 1  ; var3(var4)
      53 [-]: MOVE R5 R2   ; var5 = var2
      54 [-]: NAMECALL R3 R0 K27; var4 = var0; var3 = var0[0x1F420A3A]
      55 [-]: CALL R3 3 2  ; var3 = var3(var4, var5)
      56 [-]: LOADN R4 3   ; var4 = 3
      57 [-]: JUMPIFNOTLE R3 R4 L6; goto L6 if var3 > var132359
      58 [-]: GETUPVAL R5 2; var5 = upvalues[2]
      59 [-]: FASTCALL1 62 R5 L5; 
      60 [-]: GETIMPORT R4 1; var4 = 0x7B998233
      61 [-]: CALL R4 2 2  ; var4 = var4(var5)
L 5:  62 [-]: JUMPIF R4 L6 ; goto L6 if var4
      63 [-]: GETUPVAL R6 2; var6 = upvalues[2]
      64 [-]: LOADB R7 0   ; var7 = false
      65 [-]: NAMECALL R4 R0 K28; var5 = var0; var4 = var0[0x659D451F]
      66 [-]: CALL R4 4 1  ; var4(var5, var6, var7)
      67 [-]: LOADNIL R4   ; var4 = nil
      68 [-]: SETUPVAL R4 2; upvalues[4] = var2
L 6:  69 [-]: GETUPVAL R5 0; var5 = upvalues[0]
      70 [-]: FASTCALL1 62 R5 L7; 
      71 [-]: GETIMPORT R4 1; var4 = 0x7B998233
      72 [-]: CALL R4 2 2  ; var4 = var4(var5)
L 7:  73 [-]: JUMPIFNOT R4 L8; goto L8 if not var4
      74 [-]: RETURN R0 0  ; 
L 8:  75 [-]: LOADN R4 2   ; var4 = 2
      76 [-]: JUMPIFLT R3 R4 L9; goto L9 if var3 < var-2621396
      77 [-]: JUMPBACK L4  ; goto L4
L 9:  78 [-]: NAMECALL R3 R1 K8; var4 = var1; var3 = var1[0x2E333568]
      79 [-]: CALL R3 2 2  ; var3 = var3(var4)
      80 [-]: JUMPXEQKN R3 K29 L15; 
      81 [-]: LOADN R5 2   ; var5 = 2
      82 [-]: NAMECALL R3 R1 K30; var4 = var1; var3 = var1[0xB35F65B4]
      83 [-]: CALL R3 3 1  ; var3(var4, var5)
      84 [-]: GETUPVAL R3 3; var3 = upvalues[3]
      85 [-]: GETUPVAL R5 4; var5 = upvalues[4]
      86 [-]: GETUPVAL R7 3; var7 = upvalues[3]
      87 [-]: GETUPVAL R9 4; var9 = upvalues[4]
      88 [-]: LOADN R10 0  ; var10 = 0
      89 [-]: NAMECALL R7 R7 K31; var8 = var7; var7 = var7[0x0EB34C69]
      90 [-]: CALL R7 4 2  ; var7 = var7(var8, var9, var10)
      91 [-]: ADDK R6 R7 K29; var6 = var7 + 1
      92 [-]: NAMECALL R3 R3 K32; var4 = var3; var3 = var3[0x751F061D]
      93 [-]: CALL R3 4 1  ; var3(var4, var5, var6)
      94 [-]: GETUPVAL R4 0; var4 = upvalues[0]
      95 [-]: FASTCALL1 62 R4 L10; 
      96 [-]: GETIMPORT R3 1; var3 = 0x7B998233
      97 [-]: CALL R3 2 2  ; var3 = var3(var4)
L10:  98 [-]: JUMPIF R3 L11; goto L11 if var3
      99 [-]: GETUPVAL R3 0; var3 = upvalues[0]
     100 [-]: MOVE R5 R0   ; var5 = var0
     101 [-]: NAMECALL R3 R3 K33; var4 = var3; var3 = var3[0x73C5BE11]
     102 [-]: CALL R3 3 1  ; var3(var4, var5)
L11: 103 [-]: GETUPVAL R3 3; var3 = upvalues[3]
     104 [-]: GETUPVAL R5 4; var5 = upvalues[4]
     105 [-]: LOADN R6 0   ; var6 = 0
     106 [-]: NAMECALL R3 R3 K31; var4 = var3; var3 = var3[0x0EB34C69]
     107 [-]: CALL R3 4 2  ; var3 = var3(var4, var5, var6)
     108 [-]: JUMPXEQKN R3 K29 L12 NOT; 
     109 [-]: GETUPVAL R5 5; var5 = upvalues[5]
     110 [-]: GETTABLEKS R4 R5 K34; var4 = var5[0x9742B85B]
     111 [-]: GETIMPORT R5 36; var5 = 0xE91D7466
     112 [-]: GETIMPORT R6 18; var6 = 0x0469F296
     113 [-]: LOADK R7 K37 ; var7 = "DKSDestroyOrderLotus"
     114 [-]: CALL R6 2 0  ; var6, ... = var6(var7)
     115 [-]: CALL R4 0 1  ; var4(var5, ...)
     116 [-]: JUMP L15     ; goto L15
L12: 117 [-]: LOADN R4 6   ; var4 = 6
     118 [-]: JUMPIFNOTLT R3 R4 L13; goto L13 if var3 >= var328967
     119 [-]: GETUPVAL R5 5; var5 = upvalues[5]
     120 [-]: GETTABLEKS R4 R5 K34; var4 = var5[0x9742B85B]
     121 [-]: GETIMPORT R5 36; var5 = 0xE91D7466
     122 [-]: GETIMPORT R6 18; var6 = 0x0469F296
     123 [-]: LOADK R7 K38 ; var7 = "DKSEnergyGatheredWormQueen"
     124 [-]: CALL R6 2 0  ; var6, ... = var6(var7)
     125 [-]: CALL R4 0 1  ; var4(var5, ...)
     126 [-]: JUMP L15     ; goto L15
L13: 127 [-]: JUMPXEQKN R3 K39 L14 NOT; 
     128 [-]: GETUPVAL R5 5; var5 = upvalues[5]
     129 [-]: GETTABLEKS R4 R5 K34; var4 = var5[0x9742B85B]
     130 [-]: GETIMPORT R5 36; var5 = 0xE91D7466
     131 [-]: GETIMPORT R6 18; var6 = 0x0469F296
     132 [-]: LOADK R7 K40 ; var7 = "DKSEnergyAlmostCompWormQueen"
     133 [-]: CALL R6 2 0  ; var6, ... = var6(var7)
     134 [-]: CALL R4 0 1  ; var4(var5, ...)
     135 [-]: JUMP L15     ; goto L15
L14: 136 [-]: JUMPXEQKN R3 K41 L15 NOT; 
     137 [-]: GETUPVAL R5 5; var5 = upvalues[5]
     138 [-]: GETTABLEKS R4 R5 K34; var4 = var5[0x9742B85B]
     139 [-]: GETIMPORT R5 36; var5 = 0xE91D7466
     140 [-]: GETIMPORT R6 18; var6 = 0x0469F296
     141 [-]: LOADK R7 K42 ; var7 = "DKSSiphonFullWormQueen"
     142 [-]: CALL R6 2 0  ; var6, ... = var6(var7)
     143 [-]: CALL R4 0 1  ; var4(var5, ...)
     144 [-]: GETUPVAL R5 5; var5 = upvalues[5]
     145 [-]: GETTABLEKS R4 R5 K34; var4 = var5[0x9742B85B]
     146 [-]: GETIMPORT R5 36; var5 = 0xE91D7466
     147 [-]: GETIMPORT R6 18; var6 = 0x0469F296
     148 [-]: LOADK R7 K43 ; var7 = "DKSSiphonFullLotus"
     149 [-]: CALL R6 2 0  ; var6, ... = var6(var7)
     150 [-]: CALL R4 0 1  ; var4(var5, ...)
L15: 151 [-]: GETUPVAL R4 6; var4 = upvalues[6]
     152 [-]: GETTABLEKS R3 R4 K44; var3 = var4[0xD16E8ECE]
     153 [-]: GETUPVAL R4 1; var4 = upvalues[1]
     154 [-]: MOVE R5 R0   ; var5 = var0
     155 [-]: CALL R3 3 2  ; var3 = var3(var4, var5)
     156 [-]: LOADN R4 0   ; var4 = 0
     157 [-]: JUMPIFNOTLT R4 R3 L16; goto L16 if var4 >= var3015758
     158 [-]: GETIMPORT R4 46; var4 = 0x33BDD652[0x9C1F3B5A]
     159 [-]: GETUPVAL R5 1; var5 = upvalues[1]
     160 [-]: MOVE R6 R3   ; var6 = var3
     161 [-]: CALL R4 3 1  ; var4(var5, var6)
L16: 162 [-]: NAMECALL R4 R0 K2; var5 = var0; var4 = var0[0xA2880940]
     163 [-]: CALL R4 2 1  ; var4(var5)
     164 [-]: RETURN R0 0  ; 


; Name:            
; Defined at line: 372
; #Upvalues:       21
; #Parameters:     1
; Is_vararg:       0
; Max Stack Size:  17

       0 [-]: GETIMPORT R1 1; var1 = 0x89326C93
       1 [-]: NAMECALL R1 R1 K2; var2 = var1; var1 = var1[0x7D108DDB]
       2 [-]: CALL R1 2 2  ; var1 = var1(var2)
       3 [-]: SETUPVAL R1 0; upvalues[1] = var0
       4 [-]: GETUPVAL R3 0; var3 = upvalues[0]
       5 [-]: LENGTH R2 R3 ; var2 = #var3
       6 [-]: ADDK R1 R2 K3; var1 = var2 + 1
       7 [-]: SETUPVAL R1 1; upvalues[1] = var1
       8 [-]: GETUPVAL R3 0; var3 = upvalues[0]
       9 [-]: LENGTH R2 R3 ; var2 = #var3
      10 [-]: LOADN R4 2   ; var4 = 2
      11 [-]: GETUPVAL R6 0; var6 = upvalues[0]
      12 [-]: LENGTH R5 R6 ; var5 = #var6
      13 [-]: MUL R3 R4 R5 ; var3 = var4 * var5
      14 [-]: ADD R1 R2 R3 ; var1 = var2 + var3
      15 [-]: SETUPVAL R1 2; upvalues[1] = var2
      16 [-]: GETIMPORT R1 1; var1 = 0x89326C93
      17 [-]: LOADK R3 K4  ; var3 = "OnPlayersChanged"
      18 [-]: NAMECALL R1 R1 K5; var2 = var1; var1 = var1[0xB7D33840]
      19 [-]: CALL R1 3 1  ; var1(var2, var3)
      20 [-]: GETIMPORT R1 7; var1 = 0xB009BBC6
      21 [-]: LOADK R2 K8  ; var2 = "/Lotus/Types/Game/EnemySpecs/GhostTowerSquadOne"
      22 [-]: CALL R1 2 2  ; var1 = var1(var2)
      23 [-]: NAMECALL R1 R1 K9; var2 = var1; var1 = var1[0xEC195A1E]
      24 [-]: CALL R1 2 2  ; var1 = var1(var2)
      25 [-]: GETIMPORT R2 11; var2 = 0xC8802016
      26 [-]: MOVE R3 R1   ; var3 = var1
      27 [-]: CALL R2 2 4  ; var2, var3, var4 = var2(var3)
      28 [-]: FORGPREP_INEXT R2 L1; 
L 0:  29 [-]: GETUPVAL R8 3; var8 = upvalues[3]
      30 [-]: GETIMPORT R9 13; var9 = 0x88EFC25E
      31 [-]: GETTABLEKS R10 R6 K14; var10 = var6["agent"]
      32 [-]: CALL R9 2 0  ; var9, ... = var9(var10)
      33 [-]: FASTCALL 52 L1; 
      34 [-]: GETIMPORT R7 17; var7 = 0x33BDD652[0x23D5322F]
      35 [-]: CALL R7 0 1  ; var7(var8, ...)
L 1:  36 [-]: FORGLOOP R2 L0 2 [inext]; 
      37 [-]: GETIMPORT R2 1; var2 = 0x89326C93
      38 [-]: GETUPVAL R4 5; var4 = upvalues[5]
      39 [-]: NAMECALL R5 R0 K18; var6 = var0; var5 = var0[0xD1586535]
      40 [-]: CALL R5 2 2  ; var5 = var5(var6)
      41 [-]: LOADN R6 5   ; var6 = 5
      42 [-]: NAMECALL R2 R2 K19; var3 = var2; var2 = var2[0x4E5939A5]
      43 [-]: CALL R2 5 2  ; var2 = var2(var3, var4, var5, var6)
      44 [-]: SETUPVAL R2 4; upvalues[2] = var4
      45 [-]: GETIMPORT R2 1; var2 = 0x89326C93
      46 [-]: GETIMPORT R4 21; var4 = gVoidNegationTowerAvatarType
      47 [-]: NAMECALL R5 R0 K18; var6 = var0; var5 = var0[0xD1586535]
      48 [-]: CALL R5 2 2  ; var5 = var5(var6)
      49 [-]: LOADK R6 K22 ; var6 = 3.4028234663852886e+38
      50 [-]: NAMECALL R2 R2 K19; var3 = var2; var2 = var2[0x4E5939A5]
      51 [-]: CALL R2 5 2  ; var2 = var2(var3, var4, var5, var6)
      52 [-]: SETUPVAL R2 6; upvalues[2] = var6
L 2:  53 [-]: GETUPVAL R3 6; var3 = upvalues[6]
      54 [-]: FASTCALL1 62 R3 L3; 
      55 [-]: GETIMPORT R2 24; var2 = 0x7B998233
      56 [-]: CALL R2 2 2  ; var2 = var2(var3)
L 3:  57 [-]: JUMPIFNOT R2 L4; goto L4 if not var2
      58 [-]: GETIMPORT R2 26; var2 = 0xCBD666E1
      59 [-]: LOADN R3 1   ; var3 = 1
      60 [-]: CALL R2 2 1  ; var2(var3)
      61 [-]: GETIMPORT R2 1; var2 = 0x89326C93
      62 [-]: GETIMPORT R4 21; var4 = gVoidNegationTowerAvatarType
      63 [-]: NAMECALL R5 R0 K18; var6 = var0; var5 = var0[0xD1586535]
      64 [-]: CALL R5 2 2  ; var5 = var5(var6)
      65 [-]: LOADK R6 K22 ; var6 = 3.4028234663852886e+38
      66 [-]: NAMECALL R2 R2 K19; var3 = var2; var2 = var2[0x4E5939A5]
      67 [-]: CALL R2 5 2  ; var2 = var2(var3, var4, var5, var6)
      68 [-]: SETUPVAL R2 6; upvalues[2] = var6
      69 [-]: JUMPBACK L2  ; goto L2
L 4:  70 [-]: GETUPVAL R2 6; var2 = upvalues[6]
      71 [-]: NAMECALL R2 R2 K27; var3 = var2; var2 = var2[0xFA9E477F]
      72 [-]: CALL R2 2 2  ; var2 = var2(var3)
      73 [-]: SETUPVAL R2 7; upvalues[2] = var7
L 5:  74 [-]: GETUPVAL R3 6; var3 = upvalues[6]
      75 [-]: NAMECALL R3 R3 K28; var4 = var3; var3 = var3[0xE79E7EF4]
      76 [-]: CALL R3 2 2  ; var3 = var3(var4)
      77 [-]: FASTCALL1 62 R3 L6; 
      78 [-]: GETIMPORT R2 24; var2 = 0x7B998233
      79 [-]: CALL R2 2 2  ; var2 = var2(var3)
L 6:  80 [-]: JUMPIFNOT R2 L7; goto L7 if not var2
      81 [-]: GETIMPORT R2 26; var2 = 0xCBD666E1
      82 [-]: LOADN R3 0   ; var3 = 0
      83 [-]: CALL R2 2 1  ; var2(var3)
      84 [-]: JUMPBACK L5  ; goto L5
L 7:  85 [-]: GETUPVAL R2 6; var2 = upvalues[6]
      86 [-]: NAMECALL R2 R2 K29; var3 = var2; var2 = var2[0x1C7D4588]
      87 [-]: CALL R2 2 1  ; var2(var3)
      88 [-]: GETUPVAL R3 8; var3 = upvalues[8]
      89 [-]: GETTABLEKS R2 R3 K30; var2 = var3[0x9742B85B]
      90 [-]: GETIMPORT R3 32; var3 = 0xE91D7466
      91 [-]: GETIMPORT R4 34; var4 = 0x0469F296
      92 [-]: LOADK R5 K35 ; var5 = "DKSApproachSiphonLotus"
      93 [-]: CALL R4 2 0  ; var4, ... = var4(var5)
      94 [-]: CALL R2 0 1  ; var2(var3, ...)
      95 [-]: GETUPVAL R3 8; var3 = upvalues[8]
      96 [-]: GETTABLEKS R2 R3 K30; var2 = var3[0x9742B85B]
      97 [-]: GETIMPORT R3 32; var3 = 0xE91D7466
      98 [-]: GETIMPORT R4 34; var4 = 0x0469F296
      99 [-]: LOADK R5 K36 ; var5 = "DKSWormAnnounceWormQueen"
     100 [-]: CALL R4 2 0  ; var4, ... = var4(var5)
     101 [-]: CALL R2 0 1  ; var2(var3, ...)
     102 [-]: GETUPVAL R2 6; var2 = upvalues[6]
     103 [-]: NAMECALL R2 R2 K28; var3 = var2; var2 = var2[0xE79E7EF4]
     104 [-]: CALL R2 2 2  ; var2 = var2(var3)
     105 [-]: NAMECALL R2 R2 K37; var3 = var2; var2 = var2[0x9435EB6D]
     106 [-]: CALL R2 2 2  ; var2 = var2(var3)
     107 [-]: SETUPVAL R2 9; upvalues[2] = var9
     108 [-]: LOADN R4 1   ; var4 = 1
     109 [-]: LOADN R2 4   ; var2 = 4
     110 [-]: LOADN R3 1   ; var3 = 1
     111 [-]: FORNPREP R2 L10; nforprep start - [escape at L10] -- var2 = iterator
L 8: 112 [-]: NEWTABLE R5 4 0; var5 = {}
     113 [-]: NEWTABLE R6 0 0; var6 = {}
     114 [-]: SETTABLEKS R6 R5 K38; var6["Spawns"] = var5
     115 [-]: NEWTABLE R6 0 0; var6 = {}
     116 [-]: SETTABLEKS R6 R5 K39; var6["GhostSpawns"] = var5
     117 [-]: NEWTABLE R6 0 0; var6 = {}
     118 [-]: SETTABLEKS R6 R5 K40; var6["Enemies"] = var5
     119 [-]: NEWTABLE R6 0 0; var6 = {}
     120 [-]: SETTABLEKS R6 R5 K41; var6["Guards"] = var5
     121 [-]: GETUPVAL R7 10; var7 = upvalues[10]
     122 [-]: FASTCALL2 52 R7 R5 L9; 
     123 [-]: MOVE R8 R5   ; var8 = var5
     124 [-]: GETIMPORT R6 17; var6 = 0x33BDD652[0x23D5322F]
     125 [-]: CALL R6 3 1  ; var6(var7, var8)
L 9: 126 [-]: FORNLOOP R2 L8; nforloop end - iterate + goto L8
L10: 127 [-]: GETIMPORT R2 1; var2 = 0x89326C93
     128 [-]: GETIMPORT R4 43; var4 = gNpcSpawnPointType
     129 [-]: NAMECALL R2 R2 K44; var3 = var2; var2 = var2[0xFB669000]
     130 [-]: CALL R2 3 2  ; var2 = var2(var3, var4)
     131 [-]: GETIMPORT R3 11; var3 = 0xC8802016
     132 [-]: MOVE R4 R2   ; var4 = var2
     133 [-]: CALL R3 2 4  ; var3, var4, var5 = var3(var4)
     134 [-]: FORGPREP_INEXT R3 L13; 
L11: 135 [-]: NAMECALL R8 R7 K28; var9 = var7; var8 = var7[0xE79E7EF4]
     136 [-]: CALL R8 2 2  ; var8 = var8(var9)
     137 [-]: FASTCALL1 62 R8 L12; 
     138 [-]: MOVE R10 R8  ; var10 = var8
     139 [-]: GETIMPORT R9 24; var9 = 0x7B998233
     140 [-]: CALL R9 2 2  ; var9 = var9(var10)
L12: 141 [-]: JUMPIF R9 L13; goto L13 if var9
     142 [-]: NAMECALL R9 R8 K37; var10 = var8; var9 = var8[0x9435EB6D]
     143 [-]: CALL R9 2 2  ; var9 = var9(var10)
     144 [-]: GETUPVAL R10 9; var10 = upvalues[9]
     145 [-]: JUMPIFNOTEQ R9 R10 L13; goto L13 if var9 ~= var100796727
     146 [-]: GETTABLE R9 R2 R6; var9 = var2[var6]
     147 [-]: NAMECALL R9 R9 K45; var10 = var9; var9 = var9[0x22DA1852]
     148 [-]: CALL R9 2 2  ; var9 = var9(var10)
     149 [-]: GETIMPORT R10 47; var10 = EMPTY_SYMBOL
     150 [-]: JUMPIFNOTEQ R9 R10 L13; goto L13 if var9 ~= var723207
     151 [-]: GETUPVAL R9 11; var9 = upvalues[11]
     152 [-]: GETUPVAL R10 6; var10 = upvalues[6]
     153 [-]: MOVE R11 R7  ; var11 = var7
     154 [-]: CALL R9 3 2  ; var9 = var9(var10, var11)
     155 [-]: LOADN R10 4  ; var10 = 4
     156 [-]: JUMPIFNOTLE R9 R10 L13; goto L13 if var9 > var68167
     157 [-]: LOADN R10 1  ; var10 = 1
     158 [-]: JUMPIFNOTLE R10 R9 L13; goto L13 if var10 > var658695
     159 [-]: GETUPVAL R13 10; var13 = upvalues[10]
     160 [-]: GETTABLE R12 R13 R9; var12 = var13[var9]
     161 [-]: GETTABLEKS R11 R12 K38; var11 = var12["Spawns"]
     162 [-]: FASTCALL2 52 R11 R7 L13; 
     163 [-]: MOVE R12 R7  ; var12 = var7
     164 [-]: GETIMPORT R10 17; var10 = 0x33BDD652[0x23D5322F]
     165 [-]: CALL R10 3 1 ; var10(var11, var12)
L13: 166 [-]: FORGLOOP R3 L11 2 [inext]; 
     167 [-]: GETIMPORT R3 1; var3 = 0x89326C93
     168 [-]: GETUPVAL R5 12; var5 = upvalues[12]
     169 [-]: NAMECALL R3 R3 K44; var4 = var3; var3 = var3[0xFB669000]
     170 [-]: CALL R3 3 2  ; var3 = var3(var4, var5)
     171 [-]: GETIMPORT R4 11; var4 = 0xC8802016
     172 [-]: MOVE R5 R3   ; var5 = var3
     173 [-]: CALL R4 2 4  ; var4, var5, var6 = var4(var5)
     174 [-]: FORGPREP_INEXT R4 L16; 
L14: 175 [-]: NAMECALL R9 R8 K28; var10 = var8; var9 = var8[0xE79E7EF4]
     176 [-]: CALL R9 2 2  ; var9 = var9(var10)
     177 [-]: FASTCALL1 62 R9 L15; 
     178 [-]: MOVE R11 R9  ; var11 = var9
     179 [-]: GETIMPORT R10 24; var10 = 0x7B998233
     180 [-]: CALL R10 2 2 ; var10 = var10(var11)
L15: 181 [-]: JUMPIF R10 L16; goto L16 if var10
     182 [-]: NAMECALL R10 R9 K37; var11 = var9; var10 = var9[0x9435EB6D]
     183 [-]: CALL R10 2 2 ; var10 = var10(var11)
     184 [-]: GETUPVAL R11 9; var11 = upvalues[9]
     185 [-]: JUMPIFNOTEQ R10 R11 L16; goto L16 if var10 ~= var723463
     186 [-]: GETUPVAL R10 11; var10 = upvalues[11]
     187 [-]: GETUPVAL R11 6; var11 = upvalues[6]
     188 [-]: MOVE R12 R8  ; var12 = var8
     189 [-]: CALL R10 3 2 ; var10 = var10(var11, var12)
     190 [-]: LOADN R11 4  ; var11 = 4
     191 [-]: JUMPIFNOTLE R10 R11 L16; goto L16 if var10 > var68423
     192 [-]: LOADN R11 1  ; var11 = 1
     193 [-]: JUMPIFNOTLE R11 R10 L16; goto L16 if var11 > var658951
     194 [-]: GETUPVAL R14 10; var14 = upvalues[10]
     195 [-]: GETTABLE R13 R14 R10; var13 = var14[var10]
     196 [-]: GETTABLEKS R12 R13 K39; var12 = var13["GhostSpawns"]
     197 [-]: FASTCALL2 52 R12 R8 L16; 
     198 [-]: MOVE R13 R8  ; var13 = var8
     199 [-]: GETIMPORT R11 17; var11 = 0x33BDD652[0x23D5322F]
     200 [-]: CALL R11 3 1 ; var11(var12, var13)
L16: 201 [-]: FORGLOOP R4 L14 2 [inext]; 
     202 [-]: GETIMPORT R4 49; var4 = 0x14459A1C
     203 [-]: JUMPIFNOT R4 L25; goto L25 if not var4
     204 [-]: GETIMPORT R4 1; var4 = 0x89326C93
     205 [-]: GETUPVAL R6 13; var6 = upvalues[13]
     206 [-]: NAMECALL R4 R4 K44; var5 = var4; var4 = var4[0xFB669000]
     207 [-]: CALL R4 3 2  ; var4 = var4(var5, var6)
     208 [-]: GETIMPORT R5 11; var5 = 0xC8802016
     209 [-]: MOVE R6 R4   ; var6 = var4
     210 [-]: CALL R5 2 4  ; var5, var6, var7 = var5(var6)
     211 [-]: FORGPREP_INEXT R5 L19; 
L17: 212 [-]: NAMECALL R10 R9 K28; var11 = var9; var10 = var9[0xE79E7EF4]
     213 [-]: CALL R10 2 2 ; var10 = var10(var11)
     214 [-]: FASTCALL1 62 R10 L18; 
     215 [-]: MOVE R12 R10 ; var12 = var10
     216 [-]: GETIMPORT R11 24; var11 = 0x7B998233
     217 [-]: CALL R11 2 2 ; var11 = var11(var12)
L18: 218 [-]: JUMPIF R11 L19; goto L19 if var11
     219 [-]: NAMECALL R11 R10 K37; var12 = var10; var11 = var10[0x9435EB6D]
     220 [-]: CALL R11 2 2 ; var11 = var11(var12)
     221 [-]: GETUPVAL R12 6; var12 = upvalues[6]
     222 [-]: NAMECALL R12 R12 K28; var13 = var12; var12 = var12[0xE79E7EF4]
     223 [-]: CALL R12 2 2 ; var12 = var12(var13)
     224 [-]: NAMECALL R12 R12 K37; var13 = var12; var12 = var12[0x9435EB6D]
     225 [-]: CALL R12 2 2 ; var12 = var12(var13)
     226 [-]: JUMPIFNOTEQ R11 R12 L19; goto L19 if var11 ~= var1074334533
     227 [-]: NAMECALL R11 R9 K50; var12 = var9; var11 = var9[0xA2880940]
     228 [-]: CALL R11 2 1 ; var11(var12)
L19: 229 [-]: FORGLOOP R5 L17 2 [inext]; 
     230 [-]: GETIMPORT R5 1; var5 = 0x89326C93
     231 [-]: GETIMPORT R7 52; var7 = gLotusNpcAvatarType
     232 [-]: NAMECALL R5 R5 K44; var6 = var5; var5 = var5[0xFB669000]
     233 [-]: CALL R5 3 2  ; var5 = var5(var6, var7)
     234 [-]: GETIMPORT R6 11; var6 = 0xC8802016
     235 [-]: MOVE R7 R5   ; var7 = var5
     236 [-]: CALL R6 2 4  ; var6, var7, var8 = var6(var7)
     237 [-]: FORGPREP_INEXT R6 L24; 
L20: 238 [-]: GETUPVAL R13 14; var13 = upvalues[14]
     239 [-]: NAMECALL R11 R10 K53; var12 = var10; var11 = var10[0xF2DEAF69]
     240 [-]: CALL R11 3 2 ; var11 = var11(var12, var13)
     241 [-]: JUMPIFNOT R11 L22; goto L22 if not var11
     242 [-]: GETUPVAL R11 11; var11 = upvalues[11]
     243 [-]: GETUPVAL R12 6; var12 = upvalues[6]
     244 [-]: MOVE R13 R10 ; var13 = var10
     245 [-]: CALL R11 3 2 ; var11 = var11(var12, var13)
     246 [-]: LOADN R12 4  ; var12 = 4
     247 [-]: JUMPIFNOTLE R11 R12 L24; goto L24 if var11 > var68679
     248 [-]: LOADN R12 1  ; var12 = 1
     249 [-]: JUMPIFNOTLE R12 R11 L24; goto L24 if var12 > var659207
     250 [-]: GETUPVAL R15 10; var15 = upvalues[10]
     251 [-]: GETTABLE R14 R15 R11; var14 = var15[var11]
     252 [-]: GETTABLEKS R13 R14 K41; var13 = var14["Guards"]
     253 [-]: NAMECALL R14 R10 K27; var15 = var10; var14 = var10[0xFA9E477F]
     254 [-]: CALL R14 2 0 ; var14, ... = var14(var15)
     255 [-]: FASTCALL 52 L21; 
     256 [-]: GETIMPORT R12 17; var12 = 0x33BDD652[0x23D5322F]
     257 [-]: CALL R12 0 1 ; var12(var13, ...)
L21: 258 [-]: JUMP L24     ; goto L24
L22: 259 [-]: NAMECALL R11 R10 K28; var12 = var10; var11 = var10[0xE79E7EF4]
     260 [-]: CALL R11 2 2 ; var11 = var11(var12)
     261 [-]: FASTCALL1 62 R11 L23; 
     262 [-]: MOVE R13 R11 ; var13 = var11
     263 [-]: GETIMPORT R12 24; var12 = 0x7B998233
     264 [-]: CALL R12 2 2 ; var12 = var12(var13)
L23: 265 [-]: JUMPIF R12 L24; goto L24 if var12
     266 [-]: NAMECALL R12 R10 K54; var13 = var10; var12 = var10[0x2D0A291F]
     267 [-]: CALL R12 2 2 ; var12 = var12(var13)
     268 [-]: GETIMPORT R13 34; var13 = 0x0469F296
     269 [-]: LOADK R14 K55; var14 = "TENNO"
     270 [-]: CALL R13 2 2 ; var13 = var13(var14)
     271 [-]: JUMPIFEQ R12 R13 L24; goto L24 if var12 == var1829440581
     272 [-]: NAMECALL R12 R11 K37; var13 = var11; var12 = var11[0x9435EB6D]
     273 [-]: CALL R12 2 2 ; var12 = var12(var13)
     274 [-]: GETUPVAL R13 9; var13 = upvalues[9]
     275 [-]: JUMPIFNOTEQ R12 R13 L24; goto L24 if var12 ~= var723975
     276 [-]: GETUPVAL R12 11; var12 = upvalues[11]
     277 [-]: GETUPVAL R13 6; var13 = upvalues[6]
     278 [-]: MOVE R14 R10 ; var14 = var10
     279 [-]: CALL R12 3 2 ; var12 = var12(var13, var14)
     280 [-]: LOADN R13 4  ; var13 = 4
     281 [-]: JUMPIFNOTLE R12 R13 L24; goto L24 if var12 > var68935
     282 [-]: LOADN R13 1  ; var13 = 1
     283 [-]: JUMPIFNOTLE R13 R12 L24; goto L24 if var13 > var659463
     284 [-]: GETUPVAL R16 10; var16 = upvalues[10]
     285 [-]: GETTABLE R15 R16 R12; var15 = var16[var12]
     286 [-]: GETTABLEKS R14 R15 K40; var14 = var15["Enemies"]
     287 [-]: NAMECALL R15 R10 K27; var16 = var10; var15 = var10[0xFA9E477F]
     288 [-]: CALL R15 2 0 ; var15, ... = var15(var16)
     289 [-]: FASTCALL 52 L24; 
     290 [-]: GETIMPORT R13 17; var13 = 0x33BDD652[0x23D5322F]
     291 [-]: CALL R13 0 1 ; var13(var14, ...)
L24: 292 [-]: FORGLOOP R6 L20 2 [inext]; 
     293 [-]: JUMP L28     ; goto L28
L25: 294 [-]: LOADN R6 1   ; var6 = 1
     295 [-]: GETUPVAL R4 1; var4 = upvalues[1]
     296 [-]: LOADN R5 1   ; var5 = 1
     297 [-]: FORNPREP R4 L27; nforprep start - [escape at L27] -- var4 = iterator
L26: 298 [-]: GETUPVAL R7 15; var7 = upvalues[15]
     299 [-]: LOADN R10 1  ; var10 = 1
     300 [-]: ADD R9 R10 R6; var9 = var10 + var6
     301 [-]: GETUPVAL R10 16; var10 = upvalues[16]
     302 [-]: LOADB R11 0  ; var11 = false
     303 [-]: NAMECALL R7 R7 K56; var8 = var7; var7 = var7[0xBD2E96EA]
     304 [-]: CALL R7 5 1  ; var7(var8, var9, var10, var11)
     305 [-]: FORNLOOP R4 L26; nforloop end - iterate + goto L26
L27: 306 [-]: GETUPVAL R4 1; var4 = upvalues[1]
     307 [-]: SETUPVAL R4 17; upvalues[4] = var17
L28: 308 [-]: GETUPVAL R4 15; var4 = upvalues[15]
     309 [-]: LOADN R6 30  ; var6 = 30
     310 [-]: GETUPVAL R7 19; var7 = upvalues[19]
     311 [-]: LOADB R8 1   ; var8 = true
     312 [-]: NAMECALL R4 R4 K56; var5 = var4; var4 = var4[0xBD2E96EA]
     313 [-]: CALL R4 5 2  ; var4 = var4(var5, var6, var7, var8)
     314 [-]: SETUPVAL R4 18; upvalues[4] = var18
     315 [-]: GETUPVAL R4 15; var4 = upvalues[15]
     316 [-]: LOADN R6 3   ; var6 = 3
     317 [-]: GETUPVAL R7 20; var7 = upvalues[20]
     318 [-]: LOADB R8 1   ; var8 = true
     319 [-]: NAMECALL R4 R4 K56; var5 = var4; var4 = var4[0xBD2E96EA]
     320 [-]: CALL R4 5 1  ; var4(var5, var6, var7, var8)
     321 [-]: RETURN R0 0  ; 


; Name:            
; Defined at line: 471
; #Upvalues:       1
; #Parameters:     0
; Is_vararg:       0
; Max Stack Size:  8

       0 [-]: LOADN R0 0   ; var0 = 0
       1 [-]: GETIMPORT R1 1; var1 = 0xC8802016
       2 [-]: GETUPVAL R2 0; var2 = upvalues[0]
       3 [-]: CALL R1 2 4  ; var1, var2, var3 = var1(var2)
       4 [-]: FORGPREP_INEXT R1 L1; 
L 0:   5 [-]: GETTABLEKS R7 R5 K2; var7 = var5["Guards"]
       6 [-]: LENGTH R6 R7 ; var6 = #var7
       7 [-]: ADD R0 R0 R6 ; var0 = var0 + var6
L 1:   8 [-]: FORGLOOP R1 L0 2 [inext]; 
       9 [-]: RETURN R0 1  ; 


; Name:            
; Defined at line: 479
; #Upvalues:       2
; #Parameters:     0
; Is_vararg:       0
; Max Stack Size:  12

       0 [-]: GETIMPORT R0 1; var0 = 0xC8802016
       1 [-]: GETUPVAL R1 0; var1 = upvalues[0]
       2 [-]: CALL R0 2 4  ; var0, var1, var2 = var0(var1)
       3 [-]: FORGPREP_INEXT R0 L1; 
L 0:   4 [-]: GETUPVAL R5 1; var5 = upvalues[1]
       5 [-]: GETIMPORT R7 3; var7 = 0x0469F296
       6 [-]: LOADK R9 K4  ; var9 = "Quadrant"
       7 [-]: MOVE R10 R3  ; var10 = var3
       8 [-]: LOADK R11 K5 ; var11 = " Enemies"
       9 [-]: CONCAT R8 R9 R11; var8 = var9 .. var11
      10 [-]: CALL R7 2 2  ; var7 = var7(var8)
      11 [-]: GETIMPORT R8 7; var8 = 0x64FB1586
      12 [-]: GETTABLEKS R10 R4 K8; var10 = var4["Enemies"]
      13 [-]: LENGTH R9 R10; var9 = #var10
      14 [-]: CALL R8 2 0  ; var8, ... = var8(var9)
      15 [-]: NAMECALL R5 R5 K9; var6 = var5; var5 = var5[0xC7A98999]
      16 [-]: CALL R5 0 1  ; var5(var6, ...)
      17 [-]: GETUPVAL R5 1; var5 = upvalues[1]
      18 [-]: GETIMPORT R7 3; var7 = 0x0469F296
      19 [-]: LOADK R9 K4  ; var9 = "Quadrant"
      20 [-]: MOVE R10 R3  ; var10 = var3
      21 [-]: LOADK R11 K10; var11 = " Guards"
      22 [-]: CONCAT R8 R9 R11; var8 = var9 .. var11
      23 [-]: CALL R7 2 2  ; var7 = var7(var8)
      24 [-]: GETIMPORT R8 7; var8 = 0x64FB1586
      25 [-]: GETTABLEKS R10 R4 K11; var10 = var4["Guards"]
      26 [-]: LENGTH R9 R10; var9 = #var10
      27 [-]: CALL R8 2 0  ; var8, ... = var8(var9)
      28 [-]: NAMECALL R5 R5 K9; var6 = var5; var5 = var5[0xC7A98999]
      29 [-]: CALL R5 0 1  ; var5(var6, ...)
L 1:  30 [-]: FORGLOOP R0 L0 2 [inext]; 
      31 [-]: RETURN R0 0  ; 


; Name:            
; Defined at line: 486
; #Upvalues:       3
; #Parameters:     0
; Is_vararg:       0
; Max Stack Size:  6

       0 [-]: LOADN R0 4   ; var0 = 4
       1 [-]: GETUPVAL R2 0; var2 = upvalues[0]
       2 [-]: FASTCALL1 62 R2 L0; 
       3 [-]: GETIMPORT R1 1; var1 = 0x7B998233
       4 [-]: CALL R1 2 2  ; var1 = var1(var2)
L 0:   5 [-]: JUMPIF R1 L1 ; goto L1 if var1
       6 [-]: GETUPVAL R1 0; var1 = upvalues[0]
       7 [-]: NAMECALL R1 R1 K2; var2 = var1; var1 = var1[0xEFF44F5B]
       8 [-]: CALL R1 2 2  ; var1 = var1(var2)
       9 [-]: MOVE R0 R1   ; var0 = var1
L 1:  10 [-]: GETUPVAL R2 1; var2 = upvalues[1]
      11 [-]: GETUPVAL R4 2; var4 = upvalues[2]
      12 [-]: LOADN R5 0   ; var5 = 0
      13 [-]: NAMECALL R2 R2 K3; var3 = var2; var2 = var2[0x0EB34C69]
      14 [-]: CALL R2 4 2  ; var2 = var2(var3, var4, var5)
      15 [-]: FASTCALL2K 19 R2 K4 L2; 
      16 [-]: LOADK R3 K4  ; var3 = 8
      17 [-]: GETIMPORT R1 7; var1 = 0x5BCED4C4[0xAC1B386A]
      18 [-]: CALL R1 3 2  ; var1 = var1(var2, var3)
L 2:  19 [-]: GETIMPORT R2 9; var2 = _T
      20 [-]: DUPTABLE R3 13; 
      21 [-]: LOADN R5 4   ; var5 = 4
      22 [-]: SUB R4 R5 R0 ; var4 = var5 - var0
      23 [-]: SETTABLEKS R4 R3 K10; var4["Curr"] = var3
      24 [-]: LOADN R4 4   ; var4 = 4
      25 [-]: SETTABLEKS R4 R3 K11; var4["Total"] = var3
      26 [-]: DUPTABLE R4 15; 
      27 [-]: LOADK R5 K16 ; var5 = "/Lotus/Language/Menu/GhostTowerKuvaProgress"
      28 [-]: SETTABLEKS R5 R4 K14; var5["Title"] = var4
      29 [-]: SETTABLEKS R1 R4 K10; var1["Curr"] = var4
      30 [-]: LOADN R5 8   ; var5 = 8
      31 [-]: SETTABLEKS R5 R4 K11; var5["Total"] = var4
      32 [-]: SETTABLEKS R4 R3 K12; var4["List"] = var3
      33 [-]: SETTABLEKS R3 R2 K17; var3["VoidTearProgress"] = var2
      34 [-]: RETURN R0 0  ; 


; Name:            
; Defined at line: 498
; #Upvalues:       2
; #Parameters:     2
; Is_vararg:       0
; Max Stack Size:  17

       0 [-]: GETIMPORT R2 1; var2 = 0x89326C93
       1 [-]: NAMECALL R2 R2 K2; var3 = var2; var2 = var2[0x7C1A0374]
       2 [-]: CALL R2 2 2  ; var2 = var2(var3)
       3 [-]: FASTCALL1 62 R2 L0; 
       4 [-]: MOVE R4 R2   ; var4 = var2
       5 [-]: GETIMPORT R3 4; var3 = 0x7B998233
       6 [-]: CALL R3 2 2  ; var3 = var3(var4)
L 0:   7 [-]: JUMPIFNOT R3 L1; goto L1 if not var3
       8 [-]: RETURN R0 0  ; 
L 1:   9 [-]: RETURN R0 0  ; 
      10 [-]: JUMPIFNOT R0 L2; goto L2 if not var0
      11 [-]: NAMECALL R3 R1 K5; var4 = var1; var3 = var1[0x0B4BCFB6]
      12 [-]: CALL R3 2 2  ; var3 = var3(var4)
      13 [-]: GETIMPORT R5 7; var5 = 0x6C0CD726
      14 [-]: LOADN R6 3   ; var6 = 3
      15 [-]: LOADN R7 -1  ; var7 = -1
      16 [-]: LOADN R8 3   ; var8 = 3
      17 [-]: NAMECALL R3 R3 K8; var4 = var3; var3 = var3[0x758C046D]
      18 [-]: CALL R3 6 1  ; var3(var4, var5, var6, var7, var8)
      19 [-]: JUMP L3      ; goto L3
L 2:  20 [-]: NAMECALL R3 R1 K5; var4 = var1; var3 = var1[0x0B4BCFB6]
      21 [-]: CALL R3 2 2  ; var3 = var3(var4)
      22 [-]: GETIMPORT R5 7; var5 = 0x6C0CD726
      23 [-]: NAMECALL R3 R3 K9; var4 = var3; var3 = var3[0xBD5007D9]
      24 [-]: CALL R3 3 1  ; var3(var4, var5)
L 3:  25 [-]: GETIMPORT R3 1; var3 = 0x89326C93
      26 [-]: GETIMPORT R5 11; var5 = gZoneAttribsType
      27 [-]: NAMECALL R3 R3 K12; var4 = var3; var3 = var3[0xFB669000]
      28 [-]: CALL R3 3 2  ; var3 = var3(var4, var5)
      29 [-]: NEWTABLE R4 0 0; var4 = {}
      30 [-]: GETIMPORT R5 14; var5 = 0x0469F296
      31 [-]: LOADK R6 K15 ; var6 = "Backdrop"
      32 [-]: CALL R5 2 2  ; var5 = var5(var6)
      33 [-]: GETIMPORT R6 14; var6 = 0x0469F296
      34 [-]: LOADK R7 K16 ; var7 = "FlyIn"
      35 [-]: CALL R6 2 2  ; var6 = var6(var7)
      36 [-]: GETUPVAL R8 0; var8 = upvalues[0]
      37 [-]: LENGTH R7 R8 ; var7 = #var8
      38 [-]: JUMPXEQKN R7 K17 L10 NOT; 
      39 [-]: LOADN R9 1   ; var9 = 1
      40 [-]: LENGTH R7 R3 ; var7 = #var3
      41 [-]: LOADN R8 1   ; var8 = 1
      42 [-]: FORNPREP R7 L10; nforprep start - [escape at L10] -- var7 = iterator
L 4:  43 [-]: GETTABLE R11 R3 R9; var11 = var3[var9]
      44 [-]: FASTCALL1 62 R11 L5; 
      45 [-]: GETIMPORT R10 4; var10 = 0x7B998233
      46 [-]: CALL R10 2 2 ; var10 = var10(var11)
L 5:  47 [-]: JUMPIF R10 L9; goto L9 if var10
      48 [-]: GETTABLE R10 R3 R9; var10 = var3[var9]
      49 [-]: NAMECALL R10 R10 K18; var11 = var10; var10 = var10[0xEFE29E59]
      50 [-]: CALL R10 2 2 ; var10 = var10(var11)
      51 [-]: JUMPIFNOTEQ R10 R6 L6; goto L6 if var10 ~= var1507392
      52 [-]: JUMP L9      ; goto L9
L 6:  53 [-]: GETTABLE R10 R3 R9; var10 = var3[var9]
      54 [-]: NAMECALL R10 R10 K19; var11 = var10; var10 = var10[0x22DA1852]
      55 [-]: CALL R10 2 2 ; var10 = var10(var11)
      56 [-]: JUMPIFEQ R10 R5 L8; goto L8 if var10 == var2823
      57 [-]: GETUPVAL R11 0; var11 = upvalues[0]
      58 [-]: GETTABLE R12 R3 R9; var12 = var3[var9]
      59 [-]: NAMECALL R12 R12 K20; var13 = var12; var12 = var12[0xE79E7EF4]
      60 [-]: CALL R12 2 0 ; var12, ... = var12(var13)
      61 [-]: FASTCALL 52 L7; 
      62 [-]: GETIMPORT R10 23; var10 = 0x33BDD652[0x23D5322F]
      63 [-]: CALL R10 0 1 ; var10(var11, ...)
L 7:  64 [-]: JUMP L9      ; goto L9
L 8:  65 [-]: GETTABLE R12 R3 R9; var12 = var3[var9]
      66 [-]: FASTCALL2 52 R4 R12 L9; 
      67 [-]: MOVE R11 R4  ; var11 = var4
      68 [-]: GETIMPORT R10 23; var10 = 0x33BDD652[0x23D5322F]
      69 [-]: CALL R10 3 1 ; var10(var11, var12)
L 9:  70 [-]: FORNLOOP R7 L4; nforloop end - iterate + goto L4
L10:  71 [-]: JUMPIFNOT R0 L14; goto L14 if not var0
      72 [-]: GETIMPORT R7 25; var7 = 0xC8802016
      73 [-]: GETUPVAL R8 0; var8 = upvalues[0]
      74 [-]: CALL R7 2 4  ; var7, var8, var9 = var7(var8)
      75 [-]: FORGPREP_INEXT R7 L13; 
L11:  76 [-]: FASTCALL1 62 R11 L12; 
      77 [-]: MOVE R13 R11 ; var13 = var11
      78 [-]: GETIMPORT R12 4; var12 = 0x7B998233
      79 [-]: CALL R12 2 2 ; var12 = var12(var13)
L12:  80 [-]: JUMPIF R12 L13; goto L13 if var12
      81 [-]: GETUPVAL R12 1; var12 = upvalues[1]
      82 [-]: NEWTABLE R13 0 0; var13 = {}
      83 [-]: SETTABLE R13 R12 R10; var13[var12] = var10
      84 [-]: GETUPVAL R13 1; var13 = upvalues[1]
      85 [-]: GETTABLE R12 R13 R10; var12 = var13[var10]
      86 [-]: NAMECALL R13 R11 K26; var14 = var11; var13 = var11[0x30CC91B5]
      87 [-]: CALL R13 2 2 ; var13 = var13(var14)
      88 [-]: SETTABLEKS R13 R12 K27; var13["color"] = var12
      89 [-]: GETUPVAL R13 1; var13 = upvalues[1]
      90 [-]: GETTABLE R12 R13 R10; var12 = var13[var10]
      91 [-]: NAMECALL R13 R11 K28; var14 = var11; var13 = var11[0x9D57BB35]
      92 [-]: CALL R13 2 2 ; var13 = var13(var14)
      93 [-]: SETTABLEKS R13 R12 K29; var13["density"] = var12
      94 [-]: GETIMPORT R14 31; var14 = 0x9FB5C070
      95 [-]: NAMECALL R12 R11 K32; var13 = var11; var12 = var11[0x16A61AD1]
      96 [-]: CALL R12 3 1 ; var12(var13, var14)
      97 [-]: LOADN R14 1  ; var14 = 1
      98 [-]: NAMECALL R12 R11 K33; var13 = var11; var12 = var11[0x5E78B499]
      99 [-]: CALL R12 3 1 ; var12(var13, var14)
L13: 100 [-]: FORGLOOP R7 L11 2 [inext]; 
     101 [-]: RETURN R0 0  ; 
L14: 102 [-]: GETIMPORT R7 25; var7 = 0xC8802016
     103 [-]: GETUPVAL R8 0; var8 = upvalues[0]
     104 [-]: CALL R7 2 4  ; var7, var8, var9 = var7(var8)
     105 [-]: FORGPREP_INEXT R7 L17; 
L15: 106 [-]: FASTCALL1 62 R11 L16; 
     107 [-]: MOVE R13 R11 ; var13 = var11
     108 [-]: GETIMPORT R12 4; var12 = 0x7B998233
     109 [-]: CALL R12 2 2 ; var12 = var12(var13)
L16: 110 [-]: JUMPIF R12 L17; goto L17 if var12
     111 [-]: GETUPVAL R16 1; var16 = upvalues[1]
     112 [-]: GETTABLE R15 R16 R10; var15 = var16[var10]
     113 [-]: GETTABLEKS R14 R15 K27; var14 = var15["color"]
     114 [-]: NAMECALL R12 R11 K32; var13 = var11; var12 = var11[0x16A61AD1]
     115 [-]: CALL R12 3 1 ; var12(var13, var14)
     116 [-]: GETUPVAL R16 1; var16 = upvalues[1]
     117 [-]: GETTABLE R15 R16 R10; var15 = var16[var10]
     118 [-]: GETTABLEKS R14 R15 K29; var14 = var15["density"]
     119 [-]: NAMECALL R12 R11 K33; var13 = var11; var12 = var11[0x5E78B499]
     120 [-]: CALL R12 3 1 ; var12(var13, var14)
L17: 121 [-]: FORGLOOP R7 L15 2 [inext]; 
     122 [-]: RETURN R0 0  ; 


; Name:            
; Defined at line: 564
; #Upvalues:       4
; #Parameters:     0
; Is_vararg:       0
; Max Stack Size:  11

       0 [-]: GETIMPORT R0 1; var0 = 0x89326C93
       1 [-]: GETIMPORT R2 3; var2 = gLotusOperatorAvatarType
       2 [-]: NAMECALL R0 R0 K4; var1 = var0; var0 = var0[0xFB669000]
       3 [-]: CALL R0 3 2  ; var0 = var0(var1, var2)
       4 [-]: LOADB R1 0   ; var1 = false
       5 [-]: GETIMPORT R2 6; var2 = 0xC8802016
       6 [-]: MOVE R3 R0   ; var3 = var0
       7 [-]: CALL R2 2 4  ; var2, var3, var4 = var2(var3)
       8 [-]: FORGPREP_INEXT R2 L3; 
L 0:   9 [-]: GETUPVAL R7 0; var7 = upvalues[0]
      10 [-]: MOVE R9 R6   ; var9 = var6
      11 [-]: NAMECALL R7 R7 K7; var8 = var7; var7 = var7[0xBEBAD19F]
      12 [-]: CALL R7 3 2  ; var7 = var7(var8, var9)
      13 [-]: LOADN R8 30  ; var8 = 30
      14 [-]: JUMPIFNOTLT R7 R8 L3; goto L3 if var7 >= var657230
      15 [-]: GETIMPORT R7 10; var7 = 0x5BCED4C4[0x3630E649]
      16 [-]: CALL R7 1 2  ; var7 = var7()
      17 [-]: LOADK R8 K11 ; var8 = 0.5
      18 [-]: JUMPIFNOTLT R7 R8 L1; goto L1 if var7 >= var67591
      19 [-]: GETUPVAL R8 1; var8 = upvalues[1]
      20 [-]: GETTABLEKS R7 R8 K12; var7 = var8[0x9742B85B]
      21 [-]: GETIMPORT R8 14; var8 = 0xE91D7466
      22 [-]: GETIMPORT R9 16; var9 = 0x0469F296
      23 [-]: LOADK R10 K17; var10 = "DKSSwitchOperatorWormQueen"
      24 [-]: CALL R9 2 0  ; var9, ... = var9(var10)
      25 [-]: CALL R7 0 1  ; var7(var8, ...)
      26 [-]: JUMP L2      ; goto L2
L 1:  27 [-]: GETUPVAL R8 1; var8 = upvalues[1]
      28 [-]: GETTABLEKS R7 R8 K12; var7 = var8[0x9742B85B]
      29 [-]: GETIMPORT R8 14; var8 = 0xE91D7466
      30 [-]: GETIMPORT R9 16; var9 = 0x0469F296
      31 [-]: LOADK R10 K18; var10 = "DKSSwitchOperatorLotus"
      32 [-]: CALL R9 2 0  ; var9, ... = var9(var10)
      33 [-]: CALL R7 0 1  ; var7(var8, ...)
L 2:  34 [-]: LOADB R1 1   ; var1 = true
      35 [-]: JUMP L4      ; goto L4
L 3:  36 [-]: FORGLOOP R2 L0 2 [inext]; 
L 4:  37 [-]: JUMPIF R1 L5 ; goto L5 if var1
      38 [-]: GETUPVAL R2 2; var2 = upvalues[2]
      39 [-]: LOADN R4 2   ; var4 = 2
      40 [-]: GETUPVAL R5 3; var5 = upvalues[3]
      41 [-]: LOADB R6 0   ; var6 = false
      42 [-]: NAMECALL R2 R2 K19; var3 = var2; var2 = var2[0xBD2E96EA]
      43 [-]: CALL R2 5 1  ; var2(var3, var4, var5, var6)
L 5:  44 [-]: RETURN R0 0  ; 


; Name:            
; Defined at line: 585
; #Upvalues:       20
; #Parameters:     1
; Is_vararg:       0
; Max Stack Size:  19

       0 [-]: GETIMPORT R1 1; var1 = 0x2D0FAD09
       1 [-]: LOADK R2 K2  ; var2 = "Lotus.Interface.Libs.TimerMgr"
       2 [-]: CALL R1 2 2  ; var1 = var1(var2)
       3 [-]: GETTABLEKS R2 R1 K3; var2 = var1[0xDE474187]
       4 [-]: CALL R2 1 2  ; var2 = var2()
       5 [-]: SETUPVAL R2 0; upvalues[2] = var0
       6 [-]: GETIMPORT R2 5; var2 = 0x89326C93
       7 [-]: NAMECALL R2 R2 K6; var3 = var2; var2 = var2[0x18D05D30]
       8 [-]: CALL R2 2 2  ; var2 = var2(var3)
       9 [-]: JUMPIFNOT R2 L0; goto L0 if not var2
      10 [-]: LOADN R4 1   ; var4 = 1
      11 [-]: NAMECALL R2 R0 K7; var3 = var0; var2 = var0[0x05EEB9DB]
      12 [-]: CALL R2 3 1  ; var2(var3, var4)
L 0:  13 [-]: GETIMPORT R2 10; var2 = _T["VoidTearOverride"]
      14 [-]: LOADK R3 K11 ; var3 = "/Lotus/Language/Menu/GhostTowerProgress"
      15 [-]: GETUPVAL R4 1; var4 = upvalues[1]
      16 [-]: LOADN R5 32  ; var5 = 32
      17 [-]: CALL R2 4 1  ; var2(var3, var4, var5)
      18 [-]: GETIMPORT R2 5; var2 = 0x89326C93
      19 [-]: NAMECALL R2 R2 K6; var3 = var2; var2 = var2[0x18D05D30]
      20 [-]: CALL R2 2 2  ; var2 = var2(var3)
      21 [-]: JUMPIF R2 L5 ; goto L5 if var2
L 1:  22 [-]: GETUPVAL R3 2; var3 = upvalues[2]
      23 [-]: FASTCALL1 62 R3 L2; 
      24 [-]: GETIMPORT R2 13; var2 = 0x7B998233
      25 [-]: CALL R2 2 2  ; var2 = var2(var3)
L 2:  26 [-]: JUMPIFNOT R2 L3; goto L3 if not var2
      27 [-]: GETIMPORT R2 15; var2 = 0xCBD666E1
      28 [-]: LOADN R3 1   ; var3 = 1
      29 [-]: CALL R2 2 1  ; var2(var3)
      30 [-]: GETIMPORT R2 5; var2 = 0x89326C93
      31 [-]: GETIMPORT R4 17; var4 = gVoidNegationTowerAvatarType
      32 [-]: NAMECALL R5 R0 K18; var6 = var0; var5 = var0[0xD1586535]
      33 [-]: CALL R5 2 2  ; var5 = var5(var6)
      34 [-]: LOADK R6 K19 ; var6 = 3.4028234663852886e+38
      35 [-]: NAMECALL R2 R2 K20; var3 = var2; var2 = var2[0x4E5939A5]
      36 [-]: CALL R2 5 2  ; var2 = var2(var3, var4, var5, var6)
      37 [-]: SETUPVAL R2 2; upvalues[2] = var2
      38 [-]: JUMPBACK L1  ; goto L1
L 3:  39 [-]: GETIMPORT R2 5; var2 = 0x89326C93
      40 [-]: NAMECALL R2 R2 K6; var3 = var2; var2 = var2[0x18D05D30]
      41 [-]: CALL R2 2 2  ; var2 = var2(var3)
      42 [-]: JUMPIF R2 L5 ; goto L5 if var2
      43 [-]: NAMECALL R2 R0 K21; var3 = var0; var2 = var0[0xF37943FF]
      44 [-]: CALL R2 2 2  ; var2 = var2(var3)
      45 [-]: JUMPIF R2 L4 ; goto L4 if var2
      46 [-]: GETIMPORT R2 22; var2 = _T
      47 [-]: LOADNIL R3   ; var3 = nil
      48 [-]: SETTABLEKS R3 R2 K23; var3["VoidTearProgress"] = var2
      49 [-]: RETURN R0 0  ; 
L 4:  50 [-]: GETUPVAL R2 3; var2 = upvalues[3]
      51 [-]: CALL R2 1 1  ; var2()
      52 [-]: GETIMPORT R2 15; var2 = 0xCBD666E1
      53 [-]: LOADN R3 0   ; var3 = 0
      54 [-]: CALL R2 2 1  ; var2(var3)
      55 [-]: JUMPBACK L3  ; goto L3
L 5:  56 [-]: GETUPVAL R3 4; var3 = upvalues[4]
      57 [-]: FASTCALL1 62 R3 L6; 
      58 [-]: GETIMPORT R2 13; var2 = 0x7B998233
      59 [-]: CALL R2 2 2  ; var2 = var2(var3)
L 6:  60 [-]: JUMPIFNOT R2 L7; goto L7 if not var2
      61 [-]: GETIMPORT R2 25; var2 = 0xBE190284
      62 [-]: SETUPVAL R2 4; upvalues[2] = var4
      63 [-]: GETIMPORT R2 15; var2 = 0xCBD666E1
      64 [-]: LOADN R3 0   ; var3 = 0
      65 [-]: CALL R2 2 1  ; var2(var3)
      66 [-]: JUMPBACK L5  ; goto L5
L 7:  67 [-]: GETIMPORT R2 27; var2 = 0x14459A1C
      68 [-]: JUMPIFNOT R2 L11; goto L11 if not var2
L 8:  69 [-]: GETIMPORT R3 10; var3 = _T["VoidTearOverride"]
      70 [-]: FASTCALL1 62 R3 L9; 
      71 [-]: GETIMPORT R2 13; var2 = 0x7B998233
      72 [-]: CALL R2 2 2  ; var2 = var2(var3)
L 9:  73 [-]: JUMPIFNOT R2 L10; goto L10 if not var2
      74 [-]: GETIMPORT R2 15; var2 = 0xCBD666E1
      75 [-]: LOADN R3 0   ; var3 = 0
      76 [-]: CALL R2 2 1  ; var2(var3)
      77 [-]: JUMPBACK L8  ; goto L8
L10:  78 [-]: GETIMPORT R2 10; var2 = _T["VoidTearOverride"]
      79 [-]: LOADK R3 K11 ; var3 = "/Lotus/Language/Menu/GhostTowerProgress"
      80 [-]: GETUPVAL R4 1; var4 = upvalues[1]
      81 [-]: LOADN R5 32  ; var5 = 32
      82 [-]: CALL R2 4 1  ; var2(var3, var4, var5)
L11:  83 [-]: GETUPVAL R2 5; var2 = upvalues[5]
      84 [-]: MOVE R3 R0   ; var3 = var0
      85 [-]: CALL R2 2 1  ; var2(var3)
      86 [-]: GETIMPORT R2 27; var2 = 0x14459A1C
      87 [-]: JUMPIF R2 L12; goto L12 if var2
      88 [-]: GETUPVAL R2 0; var2 = upvalues[0]
      89 [-]: LOADN R4 2   ; var4 = 2
      90 [-]: GETUPVAL R5 6; var5 = upvalues[6]
      91 [-]: LOADB R6 0   ; var6 = false
      92 [-]: NAMECALL R2 R2 K28; var3 = var2; var2 = var2[0xBD2E96EA]
      93 [-]: CALL R2 5 1  ; var2(var3, var4, var5, var6)
L12:  94 [-]: LOADN R2 0   ; var2 = 0
      95 [-]: LOADN R3 4   ; var3 = 4
      96 [-]: GETIMPORT R4 27; var4 = 0x14459A1C
      97 [-]: LOADB R5 0   ; var5 = false
L13:  98 [-]: GETUPVAL R6 7; var6 = upvalues[7]
      99 [-]: JUMPIF R6 L38; goto L38 if var6
     100 [-]: GETUPVAL R6 8; var6 = upvalues[8]
     101 [-]: JUMPIF R6 L38; goto L38 if var6
     102 [-]: GETIMPORT R6 15; var6 = 0xCBD666E1
     103 [-]: LOADN R7 0   ; var7 = 0
     104 [-]: CALL R6 2 1  ; var6(var7)
     105 [-]: GETUPVAL R6 3; var6 = upvalues[3]
     106 [-]: CALL R6 1 1  ; var6()
     107 [-]: GETUPVAL R6 0; var6 = upvalues[0]
     108 [-]: GETIMPORT R8 30; var8 = 0x67652851
     109 [-]: CALL R8 1 0  ; var8, ... = var8()
     110 [-]: NAMECALL R6 R6 K31; var7 = var6; var6 = var6[0xFAA69527]
     111 [-]: CALL R6 0 1  ; var6(var7, ...)
     112 [-]: GETUPVAL R6 9; var6 = upvalues[9]
     113 [-]: CALL R6 1 1  ; var6()
     114 [-]: GETIMPORT R7 32; var7 = _T["VoidTearProgress"]
     115 [-]: FASTCALL1 62 R7 L14; 
     116 [-]: GETIMPORT R6 13; var6 = 0x7B998233
     117 [-]: CALL R6 2 2  ; var6 = var6(var7)
L14: 118 [-]: JUMPIF R6 L15; goto L15 if var6
     119 [-]: JUMPIF R5 L15; goto L15 if var5
     120 [-]: GETUPVAL R7 10; var7 = upvalues[10]
     121 [-]: GETTABLEKS R6 R7 K33; var6 = var7[0xCF85C639]
     122 [-]: CALL R6 1 1  ; var6()
     123 [-]: LOADB R5 1   ; var5 = true
L15: 124 [-]: GETUPVAL R7 2; var7 = upvalues[2]
     125 [-]: FASTCALL1 62 R7 L16; 
     126 [-]: GETIMPORT R6 13; var6 = 0x7B998233
     127 [-]: CALL R6 2 2  ; var6 = var6(var7)
L16: 128 [-]: JUMPIF R6 L17; goto L17 if var6
     129 [-]: GETUPVAL R6 2; var6 = upvalues[2]
     130 [-]: NAMECALL R6 R6 K34; var7 = var6; var6 = var6[0xEFF44F5B]
     131 [-]: CALL R6 2 2  ; var6 = var6(var7)
     132 [-]: MOVE R3 R6   ; var3 = var6
     133 [-]: JUMP L18     ; goto L18
L17: 134 [-]: GETIMPORT R6 36; var6 = 0x3D106989
     135 [-]: LOADK R7 K37 ; var7 = "GhostTowerAvatar is null during the update loop"
     136 [-]: CALL R6 2 1  ; var6(var7)
     137 [-]: GETIMPORT R6 5; var6 = 0x89326C93
     138 [-]: GETIMPORT R8 17; var8 = gVoidNegationTowerAvatarType
     139 [-]: NAMECALL R9 R0 K18; var10 = var0; var9 = var0[0xD1586535]
     140 [-]: CALL R9 2 2  ; var9 = var9(var10)
     141 [-]: LOADK R10 K19; var10 = 3.4028234663852886e+38
     142 [-]: NAMECALL R6 R6 K20; var7 = var6; var6 = var6[0x4E5939A5]
     143 [-]: CALL R6 5 2  ; var6 = var6(var7, var8, var9, var10)
     144 [-]: SETUPVAL R6 2; upvalues[6] = var2
L18: 145 [-]: LOADN R6 60  ; var6 = 60
     146 [-]: JUMPIFNOTLT R6 R2 L21; goto L21 if var6 >= var263751
     147 [-]: LOADN R6 4   ; var6 = 4
     148 [-]: JUMPIFNOTLE R6 R3 L21; goto L21 if var6 > var1836100
     149 [-]: JUMPIF R4 L21; goto L21 if var4
     150 [-]: GETIMPORT R6 40; var6 = 0x5BCED4C4[0x3630E649]
     151 [-]: CALL R6 1 2  ; var6 = var6()
     152 [-]: LOADK R7 K41 ; var7 = 0.5
     153 [-]: JUMPIFNOTLT R6 R7 L19; goto L19 if var6 >= var722695
     154 [-]: GETUPVAL R7 11; var7 = upvalues[11]
     155 [-]: GETTABLEKS R6 R7 K42; var6 = var7[0x9742B85B]
     156 [-]: GETIMPORT R7 44; var7 = 0xE91D7466
     157 [-]: GETIMPORT R8 46; var8 = 0x0469F296
     158 [-]: LOADK R9 K47 ; var9 = "DKSDestroyAttemptWormQueen"
     159 [-]: CALL R8 2 0  ; var8, ... = var8(var9)
     160 [-]: CALL R6 0 1  ; var6(var7, ...)
     161 [-]: JUMP L20     ; goto L20
L19: 162 [-]: GETUPVAL R7 11; var7 = upvalues[11]
     163 [-]: GETTABLEKS R6 R7 K42; var6 = var7[0x9742B85B]
     164 [-]: GETIMPORT R7 44; var7 = 0xE91D7466
     165 [-]: GETIMPORT R8 46; var8 = 0x0469F296
     166 [-]: LOADK R9 K48 ; var9 = "DKSDestroyAttemptLotus"
     167 [-]: CALL R8 2 0  ; var8, ... = var8(var9)
     168 [-]: CALL R6 0 1  ; var6(var7, ...)
L20: 169 [-]: LOADB R4 1   ; var4 = true
L21: 170 [-]: GETIMPORT R6 30; var6 = 0x67652851
     171 [-]: CALL R6 1 2  ; var6 = var6()
     172 [-]: ADD R2 R2 R6 ; var2 = var2 + var6
     173 [-]: LOADN R8 0   ; var8 = 0
     174 [-]: GETIMPORT R9 50; var9 = 0xC8802016
     175 [-]: GETUPVAL R10 12; var10 = upvalues[12]
     176 [-]: CALL R9 2 4  ; var9, var10, var11 = var9(var10)
     177 [-]: FORGPREP_INEXT R9 L23; 
L22: 178 [-]: GETTABLEKS R15 R13 K51; var15 = var13["Guards"]
     179 [-]: LENGTH R14 R15; var14 = #var15
     180 [-]: ADD R8 R8 R14; var8 = var8 + var14
L23: 181 [-]: FORGLOOP R9 L22 2 [inext]; 
     182 [-]: MOVE R7 R8   ; var7 = var8
     183 [-]: GETUPVAL R8 13; var8 = upvalues[13]
     184 [-]: ADD R6 R7 R8 ; var6 = var7 + var8
     185 [-]: JUMPXEQKN R6 K52 L26 NOT; 
     186 [-]: LOADN R8 1   ; var8 = 1
     187 [-]: GETUPVAL R6 14; var6 = upvalues[14]
     188 [-]: LOADN R7 1   ; var7 = 1
     189 [-]: FORNPREP R6 L25; nforprep start - [escape at L25] -- var6 = iterator
L24: 190 [-]: GETUPVAL R9 0; var9 = upvalues[0]
     191 [-]: LOADN R11 50 ; var11 = 50
     192 [-]: GETUPVAL R12 15; var12 = upvalues[15]
     193 [-]: LOADB R13 0  ; var13 = false
     194 [-]: NAMECALL R9 R9 K28; var10 = var9; var9 = var9[0xBD2E96EA]
     195 [-]: CALL R9 5 1  ; var9(var10, var11, var12, var13)
     196 [-]: FORNLOOP R6 L24; nforloop end - iterate + goto L24
L25: 197 [-]: GETUPVAL R6 14; var6 = upvalues[14]
     198 [-]: SETUPVAL R6 13; upvalues[6] = var13
L26: 199 [-]: GETIMPORT R6 50; var6 = 0xC8802016
     200 [-]: GETUPVAL R7 12; var7 = upvalues[12]
     201 [-]: CALL R6 2 4  ; var6, var7, var8 = var6(var7)
     202 [-]: FORGPREP_INEXT R6 L35; 
L27: 203 [-]: GETTABLEKS R14 R10 K53; var14 = var10["Enemies"]
     204 [-]: LENGTH R13 R14; var13 = #var14
     205 [-]: LOADN R11 1  ; var11 = 1
     206 [-]: LOADN R12 -1 ; var12 = -1
     207 [-]: FORNPREP R11 L31; nforprep start - [escape at L31] -- var11 = iterator
L28: 208 [-]: GETTABLEKS R15 R10 K53; var15 = var10["Enemies"]
     209 [-]: GETTABLE R14 R15 R13; var14 = var15[var13]
     210 [-]: FASTCALL1 62 R14 L29; 
     211 [-]: MOVE R16 R14 ; var16 = var14
     212 [-]: GETIMPORT R15 13; var15 = 0x7B998233
     213 [-]: CALL R15 2 2 ; var15 = var15(var16)
L29: 214 [-]: JUMPIFNOT R15 L30; goto L30 if not var15
     215 [-]: GETIMPORT R15 56; var15 = 0x33BDD652[0x9C1F3B5A]
     216 [-]: GETTABLEKS R16 R10 K53; var16 = var10["Enemies"]
     217 [-]: MOVE R17 R13 ; var17 = var13
     218 [-]: CALL R15 3 1 ; var15(var16, var17)
L30: 219 [-]: FORNLOOP R11 L28; nforloop end - iterate + goto L28
L31: 220 [-]: GETTABLEKS R14 R10 K51; var14 = var10["Guards"]
     221 [-]: LENGTH R13 R14; var13 = #var14
     222 [-]: LOADN R11 1  ; var11 = 1
     223 [-]: LOADN R12 -1 ; var12 = -1
     224 [-]: FORNPREP R11 L35; nforprep start - [escape at L35] -- var11 = iterator
L32: 225 [-]: GETTABLEKS R15 R10 K51; var15 = var10["Guards"]
     226 [-]: GETTABLE R14 R15 R13; var14 = var15[var13]
     227 [-]: FASTCALL1 62 R14 L33; 
     228 [-]: MOVE R16 R14 ; var16 = var14
     229 [-]: GETIMPORT R15 13; var15 = 0x7B998233
     230 [-]: CALL R15 2 2 ; var15 = var15(var16)
L33: 231 [-]: JUMPIFNOT R15 L34; goto L34 if not var15
     232 [-]: GETIMPORT R15 56; var15 = 0x33BDD652[0x9C1F3B5A]
     233 [-]: GETTABLEKS R16 R10 K51; var16 = var10["Guards"]
     234 [-]: MOVE R17 R13 ; var17 = var13
     235 [-]: CALL R15 3 1 ; var15(var16, var17)
L34: 236 [-]: FORNLOOP R11 L32; nforloop end - iterate + goto L32
L35: 237 [-]: FORGLOOP R6 L27 2 [inext]; 
     238 [-]: LOADN R6 0   ; var6 = 0
     239 [-]: JUMPIFNOTLE R3 R6 L36; goto L36 if var3 > var67099
     240 [-]: LOADB R6 1   ; var6 = true
     241 [-]: SETUPVAL R6 7; upvalues[6] = var7
     242 [-]: JUMP L37     ; goto L37
L36: 243 [-]: GETUPVAL R6 4; var6 = upvalues[4]
     244 [-]: GETUPVAL R8 16; var8 = upvalues[16]
     245 [-]: LOADN R9 0   ; var9 = 0
     246 [-]: NAMECALL R6 R6 K57; var7 = var6; var6 = var6[0x0EB34C69]
     247 [-]: CALL R6 4 2  ; var6 = var6(var7, var8, var9)
     248 [-]: LOADN R7 8   ; var7 = 8
     249 [-]: JUMPIFNOTLE R7 R6 L37; goto L37 if var7 > var67099
     250 [-]: LOADB R6 1   ; var6 = true
     251 [-]: SETUPVAL R6 8; upvalues[6] = var8
L37: 252 [-]: JUMPBACK L13 ; goto L13
L38: 253 [-]: GETIMPORT R6 50; var6 = 0xC8802016
     254 [-]: GETUPVAL R7 12; var7 = upvalues[12]
     255 [-]: CALL R6 2 4  ; var6, var7, var8 = var6(var7)
     256 [-]: FORGPREP_INEXT R6 L43; 
L39: 257 [-]: GETIMPORT R11 50; var11 = 0xC8802016
     258 [-]: GETTABLEKS R12 R10 K51; var12 = var10["Guards"]
     259 [-]: CALL R11 2 4 ; var11, var12, var13 = var11(var12)
     260 [-]: FORGPREP_INEXT R11 L42; 
L40: 261 [-]: FASTCALL1 62 R15 L41; 
     262 [-]: MOVE R17 R15 ; var17 = var15
     263 [-]: GETIMPORT R16 13; var16 = 0x7B998233
     264 [-]: CALL R16 2 2 ; var16 = var16(var17)
L41: 265 [-]: JUMPIF R16 L42; goto L42 if var16
     266 [-]: NAMECALL R16 R15 K58; var17 = var15; var16 = var15[0xBB610E5B]
     267 [-]: CALL R16 2 2 ; var16 = var16(var17)
     268 [-]: NAMECALL R17 R16 K59; var18 = var16; var17 = var16[0xA2880940]
     269 [-]: CALL R17 2 1 ; var17(var18)
L42: 270 [-]: FORGLOOP R11 L40 2 [inext]; 
L43: 271 [-]: FORGLOOP R6 L39 2 [inext]; 
     272 [-]: LOADN R6 0   ; var6 = 0
     273 [-]: LOADN R9 1   ; var9 = 1
     274 [-]: LOADN R10 4  ; var10 = 4
     275 [-]: SUB R7 R10 R3; var7 = var10 - var3
     276 [-]: LOADN R8 1   ; var8 = 1
     277 [-]: FORNPREP R7 L45; nforprep start - [escape at L45] -- var7 = iterator
L44: 278 [-]: GETIMPORT R10 61; var10 = 0x55730E1A
     279 [-]: LOADN R11 90 ; var11 = 90
     280 [-]: LOADN R12 120; var12 = 120
     281 [-]: CALL R10 3 2 ; var10 = var10(var11, var12)
     282 [-]: ADD R6 R6 R10; var6 = var6 + var10
     283 [-]: FORNLOOP R7 L44; nforloop end - iterate + goto L44
L45: 284 [-]: GETUPVAL R7 7; var7 = upvalues[7]
     285 [-]: JUMPIFNOT R7 L46; goto L46 if not var7
     286 [-]: GETIMPORT R7 61; var7 = 0x55730E1A
     287 [-]: LOADN R8 180 ; var8 = 180
     288 [-]: LOADN R9 220 ; var9 = 220
     289 [-]: CALL R7 3 2  ; var7 = var7(var8, var9)
     290 [-]: ADD R6 R6 R7 ; var6 = var6 + var7
     291 [-]: GETUPVAL R8 11; var8 = upvalues[11]
     292 [-]: GETTABLEKS R7 R8 K42; var7 = var8[0x9742B85B]
     293 [-]: GETIMPORT R8 44; var8 = 0xE91D7466
     294 [-]: GETIMPORT R9 46; var9 = 0x0469F296
     295 [-]: LOADK R10 K62; var10 = "DKSSiphonDestroyedWormQueen"
     296 [-]: CALL R9 2 0  ; var9, ... = var9(var10)
     297 [-]: CALL R7 0 1  ; var7(var8, ...)
     298 [-]: GETUPVAL R8 11; var8 = upvalues[11]
     299 [-]: GETTABLEKS R7 R8 K42; var7 = var8[0x9742B85B]
     300 [-]: GETIMPORT R8 44; var8 = 0xE91D7466
     301 [-]: GETIMPORT R9 46; var9 = 0x0469F296
     302 [-]: LOADK R10 K63; var10 = "DKSSiphonDestroyedLotus"
     303 [-]: CALL R9 2 0  ; var9, ... = var9(var10)
     304 [-]: CALL R7 0 1  ; var7(var8, ...)
L46: 305 [-]: LOADN R7 0   ; var7 = 0
     306 [-]: JUMPIFNOTLT R7 R6 L50; goto L50 if var7 >= var1640526
     307 [-]: GETIMPORT R8 25; var8 = 0xBE190284
     308 [-]: NAMECALL R8 R8 K64; var9 = var8; var8 = var8[0xEF893AEC]
     309 [-]: CALL R8 2 2  ; var8 = var8(var9)
     310 [-]: GETTABLEKS R7 R8 K65; var7 = var8["minEnemyLevel"]
     311 [-]: LOADN R8 80  ; var8 = 80
     312 [-]: JUMPIFNOTLE R8 R7 L47; goto L47 if var8 > var1107691011
     313 [-]: MULK R6 R6 K66; var6 = var6 * 2
L47: 314 [-]: GETIMPORT R7 50; var7 = 0xC8802016
     315 [-]: GETUPVAL R8 17; var8 = upvalues[17]
     316 [-]: CALL R7 2 4  ; var7, var8, var9 = var7(var8)
     317 [-]: FORGPREP_INEXT R7 L49; 
L48: 318 [-]: NAMECALL R12 R11 K58; var13 = var11; var12 = var11[0xBB610E5B]
     319 [-]: CALL R12 2 2 ; var12 = var12(var13)
     320 [-]: NAMECALL R12 R12 K67; var13 = var12; var12 = var12[0xDE321E6F]
     321 [-]: CALL R12 2 2 ; var12 = var12(var13)
     322 [-]: GETUPVAL R14 18; var14 = upvalues[18]
     323 [-]: MOVE R15 R6  ; var15 = var6
     324 [-]: NAMECALL R12 R12 K68; var13 = var12; var12 = var12[0xEC017EFA]
     325 [-]: CALL R12 4 1 ; var12(var13, var14, var15)
L49: 326 [-]: FORGLOOP R7 L48 2 [inext]; 
L50: 327 [-]: GETIMPORT R7 5; var7 = 0x89326C93
     328 [-]: GETIMPORT R9 70; var9 = 0x7ED0A956
     329 [-]: LOADK R10 K71; var10 = "/Lotus/Types/Enemies/Grineer/GhostTower/GhostAvatar"
     330 [-]: CALL R9 2 0  ; var9, ... = var9(var10)
     331 [-]: NAMECALL R7 R7 K72; var8 = var7; var7 = var7[0xFB669000]
     332 [-]: CALL R7 0 2  ; var7 = var7(var8, ...)
     333 [-]: GETIMPORT R8 50; var8 = 0xC8802016
     334 [-]: MOVE R9 R7   ; var9 = var7
     335 [-]: CALL R8 2 4  ; var8, var9, var10 = var8(var9)
     336 [-]: FORGPREP_INEXT R8 L52; 
L51: 337 [-]: NAMECALL R13 R12 K59; var14 = var12; var13 = var12[0xA2880940]
     338 [-]: CALL R13 2 1 ; var13(var14)
L52: 339 [-]: FORGLOOP R8 L51 2 [inext]; 
     340 [-]: NAMECALL R8 R0 K73; var9 = var0; var8 = var0[0xF4E253B6]
     341 [-]: CALL R8 2 1  ; var8(var9)
     342 [-]: GETUPVAL R8 19; var8 = upvalues[19]
     343 [-]: JUMPXEQKNIL R8 L53; 
     344 [-]: GETUPVAL R8 0; var8 = upvalues[0]
     345 [-]: GETUPVAL R10 19; var10 = upvalues[19]
     346 [-]: NAMECALL R8 R8 K74; var9 = var8; var8 = var8[0x775C858B]
     347 [-]: CALL R8 3 1  ; var8(var9, var10)
L53: 348 [-]: GETIMPORT R8 22; var8 = _T
     349 [-]: LOADNIL R9   ; var9 = nil
     350 [-]: SETTABLEKS R9 R8 K23; var9["VoidTearProgress"] = var8
     351 [-]: GETUPVAL R8 2; var8 = upvalues[2]
     352 [-]: GETIMPORT R10 76; var10 = gTriggerType
     353 [-]: NAMECALL R8 R8 K77; var9 = var8; var8 = var8[0xC9F6A7D7]
     354 [-]: CALL R8 3 2  ; var8 = var8(var9, var10)
     355 [-]: NAMECALL R9 R8 K73; var10 = var8; var9 = var8[0xF4E253B6]
     356 [-]: CALL R9 2 1  ; var9(var10)
     357 [-]: GETUPVAL R10 2; var10 = upvalues[2]
     358 [-]: FASTCALL1 62 R10 L54; 
     359 [-]: GETIMPORT R9 13; var9 = 0x7B998233
     360 [-]: CALL R9 2 2  ; var9 = var9(var10)
L54: 361 [-]: JUMPIF R9 L55; goto L55 if var9
     362 [-]: GETIMPORT R9 15; var9 = 0xCBD666E1
     363 [-]: LOADN R10 3  ; var10 = 3
     364 [-]: CALL R9 2 1  ; var9(var10)
     365 [-]: GETIMPORT R9 5; var9 = 0x89326C93
     366 [-]: GETIMPORT R11 79; var11 = 0x66A5D072
     367 [-]: GETUPVAL R12 2; var12 = upvalues[2]
     368 [-]: NAMECALL R12 R12 K18; var13 = var12; var12 = var12[0xD1586535]
     369 [-]: CALL R12 2 2 ; var12 = var12(var13)
     370 [-]: GETIMPORT R13 81; var13 = ZERO_ROTATION
     371 [-]: NAMECALL R9 R9 K82; var10 = var9; var9 = var9[0x05909209]
     372 [-]: CALL R9 5 1  ; var9(var10, var11, var12, var13)
     373 [-]: GETUPVAL R9 2; var9 = upvalues[2]
     374 [-]: NAMECALL R9 R9 K59; var10 = var9; var9 = var9[0xA2880940]
     375 [-]: CALL R9 2 1  ; var9(var10)
L55: 376 [-]: RETURN R0 0  ; 


; Name:            
; Defined at line: 747
; #Upvalues:       3
; #Parameters:     0
; Is_vararg:       0
; Max Stack Size:  6

       0 [-]: GETIMPORT R0 1; var0 = 0x89326C93
       1 [-]: NAMECALL R0 R0 K2; var1 = var0; var0 = var0[0x7D108DDB]
       2 [-]: CALL R0 2 2  ; var0 = var0(var1)
       3 [-]: SETUPVAL R0 0; upvalues[0] = var0
       4 [-]: GETUPVAL R2 0; var2 = upvalues[0]
       5 [-]: LENGTH R1 R2 ; var1 = #var2
       6 [-]: ADDK R0 R1 K3; var0 = var1 + 1
       7 [-]: SETUPVAL R0 1; upvalues[0] = var1
       8 [-]: GETUPVAL R2 0; var2 = upvalues[0]
       9 [-]: LENGTH R1 R2 ; var1 = #var2
      10 [-]: LOADN R3 2   ; var3 = 2
      11 [-]: GETUPVAL R5 0; var5 = upvalues[0]
      12 [-]: LENGTH R4 R5 ; var4 = #var5
      13 [-]: MUL R2 R3 R4 ; var2 = var3 * var4
      14 [-]: ADD R0 R1 R2 ; var0 = var1 + var2
      15 [-]: SETUPVAL R0 2; upvalues[0] = var2
      16 [-]: RETURN R0 0  ; 


; Name:            
; Defined at line: 752
; #Upvalues:       0
; #Parameters:     1
; Is_vararg:       0
; Max Stack Size:  4

       0 [-]: GETIMPORT R2 2; var2 = _T["ToggleOperatorCallbacks"]
       1 [-]: FASTCALL1 62 R2 L0; 
       2 [-]: GETIMPORT R1 4; var1 = 0x7B998233
       3 [-]: CALL R1 2 2  ; var1 = var1(var2)
L 0:   4 [-]: JUMPIFNOT R1 L1; goto L1 if not var1
       5 [-]: GETIMPORT R1 5; var1 = _T
       6 [-]: NEWTABLE R2 0 0; var2 = {}
       7 [-]: SETTABLEKS R2 R1 K1; var2["ToggleOperatorCallbacks"] = var1
L 1:   8 [-]: GETIMPORT R2 2; var2 = _T["ToggleOperatorCallbacks"]
       9 [-]: FASTCALL2 52 R2 R0 L2; 
      10 [-]: MOVE R3 R0   ; var3 = var0
      11 [-]: GETIMPORT R1 8; var1 = 0x33BDD652[0x23D5322F]
      12 [-]: CALL R1 3 1  ; var1(var2, var3)
L 2:  13 [-]: RETURN R0 0  ; 


; Name:            
; Defined at line: 759
; #Upvalues:       0
; #Parameters:     1
; Is_vararg:       0
; Max Stack Size:  9

       0 [-]: GETIMPORT R1 1; var1 = 0xC8802016
       1 [-]: GETIMPORT R2 4; var2 = _T["ToggleOperatorCallbacks"]
       2 [-]: CALL R1 2 4  ; var1, var2, var3 = var1(var2)
       3 [-]: FORGPREP_INEXT R1 L1; 
L 0:   4 [-]: JUMPIFNOTEQ R5 R0 L1; goto L1 if var5 ~= var460366
       5 [-]: GETIMPORT R6 7; var6 = 0x33BDD652[0x9C1F3B5A]
       6 [-]: GETIMPORT R7 4; var7 = _T["ToggleOperatorCallbacks"]
       7 [-]: MOVE R8 R4   ; var8 = var4
       8 [-]: CALL R6 3 1  ; var6(var7, var8)
L 1:   9 [-]: FORGLOOP R1 L0 2 [inext]; 
      10 [-]: RETURN R0 0  ; 


; Name:            
; Defined at line: 767
; #Upvalues:       0
; #Parameters:     0
; Is_vararg:       0
; Max Stack Size:  9

       0 [-]: GETIMPORT R0 1; var0 = 0x89326C93
       1 [-]: NAMECALL R0 R0 K2; var1 = var0; var0 = var0[0x7D108DDB]
       2 [-]: CALL R0 2 2  ; var0 = var0(var1)
       3 [-]: GETIMPORT R1 4; var1 = 0xC8802016
       4 [-]: MOVE R2 R0   ; var2 = var0
       5 [-]: CALL R1 2 4  ; var1, var2, var3 = var1(var2)
       6 [-]: FORGPREP_INEXT R1 L1; 
L 0:   7 [-]: NAMECALL R6 R5 K5; var7 = var5; var6 = var5[0x62C81B76]
       8 [-]: CALL R6 2 2  ; var6 = var6(var7)
       9 [-]: NAMECALL R7 R6 K6; var8 = var6; var7 = var6[0x9094066E]
      10 [-]: CALL R7 2 2  ; var7 = var7(var8)
      11 [-]: JUMPIFNOT R7 L1; goto L1 if not var7
      12 [-]: LOADB R7 1   ; var7 = true
      13 [-]: RETURN R7 1  ; 
L 1:  14 [-]: FORGLOOP R1 L0 2 [inext]; 
      15 [-]: LOADB R1 0   ; var1 = false
      16 [-]: RETURN R1 1  ; 


; Name:            
; Defined at line: 779
; #Upvalues:       2
; #Parameters:     0
; Is_vararg:       0
; Max Stack Size:  1

       0 [-]: GETUPVAL R0 1; var0 = upvalues[1]
       1 [-]: CALL R0 1 2  ; var0 = var0()
       2 [-]: SETUPVAL R0 0; upvalues[0] = var0
       3 [-]: RETURN R0 0  ; 


; Name:            
; Defined at line: 784
; #Upvalues:       11
; #Parameters:     1
; Is_vararg:       0
; Max Stack Size:  26

       0 [-]: GETUPVAL R2 0; var2 = upvalues[0]
       1 [-]: GETTABLEKS R1 R2 K0; var1 = var2[0x6FB05708]
       2 [-]: CALL R1 1 1  ; var1()
       3 [-]: GETIMPORT R1 2; var1 = 0x89326C93
       4 [-]: NAMECALL R1 R1 K3; var2 = var1; var1 = var1[0x18D05D30]
       5 [-]: CALL R1 2 2  ; var1 = var1(var2)
       6 [-]: JUMPIFNOT R1 L4; goto L4 if not var1
       7 [-]: GETUPVAL R1 1; var1 = upvalues[1]
       8 [-]: NAMECALL R1 R1 K4; var2 = var1; var1 = var1[0xEF893AEC]
       9 [-]: CALL R1 2 2  ; var1 = var1(var2)
      10 [-]: GETIMPORT R2 6; var2 = 0x55730E1A
      11 [-]: GETTABLEKS R3 R1 K7; var3 = var1["minEnemyLevel"]
      12 [-]: GETTABLEKS R4 R1 K8; var4 = var1["maxEnemyLevel"]
      13 [-]: CALL R2 3 2  ; var2 = var2(var3, var4)
      14 [-]: GETIMPORT R3 2; var3 = 0x89326C93
      15 [-]: GETUPVAL R5 3; var5 = upvalues[3]
      16 [-]: NAMECALL R6 R0 K9; var7 = var0; var6 = var0[0xD1586535]
      17 [-]: CALL R6 2 2  ; var6 = var6(var7)
      18 [-]: LOADN R7 5   ; var7 = 5
      19 [-]: NAMECALL R3 R3 K10; var4 = var3; var3 = var3[0x4E5939A5]
      20 [-]: CALL R3 5 2  ; var3 = var3(var4, var5, var6, var7)
      21 [-]: SETUPVAL R3 2; upvalues[3] = var2
      22 [-]: GETIMPORT R3 12; var3 = 0xA421AF95
      23 [-]: CALL R3 1 2  ; var3 = var3()
      24 [-]: GETUPVAL R4 2; var4 = upvalues[2]
      25 [-]: NAMECALL R4 R4 K9; var5 = var4; var4 = var4[0xD1586535]
      26 [-]: CALL R4 2 2  ; var4 = var4(var5)
      27 [-]: GETIMPORT R5 2; var5 = 0x89326C93
      28 [-]: GETUPVAL R8 2; var8 = upvalues[2]
      29 [-]: NAMECALL R8 R8 K9; var9 = var8; var8 = var8[0xD1586535]
      30 [-]: CALL R8 2 2  ; var8 = var8(var9)
      31 [-]: GETIMPORT R9 12; var9 = 0xA421AF95
      32 [-]: LOADN R10 0  ; var10 = 0
      33 [-]: LOADK R11 K13; var11 = 0.5
      34 [-]: LOADN R12 0  ; var12 = 0
      35 [-]: CALL R9 4 2  ; var9 = var9(var10, var11, var12)
      36 [-]: ADD R7 R8 R9 ; var7 = var8 + var9
      37 [-]: GETUPVAL R9 2; var9 = upvalues[2]
      38 [-]: NAMECALL R9 R9 K9; var10 = var9; var9 = var9[0xD1586535]
      39 [-]: CALL R9 2 2  ; var9 = var9(var10)
      40 [-]: GETIMPORT R10 12; var10 = 0xA421AF95
      41 [-]: LOADN R11 0  ; var11 = 0
      42 [-]: LOADN R12 5  ; var12 = 5
      43 [-]: LOADN R13 0  ; var13 = 0
      44 [-]: CALL R10 4 2 ; var10 = var10(var11, var12, var13)
      45 [-]: SUB R8 R9 R10; var8 = var9 - var10
      46 [-]: LOADNIL R9   ; var9 = nil
      47 [-]: LOADNIL R10  ; var10 = nil
      48 [-]: MOVE R11 R3  ; var11 = var3
      49 [-]: LOADB R12 1  ; var12 = true
      50 [-]: NAMECALL R5 R5 K14; var6 = var5; var5 = var5[0xBD5D0EC1]
      51 [-]: CALL R5 8 2  ; var5 = var5(var6, var7, var8, var9, var10, var11, var12)
      52 [-]: JUMPIFNOT R5 L0; goto L0 if not var5
      53 [-]: GETIMPORT R5 12; var5 = 0xA421AF95
      54 [-]: LOADN R6 0   ; var6 = 0
      55 [-]: LOADK R7 K13 ; var7 = 0.5
      56 [-]: LOADN R8 0   ; var8 = 0
      57 [-]: CALL R5 4 2  ; var5 = var5(var6, var7, var8)
      58 [-]: ADD R4 R3 R5 ; var4 = var3 + var5
L 0:  59 [-]: GETIMPORT R5 2; var5 = 0x89326C93
      60 [-]: NAMECALL R5 R5 K15; var6 = var5; var5 = var5[0x29EF273D]
      61 [-]: CALL R5 2 2  ; var5 = var5(var6)
      62 [-]: GETIMPORT R7 17; var7 = 0x54E54E2F
      63 [-]: MOVE R8 R4   ; var8 = var4
      64 [-]: GETUPVAL R9 2; var9 = upvalues[2]
      65 [-]: NAMECALL R9 R9 K18; var10 = var9; var9 = var9[0xCB3851B8]
      66 [-]: CALL R9 2 2  ; var9 = var9(var10)
      67 [-]: GETIMPORT R10 20; var10 = 0x0469F296
      68 [-]: CALL R10 1 2 ; var10 = var10()
      69 [-]: MOVE R11 R2  ; var11 = var2
      70 [-]: NAMECALL R5 R5 K21; var6 = var5; var5 = var5[0x6CD833C5]
      71 [-]: CALL R5 7 2  ; var5 = var5(var6, var7, var8, var9, var10, var11)
      72 [-]: SETUPVAL R5 4; upvalues[5] = var4
      73 [-]: GETUPVAL R6 4; var6 = upvalues[4]
      74 [-]: FASTCALL1 62 R6 L1; 
      75 [-]: GETIMPORT R5 23; var5 = 0x7B998233
      76 [-]: CALL R5 2 2  ; var5 = var5(var6)
L 1:  77 [-]: JUMPIFNOT R5 L2; goto L2 if not var5
      78 [-]: GETIMPORT R5 25; var5 = 0x3D106989
      79 [-]: LOADK R6 K26 ; var6 = "GhostTower.lua::GhostTower - Failed to create ghost tower agent"
      80 [-]: CALL R5 2 1  ; var5(var6)
      81 [-]: RETURN R0 0  ; 
L 2:  82 [-]: GETUPVAL R5 4; var5 = upvalues[4]
      83 [-]: NAMECALL R5 R5 K27; var6 = var5; var5 = var5[0xBB610E5B]
      84 [-]: CALL R5 2 2  ; var5 = var5(var6)
      85 [-]: SETUPVAL R5 5; upvalues[5] = var5
      86 [-]: GETIMPORT R6 30; var6 = _T["UseAiDirectorPopulationSpawnCount"]
      87 [-]: FASTCALL1 62 R6 L3; 
      88 [-]: GETIMPORT R5 23; var5 = 0x7B998233
      89 [-]: CALL R5 2 2  ; var5 = var5(var6)
L 3:  90 [-]: JUMPIF R5 L4 ; goto L4 if var5
      91 [-]: GETIMPORT R5 30; var5 = _T["UseAiDirectorPopulationSpawnCount"]
      92 [-]: JUMPIFNOT R5 L4; goto L4 if not var5
      93 [-]: GETUPVAL R5 6; var5 = upvalues[6]
      94 [-]: LOADN R7 1   ; var7 = 1
      95 [-]: NAMECALL R5 R5 K31; var6 = var5; var5 = var5[0xF2D6020E]
      96 [-]: CALL R5 3 1  ; var5(var6, var7)
L 4:  97 [-]: GETIMPORT R1 2; var1 = 0x89326C93
      98 [-]: LOADK R3 K32 ; var3 = "OnPlayersChangedSiphonTrigger"
      99 [-]: NAMECALL R1 R1 K33; var2 = var1; var1 = var1[0xB7D33840]
     100 [-]: CALL R1 3 1  ; var1(var2, var3)
     101 [-]: GETUPVAL R1 8; var1 = upvalues[8]
     102 [-]: CALL R1 1 2  ; var1 = var1()
     103 [-]: SETUPVAL R1 7; upvalues[1] = var7
     104 [-]: LOADNIL R1   ; var1 = nil
L 5: 105 [-]: NAMECALL R3 R0 K34; var4 = var0; var3 = var0[0xE79E7EF4]
     106 [-]: CALL R3 2 2  ; var3 = var3(var4)
     107 [-]: FASTCALL1 62 R3 L6; 
     108 [-]: GETIMPORT R2 23; var2 = 0x7B998233
     109 [-]: CALL R2 2 2  ; var2 = var2(var3)
L 6: 110 [-]: JUMPIFNOT R2 L7; goto L7 if not var2
     111 [-]: GETIMPORT R2 36; var2 = 0xCBD666E1
     112 [-]: LOADN R3 0   ; var3 = 0
     113 [-]: CALL R2 2 1  ; var2(var3)
     114 [-]: JUMPBACK L5  ; goto L5
L 7: 115 [-]: NAMECALL R2 R0 K34; var3 = var0; var2 = var0[0xE79E7EF4]
     116 [-]: CALL R2 2 2  ; var2 = var2(var3)
     117 [-]: MOVE R1 R2   ; var1 = var2
L 8: 118 [-]: GETUPVAL R3 5; var3 = upvalues[5]
     119 [-]: FASTCALL1 62 R3 L9; 
     120 [-]: GETIMPORT R2 23; var2 = 0x7B998233
     121 [-]: CALL R2 2 2  ; var2 = var2(var3)
L 9: 122 [-]: JUMPIFNOT R2 L10; goto L10 if not var2
     123 [-]: GETIMPORT R2 36; var2 = 0xCBD666E1
     124 [-]: LOADN R3 0   ; var3 = 0
     125 [-]: CALL R2 2 1  ; var2(var3)
     126 [-]: GETIMPORT R2 2; var2 = 0x89326C93
     127 [-]: GETIMPORT R4 38; var4 = gVoidNegationTowerAvatarType
     128 [-]: NAMECALL R5 R0 K9; var6 = var0; var5 = var0[0xD1586535]
     129 [-]: CALL R5 2 2  ; var5 = var5(var6)
     130 [-]: LOADK R6 K39 ; var6 = 3.4028234663852886e+38
     131 [-]: NAMECALL R2 R2 K10; var3 = var2; var2 = var2[0x4E5939A5]
     132 [-]: CALL R2 5 2  ; var2 = var2(var3, var4, var5, var6)
     133 [-]: SETUPVAL R2 5; upvalues[2] = var5
     134 [-]: JUMPBACK L8  ; goto L8
L10: 135 [-]: GETUPVAL R2 5; var2 = upvalues[5]
     136 [-]: GETIMPORT R4 41; var4 = gBaseMarkerInfoType
     137 [-]: NAMECALL R2 R2 K42; var3 = var2; var2 = var2[0xC9F6A7D7]
     138 [-]: CALL R2 3 2  ; var2 = var2(var3, var4)
     139 [-]: LOADNIL R3   ; var3 = nil
     140 [-]: LOADB R4 0   ; var4 = false
     141 [-]: NEWCLOSURE R5 P0; 
     142 [-]: CAPTURE REF R4; 
     143 [-]: CAPTURE UPVAL U9; 
     144 [-]: GETIMPORT R7 44; var7 = _T["ToggleOperatorCallbacks"]
     145 [-]: FASTCALL1 62 R7 L11; 
     146 [-]: GETIMPORT R6 23; var6 = 0x7B998233
     147 [-]: CALL R6 2 2  ; var6 = var6(var7)
L11: 148 [-]: JUMPIFNOT R6 L12; goto L12 if not var6
     149 [-]: GETIMPORT R6 45; var6 = _T
     150 [-]: NEWTABLE R7 0 0; var7 = {}
     151 [-]: SETTABLEKS R7 R6 K43; var7["ToggleOperatorCallbacks"] = var6
L12: 152 [-]: GETIMPORT R7 44; var7 = _T["ToggleOperatorCallbacks"]
     153 [-]: FASTCALL2 52 R7 R5 L13; 
     154 [-]: MOVE R8 R5   ; var8 = var5
     155 [-]: GETIMPORT R6 48; var6 = 0x33BDD652[0x23D5322F]
     156 [-]: CALL R6 3 1  ; var6(var7, var8)
L13: 157 [-]: NAMECALL R6 R0 K49; var7 = var0; var6 = var0[0xF37943FF]
     158 [-]: CALL R6 2 2  ; var6 = var6(var7)
     159 [-]: JUMPIFNOT R6 L43; goto L43 if not var6
     160 [-]: NEWTABLE R6 0 0; var6 = {}
     161 [-]: GETIMPORT R7 2; var7 = 0x89326C93
     162 [-]: NAMECALL R7 R7 K3; var8 = var7; var7 = var7[0x18D05D30]
     163 [-]: CALL R7 2 2  ; var7 = var7(var8)
     164 [-]: JUMPIFNOT R7 L17; goto L17 if not var7
     165 [-]: GETUPVAL R7 7; var7 = upvalues[7]
     166 [-]: JUMPIFNOT R7 L17; goto L17 if not var7
     167 [-]: GETIMPORT R7 2; var7 = 0x89326C93
     168 [-]: NAMECALL R7 R7 K50; var8 = var7; var7 = var7[0x8B5B1F58]
     169 [-]: CALL R7 2 2  ; var7 = var7(var8)
     170 [-]: MOVE R6 R7   ; var6 = var7
     171 [-]: FASTCALL1 62 R6 L14; 
     172 [-]: MOVE R8 R6   ; var8 = var6
     173 [-]: GETIMPORT R7 23; var7 = 0x7B998233
     174 [-]: CALL R7 2 2  ; var7 = var7(var8)
L14: 175 [-]: JUMPIF R7 L15; goto L15 if var7
     176 [-]: LENGTH R7 R6 ; var7 = #var6
     177 [-]: JUMPXEQKN R7 K51 L18 NOT; 
L15: 178 [-]: NEWTABLE R6 0 0; var6 = {}
     179 [-]: MOVE R8 R6   ; var8 = var6
     180 [-]: GETIMPORT R9 2; var9 = 0x89326C93
     181 [-]: NAMECALL R9 R9 K52; var10 = var9; var9 = var9[0x78298275]
     182 [-]: CALL R9 2 0  ; var9, ... = var9(var10)
     183 [-]: FASTCALL 52 L16; 
     184 [-]: GETIMPORT R7 48; var7 = 0x33BDD652[0x23D5322F]
     185 [-]: CALL R7 0 1  ; var7(var8, ...)
L16: 186 [-]: JUMP L18     ; goto L18
L17: 187 [-]: MOVE R8 R6   ; var8 = var6
     188 [-]: GETIMPORT R9 2; var9 = 0x89326C93
     189 [-]: NAMECALL R9 R9 K52; var10 = var9; var9 = var9[0x78298275]
     190 [-]: CALL R9 2 0  ; var9, ... = var9(var10)
     191 [-]: FASTCALL 52 L18; 
     192 [-]: GETIMPORT R7 48; var7 = 0x33BDD652[0x23D5322F]
     193 [-]: CALL R7 0 1  ; var7(var8, ...)
L18: 194 [-]: GETIMPORT R7 2; var7 = 0x89326C93
     195 [-]: NAMECALL R7 R7 K52; var8 = var7; var7 = var7[0x78298275]
     196 [-]: CALL R7 2 2  ; var7 = var7(var8)
     197 [-]: LOADN R10 1  ; var10 = 1
     198 [-]: LENGTH R8 R6 ; var8 = #var6
     199 [-]: LOADN R9 1   ; var9 = 1
     200 [-]: FORNPREP R8 L42; nforprep start - [escape at L42] -- var8 = iterator
L19: 201 [-]: GETTABLE R3 R6 R10; var3 = var6[var10]
     202 [-]: FASTCALL1 62 R3 L20; 
     203 [-]: MOVE R12 R3  ; var12 = var3
     204 [-]: GETIMPORT R11 23; var11 = 0x7B998233
     205 [-]: CALL R11 2 2 ; var11 = var11(var12)
L20: 206 [-]: JUMPIF R11 L38; goto L38 if var11
     207 [-]: NAMECALL R11 R3 K53; var12 = var3; var11 = var3[0x2047CFE7]
     208 [-]: CALL R11 2 2 ; var11 = var11(var12)
     209 [-]: JUMPIF R11 L38; goto L38 if var11
     210 [-]: NAMECALL R12 R3 K34; var13 = var3; var12 = var3[0xE79E7EF4]
     211 [-]: CALL R12 2 2 ; var12 = var12(var13)
     212 [-]: FASTCALL1 62 R12 L21; 
     213 [-]: GETIMPORT R11 23; var11 = 0x7B998233
     214 [-]: CALL R11 2 2 ; var11 = var11(var12)
L21: 215 [-]: JUMPIF R11 L38; goto L38 if var11
     216 [-]: FASTCALL1 62 R7 L22; 
     217 [-]: MOVE R12 R7  ; var12 = var7
     218 [-]: GETIMPORT R11 23; var11 = 0x7B998233
     219 [-]: CALL R11 2 2 ; var11 = var11(var12)
L22: 220 [-]: JUMPIF R11 L38; goto L38 if var11
     221 [-]: NAMECALL R11 R3 K34; var12 = var3; var11 = var3[0xE79E7EF4]
     222 [-]: CALL R11 2 2 ; var11 = var11(var12)
     223 [-]: GETIMPORT R12 2; var12 = 0x89326C93
     224 [-]: MOVE R14 R1  ; var14 = var1
     225 [-]: MOVE R15 R11 ; var15 = var11
     226 [-]: NAMECALL R12 R12 K54; var13 = var12; var12 = var12[0xF8F0A754]
     227 [-]: CALL R12 4 2 ; var12 = var12(var13, var14, var15)
     228 [-]: LOADB R13 0  ; var13 = false
     229 [-]: LENGTH R14 R12; var14 = #var12
     230 [-]: JUMPXEQKN R14 K51 L24 NOT; 
     231 [-]: NAMECALL R14 R3 K34; var15 = var3; var14 = var3[0xE79E7EF4]
     232 [-]: CALL R14 2 2 ; var14 = var14(var15)
     233 [-]: JUMPIFNOTEQ R14 R1 L23; goto L23 if var14 ~= var16780571
     234 [-]: LOADB R13 0 +1; var13 = false
L23: 235 [-]: LOADB R13 1  ; var13 = true
L24: 236 [-]: LOADNIL R14  ; var14 = nil
     237 [-]: NEWTABLE R15 0 0; var15 = {}
     238 [-]: FASTCALL1 62 R12 L25; 
     239 [-]: MOVE R17 R12 ; var17 = var12
     240 [-]: GETIMPORT R16 23; var16 = 0x7B998233
     241 [-]: CALL R16 2 2 ; var16 = var16(var17)
L25: 242 [-]: JUMPIF R16 L28; goto L28 if var16
     243 [-]: GETIMPORT R16 56; var16 = 0xC8802016
     244 [-]: MOVE R17 R12 ; var17 = var12
     245 [-]: CALL R16 2 4 ; var16, var17, var18 = var16(var17)
     246 [-]: FORGPREP_INEXT R16 L27; 
L26: 247 [-]: NAMECALL R22 R20 K58; var23 = var20; var22 = var20[0x9435EB6D]
     248 [-]: CALL R22 2 2 ; var22 = var22(var23)
     249 [-]: SUBK R21 R22 K57; var21 = var22 - 1
     250 [-]: JUMPIFEQ R14 R21 L27; goto L27 if var14 == var1830032709
     251 [-]: NAMECALL R21 R20 K58; var22 = var20; var21 = var20[0x9435EB6D]
     252 [-]: CALL R21 2 2 ; var21 = var21(var22)
     253 [-]: SUBK R14 R21 K57; var14 = var21 - 1
     254 [-]: NAMECALL R24 R20 K58; var25 = var20; var24 = var20[0x9435EB6D]
     255 [-]: CALL R24 2 2 ; var24 = var24(var25)
     256 [-]: SUBK R23 R24 K57; var23 = var24 - 1
     257 [-]: FASTCALL2 52 R15 R23 L27; 
     258 [-]: MOVE R22 R15 ; var22 = var15
     259 [-]: GETIMPORT R21 48; var21 = 0x33BDD652[0x23D5322F]
     260 [-]: CALL R21 3 1 ; var21(var22, var23)
L27: 261 [-]: FORGLOOP R16 L26 2 [inext]; 
L28: 262 [-]: LOADB R16 0  ; var16 = false
     263 [-]: LENGTH R17 R15; var17 = #var15
     264 [-]: LOADN R18 3  ; var18 = 3
     265 [-]: JUMPIFNOTLT R17 R18 L29; goto L29 if var17 >= var856088
     266 [-]: NOT R16 R13  ; var16 = not var13
L29: 267 [-]: JUMPIFNOT R16 L37; goto L37 if not var16
     268 [-]: JUMPIF R4 L30; goto L30 if var4
     269 [-]: JUMPIFNOTEQ R7 R3 L30; goto L30 if var7 ~= var66587
     270 [-]: LOADB R4 1   ; var4 = true
     271 [-]: GETUPVAL R17 9; var17 = upvalues[9]
     272 [-]: LOADB R18 1  ; var18 = true
     273 [-]: MOVE R19 R3  ; var19 = var3
     274 [-]: CALL R17 3 1 ; var17(var18, var19)
L30: 275 [-]: GETIMPORT R17 2; var17 = 0x89326C93
     276 [-]: NAMECALL R17 R17 K3; var18 = var17; var17 = var17[0x18D05D30]
     277 [-]: CALL R17 2 2 ; var17 = var17(var18)
     278 [-]: JUMPIF R17 L31; goto L31 if var17
     279 [-]: GETIMPORT R17 60; var17 = 0x14459A1C
     280 [-]: JUMPIFNOT R17 L41; goto L41 if not var17
L31: 281 [-]: LENGTH R17 R15; var17 = #var15
     282 [-]: LOADN R18 1  ; var18 = 1
     283 [-]: JUMPIFNOTLE R17 R18 L41; goto L41 if var17 > var-1627385531
     284 [-]: NAMECALL R17 R0 K61; var18 = var0; var17 = var0[0x53C3399F]
     285 [-]: CALL R17 2 2 ; var17 = var17(var18)
     286 [-]: JUMPXEQKN R17 K57 L41; 
     287 [-]: GETUPVAL R17 7; var17 = upvalues[7]
     288 [-]: JUMPIFNOT R17 L41; goto L41 if not var17
     289 [-]: LOADB R17 0  ; var17 = false
     290 [-]: SETUPVAL R17 7; upvalues[17] = var7
     291 [-]: LOADK R19 K62; var19 = "Execute"
     292 [-]: NAMECALL R17 R0 K63; var18 = var0; var17 = var0[0x8EB2112D]
     293 [-]: CALL R17 3 1 ; var17(var18, var19)
     294 [-]: FASTCALL1 62 R2 L32; 
     295 [-]: MOVE R18 R2  ; var18 = var2
     296 [-]: GETIMPORT R17 23; var17 = 0x7B998233
     297 [-]: CALL R17 2 2 ; var17 = var17(var18)
L32: 298 [-]: JUMPIFNOT R17 L36; goto L36 if not var17
L33: 299 [-]: GETUPVAL R18 5; var18 = upvalues[5]
     300 [-]: FASTCALL1 62 R18 L34; 
     301 [-]: GETIMPORT R17 23; var17 = 0x7B998233
     302 [-]: CALL R17 2 2 ; var17 = var17(var18)
L34: 303 [-]: JUMPIFNOT R17 L35; goto L35 if not var17
     304 [-]: GETIMPORT R17 36; var17 = 0xCBD666E1
     305 [-]: LOADN R18 0  ; var18 = 0
     306 [-]: CALL R17 2 1 ; var17(var18)
     307 [-]: GETIMPORT R17 2; var17 = 0x89326C93
     308 [-]: GETIMPORT R19 38; var19 = gVoidNegationTowerAvatarType
     309 [-]: NAMECALL R20 R0 K9; var21 = var0; var20 = var0[0xD1586535]
     310 [-]: CALL R20 2 2 ; var20 = var20(var21)
     311 [-]: LOADK R21 K39; var21 = 3.4028234663852886e+38
     312 [-]: NAMECALL R17 R17 K10; var18 = var17; var17 = var17[0x4E5939A5]
     313 [-]: CALL R17 5 2 ; var17 = var17(var18, var19, var20, var21)
     314 [-]: SETUPVAL R17 5; upvalues[17] = var5
     315 [-]: JUMPBACK L33 ; goto L33
L35: 316 [-]: GETUPVAL R17 5; var17 = upvalues[5]
     317 [-]: GETIMPORT R19 41; var19 = gBaseMarkerInfoType
     318 [-]: NAMECALL R17 R17 K42; var18 = var17; var17 = var17[0xC9F6A7D7]
     319 [-]: CALL R17 3 2 ; var17 = var17(var18, var19)
     320 [-]: MOVE R2 R17  ; var2 = var17
L36: 321 [-]: NAMECALL R17 R2 K49; var18 = var2; var17 = var2[0xF37943FF]
     322 [-]: CALL R17 2 2 ; var17 = var17(var18)
     323 [-]: JUMPIF R17 L41; goto L41 if var17
     324 [-]: NAMECALL R17 R2 K64; var18 = var2; var17 = var2[0x383D2E7D]
     325 [-]: CALL R17 2 1 ; var17(var18)
     326 [-]: JUMP L41     ; goto L41
L37: 327 [-]: JUMPIFNOT R4 L41; goto L41 if not var4
     328 [-]: JUMPIFNOTEQ R7 R3 L41; goto L41 if var7 ~= var594183
     329 [-]: GETUPVAL R17 9; var17 = upvalues[9]
     330 [-]: LOADB R18 0  ; var18 = false
     331 [-]: MOVE R19 R3  ; var19 = var3
     332 [-]: CALL R17 3 1 ; var17(var18, var19)
     333 [-]: LOADB R4 0   ; var4 = false
     334 [-]: JUMP L41     ; goto L41
L38: 335 [-]: FASTCALL1 62 R3 L39; 
     336 [-]: MOVE R12 R3  ; var12 = var3
     337 [-]: GETIMPORT R11 23; var11 = 0x7B998233
     338 [-]: CALL R11 2 2 ; var11 = var11(var12)
L39: 339 [-]: JUMPIF R11 L40; goto L40 if var11
     340 [-]: NAMECALL R11 R3 K53; var12 = var3; var11 = var3[0x2047CFE7]
     341 [-]: CALL R11 2 2 ; var11 = var11(var12)
     342 [-]: JUMPIFNOT R11 L41; goto L41 if not var11
L40: 343 [-]: JUMPIFNOTEQ R7 R3 L41; goto L41 if var7 ~= var1051
     344 [-]: LOADB R4 0   ; var4 = false
L41: 345 [-]: FORNLOOP R8 L19; nforloop end - iterate + goto L19
L42: 346 [-]: GETIMPORT R8 36; var8 = 0xCBD666E1
     347 [-]: LOADN R9 1   ; var9 = 1
     348 [-]: CALL R8 2 1  ; var8(var9)
     349 [-]: JUMPBACK L13 ; goto L13
L43: 350 [-]: GETUPVAL R6 10; var6 = upvalues[10]
     351 [-]: MOVE R7 R5   ; var7 = var5
     352 [-]: CALL R6 2 1  ; var6(var7)
     353 [-]: GETUPVAL R6 9; var6 = upvalues[9]
     354 [-]: LOADB R7 0   ; var7 = false
     355 [-]: GETIMPORT R8 2; var8 = 0x89326C93
     356 [-]: NAMECALL R8 R8 K52; var9 = var8; var8 = var8[0x78298275]
     357 [-]: CALL R8 2 0  ; var8, ... = var8(var9)
     358 [-]: CALL R6 0 1  ; var6(var7, ...)
     359 [-]: GETIMPORT R6 2; var6 = 0x89326C93
     360 [-]: NAMECALL R6 R6 K3; var7 = var6; var6 = var6[0x18D05D30]
     361 [-]: CALL R6 2 2  ; var6 = var6(var7)
     362 [-]: JUMPIFNOT R6 L45; goto L45 if not var6
     363 [-]: FASTCALL1 62 R2 L44; 
     364 [-]: MOVE R7 R2   ; var7 = var2
     365 [-]: GETIMPORT R6 23; var6 = 0x7B998233
     366 [-]: CALL R6 2 2  ; var6 = var6(var7)
L44: 367 [-]: JUMPIF R6 L45; goto L45 if var6
     368 [-]: NAMECALL R6 R2 K65; var7 = var2; var6 = var2[0xF4E253B6]
     369 [-]: CALL R6 2 1  ; var6(var7)
L45: 370 [-]: CLOSEUPVALS R4; 
     371 [-]: RETURN R0 0  ; 


; Name:            
; Defined at line: 916
; #Upvalues:       2
; #Parameters:     1
; Is_vararg:       0
; Max Stack Size:  4

       0 [-]: GETUPVAL R2 0; var2 = upvalues[0]
       1 [-]: FASTCALL1 62 R2 L0; 
       2 [-]: GETIMPORT R1 1; var1 = 0x7B998233
       3 [-]: CALL R1 2 2  ; var1 = var1(var2)
L 0:   4 [-]: JUMPIF R1 L1 ; goto L1 if var1
       5 [-]: GETUPVAL R1 0; var1 = upvalues[0]
       6 [-]: NAMECALL R1 R1 K2; var2 = var1; var1 = var1[0x2047CFE7]
       7 [-]: CALL R1 2 2  ; var1 = var1(var2)
       8 [-]: JUMPIFNOT R1 L2; goto L2 if not var1
L 1:   9 [-]: RETURN R0 0  ; 
L 2:  10 [-]: GETUPVAL R3 0; var3 = upvalues[0]
      11 [-]: NAMECALL R1 R0 K3; var2 = var0; var1 = var0[0x13D5D3FB]
      12 [-]: CALL R1 3 2  ; var1 = var1(var2, var3)
      13 [-]: JUMPIFNOT R1 L3; goto L3 if not var1
      14 [-]: LOADB R1 1   ; var1 = true
      15 [-]: SETUPVAL R1 1; upvalues[1] = var1
L 3:  16 [-]: RETURN R0 0  ; 


; Name:            
; Defined at line: 926
; #Upvalues:       2
; #Parameters:     1
; Is_vararg:       0
; Max Stack Size:  4

       0 [-]: GETUPVAL R2 0; var2 = upvalues[0]
       1 [-]: FASTCALL1 62 R2 L0; 
       2 [-]: GETIMPORT R1 1; var1 = 0x7B998233
       3 [-]: CALL R1 2 2  ; var1 = var1(var2)
L 0:   4 [-]: JUMPIF R1 L1 ; goto L1 if var1
       5 [-]: GETUPVAL R1 0; var1 = upvalues[0]
       6 [-]: NAMECALL R1 R1 K2; var2 = var1; var1 = var1[0x2047CFE7]
       7 [-]: CALL R1 2 2  ; var1 = var1(var2)
       8 [-]: JUMPIFNOT R1 L2; goto L2 if not var1
L 1:   9 [-]: RETURN R0 0  ; 
L 2:  10 [-]: GETUPVAL R3 0; var3 = upvalues[0]
      11 [-]: NAMECALL R1 R0 K3; var2 = var0; var1 = var0[0x13D5D3FB]
      12 [-]: CALL R1 3 2  ; var1 = var1(var2, var3)
      13 [-]: JUMPIF R1 L3 ; goto L3 if var1
      14 [-]: LOADB R1 0   ; var1 = false
      15 [-]: SETUPVAL R1 1; upvalues[1] = var1
L 3:  16 [-]: RETURN R0 0  ; 


; Name:            
; Defined at line: 936
; #Upvalues:       3
; #Parameters:     1
; Is_vararg:       0
; Max Stack Size:  11

       0 [-]: GETIMPORT R1 1; var1 = 0xCBD666E1
       1 [-]: LOADN R2 2   ; var2 = 2
       2 [-]: CALL R1 2 1  ; var1(var2)
       3 [-]: GETUPVAL R2 0; var2 = upvalues[0]
       4 [-]: GETTABLEKS R1 R2 K2; var1 = var2[0x52FB05B3]
       5 [-]: GETIMPORT R2 4; var2 = 0x7ED0A956
       6 [-]: LOADK R3 K5  ; var3 = "/Lotus/Types/Keys/WarWithinQuest/WarWithinQuestKeyChain"
       7 [-]: CALL R2 2 0  ; var2, ... = var2(var3)
       8 [-]: CALL R1 0 2  ; var1 = var1(var2, ...)
       9 [-]: JUMPIF R1 L0 ; goto L0 if var1
      10 [-]: RETURN R0 0  ; 
L 0:  11 [-]: GETIMPORT R1 7; var1 = 0x11A19C5E
      12 [-]: MOVE R2 R0   ; var2 = var0
      13 [-]: LOADK R3 K8  ; var3 = "OnTouched"
      14 [-]: CALL R1 3 1  ; var1(var2, var3)
      15 [-]: GETIMPORT R1 7; var1 = 0x11A19C5E
      16 [-]: MOVE R2 R0   ; var2 = var0
      17 [-]: LOADK R3 K9  ; var3 = "OnUntouched"
      18 [-]: CALL R1 3 1  ; var1(var2, var3)
      19 [-]: LOADB R1 0   ; var1 = false
      20 [-]: GETIMPORT R2 11; var2 = 0x89326C93
      21 [-]: NAMECALL R2 R2 K12; var3 = var2; var2 = var2[0x78298275]
      22 [-]: CALL R2 2 2  ; var2 = var2(var3)
      23 [-]: SETUPVAL R2 1; upvalues[2] = var1
      24 [-]: DUPCLOSURE R2 K13; 
L 1:  25 [-]: FASTCALL1 62 R0 L2; 
      26 [-]: MOVE R4 R0   ; var4 = var0
      27 [-]: GETIMPORT R3 15; var3 = 0x7B998233
      28 [-]: CALL R3 2 2  ; var3 = var3(var4)
L 2:  29 [-]: JUMPIF R3 L10; goto L10 if var3
      30 [-]: NAMECALL R3 R0 K16; var4 = var0; var3 = var0[0xF37943FF]
      31 [-]: CALL R3 2 2  ; var3 = var3(var4)
      32 [-]: JUMPIFNOT R3 L10; goto L10 if not var3
      33 [-]: GETUPVAL R4 1; var4 = upvalues[1]
      34 [-]: FASTCALL1 62 R4 L3; 
      35 [-]: GETIMPORT R3 15; var3 = 0x7B998233
      36 [-]: CALL R3 2 2  ; var3 = var3(var4)
L 3:  37 [-]: JUMPIF R3 L4 ; goto L4 if var3
      38 [-]: GETUPVAL R3 1; var3 = upvalues[1]
      39 [-]: NAMECALL R3 R3 K17; var4 = var3; var3 = var3[0x2047CFE7]
      40 [-]: CALL R3 2 2  ; var3 = var3(var4)
      41 [-]: JUMPIFNOT R3 L5; goto L5 if not var3
L 4:  42 [-]: GETIMPORT R3 11; var3 = 0x89326C93
      43 [-]: NAMECALL R3 R3 K12; var4 = var3; var3 = var3[0x78298275]
      44 [-]: CALL R3 2 2  ; var3 = var3(var4)
      45 [-]: SETUPVAL R3 1; upvalues[3] = var1
      46 [-]: JUMP L9      ; goto L9
L 5:  47 [-]: GETUPVAL R3 2; var3 = upvalues[2]
      48 [-]: JUMPIFNOT R3 L6; goto L6 if not var3
      49 [-]: JUMPIF R1 L6 ; goto L6 if var1
      50 [-]: GETIMPORT R3 20; var3 = _T["ShowImpactMessage"]
      51 [-]: MOVE R4 R2   ; var4 = var2
      52 [-]: LOADN R5 -1  ; var5 = -1
      53 [-]: LOADB R6 1   ; var6 = true
      54 [-]: LOADNIL R7   ; var7 = nil
      55 [-]: LOADB R8 0   ; var8 = false
      56 [-]: LOADNIL R9   ; var9 = nil
      57 [-]: LOADN R10 3  ; var10 = 3
      58 [-]: CALL R3 8 1  ; var3(var4, var5, var6, var7, var8, var9, var10)
      59 [-]: LOADB R1 1   ; var1 = true
      60 [-]: JUMP L7      ; goto L7
L 6:  61 [-]: GETUPVAL R3 2; var3 = upvalues[2]
      62 [-]: JUMPIF R3 L7 ; goto L7 if var3
      63 [-]: JUMPIFNOT R1 L7; goto L7 if not var1
      64 [-]: GETIMPORT R3 22; var3 = _T["HideImpactMessage"]
      65 [-]: CALL R3 1 1  ; var3()
      66 [-]: LOADB R1 0   ; var1 = false
L 7:  67 [-]: JUMPIFNOT R1 L9; goto L9 if not var1
      68 [-]: GETUPVAL R3 1; var3 = upvalues[1]
      69 [-]: GETIMPORT R5 4; var5 = 0x7ED0A956
      70 [-]: LOADK R6 K23 ; var6 = "/Lotus/Types/Friendly/Tenno/OperatorAvatar"
      71 [-]: CALL R5 2 0  ; var5, ... = var5(var6)
      72 [-]: NAMECALL R3 R3 K24; var4 = var3; var3 = var3[0xF2DEAF69]
      73 [-]: CALL R3 0 2  ; var3 = var3(var4, ...)
      74 [-]: JUMPIF R3 L8 ; goto L8 if var3
      75 [-]: GETIMPORT R3 11; var3 = 0x89326C93
      76 [-]: NAMECALL R3 R3 K12; var4 = var3; var3 = var3[0x78298275]
      77 [-]: CALL R3 2 2  ; var3 = var3(var4)
      78 [-]: SETUPVAL R3 1; upvalues[3] = var1
      79 [-]: JUMP L9      ; goto L9
L 8:  80 [-]: GETIMPORT R3 22; var3 = _T["HideImpactMessage"]
      81 [-]: CALL R3 1 1  ; var3()
      82 [-]: RETURN R0 0  ; 
L 9:  83 [-]: GETIMPORT R3 1; var3 = 0xCBD666E1
      84 [-]: LOADN R4 0   ; var4 = 0
      85 [-]: CALL R3 2 1  ; var3(var4)
      86 [-]: JUMPBACK L1  ; goto L1
L10:  87 [-]: GETIMPORT R3 22; var3 = _T["HideImpactMessage"]
      88 [-]: CALL R3 1 1  ; var3()
      89 [-]: RETURN R0 0  ; 



