; Name:            
; Defined at line: 1
; #Upvalues:       0
; #Parameters:     0
; Is_vararg:       1
; Max Stack Size:  24

       1 [-]: GETIMPORT R0 1; var0 = 0x0469F296
       2 [-]: LOADK R1 K2  ; var1 = "EmissiveTintColor"
       3 [-]: CALL R0 2 2  ; var0 = var0(var1)
       4 [-]: NEWTABLE R1 0 0; var1 = {}
       5 [-]: NEWTABLE R2 0 0; var2 = {}
       6 [-]: NEWTABLE R3 0 0; var3 = {}
       7 [-]: GETIMPORT R4 1; var4 = 0x0469F296
       8 [-]: LOADK R5 K3  ; var5 = "EmissiveMapAtten"
       9 [-]: CALL R4 2 2  ; var4 = var4(var5)
      10 [-]: GETIMPORT R5 1; var5 = 0x0469F296
      11 [-]: LOADK R6 K4  ; var6 = "waveIdleAtten"
      12 [-]: CALL R5 2 2  ; var5 = var5(var6)
      13 [-]: NEWTABLE R6 0 4; var6 = {}
      14 [-]: GETIMPORT R7 1; var7 = 0x0469F296
      15 [-]: LOADK R8 K5  ; var8 = "waveOne"
      16 [-]: CALL R7 2 2  ; var7 = var7(var8)
      17 [-]: GETIMPORT R8 1; var8 = 0x0469F296
      18 [-]: LOADK R9 K6  ; var9 = "waveTwo"
      19 [-]: CALL R8 2 2  ; var8 = var8(var9)
      20 [-]: GETIMPORT R9 1; var9 = 0x0469F296
      21 [-]: LOADK R10 K7 ; var10 = "waveThree"
      22 [-]: CALL R9 2 2  ; var9 = var9(var10)
      23 [-]: GETIMPORT R10 1; var10 = 0x0469F296
      24 [-]: LOADK R11 K8 ; var11 = "waveFour"
      25 [-]: CALL R10 2 0 ; var10, ... = var10(var11)
      26 [-]: SETLIST R6 R7 -1 [1]; 
      27 [-]: GETIMPORT R7 1; var7 = 0x0469F296
      28 [-]: LOADK R8 K9  ; var8 = "offsetAmount"
      29 [-]: CALL R7 2 2  ; var7 = var7(var8)
      30 [-]: GETIMPORT R8 11; var8 = 0x2D0FAD09
      31 [-]: LOADK R9 K12 ; var9 = "EE.Interface.Utilities"
      32 [-]: CALL R8 2 2  ; var8 = var8(var9)
      33 [-]: GETIMPORT R9 11; var9 = 0x2D0FAD09
      34 [-]: LOADK R10 K13; var10 = "Lotus.Interface.LotusUtilities"
      35 [-]: CALL R9 2 2  ; var9 = var9(var10)
      36 [-]: LOADB R10 0  ; var10 = false
      37 [-]: DUPCLOSURE R11 K14; 
      38 [-]: CAPTURE VAL R0; 
      39 [-]: CAPTURE VAL R7; 
      40 [-]: CAPTURE VAL R4; 
      41 [-]: DUPCLOSURE R12 K15; 
      42 [-]: CAPTURE VAL R0; 
      43 [-]: CAPTURE VAL R4; 
      44 [-]: CAPTURE VAL R7; 
      45 [-]: CAPTURE VAL R6; 
      46 [-]: CAPTURE VAL R5; 
      47 [-]: DUPCLOSURE R13 K16; 
      48 [-]: CAPTURE VAL R4; 
      49 [-]: CAPTURE VAL R0; 
      50 [-]: CAPTURE VAL R7; 
      51 [-]: CAPTURE VAL R6; 
      52 [-]: CAPTURE VAL R5; 
      53 [-]: DUPCLOSURE R14 K17; 
      54 [-]: CAPTURE VAL R6; 
      55 [-]: CAPTURE VAL R0; 
      56 [-]: CAPTURE VAL R5; 
      57 [-]: CAPTURE VAL R4; 
      58 [-]: CAPTURE VAL R7; 
      59 [-]: CAPTURE VAL R11; 
      60 [-]: CAPTURE VAL R12; 
      61 [-]: DUPCLOSURE R15 K18; 
      62 [-]: CAPTURE VAL R6; 
      63 [-]: CAPTURE VAL R0; 
      64 [-]: CAPTURE VAL R5; 
      65 [-]: CAPTURE VAL R4; 
      66 [-]: CAPTURE VAL R7; 
      67 [-]: SETGLOBAL R15 K19; "ChatterFromGlobal" = var15
      68 [-]: NEWCLOSURE R15 P5; 
      69 [-]: CAPTURE REF R1; 
      70 [-]: CAPTURE VAL R8; 
      71 [-]: NEWCLOSURE R16 P6; 
      72 [-]: CAPTURE REF R2; 
      73 [-]: CAPTURE VAL R8; 
      74 [-]: NEWCLOSURE R17 P7; 
      75 [-]: CAPTURE REF R3; 
      76 [-]: CAPTURE VAL R8; 
      77 [-]: NEWCLOSURE R18 P8; 
      78 [-]: CAPTURE REF R1; 
      79 [-]: CAPTURE VAL R15; 
      80 [-]: CAPTURE VAL R14; 
      81 [-]: NEWCLOSURE R19 P9; 
      82 [-]: CAPTURE REF R2; 
      83 [-]: CAPTURE VAL R16; 
      84 [-]: CAPTURE VAL R14; 
      85 [-]: NEWCLOSURE R20 P10; 
      86 [-]: CAPTURE REF R3; 
      87 [-]: CAPTURE VAL R17; 
      88 [-]: CAPTURE VAL R14; 
      89 [-]: DUPCLOSURE R21 K20; 
      90 [-]: SETGLOBAL R21 K21; "OnProfileSaved" = var21
      91 [-]: NEWCLOSURE R21 P12; 
      92 [-]: CAPTURE REF R10; 
      93 [-]: CAPTURE VAL R19; 
      94 [-]: CAPTURE VAL R12; 
      95 [-]: CAPTURE VAL R11; 
      96 [-]: DUPCLOSURE R22 K22; 
      97 [-]: NEWCLOSURE R23 P14; 
      98 [-]: CAPTURE VAL R11; 
      99 [-]: CAPTURE REF R10; 
     100 [-]: CAPTURE VAL R15; 
     101 [-]: CAPTURE VAL R16; 
     102 [-]: CAPTURE VAL R17; 
     103 [-]: CAPTURE VAL R9; 
     104 [-]: CAPTURE VAL R13; 
     105 [-]: CAPTURE VAL R21; 
     106 [-]: CAPTURE VAL R14; 
     107 [-]: CAPTURE VAL R18; 
     108 [-]: CAPTURE VAL R20; 
     109 [-]: CAPTURE VAL R19; 
     110 [-]: SETGLOBAL R23 K23; "RadioChatter" = var23
     111 [-]: CLOSEUPVALS R1; 
     112 [-]: RETURN R0 0  ; 


; Name:            
; Defined at line: 43
; #Upvalues:       3
; #Parameters:     0
; Is_vararg:       0
; Max Stack Size:  11

       0 [-]: LOADN R0 0   ; var0 = 0
       1 [-]: LOADN R1 0   ; var1 = 0
       2 [-]: LOADN R2 0   ; var2 = 0
       3 [-]: LOADN R3 0   ; var3 = 0
L 0:   4 [-]: LOADN R4 1   ; var4 = 1
       5 [-]: JUMPIFNOTLT R0 R4 L7; goto L7 if var0 >= var66849
       6 [-]: GETIMPORT R5 1; var5 = 0xEEFD714E
       7 [-]: FASTCALL1 64 R5 L1; 
       8 [-]: GETIMPORT R4 3; var4 = 0x7B998233
       9 [-]: CALL R4 2 2  ; var4 = var4(var5)
L 1:  10 [-]: JUMPIF R4 L7 ; goto L7 if var4
      11 [-]: GETIMPORT R4 5; var4 = 0xB693B6C1
      12 [-]: CALL R4 1 2  ; var4 = var4()
      13 [-]: ADD R0 R0 R4 ; var0 = var0 + var4
      14 [-]: LOADN R4 2   ; var4 = 2
      15 [-]: LOADN R6 2   ; var6 = 2
      16 [-]: MULK R7 R0 K6; var7 = var0 * 2
      17 [-]: FASTCALL2 19 R6 R7 L2; 
      18 [-]: GETIMPORT R5 9; var5 = 0x5BCED4C4[0xAC1B386A]
      19 [-]: CALL R5 3 2  ; var5 = var5(var6, var7)
L 2:  20 [-]: SUB R1 R4 R5 ; var1 = var4 - var5
      21 [-]: LOADN R4 1   ; var4 = 1
      22 [-]: LOADN R6 1   ; var6 = 1
      23 [-]: FASTCALL2 19 R6 R0 L3; 
      24 [-]: MOVE R7 R0   ; var7 = var0
      25 [-]: GETIMPORT R5 9; var5 = 0x5BCED4C4[0xAC1B386A]
      26 [-]: CALL R5 3 2  ; var5 = var5(var6, var7)
L 3:  27 [-]: SUB R2 R4 R5 ; var2 = var4 - var5
      28 [-]: GETIMPORT R4 1; var4 = 0xEEFD714E
      29 [-]: GETIMPORT R6 11; var6 = 0x838B0418
      30 [-]: LOADN R7 0   ; var7 = 0
      31 [-]: NAMECALL R4 R4 K12; var5 = var4; var4 = var4[0x986D2AB8]
      32 [-]: CALL R4 4 1  ; var4(var5, var6, var7)
      33 [-]: GETIMPORT R4 1; var4 = 0xEEFD714E
      34 [-]: GETIMPORT R6 14; var6 = 0x868B08D1
      35 [-]: LOADN R8 1   ; var8 = 1
      36 [-]: SUB R7 R8 R0 ; var7 = var8 - var0
      37 [-]: NAMECALL R4 R4 K12; var5 = var4; var4 = var4[0x986D2AB8]
      38 [-]: CALL R4 4 1  ; var4(var5, var6, var7)
      39 [-]: LOADN R5 0   ; var5 = 0
      40 [-]: LOADN R7 1   ; var7 = 1
      41 [-]: SUB R6 R7 R0 ; var6 = var7 - var0
      42 [-]: FASTCALL2 18 R5 R6 L4; 
      43 [-]: GETIMPORT R4 16; var4 = 0x5BCED4C4[0xB62ECFE0]
      44 [-]: CALL R4 3 2  ; var4 = var4(var5, var6)
L 4:  45 [-]: MOVE R3 R4   ; var3 = var4
      46 [-]: GETIMPORT R5 18; var5 = 0x334AFF38
      47 [-]: FASTCALL1 64 R5 L5; 
      48 [-]: GETIMPORT R4 3; var4 = 0x7B998233
      49 [-]: CALL R4 2 2  ; var4 = var4(var5)
L 5:  50 [-]: JUMPIF R4 L6 ; goto L6 if var4
      51 [-]: GETIMPORT R4 18; var4 = 0x334AFF38
      52 [-]: GETUPVAL R6 0; var6 = upvalues[0]
      53 [-]: MOVE R7 R3   ; var7 = var3
      54 [-]: MOVE R8 R3   ; var8 = var3
      55 [-]: MOVE R9 R3   ; var9 = var3
      56 [-]: LOADN R10 1  ; var10 = 1
      57 [-]: NAMECALL R4 R4 K12; var5 = var4; var4 = var4[0x986D2AB8]
      58 [-]: CALL R4 7 1  ; var4(var5, var6, var7, var8, var9, var10)
L 6:  59 [-]: GETIMPORT R4 20; var4 = 0xCBD666E1
      60 [-]: LOADN R5 0   ; var5 = 0
      61 [-]: CALL R4 2 1  ; var4(var5)
      62 [-]: JUMPBACK L0  ; goto L0
L 7:  63 [-]: GETIMPORT R5 1; var5 = 0xEEFD714E
      64 [-]: FASTCALL1 64 R5 L8; 
      65 [-]: GETIMPORT R4 3; var4 = 0x7B998233
      66 [-]: CALL R4 2 2  ; var4 = var4(var5)
L 8:  67 [-]: JUMPIF R4 L9 ; goto L9 if var4
      68 [-]: GETIMPORT R4 1; var4 = 0xEEFD714E
      69 [-]: GETIMPORT R6 23; var6 = 0x6C97A788["UNLIT_ATTEN"]
      70 [-]: LOADN R7 0   ; var7 = 0
      71 [-]: NAMECALL R4 R4 K12; var5 = var4; var4 = var4[0x986D2AB8]
      72 [-]: CALL R4 4 1  ; var4(var5, var6, var7)
      73 [-]: GETIMPORT R4 1; var4 = 0xEEFD714E
      74 [-]: GETUPVAL R6 1; var6 = upvalues[1]
      75 [-]: LOADN R7 0   ; var7 = 0
      76 [-]: NAMECALL R4 R4 K12; var5 = var4; var4 = var4[0x986D2AB8]
      77 [-]: CALL R4 4 1  ; var4(var5, var6, var7)
L 9:  78 [-]: GETIMPORT R5 18; var5 = 0x334AFF38
      79 [-]: FASTCALL1 64 R5 L10; 
      80 [-]: GETIMPORT R4 3; var4 = 0x7B998233
      81 [-]: CALL R4 2 2  ; var4 = var4(var5)
L10:  82 [-]: JUMPIF R4 L11; goto L11 if var4
      83 [-]: GETIMPORT R4 18; var4 = 0x334AFF38
      84 [-]: GETUPVAL R6 2; var6 = upvalues[2]
      85 [-]: LOADN R7 0   ; var7 = 0
      86 [-]: NAMECALL R4 R4 K12; var5 = var4; var4 = var4[0x986D2AB8]
      87 [-]: CALL R4 4 1  ; var4(var5, var6, var7)
L11:  88 [-]: GETIMPORT R5 25; var5 = 0x34BF6C85
      89 [-]: FASTCALL1 64 R5 L12; 
      90 [-]: GETIMPORT R4 3; var4 = 0x7B998233
      91 [-]: CALL R4 2 2  ; var4 = var4(var5)
L12:  92 [-]: JUMPIF R4 L13; goto L13 if var4
      93 [-]: GETIMPORT R4 25; var4 = 0x34BF6C85
      94 [-]: LOADN R6 0   ; var6 = 0
      95 [-]: NAMECALL R4 R4 K26; var5 = var4; var4 = var4[0x178D8B0F]
      96 [-]: CALL R4 3 1  ; var4(var5, var6)
L13:  97 [-]: GETIMPORT R5 28; var5 = 0x2BC57C41
      98 [-]: FASTCALL1 64 R5 L14; 
      99 [-]: GETIMPORT R4 3; var4 = 0x7B998233
     100 [-]: CALL R4 2 2  ; var4 = var4(var5)
L14: 101 [-]: JUMPIF R4 L15; goto L15 if var4
     102 [-]: GETIMPORT R4 28; var4 = 0x2BC57C41
     103 [-]: NAMECALL R4 R4 K29; var5 = var4; var4 = var4[0x6B5E0C7A]
     104 [-]: CALL R4 2 1  ; var4(var5)
L15: 105 [-]: RETURN R0 0  ; 


; Name:            
; Defined at line: 76
; #Upvalues:       5
; #Parameters:     0
; Is_vararg:       0
; Max Stack Size:  10

       0 [-]: GETIMPORT R1 1; var1 = 0x334AFF38
       1 [-]: FASTCALL1 64 R1 L0; 
       2 [-]: GETIMPORT R0 3; var0 = 0x7B998233
       3 [-]: CALL R0 2 2  ; var0 = var0(var1)
L 0:   4 [-]: JUMPIF R0 L1 ; goto L1 if var0
       5 [-]: GETIMPORT R0 1; var0 = 0x334AFF38
       6 [-]: GETUPVAL R2 0; var2 = upvalues[0]
       7 [-]: LOADN R3 1   ; var3 = 1
       8 [-]: LOADN R4 1   ; var4 = 1
       9 [-]: LOADN R5 1   ; var5 = 1
      10 [-]: LOADN R6 1   ; var6 = 1
      11 [-]: NAMECALL R0 R0 K4; var1 = var0; var0 = var0[0x986D2AB8]
      12 [-]: CALL R0 7 1  ; var0(var1, var2, var3, var4, var5, var6)
L 1:  13 [-]: GETIMPORT R1 1; var1 = 0x334AFF38
      14 [-]: FASTCALL1 64 R1 L2; 
      15 [-]: GETIMPORT R0 3; var0 = 0x7B998233
      16 [-]: CALL R0 2 2  ; var0 = var0(var1)
L 2:  17 [-]: JUMPIF R0 L3 ; goto L3 if var0
      18 [-]: GETIMPORT R0 1; var0 = 0x334AFF38
      19 [-]: GETUPVAL R2 1; var2 = upvalues[1]
      20 [-]: LOADK R3 K5  ; var3 = 0.25
      21 [-]: NAMECALL R0 R0 K4; var1 = var0; var0 = var0[0x986D2AB8]
      22 [-]: CALL R0 4 1  ; var0(var1, var2, var3)
      23 [-]: GETIMPORT R0 1; var0 = 0x334AFF38
      24 [-]: GETUPVAL R2 0; var2 = upvalues[0]
      25 [-]: LOADN R3 1   ; var3 = 1
      26 [-]: LOADN R4 1   ; var4 = 1
      27 [-]: LOADN R5 1   ; var5 = 1
      28 [-]: LOADN R6 1   ; var6 = 1
      29 [-]: NAMECALL R0 R0 K4; var1 = var0; var0 = var0[0x986D2AB8]
      30 [-]: CALL R0 7 1  ; var0(var1, var2, var3, var4, var5, var6)
L 3:  31 [-]: GETIMPORT R1 7; var1 = 0xEEFD714E
      32 [-]: FASTCALL1 64 R1 L4; 
      33 [-]: GETIMPORT R0 3; var0 = 0x7B998233
      34 [-]: CALL R0 2 2  ; var0 = var0(var1)
L 4:  35 [-]: JUMPIF R0 L7 ; goto L7 if var0
      36 [-]: GETIMPORT R0 7; var0 = 0xEEFD714E
      37 [-]: GETIMPORT R2 10; var2 = 0x6C97A788["UNLIT_ATTEN"]
      38 [-]: LOADK R3 K5  ; var3 = 0.25
      39 [-]: NAMECALL R0 R0 K4; var1 = var0; var0 = var0[0x986D2AB8]
      40 [-]: CALL R0 4 1  ; var0(var1, var2, var3)
      41 [-]: GETIMPORT R0 7; var0 = 0xEEFD714E
      42 [-]: GETUPVAL R2 2; var2 = upvalues[2]
      43 [-]: LOADN R3 0   ; var3 = 0
      44 [-]: NAMECALL R0 R0 K4; var1 = var0; var0 = var0[0x986D2AB8]
      45 [-]: CALL R0 4 1  ; var0(var1, var2, var3)
      46 [-]: LOADN R2 1   ; var2 = 1
      47 [-]: GETUPVAL R3 3; var3 = upvalues[3]
      48 [-]: LENGTH R0 R3 ; var0 = #var3
      49 [-]: LOADN R1 1   ; var1 = 1
      50 [-]: FORNPREP R0 L6; nforprep start - [escape at L6] -- var0 = iterator
L 5:  51 [-]: GETIMPORT R3 7; var3 = 0xEEFD714E
      52 [-]: GETUPVAL R6 3; var6 = upvalues[3]
      53 [-]: GETTABLE R5 R6 R2; var5 = var6[var2]
      54 [-]: LOADN R6 4   ; var6 = 4
      55 [-]: LOADK R7 K11 ; var7 = 0.10000000149011612
      56 [-]: LOADN R8 0   ; var8 = 0
      57 [-]: LOADK R9 K12 ; var9 = 0.0099999997764825821
      58 [-]: NAMECALL R3 R3 K4; var4 = var3; var3 = var3[0x986D2AB8]
      59 [-]: CALL R3 7 1  ; var3(var4, var5, var6, var7, var8, var9)
      60 [-]: FORNLOOP R0 L5; nforloop end - iterate + goto L5
L 6:  61 [-]: GETIMPORT R0 7; var0 = 0xEEFD714E
      62 [-]: GETIMPORT R2 14; var2 = 0x838B0418
      63 [-]: LOADN R3 2   ; var3 = 2
      64 [-]: NAMECALL R0 R0 K4; var1 = var0; var0 = var0[0x986D2AB8]
      65 [-]: CALL R0 4 1  ; var0(var1, var2, var3)
      66 [-]: GETIMPORT R0 7; var0 = 0xEEFD714E
      67 [-]: GETIMPORT R2 16; var2 = 0x868B08D1
      68 [-]: LOADN R3 1   ; var3 = 1
      69 [-]: NAMECALL R0 R0 K4; var1 = var0; var0 = var0[0x986D2AB8]
      70 [-]: CALL R0 4 1  ; var0(var1, var2, var3)
L 7:  71 [-]: GETIMPORT R1 18; var1 = 0x34BF6C85
      72 [-]: FASTCALL1 64 R1 L8; 
      73 [-]: GETIMPORT R0 3; var0 = 0x7B998233
      74 [-]: CALL R0 2 2  ; var0 = var0(var1)
L 8:  75 [-]: JUMPIF R0 L9 ; goto L9 if var0
      76 [-]: GETIMPORT R0 18; var0 = 0x34BF6C85
      77 [-]: LOADK R2 K5  ; var2 = 0.25
      78 [-]: NAMECALL R0 R0 K19; var1 = var0; var0 = var0[0x178D8B0F]
      79 [-]: CALL R0 3 1  ; var0(var1, var2)
L 9:  80 [-]: LOADN R0 0   ; var0 = 0
      81 [-]: GETIMPORT R2 7; var2 = 0xEEFD714E
      82 [-]: FASTCALL1 64 R2 L10; 
      83 [-]: GETIMPORT R1 3; var1 = 0x7B998233
      84 [-]: CALL R1 2 2  ; var1 = var1(var2)
L10:  85 [-]: JUMPIF R1 L13; goto L13 if var1
      86 [-]: LOADN R1 0   ; var1 = 0
L11:  87 [-]: LOADN R2 1   ; var2 = 1
      88 [-]: JUMPIFNOTLT R1 R2 L13; goto L13 if var1 >= var1376801
      89 [-]: GETIMPORT R2 21; var2 = 0xB693B6C1
      90 [-]: CALL R2 1 2  ; var2 = var2()
      91 [-]: ADD R1 R1 R2 ; var1 = var1 + var2
      92 [-]: LOADN R3 0   ; var3 = 0
      93 [-]: LOADN R5 1   ; var5 = 1
      94 [-]: SUB R4 R5 R1 ; var4 = var5 - var1
      95 [-]: FASTCALL2 18 R3 R4 L12; 
      96 [-]: GETIMPORT R2 24; var2 = 0x5BCED4C4[0xB62ECFE0]
      97 [-]: CALL R2 3 2  ; var2 = var2(var3, var4)
L12:  98 [-]: MOVE R0 R2   ; var0 = var2
      99 [-]: GETIMPORT R2 7; var2 = 0xEEFD714E
     100 [-]: GETUPVAL R4 4; var4 = upvalues[4]
     101 [-]: MOVE R5 R0   ; var5 = var0
     102 [-]: NAMECALL R2 R2 K4; var3 = var2; var2 = var2[0x986D2AB8]
     103 [-]: CALL R2 4 1  ; var2(var3, var4, var5)
     104 [-]: GETIMPORT R2 26; var2 = 0xCBD666E1
     105 [-]: LOADN R3 0   ; var3 = 0
     106 [-]: CALL R2 2 1  ; var2(var3)
     107 [-]: JUMPBACK L11 ; goto L11
L13: 108 [-]: RETURN R0 0  ; 


; Name:            
; Defined at line: 111
; #Upvalues:       5
; #Parameters:     0
; Is_vararg:       0
; Max Stack Size:  10

       0 [-]: GETIMPORT R1 1; var1 = 0x334AFF38
       1 [-]: FASTCALL1 64 R1 L0; 
       2 [-]: GETIMPORT R0 3; var0 = 0x7B998233
       3 [-]: CALL R0 2 2  ; var0 = var0(var1)
L 0:   4 [-]: JUMPIF R0 L1 ; goto L1 if var0
       5 [-]: GETIMPORT R0 1; var0 = 0x334AFF38
       6 [-]: GETUPVAL R2 0; var2 = upvalues[0]
       7 [-]: LOADK R3 K4  ; var3 = 0.25
       8 [-]: NAMECALL R0 R0 K5; var1 = var0; var0 = var0[0x986D2AB8]
       9 [-]: CALL R0 4 1  ; var0(var1, var2, var3)
      10 [-]: GETIMPORT R0 1; var0 = 0x334AFF38
      11 [-]: GETUPVAL R2 1; var2 = upvalues[1]
      12 [-]: LOADN R3 1   ; var3 = 1
      13 [-]: LOADN R4 1   ; var4 = 1
      14 [-]: LOADN R5 1   ; var5 = 1
      15 [-]: LOADN R6 1   ; var6 = 1
      16 [-]: NAMECALL R0 R0 K5; var1 = var0; var0 = var0[0x986D2AB8]
      17 [-]: CALL R0 7 1  ; var0(var1, var2, var3, var4, var5, var6)
L 1:  18 [-]: GETIMPORT R1 7; var1 = 0xEEFD714E
      19 [-]: FASTCALL1 64 R1 L2; 
      20 [-]: GETIMPORT R0 3; var0 = 0x7B998233
      21 [-]: CALL R0 2 2  ; var0 = var0(var1)
L 2:  22 [-]: JUMPIF R0 L5 ; goto L5 if var0
      23 [-]: GETIMPORT R0 7; var0 = 0xEEFD714E
      24 [-]: GETIMPORT R2 10; var2 = 0x6C97A788["UNLIT_ATTEN"]
      25 [-]: LOADK R3 K4  ; var3 = 0.25
      26 [-]: NAMECALL R0 R0 K5; var1 = var0; var0 = var0[0x986D2AB8]
      27 [-]: CALL R0 4 1  ; var0(var1, var2, var3)
      28 [-]: GETIMPORT R0 7; var0 = 0xEEFD714E
      29 [-]: GETUPVAL R2 2; var2 = upvalues[2]
      30 [-]: LOADN R3 0   ; var3 = 0
      31 [-]: NAMECALL R0 R0 K5; var1 = var0; var0 = var0[0x986D2AB8]
      32 [-]: CALL R0 4 1  ; var0(var1, var2, var3)
      33 [-]: LOADN R2 1   ; var2 = 1
      34 [-]: GETUPVAL R3 3; var3 = upvalues[3]
      35 [-]: LENGTH R0 R3 ; var0 = #var3
      36 [-]: LOADN R1 1   ; var1 = 1
      37 [-]: FORNPREP R0 L4; nforprep start - [escape at L4] -- var0 = iterator
L 3:  38 [-]: GETIMPORT R3 7; var3 = 0xEEFD714E
      39 [-]: GETUPVAL R6 3; var6 = upvalues[3]
      40 [-]: GETTABLE R5 R6 R2; var5 = var6[var2]
      41 [-]: LOADN R6 60  ; var6 = 60
      42 [-]: LOADK R7 K4  ; var7 = 0.25
      43 [-]: LOADN R8 0   ; var8 = 0
      44 [-]: LOADK R9 K11 ; var9 = 0.0099999997764825821
      45 [-]: NAMECALL R3 R3 K5; var4 = var3; var3 = var3[0x986D2AB8]
      46 [-]: CALL R3 7 1  ; var3(var4, var5, var6, var7, var8, var9)
      47 [-]: FORNLOOP R0 L3; nforloop end - iterate + goto L3
L 4:  48 [-]: GETIMPORT R0 7; var0 = 0xEEFD714E
      49 [-]: GETIMPORT R2 13; var2 = 0x838B0418
      50 [-]: LOADN R3 2   ; var3 = 2
      51 [-]: NAMECALL R0 R0 K5; var1 = var0; var0 = var0[0x986D2AB8]
      52 [-]: CALL R0 4 1  ; var0(var1, var2, var3)
      53 [-]: GETIMPORT R0 7; var0 = 0xEEFD714E
      54 [-]: GETIMPORT R2 15; var2 = 0x868B08D1
      55 [-]: LOADN R3 1   ; var3 = 1
      56 [-]: NAMECALL R0 R0 K5; var1 = var0; var0 = var0[0x986D2AB8]
      57 [-]: CALL R0 4 1  ; var0(var1, var2, var3)
      58 [-]: GETIMPORT R0 7; var0 = 0xEEFD714E
      59 [-]: GETUPVAL R2 4; var2 = upvalues[4]
      60 [-]: LOADN R3 0   ; var3 = 0
      61 [-]: NAMECALL R0 R0 K5; var1 = var0; var0 = var0[0x986D2AB8]
      62 [-]: CALL R0 4 1  ; var0(var1, var2, var3)
L 5:  63 [-]: GETIMPORT R1 17; var1 = 0x34BF6C85
      64 [-]: FASTCALL1 64 R1 L6; 
      65 [-]: GETIMPORT R0 3; var0 = 0x7B998233
      66 [-]: CALL R0 2 2  ; var0 = var0(var1)
L 6:  67 [-]: JUMPIF R0 L7 ; goto L7 if var0
      68 [-]: GETIMPORT R0 17; var0 = 0x34BF6C85
      69 [-]: LOADK R2 K4  ; var2 = 0.25
      70 [-]: NAMECALL R0 R0 K18; var1 = var0; var0 = var0[0x178D8B0F]
      71 [-]: CALL R0 3 1  ; var0(var1, var2)
L 7:  72 [-]: RETURN R0 0  ; 


; Name:            
; Defined at line: 133
; #Upvalues:       7
; #Parameters:     2
; Is_vararg:       0
; Max Stack Size:  21

       0 [-]: FASTCALL1 64 R0 L0; 
       1 [-]: MOVE R3 R0   ; var3 = var0
       2 [-]: GETIMPORT R2 1; var2 = 0x7B998233
       3 [-]: CALL R2 2 2  ; var2 = var2(var3)
L 0:   4 [-]: JUMPIF R2 L2 ; goto L2 if var2
       5 [-]: FASTCALL1 64 R1 L1; 
       6 [-]: MOVE R3 R1   ; var3 = var1
       7 [-]: GETIMPORT R2 1; var2 = 0x7B998233
       8 [-]: CALL R2 2 2  ; var2 = var2(var3)
L 1:   9 [-]: JUMPIFNOT R2 L3; goto L3 if not var2
L 2:  10 [-]: RETURN R0 0  ; 
L 3:  11 [-]: NEWTABLE R2 0 0; var2 = {}
      12 [-]: LOADN R5 1   ; var5 = 1
      13 [-]: GETUPVAL R6 0; var6 = upvalues[0]
      14 [-]: LENGTH R3 R6 ; var3 = #var6
      15 [-]: LOADN R4 1   ; var4 = 1
      16 [-]: FORNPREP R3 L5; nforprep start - [escape at L5] -- var3 = iterator
L 4:  17 [-]: LOADN R7 1   ; var7 = 1
      18 [-]: DIV R6 R7 R5 ; var6 = var7 / var5
      19 [-]: SUBK R8 R5 K3; var8 = var5 - 1
      20 [-]: MULK R7 R8 K2; var7 = var8 * 4
      21 [-]: ADDK R8 R7 K3; var8 = var7 + 1
      22 [-]: MUL R11 R5 R5; var11 = var5 * var5
      23 [-]: ADDK R10 R11 K3; var10 = var11 + 1
      24 [-]: GETIMPORT R11 6; var11 = 0x5BCED4C4[0x3630E649]
      25 [-]: LOADN R12 -1 ; var12 = -1
      26 [-]: LOADN R13 2  ; var13 = 2
      27 [-]: CALL R11 3 2 ; var11 = var11(var12, var13)
      28 [-]: ADD R9 R10 R11; var9 = var10 + var11
      29 [-]: SETTABLE R9 R2 R8; var9[var2] = var8
      30 [-]: ADDK R8 R7 K7; var8 = var7 + 2
      31 [-]: GETIMPORT R10 9; var10 = 0xC163F229
      32 [-]: LOADK R11 K10; var11 = 0.15000000596046448
      33 [-]: LOADK R12 K11; var12 = 0.25
      34 [-]: CALL R10 3 2 ; var10 = var10(var11, var12)
      35 [-]: MUL R9 R6 R10; var9 = var6 * var10
      36 [-]: SETTABLE R9 R2 R8; var9[var2] = var8
      37 [-]: ADDK R8 R7 K12; var8 = var7 + 3
      38 [-]: GETIMPORT R9 9; var9 = 0xC163F229
      39 [-]: LOADN R10 -3 ; var10 = -3
      40 [-]: LOADN R11 3  ; var11 = 3
      41 [-]: CALL R9 3 2  ; var9 = var9(var10, var11)
      42 [-]: SETTABLE R9 R2 R8; var9[var2] = var8
      43 [-]: ADDK R8 R7 K2; var8 = var7 + 4
      44 [-]: GETIMPORT R9 9; var9 = 0xC163F229
      45 [-]: LOADN R10 -1 ; var10 = -1
      46 [-]: LOADN R11 1  ; var11 = 1
      47 [-]: CALL R9 3 2  ; var9 = var9(var10, var11)
      48 [-]: SETTABLE R9 R2 R8; var9[var2] = var8
      49 [-]: FORNLOOP R3 L4; nforloop end - iterate + goto L4
L 5:  50 [-]: MOVE R5 R1   ; var5 = var1
      51 [-]: LOADB R6 0   ; var6 = false
      52 [-]: LOADN R7 1   ; var7 = 1
      53 [-]: LOADB R8 0   ; var8 = false
      54 [-]: NAMECALL R3 R0 K13; var4 = var0; var3 = var0[0x659D451F]
      55 [-]: CALL R3 6 2  ; var3 = var3(var4, var5, var6, var7, var8)
      56 [-]: GETIMPORT R5 15; var5 = 0x2BC57C41
      57 [-]: FASTCALL1 64 R5 L6; 
      58 [-]: GETIMPORT R4 1; var4 = 0x7B998233
      59 [-]: CALL R4 2 2  ; var4 = var4(var5)
L 6:  60 [-]: JUMPIF R4 L7 ; goto L7 if var4
      61 [-]: GETIMPORT R4 15; var4 = 0x2BC57C41
      62 [-]: NAMECALL R4 R4 K16; var5 = var4; var4 = var4[0xD199E920]
      63 [-]: CALL R4 2 1  ; var4(var5)
L 7:  64 [-]: GETIMPORT R4 18; var4 = 0xEEFD714E
      65 [-]: GETIMPORT R6 20; var6 = 0x838B0418
      66 [-]: LOADN R7 2   ; var7 = 2
      67 [-]: NAMECALL R4 R4 K21; var5 = var4; var4 = var4[0x986D2AB8]
      68 [-]: CALL R4 4 1  ; var4(var5, var6, var7)
      69 [-]: GETIMPORT R4 18; var4 = 0xEEFD714E
      70 [-]: GETIMPORT R6 23; var6 = 0x868B08D1
      71 [-]: LOADN R7 1   ; var7 = 1
      72 [-]: NAMECALL R4 R4 K21; var5 = var4; var4 = var4[0x986D2AB8]
      73 [-]: CALL R4 4 1  ; var4(var5, var6, var7)
      74 [-]: GETIMPORT R5 25; var5 = 0x334AFF38
      75 [-]: FASTCALL1 64 R5 L8; 
      76 [-]: GETIMPORT R4 1; var4 = 0x7B998233
      77 [-]: CALL R4 2 2  ; var4 = var4(var5)
L 8:  78 [-]: JUMPIF R4 L9 ; goto L9 if var4
      79 [-]: GETIMPORT R4 25; var4 = 0x334AFF38
      80 [-]: GETUPVAL R6 1; var6 = upvalues[1]
      81 [-]: LOADN R7 1   ; var7 = 1
      82 [-]: LOADN R8 1   ; var8 = 1
      83 [-]: LOADN R9 1   ; var9 = 1
      84 [-]: LOADN R10 1  ; var10 = 1
      85 [-]: NAMECALL R4 R4 K21; var5 = var4; var4 = var4[0x986D2AB8]
      86 [-]: CALL R4 7 1  ; var4(var5, var6, var7, var8, var9, var10)
L 9:  87 [-]: GETIMPORT R4 18; var4 = 0xEEFD714E
      88 [-]: GETUPVAL R6 2; var6 = upvalues[2]
      89 [-]: LOADN R7 1   ; var7 = 1
      90 [-]: NAMECALL R4 R4 K21; var5 = var4; var4 = var4[0x986D2AB8]
      91 [-]: CALL R4 4 1  ; var4(var5, var6, var7)
L10:  92 [-]: FASTCALL1 64 R3 L11; 
      93 [-]: MOVE R5 R3   ; var5 = var3
      94 [-]: GETIMPORT R4 1; var4 = 0x7B998233
      95 [-]: CALL R4 2 2  ; var4 = var4(var5)
L11:  96 [-]: JUMPIF R4 L27; goto L27 if var4
      97 [-]: GETIMPORT R4 27; var4 = 0xDFEBB754
      98 [-]: GETIMPORT R5 29; var5 = 0x107BF6DA
      99 [-]: GETIMPORT R7 32; var7 = 0x55156FF7
     100 [-]: CALL R7 1 2  ; var7 = var7()
     101 [-]: MULK R6 R7 K30; var6 = var7 * 0.10000000149011612
     102 [-]: CALL R5 2 0  ; var5, ... = var5(var6)
     103 [-]: CALL R4 0 2  ; var4 = var4(var5, ...)
     104 [-]: GETIMPORT R5 27; var5 = 0xDFEBB754
     105 [-]: GETIMPORT R6 29; var6 = 0x107BF6DA
     106 [-]: GETIMPORT R8 32; var8 = 0x55156FF7
     107 [-]: CALL R8 1 2  ; var8 = var8()
     108 [-]: MULK R7 R8 K33; var7 = var8 * 0.60000002384185791
     109 [-]: CALL R6 2 0  ; var6, ... = var6(var7)
     110 [-]: CALL R5 0 2  ; var5 = var5(var6, ...)
     111 [-]: NAMECALL R6 R3 K34; var7 = var3; var6 = var3[0xDAE5BCB5]
     112 [-]: CALL R6 2 2  ; var6 = var6(var7)
     113 [-]: GETIMPORT R8 25; var8 = 0x334AFF38
     114 [-]: FASTCALL1 64 R8 L12; 
     115 [-]: GETIMPORT R7 1; var7 = 0x7B998233
     116 [-]: CALL R7 2 2  ; var7 = var7(var8)
L12: 117 [-]: JUMPIF R7 L13; goto L13 if var7
     118 [-]: GETIMPORT R7 25; var7 = 0x334AFF38
     119 [-]: GETUPVAL R9 3; var9 = upvalues[3]
     120 [-]: LOADK R11 K11; var11 = 0.25
     121 [-]: MULK R12 R6 K2; var12 = var6 * 4
     122 [-]: ADD R10 R11 R12; var10 = var11 + var12
     123 [-]: NAMECALL R7 R7 K21; var8 = var7; var7 = var7[0x986D2AB8]
     124 [-]: CALL R7 4 1  ; var7(var8, var9, var10)
L13: 125 [-]: FASTCALL1 64 R3 L14; 
     126 [-]: MOVE R8 R3   ; var8 = var3
     127 [-]: GETIMPORT R7 1; var7 = 0x7B998233
     128 [-]: CALL R7 2 2  ; var7 = var7(var8)
L14: 129 [-]: JUMPIF R7 L15; goto L15 if var7
     130 [-]: LOADN R9 1   ; var9 = 1
     131 [-]: GETIMPORT R10 36; var10 = 0x42DCC9F5
     132 [-]: MOVE R11 R4  ; var11 = var4
     133 [-]: LOADN R12 0  ; var12 = 0
     134 [-]: LOADN R13 1  ; var13 = 1
     135 [-]: CALL R10 4 0 ; var10, ... = var10(var11, var12, var13)
     136 [-]: NAMECALL R7 R3 K37; var8 = var3; var7 = var3[0xEF040C26]
     137 [-]: CALL R7 0 1  ; var7(var8, ...)
     138 [-]: LOADN R9 4   ; var9 = 4
     139 [-]: GETIMPORT R10 36; var10 = 0x42DCC9F5
     140 [-]: MOVE R11 R5  ; var11 = var5
     141 [-]: LOADN R12 0  ; var12 = 0
     142 [-]: LOADN R13 1  ; var13 = 1
     143 [-]: CALL R10 4 0 ; var10, ... = var10(var11, var12, var13)
     144 [-]: NAMECALL R7 R3 K37; var8 = var3; var7 = var3[0xEF040C26]
     145 [-]: CALL R7 0 1  ; var7(var8, ...)
L15: 146 [-]: GETIMPORT R8 18; var8 = 0xEEFD714E
     147 [-]: FASTCALL1 64 R8 L16; 
     148 [-]: GETIMPORT R7 1; var7 = 0x7B998233
     149 [-]: CALL R7 2 2  ; var7 = var7(var8)
L16: 150 [-]: JUMPIF R7 L19; goto L19 if var7
     151 [-]: GETIMPORT R7 18; var7 = 0xEEFD714E
     152 [-]: GETIMPORT R9 40; var9 = 0x6C97A788["UNLIT_ATTEN"]
     153 [-]: LOADK R11 K11; var11 = 0.25
     154 [-]: MULK R12 R6 K2; var12 = var6 * 4
     155 [-]: ADD R10 R11 R12; var10 = var11 + var12
     156 [-]: NAMECALL R7 R7 K21; var8 = var7; var7 = var7[0x986D2AB8]
     157 [-]: CALL R7 4 1  ; var7(var8, var9, var10)
     158 [-]: GETIMPORT R7 18; var7 = 0xEEFD714E
     159 [-]: GETUPVAL R9 4; var9 = upvalues[4]
     160 [-]: MULK R10 R6 K41; var10 = var6 * 0.039999999105930328
     161 [-]: NAMECALL R7 R7 K21; var8 = var7; var7 = var7[0x986D2AB8]
     162 [-]: CALL R7 4 1  ; var7(var8, var9, var10)
     163 [-]: LOADN R9 1   ; var9 = 1
     164 [-]: GETUPVAL R10 0; var10 = upvalues[0]
     165 [-]: LENGTH R7 R10; var7 = #var10
     166 [-]: LOADN R8 1   ; var8 = 1
     167 [-]: FORNPREP R7 L19; nforprep start - [escape at L19] -- var7 = iterator
L17: 168 [-]: SUBK R11 R9 K3; var11 = var9 - 1
     169 [-]: MULK R10 R11 K2; var10 = var11 * 4
     170 [-]: GETIMPORT R11 36; var11 = 0x42DCC9F5
     171 [-]: LOADN R13 4  ; var13 = 4
     172 [-]: GETIMPORT R14 27; var14 = 0xDFEBB754
     173 [-]: GETIMPORT R16 29; var16 = 0x107BF6DA
     174 [-]: GETIMPORT R17 32; var17 = 0x55156FF7
     175 [-]: CALL R17 1 0 ; var17, ... = var17()
     176 [-]: CALL R16 0 2 ; var16 = var16(var17, ...)
     177 [-]: MUL R15 R9 R16; var15 = var9 * var16
     178 [-]: CALL R14 2 2 ; var14 = var14(var15)
     179 [-]: MUL R12 R13 R14; var12 = var13 * var14
     180 [-]: LOADK R13 K42; var13 = 0.5
     181 [-]: LOADN R14 1  ; var14 = 1
     182 [-]: CALL R11 4 2 ; var11 = var11(var12, var13, var14)
     183 [-]: GETIMPORT R12 18; var12 = 0xEEFD714E
     184 [-]: GETUPVAL R15 0; var15 = upvalues[0]
     185 [-]: GETTABLE R14 R15 R9; var14 = var15[var9]
     186 [-]: ADDK R16 R10 K3; var16 = var10 + 1
     187 [-]: GETTABLE R15 R2 R16; var15 = var2[var16]
     188 [-]: LOADN R19 1  ; var19 = 1
     189 [-]: FASTCALL2 19 R19 R6 L18; 
     190 [-]: MOVE R20 R6  ; var20 = var6
     191 [-]: GETIMPORT R18 44; var18 = 0x5BCED4C4[0xAC1B386A]
     192 [-]: CALL R18 3 2 ; var18 = var18(var19, var20)
L18: 193 [-]: MUL R17 R11 R18; var17 = var11 * var18
     194 [-]: ADDK R19 R10 K7; var19 = var10 + 2
     195 [-]: GETTABLE R18 R2 R19; var18 = var2[var19]
     196 [-]: MUL R16 R17 R18; var16 = var17 * var18
     197 [-]: MULK R18 R11 K45; var18 = var11 * 12
     198 [-]: ADDK R20 R10 K12; var20 = var10 + 3
     199 [-]: GETTABLE R19 R2 R20; var19 = var2[var20]
     200 [-]: ADD R17 R18 R19; var17 = var18 + var19
     201 [-]: ADDK R19 R10 K2; var19 = var10 + 4
     202 [-]: GETTABLE R18 R2 R19; var18 = var2[var19]
     203 [-]: NAMECALL R12 R12 K21; var13 = var12; var12 = var12[0x986D2AB8]
     204 [-]: CALL R12 7 1 ; var12(var13, var14, var15, var16, var17, var18)
     205 [-]: FORNLOOP R7 L17; nforloop end - iterate + goto L17
L19: 206 [-]: GETIMPORT R8 47; var8 = 0x34BF6C85
     207 [-]: FASTCALL1 64 R8 L20; 
     208 [-]: GETIMPORT R7 1; var7 = 0x7B998233
     209 [-]: CALL R7 2 2  ; var7 = var7(var8)
L20: 210 [-]: JUMPIF R7 L21; goto L21 if var7
     211 [-]: GETIMPORT R7 47; var7 = 0x34BF6C85
     212 [-]: LOADK R10 K11; var10 = 0.25
     213 [-]: MULK R11 R6 K2; var11 = var6 * 4
     214 [-]: ADD R9 R10 R11; var9 = var10 + var11
     215 [-]: NAMECALL R7 R7 K48; var8 = var7; var7 = var7[0x178D8B0F]
     216 [-]: CALL R7 3 1  ; var7(var8, var9)
L21: 217 [-]: GETIMPORT R8 15; var8 = 0x2BC57C41
     218 [-]: FASTCALL1 64 R8 L22; 
     219 [-]: GETIMPORT R7 1; var7 = 0x7B998233
     220 [-]: CALL R7 2 2  ; var7 = var7(var8)
L22: 221 [-]: JUMPIF R7 L23; goto L23 if var7
     222 [-]: GETIMPORT R7 15; var7 = 0x2BC57C41
     223 [-]: MULK R9 R6 K12; var9 = var6 * 3
     224 [-]: NAMECALL R7 R7 K49; var8 = var7; var7 = var7[0xE29E950D]
     225 [-]: CALL R7 3 1  ; var7(var8, var9)
L23: 226 [-]: GETIMPORT R7 51; var7 = 0xCBD666E1
     227 [-]: LOADN R8 0   ; var8 = 0
     228 [-]: CALL R7 2 1  ; var7(var8)
     229 [-]: GETIMPORT R7 54; var7 = _T["RadioChatterDisabled"]
     230 [-]: JUMPXEQKB R7 1 L26 NOT; 
     231 [-]: FASTCALL1 64 R3 L24; 
     232 [-]: MOVE R8 R3   ; var8 = var3
     233 [-]: GETIMPORT R7 1; var7 = 0x7B998233
     234 [-]: CALL R7 2 2  ; var7 = var7(var8)
L24: 235 [-]: JUMPIF R7 L25; goto L25 if var7
     236 [-]: LOADB R9 1   ; var9 = true
     237 [-]: NAMECALL R7 R3 K55; var8 = var3; var7 = var3[0x6CF1E476]
     238 [-]: CALL R7 3 1  ; var7(var8, var9)
L25: 239 [-]: GETUPVAL R7 5; var7 = upvalues[5]
     240 [-]: CALL R7 1 1  ; var7()
     241 [-]: RETURN R0 0  ; 
L26: 242 [-]: JUMPBACK L10 ; goto L10
L27: 243 [-]: GETUPVAL R4 6; var4 = upvalues[6]
     244 [-]: CALL R4 1 1  ; var4()
     245 [-]: RETURN R0 0  ; 


; Name:            
; Defined at line: 205
; #Upvalues:       5
; #Parameters:     1
; Is_vararg:       0
; Max Stack Size:  17

       0 [-]: FASTCALL1 64 R0 L0; 
       1 [-]: MOVE R2 R0   ; var2 = var0
       2 [-]: GETIMPORT R1 1; var1 = 0x7B998233
       3 [-]: CALL R1 2 2  ; var1 = var1(var2)
L 0:   4 [-]: JUMPIFNOT R1 L1; goto L1 if not var1
       5 [-]: RETURN R0 0  ; 
L 1:   6 [-]: NEWTABLE R1 0 0; var1 = {}
       7 [-]: LOADN R4 1   ; var4 = 1
       8 [-]: GETUPVAL R5 0; var5 = upvalues[0]
       9 [-]: LENGTH R2 R5 ; var2 = #var5
      10 [-]: LOADN R3 1   ; var3 = 1
      11 [-]: FORNPREP R2 L3; nforprep start - [escape at L3] -- var2 = iterator
L 2:  12 [-]: LOADN R6 1   ; var6 = 1
      13 [-]: DIV R5 R6 R4 ; var5 = var6 / var4
      14 [-]: SUBK R7 R4 K3; var7 = var4 - 1
      15 [-]: MULK R6 R7 K2; var6 = var7 * 4
      16 [-]: ADDK R7 R6 K3; var7 = var6 + 1
      17 [-]: MUL R10 R4 R4; var10 = var4 * var4
      18 [-]: ADDK R9 R10 K3; var9 = var10 + 1
      19 [-]: GETIMPORT R10 6; var10 = 0x5BCED4C4[0x3630E649]
      20 [-]: LOADN R11 -1 ; var11 = -1
      21 [-]: LOADN R12 2  ; var12 = 2
      22 [-]: CALL R10 3 2 ; var10 = var10(var11, var12)
      23 [-]: ADD R8 R9 R10; var8 = var9 + var10
      24 [-]: SETTABLE R8 R1 R7; var8[var1] = var7
      25 [-]: ADDK R7 R6 K7; var7 = var6 + 2
      26 [-]: GETIMPORT R9 9; var9 = 0xC163F229
      27 [-]: LOADK R10 K10; var10 = 0.15000000596046448
      28 [-]: LOADK R11 K11; var11 = 0.25
      29 [-]: CALL R9 3 2  ; var9 = var9(var10, var11)
      30 [-]: MUL R8 R5 R9 ; var8 = var5 * var9
      31 [-]: SETTABLE R8 R1 R7; var8[var1] = var7
      32 [-]: ADDK R7 R6 K12; var7 = var6 + 3
      33 [-]: GETIMPORT R8 9; var8 = 0xC163F229
      34 [-]: LOADN R9 -3  ; var9 = -3
      35 [-]: LOADN R10 3  ; var10 = 3
      36 [-]: CALL R8 3 2  ; var8 = var8(var9, var10)
      37 [-]: SETTABLE R8 R1 R7; var8[var1] = var7
      38 [-]: ADDK R7 R6 K2; var7 = var6 + 4
      39 [-]: GETIMPORT R8 9; var8 = 0xC163F229
      40 [-]: LOADN R9 -1  ; var9 = -1
      41 [-]: LOADN R10 1  ; var10 = 1
      42 [-]: CALL R8 3 2  ; var8 = var8(var9, var10)
      43 [-]: SETTABLE R8 R1 R7; var8[var1] = var7
      44 [-]: FORNLOOP R2 L2; nforloop end - iterate + goto L2
L 3:  45 [-]: GETIMPORT R3 14; var3 = 0x2BC57C41
      46 [-]: FASTCALL1 64 R3 L4; 
      47 [-]: GETIMPORT R2 1; var2 = 0x7B998233
      48 [-]: CALL R2 2 2  ; var2 = var2(var3)
L 4:  49 [-]: JUMPIF R2 L5 ; goto L5 if var2
      50 [-]: GETIMPORT R2 14; var2 = 0x2BC57C41
      51 [-]: NAMECALL R2 R2 K15; var3 = var2; var2 = var2[0xD199E920]
      52 [-]: CALL R2 2 1  ; var2(var3)
L 5:  53 [-]: GETIMPORT R2 17; var2 = 0xEEFD714E
      54 [-]: GETIMPORT R4 19; var4 = 0x838B0418
      55 [-]: LOADN R5 2   ; var5 = 2
      56 [-]: NAMECALL R2 R2 K20; var3 = var2; var2 = var2[0x986D2AB8]
      57 [-]: CALL R2 4 1  ; var2(var3, var4, var5)
      58 [-]: GETIMPORT R2 17; var2 = 0xEEFD714E
      59 [-]: GETIMPORT R4 22; var4 = 0x868B08D1
      60 [-]: LOADN R5 1   ; var5 = 1
      61 [-]: NAMECALL R2 R2 K20; var3 = var2; var2 = var2[0x986D2AB8]
      62 [-]: CALL R2 4 1  ; var2(var3, var4, var5)
      63 [-]: GETIMPORT R3 24; var3 = 0x334AFF38
      64 [-]: FASTCALL1 64 R3 L6; 
      65 [-]: GETIMPORT R2 1; var2 = 0x7B998233
      66 [-]: CALL R2 2 2  ; var2 = var2(var3)
L 6:  67 [-]: JUMPIF R2 L7 ; goto L7 if var2
      68 [-]: GETIMPORT R2 24; var2 = 0x334AFF38
      69 [-]: GETUPVAL R4 1; var4 = upvalues[1]
      70 [-]: LOADN R5 1   ; var5 = 1
      71 [-]: LOADN R6 1   ; var6 = 1
      72 [-]: LOADN R7 1   ; var7 = 1
      73 [-]: LOADN R8 1   ; var8 = 1
      74 [-]: NAMECALL R2 R2 K20; var3 = var2; var2 = var2[0x986D2AB8]
      75 [-]: CALL R2 7 1  ; var2(var3, var4, var5, var6, var7, var8)
L 7:  76 [-]: GETIMPORT R2 17; var2 = 0xEEFD714E
      77 [-]: GETUPVAL R4 2; var4 = upvalues[2]
      78 [-]: LOADN R5 1   ; var5 = 1
      79 [-]: NAMECALL R2 R2 K20; var3 = var2; var2 = var2[0x986D2AB8]
      80 [-]: CALL R2 4 1  ; var2(var3, var4, var5)
L 8:  81 [-]: GETIMPORT R2 27; var2 = _T["FullscreenOverlayTransmissionAmplitude"]
      82 [-]: JUMPIF R2 L9 ; goto L9 if var2
      83 [-]: LOADN R2 0   ; var2 = 0
L 9:  84 [-]: GETIMPORT R4 24; var4 = 0x334AFF38
      85 [-]: FASTCALL1 64 R4 L10; 
      86 [-]: GETIMPORT R3 1; var3 = 0x7B998233
      87 [-]: CALL R3 2 2  ; var3 = var3(var4)
L10:  88 [-]: JUMPIF R3 L11; goto L11 if var3
      89 [-]: GETIMPORT R3 24; var3 = 0x334AFF38
      90 [-]: GETUPVAL R5 3; var5 = upvalues[3]
      91 [-]: LOADK R7 K11 ; var7 = 0.25
      92 [-]: MULK R8 R2 K2; var8 = var2 * 4
      93 [-]: ADD R6 R7 R8 ; var6 = var7 + var8
      94 [-]: NAMECALL R3 R3 K20; var4 = var3; var3 = var3[0x986D2AB8]
      95 [-]: CALL R3 4 1  ; var3(var4, var5, var6)
L11:  96 [-]: GETIMPORT R4 17; var4 = 0xEEFD714E
      97 [-]: FASTCALL1 64 R4 L12; 
      98 [-]: GETIMPORT R3 1; var3 = 0x7B998233
      99 [-]: CALL R3 2 2  ; var3 = var3(var4)
L12: 100 [-]: JUMPIF R3 L15; goto L15 if var3
     101 [-]: GETIMPORT R3 17; var3 = 0xEEFD714E
     102 [-]: GETIMPORT R5 30; var5 = 0x6C97A788["UNLIT_ATTEN"]
     103 [-]: LOADK R7 K11 ; var7 = 0.25
     104 [-]: MULK R8 R2 K2; var8 = var2 * 4
     105 [-]: ADD R6 R7 R8 ; var6 = var7 + var8
     106 [-]: NAMECALL R3 R3 K20; var4 = var3; var3 = var3[0x986D2AB8]
     107 [-]: CALL R3 4 1  ; var3(var4, var5, var6)
     108 [-]: GETIMPORT R3 17; var3 = 0xEEFD714E
     109 [-]: GETUPVAL R5 4; var5 = upvalues[4]
     110 [-]: MULK R6 R2 K31; var6 = var2 * 0.039999999105930328
     111 [-]: NAMECALL R3 R3 K20; var4 = var3; var3 = var3[0x986D2AB8]
     112 [-]: CALL R3 4 1  ; var3(var4, var5, var6)
     113 [-]: LOADN R5 1   ; var5 = 1
     114 [-]: GETUPVAL R6 0; var6 = upvalues[0]
     115 [-]: LENGTH R3 R6 ; var3 = #var6
     116 [-]: LOADN R4 1   ; var4 = 1
     117 [-]: FORNPREP R3 L15; nforprep start - [escape at L15] -- var3 = iterator
L13: 118 [-]: SUBK R7 R5 K3; var7 = var5 - 1
     119 [-]: MULK R6 R7 K2; var6 = var7 * 4
     120 [-]: GETIMPORT R7 33; var7 = 0x42DCC9F5
     121 [-]: LOADN R9 4   ; var9 = 4
     122 [-]: GETIMPORT R10 35; var10 = 0xDFEBB754
     123 [-]: GETIMPORT R12 37; var12 = 0x107BF6DA
     124 [-]: GETIMPORT R13 39; var13 = 0x55156FF7
     125 [-]: CALL R13 1 0 ; var13, ... = var13()
     126 [-]: CALL R12 0 2 ; var12 = var12(var13, ...)
     127 [-]: MUL R11 R5 R12; var11 = var5 * var12
     128 [-]: CALL R10 2 2 ; var10 = var10(var11)
     129 [-]: MUL R8 R9 R10; var8 = var9 * var10
     130 [-]: LOADK R9 K40 ; var9 = 0.5
     131 [-]: LOADN R10 1  ; var10 = 1
     132 [-]: CALL R7 4 2  ; var7 = var7(var8, var9, var10)
     133 [-]: GETIMPORT R8 17; var8 = 0xEEFD714E
     134 [-]: GETUPVAL R11 0; var11 = upvalues[0]
     135 [-]: GETTABLE R10 R11 R5; var10 = var11[var5]
     136 [-]: ADDK R12 R6 K3; var12 = var6 + 1
     137 [-]: GETTABLE R11 R1 R12; var11 = var1[var12]
     138 [-]: LOADN R15 1  ; var15 = 1
     139 [-]: FASTCALL2 19 R15 R2 L14; 
     140 [-]: MOVE R16 R2  ; var16 = var2
     141 [-]: GETIMPORT R14 42; var14 = 0x5BCED4C4[0xAC1B386A]
     142 [-]: CALL R14 3 2 ; var14 = var14(var15, var16)
L14: 143 [-]: MUL R13 R7 R14; var13 = var7 * var14
     144 [-]: ADDK R15 R6 K7; var15 = var6 + 2
     145 [-]: GETTABLE R14 R1 R15; var14 = var1[var15]
     146 [-]: MUL R12 R13 R14; var12 = var13 * var14
     147 [-]: MULK R14 R7 K43; var14 = var7 * 12
     148 [-]: ADDK R16 R6 K12; var16 = var6 + 3
     149 [-]: GETTABLE R15 R1 R16; var15 = var1[var16]
     150 [-]: ADD R13 R14 R15; var13 = var14 + var15
     151 [-]: ADDK R15 R6 K2; var15 = var6 + 4
     152 [-]: GETTABLE R14 R1 R15; var14 = var1[var15]
     153 [-]: NAMECALL R8 R8 K20; var9 = var8; var8 = var8[0x986D2AB8]
     154 [-]: CALL R8 7 1  ; var8(var9, var10, var11, var12, var13, var14)
     155 [-]: FORNLOOP R3 L13; nforloop end - iterate + goto L13
L15: 156 [-]: GETIMPORT R4 45; var4 = 0x34BF6C85
     157 [-]: FASTCALL1 64 R4 L16; 
     158 [-]: GETIMPORT R3 1; var3 = 0x7B998233
     159 [-]: CALL R3 2 2  ; var3 = var3(var4)
L16: 160 [-]: JUMPIF R3 L17; goto L17 if var3
     161 [-]: GETIMPORT R3 45; var3 = 0x34BF6C85
     162 [-]: LOADK R6 K11 ; var6 = 0.25
     163 [-]: MULK R7 R2 K2; var7 = var2 * 4
     164 [-]: ADD R5 R6 R7 ; var5 = var6 + var7
     165 [-]: NAMECALL R3 R3 K46; var4 = var3; var3 = var3[0x178D8B0F]
     166 [-]: CALL R3 3 1  ; var3(var4, var5)
L17: 167 [-]: GETIMPORT R4 14; var4 = 0x2BC57C41
     168 [-]: FASTCALL1 64 R4 L18; 
     169 [-]: GETIMPORT R3 1; var3 = 0x7B998233
     170 [-]: CALL R3 2 2  ; var3 = var3(var4)
L18: 171 [-]: JUMPIF R3 L19; goto L19 if var3
     172 [-]: GETIMPORT R3 14; var3 = 0x2BC57C41
     173 [-]: MULK R5 R2 K12; var5 = var2 * 3
     174 [-]: NAMECALL R3 R3 K47; var4 = var3; var3 = var3[0xE29E950D]
     175 [-]: CALL R3 3 1  ; var3(var4, var5)
L19: 176 [-]: GETIMPORT R3 49; var3 = 0xCBD666E1
     177 [-]: LOADN R4 0   ; var4 = 0
     178 [-]: CALL R3 2 1  ; var3(var4)
     179 [-]: JUMPBACK L8  ; goto L8
     180 [-]: RETURN R0 0  ; 


; Name:            
; Defined at line: 262
; #Upvalues:       2
; #Parameters:     0
; Is_vararg:       0
; Max Stack Size:  6

       0 [-]: NEWTABLE R0 0 0; var0 = {}
       1 [-]: SETUPVAL R0 0; upvalues[0] = var0
       2 [-]: GETUPVAL R1 0; var1 = upvalues[0]
       3 [-]: FASTCALL2K 52 R1 K0 L0; 
       4 [-]: LOADK R2 K0  ; var2 = 0
       5 [-]: GETIMPORT R0 3; var0 = 0x33BDD652[0x23D5322F]
       6 [-]: CALL R0 3 1  ; var0(var1, var2)
L 0:   7 [-]: LOADN R2 1   ; var2 = 1
       8 [-]: GETIMPORT R3 5; var3 = 0xA0586859
       9 [-]: LENGTH R0 R3 ; var0 = #var3
      10 [-]: LOADN R1 1   ; var1 = 1
      11 [-]: FORNPREP R0 L4; nforprep start - [escape at L4] -- var0 = iterator
L 1:  12 [-]: GETIMPORT R5 5; var5 = 0xA0586859
      13 [-]: GETTABLE R4 R5 R2; var4 = var5[var2]
      14 [-]: FASTCALL1 64 R4 L2; 
      15 [-]: GETIMPORT R3 7; var3 = 0x7B998233
      16 [-]: CALL R3 2 2  ; var3 = var3(var4)
L 2:  17 [-]: JUMPIFNOT R3 L3; goto L3 if not var3
      18 [-]: GETUPVAL R4 0; var4 = upvalues[0]
      19 [-]: FASTCALL2 52 R4 R2 L3; 
      20 [-]: MOVE R5 R2   ; var5 = var2
      21 [-]: GETIMPORT R3 3; var3 = 0x33BDD652[0x23D5322F]
      22 [-]: CALL R3 3 1  ; var3(var4, var5)
L 3:  23 [-]: FORNLOOP R0 L1; nforloop end - iterate + goto L1
L 4:  24 [-]: GETUPVAL R1 1; var1 = upvalues[1]
      25 [-]: GETTABLEKS R0 R1 K8; var0 = var1[0x622A0C19]
      26 [-]: GETUPVAL R1 0; var1 = upvalues[0]
      27 [-]: CALL R0 2 1  ; var0(var1)
      28 [-]: RETURN R0 0  ; 


; Name:            
; Defined at line: 273
; #Upvalues:       2
; #Parameters:     0
; Is_vararg:       0
; Max Stack Size:  7

       0 [-]: NEWTABLE R0 0 0; var0 = {}
       1 [-]: SETUPVAL R0 0; upvalues[0] = var0
       2 [-]: LOADN R2 1   ; var2 = 1
       3 [-]: GETIMPORT R3 1; var3 = 0x89D56873
       4 [-]: LENGTH R0 R3 ; var0 = #var3
       5 [-]: LOADN R1 1   ; var1 = 1
       6 [-]: FORNPREP R0 L3; nforprep start - [escape at L3] -- var0 = iterator
L 0:   7 [-]: GETIMPORT R5 1; var5 = 0x89D56873
       8 [-]: GETTABLE R4 R5 R2; var4 = var5[var2]
       9 [-]: FASTCALL1 64 R4 L1; 
      10 [-]: GETIMPORT R3 3; var3 = 0x7B998233
      11 [-]: CALL R3 2 2  ; var3 = var3(var4)
L 1:  12 [-]: JUMPIF R3 L2 ; goto L2 if var3
      13 [-]: GETUPVAL R4 0; var4 = upvalues[0]
      14 [-]: FASTCALL2 52 R4 R2 L2; 
      15 [-]: MOVE R5 R2   ; var5 = var2
      16 [-]: GETIMPORT R3 6; var3 = 0x33BDD652[0x23D5322F]
      17 [-]: CALL R3 3 1  ; var3(var4, var5)
L 2:  18 [-]: FORNLOOP R0 L0; nforloop end - iterate + goto L0
L 3:  19 [-]: GETIMPORT R0 9; var0 = _T["QuestRadioChatter"]
      20 [-]: JUMPIFNOT R0 L6; goto L6 if not var0
      21 [-]: GETIMPORT R1 9; var1 = _T["QuestRadioChatter"]
      22 [-]: LENGTH R0 R1 ; var0 = #var1
      23 [-]: LOADN R1 0   ; var1 = 0
      24 [-]: JUMPIFNOTLT R1 R0 L6; goto L6 if var1 >= var316
      25 [-]: GETUPVAL R1 0; var1 = upvalues[0]
      26 [-]: LENGTH R0 R1 ; var0 = #var1
      27 [-]: LOADN R3 1   ; var3 = 1
      28 [-]: GETIMPORT R4 9; var4 = _T["QuestRadioChatter"]
      29 [-]: LENGTH R1 R4 ; var1 = #var4
      30 [-]: LOADN R2 1   ; var2 = 1
      31 [-]: FORNPREP R1 L6; nforprep start - [escape at L6] -- var1 = iterator
L 4:  32 [-]: GETUPVAL R5 0; var5 = upvalues[0]
      33 [-]: ADD R6 R0 R3 ; var6 = var0 + var3
      34 [-]: FASTCALL2 52 R5 R6 L5; 
      35 [-]: GETIMPORT R4 6; var4 = 0x33BDD652[0x23D5322F]
      36 [-]: CALL R4 3 1  ; var4(var5, var6)
L 5:  37 [-]: FORNLOOP R1 L4; nforloop end - iterate + goto L4
L 6:  38 [-]: GETUPVAL R1 1; var1 = upvalues[1]
      39 [-]: GETTABLEKS R0 R1 K10; var0 = var1[0x622A0C19]
      40 [-]: GETUPVAL R1 0; var1 = upvalues[0]
      41 [-]: CALL R0 2 1  ; var0(var1)
      42 [-]: RETURN R0 0  ; 


; Name:            
; Defined at line: 291
; #Upvalues:       2
; #Parameters:     0
; Is_vararg:       0
; Max Stack Size:  6

       0 [-]: NEWTABLE R0 0 0; var0 = {}
       1 [-]: SETUPVAL R0 0; upvalues[0] = var0
       2 [-]: GETUPVAL R1 0; var1 = upvalues[0]
       3 [-]: FASTCALL2K 52 R1 K0 L0; 
       4 [-]: LOADK R2 K0  ; var2 = 0
       5 [-]: GETIMPORT R0 3; var0 = 0x33BDD652[0x23D5322F]
       6 [-]: CALL R0 3 1  ; var0(var1, var2)
L 0:   7 [-]: LOADN R2 1   ; var2 = 1
       8 [-]: GETIMPORT R3 5; var3 = 0x59432AE2
       9 [-]: LENGTH R0 R3 ; var0 = #var3
      10 [-]: LOADN R1 1   ; var1 = 1
      11 [-]: FORNPREP R0 L4; nforprep start - [escape at L4] -- var0 = iterator
L 1:  12 [-]: GETIMPORT R5 5; var5 = 0x59432AE2
      13 [-]: GETTABLE R4 R5 R2; var4 = var5[var2]
      14 [-]: FASTCALL1 64 R4 L2; 
      15 [-]: GETIMPORT R3 7; var3 = 0x7B998233
      16 [-]: CALL R3 2 2  ; var3 = var3(var4)
L 2:  17 [-]: JUMPIFNOT R3 L3; goto L3 if not var3
      18 [-]: GETUPVAL R4 0; var4 = upvalues[0]
      19 [-]: FASTCALL2 52 R4 R2 L3; 
      20 [-]: MOVE R5 R2   ; var5 = var2
      21 [-]: GETIMPORT R3 3; var3 = 0x33BDD652[0x23D5322F]
      22 [-]: CALL R3 3 1  ; var3(var4, var5)
L 3:  23 [-]: FORNLOOP R0 L1; nforloop end - iterate + goto L1
L 4:  24 [-]: GETUPVAL R1 1; var1 = upvalues[1]
      25 [-]: GETTABLEKS R0 R1 K8; var0 = var1[0x622A0C19]
      26 [-]: GETUPVAL R1 0; var1 = upvalues[0]
      27 [-]: CALL R0 2 1  ; var0(var1)
      28 [-]: RETURN R0 0  ; 


; Name:            
; Defined at line: 302
; #Upvalues:       3
; #Parameters:     1
; Is_vararg:       0
; Max Stack Size:  7

       0 [-]: GETUPVAL R2 0; var2 = upvalues[0]
       1 [-]: LENGTH R1 R2 ; var1 = #var2
       2 [-]: LOADN R2 1   ; var2 = 1
       3 [-]: JUMPIFNOTLT R1 R2 L0; goto L0 if var1 >= var65852
       4 [-]: GETUPVAL R1 1; var1 = upvalues[1]
       5 [-]: CALL R1 1 1  ; var1()
       6 [-]: RETURN R0 0  ; 
L 0:   7 [-]: GETUPVAL R3 0; var3 = upvalues[0]
       8 [-]: GETUPVAL R5 0; var5 = upvalues[0]
       9 [-]: LENGTH R4 R5 ; var4 = #var5
      10 [-]: GETTABLE R2 R3 R4; var2 = var3[var4]
      11 [-]: ADDK R1 R2 K0; var1 = var2 + 1
      12 [-]: GETIMPORT R2 3; var2 = 0x33BDD652[0x9C1F3B5A]
      13 [-]: GETUPVAL R3 0; var3 = upvalues[0]
      14 [-]: GETUPVAL R5 0; var5 = upvalues[0]
      15 [-]: LENGTH R4 R5 ; var4 = #var5
      16 [-]: CALL R2 3 1  ; var2(var3, var4)
      17 [-]: GETIMPORT R3 5; var3 = 0xA0586859
      18 [-]: GETTABLE R2 R3 R1; var2 = var3[var1]
L 1:  19 [-]: FASTCALL1 64 R2 L2; 
      20 [-]: MOVE R4 R2   ; var4 = var2
      21 [-]: GETIMPORT R3 7; var3 = 0x7B998233
      22 [-]: CALL R3 2 2  ; var3 = var3(var4)
L 2:  23 [-]: JUMPIF R3 L3 ; goto L3 if var3
      24 [-]: GETUPVAL R3 2; var3 = upvalues[2]
      25 [-]: MOVE R4 R0   ; var4 = var0
      26 [-]: MOVE R5 R2   ; var5 = var2
      27 [-]: CALL R3 3 1  ; var3(var4, var5)
      28 [-]: GETIMPORT R3 9; var3 = 0xCBD666E1
      29 [-]: GETIMPORT R4 12; var4 = 0x5BCED4C4[0x3630E649]
      30 [-]: GETIMPORT R5 14; var5 = 0xA4B2F57C
      31 [-]: GETIMPORT R6 16; var6 = 0xAE3A6E72
      32 [-]: CALL R4 3 0  ; var4, ... = var4(var5, var6)
      33 [-]: CALL R3 0 1  ; var3(var4, ...)
      34 [-]: ADDK R1 R1 K0; var1 = var1 + 1
      35 [-]: GETIMPORT R3 5; var3 = 0xA0586859
      36 [-]: GETTABLE R2 R3 R1; var2 = var3[var1]
      37 [-]: JUMPBACK L1  ; goto L1
L 3:  38 [-]: RETURN R0 0  ; 


; Name:            
; Defined at line: 321
; #Upvalues:       3
; #Parameters:     1
; Is_vararg:       0
; Max Stack Size:  7

       0 [-]: GETUPVAL R2 0; var2 = upvalues[0]
       1 [-]: LENGTH R1 R2 ; var1 = #var2
       2 [-]: LOADN R2 1   ; var2 = 1
       3 [-]: JUMPIFNOTLT R1 R2 L0; goto L0 if var1 >= var65852
       4 [-]: GETUPVAL R1 1; var1 = upvalues[1]
       5 [-]: CALL R1 1 1  ; var1()
       6 [-]: RETURN R0 0  ; 
L 0:   7 [-]: LOADNIL R1   ; var1 = nil
       8 [-]: GETUPVAL R3 0; var3 = upvalues[0]
       9 [-]: GETUPVAL R5 0; var5 = upvalues[0]
      10 [-]: LENGTH R4 R5 ; var4 = #var5
      11 [-]: GETTABLE R2 R3 R4; var2 = var3[var4]
      12 [-]: GETIMPORT R4 1; var4 = 0x89D56873
      13 [-]: LENGTH R3 R4 ; var3 = #var4
      14 [-]: JUMPIFNOTLE R2 R3 L1; goto L1 if var2 > var66337
      15 [-]: GETIMPORT R3 1; var3 = 0x89D56873
      16 [-]: GETTABLE R1 R3 R2; var1 = var3[var2]
      17 [-]: JUMP L2      ; goto L2
L 1:  18 [-]: GETIMPORT R3 4; var3 = _T["QuestRadioChatter"]
      19 [-]: JUMPIFNOT R3 L2; goto L2 if not var3
      20 [-]: GETIMPORT R4 4; var4 = _T["QuestRadioChatter"]
      21 [-]: LENGTH R3 R4 ; var3 = #var4
      22 [-]: LOADN R4 0   ; var4 = 0
      23 [-]: JUMPIFNOTLT R4 R3 L2; goto L2 if var4 >= var66593
      24 [-]: GETIMPORT R4 1; var4 = 0x89D56873
      25 [-]: LENGTH R3 R4 ; var3 = #var4
      26 [-]: SUB R2 R2 R3 ; var2 = var2 - var3
      27 [-]: GETIMPORT R3 4; var3 = _T["QuestRadioChatter"]
      28 [-]: GETTABLE R1 R3 R2; var1 = var3[var2]
L 2:  29 [-]: GETIMPORT R3 7; var3 = 0x33BDD652[0x9C1F3B5A]
      30 [-]: GETUPVAL R4 0; var4 = upvalues[0]
      31 [-]: GETUPVAL R6 0; var6 = upvalues[0]
      32 [-]: LENGTH R5 R6 ; var5 = #var6
      33 [-]: CALL R3 3 1  ; var3(var4, var5)
      34 [-]: GETUPVAL R3 2; var3 = upvalues[2]
      35 [-]: MOVE R4 R0   ; var4 = var0
      36 [-]: MOVE R5 R1   ; var5 = var1
      37 [-]: CALL R3 3 1  ; var3(var4, var5)
      38 [-]: RETURN R0 0  ; 


; Name:            
; Defined at line: 340
; #Upvalues:       3
; #Parameters:     1
; Is_vararg:       0
; Max Stack Size:  11

       0 [-]: GETUPVAL R2 0; var2 = upvalues[0]
       1 [-]: LENGTH R1 R2 ; var1 = #var2
       2 [-]: LOADN R2 1   ; var2 = 1
       3 [-]: JUMPIFNOTLT R1 R2 L0; goto L0 if var1 >= var65852
       4 [-]: GETUPVAL R1 1; var1 = upvalues[1]
       5 [-]: CALL R1 1 1  ; var1()
       6 [-]: RETURN R0 0  ; 
L 0:   7 [-]: GETUPVAL R3 0; var3 = upvalues[0]
       8 [-]: GETUPVAL R5 0; var5 = upvalues[0]
       9 [-]: LENGTH R4 R5 ; var4 = #var5
      10 [-]: GETTABLE R2 R3 R4; var2 = var3[var4]
      11 [-]: ADDK R1 R2 K0; var1 = var2 + 1
      12 [-]: GETIMPORT R2 3; var2 = 0x33BDD652[0x9C1F3B5A]
      13 [-]: GETUPVAL R3 0; var3 = upvalues[0]
      14 [-]: GETUPVAL R5 0; var5 = upvalues[0]
      15 [-]: LENGTH R4 R5 ; var4 = #var5
      16 [-]: CALL R2 3 1  ; var2(var3, var4)
      17 [-]: GETIMPORT R3 5; var3 = 0x59432AE2
      18 [-]: GETTABLE R2 R3 R1; var2 = var3[var1]
      19 [-]: FASTCALL1 64 R2 L1; 
      20 [-]: MOVE R4 R2   ; var4 = var2
      21 [-]: GETIMPORT R3 7; var3 = 0x7B998233
      22 [-]: CALL R3 2 2  ; var3 = var3(var4)
L 1:  23 [-]: JUMPIF R3 L11; goto L11 if var3
      24 [-]: FASTCALL1 64 R0 L2; 
      25 [-]: MOVE R4 R0   ; var4 = var0
      26 [-]: GETIMPORT R3 7; var3 = 0x7B998233
      27 [-]: CALL R3 2 2  ; var3 = var3(var4)
L 2:  28 [-]: JUMPIF R3 L11; goto L11 if var3
      29 [-]: GETIMPORT R5 9; var5 = 0xE08B556F
      30 [-]: LOADB R6 0   ; var6 = false
      31 [-]: LOADN R7 1   ; var7 = 1
      32 [-]: LOADB R8 0   ; var8 = false
      33 [-]: NAMECALL R3 R0 K10; var4 = var0; var3 = var0[0x659D451F]
      34 [-]: CALL R3 6 2  ; var3 = var3(var4, var5, var6, var7, var8)
      35 [-]: GETIMPORT R4 12; var4 = 0xCBD666E1
      36 [-]: LOADN R5 2   ; var5 = 2
      37 [-]: CALL R4 2 1  ; var4(var5)
      38 [-]: GETIMPORT R6 14; var6 = 0x9AACB9C8
      39 [-]: LOADB R7 0   ; var7 = false
      40 [-]: LOADN R8 1   ; var8 = 1
      41 [-]: LOADB R9 0   ; var9 = false
      42 [-]: NAMECALL R4 R0 K10; var5 = var0; var4 = var0[0x659D451F]
      43 [-]: CALL R4 6 2  ; var4 = var4(var5, var6, var7, var8, var9)
L 3:  44 [-]: FASTCALL1 64 R2 L4; 
      45 [-]: MOVE R6 R2   ; var6 = var2
      46 [-]: GETIMPORT R5 7; var5 = 0x7B998233
      47 [-]: CALL R5 2 2  ; var5 = var5(var6)
L 4:  48 [-]: JUMPIF R5 L5 ; goto L5 if var5
      49 [-]: GETUPVAL R5 2; var5 = upvalues[2]
      50 [-]: MOVE R6 R0   ; var6 = var0
      51 [-]: MOVE R7 R2   ; var7 = var2
      52 [-]: CALL R5 3 1  ; var5(var6, var7)
      53 [-]: ADDK R1 R1 K0; var1 = var1 + 1
      54 [-]: GETIMPORT R5 5; var5 = 0x59432AE2
      55 [-]: GETTABLE R2 R5 R1; var2 = var5[var1]
      56 [-]: JUMPBACK L3  ; goto L3
L 5:  57 [-]: FASTCALL1 64 R3 L6; 
      58 [-]: MOVE R6 R3   ; var6 = var3
      59 [-]: GETIMPORT R5 7; var5 = 0x7B998233
      60 [-]: CALL R5 2 2  ; var5 = var5(var6)
L 6:  61 [-]: JUMPIF R5 L7 ; goto L7 if var5
      62 [-]: LOADB R7 0   ; var7 = false
      63 [-]: NAMECALL R5 R3 K15; var6 = var3; var5 = var3[0x6CF1E476]
      64 [-]: CALL R5 3 1  ; var5(var6, var7)
L 7:  65 [-]: FASTCALL1 64 R4 L8; 
      66 [-]: MOVE R6 R4   ; var6 = var4
      67 [-]: GETIMPORT R5 7; var5 = 0x7B998233
      68 [-]: CALL R5 2 2  ; var5 = var5(var6)
L 8:  69 [-]: JUMPIF R5 L9 ; goto L9 if var5
      70 [-]: LOADB R7 0   ; var7 = false
      71 [-]: NAMECALL R5 R4 K15; var6 = var4; var5 = var4[0x6CF1E476]
      72 [-]: CALL R5 3 1  ; var5(var6, var7)
L 9:  73 [-]: GETIMPORT R6 17; var6 = 0x334AFF38
      74 [-]: FASTCALL1 64 R6 L10; 
      75 [-]: GETIMPORT R5 7; var5 = 0x7B998233
      76 [-]: CALL R5 2 2  ; var5 = var5(var6)
L10:  77 [-]: JUMPIF R5 L11; goto L11 if var5
      78 [-]: GETIMPORT R5 17; var5 = 0x334AFF38
      79 [-]: GETIMPORT R7 19; var7 = 0x5B6D2DEE
      80 [-]: LOADB R8 1   ; var8 = true
      81 [-]: LOADN R9 1   ; var9 = 1
      82 [-]: LOADB R10 0  ; var10 = false
      83 [-]: NAMECALL R5 R5 K10; var6 = var5; var5 = var5[0x659D451F]
      84 [-]: CALL R5 6 1  ; var5(var6, var7, var8, var9, var10)
L11:  85 [-]: RETURN R0 0  ; 


; Name:            
; Defined at line: 375
; #Upvalues:       0
; #Parameters:     1
; Is_vararg:       0
; Max Stack Size:  3

       0 [-]: GETIMPORT R1 1; var1 = 0x3D106989
       1 [-]: LOADK R2 K2  ; var2 = "RadioChatter::OnProfileSaved"
       2 [-]: CALL R1 2 1  ; var1(var2)
       3 [-]: JUMPIF R0 L0 ; goto L0 if var0
       4 [-]: GETIMPORT R1 1; var1 = 0x3D106989
       5 [-]: LOADK R2 K3  ; var2 = "ERROR: Profile failed to save"
       6 [-]: CALL R1 2 1  ; var1(var2)
L 0:   7 [-]: RETURN R0 0  ; 


; Name:            
; Defined at line: 382
; #Upvalues:       4
; #Parameters:     2
; Is_vararg:       0
; Max Stack Size:  5

       0 [-]: LOADN R2 0   ; var2 = 0
L 0:   1 [-]: JUMPIFNOTLT R2 R1 L5; goto L5 if var2 >= var66337
       2 [-]: GETIMPORT R3 1; var3 = 0xB693B6C1
       3 [-]: CALL R3 1 2  ; var3 = var3()
       4 [-]: ADD R2 R2 R3 ; var2 = var2 + var3
       5 [-]: GETUPVAL R3 0; var3 = upvalues[0]
       6 [-]: JUMPXEQKB R3 1 L2 NOT; 
       7 [-]: GETIMPORT R3 4; var3 = _T["RadioChatterDisabled"]
       8 [-]: JUMPXEQKB R3 0 L2 NOT; 
       9 [-]: GETIMPORT R3 4; var3 = _T["RadioChatterDisabled"]
      10 [-]: SETUPVAL R3 0; upvalues[3] = var0
      11 [-]: GETIMPORT R3 6; var3 = _T["RadioChatter_SuppressEnableChatter"]
      12 [-]: JUMPIF R3 L1 ; goto L1 if var3
      13 [-]: GETUPVAL R3 1; var3 = upvalues[1]
      14 [-]: MOVE R4 R0   ; var4 = var0
      15 [-]: CALL R3 2 1  ; var3(var4)
      16 [-]: LOADB R3 0   ; var3 = false
      17 [-]: RETURN R3 1  ; 
L 1:  18 [-]: GETIMPORT R3 7; var3 = _T
      19 [-]: LOADNIL R4   ; var4 = nil
      20 [-]: SETTABLEKS R4 R3 K5; var4["RadioChatter_SuppressEnableChatter"] = var3
      21 [-]: GETUPVAL R3 2; var3 = upvalues[2]
      22 [-]: CALL R3 1 1  ; var3()
      23 [-]: JUMP L4      ; goto L4
L 2:  24 [-]: GETUPVAL R3 0; var3 = upvalues[0]
      25 [-]: JUMPXEQKB R3 0 L3 NOT; 
      26 [-]: GETIMPORT R3 4; var3 = _T["RadioChatterDisabled"]
      27 [-]: JUMPXEQKB R3 1 L3 NOT; 
      28 [-]: GETUPVAL R3 3; var3 = upvalues[3]
      29 [-]: CALL R3 1 1  ; var3()
      30 [-]: GETIMPORT R3 4; var3 = _T["RadioChatterDisabled"]
      31 [-]: SETUPVAL R3 0; upvalues[3] = var0
      32 [-]: LOADB R3 0   ; var3 = false
      33 [-]: RETURN R3 1  ; 
L 3:  34 [-]: GETIMPORT R3 9; var3 = 0xCBD666E1
      35 [-]: LOADN R4 0   ; var4 = 0
      36 [-]: CALL R3 2 1  ; var3(var4)
L 4:  37 [-]: JUMPBACK L0  ; goto L0
L 5:  38 [-]: LOADB R3 1   ; var3 = true
      39 [-]: RETURN R3 1  ; 


; Name:            
; Defined at line: 405
; #Upvalues:       0
; #Parameters:     0
; Is_vararg:       0
; Max Stack Size:  3

       0 [-]: GETIMPORT R0 2; var0 = _T["questInfo"]
       1 [-]: JUMPXEQKNIL R0 L1; 
       2 [-]: GETTABLEKS R2 R0 K3; var2 = var0["activeQuest"]
       3 [-]: FASTCALL1 64 R2 L0; 
       4 [-]: GETIMPORT R1 5; var1 = 0x7B998233
       5 [-]: CALL R1 2 2  ; var1 = var1(var2)
L 0:   6 [-]: JUMPIF R1 L1 ; goto L1 if var1
       7 [-]: LOADB R1 1   ; var1 = true
       8 [-]: RETURN R1 1  ; 
L 1:   9 [-]: LOADB R1 0   ; var1 = false
      10 [-]: RETURN R1 1  ; 


; Name:            
; Defined at line: 414
; #Upvalues:       12
; #Parameters:     1
; Is_vararg:       0
; Max Stack Size:  11

       0 [-]: GETUPVAL R1 0; var1 = upvalues[0]
       1 [-]: CALL R1 1 1  ; var1()
       2 [-]: GETIMPORT R1 1; var1 = _T
       3 [-]: SETTABLEKS R0 R1 K2; var0["chatterTrigger"] = var1
L 0:   4 [-]: GETIMPORT R1 4; var1 = 0x76EA806B
       5 [-]: NAMECALL R1 R1 K5; var2 = var1; var1 = var1[0x8792AAAB]
       6 [-]: CALL R1 2 2  ; var1 = var1(var2)
       7 [-]: JUMPIF R1 L1 ; goto L1 if var1
       8 [-]: GETIMPORT R1 7; var1 = 0xCBD666E1
       9 [-]: LOADN R2 1   ; var2 = 1
      10 [-]: CALL R1 2 1  ; var1(var2)
      11 [-]: JUMPBACK L0  ; goto L0
L 1:  12 [-]: GETIMPORT R1 4; var1 = 0x76EA806B
      13 [-]: LOADN R3 0   ; var3 = 0
      14 [-]: NAMECALL R1 R1 K8; var2 = var1; var1 = var1[0x3F3AE64C]
      15 [-]: CALL R1 3 2  ; var1 = var1(var2, var3)
      16 [-]: FASTCALL1 64 R1 L2; 
      17 [-]: MOVE R3 R1   ; var3 = var1
      18 [-]: GETIMPORT R2 10; var2 = 0x7B998233
      19 [-]: CALL R2 2 2  ; var2 = var2(var3)
L 2:  20 [-]: JUMPIFNOT R2 L3; goto L3 if not var2
      21 [-]: RETURN R0 0  ; 
L 3:  22 [-]: NAMECALL R2 R1 K11; var3 = var1; var2 = var1[0x80563238]
      23 [-]: CALL R2 2 2  ; var2 = var2(var3)
      24 [-]: FASTCALL1 64 R2 L4; 
      25 [-]: MOVE R4 R2   ; var4 = var2
      26 [-]: GETIMPORT R3 10; var3 = 0x7B998233
      27 [-]: CALL R3 2 2  ; var3 = var3(var4)
L 4:  28 [-]: JUMPIFNOT R3 L5; goto L5 if not var3
      29 [-]: RETURN R0 0  ; 
L 5:  30 [-]: FASTCALL1 64 R1 L6; 
      31 [-]: MOVE R4 R1   ; var4 = var1
      32 [-]: GETIMPORT R3 10; var3 = 0x7B998233
      33 [-]: CALL R3 2 2  ; var3 = var3(var4)
L 6:  34 [-]: JUMPIF R3 L7 ; goto L7 if var3
      35 [-]: NAMECALL R3 R1 K12; var4 = var1; var3 = var1[0x40E9C32B]
      36 [-]: CALL R3 2 2  ; var3 = var3(var4)
      37 [-]: GETIMPORT R4 1; var4 = _T
      38 [-]: NAMECALL R5 R3 K13; var6 = var3; var5 = var3[0xC65D7046]
      39 [-]: CALL R5 2 2  ; var5 = var5(var6)
      40 [-]: SETTABLEKS R5 R4 K14; var5["RadioChatterDisabled"] = var4
      41 [-]: GETIMPORT R4 15; var4 = _T["RadioChatterDisabled"]
      42 [-]: SETUPVAL R4 1; upvalues[4] = var1
L 7:  43 [-]: GETUPVAL R3 2; var3 = upvalues[2]
      44 [-]: CALL R3 1 1  ; var3()
      45 [-]: GETUPVAL R3 3; var3 = upvalues[3]
      46 [-]: CALL R3 1 1  ; var3()
      47 [-]: GETUPVAL R3 4; var3 = upvalues[4]
      48 [-]: CALL R3 1 1  ; var3()
L 8:  49 [-]: FASTCALL1 64 R2 L9; 
      50 [-]: MOVE R4 R2   ; var4 = var2
      51 [-]: GETIMPORT R3 10; var3 = 0x7B998233
      52 [-]: CALL R3 2 2  ; var3 = var3(var4)
L 9:  53 [-]: JUMPIF R3 L10; goto L10 if var3
      54 [-]: GETUPVAL R6 5; var6 = upvalues[5]
      55 [-]: GETTABLEKS R5 R6 K16; var5 = var6["SF_SOCIAL_MENU"]
      56 [-]: NAMECALL R3 R2 K17; var4 = var2; var3 = var2[0x4AE54C32]
      57 [-]: CALL R3 3 2  ; var3 = var3(var4, var5)
      58 [-]: JUMPIF R3 L10; goto L10 if var3
      59 [-]: GETIMPORT R3 7; var3 = 0xCBD666E1
      60 [-]: LOADN R4 1   ; var4 = 1
      61 [-]: CALL R3 2 1  ; var3(var4)
      62 [-]: JUMPBACK L8  ; goto L8
L10:  63 [-]: GETIMPORT R3 15; var3 = _T["RadioChatterDisabled"]
      64 [-]: JUMPIF R3 L11; goto L11 if var3
      65 [-]: GETUPVAL R3 6; var3 = upvalues[6]
      66 [-]: CALL R3 1 1  ; var3()
L11:  67 [-]: GETIMPORT R3 20; var3 = 0x34291F5C[0xE82B9B03]
      68 [-]: MOVE R4 R0   ; var4 = var0
      69 [-]: CALL R3 2 1  ; var3(var4)
      70 [-]: GETUPVAL R3 7; var3 = upvalues[7]
      71 [-]: MOVE R4 R0   ; var4 = var0
      72 [-]: GETIMPORT R5 22; var5 = 0x2CBBE8AF
      73 [-]: CALL R3 3 1  ; var3(var4, var5)
L12:  74 [-]: FASTCALL1 64 R2 L13; 
      75 [-]: MOVE R4 R2   ; var4 = var2
      76 [-]: GETIMPORT R3 10; var3 = 0x7B998233
      77 [-]: CALL R3 2 2  ; var3 = var3(var4)
L13:  78 [-]: JUMPIF R3 L31; goto L31 if var3
      79 [-]: FASTCALL1 64 R0 L14; 
      80 [-]: MOVE R4 R0   ; var4 = var0
      81 [-]: GETIMPORT R3 10; var3 = 0x7B998233
      82 [-]: CALL R3 2 2  ; var3 = var3(var4)
L14:  83 [-]: JUMPIF R3 L31; goto L31 if var3
      84 [-]: GETIMPORT R3 15; var3 = _T["RadioChatterDisabled"]
      85 [-]: JUMPIF R3 L30; goto L30 if var3
      86 [-]: GETIMPORT R4 24; var4 = _T["questInfo"]
      87 [-]: JUMPXEQKNIL R4 L16; 
      88 [-]: GETTABLEKS R6 R4 K25; var6 = var4["activeQuest"]
      89 [-]: FASTCALL1 64 R6 L15; 
      90 [-]: GETIMPORT R5 10; var5 = 0x7B998233
      91 [-]: CALL R5 2 2  ; var5 = var5(var6)
L15:  92 [-]: JUMPIF R5 L16; goto L16 if var5
      93 [-]: LOADB R3 1   ; var3 = true
      94 [-]: JUMP L17     ; goto L17
L16:  95 [-]: LOADB R3 0   ; var3 = false
L17:  96 [-]: JUMPIF R3 L30; goto L30 if var3
      97 [-]: GETIMPORT R3 27; var3 = _T["gShowingLoginScreen"]
      98 [-]: JUMPXEQKB R3 0 L30 NOT; 
      99 [-]: GETIMPORT R4 29; var4 = 0x0032441C
     100 [-]: GETTABLEKS R3 R4 K30; var3 = var4["CachedGoalInfo"]
     101 [-]: JUMPIFNOT R3 L27; goto L27 if not var3
     102 [-]: NAMECALL R3 R2 K31; var4 = var2; var3 = var2[0x972D2737]
     103 [-]: CALL R3 2 2  ; var3 = var3(var4)
     104 [-]: JUMPIF R3 L27; goto L27 if var3
     105 [-]: GETUPVAL R3 7; var3 = upvalues[7]
     106 [-]: MOVE R4 R0   ; var4 = var0
     107 [-]: LOADN R5 25  ; var5 = 25
     108 [-]: CALL R3 3 2  ; var3 = var3(var4, var5)
     109 [-]: JUMPIFNOT R3 L30; goto L30 if not var3
L18: 110 [-]: GETIMPORT R3 33; var3 = _T["QueuedTransmissions"]
     111 [-]: JUMPIFNOT R3 L19; goto L19 if not var3
     112 [-]: GETIMPORT R4 33; var4 = _T["QueuedTransmissions"]
     113 [-]: LENGTH R3 R4 ; var3 = #var4
     114 [-]: LOADN R4 0   ; var4 = 0
     115 [-]: JUMPIFLT R4 R3 L20; goto L20 if var4 < var2294561
L19: 116 [-]: GETIMPORT R3 35; var3 = 0x9BA7909F
     117 [-]: GETIMPORT R6 29; var6 = 0x0032441C
     118 [-]: GETTABLEKS R5 R6 K36; var5 = var6["UIMovie_TransmissionMovie"]
     119 [-]: NAMECALL R3 R3 K37; var4 = var3; var3 = var3[0xBCFB64AB]
     120 [-]: CALL R3 3 2  ; var3 = var3(var4, var5)
     121 [-]: JUMPIFNOT R3 L21; goto L21 if not var3
L20: 122 [-]: GETIMPORT R3 7; var3 = 0xCBD666E1
     123 [-]: LOADN R4 10  ; var4 = 10
     124 [-]: CALL R3 2 1  ; var3(var4)
     125 [-]: JUMPBACK L18 ; goto L18
L21: 126 [-]: FASTCALL1 64 R2 L22; 
     127 [-]: MOVE R4 R2   ; var4 = var2
     128 [-]: GETIMPORT R3 10; var3 = 0x7B998233
     129 [-]: CALL R3 2 2  ; var3 = var3(var4)
L22: 130 [-]: JUMPIF R3 L23; goto L23 if var3
     131 [-]: NAMECALL R3 R2 K38; var4 = var2; var3 = var2[0x6873DB9F]
     132 [-]: CALL R3 2 1  ; var3(var4)
L23: 133 [-]: GETIMPORT R3 40; var3 = 0xCFC01047
     134 [-]: GETIMPORT R6 29; var6 = 0x0032441C
     135 [-]: GETTABLEKS R4 R6 K30; var4 = var6["CachedGoalInfo"]
     136 [-]: CALL R3 2 4  ; var3, var4, var5 = var3(var4)
     137 [-]: FORGPREP_NEXT R3 L26; 
L24: 138 [-]: GETTABLEKS R9 R7 K41; var9 = var7["mRadioSound"]
     139 [-]: FASTCALL1 64 R9 L25; 
     140 [-]: GETIMPORT R8 10; var8 = 0x7B998233
     141 [-]: CALL R8 2 2  ; var8 = var8(var9)
L25: 142 [-]: JUMPIF R8 L26; goto L26 if var8
     143 [-]: GETUPVAL R8 8; var8 = upvalues[8]
     144 [-]: MOVE R9 R0   ; var9 = var0
     145 [-]: GETTABLEKS R10 R7 K41; var10 = var7["mRadioSound"]
     146 [-]: CALL R8 3 1  ; var8(var9, var10)
     147 [-]: JUMP L30     ; goto L30
L26: 148 [-]: FORGLOOP R3 L24 2; 
     149 [-]: JUMP L30     ; goto L30
L27: 150 [-]: GETIMPORT R3 44; var3 = 0x5BCED4C4[0x3630E649]
     151 [-]: CALL R3 1 2  ; var3 = var3()
     152 [-]: GETIMPORT R4 46; var4 = 0xDBDDD1EA
     153 [-]: JUMPIFNOTLT R3 R4 L28; goto L28 if var3 >= var590652
     154 [-]: GETUPVAL R3 9; var3 = upvalues[9]
     155 [-]: MOVE R4 R0   ; var4 = var0
     156 [-]: CALL R3 2 1  ; var3(var4)
     157 [-]: JUMP L30     ; goto L30
L28: 158 [-]: GETIMPORT R3 44; var3 = 0x5BCED4C4[0x3630E649]
     159 [-]: CALL R3 1 2  ; var3 = var3()
     160 [-]: GETIMPORT R4 48; var4 = 0x93ED88CF
     161 [-]: JUMPIFNOTLT R3 R4 L29; goto L29 if var3 >= var656188
     162 [-]: GETUPVAL R3 10; var3 = upvalues[10]
     163 [-]: MOVE R4 R0   ; var4 = var0
     164 [-]: CALL R3 2 1  ; var3(var4)
     165 [-]: JUMP L30     ; goto L30
L29: 166 [-]: GETUPVAL R3 11; var3 = upvalues[11]
     167 [-]: MOVE R4 R0   ; var4 = var0
     168 [-]: CALL R3 2 1  ; var3(var4)
L30: 169 [-]: GETIMPORT R3 44; var3 = 0x5BCED4C4[0x3630E649]
     170 [-]: GETIMPORT R4 50; var4 = 0x53F1BCA5
     171 [-]: GETIMPORT R5 52; var5 = 0x0AD1F9AB
     172 [-]: CALL R3 3 2  ; var3 = var3(var4, var5)
     173 [-]: GETUPVAL R4 7; var4 = upvalues[7]
     174 [-]: MOVE R5 R0   ; var5 = var0
     175 [-]: MOVE R6 R3   ; var6 = var3
     176 [-]: CALL R4 3 1  ; var4(var5, var6)
     177 [-]: JUMPBACK L12 ; goto L12
L31: 178 [-]: RETURN R0 0  ; 



