; This file has been disassembled using luadec 2.0.2 by sztupy (modified by Reversive)

; Name:            
; Defined at line: 0
; #Upvalues:       0
; #Parameters:     0
; Is_vararg:       2
; Max Stack Size:  23

  1 [-]: GETGLOBAL R0 K0        ; R0 := 0x7ed0a956
  2 [-]: LOADK     R1 K1        ; R1 := "/Lotus/Sounds/Dialog/Taunts/Stalker/TauntIntro1"
  3 [-]: CALL      R0 2 2       ; R0 := R0(R1)
  4 [-]: GETGLOBAL R1 K0        ; R1 := 0x7ed0a956
  5 [-]: LOADK     R2 K2        ; R2 := "/Lotus/Sounds/Dialog/Taunts/Stalker/TauntIntro2"
  6 [-]: CALL      R1 2 2       ; R1 := R1(R2)
  7 [-]: GETGLOBAL R2 K0        ; R2 := 0x7ed0a956
  8 [-]: LOADK     R3 K3        ; R3 := "/Lotus/Sounds/Dialog/Taunts/Stalker/TauntIntro3"
  9 [-]: CALL      R2 2 2       ; R2 := R2(R3)
 10 [-]: GETGLOBAL R3 K0        ; R3 := 0x7ed0a956
 11 [-]: LOADK     R4 K4        ; R4 := "/Lotus/Sounds/Dialog/Taunts/Stalker/TauntTargetEliminatedA"
 12 [-]: CALL      R3 2 2       ; R3 := R3(R4)
 13 [-]: GETGLOBAL R4 K0        ; R4 := 0x7ed0a956
 14 [-]: LOADK     R5 K5        ; R5 := "/Lotus/Sounds/Dialog/Taunts/Stalker/TauntDeathA"
 15 [-]: CALL      R4 2 2       ; R4 := R4(R5)
 16 [-]: GETGLOBAL R5 K0        ; R5 := 0x7ed0a956
 17 [-]: LOADK     R6 K6        ; R6 := "/Lotus/Interface/Rage.swf"
 18 [-]: CALL      R5 2 2       ; R5 := R5(R6)
 19 [-]: GETGLOBAL R6 K0        ; R6 := 0x7ed0a956
 20 [-]: LOADK     R7 K7        ; R7 := "/Lotus/Animations/Tenno/Menu/KneelIdle_anim.fbx"
 21 [-]: CALL      R6 2 2       ; R6 := R6(R7)
 22 [-]: GETGLOBAL R7 K0        ; R7 := 0x7ed0a956
 23 [-]: LOADK     R8 K8        ; R8 := "/Lotus/Animations/Tenno/Menu/KneelToStand_anim.fbx"
 24 [-]: CALL      R7 2 2       ; R7 := R7(R8)
 25 [-]: GETGLOBAL R8 K0        ; R8 := 0x7ed0a956
 26 [-]: LOADK     R9 K9        ; R9 := "/Lotus/Animations/Tenno/Menu/StandToKneel_anim.fbx"
 27 [-]: CALL      R8 2 2       ; R8 := R8(R9)
 28 [-]: GETGLOBAL R9 K0        ; R9 := 0x7ed0a956
 29 [-]: LOADK     R10 K10      ; R10 := "/Lotus/Powersuits/PowersuitAbilities/SmokeScreenAbility"
 30 [-]: CALL      R9 2 2       ; R9 := R9(R10)
 31 [-]: GETGLOBAL R10 K0       ; R10 := 0x7ed0a956
 32 [-]: LOADK     R11 K11      ; R11 := "/Lotus/Fx/Enemies/Stalker/StalkerSpawnIn"
 33 [-]: CALL      R10 2 2      ; R10 := R10(R11)
 34 [-]: GETGLOBAL R11 K0       ; R11 := 0x7ed0a956
 35 [-]: LOADK     R12 K12      ; R12 := "/Lotus/Fx/Enemies/Stalker/StalkerSpawnOut"
 36 [-]: CALL      R11 2 2      ; R11 := R11(R12)
 37 [-]: GETGLOBAL R12 K0       ; R12 := 0x7ed0a956
 38 [-]: LOADK     R13 K13      ; R13 := "/Lotus/Fx/Enemies/Stalker/StalkerExclusiveProjector"
 39 [-]: CALL      R12 2 2      ; R12 := R12(R13)
 40 [-]: GETGLOBAL R13 K0       ; R13 := 0x7ed0a956
 41 [-]: LOADK     R14 K14      ; R14 := "/Lotus/Fx/Enemies/Stalker/AmbientSmokeA"
 42 [-]: CALL      R13 2 2      ; R13 := R13(R14)
 43 [-]: GETGLOBAL R14 K0       ; R14 := 0x7ed0a956
 44 [-]: LOADK     R15 K15      ; R15 := "/Lotus/Fx/Enemies/Stalker/AmbientSmokeB"
 45 [-]: CALL      R14 2 2      ; R14 := R14(R15)
 46 [-]: GETGLOBAL R15 K0       ; R15 := 0x7ed0a956
 47 [-]: LOADK     R16 K16      ; R16 := "/Lotus/Sounds/Warframes/StalkerAssassin/StalkerAssassinTease"
 48 [-]: CALL      R15 2 2      ; R15 := R15(R16)
 49 [-]: GETGLOBAL R16 K0       ; R16 := 0x7ed0a956
 50 [-]: LOADK     R17 K17      ; R17 := "/Lotus/Types/DropTables/StalkerAgentDropTable"
 51 [-]: CALL      R16 2 2      ; R16 := R16(R17)
 52 [-]: GETGLOBAL R17 K18      ; R17 := 0x0469f296
 53 [-]: LOADK     R18 K19      ; R18 := "IAMYOURRECKONING"
 54 [-]: CALL      R17 2 2      ; R17 := R17(R18)
 55 [-]: GETGLOBAL R18 K20      ; R18 := 0x2d0fad09
 56 [-]: LOADK     R19 K21      ; R19 := "Lotus.Interface.LotusUtilities"
 57 [-]: CALL      R18 2 2      ; R18 := R18(R19)
 58 [-]: CLOSURE   R19 0        ; R19 := closure(Function #1)
 59 [-]: MOVE      R0 R15       ; R0 := R15
 60 [-]: CLOSURE   R20 1        ; R20 := closure(Function #2)
 61 [-]: CLOSURE   R21 2        ; R21 := closure(Function #3)
 62 [-]: MOVE      R0 R17       ; R0 := R17
 63 [-]: CLOSURE   R22 3        ; R22 := closure(Function #4)
 64 [-]: MOVE      R0 R9        ; R0 := R9
 65 [-]: MOVE      R0 R10       ; R0 := R10
 66 [-]: MOVE      R0 R11       ; R0 := R11
 67 [-]: MOVE      R0 R12       ; R0 := R12
 68 [-]: MOVE      R0 R13       ; R0 := R13
 69 [-]: MOVE      R0 R14       ; R0 := R14
 70 [-]: MOVE      R0 R15       ; R0 := R15
 71 [-]: MOVE      R0 R16       ; R0 := R16
 72 [-]: MOVE      R0 R8        ; R0 := R8
 73 [-]: MOVE      R0 R7        ; R0 := R7
 74 [-]: MOVE      R0 R18       ; R0 := R18
 75 [-]: MOVE      R0 R17       ; R0 := R17
 76 [-]: MOVE      R0 R21       ; R0 := R21
 77 [-]: MOVE      R0 R5        ; R0 := R5
 78 [-]: MOVE      R0 R6        ; R0 := R6
 79 [-]: MOVE      R0 R19       ; R0 := R19
 80 [-]: MOVE      R0 R20       ; R0 := R20
 81 [-]: MOVE      R0 R0        ; R0 := R0
 82 [-]: MOVE      R0 R1        ; R0 := R1
 83 [-]: MOVE      R0 R2        ; R0 := R2
 84 [-]: MOVE      R0 R3        ; R0 := R3
 85 [-]: MOVE      R0 R4        ; R0 := R4
 86 [-]: SETGLOBAL R22 K22      ; Initialize := R22
 87 [-]: CLOSURE   R22 4        ; R22 := closure(Function #5)
 88 [-]: SETGLOBAL R22 K23      ; LeaveSquadDone := R22
 89 [-]: CLOSURE   R22 5        ; R22 := closure(Function #6)
 90 [-]: SETGLOBAL R22 K24      ; OnUpdateSessionSettings := R22
 91 [-]: RETURN    R0 1         ; return 


; Function #1:
;
; Name:            
; Defined at line: 27
; #Upvalues:       1
; #Parameters:     0
; Is_vararg:       0
; Max Stack Size:  12

  1 [-]: GETGLOBAL R0 K0        ; R0 := 0x89326c93
  2 [-]: SELF      R0 R0 K1     ; R1 := R0; R0 := R0[0x7d108ddb]
  3 [-]: CALL      R0 2 2       ; R0 := R0(R1)
  4 [-]: CONST     R1 1         ; R1 := 1.000000
  5 [-]: LEN       R2 R0        ; R2 := # R0
  6 [-]: CONST     R3 1         ; R3 := 1.000000
  7 [-]: FORPREP   R1 29        ; R1 -= R3; PC := 29
  8 [-]: GETTABLE  R5 R0 R4     ; R5 := R0[R4]
  9 [-]: SELF      R5 R5 K2     ; R6 := R5; R5 := R5[0xbfef315d]
 10 [-]: CONST     R7 0         ; R7 := 0.500000
 11 [-]: GETGLOBAL R8 K3        ; R8 := 0xb37905d5
 12 [-]: CALL      R5 4 1       ; R5(R6,R7,R8)
 13 [-]: GETTABLE  R5 R0 R4     ; R5 := R0[R4]
 14 [-]: SELF      R5 R5 K4     ; R6 := R5; R5 := R5[0xbb610e5b]
 15 [-]: CALL      R5 2 2       ; R5 := R5(R6)
 16 [-]: GETGLOBAL R6 K5        ; R6 := 0x7b998233
 17 [-]: MOVE      R7 R5        ; R7 := R5
 18 [-]: CALL      R6 2 2       ; R6 := R6(R7)
 19 [-]: TEST      R6 1         ; if R6 then PC := 29
 20 [-]: JMP       29           ; PC := 29
 21 [-]: SELF      R6 R5 K6     ; R7 := R5; R6 := R5[0x659d451f]
 22 [-]: GETGLOBAL R8 K7        ; R8 := 0xb009bbc6
 23 [-]: GETUPVAL  R9 U0        ; R9 := U0
 24 [-]: CALL      R8 2 2       ; R8 := R8(R9)
 25 [-]: LOADKB    R9 0 0       ; R9 := false
 26 [-]: CONST     R10 0        ; R10 := 0.000000
 27 [-]: LOADKB    R11 1 0      ; R11 := true
 28 [-]: CALL      R6 6 1       ; R6(R7,R8,R9,R10,R11)
 29 [-]: FORLOOP   R1 8         ; R1 += R3; if R1 <= R2 then begin PC := 8; R4 := R1 end
 30 [-]: RETURN    R0 1         ; return 


; Function #2:
;
; Name:            
; Defined at line: 38
; #Upvalues:       0
; #Parameters:     1
; Is_vararg:       0
; Max Stack Size:  10

  1 [-]: GETGLOBAL R1 K0        ; R1 := 0x89326c93
  2 [-]: SELF      R1 R1 K1     ; R2 := R1; R1 := R1[0x8b5b1f58]
  3 [-]: CALL      R1 2 2       ; R1 := R1(R2)
  4 [-]: GETGLOBAL R2 K2        ; R2 := 0xc8802016
  5 [-]: MOVE      R3 R1        ; R3 := R1
  6 [-]: CALL      R2 2 4       ; R2,R3,R4 := R2(R3)
  7 [-]: JMP       11           ; PC := 11
  8 [-]: SELF      R7 R6 K3     ; R8 := R6; R7 := R6[0x2a748f85]
  9 [-]: MOVE      R9 R0        ; R9 := R0
 10 [-]: CALL      R7 3 1       ; R7(R8,R9)
 11 [-]: TFORLOOP  R2 2         ; R5,R6 :=  R2(R3,R4); if R5 ~= nil then begin PC = 8; R4 := R5 end
 12 [-]: JMP       8            ; PC := 8
 13 [-]: RETURN    R0 1         ; return 


; Function #3:
;
; Name:            
; Defined at line: 45
; #Upvalues:       1
; #Parameters:     2
; Is_vararg:       0
; Max Stack Size:  9

  1 [-]: GETGLOBAL R2 K0        ; R2 := 0x7b998233
  2 [-]: MOVE      R3 R0        ; R3 := R0
  3 [-]: CALL      R2 2 2       ; R2 := R2(R3)
  4 [-]: TEST      R2 0         ; if not R2 then PC := 7
  5 [-]: JMP       7            ; PC := 7
  6 [-]: RETURN    R0 1         ; return 
  7 [-]: SELF      R2 R0 K1     ; R3 := R0; R2 := R0[0x1ac1655c]
  8 [-]: CALL      R2 2 2       ; R2 := R2(R3)
  9 [-]: TEST      R1 0         ; if not R1 then PC := 59
 10 [-]: JMP       59           ; PC := 59
 11 [-]: SELF      R3 R2 K2     ; R4 := R2; R3 := R2[0xaa0faa2c]
 12 [-]: CONST     R5 5         ; R5 := 5.000000
 13 [-]: GETUPVAL  R6 U0        ; R6 := U0
 14 [-]: CALL      R3 4 1       ; R3(R4,R5,R6)
 15 [-]: SELF      R3 R2 K2     ; R4 := R2; R3 := R2[0xaa0faa2c]
 16 [-]: CONST     R5 6         ; R5 := 6.000000
 17 [-]: GETUPVAL  R6 U0        ; R6 := U0
 18 [-]: CALL      R3 4 1       ; R3(R4,R5,R6)
 19 [-]: SELF      R3 R2 K2     ; R4 := R2; R3 := R2[0xaa0faa2c]
 20 [-]: CONST     R5 3         ; R5 := 3.000000
 21 [-]: GETUPVAL  R6 U0        ; R6 := U0
 22 [-]: CALL      R3 4 1       ; R3(R4,R5,R6)
 23 [-]: SELF      R3 R2 K2     ; R4 := R2; R3 := R2[0xaa0faa2c]
 24 [-]: CONST     R5 9         ; R5 := 9.000000
 25 [-]: GETUPVAL  R6 U0        ; R6 := U0
 26 [-]: CALL      R3 4 1       ; R3(R4,R5,R6)
 27 [-]: SELF      R3 R2 K2     ; R4 := R2; R3 := R2[0xaa0faa2c]
 28 [-]: CONST     R5 4         ; R5 := 4.000000
 29 [-]: GETUPVAL  R6 U0        ; R6 := U0
 30 [-]: CALL      R3 4 1       ; R3(R4,R5,R6)
 31 [-]: SELF      R3 R2 K2     ; R4 := R2; R3 := R2[0xaa0faa2c]
 32 [-]: CONST     R5 8         ; R5 := 8.000000
 33 [-]: GETUPVAL  R6 U0        ; R6 := U0
 34 [-]: CALL      R3 4 1       ; R3(R4,R5,R6)
 35 [-]: SELF      R3 R2 K4     ; R4 := R2; R3 := R2[0x857557de]
 36 [-]: GETUPVAL  R5 U0        ; R5 := U0
 37 [-]: CALL      R3 3 1       ; R3(R4,R5)
 38 [-]: SELF      R3 R0 K1     ; R4 := R0; R3 := R0[0x1ac1655c]
 39 [-]: CALL      R3 2 2       ; R3 := R3(R4)
 40 [-]: SELF      R3 R3 K5     ; R4 := R3; R3 := R3[0xa383de31]
 41 [-]: GETUPVAL  R5 U0        ; R5 := U0
 42 [-]: CONST     R6 25        ; R6 := 25.000000
 43 [-]: CONST     R7 6         ; R7 := 6.000000
 44 [-]: CONST     R8 0         ; R8 := 0.000000
 45 [-]: CALL      R3 6 1       ; R3(R4,R5,R6,R7,R8)
 46 [-]: SELF      R3 R0 K1     ; R4 := R0; R3 := R0[0x1ac1655c]
 47 [-]: CALL      R3 2 2       ; R3 := R3(R4)
 48 [-]: SELF      R3 R3 K6     ; R4 := R3; R3 := R3[0x4cb29d1c]
 49 [-]: GETUPVAL  R5 U0        ; R5 := U0
 50 [-]: CONST     R6 25        ; R6 := 25.000000
 51 [-]: CONST     R7 6         ; R7 := 6.000000
 52 [-]: CONST     R8 0         ; R8 := 0.000000
 53 [-]: CALL      R3 6 1       ; R3(R4,R5,R6,R7,R8)
 54 [-]: SELF      R3 R0 K7     ; R4 := R0; R3 := R0[0xffc58a04]
 55 [-]: CONST     R5 0         ; R5 := 0.000000
 56 [-]: GETUPVAL  R6 U0        ; R6 := U0
 57 [-]: CALL      R3 4 1       ; R3(R4,R5,R6)
 58 [-]: JMP       72           ; PC := 72
 59 [-]: SELF      R3 R2 K9     ; R4 := R2; R3 := R2[0x571105c9]
 60 [-]: GETUPVAL  R5 U0        ; R5 := U0
 61 [-]: CALL      R3 3 1       ; R3(R4,R5)
 62 [-]: SELF      R3 R0 K1     ; R4 := R0; R3 := R0[0x1ac1655c]
 63 [-]: CALL      R3 2 2       ; R3 := R3(R4)
 64 [-]: SELF      R3 R3 K10    ; R4 := R3; R3 := R3[0x8e3e343e]
 65 [-]: GETUPVAL  R5 U0        ; R5 := U0
 66 [-]: CALL      R3 3 1       ; R3(R4,R5)
 67 [-]: SELF      R3 R0 K1     ; R4 := R0; R3 := R0[0x1ac1655c]
 68 [-]: CALL      R3 2 2       ; R3 := R3(R4)
 69 [-]: SELF      R3 R3 K11    ; R4 := R3; R3 := R3[0x9326ca4b]
 70 [-]: GETUPVAL  R5 U0        ; R5 := U0
 71 [-]: CALL      R3 3 1       ; R3(R4,R5)
 72 [-]: RETURN    R0 1         ; return 


; Function #4:
;
; Name:            
; Defined at line: 70
; #Upvalues:       22
; #Parameters:     1
; Is_vararg:       0
; Max Stack Size:  34

  1 [-]: GETGLOBAL R1 K0        ; R1 := 0x76ea806b
  2 [-]: TEST      R1 0         ; if not R1 then PC := 9
  3 [-]: JMP       9            ; PC := 9
  4 [-]: GETGLOBAL R1 K0        ; R1 := 0x76ea806b
  5 [-]: SELF      R1 R1 K1     ; R2 := R1; R1 := R1[0x8792aaab]
  6 [-]: CALL      R1 2 2       ; R1 := R1(R2)
  7 [-]: TEST      R1 1         ; if R1 then PC := 10
  8 [-]: JMP       10           ; PC := 10
  9 [-]: RETURN    R0 1         ; return 
 10 [-]: GETGLOBAL R1 K2        ; R1 := 0x7b998233
 11 [-]: SELF      R2 R0 K3     ; R3 := R0; R2 := R0[0x5163741e]
 12 [-]: CALL      R2 2 0       ; R2,... := R2(R3)
 13 [-]: CALL      R1 0 2       ; R1 := R1(R2,...)
 14 [-]: TEST      R1 0         ; if not R1 then PC := 20
 15 [-]: JMP       20           ; PC := 20
 16 [-]: GETGLOBAL R1 K4        ; R1 := 0xcbd666e1
 17 [-]: CONST     R2 0         ; R2 := 0.000000
 18 [-]: CALL      R1 2 1       ; R1(R2)
 19 [-]: JMP       10           ; PC := 10
 20 [-]: SELF      R1 R0 K3     ; R2 := R0; R1 := R0[0x5163741e]
 21 [-]: CALL      R1 2 2       ; R1 := R1(R2)
 22 [-]: GETGLOBAL R2 K2        ; R2 := 0x7b998233
 23 [-]: SELF      R3 R1 K5     ; R4 := R1; R3 := R1[0x5e651723]
 24 [-]: CALL      R3 2 0       ; R3,... := R3(R4)
 25 [-]: CALL      R2 0 2       ; R2 := R2(R3,...)
 26 [-]: TEST      R2 0         ; if not R2 then PC := 32
 27 [-]: JMP       32           ; PC := 32
 28 [-]: SELF      R2 R1 K6     ; R3 := R1; R2 := R1[0x66472bf5]
 29 [-]: CONST     R4 0         ; R4 := 0.000000
 30 [-]: CALL      R2 3 1       ; R2(R3,R4)
 31 [-]: RETURN    R0 1         ; return 
 32 [-]: GETGLOBAL R2 K7        ; R2 := _T
 33 [-]: SETTABLE  R2 K8 R1     ; R2["StalkerPlayerAvatar"] := R1
 34 [-]: GETGLOBAL R2 K7        ; R2 := _T
 35 [-]: SELF      R3 R1 K5     ; R4 := R1; R3 := R1[0x5e651723]
 36 [-]: CALL      R3 2 2       ; R3 := R3(R4)
 37 [-]: SETTABLE  R2 K9 R3     ; R2["StalkerPlayer"] := R3
 38 [-]: GETGLOBAL R2 K7        ; R2 := _T
 39 [-]: GETTABLE  R2 R2 K9     ; R2 := R2["StalkerPlayer"]
 40 [-]: SELF      R2 R2 K10    ; R3 := R2; R2 := R2[0x0bb16e53]
 41 [-]: LOADKB    R4 1 0       ; R4 := true
 42 [-]: CALL      R2 3 1       ; R2(R3,R4)
 43 [-]: SELF      R2 R1 K11    ; R3 := R1; R2 := R1[0xa5e492d4]
 44 [-]: CALL      R2 2 2       ; R2 := R2(R3)
 45 [-]: GETGLOBAL R3 K12       ; R3 := 0x89326c93
 46 [-]: SELF      R3 R3 K13    ; R4 := R3; R3 := R3[0x18d05d30]
 47 [-]: CALL      R3 2 2       ; R3 := R3(R4)
 48 [-]: TEST      R3 0         ; if not R3 then PC := 136
 49 [-]: JMP       136          ; PC := 136
 50 [-]: TEST      R2 1         ; if R2 then PC := 70
 51 [-]: JMP       70           ; PC := 70
 52 [-]: GETGLOBAL R3 K7        ; R3 := _T
 53 [-]: GETTABLE  R3 R3 K14    ; R3 := R3["gStalkerActive"]
 54 [-]: EQ        1 R3 K15     ; if R3 == true then PC := 60
 55 [-]: JMP       60           ; PC := 60
 56 [-]: GETGLOBAL R3 K7        ; R3 := _T
 57 [-]: GETTABLE  R3 R3 K16    ; R3 := R3["gDisableStalker"]
 58 [-]: EQ        0 R3 K15     ; if R3 ~= true then PC := 70
 59 [-]: JMP       70           ; PC := 70
 60 [-]: GETGLOBAL R3 K4        ; R3 := 0xcbd666e1
 61 [-]: CONST     R4 0         ; R4 := 0.000000
 62 [-]: CALL      R3 2 1       ; R3(R4)
 63 [-]: GETGLOBAL R3 K17       ; R3 := 0xe7f2b02f
 64 [-]: SELF      R3 R3 K18    ; R4 := R3; R3 := R3[0x0a7813f5]
 65 [-]: SELF      R5 R1 K5     ; R6 := R1; R5 := R1[0x5e651723]
 66 [-]: CALL      R5 2 2       ; R5 := R5(R6)
 67 [-]: LOADKB    R6 1 0       ; R6 := true
 68 [-]: CALL      R3 4 1       ; R3(R4,R5,R6)
 69 [-]: RETURN    R0 1         ; return 
 70 [-]: TEST      R2 0         ; if not R2 then PC := 83
 71 [-]: JMP       83           ; PC := 83
 72 [-]: GETGLOBAL R3 K2        ; R3 := 0x7b998233
 73 [-]: GETGLOBAL R4 K17       ; R4 := 0xe7f2b02f
 74 [-]: SELF      R4 R4 K19    ; R5 := R4; R4 := R4[0x565be9ee]
 75 [-]: CALL      R4 2 0       ; R4,... := R4(R5)
 76 [-]: CALL      R3 0 2       ; R3 := R3(R4,...)
 77 [-]: TEST      R3 1         ; if R3 then PC := 83
 78 [-]: JMP       83           ; PC := 83
 79 [-]: GETGLOBAL R3 K17       ; R3 := 0xe7f2b02f
 80 [-]: SELF      R3 R3 K20    ; R4 := R3; R3 := R3[0x8229d239]
 81 [-]: LOADK     R5 K21       ; R5 := "LeaveSquadDone"
 82 [-]: CALL      R3 3 1       ; R3(R4,R5)
 83 [-]: NEWTABLE  R3 9 0       ; R3 := {}
 84 [-]: GETUPVAL  R4 U0        ; R4 := U0
 85 [-]: SELF      R4 R4 K22    ; R5 := R4; R4 := R4[0xed4e0128]
 86 [-]: CALL      R4 2 2       ; R4 := R4(R5)
 87 [-]: GETUPVAL  R5 U1        ; R5 := U1
 88 [-]: SELF      R5 R5 K22    ; R6 := R5; R5 := R5[0xed4e0128]
 89 [-]: CALL      R5 2 2       ; R5 := R5(R6)
 90 [-]: GETUPVAL  R6 U2        ; R6 := U2
 91 [-]: SELF      R6 R6 K22    ; R7 := R6; R6 := R6[0xed4e0128]
 92 [-]: CALL      R6 2 2       ; R6 := R6(R7)
 93 [-]: GETUPVAL  R7 U3        ; R7 := U3
 94 [-]: SELF      R7 R7 K22    ; R8 := R7; R7 := R7[0xed4e0128]
 95 [-]: CALL      R7 2 2       ; R7 := R7(R8)
 96 [-]: GETUPVAL  R8 U4        ; R8 := U4
 97 [-]: SELF      R8 R8 K22    ; R9 := R8; R8 := R8[0xed4e0128]
 98 [-]: CALL      R8 2 2       ; R8 := R8(R9)
 99 [-]: GETUPVAL  R9 U5        ; R9 := U5
100 [-]: SELF      R9 R9 K22    ; R10 := R9; R9 := R9[0xed4e0128]
101 [-]: CALL      R9 2 2       ; R9 := R9(R10)
102 [-]: GETUPVAL  R10 U6       ; R10 := U6
103 [-]: SELF      R10 R10 K22  ; R11 := R10; R10 := R10[0xed4e0128]
104 [-]: CALL      R10 2 2      ; R10 := R10(R11)
105 [-]: GETUPVAL  R11 U7       ; R11 := U7
106 [-]: SELF      R11 R11 K22  ; R12 := R11; R11 := R11[0xed4e0128]
107 [-]: CALL      R11 2 2      ; R11 := R11(R12)
108 [-]: GETUPVAL  R12 U8       ; R12 := U8
109 [-]: SELF      R12 R12 K22  ; R13 := R12; R12 := R12[0xed4e0128]
110 [-]: CALL      R12 2 2      ; R12 := R12(R13)
111 [-]: GETUPVAL  R13 U9       ; R13 := U9
112 [-]: SELF      R13 R13 K22  ; R14 := R13; R13 := R13[0xed4e0128]
113 [-]: CALL      R13 2 0      ; R13,... := R13(R14)
114 [-]: SETLIST   R3 0 1       ; R3[(1-1)*FPF+i] := R(3+i), 1 <= i <= 0
115 [-]: GETGLOBAL R4 K23       ; R4 := 0xbe190284
116 [-]: SELF      R4 R4 K24    ; R5 := R4; R4 := R4[0xf91cabaa]
117 [-]: MOVE      R6 R3        ; R6 := R3
118 [-]: CALL      R4 3 1       ; R4(R5,R6)
119 [-]: GETGLOBAL R4 K2        ; R4 := 0x7b998233
120 [-]: GETGLOBAL R5 K17       ; R5 := 0xe7f2b02f
121 [-]: SELF      R5 R5 K19    ; R6 := R5; R5 := R5[0x565be9ee]
122 [-]: CALL      R5 2 0       ; R5,... := R5(R6)
123 [-]: CALL      R4 0 2       ; R4 := R4(R5,...)
124 [-]: TEST      R4 1         ; if R4 then PC := 136
125 [-]: JMP       136          ; PC := 136
126 [-]: GETGLOBAL R4 K17       ; R4 := 0xe7f2b02f
127 [-]: SELF      R4 R4 K19    ; R5 := R4; R4 := R4[0x565be9ee]
128 [-]: CALL      R4 2 2       ; R4 := R4(R5)
129 [-]: SELF      R4 R4 K25    ; R5 := R4; R4 := R4[0xfdd3576f]
130 [-]: CALL      R4 2 2       ; R4 := R4(R5)
131 [-]: GETGLOBAL R5 K17       ; R5 := 0xe7f2b02f
132 [-]: SELF      R5 R5 K26    ; R6 := R5; R5 := R5[0xee2f24fc]
133 [-]: MOVE      R7 R4        ; R7 := R4
134 [-]: LOADK     R8 K27       ; R8 := "OnUpdateSessionSettings"
135 [-]: CALL      R5 4 1       ; R5(R6,R7,R8)
136 [-]: GETGLOBAL R5 K2        ; R5 := 0x7b998233
137 [-]: MOVE      R6 R1        ; R6 := R1
138 [-]: CALL      R5 2 2       ; R5 := R5(R6)
139 [-]: TEST      R5 1         ; if R5 then PC := 174
140 [-]: JMP       174          ; PC := 174
141 [-]: GETGLOBAL R5 K7        ; R5 := _T
142 [-]: GETTABLE  R5 R5 K9     ; R5 := R5["StalkerPlayer"]
143 [-]: SELF      R5 R5 K28    ; R6 := R5; R5 := R5[0x5ca33548]
144 [-]: CALL      R5 2 2       ; R5 := R5(R6)
145 [-]: GETUPVAL  R6 U10       ; R6 := U10
146 [-]: GETTABLE  R6 R6 K29    ; R6 := R6["HIDDEN_PLAYER_NAME"]
147 [-]: EQ        1 R5 R6      ; if R5 == R6 then PC := 174
148 [-]: JMP       174          ; PC := 174
149 [-]: GETGLOBAL R5 K4        ; R5 := 0xcbd666e1
150 [-]: CONST     R6 0         ; R6 := 0.000000
151 [-]: CALL      R5 2 1       ; R5(R6)
152 [-]: TEST      R2 0         ; if not R2 then PC := 162
153 [-]: JMP       162          ; PC := 162
154 [-]: GETGLOBAL R5 K0        ; R5 := 0x76ea806b
155 [-]: SELF      R5 R5 K30    ; R6 := R5; R5 := R5[0x63e78018]
156 [-]: CALL      R5 2 1       ; R5(R6)
157 [-]: GETGLOBAL R5 K31       ; R5 := 0x34291f5c
158 [-]: GETTABLE  R5 R5 K32    ; R5 := R5[0x8ee24660]
159 [-]: LOADKB    R6 1 0       ; R6 := true
160 [-]: CALL      R5 2 1       ; R5(R6)
161 [-]: JMP       173          ; PC := 173
162 [-]: GETGLOBAL R5 K12       ; R5 := 0x89326c93
163 [-]: SELF      R5 R5 K13    ; R6 := R5; R5 := R5[0x18d05d30]
164 [-]: CALL      R5 2 2       ; R5 := R5(R6)
165 [-]: TEST      R5 0         ; if not R5 then PC := 173
166 [-]: JMP       173          ; PC := 173
167 [-]: GETGLOBAL R5 K17       ; R5 := 0xe7f2b02f
168 [-]: SELF      R5 R5 K18    ; R6 := R5; R5 := R5[0x0a7813f5]
169 [-]: SELF      R7 R1 K5     ; R8 := R1; R7 := R1[0x5e651723]
170 [-]: CALL      R7 2 2       ; R7 := R7(R8)
171 [-]: LOADKB    R8 1 0       ; R8 := true
172 [-]: CALL      R5 4 1       ; R5(R6,R7,R8)
173 [-]: RETURN    R0 1         ; return 
174 [-]: GETGLOBAL R5 K7        ; R5 := _T
175 [-]: SETTABLE  R5 K16 K15   ; R5["gDisableStalker"] := true
176 [-]: GETGLOBAL R5 K7        ; R5 := _T
177 [-]: SETTABLE  R5 K14 K15   ; R5["gStalkerActive"] := true
178 [-]: SELF      R5 R0 K33    ; R6 := R0; R5 := R0[0x4af1933a]
179 [-]: CONST     R7 3         ; R7 := 3.000000
180 [-]: CALL      R5 3 1       ; R5(R6,R7)
181 [-]: SELF      R5 R0 K34    ; R6 := R0; R5 := R0[0x2f1a1960]
182 [-]: GETGLOBAL R7 K35       ; R7 := 0x88efc25e
183 [-]: GETUPVAL  R8 U0        ; R8 := U0
184 [-]: CALL      R7 2 2       ; R7 := R7(R8)
185 [-]: CONST     R8 0         ; R8 := 0.000000
186 [-]: CALL      R5 4 1       ; R5(R6,R7,R8)
187 [-]: SELF      R5 R1 K36    ; R6 := R1; R5 := R1[0xde321e6f]
188 [-]: CALL      R5 2 2       ; R5 := R5(R6)
189 [-]: SELF      R6 R1 K37    ; R7 := R1; R6 := R1[0x1ac1655c]
190 [-]: CALL      R6 2 2       ; R6 := R6(R7)
191 [-]: SELF      R7 R5 K38    ; R8 := R5; R7 := R5[0x5e6704ff]
192 [-]: CONST     R9 160       ; R9 := 160.000000
193 [-]: CONST     R10 2        ; R10 := 2.000000
194 [-]: LOADK     R11 K40      ; R11 := 0.150000
195 [-]: LOADNIL   R12 R13      ; R12 := R13 := nil
196 [-]: CONST     R14 25       ; R14 := 25.000000
197 [-]: GETGLOBAL R15 K41      ; R15 := 0x0469f296
198 [-]: CALL      R15 1 2      ; R15 := R15()
199 [-]: LOADKB    R16 1 0      ; R16 := true
200 [-]: CALL      R7 10 1      ; R7(R8,R9,R10,R11,R12,R13,R14,R15,R16)
201 [-]: SELF      R7 R5 K38    ; R8 := R5; R7 := R5[0x5e6704ff]
202 [-]: CONST     R9 159       ; R9 := 159.000000
203 [-]: CONST     R10 2        ; R10 := 2.000000
204 [-]: CONST     R11 10       ; R11 := 10.000000
205 [-]: LOADNIL   R12 R13      ; R12 := R13 := nil
206 [-]: CONST     R14 25       ; R14 := 25.000000
207 [-]: GETGLOBAL R15 K41      ; R15 := 0x0469f296
208 [-]: CALL      R15 1 2      ; R15 := R15()
209 [-]: LOADKB    R16 1 0      ; R16 := true
210 [-]: CALL      R7 10 1      ; R7(R8,R9,R10,R11,R12,R13,R14,R15,R16)
211 [-]: SELF      R7 R5 K38    ; R8 := R5; R7 := R5[0x5e6704ff]
212 [-]: CONST     R9 159       ; R9 := 159.000000
213 [-]: CONST     R10 2        ; R10 := 2.000000
214 [-]: LOADK     R11 K42      ; R11 := 0.005000
215 [-]: LOADNIL   R12 R13      ; R12 := R13 := nil
216 [-]: CONST     R14 25       ; R14 := 25.000000
217 [-]: GETGLOBAL R15 K41      ; R15 := 0x0469f296
218 [-]: LOADK     R16 K43      ; R16 := "TENNO"
219 [-]: CALL      R15 2 2      ; R15 := R15(R16)
220 [-]: LOADKB    R16 1 0      ; R16 := true
221 [-]: CALL      R7 10 1      ; R7(R8,R9,R10,R11,R12,R13,R14,R15,R16)
222 [-]: SELF      R7 R5 K38    ; R8 := R5; R7 := R5[0x5e6704ff]
223 [-]: CONST     R9 168       ; R9 := 168.000000
224 [-]: CONST     R10 2        ; R10 := 2.000000
225 [-]: CONST     R11 0        ; R11 := 0.000000
226 [-]: LOADNIL   R12 R13      ; R12 := R13 := nil
227 [-]: CONST     R14 25       ; R14 := 25.000000
228 [-]: GETGLOBAL R15 K41      ; R15 := 0x0469f296
229 [-]: CALL      R15 1 2      ; R15 := R15()
230 [-]: LOADKB    R16 1 0      ; R16 := true
231 [-]: CALL      R7 10 1      ; R7(R8,R9,R10,R11,R12,R13,R14,R15,R16)
232 [-]: SELF      R7 R5 K38    ; R8 := R5; R7 := R5[0x5e6704ff]
233 [-]: CONST     R9 65        ; R9 := 65.000000
234 [-]: CONST     R10 0        ; R10 := 0.000000
235 [-]: CONST     R11 3000     ; R11 := 3000.000000
236 [-]: CALL      R7 5 1       ; R7(R8,R9,R10,R11)
237 [-]: SELF      R7 R5 K38    ; R8 := R5; R7 := R5[0x5e6704ff]
238 [-]: CONST     R9 120       ; R9 := 120.000000
239 [-]: CONST     R10 0        ; R10 := 0.000000
240 [-]: CONST     R11 1500     ; R11 := 1500.000000
241 [-]: CALL      R7 5 1       ; R7(R8,R9,R10,R11)
242 [-]: SELF      R7 R5 K38    ; R8 := R5; R7 := R5[0x5e6704ff]
243 [-]: CONST     R9 88        ; R9 := 88.000000
244 [-]: CONST     R10 0        ; R10 := 0.000000
245 [-]: CONST     R11 1000     ; R11 := 1000.000000
246 [-]: LOADNIL   R12 R13      ; R12 := R13 := nil
247 [-]: CONST     R14 25       ; R14 := 25.000000
248 [-]: GETGLOBAL R15 K41      ; R15 := 0x0469f296
249 [-]: CALL      R15 1 2      ; R15 := R15()
250 [-]: LOADKB    R16 1 0      ; R16 := true
251 [-]: CALL      R7 10 1      ; R7(R8,R9,R10,R11,R12,R13,R14,R15,R16)
252 [-]: SELF      R7 R5 K38    ; R8 := R5; R7 := R5[0x5e6704ff]
253 [-]: CONST     R9 15        ; R9 := 15.000000
254 [-]: CONST     R10 2        ; R10 := 2.000000
255 [-]: CONST     R11 2        ; R11 := 2.000000
256 [-]: CALL      R7 5 1       ; R7(R8,R9,R10,R11)
257 [-]: SELF      R7 R5 K38    ; R8 := R5; R7 := R5[0x5e6704ff]
258 [-]: CONST     R9 147       ; R9 := 147.000000
259 [-]: CONST     R10 3        ; R10 := 3.000000
260 [-]: CONST     R11 0        ; R11 := 0.000000
261 [-]: CALL      R7 5 1       ; R7(R8,R9,R10,R11)
262 [-]: SELF      R7 R1 K44    ; R8 := R1; R7 := R1[0x014db014]
263 [-]: SELF      R9 R1 K45    ; R10 := R1; R9 := R1[0xb40c191a]
264 [-]: CALL      R9 2 0       ; R9,... := R9(R10)
265 [-]: CALL      R7 0 1       ; R7(R8,...)
266 [-]: SELF      R7 R6 K46    ; R8 := R6; R7 := R6[0x57369b8b]
267 [-]: SELF      R9 R6 K47    ; R10 := R6; R9 := R6[0xb87f958d]
268 [-]: CALL      R9 2 0       ; R9,... := R9(R10)
269 [-]: CALL      R7 0 1       ; R7(R8,...)
270 [-]: SELF      R7 R0 K48    ; R8 := R0; R7 := R0[0x6e19d3fe]
271 [-]: SELF      R9 R0 K49    ; R10 := R0; R9 := R0[0xded54c60]
272 [-]: CALL      R9 2 0       ; R9,... := R9(R10)
273 [-]: CALL      R7 0 1       ; R7(R8,...)
274 [-]: SELF      R7 R1 K50    ; R8 := R1; R7 := R1[0x0cca925a]
275 [-]: GETUPVAL  R9 U11       ; R9 := U11
276 [-]: CALL      R7 3 1       ; R7(R8,R9)
277 [-]: SELF      R7 R1 K51    ; R8 := R1; R7 := R1[0x683d1152]
278 [-]: LOADKB    R9 1 0       ; R9 := true
279 [-]: CALL      R7 3 1       ; R7(R8,R9)
280 [-]: SELF      R7 R1 K52    ; R8 := R1; R7 := R1[0x1fedcbcf]
281 [-]: CONST     R9 -5        ; R9 := -5.000000
282 [-]: CALL      R7 3 1       ; R7(R8,R9)
283 [-]: SELF      R7 R1 K53    ; R8 := R1; R7 := R1[0x069d881f]
284 [-]: LOADKB    R9 1 0       ; R9 := true
285 [-]: CALL      R7 3 1       ; R7(R8,R9)
286 [-]: SELF      R7 R1 K54    ; R8 := R1; R7 := R1[0xbbd7cd6e]
287 [-]: GETUPVAL  R9 U11       ; R9 := U11
288 [-]: CALL      R7 3 1       ; R7(R8,R9)
289 [-]: GETUPVAL  R7 U12       ; R7 := U12
290 [-]: MOVE      R8 R1        ; R8 := R1
291 [-]: LOADKB    R9 1 0       ; R9 := true
292 [-]: CALL      R7 3 1       ; R7(R8,R9)
293 [-]: TEST      R2 0         ; if not R2 then PC := 438
294 [-]: JMP       438          ; PC := 438
295 [-]: GETGLOBAL R7 K23       ; R7 := 0xbe190284
296 [-]: SELF      R7 R7 K55    ; R8 := R7; R7 := R7[0xf2deaf69]
297 [-]: GETGLOBAL R9 K56       ; R9 := gLotusBaseGameRulesType
298 [-]: CALL      R7 3 2       ; R7 := R7(R8,R9)
299 [-]: TEST      R7 0         ; if not R7 then PC := 305
300 [-]: JMP       305          ; PC := 305
301 [-]: GETGLOBAL R7 K23       ; R7 := 0xbe190284
302 [-]: SELF      R7 R7 K57    ; R8 := R7; R7 := R7[0x962088e5]
303 [-]: LOADKB    R9 0 0       ; R9 := false
304 [-]: CALL      R7 3 1       ; R7(R8,R9)
305 [-]: GETGLOBAL R7 K7        ; R7 := _T
306 [-]: GETGLOBAL R8 K7        ; R8 := _T
307 [-]: GETTABLE  R8 R8 K59    ; R8 := R8["MATCHMAKING_QUICKMATCH_GAMEMODE"]
308 [-]: SETTABLE  R7 K58 R8    ; R7["gActiveMatchMakingMode"] := R8
309 [-]: GETGLOBAL R7 K60       ; R7 := 0x9ba7909f
310 [-]: SELF      R7 R7 K61    ; R8 := R7; R7 := R7[0xbcfb64ab]
311 [-]: GETUPVAL  R9 U13       ; R9 := U13
312 [-]: CALL      R7 3 2       ; R7 := R7(R8,R9)
313 [-]: GETGLOBAL R8 K2        ; R8 := 0x7b998233
314 [-]: MOVE      R9 R7        ; R9 := R7
315 [-]: CALL      R8 2 2       ; R8 := R8(R9)
316 [-]: TEST      R8 0         ; if not R8 then PC := 323
317 [-]: JMP       323          ; PC := 323
318 [-]: GETGLOBAL R8 K60       ; R8 := 0x9ba7909f
319 [-]: SELF      R8 R8 K62    ; R9 := R8; R8 := R8[0x6dd7aa66]
320 [-]: GETUPVAL  R10 U13      ; R10 := U13
321 [-]: CALL      R8 3 2       ; R8 := R8(R9,R10)
322 [-]: MOVE      R7 R8        ; R7 := R8
323 [-]: GETGLOBAL R8 K0        ; R8 := 0x76ea806b
324 [-]: SELF      R8 R8 K63    ; R9 := R8; R8 := R8[0x3f3ae64c]
325 [-]: CONST     R10 0        ; R10 := 0.000000
326 [-]: CALL      R8 3 2       ; R8 := R8(R9,R10)
327 [-]: SELF      R9 R8 K64    ; R10 := R8; R9 := R8[0x80563238]
328 [-]: CALL      R9 2 2       ; R9 := R9(R10)
329 [-]: SELF      R10 R8 K65   ; R11 := R8; R10 := R8[0x40e9c32b]
330 [-]: CALL      R10 2 2      ; R10 := R10(R11)
331 [-]: SELF      R11 R10 K66  ; R12 := R10; R11 := R10[0x8f96668b]
332 [-]: LOADKB    R13 1 0      ; R13 := true
333 [-]: CALL      R11 3 1      ; R11(R12,R13)
334 [-]: SELF      R11 R10 K67  ; R12 := R10; R11 := R10[0x1d312c60]
335 [-]: LOADKB    R13 0 0      ; R13 := false
336 [-]: CALL      R11 3 1      ; R11(R12,R13)
337 [-]: SELF      R11 R10 K68  ; R12 := R10; R11 := R10[0x764b3297]
338 [-]: CONST     R13 0        ; R13 := 0.000000
339 [-]: LOADKB    R14 0 0      ; R14 := false
340 [-]: CALL      R11 4 1      ; R11(R12,R13,R14)
341 [-]: SELF      R11 R9 K69   ; R12 := R9; R11 := R9[0x08800d7f]
342 [-]: LOADKB    R13 0 0      ; R13 := false
343 [-]: CALL      R11 3 1      ; R11(R12,R13)
344 [-]: GETGLOBAL R11 K23      ; R11 := 0xbe190284
345 [-]: SELF      R11 R11 K55  ; R12 := R11; R11 := R11[0xf2deaf69]
346 [-]: GETGLOBAL R13 K70      ; R13 := gLotusAttractModeGameRulesType
347 [-]: CALL      R11 3 2      ; R11 := R11(R12,R13)
348 [-]: TEST      R11 1        ; if R11 then PC := 358
349 [-]: JMP       358          ; PC := 358
350 [-]: GETGLOBAL R11 K41      ; R11 := 0x0469f296
351 [-]: LOADK     R12 K71      ; R12 := "StopNormalTransmissions"
352 [-]: CALL      R11 2 2      ; R11 := R11(R12)
353 [-]: GETGLOBAL R12 K23      ; R12 := 0xbe190284
354 [-]: SELF      R12 R12 K72  ; R13 := R12; R12 := R12[0x751f061d]
355 [-]: MOVE      R14 R11      ; R14 := R11
356 [-]: CONST     R15 1        ; R15 := 1.000000
357 [-]: CALL      R12 4 1      ; R12(R13,R14,R15)
358 [-]: GETGLOBAL R12 K7       ; R12 := _T
359 [-]: GETGLOBAL R13 K74      ; R13 := 0xb2407ae4
360 [-]: SETTABLE  R12 K73 R13  ; R12["MissionTransmissionSet"] := R13
361 [-]: SELF      R12 R1 K5    ; R13 := R1; R12 := R1[0x5e651723]
362 [-]: CALL      R12 2 2      ; R12 := R12(R13)
363 [-]: SELF      R12 R12 K75  ; R13 := R12; R12 := R12[0x23c62274]
364 [-]: CALL      R12 2 2      ; R12 := R12(R13)
365 [-]: GETGLOBAL R13 K76      ; R13 := 0xdd2d0c33
366 [-]: SELF      R13 R13 K77  ; R14 := R13; R13 := R13[0x7984e441]
367 [-]: MOVE      R15 R12      ; R15 := R12
368 [-]: LOADKB    R16 1 0      ; R16 := true
369 [-]: CALL      R13 4 1      ; R13(R14,R15,R16)
370 [-]: GETGLOBAL R13 K2       ; R13 := 0x7b998233
371 [-]: SELF      R14 R1 K78   ; R15 := R1; R14 := R1[0x0b4bcfb6]
372 [-]: CALL      R14 2 0      ; R14,... := R14(R15)
373 [-]: CALL      R13 0 2      ; R13 := R13(R14,...)
374 [-]: TEST      R13 0        ; if not R13 then PC := 380
375 [-]: JMP       380          ; PC := 380
376 [-]: GETGLOBAL R13 K4       ; R13 := 0xcbd666e1
377 [-]: CONST     R14 0        ; R14 := 0.000000
378 [-]: CALL      R13 2 1      ; R13(R14)
379 [-]: JMP       370          ; PC := 370
380 [-]: SELF      R13 R1 K78   ; R14 := R1; R13 := R1[0x0b4bcfb6]
381 [-]: CALL      R13 2 2      ; R13 := R13(R14)
382 [-]: SELF      R14 R13 K79  ; R15 := R13; R14 := R13[0xd8bcb169]
383 [-]: LOADK     R16 K80      ; R16 := 1.200000
384 [-]: LOADK     R17 K81      ; R17 := 1.050000
385 [-]: LOADK     R18 K81      ; R18 := 1.050000
386 [-]: CONST     R19 1        ; R19 := 1.500000
387 [-]: CALL      R14 6 1      ; R14(R15,R16,R17,R18,R19)
388 [-]: SELF      R14 R13 K82  ; R15 := R13; R14 := R13[0x47de28d6]
389 [-]: LOADK     R16 K83      ; R16 := 0.920000
390 [-]: CALL      R14 3 1      ; R14(R15,R16)
391 [-]: SELF      R14 R13 K84  ; R15 := R13; R14 := R13[0x758c046d]
392 [-]: GETGLOBAL R16 K85      ; R16 := 0x1ed92f72
393 [-]: CONST     R17 1        ; R17 := 1.000000
394 [-]: CONST     R18 -1       ; R18 := -1.000000
395 [-]: CONST     R19 1        ; R19 := 1.000000
396 [-]: CALL      R14 6 1      ; R14(R15,R16,R17,R18,R19)
397 [-]: GETGLOBAL R14 K23      ; R14 := 0xbe190284
398 [-]: SELF      R14 R14 K55  ; R15 := R14; R14 := R14[0xf2deaf69]
399 [-]: GETGLOBAL R16 K70      ; R16 := gLotusAttractModeGameRulesType
400 [-]: CALL      R14 3 2      ; R14 := R14(R15,R16)
401 [-]: TEST      R14 0        ; if not R14 then PC := 428
402 [-]: JMP       428          ; PC := 428
403 [-]: SELF      R14 R1 K86   ; R15 := R1; R14 := R1[0x020d4331]
404 [-]: CALL      R14 2 2      ; R14 := R14(R15)
405 [-]: SELF      R14 R14 K87  ; R15 := R14; R14 := R14[0xdf2dca58]
406 [-]: LOADKB    R16 1 0      ; R16 := true
407 [-]: CALL      R14 3 1      ; R14(R15,R16)
408 [-]: SELF      R14 R1 K88   ; R15 := R1; R14 := R1[0xd3a01177]
409 [-]: CALL      R14 2 2      ; R14 := R14(R15)
410 [-]: SELF      R14 R14 K89  ; R15 := R14; R14 := R14[0x294e7c63]
411 [-]: LOADKB    R16 0 0      ; R16 := false
412 [-]: CALL      R14 3 1      ; R14(R15,R16)
413 [-]: SELF      R14 R5 K90   ; R15 := R5; R14 := R5[0x0b5ec5b5]
414 [-]: LOADKB    R16 0 0      ; R16 := false
415 [-]: CALL      R14 3 1      ; R14(R15,R16)
416 [-]: SELF      R14 R1 K91   ; R15 := R1; R14 := R1[0x7027c544]
417 [-]: GETGLOBAL R16 K92      ; R16 := 0xb009bbc6
418 [-]: GETUPVAL  R17 U9       ; R17 := U9
419 [-]: CALL      R16 2 2      ; R16 := R16(R17)
420 [-]: LOADKB    R17 0 0      ; R17 := false
421 [-]: CONST     R18 3        ; R18 := 3.000000
422 [-]: CONST     R19 1        ; R19 := 1.000000
423 [-]: LOADKB    R20 1 0      ; R20 := true
424 [-]: CONST     R21 0        ; R21 := 0.750000
425 [-]: CALL      R14 8 1      ; R14(R15,R16,R17,R18,R19,R20,R21)
426 [-]: RETURN    R0 1         ; return 
427 [-]: JMP       438          ; PC := 438
428 [-]: GETGLOBAL R14 K2       ; R14 := 0x7b998233
429 [-]: MOVE      R15 R7       ; R15 := R7
430 [-]: CALL      R14 2 2      ; R14 := R14(R15)
431 [-]: TEST      R14 1        ; if R14 then PC := 438
432 [-]: JMP       438          ; PC := 438
433 [-]: SELF      R14 R7 K93   ; R15 := R7; R14 := R7[0x67bc869f]
434 [-]: LOADK     R16 K94      ; R16 := "Reticle"
435 [-]: CONST     R17 10       ; R17 := 10.000000
436 [-]: CONST     R18 60       ; R18 := 60.000000
437 [-]: CALL      R14 5 1      ; R14(R15,R16,R17,R18)
438 [-]: TEST      R2 1         ; if R2 then PC := 452
439 [-]: JMP       452          ; PC := 452
440 [-]: SELF      R14 R1 K95   ; R15 := R1; R14 := R1[0x7102164f]
441 [-]: LOADKB    R16 0 0      ; R16 := false
442 [-]: CALL      R14 3 1      ; R14(R15,R16)
443 [-]: SELF      R14 R1 K91   ; R15 := R1; R14 := R1[0x7027c544]
444 [-]: GETGLOBAL R16 K92      ; R16 := 0xb009bbc6
445 [-]: GETUPVAL  R17 U14      ; R17 := U14
446 [-]: CALL      R16 2 2      ; R16 := R16(R17)
447 [-]: LOADKB    R17 0 0      ; R17 := false
448 [-]: CONST     R18 3        ; R18 := 3.000000
449 [-]: CONST     R19 3        ; R19 := 3.000000
450 [-]: LOADKB    R20 1 0      ; R20 := true
451 [-]: CALL      R14 7 1      ; R14(R15,R16,R17,R18,R19,R20)
452 [-]: SELF      R14 R1 K96   ; R15 := R1; R14 := R1[0x768274d6]
453 [-]: LOADKB    R16 0 0      ; R16 := false
454 [-]: LOADKB    R17 1 0      ; R17 := true
455 [-]: CALL      R14 4 1      ; R14(R15,R16,R17)
456 [-]: SELF      R14 R5 K97   ; R15 := R5; R14 := R5[0x4da725ce]
457 [-]: CONST     R16 0        ; R16 := 0.000000
458 [-]: CALL      R14 3 1      ; R14(R15,R16)
459 [-]: SELF      R14 R5 K97   ; R15 := R5; R14 := R5[0x4da725ce]
460 [-]: CONST     R16 1        ; R16 := 1.000000
461 [-]: CALL      R14 3 1      ; R14(R15,R16)
462 [-]: SELF      R14 R5 K97   ; R15 := R5; R14 := R5[0x4da725ce]
463 [-]: CONST     R16 5        ; R16 := 5.000000
464 [-]: CALL      R14 3 1      ; R14(R15,R16)
465 [-]: SELF      R14 R1 K86   ; R15 := R1; R14 := R1[0x020d4331]
466 [-]: CALL      R14 2 2      ; R14 := R14(R15)
467 [-]: SELF      R14 R14 K87  ; R15 := R14; R14 := R14[0xdf2dca58]
468 [-]: LOADKB    R16 1 0      ; R16 := true
469 [-]: CALL      R14 3 1      ; R14(R15,R16)
470 [-]: SELF      R14 R1 K98   ; R15 := R1; R14 := R1[0x568f4e91]
471 [-]: CONST     R16 0        ; R16 := 0.000000
472 [-]: CALL      R14 3 1      ; R14(R15,R16)
473 [-]: SELF      R14 R1 K88   ; R15 := R1; R14 := R1[0xd3a01177]
474 [-]: CALL      R14 2 2      ; R14 := R14(R15)
475 [-]: SELF      R14 R14 K99  ; R15 := R14; R14 := R14[0x258e7323]
476 [-]: LOADKB    R16 0 0      ; R16 := false
477 [-]: CALL      R14 3 1      ; R14(R15,R16)
478 [-]: GETGLOBAL R14 K100     ; R14 := 0xa94df70b
479 [-]: SELF      R14 R14 K101 ; R15 := R14; R14 := R14[0xe8f5d98e]
480 [-]: CALL      R14 2 2      ; R14 := R14(R15)
481 [-]: GETGLOBAL R15 K2       ; R15 := 0x7b998233
482 [-]: GETGLOBAL R16 K12      ; R16 := 0x89326c93
483 [-]: SELF      R16 R16 K102 ; R17 := R16; R16 := R16[0xfb64e76c]
484 [-]: CALL      R16 2 0      ; R16,... := R16(R17)
485 [-]: CALL      R15 0 2      ; R15 := R15(R16,...)
486 [-]: TEST      R15 1        ; if R15 then PC := 495
487 [-]: JMP       495          ; PC := 495
488 [-]: GETGLOBAL R15 K12      ; R15 := 0x89326c93
489 [-]: SELF      R15 R15 K103 ; R16 := R15; R15 := R15[0x7c1a0374]
490 [-]: CALL      R15 2 2      ; R15 := R15(R16)
491 [-]: SELF      R15 R15 K104 ; R16 := R15; R15 := R15[0x65c7544c]
492 [-]: CALL      R15 2 2      ; R15 := R15(R16)
493 [-]: EQ        0 R15 K105   ; if R15 ~= 0.000000 then PC := 525
494 [-]: JMP       525          ; PC := 525
495 [-]: GETGLOBAL R15 K2       ; R15 := 0x7b998233
496 [-]: GETGLOBAL R16 K12      ; R16 := 0x89326c93
497 [-]: SELF      R16 R16 K106 ; R17 := R16; R16 := R16[0xdd25e9d1]
498 [-]: CALL      R16 2 0      ; R16,... := R16(R17)
499 [-]: CALL      R15 0 2      ; R15 := R15(R16,...)
500 [-]: TEST      R15 0        ; if not R15 then PC := 525
501 [-]: JMP       525          ; PC := 525
502 [-]: GETGLOBAL R15 K23      ; R15 := 0xbe190284
503 [-]: SELF      R15 R15 K107 ; R16 := R15; R15 := R15[0xee7ce8de]
504 [-]: CALL      R15 2 2      ; R15 := R15(R16)
505 [-]: TEST      R15 1        ; if R15 then PC := 525
506 [-]: JMP       525          ; PC := 525
507 [-]: GETGLOBAL R15 K2       ; R15 := 0x7b998233
508 [-]: GETGLOBAL R16 K12      ; R16 := 0x89326c93
509 [-]: SELF      R16 R16 K108 ; R17 := R16; R16 := R16[0x8b5b1f58]
510 [-]: CALL      R16 2 0      ; R16,... := R16(R17)
511 [-]: CALL      R15 0 2      ; R15 := R15(R16,...)
512 [-]: TEST      R15 1        ; if R15 then PC := 525
513 [-]: JMP       525          ; PC := 525
514 [-]: GETGLOBAL R15 K12      ; R15 := 0x89326c93
515 [-]: SELF      R15 R15 K109 ; R16 := R15; R15 := R15[0x61be252a]
516 [-]: CALL      R15 2 2      ; R15 := R15(R16)
517 [-]: EQ        1 R15 K105   ; if R15 == 0.000000 then PC := 525
518 [-]: JMP       525          ; PC := 525
519 [-]: GETGLOBAL R15 K60      ; R15 := 0x9ba7909f
520 [-]: SELF      R15 R15 K61  ; R16 := R15; R15 := R15[0xbcfb64ab]
521 [-]: MOVE      R17 R14      ; R17 := R14
522 [-]: CALL      R15 3 2      ; R15 := R15(R16,R17)
523 [-]: TEST      R15 0        ; if not R15 then PC := 529
524 [-]: JMP       529          ; PC := 529
525 [-]: GETGLOBAL R15 K4       ; R15 := 0xcbd666e1
526 [-]: CONST     R16 0        ; R16 := 0.000000
527 [-]: CALL      R15 2 1      ; R15(R16)
528 [-]: JMP       481          ; PC := 481
529 [-]: CONST     R15 5        ; R15 := 5.000000
530 [-]: CONST     R16 7        ; R16 := 7.000000
531 [-]: CONST     R17 10       ; R17 := 10.000000
532 [-]: GETGLOBAL R18 K12      ; R18 := 0x89326c93
533 [-]: SELF      R18 R18 K13  ; R19 := R18; R18 := R18[0x18d05d30]
534 [-]: CALL      R18 2 2      ; R18 := R18(R19)
535 [-]: TEST      R18 0        ; if not R18 then PC := 586
536 [-]: JMP       586          ; PC := 586
537 [-]: GETGLOBAL R18 K4       ; R18 := 0xcbd666e1
538 [-]: CONST     R19 0        ; R19 := 0.000000
539 [-]: CALL      R18 2 1      ; R18(R19)
540 [-]: GETUPVAL  R18 U15      ; R18 := U15
541 [-]: CALL      R18 1 1      ; R18()
542 [-]: GETGLOBAL R18 K4       ; R18 := 0xcbd666e1
543 [-]: MOVE      R19 R15      ; R19 := R15
544 [-]: CALL      R18 2 1      ; R18(R19)
545 [-]: GETUPVAL  R18 U15      ; R18 := U15
546 [-]: CALL      R18 1 1      ; R18()
547 [-]: GETUPVAL  R18 U16      ; R18 := U16
548 [-]: GETUPVAL  R19 U17      ; R19 := U17
549 [-]: CALL      R18 2 1      ; R18(R19)
550 [-]: GETGLOBAL R18 K4       ; R18 := 0xcbd666e1
551 [-]: MOVE      R19 R16      ; R19 := R16
552 [-]: CALL      R18 2 1      ; R18(R19)
553 [-]: GETUPVAL  R18 U15      ; R18 := U15
554 [-]: CALL      R18 1 1      ; R18()
555 [-]: GETUPVAL  R18 U16      ; R18 := U16
556 [-]: GETUPVAL  R19 U18      ; R19 := U18
557 [-]: CALL      R18 2 1      ; R18(R19)
558 [-]: GETGLOBAL R18 K4       ; R18 := 0xcbd666e1
559 [-]: MOVE      R19 R17      ; R19 := R17
560 [-]: CALL      R18 2 1      ; R18(R19)
561 [-]: GETUPVAL  R18 U15      ; R18 := U15
562 [-]: CALL      R18 1 1      ; R18()
563 [-]: GETUPVAL  R18 U16      ; R18 := U16
564 [-]: GETUPVAL  R19 U19      ; R19 := U19
565 [-]: CALL      R18 2 1      ; R18(R19)
566 [-]: GETGLOBAL R18 K2       ; R18 := 0x7b998233
567 [-]: MOVE      R19 R1       ; R19 := R1
568 [-]: CALL      R18 2 2      ; R18 := R18(R19)
569 [-]: TEST      R18 1        ; if R18 then PC := 602
570 [-]: JMP       602          ; PC := 602
571 [-]: SELF      R18 R1 K110  ; R19 := R1; R18 := R1[0x5d985c7e]
572 [-]: GETGLOBAL R20 K92      ; R20 := 0xb009bbc6
573 [-]: GETUPVAL  R21 U9       ; R21 := U9
574 [-]: CALL      R20 2 2      ; R20 := R20(R21)
575 [-]: LOADKB    R21 0 0      ; R21 := false
576 [-]: CONST     R22 3        ; R22 := 3.000000
577 [-]: CONST     R23 1        ; R23 := 1.000000
578 [-]: LOADKB    R24 1 0      ; R24 := true
579 [-]: CONST     R25 0        ; R25 := 0.750000
580 [-]: CALL      R18 8 1      ; R18(R19,R20,R21,R22,R23,R24,R25)
581 [-]: SELF      R18 R1 K96   ; R19 := R1; R18 := R1[0x768274d6]
582 [-]: LOADKB    R20 1 0      ; R20 := true
583 [-]: LOADKB    R21 1 0      ; R21 := true
584 [-]: CALL      R18 4 1      ; R18(R19,R20,R21)
585 [-]: JMP       602          ; PC := 602
586 [-]: GETGLOBAL R18 K4       ; R18 := 0xcbd666e1
587 [-]: MOVE      R19 R15      ; R19 := R15
588 [-]: CALL      R18 2 1      ; R18(R19)
589 [-]: GETGLOBAL R18 K2       ; R18 := 0x7b998233
590 [-]: MOVE      R19 R1       ; R19 := R1
591 [-]: CALL      R18 2 2      ; R18 := R18(R19)
592 [-]: TEST      R18 1        ; if R18 then PC := 602
593 [-]: JMP       602          ; PC := 602
594 [-]: SELF      R18 R1 K111  ; R19 := R1; R18 := R1[0xd4cc05b4]
595 [-]: CALL      R18 2 2      ; R18 := R18(R19)
596 [-]: TEST      R18 1        ; if R18 then PC := 602
597 [-]: JMP       602          ; PC := 602
598 [-]: GETGLOBAL R18 K4       ; R18 := 0xcbd666e1
599 [-]: CONST     R19 0        ; R19 := 0.000000
600 [-]: CALL      R18 2 1      ; R18(R19)
601 [-]: JMP       589          ; PC := 589
602 [-]: GETGLOBAL R18 K2       ; R18 := 0x7b998233
603 [-]: MOVE      R19 R1       ; R19 := R1
604 [-]: CALL      R18 2 2      ; R18 := R18(R19)
605 [-]: TEST      R18 1        ; if R18 then PC := 671
606 [-]: JMP       671          ; PC := 671
607 [-]: SELF      R18 R1 K96   ; R19 := R1; R18 := R1[0x768274d6]
608 [-]: LOADKB    R20 1 0      ; R20 := true
609 [-]: LOADKB    R21 1 0      ; R21 := true
610 [-]: CALL      R18 4 1      ; R18(R19,R20,R21)
611 [-]: SELF      R18 R1 K53   ; R19 := R1; R18 := R1[0x069d881f]
612 [-]: LOADKB    R20 0 0      ; R20 := false
613 [-]: CALL      R18 3 1      ; R18(R19,R20)
614 [-]: SELF      R18 R1 K86   ; R19 := R1; R18 := R1[0x020d4331]
615 [-]: CALL      R18 2 2      ; R18 := R18(R19)
616 [-]: SELF      R18 R18 K87  ; R19 := R18; R18 := R18[0xdf2dca58]
617 [-]: LOADKB    R20 0 0      ; R20 := false
618 [-]: CALL      R18 3 1      ; R18(R19,R20)
619 [-]: SELF      R18 R1 K98   ; R19 := R1; R18 := R1[0x568f4e91]
620 [-]: CONST     R20 1        ; R20 := 1.000000
621 [-]: CALL      R18 3 1      ; R18(R19,R20)
622 [-]: SELF      R18 R1 K88   ; R19 := R1; R18 := R1[0xd3a01177]
623 [-]: CALL      R18 2 2      ; R18 := R18(R19)
624 [-]: SELF      R18 R18 K99  ; R19 := R18; R18 := R18[0x258e7323]
625 [-]: LOADKB    R20 1 0      ; R20 := true
626 [-]: CALL      R18 3 1      ; R18(R19,R20)
627 [-]: SELF      R18 R5 K112  ; R19 := R5; R18 := R5[0xd80991c3]
628 [-]: CONST     R20 1        ; R20 := 1.000000
629 [-]: CALL      R18 3 1      ; R18(R19,R20)
630 [-]: SELF      R18 R5 K112  ; R19 := R5; R18 := R5[0xd80991c3]
631 [-]: CONST     R20 0        ; R20 := 0.000000
632 [-]: CALL      R18 3 1      ; R18(R19,R20)
633 [-]: SELF      R18 R5 K112  ; R19 := R5; R18 := R5[0xd80991c3]
634 [-]: CONST     R20 5        ; R20 := 5.000000
635 [-]: CALL      R18 3 1      ; R18(R19,R20)
636 [-]: SELF      R18 R5 K113  ; R19 := R5; R18 := R5[0x12dd9da2]
637 [-]: CONST     R20 147      ; R20 := 147.000000
638 [-]: CONST     R21 3        ; R21 := 3.000000
639 [-]: CONST     R22 0        ; R22 := 0.000000
640 [-]: CALL      R18 5 1      ; R18(R19,R20,R21,R22)
641 [-]: SELF      R18 R1 K114  ; R19 := R1; R18 := R1[0x47901f07]
642 [-]: GETGLOBAL R20 K35      ; R20 := 0x88efc25e
643 [-]: GETUPVAL  R21 U1       ; R21 := U1
644 [-]: CALL      R20 2 2      ; R20 := R20(R21)
645 [-]: GETGLOBAL R21 K115     ; R21 := EMPTY_SYMBOL
646 [-]: CALL      R18 4 1      ; R18(R19,R20,R21)
647 [-]: TEST      R2 1         ; if R2 then PC := 667
648 [-]: JMP       667          ; PC := 667
649 [-]: SELF      R18 R1 K114  ; R19 := R1; R18 := R1[0x47901f07]
650 [-]: GETGLOBAL R20 K35      ; R20 := 0x88efc25e
651 [-]: GETUPVAL  R21 U3       ; R21 := U3
652 [-]: CALL      R20 2 2      ; R20 := R20(R21)
653 [-]: GETGLOBAL R21 K115     ; R21 := EMPTY_SYMBOL
654 [-]: CALL      R18 4 1      ; R18(R19,R20,R21)
655 [-]: SELF      R18 R1 K114  ; R19 := R1; R18 := R1[0x47901f07]
656 [-]: GETGLOBAL R20 K35      ; R20 := 0x88efc25e
657 [-]: GETUPVAL  R21 U4       ; R21 := U4
658 [-]: CALL      R20 2 2      ; R20 := R20(R21)
659 [-]: GETGLOBAL R21 K115     ; R21 := EMPTY_SYMBOL
660 [-]: CALL      R18 4 1      ; R18(R19,R20,R21)
661 [-]: SELF      R18 R1 K114  ; R19 := R1; R18 := R1[0x47901f07]
662 [-]: GETGLOBAL R20 K35      ; R20 := 0x88efc25e
663 [-]: GETUPVAL  R21 U5       ; R21 := U5
664 [-]: CALL      R20 2 2      ; R20 := R20(R21)
665 [-]: GETGLOBAL R21 K115     ; R21 := EMPTY_SYMBOL
666 [-]: CALL      R18 4 1      ; R18(R19,R20,R21)
667 [-]: GETUPVAL  R18 U12      ; R18 := U12
668 [-]: MOVE      R19 R1       ; R19 := R1
669 [-]: LOADKB    R20 0 0      ; R20 := false
670 [-]: CALL      R18 3 1      ; R18(R19,R20)
671 [-]: NEWTABLE  R18 0 0      ; R18 := {}
672 [-]: CONST     R19 0        ; R19 := 0.000000
673 [-]: GETGLOBAL R20 K2       ; R20 := 0x7b998233
674 [-]: MOVE      R21 R1       ; R21 := R1
675 [-]: CALL      R20 2 2      ; R20 := R20(R21)
676 [-]: TEST      R20 1        ; if R20 then PC := 744
677 [-]: JMP       744          ; PC := 744
678 [-]: GETGLOBAL R20 K2       ; R20 := 0x7b998233
679 [-]: SELF      R21 R1 K5    ; R22 := R1; R21 := R1[0x5e651723]
680 [-]: CALL      R21 2 0      ; R21,... := R21(R22)
681 [-]: CALL      R20 0 2      ; R20 := R20(R21,...)
682 [-]: TEST      R20 1        ; if R20 then PC := 744
683 [-]: JMP       744          ; PC := 744
684 [-]: SELF      R20 R1 K116  ; R21 := R1; R20 := R1[0x2047cfe7]
685 [-]: CALL      R20 2 2      ; R20 := R20(R21)
686 [-]: TEST      R20 1        ; if R20 then PC := 744
687 [-]: JMP       744          ; PC := 744
688 [-]: SELF      R20 R6 K117  ; R21 := R6; R20 := R6[0x73901acf]
689 [-]: CALL      R20 2 2      ; R20 := R20(R21)
690 [-]: TEST      R20 1        ; if R20 then PC := 744
691 [-]: JMP       744          ; PC := 744
692 [-]: GETGLOBAL R20 K4       ; R20 := 0xcbd666e1
693 [-]: CONST     R21 1        ; R21 := 1.000000
694 [-]: CALL      R20 2 1      ; R20(R21)
695 [-]: GETGLOBAL R20 K12      ; R20 := 0x89326c93
696 [-]: SELF      R20 R20 K118 ; R21 := R20; R20 := R20[0x7d108ddb]
697 [-]: CALL      R20 2 2      ; R20 := R20(R21)
698 [-]: GETGLOBAL R21 K119     ; R21 := 0xcfc01047
699 [-]: MOVE      R22 R20      ; R22 := R20
700 [-]: CALL      R21 2 4      ; R21,R22,R23 := R21(R22)
701 [-]: JMP       738          ; PC := 738
702 [-]: GETGLOBAL R26 K2       ; R26 := 0x7b998233
703 [-]: MOVE      R27 R25      ; R27 := R25
704 [-]: CALL      R26 2 2      ; R26 := R26(R27)
705 [-]: TEST      R26 1        ; if R26 then PC := 738
706 [-]: JMP       738          ; PC := 738
707 [-]: SELF      R26 R25 K28  ; R27 := R25; R26 := R25[0x5ca33548]
708 [-]: CALL      R26 2 2      ; R26 := R26(R27)
709 [-]: GETTABLE  R26 R18 R26  ; R26 := R18[R26]
710 [-]: TEST      R26 1        ; if R26 then PC := 738
711 [-]: JMP       738          ; PC := 738
712 [-]: SELF      R26 R25 K120 ; R27 := R25; R26 := R25[0xbb610e5b]
713 [-]: CALL      R26 2 2      ; R26 := R26(R27)
714 [-]: EQ        1 R26 R1     ; if R26 == R1 then PC := 738
715 [-]: JMP       738          ; PC := 738
716 [-]: GETGLOBAL R27 K2       ; R27 := 0x7b998233
717 [-]: SELF      R28 R25 K120 ; R29 := R25; R28 := R25[0xbb610e5b]
718 [-]: CALL      R28 2 0      ; R28,... := R28(R29)
719 [-]: CALL      R27 0 2      ; R27 := R27(R28,...)
720 [-]: TEST      R27 1        ; if R27 then PC := 738
721 [-]: JMP       738          ; PC := 738
722 [-]: SELF      R27 R25 K120 ; R28 := R25; R27 := R25[0xbb610e5b]
723 [-]: CALL      R27 2 2      ; R27 := R27(R28)
724 [-]: SELF      R27 R27 K117 ; R28 := R27; R27 := R27[0x73901acf]
725 [-]: CALL      R27 2 2      ; R27 := R27(R28)
726 [-]: TEST      R27 1        ; if R27 then PC := 734
727 [-]: JMP       734          ; PC := 734
728 [-]: SELF      R27 R25 K120 ; R28 := R25; R27 := R25[0xbb610e5b]
729 [-]: CALL      R27 2 2      ; R27 := R27(R28)
730 [-]: SELF      R27 R27 K116 ; R28 := R27; R27 := R27[0x2047cfe7]
731 [-]: CALL      R27 2 2      ; R27 := R27(R28)
732 [-]: TEST      R27 0        ; if not R27 then PC := 738
733 [-]: JMP       738          ; PC := 738
734 [-]: SELF      R27 R25 K28  ; R28 := R25; R27 := R25[0x5ca33548]
735 [-]: CALL      R27 2 2      ; R27 := R27(R28)
736 [-]: SETTABLE  R18 R27 K15  ; R18[R27] := true
737 [-]: ADD       R19 R19 K121 ; R19 := R19 + 1.000000
738 [-]: TFORLOOP  R21 2        ; R24,R25 :=  R21(R22,R23); if R24 ~= nil then begin PC = 702; R23 := R24 end
739 [-]: JMP       702          ; PC := 702
740 [-]: LE        0 K121 R19   ; if 1.000000 > R19 then PC := 673
741 [-]: JMP       673          ; PC := 673
742 [-]: JMP       744          ; PC := 744
743 [-]: JMP       673          ; PC := 673
744 [-]: GETGLOBAL R27 K2       ; R27 := 0x7b998233
745 [-]: MOVE      R28 R1       ; R28 := R1
746 [-]: CALL      R27 2 2      ; R27 := R27(R28)
747 [-]: TEST      R27 1        ; if R27 then PC := 781
748 [-]: JMP       781          ; PC := 781
749 [-]: GETUPVAL  R27 U12      ; R27 := U12
750 [-]: MOVE      R28 R1       ; R28 := R1
751 [-]: LOADKB    R29 1 0      ; R29 := true
752 [-]: CALL      R27 3 1      ; R27(R28,R29)
753 [-]: GETGLOBAL R27 K12      ; R27 := 0x89326c93
754 [-]: SELF      R27 R27 K13  ; R28 := R27; R27 := R27[0x18d05d30]
755 [-]: CALL      R27 2 2      ; R27 := R27(R28)
756 [-]: TEST      R27 0        ; if not R27 then PC := 766
757 [-]: JMP       766          ; PC := 766
758 [-]: SELF      R27 R1 K110  ; R28 := R1; R27 := R1[0x5d985c7e]
759 [-]: GETGLOBAL R29 K92      ; R29 := 0xb009bbc6
760 [-]: GETUPVAL  R30 U8       ; R30 := U8
761 [-]: CALL      R29 2 2      ; R29 := R29(R30)
762 [-]: LOADKB    R30 0 0      ; R30 := false
763 [-]: CONST     R31 3        ; R31 := 3.000000
764 [-]: CONST     R32 3        ; R32 := 3.000000
765 [-]: CALL      R27 6 1      ; R27(R28,R29,R30,R31,R32)
766 [-]: SELF      R27 R1 K114  ; R28 := R1; R27 := R1[0x47901f07]
767 [-]: GETGLOBAL R29 K35      ; R29 := 0x88efc25e
768 [-]: GETUPVAL  R30 U2       ; R30 := U2
769 [-]: CALL      R29 2 2      ; R29 := R29(R30)
770 [-]: GETGLOBAL R30 K115     ; R30 := EMPTY_SYMBOL
771 [-]: CALL      R27 4 1      ; R27(R28,R29,R30)
772 [-]: SELF      R27 R5 K97   ; R28 := R5; R27 := R5[0x4da725ce]
773 [-]: CONST     R29 0        ; R29 := 0.000000
774 [-]: CALL      R27 3 1      ; R27(R28,R29)
775 [-]: SELF      R27 R5 K97   ; R28 := R5; R27 := R5[0x4da725ce]
776 [-]: CONST     R29 1        ; R29 := 1.000000
777 [-]: CALL      R27 3 1      ; R27(R28,R29)
778 [-]: SELF      R27 R5 K97   ; R28 := R5; R27 := R5[0x4da725ce]
779 [-]: CONST     R29 5        ; R29 := 5.000000
780 [-]: CALL      R27 3 1      ; R27(R28,R29)
781 [-]: GETGLOBAL R27 K12      ; R27 := 0x89326c93
782 [-]: SELF      R27 R27 K13  ; R28 := R27; R27 := R27[0x18d05d30]
783 [-]: CALL      R27 2 2      ; R27 := R27(R28)
784 [-]: TEST      R27 0        ; if not R27 then PC := 831
785 [-]: JMP       831          ; PC := 831
786 [-]: GETGLOBAL R27 K2       ; R27 := 0x7b998233
787 [-]: GETGLOBAL R28 K17      ; R28 := 0xe7f2b02f
788 [-]: SELF      R28 R28 K19  ; R29 := R28; R28 := R28[0x565be9ee]
789 [-]: CALL      R28 2 0      ; R28,... := R28(R29)
790 [-]: CALL      R27 0 2      ; R27 := R27(R28,...)
791 [-]: TEST      R27 1        ; if R27 then PC := 831
792 [-]: JMP       831          ; PC := 831
793 [-]: LOADNIL   R27 R27      ; R27 := nil
794 [-]: GETGLOBAL R28 K2       ; R28 := 0x7b998233
795 [-]: MOVE      R29 R1       ; R29 := R1
796 [-]: CALL      R28 2 2      ; R28 := R28(R29)
797 [-]: TEST      R28 1        ; if R28 then PC := 809
798 [-]: JMP       809          ; PC := 809
799 [-]: SELF      R28 R1 K116  ; R29 := R1; R28 := R1[0x2047cfe7]
800 [-]: CALL      R28 2 2      ; R28 := R28(R29)
801 [-]: TEST      R28 1        ; if R28 then PC := 809
802 [-]: JMP       809          ; PC := 809
803 [-]: SELF      R28 R6 K117  ; R29 := R6; R28 := R6[0x73901acf]
804 [-]: CALL      R28 2 2      ; R28 := R28(R29)
805 [-]: TEST      R28 1        ; if R28 then PC := 809
806 [-]: JMP       809          ; PC := 809
807 [-]: GETUPVAL  R27 U20      ; R27 := U20
808 [-]: JMP       823          ; PC := 823
809 [-]: GETUPVAL  R27 U21      ; R27 := U21
810 [-]: GETGLOBAL R28 K2       ; R28 := 0x7b998233
811 [-]: MOVE      R29 R1       ; R29 := R1
812 [-]: CALL      R28 2 2      ; R28 := R28(R29)
813 [-]: TEST      R28 1        ; if R28 then PC := 823
814 [-]: JMP       823          ; PC := 823
815 [-]: GETGLOBAL R28 K92      ; R28 := 0xb009bbc6
816 [-]: GETUPVAL  R29 U7       ; R29 := U7
817 [-]: CALL      R28 2 2      ; R28 := R28(R29)
818 [-]: SELF      R29 R28 K122 ; R30 := R28; R29 := R28[0xe4c98581]
819 [-]: MOVE      R31 R1       ; R31 := R1
820 [-]: GETGLOBAL R32 K115     ; R32 := EMPTY_SYMBOL
821 [-]: CONST     R33 0        ; R33 := 0.000000
822 [-]: CALL      R29 5 1      ; R29(R30,R31,R32,R33)
823 [-]: GETUPVAL  R29 U16      ; R29 := U16
824 [-]: MOVE      R30 R27      ; R30 := R27
825 [-]: CALL      R29 2 1      ; R29(R30)
826 [-]: GETGLOBAL R29 K4       ; R29 := 0xcbd666e1
827 [-]: CONST     R30 5        ; R30 := 5.000000
828 [-]: CALL      R29 2 1      ; R29(R30)
829 [-]: GETUPVAL  R29 U15      ; R29 := U15
830 [-]: CALL      R29 1 1      ; R29()
831 [-]: GETGLOBAL R29 K7       ; R29 := _T
832 [-]: SETTABLE  R29 K14 K123 ; R29["gStalkerActive"] := false
833 [-]: TEST      R2 0         ; if not R2 then PC := 842
834 [-]: JMP       842          ; PC := 842
835 [-]: GETGLOBAL R29 K4       ; R29 := 0xcbd666e1
836 [-]: CONST     R30 6        ; R30 := 6.500000
837 [-]: CALL      R29 2 1      ; R29(R30)
838 [-]: GETGLOBAL R29 K31      ; R29 := 0x34291f5c
839 [-]: GETTABLE  R29 R29 K32  ; R29 := R29[0x8ee24660]
840 [-]: LOADKB    R30 1 0      ; R30 := true
841 [-]: CALL      R29 2 1      ; R29(R30)
842 [-]: GETGLOBAL R29 K7       ; R29 := _T
843 [-]: SETTABLE  R29 K9 K124  ; R29["StalkerPlayer"] := nil
844 [-]: GETGLOBAL R29 K7       ; R29 := _T
845 [-]: SETTABLE  R29 K8 K124  ; R29["StalkerPlayerAvatar"] := nil
846 [-]: RETURN    R0 1         ; return 


; Function #5:
;
; Name:            
; Defined at line: 362
; #Upvalues:       0
; #Parameters:     0
; Is_vararg:       0
; Max Stack Size:  2

  1 [-]: RETURN    R0 1         ; return 


; Function #6:
;
; Name:            
; Defined at line: 365
; #Upvalues:       0
; #Parameters:     0
; Is_vararg:       0
; Max Stack Size:  2

  1 [-]: RETURN    R0 1         ; return 


