; Name:            
; Defined at line: 1
; #Upvalues:       0
; #Parameters:     0
; Is_vararg:       1
; Max Stack Size:  79

            1 [-]: GETIMPORT R0 1 [nil]
       2 [-]: LOADN R1 0   
       3 [-]: LOADN R2 1   
       4 [-]: LOADN R3 0   
       5 [-]: CALL R0 3 1  
       6 [-]: LOADK R1 K2 [0.050000000000000003]
       7 [-]: LOADN R2 300 
       8 [-]: LOADN R3 1   
       9 [-]: LOADB R4 0   
      10 [-]: LOADNIL R5   
      11 [-]: LOADNIL R6   
      12 [-]: NEWTABLE R7 0 4
      13 [-]: LOADN R8 8   
      14 [-]: LOADN R9 15  
      15 [-]: LOADN R10 25 
      16 [-]: LOADN R11 30 
      17 [-]: SETLIST R7 R8 4 [1]
      18 [-]: NEWTABLE R8 0 4
      19 [-]: LOADN R9 12  
      20 [-]: LOADN R10 25 
      21 [-]: LOADN R11 30 
      22 [-]: LOADN R12 35 
      23 [-]: SETLIST R8 R9 4 [1]
      24 [-]: NEWTABLE R9 0 4
      25 [-]: LOADN R10 7  
      26 [-]: LOADN R11 15 
      27 [-]: LOADN R12 25 
      28 [-]: LOADN R13 30 
      29 [-]: SETLIST R9 R10 4 [1]
      30 [-]: NEWTABLE R10 0 4
      31 [-]: LOADN R11 10 
      32 [-]: LOADN R12 25 
      33 [-]: LOADN R13 30 
      34 [-]: LOADN R14 35 
      35 [-]: SETLIST R10 R11 4 [1]
      36 [-]: NEWTABLE R11 0 0
      37 [-]: LOADN R12 0  
      38 [-]: LOADN R13 0  
      39 [-]: LOADN R14 900
      40 [-]: LOADN R15 1020
      41 [-]: GETIMPORT R16 4 [nil]
      42 [-]: LOADK R17 K5 ["Lotus.Interface.LotusUtilities"]
      43 [-]: CALL R16 1 1 
      44 [-]: GETIMPORT R17 4 [nil]
      45 [-]: LOADK R18 K6 ["Lotus.Scripts.Libs.TransmissionSet"]
      46 [-]: CALL R17 1 1 
      47 [-]: LOADN R18 60 
      48 [-]: GETIMPORT R19 8 [nil]
      49 [-]: LOADK R20 K9 ["/Lotus/Types/Game/SurvivalKuvaExtractorState"]
      50 [-]: CALL R19 1 1 
      51 [-]: GETIMPORT R20 11 [nil]
      52 [-]: LOADK R21 K12 ["/Lotus/Types/Items/MiscItems/Kuva"]
      53 [-]: CALL R20 1 1 
      54 [-]: GETIMPORT R21 14 [nil]
      55 [-]: LOADK R22 K15 ["/Lotus/Language/Game/SurvivalClockMessage"]
      56 [-]: CALL R21 1 1 
      57 [-]: GETIMPORT R22 14 [nil]
      58 [-]: LOADK R23 K16 ["TimeLeft"]
      59 [-]: CALL R22 1 1 
      60 [-]: GETIMPORT R23 14 [nil]
      61 [-]: LOADK R24 K17 ["TimeElapsed"]
      62 [-]: CALL R23 1 1 
      63 [-]: GETIMPORT R24 14 [nil]
      64 [-]: LOADK R25 K18 ["ArtifactIntervalTime"]
      65 [-]: CALL R24 1 1 
      66 [-]: GETIMPORT R25 14 [nil]
      67 [-]: LOADK R26 K19 ["ArtifactsActive"]
      68 [-]: CALL R25 1 1 
      69 [-]: GETIMPORT R26 14 [nil]
      70 [-]: LOADK R27 K20 ["ArtifactsUsed"]
      71 [-]: CALL R26 1 1 
      72 [-]: GETIMPORT R27 14 [nil]
      73 [-]: LOADK R28 K21 ["SurvivalMissionState"]
      74 [-]: CALL R27 1 1 
      75 [-]: GETIMPORT R28 14 [nil]
      76 [-]: LOADK R29 K22 ["RewardsGiven"]
      77 [-]: CALL R28 1 1 
      78 [-]: GETIMPORT R29 14 [nil]
      79 [-]: LOADK R30 K23 ["EndMissionTimer"]
      80 [-]: CALL R29 1 1 
      81 [-]: GETIMPORT R30 14 [nil]
      82 [-]: LOADK R31 K24 ["VoidProjectionFlow"]
      83 [-]: CALL R30 1 1 
      84 [-]: GETIMPORT R31 14 [nil]
      85 [-]: LOADK R32 K25 ["ShouldSpawnSurvivalMiniboss"]
      86 [-]: CALL R31 1 1 
      87 [-]: GETIMPORT R32 14 [nil]
      88 [-]: LOADK R33 K26 ["SurvivalCapsuleLevelCapacity"]
      89 [-]: CALL R32 1 1 
      90 [-]: GETIMPORT R33 14 [nil]
      91 [-]: LOADK R34 K27 ["SquadLinkRewardsGiven"]
      92 [-]: CALL R33 1 1 
      93 [-]: GETIMPORT R34 14 [nil]
      94 [-]: LOADK R35 K28 ["IncomingSurvivalPillars"]
      95 [-]: CALL R34 1 1 
      96 [-]: GETIMPORT R35 14 [nil]
      97 [-]: LOADK R36 K29 ["ActiveSurvivalPillars"]
      98 [-]: CALL R35 1 1 
      99 [-]: GETIMPORT R36 14 [nil]
     100 [-]: LOADK R37 K30 ["ActivatingSurvivalPillars"]
     101 [-]: CALL R36 1 1 
     102 [-]: GETIMPORT R37 14 [nil]
     103 [-]: LOADK R38 K31 ["KuvaExtractorSurvivalPillars"]
     104 [-]: CALL R37 1 1 
     105 [-]: GETIMPORT R38 4 [nil]
     106 [-]: LOADK R39 K32 ["EE.Interface.Utilities"]
     107 [-]: CALL R38 1 1 
     108 [-]: GETIMPORT R39 4 [nil]
     109 [-]: LOADK R40 K33 ["Lotus.Scripts.Libs.CommonGamemodeFunctions"]
     110 [-]: CALL R39 1 1 
     111 [-]: GETIMPORT R40 4 [nil]
     112 [-]: LOADK R41 K34 ["Lotus.Scripts.Libs.ObjectiveText"]
     113 [-]: CALL R40 1 1 
     114 [-]: GETIMPORT R41 4 [nil]
     115 [-]: LOADK R42 K35 ["Lotus.Scripts.Libs.SquadLink"]
     116 [-]: CALL R41 1 1 
     117 [-]: GETIMPORT R42 14 [nil]
     118 [-]: LOADK R43 K36 ["SurvivalTime"]
     119 [-]: CALL R42 1 1 
     120 [-]: LOADNIL R43  
     121 [-]: LOADNIL R44  
     122 [-]: GETIMPORT R45 38 [nil]
     123 [-]: GETIMPORT R47 41 [nil]
     124 [-]: ORK R46 R47 K39 [0]
     125 [-]: SETTABLEKS R46 R45 K40 ["SquadLinkSurvivalGiveRewards"]
     126 [-]: NEWCLOSURE R45 P0
     127 [-]: MOVE R1 R44  
     128 [-]: NEWCLOSURE R46 P1
     129 [-]: MOVE R1 R44  
     130 [-]: NEWCLOSURE R47 P2
     131 [-]: MOVE R1 R43  
     132 [-]: DUPCLOSURE R48 K42 []
     133 [-]: DUPCLOSURE R49 K43 []
     134 [-]: MOVE R0 R27  
     135 [-]: MOVE R0 R47  
     136 [-]: MOVE R0 R48  
     137 [-]: DUPCLOSURE R50 K44 []
     138 [-]: DUPCLOSURE R51 K45 []
     139 [-]: MOVE R0 R38  
     140 [-]: DUPCLOSURE R52 K46 []
     141 [-]: DUPCLOSURE R53 K47 []
     142 [-]: DUPCLOSURE R54 K48 []
     143 [-]: MOVE R0 R16  
     144 [-]: DUPCLOSURE R55 K49 []
     145 [-]: MOVE R0 R27  
     146 [-]: MOVE R0 R22  
     147 [-]: SETGLOBAL R55 K50 ["UpdateFog"]
     148 [-]: DUPCLOSURE R55 K51 []
     149 [-]: DUPCLOSURE R56 K52 []
     150 [-]: MOVE R0 R41  
     151 [-]: DUPCLOSURE R57 K53 []
     152 [-]: MOVE R0 R41  
     153 [-]: SETGLOBAL R57 K54 ["AlarmActionDisabledText"]
     154 [-]: DUPCLOSURE R57 K55 []
     155 [-]: SETGLOBAL R57 K56 ["ClearAlarmActionDisabledText"]
     156 [-]: DUPCLOSURE R57 K57 []
     157 [-]: DUPCLOSURE R58 K58 []
     158 [-]: DUPCLOSURE R59 K59 []
     159 [-]: NEWCLOSURE R60 P18
     160 [-]: MOVE R0 R40  
     161 [-]: MOVE R1 R18  
     162 [-]: NEWCLOSURE R61 P19
     163 [-]: MOVE R0 R40  
     164 [-]: MOVE R0 R16  
     165 [-]: MOVE R0 R39  
     166 [-]: MOVE R0 R38  
     167 [-]: MOVE R0 R22  
     168 [-]: MOVE R0 R27  
     169 [-]: MOVE R0 R34  
     170 [-]: MOVE R0 R36  
     171 [-]: MOVE R0 R35  
     172 [-]: MOVE R0 R37  
     173 [-]: MOVE R1 R18  
     174 [-]: MOVE R0 R60  
     175 [-]: MOVE R1 R6   
     176 [-]: SETGLOBAL R61 K60 ["SurvivalHUD"]
     177 [-]: DUPCLOSURE R61 K61 []
     178 [-]: MOVE R0 R22  
     179 [-]: MOVE R0 R40  
     180 [-]: MOVE R0 R16  
     181 [-]: MOVE R0 R42  
     182 [-]: DUPCLOSURE R62 K62 []
     183 [-]: MOVE R0 R22  
     184 [-]: DUPCLOSURE R63 K63 []
     185 [-]: MOVE R0 R16  
     186 [-]: MOVE R0 R22  
     187 [-]: MOVE R0 R23  
     188 [-]: MOVE R0 R17  
     189 [-]: SETGLOBAL R63 K64 ["PickupAddTime"]
     190 [-]: DUPCLOSURE R63 K65 []
     191 [-]: MOVE R0 R39  
     192 [-]: SETGLOBAL R63 K66 ["IncomingPillarMarkerFlash"]
     193 [-]: DUPCLOSURE R63 K67 []
     194 [-]: DUPCLOSURE R64 K68 []
     195 [-]: DUPCLOSURE R65 K69 []
     196 [-]: MOVE R0 R23  
     197 [-]: MOVE R0 R9   
     198 [-]: MOVE R0 R10  
     199 [-]: MOVE R0 R7   
     200 [-]: MOVE R0 R8   
     201 [-]: MOVE R0 R16  
     202 [-]: DUPCLOSURE R66 K70 []
     203 [-]: MOVE R0 R65  
     204 [-]: DUPCLOSURE R67 K71 []
     205 [-]: MOVE R0 R22  
     206 [-]: MOVE R0 R65  
     207 [-]: MOVE R0 R27  
     208 [-]: MOVE R0 R38  
     209 [-]: MOVE R0 R42  
     210 [-]: NEWCLOSURE R68 P29
     211 [-]: MOVE R1 R13  
     212 [-]: MOVE R0 R65  
     213 [-]: NEWCLOSURE R69 P30
     214 [-]: MOVE R0 R23  
     215 [-]: MOVE R0 R29  
     216 [-]: MOVE R1 R15  
     217 [-]: MOVE R0 R38  
     218 [-]: MOVE R1 R14  
     219 [-]: MOVE R0 R39  
     220 [-]: MOVE R0 R25  
     221 [-]: MOVE R0 R11  
     222 [-]: MOVE R0 R64  
     223 [-]: MOVE R0 R31  
     224 [-]: NEWCLOSURE R70 P31
     225 [-]: MOVE R0 R67  
     226 [-]: MOVE R0 R65  
     227 [-]: MOVE R1 R12  
     228 [-]: MOVE R0 R69  
     229 [-]: MOVE R1 R13  
     230 [-]: DUPCLOSURE R71 K72 []
     231 [-]: MOVE R0 R36  
     232 [-]: SETGLOBAL R71 K73 ["OnActivated"]
     233 [-]: DUPCLOSURE R71 K74 []
     234 [-]: SETGLOBAL R71 K75 ["CheckIfInUse"]
     235 [-]: DUPCLOSURE R71 K76 []
     236 [-]: MOVE R0 R32  
     237 [-]: MOVE R0 R27  
     238 [-]: MOVE R0 R35  
     239 [-]: MOVE R0 R47  
     240 [-]: MOVE R0 R49  
     241 [-]: MOVE R0 R25  
     242 [-]: MOVE R0 R24  
     243 [-]: MOVE R0 R17  
     244 [-]: MOVE R0 R34  
     245 [-]: MOVE R0 R31  
     246 [-]: DUPCLOSURE R72 K77 []
     247 [-]: MOVE R0 R71  
     248 [-]: SETGLOBAL R72 K78 ["RandomArtifactScript"]
     249 [-]: DUPCLOSURE R72 K79 []
     250 [-]: MOVE R0 R25  
     251 [-]: MOVE R0 R35  
     252 [-]: MOVE R0 R0   
     253 [-]: MOVE R0 R37  
     254 [-]: MOVE R0 R27  
     255 [-]: MOVE R0 R17  
     256 [-]: MOVE R0 R42  
     257 [-]: SETGLOBAL R72 K80 ["ArtifactEnable"]
     258 [-]: DUPCLOSURE R72 K81 []
     259 [-]: MOVE R0 R22  
     260 [-]: MOVE R0 R26  
     261 [-]: MOVE R0 R47  
     262 [-]: MOVE R0 R36  
     263 [-]: MOVE R0 R35  
     264 [-]: MOVE R0 R27  
     265 [-]: MOVE R0 R17  
     266 [-]: MOVE R0 R42  
     267 [-]: SETGLOBAL R72 K82 ["ArtifactActivated"]
     268 [-]: DUPCLOSURE R72 K83 []
     269 [-]: MOVE R0 R27  
     270 [-]: MOVE R0 R31  
     271 [-]: MOVE R0 R37  
     272 [-]: MOVE R0 R35  
     273 [-]: SETGLOBAL R72 K84 ["KuvaArtifactLoop"]
     274 [-]: NEWCLOSURE R72 P39
     275 [-]: MOVE R0 R19  
     276 [-]: MOVE R0 R59  
     277 [-]: MOVE R0 R17  
     278 [-]: MOVE R0 R27  
     279 [-]: MOVE R1 R18  
     280 [-]: MOVE R0 R39  
     281 [-]: MOVE R0 R57  
     282 [-]: MOVE R0 R20  
     283 [-]: MOVE R0 R22  
     284 [-]: MOVE R1 R4   
     285 [-]: MOVE R0 R47  
     286 [-]: MOVE R0 R37  
     287 [-]: SETGLOBAL R72 K85 ["KuvaExtractorDefense"]
     288 [-]: DUPCLOSURE R72 K86 []
     289 [-]: MOVE R0 R17  
     290 [-]: SETGLOBAL R72 K87 ["KuvaCellPickup"]
     291 [-]: DUPCLOSURE R72 K88 []
     292 [-]: MOVE R0 R28  
     293 [-]: DUPCLOSURE R73 K89 []
     294 [-]: MOVE R0 R11  
     295 [-]: MOVE R0 R64  
     296 [-]: NEWCLOSURE R74 P43
     297 [-]: MOVE R0 R28  
     298 [-]: MOVE R0 R39  
     299 [-]: MOVE R1 R3   
     300 [-]: MOVE R0 R27  
     301 [-]: MOVE R0 R17  
     302 [-]: MOVE R0 R40  
     303 [-]: MOVE R1 R6   
     304 [-]: MOVE R1 R5   
     305 [-]: DUPCLOSURE R75 K90 []
     306 [-]: MOVE R0 R30  
     307 [-]: MOVE R0 R38  
     308 [-]: MOVE R0 R16  
     309 [-]: NEWCLOSURE R76 P45
     310 [-]: MOVE R1 R5   
     311 [-]: MOVE R1 R2   
     312 [-]: MOVE R0 R38  
     313 [-]: MOVE R1 R3   
     314 [-]: MOVE R0 R22  
     315 [-]: MOVE R0 R42  
     316 [-]: MOVE R0 R61  
     317 [-]: MOVE R0 R73  
     318 [-]: MOVE R0 R70  
     319 [-]: MOVE R1 R4   
     320 [-]: MOVE R0 R28  
     321 [-]: MOVE R0 R33  
     322 [-]: MOVE R0 R17  
     323 [-]: MOVE R0 R74  
     324 [-]: MOVE R0 R75  
     325 [-]: MOVE R0 R27  
     326 [-]: MOVE R0 R23  
     327 [-]: MOVE R0 R39  
     328 [-]: DUPCLOSURE R77 K91 []
     329 [-]: MOVE R0 R41  
     330 [-]: MOVE R0 R27  
     331 [-]: MOVE R0 R22  
     332 [-]: MOVE R0 R17  
     333 [-]: MOVE R0 R40  
     334 [-]: MOVE R0 R42  
     335 [-]: MOVE R0 R21  
     336 [-]: MOVE R0 R38  
     337 [-]: MOVE R0 R39  
     338 [-]: MOVE R0 R76  
     339 [-]: MOVE R0 R72  
     340 [-]: SETGLOBAL R77 K92 ["StartSurvival"]
     341 [-]: DUPCLOSURE R77 K93 []
     342 [-]: MOVE R0 R39  
     343 [-]: SETGLOBAL R77 K94 ["AlarmContextAction"]
     344 [-]: DUPCLOSURE R77 K95 []
     345 [-]: NEWCLOSURE R78 P49
     346 [-]: MOVE R0 R17  
     347 [-]: MOVE R0 R40  
     348 [-]: MOVE R0 R29  
     349 [-]: MOVE R0 R32  
     350 [-]: MOVE R0 R39  
     351 [-]: MOVE R0 R41  
     352 [-]: MOVE R0 R55  
     353 [-]: MOVE R0 R56  
     354 [-]: MOVE R0 R27  
     355 [-]: MOVE R0 R77  
     356 [-]: MOVE R1 R44  
     357 [-]: MOVE R0 R45  
     358 [-]: MOVE R0 R46  
     359 [-]: SETGLOBAL R78 K96 ["SurvivalSetup"]
     360 [-]: NEWCLOSURE R78 P50
     361 [-]: MOVE R0 R27  
     362 [-]: MOVE R0 R23  
     363 [-]: MOVE R0 R42  
     364 [-]: MOVE R0 R40  
     365 [-]: MOVE R0 R39  
     366 [-]: MOVE R0 R29  
     367 [-]: MOVE R0 R70  
     368 [-]: MOVE R1 R1   
     369 [-]: MOVE R0 R41  
     370 [-]: MOVE R1 R2   
     371 [-]: MOVE R0 R38  
     372 [-]: SETGLOBAL R78 K97 ["EndMission"]
     373 [-]: DUPCLOSURE R78 K98 []
     374 [-]: MOVE R0 R27  
     375 [-]: MOVE R0 R28  
     376 [-]: MOVE R0 R17  
     377 [-]: MOVE R0 R47  
     378 [-]: MOVE R0 R39  
     379 [-]: MOVE R0 R19  
     380 [-]: MOVE R0 R22  
     381 [-]: MOVE R0 R40  
     382 [-]: MOVE R0 R23  
     383 [-]: MOVE R0 R38  
     384 [-]: MOVE R0 R42  
     385 [-]: MOVE R0 R21  
     386 [-]: MOVE R0 R30  
     387 [-]: MOVE R0 R75  
     388 [-]: MOVE R0 R76  
     389 [-]: SETGLOBAL R78 K99 ["HostMigrationInit"]
     390 [-]: CLOSEUPVALS R1
     391 [-]: RETURN R0 0  


; Name:            
; Defined at line: 197
; #Upvalues:       1
; #Parameters:     0
; Is_vararg:       0
; Max Stack Size:  8

       0 [-]: GETUPVAL R0 0
       1 [-]: JUMPIF R0 L0 
       2 [-]: NEWTABLE R0 0 0
L 0:   3 [-]: SETUPVAL R0 0
       4 [-]: GETIMPORT R0 1 [nil]
       5 [-]: GETIMPORT R2 3 [nil]
       6 [-]: LOADK R3 K4 ["/Lotus/Types/Actions/SurvivalHackAction"]
       7 [-]: CALL R2 1 -1 
       8 [-]: NAMECALL R0 R0 K5 [0xFB669000]
       9 [-]: CALL R0 -1 1 
      10 [-]: LOADN R3 1   
      11 [-]: LENGTH R1 R0 
      12 [-]: LOADN R2 1   
      13 [-]: FORNPREP R1 L4
L 1:  14 [-]: GETTABLE R4 R0 R3
      15 [-]: FASTCALL1 62 R4 L2
      16 [-]: MOVE R6 R4   
      17 [-]: GETIMPORT R5 7 [nil]
      18 [-]: CALL R5 1 1  
L 2:  19 [-]: JUMPIF R5 L3 
      20 [-]: NAMECALL R5 R4 K8 [0xF37943FF]
      21 [-]: CALL R5 1 1  
      22 [-]: JUMPIFNOT R5 L3
      23 [-]: NAMECALL R5 R4 K9 [0xF4E253B6]
      24 [-]: CALL R5 1 0  
      25 [-]: GETUPVAL R6 0
      26 [-]: FASTCALL2 52 R6 R4 L3
      27 [-]: MOVE R7 R4   
      28 [-]: GETIMPORT R5 12 [nil]
      29 [-]: CALL R5 2 0  
L 3:  30 [-]: FORNLOOP R1 L1
L 4:  31 [-]: RETURN R0 0  


; Name:            
; Defined at line: 210
; #Upvalues:       1
; #Parameters:     0
; Is_vararg:       0
; Max Stack Size:  6

       0 [-]: LOADN R2 1   
       1 [-]: GETUPVAL R3 0
       2 [-]: LENGTH R0 R3 
       3 [-]: LOADN R1 1   
       4 [-]: FORNPREP R0 L3
L 0:   5 [-]: GETUPVAL R4 0
       6 [-]: GETTABLE R3 R4 R2
       7 [-]: FASTCALL1 62 R3 L1
       8 [-]: MOVE R5 R3   
       9 [-]: GETIMPORT R4 1 [nil]
      10 [-]: CALL R4 1 1  
L 1:  11 [-]: JUMPIF R4 L2 
      12 [-]: NAMECALL R4 R3 K2 [0xF37943FF]
      13 [-]: CALL R4 1 1  
      14 [-]: JUMPIF R4 L2 
      15 [-]: NAMECALL R4 R3 K3 [0x383D2E7D]
      16 [-]: CALL R4 1 0  
L 2:  17 [-]: FORNLOOP R0 L0
L 3:  18 [-]: LOADNIL R0   
      19 [-]: SETUPVAL R0 0
      20 [-]: RETURN R0 0  


; Name:            
; Defined at line: 220
; #Upvalues:       1
; #Parameters:     1
; Is_vararg:       0
; Max Stack Size:  9

       0 [-]: GETUPVAL R1 0
       1 [-]: JUMPXEQKNIL R1 L0 NOT
       2 [-]: GETIMPORT R1 1 [nil]
       3 [-]: GETIMPORT R3 3 [nil]
       4 [-]: LOADK R4 K4 ["SurvivalCapsule"]
       5 [-]: CALL R3 1 -1 
       6 [-]: NAMECALL R1 R1 K5 [0xC7FCADA9]
       7 [-]: CALL R1 -1 1 
       8 [-]: SETUPVAL R1 0
L 0:   9 [-]: NEWTABLE R1 0 0
      10 [-]: LOADN R4 1   
      11 [-]: GETUPVAL R5 0
      12 [-]: LENGTH R2 R5 
      13 [-]: LOADN R3 1   
      14 [-]: FORNPREP R2 L3
L 1:  15 [-]: GETUPVAL R6 0
      16 [-]: GETTABLE R5 R6 R4
      17 [-]: NAMECALL R5 R5 K6 [0x53C3399F]
      18 [-]: CALL R5 1 1  
      19 [-]: JUMPIFNOTEQ R5 R0 L2
      20 [-]: GETUPVAL R8 0
      21 [-]: GETTABLE R7 R8 R4
      22 [-]: FASTCALL2 52 R1 R7 L2
      23 [-]: MOVE R6 R1   
      24 [-]: GETIMPORT R5 9 [nil]
      25 [-]: CALL R5 2 0  
L 2:  26 [-]: FORNLOOP R2 L1
L 3:  27 [-]: RETURN R1 1  


; Name:            
; Defined at line: 237
; #Upvalues:       0
; #Parameters:     3
; Is_vararg:       0
; Max Stack Size:  13

       0 [-]: LOADK R3 K0 [3.4028234663852886e+38]
       1 [-]: LOADN R4 0   
       2 [-]: LOADNIL R5   
       3 [-]: LOADNIL R6   
       4 [-]: LOADN R9 1   
       5 [-]: LENGTH R7 R0 
       6 [-]: LOADN R8 1   
       7 [-]: FORNPREP R7 L3
L 0:   8 [-]: GETTABLE R10 R0 R9
       9 [-]: MOVE R12 R1  
      10 [-]: NAMECALL R10 R10 K1 [0x1F420A3A]
      11 [-]: CALL R10 2 1 
      12 [-]: JUMPIFNOTLT R10 R3 L1
      13 [-]: JUMPIFNOTLT R2 R10 L1
      14 [-]: GETTABLE R5 R0 R9
      15 [-]: MOVE R3 R10  
L 1:  16 [-]: JUMPIFNOTLT R4 R10 L2
      17 [-]: GETTABLE R6 R0 R9
      18 [-]: MOVE R4 R10  
L 2:  19 [-]: FORNLOOP R7 L0
L 3:  20 [-]: MOVE R7 R5   
      21 [-]: FASTCALL1 62 R7 L4
      22 [-]: MOVE R9 R7   
      23 [-]: GETIMPORT R8 3 [nil]
      24 [-]: CALL R8 1 1  
L 4:  25 [-]: JUMPIFNOT R8 L5
      26 [-]: MOVE R7 R6   
L 5:  27 [-]: RETURN R7 1  


; Name:            
; Defined at line: 262
; #Upvalues:       3
; #Parameters:     2
; Is_vararg:       0
; Max Stack Size:  20

       0 [-]: LOADK R2 K0 [3.4028234663852886e+38]
       1 [-]: LOADN R3 0   
       2 [-]: LOADNIL R4   
       3 [-]: LOADNIL R5   
       4 [-]: GETIMPORT R6 2 [nil]
       5 [-]: NAMECALL R6 R6 K3 [0x29EF273D]
       6 [-]: CALL R6 1 1  
       7 [-]: NAMECALL R7 R6 K4 [0x66905CB0]
       8 [-]: CALL R7 1 1  
       9 [-]: GETIMPORT R8 6 [nil]
      10 [-]: LOADN R11 1  
      11 [-]: LENGTH R9 R0 
      12 [-]: LOADN R10 1  
      13 [-]: FORNPREP R9 L3
L 0:  14 [-]: GETTABLE R14 R0 R11
      15 [-]: NAMECALL R12 R7 K7 [0x038C6583]
      16 [-]: CALL R12 2 1 
      17 [-]: JUMPIFNOTLT R12 R2 L1
      18 [-]: JUMPIFNOTLT R1 R12 L1
      19 [-]: GETTABLE R4 R0 R11
      20 [-]: MOVE R2 R12  
L 1:  21 [-]: JUMPIFNOTLT R3 R12 L2
      22 [-]: GETTABLE R5 R0 R11
      23 [-]: MOVE R3 R12  
L 2:  24 [-]: FORNLOOP R9 L0
L 3:  25 [-]: MOVE R9 R4   
      26 [-]: FASTCALL1 62 R9 L4
      27 [-]: MOVE R11 R9  
      28 [-]: GETIMPORT R10 9 [nil]
      29 [-]: CALL R10 1 1 
L 4:  30 [-]: JUMPIFNOT R10 L5
      31 [-]: MOVE R9 R5   
L 5:  32 [-]: FASTCALL1 62 R9 L6
      33 [-]: MOVE R11 R9  
      34 [-]: GETIMPORT R10 9 [nil]
      35 [-]: CALL R10 1 1 
L 6:  36 [-]: JUMPIFNOT R10 L18
      37 [-]: GETIMPORT R10 11 [nil]
      38 [-]: LOADK R11 K12 ["Survival: Couldn't find next capsule over nav, using fallback distance check!"]
      39 [-]: CALL R10 1 0 
      40 [-]: LOADNIL R10  
      41 [-]: GETUPVAL R13 0
      42 [-]: NAMECALL R11 R8 K13 [0x0EB34C69]
      43 [-]: CALL R11 2 1 
      44 [-]: LOADN R12 1  
      45 [-]: JUMPIFNOTLT R12 R11 L11
      46 [-]: NEWTABLE R12 0 4
      47 [-]: LOADN R13 3  
      48 [-]: LOADN R14 1  
      49 [-]: LOADN R15 2  
      50 [-]: LOADN R16 4  
      51 [-]: SETLIST R12 R13 4 [1]
      52 [-]: LOADNIL R13  
      53 [-]: LOADN R16 1  
      54 [-]: LENGTH R14 R12
      55 [-]: LOADN R15 1  
      56 [-]: FORNPREP R14 L8
L 7:  57 [-]: GETUPVAL R17 1
      58 [-]: GETTABLE R18 R12 R16
      59 [-]: CALL R17 1 1 
      60 [-]: MOVE R13 R17 
      61 [-]: LENGTH R17 R13
      62 [-]: LOADN R18 0  
      63 [-]: JUMPIFLT R18 R17 L8
      64 [-]: FORNLOOP R14 L7
L 8:  65 [-]: GETTABLEN R15 R13 1
      66 [-]: FASTCALL1 62 R15 L9
      67 [-]: GETIMPORT R14 9 [nil]
      68 [-]: CALL R14 1 1 
L 9:  69 [-]: JUMPIFNOT R14 L10
      70 [-]: GETIMPORT R14 11 [nil]
      71 [-]: LOADK R15 K14 ["Survival: Error finding the next capsule location!"]
      72 [-]: CALL R14 1 0 
      73 [-]: JUMP L11
    
L10:  74 [-]: GETTABLEN R14 R13 1
      75 [-]: NAMECALL R14 R14 K15 [0xD1586535]
      76 [-]: CALL R14 1 1 
      77 [-]: MOVE R10 R14 
L11:  78 [-]: FASTCALL1 62 R10 L12
      79 [-]: MOVE R13 R10 
      80 [-]: GETIMPORT R12 9 [nil]
      81 [-]: CALL R12 1 1 
L12:  82 [-]: JUMPIFNOT R12 L15
      83 [-]: GETIMPORT R12 2 [nil]
      84 [-]: GETIMPORT R14 17 [nil]
      85 [-]: LOADK R15 K18 ["AlarmObjMarker"]
      86 [-]: CALL R14 1 -1
      87 [-]: NAMECALL R12 R12 K19 [0xC7FCADA9]
      88 [-]: CALL R12 -1 1
      89 [-]: LOADN R15 1  
      90 [-]: LENGTH R13 R12
      91 [-]: LOADN R14 1  
      92 [-]: FORNPREP R13 L15
L13:  93 [-]: GETTABLE R16 R12 R15
      94 [-]: NAMECALL R16 R16 K20 [0xE79E7EF4]
      95 [-]: CALL R16 1 1 
      96 [-]: NAMECALL R17 R16 K21 [0x22DA1852]
      97 [-]: CALL R17 1 1 
      98 [-]: GETIMPORT R18 17 [nil]
      99 [-]: LOADK R19 K22 ["Spawn"]
     100 [-]: CALL R18 1 1 
     101 [-]: JUMPIFNOTEQ R17 R18 L14
     102 [-]: GETTABLE R18 R12 R15
     103 [-]: NAMECALL R18 R18 K15 [0xD1586535]
     104 [-]: CALL R18 1 1 
     105 [-]: MOVE R10 R18 
     106 [-]: JUMP L15
    
L14: 107 [-]: FORNLOOP R13 L13
L15: 108 [-]: FASTCALL1 62 R10 L16
     109 [-]: MOVE R13 R10 
     110 [-]: GETIMPORT R12 9 [nil]
     111 [-]: CALL R12 1 1 
L16: 112 [-]: JUMPIFNOT R12 L17
     113 [-]: GETIMPORT R12 11 [nil]
     114 [-]: LOADK R13 K23 ["Survival: Couldn't determine pos, using origin!"]
     115 [-]: CALL R12 1 0 
     116 [-]: GETIMPORT R12 25 [nil]
     117 [-]: CALL R12 0 1 
     118 [-]: MOVE R10 R12 
L17: 119 [-]: GETUPVAL R12 2
     120 [-]: MOVE R13 R0  
     121 [-]: MOVE R14 R10 
     122 [-]: LOADN R15 0  
     123 [-]: CALL R12 3 1 
     124 [-]: MOVE R9 R12  
L18: 125 [-]: RETURN R9 1  


; Name:            
; Defined at line: 331
; #Upvalues:       0
; #Parameters:     0
; Is_vararg:       0
; Max Stack Size:  4

       0 [-]: GETIMPORT R0 1 [nil]
       1 [-]: NAMECALL R0 R0 K2 [0xEF893AEC]
       2 [-]: CALL R0 1 1  
       3 [-]: LOADB R1 1   
       4 [-]: GETTABLEKS R2 R0 K3 ["alertId"]
       5 [-]: JUMPXEQKS R2 K4 L1 NOT [""]
       6 [-]: LOADB R1 1   
       7 [-]: GETTABLEKS R2 R0 K5 ["invasionId"]
       8 [-]: JUMPXEQKS R2 K4 L1 NOT [""]
       9 [-]: GETTABLEKS R1 R0 K6 ["syndicateTag"]
      10 [-]: NAMECALL R1 R1 K7 [0x56C01834]
      11 [-]: CALL R1 1 1  
      12 [-]: JUMPIF R1 L1 
      13 [-]: GETTABLEKS R2 R0 K8 ["maxWaveNum"]
      14 [-]: LOADN R3 0   
      15 [-]: JUMPIFLT R3 R2 L0
      16 [-]: LOADB R1 0 +1
L 0:  17 [-]: LOADB R1 1   
L 1:  18 [-]: RETURN R1 1  


; Name:            
; Defined at line: 336
; #Upvalues:       1
; #Parameters:     0
; Is_vararg:       0
; Max Stack Size:  6

       0 [-]: GETIMPORT R0 1 [nil]
       1 [-]: NAMECALL R0 R0 K2 [0xEF893AEC]
       2 [-]: CALL R0 1 1  
       3 [-]: GETUPVAL R2 0
       4 [-]: GETTABLEKS R1 R2 K3 [0x06D055F9]
       5 [-]: GETTABLEKS R3 R0 K4 ["maxWaveNum"]
       6 [-]: LOADN R4 0   
       7 [-]: JUMPIFLT R4 R3 L0
       8 [-]: LOADB R2 0 +1
L 0:   9 [-]: LOADB R2 1   
L 1:  10 [-]: GETTABLEKS R5 R0 K4 ["maxWaveNum"]
      11 [-]: MULK R4 R5 K5 [60]
      12 [-]: FASTCALL2K 19 R4 K6 L2 [3600]
      13 [-]: LOADK R5 K6 [3600]
      14 [-]: GETIMPORT R3 9 [nil]
      15 [-]: CALL R3 2 1  
L 2:  16 [-]: LOADN R4 600 
      17 [-]: CALL R1 3 -1 
      18 [-]: RETURN R1 -1 


; Name:            
; Defined at line: 341
; #Upvalues:       0
; #Parameters:     0
; Is_vararg:       0
; Max Stack Size:  4

       0 [-]: GETIMPORT R0 1 [nil]
       1 [-]: NAMECALL R0 R0 K2 [0xEF893AEC]
       2 [-]: CALL R0 1 1  
       3 [-]: GETTABLEKS R1 R0 K3 ["goalTag"]
       4 [-]: GETIMPORT R2 5 [nil]
       5 [-]: LOADK R3 K6 ["LateStartSurvivalMission"]
       6 [-]: CALL R2 1 1  
       7 [-]: JUMPIFNOTEQ R1 R2 L0
       8 [-]: LOADB R2 1   
       9 [-]: RETURN R2 1  
L 0:  10 [-]: LOADB R2 0   
      11 [-]: RETURN R2 1  


; Name:            
; Defined at line: 351
; #Upvalues:       0
; #Parameters:     0
; Is_vararg:       0
; Max Stack Size:  4

       0 [-]: GETIMPORT R0 1 [nil]
       1 [-]: NAMECALL R0 R0 K2 [0xEF893AEC]
       2 [-]: CALL R0 1 1  
       3 [-]: GETTABLEKS R1 R0 K3 ["goalTag"]
       4 [-]: GETIMPORT R2 5 [nil]
       5 [-]: LOADK R3 K6 ["KuvaSurvival"]
       6 [-]: CALL R2 1 1  
       7 [-]: JUMPIFNOTEQ R1 R2 L0
       8 [-]: LOADB R2 1   
       9 [-]: RETURN R2 1  
L 0:  10 [-]: LOADB R2 0   
      11 [-]: RETURN R2 1  


; Name:            
; Defined at line: 360
; #Upvalues:       1
; #Parameters:     0
; Is_vararg:       0
; Max Stack Size:  4

       0 [-]: LOADB R0 1   
       1 [-]: GETIMPORT R2 1 [nil]
       2 [-]: NAMECALL R2 R2 K2 [0xEF893AEC]
       3 [-]: CALL R2 1 1  
       4 [-]: GETTABLEKS R1 R2 K3 ["periodicMissionTag"]
       5 [-]: GETUPVAL R3 0
       6 [-]: GETTABLEKS R2 R3 K4 ["ELITE_ALERT_PERIODIC_MISSION_TAG"]
       7 [-]: JUMPIFEQ R1 R2 L1
       8 [-]: GETIMPORT R2 1 [nil]
       9 [-]: NAMECALL R2 R2 K2 [0xEF893AEC]
      10 [-]: CALL R2 1 1  
      11 [-]: GETTABLEKS R1 R2 K3 ["periodicMissionTag"]
      12 [-]: GETUPVAL R3 0
      13 [-]: GETTABLEKS R2 R3 K5 ["ELITE_ALERT_PERIODIC_MISSION_TAG_ALT"]
      14 [-]: JUMPIFEQ R1 R2 L0
      15 [-]: LOADB R0 0 +1
L 0:  16 [-]: LOADB R0 1   
L 1:  17 [-]: RETURN R0 1  


; Name:            
; Defined at line: 366
; #Upvalues:       2
; #Parameters:     0
; Is_vararg:       0
; Max Stack Size:  25

       0 [-]: GETIMPORT R0 1 [nil]
       1 [-]: NAMECALL R0 R0 K2 [0xEF893AEC]
       2 [-]: CALL R0 1 1  
       3 [-]: GETTABLEKS R1 R0 K3 ["fxLayer"]
       4 [-]: GETIMPORT R2 5 [nil]
       5 [-]: LOADK R3 K6 ["Fire"]
       6 [-]: CALL R2 1 1  
       7 [-]: JUMPIFEQ R1 R2 L0
       8 [-]: GETIMPORT R2 5 [nil]
       9 [-]: LOADK R3 K7 ["Radiation"]
      10 [-]: CALL R2 1 1  
      11 [-]: JUMPIFEQ R1 R2 L0
      12 [-]: GETIMPORT R2 5 [nil]
      13 [-]: LOADK R3 K8 ["Toxin"]
      14 [-]: CALL R2 1 1  
      15 [-]: JUMPIFNOTEQ R1 R2 L1
L 0:  16 [-]: RETURN R0 0  
L 1:  17 [-]: GETIMPORT R2 10 [nil]
      18 [-]: JUMPIF R2 L2 
      19 [-]: GETIMPORT R2 12 [nil]
      20 [-]: JUMPIFNOT R2 L36
      21 [-]: GETIMPORT R2 15 [nil]
      22 [-]: GETIMPORT R3 5 [nil]
      23 [-]: LOADK R4 K16 ["Infestation"]
      24 [-]: CALL R3 1 1  
      25 [-]: JUMPIFNOTEQ R2 R3 L36
L 2:  26 [-]: GETIMPORT R2 18 [nil]
      27 [-]: GETIMPORT R4 20 [nil]
      28 [-]: NAMECALL R2 R2 K21 [0xFB669000]
      29 [-]: CALL R2 2 1  
      30 [-]: NEWTABLE R3 0 0
      31 [-]: LOADN R6 1   
      32 [-]: LENGTH R4 R2 
      33 [-]: LOADN R5 1   
      34 [-]: FORNPREP R4 L6
L 3:  35 [-]: GETTABLE R8 R2 R6
      36 [-]: FASTCALL1 62 R8 L4
      37 [-]: GETIMPORT R7 23 [nil]
      38 [-]: CALL R7 1 1  
L 4:  39 [-]: JUMPIF R7 L5 
      40 [-]: GETTABLE R7 R2 R6
      41 [-]: NAMECALL R7 R7 K24 [0x22DA1852]
      42 [-]: CALL R7 1 1  
      43 [-]: GETIMPORT R8 5 [nil]
      44 [-]: LOADK R9 K25 ["Backdrop"]
      45 [-]: CALL R8 1 1  
      46 [-]: JUMPIFEQ R7 R8 L5
      47 [-]: GETIMPORT R8 5 [nil]
      48 [-]: LOADK R9 K26 ["Cinematics"]
      49 [-]: CALL R8 1 1  
      50 [-]: JUMPIFEQ R7 R8 L5
      51 [-]: MOVE R9 R3   
      52 [-]: GETTABLE R10 R2 R6
      53 [-]: NAMECALL R10 R10 K27 [0xE79E7EF4]
      54 [-]: CALL R10 1 -1
      55 [-]: FASTCALL 52 L5
      56 [-]: GETIMPORT R8 30 [nil]
      57 [-]: CALL R8 -1 0 
L 5:  58 [-]: FORNLOOP R4 L3
L 6:  59 [-]: GETIMPORT R4 18 [nil]
      60 [-]: GETIMPORT R6 32 [nil]
      61 [-]: NAMECALL R4 R4 K21 [0xFB669000]
      62 [-]: CALL R4 2 1  
      63 [-]: LOADNIL R5   
      64 [-]: GETIMPORT R6 15 [nil]
      65 [-]: GETIMPORT R7 5 [nil]
      66 [-]: LOADK R8 K16 ["Infestation"]
      67 [-]: CALL R7 1 1  
      68 [-]: JUMPIFNOTEQ R6 R7 L7
      69 [-]: GETIMPORT R6 12 [nil]
      70 [-]: JUMPIFNOT R6 L7
      71 [-]: GETIMPORT R5 34 [nil]
      72 [-]: JUMP L8
     
L 7:  73 [-]: GETIMPORT R5 36 [nil]
L 8:  74 [-]: GETIMPORT R6 18 [nil]
      75 [-]: NAMECALL R6 R6 K37 [0x18D05D30]
      76 [-]: CALL R6 1 1  
      77 [-]: JUMPIFNOT R6 L12
      78 [-]: LOADN R8 1   
      79 [-]: LENGTH R6 R2 
      80 [-]: LOADN R7 1   
      81 [-]: FORNPREP R6 L19
L 9:  82 [-]: GETTABLE R9 R2 R8
      83 [-]: NAMECALL R9 R9 K24 [0x22DA1852]
      84 [-]: CALL R9 1 1  
      85 [-]: GETIMPORT R10 5 [nil]
      86 [-]: LOADK R11 K25 ["Backdrop"]
      87 [-]: CALL R10 1 1 
      88 [-]: JUMPIFEQ R9 R10 L10
      89 [-]: GETIMPORT R10 5 [nil]
      90 [-]: LOADK R11 K26 ["Cinematics"]
      91 [-]: CALL R10 1 1 
      92 [-]: JUMPIFNOTEQ R9 R10 L11
L10:  93 [-]: GETTABLE R10 R2 R8
      94 [-]: NAMECALL R10 R10 K38 [0xD1586535]
      95 [-]: CALL R10 1 1 
      96 [-]: GETTABLE R11 R2 R8
      97 [-]: NAMECALL R11 R11 K39 [0xCB3851B8]
      98 [-]: CALL R11 1 1 
      99 [-]: GETIMPORT R12 18 [nil]
     100 [-]: GETIMPORT R14 32 [nil]
     101 [-]: MOVE R15 R10 
     102 [-]: MOVE R16 R11 
     103 [-]: NAMECALL R12 R12 K40 [0x05909209]
     104 [-]: CALL R12 4 1 
     105 [-]: GETIMPORT R15 43 [nil]
     106 [-]: GETTABLEKS R17 R5 K45 ["red"]
     107 [-]: DIVK R16 R17 K44 [255]
     108 [-]: GETTABLEKS R18 R5 K46 ["green"]
     109 [-]: DIVK R17 R18 K44 [255]
     110 [-]: GETTABLEKS R19 R5 K47 ["blue"]
     111 [-]: DIVK R18 R19 K44 [255]
     112 [-]: GETTABLEKS R20 R5 K48 ["alpha"]
     113 [-]: DIVK R19 R20 K44 [255]
     114 [-]: NAMECALL R13 R12 K49 [0x986D2AB8]
     115 [-]: CALL R13 6 0 
     116 [-]: GETIMPORT R15 51 [nil]
     117 [-]: GETIMPORT R16 53 [nil]
     118 [-]: NAMECALL R13 R12 K49 [0x986D2AB8]
     119 [-]: CALL R13 3 0 
L11: 120 [-]: FORNLOOP R6 L9
     121 [-]: JUMP L19
    
L12: 122 [-]: GETIMPORT R6 18 [nil]
     123 [-]: GETIMPORT R8 32 [nil]
     124 [-]: NAMECALL R6 R6 K21 [0xFB669000]
     125 [-]: CALL R6 2 1  
     126 [-]: LOADN R7 0   
L13: 127 [-]: FASTCALL1 62 R6 L14
     128 [-]: MOVE R9 R6   
     129 [-]: GETIMPORT R8 23 [nil]
     130 [-]: CALL R8 1 1  
L14: 131 [-]: JUMPIF R8 L15
     132 [-]: LENGTH R8 R6 
     133 [-]: JUMPXEQKN R8 K54 L16 NOT [0]
L15: 134 [-]: LOADN R8 10  
     135 [-]: JUMPIFNOTLT R7 R8 L16
     136 [-]: GETIMPORT R8 18 [nil]
     137 [-]: GETIMPORT R10 32 [nil]
     138 [-]: NAMECALL R8 R8 K21 [0xFB669000]
     139 [-]: CALL R8 2 1  
     140 [-]: MOVE R6 R8   
     141 [-]: ADDK R7 R7 K55 [0.20000000000000001]
     142 [-]: GETIMPORT R8 57 [nil]
     143 [-]: LOADK R9 K55 [0.20000000000000001]
     144 [-]: CALL R8 1 0  
     145 [-]: JUMPBACK L13 
L16: 146 [-]: GETIMPORT R8 59 [nil]
     147 [-]: MOVE R9 R6   
     148 [-]: CALL R8 1 3  
     149 [-]: FORGPREP_INEXT R8 L18
L17: 150 [-]: GETIMPORT R15 43 [nil]
     151 [-]: GETTABLEKS R17 R5 K45 ["red"]
     152 [-]: DIVK R16 R17 K44 [255]
     153 [-]: GETTABLEKS R18 R5 K46 ["green"]
     154 [-]: DIVK R17 R18 K44 [255]
     155 [-]: GETTABLEKS R19 R5 K47 ["blue"]
     156 [-]: DIVK R18 R19 K44 [255]
     157 [-]: GETTABLEKS R20 R5 K48 ["alpha"]
     158 [-]: DIVK R19 R20 K44 [255]
     159 [-]: NAMECALL R13 R12 K49 [0x986D2AB8]
     160 [-]: CALL R13 6 0 
     161 [-]: GETIMPORT R15 51 [nil]
     162 [-]: GETIMPORT R16 53 [nil]
     163 [-]: NAMECALL R13 R12 K49 [0x986D2AB8]
     164 [-]: CALL R13 3 0 
L18: 165 [-]: FORGLOOP R8 L17 2 [inext]
L19: 166 [-]: LOADN R8 1   
     167 [-]: LENGTH R6 R3 
     168 [-]: LOADN R7 1   
     169 [-]: FORNPREP R6 L23
L20: 170 [-]: GETTABLE R10 R3 R8
     171 [-]: FASTCALL1 62 R10 L21
     172 [-]: GETIMPORT R9 23 [nil]
     173 [-]: CALL R9 1 1  
L21: 174 [-]: JUMPIF R9 L22
     175 [-]: GETTABLE R9 R3 R8
     176 [-]: MOVE R11 R5  
     177 [-]: NAMECALL R9 R9 K60 [0x16A61AD1]
     178 [-]: CALL R9 2 0  
     179 [-]: GETTABLE R9 R3 R8
     180 [-]: GETIMPORT R11 62 [nil]
     181 [-]: NAMECALL R9 R9 K63 [0x5E78B499]
     182 [-]: CALL R9 2 0  
L22: 183 [-]: FORNLOOP R6 L20
L23: 184 [-]: GETIMPORT R6 1 [nil]
L24: 185 [-]: FASTCALL1 62 R6 L25
     186 [-]: MOVE R8 R6   
     187 [-]: GETIMPORT R7 23 [nil]
     188 [-]: CALL R7 1 1  
L25: 189 [-]: JUMPIF R7 L26
     190 [-]: GETUPVAL R9 0
     191 [-]: NAMECALL R7 R6 K64 [0x0EB34C69]
     192 [-]: CALL R7 2 1  
     193 [-]: JUMPXEQKN R7 K54 L26 NOT [0]
     194 [-]: GETIMPORT R7 57 [nil]
     195 [-]: LOADN R8 0   
     196 [-]: CALL R7 1 0  
     197 [-]: JUMPBACK L24 
L26: 198 [-]: FASTCALL1 62 R6 L27
     199 [-]: MOVE R8 R6   
     200 [-]: GETIMPORT R7 23 [nil]
     201 [-]: CALL R7 1 1  
L27: 202 [-]: JUMPIF R7 L36
     203 [-]: GETUPVAL R9 0
     204 [-]: NAMECALL R7 R6 K64 [0x0EB34C69]
     205 [-]: CALL R7 2 1  
     206 [-]: JUMPXEQKN R7 K65 L36 [4]
     207 [-]: GETIMPORT R7 1 [nil]
     208 [-]: GETUPVAL R9 1
     209 [-]: NAMECALL R7 R7 K64 [0x0EB34C69]
     210 [-]: CALL R7 2 1  
     211 [-]: DIVK R8 R7 K66 [150]
     212 [-]: GETIMPORT R9 68 [nil]
     213 [-]: GETIMPORT R10 70 [nil]
     214 [-]: GETIMPORT R11 62 [nil]
     215 [-]: MOVE R12 R8  
     216 [-]: CALL R9 3 1  
     217 [-]: LOADNIL R10  
     218 [-]: GETIMPORT R11 15 [nil]
     219 [-]: GETIMPORT R12 5 [nil]
     220 [-]: LOADK R13 K16 ["Infestation"]
     221 [-]: CALL R12 1 1 
     222 [-]: JUMPIFNOTEQ R11 R12 L28
     223 [-]: GETIMPORT R11 12 [nil]
     224 [-]: JUMPIFNOT R11 L28
     225 [-]: GETIMPORT R11 72 [nil]
     226 [-]: GETIMPORT R13 34 [nil]
     227 [-]: MOVE R14 R8  
     228 [-]: NAMECALL R11 R11 K67 [0x9BAFFFE3]
     229 [-]: CALL R11 3 1 
     230 [-]: MOVE R10 R11 
     231 [-]: JUMP L29
    
L28: 232 [-]: GETIMPORT R11 74 [nil]
     233 [-]: GETIMPORT R13 36 [nil]
     234 [-]: MOVE R14 R8  
     235 [-]: NAMECALL R11 R11 K67 [0x9BAFFFE3]
     236 [-]: CALL R11 3 1 
     237 [-]: MOVE R10 R11 
L29: 238 [-]: GETIMPORT R11 68 [nil]
     239 [-]: GETIMPORT R12 76 [nil]
     240 [-]: GETIMPORT R13 53 [nil]
     241 [-]: MOVE R14 R8  
     242 [-]: CALL R11 3 1 
     243 [-]: GETIMPORT R12 59 [nil]
     244 [-]: MOVE R13 R4  
     245 [-]: CALL R12 1 3 
     246 [-]: FORGPREP_INEXT R12 L31
L30: 247 [-]: GETIMPORT R19 43 [nil]
     248 [-]: GETTABLEKS R21 R10 K45 ["red"]
     249 [-]: DIVK R20 R21 K44 [255]
     250 [-]: GETTABLEKS R22 R10 K46 ["green"]
     251 [-]: DIVK R21 R22 K44 [255]
     252 [-]: GETTABLEKS R23 R10 K47 ["blue"]
     253 [-]: DIVK R22 R23 K44 [255]
     254 [-]: GETTABLEKS R24 R10 K48 ["alpha"]
     255 [-]: DIVK R23 R24 K44 [255]
     256 [-]: NAMECALL R17 R16 K49 [0x986D2AB8]
     257 [-]: CALL R17 6 0 
     258 [-]: GETIMPORT R19 51 [nil]
     259 [-]: MOVE R20 R11 
     260 [-]: NAMECALL R17 R16 K49 [0x986D2AB8]
     261 [-]: CALL R17 3 0 
L31: 262 [-]: FORGLOOP R12 L30 2 [inext]
     263 [-]: LOADN R14 1  
     264 [-]: LENGTH R12 R3
     265 [-]: LOADN R13 1  
     266 [-]: FORNPREP R12 L35
L32: 267 [-]: GETTABLE R16 R3 R14
     268 [-]: FASTCALL1 62 R16 L33
     269 [-]: GETIMPORT R15 23 [nil]
     270 [-]: CALL R15 1 1 
L33: 271 [-]: JUMPIF R15 L34
     272 [-]: GETTABLE R15 R3 R14
     273 [-]: MOVE R17 R10 
     274 [-]: NAMECALL R15 R15 K60 [0x16A61AD1]
     275 [-]: CALL R15 2 0 
     276 [-]: GETTABLE R15 R3 R14
     277 [-]: MOVE R17 R9  
     278 [-]: NAMECALL R15 R15 K63 [0x5E78B499]
     279 [-]: CALL R15 2 0 
L34: 280 [-]: FORNLOOP R12 L32
L35: 281 [-]: GETIMPORT R12 57 [nil]
     282 [-]: LOADN R13 0  
     283 [-]: CALL R12 1 0 
     284 [-]: JUMPBACK L26 
L36: 285 [-]: RETURN R0 0  


; Name:            
; Defined at line: 471
; #Upvalues:       0
; #Parameters:     2
; Is_vararg:       0
; Max Stack Size:  14

       0 [-]: JUMPXEQKNIL R0 L1
       1 [-]: FASTCALL1 40 R0 L0
       2 [-]: MOVE R3 R0   
       3 [-]: GETIMPORT R2 1 [nil]
       4 [-]: CALL R2 1 1  
L 0:   5 [-]: JUMPXEQKS R2 K2 L13 NOT ["table"]
L 1:   6 [-]: FASTCALL1 40 R1 L2
       7 [-]: MOVE R3 R1   
       8 [-]: GETIMPORT R2 1 [nil]
       9 [-]: CALL R2 1 1  
L 2:  10 [-]: JUMPXEQKS R2 K2 L13 NOT ["table"]
      11 [-]: GETIMPORT R3 5 [nil]
      12 [-]: FASTCALL1 62 R3 L3
      13 [-]: GETIMPORT R2 7 [nil]
      14 [-]: CALL R2 1 1  
L 3:  15 [-]: JUMPIF R2 L4 
      16 [-]: GETIMPORT R2 5 [nil]
      17 [-]: MOVE R3 R0   
      18 [-]: MOVE R4 R1   
      19 [-]: CALL R2 2 0  
L 4:  20 [-]: LOADN R4 1   
      21 [-]: LENGTH R2 R1 
      22 [-]: LOADN R3 1   
      23 [-]: FORNPREP R2 L13
L 5:  24 [-]: JUMPIFNOT R0 L6
      25 [-]: GETTABLE R6 R0 R4
      26 [-]: JUMPIFNOT R6 L6
      27 [-]: GETTABLE R6 R0 R4
      28 [-]: GETTABLEKS R5 R6 K8 ["s"]
      29 [-]: JUMPIF R5 L7 
L 6:  30 [-]: LOADN R5 0   
L 7:  31 [-]: GETTABLE R7 R1 R4
      32 [-]: JUMPIFNOT R7 L8
      33 [-]: GETTABLE R7 R1 R4
      34 [-]: GETTABLEKS R6 R7 K8 ["s"]
      35 [-]: JUMPIF R6 L9 
L 8:  36 [-]: LOADN R6 0   
L 9:  37 [-]: JUMPIFEQ R5 R6 L10
      38 [-]: JUMPXEQKN R6 K9 L10 NOT [1]
      39 [-]: GETIMPORT R7 10 [nil]
      40 [-]: GETIMPORT R9 12 [nil]
      41 [-]: ADDK R8 R9 K9 [1]
      42 [-]: SETTABLEKS R8 R7 K11 ["SquadLinkSurvivalGiveRewards"]
L10:  43 [-]: JUMPXEQKN R6 K13 L12 NOT [3]
      44 [-]: GETTABLE R7 R1 R4
      45 [-]: JUMPIFNOT R7 L11
      46 [-]: GETTABLE R8 R1 R4
      47 [-]: GETTABLEKS R7 R8 K14 ["t"]
L11:  48 [-]: JUMPIFNOT R7 L12
      49 [-]: GETIMPORT R8 16 [nil]
      50 [-]: LOADK R10 K17 ["SquadLink - Vault"]
      51 [-]: MOVE R11 R4  
      52 [-]: LOADK R12 K18 [" timer: "]
      53 [-]: MOVE R13 R7  
      54 [-]: CONCAT R9 R10 R13
      55 [-]: CALL R8 1 0  
L12:  56 [-]: FORNLOOP R2 L5
L13:  57 [-]: RETURN R0 0  


; Name:            
; Defined at line: 497
; #Upvalues:       1
; #Parameters:     0
; Is_vararg:       0
; Max Stack Size:  3

       0 [-]: GETUPVAL R1 0
       1 [-]: GETTABLEKS R0 R1 K0 [0xAD362F29]
       2 [-]: GETUPVAL R2 0
       3 [-]: GETTABLEKS R1 R2 K1 ["INITIATOR_SUCCESS"]
       4 [-]: CALL R0 1 0  
       5 [-]: RETURN R0 0  


; Name:            
; Defined at line: 501
; #Upvalues:       1
; #Parameters:     2
; Is_vararg:       0
; Max Stack Size:  5

       0 [-]: GETIMPORT R2 1 [nil]
       1 [-]: NAMECALL R2 R2 K2 [0x78298275]
       2 [-]: CALL R2 1 1  
       3 [-]: JUMPIFNOTEQ R1 R2 L0
       4 [-]: GETUPVAL R3 0
       5 [-]: GETTABLEKS R2 R3 K3 [0x087BDEAB]
       6 [-]: CALL R2 0 1  
       7 [-]: JUMPIFNOT R2 L0
       8 [-]: GETIMPORT R2 1 [nil]
       9 [-]: NAMECALL R2 R2 K4 [0xFB64E76C]
      10 [-]: CALL R2 1 1  
      11 [-]: NAMECALL R2 R2 K5 [0x0803EEE1]
      12 [-]: CALL R2 1 1  
      13 [-]: LOADK R4 K6 ["/Lotus/Language/SquadLink/ActionDisabledWhileMatchmaking"]
      14 [-]: NAMECALL R2 R2 K7 [0x89212ED6]
      15 [-]: CALL R2 2 0  
L 0:  16 [-]: RETURN R0 0  


; Name:            
; Defined at line: 507
; #Upvalues:       0
; #Parameters:     2
; Is_vararg:       0
; Max Stack Size:  5

       0 [-]: GETIMPORT R2 1 [nil]
       1 [-]: NAMECALL R2 R2 K2 [0x78298275]
       2 [-]: CALL R2 1 1  
       3 [-]: JUMPIFNOTEQ R1 R2 L0
       4 [-]: GETIMPORT R2 1 [nil]
       5 [-]: NAMECALL R2 R2 K3 [0xFB64E76C]
       6 [-]: CALL R2 1 1  
       7 [-]: NAMECALL R2 R2 K4 [0x0803EEE1]
       8 [-]: CALL R2 1 1  
       9 [-]: LOADK R4 K5 [""]
      10 [-]: NAMECALL R2 R2 K6 [0x89212ED6]
      11 [-]: CALL R2 2 0  
L 0:  12 [-]: RETURN R0 0  


; Name:            
; Defined at line: 515
; #Upvalues:       0
; #Parameters:     2
; Is_vararg:       0
; Max Stack Size:  12

       0 [-]: FASTCALL1 62 R0 L0
       1 [-]: MOVE R3 R0   
       2 [-]: GETIMPORT R2 1 [nil]
       3 [-]: CALL R2 1 1  
L 0:   4 [-]: JUMPIFNOT R2 L1
       5 [-]: RETURN R0 0  
L 1:   6 [-]: GETIMPORT R2 3 [nil]
       7 [-]: NAMECALL R2 R2 K4 [0x8B5B1F58]
       8 [-]: CALL R2 1 1  
       9 [-]: GETIMPORT R3 6 [nil]
      10 [-]: MOVE R4 R2   
      11 [-]: CALL R3 1 3  
      12 [-]: FORGPREP_INEXT R3 L4
L 2:  13 [-]: NAMECALL R9 R7 K7 [0x5E651723]
      14 [-]: CALL R9 1 1  
      15 [-]: FASTCALL1 62 R9 L3
      16 [-]: GETIMPORT R8 1 [nil]
      17 [-]: CALL R8 1 1  
L 3:  18 [-]: JUMPIF R8 L4 
      19 [-]: NAMECALL R8 R7 K7 [0x5E651723]
      20 [-]: CALL R8 1 1  
      21 [-]: NAMECALL R8 R8 K8 [0xD8140B94]
      22 [-]: CALL R8 1 1  
      23 [-]: JUMPIFNOT R8 L4
      24 [-]: NAMECALL R8 R7 K9 [0xDE321E6F]
      25 [-]: CALL R8 1 1  
      26 [-]: MOVE R10 R0  
      27 [-]: MOVE R11 R1  
      28 [-]: NAMECALL R8 R8 K10 [0xEC017EFA]
      29 [-]: CALL R8 3 0  
L 4:  30 [-]: FORGLOOP R3 L2 2 [inext]
      31 [-]: RETURN R0 0  


; Name:            
; Defined at line: 528
; #Upvalues:       0
; #Parameters:     1
; Is_vararg:       0
; Max Stack Size:  7

       0 [-]: GETIMPORT R1 1 [nil]
       1 [-]: GETIMPORT R3 3 [nil]
       2 [-]: NAMECALL R1 R1 K4 [0x6DD7AA66]
       3 [-]: CALL R1 2 1  
       4 [-]: FASTCALL1 62 R1 L0
       5 [-]: MOVE R3 R1   
       6 [-]: GETIMPORT R2 6 [nil]
       7 [-]: CALL R2 1 1  
L 0:   8 [-]: JUMPIF R2 L1 
       9 [-]: LOADK R4 K7 ["ShowReward"]
      10 [-]: GETIMPORT R5 9 [nil]
      11 [-]: MOVE R6 R0   
      12 [-]: CALL R5 1 -1 
      13 [-]: NAMECALL R2 R1 K10 [0xE4162EED]
      14 [-]: CALL R2 -1 0 
L 1:  15 [-]: RETURN R0 0  


; Name:            
; Defined at line: 535
; #Upvalues:       0
; #Parameters:     1
; Is_vararg:       0
; Max Stack Size:  16

       0 [-]: GETIMPORT R1 1 [nil]
       1 [-]: NAMECALL R1 R1 K2 [0x8B5B1F58]
       2 [-]: CALL R1 1 1  
       3 [-]: GETIMPORT R2 4 [nil]
       4 [-]: GETIMPORT R3 6 [nil]
       5 [-]: MOVE R4 R1   
       6 [-]: CALL R3 1 3  
       7 [-]: FORGPREP_INEXT R3 L1
L 0:   8 [-]: NAMECALL R10 R7 K7 [0x5E651723]
       9 [-]: CALL R10 1 1 
      10 [-]: MOVE R11 R0  
      11 [-]: LOADK R12 K8 [""]
      12 [-]: LOADN R13 0  
      13 [-]: LOADN R14 2  
      14 [-]: LOADB R15 1  
      15 [-]: NAMECALL R8 R2 K9 [0x06D4C9EB]
      16 [-]: CALL R8 7 0  
L 1:  17 [-]: FORGLOOP R3 L0 2 [inext]
      18 [-]: RETURN R0 0  


; Name:            
; Defined at line: 544
; #Upvalues:       2
; #Parameters:     1
; Is_vararg:       0
; Max Stack Size:  15

       0 [-]: GETUPVAL R2 0
       1 [-]: GETTABLEKS R1 R2 K0 [0xBD51F1E9]
       2 [-]: CALL R1 0 1  
       3 [-]: NEWTABLE R2 0 0
       4 [-]: LOADK R3 K1 [3.4028234663852886e+38]
       5 [-]: LOADN R6 1   
       6 [-]: LENGTH R4 R0 
       7 [-]: LOADN R5 1   
       8 [-]: FORNPREP R4 L9
L 0:   9 [-]: LOADNIL R7   
      10 [-]: LENGTH R10 R0
      11 [-]: LOADN R8 1   
      12 [-]: LOADN R9 -1  
      13 [-]: FORNPREP R8 L5
L 1:  14 [-]: GETTABLE R13 R0 R10
      15 [-]: GETTABLEKS R12 R13 K2 ["extractState"]
      16 [-]: FASTCALL1 62 R12 L2
      17 [-]: GETIMPORT R11 4 [nil]
      18 [-]: CALL R11 1 1 
L 2:  19 [-]: JUMPIF R11 L3
      20 [-]: GETUPVAL R12 1
      21 [-]: GETTABLE R14 R0 R10
      22 [-]: GETTABLEKS R13 R14 K2 ["extractState"]
      23 [-]: NAMECALL R13 R13 K5 [0x17DD42BB]
      24 [-]: CALL R13 1 1 
      25 [-]: SUB R11 R12 R13
      26 [-]: JUMPIFNOTLT R11 R3 L4
      27 [-]: MOVE R3 R11  
      28 [-]: MOVE R7 R10  
      29 [-]: JUMP L4
     
L 3:  30 [-]: GETIMPORT R11 8 [nil]
      31 [-]: MOVE R12 R0  
      32 [-]: MOVE R13 R10 
      33 [-]: CALL R11 2 0 
L 4:  34 [-]: FORNLOOP R8 L1
L 5:  35 [-]: FASTCALL1 62 R7 L6
      36 [-]: MOVE R9 R7   
      37 [-]: GETIMPORT R8 4 [nil]
      38 [-]: CALL R8 1 1  
L 6:  39 [-]: JUMPIF R8 L8 
      40 [-]: GETTABLE R10 R0 R7
      41 [-]: FASTCALL2 52 R2 R10 L7
      42 [-]: MOVE R9 R2   
      43 [-]: GETIMPORT R8 10 [nil]
      44 [-]: CALL R8 2 0  
L 7:  45 [-]: GETIMPORT R8 8 [nil]
      46 [-]: MOVE R9 R0   
      47 [-]: MOVE R10 R7  
      48 [-]: CALL R8 2 0  
L 8:  49 [-]: FORNLOOP R4 L0
L 9:  50 [-]: GETIMPORT R4 12 [nil]
      51 [-]: MOVE R5 R2   
      52 [-]: CALL R4 1 3  
      53 [-]: FORGPREP_INEXT R4 L11
L10:  54 [-]: ADDK R11 R7 K14 [1]
      55 [-]: MUL R10 R7 R11
      56 [-]: DIVK R9 R10 K13 [2]
      57 [-]: ADDK R11 R1 K15 [10]
      58 [-]: ADD R10 R11 R9
      59 [-]: ADDK R12 R1 K16 [11]
      60 [-]: ADD R11 R12 R9
      61 [-]: GETTABLEKS R13 R8 K17 ["healthTracker"]
      62 [-]: GETTABLEKS R12 R13 K18 ["SetSortPriority"]
      63 [-]: MOVE R13 R10 
      64 [-]: LOADB R14 0  
      65 [-]: CALL R12 2 0 
      66 [-]: GETTABLEKS R13 R8 K19 ["statusTracker"]
      67 [-]: GETTABLEKS R12 R13 K18 ["SetSortPriority"]
      68 [-]: MOVE R13 R11 
      69 [-]: LOADB R14 0  
      70 [-]: CALL R12 2 0 
L11:  71 [-]: FORGLOOP R4 L10 2 [inext]
      72 [-]: RETURN R0 0  


; Name:            
; Defined at line: 576
; #Upvalues:       13
; #Parameters:     0
; Is_vararg:       0
; Max Stack Size:  47

       0 [-]: GETIMPORT R0 1 [nil]
L 0:   1 [-]: FASTCALL1 62 R0 L1
       2 [-]: MOVE R2 R0   
       3 [-]: GETIMPORT R1 3 [nil]
       4 [-]: CALL R1 1 1  
L 1:   5 [-]: JUMPIFNOT R1 L2
       6 [-]: GETIMPORT R0 1 [nil]
       7 [-]: GETIMPORT R1 5 [nil]
       8 [-]: LOADK R2 K6 [0.10000000000000001]
       9 [-]: CALL R1 1 0  
      10 [-]: JUMPBACK L0  
L 2:  11 [-]: NAMECALL R1 R0 K7 [0x33307F92]
      12 [-]: CALL R1 1 1  
L 3:  13 [-]: FASTCALL1 62 R1 L4
      14 [-]: MOVE R3 R1   
      15 [-]: GETIMPORT R2 3 [nil]
      16 [-]: CALL R2 1 1  
L 4:  17 [-]: JUMPIFNOT R2 L5
      18 [-]: NAMECALL R2 R0 K7 [0x33307F92]
      19 [-]: CALL R2 1 1  
      20 [-]: MOVE R1 R2   
      21 [-]: GETIMPORT R2 5 [nil]
      22 [-]: LOADK R3 K6 [0.10000000000000001]
      23 [-]: CALL R2 1 0  
      24 [-]: JUMPBACK L3  
L 5:  25 [-]: GETUPVAL R4 0
      26 [-]: GETTABLEKS R3 R4 K9 [0xBD51F1E9]
      27 [-]: CALL R3 0 1  
      28 [-]: ADDK R2 R3 K8 [5]
      29 [-]: GETIMPORT R3 12 [nil]
      30 [-]: LOADK R4 K13 ["SurvivalLSLabel"]
      31 [-]: GETUPVAL R6 1
      32 [-]: GETTABLEKS R5 R6 K14 ["HT_LABEL"]
      33 [-]: LOADK R6 K15 [0.14999999999999999]
      34 [-]: MOVE R7 R2   
      35 [-]: LOADB R8 0   
      36 [-]: CALL R3 5 1  
      37 [-]: GETUPVAL R5 0
      38 [-]: GETTABLEKS R4 R5 K16 [0x1645F3C0]
      39 [-]: CALL R4 0 2  
      40 [-]: GETTABLEKS R6 R3 K17 ["SetOffset"]
      41 [-]: ADDK R7 R4 K18 [60]
      42 [-]: LOADN R8 -15 
      43 [-]: CALL R6 2 0  
      44 [-]: LOADK R7 K19 ["</font><font color=\""]
      45 [-]: GETTABLEKS R10 R3 K20 ["Colorize"]
      46 [-]: LOADN R11 24 
      47 [-]: CALL R10 1 1 
      48 [-]: MOVE R8 R10  
      49 [-]: LOADK R9 K21 ["\"><b>"]
      50 [-]: CONCAT R6 R7 R9
      51 [-]: LOADK R8 K22 ["</b></font><font color=\""]
      52 [-]: GETTABLEKS R11 R3 K20 ["Colorize"]
      53 [-]: LOADN R12 38 
      54 [-]: CALL R11 1 1 
      55 [-]: MOVE R9 R11  
      56 [-]: LOADK R10 K21 ["\"><b>"]
      57 [-]: CONCAT R7 R8 R10
      58 [-]: LOADK R9 K19 ["</font><font color=\""]
      59 [-]: GETTABLEKS R12 R3 K20 ["Colorize"]
      60 [-]: LOADN R13 27 
      61 [-]: CALL R12 1 1 
      62 [-]: MOVE R10 R12 
      63 [-]: LOADK R11 K21 ["\"><b>"]
      64 [-]: CONCAT R8 R9 R11
      65 [-]: LOADK R11 K23 ["<SURVIVAL_PILLAR_MARKER>"]
      66 [-]: LOADB R12 1  
      67 [-]: NAMECALL R9 R1 K24 [0x42B04007]
      68 [-]: CALL R9 3 1  
      69 [-]: LOADK R12 K25 ["<SURVIVAL_PILLAR_OUTLINE_MARKER>"]
      70 [-]: LOADB R13 1  
      71 [-]: NAMECALL R10 R1 K24 [0x42B04007]
      72 [-]: CALL R10 3 1 
      73 [-]: GETIMPORT R12 1 [nil]
      74 [-]: NAMECALL R12 R12 K26 [0xEF893AEC]
      75 [-]: CALL R12 1 1 
      76 [-]: GETTABLEKS R13 R12 K27 ["goalTag"]
      77 [-]: GETIMPORT R14 29 [nil]
      78 [-]: LOADK R15 K30 ["KuvaSurvival"]
      79 [-]: CALL R14 1 1 
      80 [-]: JUMPIFNOTEQ R13 R14 L6
      81 [-]: LOADB R11 1  
      82 [-]: JUMP L7
     
L 6:  83 [-]: LOADB R11 0  
L 7:  84 [-]: LOADK R12 K31 [""]
      85 [-]: GETUPVAL R14 2
      86 [-]: GETTABLEKS R13 R14 K32 [0x7E1C98B2]
      87 [-]: CALL R13 0 1 
      88 [-]: LOADB R14 0  
      89 [-]: DUPCLOSURE R15 K33 []
      90 [-]: MOVE R2 R3   
      91 [-]: NEWTABLE R16 0 3
      92 [-]: LOADNIL R17  
      93 [-]: LOADNIL R18  
      94 [-]: LOADNIL R19  
      95 [-]: SETLIST R16 R17 3 [1]
      96 [-]: NEWTABLE R17 0 3
      97 [-]: LOADNIL R18  
      98 [-]: LOADNIL R19  
      99 [-]: LOADNIL R20  
     100 [-]: SETLIST R17 R18 3 [1]
     101 [-]: LOADB R18 0  
     102 [-]: LOADN R19 -1 
     103 [-]: GETUPVAL R22 4
     104 [-]: NAMECALL R20 R0 K34 [0x0EB34C69]
     105 [-]: CALL R20 2 1 
L 8: 106 [-]: FASTCALL1 62 R1 L9
     107 [-]: MOVE R22 R1  
     108 [-]: GETIMPORT R21 3 [nil]
     109 [-]: CALL R21 1 1 
L 9: 110 [-]: JUMPIF R21 L50
     111 [-]: FASTCALL1 62 R0 L10
     112 [-]: MOVE R22 R0  
     113 [-]: GETIMPORT R21 3 [nil]
     114 [-]: CALL R21 1 1 
L10: 115 [-]: JUMPIF R21 L50
     116 [-]: GETUPVAL R23 5
     117 [-]: NAMECALL R21 R0 K34 [0x0EB34C69]
     118 [-]: CALL R21 2 1 
     119 [-]: JUMPXEQKN R21 K35 L50 [4]
     120 [-]: LOADK R22 K36 ["<p><font color=\""]
     121 [-]: GETTABLEKS R25 R3 K20 ["Colorize"]
     122 [-]: LOADN R26 38 
     123 [-]: CALL R25 1 1 
     124 [-]: MOVE R23 R25 
     125 [-]: LOADK R24 K37 ["\">"]
     126 [-]: CONCAT R21 R22 R24
     127 [-]: GETUPVAL R24 6
     128 [-]: NAMECALL R22 R0 K34 [0x0EB34C69]
     129 [-]: CALL R22 2 1 
     130 [-]: GETUPVAL R25 7
     131 [-]: NAMECALL R23 R0 K34 [0x0EB34C69]
     132 [-]: CALL R23 2 1 
     133 [-]: GETUPVAL R26 8
     134 [-]: NAMECALL R24 R0 K34 [0x0EB34C69]
     135 [-]: CALL R24 2 1 
     136 [-]: GETUPVAL R27 9
     137 [-]: NAMECALL R25 R0 K34 [0x0EB34C69]
     138 [-]: CALL R25 2 1 
     139 [-]: SUB R24 R24 R23
     140 [-]: JUMPXEQKN R22 K38 L11 NOT [1]
     141 [-]: MOVE R26 R21 
     142 [-]: MOVE R27 R6  
     143 [-]: MOVE R28 R10 
     144 [-]: MOVE R29 R7  
     145 [-]: CONCAT R21 R26 R29
L11: 146 [-]: LOADN R28 1  
     147 [-]: MOVE R26 R24 
     148 [-]: LOADN R27 1  
     149 [-]: FORNPREP R26 L13
L12: 150 [-]: MOVE R29 R21 
     151 [-]: MOVE R30 R9  
     152 [-]: CONCAT R21 R29 R30
     153 [-]: FORNLOOP R26 L12
L13: 154 [-]: LOADN R28 1  
     155 [-]: MOVE R26 R25 
     156 [-]: LOADN R27 1  
     157 [-]: FORNPREP R26 L15
L14: 158 [-]: MOVE R29 R21 
     159 [-]: MOVE R30 R8  
     160 [-]: MOVE R31 R9  
     161 [-]: MOVE R32 R7  
     162 [-]: CONCAT R21 R29 R32
     163 [-]: FORNLOOP R26 L14
L15: 164 [-]: LOADN R28 1  
     165 [-]: MOVE R26 R23 
     166 [-]: LOADN R27 1  
     167 [-]: FORNPREP R26 L17
L16: 168 [-]: MOVE R29 R21 
     169 [-]: MOVE R30 R15 
     170 [-]: MOVE R31 R10 
     171 [-]: CALL R30 1 1 
     172 [-]: CONCAT R21 R29 R30
     173 [-]: FORNLOOP R26 L16
L17: 174 [-]: MOVE R26 R21 
     175 [-]: LOADK R27 K39 ["</b></font></p>"]
     176 [-]: CONCAT R21 R26 R27
     177 [-]: GETTABLEKS R26 R3 K40 ["SetLabel"]
     178 [-]: MOVE R27 R21 
     179 [-]: CALL R26 1 0 
     180 [-]: GETUPVAL R28 4
     181 [-]: NAMECALL R26 R0 K34 [0x0EB34C69]
     182 [-]: CALL R26 2 1 
     183 [-]: JUMPIFNOTLT R20 R26 L18
     184 [-]: JUMPXEQKN R19 K41 L18 NOT [-1]
     185 [-]: LOADK R19 K42 [0.5]
L18: 186 [-]: MOVE R20 R26 
     187 [-]: GETIMPORT R27 44 [nil]
     188 [-]: NAMECALL R27 R27 K45 [0x18D05D30]
     189 [-]: CALL R27 1 1 
     190 [-]: JUMPIFNOT R27 L23
     191 [-]: GETUPVAL R29 4
     192 [-]: NAMECALL R27 R0 K34 [0x0EB34C69]
     193 [-]: CALL R27 2 1 
     194 [-]: DIVK R28 R27 K46 [150]
     195 [-]: LOADK R29 K47 [0.20000000000000001]
     196 [-]: JUMPIFNOTLE R28 R29 L19
     197 [-]: GETUPVAL R29 0
     198 [-]: GETTABLEKS R28 R29 K48 [0x8D698BFC]
     199 [-]: LOADN R29 38 
     200 [-]: LOADN R30 34 
     201 [-]: CALL R28 2 0 
     202 [-]: LOADB R18 1  
     203 [-]: JUMP L23
    
L19: 204 [-]: LOADN R28 0  
     205 [-]: JUMPIFNOTLT R28 R19 L21
     206 [-]: GETUPVAL R29 0
     207 [-]: GETTABLEKS R28 R29 K48 [0x8D698BFC]
     208 [-]: LOADN R29 38 
     209 [-]: LOADN R30 34 
     210 [-]: LOADK R31 K42 [0.5]
     211 [-]: CALL R28 3 0 
     212 [-]: GETIMPORT R30 50 [nil]
     213 [-]: CALL R30 0 1 
     214 [-]: SUB R29 R19 R30
     215 [-]: FASTCALL2K 18 R29 K51 L20 [0]
     216 [-]: LOADK R30 K51 [0]
     217 [-]: GETIMPORT R28 54 [nil]
     218 [-]: CALL R28 2 1 
L20: 219 [-]: MOVE R19 R28 
     220 [-]: JUMP L23
    
L21: 221 [-]: JUMPIF R18 L22
     222 [-]: JUMPXEQKN R19 K51 L23 NOT [0]
L22: 223 [-]: GETUPVAL R29 0
     224 [-]: GETTABLEKS R28 R29 K48 [0x8D698BFC]
     225 [-]: LOADN R29 38 
     226 [-]: CALL R28 1 0 
     227 [-]: LOADN R19 -1 
L23: 228 [-]: JUMPIFNOT R11 L45
     229 [-]: GETIMPORT R27 44 [nil]
     230 [-]: NAMECALL R27 R27 K45 [0x18D05D30]
     231 [-]: CALL R27 1 1 
     232 [-]: JUMPIFNOT R27 L45
     233 [-]: GETIMPORT R28 56 [nil]
     234 [-]: FASTCALL1 62 R28 L24
     235 [-]: GETIMPORT R27 3 [nil]
     236 [-]: CALL R27 1 1 
L24: 237 [-]: JUMPIF R27 L45
     238 [-]: LOADB R27 0  
     239 [-]: NEWTABLE R28 0 0
     240 [-]: LOADN R31 1  
     241 [-]: LOADN R29 3  
     242 [-]: LOADN R30 1  
     243 [-]: FORNPREP R29 L44
L25: 244 [-]: LOADK R33 K57 ["KuvaHealthTracker"]
     245 [-]: MOVE R34 R31 
     246 [-]: CONCAT R32 R33 R34
     247 [-]: LOADK R34 K58 ["SurvivalKuvaStatus"]
     248 [-]: MOVE R35 R31 
     249 [-]: CONCAT R33 R34 R35
     250 [-]: GETIMPORT R35 56 [nil]
     251 [-]: GETTABLE R34 R35 R31
     252 [-]: LOADNIL R35  
     253 [-]: JUMPXEQKN R34 K51 L26 [0]
     254 [-]: NAMECALL R36 R34 K59 [0xBB610E5B]
     255 [-]: CALL R36 1 1 
     256 [-]: MOVE R35 R36 
L26: 257 [-]: FASTCALL1 62 R35 L27
     258 [-]: MOVE R37 R35 
     259 [-]: GETIMPORT R36 3 [nil]
     260 [-]: CALL R36 1 1 
L27: 261 [-]: JUMPIF R36 L38
     262 [-]: GETIMPORT R37 61 [nil]
     263 [-]: MOVE R38 R32 
     264 [-]: CALL R37 1 1 
     265 [-]: FASTCALL1 62 R37 L28
     266 [-]: GETIMPORT R36 3 [nil]
     267 [-]: CALL R36 1 1 
L28: 268 [-]: JUMPIFNOT R36 L31
     269 [-]: GETUPVAL R37 0
     270 [-]: GETTABLEKS R36 R37 K16 [0x1645F3C0]
     271 [-]: CALL R36 0 2 
     272 [-]: GETUPVAL R39 3
     273 [-]: GETTABLEKS R38 R39 K62 [0x06D055F9]
     274 [-]: JUMPXEQKN R31 K38 L29 [1]
     275 [-]: LOADB R39 0 +1
L29: 276 [-]: LOADB R39 1  
L30: 277 [-]: ADDK R40 R37 K63 [10]
     278 [-]: ADDK R41 R37 K8 [5]
     279 [-]: CALL R38 3 1 
     280 [-]: MOVE R37 R38 
     281 [-]: GETIMPORT R38 12 [nil]
     282 [-]: MOVE R39 R32 
     283 [-]: GETUPVAL R41 1
     284 [-]: GETTABLEKS R40 R41 K64 ["HT_HEALTH_TRACKER"]
     285 [-]: LOADK R41 K15 [0.14999999999999999]
     286 [-]: LOADN R42 10 
     287 [-]: LOADB R43 1  
     288 [-]: CALL R38 5 1 
     289 [-]: SETTABLE R38 R17 R31
     290 [-]: GETTABLE R39 R17 R31
     291 [-]: GETTABLEKS R38 R39 K17 ["SetOffset"]
     292 [-]: LOADN R39 3  
     293 [-]: MOVE R40 R37 
     294 [-]: CALL R38 2 0 
     295 [-]: GETTABLE R39 R17 R31
     296 [-]: GETTABLEKS R38 R39 K65 ["SetTarget"]
     297 [-]: MOVE R39 R35 
     298 [-]: CALL R38 1 0 
     299 [-]: GETTABLE R39 R17 R31
     300 [-]: GETTABLEKS R38 R39 K66 ["SetHealthWarningThreshold"]
     301 [-]: LOADN R39 20 
     302 [-]: CALL R38 1 0 
     303 [-]: GETTABLE R39 R17 R31
     304 [-]: GETTABLEKS R38 R39 K67 ["SetRemoveOnNullTarget"]
     305 [-]: LOADB R39 1  
     306 [-]: CALL R38 1 0 
     307 [-]: LOADB R27 1  
L31: 308 [-]: GETIMPORT R37 61 [nil]
     309 [-]: MOVE R38 R33 
     310 [-]: CALL R37 1 1 
     311 [-]: FASTCALL1 62 R37 L32
     312 [-]: GETIMPORT R36 3 [nil]
     313 [-]: CALL R36 1 1 
L32: 314 [-]: JUMPIFNOT R36 L35
     315 [-]: GETIMPORT R36 12 [nil]
     316 [-]: MOVE R37 R33 
     317 [-]: GETUPVAL R39 1
     318 [-]: GETTABLEKS R38 R39 K14 ["HT_LABEL"]
     319 [-]: LOADK R39 K15 [0.14999999999999999]
     320 [-]: LOADN R40 10 
     321 [-]: LOADB R41 1  
     322 [-]: CALL R36 5 1 
     323 [-]: SETTABLE R36 R16 R31
     324 [-]: GETTABLE R37 R16 R31
     325 [-]: GETTABLEKS R36 R37 K17 ["SetOffset"]
     326 [-]: LOADN R37 0  
     327 [-]: LOADN R38 -15
     328 [-]: CALL R36 2 0 
     329 [-]: JUMPXEQKS R12 K31 L33 [""]
     330 [-]: JUMPXEQKS R12 K68 L34 NOT ["/Lotus/Language/Game/ExcavationTime"]
L33: 331 [-]: GETTABLE R37 R16 R31
     332 [-]: GETTABLEKS R36 R37 K69 ["Localize"]
     333 [-]: LOADK R37 K68 ["/Lotus/Language/Game/ExcavationTime"]
     334 [-]: LOADNIL R38  
     335 [-]: LOADB R39 0  
     336 [-]: CALL R36 3 1 
     337 [-]: MOVE R12 R36 
L34: 338 [-]: LOADB R27 1  
L35: 339 [-]: GETTABLE R37 R16 R31
     340 [-]: FASTCALL1 62 R37 L36
     341 [-]: GETIMPORT R36 3 [nil]
     342 [-]: CALL R36 1 1 
L36: 343 [-]: JUMPIF R36 L42
     344 [-]: GETTABLE R37 R16 R31
     345 [-]: GETTABLEKS R36 R37 K70 ["Removing"]
     346 [-]: JUMPIF R36 L42
     347 [-]: GETUPVAL R37 10
     348 [-]: NAMECALL R39 R34 K71 [0x17DD42BB]
     349 [-]: CALL R39 1 1 
     350 [-]: FASTCALL1 12 R39 L37
     351 [-]: GETIMPORT R38 73 [nil]
     352 [-]: CALL R38 1 1 
L37: 353 [-]: SUB R36 R37 R38
     354 [-]: LOADK R38 K36 ["<p><font color=\""]
     355 [-]: GETTABLE R46 R16 R31
     356 [-]: GETTABLEKS R45 R46 K20 ["Colorize"]
     357 [-]: LOADN R46 38 
     358 [-]: CALL R45 1 1 
     359 [-]: MOVE R39 R45 
     360 [-]: LOADK R40 K21 ["\"><b>"]
     361 [-]: MOVE R41 R12 
     362 [-]: LOADK R42 K74 ["</b> "]
     363 [-]: GETUPVAL R46 2
     364 [-]: GETTABLEKS R45 R46 K75 [0xC70DAAAC]
     365 [-]: MOVE R46 R36 
     366 [-]: CALL R45 1 1 
     367 [-]: MOVE R43 R45 
     368 [-]: LOADK R44 K39 ["</b></font></p>"]
     369 [-]: CONCAT R37 R38 R44
     370 [-]: GETTABLE R39 R16 R31
     371 [-]: GETTABLEKS R38 R39 K40 ["SetLabel"]
     372 [-]: MOVE R39 R37 
     373 [-]: CALL R38 1 0 
     374 [-]: JUMP L42
    
L38: 375 [-]: GETTABLE R37 R17 R31
     376 [-]: FASTCALL1 62 R37 L39
     377 [-]: GETIMPORT R36 3 [nil]
     378 [-]: CALL R36 1 1 
L39: 379 [-]: JUMPIFNOT R36 L41
     380 [-]: GETTABLE R37 R16 R31
     381 [-]: FASTCALL1 62 R37 L40
     382 [-]: GETIMPORT R36 3 [nil]
     383 [-]: CALL R36 1 1 
L40: 384 [-]: JUMPIF R36 L42
L41: 385 [-]: LOADNIL R36  
     386 [-]: SETTABLE R36 R17 R31
     387 [-]: LOADNIL R36  
     388 [-]: SETTABLE R36 R16 R31
     389 [-]: LOADB R27 1  
L42: 390 [-]: NEWTABLE R36 2 1
     391 [-]: GETTABLE R38 R17 R31
     392 [-]: SETTABLEKS R38 R36 K76 ["healthTracker"]
     393 [-]: GETTABLE R38 R16 R31
     394 [-]: SETTABLEKS R38 R36 K77 ["statusTracker"]
     395 [-]: MOVE R37 R34 
     396 [-]: SETLIST R36 R37 1 [1]
     397 [-]: FASTCALL2 52 R28 R36 L43
     398 [-]: MOVE R38 R28 
     399 [-]: MOVE R39 R36 
     400 [-]: GETIMPORT R37 80 [nil]
     401 [-]: CALL R37 2 0 
L43: 402 [-]: FORNLOOP R29 L25
L44: 403 [-]: JUMPIFNOT R27 L45
     404 [-]: GETUPVAL R29 11
     405 [-]: MOVE R30 R28 
     406 [-]: CALL R29 1 0 
L45: 407 [-]: GETUPVAL R27 12
     408 [-]: JUMPXEQKNIL R27 L49 NOT
     409 [-]: FASTCALL1 62 R13 L46
     410 [-]: MOVE R28 R13 
     411 [-]: GETIMPORT R27 3 [nil]
     412 [-]: CALL R27 1 1 
L46: 413 [-]: JUMPIFNOT R27 L47
     414 [-]: GETUPVAL R28 2
     415 [-]: GETTABLEKS R27 R28 K32 [0x7E1C98B2]
     416 [-]: CALL R27 0 1 
     417 [-]: MOVE R13 R27 
     418 [-]: JUMP L49
    
L47: 419 [-]: GETUPVAL R28 0
     420 [-]: GETTABLEKS R27 R28 K81 [0x37B5A5F2]
     421 [-]: CALL R27 0 1 
     422 [-]: LOADN R28 0  
     423 [-]: JUMPIFNOTLT R28 R27 L48
     424 [-]: JUMPIF R14 L48
     425 [-]: LOADN R30 0  
     426 [-]: NAMECALL R28 R13 K82 [0xBF4030D2]
     427 [-]: CALL R28 2 0 
     428 [-]: LOADB R14 1  
     429 [-]: JUMP L49
    
L48: 430 [-]: JUMPXEQKN R27 K51 L49 NOT [0]
     431 [-]: JUMPIFNOT R14 L49
     432 [-]: LOADN R30 1  
     433 [-]: NAMECALL R28 R13 K82 [0xBF4030D2]
     434 [-]: CALL R28 2 0 
     435 [-]: LOADB R14 0  
L49: 436 [-]: GETIMPORT R27 5 [nil]
     437 [-]: LOADN R28 0  
     438 [-]: CALL R27 1 0 
     439 [-]: JUMPBACK L8  
L50: 440 [-]: GETIMPORT R21 84 [nil]
     441 [-]: JUMPIFNOT R21 L51
     442 [-]: JUMPIFNOT R3 L51
     443 [-]: GETIMPORT R21 84 [nil]
     444 [-]: MOVE R22 R3  
     445 [-]: CALL R21 1 0 
     446 [-]: LOADNIL R3   
     447 [-]: GETUPVAL R22 0
     448 [-]: GETTABLEKS R21 R22 K48 [0x8D698BFC]
     449 [-]: LOADN R22 10 
     450 [-]: CALL R21 1 0 
     451 [-]: GETIMPORT R21 84 [nil]
     452 [-]: LOADK R23 K58 ["SurvivalKuvaStatus"]
     453 [-]: LOADN R24 1  
     454 [-]: CONCAT R22 R23 R24
     455 [-]: CALL R21 1 0 
     456 [-]: GETIMPORT R21 84 [nil]
     457 [-]: LOADK R23 K57 ["KuvaHealthTracker"]
     458 [-]: LOADN R24 1  
     459 [-]: CONCAT R22 R23 R24
     460 [-]: CALL R21 1 0 
     461 [-]: GETIMPORT R21 84 [nil]
     462 [-]: LOADK R23 K58 ["SurvivalKuvaStatus"]
     463 [-]: LOADN R24 2  
     464 [-]: CONCAT R22 R23 R24
     465 [-]: CALL R21 1 0 
     466 [-]: GETIMPORT R21 84 [nil]
     467 [-]: LOADK R23 K57 ["KuvaHealthTracker"]
     468 [-]: LOADN R24 2  
     469 [-]: CONCAT R22 R23 R24
     470 [-]: CALL R21 1 0 
     471 [-]: GETIMPORT R21 84 [nil]
     472 [-]: LOADK R23 K58 ["SurvivalKuvaStatus"]
     473 [-]: LOADN R24 3  
     474 [-]: CONCAT R22 R23 R24
     475 [-]: CALL R21 1 0 
     476 [-]: GETIMPORT R21 84 [nil]
     477 [-]: LOADK R23 K57 ["KuvaHealthTracker"]
     478 [-]: LOADN R24 3  
     479 [-]: CONCAT R22 R23 R24
     480 [-]: CALL R21 1 0 
L51: 481 [-]: RETURN R0 0  


; Name:            
; Defined at line: 761
; #Upvalues:       4
; #Parameters:     0
; Is_vararg:       0
; Max Stack Size:  12

       0 [-]: GETIMPORT R0 1 [nil]
       1 [-]: JUMPXEQKNIL R0 L0 NOT
       2 [-]: RETURN R0 0  
L 0:   3 [-]: NAMECALL R1 R0 K2 [0x33307F92]
       4 [-]: CALL R1 1 1  
       5 [-]: JUMPXEQKNIL R1 L1 NOT
       6 [-]: RETURN R0 0  
L 1:   7 [-]: GETUPVAL R4 0
       8 [-]: NAMECALL R2 R0 K3 [0x0EB34C69]
       9 [-]: CALL R2 2 1  
      10 [-]: DIVK R3 R2 K4 [150]
      11 [-]: GETIMPORT R5 7 [nil]
      12 [-]: FASTCALL1 62 R5 L2
      13 [-]: GETIMPORT R4 9 [nil]
      14 [-]: CALL R4 1 1  
L 2:  15 [-]: JUMPIFNOT R4 L4
      16 [-]: GETUPVAL R5 1
      17 [-]: GETTABLEKS R4 R5 K10 [0xEA753E99]
      18 [-]: LOADK R5 K11 ["/Lotus/Language/Game/SurvivalProgressBar"]
      19 [-]: MULK R7 R3 K12 [100]
      20 [-]: FASTCALL1 12 R7 L3
      21 [-]: GETIMPORT R6 15 [nil]
      22 [-]: CALL R6 1 1  
L 3:  23 [-]: LOADN R7 100 
      24 [-]: GETIMPORT R8 17 [nil]
      25 [-]: LOADB R9 1   
      26 [-]: CALL R4 5 0  
L 4:  27 [-]: GETUPVAL R5 1
      28 [-]: GETTABLEKS R4 R5 K18 [0x03FC64EF]
      29 [-]: MULK R6 R3 K12 [100]
      30 [-]: FASTCALL1 12 R6 L5
      31 [-]: GETIMPORT R5 15 [nil]
      32 [-]: CALL R5 1 1  
L 5:  33 [-]: LOADN R6 100 
      34 [-]: CALL R4 2 0  
      35 [-]: GETIMPORT R5 20 [nil]
      36 [-]: FASTCALL1 62 R5 L6
      37 [-]: GETIMPORT R4 9 [nil]
      38 [-]: CALL R4 1 1  
L 6:  39 [-]: JUMPIFNOT R4 L10
      40 [-]: GETUPVAL R6 1
      41 [-]: GETTABLEKS R5 R6 K22 [0xBD51F1E9]
      42 [-]: CALL R5 0 1  
      43 [-]: ADDK R4 R5 K21 [5]
      44 [-]: GETIMPORT R5 23 [nil]
      45 [-]: GETIMPORT R6 25 [nil]
      46 [-]: LOADK R7 K19 ["SurvivalTimer"]
      47 [-]: GETUPVAL R9 2
      48 [-]: GETTABLEKS R8 R9 K26 ["HT_TIMER"]
      49 [-]: LOADK R9 K27 [0.25]
      50 [-]: MOVE R10 R4  
      51 [-]: LOADB R11 1  
      52 [-]: CALL R6 5 1  
      53 [-]: SETTABLEKS R6 R5 K19 ["SurvivalTimer"]
      54 [-]: GETIMPORT R6 1 [nil]
      55 [-]: NAMECALL R6 R6 K28 [0xEF893AEC]
      56 [-]: CALL R6 1 1  
      57 [-]: LOADB R5 1   
      58 [-]: GETTABLEKS R7 R6 K29 ["alertId"]
      59 [-]: JUMPXEQKS R7 K30 L8 NOT [""]
      60 [-]: LOADB R5 1   
      61 [-]: GETTABLEKS R7 R6 K31 ["invasionId"]
      62 [-]: JUMPXEQKS R7 K30 L8 NOT [""]
      63 [-]: GETTABLEKS R7 R6 K32 ["syndicateTag"]
      64 [-]: NAMECALL R7 R7 K33 [0x56C01834]
      65 [-]: CALL R7 1 1  
      66 [-]: MOVE R5 R7   
      67 [-]: JUMPIF R5 L8 
      68 [-]: GETTABLEKS R7 R6 K34 ["maxWaveNum"]
      69 [-]: LOADN R8 0   
      70 [-]: JUMPIFLT R8 R7 L7
      71 [-]: LOADB R5 0 +1
L 7:  72 [-]: LOADB R5 1   
L 8:  73 [-]: JUMPIFNOT R5 L9
      74 [-]: GETIMPORT R5 36 [nil]
      75 [-]: LOADK R6 K37 ["/Lotus/Language/Objectives/ObjectiveTimeLeft"]
      76 [-]: CALL R5 1 0  
L 9:  77 [-]: GETUPVAL R6 1
      78 [-]: GETTABLEKS R5 R6 K38 [0x1645F3C0]
      79 [-]: CALL R5 0 2  
      80 [-]: GETIMPORT R7 40 [nil]
      81 [-]: MOVE R8 R5   
      82 [-]: MOVE R9 R6   
      83 [-]: LOADB R10 1  
      84 [-]: CALL R7 3 0  
L10:  85 [-]: GETUPVAL R7 3
      86 [-]: NAMECALL R5 R0 K41 [0xFFDDF768]
      87 [-]: CALL R5 2 1  
      88 [-]: FASTCALL1 12 R5 L11
      89 [-]: GETIMPORT R4 15 [nil]
      90 [-]: CALL R4 1 1  
L11:  91 [-]: GETIMPORT R5 43 [nil]
      92 [-]: MOVE R6 R4   
      93 [-]: CALL R5 1 0  
      94 [-]: RETURN R0 0  


; Name:            
; Defined at line: 793
; #Upvalues:       1
; #Parameters:     1
; Is_vararg:       0
; Max Stack Size:  8

       0 [-]: GETIMPORT R1 1 [nil]
       1 [-]: GETUPVAL R4 0
       2 [-]: NAMECALL R2 R1 K2 [0x0EB34C69]
       3 [-]: CALL R2 2 1  
       4 [-]: LOADN R3 0   
       5 [-]: JUMPIFNOTLE R2 R3 L0
       6 [-]: RETURN R0 0  
L 0:   7 [-]: ADD R3 R2 R0 
       8 [-]: LOADN R4 150 
       9 [-]: JUMPIFNOTLT R4 R3 L1
      10 [-]: LOADN R3 150 
L 1:  11 [-]: GETUPVAL R6 0
      12 [-]: MOVE R7 R3   
      13 [-]: NAMECALL R4 R1 K3 [0x751F061D]
      14 [-]: CALL R4 3 0  
      15 [-]: RETURN R0 0  


; Name:            
; Defined at line: 807
; #Upvalues:       4
; #Parameters:     0
; Is_vararg:       0
; Max Stack Size:  9

       0 [-]: GETIMPORT R0 1 [nil]
       1 [-]: NAMECALL R0 R0 K2 [0x18D05D30]
       2 [-]: CALL R0 1 1  
       3 [-]: JUMPIF R0 L0 
       4 [-]: RETURN R0 0  
L 0:   5 [-]: LOADN R0 7   
       6 [-]: LOADB R1 1   
       7 [-]: GETIMPORT R3 4 [nil]
       8 [-]: NAMECALL R3 R3 K5 [0xEF893AEC]
       9 [-]: CALL R3 1 1  
      10 [-]: GETTABLEKS R2 R3 K6 ["periodicMissionTag"]
      11 [-]: GETUPVAL R4 0
      12 [-]: GETTABLEKS R3 R4 K7 ["ELITE_ALERT_PERIODIC_MISSION_TAG"]
      13 [-]: JUMPIFEQ R2 R3 L2
      14 [-]: GETIMPORT R3 4 [nil]
      15 [-]: NAMECALL R3 R3 K5 [0xEF893AEC]
      16 [-]: CALL R3 1 1  
      17 [-]: GETTABLEKS R2 R3 K6 ["periodicMissionTag"]
      18 [-]: GETUPVAL R4 0
      19 [-]: GETTABLEKS R3 R4 K8 ["ELITE_ALERT_PERIODIC_MISSION_TAG_ALT"]
      20 [-]: JUMPIFEQ R2 R3 L1
      21 [-]: LOADB R1 0 +1
L 1:  22 [-]: LOADB R1 1   
L 2:  23 [-]: JUMPIFNOT R1 L3
      24 [-]: MULK R0 R0 K9 [0.75]
L 3:  25 [-]: MOVE R1 R0   
      26 [-]: GETIMPORT R2 4 [nil]
      27 [-]: GETUPVAL R5 1
      28 [-]: NAMECALL R3 R2 K10 [0x0EB34C69]
      29 [-]: CALL R3 2 1  
      30 [-]: LOADN R4 0   
      31 [-]: JUMPIFNOTLE R3 R4 L4
      32 [-]: JUMP L6
     
L 4:  33 [-]: ADD R4 R3 R1 
      34 [-]: LOADN R5 150 
      35 [-]: JUMPIFNOTLT R5 R4 L5
      36 [-]: LOADN R4 150 
L 5:  37 [-]: GETUPVAL R7 1
      38 [-]: MOVE R8 R4   
      39 [-]: NAMECALL R5 R2 K11 [0x751F061D]
      40 [-]: CALL R5 3 0  
L 6:  41 [-]: GETIMPORT R1 4 [nil]
      42 [-]: GETUPVAL R3 2
      43 [-]: NAMECALL R1 R1 K10 [0x0EB34C69]
      44 [-]: CALL R1 2 1  
      45 [-]: LOADN R2 60  
      46 [-]: JUMPIFNOTLT R1 R2 L7
      47 [-]: GETIMPORT R3 4 [nil]
      48 [-]: NAMECALL R3 R3 K5 [0xEF893AEC]
      49 [-]: CALL R3 1 1  
      50 [-]: GETTABLEKS R2 R3 K12 ["difficulty"]
      51 [-]: LOADK R3 K13 [0.80000000000000004]
      52 [-]: JUMPIFNOTLT R2 R3 L7
      53 [-]: GETUPVAL R3 3
      54 [-]: GETTABLEKS R2 R3 K14 [0x9742B85B]
      55 [-]: GETIMPORT R3 17 [nil]
      56 [-]: GETIMPORT R4 19 [nil]
      57 [-]: LOADK R5 K20 ["SurvivalPickupVO"]
      58 [-]: CALL R4 1 -1 
      59 [-]: CALL R2 -1 0 
L 7:  60 [-]: RETURN R0 0  


; Name:            
; Defined at line: 822
; #Upvalues:       1
; #Parameters:     1
; Is_vararg:       0
; Max Stack Size:  3

       0 [-]: GETUPVAL R2 0
       1 [-]: GETTABLEKS R1 R2 K0 [0x34A96A3D]
       2 [-]: MOVE R2 R0   
       3 [-]: CALL R1 1 0  
       4 [-]: RETURN R0 0  


; Name:            
; Defined at line: 828
; #Upvalues:       0
; #Parameters:     0
; Is_vararg:       0
; Max Stack Size:  4

       0 [-]: GETIMPORT R1 2 [nil]
       1 [-]: FASTCALL1 62 R1 L0
       2 [-]: GETIMPORT R0 4 [nil]
       3 [-]: CALL R0 1 1  
L 0:   4 [-]: JUMPIFNOT R0 L1
       5 [-]: GETIMPORT R0 6 [nil]
       6 [-]: NAMECALL R0 R0 K7 [0x29EF273D]
       7 [-]: CALL R0 1 1  
       8 [-]: NAMECALL R0 R0 K8 [0x66905CB0]
       9 [-]: CALL R0 1 1  
      10 [-]: GETIMPORT R1 9 [nil]
      11 [-]: NAMECALL R2 R0 K10 [0xCEA36880]
      12 [-]: CALL R2 1 1  
      13 [-]: SETTABLEKS R2 R1 K1 ["EndlessModeEnemyLevel"]
L 1:  14 [-]: GETIMPORT R2 2 [nil]
      15 [-]: DIVK R1 R2 K11 [30]
      16 [-]: FASTCALL2K 19 R1 K12 L2 [1]
      17 [-]: LOADK R2 K12 [1]
      18 [-]: GETIMPORT R0 15 [nil]
      19 [-]: CALL R0 2 1  
L 2:  20 [-]: RETURN R0 1  


; Name:            
; Defined at line: 837
; #Upvalues:       0
; #Parameters:     2
; Is_vararg:       0
; Max Stack Size:  14

       0 [-]: NAMECALL R2 R0 K0 [0x9E21E394]
       1 [-]: CALL R2 1 0  
       2 [-]: GETIMPORT R2 2 [nil]
       3 [-]: LOADN R3 0   
       4 [-]: CALL R2 1 0  
       5 [-]: FASTCALL1 62 R0 L0
       6 [-]: MOVE R3 R0   
       7 [-]: GETIMPORT R2 4 [nil]
       8 [-]: CALL R2 1 1  
L 0:   9 [-]: JUMPIFNOT R2 L1
      10 [-]: RETURN R0 0  
L 1:  11 [-]: NAMECALL R2 R0 K5 [0xBB610E5B]
      12 [-]: CALL R2 1 1  
      13 [-]: FASTCALL1 62 R2 L2
      14 [-]: MOVE R4 R2   
      15 [-]: GETIMPORT R3 4 [nil]
      16 [-]: CALL R3 1 1  
L 2:  17 [-]: JUMPIFNOT R3 L3
      18 [-]: RETURN R0 0  
L 3:  19 [-]: LOADNIL R3   
      20 [-]: GETIMPORT R5 8 [nil]
      21 [-]: FASTCALL1 62 R5 L4
      22 [-]: GETIMPORT R4 4 [nil]
      23 [-]: CALL R4 1 1  
L 4:  24 [-]: JUMPIF R4 L9 
      25 [-]: NEWTABLE R4 0 0
      26 [-]: GETIMPORT R5 10 [nil]
      27 [-]: GETIMPORT R6 8 [nil]
      28 [-]: CALL R5 1 3  
      29 [-]: FORGPREP_INEXT R5 L7
L 5:  30 [-]: JUMPXEQKN R9 K11 L7 [0]
      31 [-]: NAMECALL R10 R9 K5 [0xBB610E5B]
      32 [-]: CALL R10 1 1 
      33 [-]: FASTCALL1 62 R10 L6
      34 [-]: MOVE R12 R10 
      35 [-]: GETIMPORT R11 4 [nil]
      36 [-]: CALL R11 1 1 
L 6:  37 [-]: JUMPIF R11 L7
      38 [-]: FASTCALL2 52 R4 R10 L7
      39 [-]: MOVE R12 R4  
      40 [-]: MOVE R13 R10 
      41 [-]: GETIMPORT R11 14 [nil]
      42 [-]: CALL R11 2 0 
L 7:  43 [-]: FORGLOOP R5 L5 2 [inext]
      44 [-]: LENGTH R5 R4 
      45 [-]: JUMPXEQKN R5 K15 L8 NOT [1]
      46 [-]: GETTABLEN R3 R4 1
      47 [-]: JUMP L9
     
L 8:  48 [-]: LENGTH R5 R4 
      49 [-]: LOADN R6 1   
      50 [-]: JUMPIFNOTLT R6 R5 L9
      51 [-]: GETIMPORT R5 17 [nil]
      52 [-]: MOVE R7 R2   
      53 [-]: MOVE R8 R4   
      54 [-]: NAMECALL R5 R5 K18 [0xEBBDC5C2]
      55 [-]: CALL R5 3 1  
      56 [-]: MOVE R3 R5   
L 9:  57 [-]: FASTCALL1 62 R3 L10
      58 [-]: MOVE R5 R3   
      59 [-]: GETIMPORT R4 4 [nil]
      60 [-]: CALL R4 1 1  
L10:  61 [-]: JUMPIFNOT R4 L19
      62 [-]: LOADN R4 1   
L11:  63 [-]: LENGTH R5 R1 
      64 [-]: JUMPIFNOTLE R4 R5 L16
      65 [-]: GETTABLE R6 R1 R4
      66 [-]: FASTCALL1 62 R6 L12
      67 [-]: GETIMPORT R5 4 [nil]
      68 [-]: CALL R5 1 1  
L12:  69 [-]: JUMPIF R5 L13
      70 [-]: GETTABLE R5 R1 R4
      71 [-]: NAMECALL R5 R5 K19 [0x2047CFE7]
      72 [-]: CALL R5 1 1  
      73 [-]: JUMPIFNOT R5 L14
L13:  74 [-]: GETIMPORT R5 21 [nil]
      75 [-]: MOVE R6 R1   
      76 [-]: MOVE R7 R4   
      77 [-]: CALL R5 2 0  
      78 [-]: JUMP L15
    
L14:  79 [-]: ADDK R4 R4 K15 [1]
L15:  80 [-]: JUMPBACK L11 
L16:  81 [-]: LENGTH R4 R1 
      82 [-]: JUMPXEQKN R4 K11 L17 NOT [0]
      83 [-]: LOADNIL R3   
      84 [-]: JUMP L19
    
L17:  85 [-]: JUMPXEQKN R4 K15 L18 NOT [1]
      86 [-]: GETTABLEN R3 R1 1
      87 [-]: JUMP L19
    
L18:  88 [-]: GETIMPORT R5 17 [nil]
      89 [-]: MOVE R7 R2   
      90 [-]: MOVE R8 R1   
      91 [-]: NAMECALL R5 R5 K18 [0xEBBDC5C2]
      92 [-]: CALL R5 3 1  
      93 [-]: MOVE R3 R5   
L19:  94 [-]: FASTCALL1 62 R3 L20
      95 [-]: MOVE R5 R3   
      96 [-]: GETIMPORT R4 4 [nil]
      97 [-]: CALL R4 1 1  
L20:  98 [-]: JUMPIFNOT R4 L21
      99 [-]: GETIMPORT R4 23 [nil]
     100 [-]: LOADK R6 K24 ["No target to storm for "]
     101 [-]: NAMECALL R7 R2 K25 [0xED4E0128]
     102 [-]: CALL R7 1 1  
     103 [-]: CONCAT R5 R6 R7
     104 [-]: CALL R4 1 0  
     105 [-]: RETURN R0 0  
L21: 106 [-]: MOVE R6 R3   
     107 [-]: NAMECALL R4 R0 K26 [0xA64A1F4A]
     108 [-]: CALL R4 2 0  
     109 [-]: RETURN R0 0  


; Name:            
; Defined at line: 900
; #Upvalues:       6
; #Parameters:     0
; Is_vararg:       0
; Max Stack Size:  20

       0 [-]: GETIMPORT R0 1 [nil]
       1 [-]: NAMECALL R0 R0 K2 [0x29EF273D]
       2 [-]: CALL R0 1 1  
       3 [-]: NAMECALL R1 R0 K3 [0x66905CB0]
       4 [-]: CALL R1 1 1  
       5 [-]: GETIMPORT R2 5 [nil]
       6 [-]: NAMECALL R3 R2 K6 [0xEF893AEC]
       7 [-]: CALL R3 1 1  
       8 [-]: GETIMPORT R5 1 [nil]
       9 [-]: NAMECALL R5 R5 K7 [0x61BE252A]
      10 [-]: CALL R5 1 1  
      11 [-]: GETIMPORT R6 9 [nil]
      12 [-]: LOADK R8 K10 ["Server.NumVirtualTestClients"]
      13 [-]: NAMECALL R6 R6 K11 [0x8151451D]
      14 [-]: CALL R6 2 1  
      15 [-]: ADD R4 R5 R6 
      16 [-]: GETUPVAL R7 0
      17 [-]: NAMECALL R5 R2 K12 [0x0EB34C69]
      18 [-]: CALL R5 2 1  
      19 [-]: GETUPVAL R6 1
      20 [-]: GETUPVAL R7 2
      21 [-]: FASTCALL2K 19 R4 K13 L0 [4]
      22 [-]: MOVE R9 R4   
      23 [-]: LOADK R10 K13 [4]
      24 [-]: GETIMPORT R8 16 [nil]
      25 [-]: CALL R8 2 1  
L 0:  26 [-]: NAMECALL R9 R3 K17 [0x243148D6]
      27 [-]: CALL R9 1 1  
      28 [-]: GETIMPORT R10 19 [nil]
      29 [-]: LOADK R11 K20 ["Infestation"]
      30 [-]: CALL R10 1 1 
      31 [-]: JUMPIFNOTEQ R9 R10 L1
      32 [-]: GETUPVAL R6 3
      33 [-]: GETUPVAL R7 4
L 1:  34 [-]: GETUPVAL R11 5
      35 [-]: GETTABLEKS R10 R11 K21 [0x4A85E2C2]
      36 [-]: CALL R10 0 1 
      37 [-]: JUMPIFNOT R10 L2
      38 [-]: LOADN R8 4   
L 2:  39 [-]: GETIMPORT R10 24 [nil]
      40 [-]: CALL R10 0 1 
      41 [-]: JUMPIFNOT R10 L4
      42 [-]: LOADN R11 3  
      43 [-]: FASTCALL2 19 R11 R8 L3
      44 [-]: MOVE R12 R8  
      45 [-]: GETIMPORT R10 16 [nil]
      46 [-]: CALL R10 2 1 
L 3:  47 [-]: MOVE R8 R10  
L 4:  48 [-]: NAMECALL R11 R1 K25 [0x9A49D00C]
      49 [-]: CALL R11 1 1 
      50 [-]: GETTABLE R12 R6 R8
      51 [-]: FASTCALL2 19 R11 R12 L5
      52 [-]: GETIMPORT R10 16 [nil]
      53 [-]: CALL R10 2 1 
L 5:  54 [-]: NAMECALL R12 R1 K25 [0x9A49D00C]
      55 [-]: CALL R12 1 1 
      56 [-]: GETTABLE R13 R7 R8
      57 [-]: FASTCALL2 19 R12 R13 L6
      58 [-]: GETIMPORT R11 16 [nil]
      59 [-]: CALL R11 2 1 
L 6:  60 [-]: GETIMPORT R12 27 [nil]
      61 [-]: MOVE R13 R10 
      62 [-]: MOVE R14 R11 
      63 [-]: GETIMPORT R17 30 [nil]
      64 [-]: FASTCALL1 62 R17 L7
      65 [-]: GETIMPORT R16 32 [nil]
      66 [-]: CALL R16 1 1 
L 7:  67 [-]: JUMPIFNOT R16 L8
      68 [-]: GETIMPORT R16 1 [nil]
      69 [-]: NAMECALL R16 R16 K2 [0x29EF273D]
      70 [-]: CALL R16 1 1 
      71 [-]: NAMECALL R16 R16 K3 [0x66905CB0]
      72 [-]: CALL R16 1 1 
      73 [-]: GETIMPORT R17 33 [nil]
      74 [-]: NAMECALL R18 R16 K34 [0xCEA36880]
      75 [-]: CALL R18 1 1 
      76 [-]: SETTABLEKS R18 R17 K29 ["EndlessModeEnemyLevel"]
L 8:  77 [-]: GETIMPORT R18 30 [nil]
      78 [-]: DIVK R17 R18 K35 [30]
      79 [-]: FASTCALL2K 19 R17 K36 L9 [1]
      80 [-]: LOADK R18 K36 [1]
      81 [-]: GETIMPORT R16 16 [nil]
      82 [-]: CALL R16 2 1 
L 9:  83 [-]: MOVE R15 R16 
      84 [-]: CALL R12 3 1 
      85 [-]: FASTCALL1 12 R12 L10
      86 [-]: MOVE R14 R12 
      87 [-]: GETIMPORT R13 38 [nil]
      88 [-]: CALL R13 1 1 
L10:  89 [-]: RETURN R13 1 


; Name:            
; Defined at line: 938
; #Upvalues:       1
; #Parameters:     0
; Is_vararg:       0
; Max Stack Size:  5

       0 [-]: GETIMPORT R0 1 [nil]
       1 [-]: NAMECALL R0 R0 K2 [0x29EF273D]
       2 [-]: CALL R0 1 1  
       3 [-]: NAMECALL R1 R0 K3 [0x66905CB0]
       4 [-]: CALL R1 1 1  
       5 [-]: GETUPVAL R2 0
       6 [-]: CALL R2 0 1  
       7 [-]: NAMECALL R3 R1 K4 [0xE2E98521]
       8 [-]: CALL R3 1 1  
       9 [-]: JUMPIFNOTLT R3 R2 L0
      10 [-]: NAMECALL R3 R1 K5 [0xE830AC3D]
      11 [-]: CALL R3 1 1  
      12 [-]: ADDK R4 R2 K6 [20]
      13 [-]: JUMPIFNOTLT R3 R4 L0
      14 [-]: LOADB R3 1   
      15 [-]: RETURN R3 1  
L 0:  16 [-]: LOADB R3 0   
      17 [-]: RETURN R3 1  


; Name:            
; Defined at line: 948
; #Upvalues:       5
; #Parameters:     0
; Is_vararg:       0
; Max Stack Size:  12

       0 [-]: GETIMPORT R0 1 [nil]
       1 [-]: GETUPVAL R3 0
       2 [-]: NAMECALL R1 R0 K2 [0x0EB34C69]
       3 [-]: CALL R1 2 1  
       4 [-]: DIVK R2 R1 K3 [150]
       5 [-]: GETUPVAL R3 1
       6 [-]: CALL R3 0 1  
       7 [-]: LOADK R6 K5 [29.903225806451612]
       8 [-]: LOADK R8 K6 [-0.61290322580645162]
       9 [-]: MUL R7 R8 R3 
      10 [-]: ADD R5 R6 R7 
      11 [-]: DIVK R4 R5 K4 [100]
      12 [-]: GETUPVAL R7 2
      13 [-]: NAMECALL R5 R0 K2 [0x0EB34C69]
      14 [-]: CALL R5 2 1  
      15 [-]: JUMPXEQKN R5 K7 L0 NOT [4]
      16 [-]: LOADN R4 0   
      17 [-]: JUMP L2
     
L 0:  18 [-]: LOADK R5 K8 [0.050000000000000003]
      19 [-]: JUMPIFNOTLE R2 R5 L1
      20 [-]: MULK R4 R4 K9 [1.5]
      21 [-]: JUMP L2
     
L 1:  22 [-]: LOADK R5 K10 [0.94999999999999996]
      23 [-]: JUMPIFNOTLE R5 R2 L2
      24 [-]: MULK R4 R4 K11 [0.5]
L 2:  25 [-]: GETIMPORT R6 1 [nil]
      26 [-]: NAMECALL R6 R6 K12 [0xEF893AEC]
      27 [-]: CALL R6 1 1  
      28 [-]: LOADB R5 1   
      29 [-]: GETTABLEKS R7 R6 K13 ["alertId"]
      30 [-]: JUMPXEQKS R7 K14 L4 NOT [""]
      31 [-]: LOADB R5 1   
      32 [-]: GETTABLEKS R7 R6 K15 ["invasionId"]
      33 [-]: JUMPXEQKS R7 K14 L4 NOT [""]
      34 [-]: GETTABLEKS R7 R6 K16 ["syndicateTag"]
      35 [-]: NAMECALL R7 R7 K17 [0x56C01834]
      36 [-]: CALL R7 1 1  
      37 [-]: MOVE R5 R7   
      38 [-]: JUMPIF R5 L4 
      39 [-]: GETTABLEKS R7 R6 K18 ["maxWaveNum"]
      40 [-]: LOADN R8 0   
      41 [-]: JUMPIFLT R8 R7 L3
      42 [-]: LOADB R5 0 +1
L 3:  43 [-]: LOADB R5 1   
L 4:  44 [-]: JUMPIFNOT R5 L10
      45 [-]: GETIMPORT R6 1 [nil]
      46 [-]: NAMECALL R6 R6 K12 [0xEF893AEC]
      47 [-]: CALL R6 1 1  
      48 [-]: GETUPVAL R8 3
      49 [-]: GETTABLEKS R7 R8 K19 [0x06D055F9]
      50 [-]: GETTABLEKS R9 R6 K18 ["maxWaveNum"]
      51 [-]: LOADN R10 0  
      52 [-]: JUMPIFLT R10 R9 L5
      53 [-]: LOADB R8 0 +1
L 5:  54 [-]: LOADB R8 1   
L 6:  55 [-]: GETTABLEKS R11 R6 K18 ["maxWaveNum"]
      56 [-]: MULK R10 R11 K20 [60]
      57 [-]: FASTCALL2K 19 R10 K21 L7 [3600]
      58 [-]: LOADK R11 K21 [3600]
      59 [-]: GETIMPORT R9 24 [nil]
      60 [-]: CALL R9 2 1  
L 7:  61 [-]: LOADN R10 600
      62 [-]: CALL R7 3 1  
      63 [-]: MOVE R5 R7   
      64 [-]: LOADN R6 600 
      65 [-]: JUMPIFNOTLE R5 R6 L8
      66 [-]: MULK R4 R4 K25 [0.90000000000000002]
      67 [-]: JUMP L9
     
L 8:  68 [-]: LOADN R6 600 
      69 [-]: JUMPIFNOTLT R6 R5 L9
      70 [-]: LOADN R6 1200
      71 [-]: JUMPIFNOTLT R5 R6 L9
      72 [-]: SUBK R7 R5 K26 [600]
      73 [-]: DIVK R6 R7 K26 [600]
      74 [-]: GETIMPORT R7 28 [nil]
      75 [-]: MULK R8 R4 K25 [0.90000000000000002]
      76 [-]: MOVE R9 R4   
      77 [-]: MOVE R10 R6  
      78 [-]: CALL R7 3 1  
      79 [-]: MOVE R4 R7   
L 9:  80 [-]: GETUPVAL R8 4
      81 [-]: NAMECALL R6 R0 K29 [0xFFDDF768]
      82 [-]: CALL R6 2 1  
      83 [-]: LOADN R7 0   
      84 [-]: JUMPIFNOTLE R6 R7 L10
      85 [-]: LOADN R4 0   
L10:  86 [-]: MOVE R7 R4   
      87 [-]: GETIMPORT R8 31 [nil]
      88 [-]: NAMECALL R5 R0 K32 [0xDDA55336]
      89 [-]: CALL R5 3 0  
      90 [-]: RETURN R0 0  


; Name:            
; Defined at line: 989
; #Upvalues:       2
; #Parameters:     0
; Is_vararg:       0
; Max Stack Size:  6

       0 [-]: LOADK R1 K0 [0.25]
       1 [-]: GETUPVAL R5 0
       2 [-]: FASTCALL1 9 R5 L0
       3 [-]: GETIMPORT R4 5 [nil]
       4 [-]: CALL R4 1 1  
L 0:   5 [-]: ADDK R3 R4 K2 [0.98999999999999999]
       6 [-]: POWK R2 R3 K1 [2]
       7 [-]: MUL R0 R1 R2 
       8 [-]: GETIMPORT R1 7 [nil]
       9 [-]: LOADK R2 K8 [0.10000000000000001]
      10 [-]: LOADK R3 K9 [1.8]
      11 [-]: MOVE R4 R0   
      12 [-]: CALL R1 3 1  
      13 [-]: LOADK R3 K10 [6.2800000000000002]
      14 [-]: GETUPVAL R4 1
      15 [-]: CALL R4 0 1  
      16 [-]: DIV R2 R3 R4 
      17 [-]: GETUPVAL R4 0
      18 [-]: ADD R3 R4 R2 
      19 [-]: SETUPVAL R3 0
      20 [-]: GETUPVAL R3 0
      21 [-]: LOADK R4 K10 [6.2800000000000002]
      22 [-]: JUMPIFNOTLT R4 R3 L1
      23 [-]: GETIMPORT R3 12 [nil]
      24 [-]: GETUPVAL R4 0
      25 [-]: LOADK R5 K10 [6.2800000000000002]
      26 [-]: CALL R3 2 1  
      27 [-]: SETUPVAL R3 0
L 1:  28 [-]: RETURN R1 1  


; Name:            
; Defined at line: 1000
; #Upvalues:       10
; #Parameters:     0
; Is_vararg:       0
; Max Stack Size:  33

       0 [-]: GETIMPORT R0 1 [nil]
       1 [-]: NAMECALL R0 R0 K2 [0x29EF273D]
       2 [-]: CALL R0 1 1  
       3 [-]: NAMECALL R1 R0 K3 [0x66905CB0]
       4 [-]: CALL R1 1 1  
       5 [-]: GETIMPORT R2 5 [nil]
       6 [-]: GETUPVAL R5 0
       7 [-]: NAMECALL R3 R2 K6 [0x0EB34C69]
       8 [-]: CALL R3 2 1  
       9 [-]: GETIMPORT R4 1 [nil]
      10 [-]: NAMECALL R4 R4 K7 [0x8B5B1F58]
      11 [-]: CALL R4 1 1  
      12 [-]: GETUPVAL R7 1
      13 [-]: NAMECALL R5 R2 K6 [0x0EB34C69]
      14 [-]: CALL R5 2 1  
      15 [-]: ADD R3 R3 R5 
      16 [-]: NAMECALL R6 R1 K8 [0xCEA36880]
      17 [-]: CALL R6 1 1  
      18 [-]: NAMECALL R7 R1 K9 [0x6968EA36]
      19 [-]: CALL R7 1 1  
      20 [-]: LOADNIL R8   
      21 [-]: GETIMPORT R10 5 [nil]
      22 [-]: NAMECALL R10 R10 K10 [0xEF893AEC]
      23 [-]: CALL R10 1 1 
      24 [-]: LOADB R9 1   
      25 [-]: GETTABLEKS R11 R10 K11 ["alertId"]
      26 [-]: JUMPXEQKS R11 K12 L1 NOT [""]
      27 [-]: LOADB R9 1   
      28 [-]: GETTABLEKS R11 R10 K13 ["invasionId"]
      29 [-]: JUMPXEQKS R11 K12 L1 NOT [""]
      30 [-]: GETTABLEKS R11 R10 K14 ["syndicateTag"]
      31 [-]: NAMECALL R11 R11 K15 [0x56C01834]
      32 [-]: CALL R11 1 1 
      33 [-]: MOVE R9 R11  
      34 [-]: JUMPIF R9 L1 
      35 [-]: GETTABLEKS R11 R10 K16 ["maxWaveNum"]
      36 [-]: LOADN R12 0  
      37 [-]: JUMPIFLT R12 R11 L0
      38 [-]: LOADB R9 0 +1
L 0:  39 [-]: LOADB R9 1   
L 1:  40 [-]: JUMPIFNOT R9 L11
      41 [-]: GETIMPORT R10 5 [nil]
      42 [-]: NAMECALL R10 R10 K10 [0xEF893AEC]
      43 [-]: CALL R10 1 1 
      44 [-]: GETUPVAL R12 3
      45 [-]: GETTABLEKS R11 R12 K17 [0x06D055F9]
      46 [-]: GETTABLEKS R13 R10 K16 ["maxWaveNum"]
      47 [-]: LOADN R14 0  
      48 [-]: JUMPIFLT R14 R13 L2
      49 [-]: LOADB R12 0 +1
L 2:  50 [-]: LOADB R12 1  
L 3:  51 [-]: GETTABLEKS R15 R10 K16 ["maxWaveNum"]
      52 [-]: MULK R14 R15 K18 [60]
      53 [-]: FASTCALL2K 19 R14 K19 L4 [3600]
      54 [-]: LOADK R15 K19 [3600]
      55 [-]: GETIMPORT R13 22 [nil]
      56 [-]: CALL R13 2 1 
L 4:  57 [-]: LOADN R14 600
      58 [-]: CALL R11 3 1 
      59 [-]: MOVE R9 R11  
      60 [-]: SETUPVAL R9 2
      61 [-]: GETIMPORT R10 5 [nil]
      62 [-]: NAMECALL R10 R10 K10 [0xEF893AEC]
      63 [-]: CALL R10 1 1 
      64 [-]: GETUPVAL R12 3
      65 [-]: GETTABLEKS R11 R12 K17 [0x06D055F9]
      66 [-]: GETTABLEKS R13 R10 K16 ["maxWaveNum"]
      67 [-]: LOADN R14 0  
      68 [-]: JUMPIFLT R14 R13 L5
      69 [-]: LOADB R12 0 +1
L 5:  70 [-]: LOADB R12 1  
L 6:  71 [-]: GETTABLEKS R15 R10 K16 ["maxWaveNum"]
      72 [-]: MULK R14 R15 K18 [60]
      73 [-]: FASTCALL2K 19 R14 K19 L7 [3600]
      74 [-]: LOADK R15 K19 [3600]
      75 [-]: GETIMPORT R13 22 [nil]
      76 [-]: CALL R13 2 1 
L 7:  77 [-]: LOADN R14 600
      78 [-]: CALL R11 3 1 
      79 [-]: MOVE R9 R11  
      80 [-]: SETUPVAL R9 4
      81 [-]: GETUPVAL R10 5
      82 [-]: GETTABLEKS R9 R10 K23 [0x51B51D4A]
      83 [-]: CALL R9 0 1  
      84 [-]: JUMPIFNOT R9 L9
      85 [-]: ADDK R11 R6 K24 [15]
      86 [-]: FASTCALL2 18 R7 R11 L8
      87 [-]: MOVE R10 R7  
      88 [-]: GETIMPORT R9 26 [nil]
      89 [-]: CALL R9 2 1  
L 8:  90 [-]: MOVE R7 R9   
      91 [-]: JUMP L11
    
L 9:  92 [-]: ADDK R11 R6 K27 [5]
      93 [-]: FASTCALL2 18 R7 R11 L10
      94 [-]: MOVE R10 R7  
      95 [-]: GETIMPORT R9 26 [nil]
      96 [-]: CALL R9 2 1  
L10:  97 [-]: MOVE R7 R9   
L11:  98 [-]: GETIMPORT R10 5 [nil]
      99 [-]: NAMECALL R10 R10 K10 [0xEF893AEC]
     100 [-]: CALL R10 1 1 
     101 [-]: GETTABLEKS R11 R10 K28 ["goalTag"]
     102 [-]: GETIMPORT R12 30 [nil]
     103 [-]: LOADK R13 K31 ["KuvaSurvival"]
     104 [-]: CALL R12 1 1 
     105 [-]: JUMPIFNOTEQ R11 R12 L12
     106 [-]: LOADB R9 1   
     107 [-]: JUMP L13
    
L12: 108 [-]: LOADB R9 0   
L13: 109 [-]: JUMPIFNOT R9 L14
     110 [-]: LOADN R9 600 
     111 [-]: SETUPVAL R9 2
     112 [-]: LOADN R9 600 
     113 [-]: SETUPVAL R9 4
L14: 114 [-]: GETUPVAL R9 2
     115 [-]: JUMPIFNOTLT R9 R3 L18
     116 [-]: LOADN R12 40 
     117 [-]: GETUPVAL R16 2
     118 [-]: SUB R15 R3 R16
     119 [-]: DIVK R14 R15 K33 [40]
     120 [-]: MULK R13 R14 K32 [0.13]
     121 [-]: SUB R11 R12 R13
     122 [-]: FASTCALL1 12 R11 L15
     123 [-]: GETIMPORT R10 35 [nil]
     124 [-]: CALL R10 1 1 
L15: 125 [-]: FASTCALL2K 18 R10 K36 L16 [3]
     126 [-]: LOADK R11 K36 [3]
     127 [-]: GETIMPORT R9 26 [nil]
     128 [-]: CALL R9 2 1  
L16: 129 [-]: GETUPVAL R13 2
     130 [-]: SUB R12 R3 R13
     131 [-]: DIV R11 R12 R9
     132 [-]: FASTCALL1 12 R11 L17
     133 [-]: GETIMPORT R10 35 [nil]
     134 [-]: CALL R10 1 1 
L17: 135 [-]: ADD R8 R7 R10
     136 [-]: JUMP L19
    
L18: 137 [-]: GETUPVAL R10 4
     138 [-]: DIV R9 R3 R10
     139 [-]: GETIMPORT R10 38 [nil]
     140 [-]: MOVE R11 R6  
     141 [-]: MOVE R12 R7  
     142 [-]: MOVE R13 R9  
     143 [-]: CALL R10 3 1 
     144 [-]: MOVE R8 R10  
L19: 145 [-]: GETIMPORT R11 41 [nil]
     146 [-]: FASTCALL2 19 R8 R11 L20
     147 [-]: MOVE R10 R8  
     148 [-]: GETIMPORT R9 22 [nil]
     149 [-]: CALL R9 2 1  
L20: 150 [-]: MOVE R8 R9   
     151 [-]: GETIMPORT R9 43 [nil]
     152 [-]: SETTABLEKS R8 R9 K44 ["EndlessModeEnemyLevel"]
     153 [-]: NAMECALL R9 R2 K10 [0xEF893AEC]
     154 [-]: CALL R9 1 1  
     155 [-]: LOADN R10 120
     156 [-]: GETIMPORT R12 5 [nil]
     157 [-]: NAMECALL R12 R12 K10 [0xEF893AEC]
     158 [-]: CALL R12 1 1 
     159 [-]: LOADB R11 1  
     160 [-]: GETTABLEKS R13 R12 K11 ["alertId"]
     161 [-]: JUMPXEQKS R13 K12 L22 NOT [""]
     162 [-]: LOADB R11 1  
     163 [-]: GETTABLEKS R13 R12 K13 ["invasionId"]
     164 [-]: JUMPXEQKS R13 K12 L22 NOT [""]
     165 [-]: GETTABLEKS R13 R12 K14 ["syndicateTag"]
     166 [-]: NAMECALL R13 R13 K15 [0x56C01834]
     167 [-]: CALL R13 1 1 
     168 [-]: MOVE R11 R13 
     169 [-]: JUMPIF R11 L22
     170 [-]: GETTABLEKS R13 R12 K16 ["maxWaveNum"]
     171 [-]: LOADN R14 0  
     172 [-]: JUMPIFLT R14 R13 L21
     173 [-]: LOADB R11 0 +1
L21: 174 [-]: LOADB R11 1  
L22: 175 [-]: JUMPIFNOT R11 L28
     176 [-]: LOADN R12 5  
     177 [-]: GETIMPORT R15 5 [nil]
     178 [-]: NAMECALL R15 R15 K10 [0xEF893AEC]
     179 [-]: CALL R15 1 1 
     180 [-]: GETUPVAL R17 3
     181 [-]: GETTABLEKS R16 R17 K17 [0x06D055F9]
     182 [-]: GETTABLEKS R18 R15 K16 ["maxWaveNum"]
     183 [-]: LOADN R19 0  
     184 [-]: JUMPIFLT R19 R18 L23
     185 [-]: LOADB R17 0 +1
L23: 186 [-]: LOADB R17 1  
L24: 187 [-]: GETTABLEKS R20 R15 K16 ["maxWaveNum"]
     188 [-]: MULK R19 R20 K18 [60]
     189 [-]: FASTCALL2K 19 R19 K19 L25 [3600]
     190 [-]: LOADK R20 K19 [3600]
     191 [-]: GETIMPORT R18 22 [nil]
     192 [-]: CALL R18 2 1 
L25: 193 [-]: LOADN R19 600
     194 [-]: CALL R16 3 1 
     195 [-]: MOVE R14 R16 
     196 [-]: SUBK R13 R14 K45 [300]
     197 [-]: FASTCALL2 18 R12 R13 L26
     198 [-]: GETIMPORT R11 26 [nil]
     199 [-]: CALL R11 2 1 
L26: 200 [-]: DIVK R12 R11 K46 [120]
     201 [-]: LOADN R13 5  
     202 [-]: JUMPIFNOTLT R12 R13 L27
     203 [-]: DIVK R10 R11 K27 [5]
L27: 204 [-]: GETUPVAL R13 5
     205 [-]: GETTABLEKS R12 R13 K23 [0x51B51D4A]
     206 [-]: CALL R12 0 1 
     207 [-]: JUMPIFNOT R12 L28
     208 [-]: MULK R10 R10 K47 [0.5]
L28: 209 [-]: DIV R13 R3 R10
     210 [-]: FASTCALL1 12 R13 L29
     211 [-]: GETIMPORT R12 35 [nil]
     212 [-]: CALL R12 1 1 
L29: 213 [-]: MULK R11 R12 K48 [1]
     214 [-]: FASTCALL2K 18 R11 K49 L30 [0]
     215 [-]: MOVE R13 R11 
     216 [-]: LOADK R14 K49 [0]
     217 [-]: GETIMPORT R12 26 [nil]
     218 [-]: CALL R12 2 1 
L30: 219 [-]: MOVE R11 R12 
     220 [-]: FASTCALL2K 19 R11 K27 L31 [5]
     221 [-]: MOVE R13 R11 
     222 [-]: LOADK R14 K27 [5]
     223 [-]: GETIMPORT R12 22 [nil]
     224 [-]: CALL R12 2 1 
L31: 225 [-]: MOVE R11 R12 
     226 [-]: MOVE R14 R11 
     227 [-]: NAMECALL R12 R1 K50 [0xD5BF651F]
     228 [-]: CALL R12 2 0 
     229 [-]: LOADB R12 0  
     230 [-]: GETIMPORT R15 51 [nil]
     231 [-]: FASTCALL1 62 R15 L32
     232 [-]: GETIMPORT R14 53 [nil]
     233 [-]: CALL R14 1 1 
L32: 234 [-]: JUMPIFNOT R14 L33
     235 [-]: GETIMPORT R14 1 [nil]
     236 [-]: NAMECALL R14 R14 K2 [0x29EF273D]
     237 [-]: CALL R14 1 1 
     238 [-]: NAMECALL R14 R14 K3 [0x66905CB0]
     239 [-]: CALL R14 1 1 
     240 [-]: GETIMPORT R15 43 [nil]
     241 [-]: NAMECALL R16 R14 K8 [0xCEA36880]
     242 [-]: CALL R16 1 1 
     243 [-]: SETTABLEKS R16 R15 K44 ["EndlessModeEnemyLevel"]
L33: 244 [-]: GETIMPORT R16 51 [nil]
     245 [-]: DIVK R15 R16 K54 [30]
     246 [-]: FASTCALL2K 19 R15 K48 L34 [1]
     247 [-]: LOADK R16 K48 [1]
     248 [-]: GETIMPORT R14 22 [nil]
     249 [-]: CALL R14 2 1 
L34: 250 [-]: MOVE R13 R14 
     251 [-]: LOADN R15 300
     252 [-]: GETIMPORT R16 38 [nil]
     253 [-]: LOADN R17 600
     254 [-]: LOADN R18 0  
     255 [-]: MOVE R19 R13 
     256 [-]: CALL R16 3 1 
     257 [-]: ADD R14 R15 R16
     258 [-]: LOADN R16 3000
     259 [-]: GETIMPORT R17 38 [nil]
     260 [-]: LOADN R18 600
     261 [-]: LOADN R19 0  
     262 [-]: MOVE R20 R13 
     263 [-]: CALL R17 3 1 
     264 [-]: ADD R15 R16 R17
     265 [-]: LOADK R16 K55 [0.01]
     266 [-]: LOADK R17 K56 [0.14999999999999999]
     267 [-]: GETTABLEKS R18 R9 K57 ["leadersAlwaysAllowed"]
     268 [-]: JUMPIFNOT R18 L36
     269 [-]: GETTABLEKS R18 R9 K58 ["sortieId"]
     270 [-]: JUMPXEQKS R18 K12 L35 NOT [""]
     271 [-]: GETTABLEKS R18 R9 K11 ["alertId"]
     272 [-]: JUMPXEQKS R18 K12 L35 NOT [""]
     273 [-]: GETTABLEKS R18 R9 K59 ["goalId"]
     274 [-]: JUMPXEQKS R18 K12 L36 [""]
L35: 275 [-]: GETIMPORT R18 61 [nil]
     276 [-]: MULK R19 R14 K62 [0.10000000000000001]
     277 [-]: LOADN R20 1  
     278 [-]: MOVE R21 R14 
     279 [-]: CALL R18 3 1 
     280 [-]: MOVE R14 R18 
     281 [-]: GETIMPORT R18 61 [nil]
     282 [-]: MULK R19 R15 K62 [0.10000000000000001]
     283 [-]: LOADN R20 1  
     284 [-]: MOVE R21 R15 
     285 [-]: CALL R18 3 1 
     286 [-]: MOVE R15 R18 
     287 [-]: MULK R16 R16 K27 [5]
     288 [-]: MULK R17 R17 K27 [5]
L36: 289 [-]: JUMPIFNOTLE R14 R3 L38
     290 [-]: SUB R20 R3 R14
     291 [-]: SUB R21 R15 R14
     292 [-]: DIV R19 R20 R21
     293 [-]: FASTCALL2K 19 R19 K48 L37 [1]
     294 [-]: LOADK R20 K48 [1]
     295 [-]: GETIMPORT R18 22 [nil]
     296 [-]: CALL R18 2 1 
L37: 297 [-]: GETIMPORT R19 38 [nil]
     298 [-]: MOVE R20 R16 
     299 [-]: MOVE R21 R17 
     300 [-]: MOVE R22 R18 
     301 [-]: CALL R19 3 1 
     302 [-]: GETIMPORT R20 64 [nil]
     303 [-]: CALL R20 0 1 
     304 [-]: JUMPIFNOTLE R20 R19 L38
     305 [-]: LOADB R12 1  
L38: 306 [-]: LOADNIL R18  
     307 [-]: GETIMPORT R20 66 [nil]
     308 [-]: FASTCALL1 62 R20 L39
     309 [-]: GETIMPORT R19 53 [nil]
     310 [-]: CALL R19 1 1 
L39: 311 [-]: JUMPIF R19 L49
     312 [-]: GETUPVAL R21 6
     313 [-]: NAMECALL R19 R2 K6 [0x0EB34C69]
     314 [-]: CALL R19 2 1 
     315 [-]: LOADN R21 10 
     316 [-]: SUBK R23 R19 K48 [1]
     317 [-]: MODK R22 R23 K36 [3]
     318 [-]: ADD R20 R21 R22
     319 [-]: GETIMPORT R21 51 [nil]
     320 [-]: GETIMPORT R24 68 [nil]
     321 [-]: MOVE R25 R21 
     322 [-]: LOADB R26 1  
     323 [-]: LOADB R27 0  
     324 [-]: MOVE R28 R20 
     325 [-]: LOADB R29 1  
     326 [-]: NAMECALL R22 R1 K69 [0xFEEEA290]
     327 [-]: CALL R22 7 1 
     328 [-]: FASTCALL1 62 R22 L40
     329 [-]: MOVE R24 R22 
     330 [-]: GETIMPORT R23 53 [nil]
     331 [-]: CALL R23 1 1 
L40: 332 [-]: JUMPIFNOT R23 L41
     333 [-]: LOADN R20 5  
     334 [-]: GETIMPORT R25 68 [nil]
     335 [-]: MOVE R26 R21 
     336 [-]: LOADB R27 1  
     337 [-]: LOADB R28 0  
     338 [-]: MOVE R29 R20 
     339 [-]: LOADB R30 0  
     340 [-]: NAMECALL R23 R1 K69 [0xFEEEA290]
     341 [-]: CALL R23 7 1 
     342 [-]: MOVE R22 R23 
L41: 343 [-]: GETIMPORT R25 66 [nil]
     344 [-]: NAMECALL R25 R25 K70 [0xD1586535]
     345 [-]: CALL R25 1 1 
     346 [-]: LOADN R26 5  
     347 [-]: LOADN R27 35 
     348 [-]: LOADB R28 1  
     349 [-]: LOADK R29 K62 [0.10000000000000001]
     350 [-]: NAMECALL R23 R1 K71 [0x96930263]
     351 [-]: CALL R23 6 1 
     352 [-]: MOVE R26 R22 
     353 [-]: MOVE R27 R23 
     354 [-]: GETIMPORT R28 73 [nil]
     355 [-]: CALL R28 0 1 
     356 [-]: GETIMPORT R29 30 [nil]
     357 [-]: LOADK R30 K74 ["MiniBossTeam"]
     358 [-]: CALL R29 1 1 
     359 [-]: MOVE R30 R21 
     360 [-]: LOADNIL R31  
     361 [-]: LOADN R32 1  
     362 [-]: NAMECALL R24 R1 K75 [0x6CD833C5]
     363 [-]: CALL R24 8 1 
     364 [-]: MOVE R18 R24 
     365 [-]: FASTCALL1 62 R18 L42
     366 [-]: MOVE R25 R18 
     367 [-]: GETIMPORT R24 53 [nil]
     368 [-]: CALL R24 1 1 
L42: 369 [-]: JUMPIF R24 L48
     370 [-]: NAMECALL R24 R18 K76 [0xBB610E5B]
     371 [-]: CALL R24 1 1 
     372 [-]: GETIMPORT R26 5 [nil]
     373 [-]: NAMECALL R26 R26 K10 [0xEF893AEC]
     374 [-]: CALL R26 1 1 
     375 [-]: GETTABLEKS R27 R26 K28 ["goalTag"]
     376 [-]: GETIMPORT R28 30 [nil]
     377 [-]: LOADK R29 K31 ["KuvaSurvival"]
     378 [-]: CALL R28 1 1 
     379 [-]: JUMPIFNOTEQ R27 R28 L43
     380 [-]: LOADB R25 1  
     381 [-]: JUMP L44
    
L43: 382 [-]: LOADB R25 0  
L44: 383 [-]: JUMPIFNOT R25 L45
     384 [-]: GETIMPORT R27 78 [nil]
     385 [-]: NAMECALL R25 R24 K79 [0x22C4E9DD]
     386 [-]: CALL R25 2 0 
     387 [-]: JUMP L47
    
L45: 388 [-]: GETUPVAL R26 7
     389 [-]: FASTCALL2 52 R26 R18 L46
     390 [-]: MOVE R27 R18 
     391 [-]: GETIMPORT R25 82 [nil]
     392 [-]: CALL R25 2 0 
L46: 393 [-]: GETUPVAL R25 8
     394 [-]: MOVE R26 R18 
     395 [-]: MOVE R27 R4  
     396 [-]: CALL R25 2 0 
L47: 397 [-]: GETIMPORT R27 84 [nil]
     398 [-]: GETIMPORT R28 30 [nil]
     399 [-]: LOADK R29 K85 ["GAME_C1_SPINE3"]
     400 [-]: CALL R28 1 -1
     401 [-]: NAMECALL R25 R24 K86 [0x47901F07]
     402 [-]: CALL R25 -1 0
     403 [-]: GETIMPORT R25 43 [nil]
     404 [-]: LOADNIL R26  
     405 [-]: SETTABLEKS R26 R25 K65 ["gMiniBossArtifactSpawn"]
L48: 406 [-]: GETUPVAL R26 9
     407 [-]: LOADN R27 0  
     408 [-]: NAMECALL R24 R2 K87 [0x751F061D]
     409 [-]: CALL R24 3 0 
     410 [-]: RETURN R18 1 
L49: 411 [-]: LOADNIL R21  
     412 [-]: GETIMPORT R22 30 [nil]
     413 [-]: LOADK R23 K88 ["RandomTeam"]
     414 [-]: CALL R22 1 1 
     415 [-]: MOVE R23 R8  
     416 [-]: LOADNIL R24  
     417 [-]: GETUPVAL R26 3
     418 [-]: GETTABLEKS R25 R26 K17 [0x06D055F9]
     419 [-]: MOVE R26 R12 
     420 [-]: LOADN R27 1  
     421 [-]: LOADN R28 0  
     422 [-]: CALL R25 3 -1
     423 [-]: NAMECALL R19 R1 K89 [0xC3F557D6]
     424 [-]: CALL R19 -1 1
     425 [-]: MOVE R18 R19 
     426 [-]: FASTCALL1 62 R18 L50
     427 [-]: MOVE R20 R18 
     428 [-]: GETIMPORT R19 53 [nil]
     429 [-]: CALL R19 1 1 
L50: 430 [-]: JUMPIF R19 L52
     431 [-]: GETUPVAL R20 7
     432 [-]: FASTCALL2 52 R20 R18 L51
     433 [-]: MOVE R21 R18 
     434 [-]: GETIMPORT R19 82 [nil]
     435 [-]: CALL R19 2 0 
L51: 436 [-]: GETUPVAL R19 8
     437 [-]: MOVE R20 R18 
     438 [-]: MOVE R21 R4  
     439 [-]: CALL R19 2 0 
L52: 440 [-]: RETURN R18 1 


; Name:            
; Defined at line: 1132
; #Upvalues:       5
; #Parameters:     1
; Is_vararg:       0
; Max Stack Size:  10

       0 [-]: LOADN R1 0   
       1 [-]: GETUPVAL R2 0
       2 [-]: CALL R2 0 0  
       3 [-]: GETIMPORT R3 1 [nil]
       4 [-]: NAMECALL R3 R3 K2 [0x29EF273D]
       5 [-]: CALL R3 1 1  
       6 [-]: NAMECALL R4 R3 K3 [0x66905CB0]
       7 [-]: CALL R4 1 1  
       8 [-]: GETUPVAL R5 1
       9 [-]: CALL R5 0 1  
      10 [-]: NAMECALL R6 R4 K4 [0xE2E98521]
      11 [-]: CALL R6 1 1  
      12 [-]: JUMPIFNOTLT R6 R5 L0
      13 [-]: NAMECALL R6 R4 K5 [0xE830AC3D]
      14 [-]: CALL R6 1 1  
      15 [-]: ADDK R7 R5 K6 [20]
      16 [-]: JUMPIFNOTLT R6 R7 L0
      17 [-]: LOADB R2 1   
      18 [-]: JUMP L1
     
L 0:  19 [-]: LOADB R2 0   
L 1:  20 [-]: JUMPIFNOT R2 L10
      21 [-]: GETUPVAL R4 2
      22 [-]: SUB R3 R4 R0 
      23 [-]: MINUS R4 R0  
      24 [-]: FASTCALL2 18 R3 R4 L2
      25 [-]: GETIMPORT R2 9 [nil]
      26 [-]: CALL R2 2 1  
L 2:  27 [-]: SETUPVAL R2 2
L 3:  28 [-]: GETIMPORT R3 1 [nil]
      29 [-]: NAMECALL R3 R3 K2 [0x29EF273D]
      30 [-]: CALL R3 1 1  
      31 [-]: NAMECALL R4 R3 K3 [0x66905CB0]
      32 [-]: CALL R4 1 1  
      33 [-]: GETUPVAL R5 1
      34 [-]: CALL R5 0 1  
      35 [-]: NAMECALL R6 R4 K4 [0xE2E98521]
      36 [-]: CALL R6 1 1  
      37 [-]: JUMPIFNOTLT R6 R5 L4
      38 [-]: NAMECALL R6 R4 K5 [0xE830AC3D]
      39 [-]: CALL R6 1 1  
      40 [-]: ADDK R7 R5 K6 [20]
      41 [-]: JUMPIFNOTLT R6 R7 L4
      42 [-]: LOADB R2 1   
      43 [-]: JUMP L5
     
L 4:  44 [-]: LOADB R2 0   
L 5:  45 [-]: JUMPIFNOT R2 L10
      46 [-]: GETUPVAL R2 2
      47 [-]: LOADN R3 0   
      48 [-]: JUMPIFLT R3 R2 L10
      49 [-]: JUMPIFLE R0 R1 L10
      50 [-]: GETUPVAL R2 3
      51 [-]: CALL R2 0 1  
      52 [-]: FASTCALL1 62 R2 L6
      53 [-]: MOVE R4 R2   
      54 [-]: GETIMPORT R3 11 [nil]
      55 [-]: CALL R3 1 1  
L 6:  56 [-]: JUMPIF R3 L9 
      57 [-]: LOADK R5 K12 [0.25]
      58 [-]: GETUPVAL R9 4
      59 [-]: FASTCALL1 9 R9 L7
      60 [-]: GETIMPORT R8 16 [nil]
      61 [-]: CALL R8 1 1  
L 7:  62 [-]: ADDK R7 R8 K14 [0.98999999999999999]
      63 [-]: POWK R6 R7 K13 [2]
      64 [-]: MUL R4 R5 R6 
      65 [-]: GETIMPORT R5 18 [nil]
      66 [-]: LOADK R6 K19 [0.10000000000000001]
      67 [-]: LOADK R7 K20 [1.8]
      68 [-]: MOVE R8 R4   
      69 [-]: CALL R5 3 1  
      70 [-]: LOADK R7 K21 [6.2800000000000002]
      71 [-]: GETUPVAL R8 1
      72 [-]: CALL R8 0 1  
      73 [-]: DIV R6 R7 R8 
      74 [-]: GETUPVAL R8 4
      75 [-]: ADD R7 R8 R6 
      76 [-]: SETUPVAL R7 4
      77 [-]: GETUPVAL R7 4
      78 [-]: LOADK R8 K21 [6.2800000000000002]
      79 [-]: JUMPIFNOTLT R8 R7 L8
      80 [-]: GETIMPORT R7 23 [nil]
      81 [-]: GETUPVAL R8 4
      82 [-]: LOADK R9 K21 [6.2800000000000002]
      83 [-]: CALL R7 2 1  
      84 [-]: SETUPVAL R7 4
L 8:  85 [-]: MOVE R3 R5   
      86 [-]: GETUPVAL R5 2
      87 [-]: ADD R4 R5 R3 
      88 [-]: SETUPVAL R4 2
L 9:  89 [-]: GETIMPORT R3 25 [nil]
      90 [-]: CALL R3 0 1  
      91 [-]: ADD R1 R1 R3 
      92 [-]: GETIMPORT R3 27 [nil]
      93 [-]: LOADN R4 0   
      94 [-]: CALL R3 1 0  
      95 [-]: JUMPBACK L3  
L10:  96 [-]: RETURN R1 1  


; Name:            
; Defined at line: 1159
; #Upvalues:       1
; #Parameters:     0
; Is_vararg:       0
; Max Stack Size:  6

       0 [-]: GETIMPORT R0 1 [nil]
       1 [-]: GETUPVAL R3 0
       2 [-]: NAMECALL R1 R0 K2 [0x0EB34C69]
       3 [-]: CALL R1 2 1  
       4 [-]: GETUPVAL R4 0
       5 [-]: ADDK R5 R1 K3 [1]
       6 [-]: NAMECALL R2 R0 K4 [0x751F061D]
       7 [-]: CALL R2 3 0  
       8 [-]: RETURN R0 0  


; Name:            
; Defined at line: 1165
; #Upvalues:       0
; #Parameters:     1
; Is_vararg:       0
; Max Stack Size:  4

       0 [-]: GETIMPORT R1 1 [nil]
       1 [-]: MOVE R2 R0   
       2 [-]: LOADK R3 K2 ["OnActivated"]
       3 [-]: CALL R1 2 0  
       4 [-]: RETURN R0 0  


; Name:            
; Defined at line: 1169
; #Upvalues:       10
; #Parameters:     0
; Is_vararg:       0
; Max Stack Size:  17

       0 [-]: GETIMPORT R0 1 [nil]
       1 [-]: GETIMPORT R2 1 [nil]
       2 [-]: NAMECALL R2 R2 K2 [0xEF893AEC]
       3 [-]: CALL R2 1 1  
       4 [-]: LOADB R1 1   
       5 [-]: GETTABLEKS R3 R2 K3 ["alertId"]
       6 [-]: JUMPXEQKS R3 K4 L1 NOT [""]
       7 [-]: LOADB R1 1   
       8 [-]: GETTABLEKS R3 R2 K5 ["invasionId"]
       9 [-]: JUMPXEQKS R3 K4 L1 NOT [""]
      10 [-]: GETTABLEKS R3 R2 K6 ["syndicateTag"]
      11 [-]: NAMECALL R3 R3 K7 [0x56C01834]
      12 [-]: CALL R3 1 1  
      13 [-]: MOVE R1 R3   
      14 [-]: JUMPIF R1 L1 
      15 [-]: GETTABLEKS R3 R2 K8 ["maxWaveNum"]
      16 [-]: LOADN R4 0   
      17 [-]: JUMPIFLT R4 R3 L0
      18 [-]: LOADB R1 0 +1
L 0:  19 [-]: LOADB R1 1   
L 1:  20 [-]: GETUPVAL R4 0
      21 [-]: NAMECALL R2 R0 K9 [0x0EB34C69]
      22 [-]: CALL R2 2 1  
      23 [-]: GETIMPORT R4 1 [nil]
      24 [-]: NAMECALL R4 R4 K2 [0xEF893AEC]
      25 [-]: CALL R4 1 1  
      26 [-]: GETTABLEKS R5 R4 K10 ["goalTag"]
      27 [-]: GETIMPORT R6 12 [nil]
      28 [-]: LOADK R7 K13 ["KuvaSurvival"]
      29 [-]: CALL R6 1 1  
      30 [-]: JUMPIFNOTEQ R5 R6 L2
      31 [-]: LOADB R3 1   
      32 [-]: JUMP L3
     
L 2:  33 [-]: LOADB R3 0   
L 3:  34 [-]: GETUPVAL R6 1
      35 [-]: NAMECALL R4 R0 K9 [0x0EB34C69]
      36 [-]: CALL R4 2 1  
      37 [-]: LOADN R5 4   
      38 [-]: JUMPIFNOTLT R4 R5 L29
      39 [-]: LOADNIL R4   
      40 [-]: GETUPVAL R7 2
      41 [-]: NAMECALL R5 R0 K9 [0x0EB34C69]
      42 [-]: CALL R5 2 1  
L 4:  43 [-]: FASTCALL1 62 R4 L5
      44 [-]: MOVE R7 R4   
      45 [-]: GETIMPORT R6 15 [nil]
      46 [-]: CALL R6 1 1  
L 5:  47 [-]: JUMPIF R6 L6 
      48 [-]: LOADN R6 9   
      49 [-]: JUMPIFLE R6 R5 L6
      50 [-]: JUMPIFNOTLE R2 R5 L13
L 6:  51 [-]: LOADN R6 9   
      52 [-]: JUMPIFNOTLT R5 R6 L10
      53 [-]: JUMPIFNOTLT R5 R2 L10
      54 [-]: GETUPVAL R6 3
      55 [-]: LOADN R7 0   
      56 [-]: CALL R6 1 1  
      57 [-]: LENGTH R7 R6 
      58 [-]: LOADN R8 0   
      59 [-]: JUMPIFNOTLT R8 R7 L7
      60 [-]: GETUPVAL R7 4
      61 [-]: MOVE R8 R6   
      62 [-]: LOADN R9 0   
      63 [-]: CALL R7 2 1  
      64 [-]: MOVE R4 R7   
      65 [-]: JUMP L10
    
L 7:  66 [-]: GETUPVAL R7 3
      67 [-]: LOADN R8 2   
      68 [-]: CALL R7 1 1  
      69 [-]: LENGTH R8 R7 
      70 [-]: JUMPXEQKN R8 K16 L8 NOT [0]
      71 [-]: GETUPVAL R8 3
      72 [-]: LOADN R9 3   
      73 [-]: CALL R8 1 1  
      74 [-]: MOVE R7 R8   
L 8:  75 [-]: LOADN R10 1  
      76 [-]: LENGTH R8 R7 
      77 [-]: LOADN R9 1   
      78 [-]: FORNPREP R8 L10
L 9:  79 [-]: GETTABLE R11 R7 R10
      80 [-]: LOADN R13 0  
      81 [-]: NAMECALL R11 R11 K17 [0x05EEB9DB]
      82 [-]: CALL R11 2 0 
      83 [-]: FORNLOOP R8 L9
L10:  84 [-]: GETUPVAL R8 1
      85 [-]: NAMECALL R6 R0 K9 [0x0EB34C69]
      86 [-]: CALL R6 2 1  
      87 [-]: JUMPXEQKN R6 K18 L11 [4]
      88 [-]: GETIMPORT R6 21 [nil]
      89 [-]: JUMPIFNOT R6 L12
L11:  90 [-]: RETURN R0 0  
L12:  91 [-]: GETIMPORT R6 23 [nil]
      92 [-]: LOADK R7 K24 [0.10000000000000001]
      93 [-]: CALL R6 1 0  
      94 [-]: GETUPVAL R8 2
      95 [-]: NAMECALL R6 R0 K9 [0x0EB34C69]
      96 [-]: CALL R6 2 1  
      97 [-]: MOVE R5 R6   
      98 [-]: JUMPBACK L4  
L13:  99 [-]: NAMECALL R6 R4 K25 [0x2B54251B]
     100 [-]: CALL R6 1 1  
     101 [-]: NAMECALL R7 R6 K26 [0xCB3851B8]
     102 [-]: CALL R7 1 1  
     103 [-]: GETUPVAL R10 5
     104 [-]: NAMECALL R8 R0 K9 [0x0EB34C69]
     105 [-]: CALL R8 2 1  
     106 [-]: LOADN R9 0   
     107 [-]: JUMPIFNOTLT R9 R8 L25
     108 [-]: GETUPVAL R10 6
     109 [-]: NAMECALL R8 R0 K9 [0x0EB34C69]
     110 [-]: CALL R8 2 1  
     111 [-]: LOADN R11 90 
     112 [-]: SUB R10 R11 R8
     113 [-]: FASTCALL2K 18 R10 K16 L14 [0]
     114 [-]: LOADK R11 K16 [0]
     115 [-]: GETIMPORT R9 29 [nil]
     116 [-]: CALL R9 2 1  
L14: 117 [-]: MOVE R10 R9  
L15: 118 [-]: LOADN R11 30 
     119 [-]: JUMPIFNOTLT R11 R10 L19
     120 [-]: SUBK R12 R10 K30 [0.5]
     121 [-]: FASTCALL2K 18 R12 K16 L16 [0]
     122 [-]: LOADK R13 K16 [0]
     123 [-]: GETIMPORT R11 29 [nil]
     124 [-]: CALL R11 2 1 
L16: 125 [-]: MOVE R10 R11 
     126 [-]: GETUPVAL R13 1
     127 [-]: NAMECALL R11 R0 K9 [0x0EB34C69]
     128 [-]: CALL R11 2 1 
     129 [-]: JUMPXEQKN R11 K18 L17 [4]
     130 [-]: GETIMPORT R11 21 [nil]
     131 [-]: JUMPIFNOT R11 L18
L17: 132 [-]: RETURN R0 0  
L18: 133 [-]: ADDK R8 R8 K30 [0.5]
     134 [-]: GETUPVAL R13 6
     135 [-]: MOVE R14 R8  
     136 [-]: NAMECALL R11 R0 K31 [0x751F061D]
     137 [-]: CALL R11 3 0 
     138 [-]: GETIMPORT R11 23 [nil]
     139 [-]: LOADK R12 K30 [0.5]
     140 [-]: CALL R11 1 0 
     141 [-]: JUMPBACK L15 
L19: 142 [-]: LOADN R11 0  
     143 [-]: JUMPIFNOTLT R11 R9 L20
     144 [-]: GETUPVAL R12 7
     145 [-]: GETTABLEKS R11 R12 K32 [0x9742B85B]
     146 [-]: GETIMPORT R12 34 [nil]
     147 [-]: GETIMPORT R13 12 [nil]
     148 [-]: LOADK R14 K35 ["AdvanceWarningVO"]
     149 [-]: CALL R13 1 -1
     150 [-]: CALL R11 -1 0
     151 [-]: GETIMPORT R13 37 [nil]
     152 [-]: GETIMPORT R14 39 [nil]
     153 [-]: GETIMPORT R15 41 [nil]
     154 [-]: MOVE R16 R7  
     155 [-]: NAMECALL R11 R6 K42 [0x47901F07]
     156 [-]: CALL R11 5 0 
     157 [-]: GETUPVAL R13 8
     158 [-]: LOADN R14 1  
     159 [-]: NAMECALL R11 R0 K31 [0x751F061D]
     160 [-]: CALL R11 3 0 
L20: 161 [-]: LOADN R12 30 
     162 [-]: FASTCALL2 19 R12 R9 L21
     163 [-]: MOVE R13 R9  
     164 [-]: GETIMPORT R11 44 [nil]
     165 [-]: CALL R11 2 1 
L21: 166 [-]: LOADN R12 0  
     167 [-]: JUMPIFNOTLT R12 R11 L25
     168 [-]: SUBK R13 R11 K30 [0.5]
     169 [-]: FASTCALL2K 18 R13 K16 L22 [0]
     170 [-]: LOADK R14 K16 [0]
     171 [-]: GETIMPORT R12 29 [nil]
     172 [-]: CALL R12 2 1 
L22: 173 [-]: MOVE R11 R12 
     174 [-]: GETUPVAL R14 1
     175 [-]: NAMECALL R12 R0 K9 [0x0EB34C69]
     176 [-]: CALL R12 2 1 
     177 [-]: JUMPXEQKN R12 K18 L23 [4]
     178 [-]: GETIMPORT R12 21 [nil]
     179 [-]: JUMPIFNOT R12 L24
L23: 180 [-]: RETURN R0 0  
L24: 181 [-]: ADDK R8 R8 K30 [0.5]
     182 [-]: GETUPVAL R14 6
     183 [-]: MOVE R15 R8  
     184 [-]: NAMECALL R12 R0 K31 [0x751F061D]
     185 [-]: CALL R12 3 0 
     186 [-]: GETIMPORT R12 23 [nil]
     187 [-]: LOADK R13 K30 [0.5]
     188 [-]: CALL R12 1 0 
     189 [-]: JUMPBACK L21 
L25: 190 [-]: GETUPVAL R10 8
     191 [-]: LOADN R11 0  
     192 [-]: NAMECALL R8 R0 K31 [0x751F061D]
     193 [-]: CALL R8 3 0  
     194 [-]: GETUPVAL R10 6
     195 [-]: LOADN R11 0  
     196 [-]: NAMECALL R8 R0 K31 [0x751F061D]
     197 [-]: CALL R8 3 0  
     198 [-]: GETUPVAL R10 1
     199 [-]: NAMECALL R8 R0 K9 [0x0EB34C69]
     200 [-]: CALL R8 2 1  
     201 [-]: JUMPXEQKN R8 K18 L26 [4]
     202 [-]: GETIMPORT R8 21 [nil]
     203 [-]: JUMPIFNOT R8 L27
L26: 204 [-]: RETURN R0 0  
L27: 205 [-]: LOADK R10 K45 ["Execute"]
     206 [-]: NAMECALL R8 R4 K46 [0x8EB2112D]
     207 [-]: CALL R8 2 0  
     208 [-]: JUMPIFNOT R3 L28
     209 [-]: GETUPVAL R10 9
     210 [-]: LOADN R11 1  
     211 [-]: NAMECALL R8 R0 K31 [0x751F061D]
     212 [-]: CALL R8 3 0  
     213 [-]: GETIMPORT R8 47 [nil]
     214 [-]: SETTABLEKS R4 R8 K48 ["gMiniBossArtifactSpawn"]
L28: 215 [-]: GETIMPORT R8 23 [nil]
     216 [-]: LOADN R9 0   
     217 [-]: CALL R8 1 0  
     218 [-]: JUMPBACK L3  
L29: 219 [-]: RETURN R0 0  


; Name:            
; Defined at line: 1270
; #Upvalues:       1
; #Parameters:     0
; Is_vararg:       0
; Max Stack Size:  1

       0 [-]: GETUPVAL R0 0
       1 [-]: CALL R0 0 0  
       2 [-]: RETURN R0 0  


; Name:            
; Defined at line: 1274
; #Upvalues:       7
; #Parameters:     1
; Is_vararg:       0
; Max Stack Size:  18

       0 [-]: GETIMPORT R1 1 [nil]
       1 [-]: GETIMPORT R2 3 [nil]
       2 [-]: NAMECALL R2 R2 K4 [0x29EF273D]
       3 [-]: CALL R2 1 1  
       4 [-]: NAMECALL R3 R2 K5 [0x66905CB0]
       5 [-]: CALL R3 1 1  
       6 [-]: NAMECALL R4 R0 K6 [0x2B54251B]
       7 [-]: CALL R4 1 1  
       8 [-]: LOADK R7 K7 ["Show"]
       9 [-]: NAMECALL R5 R4 K8 [0x8EB2112D]
      10 [-]: CALL R5 2 0  
      11 [-]: GETUPVAL R7 0
      12 [-]: NAMECALL R5 R1 K9 [0x0EB34C69]
      13 [-]: CALL R5 2 1  
      14 [-]: ADDK R5 R5 K10 [1]
      15 [-]: GETUPVAL R8 0
      16 [-]: MOVE R9 R5   
      17 [-]: NAMECALL R6 R1 K11 [0x751F061D]
      18 [-]: CALL R6 3 0  
      19 [-]: GETUPVAL R8 1
      20 [-]: NAMECALL R6 R1 K9 [0x0EB34C69]
      21 [-]: CALL R6 2 1  
      22 [-]: GETUPVAL R9 1
      23 [-]: ADDK R10 R6 K10 [1]
      24 [-]: NAMECALL R7 R1 K11 [0x751F061D]
      25 [-]: CALL R7 3 0  
      26 [-]: GETIMPORT R9 13 [nil]
      27 [-]: GETIMPORT R10 15 [nil]
      28 [-]: GETUPVAL R11 2
      29 [-]: NAMECALL R7 R4 K16 [0x47901F07]
      30 [-]: CALL R7 4 0  
      31 [-]: LOADN R9 1   
      32 [-]: NAMECALL R7 R0 K17 [0x05EEB9DB]
      33 [-]: CALL R7 2 0  
      34 [-]: GETIMPORT R8 1 [nil]
      35 [-]: NAMECALL R8 R8 K18 [0xEF893AEC]
      36 [-]: CALL R8 1 1  
      37 [-]: GETTABLEKS R9 R8 K19 ["goalTag"]
      38 [-]: GETIMPORT R10 21 [nil]
      39 [-]: LOADK R11 K22 ["KuvaSurvival"]
      40 [-]: CALL R10 1 1 
      41 [-]: JUMPIFNOTEQ R9 R10 L0
      42 [-]: LOADB R7 1   
      43 [-]: JUMP L1
     
L 0:  44 [-]: LOADB R7 0   
L 1:  45 [-]: JUMPIFNOT R7 L2
      46 [-]: GETUPVAL R10 3
      47 [-]: NAMECALL R8 R1 K9 [0x0EB34C69]
      48 [-]: CALL R8 2 1  
      49 [-]: JUMPXEQKN R8 K23 L3 NOT [0]
      50 [-]: MOVE R11 R4  
      51 [-]: NAMECALL R9 R3 K24 [0xE2871589]
      52 [-]: CALL R9 2 0  
      53 [-]: JUMP L3
     
L 2:  54 [-]: MOVE R10 R4  
      55 [-]: NAMECALL R8 R3 K24 [0xE2871589]
      56 [-]: CALL R8 2 0  
L 3:  57 [-]: GETIMPORT R10 26 [nil]
      58 [-]: GETIMPORT R11 15 [nil]
      59 [-]: GETIMPORT R12 28 [nil]
      60 [-]: NAMECALL R13 R4 K29 [0xCB3851B8]
      61 [-]: CALL R13 1 -1
      62 [-]: NAMECALL R8 R4 K16 [0x47901F07]
      63 [-]: CALL R8 -1 0 
      64 [-]: GETUPVAL R10 4
      65 [-]: NAMECALL R8 R1 K9 [0x0EB34C69]
      66 [-]: CALL R8 2 1  
      67 [-]: LOADN R9 2   
      68 [-]: JUMPIFNOTLT R8 R9 L5
      69 [-]: JUMPIF R7 L4 
      70 [-]: GETUPVAL R10 5
      71 [-]: GETTABLEKS R9 R10 K30 [0x9742B85B]
      72 [-]: GETIMPORT R10 33 [nil]
      73 [-]: GETIMPORT R11 21 [nil]
      74 [-]: LOADK R12 K34 ["SurvivalFirstDrop"]
      75 [-]: CALL R11 1 -1
      76 [-]: CALL R9 -1 0 
L 4:  77 [-]: GETUPVAL R11 4
      78 [-]: LOADN R12 2  
      79 [-]: NAMECALL R9 R1 K11 [0x751F061D]
      80 [-]: CALL R9 3 0  
      81 [-]: JUMP L6
     
L 5:  82 [-]: GETUPVAL R10 5
      83 [-]: GETTABLEKS R9 R10 K30 [0x9742B85B]
      84 [-]: GETIMPORT R10 33 [nil]
      85 [-]: GETIMPORT R11 21 [nil]
      86 [-]: LOADK R12 K35 ["SurvivalDrop"]
      87 [-]: CALL R11 1 -1
      88 [-]: CALL R9 -1 0 
L 6:  89 [-]: GETIMPORT R11 37 [nil]
      90 [-]: NAMECALL R9 R4 K38 [0xC9F6A7D7]
      91 [-]: CALL R9 2 1  
      92 [-]: FASTCALL1 62 R9 L7
      93 [-]: MOVE R11 R9  
      94 [-]: GETIMPORT R10 40 [nil]
      95 [-]: CALL R10 1 1 
L 7:  96 [-]: JUMPIF R10 L8
      97 [-]: NAMECALL R10 R9 K41 [0xA2880940]
      98 [-]: CALL R10 1 0 
L 8:  99 [-]: GETUPVAL R12 6
     100 [-]: NAMECALL R10 R1 K42 [0xFFDDF768]
     101 [-]: CALL R10 2 1 
     102 [-]: GETIMPORT R11 44 [nil]
     103 [-]: LOADK R13 K45 ["Survival: New capsule "]
     104 [-]: MOVE R14 R5  
     105 [-]: LOADK R15 K46 [" became available at "]
     106 [-]: MOVE R16 R10 
     107 [-]: LOADK R17 K47 [" seconds."]
     108 [-]: CONCAT R12 R13 R17
     109 [-]: CALL R11 1 0 
     110 [-]: RETURN R0 0  


; Name:            
; Defined at line: 1327
; #Upvalues:       8
; #Parameters:     2
; Is_vararg:       0
; Max Stack Size:  17

       0 [-]: NAMECALL R2 R0 K0 [0x2B54251B]
       1 [-]: CALL R2 1 1  
       2 [-]: FASTCALL1 62 R2 L0
       3 [-]: MOVE R4 R2   
       4 [-]: GETIMPORT R3 2 [nil]
       5 [-]: CALL R3 1 1  
L 0:   6 [-]: JUMPIF R3 L4 
       7 [-]: GETIMPORT R5 4 [nil]
       8 [-]: NAMECALL R3 R2 K5 [0xC1595BD5]
       9 [-]: CALL R3 2 1  
      10 [-]: FASTCALL1 62 R3 L1
      11 [-]: MOVE R5 R3   
      12 [-]: GETIMPORT R4 2 [nil]
      13 [-]: CALL R4 1 1  
L 1:  14 [-]: JUMPIF R4 L3 
      15 [-]: GETTABLEN R5 R3 1
      16 [-]: FASTCALL1 62 R5 L2
      17 [-]: GETIMPORT R4 2 [nil]
      18 [-]: CALL R4 1 1  
L 2:  19 [-]: JUMPIF R4 L3 
      20 [-]: GETTABLEN R4 R3 1
      21 [-]: NAMECALL R4 R4 K6 [0xA2880940]
      22 [-]: CALL R4 1 0  
L 3:  23 [-]: LOADK R6 K7 ["Hide"]
      24 [-]: NAMECALL R4 R2 K8 [0x8EB2112D]
      25 [-]: CALL R4 2 0  
      26 [-]: GETIMPORT R6 10 [nil]
      27 [-]: GETIMPORT R7 12 [nil]
      28 [-]: GETIMPORT R8 14 [nil]
      29 [-]: NAMECALL R9 R2 K15 [0xCB3851B8]
      30 [-]: CALL R9 1 -1 
      31 [-]: NAMECALL R4 R2 K16 [0x47901F07]
      32 [-]: CALL R4 -1 0 
      33 [-]: GETIMPORT R6 18 [nil]
      34 [-]: GETIMPORT R7 12 [nil]
      35 [-]: GETIMPORT R8 14 [nil]
      36 [-]: NAMECALL R9 R2 K15 [0xCB3851B8]
      37 [-]: CALL R9 1 -1 
      38 [-]: NAMECALL R4 R2 K16 [0x47901F07]
      39 [-]: CALL R4 -1 0 
L 4:  40 [-]: GETIMPORT R3 20 [nil]
      41 [-]: NAMECALL R3 R3 K21 [0x18D05D30]
      42 [-]: CALL R3 1 1  
      43 [-]: JUMPIF R3 L5 
      44 [-]: RETURN R0 0  
L 5:  45 [-]: GETIMPORT R3 23 [nil]
      46 [-]: GETUPVAL R6 0
      47 [-]: NAMECALL R4 R3 K24 [0x0EB34C69]
      48 [-]: CALL R4 2 1  
      49 [-]: LOADN R5 0   
      50 [-]: JUMPIFNOTLE R4 R5 L6
      51 [-]: JUMP L8
     
L 6:  52 [-]: ADDK R5 R4 K25 [45]
      53 [-]: LOADN R6 150 
      54 [-]: JUMPIFNOTLT R6 R5 L7
      55 [-]: LOADN R5 150 
L 7:  56 [-]: GETUPVAL R8 0
      57 [-]: MOVE R9 R5   
      58 [-]: NAMECALL R6 R3 K26 [0x751F061D]
      59 [-]: CALL R6 3 0  
L 8:  60 [-]: GETIMPORT R3 23 [nil]
      61 [-]: GETUPVAL R6 1
      62 [-]: NAMECALL R4 R3 K24 [0x0EB34C69]
      63 [-]: CALL R4 2 1  
      64 [-]: GETUPVAL R5 2
      65 [-]: LOADN R6 3   
      66 [-]: CALL R5 1 1  
      67 [-]: LOADN R8 1   
      68 [-]: LENGTH R6 R5 
      69 [-]: LOADN R7 1   
      70 [-]: FORNPREP R6 L10
L 9:  71 [-]: GETTABLE R9 R5 R8
      72 [-]: LOADN R11 2  
      73 [-]: NAMECALL R9 R9 K27 [0x05EEB9DB]
      74 [-]: CALL R9 2 0  
      75 [-]: FORNLOOP R6 L9
L10:  76 [-]: FASTCALL1 62 R2 L11
      77 [-]: MOVE R7 R2   
      78 [-]: GETIMPORT R6 2 [nil]
      79 [-]: CALL R6 1 1  
L11:  80 [-]: JUMPIF R6 L14
      81 [-]: GETIMPORT R8 29 [nil]
      82 [-]: NAMECALL R6 R2 K5 [0xC1595BD5]
      83 [-]: CALL R6 2 1  
      84 [-]: FASTCALL1 62 R6 L12
      85 [-]: MOVE R8 R6   
      86 [-]: GETIMPORT R7 2 [nil]
      87 [-]: CALL R7 1 1  
L12:  88 [-]: JUMPIF R7 L14
      89 [-]: GETTABLEN R8 R6 1
      90 [-]: FASTCALL1 62 R8 L13
      91 [-]: GETIMPORT R7 2 [nil]
      92 [-]: CALL R7 1 1  
L13:  93 [-]: JUMPIF R7 L14
      94 [-]: GETTABLEN R7 R6 1
      95 [-]: LOADN R9 3   
      96 [-]: NAMECALL R7 R7 K27 [0x05EEB9DB]
      97 [-]: CALL R7 2 0  
L14:  98 [-]: ADDK R4 R4 K30 [1]
      99 [-]: GETUPVAL R8 1
     100 [-]: MOVE R9 R4   
     101 [-]: NAMECALL R6 R3 K26 [0x751F061D]
     102 [-]: CALL R6 3 0  
     103 [-]: GETUPVAL R8 3
     104 [-]: NAMECALL R6 R3 K24 [0x0EB34C69]
     105 [-]: CALL R6 2 1  
     106 [-]: SUBK R8 R6 K30 [1]
     107 [-]: FASTCALL2K 18 R8 K31 L15 [0]
     108 [-]: LOADK R9 K31 [0]
     109 [-]: GETIMPORT R7 34 [nil]
     110 [-]: CALL R7 2 1  
L15: 111 [-]: MOVE R6 R7   
     112 [-]: GETUPVAL R9 3
     113 [-]: MOVE R10 R6  
     114 [-]: NAMECALL R7 R3 K26 [0x751F061D]
     115 [-]: CALL R7 3 0  
     116 [-]: GETUPVAL R9 4
     117 [-]: NAMECALL R7 R3 K24 [0x0EB34C69]
     118 [-]: CALL R7 2 1  
     119 [-]: SUBK R9 R7 K30 [1]
     120 [-]: FASTCALL2K 18 R9 K31 L16 [0]
     121 [-]: LOADK R10 K31 [0]
     122 [-]: GETIMPORT R8 34 [nil]
     123 [-]: CALL R8 2 1  
L16: 124 [-]: MOVE R7 R8   
     125 [-]: GETUPVAL R10 4
     126 [-]: MOVE R11 R7  
     127 [-]: NAMECALL R8 R3 K26 [0x751F061D]
     128 [-]: CALL R8 3 0  
     129 [-]: GETUPVAL R10 5
     130 [-]: NAMECALL R8 R3 K24 [0x0EB34C69]
     131 [-]: CALL R8 2 1  
     132 [-]: JUMPXEQKN R8 K35 L17 [4]
     133 [-]: GETUPVAL R10 6
     134 [-]: GETTABLEKS R9 R10 K36 [0x9742B85B]
     135 [-]: GETIMPORT R10 39 [nil]
     136 [-]: GETIMPORT R11 41 [nil]
     137 [-]: LOADK R12 K42 ["SurvivalDropActivated"]
     138 [-]: CALL R11 1 -1
     139 [-]: CALL R9 -1 0 
L17: 140 [-]: GETIMPORT R9 23 [nil]
     141 [-]: GETUPVAL R11 7
     142 [-]: NAMECALL R9 R9 K43 [0xFFDDF768]
     143 [-]: CALL R9 2 1  
     144 [-]: GETIMPORT R10 45 [nil]
     145 [-]: LOADK R12 K46 ["Survival: Capsule "]
     146 [-]: MOVE R13 R4  
     147 [-]: LOADK R14 K47 [" activated at "]
     148 [-]: MOVE R15 R9  
     149 [-]: LOADK R16 K48 [" seconds."]
     150 [-]: CONCAT R11 R12 R16
     151 [-]: CALL R10 1 0 
     152 [-]: GETIMPORT R10 49 [nil]
     153 [-]: LOADB R11 1  
     154 [-]: SETTABLEKS R11 R10 K50 ["gUpdateElementalLayer"]
     155 [-]: RETURN R0 0  


; Name:            
; Defined at line: 1388
; #Upvalues:       4
; #Parameters:     1
; Is_vararg:       0
; Max Stack Size:  27

       0 [-]: GETIMPORT R3 1 [nil]
       1 [-]: NAMECALL R1 R0 K2 [0xC9F6A7D7]
       2 [-]: CALL R1 2 1  
       3 [-]: GETIMPORT R4 4 [nil]
       4 [-]: NAMECALL R2 R0 K2 [0xC9F6A7D7]
       5 [-]: CALL R2 2 1  
       6 [-]: NAMECALL R3 R0 K5 [0xD1586535]
       7 [-]: CALL R3 1 1  
       8 [-]: NAMECALL R4 R0 K6 [0xCB3851B8]
       9 [-]: CALL R4 1 1  
      10 [-]: GETIMPORT R5 8 [nil]
      11 [-]: NAMECALL R5 R5 K9 [0x29EF273D]
      12 [-]: CALL R5 1 1  
      13 [-]: NAMECALL R5 R5 K10 [0x66905CB0]
      14 [-]: CALL R5 1 1  
      15 [-]: GETIMPORT R6 12 [nil]
      16 [-]: FASTCALL1 62 R6 L0
      17 [-]: MOVE R8 R6   
      18 [-]: GETIMPORT R7 14 [nil]
      19 [-]: CALL R7 1 1  
L 0:  20 [-]: JUMPIFNOT R7 L1
      21 [-]: RETURN R0 0  
L 1:  22 [-]: GETUPVAL R9 0
      23 [-]: NAMECALL R7 R6 K15 [0x0EB34C69]
      24 [-]: CALL R7 2 1  
L 2:  25 [-]: LOADN R8 4   
      26 [-]: JUMPIFNOTLT R7 R8 L25
      27 [-]: FASTCALL1 62 R6 L3
      28 [-]: MOVE R9 R6   
      29 [-]: GETIMPORT R8 14 [nil]
      30 [-]: CALL R8 1 1  
L 3:  31 [-]: JUMPIFNOT R8 L4
      32 [-]: GETIMPORT R6 12 [nil]
L 4:  33 [-]: FASTCALL1 62 R6 L5
      34 [-]: MOVE R9 R6   
      35 [-]: GETIMPORT R8 14 [nil]
      36 [-]: CALL R8 1 1  
L 5:  37 [-]: JUMPIF R8 L24
      38 [-]: GETIMPORT R8 8 [nil]
      39 [-]: NAMECALL R8 R8 K16 [0x18D05D30]
      40 [-]: CALL R8 1 1  
      41 [-]: JUMPIFNOT R8 L24
      42 [-]: GETUPVAL R10 0
      43 [-]: NAMECALL R8 R6 K15 [0x0EB34C69]
      44 [-]: CALL R8 2 1  
      45 [-]: MOVE R7 R8   
      46 [-]: GETUPVAL R10 1
      47 [-]: NAMECALL R8 R6 K15 [0x0EB34C69]
      48 [-]: CALL R8 2 1  
      49 [-]: JUMPXEQKN R8 K17 L7 NOT [1]
      50 [-]: GETIMPORT R9 20 [nil]
      51 [-]: FASTCALL1 62 R9 L6
      52 [-]: GETIMPORT R8 14 [nil]
      53 [-]: CALL R8 1 1  
L 6:  54 [-]: JUMPIFNOT R8 L7
      55 [-]: GETIMPORT R8 21 [nil]
      56 [-]: SETTABLEKS R0 R8 K19 ["gMiniBossArtifactSpawn"]
L 7:  57 [-]: LOADN R8 0   
      58 [-]: GETIMPORT R11 4 [nil]
      59 [-]: NAMECALL R9 R0 K2 [0xC9F6A7D7]
      60 [-]: CALL R9 2 1  
      61 [-]: MOVE R2 R9   
      62 [-]: FASTCALL1 62 R2 L8
      63 [-]: MOVE R10 R2  
      64 [-]: GETIMPORT R9 14 [nil]
      65 [-]: CALL R9 1 1  
L 8:  66 [-]: JUMPIF R9 L9 
      67 [-]: NAMECALL R9 R2 K22 [0x9CBE2EA2]
      68 [-]: CALL R9 1 1  
      69 [-]: MOVE R8 R9   
L 9:  70 [-]: GETUPVAL R11 2
      71 [-]: NAMECALL R9 R6 K15 [0x0EB34C69]
      72 [-]: CALL R9 2 1  
      73 [-]: LOADN R10 3  
      74 [-]: JUMPIFNOTLT R9 R10 L22
      75 [-]: FASTCALL1 62 R1 L10
      76 [-]: MOVE R11 R1  
      77 [-]: GETIMPORT R10 14 [nil]
      78 [-]: CALL R10 1 1 
L10:  79 [-]: JUMPIF R10 L22
      80 [-]: NAMECALL R10 R1 K23 [0x53C3399F]
      81 [-]: CALL R10 1 1 
      82 [-]: JUMPXEQKN R10 K17 L22 NOT [1]
      83 [-]: JUMPXEQKN R8 K24 L22 NOT [0]
      84 [-]: GETIMPORT R10 8 [nil]
      85 [-]: NAMECALL R10 R10 K25 [0x8B5B1F58]
      86 [-]: CALL R10 1 1 
      87 [-]: GETIMPORT R11 27 [nil]
      88 [-]: MOVE R12 R10 
      89 [-]: CALL R11 1 3 
      90 [-]: FORGPREP_INEXT R11 L21
L11:  91 [-]: GETIMPORT R18 29 [nil]
      92 [-]: NAMECALL R16 R15 K30 [0x0866B4BD]
      93 [-]: CALL R16 2 1 
      94 [-]: JUMPIFNOT R16 L21
      95 [-]: MOVE R18 R3  
      96 [-]: NAMECALL R16 R15 K31 [0x1F420A3A]
      97 [-]: CALL R16 2 1 
      98 [-]: LOADN R17 3  
      99 [-]: JUMPIFNOTLT R16 R17 L21
     100 [-]: GETIMPORT R18 29 [nil]
     101 [-]: NAMECALL R16 R15 K32 [0x35B09371]
     102 [-]: CALL R16 2 0 
     103 [-]: GETUPVAL R18 2
     104 [-]: LOADN R19 0  
     105 [-]: NAMECALL R16 R6 K15 [0x0EB34C69]
     106 [-]: CALL R16 3 1 
     107 [-]: GETUPVAL R19 2
     108 [-]: ADDK R20 R16 K17 [1]
     109 [-]: NAMECALL R17 R6 K33 [0x751F061D]
     110 [-]: CALL R17 3 0 
     111 [-]: GETUPVAL R19 3
     112 [-]: NAMECALL R17 R6 K15 [0x0EB34C69]
     113 [-]: CALL R17 2 1 
     114 [-]: GETUPVAL R20 3
     115 [-]: SUBK R21 R17 K17 [1]
     116 [-]: NAMECALL R18 R6 K33 [0x751F061D]
     117 [-]: CALL R18 3 0 
     118 [-]: LOADN R20 4  
     119 [-]: NAMECALL R18 R1 K34 [0x05EEB9DB]
     120 [-]: CALL R18 2 0 
     121 [-]: GETIMPORT R20 36 [nil]
     122 [-]: NAMECALL R18 R0 K2 [0xC9F6A7D7]
     123 [-]: CALL R18 2 1 
     124 [-]: FASTCALL1 62 R18 L12
     125 [-]: MOVE R20 R18 
     126 [-]: GETIMPORT R19 14 [nil]
     127 [-]: CALL R19 1 1 
L12: 128 [-]: JUMPIF R19 L13
     129 [-]: NAMECALL R19 R18 K37 [0xA2880940]
     130 [-]: CALL R19 1 0 
L13: 131 [-]: LOADK R21 K38 ["Hide"]
     132 [-]: NAMECALL R19 R0 K39 [0x8EB2112D]
     133 [-]: CALL R19 2 0 
     134 [-]: GETIMPORT R21 41 [nil]
     135 [-]: NAMECALL R19 R0 K2 [0xC9F6A7D7]
     136 [-]: CALL R19 2 1 
     137 [-]: FASTCALL1 62 R19 L14
     138 [-]: MOVE R21 R19 
     139 [-]: GETIMPORT R20 14 [nil]
     140 [-]: CALL R20 1 1 
L14: 141 [-]: JUMPIF R20 L15
     142 [-]: NAMECALL R20 R19 K37 [0xA2880940]
     143 [-]: CALL R20 1 0 
L15: 144 [-]: GETIMPORT R22 43 [nil]
     145 [-]: MOVE R23 R3  
     146 [-]: MOVE R24 R4  
     147 [-]: GETIMPORT R25 45 [nil]
     148 [-]: LOADK R26 K46 ["KuvaTowerTeam"]
     149 [-]: CALL R25 1 -1
     150 [-]: NAMECALL R20 R5 K47 [0x3ACD2A13]
     151 [-]: CALL R20 -1 1
L16: 152 [-]: FASTCALL1 62 R20 L17
     153 [-]: MOVE R22 R20 
     154 [-]: GETIMPORT R21 14 [nil]
     155 [-]: CALL R21 1 1 
L17: 156 [-]: JUMPIF R21 L18
     157 [-]: GETIMPORT R21 49 [nil]
     158 [-]: LOADN R22 0  
     159 [-]: CALL R21 1 0 
     160 [-]: JUMPBACK L16 
L18: 161 [-]: LOADN R23 3  
     162 [-]: NAMECALL R21 R1 K34 [0x05EEB9DB]
     163 [-]: CALL R21 2 0 
     164 [-]: LOADN R21 0  
L19: 165 [-]: LOADN R22 20 
     166 [-]: JUMPIFNOTLT R21 R22 L20
     167 [-]: GETIMPORT R22 51 [nil]
     168 [-]: CALL R22 0 1 
     169 [-]: ADD R21 R21 R22
     170 [-]: GETIMPORT R22 49 [nil]
     171 [-]: LOADN R23 0  
     172 [-]: CALL R22 1 0 
     173 [-]: JUMPBACK L19 
L20: 174 [-]: LOADN R24 2  
     175 [-]: NAMECALL R22 R1 K34 [0x05EEB9DB]
     176 [-]: CALL R22 2 0 
     177 [-]: JUMP L24
    
L21: 178 [-]: FORGLOOP R11 L11 2 [inext]
     179 [-]: JUMP L24
    
L22: 180 [-]: FASTCALL1 62 R1 L23
     181 [-]: MOVE R11 R1  
     182 [-]: GETIMPORT R10 14 [nil]
     183 [-]: CALL R10 1 1 
L23: 184 [-]: JUMPIFNOT R10 L24
     185 [-]: GETIMPORT R12 1 [nil]
     186 [-]: NAMECALL R10 R0 K2 [0xC9F6A7D7]
     187 [-]: CALL R10 2 1 
     188 [-]: MOVE R1 R10  
L24: 189 [-]: GETIMPORT R8 49 [nil]
     190 [-]: LOADN R9 0   
     191 [-]: CALL R8 1 0  
     192 [-]: JUMPBACK L2  
L25: 193 [-]: RETURN R0 0  


; Name:            
; Defined at line: 1472
; #Upvalues:       12
; #Parameters:     1
; Is_vararg:       0
; Max Stack Size:  19

       0 [-]: GETIMPORT R1 1 [nil]
       1 [-]: LOADN R2 0   
       2 [-]: CALL R1 1 0  
       3 [-]: GETIMPORT R1 3 [nil]
       4 [-]: GETIMPORT R2 5 [nil]
       5 [-]: NAMECALL R2 R2 K6 [0x29EF273D]
       6 [-]: CALL R2 1 1  
       7 [-]: NAMECALL R2 R2 K7 [0x66905CB0]
       8 [-]: CALL R2 1 1  
       9 [-]: NAMECALL R3 R0 K8 [0xD1586535]
      10 [-]: CALL R3 1 1  
      11 [-]: NAMECALL R4 R0 K9 [0xCB3851B8]
      12 [-]: CALL R4 1 1  
      13 [-]: NAMECALL R5 R2 K10 [0xCEA36880]
      14 [-]: CALL R5 1 1  
      15 [-]: LOADN R7 500 
      16 [-]: POWK R8 R5 K11 [0.59999999999999998]
      17 [-]: MUL R6 R7 R8 
      18 [-]: MODK R7 R6 K12 [100]
      19 [-]: SUB R6 R6 R7 
      20 [-]: NAMECALL R7 R0 K13 [0xD2715720]
      21 [-]: CALL R7 1 1  
      22 [-]: JUMPIFNOTLT R6 R7 L0
      23 [-]: MOVE R10 R6  
      24 [-]: LOADB R11 0  
      25 [-]: NAMECALL R8 R0 K14 [0x014DB014]
      26 [-]: CALL R8 3 0  
L 0:  27 [-]: MOVE R10 R6  
      28 [-]: LOADB R11 1  
      29 [-]: NAMECALL R8 R0 K15 [0xA31BA7EE]
      30 [-]: CALL R8 3 0  
      31 [-]: GETIMPORT R8 5 [nil]
      32 [-]: GETUPVAL R10 0
      33 [-]: MOVE R11 R3  
      34 [-]: LOADN R12 5  
      35 [-]: NAMECALL R8 R8 K16 [0x4E5939A5]
      36 [-]: CALL R8 4 1  
      37 [-]: FASTCALL1 62 R8 L1
      38 [-]: MOVE R10 R8  
      39 [-]: GETIMPORT R9 18 [nil]
      40 [-]: CALL R9 1 1  
L 1:  41 [-]: JUMPIFNOT R9 L2
      42 [-]: RETURN R0 0  
L 2:  43 [-]: LOADB R11 1  
      44 [-]: NAMECALL R9 R8 K19 [0x383D2E7D]
      45 [-]: CALL R9 2 0  
      46 [-]: MOVE R11 R0  
      47 [-]: NAMECALL R9 R8 K20 [0x00F85B37]
      48 [-]: CALL R9 2 0  
      49 [-]: GETIMPORT R10 23 [nil]
      50 [-]: FASTCALL1 62 R10 L3
      51 [-]: GETIMPORT R9 18 [nil]
      52 [-]: CALL R9 1 1  
L 3:  53 [-]: JUMPIFNOT R9 L4
      54 [-]: GETIMPORT R9 24 [nil]
      55 [-]: NEWTABLE R10 0 3
      56 [-]: LOADN R11 0  
      57 [-]: LOADN R12 0  
      58 [-]: LOADN R13 0  
      59 [-]: SETLIST R10 R11 3 [1]
      60 [-]: SETTABLEKS R10 R9 K22 ["kuvaExtractorList"]
L 4:  61 [-]: LOADN R11 1  
      62 [-]: GETIMPORT R12 23 [nil]
      63 [-]: LENGTH R9 R12
      64 [-]: LOADN R10 1  
      65 [-]: FORNPREP R9 L7
L 5:  66 [-]: GETIMPORT R13 23 [nil]
      67 [-]: GETTABLE R12 R13 R11
      68 [-]: JUMPXEQKN R12 K25 L6 NOT [0]
      69 [-]: GETIMPORT R12 23 [nil]
      70 [-]: SETTABLE R8 R12 R11
      71 [-]: JUMP L7
     
L 6:  72 [-]: FORNLOOP R9 L5
L 7:  73 [-]: NAMECALL R9 R8 K26 [0x17DD42BB]
      74 [-]: CALL R9 1 1  
      75 [-]: MOVE R12 R0  
      76 [-]: NAMECALL R10 R2 K27 [0xE2871589]
      77 [-]: CALL R10 2 0 
      78 [-]: GETUPVAL R10 1
      79 [-]: LOADK R11 K28 ["/Lotus/Language/Objectives/KuvaTowerStarted"]
      80 [-]: CALL R10 1 0 
      81 [-]: GETUPVAL R11 2
      82 [-]: GETTABLEKS R10 R11 K29 [0x9742B85B]
      83 [-]: GETIMPORT R11 31 [nil]
      84 [-]: GETIMPORT R12 33 [nil]
      85 [-]: LOADK R13 K34 ["KuvaTowerStarted"]
      86 [-]: CALL R12 1 -1
      87 [-]: CALL R10 -1 0
      88 [-]: GETUPVAL R11 2
      89 [-]: GETTABLEKS R10 R11 K29 [0x9742B85B]
      90 [-]: GETIMPORT R11 31 [nil]
      91 [-]: GETIMPORT R12 33 [nil]
      92 [-]: LOADK R13 K35 ["KuvaTowerWarningIntro"]
      93 [-]: CALL R12 1 -1
      94 [-]: CALL R10 -1 0
      95 [-]: GETIMPORT R11 37 [nil]
      96 [-]: FASTCALL1 62 R11 L8
      97 [-]: GETIMPORT R10 18 [nil]
      98 [-]: CALL R10 1 1 
L 8:  99 [-]: JUMPIF R10 L9
     100 [-]: GETIMPORT R12 37 [nil]
     101 [-]: LOADB R13 0  
     102 [-]: LOADN R14 1  
     103 [-]: LOADB R15 1  
     104 [-]: NAMECALL R10 R0 K38 [0x659D451F]
     105 [-]: CALL R10 5 0 
L 9: 106 [-]: GETIMPORT R11 40 [nil]
     107 [-]: FASTCALL1 62 R11 L10
     108 [-]: GETIMPORT R10 18 [nil]
     109 [-]: CALL R10 1 1 
L10: 110 [-]: JUMPIF R10 L11
     111 [-]: GETIMPORT R12 40 [nil]
     112 [-]: LOADB R13 0  
     113 [-]: LOADN R14 1  
     114 [-]: LOADB R15 1  
     115 [-]: NAMECALL R10 R0 K38 [0x659D451F]
     116 [-]: CALL R10 5 0 
L11: 117 [-]: GETUPVAL R12 3
     118 [-]: NAMECALL R10 R1 K41 [0x0EB34C69]
     119 [-]: CALL R10 2 1 
L12: 120 [-]: FASTCALL1 62 R0 L13
     121 [-]: MOVE R12 R0  
     122 [-]: GETIMPORT R11 18 [nil]
     123 [-]: CALL R11 1 1 
L13: 124 [-]: JUMPIF R11 L14
     125 [-]: NAMECALL R11 R0 K42 [0x2047CFE7]
     126 [-]: CALL R11 1 1 
     127 [-]: JUMPIF R11 L14
     128 [-]: GETUPVAL R11 4
     129 [-]: JUMPIFNOTLE R9 R11 L14
     130 [-]: LOADN R11 4  
     131 [-]: JUMPIFNOTLT R10 R11 L14
     132 [-]: MOVE R13 R9  
     133 [-]: NAMECALL R11 R8 K43 [0x2F5F5657]
     134 [-]: CALL R11 2 0 
     135 [-]: ADDK R9 R9 K44 [0.5]
     136 [-]: GETIMPORT R11 1 [nil]
     137 [-]: LOADK R12 K44 [0.5]
     138 [-]: CALL R11 1 0 
     139 [-]: GETUPVAL R13 3
     140 [-]: NAMECALL R11 R1 K41 [0x0EB34C69]
     141 [-]: CALL R11 2 1 
     142 [-]: MOVE R10 R11 
     143 [-]: JUMPBACK L12 
L14: 144 [-]: FASTCALL1 62 R0 L15
     145 [-]: MOVE R12 R0  
     146 [-]: GETIMPORT R11 18 [nil]
     147 [-]: CALL R11 1 1 
L15: 148 [-]: JUMPIF R11 L16
     149 [-]: NAMECALL R11 R0 K42 [0x2047CFE7]
     150 [-]: CALL R11 1 1 
     151 [-]: JUMPIF R11 L16
     152 [-]: LOADN R11 4  
     153 [-]: JUMPIFNOTLE R11 R10 L21
L16: 154 [-]: LOADN R11 4  
     155 [-]: JUMPIFNOTLT R10 R11 L17
     156 [-]: GETUPVAL R11 1
     157 [-]: LOADK R12 K45 ["/Lotus/Language/Objectives/KuvaTowerDestroyed"]
     158 [-]: CALL R11 1 0 
     159 [-]: GETUPVAL R12 2
     160 [-]: GETTABLEKS R11 R12 K29 [0x9742B85B]
     161 [-]: GETIMPORT R12 31 [nil]
     162 [-]: GETIMPORT R13 33 [nil]
     163 [-]: LOADK R14 K46 ["KuvaTowerDestroyed"]
     164 [-]: CALL R13 1 -1
     165 [-]: CALL R11 -1 0
L17: 166 [-]: GETIMPORT R12 48 [nil]
     167 [-]: FASTCALL1 62 R12 L18
     168 [-]: GETIMPORT R11 18 [nil]
     169 [-]: CALL R11 1 1 
L18: 170 [-]: JUMPIF R11 L19
     171 [-]: GETIMPORT R11 5 [nil]
     172 [-]: GETIMPORT R13 48 [nil]
     173 [-]: MOVE R14 R3  
     174 [-]: MOVE R15 R4  
     175 [-]: NAMECALL R11 R11 K49 [0x05909209]
     176 [-]: CALL R11 4 0 
L19: 177 [-]: GETIMPORT R12 51 [nil]
     178 [-]: FASTCALL1 62 R12 L20
     179 [-]: GETIMPORT R11 18 [nil]
     180 [-]: CALL R11 1 1 
L20: 181 [-]: JUMPIF R11 L31
     182 [-]: GETIMPORT R13 51 [nil]
     183 [-]: LOADB R14 0  
     184 [-]: LOADN R15 1  
     185 [-]: LOADB R16 1  
     186 [-]: NAMECALL R11 R0 K38 [0x659D451F]
     187 [-]: CALL R11 5 0 
     188 [-]: JUMP L31
    
L21: 189 [-]: GETUPVAL R11 1
     190 [-]: LOADK R12 K52 ["/Lotus/Language/Objectives/KuvaTowerCompleted"]
     191 [-]: CALL R11 1 0 
     192 [-]: GETIMPORT R12 54 [nil]
     193 [-]: FASTCALL1 62 R12 L22
     194 [-]: GETIMPORT R11 18 [nil]
     195 [-]: CALL R11 1 1 
L22: 196 [-]: JUMPIF R11 L23
     197 [-]: GETIMPORT R11 5 [nil]
     198 [-]: GETIMPORT R13 54 [nil]
     199 [-]: MOVE R14 R3  
     200 [-]: MOVE R15 R4  
     201 [-]: NAMECALL R11 R11 K49 [0x05909209]
     202 [-]: CALL R11 4 0 
L23: 203 [-]: GETIMPORT R12 56 [nil]
     204 [-]: FASTCALL1 62 R12 L24
     205 [-]: GETIMPORT R11 18 [nil]
     206 [-]: CALL R11 1 1 
L24: 207 [-]: JUMPIF R11 L25
     208 [-]: GETIMPORT R13 56 [nil]
     209 [-]: LOADB R14 0  
     210 [-]: LOADN R15 1  
     211 [-]: LOADB R16 1  
     212 [-]: NAMECALL R11 R0 K38 [0x659D451F]
     213 [-]: CALL R11 5 0 
L25: 214 [-]: GETIMPORT R11 58 [nil]
     215 [-]: LOADN R12 200
     216 [-]: LOADN R13 1000
     217 [-]: GETIMPORT R16 60 [nil]
     218 [-]: FASTCALL1 62 R16 L26
     219 [-]: GETIMPORT R15 18 [nil]
     220 [-]: CALL R15 1 1 
L26: 221 [-]: JUMPIFNOT R15 L27
     222 [-]: GETIMPORT R15 5 [nil]
     223 [-]: NAMECALL R15 R15 K6 [0x29EF273D]
     224 [-]: CALL R15 1 1 
     225 [-]: NAMECALL R15 R15 K7 [0x66905CB0]
     226 [-]: CALL R15 1 1 
     227 [-]: GETIMPORT R16 24 [nil]
     228 [-]: NAMECALL R17 R15 K10 [0xCEA36880]
     229 [-]: CALL R17 1 1 
     230 [-]: SETTABLEKS R17 R16 K59 ["EndlessModeEnemyLevel"]
L27: 231 [-]: GETIMPORT R17 60 [nil]
     232 [-]: DIVK R16 R17 K61 [30]
     233 [-]: FASTCALL2K 19 R16 K62 L28 [1]
     234 [-]: LOADK R17 K62 [1]
     235 [-]: GETIMPORT R15 65 [nil]
     236 [-]: CALL R15 2 1 
L28: 237 [-]: MOVE R14 R15 
     238 [-]: CALL R11 3 1 
     239 [-]: GETUPVAL R13 5
     240 [-]: GETTABLEKS R12 R13 K66 [0x748E60B8]
     241 [-]: MOVE R13 R11 
     242 [-]: GETIMPORT R14 33 [nil]
     243 [-]: LOADK R15 K67 ["/Lotus/Language/Game/GenericObjectiveCompleteXp"]
     244 [-]: CALL R14 1 -1
     245 [-]: CALL R12 -1 0
     246 [-]: GETUPVAL R12 6
     247 [-]: GETUPVAL R13 7
     248 [-]: LOADN R14 200
     249 [-]: CALL R12 2 0 
     250 [-]: GETIMPORT R12 5 [nil]
     251 [-]: GETIMPORT R14 69 [nil]
     252 [-]: MOVE R15 R3  
     253 [-]: MOVE R16 R4  
     254 [-]: NAMECALL R12 R12 K49 [0x05909209]
     255 [-]: CALL R12 4 0 
     256 [-]: GETIMPORT R12 5 [nil]
     257 [-]: GETIMPORT R14 71 [nil]
     258 [-]: MOVE R15 R3  
     259 [-]: MOVE R16 R4  
     260 [-]: NAMECALL R12 R12 K49 [0x05909209]
     261 [-]: CALL R12 4 0 
     262 [-]: GETIMPORT R12 3 [nil]
     263 [-]: GETUPVAL R15 8
     264 [-]: NAMECALL R13 R12 K41 [0x0EB34C69]
     265 [-]: CALL R13 2 1 
     266 [-]: LOADN R14 0  
     267 [-]: JUMPIFNOTLE R13 R14 L29
     268 [-]: JUMP L31
    
L29: 269 [-]: ADDK R14 R13 K72 [15]
     270 [-]: LOADN R15 150
     271 [-]: JUMPIFNOTLT R15 R14 L30
     272 [-]: LOADN R14 150
L30: 273 [-]: GETUPVAL R17 8
     274 [-]: MOVE R18 R14 
     275 [-]: NAMECALL R15 R12 K73 [0x751F061D]
     276 [-]: CALL R15 3 0 
L31: 277 [-]: GETUPVAL R11 9
     278 [-]: JUMPIF R11 L32
     279 [-]: LOADB R13 1  
     280 [-]: NAMECALL R11 R1 K74 [0xD1961230]
     281 [-]: CALL R11 2 0 
     282 [-]: LOADB R11 1  
     283 [-]: SETUPVAL R11 9
L32: 284 [-]: LOADB R13 0  
     285 [-]: NAMECALL R11 R8 K19 [0x383D2E7D]
     286 [-]: CALL R11 2 0 
     287 [-]: LOADNIL R13  
     288 [-]: NAMECALL R11 R8 K20 [0x00F85B37]
     289 [-]: CALL R11 2 0 
     290 [-]: LOADN R13 0  
     291 [-]: NAMECALL R11 R8 K43 [0x2F5F5657]
     292 [-]: CALL R11 2 0 
     293 [-]: GETIMPORT R11 76 [nil]
     294 [-]: GETIMPORT R12 23 [nil]
     295 [-]: CALL R11 1 3 
     296 [-]: FORGPREP_INEXT R11 L34
L33: 297 [-]: JUMPIFNOTEQ R15 R8 L34
     298 [-]: GETIMPORT R16 23 [nil]
     299 [-]: LOADN R17 0  
     300 [-]: SETTABLE R17 R16 R14
L34: 301 [-]: FORGLOOP R11 L33 2 [inext]
     302 [-]: LOADN R13 1  
     303 [-]: LOADN R11 3  
     304 [-]: LOADN R12 1  
     305 [-]: FORNPREP R11 L37
L35: 306 [-]: LOADK R15 K77 ["SurvivalKuvaStatus"]
     307 [-]: MOVE R16 R13 
     308 [-]: CONCAT R14 R15 R16
     309 [-]: LOADK R16 K78 ["KuvaHealthTracker"]
     310 [-]: MOVE R17 R13 
     311 [-]: CONCAT R15 R16 R17
     312 [-]: GETIMPORT R17 23 [nil]
     313 [-]: GETTABLE R16 R17 R13
     314 [-]: JUMPXEQKN R16 K25 L36 NOT [0]
     315 [-]: GETIMPORT R16 80 [nil]
     316 [-]: MOVE R17 R14 
     317 [-]: CALL R16 1 0 
     318 [-]: GETIMPORT R16 80 [nil]
     319 [-]: MOVE R17 R15 
     320 [-]: CALL R16 1 0 
L36: 321 [-]: FORNLOOP R11 L35
L37: 322 [-]: GETUPVAL R11 10
     323 [-]: LOADN R12 1  
     324 [-]: CALL R11 1 1 
     325 [-]: FASTCALL1 62 R11 L38
     326 [-]: MOVE R13 R11 
     327 [-]: GETIMPORT R12 18 [nil]
     328 [-]: CALL R12 1 1 
L38: 329 [-]: JUMPIF R12 L39
     330 [-]: LENGTH R12 R11
     331 [-]: LOADN R13 0  
     332 [-]: JUMPIFNOTLT R13 R12 L39
     333 [-]: GETTABLEN R14 R11 1
     334 [-]: NAMECALL R12 R2 K27 [0xE2871589]
     335 [-]: CALL R12 2 0 
L39: 336 [-]: GETUPVAL R14 11
     337 [-]: LOADN R15 0  
     338 [-]: NAMECALL R12 R1 K41 [0x0EB34C69]
     339 [-]: CALL R12 3 1 
     340 [-]: GETUPVAL R15 11
     341 [-]: SUBK R17 R12 K62 [1]
     342 [-]: FASTCALL2K 18 R17 K25 L40 [0]
     343 [-]: LOADK R18 K25 [0]
     344 [-]: GETIMPORT R16 82 [nil]
     345 [-]: CALL R16 2 1 
L40: 346 [-]: NAMECALL R13 R1 K73 [0x751F061D]
     347 [-]: CALL R13 3 0 
     348 [-]: NAMECALL R13 R0 K83 [0xA2880940]
     349 [-]: CALL R13 1 0 
     350 [-]: RETURN R0 0  


; Name:            
; Defined at line: 1618
; #Upvalues:       1
; #Parameters:     1
; Is_vararg:       0
; Max Stack Size:  6

       0 [-]: NAMECALL R1 R0 K0 [0xBB610E5B]
       1 [-]: CALL R1 1 1  
       2 [-]: FASTCALL1 62 R1 L0
       3 [-]: MOVE R3 R1   
       4 [-]: GETIMPORT R2 2 [nil]
       5 [-]: CALL R2 1 1  
L 0:   6 [-]: JUMPIF R2 L1 
       7 [-]: GETUPVAL R3 0
       8 [-]: GETTABLEKS R2 R3 K3 [0xF22CFC77]
       9 [-]: GETIMPORT R3 6 [nil]
      10 [-]: GETIMPORT R4 8 [nil]
      11 [-]: LOADK R5 K9 ["KuvaCellPickedUp"]
      12 [-]: CALL R4 1 1  
      13 [-]: MOVE R5 R1   
      14 [-]: CALL R2 3 0  
L 1:  15 [-]: RETURN R0 0  


; Name:            
; Defined at line: 1629
; #Upvalues:       1
; #Parameters:     0
; Is_vararg:       0
; Max Stack Size:  11

       0 [-]: GETIMPORT R0 1 [nil]
       1 [-]: GETUPVAL R3 0
       2 [-]: LOADK R4 K2 [65535]
       3 [-]: NAMECALL R1 R0 K3 [0x0EB34C69]
       4 [-]: CALL R1 3 1  
L 0:   5 [-]: GETIMPORT R2 5 [nil]
       6 [-]: JUMPIF R2 L2 
       7 [-]: FASTCALL1 62 R0 L1
       8 [-]: MOVE R3 R0   
       9 [-]: GETIMPORT R2 7 [nil]
      10 [-]: CALL R2 1 1  
L 1:  11 [-]: JUMPIFNOT R2 L3
L 2:  12 [-]: GETIMPORT R2 9 [nil]
      13 [-]: LOADK R3 K10 ["Survival: Bailing on SurvivalLoopClient because I am now the host!"]
      14 [-]: CALL R2 1 0  
      15 [-]: RETURN R0 0  
L 3:  16 [-]: GETUPVAL R4 0
      17 [-]: NAMECALL R2 R0 K3 [0x0EB34C69]
      18 [-]: CALL R2 2 1  
      19 [-]: JUMPIFEQ R1 R2 L11
      20 [-]: JUMPIFNOTLT R1 R2 L10
      21 [-]: MOVE R5 R1   
      22 [-]: NAMECALL R3 R0 K11 [0x7A91BA3D]
      23 [-]: CALL R3 2 0  
      24 [-]: NAMECALL R3 R0 K12 [0x7606ACC3]
      25 [-]: CALL R3 1 0  
L 4:  26 [-]: JUMPIFEQ R1 R2 L9
      27 [-]: GETIMPORT R3 9 [nil]
      28 [-]: LOADK R5 K13 ["Survival: Client: trying to catch up with new reward count= "]
      29 [-]: GETIMPORT R9 15 [nil]
      30 [-]: MOVE R10 R2  
      31 [-]: CALL R9 1 1  
      32 [-]: MOVE R6 R9   
      33 [-]: LOADK R7 K16 [", current="]
      34 [-]: GETIMPORT R8 15 [nil]
      35 [-]: MOVE R9 R1   
      36 [-]: CALL R8 1 1  
      37 [-]: CONCAT R4 R5 R8
      38 [-]: CALL R3 1 0  
      39 [-]: ADDK R1 R1 K17 [1]
      40 [-]: GETIMPORT R4 1 [nil]
      41 [-]: NAMECALL R4 R4 K18 [0xEF893AEC]
      42 [-]: CALL R4 1 1  
      43 [-]: LOADB R3 1   
      44 [-]: GETTABLEKS R5 R4 K19 ["alertId"]
      45 [-]: JUMPXEQKS R5 K20 L6 NOT [""]
      46 [-]: LOADB R3 1   
      47 [-]: GETTABLEKS R5 R4 K21 ["invasionId"]
      48 [-]: JUMPXEQKS R5 K20 L6 NOT [""]
      49 [-]: GETTABLEKS R5 R4 K22 ["syndicateTag"]
      50 [-]: NAMECALL R5 R5 K23 [0x56C01834]
      51 [-]: CALL R5 1 1  
      52 [-]: MOVE R3 R5   
      53 [-]: JUMPIF R3 L6 
      54 [-]: GETTABLEKS R5 R4 K24 ["maxWaveNum"]
      55 [-]: LOADN R6 0   
      56 [-]: JUMPIFLT R6 R5 L5
      57 [-]: LOADB R3 0 +1
L 5:  58 [-]: LOADB R3 1   
L 6:  59 [-]: JUMPIF R3 L8 
      60 [-]: MOVE R3 R1   
      61 [-]: GETIMPORT R4 26 [nil]
      62 [-]: GETIMPORT R6 28 [nil]
      63 [-]: NAMECALL R4 R4 K29 [0x6DD7AA66]
      64 [-]: CALL R4 2 1  
      65 [-]: FASTCALL1 62 R4 L7
      66 [-]: MOVE R6 R4   
      67 [-]: GETIMPORT R5 7 [nil]
      68 [-]: CALL R5 1 1  
L 7:  69 [-]: JUMPIF R5 L8 
      70 [-]: LOADK R7 K30 ["ShowReward"]
      71 [-]: GETIMPORT R8 15 [nil]
      72 [-]: MOVE R9 R3   
      73 [-]: CALL R8 1 -1 
      74 [-]: NAMECALL R5 R4 K31 [0xE4162EED]
      75 [-]: CALL R5 -1 0 
L 8:  76 [-]: GETIMPORT R3 33 [nil]
      77 [-]: LOADN R4 0   
      78 [-]: CALL R3 1 0  
      79 [-]: JUMPBACK L4  
L 9:  80 [-]: GETIMPORT R3 9 [nil]
      81 [-]: LOADK R4 K34 ["Survival: Client: Reward count matches new reward count."]
      82 [-]: CALL R3 1 0  
      83 [-]: JUMP L11
    
L10:  84 [-]: JUMPXEQKN R1 K2 L11 NOT [65535]
      85 [-]: GETIMPORT R3 9 [nil]
      86 [-]: LOADK R5 K35 ["Survival: Client: Reward count not yet initialized, setting to "]
      87 [-]: GETIMPORT R6 15 [nil]
      88 [-]: MOVE R7 R2   
      89 [-]: CALL R6 1 1  
      90 [-]: CONCAT R4 R5 R6
      91 [-]: CALL R3 1 0  
      92 [-]: MOVE R1 R2   
L11:  93 [-]: GETIMPORT R3 33 [nil]
      94 [-]: LOADN R4 0   
      95 [-]: CALL R3 1 0  
      96 [-]: JUMPBACK L0  
      97 [-]: RETURN R0 0  


; Name:            
; Defined at line: 1678
; #Upvalues:       2
; #Parameters:     0
; Is_vararg:       0
; Max Stack Size:  6

L 0:   0 [-]: GETUPVAL R1 0
       1 [-]: LENGTH R0 R1 
       2 [-]: LOADN R1 0   
       3 [-]: JUMPIFNOTLT R1 R0 L7
       4 [-]: GETIMPORT R0 2 [nil]
       5 [-]: GETUPVAL R1 0
       6 [-]: CALL R0 1 1  
       7 [-]: FASTCALL1 62 R0 L1
       8 [-]: MOVE R2 R0   
       9 [-]: GETIMPORT R1 4 [nil]
      10 [-]: CALL R1 1 1  
L 1:  11 [-]: JUMPIF R1 L6 
      12 [-]: NAMECALL R1 R0 K5 [0xBB610E5B]
      13 [-]: CALL R1 1 1  
      14 [-]: NAMECALL R1 R1 K6 [0x2047CFE7]
      15 [-]: CALL R1 1 1  
      16 [-]: JUMPIF R1 L6 
      17 [-]: GETUPVAL R2 0
      18 [-]: LOADN R3 1   
      19 [-]: MOVE R4 R0   
      20 [-]: FASTCALL 52 L2
      21 [-]: GETIMPORT R1 8 [nil]
      22 [-]: CALL R1 3 0  
L 2:  23 [-]: NAMECALL R1 R0 K9 [0x9ACF9296]
      24 [-]: CALL R1 1 1  
      25 [-]: FASTCALL1 62 R1 L3
      26 [-]: MOVE R3 R1   
      27 [-]: GETIMPORT R2 4 [nil]
      28 [-]: CALL R2 1 1  
L 3:  29 [-]: JUMPIF R2 L4 
      30 [-]: GETIMPORT R4 11 [nil]
      31 [-]: NAMECALL R2 R1 K12 [0xF2DEAF69]
      32 [-]: CALL R2 2 1  
      33 [-]: JUMPIFNOT R2 L5
      34 [-]: NAMECALL R2 R1 K6 [0x2047CFE7]
      35 [-]: CALL R2 1 1  
      36 [-]: JUMPIFNOT R2 L5
L 4:  37 [-]: GETUPVAL R2 1
      38 [-]: MOVE R3 R0   
      39 [-]: GETIMPORT R4 14 [nil]
      40 [-]: NAMECALL R4 R4 K15 [0x8B5B1F58]
      41 [-]: CALL R4 1 -1 
      42 [-]: CALL R2 -1 0 
L 5:  43 [-]: RETURN R0 0  
L 6:  44 [-]: JUMPBACK L0  
L 7:  45 [-]: RETURN R0 0  


; Name:            
; Defined at line: 1692
; #Upvalues:       8
; #Parameters:     0
; Is_vararg:       0
; Max Stack Size:  10

       0 [-]: GETIMPORT R0 1 [nil]
       1 [-]: GETIMPORT R1 3 [nil]
       2 [-]: NAMECALL R1 R1 K4 [0x29EF273D]
       3 [-]: CALL R1 1 1  
       4 [-]: NAMECALL R2 R1 K5 [0x66905CB0]
       5 [-]: CALL R2 1 1  
       6 [-]: GETUPVAL R5 0
       7 [-]: NAMECALL R3 R0 K6 [0x0EB34C69]
       8 [-]: CALL R3 2 1  
       9 [-]: GETUPVAL R5 1
      10 [-]: GETTABLEKS R4 R5 K7 [0x7E1C98B2]
      11 [-]: CALL R4 0 1  
      12 [-]: NAMECALL R5 R2 K8 [0x4929DAAA]
      13 [-]: CALL R5 1 1  
      14 [-]: JUMPIF R5 L2 
      15 [-]: GETUPVAL R5 2
      16 [-]: JUMPIFNOTLE R5 R3 L2
      17 [-]: GETUPVAL R7 3
      18 [-]: LOADN R8 3   
      19 [-]: NAMECALL R5 R0 K9 [0x751F061D]
      20 [-]: CALL R5 3 0  
      21 [-]: LOADB R7 1   
      22 [-]: NAMECALL R5 R0 K10 [0xC7C8DAD6]
      23 [-]: CALL R5 2 0  
      24 [-]: LOADK R7 K11 ["Enable"]
      25 [-]: NAMECALL R5 R4 K12 [0x8EB2112D]
      26 [-]: CALL R5 2 0  
      27 [-]: GETUPVAL R6 4
      28 [-]: GETTABLEKS R5 R6 K13 [0x9742B85B]
      29 [-]: GETIMPORT R6 16 [nil]
      30 [-]: GETIMPORT R7 18 [nil]
      31 [-]: LOADK R8 K19 ["SurvivalExtractionReady"]
      32 [-]: CALL R7 1 -1 
      33 [-]: CALL R5 -1 0 
      34 [-]: GETIMPORT R6 1 [nil]
      35 [-]: NAMECALL R6 R6 K20 [0xEF893AEC]
      36 [-]: CALL R6 1 1  
      37 [-]: LOADB R5 1   
      38 [-]: GETTABLEKS R7 R6 K21 ["alertId"]
      39 [-]: JUMPXEQKS R7 K22 L1 NOT [""]
      40 [-]: LOADB R5 1   
      41 [-]: GETTABLEKS R7 R6 K23 ["invasionId"]
      42 [-]: JUMPXEQKS R7 K22 L1 NOT [""]
      43 [-]: GETTABLEKS R7 R6 K24 ["syndicateTag"]
      44 [-]: NAMECALL R7 R7 K25 [0x56C01834]
      45 [-]: CALL R7 1 1  
      46 [-]: MOVE R5 R7   
      47 [-]: JUMPIF R5 L1 
      48 [-]: GETTABLEKS R7 R6 K26 ["maxWaveNum"]
      49 [-]: LOADN R8 0   
      50 [-]: JUMPIFLT R8 R7 L0
      51 [-]: LOADB R5 0 +1
L 0:  52 [-]: LOADB R5 1   
L 1:  53 [-]: JUMPIFNOT R5 L2
      54 [-]: GETUPVAL R6 5
      55 [-]: GETTABLEKS R5 R6 K27 [0xCC6A9F67]
      56 [-]: CALL R5 0 0  
L 2:  57 [-]: GETUPVAL R7 0
      58 [-]: NAMECALL R5 R0 K6 [0x0EB34C69]
      59 [-]: CALL R5 2 1  
      60 [-]: FASTCALL1 62 R4 L3
      61 [-]: MOVE R7 R4   
      62 [-]: GETIMPORT R6 29 [nil]
      63 [-]: CALL R6 1 1  
L 3:  64 [-]: JUMPIF R6 L5 
      65 [-]: JUMPXEQKN R5 K30 L4 [1]
      66 [-]: LOADN R6 0   
      67 [-]: JUMPIFNOTLT R6 R5 L5
      68 [-]: MODK R6 R5 K31 [4]
      69 [-]: JUMPXEQKN R6 K32 L5 NOT [0]
L 4:  70 [-]: LOADN R8 0   
      71 [-]: NAMECALL R6 R4 K33 [0xBF4030D2]
      72 [-]: CALL R6 2 0  
      73 [-]: GETUPVAL R6 6
      74 [-]: JUMPXEQKNIL R6 L5 NOT
      75 [-]: GETUPVAL R6 7
      76 [-]: LOADN R8 60  
      77 [-]: NEWCLOSURE R9 P0
      78 [-]: MOVE R0 R4   
      79 [-]: MOVE R2 R7   
      80 [-]: MOVE R2 R6   
      81 [-]: NAMECALL R6 R6 K34 [0xBD2E96EA]
      82 [-]: CALL R6 3 1  
      83 [-]: SETUPVAL R6 6
L 5:  84 [-]: RETURN R0 0  


; Name:            
; Defined at line: 1725
; #Upvalues:       3
; #Parameters:     2
; Is_vararg:       0
; Max Stack Size:  9

       0 [-]: LOADB R2 0   
       1 [-]: GETIMPORT R3 2 [nil]
       2 [-]: GETIMPORT R4 4 [nil]
       3 [-]: GETIMPORT R6 6 [nil]
       4 [-]: NAMECALL R6 R6 K7 [0xEF893AEC]
       5 [-]: CALL R6 1 1  
       6 [-]: GETTABLEKS R5 R6 K8 ["activeMissionTag"]
       7 [-]: CALL R4 1 1  
       8 [-]: LOADK R5 K9 ["Void"]
       9 [-]: CALL R3 2 1  
      10 [-]: JUMPIFNOT R3 L11
      11 [-]: JUMPXEQKNIL R1 L0
      12 [-]: JUMPXEQKN R1 K10 L11 NOT [1]
L 0:  13 [-]: GETIMPORT R4 6 [nil]
      14 [-]: GETUPVAL R6 0
      15 [-]: LOADN R7 1   
      16 [-]: NAMECALL R4 R4 K11 [0x751F061D]
      17 [-]: CALL R4 3 0  
      18 [-]: GETUPVAL R5 1
      19 [-]: GETTABLEKS R4 R5 K12 [0x06D055F9]
      20 [-]: JUMPXEQKNIL R1 L1
      21 [-]: LOADB R5 0 +1
L 1:  22 [-]: LOADB R5 1   
L 2:  23 [-]: LOADN R6 10  
      24 [-]: LOADN R7 0   
      25 [-]: CALL R4 3 1  
L 3:  26 [-]: GETUPVAL R6 2
      27 [-]: GETTABLEKS R5 R6 K13 [0x0DEACD54]
      28 [-]: CALL R5 0 1  
      29 [-]: JUMPIF R5 L4 
      30 [-]: GETIMPORT R5 15 [nil]
      31 [-]: CALL R5 0 1  
      32 [-]: SUB R4 R4 R5 
      33 [-]: LOADN R5 0   
      34 [-]: JUMPIFLE R4 R5 L4
      35 [-]: GETIMPORT R5 17 [nil]
      36 [-]: LOADN R6 0   
      37 [-]: CALL R5 1 0  
      38 [-]: JUMPBACK L3  
L 4:  39 [-]: LOADN R4 20  
L 5:  40 [-]: GETUPVAL R6 2
      41 [-]: GETTABLEKS R5 R6 K13 [0x0DEACD54]
      42 [-]: CALL R5 0 1  
      43 [-]: JUMPIFNOT R5 L6
      44 [-]: GETIMPORT R5 15 [nil]
      45 [-]: CALL R5 0 1  
      46 [-]: SUB R4 R4 R5 
      47 [-]: LOADN R5 0   
      48 [-]: JUMPIFLE R4 R5 L6
      49 [-]: GETIMPORT R5 17 [nil]
      50 [-]: LOADN R6 0   
      51 [-]: CALL R5 1 0  
      52 [-]: JUMPBACK L5  
L 6:  53 [-]: GETIMPORT R5 6 [nil]
      54 [-]: MOVE R7 R0   
      55 [-]: LOADB R8 0   
      56 [-]: NAMECALL R5 R5 K18 [0xDCED2D0E]
      57 [-]: CALL R5 3 1  
      58 [-]: FASTCALL1 62 R5 L7
      59 [-]: MOVE R7 R5   
      60 [-]: GETIMPORT R6 20 [nil]
      61 [-]: CALL R6 1 1  
L 7:  62 [-]: JUMPIF R6 L11
      63 [-]: LOADB R2 1   
L 8:  64 [-]: FASTCALL1 62 R5 L9
      65 [-]: MOVE R7 R5   
      66 [-]: GETIMPORT R6 20 [nil]
      67 [-]: CALL R6 1 1  
L 9:  68 [-]: JUMPIF R6 L10
      69 [-]: GETIMPORT R6 17 [nil]
      70 [-]: LOADN R7 0   
      71 [-]: CALL R6 1 0  
      72 [-]: JUMPBACK L8  
L10:  73 [-]: GETIMPORT R6 6 [nil]
      74 [-]: NAMECALL R6 R6 K21 [0xF36E974A]
      75 [-]: CALL R6 1 0  
L11:  76 [-]: JUMPIF R2 L12
      77 [-]: JUMPXEQKN R1 K22 L18 NOT [2]
L12:  78 [-]: GETIMPORT R4 6 [nil]
      79 [-]: GETUPVAL R6 0
      80 [-]: LOADN R7 2   
      81 [-]: NAMECALL R4 R4 K11 [0x751F061D]
      82 [-]: CALL R4 3 0  
      83 [-]: GETIMPORT R4 6 [nil]
      84 [-]: JUMPXEQKNIL R1 L13 NOT
      85 [-]: LOADB R6 0 +1
L13:  86 [-]: LOADB R6 1   
L14:  87 [-]: NAMECALL R4 R4 K23 [0x494DB239]
      88 [-]: CALL R4 2 1  
      89 [-]: FASTCALL1 62 R4 L15
      90 [-]: MOVE R6 R4   
      91 [-]: GETIMPORT R5 20 [nil]
      92 [-]: CALL R5 1 1  
L15:  93 [-]: JUMPIF R5 L18
L16:  94 [-]: FASTCALL1 62 R4 L17
      95 [-]: MOVE R6 R4   
      96 [-]: GETIMPORT R5 20 [nil]
      97 [-]: CALL R5 1 1  
L17:  98 [-]: JUMPIF R5 L18
      99 [-]: GETIMPORT R5 17 [nil]
     100 [-]: LOADN R6 0   
     101 [-]: CALL R5 1 0  
     102 [-]: JUMPBACK L16 
L18: 103 [-]: GETIMPORT R4 6 [nil]
     104 [-]: GETUPVAL R6 0
     105 [-]: LOADN R7 0   
     106 [-]: NAMECALL R4 R4 K11 [0x751F061D]
     107 [-]: CALL R4 3 0  
     108 [-]: RETURN R0 0  


; Name:            
; Defined at line: 1780
; #Upvalues:       18
; #Parameters:     0
; Is_vararg:       0
; Max Stack Size:  28

       0 [-]: GETIMPORT R0 1 [nil]
       1 [-]: GETIMPORT R1 3 [nil]
       2 [-]: NAMECALL R1 R1 K4 [0x29EF273D]
       3 [-]: CALL R1 1 1  
       4 [-]: NAMECALL R2 R1 K5 [0x66905CB0]
       5 [-]: CALL R2 1 1  
       6 [-]: GETIMPORT R4 1 [nil]
       7 [-]: NAMECALL R4 R4 K6 [0xEF893AEC]
       8 [-]: CALL R4 1 1  
       9 [-]: LOADB R3 1   
      10 [-]: GETTABLEKS R5 R4 K7 ["alertId"]
      11 [-]: JUMPXEQKS R5 K8 L1 NOT [""]
      12 [-]: LOADB R3 1   
      13 [-]: GETTABLEKS R5 R4 K9 ["invasionId"]
      14 [-]: JUMPXEQKS R5 K8 L1 NOT [""]
      15 [-]: GETTABLEKS R5 R4 K10 ["syndicateTag"]
      16 [-]: NAMECALL R5 R5 K11 [0x56C01834]
      17 [-]: CALL R5 1 1  
      18 [-]: MOVE R3 R5   
      19 [-]: JUMPIF R3 L1 
      20 [-]: GETTABLEKS R5 R4 K12 ["maxWaveNum"]
      21 [-]: LOADN R6 0   
      22 [-]: JUMPIFLT R6 R5 L0
      23 [-]: LOADB R3 0 +1
L 0:  24 [-]: LOADB R3 1   
L 1:  25 [-]: LOADN R4 0   
      26 [-]: GETIMPORT R5 14 [nil]
      27 [-]: LOADK R6 K15 ["Lotus.Interface.Libs.TimerMgr"]
      28 [-]: CALL R5 1 1  
      29 [-]: GETTABLEKS R6 R5 K16 [0xDE474187]
      30 [-]: CALL R6 0 1  
      31 [-]: SETUPVAL R6 0
      32 [-]: GETIMPORT R6 18 [nil]
      33 [-]: LOADK R7 K19 ["Survival: Main gameplay loop started"]
      34 [-]: CALL R6 1 0  
      35 [-]: JUMPIFNOT R3 L5
      36 [-]: GETIMPORT R7 1 [nil]
      37 [-]: NAMECALL R7 R7 K6 [0xEF893AEC]
      38 [-]: CALL R7 1 1  
      39 [-]: GETUPVAL R9 2
      40 [-]: GETTABLEKS R8 R9 K20 [0x06D055F9]
      41 [-]: GETTABLEKS R10 R7 K12 ["maxWaveNum"]
      42 [-]: LOADN R11 0  
      43 [-]: JUMPIFLT R11 R10 L2
      44 [-]: LOADB R9 0 +1
L 2:  45 [-]: LOADB R9 1   
L 3:  46 [-]: GETTABLEKS R12 R7 K12 ["maxWaveNum"]
      47 [-]: MULK R11 R12 K21 [60]
      48 [-]: FASTCALL2K 19 R11 K22 L4 [3600]
      49 [-]: LOADK R12 K22 [3600]
      50 [-]: GETIMPORT R10 25 [nil]
      51 [-]: CALL R10 2 1 
L 4:  52 [-]: LOADN R11 600
      53 [-]: CALL R8 3 1  
      54 [-]: MOVE R6 R8   
      55 [-]: SETUPVAL R6 1
L 5:  56 [-]: GETIMPORT R7 1 [nil]
      57 [-]: NAMECALL R7 R7 K6 [0xEF893AEC]
      58 [-]: CALL R7 1 1  
      59 [-]: GETTABLEKS R6 R7 K26 ["goalId"]
      60 [-]: JUMPXEQKS R6 K8 L8 [""]
      61 [-]: GETIMPORT R7 1 [nil]
      62 [-]: NAMECALL R7 R7 K6 [0xEF893AEC]
      63 [-]: CALL R7 1 1  
      64 [-]: LOADB R6 1   
      65 [-]: GETTABLEKS R8 R7 K7 ["alertId"]
      66 [-]: JUMPXEQKS R8 K8 L7 NOT [""]
      67 [-]: LOADB R6 1   
      68 [-]: GETTABLEKS R8 R7 K9 ["invasionId"]
      69 [-]: JUMPXEQKS R8 K8 L7 NOT [""]
      70 [-]: GETTABLEKS R8 R7 K10 ["syndicateTag"]
      71 [-]: NAMECALL R8 R8 K11 [0x56C01834]
      72 [-]: CALL R8 1 1  
      73 [-]: MOVE R6 R8   
      74 [-]: JUMPIF R6 L7 
      75 [-]: GETTABLEKS R8 R7 K12 ["maxWaveNum"]
      76 [-]: LOADN R9 0   
      77 [-]: JUMPIFLT R9 R8 L6
      78 [-]: LOADB R6 0 +1
L 6:  79 [-]: LOADB R6 1   
L 7:  80 [-]: JUMPIF R6 L8 
      81 [-]: LOADN R6 4   
      82 [-]: SETUPVAL R6 3
L 8:  83 [-]: LOADN R8 250 
      84 [-]: LOADN R9 250 
      85 [-]: LOADB R10 0  
      86 [-]: LOADB R11 0  
      87 [-]: NAMECALL R6 R2 K27 [0x2B39CBDE]
      88 [-]: CALL R6 5 0  
      89 [-]: LOADN R8 25  
      90 [-]: LOADN R9 250 
      91 [-]: LOADN R10 0  
      92 [-]: LOADN R11 2  
      93 [-]: LOADB R12 1  
      94 [-]: LOADB R13 0  
      95 [-]: LOADB R14 1  
      96 [-]: NAMECALL R6 R2 K28 [0xA2367658]
      97 [-]: CALL R6 8 0  
      98 [-]: LOADB R8 1   
      99 [-]: NAMECALL R6 R2 K29 [0x1A82855B]
     100 [-]: CALL R6 2 0  
     101 [-]: GETIMPORT R8 31 [nil]
     102 [-]: LOADK R9 K32 ["DefenseAgentSpawn"]
     103 [-]: CALL R8 1 -1 
     104 [-]: NAMECALL R6 R2 K33 [0xA7FB023F]
     105 [-]: CALL R6 -1 0 
     106 [-]: GETIMPORT R8 31 [nil]
     107 [-]: LOADK R9 K34 ["BipedSpecialSpawn"]
     108 [-]: CALL R8 1 -1 
     109 [-]: NAMECALL R6 R2 K33 [0xA7FB023F]
     110 [-]: CALL R6 -1 0 
     111 [-]: GETIMPORT R8 31 [nil]
     112 [-]: LOADK R9 K35 ["DoNotUse"]
     113 [-]: CALL R8 1 -1 
     114 [-]: NAMECALL R6 R2 K33 [0xA7FB023F]
     115 [-]: CALL R6 -1 0 
     116 [-]: GETIMPORT R8 31 [nil]
     117 [-]: LOADK R9 K36 ["CameraSpawn"]
     118 [-]: CALL R8 1 -1 
     119 [-]: NAMECALL R6 R2 K33 [0xA7FB023F]
     120 [-]: CALL R6 -1 0 
     121 [-]: GETIMPORT R8 31 [nil]
     122 [-]: LOADK R9 K37 ["TurretSpawn"]
     123 [-]: CALL R8 1 -1 
     124 [-]: NAMECALL R6 R2 K33 [0xA7FB023F]
     125 [-]: CALL R6 -1 0 
     126 [-]: GETIMPORT R8 31 [nil]
     127 [-]: LOADK R9 K38 ["WaterSpawn"]
     128 [-]: CALL R8 1 -1 
     129 [-]: NAMECALL R6 R2 K33 [0xA7FB023F]
     130 [-]: CALL R6 -1 0 
     131 [-]: LOADB R8 0   
     132 [-]: NAMECALL R6 R2 K39 [0x8F4DC1B0]
     133 [-]: CALL R6 2 0  
     134 [-]: LOADN R8 0   
     135 [-]: NAMECALL R6 R2 K40 [0xFDA3B6ED]
     136 [-]: CALL R6 2 0  
     137 [-]: GETUPVAL R8 4
     138 [-]: NAMECALL R6 R0 K41 [0x0EB34C69]
     139 [-]: CALL R6 2 1  
L 9: 140 [-]: LOADN R7 0   
     141 [-]: JUMPIFNOTLT R7 R6 L48
     142 [-]: GETIMPORT R7 44 [nil]
     143 [-]: JUMPXEQKB R7 1 L48
     144 [-]: GETUPVAL R9 5
     145 [-]: NAMECALL R7 R0 K45 [0xFFDDF768]
     146 [-]: CALL R7 2 1  
     147 [-]: JUMPIFNOT R3 L14
     148 [-]: LOADN R9 0   
     149 [-]: GETIMPORT R12 1 [nil]
     150 [-]: NAMECALL R12 R12 K6 [0xEF893AEC]
     151 [-]: CALL R12 1 1 
     152 [-]: GETUPVAL R14 2
     153 [-]: GETTABLEKS R13 R14 K20 [0x06D055F9]
     154 [-]: GETTABLEKS R15 R12 K12 ["maxWaveNum"]
     155 [-]: LOADN R16 0  
     156 [-]: JUMPIFLT R16 R15 L10
     157 [-]: LOADB R14 0 +1
L10: 158 [-]: LOADB R14 1  
L11: 159 [-]: GETTABLEKS R17 R12 K12 ["maxWaveNum"]
     160 [-]: MULK R16 R17 K21 [60]
     161 [-]: FASTCALL2K 19 R16 K22 L12 [3600]
     162 [-]: LOADK R17 K22 [3600]
     163 [-]: GETIMPORT R15 25 [nil]
     164 [-]: CALL R15 2 1 
L12: 165 [-]: LOADN R16 600
     166 [-]: CALL R13 3 1 
     167 [-]: MOVE R11 R13 
     168 [-]: SUB R10 R11 R7
     169 [-]: FASTCALL2 18 R9 R10 L13
     170 [-]: GETIMPORT R8 47 [nil]
     171 [-]: CALL R8 2 1  
L13: 172 [-]: MOVE R7 R8   
L14: 173 [-]: GETUPVAL R8 6
     174 [-]: CALL R8 0 0  
     175 [-]: GETUPVAL R8 7
     176 [-]: CALL R8 0 0  
     177 [-]: GETUPVAL R8 8
     178 [-]: LOADK R9 K48 [0.5]
     179 [-]: CALL R8 1 1  
     180 [-]: GETUPVAL R9 0
     181 [-]: LOADK R13 K48 [0.5]
     182 [-]: ADD R12 R13 R8
     183 [-]: GETIMPORT R13 50 [nil]
     184 [-]: CALL R13 0 1 
     185 [-]: ADD R11 R12 R13
     186 [-]: NAMECALL R9 R9 K51 [0xFAA69527]
     187 [-]: CALL R9 2 0  
     188 [-]: GETUPVAL R9 9
     189 [-]: JUMPIF R9 L16
     190 [-]: LOADN R9 60  
     191 [-]: JUMPIFLT R6 R9 L15
     192 [-]: LOADN R9 210 
     193 [-]: JUMPIFNOTLE R9 R7 L16
L15: 194 [-]: LOADB R11 1  
     195 [-]: NAMECALL R9 R0 K52 [0xD1961230]
     196 [-]: CALL R9 2 0  
     197 [-]: LOADB R9 1   
     198 [-]: SETUPVAL R9 9
L16: 199 [-]: GETIMPORT R9 54 [nil]
     200 [-]: GETUPVAL R12 10
     201 [-]: NAMECALL R10 R0 K41 [0x0EB34C69]
     202 [-]: CALL R10 2 1 
     203 [-]: GETUPVAL R13 11
     204 [-]: LOADN R14 0  
     205 [-]: NAMECALL R11 R0 K41 [0x0EB34C69]
     206 [-]: CALL R11 3 1 
     207 [-]: GETUPVAL R16 1
     208 [-]: DIV R15 R7 R16
     209 [-]: FASTCALL1 12 R15 L17
     210 [-]: GETIMPORT R14 56 [nil]
     211 [-]: CALL R14 1 1 
L17: 212 [-]: ADD R13 R14 R11
     213 [-]: ADD R12 R13 R9
     214 [-]: ADDK R15 R10 K57 [1]
     215 [-]: MOVE R13 R12 
     216 [-]: LOADN R14 1  
     217 [-]: FORNPREP R13 L31
L18: 218 [-]: LOADN R16 0  
     219 [-]: JUMPIFNOTLT R16 R9 L19
     220 [-]: SUB R16 R12 R9
     221 [-]: JUMPIFNOTLT R16 R15 L19
     222 [-]: GETUPVAL R18 11
     223 [-]: GETUPVAL R22 11
     224 [-]: LOADN R23 0  
     225 [-]: NAMECALL R20 R0 K41 [0x0EB34C69]
     226 [-]: CALL R20 3 1 
     227 [-]: ADDK R19 R20 K57 [1]
     228 [-]: NAMECALL R16 R0 K58 [0x751F061D]
     229 [-]: CALL R16 3 0 
     230 [-]: GETIMPORT R16 59 [nil]
     231 [-]: GETIMPORT R18 54 [nil]
     232 [-]: SUBK R17 R18 K57 [1]
     233 [-]: SETTABLEKS R17 R16 K53 ["SquadLinkSurvivalGiveRewards"]
L19: 234 [-]: JUMPXEQKN R15 K57 L21 NOT [1]
     235 [-]: LOADB R18 1  
     236 [-]: NAMECALL R16 R0 K52 [0xD1961230]
     237 [-]: CALL R16 2 0 
     238 [-]: NAMECALL R16 R0 K60 [0x7606ACC3]
     239 [-]: CALL R16 1 0 
     240 [-]: GETUPVAL R18 10
     241 [-]: LOADN R19 1  
     242 [-]: NAMECALL R16 R0 K58 [0x751F061D]
     243 [-]: CALL R16 3 0 
     244 [-]: NAMECALL R16 R0 K61 [0x7A91BA3D]
     245 [-]: CALL R16 1 0 
     246 [-]: JUMPIF R3 L24
     247 [-]: GETIMPORT R16 18 [nil]
     248 [-]: LOADK R17 K62 ["Survival: Host - first reward"]
     249 [-]: CALL R16 1 0 
     250 [-]: GETIMPORT R16 64 [nil]
     251 [-]: GETIMPORT R18 66 [nil]
     252 [-]: NAMECALL R16 R16 K67 [0x6DD7AA66]
     253 [-]: CALL R16 2 1 
     254 [-]: FASTCALL1 62 R16 L20
     255 [-]: MOVE R18 R16 
     256 [-]: GETIMPORT R17 69 [nil]
     257 [-]: CALL R17 1 1 
L20: 258 [-]: JUMPIF R17 L24
     259 [-]: LOADK R19 K70 ["ShowReward"]
     260 [-]: GETIMPORT R20 72 [nil]
     261 [-]: LOADN R21 1  
     262 [-]: CALL R20 1 -1
     263 [-]: NAMECALL R17 R16 K73 [0xE4162EED]
     264 [-]: CALL R17 -1 0
     265 [-]: JUMP L24
    
L21: 266 [-]: JUMPIF R3 L24
     267 [-]: SUBK R18 R15 K57 [1]
     268 [-]: NAMECALL R16 R0 K61 [0x7A91BA3D]
     269 [-]: CALL R16 2 0 
     270 [-]: GETIMPORT R16 64 [nil]
     271 [-]: GETIMPORT R18 66 [nil]
     272 [-]: NAMECALL R16 R16 K67 [0x6DD7AA66]
     273 [-]: CALL R16 2 1 
     274 [-]: FASTCALL1 62 R16 L22
     275 [-]: MOVE R18 R16 
     276 [-]: GETIMPORT R17 69 [nil]
     277 [-]: CALL R17 1 1 
L22: 278 [-]: JUMPIF R17 L23
     279 [-]: LOADK R19 K70 ["ShowReward"]
     280 [-]: GETIMPORT R20 72 [nil]
     281 [-]: MOVE R21 R15 
     282 [-]: CALL R20 1 -1
     283 [-]: NAMECALL R17 R16 K73 [0xE4162EED]
     284 [-]: CALL R17 -1 0
L23: 285 [-]: GETUPVAL R18 10
     286 [-]: MOVE R19 R15 
     287 [-]: NAMECALL R16 R0 K58 [0x751F061D]
     288 [-]: CALL R16 3 0 
     289 [-]: GETUPVAL R17 12
     290 [-]: GETTABLEKS R16 R17 K74 [0x9742B85B]
     291 [-]: GETIMPORT R17 76 [nil]
     292 [-]: GETIMPORT R18 31 [nil]
     293 [-]: LOADK R19 K77 ["SurvivalRewardReached"]
     294 [-]: CALL R18 1 -1
     295 [-]: CALL R16 -1 0
     296 [-]: SUB R16 R12 R9
     297 [-]: JUMPIFNOTLE R15 R16 L24
     298 [-]: SUB R16 R15 R11
     299 [-]: LOADN R17 1  
     300 [-]: JUMPIFNOTLT R17 R16 L24
     301 [-]: GETUPVAL R16 13
     302 [-]: CALL R16 0 0 
     303 [-]: GETUPVAL R16 14
     304 [-]: SUB R17 R15 R11
     305 [-]: CALL R16 1 0 
L24: 306 [-]: SUB R16 R15 R11
     307 [-]: JUMPXEQKN R16 K57 L30 NOT [1]
     308 [-]: GETUPVAL R16 1
     309 [-]: JUMPIFNOTLE R16 R7 L30
     310 [-]: GETUPVAL R16 13
     311 [-]: CALL R16 0 0 
     312 [-]: GETUPVAL R17 12
     313 [-]: GETTABLEKS R16 R17 K74 [0x9742B85B]
     314 [-]: GETIMPORT R17 76 [nil]
     315 [-]: GETIMPORT R18 31 [nil]
     316 [-]: LOADK R19 K78 ["SurvivalFirstTimeReached"]
     317 [-]: CALL R18 1 -1
     318 [-]: CALL R16 -1 0
     319 [-]: GETIMPORT R16 80 [nil]
     320 [-]: LOADN R17 0  
     321 [-]: CALL R16 1 0 
     322 [-]: GETUPVAL R16 14
     323 [-]: LOADN R17 1  
     324 [-]: CALL R16 1 0 
     325 [-]: JUMPIFNOT R3 L28
     326 [-]: GETIMPORT R16 3 [nil]
     327 [-]: NAMECALL R16 R16 K81 [0x8B5B1F58]
     328 [-]: CALL R16 1 1 
     329 [-]: LOADN R19 1  
     330 [-]: LENGTH R17 R16
     331 [-]: LOADN R18 1  
     332 [-]: FORNPREP R17 L26
L25: 333 [-]: GETIMPORT R20 1 [nil]
     334 [-]: GETTABLE R22 R16 R19
     335 [-]: NAMECALL R22 R22 K82 [0x5E651723]
     336 [-]: CALL R22 1 1 
     337 [-]: LOADK R23 K83 ["/Lotus/Language/Game/ExtractionTimer"]
     338 [-]: LOADK R24 K8 [""]
     339 [-]: LOADN R25 0  
     340 [-]: LOADN R26 3  
     341 [-]: LOADB R27 1  
     342 [-]: NAMECALL R20 R20 K84 [0x06D4C9EB]
     343 [-]: CALL R20 7 0 
     344 [-]: FORNLOOP R17 L25
L26: 345 [-]: LOADN R17 31 
     346 [-]: JUMPIFNOTLE R6 R17 L27
     347 [-]: LOADK R18 K85 [30.5]
     348 [-]: GETIMPORT R19 50 [nil]
     349 [-]: CALL R19 0 1 
     350 [-]: SUB R17 R18 R19
     351 [-]: JUMPIFNOTLE R17 R6 L27
     352 [-]: GETUPVAL R18 12
     353 [-]: GETTABLEKS R17 R18 K74 [0x9742B85B]
     354 [-]: GETIMPORT R18 76 [nil]
     355 [-]: GETIMPORT R19 31 [nil]
     356 [-]: LOADK R20 K86 ["SurvivalExtractionUrgent"]
     357 [-]: CALL R19 1 -1
     358 [-]: CALL R17 -1 0
     359 [-]: JUMP L31
    
L27: 360 [-]: GETUPVAL R18 12
     361 [-]: GETTABLEKS R17 R18 K74 [0x9742B85B]
     362 [-]: GETIMPORT R18 76 [nil]
     363 [-]: GETIMPORT R19 31 [nil]
     364 [-]: LOADK R20 K87 ["SurvivalExtractionReady"]
     365 [-]: CALL R19 1 -1
     366 [-]: CALL R17 -1 0
     367 [-]: JUMP L31
    
L28: 368 [-]: LOADN R16 30 
     369 [-]: JUMPIFNOTLE R6 R16 L30
     370 [-]: GETIMPORT R16 89 [nil]
     371 [-]: JUMPIFNOT R16 L29
     372 [-]: GETIMPORT R16 91 [nil]
     373 [-]: GETIMPORT R17 31 [nil]
     374 [-]: LOADK R18 K92 ["Infestation"]
     375 [-]: CALL R17 1 1 
     376 [-]: JUMPIFNOTEQ R16 R17 L29
     377 [-]: GETUPVAL R17 12
     378 [-]: GETTABLEKS R16 R17 K74 [0x9742B85B]
     379 [-]: GETIMPORT R17 76 [nil]
     380 [-]: GETIMPORT R18 31 [nil]
     381 [-]: LOADK R19 K93 ["SurvivalExtractionUrgentInfested"]
     382 [-]: CALL R18 1 -1
     383 [-]: CALL R16 -1 0
     384 [-]: JUMP L30
    
L29: 385 [-]: GETUPVAL R18 10
     386 [-]: NAMECALL R16 R0 K41 [0x0EB34C69]
     387 [-]: CALL R16 2 1 
     388 [-]: GETUPVAL R17 3
     389 [-]: JUMPIFNOTLE R17 R16 L30
     390 [-]: GETUPVAL R17 12
     391 [-]: GETTABLEKS R16 R17 K74 [0x9742B85B]
     392 [-]: GETIMPORT R17 76 [nil]
     393 [-]: GETIMPORT R18 31 [nil]
     394 [-]: LOADK R19 K86 ["SurvivalExtractionUrgent"]
     395 [-]: CALL R18 1 -1
     396 [-]: CALL R16 -1 0
L30: 397 [-]: FORNLOOP R13 L18
L31: 398 [-]: GETUPVAL R15 15
     399 [-]: NAMECALL R13 R0 K41 [0x0EB34C69]
     400 [-]: CALL R13 2 1 
     401 [-]: LOADN R14 31 
     402 [-]: JUMPIFNOTLE R6 R14 L34
     403 [-]: LOADK R15 K85 [30.5]
     404 [-]: GETIMPORT R16 50 [nil]
     405 [-]: CALL R16 0 1 
     406 [-]: SUB R14 R15 R16
     407 [-]: JUMPIFNOTLE R14 R6 L34
     408 [-]: LOADN R14 3  
     409 [-]: JUMPIFNOTLE R14 R13 L33
     410 [-]: GETUPVAL R16 10
     411 [-]: NAMECALL R14 R0 K41 [0x0EB34C69]
     412 [-]: CALL R14 2 1 
     413 [-]: GETUPVAL R15 3
     414 [-]: JUMPIFNOTLE R15 R14 L33
     415 [-]: GETIMPORT R14 89 [nil]
     416 [-]: JUMPIFNOT R14 L32
     417 [-]: GETIMPORT R14 91 [nil]
     418 [-]: GETIMPORT R15 31 [nil]
     419 [-]: LOADK R16 K92 ["Infestation"]
     420 [-]: CALL R15 1 1 
     421 [-]: JUMPIFNOTEQ R14 R15 L32
     422 [-]: GETUPVAL R15 12
     423 [-]: GETTABLEKS R14 R15 K74 [0x9742B85B]
     424 [-]: GETIMPORT R15 76 [nil]
     425 [-]: GETIMPORT R16 31 [nil]
     426 [-]: LOADK R17 K93 ["SurvivalExtractionUrgentInfested"]
     427 [-]: CALL R16 1 -1
     428 [-]: CALL R14 -1 0
     429 [-]: JUMP L35
    
L32: 430 [-]: GETUPVAL R15 12
     431 [-]: GETTABLEKS R14 R15 K74 [0x9742B85B]
     432 [-]: GETIMPORT R15 76 [nil]
     433 [-]: GETIMPORT R16 31 [nil]
     434 [-]: LOADK R17 K86 ["SurvivalExtractionUrgent"]
     435 [-]: CALL R16 1 -1
     436 [-]: CALL R14 -1 0
     437 [-]: JUMP L35
    
L33: 438 [-]: GETUPVAL R15 12
     439 [-]: GETTABLEKS R14 R15 K74 [0x9742B85B]
     440 [-]: GETIMPORT R15 76 [nil]
     441 [-]: GETIMPORT R16 31 [nil]
     442 [-]: LOADK R17 K94 ["Survival30SecondsLeft"]
     443 [-]: CALL R16 1 -1
     444 [-]: CALL R14 -1 0
     445 [-]: JUMP L35
    
L34: 446 [-]: LOADN R14 61 
     447 [-]: JUMPIFNOTLE R6 R14 L35
     448 [-]: LOADK R15 K95 [60.5]
     449 [-]: GETIMPORT R16 50 [nil]
     450 [-]: CALL R16 0 1 
     451 [-]: SUB R14 R15 R16
     452 [-]: JUMPIFNOTLE R14 R6 L35
     453 [-]: GETUPVAL R15 12
     454 [-]: GETTABLEKS R14 R15 K74 [0x9742B85B]
     455 [-]: GETIMPORT R15 76 [nil]
     456 [-]: GETIMPORT R16 31 [nil]
     457 [-]: LOADK R17 K96 ["Survival60SecondsLeft"]
     458 [-]: CALL R16 1 -1
     459 [-]: CALL R14 -1 0
L35: 460 [-]: GETUPVAL R16 4
     461 [-]: NAMECALL R14 R0 K41 [0x0EB34C69]
     462 [-]: CALL R14 2 1 
     463 [-]: SUBK R15 R14 K57 [1]
     464 [-]: JUMPIFLE R6 R15 L36
     465 [-]: ADDK R15 R14 K57 [1]
     466 [-]: JUMPIFNOTLE R15 R6 L37
L36: 467 [-]: MOVE R6 R14  
L37: 468 [-]: SUBK R15 R6 K48 [0.5]
     469 [-]: SUB R6 R15 R8
     470 [-]: LOADN R15 0  
     471 [-]: JUMPIFNOTLE R6 R15 L40
     472 [-]: LOADN R6 0   
     473 [-]: GETIMPORT R15 18 [nil]
     474 [-]: LOADK R16 K97 ["Survival: Life support is at 0, checking for capsules still in use."]
     475 [-]: CALL R15 1 0 
     476 [-]: GETIMPORT R15 3 [nil]
     477 [-]: GETIMPORT R17 99 [nil]
     478 [-]: NAMECALL R15 R15 K100 [0xFB669000]
     479 [-]: CALL R15 2 1 
     480 [-]: LOADN R16 0  
     481 [-]: LOADN R19 1  
     482 [-]: LENGTH R17 R15
     483 [-]: LOADN R18 1  
     484 [-]: FORNPREP R17 L39
L38: 485 [-]: GETTABLE R20 R15 R19
     486 [-]: NAMECALL R20 R20 K101 [0x9CBE2EA2]
     487 [-]: CALL R20 1 1 
     488 [-]: ADD R16 R16 R20
     489 [-]: FORNLOOP R17 L38
L39: 490 [-]: LOADN R17 0  
     491 [-]: JUMPIFNOTLT R17 R16 L40
     492 [-]: GETIMPORT R17 18 [nil]
     493 [-]: LOADK R18 K102 ["Survival: Life support capsule being activated, waiting for it to finish."]
     494 [-]: CALL R17 1 0 
     495 [-]: ADDK R6 R6 K103 [3]
L40: 496 [-]: FASTCALL1 7 R6 L41
     497 [-]: MOVE R16 R6  
     498 [-]: GETIMPORT R15 105 [nil]
     499 [-]: CALL R15 1 1 
L41: 500 [-]: GETUPVAL R18 4
     501 [-]: MOVE R19 R15 
     502 [-]: NAMECALL R16 R0 K58 [0x751F061D]
     503 [-]: CALL R16 3 0 
     504 [-]: LOADN R16 0  
     505 [-]: JUMPIFNOTLT R7 R16 L42
     506 [-]: LOADN R7 0   
     507 [-]: JUMP L43
    
L42: 508 [-]: GETIMPORT R16 50 [nil]
     509 [-]: CALL R16 0 1 
     510 [-]: ADD R7 R7 R16
L43: 511 [-]: FASTCALL1 12 R7 L44
     512 [-]: MOVE R17 R7  
     513 [-]: GETIMPORT R16 56 [nil]
     514 [-]: CALL R16 1 1 
L44: 515 [-]: MODK R17 R16 K21 [60]
     516 [-]: JUMPXEQKN R17 K106 L45 NOT [0]
     517 [-]: JUMPIFNOTLT R4 R16 L45
     518 [-]: LOADK R18 K107 ["SurvivalTimed"]
     519 [-]: DIVK R19 R16 K21 [60]
     520 [-]: LOADK R20 K108 ["Mins"]
     521 [-]: CONCAT R17 R18 R20
     522 [-]: GETUPVAL R19 12
     523 [-]: GETTABLEKS R18 R19 K74 [0x9742B85B]
     524 [-]: GETIMPORT R19 76 [nil]
     525 [-]: GETIMPORT R20 31 [nil]
     526 [-]: MOVE R21 R17 
     527 [-]: CALL R20 1 -1
     528 [-]: CALL R18 -1 0
     529 [-]: MOVE R4 R15  
L45: 530 [-]: GETUPVAL R19 5
     531 [-]: NAMECALL R17 R0 K109 [0x6471C498]
     532 [-]: CALL R17 2 1 
     533 [-]: JUMPIFNOT R17 L46
     534 [-]: JUMPIFNOT R3 L47
L46: 535 [-]: GETUPVAL R19 16
     536 [-]: MOVE R20 R7  
     537 [-]: NAMECALL R17 R0 K58 [0x751F061D]
     538 [-]: CALL R17 3 0 
L47: 539 [-]: GETIMPORT R17 80 [nil]
     540 [-]: LOADK R18 K48 [0.5]
     541 [-]: CALL R17 1 0 
     542 [-]: JUMPBACK L9  
L48: 543 [-]: GETUPVAL R9 16
     544 [-]: NAMECALL R7 R0 K41 [0x0EB34C69]
     545 [-]: CALL R7 2 1  
     546 [-]: GETIMPORT R8 18 [nil]
     547 [-]: LOADK R10 K110 ["Survival: Final score is "]
     548 [-]: MOVE R11 R7  
     549 [-]: CONCAT R9 R10 R11
     550 [-]: CALL R8 1 0  
     551 [-]: LOADN R8 0   
     552 [-]: JUMPIFNOTLE R6 R8 L49
     553 [-]: GETIMPORT R8 80 [nil]
     554 [-]: LOADN R9 1   
     555 [-]: CALL R8 1 0  
     556 [-]: GETUPVAL R9 17
     557 [-]: GETTABLEKS R8 R9 K111 [0x5CD57AED]
     558 [-]: GETIMPORT R9 31 [nil]
     559 [-]: LOADK R10 K112 ["EndMissionScript"]
     560 [-]: CALL R9 1 1  
     561 [-]: LOADB R10 0  
     562 [-]: LOADB R11 1  
     563 [-]: CALL R8 3 0  
L49: 564 [-]: RETURN R0 0  


; Name:            
; Defined at line: 1988
; #Upvalues:       11
; #Parameters:     0
; Is_vararg:       0
; Max Stack Size:  15

       0 [-]: GETIMPORT R0 1 [nil]
       1 [-]: NAMECALL R0 R0 K2 [0x29EF273D]
       2 [-]: CALL R0 1 1  
       3 [-]: NAMECALL R0 R0 K3 [0x66905CB0]
       4 [-]: CALL R0 1 1  
       5 [-]: GETIMPORT R1 5 [nil]
       6 [-]: LOADK R2 K6 ["Survival: Alarm triggered"]
       7 [-]: CALL R1 1 0  
       8 [-]: GETUPVAL R2 0
       9 [-]: GETTABLEKS R1 R2 K7 [0xC506EE83]
      10 [-]: CALL R1 0 0  
      11 [-]: GETIMPORT R1 9 [nil]
      12 [-]: GETIMPORT R2 1 [nil]
      13 [-]: NAMECALL R2 R2 K10 [0x18D05D30]
      14 [-]: CALL R2 1 1  
      15 [-]: JUMPIFNOT R2 L0
      16 [-]: GETUPVAL R4 1
      17 [-]: LOADN R5 1   
      18 [-]: NAMECALL R2 R1 K11 [0x751F061D]
      19 [-]: CALL R2 3 0  
      20 [-]: GETUPVAL R4 2
      21 [-]: LOADN R5 150 
      22 [-]: NAMECALL R2 R1 K11 [0x751F061D]
      23 [-]: CALL R2 3 0  
      24 [-]: JUMP L2
     
L 0:  25 [-]: FASTCALL1 62 R1 L1
      26 [-]: MOVE R3 R1   
      27 [-]: GETIMPORT R2 13 [nil]
      28 [-]: CALL R2 1 1  
L 1:  29 [-]: JUMPIFNOT R2 L2
      30 [-]: GETIMPORT R2 15 [nil]
      31 [-]: LOADN R3 0   
      32 [-]: CALL R2 1 0  
      33 [-]: GETIMPORT R1 9 [nil]
      34 [-]: JUMPBACK L0  
L 2:  35 [-]: GETIMPORT R3 9 [nil]
      36 [-]: NAMECALL R3 R3 K16 [0xEF893AEC]
      37 [-]: CALL R3 1 1  
      38 [-]: GETTABLEKS R4 R3 K17 ["goalTag"]
      39 [-]: GETIMPORT R5 19 [nil]
      40 [-]: LOADK R6 K20 ["LateStartSurvivalMission"]
      41 [-]: CALL R5 1 1  
      42 [-]: JUMPIFNOTEQ R4 R5 L3
      43 [-]: LOADB R2 1   
      44 [-]: JUMP L4
     
L 3:  45 [-]: LOADB R2 0   
      46 [-]: JUMP L4
     
L 4:  47 [-]: JUMPIFNOT R2 L5
      48 [-]: LOADB R4 1   
      49 [-]: NAMECALL R2 R0 K21 [0xE603BAB2]
      50 [-]: CALL R2 2 0  
L 5:  51 [-]: GETIMPORT R2 23 [nil]
      52 [-]: LOADB R4 1   
      53 [-]: NAMECALL R2 R2 K24 [0xB7CBC6FA]
      54 [-]: CALL R2 2 0  
      55 [-]: GETIMPORT R4 19 [nil]
      56 [-]: LOADK R5 K25 ["WaterSpawn"]
      57 [-]: CALL R4 1 -1 
      58 [-]: NAMECALL R2 R0 K26 [0xA7FB023F]
      59 [-]: CALL R2 -1 0 
      60 [-]: GETIMPORT R2 1 [nil]
      61 [-]: GETIMPORT R4 19 [nil]
      62 [-]: LOADK R5 K25 ["WaterSpawn"]
      63 [-]: CALL R4 1 -1 
      64 [-]: NAMECALL R2 R2 K27 [0xC7FCADA9]
      65 [-]: CALL R2 -1 1 
      66 [-]: GETIMPORT R3 29 [nil]
      67 [-]: MOVE R4 R2   
      68 [-]: CALL R3 1 3  
      69 [-]: FORGPREP_INEXT R3 L7
L 6:  70 [-]: LOADK R10 K30 ["Disable"]
      71 [-]: NAMECALL R8 R7 K31 [0x8EB2112D]
      72 [-]: CALL R8 2 0  
L 7:  73 [-]: FORGLOOP R3 L6 2 [inext]
      74 [-]: GETIMPORT R4 9 [nil]
      75 [-]: NAMECALL R4 R4 K16 [0xEF893AEC]
      76 [-]: CALL R4 1 1  
      77 [-]: GETTABLEKS R5 R4 K17 ["goalTag"]
      78 [-]: GETIMPORT R6 19 [nil]
      79 [-]: LOADK R7 K32 ["KuvaSurvival"]
      80 [-]: CALL R6 1 1  
      81 [-]: JUMPIFNOTEQ R5 R6 L8
      82 [-]: LOADB R3 1   
      83 [-]: JUMP L9
     
L 8:  84 [-]: LOADB R3 0   
L 9:  85 [-]: JUMPIFNOT R3 L10
      86 [-]: GETUPVAL R4 3
      87 [-]: GETTABLEKS R3 R4 K33 [0x9742B85B]
      88 [-]: GETIMPORT R4 36 [nil]
      89 [-]: GETIMPORT R5 19 [nil]
      90 [-]: LOADK R6 K37 ["SurvivalLifeSupportCutKuva"]
      91 [-]: CALL R5 1 -1 
      92 [-]: CALL R3 -1 0 
      93 [-]: JUMP L12
    
L10:  94 [-]: GETIMPORT R3 39 [nil]
      95 [-]: JUMPIFNOT R3 L11
      96 [-]: GETIMPORT R3 41 [nil]
      97 [-]: GETIMPORT R4 19 [nil]
      98 [-]: LOADK R5 K42 ["Infestation"]
      99 [-]: CALL R4 1 1  
     100 [-]: JUMPIFNOTEQ R3 R4 L11
     101 [-]: GETUPVAL R4 3
     102 [-]: GETTABLEKS R3 R4 K33 [0x9742B85B]
     103 [-]: GETIMPORT R4 36 [nil]
     104 [-]: GETIMPORT R5 19 [nil]
     105 [-]: LOADK R6 K43 ["SurvivalLifeSupportCutInfested"]
     106 [-]: CALL R5 1 -1 
     107 [-]: CALL R3 -1 0 
     108 [-]: JUMP L12
    
L11: 109 [-]: GETUPVAL R4 3
     110 [-]: GETTABLEKS R3 R4 K33 [0x9742B85B]
     111 [-]: GETIMPORT R4 36 [nil]
     112 [-]: GETIMPORT R5 19 [nil]
     113 [-]: LOADK R6 K44 ["SurvivalLifeSupportCut"]
     114 [-]: CALL R5 1 -1 
     115 [-]: CALL R3 -1 0 
L12: 116 [-]: GETIMPORT R3 45 [nil]
     117 [-]: NAMECALL R4 R1 K46 [0x9DDA54DC]
     118 [-]: CALL R4 1 1  
     119 [-]: SETTABLEKS R4 R3 K47 ["gSurvivalRewardSeed"]
     120 [-]: GETUPVAL R4 4
     121 [-]: GETTABLEKS R3 R4 K48 [0xDC3B2033]
     122 [-]: CALL R3 0 0  
     123 [-]: GETIMPORT R3 15 [nil]
     124 [-]: LOADN R4 2   
     125 [-]: CALL R3 1 0  
     126 [-]: GETIMPORT R1 9 [nil]
L13: 127 [-]: NAMECALL R3 R1 K49 [0x33307F92]
     128 [-]: CALL R3 1 1  
     129 [-]: FASTCALL1 62 R3 L14
     130 [-]: MOVE R5 R3   
     131 [-]: GETIMPORT R4 13 [nil]
     132 [-]: CALL R4 1 1  
L14: 133 [-]: JUMPIF R4 L16
     134 [-]: GETIMPORT R4 51 [nil]
     135 [-]: JUMPXEQKNIL R4 L16
     136 [-]: GETIMPORT R5 53 [nil]
     137 [-]: FASTCALL1 62 R5 L15
     138 [-]: GETIMPORT R4 13 [nil]
     139 [-]: CALL R4 1 1  
L15: 140 [-]: JUMPIFNOT R4 L17
     141 [-]: GETUPVAL R5 4
     142 [-]: GETTABLEKS R4 R5 K54 [0xEA753E99]
     143 [-]: LOADK R5 K55 ["/Lotus/Language/Game/SurvivalProgressBar"]
     144 [-]: LOADN R6 100 
     145 [-]: LOADN R7 100 
     146 [-]: GETIMPORT R8 57 [nil]
     147 [-]: LOADB R9 1   
     148 [-]: CALL R4 5 0  
     149 [-]: JUMP L17
    
L16: 150 [-]: GETIMPORT R4 5 [nil]
     151 [-]: LOADK R5 K58 ["Survival: Waiting for hud to be a thing"]
     152 [-]: CALL R4 1 0  
     153 [-]: GETIMPORT R4 15 [nil]
     154 [-]: LOADK R5 K59 [0.10000000000000001]
     155 [-]: CALL R4 1 0  
     156 [-]: JUMPBACK L13 
L17: 157 [-]: GETIMPORT R3 1 [nil]
     158 [-]: NAMECALL R3 R3 K10 [0x18D05D30]
     159 [-]: CALL R3 1 1  
     160 [-]: JUMPIFNOT R3 L27
     161 [-]: GETIMPORT R3 1 [nil]
     162 [-]: GETIMPORT R5 19 [nil]
     163 [-]: LOADK R6 K60 ["AlarmObjMarker"]
     164 [-]: CALL R5 1 -1 
     165 [-]: NAMECALL R3 R3 K27 [0xC7FCADA9]
     166 [-]: CALL R3 -1 1 
     167 [-]: LOADN R6 1   
     168 [-]: LENGTH R4 R3 
     169 [-]: LOADN R5 1   
     170 [-]: FORNPREP R4 L19
L18: 171 [-]: GETTABLE R7 R3 R6
     172 [-]: NAMECALL R7 R7 K61 [0xF4E253B6]
     173 [-]: CALL R7 1 0  
     174 [-]: FORNLOOP R4 L18
L19: 175 [-]: GETIMPORT R5 9 [nil]
     176 [-]: NAMECALL R5 R5 K16 [0xEF893AEC]
     177 [-]: CALL R5 1 1  
     178 [-]: LOADB R4 1   
     179 [-]: GETTABLEKS R6 R5 K62 ["alertId"]
     180 [-]: JUMPXEQKS R6 K63 L21 NOT [""]
     181 [-]: LOADB R4 1   
     182 [-]: GETTABLEKS R6 R5 K64 ["invasionId"]
     183 [-]: JUMPXEQKS R6 K63 L21 NOT [""]
     184 [-]: GETTABLEKS R6 R5 K65 ["syndicateTag"]
     185 [-]: NAMECALL R6 R6 K66 [0x56C01834]
     186 [-]: CALL R6 1 1  
     187 [-]: MOVE R4 R6   
     188 [-]: JUMPIF R4 L21
     189 [-]: GETTABLEKS R6 R5 K67 ["maxWaveNum"]
     190 [-]: LOADN R7 0   
     191 [-]: JUMPIFLT R7 R6 L20
     192 [-]: LOADB R4 0 +1
L20: 193 [-]: LOADB R4 1   
L21: 194 [-]: JUMPIFNOT R4 L25
     195 [-]: GETUPVAL R6 5
     196 [-]: GETUPVAL R7 6
     197 [-]: GETIMPORT R9 9 [nil]
     198 [-]: NAMECALL R9 R9 K16 [0xEF893AEC]
     199 [-]: CALL R9 1 1  
     200 [-]: GETUPVAL R11 7
     201 [-]: GETTABLEKS R10 R11 K68 [0x06D055F9]
     202 [-]: GETTABLEKS R12 R9 K67 ["maxWaveNum"]
     203 [-]: LOADN R13 0  
     204 [-]: JUMPIFLT R13 R12 L22
     205 [-]: LOADB R11 0 +1
L22: 206 [-]: LOADB R11 1  
L23: 207 [-]: GETTABLEKS R14 R9 K67 ["maxWaveNum"]
     208 [-]: MULK R13 R14 K69 [60]
     209 [-]: FASTCALL2K 19 R13 K70 L24 [3600]
     210 [-]: LOADK R14 K70 [3600]
     211 [-]: GETIMPORT R12 73 [nil]
     212 [-]: CALL R12 2 1 
L24: 213 [-]: LOADN R13 600
     214 [-]: CALL R10 3 1 
     215 [-]: MOVE R8 R10  
     216 [-]: LOADB R9 0   
     217 [-]: LOADB R10 1  
     218 [-]: LOADB R11 0  
     219 [-]: NAMECALL R4 R1 K74 [0xFE23FE59]
     220 [-]: CALL R4 7 0  
     221 [-]: JUMP L26
    
L25: 222 [-]: GETUPVAL R6 5
     223 [-]: GETUPVAL R7 6
     224 [-]: LOADN R8 0   
     225 [-]: LOADB R9 0   
     226 [-]: LOADB R10 1  
     227 [-]: LOADB R11 1  
     228 [-]: NAMECALL R4 R1 K74 [0xFE23FE59]
     229 [-]: CALL R4 7 0  
L26: 230 [-]: GETUPVAL R5 8
     231 [-]: GETTABLEKS R4 R5 K75 [0x5CD57AED]
     232 [-]: GETIMPORT R5 19 [nil]
     233 [-]: LOADK R6 K76 ["RandomArtifactScript"]
     234 [-]: CALL R5 1 1  
     235 [-]: LOADB R6 0   
     236 [-]: LOADB R7 1   
     237 [-]: CALL R4 3 0  
     238 [-]: NAMECALL R4 R1 K77 [0xD040A6D3]
     239 [-]: CALL R4 1 0  
     240 [-]: GETUPVAL R5 4
     241 [-]: GETTABLEKS R4 R5 K78 [0xA1DF01D6]
     242 [-]: LOADK R5 K79 ["/Lotus/Language/Missions/MissionName_Survival"]
     243 [-]: LOADN R6 0   
     244 [-]: CALL R4 2 0  
     245 [-]: GETIMPORT R4 15 [nil]
     246 [-]: LOADN R5 1   
     247 [-]: CALL R4 1 0  
     248 [-]: GETUPVAL R4 9
     249 [-]: CALL R4 0 0  
     250 [-]: RETURN R0 0  
L27: 251 [-]: GETIMPORT R3 15 [nil]
     252 [-]: LOADN R4 1   
     253 [-]: CALL R3 1 0  
     254 [-]: GETUPVAL R3 10
     255 [-]: CALL R3 0 0  
     256 [-]: RETURN R0 0  


; Name:            
; Defined at line: 2075
; #Upvalues:       1
; #Parameters:     3
; Is_vararg:       0
; Max Stack Size:  11

       0 [-]: GETIMPORT R3 1 [nil]
       1 [-]: GETIMPORT R5 3 [nil]
       2 [-]: LOADK R6 K4 ["DoorHint"]
       3 [-]: CALL R5 1 -1 
       4 [-]: NAMECALL R3 R3 K5 [0xC7FCADA9]
       5 [-]: CALL R3 -1 1 
       6 [-]: FASTCALL1 62 R0 L0
       7 [-]: MOVE R5 R0   
       8 [-]: GETIMPORT R4 7 [nil]
       9 [-]: CALL R4 1 1  
L 0:  10 [-]: JUMPIFNOT R4 L1
      11 [-]: RETURN R0 0  
L 1:  12 [-]: NAMECALL R5 R0 K8 [0xFA9E477F]
      13 [-]: CALL R5 1 1  
      14 [-]: FASTCALL1 62 R5 L2
      15 [-]: GETIMPORT R4 7 [nil]
      16 [-]: CALL R4 1 1  
L 2:  17 [-]: JUMPIF R4 L3 
      18 [-]: LOADN R1 1   
L 3:  19 [-]: JUMPXEQKNIL R1 L4 NOT
      20 [-]: LOADN R1 1   
L 4:  21 [-]: JUMPXEQKN R1 K9 L17 NOT [1]
      22 [-]: GETUPVAL R5 0
      23 [-]: GETTABLEKS R4 R5 K10 [0x5CD57AED]
      24 [-]: GETIMPORT R5 3 [nil]
      25 [-]: LOADK R6 K11 ["StartSurvival"]
      26 [-]: CALL R5 1 1  
      27 [-]: LOADB R6 0   
      28 [-]: LOADB R7 1   
      29 [-]: CALL R4 3 0  
      30 [-]: GETIMPORT R5 13 [nil]
      31 [-]: FASTCALL1 62 R5 L5
      32 [-]: GETIMPORT R4 7 [nil]
      33 [-]: CALL R4 1 1  
L 5:  34 [-]: JUMPIF R4 L8 
      35 [-]: GETIMPORT R5 15 [nil]
      36 [-]: FASTCALL1 62 R5 L6
      37 [-]: GETIMPORT R4 7 [nil]
      38 [-]: CALL R4 1 1  
L 6:  39 [-]: JUMPIF R4 L7 
      40 [-]: GETIMPORT R4 13 [nil]
      41 [-]: GETIMPORT R6 17 [nil]
      42 [-]: GETIMPORT R7 15 [nil]
      43 [-]: NAMECALL R4 R4 K18 [0xCDDC3ABB]
      44 [-]: CALL R4 3 0  
L 7:  45 [-]: GETIMPORT R4 13 [nil]
      46 [-]: GETIMPORT R6 20 [nil]
      47 [-]: LOADB R7 0   
      48 [-]: LOADN R8 0   
      49 [-]: LOADB R9 1   
      50 [-]: NAMECALL R4 R4 K21 [0x659D451F]
      51 [-]: CALL R4 5 0  
L 8:  52 [-]: LOADK R6 K22 ["Disable"]
      53 [-]: NAMECALL R4 R2 K23 [0x8EB2112D]
      54 [-]: CALL R4 2 0  
      55 [-]: GETIMPORT R5 25 [nil]
      56 [-]: FASTCALL1 62 R5 L9
      57 [-]: GETIMPORT R4 7 [nil]
      58 [-]: CALL R4 1 1  
L 9:  59 [-]: JUMPIF R4 L10
      60 [-]: GETIMPORT R4 25 [nil]
      61 [-]: LOADK R6 K22 ["Disable"]
      62 [-]: NAMECALL R4 R4 K23 [0x8EB2112D]
      63 [-]: CALL R4 2 0  
L10:  64 [-]: GETIMPORT R5 27 [nil]
      65 [-]: FASTCALL1 62 R5 L11
      66 [-]: GETIMPORT R4 7 [nil]
      67 [-]: CALL R4 1 1  
L11:  68 [-]: JUMPIF R4 L12
      69 [-]: GETIMPORT R4 27 [nil]
      70 [-]: LOADK R6 K28 ["TurnOff"]
      71 [-]: NAMECALL R4 R4 K23 [0x8EB2112D]
      72 [-]: CALL R4 2 0  
L12:  73 [-]: FASTCALL1 62 R3 L13
      74 [-]: MOVE R5 R3   
      75 [-]: GETIMPORT R4 7 [nil]
      76 [-]: CALL R4 1 1  
L13:  77 [-]: JUMPIF R4 L15
      78 [-]: LOADN R6 1   
      79 [-]: LENGTH R4 R3 
      80 [-]: LOADN R5 1   
      81 [-]: FORNPREP R4 L15
L14:  82 [-]: GETTABLE R7 R3 R6
      83 [-]: LOADK R9 K29 ["Unlock"]
      84 [-]: NAMECALL R7 R7 K23 [0x8EB2112D]
      85 [-]: CALL R7 2 0  
      86 [-]: FORNLOOP R4 L14
L15:  87 [-]: GETIMPORT R4 1 [nil]
      88 [-]: GETIMPORT R6 3 [nil]
      89 [-]: LOADK R7 K30 ["SurvivalDoor"]
      90 [-]: CALL R6 1 -1 
      91 [-]: NAMECALL R4 R4 K5 [0xC7FCADA9]
      92 [-]: CALL R4 -1 1 
      93 [-]: LOADN R7 1   
      94 [-]: LENGTH R5 R4 
      95 [-]: LOADN R6 1   
      96 [-]: FORNPREP R5 L17
L16:  97 [-]: GETTABLE R8 R4 R7
      98 [-]: LOADK R10 K31 ["Start"]
      99 [-]: NAMECALL R8 R8 K23 [0x8EB2112D]
     100 [-]: CALL R8 2 0  
     101 [-]: FORNLOOP R5 L16
L17: 102 [-]: RETURN R0 0  


; Name:            
; Defined at line: 2122
; #Upvalues:       0
; #Parameters:     0
; Is_vararg:       0
; Max Stack Size:  9

       0 [-]: GETIMPORT R0 1 [nil]
       1 [-]: NAMECALL R0 R0 K2 [0x8B5B1F58]
       2 [-]: CALL R0 1 1  
       3 [-]: LOADNIL R1   
       4 [-]: LOADN R4 1   
       5 [-]: LENGTH R2 R0 
       6 [-]: LOADN R3 1   
       7 [-]: FORNPREP R2 L3
L 0:   8 [-]: GETTABLE R6 R0 R4
       9 [-]: FASTCALL1 62 R6 L1
      10 [-]: GETIMPORT R5 4 [nil]
      11 [-]: CALL R5 1 1  
L 1:  12 [-]: JUMPIF R5 L2 
      13 [-]: GETTABLE R5 R0 R4
      14 [-]: NAMECALL R5 R5 K5 [0x2047CFE7]
      15 [-]: CALL R5 1 1  
      16 [-]: JUMPIF R5 L2 
      17 [-]: GETTABLE R1 R0 R4
      18 [-]: JUMP L3
     
L 2:  19 [-]: FORNLOOP R2 L0
L 3:  20 [-]: FASTCALL1 62 R1 L4
      21 [-]: MOVE R3 R1   
      22 [-]: GETIMPORT R2 4 [nil]
      23 [-]: CALL R2 1 1  
L 4:  24 [-]: JUMPIFNOT R2 L5
      25 [-]: LOADB R2 0   
      26 [-]: RETURN R2 1  
L 5:  27 [-]: GETIMPORT R2 1 [nil]
      28 [-]: GETIMPORT R4 7 [nil]
      29 [-]: LOADK R5 K8 ["/Lotus/Types/Actions/SurvivalHackAction"]
      30 [-]: CALL R4 1 -1 
      31 [-]: NAMECALL R2 R2 K9 [0xFB669000]
      32 [-]: CALL R2 -1 1 
      33 [-]: LOADN R5 1   
      34 [-]: LENGTH R3 R2 
      35 [-]: LOADN R4 1   
      36 [-]: FORNPREP R3 L9
L 6:  37 [-]: GETTABLE R7 R2 R5
      38 [-]: FASTCALL1 62 R7 L7
      39 [-]: GETIMPORT R6 4 [nil]
      40 [-]: CALL R6 1 1  
L 7:  41 [-]: JUMPIF R6 L8 
      42 [-]: GETTABLE R6 R2 R5
      43 [-]: NAMECALL R6 R6 K10 [0xF37943FF]
      44 [-]: CALL R6 1 1  
      45 [-]: JUMPIFNOT R6 L8
      46 [-]: GETTABLE R6 R2 R5
      47 [-]: LOADN R8 1   
      48 [-]: NAMECALL R6 R6 K11 [0x9A558B01]
      49 [-]: CALL R6 2 0  
      50 [-]: GETTABLE R6 R2 R5
      51 [-]: MOVE R8 R1   
      52 [-]: NAMECALL R6 R6 K12 [0x6C79D32F]
      53 [-]: CALL R6 2 0  
      54 [-]: GETTABLE R6 R2 R5
      55 [-]: NAMECALL R6 R6 K13 [0xF4E253B6]
      56 [-]: CALL R6 1 0  
      57 [-]: LOADB R6 1   
      58 [-]: RETURN R6 1  
L 8:  59 [-]: FORNLOOP R3 L6
L 9:  60 [-]: LOADB R3 0   
      61 [-]: RETURN R3 1  


; Name:            
; Defined at line: 2152
; #Upvalues:       13
; #Parameters:     1
; Is_vararg:       0
; Max Stack Size:  22

       0 [-]: GETIMPORT R1 1 [nil]
       1 [-]: LOADB R2 0   
       2 [-]: SETTABLEKS R2 R1 K2 ["AllowWrinkles"]
       3 [-]: GETIMPORT R1 1 [nil]
       4 [-]: LOADB R2 1   
       5 [-]: SETTABLEKS R2 R1 K3 ["gSkipExtractionTimer"]
       6 [-]: GETIMPORT R1 5 [nil]
       7 [-]: JUMPIFNOT R1 L0
       8 [-]: RETURN R0 0  
L 0:   9 [-]: GETIMPORT R1 7 [nil]
      10 [-]: LOADK R2 K8 ["Survival: Mission started"]
      11 [-]: CALL R1 1 0  
      12 [-]: GETIMPORT R1 10 [nil]
      13 [-]: NAMECALL R1 R1 K11 [0x18D05D30]
      14 [-]: CALL R1 1 1  
      15 [-]: JUMPIFNOT R1 L42
      16 [-]: GETIMPORT R2 13 [nil]
      17 [-]: NAMECALL R2 R2 K14 [0xEF893AEC]
      18 [-]: CALL R2 1 1  
      19 [-]: GETTABLEKS R3 R2 K15 ["goalTag"]
      20 [-]: GETIMPORT R4 17 [nil]
      21 [-]: LOADK R5 K18 ["LateStartSurvivalMission"]
      22 [-]: CALL R4 1 1  
      23 [-]: JUMPIFNOTEQ R3 R4 L1
      24 [-]: LOADB R1 1   
      25 [-]: JUMP L2
     
L 1:  26 [-]: LOADB R1 0   
      27 [-]: JUMP L2
     
L 2:  28 [-]: GETIMPORT R3 13 [nil]
      29 [-]: NAMECALL R3 R3 K14 [0xEF893AEC]
      30 [-]: CALL R3 1 1  
      31 [-]: GETTABLEKS R4 R3 K15 ["goalTag"]
      32 [-]: GETIMPORT R5 17 [nil]
      33 [-]: LOADK R6 K19 ["KuvaSurvival"]
      34 [-]: CALL R5 1 1  
      35 [-]: JUMPIFNOTEQ R4 R5 L3
      36 [-]: LOADB R2 1   
      37 [-]: JUMP L4
     
L 3:  38 [-]: LOADB R2 0   
L 4:  39 [-]: GETUPVAL R4 0
      40 [-]: GETTABLEKS R3 R4 K20 [0x59F914CD]
      41 [-]: GETIMPORT R4 22 [nil]
      42 [-]: CALL R3 1 0  
      43 [-]: JUMPIFNOT R2 L5
      44 [-]: GETUPVAL R4 0
      45 [-]: GETTABLEKS R3 R4 K23 [0x9742B85B]
      46 [-]: GETIMPORT R4 25 [nil]
      47 [-]: GETIMPORT R5 17 [nil]
      48 [-]: LOADK R6 K26 ["ObjectiveStartKuva"]
      49 [-]: CALL R5 1 -1 
      50 [-]: CALL R3 -1 0 
      51 [-]: JUMP L7
     
L 5:  52 [-]: GETIMPORT R3 28 [nil]
      53 [-]: JUMPIFNOT R3 L6
      54 [-]: GETIMPORT R3 30 [nil]
      55 [-]: GETIMPORT R4 17 [nil]
      56 [-]: LOADK R5 K31 ["Infestation"]
      57 [-]: CALL R4 1 1  
      58 [-]: JUMPIFNOTEQ R3 R4 L6
      59 [-]: GETUPVAL R4 0
      60 [-]: GETTABLEKS R3 R4 K23 [0x9742B85B]
      61 [-]: GETIMPORT R4 25 [nil]
      62 [-]: GETIMPORT R5 17 [nil]
      63 [-]: LOADK R6 K32 ["ObjectiveStartInfested"]
      64 [-]: CALL R5 1 -1 
      65 [-]: CALL R3 -1 0 
      66 [-]: JUMP L7
     
L 6:  67 [-]: GETUPVAL R4 0
      68 [-]: GETTABLEKS R3 R4 K23 [0x9742B85B]
      69 [-]: GETIMPORT R4 25 [nil]
      70 [-]: GETIMPORT R5 17 [nil]
      71 [-]: LOADK R6 K33 ["ObjectiveStart"]
      72 [-]: CALL R5 1 -1 
      73 [-]: CALL R3 -1 0 
L 7:  74 [-]: JUMPIF R1 L10
      75 [-]: GETIMPORT R3 10 [nil]
      76 [-]: GETIMPORT R5 17 [nil]
      77 [-]: LOADK R6 K34 ["DoorHint"]
      78 [-]: CALL R5 1 -1 
      79 [-]: NAMECALL R3 R3 K35 [0xC7FCADA9]
      80 [-]: CALL R3 -1 1 
      81 [-]: FASTCALL1 62 R3 L8
      82 [-]: MOVE R5 R3   
      83 [-]: GETIMPORT R4 37 [nil]
      84 [-]: CALL R4 1 1  
L 8:  85 [-]: JUMPIF R4 L10
      86 [-]: LOADN R6 1   
      87 [-]: LENGTH R4 R3 
      88 [-]: LOADN R5 1   
      89 [-]: FORNPREP R4 L10
L 9:  90 [-]: GETTABLE R7 R3 R6
      91 [-]: LOADK R9 K38 ["Lock"]
      92 [-]: NAMECALL R7 R7 K39 [0x8EB2112D]
      93 [-]: CALL R7 2 0  
      94 [-]: FORNLOOP R4 L9
L10:  95 [-]: GETIMPORT R3 10 [nil]
      96 [-]: GETIMPORT R5 17 [nil]
      97 [-]: LOADK R6 K40 ["SurvivalSetupForwarder"]
      98 [-]: CALL R5 1 -1 
      99 [-]: NAMECALL R3 R3 K35 [0xC7FCADA9]
     100 [-]: CALL R3 -1 1 
     101 [-]: GETIMPORT R4 42 [nil]
     102 [-]: MOVE R5 R3   
     103 [-]: CALL R4 1 3  
     104 [-]: FORGPREP_INEXT R4 L12
L11: 105 [-]: LOADK R11 K43 ["TriggerPort"]
     106 [-]: NAMECALL R9 R8 K39 [0x8EB2112D]
     107 [-]: CALL R9 2 0  
L12: 108 [-]: FORGLOOP R4 L11 2 [inext]
     109 [-]: JUMPIF R1 L13
     110 [-]: GETUPVAL R5 1
     111 [-]: GETTABLEKS R4 R5 K44 [0xA1DF01D6]
     112 [-]: LOADK R5 K45 ["/Lotus/Language/Objectives/SurvivalTriggerAlarm"]
     113 [-]: CALL R4 1 0  
L13: 114 [-]: GETIMPORT R4 10 [nil]
     115 [-]: GETIMPORT R6 17 [nil]
     116 [-]: LOADK R7 K46 ["BreakableOnPath"]
     117 [-]: CALL R6 1 -1 
     118 [-]: NAMECALL R4 R4 K35 [0xC7FCADA9]
     119 [-]: CALL R4 -1 1 
     120 [-]: LOADN R7 1   
     121 [-]: LENGTH R5 R4 
     122 [-]: LOADN R6 1   
     123 [-]: FORNPREP R5 L15
L14: 124 [-]: GETTABLE R8 R4 R7
     125 [-]: LOADK R10 K47 ["Destroy"]
     126 [-]: NAMECALL R8 R8 K39 [0x8EB2112D]
     127 [-]: CALL R8 2 0  
     128 [-]: FORNLOOP R5 L14
L15: 129 [-]: GETIMPORT R5 10 [nil]
     130 [-]: NAMECALL R5 R5 K48 [0x29EF273D]
     131 [-]: CALL R5 1 1  
     132 [-]: NAMECALL R6 R5 K49 [0x66905CB0]
     133 [-]: CALL R6 1 1  
     134 [-]: GETIMPORT R7 13 [nil]
     135 [-]: LOADB R10 1  
     136 [-]: NAMECALL R8 R6 K50 [0x383D2E7D]
     137 [-]: CALL R8 2 0  
     138 [-]: JUMPIFNOT R1 L16
     139 [-]: LOADB R10 1  
     140 [-]: NAMECALL R8 R6 K51 [0x2FAEAD12]
     141 [-]: CALL R8 2 0  
     142 [-]: JUMP L17
    
L16: 143 [-]: LOADB R10 0  
     144 [-]: NAMECALL R8 R6 K51 [0x2FAEAD12]
     145 [-]: CALL R8 2 0  
     146 [-]: LOADB R10 1  
     147 [-]: NAMECALL R8 R6 K52 [0xE603BAB2]
     148 [-]: CALL R8 2 0  
L17: 149 [-]: LOADN R10 0  
     150 [-]: NAMECALL R8 R6 K53 [0x3EA76F0C]
     151 [-]: CALL R8 2 0  
     152 [-]: GETUPVAL R10 2
     153 [-]: LOADN R11 0  
     154 [-]: NAMECALL R8 R7 K54 [0x751F061D]
     155 [-]: CALL R8 3 0  
     156 [-]: LOADB R10 0  
     157 [-]: NAMECALL R8 R6 K55 [0x911CE2B4]
     158 [-]: CALL R8 2 0  
     159 [-]: GETIMPORT R8 10 [nil]
     160 [-]: GETIMPORT R10 17 [nil]
     161 [-]: LOADK R11 K56 ["SurvivalArtifactSpawn"]
     162 [-]: CALL R10 1 -1
     163 [-]: NAMECALL R8 R8 K35 [0xC7FCADA9]
     164 [-]: CALL R8 -1 1 
     165 [-]: NEWTABLE R9 0 0
     166 [-]: GETIMPORT R10 42 [nil]
     167 [-]: MOVE R11 R8  
     168 [-]: CALL R10 1 3 
     169 [-]: FORGPREP_INEXT R10 L21
L18: 170 [-]: NAMECALL R15 R14 K57 [0xE79E7EF4]
     171 [-]: CALL R15 1 1 
     172 [-]: FASTCALL1 62 R15 L19
     173 [-]: MOVE R17 R15 
     174 [-]: GETIMPORT R16 37 [nil]
     175 [-]: CALL R16 1 1 
L19: 176 [-]: JUMPIF R16 L21
     177 [-]: NAMECALL R16 R15 K58 [0x22DA1852]
     178 [-]: CALL R16 1 1 
     179 [-]: GETIMPORT R17 17 [nil]
     180 [-]: LOADK R18 K59 ["Intermediate"]
     181 [-]: CALL R17 1 1 
     182 [-]: JUMPIFEQ R16 R17 L20
     183 [-]: GETIMPORT R17 17 [nil]
     184 [-]: LOADK R18 K60 ["Boss"]
     185 [-]: CALL R17 1 1 
     186 [-]: JUMPIFNOTEQ R16 R17 L21
L20: 187 [-]: GETIMPORT R17 62 [nil]
     188 [-]: JUMPIFEQ R14 R17 L21
     189 [-]: FASTCALL2 52 R9 R14 L21
     190 [-]: MOVE R18 R9  
     191 [-]: MOVE R19 R14 
     192 [-]: GETIMPORT R17 65 [nil]
     193 [-]: CALL R17 2 0 
L21: 194 [-]: FORGLOOP R10 L18 2 [inext]
     195 [-]: GETIMPORT R10 67 [nil]
     196 [-]: GETIMPORT R12 13 [nil]
     197 [-]: NAMECALL R12 R12 K14 [0xEF893AEC]
     198 [-]: CALL R12 1 1 
     199 [-]: GETTABLEKS R13 R12 K15 ["goalTag"]
     200 [-]: GETIMPORT R14 17 [nil]
     201 [-]: LOADK R15 K19 ["KuvaSurvival"]
     202 [-]: CALL R14 1 1 
     203 [-]: JUMPIFNOTEQ R13 R14 L22
     204 [-]: LOADB R11 1  
     205 [-]: JUMP L23
    
L22: 206 [-]: LOADB R11 0  
L23: 207 [-]: JUMPIFNOT R11 L24
     208 [-]: GETIMPORT R10 69 [nil]
L24: 209 [-]: GETIMPORT R11 42 [nil]
     210 [-]: MOVE R12 R9  
     211 [-]: CALL R11 1 3 
     212 [-]: FORGPREP_INEXT R11 L26
L25: 213 [-]: GETIMPORT R16 10 [nil]
     214 [-]: MOVE R18 R10 
     215 [-]: NAMECALL R19 R15 K70 [0xD1586535]
     216 [-]: CALL R19 1 1 
     217 [-]: NAMECALL R20 R15 K71 [0xCB3851B8]
     218 [-]: CALL R20 1 -1
     219 [-]: NAMECALL R16 R16 K72 [0x05909209]
     220 [-]: CALL R16 -1 0
L26: 221 [-]: FORGLOOP R11 L25 2 [inext]
     222 [-]: GETIMPORT R11 7 [nil]
     223 [-]: LOADK R13 K73 ["Survival: "]
     224 [-]: LENGTH R14 R9
     225 [-]: LOADK R15 K74 [" valid life support spawns available."]
     226 [-]: CONCAT R12 R13 R15
     227 [-]: CALL R11 1 0 
     228 [-]: GETUPVAL R13 3
     229 [-]: LENGTH R14 R9
     230 [-]: NAMECALL R11 R7 K54 [0x751F061D]
     231 [-]: CALL R11 3 0 
     232 [-]: GETIMPORT R11 17 [nil]
     233 [-]: LOADK R12 K75 ["Spawn"]
     234 [-]: CALL R11 1 1 
     235 [-]: JUMPIFNOT R1 L27
     236 [-]: GETIMPORT R12 17 [nil]
     237 [-]: LOADK R13 K59 ["Intermediate"]
     238 [-]: CALL R12 1 1 
     239 [-]: MOVE R11 R12 
L27: 240 [-]: GETIMPORT R12 10 [nil]
     241 [-]: GETIMPORT R14 17 [nil]
     242 [-]: LOADK R15 K76 ["AlarmObjMarker"]
     243 [-]: CALL R14 1 -1
     244 [-]: NAMECALL R12 R12 K35 [0xC7FCADA9]
     245 [-]: CALL R12 -1 1
     246 [-]: LOADNIL R13  
     247 [-]: LOADN R16 1  
     248 [-]: LENGTH R14 R12
     249 [-]: LOADN R15 1  
     250 [-]: FORNPREP R14 L30
L28: 251 [-]: GETTABLE R17 R12 R16
     252 [-]: NAMECALL R17 R17 K57 [0xE79E7EF4]
     253 [-]: CALL R17 1 1 
     254 [-]: NAMECALL R18 R17 K58 [0x22DA1852]
     255 [-]: CALL R18 1 1 
     256 [-]: JUMPIFNOTEQ R18 R11 L29
     257 [-]: GETTABLE R13 R12 R16
     258 [-]: JUMP L30
    
L29: 259 [-]: FORNLOOP R14 L28
L30: 260 [-]: NAMECALL R14 R13 K50 [0x383D2E7D]
     261 [-]: CALL R14 1 0 
     262 [-]: MOVE R16 R13 
     263 [-]: NAMECALL R14 R6 K77 [0xE2871589]
     264 [-]: CALL R14 2 0 
     265 [-]: GETUPVAL R15 4
     266 [-]: GETTABLEKS R14 R15 K78 [0x5CD57AED]
     267 [-]: GETIMPORT R15 17 [nil]
     268 [-]: LOADK R16 K79 ["SurvivalFog"]
     269 [-]: CALL R15 1 1 
     270 [-]: LOADB R16 0  
     271 [-]: LOADB R17 1  
     272 [-]: CALL R14 3 0 
     273 [-]: GETUPVAL R15 4
     274 [-]: GETTABLEKS R14 R15 K80 [0xEDCEF9D4]
     275 [-]: CALL R14 0 0 
     276 [-]: GETIMPORT R15 13 [nil]
     277 [-]: NAMECALL R15 R15 K14 [0xEF893AEC]
     278 [-]: CALL R15 1 1 
     279 [-]: LOADB R14 1  
     280 [-]: GETTABLEKS R16 R15 K81 ["alertId"]
     281 [-]: JUMPXEQKS R16 K82 L32 NOT [""]
     282 [-]: LOADB R14 1  
     283 [-]: GETTABLEKS R16 R15 K83 ["invasionId"]
     284 [-]: JUMPXEQKS R16 K82 L32 NOT [""]
     285 [-]: GETTABLEKS R16 R15 K84 ["syndicateTag"]
     286 [-]: NAMECALL R16 R16 K85 [0x56C01834]
     287 [-]: CALL R16 1 1 
     288 [-]: MOVE R14 R16 
     289 [-]: JUMPIF R14 L32
     290 [-]: GETTABLEKS R16 R15 K86 ["maxWaveNum"]
     291 [-]: LOADN R17 0  
     292 [-]: JUMPIFLT R17 R16 L31
     293 [-]: LOADB R14 0 +1
L31: 294 [-]: LOADB R14 1  
L32: 295 [-]: JUMPIF R14 L34
     296 [-]: GETUPVAL R15 5
     297 [-]: GETTABLEKS R14 R15 K87 [0x4E6C2326]
     298 [-]: LOADK R15 K88 ["SurvivalSpy"]
     299 [-]: CALL R14 1 0 
     300 [-]: GETUPVAL R15 5
     301 [-]: GETTABLEKS R14 R15 K89 [0x17D4853A]
     302 [-]: LOADK R15 K88 ["SurvivalSpy"]
     303 [-]: LOADK R16 K90 ["Vaults"]
     304 [-]: GETUPVAL R17 6
     305 [-]: CALL R14 3 0 
     306 [-]: GETIMPORT R14 1 [nil]
     307 [-]: GETIMPORT R15 92 [nil]
     308 [-]: JUMPIF R15 L33
     309 [-]: NEWTABLE R15 0 0
L33: 310 [-]: SETTABLEKS R15 R14 K91 ["AllPlayersExtractingCallbacks"]
     311 [-]: GETIMPORT R15 92 [nil]
     312 [-]: GETUPVAL R16 7
     313 [-]: FASTCALL2 52 R15 R16 L34
     314 [-]: GETIMPORT R14 65 [nil]
     315 [-]: CALL R14 2 0 
L34: 316 [-]: GETIMPORT R14 94 [nil]
     317 [-]: LOADN R15 0  
     318 [-]: JUMPIFNOTLT R15 R14 L42
     319 [-]: LOADN R14 0  
L35: 320 [-]: GETUPVAL R17 8
     321 [-]: NAMECALL R15 R7 K95 [0x0EB34C69]
     322 [-]: CALL R15 2 1 
     323 [-]: JUMPXEQKN R15 K96 L42 NOT [0]
     324 [-]: GETIMPORT R15 98 [nil]
     325 [-]: CALL R15 0 1 
     326 [-]: ADD R14 R14 R15
     327 [-]: GETIMPORT R15 94 [nil]
     328 [-]: JUMPIFNOTLT R15 R14 L39
     329 [-]: GETUPVAL R16 5
     330 [-]: GETTABLEKS R15 R16 K99 [0xC506EE83]
     331 [-]: CALL R15 0 0 
L36: 332 [-]: GETUPVAL R16 5
     333 [-]: GETTABLEKS R15 R16 K100 [0x087BDEAB]
     334 [-]: CALL R15 0 1 
     335 [-]: JUMPIFNOT R15 L37
     336 [-]: GETIMPORT R15 102 [nil]
     337 [-]: LOADN R16 0  
     338 [-]: CALL R15 1 0 
     339 [-]: JUMPBACK L36 
L37: 340 [-]: GETUPVAL R15 9
     341 [-]: CALL R15 0 1 
     342 [-]: JUMPIFNOT R15 L38
     343 [-]: JUMP L42
    
L38: 344 [-]: GETUPVAL R16 5
     345 [-]: GETTABLEKS R15 R16 K103 [0xAD362F29]
     346 [-]: GETUPVAL R17 5
     347 [-]: GETTABLEKS R16 R17 K104 ["INITIATOR_FAILURE"]
     348 [-]: CALL R15 1 0 
     349 [-]: GETIMPORT R15 13 [nil]
     350 [-]: LOADN R17 0  
     351 [-]: NAMECALL R15 R15 K105 [0xF9BFC5D9]
     352 [-]: CALL R15 2 0 
     353 [-]: RETURN R0 0  
L39: 354 [-]: GETUPVAL R16 5
     355 [-]: GETTABLEKS R15 R16 K100 [0x087BDEAB]
     356 [-]: CALL R15 0 1 
     357 [-]: JUMPIFNOT R15 L40
     358 [-]: GETUPVAL R16 10
     359 [-]: JUMPIF R16 L40
     360 [-]: GETUPVAL R16 11
     361 [-]: CALL R16 0 0 
     362 [-]: JUMP L41
    
L40: 363 [-]: JUMPIF R15 L41
     364 [-]: GETUPVAL R16 10
     365 [-]: JUMPIFNOT R16 L41
     366 [-]: GETUPVAL R16 12
     367 [-]: CALL R16 0 0 
L41: 368 [-]: GETIMPORT R16 102 [nil]
     369 [-]: LOADN R17 0  
     370 [-]: CALL R16 1 0 
     371 [-]: JUMPBACK L35 
L42: 372 [-]: GETIMPORT R1 10 [nil]
     373 [-]: NAMECALL R1 R1 K11 [0x18D05D30]
     374 [-]: CALL R1 1 1  
     375 [-]: JUMPIFNOT R1 L43
     376 [-]: GETUPVAL R2 4
     377 [-]: GETTABLEKS R1 R2 K78 [0x5CD57AED]
     378 [-]: GETIMPORT R2 17 [nil]
     379 [-]: LOADK R3 K106 ["SurvivalHudScript"]
     380 [-]: CALL R2 1 1  
     381 [-]: LOADB R3 0   
     382 [-]: LOADB R4 1   
     383 [-]: CALL R1 3 0  
L43: 384 [-]: RETURN R0 0  


; Name:            
; Defined at line: 2312
; #Upvalues:       11
; #Parameters:     1
; Is_vararg:       0
; Max Stack Size:  27

       0 [-]: GETIMPORT R1 1 [nil]
       1 [-]: NAMECALL R1 R1 K2 [0x18D05D30]
       2 [-]: CALL R1 1 1  
       3 [-]: JUMPIFNOT R1 L0
       4 [-]: GETIMPORT R1 4 [nil]
       5 [-]: GETUPVAL R3 0
       6 [-]: LOADN R4 4   
       7 [-]: NAMECALL R1 R1 K5 [0x751F061D]
       8 [-]: CALL R1 3 0  
L 0:   9 [-]: GETIMPORT R1 4 [nil]
      10 [-]: GETIMPORT R2 8 [nil]
      11 [-]: JUMPIFNOT R2 L1
      12 [-]: GETIMPORT R2 10 [nil]
      13 [-]: GETIMPORT R3 8 [nil]
      14 [-]: CALL R2 1 0  
      15 [-]: GETIMPORT R2 11 [nil]
      16 [-]: LOADNIL R3   
      17 [-]: SETTABLEKS R3 R2 K7 ["LifeSupportBar"]
L 1:  18 [-]: GETUPVAL R4 1
      19 [-]: NAMECALL R2 R1 K12 [0x0EB34C69]
      20 [-]: CALL R2 2 1  
      21 [-]: GETIMPORT R3 14 [nil]
      22 [-]: LOADK R5 K15 ["Survival: Life support ran out at "]
      23 [-]: MOVE R6 R2   
      24 [-]: CONCAT R4 R5 R6
      25 [-]: CALL R3 1 0  
      26 [-]: GETUPVAL R5 2
      27 [-]: GETIMPORT R6 17 [nil]
      28 [-]: CALL R6 0 1  
      29 [-]: LOADN R7 -1  
      30 [-]: LOADB R8 0   
      31 [-]: LOADB R9 0   
      32 [-]: NAMECALL R3 R1 K18 [0xFE23FE59]
      33 [-]: CALL R3 6 0  
      34 [-]: GETIMPORT R3 11 [nil]
      35 [-]: LOADB R4 0   
      36 [-]: SETTABLEKS R4 R3 K19 ["gSkipExtractionTimer"]
      37 [-]: GETUPVAL R4 3
      38 [-]: GETTABLEKS R3 R4 K20 [0xCC6A9F67]
      39 [-]: CALL R3 0 0  
      40 [-]: GETUPVAL R4 4
      41 [-]: GETTABLEKS R3 R4 K21 [0x7E1C98B2]
      42 [-]: CALL R3 0 1  
      43 [-]: LOADN R6 0   
      44 [-]: NAMECALL R4 R3 K22 [0xBF4030D2]
      45 [-]: CALL R4 2 0  
      46 [-]: GETIMPORT R4 1 [nil]
      47 [-]: NAMECALL R4 R4 K2 [0x18D05D30]
      48 [-]: CALL R4 1 1  
      49 [-]: JUMPIFNOT R4 L40
      50 [-]: GETUPVAL R5 4
      51 [-]: GETTABLEKS R4 R5 K23 [0x203C8F48]
      52 [-]: LOADB R5 1   
      53 [-]: CALL R4 1 0  
      54 [-]: GETIMPORT R4 1 [nil]
      55 [-]: GETIMPORT R6 25 [nil]
      56 [-]: NAMECALL R4 R4 K26 [0xFB669000]
      57 [-]: CALL R4 2 1  
      58 [-]: LOADN R7 1   
      59 [-]: LENGTH R5 R4 
      60 [-]: LOADN R6 1   
      61 [-]: FORNPREP R5 L3
L 2:  62 [-]: GETTABLE R8 R4 R7
      63 [-]: LOADK R10 K27 ["Disable"]
      64 [-]: NAMECALL R8 R8 K28 [0x8EB2112D]
      65 [-]: CALL R8 2 0  
      66 [-]: FORNLOOP R5 L2
L 3:  67 [-]: GETIMPORT R5 1 [nil]
      68 [-]: GETIMPORT R7 17 [nil]
      69 [-]: LOADK R8 K29 ["ArtifactDeco"]
      70 [-]: CALL R7 1 -1 
      71 [-]: NAMECALL R5 R5 K30 [0xC7FCADA9]
      72 [-]: CALL R5 -1 1 
      73 [-]: LOADN R8 1   
      74 [-]: LENGTH R6 R5 
      75 [-]: LOADN R7 1   
      76 [-]: FORNPREP R6 L5
L 4:  77 [-]: GETTABLE R9 R5 R8
      78 [-]: LOADK R11 K31 ["Hide"]
      79 [-]: NAMECALL R9 R9 K28 [0x8EB2112D]
      80 [-]: CALL R9 2 0  
      81 [-]: FORNLOOP R6 L4
L 5:  82 [-]: GETIMPORT R6 1 [nil]
      83 [-]: GETIMPORT R8 33 [nil]
      84 [-]: NAMECALL R6 R6 K26 [0xFB669000]
      85 [-]: CALL R6 2 1  
      86 [-]: LOADN R9 1   
      87 [-]: LENGTH R7 R6 
      88 [-]: LOADN R8 1   
      89 [-]: FORNPREP R7 L7
L 6:  90 [-]: GETTABLE R10 R6 R9
      91 [-]: NAMECALL R10 R10 K34 [0xA2880940]
      92 [-]: CALL R10 1 0 
      93 [-]: FORNLOOP R7 L6
L 7:  94 [-]: GETIMPORT R7 1 [nil]
      95 [-]: GETIMPORT R9 17 [nil]
      96 [-]: LOADK R10 K35 ["ArtifactObjMarker"]
      97 [-]: CALL R9 1 -1 
      98 [-]: NAMECALL R7 R7 K30 [0xC7FCADA9]
      99 [-]: CALL R7 -1 1 
     100 [-]: LOADN R10 1  
     101 [-]: LENGTH R8 R7 
     102 [-]: LOADN R9 1   
     103 [-]: FORNPREP R8 L9
L 8: 104 [-]: GETTABLE R11 R7 R10
     105 [-]: LOADK R13 K27 ["Disable"]
     106 [-]: NAMECALL R11 R11 K28 [0x8EB2112D]
     107 [-]: CALL R11 2 0 
     108 [-]: FORNLOOP R8 L8
L 9: 109 [-]: GETIMPORT R8 1 [nil]
     110 [-]: GETIMPORT R10 37 [nil]
     111 [-]: NAMECALL R8 R8 K26 [0xFB669000]
     112 [-]: CALL R8 2 1  
     113 [-]: LOADN R11 1  
     114 [-]: LENGTH R9 R8 
     115 [-]: LOADN R10 1  
     116 [-]: FORNPREP R9 L11
L10: 117 [-]: GETTABLE R12 R8 R11
     118 [-]: NAMECALL R12 R12 K34 [0xA2880940]
     119 [-]: CALL R12 1 0 
     120 [-]: FORNLOOP R9 L10
L11: 121 [-]: GETIMPORT R9 1 [nil]
     122 [-]: GETIMPORT R11 39 [nil]
     123 [-]: GETIMPORT R12 41 [nil]
     124 [-]: CALL R12 0 1 
     125 [-]: LOADB R13 0  
     126 [-]: NAMECALL R9 R9 K42 [0x659D451F]
     127 [-]: CALL R9 4 0  
     128 [-]: GETIMPORT R10 4 [nil]
     129 [-]: NAMECALL R10 R10 K43 [0xEF893AEC]
     130 [-]: CALL R10 1 1 
     131 [-]: LOADB R9 1   
     132 [-]: GETTABLEKS R11 R10 K44 ["alertId"]
     133 [-]: JUMPXEQKS R11 K45 L13 NOT [""]
     134 [-]: LOADB R9 1   
     135 [-]: GETTABLEKS R11 R10 K46 ["invasionId"]
     136 [-]: JUMPXEQKS R11 K45 L13 NOT [""]
     137 [-]: GETTABLEKS R11 R10 K47 ["syndicateTag"]
     138 [-]: NAMECALL R11 R11 K48 [0x56C01834]
     139 [-]: CALL R11 1 1 
     140 [-]: MOVE R9 R11  
     141 [-]: JUMPIF R9 L13
     142 [-]: GETTABLEKS R11 R10 K49 ["maxWaveNum"]
     143 [-]: LOADN R12 0  
     144 [-]: JUMPIFLT R12 R11 L12
     145 [-]: LOADB R9 0 +1
L12: 146 [-]: LOADB R9 1   
L13: 147 [-]: GETUPVAL R12 5
     148 [-]: NAMECALL R10 R1 K12 [0x0EB34C69]
     149 [-]: CALL R10 2 1 
L14: 150 [-]: GETIMPORT R11 51 [nil]
     151 [-]: JUMPIFNOT R11 L15
     152 [-]: RETURN R0 0  
L15: 153 [-]: FASTCALL1 12 R10 L16
     154 [-]: MOVE R12 R10 
     155 [-]: GETIMPORT R11 54 [nil]
     156 [-]: CALL R11 1 1 
L16: 157 [-]: GETUPVAL R14 5
     158 [-]: MOVE R15 R11 
     159 [-]: NAMECALL R12 R1 K5 [0x751F061D]
     160 [-]: CALL R12 3 0 
     161 [-]: LOADN R12 0  
     162 [-]: JUMPIFNOT R9 L18
     163 [-]: LOADN R13 30 
     164 [-]: JUMPIFNOTLT R11 R13 L17
     165 [-]: GETUPVAL R13 6
     166 [-]: LOADK R14 K55 [0.5]
     167 [-]: CALL R13 1 1 
     168 [-]: MOVE R12 R13 
L17: 169 [-]: LOADK R13 K56 [0.02]
     170 [-]: SETUPVAL R13 7
     171 [-]: JUMP L19
    
L18: 172 [-]: GETUPVAL R13 6
     173 [-]: LOADK R14 K55 [0.5]
     174 [-]: CALL R13 1 1 
     175 [-]: MOVE R12 R13 
L19: 176 [-]: MODK R13 R10 K57 [1]
     177 [-]: LOADK R14 K58 [0.25]
     178 [-]: JUMPIFNOTLT R13 R14 L31
     179 [-]: GETIMPORT R13 1 [nil]
     180 [-]: NAMECALL R13 R13 K59 [0x8B5B1F58]
     181 [-]: CALL R13 1 1 
     182 [-]: FASTCALL1 62 R13 L20
     183 [-]: MOVE R15 R13 
     184 [-]: GETIMPORT R14 61 [nil]
     185 [-]: CALL R14 1 1 
L20: 186 [-]: JUMPIF R14 L31
     187 [-]: GETIMPORT R14 1 [nil]
     188 [-]: NAMECALL R14 R14 K2 [0x18D05D30]
     189 [-]: CALL R14 1 1 
     190 [-]: JUMPIFNOT R14 L31
     191 [-]: LOADN R16 1  
     192 [-]: LENGTH R14 R13
     193 [-]: LOADN R15 1  
     194 [-]: FORNPREP R14 L31
L21: 195 [-]: GETTABLE R18 R13 R16
     196 [-]: FASTCALL1 62 R18 L22
     197 [-]: GETIMPORT R17 61 [nil]
     198 [-]: CALL R17 1 1 
L22: 199 [-]: JUMPIF R17 L30
     200 [-]: GETTABLE R17 R13 R16
     201 [-]: NAMECALL R17 R17 K62 [0x1AC1655C]
     202 [-]: CALL R17 1 1 
     203 [-]: GETTABLE R18 R13 R16
     204 [-]: NAMECALL R18 R18 K63 [0xD2715720]
     205 [-]: CALL R18 1 1 
     206 [-]: GETTABLE R20 R13 R16
     207 [-]: NAMECALL R20 R20 K64 [0xB40C191A]
     208 [-]: CALL R20 1 1 
     209 [-]: GETUPVAL R21 7
     210 [-]: MUL R19 R20 R21
     211 [-]: LOADK R23 K65 [1.25]
     212 [-]: MULK R24 R10 K66 [0.10000000000000001]
     213 [-]: POW R22 R23 R24
     214 [-]: MUL R21 R19 R22
     215 [-]: FASTCALL1 12 R21 L23
     216 [-]: GETIMPORT R20 54 [nil]
     217 [-]: CALL R20 1 1 
L23: 218 [-]: LOADN R21 0  
     219 [-]: JUMPIFNOTLT R21 R18 L29
     220 [-]: GETTABLE R21 R13 R16
     221 [-]: NAMECALL R21 R21 K67 [0x2047CFE7]
     222 [-]: CALL R21 1 1 
     223 [-]: JUMPIF R21 L29
     224 [-]: FASTCALL1 62 R17 L24
     225 [-]: MOVE R22 R17 
     226 [-]: GETIMPORT R21 61 [nil]
     227 [-]: CALL R21 1 1 
L24: 228 [-]: JUMPIF R21 L29
     229 [-]: NAMECALL R21 R17 K68 [0x73901ACF]
     230 [-]: CALL R21 1 1 
     231 [-]: JUMPIF R21 L29
     232 [-]: NAMECALL R21 R17 K69 [0xF456C2D7]
     233 [-]: CALL R21 1 1 
     234 [-]: LOADN R22 0  
     235 [-]: JUMPIFNOTLE R21 R22 L27
     236 [-]: SUB R22 R18 R20
     237 [-]: FASTCALL2K 18 R22 K70 L25 [5]
     238 [-]: LOADK R23 K70 [5]
     239 [-]: GETIMPORT R21 72 [nil]
     240 [-]: CALL R21 2 1 
L25: 241 [-]: GETTABLE R22 R13 R16
     242 [-]: MOVE R24 R21 
     243 [-]: NAMECALL R22 R22 K73 [0x014DB014]
     244 [-]: CALL R22 2 0 
     245 [-]: GETIMPORT R22 17 [nil]
     246 [-]: LOADK R23 K74 ["IronSkinDM"]
     247 [-]: CALL R22 1 1 
     248 [-]: GETTABLE R23 R13 R16
     249 [-]: NAMECALL R23 R23 K62 [0x1AC1655C]
     250 [-]: CALL R23 1 1 
     251 [-]: FASTCALL1 62 R23 L26
     252 [-]: MOVE R25 R23 
     253 [-]: GETIMPORT R24 61 [nil]
     254 [-]: CALL R24 1 1 
L26: 255 [-]: JUMPIF R24 L27
     256 [-]: GETTABLE R24 R13 R16
     257 [-]: NAMECALL R24 R24 K63 [0xD2715720]
     258 [-]: CALL R24 1 1 
     259 [-]: LOADN R25 20 
     260 [-]: JUMPIFNOTLT R24 R25 L27
     261 [-]: MOVE R26 R22 
     262 [-]: NAMECALL R24 R23 K75 [0x28B6EB3C]
     263 [-]: CALL R24 2 1 
     264 [-]: LOADN R25 0  
     265 [-]: JUMPIFNOTLT R25 R24 L27
     266 [-]: MOVE R26 R22 
     267 [-]: NAMECALL R24 R23 K76 [0x78D582B0]
     268 [-]: CALL R24 2 0 
L27: 269 [-]: GETTABLE R21 R13 R16
     270 [-]: NAMECALL R21 R21 K77 [0xDE321E6F]
     271 [-]: CALL R21 1 1 
     272 [-]: NAMECALL R21 R21 K78 [0xF7D48EE0]
     273 [-]: CALL R21 1 1 
     274 [-]: NAMECALL R22 R17 K69 [0xF456C2D7]
     275 [-]: CALL R22 1 1 
     276 [-]: SUB R24 R22 R20
     277 [-]: FASTCALL2K 18 R24 K79 L28 [0]
     278 [-]: LOADK R25 K79 [0]
     279 [-]: GETIMPORT R23 72 [nil]
     280 [-]: CALL R23 2 1 
L28: 281 [-]: MOVE R26 R23 
     282 [-]: NAMECALL R24 R17 K80 [0x57369B8B]
     283 [-]: CALL R24 2 0 
     284 [-]: LOADN R24 0  
     285 [-]: JUMPIFNOTLE R23 R24 L29
     286 [-]: LOADN R26 0  
     287 [-]: NAMECALL R24 R17 K81 [0x7B1C3D01]
     288 [-]: CALL R24 2 0 
L29: 289 [-]: GETIMPORT R21 83 [nil]
     290 [-]: JUMPIF R21 L30
     291 [-]: GETIMPORT R21 85 [nil]
     292 [-]: GETIMPORT R22 17 [nil]
     293 [-]: LOADK R23 K86 ["Infestation"]
     294 [-]: CALL R22 1 1 
     295 [-]: JUMPIFEQ R21 R22 L30
     296 [-]: GETTABLE R21 R13 R16
     297 [-]: LOADB R23 1  
     298 [-]: NAMECALL R21 R21 K87 [0x86665C02]
     299 [-]: CALL R21 2 0 
L30: 300 [-]: FORNLOOP R14 L21
L31: 301 [-]: LOADN R13 300
     302 [-]: JUMPIFNOTLT R13 R10 L32
     303 [-]: JUMPIF R9 L32
     304 [-]: GETIMPORT R13 14 [nil]
     305 [-]: LOADK R14 K88 ["Survival: 5 minutes elapsed after life support ran out, mission failed."]
     306 [-]: CALL R13 1 0 
     307 [-]: GETUPVAL R14 8
     308 [-]: GETTABLEKS R13 R14 K89 [0xC506EE83]
     309 [-]: CALL R13 0 0 
     310 [-]: GETUPVAL R14 8
     311 [-]: GETTABLEKS R13 R14 K90 [0xAD362F29]
     312 [-]: GETUPVAL R15 8
     313 [-]: GETTABLEKS R14 R15 K91 ["INITIATOR_FAILURE"]
     314 [-]: CALL R13 1 0 
     315 [-]: GETUPVAL R15 1
     316 [-]: LOADN R16 0  
     317 [-]: NAMECALL R13 R1 K5 [0x751F061D]
     318 [-]: CALL R13 3 0 
     319 [-]: LOADN R15 0  
     320 [-]: NAMECALL R13 R1 K92 [0xF9BFC5D9]
     321 [-]: CALL R13 2 0 
     322 [-]: RETURN R0 0  
L32: 323 [-]: GETIMPORT R14 4 [nil]
     324 [-]: NAMECALL R14 R14 K43 [0xEF893AEC]
     325 [-]: CALL R14 1 1 
     326 [-]: LOADB R13 1  
     327 [-]: GETTABLEKS R15 R14 K44 ["alertId"]
     328 [-]: JUMPXEQKS R15 K45 L34 NOT [""]
     329 [-]: LOADB R13 1  
     330 [-]: GETTABLEKS R15 R14 K46 ["invasionId"]
     331 [-]: JUMPXEQKS R15 K45 L34 NOT [""]
     332 [-]: GETTABLEKS R15 R14 K47 ["syndicateTag"]
     333 [-]: NAMECALL R15 R15 K48 [0x56C01834]
     334 [-]: CALL R15 1 1 
     335 [-]: MOVE R13 R15 
     336 [-]: JUMPIF R13 L34
     337 [-]: GETTABLEKS R15 R14 K49 ["maxWaveNum"]
     338 [-]: LOADN R16 0  
     339 [-]: JUMPIFLT R16 R15 L33
     340 [-]: LOADB R13 0 +1
L33: 341 [-]: LOADB R13 1  
L34: 342 [-]: JUMPIFNOT R13 L38
     343 [-]: GETIMPORT R14 4 [nil]
     344 [-]: NAMECALL R14 R14 K43 [0xEF893AEC]
     345 [-]: CALL R14 1 1 
     346 [-]: GETUPVAL R16 10
     347 [-]: GETTABLEKS R15 R16 K93 [0x06D055F9]
     348 [-]: GETTABLEKS R17 R14 K49 ["maxWaveNum"]
     349 [-]: LOADN R18 0  
     350 [-]: JUMPIFLT R18 R17 L35
     351 [-]: LOADB R16 0 +1
L35: 352 [-]: LOADB R16 1  
L36: 353 [-]: GETTABLEKS R19 R14 K49 ["maxWaveNum"]
     354 [-]: MULK R18 R19 K94 [60]
     355 [-]: FASTCALL2K 19 R18 K95 L37 [3600]
     356 [-]: LOADK R19 K95 [3600]
     357 [-]: GETIMPORT R17 97 [nil]
     358 [-]: CALL R17 2 1 
L37: 359 [-]: LOADN R18 600
     360 [-]: CALL R15 3 1 
     361 [-]: MOVE R13 R15 
     362 [-]: SETUPVAL R13 9
L38: 363 [-]: LOADN R13 5  
     364 [-]: JUMPIFNOTLT R13 R10 L39
     365 [-]: GETUPVAL R13 9
     366 [-]: JUMPIFNOTLT R2 R13 L39
     367 [-]: GETIMPORT R13 14 [nil]
     368 [-]: LOADK R14 K98 ["Survival: Life support ran out before first reward reached, mission failed."]
     369 [-]: CALL R13 1 0 
     370 [-]: GETUPVAL R14 8
     371 [-]: GETTABLEKS R13 R14 K89 [0xC506EE83]
     372 [-]: CALL R13 0 0 
     373 [-]: GETUPVAL R14 8
     374 [-]: GETTABLEKS R13 R14 K90 [0xAD362F29]
     375 [-]: GETUPVAL R15 8
     376 [-]: GETTABLEKS R14 R15 K91 ["INITIATOR_FAILURE"]
     377 [-]: CALL R13 1 0 
     378 [-]: GETUPVAL R15 1
     379 [-]: LOADN R16 0  
     380 [-]: NAMECALL R13 R1 K5 [0x751F061D]
     381 [-]: CALL R13 3 0 
     382 [-]: LOADN R15 0  
     383 [-]: NAMECALL R13 R1 K92 [0xF9BFC5D9]
     384 [-]: CALL R13 2 0 
     385 [-]: RETURN R0 0  
L39: 386 [-]: ADDK R13 R10 K58 [0.25]
     387 [-]: ADD R10 R13 R12
     388 [-]: GETIMPORT R13 100 [nil]
     389 [-]: LOADK R14 K58 [0.25]
     390 [-]: CALL R13 1 0 
     391 [-]: JUMPBACK L14 
L40: 392 [-]: RETURN R0 0  


; Name:            
; Defined at line: 2463
; #Upvalues:       15
; #Parameters:     1
; Is_vararg:       0
; Max Stack Size:  24

       0 [-]: GETIMPORT R1 1 [nil]
       1 [-]: NAMECALL R2 R1 K2 [0x5C390F04]
       2 [-]: CALL R2 1 1  
       3 [-]: LOADN R3 2   
       4 [-]: JUMPIFEQ R2 R3 L0
       5 [-]: RETURN R0 0  
L 0:   6 [-]: NAMECALL R2 R0 K3 [0xE79E7EF4]
       7 [-]: CALL R2 1 1  
       8 [-]: NAMECALL R2 R2 K4 [0x22DA1852]
       9 [-]: CALL R2 1 1  
      10 [-]: GETIMPORT R3 6 [nil]
      11 [-]: LOADK R4 K7 ["Objective"]
      12 [-]: CALL R3 1 1  
      13 [-]: JUMPIFEQ R2 R3 L1
      14 [-]: GETIMPORT R3 6 [nil]
      15 [-]: LOADK R4 K8 ["Boss"]
      16 [-]: CALL R3 1 1  
      17 [-]: JUMPIFEQ R2 R3 L1
      18 [-]: RETURN R0 0  
L 1:  19 [-]: GETIMPORT R3 10 [nil]
      20 [-]: NAMECALL R3 R3 K11 [0x29EF273D]
      21 [-]: CALL R3 1 1  
      22 [-]: NAMECALL R4 R3 K12 [0x66905CB0]
      23 [-]: CALL R4 1 1  
      24 [-]: GETIMPORT R5 1 [nil]
      25 [-]: GETUPVAL R7 0
      26 [-]: NAMECALL R5 R5 K13 [0x0EB34C69]
      27 [-]: CALL R5 2 1  
      28 [-]: GETIMPORT R6 15 [nil]
      29 [-]: LOADB R7 0   
      30 [-]: SETTABLEKS R7 R6 K16 ["AllowWrinkles"]
      31 [-]: GETIMPORT R6 15 [nil]
      32 [-]: LOADB R7 1   
      33 [-]: SETTABLEKS R7 R6 K17 ["gSkipExtractionTimer"]
      34 [-]: GETIMPORT R6 15 [nil]
      35 [-]: NAMECALL R7 R1 K18 [0x9DDA54DC]
      36 [-]: CALL R7 1 1  
      37 [-]: SETTABLEKS R7 R6 K19 ["gSurvivalRewardSeed"]
      38 [-]: GETIMPORT R6 1 [nil]
      39 [-]: GETUPVAL R8 1
      40 [-]: NAMECALL R6 R6 K13 [0x0EB34C69]
      41 [-]: CALL R6 2 1  
      42 [-]: GETIMPORT R7 21 [nil]
      43 [-]: CALL R7 0 1  
      44 [-]: GETIMPORT R8 23 [nil]
      45 [-]: GETIMPORT R9 24 [nil]
      46 [-]: MOVE R10 R6  
      47 [-]: CALL R8 2 0  
      48 [-]: GETIMPORT R8 15 [nil]
      49 [-]: GETIMPORT R9 21 [nil]
      50 [-]: CALL R9 0 1  
      51 [-]: SETTABLEKS R9 R8 K19 ["gSurvivalRewardSeed"]
      52 [-]: GETIMPORT R8 26 [nil]
      53 [-]: MOVE R9 R7   
      54 [-]: CALL R8 1 0  
      55 [-]: GETIMPORT R8 28 [nil]
      56 [-]: LOADK R10 K29 ["Survival: Host migration init mission state: "]
      57 [-]: GETIMPORT R11 31 [nil]
      58 [-]: MOVE R12 R5  
      59 [-]: CALL R11 1 1 
      60 [-]: CONCAT R9 R10 R11
      61 [-]: CALL R8 1 0  
      62 [-]: GETUPVAL R9 2
      63 [-]: GETTABLEKS R8 R9 K32 [0x59F914CD]
      64 [-]: GETIMPORT R9 34 [nil]
      65 [-]: CALL R8 1 0  
      66 [-]: LOADN R8 2   
      67 [-]: JUMPIFNOTLT R5 R8 L8
      68 [-]: LOADNIL R8   
      69 [-]: GETIMPORT R9 10 [nil]
      70 [-]: GETIMPORT R11 6 [nil]
      71 [-]: LOADK R12 K35 ["AlarmObjMarker"]
      72 [-]: CALL R11 1 -1
      73 [-]: NAMECALL R9 R9 K36 [0xC7FCADA9]
      74 [-]: CALL R9 -1 1 
      75 [-]: LOADN R12 1  
      76 [-]: LENGTH R10 R9
      77 [-]: LOADN R11 1  
      78 [-]: FORNPREP R10 L4
L 2:  79 [-]: GETTABLE R13 R9 R12
      80 [-]: NAMECALL R13 R13 K3 [0xE79E7EF4]
      81 [-]: CALL R13 1 1 
      82 [-]: NAMECALL R14 R13 K4 [0x22DA1852]
      83 [-]: CALL R14 1 1 
      84 [-]: GETIMPORT R15 6 [nil]
      85 [-]: LOADK R16 K37 ["Spawn"]
      86 [-]: CALL R15 1 1 
      87 [-]: JUMPIFNOTEQ R14 R15 L3
      88 [-]: GETTABLE R8 R9 R12
      89 [-]: JUMP L4
     
L 3:  90 [-]: FORNLOOP R10 L2
L 4:  91 [-]: FASTCALL1 62 R8 L5
      92 [-]: MOVE R11 R8  
      93 [-]: GETIMPORT R10 39 [nil]
      94 [-]: CALL R10 1 1 
L 5:  95 [-]: JUMPIFNOT R10 L6
      96 [-]: GETIMPORT R10 28 [nil]
      97 [-]: LOADK R11 K40 ["Survival: Can't find alarm panel to set objective after host migration."]
      98 [-]: CALL R10 1 0 
L 6:  99 [-]: JUMPXEQKN R5 K41 L7 NOT [0]
     100 [-]: MOVE R12 R8  
     101 [-]: NAMECALL R10 R4 K42 [0xE2871589]
     102 [-]: CALL R10 2 0 
     103 [-]: RETURN R0 0  
L 7: 104 [-]: JUMPXEQKN R5 K43 L15 NOT [1]
     105 [-]: MOVE R12 R8  
     106 [-]: NAMECALL R10 R4 K42 [0xE2871589]
     107 [-]: CALL R10 2 0 
     108 [-]: JUMP L15
    
L 8: 109 [-]: NEWTABLE R8 0 4
     110 [-]: LOADN R9 1   
     111 [-]: LOADN R10 3  
     112 [-]: LOADN R11 2  
     113 [-]: LOADN R12 4  
     114 [-]: SETLIST R8 R9 4 [1]
     115 [-]: LOADNIL R9   
     116 [-]: LOADNIL R10  
     117 [-]: LOADN R13 1  
     118 [-]: LENGTH R11 R8
     119 [-]: LOADN R12 1  
     120 [-]: FORNPREP R11 L10
L 9: 121 [-]: GETUPVAL R14 3
     122 [-]: GETTABLE R15 R8 R13
     123 [-]: CALL R14 1 1 
     124 [-]: MOVE R9 R14  
     125 [-]: LENGTH R14 R9
     126 [-]: LOADN R15 0  
     127 [-]: JUMPIFLT R15 R14 L10
     128 [-]: FORNLOOP R11 L9
L10: 129 [-]: GETTABLEN R12 R9 1
     130 [-]: FASTCALL1 62 R12 L11
     131 [-]: GETIMPORT R11 39 [nil]
     132 [-]: CALL R11 1 1 
L11: 133 [-]: JUMPIF R11 L12
     134 [-]: GETTABLEN R10 R9 1
L12: 135 [-]: GETUPVAL R12 4
     136 [-]: GETTABLEKS R11 R12 K44 [0x5CD57AED]
     137 [-]: GETIMPORT R12 6 [nil]
     138 [-]: LOADK R13 K45 ["SurvivalFog"]
     139 [-]: CALL R12 1 1 
     140 [-]: LOADB R13 0  
     141 [-]: LOADB R14 1  
     142 [-]: CALL R11 3 0 
     143 [-]: FASTCALL1 62 R10 L13
     144 [-]: MOVE R12 R10 
     145 [-]: GETIMPORT R11 39 [nil]
     146 [-]: CALL R11 1 1 
L13: 147 [-]: JUMPIF R11 L14
     148 [-]: MOVE R13 R10 
     149 [-]: NAMECALL R11 R4 K42 [0xE2871589]
     150 [-]: CALL R11 2 0 
     151 [-]: JUMP L15
    
L14: 152 [-]: GETIMPORT R11 28 [nil]
     153 [-]: LOADK R12 K46 ["Survival: Error restarting objective after host migration!"]
     154 [-]: CALL R11 1 0 
L15: 155 [-]: GETIMPORT R9 1 [nil]
     156 [-]: NAMECALL R9 R9 K47 [0xEF893AEC]
     157 [-]: CALL R9 1 1  
     158 [-]: GETTABLEKS R10 R9 K48 ["goalTag"]
     159 [-]: GETIMPORT R11 6 [nil]
     160 [-]: LOADK R12 K49 ["KuvaSurvival"]
     161 [-]: CALL R11 1 1 
     162 [-]: JUMPIFNOTEQ R10 R11 L16
     163 [-]: LOADB R8 1   
     164 [-]: JUMP L17
    
L16: 165 [-]: LOADB R8 0   
L17: 166 [-]: GETIMPORT R9 10 [nil]
     167 [-]: NAMECALL R9 R9 K50 [0x18D05D30]
     168 [-]: CALL R9 1 1  
     169 [-]: JUMPIFNOT R9 L23
     170 [-]: JUMPIFNOT R8 L23
     171 [-]: GETIMPORT R9 15 [nil]
     172 [-]: NEWTABLE R10 0 3
     173 [-]: LOADN R11 0  
     174 [-]: LOADN R12 0  
     175 [-]: LOADN R13 0  
     176 [-]: SETLIST R10 R11 3 [1]
     177 [-]: SETTABLEKS R10 R9 K51 ["kuvaExtractorList"]
     178 [-]: GETIMPORT R9 10 [nil]
     179 [-]: GETUPVAL R11 5
     180 [-]: NAMECALL R9 R9 K52 [0xFB669000]
     181 [-]: CALL R9 2 1  
     182 [-]: FASTCALL1 62 R9 L18
     183 [-]: MOVE R11 R9  
     184 [-]: GETIMPORT R10 39 [nil]
     185 [-]: CALL R10 1 1 
L18: 186 [-]: JUMPIF R10 L23
     187 [-]: LOADN R12 1  
     188 [-]: LOADN R10 3  
     189 [-]: LOADN R11 1  
     190 [-]: FORNPREP R10 L23
L19: 191 [-]: GETTABLE R14 R9 R12
     192 [-]: FASTCALL1 62 R14 L20
     193 [-]: GETIMPORT R13 39 [nil]
     194 [-]: CALL R13 1 1 
L20: 195 [-]: JUMPIF R13 L22
     196 [-]: GETTABLE R14 R9 R12
     197 [-]: NAMECALL R14 R14 K53 [0xBB610E5B]
     198 [-]: CALL R14 1 1 
     199 [-]: FASTCALL1 62 R14 L21
     200 [-]: GETIMPORT R13 39 [nil]
     201 [-]: CALL R13 1 1 
L21: 202 [-]: JUMPIF R13 L22
     203 [-]: GETIMPORT R13 54 [nil]
     204 [-]: GETTABLE R14 R9 R12
     205 [-]: SETTABLE R14 R13 R12
L22: 206 [-]: FORNLOOP R10 L19
L23: 207 [-]: GETIMPORT R9 10 [nil]
     208 [-]: NAMECALL R9 R9 K50 [0x18D05D30]
     209 [-]: CALL R9 1 1  
     210 [-]: JUMPIFNOT R9 L24
     211 [-]: GETUPVAL R10 4
     212 [-]: GETTABLEKS R9 R10 K44 [0x5CD57AED]
     213 [-]: GETIMPORT R10 6 [nil]
     214 [-]: LOADK R11 K55 ["SurvivalHudScript"]
     215 [-]: CALL R10 1 1 
     216 [-]: LOADB R11 0  
     217 [-]: LOADB R12 1  
     218 [-]: CALL R9 3 0  
L24: 219 [-]: GETUPVAL R11 6
     220 [-]: NAMECALL R9 R1 K13 [0x0EB34C69]
     221 [-]: CALL R9 2 1  
     222 [-]: DIVK R10 R9 K56 [150]
     223 [-]: GETIMPORT R12 58 [nil]
     224 [-]: FASTCALL1 62 R12 L25
     225 [-]: GETIMPORT R11 39 [nil]
     226 [-]: CALL R11 1 1 
L25: 227 [-]: JUMPIFNOT R11 L27
     228 [-]: GETUPVAL R12 7
     229 [-]: GETTABLEKS R11 R12 K59 [0xEA753E99]
     230 [-]: LOADK R12 K60 ["/Lotus/Language/Game/SurvivalProgressBar"]
     231 [-]: MULK R14 R10 K61 [100]
     232 [-]: FASTCALL1 12 R14 L26
     233 [-]: GETIMPORT R13 64 [nil]
     234 [-]: CALL R13 1 1 
L26: 235 [-]: LOADN R14 100
     236 [-]: GETIMPORT R15 66 [nil]
     237 [-]: LOADB R16 1  
     238 [-]: CALL R11 5 0 
L27: 239 [-]: GETIMPORT R11 28 [nil]
     240 [-]: LOADK R13 K67 ["Survival: Host migration init progress bar initialized: "]
     241 [-]: MOVE R14 R9  
     242 [-]: LOADK R15 K68 [" seconds left."]
     243 [-]: CONCAT R12 R13 R15
     244 [-]: CALL R11 1 0 
     245 [-]: GETIMPORT R11 70 [nil]
     246 [-]: LOADN R12 1  
     247 [-]: CALL R11 1 0 
L28: 248 [-]: GETIMPORT R11 1 [nil]
     249 [-]: NAMECALL R11 R11 K71 [0xC1F9F0D9]
     250 [-]: CALL R11 1 1 
     251 [-]: JUMPIF R11 L29
     252 [-]: GETIMPORT R11 70 [nil]
     253 [-]: LOADK R12 K72 [0.10000000000000001]
     254 [-]: CALL R11 1 0 
     255 [-]: JUMPBACK L28 
L29: 256 [-]: LOADB R13 1  
     257 [-]: NAMECALL R11 R4 K73 [0x383D2E7D]
     258 [-]: CALL R11 2 0 
     259 [-]: LOADB R13 0  
     260 [-]: NAMECALL R11 R4 K74 [0x2FAEAD12]
     261 [-]: CALL R11 2 0 
     262 [-]: LOADB R13 1  
     263 [-]: NAMECALL R11 R4 K75 [0xE603BAB2]
     264 [-]: CALL R11 2 0 
     265 [-]: GETUPVAL R12 4
     266 [-]: GETTABLEKS R11 R12 K44 [0x5CD57AED]
     267 [-]: GETIMPORT R12 6 [nil]
     268 [-]: LOADK R13 K76 ["RandomArtifactScript"]
     269 [-]: CALL R12 1 1 
     270 [-]: LOADB R13 0  
     271 [-]: LOADB R14 1  
     272 [-]: CALL R11 3 0 
     273 [-]: GETIMPORT R11 70 [nil]
     274 [-]: LOADK R12 K77 [0.5]
     275 [-]: CALL R11 1 0 
     276 [-]: GETUPVAL R13 8
     277 [-]: NAMECALL R11 R1 K13 [0x0EB34C69]
     278 [-]: CALL R11 2 1 
     279 [-]: GETIMPORT R13 1 [nil]
     280 [-]: NAMECALL R13 R13 K47 [0xEF893AEC]
     281 [-]: CALL R13 1 1 
     282 [-]: LOADB R12 1  
     283 [-]: GETTABLEKS R14 R13 K78 ["alertId"]
     284 [-]: JUMPXEQKS R14 K79 L31 NOT [""]
     285 [-]: LOADB R12 1  
     286 [-]: GETTABLEKS R14 R13 K80 ["invasionId"]
     287 [-]: JUMPXEQKS R14 K79 L31 NOT [""]
     288 [-]: GETTABLEKS R14 R13 K81 ["syndicateTag"]
     289 [-]: NAMECALL R14 R14 K82 [0x56C01834]
     290 [-]: CALL R14 1 1 
     291 [-]: MOVE R12 R14 
     292 [-]: JUMPIF R12 L31
     293 [-]: GETTABLEKS R14 R13 K83 ["maxWaveNum"]
     294 [-]: LOADN R15 0  
     295 [-]: JUMPIFLT R15 R14 L30
     296 [-]: LOADB R12 0 +1
L30: 297 [-]: LOADB R12 1  
L31: 298 [-]: JUMPIFNOT R12 L36
     299 [-]: LOADN R13 0  
     300 [-]: GETIMPORT R16 1 [nil]
     301 [-]: NAMECALL R16 R16 K47 [0xEF893AEC]
     302 [-]: CALL R16 1 1 
     303 [-]: GETUPVAL R18 9
     304 [-]: GETTABLEKS R17 R18 K84 [0x06D055F9]
     305 [-]: GETTABLEKS R19 R16 K83 ["maxWaveNum"]
     306 [-]: LOADN R20 0  
     307 [-]: JUMPIFLT R20 R19 L32
     308 [-]: LOADB R18 0 +1
L32: 309 [-]: LOADB R18 1  
L33: 310 [-]: GETTABLEKS R21 R16 K83 ["maxWaveNum"]
     311 [-]: MULK R20 R21 K85 [60]
     312 [-]: FASTCALL2K 19 R20 K86 L34 [3600]
     313 [-]: LOADK R21 K86 [3600]
     314 [-]: GETIMPORT R19 88 [nil]
     315 [-]: CALL R19 2 1 
L34: 316 [-]: LOADN R20 600
     317 [-]: CALL R17 3 1 
     318 [-]: MOVE R15 R17 
     319 [-]: SUB R14 R15 R11
     320 [-]: FASTCALL2 18 R13 R14 L35
     321 [-]: GETIMPORT R12 90 [nil]
     322 [-]: CALL R12 2 1 
L35: 323 [-]: GETUPVAL R15 10
     324 [-]: GETUPVAL R16 11
     325 [-]: MOVE R17 R12 
     326 [-]: LOADB R18 0  
     327 [-]: LOADB R19 1  
     328 [-]: LOADB R20 0  
     329 [-]: NAMECALL R13 R1 K91 [0xFE23FE59]
     330 [-]: CALL R13 7 0 
     331 [-]: GETUPVAL R15 10
     332 [-]: MOVE R16 R12 
     333 [-]: NAMECALL R13 R1 K92 [0x39A80406]
     334 [-]: CALL R13 3 0 
     335 [-]: JUMP L37
    
L36: 336 [-]: GETUPVAL R14 10
     337 [-]: GETUPVAL R15 11
     338 [-]: LOADN R16 0  
     339 [-]: LOADB R17 0  
     340 [-]: LOADB R18 1  
     341 [-]: LOADB R19 1  
     342 [-]: NAMECALL R12 R1 K91 [0xFE23FE59]
     343 [-]: CALL R12 7 0 
     344 [-]: GETUPVAL R14 10
     345 [-]: MOVE R15 R11 
     346 [-]: NAMECALL R12 R1 K92 [0x39A80406]
     347 [-]: CALL R12 3 0 
L37: 348 [-]: GETIMPORT R12 28 [nil]
     349 [-]: LOADK R14 K93 ["Survival: Host migration init timer restarted: "]
     350 [-]: MOVE R15 R11 
     351 [-]: LOADK R16 K94 [" seconds elapsed."]
     352 [-]: CONCAT R13 R14 R16
     353 [-]: CALL R12 1 0 
     354 [-]: GETUPVAL R14 12
     355 [-]: LOADN R15 0  
     356 [-]: NAMECALL R12 R1 K13 [0x0EB34C69]
     357 [-]: CALL R12 3 1 
     358 [-]: JUMPXEQKN R12 K41 L41 [0]
     359 [-]: GETIMPORT R13 96 [nil]
     360 [-]: GETIMPORT R15 98 [nil]
     361 [-]: NAMECALL R13 R13 K99 [0xBCFB64AB]
     362 [-]: CALL R13 2 1 
L38: 363 [-]: FASTCALL1 62 R13 L39
     364 [-]: MOVE R15 R13 
     365 [-]: GETIMPORT R14 39 [nil]
     366 [-]: CALL R14 1 1 
L39: 367 [-]: JUMPIF R14 L40
     368 [-]: GETIMPORT R14 70 [nil]
     369 [-]: LOADN R15 0  
     370 [-]: CALL R14 1 0 
     371 [-]: JUMPBACK L38 
L40: 372 [-]: GETUPVAL R14 13
     373 [-]: MOVE R15 R6  
     374 [-]: MOVE R16 R12 
     375 [-]: CALL R14 2 0 
L41: 376 [-]: GETIMPORT R13 10 [nil]
     377 [-]: NAMECALL R13 R13 K50 [0x18D05D30]
     378 [-]: CALL R13 1 1 
     379 [-]: JUMPIFNOT R13 L47
     380 [-]: JUMPIFNOT R8 L47
     381 [-]: GETIMPORT R13 10 [nil]
     382 [-]: NAMECALL R13 R13 K100 [0x21C948F8]
     383 [-]: CALL R13 1 1 
L42: 384 [-]: FASTCALL1 62 R13 L43
     385 [-]: MOVE R15 R13 
     386 [-]: GETIMPORT R14 39 [nil]
     387 [-]: CALL R14 1 1 
L43: 388 [-]: JUMPIFNOT R14 L44
     389 [-]: GETIMPORT R14 10 [nil]
     390 [-]: NAMECALL R14 R14 K100 [0x21C948F8]
     391 [-]: CALL R14 1 1 
     392 [-]: MOVE R13 R14 
     393 [-]: GETIMPORT R14 70 [nil]
     394 [-]: LOADN R15 0  
     395 [-]: CALL R14 1 0 
     396 [-]: JUMPBACK L42 
L44: 397 [-]: GETIMPORT R14 102 [nil]
     398 [-]: MOVE R15 R13 
     399 [-]: CALL R14 1 3 
     400 [-]: FORGPREP_INEXT R14 L46
L45: 401 [-]: NAMECALL R19 R18 K103 [0x3CC8EBE1]
     402 [-]: CALL R19 1 1 
     403 [-]: GETIMPORT R20 105 [nil]
     404 [-]: JUMPIFNOTEQ R19 R20 L46
     405 [-]: GETIMPORT R21 107 [nil]
     406 [-]: GETIMPORT R22 6 [nil]
     407 [-]: LOADK R23 K108 ["GAME_C1_SPINE3"]
     408 [-]: CALL R22 1 -1
     409 [-]: NAMECALL R19 R18 K109 [0x47901F07]
     410 [-]: CALL R19 -1 0
L46: 411 [-]: FORGLOOP R14 L45 2 [inext]
L47: 412 [-]: GETUPVAL R13 14
     413 [-]: CALL R13 0 0 
     414 [-]: RETURN R0 0  



