; Name:            
; Defined at line: 1
; #Upvalues:       0
; #Parameters:     0
; Is_vararg:       1
; Max Stack Size:  14

       1 [-]: GETIMPORT R0 1 [0x2D0FAD09]
       2 [-]: LOADK R1 K2 ["EE.Interface.Utilities"]
       3 [-]: CALL R0 1 1  
       4 [-]: GETIMPORT R1 1 [0x2D0FAD09]
       5 [-]: LOADK R2 K3 ["Lotus.Interface.UIStyleUtilities"]
       6 [-]: CALL R1 1 1  
       7 [-]: GETIMPORT R2 1 [0x2D0FAD09]
       8 [-]: LOADK R3 K4 ["EE.Interface.AnchorMgr"]
       9 [-]: CALL R2 1 1  
      10 [-]: LOADNIL R3   
      11 [-]: LOADB R4 0   
      12 [-]: LOADB R5 1   
      13 [-]: LOADNIL R6   
      14 [-]: LOADNIL R7   
      15 [-]: LOADNIL R8   
      16 [-]: NEWCLOSURE R9 P0
      17 [-]: MOVE R0 R1   
      18 [-]: MOVE R0 R0   
      19 [-]: MOVE R1 R6   
      20 [-]: MOVE R1 R7   
      21 [-]: NEWCLOSURE R10 P1
      22 [-]: MOVE R1 R5   
      23 [-]: SETGLOBAL R10 K5 ["HasFocus"]
      24 [-]: NEWCLOSURE R10 P2
      25 [-]: MOVE R1 R6   
      26 [-]: MOVE R1 R7   
      27 [-]: MOVE R1 R3   
      28 [-]: MOVE R0 R2   
      29 [-]: MOVE R0 R9   
      30 [-]: MOVE R1 R4   
      31 [-]: SETGLOBAL R10 K6 ["Initialize"]
      32 [-]: DUPCLOSURE R10 K7 []
      33 [-]: MOVE R0 R0   
      34 [-]: NEWCLOSURE R11 P4
      35 [-]: MOVE R1 R6   
      36 [-]: MOVE R1 R7   
      37 [-]: SETGLOBAL R11 K8 ["IconCacheFlushed"]
      38 [-]: DUPCLOSURE R11 K9 []
      39 [-]: NEWCLOSURE R12 P6
      40 [-]: MOVE R1 R4   
      41 [-]: MOVE R1 R5   
      42 [-]: MOVE R1 R8   
      43 [-]: MOVE R0 R10  
      44 [-]: MOVE R0 R11  
      45 [-]: MOVE R1 R6   
      46 [-]: SETGLOBAL R12 K10 ["Update"]
      47 [-]: GETIMPORT R12 12 ["_T"]
      48 [-]: NEWCLOSURE R13 P7
      49 [-]: MOVE R1 R5   
      50 [-]: SETTABLEKS R13 R12 K13 ["HandleAcceptInviteFade"]
      51 [-]: DUPCLOSURE R12 K14 []
      52 [-]: MOVE R0 R0   
      53 [-]: SETGLOBAL R12 K15 ["OnAccept"]
      54 [-]: DUPCLOSURE R12 K16 []
      55 [-]: MOVE R0 R0   
      56 [-]: SETGLOBAL R12 K17 ["OnCancel"]
      57 [-]: NEWCLOSURE R12 P10
      58 [-]: MOVE R1 R5   
      59 [-]: SETGLOBAL R12 K18 ["IsInputBlocked"]
      60 [-]: NEWCLOSURE R12 P11
      61 [-]: MOVE R1 R3   
      62 [-]: SETGLOBAL R12 K19 ["onViewportSizeChanged"]
      63 [-]: NEWCLOSURE R12 P12
      64 [-]: MOVE R1 R3   
      65 [-]: SETGLOBAL R12 K20 ["onMenuScaleChanged"]
      66 [-]: DUPCLOSURE R12 K21 []
      67 [-]: MOVE R0 R0   
      68 [-]: NEWCLOSURE R13 P14
      69 [-]: MOVE R0 R12  
      70 [-]: MOVE R1 R5   
      71 [-]: MOVE R1 R6   
      72 [-]: SETGLOBAL R13 K22 ["onKeyUp_MENU_SELECT"]
      73 [-]: NEWCLOSURE R13 P15
      74 [-]: MOVE R0 R12  
      75 [-]: MOVE R1 R5   
      76 [-]: MOVE R1 R6   
      77 [-]: SETGLOBAL R13 K23 ["onKeyUp_MENU_GENERIC1"]
      78 [-]: NEWCLOSURE R13 P16
      79 [-]: MOVE R0 R12  
      80 [-]: MOVE R1 R5   
      81 [-]: MOVE R1 R7   
      82 [-]: SETGLOBAL R13 K24 ["onKeyDown_MENU_CANCEL"]
      83 [-]: DUPCLOSURE R13 K25 []
      84 [-]: SETGLOBAL R13 K26 ["onKeyDown_HIDE_PAUSE_MENU"]
      85 [-]: NEWCLOSURE R13 P18
      86 [-]: MOVE R1 R6   
      87 [-]: MOVE R1 R7   
      88 [-]: SETGLOBAL R13 K27 ["OnGamepadTransition"]
      89 [-]: DUPCLOSURE R13 K28 []
      90 [-]: MOVE R0 R9   
      91 [-]: SETGLOBAL R13 K29 ["OnStyleChangedCallback"]
      92 [-]: DUPCLOSURE R13 K30 []
      93 [-]: SETGLOBAL R13 K31 ["SupportsThemes"]
      94 [-]: CLOSEUPVALS R3
      95 [-]: RETURN R0 0  


; Name:            
; Defined at line: 20
; #Upvalues:       4
; #Parameters:     0
; Is_vararg:       0
; Max Stack Size:  16

       0 [-]: GETUPVAL R1 0
       1 [-]: GETTABLEKS R0 R1 K0 [0x5D10207D]
       2 [-]: LOADN R1 2   
       3 [-]: LOADB R2 1   
       4 [-]: CALL R0 2 1  
       5 [-]: GETUPVAL R2 0
       6 [-]: GETTABLEKS R1 R2 K0 [0x5D10207D]
       7 [-]: LOADN R2 9   
       8 [-]: LOADB R3 1   
       9 [-]: CALL R1 2 1  
      10 [-]: GETUPVAL R3 0
      11 [-]: GETTABLEKS R2 R3 K0 [0x5D10207D]
      12 [-]: LOADN R3 6   
      13 [-]: CALL R2 1 1  
      14 [-]: GETIMPORT R3 2 [0xAE91E43B]
      15 [-]: LOADK R5 K3 ["Container.Dialog.Label"]
      16 [-]: LOADN R6 9   
      17 [-]: NAMECALL R7 R2 K4 [0xA5D5C8F6]
      18 [-]: CALL R7 1 -1 
      19 [-]: NAMECALL R3 R3 K5 [0x67BC869F]
      20 [-]: CALL R3 -1 0 
      21 [-]: NEWTABLE R3 0 8
      22 [-]: LOADK R4 K6 ["Container.FancyBits.LeftLines"]
      23 [-]: LOADK R5 K7 ["Container.FancyBits.RightLines"]
      24 [-]: LOADK R6 K8 ["Container.Dialog.LeftLines.FadeLineTop"]
      25 [-]: LOADK R7 K9 ["Container.Dialog.LeftLines.FadeLineMiddle"]
      26 [-]: LOADK R8 K10 ["Container.Dialog.LeftLines.FadeLineBottom"]
      27 [-]: LOADK R9 K11 ["Container.Dialog.RightLines.FadeLineTop"]
      28 [-]: LOADK R10 K12 ["Container.Dialog.RightLines.FadeLineMiddle"]
      29 [-]: LOADK R11 K13 ["Container.Dialog.RightLines.FadeLineBottom"]
      30 [-]: SETLIST R3 R4 8 [1]
      31 [-]: LOADN R6 1   
      32 [-]: LENGTH R4 R3 
      33 [-]: LOADN R5 1   
      34 [-]: FORNPREP R4 L1
L 0:  35 [-]: GETTABLE R7 R3 R6
      36 [-]: GETIMPORT R8 2 [0xAE91E43B]
      37 [-]: MOVE R10 R7  
      38 [-]: LOADN R11 9  
      39 [-]: MOVE R12 R1  
      40 [-]: NAMECALL R8 R8 K5 [0x67BC869F]
      41 [-]: CALL R8 4 0  
      42 [-]: GETIMPORT R8 2 [0xAE91E43B]
      43 [-]: MOVE R10 R7  
      44 [-]: LOADK R11 K14 ["RipplesColor"]
      45 [-]: GETTABLEKS R13 R2 K16 ["red"]
      46 [-]: DIVK R12 R13 K15 [255]
      47 [-]: GETTABLEKS R14 R2 K17 ["green"]
      48 [-]: DIVK R13 R14 K15 [255]
      49 [-]: GETTABLEKS R15 R2 K18 ["blue"]
      50 [-]: DIVK R14 R15 K15 [255]
      51 [-]: LOADK R15 K19 [0.90000000000000002]
      52 [-]: NAMECALL R8 R8 K20 [0x91E13703]
      53 [-]: CALL R8 7 0  
      54 [-]: FORNLOOP R4 L0
L 1:  55 [-]: GETUPVAL R5 1
      56 [-]: GETTABLEKS R4 R5 K21 [0x8BCD12B6]
      57 [-]: MOVE R5 R1   
      58 [-]: CALL R4 1 1  
      59 [-]: GETUPVAL R6 1
      60 [-]: GETTABLEKS R5 R6 K21 [0x8BCD12B6]
      61 [-]: MOVE R6 R0   
      62 [-]: CALL R5 1 1  
      63 [-]: GETIMPORT R6 2 [0xAE91E43B]
      64 [-]: LOADK R8 K22 ["Container.Dialog.BGPanel"]
      65 [-]: LOADK R9 K23 ["RectEdgeColor"]
      66 [-]: GETTABLEKS R10 R4 K24 ["r"]
      67 [-]: GETTABLEKS R11 R4 K25 ["g"]
      68 [-]: GETTABLEKS R12 R4 K26 ["b"]
      69 [-]: LOADK R13 K27 [0.29999999999999999]
      70 [-]: NAMECALL R6 R6 K20 [0x91E13703]
      71 [-]: CALL R6 7 0  
      72 [-]: GETIMPORT R6 2 [0xAE91E43B]
      73 [-]: LOADK R8 K22 ["Container.Dialog.BGPanel"]
      74 [-]: LOADK R9 K28 ["RectInnerColor"]
      75 [-]: GETTABLEKS R10 R5 K24 ["r"]
      76 [-]: GETTABLEKS R11 R5 K25 ["g"]
      77 [-]: GETTABLEKS R12 R5 K26 ["b"]
      78 [-]: LOADN R13 1  
      79 [-]: NAMECALL R6 R6 K20 [0x91E13703]
      80 [-]: CALL R6 7 0  
      81 [-]: GETIMPORT R6 2 [0xAE91E43B]
      82 [-]: LOADK R8 K29 ["Container.Dialog.BGPanel2"]
      83 [-]: LOADK R9 K23 ["RectEdgeColor"]
      84 [-]: GETTABLEKS R10 R4 K24 ["r"]
      85 [-]: GETTABLEKS R11 R4 K25 ["g"]
      86 [-]: GETTABLEKS R12 R4 K26 ["b"]
      87 [-]: LOADN R13 0  
      88 [-]: NAMECALL R6 R6 K20 [0x91E13703]
      89 [-]: CALL R6 7 0  
      90 [-]: GETIMPORT R6 2 [0xAE91E43B]
      91 [-]: LOADK R8 K29 ["Container.Dialog.BGPanel2"]
      92 [-]: LOADK R9 K28 ["RectInnerColor"]
      93 [-]: GETTABLEKS R10 R4 K24 ["r"]
      94 [-]: GETTABLEKS R11 R4 K25 ["g"]
      95 [-]: GETTABLEKS R12 R4 K26 ["b"]
      96 [-]: LOADN R13 1  
      97 [-]: NAMECALL R6 R6 K20 [0x91E13703]
      98 [-]: CALL R6 7 0  
      99 [-]: GETUPVAL R6 2
     100 [-]: NAMECALL R6 R6 K30 [0x087CBD3F]
     101 [-]: CALL R6 1 0  
     102 [-]: GETUPVAL R6 3
     103 [-]: NAMECALL R6 R6 K30 [0x087CBD3F]
     104 [-]: CALL R6 1 0  
     105 [-]: GETIMPORT R6 2 [0xAE91E43B]
     106 [-]: MOVE R8 R0   
     107 [-]: NAMECALL R6 R6 K31 [0xC6A10AB1]
     108 [-]: CALL R6 2 0  
     109 [-]: RETURN R0 0  


; Name:            
; Defined at line: 51
; #Upvalues:       1
; #Parameters:     0
; Is_vararg:       0
; Max Stack Size:  2

       0 [-]: GETUPVAL R1 0
       1 [-]: NOT R0 R1    
       2 [-]: RETURN R0 1  


; Name:            
; Defined at line: 55
; #Upvalues:       6
; #Parameters:     0
; Is_vararg:       0
; Max Stack Size:  9

       0 [-]: GETIMPORT R0 1 [0x2D0FAD09]
       1 [-]: LOADK R1 K2 ["Lotus.Interface.Components.ThemedButton"]
       2 [-]: CALL R0 1 1  
       3 [-]: GETTABLEKS R1 R0 K3 [0xAE6791BA]
       4 [-]: GETIMPORT R2 5 [0xAE91E43B]
       5 [-]: LOADK R3 K6 ["Container.Dialog.AcceptButton"]
       6 [-]: LOADK R4 K7 ["/Lotus/Language/Menu/Global_Accept"]
       7 [-]: LOADNIL R5   
       8 [-]: LOADK R6 K8 ["<MENU_GENERIC1>"]
       9 [-]: CALL R1 5 1  
      10 [-]: SETUPVAL R1 0
      11 [-]: GETTABLEKS R1 R0 K3 [0xAE6791BA]
      12 [-]: GETIMPORT R2 5 [0xAE91E43B]
      13 [-]: LOADK R3 K9 ["Container.Dialog.DeclineButton"]
      14 [-]: LOADK R4 K10 ["/Lotus/Language/Menu/Global_Decline"]
      15 [-]: LOADNIL R5   
      16 [-]: LOADK R6 K11 ["<MENU_CANCEL>"]
      17 [-]: CALL R1 5 1  
      18 [-]: SETUPVAL R1 1
      19 [-]: GETUPVAL R1 0
      20 [-]: LOADN R3 169 
      21 [-]: NAMECALL R1 R1 K12 [0x8D77B2B2]
      22 [-]: CALL R1 2 0  
      23 [-]: GETUPVAL R1 1
      24 [-]: LOADN R3 169 
      25 [-]: NAMECALL R1 R1 K12 [0x8D77B2B2]
      26 [-]: CALL R1 2 0  
      27 [-]: GETUPVAL R1 0
      28 [-]: DUPCLOSURE R2 K13 []
      29 [-]: SETTABLEKS R2 R1 K14 ["mOnReleasedCallback"]
      30 [-]: GETUPVAL R1 1
      31 [-]: DUPCLOSURE R2 K15 []
      32 [-]: SETTABLEKS R2 R1 K14 ["mOnReleasedCallback"]
      33 [-]: GETUPVAL R1 0
      34 [-]: NAMECALL R1 R1 K16 [0x71E9AC81]
      35 [-]: CALL R1 1 0  
      36 [-]: GETUPVAL R1 1
      37 [-]: NAMECALL R1 R1 K16 [0x71E9AC81]
      38 [-]: CALL R1 1 0  
      39 [-]: GETIMPORT R1 5 [0xAE91E43B]
      40 [-]: LOADK R3 K17 ["_root"]
      41 [-]: LOADN R4 11  
      42 [-]: LOADB R5 0   
      43 [-]: NAMECALL R1 R1 K18 [0xAADE900E]
      44 [-]: CALL R1 4 0  
      45 [-]: GETIMPORT R1 5 [0xAE91E43B]
      46 [-]: LOADB R3 1   
      47 [-]: NAMECALL R1 R1 K19 [0xBED40E9C]
      48 [-]: CALL R1 2 0  
      49 [-]: GETUPVAL R2 3
      50 [-]: GETTABLEKS R1 R2 K3 [0xAE6791BA]
      51 [-]: GETIMPORT R2 5 [0xAE91E43B]
      52 [-]: CALL R1 1 1  
      53 [-]: SETUPVAL R1 2
      54 [-]: GETUPVAL R1 2
      55 [-]: GETIMPORT R3 5 [0xAE91E43B]
      56 [-]: LOADK R4 K20 ["Container"]
      57 [-]: NEWTABLE R5 0 2
      58 [-]: GETUPVAL R7 2
      59 [-]: GETTABLEKS R6 R7 K21 ["ANCHOR_V_BOTTOM"]
      60 [-]: GETUPVAL R8 2
      61 [-]: GETTABLEKS R7 R8 K22 ["ANCHOR_H_CENTRE"]
      62 [-]: SETLIST R5 R6 2 [1]
      63 [-]: NAMECALL R1 R1 K23 [0x20FF29F7]
      64 [-]: CALL R1 4 0  
      65 [-]: GETUPVAL R1 2
      66 [-]: GETIMPORT R3 5 [0xAE91E43B]
      67 [-]: NAMECALL R3 R3 K24 [0x6B837788]
      68 [-]: CALL R3 1 1  
      69 [-]: GETIMPORT R4 5 [0xAE91E43B]
      70 [-]: NAMECALL R4 R4 K25 [0xAF9FDA9F]
      71 [-]: CALL R4 1 -1 
      72 [-]: NAMECALL R1 R1 K26 [0xFAA69527]
      73 [-]: CALL R1 -1 0 
      74 [-]: NEWTABLE R1 0 4
      75 [-]: LOADK R2 K27 ["Container.FancyBits.LeftLines"]
      76 [-]: LOADK R3 K28 ["Container.Dialog.LeftLines.FadeLineTop"]
      77 [-]: LOADK R4 K29 ["Container.Dialog.LeftLines.FadeLineMiddle"]
      78 [-]: LOADK R5 K30 ["Container.Dialog.LeftLines.FadeLineBottom"]
      79 [-]: SETLIST R1 R2 4 [1]
      80 [-]: LOADN R4 1   
      81 [-]: LENGTH R2 R1 
      82 [-]: LOADN R3 1   
      83 [-]: FORNPREP R2 L1
L 0:  84 [-]: GETIMPORT R5 5 [0xAE91E43B]
      85 [-]: GETTABLE R7 R1 R4
      86 [-]: GETIMPORT R8 32 [0x996808CC]
      87 [-]: NAMECALL R5 R5 K33 [0xD5181643]
      88 [-]: CALL R5 3 0  
      89 [-]: FORNLOOP R2 L0
L 1:  90 [-]: NEWTABLE R2 0 4
      91 [-]: LOADK R3 K34 ["Container.FancyBits.RightLines"]
      92 [-]: LOADK R4 K35 ["Container.Dialog.RightLines.FadeLineTop"]
      93 [-]: LOADK R5 K36 ["Container.Dialog.RightLines.FadeLineMiddle"]
      94 [-]: LOADK R6 K37 ["Container.Dialog.RightLines.FadeLineBottom"]
      95 [-]: SETLIST R2 R3 4 [1]
      96 [-]: MOVE R1 R2   
      97 [-]: LOADN R4 1   
      98 [-]: LENGTH R2 R1 
      99 [-]: LOADN R3 1   
     100 [-]: FORNPREP R2 L3
L 2: 101 [-]: GETIMPORT R5 5 [0xAE91E43B]
     102 [-]: GETTABLE R7 R1 R4
     103 [-]: GETIMPORT R8 39 [0xC9E06D1B]
     104 [-]: NAMECALL R5 R5 K33 [0xD5181643]
     105 [-]: CALL R5 3 0  
     106 [-]: FORNLOOP R2 L2
L 3: 107 [-]: GETIMPORT R2 5 [0xAE91E43B]
     108 [-]: LOADK R4 K40 ["Container.Dialog.BGPanel"]
     109 [-]: GETIMPORT R5 42 [0xDB848E18]
     110 [-]: NAMECALL R2 R2 K33 [0xD5181643]
     111 [-]: CALL R2 3 0  
     112 [-]: GETIMPORT R2 5 [0xAE91E43B]
     113 [-]: LOADK R4 K43 ["Container.Dialog.BGPanel2"]
     114 [-]: GETIMPORT R5 42 [0xDB848E18]
     115 [-]: NAMECALL R2 R2 K33 [0xD5181643]
     116 [-]: CALL R2 3 0  
     117 [-]: GETUPVAL R2 4
     118 [-]: CALL R2 0 0  
     119 [-]: GETIMPORT R2 46 [0xA7A2E381]
     120 [-]: CALL R2 0 1  
     121 [-]: JUMPIFNOT R2 L4
     122 [-]: GETIMPORT R2 5 [0xAE91E43B]
     123 [-]: LOADK R4 K47 ["Container.Dialog.Label"]
     124 [-]: LOADN R5 41  
     125 [-]: LOADK R6 K48 ["Arial Unicode MS"]
     126 [-]: NAMECALL R2 R2 K49 [0x5F56EEAB]
     127 [-]: CALL R2 4 0  
L 4: 128 [-]: LOADB R2 1   
     129 [-]: SETUPVAL R2 5
     130 [-]: RETURN R0 0  


; Name:            
; Defined at line: 96
; #Upvalues:       1
; #Parameters:     4
; Is_vararg:       0
; Max Stack Size:  18

       0 [-]: ORK R1 R1 K0 [0.5]
       1 [-]: ORK R2 R2 K1 [0.01]
       2 [-]: NEWCLOSURE R4 P0
       3 [-]: MOVE R0 R0   
       4 [-]: JUMPIFNOT R0 L0
       5 [-]: GETIMPORT R5 3 [0x25312C9B]
       6 [-]: GETIMPORT R6 5 [0xAE91E43B]
       7 [-]: LOADK R7 K6 ["Container.Dialog.BGPanel"]
       8 [-]: LOADN R8 2   
       9 [-]: NEWTABLE R9 0 1
      10 [-]: NEWCLOSURE R10 P1
      11 [-]: MOVE R0 R0   
      12 [-]: SETLIST R9 R10 1 [1]
      13 [-]: NEWTABLE R10 0 1
      14 [-]: LOADN R11 1  
      15 [-]: SETLIST R10 R11 1 [1]
      16 [-]: MOVE R11 R1  
      17 [-]: MOVE R12 R2  
      18 [-]: NEWCLOSURE R13 P2
      19 [-]: MOVE R1 R1   
      20 [-]: CALL R5 8 0  
      21 [-]: GETIMPORT R5 3 [0x25312C9B]
      22 [-]: GETIMPORT R6 5 [0xAE91E43B]
      23 [-]: LOADK R7 K7 ["Container.Dialog.BGPanel2"]
      24 [-]: LOADN R8 2   
      25 [-]: NEWTABLE R9 0 1
      26 [-]: NEWCLOSURE R10 P3
      27 [-]: MOVE R0 R0   
      28 [-]: SETLIST R9 R10 1 [1]
      29 [-]: NEWTABLE R10 0 1
      30 [-]: LOADN R11 1  
      31 [-]: SETLIST R10 R11 1 [1]
      32 [-]: MOVE R11 R1  
      33 [-]: LOADN R12 0  
      34 [-]: DUPCLOSURE R13 K8 []
      35 [-]: CALL R5 8 0  
      36 [-]: JUMP L1
     
L 0:  37 [-]: GETIMPORT R5 5 [0xAE91E43B]
      38 [-]: LOADK R7 K9 ["Container.Dialog.Blurer"]
      39 [-]: LOADN R8 10  
      40 [-]: LOADN R9 0   
      41 [-]: NAMECALL R5 R5 K10 [0x67BC869F]
      42 [-]: CALL R5 4 0  
      43 [-]: GETIMPORT R5 3 [0x25312C9B]
      44 [-]: GETIMPORT R6 5 [0xAE91E43B]
      45 [-]: LOADK R7 K6 ["Container.Dialog.BGPanel"]
      46 [-]: LOADN R8 1   
      47 [-]: NEWTABLE R9 0 1
      48 [-]: NEWCLOSURE R10 P5
      49 [-]: MOVE R0 R0   
      50 [-]: SETLIST R9 R10 1 [1]
      51 [-]: NEWTABLE R10 0 1
      52 [-]: LOADN R11 1  
      53 [-]: SETLIST R10 R11 1 [1]
      54 [-]: MOVE R11 R1  
      55 [-]: CALL R5 6 0  
L 1:  56 [-]: NEWCLOSURE R5 P6
      57 [-]: MOVE R0 R0   
      58 [-]: GETIMPORT R6 3 [0x25312C9B]
      59 [-]: GETIMPORT R7 5 [0xAE91E43B]
      60 [-]: LOADK R8 K11 ["Container.FancyBits"]
      61 [-]: LOADN R9 2   
      62 [-]: NEWTABLE R10 0 1
      63 [-]: MOVE R11 R5  
      64 [-]: SETLIST R10 R11 1 [1]
      65 [-]: NEWTABLE R11 0 1
      66 [-]: LOADK R12 K12 [0.69999999999999996]
      67 [-]: SETLIST R11 R12 1 [1]
      68 [-]: MOVE R12 R1  
      69 [-]: LOADN R13 0  
      70 [-]: CALL R6 7 0  
      71 [-]: DIVK R6 R1 K13 [2]
      72 [-]: GETUPVAL R8 0
      73 [-]: GETTABLEKS R7 R8 K14 [0x06D055F9]
      74 [-]: MOVE R8 R0   
      75 [-]: LOADK R9 K15 [0.050000000000000003]
      76 [-]: LOADN R10 0  
      77 [-]: CALL R7 3 1  
      78 [-]: GETUPVAL R9 0
      79 [-]: GETTABLEKS R8 R9 K14 [0x06D055F9]
      80 [-]: MOVE R9 R0   
      81 [-]: LOADN R10 100
      82 [-]: LOADN R11 0  
      83 [-]: CALL R8 3 1  
      84 [-]: GETIMPORT R9 3 [0x25312C9B]
      85 [-]: GETIMPORT R10 5 [0xAE91E43B]
      86 [-]: LOADK R11 K16 ["Container.Dialog.Label"]
      87 [-]: LOADN R12 2  
      88 [-]: NEWTABLE R13 0 1
      89 [-]: LOADN R14 10 
      90 [-]: SETLIST R13 R14 1 [1]
      91 [-]: NEWTABLE R14 0 1
      92 [-]: MOVE R15 R8  
      93 [-]: SETLIST R14 R15 1 [1]
      94 [-]: MOVE R15 R6  
      95 [-]: MOVE R16 R7  
      96 [-]: CALL R9 7 0  
      97 [-]: GETIMPORT R9 3 [0x25312C9B]
      98 [-]: GETIMPORT R10 5 [0xAE91E43B]
      99 [-]: LOADK R11 K17 ["Container.Dialog.Buttons"]
     100 [-]: LOADN R12 2  
     101 [-]: NEWTABLE R13 0 1
     102 [-]: LOADN R14 10 
     103 [-]: SETLIST R13 R14 1 [1]
     104 [-]: NEWTABLE R14 0 1
     105 [-]: MOVE R15 R8  
     106 [-]: SETLIST R14 R15 1 [1]
     107 [-]: MOVE R15 R6  
     108 [-]: MOVE R16 R7  
     109 [-]: MOVE R17 R3  
     110 [-]: CALL R9 8 0  
     111 [-]: CLOSEUPVALS R1
     112 [-]: RETURN R0 0  


; Name:            
; Defined at line: 147
; #Upvalues:       2
; #Parameters:     0
; Is_vararg:       0
; Max Stack Size:  2

       0 [-]: GETIMPORT R0 1 [0xAE91E43B]
       1 [-]: JUMPIFNOT R0 L1
       2 [-]: GETUPVAL R0 0
       3 [-]: JUMPXEQKNIL R0 L0
       4 [-]: GETUPVAL R0 0
       5 [-]: NAMECALL R0 R0 K2 [0x71E9AC81]
       6 [-]: CALL R0 1 0  
L 0:   7 [-]: GETUPVAL R0 1
       8 [-]: JUMPXEQKNIL R0 L1
       9 [-]: GETUPVAL R0 1
      10 [-]: NAMECALL R0 R0 K2 [0x71E9AC81]
      11 [-]: CALL R0 1 0  
L 1:  12 [-]: RETURN R0 0  


; Name:            
; Defined at line: 158
; #Upvalues:       0
; #Parameters:     0
; Is_vararg:       0
; Max Stack Size:  8

       0 [-]: GETIMPORT R0 1 [0xAE91E43B]
       1 [-]: LOADK R2 K2 ["Container.Dialog.Label.text"]
       2 [-]: GETIMPORT R3 5 ["UserInvitePending"]
       3 [-]: LOADB R4 1   
       4 [-]: NAMECALL R0 R0 K6 [0x20B98DB3]
       5 [-]: CALL R0 4 0  
       6 [-]: GETIMPORT R0 1 [0xAE91E43B]
       7 [-]: LOADK R2 K7 ["Container.Dialog.Label"]
       8 [-]: LOADN R3 34  
       9 [-]: NAMECALL R0 R0 K8 [0x91A24E4B]
      10 [-]: CALL R0 3 1  
      11 [-]: JUMPXEQKNIL R0 L0
      12 [-]: ADDK R1 R0 K9 [75]
      13 [-]: GETIMPORT R2 1 [0xAE91E43B]
      14 [-]: LOADK R4 K10 ["Container.Dialog"]
      15 [-]: LOADN R5 1   
      16 [-]: MINUS R6 R1  
      17 [-]: NAMECALL R2 R2 K11 [0x67BC869F]
      18 [-]: CALL R2 4 0  
      19 [-]: GETIMPORT R2 1 [0xAE91E43B]
      20 [-]: LOADK R4 K12 ["Container.FancyBits"]
      21 [-]: LOADN R5 1   
      22 [-]: MINUS R7 R1  
      23 [-]: DIVK R6 R7 K13 [2]
      24 [-]: NAMECALL R2 R2 K11 [0x67BC869F]
      25 [-]: CALL R2 4 0  
      26 [-]: GETIMPORT R2 1 [0xAE91E43B]
      27 [-]: LOADK R4 K14 ["Container.Dialog.BGPanel"]
      28 [-]: LOADN R5 13  
      29 [-]: MOVE R6 R1   
      30 [-]: NAMECALL R2 R2 K11 [0x67BC869F]
      31 [-]: CALL R2 4 0  
      32 [-]: GETIMPORT R2 1 [0xAE91E43B]
      33 [-]: LOADK R4 K15 ["Container.Dialog.BGPanel2"]
      34 [-]: LOADN R5 13  
      35 [-]: MOVE R6 R1   
      36 [-]: NAMECALL R2 R2 K11 [0x67BC869F]
      37 [-]: CALL R2 4 0  
      38 [-]: GETIMPORT R2 1 [0xAE91E43B]
      39 [-]: LOADK R4 K16 ["Container.Dialog.Blurer"]
      40 [-]: LOADN R5 13  
      41 [-]: MOVE R6 R1   
      42 [-]: NAMECALL R2 R2 K11 [0x67BC869F]
      43 [-]: CALL R2 4 0  
      44 [-]: GETIMPORT R2 1 [0xAE91E43B]
      45 [-]: LOADK R4 K17 ["Container.Dialog.AcceptButton"]
      46 [-]: LOADN R5 1   
      47 [-]: ADDK R6 R0 K18 [32]
      48 [-]: NAMECALL R2 R2 K11 [0x67BC869F]
      49 [-]: CALL R2 4 0  
      50 [-]: GETIMPORT R2 1 [0xAE91E43B]
      51 [-]: LOADK R4 K19 ["Container.Dialog.DeclineButton"]
      52 [-]: LOADN R5 1   
      53 [-]: ADDK R6 R0 K18 [32]
      54 [-]: NAMECALL R2 R2 K11 [0x67BC869F]
      55 [-]: CALL R2 4 0  
L 0:  56 [-]: RETURN R0 0  


; Name:            
; Defined at line: 174
; #Upvalues:       6
; #Parameters:     0
; Is_vararg:       0
; Max Stack Size:  9

       0 [-]: GETIMPORT R1 1 [0xAE91E43B]
       1 [-]: FASTCALL1 62 R1 L0
       2 [-]: GETIMPORT R0 3 [0x7B998233]
       3 [-]: CALL R0 1 1  
L 0:   4 [-]: JUMPIF R0 L1 
       5 [-]: GETUPVAL R0 0
       6 [-]: JUMPIF R0 L2 
L 1:   7 [-]: RETURN R0 0  
L 2:   8 [-]: GETIMPORT R0 1 [0xAE91E43B]
       9 [-]: GETIMPORT R2 5 [0xB693B6C1]
      10 [-]: CALL R2 0 -1 
      11 [-]: NAMECALL R0 R0 K6 [0x8A8C8D5A]
      12 [-]: CALL R0 -1 0 
      13 [-]: GETIMPORT R0 1 [0xAE91E43B]
      14 [-]: GETIMPORT R3 9 ["RadialSolarMapOpen"]
      15 [-]: JUMPXEQKB R3 1 L3
      16 [-]: LOADB R2 0 +1
L 3:  17 [-]: LOADB R2 1   
L 4:  18 [-]: NAMECALL R0 R0 K10 [0x2002E1DC]
      19 [-]: CALL R0 2 0  
      20 [-]: GETUPVAL R0 1
      21 [-]: GETIMPORT R1 12 [0x9BA7909F]
      22 [-]: GETIMPORT R4 14 [0x0032441C]
      23 [-]: GETTABLEKS R3 R4 K15 ["UIMovie_SolarMap"]
      24 [-]: NAMECALL R1 R1 K16 [0xBCFB64AB]
      25 [-]: CALL R1 2 1  
      26 [-]: SETUPVAL R1 2
      27 [-]: GETUPVAL R3 2
      28 [-]: FASTCALL1 62 R3 L5
      29 [-]: GETIMPORT R2 3 [0x7B998233]
      30 [-]: CALL R2 1 1  
L 5:  31 [-]: JUMPIFNOT R2 L6
      32 [-]: GETIMPORT R2 18 ["TopMenuOpen"]
      33 [-]: NOT R1 R2    
      34 [-]: JUMPIF R1 L9 
L 6:  35 [-]: GETIMPORT R3 20 ["UserInvitePending"]
      36 [-]: FASTCALL1 62 R3 L7
      37 [-]: GETIMPORT R2 3 [0x7B998233]
      38 [-]: CALL R2 1 1  
L 7:  39 [-]: JUMPIFNOT R2 L8
      40 [-]: GETIMPORT R2 22 ["UserInGameInvitePending"]
      41 [-]: NOT R1 R2    
      42 [-]: JUMPIF R1 L9 
L 8:  43 [-]: GETIMPORT R2 14 [0x0032441C]
      44 [-]: GETTABLEKS R1 R2 K23 ["mDoNotDisturb"]
      45 [-]: JUMPIF R1 L9 
      46 [-]: GETIMPORT R1 25 ["IsScreenOpen"]
      47 [-]: LOADK R2 K26 ["Friends"]
      48 [-]: CALL R1 1 1  
      49 [-]: JUMPIF R1 L9 
      50 [-]: GETIMPORT R1 25 ["IsScreenOpen"]
      51 [-]: LOADK R2 K27 ["Inbox"]
      52 [-]: CALL R1 1 1  
      53 [-]: JUMPIF R1 L9 
      54 [-]: GETIMPORT R1 25 ["IsScreenOpen"]
      55 [-]: LOADK R2 K28 ["Profile"]
      56 [-]: CALL R1 1 1  
      57 [-]: JUMPIF R1 L9 
      58 [-]: GETIMPORT R1 25 ["IsScreenOpen"]
      59 [-]: LOADK R2 K29 ["Clan"]
      60 [-]: CALL R1 1 1  
      61 [-]: JUMPIF R1 L9 
      62 [-]: GETIMPORT R1 25 ["IsScreenOpen"]
      63 [-]: LOADK R2 K30 ["ClanSearch"]
      64 [-]: CALL R1 1 1  
      65 [-]: JUMPIF R1 L9 
      66 [-]: GETIMPORT R1 25 ["IsScreenOpen"]
      67 [-]: LOADK R2 K31 ["Settings"]
      68 [-]: CALL R1 1 1  
L 9:  69 [-]: SETUPVAL R1 1
      70 [-]: GETUPVAL R1 1
      71 [-]: JUMPIFEQ R0 R1 L12
      72 [-]: GETUPVAL R1 1
      73 [-]: JUMPIFNOT R1 L10
      74 [-]: GETIMPORT R1 1 [0xAE91E43B]
      75 [-]: LOADK R3 K32 ["Container.Dialog.BGPanel"]
      76 [-]: LOADN R4 10  
      77 [-]: LOADN R5 100 
      78 [-]: NAMECALL R1 R1 K33 [0x67BC869F]
      79 [-]: CALL R1 4 0  
      80 [-]: GETUPVAL R1 3
      81 [-]: LOADB R2 0   
      82 [-]: LOADK R3 K34 [0.25]
      83 [-]: LOADNIL R4   
      84 [-]: DUPCLOSURE R5 K35 []
      85 [-]: CALL R1 4 0  
      86 [-]: JUMP L11
    
L10:  87 [-]: GETIMPORT R1 1 [0xAE91E43B]
      88 [-]: LOADK R3 K36 ["_root"]
      89 [-]: LOADN R4 11  
      90 [-]: LOADB R5 1   
      91 [-]: NAMECALL R1 R1 K37 [0xAADE900E]
      92 [-]: CALL R1 4 0  
      93 [-]: GETIMPORT R1 1 [0xAE91E43B]
      94 [-]: LOADK R3 K38 ["Container.Dialog.Blurer"]
      95 [-]: LOADN R4 10  
      96 [-]: LOADN R5 0   
      97 [-]: NAMECALL R1 R1 K33 [0x67BC869F]
      98 [-]: CALL R1 4 0  
      99 [-]: GETIMPORT R1 1 [0xAE91E43B]
     100 [-]: LOADK R3 K39 ["Container.Dialog.BGPanel2"]
     101 [-]: LOADN R4 10  
     102 [-]: LOADN R5 100 
     103 [-]: NAMECALL R1 R1 K33 [0x67BC869F]
     104 [-]: CALL R1 4 0  
     105 [-]: GETIMPORT R1 1 [0xAE91E43B]
     106 [-]: LOADK R3 K39 ["Container.Dialog.BGPanel2"]
     107 [-]: LOADK R4 K40 ["AlphaTestThreshold"]
     108 [-]: LOADN R5 0   
     109 [-]: LOADN R6 0   
     110 [-]: LOADN R7 1   
     111 [-]: LOADN R8 1   
     112 [-]: NAMECALL R1 R1 K41 [0x91E13703]
     113 [-]: CALL R1 7 0  
     114 [-]: GETUPVAL R1 4
     115 [-]: CALL R1 0 0  
     116 [-]: GETUPVAL R1 3
     117 [-]: LOADB R2 1   
     118 [-]: LOADK R3 K42 [0.5]
     119 [-]: LOADNIL R4   
     120 [-]: CALL R1 3 0  
     121 [-]: GETIMPORT R1 22 ["UserInGameInvitePending"]
     122 [-]: JUMPIFNOT R1 L11
     123 [-]: GETUPVAL R1 5
     124 [-]: LOADB R3 0   
     125 [-]: NAMECALL R1 R1 K43 [0x46610C50]
     126 [-]: CALL R1 2 0  
L11: 127 [-]: GETIMPORT R1 1 [0xAE91E43B]
     128 [-]: GETUPVAL R3 1
     129 [-]: NAMECALL R1 R1 K44 [0xBED40E9C]
     130 [-]: CALL R1 2 0  
L12: 131 [-]: GETUPVAL R1 1
     132 [-]: JUMPIF R1 L13
     133 [-]: GETIMPORT R1 1 [0xAE91E43B]
     134 [-]: LOADK R3 K45 ["Container.Dialog.Label"]
     135 [-]: LOADN R4 29  
     136 [-]: NAMECALL R1 R1 K46 [0x54A95D6F]
     137 [-]: CALL R1 3 1  
     138 [-]: GETIMPORT R2 20 ["UserInvitePending"]
     139 [-]: JUMPIFEQ R1 R2 L13
     140 [-]: GETUPVAL R1 4
     141 [-]: CALL R1 0 0  
L13: 142 [-]: RETURN R0 0  


; Name:            
; Defined at line: 229
; #Upvalues:       1
; #Parameters:     0
; Is_vararg:       0
; Max Stack Size:  5

       0 [-]: GETUPVAL R0 0
       1 [-]: JUMPIFNOT R0 L0
       2 [-]: GETIMPORT R0 1 [0xAE91E43B]
       3 [-]: LOADK R2 K2 ["_root"]
       4 [-]: LOADN R3 11  
       5 [-]: LOADB R4 0   
       6 [-]: NAMECALL R0 R0 K3 [0xAADE900E]
       7 [-]: CALL R0 4 0  
L 0:   8 [-]: RETURN R0 0  


; Name:            
; Defined at line: 235
; #Upvalues:       1
; #Parameters:     0
; Is_vararg:       0
; Max Stack Size:  5

       0 [-]: GETIMPORT R0 2 ["UserInGameInvitePending"]
       1 [-]: JUMPIFNOT R0 L0
       2 [-]: GETIMPORT R0 3 ["_T"]
       3 [-]: LOADNIL R1   
       4 [-]: SETTABLEKS R1 R0 K4 ["UserInvitePending"]
       5 [-]: GETIMPORT R0 3 ["_T"]
       6 [-]: LOADNIL R1   
       7 [-]: SETTABLEKS R1 R0 K1 ["UserInGameInvitePending"]
       8 [-]: RETURN R0 0  
L 0:   9 [-]: GETIMPORT R1 6 ["SquadOverlay"]
      10 [-]: FASTCALL1 62 R1 L1
      11 [-]: GETIMPORT R0 8 [0x7B998233]
      12 [-]: CALL R0 1 1  
L 1:  13 [-]: JUMPIF R0 L2 
      14 [-]: GETUPVAL R1 0
      15 [-]: GETTABLEKS R0 R1 K9 [0x659D451F]
      16 [-]: GETIMPORT R2 11 [0x0032441C]
      17 [-]: GETTABLEKS R1 R2 K12 ["UISound_Select"]
      18 [-]: CALL R0 1 0  
      19 [-]: GETUPVAL R1 0
      20 [-]: GETTABLEKS R0 R1 K9 [0x659D451F]
      21 [-]: GETIMPORT R2 11 [0x0032441C]
      22 [-]: GETTABLEKS R1 R2 K13 ["UISound_ButtonSelect"]
      23 [-]: CALL R0 1 0  
      24 [-]: GETUPVAL R1 0
      25 [-]: GETTABLEKS R0 R1 K9 [0x659D451F]
      26 [-]: GETIMPORT R2 11 [0x0032441C]
      27 [-]: GETTABLEKS R1 R2 K14 ["UISound_DialogOpen"]
      28 [-]: CALL R0 1 0  
      29 [-]: GETIMPORT R0 6 ["SquadOverlay"]
      30 [-]: LOADK R2 K15 ["JoinInviteConfirm"]
      31 [-]: GETIMPORT R3 17 [0x64FB1586]
      32 [-]: LOADN R4 4   
      33 [-]: CALL R3 1 -1 
      34 [-]: NAMECALL R0 R0 K18 [0xE4162EED]
      35 [-]: CALL R0 -1 0 
L 2:  36 [-]: RETURN R0 0  


; Name:            
; Defined at line: 249
; #Upvalues:       1
; #Parameters:     0
; Is_vararg:       0
; Max Stack Size:  5

       0 [-]: GETIMPORT R1 2 ["SquadOverlay"]
       1 [-]: FASTCALL1 62 R1 L0
       2 [-]: GETIMPORT R0 4 [0x7B998233]
       3 [-]: CALL R0 1 1  
L 0:   4 [-]: JUMPIF R0 L1 
       5 [-]: GETUPVAL R1 0
       6 [-]: GETTABLEKS R0 R1 K5 [0x659D451F]
       7 [-]: GETIMPORT R2 7 [0x0032441C]
       8 [-]: GETTABLEKS R1 R2 K8 ["UISound_Select"]
       9 [-]: CALL R0 1 0  
      10 [-]: GETUPVAL R1 0
      11 [-]: GETTABLEKS R0 R1 K5 [0x659D451F]
      12 [-]: GETIMPORT R2 7 [0x0032441C]
      13 [-]: GETTABLEKS R1 R2 K9 ["UISound_GridOpenTwo"]
      14 [-]: CALL R0 1 0  
      15 [-]: GETIMPORT R0 2 ["SquadOverlay"]
      16 [-]: LOADK R2 K10 ["JoinInviteConfirm"]
      17 [-]: GETIMPORT R3 12 [0x64FB1586]
      18 [-]: LOADN R4 5   
      19 [-]: CALL R3 1 -1 
      20 [-]: NAMECALL R0 R0 K13 [0xE4162EED]
      21 [-]: CALL R0 -1 0 
L 1:  22 [-]: RETURN R0 0  


; Name:            
; Defined at line: 257
; #Upvalues:       1
; #Parameters:     0
; Is_vararg:       0
; Max Stack Size:  1

       0 [-]: GETUPVAL R0 0
       1 [-]: RETURN R0 1  


; Name:            
; Defined at line: 261
; #Upvalues:       1
; #Parameters:     4
; Is_vararg:       0
; Max Stack Size:  8

       0 [-]: GETUPVAL R5 0
       1 [-]: FASTCALL1 62 R5 L0
       2 [-]: GETIMPORT R4 1 [0x7B998233]
       3 [-]: CALL R4 1 1  
L 0:   4 [-]: JUMPIF R4 L1 
       5 [-]: GETUPVAL R4 0
       6 [-]: MOVE R6 R0   
       7 [-]: MOVE R7 R1   
       8 [-]: NAMECALL R4 R4 K2 [0xFAA69527]
       9 [-]: CALL R4 3 0  
L 1:  10 [-]: RETURN R0 0  


; Name:            
; Defined at line: 267
; #Upvalues:       1
; #Parameters:     0
; Is_vararg:       0
; Max Stack Size:  5

       0 [-]: GETUPVAL R1 0
       1 [-]: FASTCALL1 62 R1 L0
       2 [-]: GETIMPORT R0 1 [0x7B998233]
       3 [-]: CALL R0 1 1  
L 0:   4 [-]: JUMPIF R0 L1 
       5 [-]: GETUPVAL R0 0
       6 [-]: GETIMPORT R2 3 [0xAE91E43B]
       7 [-]: NAMECALL R2 R2 K4 [0x6B837788]
       8 [-]: CALL R2 1 1  
       9 [-]: GETIMPORT R3 3 [0xAE91E43B]
      10 [-]: NAMECALL R3 R3 K5 [0xAF9FDA9F]
      11 [-]: CALL R3 1 -1 
      12 [-]: NAMECALL R0 R0 K6 [0xFAA69527]
      13 [-]: CALL R0 -1 0 
L 1:  14 [-]: RETURN R0 0  


; Name:            
; Defined at line: 275
; #Upvalues:       1
; #Parameters:     0
; Is_vararg:       0
; Max Stack Size:  5

       0 [-]: GETIMPORT R0 2 [0x1467D5F4]
       1 [-]: CALL R0 0 1  
       2 [-]: JUMPIF R0 L1 
       3 [-]: GETIMPORT R0 4 [0x9BA7909F]
       4 [-]: GETUPVAL R3 0
       5 [-]: GETTABLEKS R2 R3 K5 [0xC472E470]
       6 [-]: CALL R2 0 -1 
       7 [-]: NAMECALL R0 R0 K6 [0xBCFB64AB]
       8 [-]: CALL R0 -1 1 
       9 [-]: FASTCALL1 62 R0 L0
      10 [-]: MOVE R2 R0   
      11 [-]: GETIMPORT R1 8 [0x7B998233]
      12 [-]: CALL R1 1 1  
L 0:  13 [-]: JUMPIF R1 L1 
      14 [-]: LOADK R3 K9 ["IsFull"]
      15 [-]: LOADK R4 K10 [""]
      16 [-]: NAMECALL R1 R0 K11 [0xE4162EED]
      17 [-]: CALL R1 3 1  
      18 [-]: JUMPIFNOT R1 L1
      19 [-]: LOADB R1 0   
      20 [-]: RETURN R1 1  
L 1:  21 [-]: LOADB R0 1   
      22 [-]: RETURN R0 1  


; Name:            
; Defined at line: 286
; #Upvalues:       3
; #Parameters:     0
; Is_vararg:       0
; Max Stack Size:  2

       0 [-]: GETUPVAL R0 0
       1 [-]: CALL R0 0 1  
       2 [-]: JUMPIFNOT R0 L0
       3 [-]: GETUPVAL R0 1
       4 [-]: JUMPIF R0 L0 
       5 [-]: GETIMPORT R0 2 [0x1467D5F4]
       6 [-]: CALL R0 0 1  
       7 [-]: JUMPIF R0 L0 
       8 [-]: GETUPVAL R0 2
       9 [-]: NAMECALL R0 R0 K3 [0xDB2B9A70]
      10 [-]: CALL R0 1 0  
      11 [-]: LOADB R0 1   
      12 [-]: RETURN R0 1  
L 0:  13 [-]: LOADB R0 0   
      14 [-]: RETURN R0 1  


; Name:            
; Defined at line: 296
; #Upvalues:       3
; #Parameters:     0
; Is_vararg:       0
; Max Stack Size:  2

       0 [-]: GETUPVAL R0 0
       1 [-]: CALL R0 0 1  
       2 [-]: JUMPIFNOT R0 L2
       3 [-]: GETUPVAL R0 1
       4 [-]: JUMPIF R0 L2 
       5 [-]: GETUPVAL R1 2
       6 [-]: FASTCALL1 62 R1 L0
       7 [-]: GETIMPORT R0 1 [0x7B998233]
       8 [-]: CALL R0 1 1  
L 0:   9 [-]: JUMPIF R0 L1 
      10 [-]: GETUPVAL R0 2
      11 [-]: NAMECALL R0 R0 K2 [0xDB2B9A70]
      12 [-]: CALL R0 1 0  
L 1:  13 [-]: LOADB R0 1   
      14 [-]: RETURN R0 1  
L 2:  15 [-]: LOADB R0 0   
      16 [-]: RETURN R0 1  


; Name:            
; Defined at line: 307
; #Upvalues:       3
; #Parameters:     0
; Is_vararg:       0
; Max Stack Size:  2

       0 [-]: GETUPVAL R0 0
       1 [-]: CALL R0 0 1  
       2 [-]: JUMPIFNOT R0 L2
       3 [-]: GETUPVAL R0 1
       4 [-]: JUMPIF R0 L2 
       5 [-]: GETIMPORT R0 2 [0x1467D5F4]
       6 [-]: CALL R0 0 1  
       7 [-]: JUMPIFNOT R0 L2
       8 [-]: GETUPVAL R1 2
       9 [-]: FASTCALL1 62 R1 L0
      10 [-]: GETIMPORT R0 4 [0x7B998233]
      11 [-]: CALL R0 1 1  
L 0:  12 [-]: JUMPIF R0 L1 
      13 [-]: GETUPVAL R0 2
      14 [-]: NAMECALL R0 R0 K5 [0xDB2B9A70]
      15 [-]: CALL R0 1 0  
L 1:  16 [-]: LOADB R0 1   
      17 [-]: RETURN R0 1  
L 2:  18 [-]: LOADB R0 0   
      19 [-]: RETURN R0 1  


; Name:            
; Defined at line: 318
; #Upvalues:       0
; #Parameters:     0
; Is_vararg:       0
; Max Stack Size:  2

       0 [-]: GETIMPORT R0 2 [0x1467D5F4]
       1 [-]: CALL R0 0 1  
       2 [-]: JUMPIFNOT R0 L1
       3 [-]: GETIMPORT R1 4 [0xBE190284]
       4 [-]: FASTCALL1 62 R1 L0
       5 [-]: GETIMPORT R0 6 [0x7B998233]
       6 [-]: CALL R0 1 1  
L 0:   7 [-]: JUMPIF R0 L1 
       8 [-]: GETIMPORT R0 4 [0xBE190284]
       9 [-]: NAMECALL R0 R0 K7 [0x9AC735D2]
      10 [-]: CALL R0 1 1  
      11 [-]: JUMPIFNOT R0 L1
      12 [-]: GETIMPORT R0 4 [0xBE190284]
      13 [-]: NAMECALL R0 R0 K8 [0xAEB5AA53]
      14 [-]: CALL R0 1 0  
      15 [-]: LOADB R0 1   
      16 [-]: RETURN R0 1  
L 1:  17 [-]: LOADB R0 0   
      18 [-]: RETURN R0 1  


; Name:            
; Defined at line: 327
; #Upvalues:       2
; #Parameters:     1
; Is_vararg:       0
; Max Stack Size:  3

       0 [-]: GETUPVAL R2 0
       1 [-]: FASTCALL1 62 R2 L0
       2 [-]: GETIMPORT R1 1 [0x7B998233]
       3 [-]: CALL R1 1 1  
L 0:   4 [-]: JUMPIF R1 L1 
       5 [-]: GETUPVAL R1 0
       6 [-]: NAMECALL R1 R1 K2 [0x71E9AC81]
       7 [-]: CALL R1 1 0  
L 1:   8 [-]: GETUPVAL R2 1
       9 [-]: FASTCALL1 62 R2 L2
      10 [-]: GETIMPORT R1 1 [0x7B998233]
      11 [-]: CALL R1 1 1  
L 2:  12 [-]: JUMPIF R1 L3 
      13 [-]: GETUPVAL R1 1
      14 [-]: NAMECALL R1 R1 K2 [0x71E9AC81]
      15 [-]: CALL R1 1 0  
L 3:  16 [-]: RETURN R0 0  


; Name:            
; Defined at line: 336
; #Upvalues:       1
; #Parameters:     0
; Is_vararg:       0
; Max Stack Size:  1

       0 [-]: GETUPVAL R0 0
       1 [-]: CALL R0 0 0  
       2 [-]: RETURN R0 0  


; Name:            
; Defined at line: 340
; #Upvalues:       0
; #Parameters:     0
; Is_vararg:       0
; Max Stack Size:  1

       0 [-]: LOADB R0 1   
       1 [-]: RETURN R0 1  



