; Name:            
; Defined at line: 1
; #Upvalues:       0
; #Parameters:     0
; Is_vararg:       1
; Max Stack Size:  54

            1 [-]: GETIMPORT R0 1 [nil]
       2 [-]: LOADK R1 K2 ["EE.Interface.Utilities"]
       3 [-]: CALL R0 1 1  
       4 [-]: GETIMPORT R1 1 [nil]
       5 [-]: LOADK R2 K3 ["Lotus.Interface.LotusUtilities"]
       6 [-]: CALL R1 1 1  
       7 [-]: GETIMPORT R2 1 [nil]
       8 [-]: LOADK R3 K4 ["Lotus.Interface.UIUtilities"]
       9 [-]: CALL R2 1 1  
      10 [-]: GETIMPORT R3 1 [nil]
      11 [-]: LOADK R4 K5 ["Lotus.Interface.StoreItemUtilities"]
      12 [-]: CALL R3 1 1  
      13 [-]: GETIMPORT R4 1 [nil]
      14 [-]: LOADK R5 K6 ["Lotus.Interface.UIStyleUtilities"]
      15 [-]: CALL R4 1 1  
      16 [-]: GETIMPORT R5 1 [nil]
      17 [-]: LOADK R6 K7 ["Lotus.Interface.LoadoutUtilities"]
      18 [-]: CALL R5 1 1  
      19 [-]: GETIMPORT R6 1 [nil]
      20 [-]: LOADK R7 K8 ["EE.Interface.AnchorMgr"]
      21 [-]: CALL R6 1 1  
      22 [-]: GETIMPORT R7 1 [nil]
      23 [-]: LOADK R8 K9 ["Lotus.Interface.Libs.PreviewLinkUtilities"]
      24 [-]: CALL R7 1 1  
      25 [-]: DUPTABLE R8 13
      26 [-]: LOADN R9 0   
      27 [-]: SETTABLEKS R9 R8 K10 ["Center"]
      28 [-]: LOADK R9 K14 [0.34999999999999998]
      29 [-]: SETTABLEKS R9 R8 K11 ["Size"]
      30 [-]: LOADK R9 K15 [0.25]
      31 [-]: SETTABLEKS R9 R8 K12 ["FadeSize"]
      32 [-]: GETIMPORT R9 17 [nil]
      33 [-]: LOADK R10 K18 ["/Lotus/Types/Vehicles/Hoverboard/HoverboardSuit"]
      34 [-]: CALL R9 1 1  
      35 [-]: GETIMPORT R10 17 [nil]
      36 [-]: LOADK R11 K19 ["/Lotus/Types/Friendly/Pets/MoaPets/MoaPetPowerSuit"]
      37 [-]: CALL R10 1 1 
      38 [-]: GETIMPORT R11 17 [nil]
      39 [-]: LOADK R12 K20 ["/Lotus/Interface/LoadOutRedux.swf"]
      40 [-]: CALL R11 1 1 
      41 [-]: GETIMPORT R12 17 [nil]
      42 [-]: LOADK R13 K21 ["/Lotus/Upgrades/Skins/UnlockAnimSetBase"]
      43 [-]: CALL R12 1 1 
      44 [-]: DUPTABLE R13 26
      45 [-]: LOADNIL R14  
      46 [-]: SETTABLEKS R14 R13 K22 ["Loader"]
      47 [-]: LOADNIL R14  
      48 [-]: SETTABLEKS R14 R13 K23 ["SecondaryLoader"]
      49 [-]: LOADB R14 0  
      50 [-]: SETTABLEKS R14 R13 K24 ["IsLoading"]
      51 [-]: LOADB R14 0  
      52 [-]: SETTABLEKS R14 R13 K25 ["IsLoadingSecond"]
      53 [-]: LOADNIL R14  
      54 [-]: LOADB R15 0  
      55 [-]: LOADNIL R16  
      56 [-]: LOADNIL R17  
      57 [-]: NEWTABLE R18 2 0
      58 [-]: LOADNIL R19  
      59 [-]: LOADNIL R20  
      60 [-]: LOADNIL R21  
      61 [-]: LOADNIL R22  
      62 [-]: LOADB R23 0  
      63 [-]: LOADNIL R24  
      64 [-]: NEWTABLE R25 2 0
      65 [-]: NEWTABLE R26 0 0
      66 [-]: LOADB R27 0  
      67 [-]: LOADB R28 0  
      68 [-]: NEWTABLE R29 0 0
      69 [-]: NEWTABLE R30 0 0
      70 [-]: LOADB R31 0  
      71 [-]: LOADNIL R32  
      72 [-]: LOADN R33 0  
      73 [-]: NEWTABLE R34 0 0
      74 [-]: LOADNIL R35  
      75 [-]: NEWCLOSURE R36 P0
      76 [-]: MOVE R1 R23  
      77 [-]: SETGLOBAL R36 K27 ["IsInputBlocked"]
      78 [-]: NEWCLOSURE R36 P1
      79 [-]: MOVE R1 R24  
      80 [-]: DUPCLOSURE R37 K28 []
      81 [-]: NEWCLOSURE R38 P3
      82 [-]: MOVE R1 R26  
      83 [-]: MOVE R0 R38  
      84 [-]: NEWCLOSURE R39 P4
      85 [-]: MOVE R1 R26  
      86 [-]: NEWCLOSURE R40 P5
      87 [-]: MOVE R1 R35  
      88 [-]: MOVE R1 R34  
      89 [-]: MOVE R0 R3   
      90 [-]: MOVE R1 R28  
      91 [-]: MOVE R0 R8   
      92 [-]: MOVE R1 R30  
      93 [-]: NEWCLOSURE R41 P6
      94 [-]: MOVE R1 R25  
      95 [-]: MOVE R1 R17  
      96 [-]: MOVE R1 R20  
      97 [-]: NEWCLOSURE R42 P7
      98 [-]: MOVE R1 R34  
      99 [-]: MOVE R1 R25  
     100 [-]: MOVE R0 R5   
     101 [-]: MOVE R0 R37  
     102 [-]: MOVE R0 R12  
     103 [-]: MOVE R1 R26  
     104 [-]: MOVE R0 R38  
     105 [-]: MOVE R0 R40  
     106 [-]: MOVE R0 R13  
     107 [-]: MOVE R0 R41  
     108 [-]: MOVE R1 R20  
     109 [-]: NEWCLOSURE R43 P8
     110 [-]: MOVE R1 R21  
     111 [-]: MOVE R0 R7   
     112 [-]: MOVE R1 R25  
     113 [-]: MOVE R1 R27  
     114 [-]: MOVE R1 R26  
     115 [-]: MOVE R0 R1   
     116 [-]: MOVE R0 R39  
     117 [-]: MOVE R0 R13  
     118 [-]: MOVE R0 R42  
     119 [-]: NEWCLOSURE R44 P9
     120 [-]: MOVE R1 R25  
     121 [-]: MOVE R1 R32  
     122 [-]: MOVE R0 R0   
     123 [-]: DUPCLOSURE R45 K29 []
     124 [-]: MOVE R0 R44  
     125 [-]: MOVE R0 R9   
     126 [-]: MOVE R0 R10  
     127 [-]: DUPCLOSURE R46 K30 []
     128 [-]: MOVE R0 R2   
     129 [-]: MOVE R0 R36  
     130 [-]: NEWCLOSURE R47 P12
     131 [-]: MOVE R1 R22  
     132 [-]: MOVE R1 R27  
     133 [-]: MOVE R1 R30  
     134 [-]: MOVE R1 R28  
     135 [-]: MOVE R1 R15  
     136 [-]: MOVE R0 R2   
     137 [-]: MOVE R0 R29  
     138 [-]: MOVE R0 R1   
     139 [-]: MOVE R1 R31  
     140 [-]: MOVE R1 R24  
     141 [-]: SETGLOBAL R47 K31 ["Shutdown"]
     142 [-]: NEWCLOSURE R47 P13
     143 [-]: MOVE R1 R21  
     144 [-]: MOVE R1 R22  
     145 [-]: MOVE R1 R23  
     146 [-]: MOVE R1 R32  
     147 [-]: MOVE R1 R33  
     148 [-]: MOVE R0 R5   
     149 [-]: MOVE R1 R25  
     150 [-]: SETGLOBAL R47 K32 ["ApplyAppearance"]
     151 [-]: NEWCLOSURE R47 P14
     152 [-]: MOVE R0 R0   
     153 [-]: MOVE R1 R32  
     154 [-]: MOVE R1 R33  
     155 [-]: MOVE R0 R44  
     156 [-]: SETGLOBAL R47 K33 ["EquipAppearance"]
     157 [-]: NEWCLOSURE R47 P15
     158 [-]: MOVE R1 R32  
     159 [-]: MOVE R1 R33  
     160 [-]: MOVE R0 R5   
     161 [-]: MOVE R0 R1   
     162 [-]: SETGLOBAL R47 K34 ["ConfirmEquipAppearance"]
     163 [-]: NEWCLOSURE R47 P16
     164 [-]: MOVE R0 R1   
     165 [-]: MOVE R1 R25  
     166 [-]: MOVE R1 R32  
     167 [-]: MOVE R1 R33  
     168 [-]: MOVE R0 R11  
     169 [-]: MOVE R0 R36  
     170 [-]: SETGLOBAL R47 K35 ["OnSaveLoadOutComplete"]
     171 [-]: DUPCLOSURE R47 K36 []
     172 [-]: SETGLOBAL R47 K37 ["OnUpdateSessionSettings"]
     173 [-]: NEWCLOSURE R47 P18
     174 [-]: MOVE R1 R35  
     175 [-]: MOVE R0 R0   
     176 [-]: NEWCLOSURE R48 P19
     177 [-]: MOVE R1 R26  
     178 [-]: MOVE R0 R1   
     179 [-]: MOVE R0 R42  
     180 [-]: MOVE R1 R22  
     181 [-]: NEWCLOSURE R49 P20
     182 [-]: MOVE R1 R35  
     183 [-]: MOVE R0 R2   
     184 [-]: MOVE R0 R48  
     185 [-]: MOVE R1 R22  
     186 [-]: MOVE R1 R18  
     187 [-]: MOVE R0 R47  
     188 [-]: NEWCLOSURE R50 P21
     189 [-]: MOVE R1 R18  
     190 [-]: MOVE R0 R4   
     191 [-]: MOVE R1 R14  
     192 [-]: MOVE R1 R30  
     193 [-]: MOVE R0 R2   
     194 [-]: MOVE R0 R29  
     195 [-]: MOVE R0 R1   
     196 [-]: MOVE R1 R31  
     197 [-]: MOVE R1 R16  
     198 [-]: MOVE R1 R17  
     199 [-]: MOVE R0 R0   
     200 [-]: MOVE R1 R19  
     201 [-]: MOVE R0 R6   
     202 [-]: MOVE R1 R20  
     203 [-]: MOVE R0 R49  
     204 [-]: MOVE R0 R46  
     205 [-]: SETGLOBAL R50 K38 ["Initialize"]
     206 [-]: NEWCLOSURE R50 P22
     207 [-]: MOVE R1 R14  
     208 [-]: MOVE R0 R13  
     209 [-]: MOVE R0 R42  
     210 [-]: MOVE R0 R41  
     211 [-]: MOVE R1 R17  
     212 [-]: MOVE R1 R15  
     213 [-]: MOVE R0 R45  
     214 [-]: MOVE R0 R0   
     215 [-]: MOVE R1 R16  
     216 [-]: MOVE R1 R23  
     217 [-]: SETGLOBAL R50 K39 ["Update"]
     218 [-]: NEWCLOSURE R50 P23
     219 [-]: MOVE R1 R19  
     220 [-]: MOVE R0 R47  
     221 [-]: SETGLOBAL R50 K40 ["onViewportSizeChanged"]
     222 [-]: NEWCLOSURE R50 P24
     223 [-]: MOVE R1 R21  
     224 [-]: MOVE R0 R43  
     225 [-]: MOVE R0 R36  
     226 [-]: SETGLOBAL R50 K41 ["SetLink"]
     227 [-]: NEWCLOSURE R50 P25
     228 [-]: MOVE R1 R24  
     229 [-]: SETGLOBAL R50 K42 ["SetOnCloseCallback"]
     230 [-]: DUPCLOSURE R50 K43 []
     231 [-]: SETGLOBAL R50 K44 ["SupportsThemes"]
     232 [-]: NEWCLOSURE R50 P27
     233 [-]: MOVE R1 R23  
     234 [-]: MOVE R1 R35  
     235 [-]: SETGLOBAL R50 K45 ["ItemPressed"]
     236 [-]: NEWCLOSURE R50 P28
     237 [-]: MOVE R1 R35  
     238 [-]: SETGLOBAL R50 K46 ["ItemFocused"]
     239 [-]: NEWCLOSURE R50 P29
     240 [-]: MOVE R1 R35  
     241 [-]: SETGLOBAL R50 K47 ["ItemUnfocused"]
     242 [-]: NEWCLOSURE R50 P30
     243 [-]: MOVE R1 R23  
     244 [-]: MOVE R1 R16  
     245 [-]: DUPCLOSURE R51 K48 []
     246 [-]: MOVE R0 R50  
     247 [-]: SETGLOBAL R51 K49 ["onKeyDown_MENU_RIGHT_X"]
     248 [-]: DUPCLOSURE R51 K50 []
     249 [-]: MOVE R0 R50  
     250 [-]: SETGLOBAL R51 K51 ["onKeyUp_MENU_RIGHT_X"]
     251 [-]: NEWCLOSURE R51 P33
     252 [-]: MOVE R1 R16  
     253 [-]: NEWCLOSURE R52 P34
     254 [-]: MOVE R1 R16  
     255 [-]: NEWCLOSURE R53 P35
     256 [-]: MOVE R1 R23  
     257 [-]: MOVE R1 R35  
     258 [-]: SETGLOBAL R53 K52 ["onKeyDown_MENU_MOUSE_Z"]
     259 [-]: DUPCLOSURE R53 K53 []
     260 [-]: MOVE R0 R51  
     261 [-]: MOVE R0 R52  
     262 [-]: SETGLOBAL R53 K54 ["onRawInputEvent"]
     263 [-]: CLOSEUPVALS R14
     264 [-]: RETURN R0 0  


; Name:            
; Defined at line: 48
; #Upvalues:       1
; #Parameters:     0
; Is_vararg:       0
; Max Stack Size:  1

       0 [-]: GETUPVAL R0 0
       1 [-]: RETURN R0 1  


; Name:            
; Defined at line: 52
; #Upvalues:       1
; #Parameters:     0
; Is_vararg:       0
; Max Stack Size:  4

       0 [-]: GETIMPORT R0 2 [nil]
       1 [-]: GETIMPORT R1 4 [nil]
       2 [-]: LOADNIL R2   
       3 [-]: CALL R0 2 0  
       4 [-]: GETUPVAL R0 0
       5 [-]: JUMPXEQKNIL R0 L1
       6 [-]: GETIMPORT R2 5 [nil]
       7 [-]: GETUPVAL R3 0
       8 [-]: GETTABLE R1 R2 R3
       9 [-]: FASTCALL1 62 R1 L0
      10 [-]: GETIMPORT R0 7 [nil]
      11 [-]: CALL R0 1 1  
L 0:  12 [-]: JUMPIF R0 L1 
      13 [-]: GETIMPORT R1 5 [nil]
      14 [-]: GETUPVAL R2 0
      15 [-]: GETTABLE R0 R1 R2
      16 [-]: CALL R0 0 0  
      17 [-]: LOADNIL R0   
      18 [-]: SETUPVAL R0 0
L 1:  19 [-]: GETIMPORT R0 4 [nil]
      20 [-]: NAMECALL R0 R0 K8 [0x32302B4A]
      21 [-]: CALL R0 1 0  
      22 [-]: RETURN R0 0  


; Name:            
; Defined at line: 63
; #Upvalues:       0
; #Parameters:     2
; Is_vararg:       0
; Max Stack Size:  9

       0 [-]: FASTCALL1 62 R1 L0
       1 [-]: MOVE R3 R1   
       2 [-]: GETIMPORT R2 1 [nil]
       3 [-]: CALL R2 1 1  
L 0:   4 [-]: JUMPIFNOT R2 L1
       5 [-]: LOADNIL R2   
       6 [-]: RETURN R2 1  
L 1:   7 [-]: GETIMPORT R2 3 [nil]
       8 [-]: MOVE R3 R0   
       9 [-]: CALL R2 1 3  
      10 [-]: FORGPREP_INEXT R2 L3
L 2:  11 [-]: GETTABLEKS R7 R6 K4 ["mItemType"]
      12 [-]: JUMPIFNOTEQ R7 R1 L3
      13 [-]: GETTABLEKS R8 R6 K5 ["mItemId"]
      14 [-]: GETTABLEKS R7 R8 K6 ["mId"]
      15 [-]: JUMPXEQKS R7 K7 L3 [""]
      16 [-]: RETURN R6 1  
L 3:  17 [-]: FORGLOOP R2 L2 2 [inext]
      18 [-]: LOADNIL R2   
      19 [-]: RETURN R2 1  


; Name:            
; Defined at line: 77
; #Upvalues:       2
; #Parameters:     2
; Is_vararg:       0
; Max Stack Size:  16

       0 [-]: LOADB R2 0   
       1 [-]: LOADB R3 0   
       2 [-]: LOADNIL R4   
       3 [-]: GETIMPORT R5 1 [nil]
       4 [-]: GETUPVAL R6 0
       5 [-]: CALL R5 1 3  
       6 [-]: FORGPREP_INEXT R5 L8
L 0:   7 [-]: GETTABLEKS R10 R9 K2 ["mPicker"]
       8 [-]: GETTABLEKS R11 R9 K3 ["mStoreItem"]
       9 [-]: NAMECALL R11 R11 K4 [0x9A0BF00D]
      10 [-]: CALL R11 1 1 
      11 [-]: JUMPIFNOT R11 L8
      12 [-]: FASTCALL1 62 R10 L1
      13 [-]: MOVE R12 R10 
      14 [-]: GETIMPORT R11 6 [nil]
      15 [-]: CALL R11 1 1 
L 1:  16 [-]: JUMPIF R11 L8
      17 [-]: GETIMPORT R13 8 [nil]
      18 [-]: NAMECALL R11 R10 K9 [0xF2DEAF69]
      19 [-]: CALL R11 2 1 
      20 [-]: JUMPIFNOT R11 L2
      21 [-]: GETIMPORT R12 12 [nil]
      22 [-]: LOADK R13 K13 ["0x%08X"]
      23 [-]: NAMECALL R14 R10 K14 [0x5D10207D]
      24 [-]: CALL R14 1 1 
      25 [-]: NAMECALL R14 R14 K15 [0xA5D5C8F6]
      26 [-]: CALL R14 1 -1
      27 [-]: CALL R12 -1 1
      28 [-]: JUMPIFEQ R12 R0 L5
L 2:  29 [-]: JUMPIF R11 L8
      30 [-]: MOVE R14 R0  
      31 [-]: JUMPXEQKB R1 1 L3
      32 [-]: LOADB R15 0 +1
L 3:  33 [-]: LOADB R15 1  
L 4:  34 [-]: NAMECALL R12 R10 K16 [0x96DF7104]
      35 [-]: CALL R12 3 1 
      36 [-]: JUMPIFNOT R12 L8
L 5:  37 [-]: GETTABLEKS R12 R9 K17 ["mOwned"]
      38 [-]: GETTABLEKS R13 R9 K3 ["mStoreItem"]
      39 [-]: NAMECALL R13 R13 K18 [0xC055CEF8]
      40 [-]: CALL R13 1 1 
      41 [-]: JUMPXEQKNIL R4 L7
      42 [-]: JUMPIFNOT R12 L6
      43 [-]: JUMPIFNOT R2 L7
L 6:  44 [-]: JUMPIF R2 L8 
      45 [-]: JUMPIFNOT R13 L8
      46 [-]: JUMPIF R3 L8 
L 7:  47 [-]: MOVE R4 R9   
      48 [-]: MOVE R2 R12  
      49 [-]: MOVE R3 R13  
L 8:  50 [-]: FORGLOOP R5 L0 2 [inext]
      51 [-]: JUMPXEQKNIL R1 L11 NOT
      52 [-]: GETUPVAL R5 1
      53 [-]: MOVE R6 R0   
      54 [-]: LOADB R7 1   
      55 [-]: CALL R5 2 3  
      56 [-]: JUMPXEQKNIL R5 L11
      57 [-]: JUMPXEQKNIL R4 L10
      58 [-]: JUMPIFNOT R6 L9
      59 [-]: JUMPIFNOT R2 L10
L 9:  60 [-]: JUMPIF R2 L11
      61 [-]: JUMPIFNOT R7 L11
      62 [-]: JUMPIF R3 L11
L10:  63 [-]: MOVE R4 R5   
L11:  64 [-]: MOVE R5 R4   
      65 [-]: MOVE R6 R2   
      66 [-]: MOVE R7 R3   
      67 [-]: RETURN R5 3  


; Name:            
; Defined at line: 117
; #Upvalues:       1
; #Parameters:     3
; Is_vararg:       0
; Max Stack Size:  19

       0 [-]: GETIMPORT R5 1 [nil]
       1 [-]: FASTCALL1 62 R5 L0
       2 [-]: GETIMPORT R4 3 [nil]
       3 [-]: CALL R4 1 1  
L 0:   4 [-]: JUMPIF R4 L1 
       5 [-]: GETIMPORT R3 1 [nil]
       6 [-]: NAMECALL R3 R3 K4 [0x25A6E75E]
       7 [-]: CALL R3 1 1  
       8 [-]: NAMECALL R3 R3 K5 [0xD8DFA041]
       9 [-]: CALL R3 1 1  
      10 [-]: JUMPIF R3 L2 
L 1:  11 [-]: LOADNIL R3   
L 2:  12 [-]: GETIMPORT R4 1 [nil]
      13 [-]: NAMECALL R4 R4 K4 [0x25A6E75E]
      14 [-]: CALL R4 1 1  
      15 [-]: GETIMPORT R5 8 [nil]
      16 [-]: MOVE R6 R0   
      17 [-]: MOVE R7 R4   
      18 [-]: CALL R5 2 1  
      19 [-]: GETIMPORT R8 10 [nil]
      20 [-]: NAMECALL R6 R0 K11 [0xE9CBFFA8]
      21 [-]: CALL R6 2 1  
      22 [-]: GETIMPORT R7 13 [nil]
      23 [-]: MOVE R8 R6   
      24 [-]: CALL R7 1 3  
      25 [-]: FORGPREP_INEXT R7 L11
L 3:  26 [-]: GETIMPORT R12 15 [nil]
      27 [-]: LOADN R13 0  
      28 [-]: CALL R12 1 0 
      29 [-]: FASTCALL1 62 R11 L4
      30 [-]: MOVE R13 R11 
      31 [-]: GETIMPORT R12 3 [nil]
      32 [-]: CALL R12 1 1 
L 4:  33 [-]: JUMPIF R12 L11
      34 [-]: NAMECALL R12 R11 K16 [0xFE9EB1A5]
      35 [-]: CALL R12 1 1 
      36 [-]: LOADN R13 10 
      37 [-]: JUMPIFNOTEQ R12 R13 L11
      38 [-]: NAMECALL R12 R11 K17 [0xF278F8A1]
      39 [-]: CALL R12 1 1 
      40 [-]: FASTCALL1 62 R12 L5
      41 [-]: MOVE R14 R12 
      42 [-]: GETIMPORT R13 3 [nil]
      43 [-]: CALL R13 1 1 
L 5:  44 [-]: JUMPIF R13 L11
      45 [-]: NAMECALL R13 R11 K18 [0x31E559D2]
      46 [-]: CALL R13 1 1 
      47 [-]: JUMPIF R13 L8
      48 [-]: LOADN R16 1  
      49 [-]: LENGTH R14 R3
      50 [-]: LOADN R15 1  
      51 [-]: FORNPREP R14 L8
L 6:  52 [-]: GETTABLE R18 R3 R16
      53 [-]: GETTABLEKS R17 R18 K19 ["mItemType"]
      54 [-]: JUMPIFNOTEQ R17 R12 L7
      55 [-]: LOADB R13 1  
      56 [-]: JUMP L8
     
L 7:  57 [-]: FORNLOOP R14 L6
L 8:  58 [-]: JUMPIF R13 L10
      59 [-]: NAMECALL R14 R11 K20 [0xC055CEF8]
      60 [-]: CALL R14 1 1 
      61 [-]: JUMPIF R14 L9
      62 [-]: JUMPIFNOT R2 L11
L 9:  63 [-]: JUMPIF R1 L11
L10:  64 [-]: MOVE R16 R11 
      65 [-]: NAMECALL R14 R5 K21 [0x4018C310]
      66 [-]: CALL R14 2 1 
      67 [-]: JUMPXEQKNIL R14 L11
      68 [-]: LENGTH R15 R14
      69 [-]: LOADN R16 0  
      70 [-]: JUMPIFNOTLT R16 R15 L11
      71 [-]: GETUPVAL R16 0
      72 [-]: DUPTABLE R17 24
      73 [-]: SETTABLEKS R11 R17 K22 ["mStoreItem"]
      74 [-]: SETTABLEKS R13 R17 K23 ["mOwned"]
      75 [-]: FASTCALL2 52 R16 R17 L11
      76 [-]: GETIMPORT R15 27 [nil]
      77 [-]: CALL R15 2 0 
L11:  78 [-]: FORGLOOP R7 L3 2 [inext]
      79 [-]: RETURN R0 0  


; Name:            
; Defined at line: 154
; #Upvalues:       6
; #Parameters:     0
; Is_vararg:       0
; Max Stack Size:  12

       0 [-]: GETUPVAL R0 0
       1 [-]: LOADB R2 1   
       2 [-]: LOADB R3 1   
       3 [-]: NAMECALL R0 R0 K0 [0x7C09C373]
       4 [-]: CALL R0 3 0  
       5 [-]: GETIMPORT R0 2 [nil]
       6 [-]: GETUPVAL R1 1
       7 [-]: CALL R0 1 3  
       8 [-]: FORGPREP_NEXT R0 L1
L 0:   9 [-]: GETUPVAL R6 2
      10 [-]: GETTABLEKS R5 R6 K3 [0x08681F50]
      11 [-]: GETIMPORT R6 5 [nil]
      12 [-]: MOVE R7 R4   
      13 [-]: LOADNIL R8   
      14 [-]: LOADNIL R9   
      15 [-]: LOADNIL R10  
      16 [-]: LOADB R11 1  
      17 [-]: CALL R5 6 1  
      18 [-]: LOADN R6 0   
      19 [-]: SETTABLEKS R6 R5 K6 ["Count"]
      20 [-]: GETUPVAL R6 0
      21 [-]: MOVE R8 R5   
      22 [-]: LOADB R9 1   
      23 [-]: NAMECALL R6 R6 K7 [0xBAD4316F]
      24 [-]: CALL R6 3 0  
L 1:  25 [-]: FORGLOOP R0 L0 2
      26 [-]: GETUPVAL R0 0
      27 [-]: NAMECALL R0 R0 K8 [0x5FBDDC1A]
      28 [-]: CALL R0 1 1  
      29 [-]: GETUPVAL R4 0
      30 [-]: GETTABLEKS R3 R4 K9 ["mVisibleElements"]
      31 [-]: SUB R2 R3 R0 
      32 [-]: GETUPVAL R5 0
      33 [-]: GETTABLEKS R4 R5 K10 ["mColumns"]
      34 [-]: MOD R3 R0 R4 
      35 [-]: FASTCALL2 18 R2 R3 L2
      36 [-]: GETIMPORT R1 13 [nil]
      37 [-]: CALL R1 2 1  
L 2:  38 [-]: LOADN R4 1   
      39 [-]: MOVE R2 R1   
      40 [-]: LOADN R3 1   
      41 [-]: FORNPREP R2 L4
L 3:  42 [-]: GETUPVAL R5 0
      43 [-]: DUPTABLE R7 15
      44 [-]: LOADB R8 1   
      45 [-]: SETTABLEKS R8 R7 K14 ["Filler"]
      46 [-]: LOADB R8 1   
      47 [-]: NAMECALL R5 R5 K7 [0xBAD4316F]
      48 [-]: CALL R5 3 0  
      49 [-]: FORNLOOP R2 L3
L 4:  50 [-]: GETUPVAL R2 0
      51 [-]: NAMECALL R2 R2 K16 [0x71E9AC81]
      52 [-]: CALL R2 1 0  
      53 [-]: LOADN R3 0   
      54 [-]: JUMPIFLT R3 R0 L5
      55 [-]: LOADB R2 0 +1
L 5:  56 [-]: LOADB R2 1   
L 6:  57 [-]: GETIMPORT R3 5 [nil]
      58 [-]: LOADK R5 K17 ["ItemGrid"]
      59 [-]: LOADN R6 11  
      60 [-]: MOVE R7 R2   
      61 [-]: NAMECALL R3 R3 K18 [0xAADE900E]
      62 [-]: CALL R3 4 0  
      63 [-]: JUMPIFNOT R2 L8
      64 [-]: GETIMPORT R4 21 [nil]
      65 [-]: FASTCALL1 62 R4 L7
      66 [-]: GETIMPORT R3 23 [nil]
      67 [-]: CALL R3 1 1  
L 7:  68 [-]: JUMPIF R3 L10
      69 [-]: LOADB R3 1   
      70 [-]: SETUPVAL R3 3
      71 [-]: GETIMPORT R3 21 [nil]
      72 [-]: LOADK R4 K24 [0.25]
      73 [-]: LOADNIL R5   
      74 [-]: LOADNIL R6   
      75 [-]: GETUPVAL R7 4
      76 [-]: CALL R3 4 0  
      77 [-]: RETURN R0 0  
L 8:  78 [-]: GETUPVAL R4 5
      79 [-]: GETTABLEKS R3 R4 K25 ["Visible"]
      80 [-]: JUMPIFNOT R3 L10
      81 [-]: GETIMPORT R4 27 [nil]
      82 [-]: FASTCALL1 62 R4 L9
      83 [-]: GETIMPORT R3 23 [nil]
      84 [-]: CALL R3 1 1  
L 9:  85 [-]: JUMPIF R3 L10
      86 [-]: GETIMPORT R3 27 [nil]
      87 [-]: CALL R3 0 0  
L10:  88 [-]: RETURN R0 0  


; Name:            
; Defined at line: 183
; #Upvalues:       3
; #Parameters:     0
; Is_vararg:       0
; Max Stack Size:  7

       0 [-]: GETUPVAL R2 0
       1 [-]: GETTABLEKS R1 R2 K0 ["mItemType"]
       2 [-]: FASTCALL1 62 R1 L0
       3 [-]: GETIMPORT R0 2 [nil]
       4 [-]: CALL R0 1 1  
L 0:   5 [-]: JUMPIF R0 L2 
       6 [-]: DUPTABLE R0 5
       7 [-]: LOADB R1 1   
       8 [-]: SETTABLEKS R1 R0 K3 ["SkipCustomDiorama"]
       9 [-]: LOADB R1 1   
      10 [-]: SETTABLEKS R1 R0 K4 ["SkipPreviewKubrow"]
      11 [-]: GETUPVAL R3 0
      12 [-]: GETTABLEKS R2 R3 K6 ["mModularParts"]
      13 [-]: LENGTH R1 R2 
      14 [-]: LOADN R2 0   
      15 [-]: JUMPIFNOTLT R2 R1 L1
      16 [-]: DUPTABLE R1 9
      17 [-]: LOADB R2 1   
      18 [-]: SETTABLEKS R2 R1 K7 ["Gild"]
      19 [-]: GETUPVAL R3 0
      20 [-]: GETTABLEKS R2 R3 K6 ["mModularParts"]
      21 [-]: SETTABLEKS R2 R1 K8 ["Parts"]
      22 [-]: SETTABLEKS R1 R0 K10 ["ModularInfo"]
L 1:  23 [-]: GETUPVAL R1 1
      24 [-]: GETIMPORT R3 12 [nil]
      25 [-]: GETUPVAL R5 0
      26 [-]: GETTABLEKS R4 R5 K13 ["mStoreItem"]
      27 [-]: LOADNIL R5   
      28 [-]: MOVE R6 R0   
      29 [-]: NAMECALL R1 R1 K14 [0xFEC1C88A]
      30 [-]: CALL R1 5 0  
L 2:  31 [-]: GETUPVAL R0 2
      32 [-]: GETUPVAL R5 0
      33 [-]: GETTABLEKS R4 R5 K15 ["mWeaponInfos"]
      34 [-]: LENGTH R3 R4 
      35 [-]: LOADN R4 0   
      36 [-]: JUMPIFLT R4 R3 L3
      37 [-]: LOADB R2 0 +1
L 3:  38 [-]: LOADB R2 1   
L 4:  39 [-]: NAMECALL R0 R0 K16 [0x46610C50]
      40 [-]: CALL R0 2 0  
      41 [-]: RETURN R0 0  


; Name:            
; Defined at line: 195
; #Upvalues:       11
; #Parameters:     1
; Is_vararg:       0
; Max Stack Size:  26

       0 [-]: GETIMPORT R1 1 [nil]
       1 [-]: NAMECALL R1 R1 K2 [0x25A6E75E]
       2 [-]: CALL R1 1 1  
       3 [-]: FASTCALL1 62 R1 L0
       4 [-]: MOVE R3 R1   
       5 [-]: GETIMPORT R2 4 [nil]
       6 [-]: CALL R2 1 1  
L 0:   7 [-]: JUMPIFNOT R2 L1
       8 [-]: LOADB R2 0   
       9 [-]: RETURN R2 1  
L 1:  10 [-]: GETIMPORT R2 6 [nil]
      11 [-]: NAMECALL R2 R2 K7 [0xA1C390FE]
      12 [-]: CALL R2 1 1  
      13 [-]: FASTCALL1 62 R2 L2
      14 [-]: MOVE R4 R2   
      15 [-]: GETIMPORT R3 4 [nil]
      16 [-]: CALL R3 1 1  
L 2:  17 [-]: JUMPIFNOT R3 L3
      18 [-]: LOADB R3 0   
      19 [-]: RETURN R3 1  
L 3:  20 [-]: NEWTABLE R3 0 0
      21 [-]: NEWTABLE R4 0 0
      22 [-]: SETUPVAL R4 0
      23 [-]: GETUPVAL R4 1
      24 [-]: GETIMPORT R5 1 [nil]
      25 [-]: NAMECALL R5 R5 K8 [0x62C81B76]
      26 [-]: CALL R5 1 1  
      27 [-]: GETUPVAL R8 1
      28 [-]: GETTABLEKS R7 R8 K9 ["mLoadOutType"]
      29 [-]: GETUPVAL R9 1
      30 [-]: GETTABLEKS R8 R9 K10 ["mLoadOutSlot"]
      31 [-]: NAMECALL R5 R5 K11 [0xC1A84A4B]
      32 [-]: CALL R5 3 1  
      33 [-]: SETTABLEKS R5 R4 K12 ["mEquippedItem"]
      34 [-]: GETUPVAL R4 1
      35 [-]: GETUPVAL R6 2
      36 [-]: GETTABLEKS R5 R6 K13 [0xBE53A7A2]
      37 [-]: MOVE R6 R1   
      38 [-]: GETUPVAL R8 1
      39 [-]: GETTABLEKS R7 R8 K14 ["mItemType"]
      40 [-]: GETUPVAL R9 1
      41 [-]: GETTABLEKS R8 R9 K12 ["mEquippedItem"]
      42 [-]: GETUPVAL R14 1
      43 [-]: GETTABLEKS R13 R14 K12 ["mEquippedItem"]
      44 [-]: GETTABLEKS R12 R13 K15 ["mItem"]
      45 [-]: GETTABLEKS R11 R12 K14 ["mItemType"]
      46 [-]: FASTCALL1 62 R11 L4
      47 [-]: GETIMPORT R10 4 [nil]
      48 [-]: CALL R10 1 1 
L 4:  49 [-]: NOT R9 R10   
      50 [-]: CALL R5 4 1  
      51 [-]: SETTABLEKS R5 R4 K16 ["mWeaponInfos"]
      52 [-]: GETUPVAL R6 1
      53 [-]: GETTABLEKS R5 R6 K16 ["mWeaponInfos"]
      54 [-]: LENGTH R4 R5 
      55 [-]: JUMPXEQKN R4 K17 L5 NOT [0]
      56 [-]: GETUPVAL R4 1
      57 [-]: NEWTABLE R5 0 0
      58 [-]: SETTABLEKS R5 R4 K16 ["mWeaponInfos"]
      59 [-]: GETUPVAL R5 0
      60 [-]: GETUPVAL R7 1
      61 [-]: GETTABLEKS R6 R7 K18 ["mStoreItem"]
      62 [-]: FASTCALL2 52 R5 R6 L5
      63 [-]: GETIMPORT R4 21 [nil]
      64 [-]: CALL R4 2 0  
L 5:  65 [-]: NAMECALL R4 R1 K22 [0xE9131614]
      66 [-]: CALL R4 1 1  
      67 [-]: NAMECALL R5 R1 K23 [0xD8DFA041]
      68 [-]: CALL R5 1 1  
      69 [-]: GETIMPORT R6 25 [nil]
      70 [-]: GETUPVAL R8 1
      71 [-]: GETTABLEKS R7 R8 K14 ["mItemType"]
      72 [-]: CALL R6 1 1  
      73 [-]: LOADN R9 0   
      74 [-]: LOADN R10 29 
      75 [-]: SUBK R7 R10 K26 [1]
      76 [-]: LOADN R8 1   
      77 [-]: FORNPREP R7 L34
L 6:  78 [-]: MOVE R12 R9  
      79 [-]: NAMECALL R10 R6 K27 [0x0911AE7C]
      80 [-]: CALL R10 2 1 
      81 [-]: FASTCALL1 62 R10 L7
      82 [-]: MOVE R12 R10 
      83 [-]: GETIMPORT R11 4 [nil]
      84 [-]: CALL R11 1 1 
L 7:  85 [-]: JUMPIF R11 L8
      86 [-]: MOVE R12 R3  
      87 [-]: NAMECALL R13 R10 K28 [0xED4E0128]
      88 [-]: CALL R13 1 -1
      89 [-]: FASTCALL 52 L8
      90 [-]: GETIMPORT R11 21 [nil]
      91 [-]: CALL R11 -1 0
L 8:  92 [-]: GETUPVAL R15 1
      93 [-]: GETTABLEKS R14 R15 K29 ["mSkins"]
      94 [-]: GETTABLE R13 R14 R9
      95 [-]: GETTABLEKS R12 R13 K14 ["mItemType"]
      96 [-]: FASTCALL1 62 R12 L9
      97 [-]: GETIMPORT R11 4 [nil]
      98 [-]: CALL R11 1 1 
L 9:  99 [-]: JUMPIF R11 L33
     100 [-]: GETUPVAL R14 1
     101 [-]: GETTABLEKS R13 R14 K29 ["mSkins"]
     102 [-]: GETTABLE R12 R13 R9
     103 [-]: GETTABLEKS R11 R12 K18 ["mStoreItem"]
     104 [-]: GETUPVAL R12 3
     105 [-]: MOVE R13 R4  
     106 [-]: GETUPVAL R17 1
     107 [-]: GETTABLEKS R16 R17 K29 ["mSkins"]
     108 [-]: GETTABLE R15 R16 R9
     109 [-]: GETTABLEKS R14 R15 K14 ["mItemType"]
     110 [-]: CALL R12 2 1 
     111 [-]: MOVE R13 R12 
     112 [-]: JUMPIFNOT R13 L11
     113 [-]: GETTABLEKS R15 R12 K30 ["mItemId"]
     114 [-]: GETTABLEKS R14 R15 K31 ["mId"]
     115 [-]: JUMPXEQKS R14 K32 L10 NOT [""]
     116 [-]: LOADB R13 0 +1
L10: 117 [-]: LOADB R13 1  
L11: 118 [-]: FASTCALL1 62 R11 L12
     119 [-]: MOVE R15 R11 
     120 [-]: GETIMPORT R14 4 [nil]
     121 [-]: CALL R14 1 1 
L12: 122 [-]: JUMPIF R14 L32
     123 [-]: LOADB R14 1  
     124 [-]: NAMECALL R15 R11 K33 [0x4E485A6F]
     125 [-]: CALL R15 1 1 
     126 [-]: LOADN R16 0  
     127 [-]: JUMPIFLT R16 R15 L14
     128 [-]: NAMECALL R15 R11 K34 [0x2CE719D4]
     129 [-]: CALL R15 1 1 
     130 [-]: LOADN R16 0  
     131 [-]: JUMPIFLT R16 R15 L13
     132 [-]: LOADB R14 0 +1
L13: 133 [-]: LOADB R14 1  
L14: 134 [-]: JUMPIF R13 L31
     135 [-]: NAMECALL R15 R11 K35 [0xBB90E4FE]
     136 [-]: CALL R15 1 1 
     137 [-]: FASTCALL1 62 R15 L15
     138 [-]: MOVE R17 R15 
     139 [-]: GETIMPORT R16 4 [nil]
     140 [-]: CALL R16 1 1 
L15: 141 [-]: JUMPIF R16 L31
     142 [-]: NAMECALL R16 R11 K36 [0x29BA1D84]
     143 [-]: CALL R16 1 1 
     144 [-]: MOVE R19 R15 
     145 [-]: NAMECALL R17 R2 K37 [0x105074FB]
     146 [-]: CALL R17 2 1 
     147 [-]: FASTCALL1 62 R17 L16
     148 [-]: MOVE R19 R17 
     149 [-]: GETIMPORT R18 4 [nil]
     150 [-]: CALL R18 1 1 
L16: 151 [-]: JUMPIF R18 L19
     152 [-]: MOVE R18 R14 
     153 [-]: JUMPIF R18 L18
     154 [-]: LOADB R18 1  
     155 [-]: NAMECALL R19 R17 K33 [0x4E485A6F]
     156 [-]: CALL R19 1 1 
     157 [-]: LOADN R20 0  
     158 [-]: JUMPIFLT R20 R19 L18
     159 [-]: NAMECALL R19 R17 K34 [0x2CE719D4]
     160 [-]: CALL R19 1 1 
     161 [-]: LOADN R20 0  
     162 [-]: JUMPIFLT R20 R19 L17
     163 [-]: LOADB R18 0 +1
L17: 164 [-]: LOADB R18 1  
L18: 165 [-]: MOVE R14 R18 
     166 [-]: MOVE R11 R17 
L19: 167 [-]: NAMECALL R20 R11 K38 [0xF278F8A1]
     168 [-]: CALL R20 1 1 
     169 [-]: FASTCALL1 62 R20 L20
     170 [-]: GETIMPORT R19 4 [nil]
     171 [-]: CALL R19 1 1 
L20: 172 [-]: NOT R18 R19  
     173 [-]: JUMPIFNOT R18 L21
     174 [-]: NAMECALL R18 R11 K38 [0xF278F8A1]
     175 [-]: CALL R18 1 1 
     176 [-]: GETUPVAL R20 4
     177 [-]: NAMECALL R18 R18 K39 [0xF2DEAF69]
     178 [-]: CALL R18 2 1 
L21: 179 [-]: GETIMPORT R19 41 [nil]
     180 [-]: MOVE R20 R5  
     181 [-]: CALL R19 1 3 
     182 [-]: FORGPREP_INEXT R19 L23
L22: 183 [-]: GETTABLEKS R24 R23 K14 ["mItemType"]
     184 [-]: JUMPIFNOTEQ R24 R15 L23
     185 [-]: LOADB R13 1  
     186 [-]: JUMP L24
    
L23: 187 [-]: FORGLOOP R19 L22 2 [inext]
L24: 188 [-]: JUMPIF R13 L31
     189 [-]: JUMPIFNOT R18 L31
     190 [-]: FASTCALL1 62 R16 L25
     191 [-]: MOVE R20 R16 
     192 [-]: GETIMPORT R19 4 [nil]
     193 [-]: CALL R19 1 1 
L25: 194 [-]: JUMPIF R19 L31
     195 [-]: GETUPVAL R21 1
     196 [-]: GETTABLEKS R20 R21 K16 ["mWeaponInfos"]
     197 [-]: LENGTH R19 R20
     198 [-]: LOADN R20 0  
     199 [-]: JUMPIFLT R20 R19 L26
     200 [-]: LOADB R13 0 +1
L26: 201 [-]: LOADB R13 1  
L27: 202 [-]: LOADN R21 1  
     203 [-]: GETUPVAL R23 1
     204 [-]: GETTABLEKS R22 R23 K16 ["mWeaponInfos"]
     205 [-]: LENGTH R19 R22
     206 [-]: LOADN R20 1  
     207 [-]: FORNPREP R19 L31
L28: 208 [-]: GETUPVAL R25 1
     209 [-]: GETTABLEKS R24 R25 K16 ["mWeaponInfos"]
     210 [-]: GETTABLE R23 R24 R21
     211 [-]: GETTABLEKS R22 R23 K14 ["mItemType"]
     212 [-]: FASTCALL1 62 R22 L29
     213 [-]: MOVE R24 R22 
     214 [-]: GETIMPORT R23 4 [nil]
     215 [-]: CALL R23 1 1 
L29: 216 [-]: JUMPIF R23 L30
     217 [-]: MOVE R25 R16 
     218 [-]: NAMECALL R23 R22 K39 [0xF2DEAF69]
     219 [-]: CALL R23 2 1 
     220 [-]: JUMPIF R23 L30
     221 [-]: LOADB R13 0  
     222 [-]: JUMP L31
    
L30: 223 [-]: FORNLOOP R19 L28
L31: 224 [-]: JUMPIF R13 L32
     225 [-]: JUMPIFNOT R14 L32
     226 [-]: NAMECALL R15 R11 K42 [0x31E559D2]
     227 [-]: CALL R15 1 1 
     228 [-]: JUMPIF R15 L32
     229 [-]: GETUPVAL R15 0
     230 [-]: NAMECALL R16 R11 K28 [0xED4E0128]
     231 [-]: CALL R16 1 1 
     232 [-]: SETTABLE R11 R15 R16
L32: 233 [-]: GETUPVAL R16 1
     234 [-]: GETTABLEKS R15 R16 K29 ["mSkins"]
     235 [-]: GETTABLE R14 R15 R9
     236 [-]: SETTABLEKS R12 R14 K43 ["mSkinInfo"]
     237 [-]: GETUPVAL R16 1
     238 [-]: GETTABLEKS R15 R16 K29 ["mSkins"]
     239 [-]: GETTABLE R14 R15 R9
     240 [-]: SETTABLEKS R13 R14 K44 ["mOwned"]
L33: 241 [-]: FORNLOOP R7 L6
L34: 242 [-]: GETIMPORT R7 41 [nil]
     243 [-]: GETUPVAL R8 5
     244 [-]: CALL R7 1 3  
     245 [-]: FORGPREP_INEXT R7 L36
L35: 246 [-]: GETUPVAL R12 5
     247 [-]: DUPTABLE R13 46
     248 [-]: GETTABLEKS R14 R11 K18 ["mStoreItem"]
     249 [-]: SETTABLEKS R14 R13 K18 ["mStoreItem"]
     250 [-]: GETIMPORT R14 25 [nil]
     251 [-]: GETTABLEKS R15 R11 K18 ["mStoreItem"]
     252 [-]: NAMECALL R15 R15 K38 [0xF278F8A1]
     253 [-]: CALL R15 1 -1
     254 [-]: CALL R14 -1 1
     255 [-]: SETTABLEKS R14 R13 K45 ["mPicker"]
     256 [-]: GETTABLEKS R14 R11 K44 ["mOwned"]
     257 [-]: SETTABLEKS R14 R13 K44 ["mOwned"]
     258 [-]: SETTABLE R13 R12 R10
L36: 259 [-]: FORGLOOP R7 L35 2 [inext]
     260 [-]: LOADN R9 0   
     261 [-]: LOADN R7 6   
     262 [-]: LOADN R8 1   
     263 [-]: FORNPREP R7 L46
L37: 264 [-]: LOADN R10 2  
     265 [-]: JUMPIFNOTEQ R9 R10 L38
     266 [-]: GETUPVAL R11 1
     267 [-]: GETTABLEKS R10 R11 K47 ["mIsHoverboard"]
     268 [-]: JUMPIFNOT R10 L45
L38: 269 [-]: LOADN R10 5  
     270 [-]: JUMPIFEQ R9 R10 L45
     271 [-]: GETUPVAL R13 1
     272 [-]: GETTABLEKS R12 R13 K48 ["mColours"]
     273 [-]: GETTABLE R11 R12 R9
     274 [-]: GETTABLEKS R10 R11 K49 ["mRawPalette"]
     275 [-]: GETIMPORT R11 52 [nil]
     276 [-]: CALL R11 0 1 
     277 [-]: NEWTABLE R12 0 0
     278 [-]: LOADN R15 0  
     279 [-]: LOADN R16 8  
     280 [-]: SUBK R13 R16 K26 [1]
     281 [-]: LOADN R14 1  
     282 [-]: FORNPREP R13 L44
L39: 283 [-]: MOVE R18 R15 
     284 [-]: NAMECALL R16 R10 K53 [0x697019D0]
     285 [-]: CALL R16 2 1 
     286 [-]: JUMPIFNOT R16 L43
     287 [-]: MOVE R18 R15 
     288 [-]: NAMECALL R16 R10 K54 [0x5D10207D]
     289 [-]: CALL R16 2 1 
     290 [-]: GETUPVAL R17 6
     291 [-]: GETIMPORT R18 57 [nil]
     292 [-]: LOADK R19 K58 ["0x%08X"]
     293 [-]: NAMECALL R20 R16 K59 [0xA5D5C8F6]
     294 [-]: CALL R20 1 -1
     295 [-]: CALL R18 -1 -1
     296 [-]: CALL R17 -1 1
     297 [-]: FASTCALL1 62 R17 L40
     298 [-]: MOVE R19 R17 
     299 [-]: GETIMPORT R18 4 [nil]
     300 [-]: CALL R18 1 1 
L40: 301 [-]: JUMPIF R18 L43
     302 [-]: GETTABLEKS R18 R17 K44 ["mOwned"]
     303 [-]: JUMPIFNOT R18 L41
     304 [-]: MOVE R20 R15 
     305 [-]: MOVE R21 R16 
     306 [-]: NAMECALL R18 R11 K60 [0xA3927FE9]
     307 [-]: CALL R18 3 0 
     308 [-]: MOVE R20 R15 
     309 [-]: LOADB R21 1  
     310 [-]: NAMECALL R18 R11 K61 [0xFC5D7158]
     311 [-]: CALL R18 3 0 
     312 [-]: JUMP L42
    
L41: 313 [-]: GETUPVAL R18 0
     314 [-]: GETTABLEKS R19 R17 K18 ["mStoreItem"]
     315 [-]: NAMECALL R19 R19 K28 [0xED4E0128]
     316 [-]: CALL R19 1 1 
     317 [-]: GETTABLEKS R20 R17 K18 ["mStoreItem"]
     318 [-]: SETTABLE R20 R18 R19
L42: 319 [-]: SETTABLE R17 R12 R15
L43: 320 [-]: FORNLOOP R13 L39
L44: 321 [-]: GETUPVAL R15 1
     322 [-]: GETTABLEKS R14 R15 K48 ["mColours"]
     323 [-]: GETTABLE R13 R14 R9
     324 [-]: SETTABLEKS R12 R13 K62 ["mColourPickers"]
     325 [-]: GETUPVAL R15 1
     326 [-]: GETTABLEKS R14 R15 K48 ["mColours"]
     327 [-]: GETTABLE R13 R14 R9
     328 [-]: SETTABLEKS R11 R13 K63 ["mPalette"]
L45: 329 [-]: FORNLOOP R7 L37
L46: 330 [-]: GETIMPORT R7 65 [nil]
     331 [-]: LOADK R9 K66 ["Link"]
     332 [-]: LOADN R10 29 
     333 [-]: LOADK R11 K32 [""]
     334 [-]: NAMECALL R7 R7 K67 [0x5F56EEAB]
     335 [-]: CALL R7 4 0  
     336 [-]: GETUPVAL R7 7
     337 [-]: CALL R7 0 0  
     338 [-]: JUMPIF R0 L48
     339 [-]: LENGTH R7 R3 
     340 [-]: LOADN R8 0   
     341 [-]: JUMPIFNOTLT R8 R7 L47
     342 [-]: GETUPVAL R7 8
     343 [-]: LOADB R8 1   
     344 [-]: SETTABLEKS R8 R7 K68 ["IsLoadingSecond"]
     345 [-]: GETUPVAL R7 8
     346 [-]: GETIMPORT R8 71 [nil]
     347 [-]: MOVE R9 R3   
     348 [-]: CALL R8 1 1  
     349 [-]: SETTABLEKS R8 R7 K72 ["SecondaryLoader"]
     350 [-]: JUMP L48
    
L47: 351 [-]: GETUPVAL R7 9
     352 [-]: CALL R7 0 0  
L48: 353 [-]: GETUPVAL R9 1
     354 [-]: GETTABLEKS R8 R9 K16 ["mWeaponInfos"]
     355 [-]: LENGTH R7 R8 
     356 [-]: JUMPXEQKN R7 K17 L49 NOT [0]
     357 [-]: GETUPVAL R7 10
     358 [-]: LOADB R9 0   
     359 [-]: NAMECALL R7 R7 K73 [0x46610C50]
     360 [-]: CALL R7 2 0  
     361 [-]: GETUPVAL R7 10
     362 [-]: LOADK R9 K74 ["/Lotus/Language/Menu/AppearancePreview_ApplyBtn_Disabled"]
     363 [-]: NAMECALL R7 R7 K75 [0x9B71E815]
     364 [-]: CALL R7 2 0  
L49: 365 [-]: LOADB R7 1   
     366 [-]: RETURN R7 1  


; Name:            
; Defined at line: 381
; #Upvalues:       9
; #Parameters:     0
; Is_vararg:       0
; Max Stack Size:  14

       0 [-]: GETUPVAL R0 0
       1 [-]: JUMPXEQKNIL R0 L1
       2 [-]: GETIMPORT R1 1 [nil]
       3 [-]: FASTCALL1 62 R1 L0
       4 [-]: GETIMPORT R0 3 [nil]
       5 [-]: CALL R0 1 1  
L 0:   6 [-]: JUMPIFNOT R0 L2
L 1:   7 [-]: LOADB R0 0   
       8 [-]: RETURN R0 1  
L 2:   9 [-]: GETUPVAL R1 1
      10 [-]: GETTABLEKS R0 R1 K4 [0x3B05DE19]
      11 [-]: GETUPVAL R1 0
      12 [-]: LOADB R2 0   
      13 [-]: CALL R0 2 2  
      14 [-]: JUMPIF R0 L3 
      15 [-]: GETIMPORT R2 6 [nil]
      16 [-]: LOADK R4 K7 ["Trying to decode bad link "]
      17 [-]: GETUPVAL R5 0
      18 [-]: CONCAT R3 R4 R5
      19 [-]: CALL R2 1 0  
      20 [-]: LOADB R2 0   
      21 [-]: RETURN R2 1  
L 3:  22 [-]: SETUPVAL R1 2
      23 [-]: GETUPVAL R4 2
      24 [-]: GETTABLEKS R3 R4 K8 ["mStoreItem"]
      25 [-]: FASTCALL1 62 R3 L4
      26 [-]: GETIMPORT R2 3 [nil]
      27 [-]: CALL R2 1 1  
L 4:  28 [-]: JUMPIF R2 L7 
      29 [-]: GETIMPORT R3 11 [nil]
      30 [-]: FASTCALL1 62 R3 L5
      31 [-]: GETIMPORT R2 3 [nil]
      32 [-]: CALL R2 1 1  
L 5:  33 [-]: JUMPIF R2 L7 
      34 [-]: GETUPVAL R3 2
      35 [-]: GETTABLEKS R2 R3 K12 ["mSender"]
      36 [-]: JUMPIF R2 L6 
      37 [-]: GETIMPORT R2 14 [nil]
      38 [-]: LOADK R4 K15 ["/Lotus/Language/Menu/Codex_Tenno"]
      39 [-]: LOADB R5 0   
      40 [-]: NAMECALL R2 R2 K16 [0x42B04007]
      41 [-]: CALL R2 3 1  
L 6:  42 [-]: GETIMPORT R3 14 [nil]
      43 [-]: GETUPVAL R6 2
      44 [-]: GETTABLEKS R5 R6 K8 ["mStoreItem"]
      45 [-]: NAMECALL R5 R5 K17 [0xD3A9D01F]
      46 [-]: CALL R5 1 1  
      47 [-]: NAMECALL R5 R5 K18 [0x6D604BA7]
      48 [-]: CALL R5 1 1  
      49 [-]: LOADB R6 0   
      50 [-]: NAMECALL R3 R3 K16 [0x42B04007]
      51 [-]: CALL R3 3 1  
      52 [-]: GETIMPORT R4 14 [nil]
      53 [-]: LOADK R6 K19 ["/Lotus/Language/Menu/AppearancePreview_Title"]
      54 [-]: LOADB R7 0   
      55 [-]: DUPTABLE R8 22
      56 [-]: SETTABLEKS R2 R8 K20 ["SENDER"]
      57 [-]: SETTABLEKS R3 R8 K21 ["WEAPON"]
      58 [-]: NAMECALL R4 R4 K16 [0x42B04007]
      59 [-]: CALL R4 4 1  
      60 [-]: GETIMPORT R5 11 [nil]
      61 [-]: MOVE R6 R4   
      62 [-]: CALL R5 1 0  
      63 [-]: LOADB R5 1   
      64 [-]: SETUPVAL R5 3
L 7:  65 [-]: NEWTABLE R2 0 0
      66 [-]: MOVE R4 R2   
      67 [-]: GETUPVAL R6 2
      68 [-]: GETTABLEKS R5 R6 K23 ["mItemType"]
      69 [-]: NAMECALL R5 R5 K24 [0xED4E0128]
      70 [-]: CALL R5 1 -1 
      71 [-]: FASTCALL 52 L8
      72 [-]: GETIMPORT R3 27 [nil]
      73 [-]: CALL R3 -1 0 
L 8:  74 [-]: GETIMPORT R3 29 [nil]
      75 [-]: GETUPVAL R6 2
      76 [-]: GETTABLEKS R4 R6 K30 ["mModularParts"]
      77 [-]: CALL R3 1 3  
      78 [-]: FORGPREP_INEXT R3 L10
L 9:  79 [-]: MOVE R9 R2   
      80 [-]: NAMECALL R10 R7 K24 [0xED4E0128]
      81 [-]: CALL R10 1 -1
      82 [-]: FASTCALL 52 L10
      83 [-]: GETIMPORT R8 27 [nil]
      84 [-]: CALL R8 -1 0 
L10:  85 [-]: FORGLOOP R3 L9 2 [inext]
      86 [-]: GETIMPORT R3 29 [nil]
      87 [-]: GETUPVAL R6 2
      88 [-]: GETTABLEKS R4 R6 K31 ["mSkins"]
      89 [-]: CALL R3 1 3  
      90 [-]: FORGPREP_INEXT R3 L13
L11:  91 [-]: GETTABLEKS R9 R7 K32 ["skinType"]
      92 [-]: FASTCALL1 62 R9 L12
      93 [-]: GETIMPORT R8 3 [nil]
      94 [-]: CALL R8 1 1  
L12:  95 [-]: JUMPIF R8 L13
      96 [-]: MOVE R9 R2   
      97 [-]: GETTABLEKS R10 R7 K32 ["skinType"]
      98 [-]: NAMECALL R10 R10 K24 [0xED4E0128]
      99 [-]: CALL R10 1 -1
     100 [-]: FASTCALL 52 L13
     101 [-]: GETIMPORT R8 27 [nil]
     102 [-]: CALL R8 -1 0 
L13: 103 [-]: FORGLOOP R3 L11 2 [inext]
     104 [-]: GETIMPORT R3 34 [nil]
     105 [-]: NAMECALL R3 R3 K35 [0xA1C390FE]
     106 [-]: CALL R3 1 1  
     107 [-]: GETUPVAL R5 5
     108 [-]: GETTABLEKS R4 R5 K36 [0xD3FED720]
     109 [-]: MOVE R5 R3   
     110 [-]: LOADB R6 0   
     111 [-]: LOADB R7 1   
     112 [-]: CALL R4 3 1  
     113 [-]: SETUPVAL R4 4
     114 [-]: GETUPVAL R5 2
     115 [-]: GETTABLEKS R4 R5 K37 ["mIsPet"]
     116 [-]: JUMPIFNOT R4 L14
     117 [-]: GETUPVAL R4 6
     118 [-]: MOVE R5 R3   
     119 [-]: LOADB R6 0   
     120 [-]: LOADB R7 1   
     121 [-]: CALL R4 3 0  
L14: 122 [-]: GETIMPORT R4 29 [nil]
     123 [-]: GETUPVAL R5 4
     124 [-]: CALL R4 1 3  
     125 [-]: FORGPREP_INEXT R4 L17
L15: 126 [-]: GETTABLEKS R9 R8 K8 ["mStoreItem"]
     127 [-]: NAMECALL R9 R9 K38 [0xF278F8A1]
     128 [-]: CALL R9 1 1  
     129 [-]: FASTCALL1 62 R9 L16
     130 [-]: MOVE R11 R9  
     131 [-]: GETIMPORT R10 3 [nil]
     132 [-]: CALL R10 1 1 
L16: 133 [-]: JUMPIF R10 L17
     134 [-]: MOVE R11 R2  
     135 [-]: NAMECALL R12 R9 K24 [0xED4E0128]
     136 [-]: CALL R12 1 -1
     137 [-]: FASTCALL 52 L17
     138 [-]: GETIMPORT R10 27 [nil]
     139 [-]: CALL R10 -1 0
L17: 140 [-]: FORGLOOP R4 L15 2 [inext]
     141 [-]: LENGTH R4 R2 
     142 [-]: LOADN R5 0   
     143 [-]: JUMPIFNOTLT R5 R4 L18
     144 [-]: GETUPVAL R4 7
     145 [-]: LOADB R5 1   
     146 [-]: SETTABLEKS R5 R4 K39 ["IsLoading"]
     147 [-]: GETUPVAL R4 7
     148 [-]: GETIMPORT R5 42 [nil]
     149 [-]: MOVE R6 R2   
     150 [-]: CALL R5 1 1  
     151 [-]: SETTABLEKS R5 R4 K43 ["Loader"]
     152 [-]: JUMP L19
    
L18: 153 [-]: GETUPVAL R4 8
     154 [-]: CALL R4 0 -1 
     155 [-]: RETURN R4 -1 
L19: 156 [-]: LOADB R4 1   
     157 [-]: RETURN R4 1  


; Name:            
; Defined at line: 441
; #Upvalues:       3
; #Parameters:     3
; Is_vararg:       0
; Max Stack Size:  18

       0 [-]: GETUPVAL R4 0
       1 [-]: GETTABLEKS R3 R4 K0 ["mUglyMode"]
       2 [-]: SETTABLEKS R3 R0 K1 ["mAllowUglyMode"]
       3 [-]: LOADN R5 0   
       4 [-]: LOADN R6 29  
       5 [-]: SUBK R3 R6 K2 [1]
       6 [-]: LOADN R4 1   
       7 [-]: FORNPREP R3 L13
L 0:   8 [-]: GETUPVAL R10 0
       9 [-]: GETTABLEKS R9 R10 K3 ["mSkins"]
      10 [-]: GETTABLE R8 R9 R5
      11 [-]: GETTABLEKS R7 R8 K4 ["mItemType"]
      12 [-]: FASTCALL1 62 R7 L1
      13 [-]: GETIMPORT R6 6 [nil]
      14 [-]: CALL R6 1 1  
L 1:  15 [-]: JUMPIF R6 L12
      16 [-]: LOADB R6 1   
      17 [-]: JUMPIF R2 L8 
      18 [-]: GETUPVAL R10 0
      19 [-]: GETTABLEKS R9 R10 K3 ["mSkins"]
      20 [-]: GETTABLE R8 R9 R5
      21 [-]: GETTABLEKS R7 R8 K7 ["mStoreItem"]
      22 [-]: NAMECALL R8 R7 K8 [0x29BA1D84]
      23 [-]: CALL R8 1 1  
      24 [-]: FASTCALL1 62 R8 L2
      25 [-]: MOVE R10 R8  
      26 [-]: GETIMPORT R9 6 [nil]
      27 [-]: CALL R9 1 1  
L 2:  28 [-]: JUMPIF R9 L3 
      29 [-]: GETUPVAL R10 1
      30 [-]: GETTABLEKS R9 R10 K4 ["mItemType"]
      31 [-]: MOVE R11 R8  
      32 [-]: NAMECALL R9 R9 K9 [0xF2DEAF69]
      33 [-]: CALL R9 2 1  
L 3:  34 [-]: GETUPVAL R13 0
      35 [-]: GETTABLEKS R12 R13 K3 ["mSkins"]
      36 [-]: GETTABLE R11 R12 R5
      37 [-]: GETTABLEKS R10 R11 K10 ["mOwned"]
      38 [-]: JUMPIF R10 L4
      39 [-]: NAMECALL R11 R7 K11 [0x31E559D2]
      40 [-]: CALL R11 1 1 
      41 [-]: AND R10 R11 R9
L 4:  42 [-]: JUMPIF R9 L7 
      43 [-]: NAMECALL R11 R7 K12 [0xB6525E9D]
      44 [-]: CALL R11 1 1 
      45 [-]: FASTCALL1 62 R11 L5
      46 [-]: MOVE R14 R11 
      47 [-]: GETIMPORT R13 6 [nil]
      48 [-]: CALL R13 1 1 
L 5:  49 [-]: NOT R12 R13  
      50 [-]: JUMPIFNOT R12 L6
      51 [-]: GETUPVAL R13 1
      52 [-]: GETTABLEKS R12 R13 K4 ["mItemType"]
      53 [-]: MOVE R14 R11 
      54 [-]: NAMECALL R12 R12 K9 [0xF2DEAF69]
      55 [-]: CALL R12 2 1 
L 6:  56 [-]: MOVE R9 R12  
L 7:  57 [-]: AND R6 R9 R10
L 8:  58 [-]: JUMPIFNOT R6 L12
      59 [-]: GETIMPORT R7 14 [nil]
      60 [-]: GETUPVAL R11 0
      61 [-]: GETTABLEKS R10 R11 K3 ["mSkins"]
      62 [-]: GETTABLE R9 R10 R5
      63 [-]: GETTABLEKS R8 R9 K4 ["mItemType"]
      64 [-]: CALL R7 1 1  
      65 [-]: MOVE R10 R7  
      66 [-]: MOVE R11 R5  
      67 [-]: NAMECALL R8 R0 K15 [0xEDD0B8C3]
      68 [-]: CALL R8 3 0  
      69 [-]: LOADN R10 0  
      70 [-]: LOADN R11 29 
      71 [-]: SUBK R8 R11 K2 [1]
      72 [-]: LOADN R9 1   
      73 [-]: FORNPREP R8 L12
L 9:  74 [-]: GETIMPORT R11 14 [nil]
      75 [-]: MOVE R14 R10 
      76 [-]: NAMECALL R12 R7 K16 [0xB8EF5B34]
      77 [-]: CALL R12 2 -1
      78 [-]: CALL R11 -1 1
      79 [-]: FASTCALL1 62 R11 L10
      80 [-]: MOVE R13 R11 
      81 [-]: GETIMPORT R12 6 [nil]
      82 [-]: CALL R12 1 1 
L10:  83 [-]: JUMPIF R12 L11
      84 [-]: MOVE R14 R11 
      85 [-]: MOVE R15 R10 
      86 [-]: NAMECALL R12 R0 K15 [0xEDD0B8C3]
      87 [-]: CALL R12 3 0 
L11:  88 [-]: FORNLOOP R8 L9
L12:  89 [-]: FORNLOOP R3 L0
L13:  90 [-]: LOADN R5 0   
      91 [-]: LOADN R3 6   
      92 [-]: LOADN R4 1   
      93 [-]: FORNPREP R3 L21
L14:  94 [-]: LOADN R6 2   
      95 [-]: JUMPIFNOTEQ R5 R6 L15
      96 [-]: GETUPVAL R7 0
      97 [-]: GETTABLEKS R6 R7 K17 ["mIsHoverboard"]
      98 [-]: JUMPIFNOT R6 L20
L15:  99 [-]: LOADN R6 5   
     100 [-]: JUMPIFEQ R5 R6 L20
     101 [-]: GETUPVAL R8 0
     102 [-]: GETTABLEKS R7 R8 K18 ["mColours"]
     103 [-]: GETTABLE R6 R7 R5
     104 [-]: GETUPVAL R8 2
     105 [-]: GETTABLEKS R7 R8 K19 [0x06D055F9]
     106 [-]: MOVE R8 R2   
     107 [-]: GETTABLEKS R9 R6 K20 ["mRawPalette"]
     108 [-]: GETTABLEKS R10 R6 K21 ["mPalette"]
     109 [-]: CALL R7 3 1  
     110 [-]: MOVE R10 R5  
     111 [-]: NAMECALL R8 R0 K22 [0x8E62760A]
     112 [-]: CALL R8 2 1  
     113 [-]: LOADN R11 0  
     114 [-]: LOADN R12 8  
     115 [-]: SUBK R9 R12 K2 [1]
     116 [-]: LOADN R10 1  
     117 [-]: FORNPREP R9 L19
L16: 118 [-]: MOVE R14 R11 
     119 [-]: NAMECALL R12 R7 K23 [0x697019D0]
     120 [-]: CALL R12 2 1 
     121 [-]: JUMPIFNOT R12 L17
     122 [-]: MOVE R14 R11 
     123 [-]: MOVE R17 R11 
     124 [-]: NAMECALL R15 R7 K24 [0x5D10207D]
     125 [-]: CALL R15 2 -1
     126 [-]: NAMECALL R12 R8 K25 [0xA3927FE9]
     127 [-]: CALL R12 -1 0
     128 [-]: MOVE R14 R11 
     129 [-]: LOADB R15 1  
     130 [-]: NAMECALL R12 R8 K26 [0xFC5D7158]
     131 [-]: CALL R12 3 0 
     132 [-]: JUMP L18
    
L17: 133 [-]: JUMPIFNOT R1 L18
     134 [-]: MOVE R14 R11 
     135 [-]: LOADB R15 0  
     136 [-]: NAMECALL R12 R8 K26 [0xFC5D7158]
     137 [-]: CALL R12 3 0 
L18: 138 [-]: FORNLOOP R9 L16
L19: 139 [-]: MOVE R11 R5  
     140 [-]: MOVE R12 R8  
     141 [-]: NAMECALL R9 R0 K27 [0x199EDF6E]
     142 [-]: CALL R9 3 0  
L20: 143 [-]: FORNLOOP R3 L14
L21: 144 [-]: RETURN R0 0  


; Name:            
; Defined at line: 498
; #Upvalues:       3
; #Parameters:     2
; Is_vararg:       0
; Max Stack Size:  7

       0 [-]: FASTCALL1 62 R0 L0
       1 [-]: MOVE R3 R0   
       2 [-]: GETIMPORT R2 1 [nil]
       3 [-]: CALL R2 1 1  
L 0:   4 [-]: JUMPIFNOT R2 L1
       5 [-]: RETURN R0 0  
L 1:   6 [-]: GETIMPORT R4 3 [nil]
       7 [-]: NAMECALL R2 R0 K4 [0xF2DEAF69]
       8 [-]: CALL R2 2 1  
       9 [-]: JUMPIFNOT R2 L2
      10 [-]: NAMECALL R2 R0 K5 [0x7C595670]
      11 [-]: CALL R2 1 0  
L 2:  12 [-]: GETIMPORT R2 8 [nil]
      13 [-]: CALL R2 0 1  
      14 [-]: GETUPVAL R3 0
      15 [-]: MOVE R4 R2   
      16 [-]: LOADB R5 0   
      17 [-]: LOADB R6 1   
      18 [-]: CALL R3 3 0  
      19 [-]: MOVE R5 R2   
      20 [-]: NAMECALL R3 R0 K9 [0xAA041663]
      21 [-]: CALL R3 2 0  
      22 [-]: GETUPVAL R5 1
      23 [-]: NAMECALL R3 R0 K4 [0xF2DEAF69]
      24 [-]: CALL R3 2 1  
      25 [-]: JUMPIF R3 L3 
      26 [-]: GETUPVAL R5 2
      27 [-]: NAMECALL R3 R0 K4 [0xF2DEAF69]
      28 [-]: CALL R3 2 1  
      29 [-]: JUMPIFNOT R3 L5
L 3:  30 [-]: FASTCALL1 62 R1 L4
      31 [-]: MOVE R4 R1   
      32 [-]: GETIMPORT R3 1 [nil]
      33 [-]: CALL R3 1 1  
L 4:  34 [-]: JUMPIF R3 L5 
      35 [-]: MOVE R5 R1   
      36 [-]: NAMECALL R3 R2 K10 [0x61B59A83]
      37 [-]: CALL R3 2 0  
L 5:  38 [-]: RETURN R0 0  


; Name:            
; Defined at line: 517
; #Upvalues:       2
; #Parameters:     0
; Is_vararg:       0
; Max Stack Size:  8

       0 [-]: NEWTABLE R0 0 0
       1 [-]: DUPTABLE R3 3
       2 [-]: GETIMPORT R4 5 [nil]
       3 [-]: LOADK R6 K6 ["<WARNING>"]
       4 [-]: LOADB R7 1   
       5 [-]: NAMECALL R4 R4 K7 [0x42B04007]
       6 [-]: CALL R4 3 1  
       7 [-]: SETTABLEKS R4 R3 K0 ["Label"]
       8 [-]: GETUPVAL R5 0
       9 [-]: GETTABLEKS R4 R5 K8 [0xA7D904B8]
      10 [-]: GETIMPORT R5 5 [nil]
      11 [-]: LOADK R6 K9 ["/Lotus/Language/WarframeHints/AppearancePreview_"]
      12 [-]: CALL R4 2 1  
      13 [-]: SETTABLEKS R4 R3 K1 ["Tips"]
      14 [-]: LOADN R4 -10 
      15 [-]: SETTABLEKS R4 R3 K2 ["Padding"]
      16 [-]: FASTCALL2 52 R0 R3 L0
      17 [-]: MOVE R2 R0   
      18 [-]: GETIMPORT R1 12 [nil]
      19 [-]: CALL R1 2 0  
L 0:  20 [-]: DUPTABLE R3 15
      21 [-]: LOADK R4 K16 ["/Lotus/Language/Menu/Global_Back"]
      22 [-]: SETTABLEKS R4 R3 K0 ["Label"]
      23 [-]: GETUPVAL R4 1
      24 [-]: SETTABLEKS R4 R3 K13 ["CallBack"]
      25 [-]: LOADK R4 K17 ["MENU_CANCEL"]
      26 [-]: SETTABLEKS R4 R3 K14 ["CallOut"]
      27 [-]: FASTCALL2 52 R0 R3 L1
      28 [-]: MOVE R2 R0   
      29 [-]: GETIMPORT R1 12 [nil]
      30 [-]: CALL R1 2 0  
L 1:  31 [-]: GETIMPORT R2 20 [nil]
      32 [-]: FASTCALL1 62 R2 L2
      33 [-]: GETIMPORT R1 22 [nil]
      34 [-]: CALL R1 1 1  
L 2:  35 [-]: JUMPIF R1 L3 
      36 [-]: GETIMPORT R1 20 [nil]
      37 [-]: GETIMPORT R2 5 [nil]
      38 [-]: MOVE R3 R0   
      39 [-]: GETIMPORT R4 24 [nil]
      40 [-]: LOADN R5 1   
      41 [-]: CALL R4 1 -1 
      42 [-]: CALL R1 -1 0 
L 3:  43 [-]: RETURN R0 0  


; Name:            
; Defined at line: 529
; #Upvalues:       10
; #Parameters:     0
; Is_vararg:       0
; Max Stack Size:  6

       0 [-]: GETUPVAL R1 0
       1 [-]: FASTCALL1 62 R1 L0
       2 [-]: GETIMPORT R0 1 [nil]
       3 [-]: CALL R0 1 1  
L 0:   4 [-]: JUMPIF R0 L1 
       5 [-]: GETUPVAL R0 0
       6 [-]: NAMECALL R0 R0 K2 [0x32302B4A]
       7 [-]: CALL R0 1 0  
L 1:   8 [-]: GETIMPORT R0 4 [nil]
       9 [-]: LOADNIL R1   
      10 [-]: SETTABLEKS R1 R0 K5 ["InfoPopup_Data"]
      11 [-]: GETIMPORT R0 4 [nil]
      12 [-]: LOADNIL R1   
      13 [-]: SETTABLEKS R1 R0 K6 ["InfoPopup_Grid"]
      14 [-]: GETIMPORT R0 4 [nil]
      15 [-]: LOADB R1 0   
      16 [-]: SETTABLEKS R1 R0 K7 ["AppearancePreviewOpen"]
      17 [-]: GETUPVAL R0 1
      18 [-]: JUMPIFNOT R0 L3
      19 [-]: GETIMPORT R1 9 [nil]
      20 [-]: FASTCALL1 62 R1 L2
      21 [-]: GETIMPORT R0 1 [nil]
      22 [-]: CALL R0 1 1  
L 2:  23 [-]: JUMPIF R0 L3 
      24 [-]: GETIMPORT R0 9 [nil]
      25 [-]: CALL R0 0 0  
L 3:  26 [-]: GETUPVAL R1 2
      27 [-]: GETTABLEKS R0 R1 K10 ["Visible"]
      28 [-]: JUMPIFNOT R0 L5
      29 [-]: GETIMPORT R1 12 [nil]
      30 [-]: FASTCALL1 62 R1 L4
      31 [-]: GETIMPORT R0 1 [nil]
      32 [-]: CALL R0 1 1  
L 4:  33 [-]: JUMPIF R0 L5 
      34 [-]: GETIMPORT R0 12 [nil]
      35 [-]: LOADN R1 0   
      36 [-]: GETUPVAL R3 2
      37 [-]: GETTABLEKS R2 R3 K13 ["HighlightOffset"]
      38 [-]: GETUPVAL R4 2
      39 [-]: GETTABLEKS R3 R4 K14 ["HighlightOn"]
      40 [-]: GETUPVAL R5 2
      41 [-]: GETTABLEKS R4 R5 K15 ["VisRangeInfo"]
      42 [-]: CALL R0 4 0  
      43 [-]: JUMP L7
     
L 5:  44 [-]: GETUPVAL R0 3
      45 [-]: JUMPIFNOT R0 L7
      46 [-]: GETIMPORT R1 17 [nil]
      47 [-]: FASTCALL1 62 R1 L6
      48 [-]: GETIMPORT R0 1 [nil]
      49 [-]: CALL R0 1 1  
L 6:  50 [-]: JUMPIF R0 L7 
      51 [-]: GETIMPORT R0 17 [nil]
      52 [-]: CALL R0 0 0  
L 7:  53 [-]: GETUPVAL R0 4
      54 [-]: JUMPIFNOT R0 L9
      55 [-]: GETIMPORT R1 19 [nil]
      56 [-]: FASTCALL1 62 R1 L8
      57 [-]: GETIMPORT R0 1 [nil]
      58 [-]: CALL R0 1 1  
L 8:  59 [-]: JUMPIF R0 L9 
      60 [-]: GETIMPORT R0 19 [nil]
      61 [-]: NAMECALL R0 R0 K20 [0xB21930E8]
      62 [-]: CALL R0 1 0  
L 9:  63 [-]: GETUPVAL R1 5
      64 [-]: GETTABLEKS R0 R1 K21 [0x37D68E16]
      65 [-]: LOADB R1 1   
      66 [-]: GETUPVAL R2 6
      67 [-]: CALL R0 2 0  
      68 [-]: GETUPVAL R1 7
      69 [-]: GETTABLEKS R0 R1 K22 [0x9E0F8295]
      70 [-]: LOADB R1 0   
      71 [-]: CALL R0 1 0  
      72 [-]: GETUPVAL R1 7
      73 [-]: GETTABLEKS R0 R1 K23 [0x9E3D3434]
      74 [-]: LOADB R1 0   
      75 [-]: CALL R0 1 0  
      76 [-]: GETUPVAL R1 7
      77 [-]: GETTABLEKS R0 R1 K24 [0x154D0AD2]
      78 [-]: LOADB R1 0   
      79 [-]: CALL R0 1 0  
      80 [-]: GETIMPORT R0 19 [nil]
      81 [-]: LOADK R2 K25 ["HideScreenForPlatPurchase"]
      82 [-]: LOADK R3 K26 ["false"]
      83 [-]: NAMECALL R0 R0 K27 [0x7E17AE26]
      84 [-]: CALL R0 3 0  
      85 [-]: GETUPVAL R0 8
      86 [-]: JUMPIFNOT R0 L10
      87 [-]: GETIMPORT R0 29 [nil]
      88 [-]: CALL R0 0 0  
L10:  89 [-]: GETIMPORT R0 19 [nil]
      90 [-]: GETIMPORT R3 31 [nil]
      91 [-]: GETTABLEKS R2 R3 K32 ["UIMovie_DetailedPurchaseDialog"]
      92 [-]: NAMECALL R0 R0 K33 [0xBCFB64AB]
      93 [-]: CALL R0 2 1  
      94 [-]: FASTCALL1 62 R0 L11
      95 [-]: MOVE R2 R0   
      96 [-]: GETIMPORT R1 1 [nil]
      97 [-]: CALL R1 1 1  
L11:  98 [-]: JUMPIF R1 L12
      99 [-]: LOADK R3 K34 ["HideScreen"]
     100 [-]: LOADK R4 K26 ["false"]
     101 [-]: NAMECALL R1 R0 K35 [0xE4162EED]
     102 [-]: CALL R1 3 0  
L12: 103 [-]: GETUPVAL R1 9
     104 [-]: JUMPXEQKNIL R1 L14
     105 [-]: GETIMPORT R3 4 [nil]
     106 [-]: GETUPVAL R4 9
     107 [-]: GETTABLE R2 R3 R4
     108 [-]: FASTCALL1 62 R2 L13
     109 [-]: GETIMPORT R1 1 [nil]
     110 [-]: CALL R1 1 1  
L13: 111 [-]: JUMPIF R1 L14
     112 [-]: GETIMPORT R2 4 [nil]
     113 [-]: GETUPVAL R3 9
     114 [-]: GETTABLE R1 R2 R3
     115 [-]: CALL R1 0 0  
L14: 116 [-]: LOADNIL R1   
     117 [-]: SETUPVAL R1 9
     118 [-]: RETURN R0 0  


; Name:            
; Defined at line: 574
; #Upvalues:       7
; #Parameters:     0
; Is_vararg:       0
; Max Stack Size:  4

       0 [-]: GETUPVAL R0 0
       1 [-]: JUMPXEQKNIL R0 L0 NOT
       2 [-]: RETURN R0 0  
L 0:   3 [-]: GETIMPORT R0 1 [nil]
       4 [-]: GETIMPORT R3 3 [nil]
       5 [-]: GETTABLEKS R2 R3 K4 ["UIMovie_GenericMenu"]
       6 [-]: NAMECALL R0 R0 K5 [0x1FD6ABD0]
       7 [-]: CALL R0 2 1  
       8 [-]: SETUPVAL R0 1
       9 [-]: GETUPVAL R1 1
      10 [-]: FASTCALL1 62 R1 L1
      11 [-]: GETIMPORT R0 7 [nil]
      12 [-]: CALL R0 1 1  
L 1:  13 [-]: JUMPIF R0 L2 
      14 [-]: LOADB R0 1   
      15 [-]: SETUPVAL R0 2
      16 [-]: GETUPVAL R0 1
      17 [-]: LOADK R2 K8 ["SetTitle"]
      18 [-]: LOADK R3 K9 ["/Lotus/Language/Menu/Appearance_Prefix"]
      19 [-]: NAMECALL R0 R0 K10 [0xE4162EED]
      20 [-]: CALL R0 3 0  
      21 [-]: GETIMPORT R0 12 [nil]
      22 [-]: NEWCLOSURE R1 P0
      23 [-]: MOVE R2 R2   
      24 [-]: MOVE R2 R3   
      25 [-]: MOVE R2 R4   
      26 [-]: SETTABLEKS R1 R0 K13 ["ConfigSelectionDone"]
      27 [-]: GETUPVAL R0 1
      28 [-]: LOADK R2 K14 ["SetCallBack"]
      29 [-]: LOADK R3 K13 ["ConfigSelectionDone"]
      30 [-]: NAMECALL R0 R0 K10 [0xE4162EED]
      31 [-]: CALL R0 3 0  
      32 [-]: GETIMPORT R0 12 [nil]
      33 [-]: NEWCLOSURE R1 P1
      34 [-]: MOVE R2 R5   
      35 [-]: MOVE R2 R6   
      36 [-]: SETTABLEKS R1 R0 K15 ["GetConfigList"]
      37 [-]: GETUPVAL R0 1
      38 [-]: LOADK R2 K16 ["SetElementsFunction"]
      39 [-]: LOADK R3 K15 ["GetConfigList"]
      40 [-]: NAMECALL R0 R0 K10 [0xE4162EED]
      41 [-]: CALL R0 3 0  
L 2:  42 [-]: RETURN R0 0  


; Name:            
; Defined at line: 608
; #Upvalues:       4
; #Parameters:     1
; Is_vararg:       0
; Max Stack Size:  9

       0 [-]: GETIMPORT R1 1 [nil]
       1 [-]: LOADK R3 K2 ["/Lotus/Language/Menu/AppearancePreview_ConfirmWord"]
       2 [-]: LOADB R4 0   
       3 [-]: NAMECALL R1 R1 K3 [0x42B04007]
       4 [-]: CALL R1 3 1  
       5 [-]: JUMPXEQKNIL R0 L0
       6 [-]: GETIMPORT R2 6 [nil]
       7 [-]: MOVE R3 R0   
       8 [-]: CALL R2 1 1  
       9 [-]: GETIMPORT R3 6 [nil]
      10 [-]: MOVE R4 R1   
      11 [-]: CALL R3 1 1  
      12 [-]: JUMPIFEQ R2 R3 L1
L 0:  13 [-]: GETUPVAL R3 0
      14 [-]: GETTABLEKS R2 R3 K7 [0xA53F5E12]
      15 [-]: LOADK R3 K8 ["/Lotus/Language/Dojo/VaultContributionDecoIncorrectConfirmWord"]
      16 [-]: CALL R2 1 0  
      17 [-]: RETURN R0 0  
L 1:  18 [-]: GETIMPORT R2 10 [nil]
      19 [-]: NAMECALL R2 R2 K11 [0x25A6E75E]
      20 [-]: CALL R2 1 1  
      21 [-]: FASTCALL1 62 R2 L2
      22 [-]: MOVE R4 R2   
      23 [-]: GETIMPORT R3 13 [nil]
      24 [-]: CALL R3 1 1  
L 2:  25 [-]: JUMPIFNOT R3 L3
      26 [-]: RETURN R0 0  
L 3:  27 [-]: GETUPVAL R3 1
      28 [-]: JUMPXEQKNIL R3 L4
      29 [-]: GETUPVAL R5 1
      30 [-]: GETTABLEKS R4 R5 K14 ["mItemId"]
      31 [-]: GETTABLEKS R3 R4 K15 ["mId"]
      32 [-]: JUMPXEQKS R3 K16 L5 NOT [""]
L 4:  33 [-]: RETURN R0 0  
L 5:  34 [-]: GETUPVAL R3 1
      35 [-]: GETUPVAL R5 2
      36 [-]: NAMECALL R3 R3 K17 [0x68D708A7]
      37 [-]: CALL R3 2 1  
      38 [-]: GETUPVAL R4 3
      39 [-]: MOVE R5 R3   
      40 [-]: LOADB R6 1   
      41 [-]: CALL R4 2 0  
      42 [-]: GETUPVAL R8 1
      43 [-]: GETTABLEKS R7 R8 K14 ["mItemId"]
      44 [-]: GETTABLEKS R6 R7 K15 ["mId"]
      45 [-]: GETUPVAL R7 2
      46 [-]: MOVE R8 R3   
      47 [-]: NAMECALL R4 R2 K18 [0x9B051033]
      48 [-]: CALL R4 4 0  
      49 [-]: GETIMPORT R4 10 [nil]
      50 [-]: LOADK R6 K19 ["OnSaveLoadOutComplete"]
      51 [-]: NAMECALL R4 R4 K20 [0xB6E2AB0D]
      52 [-]: CALL R4 2 0  
      53 [-]: GETIMPORT R5 22 [nil]
      54 [-]: FASTCALL1 62 R5 L6
      55 [-]: GETIMPORT R4 13 [nil]
      56 [-]: CALL R4 1 1  
L 6:  57 [-]: JUMPIF R4 L7 
      58 [-]: GETIMPORT R4 22 [nil]
      59 [-]: GETIMPORT R6 24 [nil]
      60 [-]: LOADK R7 K25 ["LOOK_LINK"]
      61 [-]: CALL R6 1 1  
      62 [-]: LOADK R7 K26 ["APPLIED"]
      63 [-]: NAMECALL R4 R4 K27 [0x8B8FB8B7]
      64 [-]: CALL R4 3 0  
L 7:  65 [-]: RETURN R0 0  


; Name:            
; Defined at line: 636
; #Upvalues:       4
; #Parameters:     0
; Is_vararg:       0
; Max Stack Size:  15

       0 [-]: LOADK R0 K0 [""]
       1 [-]: LOADK R1 K0 [""]
       2 [-]: GETUPVAL R3 0
       3 [-]: FASTCALL1 62 R3 L0
       4 [-]: GETIMPORT R2 2 [nil]
       5 [-]: CALL R2 1 1  
L 0:   6 [-]: JUMPIF R2 L3 
       7 [-]: GETIMPORT R2 4 [nil]
       8 [-]: NAMECALL R2 R2 K5 [0xA1C390FE]
       9 [-]: CALL R2 1 1  
      10 [-]: FASTCALL1 62 R2 L1
      11 [-]: MOVE R4 R2   
      12 [-]: GETIMPORT R3 2 [nil]
      13 [-]: CALL R3 1 1  
L 1:  14 [-]: JUMPIF R3 L3 
      15 [-]: GETUPVAL R6 0
      16 [-]: GETTABLEKS R5 R6 K6 ["mItemType"]
      17 [-]: NAMECALL R3 R2 K7 [0x105074FB]
      18 [-]: CALL R3 2 1  
      19 [-]: FASTCALL1 62 R3 L2
      20 [-]: MOVE R5 R3   
      21 [-]: GETIMPORT R4 2 [nil]
      22 [-]: CALL R4 1 1  
L 2:  23 [-]: JUMPIF R4 L3 
      24 [-]: GETIMPORT R4 9 [nil]
      25 [-]: NAMECALL R6 R3 K10 [0xD3A9D01F]
      26 [-]: CALL R6 1 1  
      27 [-]: NAMECALL R6 R6 K11 [0x6D604BA7]
      28 [-]: CALL R6 1 1  
      29 [-]: LOADB R7 0   
      30 [-]: NAMECALL R4 R4 K12 [0x42B04007]
      31 [-]: CALL R4 3 1  
      32 [-]: MOVE R0 R4   
L 3:  33 [-]: GETUPVAL R3 1
      34 [-]: FASTCALL1 62 R3 L4
      35 [-]: GETIMPORT R2 2 [nil]
      36 [-]: CALL R2 1 1  
L 4:  37 [-]: JUMPIF R2 L5 
      38 [-]: GETUPVAL R3 2
      39 [-]: GETTABLEKS R2 R3 K13 ["CONFIG_TYPES"]
      40 [-]: GETUPVAL R4 1
      41 [-]: ADDK R3 R4 K14 [1]
      42 [-]: GETTABLE R1 R2 R3
L 5:  43 [-]: GETIMPORT R2 9 [nil]
      44 [-]: LOADK R4 K15 ["/Lotus/Language/Menu/AppearancePreview_ConfirmWord"]
      45 [-]: LOADB R5 0   
      46 [-]: NAMECALL R2 R2 K12 [0x42B04007]
      47 [-]: CALL R2 3 1  
      48 [-]: GETIMPORT R3 9 [nil]
      49 [-]: LOADK R5 K16 ["/Lotus/Language/Menu/AppearancePreview_ConfirmTitle"]
      50 [-]: LOADB R6 0   
      51 [-]: NAMECALL R3 R3 K12 [0x42B04007]
      52 [-]: CALL R3 3 1  
      53 [-]: GETIMPORT R4 9 [nil]
      54 [-]: LOADK R6 K17 ["/Lotus/Language/Menu/AppearancePreview_ConfirmDesc"]
      55 [-]: LOADB R7 0   
      56 [-]: DUPTABLE R8 21
      57 [-]: SETTABLEKS R0 R8 K18 ["WEAPON"]
      58 [-]: SETTABLEKS R1 R8 K19 ["CONFIG"]
      59 [-]: SETTABLEKS R2 R8 K20 ["OVERRIDE"]
      60 [-]: NAMECALL R4 R4 K12 [0x42B04007]
      61 [-]: CALL R4 4 1  
      62 [-]: GETIMPORT R5 9 [nil]
      63 [-]: LOADK R7 K22 ["/Lotus/Language/Menu/AppearancePreview_ConfirmShortDesc1"]
      64 [-]: LOADB R8 0   
      65 [-]: DUPTABLE R9 23
      66 [-]: SETTABLEKS R0 R9 K18 ["WEAPON"]
      67 [-]: SETTABLEKS R1 R9 K19 ["CONFIG"]
      68 [-]: NAMECALL R5 R5 K12 [0x42B04007]
      69 [-]: CALL R5 4 1  
      70 [-]: GETIMPORT R6 9 [nil]
      71 [-]: LOADK R8 K24 ["/Lotus/Language/Menu/AppearancePreview_ConfirmShortDesc2"]
      72 [-]: LOADB R9 0   
      73 [-]: DUPTABLE R10 25
      74 [-]: SETTABLEKS R2 R10 K20 ["OVERRIDE"]
      75 [-]: NAMECALL R6 R6 K12 [0x42B04007]
      76 [-]: CALL R6 4 1  
      77 [-]: GETUPVAL R8 3
      78 [-]: GETTABLEKS R7 R8 K26 [0x78A7195B]
      79 [-]: GETIMPORT R8 9 [nil]
      80 [-]: GETIMPORT R9 29 [nil]
      81 [-]: MOVE R10 R2  
      82 [-]: CALL R9 1 1  
      83 [-]: MOVE R10 R3  
      84 [-]: MOVE R11 R5  
      85 [-]: MOVE R12 R6  
      86 [-]: LOADK R13 K30 ["EquipAppearance"]
      87 [-]: MOVE R14 R4  
      88 [-]: CALL R7 7 0  
      89 [-]: RETURN R0 0  


; Name:            
; Defined at line: 661
; #Upvalues:       6
; #Parameters:     2
; Is_vararg:       0
; Max Stack Size:  10

       0 [-]: GETIMPORT R3 1 [nil]
       1 [-]: FASTCALL1 62 R3 L0
       2 [-]: GETIMPORT R2 3 [nil]
       3 [-]: CALL R2 1 1  
L 0:   4 [-]: JUMPIF R2 L1 
       5 [-]: GETIMPORT R2 1 [nil]
       6 [-]: GETIMPORT R4 5 [nil]
       7 [-]: NAMECALL R2 R2 K6 [0xF2DEAF69]
       8 [-]: CALL R2 2 1  
       9 [-]: JUMPIFNOT R2 L1
      10 [-]: GETIMPORT R2 1 [nil]
      11 [-]: NAMECALL R2 R2 K7 [0x3C903E33]
      12 [-]: CALL R2 1 1  
      13 [-]: JUMPIF R2 L2 
L 1:  14 [-]: GETUPVAL R3 0
      15 [-]: GETTABLEKS R2 R3 K8 [0x8FBD62E4]
      16 [-]: LOADK R3 K9 ["OnUpdateSessionSettings"]
      17 [-]: CALL R2 1 0  
L 2:  18 [-]: GETIMPORT R2 11 [nil]
      19 [-]: NAMECALL R2 R2 K12 [0xFB64E76C]
      20 [-]: CALL R2 1 1  
      21 [-]: FASTCALL1 62 R2 L3
      22 [-]: MOVE R4 R2   
      23 [-]: GETIMPORT R3 3 [nil]
      24 [-]: CALL R3 1 1  
L 3:  25 [-]: JUMPIF R3 L6 
      26 [-]: NAMECALL R3 R2 K13 [0xA534C3AC]
      27 [-]: CALL R3 1 1  
      28 [-]: FASTCALL1 62 R3 L4
      29 [-]: MOVE R5 R3   
      30 [-]: GETIMPORT R4 3 [nil]
      31 [-]: CALL R4 1 1  
L 4:  32 [-]: JUMPIF R4 L6 
      33 [-]: GETIMPORT R6 15 [nil]
      34 [-]: GETIMPORT R7 17 [nil]
      35 [-]: NAMECALL R4 R3 K18 [0x47901F07]
      36 [-]: CALL R4 3 0  
      37 [-]: GETUPVAL R5 0
      38 [-]: GETTABLEKS R4 R5 K19 [0xCF1FCBA4]
      39 [-]: CALL R4 0 1  
      40 [-]: JUMPIFNOT R4 L5
      41 [-]: LOADK R5 K20 ["{\"loadout\":"]
      42 [-]: GETIMPORT R8 1 [nil]
      43 [-]: NAMECALL R8 R8 K21 [0xE08C150E]
      44 [-]: CALL R8 1 1  
      45 [-]: MOVE R6 R8   
      46 [-]: LOADK R7 K22 ["}"]
      47 [-]: CONCAT R4 R5 R7
      48 [-]: GETIMPORT R5 1 [nil]
      49 [-]: MOVE R7 R4   
      50 [-]: NAMECALL R5 R5 K23 [0x83BFAED0]
      51 [-]: CALL R5 2 0  
      52 [-]: GETIMPORT R5 1 [nil]
      53 [-]: MOVE R7 R3   
      54 [-]: NAMECALL R5 R5 K24 [0x6DD14378]
      55 [-]: CALL R5 2 0  
L 5:  56 [-]: GETUPVAL R5 1
      57 [-]: GETTABLEKS R4 R5 K25 ["mLoadOutType"]
      58 [-]: LOADN R5 0   
      59 [-]: JUMPIFNOTEQ R4 R5 L6
      60 [-]: GETUPVAL R8 1
      61 [-]: GETTABLEKS R7 R8 K26 ["mEquippedItem"]
      62 [-]: GETTABLEKS R6 R7 K27 ["mItem"]
      63 [-]: GETTABLEKS R5 R6 K28 ["mItemId"]
      64 [-]: GETTABLEKS R4 R5 K29 ["mId"]
      65 [-]: GETUPVAL R7 2
      66 [-]: GETTABLEKS R6 R7 K28 ["mItemId"]
      67 [-]: GETTABLEKS R5 R6 K29 ["mId"]
      68 [-]: JUMPIFNOTEQ R4 R5 L6
      69 [-]: GETUPVAL R6 1
      70 [-]: GETTABLEKS R5 R6 K26 ["mEquippedItem"]
      71 [-]: GETTABLEKS R4 R5 K30 ["mCustSlot"]
      72 [-]: GETUPVAL R5 3
      73 [-]: JUMPIFNOTEQ R4 R5 L6
      74 [-]: NAMECALL R4 R3 K31 [0xDE321E6F]
      75 [-]: CALL R4 1 1  
      76 [-]: GETIMPORT R6 33 [nil]
      77 [-]: NAMECALL R6 R6 K34 [0x62C81B76]
      78 [-]: CALL R6 1 1  
      79 [-]: GETUPVAL R8 1
      80 [-]: GETTABLEKS R7 R8 K25 ["mLoadOutType"]
      81 [-]: NAMECALL R4 R4 K35 [0x1D2DFE4A]
      82 [-]: CALL R4 3 0  
L 6:  83 [-]: GETIMPORT R3 37 [nil]
      84 [-]: GETUPVAL R5 4
      85 [-]: NAMECALL R3 R3 K38 [0xBCFB64AB]
      86 [-]: CALL R3 2 1  
      87 [-]: FASTCALL1 62 R3 L7
      88 [-]: MOVE R5 R3   
      89 [-]: GETIMPORT R4 3 [nil]
      90 [-]: CALL R4 1 1  
L 7:  91 [-]: JUMPIF R4 L8 
      92 [-]: LOADK R6 K39 ["OnAppearanceCopied"]
      93 [-]: GETUPVAL R9 2
      94 [-]: GETTABLEKS R8 R9 K28 ["mItemId"]
      95 [-]: GETTABLEKS R7 R8 K29 ["mId"]
      96 [-]: NAMECALL R4 R3 K40 [0xE4162EED]
      97 [-]: CALL R4 3 0  
L 8:  98 [-]: GETUPVAL R4 5
      99 [-]: CALL R4 0 0  
     100 [-]: RETURN R0 0  


; Name:            
; Defined at line: 699
; #Upvalues:       0
; #Parameters:     0
; Is_vararg:       0
; Max Stack Size:  0

       0 [-]: RETURN R0 0  


; Name:            
; Defined at line: 702
; #Upvalues:       2
; #Parameters:     0
; Is_vararg:       0
; Max Stack Size:  15

       0 [-]: GETUPVAL R1 0
       1 [-]: FASTCALL1 62 R1 L0
       2 [-]: GETIMPORT R0 1 [nil]
       3 [-]: CALL R0 1 1  
L 0:   4 [-]: JUMPIFNOT R0 L1
       5 [-]: RETURN R0 0  
L 1:   6 [-]: NEWTABLE R0 0 3
       7 [-]: GETIMPORT R1 3 [nil]
       8 [-]: GETIMPORT R2 5 [nil]
       9 [-]: GETIMPORT R3 7 [nil]
      10 [-]: SETLIST R0 R1 3 [1]
      11 [-]: GETIMPORT R1 9 [nil]
      12 [-]: LOADK R3 K10 ["ItemGrid"]
      13 [-]: LOADN R4 1   
      14 [-]: NAMECALL R1 R1 K11 [0x91A24E4B]
      15 [-]: CALL R1 3 1  
      16 [-]: GETUPVAL R5 0
      17 [-]: GETTABLEKS R4 R5 K12 ["mRowSeparation"]
      18 [-]: GETUPVAL R6 0
      19 [-]: GETTABLEKS R5 R6 K13 ["mRows"]
      20 [-]: MUL R3 R4 R5 
      21 [-]: GETUPVAL R5 0
      22 [-]: GETTABLEKS R4 R5 K14 ["ElementDimBuffer"]
      23 [-]: SUB R2 R3 R4 
      24 [-]: GETUPVAL R4 1
      25 [-]: GETTABLEKS R3 R4 K15 [0xE5E5A417]
      26 [-]: GETIMPORT R4 9 [nil]
      27 [-]: GETUPVAL R9 0
      28 [-]: GETTABLEKS R8 R9 K16 ["mInitialY"]
      29 [-]: GETUPVAL R11 0
      30 [-]: GETTABLEKS R10 R11 K18 ["ElementHeight"]
      31 [-]: DIVK R9 R10 K17 [2]
      32 [-]: SUB R7 R8 R9 
      33 [-]: ADD R6 R1 R7 
      34 [-]: DIVK R7 R2 K17 [2]
      35 [-]: ADD R5 R6 R7 
      36 [-]: CALL R3 2 1  
      37 [-]: GETUPVAL R5 1
      38 [-]: GETTABLEKS R4 R5 K19 [0xD718F59B]
      39 [-]: GETIMPORT R5 9 [nil]
      40 [-]: MOVE R6 R2   
      41 [-]: CALL R4 2 1  
      42 [-]: GETUPVAL R6 1
      43 [-]: GETTABLEKS R5 R6 K20 [0x0DB7934D]
      44 [-]: GETIMPORT R6 9 [nil]
      45 [-]: LOADN R7 10  
      46 [-]: CALL R5 2 1  
      47 [-]: GETIMPORT R6 22 [nil]
      48 [-]: MOVE R7 R0   
      49 [-]: CALL R6 1 3  
      50 [-]: FORGPREP_INEXT R6 L3
L 2:  51 [-]: GETIMPORT R13 25 [nil]
      52 [-]: MOVE R14 R3  
      53 [-]: NAMECALL R11 R10 K26 [0x830EEA67]
      54 [-]: CALL R11 3 0 
      55 [-]: GETIMPORT R13 28 [nil]
      56 [-]: MOVE R14 R4  
      57 [-]: NAMECALL R11 R10 K26 [0x830EEA67]
      58 [-]: CALL R11 3 0 
      59 [-]: GETIMPORT R13 30 [nil]
      60 [-]: MOVE R14 R5  
      61 [-]: NAMECALL R11 R10 K26 [0x830EEA67]
      62 [-]: CALL R11 3 0 
L 3:  63 [-]: FORGLOOP R6 L2 2 [inext]
      64 [-]: RETURN R0 0  


; Name:            
; Defined at line: 720
; #Upvalues:       4
; #Parameters:     3
; Is_vararg:       0
; Max Stack Size:  8

       0 [-]: JUMPIFNOT R0 L1
       1 [-]: JUMPIF R2 L1 
       2 [-]: GETIMPORT R3 1 [nil]
       3 [-]: NAMECALL R3 R3 K2 [0xA1C390FE]
       4 [-]: CALL R3 1 1  
       5 [-]: GETUPVAL R5 1
       6 [-]: GETTABLEKS R4 R5 K3 [0xD3FED720]
       7 [-]: MOVE R5 R3   
       8 [-]: LOADB R6 0   
       9 [-]: CALL R4 2 1  
      10 [-]: SETUPVAL R4 0
      11 [-]: GETUPVAL R4 2
      12 [-]: LOADB R5 1   
      13 [-]: CALL R4 1 0  
      14 [-]: GETUPVAL R5 3
      15 [-]: FASTCALL1 62 R5 L0
      16 [-]: GETIMPORT R4 5 [nil]
      17 [-]: CALL R4 1 1  
L 0:  18 [-]: JUMPIF R4 L1 
      19 [-]: GETUPVAL R4 3
      20 [-]: LOADK R6 K6 ["TransitionOut"]
      21 [-]: LOADK R7 K7 [""]
      22 [-]: NAMECALL R4 R4 K8 [0xE4162EED]
      23 [-]: CALL R4 3 0  
L 1:  24 [-]: RETURN R0 0  


; Name:            
; Defined at line: 734
; #Upvalues:       6
; #Parameters:     0
; Is_vararg:       0
; Max Stack Size:  7

       0 [-]: GETIMPORT R0 1 [nil]
       1 [-]: LOADK R1 K2 ["EE.Interface.Components.Grid"]
       2 [-]: CALL R0 1 1  
       3 [-]: GETTABLEKS R1 R0 K3 [0xDA0C93A2]
       4 [-]: GETIMPORT R2 5 [nil]
       5 [-]: LOADK R3 K6 ["ItemGrid.Item"]
       6 [-]: LOADNIL R4   
       7 [-]: LOADN R5 2   
       8 [-]: LOADN R6 4   
       9 [-]: CALL R1 5 1  
      10 [-]: SETUPVAL R1 0
      11 [-]: GETUPVAL R1 0
      12 [-]: LOADK R3 K7 ["ItemPressed"]
      13 [-]: LOADK R4 K8 ["ItemFocused"]
      14 [-]: LOADK R5 K9 ["ItemUnfocused"]
      15 [-]: NAMECALL R1 R1 K10 [0x1E5B5CFE]
      16 [-]: CALL R1 4 0  
      17 [-]: GETUPVAL R1 0
      18 [-]: LOADB R2 0   
      19 [-]: SETTABLEKS R2 R1 K11 ["mSelectElementsOnFocus"]
      20 [-]: GETUPVAL R1 0
      21 [-]: LOADN R2 140 
      22 [-]: SETTABLEKS R2 R1 K12 ["ElementWidth"]
      23 [-]: GETUPVAL R1 0
      24 [-]: LOADN R2 140 
      25 [-]: SETTABLEKS R2 R1 K13 ["ElementHeight"]
      26 [-]: GETUPVAL R1 0
      27 [-]: LOADN R2 27  
      28 [-]: SETTABLEKS R2 R1 K14 ["ElementDimBuffer"]
      29 [-]: GETUPVAL R1 0
      30 [-]: LOADN R2 350 
      31 [-]: SETTABLEKS R2 R1 K15 ["Width"]
      32 [-]: GETUPVAL R1 0
      33 [-]: LOADN R2 650 
      34 [-]: SETTABLEKS R2 R1 K16 ["Height"]
      35 [-]: GETUPVAL R2 1
      36 [-]: GETTABLEKS R1 R2 K17 [0x27658FAB]
      37 [-]: GETIMPORT R2 5 [nil]
      38 [-]: GETUPVAL R3 0
      39 [-]: CALL R1 2 0  
      40 [-]: GETUPVAL R1 0
      41 [-]: LOADK R3 K18 ["ItemGrid.ScrollBar"]
      42 [-]: LOADN R4 -25 
      43 [-]: NAMECALL R1 R1 K19 [0x3BC79F4F]
      44 [-]: CALL R1 3 0  
      45 [-]: GETUPVAL R1 0
      46 [-]: NAMECALL R1 R1 K20 [0x7220ACB6]
      47 [-]: CALL R1 1 0  
      48 [-]: GETUPVAL R1 0
      49 [-]: LOADB R2 1   
      50 [-]: SETTABLEKS R2 R1 K21 ["mScrollAlwaysVisible"]
      51 [-]: GETUPVAL R1 0
      52 [-]: GETIMPORT R2 23 [nil]
      53 [-]: SETTABLEKS R2 R1 K24 ["VisibleRangeMaterial"]
      54 [-]: GETUPVAL R1 0
      55 [-]: GETIMPORT R2 26 [nil]
      56 [-]: SETTABLEKS R2 R1 K27 ["TextVisibleRangeMaterial"]
      57 [-]: GETUPVAL R1 0
      58 [-]: GETIMPORT R2 29 [nil]
      59 [-]: SETTABLEKS R2 R1 K30 ["RectangleVisibleRangeMaterial"]
      60 [-]: GETUPVAL R1 0
      61 [-]: NEWCLOSURE R2 P0
      62 [-]: MOVE R2 R1   
      63 [-]: MOVE R2 R0   
      64 [-]: SETTABLEKS R2 R1 K31 ["mClipCreatedCallback"]
      65 [-]: GETUPVAL R1 0
      66 [-]: NEWCLOSURE R2 P1
      67 [-]: MOVE R2 R2   
      68 [-]: MOVE R2 R3   
      69 [-]: SETTABLEKS R2 R1 K32 ["mOnSelectedCallback"]
      70 [-]: GETUPVAL R1 0
      71 [-]: NEWCLOSURE R2 P2
      72 [-]: MOVE R2 R1   
      73 [-]: MOVE R2 R0   
      74 [-]: SETTABLEKS R2 R1 K33 ["mOnFocusedCallback"]
      75 [-]: GETUPVAL R1 0
      76 [-]: NEWCLOSURE R2 P3
      77 [-]: MOVE R2 R1   
      78 [-]: MOVE R2 R0   
      79 [-]: SETTABLEKS R2 R1 K34 ["mOnUnfocusedCallback"]
      80 [-]: GETUPVAL R1 0
      81 [-]: NEWCLOSURE R2 P4
      82 [-]: MOVE R2 R1   
      83 [-]: MOVE R2 R0   
      84 [-]: SETTABLEKS R2 R1 K35 ["mElementDrawCallback"]
      85 [-]: GETIMPORT R1 5 [nil]
      86 [-]: LOADK R3 K36 ["ItemGrid.Title.text"]
      87 [-]: LOADK R4 K37 ["/Lotus/Language/Menu/AppearancePreview_GridTitle"]
      88 [-]: NAMECALL R1 R1 K38 [0x20B98DB3]
      89 [-]: CALL R1 3 0  
      90 [-]: GETIMPORT R1 5 [nil]
      91 [-]: LOADK R3 K39 ["ItemGrid.Title"]
      92 [-]: LOADN R4 36  
      93 [-]: GETUPVAL R6 4
      94 [-]: GETTABLEKS R5 R6 K40 ["FloatingContent"]
      95 [-]: NAMECALL R1 R1 K41 [0x67BC869F]
      96 [-]: CALL R1 4 0  
      97 [-]: GETUPVAL R1 5
      98 [-]: CALL R1 0 0  
      99 [-]: RETURN R0 0  


; Name:            
; Defined at line: 798
; #Upvalues:       16
; #Parameters:     0
; Is_vararg:       0
; Max Stack Size:  12

       0 [-]: NEWTABLE R0 0 0
       1 [-]: SETUPVAL R0 0
       2 [-]: GETUPVAL R0 0
       3 [-]: GETUPVAL R2 1
       4 [-]: GETTABLEKS R1 R2 K0 [0x5D10207D]
       5 [-]: LOADN R2 2   
       6 [-]: LOADB R3 1   
       7 [-]: CALL R1 2 1  
       8 [-]: SETTABLEKS R1 R0 K1 ["Background1"]
       9 [-]: GETUPVAL R0 0
      10 [-]: GETUPVAL R2 1
      11 [-]: GETTABLEKS R1 R2 K0 [0x5D10207D]
      12 [-]: LOADN R2 9   
      13 [-]: LOADB R3 1   
      14 [-]: CALL R1 2 1  
      15 [-]: SETTABLEKS R1 R0 K2 ["FloatingContent"]
      16 [-]: GETIMPORT R0 4 [nil]
      17 [-]: LOADK R1 K5 ["Lotus.Interface.Components.ThemedSpinner"]
      18 [-]: CALL R0 1 1  
      19 [-]: GETTABLEKS R1 R0 K6 [0xAE6791BA]
      20 [-]: GETIMPORT R2 8 [nil]
      21 [-]: LOADK R3 K9 ["Spinner"]
      22 [-]: CALL R1 2 1  
      23 [-]: SETUPVAL R1 2
      24 [-]: GETUPVAL R1 2
      25 [-]: LOADB R3 1   
      26 [-]: NAMECALL R1 R1 K10 [0x46610C50]
      27 [-]: CALL R1 2 0  
      28 [-]: GETUPVAL R2 1
      29 [-]: GETTABLEKS R1 R2 K11 [0xB6BA7AF3]
      30 [-]: CALL R1 0 1  
      31 [-]: SETUPVAL R1 3
      32 [-]: GETUPVAL R2 4
      33 [-]: GETTABLEKS R1 R2 K12 [0x37D68E16]
      34 [-]: LOADB R2 0   
      35 [-]: GETUPVAL R3 5
      36 [-]: CALL R1 2 0  
      37 [-]: GETUPVAL R2 6
      38 [-]: GETTABLEKS R1 R2 K13 [0x9E0F8295]
      39 [-]: LOADB R2 1   
      40 [-]: CALL R1 1 0  
      41 [-]: GETUPVAL R2 6
      42 [-]: GETTABLEKS R1 R2 K14 [0x9E3D3434]
      43 [-]: LOADB R2 1   
      44 [-]: CALL R1 1 0  
      45 [-]: GETUPVAL R2 6
      46 [-]: GETTABLEKS R1 R2 K15 [0x154D0AD2]
      47 [-]: LOADB R2 1   
      48 [-]: CALL R1 1 0  
      49 [-]: GETIMPORT R1 8 [nil]
      50 [-]: GETIMPORT R4 18 [nil]
      51 [-]: JUMPXEQKB R4 1 L0
      52 [-]: LOADB R3 0 +1
L 0:  53 [-]: LOADB R3 1   
L 1:  54 [-]: NAMECALL R1 R1 K19 [0x2002E1DC]
      55 [-]: CALL R1 2 0  
      56 [-]: GETIMPORT R1 8 [nil]
      57 [-]: LOADB R3 1   
      58 [-]: NAMECALL R1 R1 K20 [0x767C0947]
      59 [-]: CALL R1 2 0  
      60 [-]: GETIMPORT R1 22 [nil]
      61 [-]: JUMPIF R1 L2 
      62 [-]: GETIMPORT R1 24 [nil]
      63 [-]: CALL R1 0 0  
      64 [-]: LOADB R1 1   
      65 [-]: SETUPVAL R1 7
L 2:  66 [-]: GETIMPORT R1 26 [nil]
      67 [-]: GETIMPORT R4 28 [nil]
      68 [-]: GETTABLEKS R3 R4 K29 ["UIMovie_DetailedPurchaseDialog"]
      69 [-]: NAMECALL R1 R1 K30 [0xBCFB64AB]
      70 [-]: CALL R1 2 1  
      71 [-]: FASTCALL1 62 R1 L3
      72 [-]: MOVE R3 R1   
      73 [-]: GETIMPORT R2 32 [nil]
      74 [-]: CALL R2 1 1  
L 3:  75 [-]: JUMPIF R2 L4 
      76 [-]: LOADK R4 K33 ["HideScreen"]
      77 [-]: LOADK R5 K34 ["true"]
      78 [-]: NAMECALL R2 R1 K35 [0xE4162EED]
      79 [-]: CALL R2 3 0  
L 4:  80 [-]: GETIMPORT R2 4 [nil]
      81 [-]: LOADK R3 K36 ["Lotus.Interface.Components.RotationControl"]
      82 [-]: CALL R2 1 1  
      83 [-]: GETTABLEKS R3 R2 K6 [0xAE6791BA]
      84 [-]: GETIMPORT R4 8 [nil]
      85 [-]: CALL R3 1 1  
      86 [-]: SETUPVAL R3 8
      87 [-]: GETUPVAL R3 8
      88 [-]: LOADB R4 1   
      89 [-]: SETTABLEKS R4 R3 K37 ["mUseControllerDeltaIfSet"]
      90 [-]: GETIMPORT R3 4 [nil]
      91 [-]: LOADK R4 K38 ["Lotus.Interface.Components.AvatarDiorama"]
      92 [-]: CALL R3 1 1  
      93 [-]: GETTABLEKS R4 R3 K39 [0x9618BEA2]
      94 [-]: GETIMPORT R5 8 [nil]
      95 [-]: CALL R4 1 1  
      96 [-]: SETUPVAL R4 9
      97 [-]: GETIMPORT R4 8 [nil]
      98 [-]: GETUPVAL R7 0
      99 [-]: GETTABLEKS R6 R7 K1 ["Background1"]
     100 [-]: NAMECALL R4 R4 K40 [0xC6A10AB1]
     101 [-]: CALL R4 2 0  
     102 [-]: GETUPVAL R5 10
     103 [-]: GETTABLEKS R4 R5 K41 [0x4C232AFC]
     104 [-]: GETIMPORT R5 8 [nil]
     105 [-]: LOADK R6 K42 [0.90000000000000002]
     106 [-]: LOADK R7 K43 [0.25]
     107 [-]: CALL R4 3 0  
     108 [-]: GETIMPORT R4 44 [nil]
     109 [-]: LOADB R5 1   
     110 [-]: SETTABLEKS R5 R4 K45 ["AppearancePreviewOpen"]
     111 [-]: GETUPVAL R5 12
     112 [-]: GETTABLEKS R4 R5 K6 [0xAE6791BA]
     113 [-]: GETIMPORT R5 8 [nil]
     114 [-]: CALL R4 1 1  
     115 [-]: SETUPVAL R4 11
     116 [-]: GETUPVAL R4 11
     117 [-]: GETIMPORT R6 8 [nil]
     118 [-]: LOADK R7 K46 ["ItemGrid"]
     119 [-]: NEWTABLE R8 0 2
     120 [-]: GETUPVAL R10 11
     121 [-]: GETTABLEKS R9 R10 K47 ["ANCHOR_V_TOP"]
     122 [-]: GETUPVAL R11 11
     123 [-]: GETTABLEKS R10 R11 K48 ["ANCHOR_H_LEFT"]
     124 [-]: SETLIST R8 R9 2 [1]
     125 [-]: NAMECALL R4 R4 K49 [0x20FF29F7]
     126 [-]: CALL R4 4 0  
     127 [-]: GETUPVAL R4 11
     128 [-]: GETIMPORT R6 8 [nil]
     129 [-]: LOADK R7 K50 ["ApplyBtn"]
     130 [-]: NEWTABLE R8 0 2
     131 [-]: GETUPVAL R10 11
     132 [-]: GETTABLEKS R9 R10 K51 ["ANCHOR_V_BOTTOM"]
     133 [-]: GETUPVAL R11 11
     134 [-]: GETTABLEKS R10 R11 K52 ["ANCHOR_H_RIGHT"]
     135 [-]: SETLIST R8 R9 2 [1]
     136 [-]: NAMECALL R4 R4 K49 [0x20FF29F7]
     137 [-]: CALL R4 4 0  
     138 [-]: GETUPVAL R4 11
     139 [-]: GETIMPORT R6 8 [nil]
     140 [-]: NAMECALL R6 R6 K53 [0x6B837788]
     141 [-]: CALL R6 1 1  
     142 [-]: GETIMPORT R7 8 [nil]
     143 [-]: NAMECALL R7 R7 K54 [0xAF9FDA9F]
     144 [-]: CALL R7 1 -1 
     145 [-]: NAMECALL R4 R4 K55 [0xFAA69527]
     146 [-]: CALL R4 -1 0 
     147 [-]: GETIMPORT R4 4 [nil]
     148 [-]: LOADK R5 K56 ["Lotus.Interface.Components.ThemedButton"]
     149 [-]: CALL R4 1 1  
     150 [-]: GETTABLEKS R5 R4 K6 [0xAE6791BA]
     151 [-]: GETIMPORT R6 8 [nil]
     152 [-]: LOADK R7 K50 ["ApplyBtn"]
     153 [-]: LOADK R8 K57 ["/Lotus/Language/Menu/AppearancePreview_ApplyBtn"]
     154 [-]: LOADK R9 K58 ["ApplyAppearance"]
     155 [-]: CALL R5 4 1  
     156 [-]: SETUPVAL R5 13
     157 [-]: GETUPVAL R5 13
     158 [-]: NAMECALL R5 R5 K59 [0x4E86C602]
     159 [-]: CALL R5 1 0  
     160 [-]: GETUPVAL R5 13
     161 [-]: LOADN R7 257 
     162 [-]: NAMECALL R5 R5 K60 [0x8D77B2B2]
     163 [-]: CALL R5 2 0  
     164 [-]: GETUPVAL R5 13
     165 [-]: LOADB R7 0   
     166 [-]: NAMECALL R5 R5 K10 [0x46610C50]
     167 [-]: CALL R5 2 0  
     168 [-]: GETUPVAL R5 13
     169 [-]: NAMECALL R5 R5 K61 [0x71E9AC81]
     170 [-]: CALL R5 1 0  
     171 [-]: GETIMPORT R5 8 [nil]
     172 [-]: LOADK R7 K62 ["Link"]
     173 [-]: LOADN R8 11  
     174 [-]: LOADB R9 0   
     175 [-]: NAMECALL R5 R5 K63 [0xAADE900E]
     176 [-]: CALL R5 4 0  
     177 [-]: GETIMPORT R5 8 [nil]
     178 [-]: LOADK R7 K46 ["ItemGrid"]
     179 [-]: LOADN R8 11  
     180 [-]: LOADB R9 0   
     181 [-]: NAMECALL R5 R5 K63 [0xAADE900E]
     182 [-]: CALL R5 4 0  
     183 [-]: GETUPVAL R5 14
     184 [-]: CALL R5 0 0  
     185 [-]: GETIMPORT R5 26 [nil]
     186 [-]: LOADK R7 K64 ["HideScreenForPlatPurchase"]
     187 [-]: LOADK R8 K34 ["true"]
     188 [-]: NAMECALL R5 R5 K65 [0x7E17AE26]
     189 [-]: CALL R5 3 0  
     190 [-]: GETUPVAL R5 15
     191 [-]: CALL R5 0 0  
     192 [-]: GETIMPORT R6 67 [nil]
     193 [-]: FASTCALL1 62 R6 L5
     194 [-]: GETIMPORT R5 32 [nil]
     195 [-]: CALL R5 1 1  
L 5: 196 [-]: JUMPIF R5 L6 
     197 [-]: GETIMPORT R5 67 [nil]
     198 [-]: GETIMPORT R7 69 [nil]
     199 [-]: LOADK R8 K70 ["LOOK_LINK"]
     200 [-]: CALL R7 1 1  
     201 [-]: LOADK R8 K71 ["OPENED"]
     202 [-]: NAMECALL R5 R5 K72 [0x8B8FB8B7]
     203 [-]: CALL R5 3 0  
L 6: 204 [-]: RETURN R0 0  


; Name:            
; Defined at line: 864
; #Upvalues:       10
; #Parameters:     0
; Is_vararg:       0
; Max Stack Size:  8

       0 [-]: GETIMPORT R0 1 [nil]
       1 [-]: GETIMPORT R2 3 [nil]
       2 [-]: CALL R2 0 -1 
       3 [-]: NAMECALL R0 R0 K4 [0x8A8C8D5A]
       4 [-]: CALL R0 -1 0 
       5 [-]: GETUPVAL R1 0
       6 [-]: FASTCALL1 62 R1 L0
       7 [-]: GETIMPORT R0 6 [nil]
       8 [-]: CALL R0 1 1  
L 0:   9 [-]: JUMPIF R0 L1 
      10 [-]: GETUPVAL R0 0
      11 [-]: NAMECALL R0 R0 K7 [0xFAA69527]
      12 [-]: CALL R0 1 0  
L 1:  13 [-]: GETUPVAL R1 1
      14 [-]: GETTABLEKS R0 R1 K8 ["IsLoading"]
      15 [-]: JUMPIFNOT R0 L3
      16 [-]: GETUPVAL R2 1
      17 [-]: GETTABLEKS R1 R2 K9 ["Loader"]
      18 [-]: FASTCALL1 62 R1 L2
      19 [-]: GETIMPORT R0 6 [nil]
      20 [-]: CALL R0 1 1  
L 2:  21 [-]: JUMPIF R0 L3 
      22 [-]: GETUPVAL R1 1
      23 [-]: GETTABLEKS R0 R1 K9 ["Loader"]
      24 [-]: NAMECALL R0 R0 K10 [0xD2D3875A]
      25 [-]: CALL R0 1 1  
      26 [-]: JUMPIFNOT R0 L3
      27 [-]: GETUPVAL R0 1
      28 [-]: LOADB R1 0   
      29 [-]: SETTABLEKS R1 R0 K8 ["IsLoading"]
      30 [-]: GETUPVAL R0 2
      31 [-]: CALL R0 0 0  
L 3:  32 [-]: GETUPVAL R1 1
      33 [-]: GETTABLEKS R0 R1 K11 ["IsLoadingSecond"]
      34 [-]: JUMPIFNOT R0 L5
      35 [-]: GETUPVAL R2 1
      36 [-]: GETTABLEKS R1 R2 K12 ["SecondaryLoader"]
      37 [-]: FASTCALL1 62 R1 L4
      38 [-]: GETIMPORT R0 6 [nil]
      39 [-]: CALL R0 1 1  
L 4:  40 [-]: JUMPIF R0 L5 
      41 [-]: GETUPVAL R1 1
      42 [-]: GETTABLEKS R0 R1 K12 ["SecondaryLoader"]
      43 [-]: NAMECALL R0 R0 K10 [0xD2D3875A]
      44 [-]: CALL R0 1 1  
      45 [-]: JUMPIFNOT R0 L5
      46 [-]: GETUPVAL R0 1
      47 [-]: LOADB R1 0   
      48 [-]: SETTABLEKS R1 R0 K11 ["IsLoadingSecond"]
      49 [-]: GETUPVAL R0 3
      50 [-]: CALL R0 0 0  
L 5:  51 [-]: GETUPVAL R1 4
      52 [-]: GETTABLEKS R0 R1 K13 ["mDioramaLoader"]
      53 [-]: NAMECALL R0 R0 K14 [0xCFD9CD76]
      54 [-]: CALL R0 1 1  
      55 [-]: JUMPIFNOT R0 L7
      56 [-]: GETUPVAL R1 4
      57 [-]: GETTABLEKS R0 R1 K13 ["mDioramaLoader"]
      58 [-]: NAMECALL R0 R0 K15 [0x842BDEF9]
      59 [-]: CALL R0 1 1  
      60 [-]: JUMPIFNOT R0 L8
      61 [-]: LOADB R0 1   
      62 [-]: SETUPVAL R0 5
      63 [-]: GETUPVAL R1 4
      64 [-]: GETTABLEKS R0 R1 K13 ["mDioramaLoader"]
      65 [-]: NAMECALL R0 R0 K16 [0xA4497305]
      66 [-]: CALL R0 1 0  
      67 [-]: GETUPVAL R0 4
      68 [-]: NAMECALL R0 R0 K17 [0x4E1978B3]
      69 [-]: CALL R0 1 3  
      70 [-]: GETUPVAL R3 6
      71 [-]: GETUPVAL R5 7
      72 [-]: GETTABLEKS R4 R5 K18 [0x06D055F9]
      73 [-]: FASTCALL1 62 R1 L6
      74 [-]: MOVE R7 R1   
      75 [-]: GETIMPORT R6 6 [nil]
      76 [-]: CALL R6 1 1  
L 6:  77 [-]: NOT R5 R6    
      78 [-]: MOVE R6 R1   
      79 [-]: MOVE R7 R2   
      80 [-]: CALL R4 3 1  
      81 [-]: MOVE R5 R0   
      82 [-]: CALL R3 2 0  
      83 [-]: GETUPVAL R4 7
      84 [-]: GETTABLEKS R3 R4 K19 [0x4C232AFC]
      85 [-]: GETIMPORT R4 1 [nil]
      86 [-]: LOADN R5 0   
      87 [-]: LOADK R6 K20 [0.25]
      88 [-]: CALL R3 3 0  
      89 [-]: GETUPVAL R3 0
      90 [-]: LOADB R5 0   
      91 [-]: NAMECALL R3 R3 K21 [0x46610C50]
      92 [-]: CALL R3 2 0  
      93 [-]: JUMP L8
     
L 7:  94 [-]: GETUPVAL R0 4
      95 [-]: GETUPVAL R2 8
      96 [-]: NAMECALL R0 R0 K22 [0x5E2C4C49]
      97 [-]: CALL R0 2 0  
      98 [-]: GETUPVAL R0 4
      99 [-]: NAMECALL R0 R0 K7 [0xFAA69527]
     100 [-]: CALL R0 1 0  
L 8: 101 [-]: GETIMPORT R0 25 [nil]
     102 [-]: CALL R0 0 1  
     103 [-]: JUMPIFNOT R0 L10
     104 [-]: GETUPVAL R0 9
     105 [-]: JUMPIF R0 L11
     106 [-]: GETUPVAL R1 4
     107 [-]: FASTCALL1 62 R1 L9
     108 [-]: GETIMPORT R0 6 [nil]
     109 [-]: CALL R0 1 1  
L 9: 110 [-]: JUMPIF R0 L11
     111 [-]: GETUPVAL R0 4
     112 [-]: NAMECALL R0 R0 K26 [0x85F5FAD3]
     113 [-]: CALL R0 1 1  
     114 [-]: JUMPIFNOT R0 L11
     115 [-]: GETUPVAL R0 8
     116 [-]: LOADB R1 1   
     117 [-]: SETTABLEKS R1 R0 K27 ["mForceUseControllerDelta"]
     118 [-]: GETUPVAL R0 8
     119 [-]: LOADB R2 1   
     120 [-]: NAMECALL R0 R0 K28 [0xCC64D64D]
     121 [-]: CALL R0 2 0  
     122 [-]: GETIMPORT R0 1 [nil]
     123 [-]: LOADB R2 1   
     124 [-]: NAMECALL R0 R0 K29 [0x824D113A]
     125 [-]: CALL R0 2 0  
     126 [-]: GETUPVAL R0 8
     127 [-]: NAMECALL R0 R0 K7 [0xFAA69527]
     128 [-]: CALL R0 1 0  
     129 [-]: RETURN R0 0  
L10: 130 [-]: GETUPVAL R0 8
     131 [-]: LOADB R1 0   
     132 [-]: SETTABLEKS R1 R0 K27 ["mForceUseControllerDelta"]
     133 [-]: GETUPVAL R0 8
     134 [-]: NAMECALL R0 R0 K7 [0xFAA69527]
     135 [-]: CALL R0 1 0  
L11: 136 [-]: RETURN R0 0  


; Name:            
; Defined at line: 910
; #Upvalues:       2
; #Parameters:     4
; Is_vararg:       0
; Max Stack Size:  9

       0 [-]: GETUPVAL R5 0
       1 [-]: FASTCALL1 62 R5 L0
       2 [-]: GETIMPORT R4 1 [nil]
       3 [-]: CALL R4 1 1  
L 0:   4 [-]: JUMPIF R4 L1 
       5 [-]: GETUPVAL R4 0
       6 [-]: GETIMPORT R6 3 [nil]
       7 [-]: NAMECALL R6 R6 K4 [0x6B837788]
       8 [-]: CALL R6 1 1  
       9 [-]: GETIMPORT R7 3 [nil]
      10 [-]: NAMECALL R7 R7 K5 [0xAF9FDA9F]
      11 [-]: CALL R7 1 -1 
      12 [-]: NAMECALL R4 R4 K6 [0xFAA69527]
      13 [-]: CALL R4 -1 0 
L 1:  14 [-]: GETUPVAL R4 1
      15 [-]: CALL R4 0 0  
      16 [-]: RETURN R0 0  


; Name:            
; Defined at line: 918
; #Upvalues:       3
; #Parameters:     1
; Is_vararg:       0
; Max Stack Size:  2

       0 [-]: SETUPVAL R0 0
       1 [-]: GETUPVAL R1 1
       2 [-]: CALL R1 0 1  
       3 [-]: JUMPIF R1 L0 
       4 [-]: GETUPVAL R1 2
       5 [-]: CALL R1 0 0  
L 0:   6 [-]: RETURN R0 0  


; Name:            
; Defined at line: 929
; #Upvalues:       1
; #Parameters:     1
; Is_vararg:       0
; Max Stack Size:  1

       0 [-]: SETUPVAL R0 0
       1 [-]: RETURN R0 0  


; Name:            
; Defined at line: 933
; #Upvalues:       0
; #Parameters:     0
; Is_vararg:       0
; Max Stack Size:  1

       0 [-]: LOADB R0 1   
       1 [-]: RETURN R0 1  


; Name:            
; Defined at line: 937
; #Upvalues:       2
; #Parameters:     1
; Is_vararg:       0
; Max Stack Size:  5

       0 [-]: GETUPVAL R1 0
       1 [-]: JUMPIF R1 L1 
       2 [-]: GETUPVAL R2 1
       3 [-]: FASTCALL1 62 R2 L0
       4 [-]: GETIMPORT R1 1 [nil]
       5 [-]: CALL R1 1 1  
L 0:   6 [-]: JUMPIF R1 L1 
       7 [-]: GETUPVAL R1 1
       8 [-]: GETIMPORT R3 3 [nil]
       9 [-]: MOVE R4 R0   
      10 [-]: CALL R3 1 1  
      11 [-]: LOADB R4 1   
      12 [-]: NAMECALL R1 R1 K4 [0x070DAA5A]
      13 [-]: CALL R1 3 0  
L 1:  14 [-]: RETURN R0 0  


; Name:            
; Defined at line: 943
; #Upvalues:       1
; #Parameters:     1
; Is_vararg:       0
; Max Stack Size:  5

       0 [-]: GETUPVAL R2 0
       1 [-]: FASTCALL1 62 R2 L0
       2 [-]: GETIMPORT R1 1 [nil]
       3 [-]: CALL R1 1 1  
L 0:   4 [-]: JUMPIF R1 L1 
       5 [-]: GETUPVAL R1 0
       6 [-]: GETIMPORT R3 3 [nil]
       7 [-]: MOVE R4 R0   
       8 [-]: CALL R3 1 1  
       9 [-]: LOADB R4 1   
      10 [-]: NAMECALL R1 R1 K4 [0xDF42446E]
      11 [-]: CALL R1 3 0  
L 1:  12 [-]: RETURN R0 0  


; Name:            
; Defined at line: 949
; #Upvalues:       1
; #Parameters:     1
; Is_vararg:       0
; Max Stack Size:  5

       0 [-]: GETUPVAL R2 0
       1 [-]: FASTCALL1 62 R2 L0
       2 [-]: GETIMPORT R1 1 [nil]
       3 [-]: CALL R1 1 1  
L 0:   4 [-]: JUMPIF R1 L1 
       5 [-]: GETUPVAL R1 0
       6 [-]: GETIMPORT R3 3 [nil]
       7 [-]: MOVE R4 R0   
       8 [-]: CALL R3 1 1  
       9 [-]: LOADB R4 1   
      10 [-]: NAMECALL R1 R1 K4 [0xBCE5A201]
      11 [-]: CALL R1 3 0  
L 1:  12 [-]: RETURN R0 0  


; Name:            
; Defined at line: 955
; #Upvalues:       2
; #Parameters:     1
; Is_vararg:       0
; Max Stack Size:  4

       0 [-]: GETUPVAL R1 0
       1 [-]: JUMPIF R1 L0 
       2 [-]: GETUPVAL R1 1
       3 [-]: MOVE R3 R0   
       4 [-]: NAMECALL R1 R1 K0 [0x99F92C72]
       5 [-]: CALL R1 2 0  
       6 [-]: GETUPVAL R1 1
       7 [-]: LOADB R3 1   
       8 [-]: NAMECALL R1 R1 K1 [0xCC64D64D]
       9 [-]: CALL R1 2 0  
      10 [-]: RETURN R0 0  
L 0:  11 [-]: GETUPVAL R1 1
      12 [-]: LOADN R3 0   
      13 [-]: NAMECALL R1 R1 K0 [0x99F92C72]
      14 [-]: CALL R1 2 0  
      15 [-]: GETUPVAL R1 1
      16 [-]: LOADB R3 0   
      17 [-]: NAMECALL R1 R1 K1 [0xCC64D64D]
      18 [-]: CALL R1 2 0  
      19 [-]: RETURN R0 0  


; Name:            
; Defined at line: 965
; #Upvalues:       1
; #Parameters:     2
; Is_vararg:       0
; Max Stack Size:  4

       0 [-]: GETUPVAL R2 0
       1 [-]: MOVE R3 R1   
       2 [-]: CALL R2 1 0  
       3 [-]: LOADB R2 1   
       4 [-]: RETURN R2 1  


; Name:            
; Defined at line: 970
; #Upvalues:       1
; #Parameters:     2
; Is_vararg:       0
; Max Stack Size:  4

       0 [-]: GETUPVAL R2 0
       1 [-]: MOVE R3 R1   
       2 [-]: CALL R2 1 0  
       3 [-]: LOADB R2 1   
       4 [-]: RETURN R2 1  


; Name:            
; Defined at line: 975
; #Upvalues:       1
; #Parameters:     0
; Is_vararg:       0
; Max Stack Size:  3

       0 [-]: GETUPVAL R1 0
       1 [-]: FASTCALL1 62 R1 L0
       2 [-]: GETIMPORT R0 1 [nil]
       3 [-]: CALL R0 1 1  
L 0:   4 [-]: JUMPIF R0 L1 
       5 [-]: GETUPVAL R0 0
       6 [-]: LOADB R2 1   
       7 [-]: NAMECALL R0 R0 K2 [0xCC64D64D]
       8 [-]: CALL R0 2 0  
L 1:   9 [-]: RETURN R0 0  


; Name:            
; Defined at line: 981
; #Upvalues:       1
; #Parameters:     0
; Is_vararg:       0
; Max Stack Size:  3

       0 [-]: GETUPVAL R1 0
       1 [-]: FASTCALL1 62 R1 L0
       2 [-]: GETIMPORT R0 1 [nil]
       3 [-]: CALL R0 1 1  
L 0:   4 [-]: JUMPIF R0 L1 
       5 [-]: GETUPVAL R0 0
       6 [-]: LOADB R2 0   
       7 [-]: NAMECALL R0 R0 K2 [0xCC64D64D]
       8 [-]: CALL R0 2 0  
L 1:   9 [-]: RETURN R0 0  


; Name:            
; Defined at line: 987
; #Upvalues:       2
; #Parameters:     2
; Is_vararg:       0
; Max Stack Size:  6

       0 [-]: GETUPVAL R2 0
       1 [-]: JUMPIF R2 L1 
       2 [-]: GETUPVAL R4 1
       3 [-]: GETTABLEKS R3 R4 K0 ["mScrollBar"]
       4 [-]: FASTCALL1 62 R3 L0
       5 [-]: GETIMPORT R2 2 [nil]
       6 [-]: CALL R2 1 1  
L 0:   7 [-]: JUMPIF R2 L1 
       8 [-]: GETUPVAL R3 1
       9 [-]: GETTABLEKS R2 R3 K0 ["mScrollBar"]
      10 [-]: GETIMPORT R4 4 [nil]
      11 [-]: MOVE R5 R1   
      12 [-]: CALL R4 1 -1 
      13 [-]: NAMECALL R2 R2 K5 [0x30456F58]
      14 [-]: CALL R2 -1 0 
L 1:  15 [-]: RETURN R0 0  


; Name:            
; Defined at line: 993
; #Upvalues:       2
; #Parameters:     3
; Is_vararg:       0
; Max Stack Size:  4

       0 [-]: JUMPXEQKS R1 K0 L1 NOT ["EN_MOUSE_B0"]
       1 [-]: JUMPXEQKS R2 K1 L0 NOT ["1"]
       2 [-]: GETUPVAL R3 0
       3 [-]: CALL R3 0 0  
       4 [-]: RETURN R0 0  
L 0:   5 [-]: GETUPVAL R3 1
       6 [-]: CALL R3 0 0  
L 1:   7 [-]: RETURN R0 0  



