; Name:            
; Defined at line: 1
; #Upvalues:       0
; #Parameters:     0
; Is_vararg:       1
; Max Stack Size:  23

       1 [-]: GETIMPORT R0 1; var0 = 0x2D0FAD09
       2 [-]: LOADK R1 K2  ; var1 = "EE.Interface.Utilities"
       3 [-]: CALL R0 2 2  ; var0 = var0(var1)
       4 [-]: GETIMPORT R1 1; var1 = 0x2D0FAD09
       5 [-]: LOADK R2 K3  ; var2 = "Lotus.Interface.LotusUtilities"
       6 [-]: CALL R1 2 2  ; var1 = var1(var2)
       7 [-]: GETIMPORT R2 1; var2 = 0x2D0FAD09
       8 [-]: LOADK R3 K4  ; var3 = "Lotus.Interface.UIStyleUtilities"
       9 [-]: CALL R2 2 2  ; var2 = var2(var3)
      10 [-]: GETIMPORT R3 1; var3 = 0x2D0FAD09
      11 [-]: LOADK R4 K5  ; var4 = "Lotus.Interface.UIUtilities"
      12 [-]: CALL R3 2 2  ; var3 = var3(var4)
      13 [-]: GETIMPORT R4 1; var4 = 0x2D0FAD09
      14 [-]: LOADK R5 K6  ; var5 = "Lotus.Interface.StoreItemUtilities"
      15 [-]: CALL R4 2 2  ; var4 = var4(var5)
      16 [-]: LOADB R5 1   ; var5 = true
      17 [-]: LOADNIL R6   ; var6 = nil
      18 [-]: LOADNIL R7   ; var7 = nil
      19 [-]: NEWTABLE R8 4 0; var8 = {}
      20 [-]: LOADNIL R9   ; var9 = nil
      21 [-]: LOADNIL R10  ; var10 = nil
      22 [-]: LOADNIL R11  ; var11 = nil
      23 [-]: LOADB R12 0  ; var12 = false
      24 [-]: LOADNIL R13  ; var13 = nil
      25 [-]: NEWTABLE R14 0 6; var14 = {}
      26 [-]: DUPTABLE R15 9; 
      27 [-]: GETIMPORT R16 11; var16 = 0xB009BBC6
      28 [-]: LOADK R17 K12; var17 = "/Lotus/Types/StoreItems/Boosters/AffinityBlessingStoreItem"
      29 [-]: CALL R16 2 2 ; var16 = var16(var17)
      30 [-]: SETTABLEKS R16 R15 K7; var16["StoreItem"] = var15
      31 [-]: LOADK R16 K13; var16 = "xp"
      32 [-]: SETTABLEKS R16 R15 K8; var16["Tag"] = var15
      33 [-]: DUPTABLE R16 9; 
      34 [-]: GETIMPORT R17 11; var17 = 0xB009BBC6
      35 [-]: LOADK R18 K14; var18 = "/Lotus/Types/StoreItems/Boosters/CreditBlessingStoreItem"
      36 [-]: CALL R17 2 2 ; var17 = var17(var18)
      37 [-]: SETTABLEKS R17 R16 K7; var17["StoreItem"] = var16
      38 [-]: LOADK R17 K15; var17 = "cred"
      39 [-]: SETTABLEKS R17 R16 K8; var17["Tag"] = var16
      40 [-]: DUPTABLE R17 9; 
      41 [-]: GETIMPORT R18 11; var18 = 0xB009BBC6
      42 [-]: LOADK R19 K16; var19 = "/Lotus/Types/StoreItems/Boosters/ResourceDropChanceBlessingStoreItem"
      43 [-]: CALL R18 2 2 ; var18 = var18(var19)
      44 [-]: SETTABLEKS R18 R17 K7; var18["StoreItem"] = var17
      45 [-]: LOADK R18 K17; var18 = "res"
      46 [-]: SETTABLEKS R18 R17 K8; var18["Tag"] = var17
      47 [-]: DUPTABLE R18 9; 
      48 [-]: GETIMPORT R19 11; var19 = 0xB009BBC6
      49 [-]: LOADK R20 K18; var20 = "/Lotus/Types/StoreItems/Boosters/DamageBlessingStoreItem"
      50 [-]: CALL R19 2 2 ; var19 = var19(var20)
      51 [-]: SETTABLEKS R19 R18 K7; var19["StoreItem"] = var18
      52 [-]: LOADK R19 K19; var19 = "dmg"
      53 [-]: SETTABLEKS R19 R18 K8; var19["Tag"] = var18
      54 [-]: DUPTABLE R19 9; 
      55 [-]: GETIMPORT R20 11; var20 = 0xB009BBC6
      56 [-]: LOADK R21 K20; var21 = "/Lotus/Types/StoreItems/Boosters/HealthBlessingStoreItem"
      57 [-]: CALL R20 2 2 ; var20 = var20(var21)
      58 [-]: SETTABLEKS R20 R19 K7; var20["StoreItem"] = var19
      59 [-]: LOADK R20 K21; var20 = "hp"
      60 [-]: SETTABLEKS R20 R19 K8; var20["Tag"] = var19
      61 [-]: DUPTABLE R20 9; 
      62 [-]: GETIMPORT R21 11; var21 = 0xB009BBC6
      63 [-]: LOADK R22 K22; var22 = "/Lotus/Types/StoreItems/Boosters/ShieldBlessingStoreItem"
      64 [-]: CALL R21 2 2 ; var21 = var21(var22)
      65 [-]: SETTABLEKS R21 R20 K7; var21["StoreItem"] = var20
      66 [-]: LOADK R21 K23; var21 = "shld"
      67 [-]: SETTABLEKS R21 R20 K8; var21["Tag"] = var20
      68 [-]: SETLIST R14 R15 6 [1]; var14[1] = var15; var14[2] = var16; var14[3] = var17; var14[4] = var18; var14[5] = var19; var14[6] = var20; var14[7] = var21; 
      69 [-]: NEWCLOSURE R15 P0; 
      70 [-]: CAPTURE REF R5; 
      71 [-]: SETGLOBAL R15 K24; "IsInputBlocked" = var15
      72 [-]: NEWCLOSURE R15 P1; 
      73 [-]: CAPTURE VAL R0; 
      74 [-]: CAPTURE REF R6; 
      75 [-]: CAPTURE VAL R1; 
      76 [-]: CAPTURE REF R12; 
      77 [-]: CAPTURE REF R5; 
      78 [-]: NEWCLOSURE R16 P2; 
      79 [-]: CAPTURE REF R10; 
      80 [-]: CAPTURE VAL R0; 
      81 [-]: DUPCLOSURE R17 K25; 
      82 [-]: CAPTURE VAL R16; 
      83 [-]: SETGLOBAL R17 K26; "TransitionOut" = var17
      84 [-]: DUPCLOSURE R17 K27; 
      85 [-]: NEWCLOSURE R18 P5; 
      86 [-]: CAPTURE REF R7; 
      87 [-]: CAPTURE VAL R0; 
      88 [-]: CAPTURE REF R9; 
      89 [-]: NEWCLOSURE R19 P6; 
      90 [-]: CAPTURE REF R9; 
      91 [-]: CAPTURE VAL R16; 
      92 [-]: CAPTURE VAL R0; 
      93 [-]: SETGLOBAL R19 K28; "OnBlessingConfirmed" = var19
      94 [-]: NEWCLOSURE R19 P7; 
      95 [-]: CAPTURE REF R9; 
      96 [-]: CAPTURE VAL R3; 
      97 [-]: CAPTURE REF R5; 
      98 [-]: CAPTURE REF R12; 
      99 [-]: CAPTURE REF R11; 
     100 [-]: CAPTURE VAL R1; 
     101 [-]: CAPTURE VAL R0; 
     102 [-]: NEWCLOSURE R20 P8; 
     103 [-]: CAPTURE REF R9; 
     104 [-]: CAPTURE VAL R14; 
     105 [-]: CAPTURE VAL R4; 
     106 [-]: NEWCLOSURE R21 P9; 
     107 [-]: CAPTURE VAL R1; 
     108 [-]: CAPTURE REF R6; 
     109 [-]: CAPTURE VAL R17; 
     110 [-]: CAPTURE VAL R8; 
     111 [-]: CAPTURE VAL R2; 
     112 [-]: CAPTURE REF R7; 
     113 [-]: CAPTURE REF R13; 
     114 [-]: CAPTURE VAL R0; 
     115 [-]: CAPTURE REF R11; 
     116 [-]: CAPTURE REF R12; 
     117 [-]: CAPTURE VAL R19; 
     118 [-]: CAPTURE VAL R20; 
     119 [-]: CAPTURE VAL R18; 
     120 [-]: CAPTURE VAL R15; 
     121 [-]: SETGLOBAL R21 K29; "Initialize" = var21
     122 [-]: NEWCLOSURE R21 P10; 
     123 [-]: CAPTURE REF R12; 
     124 [-]: CAPTURE REF R11; 
     125 [-]: CAPTURE VAL R1; 
     126 [-]: CAPTURE REF R6; 
     127 [-]: CAPTURE REF R13; 
     128 [-]: SETGLOBAL R21 K30; "Update" = var21
     129 [-]: DUPCLOSURE R21 K31; 
     130 [-]: CAPTURE VAL R1; 
     131 [-]: SETGLOBAL R21 K32; "Shutdown" = var21
     132 [-]: DUPCLOSURE R21 K33; 
     133 [-]: CAPTURE VAL R18; 
     134 [-]: SETGLOBAL R21 K34; "onViewportSizeChanged" = var21
     135 [-]: NEWCLOSURE R21 P13; 
     136 [-]: CAPTURE REF R9; 
     137 [-]: CAPTURE REF R5; 
     138 [-]: SETGLOBAL R21 K35; "BlessingFocused" = var21
     139 [-]: NEWCLOSURE R21 P14; 
     140 [-]: CAPTURE REF R9; 
     141 [-]: SETGLOBAL R21 K36; "BlessingUnfocused" = var21
     142 [-]: NEWCLOSURE R21 P15; 
     143 [-]: CAPTURE REF R9; 
     144 [-]: CAPTURE REF R5; 
     145 [-]: SETGLOBAL R21 K37; "BlessingSelected" = var21
     146 [-]: NEWCLOSURE R21 P16; 
     147 [-]: CAPTURE REF R10; 
     148 [-]: SETGLOBAL R21 K38; "SetTrigger" = var21
     149 [-]: DUPCLOSURE R21 K39; 
     150 [-]: SETGLOBAL R21 K40; "SupportsThemes" = var21
     151 [-]: CLOSEUPVALS R5; 
     152 [-]: RETURN R0 0  ; 


; Name:            
; Defined at line: 39
; #Upvalues:       1
; #Parameters:     0
; Is_vararg:       0
; Max Stack Size:  1

       0 [-]: GETUPVAL R0 0; var0 = upvalues[0]
       1 [-]: RETURN R0 1  ; 


; Name:            
; Defined at line: 43
; #Upvalues:       5
; #Parameters:     0
; Is_vararg:       0
; Max Stack Size:  11

       0 [-]: GETIMPORT R0 1; var0 = 0xAE91E43B
       1 [-]: LOADK R2 K2  ; var2 = "Panel.MasteryIcon"
       2 [-]: LOADN R3 1   ; var3 = 1
       3 [-]: LOADN R4 -400; var4 = -400
       4 [-]: NAMECALL R0 R0 K3; var1 = var0; var0 = var0[0x67BC869F]
       5 [-]: CALL R0 5 1  ; var0(var1, var2, var3, var4)
       6 [-]: GETIMPORT R0 1; var0 = 0xAE91E43B
       7 [-]: LOADK R2 K4  ; var2 = "Panel.MasteryIcon.Banner.Fill"
       8 [-]: LOADN R3 13  ; var3 = 13
       9 [-]: LOADN R4 200 ; var4 = 200
      10 [-]: NAMECALL R0 R0 K3; var1 = var0; var0 = var0[0x67BC869F]
      11 [-]: CALL R0 5 1  ; var0(var1, var2, var3, var4)
      12 [-]: GETIMPORT R0 1; var0 = 0xAE91E43B
      13 [-]: LOADK R2 K5  ; var2 = "Panel.MasteryIcon.Banner.LinesFill"
      14 [-]: LOADN R3 13  ; var3 = 13
      15 [-]: LOADN R4 200 ; var4 = 200
      16 [-]: NAMECALL R0 R0 K3; var1 = var0; var0 = var0[0x67BC869F]
      17 [-]: CALL R0 5 1  ; var0(var1, var2, var3, var4)
      18 [-]: GETIMPORT R0 1; var0 = 0xAE91E43B
      19 [-]: LOADK R2 K6  ; var2 = "Panel.MasteryIcon.Banner.BgBottom"
      20 [-]: LOADN R3 1   ; var3 = 1
      21 [-]: LOADN R4 200 ; var4 = 200
      22 [-]: NAMECALL R0 R0 K3; var1 = var0; var0 = var0[0x67BC869F]
      23 [-]: CALL R0 5 1  ; var0(var1, var2, var3, var4)
      24 [-]: GETIMPORT R0 1; var0 = 0xAE91E43B
      25 [-]: LOADK R2 K7  ; var2 = "Panel.MasteryIcon.Banner.LinesBottom"
      26 [-]: LOADN R3 1   ; var3 = 1
      27 [-]: LOADN R4 200 ; var4 = 200
      28 [-]: NAMECALL R0 R0 K3; var1 = var0; var0 = var0[0x67BC869F]
      29 [-]: CALL R0 5 1  ; var0(var1, var2, var3, var4)
      30 [-]: GETIMPORT R0 1; var0 = 0xAE91E43B
      31 [-]: LOADK R2 K8  ; var2 = "Panel.MasteryIcon.Icon"
      32 [-]: LOADN R3 10  ; var3 = 10
      33 [-]: LOADN R4 0   ; var4 = 0
      34 [-]: NAMECALL R0 R0 K3; var1 = var0; var0 = var0[0x67BC869F]
      35 [-]: CALL R0 5 1  ; var0(var1, var2, var3, var4)
      36 [-]: GETIMPORT R0 1; var0 = 0xAE91E43B
      37 [-]: LOADK R2 K8  ; var2 = "Panel.MasteryIcon.Icon"
      38 [-]: LOADN R3 4   ; var3 = 4
      39 [-]: LOADN R4 -10000; var4 = -10000
      40 [-]: NAMECALL R0 R0 K3; var1 = var0; var0 = var0[0x67BC869F]
      41 [-]: CALL R0 5 1  ; var0(var1, var2, var3, var4)
      42 [-]: GETIMPORT R0 1; var0 = 0xAE91E43B
      43 [-]: LOADK R2 K9  ; var2 = "Panel.MasteryIcon.FlareTop"
      44 [-]: LOADN R3 10  ; var3 = 10
      45 [-]: LOADN R4 0   ; var4 = 0
      46 [-]: NAMECALL R0 R0 K3; var1 = var0; var0 = var0[0x67BC869F]
      47 [-]: CALL R0 5 1  ; var0(var1, var2, var3, var4)
      48 [-]: GETIMPORT R0 1; var0 = 0xAE91E43B
      49 [-]: LOADK R2 K10 ; var2 = "Panel.MasteryIcon.FlareBottom"
      50 [-]: LOADN R3 10  ; var3 = 10
      51 [-]: LOADN R4 0   ; var4 = 0
      52 [-]: NAMECALL R0 R0 K3; var1 = var0; var0 = var0[0x67BC869F]
      53 [-]: CALL R0 5 1  ; var0(var1, var2, var3, var4)
      54 [-]: GETIMPORT R0 1; var0 = 0xAE91E43B
      55 [-]: LOADK R2 K11 ; var2 = "Panel.MasteryIcon.Highlight"
      56 [-]: LOADN R3 10  ; var3 = 10
      57 [-]: LOADN R4 0   ; var4 = 0
      58 [-]: NAMECALL R0 R0 K3; var1 = var0; var0 = var0[0x67BC869F]
      59 [-]: CALL R0 5 1  ; var0(var1, var2, var3, var4)
      60 [-]: GETIMPORT R0 1; var0 = 0xAE91E43B
      61 [-]: LOADK R2 K12 ; var2 = "Panel.LinesLeft"
      62 [-]: LOADN R3 10  ; var3 = 10
      63 [-]: LOADN R4 0   ; var4 = 0
      64 [-]: NAMECALL R0 R0 K3; var1 = var0; var0 = var0[0x67BC869F]
      65 [-]: CALL R0 5 1  ; var0(var1, var2, var3, var4)
      66 [-]: GETIMPORT R0 1; var0 = 0xAE91E43B
      67 [-]: LOADK R2 K13 ; var2 = "Panel.LinesRight"
      68 [-]: LOADN R3 10  ; var3 = 10
      69 [-]: LOADN R4 0   ; var4 = 0
      70 [-]: NAMECALL R0 R0 K3; var1 = var0; var0 = var0[0x67BC869F]
      71 [-]: CALL R0 5 1  ; var0(var1, var2, var3, var4)
      72 [-]: NEWTABLE R0 0 5; var0 = {}
      73 [-]: LOADK R1 K14 ; var1 = "Panel.Timer"
      74 [-]: LOADK R2 K15 ; var2 = "Panel.Title"
      75 [-]: LOADK R3 K16 ; var3 = "Panel.Description"
      76 [-]: LOADK R4 K17 ; var4 = "Panel.GridSeparator"
      77 [-]: LOADK R5 K18 ; var5 = "Panel.Grid"
      78 [-]: SETLIST R0 R1 5 [1]; var0[1] = var1; var0[2] = var2; var0[3] = var3; var0[4] = var4; var0[5] = var5; var0[6] = var6; 
      79 [-]: GETIMPORT R1 20; var1 = 0xC8802016
      80 [-]: MOVE R2 R0   ; var2 = var0
      81 [-]: CALL R1 2 4  ; var1, var2, var3 = var1(var2)
      82 [-]: FORGPREP_INEXT R1 L1; 
L 0:  83 [-]: GETIMPORT R6 1; var6 = 0xAE91E43B
      84 [-]: MOVE R8 R5   ; var8 = var5
      85 [-]: LOADN R9 4   ; var9 = 4
      86 [-]: LOADN R10 10000; var10 = 10000
      87 [-]: NAMECALL R6 R6 K3; var7 = var6; var6 = var6[0x67BC869F]
      88 [-]: CALL R6 5 1  ; var6(var7, var8, var9, var10)
      89 [-]: GETIMPORT R6 1; var6 = 0xAE91E43B
      90 [-]: MOVE R8 R5   ; var8 = var5
      91 [-]: LOADN R9 10  ; var9 = 10
      92 [-]: LOADN R10 0  ; var10 = 0
      93 [-]: NAMECALL R6 R6 K3; var7 = var6; var6 = var6[0x67BC869F]
      94 [-]: CALL R6 5 1  ; var6(var7, var8, var9, var10)
L 1:  95 [-]: FORGLOOP R1 L0 2 [inext]; 
      96 [-]: GETIMPORT R2 22; var2 = 0xEE44E9D2
      97 [-]: FASTCALL1 64 R2 L2; 
      98 [-]: GETIMPORT R1 24; var1 = 0x7B998233
      99 [-]: CALL R1 2 2  ; var1 = var1(var2)
L 2: 100 [-]: JUMPIF R1 L3 ; goto L3 if var1
     101 [-]: GETUPVAL R2 0; var2 = upvalues[0]
     102 [-]: GETTABLEKS R1 R2 K25; var1 = var2[0x659D451F]
     103 [-]: GETIMPORT R2 22; var2 = 0xEE44E9D2
     104 [-]: CALL R1 2 1  ; var1(var2)
L 3: 105 [-]: GETUPVAL R1 1; var1 = upvalues[1]
     106 [-]: LOADK R3 K26 ; var3 = 0.34999999403953552
     107 [-]: NEWCLOSURE R4 P0; 
     108 [-]: CAPTURE UPVAL U0; 
     109 [-]: CAPTURE UPVAL U2; 
     110 [-]: CAPTURE VAL R0; 
     111 [-]: CAPTURE UPVAL U3; 
     112 [-]: CAPTURE UPVAL U4; 
     113 [-]: NAMECALL R1 R1 K27; var2 = var1; var1 = var1[0xBD2E96EA]
     114 [-]: CALL R1 4 1  ; var1(var2, var3, var4)
     115 [-]: RETURN R0 0  ; 


; Name:            
; Defined at line: 106
; #Upvalues:       2
; #Parameters:     0
; Is_vararg:       0
; Max Stack Size:  9

       0 [-]: GETIMPORT R0 1; var0 = 0x25312C9B
       1 [-]: GETIMPORT R1 3; var1 = 0xAE91E43B
       2 [-]: LOADK R2 K4  ; var2 = "_root"
       3 [-]: LOADN R3 2   ; var3 = 2
       4 [-]: NEWTABLE R4 0 2; var4 = {}
       5 [-]: LOADN R5 10  ; var5 = 10
       6 [-]: LOADN R6 4   ; var6 = 4
       7 [-]: SETLIST R4 R5 2 [1]; var4[1] = var5; var4[2] = var6; var4[3] = var7; 
       8 [-]: NEWTABLE R5 0 2; var5 = {}
       9 [-]: LOADN R6 0   ; var6 = 0
      10 [-]: LOADN R7 -15000; var7 = -15000
      11 [-]: SETLIST R5 R6 2 [1]; var5[1] = var6; var5[2] = var7; var5[3] = var8; 
      12 [-]: LOADK R6 K5  ; var6 = 0.25
      13 [-]: LOADN R7 0   ; var7 = 0
      14 [-]: NEWCLOSURE R8 P0; 
      15 [-]: CAPTURE UPVAL U0; 
      16 [-]: CALL R0 9 1  ; var0(var1, var2, var3, var4, var5, var6, var7, var8)
      17 [-]: GETIMPORT R1 7; var1 = 0x218E8D24
      18 [-]: FASTCALL1 64 R1 L0; 
      19 [-]: GETIMPORT R0 9; var0 = 0x7B998233
      20 [-]: CALL R0 2 2  ; var0 = var0(var1)
L 0:  21 [-]: JUMPIF R0 L1 ; goto L1 if var0
      22 [-]: GETUPVAL R1 1; var1 = upvalues[1]
      23 [-]: GETTABLEKS R0 R1 K10; var0 = var1[0x659D451F]
      24 [-]: GETIMPORT R1 7; var1 = 0x218E8D24
      25 [-]: CALL R0 2 1  ; var0(var1)
L 1:  26 [-]: RETURN R0 0  ; 


; Name:            
; Defined at line: 120
; #Upvalues:       1
; #Parameters:     0
; Is_vararg:       0
; Max Stack Size:  1

       0 [-]: GETUPVAL R0 0; var0 = upvalues[0]
       1 [-]: CALL R0 1 1  ; var0()
       2 [-]: RETURN R0 0  ; 


; Name:            
; Defined at line: 124
; #Upvalues:       0
; #Parameters:     0
; Is_vararg:       0
; Max Stack Size:  6

       0 [-]: NEWTABLE R0 0 0; var0 = {}
       1 [-]: DUPTABLE R3 3; 
       2 [-]: LOADK R4 K4  ; var4 = "/Lotus/Language/Menu/NavBar_Cancel"
       3 [-]: SETTABLEKS R4 R3 K0; var4["Label"] = var3
       4 [-]: DUPCLOSURE R4 K5; 
       5 [-]: SETTABLEKS R4 R3 K1; var4["CallBack"] = var3
       6 [-]: LOADK R4 K6  ; var4 = "MENU_CANCEL"
       7 [-]: SETTABLEKS R4 R3 K2; var4["CallOut"] = var3
       8 [-]: FASTCALL2 52 R0 R3 L0; 
       9 [-]: MOVE R2 R0   ; var2 = var0
      10 [-]: GETIMPORT R1 9; var1 = 0x33BDD652[0x23D5322F]
      11 [-]: CALL R1 3 1  ; var1(var2, var3)
L 0:  12 [-]: GETIMPORT R2 12; var2 = _T["SetButtons"]
      13 [-]: FASTCALL1 64 R2 L1; 
      14 [-]: GETIMPORT R1 14; var1 = 0x7B998233
      15 [-]: CALL R1 2 2  ; var1 = var1(var2)
L 1:  16 [-]: JUMPIF R1 L2 ; goto L2 if var1
      17 [-]: GETIMPORT R1 12; var1 = _T["SetButtons"]
      18 [-]: GETIMPORT R2 16; var2 = 0xAE91E43B
      19 [-]: MOVE R3 R0   ; var3 = var0
      20 [-]: GETIMPORT R4 18; var4 = 0xCD0165A3
      21 [-]: LOADN R5 1   ; var5 = 1
      22 [-]: CALL R4 2 0  ; var4, ... = var4(var5)
      23 [-]: CALL R1 0 1  ; var1(var2, ...)
L 2:  24 [-]: RETURN R0 0  ; 


; Name:            
; Defined at line: 134
; #Upvalues:       3
; #Parameters:     0
; Is_vararg:       0
; Max Stack Size:  16

       0 [-]: GETUPVAL R1 0; var1 = upvalues[0]
       1 [-]: FASTCALL1 64 R1 L0; 
       2 [-]: GETIMPORT R0 1; var0 = 0x7B998233
       3 [-]: CALL R0 2 2  ; var0 = var0(var1)
L 0:   4 [-]: JUMPIF R0 L1 ; goto L1 if var0
       5 [-]: GETUPVAL R0 0; var0 = upvalues[0]
       6 [-]: GETIMPORT R2 3; var2 = 0xAE91E43B
       7 [-]: NAMECALL R2 R2 K4; var3 = var2; var2 = var2[0x6B837788]
       8 [-]: CALL R2 2 2  ; var2 = var2(var3)
       9 [-]: GETIMPORT R3 3; var3 = 0xAE91E43B
      10 [-]: NAMECALL R3 R3 K5; var4 = var3; var3 = var3[0xAF9FDA9F]
      11 [-]: CALL R3 2 0  ; var3, ... = var3(var4)
      12 [-]: NAMECALL R0 R0 K6; var1 = var0; var0 = var0[0xFAA69527]
      13 [-]: CALL R0 0 1  ; var0(var1, ...)
L 1:  14 [-]: LOADNIL R0   ; var0 = nil
      15 [-]: LOADNIL R1   ; var1 = nil
      16 [-]: GETUPVAL R3 1; var3 = upvalues[1]
      17 [-]: GETTABLEKS R2 R3 K7; var2 = var3[0x0DB7934D]
      18 [-]: GETIMPORT R3 3; var3 = 0xAE91E43B
      19 [-]: LOADN R4 5   ; var4 = 5
      20 [-]: CALL R2 3 2  ; var2 = var2(var3, var4)
      21 [-]: GETUPVAL R4 2; var4 = upvalues[2]
      22 [-]: FASTCALL1 64 R4 L2; 
      23 [-]: GETIMPORT R3 1; var3 = 0x7B998233
      24 [-]: CALL R3 2 2  ; var3 = var3(var4)
L 2:  25 [-]: JUMPIF R3 L5 ; goto L5 if var3
      26 [-]: GETUPVAL R4 1; var4 = upvalues[1]
      27 [-]: GETTABLEKS R3 R4 K8; var3 = var4[0xB5BE5D4A]
      28 [-]: GETIMPORT R4 3; var4 = 0xAE91E43B
      29 [-]: LOADK R5 K9  ; var5 = "Panel.Grid"
      30 [-]: CALL R3 3 3  ; var3, var4 = var3(var4, var5)
      31 [-]: GETUPVAL R8 2; var8 = upvalues[2]
      32 [-]: GETTABLEKS R7 R8 K11; var7 = var8["mRows"]
      33 [-]: GETUPVAL R9 2; var9 = upvalues[2]
      34 [-]: GETTABLEKS R8 R9 K12; var8 = var9["mRowSeparation"]
      35 [-]: MUL R6 R7 R8 ; var6 = var7 * var8
      36 [-]: SUBK R5 R6 K10; var5 = var6 - 6
      37 [-]: GETUPVAL R7 1; var7 = upvalues[1]
      38 [-]: GETTABLEKS R6 R7 K13; var6 = var7[0xE5E5A417]
      39 [-]: GETIMPORT R7 3; var7 = 0xAE91E43B
      40 [-]: SUBK R9 R4 K14; var9 = var4 - 3
           42 [-]: ADD R8 R9 R10; var8 = var9 + var10
      43 [-]: CALL R6 3 2  ; var6 = var6(var7, var8)
      44 [-]: MOVE R0 R6   ; var0 = var6
      45 [-]: GETUPVAL R7 1; var7 = upvalues[1]
      46 [-]: GETTABLEKS R6 R7 K16; var6 = var7[0xD718F59B]
      47 [-]: GETIMPORT R7 3; var7 = 0xAE91E43B
      48 [-]: MOVE R8 R5   ; var8 = var5
      49 [-]: CALL R6 3 2  ; var6 = var6(var7, var8)
      50 [-]: MOVE R1 R6   ; var1 = var6
      51 [-]: NEWTABLE R6 0 3; var6 = {}
      52 [-]: GETIMPORT R7 18; var7 = 0x0F20C9BD
      53 [-]: GETIMPORT R8 20; var8 = 0x5B54EC72
      54 [-]: GETIMPORT R9 22; var9 = 0x09B6DACC
      55 [-]: SETLIST R6 R7 3 [1]; var6[1] = var7; var6[2] = var8; var6[3] = var9; var6[4] = var10; 
      56 [-]: GETIMPORT R7 24; var7 = 0xCFC01047
      57 [-]: MOVE R8 R6   ; var8 = var6
      58 [-]: CALL R7 2 4  ; var7, var8, var9 = var7(var8)
      59 [-]: FORGPREP_NEXT R7 L4; 
L 3:  60 [-]: GETIMPORT R14 27; var14 = 0x6C97A788["VISIBILITY_CENTER"]
      61 [-]: MOVE R15 R0  ; var15 = var0
      62 [-]: NAMECALL R12 R11 K28; var13 = var11; var12 = var11[0x830EEA67]
      63 [-]: CALL R12 4 1 ; var12(var13, var14, var15)
      64 [-]: GETIMPORT R14 30; var14 = 0x6C97A788["VISIBILITY_SIZE"]
      65 [-]: MOVE R15 R1  ; var15 = var1
      66 [-]: NAMECALL R12 R11 K28; var13 = var11; var12 = var11[0x830EEA67]
      67 [-]: CALL R12 4 1 ; var12(var13, var14, var15)
      68 [-]: GETIMPORT R14 32; var14 = 0x6C97A788["VISIBILITY_FADE_SIZE"]
      69 [-]: MOVE R15 R2  ; var15 = var2
      70 [-]: NAMECALL R12 R11 K28; var13 = var11; var12 = var11[0x830EEA67]
      71 [-]: CALL R12 4 1 ; var12(var13, var14, var15)
L 4:  72 [-]: FORGLOOP R7 L3 2; 
L 5:  73 [-]: RETURN R0 0  ; 


; Name:            
; Defined at line: 157
; #Upvalues:       3
; #Parameters:     1
; Is_vararg:       0
; Max Stack Size:  6

       0 [-]: GETIMPORT R1 1; var1 = 0x3D106989
       1 [-]: LOADK R3 K2  ; var3 = "OnBlessingConfirmed "
       2 [-]: FASTCALL1 63 R0 L0; 
       3 [-]: MOVE R5 R0   ; var5 = var0
       4 [-]: GETIMPORT R4 4; var4 = 0x64FB1586
       5 [-]: CALL R4 2 2  ; var4 = var4(var5)
L 0:   6 [-]: CONCAT R2 R3 R4; var2 = var3 .. var4
       7 [-]: CALL R1 2 1  ; var1(var2)
       8 [-]: FASTCALL1 62 R0 L1; 
       9 [-]: MOVE R2 R0   ; var2 = var0
      10 [-]: GETIMPORT R1 6; var1 = 0x03F57322
      11 [-]: CALL R1 2 2  ; var1 = var1(var2)
L 1:  12 [-]: LOADN R2 4   ; var2 = 4
      13 [-]: JUMPIFNOTEQ R1 R2 L4; goto L4 if var1 ~= var590369
      14 [-]: GETIMPORT R2 9; var2 = _T["SendHubBlessing"]
      15 [-]: FASTCALL1 64 R2 L2; 
      16 [-]: GETIMPORT R1 11; var1 = 0x7B998233
      17 [-]: CALL R1 2 2  ; var1 = var1(var2)
L 2:  18 [-]: JUMPIF R1 L3 ; goto L3 if var1
      19 [-]: GETUPVAL R2 0; var2 = upvalues[0]
      20 [-]: GETTABLEKS R1 R2 K12; var1 = var2["mSelectedElement"]
      21 [-]: GETIMPORT R2 9; var2 = _T["SendHubBlessing"]
      22 [-]: GETTABLEKS R3 R1 K13; var3 = var1["Blessing"]
      23 [-]: CALL R2 2 1  ; var2(var3)
      24 [-]: GETUPVAL R2 1; var2 = upvalues[1]
      25 [-]: CALL R2 1 1  ; var2()
      26 [-]: RETURN R0 0  ; 
L 3:  27 [-]: GETUPVAL R2 2; var2 = upvalues[2]
      28 [-]: GETTABLEKS R1 R2 K14; var1 = var2[0xA53F5E12]
      29 [-]: LOADK R2 K15 ; var2 = "[HC] SendHubBlessing doesn't exist!"
      30 [-]: CALL R1 2 1  ; var1(var2)
L 4:  31 [-]: RETURN R0 0  ; 


; Name:            
; Defined at line: 171
; #Upvalues:       7
; #Parameters:     0
; Is_vararg:       0
; Max Stack Size:  7

       0 [-]: GETIMPORT R0 1; var0 = 0x2D0FAD09
       1 [-]: LOADK R1 K2  ; var1 = "EE.Interface.Components.Grid"
       2 [-]: CALL R0 2 2  ; var0 = var0(var1)
       3 [-]: GETTABLEKS R1 R0 K3; var1 = var0[0xDA0C93A2]
       4 [-]: GETIMPORT R2 5; var2 = 0xAE91E43B
       5 [-]: LOADK R3 K6  ; var3 = "Panel.Grid.Element"
       6 [-]: LOADNIL R4   ; var4 = nil
       7 [-]: LOADN R5 6   ; var5 = 6
       8 [-]: LOADN R6 1   ; var6 = 1
       9 [-]: CALL R1 6 2  ; var1 = var1(var2, var3, var4, var5, var6)
      10 [-]: SETUPVAL R1 0; upvalues[1] = var0
      11 [-]: GETUPVAL R1 0; var1 = upvalues[0]
      12 [-]: LOADK R3 K7  ; var3 = "BlessingSelected"
      13 [-]: LOADK R4 K8  ; var4 = "BlessingFocused"
      14 [-]: LOADK R5 K9  ; var5 = "BlessingUnfocused"
      15 [-]: NAMECALL R1 R1 K10; var2 = var1; var1 = var1[0x1E5B5CFE]
      16 [-]: CALL R1 5 1  ; var1(var2, var3, var4, var5)
      17 [-]: GETUPVAL R1 0; var1 = upvalues[0]
      18 [-]: LOADN R2 34  ; var2 = 34
      19 [-]: SETTABLEKS R2 R1 K11; var2["ElementDimBuffer"] = var1
      20 [-]: GETUPVAL R1 0; var1 = upvalues[0]
      21 [-]: LOADN R2 173 ; var2 = 173
      22 [-]: SETTABLEKS R2 R1 K12; var2["ElementWidth"] = var1
      23 [-]: GETUPVAL R1 0; var1 = upvalues[0]
      24 [-]: LOADN R2 173 ; var2 = 173
      25 [-]: SETTABLEKS R2 R1 K13; var2["ElementHeight"] = var1
      26 [-]: GETUPVAL R1 0; var1 = upvalues[0]
      27 [-]: LOADN R2 1300; var2 = 1300
      28 [-]: SETTABLEKS R2 R1 K14; var2["Width"] = var1
      29 [-]: GETUPVAL R1 0; var1 = upvalues[0]
      30 [-]: LOADN R2 100 ; var2 = 100
      31 [-]: SETTABLEKS R2 R1 K15; var2["mSelectedScale"] = var1
      32 [-]: GETUPVAL R1 0; var1 = upvalues[0]
      33 [-]: LOADK R3 K16 ; var3 = "Panel.Grid.ScrollBar"
      34 [-]: LOADN R4 0   ; var4 = 0
      35 [-]: NAMECALL R1 R1 K17; var2 = var1; var1 = var1[0x3BC79F4F]
      36 [-]: CALL R1 4 1  ; var1(var2, var3, var4)
      37 [-]: GETUPVAL R1 0; var1 = upvalues[0]
      38 [-]: NAMECALL R1 R1 K18; var2 = var1; var1 = var1[0x7220ACB6]
      39 [-]: CALL R1 2 1  ; var1(var2)
      40 [-]: GETUPVAL R1 0; var1 = upvalues[0]
      41 [-]: GETIMPORT R2 20; var2 = 0x5B54EC72
      42 [-]: SETTABLEKS R2 R1 K21; var2["RectangleVisibleRangeMaterial"] = var1
      43 [-]: GETUPVAL R1 0; var1 = upvalues[0]
      44 [-]: GETIMPORT R2 23; var2 = 0x0F20C9BD
      45 [-]: SETTABLEKS R2 R1 K24; var2["VisibleRangeMaterial"] = var1
      46 [-]: GETUPVAL R1 0; var1 = upvalues[0]
      47 [-]: GETIMPORT R2 26; var2 = 0x09B6DACC
      48 [-]: SETTABLEKS R2 R1 K27; var2["TextVisibleRangeMaterial"] = var1
      49 [-]: GETUPVAL R2 1; var2 = upvalues[1]
      50 [-]: GETTABLEKS R1 R2 K28; var1 = var2[0x27658FAB]
      51 [-]: GETIMPORT R2 5; var2 = 0xAE91E43B
      52 [-]: GETUPVAL R3 0; var3 = upvalues[0]
      53 [-]: CALL R1 3 1  ; var1(var2, var3)
      54 [-]: GETUPVAL R1 0; var1 = upvalues[0]
      55 [-]: NEWCLOSURE R2 P0; 
      56 [-]: CAPTURE UPVAL U1; 
      57 [-]: CAPTURE UPVAL U0; 
      58 [-]: SETTABLEKS R2 R1 K29; var2["mClipCreatedCallback"] = var1
      59 [-]: GETUPVAL R1 0; var1 = upvalues[0]
      60 [-]: NEWCLOSURE R2 P1; 
      61 [-]: CAPTURE UPVAL U1; 
      62 [-]: CAPTURE UPVAL U0; 
      63 [-]: SETTABLEKS R2 R1 K30; var2["mOnFocusedCallback"] = var1
      64 [-]: GETUPVAL R1 0; var1 = upvalues[0]
      65 [-]: NEWCLOSURE R2 P2; 
      66 [-]: CAPTURE UPVAL U1; 
      67 [-]: CAPTURE UPVAL U0; 
      68 [-]: SETTABLEKS R2 R1 K31; var2["mOnUnfocusedCallback"] = var1
      69 [-]: GETUPVAL R1 0; var1 = upvalues[0]
      70 [-]: NEWCLOSURE R2 P3; 
      71 [-]: CAPTURE UPVAL U0; 
      72 [-]: CAPTURE UPVAL U1; 
      73 [-]: SETTABLEKS R2 R1 K32; var2["mElementDrawCallback"] = var1
      74 [-]: GETUPVAL R1 0; var1 = upvalues[0]
      75 [-]: NEWCLOSURE R2 P4; 
      76 [-]: CAPTURE UPVAL U2; 
      77 [-]: CAPTURE UPVAL U3; 
      78 [-]: CAPTURE UPVAL U4; 
      79 [-]: CAPTURE UPVAL U5; 
      80 [-]: CAPTURE UPVAL U6; 
      81 [-]: SETTABLEKS R2 R1 K33; var2["mOnSelectedCallback"] = var1
      82 [-]: RETURN R0 0  ; 


; Name:            
; Defined at line: 236
; #Upvalues:       3
; #Parameters:     0
; Is_vararg:       0
; Max Stack Size:  10

       0 [-]: GETUPVAL R0 0; var0 = upvalues[0]
       1 [-]: LOADB R2 1   ; var2 = true
       2 [-]: LOADB R3 1   ; var3 = true
       3 [-]: NAMECALL R0 R0 K0; var1 = var0; var0 = var0[0x7C09C373]
       4 [-]: CALL R0 4 1  ; var0(var1, var2, var3)
       5 [-]: LOADN R2 1   ; var2 = 1
       6 [-]: GETUPVAL R3 1; var3 = upvalues[1]
       7 [-]: LENGTH R0 R3 ; var0 = #var3
       8 [-]: LOADN R1 1   ; var1 = 1
       9 [-]: FORNPREP R0 L1; nforprep start - [escape at L1] -- var0 = iterator
L 0:  10 [-]: GETUPVAL R4 2; var4 = upvalues[2]
      11 [-]: GETTABLEKS R3 R4 K1; var3 = var4[0x08681F50]
      12 [-]: GETIMPORT R4 3; var4 = 0xAE91E43B
      13 [-]: GETUPVAL R7 1; var7 = upvalues[1]
      14 [-]: GETTABLE R6 R7 R2; var6 = var7[var2]
      15 [-]: GETTABLEKS R5 R6 K4; var5 = var6["StoreItem"]
      16 [-]: LOADNIL R6   ; var6 = nil
      17 [-]: LOADNIL R7   ; var7 = nil
      18 [-]: LOADNIL R8   ; var8 = nil
      19 [-]: LOADB R9 1   ; var9 = true
      20 [-]: CALL R3 7 2  ; var3 = var3(var4, var5, var6, var7, var8, var9)
      21 [-]: GETUPVAL R6 1; var6 = upvalues[1]
      22 [-]: GETTABLE R5 R6 R2; var5 = var6[var2]
      23 [-]: GETTABLEKS R4 R5 K5; var4 = var5["Tag"]
      24 [-]: SETTABLEKS R4 R3 K6; var4["Blessing"] = var3
      25 [-]: GETUPVAL R4 0; var4 = upvalues[0]
      26 [-]: MOVE R6 R3   ; var6 = var3
      27 [-]: LOADB R7 1   ; var7 = true
      28 [-]: NAMECALL R4 R4 K7; var5 = var4; var4 = var4[0xBAD4316F]
      29 [-]: CALL R4 4 1  ; var4(var5, var6, var7)
      30 [-]: FORNLOOP R0 L0; nforloop end - iterate + goto L0
L 1:  31 [-]: GETUPVAL R0 0; var0 = upvalues[0]
      32 [-]: NAMECALL R0 R0 K8; var1 = var0; var0 = var0[0x71E9AC81]
      33 [-]: CALL R0 2 1  ; var0(var1)
      34 [-]: RETURN R0 0  ; 


; Name:            
; Defined at line: 249
; #Upvalues:       14
; #Parameters:     0
; Is_vararg:       0
; Max Stack Size:  10

       0 [-]: GETIMPORT R1 2; var1 = _T["ShowBackground"]
       1 [-]: FASTCALL1 64 R1 L0; 
       2 [-]: GETIMPORT R0 4; var0 = 0x7B998233
       3 [-]: CALL R0 2 2  ; var0 = var0(var1)
L 0:   4 [-]: JUMPIF R0 L1 ; goto L1 if var0
       5 [-]: GETIMPORT R0 2; var0 = _T["ShowBackground"]
       6 [-]: LOADK R1 K5  ; var1 = 0.20000000298023224
       7 [-]: CALL R0 2 1  ; var0(var1)
L 1:   8 [-]: GETUPVAL R1 0; var1 = upvalues[0]
       9 [-]: GETTABLEKS R0 R1 K6; var0 = var1[0x9E3D3434]
      10 [-]: LOADB R1 1   ; var1 = true
      11 [-]: CALL R0 2 1  ; var0(var1)
      12 [-]: GETIMPORT R0 8; var0 = 0x2D0FAD09
      13 [-]: LOADK R1 K9  ; var1 = "Lotus.Interface.Libs.TimerMgr"
      14 [-]: CALL R0 2 2  ; var0 = var0(var1)
      15 [-]: GETTABLEKS R1 R0 K10; var1 = var0[0xDE474187]
      16 [-]: CALL R1 1 2  ; var1 = var1()
      17 [-]: SETUPVAL R1 1; upvalues[1] = var1
      18 [-]: GETUPVAL R1 2; var1 = upvalues[2]
      19 [-]: CALL R1 1 1  ; var1()
      20 [-]: GETUPVAL R1 3; var1 = upvalues[3]
      21 [-]: GETUPVAL R3 4; var3 = upvalues[4]
      22 [-]: GETTABLEKS R2 R3 K11; var2 = var3[0x5D10207D]
      23 [-]: LOADN R3 9   ; var3 = 9
      24 [-]: LOADB R4 1   ; var4 = true
      25 [-]: CALL R2 3 2  ; var2 = var2(var3, var4)
      26 [-]: SETTABLEKS R2 R1 K12; var2["FloatingContent"] = var1
      27 [-]: GETUPVAL R1 3; var1 = upvalues[3]
      28 [-]: GETUPVAL R3 4; var3 = upvalues[4]
      29 [-]: GETTABLEKS R2 R3 K11; var2 = var3[0x5D10207D]
      30 [-]: LOADN R3 10  ; var3 = 10
      31 [-]: LOADB R4 1   ; var4 = true
      32 [-]: CALL R2 3 2  ; var2 = var2(var3, var4)
      33 [-]: SETTABLEKS R2 R1 K13; var2["FloatingContentHighlight"] = var1
      34 [-]: GETUPVAL R1 3; var1 = upvalues[3]
      35 [-]: GETUPVAL R3 4; var3 = upvalues[4]
      36 [-]: GETTABLEKS R2 R3 K11; var2 = var3[0x5D10207D]
      37 [-]: LOADN R3 6   ; var3 = 6
      38 [-]: LOADB R4 1   ; var4 = true
      39 [-]: CALL R2 3 2  ; var2 = var2(var3, var4)
      40 [-]: SETTABLEKS R2 R1 K14; var2["Content"] = var1
      41 [-]: GETUPVAL R1 3; var1 = upvalues[3]
      42 [-]: GETUPVAL R3 4; var3 = upvalues[4]
      43 [-]: GETTABLEKS R2 R3 K11; var2 = var3[0x5D10207D]
      44 [-]: LOADN R3 2   ; var3 = 2
      45 [-]: LOADB R4 1   ; var4 = true
      46 [-]: CALL R2 3 2  ; var2 = var2(var3, var4)
      47 [-]: SETTABLEKS R2 R1 K15; var2["Background1"] = var1
      48 [-]: GETIMPORT R1 8; var1 = 0x2D0FAD09
      49 [-]: LOADK R2 K16 ; var2 = "EE.Interface.AnchorMgr"
      50 [-]: CALL R1 2 2  ; var1 = var1(var2)
      51 [-]: GETTABLEKS R2 R1 K17; var2 = var1[0xAE6791BA]
      52 [-]: GETIMPORT R3 19; var3 = 0xAE91E43B
      53 [-]: CALL R2 2 2  ; var2 = var2(var3)
      54 [-]: SETUPVAL R2 5; upvalues[2] = var5
      55 [-]: GETUPVAL R2 5; var2 = upvalues[5]
      56 [-]: GETIMPORT R4 19; var4 = 0xAE91E43B
      57 [-]: LOADK R5 K20 ; var5 = "Panel"
      58 [-]: NEWTABLE R6 0 2; var6 = {}
      59 [-]: GETUPVAL R8 5; var8 = upvalues[5]
      60 [-]: GETTABLEKS R7 R8 K21; var7 = var8["ANCHOR_V_TOP"]
      61 [-]: GETUPVAL R9 5; var9 = upvalues[5]
      62 [-]: GETTABLEKS R8 R9 K22; var8 = var9["ANCHOR_H_CENTRE"]
      63 [-]: SETLIST R6 R7 2 [1]; var6[1] = var7; var6[2] = var8; var6[3] = var9; 
      64 [-]: NAMECALL R2 R2 K23; var3 = var2; var2 = var2[0x20FF29F7]
      65 [-]: CALL R2 5 1  ; var2(var3, var4, var5, var6)
      66 [-]: GETIMPORT R2 8; var2 = 0x2D0FAD09
      67 [-]: LOADK R3 K24 ; var3 = "Lotus.Interface.Components.MasteryIcon"
      68 [-]: CALL R2 2 2  ; var2 = var2(var3)
      69 [-]: GETTABLEKS R3 R2 K17; var3 = var2[0xAE6791BA]
      70 [-]: GETIMPORT R4 19; var4 = 0xAE91E43B
      71 [-]: LOADK R5 K25 ; var5 = "Panel.MasteryIcon.Icon.Icon"
      72 [-]: LOADN R6 30  ; var6 = 30
      73 [-]: CALL R3 4 2  ; var3 = var3(var4, var5, var6)
      74 [-]: SETUPVAL R3 6; upvalues[3] = var6
      75 [-]: GETIMPORT R3 19; var3 = 0xAE91E43B
      76 [-]: LOADK R5 K26 ; var5 = "Panel.MasteryIcon.Icon.RankBg"
      77 [-]: GETIMPORT R6 28; var6 = 0x1ED92580
      78 [-]: NAMECALL R3 R3 K29; var4 = var3; var3 = var3[0x1CB415C1]
      79 [-]: CALL R3 4 1  ; var3(var4, var5, var6)
      80 [-]: GETIMPORT R3 19; var3 = 0xAE91E43B
      81 [-]: LOADK R5 K26 ; var5 = "Panel.MasteryIcon.Icon.RankBg"
      82 [-]: LOADN R6 9   ; var6 = 9
      83 [-]: GETIMPORT R8 31; var8 = 0x0032441C
      84 [-]: GETTABLEKS R7 R8 K32; var7 = var8["UIColor_Black"]
      85 [-]: NAMECALL R3 R3 K33; var4 = var3; var3 = var3[0x67BC869F]
      86 [-]: CALL R3 5 1  ; var3(var4, var5, var6, var7)
      87 [-]: GETIMPORT R3 19; var3 = 0xAE91E43B
      88 [-]: LOADK R5 K26 ; var5 = "Panel.MasteryIcon.Icon.RankBg"
      89 [-]: LOADN R6 10  ; var6 = 10
      90 [-]: LOADN R7 30  ; var7 = 30
      91 [-]: NAMECALL R3 R3 K33; var4 = var3; var3 = var3[0x67BC869F]
      92 [-]: CALL R3 5 1  ; var3(var4, var5, var6, var7)
      93 [-]: GETIMPORT R3 19; var3 = 0xAE91E43B
      94 [-]: LOADK R5 K34 ; var5 = "Panel.MasteryIcon.Icon.Rank"
      95 [-]: LOADN R6 31  ; var6 = 31
      96 [-]: GETUPVAL R8 7; var8 = upvalues[7]
      97 [-]: GETTABLEKS R7 R8 K35; var7 = var8[0x1142C7A8]
      98 [-]: LOADN R8 30  ; var8 = 30
      99 [-]: CALL R7 2 0  ; var7, ... = var7(var8)
     100 [-]: NAMECALL R3 R3 K36; var4 = var3; var3 = var3[0x5F56EEAB]
     101 [-]: CALL R3 0 1  ; var3(var4, ...)
     102 [-]: GETIMPORT R3 19; var3 = 0xAE91E43B
     103 [-]: LOADK R5 K37 ; var5 = "Panel.MasteryIcon.FlareTop"
     104 [-]: GETIMPORT R6 39; var6 = 0x193FB0B3
     105 [-]: NAMECALL R3 R3 K40; var4 = var3; var3 = var3[0xD5181643]
     106 [-]: CALL R3 4 1  ; var3(var4, var5, var6)
     107 [-]: GETIMPORT R3 19; var3 = 0xAE91E43B
     108 [-]: LOADK R5 K41 ; var5 = "Panel.MasteryIcon.FlareBottom"
     109 [-]: GETIMPORT R6 39; var6 = 0x193FB0B3
     110 [-]: NAMECALL R3 R3 K40; var4 = var3; var3 = var3[0xD5181643]
     111 [-]: CALL R3 4 1  ; var3(var4, var5, var6)
     112 [-]: GETIMPORT R3 19; var3 = 0xAE91E43B
     113 [-]: LOADK R5 K37 ; var5 = "Panel.MasteryIcon.FlareTop"
     114 [-]: LOADN R6 9   ; var6 = 9
     115 [-]: GETUPVAL R8 3; var8 = upvalues[3]
     116 [-]: GETTABLEKS R7 R8 K12; var7 = var8["FloatingContent"]
     117 [-]: NAMECALL R3 R3 K33; var4 = var3; var3 = var3[0x67BC869F]
     118 [-]: CALL R3 5 1  ; var3(var4, var5, var6, var7)
     119 [-]: GETIMPORT R3 19; var3 = 0xAE91E43B
     120 [-]: LOADK R5 K41 ; var5 = "Panel.MasteryIcon.FlareBottom"
     121 [-]: LOADN R6 9   ; var6 = 9
     122 [-]: GETUPVAL R8 3; var8 = upvalues[3]
     123 [-]: GETTABLEKS R7 R8 K12; var7 = var8["FloatingContent"]
     124 [-]: NAMECALL R3 R3 K33; var4 = var3; var3 = var3[0x67BC869F]
     125 [-]: CALL R3 5 1  ; var3(var4, var5, var6, var7)
     126 [-]: GETIMPORT R3 19; var3 = 0xAE91E43B
     127 [-]: LOADK R5 K42 ; var5 = "Panel.MasteryIcon.Banner.LinesFill"
     128 [-]: GETIMPORT R7 31; var7 = 0x0032441C
     129 [-]: GETTABLEKS R6 R7 K43; var6 = var7["UIMaterial_VitruvianLines"]
     130 [-]: NAMECALL R3 R3 K40; var4 = var3; var3 = var3[0xD5181643]
     131 [-]: CALL R3 4 1  ; var3(var4, var5, var6)
     132 [-]: GETIMPORT R3 19; var3 = 0xAE91E43B
     133 [-]: LOADK R5 K44 ; var5 = "Panel.MasteryIcon.Banner.LinesBottom"
     134 [-]: GETIMPORT R7 31; var7 = 0x0032441C
     135 [-]: GETTABLEKS R6 R7 K43; var6 = var7["UIMaterial_VitruvianLines"]
     136 [-]: NAMECALL R3 R3 K40; var4 = var3; var3 = var3[0xD5181643]
     137 [-]: CALL R3 4 1  ; var3(var4, var5, var6)
     138 [-]: GETIMPORT R3 19; var3 = 0xAE91E43B
     139 [-]: LOADK R5 K42 ; var5 = "Panel.MasteryIcon.Banner.LinesFill"
     140 [-]: LOADN R6 9   ; var6 = 9
     141 [-]: GETUPVAL R8 3; var8 = upvalues[3]
     142 [-]: GETTABLEKS R7 R8 K12; var7 = var8["FloatingContent"]
     143 [-]: NAMECALL R3 R3 K33; var4 = var3; var3 = var3[0x67BC869F]
     144 [-]: CALL R3 5 1  ; var3(var4, var5, var6, var7)
     145 [-]: GETIMPORT R3 19; var3 = 0xAE91E43B
     146 [-]: LOADK R5 K44 ; var5 = "Panel.MasteryIcon.Banner.LinesBottom"
     147 [-]: LOADN R6 9   ; var6 = 9
     148 [-]: GETUPVAL R8 3; var8 = upvalues[3]
     149 [-]: GETTABLEKS R7 R8 K12; var7 = var8["FloatingContent"]
     150 [-]: NAMECALL R3 R3 K33; var4 = var3; var3 = var3[0x67BC869F]
     151 [-]: CALL R3 5 1  ; var3(var4, var5, var6, var7)
     152 [-]: GETIMPORT R3 19; var3 = 0xAE91E43B
     153 [-]: LOADK R5 K45 ; var5 = "Panel.LineLeftCap"
     154 [-]: GETIMPORT R7 31; var7 = 0x0032441C
     155 [-]: GETTABLEKS R6 R7 K43; var6 = var7["UIMaterial_VitruvianLines"]
     156 [-]: NAMECALL R3 R3 K40; var4 = var3; var3 = var3[0xD5181643]
     157 [-]: CALL R3 4 1  ; var3(var4, var5, var6)
     158 [-]: GETIMPORT R3 19; var3 = 0xAE91E43B
     159 [-]: LOADK R5 K46 ; var5 = "Panel.LineLeftFill"
     160 [-]: GETIMPORT R7 31; var7 = 0x0032441C
     161 [-]: GETTABLEKS R6 R7 K43; var6 = var7["UIMaterial_VitruvianLines"]
     162 [-]: NAMECALL R3 R3 K40; var4 = var3; var3 = var3[0xD5181643]
     163 [-]: CALL R3 4 1  ; var3(var4, var5, var6)
     164 [-]: GETIMPORT R3 19; var3 = 0xAE91E43B
     165 [-]: LOADK R5 K47 ; var5 = "Panel.LineRightCap"
     166 [-]: GETIMPORT R7 31; var7 = 0x0032441C
     167 [-]: GETTABLEKS R6 R7 K43; var6 = var7["UIMaterial_VitruvianLines"]
     168 [-]: NAMECALL R3 R3 K40; var4 = var3; var3 = var3[0xD5181643]
     169 [-]: CALL R3 4 1  ; var3(var4, var5, var6)
     170 [-]: GETIMPORT R3 19; var3 = 0xAE91E43B
     171 [-]: LOADK R5 K48 ; var5 = "Panel.LineRightFill"
     172 [-]: GETIMPORT R7 31; var7 = 0x0032441C
     173 [-]: GETTABLEKS R6 R7 K43; var6 = var7["UIMaterial_VitruvianLines"]
     174 [-]: NAMECALL R3 R3 K40; var4 = var3; var3 = var3[0xD5181643]
     175 [-]: CALL R3 4 1  ; var3(var4, var5, var6)
     176 [-]: GETIMPORT R3 19; var3 = 0xAE91E43B
     177 [-]: LOADK R5 K45 ; var5 = "Panel.LineLeftCap"
     178 [-]: LOADN R6 9   ; var6 = 9
     179 [-]: GETUPVAL R8 3; var8 = upvalues[3]
     180 [-]: GETTABLEKS R7 R8 K12; var7 = var8["FloatingContent"]
     181 [-]: NAMECALL R3 R3 K33; var4 = var3; var3 = var3[0x67BC869F]
     182 [-]: CALL R3 5 1  ; var3(var4, var5, var6, var7)
     183 [-]: GETIMPORT R3 19; var3 = 0xAE91E43B
     184 [-]: LOADK R5 K46 ; var5 = "Panel.LineLeftFill"
     185 [-]: LOADN R6 9   ; var6 = 9
     186 [-]: GETUPVAL R8 3; var8 = upvalues[3]
     187 [-]: GETTABLEKS R7 R8 K12; var7 = var8["FloatingContent"]
     188 [-]: NAMECALL R3 R3 K33; var4 = var3; var3 = var3[0x67BC869F]
     189 [-]: CALL R3 5 1  ; var3(var4, var5, var6, var7)
     190 [-]: GETIMPORT R3 19; var3 = 0xAE91E43B
     191 [-]: LOADK R5 K47 ; var5 = "Panel.LineRightCap"
     192 [-]: LOADN R6 9   ; var6 = 9
     193 [-]: GETUPVAL R8 3; var8 = upvalues[3]
     194 [-]: GETTABLEKS R7 R8 K12; var7 = var8["FloatingContent"]
     195 [-]: NAMECALL R3 R3 K33; var4 = var3; var3 = var3[0x67BC869F]
     196 [-]: CALL R3 5 1  ; var3(var4, var5, var6, var7)
     197 [-]: GETIMPORT R3 19; var3 = 0xAE91E43B
     198 [-]: LOADK R5 K48 ; var5 = "Panel.LineRightFill"
     199 [-]: LOADN R6 9   ; var6 = 9
     200 [-]: GETUPVAL R8 3; var8 = upvalues[3]
     201 [-]: GETTABLEKS R7 R8 K12; var7 = var8["FloatingContent"]
     202 [-]: NAMECALL R3 R3 K33; var4 = var3; var3 = var3[0x67BC869F]
     203 [-]: CALL R3 5 1  ; var3(var4, var5, var6, var7)
     204 [-]: GETIMPORT R3 19; var3 = 0xAE91E43B
     205 [-]: LOADK R5 K49 ; var5 = "Panel.GridSeparator.CapLeft"
     206 [-]: GETIMPORT R7 31; var7 = 0x0032441C
     207 [-]: GETTABLEKS R6 R7 K43; var6 = var7["UIMaterial_VitruvianLines"]
     208 [-]: NAMECALL R3 R3 K40; var4 = var3; var3 = var3[0xD5181643]
     209 [-]: CALL R3 4 1  ; var3(var4, var5, var6)
     210 [-]: GETIMPORT R3 19; var3 = 0xAE91E43B
     211 [-]: LOADK R5 K50 ; var5 = "Panel.GridSeparator.Fill"
     212 [-]: GETIMPORT R7 31; var7 = 0x0032441C
     213 [-]: GETTABLEKS R6 R7 K43; var6 = var7["UIMaterial_VitruvianLines"]
     214 [-]: NAMECALL R3 R3 K40; var4 = var3; var3 = var3[0xD5181643]
     215 [-]: CALL R3 4 1  ; var3(var4, var5, var6)
     216 [-]: GETIMPORT R3 19; var3 = 0xAE91E43B
     217 [-]: LOADK R5 K51 ; var5 = "Panel.GridSeparator.CapRight"
     218 [-]: GETIMPORT R7 31; var7 = 0x0032441C
     219 [-]: GETTABLEKS R6 R7 K43; var6 = var7["UIMaterial_VitruvianLines"]
     220 [-]: NAMECALL R3 R3 K40; var4 = var3; var3 = var3[0xD5181643]
     221 [-]: CALL R3 4 1  ; var3(var4, var5, var6)
     222 [-]: GETIMPORT R3 19; var3 = 0xAE91E43B
     223 [-]: LOADK R5 K49 ; var5 = "Panel.GridSeparator.CapLeft"
     224 [-]: LOADN R6 9   ; var6 = 9
     225 [-]: GETUPVAL R8 3; var8 = upvalues[3]
     226 [-]: GETTABLEKS R7 R8 K12; var7 = var8["FloatingContent"]
     227 [-]: NAMECALL R3 R3 K33; var4 = var3; var3 = var3[0x67BC869F]
     228 [-]: CALL R3 5 1  ; var3(var4, var5, var6, var7)
     229 [-]: GETIMPORT R3 19; var3 = 0xAE91E43B
     230 [-]: LOADK R5 K50 ; var5 = "Panel.GridSeparator.Fill"
     231 [-]: LOADN R6 9   ; var6 = 9
     232 [-]: GETUPVAL R8 3; var8 = upvalues[3]
     233 [-]: GETTABLEKS R7 R8 K12; var7 = var8["FloatingContent"]
     234 [-]: NAMECALL R3 R3 K33; var4 = var3; var3 = var3[0x67BC869F]
     235 [-]: CALL R3 5 1  ; var3(var4, var5, var6, var7)
     236 [-]: GETIMPORT R3 19; var3 = 0xAE91E43B
     237 [-]: LOADK R5 K51 ; var5 = "Panel.GridSeparator.CapRight"
     238 [-]: LOADN R6 9   ; var6 = 9
     239 [-]: GETUPVAL R8 3; var8 = upvalues[3]
     240 [-]: GETTABLEKS R7 R8 K12; var7 = var8["FloatingContent"]
     241 [-]: NAMECALL R3 R3 K33; var4 = var3; var3 = var3[0x67BC869F]
     242 [-]: CALL R3 5 1  ; var3(var4, var5, var6, var7)
     243 [-]: GETIMPORT R3 53; var3 = 0x25D99D89
     244 [-]: NAMECALL R3 R3 K54; var4 = var3; var3 = var3[0xE222117A]
     245 [-]: CALL R3 2 2  ; var3 = var3(var4)
     246 [-]: SETUPVAL R3 8; upvalues[3] = var8
     247 [-]: GETIMPORT R4 57; var4 = 0x34291F5C[0x397B920F]
     248 [-]: GETUPVAL R5 8; var5 = upvalues[8]
     249 [-]: CALL R4 2 2  ; var4 = var4(var5)
     250 [-]: LOADN R5 0   ; var5 = 0
     251 [-]: JUMPIFLT R5 R4 L2; goto L2 if var5 < var16777990
     252 [-]: LOADB R3 0 +1; var3 = false
L 2: 253 [-]: LOADB R3 1   ; var3 = true
L 3: 254 [-]: SETUPVAL R3 9; upvalues[3] = var9
     255 [-]: GETIMPORT R3 19; var3 = 0xAE91E43B
     256 [-]: LOADK R5 K58 ; var5 = "Panel.Timer"
     257 [-]: LOADN R6 38  ; var6 = 38
     258 [-]: GETUPVAL R8 3; var8 = upvalues[3]
     259 [-]: GETTABLEKS R7 R8 K13; var7 = var8["FloatingContentHighlight"]
     260 [-]: NAMECALL R3 R3 K33; var4 = var3; var3 = var3[0x67BC869F]
     261 [-]: CALL R3 5 1  ; var3(var4, var5, var6, var7)
     262 [-]: GETIMPORT R3 19; var3 = 0xAE91E43B
     263 [-]: LOADK R5 K58 ; var5 = "Panel.Timer"
     264 [-]: LOADN R6 31  ; var6 = 31
     265 [-]: LOADK R7 K59 ; var7 = ""
     266 [-]: NAMECALL R3 R3 K36; var4 = var3; var3 = var3[0x5F56EEAB]
     267 [-]: CALL R3 5 1  ; var3(var4, var5, var6, var7)
     268 [-]: GETIMPORT R3 19; var3 = 0xAE91E43B
     269 [-]: LOADK R5 K60 ; var5 = "Panel.Title"
     270 [-]: LOADN R6 38  ; var6 = 38
     271 [-]: GETUPVAL R8 3; var8 = upvalues[3]
     272 [-]: GETTABLEKS R7 R8 K14; var7 = var8["Content"]
     273 [-]: NAMECALL R3 R3 K33; var4 = var3; var3 = var3[0x67BC869F]
     274 [-]: CALL R3 5 1  ; var3(var4, var5, var6, var7)
     275 [-]: GETIMPORT R3 19; var3 = 0xAE91E43B
     276 [-]: LOADK R5 K61 ; var5 = "Panel.Title.text"
     277 [-]: LOADK R6 K62 ; var6 = "/Lotus/Language/Blessings/BlessingTitle"
     278 [-]: NAMECALL R3 R3 K63; var4 = var3; var3 = var3[0x20B98DB3]
     279 [-]: CALL R3 4 1  ; var3(var4, var5, var6)
     280 [-]: GETIMPORT R3 19; var3 = 0xAE91E43B
     281 [-]: LOADK R5 K64 ; var5 = "Panel.Description"
     282 [-]: LOADN R6 38  ; var6 = 38
     283 [-]: GETUPVAL R8 3; var8 = upvalues[3]
     284 [-]: GETTABLEKS R7 R8 K13; var7 = var8["FloatingContentHighlight"]
     285 [-]: NAMECALL R3 R3 K33; var4 = var3; var3 = var3[0x67BC869F]
     286 [-]: CALL R3 5 1  ; var3(var4, var5, var6, var7)
     287 [-]: LOADK R4 K65 ; var4 = "/Lotus/Language/Blessings/"
     288 [-]: GETUPVAL R6 7; var6 = upvalues[7]
     289 [-]: GETTABLEKS R5 R6 K66; var5 = var6[0x06D055F9]
     290 [-]: GETUPVAL R6 9; var6 = upvalues[9]
     291 [-]: LOADK R7 K67 ; var7 = "BlessingDescCooldown"
     292 [-]: LOADK R8 K68 ; var8 = "BlessingDescReady"
     293 [-]: CALL R5 4 2  ; var5 = var5(var6, var7, var8)
     294 [-]: CONCAT R3 R4 R5; var3 = var4 .. var5
     295 [-]: GETIMPORT R4 19; var4 = 0xAE91E43B
     296 [-]: LOADK R6 K69 ; var6 = "Panel.Description.text"
     297 [-]: MOVE R7 R3   ; var7 = var3
     298 [-]: NAMECALL R4 R4 K63; var5 = var4; var4 = var4[0x20B98DB3]
     299 [-]: CALL R4 4 1  ; var4(var5, var6, var7)
     300 [-]: GETUPVAL R4 10; var4 = upvalues[10]
     301 [-]: CALL R4 1 1  ; var4()
     302 [-]: GETUPVAL R4 11; var4 = upvalues[11]
     303 [-]: CALL R4 1 1  ; var4()
     304 [-]: GETUPVAL R4 12; var4 = upvalues[12]
     305 [-]: CALL R4 1 1  ; var4()
     306 [-]: GETUPVAL R4 13; var4 = upvalues[13]
     307 [-]: CALL R4 1 1  ; var4()
     308 [-]: RETURN R0 0  ; 


; Name:            
; Defined at line: 323
; #Upvalues:       5
; #Parameters:     0
; Is_vararg:       0
; Max Stack Size:  10

       0 [-]: GETIMPORT R0 1; var0 = 0xAE91E43B
       1 [-]: GETIMPORT R2 3; var2 = 0xB693B6C1
       2 [-]: CALL R2 1 0  ; var2, ... = var2()
       3 [-]: NAMECALL R0 R0 K4; var1 = var0; var0 = var0[0x8A8C8D5A]
       4 [-]: CALL R0 0 1  ; var0(var1, ...)
       5 [-]: GETUPVAL R0 0; var0 = upvalues[0]
       6 [-]: JUMPIFNOT R0 L1; goto L1 if not var0
       7 [-]: GETIMPORT R0 7; var0 = 0x34291F5C[0x397B920F]
       8 [-]: GETUPVAL R1 1; var1 = upvalues[1]
       9 [-]: CALL R0 2 2  ; var0 = var0(var1)
      10 [-]: LOADN R1 0   ; var1 = 0
      11 [-]: JUMPIFNOTLE R0 R1 L0; goto L0 if var0 > var262
      12 [-]: LOADB R1 0   ; var1 = false
      13 [-]: SETUPVAL R1 0; upvalues[1] = var0
      14 [-]: GETIMPORT R1 1; var1 = 0xAE91E43B
      15 [-]: LOADK R3 K8  ; var3 = "Panel.Timer"
      16 [-]: LOADN R4 31  ; var4 = 31
      17 [-]: LOADK R5 K9  ; var5 = ""
      18 [-]: NAMECALL R1 R1 K10; var2 = var1; var1 = var1[0x5F56EEAB]
      19 [-]: CALL R1 5 1  ; var1(var2, var3, var4, var5)
      20 [-]: GETIMPORT R1 1; var1 = 0xAE91E43B
      21 [-]: LOADK R3 K11 ; var3 = "Panel.Grid"
      22 [-]: LOADN R4 10  ; var4 = 10
      23 [-]: LOADN R5 100 ; var5 = 100
      24 [-]: NAMECALL R1 R1 K12; var2 = var1; var1 = var1[0x67BC869F]
      25 [-]: CALL R1 5 1  ; var1(var2, var3, var4, var5)
      26 [-]: JUMP L1      ; goto L1
L 0:  27 [-]: GETIMPORT R1 1; var1 = 0xAE91E43B
      28 [-]: LOADK R3 K13 ; var3 = "Panel.Timer.text"
      29 [-]: LOADK R5 K14 ; var5 = "<TIMER> "
      30 [-]: GETUPVAL R7 2; var7 = upvalues[2]
      31 [-]: GETTABLEKS R6 R7 K15; var6 = var7[0xCFE63447]
      32 [-]: MOVE R7 R0   ; var7 = var0
      33 [-]: LOADB R8 0   ; var8 = false
      34 [-]: LOADB R9 1   ; var9 = true
      35 [-]: CALL R6 4 2  ; var6 = var6(var7, var8, var9)
      36 [-]: CONCAT R4 R5 R6; var4 = var5 .. var6
      37 [-]: NAMECALL R1 R1 K16; var2 = var1; var1 = var1[0x20B98DB3]
      38 [-]: CALL R1 4 1  ; var1(var2, var3, var4)
L 1:  39 [-]: GETUPVAL R1 3; var1 = upvalues[3]
      40 [-]: FASTCALL1 64 R1 L2; 
      41 [-]: GETIMPORT R0 18; var0 = 0x7B998233
      42 [-]: CALL R0 2 2  ; var0 = var0(var1)
L 2:  43 [-]: JUMPIF R0 L3 ; goto L3 if var0
      44 [-]: GETUPVAL R0 3; var0 = upvalues[3]
      45 [-]: GETIMPORT R2 3; var2 = 0xB693B6C1
      46 [-]: CALL R2 1 0  ; var2, ... = var2()
      47 [-]: NAMECALL R0 R0 K19; var1 = var0; var0 = var0[0xFAA69527]
      48 [-]: CALL R0 0 1  ; var0(var1, ...)
L 3:  49 [-]: GETUPVAL R0 4; var0 = upvalues[4]
      50 [-]: JUMPXEQKNIL R0 L4; 
      51 [-]: GETUPVAL R0 4; var0 = upvalues[4]
      52 [-]: NAMECALL R0 R0 K19; var1 = var0; var0 = var0[0xFAA69527]
      53 [-]: CALL R0 2 1  ; var0(var1)
L 4:  54 [-]: RETURN R0 0  ; 


; Name:            
; Defined at line: 346
; #Upvalues:       1
; #Parameters:     0
; Is_vararg:       0
; Max Stack Size:  2

       0 [-]: GETIMPORT R0 1; var0 = _T
       1 [-]: LOADNIL R1   ; var1 = nil
       2 [-]: SETTABLEKS R1 R0 K2; var1["InfoPopup_Data"] = var0
       3 [-]: GETUPVAL R1 0; var1 = upvalues[0]
       4 [-]: GETTABLEKS R0 R1 K3; var0 = var1[0x9E3D3434]
       5 [-]: LOADB R1 0   ; var1 = false
       6 [-]: CALL R0 2 1  ; var0(var1)
       7 [-]: GETIMPORT R1 5; var1 = _T["HideBackground"]
       8 [-]: FASTCALL1 64 R1 L0; 
       9 [-]: GETIMPORT R0 7; var0 = 0x7B998233
      10 [-]: CALL R0 2 2  ; var0 = var0(var1)
L 0:  11 [-]: JUMPIF R0 L1 ; goto L1 if var0
      12 [-]: GETIMPORT R0 5; var0 = _T["HideBackground"]
      13 [-]: LOADK R1 K8  ; var1 = 0.25
      14 [-]: CALL R0 2 1  ; var0(var1)
L 1:  15 [-]: RETURN R0 0  ; 


; Name:            
; Defined at line: 355
; #Upvalues:       1
; #Parameters:     2
; Is_vararg:       0
; Max Stack Size:  3

       0 [-]: GETUPVAL R2 0; var2 = upvalues[0]
       1 [-]: CALL R2 1 1  ; var2()
       2 [-]: RETURN R0 0  ; 


; Name:            
; Defined at line: 359
; #Upvalues:       2
; #Parameters:     1
; Is_vararg:       0
; Max Stack Size:  5

       0 [-]: GETUPVAL R2 0; var2 = upvalues[0]
       1 [-]: FASTCALL1 64 R2 L0; 
       2 [-]: GETIMPORT R1 1; var1 = 0x7B998233
       3 [-]: CALL R1 2 2  ; var1 = var1(var2)
L 0:   4 [-]: JUMPIF R1 L2 ; goto L2 if var1
       5 [-]: GETUPVAL R1 1; var1 = upvalues[1]
       6 [-]: JUMPIF R1 L2 ; goto L2 if var1
       7 [-]: GETUPVAL R1 0; var1 = upvalues[0]
       8 [-]: FASTCALL1 62 R0 L1; 
       9 [-]: MOVE R4 R0   ; var4 = var0
      10 [-]: GETIMPORT R3 3; var3 = 0x03F57322
      11 [-]: CALL R3 2 2  ; var3 = var3(var4)
L 1:  12 [-]: NAMECALL R1 R1 K4; var2 = var1; var1 = var1[0xDF42446E]
      13 [-]: CALL R1 3 1  ; var1(var2, var3)
L 2:  14 [-]: RETURN R0 0  ; 


; Name:            
; Defined at line: 365
; #Upvalues:       1
; #Parameters:     1
; Is_vararg:       0
; Max Stack Size:  5

       0 [-]: GETUPVAL R2 0; var2 = upvalues[0]
       1 [-]: FASTCALL1 64 R2 L0; 
       2 [-]: GETIMPORT R1 1; var1 = 0x7B998233
       3 [-]: CALL R1 2 2  ; var1 = var1(var2)
L 0:   4 [-]: JUMPIF R1 L2 ; goto L2 if var1
       5 [-]: GETUPVAL R1 0; var1 = upvalues[0]
       6 [-]: FASTCALL1 62 R0 L1; 
       7 [-]: MOVE R4 R0   ; var4 = var0
       8 [-]: GETIMPORT R3 3; var3 = 0x03F57322
       9 [-]: CALL R3 2 2  ; var3 = var3(var4)
L 1:  10 [-]: NAMECALL R1 R1 K4; var2 = var1; var1 = var1[0xBCE5A201]
      11 [-]: CALL R1 3 1  ; var1(var2, var3)
L 2:  12 [-]: RETURN R0 0  ; 


; Name:            
; Defined at line: 371
; #Upvalues:       2
; #Parameters:     1
; Is_vararg:       0
; Max Stack Size:  5

       0 [-]: GETUPVAL R2 0; var2 = upvalues[0]
       1 [-]: FASTCALL1 64 R2 L0; 
       2 [-]: GETIMPORT R1 1; var1 = 0x7B998233
       3 [-]: CALL R1 2 2  ; var1 = var1(var2)
L 0:   4 [-]: JUMPIF R1 L2 ; goto L2 if var1
       5 [-]: GETUPVAL R1 1; var1 = upvalues[1]
       6 [-]: JUMPIF R1 L2 ; goto L2 if var1
       7 [-]: GETUPVAL R1 0; var1 = upvalues[0]
       8 [-]: FASTCALL1 62 R0 L1; 
       9 [-]: MOVE R4 R0   ; var4 = var0
      10 [-]: GETIMPORT R3 3; var3 = 0x03F57322
      11 [-]: CALL R3 2 2  ; var3 = var3(var4)
L 1:  12 [-]: LOADB R4 1   ; var4 = true
      13 [-]: NAMECALL R1 R1 K4; var2 = var1; var1 = var1[0x070DAA5A]
      14 [-]: CALL R1 4 1  ; var1(var2, var3, var4)
L 2:  15 [-]: RETURN R0 0  ; 


; Name:            
; Defined at line: 377
; #Upvalues:       1
; #Parameters:     1
; Is_vararg:       0
; Max Stack Size:  2

       0 [-]: SETUPVAL R0 0; upvalues[0] = var0
       1 [-]: LOADB R1 1   ; var1 = true
       2 [-]: RETURN R1 1  ; 


; Name:            
; Defined at line: 382
; #Upvalues:       0
; #Parameters:     0
; Is_vararg:       0
; Max Stack Size:  1

       0 [-]: LOADB R0 1   ; var0 = true
       1 [-]: RETURN R0 1  ; 



