; Name:            
; Defined at line: 1
; #Upvalues:       0
; #Parameters:     0
; Is_vararg:       1
; Max Stack Size:  13

            1 [-]: GETIMPORT R0 1 [nil]
       2 [-]: LOADK R1 K2 ["EE.Interface.Utilities"]
       3 [-]: CALL R0 1 1  
       4 [-]: LOADNIL R1   
       5 [-]: LOADNIL R2   
       6 [-]: LOADNIL R3   
       7 [-]: LOADNIL R4   
       8 [-]: LOADNIL R5   
       9 [-]: LOADNIL R6   
      10 [-]: LOADNIL R7   
      11 [-]: LOADNIL R8   
      12 [-]: GETIMPORT R9 4 [nil]
      13 [-]: LOADK R10 K5 ["/Lotus/Types/Player/DuviriDrifterInputFilter"]
      14 [-]: CALL R9 1 1  
      15 [-]: DUPCLOSURE R10 K6 []
      16 [-]: SETGLOBAL R10 K7 ["Shutdown"]
      17 [-]: NEWCLOSURE R10 P1
      18 [-]: MOVE R1 R1   
      19 [-]: SETGLOBAL R10 K8 ["Initialize"]
      20 [-]: NEWCLOSURE R10 P2
      21 [-]: MOVE R1 R3   
      22 [-]: MOVE R1 R4   
      23 [-]: NEWCLOSURE R11 P3
      24 [-]: MOVE R1 R2   
      25 [-]: MOVE R1 R3   
      26 [-]: MOVE R1 R4   
      27 [-]: NEWCLOSURE R12 P4
      28 [-]: MOVE R1 R6   
      29 [-]: MOVE R1 R4   
      30 [-]: MOVE R1 R7   
      31 [-]: MOVE R1 R3   
      32 [-]: MOVE R1 R5   
      33 [-]: MOVE R1 R8   
      34 [-]: MOVE R0 R0   
      35 [-]: MOVE R0 R9   
      36 [-]: SETGLOBAL R12 K9 ["Update"]
      37 [-]: NEWCLOSURE R12 P5
      38 [-]: MOVE R1 R1   
      39 [-]: SETGLOBAL R12 K10 ["onViewportSizeChanged"]
      40 [-]: NEWCLOSURE R12 P6
      41 [-]: MOVE R1 R7   
      42 [-]: SETGLOBAL R12 K11 ["OnGamepadTransition"]
      43 [-]: DUPCLOSURE R12 K12 []
      44 [-]: SETGLOBAL R12 K13 ["SupportsThemes"]
      45 [-]: NEWCLOSURE R12 P8
      46 [-]: MOVE R1 R2   
      47 [-]: MOVE R1 R7   
      48 [-]: MOVE R0 R11  
      49 [-]: SETGLOBAL R12 K14 ["Hide"]
      50 [-]: CLOSEUPVALS R1
      51 [-]: RETURN R0 0  


; Name:            
; Defined at line: 17
; #Upvalues:       0
; #Parameters:     0
; Is_vararg:       0
; Max Stack Size:  0

       0 [-]: RETURN R0 0  


; Name:            
; Defined at line: 20
; #Upvalues:       1
; #Parameters:     0
; Is_vararg:       0
; Max Stack Size:  9

       0 [-]: GETIMPORT R0 1 [nil]
       1 [-]: LOADK R2 K2 ["_root"]
       2 [-]: LOADN R3 10  
       3 [-]: LOADN R4 0   
       4 [-]: NAMECALL R0 R0 K3 [0x67BC869F]
       5 [-]: CALL R0 4 0  
       6 [-]: GETIMPORT R0 5 [nil]
       7 [-]: LOADK R1 K6 ["EE.Interface.AnchorMgr"]
       8 [-]: CALL R0 1 1  
       9 [-]: GETTABLEKS R1 R0 K7 [0xAE6791BA]
      10 [-]: GETIMPORT R2 1 [nil]
      11 [-]: CALL R1 1 1  
      12 [-]: SETUPVAL R1 0
      13 [-]: GETUPVAL R1 0
      14 [-]: GETIMPORT R3 1 [nil]
      15 [-]: LOADK R4 K8 ["Notification"]
      16 [-]: NEWTABLE R5 0 2
      17 [-]: GETUPVAL R7 0
      18 [-]: GETTABLEKS R6 R7 K9 ["ANCHOR_V_BOTTOM"]
      19 [-]: GETUPVAL R8 0
      20 [-]: GETTABLEKS R7 R8 K10 ["ANCHOR_H_CENTRE"]
      21 [-]: SETLIST R5 R6 2 [1]
      22 [-]: NAMECALL R1 R1 K11 [0x20FF29F7]
      23 [-]: CALL R1 4 0  
      24 [-]: GETUPVAL R1 0
      25 [-]: GETIMPORT R3 1 [nil]
      26 [-]: NAMECALL R3 R3 K12 [0x6B837788]
      27 [-]: CALL R3 1 1  
      28 [-]: GETIMPORT R4 1 [nil]
      29 [-]: NAMECALL R4 R4 K13 [0xAF9FDA9F]
      30 [-]: CALL R4 1 -1 
      31 [-]: NAMECALL R1 R1 K14 [0xFAA69527]
      32 [-]: CALL R1 -1 0 
      33 [-]: GETIMPORT R1 1 [nil]
      34 [-]: LOADK R3 K15 ["Notification.Label"]
      35 [-]: LOADN R4 46  
      36 [-]: LOADB R5 1   
      37 [-]: NAMECALL R1 R1 K16 [0xAADE900E]
      38 [-]: CALL R1 4 0  
      39 [-]: GETIMPORT R1 1 [nil]
      40 [-]: LOADK R3 K15 ["Notification.Label"]
      41 [-]: LOADN R4 38  
      42 [-]: LOADK R5 K17 ["center"]
      43 [-]: NAMECALL R1 R1 K18 [0x5F56EEAB]
      44 [-]: CALL R1 4 0  
      45 [-]: RETURN R0 0  


; Name:            
; Defined at line: 32
; #Upvalues:       2
; #Parameters:     0
; Is_vararg:       0
; Max Stack Size:  8

       0 [-]: GETIMPORT R0 1 [nil]
       1 [-]: LOADK R2 K2 ["_root"]
       2 [-]: LOADN R3 10  
       3 [-]: GETUPVAL R6 0
       4 [-]: ORK R5 R6 K3 [100]
       5 [-]: GETUPVAL R7 1
       6 [-]: ORK R6 R7 K3 [100]
       7 [-]: FASTCALL2 19 R5 R6 L0
       8 [-]: GETIMPORT R4 6 [nil]
       9 [-]: CALL R4 2 1  
L 0:  10 [-]: NAMECALL R0 R0 K7 [0x67BC869F]
      11 [-]: CALL R0 4 0  
      12 [-]: RETURN R0 0  


; Name:            
; Defined at line: 36
; #Upvalues:       3
; #Parameters:     1
; Is_vararg:       0
; Max Stack Size:  9

       0 [-]: GETUPVAL R1 0
       1 [-]: JUMPIFNOT R1 L0
       2 [-]: LOADN R1 100 
       3 [-]: SUB R0 R1 R0 
L 0:   4 [-]: SETUPVAL R0 1
       5 [-]: GETIMPORT R1 1 [nil]
       6 [-]: LOADK R3 K2 ["_root"]
       7 [-]: LOADN R4 10  
       8 [-]: GETUPVAL R7 1
       9 [-]: ORK R6 R7 K3 [100]
      10 [-]: GETUPVAL R8 2
      11 [-]: ORK R7 R8 K3 [100]
      12 [-]: FASTCALL2 19 R6 R7 L1
      13 [-]: GETIMPORT R5 6 [nil]
      14 [-]: CALL R5 2 1  
L 1:  15 [-]: NAMECALL R1 R1 K7 [0x67BC869F]
      16 [-]: CALL R1 4 0  
      17 [-]: RETURN R0 0  


; Name:            
; Defined at line: 45
; #Upvalues:       8
; #Parameters:     0
; Is_vararg:       0
; Max Stack Size:  18

       0 [-]: GETIMPORT R0 1 [nil]
       1 [-]: CALL R0 0 1  
       2 [-]: GETIMPORT R2 3 [nil]
       3 [-]: FASTCALL1 62 R2 L0
       4 [-]: GETIMPORT R1 5 [nil]
       5 [-]: CALL R1 1 1  
L 0:   6 [-]: JUMPIFNOT R1 L1
       7 [-]: RETURN R0 0  
L 1:   8 [-]: GETIMPORT R1 3 [nil]
       9 [-]: MOVE R3 R0   
      10 [-]: NAMECALL R1 R1 K6 [0x8A8C8D5A]
      11 [-]: CALL R1 2 0  
      12 [-]: GETUPVAL R2 0
      13 [-]: FASTCALL1 62 R2 L2
      14 [-]: GETIMPORT R1 5 [nil]
      15 [-]: CALL R1 1 1  
L 2:  16 [-]: JUMPIFNOT R1 L4
      17 [-]: GETIMPORT R2 8 [nil]
      18 [-]: FASTCALL1 62 R2 L3
      19 [-]: GETIMPORT R1 5 [nil]
      20 [-]: CALL R1 1 1  
L 3:  21 [-]: JUMPIF R1 L4 
      22 [-]: GETIMPORT R1 8 [nil]
      23 [-]: NAMECALL R1 R1 K9 [0x33307F92]
      24 [-]: CALL R1 1 1  
      25 [-]: SETUPVAL R1 0
L 4:  26 [-]: GETUPVAL R2 0
      27 [-]: FASTCALL1 62 R2 L5
      28 [-]: GETIMPORT R1 5 [nil]
      29 [-]: CALL R1 1 1  
L 5:  30 [-]: JUMPIF R1 L10
      31 [-]: GETUPVAL R1 0
      32 [-]: LOADK R3 K10 ["_root"]
      33 [-]: LOADN R4 10  
      34 [-]: NAMECALL R1 R1 K11 [0x91A24E4B]
      35 [-]: CALL R1 3 1  
      36 [-]: GETUPVAL R2 0
      37 [-]: LOADK R4 K10 ["_root"]
      38 [-]: LOADN R5 11  
      39 [-]: NAMECALL R2 R2 K12 [0x5B0290D2]
      40 [-]: CALL R2 3 1  
      41 [-]: JUMPIFNOT R2 L6
      42 [-]: GETIMPORT R3 15 [nil]
      43 [-]: NOT R2 R3    
      44 [-]: JUMPIFNOT R2 L6
      45 [-]: GETIMPORT R3 17 [nil]
      46 [-]: NOT R2 R3    
L 6:  47 [-]: GETUPVAL R3 1
      48 [-]: JUMPIFEQ R3 R1 L9
      49 [-]: GETUPVAL R3 1
      50 [-]: JUMPXEQKN R3 K18 L7 NOT [0]
      51 [-]: LOADN R3 0   
      52 [-]: JUMPIFNOTLT R3 R1 L7
      53 [-]: GETIMPORT R3 19 [nil]
      54 [-]: LOADB R4 1   
      55 [-]: SETTABLEKS R4 R3 K20 ["BoonNotificationSilent"]
      56 [-]: LOADNIL R3   
      57 [-]: SETUPVAL R3 2
L 7:  58 [-]: SETUPVAL R1 1
      59 [-]: GETIMPORT R3 3 [nil]
      60 [-]: LOADK R5 K10 ["_root"]
      61 [-]: LOADN R6 10  
      62 [-]: GETUPVAL R9 3
      63 [-]: ORK R8 R9 K21 [100]
      64 [-]: GETUPVAL R10 1
      65 [-]: ORK R9 R10 K21 [100]
      66 [-]: FASTCALL2 19 R8 R9 L8
      67 [-]: GETIMPORT R7 24 [nil]
      68 [-]: CALL R7 2 1  
L 8:  69 [-]: NAMECALL R3 R3 K25 [0x67BC869F]
      70 [-]: CALL R3 4 0  
L 9:  71 [-]: GETUPVAL R3 4
      72 [-]: JUMPIFEQ R3 R2 L10
      73 [-]: SETUPVAL R2 4
      74 [-]: GETIMPORT R3 3 [nil]
      75 [-]: LOADK R5 K10 ["_root"]
      76 [-]: LOADN R6 11  
      77 [-]: MOVE R7 R2   
      78 [-]: NAMECALL R3 R3 K26 [0xAADE900E]
      79 [-]: CALL R3 4 0  
L10:  80 [-]: GETIMPORT R1 28 [nil]
      81 [-]: NAMECALL R1 R1 K29 [0xFB64E76C]
      82 [-]: CALL R1 1 1  
      83 [-]: FASTCALL1 62 R1 L11
      84 [-]: MOVE R3 R1   
      85 [-]: GETIMPORT R2 5 [nil]
      86 [-]: CALL R2 1 1  
L11:  87 [-]: JUMPIF R2 L21
      88 [-]: NAMECALL R2 R1 K30 [0xBB610E5B]
      89 [-]: CALL R2 1 1  
      90 [-]: NAMECALL R3 R1 K31 [0x0AE03F5F]
      91 [-]: CALL R3 1 1  
      92 [-]: JUMPXEQKN R3 K18 L12 NOT [0]
      93 [-]: LOADN R4 0   
      94 [-]: SETUPVAL R4 2
      95 [-]: GETIMPORT R4 3 [nil]
      96 [-]: NAMECALL R4 R4 K32 [0x32302B4A]
      97 [-]: CALL R4 1 0  
      98 [-]: RETURN R0 0  
L12:  99 [-]: GETUPVAL R4 2
     100 [-]: JUMPIFNOTEQ R3 R4 L13
     101 [-]: GETUPVAL R4 5
     102 [-]: JUMPIFEQ R4 R2 L21
L13: 103 [-]: GETUPVAL R5 2
     104 [-]: JUMPIFNOTEQ R3 R5 L14
     105 [-]: LOADB R4 0 +1
L14: 106 [-]: LOADB R4 1   
L15: 107 [-]: SETUPVAL R3 2
     108 [-]: SETUPVAL R2 5
     109 [-]: GETUPVAL R6 2
     110 [-]: LOADN R7 1   
     111 [-]: JUMPIFNOTLT R7 R6 L16
     112 [-]: LOADK R5 K33 ["/Lotus/Language/Duviri/BoonTrackerTextPlural"]
     113 [-]: JUMP L17
    
L16: 114 [-]: LOADK R5 K34 ["/Lotus/Language/Duviri/BoonTrackerText"]
L17: 115 [-]: GETUPVAL R7 6
     116 [-]: GETTABLEKS R6 R7 K35 [0x06D055F9]
     117 [-]: GETIMPORT R7 38 [nil]
     118 [-]: CALL R7 0 1  
     119 [-]: LOADK R8 K39 ["<MINI_INVENTORY_TOGGLE>"]
     120 [-]: LOADK R9 K40 ["<MINI_INVENTORY_HOLD>"]
     121 [-]: CALL R6 3 1  
     122 [-]: GETUPVAL R7 7
     123 [-]: GETUPVAL R9 5
     124 [-]: FASTCALL1 62 R9 L18
     125 [-]: GETIMPORT R8 5 [nil]
     126 [-]: CALL R8 1 1  
L18: 127 [-]: JUMPIF R8 L19
     128 [-]: GETUPVAL R8 5
     129 [-]: NAMECALL R8 R8 K41 [0xFBC94898]
     130 [-]: CALL R8 1 1  
     131 [-]: MOVE R7 R8   
L19: 132 [-]: LOADK R9 K42 ["<p><font color=\"#FFFFFF\">"]
     133 [-]: GETIMPORT R12 3 [nil]
     134 [-]: MOVE R14 R5  
     135 [-]: MOVE R15 R7  
     136 [-]: DUPTABLE R16 47
     137 [-]: GETUPVAL R17 2
     138 [-]: SETTABLEKS R17 R16 K43 ["COUNT"]
     139 [-]: LOADK R17 K48 ["<font face=\"Roboto\" color=\"#FFFE91\">"]
     140 [-]: SETTABLEKS R17 R16 K44 ["COLOR_START"]
     141 [-]: LOADK R17 K49 ["</font>"]
     142 [-]: SETTABLEKS R17 R16 K45 ["COLOR_END"]
     143 [-]: SETTABLEKS R6 R16 K46 ["CALLOUT"]
     144 [-]: NAMECALL R12 R12 K50 [0x54F5D6AD]
     145 [-]: CALL R12 4 1 
     146 [-]: MOVE R10 R12 
     147 [-]: LOADK R11 K51 ["</font></p>"]
     148 [-]: CONCAT R8 R9 R11
     149 [-]: GETIMPORT R9 3 [nil]
     150 [-]: LOADK R11 K52 ["Notification.Label"]
     151 [-]: LOADN R12 29 
     152 [-]: MOVE R13 R8  
     153 [-]: NAMECALL R9 R9 K53 [0x5F56EEAB]
     154 [-]: CALL R9 4 0  
     155 [-]: GETIMPORT R9 54 [nil]
     156 [-]: JUMPIFNOT R9 L20
     157 [-]: GETIMPORT R9 19 [nil]
     158 [-]: LOADNIL R10  
     159 [-]: SETTABLEKS R10 R9 K20 ["BoonNotificationSilent"]
     160 [-]: RETURN R0 0  
L20: 161 [-]: JUMPIFNOT R4 L21
     162 [-]: GETUPVAL R10 6
     163 [-]: GETTABLEKS R9 R10 K55 [0x659D451F]
     164 [-]: GETIMPORT R10 57 [nil]
     165 [-]: CALL R9 1 0  
     166 [-]: GETUPVAL R10 6
     167 [-]: GETTABLEKS R9 R10 K55 [0x659D451F]
     168 [-]: GETIMPORT R10 59 [nil]
     169 [-]: CALL R9 1 0  
L21: 170 [-]: RETURN R0 0  


; Name:            
; Defined at line: 105
; #Upvalues:       1
; #Parameters:     4
; Is_vararg:       0
; Max Stack Size:  8

       0 [-]: GETUPVAL R5 0
       1 [-]: FASTCALL1 62 R5 L0
       2 [-]: GETIMPORT R4 1 [nil]
       3 [-]: CALL R4 1 1  
L 0:   4 [-]: JUMPIF R4 L1 
       5 [-]: GETUPVAL R4 0
       6 [-]: MOVE R6 R0   
       7 [-]: MOVE R7 R1   
       8 [-]: NAMECALL R4 R4 K2 [0xFAA69527]
       9 [-]: CALL R4 3 0  
L 1:  10 [-]: RETURN R0 0  


; Name:            
; Defined at line: 111
; #Upvalues:       1
; #Parameters:     1
; Is_vararg:       0
; Max Stack Size:  2

       0 [-]: LOADNIL R1   
       1 [-]: SETUPVAL R1 0
       2 [-]: RETURN R0 0  


; Name:            
; Defined at line: 115
; #Upvalues:       0
; #Parameters:     0
; Is_vararg:       0
; Max Stack Size:  1

       0 [-]: LOADB R0 1   
       1 [-]: RETURN R0 1  


; Name:            
; Defined at line: 119
; #Upvalues:       3
; #Parameters:     1
; Is_vararg:       0
; Max Stack Size:  8

       0 [-]: JUMPXEQKS R0 K0 L0 ["true"]
       1 [-]: LOADB R1 0 +1
L 0:   2 [-]: LOADB R1 1   
L 1:   3 [-]: SETUPVAL R1 0
       4 [-]: GETUPVAL R1 0
       5 [-]: JUMPIFNOT R1 L2
       6 [-]: GETIMPORT R1 2 [nil]
       7 [-]: LOADB R2 1   
       8 [-]: SETTABLEKS R2 R1 K3 ["BoonNotificationSilent"]
       9 [-]: LOADNIL R1   
      10 [-]: SETUPVAL R1 1
L 2:  11 [-]: GETIMPORT R1 5 [nil]
      12 [-]: GETIMPORT R2 7 [nil]
      13 [-]: LOADK R3 K8 ["nothing"]
      14 [-]: LOADN R4 1   
      15 [-]: NEWTABLE R5 0 1
      16 [-]: GETUPVAL R6 2
      17 [-]: SETLIST R5 R6 1 [1]
      18 [-]: NEWTABLE R6 0 1
      19 [-]: LOADN R7 100 
      20 [-]: SETLIST R6 R7 1 [1]
      21 [-]: LOADK R7 K9 [0.14999999999999999]
      22 [-]: CALL R1 6 0  
      23 [-]: RETURN R0 0  



