; Name:            
; Defined at line: 1
; #Upvalues:       0
; #Parameters:     0
; Is_vararg:       1
; Max Stack Size:  78

            1 [-]: GETIMPORT R0 1 [nil]
       2 [-]: LOADK R1 K2 ["EE.Interface.Utilities"]
       3 [-]: CALL R0 1 1  
       4 [-]: GETIMPORT R1 1 [nil]
       5 [-]: LOADK R2 K3 ["Lotus.Interface.UIUtilities"]
       6 [-]: CALL R1 1 1  
       7 [-]: GETIMPORT R2 1 [nil]
       8 [-]: LOADK R3 K4 ["Lotus.Interface.LotusUtilities"]
       9 [-]: CALL R2 1 1  
      10 [-]: GETIMPORT R3 1 [nil]
      11 [-]: LOADK R4 K5 ["Lotus.Interface.UIStyleUtilities"]
      12 [-]: CALL R3 1 1  
      13 [-]: GETIMPORT R4 1 [nil]
      14 [-]: LOADK R5 K6 ["Lotus.Interface.StoreItemUtilities"]
      15 [-]: CALL R4 1 1  
      16 [-]: GETIMPORT R5 1 [nil]
      17 [-]: LOADK R6 K7 ["Lotus.Interface.CardUtilitiesRedux"]
      18 [-]: CALL R5 1 1  
      19 [-]: GETIMPORT R6 1 [nil]
      20 [-]: LOADK R7 K8 ["Lotus.Interface.Components.AbilityList"]
      21 [-]: CALL R6 1 1  
      22 [-]: GETIMPORT R7 1 [nil]
      23 [-]: LOADK R8 K9 ["Lotus.Interface.Libs.DuviriUtil"]
      24 [-]: CALL R7 1 1  
      25 [-]: GETIMPORT R8 11 [nil]
      26 [-]: LOADK R9 K12 ["/Lotus/Types/Game/BaseCosmeticEnhancer"]
      27 [-]: CALL R8 1 1  
      28 [-]: GETIMPORT R9 14 [nil]
      29 [-]: LOADK R10 K15 ["/Lotus/Fx/Interface/EvolvingWeapons/EvolvingWeaponsNodeDeco"]
      30 [-]: CALL R9 1 1  
      31 [-]: GETIMPORT R10 14 [nil]
      32 [-]: LOADK R11 K16 ["/Lotus/Fx/Interface/EvolvingWeapons/EvolvingWeaponsSpline"]
      33 [-]: CALL R10 1 1 
      34 [-]: GETIMPORT R11 14 [nil]
      35 [-]: LOADK R12 K17 ["/Lotus/Fx/Interface/EvolvingWeapons/EvolvingNodeFlyerDeco"]
      36 [-]: CALL R11 1 1 
      37 [-]: GETIMPORT R12 19 [nil]
      38 [-]: LOADK R13 K20 ["/Lotus/Fx/Interface/EvolvingWeapons/EvolvingWeaponsNodeDecoMatA"]
      39 [-]: CALL R12 1 1 
      40 [-]: GETIMPORT R13 19 [nil]
      41 [-]: LOADK R14 K21 ["/Lotus/Fx/Interface/EvolvingWeapons/EvolvingWeaponsNodeDecoMatDisabled"]
      42 [-]: CALL R13 1 1 
      43 [-]: DUPTABLE R14 25
      44 [-]: LOADN R15 0  
      45 [-]: SETTABLEKS R15 R14 K22 ["Center"]
      46 [-]: LOADK R15 K26 [0.55000000000000004]
      47 [-]: SETTABLEKS R15 R14 K23 ["Size"]
      48 [-]: LOADK R15 K27 [0.14999999999999999]
      49 [-]: SETTABLEKS R15 R14 K24 ["FadeSize"]
      50 [-]: GETIMPORT R15 29 [nil]
      51 [-]: CALL R15 0 1 
      52 [-]: LOADN R16 0  
      53 [-]: LOADNIL R17  
      54 [-]: LOADNIL R18  
      55 [-]: LOADNIL R19  
      56 [-]: DUPTABLE R20 42
      57 [-]: LOADN R21 1  
      58 [-]: SETTABLEKS R21 R20 K30 ["RerollStartIndex"]
      59 [-]: LOADB R21 0  
      60 [-]: SETTABLEKS R21 R20 K31 ["NeedReroll"]
      61 [-]: LOADNIL R21  
      62 [-]: SETTABLEKS R21 R20 K32 ["PendingRewards"]
      63 [-]: LOADN R21 0  
      64 [-]: SETTABLEKS R21 R20 K33 ["IconCycleTimer"]
      65 [-]: LOADNIL R21  
      66 [-]: SETTABLEKS R21 R20 K34 ["Spinner"]
      67 [-]: LOADNIL R21  
      68 [-]: SETTABLEKS R21 R20 K35 ["Loader"]
      69 [-]: LOADB R21 0  
      70 [-]: SETTABLEKS R21 R20 K36 ["IsLoading"]
      71 [-]: LOADNIL R21  
      72 [-]: SETTABLEKS R21 R20 K37 ["NormalBtn"]
      73 [-]: LOADNIL R21  
      74 [-]: SETTABLEKS R21 R20 K38 ["HardBtn"]
      75 [-]: LOADNIL R21  
      76 [-]: SETTABLEKS R21 R20 K39 ["StartBtn"]
      77 [-]: LOADNIL R21  
      78 [-]: SETTABLEKS R21 R20 K40 ["Grid"]
      79 [-]: LOADN R21 1  
      80 [-]: SETTABLEKS R21 R20 K41 ["Tier"]
      81 [-]: DUPTABLE R21 52
      82 [-]: LOADNIL R22  
      83 [-]: SETTABLEKS R22 R21 K43 ["Fx"]
      84 [-]: LOADNIL R22  
      85 [-]: SETTABLEKS R22 R21 K44 ["ShowingElement"]
      86 [-]: NEWTABLE R22 0 0
      87 [-]: SETTABLEKS R22 R21 K45 ["Elements"]
      88 [-]: LOADN R22 0  
      89 [-]: SETTABLEKS R22 R21 K46 ["CurrIndex"]
      90 [-]: LOADN R22 1  
      91 [-]: SETTABLEKS R22 R21 K47 ["StartIndex"]
      92 [-]: LOADN R22 0  
      93 [-]: SETTABLEKS R22 R21 K48 ["Num"]
      94 [-]: LOADB R22 0  
      95 [-]: SETTABLEKS R22 R21 K49 ["HasClaim"]
      96 [-]: LOADNIL R22  
      97 [-]: SETTABLEKS R22 R21 K50 ["Rewards"]
      98 [-]: LOADNIL R22  
      99 [-]: SETTABLEKS R22 R21 K51 ["Timer"]
     100 [-]: NEWTABLE R22 4 0
     101 [-]: LOADNIL R23  
     102 [-]: LOADNIL R24  
     103 [-]: DUPTABLE R25 63
     104 [-]: LOADNIL R26  
     105 [-]: SETTABLEKS R26 R25 K53 ["Configs"]
     106 [-]: LOADNIL R26  
     107 [-]: SETTABLEKS R26 R25 K54 ["CameraSpot"]
     108 [-]: LOADNIL R26  
     109 [-]: SETTABLEKS R26 R25 K55 ["WeaponDecos"]
     110 [-]: LOADB R26 0  
     111 [-]: SETTABLEKS R26 R25 K56 ["HasOffHand"]
     112 [-]: LOADB R26 0  
     113 [-]: SETTABLEKS R26 R25 K57 ["QueueConfigure"]
     114 [-]: NEWTABLE R26 0 0
     115 [-]: SETTABLEKS R26 R25 K58 ["WeaponTypes"]
     116 [-]: LOADN R26 1  
     117 [-]: SETTABLEKS R26 R25 K59 ["WeaponIndex"]
     118 [-]: LOADNIL R26  
     119 [-]: SETTABLEKS R26 R25 K60 ["Weapon"]
     120 [-]: LOADNIL R26  
     121 [-]: SETTABLEKS R26 R25 K35 ["Loader"]
     122 [-]: LOADB R26 0  
     123 [-]: SETTABLEKS R26 R25 K36 ["IsLoading"]
     124 [-]: LOADB R26 0  
     125 [-]: SETTABLEKS R26 R25 K61 ["Loaded"]
     126 [-]: LOADNIL R26  
     127 [-]: SETTABLEKS R26 R25 K62 ["DioWRes"]
     128 [-]: LOADB R26 0  
     129 [-]: LOADB R27 0  
     130 [-]: LOADB R28 0  
     131 [-]: LOADNIL R29  
     132 [-]: LOADNIL R30  
     133 [-]: LOADNIL R31  
     134 [-]: LOADB R32 0  
     135 [-]: DUPTABLE R33 64
     136 [-]: LOADNIL R34  
     137 [-]: SETTABLEKS R34 R33 K35 ["Loader"]
     138 [-]: LOADB R34 0  
     139 [-]: SETTABLEKS R34 R33 K36 ["IsLoading"]
     140 [-]: LOADB R34 0  
     141 [-]: LOADNIL R35  
     142 [-]: LOADNIL R36  
     143 [-]: LOADNIL R37  
     144 [-]: LOADNIL R38  
     145 [-]: NEWTABLE R39 0 0
     146 [-]: LOADN R40 1  
     147 [-]: LOADN R41 100
     148 [-]: LOADN R42 100
     149 [-]: LOADNIL R43  
     150 [-]: LOADNIL R44  
     151 [-]: LOADNIL R45  
     152 [-]: LOADNIL R46  
     153 [-]: LOADNIL R47  
     154 [-]: LOADNIL R48  
     155 [-]: LOADNIL R49  
     156 [-]: LOADNIL R50  
     157 [-]: LOADNIL R51  
     158 [-]: LOADNIL R52  
     159 [-]: LOADB R53 0  
     160 [-]: LOADNIL R54  
     161 [-]: LOADNIL R55  
     162 [-]: NEWCLOSURE R56 P0
     163 [-]: MOVE R1 R52  
     164 [-]: MOVE R1 R53  
     165 [-]: NEWCLOSURE R57 P1
     166 [-]: MOVE R1 R26  
     167 [-]: MOVE R1 R27  
     168 [-]: MOVE R1 R45  
     169 [-]: NEWCLOSURE R58 P2
     170 [-]: MOVE R1 R26  
     171 [-]: MOVE R0 R0   
     172 [-]: MOVE R1 R28  
     173 [-]: MOVE R1 R16  
     174 [-]: NEWCLOSURE R59 P3
     175 [-]: MOVE R1 R16  
     176 [-]: MOVE R1 R49  
     177 [-]: MOVE R1 R50  
     178 [-]: MOVE R0 R20  
     179 [-]: NEWCLOSURE R60 P4
     180 [-]: MOVE R0 R20  
     181 [-]: MOVE R0 R25  
     182 [-]: MOVE R0 R14  
     183 [-]: MOVE R0 R21  
     184 [-]: MOVE R1 R24  
     185 [-]: MOVE R1 R27  
     186 [-]: MOVE R0 R57  
     187 [-]: MOVE R0 R59  
     188 [-]: SETGLOBAL R60 K65 ["OnClaimedRewardsViewed"]
     189 [-]: NEWCLOSURE R60 P5
     190 [-]: MOVE R0 R4   
     191 [-]: MOVE R1 R19  
     192 [-]: MOVE R0 R8   
     193 [-]: MOVE R0 R5   
     194 [-]: MOVE R0 R0   
     195 [-]: NEWCLOSURE R61 P6
     196 [-]: MOVE R0 R0   
     197 [-]: MOVE R0 R21  
     198 [-]: MOVE R1 R24  
     199 [-]: MOVE R0 R2   
     200 [-]: MOVE R0 R20  
     201 [-]: MOVE R1 R35  
     202 [-]: MOVE R1 R40  
     203 [-]: MOVE R0 R61  
     204 [-]: NEWCLOSURE R62 P7
     205 [-]: MOVE R0 R21  
     206 [-]: MOVE R1 R35  
     207 [-]: MOVE R1 R40  
     208 [-]: MOVE R1 R36  
     209 [-]: MOVE R0 R60  
     210 [-]: MOVE R0 R61  
     211 [-]: MOVE R1 R27  
     212 [-]: MOVE R0 R57  
     213 [-]: MOVE R1 R32  
     214 [-]: NEWCLOSURE R63 P8
     215 [-]: MOVE R1 R54  
     216 [-]: MOVE R0 R21  
     217 [-]: MOVE R0 R0   
     218 [-]: MOVE R1 R35  
     219 [-]: SETGLOBAL R63 K66 ["OnRewardsClaimed"]
     220 [-]: NEWCLOSURE R63 P9
     221 [-]: MOVE R1 R36  
     222 [-]: MOVE R1 R38  
     223 [-]: DUPCLOSURE R64 K67 []
     224 [-]: NEWCLOSURE R65 P11
     225 [-]: MOVE R1 R16  
     226 [-]: MOVE R0 R20  
     227 [-]: MOVE R0 R0   
     228 [-]: MOVE R1 R22  
     229 [-]: MOVE R1 R40  
     230 [-]: MOVE R0 R7   
     231 [-]: MOVE R1 R35  
     232 [-]: MOVE R1 R36  
     233 [-]: MOVE R1 R37  
     234 [-]: MOVE R0 R39  
     235 [-]: MOVE R0 R64  
     236 [-]: MOVE R1 R38  
     237 [-]: MOVE R0 R63  
     238 [-]: MOVE R0 R25  
     239 [-]: MOVE R0 R21  
     240 [-]: MOVE R1 R32  
     241 [-]: MOVE R1 R54  
     242 [-]: MOVE R0 R59  
     243 [-]: MOVE R0 R58  
     244 [-]: NEWCLOSURE R49 P12
     245 [-]: MOVE R1 R26  
     246 [-]: MOVE R0 R0   
     247 [-]: MOVE R0 R14  
     248 [-]: MOVE R1 R46  
     249 [-]: MOVE R0 R65  
     250 [-]: MOVE R0 R57  
     251 [-]: NEWCLOSURE R50 P13
     252 [-]: MOVE R1 R26  
     253 [-]: MOVE R1 R28  
     254 [-]: MOVE R0 R0   
     255 [-]: MOVE R0 R14  
     256 [-]: MOVE R1 R47  
     257 [-]: MOVE R0 R65  
     258 [-]: MOVE R0 R57  
     259 [-]: DUPCLOSURE R66 K68 []
     260 [-]: SETGLOBAL R66 K69 ["ForceReroll"]
     261 [-]: NEWCLOSURE R45 P15
     262 [-]: MOVE R1 R27  
     263 [-]: MOVE R1 R26  
     264 [-]: MOVE R0 R1   
     265 [-]: NEWCLOSURE R66 P16
     266 [-]: MOVE R1 R32  
     267 [-]: MOVE R1 R52  
     268 [-]: MOVE R1 R53  
     269 [-]: MOVE R0 R56  
     270 [-]: SETGLOBAL R66 K70 ["StartEndless"]
     271 [-]: NEWCLOSURE R66 P17
     272 [-]: MOVE R1 R32  
     273 [-]: MOVE R0 R0   
     274 [-]: MOVE R0 R65  
     275 [-]: DUPCLOSURE R67 K71 []
     276 [-]: MOVE R0 R66  
     277 [-]: MOVE R0 R0   
     278 [-]: SETGLOBAL R67 K72 ["SetNormalMode"]
     279 [-]: DUPCLOSURE R67 K73 []
     280 [-]: MOVE R0 R66  
     281 [-]: MOVE R0 R0   
     282 [-]: SETGLOBAL R67 K74 ["SetHardMode"]
     283 [-]: NEWCLOSURE R67 P20
     284 [-]: MOVE R0 R20  
     285 [-]: MOVE R0 R2   
     286 [-]: MOVE R0 R0   
     287 [-]: MOVE R1 R22  
     288 [-]: MOVE R1 R41  
     289 [-]: MOVE R1 R42  
     290 [-]: MOVE R0 R5   
     291 [-]: MOVE R0 R8   
     292 [-]: MOVE R0 R1   
     293 [-]: MOVE R0 R7   
     294 [-]: NEWCLOSURE R48 P21
     295 [-]: MOVE R1 R51  
     296 [-]: MOVE R1 R35  
     297 [-]: MOVE R1 R40  
     298 [-]: MOVE R0 R20  
     299 [-]: MOVE R0 R60  
     300 [-]: MOVE R0 R7   
     301 [-]: MOVE R1 R22  
     302 [-]: MOVE R1 R36  
     303 [-]: NEWCLOSURE R68 P22
     304 [-]: MOVE R1 R29  
     305 [-]: MOVE R0 R0   
     306 [-]: MOVE R1 R28  
     307 [-]: MOVE R0 R4   
     308 [-]: MOVE R1 R30  
     309 [-]: NEWCLOSURE R46 P23
     310 [-]: MOVE R1 R29  
     311 [-]: MOVE R1 R30  
     312 [-]: MOVE R1 R36  
     313 [-]: MOVE R1 R38  
     314 [-]: MOVE R0 R4   
     315 [-]: MOVE R1 R31  
     316 [-]: MOVE R0 R33  
     317 [-]: MOVE R0 R68  
     318 [-]: NEWCLOSURE R47 P24
     319 [-]: MOVE R1 R29  
     320 [-]: MOVE R1 R30  
     321 [-]: MOVE R1 R36  
     322 [-]: MOVE R1 R38  
     323 [-]: MOVE R0 R4   
     324 [-]: MOVE R1 R31  
     325 [-]: MOVE R0 R33  
     326 [-]: MOVE R0 R68  
     327 [-]: NEWCLOSURE R69 P25
     328 [-]: MOVE R0 R0   
     329 [-]: MOVE R1 R28  
     330 [-]: MOVE R1 R50  
     331 [-]: MOVE R1 R49  
     332 [-]: MOVE R1 R55  
     333 [-]: SETGLOBAL R69 K75 ["OnPathSelectionCommited"]
     334 [-]: NEWCLOSURE R69 P26
     335 [-]: MOVE R1 R29  
     336 [-]: MOVE R0 R0   
     337 [-]: MOVE R1 R55  
     338 [-]: SETGLOBAL R69 K76 ["OnPathSelectionConfirmed"]
     339 [-]: NEWCLOSURE R69 P27
     340 [-]: MOVE R1 R29  
     341 [-]: MOVE R1 R55  
     342 [-]: SETGLOBAL R69 K77 ["OnItemSelectionConfirm"]
     343 [-]: NEWCLOSURE R69 P28
     344 [-]: MOVE R1 R29  
     345 [-]: MOVE R0 R0   
     346 [-]: SETGLOBAL R69 K78 ["ChooseItems"]
     347 [-]: NEWCLOSURE R69 P29
     348 [-]: MOVE R1 R29  
     349 [-]: MOVE R1 R22  
     350 [-]: MOVE R0 R0   
     351 [-]: MOVE R1 R28  
     352 [-]: MOVE R1 R18  
     353 [-]: MOVE R0 R1   
     354 [-]: MOVE R1 R19  
     355 [-]: MOVE R1 R30  
     356 [-]: MOVE R0 R5   
     357 [-]: MOVE R0 R6   
     358 [-]: MOVE R1 R31  
     359 [-]: NEWCLOSURE R51 P30
     360 [-]: MOVE R0 R25  
     361 [-]: MOVE R1 R35  
     362 [-]: MOVE R1 R40  
     363 [-]: MOVE R1 R36  
     364 [-]: MOVE R1 R16  
     365 [-]: NEWCLOSURE R70 P31
     366 [-]: MOVE R1 R22  
     367 [-]: MOVE R0 R21  
     368 [-]: MOVE R0 R20  
     369 [-]: MOVE R1 R43  
     370 [-]: NEWCLOSURE R71 P32
     371 [-]: MOVE R0 R2   
     372 [-]: MOVE R1 R34  
     373 [-]: MOVE R0 R0   
     374 [-]: MOVE R0 R15  
     375 [-]: MOVE R1 R18  
     376 [-]: MOVE R1 R19  
     377 [-]: MOVE R1 R17  
     378 [-]: MOVE R0 R4   
     379 [-]: MOVE R1 R22  
     380 [-]: MOVE R0 R3   
     381 [-]: MOVE R1 R24  
     382 [-]: MOVE R1 R23  
     383 [-]: MOVE R1 R44  
     384 [-]: MOVE R0 R67  
     385 [-]: MOVE R0 R69  
     386 [-]: MOVE R0 R70  
     387 [-]: MOVE R0 R57  
     388 [-]: MOVE R0 R65  
     389 [-]: SETGLOBAL R71 K79 ["Initialize"]
     390 [-]: DUPCLOSURE R71 K80 []
     391 [-]: MOVE R0 R5   
     392 [-]: DUPCLOSURE R72 K81 []
     393 [-]: MOVE R0 R9   
     394 [-]: MOVE R0 R10  
     395 [-]: MOVE R0 R12  
     396 [-]: MOVE R0 R13  
     397 [-]: MOVE R0 R25  
     398 [-]: MOVE R0 R7   
     399 [-]: DUPCLOSURE R73 K82 []
     400 [-]: MOVE R0 R25  
     401 [-]: MOVE R0 R7   
     402 [-]: MOVE R0 R72  
     403 [-]: MOVE R0 R0   
     404 [-]: NEWCLOSURE R74 P36
     405 [-]: MOVE R1 R24  
     406 [-]: MOVE R0 R20  
     407 [-]: MOVE R0 R25  
     408 [-]: MOVE R0 R0   
     409 [-]: MOVE R1 R26  
     410 [-]: MOVE R1 R27  
     411 [-]: MOVE R0 R14  
     412 [-]: MOVE R1 R16  
     413 [-]: MOVE R0 R73  
     414 [-]: MOVE R0 R72  
     415 [-]: MOVE R0 R7   
     416 [-]: MOVE R0 R11  
     417 [-]: MOVE R1 R48  
     418 [-]: MOVE R0 R21  
     419 [-]: MOVE R0 R59  
     420 [-]: MOVE R0 R62  
     421 [-]: MOVE R0 R33  
     422 [-]: MOVE R1 R31  
     423 [-]: MOVE R0 R68  
     424 [-]: MOVE R1 R35  
     425 [-]: MOVE R1 R40  
     426 [-]: MOVE R0 R63  
     427 [-]: MOVE R1 R22  
     428 [-]: MOVE R0 R2   
     429 [-]: MOVE R0 R71  
     430 [-]: MOVE R1 R29  
     431 [-]: SETGLOBAL R74 K83 ["Update"]
     432 [-]: NEWCLOSURE R74 P37
     433 [-]: MOVE R1 R34  
     434 [-]: MOVE R0 R2   
     435 [-]: MOVE R1 R29  
     436 [-]: MOVE R0 R0   
     437 [-]: MOVE R0 R21  
     438 [-]: MOVE R0 R25  
     439 [-]: SETGLOBAL R74 K84 ["Shutdown"]
     440 [-]: NEWCLOSURE R44 P38
     441 [-]: MOVE R1 R23  
     442 [-]: MOVE R0 R0   
     443 [-]: NEWCLOSURE R74 P39
     444 [-]: MOVE R1 R44  
     445 [-]: SETGLOBAL R74 K85 ["onViewportSizeChanged"]
     446 [-]: DUPCLOSURE R74 K86 []
     447 [-]: SETGLOBAL R74 K87 ["SupportsThemes"]
     448 [-]: DUPCLOSURE R74 K88 []
     449 [-]: MOVE R0 R20  
     450 [-]: SETGLOBAL R74 K89 ["RewardFocused"]
     451 [-]: DUPCLOSURE R74 K90 []
     452 [-]: MOVE R0 R20  
     453 [-]: SETGLOBAL R74 K91 ["RewardUnfocused"]
     454 [-]: NEWCLOSURE R74 P43
     455 [-]: MOVE R1 R32  
     456 [-]: MOVE R1 R29  
     457 [-]: MOVE R0 R0   
     458 [-]: SETGLOBAL R74 K92 ["PathItemPressed"]
     459 [-]: NEWCLOSURE R74 P44
     460 [-]: MOVE R1 R29  
     461 [-]: SETGLOBAL R74 K93 ["PathItemFocused"]
     462 [-]: NEWCLOSURE R74 P45
     463 [-]: MOVE R1 R29  
     464 [-]: SETGLOBAL R74 K94 ["PathItemUnfocused"]
     465 [-]: NEWCLOSURE R74 P46
     466 [-]: MOVE R1 R29  
     467 [-]: NEWCLOSURE R75 P47
     468 [-]: MOVE R1 R32  
     469 [-]: MOVE R0 R74  
     470 [-]: SETGLOBAL R75 K95 ["FrameAbilityFocused"]
     471 [-]: NEWCLOSURE R75 P48
     472 [-]: MOVE R1 R32  
     473 [-]: MOVE R0 R74  
     474 [-]: SETGLOBAL R75 K96 ["FrameAbilityUnfocused"]
     475 [-]: NEWCLOSURE R75 P49
     476 [-]: MOVE R1 R29  
     477 [-]: NEWCLOSURE R76 P50
     478 [-]: MOVE R1 R32  
     479 [-]: MOVE R0 R75  
     480 [-]: SETGLOBAL R76 K97 ["EvoFocused"]
     481 [-]: NEWCLOSURE R76 P51
     482 [-]: MOVE R1 R32  
     483 [-]: MOVE R0 R75  
     484 [-]: SETGLOBAL R76 K98 ["EvoUnfocused"]
     485 [-]: NEWCLOSURE R76 P52
     486 [-]: MOVE R0 R0   
     487 [-]: MOVE R1 R22  
     488 [-]: DUPCLOSURE R77 K99 []
     489 [-]: MOVE R0 R0   
     490 [-]: MOVE R0 R76  
     491 [-]: SETGLOBAL R77 K100 ["ArrowFocused"]
     492 [-]: DUPCLOSURE R77 K101 []
     493 [-]: MOVE R0 R76  
     494 [-]: SETGLOBAL R77 K102 ["ArrowUnfocused"]
     495 [-]: DUPCLOSURE R77 K103 []
     496 [-]: MOVE R0 R20  
     497 [-]: MOVE R0 R0   
     498 [-]: SETGLOBAL R77 K104 ["ArrowPressed"]
     499 [-]: DUPCLOSURE R77 K105 []
     500 [-]: MOVE R0 R56  
     501 [-]: SETGLOBAL R77 K106 ["OnFrameSelectionBackoutConfirm"]
     502 [-]: NEWCLOSURE R77 P57
     503 [-]: MOVE R1 R32  
     504 [-]: MOVE R1 R27  
     505 [-]: MOVE R1 R26  
     506 [-]: MOVE R0 R0   
     507 [-]: MOVE R1 R28  
     508 [-]: MOVE R0 R56  
     509 [-]: SETGLOBAL R77 K107 ["onKeyDown_MENU_CANCEL"]
     510 [-]: NEWCLOSURE R77 P58
     511 [-]: MOVE R1 R52  
     512 [-]: SETGLOBAL R77 K108 ["SetCloseCallback"]
     513 [-]: CLOSEUPVALS R16
     514 [-]: RETURN R0 0  


; Name:            
; Defined at line: 124
; #Upvalues:       2
; #Parameters:     0
; Is_vararg:       0
; Max Stack Size:  6

       0 [-]: GETIMPORT R0 1 [nil]
       1 [-]: NAMECALL R0 R0 K2 [0x33ABEE92]
       2 [-]: CALL R0 1 1  
       3 [-]: FASTCALL1 62 R0 L0
       4 [-]: MOVE R2 R0   
       5 [-]: GETIMPORT R1 4 [nil]
       6 [-]: CALL R1 1 1  
L 0:   7 [-]: JUMPIF R1 L1 
       8 [-]: GETUPVAL R1 0
       9 [-]: JUMPIFNOT R1 L1
      10 [-]: GETUPVAL R1 1
      11 [-]: JUMPIF R1 L1 
      12 [-]: GETIMPORT R1 6 [nil]
      13 [-]: LOADB R2 1   
      14 [-]: SETTABLEKS R2 R1 K7 ["DuviriEndlessSetupComplete"]
      15 [-]: GETUPVAL R3 0
      16 [-]: NEWTABLE R4 0 1
      17 [-]: LOADK R5 K8 ["false"]
      18 [-]: SETLIST R4 R5 1 [1]
      19 [-]: NAMECALL R1 R0 K9 [0xF56F3887]
      20 [-]: CALL R1 3 0  
L 1:  21 [-]: GETIMPORT R1 1 [nil]
      22 [-]: NAMECALL R1 R1 K10 [0x32302B4A]
      23 [-]: CALL R1 1 0  
      24 [-]: RETURN R0 0  


; Name:            
; Defined at line: 134
; #Upvalues:       3
; #Parameters:     0
; Is_vararg:       0
; Max Stack Size:  6

       0 [-]: GETIMPORT R0 1 [nil]
       1 [-]: LOADK R2 K2 ["RewardPanel"]
       2 [-]: LOADN R3 11  
       3 [-]: GETUPVAL R5 0
       4 [-]: NOT R4 R5    
       5 [-]: JUMPIFNOT R4 L0
       6 [-]: GETUPVAL R5 1
       7 [-]: NOT R4 R5    
L 0:   8 [-]: NAMECALL R0 R0 K3 [0xAADE900E]
       9 [-]: CALL R0 4 0  
      10 [-]: GETIMPORT R0 1 [nil]
      11 [-]: LOADK R2 K4 ["FrameSelect"]
      12 [-]: LOADN R3 11  
      13 [-]: GETUPVAL R4 0
      14 [-]: JUMPIFNOT R4 L1
      15 [-]: GETUPVAL R5 1
      16 [-]: NOT R4 R5    
L 1:  17 [-]: NAMECALL R0 R0 K3 [0xAADE900E]
      18 [-]: CALL R0 4 0  
      19 [-]: GETIMPORT R0 1 [nil]
      20 [-]: LOADK R2 K5 ["Earned"]
      21 [-]: LOADN R3 11  
      22 [-]: GETUPVAL R4 1
      23 [-]: NAMECALL R0 R0 K3 [0xAADE900E]
      24 [-]: CALL R0 4 0  
      25 [-]: GETUPVAL R0 2
      26 [-]: CALL R0 0 0  
      27 [-]: RETURN R0 0  


; Name:            
; Defined at line: 142
; #Upvalues:       4
; #Parameters:     1
; Is_vararg:       0
; Max Stack Size:  8

       0 [-]: LOADK R1 K0 [""]
       1 [-]: GETUPVAL R2 0
       2 [-]: JUMPIFNOT R2 L0
       3 [-]: LOADK R2 K1 ["/Lotus/Language/Duviri/"]
       4 [-]: GETUPVAL R4 1
       5 [-]: GETTABLEKS R3 R4 K2 [0x06D055F9]
       6 [-]: GETUPVAL R4 2
       7 [-]: LOADK R5 K3 ["EndlessSetupIncarnonSelectTitle"]
       8 [-]: LOADK R6 K4 ["EndlessSetupWarframeSelectTitle"]
       9 [-]: CALL R3 3 1  
      10 [-]: CONCAT R1 R2 R3
      11 [-]: JUMP L3
     
L 0:  12 [-]: LOADK R2 K5 ["/Lotus/Language/Labels/"]
      13 [-]: GETUPVAL R4 1
      14 [-]: GETTABLEKS R3 R4 K2 [0x06D055F9]
      15 [-]: GETUPVAL R5 3
      16 [-]: JUMPXEQKN R5 K6 L1 [0]
      17 [-]: LOADB R4 0 +1
L 1:  18 [-]: LOADB R4 1   
L 2:  19 [-]: LOADK R5 K7 ["NormalModeShort"]
      20 [-]: LOADK R6 K8 ["HardModeShort"]
      21 [-]: CALL R3 3 1  
      22 [-]: CONCAT R1 R2 R3
L 3:  23 [-]: GETIMPORT R3 11 [nil]
      24 [-]: FASTCALL1 62 R3 L4
      25 [-]: GETIMPORT R2 13 [nil]
      26 [-]: CALL R2 1 1  
L 4:  27 [-]: JUMPIF R2 L5 
      28 [-]: GETIMPORT R2 11 [nil]
      29 [-]: GETIMPORT R3 15 [nil]
      30 [-]: LOADK R5 K16 ["/Lotus/Language/Duviri/MapNodeEndless"]
      31 [-]: LOADB R6 0   
      32 [-]: NAMECALL R3 R3 K17 [0x42B04007]
      33 [-]: CALL R3 3 1  
      34 [-]: GETIMPORT R4 15 [nil]
      35 [-]: MOVE R6 R1   
      36 [-]: LOADB R7 0   
      37 [-]: NAMECALL R4 R4 K17 [0x42B04007]
      38 [-]: CALL R4 3 1  
      39 [-]: NOT R5 R0    
      40 [-]: CALL R2 3 0  
L 5:  41 [-]: RETURN R0 0  


; Name:            
; Defined at line: 156
; #Upvalues:       4
; #Parameters:     0
; Is_vararg:       0
; Max Stack Size:  2

       0 [-]: GETUPVAL R0 0
       1 [-]: JUMPXEQKN R0 K0 L0 NOT [0]
       2 [-]: GETUPVAL R0 1
       3 [-]: CALL R0 0 0  
       4 [-]: JUMP L1
     
L 0:   5 [-]: GETUPVAL R0 2
       6 [-]: CALL R0 0 0  
L 1:   7 [-]: GETUPVAL R0 3
       8 [-]: LOADB R1 0   
       9 [-]: SETTABLEKS R1 R0 K1 ["NeedReroll"]
      10 [-]: RETURN R0 0  


; Name:            
; Defined at line: 166
; #Upvalues:       8
; #Parameters:     0
; Is_vararg:       0
; Max Stack Size:  9

       0 [-]: GETUPVAL R1 0
       1 [-]: GETTABLEKS R0 R1 K0 ["NeedReroll"]
       2 [-]: JUMPIF R0 L1 
       3 [-]: GETUPVAL R1 1
       4 [-]: GETTABLEKS R0 R1 K1 ["Loaded"]
       5 [-]: JUMPIFNOT R0 L1
       6 [-]: GETIMPORT R1 4 [nil]
       7 [-]: FASTCALL1 62 R1 L0
       8 [-]: GETIMPORT R0 6 [nil]
       9 [-]: CALL R0 1 1  
L 0:  10 [-]: JUMPIF R0 L1 
      11 [-]: GETIMPORT R0 4 [nil]
      12 [-]: LOADK R1 K7 [0.25]
      13 [-]: LOADNIL R2   
      14 [-]: LOADNIL R3   
      15 [-]: GETUPVAL R4 2
      16 [-]: CALL R0 4 0  
L 1:  17 [-]: GETIMPORT R0 9 [nil]
      18 [-]: LOADK R2 K10 ["Earned.RewardLabel"]
      19 [-]: NAMECALL R0 R0 K11 [0xAF5300DC]
      20 [-]: CALL R0 2 0  
      21 [-]: GETIMPORT R0 9 [nil]
      22 [-]: LOADK R2 K12 ["Earned.Reward"]
      23 [-]: NAMECALL R0 R0 K11 [0xAF5300DC]
      24 [-]: CALL R0 2 0  
      25 [-]: GETUPVAL R1 3
      26 [-]: GETTABLEKS R0 R1 K13 ["Timer"]
      27 [-]: JUMPXEQKNIL R0 L2
      28 [-]: GETUPVAL R0 4
      29 [-]: GETUPVAL R3 3
      30 [-]: GETTABLEKS R2 R3 K13 ["Timer"]
      31 [-]: NAMECALL R0 R0 K14 [0x775C858B]
      32 [-]: CALL R0 2 0  
      33 [-]: GETUPVAL R0 3
      34 [-]: LOADNIL R1   
      35 [-]: SETTABLEKS R1 R0 K13 ["Timer"]
L 2:  36 [-]: GETUPVAL R1 3
      37 [-]: GETTABLEKS R0 R1 K15 ["Fx"]
      38 [-]: JUMPXEQKNIL R0 L3
      39 [-]: GETUPVAL R1 3
      40 [-]: GETTABLEKS R0 R1 K15 ["Fx"]
      41 [-]: NAMECALL R0 R0 K16 [0xA2880940]
      42 [-]: CALL R0 1 0  
      43 [-]: GETUPVAL R0 3
      44 [-]: LOADNIL R1   
      45 [-]: SETTABLEKS R1 R0 K15 ["Fx"]
L 3:  46 [-]: GETIMPORT R0 18 [nil]
      47 [-]: GETIMPORT R1 9 [nil]
      48 [-]: LOADK R2 K19 ["Earned"]
      49 [-]: LOADN R3 2   
      50 [-]: NEWTABLE R4 0 1
      51 [-]: LOADN R5 10  
      52 [-]: SETLIST R4 R5 1 [1]
      53 [-]: NEWTABLE R5 0 1
      54 [-]: LOADN R6 0   
      55 [-]: SETLIST R5 R6 1 [1]
      56 [-]: LOADK R6 K20 [0.5]
      57 [-]: LOADN R7 0   
      58 [-]: NEWCLOSURE R8 P0
      59 [-]: MOVE R2 R3   
      60 [-]: MOVE R2 R5   
      61 [-]: MOVE R2 R6   
      62 [-]: MOVE R2 R0   
      63 [-]: MOVE R2 R7   
      64 [-]: CALL R0 8 0  
      65 [-]: RETURN R0 0  


; Name:            
; Defined at line: 193
; #Upvalues:       5
; #Parameters:     2
; Is_vararg:       0
; Max Stack Size:  11

       0 [-]: GETUPVAL R3 0
       1 [-]: GETTABLEKS R2 R3 K0 [0x08681F50]
       2 [-]: GETIMPORT R3 2 [nil]
       3 [-]: GETIMPORT R4 4 [nil]
       4 [-]: GETTABLEKS R5 R0 K5 ["mStoreItem"]
       5 [-]: CALL R4 1 1  
       6 [-]: DUPTABLE R5 7
       7 [-]: DUPTABLE R6 9
       8 [-]: GETTABLEKS R7 R0 K10 ["mItemCount"]
       9 [-]: SETTABLEKS R7 R6 K8 ["Count"]
      10 [-]: SETTABLEKS R6 R5 K6 ["AppendInfo"]
      11 [-]: GETUPVAL R6 1
      12 [-]: LOADNIL R7   
      13 [-]: LOADB R8 1   
      14 [-]: CALL R2 6 1  
      15 [-]: JUMPXEQKNIL R2 L1
      16 [-]: GETTABLEKS R4 R2 K11 ["Type"]
      17 [-]: FASTCALL1 62 R4 L0
      18 [-]: GETIMPORT R3 13 [nil]
      19 [-]: CALL R3 1 1  
L 0:  20 [-]: JUMPIFNOT R3 L2
L 1:  21 [-]: RETURN R2 1  
L 2:  22 [-]: GETTABLEKS R3 R2 K11 ["Type"]
      23 [-]: GETIMPORT R5 15 [nil]
      24 [-]: NAMECALL R3 R3 K16 [0xF2DEAF69]
      25 [-]: CALL R3 2 1  
      26 [-]: JUMPIFNOT R3 L3
      27 [-]: GETTABLEKS R4 R2 K11 ["Type"]
      28 [-]: GETUPVAL R6 2
      29 [-]: NAMECALL R4 R4 K16 [0xF2DEAF69]
      30 [-]: CALL R4 2 1  
      31 [-]: NOT R3 R4    
L 3:  32 [-]: JUMPIFNOT R3 L4
      33 [-]: GETIMPORT R4 19 [nil]
      34 [-]: CALL R4 0 1  
      35 [-]: GETTABLEKS R5 R2 K11 ["Type"]
      36 [-]: SETTABLEKS R5 R4 K20 ["mItemType"]
      37 [-]: GETTABLEKS R5 R2 K8 ["Count"]
      38 [-]: SETTABLEKS R5 R4 K10 ["mItemCount"]
      39 [-]: GETTABLEKS R5 R4 K21 ["mInstance"]
      40 [-]: GETTABLEKS R7 R4 K21 ["mInstance"]
      41 [-]: LOADK R9 K22 [""]
      42 [-]: NAMECALL R7 R7 K23 [0x91FB01D5]
      43 [-]: CALL R7 2 -1 
      44 [-]: NAMECALL R5 R5 K24 [0x86BA2663]
      45 [-]: CALL R5 -1 1 
      46 [-]: SETTABLEKS R5 R4 K25 ["mUpgradeFingerprint"]
      47 [-]: GETUPVAL R6 3
      48 [-]: GETTABLEKS R5 R6 K26 [0xFC31B69E]
      49 [-]: MOVE R6 R4   
      50 [-]: MOVE R7 R1   
      51 [-]: CALL R5 2 1  
      52 [-]: SETTABLEKS R5 R2 K27 ["Card"]
      53 [-]: RETURN R2 1  
L 4:  54 [-]: GETTABLEKS R4 R2 K8 ["Count"]
      55 [-]: LOADN R5 1   
      56 [-]: JUMPIFNOTLT R5 R4 L5
      57 [-]: GETIMPORT R4 2 [nil]
      58 [-]: LOADK R6 K28 ["/Lotus/Language/Items/LargeBatchItem"]
      59 [-]: LOADB R7 0   
      60 [-]: DUPTABLE R8 31
      61 [-]: GETTABLEKS R9 R2 K32 ["Name"]
      62 [-]: SETTABLEKS R9 R8 K29 ["ITEM"]
      63 [-]: GETUPVAL R10 4
      64 [-]: GETTABLEKS R9 R10 K33 [0x1142C7A8]
      65 [-]: GETTABLEKS R10 R2 K8 ["Count"]
      66 [-]: CALL R9 1 1  
      67 [-]: SETTABLEKS R9 R8 K30 ["NUM"]
      68 [-]: NAMECALL R4 R4 K34 [0x42B04007]
      69 [-]: CALL R4 4 1  
      70 [-]: SETTABLEKS R4 R2 K32 ["Name"]
L 5:  71 [-]: RETURN R2 1  


; Name:            
; Defined at line: 214
; #Upvalues:       8
; #Parameters:     0
; Is_vararg:       0
; Max Stack Size:  15

       0 [-]: GETUPVAL R1 0
       1 [-]: GETTABLEKS R0 R1 K0 [0x659D451F]
       2 [-]: GETIMPORT R1 2 [nil]
       3 [-]: CALL R0 1 0  
       4 [-]: GETUPVAL R1 1
       5 [-]: GETTABLEKS R0 R1 K3 ["Fx"]
       6 [-]: JUMPXEQKNIL R0 L0
       7 [-]: GETUPVAL R1 1
       8 [-]: GETTABLEKS R0 R1 K3 ["Fx"]
       9 [-]: NAMECALL R0 R0 K4 [0xA2880940]
      10 [-]: CALL R0 1 0  
      11 [-]: GETUPVAL R0 1
      12 [-]: LOADNIL R1   
      13 [-]: SETTABLEKS R1 R0 K3 ["Fx"]
L 0:  14 [-]: GETUPVAL R0 2
      15 [-]: LOADK R2 K5 [0.34999999999999998]
      16 [-]: DUPCLOSURE R3 K6 []
      17 [-]: MOVE R2 R1   
      18 [-]: MOVE R2 R0   
      19 [-]: MOVE R2 R3   
      20 [-]: NAMECALL R0 R0 K7 [0xBD2E96EA]
      21 [-]: CALL R0 3 0  
      22 [-]: GETIMPORT R0 9 [nil]
      23 [-]: LOADK R2 K10 ["/Lotus/Language/Duviri/EndlessSetupClaimedTitle"]
      24 [-]: LOADB R3 0   
      25 [-]: NAMECALL R0 R0 K11 [0x42B04007]
      26 [-]: CALL R0 3 1  
      27 [-]: GETUPVAL R2 1
      28 [-]: GETTABLEKS R1 R2 K12 ["Num"]
      29 [-]: LOADN R2 1   
      30 [-]: JUMPIFNOTLT R2 R1 L1
      31 [-]: MOVE R1 R0   
      32 [-]: LOADK R2 K13 [" ("]
      33 [-]: GETUPVAL R8 0
      34 [-]: GETTABLEKS R7 R8 K14 [0x1142C7A8]
      35 [-]: GETUPVAL R9 1
      36 [-]: GETTABLEKS R8 R9 K15 ["CurrIndex"]
      37 [-]: CALL R7 1 1  
      38 [-]: MOVE R3 R7   
      39 [-]: LOADK R4 K16 ["/"]
      40 [-]: GETUPVAL R8 0
      41 [-]: GETTABLEKS R7 R8 K14 [0x1142C7A8]
      42 [-]: GETUPVAL R9 1
      43 [-]: GETTABLEKS R8 R9 K12 ["Num"]
      44 [-]: CALL R7 1 1  
      45 [-]: MOVE R5 R7   
      46 [-]: LOADK R6 K17 [")"]
      47 [-]: CONCAT R0 R1 R6
L 1:  48 [-]: GETIMPORT R1 9 [nil]
      49 [-]: LOADK R3 K18 ["Earned.Title"]
      50 [-]: LOADN R4 29  
      51 [-]: MOVE R5 R0   
      52 [-]: NAMECALL R1 R1 K19 [0x5F56EEAB]
      53 [-]: CALL R1 4 0  
      54 [-]: GETIMPORT R1 9 [nil]
      55 [-]: LOADK R3 K20 ["Earned.TitleBg"]
      56 [-]: LOADN R4 12  
      57 [-]: GETIMPORT R6 9 [nil]
      58 [-]: LOADK R8 K18 ["Earned.Title"]
      59 [-]: LOADN R9 33  
      60 [-]: NAMECALL R6 R6 K22 [0x91A24E4B]
      61 [-]: CALL R6 3 1  
      62 [-]: ADDK R5 R6 K21 [10]
      63 [-]: NAMECALL R1 R1 K23 [0x67BC869F]
      64 [-]: CALL R1 4 0  
      65 [-]: GETUPVAL R2 1
      66 [-]: GETTABLEKS R1 R2 K15 ["CurrIndex"]
      67 [-]: GETUPVAL R4 1
      68 [-]: GETTABLEKS R3 R4 K24 ["Elements"]
      69 [-]: LENGTH R2 R3 
      70 [-]: JUMPIFNOTLE R1 R2 L5
      71 [-]: GETUPVAL R2 1
      72 [-]: GETTABLEKS R1 R2 K25 ["ShowingElement"]
      73 [-]: GETUPVAL R4 1
      74 [-]: GETTABLEKS R3 R4 K24 ["Elements"]
      75 [-]: GETUPVAL R5 1
      76 [-]: GETTABLEKS R4 R5 K15 ["CurrIndex"]
      77 [-]: GETTABLE R2 R3 R4
      78 [-]: SETTABLEKS R2 R1 K26 ["RewardInfos"]
      79 [-]: GETUPVAL R3 4
      80 [-]: GETTABLEKS R2 R3 K27 ["Grid"]
      81 [-]: GETTABLEKS R1 R2 K28 ["mElementDrawCallback"]
      82 [-]: GETUPVAL R3 1
      83 [-]: GETTABLEKS R2 R3 K25 ["ShowingElement"]
      84 [-]: CALL R1 1 0  
      85 [-]: GETIMPORT R1 9 [nil]
      86 [-]: GETUPVAL R5 1
      87 [-]: GETTABLEKS R4 R5 K25 ["ShowingElement"]
      88 [-]: GETTABLEKS R3 R4 K29 ["mClipName"]
      89 [-]: LOADK R4 K30 ["LineStraightRight"]
      90 [-]: LOADN R5 11  
      91 [-]: LOADB R6 0   
      92 [-]: NAMECALL R1 R1 K31 [0xC0A3774B]
      93 [-]: CALL R1 5 0  
      94 [-]: GETIMPORT R1 9 [nil]
      95 [-]: GETUPVAL R5 1
      96 [-]: GETTABLEKS R4 R5 K25 ["ShowingElement"]
      97 [-]: GETTABLEKS R3 R4 K29 ["mClipName"]
      98 [-]: LOADK R4 K32 ["IconFade"]
      99 [-]: LOADN R5 11  
     100 [-]: LOADB R6 0   
     101 [-]: NAMECALL R1 R1 K31 [0xC0A3774B]
     102 [-]: CALL R1 5 0  
     103 [-]: GETIMPORT R1 9 [nil]
     104 [-]: GETUPVAL R5 1
     105 [-]: GETTABLEKS R4 R5 K25 ["ShowingElement"]
     106 [-]: GETTABLEKS R3 R4 K29 ["mClipName"]
     107 [-]: LOADK R4 K33 ["EarnedState"]
     108 [-]: LOADN R5 11  
     109 [-]: LOADB R6 0   
     110 [-]: NAMECALL R1 R1 K31 [0xC0A3774B]
     111 [-]: CALL R1 5 0  
     112 [-]: GETUPVAL R3 1
     113 [-]: GETTABLEKS R2 R3 K34 ["StartIndex"]
     114 [-]: GETUPVAL R5 1
     115 [-]: GETTABLEKS R4 R5 K15 ["CurrIndex"]
     116 [-]: SUBK R3 R4 K35 [1]
     117 [-]: ADD R1 R2 R3 
     118 [-]: GETUPVAL R3 5
     119 [-]: GETUPVAL R4 6
     120 [-]: GETTABLE R2 R3 R4
     121 [-]: GETTABLEKS R5 R2 K36 ["mPendingRewards"]
     122 [-]: LENGTH R4 R5 
     123 [-]: JUMPIFLT R4 R1 L2
     124 [-]: LOADB R3 0 +1
L 2: 125 [-]: LOADB R3 1   
L 3: 126 [-]: GETIMPORT R4 9 [nil]
     127 [-]: GETUPVAL R8 1
     128 [-]: GETTABLEKS R7 R8 K25 ["ShowingElement"]
     129 [-]: GETTABLEKS R6 R7 K29 ["mClipName"]
     130 [-]: LOADK R7 K37 ["Tier"]
     131 [-]: LOADN R8 11  
     132 [-]: NOT R9 R3    
     133 [-]: NAMECALL R4 R4 K31 [0xC0A3774B]
     134 [-]: CALL R4 5 0  
     135 [-]: GETIMPORT R4 9 [nil]
     136 [-]: GETUPVAL R8 1
     137 [-]: GETTABLEKS R7 R8 K25 ["ShowingElement"]
     138 [-]: GETTABLEKS R6 R7 K29 ["mClipName"]
     139 [-]: LOADK R7 K37 ["Tier"]
     140 [-]: LOADN R8 12  
     141 [-]: LOADN R9 46  
     142 [-]: NAMECALL R4 R4 K38 [0xF64B7262]
     143 [-]: CALL R4 5 0  
     144 [-]: GETIMPORT R4 9 [nil]
     145 [-]: GETUPVAL R8 1
     146 [-]: GETTABLEKS R7 R8 K25 ["ShowingElement"]
     147 [-]: GETTABLEKS R6 R7 K29 ["mClipName"]
     148 [-]: LOADK R7 K37 ["Tier"]
     149 [-]: LOADN R8 13  
     150 [-]: LOADN R9 37  
     151 [-]: NAMECALL R4 R4 K38 [0xF64B7262]
     152 [-]: CALL R4 5 0  
     153 [-]: GETIMPORT R4 9 [nil]
     154 [-]: GETUPVAL R8 1
     155 [-]: GETTABLEKS R7 R8 K25 ["ShowingElement"]
     156 [-]: GETTABLEKS R6 R7 K29 ["mClipName"]
     157 [-]: LOADK R7 K39 ["Tier.Num"]
     158 [-]: LOADN R8 29  
     159 [-]: GETUPVAL R10 0
     160 [-]: GETTABLEKS R9 R10 K14 [0x1142C7A8]
     161 [-]: MOVE R10 R1  
     162 [-]: CALL R9 1 -1 
     163 [-]: NAMECALL R4 R4 K40 [0xE261AA96]
     164 [-]: CALL R4 -1 0 
     165 [-]: GETIMPORT R4 9 [nil]
     166 [-]: GETUPVAL R8 1
     167 [-]: GETTABLEKS R7 R8 K25 ["ShowingElement"]
     168 [-]: GETTABLEKS R6 R7 K29 ["mClipName"]
     169 [-]: LOADK R7 K37 ["Tier"]
     170 [-]: LOADN R8 1   
     171 [-]: LOADN R9 53  
     172 [-]: NAMECALL R4 R4 K38 [0xF64B7262]
     173 [-]: CALL R4 5 0  
     174 [-]: GETUPVAL R7 1
     175 [-]: GETTABLEKS R6 R7 K25 ["ShowingElement"]
     176 [-]: GETTABLEKS R5 R6 K26 ["RewardInfos"]
     177 [-]: GETTABLEN R4 R5 1
     178 [-]: GETTABLEKS R7 R4 K41 ["Card"]
     179 [-]: FASTCALL1 62 R7 L4
     180 [-]: GETIMPORT R6 43 [nil]
     181 [-]: CALL R6 1 1  
L 4: 182 [-]: NOT R5 R6    
     183 [-]: GETIMPORT R6 9 [nil]
     184 [-]: LOADK R8 K44 ["Earned.Name"]
     185 [-]: LOADN R9 11  
     186 [-]: NOT R10 R5   
     187 [-]: NAMECALL R6 R6 K45 [0xAADE900E]
     188 [-]: CALL R6 4 0  
     189 [-]: GETIMPORT R6 9 [nil]
     190 [-]: LOADK R8 K46 ["Earned.NameBg"]
     191 [-]: LOADN R9 11  
     192 [-]: NOT R10 R5   
     193 [-]: NAMECALL R6 R6 K45 [0xAADE900E]
     194 [-]: CALL R6 4 0  
     195 [-]: GETIMPORT R6 9 [nil]
     196 [-]: LOADK R8 K44 ["Earned.Name"]
     197 [-]: LOADN R9 29  
     198 [-]: GETTABLEKS R10 R4 K47 ["Name"]
     199 [-]: NAMECALL R6 R6 K19 [0x5F56EEAB]
     200 [-]: CALL R6 4 0  
     201 [-]: GETIMPORT R6 9 [nil]
     202 [-]: LOADK R8 K46 ["Earned.NameBg"]
     203 [-]: LOADN R9 12  
     204 [-]: GETIMPORT R11 9 [nil]
     205 [-]: LOADK R13 K44 ["Earned.Name"]
     206 [-]: LOADN R14 33 
     207 [-]: NAMECALL R11 R11 K22 [0x91A24E4B]
     208 [-]: CALL R11 3 1 
     209 [-]: ADDK R10 R11 K21 [10]
     210 [-]: NAMECALL R6 R6 K23 [0x67BC869F]
     211 [-]: CALL R6 4 0  
L 5: 212 [-]: GETUPVAL R1 1
     213 [-]: GETUPVAL R2 2
     214 [-]: LOADN R4 4   
     215 [-]: DUPCLOSURE R5 K48 []
     216 [-]: MOVE R2 R1   
     217 [-]: MOVE R2 R7   
     218 [-]: NAMECALL R2 R2 K7 [0xBD2E96EA]
     219 [-]: CALL R2 3 1  
     220 [-]: SETTABLEKS R2 R1 K49 ["Timer"]
     221 [-]: RETURN R0 0  


; Name:            
; Defined at line: 275
; #Upvalues:       9
; #Parameters:     0
; Is_vararg:       0
; Max Stack Size:  28

       0 [-]: GETIMPORT R1 2 [nil]
       1 [-]: FASTCALL1 62 R1 L0
       2 [-]: GETIMPORT R0 4 [nil]
       3 [-]: CALL R0 1 1  
L 0:   4 [-]: JUMPIF R0 L1 
       5 [-]: GETIMPORT R0 2 [nil]
       6 [-]: LOADK R1 K5 [0.25]
       7 [-]: LOADNIL R2   
       8 [-]: LOADNIL R3   
       9 [-]: LOADNIL R4   
      10 [-]: CALL R0 4 0  
L 1:  11 [-]: GETUPVAL R0 0
      12 [-]: NEWTABLE R1 0 0
      13 [-]: SETTABLEKS R1 R0 K6 ["Elements"]
      14 [-]: GETUPVAL R0 0
      15 [-]: LOADN R1 1   
      16 [-]: SETTABLEKS R1 R0 K7 ["CurrIndex"]
      17 [-]: GETUPVAL R1 1
      18 [-]: GETUPVAL R2 2
      19 [-]: GETTABLE R0 R1 R2
      20 [-]: GETUPVAL R4 0
      21 [-]: GETTABLEKS R3 R4 K8 ["StartIndex"]
      22 [-]: GETUPVAL R6 0
      23 [-]: GETTABLEKS R5 R6 K10 ["Num"]
      24 [-]: SUBK R4 R5 K9 [1]
      25 [-]: ADD R2 R3 R4 
      26 [-]: GETTABLEKS R4 R0 K11 ["mPendingRewards"]
      27 [-]: LENGTH R3 R4 
      28 [-]: SUB R1 R2 R3 
      29 [-]: NEWTABLE R2 0 0
      30 [-]: LOADN R3 0   
      31 [-]: JUMPIFNOTLT R3 R1 L22
      32 [-]: GETIMPORT R3 13 [nil]
      33 [-]: GETUPVAL R5 3
      34 [-]: GETTABLEKS R4 R5 K14 ["mRepeatedRewards"]
      35 [-]: CALL R3 1 1  
      36 [-]: GETIMPORT R4 17 [nil]
      37 [-]: GETUPVAL R6 0
      38 [-]: GETTABLEKS R5 R6 K18 ["Rewards"]
      39 [-]: CALL R4 1 1  
      40 [-]: FASTCALL1 62 R3 L2
      41 [-]: MOVE R6 R3   
      42 [-]: GETIMPORT R5 4 [nil]
      43 [-]: CALL R5 1 1  
L 2:  44 [-]: JUMPIF R5 L22
      45 [-]: JUMPXEQKNIL R4 L22
      46 [-]: NEWTABLE R5 0 0
      47 [-]: LOADN R8 0   
      48 [-]: NAMECALL R6 R3 K19 [0x509D9F9E]
      49 [-]: CALL R6 2 1  
      50 [-]: GETIMPORT R7 21 [nil]
      51 [-]: GETTABLEKS R8 R4 K22 ["InventoryChanges"]
      52 [-]: CALL R7 1 3  
      53 [-]: FORGPREP_NEXT R7 L21
L 3:  54 [-]: FASTCALL1 40 R11 L4
      55 [-]: MOVE R13 R11 
      56 [-]: GETIMPORT R12 24 [nil]
      57 [-]: CALL R12 1 1 
L 4:  58 [-]: JUMPXEQKS R12 K25 L12 NOT ["table"]
      59 [-]: GETIMPORT R12 21 [nil]
      60 [-]: MOVE R13 R11 
      61 [-]: CALL R12 1 3 
      62 [-]: FORGPREP_NEXT R12 L11
L 5:  63 [-]: GETIMPORT R17 28 [nil]
      64 [-]: GETTABLEKS R18 R16 K29 ["ItemType"]
      65 [-]: LOADK R19 K30 ["/Lotus"]
      66 [-]: LOADK R20 K31 ["/Lotus/StoreItems"]
      67 [-]: LOADN R21 1  
      68 [-]: CALL R17 4 1 
      69 [-]: GETIMPORT R18 13 [nil]
      70 [-]: MOVE R19 R17 
      71 [-]: CALL R18 1 1 
      72 [-]: FASTCALL1 62 R18 L6
      73 [-]: MOVE R20 R18 
      74 [-]: GETIMPORT R19 4 [nil]
      75 [-]: CALL R19 1 1 
L 6:  76 [-]: JUMPIF R19 L11
      77 [-]: LOADN R21 0  
      78 [-]: SUBK R19 R6 K9 [1]
      79 [-]: LOADN R20 1  
      80 [-]: FORNPREP R19 L11
L 7:  81 [-]: LOADN R24 0  
      82 [-]: MOVE R25 R21 
      83 [-]: NAMECALL R22 R3 K32 [0x04D63414]
      84 [-]: CALL R22 3 1 
      85 [-]: FASTCALL1 62 R22 L8
      86 [-]: MOVE R24 R22 
      87 [-]: GETIMPORT R23 4 [nil]
      88 [-]: CALL R23 1 1 
L 8:  89 [-]: JUMPIF R23 L10
      90 [-]: GETTABLEKS R23 R22 K33 ["mStoreItem"]
      91 [-]: JUMPIFNOTEQ R23 R18 L10
      92 [-]: MOVE R24 R2  
      93 [-]: GETUPVAL R25 4
      94 [-]: MOVE R26 R22 
      95 [-]: MOVE R27 R21 
      96 [-]: CALL R25 2 -1
      97 [-]: FASTCALL 52 L9
      98 [-]: GETIMPORT R23 36 [nil]
      99 [-]: CALL R23 -1 0
L 9: 100 [-]: JUMP L11
    
L10: 101 [-]: FORNLOOP R19 L7
L11: 102 [-]: FORGLOOP R12 L5 2
     103 [-]: JUMP L21
    
L12: 104 [-]: JUMPXEQKS R10 K37 L13 ["RegularCredits"]
     105 [-]: JUMPXEQKS R10 K38 L21 NOT ["FusionPoints"]
L13: 106 [-]: LOADN R14 0  
     107 [-]: SUBK R12 R6 K9 [1]
     108 [-]: LOADN R13 1  
     109 [-]: FORNPREP R12 L21
L14: 110 [-]: LOADN R17 0  
     111 [-]: MOVE R18 R14 
     112 [-]: NAMECALL R15 R3 K32 [0x04D63414]
     113 [-]: CALL R15 3 1 
     114 [-]: FASTCALL1 62 R15 L15
     115 [-]: MOVE R17 R15 
     116 [-]: GETIMPORT R16 4 [nil]
     117 [-]: CALL R16 1 1 
L15: 118 [-]: JUMPIF R16 L20
     119 [-]: JUMPXEQKS R10 K37 L16 NOT ["RegularCredits"]
     120 [-]: GETTABLEKS R16 R15 K33 ["mStoreItem"]
     121 [-]: NAMECALL R16 R16 K39 [0xFE9EB1A5]
     122 [-]: CALL R16 1 1 
     123 [-]: LOADN R17 14 
     124 [-]: JUMPIFEQ R16 R17 L17
L16: 125 [-]: JUMPXEQKS R10 K38 L20 NOT ["FusionPoints"]
     126 [-]: GETTABLEKS R16 R15 K33 ["mStoreItem"]
     127 [-]: NAMECALL R16 R16 K39 [0xFE9EB1A5]
     128 [-]: CALL R16 1 1 
     129 [-]: LOADN R17 35 
     130 [-]: JUMPIFNOTEQ R16 R17 L20
L17: 131 [-]: LOADN R17 -1 
     132 [-]: GETTABLEKS R18 R15 K33 ["mStoreItem"]
     133 [-]: NAMECALL R18 R18 K40 [0x4E485A6F]
     134 [-]: CALL R18 1 1 
     135 [-]: MUL R16 R17 R18
     136 [-]: GETIMPORT R17 42 [nil]
     137 [-]: MOVE R18 R11 
     138 [-]: CALL R17 1 1 
L18: 139 [-]: JUMPIFNOTLE R16 R17 L20
     140 [-]: MOVE R19 R2  
     141 [-]: GETUPVAL R20 4
     142 [-]: MOVE R21 R15 
     143 [-]: MOVE R22 R14 
     144 [-]: CALL R20 2 -1
     145 [-]: FASTCALL 52 L19
     146 [-]: GETIMPORT R18 36 [nil]
     147 [-]: CALL R18 -1 0
L19: 148 [-]: SUB R17 R17 R16
     149 [-]: JUMP L20
    
     150 [-]: JUMPBACK L18 
L20: 151 [-]: FORNLOOP R12 L14
L21: 152 [-]: FORGLOOP R7 L3 2
L22: 153 [-]: GETUPVAL R6 0
     154 [-]: GETTABLEKS R5 R6 K8 ["StartIndex"]
     155 [-]: GETUPVAL R8 0
     156 [-]: GETTABLEKS R7 R8 K8 ["StartIndex"]
     157 [-]: GETUPVAL R9 0
     158 [-]: GETTABLEKS R8 R9 K10 ["Num"]
     159 [-]: ADD R6 R7 R8 
     160 [-]: SUBK R3 R6 K9 [1]
     161 [-]: LOADN R4 1   
     162 [-]: FORNPREP R3 L29
L23: 163 [-]: GETTABLEKS R7 R0 K11 ["mPendingRewards"]
     164 [-]: LENGTH R6 R7 
     165 [-]: JUMPIFLT R6 R5 L29
     166 [-]: GETTABLEKS R7 R0 K11 ["mPendingRewards"]
     167 [-]: GETTABLE R6 R7 R5
     168 [-]: NEWTABLE R7 0 0
     169 [-]: LOADN R10 1  
     170 [-]: GETTABLEKS R11 R6 K43 ["mRewards"]
     171 [-]: LENGTH R8 R11
     172 [-]: LOADN R9 1   
     173 [-]: FORNPREP R8 L27
L24: 174 [-]: GETTABLEKS R13 R6 K43 ["mRewards"]
     175 [-]: GETTABLE R12 R13 R10
     176 [-]: GETTABLEKS R11 R12 K33 ["mStoreItem"]
     177 [-]: FASTCALL1 62 R11 L25
     178 [-]: MOVE R13 R11 
     179 [-]: GETIMPORT R12 4 [nil]
     180 [-]: CALL R12 1 1 
L25: 181 [-]: JUMPIF R12 L26
     182 [-]: MOVE R13 R7  
     183 [-]: GETUPVAL R14 4
     184 [-]: GETTABLEKS R16 R6 K43 ["mRewards"]
     185 [-]: GETTABLE R15 R16 R10
     186 [-]: CALL R14 1 -1
     187 [-]: FASTCALL 52 L26
     188 [-]: GETIMPORT R12 36 [nil]
     189 [-]: CALL R12 -1 0
L26: 190 [-]: FORNLOOP R8 L24
L27: 191 [-]: GETUPVAL R10 0
     192 [-]: GETTABLEKS R9 R10 K6 ["Elements"]
     193 [-]: FASTCALL2 52 R9 R7 L28
     194 [-]: MOVE R10 R7  
     195 [-]: GETIMPORT R8 36 [nil]
     196 [-]: CALL R8 2 0  
L28: 197 [-]: FORNLOOP R3 L23
L29: 198 [-]: GETIMPORT R3 21 [nil]
     199 [-]: MOVE R4 R2   
     200 [-]: CALL R3 1 3  
     201 [-]: FORGPREP_NEXT R3 L31
L30: 202 [-]: GETUPVAL R10 0
     203 [-]: GETTABLEKS R9 R10 K6 ["Elements"]
     204 [-]: NEWTABLE R10 0 1
     205 [-]: MOVE R11 R7  
     206 [-]: SETLIST R10 R11 1 [1]
     207 [-]: FASTCALL2 52 R9 R10 L31
     208 [-]: GETIMPORT R8 36 [nil]
     209 [-]: CALL R8 2 0  
L31: 210 [-]: FORGLOOP R3 L30 2
     211 [-]: GETIMPORT R3 45 [nil]
     212 [-]: LOADK R5 K46 ["Earned"]
     213 [-]: LOADN R6 10  
     214 [-]: LOADN R7 0   
     215 [-]: NAMECALL R3 R3 K47 [0x67BC869F]
     216 [-]: CALL R3 4 0  
     217 [-]: GETIMPORT R3 49 [nil]
     218 [-]: GETIMPORT R4 45 [nil]
     219 [-]: LOADK R5 K46 ["Earned"]
     220 [-]: LOADN R6 2   
     221 [-]: NEWTABLE R7 0 1
     222 [-]: LOADN R8 10  
     223 [-]: SETLIST R7 R8 1 [1]
     224 [-]: NEWTABLE R8 0 1
     225 [-]: LOADN R9 100 
     226 [-]: SETLIST R8 R9 1 [1]
     227 [-]: LOADK R9 K50 [0.34999999999999998]
     228 [-]: CALL R3 6 0  
     229 [-]: GETUPVAL R3 5
     230 [-]: CALL R3 0 0  
     231 [-]: LOADB R3 1   
     232 [-]: SETUPVAL R3 6
     233 [-]: GETUPVAL R3 7
     234 [-]: CALL R3 0 0  
     235 [-]: GETUPVAL R3 0
     236 [-]: LOADNIL R4   
     237 [-]: SETTABLEKS R4 R3 K18 ["Rewards"]
     238 [-]: LOADB R3 0   
     239 [-]: SETUPVAL R3 8
     240 [-]: RETURN R0 0  


; Name:            
; Defined at line: 360
; #Upvalues:       4
; #Parameters:     2
; Is_vararg:       0
; Max Stack Size:  6

       0 [-]: GETIMPORT R3 2 [nil]
       1 [-]: FASTCALL1 62 R3 L0
       2 [-]: GETIMPORT R2 4 [nil]
       3 [-]: CALL R2 1 1  
L 0:   4 [-]: JUMPIF R2 L1 
       5 [-]: GETIMPORT R2 2 [nil]
       6 [-]: LOADK R4 K5 ["ShowBlockingMessage"]
       7 [-]: LOADK R5 K6 ["0"]
       8 [-]: NAMECALL R2 R2 K7 [0xE4162EED]
       9 [-]: CALL R2 3 0  
L 1:  10 [-]: LOADNIL R2   
      11 [-]: SETUPVAL R2 0
      12 [-]: JUMPIF R0 L2 
      13 [-]: GETUPVAL R2 1
      14 [-]: LOADB R3 0   
      15 [-]: SETTABLEKS R3 R2 K8 ["HasClaim"]
      16 [-]: GETUPVAL R3 2
      17 [-]: GETTABLEKS R2 R3 K9 [0xA53F5E12]
      18 [-]: LOADK R3 K10 ["/Lotus/Language/Duviri/EndlessSetupClaimFailed"]
      19 [-]: CALL R2 1 0  
      20 [-]: GETIMPORT R2 12 [nil]
      21 [-]: NAMECALL R2 R2 K13 [0x32302B4A]
      22 [-]: CALL R2 1 0  
      23 [-]: RETURN R0 0  
L 2:  24 [-]: GETUPVAL R2 1
      25 [-]: SETTABLEKS R1 R2 K14 ["Rewards"]
      26 [-]: GETIMPORT R2 16 [nil]
      27 [-]: NAMECALL R2 R2 K17 [0x66A70FFD]
      28 [-]: CALL R2 1 1  
      29 [-]: SETUPVAL R2 3
      30 [-]: RETURN R0 0  


; Name:            
; Defined at line: 380
; #Upvalues:       2
; #Parameters:     1
; Is_vararg:       0
; Max Stack Size:  11

       0 [-]: GETUPVAL R2 0
       1 [-]: GETTABLEKS R1 R2 K0 ["mChoices"]
       2 [-]: LOADN R4 1   
       3 [-]: GETUPVAL R5 1
       4 [-]: LENGTH R2 R5 
       5 [-]: LOADN R3 1   
       6 [-]: FORNPREP R2 L3
L 0:   7 [-]: GETUPVAL R6 1
       8 [-]: GETTABLE R5 R6 R4
       9 [-]: GETTABLE R6 R1 R5
      10 [-]: FASTCALL1 62 R6 L1
      11 [-]: MOVE R8 R6   
      12 [-]: GETIMPORT R7 2 [nil]
      13 [-]: CALL R7 1 1  
L 1:  14 [-]: JUMPIF R7 L2 
      15 [-]: MOVE R8 R0   
      16 [-]: GETTABLEKS R9 R6 K3 ["mChoiceParent"]
      17 [-]: NAMECALL R9 R9 K4 [0xED4E0128]
      18 [-]: CALL R9 1 -1 
      19 [-]: FASTCALL 52 L2
      20 [-]: GETIMPORT R7 7 [nil]
      21 [-]: CALL R7 -1 0 
L 2:  22 [-]: FORNLOOP R2 L0
L 3:  23 [-]: RETURN R0 0  


; Name:            
; Defined at line: 391
; #Upvalues:       0
; #Parameters:     2
; Is_vararg:       0
; Max Stack Size:  14

       0 [-]: NEWTABLE R2 0 0
       1 [-]: LOADN R5 1   
       2 [-]: LENGTH R3 R0 
       3 [-]: LOADN R4 1   
       4 [-]: FORNPREP R3 L5
L 0:   5 [-]: GETIMPORT R6 1 [nil]
       6 [-]: GETTABLE R7 R0 R5
       7 [-]: CALL R6 1 1  
       8 [-]: LOADN R9 1   
       9 [-]: LENGTH R7 R1 
      10 [-]: LOADN R8 1   
      11 [-]: FORNPREP R7 L4
L 1:  12 [-]: GETTABLE R10 R1 R9
      13 [-]: GETTABLEKS R11 R10 K2 ["mTag"]
      14 [-]: JUMPIFNOTEQ R11 R6 L3
      15 [-]: FASTCALL2 52 R2 R9 L2
      16 [-]: MOVE R12 R2  
      17 [-]: MOVE R13 R9  
      18 [-]: GETIMPORT R11 5 [nil]
      19 [-]: CALL R11 2 0 
L 2:  20 [-]: JUMP L4
     
L 3:  21 [-]: FORNLOOP R7 L1
L 4:  22 [-]: FORNLOOP R3 L0
L 5:  23 [-]: RETURN R2 1  


; Name:            
; Defined at line: 406
; #Upvalues:       19
; #Parameters:     0
; Is_vararg:       0
; Max Stack Size:  21

       0 [-]: GETIMPORT R0 1 [nil]
       1 [-]: NAMECALL R0 R0 K2 [0xEFC55311]
       2 [-]: CALL R0 1 1  
       3 [-]: SETUPVAL R0 0
       4 [-]: GETUPVAL R1 1
       5 [-]: GETTABLEKS R0 R1 K3 ["NormalBtn"]
       6 [-]: GETUPVAL R2 2
       7 [-]: GETTABLEKS R1 R2 K4 [0x06D055F9]
       8 [-]: GETUPVAL R3 0
       9 [-]: JUMPXEQKN R3 K5 L0 [0]
      10 [-]: LOADB R2 0 +1
L 0:  11 [-]: LOADB R2 1   
L 1:  12 [-]: GETUPVAL R4 3
      13 [-]: GETTABLEKS R3 R4 K6 ["FloatingContentHighlight"]
      14 [-]: LOADNIL R4   
      15 [-]: CALL R1 3 1  
      16 [-]: SETTABLEKS R1 R0 K7 ["mActiveColor"]
      17 [-]: GETUPVAL R1 1
      18 [-]: GETTABLEKS R0 R1 K8 ["HardBtn"]
      19 [-]: GETUPVAL R2 2
      20 [-]: GETTABLEKS R1 R2 K4 [0x06D055F9]
      21 [-]: GETUPVAL R3 0
      22 [-]: JUMPXEQKN R3 K9 L2 [1]
      23 [-]: LOADB R2 0 +1
L 2:  24 [-]: LOADB R2 1   
L 3:  25 [-]: GETUPVAL R4 3
      26 [-]: GETTABLEKS R3 R4 K6 ["FloatingContentHighlight"]
      27 [-]: LOADNIL R4   
      28 [-]: CALL R1 3 1  
      29 [-]: SETTABLEKS R1 R0 K7 ["mActiveColor"]
      30 [-]: GETUPVAL R1 1
      31 [-]: GETTABLEKS R0 R1 K3 ["NormalBtn"]
      32 [-]: NAMECALL R0 R0 K10 [0x087CBD3F]
      33 [-]: CALL R0 1 0  
      34 [-]: GETUPVAL R1 1
      35 [-]: GETTABLEKS R0 R1 K8 ["HardBtn"]
      36 [-]: NAMECALL R0 R0 K10 [0x087CBD3F]
      37 [-]: CALL R0 1 0  
      38 [-]: GETUPVAL R1 5
      39 [-]: GETTABLEKS R0 R1 K11 [0xC00DF526]
      40 [-]: GETUPVAL R1 0
      41 [-]: CALL R0 1 1  
      42 [-]: SETUPVAL R0 4
      43 [-]: GETIMPORT R0 1 [nil]
      44 [-]: NAMECALL R0 R0 K12 [0x66A70FFD]
      45 [-]: CALL R0 1 1  
      46 [-]: SETUPVAL R0 6
      47 [-]: GETIMPORT R0 14 [nil]
      48 [-]: GETUPVAL R3 2
      49 [-]: GETTABLEKS R2 R3 K4 [0x06D055F9]
      50 [-]: GETUPVAL R4 0
      51 [-]: JUMPXEQKN R4 K5 L4 [0]
      52 [-]: LOADB R3 0 +1
L 4:  53 [-]: LOADB R3 1   
L 5:  54 [-]: LOADN R4 0   
      55 [-]: LOADN R5 1   
      56 [-]: CALL R2 3 -1 
      57 [-]: NAMECALL R0 R0 K15 [0x5213FF59]
      58 [-]: CALL R0 -1 1 
      59 [-]: SETUPVAL R0 7
      60 [-]: GETUPVAL R0 1
      61 [-]: GETUPVAL R2 5
      62 [-]: GETTABLEKS R1 R2 K16 [0x9728F7A7]
      63 [-]: GETUPVAL R2 0
      64 [-]: GETUPVAL R3 6
      65 [-]: CALL R1 2 1  
      66 [-]: SETTABLEKS R1 R0 K17 ["NeedReroll"]
      67 [-]: GETUPVAL R1 8
      68 [-]: FASTCALL1 62 R1 L6
      69 [-]: GETIMPORT R0 19 [nil]
      70 [-]: CALL R0 1 1  
L 6:  71 [-]: JUMPIFNOT R0 L7
      72 [-]: GETIMPORT R0 1 [nil]
      73 [-]: NAMECALL R0 R0 K20 [0x69727E0B]
      74 [-]: CALL R0 1 1  
      75 [-]: GETTABLEKS R1 R0 K21 ["mEndlessXpChoices"]
      76 [-]: SETUPVAL R1 8
L 7:  77 [-]: GETUPVAL R1 9
      78 [-]: GETUPVAL R2 0
      79 [-]: GETTABLE R0 R1 R2
      80 [-]: JUMPXEQKNIL R0 L11 NOT
      81 [-]: LOADN R2 1   
      82 [-]: GETUPVAL R3 8
      83 [-]: LENGTH R0 R3 
      84 [-]: LOADN R1 1   
      85 [-]: FORNPREP R0 L11
L 8:  86 [-]: GETUPVAL R4 8
      87 [-]: GETTABLE R3 R4 R2
      88 [-]: GETTABLEKS R4 R3 K22 ["mCategory"]
      89 [-]: LOADN R5 0   
      90 [-]: LOADN R6 1   
      91 [-]: JUMPIFNOTEQ R4 R6 L9
      92 [-]: LOADN R5 1   
L 9:  93 [-]: GETUPVAL R6 0
      94 [-]: JUMPIFNOTEQ R5 R6 L10
      95 [-]: GETUPVAL R6 9
      96 [-]: GETUPVAL R7 10
      97 [-]: GETTABLEKS R8 R3 K23 ["mChoices"]
      98 [-]: GETUPVAL R10 7
      99 [-]: GETTABLEKS R9 R10 K23 ["mChoices"]
     100 [-]: CALL R7 2 1  
     101 [-]: SETTABLE R7 R6 R5
     102 [-]: JUMP L11
    
L10: 103 [-]: FORNLOOP R0 L8
L11: 104 [-]: GETUPVAL R1 9
     105 [-]: GETUPVAL R2 0
     106 [-]: GETTABLE R0 R1 R2
     107 [-]: SETUPVAL R0 11
     108 [-]: GETIMPORT R0 26 [nil]
     109 [-]: JUMPIFNOT R0 L12
     110 [-]: GETUPVAL R0 1
     111 [-]: LOADB R1 1   
     112 [-]: SETTABLEKS R1 R0 K17 ["NeedReroll"]
     113 [-]: GETIMPORT R0 27 [nil]
     114 [-]: LOADNIL R1   
     115 [-]: SETTABLEKS R1 R0 K25 ["ForceReroll"]
L12: 116 [-]: NEWTABLE R0 0 0
     117 [-]: GETUPVAL R2 1
     118 [-]: GETTABLEKS R1 R2 K17 ["NeedReroll"]
     119 [-]: JUMPIFNOT R1 L13
     120 [-]: GETUPVAL R1 12
     121 [-]: MOVE R2 R0   
     122 [-]: CALL R1 1 0  
L13: 123 [-]: GETUPVAL R2 6
     124 [-]: FASTCALL1 62 R2 L14
     125 [-]: GETIMPORT R1 19 [nil]
     126 [-]: CALL R1 1 1  
L14: 127 [-]: JUMPIF R1 L41
     128 [-]: GETUPVAL R1 4
     129 [-]: JUMPXEQKNIL R1 L41
     130 [-]: GETUPVAL R3 6
     131 [-]: GETUPVAL R4 4
     132 [-]: GETTABLE R2 R3 R4
     133 [-]: FASTCALL1 62 R2 L15
     134 [-]: GETIMPORT R1 19 [nil]
     135 [-]: CALL R1 1 1  
L15: 136 [-]: JUMPIF R1 L41
     137 [-]: GETUPVAL R2 6
     138 [-]: GETUPVAL R3 4
     139 [-]: GETTABLE R1 R2 R3
     140 [-]: MOVE R3 R0   
     141 [-]: GETUPVAL R5 7
     142 [-]: GETTABLEKS R4 R5 K28 ["mRepeatedRewards"]
     143 [-]: NAMECALL R4 R4 K29 [0xED4E0128]
     144 [-]: CALL R4 1 -1 
     145 [-]: FASTCALL 52 L16
     146 [-]: GETIMPORT R2 32 [nil]
     147 [-]: CALL R2 -1 0 
L16: 148 [-]: GETUPVAL R3 1
     149 [-]: GETTABLEKS R2 R3 K17 ["NeedReroll"]
     150 [-]: JUMPIF R2 L22
     151 [-]: LOADN R4 1   
     152 [-]: GETTABLEKS R5 R1 K23 ["mChoices"]
     153 [-]: LENGTH R2 R5 
     154 [-]: LOADN R3 1   
     155 [-]: FORNPREP R2 L22
L17: 156 [-]: LOADN R7 1   
     157 [-]: GETUPVAL R9 7
     158 [-]: GETTABLEKS R8 R9 K23 ["mChoices"]
     159 [-]: LENGTH R5 R8 
     160 [-]: LOADN R6 1   
     161 [-]: FORNPREP R5 L21
L18: 162 [-]: GETTABLEKS R9 R1 K23 ["mChoices"]
     163 [-]: GETTABLE R8 R9 R4
     164 [-]: GETUPVAL R12 7
     165 [-]: GETTABLEKS R11 R12 K23 ["mChoices"]
     166 [-]: GETTABLE R10 R11 R7
     167 [-]: GETTABLEKS R9 R10 K33 ["mTag"]
     168 [-]: JUMPIFNOTEQ R8 R9 L20
     169 [-]: MOVE R9 R0   
     170 [-]: GETUPVAL R13 7
     171 [-]: GETTABLEKS R12 R13 K23 ["mChoices"]
     172 [-]: GETTABLE R11 R12 R7
     173 [-]: GETTABLEKS R10 R11 K34 ["mChoiceParent"]
     174 [-]: NAMECALL R10 R10 K29 [0xED4E0128]
     175 [-]: CALL R10 1 -1
     176 [-]: FASTCALL 52 L19
     177 [-]: GETIMPORT R8 32 [nil]
     178 [-]: CALL R8 -1 0 
L19: 179 [-]: JUMP L21
    
L20: 180 [-]: FORNLOOP R5 L18
L21: 181 [-]: FORNLOOP R2 L17
L22: 182 [-]: LOADN R2 0   
     183 [-]: LOADN R3 0   
     184 [-]: GETTABLEKS R4 R1 K35 ["mEarnedAmount"]
     185 [-]: GETTABLEKS R5 R1 K36 ["mClaimedAmount"]
     186 [-]: GETTABLEKS R7 R1 K37 ["mPendingRewards"]
     187 [-]: LENGTH R6 R7 
     188 [-]: LOADN R7 1   
     189 [-]: LOADN R10 1  
     190 [-]: MOVE R8 R6   
     191 [-]: LOADN R9 1   
     192 [-]: FORNPREP R8 L30
L23: 193 [-]: GETTABLEKS R12 R1 K37 ["mPendingRewards"]
     194 [-]: GETTABLE R11 R12 R10
     195 [-]: GETTABLEKS R12 R11 K38 ["mRequiredTotalXp"]
     196 [-]: JUMPIFNOTLE R12 R5 L24
     197 [-]: ADDK R3 R3 K9 [1]
L24: 198 [-]: JUMPIFNOTLE R12 R4 L25
     199 [-]: ADDK R2 R2 K9 [1]
L25: 200 [-]: LOADN R15 1  
     201 [-]: GETTABLEKS R16 R11 K39 ["mRewards"]
     202 [-]: LENGTH R13 R16
     203 [-]: LOADN R14 1  
     204 [-]: FORNPREP R13 L29
L26: 205 [-]: GETTABLEKS R18 R11 K39 ["mRewards"]
     206 [-]: GETTABLE R17 R18 R15
     207 [-]: GETTABLEKS R16 R17 K40 ["mStoreItem"]
     208 [-]: FASTCALL1 62 R16 L27
     209 [-]: MOVE R18 R16 
     210 [-]: GETIMPORT R17 19 [nil]
     211 [-]: CALL R17 1 1 
L27: 212 [-]: JUMPIF R17 L28
     213 [-]: MOVE R18 R0  
     214 [-]: NAMECALL R19 R16 K29 [0xED4E0128]
     215 [-]: CALL R19 1 -1
     216 [-]: FASTCALL 52 L28
     217 [-]: GETIMPORT R17 32 [nil]
     218 [-]: CALL R17 -1 0
L28: 219 [-]: FORNLOOP R13 L26
L29: 220 [-]: MOVE R7 R12  
     221 [-]: FORNLOOP R8 L23
L30: 222 [-]: GETUPVAL R9 7
     223 [-]: GETTABLEKS R8 R9 K41 ["mXpPerRepeatedReward"]
     224 [-]: JUMPIFNOTEQ R2 R6 L32
     225 [-]: SUB R9 R4 R7 
     226 [-]: DIV R11 R9 R8
     227 [-]: FASTCALL1 12 R11 L31
     228 [-]: GETIMPORT R10 44 [nil]
     229 [-]: CALL R10 1 1 
L31: 230 [-]: ADD R2 R2 R10
L32: 231 [-]: JUMPIFNOTEQ R3 R6 L34
     232 [-]: SUB R9 R5 R7 
     233 [-]: DIV R11 R9 R8
     234 [-]: FASTCALL1 12 R11 L33
     235 [-]: GETIMPORT R10 44 [nil]
     236 [-]: CALL R10 1 1 
L33: 237 [-]: ADD R3 R3 R10
L34: 238 [-]: GETUPVAL R9 13
     239 [-]: GETUPVAL R11 2
     240 [-]: GETTABLEKS R10 R11 K4 [0x06D055F9]
     241 [-]: LOADN R12 5  
     242 [-]: JUMPIFLT R2 R12 L35
     243 [-]: LOADB R11 0 +1
L35: 244 [-]: LOADB R11 1  
L36: 245 [-]: LOADN R12 1  
     246 [-]: LOADN R13 2  
     247 [-]: CALL R10 3 1 
     248 [-]: SETTABLEKS R10 R9 K45 ["WeaponIndex"]
     249 [-]: JUMPIFNOTLT R3 R2 L41
     250 [-]: GETUPVAL R9 14
     251 [-]: ADDK R10 R3 K9 [1]
     252 [-]: SETTABLEKS R10 R9 K46 ["StartIndex"]
     253 [-]: GETUPVAL R9 14
     254 [-]: SUB R10 R2 R3
     255 [-]: SETTABLEKS R10 R9 K47 ["Num"]
     256 [-]: LOADB R9 1   
     257 [-]: SETUPVAL R9 15
     258 [-]: GETIMPORT R10 49 [nil]
     259 [-]: FASTCALL1 62 R10 L37
     260 [-]: GETIMPORT R9 19 [nil]
     261 [-]: CALL R9 1 1  
L37: 262 [-]: JUMPIF R9 L38
     263 [-]: GETIMPORT R9 49 [nil]
     264 [-]: LOADK R11 K50 ["ShowBlockingMessage"]
     265 [-]: LOADK R12 K51 ["2"]
     266 [-]: NAMECALL R9 R9 K52 [0xE4162EED]
     267 [-]: CALL R9 3 0  
L38: 268 [-]: GETUPVAL R9 14
     269 [-]: LOADB R10 1  
     270 [-]: SETTABLEKS R10 R9 K53 ["HasClaim"]
     271 [-]: GETIMPORT R9 56 [nil]
     272 [-]: GETUPVAL R11 2
     273 [-]: GETTABLEKS R10 R11 K4 [0x06D055F9]
     274 [-]: GETUPVAL R12 0
     275 [-]: JUMPXEQKN R12 K5 L39 [0]
     276 [-]: LOADB R11 0 +1
L39: 277 [-]: LOADB R11 1  
L40: 278 [-]: LOADN R12 0  
     279 [-]: LOADN R13 1  
     280 [-]: CALL R10 3 1 
     281 [-]: LOADK R11 K57 ["OnRewardsClaimed"]
     282 [-]: CALL R9 2 1  
     283 [-]: SETUPVAL R9 16
     284 [-]: GETUPVAL R9 16
     285 [-]: NAMECALL R9 R9 K52 [0xE4162EED]
     286 [-]: CALL R9 1 0  
L41: 287 [-]: GETUPVAL R2 1
     288 [-]: GETTABLEKS R1 R2 K58 ["Grid"]
     289 [-]: NAMECALL R1 R1 K59 [0x7C09C373]
     290 [-]: CALL R1 1 0  
     291 [-]: GETIMPORT R1 61 [nil]
     292 [-]: LOADK R3 K62 ["RewardPanel.ExtraReward"]
     293 [-]: LOADN R4 11  
     294 [-]: LOADB R5 0   
     295 [-]: NAMECALL R1 R1 K63 [0xAADE900E]
     296 [-]: CALL R1 4 0  
     297 [-]: GETIMPORT R1 61 [nil]
     298 [-]: LOADK R3 K64 ["RewardPanel.XpBar"]
     299 [-]: LOADN R4 11  
     300 [-]: LOADB R5 0   
     301 [-]: NAMECALL R1 R1 K63 [0xAADE900E]
     302 [-]: CALL R1 4 0  
     303 [-]: LENGTH R1 R0 
     304 [-]: LOADN R2 0   
     305 [-]: JUMPIFNOTLT R2 R1 L42
     306 [-]: GETUPVAL R1 1
     307 [-]: GETIMPORT R2 67 [nil]
     308 [-]: MOVE R3 R0   
     309 [-]: CALL R2 1 1  
     310 [-]: SETTABLEKS R2 R1 K68 ["Loader"]
     311 [-]: GETUPVAL R1 1
     312 [-]: LOADB R2 1   
     313 [-]: SETTABLEKS R2 R1 K69 ["IsLoading"]
     314 [-]: GETUPVAL R2 1
     315 [-]: GETTABLEKS R1 R2 K70 ["Spinner"]
     316 [-]: LOADB R3 1   
     317 [-]: NAMECALL R1 R1 K71 [0x46610C50]
     318 [-]: CALL R1 2 0  
     319 [-]: JUMP L43
    
L42: 320 [-]: GETUPVAL R2 1
     321 [-]: GETTABLEKS R1 R2 K17 ["NeedReroll"]
     322 [-]: JUMPIFNOT R1 L43
     323 [-]: GETUPVAL R1 17
     324 [-]: CALL R1 0 0  
L43: 325 [-]: GETUPVAL R1 18
     326 [-]: CALL R1 0 0  
     327 [-]: GETIMPORT R1 61 [nil]
     328 [-]: LOADK R3 K72 ["RewardPanel.Modes.NormalBtn"]
     329 [-]: LOADN R4 59  
     330 [-]: GETUPVAL R6 0
     331 [-]: JUMPXEQKN R6 K9 L44 [1]
     332 [-]: LOADB R5 0 +1
L44: 333 [-]: LOADB R5 1   
L45: 334 [-]: NAMECALL R1 R1 K63 [0xAADE900E]
     335 [-]: CALL R1 4 0  
     336 [-]: GETIMPORT R1 61 [nil]
     337 [-]: LOADK R3 K73 ["RewardPanel.Modes.HardBtn"]
     338 [-]: LOADN R4 59  
     339 [-]: GETUPVAL R6 0
     340 [-]: JUMPXEQKN R6 K5 L46 [0]
     341 [-]: LOADB R5 0 +1
L46: 342 [-]: LOADB R5 1   
L47: 343 [-]: NAMECALL R1 R1 K63 [0xAADE900E]
     344 [-]: CALL R1 4 0  
     345 [-]: GETIMPORT R1 61 [nil]
     346 [-]: LOADK R3 K74 ["RewardPanel.NoDioIcon"]
     347 [-]: LOADN R4 11  
     348 [-]: LOADB R5 0   
     349 [-]: NAMECALL R1 R1 K63 [0xAADE900E]
     350 [-]: CALL R1 4 0  
     351 [-]: RETURN R0 0  


; Name:            
; Defined at line: 532
; #Upvalues:       6
; #Parameters:     0
; Is_vararg:       0
; Max Stack Size:  8

       0 [-]: GETUPVAL R1 0
       1 [-]: NOT R0 R1    
       2 [-]: SETUPVAL R0 0
       3 [-]: GETIMPORT R0 1 [nil]
       4 [-]: LOADNIL R1   
       5 [-]: SETTABLEKS R1 R0 K2 ["gToolTip"]
       6 [-]: GETIMPORT R1 4 [nil]
       7 [-]: FASTCALL1 62 R1 L0
       8 [-]: GETIMPORT R0 6 [nil]
       9 [-]: CALL R0 1 1  
L 0:  10 [-]: JUMPIF R0 L1 
      11 [-]: GETIMPORT R0 4 [nil]
      12 [-]: LOADK R1 K7 [0.25]
      13 [-]: LOADNIL R2   
      14 [-]: LOADNIL R3   
      15 [-]: GETUPVAL R5 1
      16 [-]: GETTABLEKS R4 R5 K8 [0x06D055F9]
      17 [-]: GETUPVAL R5 0
      18 [-]: LOADNIL R6   
      19 [-]: GETUPVAL R7 2
      20 [-]: CALL R4 3 -1 
      21 [-]: CALL R0 -1 0 
L 1:  22 [-]: GETUPVAL R0 0
      23 [-]: JUMPIFNOT R0 L2
      24 [-]: GETUPVAL R0 3
      25 [-]: CALL R0 0 0  
      26 [-]: JUMP L3
     
L 2:  27 [-]: GETUPVAL R0 4
      28 [-]: CALL R0 0 0  
L 3:  29 [-]: GETUPVAL R0 5
      30 [-]: CALL R0 0 0  
      31 [-]: RETURN R0 0  


; Name:            
; Defined at line: 549
; #Upvalues:       7
; #Parameters:     0
; Is_vararg:       0
; Max Stack Size:  8

       0 [-]: GETUPVAL R1 0
       1 [-]: NOT R0 R1    
       2 [-]: SETUPVAL R0 0
       3 [-]: GETUPVAL R1 1
       4 [-]: NOT R0 R1    
       5 [-]: SETUPVAL R0 1
       6 [-]: GETIMPORT R0 1 [nil]
       7 [-]: LOADNIL R1   
       8 [-]: SETTABLEKS R1 R0 K2 ["gToolTip"]
       9 [-]: GETIMPORT R1 4 [nil]
      10 [-]: FASTCALL1 62 R1 L0
      11 [-]: GETIMPORT R0 6 [nil]
      12 [-]: CALL R0 1 1  
L 0:  13 [-]: JUMPIF R0 L1 
      14 [-]: GETIMPORT R0 4 [nil]
      15 [-]: LOADK R1 K7 [0.25]
      16 [-]: LOADNIL R2   
      17 [-]: LOADNIL R3   
      18 [-]: GETUPVAL R5 2
      19 [-]: GETTABLEKS R4 R5 K8 [0x06D055F9]
      20 [-]: GETUPVAL R5 0
      21 [-]: LOADNIL R6   
      22 [-]: GETUPVAL R7 3
      23 [-]: CALL R4 3 -1 
      24 [-]: CALL R0 -1 0 
L 1:  25 [-]: GETUPVAL R0 0
      26 [-]: JUMPIFNOT R0 L2
      27 [-]: GETUPVAL R0 4
      28 [-]: CALL R0 0 0  
      29 [-]: JUMP L3
     
L 2:  30 [-]: GETUPVAL R0 5
      31 [-]: CALL R0 0 0  
L 3:  32 [-]: GETUPVAL R0 6
      33 [-]: CALL R0 0 0  
      34 [-]: RETURN R0 0  


; Name:            
; Defined at line: 567
; #Upvalues:       0
; #Parameters:     0
; Is_vararg:       0
; Max Stack Size:  2

       0 [-]: GETIMPORT R0 1 [nil]
       1 [-]: LOADB R1 1   
       2 [-]: SETTABLEKS R1 R0 K2 ["ForceReroll"]
       3 [-]: RETURN R0 0  


; Name:            
; Defined at line: 571
; #Upvalues:       3
; #Parameters:     0
; Is_vararg:       0
; Max Stack Size:  9

       0 [-]: NEWTABLE R0 0 0
       1 [-]: GETUPVAL R1 0
       2 [-]: JUMPIF R1 L1 
       3 [-]: GETUPVAL R1 1
       4 [-]: JUMPIF R1 L0 
       5 [-]: GETUPVAL R2 2
       6 [-]: GETTABLEKS R1 R2 K0 [0xA7D904B8]
       7 [-]: GETIMPORT R2 2 [nil]
       8 [-]: LOADK R3 K3 ["/Lotus/Language/Hints/DuviriEndless_"]
       9 [-]: CALL R1 2 1  
      10 [-]: LENGTH R2 R1 
      11 [-]: LOADN R3 0   
      12 [-]: JUMPIFNOTLT R3 R2 L0
      13 [-]: DUPTABLE R4 7
      14 [-]: GETIMPORT R5 2 [nil]
      15 [-]: LOADK R7 K8 ["<WARNING>"]
      16 [-]: LOADB R8 1   
      17 [-]: NAMECALL R5 R5 K9 [0x42B04007]
      18 [-]: CALL R5 3 1  
      19 [-]: SETTABLEKS R5 R4 K4 ["Label"]
      20 [-]: SETTABLEKS R1 R4 K5 ["Tips"]
      21 [-]: LOADN R5 -10 
      22 [-]: SETTABLEKS R5 R4 K6 ["Padding"]
      23 [-]: FASTCALL2 52 R0 R4 L0
      24 [-]: MOVE R3 R0   
      25 [-]: GETIMPORT R2 12 [nil]
      26 [-]: CALL R2 2 0  
L 0:  27 [-]: DUPTABLE R3 15
      28 [-]: LOADK R4 K16 ["/Lotus/Language/Menu/Exit"]
      29 [-]: SETTABLEKS R4 R3 K4 ["Label"]
      30 [-]: DUPCLOSURE R4 K17 []
      31 [-]: SETTABLEKS R4 R3 K13 ["CallBack"]
      32 [-]: LOADK R4 K18 ["MENU_CANCEL"]
      33 [-]: SETTABLEKS R4 R3 K14 ["CallOut"]
      34 [-]: FASTCALL2 52 R0 R3 L1
      35 [-]: MOVE R2 R0   
      36 [-]: GETIMPORT R1 12 [nil]
      37 [-]: CALL R1 2 0  
L 1:  38 [-]: GETIMPORT R2 21 [nil]
      39 [-]: FASTCALL1 62 R2 L2
      40 [-]: GETIMPORT R1 23 [nil]
      41 [-]: CALL R1 1 1  
L 2:  42 [-]: JUMPIF R1 L3 
      43 [-]: GETIMPORT R1 21 [nil]
      44 [-]: GETIMPORT R2 2 [nil]
      45 [-]: MOVE R3 R0   
      46 [-]: GETIMPORT R4 25 [nil]
      47 [-]: LOADN R5 1   
      48 [-]: CALL R4 1 -1 
      49 [-]: CALL R1 -1 0 
L 3:  50 [-]: RETURN R0 0  


; Name:            
; Defined at line: 595
; #Upvalues:       4
; #Parameters:     0
; Is_vararg:       0
; Max Stack Size:  6

       0 [-]: GETUPVAL R0 0
       1 [-]: JUMPIFNOT R0 L0
       2 [-]: RETURN R0 0  
L 0:   3 [-]: GETIMPORT R0 1 [nil]
       4 [-]: NAMECALL R0 R0 K2 [0x33ABEE92]
       5 [-]: CALL R0 1 1  
       6 [-]: FASTCALL1 62 R0 L1
       7 [-]: MOVE R2 R0   
       8 [-]: GETIMPORT R1 4 [nil]
       9 [-]: CALL R1 1 1  
L 1:  10 [-]: JUMPIF R1 L4 
      11 [-]: GETUPVAL R1 1
      12 [-]: JUMPIFNOT R1 L2
      13 [-]: GETIMPORT R1 6 [nil]
      14 [-]: LOADB R2 1   
      15 [-]: SETTABLEKS R2 R1 K7 ["DuviriEndlessSetupComplete"]
      16 [-]: LOADB R1 1   
      17 [-]: SETUPVAL R1 2
      18 [-]: GETUPVAL R3 1
      19 [-]: NEWTABLE R4 0 1
      20 [-]: LOADK R5 K8 ["true"]
      21 [-]: SETLIST R4 R5 1 [1]
      22 [-]: NAMECALL R1 R0 K9 [0xF56F3887]
      23 [-]: CALL R1 3 0  
      24 [-]: JUMP L3
     
L 2:  25 [-]: LOADK R3 K10 ["LaunchDuviriEndless"]
      26 [-]: LOADK R4 K11 [""]
      27 [-]: NAMECALL R1 R0 K12 [0xE4162EED]
      28 [-]: CALL R1 3 0  
L 3:  29 [-]: GETUPVAL R1 3
      30 [-]: CALL R1 0 0  
L 4:  31 [-]: RETURN R0 0  


; Name:            
; Defined at line: 614
; #Upvalues:       3
; #Parameters:     1
; Is_vararg:       0
; Max Stack Size:  7

       0 [-]: GETUPVAL R1 0
       1 [-]: JUMPIFNOT R1 L0
       2 [-]: RETURN R0 0  
L 0:   3 [-]: GETIMPORT R1 2 [nil]
       4 [-]: JUMPXEQKB R1 1 L2 NOT
       5 [-]: GETIMPORT R1 4 [nil]
       6 [-]: NAMECALL R1 R1 K5 [0x33ABEE92]
       7 [-]: CALL R1 1 1  
       8 [-]: FASTCALL1 62 R1 L1
       9 [-]: MOVE R3 R1   
      10 [-]: GETIMPORT R2 7 [nil]
      11 [-]: CALL R2 1 1  
L 1:  12 [-]: JUMPIF R2 L5 
      13 [-]: LOADK R4 K8 ["SetDifficulty"]
      14 [-]: MOVE R5 R0   
      15 [-]: NAMECALL R2 R1 K9 [0xE4162EED]
      16 [-]: CALL R2 3 0  
      17 [-]: JUMP L5
     
L 2:  18 [-]: GETIMPORT R1 11 [nil]
      19 [-]: GETUPVAL R4 1
      20 [-]: GETTABLEKS R3 R4 K12 [0x06D055F9]
      21 [-]: JUMPXEQKN R0 K13 L3 [1]
      22 [-]: LOADB R4 0 +1
L 3:  23 [-]: LOADB R4 1   
L 4:  24 [-]: LOADN R5 0   
      25 [-]: LOADN R6 1   
      26 [-]: CALL R3 3 -1 
      27 [-]: NAMECALL R1 R1 K14 [0x04B318AD]
      28 [-]: CALL R1 -1 0 
L 5:  29 [-]: GETUPVAL R1 2
      30 [-]: CALL R1 0 0  
      31 [-]: RETURN R0 0  


; Name:            
; Defined at line: 631
; #Upvalues:       2
; #Parameters:     0
; Is_vararg:       0
; Max Stack Size:  3

       0 [-]: GETUPVAL R0 0
       1 [-]: LOADN R1 1   
       2 [-]: CALL R0 1 0  
       3 [-]: GETUPVAL R1 1
       4 [-]: GETTABLEKS R0 R1 K0 [0x659D451F]
       5 [-]: GETIMPORT R2 2 [nil]
       6 [-]: GETTABLEKS R1 R2 K3 ["UISound_ButtonSelect"]
       7 [-]: CALL R0 1 0  
       8 [-]: RETURN R0 0  


; Name:            
; Defined at line: 636
; #Upvalues:       2
; #Parameters:     0
; Is_vararg:       0
; Max Stack Size:  3

       0 [-]: GETUPVAL R0 0
       1 [-]: LOADN R1 2   
       2 [-]: CALL R0 1 0  
       3 [-]: GETUPVAL R1 1
       4 [-]: GETTABLEKS R0 R1 K0 [0x659D451F]
       5 [-]: GETIMPORT R2 2 [nil]
       6 [-]: GETTABLEKS R1 R2 K3 ["UISound_ButtonSelect"]
       7 [-]: CALL R0 1 0  
       8 [-]: RETURN R0 0  


; Name:            
; Defined at line: 641
; #Upvalues:       10
; #Parameters:     0
; Is_vararg:       0
; Max Stack Size:  12

       0 [-]: GETIMPORT R0 1 [nil]
       1 [-]: LOADK R1 K2 ["Lotus.Interface.Components.ThemedButton"]
       2 [-]: CALL R0 1 1  
       3 [-]: GETUPVAL R1 0
       4 [-]: GETTABLEKS R2 R0 K3 [0xAE6791BA]
       5 [-]: GETIMPORT R3 5 [nil]
       6 [-]: LOADK R4 K6 ["RewardPanel.Modes.NormalBtn"]
       7 [-]: LOADK R5 K7 ["/Lotus/Language/Labels/NormalModeShort"]
       8 [-]: LOADK R6 K8 ["SetNormalMode"]
       9 [-]: CALL R2 4 1  
      10 [-]: SETTABLEKS R2 R1 K9 ["NormalBtn"]
      11 [-]: GETUPVAL R2 0
      12 [-]: GETTABLEKS R1 R2 K9 ["NormalBtn"]
      13 [-]: LOADN R3 176 
      14 [-]: NAMECALL R1 R1 K10 [0x8D77B2B2]
      15 [-]: CALL R1 2 0  
      16 [-]: GETUPVAL R3 1
      17 [-]: GETTABLEKS R2 R3 K11 [0x1B0C4985]
      18 [-]: CALL R2 0 1  
      19 [-]: NOT R1 R2    
      20 [-]: GETIMPORT R5 5 [nil]
      21 [-]: GETUPVAL R8 2
      22 [-]: GETTABLEKS R7 R8 K12 [0x06D055F9]
      23 [-]: MOVE R8 R1   
      24 [-]: LOADK R9 K13 ["<LOCKED> "]
      25 [-]: LOADK R10 K14 [""]
      26 [-]: CALL R7 3 1  
      27 [-]: LOADB R8 1   
      28 [-]: NAMECALL R5 R5 K15 [0x42B04007]
      29 [-]: CALL R5 3 1  
      30 [-]: MOVE R3 R5   
      31 [-]: GETIMPORT R4 5 [nil]
      32 [-]: LOADK R6 K16 ["/Lotus/Language/Labels/HardModeShort"]
      33 [-]: LOADB R7 0   
      34 [-]: NAMECALL R4 R4 K15 [0x42B04007]
      35 [-]: CALL R4 3 1  
      36 [-]: CONCAT R2 R3 R4
      37 [-]: GETUPVAL R3 0
      38 [-]: GETTABLEKS R4 R0 K3 [0xAE6791BA]
      39 [-]: GETIMPORT R5 5 [nil]
      40 [-]: LOADK R6 K17 ["RewardPanel.Modes.HardBtn"]
      41 [-]: MOVE R7 R2   
      42 [-]: LOADK R8 K18 ["SetHardMode"]
      43 [-]: CALL R4 4 1  
      44 [-]: SETTABLEKS R4 R3 K19 ["HardBtn"]
      45 [-]: GETUPVAL R4 0
      46 [-]: GETTABLEKS R3 R4 K19 ["HardBtn"]
      47 [-]: NOT R5 R1    
      48 [-]: NAMECALL R3 R3 K20 [0x46610C50]
      49 [-]: CALL R3 2 0  
      50 [-]: GETUPVAL R4 0
      51 [-]: GETTABLEKS R3 R4 K19 ["HardBtn"]
      52 [-]: LOADN R5 176 
      53 [-]: NAMECALL R3 R3 K10 [0x8D77B2B2]
      54 [-]: CALL R3 2 0  
      55 [-]: GETUPVAL R3 0
      56 [-]: GETTABLEKS R4 R0 K3 [0xAE6791BA]
      57 [-]: GETIMPORT R5 5 [nil]
      58 [-]: LOADK R6 K21 ["RewardPanel.Modes.StartBtn"]
      59 [-]: LOADK R7 K22 ["/Lotus/Language/Duviri/EndlessSetupStart"]
      60 [-]: LOADK R8 K23 ["StartEndless"]
      61 [-]: CALL R4 4 1  
      62 [-]: SETTABLEKS R4 R3 K24 ["StartBtn"]
      63 [-]: GETUPVAL R4 0
      64 [-]: GETTABLEKS R3 R4 K24 ["StartBtn"]
      65 [-]: NAMECALL R3 R3 K25 [0x4E86C602]
      66 [-]: CALL R3 1 0  
      67 [-]: GETUPVAL R4 0
      68 [-]: GETTABLEKS R3 R4 K24 ["StartBtn"]
      69 [-]: NAMECALL R3 R3 K26 [0x71E9AC81]
      70 [-]: CALL R3 1 0  
      71 [-]: GETUPVAL R4 0
      72 [-]: GETTABLEKS R3 R4 K24 ["StartBtn"]
      73 [-]: GETUPVAL R6 2
      74 [-]: GETTABLEKS R5 R6 K27 ["CENTER_ALIGNED"]
      75 [-]: NAMECALL R3 R3 K28 [0x240F1807]
      76 [-]: CALL R3 2 0  
      77 [-]: GETIMPORT R3 5 [nil]
      78 [-]: LOADK R5 K29 ["RewardPanel.NoDioIcon"]
      79 [-]: LOADN R6 11  
      80 [-]: LOADB R7 0   
      81 [-]: NAMECALL R3 R3 K30 [0xAADE900E]
      82 [-]: CALL R3 4 0  
      83 [-]: GETIMPORT R3 5 [nil]
      84 [-]: LOADK R5 K31 ["RewardPanel.Modes.BtnBookmarkLeft"]
      85 [-]: GETIMPORT R6 33 [nil]
      86 [-]: NAMECALL R3 R3 K34 [0x1CB415C1]
      87 [-]: CALL R3 3 0  
      88 [-]: GETIMPORT R3 5 [nil]
      89 [-]: LOADK R5 K35 ["RewardPanel.Modes.BtnBookmarkRight"]
      90 [-]: GETIMPORT R6 33 [nil]
      91 [-]: NAMECALL R3 R3 K34 [0x1CB415C1]
      92 [-]: CALL R3 3 0  
      93 [-]: GETIMPORT R3 5 [nil]
      94 [-]: LOADK R5 K31 ["RewardPanel.Modes.BtnBookmarkLeft"]
      95 [-]: LOADN R6 9   
      96 [-]: GETUPVAL R8 3
      97 [-]: GETTABLEKS R7 R8 K36 ["FloatingContent"]
      98 [-]: NAMECALL R3 R3 K37 [0x67BC869F]
      99 [-]: CALL R3 4 0  
     100 [-]: GETIMPORT R3 5 [nil]
     101 [-]: LOADK R5 K35 ["RewardPanel.Modes.BtnBookmarkRight"]
     102 [-]: LOADN R6 9   
     103 [-]: GETUPVAL R8 3
     104 [-]: GETTABLEKS R7 R8 K36 ["FloatingContent"]
     105 [-]: NAMECALL R3 R3 K37 [0x67BC869F]
     106 [-]: CALL R3 4 0  
     107 [-]: GETIMPORT R3 5 [nil]
     108 [-]: LOADK R5 K38 ["RewardPanel.ExtraReward.LeftArrow"]
     109 [-]: GETIMPORT R6 40 [nil]
     110 [-]: NAMECALL R3 R3 K34 [0x1CB415C1]
     111 [-]: CALL R3 3 0  
     112 [-]: GETIMPORT R3 5 [nil]
     113 [-]: LOADK R5 K41 ["RewardPanel.ExtraReward.RightArrow"]
     114 [-]: GETIMPORT R6 40 [nil]
     115 [-]: NAMECALL R3 R3 K34 [0x1CB415C1]
     116 [-]: CALL R3 3 0  
     117 [-]: GETIMPORT R3 5 [nil]
     118 [-]: LOADK R5 K38 ["RewardPanel.ExtraReward.LeftArrow"]
     119 [-]: LOADN R6 9   
     120 [-]: GETUPVAL R8 3
     121 [-]: GETTABLEKS R7 R8 K36 ["FloatingContent"]
     122 [-]: NAMECALL R3 R3 K37 [0x67BC869F]
     123 [-]: CALL R3 4 0  
     124 [-]: GETIMPORT R3 5 [nil]
     125 [-]: LOADK R5 K41 ["RewardPanel.ExtraReward.RightArrow"]
     126 [-]: LOADN R6 9   
     127 [-]: GETUPVAL R8 3
     128 [-]: GETTABLEKS R7 R8 K36 ["FloatingContent"]
     129 [-]: NAMECALL R3 R3 K37 [0x67BC869F]
     130 [-]: CALL R3 4 0  
     131 [-]: GETIMPORT R3 5 [nil]
     132 [-]: LOADK R5 K38 ["RewardPanel.ExtraReward.LeftArrow"]
     133 [-]: LOADN R6 85  
     134 [-]: LOADN R7 -1  
     135 [-]: NAMECALL R3 R3 K37 [0x67BC869F]
     136 [-]: CALL R3 4 0  
     137 [-]: GETIMPORT R3 5 [nil]
     138 [-]: LOADK R5 K41 ["RewardPanel.ExtraReward.RightArrow"]
     139 [-]: LOADN R6 85  
     140 [-]: LOADN R7 1   
     141 [-]: NAMECALL R3 R3 K37 [0x67BC869F]
     142 [-]: CALL R3 4 0  
     143 [-]: GETIMPORT R3 5 [nil]
     144 [-]: LOADK R5 K38 ["RewardPanel.ExtraReward.LeftArrow"]
     145 [-]: LOADK R6 K42 ["ArrowFocused"]
     146 [-]: LOADK R7 K43 ["ArrowUnfocused"]
     147 [-]: LOADK R8 K44 ["ArrowPressed"]
     148 [-]: LOADNIL R9   
     149 [-]: NAMECALL R3 R3 K45 [0x1E5B5CFE]
     150 [-]: CALL R3 6 0  
     151 [-]: GETIMPORT R3 5 [nil]
     152 [-]: LOADK R5 K41 ["RewardPanel.ExtraReward.RightArrow"]
     153 [-]: LOADK R6 K42 ["ArrowFocused"]
     154 [-]: LOADK R7 K43 ["ArrowUnfocused"]
     155 [-]: LOADK R8 K44 ["ArrowPressed"]
     156 [-]: LOADNIL R9   
     157 [-]: NAMECALL R3 R3 K45 [0x1E5B5CFE]
     158 [-]: CALL R3 6 0  
     159 [-]: GETIMPORT R3 1 [nil]
     160 [-]: LOADK R4 K46 ["Lotus.Interface.Components.ThemedSpinner"]
     161 [-]: CALL R3 1 1  
     162 [-]: GETUPVAL R4 0
     163 [-]: GETTABLEKS R5 R3 K3 [0xAE6791BA]
     164 [-]: GETIMPORT R6 5 [nil]
     165 [-]: LOADK R7 K47 ["RewardPanel.Spinner"]
     166 [-]: CALL R5 2 1  
     167 [-]: SETTABLEKS R5 R4 K48 ["Spinner"]
     168 [-]: GETUPVAL R5 0
     169 [-]: GETTABLEKS R4 R5 K48 ["Spinner"]
     170 [-]: LOADB R6 0   
     171 [-]: NAMECALL R4 R4 K20 [0x46610C50]
     172 [-]: CALL R4 2 0  
     173 [-]: GETIMPORT R5 5 [nil]
     174 [-]: LOADK R7 K50 ["RewardPanel.RewardPath.RewardElement.Icon"]
     175 [-]: LOADN R8 5   
     176 [-]: NAMECALL R5 R5 K51 [0x91A24E4B]
     177 [-]: CALL R5 3 1  
     178 [-]: ORK R4 R5 K49 [100]
     179 [-]: SETUPVAL R4 4
     180 [-]: GETIMPORT R5 5 [nil]
     181 [-]: LOADK R7 K52 ["RewardPanel.RewardPath.RewardElement.IconMask"]
     182 [-]: LOADN R8 5   
     183 [-]: NAMECALL R5 R5 K51 [0x91A24E4B]
     184 [-]: CALL R5 3 1  
     185 [-]: ORK R4 R5 K49 [100]
     186 [-]: SETUPVAL R4 5
     187 [-]: GETIMPORT R4 1 [nil]
     188 [-]: LOADK R5 K53 ["EE.Interface.Components.Grid"]
     189 [-]: CALL R4 1 1  
     190 [-]: GETUPVAL R5 0
     191 [-]: GETTABLEKS R6 R4 K54 [0xDA0C93A2]
     192 [-]: GETIMPORT R7 5 [nil]
     193 [-]: LOADK R8 K55 ["RewardPanel.RewardPath.RewardElement"]
     194 [-]: LOADNIL R9   
     195 [-]: LOADN R10 3  
     196 [-]: LOADN R11 4  
     197 [-]: CALL R6 5 1  
     198 [-]: SETTABLEKS R6 R5 K56 ["Grid"]
     199 [-]: GETUPVAL R6 0
     200 [-]: GETTABLEKS R5 R6 K56 ["Grid"]
     201 [-]: LOADN R6 175 
     202 [-]: SETTABLEKS R6 R5 K57 ["mColumnSeparation"]
     203 [-]: GETUPVAL R6 0
     204 [-]: GETTABLEKS R5 R6 K56 ["Grid"]
     205 [-]: LOADN R6 155 
     206 [-]: SETTABLEKS R6 R5 K58 ["mRowSeparation"]
     207 [-]: GETUPVAL R6 0
     208 [-]: GETTABLEKS R5 R6 K56 ["Grid"]
     209 [-]: NEWTABLE R6 0 0
     210 [-]: SETTABLEKS R6 R5 K59 ["mInitDims"]
     211 [-]: GETUPVAL R6 0
     212 [-]: GETTABLEKS R5 R6 K56 ["Grid"]
     213 [-]: LOADNIL R7   
     214 [-]: LOADK R8 K60 ["RewardFocused"]
     215 [-]: LOADK R9 K61 ["RewardUnfocused"]
     216 [-]: NAMECALL R5 R5 K45 [0x1E5B5CFE]
     217 [-]: CALL R5 4 0  
     218 [-]: GETUPVAL R6 0
     219 [-]: GETTABLEKS R5 R6 K56 ["Grid"]
     220 [-]: GETUPVAL R8 0
     221 [-]: GETTABLEKS R7 R8 K56 ["Grid"]
     222 [-]: GETTABLEKS R6 R7 K62 ["CalculateX"]
     223 [-]: SETTABLEKS R6 R5 K63 ["RewardPanel_CalculateX"]
     224 [-]: GETUPVAL R6 0
     225 [-]: GETTABLEKS R5 R6 K56 ["Grid"]
     226 [-]: DUPCLOSURE R6 K64 []
     227 [-]: SETTABLEKS R6 R5 K62 ["CalculateX"]
     228 [-]: GETUPVAL R6 0
     229 [-]: GETTABLEKS R5 R6 K56 ["Grid"]
     230 [-]: GETUPVAL R8 0
     231 [-]: GETTABLEKS R7 R8 K56 ["Grid"]
     232 [-]: GETTABLEKS R6 R7 K65 ["CalculateY"]
     233 [-]: SETTABLEKS R6 R5 K66 ["RewardPanel_CalculateY"]
     234 [-]: GETUPVAL R6 0
     235 [-]: GETTABLEKS R5 R6 K56 ["Grid"]
     236 [-]: DUPCLOSURE R6 K67 []
     237 [-]: SETTABLEKS R6 R5 K65 ["CalculateY"]
     238 [-]: GETUPVAL R6 0
     239 [-]: GETTABLEKS R5 R6 K56 ["Grid"]
     240 [-]: NEWCLOSURE R6 P2
     241 [-]: MOVE R2 R3   
     242 [-]: MOVE R2 R2   
     243 [-]: SETTABLEKS R6 R5 K68 ["RefreshExtraLabel"]
     244 [-]: GETUPVAL R6 0
     245 [-]: GETTABLEKS R5 R6 K56 ["Grid"]
     246 [-]: DUPCLOSURE R6 K69 []
     247 [-]: MOVE R2 R0   
     248 [-]: MOVE R2 R2   
     249 [-]: MOVE R2 R6   
     250 [-]: MOVE R2 R7   
     251 [-]: SETTABLEKS R6 R5 K70 ["CycleReward"]
     252 [-]: GETUPVAL R6 0
     253 [-]: GETTABLEKS R5 R6 K56 ["Grid"]
     254 [-]: DUPCLOSURE R6 K71 []
     255 [-]: SETTABLEKS R6 R5 K72 ["UpdateIcons"]
     256 [-]: GETUPVAL R6 0
     257 [-]: GETTABLEKS R5 R6 K56 ["Grid"]
     258 [-]: DUPCLOSURE R6 K73 []
     259 [-]: SETTABLEKS R6 R5 K74 ["GetElementByTier"]
     260 [-]: GETUPVAL R6 0
     261 [-]: GETTABLEKS R5 R6 K56 ["Grid"]
     262 [-]: NEWCLOSURE R6 P6
     263 [-]: MOVE R2 R3   
     264 [-]: SETTABLEKS R6 R5 K75 ["mClipCreatedCallback"]
     265 [-]: GETUPVAL R6 0
     266 [-]: GETTABLEKS R5 R6 K56 ["Grid"]
     267 [-]: NEWCLOSURE R6 P7
     268 [-]: MOVE R2 R0   
     269 [-]: MOVE R2 R2   
     270 [-]: MOVE R2 R3   
     271 [-]: SETTABLEKS R6 R5 K76 ["mElementDrawCallback"]
     272 [-]: GETUPVAL R6 0
     273 [-]: GETTABLEKS R5 R6 K56 ["Grid"]
     274 [-]: DUPCLOSURE R6 K77 []
     275 [-]: MOVE R2 R2   
     276 [-]: MOVE R2 R0   
     277 [-]: MOVE R2 R6   
     278 [-]: MOVE R2 R8   
     279 [-]: SETTABLEKS R6 R5 K78 ["mOnFocusedCallback"]
     280 [-]: GETUPVAL R6 0
     281 [-]: GETTABLEKS R5 R6 K56 ["Grid"]
     282 [-]: DUPCLOSURE R6 K79 []
     283 [-]: MOVE R2 R6   
     284 [-]: MOVE R2 R0   
     285 [-]: SETTABLEKS R6 R5 K80 ["mOnUnfocusedCallback"]
     286 [-]: GETUPVAL R7 0
     287 [-]: GETTABLEKS R6 R7 K56 ["Grid"]
     288 [-]: GETTABLEKS R5 R6 K59 ["mInitDims"]
     289 [-]: LOADN R6 110 
     290 [-]: SETTABLEKS R6 R5 K81 ["Backer"]
     291 [-]: GETUPVAL R7 0
     292 [-]: GETTABLEKS R6 R7 K56 ["Grid"]
     293 [-]: GETTABLEKS R5 R6 K59 ["mInitDims"]
     294 [-]: LOADN R6 101 
     295 [-]: SETTABLEKS R6 R5 K82 ["IconFade"]
     296 [-]: GETUPVAL R7 0
     297 [-]: GETTABLEKS R6 R7 K56 ["Grid"]
     298 [-]: GETTABLEKS R5 R6 K59 ["mInitDims"]
     299 [-]: LOADN R6 94  
     300 [-]: SETTABLEKS R6 R5 K83 ["Icon"]
     301 [-]: GETUPVAL R7 0
     302 [-]: GETTABLEKS R6 R7 K56 ["Grid"]
     303 [-]: GETTABLEKS R5 R6 K59 ["mInitDims"]
     304 [-]: LOADN R6 116 
     305 [-]: SETTABLEKS R6 R5 K84 ["BackerEdge"]
     306 [-]: GETUPVAL R7 0
     307 [-]: GETTABLEKS R6 R7 K56 ["Grid"]
     308 [-]: GETTABLEKS R5 R6 K59 ["mInitDims"]
     309 [-]: LOADN R6 124 
     310 [-]: SETTABLEKS R6 R5 K85 ["BackerEdge2"]
     311 [-]: GETUPVAL R7 0
     312 [-]: GETTABLEKS R6 R7 K56 ["Grid"]
     313 [-]: GETTABLEKS R5 R6 K59 ["mInitDims"]
     314 [-]: LOADN R6 130 
     315 [-]: SETTABLEKS R6 R5 K86 ["CurrTier"]
     316 [-]: GETUPVAL R7 0
     317 [-]: GETTABLEKS R6 R7 K56 ["Grid"]
     318 [-]: GETTABLEKS R5 R6 K59 ["mInitDims"]
     319 [-]: DUPTABLE R6 90
     320 [-]: GETIMPORT R7 5 [nil]
     321 [-]: GETUPVAL R11 0
     322 [-]: GETTABLEKS R10 R11 K56 ["Grid"]
     323 [-]: GETTABLEKS R9 R10 K91 ["mClipName"]
     324 [-]: LOADK R10 K92 ["Highlight"]
     325 [-]: LOADN R11 1  
     326 [-]: NAMECALL R7 R7 K93 [0x2CE15376]
     327 [-]: CALL R7 4 1  
     328 [-]: SETTABLEKS R7 R6 K87 ["Y"]
     329 [-]: GETIMPORT R7 5 [nil]
     330 [-]: GETUPVAL R11 0
     331 [-]: GETTABLEKS R10 R11 K56 ["Grid"]
     332 [-]: GETTABLEKS R9 R10 K91 ["mClipName"]
     333 [-]: LOADK R10 K92 ["Highlight"]
     334 [-]: LOADN R11 12 
     335 [-]: NAMECALL R7 R7 K93 [0x2CE15376]
     336 [-]: CALL R7 4 1  
     337 [-]: SETTABLEKS R7 R6 K88 ["W"]
     338 [-]: GETIMPORT R7 5 [nil]
     339 [-]: GETUPVAL R11 0
     340 [-]: GETTABLEKS R10 R11 K56 ["Grid"]
     341 [-]: GETTABLEKS R9 R10 K91 ["mClipName"]
     342 [-]: LOADK R10 K92 ["Highlight"]
     343 [-]: LOADN R11 13 
     344 [-]: NAMECALL R7 R7 K93 [0x2CE15376]
     345 [-]: CALL R7 4 1  
     346 [-]: SETTABLEKS R7 R6 K89 ["H"]
     347 [-]: SETTABLEKS R6 R5 K92 ["Highlight"]
     348 [-]: GETUPVAL R7 0
     349 [-]: GETTABLEKS R6 R7 K56 ["Grid"]
     350 [-]: GETTABLEKS R5 R6 K59 ["mInitDims"]
     351 [-]: GETIMPORT R6 5 [nil]
     352 [-]: GETUPVAL R10 0
     353 [-]: GETTABLEKS R9 R10 K56 ["Grid"]
     354 [-]: GETTABLEKS R8 R9 K91 ["mClipName"]
     355 [-]: LOADK R9 K94 ["Tier"]
     356 [-]: LOADN R10 1  
     357 [-]: NAMECALL R6 R6 K93 [0x2CE15376]
     358 [-]: CALL R6 4 1  
     359 [-]: SETTABLEKS R6 R5 K94 ["Tier"]
     360 [-]: GETUPVAL R6 9
     361 [-]: GETTABLEKS R5 R6 K95 [0x2ADF63D9]
     362 [-]: GETIMPORT R6 5 [nil]
     363 [-]: LOADK R7 K96 ["RewardPanel.XpBar"]
     364 [-]: GETUPVAL R8 3
     365 [-]: GETIMPORT R9 98 [nil]
     366 [-]: CALL R5 4 0  
     367 [-]: GETIMPORT R5 5 [nil]
     368 [-]: LOADK R7 K99 ["RewardPanel.BottomFade"]
     369 [-]: GETIMPORT R8 101 [nil]
     370 [-]: NAMECALL R5 R5 K34 [0x1CB415C1]
     371 [-]: CALL R5 3 0  
     372 [-]: GETIMPORT R5 5 [nil]
     373 [-]: LOADK R7 K99 ["RewardPanel.BottomFade"]
     374 [-]: LOADN R8 9   
     375 [-]: GETUPVAL R10 3
     376 [-]: GETTABLEKS R9 R10 K102 ["Background1"]
     377 [-]: NAMECALL R5 R5 K37 [0x67BC869F]
     378 [-]: CALL R5 4 0  
     379 [-]: RETURN R0 0  


; Name:            
; Defined at line: 1064
; #Upvalues:       8
; #Parameters:     0
; Is_vararg:       0
; Max Stack Size:  16

       0 [-]: GETUPVAL R0 0
       1 [-]: CALL R0 0 0  
       2 [-]: NEWTABLE R0 0 0
       3 [-]: GETUPVAL R2 1
       4 [-]: GETUPVAL R3 2
       5 [-]: GETTABLE R1 R2 R3
       6 [-]: LOADB R2 0   
       7 [-]: GETUPVAL R3 3
       8 [-]: LOADN R4 0   
       9 [-]: SETTABLEKS R4 R3 K0 ["Tier"]
      10 [-]: GETUPVAL R3 3
      11 [-]: LOADN R4 10  
      12 [-]: SETTABLEKS R4 R3 K1 ["IconCycleTimer"]
      13 [-]: LOADN R5 1   
      14 [-]: GETTABLEKS R6 R1 K2 ["mPendingRewards"]
      15 [-]: LENGTH R3 R6 
      16 [-]: LOADN R4 1   
      17 [-]: FORNPREP R3 L9
L 0:  18 [-]: DUPTABLE R6 4
      19 [-]: NEWTABLE R7 0 0
      20 [-]: SETTABLEKS R7 R6 K3 ["RewardInfos"]
      21 [-]: GETTABLEKS R8 R1 K2 ["mPendingRewards"]
      22 [-]: GETTABLE R7 R8 R5
      23 [-]: LOADN R10 1  
      24 [-]: GETTABLEKS R11 R7 K5 ["mRewards"]
      25 [-]: LENGTH R8 R11
      26 [-]: LOADN R9 1   
      27 [-]: FORNPREP R8 L4
L 1:  28 [-]: GETTABLEKS R13 R7 K5 ["mRewards"]
      29 [-]: GETTABLE R12 R13 R10
      30 [-]: GETTABLEKS R11 R12 K6 ["mStoreItem"]
      31 [-]: FASTCALL1 62 R11 L2
      32 [-]: MOVE R13 R11 
      33 [-]: GETIMPORT R12 8 [nil]
      34 [-]: CALL R12 1 1 
L 2:  35 [-]: JUMPIF R12 L3
      36 [-]: GETUPVAL R12 4
      37 [-]: GETTABLEKS R14 R7 K5 ["mRewards"]
      38 [-]: GETTABLE R13 R14 R10
      39 [-]: MUL R14 R5 R10
      40 [-]: CALL R12 2 1 
      41 [-]: JUMPXEQKNIL R12 L3
      42 [-]: GETTABLEKS R14 R6 K3 ["RewardInfos"]
      43 [-]: FASTCALL2 52 R14 R12 L3
      44 [-]: MOVE R15 R12 
      45 [-]: GETIMPORT R13 11 [nil]
      46 [-]: CALL R13 2 0 
L 3:  47 [-]: FORNLOOP R8 L1
L 4:  48 [-]: SETTABLEKS R5 R6 K12 ["mNum"]
      49 [-]: GETTABLEKS R9 R1 K13 ["mEarnedAmount"]
      50 [-]: GETTABLEKS R10 R7 K14 ["mRequiredTotalXp"]
      51 [-]: JUMPIFLE R10 R9 L5
      52 [-]: LOADB R8 0 +1
L 5:  53 [-]: LOADB R8 1   
L 6:  54 [-]: SETTABLEKS R8 R6 K15 ["mEarned"]
      55 [-]: LOADN R8 1   
      56 [-]: SETTABLEKS R8 R6 K16 ["mIconIndex"]
      57 [-]: GETTABLEKS R8 R6 K15 ["mEarned"]
      58 [-]: JUMPIF R8 L7 
      59 [-]: JUMPIF R2 L7 
      60 [-]: GETUPVAL R8 3
      61 [-]: GETTABLEKS R9 R6 K12 ["mNum"]
      62 [-]: SETTABLEKS R9 R8 K0 ["Tier"]
      63 [-]: LOADB R2 1   
L 7:  64 [-]: FASTCALL2 52 R0 R6 L8
      65 [-]: MOVE R9 R0   
      66 [-]: MOVE R10 R6  
      67 [-]: GETIMPORT R8 11 [nil]
      68 [-]: CALL R8 2 0  
L 8:  69 [-]: FORNLOOP R3 L0
L 9:  70 [-]: JUMPIF R2 L10
      71 [-]: GETUPVAL R3 3
      72 [-]: GETTABLEKS R6 R1 K2 ["mPendingRewards"]
      73 [-]: LENGTH R5 R6 
      74 [-]: ADDK R4 R5 K17 [1]
      75 [-]: SETTABLEKS R4 R3 K0 ["Tier"]
L10:  76 [-]: LOADN R5 1   
      77 [-]: LENGTH R3 R0 
      78 [-]: LOADN R4 1   
      79 [-]: FORNPREP R3 L14
L11:  80 [-]: GETTABLE R6 R0 R5
      81 [-]: JUMPXEQKN R5 K18 L12 NOT [4]
      82 [-]: GETTABLEN R6 R0 6
      83 [-]: JUMP L13
    
L12:  84 [-]: JUMPXEQKN R5 K19 L13 NOT [6]
      85 [-]: GETTABLEN R6 R0 4
L13:  86 [-]: GETUPVAL R8 3
      87 [-]: GETTABLEKS R7 R8 K20 ["Grid"]
      88 [-]: MOVE R9 R6   
      89 [-]: LOADB R10 1  
      90 [-]: NAMECALL R7 R7 K21 [0xBAD4316F]
      91 [-]: CALL R7 3 0  
      92 [-]: FORNLOOP R3 L11
L14:  93 [-]: GETUPVAL R4 5
      94 [-]: GETTABLEKS R3 R4 K22 [0x260420F5]
      95 [-]: GETIMPORT R4 24 [nil]
      96 [-]: LOADK R5 K25 ["RewardPanel.XpBar"]
      97 [-]: MOVE R6 R1   
      98 [-]: GETUPVAL R7 3
      99 [-]: GETUPVAL R8 6
     100 [-]: GETUPVAL R10 7
     101 [-]: GETTABLEKS R9 R10 K26 ["mXpPerRepeatedReward"]
     102 [-]: CALL R3 6 0  
     103 [-]: GETIMPORT R3 24 [nil]
     104 [-]: LOADK R5 K25 ["RewardPanel.XpBar"]
     105 [-]: LOADN R6 11  
     106 [-]: LOADB R7 1   
     107 [-]: NAMECALL R3 R3 K27 [0xAADE900E]
     108 [-]: CALL R3 4 0  
     109 [-]: GETUPVAL R4 3
     110 [-]: GETTABLEKS R3 R4 K20 ["Grid"]
     111 [-]: NAMECALL R3 R3 K28 [0x71E9AC81]
     112 [-]: CALL R3 1 0  
     113 [-]: DUPTABLE R3 29
     114 [-]: NEWTABLE R4 0 0
     115 [-]: SETTABLEKS R4 R3 K3 ["RewardInfos"]
     116 [-]: LOADN R4 1   
     117 [-]: SETTABLEKS R4 R3 K16 ["mIconIndex"]
     118 [-]: GETUPVAL R5 3
     119 [-]: GETTABLEKS R4 R5 K0 ["Tier"]
     120 [-]: GETTABLEKS R7 R1 K2 ["mPendingRewards"]
     121 [-]: LENGTH R6 R7 
     122 [-]: ADDK R5 R6 K17 [1]
     123 [-]: JUMPIFNOTLE R5 R4 L19
     124 [-]: LOADB R4 1   
     125 [-]: SETTABLEKS R4 R3 K30 ["mIsExtra"]
     126 [-]: GETIMPORT R4 32 [nil]
     127 [-]: GETUPVAL R6 7
     128 [-]: GETTABLEKS R5 R6 K33 ["mRepeatedRewards"]
     129 [-]: CALL R4 1 1  
     130 [-]: FASTCALL1 62 R4 L15
     131 [-]: MOVE R6 R4   
     132 [-]: GETIMPORT R5 8 [nil]
     133 [-]: CALL R5 1 1  
L15: 134 [-]: JUMPIF R5 L23
     135 [-]: LOADN R7 0   
     136 [-]: NAMECALL R5 R4 K34 [0x509D9F9E]
     137 [-]: CALL R5 2 1  
     138 [-]: LOADN R8 0   
     139 [-]: SUBK R6 R5 K17 [1]
     140 [-]: LOADN R7 1   
     141 [-]: FORNPREP R6 L23
L16: 142 [-]: LOADN R11 0  
     143 [-]: MOVE R12 R8  
     144 [-]: NAMECALL R9 R4 K35 [0x04D63414]
     145 [-]: CALL R9 3 1  
     146 [-]: FASTCALL1 62 R9 L17
     147 [-]: MOVE R11 R9  
     148 [-]: GETIMPORT R10 8 [nil]
     149 [-]: CALL R10 1 1 
L17: 150 [-]: JUMPIF R10 L18
     151 [-]: GETTABLEKS R11 R3 K3 ["RewardInfos"]
     152 [-]: GETUPVAL R12 4
     153 [-]: MOVE R13 R9  
     154 [-]: MOVE R14 R8  
     155 [-]: CALL R12 2 -1
     156 [-]: FASTCALL 52 L18
     157 [-]: GETIMPORT R10 11 [nil]
     158 [-]: CALL R10 -1 0
L18: 159 [-]: FORNLOOP R6 L16
     160 [-]: JUMP L23
    
L19: 161 [-]: LOADB R4 1   
     162 [-]: SETTABLEKS R4 R3 K36 ["mIsCurrent"]
     163 [-]: GETTABLEKS R5 R1 K2 ["mPendingRewards"]
     164 [-]: GETUPVAL R7 3
     165 [-]: GETTABLEKS R6 R7 K0 ["Tier"]
     166 [-]: GETTABLE R4 R5 R6
     167 [-]: LOADN R7 1   
     168 [-]: GETTABLEKS R8 R4 K5 ["mRewards"]
     169 [-]: LENGTH R5 R8 
     170 [-]: LOADN R6 1   
     171 [-]: FORNPREP R5 L23
L20: 172 [-]: GETTABLEKS R10 R4 K5 ["mRewards"]
     173 [-]: GETTABLE R9 R10 R7
     174 [-]: GETTABLEKS R8 R9 K6 ["mStoreItem"]
     175 [-]: FASTCALL1 62 R8 L21
     176 [-]: MOVE R10 R8  
     177 [-]: GETIMPORT R9 8 [nil]
     178 [-]: CALL R9 1 1  
L21: 179 [-]: JUMPIF R9 L22
     180 [-]: GETUPVAL R9 4
     181 [-]: GETTABLEKS R11 R4 K5 ["mRewards"]
     182 [-]: GETTABLE R10 R11 R7
     183 [-]: MOVE R11 R7  
     184 [-]: CALL R9 2 1  
     185 [-]: JUMPXEQKNIL R9 L22
     186 [-]: GETTABLEKS R11 R3 K3 ["RewardInfos"]
     187 [-]: FASTCALL2 52 R11 R9 L22
     188 [-]: MOVE R12 R9  
     189 [-]: GETIMPORT R10 11 [nil]
     190 [-]: CALL R10 2 0 
L22: 191 [-]: FORNLOOP R5 L20
L23: 192 [-]: LOADK R4 K37 ["RewardPanel.ExtraReward.Reward"]
     193 [-]: SETTABLEKS R4 R3 K38 ["mClipName"]
     194 [-]: GETUPVAL R6 3
     195 [-]: GETTABLEKS R5 R6 K20 ["Grid"]
     196 [-]: GETTABLEKS R4 R5 K39 ["mClipCreatedCallback"]
     197 [-]: GETTABLEKS R5 R3 K38 ["mClipName"]
     198 [-]: CALL R4 1 0  
     199 [-]: GETUPVAL R6 3
     200 [-]: GETTABLEKS R5 R6 K20 ["Grid"]
     201 [-]: GETTABLEKS R4 R5 K40 ["mElementDrawCallback"]
     202 [-]: MOVE R5 R3   
     203 [-]: CALL R4 1 0  
     204 [-]: GETIMPORT R4 24 [nil]
     205 [-]: GETTABLEKS R6 R3 K38 ["mClipName"]
     206 [-]: LOADK R7 K41 ["Btn"]
     207 [-]: LOADN R8 85  
     208 [-]: LOADN R9 20  
     209 [-]: NAMECALL R4 R4 K42 [0xF64B7262]
     210 [-]: CALL R4 5 0  
     211 [-]: GETIMPORT R4 24 [nil]
     212 [-]: GETTABLEKS R7 R3 K38 ["mClipName"]
     213 [-]: LOADK R8 K43 [".Btn"]
     214 [-]: CONCAT R6 R7 R8
     215 [-]: LOADK R7 K44 ["RewardFocused"]
     216 [-]: LOADK R8 K45 ["RewardUnfocused"]
     217 [-]: LOADNIL R9   
     218 [-]: LOADNIL R10  
     219 [-]: NAMECALL R4 R4 K46 [0x1E5B5CFE]
     220 [-]: CALL R4 6 0  
     221 [-]: GETIMPORT R4 24 [nil]
     222 [-]: GETTABLEKS R6 R3 K38 ["mClipName"]
     223 [-]: LOADK R7 K47 ["LineStraightRight"]
     224 [-]: LOADN R8 11  
     225 [-]: LOADB R9 0   
     226 [-]: NAMECALL R4 R4 K48 [0xC0A3774B]
     227 [-]: CALL R4 5 0  
     228 [-]: GETUPVAL R5 3
     229 [-]: GETTABLEKS R4 R5 K20 ["Grid"]
     230 [-]: SETTABLEKS R3 R4 K49 ["mExtraReward"]
     231 [-]: GETIMPORT R4 24 [nil]
     232 [-]: LOADK R6 K50 ["RewardPanel.ExtraReward"]
     233 [-]: LOADN R7 11  
     234 [-]: LOADB R8 1   
     235 [-]: NAMECALL R4 R4 K27 [0xAADE900E]
     236 [-]: CALL R4 4 0  
     237 [-]: GETIMPORT R4 24 [nil]
     238 [-]: LOADK R6 K51 ["RewardPanel.ExtraReward.LeftArrow"]
     239 [-]: LOADN R7 11  
     240 [-]: LOADB R8 0   
     241 [-]: GETTABLEKS R10 R3 K3 ["RewardInfos"]
     242 [-]: LENGTH R9 R10
     243 [-]: LOADN R10 1  
     244 [-]: JUMPIFNOTLT R10 R9 L24
     245 [-]: GETTABLEKS R8 R3 K30 ["mIsExtra"]
L24: 246 [-]: NAMECALL R4 R4 K27 [0xAADE900E]
     247 [-]: CALL R4 4 0  
     248 [-]: GETIMPORT R4 24 [nil]
     249 [-]: LOADK R6 K52 ["RewardPanel.ExtraReward.RightArrow"]
     250 [-]: LOADN R7 11  
     251 [-]: LOADB R8 0   
     252 [-]: GETTABLEKS R10 R3 K3 ["RewardInfos"]
     253 [-]: LENGTH R9 R10
     254 [-]: LOADN R10 1  
     255 [-]: JUMPIFNOTLT R10 R9 L25
     256 [-]: GETTABLEKS R8 R3 K30 ["mIsExtra"]
L25: 257 [-]: NAMECALL R4 R4 K27 [0xAADE900E]
     258 [-]: CALL R4 4 0  
     259 [-]: GETUPVAL R6 3
     260 [-]: GETTABLEKS R5 R6 K20 ["Grid"]
     261 [-]: GETTABLEKS R4 R5 K53 ["RefreshExtraLabel"]
     262 [-]: MOVE R5 R3   
     263 [-]: CALL R4 1 0  
     264 [-]: GETIMPORT R4 24 [nil]
     265 [-]: LOADK R6 K37 ["RewardPanel.ExtraReward.Reward"]
     266 [-]: LOADN R7 1   
     267 [-]: NAMECALL R4 R4 K54 [0x91A24E4B]
     268 [-]: CALL R4 3 1  
     269 [-]: LOADN R5 0   
     270 [-]: GETTABLEKS R6 R3 K30 ["mIsExtra"]
     271 [-]: JUMPIFNOT R6 L26
     272 [-]: GETIMPORT R6 24 [nil]
     273 [-]: LOADK R8 K55 ["RewardPanel.ExtraReward.Label"]
     274 [-]: LOADN R9 33  
     275 [-]: NAMECALL R6 R6 K54 [0x91A24E4B]
     276 [-]: CALL R6 3 1  
     277 [-]: DIVK R7 R6 K56 [2]
     278 [-]: SUB R5 R5 R7 
     279 [-]: JUMP L27
    
L26: 280 [-]: SUBK R5 R5 K57 [55]
L27: 281 [-]: GETIMPORT R6 24 [nil]
     282 [-]: LOADK R8 K37 ["RewardPanel.ExtraReward.Reward"]
     283 [-]: LOADN R9 1   
     284 [-]: MOVE R10 R4  
     285 [-]: NAMECALL R6 R6 K58 [0x67BC869F]
     286 [-]: CALL R6 4 0  
     287 [-]: GETIMPORT R6 24 [nil]
     288 [-]: LOADK R8 K37 ["RewardPanel.ExtraReward.Reward"]
     289 [-]: LOADN R9 0   
     290 [-]: MOVE R10 R5  
     291 [-]: NAMECALL R6 R6 K58 [0x67BC869F]
     292 [-]: CALL R6 4 0  
     293 [-]: GETIMPORT R6 24 [nil]
     294 [-]: LOADK R8 K51 ["RewardPanel.ExtraReward.LeftArrow"]
     295 [-]: LOADN R9 0   
     296 [-]: SUBK R10 R5 K59 [85]
     297 [-]: NAMECALL R6 R6 K58 [0x67BC869F]
     298 [-]: CALL R6 4 0  
     299 [-]: GETIMPORT R6 24 [nil]
     300 [-]: LOADK R8 K52 ["RewardPanel.ExtraReward.RightArrow"]
     301 [-]: LOADN R9 0   
     302 [-]: ADDK R10 R5 K59 [85]
     303 [-]: NAMECALL R6 R6 K58 [0x67BC869F]
     304 [-]: CALL R6 4 0  
     305 [-]: GETIMPORT R6 24 [nil]
     306 [-]: LOADK R8 K51 ["RewardPanel.ExtraReward.LeftArrow"]
     307 [-]: LOADN R9 1   
     308 [-]: MOVE R10 R4  
     309 [-]: NAMECALL R6 R6 K58 [0x67BC869F]
     310 [-]: CALL R6 4 0  
     311 [-]: GETIMPORT R6 24 [nil]
     312 [-]: LOADK R8 K52 ["RewardPanel.ExtraReward.RightArrow"]
     313 [-]: LOADN R9 1   
     314 [-]: MOVE R10 R4  
     315 [-]: NAMECALL R6 R6 K58 [0x67BC869F]
     316 [-]: CALL R6 4 0  
     317 [-]: RETURN R0 0  


; Name:            
; Defined at line: 1168
; #Upvalues:       5
; #Parameters:     0
; Is_vararg:       0
; Max Stack Size:  11

       0 [-]: GETUPVAL R0 0
       1 [-]: GETUPVAL R2 1
       2 [-]: GETTABLEKS R1 R2 K0 [0x06D055F9]
       3 [-]: GETUPVAL R2 2
       4 [-]: LOADN R3 300 
       5 [-]: LOADN R4 470 
       6 [-]: CALL R1 3 1  
       7 [-]: SETTABLEKS R1 R0 K1 ["mForcedHorizontalSeparation"]
       8 [-]: GETUPVAL R0 0
       9 [-]: GETUPVAL R1 2
      10 [-]: SETTABLEKS R1 R0 K2 ["CanPreviewElements"]
      11 [-]: GETUPVAL R0 2
      12 [-]: JUMPIFNOT R0 L0
      13 [-]: GETUPVAL R0 0
      14 [-]: DUPCLOSURE R2 K3 []
      15 [-]: MOVE R2 R3   
      16 [-]: NAMECALL R0 R0 K4 [0xEA061E98]
      17 [-]: CALL R0 2 0  
L 0:  18 [-]: GETUPVAL R0 0
      19 [-]: NAMECALL R0 R0 K5 [0x71E9AC81]
      20 [-]: CALL R0 1 0  
      21 [-]: GETIMPORT R0 7 [nil]
      22 [-]: LOADK R2 K8 ["FrameSelect.FrameList"]
      23 [-]: LOADN R3 11  
      24 [-]: LOADB R4 1   
      25 [-]: NAMECALL R0 R0 K9 [0xAADE900E]
      26 [-]: CALL R0 4 0  
      27 [-]: GETIMPORT R0 7 [nil]
      28 [-]: LOADK R2 K8 ["FrameSelect.FrameList"]
      29 [-]: LOADN R3 0   
      30 [-]: GETUPVAL R8 0
      31 [-]: NAMECALL R8 R8 K11 [0x5FBDDC1A]
      32 [-]: CALL R8 1 1  
      33 [-]: GETUPVAL R10 0
      34 [-]: GETTABLEKS R9 R10 K1 ["mForcedHorizontalSeparation"]
      35 [-]: MUL R7 R8 R9 
      36 [-]: DIVK R6 R7 K10 [2]
      37 [-]: MINUS R5 R6  
      38 [-]: GETUPVAL R8 0
      39 [-]: GETTABLEKS R7 R8 K1 ["mForcedHorizontalSeparation"]
      40 [-]: DIVK R6 R7 K10 [2]
      41 [-]: ADD R4 R5 R6 
      42 [-]: NAMECALL R0 R0 K12 [0x67BC869F]
      43 [-]: CALL R0 4 0  
      44 [-]: LOADK R1 K13 ["/Lotus/Language/Duviri/"]
      45 [-]: GETUPVAL R3 1
      46 [-]: GETTABLEKS R2 R3 K0 [0x06D055F9]
      47 [-]: GETUPVAL R3 2
      48 [-]: LOADK R4 K14 ["EndlessSetupIncarnonHint"]
      49 [-]: LOADK R5 K15 ["EndlessSetupFrameHint"]
      50 [-]: CALL R2 3 1  
      51 [-]: CONCAT R0 R1 R2
      52 [-]: GETIMPORT R1 7 [nil]
      53 [-]: LOADK R3 K16 ["FrameSelect.Hint.text"]
      54 [-]: MOVE R4 R0   
      55 [-]: NAMECALL R1 R1 K17 [0x20B98DB3]
      56 [-]: CALL R1 3 0  
      57 [-]: GETIMPORT R1 7 [nil]
      58 [-]: LOADK R3 K18 ["FrameSelect.Hint"]
      59 [-]: LOADN R4 11  
      60 [-]: LOADB R5 1   
      61 [-]: NAMECALL R1 R1 K9 [0xAADE900E]
      62 [-]: CALL R1 4 0  
      63 [-]: GETIMPORT R1 7 [nil]
      64 [-]: LOADK R3 K19 ["FrameSelect.Title"]
      65 [-]: LOADN R4 11  
      66 [-]: LOADB R5 1   
      67 [-]: NAMECALL R1 R1 K9 [0xAADE900E]
      68 [-]: CALL R1 4 0  
      69 [-]: GETUPVAL R1 4
      70 [-]: GETUPVAL R3 2
      71 [-]: NAMECALL R1 R1 K20 [0x368AD758]
      72 [-]: CALL R1 2 0  
      73 [-]: GETUPVAL R1 4
      74 [-]: NAMECALL R1 R1 K21 [0xD3B32E08]
      75 [-]: CALL R1 1 0  
      76 [-]: RETURN R0 0  


; Name:            
; Defined at line: 1195
; #Upvalues:       8
; #Parameters:     0
; Is_vararg:       0
; Max Stack Size:  14

       0 [-]: GETUPVAL R0 0
       1 [-]: LOADB R2 1   
       2 [-]: LOADB R3 1   
       3 [-]: NAMECALL R0 R0 K0 [0x7C09C373]
       4 [-]: CALL R0 3 0  
       5 [-]: GETUPVAL R0 0
       6 [-]: NEWTABLE R1 0 0
       7 [-]: SETTABLEKS R1 R0 K1 ["mSelectedElementIds"]
       8 [-]: GETIMPORT R0 3 [nil]
       9 [-]: LOADK R2 K4 ["FrameSelect.FrameList"]
      10 [-]: LOADN R3 11  
      11 [-]: LOADB R4 0   
      12 [-]: NAMECALL R0 R0 K5 [0xAADE900E]
      13 [-]: CALL R0 4 0  
      14 [-]: GETIMPORT R0 3 [nil]
      15 [-]: LOADK R2 K6 ["FrameSelect.Hint"]
      16 [-]: LOADN R3 11  
      17 [-]: LOADB R4 0   
      18 [-]: NAMECALL R0 R0 K5 [0xAADE900E]
      19 [-]: CALL R0 4 0  
      20 [-]: GETIMPORT R0 3 [nil]
      21 [-]: LOADK R2 K7 ["FrameSelect.Title"]
      22 [-]: LOADN R3 11  
      23 [-]: LOADB R4 0   
      24 [-]: NAMECALL R0 R0 K5 [0xAADE900E]
      25 [-]: CALL R0 4 0  
      26 [-]: GETUPVAL R0 1
      27 [-]: LOADB R2 0   
      28 [-]: NAMECALL R0 R0 K8 [0x368AD758]
      29 [-]: CALL R0 2 0  
      30 [-]: NEWTABLE R0 0 0
      31 [-]: GETUPVAL R2 2
      32 [-]: GETTABLEKS R1 R2 K9 ["mChoices"]
      33 [-]: GETIMPORT R2 11 [nil]
      34 [-]: GETUPVAL R3 3
      35 [-]: CALL R2 1 3  
      36 [-]: FORGPREP_INEXT R2 L2
L 0:  37 [-]: GETUPVAL R8 4
      38 [-]: GETTABLEKS R7 R8 K12 [0x08681F50]
      39 [-]: GETIMPORT R8 3 [nil]
      40 [-]: GETIMPORT R9 14 [nil]
      41 [-]: GETTABLE R11 R1 R6
      42 [-]: GETTABLEKS R10 R11 K15 ["mChoiceParent"]
      43 [-]: CALL R9 1 1  
      44 [-]: LOADNIL R10  
      45 [-]: LOADNIL R11  
      46 [-]: LOADNIL R12  
      47 [-]: LOADB R13 1  
      48 [-]: CALL R7 6 1  
      49 [-]: GETTABLE R9 R1 R6
      50 [-]: GETTABLEKS R8 R9 K16 ["mTag"]
      51 [-]: NAMECALL R8 R8 K17 [0x6D604BA7]
      52 [-]: CALL R8 1 1  
      53 [-]: SETTABLEKS R8 R7 K16 ["mTag"]
      54 [-]: MOVE R9 R0   
      55 [-]: GETTABLEKS R10 R7 K18 ["Type"]
      56 [-]: NAMECALL R10 R10 K19 [0xED4E0128]
      57 [-]: CALL R10 1 -1
      58 [-]: FASTCALL 52 L1
      59 [-]: GETIMPORT R8 22 [nil]
      60 [-]: CALL R8 -1 0 
L 1:  61 [-]: GETUPVAL R8 0
      62 [-]: MOVE R10 R7  
      63 [-]: LOADB R11 1  
      64 [-]: NAMECALL R8 R8 K23 [0xBAD4316F]
      65 [-]: CALL R8 3 0  
L 2:  66 [-]: FORGLOOP R2 L0 2 [inext]
      67 [-]: LENGTH R2 R0 
      68 [-]: LOADN R3 0   
      69 [-]: JUMPIFNOTLT R3 R2 L3
      70 [-]: GETUPVAL R2 5
      71 [-]: LOADB R4 1   
      72 [-]: NAMECALL R2 R2 K24 [0x46610C50]
      73 [-]: CALL R2 2 0  
      74 [-]: GETUPVAL R2 6
      75 [-]: GETIMPORT R3 27 [nil]
      76 [-]: MOVE R4 R0   
      77 [-]: CALL R3 1 1  
      78 [-]: SETTABLEKS R3 R2 K28 ["Loader"]
      79 [-]: GETUPVAL R2 6
      80 [-]: LOADB R3 1   
      81 [-]: SETTABLEKS R3 R2 K29 ["IsLoading"]
      82 [-]: RETURN R0 0  
L 3:  83 [-]: GETUPVAL R2 7
      84 [-]: CALL R2 0 0  
      85 [-]: RETURN R0 0  


; Name:            
; Defined at line: 1222
; #Upvalues:       8
; #Parameters:     0
; Is_vararg:       0
; Max Stack Size:  14

       0 [-]: GETUPVAL R0 0
       1 [-]: LOADB R2 1   
       2 [-]: LOADB R3 1   
       3 [-]: NAMECALL R0 R0 K0 [0x7C09C373]
       4 [-]: CALL R0 3 0  
       5 [-]: GETIMPORT R0 2 [nil]
       6 [-]: LOADK R2 K3 ["FrameSelect.FrameList"]
       7 [-]: LOADN R3 11  
       8 [-]: LOADB R4 0   
       9 [-]: NAMECALL R0 R0 K4 [0xAADE900E]
      10 [-]: CALL R0 4 0  
      11 [-]: GETIMPORT R0 2 [nil]
      12 [-]: LOADK R2 K5 ["FrameSelect.Hint"]
      13 [-]: LOADN R3 11  
      14 [-]: LOADB R4 0   
      15 [-]: NAMECALL R0 R0 K4 [0xAADE900E]
      16 [-]: CALL R0 4 0  
      17 [-]: GETIMPORT R0 2 [nil]
      18 [-]: LOADK R2 K6 ["FrameSelect.Title"]
      19 [-]: LOADN R3 11  
      20 [-]: LOADB R4 0   
      21 [-]: NAMECALL R0 R0 K4 [0xAADE900E]
      22 [-]: CALL R0 4 0  
      23 [-]: GETUPVAL R0 1
      24 [-]: LOADB R2 0   
      25 [-]: NAMECALL R0 R0 K7 [0x368AD758]
      26 [-]: CALL R0 2 0  
      27 [-]: NEWTABLE R0 0 0
      28 [-]: GETUPVAL R2 2
      29 [-]: GETTABLEKS R1 R2 K8 ["mChoices"]
      30 [-]: GETIMPORT R2 10 [nil]
      31 [-]: GETUPVAL R3 3
      32 [-]: CALL R2 1 3  
      33 [-]: FORGPREP_INEXT R2 L4
L 0:  34 [-]: GETUPVAL R8 4
      35 [-]: GETTABLEKS R7 R8 K11 [0x08681F50]
      36 [-]: GETIMPORT R8 2 [nil]
      37 [-]: GETIMPORT R9 13 [nil]
      38 [-]: GETTABLE R11 R1 R6
      39 [-]: GETTABLEKS R10 R11 K14 ["mChoiceParent"]
      40 [-]: CALL R9 1 1  
      41 [-]: LOADNIL R10  
      42 [-]: LOADNIL R11  
      43 [-]: LOADNIL R12  
      44 [-]: LOADB R13 1  
      45 [-]: CALL R7 6 1  
      46 [-]: GETTABLE R9 R1 R6
      47 [-]: GETTABLEKS R8 R9 K15 ["mTag"]
      48 [-]: NAMECALL R8 R8 K16 [0x6D604BA7]
      49 [-]: CALL R8 1 1  
      50 [-]: SETTABLEKS R8 R7 K15 ["mTag"]
      51 [-]: GETTABLEKS R8 R7 K17 ["StoreItem"]
      52 [-]: NAMECALL R8 R8 K18 [0xA338DCE2]
      53 [-]: CALL R8 1 1  
      54 [-]: FASTCALL1 62 R8 L1
      55 [-]: MOVE R10 R8  
      56 [-]: GETIMPORT R9 20 [nil]
      57 [-]: CALL R9 1 1  
L 1:  58 [-]: JUMPIF R9 L2 
      59 [-]: MOVE R10 R0  
      60 [-]: NAMECALL R11 R8 K21 [0xED4E0128]
      61 [-]: CALL R11 1 -1
      62 [-]: FASTCALL 52 L2
      63 [-]: GETIMPORT R9 24 [nil]
      64 [-]: CALL R9 -1 0 
L 2:  65 [-]: MOVE R10 R0  
      66 [-]: GETTABLEKS R11 R7 K25 ["Type"]
      67 [-]: NAMECALL R11 R11 K21 [0xED4E0128]
      68 [-]: CALL R11 1 -1
      69 [-]: FASTCALL 52 L3
      70 [-]: GETIMPORT R9 24 [nil]
      71 [-]: CALL R9 -1 0 
L 3:  72 [-]: GETUPVAL R9 0
      73 [-]: MOVE R11 R7  
      74 [-]: LOADB R12 1  
      75 [-]: NAMECALL R9 R9 K26 [0xBAD4316F]
      76 [-]: CALL R9 3 0  
L 4:  77 [-]: FORGLOOP R2 L0 2 [inext]
      78 [-]: LENGTH R2 R0 
      79 [-]: LOADN R3 0   
      80 [-]: JUMPIFNOTLT R3 R2 L5
      81 [-]: GETUPVAL R2 5
      82 [-]: LOADB R4 1   
      83 [-]: NAMECALL R2 R2 K27 [0x46610C50]
      84 [-]: CALL R2 2 0  
      85 [-]: GETUPVAL R2 6
      86 [-]: GETIMPORT R3 30 [nil]
      87 [-]: MOVE R4 R0   
      88 [-]: CALL R3 1 1  
      89 [-]: SETTABLEKS R3 R2 K31 ["Loader"]
      90 [-]: GETUPVAL R2 6
      91 [-]: LOADB R3 1   
      92 [-]: SETTABLEKS R3 R2 K32 ["IsLoading"]
      93 [-]: RETURN R0 0  
L 5:  94 [-]: GETUPVAL R2 7
      95 [-]: CALL R2 0 0  
      96 [-]: RETURN R0 0  


; Name:            
; Defined at line: 1252
; #Upvalues:       5
; #Parameters:     2
; Is_vararg:       0
; Max Stack Size:  6

       0 [-]: GETIMPORT R3 2 [nil]
       1 [-]: FASTCALL1 62 R3 L0
       2 [-]: GETIMPORT R2 4 [nil]
       3 [-]: CALL R2 1 1  
L 0:   4 [-]: JUMPIF R2 L1 
       5 [-]: GETIMPORT R2 2 [nil]
       6 [-]: LOADK R4 K5 ["ShowBlockingMessage"]
       7 [-]: LOADK R5 K6 ["0"]
       8 [-]: NAMECALL R2 R2 K7 [0xE4162EED]
       9 [-]: CALL R2 3 0  
L 1:  10 [-]: JUMPIF R0 L2 
      11 [-]: GETIMPORT R2 9 [nil]
      12 [-]: NAMECALL R2 R2 K10 [0x32302B4A]
      13 [-]: CALL R2 1 0  
      14 [-]: RETURN R0 0  
L 2:  15 [-]: GETUPVAL R3 0
      16 [-]: GETTABLEKS R2 R3 K11 [0x659D451F]
      17 [-]: GETIMPORT R3 13 [nil]
      18 [-]: CALL R2 1 0  
      19 [-]: GETUPVAL R2 1
      20 [-]: JUMPIFNOT R2 L3
      21 [-]: GETUPVAL R2 2
      22 [-]: CALL R2 0 0  
      23 [-]: JUMP L4
     
L 3:  24 [-]: GETUPVAL R2 3
      25 [-]: CALL R2 0 0  
L 4:  26 [-]: LOADNIL R2   
      27 [-]: SETUPVAL R2 4
      28 [-]: RETURN R0 0  


; Name:            
; Defined at line: 1274
; #Upvalues:       3
; #Parameters:     1
; Is_vararg:       0
; Max Stack Size:  7

       0 [-]: GETIMPORT R1 1 [nil]
       1 [-]: MOVE R2 R0   
       2 [-]: CALL R1 1 1  
       3 [-]: LOADN R2 4   
       4 [-]: JUMPIFNOTEQ R1 R2 L4
       5 [-]: GETUPVAL R2 0
       6 [-]: GETTABLEKS R1 R2 K2 ["mSelectedElement"]
       7 [-]: FASTCALL1 62 R1 L0
       8 [-]: MOVE R3 R1   
       9 [-]: GETIMPORT R2 4 [nil]
      10 [-]: CALL R2 1 1  
L 0:  11 [-]: JUMPIFNOT R2 L1
      12 [-]: RETURN R0 0  
L 1:  13 [-]: GETUPVAL R3 1
      14 [-]: GETTABLEKS R2 R3 K5 [0x659D451F]
      15 [-]: GETIMPORT R4 7 [nil]
      16 [-]: GETTABLEKS R3 R4 K8 ["UISound_SweetenerTwo"]
      17 [-]: CALL R2 1 0  
      18 [-]: GETIMPORT R3 11 [nil]
      19 [-]: FASTCALL1 62 R3 L2
      20 [-]: GETIMPORT R2 4 [nil]
      21 [-]: CALL R2 1 1  
L 2:  22 [-]: JUMPIF R2 L3 
      23 [-]: GETIMPORT R2 11 [nil]
      24 [-]: LOADK R4 K12 ["ShowBlockingMessage"]
      25 [-]: LOADK R5 K13 ["2"]
      26 [-]: NAMECALL R2 R2 K14 [0xE4162EED]
      27 [-]: CALL R2 3 0  
L 3:  28 [-]: GETIMPORT R2 17 [nil]
      29 [-]: LOADN R3 0   
      30 [-]: NEWTABLE R4 0 1
      31 [-]: GETIMPORT R5 19 [nil]
      32 [-]: GETTABLEKS R6 R1 K20 ["mTag"]
      33 [-]: CALL R5 1 -1 
      34 [-]: SETLIST R4 R5 -1 [1]
      35 [-]: LOADK R5 K21 ["OnPathSelectionCommited"]
      36 [-]: CALL R2 3 1  
      37 [-]: SETUPVAL R2 2
      38 [-]: GETUPVAL R2 2
      39 [-]: NAMECALL R2 R2 K14 [0xE4162EED]
      40 [-]: CALL R2 1 0  
L 4:  41 [-]: RETURN R0 0  


; Name:            
; Defined at line: 1292
; #Upvalues:       2
; #Parameters:     1
; Is_vararg:       0
; Max Stack Size:  11

       0 [-]: GETIMPORT R1 1 [nil]
       1 [-]: MOVE R2 R0   
       2 [-]: CALL R1 1 1  
       3 [-]: LOADN R2 4   
       4 [-]: JUMPIFNOTEQ R1 R2 L8
       5 [-]: GETUPVAL R2 0
       6 [-]: GETTABLEKS R1 R2 K2 ["mSelectedElement"]
       7 [-]: FASTCALL1 62 R1 L0
       8 [-]: MOVE R3 R1   
       9 [-]: GETIMPORT R2 4 [nil]
      10 [-]: CALL R2 1 1  
L 0:  11 [-]: JUMPIFNOT R2 L1
      12 [-]: RETURN R0 0  
L 1:  13 [-]: NEWTABLE R2 0 0
      14 [-]: LOADN R5 1   
      15 [-]: GETUPVAL R7 0
      16 [-]: GETTABLEKS R6 R7 K5 ["mSelectedElementIds"]
      17 [-]: LENGTH R3 R6 
      18 [-]: LOADN R4 1   
      19 [-]: FORNPREP R3 L5
L 2:  20 [-]: GETUPVAL R6 0
      21 [-]: GETUPVAL R10 0
      22 [-]: GETTABLEKS R9 R10 K5 ["mSelectedElementIds"]
      23 [-]: GETTABLE R8 R9 R5
      24 [-]: NAMECALL R6 R6 K6 [0xCA30DFB6]
      25 [-]: CALL R6 2 1  
      26 [-]: FASTCALL1 62 R6 L3
      27 [-]: MOVE R8 R6   
      28 [-]: GETIMPORT R7 4 [nil]
      29 [-]: CALL R7 1 1  
L 3:  30 [-]: JUMPIF R7 L4 
      31 [-]: MOVE R8 R2   
      32 [-]: GETIMPORT R9 8 [nil]
      33 [-]: GETTABLEKS R10 R6 K9 ["mTag"]
      34 [-]: CALL R9 1 -1 
      35 [-]: FASTCALL 52 L4
      36 [-]: GETIMPORT R7 12 [nil]
      37 [-]: CALL R7 -1 0 
L 4:  38 [-]: FORNLOOP R3 L2
L 5:  39 [-]: GETIMPORT R4 15 [nil]
      40 [-]: FASTCALL1 62 R4 L6
      41 [-]: GETIMPORT R3 4 [nil]
      42 [-]: CALL R3 1 1  
L 6:  43 [-]: JUMPIF R3 L7 
      44 [-]: GETIMPORT R3 15 [nil]
      45 [-]: LOADK R5 K16 ["ShowBlockingMessage"]
      46 [-]: LOADK R6 K17 ["2"]
      47 [-]: NAMECALL R3 R3 K18 [0xE4162EED]
      48 [-]: CALL R3 3 0  
L 7:  49 [-]: GETIMPORT R3 21 [nil]
      50 [-]: LOADN R4 1   
      51 [-]: MOVE R5 R2   
      52 [-]: LOADK R6 K22 ["OnPathSelectionCommited"]
      53 [-]: CALL R3 3 1  
      54 [-]: SETUPVAL R3 1
      55 [-]: GETUPVAL R3 1
      56 [-]: NAMECALL R3 R3 K18 [0xE4162EED]
      57 [-]: CALL R3 1 0  
L 8:  58 [-]: RETURN R0 0  


; Name:            
; Defined at line: 1314
; #Upvalues:       2
; #Parameters:     0
; Is_vararg:       0
; Max Stack Size:  9

       0 [-]: NEWTABLE R0 0 0
       1 [-]: LOADN R3 1   
       2 [-]: GETUPVAL R5 0
       3 [-]: GETTABLEKS R4 R5 K0 ["mSelectedElementIds"]
       4 [-]: LENGTH R1 R4 
       5 [-]: LOADN R2 1   
       6 [-]: FORNPREP R1 L3
L 0:   7 [-]: GETUPVAL R4 0
       8 [-]: GETUPVAL R8 0
       9 [-]: GETTABLEKS R7 R8 K0 ["mSelectedElementIds"]
      10 [-]: GETTABLE R6 R7 R3
      11 [-]: NAMECALL R4 R4 K1 [0xCA30DFB6]
      12 [-]: CALL R4 2 1  
      13 [-]: FASTCALL1 62 R4 L1
      14 [-]: MOVE R6 R4   
      15 [-]: GETIMPORT R5 3 [nil]
      16 [-]: CALL R5 1 1  
L 1:  17 [-]: JUMPIF R5 L2 
      18 [-]: GETTABLEKS R7 R4 K4 ["mCachedName"]
      19 [-]: FASTCALL2 52 R0 R7 L2
      20 [-]: MOVE R6 R0   
      21 [-]: GETIMPORT R5 7 [nil]
      22 [-]: CALL R5 2 0  
L 2:  23 [-]: FORNLOOP R1 L0
L 3:  24 [-]: GETIMPORT R1 9 [nil]
      25 [-]: LOADK R3 K10 ["/Lotus/Language/Duviri/EndlessSetupIncarnonSelectConfirm"]
      26 [-]: LOADB R4 1   
      27 [-]: DUPTABLE R5 13
      28 [-]: GETTABLEN R6 R0 1
      29 [-]: SETTABLEKS R6 R5 K11 ["CHOICE_A"]
      30 [-]: GETTABLEN R6 R0 2
      31 [-]: SETTABLEKS R6 R5 K12 ["CHOICE_B"]
      32 [-]: NAMECALL R1 R1 K14 [0x42B04007]
      33 [-]: CALL R1 4 1  
      34 [-]: GETUPVAL R3 1
      35 [-]: GETTABLEKS R2 R3 K15 [0xDEDFDED7]
      36 [-]: MOVE R3 R1   
      37 [-]: LOADK R4 K16 ["OnItemSelectionConfirm"]
      38 [-]: CALL R2 2 0  
      39 [-]: RETURN R0 0  


; Name:            
; Defined at line: 1327
; #Upvalues:       11
; #Parameters:     0
; Is_vararg:       0
; Max Stack Size:  10

       0 [-]: GETIMPORT R0 1 [nil]
       1 [-]: LOADK R1 K2 ["EE.Interface.Components.List"]
       2 [-]: CALL R0 1 1  
       3 [-]: GETTABLEKS R1 R0 K3 [0x9383BC56]
       4 [-]: GETIMPORT R2 5 [nil]
       5 [-]: LOADK R3 K6 ["FrameSelect.FrameList.Element"]
       6 [-]: LOADN R4 5   
       7 [-]: CALL R1 3 1  
       8 [-]: SETUPVAL R1 0
       9 [-]: GETUPVAL R1 0
      10 [-]: LOADK R3 K7 ["PathItemPressed"]
      11 [-]: LOADK R4 K8 ["PathItemFocused"]
      12 [-]: LOADK R5 K9 ["PathItemUnfocused"]
      13 [-]: NAMECALL R1 R1 K10 [0x1E5B5CFE]
      14 [-]: CALL R1 4 0  
      15 [-]: GETUPVAL R1 0
      16 [-]: LOADN R2 0   
      17 [-]: SETTABLEKS R2 R1 K11 ["mForcedVerticalSeparation"]
      18 [-]: GETUPVAL R1 0
      19 [-]: LOADN R2 470 
      20 [-]: SETTABLEKS R2 R1 K12 ["mForcedHorizontalSeparation"]
      21 [-]: GETUPVAL R1 0
      22 [-]: NEWTABLE R2 0 0
      23 [-]: SETTABLEKS R2 R1 K13 ["mSelectedElementIds"]
      24 [-]: GETUPVAL R1 0
      25 [-]: NEWCLOSURE R2 P0
      26 [-]: MOVE R2 R1   
      27 [-]: SETTABLEKS R2 R1 K14 ["mClipCreatedCallback"]
      28 [-]: GETUPVAL R1 0
      29 [-]: DUPCLOSURE R2 K15 []
      30 [-]: SETTABLEKS R2 R1 K16 ["IsSelected"]
      31 [-]: GETUPVAL R1 0
      32 [-]: NEWCLOSURE R2 P2
      33 [-]: MOVE R2 R0   
      34 [-]: MOVE R2 R2   
      35 [-]: MOVE R2 R3   
      36 [-]: MOVE R2 R1   
      37 [-]: MOVE R2 R4   
      38 [-]: MOVE R2 R5   
      39 [-]: MOVE R2 R6   
      40 [-]: SETTABLEKS R2 R1 K17 ["UpdateFocus"]
      41 [-]: GETUPVAL R1 0
      42 [-]: DUPCLOSURE R2 K18 []
      43 [-]: MOVE R2 R2   
      44 [-]: SETTABLEKS R2 R1 K19 ["UpdateTiers"]
      45 [-]: GETUPVAL R1 0
      46 [-]: GETUPVAL R3 0
      47 [-]: GETTABLEKS R2 R3 K20 ["Redraw"]
      48 [-]: SETTABLEKS R2 R1 K21 ["_FrameList_Redraw"]
      49 [-]: GETUPVAL R1 0
      50 [-]: NEWCLOSURE R2 P4
      51 [-]: MOVE R2 R2   
      52 [-]: MOVE R2 R3   
      53 [-]: SETTABLEKS R2 R1 K20 ["Redraw"]
      54 [-]: GETUPVAL R1 0
      55 [-]: NEWCLOSURE R2 P5
      56 [-]: MOVE R2 R2   
      57 [-]: MOVE R2 R0   
      58 [-]: SETTABLEKS R2 R1 K22 ["mOnFocusedCallback"]
      59 [-]: GETUPVAL R1 0
      60 [-]: NEWCLOSURE R2 P6
      61 [-]: MOVE R2 R0   
      62 [-]: SETTABLEKS R2 R1 K23 ["mOnUnfocusedCallback"]
      63 [-]: GETUPVAL R1 0
      64 [-]: NEWCLOSURE R2 P7
      65 [-]: MOVE R2 R2   
      66 [-]: MOVE R2 R3   
      67 [-]: MOVE R2 R0   
      68 [-]: MOVE R2 R7   
      69 [-]: SETTABLEKS R2 R1 K24 ["mOnSelectedCallback"]
      70 [-]: GETUPVAL R1 0
      71 [-]: NEWCLOSURE R2 P8
      72 [-]: MOVE R2 R3   
      73 [-]: MOVE R2 R1   
      74 [-]: MOVE R2 R2   
      75 [-]: MOVE R2 R0   
      76 [-]: MOVE R0 R0   
      77 [-]: MOVE R2 R5   
      78 [-]: MOVE R2 R8   
      79 [-]: MOVE R2 R9   
      80 [-]: SETTABLEKS R2 R1 K25 ["mElementDrawCallback"]
      81 [-]: GETIMPORT R1 1 [nil]
      82 [-]: LOADK R2 K26 ["Lotus.Interface.Components.ThemedSpinner"]
      83 [-]: CALL R1 1 1  
      84 [-]: GETTABLEKS R2 R1 K27 [0xAE6791BA]
      85 [-]: GETIMPORT R3 5 [nil]
      86 [-]: LOADK R4 K28 ["FrameSelect.Spinner"]
      87 [-]: CALL R2 2 1  
      88 [-]: SETUPVAL R2 10
      89 [-]: GETUPVAL R2 10
      90 [-]: LOADB R4 0   
      91 [-]: NAMECALL R2 R2 K29 [0x46610C50]
      92 [-]: CALL R2 2 0  
      93 [-]: GETIMPORT R2 5 [nil]
      94 [-]: LOADK R4 K30 ["FrameSelect.Hint"]
      95 [-]: LOADN R5 36  
      96 [-]: GETUPVAL R7 1
      97 [-]: GETTABLEKS R6 R7 K31 ["FloatingContent"]
      98 [-]: NAMECALL R2 R2 K32 [0x67BC869F]
      99 [-]: CALL R2 4 0  
     100 [-]: GETIMPORT R2 5 [nil]
     101 [-]: LOADK R4 K33 ["FrameSelect.Title.Label"]
     102 [-]: LOADN R5 36  
     103 [-]: GETUPVAL R7 1
     104 [-]: GETTABLEKS R6 R7 K31 ["FloatingContent"]
     105 [-]: NAMECALL R2 R2 K32 [0x67BC869F]
     106 [-]: CALL R2 4 0  
     107 [-]: GETIMPORT R2 5 [nil]
     108 [-]: LOADK R4 K34 ["FrameSelect.Title.Label.text"]
     109 [-]: LOADK R5 K35 ["/Lotus/Language/Duviri/EndlessSetupPathSelectTitle"]
     110 [-]: NAMECALL R2 R2 K36 [0x20B98DB3]
     111 [-]: CALL R2 3 0  
     112 [-]: GETIMPORT R2 5 [nil]
     113 [-]: LOADK R4 K37 ["FrameSelect.Title.BookendLeft"]
     114 [-]: GETIMPORT R5 39 [nil]
     115 [-]: NAMECALL R2 R2 K40 [0x1CB415C1]
     116 [-]: CALL R2 3 0  
     117 [-]: GETIMPORT R2 5 [nil]
     118 [-]: LOADK R4 K37 ["FrameSelect.Title.BookendLeft"]
     119 [-]: LOADN R5 9   
     120 [-]: GETUPVAL R7 1
     121 [-]: GETTABLEKS R6 R7 K31 ["FloatingContent"]
     122 [-]: NAMECALL R2 R2 K32 [0x67BC869F]
     123 [-]: CALL R2 4 0  
     124 [-]: GETIMPORT R2 5 [nil]
     125 [-]: LOADK R4 K41 ["FrameSelect.Title.BookendRight"]
     126 [-]: GETIMPORT R5 39 [nil]
     127 [-]: NAMECALL R2 R2 K40 [0x1CB415C1]
     128 [-]: CALL R2 3 0  
     129 [-]: GETIMPORT R2 5 [nil]
     130 [-]: LOADK R4 K41 ["FrameSelect.Title.BookendRight"]
     131 [-]: LOADN R5 9   
     132 [-]: GETUPVAL R7 1
     133 [-]: GETTABLEKS R6 R7 K31 ["FloatingContent"]
     134 [-]: NAMECALL R2 R2 K32 [0x67BC869F]
     135 [-]: CALL R2 4 0  
     136 [-]: GETIMPORT R2 5 [nil]
     137 [-]: LOADK R4 K33 ["FrameSelect.Title.Label"]
     138 [-]: LOADN R5 33  
     139 [-]: NAMECALL R2 R2 K42 [0x91A24E4B]
     140 [-]: CALL R2 3 1  
     141 [-]: GETIMPORT R3 5 [nil]
     142 [-]: LOADK R5 K37 ["FrameSelect.Title.BookendLeft"]
     143 [-]: LOADN R6 0   
     144 [-]: DIVK R9 R2 K44 [2]
     145 [-]: MINUS R8 R9  
     146 [-]: SUBK R7 R8 K43 [17]
     147 [-]: NAMECALL R3 R3 K32 [0x67BC869F]
     148 [-]: CALL R3 4 0  
     149 [-]: GETIMPORT R3 5 [nil]
     150 [-]: LOADK R5 K41 ["FrameSelect.Title.BookendRight"]
     151 [-]: LOADN R6 0   
     152 [-]: DIVK R8 R2 K44 [2]
     153 [-]: ADDK R7 R8 K45 [15]
     154 [-]: NAMECALL R3 R3 K32 [0x67BC869F]
     155 [-]: CALL R3 4 0  
     156 [-]: GETIMPORT R3 1 [nil]
     157 [-]: LOADK R4 K46 ["Lotus.Interface.Components.ThemedButton"]
     158 [-]: CALL R3 1 1  
     159 [-]: GETTABLEKS R4 R3 K27 [0xAE6791BA]
     160 [-]: GETIMPORT R5 5 [nil]
     161 [-]: LOADK R6 K47 ["FrameSelect.ClaimBtn"]
     162 [-]: LOADK R7 K48 [""]
     163 [-]: LOADK R8 K49 ["ChooseItems"]
     164 [-]: CALL R4 4 1  
     165 [-]: SETUPVAL R4 7
     166 [-]: GETUPVAL R4 7
     167 [-]: NEWCLOSURE R5 P9
     168 [-]: MOVE R2 R3   
     169 [-]: MOVE R2 R0   
     170 [-]: MOVE R2 R2   
     171 [-]: SETTABLEKS R5 R4 K50 ["UpdateState"]
     172 [-]: GETUPVAL R4 7
     173 [-]: NAMECALL R4 R4 K51 [0x4E86C602]
     174 [-]: CALL R4 1 0  
     175 [-]: GETUPVAL R4 7
     176 [-]: LOADN R6 250 
     177 [-]: NAMECALL R4 R4 K52 [0x8D77B2B2]
     178 [-]: CALL R4 2 0  
     179 [-]: GETUPVAL R4 7
     180 [-]: NAMECALL R4 R4 K53 [0x71E9AC81]
     181 [-]: CALL R4 1 0  
     182 [-]: GETUPVAL R4 7
     183 [-]: GETUPVAL R7 2
     184 [-]: GETTABLEKS R6 R7 K54 ["CENTER_ALIGNED"]
     185 [-]: NAMECALL R4 R4 K55 [0x240F1807]
     186 [-]: CALL R4 2 0  
     187 [-]: GETUPVAL R4 7
     188 [-]: LOADB R6 0   
     189 [-]: NAMECALL R4 R4 K56 [0x368AD758]
     190 [-]: CALL R4 2 0  
     191 [-]: RETURN R0 0  


; Name:            
; Defined at line: 1834
; #Upvalues:       5
; #Parameters:     0
; Is_vararg:       0
; Max Stack Size:  16

       0 [-]: GETIMPORT R1 2 [nil]
       1 [-]: FASTCALL1 62 R1 L0
       2 [-]: GETIMPORT R0 4 [nil]
       3 [-]: CALL R0 1 1  
L 0:   4 [-]: JUMPIF R0 L1 
       5 [-]: GETIMPORT R0 2 [nil]
       6 [-]: LOADK R1 K5 [0.25]
       7 [-]: LOADNIL R2   
       8 [-]: LOADNIL R3   
       9 [-]: LOADNIL R4   
      10 [-]: CALL R0 4 0  
L 1:  11 [-]: GETUPVAL R1 0
      12 [-]: GETTABLEKS R0 R1 K6 ["Loaded"]
      13 [-]: JUMPIFNOT R0 L2
      14 [-]: GETIMPORT R0 8 [nil]
      15 [-]: NAMECALL R0 R0 K9 [0xB21930E8]
      16 [-]: CALL R0 1 0  
      17 [-]: GETUPVAL R0 0
      18 [-]: LOADB R1 0   
      19 [-]: SETTABLEKS R1 R0 K6 ["Loaded"]
L 2:  20 [-]: GETUPVAL R2 0
      21 [-]: GETTABLEKS R1 R2 K10 ["Weapon"]
      22 [-]: FASTCALL1 62 R1 L3
      23 [-]: GETIMPORT R0 4 [nil]
      24 [-]: CALL R0 1 1  
L 3:  25 [-]: JUMPIF R0 L4 
      26 [-]: GETIMPORT R0 12 [nil]
      27 [-]: GETUPVAL R3 0
      28 [-]: GETTABLEKS R2 R3 K10 ["Weapon"]
      29 [-]: NAMECALL R0 R0 K13 [0x59C96E77]
      30 [-]: CALL R0 2 0  
      31 [-]: GETUPVAL R0 0
      32 [-]: LOADNIL R1   
      33 [-]: SETTABLEKS R1 R0 K10 ["Weapon"]
L 4:  34 [-]: GETUPVAL R0 0
      35 [-]: NEWTABLE R1 0 0
      36 [-]: SETTABLEKS R1 R0 K14 ["WeaponTypes"]
      37 [-]: GETUPVAL R0 0
      38 [-]: LOADNIL R1   
      39 [-]: SETTABLEKS R1 R0 K15 ["DioWRes"]
      40 [-]: GETUPVAL R0 0
      41 [-]: LOADNIL R1   
      42 [-]: SETTABLEKS R1 R0 K16 ["Configs"]
      43 [-]: NEWTABLE R0 0 0
      44 [-]: GETUPVAL R2 1
      45 [-]: GETUPVAL R3 2
      46 [-]: GETTABLE R1 R2 R3
      47 [-]: NEWTABLE R2 0 0
      48 [-]: GETTABLEKS R4 R1 K17 ["mChoices"]
      49 [-]: LENGTH R3 R4 
      50 [-]: LOADN R4 0   
      51 [-]: JUMPIFNOTLT R4 R3 L12
      52 [-]: LOADN R5 1   
      53 [-]: GETTABLEKS R6 R1 K17 ["mChoices"]
      54 [-]: LENGTH R3 R6 
      55 [-]: LOADN R4 1   
      56 [-]: FORNPREP R3 L12
L 5:  57 [-]: LOADN R8 1   
      58 [-]: GETUPVAL R10 3
      59 [-]: GETTABLEKS R9 R10 K17 ["mChoices"]
      60 [-]: LENGTH R6 R9 
      61 [-]: LOADN R7 1   
      62 [-]: FORNPREP R6 L11
L 6:  63 [-]: GETTABLEKS R10 R1 K17 ["mChoices"]
      64 [-]: GETTABLE R9 R10 R5
      65 [-]: GETUPVAL R13 3
      66 [-]: GETTABLEKS R12 R13 K17 ["mChoices"]
      67 [-]: GETTABLE R11 R12 R8
      68 [-]: GETTABLEKS R10 R11 K18 ["mTag"]
      69 [-]: JUMPIFNOTEQ R9 R10 L10
      70 [-]: GETUPVAL R9 4
      71 [-]: JUMPXEQKN R9 K19 L7 NOT [0]
      72 [-]: GETUPVAL R9 0
      73 [-]: GETIMPORT R10 21 [nil]
      74 [-]: GETUPVAL R14 3
      75 [-]: GETTABLEKS R13 R14 K17 ["mChoices"]
      76 [-]: GETTABLE R12 R13 R8
      77 [-]: GETTABLEKS R11 R12 K22 ["mChoiceParent"]
      78 [-]: CALL R10 1 1 
      79 [-]: NAMECALL R10 R10 K23 [0x9B4BBE31]
      80 [-]: CALL R10 1 1 
      81 [-]: SETTABLEKS R10 R9 K15 ["DioWRes"]
      82 [-]: JUMP L11
    
L 7:  83 [-]: GETIMPORT R9 21 [nil]
      84 [-]: GETUPVAL R13 3
      85 [-]: GETTABLEKS R12 R13 K17 ["mChoices"]
      86 [-]: GETTABLE R11 R12 R8
      87 [-]: GETTABLEKS R10 R11 K22 ["mChoiceParent"]
      88 [-]: CALL R9 1 1  
      89 [-]: NAMECALL R9 R9 K24 [0xF278F8A1]
      90 [-]: CALL R9 1 1  
      91 [-]: GETUPVAL R12 0
      92 [-]: GETTABLEKS R11 R12 K14 ["WeaponTypes"]
      93 [-]: FASTCALL2 52 R11 R9 L8
      94 [-]: MOVE R12 R9  
      95 [-]: GETIMPORT R10 27 [nil]
      96 [-]: CALL R10 2 0 
L 8:  97 [-]: GETUPVAL R15 3
      98 [-]: GETTABLEKS R14 R15 K17 ["mChoices"]
      99 [-]: GETTABLE R13 R14 R8
     100 [-]: GETTABLEKS R12 R13 K22 ["mChoiceParent"]
     101 [-]: FASTCALL2 52 R2 R12 L9
     102 [-]: MOVE R11 R2  
     103 [-]: GETIMPORT R10 27 [nil]
     104 [-]: CALL R10 2 0 
L 9: 105 [-]: MOVE R11 R0  
     106 [-]: NAMECALL R12 R9 K28 [0xED4E0128]
     107 [-]: CALL R12 1 -1
     108 [-]: FASTCALL 52 L10
     109 [-]: GETIMPORT R10 27 [nil]
     110 [-]: CALL R10 -1 0
L10: 111 [-]: FORNLOOP R6 L6
L11: 112 [-]: FORNLOOP R3 L5
L12: 113 [-]: GETUPVAL R3 4
     114 [-]: JUMPXEQKN R3 K29 L13 NOT [1]
     115 [-]: GETUPVAL R3 0
     116 [-]: GETIMPORT R4 31 [nil]
     117 [-]: SETTABLEKS R4 R3 K15 ["DioWRes"]
     118 [-]: GETUPVAL R5 0
     119 [-]: GETTABLEKS R4 R5 K14 ["WeaponTypes"]
     120 [-]: GETUPVAL R6 0
     121 [-]: GETTABLEKS R5 R6 K32 ["WeaponIndex"]
     122 [-]: GETTABLE R3 R4 R5
     123 [-]: GETIMPORT R4 34 [nil]
     124 [-]: GETIMPORT R5 36 [nil]
     125 [-]: MOVE R6 R3   
     126 [-]: CALL R4 2 1  
     127 [-]: JUMPXEQKNIL R4 L13
     128 [-]: GETUPVAL R4 0
     129 [-]: GETIMPORT R5 38 [nil]
     130 [-]: SETTABLEKS R5 R4 K15 ["DioWRes"]
     131 [-]: GETIMPORT R4 40 [nil]
     132 [-]: LOADK R6 K41 ["RewardPanel.NoDioIcon"]
     133 [-]: GETIMPORT R7 21 [nil]
     134 [-]: GETUPVAL R10 0
     135 [-]: GETTABLEKS R9 R10 K32 ["WeaponIndex"]
     136 [-]: GETTABLE R8 R2 R9
     137 [-]: CALL R7 1 1  
     138 [-]: NAMECALL R7 R7 K42 [0x87713606]
     139 [-]: CALL R7 1 -1 
     140 [-]: NAMECALL R4 R4 K43 [0x1CB415C1]
     141 [-]: CALL R4 -1 0 
L13: 142 [-]: GETUPVAL R4 0
     143 [-]: GETTABLEKS R3 R4 K15 ["DioWRes"]
     144 [-]: JUMPXEQKNIL R3 L14 NOT
     145 [-]: GETUPVAL R3 0
     146 [-]: GETIMPORT R4 38 [nil]
     147 [-]: SETTABLEKS R4 R3 K15 ["DioWRes"]
L14: 148 [-]: MOVE R4 R0   
     149 [-]: GETUPVAL R6 0
     150 [-]: GETTABLEKS R5 R6 K15 ["DioWRes"]
     151 [-]: NAMECALL R5 R5 K28 [0xED4E0128]
     152 [-]: CALL R5 1 -1 
     153 [-]: FASTCALL 52 L15
     154 [-]: GETIMPORT R3 27 [nil]
     155 [-]: CALL R3 -1 0 
L15: 156 [-]: GETUPVAL R5 0
     157 [-]: GETTABLEKS R4 R5 K44 ["Loader"]
     158 [-]: FASTCALL1 62 R4 L16
     159 [-]: GETIMPORT R3 4 [nil]
     160 [-]: CALL R3 1 1  
L16: 161 [-]: JUMPIF R3 L17
     162 [-]: GETUPVAL R4 0
     163 [-]: GETTABLEKS R3 R4 K45 ["IsLoading"]
     164 [-]: JUMPIFNOT R3 L17
     165 [-]: GETUPVAL R4 0
     166 [-]: GETTABLEKS R3 R4 K44 ["Loader"]
     167 [-]: NAMECALL R3 R3 K46 [0x8B1FAB28]
     168 [-]: CALL R3 1 0  
L17: 169 [-]: GETUPVAL R3 0
     170 [-]: GETIMPORT R4 49 [nil]
     171 [-]: MOVE R5 R0   
     172 [-]: CALL R4 1 1  
     173 [-]: SETTABLEKS R4 R3 K44 ["Loader"]
     174 [-]: GETUPVAL R3 0
     175 [-]: LOADB R4 1   
     176 [-]: SETTABLEKS R4 R3 K45 ["IsLoading"]
     177 [-]: RETURN R0 0  


; Name:            
; Defined at line: 1895
; #Upvalues:       4
; #Parameters:     0
; Is_vararg:       0
; Max Stack Size:  11

       0 [-]: NEWTABLE R0 0 4
       1 [-]: LOADK R1 K0 ["TopLeft"]
       2 [-]: LOADK R2 K1 ["TopRight"]
       3 [-]: LOADK R3 K2 ["BottomLeft"]
       4 [-]: LOADK R4 K3 ["BottomRight"]
       5 [-]: SETLIST R0 R1 4 [1]
       6 [-]: LOADN R3 1   
       7 [-]: LENGTH R1 R0 
       8 [-]: LOADN R2 1   
       9 [-]: FORNPREP R1 L1
L 0:  10 [-]: GETIMPORT R4 5 [nil]
      11 [-]: LOADK R7 K6 ["Earned.Bg."]
      12 [-]: GETTABLE R8 R0 R3
      13 [-]: CONCAT R6 R7 R8
      14 [-]: GETIMPORT R8 8 [nil]
      15 [-]: GETTABLEN R7 R8 2
      16 [-]: NAMECALL R4 R4 K9 [0x1CB415C1]
      17 [-]: CALL R4 3 0  
      18 [-]: GETIMPORT R4 5 [nil]
      19 [-]: LOADK R6 K10 ["Earned.Bg"]
      20 [-]: GETTABLE R7 R0 R3
      21 [-]: LOADN R8 9   
      22 [-]: GETUPVAL R10 0
      23 [-]: GETTABLEKS R9 R10 K11 ["FloatingContent"]
      24 [-]: NAMECALL R4 R4 K12 [0xF64B7262]
      25 [-]: CALL R4 5 0  
      26 [-]: FORNLOOP R1 L0
L 1:  27 [-]: GETIMPORT R1 5 [nil]
      28 [-]: LOADK R3 K13 ["Earned.TitleSchmoo"]
      29 [-]: GETIMPORT R5 8 [nil]
      30 [-]: GETTABLEN R4 R5 1
      31 [-]: NAMECALL R1 R1 K9 [0x1CB415C1]
      32 [-]: CALL R1 3 0  
      33 [-]: GETIMPORT R1 5 [nil]
      34 [-]: LOADK R3 K13 ["Earned.TitleSchmoo"]
      35 [-]: LOADN R4 9   
      36 [-]: GETUPVAL R6 0
      37 [-]: GETTABLEKS R5 R6 K11 ["FloatingContent"]
      38 [-]: NAMECALL R1 R1 K14 [0x67BC869F]
      39 [-]: CALL R1 4 0  
      40 [-]: GETIMPORT R1 5 [nil]
      41 [-]: LOADK R3 K15 ["Earned.Title"]
      42 [-]: LOADN R4 36  
      43 [-]: GETUPVAL R6 0
      44 [-]: GETTABLEKS R5 R6 K16 ["FloatingContentHighlight"]
      45 [-]: NAMECALL R1 R1 K14 [0x67BC869F]
      46 [-]: CALL R1 4 0  
      47 [-]: GETIMPORT R1 5 [nil]
      48 [-]: LOADK R3 K17 ["Earned.TitleBg"]
      49 [-]: GETIMPORT R5 8 [nil]
      50 [-]: GETTABLEN R4 R5 3
      51 [-]: NAMECALL R1 R1 K9 [0x1CB415C1]
      52 [-]: CALL R1 3 0  
      53 [-]: GETIMPORT R1 5 [nil]
      54 [-]: LOADK R3 K17 ["Earned.TitleBg"]
      55 [-]: LOADN R4 9   
      56 [-]: GETUPVAL R6 0
      57 [-]: GETTABLEKS R5 R6 K18 ["Background1"]
      58 [-]: NAMECALL R1 R1 K14 [0x67BC869F]
      59 [-]: CALL R1 4 0  
      60 [-]: GETIMPORT R1 5 [nil]
      61 [-]: LOADK R3 K19 ["Earned.Name"]
      62 [-]: LOADN R4 36  
      63 [-]: GETUPVAL R6 0
      64 [-]: GETTABLEKS R5 R6 K16 ["FloatingContentHighlight"]
      65 [-]: NAMECALL R1 R1 K14 [0x67BC869F]
      66 [-]: CALL R1 4 0  
      67 [-]: GETIMPORT R1 5 [nil]
      68 [-]: LOADK R3 K20 ["Earned.NameBg"]
      69 [-]: GETIMPORT R5 8 [nil]
      70 [-]: GETTABLEN R4 R5 3
      71 [-]: NAMECALL R1 R1 K9 [0x1CB415C1]
      72 [-]: CALL R1 3 0  
      73 [-]: GETIMPORT R1 5 [nil]
      74 [-]: LOADK R3 K20 ["Earned.NameBg"]
      75 [-]: LOADN R4 9   
      76 [-]: GETUPVAL R6 0
      77 [-]: GETTABLEKS R5 R6 K18 ["Background1"]
      78 [-]: NAMECALL R1 R1 K14 [0x67BC869F]
      79 [-]: CALL R1 4 0  
      80 [-]: GETIMPORT R1 5 [nil]
      81 [-]: LOADK R3 K21 ["Earned.UnderGlow.StarburstOne"]
      82 [-]: LOADN R4 9   
      83 [-]: GETUPVAL R6 0
      84 [-]: GETTABLEKS R5 R6 K22 ["BackerHighlight"]
      85 [-]: NAMECALL R1 R1 K14 [0x67BC869F]
      86 [-]: CALL R1 4 0  
      87 [-]: GETIMPORT R1 5 [nil]
      88 [-]: LOADK R3 K23 ["Earned.UnderGlow.StarburstTwo"]
      89 [-]: LOADN R4 9   
      90 [-]: GETUPVAL R6 0
      91 [-]: GETTABLEKS R5 R6 K24 ["Content"]
      92 [-]: NAMECALL R1 R1 K14 [0x67BC869F]
      93 [-]: CALL R1 4 0  
      94 [-]: GETIMPORT R1 5 [nil]
      95 [-]: LOADK R3 K25 ["Earned.UnderGlow.Sparkles"]
      96 [-]: LOADN R4 9   
      97 [-]: GETUPVAL R6 0
      98 [-]: GETTABLEKS R5 R6 K16 ["FloatingContentHighlight"]
      99 [-]: NAMECALL R1 R1 K14 [0x67BC869F]
     100 [-]: CALL R1 4 0  
     101 [-]: GETUPVAL R1 1
     102 [-]: DUPTABLE R2 29
     103 [-]: LOADK R3 K30 ["Earned.Reward"]
     104 [-]: SETTABLEKS R3 R2 K26 ["mClipName"]
     105 [-]: NEWTABLE R3 0 0
     106 [-]: SETTABLEKS R3 R2 K27 ["RewardInfos"]
     107 [-]: LOADN R3 1   
     108 [-]: SETTABLEKS R3 R2 K28 ["mIconIndex"]
     109 [-]: SETTABLEKS R2 R1 K31 ["ShowingElement"]
     110 [-]: GETUPVAL R3 2
     111 [-]: GETTABLEKS R2 R3 K32 ["Grid"]
     112 [-]: GETTABLEKS R1 R2 K33 ["mClipCreatedCallback"]
     113 [-]: GETUPVAL R4 1
     114 [-]: GETTABLEKS R3 R4 K31 ["ShowingElement"]
     115 [-]: GETTABLEKS R2 R3 K26 ["mClipName"]
     116 [-]: CALL R1 1 0  
     117 [-]: GETIMPORT R1 5 [nil]
     118 [-]: GETUPVAL R5 1
     119 [-]: GETTABLEKS R4 R5 K31 ["ShowingElement"]
     120 [-]: GETTABLEKS R3 R4 K26 ["mClipName"]
     121 [-]: LOADN R4 5   
     122 [-]: LOADN R5 210 
     123 [-]: NAMECALL R1 R1 K14 [0x67BC869F]
     124 [-]: CALL R1 4 0  
     125 [-]: GETIMPORT R1 5 [nil]
     126 [-]: GETUPVAL R5 1
     127 [-]: GETTABLEKS R4 R5 K31 ["ShowingElement"]
     128 [-]: GETTABLEKS R3 R4 K26 ["mClipName"]
     129 [-]: LOADN R4 6   
     130 [-]: LOADN R5 210 
     131 [-]: NAMECALL R1 R1 K14 [0x67BC869F]
     132 [-]: CALL R1 4 0  
     133 [-]: GETIMPORT R1 35 [nil]
     134 [-]: LOADK R2 K36 ["Lotus.Interface.Components.ThemedButton"]
     135 [-]: CALL R1 1 1  
     136 [-]: GETTABLEKS R2 R1 K37 [0xAE6791BA]
     137 [-]: GETIMPORT R3 5 [nil]
     138 [-]: LOADK R4 K38 ["Earned.SkipBtn"]
     139 [-]: LOADK R5 K39 ["/Lotus/Language/Menu/SkipTutorialShort"]
     140 [-]: LOADK R6 K40 ["OnClaimedRewardsViewed"]
     141 [-]: CALL R2 4 1  
     142 [-]: SETUPVAL R2 3
     143 [-]: GETUPVAL R2 3
     144 [-]: LOADN R4 150 
     145 [-]: NAMECALL R2 R2 K41 [0x8D77B2B2]
     146 [-]: CALL R2 2 0  
     147 [-]: RETURN R0 0  


; Name:            
; Defined at line: 1926
; #Upvalues:       18
; #Parameters:     0
; Is_vararg:       0
; Max Stack Size:  10

       0 [-]: GETIMPORT R1 2 [nil]
       1 [-]: FASTCALL1 62 R1 L0
       2 [-]: GETIMPORT R0 4 [nil]
       3 [-]: CALL R0 1 1  
L 0:   4 [-]: JUMPIF R0 L1 
       5 [-]: GETIMPORT R0 2 [nil]
       6 [-]: LOADK R1 K5 [0.25]
       7 [-]: LOADNIL R2   
       8 [-]: LOADNIL R3   
       9 [-]: LOADNIL R4   
      10 [-]: CALL R0 4 0  
L 1:  11 [-]: GETIMPORT R0 6 [nil]
      12 [-]: LOADB R1 0   
      13 [-]: SETTABLEKS R1 R0 K7 ["DuviriEndlessSetupComplete"]
      14 [-]: GETUPVAL R1 0
      15 [-]: GETTABLEKS R0 R1 K8 [0x15DEABB1]
      16 [-]: LOADB R1 1   
      17 [-]: CALL R0 1 0  
      18 [-]: GETUPVAL R1 0
      19 [-]: GETTABLEKS R0 R1 K9 [0x9E3D3434]
      20 [-]: LOADB R1 1   
      21 [-]: CALL R0 1 0  
      22 [-]: GETIMPORT R0 11 [nil]
      23 [-]: LOADB R2 1   
      24 [-]: NAMECALL R0 R0 K12 [0xC02F2CB8]
      25 [-]: CALL R0 2 0  
      26 [-]: GETIMPORT R0 14 [nil]
      27 [-]: GETIMPORT R3 16 [nil]
      28 [-]: JUMPXEQKB R3 1 L2
      29 [-]: LOADB R2 0 +1
L 2:  30 [-]: LOADB R2 1   
L 3:  31 [-]: NAMECALL R0 R0 K17 [0x2002E1DC]
      32 [-]: CALL R0 2 0  
      33 [-]: GETIMPORT R0 19 [nil]
      34 [-]: JUMPIF R0 L5 
      35 [-]: GETIMPORT R1 21 [nil]
      36 [-]: FASTCALL1 62 R1 L4
      37 [-]: GETIMPORT R0 4 [nil]
      38 [-]: CALL R0 1 1  
L 4:  39 [-]: JUMPIF R0 L5 
      40 [-]: GETIMPORT R0 21 [nil]
      41 [-]: CALL R0 0 0  
      42 [-]: LOADB R0 1   
      43 [-]: SETUPVAL R0 1
L 5:  44 [-]: GETIMPORT R1 23 [nil]
      45 [-]: FASTCALL1 62 R1 L6
      46 [-]: GETIMPORT R0 4 [nil]
      47 [-]: CALL R0 1 1  
L 6:  48 [-]: JUMPIF R0 L7 
      49 [-]: LOADB R0 1   
      50 [-]: SETUPVAL R0 1
      51 [-]: GETIMPORT R0 23 [nil]
      52 [-]: LOADK R2 K24 ["SkipDisableInputOnClose"]
      53 [-]: LOADK R3 K25 ["true"]
      54 [-]: NAMECALL R0 R0 K26 [0xE4162EED]
      55 [-]: CALL R0 3 0  
      56 [-]: GETIMPORT R0 23 [nil]
      57 [-]: LOADK R2 K27 ["Close"]
      58 [-]: LOADK R3 K28 [""]
      59 [-]: NAMECALL R0 R0 K26 [0xE4162EED]
      60 [-]: CALL R0 3 0  
L 7:  61 [-]: GETUPVAL R1 2
      62 [-]: GETTABLEKS R0 R1 K29 [0x659D451F]
      63 [-]: GETIMPORT R2 31 [nil]
      64 [-]: GETTABLEKS R1 R2 K32 ["UISound_Select"]
      65 [-]: CALL R0 1 0  
      66 [-]: GETUPVAL R1 2
      67 [-]: GETTABLEKS R0 R1 K29 [0x659D451F]
      68 [-]: GETIMPORT R2 31 [nil]
      69 [-]: GETTABLEKS R1 R2 K33 ["UISound_GridOpen"]
      70 [-]: CALL R0 1 0  
      71 [-]: GETUPVAL R0 3
      72 [-]: GETIMPORT R1 35 [nil]
      73 [-]: SETTABLEKS R1 R0 K36 ["sec"]
      74 [-]: GETIMPORT R0 38 [nil]
      75 [-]: NAMECALL R0 R0 K39 [0x25A6E75E]
      76 [-]: CALL R0 1 1  
      77 [-]: SETUPVAL R0 4
      78 [-]: GETIMPORT R0 11 [nil]
      79 [-]: NAMECALL R0 R0 K40 [0xA1C390FE]
      80 [-]: CALL R0 1 1  
      81 [-]: SETUPVAL R0 5
      82 [-]: GETUPVAL R1 7
      83 [-]: GETTABLEKS R0 R1 K41 [0x71A5B951]
      84 [-]: GETUPVAL R1 5
      85 [-]: GETUPVAL R2 4
      86 [-]: CALL R0 2 1  
      87 [-]: SETUPVAL R0 6
      88 [-]: GETIMPORT R1 43 [nil]
      89 [-]: GETTABLEN R0 R1 2
      90 [-]: GETIMPORT R2 46 [nil]
      91 [-]: LOADN R3 0   
      92 [-]: NAMECALL R0 R0 K47 [0x830EEA67]
      93 [-]: CALL R0 3 0  
      94 [-]: GETIMPORT R1 43 [nil]
      95 [-]: GETTABLEN R0 R1 2
      96 [-]: GETIMPORT R2 49 [nil]
      97 [-]: LOADN R3 2   
      98 [-]: NAMECALL R0 R0 K47 [0x830EEA67]
      99 [-]: CALL R0 3 0  
     100 [-]: DUPTABLE R0 56
     101 [-]: GETUPVAL R2 9
     102 [-]: GETTABLEKS R1 R2 K57 [0x5D10207D]
     103 [-]: LOADN R2 1   
     104 [-]: LOADB R3 1   
     105 [-]: CALL R1 2 1  
     106 [-]: SETTABLEKS R1 R0 K50 ["BackerHighlight"]
     107 [-]: GETUPVAL R2 9
     108 [-]: GETTABLEKS R1 R2 K57 [0x5D10207D]
     109 [-]: LOADN R2 0   
     110 [-]: LOADB R3 1   
     111 [-]: CALL R1 2 1  
     112 [-]: SETTABLEKS R1 R0 K51 ["Backer"]
     113 [-]: GETUPVAL R2 9
     114 [-]: GETTABLEKS R1 R2 K57 [0x5D10207D]
     115 [-]: LOADN R2 9   
     116 [-]: LOADB R3 1   
     117 [-]: CALL R1 2 1  
     118 [-]: SETTABLEKS R1 R0 K52 ["FloatingContent"]
     119 [-]: GETUPVAL R2 9
     120 [-]: GETTABLEKS R1 R2 K57 [0x5D10207D]
     121 [-]: LOADN R2 10  
     122 [-]: LOADB R3 1   
     123 [-]: CALL R1 2 1  
     124 [-]: SETTABLEKS R1 R0 K53 ["FloatingContentHighlight"]
     125 [-]: GETUPVAL R2 9
     126 [-]: GETTABLEKS R1 R2 K57 [0x5D10207D]
     127 [-]: LOADN R2 2   
     128 [-]: LOADB R3 1   
     129 [-]: CALL R1 2 1  
     130 [-]: SETTABLEKS R1 R0 K54 ["Background1"]
     131 [-]: GETUPVAL R2 9
     132 [-]: GETTABLEKS R1 R2 K57 [0x5D10207D]
     133 [-]: LOADN R2 6   
     134 [-]: LOADB R3 1   
     135 [-]: CALL R1 2 1  
     136 [-]: SETTABLEKS R1 R0 K55 ["Content"]
     137 [-]: SETUPVAL R0 8
     138 [-]: GETUPVAL R0 8
     139 [-]: GETUPVAL R2 2
     140 [-]: GETTABLEKS R1 R2 K58 [0x8BCD12B6]
     141 [-]: GETUPVAL R3 8
     142 [-]: GETTABLEKS R2 R3 K54 ["Background1"]
     143 [-]: CALL R1 1 1  
     144 [-]: SETTABLEKS R1 R0 K59 ["Background1Object"]
     145 [-]: GETUPVAL R0 8
     146 [-]: GETUPVAL R2 2
     147 [-]: GETTABLEKS R1 R2 K58 [0x8BCD12B6]
     148 [-]: GETUPVAL R3 8
     149 [-]: GETTABLEKS R2 R3 K52 ["FloatingContent"]
     150 [-]: CALL R1 1 1  
     151 [-]: SETTABLEKS R1 R0 K60 ["FloatingContentObject"]
     152 [-]: GETUPVAL R0 8
     153 [-]: GETUPVAL R2 2
     154 [-]: GETTABLEKS R1 R2 K61 [0x9F57DD7D]
     155 [-]: GETUPVAL R3 8
     156 [-]: GETTABLEKS R2 R3 K52 ["FloatingContent"]
     157 [-]: CALL R1 1 1  
     158 [-]: SETTABLEKS R1 R0 K62 ["FloatingContentHex"]
     159 [-]: GETUPVAL R0 8
     160 [-]: GETUPVAL R2 2
     161 [-]: GETTABLEKS R1 R2 K61 [0x9F57DD7D]
     162 [-]: GETUPVAL R3 8
     163 [-]: GETTABLEKS R2 R3 K53 ["FloatingContentHighlight"]
     164 [-]: CALL R1 1 1  
     165 [-]: SETTABLEKS R1 R0 K63 ["FloatingContentHighlightHex"]
     166 [-]: GETIMPORT R0 65 [nil]
     167 [-]: LOADK R1 K66 ["Lotus.Interface.Libs.TimerMgr"]
     168 [-]: CALL R0 1 1  
     169 [-]: GETTABLEKS R1 R0 K67 [0xDE474187]
     170 [-]: CALL R1 0 1  
     171 [-]: SETUPVAL R1 10
     172 [-]: GETIMPORT R1 65 [nil]
     173 [-]: LOADK R2 K68 ["EE.Interface.AnchorMgr"]
     174 [-]: CALL R1 1 1  
     175 [-]: GETTABLEKS R2 R1 K69 [0xAE6791BA]
     176 [-]: GETIMPORT R3 14 [nil]
     177 [-]: CALL R2 1 1  
     178 [-]: SETUPVAL R2 11
     179 [-]: GETUPVAL R2 11
     180 [-]: GETIMPORT R4 14 [nil]
     181 [-]: LOADK R5 K70 ["RewardPanel.RewardPath"]
     182 [-]: NEWTABLE R6 0 2
     183 [-]: GETUPVAL R8 11
     184 [-]: GETTABLEKS R7 R8 K71 ["ANCHOR_V_TOP"]
     185 [-]: GETUPVAL R9 11
     186 [-]: GETTABLEKS R8 R9 K72 ["ANCHOR_H_LEFT"]
     187 [-]: SETLIST R6 R7 2 [1]
     188 [-]: NAMECALL R2 R2 K73 [0x20FF29F7]
     189 [-]: CALL R2 4 0  
     190 [-]: GETUPVAL R2 11
     191 [-]: GETIMPORT R4 14 [nil]
     192 [-]: LOADK R5 K74 ["RewardPanel.XpBar"]
     193 [-]: NEWTABLE R6 0 1
     194 [-]: GETUPVAL R8 11
     195 [-]: GETTABLEKS R7 R8 K75 ["ANCHOR_V_BOTTOM"]
     196 [-]: SETLIST R6 R7 1 [1]
     197 [-]: NAMECALL R2 R2 K73 [0x20FF29F7]
     198 [-]: CALL R2 4 0  
     199 [-]: GETUPVAL R2 11
     200 [-]: GETIMPORT R4 14 [nil]
     201 [-]: LOADK R5 K76 ["RewardPanel.BottomFade"]
     202 [-]: NEWTABLE R6 0 1
     203 [-]: GETUPVAL R8 11
     204 [-]: GETTABLEKS R7 R8 K75 ["ANCHOR_V_BOTTOM"]
     205 [-]: SETLIST R6 R7 1 [1]
     206 [-]: NAMECALL R2 R2 K73 [0x20FF29F7]
     207 [-]: CALL R2 4 0  
     208 [-]: GETUPVAL R2 11
     209 [-]: GETIMPORT R4 14 [nil]
     210 [-]: LOADK R5 K77 ["RewardPanel.Modes"]
     211 [-]: NEWTABLE R6 0 1
     212 [-]: GETUPVAL R8 11
     213 [-]: GETTABLEKS R7 R8 K75 ["ANCHOR_V_BOTTOM"]
     214 [-]: SETLIST R6 R7 1 [1]
     215 [-]: NAMECALL R2 R2 K73 [0x20FF29F7]
     216 [-]: CALL R2 4 0  
     217 [-]: GETUPVAL R2 11
     218 [-]: GETIMPORT R4 14 [nil]
     219 [-]: LOADK R5 K78 ["RewardPanel.ExtraReward"]
     220 [-]: NEWTABLE R6 0 1
     221 [-]: GETUPVAL R8 11
     222 [-]: GETTABLEKS R7 R8 K75 ["ANCHOR_V_BOTTOM"]
     223 [-]: SETLIST R6 R7 1 [1]
     224 [-]: NAMECALL R2 R2 K73 [0x20FF29F7]
     225 [-]: CALL R2 4 0  
     226 [-]: GETUPVAL R2 12
     227 [-]: GETIMPORT R3 14 [nil]
     228 [-]: NAMECALL R3 R3 K79 [0x6B837788]
     229 [-]: CALL R3 1 1  
     230 [-]: GETIMPORT R4 14 [nil]
     231 [-]: NAMECALL R4 R4 K80 [0xAF9FDA9F]
     232 [-]: CALL R4 1 -1 
     233 [-]: CALL R2 -1 0 
     234 [-]: GETIMPORT R2 14 [nil]
     235 [-]: GETUPVAL R5 8
     236 [-]: GETTABLEKS R4 R5 K54 ["Background1"]
     237 [-]: NAMECALL R2 R2 K81 [0xC6A10AB1]
     238 [-]: CALL R2 2 0  
     239 [-]: GETUPVAL R2 13
     240 [-]: CALL R2 0 0  
     241 [-]: GETUPVAL R2 14
     242 [-]: CALL R2 0 0  
     243 [-]: GETUPVAL R2 15
     244 [-]: CALL R2 0 0  
     245 [-]: GETUPVAL R2 16
     246 [-]: CALL R2 0 0  
     247 [-]: GETUPVAL R2 17
     248 [-]: CALL R2 0 0  
     249 [-]: RETURN R0 0  


; Name:            
; Defined at line: 2001
; #Upvalues:       1
; #Parameters:     2
; Is_vararg:       0
; Max Stack Size:  6

       0 [-]: GETTABLEKS R3 R0 K0 ["RewardInfos"]
       1 [-]: GETTABLEKS R4 R0 K1 ["mIconIndex"]
       2 [-]: GETTABLE R2 R3 R4
       3 [-]: FASTCALL1 62 R2 L0
       4 [-]: MOVE R4 R2   
       5 [-]: GETIMPORT R3 3 [nil]
       6 [-]: CALL R3 1 1  
L 0:   7 [-]: JUMPIF R3 L3 
       8 [-]: GETTABLEKS R4 R2 K4 ["Card"]
       9 [-]: FASTCALL1 62 R4 L1
      10 [-]: GETIMPORT R3 3 [nil]
      11 [-]: CALL R3 1 1  
L 1:  12 [-]: JUMPIF R3 L3 
      13 [-]: GETTABLEKS R4 R2 K5 ["CardSlot"]
      14 [-]: FASTCALL1 62 R4 L2
      15 [-]: GETIMPORT R3 3 [nil]
      16 [-]: CALL R3 1 1  
L 2:  17 [-]: JUMPIFNOT R3 L4
L 3:  18 [-]: RETURN R0 0  
L 4:  19 [-]: GETUPVAL R4 0
      20 [-]: GETTABLEKS R3 R4 K6 [0xFAA69527]
      21 [-]: GETTABLEKS R4 R2 K5 ["CardSlot"]
      22 [-]: MOVE R5 R1   
      23 [-]: CALL R3 2 0  
      24 [-]: RETURN R0 0  


; Name:            
; Defined at line: 2010
; #Upvalues:       6
; #Parameters:     0
; Is_vararg:       0
; Max Stack Size:  10

       0 [-]: DUPTABLE R0 4
       1 [-]: GETUPVAL R1 0
       2 [-]: SETTABLEKS R1 R0 K0 ["NodeType"]
       3 [-]: GETUPVAL R1 1
       4 [-]: SETTABLEKS R1 R0 K1 ["SplineConnectionType"]
       5 [-]: GETUPVAL R1 2
       6 [-]: SETTABLEKS R1 R0 K2 ["NodeEnabledMat"]
       7 [-]: GETUPVAL R1 3
       8 [-]: SETTABLEKS R1 R0 K3 ["NodeDisabledMat"]
       9 [-]: GETUPVAL R1 4
      10 [-]: GETUPVAL R3 5
      11 [-]: GETTABLEKS R2 R3 K5 [0xF45112B5]
      12 [-]: GETUPVAL R4 4
      13 [-]: GETTABLEKS R3 R4 K6 ["CameraSpot"]
      14 [-]: GETUPVAL R5 4
      15 [-]: GETTABLEKS R4 R5 K7 ["Weapon"]
      16 [-]: GETUPVAL R6 4
      17 [-]: GETTABLEKS R5 R6 K8 ["WeaponDecos"]
      18 [-]: GETUPVAL R7 4
      19 [-]: GETTABLEKS R6 R7 K9 ["HasOffHand"]
      20 [-]: MOVE R7 R0   
      21 [-]: LOADN R8 4   
      22 [-]: LOADN R9 4   
      23 [-]: CALL R2 7 1  
      24 [-]: SETTABLEKS R2 R1 K10 ["Configs"]
      25 [-]: GETUPVAL R2 4
      26 [-]: GETTABLEKS R1 R2 K10 ["Configs"]
      27 [-]: LOADN R2 60  
      28 [-]: SETTABLEKS R2 R1 K11 ["TransTimeOverride"]
      29 [-]: GETUPVAL R2 4
      30 [-]: GETTABLEKS R1 R2 K10 ["Configs"]
      31 [-]: LOADN R2 1   
      32 [-]: SETTABLEKS R2 R1 K12 ["CurrentNode"]
      33 [-]: GETUPVAL R2 4
      34 [-]: GETTABLEKS R1 R2 K10 ["Configs"]
      35 [-]: GETIMPORT R2 14 [nil]
      36 [-]: LOADK R3 K15 [-0.089999999999999997]
      37 [-]: LOADK R4 K16 [-0.037999999999999999]
      38 [-]: LOADK R5 K17 [-0.59999999999999998]
      39 [-]: CALL R2 3 1  
      40 [-]: SETTABLEKS R2 R1 K18 ["FinalCameraOffset"]
      41 [-]: GETIMPORT R1 20 [nil]
      42 [-]: GETIMPORT R2 22 [nil]
      43 [-]: CALL R1 1 3  
      44 [-]: FORGPREP_INEXT R1 L1
L 0:  45 [-]: GETUPVAL R7 4
      46 [-]: GETTABLEKS R6 R7 K7 ["Weapon"]
      47 [-]: MOVE R8 R5   
      48 [-]: NAMECALL R6 R6 K23 [0xF2DEAF69]
      49 [-]: CALL R6 2 1  
      50 [-]: JUMPIFNOT R6 L1
      51 [-]: GETUPVAL R7 4
      52 [-]: GETTABLEKS R6 R7 K10 ["Configs"]
      53 [-]: GETIMPORT R8 25 [nil]
      54 [-]: GETTABLE R7 R8 R4
      55 [-]: SETTABLEKS R7 R6 K12 ["CurrentNode"]
      56 [-]: GETUPVAL R7 4
      57 [-]: GETTABLEKS R6 R7 K10 ["Configs"]
      58 [-]: GETTABLEKS R7 R6 K18 ["FinalCameraOffset"]
      59 [-]: GETIMPORT R9 27 [nil]
      60 [-]: GETTABLE R8 R9 R4
      61 [-]: ADD R7 R7 R8 
      62 [-]: SETTABLEKS R7 R6 K18 ["FinalCameraOffset"]
L 1:  63 [-]: FORGLOOP R1 L0 2 [inext]
      64 [-]: GETUPVAL R2 5
      65 [-]: GETTABLEKS R1 R2 K28 [0x2862D37E]
      66 [-]: GETUPVAL R3 4
      67 [-]: GETTABLEKS R2 R3 K6 ["CameraSpot"]
      68 [-]: GETUPVAL R4 4
      69 [-]: GETTABLEKS R3 R4 K10 ["Configs"]
      70 [-]: GETUPVAL R7 4
      71 [-]: GETTABLEKS R6 R7 K10 ["Configs"]
      72 [-]: GETTABLEKS R5 R6 K29 ["NodeNormals"]
      73 [-]: GETUPVAL R8 4
      74 [-]: GETTABLEKS R7 R8 K10 ["Configs"]
      75 [-]: GETTABLEKS R6 R7 K12 ["CurrentNode"]
      76 [-]: GETTABLE R4 R5 R6
      77 [-]: CALL R1 3 0  
      78 [-]: RETURN R0 0  


; Name:            
; Defined at line: 2028
; #Upvalues:       4
; #Parameters:     0
; Is_vararg:       0
; Max Stack Size:  16

       0 [-]: GETUPVAL R2 0
       1 [-]: GETTABLEKS R1 R2 K0 ["Weapon"]
       2 [-]: FASTCALL1 62 R1 L0
       3 [-]: GETIMPORT R0 2 [nil]
       4 [-]: CALL R0 1 1  
L 0:   5 [-]: JUMPIF R0 L1 
       6 [-]: GETIMPORT R0 4 [nil]
       7 [-]: GETUPVAL R3 0
       8 [-]: GETTABLEKS R2 R3 K0 ["Weapon"]
       9 [-]: NAMECALL R0 R0 K5 [0x59C96E77]
      10 [-]: CALL R0 2 0  
      11 [-]: GETUPVAL R0 0
      12 [-]: LOADNIL R1   
      13 [-]: SETTABLEKS R1 R0 K0 ["Weapon"]
L 1:  14 [-]: LOADN R2 1   
      15 [-]: GETUPVAL R4 0
      16 [-]: GETTABLEKS R3 R4 K6 ["WeaponDecos"]
      17 [-]: LENGTH R0 R3 
      18 [-]: LOADN R1 1   
      19 [-]: FORNPREP R0 L11
L 2:  20 [-]: GETUPVAL R5 0
      21 [-]: GETTABLEKS R4 R5 K6 ["WeaponDecos"]
      22 [-]: FASTCALL1 62 R4 L3
      23 [-]: GETIMPORT R3 2 [nil]
      24 [-]: CALL R3 1 1  
L 3:  25 [-]: JUMPIF R3 L5 
      26 [-]: GETUPVAL R6 0
      27 [-]: GETTABLEKS R5 R6 K6 ["WeaponDecos"]
      28 [-]: GETTABLE R4 R5 R2
      29 [-]: FASTCALL1 62 R4 L4
      30 [-]: GETIMPORT R3 2 [nil]
      31 [-]: CALL R3 1 1  
L 4:  32 [-]: JUMPIF R3 L5 
      33 [-]: GETUPVAL R5 0
      34 [-]: GETTABLEKS R4 R5 K6 ["WeaponDecos"]
      35 [-]: GETTABLE R3 R4 R2
      36 [-]: LOADNIL R5   
      37 [-]: LOADB R6 1   
      38 [-]: LOADB R7 0   
      39 [-]: NAMECALL R3 R3 K7 [0x2970F52F]
      40 [-]: CALL R3 4 0  
L 5:  41 [-]: LOADN R5 1   
      42 [-]: LOADN R3 2   
      43 [-]: LOADN R4 1   
      44 [-]: FORNPREP R3 L10
L 6:  45 [-]: GETUPVAL R8 0
      46 [-]: GETTABLEKS R7 R8 K8 ["IncarnonAttachment"]
      47 [-]: FASTCALL1 62 R7 L7
      48 [-]: GETIMPORT R6 2 [nil]
      49 [-]: CALL R6 1 1  
L 7:  50 [-]: JUMPIF R6 L9 
      51 [-]: GETUPVAL R9 0
      52 [-]: GETTABLEKS R8 R9 K8 ["IncarnonAttachment"]
      53 [-]: GETTABLE R7 R8 R5
      54 [-]: FASTCALL1 62 R7 L8
      55 [-]: GETIMPORT R6 2 [nil]
      56 [-]: CALL R6 1 1  
L 8:  57 [-]: JUMPIF R6 L9 
      58 [-]: GETUPVAL R8 0
      59 [-]: GETTABLEKS R7 R8 K8 ["IncarnonAttachment"]
      60 [-]: GETTABLE R6 R7 R5
      61 [-]: NAMECALL R6 R6 K9 [0xA2880940]
      62 [-]: CALL R6 1 0  
      63 [-]: GETUPVAL R7 0
      64 [-]: GETTABLEKS R6 R7 K8 ["IncarnonAttachment"]
      65 [-]: LOADNIL R7   
      66 [-]: SETTABLE R7 R6 R5
L 9:  67 [-]: FORNLOOP R3 L6
L10:  68 [-]: FORNLOOP R0 L2
L11:  69 [-]: GETUPVAL R2 0
      70 [-]: GETTABLEKS R1 R2 K10 ["Configs"]
      71 [-]: FASTCALL1 62 R1 L12
      72 [-]: GETIMPORT R0 2 [nil]
      73 [-]: CALL R0 1 1  
L12:  74 [-]: JUMPIF R0 L18
      75 [-]: GETUPVAL R3 0
      76 [-]: GETTABLEKS R2 R3 K10 ["Configs"]
      77 [-]: GETTABLEKS R1 R2 K11 ["NodeFlyerEffect"]
      78 [-]: FASTCALL1 62 R1 L13
      79 [-]: GETIMPORT R0 2 [nil]
      80 [-]: CALL R0 1 1  
L13:  81 [-]: JUMPIF R0 L14
      82 [-]: GETIMPORT R0 13 [nil]
      83 [-]: GETUPVAL R4 0
      84 [-]: GETTABLEKS R3 R4 K10 ["Configs"]
      85 [-]: GETTABLEKS R2 R3 K11 ["NodeFlyerEffect"]
      86 [-]: NAMECALL R0 R0 K5 [0x59C96E77]
      87 [-]: CALL R0 2 0  
      88 [-]: GETUPVAL R1 0
      89 [-]: GETTABLEKS R0 R1 K10 ["Configs"]
      90 [-]: LOADNIL R1   
      91 [-]: SETTABLEKS R1 R0 K11 ["NodeFlyerEffect"]
L14:  92 [-]: LOADN R2 1   
      93 [-]: GETUPVAL R5 0
      94 [-]: GETTABLEKS R4 R5 K10 ["Configs"]
      95 [-]: GETTABLEKS R3 R4 K14 ["NodeDecos"]
      96 [-]: LENGTH R0 R3 
      97 [-]: LOADN R1 1   
      98 [-]: FORNPREP R0 L16
L15:  99 [-]: GETIMPORT R3 13 [nil]
     100 [-]: GETUPVAL R8 0
     101 [-]: GETTABLEKS R7 R8 K10 ["Configs"]
     102 [-]: GETTABLEKS R6 R7 K14 ["NodeDecos"]
     103 [-]: GETTABLE R5 R6 R2
     104 [-]: NAMECALL R3 R3 K5 [0x59C96E77]
     105 [-]: CALL R3 2 0  
     106 [-]: FORNLOOP R0 L15
L16: 107 [-]: LOADN R2 1   
     108 [-]: GETUPVAL R5 0
     109 [-]: GETTABLEKS R4 R5 K10 ["Configs"]
     110 [-]: GETTABLEKS R3 R4 K15 ["SplineInstances"]
     111 [-]: LENGTH R0 R3 
     112 [-]: LOADN R1 1   
     113 [-]: FORNPREP R0 L18
L17: 114 [-]: GETIMPORT R3 13 [nil]
     115 [-]: GETUPVAL R8 0
     116 [-]: GETTABLEKS R7 R8 K10 ["Configs"]
     117 [-]: GETTABLEKS R6 R7 K15 ["SplineInstances"]
     118 [-]: GETTABLE R5 R6 R2
     119 [-]: NAMECALL R3 R3 K5 [0x59C96E77]
     120 [-]: CALL R3 2 0  
     121 [-]: FORNLOOP R0 L17
L18: 122 [-]: GETIMPORT R0 18 [nil]
     123 [-]: GETIMPORT R1 20 [nil]
     124 [-]: GETUPVAL R4 0
     125 [-]: GETTABLEKS R3 R4 K21 ["WeaponTypes"]
     126 [-]: GETUPVAL R5 0
     127 [-]: GETTABLEKS R4 R5 K22 ["WeaponIndex"]
     128 [-]: GETTABLE R2 R3 R4
     129 [-]: CALL R0 2 1  
     130 [-]: JUMPXEQKNIL R0 L19
     131 [-]: GETIMPORT R0 24 [nil]
     132 [-]: LOADK R2 K25 ["RewardPanel.NoDioIcon"]
     133 [-]: LOADN R3 11  
     134 [-]: LOADB R4 1   
     135 [-]: NAMECALL R0 R0 K26 [0xAADE900E]
     136 [-]: CALL R0 4 0  
     137 [-]: RETURN R0 0  
L19: 138 [-]: GETIMPORT R0 4 [nil]
     139 [-]: NAMECALL R0 R0 K27 [0x78298275]
     140 [-]: CALL R0 1 1  
     141 [-]: FASTCALL1 62 R0 L20
     142 [-]: MOVE R2 R0   
     143 [-]: GETIMPORT R1 2 [nil]
     144 [-]: CALL R1 1 1  
L20: 145 [-]: JUMPIF R1 L22
     146 [-]: GETUPVAL R1 0
     147 [-]: GETIMPORT R2 4 [nil]
     148 [-]: GETIMPORT R4 29 [nil]
     149 [-]: GETUPVAL R7 0
     150 [-]: GETTABLEKS R6 R7 K21 ["WeaponTypes"]
     151 [-]: GETUPVAL R8 0
     152 [-]: GETTABLEKS R7 R8 K22 ["WeaponIndex"]
     153 [-]: GETTABLE R5 R6 R7
     154 [-]: CALL R4 1 1  
     155 [-]: MOVE R5 R0   
     156 [-]: NAMECALL R2 R2 K30 [0x765DAD71]
     157 [-]: CALL R2 3 1  
     158 [-]: SETTABLEKS R2 R1 K0 ["Weapon"]
     159 [-]: GETUPVAL R3 0
     160 [-]: GETTABLEKS R2 R3 K0 ["Weapon"]
     161 [-]: FASTCALL1 62 R2 L21
     162 [-]: GETIMPORT R1 2 [nil]
     163 [-]: CALL R1 1 1  
L21: 164 [-]: JUMPIF R1 L22
     165 [-]: GETUPVAL R2 0
     166 [-]: GETTABLEKS R1 R2 K0 ["Weapon"]
     167 [-]: MOVE R3 R0   
     168 [-]: NAMECALL R1 R1 K31 [0x054E3C19]
     169 [-]: CALL R1 2 0  
L22: 170 [-]: GETUPVAL R1 0
     171 [-]: GETUPVAL R2 0
     172 [-]: GETUPVAL R3 0
     173 [-]: GETUPVAL R4 0
     174 [-]: GETUPVAL R6 1
     175 [-]: GETTABLEKS R5 R6 K32 [0x5333C3AF]
     176 [-]: GETUPVAL R9 0
     177 [-]: GETTABLEKS R6 R9 K0 ["Weapon"]
     178 [-]: CALL R5 1 4  
     179 [-]: SETTABLEKS R5 R1 K33 ["CameraSpot"]
     180 [-]: SETTABLEKS R6 R2 K6 ["WeaponDecos"]
     181 [-]: SETTABLEKS R7 R3 K34 ["HasOffHand"]
     182 [-]: SETTABLEKS R8 R4 K35 ["QueueDioConfigure"]
     183 [-]: GETUPVAL R3 0
     184 [-]: GETTABLEKS R2 R3 K33 ["CameraSpot"]
     185 [-]: FASTCALL1 62 R2 L23
     186 [-]: GETIMPORT R1 2 [nil]
     187 [-]: CALL R1 1 1  
L23: 188 [-]: JUMPIF R1 L25
     189 [-]: GETUPVAL R3 0
     190 [-]: GETTABLEKS R2 R3 K6 ["WeaponDecos"]
     191 [-]: FASTCALL1 62 R2 L24
     192 [-]: GETIMPORT R1 2 [nil]
     193 [-]: CALL R1 1 1  
L24: 194 [-]: JUMPIF R1 L25
     195 [-]: GETUPVAL R3 0
     196 [-]: GETTABLEKS R2 R3 K6 ["WeaponDecos"]
     197 [-]: LENGTH R1 R2 
     198 [-]: LOADN R2 2   
     199 [-]: JUMPIFNOTLE R2 R1 L25
     200 [-]: GETUPVAL R2 0
     201 [-]: GETTABLEKS R1 R2 K35 ["QueueDioConfigure"]
     202 [-]: JUMPIF R1 L25
     203 [-]: GETUPVAL R1 2
     204 [-]: CALL R1 0 0  
L25: 205 [-]: GETUPVAL R3 0
     206 [-]: GETTABLEKS R2 R3 K0 ["Weapon"]
     207 [-]: FASTCALL1 62 R2 L26
     208 [-]: GETIMPORT R1 2 [nil]
     209 [-]: CALL R1 1 1  
L26: 210 [-]: JUMPIF R1 L37
     211 [-]: LOADN R3 1   
     212 [-]: LOADN R1 2   
     213 [-]: LOADN R2 1   
     214 [-]: FORNPREP R1 L37
L27: 215 [-]: GETUPVAL R6 0
     216 [-]: GETTABLEKS R5 R6 K0 ["Weapon"]
     217 [-]: LOADN R7 1   
     218 [-]: GETUPVAL R9 3
     219 [-]: GETTABLEKS R8 R9 K36 [0x06D055F9]
     220 [-]: JUMPXEQKN R3 K37 L28 [1]
     221 [-]: LOADB R9 0 +1
L28: 222 [-]: LOADB R9 1   
L29: 223 [-]: LOADN R10 2  
     224 [-]: LOADN R11 3  
     225 [-]: CALL R8 3 -1 
     226 [-]: NAMECALL R5 R5 K38 [0xDD787662]
     227 [-]: CALL R5 -1 1 
     228 [-]: GETTABLEKS R4 R5 K39 ["mType"]
     229 [-]: FASTCALL1 62 R4 L30
     230 [-]: MOVE R6 R4   
     231 [-]: GETIMPORT R5 2 [nil]
     232 [-]: CALL R5 1 1  
L30: 233 [-]: JUMPIF R5 L36
     234 [-]: GETUPVAL R6 0
     235 [-]: GETTABLEKS R5 R6 K8 ["IncarnonAttachment"]
     236 [-]: JUMPXEQKNIL R5 L31 NOT
     237 [-]: GETUPVAL R5 0
     238 [-]: NEWTABLE R6 0 0
     239 [-]: SETTABLEKS R6 R5 K8 ["IncarnonAttachment"]
L31: 240 [-]: GETUPVAL R8 0
     241 [-]: GETTABLEKS R7 R8 K8 ["IncarnonAttachment"]
     242 [-]: LENGTH R6 R7 
     243 [-]: ADDK R5 R6 K37 [1]
     244 [-]: GETUPVAL R9 0
     245 [-]: GETTABLEKS R8 R9 K6 ["WeaponDecos"]
     246 [-]: GETTABLE R7 R8 R5
     247 [-]: FASTCALL1 62 R7 L32
     248 [-]: GETIMPORT R6 2 [nil]
     249 [-]: CALL R6 1 1  
L32: 250 [-]: JUMPIF R6 L36
     251 [-]: GETUPVAL R7 0
     252 [-]: GETTABLEKS R6 R7 K8 ["IncarnonAttachment"]
     253 [-]: GETUPVAL R9 0
     254 [-]: GETTABLEKS R8 R9 K6 ["WeaponDecos"]
     255 [-]: GETTABLE R7 R8 R5
     256 [-]: MOVE R9 R4   
     257 [-]: GETIMPORT R10 41 [nil]
     258 [-]: GETIMPORT R11 43 [nil]
     259 [-]: GETIMPORT R12 45 [nil]
     260 [-]: GETUPVAL R15 0
     261 [-]: GETTABLEKS R14 R15 K6 ["WeaponDecos"]
     262 [-]: GETTABLEN R13 R14 1
     263 [-]: NAMECALL R13 R13 K46 [0xED324116]
     264 [-]: CALL R13 1 -1
     265 [-]: NAMECALL R7 R7 K47 [0x47901F07]
     266 [-]: CALL R7 -1 1 
     267 [-]: SETTABLE R7 R6 R5
     268 [-]: GETUPVAL R9 0
     269 [-]: GETTABLEKS R8 R9 K8 ["IncarnonAttachment"]
     270 [-]: GETTABLE R7 R8 R5
     271 [-]: FASTCALL1 62 R7 L33
     272 [-]: GETIMPORT R6 2 [nil]
     273 [-]: CALL R6 1 1  
L33: 274 [-]: JUMPIF R6 L36
     275 [-]: GETUPVAL R8 0
     276 [-]: GETTABLEKS R7 R8 K8 ["IncarnonAttachment"]
     277 [-]: GETTABLE R6 R7 R5
     278 [-]: NAMECALL R6 R6 K48 [0x905BB2BD]
     279 [-]: CALL R6 1 1  
     280 [-]: GETIMPORT R7 50 [nil]
     281 [-]: MOVE R8 R6   
     282 [-]: CALL R7 1 3  
     283 [-]: FORGPREP_INEXT R7 L35
L34: 284 [-]: GETIMPORT R12 52 [nil]
     285 [-]: NAMECALL R13 R11 K53 [0xED4E0128]
     286 [-]: CALL R13 1 1 
     287 [-]: LOADK R14 K54 ["Incarnon"]
     288 [-]: CALL R12 2 1 
     289 [-]: JUMPIFNOT R12 L35
     290 [-]: LOADB R14 0  
     291 [-]: NAMECALL R12 R11 K55 [0x33F6EBDE]
     292 [-]: CALL R12 2 0 
L35: 293 [-]: FORGLOOP R7 L34 2 [inext]
     294 [-]: GETUPVAL R9 0
     295 [-]: GETTABLEKS R8 R9 K8 ["IncarnonAttachment"]
     296 [-]: GETTABLE R7 R8 R5
     297 [-]: LOADN R9 1   
     298 [-]: NAMECALL R7 R7 K56 [0x66472BF5]
     299 [-]: CALL R7 2 0  
L36: 300 [-]: FORNLOOP R1 L27
L37: 301 [-]: RETURN R0 0  


; Name:            
; Defined at line: 2107
; #Upvalues:       26
; #Parameters:     0
; Is_vararg:       0
; Max Stack Size:  16

       0 [-]: GETIMPORT R0 1 [nil]
       1 [-]: CALL R0 0 1  
       2 [-]: GETIMPORT R1 3 [nil]
       3 [-]: MOVE R3 R0   
       4 [-]: NAMECALL R1 R1 K4 [0x8A8C8D5A]
       5 [-]: CALL R1 2 0  
       6 [-]: GETUPVAL R2 0
       7 [-]: FASTCALL1 62 R2 L0
       8 [-]: GETIMPORT R1 6 [nil]
       9 [-]: CALL R1 1 1  
L 0:  10 [-]: JUMPIF R1 L1 
      11 [-]: GETUPVAL R1 0
      12 [-]: GETIMPORT R3 1 [nil]
      13 [-]: CALL R3 0 -1 
      14 [-]: NAMECALL R1 R1 K7 [0xFAA69527]
      15 [-]: CALL R1 -1 0 
L 1:  16 [-]: GETUPVAL R3 1
      17 [-]: GETTABLEKS R2 R3 K8 ["Grid"]
      18 [-]: FASTCALL1 62 R2 L2
      19 [-]: GETIMPORT R1 6 [nil]
      20 [-]: CALL R1 1 1  
L 2:  21 [-]: JUMPIF R1 L4 
      22 [-]: GETUPVAL R2 1
      23 [-]: GETTABLEKS R1 R2 K9 ["Tier"]
      24 [-]: JUMPXEQKNIL R1 L4
      25 [-]: GETUPVAL R2 1
      26 [-]: GETTABLEKS R1 R2 K8 ["Grid"]
      27 [-]: GETUPVAL R4 1
      28 [-]: GETTABLEKS R3 R4 K9 ["Tier"]
      29 [-]: NAMECALL R1 R1 K10 [0xA14DAA2B]
      30 [-]: CALL R1 2 1  
      31 [-]: FASTCALL1 62 R1 L3
      32 [-]: MOVE R3 R1   
      33 [-]: GETIMPORT R2 6 [nil]
      34 [-]: CALL R2 1 1  
L 3:  35 [-]: JUMPIF R2 L4 
      36 [-]: GETIMPORT R2 3 [nil]
      37 [-]: GETTABLEKS R4 R1 K11 ["mClipName"]
      38 [-]: LOADK R5 K12 ["CurrTier.Outer"]
      39 [-]: LOADN R6 14  
      40 [-]: NAMECALL R2 R2 K13 [0x2CE15376]
      41 [-]: CALL R2 4 1  
      42 [-]: GETIMPORT R3 3 [nil]
      43 [-]: GETTABLEKS R5 R1 K11 ["mClipName"]
      44 [-]: LOADK R6 K12 ["CurrTier.Outer"]
      45 [-]: LOADN R7 14  
      46 [-]: ADDK R9 R2 K15 [1]
      47 [-]: MODK R8 R9 K14 [360]
      48 [-]: NAMECALL R3 R3 K16 [0xF64B7262]
      49 [-]: CALL R3 5 0  
L 4:  50 [-]: GETUPVAL R2 2
      51 [-]: GETTABLEKS R1 R2 K17 ["IsLoading"]
      52 [-]: JUMPIFNOT R1 L9
      53 [-]: GETUPVAL R3 2
      54 [-]: GETTABLEKS R2 R3 K18 ["Loader"]
      55 [-]: FASTCALL1 62 R2 L5
      56 [-]: GETIMPORT R1 6 [nil]
      57 [-]: CALL R1 1 1  
L 5:  58 [-]: JUMPIF R1 L9 
      59 [-]: GETUPVAL R2 2
      60 [-]: GETTABLEKS R1 R2 K18 ["Loader"]
      61 [-]: NAMECALL R1 R1 K19 [0xD2D3875A]
      62 [-]: CALL R1 1 1  
      63 [-]: JUMPIFNOT R1 L9
      64 [-]: GETUPVAL R1 2
      65 [-]: LOADB R2 0   
      66 [-]: SETTABLEKS R2 R1 K17 ["IsLoading"]
      67 [-]: GETUPVAL R1 2
      68 [-]: LOADB R2 1   
      69 [-]: SETTABLEKS R2 R1 K20 ["Loaded"]
      70 [-]: GETIMPORT R1 22 [nil]
      71 [-]: GETUPVAL R3 2
      72 [-]: GETTABLEKS R2 R3 K23 ["DioWRes"]
      73 [-]: CALL R1 1 1  
      74 [-]: GETIMPORT R2 25 [nil]
      75 [-]: MOVE R4 R1   
      76 [-]: NAMECALL R2 R2 K26 [0xC019F5E6]
      77 [-]: CALL R2 2 0  
      78 [-]: GETIMPORT R3 29 [nil]
      79 [-]: FASTCALL1 62 R3 L6
      80 [-]: GETIMPORT R2 6 [nil]
      81 [-]: CALL R2 1 1  
L 6:  82 [-]: JUMPIF R2 L8 
      83 [-]: GETIMPORT R2 29 [nil]
      84 [-]: LOADK R3 K30 [0.25]
      85 [-]: LOADNIL R4   
      86 [-]: LOADNIL R5   
      87 [-]: GETUPVAL R7 3
      88 [-]: GETTABLEKS R6 R7 K31 [0x06D055F9]
      89 [-]: GETUPVAL R7 4
      90 [-]: JUMPIF R7 L7 
      91 [-]: GETUPVAL R7 5
L 7:  92 [-]: LOADNIL R8   
      93 [-]: GETUPVAL R9 6
      94 [-]: CALL R6 3 -1 
      95 [-]: CALL R2 -1 0 
L 8:  96 [-]: GETUPVAL R2 7
      97 [-]: JUMPXEQKN R2 K15 L11 NOT [1]
      98 [-]: GETUPVAL R2 8
      99 [-]: CALL R2 0 0  
     100 [-]: JUMP L11
    
L 9: 101 [-]: GETUPVAL R2 2
     102 [-]: GETTABLEKS R1 R2 K20 ["Loaded"]
     103 [-]: JUMPIFNOT R1 L11
     104 [-]: GETUPVAL R1 7
     105 [-]: JUMPXEQKN R1 K15 L11 NOT [1]
     106 [-]: GETUPVAL R2 2
     107 [-]: GETTABLEKS R1 R2 K32 ["QueueDioConfigure"]
     108 [-]: JUMPIFNOT R1 L10
     109 [-]: GETUPVAL R1 9
     110 [-]: CALL R1 0 0  
     111 [-]: GETUPVAL R1 2
     112 [-]: LOADB R2 0   
     113 [-]: SETTABLEKS R2 R1 K32 ["QueueDioConfigure"]
     114 [-]: JUMP L11
    
L10: 115 [-]: GETUPVAL R2 2
     116 [-]: GETTABLEKS R1 R2 K33 ["Configs"]
     117 [-]: JUMPXEQKNIL R1 L11
     118 [-]: GETUPVAL R2 10
     119 [-]: GETTABLEKS R1 R2 K34 [0xBC21747F]
     120 [-]: GETUPVAL R3 2
     121 [-]: GETTABLEKS R2 R3 K35 ["CameraSpot"]
     122 [-]: GETUPVAL R4 2
     123 [-]: GETTABLEKS R3 R4 K33 ["Configs"]
     124 [-]: MOVE R4 R0   
     125 [-]: CALL R1 3 0  
     126 [-]: GETUPVAL R2 10
     127 [-]: GETTABLEKS R1 R2 K36 [0x63A826C3]
     128 [-]: GETUPVAL R3 2
     129 [-]: GETTABLEKS R2 R3 K35 ["CameraSpot"]
     130 [-]: GETUPVAL R4 2
     131 [-]: GETTABLEKS R3 R4 K33 ["Configs"]
     132 [-]: MOVE R4 R0   
     133 [-]: LOADN R5 4   
     134 [-]: GETUPVAL R6 11
     135 [-]: CALL R1 5 0  
L11: 136 [-]: GETUPVAL R2 1
     137 [-]: GETTABLEKS R1 R2 K17 ["IsLoading"]
     138 [-]: JUMPIFNOT R1 L14
     139 [-]: GETUPVAL R3 1
     140 [-]: GETTABLEKS R2 R3 K18 ["Loader"]
     141 [-]: FASTCALL1 62 R2 L12
     142 [-]: GETIMPORT R1 6 [nil]
     143 [-]: CALL R1 1 1  
L12: 144 [-]: JUMPIF R1 L14
     145 [-]: GETUPVAL R2 1
     146 [-]: GETTABLEKS R1 R2 K18 ["Loader"]
     147 [-]: NAMECALL R1 R1 K19 [0xD2D3875A]
     148 [-]: CALL R1 1 1  
     149 [-]: JUMPIFNOT R1 L14
     150 [-]: GETUPVAL R1 1
     151 [-]: LOADB R2 0   
     152 [-]: SETTABLEKS R2 R1 K17 ["IsLoading"]
     153 [-]: GETUPVAL R2 1
     154 [-]: GETTABLEKS R1 R2 K37 ["Spinner"]
     155 [-]: LOADB R3 0   
     156 [-]: NAMECALL R1 R1 K38 [0x46610C50]
     157 [-]: CALL R1 2 0  
     158 [-]: GETUPVAL R2 1
     159 [-]: GETTABLEKS R1 R2 K39 ["NeedReroll"]
     160 [-]: JUMPIF R1 L13
     161 [-]: GETUPVAL R1 12
     162 [-]: CALL R1 0 0  
L13: 163 [-]: GETUPVAL R2 13
     164 [-]: GETTABLEKS R1 R2 K40 ["HasClaim"]
     165 [-]: JUMPIF R1 L14
     166 [-]: GETUPVAL R2 1
     167 [-]: GETTABLEKS R1 R2 K39 ["NeedReroll"]
     168 [-]: JUMPIFNOT R1 L14
     169 [-]: GETUPVAL R1 14
     170 [-]: CALL R1 0 0  
L14: 171 [-]: GETUPVAL R2 13
     172 [-]: GETTABLEKS R1 R2 K40 ["HasClaim"]
     173 [-]: JUMPIFNOT R1 L15
     174 [-]: GETUPVAL R2 13
     175 [-]: GETTABLEKS R1 R2 K41 ["Rewards"]
     176 [-]: JUMPXEQKNIL R1 L15
     177 [-]: GETUPVAL R2 1
     178 [-]: GETTABLEKS R1 R2 K17 ["IsLoading"]
     179 [-]: JUMPIF R1 L15
     180 [-]: GETUPVAL R1 15
     181 [-]: CALL R1 0 0  
L15: 182 [-]: GETUPVAL R2 16
     183 [-]: GETTABLEKS R1 R2 K17 ["IsLoading"]
     184 [-]: JUMPIFNOT R1 L17
     185 [-]: GETUPVAL R3 16
     186 [-]: GETTABLEKS R2 R3 K18 ["Loader"]
     187 [-]: FASTCALL1 62 R2 L16
     188 [-]: GETIMPORT R1 6 [nil]
     189 [-]: CALL R1 1 1  
L16: 190 [-]: JUMPIF R1 L17
     191 [-]: GETUPVAL R2 16
     192 [-]: GETTABLEKS R1 R2 K18 ["Loader"]
     193 [-]: NAMECALL R1 R1 K19 [0xD2D3875A]
     194 [-]: CALL R1 1 1  
     195 [-]: JUMPIFNOT R1 L17
     196 [-]: GETUPVAL R1 16
     197 [-]: LOADB R2 0   
     198 [-]: SETTABLEKS R2 R1 K17 ["IsLoading"]
     199 [-]: GETUPVAL R1 17
     200 [-]: LOADB R3 0   
     201 [-]: NAMECALL R1 R1 K38 [0x46610C50]
     202 [-]: CALL R1 2 0  
     203 [-]: GETUPVAL R1 18
     204 [-]: CALL R1 0 0  
L17: 205 [-]: GETUPVAL R1 4
     206 [-]: JUMPIF R1 L26
     207 [-]: GETUPVAL R2 13
     208 [-]: GETTABLEKS R1 R2 K40 ["HasClaim"]
     209 [-]: JUMPIF R1 L26
     210 [-]: GETUPVAL R2 1
     211 [-]: GETTABLEKS R1 R2 K17 ["IsLoading"]
     212 [-]: JUMPIF R1 L26
     213 [-]: GETUPVAL R3 1
     214 [-]: GETTABLEKS R2 R3 K8 ["Grid"]
     215 [-]: FASTCALL1 62 R2 L18
     216 [-]: GETIMPORT R1 6 [nil]
     217 [-]: CALL R1 1 1  
L18: 218 [-]: JUMPIF R1 L26
     219 [-]: GETUPVAL R2 19
     220 [-]: FASTCALL1 62 R2 L19
     221 [-]: GETIMPORT R1 6 [nil]
     222 [-]: CALL R1 1 1  
L19: 223 [-]: JUMPIF R1 L23
     224 [-]: GETUPVAL R3 19
     225 [-]: GETUPVAL R4 20
     226 [-]: GETTABLE R2 R3 R4
     227 [-]: FASTCALL1 62 R2 L20
     228 [-]: GETIMPORT R1 6 [nil]
     229 [-]: CALL R1 1 1  
L20: 230 [-]: JUMPIF R1 L23
     231 [-]: GETIMPORT R1 44 [nil]
     232 [-]: GETUPVAL R4 19
     233 [-]: GETUPVAL R5 20
     234 [-]: GETTABLE R3 R4 R5
     235 [-]: GETTABLEKS R2 R3 K45 ["mExpiry"]
     236 [-]: CALL R1 1 1  
     237 [-]: LOADN R2 0   
     238 [-]: JUMPIFLE R1 R2 L21
     239 [-]: GETIMPORT R2 47 [nil]
     240 [-]: JUMPIFNOT R2 L22
L21: 241 [-]: GETIMPORT R2 48 [nil]
     242 [-]: LOADNIL R3   
     243 [-]: SETTABLEKS R3 R2 K46 ["ForceReroll"]
     244 [-]: NEWTABLE R2 0 0
     245 [-]: GETUPVAL R3 21
     246 [-]: MOVE R4 R2   
     247 [-]: CALL R3 1 0  
     248 [-]: GETUPVAL R3 1
     249 [-]: LOADB R4 1   
     250 [-]: SETTABLEKS R4 R3 K39 ["NeedReroll"]
     251 [-]: GETUPVAL R4 1
     252 [-]: GETTABLEKS R3 R4 K8 ["Grid"]
     253 [-]: NAMECALL R3 R3 K49 [0x7C09C373]
     254 [-]: CALL R3 1 0  
     255 [-]: GETIMPORT R3 3 [nil]
     256 [-]: LOADK R5 K50 ["RewardPanel.ExtraReward"]
     257 [-]: LOADN R6 11  
     258 [-]: LOADB R7 0   
     259 [-]: NAMECALL R3 R3 K51 [0xAADE900E]
     260 [-]: CALL R3 4 0  
     261 [-]: GETIMPORT R3 3 [nil]
     262 [-]: LOADK R5 K52 ["RewardPanel.XpBar"]
     263 [-]: LOADN R6 11  
     264 [-]: LOADB R7 0   
     265 [-]: NAMECALL R3 R3 K51 [0xAADE900E]
     266 [-]: CALL R3 4 0  
     267 [-]: GETUPVAL R3 1
     268 [-]: GETIMPORT R4 55 [nil]
     269 [-]: MOVE R5 R2   
     270 [-]: CALL R4 1 1  
     271 [-]: SETTABLEKS R4 R3 K18 ["Loader"]
     272 [-]: GETUPVAL R3 1
     273 [-]: LOADB R4 1   
     274 [-]: SETTABLEKS R4 R3 K17 ["IsLoading"]
     275 [-]: GETUPVAL R4 1
     276 [-]: GETTABLEKS R3 R4 K37 ["Spinner"]
     277 [-]: LOADB R5 1   
     278 [-]: NAMECALL R3 R3 K38 [0x46610C50]
     279 [-]: CALL R3 2 0  
     280 [-]: GETUPVAL R4 3
     281 [-]: GETTABLEKS R3 R4 K56 [0xE0CBA3CA]
     282 [-]: LOADK R4 K57 ["/Lotus/Language/Duviri/EndlessSetupWeekRollover"]
     283 [-]: CALL R3 1 0  
     284 [-]: JUMP L23
    
L22: 285 [-]: LOADK R3 K58 ["<p><font color=\""]
     286 [-]: GETUPVAL R7 22
     287 [-]: GETTABLEKS R4 R7 K59 ["FloatingContentHex"]
     288 [-]: LOADK R5 K60 ["\">"]
     289 [-]: GETIMPORT R6 3 [nil]
     290 [-]: LOADK R8 K61 ["/Lotus/Language/Duviri/EndlessSetupRewardResetTime"]
     291 [-]: LOADB R9 1   
     292 [-]: DUPTABLE R10 65
     293 [-]: LOADK R12 K66 ["<font color=\""]
     294 [-]: GETUPVAL R15 22
     295 [-]: GETTABLEKS R13 R15 K67 ["FloatingContentHighlightHex"]
     296 [-]: LOADK R14 K60 ["\">"]
     297 [-]: CONCAT R11 R12 R14
     298 [-]: SETTABLEKS R11 R10 K62 ["OPEN_COLOR"]
     299 [-]: GETUPVAL R12 23
     300 [-]: GETTABLEKS R11 R12 K68 [0xCFE63447]
     301 [-]: MOVE R12 R1  
     302 [-]: LOADB R13 1  
     303 [-]: LOADB R14 1  
     304 [-]: CALL R11 3 1 
     305 [-]: SETTABLEKS R11 R10 K63 ["TIME"]
     306 [-]: LOADK R11 K69 ["</font>"]
     307 [-]: SETTABLEKS R11 R10 K64 ["CLOSE_COLOR"]
     308 [-]: NAMECALL R6 R6 K70 [0x42B04007]
     309 [-]: CALL R6 4 1  
     310 [-]: CONCAT R2 R3 R6
     311 [-]: MOVE R3 R2   
     312 [-]: LOADK R4 K71 ["</font></p>"]
     313 [-]: CONCAT R2 R3 R4
     314 [-]: GETIMPORT R3 3 [nil]
     315 [-]: LOADK R5 K72 ["RewardPanel.Modes.TimeLeft"]
     316 [-]: LOADN R6 29  
     317 [-]: MOVE R7 R2   
     318 [-]: NAMECALL R3 R3 K73 [0x5F56EEAB]
     319 [-]: CALL R3 4 0  
L23: 320 [-]: GETUPVAL R1 1
     321 [-]: GETUPVAL R4 1
     322 [-]: GETTABLEKS R3 R4 K74 ["IconCycleTimer"]
     323 [-]: SUB R2 R3 R0 
     324 [-]: SETTABLEKS R2 R1 K74 ["IconCycleTimer"]
     325 [-]: GETUPVAL R2 1
     326 [-]: GETTABLEKS R1 R2 K74 ["IconCycleTimer"]
     327 [-]: LOADN R2 0   
     328 [-]: JUMPIFNOTLE R1 R2 L24
     329 [-]: GETUPVAL R1 1
     330 [-]: LOADN R2 10  
     331 [-]: SETTABLEKS R2 R1 K74 ["IconCycleTimer"]
     332 [-]: GETUPVAL R2 1
     333 [-]: GETTABLEKS R1 R2 K8 ["Grid"]
     334 [-]: NAMECALL R1 R1 K75 [0x48396E2F]
     335 [-]: CALL R1 1 0  
L24: 336 [-]: GETUPVAL R2 1
     337 [-]: GETTABLEKS R1 R2 K8 ["Grid"]
     338 [-]: NEWCLOSURE R3 P0
     339 [-]: MOVE R2 R24  
     340 [-]: MOVE R0 R0   
     341 [-]: NAMECALL R1 R1 K76 [0xEA061E98]
     342 [-]: CALL R1 2 0  
     343 [-]: GETUPVAL R4 1
     344 [-]: GETTABLEKS R3 R4 K8 ["Grid"]
     345 [-]: GETTABLEKS R2 R3 K77 ["mExtraReward"]
     346 [-]: FASTCALL1 62 R2 L25
     347 [-]: GETIMPORT R1 6 [nil]
     348 [-]: CALL R1 1 1  
L25: 349 [-]: JUMPIF R1 L26
     350 [-]: GETUPVAL R1 24
     351 [-]: GETUPVAL R4 1
     352 [-]: GETTABLEKS R3 R4 K8 ["Grid"]
     353 [-]: GETTABLEKS R2 R3 K77 ["mExtraReward"]
     354 [-]: MOVE R3 R0   
     355 [-]: CALL R1 2 0  
L26: 356 [-]: GETUPVAL R1 5
     357 [-]: JUMPIFNOT R1 L27
     358 [-]: GETUPVAL R2 13
     359 [-]: GETTABLEKS R1 R2 K78 ["Fx"]
     360 [-]: JUMPXEQKNIL R1 L27
     361 [-]: GETUPVAL R2 13
     362 [-]: GETTABLEKS R1 R2 K78 ["Fx"]
     363 [-]: MOVE R3 R0   
     364 [-]: NAMECALL R1 R1 K7 [0xFAA69527]
     365 [-]: CALL R1 2 0  
L27: 366 [-]: GETUPVAL R1 25
     367 [-]: JUMPXEQKNIL R1 L28
     368 [-]: GETUPVAL R1 25
     369 [-]: NEWCLOSURE R3 P1
     370 [-]: MOVE R0 R0   
     371 [-]: NAMECALL R1 R1 K76 [0xEA061E98]
     372 [-]: CALL R1 2 0  
L28: 373 [-]: RETURN R0 0  


; Name:            
; Defined at line: 2228
; #Upvalues:       6
; #Parameters:     0
; Is_vararg:       0
; Max Stack Size:  3

       0 [-]: GETIMPORT R0 1 [nil]
       1 [-]: LOADNIL R1   
       2 [-]: SETTABLEKS R1 R0 K2 ["InfoPopup_Grid"]
       3 [-]: GETIMPORT R0 1 [nil]
       4 [-]: LOADNIL R1   
       5 [-]: SETTABLEKS R1 R0 K3 ["InfoPopup_Data"]
       6 [-]: GETIMPORT R0 1 [nil]
       7 [-]: LOADNIL R1   
       8 [-]: SETTABLEKS R1 R0 K4 ["InfoPopup_Data2"]
       9 [-]: GETIMPORT R0 1 [nil]
      10 [-]: LOADNIL R1   
      11 [-]: SETTABLEKS R1 R0 K5 ["gToolTip"]
      12 [-]: GETUPVAL R0 0
      13 [-]: JUMPIFNOT R0 L1
      14 [-]: GETIMPORT R1 7 [nil]
      15 [-]: FASTCALL1 62 R1 L0
      16 [-]: GETIMPORT R0 9 [nil]
      17 [-]: CALL R0 1 1  
L 0:  18 [-]: JUMPIF R0 L1 
      19 [-]: GETIMPORT R0 7 [nil]
      20 [-]: CALL R0 0 0  
L 1:  21 [-]: GETUPVAL R1 1
      22 [-]: GETTABLEKS R0 R1 K10 [0x15DEABB1]
      23 [-]: LOADB R1 0   
      24 [-]: CALL R0 1 0  
      25 [-]: GETUPVAL R1 1
      26 [-]: GETTABLEKS R0 R1 K11 [0x9E3D3434]
      27 [-]: LOADB R1 0   
      28 [-]: CALL R0 1 0  
      29 [-]: GETIMPORT R1 13 [nil]
      30 [-]: FASTCALL1 62 R1 L2
      31 [-]: GETIMPORT R0 9 [nil]
      32 [-]: CALL R0 1 1  
L 2:  33 [-]: JUMPIF R0 L3 
      34 [-]: GETIMPORT R0 13 [nil]
      35 [-]: LOADB R2 0   
      36 [-]: NAMECALL R0 R0 K14 [0xC02F2CB8]
      37 [-]: CALL R0 2 0  
L 3:  38 [-]: GETUPVAL R0 2
      39 [-]: DUPCLOSURE R2 K15 []
      40 [-]: NAMECALL R0 R0 K16 [0xEA061E98]
      41 [-]: CALL R0 2 0  
      42 [-]: GETUPVAL R1 3
      43 [-]: GETTABLEKS R0 R1 K17 [0x659D451F]
      44 [-]: GETIMPORT R2 19 [nil]
      45 [-]: GETTABLEKS R1 R2 K20 ["UISound_GridOpenTwo"]
      46 [-]: CALL R0 1 0  
      47 [-]: GETUPVAL R1 4
      48 [-]: GETTABLEKS R0 R1 K21 ["Fx"]
      49 [-]: JUMPXEQKNIL R0 L4
      50 [-]: GETUPVAL R1 4
      51 [-]: GETTABLEKS R0 R1 K21 ["Fx"]
      52 [-]: NAMECALL R0 R0 K22 [0xA2880940]
      53 [-]: CALL R0 1 0  
      54 [-]: GETUPVAL R0 4
      55 [-]: LOADNIL R1   
      56 [-]: SETTABLEKS R1 R0 K21 ["Fx"]
L 4:  57 [-]: GETUPVAL R1 5
      58 [-]: GETTABLEKS R0 R1 K23 ["Loaded"]
      59 [-]: JUMPIFNOT R0 L6
      60 [-]: GETIMPORT R1 25 [nil]
      61 [-]: FASTCALL1 62 R1 L5
      62 [-]: GETIMPORT R0 9 [nil]
      63 [-]: CALL R0 1 1  
L 5:  64 [-]: JUMPIF R0 L6 
      65 [-]: GETIMPORT R0 25 [nil]
      66 [-]: NAMECALL R0 R0 K26 [0xB21930E8]
      67 [-]: CALL R0 1 0  
L 6:  68 [-]: GETIMPORT R1 28 [nil]
      69 [-]: FASTCALL1 62 R1 L7
      70 [-]: GETIMPORT R0 9 [nil]
      71 [-]: CALL R0 1 1  
L 7:  72 [-]: JUMPIF R0 L8 
      73 [-]: GETIMPORT R0 28 [nil]
      74 [-]: CALL R0 0 0  
L 8:  75 [-]: GETIMPORT R1 30 [nil]
      76 [-]: FASTCALL1 62 R1 L9
      77 [-]: GETIMPORT R0 9 [nil]
      78 [-]: CALL R0 1 1  
L 9:  79 [-]: JUMPIF R0 L10
      80 [-]: GETIMPORT R0 30 [nil]
      81 [-]: GETIMPORT R1 32 [nil]
      82 [-]: LOADNIL R2   
      83 [-]: CALL R0 2 0  
L10:  84 [-]: GETIMPORT R1 34 [nil]
      85 [-]: FASTCALL1 62 R1 L11
      86 [-]: GETIMPORT R0 9 [nil]
      87 [-]: CALL R0 1 1  
L11:  88 [-]: JUMPIF R0 L12
      89 [-]: GETIMPORT R0 34 [nil]
      90 [-]: CALL R0 0 0  
L12:  91 [-]: RETURN R0 0  


; Name:            
; Defined at line: 2277
; #Upvalues:       2
; #Parameters:     4
; Is_vararg:       0
; Max Stack Size:  11

       0 [-]: GETUPVAL R5 0
       1 [-]: FASTCALL1 62 R5 L0
       2 [-]: GETIMPORT R4 1 [nil]
       3 [-]: CALL R4 1 1  
L 0:   4 [-]: JUMPIF R4 L1 
       5 [-]: GETUPVAL R4 0
       6 [-]: MOVE R6 R0   
       7 [-]: MOVE R7 R1   
       8 [-]: NAMECALL R4 R4 K2 [0xFAA69527]
       9 [-]: CALL R4 3 0  
L 1:  10 [-]: GETUPVAL R5 1
      11 [-]: GETTABLEKS R4 R5 K3 [0x44537ADF]
      12 [-]: GETIMPORT R5 5 [nil]
      13 [-]: CALL R4 1 2  
      14 [-]: GETIMPORT R6 5 [nil]
      15 [-]: LOADK R8 K6 ["RewardPanel.BottomFade"]
      16 [-]: LOADN R9 12  
      17 [-]: MULK R10 R4 K7 [2]
      18 [-]: NAMECALL R6 R6 K8 [0x67BC869F]
      19 [-]: CALL R6 4 0  
      20 [-]: RETURN R0 0  


; Name:            
; Defined at line: 2286
; #Upvalues:       1
; #Parameters:     4
; Is_vararg:       0
; Max Stack Size:  9

       0 [-]: GETUPVAL R4 0
       1 [-]: MOVE R5 R0   
       2 [-]: MOVE R6 R1   
       3 [-]: MOVE R7 R2   
       4 [-]: MOVE R8 R3   
       5 [-]: CALL R4 4 0  
       6 [-]: RETURN R0 0  


; Name:            
; Defined at line: 2290
; #Upvalues:       0
; #Parameters:     0
; Is_vararg:       0
; Max Stack Size:  1

       0 [-]: LOADB R0 1   
       1 [-]: RETURN R0 1  


; Name:            
; Defined at line: 2294
; #Upvalues:       1
; #Parameters:     1
; Is_vararg:       0
; Max Stack Size:  5

       0 [-]: GETUPVAL R3 0
       1 [-]: GETTABLEKS R2 R3 K0 ["Grid"]
       2 [-]: FASTCALL1 62 R2 L0
       3 [-]: GETIMPORT R1 2 [nil]
       4 [-]: CALL R1 1 1  
L 0:   5 [-]: JUMPIF R1 L2 
       6 [-]: JUMPXEQKN R0 K3 L1 NOT [20]
       7 [-]: GETUPVAL R3 0
       8 [-]: GETTABLEKS R2 R3 K0 ["Grid"]
       9 [-]: GETTABLEKS R1 R2 K4 ["mOnFocusedCallback"]
      10 [-]: GETUPVAL R4 0
      11 [-]: GETTABLEKS R3 R4 K0 ["Grid"]
      12 [-]: GETTABLEKS R2 R3 K5 ["mExtraReward"]
      13 [-]: CALL R1 1 0  
      14 [-]: RETURN R0 0  
L 1:  15 [-]: GETUPVAL R2 0
      16 [-]: GETTABLEKS R1 R2 K0 ["Grid"]
      17 [-]: MOVE R3 R0   
      18 [-]: NAMECALL R1 R1 K6 [0xDF42446E]
      19 [-]: CALL R1 2 0  
L 2:  20 [-]: RETURN R0 0  


; Name:            
; Defined at line: 2304
; #Upvalues:       1
; #Parameters:     1
; Is_vararg:       0
; Max Stack Size:  5

       0 [-]: GETUPVAL R3 0
       1 [-]: GETTABLEKS R2 R3 K0 ["Grid"]
       2 [-]: FASTCALL1 62 R2 L0
       3 [-]: GETIMPORT R1 2 [nil]
       4 [-]: CALL R1 1 1  
L 0:   5 [-]: JUMPIF R1 L2 
       6 [-]: JUMPXEQKN R0 K3 L1 NOT [20]
       7 [-]: GETUPVAL R3 0
       8 [-]: GETTABLEKS R2 R3 K0 ["Grid"]
       9 [-]: GETTABLEKS R1 R2 K4 ["mOnUnfocusedCallback"]
      10 [-]: GETUPVAL R4 0
      11 [-]: GETTABLEKS R3 R4 K0 ["Grid"]
      12 [-]: GETTABLEKS R2 R3 K5 ["mExtraReward"]
      13 [-]: CALL R1 1 0  
      14 [-]: RETURN R0 0  
L 1:  15 [-]: GETUPVAL R2 0
      16 [-]: GETTABLEKS R1 R2 K0 ["Grid"]
      17 [-]: MOVE R3 R0   
      18 [-]: NAMECALL R1 R1 K6 [0xBCE5A201]
      19 [-]: CALL R1 2 0  
L 2:  20 [-]: RETURN R0 0  


; Name:            
; Defined at line: 2314
; #Upvalues:       3
; #Parameters:     1
; Is_vararg:       0
; Max Stack Size:  5

       0 [-]: GETUPVAL R1 0
       1 [-]: JUMPIF R1 L0 
       2 [-]: GETUPVAL R1 1
       3 [-]: JUMPXEQKNIL R1 L1 NOT
L 0:   4 [-]: RETURN R0 0  
L 1:   5 [-]: GETUPVAL R2 2
       6 [-]: GETTABLEKS R1 R2 K0 [0x659D451F]
       7 [-]: GETIMPORT R3 2 [nil]
       8 [-]: GETTABLEKS R2 R3 K3 ["UISound_Select"]
       9 [-]: CALL R1 1 0  
      10 [-]: GETUPVAL R1 1
      11 [-]: GETIMPORT R3 5 [nil]
      12 [-]: MOVE R4 R0   
      13 [-]: CALL R3 1 -1 
      14 [-]: NAMECALL R1 R1 K6 [0x070DAA5A]
      15 [-]: CALL R1 -1 0 
      16 [-]: RETURN R0 0  


; Name:            
; Defined at line: 2322
; #Upvalues:       1
; #Parameters:     1
; Is_vararg:       0
; Max Stack Size:  5

       0 [-]: GETUPVAL R1 0
       1 [-]: JUMPXEQKNIL R1 L0 NOT
       2 [-]: RETURN R0 0  
L 0:   3 [-]: GETUPVAL R1 0
       4 [-]: GETIMPORT R3 1 [nil]
       5 [-]: MOVE R4 R0   
       6 [-]: CALL R3 1 -1 
       7 [-]: NAMECALL R1 R1 K2 [0xDF42446E]
       8 [-]: CALL R1 -1 0 
       9 [-]: RETURN R0 0  


; Name:            
; Defined at line: 2330
; #Upvalues:       1
; #Parameters:     1
; Is_vararg:       0
; Max Stack Size:  5

       0 [-]: GETUPVAL R1 0
       1 [-]: JUMPXEQKNIL R1 L0 NOT
       2 [-]: RETURN R0 0  
L 0:   3 [-]: GETUPVAL R1 0
       4 [-]: GETIMPORT R3 1 [nil]
       5 [-]: MOVE R4 R0   
       6 [-]: CALL R3 1 -1 
       7 [-]: NAMECALL R1 R1 K2 [0xBCE5A201]
       8 [-]: CALL R1 -1 0 
       9 [-]: RETURN R0 0  


; Name:            
; Defined at line: 2338
; #Upvalues:       1
; #Parameters:     1
; Is_vararg:       0
; Max Stack Size:  8

       0 [-]: GETIMPORT R1 2 [nil]
       1 [-]: MOVE R2 R0   
       2 [-]: LOADK R3 K3 [".AbilityList."]
       3 [-]: CALL R1 2 1  
       4 [-]: JUMPXEQKNIL R1 L1
       5 [-]: MOVE R3 R0   
       6 [-]: LOADN R4 1   
       7 [-]: SUBK R5 R1 K4 [1]
       8 [-]: FASTCALL 45 L0
       9 [-]: GETIMPORT R2 6 [nil]
      10 [-]: CALL R2 3 1  
L 0:  11 [-]: GETIMPORT R3 8 [nil]
      12 [-]: GETIMPORT R4 10 [nil]
      13 [-]: MOVE R6 R2   
      14 [-]: LOADK R7 K11 ["Id"]
      15 [-]: NAMECALL R4 R4 K12 [0x5B638CCE]
      16 [-]: CALL R4 3 -1 
      17 [-]: CALL R3 -1 1 
      18 [-]: GETUPVAL R4 0
      19 [-]: MOVE R6 R3   
      20 [-]: NAMECALL R4 R4 K13 [0xCA30DFB6]
      21 [-]: CALL R4 2 -1 
      22 [-]: RETURN R4 -1 
L 1:  23 [-]: RETURN R0 0  


; Name:            
; Defined at line: 2347
; #Upvalues:       2
; #Parameters:     2
; Is_vararg:       0
; Max Stack Size:  7

       0 [-]: GETUPVAL R2 0
       1 [-]: JUMPIFNOT R2 L0
       2 [-]: RETURN R0 0  
L 0:   3 [-]: GETUPVAL R2 1
       4 [-]: MOVE R3 R1   
       5 [-]: CALL R2 1 1  
       6 [-]: FASTCALL1 62 R2 L1
       7 [-]: MOVE R4 R2   
       8 [-]: GETIMPORT R3 1 [nil]
       9 [-]: CALL R3 1 1  
L 1:  10 [-]: JUMPIF R3 L2 
      11 [-]: GETTABLEKS R3 R2 K2 ["mAbilityList"]
      12 [-]: GETIMPORT R5 4 [nil]
      13 [-]: MOVE R6 R0   
      14 [-]: CALL R5 1 -1 
      15 [-]: NAMECALL R3 R3 K5 [0xDF42446E]
      16 [-]: CALL R3 -1 0 
L 2:  17 [-]: RETURN R0 0  


; Name:            
; Defined at line: 2358
; #Upvalues:       2
; #Parameters:     2
; Is_vararg:       0
; Max Stack Size:  7

       0 [-]: GETUPVAL R2 0
       1 [-]: JUMPIFNOT R2 L0
       2 [-]: RETURN R0 0  
L 0:   3 [-]: GETUPVAL R2 1
       4 [-]: MOVE R3 R1   
       5 [-]: CALL R2 1 1  
       6 [-]: FASTCALL1 62 R2 L1
       7 [-]: MOVE R4 R2   
       8 [-]: GETIMPORT R3 1 [nil]
       9 [-]: CALL R3 1 1  
L 1:  10 [-]: JUMPIF R3 L2 
      11 [-]: GETTABLEKS R3 R2 K2 ["mAbilityList"]
      12 [-]: GETIMPORT R5 4 [nil]
      13 [-]: MOVE R6 R0   
      14 [-]: CALL R5 1 -1 
      15 [-]: NAMECALL R3 R3 K5 [0xBCE5A201]
      16 [-]: CALL R3 -1 0 
L 2:  17 [-]: RETURN R0 0  


; Name:            
; Defined at line: 2369
; #Upvalues:       1
; #Parameters:     1
; Is_vararg:       0
; Max Stack Size:  8

       0 [-]: GETIMPORT R1 2 [nil]
       1 [-]: MOVE R2 R0   
       2 [-]: LOADK R3 K3 [".EvoList."]
       3 [-]: CALL R1 2 1  
       4 [-]: JUMPXEQKNIL R1 L1
       5 [-]: MOVE R3 R0   
       6 [-]: LOADN R4 1   
       7 [-]: SUBK R5 R1 K4 [1]
       8 [-]: FASTCALL 45 L0
       9 [-]: GETIMPORT R2 6 [nil]
      10 [-]: CALL R2 3 1  
L 0:  11 [-]: GETIMPORT R3 8 [nil]
      12 [-]: GETIMPORT R4 10 [nil]
      13 [-]: MOVE R6 R2   
      14 [-]: LOADK R7 K11 ["Id"]
      15 [-]: NAMECALL R4 R4 K12 [0x5B638CCE]
      16 [-]: CALL R4 3 -1 
      17 [-]: CALL R3 -1 1 
      18 [-]: GETUPVAL R4 0
      19 [-]: MOVE R6 R3   
      20 [-]: NAMECALL R4 R4 K13 [0xCA30DFB6]
      21 [-]: CALL R4 2 -1 
      22 [-]: RETURN R4 -1 
L 1:  23 [-]: RETURN R0 0  


; Name:            
; Defined at line: 2378
; #Upvalues:       2
; #Parameters:     2
; Is_vararg:       0
; Max Stack Size:  7

       0 [-]: GETUPVAL R2 0
       1 [-]: JUMPIFNOT R2 L0
       2 [-]: RETURN R0 0  
L 0:   3 [-]: GETUPVAL R2 1
       4 [-]: MOVE R3 R1   
       5 [-]: CALL R2 1 1  
       6 [-]: FASTCALL1 62 R2 L1
       7 [-]: MOVE R4 R2   
       8 [-]: GETIMPORT R3 1 [nil]
       9 [-]: CALL R3 1 1  
L 1:  10 [-]: JUMPIF R3 L2 
      11 [-]: GETTABLEKS R3 R2 K2 ["mEvoList"]
      12 [-]: GETIMPORT R5 4 [nil]
      13 [-]: MOVE R6 R0   
      14 [-]: CALL R5 1 -1 
      15 [-]: NAMECALL R3 R3 K5 [0xDF42446E]
      16 [-]: CALL R3 -1 0 
L 2:  17 [-]: RETURN R0 0  


; Name:            
; Defined at line: 2389
; #Upvalues:       2
; #Parameters:     2
; Is_vararg:       0
; Max Stack Size:  7

       0 [-]: GETUPVAL R2 0
       1 [-]: JUMPIFNOT R2 L0
       2 [-]: RETURN R0 0  
L 0:   3 [-]: GETUPVAL R2 1
       4 [-]: MOVE R3 R1   
       5 [-]: CALL R2 1 1  
       6 [-]: FASTCALL1 62 R2 L1
       7 [-]: MOVE R4 R2   
       8 [-]: GETIMPORT R3 1 [nil]
       9 [-]: CALL R3 1 1  
L 1:  10 [-]: JUMPIF R3 L2 
      11 [-]: GETTABLEKS R3 R2 K2 ["mEvoList"]
      12 [-]: GETIMPORT R5 4 [nil]
      13 [-]: MOVE R6 R0   
      14 [-]: CALL R5 1 -1 
      15 [-]: NAMECALL R3 R3 K5 [0xBCE5A201]
      16 [-]: CALL R3 -1 0 
L 2:  17 [-]: RETURN R0 0  


; Name:            
; Defined at line: 2400
; #Upvalues:       2
; #Parameters:     2
; Is_vararg:       0
; Max Stack Size:  12

       0 [-]: LOADK R3 K0 ["RewardPanel.ExtraReward."]
       1 [-]: GETUPVAL R5 0
       2 [-]: GETTABLEKS R4 R5 K1 [0x06D055F9]
       3 [-]: JUMPXEQKN R0 K2 L0 [-1]
       4 [-]: LOADB R5 0 +1
L 0:   5 [-]: LOADB R5 1   
L 1:   6 [-]: LOADK R6 K3 ["LeftArrow"]
       7 [-]: LOADK R7 K4 ["RightArrow"]
       8 [-]: CALL R4 3 1  
       9 [-]: CONCAT R2 R3 R4
      10 [-]: GETIMPORT R3 6 [nil]
      11 [-]: MOVE R5 R2   
      12 [-]: LOADN R6 9   
      13 [-]: GETUPVAL R8 0
      14 [-]: GETTABLEKS R7 R8 K1 [0x06D055F9]
      15 [-]: MOVE R8 R1   
      16 [-]: GETUPVAL R10 1
      17 [-]: GETTABLEKS R9 R10 K7 ["FloatingContentHighlight"]
      18 [-]: GETUPVAL R11 1
      19 [-]: GETTABLEKS R10 R11 K8 ["FloatingContent"]
      20 [-]: CALL R7 3 -1 
      21 [-]: NAMECALL R3 R3 K9 [0x67BC869F]
      22 [-]: CALL R3 -1 0 
      23 [-]: RETURN R0 0  


; Name:            
; Defined at line: 2405
; #Upvalues:       2
; #Parameters:     1
; Is_vararg:       0
; Max Stack Size:  4

       0 [-]: GETUPVAL R2 0
       1 [-]: GETTABLEKS R1 R2 K0 [0x659D451F]
       2 [-]: GETIMPORT R3 2 [nil]
       3 [-]: GETTABLEKS R2 R3 K3 ["UISound_Focus"]
       4 [-]: CALL R1 1 0  
       5 [-]: GETUPVAL R1 1
       6 [-]: MOVE R2 R0   
       7 [-]: LOADB R3 1   
       8 [-]: CALL R1 2 0  
       9 [-]: RETURN R0 0  


; Name:            
; Defined at line: 2411
; #Upvalues:       1
; #Parameters:     1
; Is_vararg:       0
; Max Stack Size:  4

       0 [-]: GETUPVAL R1 0
       1 [-]: MOVE R2 R0   
       2 [-]: LOADB R3 0   
       3 [-]: CALL R1 2 0  
       4 [-]: RETURN R0 0  


; Name:            
; Defined at line: 2415
; #Upvalues:       2
; #Parameters:     1
; Is_vararg:       0
; Max Stack Size:  5

       0 [-]: GETUPVAL R3 0
       1 [-]: GETTABLEKS R2 R3 K0 ["Grid"]
       2 [-]: FASTCALL1 62 R2 L0
       3 [-]: GETIMPORT R1 2 [nil]
       4 [-]: CALL R1 1 1  
L 0:   5 [-]: JUMPIF R1 L2 
       6 [-]: GETUPVAL R4 0
       7 [-]: GETTABLEKS R3 R4 K0 ["Grid"]
       8 [-]: GETTABLEKS R2 R3 K3 ["mExtraReward"]
       9 [-]: FASTCALL1 62 R2 L1
      10 [-]: GETIMPORT R1 2 [nil]
      11 [-]: CALL R1 1 1  
L 1:  12 [-]: JUMPIF R1 L2 
      13 [-]: GETUPVAL R2 1
      14 [-]: GETTABLEKS R1 R2 K4 [0x659D451F]
      15 [-]: GETIMPORT R3 6 [nil]
      16 [-]: GETTABLEKS R2 R3 K7 ["UISound_Select"]
      17 [-]: CALL R1 1 0  
      18 [-]: GETUPVAL R1 0
      19 [-]: LOADN R2 10  
      20 [-]: SETTABLEKS R2 R1 K8 ["IconCycleTimer"]
      21 [-]: GETUPVAL R3 0
      22 [-]: GETTABLEKS R2 R3 K0 ["Grid"]
      23 [-]: GETTABLEKS R1 R2 K9 ["CycleReward"]
      24 [-]: GETUPVAL R4 0
      25 [-]: GETTABLEKS R3 R4 K0 ["Grid"]
      26 [-]: GETTABLEKS R2 R3 K3 ["mExtraReward"]
      27 [-]: MOVE R3 R0   
      28 [-]: LOADB R4 1   
      29 [-]: CALL R1 3 0  
L 2:  30 [-]: RETURN R0 0  


; Name:            
; Defined at line: 2423
; #Upvalues:       1
; #Parameters:     1
; Is_vararg:       0
; Max Stack Size:  3

       0 [-]: GETIMPORT R1 1 [nil]
       1 [-]: MOVE R2 R0   
       2 [-]: CALL R1 1 1  
       3 [-]: LOADN R2 4   
       4 [-]: JUMPIFNOTEQ R1 R2 L0
       5 [-]: GETUPVAL R1 0
       6 [-]: CALL R1 0 0  
L 0:   7 [-]: RETURN R0 0  


; Name:            
; Defined at line: 2429
; #Upvalues:       6
; #Parameters:     0
; Is_vararg:       0
; Max Stack Size:  9

       0 [-]: GETUPVAL R0 0
       1 [-]: JUMPIF R0 L0 
       2 [-]: GETUPVAL R0 1
       3 [-]: JUMPIFNOT R0 L1
L 0:   4 [-]: RETURN R0 0  
L 1:   5 [-]: GETUPVAL R0 2
       6 [-]: JUMPIFNOT R0 L2
       7 [-]: GETIMPORT R0 2 [nil]
       8 [-]: CALL R0 0 1  
       9 [-]: LOADN R1 1   
      10 [-]: SETTABLEKS R1 R0 K3 ["dialogType"]
      11 [-]: GETIMPORT R1 5 [nil]
      12 [-]: LOADK R4 K6 ["/Lotus/Language/Duviri/"]
      13 [-]: GETUPVAL R6 3
      14 [-]: GETTABLEKS R5 R6 K7 [0x06D055F9]
      15 [-]: GETUPVAL R6 4
      16 [-]: LOADK R7 K8 ["EndlessSetupCancelWeeklyHardChoice"]
      17 [-]: LOADK R8 K9 ["EndlessSetupCancelWeeklyChoice"]
      18 [-]: CALL R5 3 1  
      19 [-]: CONCAT R3 R4 R5
      20 [-]: LOADB R4 0   
      21 [-]: NAMECALL R1 R1 K10 [0x42B04007]
      22 [-]: CALL R1 3 1  
      23 [-]: SETTABLEKS R1 R0 K11 ["locString"]
      24 [-]: LOADK R1 K12 ["/Lotus/Language/Menu/OmegaLimit_Cancel"]
      25 [-]: SETTABLEKS R1 R0 K13 ["firstString"]
      26 [-]: LOADK R1 K14 ["/Lotus/Language/Menu/NavBar_Cancel"]
      27 [-]: SETTABLEKS R1 R0 K15 ["secondString"]
      28 [-]: LOADK R3 K16 ["OnFrameSelectionBackoutConfirm"]
      29 [-]: NAMECALL R1 R0 K17 [0xE6CCC5B9]
      30 [-]: CALL R1 2 0  
      31 [-]: GETUPVAL R2 3
      32 [-]: GETTABLEKS R1 R2 K18 [0xE99B84E7]
      33 [-]: MOVE R2 R0   
      34 [-]: CALL R1 1 0  
      35 [-]: RETURN R0 0  
L 2:  36 [-]: GETUPVAL R0 5
      37 [-]: CALL R0 0 0  
      38 [-]: RETURN R0 0  


; Name:            
; Defined at line: 2447
; #Upvalues:       1
; #Parameters:     1
; Is_vararg:       0
; Max Stack Size:  1

       0 [-]: SETUPVAL R0 0
       1 [-]: RETURN R0 0  



