; Name:            
; Defined at line: 1
; #Upvalues:       0
; #Parameters:     0
; Is_vararg:       1
; Max Stack Size:  62

       1 [-]: GETIMPORT R0 1; var0 = 0x2D0FAD09
       2 [-]: LOADK R1 K2  ; var1 = "EE.Interface.Utilities"
       3 [-]: CALL R0 2 2  ; var0 = var0(var1)
       4 [-]: GETIMPORT R1 1; var1 = 0x2D0FAD09
       5 [-]: LOADK R2 K3  ; var2 = "Lotus.Interface.LotusUtilities"
       6 [-]: CALL R1 2 2  ; var1 = var1(var2)
       7 [-]: LOADB R2 1   ; var2 = true
       8 [-]: LOADNIL R3   ; var3 = nil
       9 [-]: LOADNIL R4   ; var4 = nil
      10 [-]: LOADNIL R5   ; var5 = nil
      11 [-]: NEWTABLE R6 0 6; var6 = {}
      12 [-]: LOADN R7 0   ; var7 = 0
      13 [-]: LOADNIL R8   ; var8 = nil
      14 [-]: NEWTABLE R9 0 0; var9 = {}
      15 [-]: NEWTABLE R10 0 3; var10 = {}
      16 [-]: LOADN R11 0  ; var11 = 0
      17 [-]: LOADB R12 0  ; var12 = false
      18 [-]: LOADB R13 0  ; var13 = false
      19 [-]: GETIMPORT R14 5; var14 = 0x78CA68A2
      20 [-]: LOADN R15 0  ; var15 = 0
      21 [-]: LOADK R16 K6 ; var16 = 0.15000000596046448
      22 [-]: CALL R14 3 2 ; var14 = var14(var15, var16)
      23 [-]: GETIMPORT R15 5; var15 = 0x78CA68A2
      24 [-]: LOADN R16 0  ; var16 = 0
      25 [-]: LOADK R17 K6 ; var17 = 0.15000000596046448
      26 [-]: CALL R15 3 2 ; var15 = var15(var16, var17)
      27 [-]: GETIMPORT R16 5; var16 = 0x78CA68A2
      28 [-]: LOADN R17 0  ; var17 = 0
      29 [-]: LOADK R18 K7 ; var18 = 0.64999997615814209
      30 [-]: CALL R16 3 2 ; var16 = var16(var17, var18)
      31 [-]: GETIMPORT R17 5; var17 = 0x78CA68A2
      32 [-]: LOADN R18 0  ; var18 = 0
      33 [-]: LOADK R19 K7 ; var19 = 0.64999997615814209
      34 [-]: CALL R17 3 2 ; var17 = var17(var18, var19)
      35 [-]: LOADNIL R18  ; var18 = nil
      36 [-]: LOADB R19 0  ; var19 = false
      37 [-]: LOADNIL R20  ; var20 = nil
      38 [-]: LOADNIL R21  ; var21 = nil
      39 [-]: LOADNIL R22  ; var22 = nil
      40 [-]: LOADN R23 0  ; var23 = 0
      41 [-]: LOADNIL R24  ; var24 = nil
      42 [-]: DUPTABLE R25 25; 
      43 [-]: LOADN R26 1  ; var26 = 1
      44 [-]: SETTABLEKS R26 R25 K8; var26["ANGRY"] = var25
      45 [-]: LOADN R26 2  ; var26 = 2
      46 [-]: SETTABLEKS R26 R25 K9; var26["BORED"] = var25
      47 [-]: LOADN R26 3  ; var26 = 3
      48 [-]: SETTABLEKS R26 R25 K10; var26["CONFUSED"] = var25
      49 [-]: LOADN R26 4  ; var26 = 4
      50 [-]: SETTABLEKS R26 R25 K11; var26["DISGUSTED"] = var25
      51 [-]: LOADN R26 5  ; var26 = 5
      52 [-]: SETTABLEKS R26 R25 K12; var26["EMBARRASSED"] = var25
      53 [-]: LOADN R26 6  ; var26 = 6
      54 [-]: SETTABLEKS R26 R25 K13; var26["EXCITED"] = var25
      55 [-]: LOADN R26 7  ; var26 = 7
      56 [-]: SETTABLEKS R26 R25 K14; var26["GRUMPY"] = var25
      57 [-]: LOADN R26 8  ; var26 = 8
      58 [-]: SETTABLEKS R26 R25 K15; var26["HAPPY"] = var25
      59 [-]: LOADN R26 9  ; var26 = 9
      60 [-]: SETTABLEKS R26 R25 K16; var26["HUNGRY"] = var25
      61 [-]: LOADN R26 10 ; var26 = 10
      62 [-]: SETTABLEKS R26 R25 K17; var26["NERVOUS"] = var25
      63 [-]: LOADN R26 11 ; var26 = 11
      64 [-]: SETTABLEKS R26 R25 K18; var26["PROUD"] = var25
      65 [-]: LOADN R26 12 ; var26 = 12
      66 [-]: SETTABLEKS R26 R25 K19; var26["SAD"] = var25
      67 [-]: LOADN R26 13 ; var26 = 13
      68 [-]: SETTABLEKS R26 R25 K20; var26["SCARED"] = var25
      69 [-]: LOADN R26 14 ; var26 = 14
      70 [-]: SETTABLEKS R26 R25 K21; var26["SHY"] = var25
      71 [-]: LOADN R26 15 ; var26 = 15
      72 [-]: SETTABLEKS R26 R25 K22; var26["SICK"] = var25
      73 [-]: LOADN R26 16 ; var26 = 16
      74 [-]: SETTABLEKS R26 R25 K23; var26["SURPRISED"] = var25
      75 [-]: LOADN R26 17 ; var26 = 17
      76 [-]: SETTABLEKS R26 R25 K24; var26["TIRED"] = var25
      77 [-]: NEWTABLE R26 0 4; var26 = {}
      78 [-]: LOADN R27 2  ; var27 = 2
      79 [-]: LOADN R28 1  ; var28 = 1
      80 [-]: LOADN R29 0  ; var29 = 0
      81 [-]: LOADN R30 3  ; var30 = 3
      82 [-]: SETLIST R26 R27 4 [1]; var26[1] = var27; var26[2] = var28; var26[3] = var29; var26[4] = var30; var26[5] = var31; 
      83 [-]: NEWTABLE R27 0 4; var27 = {}
      84 [-]: LOADN R28 0  ; var28 = 0
      85 [-]: LOADN R29 1  ; var29 = 1
      86 [-]: LOADN R30 2  ; var30 = 2
      87 [-]: LOADN R31 3  ; var31 = 3
      88 [-]: SETLIST R27 R28 4 [1]; var27[1] = var28; var27[2] = var29; var27[3] = var30; var27[4] = var31; var27[5] = var32; 
      89 [-]: LOADNIL R28  ; var28 = nil
      90 [-]: NEWCLOSURE R29 P0; 
      91 [-]: CAPTURE REF R2; 
      92 [-]: SETGLOBAL R29 K26; "IsInputBlocked" = var29
      93 [-]: DUPCLOSURE R29 K27; 
      94 [-]: DUPCLOSURE R30 K28; 
      95 [-]: NEWCLOSURE R31 P3; 
      96 [-]: CAPTURE REF R2; 
      97 [-]: CAPTURE VAL R0; 
      98 [-]: CAPTURE VAL R30; 
      99 [-]: NEWCLOSURE R32 P4; 
     100 [-]: CAPTURE VAL R1; 
     101 [-]: CAPTURE REF R4; 
     102 [-]: CAPTURE VAL R0; 
     103 [-]: NEWCLOSURE R33 P5; 
     104 [-]: CAPTURE REF R5; 
     105 [-]: CAPTURE VAL R0; 
     106 [-]: CAPTURE REF R19; 
     107 [-]: CAPTURE REF R22; 
     108 [-]: NEWCLOSURE R34 P6; 
     109 [-]: CAPTURE VAL R0; 
     110 [-]: CAPTURE REF R19; 
     111 [-]: CAPTURE VAL R1; 
     112 [-]: CAPTURE REF R5; 
     113 [-]: NEWCLOSURE R35 P7; 
     114 [-]: CAPTURE REF R11; 
     115 [-]: DUPCLOSURE R36 K29; 
     116 [-]: CAPTURE VAL R9; 
     117 [-]: CAPTURE VAL R25; 
     118 [-]: DUPCLOSURE R37 K30; 
     119 [-]: CAPTURE VAL R0; 
     120 [-]: NEWCLOSURE R38 P10; 
     121 [-]: CAPTURE REF R10; 
     122 [-]: CAPTURE VAL R0; 
     123 [-]: CAPTURE REF R5; 
     124 [-]: CAPTURE VAL R37; 
     125 [-]: DUPCLOSURE R39 K31; 
     126 [-]: CAPTURE VAL R0; 
     127 [-]: DUPCLOSURE R40 K32; 
     128 [-]: DUPCLOSURE R41 K33; 
     129 [-]: CAPTURE VAL R40; 
     130 [-]: DUPCLOSURE R42 K34; 
     131 [-]: CAPTURE VAL R40; 
     132 [-]: DUPCLOSURE R43 K35; 
     133 [-]: CAPTURE VAL R40; 
     134 [-]: DUPCLOSURE R44 K36; 
     135 [-]: CAPTURE VAL R40; 
     136 [-]: DUPCLOSURE R45 K37; 
     137 [-]: CAPTURE VAL R40; 
     138 [-]: DUPCLOSURE R46 K38; 
     139 [-]: CAPTURE VAL R40; 
     140 [-]: DUPCLOSURE R47 K39; 
     141 [-]: CAPTURE VAL R40; 
     142 [-]: CAPTURE VAL R0; 
     143 [-]: DUPCLOSURE R48 K40; 
     144 [-]: CAPTURE VAL R40; 
     145 [-]: CAPTURE VAL R0; 
     146 [-]: DUPCLOSURE R49 K41; 
     147 [-]: CAPTURE VAL R40; 
     148 [-]: CAPTURE VAL R0; 
     149 [-]: NEWCLOSURE R50 P22; 
     150 [-]: CAPTURE REF R7; 
     151 [-]: CAPTURE REF R6; 
     152 [-]: CAPTURE VAL R31; 
     153 [-]: CAPTURE VAL R35; 
     154 [-]: CAPTURE REF R13; 
     155 [-]: CAPTURE REF R8; 
     156 [-]: CAPTURE VAL R0; 
     157 [-]: CAPTURE VAL R9; 
     158 [-]: CAPTURE REF R10; 
     159 [-]: CAPTURE VAL R41; 
     160 [-]: CAPTURE VAL R14; 
     161 [-]: CAPTURE VAL R15; 
     162 [-]: CAPTURE REF R22; 
     163 [-]: CAPTURE REF R18; 
     164 [-]: CAPTURE VAL R33; 
     165 [-]: CAPTURE REF R5; 
     166 [-]: CAPTURE VAL R39; 
     167 [-]: CAPTURE VAL R1; 
     168 [-]: CAPTURE REF R12; 
     169 [-]: CAPTURE REF R2; 
     170 [-]: CAPTURE REF R23; 
     171 [-]: CAPTURE REF R28; 
     172 [-]: CAPTURE VAL R29; 
     173 [-]: DUPCLOSURE R51 K42; 
     174 [-]: SETGLOBAL R51 K43; "Shutdown" = var51
     175 [-]: NEWCLOSURE R51 P24; 
     176 [-]: CAPTURE REF R3; 
     177 [-]: CAPTURE REF R19; 
     178 [-]: CAPTURE REF R22; 
     179 [-]: CAPTURE REF R5; 
     180 [-]: CAPTURE REF R18; 
     181 [-]: CAPTURE REF R4; 
     182 [-]: CAPTURE VAL R9; 
     183 [-]: CAPTURE VAL R25; 
     184 [-]: CAPTURE VAL R47; 
     185 [-]: CAPTURE VAL R46; 
     186 [-]: CAPTURE VAL R44; 
     187 [-]: CAPTURE VAL R45; 
     188 [-]: CAPTURE VAL R42; 
     189 [-]: CAPTURE VAL R49; 
     190 [-]: CAPTURE VAL R43; 
     191 [-]: CAPTURE VAL R48; 
     192 [-]: CAPTURE VAL R0; 
     193 [-]: CAPTURE REF R10; 
     194 [-]: CAPTURE VAL R41; 
     195 [-]: CAPTURE VAL R34; 
     196 [-]: CAPTURE VAL R33; 
     197 [-]: CAPTURE VAL R39; 
     198 [-]: CAPTURE REF R2; 
     199 [-]: CAPTURE REF R28; 
     200 [-]: CAPTURE VAL R29; 
     201 [-]: CAPTURE REF R6; 
     202 [-]: CAPTURE REF R7; 
     203 [-]: CAPTURE VAL R50; 
     204 [-]: CAPTURE VAL R32; 
     205 [-]: SETGLOBAL R51 K44; "Initialize" = var51
     206 [-]: NEWCLOSURE R51 P25; 
     207 [-]: CAPTURE REF R5; 
     208 [-]: CAPTURE REF R12; 
     209 [-]: CAPTURE VAL R14; 
     210 [-]: CAPTURE VAL R15; 
     211 [-]: CAPTURE REF R22; 
     212 [-]: CAPTURE REF R13; 
     213 [-]: CAPTURE REF R2; 
     214 [-]: CAPTURE VAL R26; 
     215 [-]: CAPTURE REF R23; 
     216 [-]: CAPTURE REF R10; 
     217 [-]: CAPTURE VAL R17; 
     218 [-]: CAPTURE VAL R16; 
     219 [-]: SETGLOBAL R51 K45; "Update" = var51
     220 [-]: DUPCLOSURE R51 K46; 
     221 [-]: CAPTURE VAL R32; 
     222 [-]: SETGLOBAL R51 K47; "onViewportSizeChanged" = var51
     223 [-]: NEWCLOSURE R51 P27; 
     224 [-]: CAPTURE REF R21; 
     225 [-]: CAPTURE REF R5; 
     226 [-]: CAPTURE REF R20; 
     227 [-]: CAPTURE VAL R0; 
     228 [-]: CAPTURE REF R10; 
     229 [-]: NEWCLOSURE R52 P28; 
     230 [-]: CAPTURE REF R21; 
     231 [-]: CAPTURE REF R5; 
     232 [-]: CAPTURE REF R20; 
     233 [-]: CAPTURE REF R10; 
     234 [-]: NEWCLOSURE R53 P29; 
     235 [-]: CAPTURE REF R2; 
     236 [-]: CAPTURE REF R13; 
     237 [-]: CAPTURE VAL R0; 
     238 [-]: CAPTURE REF R19; 
     239 [-]: CAPTURE VAL R51; 
     240 [-]: SETGLOBAL R53 K48; "CardRollOver" = var53
     241 [-]: NEWCLOSURE R53 P30; 
     242 [-]: CAPTURE REF R2; 
     243 [-]: CAPTURE REF R19; 
     244 [-]: CAPTURE VAL R52; 
     245 [-]: CAPTURE REF R13; 
     246 [-]: SETGLOBAL R53 K49; "CardRollOut" = var53
     247 [-]: NEWCLOSURE R53 P31; 
     248 [-]: CAPTURE VAL R0; 
     249 [-]: CAPTURE REF R5; 
     250 [-]: CAPTURE VAL R36; 
     251 [-]: CAPTURE REF R10; 
     252 [-]: CAPTURE VAL R30; 
     253 [-]: CAPTURE VAL R37; 
     254 [-]: NEWCLOSURE R54 P32; 
     255 [-]: CAPTURE REF R2; 
     256 [-]: CAPTURE REF R19; 
     257 [-]: CAPTURE VAL R53; 
     258 [-]: SETGLOBAL R54 K50; "CardSelected" = var54
     259 [-]: NEWCLOSURE R54 P33; 
     260 [-]: CAPTURE REF R2; 
     261 [-]: CAPTURE REF R19; 
     262 [-]: CAPTURE VAL R51; 
     263 [-]: CAPTURE VAL R0; 
     264 [-]: CAPTURE REF R10; 
     265 [-]: DUPCLOSURE R55 K51; 
     266 [-]: CAPTURE VAL R54; 
     267 [-]: SETGLOBAL R55 K52; "EmotionRollOver" = var55
     268 [-]: NEWCLOSURE R55 P35; 
     269 [-]: CAPTURE REF R2; 
     270 [-]: CAPTURE REF R19; 
     271 [-]: CAPTURE VAL R52; 
     272 [-]: CAPTURE REF R13; 
     273 [-]: CAPTURE REF R10; 
     274 [-]: DUPCLOSURE R56 K53; 
     275 [-]: CAPTURE VAL R55; 
     276 [-]: SETGLOBAL R56 K54; "EmotionRollOut" = var56
     277 [-]: NEWCLOSURE R56 P37; 
     278 [-]: CAPTURE REF R2; 
     279 [-]: CAPTURE REF R19; 
     280 [-]: CAPTURE VAL R53; 
     281 [-]: CAPTURE REF R10; 
     282 [-]: CAPTURE VAL R0; 
     283 [-]: CAPTURE REF R8; 
     284 [-]: CAPTURE REF R6; 
     285 [-]: CAPTURE REF R7; 
     286 [-]: CAPTURE VAL R1; 
     287 [-]: CAPTURE VAL R38; 
     288 [-]: CAPTURE REF R12; 
     289 [-]: CAPTURE REF R5; 
     290 [-]: CAPTURE VAL R37; 
     291 [-]: CAPTURE VAL R50; 
     292 [-]: CAPTURE REF R11; 
     293 [-]: CAPTURE REF R28; 
     294 [-]: DUPCLOSURE R57 K55; 
     295 [-]: CAPTURE VAL R56; 
     296 [-]: SETGLOBAL R57 K56; "EmotionSelected" = var57
     297 [-]: NEWCLOSURE R57 P39; 
     298 [-]: CAPTURE REF R2; 
     299 [-]: CAPTURE VAL R0; 
     300 [-]: CAPTURE REF R19; 
     301 [-]: CAPTURE VAL R27; 
     302 [-]: CAPTURE VAL R26; 
     303 [-]: CAPTURE VAL R56; 
     304 [-]: CAPTURE REF R10; 
     305 [-]: CAPTURE REF R23; 
     306 [-]: SETGLOBAL R57 K57; "onKeyDown_MENU_SELECT" = var57
     307 [-]: NEWCLOSURE R28 P40; 
     308 [-]: CAPTURE REF R2; 
     309 [-]: CAPTURE VAL R0; 
     310 [-]: CAPTURE REF R19; 
     311 [-]: CAPTURE VAL R27; 
     312 [-]: CAPTURE VAL R26; 
     313 [-]: CAPTURE REF R24; 
     314 [-]: CAPTURE REF R23; 
     315 [-]: CAPTURE REF R10; 
     316 [-]: CAPTURE VAL R55; 
     317 [-]: CAPTURE VAL R54; 
     318 [-]: NEWCLOSURE R57 P41; 
     319 [-]: CAPTURE REF R19; 
     320 [-]: CAPTURE REF R28; 
     321 [-]: DUPCLOSURE R58 K58; 
     322 [-]: CAPTURE VAL R57; 
     323 [-]: SETGLOBAL R58 K59; "onKeyDown_MENU_UP" = var58
     324 [-]: DUPCLOSURE R58 K60; 
     325 [-]: CAPTURE VAL R57; 
     326 [-]: SETGLOBAL R58 K61; "onKeyDown_MENU_UP_FROM_ANALOG" = var58
     327 [-]: NEWCLOSURE R58 P44; 
     328 [-]: CAPTURE REF R28; 
     329 [-]: DUPCLOSURE R59 K62; 
     330 [-]: CAPTURE VAL R58; 
     331 [-]: SETGLOBAL R59 K63; "onKeyDown_MENU_RIGHT" = var59
     332 [-]: DUPCLOSURE R59 K64; 
     333 [-]: CAPTURE VAL R58; 
     334 [-]: SETGLOBAL R59 K65; "onKeyDown_MENU_RIGHT_FROM_ANALOG" = var59
     335 [-]: NEWCLOSURE R59 P47; 
     336 [-]: CAPTURE REF R28; 
     337 [-]: DUPCLOSURE R60 K66; 
     338 [-]: CAPTURE VAL R59; 
     339 [-]: SETGLOBAL R60 K67; "onKeyDown_MENU_LEFT" = var60
     340 [-]: DUPCLOSURE R60 K68; 
     341 [-]: CAPTURE VAL R59; 
     342 [-]: SETGLOBAL R60 K69; "onKeyDown_MENU_LEFT_FROM_ANALOG" = var60
     343 [-]: NEWCLOSURE R60 P50; 
     344 [-]: CAPTURE REF R19; 
     345 [-]: CAPTURE REF R28; 
     346 [-]: DUPCLOSURE R61 K70; 
     347 [-]: CAPTURE VAL R60; 
     348 [-]: SETGLOBAL R61 K71; "onKeyDown_MENU_DOWN" = var61
     349 [-]: DUPCLOSURE R61 K72; 
     350 [-]: CAPTURE VAL R60; 
     351 [-]: SETGLOBAL R61 K73; "onKeyDown_MENU_DOWN_FROM_ANALOG" = var61
     352 [-]: CLOSEUPVALS R2; 
     353 [-]: RETURN R0 0  ; 


; Name:            
; Defined at line: 96
; #Upvalues:       1
; #Parameters:     0
; Is_vararg:       0
; Max Stack Size:  1

       0 [-]: GETUPVAL R0 0; var0 = upvalues[0]
       1 [-]: RETURN R0 1  ; 


; Name:            
; Defined at line: 100
; #Upvalues:       0
; #Parameters:     0
; Is_vararg:       0
; Max Stack Size:  6

       0 [-]: NEWTABLE R0 0 0; var0 = {}
       1 [-]: GETIMPORT R1 2; var1 = 0x34291F5C[0x1467D5F4]
       2 [-]: CALL R1 1 2  ; var1 = var1()
       3 [-]: JUMPIFNOT R1 L0; goto L0 if not var1
       4 [-]: DUPTABLE R3 5; 
       5 [-]: LOADK R4 K6  ; var4 = "/Lotus/Language/Menu/Select"
       6 [-]: SETTABLEKS R4 R3 K3; var4["Label"] = var3
       7 [-]: LOADK R4 K7  ; var4 = "MENU_SELECT"
       8 [-]: SETTABLEKS R4 R3 K4; var4["CallOut"] = var3
       9 [-]: FASTCALL2 52 R0 R3 L0; 
      10 [-]: MOVE R2 R0   ; var2 = var0
      11 [-]: GETIMPORT R1 10; var1 = 0x33BDD652[0x23D5322F]
      12 [-]: CALL R1 3 1  ; var1(var2, var3)
L 0:  13 [-]: GETIMPORT R1 13; var1 = _T["SetButtons"]
      14 [-]: GETIMPORT R2 15; var2 = 0xAE91E43B
      15 [-]: MOVE R3 R0   ; var3 = var0
      16 [-]: GETIMPORT R4 17; var4 = 0xCD0165A3
      17 [-]: LOADN R5 1   ; var5 = 1
      18 [-]: CALL R4 2 0  ; var4, ... = var4(var5)
      19 [-]: CALL R1 0 1  ; var1(var2, ...)
      20 [-]: RETURN R0 0  ; 


; Name:            
; Defined at line: 110
; #Upvalues:       0
; #Parameters:     0
; Is_vararg:       0
; Max Stack Size:  2

       0 [-]: GETIMPORT R0 1; var0 = 0xAE91E43B
       1 [-]: NAMECALL R0 R0 K2; var1 = var0; var0 = var0[0x32302B4A]
       2 [-]: CALL R0 2 1  ; var0(var1)
       3 [-]: RETURN R0 0  ; 


; Name:            
; Defined at line: 114
; #Upvalues:       3
; #Parameters:     1
; Is_vararg:       0
; Max Stack Size:  10

       0 [-]: LOADB R1 1   ; var1 = true
       1 [-]: SETUPVAL R1 0; upvalues[1] = var0
       2 [-]: GETUPVAL R2 1; var2 = upvalues[1]
       3 [-]: GETTABLEKS R1 R2 K0; var1 = var2[0x659D451F]
       4 [-]: GETIMPORT R2 2; var2 = 0xB8BF11E5
       5 [-]: CALL R1 2 1  ; var1(var2)
       6 [-]: GETIMPORT R1 4; var1 = 0x25312C9B
       7 [-]: GETIMPORT R2 6; var2 = 0xAE91E43B
       8 [-]: LOADK R3 K7  ; var3 = "_root"
       9 [-]: LOADN R4 2   ; var4 = 2
      10 [-]: NEWTABLE R5 0 2; var5 = {}
      11 [-]: LOADN R6 10  ; var6 = 10
      12 [-]: LOADN R7 4   ; var7 = 4
      13 [-]: SETLIST R5 R6 2 [1]; var5[1] = var6; var5[2] = var7; var5[3] = var8; 
      14 [-]: NEWTABLE R6 0 2; var6 = {}
      15 [-]: LOADN R7 0   ; var7 = 0
      16 [-]: LOADN R8 -15000; var8 = -15000
      17 [-]: SETLIST R6 R7 2 [1]; var6[1] = var7; var6[2] = var8; var6[3] = var9; 
      18 [-]: LOADK R7 K8  ; var7 = 0.25
      19 [-]: LOADN R8 0   ; var8 = 0
      20 [-]: MOVE R9 R0   ; var9 = var0
      21 [-]: CALL R1 9 1  ; var1(var2, var3, var4, var5, var6, var7, var8, var9)
      22 [-]: GETUPVAL R2 1; var2 = upvalues[1]
      23 [-]: GETTABLEKS R1 R2 K9; var1 = var2[0x4C232AFC]
      24 [-]: GETIMPORT R2 6; var2 = 0xAE91E43B
      25 [-]: LOADN R3 0   ; var3 = 0
      26 [-]: LOADK R4 K8  ; var4 = 0.25
      27 [-]: LOADN R5 0   ; var5 = 0
      28 [-]: GETUPVAL R6 2; var6 = upvalues[2]
      29 [-]: CALL R1 6 1  ; var1(var2, var3, var4, var5, var6)
      30 [-]: RETURN R0 0  ; 


; Name:            
; Defined at line: 122
; #Upvalues:       3
; #Parameters:     0
; Is_vararg:       0
; Max Stack Size:  7

       0 [-]: GETUPVAL R1 0; var1 = upvalues[0]
       1 [-]: GETTABLEKS R0 R1 K0; var0 = var1[0xDD3CFB64]
       2 [-]: GETIMPORT R1 2; var1 = 0xAE91E43B
       3 [-]: LOADK R2 K3  ; var2 = "Bluer"
       4 [-]: CALL R0 3 1  ; var0(var1, var2)
       5 [-]: GETUPVAL R1 1; var1 = upvalues[1]
       6 [-]: FASTCALL1 64 R1 L0; 
       7 [-]: GETIMPORT R0 5; var0 = 0x7B998233
       8 [-]: CALL R0 2 2  ; var0 = var0(var1)
L 0:   9 [-]: JUMPIF R0 L1 ; goto L1 if var0
      10 [-]: GETUPVAL R0 1; var0 = upvalues[1]
      11 [-]: GETIMPORT R2 2; var2 = 0xAE91E43B
      12 [-]: NAMECALL R2 R2 K6; var3 = var2; var2 = var2[0x6B837788]
      13 [-]: CALL R2 2 2  ; var2 = var2(var3)
      14 [-]: GETIMPORT R3 2; var3 = 0xAE91E43B
      15 [-]: NAMECALL R3 R3 K7; var4 = var3; var3 = var3[0xAF9FDA9F]
      16 [-]: CALL R3 2 0  ; var3, ... = var3(var4)
      17 [-]: NAMECALL R0 R0 K8; var1 = var0; var0 = var0[0xFAA69527]
      18 [-]: CALL R0 0 1  ; var0(var1, ...)
L 1:  19 [-]: GETUPVAL R1 2; var1 = upvalues[2]
      20 [-]: GETTABLEKS R0 R1 K9; var0 = var1[0x44537ADF]
      21 [-]: GETIMPORT R1 2; var1 = 0xAE91E43B
      22 [-]: CALL R0 2 3  ; var0, var1 = var0(var1)
      23 [-]: GETIMPORT R2 2; var2 = 0xAE91E43B
      24 [-]: LOADK R4 K10 ; var4 = "SmokeContainer"
      25 [-]: LOADN R5 12  ; var5 = 12
      26 [-]: MOVE R6 R0   ; var6 = var0
      27 [-]: NAMECALL R2 R2 K11; var3 = var2; var2 = var2[0x67BC869F]
      28 [-]: CALL R2 5 1  ; var2(var3, var4, var5, var6)
      29 [-]: RETURN R0 0  ; 


; Name:            
; Defined at line: 134
; #Upvalues:       4
; #Parameters:     4
; Is_vararg:       0
; Max Stack Size:  16

       0 [-]: JUMPXEQKNIL R2 L0 NOT; 
       1 [-]: LOADN R2 0   ; var2 = 0
L 0:   2 [-]: JUMPXEQKNIL R3 L1 NOT; 
       3 [-]: GETIMPORT R3 1; var3 = 0x1AA4578D
L 1:   4 [-]: GETUPVAL R4 0; var4 = upvalues[0]
       5 [-]: MOVE R6 R2   ; var6 = var2
       6 [-]: NEWCLOSURE R7 P0; 
       7 [-]: CAPTURE UPVAL U1; 
       8 [-]: CAPTURE REF R3; 
       9 [-]: NAMECALL R4 R4 K2; var5 = var4; var4 = var4[0xBD2E96EA]
      10 [-]: CALL R4 4 1  ; var4(var5, var6, var7)
      11 [-]: GETIMPORT R4 4; var4 = 0x25312C9B
      12 [-]: GETIMPORT R5 6; var5 = 0xAE91E43B
      13 [-]: MOVE R6 R0   ; var6 = var0
      14 [-]: LOADN R7 8   ; var7 = 8
      15 [-]: NEWTABLE R8 0 1; var8 = {}
      16 [-]: LOADN R9 1   ; var9 = 1
      17 [-]: SETLIST R8 R9 1 [1]; var8[1] = var9; var8[2] = var10; 
      18 [-]: NEWTABLE R9 0 1; var9 = {}
      19 [-]: GETUPVAL R11 1; var11 = upvalues[1]
      20 [-]: GETTABLEKS R10 R11 K7; var10 = var11[0x06D055F9]
      21 [-]: GETUPVAL R11 2; var11 = upvalues[2]
      22 [-]: GETIMPORT R14 6; var14 = 0xAE91E43B
      23 [-]: NAMECALL R14 R14 K10; var15 = var14; var14 = var14[0x2CC9D281]
      24 [-]: CALL R14 2 2 ; var14 = var14(var15)
      25 [-]: MULK R13 R14 K9; var13 = var14 * 0.5
      26 [-]: SUBK R12 R13 K8; var12 = var13 - 70
      27 [-]: GETUPVAL R13 3; var13 = upvalues[3]
      28 [-]: CALL R10 4 0 ; var10, ... = var10(var11, var12, var13)
      29 [-]: SETLIST R9 R10 -1 [1]; 
      30 [-]: LOADK R10 K11; var10 = 0.94999998807907104
      31 [-]: MOVE R11 R2  ; var11 = var2
      32 [-]: MOVE R12 R1  ; var12 = var1
      33 [-]: CALL R4 9 1  ; var4(var5, var6, var7, var8, var9, var10, var11, var12)
      34 [-]: CLOSEUPVALS R3; 
      35 [-]: RETURN R0 0  ; 


; Name:            
; Defined at line: 145
; #Upvalues:       4
; #Parameters:     1
; Is_vararg:       0
; Max Stack Size:  7

       0 [-]: GETUPVAL R2 0; var2 = upvalues[0]
       1 [-]: GETTABLEKS R1 R2 K0; var1 = var2[0x4C232AFC]
       2 [-]: GETIMPORT R2 2; var2 = 0xAE91E43B
       3 [-]: LOADN R3 1   ; var3 = 1
       4 [-]: LOADK R4 K3  ; var4 = 0.34999999403953552
       5 [-]: LOADK R5 K4  ; var5 = 0.15000000596046448
       6 [-]: NEWCLOSURE R6 P0; 
       7 [-]: CAPTURE UPVAL U1; 
       8 [-]: CAPTURE UPVAL U2; 
       9 [-]: CAPTURE UPVAL U3; 
      10 [-]: CAPTURE UPVAL U0; 
      11 [-]: CAPTURE VAL R0; 
      12 [-]: CALL R1 6 1  ; var1(var2, var3, var4, var5, var6)
      13 [-]: RETURN R0 0  ; 


; Name:            
; Defined at line: 159
; #Upvalues:       1
; #Parameters:     0
; Is_vararg:       0
; Max Stack Size:  4

       0 [-]: GETIMPORT R0 1; var0 = 0x3D106989
       1 [-]: LOADK R2 K2  ; var2 = "Errors "
       2 [-]: GETUPVAL R3 0; var3 = upvalues[0]
       3 [-]: CONCAT R1 R2 R3; var1 = var2 .. var3
       4 [-]: CALL R0 2 1  ; var0(var1)
       5 [-]: RETURN R0 0  ; 


; Name:            
; Defined at line: 163
; #Upvalues:       2
; #Parameters:     1
; Is_vararg:       0
; Max Stack Size:  9

       0 [-]: GETIMPORT R1 1; var1 = 0x3D106989
       1 [-]: LOADK R3 K2  ; var3 = "Selected "
       2 [-]: MOVE R4 R0   ; var4 = var0
       3 [-]: LOADK R5 K3  ; var5 = " > "
       4 [-]: GETUPVAL R8 0; var8 = upvalues[0]
       5 [-]: GETTABLE R7 R8 R0; var7 = var8[var0]
       6 [-]: GETTABLEKS R6 R7 K4; var6 = var7["Label"]
       7 [-]: CONCAT R2 R3 R6; var2 = var3 .. var6
       8 [-]: CALL R1 2 1  ; var1(var2)
       9 [-]: LOADNIL R1   ; var1 = nil
      10 [-]: GETIMPORT R2 6; var2 = 0xCFC01047
      11 [-]: GETUPVAL R3 1; var3 = upvalues[1]
      12 [-]: CALL R2 2 4  ; var2, var3, var4 = var2(var3)
      13 [-]: FORGPREP_NEXT R2 L1; 
L 0:  14 [-]: JUMPIFNOTEQ R6 R0 L1; goto L1 if var6 ~= var327982
      15 [-]: MOVE R1 R5   ; var1 = var5
L 1:  16 [-]: FORGLOOP R2 L0 2; 
      17 [-]: GETIMPORT R2 8; var2 = _T
      18 [-]: SETTABLEKS R1 R2 K9; var1["SelectedEmotion"] = var2
      19 [-]: RETURN R0 0  ; 


; Name:            
; Defined at line: 174
; #Upvalues:       1
; #Parameters:     2
; Is_vararg:       0
; Max Stack Size:  11

       0 [-]: GETIMPORT R2 1; var2 = 0xAE91E43B
       1 [-]: GETTABLEKS R4 R0 K2; var4 = var0["mClipName"]
       2 [-]: LOADN R5 61  ; var5 = 61
       3 [-]: LOADB R6 0   ; var6 = false
       4 [-]: NAMECALL R2 R2 K3; var3 = var2; var2 = var2[0xAADE900E]
       5 [-]: CALL R2 5 1  ; var2(var3, var4, var5, var6)
       6 [-]: LOADB R2 0   ; var2 = false
       7 [-]: SETTABLEKS R2 R0 K4; var2["mActive"] = var0
       8 [-]: GETIMPORT R2 6; var2 = 0x25312C9B
       9 [-]: GETIMPORT R3 1; var3 = 0xAE91E43B
      10 [-]: GETTABLEKS R4 R0 K2; var4 = var0["mClipName"]
      11 [-]: LOADN R5 2   ; var5 = 2
      12 [-]: NEWTABLE R6 0 1; var6 = {}
      13 [-]: LOADN R7 10  ; var7 = 10
      14 [-]: SETLIST R6 R7 1 [1]; var6[1] = var7; var6[2] = var8; 
      15 [-]: NEWTABLE R7 0 1; var7 = {}
      16 [-]: LOADN R8 0   ; var8 = 0
      17 [-]: SETLIST R7 R8 1 [1]; var7[1] = var8; var7[2] = var9; 
      18 [-]: LOADK R8 K7  ; var8 = 0.34999999403953552
      19 [-]: LOADN R9 0   ; var9 = 0
      20 [-]: MOVE R10 R1  ; var10 = var1
      21 [-]: CALL R2 9 1  ; var2(var3, var4, var5, var6, var7, var8, var9, var10)
      22 [-]: GETUPVAL R3 0; var3 = upvalues[0]
      23 [-]: GETTABLEKS R2 R3 K8; var2 = var3[0xF76783E5]
      24 [-]: GETIMPORT R3 1; var3 = 0xAE91E43B
      25 [-]: GETTABLEKS R4 R0 K2; var4 = var0["mClipName"]
      26 [-]: GETIMPORT R5 10; var5 = 0xBA5A3381
      27 [-]: LOADN R6 0   ; var6 = 0
      28 [-]: LOADN R7 0   ; var7 = 0
      29 [-]: CALL R2 6 1  ; var2(var3, var4, var5, var6, var7)
      30 [-]: RETURN R0 0  ; 


; Name:            
; Defined at line: 181
; #Upvalues:       4
; #Parameters:     2
; Is_vararg:       0
; Max Stack Size:  11

       0 [-]: LOADN R2 0   ; var2 = 0
       1 [-]: LOADN R5 1   ; var5 = 1
       2 [-]: GETUPVAL R6 0; var6 = upvalues[0]
       3 [-]: LENGTH R3 R6 ; var3 = #var6
       4 [-]: LOADN R4 1   ; var4 = 1
       5 [-]: FORNPREP R3 L4; nforprep start - [escape at L4] -- var3 = iterator
L 0:   6 [-]: GETUPVAL R7 0; var7 = upvalues[0]
       7 [-]: GETTABLE R6 R7 R5; var6 = var7[var5]
       8 [-]: JUMPIFEQ R6 R0 L3; goto L3 if var6 == var2108
       9 [-]: GETUPVAL R8 0; var8 = upvalues[0]
      10 [-]: GETTABLE R7 R8 R5; var7 = var8[var5]
      11 [-]: GETTABLEKS R6 R7 K0; var6 = var7["mActive"]
      12 [-]: JUMPIFNOT R6 L3; goto L3 if not var6
      13 [-]: GETUPVAL R7 1; var7 = upvalues[1]
      14 [-]: GETTABLEKS R6 R7 K1; var6 = var7[0x06D055F9]
      15 [-]: JUMPXEQKN R2 K2 L1; 
      16 [-]: LOADB R7 0 +1; var7 = false
L 1:  17 [-]: LOADB R7 1   ; var7 = true
L 2:  18 [-]: MOVE R8 R1   ; var8 = var1
      19 [-]: LOADNIL R9   ; var9 = nil
      20 [-]: CALL R6 4 2  ; var6 = var6(var7, var8, var9)
      21 [-]: GETUPVAL R7 2; var7 = upvalues[2]
      22 [-]: MULK R9 R2 K3; var9 = var2 * 0.15000000596046448
      23 [-]: NEWCLOSURE R10 P0; 
      24 [-]: CAPTURE UPVAL U3; 
      25 [-]: CAPTURE UPVAL U0; 
      26 [-]: CAPTURE VAL R5; 
      27 [-]: CAPTURE VAL R6; 
      28 [-]: NAMECALL R7 R7 K4; var8 = var7; var7 = var7[0xBD2E96EA]
      29 [-]: CALL R7 4 1  ; var7(var8, var9, var10)
      30 [-]: ADDK R2 R2 K5; var2 = var2 + 1
L 3:  31 [-]: FORNLOOP R3 L0; nforloop end - iterate + goto L0
L 4:  32 [-]: JUMPXEQKN R2 K2 L5 NOT; 
      33 [-]: JUMPXEQKNIL R1 L5; 
      34 [-]: MOVE R3 R1   ; var3 = var1
      35 [-]: CALL R3 1 1  ; var3()
L 5:  36 [-]: RETURN R0 0  ; 


; Name:            
; Defined at line: 198
; #Upvalues:       1
; #Parameters:     2
; Is_vararg:       0
; Max Stack Size:  13

       0 [-]: GETUPVAL R3 0; var3 = upvalues[0]
       1 [-]: GETTABLEKS R2 R3 K0; var2 = var3[0x659D451F]
       2 [-]: GETIMPORT R3 2; var3 = 0x7CE67A63
       3 [-]: CALL R2 2 1  ; var2(var3)
       4 [-]: NEWCLOSURE R2 P0; 
       5 [-]: CAPTURE VAL R0; 
       6 [-]: GETIMPORT R3 4; var3 = 0x25312C9B
       7 [-]: GETIMPORT R4 6; var4 = 0xAE91E43B
       8 [-]: MOVE R5 R0   ; var5 = var0
       9 [-]: LOADN R6 2   ; var6 = 2
      10 [-]: NEWTABLE R7 0 4; var7 = {}
      11 [-]: LOADN R8 5   ; var8 = 5
      12 [-]: LOADN R9 6   ; var9 = 6
      13 [-]: MOVE R10 R2  ; var10 = var2
      14 [-]: LOADN R11 15 ; var11 = 15
      15 [-]: SETLIST R7 R8 4 [1]; var7[1] = var8; var7[2] = var9; var7[3] = var10; var7[4] = var11; var7[5] = var12; 
      16 [-]: NEWTABLE R8 0 4; var8 = {}
      17 [-]: LOADN R9 100 ; var9 = 100
      18 [-]: LOADN R10 100; var10 = 100
      19 [-]: LOADN R11 1  ; var11 = 1
      20 [-]: LOADN R12 0  ; var12 = 0
      21 [-]: SETLIST R8 R9 4 [1]; var8[1] = var9; var8[2] = var10; var8[3] = var11; var8[4] = var12; var8[5] = var13; 
      22 [-]: LOADK R9 K7  ; var9 = 0.80000001192092896
      23 [-]: LOADN R10 0  ; var10 = 0
      24 [-]: MOVE R11 R1  ; var11 = var1
      25 [-]: CALL R3 9 1  ; var3(var4, var5, var6, var7, var8, var9, var10, var11)
      26 [-]: RETURN R0 0  ; 


; Name:            
; Defined at line: 213
; #Upvalues:       0
; #Parameters:     1
; Is_vararg:       0
; Max Stack Size:  16

       0 [-]: LOADN R3 1   ; var3 = 1
       1 [-]: LOADN R1 3   ; var1 = 3
       2 [-]: LOADN R2 1   ; var2 = 1
       3 [-]: FORNPREP R1 L1; nforprep start - [escape at L1] -- var1 = iterator
L 0:   4 [-]: MOVE R5 R0   ; var5 = var0
       5 [-]: LOADK R6 K0  ; var6 = ".Text"
       6 [-]: MOVE R7 R3   ; var7 = var3
       7 [-]: CONCAT R4 R5 R7; var4 = var5 .. var7
       8 [-]: GETIMPORT R5 2; var5 = 0xAE91E43B
       9 [-]: MOVE R7 R4   ; var7 = var4
      10 [-]: LOADN R8 0   ; var8 = 0
      11 [-]: LOADN R9 0   ; var9 = 0
      12 [-]: NAMECALL R5 R5 K3; var6 = var5; var5 = var5[0x67BC869F]
      13 [-]: CALL R5 5 1  ; var5(var6, var7, var8, var9)
      14 [-]: GETIMPORT R5 2; var5 = 0xAE91E43B
      15 [-]: MOVE R7 R4   ; var7 = var4
      16 [-]: LOADN R8 1   ; var8 = 1
      17 [-]: LOADN R9 0   ; var9 = 0
      18 [-]: NAMECALL R5 R5 K3; var6 = var5; var5 = var5[0x67BC869F]
      19 [-]: CALL R5 5 1  ; var5(var6, var7, var8, var9)
      20 [-]: GETIMPORT R5 2; var5 = 0xAE91E43B
      21 [-]: MOVE R7 R4   ; var7 = var4
      22 [-]: LOADN R8 14  ; var8 = 14
      23 [-]: LOADN R9 0   ; var9 = 0
      24 [-]: NAMECALL R5 R5 K3; var6 = var5; var5 = var5[0x67BC869F]
      25 [-]: CALL R5 5 1  ; var5(var6, var7, var8, var9)
      26 [-]: GETIMPORT R5 2; var5 = 0xAE91E43B
      27 [-]: MOVE R7 R4   ; var7 = var4
      28 [-]: LOADN R8 5   ; var8 = 5
      29 [-]: LOADN R9 100 ; var9 = 100
      30 [-]: NAMECALL R5 R5 K3; var6 = var5; var5 = var5[0x67BC869F]
      31 [-]: CALL R5 5 1  ; var5(var6, var7, var8, var9)
      32 [-]: GETIMPORT R5 2; var5 = 0xAE91E43B
      33 [-]: MOVE R7 R4   ; var7 = var4
      34 [-]: LOADN R8 6   ; var8 = 6
      35 [-]: LOADN R9 100 ; var9 = 100
      36 [-]: NAMECALL R5 R5 K3; var6 = var5; var5 = var5[0x67BC869F]
      37 [-]: CALL R5 5 1  ; var5(var6, var7, var8, var9)
      38 [-]: GETIMPORT R5 2; var5 = 0xAE91E43B
      39 [-]: MOVE R7 R4   ; var7 = var4
      40 [-]: LOADN R8 10  ; var8 = 10
      41 [-]: LOADN R9 100 ; var9 = 100
      42 [-]: NAMECALL R5 R5 K3; var6 = var5; var5 = var5[0x67BC869F]
      43 [-]: CALL R5 5 1  ; var5(var6, var7, var8, var9)
      44 [-]: GETIMPORT R5 2; var5 = 0xAE91E43B
      45 [-]: MOVE R7 R4   ; var7 = var4
      46 [-]: LOADK R8 K4  ; var8 = "Label"
      47 [-]: LOADN R9 39  ; var9 = 39
      48 [-]: LOADK R10 K5 ; var10 = "center"
      49 [-]: NAMECALL R5 R5 K6; var6 = var5; var5 = var5[0xE261AA96]
      50 [-]: CALL R5 6 1  ; var5(var6, var7, var8, var9, var10)
      51 [-]: GETIMPORT R5 2; var5 = 0xAE91E43B
      52 [-]: MOVE R7 R4   ; var7 = var4
      53 [-]: LOADK R8 K4  ; var8 = "Label"
      54 [-]: LOADN R9 0   ; var9 = 0
      55 [-]: GETIMPORT R11 2; var11 = 0xAE91E43B
      56 [-]: MOVE R14 R4  ; var14 = var4
      57 [-]: LOADK R15 K8 ; var15 = ".Label"
      58 [-]: CONCAT R13 R14 R15; var13 = var14 .. var15
      59 [-]: LOADN R14 12 ; var14 = 12
      60 [-]: NAMECALL R11 R11 K9; var12 = var11; var11 = var11[0x91A24E4B]
      61 [-]: CALL R11 4 2 ; var11 = var11(var12, var13, var14)
      62 [-]: MULK R10 R11 K7; var10 = var11 * -0.5
      63 [-]: NAMECALL R5 R5 K10; var6 = var5; var5 = var5[0xF64B7262]
      64 [-]: CALL R5 6 1  ; var5(var6, var7, var8, var9, var10)
      65 [-]: GETIMPORT R5 2; var5 = 0xAE91E43B
      66 [-]: MOVE R7 R4   ; var7 = var4
      67 [-]: LOADK R8 K4  ; var8 = "Label"
      68 [-]: LOADN R9 1   ; var9 = 1
      69 [-]: GETIMPORT R11 2; var11 = 0xAE91E43B
      70 [-]: MOVE R14 R4  ; var14 = var4
      71 [-]: LOADK R15 K8 ; var15 = ".Label"
      72 [-]: CONCAT R13 R14 R15; var13 = var14 .. var15
      73 [-]: LOADN R14 13 ; var14 = 13
      74 [-]: NAMECALL R11 R11 K9; var12 = var11; var11 = var11[0x91A24E4B]
      75 [-]: CALL R11 4 2 ; var11 = var11(var12, var13, var14)
      76 [-]: MULK R10 R11 K7; var10 = var11 * -0.5
      77 [-]: NAMECALL R5 R5 K10; var6 = var5; var5 = var5[0xF64B7262]
      78 [-]: CALL R5 6 1  ; var5(var6, var7, var8, var9, var10)
      79 [-]: GETIMPORT R5 2; var5 = 0xAE91E43B
      80 [-]: MOVE R8 R4   ; var8 = var4
      81 [-]: LOADK R9 K8  ; var9 = ".Label"
      82 [-]: CONCAT R7 R8 R9; var7 = var8 .. var9
      83 [-]: LOADNIL R8   ; var8 = nil
      84 [-]: NAMECALL R5 R5 K11; var6 = var5; var5 = var5[0xD5181643]
      85 [-]: CALL R5 4 1  ; var5(var6, var7, var8)
      86 [-]: FORNLOOP R1 L0; nforloop end - iterate + goto L0
L 1:  87 [-]: RETURN R0 0  ; 


; Name:            
; Defined at line: 230
; #Upvalues:       1
; #Parameters:     2
; Is_vararg:       0
; Max Stack Size:  14

       0 [-]: GETTABLEKS R2 R1 K0; var2 = var1["Initialized"]
       1 [-]: JUMPIF R2 L3 ; goto L3 if var2
       2 [-]: LOADB R2 1   ; var2 = true
       3 [-]: SETTABLEKS R2 R1 K0; var2["Initialized"] = var1
       4 [-]: GETUPVAL R2 0; var2 = upvalues[0]
       5 [-]: GETTABLEKS R3 R1 K1; var3 = var1["mClipName"]
       6 [-]: CALL R2 2 1  ; var2(var3)
       7 [-]: NEWTABLE R2 0 0; var2 = {}
       8 [-]: SETTABLEKS R2 R1 K2; var2["BackerTransformDelay"] = var1
       9 [-]: GETIMPORT R2 4; var2 = 0xC163F229
      10 [-]: LOADN R3 1   ; var3 = 1
      11 [-]: LOADN R4 30  ; var4 = 30
      12 [-]: CALL R2 3 2  ; var2 = var2(var3, var4)
      13 [-]: SETTABLEKS R2 R1 K5; var2["NoiseOffset"] = var1
      14 [-]: LOADN R4 1   ; var4 = 1
      15 [-]: LOADN R2 3   ; var2 = 3
      16 [-]: LOADN R3 1   ; var3 = 1
      17 [-]: FORNPREP R2 L3; nforprep start - [escape at L3] -- var2 = iterator
L 0:  18 [-]: GETTABLEKS R6 R1 K1; var6 = var1["mClipName"]
      19 [-]: LOADK R7 K6  ; var7 = ".Text"
      20 [-]: MOVE R8 R4   ; var8 = var4
      21 [-]: CONCAT R5 R6 R8; var5 = var6 .. var8
      22 [-]: LOADN R7 100 ; var7 = 100
      23 [-]: SUBK R9 R4 K8; var9 = var4 - 1
      24 [-]: MULK R8 R9 K7; var8 = var9 * 75
      25 [-]: ADD R6 R7 R8 ; var6 = var7 + var8
      26 [-]: GETIMPORT R7 10; var7 = 0xAE91E43B
      27 [-]: MOVE R9 R5   ; var9 = var5
      28 [-]: LOADN R10 5  ; var10 = 5
      29 [-]: MOVE R11 R6  ; var11 = var6
      30 [-]: NAMECALL R7 R7 K11; var8 = var7; var7 = var7[0x67BC869F]
      31 [-]: CALL R7 5 1  ; var7(var8, var9, var10, var11)
      32 [-]: GETIMPORT R7 10; var7 = 0xAE91E43B
      33 [-]: MOVE R9 R5   ; var9 = var5
      34 [-]: LOADN R10 6  ; var10 = 6
      35 [-]: MOVE R11 R6  ; var11 = var6
      36 [-]: NAMECALL R7 R7 K11; var8 = var7; var7 = var7[0x67BC869F]
      37 [-]: CALL R7 5 1  ; var7(var8, var9, var10, var11)
      38 [-]: JUMPXEQKN R4 K12 L1 NOT; 
      39 [-]: GETIMPORT R7 10; var7 = 0xAE91E43B
      40 [-]: MOVE R9 R5   ; var9 = var5
      41 [-]: LOADN R10 10 ; var10 = 10
      42 [-]: LOADN R11 15 ; var11 = 15
      43 [-]: NAMECALL R7 R7 K11; var8 = var7; var7 = var7[0x67BC869F]
      44 [-]: CALL R7 5 1  ; var7(var8, var9, var10, var11)
      45 [-]: JUMP L2      ; goto L2
L 1:  46 [-]: JUMPXEQKN R4 K13 L2 NOT; 
      47 [-]: GETIMPORT R7 10; var7 = 0xAE91E43B
      48 [-]: MOVE R9 R5   ; var9 = var5
      49 [-]: LOADN R10 10 ; var10 = 10
      50 [-]: LOADN R11 3  ; var11 = 3
      51 [-]: NAMECALL R7 R7 K11; var8 = var7; var7 = var7[0x67BC869F]
      52 [-]: CALL R7 5 1  ; var7(var8, var9, var10, var11)
L 2:  53 [-]: FORNLOOP R2 L0; nforloop end - iterate + goto L0
L 3:  54 [-]: GETIMPORT R2 15; var2 = 0xF7F90318
      55 [-]: GETTABLEKS R4 R1 K5; var4 = var1["NoiseOffset"]
      56 [-]: GETIMPORT R6 18; var6 = 0x55156FF7
      57 [-]: CALL R6 1 2  ; var6 = var6()
      58 [-]: MULK R5 R6 K16; var5 = var6 * 0.039999999105930328
      59 [-]: ADD R3 R4 R5 ; var3 = var4 + var5
      60 [-]: CALL R2 2 2  ; var2 = var2(var3)
      61 [-]: GETIMPORT R3 15; var3 = 0xF7F90318
      62 [-]: GETTABLEKS R5 R1 K5; var5 = var1["NoiseOffset"]
      63 [-]: GETIMPORT R7 18; var7 = 0x55156FF7
      64 [-]: CALL R7 1 2  ; var7 = var7()
      65 [-]: MULK R6 R7 K19; var6 = var7 * 0.02500000037252903
      66 [-]: ADD R4 R5 R6 ; var4 = var5 + var6
      67 [-]: CALL R3 2 2  ; var3 = var3(var4)
      68 [-]: LOADN R6 1   ; var6 = 1
      69 [-]: LOADN R4 3   ; var4 = 3
      70 [-]: LOADN R5 1   ; var5 = 1
      71 [-]: FORNPREP R4 L5; nforprep start - [escape at L5] -- var4 = iterator
L 4:  72 [-]: GETTABLEKS R8 R1 K1; var8 = var1["mClipName"]
      73 [-]: LOADK R9 K6  ; var9 = ".Text"
      74 [-]: MOVE R10 R6  ; var10 = var6
      75 [-]: CONCAT R7 R8 R10; var7 = var8 .. var10
      76 [-]: GETIMPORT R8 10; var8 = 0xAE91E43B
      77 [-]: MOVE R10 R7  ; var10 = var7
      78 [-]: LOADN R11 0  ; var11 = 0
      79 [-]: MULK R13 R2 K20; var13 = var2 * 30
      80 [-]: MUL R12 R13 R6; var12 = var13 * var6
      81 [-]: NAMECALL R8 R8 K11; var9 = var8; var8 = var8[0x67BC869F]
      82 [-]: CALL R8 5 1  ; var8(var9, var10, var11, var12)
      83 [-]: GETIMPORT R8 10; var8 = 0xAE91E43B
      84 [-]: MOVE R10 R7  ; var10 = var7
      85 [-]: LOADN R11 1  ; var11 = 1
      86 [-]: MULK R13 R3 K21; var13 = var3 * 40
      87 [-]: MUL R12 R13 R6; var12 = var13 * var6
      88 [-]: NAMECALL R8 R8 K11; var9 = var8; var8 = var8[0x67BC869F]
      89 [-]: CALL R8 5 1  ; var8(var9, var10, var11, var12)
      90 [-]: FORNLOOP R4 L4; nforloop end - iterate + goto L4
L 5:  91 [-]: RETURN R0 0  ; 


; Name:            
; Defined at line: 260
; #Upvalues:       1
; #Parameters:     2
; Is_vararg:       0
; Max Stack Size:  12

       0 [-]: GETTABLEKS R2 R1 K0; var2 = var1["Initialized"]
       1 [-]: JUMPIF R2 L4 ; goto L4 if var2
       2 [-]: LOADB R2 1   ; var2 = true
       3 [-]: SETTABLEKS R2 R1 K0; var2["Initialized"] = var1
       4 [-]: GETUPVAL R2 0; var2 = upvalues[0]
       5 [-]: GETTABLEKS R3 R1 K1; var3 = var1["mClipName"]
       6 [-]: CALL R2 2 1  ; var2(var3)
       7 [-]: NEWTABLE R2 0 0; var2 = {}
       8 [-]: SETTABLEKS R2 R1 K2; var2["BackerTransformDelay"] = var1
       9 [-]: GETIMPORT R2 4; var2 = 0xC163F229
      10 [-]: LOADN R3 1   ; var3 = 1
      11 [-]: LOADN R4 30  ; var4 = 30
      12 [-]: CALL R2 3 2  ; var2 = var2(var3, var4)
      13 [-]: SETTABLEKS R2 R1 K5; var2["NoiseOffset"] = var1
      14 [-]: LOADB R2 0   ; var2 = false
      15 [-]: SETTABLEKS R2 R1 K6; var2["Hide"] = var1
      16 [-]: LOADN R2 0   ; var2 = 0
      17 [-]: SETTABLEKS R2 R1 K7; var2["TransitionTime"] = var1
      18 [-]: LOADN R2 0   ; var2 = 0
      19 [-]: SETTABLEKS R2 R1 K8; var2["TransitionDelay"] = var1
      20 [-]: LOADK R2 K9  ; var2 = 1.2000000476837158
      21 [-]: SETTABLEKS R2 R1 K10; var2["TransitionDuration"] = var1
      22 [-]: LOADN R4 1   ; var4 = 1
      23 [-]: LOADN R2 3   ; var2 = 3
      24 [-]: LOADN R3 1   ; var3 = 1
      25 [-]: FORNPREP R2 L4; nforprep start - [escape at L4] -- var2 = iterator
L 0:  26 [-]: GETTABLEKS R6 R1 K1; var6 = var1["mClipName"]
      27 [-]: LOADK R7 K11 ; var7 = ".Text"
      28 [-]: MOVE R8 R4   ; var8 = var4
      29 [-]: CONCAT R5 R6 R8; var5 = var6 .. var8
      30 [-]: JUMPXEQKN R4 K12 L1 NOT; 
      31 [-]: GETIMPORT R6 14; var6 = 0xAE91E43B
      32 [-]: MOVE R8 R5   ; var8 = var5
      33 [-]: LOADN R9 5   ; var9 = 5
      34 [-]: LOADN R10 50 ; var10 = 50
      35 [-]: NAMECALL R6 R6 K15; var7 = var6; var6 = var6[0x67BC869F]
      36 [-]: CALL R6 5 1  ; var6(var7, var8, var9, var10)
      37 [-]: GETIMPORT R6 14; var6 = 0xAE91E43B
      38 [-]: MOVE R8 R5   ; var8 = var5
      39 [-]: LOADN R9 6   ; var9 = 6
      40 [-]: LOADN R10 50 ; var10 = 50
      41 [-]: NAMECALL R6 R6 K15; var7 = var6; var6 = var6[0x67BC869F]
      42 [-]: CALL R6 5 1  ; var6(var7, var8, var9, var10)
      43 [-]: GETIMPORT R6 14; var6 = 0xAE91E43B
      44 [-]: MOVE R8 R5   ; var8 = var5
      45 [-]: LOADK R9 K16 ; var9 = "Label"
      46 [-]: LOADN R10 0  ; var10 = 0
      47 [-]: LOADN R11 0  ; var11 = 0
      48 [-]: NAMECALL R6 R6 K17; var7 = var6; var6 = var6[0xF64B7262]
      49 [-]: CALL R6 6 1  ; var6(var7, var8, var9, var10, var11)
      50 [-]: JUMP L3      ; goto L3
L 1:  51 [-]: JUMPXEQKN R4 K18 L2 NOT; 
      52 [-]: GETIMPORT R6 14; var6 = 0xAE91E43B
      53 [-]: MOVE R8 R5   ; var8 = var5
      54 [-]: LOADN R9 5   ; var9 = 5
      55 [-]: LOADN R10 300; var10 = 300
      56 [-]: NAMECALL R6 R6 K15; var7 = var6; var6 = var6[0x67BC869F]
      57 [-]: CALL R6 5 1  ; var6(var7, var8, var9, var10)
      58 [-]: GETIMPORT R6 14; var6 = 0xAE91E43B
      59 [-]: MOVE R8 R5   ; var8 = var5
      60 [-]: LOADN R9 6   ; var9 = 6
      61 [-]: LOADN R10 300; var10 = 300
      62 [-]: NAMECALL R6 R6 K15; var7 = var6; var6 = var6[0x67BC869F]
      63 [-]: CALL R6 5 1  ; var6(var7, var8, var9, var10)
      64 [-]: GETIMPORT R6 14; var6 = 0xAE91E43B
      65 [-]: MOVE R8 R5   ; var8 = var5
      66 [-]: LOADN R9 10  ; var9 = 10
      67 [-]: LOADN R10 5  ; var10 = 5
      68 [-]: NAMECALL R6 R6 K15; var7 = var6; var6 = var6[0x67BC869F]
      69 [-]: CALL R6 5 1  ; var6(var7, var8, var9, var10)
      70 [-]: GETIMPORT R6 14; var6 = 0xAE91E43B
      71 [-]: MOVE R8 R5   ; var8 = var5
      72 [-]: LOADK R9 K16 ; var9 = "Label"
      73 [-]: LOADN R10 0  ; var10 = 0
      74 [-]: LOADN R11 -2 ; var11 = -2
      75 [-]: NAMECALL R6 R6 K17; var7 = var6; var6 = var6[0xF64B7262]
      76 [-]: CALL R6 6 1  ; var6(var7, var8, var9, var10, var11)
      77 [-]: JUMP L3      ; goto L3
L 2:  78 [-]: GETIMPORT R6 14; var6 = 0xAE91E43B
      79 [-]: MOVE R8 R5   ; var8 = var5
      80 [-]: LOADN R9 10  ; var9 = 10
      81 [-]: LOADN R10 0  ; var10 = 0
      82 [-]: NAMECALL R6 R6 K15; var7 = var6; var6 = var6[0x67BC869F]
      83 [-]: CALL R6 5 1  ; var6(var7, var8, var9, var10)
L 3:  84 [-]: GETIMPORT R6 14; var6 = 0xAE91E43B
      85 [-]: MOVE R8 R5   ; var8 = var5
      86 [-]: LOADK R9 K16 ; var9 = "Label"
      87 [-]: LOADN R10 39 ; var10 = 39
      88 [-]: LOADK R11 K19; var11 = "left"
      89 [-]: NAMECALL R6 R6 K20; var7 = var6; var6 = var6[0xE261AA96]
      90 [-]: CALL R6 6 1  ; var6(var7, var8, var9, var10, var11)
      91 [-]: GETIMPORT R6 14; var6 = 0xAE91E43B
      92 [-]: MOVE R8 R5   ; var8 = var5
      93 [-]: LOADK R9 K16 ; var9 = "Label"
      94 [-]: LOADN R10 1  ; var10 = 1
      95 [-]: LOADN R11 -25; var11 = -25
      96 [-]: NAMECALL R6 R6 K17; var7 = var6; var6 = var6[0xF64B7262]
      97 [-]: CALL R6 6 1  ; var6(var7, var8, var9, var10, var11)
      98 [-]: FORNLOOP R2 L0; nforloop end - iterate + goto L0
L 4:  99 [-]: GETTABLEKS R2 R1 K7; var2 = var1["TransitionTime"]
     100 [-]: LOADN R3 0   ; var3 = 0
     101 [-]: JUMPIFNOTLT R3 R2 L7; goto L7 if var3 >= var419496767
     102 [-]: GETTABLEKS R3 R1 K7; var3 = var1["TransitionTime"]
     103 [-]: SUB R2 R3 R0 ; var2 = var3 - var0
     104 [-]: SETTABLEKS R2 R1 K7; var2["TransitionTime"] = var1
     105 [-]: GETTABLEKS R3 R1 K7; var3 = var1["TransitionTime"]
     106 [-]: GETTABLEKS R4 R1 K10; var4 = var1["TransitionDuration"]
     107 [-]: DIV R2 R3 R4 ; var2 = var3 / var4
     108 [-]: LOADN R3 0   ; var3 = 0
     109 [-]: GETTABLEKS R4 R1 K6; var4 = var1["Hide"]
     110 [-]: JUMPIFNOT R4 L5; goto L5 if not var4
     111 [-]: GETIMPORT R4 22; var4 = 0x9BAFFFE3
     112 [-]: LOADN R5 50  ; var5 = 50
     113 [-]: LOADN R6 30  ; var6 = 30
     114 [-]: MOVE R7 R2   ; var7 = var2
     115 [-]: CALL R4 4 2  ; var4 = var4(var5, var6, var7)
     116 [-]: MOVE R3 R4   ; var3 = var4
     117 [-]: JUMP L6      ; goto L6
L 5: 118 [-]: GETIMPORT R4 22; var4 = 0x9BAFFFE3
     119 [-]: LOADN R5 30  ; var5 = 30
     120 [-]: LOADN R6 50  ; var6 = 50
     121 [-]: MOVE R7 R2   ; var7 = var2
     122 [-]: CALL R4 4 2  ; var4 = var4(var5, var6, var7)
     123 [-]: MOVE R3 R4   ; var3 = var4
L 6: 124 [-]: GETIMPORT R4 14; var4 = 0xAE91E43B
     125 [-]: GETTABLEKS R6 R1 K1; var6 = var1["mClipName"]
     126 [-]: LOADK R7 K23 ; var7 = "Text1"
     127 [-]: LOADN R8 5   ; var8 = 5
     128 [-]: MOVE R9 R3   ; var9 = var3
     129 [-]: NAMECALL R4 R4 K17; var5 = var4; var4 = var4[0xF64B7262]
     130 [-]: CALL R4 6 1  ; var4(var5, var6, var7, var8, var9)
     131 [-]: GETIMPORT R4 14; var4 = 0xAE91E43B
     132 [-]: GETTABLEKS R6 R1 K1; var6 = var1["mClipName"]
     133 [-]: LOADK R7 K23 ; var7 = "Text1"
     134 [-]: LOADN R8 6   ; var8 = 6
     135 [-]: MOVE R9 R3   ; var9 = var3
     136 [-]: NAMECALL R4 R4 K17; var5 = var4; var4 = var4[0xF64B7262]
     137 [-]: CALL R4 6 1  ; var4(var5, var6, var7, var8, var9)
     138 [-]: RETURN R0 0  ; 
L 7: 139 [-]: GETTABLEKS R2 R1 K8; var2 = var1["TransitionDelay"]
     140 [-]: LOADN R3 0   ; var3 = 0
     141 [-]: JUMPIFNOTLT R3 R2 L8; goto L8 if var3 >= var469828415
     142 [-]: GETTABLEKS R3 R1 K8; var3 = var1["TransitionDelay"]
     143 [-]: SUB R2 R3 R0 ; var2 = var3 - var0
     144 [-]: SETTABLEKS R2 R1 K8; var2["TransitionDelay"] = var1
     145 [-]: RETURN R0 0  ; 
L 8: 146 [-]: GETTABLEKS R2 R1 K10; var2 = var1["TransitionDuration"]
     147 [-]: SETTABLEKS R2 R1 K7; var2["TransitionTime"] = var1
     148 [-]: GETIMPORT R2 4; var2 = 0xC163F229
     149 [-]: LOADN R3 3   ; var3 = 3
     150 [-]: LOADN R4 5   ; var4 = 5
     151 [-]: CALL R2 3 2  ; var2 = var2(var3, var4)
     152 [-]: SETTABLEKS R2 R1 K8; var2["TransitionDelay"] = var1
     153 [-]: GETTABLEKS R3 R1 K6; var3 = var1["Hide"]
     154 [-]: NOT R2 R3    ; var2 = not var3
     155 [-]: SETTABLEKS R2 R1 K6; var2["Hide"] = var1
     156 [-]: RETURN R0 0  ; 


; Name:            
; Defined at line: 312
; #Upvalues:       1
; #Parameters:     2
; Is_vararg:       0
; Max Stack Size:  18

       0 [-]: GETTABLEKS R2 R1 K0; var2 = var1["Initialized"]
       1 [-]: JUMPIF R2 L2 ; goto L2 if var2
       2 [-]: LOADB R2 1   ; var2 = true
       3 [-]: SETTABLEKS R2 R1 K0; var2["Initialized"] = var1
       4 [-]: GETUPVAL R2 0; var2 = upvalues[0]
       5 [-]: GETTABLEKS R3 R1 K1; var3 = var1["mClipName"]
       6 [-]: CALL R2 2 1  ; var2(var3)
       7 [-]: LOADN R4 1   ; var4 = 1
       8 [-]: LOADN R2 3   ; var2 = 3
       9 [-]: LOADN R3 1   ; var3 = 1
      10 [-]: FORNPREP R2 L1; nforprep start - [escape at L1] -- var2 = iterator
L 0:  11 [-]: GETTABLEKS R6 R1 K1; var6 = var1["mClipName"]
      12 [-]: LOADK R7 K2  ; var7 = ".Text"
      13 [-]: MOVE R8 R4   ; var8 = var4
      14 [-]: CONCAT R5 R6 R8; var5 = var6 .. var8
      15 [-]: GETIMPORT R6 4; var6 = 0xAE91E43B
      16 [-]: MOVE R8 R5   ; var8 = var5
      17 [-]: LOADN R9 10  ; var9 = 10
      18 [-]: LOADN R10 2  ; var10 = 2
      19 [-]: NAMECALL R6 R6 K5; var7 = var6; var6 = var6[0x67BC869F]
      20 [-]: CALL R6 5 1  ; var6(var7, var8, var9, var10)
      21 [-]: GETIMPORT R6 4; var6 = 0xAE91E43B
      22 [-]: MOVE R8 R5   ; var8 = var5
      23 [-]: LOADN R9 5   ; var9 = 5
      24 [-]: LOADN R10 60 ; var10 = 60
      25 [-]: NAMECALL R6 R6 K5; var7 = var6; var6 = var6[0x67BC869F]
      26 [-]: CALL R6 5 1  ; var6(var7, var8, var9, var10)
      27 [-]: GETIMPORT R6 4; var6 = 0xAE91E43B
      28 [-]: MOVE R8 R5   ; var8 = var5
      29 [-]: LOADN R9 6   ; var9 = 6
      30 [-]: LOADN R10 60 ; var10 = 60
      31 [-]: NAMECALL R6 R6 K5; var7 = var6; var6 = var6[0x67BC869F]
      32 [-]: CALL R6 5 1  ; var6(var7, var8, var9, var10)
      33 [-]: FORNLOOP R2 L0; nforloop end - iterate + goto L0
L 1:  34 [-]: LOADN R2 0   ; var2 = 0
      35 [-]: SETTABLEKS R2 R1 K6; var2["Life"] = var1
      36 [-]: LOADN R2 0   ; var2 = 0
      37 [-]: SETTABLEKS R2 R1 K7; var2["PrevProp"] = var1
      38 [-]: GETIMPORT R2 9; var2 = 0x78CA68A2
      39 [-]: LOADN R3 0   ; var3 = 0
      40 [-]: LOADK R4 K10 ; var4 = 0.15000000596046448
      41 [-]: CALL R2 3 2  ; var2 = var2(var3, var4)
      42 [-]: SETTABLEKS R2 R1 K11; var2["SurpriseMult"] = var1
L 2:  43 [-]: GETTABLEKS R3 R1 K6; var3 = var1["Life"]
      44 [-]: MULK R4 R0 K12; var4 = var0 * 0.25
      45 [-]: ADD R2 R3 R4 ; var2 = var3 + var4
      46 [-]: SETTABLEKS R2 R1 K6; var2["Life"] = var1
      47 [-]: GETTABLEKS R2 R1 K6; var2 = var1["Life"]
      48 [-]: LOADN R3 1   ; var3 = 1
      49 [-]: JUMPIFNOTLT R3 R2 L3; goto L3 if var3 >= var-1191115969
      50 [-]: GETTABLEKS R3 R1 K6; var3 = var1["Life"]
      51 [-]: SUBK R2 R3 K13; var2 = var3 - 1
      52 [-]: SETTABLEKS R2 R1 K6; var2["Life"] = var1
L 3:  53 [-]: GETTABLEKS R2 R1 K6; var2 = var1["Life"]
      54 [-]: LOADK R3 K14 ; var3 = 0.75
      55 [-]: JUMPIFNOTLT R3 R2 L4; goto L4 if var3 >= var469828159
      56 [-]: GETTABLEKS R2 R1 K11; var2 = var1["SurpriseMult"]
      57 [-]: LOADN R4 1   ; var4 = 1
      58 [-]: NAMECALL R2 R2 K15; var3 = var2; var2 = var2[0x188E2BEE]
      59 [-]: CALL R2 3 1  ; var2(var3, var4)
      60 [-]: JUMP L5      ; goto L5
L 4:  61 [-]: GETTABLEKS R2 R1 K11; var2 = var1["SurpriseMult"]
      62 [-]: LOADN R4 0   ; var4 = 0
      63 [-]: NAMECALL R2 R2 K15; var3 = var2; var2 = var2[0x188E2BEE]
      64 [-]: CALL R2 3 1  ; var2(var3, var4)
L 5:  65 [-]: GETTABLEKS R2 R1 K11; var2 = var1["SurpriseMult"]
      66 [-]: MOVE R4 R0   ; var4 = var0
      67 [-]: NAMECALL R2 R2 K16; var3 = var2; var2 = var2[0xFAA69527]
      68 [-]: CALL R2 3 1  ; var2(var3, var4)
      69 [-]: LOADN R4 1   ; var4 = 1
      70 [-]: LOADN R2 3   ; var2 = 3
      71 [-]: LOADN R3 1   ; var3 = 1
      72 [-]: FORNPREP R2 L8; nforprep start - [escape at L8] -- var2 = iterator
L 6:  73 [-]: GETTABLEKS R6 R1 K1; var6 = var1["mClipName"]
      74 [-]: LOADK R7 K2  ; var7 = ".Text"
      75 [-]: MOVE R8 R4   ; var8 = var4
      76 [-]: CONCAT R5 R6 R8; var5 = var6 .. var8
      77 [-]: LOADN R7 60  ; var7 = 60
      78 [-]: LOADN R10 50 ; var10 = 50
      79 [-]: MUL R9 R10 R4; var9 = var10 * var4
      80 [-]: GETTABLEKS R10 R1 K11; var10 = var1["SurpriseMult"]
      81 [-]: NAMECALL R10 R10 K17; var11 = var10; var10 = var10[0x54AB95F9]
      82 [-]: CALL R10 2 2 ; var10 = var10(var11)
      83 [-]: MUL R8 R9 R10; var8 = var9 * var10
      84 [-]: ADD R6 R7 R8 ; var6 = var7 + var8
      85 [-]: GETIMPORT R7 4; var7 = 0xAE91E43B
      86 [-]: MOVE R9 R5   ; var9 = var5
      87 [-]: LOADN R10 5  ; var10 = 5
      88 [-]: MOVE R11 R6  ; var11 = var6
      89 [-]: NAMECALL R7 R7 K5; var8 = var7; var7 = var7[0x67BC869F]
      90 [-]: CALL R7 5 1  ; var7(var8, var9, var10, var11)
      91 [-]: GETIMPORT R7 4; var7 = 0xAE91E43B
      92 [-]: MOVE R9 R5   ; var9 = var5
      93 [-]: LOADN R10 6  ; var10 = 6
      94 [-]: MOVE R11 R6  ; var11 = var6
      95 [-]: NAMECALL R7 R7 K5; var8 = var7; var7 = var7[0x67BC869F]
      96 [-]: CALL R7 5 1  ; var7(var8, var9, var10, var11)
      97 [-]: GETIMPORT R7 4; var7 = 0xAE91E43B
      98 [-]: MOVE R9 R5   ; var9 = var5
      99 [-]: LOADN R10 10 ; var10 = 10
     100 [-]: LOADN R12 2  ; var12 = 2
     101 [-]: LOADN R15 35 ; var15 = 35
     102 [-]: LOADN R17 3  ; var17 = 3
     103 [-]: SUB R16 R17 R4; var16 = var17 - var4
     104 [-]: MUL R14 R15 R16; var14 = var15 * var16
     105 [-]: GETTABLEKS R15 R1 K11; var15 = var1["SurpriseMult"]
     106 [-]: NAMECALL R15 R15 K17; var16 = var15; var15 = var15[0x54AB95F9]
     107 [-]: CALL R15 2 2 ; var15 = var15(var16)
     108 [-]: MUL R13 R14 R15; var13 = var14 * var15
     109 [-]: ADD R11 R12 R13; var11 = var12 + var13
     110 [-]: NAMECALL R7 R7 K5; var8 = var7; var7 = var7[0x67BC869F]
     111 [-]: CALL R7 5 1  ; var7(var8, var9, var10, var11)
     112 [-]: GETIMPORT R7 4; var7 = 0xAE91E43B
     113 [-]: MOVE R9 R5   ; var9 = var5
     114 [-]: LOADN R10 14 ; var10 = 14
     115 [-]: GETTABLEKS R16 R1 K6; var16 = var1["Life"]
     116 [-]: MULK R17 R4 K19; var17 = var4 * 0.33000001311302185
     117 [-]: ADD R15 R16 R17; var15 = var16 + var17
     118 [-]: MULK R14 R15 K18; var14 = var15 * 200
     119 [-]: FASTCALL1 24 R14 L7; 
     120 [-]: GETIMPORT R13 22; var13 = 0x5BCED4C4[0x3EDA26FC]
     121 [-]: CALL R13 2 2 ; var13 = var13(var14)
L 7: 122 [-]: LOADN R15 5  ; var15 = 5
     123 [-]: MUL R14 R15 R4; var14 = var15 * var4
     124 [-]: MUL R12 R13 R14; var12 = var13 * var14
     125 [-]: GETTABLEKS R13 R1 K11; var13 = var1["SurpriseMult"]
     126 [-]: NAMECALL R13 R13 K17; var14 = var13; var13 = var13[0x54AB95F9]
     127 [-]: CALL R13 2 2 ; var13 = var13(var14)
     128 [-]: MUL R11 R12 R13; var11 = var12 * var13
     129 [-]: NAMECALL R7 R7 K5; var8 = var7; var7 = var7[0x67BC869F]
     130 [-]: CALL R7 5 1  ; var7(var8, var9, var10, var11)
     131 [-]: FORNLOOP R2 L6; nforloop end - iterate + goto L6
L 8: 132 [-]: RETURN R0 0  ; 


; Name:            
; Defined at line: 355
; #Upvalues:       1
; #Parameters:     2
; Is_vararg:       0
; Max Stack Size:  14

       0 [-]: GETTABLEKS R2 R1 K0; var2 = var1["Initialized"]
       1 [-]: JUMPIF R2 L0 ; goto L0 if var2
       2 [-]: LOADB R2 1   ; var2 = true
       3 [-]: SETTABLEKS R2 R1 K0; var2["Initialized"] = var1
       4 [-]: GETUPVAL R2 0; var2 = upvalues[0]
       5 [-]: GETTABLEKS R3 R1 K1; var3 = var1["mClipName"]
       6 [-]: CALL R2 2 1  ; var2(var3)
       7 [-]: GETIMPORT R2 3; var2 = 0xAE91E43B
       8 [-]: GETTABLEKS R4 R1 K1; var4 = var1["mClipName"]
       9 [-]: LOADK R5 K4  ; var5 = "Text2"
      10 [-]: LOADN R6 10  ; var6 = 10
      11 [-]: LOADN R7 5   ; var7 = 5
      12 [-]: NAMECALL R2 R2 K5; var3 = var2; var2 = var2[0xF64B7262]
      13 [-]: CALL R2 6 1  ; var2(var3, var4, var5, var6, var7)
      14 [-]: GETIMPORT R2 3; var2 = 0xAE91E43B
      15 [-]: GETTABLEKS R4 R1 K1; var4 = var1["mClipName"]
      16 [-]: LOADK R5 K4  ; var5 = "Text2"
      17 [-]: LOADN R6 5   ; var6 = 5
      18 [-]: LOADN R7 200 ; var7 = 200
      19 [-]: NAMECALL R2 R2 K5; var3 = var2; var2 = var2[0xF64B7262]
      20 [-]: CALL R2 6 1  ; var2(var3, var4, var5, var6, var7)
      21 [-]: GETIMPORT R2 3; var2 = 0xAE91E43B
      22 [-]: GETTABLEKS R4 R1 K1; var4 = var1["mClipName"]
      23 [-]: LOADK R5 K4  ; var5 = "Text2"
      24 [-]: LOADN R6 6   ; var6 = 6
      25 [-]: LOADN R7 200 ; var7 = 200
      26 [-]: NAMECALL R2 R2 K5; var3 = var2; var2 = var2[0xF64B7262]
      27 [-]: CALL R2 6 1  ; var2(var3, var4, var5, var6, var7)
      28 [-]: GETIMPORT R2 3; var2 = 0xAE91E43B
      29 [-]: GETTABLEKS R4 R1 K1; var4 = var1["mClipName"]
      30 [-]: LOADK R5 K6  ; var5 = "Text3"
      31 [-]: LOADN R6 10  ; var6 = 10
      32 [-]: LOADN R7 0   ; var7 = 0
      33 [-]: NAMECALL R2 R2 K5; var3 = var2; var2 = var2[0xF64B7262]
      34 [-]: CALL R2 6 1  ; var2(var3, var4, var5, var6, var7)
      35 [-]: GETIMPORT R2 3; var2 = 0xAE91E43B
      36 [-]: GETTABLEKS R4 R1 K1; var4 = var1["mClipName"]
      37 [-]: LOADK R5 K7  ; var5 = "Text1"
      38 [-]: LOADN R6 1   ; var6 = 1
      39 [-]: LOADN R7 25  ; var7 = 25
      40 [-]: NAMECALL R2 R2 K5; var3 = var2; var2 = var2[0xF64B7262]
      41 [-]: CALL R2 6 1  ; var2(var3, var4, var5, var6, var7)
      42 [-]: GETIMPORT R2 3; var2 = 0xAE91E43B
      43 [-]: GETTABLEKS R4 R1 K1; var4 = var1["mClipName"]
      44 [-]: LOADK R5 K8  ; var5 = "Text1.Label"
      45 [-]: LOADN R6 1   ; var6 = 1
      46 [-]: GETIMPORT R8 3; var8 = 0xAE91E43B
      47 [-]: GETTABLEKS R11 R1 K1; var11 = var1["mClipName"]
      48 [-]: LOADK R12 K9 ; var12 = ".Text1"
      49 [-]: CONCAT R10 R11 R12; var10 = var11 .. var12
      50 [-]: LOADN R11 13 ; var11 = 13
      51 [-]: NAMECALL R8 R8 K10; var9 = var8; var8 = var8[0x91A24E4B]
      52 [-]: CALL R8 4 2  ; var8 = var8(var9, var10, var11)
      53 [-]: MINUS R7 R8  ; 
      54 [-]: NAMECALL R2 R2 K5; var3 = var2; var2 = var2[0xF64B7262]
      55 [-]: CALL R2 6 1  ; var2(var3, var4, var5, var6, var7)
      56 [-]: LOADN R2 0   ; var2 = 0
      57 [-]: SETTABLEKS R2 R1 K11; var2["Life"] = var1
      58 [-]: LOADN R2 0   ; var2 = 0
      59 [-]: SETTABLEKS R2 R1 K12; var2["PrevProp"] = var1
      60 [-]: LOADN R2 -1  ; var2 = -1
      61 [-]: SETTABLEKS R2 R1 K13; var2["Direction"] = var1
      62 [-]: LOADN R2 0   ; var2 = 0
      63 [-]: SETTABLEKS R2 R1 K14; var2["Hop"] = var1
      64 [-]: LOADN R2 0   ; var2 = 0
      65 [-]: SETTABLEKS R2 R1 K15; var2["Rotation"] = var1
L 0:  66 [-]: GETTABLEKS R3 R1 K11; var3 = var1["Life"]
      67 [-]: MULK R4 R0 K16; var4 = var0 * 0.25
      68 [-]: ADD R2 R3 R4 ; var2 = var3 + var4
      69 [-]: SETTABLEKS R2 R1 K11; var2["Life"] = var1
      70 [-]: GETTABLEKS R2 R1 K11; var2 = var1["Life"]
      71 [-]: LOADN R3 1   ; var3 = 1
      72 [-]: JUMPIFNOTLT R3 R2 L1; goto L1 if var3 >= var-1191115969
      73 [-]: GETTABLEKS R3 R1 K11; var3 = var1["Life"]
      74 [-]: SUBK R2 R3 K17; var2 = var3 - 1
      75 [-]: SETTABLEKS R2 R1 K11; var2["Life"] = var1
      76 [-]: LOADN R2 0   ; var2 = 0
      77 [-]: SETTABLEKS R2 R1 K14; var2["Hop"] = var1
L 1:  78 [-]: GETTABLEKS R3 R1 K1; var3 = var1["mClipName"]
      79 [-]: LOADK R4 K9  ; var4 = ".Text1"
      80 [-]: CONCAT R2 R3 R4; var2 = var3 .. var4
      81 [-]: GETTABLEKS R3 R1 K11; var3 = var1["Life"]
      82 [-]: LOADK R4 K18 ; var4 = 0.55000001192092896
      83 [-]: JUMPIFNOTLT R4 R3 L9; goto L9 if var4 >= var-1191114945
      84 [-]: GETTABLEKS R7 R1 K11; var7 = var1["Life"]
      85 [-]: MULK R6 R7 K20; var6 = var7 * 3.1415927410125732
      86 [-]: MULK R5 R6 K19; var5 = var6 * 6
      87 [-]: FASTCALL1 24 R5 L2; 
      88 [-]: GETIMPORT R4 23; var4 = 0x5BCED4C4[0x3EDA26FC]
      89 [-]: CALL R4 2 2  ; var4 = var4(var5)
L 2:  90 [-]: FASTCALL1 2 R4 L3; 
      91 [-]: GETIMPORT R3 25; var3 = 0x5BCED4C4[0xE4A5B3CA]
      92 [-]: CALL R3 2 2  ; var3 = var3(var4)
L 3:  93 [-]: GETTABLEKS R5 R1 K12; var5 = var1["PrevProp"]
      94 [-]: SUB R4 R3 R5 ; var4 = var3 - var5
      95 [-]: LOADN R5 1   ; var5 = 1
      96 [-]: LOADN R6 0   ; var6 = 0
      97 [-]: JUMPIFNOTLT R4 R6 L4; goto L4 if var4 >= var-64208
      98 [-]: LOADN R5 -1  ; var5 = -1
L 4:  99 [-]: GETTABLEKS R6 R1 K13; var6 = var1["Direction"]
     100 [-]: JUMPIFEQ R6 R5 L6; goto L6 if var6 == var525622
     101 [-]: JUMPXEQKN R5 K17 L5 NOT; 
     102 [-]: GETIMPORT R6 27; var6 = 0xC163F229
     103 [-]: LOADN R7 -10 ; var7 = -10
     104 [-]: LOADN R8 10  ; var8 = 10
     105 [-]: CALL R6 3 2  ; var6 = var6(var7, var8)
     106 [-]: SETTABLEKS R6 R1 K15; var6["Rotation"] = var1
L 5: 107 [-]: SETTABLEKS R5 R1 K13; var5["Direction"] = var1
L 6: 108 [-]: SETTABLEKS R3 R1 K12; var3["PrevProp"] = var1
     109 [-]: GETIMPORT R6 29; var6 = 0x9BAFFFE3
     110 [-]: LOADN R7 25  ; var7 = 25
     111 [-]: LOADN R8 -20 ; var8 = -20
     112 [-]: FASTCALL2K 21 R3 K30 L7; 
     113 [-]: MOVE R10 R3  ; var10 = var3
     114 [-]: LOADK R11 K30; var11 = 3
     115 [-]: GETIMPORT R9 32; var9 = 0x5BCED4C4[0xA40531D8]
     116 [-]: CALL R9 3 2  ; var9 = var9(var10, var11)
L 7: 117 [-]: CALL R6 4 2  ; var6 = var6(var7, var8, var9)
     118 [-]: GETIMPORT R7 29; var7 = 0x9BAFFFE3
     119 [-]: LOADN R8 90  ; var8 = 90
     120 [-]: LOADN R9 160 ; var9 = 160
     121 [-]: FASTCALL2K 21 R3 K33 L8; 
     122 [-]: MOVE R11 R3  ; var11 = var3
     123 [-]: LOADK R12 K33; var12 = 4
     124 [-]: GETIMPORT R10 32; var10 = 0x5BCED4C4[0xA40531D8]
     125 [-]: CALL R10 3 2 ; var10 = var10(var11, var12)
L 8: 126 [-]: CALL R7 4 2  ; var7 = var7(var8, var9, var10)
     127 [-]: GETIMPORT R8 29; var8 = 0x9BAFFFE3
     128 [-]: LOADN R9 0   ; var9 = 0
     129 [-]: GETTABLEKS R10 R1 K15; var10 = var1["Rotation"]
     130 [-]: MOVE R11 R3  ; var11 = var3
     131 [-]: CALL R8 4 2  ; var8 = var8(var9, var10, var11)
     132 [-]: GETIMPORT R9 3; var9 = 0xAE91E43B
     133 [-]: MOVE R11 R2  ; var11 = var2
     134 [-]: LOADN R12 1  ; var12 = 1
     135 [-]: MOVE R13 R6  ; var13 = var6
     136 [-]: NAMECALL R9 R9 K34; var10 = var9; var9 = var9[0x67BC869F]
     137 [-]: CALL R9 5 1  ; var9(var10, var11, var12, var13)
     138 [-]: GETIMPORT R9 3; var9 = 0xAE91E43B
     139 [-]: MOVE R11 R2  ; var11 = var2
     140 [-]: LOADN R12 6  ; var12 = 6
     141 [-]: MOVE R13 R7  ; var13 = var7
     142 [-]: NAMECALL R9 R9 K34; var10 = var9; var9 = var9[0x67BC869F]
     143 [-]: CALL R9 5 1  ; var9(var10, var11, var12, var13)
     144 [-]: GETIMPORT R9 3; var9 = 0xAE91E43B
     145 [-]: MOVE R11 R2  ; var11 = var2
     146 [-]: LOADN R12 14 ; var12 = 14
     147 [-]: MOVE R13 R8  ; var13 = var8
     148 [-]: NAMECALL R9 R9 K34; var10 = var9; var9 = var9[0x67BC869F]
     149 [-]: CALL R9 5 1  ; var9(var10, var11, var12, var13)
     150 [-]: RETURN R0 0  ; 
L 9: 151 [-]: GETIMPORT R3 29; var3 = 0x9BAFFFE3
     152 [-]: LOADN R4 100 ; var4 = 100
     153 [-]: LOADN R5 120 ; var5 = 120
     154 [-]: GETTABLEKS R9 R1 K11; var9 = var1["Life"]
     155 [-]: MULK R8 R9 K35; var8 = var9 * 40
     156 [-]: FASTCALL1 24 R8 L10; 
     157 [-]: GETIMPORT R7 23; var7 = 0x5BCED4C4[0x3EDA26FC]
     158 [-]: CALL R7 2 2  ; var7 = var7(var8)
L10: 159 [-]: FASTCALL1 2 R7 L11; 
     160 [-]: GETIMPORT R6 25; var6 = 0x5BCED4C4[0xE4A5B3CA]
     161 [-]: CALL R6 2 2  ; var6 = var6(var7)
L11: 162 [-]: CALL R3 4 2  ; var3 = var3(var4, var5, var6)
     163 [-]: GETIMPORT R4 3; var4 = 0xAE91E43B
     164 [-]: MOVE R6 R2   ; var6 = var2
     165 [-]: LOADN R7 6   ; var7 = 6
     166 [-]: MOVE R8 R3   ; var8 = var3
     167 [-]: NAMECALL R4 R4 K34; var5 = var4; var4 = var4[0x67BC869F]
     168 [-]: CALL R4 5 1  ; var4(var5, var6, var7, var8)
     169 [-]: GETIMPORT R4 3; var4 = 0xAE91E43B
     170 [-]: MOVE R6 R2   ; var6 = var2
     171 [-]: LOADN R7 14  ; var7 = 14
     172 [-]: LOADN R8 0   ; var8 = 0
     173 [-]: NAMECALL R4 R4 K34; var5 = var4; var4 = var4[0x67BC869F]
     174 [-]: CALL R4 5 1  ; var4(var5, var6, var7, var8)
     175 [-]: RETURN R0 0  ; 


; Name:            
; Defined at line: 413
; #Upvalues:       1
; #Parameters:     2
; Is_vararg:       0
; Max Stack Size:  14

       0 [-]: GETTABLEKS R2 R1 K0; var2 = var1["Initialized"]
       1 [-]: JUMPIF R2 L0 ; goto L0 if var2
       2 [-]: LOADB R2 1   ; var2 = true
       3 [-]: SETTABLEKS R2 R1 K0; var2["Initialized"] = var1
       4 [-]: GETUPVAL R2 0; var2 = upvalues[0]
       5 [-]: GETTABLEKS R3 R1 K1; var3 = var1["mClipName"]
       6 [-]: CALL R2 2 1  ; var2(var3)
       7 [-]: NEWTABLE R2 0 0; var2 = {}
       8 [-]: SETTABLEKS R2 R1 K2; var2["Life"] = var1
       9 [-]: GETTABLEKS R2 R1 K2; var2 = var1["Life"]
      10 [-]: LOADK R3 K3  ; var3 = 0.33000001311302185
      11 [-]: SETTABLEN R3 R2 1; SETTABLEN R3 R2 1
      12 [-]: GETTABLEKS R2 R1 K2; var2 = var1["Life"]
      13 [-]: LOADK R3 K4  ; var3 = 0.6600000262260437
      14 [-]: SETTABLEN R3 R2 2; SETTABLEN R3 R2 2
      15 [-]: GETTABLEKS R2 R1 K2; var2 = var1["Life"]
      16 [-]: LOADK R3 K5  ; var3 = 0.99000000953674316
      17 [-]: SETTABLEN R3 R2 3; SETTABLEN R3 R2 3
L 0:  18 [-]: LOADN R4 1   ; var4 = 1
      19 [-]: LOADN R2 3   ; var2 = 3
      20 [-]: LOADN R3 1   ; var3 = 1
      21 [-]: FORNPREP R2 L4; nforprep start - [escape at L4] -- var2 = iterator
L 1:  22 [-]: GETTABLEKS R5 R1 K2; var5 = var1["Life"]
      23 [-]: GETTABLEKS R8 R1 K2; var8 = var1["Life"]
      24 [-]: GETTABLE R7 R8 R4; var7 = var8[var4]
      25 [-]: MULK R8 R0 K6; var8 = var0 * 0.75
      26 [-]: ADD R6 R7 R8 ; var6 = var7 + var8
      27 [-]: SETTABLE R6 R5 R4; var6[var5] = var4
      28 [-]: GETTABLEKS R6 R1 K2; var6 = var1["Life"]
      29 [-]: GETTABLE R5 R6 R4; var5 = var6[var4]
      30 [-]: LOADN R6 1   ; var6 = 1
      31 [-]: JUMPIFNOTLT R6 R5 L2; goto L2 if var6 >= var-1191115457
      32 [-]: GETTABLEKS R5 R1 K2; var5 = var1["Life"]
      33 [-]: GETTABLEKS R8 R1 K2; var8 = var1["Life"]
      34 [-]: GETTABLE R7 R8 R4; var7 = var8[var4]
      35 [-]: SUBK R6 R7 K7; var6 = var7 - 1
      36 [-]: SETTABLE R6 R5 R4; var6[var5] = var4
L 2:  37 [-]: GETTABLEKS R6 R1 K1; var6 = var1["mClipName"]
      38 [-]: LOADK R7 K8  ; var7 = ".Text"
      39 [-]: MOVE R8 R4   ; var8 = var4
      40 [-]: CONCAT R5 R6 R8; var5 = var6 .. var8
      41 [-]: GETIMPORT R6 10; var6 = 0x9BAFFFE3
      42 [-]: LOADN R7 80  ; var7 = 80
      43 [-]: LOADN R8 400 ; var8 = 400
      44 [-]: GETTABLEKS R10 R1 K2; var10 = var1["Life"]
      45 [-]: GETTABLE R9 R10 R4; var9 = var10[var4]
      46 [-]: CALL R6 4 2  ; var6 = var6(var7, var8, var9)
      47 [-]: GETIMPORT R7 12; var7 = 0xAE91E43B
      48 [-]: MOVE R9 R5   ; var9 = var5
      49 [-]: LOADN R10 5  ; var10 = 5
      50 [-]: MOVE R11 R6  ; var11 = var6
      51 [-]: NAMECALL R7 R7 K13; var8 = var7; var7 = var7[0x67BC869F]
      52 [-]: CALL R7 5 1  ; var7(var8, var9, var10, var11)
      53 [-]: GETIMPORT R7 12; var7 = 0xAE91E43B
      54 [-]: MOVE R9 R5   ; var9 = var5
      55 [-]: LOADN R10 6  ; var10 = 6
      56 [-]: MOVE R11 R6  ; var11 = var6
      57 [-]: NAMECALL R7 R7 K13; var8 = var7; var7 = var7[0x67BC869F]
      58 [-]: CALL R7 5 1  ; var7(var8, var9, var10, var11)
      59 [-]: LOADN R8 100 ; var8 = 100
      60 [-]: LOADN R11 1  ; var11 = 1
      61 [-]: GETTABLEKS R13 R1 K2; var13 = var1["Life"]
      62 [-]: GETTABLE R12 R13 R4; var12 = var13[var4]
      63 [-]: SUB R10 R11 R12; var10 = var11 - var12
      64 [-]: FASTCALL2K 21 R10 K14 L3; 
      65 [-]: LOADK R11 K14; var11 = 3
      66 [-]: GETIMPORT R9 17; var9 = 0x5BCED4C4[0xA40531D8]
      67 [-]: CALL R9 3 2  ; var9 = var9(var10, var11)
L 3:  68 [-]: MUL R7 R8 R9 ; var7 = var8 * var9
      69 [-]: GETIMPORT R8 12; var8 = 0xAE91E43B
      70 [-]: MOVE R10 R5  ; var10 = var5
      71 [-]: LOADN R11 10 ; var11 = 10
      72 [-]: MOVE R12 R7  ; var12 = var7
      73 [-]: NAMECALL R8 R8 K13; var9 = var8; var8 = var8[0x67BC869F]
      74 [-]: CALL R8 5 1  ; var8(var9, var10, var11, var12)
      75 [-]: FORNLOOP R2 L1; nforloop end - iterate + goto L1
L 4:  76 [-]: RETURN R0 0  ; 


; Name:            
; Defined at line: 441
; #Upvalues:       1
; #Parameters:     2
; Is_vararg:       0
; Max Stack Size:  14

       0 [-]: GETTABLEKS R2 R1 K0; var2 = var1["Initialized"]
       1 [-]: JUMPIF R2 L0 ; goto L0 if var2
       2 [-]: LOADB R2 1   ; var2 = true
       3 [-]: SETTABLEKS R2 R1 K0; var2["Initialized"] = var1
       4 [-]: GETUPVAL R2 0; var2 = upvalues[0]
       5 [-]: GETTABLEKS R3 R1 K1; var3 = var1["mClipName"]
       6 [-]: CALL R2 2 1  ; var2(var3)
       7 [-]: NEWTABLE R2 0 0; var2 = {}
       8 [-]: SETTABLEKS R2 R1 K2; var2["BackerTransformDelay"] = var1
       9 [-]: GETTABLEKS R2 R1 K2; var2 = var1["BackerTransformDelay"]
      10 [-]: LOADN R3 0   ; var3 = 0
      11 [-]: SETTABLEN R3 R2 1; SETTABLEN R3 R2 1
      12 [-]: GETTABLEKS R2 R1 K2; var2 = var1["BackerTransformDelay"]
      13 [-]: LOADN R3 0   ; var3 = 0
      14 [-]: SETTABLEN R3 R2 2; SETTABLEN R3 R2 2
      15 [-]: GETTABLEKS R2 R1 K2; var2 = var1["BackerTransformDelay"]
      16 [-]: LOADN R3 0   ; var3 = 0
      17 [-]: SETTABLEN R3 R2 3; SETTABLEN R3 R2 3
L 0:  18 [-]: LOADN R4 1   ; var4 = 1
      19 [-]: LOADN R2 3   ; var2 = 3
      20 [-]: LOADN R3 1   ; var3 = 1
      21 [-]: FORNPREP R2 L4; nforprep start - [escape at L4] -- var2 = iterator
L 1:  22 [-]: GETTABLEKS R6 R1 K2; var6 = var1["BackerTransformDelay"]
      23 [-]: GETTABLE R5 R6 R4; var5 = var6[var4]
      24 [-]: LOADN R6 0   ; var6 = 0
      25 [-]: JUMPIFNOTLT R5 R6 L2; goto L2 if var5 >= var-285145793
      26 [-]: GETTABLEKS R5 R1 K2; var5 = var1["BackerTransformDelay"]
      27 [-]: GETIMPORT R6 4; var6 = 0xC163F229
      28 [-]: LOADK R7 K5  ; var7 = 0.10000000149011612
      29 [-]: LOADK R8 K6  ; var8 = 0.5
      30 [-]: CALL R6 3 2  ; var6 = var6(var7, var8)
      31 [-]: SETTABLE R6 R5 R4; var6[var5] = var4
      32 [-]: GETIMPORT R5 4; var5 = 0xC163F229
      33 [-]: LOADN R6 100 ; var6 = 100
      34 [-]: LOADN R7 200 ; var7 = 200
      35 [-]: CALL R5 3 2  ; var5 = var5(var6, var7)
      36 [-]: GETTABLEKS R7 R1 K1; var7 = var1["mClipName"]
      37 [-]: LOADK R8 K7  ; var8 = ".Text"
      38 [-]: MOVE R9 R4   ; var9 = var4
      39 [-]: CONCAT R6 R7 R9; var6 = var7 .. var9
      40 [-]: GETIMPORT R7 9; var7 = 0xAE91E43B
      41 [-]: MOVE R9 R6   ; var9 = var6
      42 [-]: LOADN R10 5  ; var10 = 5
      43 [-]: MOVE R11 R5  ; var11 = var5
      44 [-]: NAMECALL R7 R7 K10; var8 = var7; var7 = var7[0x67BC869F]
      45 [-]: CALL R7 5 1  ; var7(var8, var9, var10, var11)
      46 [-]: GETIMPORT R7 9; var7 = 0xAE91E43B
      47 [-]: MOVE R9 R6   ; var9 = var6
      48 [-]: LOADN R10 6  ; var10 = 6
      49 [-]: MOVE R11 R5  ; var11 = var5
      50 [-]: NAMECALL R7 R7 K10; var8 = var7; var7 = var7[0x67BC869F]
      51 [-]: CALL R7 5 1  ; var7(var8, var9, var10, var11)
      52 [-]: GETIMPORT R7 9; var7 = 0xAE91E43B
      53 [-]: MOVE R9 R6   ; var9 = var6
      54 [-]: LOADN R10 0  ; var10 = 0
      55 [-]: GETIMPORT R11 4; var11 = 0xC163F229
      56 [-]: LOADN R12 -30; var12 = -30
      57 [-]: LOADN R13 30 ; var13 = 30
      58 [-]: CALL R11 3 0 ; var11, ... = var11(var12, var13)
      59 [-]: NAMECALL R7 R7 K10; var8 = var7; var7 = var7[0x67BC869F]
      60 [-]: CALL R7 0 1  ; var7(var8, ...)
      61 [-]: GETIMPORT R7 9; var7 = 0xAE91E43B
      62 [-]: MOVE R9 R6   ; var9 = var6
      63 [-]: LOADN R10 1  ; var10 = 1
      64 [-]: GETIMPORT R11 4; var11 = 0xC163F229
      65 [-]: LOADN R12 -15; var12 = -15
      66 [-]: LOADN R13 15 ; var13 = 15
      67 [-]: CALL R11 3 0 ; var11, ... = var11(var12, var13)
      68 [-]: NAMECALL R7 R7 K10; var8 = var7; var7 = var7[0x67BC869F]
      69 [-]: CALL R7 0 1  ; var7(var8, ...)
      70 [-]: GETIMPORT R7 9; var7 = 0xAE91E43B
      71 [-]: MOVE R9 R6   ; var9 = var6
      72 [-]: LOADN R10 10 ; var10 = 10
      73 [-]: GETIMPORT R11 4; var11 = 0xC163F229
      74 [-]: LOADN R12 1  ; var12 = 1
      75 [-]: LOADN R13 20 ; var13 = 20
      76 [-]: CALL R11 3 0 ; var11, ... = var11(var12, var13)
      77 [-]: NAMECALL R7 R7 K10; var8 = var7; var7 = var7[0x67BC869F]
      78 [-]: CALL R7 0 1  ; var7(var8, ...)
      79 [-]: JUMP L3      ; goto L3
L 2:  80 [-]: GETTABLEKS R5 R1 K2; var5 = var1["BackerTransformDelay"]
      81 [-]: GETTABLEKS R8 R1 K2; var8 = var1["BackerTransformDelay"]
      82 [-]: GETTABLE R7 R8 R4; var7 = var8[var4]
      83 [-]: SUB R6 R7 R0 ; var6 = var7 - var0
      84 [-]: SETTABLE R6 R5 R4; var6[var5] = var4
L 3:  85 [-]: FORNLOOP R2 L1; nforloop end - iterate + goto L1
L 4:  86 [-]: RETURN R0 0  ; 


; Name:            
; Defined at line: 468
; #Upvalues:       2
; #Parameters:     2
; Is_vararg:       0
; Max Stack Size:  21

       0 [-]: GETTABLEKS R3 R1 K0; var3 = var1["mClipName"]
       1 [-]: LOADK R4 K1  ; var4 = ".Text3"
       2 [-]: CONCAT R2 R3 R4; var2 = var3 .. var4
       3 [-]: GETTABLEKS R3 R1 K2; var3 = var1["Initialized"]
       4 [-]: JUMPIF R3 L4 ; goto L4 if var3
       5 [-]: LOADB R3 1   ; var3 = true
       6 [-]: SETTABLEKS R3 R1 K2; var3["Initialized"] = var1
       7 [-]: GETUPVAL R3 0; var3 = upvalues[0]
       8 [-]: GETTABLEKS R4 R1 K0; var4 = var1["mClipName"]
       9 [-]: CALL R3 2 1  ; var3(var4)
      10 [-]: GETUPVAL R4 1; var4 = upvalues[1]
      11 [-]: GETTABLEKS R3 R4 K3; var3 = var4[0xB5BE5D4A]
      12 [-]: GETIMPORT R4 5; var4 = 0xAE91E43B
      13 [-]: GETTABLEKS R5 R1 K0; var5 = var1["mClipName"]
      14 [-]: CALL R3 3 3  ; var3, var4 = var3(var4, var5)
      15 [-]: GETIMPORT R5 7; var5 = 0xC163F229
      16 [-]: LOADN R6 1   ; var6 = 1
      17 [-]: LOADN R7 30  ; var7 = 30
      18 [-]: CALL R5 3 2  ; var5 = var5(var6, var7)
      19 [-]: SETTABLEKS R5 R1 K8; var5["NoiseOffset"] = var1
      20 [-]: LOADN R7 1   ; var7 = 1
      21 [-]: LOADN R5 2   ; var5 = 2
      22 [-]: LOADN R6 1   ; var6 = 1
      23 [-]: FORNPREP R5 L3; nforprep start - [escape at L3] -- var5 = iterator
L 0:  24 [-]: GETTABLEKS R9 R1 K0; var9 = var1["mClipName"]
      25 [-]: LOADK R10 K9 ; var10 = ".Text"
      26 [-]: MOVE R11 R7  ; var11 = var7
      27 [-]: CONCAT R8 R9 R11; var8 = var9 .. var11
      28 [-]: MOVE R10 R8  ; var10 = var8
      29 [-]: LOADK R11 K10; var11 = ".Label"
      30 [-]: CONCAT R9 R10 R11; var9 = var10 .. var11
      31 [-]: GETIMPORT R10 5; var10 = 0xAE91E43B
      32 [-]: MOVE R12 R9  ; var12 = var9
      33 [-]: GETIMPORT R14 12; var14 = 0x0032441C
      34 [-]: GETTABLEKS R13 R14 K13; var13 = var14["UIMaterial_VerticalVisibilityRangeText"]
      35 [-]: NAMECALL R10 R10 K14; var11 = var10; var10 = var10[0xD5181643]
      36 [-]: CALL R10 4 1 ; var10(var11, var12, var13)
      37 [-]: GETIMPORT R10 5; var10 = 0xAE91E43B
      38 [-]: MOVE R12 R9  ; var12 = var9
      39 [-]: LOADK R13 K15; var13 = "VisibilityFadeSize"
      40 [-]: GETUPVAL R15 1; var15 = upvalues[1]
      41 [-]: GETTABLEKS R14 R15 K16; var14 = var15[0xD718F59B]
      42 [-]: GETIMPORT R15 5; var15 = 0xAE91E43B
      43 [-]: LOADN R16 1  ; var16 = 1
      44 [-]: CALL R14 3 2 ; var14 = var14(var15, var16)
      45 [-]: LOADN R15 0  ; var15 = 0
      46 [-]: LOADN R16 0  ; var16 = 0
      47 [-]: LOADN R17 0  ; var17 = 0
      48 [-]: NAMECALL R10 R10 K17; var11 = var10; var10 = var10[0x91E13703]
      49 [-]: CALL R10 8 1 ; var10(var11, var12, var13, var14, var15, var16, var17)
      50 [-]: GETIMPORT R10 5; var10 = 0xAE91E43B
      51 [-]: MOVE R12 R9  ; var12 = var9
      52 [-]: LOADK R13 K18; var13 = "VisibilitySize"
      53 [-]: GETUPVAL R15 1; var15 = upvalues[1]
      54 [-]: GETTABLEKS R14 R15 K16; var14 = var15[0xD718F59B]
      55 [-]: GETIMPORT R15 5; var15 = 0xAE91E43B
      56 [-]: LOADN R16 36 ; var16 = 36
      57 [-]: CALL R14 3 2 ; var14 = var14(var15, var16)
      58 [-]: LOADN R15 0  ; var15 = 0
      59 [-]: LOADN R16 0  ; var16 = 0
      60 [-]: LOADN R17 0  ; var17 = 0
      61 [-]: NAMECALL R10 R10 K17; var11 = var10; var10 = var10[0x91E13703]
      62 [-]: CALL R10 8 1 ; var10(var11, var12, var13, var14, var15, var16, var17)
      63 [-]: GETIMPORT R10 5; var10 = 0xAE91E43B
      64 [-]: MOVE R12 R9  ; var12 = var9
      65 [-]: LOADK R13 K19; var13 = "VisibilityCenter"
      66 [-]: GETUPVAL R15 1; var15 = upvalues[1]
      67 [-]: GETTABLEKS R14 R15 K20; var14 = var15[0xE5E5A417]
      68 [-]: GETIMPORT R15 5; var15 = 0xAE91E43B
      69 [-]: GETUPVAL R18 1; var18 = upvalues[1]
      70 [-]: GETTABLEKS R17 R18 K21; var17 = var18[0x06D055F9]
      71 [-]: JUMPXEQKN R7 K22 L1; 
      72 [-]: LOADB R18 0 +1; var18 = false
L 1:  73 [-]: LOADB R18 1  ; var18 = true
L 2:  74 [-]: LOADN R19 -20; var19 = -20
      75 [-]: LOADN R20 20 ; var20 = 20
      76 [-]: CALL R17 4 2 ; var17 = var17(var18, var19, var20)
      77 [-]: ADD R16 R4 R17; var16 = var4 + var17
      78 [-]: CALL R14 3 2 ; var14 = var14(var15, var16)
      79 [-]: LOADN R15 0  ; var15 = 0
      80 [-]: LOADN R16 0  ; var16 = 0
      81 [-]: LOADN R17 0  ; var17 = 0
      82 [-]: NAMECALL R10 R10 K17; var11 = var10; var10 = var10[0x91E13703]
      83 [-]: CALL R10 8 1 ; var10(var11, var12, var13, var14, var15, var16, var17)
      84 [-]: FORNLOOP R5 L0; nforloop end - iterate + goto L0
L 3:  85 [-]: GETIMPORT R5 5; var5 = 0xAE91E43B
      86 [-]: MOVE R7 R2   ; var7 = var2
      87 [-]: LOADN R8 10  ; var8 = 10
      88 [-]: LOADN R9 5   ; var9 = 5
      89 [-]: NAMECALL R5 R5 K23; var6 = var5; var5 = var5[0x67BC869F]
      90 [-]: CALL R5 5 1  ; var5(var6, var7, var8, var9)
L 4:  91 [-]: GETIMPORT R3 25; var3 = 0xF7F90318
      92 [-]: GETTABLEKS R5 R1 K8; var5 = var1["NoiseOffset"]
      93 [-]: GETIMPORT R7 28; var7 = 0x55156FF7
      94 [-]: CALL R7 1 2  ; var7 = var7()
      95 [-]: MULK R6 R7 K26; var6 = var7 * 0.059999998658895493
      96 [-]: ADD R4 R5 R6 ; var4 = var5 + var6
      97 [-]: CALL R3 2 2  ; var3 = var3(var4)
      98 [-]: GETIMPORT R4 25; var4 = 0xF7F90318
      99 [-]: GETTABLEKS R6 R1 K8; var6 = var1["NoiseOffset"]
     100 [-]: GETIMPORT R8 28; var8 = 0x55156FF7
     101 [-]: CALL R8 1 2  ; var8 = var8()
     102 [-]: MULK R7 R8 K29; var7 = var8 * 0.019999999552965164
     103 [-]: ADD R5 R6 R7 ; var5 = var6 + var7
     104 [-]: CALL R4 2 2  ; var4 = var4(var5)
     105 [-]: GETIMPORT R5 5; var5 = 0xAE91E43B
     106 [-]: GETTABLEKS R7 R1 K0; var7 = var1["mClipName"]
     107 [-]: LOADK R8 K30 ; var8 = "Text1"
     108 [-]: LOADN R9 0   ; var9 = 0
     109 [-]: MULK R10 R3 K31; var10 = var3 * 90
     110 [-]: NAMECALL R5 R5 K32; var6 = var5; var5 = var5[0xF64B7262]
     111 [-]: CALL R5 6 1  ; var5(var6, var7, var8, var9, var10)
     112 [-]: GETIMPORT R5 5; var5 = 0xAE91E43B
     113 [-]: GETTABLEKS R7 R1 K0; var7 = var1["mClipName"]
     114 [-]: LOADK R8 K33 ; var8 = "Text2"
     115 [-]: LOADN R9 0   ; var9 = 0
     116 [-]: MULK R10 R4 K34; var10 = var4 * 130
     117 [-]: NAMECALL R5 R5 K32; var6 = var5; var5 = var5[0xF64B7262]
     118 [-]: CALL R5 6 1  ; var5(var6, var7, var8, var9, var10)
     119 [-]: GETIMPORT R5 25; var5 = 0xF7F90318
     120 [-]: GETTABLEKS R7 R1 K8; var7 = var1["NoiseOffset"]
     121 [-]: GETIMPORT R9 28; var9 = 0x55156FF7
     122 [-]: CALL R9 1 2  ; var9 = var9()
     123 [-]: MULK R8 R9 K35; var8 = var9 * 2.4000000953674316
     124 [-]: ADD R6 R7 R8 ; var6 = var7 + var8
     125 [-]: CALL R5 2 2  ; var5 = var5(var6)
     126 [-]: GETIMPORT R6 25; var6 = 0xF7F90318
     127 [-]: GETTABLEKS R8 R1 K8; var8 = var1["NoiseOffset"]
     128 [-]: GETIMPORT R10 28; var10 = 0x55156FF7
     129 [-]: CALL R10 1 2 ; var10 = var10()
     130 [-]: MULK R9 R10 K36; var9 = var10 * 2.25
     131 [-]: ADD R7 R8 R9 ; var7 = var8 + var9
     132 [-]: CALL R6 2 2  ; var6 = var6(var7)
     133 [-]: LOADN R8 250 ; var8 = 250
     134 [-]: GETIMPORT R10 25; var10 = 0xF7F90318
     135 [-]: GETTABLEKS R12 R1 K8; var12 = var1["NoiseOffset"]
     136 [-]: GETIMPORT R14 28; var14 = 0x55156FF7
     137 [-]: CALL R14 1 2 ; var14 = var14()
     138 [-]: MULK R13 R14 K38; var13 = var14 * 1.25
     139 [-]: ADD R11 R12 R13; var11 = var12 + var13
     140 [-]: CALL R10 2 2 ; var10 = var10(var11)
     141 [-]: MULK R9 R10 K37; var9 = var10 * 15
     142 [-]: ADD R7 R8 R9 ; var7 = var8 + var9
     143 [-]: GETIMPORT R8 5; var8 = 0xAE91E43B
     144 [-]: MOVE R10 R2  ; var10 = var2
     145 [-]: LOADN R11 5  ; var11 = 5
     146 [-]: MOVE R12 R7  ; var12 = var7
     147 [-]: NAMECALL R8 R8 K23; var9 = var8; var8 = var8[0x67BC869F]
     148 [-]: CALL R8 5 1  ; var8(var9, var10, var11, var12)
     149 [-]: GETIMPORT R8 5; var8 = 0xAE91E43B
     150 [-]: MOVE R10 R2  ; var10 = var2
     151 [-]: LOADN R11 6  ; var11 = 6
     152 [-]: MOVE R12 R7  ; var12 = var7
     153 [-]: NAMECALL R8 R8 K23; var9 = var8; var8 = var8[0x67BC869F]
     154 [-]: CALL R8 5 1  ; var8(var9, var10, var11, var12)
     155 [-]: GETIMPORT R8 5; var8 = 0xAE91E43B
     156 [-]: MOVE R10 R2  ; var10 = var2
     157 [-]: LOADN R11 0  ; var11 = 0
     158 [-]: MULK R12 R5 K37; var12 = var5 * 15
     159 [-]: NAMECALL R8 R8 K23; var9 = var8; var8 = var8[0x67BC869F]
     160 [-]: CALL R8 5 1  ; var8(var9, var10, var11, var12)
     161 [-]: GETIMPORT R8 5; var8 = 0xAE91E43B
     162 [-]: MOVE R10 R2  ; var10 = var2
     163 [-]: LOADN R11 1  ; var11 = 1
     164 [-]: MULK R12 R6 K37; var12 = var6 * 15
     165 [-]: NAMECALL R8 R8 K23; var9 = var8; var8 = var8[0x67BC869F]
     166 [-]: CALL R8 5 1  ; var8(var9, var10, var11, var12)
     167 [-]: RETURN R0 0  ; 


; Name:            
; Defined at line: 504
; #Upvalues:       2
; #Parameters:     2
; Is_vararg:       0
; Max Stack Size:  14

       0 [-]: GETTABLEKS R3 R1 K0; var3 = var1["mClipName"]
       1 [-]: LOADK R4 K1  ; var4 = ".Text3"
       2 [-]: CONCAT R2 R3 R4; var2 = var3 .. var4
       3 [-]: GETTABLEKS R3 R1 K2; var3 = var1["Initialized"]
       4 [-]: JUMPIF R3 L2 ; goto L2 if var3
       5 [-]: LOADB R3 1   ; var3 = true
       6 [-]: SETTABLEKS R3 R1 K2; var3["Initialized"] = var1
       7 [-]: GETUPVAL R3 0; var3 = upvalues[0]
       8 [-]: GETTABLEKS R4 R1 K0; var4 = var1["mClipName"]
       9 [-]: CALL R3 2 1  ; var3(var4)
      10 [-]: GETUPVAL R4 1; var4 = upvalues[1]
      11 [-]: GETTABLEKS R3 R4 K3; var3 = var4[0xB5BE5D4A]
      12 [-]: GETIMPORT R4 5; var4 = 0xAE91E43B
      13 [-]: GETTABLEKS R5 R1 K0; var5 = var1["mClipName"]
      14 [-]: CALL R3 3 3  ; var3, var4 = var3(var4, var5)
      15 [-]: GETIMPORT R5 7; var5 = 0xC163F229
      16 [-]: LOADN R6 1   ; var6 = 1
      17 [-]: LOADN R7 30  ; var7 = 30
      18 [-]: CALL R5 3 2  ; var5 = var5(var6, var7)
      19 [-]: SETTABLEKS R5 R1 K8; var5["NoiseOffset"] = var1
      20 [-]: LOADN R7 1   ; var7 = 1
      21 [-]: LOADN R5 2   ; var5 = 2
      22 [-]: LOADN R6 1   ; var6 = 1
      23 [-]: FORNPREP R5 L1; nforprep start - [escape at L1] -- var5 = iterator
L 0:  24 [-]: GETTABLEKS R9 R1 K0; var9 = var1["mClipName"]
      25 [-]: LOADK R10 K9 ; var10 = ".Text"
      26 [-]: MOVE R11 R7  ; var11 = var7
      27 [-]: CONCAT R8 R9 R11; var8 = var9 .. var11
      28 [-]: GETIMPORT R9 5; var9 = 0xAE91E43B
      29 [-]: MOVE R11 R8  ; var11 = var8
      30 [-]: LOADN R12 5  ; var12 = 5
      31 [-]: LOADN R13 150; var13 = 150
      32 [-]: NAMECALL R9 R9 K10; var10 = var9; var9 = var9[0x67BC869F]
      33 [-]: CALL R9 5 1  ; var9(var10, var11, var12, var13)
      34 [-]: GETIMPORT R9 5; var9 = 0xAE91E43B
      35 [-]: MOVE R11 R8  ; var11 = var8
      36 [-]: LOADN R12 6  ; var12 = 6
      37 [-]: LOADN R13 150; var13 = 150
      38 [-]: NAMECALL R9 R9 K10; var10 = var9; var9 = var9[0x67BC869F]
      39 [-]: CALL R9 5 1  ; var9(var10, var11, var12, var13)
      40 [-]: FORNLOOP R5 L0; nforloop end - iterate + goto L0
L 1:  41 [-]: GETIMPORT R5 5; var5 = 0xAE91E43B
      42 [-]: GETTABLEKS R7 R1 K0; var7 = var1["mClipName"]
      43 [-]: LOADK R8 K11 ; var8 = "Text2"
      44 [-]: LOADN R9 10  ; var9 = 10
      45 [-]: LOADN R10 30 ; var10 = 30
      46 [-]: NAMECALL R5 R5 K12; var6 = var5; var5 = var5[0xF64B7262]
      47 [-]: CALL R5 6 1  ; var5(var6, var7, var8, var9, var10)
      48 [-]: GETIMPORT R5 5; var5 = 0xAE91E43B
      49 [-]: MOVE R7 R2   ; var7 = var2
      50 [-]: LOADN R8 5   ; var8 = 5
      51 [-]: LOADN R9 300 ; var9 = 300
      52 [-]: NAMECALL R5 R5 K10; var6 = var5; var5 = var5[0x67BC869F]
      53 [-]: CALL R5 5 1  ; var5(var6, var7, var8, var9)
      54 [-]: GETIMPORT R5 5; var5 = 0xAE91E43B
      55 [-]: MOVE R7 R2   ; var7 = var2
      56 [-]: LOADN R8 6   ; var8 = 6
      57 [-]: LOADN R9 300 ; var9 = 300
      58 [-]: NAMECALL R5 R5 K10; var6 = var5; var5 = var5[0x67BC869F]
      59 [-]: CALL R5 5 1  ; var5(var6, var7, var8, var9)
      60 [-]: GETIMPORT R5 5; var5 = 0xAE91E43B
      61 [-]: MOVE R7 R2   ; var7 = var2
      62 [-]: LOADN R8 10  ; var8 = 10
      63 [-]: LOADN R9 25  ; var9 = 25
      64 [-]: NAMECALL R5 R5 K10; var6 = var5; var5 = var5[0x67BC869F]
      65 [-]: CALL R5 5 1  ; var5(var6, var7, var8, var9)
L 2:  66 [-]: GETIMPORT R3 14; var3 = 0xF7F90318
      67 [-]: GETTABLEKS R5 R1 K8; var5 = var1["NoiseOffset"]
      68 [-]: GETIMPORT R7 17; var7 = 0x55156FF7
      69 [-]: CALL R7 1 2  ; var7 = var7()
      70 [-]: MULK R6 R7 K15; var6 = var7 * 0.059999998658895493
      71 [-]: ADD R4 R5 R6 ; var4 = var5 + var6
      72 [-]: CALL R3 2 2  ; var3 = var3(var4)
      73 [-]: GETIMPORT R4 14; var4 = 0xF7F90318
      74 [-]: GETTABLEKS R6 R1 K8; var6 = var1["NoiseOffset"]
      75 [-]: GETIMPORT R8 17; var8 = 0x55156FF7
      76 [-]: CALL R8 1 2  ; var8 = var8()
      77 [-]: MULK R7 R8 K18; var7 = var8 * 0.019999999552965164
      78 [-]: ADD R5 R6 R7 ; var5 = var6 + var7
      79 [-]: CALL R4 2 2  ; var4 = var4(var5)
      80 [-]: GETIMPORT R5 5; var5 = 0xAE91E43B
      81 [-]: GETTABLEKS R7 R1 K0; var7 = var1["mClipName"]
      82 [-]: LOADK R8 K19 ; var8 = "Text1"
      83 [-]: LOADN R9 0   ; var9 = 0
      84 [-]: MULK R10 R3 K20; var10 = var3 * 60
      85 [-]: NAMECALL R5 R5 K12; var6 = var5; var5 = var5[0xF64B7262]
      86 [-]: CALL R5 6 1  ; var5(var6, var7, var8, var9, var10)
      87 [-]: GETIMPORT R5 5; var5 = 0xAE91E43B
      88 [-]: GETTABLEKS R7 R1 K0; var7 = var1["mClipName"]
      89 [-]: LOADK R8 K11 ; var8 = "Text2"
      90 [-]: LOADN R9 0   ; var9 = 0
      91 [-]: MULK R10 R4 K21; var10 = var4 * 90
      92 [-]: NAMECALL R5 R5 K12; var6 = var5; var5 = var5[0xF64B7262]
      93 [-]: CALL R5 6 1  ; var5(var6, var7, var8, var9, var10)
      94 [-]: GETIMPORT R5 5; var5 = 0xAE91E43B
      95 [-]: GETTABLEKS R7 R1 K0; var7 = var1["mClipName"]
      96 [-]: LOADK R8 K19 ; var8 = "Text1"
      97 [-]: LOADN R9 10  ; var9 = 10
      98 [-]: LOADN R11 20 ; var11 = 20
      99 [-]: MULK R12 R3 K22; var12 = var3 * 80
     100 [-]: ADD R10 R11 R12; var10 = var11 + var12
     101 [-]: NAMECALL R5 R5 K12; var6 = var5; var5 = var5[0xF64B7262]
     102 [-]: CALL R5 6 1  ; var5(var6, var7, var8, var9, var10)
     103 [-]: GETIMPORT R5 5; var5 = 0xAE91E43B
     104 [-]: GETTABLEKS R7 R1 K0; var7 = var1["mClipName"]
     105 [-]: LOADK R8 K11 ; var8 = "Text2"
     106 [-]: LOADN R9 10  ; var9 = 10
     107 [-]: LOADN R11 10 ; var11 = 10
     108 [-]: MULK R12 R4 K23; var12 = var4 * 40
     109 [-]: ADD R10 R11 R12; var10 = var11 + var12
     110 [-]: NAMECALL R5 R5 K12; var6 = var5; var5 = var5[0xF64B7262]
     111 [-]: CALL R5 6 1  ; var5(var6, var7, var8, var9, var10)
     112 [-]: LOADN R6 2   ; var6 = 2
     113 [-]: GETIMPORT R8 14; var8 = 0xF7F90318
     114 [-]: GETTABLEKS R10 R1 K8; var10 = var1["NoiseOffset"]
     115 [-]: GETIMPORT R12 17; var12 = 0x55156FF7
     116 [-]: CALL R12 1 2 ; var12 = var12()
     117 [-]: MULK R11 R12 K25; var11 = var12 * 0.15000000596046448
     118 [-]: ADD R9 R10 R11; var9 = var10 + var11
     119 [-]: CALL R8 2 2  ; var8 = var8(var9)
     120 [-]: MULK R7 R8 K24; var7 = var8 * 10
     121 [-]: ADD R5 R6 R7 ; var5 = var6 + var7
     122 [-]: GETIMPORT R6 5; var6 = 0xAE91E43B
     123 [-]: MOVE R8 R2   ; var8 = var2
     124 [-]: LOADN R9 10  ; var9 = 10
     125 [-]: MOVE R10 R5  ; var10 = var5
     126 [-]: NAMECALL R6 R6 K10; var7 = var6; var6 = var6[0x67BC869F]
     127 [-]: CALL R6 5 1  ; var6(var7, var8, var9, var10)
     128 [-]: RETURN R0 0  ; 


; Name:            
; Defined at line: 538
; #Upvalues:       2
; #Parameters:     2
; Is_vararg:       0
; Max Stack Size:  15

       0 [-]: GETTABLEKS R3 R1 K0; var3 = var1["mClipName"]
       1 [-]: LOADK R4 K1  ; var4 = ".Text3"
       2 [-]: CONCAT R2 R3 R4; var2 = var3 .. var4
       3 [-]: GETTABLEKS R3 R1 K2; var3 = var1["Initialized"]
       4 [-]: JUMPIF R3 L2 ; goto L2 if var3
       5 [-]: LOADB R3 1   ; var3 = true
       6 [-]: SETTABLEKS R3 R1 K2; var3["Initialized"] = var1
       7 [-]: GETUPVAL R3 0; var3 = upvalues[0]
       8 [-]: GETTABLEKS R4 R1 K0; var4 = var1["mClipName"]
       9 [-]: CALL R3 2 1  ; var3(var4)
      10 [-]: GETUPVAL R4 1; var4 = upvalues[1]
      11 [-]: GETTABLEKS R3 R4 K3; var3 = var4[0xB5BE5D4A]
      12 [-]: GETIMPORT R4 5; var4 = 0xAE91E43B
      13 [-]: GETTABLEKS R5 R1 K0; var5 = var1["mClipName"]
      14 [-]: CALL R3 3 3  ; var3, var4 = var3(var4, var5)
      15 [-]: GETIMPORT R5 7; var5 = 0xC163F229
      16 [-]: LOADN R6 1   ; var6 = 1
      17 [-]: LOADN R7 30  ; var7 = 30
      18 [-]: CALL R5 3 2  ; var5 = var5(var6, var7)
      19 [-]: SETTABLEKS R5 R1 K8; var5["NoiseOffset"] = var1
      20 [-]: LOADN R7 1   ; var7 = 1
      21 [-]: LOADN R5 2   ; var5 = 2
      22 [-]: LOADN R6 1   ; var6 = 1
      23 [-]: FORNPREP R5 L1; nforprep start - [escape at L1] -- var5 = iterator
L 0:  24 [-]: GETTABLEKS R9 R1 K0; var9 = var1["mClipName"]
      25 [-]: LOADK R10 K9 ; var10 = ".Text"
      26 [-]: MOVE R11 R7  ; var11 = var7
      27 [-]: CONCAT R8 R9 R11; var8 = var9 .. var11
      28 [-]: MOVE R10 R8  ; var10 = var8
      29 [-]: LOADK R11 K10; var11 = ".Label"
      30 [-]: CONCAT R9 R10 R11; var9 = var10 .. var11
      31 [-]: GETIMPORT R10 5; var10 = 0xAE91E43B
      32 [-]: MOVE R12 R9  ; var12 = var9
      33 [-]: GETIMPORT R13 12; var13 = 0x851CCD29
      34 [-]: NAMECALL R10 R10 K13; var11 = var10; var10 = var10[0xD5181643]
      35 [-]: CALL R10 4 1 ; var10(var11, var12, var13)
      36 [-]: GETIMPORT R10 5; var10 = 0xAE91E43B
      37 [-]: MOVE R12 R8  ; var12 = var8
      38 [-]: LOADN R13 5  ; var13 = 5
      39 [-]: LOADN R14 150; var14 = 150
      40 [-]: NAMECALL R10 R10 K14; var11 = var10; var10 = var10[0x67BC869F]
      41 [-]: CALL R10 5 1 ; var10(var11, var12, var13, var14)
      42 [-]: GETIMPORT R10 5; var10 = 0xAE91E43B
      43 [-]: MOVE R12 R8  ; var12 = var8
      44 [-]: LOADN R13 6  ; var13 = 6
      45 [-]: LOADN R14 150; var14 = 150
      46 [-]: NAMECALL R10 R10 K14; var11 = var10; var10 = var10[0x67BC869F]
      47 [-]: CALL R10 5 1 ; var10(var11, var12, var13, var14)
      48 [-]: FORNLOOP R5 L0; nforloop end - iterate + goto L0
L 1:  49 [-]: GETIMPORT R5 5; var5 = 0xAE91E43B
      50 [-]: GETTABLEKS R7 R1 K0; var7 = var1["mClipName"]
      51 [-]: LOADK R8 K15 ; var8 = "Text2"
      52 [-]: LOADN R9 10  ; var9 = 10
      53 [-]: LOADN R10 30 ; var10 = 30
      54 [-]: NAMECALL R5 R5 K16; var6 = var5; var5 = var5[0xF64B7262]
      55 [-]: CALL R5 6 1  ; var5(var6, var7, var8, var9, var10)
      56 [-]: GETIMPORT R5 5; var5 = 0xAE91E43B
      57 [-]: MOVE R7 R2   ; var7 = var2
      58 [-]: LOADN R8 5   ; var8 = 5
      59 [-]: LOADN R9 300 ; var9 = 300
      60 [-]: NAMECALL R5 R5 K14; var6 = var5; var5 = var5[0x67BC869F]
      61 [-]: CALL R5 5 1  ; var5(var6, var7, var8, var9)
      62 [-]: GETIMPORT R5 5; var5 = 0xAE91E43B
      63 [-]: MOVE R7 R2   ; var7 = var2
      64 [-]: LOADN R8 6   ; var8 = 6
      65 [-]: LOADN R9 300 ; var9 = 300
      66 [-]: NAMECALL R5 R5 K14; var6 = var5; var5 = var5[0x67BC869F]
      67 [-]: CALL R5 5 1  ; var5(var6, var7, var8, var9)
      68 [-]: GETIMPORT R5 5; var5 = 0xAE91E43B
      69 [-]: MOVE R7 R2   ; var7 = var2
      70 [-]: LOADN R8 10  ; var8 = 10
      71 [-]: LOADN R9 4   ; var9 = 4
      72 [-]: NAMECALL R5 R5 K14; var6 = var5; var5 = var5[0x67BC869F]
      73 [-]: CALL R5 5 1  ; var5(var6, var7, var8, var9)
L 2:  74 [-]: GETIMPORT R3 18; var3 = 0xF7F90318
      75 [-]: GETTABLEKS R5 R1 K8; var5 = var1["NoiseOffset"]
      76 [-]: GETIMPORT R7 21; var7 = 0x55156FF7
      77 [-]: CALL R7 1 2  ; var7 = var7()
      78 [-]: MULK R6 R7 K19; var6 = var7 * 0.090000003576278687
      79 [-]: ADD R4 R5 R6 ; var4 = var5 + var6
      80 [-]: CALL R3 2 2  ; var3 = var3(var4)
      81 [-]: GETIMPORT R4 18; var4 = 0xF7F90318
      82 [-]: GETTABLEKS R6 R1 K8; var6 = var1["NoiseOffset"]
      83 [-]: GETIMPORT R8 21; var8 = 0x55156FF7
      84 [-]: CALL R8 1 2  ; var8 = var8()
      85 [-]: MULK R7 R8 K22; var7 = var8 * 0.059999998658895493
      86 [-]: ADD R5 R6 R7 ; var5 = var6 + var7
      87 [-]: CALL R4 2 2  ; var4 = var4(var5)
      88 [-]: GETIMPORT R5 5; var5 = 0xAE91E43B
      89 [-]: GETTABLEKS R7 R1 K0; var7 = var1["mClipName"]
      90 [-]: LOADK R8 K23 ; var8 = "Text1"
      91 [-]: LOADN R9 0   ; var9 = 0
      92 [-]: MULK R10 R3 K24; var10 = var3 * 60
      93 [-]: NAMECALL R5 R5 K16; var6 = var5; var5 = var5[0xF64B7262]
      94 [-]: CALL R5 6 1  ; var5(var6, var7, var8, var9, var10)
      95 [-]: GETIMPORT R5 5; var5 = 0xAE91E43B
      96 [-]: GETTABLEKS R7 R1 K0; var7 = var1["mClipName"]
      97 [-]: LOADK R8 K15 ; var8 = "Text2"
      98 [-]: LOADN R9 0   ; var9 = 0
      99 [-]: MULK R10 R4 K25; var10 = var4 * 90
     100 [-]: NAMECALL R5 R5 K16; var6 = var5; var5 = var5[0xF64B7262]
     101 [-]: CALL R5 6 1  ; var5(var6, var7, var8, var9, var10)
     102 [-]: GETIMPORT R5 5; var5 = 0xAE91E43B
     103 [-]: GETTABLEKS R7 R1 K0; var7 = var1["mClipName"]
     104 [-]: LOADK R8 K26 ; var8 = "Text3"
     105 [-]: LOADN R9 0   ; var9 = 0
     106 [-]: MULK R10 R4 K27; var10 = var4 * 100
     107 [-]: NAMECALL R5 R5 K16; var6 = var5; var5 = var5[0xF64B7262]
     108 [-]: CALL R5 6 1  ; var5(var6, var7, var8, var9, var10)
     109 [-]: GETIMPORT R5 5; var5 = 0xAE91E43B
     110 [-]: GETTABLEKS R7 R1 K0; var7 = var1["mClipName"]
     111 [-]: LOADK R8 K23 ; var8 = "Text1"
     112 [-]: LOADN R9 1   ; var9 = 1
     113 [-]: MULK R10 R3 K28; var10 = var3 * 20
     114 [-]: NAMECALL R5 R5 K16; var6 = var5; var5 = var5[0xF64B7262]
     115 [-]: CALL R5 6 1  ; var5(var6, var7, var8, var9, var10)
     116 [-]: GETIMPORT R5 5; var5 = 0xAE91E43B
     117 [-]: GETTABLEKS R7 R1 K0; var7 = var1["mClipName"]
     118 [-]: LOADK R8 K15 ; var8 = "Text2"
     119 [-]: LOADN R9 1   ; var9 = 1
     120 [-]: MULK R10 R4 K29; var10 = var4 * -10
     121 [-]: NAMECALL R5 R5 K16; var6 = var5; var5 = var5[0xF64B7262]
     122 [-]: CALL R5 6 1  ; var5(var6, var7, var8, var9, var10)
     123 [-]: GETIMPORT R5 5; var5 = 0xAE91E43B
     124 [-]: GETTABLEKS R7 R1 K0; var7 = var1["mClipName"]
     125 [-]: LOADK R8 K26 ; var8 = "Text3"
     126 [-]: LOADN R9 1   ; var9 = 1
     127 [-]: MULK R10 R4 K30; var10 = var4 * 80
     128 [-]: NAMECALL R5 R5 K16; var6 = var5; var5 = var5[0xF64B7262]
     129 [-]: CALL R5 6 1  ; var5(var6, var7, var8, var9, var10)
     130 [-]: GETIMPORT R5 5; var5 = 0xAE91E43B
     131 [-]: GETTABLEKS R8 R1 K0; var8 = var1["mClipName"]
     132 [-]: LOADK R9 K31 ; var9 = ".Text1.Label"
     133 [-]: CONCAT R7 R8 R9; var7 = var8 .. var9
     134 [-]: LOADK R8 K32 ; var8 = "PixelateBias"
     135 [-]: LOADN R9 1   ; var9 = 1
     136 [-]: LOADK R11 K33; var11 = 1.0499999523162842
     137 [-]: MULK R13 R3 K34; var13 = var3 * 3
     138 [-]: FASTCALL1 2 R13 L3; 
     139 [-]: GETIMPORT R12 37; var12 = 0x5BCED4C4[0xE4A5B3CA]
     140 [-]: CALL R12 2 2 ; var12 = var12(var13)
L 3: 141 [-]: ADD R10 R11 R12; var10 = var11 + var12
     142 [-]: LOADN R11 0  ; var11 = 0
     143 [-]: LOADK R12 K38; var12 = 0.5
     144 [-]: NAMECALL R5 R5 K39; var6 = var5; var5 = var5[0x91E13703]
     145 [-]: CALL R5 8 1  ; var5(var6, var7, var8, var9, var10, var11, var12)
     146 [-]: GETIMPORT R5 5; var5 = 0xAE91E43B
     147 [-]: GETTABLEKS R8 R1 K0; var8 = var1["mClipName"]
     148 [-]: LOADK R9 K40 ; var9 = ".Text2.Label"
     149 [-]: CONCAT R7 R8 R9; var7 = var8 .. var9
     150 [-]: LOADK R8 K32 ; var8 = "PixelateBias"
     151 [-]: LOADN R9 1   ; var9 = 1
     152 [-]: LOADN R11 1  ; var11 = 1
     153 [-]: MULK R13 R4 K38; var13 = var4 * 0.5
     154 [-]: FASTCALL1 2 R13 L4; 
     155 [-]: GETIMPORT R12 37; var12 = 0x5BCED4C4[0xE4A5B3CA]
     156 [-]: CALL R12 2 2 ; var12 = var12(var13)
L 4: 157 [-]: ADD R10 R11 R12; var10 = var11 + var12
     158 [-]: LOADN R11 0  ; var11 = 0
     159 [-]: LOADK R12 K38; var12 = 0.5
     160 [-]: NAMECALL R5 R5 K39; var6 = var5; var5 = var5[0x91E13703]
     161 [-]: CALL R5 8 1  ; var5(var6, var7, var8, var9, var10, var11, var12)
     162 [-]: RETURN R0 0  ; 


; Name:            
; Defined at line: 576
; #Upvalues:       23
; #Parameters:     0
; Is_vararg:       0
; Max Stack Size:  12

       0 [-]: GETUPVAL R0 0; var0 = upvalues[0]
       1 [-]: GETUPVAL R2 1; var2 = upvalues[1]
       2 [-]: LENGTH R1 R2 ; var1 = #var2
       3 [-]: JUMPIFNOTEQ R0 R1 L0; goto L0 if var0 ~= var131132
       4 [-]: GETUPVAL R0 2; var0 = upvalues[2]
       5 [-]: GETUPVAL R1 3; var1 = upvalues[3]
       6 [-]: CALL R0 2 1  ; var0(var1)
       7 [-]: RETURN R0 0  ; 
L 0:   8 [-]: GETUPVAL R1 0; var1 = upvalues[0]
       9 [-]: ADDK R0 R1 K0; var0 = var1 + 1
      10 [-]: SETUPVAL R0 0; upvalues[0] = var0
      11 [-]: LOADB R0 0   ; var0 = false
      12 [-]: SETUPVAL R0 4; upvalues[0] = var4
      13 [-]: GETUPVAL R1 6; var1 = upvalues[6]
      14 [-]: GETTABLEKS R0 R1 K1; var0 = var1[0xAE97C4F5]
      15 [-]: GETUPVAL R2 7; var2 = upvalues[7]
      16 [-]: GETUPVAL R5 1; var5 = upvalues[1]
      17 [-]: GETUPVAL R6 0; var6 = upvalues[0]
      18 [-]: GETTABLE R4 R5 R6; var4 = var5[var6]
      19 [-]: GETTABLEKS R3 R4 K2; var3 = var4["Emotion"]
      20 [-]: GETTABLE R1 R2 R3; var1 = var2[var3]
      21 [-]: CALL R0 2 2  ; var0 = var0(var1)
      22 [-]: SETUPVAL R0 5; upvalues[0] = var5
      23 [-]: NEWTABLE R0 0 0; var0 = {}
      24 [-]: SETUPVAL R0 8; upvalues[0] = var8
      25 [-]: GETUPVAL R1 6; var1 = upvalues[6]
      26 [-]: GETTABLEKS R0 R1 K3; var0 = var1[0x622A0C19]
      27 [-]: GETUPVAL R3 1; var3 = upvalues[1]
      28 [-]: GETUPVAL R4 0; var4 = upvalues[0]
      29 [-]: GETTABLE R2 R3 R4; var2 = var3[var4]
      30 [-]: GETTABLEKS R1 R2 K4; var1 = var2["Options"]
      31 [-]: CALL R0 2 2  ; var0 = var0(var1)
      32 [-]: LOADN R3 1   ; var3 = 1
      33 [-]: LENGTH R1 R0 ; var1 = #var0
      34 [-]: LOADN R2 1   ; var2 = 1
      35 [-]: FORNPREP R1 L4; nforprep start - [escape at L4] -- var1 = iterator
L 1:  36 [-]: GETUPVAL R4 8; var4 = upvalues[8]
      37 [-]: GETUPVAL R6 6; var6 = upvalues[6]
      38 [-]: GETTABLEKS R5 R6 K1; var5 = var6[0xAE97C4F5]
      39 [-]: GETUPVAL R7 7; var7 = upvalues[7]
      40 [-]: GETTABLE R8 R0 R3; var8 = var0[var3]
      41 [-]: GETTABLE R6 R7 R8; var6 = var7[var8]
      42 [-]: CALL R5 2 2  ; var5 = var5(var6)
      43 [-]: SETTABLE R5 R4 R3; var5[var4] = var3
      44 [-]: GETUPVAL R5 8; var5 = upvalues[8]
      45 [-]: GETTABLE R4 R5 R3; var4 = var5[var3]
      46 [-]: LOADB R5 1   ; var5 = true
      47 [-]: SETTABLEKS R5 R4 K5; var5["mActive"] = var4
      48 [-]: GETUPVAL R5 8; var5 = upvalues[8]
      49 [-]: GETTABLE R4 R5 R3; var4 = var5[var3]
      50 [-]: LOADK R6 K2  ; var6 = "Emotion"
      51 [-]: MOVE R7 R3   ; var7 = var3
      52 [-]: CONCAT R5 R6 R7; var5 = var6 .. var7
      53 [-]: SETTABLEKS R5 R4 K6; var5["mClipName"] = var4
      54 [-]: GETUPVAL R6 8; var6 = upvalues[8]
      55 [-]: GETTABLE R5 R6 R3; var5 = var6[var3]
      56 [-]: GETTABLEKS R4 R5 K7; var4 = var5["Animation"]
      57 [-]: JUMPXEQKNIL R4 L2 NOT; 
      58 [-]: GETUPVAL R5 8; var5 = upvalues[8]
      59 [-]: GETTABLE R4 R5 R3; var4 = var5[var3]
      60 [-]: GETUPVAL R5 9; var5 = upvalues[9]
      61 [-]: SETTABLEKS R5 R4 K7; var5["Animation"] = var4
L 2:  62 [-]: GETIMPORT R4 9; var4 = 0xAE91E43B
      63 [-]: LOADK R7 K2  ; var7 = "Emotion"
      64 [-]: MOVE R8 R3   ; var8 = var3
      65 [-]: CONCAT R6 R7 R8; var6 = var7 .. var8
      66 [-]: LOADN R7 10  ; var7 = 10
      67 [-]: LOADN R8 0   ; var8 = 0
      68 [-]: NAMECALL R4 R4 K10; var5 = var4; var4 = var4[0x67BC869F]
      69 [-]: CALL R4 5 1  ; var4(var5, var6, var7, var8)
      70 [-]: GETIMPORT R4 9; var4 = 0xAE91E43B
      71 [-]: LOADK R7 K2  ; var7 = "Emotion"
      72 [-]: MOVE R8 R3   ; var8 = var3
      73 [-]: CONCAT R6 R7 R8; var6 = var7 .. var8
      74 [-]: LOADN R7 61  ; var7 = 61
      75 [-]: LOADB R8 0   ; var8 = false
      76 [-]: NAMECALL R4 R4 K11; var5 = var4; var4 = var4[0xAADE900E]
      77 [-]: CALL R4 5 1  ; var4(var5, var6, var7, var8)
      78 [-]: GETIMPORT R4 9; var4 = 0xAE91E43B
      79 [-]: LOADK R7 K2  ; var7 = "Emotion"
      80 [-]: MOVE R8 R3   ; var8 = var3
      81 [-]: LOADK R9 K12 ; var9 = ".Text"
      82 [-]: LOADN R10 1  ; var10 = 1
      83 [-]: LOADK R11 K13; var11 = ".Label.text"
      84 [-]: CONCAT R6 R7 R11; var6 = var7 .. var11
      85 [-]: GETUPVAL R9 8; var9 = upvalues[8]
      86 [-]: GETTABLE R8 R9 R3; var8 = var9[var3]
      87 [-]: GETTABLEKS R7 R8 K14; var7 = var8["Label"]
      88 [-]: NAMECALL R4 R4 K15; var5 = var4; var4 = var4[0x20B98DB3]
      89 [-]: CALL R4 4 1  ; var4(var5, var6, var7)
      90 [-]: GETIMPORT R4 9; var4 = 0xAE91E43B
      91 [-]: LOADK R7 K2  ; var7 = "Emotion"
      92 [-]: MOVE R8 R3   ; var8 = var3
      93 [-]: LOADK R9 K12 ; var9 = ".Text"
      94 [-]: LOADN R10 2  ; var10 = 2
      95 [-]: LOADK R11 K13; var11 = ".Label.text"
      96 [-]: CONCAT R6 R7 R11; var6 = var7 .. var11
      97 [-]: GETUPVAL R9 8; var9 = upvalues[8]
      98 [-]: GETTABLE R8 R9 R3; var8 = var9[var3]
      99 [-]: GETTABLEKS R7 R8 K14; var7 = var8["Label"]
     100 [-]: NAMECALL R4 R4 K15; var5 = var4; var4 = var4[0x20B98DB3]
     101 [-]: CALL R4 4 1  ; var4(var5, var6, var7)
     102 [-]: GETIMPORT R4 9; var4 = 0xAE91E43B
     103 [-]: LOADK R7 K2  ; var7 = "Emotion"
     104 [-]: MOVE R8 R3   ; var8 = var3
     105 [-]: LOADK R9 K12 ; var9 = ".Text"
     106 [-]: LOADN R10 3  ; var10 = 3
     107 [-]: LOADK R11 K13; var11 = ".Label.text"
     108 [-]: CONCAT R6 R7 R11; var6 = var7 .. var11
     109 [-]: GETUPVAL R9 8; var9 = upvalues[8]
     110 [-]: GETTABLE R8 R9 R3; var8 = var9[var3]
     111 [-]: GETTABLEKS R7 R8 K14; var7 = var8["Label"]
     112 [-]: NAMECALL R4 R4 K15; var5 = var4; var4 = var4[0x20B98DB3]
     113 [-]: CALL R4 4 1  ; var4(var5, var6, var7)
     114 [-]: GETUPVAL R6 8; var6 = upvalues[8]
     115 [-]: GETTABLE R5 R6 R3; var5 = var6[var3]
     116 [-]: GETTABLEKS R4 R5 K14; var4 = var5["Label"]
     117 [-]: GETUPVAL R6 5; var6 = upvalues[5]
     118 [-]: GETTABLEKS R5 R6 K14; var5 = var6["Label"]
     119 [-]: JUMPIFNOTEQ R4 R5 L3; goto L3 if var4 ~= var328764
     120 [-]: GETUPVAL R4 5; var4 = upvalues[5]
     121 [-]: GETUPVAL R7 8; var7 = upvalues[8]
     122 [-]: GETTABLE R6 R7 R3; var6 = var7[var3]
     123 [-]: GETTABLEKS R5 R6 K6; var5 = var6["mClipName"]
     124 [-]: SETTABLEKS R5 R4 K6; var5["mClipName"] = var4
L 3: 125 [-]: FORNLOOP R1 L1; nforloop end - iterate + goto L1
L 4: 126 [-]: GETUPVAL R1 10; var1 = upvalues[10]
     127 [-]: GETIMPORT R4 9; var4 = 0xAE91E43B
     128 [-]: NAMECALL R4 R4 K17; var5 = var4; var4 = var4[0x091C120E]
     129 [-]: CALL R4 2 2  ; var4 = var4(var5)
     130 [-]: MULK R3 R4 K16; var3 = var4 * 0.5
     131 [-]: NAMECALL R1 R1 K18; var2 = var1; var1 = var1[0xD0F998CD]
     132 [-]: CALL R1 3 1  ; var1(var2, var3)
     133 [-]: GETUPVAL R1 11; var1 = upvalues[11]
     134 [-]: GETUPVAL R3 12; var3 = upvalues[12]
     135 [-]: NAMECALL R1 R1 K18; var2 = var1; var1 = var1[0xD0F998CD]
     136 [-]: CALL R1 3 1  ; var1(var2, var3)
     137 [-]: GETIMPORT R1 9; var1 = 0xAE91E43B
     138 [-]: LOADK R3 K19 ; var3 = "Card1"
     139 [-]: LOADN R4 0   ; var4 = 0
     140 [-]: GETIMPORT R6 9; var6 = 0xAE91E43B
     141 [-]: NAMECALL R6 R6 K17; var7 = var6; var6 = var6[0x091C120E]
     142 [-]: CALL R6 2 2  ; var6 = var6(var7)
     143 [-]: MULK R5 R6 K16; var5 = var6 * 0.5
     144 [-]: NAMECALL R1 R1 K10; var2 = var1; var1 = var1[0x67BC869F]
     145 [-]: CALL R1 5 1  ; var1(var2, var3, var4, var5)
     146 [-]: GETIMPORT R1 9; var1 = 0xAE91E43B
     147 [-]: LOADK R3 K19 ; var3 = "Card1"
     148 [-]: LOADN R4 1   ; var4 = 1
     149 [-]: LOADN R5 -500; var5 = -500
     150 [-]: NAMECALL R1 R1 K10; var2 = var1; var1 = var1[0x67BC869F]
     151 [-]: CALL R1 5 1  ; var1(var2, var3, var4, var5)
     152 [-]: GETIMPORT R1 9; var1 = 0xAE91E43B
     153 [-]: LOADK R3 K19 ; var3 = "Card1"
     154 [-]: LOADN R4 14  ; var4 = 14
     155 [-]: LOADN R5 0   ; var5 = 0
     156 [-]: NAMECALL R1 R1 K10; var2 = var1; var1 = var1[0x67BC869F]
     157 [-]: CALL R1 5 1  ; var1(var2, var3, var4, var5)
     158 [-]: GETIMPORT R1 9; var1 = 0xAE91E43B
     159 [-]: LOADK R3 K19 ; var3 = "Card1"
     160 [-]: LOADN R4 61  ; var4 = 61
     161 [-]: LOADB R5 0   ; var5 = false
     162 [-]: NAMECALL R1 R1 K11; var2 = var1; var1 = var1[0xAADE900E]
     163 [-]: CALL R1 5 1  ; var1(var2, var3, var4, var5)
     164 [-]: GETIMPORT R1 9; var1 = 0xAE91E43B
     165 [-]: LOADK R3 K20 ; var3 = "Card1.Emotion"
     166 [-]: LOADN R4 10  ; var4 = 10
     167 [-]: LOADN R5 0   ; var5 = 0
     168 [-]: NAMECALL R1 R1 K10; var2 = var1; var1 = var1[0x67BC869F]
     169 [-]: CALL R1 5 1  ; var1(var2, var3, var4, var5)
     170 [-]: GETIMPORT R2 22; var2 = 0x3260BAFC
     171 [-]: GETIMPORT R3 24; var3 = 0x55730E1A
     172 [-]: LOADN R4 1   ; var4 = 1
     173 [-]: GETIMPORT R6 22; var6 = 0x3260BAFC
     174 [-]: LENGTH R5 R6 ; var5 = #var6
     175 [-]: CALL R3 3 2  ; var3 = var3(var4, var5)
     176 [-]: GETTABLE R1 R2 R3; var1 = var2[var3]
     177 [-]: GETIMPORT R2 9; var2 = 0xAE91E43B
     178 [-]: LOADK R4 K25 ; var4 = "Card1.Back"
     179 [-]: MOVE R5 R1   ; var5 = var1
     180 [-]: GETIMPORT R6 27; var6 = 0xE796CFE5
     181 [-]: NAMECALL R2 R2 K28; var3 = var2; var2 = var2[0xEF99134F]
     182 [-]: CALL R2 5 1  ; var2(var3, var4, var5, var6)
     183 [-]: GETIMPORT R2 9; var2 = 0xAE91E43B
     184 [-]: LOADK R4 K29 ; var4 = "Card1.Front"
     185 [-]: MOVE R5 R1   ; var5 = var1
     186 [-]: GETIMPORT R6 27; var6 = 0xE796CFE5
     187 [-]: NAMECALL R2 R2 K28; var3 = var2; var2 = var2[0xEF99134F]
     188 [-]: CALL R2 5 1  ; var2(var3, var4, var5, var6)
     189 [-]: GETIMPORT R2 9; var2 = 0xAE91E43B
     190 [-]: LOADK R4 K20 ; var4 = "Card1.Emotion"
     191 [-]: GETIMPORT R5 27; var5 = 0xE796CFE5
     192 [-]: NAMECALL R2 R2 K30; var3 = var2; var2 = var2[0xD5181643]
     193 [-]: CALL R2 4 1  ; var2(var3, var4, var5)
     194 [-]: LOADN R4 1   ; var4 = 1
     195 [-]: LOADN R2 4   ; var2 = 4
     196 [-]: LOADN R3 1   ; var3 = 1
     197 [-]: FORNPREP R2 L6; nforprep start - [escape at L6] -- var2 = iterator
L 5: 198 [-]: GETIMPORT R5 9; var5 = 0xAE91E43B
     199 [-]: LOADK R8 K2  ; var8 = "Emotion"
     200 [-]: MOVE R9 R4   ; var9 = var4
     201 [-]: CONCAT R7 R8 R9; var7 = var8 .. var9
     202 [-]: LOADN R8 0   ; var8 = 0
     203 [-]: GETUPVAL R11 13; var11 = upvalues[13]
     204 [-]: GETTABLE R10 R11 R4; var10 = var11[var4]
     205 [-]: GETTABLEKS R9 R10 K31; var9 = var10["x"]
     206 [-]: NAMECALL R5 R5 K10; var6 = var5; var5 = var5[0x67BC869F]
     207 [-]: CALL R5 5 1  ; var5(var6, var7, var8, var9)
     208 [-]: GETIMPORT R5 9; var5 = 0xAE91E43B
     209 [-]: LOADK R8 K2  ; var8 = "Emotion"
     210 [-]: MOVE R9 R4   ; var9 = var4
     211 [-]: CONCAT R7 R8 R9; var7 = var8 .. var9
     212 [-]: LOADN R8 1   ; var8 = 1
     213 [-]: GETUPVAL R11 13; var11 = upvalues[13]
     214 [-]: GETTABLE R10 R11 R4; var10 = var11[var4]
     215 [-]: GETTABLEKS R9 R10 K32; var9 = var10["y"]
     216 [-]: NAMECALL R5 R5 K10; var6 = var5; var5 = var5[0x67BC869F]
     217 [-]: CALL R5 5 1  ; var5(var6, var7, var8, var9)
     218 [-]: FORNLOOP R2 L5; nforloop end - iterate + goto L5
L 6: 219 [-]: GETUPVAL R2 14; var2 = upvalues[14]
     220 [-]: LOADK R3 K19 ; var3 = "Card1"
     221 [-]: NEWCLOSURE R4 P0; 
     222 [-]: CAPTURE UPVAL U15; 
     223 [-]: CAPTURE UPVAL U4; 
     224 [-]: CAPTURE UPVAL U5; 
     225 [-]: CAPTURE UPVAL U6; 
     226 [-]: CAPTURE UPVAL U16; 
     227 [-]: CAPTURE UPVAL U1; 
     228 [-]: CAPTURE UPVAL U0; 
     229 [-]: CAPTURE UPVAL U17; 
     230 [-]: CAPTURE UPVAL U18; 
     231 [-]: CAPTURE UPVAL U19; 
     232 [-]: CAPTURE UPVAL U20; 
     233 [-]: CAPTURE UPVAL U21; 
     234 [-]: CAPTURE UPVAL U22; 
     235 [-]: CALL R2 3 1  ; var2(var3, var4)
     236 [-]: RETURN R0 0  ; 


; Name:            
; Defined at line: 675
; #Upvalues:       0
; #Parameters:     0
; Is_vararg:       0
; Max Stack Size:  3

       0 [-]: GETIMPORT R1 2; var1 = _T["EmotionMusic"]
       1 [-]: FASTCALL1 64 R1 L0; 
       2 [-]: GETIMPORT R0 4; var0 = 0x7B998233
       3 [-]: CALL R0 2 2  ; var0 = var0(var1)
L 0:   4 [-]: JUMPIF R0 L1 ; goto L1 if var0
       5 [-]: GETIMPORT R0 6; var0 = 0x89326C93
       6 [-]: GETIMPORT R2 2; var2 = _T["EmotionMusic"]
       7 [-]: NAMECALL R0 R0 K7; var1 = var0; var0 = var0[0x59C96E77]
       8 [-]: CALL R0 3 1  ; var0(var1, var2)
       9 [-]: GETIMPORT R0 8; var0 = _T
      10 [-]: LOADNIL R1   ; var1 = nil
      11 [-]: SETTABLEKS R1 R0 K1; var1["EmotionMusic"] = var0
L 1:  12 [-]: GETIMPORT R1 10; var1 = 0xBE190284
      13 [-]: FASTCALL1 64 R1 L2; 
      14 [-]: GETIMPORT R0 4; var0 = 0x7B998233
      15 [-]: CALL R0 2 2  ; var0 = var0(var1)
L 2:  16 [-]: JUMPIF R0 L3 ; goto L3 if var0
      17 [-]: GETIMPORT R0 10; var0 = 0xBE190284
      18 [-]: LOADB R2 0   ; var2 = false
      19 [-]: NAMECALL R0 R0 K11; var1 = var0; var0 = var0[0xC02F2CB8]
      20 [-]: CALL R0 3 1  ; var0(var1, var2)
L 3:  21 [-]: GETIMPORT R1 13; var1 = _T["SetButtons"]
      22 [-]: FASTCALL1 64 R1 L4; 
      23 [-]: GETIMPORT R0 4; var0 = 0x7B998233
      24 [-]: CALL R0 2 2  ; var0 = var0(var1)
L 4:  25 [-]: JUMPIF R0 L5 ; goto L5 if var0
      26 [-]: GETIMPORT R0 13; var0 = _T["SetButtons"]
      27 [-]: GETIMPORT R1 15; var1 = 0xAE91E43B
      28 [-]: LOADNIL R2   ; var2 = nil
      29 [-]: CALL R0 3 1  ; var0(var1, var2)
L 5:  30 [-]: RETURN R0 0  ; 


; Name:            
; Defined at line: 690
; #Upvalues:       29
; #Parameters:     0
; Is_vararg:       0
; Max Stack Size:  18

       0 [-]: GETIMPORT R0 1; var0 = 0x76EA806B
       1 [-]: LOADN R2 0   ; var2 = 0
       2 [-]: NAMECALL R0 R0 K2; var1 = var0; var0 = var0[0x3F3AE64C]
       3 [-]: CALL R0 3 2  ; var0 = var0(var1, var2)
       4 [-]: FASTCALL1 64 R0 L0; 
       5 [-]: MOVE R2 R0   ; var2 = var0
       6 [-]: GETIMPORT R1 4; var1 = 0x7B998233
       7 [-]: CALL R1 2 2  ; var1 = var1(var2)
L 0:   8 [-]: JUMPIF R1 L1 ; goto L1 if var1
       9 [-]: NAMECALL R1 R0 K5; var2 = var0; var1 = var0[0x80563238]
      10 [-]: CALL R1 2 2  ; var1 = var1(var2)
      11 [-]: SETUPVAL R1 0; upvalues[1] = var0
L 1:  12 [-]: GETUPVAL R2 0; var2 = upvalues[0]
      13 [-]: FASTCALL1 64 R2 L2; 
      14 [-]: GETIMPORT R1 4; var1 = 0x7B998233
      15 [-]: CALL R1 2 2  ; var1 = var1(var2)
L 2:  16 [-]: JUMPIFNOT R1 L3; goto L3 if not var1
      17 [-]: RETURN R0 0  ; 
L 3:  18 [-]: GETIMPORT R1 7; var1 = 0xBE190284
      19 [-]: LOADB R3 1   ; var3 = true
      20 [-]: NAMECALL R1 R1 K8; var2 = var1; var1 = var1[0xC02F2CB8]
      21 [-]: CALL R1 3 1  ; var1(var2, var3)
      22 [-]: GETIMPORT R1 11; var1 = _T["AltEmotionSelectionMode"]
      23 [-]: JUMPXEQKNIL R1 L4; 
      24 [-]: GETIMPORT R1 11; var1 = _T["AltEmotionSelectionMode"]
      25 [-]: SETUPVAL R1 1; upvalues[1] = var1
L 4:  26 [-]: GETIMPORT R3 15; var3 = 0xAE91E43B
      27 [-]: NAMECALL R3 R3 K16; var4 = var3; var3 = var3[0x2CC9D281]
      28 [-]: CALL R3 2 2  ; var3 = var3(var4)
      29 [-]: MULK R2 R3 K13; var2 = var3 * 0.5
      30 [-]: SUBK R1 R2 K12; var1 = var2 - 70
      31 [-]: SETUPVAL R1 2; upvalues[1] = var2
      32 [-]: GETIMPORT R1 18; var1 = 0x2D0FAD09
      33 [-]: LOADK R2 K19 ; var2 = "Lotus.Interface.Libs.TimerMgr"
      34 [-]: CALL R1 2 2  ; var1 = var1(var2)
      35 [-]: GETTABLEKS R2 R1 K20; var2 = var1[0xDE474187]
      36 [-]: CALL R2 1 2  ; var2 = var2()
      37 [-]: SETUPVAL R2 3; upvalues[2] = var3
      38 [-]: GETUPVAL R2 4; var2 = upvalues[4]
      39 [-]: JUMPXEQKNIL R2 L6 NOT; 
      40 [-]: NEWTABLE R2 0 0; var2 = {}
      41 [-]: SETUPVAL R2 4; upvalues[2] = var4
      42 [-]: LOADN R4 1   ; var4 = 1
      43 [-]: LOADN R2 4   ; var2 = 4
      44 [-]: LOADN R3 1   ; var3 = 1
      45 [-]: FORNPREP R2 L6; nforprep start - [escape at L6] -- var2 = iterator
L 5:  46 [-]: GETUPVAL R5 4; var5 = upvalues[4]
      47 [-]: NEWTABLE R6 0 0; var6 = {}
      48 [-]: SETTABLE R6 R5 R4; var6[var5] = var4
      49 [-]: GETUPVAL R6 4; var6 = upvalues[4]
      50 [-]: GETTABLE R5 R6 R4; var5 = var6[var4]
      51 [-]: GETIMPORT R6 15; var6 = 0xAE91E43B
      52 [-]: LOADK R9 K21 ; var9 = "Emotion"
      53 [-]: MOVE R10 R4  ; var10 = var4
      54 [-]: CONCAT R8 R9 R10; var8 = var9 .. var10
      55 [-]: LOADN R9 0   ; var9 = 0
      56 [-]: NAMECALL R6 R6 K22; var7 = var6; var6 = var6[0x91A24E4B]
      57 [-]: CALL R6 4 2  ; var6 = var6(var7, var8, var9)
      58 [-]: SETTABLEKS R6 R5 K23; var6["x"] = var5
      59 [-]: GETUPVAL R6 4; var6 = upvalues[4]
      60 [-]: GETTABLE R5 R6 R4; var5 = var6[var4]
      61 [-]: GETIMPORT R6 15; var6 = 0xAE91E43B
      62 [-]: LOADK R9 K21 ; var9 = "Emotion"
      63 [-]: MOVE R10 R4  ; var10 = var4
      64 [-]: CONCAT R8 R9 R10; var8 = var9 .. var10
      65 [-]: LOADN R9 1   ; var9 = 1
      66 [-]: NAMECALL R6 R6 K22; var7 = var6; var6 = var6[0x91A24E4B]
      67 [-]: CALL R6 4 2  ; var6 = var6(var7, var8, var9)
      68 [-]: SETTABLEKS R6 R5 K24; var6["y"] = var5
      69 [-]: FORNLOOP R2 L5; nforloop end - iterate + goto L5
L 6:  70 [-]: GETIMPORT R2 18; var2 = 0x2D0FAD09
      71 [-]: LOADK R3 K25 ; var3 = "EE.Interface.AnchorMgr"
      72 [-]: CALL R2 2 2  ; var2 = var2(var3)
      73 [-]: GETTABLEKS R3 R2 K26; var3 = var2[0xAE6791BA]
      74 [-]: GETIMPORT R4 15; var4 = 0xAE91E43B
      75 [-]: CALL R3 2 2  ; var3 = var3(var4)
      76 [-]: SETUPVAL R3 5; upvalues[3] = var5
      77 [-]: GETUPVAL R3 5; var3 = upvalues[5]
      78 [-]: GETIMPORT R5 15; var5 = 0xAE91E43B
      79 [-]: LOADK R6 K27 ; var6 = "SmokeContainer"
      80 [-]: NEWTABLE R7 0 2; var7 = {}
      81 [-]: GETUPVAL R9 5; var9 = upvalues[5]
      82 [-]: GETTABLEKS R8 R9 K28; var8 = var9["ANCHOR_V_BOTTOM"]
      83 [-]: GETUPVAL R10 5; var10 = upvalues[5]
      84 [-]: GETTABLEKS R9 R10 K29; var9 = var10["ANCHOR_H_CENTRE"]
      85 [-]: SETLIST R7 R8 2 [1]; var7[1] = var8; var7[2] = var9; var7[3] = var10; 
      86 [-]: NAMECALL R3 R3 K30; var4 = var3; var3 = var3[0x20FF29F7]
      87 [-]: CALL R3 5 1  ; var3(var4, var5, var6, var7)
      88 [-]: GETIMPORT R3 15; var3 = 0xAE91E43B
      89 [-]: LOADN R5 0   ; var5 = 0
      90 [-]: NAMECALL R3 R3 K31; var4 = var3; var3 = var3[0xC6A10AB1]
      91 [-]: CALL R3 3 1  ; var3(var4, var5)
      92 [-]: GETIMPORT R3 15; var3 = 0xAE91E43B
      93 [-]: LOADN R5 0   ; var5 = 0
      94 [-]: NAMECALL R3 R3 K32; var4 = var3; var3 = var3[0x58BEC6D6]
      95 [-]: CALL R3 3 1  ; var3(var4, var5)
      96 [-]: GETIMPORT R4 34; var4 = _T["EmotionMusic"]
      97 [-]: FASTCALL1 64 R4 L7; 
      98 [-]: GETIMPORT R3 4; var3 = 0x7B998233
      99 [-]: CALL R3 2 2  ; var3 = var3(var4)
L 7: 100 [-]: JUMPIFNOT R3 L8; goto L8 if not var3
     101 [-]: GETIMPORT R3 36; var3 = 0x89326C93
     102 [-]: NAMECALL R3 R3 K37; var4 = var3; var3 = var3[0x78298275]
     103 [-]: CALL R3 2 2  ; var3 = var3(var4)
     104 [-]: GETIMPORT R4 38; var4 = _T
     105 [-]: GETIMPORT R5 36; var5 = 0x89326C93
     106 [-]: GETIMPORT R7 40; var7 = 0x4B858385
     107 [-]: NAMECALL R8 R3 K41; var9 = var3; var8 = var3[0xF6EBD926]
     108 [-]: CALL R8 2 2  ; var8 = var8(var9)
     109 [-]: NAMECALL R9 R3 K42; var10 = var3; var9 = var3[0x5280B883]
     110 [-]: CALL R9 2 0  ; var9, ... = var9(var10)
     111 [-]: NAMECALL R5 R5 K43; var6 = var5; var5 = var5[0x05909209]
     112 [-]: CALL R5 0 2  ; var5 = var5(var6, ...)
     113 [-]: SETTABLEKS R5 R4 K33; var5["EmotionMusic"] = var4
L 8: 114 [-]: GETIMPORT R3 15; var3 = 0xAE91E43B
     115 [-]: LOADK R5 K44 ; var5 = "SmokeContainer.Smoke1"
     116 [-]: GETIMPORT R6 46; var6 = 0xC22FA08D
     117 [-]: NAMECALL R3 R3 K47; var4 = var3; var3 = var3[0xD5181643]
     118 [-]: CALL R3 4 1  ; var3(var4, var5, var6)
     119 [-]: GETIMPORT R3 15; var3 = 0xAE91E43B
     120 [-]: LOADK R5 K48 ; var5 = "SmokeContainer.Smoke2"
     121 [-]: GETIMPORT R6 50; var6 = 0xBF2F9BD4
     122 [-]: NAMECALL R3 R3 K47; var4 = var3; var3 = var3[0xD5181643]
     123 [-]: CALL R3 4 1  ; var3(var4, var5, var6)
     124 [-]: GETIMPORT R3 15; var3 = 0xAE91E43B
     125 [-]: LOADK R5 K51 ; var5 = "SmokeContainer.Smoke3"
     126 [-]: GETIMPORT R6 53; var6 = 0xC02F9D67
     127 [-]: NAMECALL R3 R3 K47; var4 = var3; var3 = var3[0xD5181643]
     128 [-]: CALL R3 4 1  ; var3(var4, var5, var6)
     129 [-]: GETIMPORT R3 15; var3 = 0xAE91E43B
     130 [-]: LOADK R5 K54 ; var5 = "SmokeContainer.Smoke4"
     131 [-]: GETIMPORT R6 56; var6 = 0xBD2F98AE
     132 [-]: NAMECALL R3 R3 K47; var4 = var3; var3 = var3[0xD5181643]
     133 [-]: CALL R3 4 1  ; var3(var4, var5, var6)
     134 [-]: GETIMPORT R3 15; var3 = 0xAE91E43B
     135 [-]: LOADK R5 K57 ; var5 = "SmokeContainer.Smoke5"
     136 [-]: GETIMPORT R6 59; var6 = 0xBE2F9A41
     137 [-]: NAMECALL R3 R3 K47; var4 = var3; var3 = var3[0xD5181643]
     138 [-]: CALL R3 4 1  ; var3(var4, var5, var6)
     139 [-]: GETIMPORT R3 15; var3 = 0xAE91E43B
     140 [-]: LOADK R5 K44 ; var5 = "SmokeContainer.Smoke1"
     141 [-]: LOADN R6 10  ; var6 = 10
     142 [-]: LOADN R7 25  ; var7 = 25
     143 [-]: NAMECALL R3 R3 K60; var4 = var3; var3 = var3[0x67BC869F]
     144 [-]: CALL R3 5 1  ; var3(var4, var5, var6, var7)
     145 [-]: GETIMPORT R3 15; var3 = 0xAE91E43B
     146 [-]: LOADK R5 K48 ; var5 = "SmokeContainer.Smoke2"
     147 [-]: LOADN R6 10  ; var6 = 10
     148 [-]: LOADN R7 60  ; var7 = 60
     149 [-]: NAMECALL R3 R3 K60; var4 = var3; var3 = var3[0x67BC869F]
     150 [-]: CALL R3 5 1  ; var3(var4, var5, var6, var7)
     151 [-]: GETIMPORT R3 15; var3 = 0xAE91E43B
     152 [-]: LOADK R5 K51 ; var5 = "SmokeContainer.Smoke3"
     153 [-]: LOADN R6 10  ; var6 = 10
     154 [-]: LOADN R7 15  ; var7 = 15
     155 [-]: NAMECALL R3 R3 K60; var4 = var3; var3 = var3[0x67BC869F]
     156 [-]: CALL R3 5 1  ; var3(var4, var5, var6, var7)
     157 [-]: GETIMPORT R3 15; var3 = 0xAE91E43B
     158 [-]: LOADK R5 K54 ; var5 = "SmokeContainer.Smoke4"
     159 [-]: LOADN R6 10  ; var6 = 10
     160 [-]: LOADN R7 20  ; var7 = 20
     161 [-]: NAMECALL R3 R3 K60; var4 = var3; var3 = var3[0x67BC869F]
     162 [-]: CALL R3 5 1  ; var3(var4, var5, var6, var7)
     163 [-]: GETIMPORT R3 15; var3 = 0xAE91E43B
     164 [-]: LOADK R5 K57 ; var5 = "SmokeContainer.Smoke5"
     165 [-]: LOADN R6 10  ; var6 = 10
     166 [-]: LOADN R7 15  ; var7 = 15
     167 [-]: NAMECALL R3 R3 K60; var4 = var3; var3 = var3[0x67BC869F]
     168 [-]: CALL R3 5 1  ; var3(var4, var5, var6, var7)
     169 [-]: GETIMPORT R3 15; var3 = 0xAE91E43B
     170 [-]: LOADK R5 K27 ; var5 = "SmokeContainer"
     171 [-]: LOADN R6 10  ; var6 = 10
     172 [-]: LOADN R7 0   ; var7 = 0
     173 [-]: NAMECALL R3 R3 K60; var4 = var3; var3 = var3[0x67BC869F]
     174 [-]: CALL R3 5 1  ; var3(var4, var5, var6, var7)
     175 [-]: GETIMPORT R3 15; var3 = 0xAE91E43B
     176 [-]: LOADK R5 K61 ; var5 = "Bluer"
     177 [-]: LOADN R6 10  ; var6 = 10
     178 [-]: LOADN R7 0   ; var7 = 0
     179 [-]: NAMECALL R3 R3 K60; var4 = var3; var3 = var3[0x67BC869F]
     180 [-]: CALL R3 5 1  ; var3(var4, var5, var6, var7)
     181 [-]: GETUPVAL R3 6; var3 = upvalues[6]
     182 [-]: GETUPVAL R5 7; var5 = upvalues[7]
     183 [-]: GETTABLEKS R4 R5 K62; var4 = var5["ANGRY"]
     184 [-]: DUPTABLE R5 66; 
     185 [-]: LOADK R6 K67 ; var6 = "/Lotus/Language/Quests/Emotion_Angry"
     186 [-]: SETTABLEKS R6 R5 K63; var6["Label"] = var5
     187 [-]: GETUPVAL R6 8; var6 = upvalues[8]
     188 [-]: SETTABLEKS R6 R5 K64; var6["Animation"] = var5
     189 [-]: GETIMPORT R6 69; var6 = 0xBE5E825C
     190 [-]: SETTABLEKS R6 R5 K65; var6["BadTransmission"] = var5
     191 [-]: SETTABLE R5 R3 R4; var5[var3] = var4
     192 [-]: GETUPVAL R3 6; var3 = upvalues[6]
     193 [-]: GETUPVAL R5 7; var5 = upvalues[7]
     194 [-]: GETTABLEKS R4 R5 K70; var4 = var5["BORED"]
     195 [-]: DUPTABLE R5 71; 
     196 [-]: LOADK R6 K72 ; var6 = "/Lotus/Language/Quests/Emotion_Bored"
     197 [-]: SETTABLEKS R6 R5 K63; var6["Label"] = var5
     198 [-]: SETTABLE R5 R3 R4; var5[var3] = var4
     199 [-]: GETUPVAL R3 6; var3 = upvalues[6]
     200 [-]: GETUPVAL R5 7; var5 = upvalues[7]
     201 [-]: GETTABLEKS R4 R5 K73; var4 = var5["CONFUSED"]
     202 [-]: DUPTABLE R5 66; 
     203 [-]: LOADK R6 K74 ; var6 = "/Lotus/Language/Quests/Emotion_Confused"
     204 [-]: SETTABLEKS R6 R5 K63; var6["Label"] = var5
     205 [-]: GETUPVAL R6 9; var6 = upvalues[9]
     206 [-]: SETTABLEKS R6 R5 K64; var6["Animation"] = var5
     207 [-]: GETIMPORT R6 76; var6 = 0xCE034D72
     208 [-]: SETTABLEKS R6 R5 K65; var6["BadTransmission"] = var5
     209 [-]: SETTABLE R5 R3 R4; var5[var3] = var4
     210 [-]: GETUPVAL R3 6; var3 = upvalues[6]
     211 [-]: GETUPVAL R5 7; var5 = upvalues[7]
     212 [-]: GETTABLEKS R4 R5 K77; var4 = var5["DISGUSTED"]
     213 [-]: DUPTABLE R5 71; 
     214 [-]: LOADK R6 K78 ; var6 = "/Lotus/Language/Quests/Emotion_Disgusted"
     215 [-]: SETTABLEKS R6 R5 K63; var6["Label"] = var5
     216 [-]: SETTABLE R5 R3 R4; var5[var3] = var4
     217 [-]: GETUPVAL R3 6; var3 = upvalues[6]
     218 [-]: GETUPVAL R5 7; var5 = upvalues[7]
     219 [-]: GETTABLEKS R4 R5 K79; var4 = var5["EMBARRASSED"]
     220 [-]: DUPTABLE R5 71; 
     221 [-]: LOADK R6 K80 ; var6 = "/Lotus/Language/Quests/Emotion_Embarrassed"
     222 [-]: SETTABLEKS R6 R5 K63; var6["Label"] = var5
     223 [-]: SETTABLE R5 R3 R4; var5[var3] = var4
     224 [-]: GETUPVAL R3 6; var3 = upvalues[6]
     225 [-]: GETUPVAL R5 7; var5 = upvalues[7]
     226 [-]: GETTABLEKS R4 R5 K81; var4 = var5["EXCITED"]
     227 [-]: DUPTABLE R5 82; 
     228 [-]: LOADK R6 K83 ; var6 = "/Lotus/Language/Quests/Emotion_Excited"
     229 [-]: SETTABLEKS R6 R5 K63; var6["Label"] = var5
     230 [-]: GETUPVAL R6 10; var6 = upvalues[10]
     231 [-]: SETTABLEKS R6 R5 K64; var6["Animation"] = var5
     232 [-]: SETTABLE R5 R3 R4; var5[var3] = var4
     233 [-]: GETUPVAL R3 6; var3 = upvalues[6]
     234 [-]: GETUPVAL R5 7; var5 = upvalues[7]
     235 [-]: GETTABLEKS R4 R5 K84; var4 = var5["GRUMPY"]
     236 [-]: DUPTABLE R5 71; 
     237 [-]: LOADK R6 K85 ; var6 = "/Lotus/Language/Quests/Emotion_Grumpy"
     238 [-]: SETTABLEKS R6 R5 K63; var6["Label"] = var5
     239 [-]: SETTABLE R5 R3 R4; var5[var3] = var4
     240 [-]: GETUPVAL R3 6; var3 = upvalues[6]
     241 [-]: GETUPVAL R5 7; var5 = upvalues[7]
     242 [-]: GETTABLEKS R4 R5 K86; var4 = var5["HAPPY"]
     243 [-]: DUPTABLE R5 82; 
     244 [-]: LOADK R6 K87 ; var6 = "/Lotus/Language/Quests/Emotion_Happy"
     245 [-]: SETTABLEKS R6 R5 K63; var6["Label"] = var5
     246 [-]: GETUPVAL R6 11; var6 = upvalues[11]
     247 [-]: SETTABLEKS R6 R5 K64; var6["Animation"] = var5
     248 [-]: SETTABLE R5 R3 R4; var5[var3] = var4
     249 [-]: GETUPVAL R3 6; var3 = upvalues[6]
     250 [-]: GETUPVAL R5 7; var5 = upvalues[7]
     251 [-]: GETTABLEKS R4 R5 K88; var4 = var5["HUNGRY"]
     252 [-]: DUPTABLE R5 71; 
     253 [-]: LOADK R6 K89 ; var6 = "/Lotus/Language/Quests/Emotion_Hungry"
     254 [-]: SETTABLEKS R6 R5 K63; var6["Label"] = var5
     255 [-]: SETTABLE R5 R3 R4; var5[var3] = var4
     256 [-]: GETUPVAL R3 6; var3 = upvalues[6]
     257 [-]: GETUPVAL R5 7; var5 = upvalues[7]
     258 [-]: GETTABLEKS R4 R5 K90; var4 = var5["NERVOUS"]
     259 [-]: DUPTABLE R5 71; 
     260 [-]: LOADK R6 K91 ; var6 = "/Lotus/Language/Quests/Emotion_Nervous"
     261 [-]: SETTABLEKS R6 R5 K63; var6["Label"] = var5
     262 [-]: SETTABLE R5 R3 R4; var5[var3] = var4
     263 [-]: GETUPVAL R3 6; var3 = upvalues[6]
     264 [-]: GETUPVAL R5 7; var5 = upvalues[7]
     265 [-]: GETTABLEKS R4 R5 K92; var4 = var5["PROUD"]
     266 [-]: DUPTABLE R5 71; 
     267 [-]: LOADK R6 K93 ; var6 = "/Lotus/Language/Quests/Emotion_Proud"
     268 [-]: SETTABLEKS R6 R5 K63; var6["Label"] = var5
     269 [-]: SETTABLE R5 R3 R4; var5[var3] = var4
     270 [-]: GETUPVAL R3 6; var3 = upvalues[6]
     271 [-]: GETUPVAL R5 7; var5 = upvalues[7]
     272 [-]: GETTABLEKS R4 R5 K94; var4 = var5["SAD"]
     273 [-]: DUPTABLE R5 71; 
     274 [-]: LOADK R6 K95 ; var6 = "/Lotus/Language/Quests/Emotion_Sad"
     275 [-]: SETTABLEKS R6 R5 K63; var6["Label"] = var5
     276 [-]: SETTABLE R5 R3 R4; var5[var3] = var4
     277 [-]: GETUPVAL R3 6; var3 = upvalues[6]
     278 [-]: GETUPVAL R5 7; var5 = upvalues[7]
     279 [-]: GETTABLEKS R4 R5 K96; var4 = var5["SCARED"]
     280 [-]: DUPTABLE R5 71; 
     281 [-]: LOADK R6 K97 ; var6 = "/Lotus/Language/Quests/Emotion_Scared"
     282 [-]: SETTABLEKS R6 R5 K63; var6["Label"] = var5
     283 [-]: SETTABLE R5 R3 R4; var5[var3] = var4
     284 [-]: GETUPVAL R3 6; var3 = upvalues[6]
     285 [-]: GETUPVAL R5 7; var5 = upvalues[7]
     286 [-]: GETTABLEKS R4 R5 K98; var4 = var5["SHY"]
     287 [-]: DUPTABLE R5 82; 
     288 [-]: LOADK R6 K99 ; var6 = "/Lotus/Language/Quests/Emotion_Shy"
     289 [-]: SETTABLEKS R6 R5 K63; var6["Label"] = var5
     290 [-]: GETUPVAL R6 12; var6 = upvalues[12]
     291 [-]: SETTABLEKS R6 R5 K64; var6["Animation"] = var5
     292 [-]: SETTABLE R5 R3 R4; var5[var3] = var4
     293 [-]: GETUPVAL R3 6; var3 = upvalues[6]
     294 [-]: GETUPVAL R5 7; var5 = upvalues[7]
     295 [-]: GETTABLEKS R4 R5 K100; var4 = var5["SICK"]
     296 [-]: DUPTABLE R5 82; 
     297 [-]: LOADK R6 K101; var6 = "/Lotus/Language/Quests/Emotion_Sick"
     298 [-]: SETTABLEKS R6 R5 K63; var6["Label"] = var5
     299 [-]: GETUPVAL R6 13; var6 = upvalues[13]
     300 [-]: SETTABLEKS R6 R5 K64; var6["Animation"] = var5
     301 [-]: SETTABLE R5 R3 R4; var5[var3] = var4
     302 [-]: GETUPVAL R3 6; var3 = upvalues[6]
     303 [-]: GETUPVAL R5 7; var5 = upvalues[7]
     304 [-]: GETTABLEKS R4 R5 K102; var4 = var5["SURPRISED"]
     305 [-]: DUPTABLE R5 66; 
     306 [-]: LOADK R6 K103; var6 = "/Lotus/Language/Quests/Emotion_Surprised"
     307 [-]: SETTABLEKS R6 R5 K63; var6["Label"] = var5
     308 [-]: GETUPVAL R6 14; var6 = upvalues[14]
     309 [-]: SETTABLEKS R6 R5 K64; var6["Animation"] = var5
     310 [-]: GETIMPORT R6 105; var6 = 0x6DD7F058
     311 [-]: SETTABLEKS R6 R5 K65; var6["BadTransmission"] = var5
     312 [-]: SETTABLE R5 R3 R4; var5[var3] = var4
     313 [-]: GETUPVAL R3 6; var3 = upvalues[6]
     314 [-]: GETUPVAL R5 7; var5 = upvalues[7]
     315 [-]: GETTABLEKS R4 R5 K106; var4 = var5["TIRED"]
     316 [-]: DUPTABLE R5 66; 
     317 [-]: LOADK R6 K107; var6 = "/Lotus/Language/Quests/Emotion_Tired"
     318 [-]: SETTABLEKS R6 R5 K63; var6["Label"] = var5
     319 [-]: GETUPVAL R6 15; var6 = upvalues[15]
     320 [-]: SETTABLEKS R6 R5 K64; var6["Animation"] = var5
     321 [-]: GETIMPORT R6 109; var6 = 0xB5F670BF
     322 [-]: SETTABLEKS R6 R5 K65; var6["BadTransmission"] = var5
     323 [-]: SETTABLE R5 R3 R4; var5[var3] = var4
     324 [-]: LOADN R5 1   ; var5 = 1
     325 [-]: GETUPVAL R6 6; var6 = upvalues[6]
     326 [-]: LENGTH R3 R6 ; var3 = #var6
     327 [-]: LOADN R4 1   ; var4 = 1
     328 [-]: FORNPREP R3 L10; nforprep start - [escape at L10] -- var3 = iterator
L 9: 329 [-]: GETUPVAL R7 6; var7 = upvalues[6]
     330 [-]: GETTABLE R6 R7 R5; var6 = var7[var5]
     331 [-]: GETIMPORT R8 111; var8 = 0x9E8DF569
     332 [-]: GETTABLE R7 R8 R5; var7 = var8[var5]
     333 [-]: SETTABLEKS R7 R6 K112; var7["Image"] = var6
     334 [-]: GETUPVAL R7 6; var7 = upvalues[6]
     335 [-]: GETTABLE R6 R7 R5; var6 = var7[var5]
     336 [-]: GETIMPORT R7 15; var7 = 0xAE91E43B
     337 [-]: GETUPVAL R11 6; var11 = upvalues[6]
     338 [-]: GETTABLE R10 R11 R5; var10 = var11[var5]
     339 [-]: GETTABLEKS R9 R10 K63; var9 = var10["Label"]
     340 [-]: LOADB R10 0  ; var10 = false
     341 [-]: NAMECALL R7 R7 K113; var8 = var7; var7 = var7[0x42B04007]
     342 [-]: CALL R7 4 2  ; var7 = var7(var8, var9, var10)
     343 [-]: SETTABLEKS R7 R6 K63; var7["Label"] = var6
     344 [-]: FORNLOOP R3 L9; nforloop end - iterate + goto L9
L10: 345 [-]: GETUPVAL R4 16; var4 = upvalues[16]
     346 [-]: GETTABLEKS R3 R4 K114; var3 = var4[0x659D451F]
     347 [-]: GETIMPORT R4 116; var4 = 0xB37CE899
     348 [-]: CALL R3 2 1  ; var3(var4)
     349 [-]: GETIMPORT R3 15; var3 = 0xAE91E43B
     350 [-]: LOADK R5 K117; var5 = "Card1"
     351 [-]: LOADN R6 1   ; var6 = 1
     352 [-]: LOADN R7 -500; var7 = -500
     353 [-]: NAMECALL R3 R3 K60; var4 = var3; var3 = var3[0x67BC869F]
     354 [-]: CALL R3 5 1  ; var3(var4, var5, var6, var7)
     355 [-]: LOADN R5 1   ; var5 = 1
     356 [-]: LOADN R3 4   ; var3 = 4
     357 [-]: LOADN R4 1   ; var4 = 1
     358 [-]: FORNPREP R3 L12; nforprep start - [escape at L12] -- var3 = iterator
L11: 359 [-]: GETIMPORT R6 15; var6 = 0xAE91E43B
     360 [-]: LOADK R9 K21 ; var9 = "Emotion"
     361 [-]: MOVE R10 R5  ; var10 = var5
     362 [-]: CONCAT R8 R9 R10; var8 = var9 .. var10
     363 [-]: LOADN R9 10  ; var9 = 10
     364 [-]: LOADN R10 0  ; var10 = 0
     365 [-]: NAMECALL R6 R6 K60; var7 = var6; var6 = var6[0x67BC869F]
     366 [-]: CALL R6 5 1  ; var6(var7, var8, var9, var10)
     367 [-]: GETIMPORT R6 15; var6 = 0xAE91E43B
     368 [-]: LOADK R9 K21 ; var9 = "Emotion"
     369 [-]: MOVE R10 R5  ; var10 = var5
     370 [-]: CONCAT R8 R9 R10; var8 = var9 .. var10
     371 [-]: LOADN R9 61  ; var9 = 61
     372 [-]: LOADB R10 0  ; var10 = false
     373 [-]: NAMECALL R6 R6 K118; var7 = var6; var6 = var6[0xAADE900E]
     374 [-]: CALL R6 5 1  ; var6(var7, var8, var9, var10)
     375 [-]: GETIMPORT R6 15; var6 = 0xAE91E43B
     376 [-]: LOADK R9 K21 ; var9 = "Emotion"
     377 [-]: MOVE R10 R5  ; var10 = var5
     378 [-]: LOADK R11 K119; var11 = ".Btn"
     379 [-]: CONCAT R8 R9 R11; var8 = var9 .. var11
     380 [-]: LOADN R9 87  ; var9 = 87
     381 [-]: MOVE R10 R5  ; var10 = var5
     382 [-]: NAMECALL R6 R6 K60; var7 = var6; var6 = var6[0x67BC869F]
     383 [-]: CALL R6 5 1  ; var6(var7, var8, var9, var10)
     384 [-]: GETIMPORT R6 15; var6 = 0xAE91E43B
     385 [-]: LOADK R9 K21 ; var9 = "Emotion"
     386 [-]: MOVE R10 R5  ; var10 = var5
     387 [-]: LOADK R11 K119; var11 = ".Btn"
     388 [-]: CONCAT R8 R9 R11; var8 = var9 .. var11
     389 [-]: LOADK R9 K120; var9 = "EmotionRollOver"
     390 [-]: LOADK R10 K121; var10 = "EmotionRollOut"
     391 [-]: LOADK R11 K122; var11 = "EmotionSelected"
     392 [-]: LOADK R12 K123; var12 = ""
     393 [-]: NAMECALL R6 R6 K124; var7 = var6; var6 = var6[0x1E5B5CFE]
     394 [-]: CALL R6 7 1  ; var6(var7, var8, var9, var10, var11, var12)
     395 [-]: FORNLOOP R3 L11; nforloop end - iterate + goto L11
L12: 396 [-]: GETUPVAL R3 1; var3 = upvalues[1]
     397 [-]: JUMPIFNOT R3 L18; goto L18 if not var3
     398 [-]: NEWTABLE R3 0 0; var3 = {}
     399 [-]: SETUPVAL R3 17; upvalues[3] = var17
     400 [-]: GETIMPORT R3 126; var3 = _T["EmotionSelectionActiveEmotions"]
     401 [-]: JUMPXEQKNIL R3 L13 NOT; 
     402 [-]: GETUPVAL R3 17; var3 = upvalues[17]
     403 [-]: GETUPVAL R5 7; var5 = upvalues[7]
     404 [-]: GETTABLEKS R4 R5 K98; var4 = var5["SHY"]
     405 [-]: SETTABLEN R4 R3 1; SETTABLEN R4 R3 1
     406 [-]: GETUPVAL R3 17; var3 = upvalues[17]
     407 [-]: GETUPVAL R5 7; var5 = upvalues[7]
     408 [-]: GETTABLEKS R4 R5 K102; var4 = var5["SURPRISED"]
     409 [-]: SETTABLEN R4 R3 2; SETTABLEN R4 R3 2
     410 [-]: GETUPVAL R3 17; var3 = upvalues[17]
     411 [-]: GETUPVAL R5 7; var5 = upvalues[7]
     412 [-]: GETTABLEKS R4 R5 K62; var4 = var5["ANGRY"]
     413 [-]: SETTABLEN R4 R3 3; SETTABLEN R4 R3 3
     414 [-]: JUMP L14     ; goto L14
L13: 415 [-]: GETUPVAL R3 17; var3 = upvalues[17]
     416 [-]: GETUPVAL R5 7; var5 = upvalues[7]
     417 [-]: GETIMPORT R7 126; var7 = _T["EmotionSelectionActiveEmotions"]
     418 [-]: GETTABLEN R6 R7 1; var6 = var7[1]
     419 [-]: GETTABLE R4 R5 R6; var4 = var5[var6]
     420 [-]: SETTABLEN R4 R3 1; SETTABLEN R4 R3 1
     421 [-]: GETUPVAL R3 17; var3 = upvalues[17]
     422 [-]: GETUPVAL R5 7; var5 = upvalues[7]
     423 [-]: GETIMPORT R7 126; var7 = _T["EmotionSelectionActiveEmotions"]
     424 [-]: GETTABLEN R6 R7 2; var6 = var7[2]
     425 [-]: GETTABLE R4 R5 R6; var4 = var5[var6]
     426 [-]: SETTABLEN R4 R3 2; SETTABLEN R4 R3 2
     427 [-]: GETUPVAL R3 17; var3 = upvalues[17]
     428 [-]: GETUPVAL R5 7; var5 = upvalues[7]
     429 [-]: GETIMPORT R7 126; var7 = _T["EmotionSelectionActiveEmotions"]
     430 [-]: GETTABLEN R6 R7 3; var6 = var7[3]
     431 [-]: GETTABLE R4 R5 R6; var4 = var5[var6]
     432 [-]: SETTABLEN R4 R3 3; SETTABLEN R4 R3 3
L14: 433 [-]: LOADN R5 1   ; var5 = 1
     434 [-]: LOADN R3 3   ; var3 = 3
     435 [-]: LOADN R4 1   ; var4 = 1
     436 [-]: FORNPREP R3 L17; nforprep start - [escape at L17] -- var3 = iterator
L15: 437 [-]: GETUPVAL R7 16; var7 = upvalues[16]
     438 [-]: GETTABLEKS R6 R7 K127; var6 = var7[0xAE97C4F5]
     439 [-]: GETUPVAL R8 6; var8 = upvalues[6]
     440 [-]: GETUPVAL R10 17; var10 = upvalues[17]
     441 [-]: GETTABLE R9 R10 R5; var9 = var10[var5]
     442 [-]: GETTABLE R7 R8 R9; var7 = var8[var9]
     443 [-]: CALL R6 2 2  ; var6 = var6(var7)
     444 [-]: GETUPVAL R8 17; var8 = upvalues[17]
     445 [-]: GETTABLE R7 R8 R5; var7 = var8[var5]
     446 [-]: SETTABLEKS R7 R6 K128; var7["Id"] = var6
     447 [-]: GETUPVAL R7 17; var7 = upvalues[17]
     448 [-]: SETTABLE R6 R7 R5; var6[var7] = var5
     449 [-]: LOADK R8 K129; var8 = "Card"
     450 [-]: MOVE R9 R5   ; var9 = var5
     451 [-]: CONCAT R7 R8 R9; var7 = var8 .. var9
     452 [-]: GETIMPORT R10 15; var10 = 0xAE91E43B
     453 [-]: NAMECALL R10 R10 K130; var11 = var10; var10 = var10[0x091C120E]
     454 [-]: CALL R10 2 2 ; var10 = var10(var11)
     455 [-]: MULK R9 R10 K13; var9 = var10 * 0.5
     456 [-]: LOADN R11 450; var11 = 450
     457 [-]: SUBK R12 R5 K131; var12 = var5 - 2
     458 [-]: MUL R10 R11 R12; var10 = var11 * var12
     459 [-]: ADD R8 R9 R10; var8 = var9 + var10
     460 [-]: GETIMPORT R9 15; var9 = 0xAE91E43B
     461 [-]: MOVE R11 R7  ; var11 = var7
     462 [-]: LOADN R12 0  ; var12 = 0
     463 [-]: MOVE R13 R8  ; var13 = var8
     464 [-]: NAMECALL R9 R9 K60; var10 = var9; var9 = var9[0x67BC869F]
     465 [-]: CALL R9 5 1  ; var9(var10, var11, var12, var13)
     466 [-]: GETIMPORT R9 15; var9 = 0xAE91E43B
     467 [-]: MOVE R11 R7  ; var11 = var7
     468 [-]: LOADN R12 1  ; var12 = 1
     469 [-]: LOADN R13 -500; var13 = -500
     470 [-]: NAMECALL R9 R9 K60; var10 = var9; var9 = var9[0x67BC869F]
     471 [-]: CALL R9 5 1  ; var9(var10, var11, var12, var13)
     472 [-]: GETIMPORT R9 15; var9 = 0xAE91E43B
     473 [-]: MOVE R11 R7  ; var11 = var7
     474 [-]: LOADN R12 14 ; var12 = 14
     475 [-]: LOADN R13 0  ; var13 = 0
     476 [-]: NAMECALL R9 R9 K60; var10 = var9; var9 = var9[0x67BC869F]
     477 [-]: CALL R9 5 1  ; var9(var10, var11, var12, var13)
     478 [-]: GETIMPORT R9 15; var9 = 0xAE91E43B
     479 [-]: MOVE R11 R7  ; var11 = var7
     480 [-]: LOADN R12 15 ; var12 = 15
     481 [-]: LOADN R13 -180; var13 = -180
     482 [-]: NAMECALL R9 R9 K60; var10 = var9; var9 = var9[0x67BC869F]
     483 [-]: CALL R9 5 1  ; var9(var10, var11, var12, var13)
     484 [-]: GETIMPORT R9 15; var9 = 0xAE91E43B
     485 [-]: MOVE R11 R7  ; var11 = var7
     486 [-]: LOADN R12 61 ; var12 = 61
     487 [-]: LOADB R13 0  ; var13 = false
     488 [-]: NAMECALL R9 R9 K118; var10 = var9; var9 = var9[0xAADE900E]
     489 [-]: CALL R9 5 1  ; var9(var10, var11, var12, var13)
     490 [-]: GETIMPORT R9 15; var9 = 0xAE91E43B
     491 [-]: MOVE R11 R7  ; var11 = var7
     492 [-]: LOADK R12 K132; var12 = "Back"
     493 [-]: LOADN R13 15 ; var13 = 15
     494 [-]: LOADN R14 180; var14 = 180
     495 [-]: NAMECALL R9 R9 K133; var10 = var9; var9 = var9[0xF64B7262]
     496 [-]: CALL R9 6 1  ; var9(var10, var11, var12, var13, var14)
     497 [-]: GETIMPORT R10 135; var10 = 0x3260BAFC
     498 [-]: GETIMPORT R11 137; var11 = 0x55730E1A
     499 [-]: LOADN R12 1  ; var12 = 1
     500 [-]: GETIMPORT R14 135; var14 = 0x3260BAFC
     501 [-]: LENGTH R13 R14; var13 = #var14
     502 [-]: CALL R11 3 2 ; var11 = var11(var12, var13)
     503 [-]: GETTABLE R9 R10 R11; var9 = var10[var11]
     504 [-]: GETIMPORT R10 15; var10 = 0xAE91E43B
     505 [-]: MOVE R13 R7  ; var13 = var7
     506 [-]: LOADK R14 K138; var14 = ".Emotion"
     507 [-]: CONCAT R12 R13 R14; var12 = var13 .. var14
     508 [-]: GETUPVAL R15 17; var15 = upvalues[17]
     509 [-]: GETTABLE R14 R15 R5; var14 = var15[var5]
     510 [-]: GETTABLEKS R13 R14 K112; var13 = var14["Image"]
     511 [-]: GETIMPORT R14 140; var14 = 0xE796CFE5
     512 [-]: NAMECALL R10 R10 K141; var11 = var10; var10 = var10[0xEF99134F]
     513 [-]: CALL R10 5 1 ; var10(var11, var12, var13, var14)
     514 [-]: GETIMPORT R10 15; var10 = 0xAE91E43B
     515 [-]: MOVE R13 R7  ; var13 = var7
     516 [-]: LOADK R14 K142; var14 = ".Front"
     517 [-]: CONCAT R12 R13 R14; var12 = var13 .. var14
     518 [-]: GETIMPORT R13 144; var13 = 0x7A409B3B
     519 [-]: GETIMPORT R14 140; var14 = 0xE796CFE5
     520 [-]: NAMECALL R10 R10 K141; var11 = var10; var10 = var10[0xEF99134F]
     521 [-]: CALL R10 5 1 ; var10(var11, var12, var13, var14)
     522 [-]: GETIMPORT R10 15; var10 = 0xAE91E43B
     523 [-]: MOVE R13 R7  ; var13 = var7
     524 [-]: LOADK R14 K145; var14 = ".Back"
     525 [-]: CONCAT R12 R13 R14; var12 = var13 .. var14
     526 [-]: MOVE R13 R9  ; var13 = var9
     527 [-]: GETIMPORT R14 140; var14 = 0xE796CFE5
     528 [-]: NAMECALL R10 R10 K141; var11 = var10; var10 = var10[0xEF99134F]
     529 [-]: CALL R10 5 1 ; var10(var11, var12, var13, var14)
     530 [-]: GETIMPORT R10 15; var10 = 0xAE91E43B
     531 [-]: MOVE R12 R7  ; var12 = var7
     532 [-]: LOADN R13 87 ; var13 = 87
     533 [-]: MOVE R14 R5  ; var14 = var5
     534 [-]: NAMECALL R10 R10 K60; var11 = var10; var10 = var10[0x67BC869F]
     535 [-]: CALL R10 5 1 ; var10(var11, var12, var13, var14)
     536 [-]: GETIMPORT R10 15; var10 = 0xAE91E43B
     537 [-]: MOVE R12 R7  ; var12 = var7
     538 [-]: LOADK R13 K146; var13 = "CardRollOver"
     539 [-]: LOADK R14 K147; var14 = "CardRollOut"
     540 [-]: LOADK R15 K148; var15 = "CardSelected"
     541 [-]: LOADK R16 K123; var16 = ""
     542 [-]: NAMECALL R10 R10 K124; var11 = var10; var10 = var10[0x1E5B5CFE]
     543 [-]: CALL R10 7 1 ; var10(var11, var12, var13, var14, var15, var16)
     544 [-]: LOADK R11 K21; var11 = "Emotion"
     545 [-]: MOVE R12 R5  ; var12 = var5
     546 [-]: CONCAT R10 R11 R12; var10 = var11 .. var12
     547 [-]: GETUPVAL R12 17; var12 = upvalues[17]
     548 [-]: GETTABLE R11 R12 R5; var11 = var12[var5]
     549 [-]: LOADB R12 1  ; var12 = true
     550 [-]: SETTABLEKS R12 R11 K149; var12["mActive"] = var11
     551 [-]: GETUPVAL R12 17; var12 = upvalues[17]
     552 [-]: GETTABLE R11 R12 R5; var11 = var12[var5]
     553 [-]: SETTABLEKS R10 R11 K150; var10["mClipName"] = var11
     554 [-]: GETUPVAL R13 17; var13 = upvalues[17]
     555 [-]: GETTABLE R12 R13 R5; var12 = var13[var5]
     556 [-]: GETTABLEKS R11 R12 K64; var11 = var12["Animation"]
     557 [-]: JUMPXEQKNIL R11 L16 NOT; 
     558 [-]: GETUPVAL R12 17; var12 = upvalues[17]
     559 [-]: GETTABLE R11 R12 R5; var11 = var12[var5]
     560 [-]: GETUPVAL R12 18; var12 = upvalues[18]
     561 [-]: SETTABLEKS R12 R11 K64; var12["Animation"] = var11
L16: 562 [-]: GETIMPORT R11 15; var11 = 0xAE91E43B
     563 [-]: MOVE R13 R10 ; var13 = var10
     564 [-]: LOADN R14 0  ; var14 = 0
     565 [-]: MOVE R15 R8  ; var15 = var8
     566 [-]: NAMECALL R11 R11 K60; var12 = var11; var11 = var11[0x67BC869F]
     567 [-]: CALL R11 5 1 ; var11(var12, var13, var14, var15)
     568 [-]: GETIMPORT R11 15; var11 = 0xAE91E43B
     569 [-]: MOVE R13 R10 ; var13 = var10
     570 [-]: LOADN R14 1  ; var14 = 1
     571 [-]: LOADN R15 740; var15 = 740
     572 [-]: NAMECALL R11 R11 K60; var12 = var11; var11 = var11[0x67BC869F]
     573 [-]: CALL R11 5 1 ; var11(var12, var13, var14, var15)
     574 [-]: GETIMPORT R11 15; var11 = 0xAE91E43B
     575 [-]: MOVE R13 R10 ; var13 = var10
     576 [-]: LOADN R14 5  ; var14 = 5
     577 [-]: LOADN R15 75 ; var15 = 75
     578 [-]: NAMECALL R11 R11 K60; var12 = var11; var11 = var11[0x67BC869F]
     579 [-]: CALL R11 5 1 ; var11(var12, var13, var14, var15)
     580 [-]: GETIMPORT R11 15; var11 = 0xAE91E43B
     581 [-]: MOVE R13 R10 ; var13 = var10
     582 [-]: LOADN R14 6  ; var14 = 6
     583 [-]: LOADN R15 75 ; var15 = 75
     584 [-]: NAMECALL R11 R11 K60; var12 = var11; var11 = var11[0x67BC869F]
     585 [-]: CALL R11 5 1 ; var11(var12, var13, var14, var15)
     586 [-]: GETIMPORT R11 15; var11 = 0xAE91E43B
     587 [-]: MOVE R13 R10 ; var13 = var10
     588 [-]: LOADN R14 10 ; var14 = 10
     589 [-]: LOADN R15 0  ; var15 = 0
     590 [-]: NAMECALL R11 R11 K60; var12 = var11; var11 = var11[0x67BC869F]
     591 [-]: CALL R11 5 1 ; var11(var12, var13, var14, var15)
     592 [-]: GETIMPORT R11 15; var11 = 0xAE91E43B
     593 [-]: MOVE R13 R10 ; var13 = var10
     594 [-]: LOADN R14 61 ; var14 = 61
     595 [-]: LOADB R15 0  ; var15 = false
     596 [-]: NAMECALL R11 R11 K118; var12 = var11; var11 = var11[0xAADE900E]
     597 [-]: CALL R11 5 1 ; var11(var12, var13, var14, var15)
     598 [-]: GETIMPORT R11 15; var11 = 0xAE91E43B
     599 [-]: MOVE R14 R10 ; var14 = var10
     600 [-]: LOADK R15 K151; var15 = ".Text"
     601 [-]: LOADN R16 1  ; var16 = 1
     602 [-]: LOADK R17 K152; var17 = ".Label.text"
     603 [-]: CONCAT R13 R14 R17; var13 = var14 .. var17
     604 [-]: GETUPVAL R16 17; var16 = upvalues[17]
     605 [-]: GETTABLE R15 R16 R5; var15 = var16[var5]
     606 [-]: GETTABLEKS R14 R15 K63; var14 = var15["Label"]
     607 [-]: NAMECALL R11 R11 K153; var12 = var11; var11 = var11[0x20B98DB3]
     608 [-]: CALL R11 4 1 ; var11(var12, var13, var14)
     609 [-]: GETIMPORT R11 15; var11 = 0xAE91E43B
     610 [-]: MOVE R14 R10 ; var14 = var10
     611 [-]: LOADK R15 K151; var15 = ".Text"
     612 [-]: LOADN R16 2  ; var16 = 2
     613 [-]: LOADK R17 K152; var17 = ".Label.text"
     614 [-]: CONCAT R13 R14 R17; var13 = var14 .. var17
     615 [-]: GETUPVAL R16 17; var16 = upvalues[17]
     616 [-]: GETTABLE R15 R16 R5; var15 = var16[var5]
     617 [-]: GETTABLEKS R14 R15 K63; var14 = var15["Label"]
     618 [-]: NAMECALL R11 R11 K153; var12 = var11; var11 = var11[0x20B98DB3]
     619 [-]: CALL R11 4 1 ; var11(var12, var13, var14)
     620 [-]: GETIMPORT R11 15; var11 = 0xAE91E43B
     621 [-]: MOVE R14 R10 ; var14 = var10
     622 [-]: LOADK R15 K151; var15 = ".Text"
     623 [-]: LOADN R16 3  ; var16 = 3
     624 [-]: LOADK R17 K152; var17 = ".Label.text"
     625 [-]: CONCAT R13 R14 R17; var13 = var14 .. var17
     626 [-]: GETUPVAL R16 17; var16 = upvalues[17]
     627 [-]: GETTABLE R15 R16 R5; var15 = var16[var5]
     628 [-]: GETTABLEKS R14 R15 K63; var14 = var15["Label"]
     629 [-]: NAMECALL R11 R11 K153; var12 = var11; var11 = var11[0x20B98DB3]
     630 [-]: CALL R11 4 1 ; var11(var12, var13, var14)
     631 [-]: FORNLOOP R3 L15; nforloop end - iterate + goto L15
L17: 632 [-]: GETIMPORT R3 15; var3 = 0xAE91E43B
     633 [-]: LOADK R5 K154; var5 = "Emotion4"
     634 [-]: LOADN R6 11  ; var6 = 11
     635 [-]: LOADB R7 0   ; var7 = false
     636 [-]: NAMECALL R3 R3 K118; var4 = var3; var3 = var3[0xAADE900E]
     637 [-]: CALL R3 5 1  ; var3(var4, var5, var6, var7)
     638 [-]: GETIMPORT R3 15; var3 = 0xAE91E43B
     639 [-]: LOADK R5 K154; var5 = "Emotion4"
     640 [-]: LOADN R6 61  ; var6 = 61
     641 [-]: LOADB R7 0   ; var7 = false
     642 [-]: NAMECALL R3 R3 K118; var4 = var3; var3 = var3[0xAADE900E]
     643 [-]: CALL R3 5 1  ; var3(var4, var5, var6, var7)
     644 [-]: GETUPVAL R3 19; var3 = upvalues[19]
     645 [-]: NEWCLOSURE R4 P0; 
     646 [-]: CAPTURE UPVAL U20; 
     647 [-]: CAPTURE UPVAL U3; 
     648 [-]: CAPTURE UPVAL U21; 
     649 [-]: CAPTURE UPVAL U16; 
     650 [-]: CAPTURE UPVAL U22; 
     651 [-]: CAPTURE UPVAL U23; 
     652 [-]: CAPTURE UPVAL U24; 
     653 [-]: CALL R3 2 1  ; var3(var4)
     654 [-]: JUMP L19     ; goto L19
L18: 655 [-]: GETIMPORT R3 15; var3 = 0xAE91E43B
     656 [-]: LOADK R6 K129; var6 = "Card"
     657 [-]: LOADN R7 2   ; var7 = 2
     658 [-]: CONCAT R5 R6 R7; var5 = var6 .. var7
     659 [-]: LOADN R6 11  ; var6 = 11
     660 [-]: LOADB R7 0   ; var7 = false
     661 [-]: NAMECALL R3 R3 K118; var4 = var3; var3 = var3[0xAADE900E]
     662 [-]: CALL R3 5 1  ; var3(var4, var5, var6, var7)
     663 [-]: GETIMPORT R3 15; var3 = 0xAE91E43B
     664 [-]: LOADK R6 K129; var6 = "Card"
     665 [-]: LOADN R7 2   ; var7 = 2
     666 [-]: CONCAT R5 R6 R7; var5 = var6 .. var7
     667 [-]: LOADN R6 61  ; var6 = 61
     668 [-]: LOADB R7 0   ; var7 = false
     669 [-]: NAMECALL R3 R3 K118; var4 = var3; var3 = var3[0xAADE900E]
     670 [-]: CALL R3 5 1  ; var3(var4, var5, var6, var7)
     671 [-]: GETIMPORT R3 15; var3 = 0xAE91E43B
     672 [-]: LOADK R6 K129; var6 = "Card"
     673 [-]: LOADN R7 3   ; var7 = 3
     674 [-]: CONCAT R5 R6 R7; var5 = var6 .. var7
     675 [-]: LOADN R6 11  ; var6 = 11
     676 [-]: LOADB R7 0   ; var7 = false
     677 [-]: NAMECALL R3 R3 K118; var4 = var3; var3 = var3[0xAADE900E]
     678 [-]: CALL R3 5 1  ; var3(var4, var5, var6, var7)
     679 [-]: GETIMPORT R3 15; var3 = 0xAE91E43B
     680 [-]: LOADK R6 K129; var6 = "Card"
     681 [-]: LOADN R7 3   ; var7 = 3
     682 [-]: CONCAT R5 R6 R7; var5 = var6 .. var7
     683 [-]: LOADN R6 61  ; var6 = 61
     684 [-]: LOADB R7 0   ; var7 = false
     685 [-]: NAMECALL R3 R3 K118; var4 = var3; var3 = var3[0xAADE900E]
     686 [-]: CALL R3 5 1  ; var3(var4, var5, var6, var7)
     687 [-]: NEWTABLE R3 0 0; var3 = {}
     688 [-]: SETUPVAL R3 25; upvalues[3] = var25
     689 [-]: LOADN R3 0   ; var3 = 0
     690 [-]: SETUPVAL R3 26; upvalues[3] = var26
     691 [-]: GETUPVAL R3 25; var3 = upvalues[25]
     692 [-]: DUPTABLE R4 159; 
     693 [-]: GETUPVAL R6 7; var6 = upvalues[7]
     694 [-]: GETTABLEKS R5 R6 K94; var5 = var6["SAD"]
     695 [-]: SETTABLEKS R5 R4 K21; var5["Emotion"] = var4
     696 [-]: NEWTABLE R5 0 4; var5 = {}
     697 [-]: GETUPVAL R7 7; var7 = upvalues[7]
     698 [-]: GETTABLEKS R6 R7 K94; var6 = var7["SAD"]
     699 [-]: GETUPVAL R8 7; var8 = upvalues[7]
     700 [-]: GETTABLEKS R7 R8 K62; var7 = var8["ANGRY"]
     701 [-]: GETUPVAL R9 7; var9 = upvalues[7]
     702 [-]: GETTABLEKS R8 R9 K73; var8 = var9["CONFUSED"]
     703 [-]: GETUPVAL R10 7; var10 = upvalues[7]
     704 [-]: GETTABLEKS R9 R10 K100; var9 = var10["SICK"]
     705 [-]: SETLIST R5 R6 4 [1]; var5[1] = var6; var5[2] = var7; var5[3] = var8; var5[4] = var9; var5[5] = var10; 
     706 [-]: SETTABLEKS R5 R4 K155; var5["Options"] = var4
     707 [-]: LOADN R5 1   ; var5 = 1
     708 [-]: SETTABLEKS R5 R4 K156; var5["Delay"] = var4
     709 [-]: GETIMPORT R5 161; var5 = 0x6D769367
     710 [-]: SETTABLEKS R5 R4 K157; var5["StartTransmission"] = var4
     711 [-]: GETIMPORT R5 163; var5 = 0xF22C1866
     712 [-]: SETTABLEKS R5 R4 K158; var5["CompleteTransmission"] = var4
     713 [-]: SETTABLEN R4 R3 1; SETTABLEN R4 R3 1
     714 [-]: GETUPVAL R3 25; var3 = upvalues[25]
     715 [-]: DUPTABLE R4 159; 
     716 [-]: GETUPVAL R6 7; var6 = upvalues[7]
     717 [-]: GETTABLEKS R5 R6 K79; var5 = var6["EMBARRASSED"]
     718 [-]: SETTABLEKS R5 R4 K21; var5["Emotion"] = var4
     719 [-]: NEWTABLE R5 0 4; var5 = {}
     720 [-]: GETUPVAL R7 7; var7 = upvalues[7]
     721 [-]: GETTABLEKS R6 R7 K79; var6 = var7["EMBARRASSED"]
     722 [-]: GETUPVAL R8 7; var8 = upvalues[7]
     723 [-]: GETTABLEKS R7 R8 K102; var7 = var8["SURPRISED"]
     724 [-]: GETUPVAL R9 7; var9 = upvalues[7]
     725 [-]: GETTABLEKS R8 R9 K106; var8 = var9["TIRED"]
     726 [-]: GETUPVAL R10 7; var10 = upvalues[7]
     727 [-]: GETTABLEKS R9 R10 K98; var9 = var10["SHY"]
     728 [-]: SETLIST R5 R6 4 [1]; var5[1] = var6; var5[2] = var7; var5[3] = var8; var5[4] = var9; var5[5] = var10; 
     729 [-]: SETTABLEKS R5 R4 K155; var5["Options"] = var4
     730 [-]: LOADN R5 1   ; var5 = 1
     731 [-]: SETTABLEKS R5 R4 K156; var5["Delay"] = var4
     732 [-]: GETIMPORT R5 165; var5 = 0xC0F10009
     733 [-]: SETTABLEKS R5 R4 K157; var5["StartTransmission"] = var4
     734 [-]: GETIMPORT R5 167; var5 = 0x333FE59C
     735 [-]: SETTABLEKS R5 R4 K158; var5["CompleteTransmission"] = var4
     736 [-]: SETTABLEN R4 R3 2; SETTABLEN R4 R3 2
     737 [-]: GETUPVAL R3 25; var3 = upvalues[25]
     738 [-]: DUPTABLE R4 169; 
     739 [-]: GETUPVAL R6 7; var6 = upvalues[7]
     740 [-]: GETTABLEKS R5 R6 K90; var5 = var6["NERVOUS"]
     741 [-]: SETTABLEKS R5 R4 K21; var5["Emotion"] = var4
     742 [-]: NEWTABLE R5 0 4; var5 = {}
     743 [-]: GETUPVAL R7 7; var7 = upvalues[7]
     744 [-]: GETTABLEKS R6 R7 K90; var6 = var7["NERVOUS"]
     745 [-]: GETUPVAL R8 7; var8 = upvalues[7]
     746 [-]: GETTABLEKS R7 R8 K81; var7 = var8["EXCITED"]
     747 [-]: GETUPVAL R9 7; var9 = upvalues[7]
     748 [-]: GETTABLEKS R8 R9 K84; var8 = var9["GRUMPY"]
     749 [-]: GETUPVAL R10 7; var10 = upvalues[7]
     750 [-]: GETTABLEKS R9 R10 K106; var9 = var10["TIRED"]
     751 [-]: SETLIST R5 R6 4 [1]; var5[1] = var6; var5[2] = var7; var5[3] = var8; var5[4] = var9; var5[5] = var10; 
     752 [-]: SETTABLEKS R5 R4 K155; var5["Options"] = var4
     753 [-]: LOADN R5 9   ; var5 = 9
     754 [-]: SETTABLEKS R5 R4 K156; var5["Delay"] = var4
     755 [-]: GETIMPORT R5 171; var5 = 0xC0C13CE0
     756 [-]: SETTABLEKS R5 R4 K157; var5["StartTransmission"] = var4
     757 [-]: GETIMPORT R5 173; var5 = 0x5D888CC5
     758 [-]: SETTABLEKS R5 R4 K158; var5["CompleteTransmission"] = var4
     759 [-]: LOADK R5 K174; var5 = 5.5
     760 [-]: SETTABLEKS R5 R4 K168; var5["EmotionDelay"] = var4
     761 [-]: SETTABLEN R4 R3 3; SETTABLEN R4 R3 3
     762 [-]: GETUPVAL R3 25; var3 = upvalues[25]
     763 [-]: DUPTABLE R4 159; 
     764 [-]: GETUPVAL R6 7; var6 = upvalues[7]
     765 [-]: GETTABLEKS R5 R6 K73; var5 = var6["CONFUSED"]
     766 [-]: SETTABLEKS R5 R4 K21; var5["Emotion"] = var4
     767 [-]: NEWTABLE R5 0 4; var5 = {}
     768 [-]: GETUPVAL R7 7; var7 = upvalues[7]
     769 [-]: GETTABLEKS R6 R7 K73; var6 = var7["CONFUSED"]
     770 [-]: GETUPVAL R8 7; var8 = upvalues[7]
     771 [-]: GETTABLEKS R7 R8 K92; var7 = var8["PROUD"]
     772 [-]: GETUPVAL R9 7; var9 = upvalues[7]
     773 [-]: GETTABLEKS R8 R9 K88; var8 = var9["HUNGRY"]
     774 [-]: GETUPVAL R10 7; var10 = upvalues[7]
     775 [-]: GETTABLEKS R9 R10 K96; var9 = var10["SCARED"]
     776 [-]: SETLIST R5 R6 4 [1]; var5[1] = var6; var5[2] = var7; var5[3] = var8; var5[4] = var9; var5[5] = var10; 
     777 [-]: SETTABLEKS R5 R4 K155; var5["Options"] = var4
     778 [-]: LOADN R5 4   ; var5 = 4
     779 [-]: SETTABLEKS R5 R4 K156; var5["Delay"] = var4
     780 [-]: GETIMPORT R5 176; var5 = 0xC6722539
     781 [-]: SETTABLEKS R5 R4 K157; var5["StartTransmission"] = var4
     782 [-]: GETIMPORT R5 178; var5 = 0xA8F6F1CC
     783 [-]: SETTABLEKS R5 R4 K158; var5["CompleteTransmission"] = var4
     784 [-]: SETTABLEN R4 R3 4; SETTABLEN R4 R3 4
     785 [-]: GETUPVAL R3 25; var3 = upvalues[25]
     786 [-]: DUPTABLE R4 159; 
     787 [-]: GETUPVAL R6 7; var6 = upvalues[7]
     788 [-]: GETTABLEKS R5 R6 K84; var5 = var6["GRUMPY"]
     789 [-]: SETTABLEKS R5 R4 K21; var5["Emotion"] = var4
     790 [-]: NEWTABLE R5 0 4; var5 = {}
     791 [-]: GETUPVAL R7 7; var7 = upvalues[7]
     792 [-]: GETTABLEKS R6 R7 K84; var6 = var7["GRUMPY"]
     793 [-]: GETUPVAL R8 7; var8 = upvalues[7]
     794 [-]: GETTABLEKS R7 R8 K70; var7 = var8["BORED"]
     795 [-]: GETUPVAL R9 7; var9 = upvalues[7]
     796 [-]: GETTABLEKS R8 R9 K77; var8 = var9["DISGUSTED"]
     797 [-]: GETUPVAL R10 7; var10 = upvalues[7]
     798 [-]: GETTABLEKS R9 R10 K90; var9 = var10["NERVOUS"]
     799 [-]: SETLIST R5 R6 4 [1]; var5[1] = var6; var5[2] = var7; var5[3] = var8; var5[4] = var9; var5[5] = var10; 
     800 [-]: SETTABLEKS R5 R4 K155; var5["Options"] = var4
     801 [-]: LOADN R5 7   ; var5 = 7
     802 [-]: SETTABLEKS R5 R4 K156; var5["Delay"] = var4
     803 [-]: GETIMPORT R5 180; var5 = 0x3CE8FA14
     804 [-]: SETTABLEKS R5 R4 K157; var5["StartTransmission"] = var4
     805 [-]: GETIMPORT R5 182; var5 = 0xDF1036D9
     806 [-]: SETTABLEKS R5 R4 K158; var5["CompleteTransmission"] = var4
     807 [-]: SETTABLEN R4 R3 5; SETTABLEN R4 R3 5
     808 [-]: GETUPVAL R3 25; var3 = upvalues[25]
     809 [-]: DUPTABLE R4 159; 
     810 [-]: GETUPVAL R6 7; var6 = upvalues[7]
     811 [-]: GETTABLEKS R5 R6 K86; var5 = var6["HAPPY"]
     812 [-]: SETTABLEKS R5 R4 K21; var5["Emotion"] = var4
     813 [-]: NEWTABLE R5 0 4; var5 = {}
     814 [-]: GETUPVAL R7 7; var7 = upvalues[7]
     815 [-]: GETTABLEKS R6 R7 K86; var6 = var7["HAPPY"]
     816 [-]: GETUPVAL R8 7; var8 = upvalues[7]
     817 [-]: GETTABLEKS R7 R8 K86; var7 = var8["HAPPY"]
     818 [-]: GETUPVAL R9 7; var9 = upvalues[7]
     819 [-]: GETTABLEKS R8 R9 K86; var8 = var9["HAPPY"]
     820 [-]: GETUPVAL R10 7; var10 = upvalues[7]
     821 [-]: GETTABLEKS R9 R10 K86; var9 = var10["HAPPY"]
     822 [-]: SETLIST R5 R6 4 [1]; var5[1] = var6; var5[2] = var7; var5[3] = var8; var5[4] = var9; var5[5] = var10; 
     823 [-]: SETTABLEKS R5 R4 K155; var5["Options"] = var4
     824 [-]: LOADN R5 4   ; var5 = 4
     825 [-]: SETTABLEKS R5 R4 K156; var5["Delay"] = var4
     826 [-]: GETIMPORT R5 184; var5 = 0x7075CAB9
     827 [-]: SETTABLEKS R5 R4 K157; var5["StartTransmission"] = var4
     828 [-]: GETIMPORT R5 186; var5 = 0x6C54D34C
     829 [-]: SETTABLEKS R5 R4 K158; var5["CompleteTransmission"] = var4
     830 [-]: SETTABLEN R4 R3 6; SETTABLEN R4 R3 6
     831 [-]: GETUPVAL R3 19; var3 = upvalues[19]
     832 [-]: GETUPVAL R4 27; var4 = upvalues[27]
     833 [-]: CALL R3 2 1  ; var3(var4)
L19: 834 [-]: GETUPVAL R3 28; var3 = upvalues[28]
     835 [-]: CALL R3 1 1  ; var3()
     836 [-]: RETURN R0 0  ; 


; Name:            
; Defined at line: 882
; #Upvalues:       12
; #Parameters:     0
; Is_vararg:       0
; Max Stack Size:  11

       0 [-]: GETIMPORT R0 1; var0 = 0x67652851
       1 [-]: CALL R0 1 2  ; var0 = var0()
       2 [-]: GETIMPORT R1 3; var1 = 0xAE91E43B
       3 [-]: MOVE R3 R0   ; var3 = var0
       4 [-]: NAMECALL R1 R1 K4; var2 = var1; var1 = var1[0x8A8C8D5A]
       5 [-]: CALL R1 3 1  ; var1(var2, var3)
       6 [-]: GETUPVAL R2 0; var2 = upvalues[0]
       7 [-]: FASTCALL1 64 R2 L0; 
       8 [-]: GETIMPORT R1 6; var1 = 0x7B998233
       9 [-]: CALL R1 2 2  ; var1 = var1(var2)
L 0:  10 [-]: JUMPIF R1 L1 ; goto L1 if var1
      11 [-]: GETUPVAL R1 0; var1 = upvalues[0]
      12 [-]: MOVE R3 R0   ; var3 = var0
      13 [-]: NAMECALL R1 R1 K7; var2 = var1; var1 = var1[0xFAA69527]
      14 [-]: CALL R1 3 1  ; var1(var2, var3)
L 1:  15 [-]: GETUPVAL R1 1; var1 = upvalues[1]
      16 [-]: JUMPIFNOT R1 L2; goto L2 if not var1
      17 [-]: GETIMPORT R1 9; var1 = 0xF7F90318
      18 [-]: GETIMPORT R3 12; var3 = 0x55156FF7
      19 [-]: CALL R3 1 2  ; var3 = var3()
      20 [-]: MULK R2 R3 K10; var2 = var3 * 0.10000000149011612
      21 [-]: CALL R1 2 2  ; var1 = var1(var2)
      22 [-]: GETIMPORT R2 9; var2 = 0xF7F90318
      23 [-]: GETIMPORT R4 12; var4 = 0x55156FF7
      24 [-]: CALL R4 1 2  ; var4 = var4()
      25 [-]: MULK R3 R4 K13; var3 = var4 * 0.05000000074505806
      26 [-]: CALL R2 2 2  ; var2 = var2(var3)
      27 [-]: GETUPVAL R3 2; var3 = upvalues[2]
      28 [-]: GETIMPORT R7 3; var7 = 0xAE91E43B
      29 [-]: NAMECALL R7 R7 K15; var8 = var7; var7 = var7[0x091C120E]
      30 [-]: CALL R7 2 2  ; var7 = var7(var8)
      31 [-]: MULK R6 R7 K14; var6 = var7 * 0.5
      32 [-]: MULK R7 R1 K16; var7 = var1 * 30
      33 [-]: ADD R5 R6 R7 ; var5 = var6 + var7
      34 [-]: NAMECALL R3 R3 K17; var4 = var3; var3 = var3[0x188E2BEE]
      35 [-]: CALL R3 3 1  ; var3(var4, var5)
      36 [-]: GETUPVAL R3 3; var3 = upvalues[3]
      37 [-]: GETUPVAL R6 4; var6 = upvalues[4]
      38 [-]: MULK R7 R2 K18; var7 = var2 * 80
      39 [-]: ADD R5 R6 R7 ; var5 = var6 + var7
      40 [-]: NAMECALL R3 R3 K17; var4 = var3; var3 = var3[0x188E2BEE]
      41 [-]: CALL R3 3 1  ; var3(var4, var5)
      42 [-]: GETUPVAL R3 2; var3 = upvalues[2]
      43 [-]: MOVE R5 R0   ; var5 = var0
      44 [-]: NAMECALL R3 R3 K7; var4 = var3; var3 = var3[0xFAA69527]
      45 [-]: CALL R3 3 1  ; var3(var4, var5)
      46 [-]: GETUPVAL R3 3; var3 = upvalues[3]
      47 [-]: MOVE R5 R0   ; var5 = var0
      48 [-]: NAMECALL R3 R3 K7; var4 = var3; var3 = var3[0xFAA69527]
      49 [-]: CALL R3 3 1  ; var3(var4, var5)
      50 [-]: GETIMPORT R3 3; var3 = 0xAE91E43B
      51 [-]: LOADK R5 K19 ; var5 = "Card1"
      52 [-]: LOADN R6 0   ; var6 = 0
      53 [-]: GETUPVAL R7 2; var7 = upvalues[2]
      54 [-]: NAMECALL R7 R7 K20; var8 = var7; var7 = var7[0x54AB95F9]
      55 [-]: CALL R7 2 0  ; var7, ... = var7(var8)
      56 [-]: NAMECALL R3 R3 K21; var4 = var3; var3 = var3[0x67BC869F]
      57 [-]: CALL R3 0 1  ; var3(var4, ...)
      58 [-]: GETIMPORT R3 3; var3 = 0xAE91E43B
      59 [-]: LOADK R5 K19 ; var5 = "Card1"
      60 [-]: LOADN R6 1   ; var6 = 1
      61 [-]: GETUPVAL R7 3; var7 = upvalues[3]
      62 [-]: NAMECALL R7 R7 K20; var8 = var7; var7 = var7[0x54AB95F9]
      63 [-]: CALL R7 2 0  ; var7, ... = var7(var8)
      64 [-]: NAMECALL R3 R3 K21; var4 = var3; var3 = var3[0x67BC869F]
      65 [-]: CALL R3 0 1  ; var3(var4, ...)
L 2:  66 [-]: GETUPVAL R1 5; var1 = upvalues[5]
      67 [-]: JUMPIF R1 L3 ; goto L3 if var1
      68 [-]: JUMP L9      ; goto L9
L 3:  69 [-]: GETIMPORT R1 3; var1 = 0xAE91E43B
      70 [-]: LOADK R3 K19 ; var3 = "Card1"
      71 [-]: NAMECALL R1 R1 K22; var2 = var1; var1 = var1[0xBF8F0712]
      72 [-]: CALL R1 3 2  ; var1 = var1(var2, var3)
      73 [-]: JUMPIF R1 L9 ; goto L9 if var1
      74 [-]: LOADN R1 0   ; var1 = 0
      75 [-]: LOADN R2 0   ; var2 = 0
      76 [-]: GETUPVAL R3 6; var3 = upvalues[6]
      77 [-]: JUMPIF R3 L8 ; goto L8 if var3
      78 [-]: LOADN R3 0   ; var3 = 0
      79 [-]: LOADN R4 0   ; var4 = 0
      80 [-]: GETIMPORT R5 25; var5 = 0x34291F5C[0x1467D5F4]
      81 [-]: CALL R5 1 2  ; var5 = var5()
      82 [-]: JUMPIFNOT R5 L6; goto L6 if not var5
      83 [-]: GETUPVAL R6 7; var6 = upvalues[7]
      84 [-]: GETUPVAL R8 8; var8 = upvalues[8]
      85 [-]: ADDK R7 R8 K26; var7 = var8 + 1
      86 [-]: GETTABLE R5 R6 R7; var5 = var6[var7]
      87 [-]: FASTCALL1 64 R5 L4; 
      88 [-]: MOVE R7 R5   ; var7 = var5
      89 [-]: GETIMPORT R6 6; var6 = 0x7B998233
      90 [-]: CALL R6 2 2  ; var6 = var6(var7)
L 4:  91 [-]: JUMPIF R6 L7 ; goto L7 if var6
      92 [-]: GETUPVAL R7 9; var7 = upvalues[9]
      93 [-]: ADDK R8 R5 K26; var8 = var5 + 1
      94 [-]: GETTABLE R6 R7 R8; var6 = var7[var8]
      95 [-]: FASTCALL1 64 R6 L5; 
      96 [-]: MOVE R8 R6   ; var8 = var6
      97 [-]: GETIMPORT R7 6; var7 = 0x7B998233
      98 [-]: CALL R7 2 2  ; var7 = var7(var8)
L 5:  99 [-]: JUMPIF R7 L7 ; goto L7 if var7
     100 [-]: GETIMPORT R7 3; var7 = 0xAE91E43B
     101 [-]: GETTABLEKS R9 R6 K27; var9 = var6["mClipName"]
     102 [-]: LOADN R10 0  ; var10 = 0
     103 [-]: NAMECALL R7 R7 K28; var8 = var7; var7 = var7[0x91A24E4B]
     104 [-]: CALL R7 4 2  ; var7 = var7(var8, var9, var10)
     105 [-]: MOVE R3 R7   ; var3 = var7
     106 [-]: GETIMPORT R7 3; var7 = 0xAE91E43B
     107 [-]: GETTABLEKS R9 R6 K27; var9 = var6["mClipName"]
     108 [-]: LOADN R10 1  ; var10 = 1
     109 [-]: NAMECALL R7 R7 K28; var8 = var7; var7 = var7[0x91A24E4B]
     110 [-]: CALL R7 4 2  ; var7 = var7(var8, var9, var10)
     111 [-]: MOVE R4 R7   ; var4 = var7
     112 [-]: JUMP L7      ; goto L7
L 6: 113 [-]: GETIMPORT R5 3; var5 = 0xAE91E43B
     114 [-]: LOADK R7 K29 ; var7 = "_root"
     115 [-]: LOADN R8 27  ; var8 = 27
     116 [-]: NAMECALL R5 R5 K28; var6 = var5; var5 = var5[0x91A24E4B]
     117 [-]: CALL R5 4 2  ; var5 = var5(var6, var7, var8)
     118 [-]: MOVE R3 R5   ; var3 = var5
     119 [-]: GETIMPORT R5 3; var5 = 0xAE91E43B
     120 [-]: LOADK R7 K29 ; var7 = "_root"
     121 [-]: LOADN R8 28  ; var8 = 28
     122 [-]: NAMECALL R5 R5 K28; var6 = var5; var5 = var5[0x91A24E4B]
     123 [-]: CALL R5 4 2  ; var5 = var5(var6, var7, var8)
     124 [-]: MOVE R4 R5   ; var4 = var5
L 7: 125 [-]: GETUPVAL R5 2; var5 = upvalues[2]
     126 [-]: NAMECALL R5 R5 K20; var6 = var5; var5 = var5[0x54AB95F9]
     127 [-]: CALL R5 2 2  ; var5 = var5(var6)
     128 [-]: SUB R1 R5 R3 ; var1 = var5 - var3
     129 [-]: GETUPVAL R5 3; var5 = upvalues[3]
     130 [-]: NAMECALL R5 R5 K20; var6 = var5; var5 = var5[0x54AB95F9]
     131 [-]: CALL R5 2 2  ; var5 = var5(var6)
     132 [-]: SUB R2 R5 R4 ; var2 = var5 - var4
L 8: 133 [-]: GETIMPORT R3 31; var3 = 0x42DCC9F5
     134 [-]: MULK R4 R1 K32; var4 = var1 * 0.20000000298023224
     135 [-]: LOADN R5 -25 ; var5 = -25
     136 [-]: LOADN R6 25  ; var6 = 25
     137 [-]: CALL R3 4 2  ; var3 = var3(var4, var5, var6)
     138 [-]: MOVE R1 R3   ; var1 = var3
     139 [-]: GETUPVAL R3 10; var3 = upvalues[10]
     140 [-]: MOVE R5 R1   ; var5 = var1
     141 [-]: NAMECALL R3 R3 K17; var4 = var3; var3 = var3[0x188E2BEE]
     142 [-]: CALL R3 3 1  ; var3(var4, var5)
     143 [-]: GETIMPORT R3 31; var3 = 0x42DCC9F5
     144 [-]: MULK R4 R2 K33; var4 = var2 * -0.10000000149011612
     145 [-]: LOADN R5 -20 ; var5 = -20
     146 [-]: LOADN R6 20  ; var6 = 20
     147 [-]: CALL R3 4 2  ; var3 = var3(var4, var5, var6)
     148 [-]: MOVE R2 R3   ; var2 = var3
     149 [-]: GETUPVAL R3 11; var3 = upvalues[11]
     150 [-]: MOVE R5 R2   ; var5 = var2
     151 [-]: NAMECALL R3 R3 K17; var4 = var3; var3 = var3[0x188E2BEE]
     152 [-]: CALL R3 3 1  ; var3(var4, var5)
     153 [-]: GETUPVAL R3 10; var3 = upvalues[10]
     154 [-]: MOVE R5 R0   ; var5 = var0
     155 [-]: NAMECALL R3 R3 K7; var4 = var3; var3 = var3[0xFAA69527]
     156 [-]: CALL R3 3 1  ; var3(var4, var5)
     157 [-]: GETUPVAL R3 11; var3 = upvalues[11]
     158 [-]: MOVE R5 R0   ; var5 = var0
     159 [-]: NAMECALL R3 R3 K7; var4 = var3; var3 = var3[0xFAA69527]
     160 [-]: CALL R3 3 1  ; var3(var4, var5)
     161 [-]: GETIMPORT R3 3; var3 = 0xAE91E43B
     162 [-]: LOADK R5 K19 ; var5 = "Card1"
     163 [-]: LOADN R6 15  ; var6 = 15
     164 [-]: GETUPVAL R7 10; var7 = upvalues[10]
     165 [-]: NAMECALL R7 R7 K20; var8 = var7; var7 = var7[0x54AB95F9]
     166 [-]: CALL R7 2 0  ; var7, ... = var7(var8)
     167 [-]: NAMECALL R3 R3 K21; var4 = var3; var3 = var3[0x67BC869F]
     168 [-]: CALL R3 0 1  ; var3(var4, ...)
     169 [-]: GETIMPORT R3 3; var3 = 0xAE91E43B
     170 [-]: LOADK R5 K19 ; var5 = "Card1"
     171 [-]: LOADN R6 16  ; var6 = 16
     172 [-]: GETUPVAL R7 11; var7 = upvalues[11]
     173 [-]: NAMECALL R7 R7 K20; var8 = var7; var7 = var7[0x54AB95F9]
     174 [-]: CALL R7 2 0  ; var7, ... = var7(var8)
     175 [-]: NAMECALL R3 R3 K21; var4 = var3; var3 = var3[0x67BC869F]
     176 [-]: CALL R3 0 1  ; var3(var4, ...)
L 9: 177 [-]: LOADN R3 1   ; var3 = 1
     178 [-]: GETUPVAL R4 9; var4 = upvalues[9]
     179 [-]: LENGTH R1 R4 ; var1 = #var4
     180 [-]: LOADN R2 1   ; var2 = 1
     181 [-]: FORNPREP R1 L11; nforprep start - [escape at L11] -- var1 = iterator
L10: 182 [-]: GETUPVAL R6 9; var6 = upvalues[9]
     183 [-]: GETTABLE R5 R6 R3; var5 = var6[var3]
     184 [-]: GETTABLEKS R4 R5 K34; var4 = var5["Animation"]
     185 [-]: MOVE R5 R0   ; var5 = var0
     186 [-]: GETUPVAL R7 9; var7 = upvalues[9]
     187 [-]: GETTABLE R6 R7 R3; var6 = var7[var3]
     188 [-]: CALL R4 3 1  ; var4(var5, var6)
     189 [-]: FORNLOOP R1 L10; nforloop end - iterate + goto L10
L11: 190 [-]: RETURN R0 0  ; 


; Name:            
; Defined at line: 948
; #Upvalues:       1
; #Parameters:     2
; Is_vararg:       0
; Max Stack Size:  3

       0 [-]: GETUPVAL R2 0; var2 = upvalues[0]
       1 [-]: CALL R2 1 1  ; var2()
       2 [-]: RETURN R0 0  ; 


; Name:            
; Defined at line: 952
; #Upvalues:       5
; #Parameters:     1
; Is_vararg:       0
; Max Stack Size:  10

       0 [-]: GETUPVAL R1 0; var1 = upvalues[0]
       1 [-]: JUMPXEQKNIL R1 L0; 
       2 [-]: GETUPVAL R1 1; var1 = upvalues[1]
       3 [-]: GETUPVAL R3 0; var3 = upvalues[0]
       4 [-]: NAMECALL R1 R1 K0; var2 = var1; var1 = var1[0x775C858B]
       5 [-]: CALL R1 3 1  ; var1(var2, var3)
       6 [-]: LOADNIL R1   ; var1 = nil
       7 [-]: SETUPVAL R1 0; upvalues[1] = var0
L 0:   8 [-]: FASTCALL2K 45 R0 K1 L1; 
       9 [-]: MOVE R3 R0   ; var3 = var0
      10 [-]: LOADK R4 K1  ; var4 = -1
      11 [-]: GETIMPORT R2 4; var2 = 0x7F5022CF[0x1A94C9CC]
      12 [-]: CALL R2 3 2  ; var2 = var2(var3, var4)
L 1:  13 [-]: FASTCALL1 62 R2 L2; 
      14 [-]: GETIMPORT R1 6; var1 = 0x03F57322
      15 [-]: CALL R1 2 2  ; var1 = var1(var2)
L 2:  16 [-]: GETUPVAL R2 2; var2 = upvalues[2]
      17 [-]: JUMPIFEQ R2 R1 L3; goto L3 if var2 == var131337
      18 [-]: SETUPVAL R1 2; upvalues[1] = var2
      19 [-]: GETUPVAL R3 3; var3 = upvalues[3]
      20 [-]: GETTABLEKS R2 R3 K7; var2 = var3[0x659D451F]
      21 [-]: GETIMPORT R3 9; var3 = 0x1E123824
      22 [-]: CALL R2 2 1  ; var2(var3)
L 3:  23 [-]: GETIMPORT R2 11; var2 = 0x25312C9B
      24 [-]: GETIMPORT R3 13; var3 = 0xAE91E43B
      25 [-]: LOADK R5 K14 ; var5 = "Card"
      26 [-]: MOVE R6 R1   ; var6 = var1
      27 [-]: CONCAT R4 R5 R6; var4 = var5 .. var6
      28 [-]: LOADN R5 2   ; var5 = 2
      29 [-]: NEWTABLE R6 0 2; var6 = {}
      30 [-]: LOADN R7 5   ; var7 = 5
      31 [-]: LOADN R8 6   ; var8 = 6
      32 [-]: SETLIST R6 R7 2 [1]; var6[1] = var7; var6[2] = var8; var6[3] = var9; 
      33 [-]: NEWTABLE R7 0 2; var7 = {}
      34 [-]: LOADN R8 110 ; var8 = 110
      35 [-]: LOADN R9 110 ; var9 = 110
      36 [-]: SETLIST R7 R8 2 [1]; var7[1] = var8; var7[2] = var9; var7[3] = var10; 
      37 [-]: LOADK R8 K15 ; var8 = 0.64999997615814209
      38 [-]: CALL R2 7 1  ; var2(var3, var4, var5, var6, var7, var8)
      39 [-]: GETIMPORT R2 13; var2 = 0xAE91E43B
      40 [-]: GETUPVAL R6 4; var6 = upvalues[4]
      41 [-]: GETTABLE R5 R6 R1; var5 = var6[var1]
      42 [-]: GETTABLEKS R4 R5 K16; var4 = var5["mClipName"]
      43 [-]: LOADN R5 9   ; var5 = 9
      44 [-]: GETIMPORT R7 18; var7 = 0x0032441C
      45 [-]: GETTABLEKS R6 R7 K19; var6 = var7["UIColor_Yellow"]
      46 [-]: NAMECALL R2 R2 K20; var3 = var2; var2 = var2[0x67BC869F]
      47 [-]: CALL R2 5 1  ; var2(var3, var4, var5, var6)
      48 [-]: RETURN R0 0  ; 


; Name:            
; Defined at line: 967
; #Upvalues:       4
; #Parameters:     1
; Is_vararg:       0
; Max Stack Size:  10

       0 [-]: GETUPVAL R1 1; var1 = upvalues[1]
       1 [-]: LOADK R3 K0  ; var3 = 0.10000000149011612
       2 [-]: NEWCLOSURE R4 P0; 
       3 [-]: CAPTURE UPVAL U2; 
       4 [-]: CAPTURE UPVAL U0; 
       5 [-]: NAMECALL R1 R1 K1; var2 = var1; var1 = var1[0xBD2E96EA]
       6 [-]: CALL R1 4 2  ; var1 = var1(var2, var3, var4)
       7 [-]: SETUPVAL R1 0; upvalues[1] = var0
       8 [-]: FASTCALL2K 45 R0 K2 L0; 
       9 [-]: MOVE R3 R0   ; var3 = var0
      10 [-]: LOADK R4 K2  ; var4 = -1
      11 [-]: GETIMPORT R2 5; var2 = 0x7F5022CF[0x1A94C9CC]
      12 [-]: CALL R2 3 2  ; var2 = var2(var3, var4)
L 0:  13 [-]: FASTCALL1 62 R2 L1; 
      14 [-]: GETIMPORT R1 7; var1 = 0x03F57322
      15 [-]: CALL R1 2 2  ; var1 = var1(var2)
L 1:  16 [-]: GETIMPORT R2 9; var2 = 0x25312C9B
      17 [-]: GETIMPORT R3 11; var3 = 0xAE91E43B
      18 [-]: LOADK R5 K12 ; var5 = "Card"
      19 [-]: MOVE R6 R1   ; var6 = var1
      20 [-]: CONCAT R4 R5 R6; var4 = var5 .. var6
      21 [-]: LOADN R5 2   ; var5 = 2
      22 [-]: NEWTABLE R6 0 2; var6 = {}
      23 [-]: LOADN R7 5   ; var7 = 5
      24 [-]: LOADN R8 6   ; var8 = 6
      25 [-]: SETLIST R6 R7 2 [1]; var6[1] = var7; var6[2] = var8; var6[3] = var9; 
      26 [-]: NEWTABLE R7 0 2; var7 = {}
      27 [-]: LOADN R8 100 ; var8 = 100
      28 [-]: LOADN R9 100 ; var9 = 100
      29 [-]: SETLIST R7 R8 2 [1]; var7[1] = var8; var7[2] = var9; var7[3] = var10; 
      30 [-]: LOADK R8 K13 ; var8 = 0.64999997615814209
      31 [-]: CALL R2 7 1  ; var2(var3, var4, var5, var6, var7, var8)
      32 [-]: GETIMPORT R2 11; var2 = 0xAE91E43B
      33 [-]: GETUPVAL R6 3; var6 = upvalues[3]
      34 [-]: GETTABLE R5 R6 R1; var5 = var6[var1]
      35 [-]: GETTABLEKS R4 R5 K14; var4 = var5["mClipName"]
      36 [-]: LOADN R5 9   ; var5 = 9
      37 [-]: GETIMPORT R7 16; var7 = 0x0032441C
      38 [-]: GETTABLEKS R6 R7 K17; var6 = var7["UIColor_White"]
      39 [-]: NAMECALL R2 R2 K18; var3 = var2; var2 = var2[0x67BC869F]
      40 [-]: CALL R2 5 1  ; var2(var3, var4, var5, var6)
      41 [-]: RETURN R0 0  ; 


; Name:            
; Defined at line: 975
; #Upvalues:       5
; #Parameters:     1
; Is_vararg:       0
; Max Stack Size:  10

       0 [-]: GETUPVAL R1 0; var1 = upvalues[0]
       1 [-]: JUMPIF R1 L1 ; goto L1 if var1
       2 [-]: GETUPVAL R1 1; var1 = upvalues[1]
       3 [-]: JUMPIF R1 L1 ; goto L1 if var1
       4 [-]: LOADK R2 K0  ; var2 = "Card"
       5 [-]: MOVE R3 R0   ; var3 = var0
       6 [-]: CONCAT R1 R2 R3; var1 = var2 .. var3
       7 [-]: GETUPVAL R3 2; var3 = upvalues[2]
       8 [-]: GETTABLEKS R2 R3 K1; var2 = var3[0x659D451F]
       9 [-]: GETIMPORT R3 3; var3 = 0xAEFB82CD
      10 [-]: CALL R2 2 1  ; var2(var3)
      11 [-]: GETUPVAL R2 3; var2 = upvalues[3]
      12 [-]: JUMPIFNOT R2 L0; goto L0 if not var2
      13 [-]: GETUPVAL R2 4; var2 = upvalues[4]
      14 [-]: MOVE R3 R1   ; var3 = var1
      15 [-]: CALL R2 2 1  ; var2(var3)
      16 [-]: RETURN R0 0  ; 
L 0:  17 [-]: GETIMPORT R2 5; var2 = 0x25312C9B
      18 [-]: GETIMPORT R3 7; var3 = 0xAE91E43B
      19 [-]: MOVE R4 R1   ; var4 = var1
      20 [-]: LOADN R5 2   ; var5 = 2
      21 [-]: NEWTABLE R6 0 2; var6 = {}
      22 [-]: LOADN R7 5   ; var7 = 5
      23 [-]: LOADN R8 6   ; var8 = 6
      24 [-]: SETLIST R6 R7 2 [1]; var6[1] = var7; var6[2] = var8; var6[3] = var9; 
      25 [-]: NEWTABLE R7 0 2; var7 = {}
      26 [-]: LOADN R8 120 ; var8 = 120
      27 [-]: LOADN R9 120 ; var9 = 120
      28 [-]: SETLIST R7 R8 2 [1]; var7[1] = var8; var7[2] = var9; var7[3] = var10; 
      29 [-]: LOADK R8 K8  ; var8 = 0.64999997615814209
      30 [-]: CALL R2 7 1  ; var2(var3, var4, var5, var6, var7, var8)
L 1:  31 [-]: RETURN R0 0  ; 


; Name:            
; Defined at line: 987
; #Upvalues:       4
; #Parameters:     1
; Is_vararg:       0
; Max Stack Size:  10

       0 [-]: GETUPVAL R1 0; var1 = upvalues[0]
       1 [-]: JUMPIF R1 L1 ; goto L1 if var1
       2 [-]: LOADK R2 K0  ; var2 = "Card"
       3 [-]: MOVE R3 R0   ; var3 = var0
       4 [-]: CONCAT R1 R2 R3; var1 = var2 .. var3
       5 [-]: GETUPVAL R2 1; var2 = upvalues[1]
       6 [-]: JUMPIFNOT R2 L0; goto L0 if not var2
       7 [-]: GETUPVAL R2 2; var2 = upvalues[2]
       8 [-]: MOVE R3 R1   ; var3 = var1
       9 [-]: CALL R2 2 1  ; var2(var3)
      10 [-]: RETURN R0 0  ; 
L 0:  11 [-]: GETUPVAL R2 3; var2 = upvalues[3]
      12 [-]: JUMPIF R2 L1 ; goto L1 if var2
      13 [-]: GETIMPORT R2 2; var2 = 0x25312C9B
      14 [-]: GETIMPORT R3 4; var3 = 0xAE91E43B
      15 [-]: MOVE R4 R1   ; var4 = var1
      16 [-]: LOADN R5 2   ; var5 = 2
      17 [-]: NEWTABLE R6 0 2; var6 = {}
      18 [-]: LOADN R7 5   ; var7 = 5
      19 [-]: LOADN R8 6   ; var8 = 6
      20 [-]: SETLIST R6 R7 2 [1]; var6[1] = var7; var6[2] = var8; var6[3] = var9; 
      21 [-]: NEWTABLE R7 0 2; var7 = {}
      22 [-]: LOADN R8 100 ; var8 = 100
      23 [-]: LOADN R9 100 ; var9 = 100
      24 [-]: SETLIST R7 R8 2 [1]; var7[1] = var8; var7[2] = var9; var7[3] = var10; 
      25 [-]: LOADK R8 K5  ; var8 = 0.64999997615814209
      26 [-]: CALL R2 7 1  ; var2(var3, var4, var5, var6, var7, var8)
L 1:  27 [-]: RETURN R0 0  ; 


; Name:            
; Defined at line: 998
; #Upvalues:       6
; #Parameters:     1
; Is_vararg:       0
; Max Stack Size:  19

       0 [-]: FASTCALL2K 45 R0 K0 L0; 
       1 [-]: MOVE R3 R0   ; var3 = var0
       2 [-]: LOADK R4 K0  ; var4 = -1
       3 [-]: GETIMPORT R2 3; var2 = 0x7F5022CF[0x1A94C9CC]
       4 [-]: CALL R2 3 2  ; var2 = var2(var3, var4)
L 0:   5 [-]: FASTCALL1 62 R2 L1; 
       6 [-]: GETIMPORT R1 5; var1 = 0x03F57322
       7 [-]: CALL R1 2 2  ; var1 = var1(var2)
L 1:   8 [-]: GETUPVAL R3 0; var3 = upvalues[0]
       9 [-]: GETTABLEKS R2 R3 K6; var2 = var3[0x659D451F]
      10 [-]: GETIMPORT R3 8; var3 = 0x6D5CA19A
      11 [-]: CALL R2 2 1  ; var2(var3)
      12 [-]: LOADK R2 K9  ; var2 = 0.20000000298023224
      13 [-]: LOADN R5 1   ; var5 = 1
      14 [-]: LOADN R3 3   ; var3 = 3
      15 [-]: LOADN R4 1   ; var4 = 1
      16 [-]: FORNPREP R3 L5; nforprep start - [escape at L5] -- var3 = iterator
L 2:  17 [-]: LOADK R7 K10 ; var7 = "Card"
      18 [-]: MOVE R8 R5   ; var8 = var5
      19 [-]: CONCAT R6 R7 R8; var6 = var7 .. var8
      20 [-]: LOADK R8 K11 ; var8 = "Emotion"
      21 [-]: MOVE R9 R5   ; var9 = var5
      22 [-]: CONCAT R7 R8 R9; var7 = var8 .. var9
      23 [-]: GETIMPORT R8 13; var8 = 0xAE91E43B
      24 [-]: MOVE R10 R7  ; var10 = var7
      25 [-]: LOADN R11 9  ; var11 = 9
      26 [-]: GETIMPORT R13 15; var13 = 0x0032441C
      27 [-]: GETTABLEKS R12 R13 K16; var12 = var13["UIColor_White"]
      28 [-]: NAMECALL R8 R8 K17; var9 = var8; var8 = var8[0x67BC869F]
      29 [-]: CALL R8 5 1  ; var8(var9, var10, var11, var12)
      30 [-]: JUMPIFNOTEQ R5 R1 L3; goto L3 if var5 ~= var1247265
      31 [-]: GETIMPORT R8 19; var8 = 0x25312C9B
      32 [-]: GETIMPORT R9 13; var9 = 0xAE91E43B
      33 [-]: MOVE R10 R7  ; var10 = var7
      34 [-]: LOADN R11 2  ; var11 = 2
      35 [-]: NEWTABLE R12 0 2; var12 = {}
      36 [-]: LOADN R13 0  ; var13 = 0
      37 [-]: LOADN R14 1  ; var14 = 1
      38 [-]: SETLIST R12 R13 2 [1]; var12[1] = var13; var12[2] = var14; var12[3] = var15; 
      39 [-]: NEWTABLE R13 0 2; var13 = {}
      40 [-]: GETIMPORT R15 13; var15 = 0xAE91E43B
      41 [-]: NAMECALL R15 R15 K21; var16 = var15; var15 = var15[0x091C120E]
      42 [-]: CALL R15 2 2 ; var15 = var15(var16)
      43 [-]: MULK R14 R15 K20; var14 = var15 * 0.5
      44 [-]: GETIMPORT R17 13; var17 = 0xAE91E43B
      45 [-]: NAMECALL R17 R17 K23; var18 = var17; var17 = var17[0x2CC9D281]
      46 [-]: CALL R17 2 2 ; var17 = var17(var18)
      47 [-]: MULK R16 R17 K20; var16 = var17 * 0.5
      48 [-]: ADDK R15 R16 K22; var15 = var16 + 350
      49 [-]: SETLIST R13 R14 2 [1]; var13[1] = var14; var13[2] = var15; var13[3] = var16; 
      50 [-]: LOADK R14 K24; var14 = 0.44999998807907104
      51 [-]: LOADK R15 K25; var15 = 0.30000001192092896
      52 [-]: CALL R8 8 1  ; var8(var9, var10, var11, var12, var13, var14, var15)
      53 [-]: GETUPVAL R8 1; var8 = upvalues[1]
      54 [-]: LOADK R10 K25; var10 = 0.30000001192092896
      55 [-]: DUPCLOSURE R11 K26; 
      56 [-]: CAPTURE UPVAL U0; 
      57 [-]: NAMECALL R8 R8 K27; var9 = var8; var8 = var8[0xBD2E96EA]
      58 [-]: CALL R8 4 1  ; var8(var9, var10, var11)
      59 [-]: GETIMPORT R8 19; var8 = 0x25312C9B
      60 [-]: GETIMPORT R9 13; var9 = 0xAE91E43B
      61 [-]: MOVE R10 R6  ; var10 = var6
      62 [-]: LOADN R11 2  ; var11 = 2
      63 [-]: NEWTABLE R12 0 4; var12 = {}
      64 [-]: LOADN R13 0  ; var13 = 0
      65 [-]: LOADN R14 1  ; var14 = 1
      66 [-]: LOADN R15 5  ; var15 = 5
      67 [-]: LOADN R16 6  ; var16 = 6
      68 [-]: SETLIST R12 R13 4 [1]; var12[1] = var13; var12[2] = var14; var12[3] = var15; var12[4] = var16; var12[5] = var17; 
      69 [-]: NEWTABLE R13 0 4; var13 = {}
      70 [-]: GETIMPORT R15 13; var15 = 0xAE91E43B
      71 [-]: NAMECALL R15 R15 K21; var16 = var15; var15 = var15[0x091C120E]
      72 [-]: CALL R15 2 2 ; var15 = var15(var16)
      73 [-]: MULK R14 R15 K20; var14 = var15 * 0.5
      74 [-]: GETIMPORT R17 13; var17 = 0xAE91E43B
      75 [-]: NAMECALL R17 R17 K23; var18 = var17; var17 = var17[0x2CC9D281]
      76 [-]: CALL R17 2 2 ; var17 = var17(var18)
      77 [-]: MULK R16 R17 K20; var16 = var17 * 0.5
      78 [-]: SUBK R15 R16 K28; var15 = var16 - 50
      79 [-]: LOADN R16 130; var16 = 130
      80 [-]: LOADN R17 130; var17 = 130
      81 [-]: SETLIST R13 R14 4 [1]; var13[1] = var14; var13[2] = var15; var13[3] = var16; var13[4] = var17; var13[5] = var18; 
      82 [-]: LOADK R14 K24; var14 = 0.44999998807907104
      83 [-]: LOADK R15 K25; var15 = 0.30000001192092896
      84 [-]: NEWCLOSURE R16 P1; 
      85 [-]: CAPTURE VAL R6; 
      86 [-]: CAPTURE UPVAL U0; 
      87 [-]: CAPTURE UPVAL U2; 
      88 [-]: CAPTURE UPVAL U3; 
      89 [-]: CAPTURE VAL R1; 
      90 [-]: CAPTURE UPVAL U4; 
      91 [-]: CALL R8 9 1  ; var8(var9, var10, var11, var12, var13, var14, var15, var16)
      92 [-]: JUMP L4      ; goto L4
L 3:  93 [-]: GETUPVAL R8 5; var8 = upvalues[5]
      94 [-]: GETUPVAL R10 3; var10 = upvalues[3]
      95 [-]: GETTABLE R9 R10 R5; var9 = var10[var5]
      96 [-]: CALL R8 2 1  ; var8(var9)
      97 [-]: GETIMPORT R8 19; var8 = 0x25312C9B
      98 [-]: GETIMPORT R9 13; var9 = 0xAE91E43B
      99 [-]: MOVE R10 R6  ; var10 = var6
     100 [-]: LOADN R11 2  ; var11 = 2
     101 [-]: NEWTABLE R12 0 2; var12 = {}
     102 [-]: LOADN R13 0  ; var13 = 0
     103 [-]: LOADN R14 14 ; var14 = 14
     104 [-]: SETLIST R12 R13 2 [1]; var12[1] = var13; var12[2] = var14; var12[3] = var15; 
     105 [-]: NEWTABLE R13 0 2; var13 = {}
     106 [-]: GETIMPORT R15 13; var15 = 0xAE91E43B
     107 [-]: NAMECALL R15 R15 K21; var16 = var15; var15 = var15[0x091C120E]
     108 [-]: CALL R15 2 2 ; var15 = var15(var16)
     109 [-]: ADDK R14 R15 K29; var14 = var15 + 500
     110 [-]: LOADN R15 35 ; var15 = 35
     111 [-]: SETLIST R13 R14 2 [1]; var13[1] = var14; var13[2] = var15; var13[3] = var16; 
     112 [-]: LOADK R14 K30; var14 = 0.64999997615814209
     113 [-]: MOVE R15 R2  ; var15 = var2
     114 [-]: CALL R8 8 1  ; var8(var9, var10, var11, var12, var13, var14, var15)
     115 [-]: ADDK R2 R2 K9; var2 = var2 + 0.20000000298023224
L 4: 116 [-]: FORNLOOP R3 L2; nforloop end - iterate + goto L2
L 5: 117 [-]: RETURN R0 0  ; 


; Name:            
; Defined at line: 1030
; #Upvalues:       3
; #Parameters:     1
; Is_vararg:       0
; Max Stack Size:  4

       0 [-]: GETUPVAL R1 0; var1 = upvalues[0]
       1 [-]: JUMPIF R1 L0 ; goto L0 if var1
       2 [-]: GETUPVAL R1 1; var1 = upvalues[1]
       3 [-]: JUMPIFNOT R1 L0; goto L0 if not var1
       4 [-]: LOADK R2 K0  ; var2 = "Card"
       5 [-]: MOVE R3 R0   ; var3 = var0
       6 [-]: CONCAT R1 R2 R3; var1 = var2 .. var3
       7 [-]: LOADB R2 1   ; var2 = true
       8 [-]: SETUPVAL R2 0; upvalues[2] = var0
       9 [-]: GETUPVAL R2 2; var2 = upvalues[2]
      10 [-]: MOVE R3 R1   ; var3 = var1
      11 [-]: CALL R2 2 1  ; var2(var3)
L 0:  12 [-]: RETURN R0 0  ; 


; Name:            
; Defined at line: 1038
; #Upvalues:       5
; #Parameters:     1
; Is_vararg:       0
; Max Stack Size:  11

       0 [-]: GETUPVAL R1 0; var1 = upvalues[0]
       1 [-]: JUMPIF R1 L4 ; goto L4 if var1
       2 [-]: GETUPVAL R1 1; var1 = upvalues[1]
       3 [-]: JUMPIFNOT R1 L0; goto L0 if not var1
       4 [-]: GETUPVAL R1 2; var1 = upvalues[2]
       5 [-]: MOVE R2 R0   ; var2 = var0
       6 [-]: CALL R1 2 1  ; var1(var2)
       7 [-]: RETURN R0 0  ; 
L 0:   8 [-]: GETUPVAL R2 3; var2 = upvalues[3]
       9 [-]: GETTABLEKS R1 R2 K0; var1 = var2[0x659D451F]
      10 [-]: GETIMPORT R2 2; var2 = 0x1E123824
      11 [-]: CALL R1 2 1  ; var1(var2)
      12 [-]: LOADN R3 1   ; var3 = 1
      13 [-]: GETUPVAL R4 4; var4 = upvalues[4]
      14 [-]: LENGTH R1 R4 ; var1 = #var4
      15 [-]: LOADN R2 1   ; var2 = 1
      16 [-]: FORNPREP R1 L4; nforprep start - [escape at L4] -- var1 = iterator
L 1:  17 [-]: GETUPVAL R6 4; var6 = upvalues[4]
      18 [-]: GETTABLE R5 R6 R3; var5 = var6[var3]
      19 [-]: GETTABLEKS R4 R5 K3; var4 = var5["mActive"]
      20 [-]: JUMPIFNOT R4 L3; goto L3 if not var4
      21 [-]: GETUPVAL R6 4; var6 = upvalues[4]
      22 [-]: GETTABLE R5 R6 R3; var5 = var6[var3]
      23 [-]: GETTABLEKS R4 R5 K4; var4 = var5["mClipName"]
      24 [-]: JUMPIFNOTEQ R4 R0 L2; goto L2 if var4 ~= var394273
      25 [-]: GETIMPORT R4 6; var4 = 0xAE91E43B
      26 [-]: GETUPVAL R8 4; var8 = upvalues[4]
      27 [-]: GETTABLE R7 R8 R3; var7 = var8[var3]
      28 [-]: GETTABLEKS R6 R7 K4; var6 = var7["mClipName"]
      29 [-]: LOADN R7 9   ; var7 = 9
      30 [-]: GETIMPORT R9 8; var9 = 0x0032441C
      31 [-]: GETTABLEKS R8 R9 K9; var8 = var9["UIColor_Yellow"]
      32 [-]: NAMECALL R4 R4 K10; var5 = var4; var4 = var4[0x67BC869F]
      33 [-]: CALL R4 5 1  ; var4(var5, var6, var7, var8)
      34 [-]: JUMP L3      ; goto L3
L 2:  35 [-]: GETIMPORT R4 12; var4 = 0x25312C9B
      36 [-]: GETIMPORT R5 6; var5 = 0xAE91E43B
      37 [-]: GETUPVAL R8 4; var8 = upvalues[4]
      38 [-]: GETTABLE R7 R8 R3; var7 = var8[var3]
      39 [-]: GETTABLEKS R6 R7 K4; var6 = var7["mClipName"]
      40 [-]: LOADN R7 2   ; var7 = 2
      41 [-]: NEWTABLE R8 0 1; var8 = {}
      42 [-]: LOADN R9 10  ; var9 = 10
      43 [-]: SETLIST R8 R9 1 [1]; var8[1] = var9; var8[2] = var10; 
      44 [-]: NEWTABLE R9 0 1; var9 = {}
      45 [-]: LOADN R10 10 ; var10 = 10
      46 [-]: SETLIST R9 R10 1 [1]; var9[1] = var10; var9[2] = var11; 
      47 [-]: LOADK R10 K13; var10 = 0.5
      48 [-]: CALL R4 7 1  ; var4(var5, var6, var7, var8, var9, var10)
L 3:  49 [-]: FORNLOOP R1 L1; nforloop end - iterate + goto L1
L 4:  50 [-]: RETURN R0 0  ; 


; Name:            
; Defined at line: 1058
; #Upvalues:       1
; #Parameters:     1
; Is_vararg:       0
; Max Stack Size:  4

       0 [-]: LOADK R2 K0  ; var2 = "Emotion"
       1 [-]: MOVE R3 R0   ; var3 = var0
       2 [-]: CONCAT R1 R2 R3; var1 = var2 .. var3
       3 [-]: GETUPVAL R2 0; var2 = upvalues[0]
       4 [-]: MOVE R3 R1   ; var3 = var1
       5 [-]: CALL R2 2 1  ; var2(var3)
       6 [-]: RETURN R0 0  ; 


; Name:            
; Defined at line: 1063
; #Upvalues:       5
; #Parameters:     1
; Is_vararg:       0
; Max Stack Size:  11

       0 [-]: GETUPVAL R1 0; var1 = upvalues[0]
       1 [-]: JUMPIF R1 L3 ; goto L3 if var1
       2 [-]: GETUPVAL R1 1; var1 = upvalues[1]
       3 [-]: JUMPIFNOT R1 L0; goto L0 if not var1
       4 [-]: GETUPVAL R1 2; var1 = upvalues[2]
       5 [-]: MOVE R2 R0   ; var2 = var0
       6 [-]: CALL R1 2 1  ; var1(var2)
       7 [-]: RETURN R0 0  ; 
L 0:   8 [-]: GETUPVAL R1 3; var1 = upvalues[3]
       9 [-]: JUMPIFNOT R1 L3; goto L3 if not var1
      10 [-]: LOADN R3 1   ; var3 = 1
      11 [-]: GETUPVAL R4 4; var4 = upvalues[4]
      12 [-]: LENGTH R1 R4 ; var1 = #var4
      13 [-]: LOADN R2 1   ; var2 = 1
      14 [-]: FORNPREP R1 L3; nforprep start - [escape at L3] -- var1 = iterator
L 1:  15 [-]: GETIMPORT R4 1; var4 = 0xAE91E43B
      16 [-]: GETUPVAL R8 4; var8 = upvalues[4]
      17 [-]: GETTABLE R7 R8 R3; var7 = var8[var3]
      18 [-]: GETTABLEKS R6 R7 K2; var6 = var7["mClipName"]
      19 [-]: LOADN R7 9   ; var7 = 9
      20 [-]: GETIMPORT R9 4; var9 = 0x0032441C
      21 [-]: GETTABLEKS R8 R9 K5; var8 = var9["UIColor_White"]
      22 [-]: NAMECALL R4 R4 K6; var5 = var4; var4 = var4[0x67BC869F]
      23 [-]: CALL R4 5 1  ; var4(var5, var6, var7, var8)
      24 [-]: GETUPVAL R6 4; var6 = upvalues[4]
      25 [-]: GETTABLE R5 R6 R3; var5 = var6[var3]
      26 [-]: GETTABLEKS R4 R5 K7; var4 = var5["mActive"]
      27 [-]: JUMPIFNOT R4 L2; goto L2 if not var4
      28 [-]: GETIMPORT R4 9; var4 = 0x25312C9B
      29 [-]: GETIMPORT R5 1; var5 = 0xAE91E43B
      30 [-]: GETUPVAL R8 4; var8 = upvalues[4]
      31 [-]: GETTABLE R7 R8 R3; var7 = var8[var3]
      32 [-]: GETTABLEKS R6 R7 K2; var6 = var7["mClipName"]
      33 [-]: LOADN R7 2   ; var7 = 2
      34 [-]: NEWTABLE R8 0 1; var8 = {}
      35 [-]: LOADN R9 10  ; var9 = 10
      36 [-]: SETLIST R8 R9 1 [1]; var8[1] = var9; var8[2] = var10; 
      37 [-]: NEWTABLE R9 0 1; var9 = {}
      38 [-]: LOADN R10 100; var10 = 100
      39 [-]: SETLIST R9 R10 1 [1]; var9[1] = var10; var9[2] = var11; 
      40 [-]: LOADK R10 K10; var10 = 0.5
      41 [-]: CALL R4 7 1  ; var4(var5, var6, var7, var8, var9, var10)
L 2:  42 [-]: FORNLOOP R1 L1; nforloop end - iterate + goto L1
L 3:  43 [-]: RETURN R0 0  ; 


; Name:            
; Defined at line: 1078
; #Upvalues:       1
; #Parameters:     1
; Is_vararg:       0
; Max Stack Size:  4

       0 [-]: LOADK R2 K0  ; var2 = "Emotion"
       1 [-]: MOVE R3 R0   ; var3 = var0
       2 [-]: CONCAT R1 R2 R3; var1 = var2 .. var3
       3 [-]: GETUPVAL R2 0; var2 = upvalues[0]
       4 [-]: MOVE R3 R1   ; var3 = var1
       5 [-]: CALL R2 2 1  ; var2(var3)
       6 [-]: RETURN R0 0  ; 


; Name:            
; Defined at line: 1083
; #Upvalues:       16
; #Parameters:     1
; Is_vararg:       0
; Max Stack Size:  10

       0 [-]: GETUPVAL R1 0; var1 = upvalues[0]
       1 [-]: JUMPIF R1 L8 ; goto L8 if var1
       2 [-]: GETUPVAL R1 1; var1 = upvalues[1]
       3 [-]: JUMPIFNOT R1 L0; goto L0 if not var1
       4 [-]: LOADB R1 1   ; var1 = true
       5 [-]: SETUPVAL R1 0; upvalues[1] = var0
       6 [-]: GETUPVAL R1 2; var1 = upvalues[2]
       7 [-]: MOVE R2 R0   ; var2 = var0
       8 [-]: CALL R1 2 1  ; var1(var2)
       9 [-]: RETURN R0 0  ; 
L 0:  10 [-]: LOADN R3 1   ; var3 = 1
      11 [-]: GETUPVAL R4 3; var4 = upvalues[3]
      12 [-]: LENGTH R1 R4 ; var1 = #var4
      13 [-]: LOADN R2 1   ; var2 = 1
      14 [-]: FORNPREP R1 L8; nforprep start - [escape at L8] -- var1 = iterator
L 1:  15 [-]: GETUPVAL R6 3; var6 = upvalues[3]
      16 [-]: GETTABLE R5 R6 R3; var5 = var6[var3]
      17 [-]: GETTABLEKS R4 R5 K0; var4 = var5["mClipName"]
      18 [-]: JUMPIFNOTEQ R4 R0 L7; goto L7 if var4 ~= var263484
      19 [-]: GETUPVAL R5 4; var5 = upvalues[4]
      20 [-]: GETTABLEKS R4 R5 K1; var4 = var5[0xF76783E5]
      21 [-]: GETIMPORT R5 3; var5 = 0xAE91E43B
      22 [-]: GETUPVAL R8 3; var8 = upvalues[3]
      23 [-]: GETTABLE R7 R8 R3; var7 = var8[var3]
      24 [-]: GETTABLEKS R6 R7 K0; var6 = var7["mClipName"]
      25 [-]: GETIMPORT R7 5; var7 = 0xD3B5DFA0
      26 [-]: LOADN R8 0   ; var8 = 0
      27 [-]: LOADN R9 0   ; var9 = 0
      28 [-]: CALL R4 6 1  ; var4(var5, var6, var7, var8, var9)
      29 [-]: GETUPVAL R6 3; var6 = upvalues[3]
      30 [-]: GETTABLE R5 R6 R3; var5 = var6[var3]
      31 [-]: GETTABLEKS R4 R5 K6; var4 = var5["Label"]
      32 [-]: GETUPVAL R6 5; var6 = upvalues[5]
      33 [-]: GETTABLEKS R5 R6 K6; var5 = var6["Label"]
      34 [-]: JUMPIFNOTEQ R4 R5 L3; goto L3 if var4 ~= var66566
      35 [-]: LOADB R4 1   ; var4 = true
      36 [-]: SETUPVAL R4 0; upvalues[4] = var0
      37 [-]: GETUPVAL R5 4; var5 = upvalues[4]
      38 [-]: GETTABLEKS R4 R5 K7; var4 = var5[0x659D451F]
      39 [-]: GETIMPORT R5 9; var5 = 0x6D5CA19A
      40 [-]: CALL R4 2 1  ; var4(var5)
      41 [-]: GETUPVAL R6 6; var6 = upvalues[6]
      42 [-]: GETUPVAL R7 7; var7 = upvalues[7]
      43 [-]: GETTABLE R5 R6 R7; var5 = var6[var7]
      44 [-]: GETTABLEKS R4 R5 K10; var4 = var5["CompleteTransmission"]
      45 [-]: JUMPXEQKNIL R4 L2; 
      46 [-]: GETUPVAL R5 8; var5 = upvalues[8]
      47 [-]: GETTABLEKS R4 R5 K11; var4 = var5[0xFE0D9469]
      48 [-]: GETIMPORT R5 14; var5 = _T["curTransmission"]
      49 [-]: CALL R4 2 1  ; var4(var5)
      50 [-]: GETUPVAL R5 8; var5 = upvalues[8]
      51 [-]: GETTABLEKS R4 R5 K15; var4 = var5[0x1F60D532]
      52 [-]: GETUPVAL R7 6; var7 = upvalues[6]
      53 [-]: GETUPVAL R8 7; var8 = upvalues[7]
      54 [-]: GETTABLE R6 R7 R8; var6 = var7[var8]
      55 [-]: GETTABLEKS R5 R6 K10; var5 = var6["CompleteTransmission"]
      56 [-]: CALL R4 2 1  ; var4(var5)
L 2:  57 [-]: GETUPVAL R4 9; var4 = upvalues[9]
      58 [-]: GETUPVAL R6 3; var6 = upvalues[3]
      59 [-]: GETTABLE R5 R6 R3; var5 = var6[var3]
      60 [-]: NEWCLOSURE R6 P0; 
      61 [-]: CAPTURE UPVAL U3; 
      62 [-]: CAPTURE VAL R3; 
      63 [-]: CAPTURE UPVAL U10; 
      64 [-]: CAPTURE UPVAL U11; 
      65 [-]: CAPTURE UPVAL U6; 
      66 [-]: CAPTURE UPVAL U7; 
      67 [-]: CAPTURE UPVAL U12; 
      68 [-]: CAPTURE UPVAL U4; 
      69 [-]: CAPTURE UPVAL U13; 
      70 [-]: CALL R4 3 1  ; var4(var5, var6)
      71 [-]: JUMP L6      ; goto L6
L 3:  72 [-]: GETUPVAL R5 4; var5 = upvalues[4]
      73 [-]: GETTABLEKS R4 R5 K7; var4 = var5[0x659D451F]
      74 [-]: GETIMPORT R5 17; var5 = 0x393F4E17
      75 [-]: CALL R4 2 1  ; var4(var5)
      76 [-]: GETUPVAL R5 8; var5 = upvalues[8]
      77 [-]: GETTABLEKS R4 R5 K11; var4 = var5[0xFE0D9469]
      78 [-]: GETIMPORT R5 14; var5 = _T["curTransmission"]
      79 [-]: CALL R4 2 1  ; var4(var5)
      80 [-]: GETUPVAL R6 3; var6 = upvalues[3]
      81 [-]: GETTABLE R5 R6 R3; var5 = var6[var3]
      82 [-]: GETTABLEKS R4 R5 K18; var4 = var5["BadTransmission"]
      83 [-]: JUMPXEQKNIL R4 L4; 
      84 [-]: GETUPVAL R5 8; var5 = upvalues[8]
      85 [-]: GETTABLEKS R4 R5 K15; var4 = var5[0x1F60D532]
      86 [-]: GETUPVAL R7 3; var7 = upvalues[3]
      87 [-]: GETTABLE R6 R7 R3; var6 = var7[var3]
      88 [-]: GETTABLEKS R5 R6 K18; var5 = var6["BadTransmission"]
      89 [-]: CALL R4 2 1  ; var4(var5)
      90 [-]: JUMP L5      ; goto L5
L 4:  91 [-]: GETUPVAL R5 8; var5 = upvalues[8]
      92 [-]: GETTABLEKS R4 R5 K15; var4 = var5[0x1F60D532]
      93 [-]: GETIMPORT R5 20; var5 = 0xE3AD466C
      94 [-]: CALL R4 2 1  ; var4(var5)
L 5:  95 [-]: GETUPVAL R5 14; var5 = upvalues[14]
      96 [-]: ADDK R4 R5 K21; var4 = var5 + 1
      97 [-]: SETUPVAL R4 14; upvalues[4] = var14
      98 [-]: GETUPVAL R4 12; var4 = upvalues[12]
      99 [-]: GETUPVAL R6 3; var6 = upvalues[3]
     100 [-]: GETTABLE R5 R6 R3; var5 = var6[var3]
     101 [-]: CALL R4 2 1  ; var4(var5)
     102 [-]: GETUPVAL R4 15; var4 = upvalues[15]
     103 [-]: LOADN R5 1   ; var5 = 1
     104 [-]: CALL R4 2 1  ; var4(var5)
L 6: 105 [-]: GETIMPORT R4 3; var4 = 0xAE91E43B
     106 [-]: GETUPVAL R8 3; var8 = upvalues[3]
     107 [-]: GETTABLE R7 R8 R3; var7 = var8[var3]
     108 [-]: GETTABLEKS R6 R7 K0; var6 = var7["mClipName"]
     109 [-]: LOADN R7 9   ; var7 = 9
     110 [-]: GETIMPORT R9 23; var9 = 0x0032441C
     111 [-]: GETTABLEKS R8 R9 K24; var8 = var9["UIColor_White"]
     112 [-]: NAMECALL R4 R4 K25; var5 = var4; var4 = var4[0x67BC869F]
     113 [-]: CALL R4 5 1  ; var4(var5, var6, var7, var8)
L 7: 114 [-]: FORNLOOP R1 L1; nforloop end - iterate + goto L1
L 8: 115 [-]: RETURN R0 0  ; 


; Name:            
; Defined at line: 1133
; #Upvalues:       1
; #Parameters:     1
; Is_vararg:       0
; Max Stack Size:  4

       0 [-]: LOADK R2 K0  ; var2 = "Emotion"
       1 [-]: MOVE R3 R0   ; var3 = var0
       2 [-]: CONCAT R1 R2 R3; var1 = var2 .. var3
       3 [-]: GETUPVAL R2 0; var2 = upvalues[0]
       4 [-]: MOVE R3 R1   ; var3 = var1
       5 [-]: CALL R2 2 1  ; var2(var3)
       6 [-]: RETURN R0 0  ; 


; Name:            
; Defined at line: 1138
; #Upvalues:       8
; #Parameters:     0
; Is_vararg:       0
; Max Stack Size:  9

       0 [-]: GETUPVAL R0 0; var0 = upvalues[0]
       1 [-]: JUMPIFNOT R0 L0; goto L0 if not var0
       2 [-]: RETURN R0 0  ; 
L 0:   3 [-]: GETUPVAL R1 1; var1 = upvalues[1]
       4 [-]: GETTABLEKS R0 R1 K0; var0 = var1[0x06D055F9]
       5 [-]: GETUPVAL R1 2; var1 = upvalues[2]
       6 [-]: GETUPVAL R2 3; var2 = upvalues[3]
       7 [-]: GETUPVAL R3 4; var3 = upvalues[4]
       8 [-]: CALL R0 4 2  ; var0 = var0(var1, var2, var3)
       9 [-]: GETUPVAL R1 5; var1 = upvalues[5]
      10 [-]: GETUPVAL R4 6; var4 = upvalues[6]
      11 [-]: GETUPVAL R8 7; var8 = upvalues[7]
      12 [-]: ADDK R7 R8 K1; var7 = var8 + 1
      13 [-]: GETTABLE R6 R0 R7; var6 = var0[var7]
      14 [-]: ADDK R5 R6 K1; var5 = var6 + 1
      15 [-]: GETTABLE R3 R4 R5; var3 = var4[var5]
      16 [-]: GETTABLEKS R2 R3 K2; var2 = var3["mClipName"]
      17 [-]: CALL R1 2 1  ; var1(var2)
      18 [-]: RETURN R0 0  ; 


; Name:            
; Defined at line: 1146
; #Upvalues:       10
; #Parameters:     1
; Is_vararg:       0
; Max Stack Size:  11

       0 [-]: GETUPVAL R1 0; var1 = upvalues[0]
       1 [-]: JUMPIFNOT R1 L0; goto L0 if not var1
       2 [-]: RETURN R0 0  ; 
L 0:   3 [-]: GETUPVAL R2 1; var2 = upvalues[1]
       4 [-]: GETTABLEKS R1 R2 K0; var1 = var2[0x06D055F9]
       5 [-]: GETUPVAL R2 2; var2 = upvalues[2]
       6 [-]: GETUPVAL R3 3; var3 = upvalues[3]
       7 [-]: GETUPVAL R4 4; var4 = upvalues[4]
       8 [-]: CALL R1 4 2  ; var1 = var1(var2, var3, var4)
       9 [-]: GETUPVAL R2 6; var2 = upvalues[6]
      10 [-]: SETUPVAL R2 5; upvalues[2] = var5
      11 [-]: GETUPVAL R3 1; var3 = upvalues[1]
      12 [-]: GETTABLEKS R2 R3 K0; var2 = var3[0x06D055F9]
      13 [-]: GETUPVAL R3 2; var3 = upvalues[2]
      14 [-]: LOADN R4 3   ; var4 = 3
      15 [-]: LOADN R5 4   ; var5 = 4
      16 [-]: CALL R2 4 2  ; var2 = var2(var3, var4, var5)
      17 [-]: GETUPVAL R5 6; var5 = upvalues[6]
      18 [-]: ADD R4 R5 R0 ; var4 = var5 + var0
      19 [-]: MOD R3 R4 R2 ; var3 = var4 var2
      20 [-]: SETUPVAL R3 6; upvalues[3] = var6
      21 [-]: GETUPVAL R3 6; var3 = upvalues[6]
      22 [-]: LOADN R4 0   ; var4 = 0
      23 [-]: JUMPIFNOTLT R3 R4 L1; goto L1 if var3 >= var394300
      24 [-]: GETUPVAL R4 6; var4 = upvalues[6]
      25 [-]: ADD R3 R4 R2 ; var3 = var4 + var2
      26 [-]: SETUPVAL R3 6; upvalues[3] = var6
L 1:  27 [-]: GETUPVAL R5 7; var5 = upvalues[7]
      28 [-]: GETUPVAL R9 6; var9 = upvalues[6]
      29 [-]: ADDK R8 R9 K1; var8 = var9 + 1
      30 [-]: GETTABLE R7 R1 R8; var7 = var1[var8]
      31 [-]: ADDK R6 R7 K1; var6 = var7 + 1
      32 [-]: GETTABLE R4 R5 R6; var4 = var5[var6]
      33 [-]: GETTABLEKS R3 R4 K2; var3 = var4["mActive"]
      34 [-]: JUMPIF R3 L4 ; goto L4 if var3
      35 [-]: GETUPVAL R5 6; var5 = upvalues[6]
      36 [-]: FASTCALL1 2 R0 L2; 
      37 [-]: MOVE R8 R0   ; var8 = var0
      38 [-]: GETIMPORT R7 5; var7 = 0x5BCED4C4[0xE4A5B3CA]
      39 [-]: CALL R7 2 2  ; var7 = var7(var8)
L 2:  40 [-]: DIV R6 R0 R7 ; var6 = var0 / var7
      41 [-]: ADD R4 R5 R6 ; var4 = var5 + var6
      42 [-]: MOD R3 R4 R2 ; var3 = var4 var2
      43 [-]: SETUPVAL R3 6; upvalues[3] = var6
      44 [-]: GETUPVAL R3 6; var3 = upvalues[6]
      45 [-]: LOADN R4 0   ; var4 = 0
      46 [-]: JUMPIFNOTLT R3 R4 L3; goto L3 if var3 >= var394300
      47 [-]: GETUPVAL R4 6; var4 = upvalues[6]
      48 [-]: ADD R3 R4 R2 ; var3 = var4 + var2
      49 [-]: SETUPVAL R3 6; upvalues[3] = var6
L 3:  50 [-]: JUMPBACK L1  ; goto L1
L 4:  51 [-]: GETUPVAL R3 5; var3 = upvalues[5]
      52 [-]: JUMPXEQKNIL R3 L5; 
      53 [-]: GETUPVAL R3 8; var3 = upvalues[8]
      54 [-]: GETUPVAL R6 7; var6 = upvalues[7]
      55 [-]: GETUPVAL R10 5; var10 = upvalues[5]
      56 [-]: ADDK R9 R10 K1; var9 = var10 + 1
      57 [-]: GETTABLE R8 R1 R9; var8 = var1[var9]
      58 [-]: ADDK R7 R8 K1; var7 = var8 + 1
      59 [-]: GETTABLE R5 R6 R7; var5 = var6[var7]
      60 [-]: GETTABLEKS R4 R5 K6; var4 = var5["mClipName"]
      61 [-]: CALL R3 2 1  ; var3(var4)
L 5:  62 [-]: GETUPVAL R3 9; var3 = upvalues[9]
      63 [-]: GETUPVAL R6 7; var6 = upvalues[7]
      64 [-]: GETUPVAL R10 6; var10 = upvalues[6]
      65 [-]: ADDK R9 R10 K1; var9 = var10 + 1
      66 [-]: GETTABLE R8 R1 R9; var8 = var1[var9]
      67 [-]: ADDK R7 R8 K1; var7 = var8 + 1
      68 [-]: GETTABLE R5 R6 R7; var5 = var6[var7]
      69 [-]: GETTABLEKS R4 R5 K6; var4 = var5["mClipName"]
      70 [-]: CALL R3 2 1  ; var3(var4)
      71 [-]: RETURN R0 0  ; 


; Name:            
; Defined at line: 1170
; #Upvalues:       2
; #Parameters:     0
; Is_vararg:       0
; Max Stack Size:  2

       0 [-]: GETUPVAL R0 0; var0 = upvalues[0]
       1 [-]: JUMPIFNOT R0 L0; goto L0 if not var0
       2 [-]: RETURN R0 0  ; 
L 0:   3 [-]: GETUPVAL R0 1; var0 = upvalues[1]
       4 [-]: LOADN R1 2   ; var1 = 2
       5 [-]: CALL R0 2 1  ; var0(var1)
       6 [-]: RETURN R0 0  ; 


; Name:            
; Defined at line: 1177
; #Upvalues:       1
; #Parameters:     0
; Is_vararg:       0
; Max Stack Size:  1

       0 [-]: GETUPVAL R0 0; var0 = upvalues[0]
       1 [-]: CALL R0 1 1  ; var0()
       2 [-]: RETURN R0 0  ; 


; Name:            
; Defined at line: 1181
; #Upvalues:       1
; #Parameters:     0
; Is_vararg:       0
; Max Stack Size:  1

       0 [-]: GETUPVAL R0 0; var0 = upvalues[0]
       1 [-]: CALL R0 1 1  ; var0()
       2 [-]: RETURN R0 0  ; 


; Name:            
; Defined at line: 1185
; #Upvalues:       1
; #Parameters:     0
; Is_vararg:       0
; Max Stack Size:  2

       0 [-]: GETUPVAL R0 0; var0 = upvalues[0]
       1 [-]: LOADN R1 1   ; var1 = 1
       2 [-]: CALL R0 2 1  ; var0(var1)
       3 [-]: RETURN R0 0  ; 


; Name:            
; Defined at line: 1189
; #Upvalues:       1
; #Parameters:     0
; Is_vararg:       0
; Max Stack Size:  1

       0 [-]: GETUPVAL R0 0; var0 = upvalues[0]
       1 [-]: CALL R0 1 1  ; var0()
       2 [-]: RETURN R0 0  ; 


; Name:            
; Defined at line: 1193
; #Upvalues:       1
; #Parameters:     0
; Is_vararg:       0
; Max Stack Size:  1

       0 [-]: GETUPVAL R0 0; var0 = upvalues[0]
       1 [-]: CALL R0 1 1  ; var0()
       2 [-]: RETURN R0 0  ; 


; Name:            
; Defined at line: 1197
; #Upvalues:       1
; #Parameters:     0
; Is_vararg:       0
; Max Stack Size:  2

       0 [-]: GETUPVAL R0 0; var0 = upvalues[0]
       1 [-]: LOADN R1 -1  ; var1 = -1
       2 [-]: CALL R0 2 1  ; var0(var1)
       3 [-]: RETURN R0 0  ; 


; Name:            
; Defined at line: 1201
; #Upvalues:       1
; #Parameters:     0
; Is_vararg:       0
; Max Stack Size:  1

       0 [-]: GETUPVAL R0 0; var0 = upvalues[0]
       1 [-]: CALL R0 1 1  ; var0()
       2 [-]: RETURN R0 0  ; 


; Name:            
; Defined at line: 1205
; #Upvalues:       1
; #Parameters:     0
; Is_vararg:       0
; Max Stack Size:  1

       0 [-]: GETUPVAL R0 0; var0 = upvalues[0]
       1 [-]: CALL R0 1 1  ; var0()
       2 [-]: RETURN R0 0  ; 


; Name:            
; Defined at line: 1209
; #Upvalues:       2
; #Parameters:     0
; Is_vararg:       0
; Max Stack Size:  2

       0 [-]: GETUPVAL R0 0; var0 = upvalues[0]
       1 [-]: JUMPIFNOT R0 L0; goto L0 if not var0
       2 [-]: RETURN R0 0  ; 
L 0:   3 [-]: GETUPVAL R0 1; var0 = upvalues[1]
       4 [-]: LOADN R1 2   ; var1 = 2
       5 [-]: CALL R0 2 1  ; var0(var1)
       6 [-]: RETURN R0 0  ; 


; Name:            
; Defined at line: 1216
; #Upvalues:       1
; #Parameters:     0
; Is_vararg:       0
; Max Stack Size:  1

       0 [-]: GETUPVAL R0 0; var0 = upvalues[0]
       1 [-]: CALL R0 1 1  ; var0()
       2 [-]: RETURN R0 0  ; 


; Name:            
; Defined at line: 1220
; #Upvalues:       1
; #Parameters:     0
; Is_vararg:       0
; Max Stack Size:  1

       0 [-]: GETUPVAL R0 0; var0 = upvalues[0]
       1 [-]: CALL R0 1 1  ; var0()
       2 [-]: RETURN R0 0  ; 



