; Name:            
; Defined at line: 1
; #Upvalues:       0
; #Parameters:     0
; Is_vararg:       1
; Max Stack Size:  75

       1 [-]: GETIMPORT R0 1; var0 = 0x2D0FAD09
       2 [-]: LOADK R1 K2  ; var1 = "Lotus.Interface.LotusUtilities"
       3 [-]: CALL R0 2 2  ; var0 = var0(var1)
       4 [-]: GETIMPORT R1 1; var1 = 0x2D0FAD09
       5 [-]: LOADK R2 K3  ; var2 = "EE.Interface.Utilities"
       6 [-]: CALL R1 2 2  ; var1 = var1(var2)
       7 [-]: GETIMPORT R2 1; var2 = 0x2D0FAD09
       8 [-]: LOADK R3 K4  ; var3 = "Lotus.Scripts.Effects.EffectsColorUtilities"
       9 [-]: CALL R2 2 2  ; var2 = var2(var3)
      10 [-]: GETIMPORT R3 1; var3 = 0x2D0FAD09
      11 [-]: LOADK R4 K5  ; var4 = "Lotus.Interface.UIStyleUtilities"
      12 [-]: CALL R3 2 2  ; var3 = var3(var4)
      13 [-]: GETIMPORT R4 1; var4 = 0x2D0FAD09
      14 [-]: LOADK R5 K6  ; var5 = "EE.Interface.AnchorMgr"
      15 [-]: CALL R4 2 2  ; var4 = var4(var5)
      16 [-]: GETIMPORT R5 1; var5 = 0x2D0FAD09
      17 [-]: LOADK R6 K7  ; var6 = "Lotus.Interface.Components.ThemedButton"
      18 [-]: CALL R5 2 2  ; var5 = var5(var6)
      19 [-]: LOADNIL R6   ; var6 = nil
      20 [-]: LOADB R7 0   ; var7 = false
      21 [-]: LOADB R8 1   ; var8 = true
      22 [-]: LOADNIL R9   ; var9 = nil
      23 [-]: LOADNIL R10  ; var10 = nil
      24 [-]: LOADNIL R11  ; var11 = nil
      25 [-]: LOADNIL R12  ; var12 = nil
      26 [-]: GETIMPORT R13 9; var13 = ZERO_VECTOR
      27 [-]: LOADB R14 0  ; var14 = false
      28 [-]: LOADNIL R15  ; var15 = nil
      29 [-]: LOADB R16 0  ; var16 = false
      30 [-]: LOADNIL R17  ; var17 = nil
      31 [-]: DUPTABLE R18 12; 
      32 [-]: LOADN R19 1  ; var19 = 1
      33 [-]: SETTABLEKS R19 R18 K10; var19["MODE_SELECT"] = var18
      34 [-]: LOADN R19 2  ; var19 = 2
      35 [-]: SETTABLEKS R19 R18 K11; var19["TREE_SELECT"] = var18
      36 [-]: DUPTABLE R19 17; 
      37 [-]: LOADN R20 1  ; var20 = 1
      38 [-]: SETTABLEKS R20 R19 K13; var20["SET_PRIMARY"] = var19
      39 [-]: LOADN R20 2  ; var20 = 2
      40 [-]: SETTABLEKS R20 R19 K14; var20["ZOOM"] = var19
      41 [-]: LOADN R20 3  ; var20 = 3
      42 [-]: SETTABLEKS R20 R19 K15; var20["TENNO_CUST"] = var19
      43 [-]: LOADN R20 4  ; var20 = 4
      44 [-]: SETTABLEKS R20 R19 K16; var20["EXIT"] = var19
      45 [-]: DUPTABLE R20 21; 
      46 [-]: LOADNIL R21  ; var21 = nil
      47 [-]: SETTABLEKS R21 R20 K18; var21["QueuedAction"] = var20
      48 [-]: LOADNIL R21  ; var21 = nil
      49 [-]: SETTABLEKS R21 R20 K19; var21["QueuedId"] = var20
      50 [-]: LOADN R21 0  ; var21 = 0
      51 [-]: SETTABLEKS R21 R20 K20; var21["Focus"] = var20
      52 [-]: DUPTABLE R21 25; 
      53 [-]: LOADNIL R22  ; var22 = nil
      54 [-]: SETTABLEKS R22 R21 K22; var22["Cached"] = var21
      55 [-]: LOADNIL R22  ; var22 = nil
      56 [-]: SETTABLEKS R22 R21 K23; var22["Total"] = var21
      57 [-]: LOADN R22 177; var22 = 177
      58 [-]: SETTABLEKS R22 R21 K24; var22["Max"] = var21
      59 [-]: GETTABLEKS R22 R18 K10; var22 = var18["MODE_SELECT"]
      60 [-]: LOADNIL R23  ; var23 = nil
      61 [-]: LOADNIL R24  ; var24 = nil
      62 [-]: NEWTABLE R25 8 0; var25 = {}
      63 [-]: LOADNIL R26  ; var26 = nil
      64 [-]: NEWTABLE R27 0 0; var27 = {}
      65 [-]: DUPTABLE R28 31; 
      66 [-]: LOADN R29 1  ; var29 = 1
      67 [-]: SETTABLEKS R29 R28 K26; var29["NARAMON"] = var28
      68 [-]: LOADN R29 2  ; var29 = 2
      69 [-]: SETTABLEKS R29 R28 K27; var29["ZENURIK"] = var28
      70 [-]: LOADN R29 3  ; var29 = 3
      71 [-]: SETTABLEKS R29 R28 K28; var29["VAZARIN"] = var28
      72 [-]: LOADN R29 4  ; var29 = 4
      73 [-]: SETTABLEKS R29 R28 K29; var29["UNAIRU"] = var28
      74 [-]: LOADN R29 5  ; var29 = 5
      75 [-]: SETTABLEKS R29 R28 K30; var29["MADURAI"] = var28
      76 [-]: NEWTABLE R29 0 5; var29 = {}
      77 [-]: LOADB R30 0  ; var30 = false
      78 [-]: LOADNIL R31  ; var31 = nil
      79 [-]: LOADNIL R32  ; var32 = nil
      80 [-]: LOADB R33 0  ; var33 = false
      81 [-]: LOADN R34 0  ; var34 = 0
      82 [-]: LOADNIL R35  ; var35 = nil
      83 [-]: LOADB R36 0  ; var36 = false
      84 [-]: LOADB R37 0  ; var37 = false
      85 [-]: GETIMPORT R38 33; var38 = 0xA421AF95
      86 [-]: LOADN R39 0  ; var39 = 0
      87 [-]: LOADK R40 K34; var40 = 0.23000000417232513
      88 [-]: LOADK R41 K35; var41 = 0.079999998211860657
      89 [-]: CALL R38 4 2 ; var38 = var38(var39, var40, var41)
      90 [-]: LOADB R39 1  ; var39 = true
      91 [-]: DUPTABLE R40 41; 
      92 [-]: LOADB R41 0  ; var41 = false
      93 [-]: SETTABLEKS R41 R40 K36; var41["Visible"] = var40
      94 [-]: LOADB R41 0  ; var41 = false
      95 [-]: SETTABLEKS R41 R40 K37; var41["TransitionedIn"] = var40
      96 [-]: LOADB R41 0  ; var41 = false
      97 [-]: SETTABLEKS R41 R40 K38; var41["Dissolving"] = var40
      98 [-]: LOADN R41 0  ; var41 = 0
      99 [-]: SETTABLEKS R41 R40 K39; var41["DissolveVal"] = var40
     100 [-]: LOADN R41 1  ; var41 = 1
     101 [-]: SETTABLEKS R41 R40 K40; var41["DissolveDir"] = var40
     102 [-]: LOADNIL R41  ; var41 = nil
     103 [-]: LOADB R42 0  ; var42 = false
     104 [-]: LOADNIL R43  ; var43 = nil
     105 [-]: LOADNIL R44  ; var44 = nil
     106 [-]: LOADNIL R45  ; var45 = nil
     107 [-]: LOADNIL R46  ; var46 = nil
     108 [-]: LOADNIL R47  ; var47 = nil
     109 [-]: LOADNIL R48  ; var48 = nil
     110 [-]: LOADNIL R49  ; var49 = nil
     111 [-]: LOADNIL R50  ; var50 = nil
     112 [-]: LOADB R51 0  ; var51 = false
     113 [-]: LOADB R52 0  ; var52 = false
     114 [-]: NEWCLOSURE R53 P0; 
     115 [-]: CAPTURE REF R25; 
     116 [-]: CAPTURE VAL R3; 
     117 [-]: CAPTURE VAL R1; 
     118 [-]: CAPTURE REF R24; 
     119 [-]: NEWCLOSURE R54 P1; 
     120 [-]: CAPTURE REF R39; 
     121 [-]: CAPTURE REF R44; 
     122 [-]: CAPTURE REF R24; 
     123 [-]: SETGLOBAL R54 K42; "Shutdown" = var54
     124 [-]: DUPCLOSURE R54 K43; 
     125 [-]: SETGLOBAL R54 K44; "InitializePod" = var54
     126 [-]: DUPCLOSURE R54 K45; 
     127 [-]: SETGLOBAL R54 K46; "OpenPod" = var54
     128 [-]: DUPCLOSURE R54 K47; 
     129 [-]: SETGLOBAL R54 K48; "ClosePod" = var54
     130 [-]: DUPCLOSURE R54 K49; 
     131 [-]: NEWCLOSURE R55 P6; 
     132 [-]: CAPTURE REF R36; 
     133 [-]: SETGLOBAL R55 K50; "OperatorLeaveChair" = var55
     134 [-]: NEWCLOSURE R55 P7; 
     135 [-]: CAPTURE REF R42; 
     136 [-]: CAPTURE REF R48; 
     137 [-]: CAPTURE VAL R19; 
     138 [-]: CAPTURE REF R41; 
     139 [-]: CAPTURE REF R36; 
     140 [-]: CAPTURE REF R37; 
     141 [-]: CAPTURE VAL R0; 
     142 [-]: CAPTURE REF R8; 
     143 [-]: CAPTURE REF R39; 
     144 [-]: CAPTURE VAL R1; 
     145 [-]: CAPTURE REF R16; 
     146 [-]: CAPTURE REF R26; 
     147 [-]: CAPTURE VAL R27; 
     148 [-]: CAPTURE VAL R54; 
     149 [-]: CAPTURE REF R52; 
     150 [-]: CAPTURE REF R51; 
     151 [-]: CAPTURE REF R44; 
     152 [-]: DUPCLOSURE R56 K51; 
     153 [-]: CAPTURE VAL R55; 
     154 [-]: SETGLOBAL R56 K52; "TransitionOut" = var56
     155 [-]: DUPCLOSURE R56 K53; 
     156 [-]: CAPTURE VAL R55; 
     157 [-]: NEWCLOSURE R57 P10; 
     158 [-]: CAPTURE REF R48; 
     159 [-]: CAPTURE VAL R19; 
     160 [-]: CAPTURE VAL R0; 
     161 [-]: CAPTURE VAL R55; 
     162 [-]: DUPCLOSURE R58 K54; 
     163 [-]: CAPTURE VAL R57; 
     164 [-]: SETGLOBAL R58 K55; "OpenTennoCustomization" = var58
     165 [-]: NEWCLOSURE R58 P12; 
     166 [-]: CAPTURE REF R12; 
     167 [-]: CAPTURE REF R13; 
     168 [-]: NEWCLOSURE R59 P13; 
     169 [-]: CAPTURE REF R15; 
     170 [-]: CAPTURE REF R24; 
     171 [-]: CAPTURE REF R50; 
     172 [-]: NEWCLOSURE R60 P14; 
     173 [-]: CAPTURE REF R14; 
     174 [-]: CAPTURE REF R24; 
     175 [-]: CAPTURE VAL R1; 
     176 [-]: CAPTURE REF R10; 
     177 [-]: NEWCLOSURE R50 P15; 
     178 [-]: CAPTURE REF R24; 
     179 [-]: CAPTURE REF R48; 
     180 [-]: CAPTURE VAL R19; 
     181 [-]: CAPTURE REF R12; 
     182 [-]: CAPTURE VAL R58; 
     183 [-]: CAPTURE REF R14; 
     184 [-]: CAPTURE REF R11; 
     185 [-]: CAPTURE REF R17; 
     186 [-]: CAPTURE VAL R1; 
     187 [-]: CAPTURE REF R15; 
     188 [-]: CAPTURE REF R8; 
     189 [-]: CAPTURE VAL R59; 
     190 [-]: CAPTURE VAL R60; 
     191 [-]: NEWCLOSURE R61 P16; 
     192 [-]: CAPTURE REF R24; 
     193 [-]: NEWCLOSURE R62 P17; 
     194 [-]: CAPTURE VAL R61; 
     195 [-]: CAPTURE REF R11; 
     196 [-]: SETGLOBAL R62 K56; "RefreshZoomedWay" = var62
     197 [-]: NEWCLOSURE R62 P18; 
     198 [-]: CAPTURE REF R50; 
     199 [-]: CAPTURE REF R15; 
     200 [-]: CAPTURE REF R8; 
     201 [-]: CAPTURE REF R44; 
     202 [-]: SETGLOBAL R62 K57; "ClearZoom" = var62
     203 [-]: NEWCLOSURE R62 P19; 
     204 [-]: CAPTURE REF R22; 
     205 [-]: CAPTURE REF R47; 
     206 [-]: CAPTURE REF R45; 
     207 [-]: CAPTURE REF R46; 
     208 [-]: NEWCLOSURE R63 P20; 
     209 [-]: CAPTURE REF R15; 
     210 [-]: CAPTURE VAL R62; 
     211 [-]: CAPTURE VAL R18; 
     212 [-]: SETGLOBAL R63 K58; "GotoWayTree" = var63
     213 [-]: NEWCLOSURE R63 P21; 
     214 [-]: CAPTURE REF R52; 
     215 [-]: CAPTURE REF R22; 
     216 [-]: CAPTURE VAL R18; 
     217 [-]: CAPTURE REF R47; 
     218 [-]: CAPTURE REF R46; 
     219 [-]: SETGLOBAL R63 K59; "ShowTreeSelection" = var63
     220 [-]: NEWCLOSURE R46 P22; 
     221 [-]: CAPTURE REF R14; 
     222 [-]: CAPTURE REF R50; 
     223 [-]: CAPTURE REF R22; 
     224 [-]: CAPTURE VAL R18; 
     225 [-]: CAPTURE REF R52; 
     226 [-]: CAPTURE VAL R62; 
     227 [-]: CAPTURE VAL R0; 
     228 [-]: NEWCLOSURE R63 P23; 
     229 [-]: CAPTURE VAL R5; 
     230 [-]: CAPTURE REF R25; 
     231 [-]: CAPTURE REF R24; 
     232 [-]: CAPTURE REF R30; 
     233 [-]: NEWCLOSURE R64 P24; 
     234 [-]: CAPTURE REF R10; 
     235 [-]: CAPTURE VAL R1; 
     236 [-]: CAPTURE REF R24; 
     237 [-]: CAPTURE REF R22; 
     238 [-]: CAPTURE VAL R18; 
     239 [-]: CAPTURE REF R14; 
     240 [-]: CAPTURE REF R32; 
     241 [-]: NEWCLOSURE R65 P25; 
     242 [-]: CAPTURE VAL R64; 
     243 [-]: CAPTURE REF R43; 
     244 [-]: CAPTURE VAL R1; 
     245 [-]: CAPTURE REF R17; 
     246 [-]: CAPTURE REF R11; 
     247 [-]: CAPTURE VAL R60; 
     248 [-]: SETGLOBAL R65 K60; "FocusAbilitySet" = var65
     249 [-]: LOADNIL R65  ; var65 = nil
     250 [-]: NEWCLOSURE R65 P26; 
     251 [-]: CAPTURE REF R31; 
     252 [-]: CAPTURE REF R65; 
     253 [-]: NEWCLOSURE R66 P27; 
     254 [-]: CAPTURE REF R24; 
     255 [-]: CAPTURE REF R32; 
     256 [-]: CAPTURE VAL R1; 
     257 [-]: CAPTURE VAL R20; 
     258 [-]: CAPTURE VAL R0; 
     259 [-]: CAPTURE REF R10; 
     260 [-]: CAPTURE REF R25; 
     261 [-]: CAPTURE REF R30; 
     262 [-]: CAPTURE REF R46; 
     263 [-]: CAPTURE REF R65; 
     264 [-]: CAPTURE REF R31; 
     265 [-]: CAPTURE REF R22; 
     266 [-]: CAPTURE VAL R18; 
     267 [-]: CAPTURE VAL R62; 
     268 [-]: CAPTURE VAL R57; 
     269 [-]: CAPTURE REF R50; 
     270 [-]: CAPTURE REF R44; 
     271 [-]: CAPTURE VAL R63; 
     272 [-]: CAPTURE REF R29; 
     273 [-]: DUPCLOSURE R67 K61; 
     274 [-]: NEWCLOSURE R68 P29; 
     275 [-]: CAPTURE VAL R67; 
     276 [-]: CAPTURE REF R9; 
     277 [-]: NEWCLOSURE R45 P30; 
     278 [-]: CAPTURE REF R24; 
     279 [-]: CAPTURE REF R22; 
     280 [-]: CAPTURE VAL R18; 
     281 [-]: CAPTURE REF R10; 
     282 [-]: CAPTURE VAL R28; 
     283 [-]: CAPTURE VAL R1; 
     284 [-]: CAPTURE VAL R40; 
     285 [-]: CAPTURE VAL R64; 
     286 [-]: CAPTURE REF R15; 
     287 [-]: CAPTURE REF R6; 
     288 [-]: CAPTURE VAL R59; 
     289 [-]: CAPTURE REF R8; 
     290 [-]: NEWCLOSURE R69 P31; 
     291 [-]: CAPTURE REF R35; 
     292 [-]: CAPTURE REF R34; 
     293 [-]: CAPTURE VAL R0; 
     294 [-]: NEWCLOSURE R70 P32; 
     295 [-]: CAPTURE REF R7; 
     296 [-]: CAPTURE REF R6; 
     297 [-]: CAPTURE REF R51; 
     298 [-]: CAPTURE REF R16; 
     299 [-]: CAPTURE VAL R69; 
     300 [-]: CAPTURE VAL R0; 
     301 [-]: CAPTURE REF R12; 
     302 [-]: CAPTURE VAL R58; 
     303 [-]: CAPTURE REF R13; 
     304 [-]: CAPTURE VAL R1; 
     305 [-]: CAPTURE REF R36; 
     306 [-]: CAPTURE VAL R38; 
     307 [-]: CAPTURE REF R52; 
     308 [-]: CAPTURE REF R34; 
     309 [-]: CAPTURE REF R33; 
     310 [-]: CAPTURE VAL R40; 
     311 [-]: CAPTURE REF R49; 
     312 [-]: CAPTURE REF R8; 
     313 [-]: SETGLOBAL R70 K62; "Update" = var70
     314 [-]: NEWCLOSURE R70 P33; 
     315 [-]: CAPTURE VAL R1; 
     316 [-]: CAPTURE REF R25; 
     317 [-]: NEWCLOSURE R71 P34; 
     318 [-]: CAPTURE VAL R20; 
     319 [-]: CAPTURE VAL R61; 
     320 [-]: CAPTURE REF R10; 
     321 [-]: CAPTURE VAL R19; 
     322 [-]: CAPTURE REF R24; 
     323 [-]: CAPTURE REF R50; 
     324 [-]: CAPTURE VAL R57; 
     325 [-]: CAPTURE VAL R55; 
     326 [-]: DUPCLOSURE R72 K63; 
     327 [-]: CAPTURE VAL R71; 
     328 [-]: CAPTURE VAL R20; 
     329 [-]: SETGLOBAL R72 K64; "OnConfirmCommitFocusChanges" = var72
     330 [-]: DUPCLOSURE R48 K65; 
     331 [-]: CAPTURE VAL R20; 
     332 [-]: CAPTURE VAL R1; 
     333 [-]: CAPTURE VAL R21; 
     334 [-]: NEWCLOSURE R47 P37; 
     335 [-]: CAPTURE REF R29; 
     336 [-]: CAPTURE REF R22; 
     337 [-]: CAPTURE VAL R18; 
     338 [-]: DUPCLOSURE R72 K66; 
     339 [-]: CAPTURE VAL R2; 
     340 [-]: NEWCLOSURE R73 P39; 
     341 [-]: CAPTURE REF R6; 
     342 [-]: CAPTURE REF R22; 
     343 [-]: CAPTURE VAL R18; 
     344 [-]: CAPTURE REF R15; 
     345 [-]: CAPTURE REF R35; 
     346 [-]: CAPTURE REF R51; 
     347 [-]: CAPTURE VAL R0; 
     348 [-]: CAPTURE VAL R53; 
     349 [-]: CAPTURE VAL R40; 
     350 [-]: CAPTURE REF R36; 
     351 [-]: CAPTURE REF R37; 
     352 [-]: CAPTURE VAL R1; 
     353 [-]: CAPTURE REF R9; 
     354 [-]: CAPTURE VAL R4; 
     355 [-]: CAPTURE VAL R72; 
     356 [-]: CAPTURE REF R47; 
     357 [-]: CAPTURE VAL R66; 
     358 [-]: CAPTURE REF R46; 
     359 [-]: CAPTURE REF R45; 
     360 [-]: CAPTURE VAL R68; 
     361 [-]: CAPTURE VAL R54; 
     362 [-]: CAPTURE REF R25; 
     363 [-]: CAPTURE VAL R70; 
     364 [-]: CAPTURE REF R7; 
     365 [-]: SETGLOBAL R73 K67; "Initialize" = var73
     366 [-]: DUPCLOSURE R73 K68; 
     367 [-]: CAPTURE VAL R68; 
     368 [-]: SETGLOBAL R73 K69; "onViewportSizeChanged" = var73
     369 [-]: NEWCLOSURE R73 P41; 
     370 [-]: CAPTURE REF R7; 
     371 [-]: CAPTURE REF R8; 
     372 [-]: CAPTURE REF R45; 
     373 [-]: SETGLOBAL R73 K70; "RefreshMenu" = var73
     374 [-]: NEWCLOSURE R73 P42; 
     375 [-]: CAPTURE REF R26; 
     376 [-]: SETGLOBAL R73 K71; "SetCallBack" = var73
     377 [-]: DUPCLOSURE R73 K72; 
     378 [-]: CAPTURE VAL R55; 
     379 [-]: SETGLOBAL R73 K73; "Close" = var73
     380 [-]: DUPCLOSURE R73 K74; 
     381 [-]: CAPTURE VAL R56; 
     382 [-]: SETGLOBAL R73 K75; "ExitScreen" = var73
     383 [-]: DUPCLOSURE R73 K76; 
     384 [-]: SETGLOBAL R73 K77; "SetTrigger" = var73
     385 [-]: NEWCLOSURE R73 P46; 
     386 [-]: CAPTURE REF R8; 
     387 [-]: CAPTURE REF R24; 
     388 [-]: SETGLOBAL R73 K78; "onKeyUp_MENU_SELECT" = var73
     389 [-]: NEWCLOSURE R73 P47; 
     390 [-]: CAPTURE REF R24; 
     391 [-]: SETGLOBAL R73 K79; "MenuEntryFocused" = var73
     392 [-]: NEWCLOSURE R73 P48; 
     393 [-]: CAPTURE REF R8; 
     394 [-]: CAPTURE REF R24; 
     395 [-]: SETGLOBAL R73 K80; "MenuEntryUnfocused" = var73
     396 [-]: NEWCLOSURE R73 P49; 
     397 [-]: CAPTURE REF R8; 
     398 [-]: CAPTURE REF R24; 
     399 [-]: SETGLOBAL R73 K81; "MenuEntryPressed" = var73
     400 [-]: DUPCLOSURE R73 K82; 
     401 [-]: CAPTURE VAL R55; 
     402 [-]: SETGLOBAL R73 K83; "onKeyDown_HIDE_PAUSE_MENU" = var73
     403 [-]: DUPCLOSURE R73 K84; 
     404 [-]: CAPTURE VAL R1; 
     405 [-]: SETGLOBAL R73 K85; "RollOver" = var73
     406 [-]: DUPCLOSURE R73 K86; 
     407 [-]: SETGLOBAL R73 K87; "onKeyDown_MENU_MOUSE_Z" = var73
     408 [-]: NEWCLOSURE R73 P53; 
     409 [-]: CAPTURE REF R8; 
     410 [-]: CAPTURE REF R24; 
     411 [-]: SETGLOBAL R73 K88; "onKeyUp_MENU_GENERIC2" = var73
     412 [-]: NEWCLOSURE R73 P54; 
     413 [-]: CAPTURE REF R8; 
     414 [-]: SETGLOBAL R73 K89; "IsInputBlocked" = var73
     415 [-]: NEWCLOSURE R73 P55; 
     416 [-]: CAPTURE REF R8; 
     417 [-]: CAPTURE REF R48; 
     418 [-]: CAPTURE VAL R19; 
     419 [-]: CAPTURE REF R24; 
     420 [-]: CAPTURE REF R43; 
     421 [-]: SETGLOBAL R73 K90; "SetAsPrimary" = var73
     422 [-]: NEWCLOSURE R73 P56; 
     423 [-]: CAPTURE REF R11; 
     424 [-]: SETGLOBAL R73 K91; "SetZoomedPrimary" = var73
     425 [-]: DUPCLOSURE R73 K92; 
     426 [-]: CAPTURE VAL R59; 
     427 [-]: SETGLOBAL R73 K93; "SuccessReviewed" = var73
     428 [-]: NEWCLOSURE R73 P58; 
     429 [-]: CAPTURE VAL R1; 
     430 [-]: CAPTURE REF R45; 
     431 [-]: CAPTURE REF R15; 
     432 [-]: CAPTURE REF R23; 
     433 [-]: CAPTURE REF R8; 
     434 [-]: SETGLOBAL R73 K94; "OnTreeUnlocked" = var73
     435 [-]: NEWCLOSURE R73 P59; 
     436 [-]: CAPTURE REF R23; 
     437 [-]: CAPTURE REF R8; 
     438 [-]: SETGLOBAL R73 K95; "OnConfirmUnlockTree" = var73
     439 [-]: NEWCLOSURE R73 P60; 
     440 [-]: CAPTURE REF R8; 
     441 [-]: CAPTURE REF R24; 
     442 [-]: CAPTURE VAL R1; 
     443 [-]: CAPTURE REF R23; 
     444 [-]: SETGLOBAL R73 K96; "UnlockTree" = var73
     445 [-]: NEWCLOSURE R73 P61; 
     446 [-]: CAPTURE VAL R1; 
     447 [-]: CAPTURE REF R36; 
     448 [-]: DUPCLOSURE R74 K97; 
     449 [-]: CAPTURE VAL R1; 
     450 [-]: CAPTURE VAL R73; 
     451 [-]: SETGLOBAL R74 K98; "DrifterFocused" = var74
     452 [-]: DUPCLOSURE R74 K99; 
     453 [-]: CAPTURE VAL R1; 
     454 [-]: SETGLOBAL R74 K100; "DrifterUnfocused" = var74
     455 [-]: NEWCLOSURE R49 P64; 
     456 [-]: CAPTURE REF R36; 
     457 [-]: CAPTURE REF R51; 
     458 [-]: CAPTURE REF R13; 
     459 [-]: CAPTURE VAL R1; 
     460 [-]: CAPTURE VAL R38; 
     461 [-]: CAPTURE REF R12; 
     462 [-]: CAPTURE VAL R72; 
     463 [-]: CAPTURE VAL R62; 
     464 [-]: CAPTURE REF R22; 
     465 [-]: CAPTURE VAL R73; 
     466 [-]: CAPTURE REF R41; 
     467 [-]: CAPTURE REF R6; 
     468 [-]: CAPTURE VAL R40; 
     469 [-]: NEWCLOSURE R74 P65; 
     470 [-]: CAPTURE REF R8; 
     471 [-]: CAPTURE VAL R1; 
     472 [-]: CAPTURE VAL R40; 
     473 [-]: CAPTURE REF R24; 
     474 [-]: SETGLOBAL R74 K101; "DrifterPressed" = var74
     475 [-]: NEWCLOSURE R74 P66; 
     476 [-]: CAPTURE REF R41; 
     477 [-]: CAPTURE VAL R55; 
     478 [-]: CAPTURE REF R42; 
     479 [-]: SETGLOBAL R74 K102; "OnSaveLoadOutComplete" = var74
     480 [-]: DUPCLOSURE R74 K103; 
     481 [-]: CAPTURE VAL R53; 
     482 [-]: SETGLOBAL R74 K104; "OnStyleChangedCallback" = var74
     483 [-]: DUPCLOSURE R74 K105; 
     484 [-]: SETGLOBAL R74 K106; "SupportsThemes" = var74
     485 [-]: DUPCLOSURE R74 K107; 
     486 [-]: SETGLOBAL R74 K108; "HideScreenForPlatPurchase" = var74
     487 [-]: CLOSEUPVALS R6; 
     488 [-]: RETURN R0 0  ; 


; Name:            
; Defined at line: 114
; #Upvalues:       4
; #Parameters:     0
; Is_vararg:       0
; Max Stack Size:  6

       0 [-]: DUPTABLE R0 7; 
       1 [-]: GETUPVAL R2 1; var2 = upvalues[1]
       2 [-]: GETTABLEKS R1 R2 K8; var1 = var2[0x5D10207D]
       3 [-]: LOADN R2 9   ; var2 = 9
       4 [-]: LOADB R3 1   ; var3 = true
       5 [-]: CALL R1 3 2  ; var1 = var1(var2, var3)
       6 [-]: SETTABLEKS R1 R0 K0; var1["FloatingContent"] = var0
       7 [-]: GETUPVAL R2 1; var2 = upvalues[1]
       8 [-]: GETTABLEKS R1 R2 K8; var1 = var2[0x5D10207D]
       9 [-]: LOADN R2 10  ; var2 = 10
      10 [-]: LOADB R3 1   ; var3 = true
      11 [-]: CALL R1 3 2  ; var1 = var1(var2, var3)
      12 [-]: SETTABLEKS R1 R0 K1; var1["FloatingContentHighlight"] = var0
      13 [-]: GETUPVAL R2 1; var2 = upvalues[1]
      14 [-]: GETTABLEKS R1 R2 K8; var1 = var2[0x5D10207D]
      15 [-]: LOADN R2 6   ; var2 = 6
      16 [-]: LOADB R3 1   ; var3 = true
      17 [-]: CALL R1 3 2  ; var1 = var1(var2, var3)
      18 [-]: SETTABLEKS R1 R0 K2; var1["Content"] = var0
      19 [-]: GETUPVAL R2 1; var2 = upvalues[1]
      20 [-]: GETTABLEKS R1 R2 K8; var1 = var2[0x5D10207D]
      21 [-]: LOADN R2 2   ; var2 = 2
      22 [-]: LOADB R3 1   ; var3 = true
      23 [-]: CALL R1 3 2  ; var1 = var1(var2, var3)
      24 [-]: SETTABLEKS R1 R0 K3; var1["Background1"] = var0
      25 [-]: GETUPVAL R2 1; var2 = upvalues[1]
      26 [-]: GETTABLEKS R1 R2 K8; var1 = var2[0x5D10207D]
      27 [-]: LOADN R2 3   ; var2 = 3
      28 [-]: LOADB R3 1   ; var3 = true
      29 [-]: CALL R1 3 2  ; var1 = var1(var2, var3)
      30 [-]: SETTABLEKS R1 R0 K4; var1["Background2"] = var0
      31 [-]: GETUPVAL R2 1; var2 = upvalues[1]
      32 [-]: GETTABLEKS R1 R2 K8; var1 = var2[0x5D10207D]
      33 [-]: LOADN R2 4   ; var2 = 4
      34 [-]: LOADB R3 1   ; var3 = true
      35 [-]: CALL R1 3 2  ; var1 = var1(var2, var3)
      36 [-]: SETTABLEKS R1 R0 K5; var1["Background3"] = var0
      37 [-]: GETUPVAL R2 1; var2 = upvalues[1]
      38 [-]: GETTABLEKS R1 R2 K8; var1 = var2[0x5D10207D]
      39 [-]: LOADN R2 12  ; var2 = 12
      40 [-]: LOADB R3 1   ; var3 = true
      41 [-]: CALL R1 3 2  ; var1 = var1(var2, var3)
      42 [-]: SETTABLEKS R1 R0 K6; var1["Negative"] = var0
      43 [-]: SETUPVAL R0 0; upvalues[0] = var0
      44 [-]: GETUPVAL R0 0; var0 = upvalues[0]
      45 [-]: GETUPVAL R2 2; var2 = upvalues[2]
      46 [-]: GETTABLEKS R1 R2 K9; var1 = var2[0x9F57DD7D]
      47 [-]: GETUPVAL R3 0; var3 = upvalues[0]
      48 [-]: GETTABLEKS R2 R3 K0; var2 = var3["FloatingContent"]
      49 [-]: CALL R1 2 2  ; var1 = var1(var2)
      50 [-]: SETTABLEKS R1 R0 K10; var1["FloatingContentHex"] = var0
      51 [-]: GETUPVAL R0 0; var0 = upvalues[0]
      52 [-]: GETUPVAL R2 2; var2 = upvalues[2]
      53 [-]: GETTABLEKS R1 R2 K9; var1 = var2[0x9F57DD7D]
      54 [-]: GETUPVAL R3 0; var3 = upvalues[0]
      55 [-]: GETTABLEKS R2 R3 K1; var2 = var3["FloatingContentHighlight"]
      56 [-]: CALL R1 2 2  ; var1 = var1(var2)
      57 [-]: SETTABLEKS R1 R0 K11; var1["FloatingContentHighlightHex"] = var0
      58 [-]: GETUPVAL R0 0; var0 = upvalues[0]
      59 [-]: GETUPVAL R2 2; var2 = upvalues[2]
      60 [-]: GETTABLEKS R1 R2 K9; var1 = var2[0x9F57DD7D]
      61 [-]: GETUPVAL R3 0; var3 = upvalues[0]
      62 [-]: GETTABLEKS R2 R3 K2; var2 = var3["Content"]
      63 [-]: CALL R1 2 2  ; var1 = var1(var2)
      64 [-]: SETTABLEKS R1 R0 K12; var1["ContentHex"] = var0
      65 [-]: GETUPVAL R0 0; var0 = upvalues[0]
      66 [-]: GETUPVAL R2 2; var2 = upvalues[2]
      67 [-]: GETTABLEKS R1 R2 K9; var1 = var2[0x9F57DD7D]
      68 [-]: GETUPVAL R3 0; var3 = upvalues[0]
      69 [-]: GETTABLEKS R2 R3 K6; var2 = var3["Negative"]
      70 [-]: CALL R1 2 2  ; var1 = var1(var2)
      71 [-]: SETTABLEKS R1 R0 K13; var1["NegativeHex"] = var0
      72 [-]: GETUPVAL R0 0; var0 = upvalues[0]
      73 [-]: GETUPVAL R2 2; var2 = upvalues[2]
      74 [-]: GETTABLEKS R1 R2 K14; var1 = var2[0x8BCD12B6]
      75 [-]: GETUPVAL R3 0; var3 = upvalues[0]
      76 [-]: GETTABLEKS R2 R3 K3; var2 = var3["Background1"]
      77 [-]: CALL R1 2 2  ; var1 = var1(var2)
      78 [-]: SETTABLEKS R1 R0 K15; var1["Background1Object"] = var0
      79 [-]: GETUPVAL R0 0; var0 = upvalues[0]
      80 [-]: GETUPVAL R2 2; var2 = upvalues[2]
      81 [-]: GETTABLEKS R1 R2 K14; var1 = var2[0x8BCD12B6]
      82 [-]: GETUPVAL R3 0; var3 = upvalues[0]
      83 [-]: GETTABLEKS R2 R3 K1; var2 = var3["FloatingContentHighlight"]
      84 [-]: CALL R1 2 2  ; var1 = var1(var2)
      85 [-]: SETTABLEKS R1 R0 K16; var1["FloatingContentHighlightObject"] = var0
      86 [-]: GETIMPORT R0 18; var0 = 0xAE91E43B
      87 [-]: LOADK R2 K19 ; var2 = "Capacity.Title"
      88 [-]: LOADN R3 9   ; var3 = 9
      89 [-]: GETUPVAL R5 0; var5 = upvalues[0]
      90 [-]: GETTABLEKS R4 R5 K2; var4 = var5["Content"]
      91 [-]: NAMECALL R0 R0 K20; var1 = var0; var0 = var0[0x67BC869F]
      92 [-]: CALL R0 5 1  ; var0(var1, var2, var3, var4)
      93 [-]: GETIMPORT R0 18; var0 = 0xAE91E43B
      94 [-]: LOADK R2 K21 ; var2 = "Capacity.Total"
      95 [-]: LOADN R3 9   ; var3 = 9
      96 [-]: GETUPVAL R5 0; var5 = upvalues[0]
      97 [-]: GETTABLEKS R4 R5 K2; var4 = var5["Content"]
      98 [-]: NAMECALL R0 R0 K20; var1 = var0; var0 = var0[0x67BC869F]
      99 [-]: CALL R0 5 1  ; var0(var1, var2, var3, var4)
     100 [-]: GETIMPORT R0 18; var0 = 0xAE91E43B
     101 [-]: LOADK R2 K22 ; var2 = "Capacity.Edges"
     102 [-]: LOADN R3 9   ; var3 = 9
     103 [-]: GETUPVAL R5 0; var5 = upvalues[0]
     104 [-]: GETTABLEKS R4 R5 K0; var4 = var5["FloatingContent"]
     105 [-]: NAMECALL R0 R0 K20; var1 = var0; var0 = var0[0x67BC869F]
     106 [-]: CALL R0 5 1  ; var0(var1, var2, var3, var4)
     107 [-]: GETIMPORT R0 18; var0 = 0xAE91E43B
     108 [-]: LOADK R2 K23 ; var2 = "Capacity.Bg"
     109 [-]: LOADN R3 9   ; var3 = 9
     110 [-]: GETUPVAL R5 0; var5 = upvalues[0]
     111 [-]: GETTABLEKS R4 R5 K3; var4 = var5["Background1"]
     112 [-]: NAMECALL R0 R0 K20; var1 = var0; var0 = var0[0x67BC869F]
     113 [-]: CALL R0 5 1  ; var0(var1, var2, var3, var4)
     114 [-]: GETUPVAL R1 3; var1 = upvalues[3]
     115 [-]: FASTCALL1 64 R1 L0; 
     116 [-]: GETIMPORT R0 25; var0 = 0x7B998233
     117 [-]: CALL R0 2 2  ; var0 = var0(var1)
L 0: 118 [-]: JUMPIF R0 L1 ; goto L1 if var0
     119 [-]: GETUPVAL R0 3; var0 = upvalues[3]
     120 [-]: GETUPVAL R3 3; var3 = upvalues[3]
     121 [-]: GETTABLEKS R2 R3 K26; var2 = var3["UpdateElementColor"]
     122 [-]: NAMECALL R0 R0 K27; var1 = var0; var0 = var0[0xEA061E98]
     123 [-]: CALL R0 3 1  ; var0(var1, var2)
L 1: 124 [-]: LOADNIL R1   ; var1 = nil
     125 [-]: FASTCALL1 64 R1 L2; 
     126 [-]: GETIMPORT R0 25; var0 = 0x7B998233
     127 [-]: CALL R0 2 2  ; var0 = var0(var1)
L 2: 128 [-]: JUMPIF R0 L3 ; goto L3 if var0
     129 [-]: LOADNIL R0   ; var0 = nil
     130 [-]: NAMECALL R0 R0 K28; var1 = var0; var0 = var0[0x087CBD3F]
     131 [-]: CALL R0 2 1  ; var0(var1)
L 3: 132 [-]: RETURN R0 0  ; 


; Name:            
; Defined at line: 146
; #Upvalues:       3
; #Parameters:     0
; Is_vararg:       0
; Max Stack Size:  6

       0 [-]: GETUPVAL R0 0; var0 = upvalues[0]
       1 [-]: JUMPIFNOT R0 L0; goto L0 if not var0
       2 [-]: GETIMPORT R0 2; var0 = _T["DisableUIInput"]
       3 [-]: CALL R0 1 1  ; var0()
L 0:   4 [-]: GETIMPORT R0 3; var0 = _T
       5 [-]: LOADNIL R1   ; var1 = nil
       6 [-]: SETTABLEKS R1 R0 K4; var1["gToolTip"] = var0
       7 [-]: GETIMPORT R0 3; var0 = _T
       8 [-]: LOADNIL R1   ; var1 = nil
       9 [-]: SETTABLEKS R1 R0 K5; var1["SetClanEnum"] = var0
      10 [-]: GETIMPORT R0 3; var0 = _T
      11 [-]: LOADNIL R1   ; var1 = nil
      12 [-]: SETTABLEKS R1 R0 K6; var1["SetCurrentResults"] = var0
      13 [-]: GETIMPORT R1 8; var1 = 0xCB79539E
      14 [-]: FASTCALL1 64 R1 L1; 
      15 [-]: GETIMPORT R0 10; var0 = 0x7B998233
      16 [-]: CALL R0 2 2  ; var0 = var0(var1)
L 1:  17 [-]: JUMPIF R0 L3 ; goto L3 if var0
      18 [-]: GETUPVAL R0 1; var0 = upvalues[1]
      19 [-]: JUMPIFNOT R0 L2; goto L2 if not var0
      20 [-]: GETIMPORT R0 8; var0 = 0xCB79539E
      21 [-]: GETIMPORT R2 12; var2 = 0x0469F296
      22 [-]: LOADK R3 K13 ; var3 = "IN_SHIP_VIEW_TIME"
      23 [-]: CALL R2 2 2  ; var2 = var2(var3)
      24 [-]: LOADK R4 K14 ; var4 = "OPERATOR_FOCUS_"
      25 [-]: GETUPVAL R5 1; var5 = upvalues[1]
      26 [-]: CONCAT R3 R4 R5; var3 = var4 .. var5
      27 [-]: NAMECALL R0 R0 K15; var1 = var0; var0 = var0[0xA9188A47]
      28 [-]: CALL R0 4 1  ; var0(var1, var2, var3)
      29 [-]: LOADNIL R0   ; var0 = nil
      30 [-]: SETUPVAL R0 1; upvalues[0] = var1
L 2:  31 [-]: GETIMPORT R0 8; var0 = 0xCB79539E
      32 [-]: GETIMPORT R2 12; var2 = 0x0469F296
      33 [-]: LOADK R3 K13 ; var3 = "IN_SHIP_VIEW_TIME"
      34 [-]: CALL R2 2 2  ; var2 = var2(var3)
      35 [-]: LOADK R3 K16 ; var3 = "OPERATOR_FOCUS_MAIN"
      36 [-]: NAMECALL R0 R0 K15; var1 = var0; var0 = var0[0xA9188A47]
      37 [-]: CALL R0 4 1  ; var0(var1, var2, var3)
L 3:  38 [-]: GETUPVAL R1 2; var1 = upvalues[2]
      39 [-]: FASTCALL1 64 R1 L4; 
      40 [-]: GETIMPORT R0 10; var0 = 0x7B998233
      41 [-]: CALL R0 2 2  ; var0 = var0(var1)
L 4:  42 [-]: JUMPIF R0 L5 ; goto L5 if var0
      43 [-]: GETUPVAL R0 2; var0 = upvalues[2]
      44 [-]: GETUPVAL R3 2; var3 = upvalues[2]
      45 [-]: GETTABLEKS R2 R3 K17; var2 = var3["UpdateFX"]
      46 [-]: NAMECALL R0 R0 K18; var1 = var0; var0 = var0[0xEA061E98]
      47 [-]: CALL R0 3 1  ; var0(var1, var2)
L 5:  48 [-]: RETURN R0 0  ; 


; Name:            
; Defined at line: 168
; #Upvalues:       0
; #Parameters:     1
; Is_vararg:       0
; Max Stack Size:  11

       0 [-]: GETIMPORT R1 1; var1 = _T
       1 [-]: DUPTABLE R2 5; 
       2 [-]: GETIMPORT R3 7; var3 = 0x55156FF7
       3 [-]: CALL R3 1 2  ; var3 = var3()
       4 [-]: SETTABLEKS R3 R2 K2; var3["PlayTime"] = var2
       5 [-]: LOADNIL R3   ; var3 = nil
       6 [-]: SETTABLEKS R3 R2 K3; var3["PendingAnimation"] = var2
       7 [-]: LOADNIL R3   ; var3 = nil
       8 [-]: SETTABLEKS R3 R2 K4; var3["LastPlayed"] = var2
       9 [-]: SETTABLEKS R2 R1 K8; var2["PodState"] = var1
L 0:  10 [-]: GETIMPORT R2 9; var2 = _T["PodState"]
      11 [-]: FASTCALL1 64 R2 L1; 
      12 [-]: GETIMPORT R1 11; var1 = 0x7B998233
      13 [-]: CALL R1 2 2  ; var1 = var1(var2)
L 1:  14 [-]: JUMPIF R1 L8 ; goto L8 if var1
      15 [-]: GETIMPORT R2 7; var2 = 0x55156FF7
      16 [-]: CALL R2 1 2  ; var2 = var2()
      17 [-]: GETIMPORT R3 12; var3 = _T["PodState"]["PlayTime"]
      18 [-]: SUB R1 R2 R3 ; var1 = var2 - var3
      19 [-]: LOADK R2 K13 ; var2 = 2.5
      20 [-]: JUMPIFNOTLT R2 R1 L8; goto L8 if var2 >= var918049
      21 [-]: GETIMPORT R2 14; var2 = _T["PodState"]["PendingAnimation"]
      22 [-]: FASTCALL1 64 R2 L2; 
      23 [-]: GETIMPORT R1 11; var1 = 0x7B998233
      24 [-]: CALL R1 2 2  ; var1 = var1(var2)
L 2:  25 [-]: JUMPIF R1 L8 ; goto L8 if var1
      26 [-]: GETIMPORT R1 14; var1 = _T["PodState"]["PendingAnimation"]
      27 [-]: GETIMPORT R2 15; var2 = _T["PodState"]["LastPlayed"]
      28 [-]: JUMPIFEQ R1 R2 L7; goto L7 if var1 == var1114401
      29 [-]: GETIMPORT R1 17; var1 = 0x89326C93
      30 [-]: GETIMPORT R3 19; var3 = 0x0469F296
      31 [-]: LOADK R4 K20 ; var4 = "OperatorPod"
      32 [-]: CALL R3 2 0  ; var3, ... = var3(var4)
      33 [-]: NAMECALL R1 R1 K21; var2 = var1; var1 = var1[0x46A0EBF5]
      34 [-]: CALL R1 0 2  ; var1 = var1(var2, ...)
      35 [-]: FASTCALL1 64 R1 L3; 
      36 [-]: MOVE R3 R1   ; var3 = var1
      37 [-]: GETIMPORT R2 11; var2 = 0x7B998233
      38 [-]: CALL R2 2 2  ; var2 = var2(var3)
L 3:  39 [-]: JUMPIF R2 L6 ; goto L6 if var2
      40 [-]: LOADN R2 -1  ; var2 = -1
      41 [-]: GETIMPORT R4 23; var4 = _T["PodState"]["RateOverride"]
      42 [-]: FASTCALL1 64 R4 L4; 
      43 [-]: GETIMPORT R3 11; var3 = 0x7B998233
      44 [-]: CALL R3 2 2  ; var3 = var3(var4)
L 4:  45 [-]: JUMPIF R3 L5 ; goto L5 if var3
      46 [-]: GETIMPORT R2 23; var2 = _T["PodState"]["RateOverride"]
      47 [-]: GETIMPORT R3 9; var3 = _T["PodState"]
      48 [-]: LOADN R4 -1  ; var4 = -1
      49 [-]: SETTABLEKS R4 R3 K22; var4["RateOverride"] = var3
L 5:  50 [-]: GETIMPORT R5 14; var5 = _T["PodState"]["PendingAnimation"]
      51 [-]: LOADB R6 0   ; var6 = false
      52 [-]: LOADB R7 0   ; var7 = false
      53 [-]: LOADN R8 0   ; var8 = 0
      54 [-]: GETIMPORT R9 19; var9 = 0x0469F296
      55 [-]: CALL R9 1 2  ; var9 = var9()
      56 [-]: MOVE R10 R2  ; var10 = var2
      57 [-]: NAMECALL R3 R1 K24; var4 = var1; var3 = var1[0x5D985C7E]
      58 [-]: CALL R3 8 1  ; var3(var4, var5, var6, var7, var8, var9, var10)
L 6:  59 [-]: GETIMPORT R2 9; var2 = _T["PodState"]
      60 [-]: GETIMPORT R3 7; var3 = 0x55156FF7
      61 [-]: CALL R3 1 2  ; var3 = var3()
      62 [-]: SETTABLEKS R3 R2 K2; var3["PlayTime"] = var2
      63 [-]: GETIMPORT R2 9; var2 = _T["PodState"]
      64 [-]: GETIMPORT R3 14; var3 = _T["PodState"]["PendingAnimation"]
      65 [-]: SETTABLEKS R3 R2 K4; var3["LastPlayed"] = var2
L 7:  66 [-]: GETIMPORT R1 9; var1 = _T["PodState"]
      67 [-]: LOADNIL R2   ; var2 = nil
      68 [-]: SETTABLEKS R2 R1 K3; var2["PendingAnimation"] = var1
L 8:  69 [-]: GETIMPORT R1 26; var1 = 0xCBD666E1
      70 [-]: LOADK R2 K27 ; var2 = 0.10000000149011612
      71 [-]: CALL R1 2 1  ; var1(var2)
      72 [-]: JUMPBACK L0  ; goto L0
      73 [-]: RETURN R0 0  ; 


; Name:            
; Defined at line: 192
; #Upvalues:       0
; #Parameters:     0
; Is_vararg:       0
; Max Stack Size:  4

       0 [-]: GETIMPORT R1 2; var1 = _T["BackgroundMovie"]
       1 [-]: FASTCALL1 64 R1 L0; 
       2 [-]: GETIMPORT R0 4; var0 = 0x7B998233
       3 [-]: CALL R0 2 2  ; var0 = var0(var1)
L 0:   4 [-]: JUMPIF R0 L1 ; goto L1 if var0
       5 [-]: GETIMPORT R0 2; var0 = _T["BackgroundMovie"]
       6 [-]: LOADK R2 K5  ; var2 = "OpenPod"
       7 [-]: LOADK R3 K6  ; var3 = ""
       8 [-]: NAMECALL R0 R0 K7; var1 = var0; var0 = var0[0xE4162EED]
       9 [-]: CALL R0 4 1  ; var0(var1, var2, var3)
L 1:  10 [-]: RETURN R0 0  ; 


; Name:            
; Defined at line: 198
; #Upvalues:       0
; #Parameters:     0
; Is_vararg:       0
; Max Stack Size:  4

       0 [-]: GETIMPORT R1 2; var1 = _T["BackgroundMovie"]
       1 [-]: FASTCALL1 64 R1 L0; 
       2 [-]: GETIMPORT R0 4; var0 = 0x7B998233
       3 [-]: CALL R0 2 2  ; var0 = var0(var1)
L 0:   4 [-]: JUMPIF R0 L1 ; goto L1 if var0
       5 [-]: GETIMPORT R0 2; var0 = _T["BackgroundMovie"]
       6 [-]: LOADK R2 K5  ; var2 = "ClosePod"
       7 [-]: LOADK R3 K6  ; var3 = ""
       8 [-]: NAMECALL R0 R0 K7; var1 = var0; var0 = var0[0xE4162EED]
       9 [-]: CALL R0 4 1  ; var0(var1, var2, var3)
L 1:  10 [-]: RETURN R0 0  ; 


; Name:            
; Defined at line: 204
; #Upvalues:       0
; #Parameters:     1
; Is_vararg:       0
; Max Stack Size:  7

       0 [-]: GETIMPORT R1 1; var1 = 0x89326C93
       1 [-]: NAMECALL R1 R1 K2; var2 = var1; var1 = var1[0xFB64E76C]
       2 [-]: CALL R1 2 2  ; var1 = var1(var2)
       3 [-]: NAMECALL R2 R1 K3; var3 = var1; var2 = var1[0xA534C3AC]
       4 [-]: CALL R2 2 2  ; var2 = var2(var3)
       5 [-]: FASTCALL1 64 R2 L0; 
       6 [-]: MOVE R4 R2   ; var4 = var2
       7 [-]: GETIMPORT R3 5; var3 = 0x7B998233
       8 [-]: CALL R3 2 2  ; var3 = var3(var4)
L 0:   9 [-]: JUMPIF R3 L1 ; goto L1 if var3
      10 [-]: GETIMPORT R5 7; var5 = gLotusOperatorAvatarType
      11 [-]: NAMECALL R3 R2 K8; var4 = var2; var3 = var2[0xF2DEAF69]
      12 [-]: CALL R3 3 2  ; var3 = var3(var4, var5)
      13 [-]: JUMPIF R3 L1 ; goto L1 if var3
      14 [-]: MOVE R5 R0   ; var5 = var0
      15 [-]: LOADB R6 1   ; var6 = true
      16 [-]: NAMECALL R3 R2 K9; var4 = var2; var3 = var2[0x768274D6]
      17 [-]: CALL R3 4 1  ; var3(var4, var5, var6)
L 1:  18 [-]: RETURN R0 0  ; 


; Name:            
; Defined at line: 212
; #Upvalues:       1
; #Parameters:     1
; Is_vararg:       0
; Max Stack Size:  15

       0 [-]: GETIMPORT R3 1; var3 = 0xF2174759
       1 [-]: LOADB R4 0   ; var4 = false
       2 [-]: LOADN R5 3   ; var5 = 3
       3 [-]: LOADN R6 1   ; var6 = 1
       4 [-]: LOADB R7 1   ; var7 = true
       5 [-]: NAMECALL R1 R0 K2; var2 = var0; var1 = var0[0x5D985C7E]
       6 [-]: CALL R1 7 1  ; var1(var2, var3, var4, var5, var6, var7)
       7 [-]: NAMECALL R1 R0 K3; var2 = var0; var1 = var0[0xD1586535]
       8 [-]: CALL R1 2 2  ; var1 = var1(var2)
       9 [-]: LOADN R2 0   ; var2 = 0
      10 [-]: GETIMPORT R3 5; var3 = 0xA421AF95
      11 [-]: LOADN R4 0   ; var4 = 0
      12 [-]: LOADN R5 0   ; var5 = 0
      13 [-]: LOADN R6 1   ; var6 = 1
      14 [-]: CALL R3 4 2  ; var3 = var3(var4, var5, var6)
      15 [-]: MULK R5 R3 K6; var5 = var3 * 1
      16 [-]: ADD R4 R1 R5 ; var4 = var1 + var5
L 0:  17 [-]: LOADN R5 1   ; var5 = 1
      18 [-]: JUMPIFNOTLT R2 R5 L2; goto L2 if var2 >= var526113
      19 [-]: GETIMPORT R7 8; var7 = 0x5DB3CE80
      20 [-]: MOVE R8 R1   ; var8 = var1
      21 [-]: MOVE R9 R4   ; var9 = var4
      22 [-]: LOADN R11 1  ; var11 = 1
      23 [-]: LOADN R14 1  ; var14 = 1
      24 [-]: SUB R13 R14 R2; var13 = var14 - var2
      25 [-]: FASTCALL2K 21 R13 K9 L1; 
      26 [-]: LOADK R14 K9 ; var14 = 2
      27 [-]: GETIMPORT R12 12; var12 = 0x5BCED4C4[0xA40531D8]
      28 [-]: CALL R12 3 2 ; var12 = var12(var13, var14)
L 1:  29 [-]: SUB R10 R11 R12; var10 = var11 - var12
      30 [-]: CALL R7 4 0  ; var7, ... = var7(var8, var9, var10)
      31 [-]: NAMECALL R5 R0 K13; var6 = var0; var5 = var0[0x589EF1C1]
      32 [-]: CALL R5 0 1  ; var5(var6, ...)
      33 [-]: GETIMPORT R5 15; var5 = 0x67652851
      34 [-]: CALL R5 1 2  ; var5 = var5()
      35 [-]: ADD R2 R2 R5 ; var2 = var2 + var5
      36 [-]: GETIMPORT R5 17; var5 = 0xCBD666E1
      37 [-]: LOADN R6 0   ; var6 = 0
      38 [-]: CALL R5 2 1  ; var5(var6)
      39 [-]: JUMPBACK L0  ; goto L0
L 2:  40 [-]: GETUPVAL R5 0; var5 = upvalues[0]
      41 [-]: JUMPIFNOT R5 L3; goto L3 if not var5
      42 [-]: NAMECALL R5 R0 K18; var6 = var0; var5 = var0[0xDE321E6F]
      43 [-]: CALL R5 2 2  ; var5 = var5(var6)
      44 [-]: LOADN R7 0   ; var7 = 0
      45 [-]: LOADN R8 2   ; var8 = 2
      46 [-]: NAMECALL R5 R5 K19; var6 = var5; var5 = var5[0x4703255B]
      47 [-]: CALL R5 4 1  ; var5(var6, var7, var8)
      48 [-]: JUMP L4      ; goto L4
L 3:  49 [-]: NAMECALL R5 R0 K18; var6 = var0; var5 = var0[0xDE321E6F]
      50 [-]: CALL R5 2 2  ; var5 = var5(var6)
      51 [-]: LOADN R7 1   ; var7 = 1
      52 [-]: LOADN R8 0   ; var8 = 0
      53 [-]: LOADN R9 2   ; var9 = 2
      54 [-]: NAMECALL R5 R5 K20; var6 = var5; var5 = var5[0xC69087F6]
      55 [-]: CALL R5 5 1  ; var5(var6, var7, var8, var9)
L 4:  56 [-]: LOADN R7 0   ; var7 = 0
      57 [-]: NAMECALL R5 R0 K21; var6 = var0; var5 = var0[0x2E9B92E3]
      58 [-]: CALL R5 3 1  ; var5(var6, var7)
      59 [-]: RETURN R0 0  ; 


; Name:            
; Defined at line: 233
; #Upvalues:       17
; #Parameters:     1
; Is_vararg:       0
; Max Stack Size:  10

       0 [-]: SETUPVAL R0 0; upvalues[0] = var0
       1 [-]: GETUPVAL R1 1; var1 = upvalues[1]
       2 [-]: GETUPVAL R3 2; var3 = upvalues[2]
       3 [-]: GETTABLEKS R2 R3 K0; var2 = var3["EXIT"]
       4 [-]: CALL R1 2 2  ; var1 = var1(var2)
       5 [-]: JUMPIFNOT R1 L0; goto L0 if not var1
       6 [-]: CLOSEUPVALS R0; 
       7 [-]: RETURN R0 0  ; 
L 0:   8 [-]: GETUPVAL R1 3; var1 = upvalues[3]
       9 [-]: JUMPXEQKB R1 0 L3 NOT; 
      10 [-]: GETIMPORT R2 3; var2 = _T["BackgroundMovie"]
      11 [-]: FASTCALL1 64 R2 L1; 
      12 [-]: GETIMPORT R1 5; var1 = 0x7B998233
      13 [-]: CALL R1 2 2  ; var1 = var1(var2)
L 1:  14 [-]: JUMPIF R1 L2 ; goto L2 if var1
      15 [-]: GETIMPORT R1 3; var1 = _T["BackgroundMovie"]
      16 [-]: LOADK R3 K6  ; var3 = "ShowBlockingMessage"
      17 [-]: LOADK R4 K7  ; var4 = "2"
      18 [-]: NAMECALL R1 R1 K8; var2 = var1; var1 = var1[0xE4162EED]
      19 [-]: CALL R1 4 1  ; var1(var2, var3, var4)
L 2:  20 [-]: GETIMPORT R1 10; var1 = 0x25D99D89
      21 [-]: LOADK R3 K11 ; var3 = "OnSaveLoadOutComplete"
      22 [-]: NAMECALL R1 R1 K12; var2 = var1; var1 = var1[0xB6E2AB0D]
      23 [-]: CALL R1 3 1  ; var1(var2, var3)
      24 [-]: CLOSEUPVALS R0; 
      25 [-]: RETURN R0 0  ; 
L 3:  26 [-]: GETUPVAL R1 4; var1 = upvalues[4]
      27 [-]: GETUPVAL R2 5; var2 = upvalues[5]
      28 [-]: JUMPIFEQ R1 R2 L4; goto L4 if var1 == var393788
      29 [-]: GETUPVAL R2 6; var2 = upvalues[6]
      30 [-]: GETTABLEKS R1 R2 K13; var1 = var2[0xCF1FCBA4]
      31 [-]: CALL R1 1 2  ; var1 = var1()
      32 [-]: JUMPIFNOT R1 L4; goto L4 if not var1
      33 [-]: LOADK R2 K14 ; var2 = "{\"loadout\":"
      34 [-]: GETIMPORT R5 16; var5 = 0xBE190284
      35 [-]: NAMECALL R5 R5 K17; var6 = var5; var5 = var5[0xE08C150E]
      36 [-]: CALL R5 2 2  ; var5 = var5(var6)
      37 [-]: MOVE R3 R5   ; var3 = var5
      38 [-]: LOADK R4 K18 ; var4 = "}"
      39 [-]: CONCAT R1 R2 R4; var1 = var2 .. var4
      40 [-]: GETIMPORT R2 16; var2 = 0xBE190284
      41 [-]: MOVE R4 R1   ; var4 = var1
      42 [-]: NAMECALL R2 R2 K19; var3 = var2; var2 = var2[0x83BFAED0]
      43 [-]: CALL R2 3 1  ; var2(var3, var4)
L 4:  44 [-]: JUMPXEQKS R0 K20 L5; 
      45 [-]: LOADB R0 0 +1; var0 = false
L 5:  46 [-]: LOADB R0 1   ; var0 = true
L 6:  47 [-]: LOADB R1 1   ; var1 = true
      48 [-]: SETUPVAL R1 7; upvalues[1] = var7
      49 [-]: NOT R1 R0    ; var1 = not var0
      50 [-]: SETUPVAL R1 8; upvalues[1] = var8
      51 [-]: GETIMPORT R1 22; var1 = 0xAE91E43B
      52 [-]: LOADB R3 1   ; var3 = true
      53 [-]: NAMECALL R1 R1 K23; var2 = var1; var1 = var1[0xBED40E9C]
      54 [-]: CALL R1 3 1  ; var1(var2, var3)
      55 [-]: GETUPVAL R2 9; var2 = upvalues[9]
      56 [-]: GETTABLEKS R1 R2 K24; var1 = var2[0x659D451F]
      57 [-]: GETIMPORT R2 26; var2 = 0xB607EFE1
      58 [-]: CALL R1 2 1  ; var1(var2)
      59 [-]: LOADB R1 1   ; var1 = true
      60 [-]: SETUPVAL R1 10; upvalues[1] = var10
      61 [-]: GETIMPORT R1 28; var1 = 0x25312C9B
      62 [-]: GETIMPORT R2 22; var2 = 0xAE91E43B
      63 [-]: LOADK R3 K29 ; var3 = "_root"
      64 [-]: LOADN R4 0   ; var4 = 0
      65 [-]: NEWTABLE R5 0 1; var5 = {}
      66 [-]: LOADN R6 10  ; var6 = 10
      67 [-]: SETLIST R5 R6 1 [1]; var5[1] = var6; var5[2] = var7; 
      68 [-]: NEWTABLE R6 0 1; var6 = {}
      69 [-]: LOADN R7 0   ; var7 = 0
      70 [-]: SETLIST R6 R7 1 [1]; var6[1] = var7; var6[2] = var8; 
      71 [-]: LOADK R7 K30 ; var7 = 0.55000001192092896
      72 [-]: LOADN R8 0   ; var8 = 0
      73 [-]: NEWCLOSURE R9 P0; 
      74 [-]: CAPTURE UPVAL U11; 
      75 [-]: CAPTURE UPVAL U12; 
      76 [-]: CAPTURE REF R0; 
      77 [-]: CAPTURE UPVAL U13; 
      78 [-]: CAPTURE UPVAL U14; 
      79 [-]: CALL R1 9 1  ; var1(var2, var3, var4, var5, var6, var7, var8, var9)
      80 [-]: GETUPVAL R1 15; var1 = upvalues[15]
      81 [-]: JUMPIFNOT R1 L9; goto L9 if not var1
      82 [-]: GETIMPORT R2 32; var2 = _T["operatorLeaveSeat"]
      83 [-]: FASTCALL1 64 R2 L7; 
      84 [-]: GETIMPORT R1 5; var1 = 0x7B998233
      85 [-]: CALL R1 2 2  ; var1 = var1(var2)
L 7:  86 [-]: JUMPIF R1 L8 ; goto L8 if var1
      87 [-]: GETIMPORT R1 32; var1 = _T["operatorLeaveSeat"]
      88 [-]: JUMPIFNOT R1 L12; goto L12 if not var1
L 8:  89 [-]: GETIMPORT R1 34; var1 = 0x89326C93
      90 [-]: NAMECALL R1 R1 K35; var2 = var1; var1 = var1[0x78298275]
      91 [-]: CALL R1 2 2  ; var1 = var1(var2)
      92 [-]: GETIMPORT R4 37; var4 = gLotusOperatorAvatarType
      93 [-]: NAMECALL R2 R1 K38; var3 = var1; var2 = var1[0xF2DEAF69]
      94 [-]: CALL R2 3 2  ; var2 = var2(var3, var4)
      95 [-]: JUMPIFNOT R2 L12; goto L12 if not var2
      96 [-]: GETIMPORT R4 40; var4 = 0x0469F296
      97 [-]: LOADK R5 K41 ; var5 = "OperatorLeaveChair"
      98 [-]: CALL R4 2 2  ; var4 = var4(var5)
      99 [-]: LOADB R5 0   ; var5 = false
     100 [-]: NAMECALL R2 R1 K42; var3 = var1; var2 = var1[0xD5F7912B]
     101 [-]: CALL R2 4 1  ; var2(var3, var4, var5)
     102 [-]: JUMP L12     ; goto L12
L 9: 103 [-]: GETIMPORT R1 34; var1 = 0x89326C93
     104 [-]: NAMECALL R1 R1 K35; var2 = var1; var1 = var1[0x78298275]
     105 [-]: CALL R1 2 2  ; var1 = var1(var2)
     106 [-]: GETIMPORT R4 37; var4 = gLotusOperatorAvatarType
     107 [-]: NAMECALL R2 R1 K38; var3 = var1; var2 = var1[0xF2DEAF69]
     108 [-]: CALL R2 3 2  ; var2 = var2(var3, var4)
     109 [-]: JUMPIFNOT R2 L12; goto L12 if not var2
     110 [-]: GETUPVAL R2 4; var2 = upvalues[4]
     111 [-]: JUMPIFNOT R2 L10; goto L10 if not var2
     112 [-]: NAMECALL R2 R1 K43; var3 = var1; var2 = var1[0xDE321E6F]
     113 [-]: CALL R2 2 2  ; var2 = var2(var3)
     114 [-]: LOADN R4 0   ; var4 = 0
     115 [-]: LOADN R5 2   ; var5 = 2
     116 [-]: NAMECALL R2 R2 K44; var3 = var2; var2 = var2[0x4703255B]
     117 [-]: CALL R2 4 1  ; var2(var3, var4, var5)
     118 [-]: JUMP L11     ; goto L11
L10: 119 [-]: NAMECALL R2 R1 K43; var3 = var1; var2 = var1[0xDE321E6F]
     120 [-]: CALL R2 2 2  ; var2 = var2(var3)
     121 [-]: LOADN R4 1   ; var4 = 1
     122 [-]: LOADN R5 0   ; var5 = 0
     123 [-]: LOADN R6 2   ; var6 = 2
     124 [-]: NAMECALL R2 R2 K45; var3 = var2; var2 = var2[0xC69087F6]
     125 [-]: CALL R2 5 1  ; var2(var3, var4, var5, var6)
L11: 126 [-]: LOADN R4 0   ; var4 = 0
     127 [-]: NAMECALL R2 R1 K46; var3 = var1; var2 = var1[0x2E9B92E3]
     128 [-]: CALL R2 3 1  ; var2(var3, var4)
L12: 129 [-]: GETIMPORT R2 48; var2 = 0xCB79539E
     130 [-]: FASTCALL1 64 R2 L13; 
     131 [-]: GETIMPORT R1 5; var1 = 0x7B998233
     132 [-]: CALL R1 2 2  ; var1 = var1(var2)
L13: 133 [-]: JUMPIF R1 L15; goto L15 if var1
     134 [-]: GETUPVAL R1 16; var1 = upvalues[16]
     135 [-]: JUMPIFNOT R1 L14; goto L14 if not var1
     136 [-]: GETIMPORT R1 48; var1 = 0xCB79539E
     137 [-]: GETIMPORT R3 40; var3 = 0x0469F296
     138 [-]: LOADK R4 K49 ; var4 = "IN_SHIP_VIEW_TIME"
     139 [-]: CALL R3 2 2  ; var3 = var3(var4)
     140 [-]: LOADK R5 K50 ; var5 = "OPERATOR_FOCUS_"
     141 [-]: GETUPVAL R6 16; var6 = upvalues[16]
     142 [-]: CONCAT R4 R5 R6; var4 = var5 .. var6
     143 [-]: NAMECALL R1 R1 K51; var2 = var1; var1 = var1[0xA9188A47]
     144 [-]: CALL R1 4 1  ; var1(var2, var3, var4)
     145 [-]: LOADNIL R1   ; var1 = nil
     146 [-]: SETUPVAL R1 16; upvalues[1] = var16
L14: 147 [-]: GETIMPORT R1 48; var1 = 0xCB79539E
     148 [-]: GETIMPORT R3 40; var3 = 0x0469F296
     149 [-]: LOADK R4 K49 ; var4 = "IN_SHIP_VIEW_TIME"
     150 [-]: CALL R3 2 2  ; var3 = var3(var4)
     151 [-]: LOADK R4 K52 ; var4 = "OPERATOR_FOCUS_MAIN"
     152 [-]: NAMECALL R1 R1 K51; var2 = var1; var1 = var1[0xA9188A47]
     153 [-]: CALL R1 4 1  ; var1(var2, var3, var4)
L15: 154 [-]: CLOSEUPVALS R0; 
     155 [-]: RETURN R0 0  ; 


; Name:            
; Defined at line: 322
; #Upvalues:       1
; #Parameters:     0
; Is_vararg:       0
; Max Stack Size:  1

       0 [-]: GETUPVAL R0 0; var0 = upvalues[0]
       1 [-]: CALL R0 1 1  ; var0()
       2 [-]: RETURN R0 0  ; 


; Name:            
; Defined at line: 326
; #Upvalues:       1
; #Parameters:     0
; Is_vararg:       0
; Max Stack Size:  3

       0 [-]: LOADB R0 0   ; var0 = false
       1 [-]: GETIMPORT R1 2; var1 = _T["BackgroundMovie"]
       2 [-]: JUMPXEQKNIL R1 L0; 
       3 [-]: GETIMPORT R1 4; var1 = _T["IsInScreenStack"]
       4 [-]: LOADK R2 K5  ; var2 = "ItemBrowsing"
       5 [-]: CALL R1 2 2  ; var1 = var1(var2)
       6 [-]: MOVE R0 R1   ; var0 = var1
L 0:   7 [-]: JUMPIFNOT R0 L1; goto L1 if not var0
       8 [-]: GETIMPORT R1 7; var1 = _T["GoToPreviousScreen"]
       9 [-]: CALL R1 1 1  ; var1()
      10 [-]: RETURN R0 0  ; 
L 1:  11 [-]: GETUPVAL R1 0; var1 = upvalues[0]
      12 [-]: CALL R1 1 1  ; var1()
      13 [-]: RETURN R0 0  ; 


; Name:            
; Defined at line: 338
; #Upvalues:       4
; #Parameters:     1
; Is_vararg:       0
; Max Stack Size:  10

       0 [-]: ORK R0 R0 K0 ; var0 = var0 or "CustomizeTenno"
       1 [-]: GETUPVAL R1 0; var1 = upvalues[0]
       2 [-]: GETUPVAL R3 1; var3 = upvalues[1]
       3 [-]: GETTABLEKS R2 R3 K1; var2 = var3["TENNO_CUST"]
       4 [-]: CALL R1 2 2  ; var1 = var1(var2)
       5 [-]: JUMPIFNOT R1 L0; goto L0 if not var1
       6 [-]: RETURN R0 0  ; 
L 0:   7 [-]: GETIMPORT R1 3; var1 = 0x7ED0A956
       8 [-]: LOADK R2 K4  ; var2 = "/Lotus/Types/Keys/WarWithinQuest/WarWithinQuestKeyChain"
       9 [-]: CALL R1 2 2  ; var1 = var1(var2)
      10 [-]: GETUPVAL R3 2; var3 = upvalues[2]
      11 [-]: GETTABLEKS R2 R3 K5; var2 = var3[0x52FB05B3]
      12 [-]: MOVE R3 R1   ; var3 = var1
      13 [-]: CALL R2 2 2  ; var2 = var2(var3)
      14 [-]: JUMPIFNOT R2 L3; goto L3 if not var2
      15 [-]: GETIMPORT R2 7; var2 = 0x89326C93
      16 [-]: NAMECALL R2 R2 K8; var3 = var2; var2 = var2[0x7C1A0374]
      17 [-]: CALL R2 2 2  ; var2 = var2(var3)
      18 [-]: LOADN R3 0   ; var3 = 0
L 1:  19 [-]: LOADK R4 K9  ; var4 = 0.5
      20 [-]: JUMPIFNOTLT R3 R4 L2; goto L2 if var3 >= var721953
      21 [-]: GETIMPORT R4 11; var4 = 0xCBD666E1
      22 [-]: LOADN R5 0   ; var5 = 0
      23 [-]: CALL R4 2 1  ; var4(var5)
      24 [-]: GETIMPORT R4 13; var4 = 0x67652851
      25 [-]: CALL R4 1 2  ; var4 = var4()
      26 [-]: ADD R3 R3 R4 ; var3 = var3 + var4
      27 [-]: GETIMPORT R6 15; var6 = 0x9BAFFFE3
      28 [-]: LOADN R7 0   ; var7 = 0
      29 [-]: LOADN R8 1   ; var8 = 1
           31 [-]: CALL R6 4 0  ; var6, ... = var6(var7, var8, var9)
      32 [-]: NAMECALL R4 R2 K16; var5 = var2; var4 = var2[0xB6DF3E50]
      33 [-]: CALL R4 0 1  ; var4(var5, ...)
      34 [-]: JUMPBACK L1  ; goto L1
L 2:  35 [-]: GETIMPORT R4 18; var4 = 0xAE91E43B
      36 [-]: LOADK R6 K19 ; var6 = "_root"
      37 [-]: LOADN R7 11  ; var7 = 11
      38 [-]: LOADB R8 0   ; var8 = false
      39 [-]: NAMECALL R4 R4 K20; var5 = var4; var4 = var4[0xAADE900E]
      40 [-]: CALL R4 5 1  ; var4(var5, var6, var7, var8)
L 3:  41 [-]: GETIMPORT R3 23; var3 = _T["ForceRestoreMiniMap"]
      42 [-]: FASTCALL1 64 R3 L4; 
      43 [-]: GETIMPORT R2 25; var2 = 0x7B998233
      44 [-]: CALL R2 2 2  ; var2 = var2(var3)
L 4:  45 [-]: JUMPIF R2 L5 ; goto L5 if var2
      46 [-]: GETIMPORT R2 23; var2 = _T["ForceRestoreMiniMap"]
      47 [-]: CALL R2 1 1  ; var2()
L 5:  48 [-]: GETIMPORT R2 27; var2 = _T["OpenScreen"]
      49 [-]: MOVE R3 R0   ; var3 = var0
      50 [-]: CALL R2 2 1  ; var2(var3)
      51 [-]: GETUPVAL R2 3; var2 = upvalues[3]
      52 [-]: LOADK R3 K28 ; var3 = "true"
      53 [-]: CALL R2 2 1  ; var2(var3)
      54 [-]: RETURN R0 0  ; 


; Name:            
; Defined at line: 364
; #Upvalues:       1
; #Parameters:     0
; Is_vararg:       0
; Max Stack Size:  1

       0 [-]: GETUPVAL R0 0; var0 = upvalues[0]
       1 [-]: CALL R0 1 1  ; var0()
       2 [-]: RETURN R0 0  ; 


; Name:            
; Defined at line: 368
; #Upvalues:       2
; #Parameters:     0
; Is_vararg:       0
; Max Stack Size:  2

       0 [-]: GETIMPORT R0 2; var0 = _T["mTrigger"]
       1 [-]: NAMECALL R0 R0 K3; var1 = var0; var0 = var0[0x02BB4FF1]
       2 [-]: CALL R0 2 2  ; var0 = var0(var1)
       3 [-]: SETUPVAL R0 0; upvalues[0] = var0
       4 [-]: GETUPVAL R0 0; var0 = upvalues[0]
       5 [-]: NAMECALL R0 R0 K4; var1 = var0; var0 = var0[0xD1586535]
       6 [-]: CALL R0 2 2  ; var0 = var0(var1)
       7 [-]: SETUPVAL R0 1; upvalues[0] = var1
       8 [-]: RETURN R0 0  ; 


; Name:            
; Defined at line: 373
; #Upvalues:       3
; #Parameters:     0
; Is_vararg:       0
; Max Stack Size:  3

       0 [-]: GETUPVAL R0 0; var0 = upvalues[0]
       1 [-]: JUMPXEQKNIL R0 L0; 
       2 [-]: GETUPVAL R0 1; var0 = upvalues[1]
       3 [-]: NEWCLOSURE R2 P0; 
       4 [-]: CAPTURE UPVAL U0; 
       5 [-]: CAPTURE UPVAL U2; 
       6 [-]: NAMECALL R0 R0 K0; var1 = var0; var0 = var0[0xEA061E98]
       7 [-]: CALL R0 3 1  ; var0(var1, var2)
       8 [-]: LOADNIL R0   ; var0 = nil
       9 [-]: SETUPVAL R0 0; upvalues[0] = var0
L 0:  10 [-]: RETURN R0 0  ; 


; Name:            
; Defined at line: 386
; #Upvalues:       4
; #Parameters:     1
; Is_vararg:       0
; Max Stack Size:  19

       0 [-]: JUMPXEQKNIL R0 L7; 
       1 [-]: GETTABLEKS R1 R0 K0; var1 = var0["mClipName"]
       2 [-]: JUMPXEQKNIL R1 L7; 
       3 [-]: LOADN R1 0   ; var1 = 0
       4 [-]: LOADN R2 0   ; var2 = 0
       5 [-]: GETUPVAL R3 0; var3 = upvalues[0]
       6 [-]: JUMPIFNOT R3 L0; goto L0 if not var3
       7 [-]: GETIMPORT R3 3; var3 = 0xAE91E43B
       8 [-]: NAMECALL R3 R3 K4; var4 = var3; var3 = var3[0x091C120E]
       9 [-]: CALL R3 2 2  ; var3 = var3(var4)
      10 [-]: MULK R1 R3 K1; var1 = var3 * 0.5
      11 [-]: GETIMPORT R3 3; var3 = 0xAE91E43B
      12 [-]: NAMECALL R3 R3 K5; var4 = var3; var3 = var3[0x2CC9D281]
      13 [-]: CALL R3 2 2  ; var3 = var3(var4)
      14 [-]: MULK R2 R3 K1; var2 = var3 * 0.5
      15 [-]: JUMP L1      ; goto L1
L 0:  16 [-]: GETUPVAL R3 1; var3 = upvalues[1]
      17 [-]: MOVE R5 R0   ; var5 = var0
      18 [-]: NAMECALL R3 R3 K6; var4 = var3; var3 = var3[0x67E369FA]
      19 [-]: CALL R3 3 2  ; var3 = var3(var4, var5)
      20 [-]: MOVE R1 R3   ; var1 = var3
      21 [-]: GETUPVAL R3 1; var3 = upvalues[1]
      22 [-]: MOVE R5 R0   ; var5 = var0
      23 [-]: NAMECALL R3 R3 K7; var4 = var3; var3 = var3[0x68E36B8D]
      24 [-]: CALL R3 3 2  ; var3 = var3(var4, var5)
      25 [-]: MOVE R2 R3   ; var2 = var3
L 1:  26 [-]: GETUPVAL R3 1; var3 = upvalues[1]
      27 [-]: NEWTABLE R5 0 2; var5 = {}
      28 [-]: LOADN R6 0   ; var6 = 0
      29 [-]: LOADN R7 1   ; var7 = 1
      30 [-]: SETLIST R5 R6 2 [1]; var5[1] = var6; var5[2] = var7; var5[3] = var8; 
      31 [-]: NEWTABLE R6 0 2; var6 = {}
      32 [-]: MOVE R7 R1   ; var7 = var1
      33 [-]: MOVE R8 R2   ; var8 = var2
      34 [-]: SETLIST R6 R7 2 [1]; var6[1] = var7; var6[2] = var8; var6[3] = var9; 
      35 [-]: NAMECALL R3 R3 K8; var4 = var3; var3 = var3[0x663039E9]
      36 [-]: CALL R3 4 3  ; var3, var4 = var3(var4, var5, var6)
      37 [-]: GETIMPORT R5 10; var5 = 0x25312C9B
      38 [-]: GETIMPORT R6 3; var6 = 0xAE91E43B
      39 [-]: GETTABLEKS R7 R0 K0; var7 = var0["mClipName"]
      40 [-]: LOADN R8 2   ; var8 = 2
      41 [-]: MOVE R9 R3   ; var9 = var3
      42 [-]: MOVE R10 R4  ; var10 = var4
      43 [-]: LOADK R11 K11; var11 = 0.30000001192092896
      44 [-]: CALL R5 7 1  ; var5(var6, var7, var8, var9, var10, var11)
      45 [-]: GETUPVAL R6 2; var6 = upvalues[2]
      46 [-]: GETTABLEKS R5 R6 K12; var5 = var6[0x06D055F9]
      47 [-]: GETUPVAL R6 0; var6 = upvalues[0]
      48 [-]: LOADN R7 0   ; var7 = 0
      49 [-]: LOADN R8 100 ; var8 = 100
      50 [-]: CALL R5 4 2  ; var5 = var5(var6, var7, var8)
      51 [-]: NEWTABLE R6 0 6; var6 = {}
      52 [-]: LOADK R7 K13 ; var7 = "Locked"
      53 [-]: LOADK R8 K14 ; var8 = "Name"
      54 [-]: LOADK R9 K15 ; var9 = "Icon"
      55 [-]: LOADK R10 K16; var10 = "Checkmark"
      56 [-]: LOADK R11 K17; var11 = "Points"
      57 [-]: LOADK R12 K18; var12 = "Status"
      58 [-]: SETLIST R6 R7 6 [1]; var6[1] = var7; var6[2] = var8; var6[3] = var9; var6[4] = var10; var6[5] = var11; var6[6] = var12; var6[7] = var13; 
      59 [-]: GETIMPORT R7 20; var7 = 0xC8802016
      60 [-]: MOVE R8 R6   ; var8 = var6
      61 [-]: CALL R7 2 4  ; var7, var8, var9 = var7(var8)
      62 [-]: FORGPREP_INEXT R7 L3; 
L 2:  63 [-]: GETIMPORT R12 10; var12 = 0x25312C9B
      64 [-]: GETIMPORT R13 3; var13 = 0xAE91E43B
      65 [-]: GETTABLEKS R15 R0 K0; var15 = var0["mClipName"]
      66 [-]: LOADK R16 K21; var16 = "."
      67 [-]: MOVE R17 R11 ; var17 = var11
      68 [-]: CONCAT R14 R15 R17; var14 = var15 .. var17
      69 [-]: LOADN R15 2  ; var15 = 2
      70 [-]: NEWTABLE R16 0 1; var16 = {}
      71 [-]: LOADN R17 10 ; var17 = 10
      72 [-]: SETLIST R16 R17 1 [1]; var16[1] = var17; var16[2] = var18; 
      73 [-]: NEWTABLE R17 0 1; var17 = {}
      74 [-]: MOVE R18 R5  ; var18 = var5
      75 [-]: SETLIST R17 R18 1 [1]; var17[1] = var18; var17[2] = var19; 
      76 [-]: LOADK R18 K22; var18 = 0.20000000298023224
      77 [-]: CALL R12 7 1 ; var12(var13, var14, var15, var16, var17, var18)
L 3:  78 [-]: FORGLOOP R7 L2 2 [inext]; 
      79 [-]: GETIMPORT R7 10; var7 = 0x25312C9B
      80 [-]: GETIMPORT R8 3; var8 = 0xAE91E43B
      81 [-]: GETTABLEKS R10 R0 K0; var10 = var0["mClipName"]
      82 [-]: LOADK R11 K23; var11 = ".Background.Image"
      83 [-]: CONCAT R9 R10 R11; var9 = var10 .. var11
      84 [-]: LOADN R10 2  ; var10 = 2
      85 [-]: NEWTABLE R11 0 1; var11 = {}
      86 [-]: LOADN R12 10 ; var12 = 10
      87 [-]: SETLIST R11 R12 1 [1]; var11[1] = var12; var11[2] = var13; 
      88 [-]: NEWTABLE R12 0 1; var12 = {}
      89 [-]: GETUPVAL R14 2; var14 = upvalues[2]
      90 [-]: GETTABLEKS R13 R14 K12; var13 = var14[0x06D055F9]
      91 [-]: GETUPVAL R14 0; var14 = upvalues[0]
      92 [-]: LOADN R15 0  ; var15 = 0
      93 [-]: LOADN R16 35 ; var16 = 35
      94 [-]: CALL R13 4 0 ; var13, ... = var13(var14, var15, var16)
      95 [-]: SETLIST R12 R13 -1 [1]; 
      96 [-]: LOADK R13 K22; var13 = 0.20000000298023224
      97 [-]: CALL R7 7 1  ; var7(var8, var9, var10, var11, var12, var13)
      98 [-]: LOADB R7 0   ; var7 = false
      99 [-]: GETUPVAL R8 3; var8 = upvalues[3]
     100 [-]: JUMPXEQKNIL R8 L5; 
     101 [-]: GETTABLEKS R8 R0 K24; var8 = var0["Id"]
     102 [-]: GETUPVAL R10 3; var10 = upvalues[3]
     103 [-]: GETTABLEKS R9 R10 K24; var9 = var10["Id"]
     104 [-]: JUMPIFEQ R8 R9 L4; goto L4 if var8 == var16779014
     105 [-]: LOADB R7 0 +1; var7 = false
L 4: 106 [-]: LOADB R7 1   ; var7 = true
L 5: 107 [-]: GETUPVAL R9 1; var9 = upvalues[1]
     108 [-]: GETTABLEKS R8 R9 K25; var8 = var9["UpdateFX"]
     109 [-]: MOVE R9 R0   ; var9 = var0
     110 [-]: MOVE R10 R7  ; var10 = var7
     111 [-]: JUMPIFNOT R10 L6; goto L6 if not var10
     112 [-]: GETUPVAL R11 0; var11 = upvalues[0]
     113 [-]: NOT R10 R11  ; var10 = not var11
L 6: 114 [-]: CALL R8 3 1  ; var8(var9, var10)
     115 [-]: JUMPIF R7 L7 ; goto L7 if var7
     116 [-]: GETUPVAL R9 1; var9 = upvalues[1]
     117 [-]: GETTABLEKS R8 R9 K25; var8 = var9["UpdateFX"]
     118 [-]: GETUPVAL R9 3; var9 = upvalues[3]
     119 [-]: GETUPVAL R11 0; var11 = upvalues[0]
     120 [-]: NOT R10 R11  ; var10 = not var11
     121 [-]: CALL R8 3 1  ; var8(var9, var10)
L 7: 122 [-]: RETURN R0 0  ; 


; Name:            
; Defined at line: 415
; #Upvalues:       13
; #Parameters:     2
; Is_vararg:       0
; Max Stack Size:  13

       0 [-]: GETUPVAL R3 0; var3 = upvalues[0]
       1 [-]: FASTCALL1 64 R3 L0; 
       2 [-]: GETIMPORT R2 1; var2 = 0x7B998233
       3 [-]: CALL R2 2 2  ; var2 = var2(var3)
L 0:   4 [-]: JUMPIF R2 L1 ; goto L1 if var2
       5 [-]: JUMPIFNOT R0 L2; goto L2 if not var0
       6 [-]: GETUPVAL R2 1; var2 = upvalues[1]
       7 [-]: GETUPVAL R4 2; var4 = upvalues[2]
       8 [-]: GETTABLEKS R3 R4 K2; var3 = var4["ZOOM"]
       9 [-]: GETTABLEKS R4 R1 K3; var4 = var1["Id"]
      10 [-]: CALL R2 3 2  ; var2 = var2(var3, var4)
      11 [-]: JUMPIFNOT R2 L2; goto L2 if not var2
L 1:  12 [-]: RETURN R0 0  ; 
L 2:  13 [-]: GETUPVAL R3 3; var3 = upvalues[3]
      14 [-]: FASTCALL1 64 R3 L3; 
      15 [-]: GETIMPORT R2 1; var2 = 0x7B998233
      16 [-]: CALL R2 2 2  ; var2 = var2(var3)
L 3:  17 [-]: JUMPIFNOT R2 L6; goto L6 if not var2
      18 [-]: GETIMPORT R3 6; var3 = _T["mTrigger"]
      19 [-]: FASTCALL1 64 R3 L4; 
      20 [-]: GETIMPORT R2 1; var2 = 0x7B998233
      21 [-]: CALL R2 2 2  ; var2 = var2(var3)
L 4:  22 [-]: JUMPIFNOT R2 L5; goto L5 if not var2
      23 [-]: GETIMPORT R2 8; var2 = 0x3D106989
      24 [-]: LOADK R3 K9  ; var3 = "ERROR: _T.mTrigger is null"
      25 [-]: CALL R2 2 1  ; var2(var3)
      26 [-]: JUMP L6      ; goto L6
L 5:  27 [-]: GETUPVAL R2 4; var2 = upvalues[4]
      28 [-]: CALL R2 1 1  ; var2()
L 6:  29 [-]: SETUPVAL R0 5; upvalues[0] = var5
      30 [-]: JUMPIFNOT R0 L7; goto L7 if not var0
      31 [-]: SETUPVAL R1 6; upvalues[1] = var6
      32 [-]: GETIMPORT R2 10; var2 = _T
      33 [-]: GETUPVAL R4 6; var4 = upvalues[6]
      34 [-]: GETTABLEKS R3 R4 K11; var3 = var4["Polarity"]
      35 [-]: SETTABLEKS R3 R2 K12; var3["PolarityTree"] = var2
      36 [-]: GETIMPORT R2 10; var2 = _T
      37 [-]: GETUPVAL R4 6; var4 = upvalues[6]
      38 [-]: GETTABLEKS R3 R4 K13; var3 = var4["Locked"]
      39 [-]: SETTABLEKS R3 R2 K14; var3["TreeLocked"] = var2
      40 [-]: GETIMPORT R2 16; var2 = 0xAE91E43B
      41 [-]: GETIMPORT R4 18; var4 = 0x5340B39E
      42 [-]: NAMECALL R2 R2 K19; var3 = var2; var2 = var2[0x1FD6ABD0]
      43 [-]: CALL R2 3 2  ; var2 = var2(var3, var4)
      44 [-]: SETUPVAL R2 7; upvalues[2] = var7
      45 [-]: GETUPVAL R2 0; var2 = upvalues[0]
      46 [-]: GETUPVAL R4 6; var4 = upvalues[6]
      47 [-]: LOADB R5 0   ; var5 = false
      48 [-]: NAMECALL R2 R2 K20; var3 = var2; var2 = var2[0x925DBCAD]
      49 [-]: CALL R2 4 1  ; var2(var3, var4, var5)
      50 [-]: JUMP L10     ; goto L10
L 7:  51 [-]: GETUPVAL R1 6; var1 = upvalues[6]
      52 [-]: GETUPVAL R2 0; var2 = upvalues[0]
      53 [-]: GETUPVAL R4 6; var4 = upvalues[6]
      54 [-]: GETUPVAL R7 6; var7 = upvalues[6]
      55 [-]: GETTABLEKS R6 R7 K3; var6 = var7["Id"]
      56 [-]: JUMPXEQKN R6 K21 L8 NOT; 
      57 [-]: LOADB R5 0 +1; var5 = false
L 8:  58 [-]: LOADB R5 1   ; var5 = true
L 9:  59 [-]: NAMECALL R2 R2 K20; var3 = var2; var2 = var2[0x925DBCAD]
      60 [-]: CALL R2 4 1  ; var2(var3, var4, var5)
L10:  61 [-]: NEWCLOSURE R2 P0; 
      62 [-]: CAPTURE UPVAL U5; 
      63 [-]: CAPTURE UPVAL U3; 
      64 [-]: GETIMPORT R3 23; var3 = 0x25312C9B
      65 [-]: GETIMPORT R4 16; var4 = 0xAE91E43B
      66 [-]: LOADK R5 K24 ; var5 = "_root"
      67 [-]: LOADN R6 2   ; var6 = 2
      68 [-]: NEWTABLE R7 0 2; var7 = {}
      69 [-]: LOADN R8 4   ; var8 = 4
      70 [-]: MOVE R9 R2   ; var9 = var2
      71 [-]: SETLIST R7 R8 2 [1]; var7[1] = var8; var7[2] = var9; var7[3] = var10; 
      72 [-]: NEWTABLE R8 0 2; var8 = {}
      73 [-]: GETUPVAL R10 8; var10 = upvalues[8]
      74 [-]: GETTABLEKS R9 R10 K25; var9 = var10[0x06D055F9]
      75 [-]: GETUPVAL R10 5; var10 = upvalues[5]
      76 [-]: LOADK R11 K26; var11 = -50000
      77 [-]: LOADN R12 0  ; var12 = 0
      78 [-]: CALL R9 4 2  ; var9 = var9(var10, var11, var12)
      79 [-]: LOADN R10 1  ; var10 = 1
      80 [-]: SETLIST R8 R9 2 [1]; var8[1] = var9; var8[2] = var10; var8[3] = var11; 
      81 [-]: LOADK R9 K27 ; var9 = 0.30000001192092896
      82 [-]: LOADN R10 0  ; var10 = 0
      83 [-]: NEWCLOSURE R11 P1; 
      84 [-]: CAPTURE UPVAL U9; 
      85 [-]: CAPTURE UPVAL U10; 
      86 [-]: CAPTURE UPVAL U11; 
      87 [-]: CALL R3 9 1  ; var3(var4, var5, var6, var7, var8, var9, var10, var11)
      88 [-]: JUMPXEQKNIL R1 L11; 
      89 [-]: GETUPVAL R3 12; var3 = upvalues[12]
      90 [-]: MOVE R4 R1   ; var4 = var1
      91 [-]: CALL R3 2 1  ; var3(var4)
L11:  92 [-]: RETURN R0 0  ; 


; Name:            
; Defined at line: 464
; #Upvalues:       1
; #Parameters:     1
; Is_vararg:       0
; Max Stack Size:  4

       0 [-]: FASTCALL1 64 R0 L0; 
       1 [-]: MOVE R2 R0   ; var2 = var0
       2 [-]: GETIMPORT R1 1; var1 = 0x7B998233
       3 [-]: CALL R1 2 2  ; var1 = var1(var2)
L 0:   4 [-]: JUMPIF R1 L2 ; goto L2 if var1
       5 [-]: GETTABLEKS R1 R0 K2; var1 = var0["mClipName"]
       6 [-]: JUMPXEQKNIL R1 L2; 
       7 [-]: GETIMPORT R2 4; var2 = 0x25D99D89
       8 [-]: FASTCALL1 64 R2 L1; 
       9 [-]: GETIMPORT R1 1; var1 = 0x7B998233
      10 [-]: CALL R1 2 2  ; var1 = var1(var2)
L 1:  11 [-]: JUMPIFNOT R1 L3; goto L3 if not var1
L 2:  12 [-]: RETURN R0 0  ; 
L 3:  13 [-]: GETIMPORT R1 4; var1 = 0x25D99D89
      14 [-]: GETTABLEKS R3 R0 K5; var3 = var0["Polarity"]
      15 [-]: NAMECALL R1 R1 K6; var2 = var1; var1 = var1[0xAD94D866]
      16 [-]: CALL R1 3 2  ; var1 = var1(var2, var3)
      17 [-]: SETTABLEKS R1 R0 K7; var1["XP"] = var0
      18 [-]: GETUPVAL R2 0; var2 = upvalues[0]
      19 [-]: GETTABLEKS R1 R2 K8; var1 = var2["UpdateFocusText"]
      20 [-]: MOVE R2 R0   ; var2 = var0
      21 [-]: CALL R1 2 1  ; var1(var2)
      22 [-]: RETURN R0 0  ; 


; Name:            
; Defined at line: 473
; #Upvalues:       2
; #Parameters:     0
; Is_vararg:       0
; Max Stack Size:  2

       0 [-]: GETUPVAL R0 0; var0 = upvalues[0]
       1 [-]: GETUPVAL R1 1; var1 = upvalues[1]
       2 [-]: CALL R0 2 1  ; var0(var1)
       3 [-]: RETURN R0 0  ; 


; Name:            
; Defined at line: 477
; #Upvalues:       4
; #Parameters:     1
; Is_vararg:       0
; Max Stack Size:  7

       0 [-]: GETUPVAL R1 0; var1 = upvalues[0]
       1 [-]: LOADB R2 0   ; var2 = false
       2 [-]: CALL R1 2 1  ; var1(var2)
       3 [-]: JUMPXEQKNIL R0 L1; 
       4 [-]: FASTCALL1 62 R0 L0; 
       5 [-]: MOVE R2 R0   ; var2 = var0
       6 [-]: GETIMPORT R1 1; var1 = 0x03F57322
       7 [-]: CALL R1 2 2  ; var1 = var1(var2)
L 0:   8 [-]: SETUPVAL R1 1; upvalues[1] = var1
       9 [-]: LOADB R1 1   ; var1 = true
      10 [-]: SETUPVAL R1 2; upvalues[1] = var2
L 1:  11 [-]: GETIMPORT R2 3; var2 = 0xCB79539E
      12 [-]: FASTCALL1 64 R2 L2; 
      13 [-]: GETIMPORT R1 5; var1 = 0x7B998233
      14 [-]: CALL R1 2 2  ; var1 = var1(var2)
L 2:  15 [-]: JUMPIF R1 L3 ; goto L3 if var1
      16 [-]: GETUPVAL R1 3; var1 = upvalues[3]
      17 [-]: JUMPIFNOT R1 L3; goto L3 if not var1
      18 [-]: GETIMPORT R1 3; var1 = 0xCB79539E
      19 [-]: GETIMPORT R3 7; var3 = 0x0469F296
      20 [-]: LOADK R4 K8  ; var4 = "IN_SHIP_VIEW_TIME"
      21 [-]: CALL R3 2 2  ; var3 = var3(var4)
      22 [-]: LOADK R5 K9  ; var5 = "OPERATOR_FOCUS_"
      23 [-]: GETUPVAL R6 3; var6 = upvalues[3]
      24 [-]: CONCAT R4 R5 R6; var4 = var5 .. var6
      25 [-]: NAMECALL R1 R1 K10; var2 = var1; var1 = var1[0xA9188A47]
      26 [-]: CALL R1 4 1  ; var1(var2, var3, var4)
      27 [-]: GETIMPORT R1 3; var1 = 0xCB79539E
      28 [-]: GETIMPORT R3 7; var3 = 0x0469F296
      29 [-]: LOADK R4 K8  ; var4 = "IN_SHIP_VIEW_TIME"
      30 [-]: CALL R3 2 2  ; var3 = var3(var4)
      31 [-]: LOADK R4 K11 ; var4 = "OPERATOR_FOCUS_MAIN"
      32 [-]: NAMECALL R1 R1 K12; var2 = var1; var1 = var1[0xA9136B2F]
      33 [-]: CALL R1 4 1  ; var1(var2, var3, var4)
      34 [-]: LOADNIL R1   ; var1 = nil
      35 [-]: SETUPVAL R1 3; upvalues[1] = var3
L 3:  36 [-]: RETURN R0 0  ; 


; Name:            
; Defined at line: 494
; #Upvalues:       4
; #Parameters:     1
; Is_vararg:       0
; Max Stack Size:  2

       0 [-]: SETUPVAL R0 0; upvalues[0] = var0
       1 [-]: GETUPVAL R1 1; var1 = upvalues[1]
       2 [-]: CALL R1 1 1  ; var1()
       3 [-]: GETUPVAL R1 2; var1 = upvalues[2]
       4 [-]: CALL R1 1 1  ; var1()
       5 [-]: GETUPVAL R1 3; var1 = upvalues[3]
       6 [-]: CALL R1 1 1  ; var1()
       7 [-]: RETURN R0 0  ; 


; Name:            
; Defined at line: 502
; #Upvalues:       3
; #Parameters:     0
; Is_vararg:       0
; Max Stack Size:  3

       0 [-]: GETIMPORT R0 2; var0 = _T["TennoWay_QueuedZoom"]
       1 [-]: JUMPXEQKNIL R0 L0; 
       2 [-]: GETIMPORT R0 2; var0 = _T["TennoWay_QueuedZoom"]
       3 [-]: SETUPVAL R0 0; upvalues[0] = var0
       4 [-]: GETUPVAL R0 1; var0 = upvalues[1]
       5 [-]: GETUPVAL R2 2; var2 = upvalues[2]
       6 [-]: GETTABLEKS R1 R2 K3; var1 = var2["TREE_SELECT"]
       7 [-]: CALL R0 2 1  ; var0(var1)
       8 [-]: GETIMPORT R0 4; var0 = _T
       9 [-]: LOADNIL R1   ; var1 = nil
      10 [-]: SETTABLEKS R1 R0 K1; var1["TennoWay_QueuedZoom"] = var0
L 0:  11 [-]: RETURN R0 0  ; 


; Name:            
; Defined at line: 510
; #Upvalues:       5
; #Parameters:     0
; Is_vararg:       0
; Max Stack Size:  4

       0 [-]: LOADB R0 1   ; var0 = true
       1 [-]: SETUPVAL R0 0; upvalues[0] = var0
       2 [-]: GETUPVAL R1 2; var1 = upvalues[2]
       3 [-]: GETTABLEKS R0 R1 K0; var0 = var1["TREE_SELECT"]
       4 [-]: SETUPVAL R0 1; upvalues[0] = var1
       5 [-]: GETIMPORT R1 3; var1 = _T["BackgroundMovie"]
       6 [-]: FASTCALL1 64 R1 L0; 
       7 [-]: GETIMPORT R0 5; var0 = 0x7B998233
       8 [-]: CALL R0 2 2  ; var0 = var0(var1)
L 0:   9 [-]: JUMPIF R0 L1 ; goto L1 if var0
      10 [-]: GETIMPORT R0 3; var0 = _T["BackgroundMovie"]
      11 [-]: LOADK R2 K6  ; var2 = "OpenPod"
      12 [-]: LOADK R3 K7  ; var3 = ""
      13 [-]: NAMECALL R0 R0 K8; var1 = var0; var0 = var0[0xE4162EED]
      14 [-]: CALL R0 4 1  ; var0(var1, var2, var3)
L 1:  15 [-]: GETUPVAL R0 3; var0 = upvalues[3]
      16 [-]: CALL R0 1 1  ; var0()
      17 [-]: GETUPVAL R0 4; var0 = upvalues[4]
      18 [-]: CALL R0 1 1  ; var0()
      19 [-]: RETURN R0 0  ; 


; Name:            
; Defined at line: 522
; #Upvalues:       7
; #Parameters:     0
; Is_vararg:       0
; Max Stack Size:  6

       0 [-]: NEWTABLE R0 0 0; var0 = {}
       1 [-]: DUPTABLE R3 3; 
       2 [-]: LOADK R4 K4  ; var4 = "/Lotus/Language/Menu/Exit"
       3 [-]: SETTABLEKS R4 R3 K0; var4["Label"] = var3
       4 [-]: NEWCLOSURE R4 P0; 
       5 [-]: CAPTURE UPVAL U0; 
       6 [-]: CAPTURE UPVAL U1; 
       7 [-]: CAPTURE UPVAL U2; 
       8 [-]: CAPTURE UPVAL U3; 
       9 [-]: CAPTURE UPVAL U4; 
      10 [-]: CAPTURE UPVAL U5; 
      11 [-]: CAPTURE UPVAL U6; 
      12 [-]: SETTABLEKS R4 R3 K1; var4["CallBack"] = var3
      13 [-]: LOADK R4 K5  ; var4 = "MENU_CANCEL"
      14 [-]: SETTABLEKS R4 R3 K2; var4["CallOut"] = var3
      15 [-]: FASTCALL2 52 R0 R3 L0; 
      16 [-]: MOVE R2 R0   ; var2 = var0
      17 [-]: GETIMPORT R1 8; var1 = 0x33BDD652[0x23D5322F]
      18 [-]: CALL R1 3 1  ; var1(var2, var3)
L 0:  19 [-]: GETIMPORT R2 11; var2 = _T["SetButtons"]
      20 [-]: FASTCALL1 64 R2 L1; 
      21 [-]: GETIMPORT R1 13; var1 = 0x7B998233
      22 [-]: CALL R1 2 2  ; var1 = var1(var2)
L 1:  23 [-]: JUMPIF R1 L2 ; goto L2 if var1
      24 [-]: GETIMPORT R1 11; var1 = _T["SetButtons"]
      25 [-]: GETIMPORT R2 15; var2 = 0xAE91E43B
      26 [-]: MOVE R3 R0   ; var3 = var0
      27 [-]: GETIMPORT R4 17; var4 = 0xCD0165A3
      28 [-]: LOADN R5 1   ; var5 = 1
      29 [-]: CALL R4 2 0  ; var4, ... = var4(var5)
      30 [-]: CALL R1 0 1  ; var1(var2, ...)
L 2:  31 [-]: RETURN R0 0  ; 


; Name:            
; Defined at line: 541
; #Upvalues:       4
; #Parameters:     6
; Is_vararg:       0
; Max Stack Size:  12

       0 [-]: GETUPVAL R7 0; var7 = upvalues[0]
       1 [-]: GETTABLEKS R6 R7 K0; var6 = var7[0xAE6791BA]
       2 [-]: GETIMPORT R7 2; var7 = 0xAE91E43B
       3 [-]: MOVE R8 R0   ; var8 = var0
       4 [-]: MOVE R9 R1   ; var9 = var1
       5 [-]: MOVE R10 R2  ; var10 = var2
       6 [-]: MOVE R11 R3  ; var11 = var3
       7 [-]: CALL R6 6 2  ; var6 = var6(var7, var8, var9, var10, var11)
       8 [-]: ORK R9 R4 K3 ; var9 = var4 or 200
       9 [-]: NAMECALL R7 R6 K4; var8 = var6; var7 = var6[0x8D77B2B2]
      10 [-]: CALL R7 3 1  ; var7(var8, var9)
      11 [-]: NEWCLOSURE R7 P0; 
      12 [-]: CAPTURE VAL R5; 
      13 [-]: CAPTURE UPVAL U1; 
      14 [-]: CAPTURE UPVAL U2; 
      15 [-]: CAPTURE UPVAL U3; 
      16 [-]: SETTABLEKS R7 R6 K5; var7["mOnFocusedCallback"] = var6
      17 [-]: NEWCLOSURE R7 P1; 
      18 [-]: CAPTURE VAL R5; 
      19 [-]: CAPTURE UPVAL U1; 
      20 [-]: CAPTURE UPVAL U2; 
      21 [-]: CAPTURE UPVAL U3; 
      22 [-]: SETTABLEKS R7 R6 K6; var7["mOnUnfocusedCallback"] = var6
      23 [-]: DUPCLOSURE R7 K7; 
      24 [-]: SETTABLEKS R7 R6 K8; var7["mOnPressedCallback"] = var6
      25 [-]: NEWCLOSURE R7 P3; 
      26 [-]: CAPTURE VAL R2; 
      27 [-]: SETTABLEKS R7 R6 K9; var7["mOnReleasedCallback"] = var6
      28 [-]: RETURN R6 1  ; 


; Name:            
; Defined at line: 573
; #Upvalues:       7
; #Parameters:     2
; Is_vararg:       0
; Max Stack Size:  5

       0 [-]: SETUPVAL R0 0; upvalues[0] = var0
       1 [-]: GETUPVAL R3 1; var3 = upvalues[1]
       2 [-]: GETTABLEKS R2 R3 K0; var2 = var3[0x659D451F]
       3 [-]: GETIMPORT R3 2; var3 = 0x7307292B
       4 [-]: CALL R2 2 1  ; var2(var3)
       5 [-]: GETUPVAL R2 2; var2 = upvalues[2]
       6 [-]: NEWCLOSURE R4 P0; 
       7 [-]: CAPTURE VAL R0; 
       8 [-]: CAPTURE UPVAL U3; 
       9 [-]: CAPTURE UPVAL U4; 
      10 [-]: CAPTURE UPVAL U1; 
      11 [-]: CAPTURE UPVAL U2; 
      12 [-]: CAPTURE VAL R1; 
      13 [-]: CAPTURE UPVAL U5; 
      14 [-]: NAMECALL R2 R2 K3; var3 = var2; var2 = var2[0xEA061E98]
      15 [-]: CALL R2 3 1  ; var2(var3, var4)
      16 [-]: GETUPVAL R3 0; var3 = upvalues[0]
      17 [-]: FASTCALL1 64 R3 L0; 
      18 [-]: GETIMPORT R2 5; var2 = 0x7B998233
      19 [-]: CALL R2 2 2  ; var2 = var2(var3)
L 0:  20 [-]: JUMPIF R2 L1 ; goto L1 if var2
      21 [-]: GETUPVAL R3 0; var3 = upvalues[0]
      22 [-]: GETTABLEKS R2 R3 K6; var2 = var3["Ability"]
      23 [-]: SETUPVAL R2 6; upvalues[2] = var6
L 1:  24 [-]: RETURN R0 0  ; 


; Name:            
; Defined at line: 612
; #Upvalues:       6
; #Parameters:     2
; Is_vararg:       0
; Max Stack Size:  9

       0 [-]: GETIMPORT R2 1; var2 = 0x3D106989
       1 [-]: LOADK R4 K2  ; var4 = "FocusAbilitySet(result="
       2 [-]: FASTCALL1 63 R0 L0; 
       3 [-]: MOVE R8 R0   ; var8 = var0
       4 [-]: GETIMPORT R7 4; var7 = 0x64FB1586
       5 [-]: CALL R7 2 2  ; var7 = var7(var8)
L 0:   6 [-]: MOVE R5 R7   ; var5 = var7
       7 [-]: LOADK R6 K5  ; var6 = ")"
       8 [-]: CONCAT R3 R4 R6; var3 = var4 .. var6
       9 [-]: CALL R2 2 1  ; var2(var3)
      10 [-]: GETIMPORT R3 8; var3 = _T["BackgroundMovie"]
      11 [-]: FASTCALL1 64 R3 L1; 
      12 [-]: GETIMPORT R2 10; var2 = 0x7B998233
      13 [-]: CALL R2 2 2  ; var2 = var2(var3)
L 1:  14 [-]: JUMPIF R2 L2 ; goto L2 if var2
      15 [-]: GETIMPORT R2 8; var2 = _T["BackgroundMovie"]
      16 [-]: LOADK R4 K11 ; var4 = "ShowBlockingMessage"
      17 [-]: LOADK R5 K12 ; var5 = "0"
      18 [-]: NAMECALL R2 R2 K13; var3 = var2; var2 = var2[0xE4162EED]
      19 [-]: CALL R2 4 1  ; var2(var3, var4, var5)
L 2:  20 [-]: JUMPIF R0 L3 ; goto L3 if var0
      21 [-]: RETURN R0 0  ; 
L 3:  22 [-]: GETUPVAL R2 0; var2 = upvalues[0]
      23 [-]: GETUPVAL R3 1; var3 = upvalues[1]
      24 [-]: CALL R2 2 1  ; var2(var3)
      25 [-]: GETUPVAL R3 2; var3 = upvalues[2]
      26 [-]: GETTABLEKS R2 R3 K14; var2 = var3[0x659D451F]
      27 [-]: GETIMPORT R3 16; var3 = 0x804E3E0A
      28 [-]: CALL R2 2 1  ; var2(var3)
      29 [-]: GETIMPORT R2 18; var2 = 0x25D99D89
      30 [-]: NAMECALL R2 R2 K19; var3 = var2; var2 = var2[0x25A6E75E]
      31 [-]: CALL R2 2 2  ; var2 = var2(var3)
      32 [-]: FASTCALL1 64 R2 L4; 
      33 [-]: MOVE R4 R2   ; var4 = var2
      34 [-]: GETIMPORT R3 10; var3 = 0x7B998233
      35 [-]: CALL R3 2 2  ; var3 = var3(var4)
L 4:  36 [-]: JUMPIF R3 L5 ; goto L5 if var3
      37 [-]: LOADN R5 0   ; var5 = 0
      38 [-]: LOADN R8 0   ; var8 = 0
      39 [-]: NAMECALL R6 R2 K20; var7 = var2; var6 = var2[0x4E457768]
      40 [-]: CALL R6 3 0  ; var6, ... = var6(var7, var8)
      41 [-]: NAMECALL R3 R2 K21; var4 = var2; var3 = var2[0x566259E1]
      42 [-]: CALL R3 0 2  ; var3 = var3(var4, ...)
      43 [-]: GETUPVAL R5 1; var5 = upvalues[1]
      44 [-]: GETTABLEKS R4 R5 K22; var4 = var5["Polarity"]
      45 [-]: SETTABLEKS R4 R3 K23; var4["mFocusSchool"] = var3
      46 [-]: LOADN R6 0   ; var6 = 0
      47 [-]: MOVE R7 R3   ; var7 = var3
      48 [-]: NAMECALL R4 R2 K24; var5 = var2; var4 = var2[0x6BEB8AE1]
      49 [-]: CALL R4 4 1  ; var4(var5, var6, var7)
      50 [-]: GETIMPORT R4 18; var4 = 0x25D99D89
      51 [-]: LOADN R6 0   ; var6 = 0
      52 [-]: MOVE R7 R3   ; var7 = var3
      53 [-]: NAMECALL R4 R4 K25; var5 = var4; var4 = var4[0x400B84A1]
      54 [-]: CALL R4 4 1  ; var4(var5, var6, var7)
      55 [-]: GETIMPORT R4 27; var4 = _T["InSimulacrum"]
      56 [-]: JUMPIFNOT R4 L5; goto L5 if not var4
      57 [-]: GETIMPORT R4 28; var4 = _T
      58 [-]: LOADB R5 1   ; var5 = true
      59 [-]: SETTABLEKS R5 R4 K29; var5["SimulacrumFocusSchoolChanged"] = var4
L 5:  60 [-]: GETUPVAL R4 3; var4 = upvalues[3]
      61 [-]: FASTCALL1 64 R4 L6; 
      62 [-]: GETIMPORT R3 10; var3 = 0x7B998233
      63 [-]: CALL R3 2 2  ; var3 = var3(var4)
L 6:  64 [-]: JUMPIF R3 L8 ; goto L8 if var3
      65 [-]: GETUPVAL R3 3; var3 = upvalues[3]
      66 [-]: LOADK R5 K30 ; var5 = "ActiveWayChanged"
      67 [-]: LOADK R6 K31 ; var6 = ""
      68 [-]: NAMECALL R3 R3 K13; var4 = var3; var3 = var3[0xE4162EED]
      69 [-]: CALL R3 4 1  ; var3(var4, var5, var6)
      70 [-]: GETUPVAL R4 4; var4 = upvalues[4]
      71 [-]: FASTCALL1 64 R4 L7; 
      72 [-]: GETIMPORT R3 10; var3 = 0x7B998233
      73 [-]: CALL R3 2 2  ; var3 = var3(var4)
L 7:  74 [-]: JUMPIF R3 L8 ; goto L8 if var3
      75 [-]: GETUPVAL R3 5; var3 = upvalues[5]
      76 [-]: GETUPVAL R4 4; var4 = upvalues[4]
      77 [-]: CALL R3 2 1  ; var3(var4)
L 8:  78 [-]: LOADNIL R3   ; var3 = nil
      79 [-]: SETUPVAL R3 1; upvalues[3] = var1
      80 [-]: RETURN R0 0  ; 


; Name:            
; Defined at line: 652
; #Upvalues:       2
; #Parameters:     1
; Is_vararg:       0
; Max Stack Size:  10

       0 [-]: GETUPVAL R1 0; var1 = upvalues[0]
       1 [-]: JUMPXEQKNIL R1 L0 NOT; 
       2 [-]: GETIMPORT R1 1; var1 = 0xAE91E43B
       3 [-]: MOVE R3 R0   ; var3 = var0
       4 [-]: LOADN R4 5   ; var4 = 5
       5 [-]: NAMECALL R1 R1 K2; var2 = var1; var1 = var1[0x91A24E4B]
       6 [-]: CALL R1 4 2  ; var1 = var1(var2, var3, var4)
       7 [-]: SETUPVAL R1 0; upvalues[1] = var0
L 0:   8 [-]: GETIMPORT R1 4; var1 = 0x25312C9B
       9 [-]: GETIMPORT R2 1; var2 = 0xAE91E43B
      10 [-]: MOVE R3 R0   ; var3 = var0
      11 [-]: LOADN R4 2   ; var4 = 2
      12 [-]: NEWTABLE R5 0 2; var5 = {}
      13 [-]: LOADN R6 5   ; var6 = 5
      14 [-]: LOADN R7 6   ; var7 = 6
      15 [-]: SETLIST R5 R6 2 [1]; var5[1] = var6; var5[2] = var7; var5[3] = var8; 
      16 [-]: NEWTABLE R6 0 2; var6 = {}
      17 [-]: GETUPVAL R8 0; var8 = upvalues[0]
      18 [-]: ADDK R7 R8 K5; var7 = var8 + 3
      19 [-]: GETUPVAL R9 0; var9 = upvalues[0]
      20 [-]: ADDK R8 R9 K5; var8 = var9 + 3
      21 [-]: SETLIST R6 R7 2 [1]; var6[1] = var7; var6[2] = var8; var6[3] = var9; 
      22 [-]: LOADK R7 K6  ; var7 = 0.34999999403953552
      23 [-]: LOADN R8 0   ; var8 = 0
      24 [-]: NEWCLOSURE R9 P0; 
      25 [-]: CAPTURE VAL R0; 
      26 [-]: CAPTURE UPVAL U0; 
      27 [-]: CAPTURE UPVAL U1; 
      28 [-]: CALL R1 9 1  ; var1(var2, var3, var4, var5, var6, var7, var8, var9)
      29 [-]: RETURN R0 0  ; 


; Name:            
; Defined at line: 663
; #Upvalues:       19
; #Parameters:     0
; Is_vararg:       0
; Max Stack Size:  6

       0 [-]: GETIMPORT R0 1; var0 = 0x3D106989
       1 [-]: LOADK R1 K2  ; var1 = "InitializeSettings()"
       2 [-]: CALL R0 2 1  ; var0(var1)
       3 [-]: GETIMPORT R0 4; var0 = 0x2D0FAD09
       4 [-]: LOADK R1 K5  ; var1 = "EE.Interface.Components.List"
       5 [-]: CALL R0 2 2  ; var0 = var0(var1)
       6 [-]: GETTABLEKS R1 R0 K6; var1 = var0[0x9383BC56]
       7 [-]: GETIMPORT R2 8; var2 = 0xAE91E43B
       8 [-]: LOADK R3 K9  ; var3 = "Way1"
       9 [-]: CALL R1 3 2  ; var1 = var1(var2, var3)
      10 [-]: SETUPVAL R1 0; upvalues[1] = var0
      11 [-]: GETUPVAL R1 0; var1 = upvalues[0]
      12 [-]: LOADK R3 K10 ; var3 = "MenuEntryPressed"
      13 [-]: LOADK R4 K11 ; var4 = "MenuEntryFocused"
      14 [-]: LOADK R5 K12 ; var5 = "MenuEntryUnfocused"
      15 [-]: NAMECALL R1 R1 K13; var2 = var1; var1 = var1[0x1E5B5CFE]
      16 [-]: CALL R1 5 1  ; var1(var2, var3, var4, var5)
      17 [-]: GETUPVAL R1 0; var1 = upvalues[0]
      18 [-]: LOADN R2 0   ; var2 = 0
      19 [-]: SETTABLEKS R2 R1 K14; var2["mForcedVerticalSeparation"] = var1
      20 [-]: GETUPVAL R1 0; var1 = upvalues[0]
      21 [-]: LOADN R2 300 ; var2 = 300
      22 [-]: SETTABLEKS R2 R1 K15; var2["mForcedHorizontalSeparation"] = var1
      23 [-]: GETUPVAL R1 0; var1 = upvalues[0]
      24 [-]: LOADK R2 K16 ; var2 = 0.25
      25 [-]: SETTABLEKS R2 R1 K17; var2["mElementTransitionTime"] = var1
      26 [-]: GETUPVAL R1 0; var1 = upvalues[0]
      27 [-]: LOADK R2 K18 ; var2 = 0.059999998658895493
      28 [-]: SETTABLEKS R2 R1 K19; var2["mElementDelayTime"] = var1
      29 [-]: GETUPVAL R1 0; var1 = upvalues[0]
      30 [-]: GETIMPORT R2 8; var2 = 0xAE91E43B
      31 [-]: LOADK R4 K20 ; var4 = "Way1.Name"
      32 [-]: LOADN R5 1   ; var5 = 1
      33 [-]: NAMECALL R2 R2 K21; var3 = var2; var2 = var2[0x91A24E4B]
      34 [-]: CALL R2 4 2  ; var2 = var2(var3, var4, var5)
      35 [-]: SETTABLEKS R2 R1 K22; var2["mInitalNameYPos"] = var1
      36 [-]: GETUPVAL R1 0; var1 = upvalues[0]
      37 [-]: DUPCLOSURE R2 K23; 
      38 [-]: SETTABLEKS R2 R1 K24; var2["Print"] = var1
      39 [-]: GETUPVAL R1 0; var1 = upvalues[0]
      40 [-]: DUPCLOSURE R2 K25; 
      41 [-]: SETTABLEKS R2 R1 K26; var2["CombineInterpolationVars"] = var1
      42 [-]: GETUPVAL R1 0; var1 = upvalues[0]
      43 [-]: NEWCLOSURE R2 P2; 
      44 [-]: CAPTURE UPVAL U1; 
      45 [-]: CAPTURE UPVAL U2; 
      46 [-]: CAPTURE UPVAL U3; 
      47 [-]: SETTABLEKS R2 R1 K27; var2["UpdateFocusText"] = var1
      48 [-]: GETUPVAL R1 0; var1 = upvalues[0]
      49 [-]: NEWCLOSURE R2 P3; 
      50 [-]: CAPTURE UPVAL U0; 
      51 [-]: CAPTURE UPVAL U4; 
      52 [-]: SETTABLEKS R2 R1 K28; var2["UpdateFX"] = var1
      53 [-]: GETUPVAL R1 0; var1 = upvalues[0]
      54 [-]: NEWCLOSURE R2 P4; 
      55 [-]: CAPTURE UPVAL U5; 
      56 [-]: CAPTURE UPVAL U6; 
      57 [-]: CAPTURE UPVAL U2; 
      58 [-]: CAPTURE UPVAL U4; 
      59 [-]: SETTABLEKS R2 R1 K29; var2["UpdateElementColor"] = var1
      60 [-]: GETUPVAL R1 0; var1 = upvalues[0]
      61 [-]: NEWCLOSURE R2 P5; 
      62 [-]: CAPTURE UPVAL U7; 
      63 [-]: CAPTURE UPVAL U2; 
      64 [-]: CAPTURE UPVAL U8; 
      65 [-]: CAPTURE UPVAL U6; 
      66 [-]: CAPTURE UPVAL U9; 
      67 [-]: CAPTURE UPVAL U5; 
      68 [-]: SETTABLEKS R2 R1 K30; var2["mOnFocusedCallback"] = var1
      69 [-]: GETUPVAL R1 0; var1 = upvalues[0]
      70 [-]: NEWCLOSURE R2 P6; 
      71 [-]: CAPTURE UPVAL U5; 
      72 [-]: CAPTURE UPVAL U2; 
      73 [-]: CAPTURE UPVAL U6; 
      74 [-]: CAPTURE UPVAL U10; 
      75 [-]: SETTABLEKS R2 R1 K31; var2["mOnUnfocusedCallback"] = var1
      76 [-]: GETUPVAL R1 0; var1 = upvalues[0]
      77 [-]: NEWCLOSURE R2 P7; 
      78 [-]: CAPTURE UPVAL U2; 
      79 [-]: CAPTURE UPVAL U11; 
      80 [-]: CAPTURE UPVAL U12; 
      81 [-]: CAPTURE UPVAL U13; 
      82 [-]: CAPTURE UPVAL U14; 
      83 [-]: CAPTURE UPVAL U15; 
      84 [-]: CAPTURE UPVAL U16; 
      85 [-]: SETTABLEKS R2 R1 K32; var2["mOnSelectedCallback"] = var1
      86 [-]: GETUPVAL R1 0; var1 = upvalues[0]
      87 [-]: NEWCLOSURE R2 P8; 
      88 [-]: CAPTURE UPVAL U0; 
      89 [-]: CAPTURE UPVAL U2; 
      90 [-]: CAPTURE UPVAL U11; 
      91 [-]: CAPTURE UPVAL U12; 
      92 [-]: CAPTURE UPVAL U17; 
      93 [-]: SETTABLEKS R2 R1 K33; var2["mElementDrawCallback"] = var1
      94 [-]: GETUPVAL R1 0; var1 = upvalues[0]
      95 [-]: NEWCLOSURE R2 P9; 
      96 [-]: CAPTURE UPVAL U5; 
      97 [-]: CAPTURE UPVAL U18; 
      98 [-]: SETTABLEKS R2 R1 K34; var2["CalculateX"] = var1
      99 [-]: GETUPVAL R1 0; var1 = upvalues[0]
     100 [-]: NEWCLOSURE R2 P10; 
     101 [-]: CAPTURE UPVAL U5; 
     102 [-]: CAPTURE UPVAL U18; 
     103 [-]: SETTABLEKS R2 R1 K35; var2["CalculateY"] = var1
     104 [-]: GETUPVAL R1 0; var1 = upvalues[0]
     105 [-]: DUPCLOSURE R2 K36; 
     106 [-]: SETTABLEKS R2 R1 K37; var2["SetupPreInterpolationValues"] = var1
     107 [-]: GETUPVAL R1 0; var1 = upvalues[0]
     108 [-]: DUPCLOSURE R2 K38; 
     109 [-]: SETTABLEKS R2 R1 K39; var2["GetInterpolationProperties"] = var1
     110 [-]: GETUPVAL R1 0; var1 = upvalues[0]
     111 [-]: DUPCLOSURE R2 K40; 
     112 [-]: SETTABLEKS R2 R1 K41; var2["SetDepthTesting"] = var1
     113 [-]: RETURN R0 0  ; 


; Name:            
; Defined at line: 960
; #Upvalues:       0
; #Parameters:     0
; Is_vararg:       0
; Max Stack Size:  18

       0 [-]: GETIMPORT R0 1; var0 = 0xAE91E43B
       1 [-]: NAMECALL R0 R0 K2; var1 = var0; var0 = var0[0x6B837788]
       2 [-]: CALL R0 2 2  ; var0 = var0(var1)
       3 [-]: GETIMPORT R1 1; var1 = 0xAE91E43B
       4 [-]: NAMECALL R1 R1 K3; var2 = var1; var1 = var1[0xAF9FDA9F]
       5 [-]: CALL R1 2 2  ; var1 = var1(var2)
       6 [-]: DIV R2 R0 R1 ; var2 = var0 / var1
       7 [-]: GETIMPORT R3 1; var3 = 0xAE91E43B
       8 [-]: NAMECALL R3 R3 K4; var4 = var3; var3 = var3[0x091C120E]
       9 [-]: CALL R3 2 2  ; var3 = var3(var4)
      10 [-]: GETIMPORT R4 1; var4 = 0xAE91E43B
      11 [-]: NAMECALL R4 R4 K5; var5 = var4; var4 = var4[0x2CC9D281]
      12 [-]: CALL R4 2 2  ; var4 = var4(var5)
      13 [-]: DIV R5 R3 R4 ; var5 = var3 / var4
      14 [-]: GETIMPORT R6 7; var6 = 0x3D106989
      15 [-]: LOADK R8 K8  ; var8 = "viewportRatio="
      16 [-]: MOVE R9 R2   ; var9 = var2
      17 [-]: CONCAT R7 R8 R9; var7 = var8 .. var9
      18 [-]: CALL R6 2 1  ; var6(var7)
      19 [-]: GETIMPORT R6 7; var6 = 0x3D106989
      20 [-]: LOADK R8 K9  ; var8 = "movieRatio="
      21 [-]: MOVE R9 R5   ; var9 = var5
      22 [-]: CONCAT R7 R8 R9; var7 = var8 .. var9
      23 [-]: CALL R6 2 1  ; var6(var7)
      24 [-]: MULK R6 R3 K10; var6 = var3 * 1.2999999523162842
      25 [-]: MULK R7 R4 K10; var7 = var4 * 1.2999999523162842
      26 [-]: JUMPIFNOTLT R5 R2 L0; goto L0 if var5 >= var84019227
      27 [-]: DIV R8 R2 R5 ; var8 = var2 / var5
      28 [-]: MUL R6 R6 R8 ; var6 = var6 * var8
      29 [-]: JUMP L1      ; goto L1
L 0:  30 [-]: DIV R8 R5 R2 ; var8 = var5 / var2
      31 [-]: MUL R7 R7 R8 ; var7 = var7 * var8
L 1:            34 [-]: GETIMPORT R10 1; var10 = 0xAE91E43B
      35 [-]: LOADK R12 K12; var12 = "Bg"
      36 [-]: LOADN R13 12 ; var13 = 12
      37 [-]: MOVE R14 R6  ; var14 = var6
      38 [-]: NAMECALL R10 R10 K13; var11 = var10; var10 = var10[0x67BC869F]
      39 [-]: CALL R10 5 1 ; var10(var11, var12, var13, var14)
      40 [-]: GETIMPORT R10 1; var10 = 0xAE91E43B
      41 [-]: LOADK R12 K12; var12 = "Bg"
      42 [-]: LOADN R13 13 ; var13 = 13
      43 [-]: MOVE R14 R7  ; var14 = var7
      44 [-]: NAMECALL R10 R10 K13; var11 = var10; var10 = var10[0x67BC869F]
      45 [-]: CALL R10 5 1 ; var10(var11, var12, var13, var14)
      46 [-]: GETIMPORT R10 1; var10 = 0xAE91E43B
      47 [-]: LOADK R12 K14; var12 = "Bg.Tile"
      48 [-]: LOADK R13 K15; var13 = "TileRepeats"
      49 [-]: MOVE R14 R8  ; var14 = var8
      50 [-]: MOVE R15 R9  ; var15 = var9
      51 [-]: LOADN R16 0  ; var16 = 0
      52 [-]: LOADN R17 0  ; var17 = 0
      53 [-]: NAMECALL R10 R10 K16; var11 = var10; var10 = var10[0x91E13703]
      54 [-]: CALL R10 8 1 ; var10(var11, var12, var13, var14, var15, var16, var17)
      55 [-]: RETURN R0 0  ; 


; Name:            
; Defined at line: 989
; #Upvalues:       2
; #Parameters:     0
; Is_vararg:       0
; Max Stack Size:  9

       0 [-]: GETIMPORT R0 1; var0 = 0xAE91E43B
       1 [-]: NAMECALL R0 R0 K2; var1 = var0; var0 = var0[0x6B837788]
       2 [-]: CALL R0 2 2  ; var0 = var0(var1)
       3 [-]: GETIMPORT R1 1; var1 = 0xAE91E43B
       4 [-]: NAMECALL R1 R1 K3; var2 = var1; var1 = var1[0xAF9FDA9F]
       5 [-]: CALL R1 2 2  ; var1 = var1(var2)
       6 [-]: GETIMPORT R2 1; var2 = 0xAE91E43B
       7 [-]: NAMECALL R2 R2 K4; var3 = var2; var2 = var2[0x091C120E]
       8 [-]: CALL R2 2 2  ; var2 = var2(var3)
       9 [-]: GETIMPORT R3 1; var3 = 0xAE91E43B
      10 [-]: NAMECALL R3 R3 K5; var4 = var3; var3 = var3[0x2CC9D281]
      11 [-]: CALL R3 2 2  ; var3 = var3(var4)
      12 [-]: GETIMPORT R4 8; var4 = 0x34291F5C[0x056BFE8B]
      13 [-]: CALL R4 1 2  ; var4 = var4()
      14 [-]: JUMPIF R4 L0 ; goto L0 if var4
      15 [-]: JUMPIFLT R1 R3 L0; goto L0 if var1 < var196672
      16 [-]: JUMPIFNOTLT R0 R2 L1; goto L1 if var0 >= var131118
L 0:  17 [-]: MOVE R0 R2   ; var0 = var2
      18 [-]: MOVE R1 R3   ; var1 = var3
L 1:  19 [-]: GETUPVAL R4 0; var4 = upvalues[0]
      20 [-]: CALL R4 1 1  ; var4()
      21 [-]: GETUPVAL R4 1; var4 = upvalues[1]
      22 [-]: JUMPXEQKNIL R4 L2; 
      23 [-]: GETUPVAL R4 1; var4 = upvalues[1]
      24 [-]: GETIMPORT R6 1; var6 = 0xAE91E43B
      25 [-]: NAMECALL R6 R6 K2; var7 = var6; var6 = var6[0x6B837788]
      26 [-]: CALL R6 2 2  ; var6 = var6(var7)
      27 [-]: GETIMPORT R7 1; var7 = 0xAE91E43B
      28 [-]: NAMECALL R7 R7 K3; var8 = var7; var7 = var7[0xAF9FDA9F]
      29 [-]: CALL R7 2 0  ; var7, ... = var7(var8)
      30 [-]: NAMECALL R4 R4 K9; var5 = var4; var4 = var4[0xFAA69527]
      31 [-]: CALL R4 0 1  ; var4(var5, ...)
L 2:  32 [-]: RETURN R0 0  ; 


; Name:            
; Defined at line: 1006
; #Upvalues:       12
; #Parameters:     0
; Is_vararg:       0
; Max Stack Size:  11

       0 [-]: GETUPVAL R0 0; var0 = upvalues[0]
       1 [-]: GETUPVAL R3 0; var3 = upvalues[0]
       2 [-]: GETTABLEKS R2 R3 K0; var2 = var3["UpdateFX"]
       3 [-]: NAMECALL R0 R0 K1; var1 = var0; var0 = var0[0xEA061E98]
       4 [-]: CALL R0 3 1  ; var0(var1, var2)
       5 [-]: GETUPVAL R0 0; var0 = upvalues[0]
       6 [-]: LOADB R2 1   ; var2 = true
       7 [-]: LOADB R3 1   ; var3 = true
       8 [-]: NAMECALL R0 R0 K2; var1 = var0; var0 = var0[0x7C09C373]
       9 [-]: CALL R0 4 1  ; var0(var1, var2, var3)
      10 [-]: GETUPVAL R0 1; var0 = upvalues[1]
      11 [-]: GETUPVAL R2 2; var2 = upvalues[2]
      12 [-]: GETTABLEKS R1 R2 K3; var1 = var2["MODE_SELECT"]
      13 [-]: JUMPIFNOTEQ R0 R1 L1; goto L1 if var0 ~= var327713
      14 [-]: GETIMPORT R0 5; var0 = 0x25D99D89
      15 [-]: NAMECALL R0 R0 K6; var1 = var0; var0 = var0[0xD8159207]
      16 [-]: CALL R0 2 2  ; var0 = var0(var1)
      17 [-]: LOADN R1 3   ; var1 = 3
      18 [-]: JUMPIFNOTLE R1 R0 L0; goto L0 if var1 > var316
      19 [-]: GETUPVAL R1 0; var1 = upvalues[0]
      20 [-]: DUPTABLE R3 10; 
      21 [-]: LOADK R4 K11 ; var4 = "/Lotus/Language/Menu/Operator_EquipmentButton"
      22 [-]: SETTABLEKS R4 R3 K7; var4["Name"] = var3
      23 [-]: GETIMPORT R5 13; var5 = 0x9FD00AF0
      24 [-]: GETTABLEN R4 R5 1; var4 = var5[1]
      25 [-]: SETTABLEKS R4 R3 K8; var4["Image"] = var3
      26 [-]: LOADB R4 1   ; var4 = true
      27 [-]: SETTABLEKS R4 R3 K9; var4["IsAmp"] = var3
      28 [-]: LOADB R4 1   ; var4 = true
      29 [-]: NAMECALL R1 R1 K14; var2 = var1; var1 = var1[0xBAD4316F]
      30 [-]: CALL R1 4 1  ; var1(var2, var3, var4)
L 0:  31 [-]: GETUPVAL R1 0; var1 = upvalues[0]
      32 [-]: DUPTABLE R3 16; 
      33 [-]: LOADK R4 K17 ; var4 = "/Lotus/Language/Menu/Focus"
      34 [-]: SETTABLEKS R4 R3 K7; var4["Name"] = var3
      35 [-]: GETIMPORT R5 13; var5 = 0x9FD00AF0
      36 [-]: GETTABLEN R4 R5 2; var4 = var5[2]
      37 [-]: SETTABLEKS R4 R3 K8; var4["Image"] = var3
      38 [-]: LOADB R4 1   ; var4 = true
      39 [-]: SETTABLEKS R4 R3 K15; var4["IsTree"] = var3
      40 [-]: LOADB R4 1   ; var4 = true
      41 [-]: NAMECALL R1 R1 K14; var2 = var1; var1 = var1[0xBAD4316F]
      42 [-]: CALL R1 4 1  ; var1(var2, var3, var4)
      43 [-]: GETUPVAL R1 0; var1 = upvalues[0]
      44 [-]: DUPTABLE R3 18; 
      45 [-]: LOADK R4 K19 ; var4 = "/Lotus/Language/Menu/Loadout_Options_Cosmetics"
      46 [-]: SETTABLEKS R4 R3 K7; var4["Name"] = var3
      47 [-]: GETIMPORT R5 13; var5 = 0x9FD00AF0
      48 [-]: GETTABLEN R4 R5 3; var4 = var5[3]
      49 [-]: SETTABLEKS R4 R3 K8; var4["Image"] = var3
      50 [-]: LOADB R4 1   ; var4 = true
      51 [-]: NAMECALL R1 R1 K14; var2 = var1; var1 = var1[0xBAD4316F]
      52 [-]: CALL R1 4 1  ; var1(var2, var3, var4)
      53 [-]: LOADNIL R1   ; var1 = nil
      54 [-]: SETUPVAL R1 3; upvalues[1] = var3
      55 [-]: JUMP L12     ; goto L12
L 1:  56 [-]: NEWTABLE R0 0 0; var0 = {}
      57 [-]: DUPTABLE R3 26; 
      58 [-]: LOADN R4 3   ; var4 = 3
      59 [-]: SETTABLEKS R4 R3 K20; var4["Polarity"] = var3
      60 [-]: GETUPVAL R5 4; var5 = upvalues[4]
      61 [-]: GETTABLEKS R4 R5 K27; var4 = var5["NARAMON"]
      62 [-]: SETTABLEKS R4 R3 K21; var4["Clan"] = var3
      63 [-]: LOADK R4 K28 ; var4 = "/Lotus/Language/TennoWay/Naramon"
      64 [-]: SETTABLEKS R4 R3 K7; var4["Name"] = var3
      65 [-]: LOADK R4 K29 ; var4 = "/Lotus/Language/TennoWay/NaramonDescription"
      66 [-]: SETTABLEKS R4 R3 K22; var4["Description"] = var3
      67 [-]: GETIMPORT R5 31; var5 = 0xCB00102D
      68 [-]: GETTABLEN R4 R5 1; var4 = var5[1]
      69 [-]: SETTABLEKS R4 R3 K23; var4["Ability"] = var3
      70 [-]: GETIMPORT R5 33; var5 = 0x520895D9
      71 [-]: GETTABLEN R4 R5 1; var4 = var5[1]
      72 [-]: SETTABLEKS R4 R3 K24; var4["Icon"] = var3
      73 [-]: GETIMPORT R5 35; var5 = 0xCC9CA930
      74 [-]: GETTABLEN R4 R5 1; var4 = var5[1]
      75 [-]: SETTABLEKS R4 R3 K8; var4["Image"] = var3
      76 [-]: DUPTABLE R4 45; 
      77 [-]: LOADN R5 0   ; var5 = 0
      78 [-]: SETTABLEKS R5 R4 K36; var5["X"] = var4
      79 [-]: LOADN R5 50  ; var5 = 50
      80 [-]: SETTABLEKS R5 R4 K37; var5["Y"] = var4
      81 [-]: LOADN R5 20  ; var5 = 20
      82 [-]: SETTABLEKS R5 R4 K38; var5["Rotation"] = var4
      83 [-]: LOADN R5 55  ; var5 = 55
      84 [-]: SETTABLEKS R5 R4 K39; var5["XScale"] = var4
      85 [-]: LOADN R5 55  ; var5 = 55
      86 [-]: SETTABLEKS R5 R4 K40; var5["YScale"] = var4
      87 [-]: LOADK R5 K46 ; var5 = 1.8999999761581421
      88 [-]: SETTABLEKS R5 R4 K41; var5["MaskScaleX"] = var4
      89 [-]: LOADK R5 K46 ; var5 = 1.8999999761581421
      90 [-]: SETTABLEKS R5 R4 K42; var5["MaskScaleY"] = var4
      91 [-]: LOADK R5 K47 ; var5 = -0.38999998569488525
      92 [-]: SETTABLEKS R5 R4 K43; var5["MaskOffsetX"] = var4
      93 [-]: LOADK R5 K48 ; var5 = -0.29499998688697815
      94 [-]: SETTABLEKS R5 R4 K44; var5["MaskOffsetY"] = var4
      95 [-]: SETTABLEKS R4 R3 K25; var4["IllustrationOffset"] = var3
      96 [-]: FASTCALL2 52 R0 R3 L2; 
      97 [-]: MOVE R2 R0   ; var2 = var0
      98 [-]: GETIMPORT R1 51; var1 = 0x33BDD652[0x23D5322F]
      99 [-]: CALL R1 3 1  ; var1(var2, var3)
L 2: 100 [-]: DUPTABLE R3 26; 
     101 [-]: LOADN R4 4   ; var4 = 4
     102 [-]: SETTABLEKS R4 R3 K20; var4["Polarity"] = var3
     103 [-]: GETUPVAL R5 4; var5 = upvalues[4]
     104 [-]: GETTABLEKS R4 R5 K52; var4 = var5["ZENURIK"]
     105 [-]: SETTABLEKS R4 R3 K21; var4["Clan"] = var3
     106 [-]: LOADK R4 K53 ; var4 = "/Lotus/Language/TennoWay/Zenurik"
     107 [-]: SETTABLEKS R4 R3 K7; var4["Name"] = var3
     108 [-]: LOADK R4 K54 ; var4 = "/Lotus/Language/TennoWay/ZenurikDescription"
     109 [-]: SETTABLEKS R4 R3 K22; var4["Description"] = var3
     110 [-]: GETIMPORT R5 31; var5 = 0xCB00102D
     111 [-]: GETTABLEN R4 R5 2; var4 = var5[2]
     112 [-]: SETTABLEKS R4 R3 K23; var4["Ability"] = var3
     113 [-]: GETIMPORT R5 33; var5 = 0x520895D9
     114 [-]: GETTABLEN R4 R5 2; var4 = var5[2]
     115 [-]: SETTABLEKS R4 R3 K24; var4["Icon"] = var3
     116 [-]: GETIMPORT R5 35; var5 = 0xCC9CA930
     117 [-]: GETTABLEN R4 R5 2; var4 = var5[2]
     118 [-]: SETTABLEKS R4 R3 K8; var4["Image"] = var3
     119 [-]: DUPTABLE R4 45; 
     120 [-]: LOADN R5 100 ; var5 = 100
     121 [-]: SETTABLEKS R5 R4 K36; var5["X"] = var4
     122 [-]: LOADN R5 70  ; var5 = 70
     123 [-]: SETTABLEKS R5 R4 K37; var5["Y"] = var4
     124 [-]: LOADN R5 -25 ; var5 = -25
     125 [-]: SETTABLEKS R5 R4 K38; var5["Rotation"] = var4
     126 [-]: LOADN R5 40  ; var5 = 40
     127 [-]: SETTABLEKS R5 R4 K39; var5["XScale"] = var4
     128 [-]: LOADN R5 40  ; var5 = 40
     129 [-]: SETTABLEKS R5 R4 K40; var5["YScale"] = var4
     130 [-]: LOADK R5 K55 ; var5 = 1.3500000238418579
     131 [-]: SETTABLEKS R5 R4 K41; var5["MaskScaleX"] = var4
     132 [-]: LOADK R5 K55 ; var5 = 1.3500000238418579
     133 [-]: SETTABLEKS R5 R4 K42; var5["MaskScaleY"] = var4
     134 [-]: LOADK R5 K56 ; var5 = 0.029999999329447746
     135 [-]: SETTABLEKS R5 R4 K43; var5["MaskOffsetX"] = var4
     136 [-]: LOADK R5 K57 ; var5 = 0.18500000238418579
     137 [-]: SETTABLEKS R5 R4 K44; var5["MaskOffsetY"] = var4
     138 [-]: SETTABLEKS R4 R3 K25; var4["IllustrationOffset"] = var3
     139 [-]: FASTCALL2 52 R0 R3 L3; 
     140 [-]: MOVE R2 R0   ; var2 = var0
     141 [-]: GETIMPORT R1 51; var1 = 0x33BDD652[0x23D5322F]
     142 [-]: CALL R1 3 1  ; var1(var2, var3)
L 3: 143 [-]: DUPTABLE R3 26; 
     144 [-]: LOADN R4 2   ; var4 = 2
     145 [-]: SETTABLEKS R4 R3 K20; var4["Polarity"] = var3
     146 [-]: GETUPVAL R5 4; var5 = upvalues[4]
     147 [-]: GETTABLEKS R4 R5 K58; var4 = var5["VAZARIN"]
     148 [-]: SETTABLEKS R4 R3 K21; var4["Clan"] = var3
     149 [-]: LOADK R4 K59 ; var4 = "/Lotus/Language/TennoWay/Vazarin"
     150 [-]: SETTABLEKS R4 R3 K7; var4["Name"] = var3
     151 [-]: LOADK R4 K60 ; var4 = "/Lotus/Language/TennoWay/VazarinDescription"
     152 [-]: SETTABLEKS R4 R3 K22; var4["Description"] = var3
     153 [-]: GETIMPORT R5 31; var5 = 0xCB00102D
     154 [-]: GETTABLEN R4 R5 3; var4 = var5[3]
     155 [-]: SETTABLEKS R4 R3 K23; var4["Ability"] = var3
     156 [-]: GETIMPORT R5 33; var5 = 0x520895D9
     157 [-]: GETTABLEN R4 R5 3; var4 = var5[3]
     158 [-]: SETTABLEKS R4 R3 K24; var4["Icon"] = var3
     159 [-]: GETIMPORT R5 35; var5 = 0xCC9CA930
     160 [-]: GETTABLEN R4 R5 3; var4 = var5[3]
     161 [-]: SETTABLEKS R4 R3 K8; var4["Image"] = var3
     162 [-]: DUPTABLE R4 45; 
     163 [-]: LOADN R5 13  ; var5 = 13
     164 [-]: SETTABLEKS R5 R4 K36; var5["X"] = var4
     165 [-]: LOADN R5 0   ; var5 = 0
     166 [-]: SETTABLEKS R5 R4 K37; var5["Y"] = var4
     167 [-]: LOADN R5 0   ; var5 = 0
     168 [-]: SETTABLEKS R5 R4 K38; var5["Rotation"] = var4
     169 [-]: LOADN R5 30  ; var5 = 30
     170 [-]: SETTABLEKS R5 R4 K39; var5["XScale"] = var4
     171 [-]: LOADN R5 30  ; var5 = 30
     172 [-]: SETTABLEKS R5 R4 K40; var5["YScale"] = var4
     173 [-]: LOADK R5 K61 ; var5 = 1.0499999523162842
     174 [-]: SETTABLEKS R5 R4 K41; var5["MaskScaleX"] = var4
     175 [-]: LOADN R5 1   ; var5 = 1
     176 [-]: SETTABLEKS R5 R4 K42; var5["MaskScaleY"] = var4
     177 [-]: LOADK R5 K62 ; var5 = 0.019999999552965164
     178 [-]: SETTABLEKS R5 R4 K43; var5["MaskOffsetX"] = var4
     179 [-]: LOADN R5 0   ; var5 = 0
     180 [-]: SETTABLEKS R5 R4 K44; var5["MaskOffsetY"] = var4
     181 [-]: SETTABLEKS R4 R3 K25; var4["IllustrationOffset"] = var3
     182 [-]: FASTCALL2 52 R0 R3 L4; 
     183 [-]: MOVE R2 R0   ; var2 = var0
     184 [-]: GETIMPORT R1 51; var1 = 0x33BDD652[0x23D5322F]
     185 [-]: CALL R1 3 1  ; var1(var2, var3)
L 4: 186 [-]: DUPTABLE R3 26; 
     187 [-]: LOADN R4 7   ; var4 = 7
     188 [-]: SETTABLEKS R4 R3 K20; var4["Polarity"] = var3
     189 [-]: GETUPVAL R5 4; var5 = upvalues[4]
     190 [-]: GETTABLEKS R4 R5 K63; var4 = var5["UNAIRU"]
     191 [-]: SETTABLEKS R4 R3 K21; var4["Clan"] = var3
     192 [-]: LOADK R4 K64 ; var4 = "/Lotus/Language/TennoWay/Unairu"
     193 [-]: SETTABLEKS R4 R3 K7; var4["Name"] = var3
     194 [-]: LOADK R4 K65 ; var4 = "/Lotus/Language/TennoWay/UnairuDescription"
     195 [-]: SETTABLEKS R4 R3 K22; var4["Description"] = var3
     196 [-]: GETIMPORT R5 31; var5 = 0xCB00102D
     197 [-]: GETTABLEN R4 R5 4; var4 = var5[4]
     198 [-]: SETTABLEKS R4 R3 K23; var4["Ability"] = var3
     199 [-]: GETIMPORT R5 33; var5 = 0x520895D9
     200 [-]: GETTABLEN R4 R5 4; var4 = var5[4]
     201 [-]: SETTABLEKS R4 R3 K24; var4["Icon"] = var3
     202 [-]: GETIMPORT R5 35; var5 = 0xCC9CA930
     203 [-]: GETTABLEN R4 R5 4; var4 = var5[4]
     204 [-]: SETTABLEKS R4 R3 K8; var4["Image"] = var3
     205 [-]: DUPTABLE R4 45; 
     206 [-]: LOADN R5 0   ; var5 = 0
     207 [-]: SETTABLEKS R5 R4 K36; var5["X"] = var4
     208 [-]: LOADN R5 90  ; var5 = 90
     209 [-]: SETTABLEKS R5 R4 K37; var5["Y"] = var4
     210 [-]: LOADN R5 0   ; var5 = 0
     211 [-]: SETTABLEKS R5 R4 K38; var5["Rotation"] = var4
     212 [-]: LOADN R5 45  ; var5 = 45
     213 [-]: SETTABLEKS R5 R4 K39; var5["XScale"] = var4
     214 [-]: LOADN R5 45  ; var5 = 45
     215 [-]: SETTABLEKS R5 R4 K40; var5["YScale"] = var4
     216 [-]: LOADK R5 K66 ; var5 = 1.5499999523162842
     217 [-]: SETTABLEKS R5 R4 K41; var5["MaskScaleX"] = var4
     218 [-]: LOADK R5 K66 ; var5 = 1.5499999523162842
     219 [-]: SETTABLEKS R5 R4 K42; var5["MaskScaleY"] = var4
     220 [-]: LOADK R5 K67 ; var5 = -0.2800000011920929
     221 [-]: SETTABLEKS R5 R4 K43; var5["MaskOffsetX"] = var4
     222 [-]: LOADK R5 K56 ; var5 = 0.029999999329447746
     223 [-]: SETTABLEKS R5 R4 K44; var5["MaskOffsetY"] = var4
     224 [-]: SETTABLEKS R4 R3 K25; var4["IllustrationOffset"] = var3
     225 [-]: FASTCALL2 52 R0 R3 L5; 
     226 [-]: MOVE R2 R0   ; var2 = var0
     227 [-]: GETIMPORT R1 51; var1 = 0x33BDD652[0x23D5322F]
     228 [-]: CALL R1 3 1  ; var1(var2, var3)
L 5: 229 [-]: DUPTABLE R3 26; 
     230 [-]: LOADN R4 1   ; var4 = 1
     231 [-]: SETTABLEKS R4 R3 K20; var4["Polarity"] = var3
     232 [-]: GETUPVAL R5 4; var5 = upvalues[4]
     233 [-]: GETTABLEKS R4 R5 K68; var4 = var5["MADURAI"]
     234 [-]: SETTABLEKS R4 R3 K21; var4["Clan"] = var3
     235 [-]: LOADK R4 K69 ; var4 = "/Lotus/Language/TennoWay/Madurai"
     236 [-]: SETTABLEKS R4 R3 K7; var4["Name"] = var3
     237 [-]: LOADK R4 K70 ; var4 = "/Lotus/Language/TennoWay/MaduraiDescription"
     238 [-]: SETTABLEKS R4 R3 K22; var4["Description"] = var3
     239 [-]: GETIMPORT R5 31; var5 = 0xCB00102D
     240 [-]: GETTABLEN R4 R5 5; var4 = var5[5]
     241 [-]: SETTABLEKS R4 R3 K23; var4["Ability"] = var3
     242 [-]: GETIMPORT R5 33; var5 = 0x520895D9
     243 [-]: GETTABLEN R4 R5 5; var4 = var5[5]
     244 [-]: SETTABLEKS R4 R3 K24; var4["Icon"] = var3
     245 [-]: GETIMPORT R5 35; var5 = 0xCC9CA930
     246 [-]: GETTABLEN R4 R5 5; var4 = var5[5]
     247 [-]: SETTABLEKS R4 R3 K8; var4["Image"] = var3
     248 [-]: DUPTABLE R4 45; 
     249 [-]: LOADN R5 -70 ; var5 = -70
     250 [-]: SETTABLEKS R5 R4 K36; var5["X"] = var4
     251 [-]: LOADN R5 80  ; var5 = 80
     252 [-]: SETTABLEKS R5 R4 K37; var5["Y"] = var4
     253 [-]: LOADN R5 -25 ; var5 = -25
     254 [-]: SETTABLEKS R5 R4 K38; var5["Rotation"] = var4
     255 [-]: LOADN R5 60  ; var5 = 60
     256 [-]: SETTABLEKS R5 R4 K39; var5["XScale"] = var4
     257 [-]: LOADN R5 60  ; var5 = 60
     258 [-]: SETTABLEKS R5 R4 K40; var5["YScale"] = var4
     259 [-]: LOADK R5 K71 ; var5 = 2.059999942779541
     260 [-]: SETTABLEKS R5 R4 K41; var5["MaskScaleX"] = var4
     261 [-]: LOADK R5 K71 ; var5 = 2.059999942779541
     262 [-]: SETTABLEKS R5 R4 K42; var5["MaskScaleY"] = var4
     263 [-]: LOADK R5 K72 ; var5 = -0.86000001430511475
     264 [-]: SETTABLEKS R5 R4 K43; var5["MaskOffsetX"] = var4
     265 [-]: LOADK R5 K73 ; var5 = -0.37999999523162842
     266 [-]: SETTABLEKS R5 R4 K44; var5["MaskOffsetY"] = var4
     267 [-]: SETTABLEKS R4 R3 K25; var4["IllustrationOffset"] = var3
     268 [-]: FASTCALL2 52 R0 R3 L6; 
     269 [-]: MOVE R2 R0   ; var2 = var0
     270 [-]: GETIMPORT R1 51; var1 = 0x33BDD652[0x23D5322F]
     271 [-]: CALL R1 3 1  ; var1(var2, var3)
L 6: 272 [-]: LOADN R3 1   ; var3 = 1
     273 [-]: LENGTH R1 R0 ; var1 = #var0
     274 [-]: LOADN R2 1   ; var2 = 1
     275 [-]: FORNPREP R1 L9; nforprep start - [escape at L9] -- var1 = iterator
L 7: 276 [-]: GETIMPORT R4 5; var4 = 0x25D99D89
     277 [-]: GETTABLE R7 R0 R3; var7 = var0[var3]
     278 [-]: GETTABLEKS R6 R7 K23; var6 = var7["Ability"]
     279 [-]: NAMECALL R4 R4 K74; var5 = var4; var4 = var4[0x9DE9471A]
     280 [-]: CALL R4 3 2  ; var4 = var4(var5, var6)
     281 [-]: GETTABLE R5 R0 R3; var5 = var0[var3]
     282 [-]: GETTABLEKS R7 R4 K75; var7 = var4["mItemType"]
     283 [-]: FASTCALL1 64 R7 L8; 
     284 [-]: GETIMPORT R6 77; var6 = 0x7B998233
     285 [-]: CALL R6 2 2  ; var6 = var6(var7)
L 8: 286 [-]: SETTABLEKS R6 R5 K78; var6["Locked"] = var5
     287 [-]: GETTABLE R5 R0 R3; var5 = var0[var3]
     288 [-]: GETIMPORT R6 5; var6 = 0x25D99D89
     289 [-]: GETTABLE R9 R0 R3; var9 = var0[var3]
     290 [-]: GETTABLEKS R8 R9 K20; var8 = var9["Polarity"]
     291 [-]: NAMECALL R6 R6 K79; var7 = var6; var6 = var6[0xAD94D866]
     292 [-]: CALL R6 3 2  ; var6 = var6(var7, var8)
     293 [-]: SETTABLEKS R6 R5 K80; var6["XP"] = var5
     294 [-]: GETTABLE R5 R0 R3; var5 = var0[var3]
     295 [-]: SETTABLEKS R3 R5 K81; var3["Id"] = var5
     296 [-]: GETUPVAL R5 0; var5 = upvalues[0]
     297 [-]: GETTABLE R7 R0 R3; var7 = var0[var3]
     298 [-]: LOADB R8 1   ; var8 = true
     299 [-]: NAMECALL R5 R5 K14; var6 = var5; var5 = var5[0xBAD4316F]
     300 [-]: CALL R5 4 1  ; var5(var6, var7, var8)
     301 [-]: FORNLOOP R1 L7; nforloop end - iterate + goto L7
L 9: 302 [-]: GETIMPORT R1 5; var1 = 0x25D99D89
     303 [-]: NAMECALL R1 R1 K82; var2 = var1; var1 = var1[0xA340C0E2]
     304 [-]: CALL R1 2 2  ; var1 = var1(var2)
     305 [-]: LOADN R4 1   ; var4 = 1
     306 [-]: LENGTH R2 R0 ; var2 = #var0
     307 [-]: LOADN R3 1   ; var3 = 1
     308 [-]: FORNPREP R2 L12; nforprep start - [escape at L12] -- var2 = iterator
L10: 309 [-]: GETTABLE R6 R0 R4; var6 = var0[var4]
     310 [-]: GETTABLEKS R5 R6 K23; var5 = var6["Ability"]
     311 [-]: JUMPIFNOTEQ R5 R1 L11; goto L11 if var5 ~= var67110173
     312 [-]: GETTABLE R5 R0 R4; var5 = var0[var4]
     313 [-]: SETUPVAL R5 3; upvalues[5] = var3
     314 [-]: JUMP L12     ; goto L12
L11: 315 [-]: FORNLOOP R2 L10; nforloop end - iterate + goto L10
L12: 316 [-]: GETIMPORT R0 84; var0 = 0x25312C9B
     317 [-]: GETIMPORT R1 86; var1 = 0xAE91E43B
     318 [-]: LOADK R2 K87 ; var2 = "Capacity"
     319 [-]: LOADN R3 8   ; var3 = 8
     320 [-]: NEWTABLE R4 0 1; var4 = {}
     321 [-]: LOADN R5 10  ; var5 = 10
     322 [-]: SETLIST R4 R5 1 [1]; var4[1] = var5; var4[2] = var6; 
     323 [-]: NEWTABLE R5 0 1; var5 = {}
     324 [-]: GETUPVAL R7 5; var7 = upvalues[5]
     325 [-]: GETTABLEKS R6 R7 K88; var6 = var7[0x06D055F9]
     326 [-]: GETUPVAL R8 1; var8 = upvalues[1]
     327 [-]: GETUPVAL R10 2; var10 = upvalues[2]
     328 [-]: GETTABLEKS R9 R10 K3; var9 = var10["MODE_SELECT"]
     329 [-]: JUMPIFEQ R8 R9 L13; goto L13 if var8 == var16779014
     330 [-]: LOADB R7 0 +1; var7 = false
L13: 331 [-]: LOADB R7 1   ; var7 = true
L14: 332 [-]: LOADN R8 0   ; var8 = 0
     333 [-]: LOADN R9 100 ; var9 = 100
     334 [-]: CALL R6 4 0  ; var6, ... = var6(var7, var8, var9)
     335 [-]: SETLIST R5 R6 -1 [1]; 
     336 [-]: LOADK R6 K89 ; var6 = 0.34999999403953552
     337 [-]: CALL R0 7 1  ; var0(var1, var2, var3, var4, var5, var6)
     338 [-]: GETUPVAL R1 6; var1 = upvalues[6]
     339 [-]: GETTABLEKS R0 R1 K90; var0 = var1["Visible"]
     340 [-]: JUMPIFNOT R0 L15; goto L15 if not var0
     341 [-]: GETUPVAL R1 6; var1 = upvalues[6]
     342 [-]: GETTABLEKS R0 R1 K91; var0 = var1["TransitionedIn"]
     343 [-]: JUMPIF R0 L15; goto L15 if var0
     344 [-]: GETUPVAL R0 6; var0 = upvalues[6]
     345 [-]: LOADB R1 1   ; var1 = true
     346 [-]: SETTABLEKS R1 R0 K91; var1["TransitionedIn"] = var0
     347 [-]: GETIMPORT R0 86; var0 = 0xAE91E43B
     348 [-]: LOADK R2 K92 ; var2 = "DrifterClick"
     349 [-]: LOADN R3 11  ; var3 = 11
     350 [-]: LOADB R4 1   ; var4 = true
     351 [-]: NAMECALL R0 R0 K93; var1 = var0; var0 = var0[0xAADE900E]
     352 [-]: CALL R0 5 1  ; var0(var1, var2, var3, var4)
     353 [-]: GETIMPORT R0 84; var0 = 0x25312C9B
     354 [-]: GETIMPORT R1 86; var1 = 0xAE91E43B
     355 [-]: LOADK R2 K92 ; var2 = "DrifterClick"
     356 [-]: LOADN R3 8   ; var3 = 8
     357 [-]: NEWTABLE R4 0 1; var4 = {}
     358 [-]: LOADN R5 10  ; var5 = 10
     359 [-]: SETLIST R4 R5 1 [1]; var4[1] = var5; var4[2] = var6; 
     360 [-]: NEWTABLE R5 0 1; var5 = {}
     361 [-]: LOADN R6 100 ; var6 = 100
     362 [-]: SETLIST R5 R6 1 [1]; var5[1] = var6; var5[2] = var7; 
     363 [-]: LOADK R6 K89 ; var6 = 0.34999999403953552
     364 [-]: LOADK R7 K94 ; var7 = 0.15000000596046448
     365 [-]: CALL R0 8 1  ; var0(var1, var2, var3, var4, var5, var6, var7)
L15: 366 [-]: GETUPVAL R0 0; var0 = upvalues[0]
     367 [-]: DUPCLOSURE R2 K95; 
     368 [-]: NAMECALL R0 R0 K96; var1 = var0; var0 = var0[0x71E9AC81]
     369 [-]: CALL R0 3 1  ; var0(var1, var2)
     370 [-]: GETUPVAL R0 7; var0 = upvalues[7]
     371 [-]: GETUPVAL R1 3; var1 = upvalues[3]
     372 [-]: LOADB R2 1   ; var2 = true
     373 [-]: CALL R0 3 1  ; var0(var1, var2)
     374 [-]: GETUPVAL R0 8; var0 = upvalues[8]
     375 [-]: JUMPXEQKNIL R0 L16; 
     376 [-]: GETUPVAL R0 9; var0 = upvalues[9]
     377 [-]: LOADK R2 K97 ; var2 = 0.75
     378 [-]: NEWCLOSURE R3 P1; 
     379 [-]: CAPTURE UPVAL U10; 
     380 [-]: CAPTURE UPVAL U11; 
     381 [-]: NAMECALL R0 R0 K98; var1 = var0; var0 = var0[0xBD2E96EA]
     382 [-]: CALL R0 4 1  ; var0(var1, var2, var3)
     383 [-]: RETURN R0 0  ; 
L16: 384 [-]: LOADB R0 0   ; var0 = false
     385 [-]: SETUPVAL R0 11; upvalues[0] = var11
     386 [-]: RETURN R0 0  ; 


; Name:            
; Defined at line: 1071
; #Upvalues:       3
; #Parameters:     0
; Is_vararg:       0
; Max Stack Size:  2

       0 [-]: GETUPVAL R0 0; var0 = upvalues[0]
       1 [-]: JUMPIFNOT R0 L0; goto L0 if not var0
       2 [-]: GETUPVAL R0 1; var0 = upvalues[1]
       3 [-]: LOADK R1 K0  ; var1 = 0.10000000149011612
       4 [-]: JUMPIFNOTLE R1 R0 L1; goto L1 if var1 > var131388
L 0:   5 [-]: GETUPVAL R1 2; var1 = upvalues[2]
       6 [-]: GETTABLEKS R0 R1 K1; var0 = var1[0x801EDC19]
       7 [-]: GETIMPORT R1 3; var1 = 0xAE91E43B
       8 [-]: CALL R0 2 1  ; var0(var1)
L 1:   9 [-]: RETURN R0 0  ; 


; Name:            
; Defined at line: 1077
; #Upvalues:       18
; #Parameters:     0
; Is_vararg:       0
; Max Stack Size:  12

       0 [-]: GETUPVAL R0 0; var0 = upvalues[0]
       1 [-]: JUMPIFNOT R0 L1; goto L1 if not var0
       2 [-]: GETIMPORT R1 1; var1 = 0xAE91E43B
       3 [-]: FASTCALL1 64 R1 L0; 
       4 [-]: GETIMPORT R0 3; var0 = 0x7B998233
       5 [-]: CALL R0 2 2  ; var0 = var0(var1)
L 0:   6 [-]: JUMPIFNOT R0 L2; goto L2 if not var0
L 1:   7 [-]: RETURN R0 0  ; 
L 2:   8 [-]: GETUPVAL R1 1; var1 = upvalues[1]
       9 [-]: FASTCALL1 64 R1 L3; 
      10 [-]: GETIMPORT R0 3; var0 = 0x7B998233
      11 [-]: CALL R0 2 2  ; var0 = var0(var1)
L 3:  12 [-]: JUMPIF R0 L4 ; goto L4 if var0
      13 [-]: GETUPVAL R0 1; var0 = upvalues[1]
      14 [-]: GETIMPORT R2 5; var2 = 0xB693B6C1
      15 [-]: CALL R2 1 0  ; var2, ... = var2()
      16 [-]: NAMECALL R0 R0 K6; var1 = var0; var0 = var0[0xFAA69527]
      17 [-]: CALL R0 0 1  ; var0(var1, ...)
L 4:  18 [-]: GETIMPORT R0 1; var0 = 0xAE91E43B
      19 [-]: GETIMPORT R2 5; var2 = 0xB693B6C1
      20 [-]: CALL R2 1 0  ; var2, ... = var2()
      21 [-]: NAMECALL R0 R0 K7; var1 = var0; var0 = var0[0x8A8C8D5A]
      22 [-]: CALL R0 0 1  ; var0(var1, ...)
      23 [-]: GETUPVAL R0 2; var0 = upvalues[2]
      24 [-]: JUMPIFNOT R0 L10; goto L10 if not var0
      25 [-]: GETUPVAL R0 3; var0 = upvalues[3]
      26 [-]: JUMPIF R0 L5 ; goto L5 if var0
      27 [-]: GETUPVAL R0 4; var0 = upvalues[4]
      28 [-]: CALL R0 1 1  ; var0()
      29 [-]: JUMP L10     ; goto L10
L 5:  30 [-]: GETIMPORT R1 10; var1 = _T["operatorLeaveSeat"]
      31 [-]: FASTCALL1 64 R1 L6; 
      32 [-]: GETIMPORT R0 3; var0 = 0x7B998233
      33 [-]: CALL R0 2 2  ; var0 = var0(var1)
L 6:  34 [-]: JUMPIF R0 L7 ; goto L7 if var0
      35 [-]: GETIMPORT R0 10; var0 = _T["operatorLeaveSeat"]
      36 [-]: JUMPIFNOT R0 L10; goto L10 if not var0
L 7:  37 [-]: GETIMPORT R1 12; var1 = _T["operatorClearLookAt"]
      38 [-]: FASTCALL1 64 R1 L8; 
      39 [-]: GETIMPORT R0 3; var0 = 0x7B998233
      40 [-]: CALL R0 2 2  ; var0 = var0(var1)
L 8:  41 [-]: JUMPIF R0 L9 ; goto L9 if var0
      42 [-]: GETIMPORT R0 12; var0 = _T["operatorClearLookAt"]
      43 [-]: JUMPIFNOT R0 L10; goto L10 if not var0
L 9:  44 [-]: GETUPVAL R1 5; var1 = upvalues[5]
      45 [-]: GETTABLEKS R0 R1 K13; var0 = var1[0xE2E728E1]
      46 [-]: CALL R0 1 1  ; var0()
L10:  47 [-]: GETUPVAL R1 6; var1 = upvalues[6]
      48 [-]: FASTCALL1 64 R1 L11; 
      49 [-]: GETIMPORT R0 3; var0 = 0x7B998233
      50 [-]: CALL R0 2 2  ; var0 = var0(var1)
L11:  51 [-]: JUMPIFNOT R0 L14; goto L14 if not var0
      52 [-]: GETIMPORT R1 15; var1 = _T["mTrigger"]
      53 [-]: FASTCALL1 64 R1 L12; 
      54 [-]: GETIMPORT R0 3; var0 = 0x7B998233
      55 [-]: CALL R0 2 2  ; var0 = var0(var1)
L12:  56 [-]: JUMPIFNOT R0 L13; goto L13 if not var0
      57 [-]: GETIMPORT R0 17; var0 = 0x3D106989
      58 [-]: LOADK R1 K18 ; var1 = "ERROR: Trigger isn't around"
      59 [-]: CALL R0 2 1  ; var0(var1)
      60 [-]: JUMP L16     ; goto L16
L13:  61 [-]: GETUPVAL R0 7; var0 = upvalues[7]
      62 [-]: CALL R0 1 1  ; var0()
      63 [-]: GETUPVAL R0 2; var0 = upvalues[2]
      64 [-]: JUMPIFNOT R0 L16; goto L16 if not var0
      65 [-]: GETUPVAL R1 8; var1 = upvalues[8]
      66 [-]: GETUPVAL R3 9; var3 = upvalues[9]
      67 [-]: GETTABLEKS R2 R3 K19; var2 = var3[0x06D055F9]
      68 [-]: GETUPVAL R3 10; var3 = upvalues[10]
      69 [-]: GETUPVAL R4 11; var4 = upvalues[11]
      70 [-]: GETIMPORT R5 21; var5 = ZERO_VECTOR
      71 [-]: CALL R2 4 2  ; var2 = var2(var3, var4, var5)
      72 [-]: ADD R0 R1 R2 ; var0 = var1 + var2
      73 [-]: GETUPVAL R1 6; var1 = upvalues[6]
      74 [-]: MOVE R3 R0   ; var3 = var0
      75 [-]: NAMECALL R1 R1 K22; var2 = var1; var1 = var1[0x9307AA51]
      76 [-]: CALL R1 3 1  ; var1(var2, var3)
      77 [-]: JUMP L16     ; goto L16
L14:  78 [-]: GETUPVAL R0 2; var0 = upvalues[2]
      79 [-]: JUMPIF R0 L16; goto L16 if var0
      80 [-]: GETUPVAL R0 3; var0 = upvalues[3]
      81 [-]: JUMPIF R0 L16; goto L16 if var0
      82 [-]: GETUPVAL R0 12; var0 = upvalues[12]
      83 [-]: JUMPIF R0 L16; goto L16 if var0
      84 [-]: GETIMPORT R0 24; var0 = 0x89326C93
      85 [-]: NAMECALL R0 R0 K25; var1 = var0; var0 = var0[0x78298275]
      86 [-]: CALL R0 2 2  ; var0 = var0(var1)
      87 [-]: FASTCALL1 64 R0 L15; 
      88 [-]: MOVE R2 R0   ; var2 = var0
      89 [-]: GETIMPORT R1 3; var1 = 0x7B998233
      90 [-]: CALL R1 2 2  ; var1 = var1(var2)
L15:  91 [-]: JUMPIF R1 L16; goto L16 if var1
      92 [-]: NAMECALL R1 R0 K26; var2 = var0; var1 = var0[0xD1586535]
      93 [-]: CALL R1 2 2  ; var1 = var1(var2)
      94 [-]: GETIMPORT R3 29; var3 = 0xF6C6E505
      95 [-]: NAMECALL R4 R0 K30; var5 = var0; var4 = var0[0x5280B883]
      96 [-]: CALL R4 2 0  ; var4, ... = var4(var5)
      97 [-]: CALL R3 0 2  ; var3 = var3(var4, ...)
      98 [-]: MULK R2 R3 K27; var2 = var3 * 0.69999998807907104
      99 [-]: GETUPVAL R4 9; var4 = upvalues[9]
     100 [-]: GETTABLEKS R3 R4 K19; var3 = var4[0x06D055F9]
     101 [-]: GETUPVAL R4 10; var4 = upvalues[10]
     102 [-]: LOADK R5 K31 ; var5 = 1.6000000238418579
     103 [-]: LOADK R6 K32 ; var6 = 1.3999999761581421
     104 [-]: CALL R3 4 2  ; var3 = var3(var4, var5, var6)
     105 [-]: SETTABLEKS R3 R2 K33; var3["y"] = var2
     106 [-]: ADD R4 R1 R2 ; var4 = var1 + var2
     107 [-]: GETIMPORT R5 35; var5 = 0x20B7F774
     108 [-]: MOVE R6 R4   ; var6 = var4
     109 [-]: GETIMPORT R8 37; var8 = 0xA421AF95
     110 [-]: LOADN R9 0   ; var9 = 0
     111 [-]: MOVE R10 R3  ; var10 = var3
     112 [-]: LOADN R11 0  ; var11 = 0
     113 [-]: CALL R8 4 2  ; var8 = var8(var9, var10, var11)
     114 [-]: ADD R7 R1 R8 ; var7 = var1 + var8
     115 [-]: CALL R5 3 2  ; var5 = var5(var6, var7)
     116 [-]: GETUPVAL R6 6; var6 = upvalues[6]
     117 [-]: MOVE R8 R4   ; var8 = var4
     118 [-]: NAMECALL R6 R6 K22; var7 = var6; var6 = var6[0x9307AA51]
     119 [-]: CALL R6 3 1  ; var6(var7, var8)
     120 [-]: GETUPVAL R6 6; var6 = upvalues[6]
     121 [-]: MOVE R8 R5   ; var8 = var5
     122 [-]: NAMECALL R6 R6 K38; var7 = var6; var6 = var6[0x70B8836C]
     123 [-]: CALL R6 3 1  ; var6(var7, var8)
     124 [-]: GETIMPORT R6 24; var6 = 0x89326C93
     125 [-]: NAMECALL R6 R6 K39; var7 = var6; var6 = var6[0x7C1A0374]
     126 [-]: CALL R6 2 2  ; var6 = var6(var7)
     127 [-]: LOADN R8 0   ; var8 = 0
     128 [-]: NAMECALL R6 R6 K40; var7 = var6; var6 = var6[0xB6DF3E50]
     129 [-]: CALL R6 3 1  ; var6(var7, var8)
L16: 130 [-]: GETUPVAL R0 13; var0 = upvalues[13]
     131 [-]: LOADK R1 K41 ; var1 = 0.10000000149011612
     132 [-]: JUMPIFNOTLE R0 R1 L25; goto L25 if var0 > var852284
     133 [-]: GETUPVAL R1 13; var1 = upvalues[13]
     134 [-]: GETIMPORT R2 43; var2 = 0x67652851
     135 [-]: CALL R2 1 2  ; var2 = var2()
     136 [-]: ADD R0 R1 R2 ; var0 = var1 + var2
     137 [-]: SETUPVAL R0 13; upvalues[0] = var13
     138 [-]: GETUPVAL R0 2; var0 = upvalues[2]
     139 [-]: JUMPIFNOT R0 L25; goto L25 if not var0
     140 [-]: GETUPVAL R0 14; var0 = upvalues[14]
     141 [-]: JUMPIF R0 L25; goto L25 if var0
     142 [-]: GETUPVAL R0 13; var0 = upvalues[13]
     143 [-]: LOADK R1 K41 ; var1 = 0.10000000149011612
     144 [-]: JUMPIFNOTLE R1 R0 L25; goto L25 if var1 > var1572897
     145 [-]: GETIMPORT R0 24; var0 = 0x89326C93
     146 [-]: NAMECALL R0 R0 K44; var1 = var0; var0 = var0[0xFB64E76C]
     147 [-]: CALL R0 2 2  ; var0 = var0(var1)
     148 [-]: NAMECALL R1 R0 K45; var2 = var0; var1 = var0[0x5578D98B]
     149 [-]: CALL R1 2 2  ; var1 = var1(var2)
     150 [-]: GETIMPORT R2 24; var2 = 0x89326C93
     151 [-]: NAMECALL R2 R2 K39; var3 = var2; var2 = var2[0x7C1A0374]
     152 [-]: CALL R2 2 2  ; var2 = var2(var3)
     153 [-]: FASTCALL1 64 R1 L17; 
     154 [-]: MOVE R4 R1   ; var4 = var1
     155 [-]: GETIMPORT R3 3; var3 = 0x7B998233
     156 [-]: CALL R3 2 2  ; var3 = var3(var4)
L17: 157 [-]: JUMPIF R3 L25; goto L25 if var3
     158 [-]: NAMECALL R3 R0 K46; var4 = var0; var3 = var0[0xBB610E5B]
     159 [-]: CALL R3 2 2  ; var3 = var3(var4)
     160 [-]: JUMPIFNOTEQ R3 R1 L25; goto L25 if var3 ~= var3146529
     161 [-]: GETIMPORT R3 48; var3 = _T["FocusManager_InstantMove"]
     162 [-]: JUMPIFNOT R3 L18; goto L18 if not var3
     163 [-]: NAMECALL R3 R1 K49; var4 = var1; var3 = var1[0xDE321E6F]
     164 [-]: CALL R3 2 2  ; var3 = var3(var4)
     165 [-]: LOADN R5 0   ; var5 = 0
     166 [-]: LOADN R6 0   ; var6 = 0
     167 [-]: LOADN R7 2   ; var7 = 2
     168 [-]: NAMECALL R3 R3 K50; var4 = var3; var3 = var3[0xC69087F6]
     169 [-]: CALL R3 5 1  ; var3(var4, var5, var6, var7)
     170 [-]: GETIMPORT R5 52; var5 = _T["defaultOperatorPos"]
     171 [-]: GETIMPORT R6 54; var6 = _T["defaultOperatorRot"]
     172 [-]: NAMECALL R3 R1 K55; var4 = var1; var3 = var1[0x589EF1C1]
     173 [-]: CALL R3 4 1  ; var3(var4, var5, var6)
     174 [-]: LOADB R5 1   ; var5 = true
     175 [-]: NAMECALL R3 R1 K56; var4 = var1; var3 = var1[0x2ABC8ECD]
     176 [-]: CALL R3 3 1  ; var3(var4, var5)
     177 [-]: LOADB R3 1   ; var3 = true
     178 [-]: SETUPVAL R3 14; upvalues[3] = var14
     179 [-]: JUMP L24     ; goto L24
L18: 180 [-]: LOADN R5 0   ; var5 = 0
     181 [-]: NAMECALL R3 R2 K40; var4 = var2; var3 = var2[0xB6DF3E50]
     182 [-]: CALL R3 3 1  ; var3(var4, var5)
     183 [-]: LOADN R3 0   ; var3 = 0
L19: 184 [-]: LOADK R4 K57 ; var4 = 1.5
     185 [-]: JUMPIFNOTLT R3 R4 L23; goto L23 if var3 >= var2819105
     186 [-]: GETIMPORT R4 43; var4 = 0x67652851
     187 [-]: CALL R4 1 2  ; var4 = var4()
     188 [-]: ADD R3 R3 R4 ; var3 = var3 + var4
     189 [-]: LOADK R4 K58 ; var4 = 0.75
     190 [-]: JUMPIFNOTLE R3 R4 L20; goto L20 if var3 > var973276753
          192 [-]: NAMECALL R4 R2 K40; var5 = var2; var4 = var2[0xB6DF3E50]
     193 [-]: CALL R4 3 1  ; var4(var5, var6)
     194 [-]: JUMP L21     ; goto L21
L20: 195 [-]: LOADN R7 1   ; var7 = 1
     196 [-]: SUBK R9 R3 K58; var9 = var3 - 0.75
          198 [-]: SUB R6 R7 R8 ; var6 = var7 - var8
     199 [-]: NAMECALL R4 R2 K40; var5 = var2; var4 = var2[0xB6DF3E50]
     200 [-]: CALL R4 3 1  ; var4(var5, var6)
L21: 201 [-]: GETUPVAL R4 14; var4 = upvalues[14]
     202 [-]: JUMPIF R4 L22; goto L22 if var4
     203 [-]: LOADK R4 K58 ; var4 = 0.75
     204 [-]: JUMPIFNOTLE R4 R3 L22; goto L22 if var4 > var1862337612
     205 [-]: NAMECALL R4 R1 K49; var5 = var1; var4 = var1[0xDE321E6F]
     206 [-]: CALL R4 2 2  ; var4 = var4(var5)
     207 [-]: LOADN R6 0   ; var6 = 0
     208 [-]: LOADN R7 0   ; var7 = 0
     209 [-]: LOADN R8 2   ; var8 = 2
     210 [-]: NAMECALL R4 R4 K50; var5 = var4; var4 = var4[0xC69087F6]
     211 [-]: CALL R4 5 1  ; var4(var5, var6, var7, var8)
     212 [-]: GETIMPORT R6 52; var6 = _T["defaultOperatorPos"]
     213 [-]: GETIMPORT R7 54; var7 = _T["defaultOperatorRot"]
     214 [-]: NAMECALL R4 R1 K55; var5 = var1; var4 = var1[0x589EF1C1]
     215 [-]: CALL R4 4 1  ; var4(var5, var6, var7)
     216 [-]: LOADB R6 1   ; var6 = true
     217 [-]: NAMECALL R4 R1 K56; var5 = var1; var4 = var1[0x2ABC8ECD]
     218 [-]: CALL R4 3 1  ; var4(var5, var6)
     219 [-]: LOADB R4 1   ; var4 = true
     220 [-]: SETUPVAL R4 14; upvalues[4] = var14
L22: 221 [-]: JUMPBACK L19 ; goto L19
L23: 222 [-]: LOADN R6 0   ; var6 = 0
     223 [-]: NAMECALL R4 R2 K40; var5 = var2; var4 = var2[0xB6DF3E50]
     224 [-]: CALL R4 3 1  ; var4(var5, var6)
L24: 225 [-]: GETIMPORT R3 59; var3 = _T
     226 [-]: LOADNIL R4   ; var4 = nil
     227 [-]: SETTABLEKS R4 R3 K47; var4["FocusManager_InstantMove"] = var3
L25: 228 [-]: GETUPVAL R1 15; var1 = upvalues[15]
     229 [-]: GETTABLEKS R0 R1 K60; var0 = var1["Dissolving"]
     230 [-]: JUMPIFNOT R0 L28; goto L28 if not var0
     231 [-]: GETUPVAL R0 15; var0 = upvalues[15]
     232 [-]: GETIMPORT R1 62; var1 = 0x42DCC9F5
     233 [-]: GETUPVAL R4 15; var4 = upvalues[15]
     234 [-]: GETTABLEKS R3 R4 K63; var3 = var4["DissolveVal"]
     235 [-]: GETIMPORT R6 43; var6 = 0x67652851
     236 [-]: CALL R6 1 2  ; var6 = var6()
     237 [-]: MULK R5 R6 K64; var5 = var6 * 4
     238 [-]: GETUPVAL R7 15; var7 = upvalues[15]
     239 [-]: GETTABLEKS R6 R7 K65; var6 = var7["DissolveDir"]
     240 [-]: MUL R4 R5 R6 ; var4 = var5 * var6
     241 [-]: ADD R2 R3 R4 ; var2 = var3 + var4
     242 [-]: LOADN R3 0   ; var3 = 0
     243 [-]: LOADN R4 1   ; var4 = 1
     244 [-]: CALL R1 4 2  ; var1 = var1(var2, var3, var4)
     245 [-]: SETTABLEKS R1 R0 K63; var1["DissolveVal"] = var0
     246 [-]: GETIMPORT R0 1; var0 = 0xAE91E43B
     247 [-]: GETUPVAL R3 15; var3 = upvalues[15]
     248 [-]: GETTABLEKS R2 R3 K63; var2 = var3["DissolveVal"]
     249 [-]: NAMECALL R0 R0 K66; var1 = var0; var0 = var0[0x58BEC6D6]
     250 [-]: CALL R0 3 1  ; var0(var1, var2)
     251 [-]: GETUPVAL R1 15; var1 = upvalues[15]
     252 [-]: GETTABLEKS R0 R1 K63; var0 = var1["DissolveVal"]
     253 [-]: JUMPXEQKN R0 K67 L26; 
     254 [-]: GETUPVAL R1 15; var1 = upvalues[15]
     255 [-]: GETTABLEKS R0 R1 K63; var0 = var1["DissolveVal"]
     256 [-]: JUMPXEQKN R0 K68 L28 NOT; 
L26: 257 [-]: GETUPVAL R0 15; var0 = upvalues[15]
     258 [-]: LOADB R1 0   ; var1 = false
     259 [-]: SETTABLEKS R1 R0 K60; var1["Dissolving"] = var0
     260 [-]: GETUPVAL R1 15; var1 = upvalues[15]
     261 [-]: GETTABLEKS R0 R1 K65; var0 = var1["DissolveDir"]
     262 [-]: JUMPXEQKN R0 K67 L27 NOT; 
     263 [-]: GETUPVAL R0 16; var0 = upvalues[16]
     264 [-]: CALL R0 1 1  ; var0()
     265 [-]: RETURN R0 0  ; 
L27: 266 [-]: LOADB R0 0   ; var0 = false
     267 [-]: SETUPVAL R0 17; upvalues[0] = var17
L28: 268 [-]: RETURN R0 0  ; 


; Name:            
; Defined at line: 1180
; #Upvalues:       2
; #Parameters:     0
; Is_vararg:       0
; Max Stack Size:  14

       0 [-]: GETIMPORT R0 1; var0 = 0xAE91E43B
       1 [-]: LOADK R2 K2  ; var2 = "PreviewNotice"
       2 [-]: LOADN R3 10  ; var3 = 10
       3 [-]: LOADN R4 0   ; var4 = 0
       4 [-]: NAMECALL R0 R0 K3; var1 = var0; var0 = var0[0x67BC869F]
       5 [-]: CALL R0 5 1  ; var0(var1, var2, var3, var4)
       6 [-]: GETIMPORT R0 1; var0 = 0xAE91E43B
       7 [-]: LOADK R2 K4  ; var2 = "PreviewNotice.Icon"
       8 [-]: GETIMPORT R3 6; var3 = 0xC81C25DA
       9 [-]: NAMECALL R0 R0 K7; var1 = var0; var0 = var0[0x1CB415C1]
      10 [-]: CALL R0 4 1  ; var0(var1, var2, var3)
      11 [-]: GETIMPORT R0 1; var0 = 0xAE91E43B
      12 [-]: LOADK R2 K2  ; var2 = "PreviewNotice"
      13 [-]: LOADN R3 0   ; var3 = 0
      14 [-]: NAMECALL R0 R0 K8; var1 = var0; var0 = var0[0x91A24E4B]
      15 [-]: CALL R0 4 2  ; var0 = var0(var1, var2, var3)
      16 [-]: GETIMPORT R1 1; var1 = 0xAE91E43B
      17 [-]: LOADK R3 K2  ; var3 = "PreviewNotice"
      18 [-]: LOADN R4 0   ; var4 = 0
      19 [-]: SUBK R5 R0 K9; var5 = var0 - 100
      20 [-]: NAMECALL R1 R1 K3; var2 = var1; var1 = var1[0x67BC869F]
      21 [-]: CALL R1 5 1  ; var1(var2, var3, var4, var5)
      22 [-]: GETIMPORT R1 1; var1 = 0xAE91E43B
      23 [-]: LOADK R3 K10 ; var3 = "PreviewNotice.FontHolder"
      24 [-]: LOADN R4 31  ; var4 = 31
      25 [-]: LOADK R5 K11 ; var5 = ""
      26 [-]: NAMECALL R1 R1 K12; var2 = var1; var1 = var1[0x5F56EEAB]
      27 [-]: CALL R1 5 1  ; var1(var2, var3, var4, var5)
      28 [-]: GETIMPORT R1 1; var1 = 0xAE91E43B
      29 [-]: LOADK R3 K13 ; var3 = "PreviewNotice.Content"
      30 [-]: LOADN R4 40  ; var4 = 40
      31 [-]: LOADK R5 K14 ; var5 = "center"
      32 [-]: NAMECALL R1 R1 K12; var2 = var1; var1 = var1[0x5F56EEAB]
      33 [-]: CALL R1 5 1  ; var1(var2, var3, var4, var5)
      34 [-]: GETIMPORT R1 16; var1 = 0x25D99D89
      35 [-]: NAMECALL R1 R1 K17; var2 = var1; var1 = var1[0xC712D7AD]
      36 [-]: CALL R1 2 2  ; var1 = var1(var2)
      37 [-]: GETIMPORT R2 1; var2 = 0xAE91E43B
      38 [-]: LOADK R4 K18 ; var4 = "/Lotus/Language/TennoWay/CapPreviewTitle"
      39 [-]: LOADB R5 1   ; var5 = true
      40 [-]: DUPTABLE R6 20; 
      41 [-]: GETUPVAL R8 0; var8 = upvalues[0]
      42 [-]: GETTABLEKS R7 R8 K21; var7 = var8[0x1142C7A8]
      43 [-]: MOVE R8 R1   ; var8 = var1
      44 [-]: CALL R7 2 2  ; var7 = var7(var8)
      45 [-]: SETTABLEKS R7 R6 K19; var7["CAP"] = var6
      46 [-]: NAMECALL R2 R2 K22; var3 = var2; var2 = var2[0x42B04007]
      47 [-]: CALL R2 5 2  ; var2 = var2(var3, var4, var5, var6)
      48 [-]: GETIMPORT R3 1; var3 = 0xAE91E43B
      49 [-]: LOADK R5 K23 ; var5 = "/Lotus/Language/TennoWay/CapPreviewMessage"
      50 [-]: LOADB R6 1   ; var6 = true
      51 [-]: NAMECALL R3 R3 K22; var4 = var3; var3 = var3[0x42B04007]
      52 [-]: CALL R3 4 2  ; var3 = var3(var4, var5, var6)
      53 [-]: LOADK R5 K24 ; var5 = "<p><font size=\"22\" color=\""
      54 [-]: GETUPVAL R10 1; var10 = upvalues[1]
      55 [-]: GETTABLEKS R6 R10 K25; var6 = var10["FloatingContentHex"]
      56 [-]: LOADK R7 K26 ; var7 = "\"><b>"
      57 [-]: MOVE R8 R2   ; var8 = var2
      58 [-]: LOADK R9 K27 ; var9 = "</b><br></font>"
      59 [-]: CONCAT R4 R5 R9; var4 = var5 .. var9
      60 [-]: MOVE R5 R4   ; var5 = var4
      61 [-]: LOADK R6 K28 ; var6 = "<font size=\"19\" color=\""
      62 [-]: GETUPVAL R11 1; var11 = upvalues[1]
      63 [-]: GETTABLEKS R7 R11 K29; var7 = var11["ContentHex"]
      64 [-]: LOADK R8 K30 ; var8 = "\">"
      65 [-]: MOVE R9 R3   ; var9 = var3
      66 [-]: LOADK R10 K31; var10 = "</font></p>"
      67 [-]: CONCAT R4 R5 R10; var4 = var5 .. var10
      68 [-]: GETIMPORT R5 1; var5 = 0xAE91E43B
      69 [-]: LOADK R7 K13 ; var7 = "PreviewNotice.Content"
      70 [-]: LOADN R8 31  ; var8 = 31
      71 [-]: MOVE R9 R4   ; var9 = var4
      72 [-]: NAMECALL R5 R5 K12; var6 = var5; var5 = var5[0x5F56EEAB]
      73 [-]: CALL R5 5 1  ; var5(var6, var7, var8, var9)
      74 [-]: GETIMPORT R5 33; var5 = 0x25312C9B
      75 [-]: GETIMPORT R6 1; var6 = 0xAE91E43B
      76 [-]: LOADK R7 K2  ; var7 = "PreviewNotice"
      77 [-]: LOADN R8 2   ; var8 = 2
      78 [-]: NEWTABLE R9 0 2; var9 = {}
      79 [-]: LOADN R10 10 ; var10 = 10
      80 [-]: LOADN R11 0  ; var11 = 0
      81 [-]: SETLIST R9 R10 2 [1]; var9[1] = var10; var9[2] = var11; var9[3] = var12; 
      82 [-]: NEWTABLE R10 0 2; var10 = {}
      83 [-]: LOADN R11 100; var11 = 100
      84 [-]: MOVE R12 R0  ; var12 = var0
      85 [-]: SETLIST R10 R11 2 [1]; var10[1] = var11; var10[2] = var12; var10[3] = var13; 
      86 [-]: LOADK R11 K34; var11 = 0.34999999403953552
      87 [-]: LOADK R12 K35; var12 = 1.25
      88 [-]: NEWCLOSURE R13 P0; 
      89 [-]: CAPTURE VAL R0; 
      90 [-]: CALL R5 9 1  ; var5(var6, var7, var8, var9, var10, var11, var12, var13)
      91 [-]: RETURN R0 0  ; 


; Name:            
; Defined at line: 1201
; #Upvalues:       8
; #Parameters:     0
; Is_vararg:       0
; Max Stack Size:  6

       0 [-]: GETUPVAL R1 0; var1 = upvalues[0]
       1 [-]: GETTABLEKS R0 R1 K0; var0 = var1["QueuedAction"]
       2 [-]: JUMPXEQKNIL R0 L0 NOT; 
       3 [-]: RETURN R0 0  ; 
L 0:   4 [-]: GETUPVAL R0 0; var0 = upvalues[0]
       5 [-]: LOADN R1 0   ; var1 = 0
       6 [-]: SETTABLEKS R1 R0 K1; var1["Focus"] = var0
       7 [-]: GETUPVAL R0 1; var0 = upvalues[1]
       8 [-]: GETUPVAL R1 2; var1 = upvalues[2]
       9 [-]: CALL R0 2 1  ; var0(var1)
      10 [-]: GETUPVAL R1 0; var1 = upvalues[0]
      11 [-]: GETTABLEKS R0 R1 K0; var0 = var1["QueuedAction"]
      12 [-]: GETUPVAL R2 3; var2 = upvalues[3]
      13 [-]: GETTABLEKS R1 R2 K2; var1 = var2["SET_PRIMARY"]
      14 [-]: JUMPIFNOTEQ R0 R1 L2; goto L2 if var0 ~= var262177
      15 [-]: GETIMPORT R0 4; var0 = 0xAE91E43B
      16 [-]: LOADK R2 K5  ; var2 = "SetAsPrimary"
      17 [-]: GETUPVAL R5 0; var5 = upvalues[0]
      18 [-]: GETTABLEKS R4 R5 K6; var4 = var5["QueuedId"]
      19 [-]: FASTCALL1 63 R4 L1; 
      20 [-]: GETIMPORT R3 8; var3 = 0x64FB1586
      21 [-]: CALL R3 2 2  ; var3 = var3(var4)
L 1:  22 [-]: NAMECALL R0 R0 K9; var1 = var0; var0 = var0[0xE4162EED]
      23 [-]: CALL R0 4 1  ; var0(var1, var2, var3)
      24 [-]: JUMP L6      ; goto L6
L 2:  25 [-]: GETUPVAL R1 0; var1 = upvalues[0]
      26 [-]: GETTABLEKS R0 R1 K0; var0 = var1["QueuedAction"]
      27 [-]: GETUPVAL R2 3; var2 = upvalues[3]
      28 [-]: GETTABLEKS R1 R2 K10; var1 = var2["ZOOM"]
      29 [-]: JUMPIFNOTEQ R0 R1 L4; goto L4 if var0 ~= var262204
      30 [-]: GETUPVAL R0 4; var0 = upvalues[4]
      31 [-]: GETUPVAL R3 0; var3 = upvalues[0]
      32 [-]: GETTABLEKS R2 R3 K6; var2 = var3["QueuedId"]
      33 [-]: NAMECALL R0 R0 K11; var1 = var0; var0 = var0[0xCA30DFB6]
      34 [-]: CALL R0 3 2  ; var0 = var0(var1, var2)
      35 [-]: FASTCALL1 64 R0 L3; 
      36 [-]: MOVE R2 R0   ; var2 = var0
      37 [-]: GETIMPORT R1 13; var1 = 0x7B998233
      38 [-]: CALL R1 2 2  ; var1 = var1(var2)
L 3:  39 [-]: JUMPIF R1 L6 ; goto L6 if var1
      40 [-]: GETUPVAL R1 5; var1 = upvalues[5]
      41 [-]: LOADB R2 1   ; var2 = true
      42 [-]: MOVE R3 R0   ; var3 = var0
      43 [-]: CALL R1 3 1  ; var1(var2, var3)
      44 [-]: JUMP L6      ; goto L6
L 4:  45 [-]: GETUPVAL R1 0; var1 = upvalues[0]
      46 [-]: GETTABLEKS R0 R1 K0; var0 = var1["QueuedAction"]
      47 [-]: GETUPVAL R2 3; var2 = upvalues[3]
      48 [-]: GETTABLEKS R1 R2 K14; var1 = var2["TENNO_CUST"]
      49 [-]: JUMPIFNOTEQ R0 R1 L5; goto L5 if var0 ~= var393276
      50 [-]: GETUPVAL R0 6; var0 = upvalues[6]
      51 [-]: CALL R0 1 1  ; var0()
      52 [-]: JUMP L6      ; goto L6
L 5:  53 [-]: GETUPVAL R1 0; var1 = upvalues[0]
      54 [-]: GETTABLEKS R0 R1 K0; var0 = var1["QueuedAction"]
      55 [-]: GETUPVAL R2 3; var2 = upvalues[3]
      56 [-]: GETTABLEKS R1 R2 K15; var1 = var2["EXIT"]
      57 [-]: JUMPIFNOTEQ R0 R1 L6; goto L6 if var0 ~= var458812
      58 [-]: GETUPVAL R0 7; var0 = upvalues[7]
      59 [-]: CALL R0 1 1  ; var0()
L 6:  60 [-]: GETUPVAL R0 0; var0 = upvalues[0]
      61 [-]: LOADNIL R1   ; var1 = nil
      62 [-]: SETTABLEKS R1 R0 K0; var1["QueuedAction"] = var0
      63 [-]: GETUPVAL R0 0; var0 = upvalues[0]
      64 [-]: LOADNIL R1   ; var1 = nil
      65 [-]: SETTABLEKS R1 R0 K6; var1["QueuedId"] = var0
      66 [-]: RETURN R0 0  ; 


; Name:            
; Defined at line: 1226
; #Upvalues:       2
; #Parameters:     1
; Is_vararg:       0
; Max Stack Size:  5

       0 [-]: FASTCALL1 62 R0 L0; 
       1 [-]: MOVE R2 R0   ; var2 = var0
       2 [-]: GETIMPORT R1 1; var1 = 0x03F57322
       3 [-]: CALL R1 2 2  ; var1 = var1(var2)
L 0:   4 [-]: LOADN R2 4   ; var2 = 4
       5 [-]: JUMPIFNOTEQ R1 R2 L1; goto L1 if var1 ~= var262433
       6 [-]: GETIMPORT R1 4; var1 = _T["BackgroundMovie"]
       7 [-]: LOADK R3 K5  ; var3 = "ShowBlockingMessage"
       8 [-]: LOADK R4 K6  ; var4 = "2"
       9 [-]: NAMECALL R1 R1 K7; var2 = var1; var1 = var1[0xE4162EED]
      10 [-]: CALL R1 4 1  ; var1(var2, var3, var4)
      11 [-]: GETIMPORT R1 9; var1 = 0x25D99D89
      12 [-]: NAMECALL R1 R1 K10; var2 = var1; var1 = var1[0xCBD24335]
      13 [-]: CALL R1 2 1  ; var1(var2)
      14 [-]: GETUPVAL R1 0; var1 = upvalues[0]
      15 [-]: CALL R1 1 1  ; var1()
      16 [-]: RETURN R0 0  ; 
L 1:  17 [-]: FASTCALL1 62 R0 L2; 
      18 [-]: MOVE R2 R0   ; var2 = var0
      19 [-]: GETIMPORT R1 1; var1 = 0x03F57322
      20 [-]: CALL R1 2 2  ; var1 = var1(var2)
L 2:  21 [-]: LOADN R2 6   ; var2 = 6
      22 [-]: JUMPIFNOTEQ R1 R2 L3; goto L3 if var1 ~= var316
      23 [-]: GETUPVAL R1 0; var1 = upvalues[0]
      24 [-]: CALL R1 1 1  ; var1()
      25 [-]: RETURN R0 0  ; 
L 3:  26 [-]: GETUPVAL R1 1; var1 = upvalues[1]
      27 [-]: LOADNIL R2   ; var2 = nil
      28 [-]: SETTABLEKS R2 R1 K11; var2["QueuedAction"] = var1
      29 [-]: GETUPVAL R1 1; var1 = upvalues[1]
      30 [-]: LOADNIL R2   ; var2 = nil
      31 [-]: SETTABLEKS R2 R1 K12; var2["QueuedId"] = var1
      32 [-]: RETURN R0 0  ; 


; Name:            
; Defined at line: 1243
; #Upvalues:       3
; #Parameters:     2
; Is_vararg:       0
; Max Stack Size:  13

       0 [-]: GETUPVAL R3 0; var3 = upvalues[0]
       1 [-]: GETTABLEKS R2 R3 K0; var2 = var3["Focus"]
       2 [-]: JUMPXEQKN R2 K1 L0 NOT; 
       3 [-]: LOADB R2 0   ; var2 = false
       4 [-]: RETURN R2 1  ; 
L 0:   5 [-]: GETUPVAL R2 0; var2 = upvalues[0]
       6 [-]: SETTABLEKS R0 R2 K2; var0["QueuedAction"] = var2
       7 [-]: GETUPVAL R2 0; var2 = upvalues[0]
       8 [-]: SETTABLEKS R1 R2 K3; var1["QueuedId"] = var2
       9 [-]: GETIMPORT R2 5; var2 = 0xAE91E43B
      10 [-]: LOADK R4 K6  ; var4 = "/Lotus/Language/TennoWay/CommitChangesLineCapacity"
      11 [-]: LOADB R5 1   ; var5 = true
      12 [-]: DUPTABLE R6 9; 
      13 [-]: GETUPVAL R8 1; var8 = upvalues[1]
      14 [-]: GETTABLEKS R7 R8 K10; var7 = var8[0x1142C7A8]
      15 [-]: GETUPVAL R9 0; var9 = upvalues[0]
      16 [-]: GETTABLEKS R8 R9 K0; var8 = var9["Focus"]
      17 [-]: LOADN R9 0   ; var9 = 0
      18 [-]: CALL R7 3 2  ; var7 = var7(var8, var9)
      19 [-]: SETTABLEKS R7 R6 K7; var7["NUM"] = var6
      20 [-]: LOADK R8 K11 ; var8 = "+"
      21 [-]: GETUPVAL R11 2; var11 = upvalues[2]
      22 [-]: GETTABLEKS R10 R11 K12; var10 = var11["Total"]
      23 [-]: GETUPVAL R12 2; var12 = upvalues[2]
      24 [-]: GETTABLEKS R11 R12 K13; var11 = var12["Cached"]
      25 [-]: SUB R9 R10 R11; var9 = var10 - var11
      26 [-]: CONCAT R7 R8 R9; var7 = var8 .. var9
      27 [-]: SETTABLEKS R7 R6 K8; var7["AMOUNT"] = var6
      28 [-]: NAMECALL R2 R2 K14; var3 = var2; var2 = var2[0x42B04007]
      29 [-]: CALL R2 5 2  ; var2 = var2(var3, var4, var5, var6)
      30 [-]: GETIMPORT R3 5; var3 = 0xAE91E43B
      31 [-]: LOADK R5 K15 ; var5 = "/Lotus/Language/TennoWay/CommitChanges"
      32 [-]: LOADB R6 0   ; var6 = false
      33 [-]: DUPTABLE R7 17; 
      34 [-]: SETTABLEKS R2 R7 K16; var2["LIST"] = var7
      35 [-]: NAMECALL R3 R3 K14; var4 = var3; var3 = var3[0x42B04007]
      36 [-]: CALL R3 5 2  ; var3 = var3(var4, var5, var6, var7)
      37 [-]: GETIMPORT R4 20; var4 = 0x34291F5C[0xE27B35BB]
      38 [-]: CALL R4 1 2  ; var4 = var4()
      39 [-]: LOADN R5 5   ; var5 = 5
      40 [-]: SETTABLEKS R5 R4 K21; var5["dialogType"] = var4
      41 [-]: SETTABLEKS R3 R4 K22; var3["locString"] = var4
      42 [-]: LOADK R5 K23 ; var5 = "/Menu/Confirm_Item_Yes"
      43 [-]: SETTABLEKS R5 R4 K24; var5["firstString"] = var4
      44 [-]: LOADK R5 K25 ; var5 = "/Menu/Confirm_Item_No"
      45 [-]: SETTABLEKS R5 R4 K26; var5["secondString"] = var4
      46 [-]: LOADK R5 K27 ; var5 = "/Lotus/Language/Menu/Loadout_Cancel"
      47 [-]: SETTABLEKS R5 R4 K28; var5["thirdString"] = var4
      48 [-]: LOADK R7 K29 ; var7 = "OnConfirmCommitFocusChanges"
      49 [-]: NAMECALL R5 R4 K30; var6 = var4; var5 = var4[0xE6CCC5B9]
      50 [-]: CALL R5 3 1  ; var5(var6, var7)
      51 [-]: GETUPVAL R6 1; var6 = upvalues[1]
      52 [-]: GETTABLEKS R5 R6 K31; var5 = var6[0xE99B84E7]
      53 [-]: MOVE R6 R4   ; var6 = var4
      54 [-]: CALL R5 2 1  ; var5(var6)
      55 [-]: LOADB R5 1   ; var5 = true
      56 [-]: RETURN R5 1  ; 


; Name:            
; Defined at line: 1268
; #Upvalues:       3
; #Parameters:     0
; Is_vararg:       0
; Max Stack Size:  13

       0 [-]: NEWTABLE R0 0 0; var0 = {}
       1 [-]: SETUPVAL R0 0; upvalues[0] = var0
       2 [-]: GETUPVAL R0 1; var0 = upvalues[1]
       3 [-]: GETUPVAL R2 2; var2 = upvalues[2]
       4 [-]: GETTABLEKS R1 R2 K0; var1 = var2["MODE_SELECT"]
       5 [-]: JUMPIFNOTEQ R0 R1 L1; goto L1 if var0 ~= var60
       6 [-]: GETUPVAL R0 0; var0 = upvalues[0]
       7 [-]: DUPTABLE R1 3; 
       8 [-]: LOADN R2 420 ; var2 = 420
       9 [-]: SETTABLEKS R2 R1 K1; var2["x"] = var1
      10 [-]: LOADN R2 500 ; var2 = 500
      11 [-]: SETTABLEKS R2 R1 K2; var2["y"] = var1
      12 [-]: SETTABLEN R1 R0 1; SETTABLEN R1 R0 1
      13 [-]: GETIMPORT R0 5; var0 = 0x25D99D89
      14 [-]: NAMECALL R0 R0 K6; var1 = var0; var0 = var0[0xD8159207]
      15 [-]: CALL R0 2 2  ; var0 = var0(var1)
      16 [-]: LOADN R1 3   ; var1 = 3
      17 [-]: JUMPIFNOTLE R1 R0 L0; goto L0 if var1 > var60
      18 [-]: GETUPVAL R0 0; var0 = upvalues[0]
      19 [-]: DUPTABLE R1 3; 
      20 [-]: LOADN R2 800 ; var2 = 800
      21 [-]: SETTABLEKS R2 R1 K1; var2["x"] = var1
      22 [-]: LOADN R2 725 ; var2 = 725
      23 [-]: SETTABLEKS R2 R1 K2; var2["y"] = var1
      24 [-]: SETTABLEN R1 R0 2; SETTABLEN R1 R0 2
      25 [-]: GETUPVAL R0 0; var0 = upvalues[0]
      26 [-]: DUPTABLE R1 3; 
      27 [-]: LOADN R2 1180; var2 = 1180
      28 [-]: SETTABLEKS R2 R1 K1; var2["x"] = var1
      29 [-]: LOADN R2 500 ; var2 = 500
      30 [-]: SETTABLEKS R2 R1 K2; var2["y"] = var1
      31 [-]: SETTABLEN R1 R0 3; SETTABLEN R1 R0 3
      32 [-]: JUMP L2      ; goto L2
L 0:  33 [-]: GETUPVAL R0 0; var0 = upvalues[0]
      34 [-]: DUPTABLE R1 3; 
      35 [-]: LOADN R2 1180; var2 = 1180
      36 [-]: SETTABLEKS R2 R1 K1; var2["x"] = var1
      37 [-]: LOADN R2 500 ; var2 = 500
      38 [-]: SETTABLEKS R2 R1 K2; var2["y"] = var1
      39 [-]: SETTABLEN R1 R0 2; SETTABLEN R1 R0 2
      40 [-]: JUMP L2      ; goto L2
L 1:  41 [-]: GETUPVAL R0 0; var0 = upvalues[0]
      42 [-]: DUPTABLE R1 3; 
      43 [-]: LOADN R2 800 ; var2 = 800
      44 [-]: SETTABLEKS R2 R1 K1; var2["x"] = var1
      45 [-]: LOADN R2 725 ; var2 = 725
      46 [-]: SETTABLEKS R2 R1 K2; var2["y"] = var1
      47 [-]: SETTABLEN R1 R0 1; SETTABLEN R1 R0 1
      48 [-]: GETUPVAL R0 0; var0 = upvalues[0]
      49 [-]: DUPTABLE R1 3; 
      50 [-]: LOADN R2 1180; var2 = 1180
      51 [-]: SETTABLEKS R2 R1 K1; var2["x"] = var1
      52 [-]: LOADN R2 500 ; var2 = 500
      53 [-]: SETTABLEKS R2 R1 K2; var2["y"] = var1
      54 [-]: SETTABLEN R1 R0 2; SETTABLEN R1 R0 2
      55 [-]: GETUPVAL R0 0; var0 = upvalues[0]
      56 [-]: DUPTABLE R1 3; 
      57 [-]: LOADN R2 1100; var2 = 1100
      58 [-]: SETTABLEKS R2 R1 K1; var2["x"] = var1
      59 [-]: LOADN R2 180 ; var2 = 180
      60 [-]: SETTABLEKS R2 R1 K2; var2["y"] = var1
      61 [-]: SETTABLEN R1 R0 3; SETTABLEN R1 R0 3
      62 [-]: GETUPVAL R0 0; var0 = upvalues[0]
      63 [-]: DUPTABLE R1 3; 
      64 [-]: LOADN R2 500 ; var2 = 500
      65 [-]: SETTABLEKS R2 R1 K1; var2["x"] = var1
      66 [-]: LOADN R2 180 ; var2 = 180
      67 [-]: SETTABLEKS R2 R1 K2; var2["y"] = var1
      68 [-]: SETTABLEN R1 R0 4; SETTABLEN R1 R0 4
      69 [-]: GETUPVAL R0 0; var0 = upvalues[0]
      70 [-]: DUPTABLE R1 3; 
      71 [-]: LOADN R2 420 ; var2 = 420
      72 [-]: SETTABLEKS R2 R1 K1; var2["x"] = var1
      73 [-]: LOADN R2 500 ; var2 = 500
      74 [-]: SETTABLEKS R2 R1 K2; var2["y"] = var1
      75 [-]: SETTABLEN R1 R0 5; SETTABLEN R1 R0 5
L 2:  76 [-]: GETIMPORT R0 8; var0 = 0xAE91E43B
      77 [-]: NAMECALL R0 R0 K9; var1 = var0; var0 = var0[0x1AE553AF]
      78 [-]: CALL R0 2 2  ; var0 = var0(var1)
      79 [-]: JUMPIFNOT R0 L4; goto L4 if not var0
      80 [-]: LOADN R1 1   ; var1 = 1
      81 [-]: GETIMPORT R2 8; var2 = 0xAE91E43B
      82 [-]: NAMECALL R2 R2 K10; var3 = var2; var2 = var2[0xC018B56E]
      83 [-]: CALL R2 2 2  ; var2 = var2(var3)
      84 [-]: DIV R0 R1 R2 ; var0 = var1 / var2
      85 [-]: GETIMPORT R2 8; var2 = 0xAE91E43B
      86 [-]: NAMECALL R2 R2 K12; var3 = var2; var2 = var2[0x091C120E]
      87 [-]: CALL R2 2 2  ; var2 = var2(var3)
      88 [-]: MULK R1 R2 K11; var1 = var2 * 0.5
      89 [-]: GETIMPORT R3 8; var3 = 0xAE91E43B
      90 [-]: NAMECALL R3 R3 K13; var4 = var3; var3 = var3[0x2CC9D281]
      91 [-]: CALL R3 2 2  ; var3 = var3(var4)
      92 [-]: MULK R2 R3 K11; var2 = var3 * 0.5
      93 [-]: LOADN R5 1   ; var5 = 1
      94 [-]: GETUPVAL R6 0; var6 = upvalues[0]
      95 [-]: LENGTH R3 R6 ; var3 = #var6
      96 [-]: LOADN R4 1   ; var4 = 1
      97 [-]: FORNPREP R3 L4; nforprep start - [escape at L4] -- var3 = iterator
L 3:  98 [-]: GETUPVAL R7 0; var7 = upvalues[0]
      99 [-]: GETTABLE R6 R7 R5; var6 = var7[var5]
     100 [-]: GETUPVAL R12 0; var12 = upvalues[0]
     101 [-]: GETTABLE R11 R12 R5; var11 = var12[var5]
     102 [-]: GETTABLEKS R10 R11 K1; var10 = var11["x"]
     103 [-]: SUB R9 R10 R1; var9 = var10 - var1
     104 [-]: MUL R8 R9 R0 ; var8 = var9 * var0
     105 [-]: ADD R7 R1 R8 ; var7 = var1 + var8
     106 [-]: SETTABLEKS R7 R6 K1; var7["x"] = var6
     107 [-]: GETUPVAL R7 0; var7 = upvalues[0]
     108 [-]: GETTABLE R6 R7 R5; var6 = var7[var5]
     109 [-]: GETUPVAL R12 0; var12 = upvalues[0]
     110 [-]: GETTABLE R11 R12 R5; var11 = var12[var5]
     111 [-]: GETTABLEKS R10 R11 K2; var10 = var11["y"]
     112 [-]: SUB R9 R10 R2; var9 = var10 - var2
     113 [-]: MUL R8 R9 R0 ; var8 = var9 * var0
     114 [-]: ADD R7 R2 R8 ; var7 = var2 + var8
     115 [-]: SETTABLEKS R7 R6 K2; var7["y"] = var6
     116 [-]: FORNLOOP R3 L3; nforloop end - iterate + goto L3
L 4: 117 [-]: RETURN R0 0  ; 


; Name:            
; Defined at line: 1298
; #Upvalues:       1
; #Parameters:     1
; Is_vararg:       0
; Max Stack Size:  12

       0 [-]: FASTCALL1 64 R0 L0; 
       1 [-]: MOVE R2 R0   ; var2 = var0
       2 [-]: GETIMPORT R1 1; var1 = 0x7B998233
       3 [-]: CALL R1 2 2  ; var1 = var1(var2)
L 0:   4 [-]: JUMPIFNOT R1 L1; goto L1 if not var1
       5 [-]: RETURN R0 0  ; 
L 1:   6 [-]: NAMECALL R1 R0 K2; var2 = var0; var1 = var0[0x68D708A7]
       7 [-]: CALL R1 2 2  ; var1 = var1(var2)
       8 [-]: LOADN R4 1   ; var4 = 1
       9 [-]: NAMECALL R2 R1 K3; var3 = var1; var2 = var1[0x8E62760A]
      10 [-]: CALL R2 3 2  ; var2 = var2(var3, var4)
      11 [-]: GETIMPORT R3 5; var3 = 0x60130201
      12 [-]: LOADN R4 5   ; var4 = 5
      13 [-]: LOADN R5 80  ; var5 = 80
      14 [-]: LOADN R6 232 ; var6 = 232
      15 [-]: LOADN R7 255 ; var7 = 255
      16 [-]: CALL R3 5 2  ; var3 = var3(var4, var5, var6, var7)
      17 [-]: GETIMPORT R4 5; var4 = 0x60130201
      18 [-]: LOADN R5 5   ; var5 = 5
      19 [-]: LOADN R6 80  ; var6 = 80
      20 [-]: LOADN R7 232 ; var7 = 232
      21 [-]: LOADN R8 255 ; var8 = 255
      22 [-]: CALL R4 5 2  ; var4 = var4(var5, var6, var7, var8)
      23 [-]: LOADN R7 6   ; var7 = 6
      24 [-]: NAMECALL R5 R2 K6; var6 = var2; var5 = var2[0x697019D0]
      25 [-]: CALL R5 3 2  ; var5 = var5(var6, var7)
      26 [-]: JUMPIFNOT R5 L2; goto L2 if not var5
      27 [-]: GETIMPORT R5 5; var5 = 0x60130201
      28 [-]: LOADN R8 6   ; var8 = 6
      29 [-]: NAMECALL R6 R2 K7; var7 = var2; var6 = var2[0x5D10207D]
      30 [-]: CALL R6 3 0  ; var6, ... = var6(var7, var8)
      31 [-]: CALL R5 0 2  ; var5 = var5(var6, ...)
      32 [-]: MOVE R3 R5   ; var3 = var5
L 2:  33 [-]: LOADN R7 6   ; var7 = 6
      34 [-]: NAMECALL R5 R2 K6; var6 = var2; var5 = var2[0x697019D0]
      35 [-]: CALL R5 3 2  ; var5 = var5(var6, var7)
      36 [-]: JUMPIFNOT R5 L3; goto L3 if not var5
      37 [-]: GETIMPORT R5 5; var5 = 0x60130201
      38 [-]: LOADN R8 7   ; var8 = 7
      39 [-]: NAMECALL R6 R2 K7; var7 = var2; var6 = var2[0x5D10207D]
      40 [-]: CALL R6 3 0  ; var6, ... = var6(var7, var8)
      41 [-]: CALL R5 0 2  ; var5 = var5(var6, ...)
      42 [-]: MOVE R4 R5   ; var4 = var5
      43 [-]: JUMP L4      ; goto L4
L 3:  44 [-]: MOVE R4 R3   ; var4 = var3
L 4:  45 [-]: GETIMPORT R5 9; var5 = 0x7484946B
      46 [-]: GETIMPORT R7 11; var7 = 0x0469F296
      47 [-]: LOADK R8 K12 ; var8 = "TintColor"
      48 [-]: CALL R7 2 2  ; var7 = var7(var8)
      49 [-]: GETUPVAL R9 0; var9 = upvalues[0]
      50 [-]: GETTABLEKS R8 R9 K13; var8 = var9[0x021DC4BE]
      51 [-]: GETTABLEKS R9 R3 K14; var9 = var3["red"]
      52 [-]: CALL R8 2 2  ; var8 = var8(var9)
      53 [-]: GETUPVAL R10 0; var10 = upvalues[0]
      54 [-]: GETTABLEKS R9 R10 K13; var9 = var10[0x021DC4BE]
      55 [-]: GETTABLEKS R10 R3 K15; var10 = var3["green"]
      56 [-]: CALL R9 2 2  ; var9 = var9(var10)
      57 [-]: GETUPVAL R11 0; var11 = upvalues[0]
      58 [-]: GETTABLEKS R10 R11 K13; var10 = var11[0x021DC4BE]
      59 [-]: GETTABLEKS R11 R3 K16; var11 = var3["blue"]
      60 [-]: CALL R10 2 2 ; var10 = var10(var11)
      61 [-]: LOADN R11 1  ; var11 = 1
      62 [-]: NAMECALL R5 R5 K17; var6 = var5; var5 = var5[0x830EEA67]
      63 [-]: CALL R5 7 1  ; var5(var6, var7, var8, var9, var10, var11)
      64 [-]: GETIMPORT R5 9; var5 = 0x7484946B
      65 [-]: GETIMPORT R7 11; var7 = 0x0469F296
      66 [-]: LOADK R8 K18 ; var8 = "GlowColor"
      67 [-]: CALL R7 2 2  ; var7 = var7(var8)
      68 [-]: GETUPVAL R9 0; var9 = upvalues[0]
      69 [-]: GETTABLEKS R8 R9 K13; var8 = var9[0x021DC4BE]
      70 [-]: GETTABLEKS R9 R4 K14; var9 = var4["red"]
      71 [-]: CALL R8 2 2  ; var8 = var8(var9)
      72 [-]: GETUPVAL R10 0; var10 = upvalues[0]
      73 [-]: GETTABLEKS R9 R10 K13; var9 = var10[0x021DC4BE]
      74 [-]: GETTABLEKS R10 R4 K15; var10 = var4["green"]
      75 [-]: CALL R9 2 2  ; var9 = var9(var10)
      76 [-]: GETUPVAL R11 0; var11 = upvalues[0]
      77 [-]: GETTABLEKS R10 R11 K13; var10 = var11[0x021DC4BE]
      78 [-]: GETTABLEKS R11 R4 K16; var11 = var4["blue"]
      79 [-]: CALL R10 2 2 ; var10 = var10(var11)
      80 [-]: LOADN R11 1  ; var11 = 1
      81 [-]: NAMECALL R5 R5 K17; var6 = var5; var5 = var5[0x830EEA67]
      82 [-]: CALL R5 7 1  ; var5(var6, var7, var8, var9, var10, var11)
      83 [-]: GETIMPORT R5 20; var5 = 0x55530C92
      84 [-]: GETIMPORT R7 11; var7 = 0x0469F296
      85 [-]: LOADK R8 K21 ; var8 = "LowColor"
      86 [-]: CALL R7 2 2  ; var7 = var7(var8)
      87 [-]: GETUPVAL R9 0; var9 = upvalues[0]
      88 [-]: GETTABLEKS R8 R9 K13; var8 = var9[0x021DC4BE]
      89 [-]: GETTABLEKS R9 R3 K14; var9 = var3["red"]
      90 [-]: CALL R8 2 2  ; var8 = var8(var9)
      91 [-]: GETUPVAL R10 0; var10 = upvalues[0]
      92 [-]: GETTABLEKS R9 R10 K13; var9 = var10[0x021DC4BE]
      93 [-]: GETTABLEKS R10 R3 K15; var10 = var3["green"]
      94 [-]: CALL R9 2 2  ; var9 = var9(var10)
      95 [-]: GETUPVAL R11 0; var11 = upvalues[0]
      96 [-]: GETTABLEKS R10 R11 K13; var10 = var11[0x021DC4BE]
      97 [-]: GETTABLEKS R11 R3 K16; var11 = var3["blue"]
      98 [-]: CALL R10 2 2 ; var10 = var10(var11)
      99 [-]: LOADN R11 1  ; var11 = 1
     100 [-]: NAMECALL R5 R5 K17; var6 = var5; var5 = var5[0x830EEA67]
     101 [-]: CALL R5 7 1  ; var5(var6, var7, var8, var9, var10, var11)
     102 [-]: GETIMPORT R5 20; var5 = 0x55530C92
     103 [-]: GETIMPORT R7 11; var7 = 0x0469F296
     104 [-]: LOADK R8 K22 ; var8 = "HighColor"
     105 [-]: CALL R7 2 2  ; var7 = var7(var8)
     106 [-]: GETUPVAL R9 0; var9 = upvalues[0]
     107 [-]: GETTABLEKS R8 R9 K13; var8 = var9[0x021DC4BE]
     108 [-]: GETTABLEKS R9 R4 K14; var9 = var4["red"]
     109 [-]: CALL R8 2 2  ; var8 = var8(var9)
     110 [-]: GETUPVAL R10 0; var10 = upvalues[0]
     111 [-]: GETTABLEKS R9 R10 K13; var9 = var10[0x021DC4BE]
     112 [-]: GETTABLEKS R10 R4 K15; var10 = var4["green"]
     113 [-]: CALL R9 2 2  ; var9 = var9(var10)
     114 [-]: GETUPVAL R11 0; var11 = upvalues[0]
     115 [-]: GETTABLEKS R10 R11 K13; var10 = var11[0x021DC4BE]
     116 [-]: GETTABLEKS R11 R4 K16; var11 = var4["blue"]
     117 [-]: CALL R10 2 2 ; var10 = var10(var11)
     118 [-]: LOADN R11 1  ; var11 = 1
     119 [-]: NAMECALL R5 R5 K17; var6 = var5; var5 = var5[0x830EEA67]
     120 [-]: CALL R5 7 1  ; var5(var6, var7, var8, var9, var10, var11)
     121 [-]: RETURN R0 0  ; 


; Name:            
; Defined at line: 1321
; #Upvalues:       24
; #Parameters:     0
; Is_vararg:       0
; Max Stack Size:  14

       0 [-]: GETIMPORT R0 1; var0 = 0x2D0FAD09
       1 [-]: LOADK R1 K2  ; var1 = "Lotus.Interface.Libs.TimerMgr"
       2 [-]: CALL R0 2 2  ; var0 = var0(var1)
       3 [-]: GETTABLEKS R1 R0 K3; var1 = var0[0xDE474187]
       4 [-]: CALL R1 1 2  ; var1 = var1()
       5 [-]: SETUPVAL R1 0; upvalues[1] = var0
       6 [-]: GETIMPORT R1 6; var1 = _T["TennoWay_QueuedZoom"]
       7 [-]: JUMPXEQKNIL R1 L0; 
       8 [-]: GETUPVAL R2 2; var2 = upvalues[2]
       9 [-]: GETTABLEKS R1 R2 K7; var1 = var2["TREE_SELECT"]
      10 [-]: SETUPVAL R1 1; upvalues[1] = var1
      11 [-]: GETIMPORT R1 6; var1 = _T["TennoWay_QueuedZoom"]
      12 [-]: SETUPVAL R1 3; upvalues[1] = var3
      13 [-]: GETIMPORT R1 8; var1 = _T
      14 [-]: LOADNIL R2   ; var2 = nil
      15 [-]: SETTABLEKS R2 R1 K5; var2["TennoWay_QueuedZoom"] = var1
L 0:  16 [-]: GETIMPORT R2 10; var2 = _T["ForceHideMiniMap"]
      17 [-]: FASTCALL1 64 R2 L1; 
      18 [-]: GETIMPORT R1 12; var1 = 0x7B998233
      19 [-]: CALL R1 2 2  ; var1 = var1(var2)
L 1:  20 [-]: JUMPIF R1 L2 ; goto L2 if var1
      21 [-]: GETIMPORT R1 10; var1 = _T["ForceHideMiniMap"]
      22 [-]: CALL R1 1 1  ; var1()
L 2:  23 [-]: GETIMPORT R1 8; var1 = _T
      24 [-]: LOADNIL R2   ; var2 = nil
      25 [-]: SETTABLEKS R2 R1 K13; var2["disableOperatorLookAt"] = var1
      26 [-]: GETIMPORT R1 15; var1 = 0x89326C93
      27 [-]: NAMECALL R1 R1 K16; var2 = var1; var1 = var1[0x78298275]
      28 [-]: CALL R1 2 2  ; var1 = var1(var2)
      29 [-]: GETIMPORT R4 18; var4 = gLotusOperatorAvatarType
      30 [-]: NAMECALL R2 R1 K19; var3 = var1; var2 = var1[0xF2DEAF69]
      31 [-]: CALL R2 3 2  ; var2 = var2(var3, var4)
      32 [-]: SETUPVAL R2 4; upvalues[2] = var4
      33 [-]: LOADB R2 0   ; var2 = false
      34 [-]: GETUPVAL R4 6; var4 = upvalues[6]
      35 [-]: GETTABLEKS R3 R4 K20; var3 = var4[0xB73D420F]
      36 [-]: CALL R3 1 2  ; var3 = var3()
      37 [-]: GETUPVAL R5 6; var5 = upvalues[6]
      38 [-]: GETTABLEKS R4 R5 K21; var4 = var5["UI_MODE_IN_SPACE_SHIP"]
      39 [-]: JUMPIFNOTEQ R3 R4 L3; goto L3 if var3 ~= var1508129
      40 [-]: GETIMPORT R3 23; var3 = 0xBE190284
      41 [-]: NAMECALL R3 R3 K24; var4 = var3; var3 = var3[0x23DDC82A]
      42 [-]: CALL R3 2 2  ; var3 = var3(var4)
      43 [-]: NOT R2 R3    ; var2 = not var3
L 3:  44 [-]: SETUPVAL R2 5; upvalues[2] = var5
      45 [-]: GETUPVAL R2 5; var2 = upvalues[5]
      46 [-]: JUMPIFNOT R2 L4; goto L4 if not var2
      47 [-]: GETUPVAL R2 4; var2 = upvalues[4]
      48 [-]: JUMPIFNOT R2 L4; goto L4 if not var2
      49 [-]: GETIMPORT R4 26; var4 = 0x943AE11E
      50 [-]: LOADB R5 0   ; var5 = false
      51 [-]: LOADN R6 3   ; var6 = 3
      52 [-]: LOADN R7 2   ; var7 = 2
      53 [-]: LOADB R8 1   ; var8 = true
      54 [-]: NAMECALL R2 R1 K27; var3 = var1; var2 = var1[0x5D985C7E]
      55 [-]: CALL R2 7 1  ; var2(var3, var4, var5, var6, var7, var8)
      56 [-]: JUMP L5      ; goto L5
L 4:  57 [-]: GETUPVAL R2 5; var2 = upvalues[5]
      58 [-]: JUMPIF R2 L5 ; goto L5 if var2
      59 [-]: LOADN R4 0   ; var4 = 0
      60 [-]: NAMECALL R2 R1 K28; var3 = var1; var2 = var1[0x2E9B92E3]
      61 [-]: CALL R2 3 1  ; var2(var3, var4)
L 5:  62 [-]: GETUPVAL R2 7; var2 = upvalues[7]
      63 [-]: CALL R2 1 1  ; var2()
      64 [-]: GETIMPORT R2 30; var2 = 0xAE91E43B
      65 [-]: LOADK R4 K31 ; var4 = "DrifterClick"
      66 [-]: LOADN R5 11  ; var5 = 11
      67 [-]: LOADB R6 0   ; var6 = false
      68 [-]: NAMECALL R2 R2 K32; var3 = var2; var2 = var2[0xAADE900E]
      69 [-]: CALL R2 5 1  ; var2(var3, var4, var5, var6)
      70 [-]: GETIMPORT R2 15; var2 = 0x89326C93
      71 [-]: NAMECALL R2 R2 K33; var3 = var2; var2 = var2[0xFB64E76C]
      72 [-]: CALL R2 2 2  ; var2 = var2(var3)
      73 [-]: GETUPVAL R3 8; var3 = upvalues[8]
      74 [-]: NAMECALL R6 R2 K34; var7 = var2; var6 = var2[0x5578D98B]
      75 [-]: CALL R6 2 0  ; var6, ... = var6(var7)
      76 [-]: FASTCALL 64 L6; 
      77 [-]: GETIMPORT R5 12; var5 = 0x7B998233
      78 [-]: CALL R5 0 2  ; var5 = var5(var6, ...)
L 6:  79 [-]: NOT R4 R5    ; var4 = not var5
      80 [-]: JUMPIFNOT R4 L7; goto L7 if not var4
      81 [-]: GETUPVAL R5 6; var5 = upvalues[6]
      82 [-]: GETTABLEKS R4 R5 K35; var4 = var5[0x52FB05B3]
      83 [-]: GETIMPORT R5 37; var5 = 0xD737CEEC
      84 [-]: CALL R4 2 2  ; var4 = var4(var5)
      85 [-]: JUMPIFNOT R4 L7; goto L7 if not var4
      86 [-]: LOADB R4 0   ; var4 = false
      87 [-]: GETIMPORT R5 39; var5 = 0x25D99D89
      88 [-]: NAMECALL R5 R5 K40; var6 = var5; var5 = var5[0xD8159207]
      89 [-]: CALL R5 2 2  ; var5 = var5(var6)
      90 [-]: LOADN R6 4   ; var6 = 4
      91 [-]: JUMPIFNOTLE R6 R5 L7; goto L7 if var6 > var1508641
      92 [-]: GETIMPORT R5 23; var5 = 0xBE190284
      93 [-]: GETIMPORT R7 42; var7 = gLotusAttractModeGameRulesType
      94 [-]: NAMECALL R5 R5 K19; var6 = var5; var5 = var5[0xF2DEAF69]
      95 [-]: CALL R5 3 2  ; var5 = var5(var6, var7)
      96 [-]: NOT R4 R5    ; var4 = not var5
      97 [-]: JUMPIF R4 L7 ; goto L7 if var4
      98 [-]: GETIMPORT R5 23; var5 = 0xBE190284
      99 [-]: NAMECALL R5 R5 K24; var6 = var5; var5 = var5[0x23DDC82A]
     100 [-]: CALL R5 2 2  ; var5 = var5(var6)
     101 [-]: NOT R4 R5    ; var4 = not var5
L 7: 102 [-]: SETTABLEKS R4 R3 K43; var4["Visible"] = var3
     103 [-]: GETUPVAL R4 8; var4 = upvalues[8]
     104 [-]: GETTABLEKS R3 R4 K43; var3 = var4["Visible"]
     105 [-]: JUMPIFNOT R3 L10; goto L10 if not var3
     106 [-]: GETIMPORT R3 39; var3 = 0x25D99D89
     107 [-]: NAMECALL R3 R3 K44; var4 = var3; var3 = var3[0x62C81B76]
     108 [-]: CALL R3 2 2  ; var3 = var3(var4)
     109 [-]: GETTABLEKS R5 R3 K45; var5 = var3["mOperatorType"]
     110 [-]: LOADN R6 4   ; var6 = 4
     111 [-]: JUMPIFEQ R5 R6 L8; goto L8 if var5 == var16778246
     112 [-]: LOADB R4 0 +1; var4 = false
L 8: 113 [-]: LOADB R4 1   ; var4 = true
L 9: 114 [-]: SETUPVAL R4 9; upvalues[4] = var9
     115 [-]: GETUPVAL R4 9; var4 = upvalues[9]
     116 [-]: SETUPVAL R4 10; upvalues[4] = var10
     117 [-]: GETIMPORT R4 30; var4 = 0xAE91E43B
     118 [-]: LOADK R6 K46 ; var6 = "DrifterClick.Label"
     119 [-]: LOADN R7 0   ; var7 = 0
     120 [-]: LOADN R8 -256; var8 = -256
     121 [-]: NAMECALL R4 R4 K47; var5 = var4; var4 = var4[0x67BC869F]
     122 [-]: CALL R4 5 1  ; var4(var5, var6, var7, var8)
     123 [-]: GETIMPORT R4 30; var4 = 0xAE91E43B
     124 [-]: LOADK R6 K46 ; var6 = "DrifterClick.Label"
     125 [-]: LOADN R7 10  ; var7 = 10
     126 [-]: LOADN R8 0   ; var8 = 0
     127 [-]: NAMECALL R4 R4 K47; var5 = var4; var4 = var4[0x67BC869F]
     128 [-]: CALL R4 5 1  ; var4(var5, var6, var7, var8)
     129 [-]: GETIMPORT R4 30; var4 = 0xAE91E43B
     130 [-]: LOADK R6 K31 ; var6 = "DrifterClick"
     131 [-]: LOADN R7 10  ; var7 = 10
     132 [-]: LOADN R8 0   ; var8 = 0
     133 [-]: NAMECALL R4 R4 K47; var5 = var4; var4 = var4[0x67BC869F]
     134 [-]: CALL R4 5 1  ; var4(var5, var6, var7, var8)
     135 [-]: GETIMPORT R4 30; var4 = 0xAE91E43B
     136 [-]: LOADK R6 K48 ; var6 = "DrifterClick.DrifterBacker"
     137 [-]: LOADK R7 K49 ; var7 = "DrifterFocused"
     138 [-]: LOADK R8 K50 ; var8 = "DrifterUnfocused"
     139 [-]: LOADNIL R9   ; var9 = nil
     140 [-]: LOADK R10 K51; var10 = "DrifterPressed"
     141 [-]: NAMECALL R4 R4 K52; var5 = var4; var4 = var4[0x1E5B5CFE]
     142 [-]: CALL R4 7 1  ; var4(var5, var6, var7, var8, var9, var10)
L10: 143 [-]: GETIMPORT R4 54; var4 = _T["EnableUIInput"]
     144 [-]: FASTCALL1 64 R4 L11; 
     145 [-]: GETIMPORT R3 12; var3 = 0x7B998233
     146 [-]: CALL R3 2 2  ; var3 = var3(var4)
L11: 147 [-]: JUMPIF R3 L12; goto L12 if var3
     148 [-]: GETIMPORT R3 54; var3 = _T["EnableUIInput"]
     149 [-]: CALL R3 1 1  ; var3()
L12: 150 [-]: GETUPVAL R4 11; var4 = upvalues[11]
     151 [-]: GETTABLEKS R3 R4 K55; var3 = var4[0x2A1108A9]
     152 [-]: LOADK R4 K56 ; var4 = "TennoWay"
     153 [-]: NAMECALL R5 R1 K57; var6 = var1; var5 = var1[0xD1586535]
     154 [-]: CALL R5 2 0  ; var5, ... = var5(var6)
     155 [-]: CALL R3 0 2  ; var3 = var3(var4, ...)
     156 [-]: FASTCALL1 64 R3 L13; 
     157 [-]: MOVE R5 R3   ; var5 = var3
     158 [-]: GETIMPORT R4 12; var4 = 0x7B998233
     159 [-]: CALL R4 2 2  ; var4 = var4(var5)
L13: 160 [-]: JUMPIF R4 L14; goto L14 if var4
     161 [-]: LOADB R6 1   ; var6 = true
     162 [-]: NAMECALL R4 R3 K58; var5 = var3; var4 = var3[0xD3A24024]
     163 [-]: CALL R4 3 1  ; var4(var5, var6)
L14: 164 [-]: GETUPVAL R5 13; var5 = upvalues[13]
     165 [-]: GETTABLEKS R4 R5 K59; var4 = var5[0xAE6791BA]
     166 [-]: GETIMPORT R5 30; var5 = 0xAE91E43B
     167 [-]: CALL R4 2 2  ; var4 = var4(var5)
     168 [-]: SETUPVAL R4 12; upvalues[4] = var12
     169 [-]: GETUPVAL R4 12; var4 = upvalues[12]
     170 [-]: GETIMPORT R6 30; var6 = 0xAE91E43B
     171 [-]: LOADK R7 K60 ; var7 = "PreviewNotice"
     172 [-]: NEWTABLE R8 0 2; var8 = {}
     173 [-]: GETUPVAL R10 12; var10 = upvalues[12]
     174 [-]: GETTABLEKS R9 R10 K61; var9 = var10["ANCHOR_V_BOTTOM"]
     175 [-]: GETUPVAL R11 12; var11 = upvalues[12]
     176 [-]: GETTABLEKS R10 R11 K62; var10 = var11["ANCHOR_H_LEFT"]
     177 [-]: SETLIST R8 R9 2 [1]; var8[1] = var9; var8[2] = var10; var8[3] = var11; 
     178 [-]: NAMECALL R4 R4 K63; var5 = var4; var4 = var4[0x20FF29F7]
     179 [-]: CALL R4 5 1  ; var4(var5, var6, var7, var8)
     180 [-]: GETUPVAL R4 12; var4 = upvalues[12]
     181 [-]: GETIMPORT R6 30; var6 = 0xAE91E43B
     182 [-]: LOADK R7 K64 ; var7 = "Capacity"
     183 [-]: NEWTABLE R8 0 2; var8 = {}
     184 [-]: GETUPVAL R10 12; var10 = upvalues[12]
     185 [-]: GETTABLEKS R9 R10 K65; var9 = var10["ANCHOR_V_CENTRE"]
     186 [-]: GETUPVAL R11 12; var11 = upvalues[12]
     187 [-]: GETTABLEKS R10 R11 K66; var10 = var11["ANCHOR_H_CENTRE"]
     188 [-]: SETLIST R8 R9 2 [1]; var8[1] = var9; var8[2] = var10; var8[3] = var11; 
     189 [-]: NAMECALL R4 R4 K63; var5 = var4; var4 = var4[0x20FF29F7]
     190 [-]: CALL R4 5 1  ; var4(var5, var6, var7, var8)
     191 [-]: GETUPVAL R4 12; var4 = upvalues[12]
     192 [-]: GETIMPORT R6 30; var6 = 0xAE91E43B
     193 [-]: NAMECALL R6 R6 K67; var7 = var6; var6 = var6[0x6B837788]
     194 [-]: CALL R6 2 2  ; var6 = var6(var7)
     195 [-]: GETIMPORT R7 30; var7 = 0xAE91E43B
     196 [-]: NAMECALL R7 R7 K68; var8 = var7; var7 = var7[0xAF9FDA9F]
     197 [-]: CALL R7 2 0  ; var7, ... = var7(var8)
     198 [-]: NAMECALL R4 R4 K69; var5 = var4; var4 = var4[0xFAA69527]
     199 [-]: CALL R4 0 1  ; var4(var5, ...)
     200 [-]: GETIMPORT R4 15; var4 = 0x89326C93
     201 [-]: NAMECALL R4 R4 K33; var5 = var4; var4 = var4[0xFB64E76C]
     202 [-]: CALL R4 2 2  ; var4 = var4(var5)
     203 [-]: FASTCALL1 64 R4 L15; 
     204 [-]: MOVE R6 R4   ; var6 = var4
     205 [-]: GETIMPORT R5 12; var5 = 0x7B998233
     206 [-]: CALL R5 2 2  ; var5 = var5(var6)
L15: 207 [-]: JUMPIF R5 L17; goto L17 if var5
     208 [-]: NAMECALL R5 R4 K34; var6 = var4; var5 = var4[0x5578D98B]
     209 [-]: CALL R5 2 2  ; var5 = var5(var6)
     210 [-]: FASTCALL1 64 R5 L16; 
     211 [-]: MOVE R7 R5   ; var7 = var5
     212 [-]: GETIMPORT R6 12; var6 = 0x7B998233
     213 [-]: CALL R6 2 2  ; var6 = var6(var7)
L16: 214 [-]: JUMPIF R6 L17; goto L17 if var6
     215 [-]: LOADB R8 1   ; var8 = true
     216 [-]: NAMECALL R6 R5 K70; var7 = var5; var6 = var5[0x044B7BE8]
     217 [-]: CALL R6 3 1  ; var6(var7, var8)
     218 [-]: NAMECALL R6 R5 K71; var7 = var5; var6 = var5[0xDE321E6F]
     219 [-]: CALL R6 2 2  ; var6 = var6(var7)
     220 [-]: NAMECALL R6 R6 K72; var7 = var6; var6 = var6[0xF7D48EE0]
     221 [-]: CALL R6 2 2  ; var6 = var6(var7)
     222 [-]: GETUPVAL R7 14; var7 = upvalues[14]
     223 [-]: MOVE R8 R6   ; var8 = var6
     224 [-]: CALL R7 2 1  ; var7(var8)
L17: 225 [-]: GETUPVAL R6 11; var6 = upvalues[11]
     226 [-]: GETTABLEKS R5 R6 K73; var5 = var6[0x659D451F]
     227 [-]: GETIMPORT R6 75; var6 = 0x0856E17D
     228 [-]: CALL R5 2 1  ; var5(var6)
     229 [-]: GETUPVAL R5 15; var5 = upvalues[15]
     230 [-]: CALL R5 1 1  ; var5()
     231 [-]: GETUPVAL R5 16; var5 = upvalues[16]
     232 [-]: CALL R5 1 1  ; var5()
     233 [-]: GETIMPORT R5 30; var5 = 0xAE91E43B
     234 [-]: LOADK R7 K64 ; var7 = "Capacity"
     235 [-]: LOADN R8 10  ; var8 = 10
     236 [-]: LOADN R9 0   ; var9 = 0
     237 [-]: NAMECALL R5 R5 K47; var6 = var5; var5 = var5[0x67BC869F]
     238 [-]: CALL R5 5 1  ; var5(var6, var7, var8, var9)
     239 [-]: GETIMPORT R5 78; var5 = 0x34291F5C[0x781669D7]
     240 [-]: CALL R5 1 2  ; var5 = var5()
     241 [-]: JUMPIFNOT R5 L18; goto L18 if not var5
     242 [-]: GETIMPORT R5 30; var5 = 0xAE91E43B
     243 [-]: LOADK R7 K64 ; var7 = "Capacity"
     244 [-]: LOADN R8 5   ; var8 = 5
     245 [-]: LOADN R9 115 ; var9 = 115
     246 [-]: NAMECALL R5 R5 K47; var6 = var5; var5 = var5[0x67BC869F]
     247 [-]: CALL R5 5 1  ; var5(var6, var7, var8, var9)
     248 [-]: GETIMPORT R5 30; var5 = 0xAE91E43B
     249 [-]: LOADK R7 K64 ; var7 = "Capacity"
     250 [-]: LOADN R8 6   ; var8 = 6
     251 [-]: LOADN R9 115 ; var9 = 115
     252 [-]: NAMECALL R5 R5 K47; var6 = var5; var5 = var5[0x67BC869F]
     253 [-]: CALL R5 5 1  ; var5(var6, var7, var8, var9)
L18: 254 [-]: GETIMPORT R5 30; var5 = 0xAE91E43B
     255 [-]: LOADK R7 K79 ; var7 = "Capacity.Bg"
     256 [-]: GETIMPORT R8 81; var8 = 0x3B3EEBE4
     257 [-]: NAMECALL R5 R5 K82; var6 = var5; var5 = var5[0xD5181643]
     258 [-]: CALL R5 4 1  ; var5(var6, var7, var8)
     259 [-]: GETIMPORT R5 30; var5 = 0xAE91E43B
     260 [-]: LOADK R7 K83 ; var7 = "Capacity.Title.text"
     261 [-]: LOADK R8 K84 ; var8 = "/Lotus/Language/TennoWay/CapacityTag"
     262 [-]: NAMECALL R5 R5 K85; var6 = var5; var5 = var5[0x20B98DB3]
     263 [-]: CALL R5 4 1  ; var5(var6, var7, var8)
     264 [-]: GETIMPORT R5 30; var5 = 0xAE91E43B
     265 [-]: LOADK R7 K86 ; var7 = "_root"
     266 [-]: LOADN R8 10  ; var8 = 10
     267 [-]: LOADN R9 0   ; var9 = 0
     268 [-]: NAMECALL R5 R5 K47; var6 = var5; var5 = var5[0x67BC869F]
     269 [-]: CALL R5 5 1  ; var5(var6, var7, var8, var9)
     270 [-]: GETIMPORT R5 30; var5 = 0xAE91E43B
     271 [-]: LOADK R7 K87 ; var7 = "Bg"
     272 [-]: LOADN R8 10  ; var8 = 10
     273 [-]: LOADN R9 0   ; var9 = 0
     274 [-]: NAMECALL R5 R5 K47; var6 = var5; var5 = var5[0x67BC869F]
     275 [-]: CALL R5 5 1  ; var5(var6, var7, var8, var9)
     276 [-]: GETIMPORT R5 30; var5 = 0xAE91E43B
     277 [-]: LOADK R7 K48 ; var7 = "DrifterClick.DrifterBacker"
     278 [-]: GETIMPORT R8 89; var8 = 0x7484946B
     279 [-]: NAMECALL R5 R5 K82; var6 = var5; var5 = var5[0xD5181643]
     280 [-]: CALL R5 4 1  ; var5(var6, var7, var8)
     281 [-]: GETIMPORT R5 30; var5 = 0xAE91E43B
     282 [-]: LOADN R7 0   ; var7 = 0
     283 [-]: NAMECALL R5 R5 K90; var6 = var5; var5 = var5[0xC6A10AB1]
     284 [-]: CALL R5 3 1  ; var5(var6, var7)
     285 [-]: GETIMPORT R5 30; var5 = 0xAE91E43B
     286 [-]: LOADN R7 0   ; var7 = 0
     287 [-]: NAMECALL R5 R5 K91; var6 = var5; var5 = var5[0x58BEC6D6]
     288 [-]: CALL R5 3 1  ; var5(var6, var7)
     289 [-]: GETIMPORT R5 30; var5 = 0xAE91E43B
     290 [-]: GETIMPORT R8 93; var8 = 0x0032441C
     291 [-]: GETTABLEKS R7 R8 K94; var7 = var8["UIMaterials_Plain"]
     292 [-]: NAMECALL R5 R5 K95; var6 = var5; var5 = var5[0x2D6BAD65]
     293 [-]: CALL R5 3 1  ; var5(var6, var7)
     294 [-]: GETIMPORT R6 97; var6 = _T["SetButtons"]
     295 [-]: FASTCALL1 64 R6 L19; 
     296 [-]: GETIMPORT R5 12; var5 = 0x7B998233
     297 [-]: CALL R5 2 2  ; var5 = var5(var6)
L19: 298 [-]: JUMPIF R5 L20; goto L20 if var5
     299 [-]: GETUPVAL R5 17; var5 = upvalues[17]
     300 [-]: CALL R5 1 1  ; var5()
L20: 301 [-]: GETIMPORT R5 99; var5 = 0x25312C9B
     302 [-]: GETIMPORT R6 30; var6 = 0xAE91E43B
     303 [-]: LOADK R7 K86 ; var7 = "_root"
     304 [-]: LOADN R8 2   ; var8 = 2
     305 [-]: NEWTABLE R9 0 1; var9 = {}
     306 [-]: LOADN R10 10 ; var10 = 10
     307 [-]: SETLIST R9 R10 1 [1]; var9[1] = var10; var9[2] = var11; 
     308 [-]: NEWTABLE R10 0 1; var10 = {}
     309 [-]: LOADN R11 100; var11 = 100
     310 [-]: SETLIST R10 R11 1 [1]; var10[1] = var11; var10[2] = var12; 
     311 [-]: LOADK R11 K100; var11 = 0.34999999403953552
     312 [-]: LOADN R12 0  ; var12 = 0
     313 [-]: GETUPVAL R13 18; var13 = upvalues[18]
     314 [-]: CALL R5 9 1  ; var5(var6, var7, var8, var9, var10, var11, var12, var13)
     315 [-]: GETUPVAL R5 19; var5 = upvalues[19]
     316 [-]: CALL R5 1 1  ; var5()
     317 [-]: GETUPVAL R5 20; var5 = upvalues[20]
     318 [-]: LOADB R6 0   ; var6 = false
     319 [-]: CALL R5 2 1  ; var5(var6)
     320 [-]: GETIMPORT R5 30; var5 = 0xAE91E43B
     321 [-]: LOADK R7 K101; var7 = "PreviewNotice.Bg"
     322 [-]: GETIMPORT R9 93; var9 = 0x0032441C
     323 [-]: GETTABLEKS R8 R9 K102; var8 = var9["UIMaterial_RectangleNoDepth"]
     324 [-]: NAMECALL R5 R5 K82; var6 = var5; var5 = var5[0xD5181643]
     325 [-]: CALL R5 4 1  ; var5(var6, var7, var8)
     326 [-]: GETIMPORT R5 30; var5 = 0xAE91E43B
     327 [-]: LOADK R7 K101; var7 = "PreviewNotice.Bg"
     328 [-]: LOADK R8 K103; var8 = "RectInnerColor"
     329 [-]: GETUPVAL R11 21; var11 = upvalues[21]
     330 [-]: GETTABLEKS R10 R11 K104; var10 = var11["Background1Object"]
     331 [-]: GETTABLEKS R9 R10 K105; var9 = var10["r"]
     332 [-]: GETUPVAL R12 21; var12 = upvalues[21]
     333 [-]: GETTABLEKS R11 R12 K104; var11 = var12["Background1Object"]
     334 [-]: GETTABLEKS R10 R11 K106; var10 = var11["g"]
     335 [-]: GETUPVAL R13 21; var13 = upvalues[21]
     336 [-]: GETTABLEKS R12 R13 K104; var12 = var13["Background1Object"]
     337 [-]: GETTABLEKS R11 R12 K107; var11 = var12["b"]
     338 [-]: LOADN R12 1  ; var12 = 1
     339 [-]: NAMECALL R5 R5 K108; var6 = var5; var5 = var5[0x91E13703]
     340 [-]: CALL R5 8 1  ; var5(var6, var7, var8, var9, var10, var11, var12)
     341 [-]: GETIMPORT R5 30; var5 = 0xAE91E43B
     342 [-]: LOADK R7 K101; var7 = "PreviewNotice.Bg"
     343 [-]: LOADK R8 K109; var8 = "RectEdgeColor"
     344 [-]: GETUPVAL R11 21; var11 = upvalues[21]
     345 [-]: GETTABLEKS R10 R11 K110; var10 = var11["FloatingContentHighlightObject"]
     346 [-]: GETTABLEKS R9 R10 K105; var9 = var10["r"]
     347 [-]: GETUPVAL R12 21; var12 = upvalues[21]
     348 [-]: GETTABLEKS R11 R12 K110; var11 = var12["FloatingContentHighlightObject"]
     349 [-]: GETTABLEKS R10 R11 K106; var10 = var11["g"]
     350 [-]: GETUPVAL R13 21; var13 = upvalues[21]
     351 [-]: GETTABLEKS R12 R13 K110; var12 = var13["FloatingContentHighlightObject"]
     352 [-]: GETTABLEKS R11 R12 K107; var11 = var12["b"]
     353 [-]: LOADK R12 K111; var12 = 0.05000000074505806
     354 [-]: NAMECALL R5 R5 K108; var6 = var5; var5 = var5[0x91E13703]
     355 [-]: CALL R5 8 1  ; var5(var6, var7, var8, var9, var10, var11, var12)
     356 [-]: GETIMPORT R5 30; var5 = 0xAE91E43B
     357 [-]: LOADK R7 K112; var7 = "PreviewNotice.Icon"
     358 [-]: LOADN R8 9   ; var8 = 9
     359 [-]: GETUPVAL R10 21; var10 = upvalues[21]
     360 [-]: GETTABLEKS R9 R10 K113; var9 = var10["FloatingContent"]
     361 [-]: NAMECALL R5 R5 K47; var6 = var5; var5 = var5[0x67BC869F]
     362 [-]: CALL R5 5 1  ; var5(var6, var7, var8, var9)
     363 [-]: GETUPVAL R5 22; var5 = upvalues[22]
     364 [-]: CALL R5 1 1  ; var5()
     365 [-]: LOADB R5 1   ; var5 = true
     366 [-]: SETUPVAL R5 23; upvalues[5] = var23
     367 [-]: GETIMPORT R6 115; var6 = 0xCB79539E
     368 [-]: FASTCALL1 64 R6 L21; 
     369 [-]: GETIMPORT R5 12; var5 = 0x7B998233
     370 [-]: CALL R5 2 2  ; var5 = var5(var6)
L21: 371 [-]: JUMPIF R5 L22; goto L22 if var5
     372 [-]: GETIMPORT R5 115; var5 = 0xCB79539E
     373 [-]: GETIMPORT R7 117; var7 = 0x0469F296
     374 [-]: LOADK R8 K118; var8 = "IN_SHIP_VIEW_TIME"
     375 [-]: CALL R7 2 2  ; var7 = var7(var8)
     376 [-]: LOADK R8 K119; var8 = "OPERATOR_FOCUS_MAIN"
     377 [-]: NAMECALL R5 R5 K120; var6 = var5; var5 = var5[0xA9136B2F]
     378 [-]: CALL R5 4 1  ; var5(var6, var7, var8)
L22: 379 [-]: RETURN R0 0  ; 


; Name:            
; Defined at line: 1440
; #Upvalues:       1
; #Parameters:     2
; Is_vararg:       0
; Max Stack Size:  3

       0 [-]: GETUPVAL R2 0; var2 = upvalues[0]
       1 [-]: CALL R2 1 1  ; var2()
       2 [-]: RETURN R0 0  ; 


; Name:            
; Defined at line: 1444
; #Upvalues:       3
; #Parameters:     0
; Is_vararg:       0
; Max Stack Size:  2

       0 [-]: GETUPVAL R0 0; var0 = upvalues[0]
       1 [-]: JUMPIF R0 L0 ; goto L0 if var0
       2 [-]: RETURN R0 0  ; 
L 0:   3 [-]: LOADB R0 1   ; var0 = true
       4 [-]: SETUPVAL R0 1; upvalues[0] = var1
       5 [-]: GETUPVAL R0 2; var0 = upvalues[2]
       6 [-]: LOADB R1 1   ; var1 = true
       7 [-]: CALL R0 2 1  ; var0(var1)
       8 [-]: RETURN R0 0  ; 


; Name:            
; Defined at line: 1453
; #Upvalues:       1
; #Parameters:     1
; Is_vararg:       0
; Max Stack Size:  1

       0 [-]: SETUPVAL R0 0; upvalues[0] = var0
       1 [-]: RETURN R0 0  ; 


; Name:            
; Defined at line: 1457
; #Upvalues:       1
; #Parameters:     1
; Is_vararg:       0
; Max Stack Size:  3

       0 [-]: GETUPVAL R1 0; var1 = upvalues[0]
       1 [-]: MOVE R2 R0   ; var2 = var0
       2 [-]: CALL R1 2 1  ; var1(var2)
       3 [-]: RETURN R0 0  ; 


; Name:            
; Defined at line: 1461
; #Upvalues:       1
; #Parameters:     0
; Is_vararg:       0
; Max Stack Size:  1

       0 [-]: GETUPVAL R0 0; var0 = upvalues[0]
       1 [-]: CALL R0 1 1  ; var0()
       2 [-]: RETURN R0 0  ; 


; Name:            
; Defined at line: 1465
; #Upvalues:       0
; #Parameters:     1
; Is_vararg:       0
; Max Stack Size:  2

       0 [-]: GETIMPORT R1 1; var1 = _T
       1 [-]: SETTABLEKS R0 R1 K2; var0["mTrigger"] = var1
       2 [-]: LOADB R1 1   ; var1 = true
       3 [-]: RETURN R1 1  ; 


; Name:            
; Defined at line: 1470
; #Upvalues:       2
; #Parameters:     0
; Is_vararg:       0
; Max Stack Size:  2

       0 [-]: GETUPVAL R0 0; var0 = upvalues[0]
       1 [-]: JUMPIF R0 L1 ; goto L1 if var0
       2 [-]: GETUPVAL R1 1; var1 = upvalues[1]
       3 [-]: FASTCALL1 64 R1 L0; 
       4 [-]: GETIMPORT R0 1; var0 = 0x7B998233
       5 [-]: CALL R0 2 2  ; var0 = var0(var1)
L 0:   6 [-]: JUMPIF R0 L1 ; goto L1 if var0
       7 [-]: GETUPVAL R0 1; var0 = upvalues[1]
       8 [-]: NAMECALL R0 R0 K2; var1 = var0; var0 = var0[0x8B24CE41]
       9 [-]: CALL R0 2 1  ; var0(var1)
L 1:  10 [-]: RETURN R0 0  ; 


; Name:            
; Defined at line: 1478
; #Upvalues:       1
; #Parameters:     1
; Is_vararg:       0
; Max Stack Size:  5

       0 [-]: GETUPVAL R2 0; var2 = upvalues[0]
       1 [-]: FASTCALL1 64 R2 L0; 
       2 [-]: GETIMPORT R1 1; var1 = 0x7B998233
       3 [-]: CALL R1 2 2  ; var1 = var1(var2)
L 0:   4 [-]: JUMPIF R1 L2 ; goto L2 if var1
       5 [-]: GETUPVAL R1 0; var1 = upvalues[0]
       6 [-]: FASTCALL1 62 R0 L1; 
       7 [-]: MOVE R4 R0   ; var4 = var0
       8 [-]: GETIMPORT R3 3; var3 = 0x03F57322
       9 [-]: CALL R3 2 2  ; var3 = var3(var4)
L 1:  10 [-]: NAMECALL R1 R1 K4; var2 = var1; var1 = var1[0xDF42446E]
      11 [-]: CALL R1 3 1  ; var1(var2, var3)
L 2:  12 [-]: RETURN R0 0  ; 


; Name:            
; Defined at line: 1484
; #Upvalues:       2
; #Parameters:     1
; Is_vararg:       0
; Max Stack Size:  5

       0 [-]: GETUPVAL R1 0; var1 = upvalues[0]
       1 [-]: JUMPIF R1 L2 ; goto L2 if var1
       2 [-]: GETUPVAL R2 1; var2 = upvalues[1]
       3 [-]: FASTCALL1 64 R2 L0; 
       4 [-]: GETIMPORT R1 1; var1 = 0x7B998233
       5 [-]: CALL R1 2 2  ; var1 = var1(var2)
L 0:   6 [-]: JUMPIF R1 L2 ; goto L2 if var1
       7 [-]: GETUPVAL R1 1; var1 = upvalues[1]
       8 [-]: FASTCALL1 62 R0 L1; 
       9 [-]: MOVE R4 R0   ; var4 = var0
      10 [-]: GETIMPORT R3 3; var3 = 0x03F57322
      11 [-]: CALL R3 2 2  ; var3 = var3(var4)
L 1:  12 [-]: NAMECALL R1 R1 K4; var2 = var1; var1 = var1[0xBCE5A201]
      13 [-]: CALL R1 3 1  ; var1(var2, var3)
L 2:  14 [-]: RETURN R0 0  ; 


; Name:            
; Defined at line: 1490
; #Upvalues:       2
; #Parameters:     1
; Is_vararg:       0
; Max Stack Size:  5

       0 [-]: GETUPVAL R1 0; var1 = upvalues[0]
       1 [-]: JUMPIF R1 L2 ; goto L2 if var1
       2 [-]: GETUPVAL R2 1; var2 = upvalues[1]
       3 [-]: FASTCALL1 64 R2 L0; 
       4 [-]: GETIMPORT R1 1; var1 = 0x7B998233
       5 [-]: CALL R1 2 2  ; var1 = var1(var2)
L 0:   6 [-]: JUMPIF R1 L2 ; goto L2 if var1
       7 [-]: GETUPVAL R1 1; var1 = upvalues[1]
       8 [-]: FASTCALL1 62 R0 L1; 
       9 [-]: MOVE R4 R0   ; var4 = var0
      10 [-]: GETIMPORT R3 3; var3 = 0x03F57322
      11 [-]: CALL R3 2 2  ; var3 = var3(var4)
L 1:  12 [-]: LOADB R4 1   ; var4 = true
      13 [-]: NAMECALL R1 R1 K4; var2 = var1; var1 = var1[0x070DAA5A]
      14 [-]: CALL R1 4 1  ; var1(var2, var3, var4)
L 2:  15 [-]: RETURN R0 0  ; 


; Name:            
; Defined at line: 1496
; #Upvalues:       1
; #Parameters:     0
; Is_vararg:       0
; Max Stack Size:  1

       0 [-]: GETUPVAL R0 0; var0 = upvalues[0]
       1 [-]: CALL R0 1 1  ; var0()
       2 [-]: LOADB R0 1   ; var0 = true
       3 [-]: RETURN R0 1  ; 


; Name:            
; Defined at line: 1501
; #Upvalues:       1
; #Parameters:     0
; Is_vararg:       0
; Max Stack Size:  3

       0 [-]: GETUPVAL R1 0; var1 = upvalues[0]
       1 [-]: GETTABLEKS R0 R1 K0; var0 = var1[0x659D451F]
       2 [-]: GETIMPORT R2 2; var2 = 0x0032441C
       3 [-]: GETTABLEKS R1 R2 K3; var1 = var2["UISound_Focus"]
       4 [-]: CALL R0 2 1  ; var0(var1)
       5 [-]: RETURN R0 0  ; 


; Name:            
; Defined at line: 1505
; #Upvalues:       0
; #Parameters:     2
; Is_vararg:       0
; Max Stack Size:  2

       0 [-]: RETURN R0 0  ; 


; Name:            
; Defined at line: 1508
; #Upvalues:       2
; #Parameters:     0
; Is_vararg:       0
; Max Stack Size:  3

       0 [-]: GETUPVAL R0 0; var0 = upvalues[0]
       1 [-]: JUMPIF R0 L0 ; goto L0 if var0
       2 [-]: GETUPVAL R0 1; var0 = upvalues[1]
       3 [-]: JUMPXEQKNIL R0 L0; 
       4 [-]: GETUPVAL R0 1; var0 = upvalues[1]
       5 [-]: NAMECALL R0 R0 K0; var1 = var0; var0 = var0[0xED1AB921]
       6 [-]: CALL R0 2 2  ; var0 = var0(var1)
       7 [-]: JUMPXEQKNIL R0 L0; 
       8 [-]: GETUPVAL R1 1; var1 = upvalues[1]
       9 [-]: NAMECALL R1 R1 K0; var2 = var1; var1 = var1[0xED1AB921]
      10 [-]: CALL R1 2 2  ; var1 = var1(var2)
      11 [-]: GETTABLEKS R0 R1 K1; var0 = var1["mMakePrimaryBtn"]
      12 [-]: JUMPXEQKNIL R0 L0; 
      13 [-]: GETUPVAL R1 1; var1 = upvalues[1]
      14 [-]: NAMECALL R1 R1 K0; var2 = var1; var1 = var1[0xED1AB921]
      15 [-]: CALL R1 2 2  ; var1 = var1(var2)
      16 [-]: GETTABLEKS R0 R1 K1; var0 = var1["mMakePrimaryBtn"]
      17 [-]: NAMECALL R0 R0 K2; var1 = var0; var0 = var0[0xDB2B9A70]
      18 [-]: CALL R0 2 1  ; var0(var1)
L 0:  19 [-]: LOADB R0 1   ; var0 = true
      20 [-]: RETURN R0 1  ; 


; Name:            
; Defined at line: 1515
; #Upvalues:       1
; #Parameters:     0
; Is_vararg:       0
; Max Stack Size:  1

       0 [-]: GETUPVAL R0 0; var0 = upvalues[0]
       1 [-]: RETURN R0 1  ; 


; Name:            
; Defined at line: 1519
; #Upvalues:       5
; #Parameters:     1
; Is_vararg:       0
; Max Stack Size:  8

       0 [-]: GETUPVAL R1 0; var1 = upvalues[0]
       1 [-]: JUMPIF R1 L7 ; goto L7 if var1
       2 [-]: GETUPVAL R1 1; var1 = upvalues[1]
       3 [-]: GETUPVAL R3 2; var3 = upvalues[2]
       4 [-]: GETTABLEKS R2 R3 K0; var2 = var3["SET_PRIMARY"]
       5 [-]: FASTCALL1 62 R0 L0; 
       6 [-]: MOVE R4 R0   ; var4 = var0
       7 [-]: GETIMPORT R3 2; var3 = 0x03F57322
       8 [-]: CALL R3 2 2  ; var3 = var3(var4)
L 0:   9 [-]: CALL R1 3 2  ; var1 = var1(var2, var3)
      10 [-]: JUMPIFNOT R1 L1; goto L1 if not var1
      11 [-]: RETURN R0 0  ; 
L 1:  12 [-]: GETUPVAL R1 3; var1 = upvalues[3]
      13 [-]: FASTCALL1 62 R0 L2; 
      14 [-]: MOVE R4 R0   ; var4 = var0
      15 [-]: GETIMPORT R3 2; var3 = 0x03F57322
      16 [-]: CALL R3 2 2  ; var3 = var3(var4)
L 2:  17 [-]: NAMECALL R1 R1 K3; var2 = var1; var1 = var1[0xCA30DFB6]
      18 [-]: CALL R1 3 2  ; var1 = var1(var2, var3)
      19 [-]: JUMPXEQKNIL R1 L7; 
      20 [-]: GETTABLEKS R3 R1 K4; var3 = var1["Ability"]
      21 [-]: FASTCALL1 64 R3 L3; 
      22 [-]: GETIMPORT R2 6; var2 = 0x7B998233
      23 [-]: CALL R2 2 2  ; var2 = var2(var3)
L 3:  24 [-]: JUMPIF R2 L7 ; goto L7 if var2
      25 [-]: GETIMPORT R3 9; var3 = _T["BackgroundMovie"]
      26 [-]: FASTCALL1 64 R3 L4; 
      27 [-]: GETIMPORT R2 6; var2 = 0x7B998233
      28 [-]: CALL R2 2 2  ; var2 = var2(var3)
L 4:  29 [-]: JUMPIF R2 L5 ; goto L5 if var2
      30 [-]: GETIMPORT R2 9; var2 = _T["BackgroundMovie"]
      31 [-]: LOADK R4 K10 ; var4 = "ShowBlockingMessage"
      32 [-]: LOADK R5 K11 ; var5 = "2"
      33 [-]: NAMECALL R2 R2 K12; var3 = var2; var2 = var2[0xE4162EED]
      34 [-]: CALL R2 4 1  ; var2(var3, var4, var5)
L 5:  35 [-]: SETUPVAL R1 4; upvalues[1] = var4
      36 [-]: GETIMPORT R2 14; var2 = 0x3D106989
      37 [-]: LOADK R4 K15 ; var4 = "ActivateAbility "
      38 [-]: GETTABLEKS R6 R1 K4; var6 = var1["Ability"]
      39 [-]: NAMECALL R6 R6 K16; var7 = var6; var6 = var6[0xED4E0128]
      40 [-]: CALL R6 2 0  ; var6, ... = var6(var7)
      41 [-]: FASTCALL 63 L6; 
      42 [-]: GETIMPORT R5 18; var5 = 0x64FB1586
      43 [-]: CALL R5 0 2  ; var5 = var5(var6, ...)
L 6:  44 [-]: CONCAT R3 R4 R5; var3 = var4 .. var5
      45 [-]: CALL R2 2 1  ; var2(var3)
      46 [-]: GETIMPORT R2 20; var2 = 0x25D99D89
      47 [-]: GETTABLEKS R4 R1 K4; var4 = var1["Ability"]
      48 [-]: LOADK R5 K21 ; var5 = "FocusAbilitySet"
      49 [-]: NAMECALL R2 R2 K22; var3 = var2; var2 = var2[0x74AD30B5]
      50 [-]: CALL R2 4 1  ; var2(var3, var4, var5)
L 7:  51 [-]: RETURN R0 0  ; 


; Name:            
; Defined at line: 1538
; #Upvalues:       1
; #Parameters:     0
; Is_vararg:       0
; Max Stack Size:  6

       0 [-]: GETUPVAL R0 0; var0 = upvalues[0]
       1 [-]: JUMPXEQKNIL R0 L0; 
       2 [-]: GETIMPORT R0 1; var0 = 0xAE91E43B
       3 [-]: LOADK R2 K2  ; var2 = "SetAsPrimary"
       4 [-]: GETUPVAL R5 0; var5 = upvalues[0]
       5 [-]: GETTABLEKS R4 R5 K3; var4 = var5["mMakePrimaryBtn"]
       6 [-]: GETTABLEKS R3 R4 K4; var3 = var4["mId"]
       7 [-]: NAMECALL R0 R0 K5; var1 = var0; var0 = var0[0xE4162EED]
       8 [-]: CALL R0 4 1  ; var0(var1, var2, var3)
L 0:   9 [-]: RETURN R0 0  ; 


; Name:            
; Defined at line: 1544
; #Upvalues:       1
; #Parameters:     0
; Is_vararg:       0
; Max Stack Size:  1

       0 [-]: GETUPVAL R0 0; var0 = upvalues[0]
       1 [-]: CALL R0 1 1  ; var0()
       2 [-]: RETURN R0 0  ; 


; Name:            
; Defined at line: 1548
; #Upvalues:       5
; #Parameters:     2
; Is_vararg:       0
; Max Stack Size:  6

       0 [-]: GETIMPORT R2 2; var2 = _T["BackgroundMovie"]
       1 [-]: JUMPXEQKNIL R2 L0; 
       2 [-]: GETIMPORT R2 2; var2 = _T["BackgroundMovie"]
       3 [-]: LOADK R4 K3  ; var4 = "ShowBlockingMessage"
       4 [-]: LOADK R5 K4  ; var5 = "0"
       5 [-]: NAMECALL R2 R2 K5; var3 = var2; var2 = var2[0xE4162EED]
       6 [-]: CALL R2 4 1  ; var2(var3, var4, var5)
L 0:   7 [-]: JUMPIFNOT R0 L1; goto L1 if not var0
       8 [-]: GETUPVAL R3 0; var3 = upvalues[0]
       9 [-]: GETTABLEKS R2 R3 K6; var2 = var3[0x659D451F]
      10 [-]: GETIMPORT R3 8; var3 = 0x556BB911
      11 [-]: CALL R2 2 1  ; var2(var3)
      12 [-]: GETUPVAL R3 0; var3 = upvalues[0]
      13 [-]: GETTABLEKS R2 R3 K9; var2 = var3[0xE0CBA3CA]
      14 [-]: LOADK R3 K10 ; var3 = "/Lotus/Language/TennoWay/UnlockTreeSuccess"
      15 [-]: LOADK R4 K11 ; var4 = "SuccessReviewed"
      16 [-]: CALL R2 3 1  ; var2(var3, var4)
      17 [-]: GETUPVAL R2 1; var2 = upvalues[1]
      18 [-]: CALL R2 1 1  ; var2()
      19 [-]: GETUPVAL R3 3; var3 = upvalues[3]
      20 [-]: GETTABLEKS R2 R3 K12; var2 = var3["Polarity"]
      21 [-]: SETUPVAL R2 2; upvalues[2] = var2
      22 [-]: JUMP L2      ; goto L2
L 1:  23 [-]: GETUPVAL R3 0; var3 = upvalues[0]
      24 [-]: GETTABLEKS R2 R3 K9; var2 = var3[0xE0CBA3CA]
      25 [-]: LOADK R3 K13 ; var3 = "/Lotus/Language/Menu/Loadout_ApplyFailed"
      26 [-]: CALL R2 2 1  ; var2(var3)
      27 [-]: LOADB R2 0   ; var2 = false
      28 [-]: SETUPVAL R2 4; upvalues[2] = var4
L 2:  29 [-]: LOADNIL R2   ; var2 = nil
      30 [-]: SETUPVAL R2 3; upvalues[2] = var3
      31 [-]: RETURN R0 0  ; 


; Name:            
; Defined at line: 1569
; #Upvalues:       2
; #Parameters:     1
; Is_vararg:       0
; Max Stack Size:  5

       0 [-]: FASTCALL1 62 R0 L0; 
       1 [-]: MOVE R2 R0   ; var2 = var0
       2 [-]: GETIMPORT R1 1; var1 = 0x03F57322
       3 [-]: CALL R1 2 2  ; var1 = var1(var2)
L 0:   4 [-]: LOADN R2 4   ; var2 = 4
       5 [-]: JUMPIFNOTEQ R1 R2 L3; goto L3 if var1 ~= var828
       6 [-]: GETUPVAL R3 0; var3 = upvalues[0]
       7 [-]: GETTABLEKS R2 R3 K2; var2 = var3["Ability"]
       8 [-]: FASTCALL1 64 R2 L1; 
       9 [-]: GETIMPORT R1 4; var1 = 0x7B998233
      10 [-]: CALL R1 2 2  ; var1 = var1(var2)
L 1:  11 [-]: JUMPIF R1 L3 ; goto L3 if var1
      12 [-]: GETIMPORT R1 6; var1 = 0x25D99D89
      13 [-]: GETUPVAL R4 0; var4 = upvalues[0]
      14 [-]: GETTABLEKS R3 R4 K2; var3 = var4["Ability"]
      15 [-]: LOADK R4 K7  ; var4 = "OnTreeUnlocked"
      16 [-]: NAMECALL R1 R1 K8; var2 = var1; var1 = var1[0x37EE9D0F]
      17 [-]: CALL R1 4 1  ; var1(var2, var3, var4)
      18 [-]: GETIMPORT R1 11; var1 = _T["BackgroundMovie"]
      19 [-]: JUMPXEQKNIL R1 L2; 
      20 [-]: GETIMPORT R1 11; var1 = _T["BackgroundMovie"]
      21 [-]: LOADK R3 K12 ; var3 = "ShowBlockingMessage"
      22 [-]: LOADK R4 K13 ; var4 = "1"
      23 [-]: NAMECALL R1 R1 K14; var2 = var1; var1 = var1[0xE4162EED]
      24 [-]: CALL R1 4 1  ; var1(var2, var3, var4)
L 2:  25 [-]: LOADB R1 1   ; var1 = true
      26 [-]: SETUPVAL R1 1; upvalues[1] = var1
      27 [-]: RETURN R0 0  ; 
L 3:  28 [-]: LOADNIL R1   ; var1 = nil
      29 [-]: SETUPVAL R1 0; upvalues[1] = var0
      30 [-]: RETURN R0 0  ; 


; Name:            
; Defined at line: 1583
; #Upvalues:       4
; #Parameters:     1
; Is_vararg:       0
; Max Stack Size:  12

       0 [-]: GETUPVAL R1 0; var1 = upvalues[0]
       1 [-]: JUMPIFNOT R1 L0; goto L0 if not var1
       2 [-]: RETURN R0 0  ; 
L 0:   3 [-]: GETUPVAL R1 1; var1 = upvalues[1]
       4 [-]: FASTCALL1 62 R0 L1; 
       5 [-]: MOVE R4 R0   ; var4 = var0
       6 [-]: GETIMPORT R3 1; var3 = 0x03F57322
       7 [-]: CALL R3 2 2  ; var3 = var3(var4)
L 1:   8 [-]: NAMECALL R1 R1 K2; var2 = var1; var1 = var1[0xCA30DFB6]
       9 [-]: CALL R1 3 2  ; var1 = var1(var2, var3)
      10 [-]: FASTCALL1 64 R1 L2; 
      11 [-]: MOVE R3 R1   ; var3 = var1
      12 [-]: GETIMPORT R2 4; var2 = 0x7B998233
      13 [-]: CALL R2 2 2  ; var2 = var2(var3)
L 2:  14 [-]: JUMPIF R2 L4 ; goto L4 if var2
      15 [-]: GETTABLEKS R2 R1 K5; var2 = var1["Locked"]
      16 [-]: JUMPIFNOT R2 L4; goto L4 if not var2
      17 [-]: GETTABLEKS R2 R1 K6; var2 = var1["Ability"]
      18 [-]: NAMECALL R2 R2 K7; var3 = var2; var2 = var2[0x4E7E3738]
      19 [-]: CALL R2 2 2  ; var2 = var2(var3)
      20 [-]: GETTABLEKS R3 R1 K8; var3 = var1["XP"]
      21 [-]: JUMPIFNOTLT R3 R2 L3; goto L3 if var3 >= var656161
      22 [-]: GETIMPORT R3 10; var3 = 0xAE91E43B
      23 [-]: LOADK R5 K11 ; var5 = "/Lotus/Language/TennoWay/UnlockTreeError"
      24 [-]: LOADB R6 1   ; var6 = true
      25 [-]: DUPTABLE R7 13; 
      26 [-]: GETUPVAL R9 2; var9 = upvalues[2]
      27 [-]: GETTABLEKS R8 R9 K14; var8 = var9[0x1142C7A8]
      28 [-]: MOVE R9 R2   ; var9 = var2
      29 [-]: LOADN R10 0  ; var10 = 0
      30 [-]: CALL R8 3 2  ; var8 = var8(var9, var10)
      31 [-]: SETTABLEKS R8 R7 K12; var8["COST"] = var7
      32 [-]: NAMECALL R3 R3 K15; var4 = var3; var3 = var3[0x42B04007]
      33 [-]: CALL R3 5 2  ; var3 = var3(var4, var5, var6, var7)
      34 [-]: GETUPVAL R5 2; var5 = upvalues[2]
      35 [-]: GETTABLEKS R4 R5 K16; var4 = var5[0xE0CBA3CA]
      36 [-]: MOVE R5 R3   ; var5 = var3
      37 [-]: CALL R4 2 1  ; var4(var5)
      38 [-]: RETURN R0 0  ; 
L 3:  39 [-]: GETIMPORT R3 10; var3 = 0xAE91E43B
      40 [-]: GETTABLEKS R5 R1 K17; var5 = var1["Name"]
      41 [-]: LOADB R6 0   ; var6 = false
      42 [-]: NAMECALL R3 R3 K15; var4 = var3; var3 = var3[0x42B04007]
      43 [-]: CALL R3 4 2  ; var3 = var3(var4, var5, var6)
      44 [-]: GETIMPORT R4 10; var4 = 0xAE91E43B
      45 [-]: LOADK R6 K18 ; var6 = "/Lotus/Language/TennoWay/UnlockAbilityConfirm"
      46 [-]: LOADB R7 1   ; var7 = true
      47 [-]: DUPTABLE R8 20; 
      48 [-]: SETTABLEKS R3 R8 K19; var3["NAME"] = var8
      49 [-]: GETUPVAL R10 2; var10 = upvalues[2]
      50 [-]: GETTABLEKS R9 R10 K14; var9 = var10[0x1142C7A8]
      51 [-]: MOVE R10 R2  ; var10 = var2
      52 [-]: LOADN R11 0  ; var11 = 0
      53 [-]: CALL R9 3 2  ; var9 = var9(var10, var11)
      54 [-]: SETTABLEKS R9 R8 K12; var9["COST"] = var8
      55 [-]: NAMECALL R4 R4 K15; var5 = var4; var4 = var4[0x42B04007]
      56 [-]: CALL R4 5 2  ; var4 = var4(var5, var6, var7, var8)
      57 [-]: SETUPVAL R1 3; upvalues[1] = var3
      58 [-]: GETUPVAL R6 2; var6 = upvalues[2]
      59 [-]: GETTABLEKS R5 R6 K21; var5 = var6[0xF616A184]
      60 [-]: MOVE R6 R4   ; var6 = var4
      61 [-]: LOADK R7 K22 ; var7 = "OnConfirmUnlockTree"
      62 [-]: CALL R5 3 1  ; var5(var6, var7)
L 4:  63 [-]: RETURN R0 0  ; 


; Name:            
; Defined at line: 1607
; #Upvalues:       2
; #Parameters:     0
; Is_vararg:       0
; Max Stack Size:  7

       0 [-]: GETIMPORT R0 1; var0 = 0xAE91E43B
       1 [-]: LOADK R2 K2  ; var2 = "DrifterClick.Label.text"
       2 [-]: GETUPVAL R4 0; var4 = upvalues[0]
       3 [-]: GETTABLEKS R3 R4 K3; var3 = var4[0x06D055F9]
       4 [-]: GETUPVAL R4 1; var4 = upvalues[1]
       5 [-]: LOADK R5 K4  ; var5 = "/Lotus/Language/Labels/NewWarOperatorChild"
       6 [-]: LOADK R6 K5  ; var6 = "/Lotus/Language/Labels/NewWarOperatorAdult"
       7 [-]: CALL R3 4 0  ; var3, ... = var3(var4, var5, var6)
       8 [-]: NAMECALL R0 R0 K6; var1 = var0; var0 = var0[0x20B98DB3]
       9 [-]: CALL R0 0 1  ; var0(var1, ...)
      10 [-]: RETURN R0 0  ; 


; Name:            
; Defined at line: 1611
; #Upvalues:       2
; #Parameters:     0
; Is_vararg:       0
; Max Stack Size:  8

       0 [-]: GETUPVAL R1 0; var1 = upvalues[0]
       1 [-]: GETTABLEKS R0 R1 K0; var0 = var1[0x659D451F]
       2 [-]: GETIMPORT R2 2; var2 = 0x0032441C
       3 [-]: GETTABLEKS R1 R2 K3; var1 = var2["UISound_Focus"]
       4 [-]: CALL R0 2 1  ; var0(var1)
       5 [-]: GETUPVAL R0 1; var0 = upvalues[1]
       6 [-]: CALL R0 1 1  ; var0()
       7 [-]: GETIMPORT R0 5; var0 = 0x25312C9B
       8 [-]: GETIMPORT R1 7; var1 = 0xAE91E43B
       9 [-]: LOADK R2 K8  ; var2 = "DrifterClick.DrifterHands"
      10 [-]: LOADN R3 2   ; var3 = 2
      11 [-]: NEWTABLE R4 0 2; var4 = {}
      12 [-]: LOADN R5 5   ; var5 = 5
      13 [-]: LOADN R6 6   ; var6 = 6
      14 [-]: SETLIST R4 R5 2 [1]; var4[1] = var5; var4[2] = var6; var4[3] = var7; 
      15 [-]: NEWTABLE R5 0 2; var5 = {}
      16 [-]: LOADN R6 110 ; var6 = 110
      17 [-]: LOADN R7 110 ; var7 = 110
      18 [-]: SETLIST R5 R6 2 [1]; var5[1] = var6; var5[2] = var7; var5[3] = var8; 
      19 [-]: LOADK R6 K9  ; var6 = 0.20000000298023224
      20 [-]: CALL R0 7 1  ; var0(var1, var2, var3, var4, var5, var6)
      21 [-]: GETIMPORT R0 5; var0 = 0x25312C9B
      22 [-]: GETIMPORT R1 7; var1 = 0xAE91E43B
      23 [-]: LOADK R2 K10 ; var2 = "DrifterClick.Label"
      24 [-]: LOADN R3 2   ; var3 = 2
      25 [-]: NEWTABLE R4 0 1; var4 = {}
      26 [-]: LOADN R5 10  ; var5 = 10
      27 [-]: SETLIST R4 R5 1 [1]; var4[1] = var5; var4[2] = var6; 
      28 [-]: NEWTABLE R5 0 1; var5 = {}
      29 [-]: LOADN R6 100 ; var6 = 100
      30 [-]: SETLIST R5 R6 1 [1]; var5[1] = var6; var5[2] = var7; 
      31 [-]: LOADK R6 K9  ; var6 = 0.20000000298023224
      32 [-]: CALL R0 7 1  ; var0(var1, var2, var3, var4, var5, var6)
      33 [-]: RETURN R0 0  ; 


; Name:            
; Defined at line: 1618
; #Upvalues:       1
; #Parameters:     0
; Is_vararg:       0
; Max Stack Size:  8

       0 [-]: GETUPVAL R1 0; var1 = upvalues[0]
       1 [-]: GETTABLEKS R0 R1 K0; var0 = var1[0x659D451F]
       2 [-]: GETIMPORT R2 2; var2 = 0x0032441C
       3 [-]: GETTABLEKS R1 R2 K3; var1 = var2["UISound_Focus"]
       4 [-]: CALL R0 2 1  ; var0(var1)
       5 [-]: GETIMPORT R0 5; var0 = 0x25312C9B
       6 [-]: GETIMPORT R1 7; var1 = 0xAE91E43B
       7 [-]: LOADK R2 K8  ; var2 = "DrifterClick.DrifterHands"
       8 [-]: LOADN R3 2   ; var3 = 2
       9 [-]: NEWTABLE R4 0 2; var4 = {}
      10 [-]: LOADN R5 5   ; var5 = 5
      11 [-]: LOADN R6 6   ; var6 = 6
      12 [-]: SETLIST R4 R5 2 [1]; var4[1] = var5; var4[2] = var6; var4[3] = var7; 
      13 [-]: NEWTABLE R5 0 2; var5 = {}
      14 [-]: LOADN R6 100 ; var6 = 100
      15 [-]: LOADN R7 100 ; var7 = 100
      16 [-]: SETLIST R5 R6 2 [1]; var5[1] = var6; var5[2] = var7; var5[3] = var8; 
      17 [-]: LOADK R6 K9  ; var6 = 0.20000000298023224
      18 [-]: CALL R0 7 1  ; var0(var1, var2, var3, var4, var5, var6)
      19 [-]: GETIMPORT R0 5; var0 = 0x25312C9B
      20 [-]: GETIMPORT R1 7; var1 = 0xAE91E43B
      21 [-]: LOADK R2 K10 ; var2 = "DrifterClick.Label"
      22 [-]: LOADN R3 2   ; var3 = 2
      23 [-]: NEWTABLE R4 0 1; var4 = {}
      24 [-]: LOADN R5 10  ; var5 = 10
      25 [-]: SETLIST R4 R5 1 [1]; var4[1] = var5; var4[2] = var6; 
      26 [-]: NEWTABLE R5 0 1; var5 = {}
      27 [-]: LOADN R6 0   ; var6 = 0
      28 [-]: SETLIST R5 R6 1 [1]; var5[1] = var6; var5[2] = var7; 
      29 [-]: LOADK R6 K9  ; var6 = 0.20000000298023224
      30 [-]: CALL R0 7 1  ; var0(var1, var2, var3, var4, var5, var6)
      31 [-]: RETURN R0 0  ; 


; Name:            
; Defined at line: 1624
; #Upvalues:       13
; #Parameters:     0
; Is_vararg:       0
; Max Stack Size:  19

       0 [-]: GETUPVAL R1 0; var1 = upvalues[0]
       1 [-]: NOT R0 R1    ; var0 = not var1
       2 [-]: SETUPVAL R0 0; upvalues[0] = var0
       3 [-]: GETIMPORT R0 1; var0 = 0x25D99D89
       4 [-]: NAMECALL R0 R0 K2; var1 = var0; var0 = var0[0x25A6E75E]
       5 [-]: CALL R0 2 2  ; var0 = var0(var1)
       6 [-]: GETUPVAL R1 0; var1 = upvalues[0]
       7 [-]: SETTABLEKS R1 R0 K3; var1["mUseAdultOperatorLoadout"] = var0
       8 [-]: GETIMPORT R1 1; var1 = 0x25D99D89
       9 [-]: NAMECALL R1 R1 K4; var2 = var1; var1 = var1[0x62C81B76]
      10 [-]: CALL R1 2 2  ; var1 = var1(var2)
      11 [-]: GETUPVAL R2 1; var2 = upvalues[1]
      12 [-]: JUMPIFNOT R2 L0; goto L0 if not var2
      13 [-]: GETUPVAL R3 2; var3 = upvalues[2]
      14 [-]: GETUPVAL R5 3; var5 = upvalues[3]
      15 [-]: GETTABLEKS R4 R5 K5; var4 = var5[0x06D055F9]
      16 [-]: GETUPVAL R5 0; var5 = upvalues[0]
      17 [-]: GETUPVAL R6 4; var6 = upvalues[4]
      18 [-]: GETIMPORT R7 7; var7 = ZERO_VECTOR
      19 [-]: CALL R4 4 2  ; var4 = var4(var5, var6, var7)
      20 [-]: ADD R2 R3 R4 ; var2 = var3 + var4
      21 [-]: GETUPVAL R3 5; var3 = upvalues[5]
      22 [-]: MOVE R5 R2   ; var5 = var2
      23 [-]: NAMECALL R3 R3 K8; var4 = var3; var3 = var3[0x9307AA51]
      24 [-]: CALL R3 3 1  ; var3(var4, var5)
L 0:  25 [-]: GETIMPORT R2 10; var2 = 0x89326C93
      26 [-]: NAMECALL R2 R2 K11; var3 = var2; var2 = var2[0xFB64E76C]
      27 [-]: CALL R2 2 2  ; var2 = var2(var3)
      28 [-]: NAMECALL R3 R2 K12; var4 = var2; var3 = var2[0x5578D98B]
      29 [-]: CALL R3 2 2  ; var3 = var3(var4)
      30 [-]: GETIMPORT R4 1; var4 = 0x25D99D89
      31 [-]: LOADB R6 1   ; var6 = true
      32 [-]: LOADB R7 0   ; var7 = false
      33 [-]: NAMECALL R4 R4 K13; var5 = var4; var4 = var4[0xC132E309]
      34 [-]: CALL R4 4 1  ; var4(var5, var6, var7)
      35 [-]: LOADNIL R4   ; var4 = nil
      36 [-]: GETUPVAL R5 0; var5 = upvalues[0]
      37 [-]: JUMPIFNOT R5 L1; goto L1 if not var5
      38 [-]: GETTABLEKS R4 R1 K14; var4 = var1["mAdultOperatorCustomization"]
      39 [-]: JUMP L2      ; goto L2
L 1:  40 [-]: GETTABLEKS R4 R1 K15; var4 = var1["mOperatorCustomization"]
L 2:  41 [-]: LOADNIL R5   ; var5 = nil
      42 [-]: NAMECALL R6 R4 K16; var7 = var4; var6 = var4[0x8F89D633]
      43 [-]: CALL R6 2 2  ; var6 = var6(var7)
      44 [-]: MOVE R5 R6   ; var5 = var6
      45 [-]: GETIMPORT R7 1; var7 = 0x25D99D89
      46 [-]: NAMECALL R7 R7 K4; var8 = var7; var7 = var7[0x62C81B76]
      47 [-]: CALL R7 2 2  ; var7 = var7(var8)
      48 [-]: GETTABLEKS R6 R7 K17; var6 = var7["mOperatorType"]
      49 [-]: LOADN R7 4   ; var7 = 4
      50 [-]: JUMPIFNOTEQ R6 R7 L3; goto L3 if var6 ~= var264240
      51 [-]: LOADN R8 4   ; var8 = 4
      52 [-]: NAMECALL R6 R3 K18; var7 = var3; var6 = var3[0x9563FC06]
      53 [-]: CALL R6 3 1  ; var6(var7, var8)
      54 [-]: GETIMPORT R8 20; var8 = 0xCE3DCF3A
      55 [-]: NAMECALL R6 R3 K21; var7 = var3; var6 = var3[0xED8EB7E6]
      56 [-]: CALL R6 3 1  ; var6(var7, var8)
      57 [-]: JUMP L4      ; goto L4
L 3:  58 [-]: LOADN R8 2   ; var8 = 2
      59 [-]: NAMECALL R6 R3 K18; var7 = var3; var6 = var3[0x9563FC06]
      60 [-]: CALL R6 3 1  ; var6(var7, var8)
      61 [-]: LOADNIL R8   ; var8 = nil
      62 [-]: NAMECALL R6 R3 K21; var7 = var3; var6 = var3[0xED8EB7E6]
      63 [-]: CALL R6 3 1  ; var6(var7, var8)
L 4:  64 [-]: GETIMPORT R6 23; var6 = 0x88EFC25E
      65 [-]: NAMECALL R7 R5 K24; var8 = var5; var7 = var5[0xA8C81A27]
      66 [-]: CALL R7 2 0  ; var7, ... = var7(var8)
      67 [-]: CALL R6 0 2  ; var6 = var6(var7, ...)
      68 [-]: GETIMPORT R7 10; var7 = 0x89326C93
      69 [-]: MOVE R9 R6   ; var9 = var6
      70 [-]: MOVE R10 R3  ; var10 = var3
      71 [-]: NAMECALL R7 R7 K25; var8 = var7; var7 = var7[0x765DAD71]
      72 [-]: CALL R7 4 2  ; var7 = var7(var8, var9, var10)
      73 [-]: FASTCALL1 64 R7 L5; 
      74 [-]: MOVE R9 R7   ; var9 = var7
      75 [-]: GETIMPORT R8 27; var8 = 0x7B998233
      76 [-]: CALL R8 2 2  ; var8 = var8(var9)
L 5:  77 [-]: JUMPIF R8 L8 ; goto L8 if var8
      78 [-]: NEWTABLE R8 0 10; var8 = {}
      79 [-]: LOADK R9 K28 ; var9 = "Morphs.HeadFemaleA"
      80 [-]: LOADK R10 K29; var10 = "Morphs.HeadFemaleB"
      81 [-]: LOADK R11 K30; var11 = "Morphs.HeadFemaleC"
      82 [-]: LOADK R12 K31; var12 = "Morphs.HeadFemaleD"
      83 [-]: LOADK R13 K32; var13 = "Morphs.HeadFemaleE"
      84 [-]: LOADK R14 K33; var14 = "Morphs.HeadMaleA"
      85 [-]: LOADK R15 K34; var15 = "Morphs.HeadMaleB"
      86 [-]: LOADK R16 K35; var16 = "Morphs.HeadMaleC"
      87 [-]: LOADK R17 K36; var17 = "Morphs.HeadMaleD"
      88 [-]: LOADK R18 K37; var18 = "Morphs.HeadMaleE"
      89 [-]: SETLIST R8 R9 10 [1]; var8[1] = var9; var8[2] = var10; var8[3] = var11; var8[4] = var12; var8[5] = var13; var8[6] = var14; var8[7] = var15; var8[8] = var16; var8[9] = var17; var8[10] = var18; var8[11] = var19; 
      90 [-]: GETIMPORT R9 39; var9 = 0xC8802016
      91 [-]: MOVE R10 R8  ; var10 = var8
      92 [-]: CALL R9 2 4  ; var9, var10, var11 = var9(var10)
      93 [-]: FORGPREP_INEXT R9 L7; 
L 6:  94 [-]: GETIMPORT R16 41; var16 = 0x0469F296
      95 [-]: MOVE R17 R13 ; var17 = var13
      96 [-]: CALL R16 2 2 ; var16 = var16(var17)
      97 [-]: LOADN R17 0  ; var17 = 0
      98 [-]: NAMECALL R14 R3 K42; var15 = var3; var14 = var3[0x7337A2C1]
      99 [-]: CALL R14 4 1 ; var14(var15, var16, var17)
L 7: 100 [-]: FORGLOOP R9 L6 2 [inext]; 
     101 [-]: GETTABLEKS R11 R5 K43; var11 = var5["mCustomization"]
     102 [-]: NAMECALL R9 R7 K44; var10 = var7; var9 = var7[0xAA041663]
     103 [-]: CALL R9 3 1  ; var9(var10, var11)
     104 [-]: GETUPVAL R9 6; var9 = upvalues[6]
     105 [-]: MOVE R10 R7  ; var10 = var7
     106 [-]: CALL R9 2 1  ; var9(var10)
L 8: 107 [-]: NAMECALL R8 R3 K45; var9 = var3; var8 = var3[0xDE321E6F]
     108 [-]: CALL R8 2 2  ; var8 = var8(var9)
     109 [-]: MOVE R10 R7  ; var10 = var7
     110 [-]: LOADB R11 1  ; var11 = true
     111 [-]: NAMECALL R8 R8 K46; var9 = var8; var8 = var8[0x511D26B8]
     112 [-]: CALL R8 4 1  ; var8(var9, var10, var11)
     113 [-]: GETUPVAL R8 1; var8 = upvalues[1]
     114 [-]: JUMPIFNOT R8 L9; goto L9 if not var8
     115 [-]: GETIMPORT R10 48; var10 = 0x943AE11E
     116 [-]: LOADB R11 0  ; var11 = false
     117 [-]: LOADN R12 3  ; var12 = 3
     118 [-]: LOADN R13 2  ; var13 = 2
     119 [-]: LOADB R14 1  ; var14 = true
     120 [-]: NAMECALL R8 R3 K49; var9 = var3; var8 = var3[0x5D985C7E]
     121 [-]: CALL R8 7 1  ; var8(var9, var10, var11, var12, var13, var14)
     122 [-]: JUMP L12     ; goto L12
L 9: 123 [-]: GETUPVAL R8 0; var8 = upvalues[0]
     124 [-]: JUMPIFNOT R8 L10; goto L10 if not var8
     125 [-]: NAMECALL R8 R3 K45; var9 = var3; var8 = var3[0xDE321E6F]
     126 [-]: CALL R8 2 2  ; var8 = var8(var9)
     127 [-]: LOADN R10 0  ; var10 = 0
     128 [-]: LOADN R11 2  ; var11 = 2
     129 [-]: NAMECALL R8 R8 K50; var9 = var8; var8 = var8[0x4703255B]
     130 [-]: CALL R8 4 1  ; var8(var9, var10, var11)
     131 [-]: JUMP L11     ; goto L11
L10: 132 [-]: NAMECALL R8 R3 K45; var9 = var3; var8 = var3[0xDE321E6F]
     133 [-]: CALL R8 2 2  ; var8 = var8(var9)
     134 [-]: LOADN R10 1  ; var10 = 1
     135 [-]: LOADN R11 0  ; var11 = 0
     136 [-]: LOADN R12 2  ; var12 = 2
     137 [-]: NAMECALL R8 R8 K51; var9 = var8; var8 = var8[0xC69087F6]
     138 [-]: CALL R8 5 1  ; var8(var9, var10, var11, var12)
L11: 139 [-]: LOADN R10 0  ; var10 = 0
     140 [-]: NAMECALL R8 R3 K52; var9 = var3; var8 = var3[0x2E9B92E3]
     141 [-]: CALL R8 3 1  ; var8(var9, var10)
L12: 142 [-]: GETUPVAL R8 7; var8 = upvalues[7]
     143 [-]: GETUPVAL R9 8; var9 = upvalues[8]
     144 [-]: CALL R8 2 1  ; var8(var9)
     145 [-]: GETUPVAL R8 9; var8 = upvalues[9]
     146 [-]: CALL R8 1 1  ; var8()
     147 [-]: LOADB R8 0   ; var8 = false
     148 [-]: SETUPVAL R8 10; upvalues[8] = var10
     149 [-]: GETUPVAL R8 11; var8 = upvalues[11]
     150 [-]: LOADK R10 K53; var10 = 0.20000000298023224
     151 [-]: DUPCLOSURE R11 K54; 
     152 [-]: CAPTURE UPVAL U12; 
     153 [-]: NAMECALL R8 R8 K55; var9 = var8; var8 = var8[0xBD2E96EA]
     154 [-]: CALL R8 4 1  ; var8(var9, var10, var11)
     155 [-]: RETURN R0 0  ; 


; Name:            
; Defined at line: 1692
; #Upvalues:       4
; #Parameters:     0
; Is_vararg:       0
; Max Stack Size:  7

       0 [-]: GETUPVAL R0 0; var0 = upvalues[0]
       1 [-]: JUMPIFNOT R0 L0; goto L0 if not var0
       2 [-]: RETURN R0 0  ; 
L 0:   3 [-]: GETIMPORT R0 1; var0 = 0x89326C93
       4 [-]: NAMECALL R0 R0 K2; var1 = var0; var0 = var0[0xFB64E76C]
       5 [-]: CALL R0 2 2  ; var0 = var0(var1)
       6 [-]: FASTCALL1 64 R0 L1; 
       7 [-]: MOVE R2 R0   ; var2 = var0
       8 [-]: GETIMPORT R1 4; var1 = 0x7B998233
       9 [-]: CALL R1 2 2  ; var1 = var1(var2)
L 1:  10 [-]: JUMPIF R1 L3 ; goto L3 if var1
      11 [-]: NAMECALL R2 R0 K5; var3 = var0; var2 = var0[0x5578D98B]
      12 [-]: CALL R2 2 0  ; var2, ... = var2(var3)
      13 [-]: FASTCALL 64 L2; 
      14 [-]: GETIMPORT R1 4; var1 = 0x7B998233
      15 [-]: CALL R1 0 2  ; var1 = var1(var2, ...)
L 2:  16 [-]: JUMPIFNOT R1 L4; goto L4 if not var1
L 3:  17 [-]: RETURN R0 0  ; 
L 4:  18 [-]: GETUPVAL R2 1; var2 = upvalues[1]
      19 [-]: GETTABLEKS R1 R2 K6; var1 = var2[0x659D451F]
      20 [-]: GETIMPORT R3 8; var3 = 0x0032441C
      21 [-]: GETTABLEKS R2 R3 K9; var2 = var3["UISound_Select"]
      22 [-]: CALL R1 2 1  ; var1(var2)
      23 [-]: GETUPVAL R2 1; var2 = upvalues[1]
      24 [-]: GETTABLEKS R1 R2 K10; var1 = var2[0xF76783E5]
      25 [-]: GETIMPORT R2 12; var2 = 0xAE91E43B
      26 [-]: LOADK R3 K13 ; var3 = "DrifterClick.DrifterHands"
      27 [-]: GETIMPORT R4 15; var4 = 0x3F921E6B
      28 [-]: LOADN R5 0   ; var5 = 0
      29 [-]: LOADN R6 0   ; var6 = 0
      30 [-]: CALL R1 6 1  ; var1(var2, var3, var4, var5, var6)
      31 [-]: LOADB R1 1   ; var1 = true
      32 [-]: SETUPVAL R1 0; upvalues[1] = var0
      33 [-]: GETUPVAL R1 2; var1 = upvalues[2]
      34 [-]: LOADB R2 1   ; var2 = true
      35 [-]: SETTABLEKS R2 R1 K16; var2["Dissolving"] = var1
      36 [-]: GETUPVAL R1 2; var1 = upvalues[2]
      37 [-]: LOADN R2 1   ; var2 = 1
      38 [-]: SETTABLEKS R2 R1 K17; var2["DissolveDir"] = var1
      39 [-]: GETUPVAL R1 2; var1 = upvalues[2]
      40 [-]: LOADN R2 0   ; var2 = 0
      41 [-]: SETTABLEKS R2 R1 K18; var2["DissolveVal"] = var1
      42 [-]: GETUPVAL R1 3; var1 = upvalues[3]
      43 [-]: GETUPVAL R4 3; var4 = upvalues[3]
      44 [-]: GETTABLEKS R3 R4 K19; var3 = var4["UpdateFX"]
      45 [-]: NAMECALL R1 R1 K20; var2 = var1; var1 = var1[0xEA061E98]
      46 [-]: CALL R1 3 1  ; var1(var2, var3)
      47 [-]: GETUPVAL R1 3; var1 = upvalues[3]
      48 [-]: LOADB R3 1   ; var3 = true
      49 [-]: LOADB R4 1   ; var4 = true
      50 [-]: NAMECALL R1 R1 K21; var2 = var1; var1 = var1[0x7C09C373]
      51 [-]: CALL R1 4 1  ; var1(var2, var3, var4)
      52 [-]: RETURN R0 0  ; 


; Name:            
; Defined at line: 1714
; #Upvalues:       3
; #Parameters:     2
; Is_vararg:       0
; Max Stack Size:  6

       0 [-]: LOADB R2 1   ; var2 = true
       1 [-]: SETUPVAL R2 0; upvalues[2] = var0
       2 [-]: GETIMPORT R3 2; var3 = _T["BackgroundMovie"]
       3 [-]: FASTCALL1 64 R3 L0; 
       4 [-]: GETIMPORT R2 4; var2 = 0x7B998233
       5 [-]: CALL R2 2 2  ; var2 = var2(var3)
L 0:   6 [-]: JUMPIF R2 L1 ; goto L1 if var2
       7 [-]: GETIMPORT R2 2; var2 = _T["BackgroundMovie"]
       8 [-]: LOADK R4 K5  ; var4 = "ShowBlockingMessage"
       9 [-]: LOADK R5 K6  ; var5 = "0"
      10 [-]: NAMECALL R2 R2 K7; var3 = var2; var2 = var2[0xE4162EED]
      11 [-]: CALL R2 4 1  ; var2(var3, var4, var5)
L 1:  12 [-]: GETUPVAL R2 1; var2 = upvalues[1]
      13 [-]: GETUPVAL R3 2; var3 = upvalues[2]
      14 [-]: CALL R2 2 1  ; var2(var3)
      15 [-]: RETURN R0 0  ; 


; Name:            
; Defined at line: 1723
; #Upvalues:       1
; #Parameters:     0
; Is_vararg:       0
; Max Stack Size:  1

       0 [-]: GETUPVAL R0 0; var0 = upvalues[0]
       1 [-]: CALL R0 1 1  ; var0()
       2 [-]: RETURN R0 0  ; 


; Name:            
; Defined at line: 1727
; #Upvalues:       0
; #Parameters:     0
; Is_vararg:       0
; Max Stack Size:  1

       0 [-]: LOADB R0 1   ; var0 = true
       1 [-]: RETURN R0 1  ; 


; Name:            
; Defined at line: 1731
; #Upvalues:       0
; #Parameters:     1
; Is_vararg:       0
; Max Stack Size:  9

       0 [-]: JUMPXEQKS R0 K0 L0 NOT; 
       1 [-]: GETIMPORT R1 2; var1 = 0x25312C9B
       2 [-]: GETIMPORT R2 4; var2 = 0xAE91E43B
       3 [-]: LOADK R3 K5  ; var3 = "_root"
       4 [-]: LOADN R4 0   ; var4 = 0
       5 [-]: NEWTABLE R5 0 1; var5 = {}
       6 [-]: LOADN R6 10  ; var6 = 10
       7 [-]: SETLIST R5 R6 1 [1]; var5[1] = var6; var5[2] = var7; 
       8 [-]: NEWTABLE R6 0 1; var6 = {}
       9 [-]: LOADN R7 0   ; var7 = 0
      10 [-]: SETLIST R6 R7 1 [1]; var6[1] = var7; var6[2] = var8; 
      11 [-]: LOADK R7 K6  ; var7 = 0.15000000596046448
      12 [-]: LOADN R8 0   ; var8 = 0
      13 [-]: CALL R1 8 1  ; var1(var2, var3, var4, var5, var6, var7, var8)
      14 [-]: RETURN R0 0  ; 
L 0:  15 [-]: GETIMPORT R1 2; var1 = 0x25312C9B
      16 [-]: GETIMPORT R2 4; var2 = 0xAE91E43B
      17 [-]: LOADK R3 K5  ; var3 = "_root"
      18 [-]: LOADN R4 2   ; var4 = 2
      19 [-]: NEWTABLE R5 0 1; var5 = {}
      20 [-]: LOADN R6 10  ; var6 = 10
      21 [-]: SETLIST R5 R6 1 [1]; var5[1] = var6; var5[2] = var7; 
      22 [-]: NEWTABLE R6 0 1; var6 = {}
      23 [-]: LOADN R7 100 ; var7 = 100
      24 [-]: SETLIST R6 R7 1 [1]; var6[1] = var7; var6[2] = var8; 
      25 [-]: LOADK R7 K6  ; var7 = 0.15000000596046448
      26 [-]: LOADN R8 0   ; var8 = 0
      27 [-]: CALL R1 8 1  ; var1(var2, var3, var4, var5, var6, var7, var8)
      28 [-]: RETURN R0 0  ; 



