; This file has been disassembled using luadec 2.0.2 by sztupy (modified by Reversive)

; Name:            
; Defined at line: 0
; #Upvalues:       0
; #Parameters:     0
; Is_vararg:       2
; Max Stack Size:  64

  1 [-]: GETGLOBAL R0 K0        ; R0 := 0x2d0fad09
  2 [-]: LOADK     R1 K1        ; R1 := "EE.Interface.Utilities"
  3 [-]: CALL      R0 2 2       ; R0 := R0(R1)
  4 [-]: GETGLOBAL R1 K0        ; R1 := 0x2d0fad09
  5 [-]: LOADK     R2 K2        ; R2 := "Lotus.Interface.UIUtilities"
  6 [-]: CALL      R1 2 2       ; R1 := R1(R2)
  7 [-]: GETGLOBAL R2 K0        ; R2 := 0x2d0fad09
  8 [-]: LOADK     R3 K3        ; R3 := "Lotus.Interface.LotusUtilities"
  9 [-]: CALL      R2 2 2       ; R2 := R2(R3)
 10 [-]: GETGLOBAL R3 K0        ; R3 := 0x2d0fad09
 11 [-]: LOADK     R4 K4        ; R4 := "Lotus.Interface.UIStyleUtilities"
 12 [-]: CALL      R3 2 2       ; R3 := R3(R4)
 13 [-]: GETGLOBAL R4 K0        ; R4 := 0x2d0fad09
 14 [-]: LOADK     R5 K5        ; R5 := "Lotus.Interface.Components.ThemedButton"
 15 [-]: CALL      R4 2 2       ; R4 := R4(R5)
 16 [-]: LOADNIL   R5 R6        ; R5 := R6 := nil
 17 [-]: LOADBOOL  R7 0 0       ; R7 := false
 18 [-]: LOADBOOL  R8 1 0       ; R8 := true
 19 [-]: LOADNIL   R9 R9        ; R9 := nil
 20 [-]: LOADK     R10 0        ; R10 := 0.000000
 21 [-]: LOADNIL   R11 R11      ; R11 := nil
 22 [-]: LOADBOOL  R12 1 0      ; R12 := true
 23 [-]: LOADBOOL  R13 1 0      ; R13 := true
 24 [-]: LOADNIL   R14 R16      ; R14 := R15 := R16 := nil
 25 [-]: NEWTABLE  R17 0 0      ; R17 := {}
 26 [-]: LOADK     R18 0        ; R18 := 0.000000
 27 [-]: LOADK     R19 0        ; R19 := 0.000000
 28 [-]: LOADNIL   R20 R20      ; R20 := nil
 29 [-]: LOADK     R21 K6       ; R21 := "Middle"
 30 [-]: LOADNIL   R22 R23      ; R22 := R23 := nil
 31 [-]: LOADK     R24 404      ; R24 := 404.000000
 32 [-]: LOADK     R25 0        ; R25 := 0.000000
 33 [-]: LOADK     R26 20       ; R26 := 20.000000
 34 [-]: LOADK     R27 22       ; R27 := 22.000000
 35 [-]: LOADK     R28 500      ; R28 := 500.000000
 36 [-]: LOADBOOL  R29 1 0      ; R29 := true
 37 [-]: LOADBOOL  R30 0 0      ; R30 := false
 38 [-]: LOADBOOL  R31 0 0      ; R31 := false
 39 [-]: LOADNIL   R32 R32      ; R32 := nil
 40 [-]: LOADK     R33 0        ; R33 := 0.000000
 41 [-]: LOADBOOL  R34 0 0      ; R34 := false
 42 [-]: LOADBOOL  R35 0 0      ; R35 := false
 43 [-]: LOADNIL   R36 R36      ; R36 := nil
 44 [-]: LOADK     R37 K7       ; R37 := 0.950000
 45 [-]: LOADK     R38 K8       ; R38 := 0.200000
 46 [-]: LOADK     R39 K8       ; R39 := 0.200000
 47 [-]: LOADK     R40 K8       ; R40 := 0.200000
 48 [-]: LOADK     R41 K8       ; R41 := 0.200000
 49 [-]: LOADBOOL  R42 0 0      ; R42 := false
 50 [-]: LOADK     R43 0        ; R43 := 0.000000
 51 [-]: LOADNIL   R44 R48      ; R44 := R45 := R46 := R47 := R48 := nil
 52 [-]: LOADBOOL  R49 0 0      ; R49 := false
 53 [-]: CLOSURE   R50 0        ; R50 := closure(Function #1)
 54 [-]: MOVE      R0 R49       ; R0 := R49
 55 [-]: MOVE      R0 R35       ; R0 := R35
 56 [-]: MOVE      R0 R15       ; R0 := R15
 57 [-]: MOVE      R0 R17       ; R0 := R17
 58 [-]: SETGLOBAL R50 K9       ; Shutdown := R50
 59 [-]: CLOSURE   R50 1        ; R50 := closure(Function #2)
 60 [-]: MOVE      R0 R8        ; R0 := R8
 61 [-]: MOVE      R0 R34       ; R0 := R34
 62 [-]: MOVE      R0 R42       ; R0 := R42
 63 [-]: MOVE      R0 R15       ; R0 := R15
 64 [-]: MOVE      R0 R35       ; R0 := R35
 65 [-]: MOVE      R0 R17       ; R0 := R17
 66 [-]: MOVE      R0 R39       ; R0 := R39
 67 [-]: MOVE      R0 R37       ; R0 := R37
 68 [-]: MOVE      R0 R41       ; R0 := R41
 69 [-]: MOVE      R0 R36       ; R0 := R36
 70 [-]: MOVE      R0 R9        ; R0 := R9
 71 [-]: CLOSURE   R51 2        ; R51 := closure(Function #3)
 72 [-]: MOVE      R0 R50       ; R0 := R50
 73 [-]: SETGLOBAL R51 K10      ; TransitionOut := R51
 74 [-]: CLOSURE   R51 3        ; R51 := closure(Function #4)
 75 [-]: MOVE      R0 R0        ; R0 := R0
 76 [-]: MOVE      R0 R50       ; R0 := R50
 77 [-]: CLOSURE   R52 4        ; R52 := closure(Function #5)
 78 [-]: MOVE      R0 R0        ; R0 := R0
 79 [-]: MOVE      R0 R5        ; R0 := R5
 80 [-]: CLOSURE   R53 5        ; R53 := closure(Function #6)
 81 [-]: MOVE      R0 R3        ; R0 := R3
 82 [-]: MOVE      R0 R0        ; R0 := R0
 83 [-]: MOVE      R0 R9        ; R0 := R9
 84 [-]: CLOSURE   R54 6        ; R54 := closure(Function #7)
 85 [-]: MOVE      R0 R22       ; R0 := R22
 86 [-]: MOVE      R0 R9        ; R0 := R9
 87 [-]: MOVE      R0 R29       ; R0 := R29
 88 [-]: MOVE      R0 R51       ; R0 := R51
 89 [-]: CLOSURE   R55 7        ; R55 := closure(Function #8)
 90 [-]: MOVE      R0 R54       ; R0 := R54
 91 [-]: SETGLOBAL R55 K11      ; UpdateButtons := R55
 92 [-]: CLOSURE   R55 8        ; R55 := closure(Function #9)
 93 [-]: MOVE      R0 R17       ; R0 := R17
 94 [-]: MOVE      R0 R9        ; R0 := R9
 95 [-]: MOVE      R0 R50       ; R0 := R50
 96 [-]: CLOSURE   R56 9        ; R56 := closure(Function #10)
 97 [-]: MOVE      R0 R55       ; R0 := R55
 98 [-]: MOVE      R0 R9        ; R0 := R9
 99 [-]: SETGLOBAL R56 K12      ; ConfirmSelection := R56
100 [-]: CLOSURE   R56 10       ; R56 := closure(Function #11)
101 [-]: MOVE      R0 R36       ; R0 := R36
102 [-]: MOVE      R0 R0        ; R0 := R0
103 [-]: MOVE      R0 R55       ; R0 := R55
104 [-]: CLOSURE   R57 11       ; R57 := closure(Function #12)
105 [-]: MOVE      R0 R9        ; R0 := R9
106 [-]: MOVE      R0 R0        ; R0 := R0
107 [-]: MOVE      R0 R30       ; R0 := R30
108 [-]: MOVE      R0 R8        ; R0 := R8
109 [-]: MOVE      R0 R47       ; R0 := R47
110 [-]: MOVE      R0 R20       ; R0 := R20
111 [-]: MOVE      R0 R24       ; R0 := R24
112 [-]: MOVE      R0 R45       ; R0 := R45
113 [-]: MOVE      R0 R46       ; R0 := R46
114 [-]: MOVE      R0 R23       ; R0 := R23
115 [-]: MOVE      R0 R18       ; R0 := R18
116 [-]: MOVE      R0 R36       ; R0 := R36
117 [-]: MOVE      R0 R56       ; R0 := R56
118 [-]: MOVE      R0 R48       ; R0 := R48
119 [-]: MOVE      R0 R43       ; R0 := R43
120 [-]: MOVE      R0 R13       ; R0 := R13
121 [-]: MOVE      R0 R4        ; R0 := R4
122 [-]: MOVE      R0 R2        ; R0 := R2
123 [-]: MOVE      R0 R3        ; R0 := R3
124 [-]: CLOSURE   R58 12       ; R58 := closure(Function #13)
125 [-]: MOVE      R0 R25       ; R0 := R25
126 [-]: MOVE      R0 R24       ; R0 := R24
127 [-]: MOVE      R0 R9        ; R0 := R9
128 [-]: MOVE      R0 R27       ; R0 := R27
129 [-]: MOVE      R0 R26       ; R0 := R26
130 [-]: MOVE      R0 R1        ; R0 := R1
131 [-]: MOVE      R0 R44       ; R0 := R44
132 [-]: CLOSURE   R59 13       ; R59 := closure(Function #14)
133 [-]: MOVE      R0 R7        ; R0 := R7
134 [-]: MOVE      R0 R6        ; R0 := R6
135 [-]: MOVE      R0 R9        ; R0 := R9
136 [-]: SETGLOBAL R59 K13      ; Update := R59
137 [-]: CLOSURE   R59 14       ; R59 := closure(Function #15)
138 [-]: MOVE      R0 R14       ; R0 := R14
139 [-]: MOVE      R0 R19       ; R0 := R19
140 [-]: MOVE      R0 R6        ; R0 := R6
141 [-]: MOVE      R0 R2        ; R0 := R2
142 [-]: MOVE      R0 R50       ; R0 := R50
143 [-]: CLOSURE   R60 15       ; R60 := closure(Function #16)
144 [-]: MOVE      R0 R59       ; R0 := R59
145 [-]: MOVE      R0 R60       ; R0 := R60
146 [-]: MOVE      R0 R14       ; R0 := R14
147 [-]: MOVE      R0 R9        ; R0 := R9
148 [-]: CLOSURE   R61 16       ; R61 := closure(Function #17)
149 [-]: MOVE      R0 R60       ; R0 := R60
150 [-]: SETGLOBAL R61 K14      ; UpdateComponents := R61
151 [-]: CLOSURE   R61 17       ; R61 := closure(Function #18)
152 [-]: MOVE      R0 R44       ; R0 := R44
153 [-]: MOVE      R0 R9        ; R0 := R9
154 [-]: MOVE      R0 R0        ; R0 := R0
155 [-]: CLOSURE   R62 18       ; R62 := closure(Function #19)
156 [-]: MOVE      R0 R59       ; R0 := R59
157 [-]: MOVE      R0 R62       ; R0 := R62
158 [-]: MOVE      R0 R14       ; R0 := R14
159 [-]: MOVE      R0 R9        ; R0 := R9
160 [-]: MOVE      R0 R50       ; R0 := R50
161 [-]: MOVE      R0 R54       ; R0 := R54
162 [-]: MOVE      R0 R44       ; R0 := R44
163 [-]: MOVE      R0 R0        ; R0 := R0
164 [-]: MOVE      R0 R24       ; R0 := R24
165 [-]: MOVE      R0 R30       ; R0 := R30
166 [-]: MOVE      R0 R25       ; R0 := R25
167 [-]: MOVE      R0 R58       ; R0 := R58
168 [-]: MOVE      R0 R27       ; R0 := R27
169 [-]: MOVE      R0 R43       ; R0 := R43
170 [-]: MOVE      R0 R2        ; R0 := R2
171 [-]: MOVE      R0 R11       ; R0 := R11
172 [-]: MOVE      R0 R28       ; R0 := R28
173 [-]: MOVE      R0 R33       ; R0 := R33
174 [-]: MOVE      R0 R21       ; R0 := R21
175 [-]: MOVE      R0 R52       ; R0 := R52
176 [-]: MOVE      R0 R10       ; R0 := R10
177 [-]: MOVE      R0 R32       ; R0 := R32
178 [-]: MOVE      R0 R8        ; R0 := R8
179 [-]: MOVE      R0 R38       ; R0 := R38
180 [-]: CLOSURE   R63 19       ; R63 := closure(Function #20)
181 [-]: MOVE      R0 R6        ; R0 := R6
182 [-]: MOVE      R0 R0        ; R0 := R0
183 [-]: MOVE      R0 R49       ; R0 := R49
184 [-]: MOVE      R0 R5        ; R0 := R5
185 [-]: MOVE      R0 R10       ; R0 := R10
186 [-]: MOVE      R0 R30       ; R0 := R30
187 [-]: MOVE      R0 R27       ; R0 := R27
188 [-]: MOVE      R0 R24       ; R0 := R24
189 [-]: MOVE      R0 R57       ; R0 := R57
190 [-]: MOVE      R0 R37       ; R0 := R37
191 [-]: MOVE      R0 R40       ; R0 := R40
192 [-]: MOVE      R0 R62       ; R0 := R62
193 [-]: MOVE      R0 R54       ; R0 := R54
194 [-]: MOVE      R0 R53       ; R0 := R53
195 [-]: MOVE      R0 R52       ; R0 := R52
196 [-]: MOVE      R0 R7        ; R0 := R7
197 [-]: SETGLOBAL R63 K15      ; Initialize := R63
198 [-]: CLOSURE   R63 20       ; R63 := closure(Function #21)
199 [-]: MOVE      R0 R7        ; R0 := R7
200 [-]: MOVE      R0 R9        ; R0 := R9
201 [-]: MOVE      R0 R8        ; R0 := R8
202 [-]: MOVE      R0 R62       ; R0 := R62
203 [-]: SETGLOBAL R63 K16      ; RefreshMenu := R63
204 [-]: CLOSURE   R63 21       ; R63 := closure(Function #22)
205 [-]: MOVE      R0 R11       ; R0 := R11
206 [-]: MOVE      R0 R30       ; R0 := R30
207 [-]: MOVE      R0 R12       ; R0 := R12
208 [-]: SETGLOBAL R63 K17      ; SetTitle := R63
209 [-]: CLOSURE   R63 22       ; R63 := closure(Function #23)
210 [-]: SETGLOBAL R63 K18      ; SetNoElementsMessage := R63
211 [-]: CLOSURE   R63 23       ; R63 := closure(Function #24)
212 [-]: MOVE      R0 R14       ; R0 := R14
213 [-]: SETGLOBAL R63 K19      ; SetElementsFunction := R63
214 [-]: CLOSURE   R63 24       ; R63 := closure(Function #25)
215 [-]: MOVE      R0 R15       ; R0 := R15
216 [-]: SETGLOBAL R63 K20      ; SetCallBack := R63
217 [-]: CLOSURE   R63 25       ; R63 := closure(Function #26)
218 [-]: MOVE      R0 R44       ; R0 := R44
219 [-]: MOVE      R0 R9        ; R0 := R9
220 [-]: MOVE      R0 R61       ; R0 := R61
221 [-]: SETGLOBAL R63 K21      ; EnableSearchBox := R63
222 [-]: CLOSURE   R63 26       ; R63 := closure(Function #27)
223 [-]: MOVE      R0 R44       ; R0 := R44
224 [-]: SETGLOBAL R63 K22      ; FocusSearchBox := R63
225 [-]: CLOSURE   R63 27       ; R63 := closure(Function #28)
226 [-]: MOVE      R0 R16       ; R0 := R16
227 [-]: SETGLOBAL R63 K23      ; SetSecondaryCallBack := R63
228 [-]: CLOSURE   R63 28       ; R63 := closure(Function #29)
229 [-]: MOVE      R0 R50       ; R0 := R50
230 [-]: SETGLOBAL R63 K24      ; Close := R63
231 [-]: CLOSURE   R63 29       ; R63 := closure(Function #30)
232 [-]: MOVE      R0 R51       ; R0 := R51
233 [-]: SETGLOBAL R63 K25      ; ExitScreen := R63
234 [-]: CLOSURE   R63 30       ; R63 := closure(Function #31)
235 [-]: MOVE      R0 R56       ; R0 := R56
236 [-]: SETGLOBAL R63 K26      ; FinishSelection := R63
237 [-]: CLOSURE   R63 31       ; R63 := closure(Function #32)
238 [-]: MOVE      R0 R8        ; R0 := R8
239 [-]: MOVE      R0 R9        ; R0 := R9
240 [-]: MOVE      R0 R44       ; R0 := R44
241 [-]: SETGLOBAL R63 K27      ; onKeyUp_MENU_SELECT := R63
242 [-]: CLOSURE   R63 32       ; R63 := closure(Function #33)
243 [-]: MOVE      R0 R52       ; R0 := R52
244 [-]: SETGLOBAL R63 K28      ; onViewportSizeChanged := R63
245 [-]: CLOSURE   R63 33       ; R63 := closure(Function #34)
246 [-]: MOVE      R0 R9        ; R0 := R9
247 [-]: SETGLOBAL R63 K29      ; MenuEntryFocused := R63
248 [-]: CLOSURE   R63 34       ; R63 := closure(Function #35)
249 [-]: MOVE      R0 R9        ; R0 := R9
250 [-]: SETGLOBAL R63 K30      ; MenuEntryUnfocused := R63
251 [-]: CLOSURE   R63 35       ; R63 := closure(Function #36)
252 [-]: MOVE      R0 R8        ; R0 := R8
253 [-]: MOVE      R0 R9        ; R0 := R9
254 [-]: SETGLOBAL R63 K31      ; MenuEntryPressed := R63
255 [-]: CLOSURE   R63 36       ; R63 := closure(Function #37)
256 [-]: MOVE      R0 R29       ; R0 := R29
257 [-]: MOVE      R0 R31       ; R0 := R31
258 [-]: MOVE      R0 R50       ; R0 := R50
259 [-]: SETGLOBAL R63 K32      ; onKeyDown_HIDE_PAUSE_MENU := R63
260 [-]: CLOSURE   R63 37       ; R63 := closure(Function #38)
261 [-]: MOVE      R0 R0        ; R0 := R0
262 [-]: SETGLOBAL R63 K33      ; RollOver := R63
263 [-]: CLOSURE   R63 38       ; R63 := closure(Function #39)
264 [-]: MOVE      R0 R8        ; R0 := R8
265 [-]: MOVE      R0 R9        ; R0 := R9
266 [-]: SETGLOBAL R63 K34      ; onKeyDown_MENU_MOUSE_Z := R63
267 [-]: CLOSURE   R63 39       ; R63 := closure(Function #40)
268 [-]: MOVE      R0 R16       ; R0 := R16
269 [-]: MOVE      R0 R34       ; R0 := R34
270 [-]: MOVE      R0 R17       ; R0 := R17
271 [-]: SETGLOBAL R63 K35      ; onKeyUp_MENU_RIGHT_CLICK := R63
272 [-]: CLOSURE   R63 40       ; R63 := closure(Function #41)
273 [-]: MOVE      R0 R8        ; R0 := R8
274 [-]: SETGLOBAL R63 K36      ; IsInputBlocked := R63
275 [-]: CLOSURE   R63 41       ; R63 := closure(Function #42)
276 [-]: MOVE      R0 R37       ; R0 := R37
277 [-]: SETGLOBAL R63 K37      ; SetTargetBackgroundAlpha := R63
278 [-]: CLOSURE   R63 42       ; R63 := closure(Function #43)
279 [-]: SETGLOBAL R63 K38      ; SetTargetBluerAlpha := R63
280 [-]: CLOSURE   R63 43       ; R63 := closure(Function #44)
281 [-]: MOVE      R0 R31       ; R0 := R31
282 [-]: SETGLOBAL R63 K39      ; SetAllowBackgroundExit := R63
283 [-]: CLOSURE   R63 44       ; R63 := closure(Function #45)
284 [-]: MOVE      R0 R32       ; R0 := R32
285 [-]: MOVE      R0 R9        ; R0 := R9
286 [-]: MOVE      R0 R43       ; R0 := R43
287 [-]: MOVE      R0 R0        ; R0 := R0
288 [-]: MOVE      R0 R33       ; R0 := R33
289 [-]: MOVE      R0 R62       ; R0 := R62
290 [-]: MOVE      R0 R34       ; R0 := R34
291 [-]: SETGLOBAL R63 K40      ; SetInitTarget := R63
292 [-]: CLOSURE   R63 45       ; R63 := closure(Function #46)
293 [-]: MOVE      R0 R28       ; R0 := R28
294 [-]: SETGLOBAL R63 K41      ; SetMinWidth := R63
295 [-]: CLOSURE   R63 46       ; R63 := closure(Function #47)
296 [-]: MOVE      R0 R21       ; R0 := R21
297 [-]: SETGLOBAL R63 K42      ; SetAlignment := R63
298 [-]: CLOSURE   R63 47       ; R63 := closure(Function #48)
299 [-]: MOVE      R0 R22       ; R0 := R22
300 [-]: SETGLOBAL R63 K43      ; SetGetButtonsFunction := R63
301 [-]: CLOSURE   R63 48       ; R63 := closure(Function #49)
302 [-]: MOVE      R0 R23       ; R0 := R23
303 [-]: SETGLOBAL R63 K44      ; SetOnElementSelectedFunction := R63
304 [-]: CLOSURE   R63 49       ; R63 := closure(Function #50)
305 [-]: MOVE      R0 R29       ; R0 := R29
306 [-]: MOVE      R0 R54       ; R0 := R54
307 [-]: SETGLOBAL R63 K45      ; SetAllowExit := R63
308 [-]: CLOSURE   R63 50       ; R63 := closure(Function #51)
309 [-]: SETGLOBAL R63 K46      ; SetScale := R63
310 [-]: CLOSURE   R63 51       ; R63 := closure(Function #52)
311 [-]: MOVE      R0 R45       ; R0 := R45
312 [-]: SETGLOBAL R63 K47      ; SetOnFocusedCallback := R63
313 [-]: CLOSURE   R63 52       ; R63 := closure(Function #53)
314 [-]: MOVE      R0 R46       ; R0 := R46
315 [-]: SETGLOBAL R63 K48      ; SetOnUnfocusedCallback := R63
316 [-]: CLOSURE   R63 53       ; R63 := closure(Function #54)
317 [-]: MOVE      R0 R47       ; R0 := R47
318 [-]: SETGLOBAL R63 K49      ; SetOnFocusedSound := R63
319 [-]: CLOSURE   R63 54       ; R63 := closure(Function #55)
320 [-]: MOVE      R0 R48       ; R0 := R48
321 [-]: SETGLOBAL R63 K50      ; SetOnSelectedSound := R63
322 [-]: CLOSURE   R63 55       ; R63 := closure(Function #56)
323 [-]: MOVE      R0 R38       ; R0 := R38
324 [-]: MOVE      R0 R39       ; R0 := R39
325 [-]: MOVE      R0 R41       ; R0 := R41
326 [-]: SETGLOBAL R63 K51      ; SetFadeTime := R63
327 [-]: CLOSURE   R63 56       ; R63 := closure(Function #57)
328 [-]: MOVE      R0 R42       ; R0 := R42
329 [-]: SETGLOBAL R63 K52      ; SetInstantCallback := R63
330 [-]: CLOSURE   R63 57       ; R63 := closure(Function #58)
331 [-]: MOVE      R0 R13       ; R0 := R13
332 [-]: MOVE      R0 R12       ; R0 := R12
333 [-]: SETGLOBAL R63 K53      ; SetTitleCaseText := R63
334 [-]: CLOSURE   R63 58       ; R63 := closure(Function #59)
335 [-]: MOVE      R0 R31       ; R0 := R31
336 [-]: MOVE      R0 R34       ; R0 := R34
337 [-]: MOVE      R0 R50       ; R0 := R50
338 [-]: SETGLOBAL R63 K54      ; MouseCatcherPressed := R63
339 [-]: CLOSURE   R63 59       ; R63 := closure(Function #60)
340 [-]: SETGLOBAL R63 K55      ; SupportsThemes := R63
341 [-]: CLOSURE   R63 60       ; R63 := closure(Function #61)
342 [-]: MOVE      R0 R53       ; R0 := R53
343 [-]: SETGLOBAL R63 K56      ; OnStyleChangedCallback := R63
344 [-]: CLOSURE   R63 61       ; R63 := closure(Function #62)
345 [-]: MOVE      R0 R25       ; R0 := R25
346 [-]: MOVE      R0 R9        ; R0 := R9
347 [-]: SETGLOBAL R63 K57      ; OnGamepadTransition := R63
348 [-]: CLOSURE   R63 62       ; R63 := closure(Function #63)
349 [-]: SETGLOBAL R63 K58      ; CallbackCompleted := R63
350 [-]: RETURN    R0 1         ; return 


; Function #1:
;
; Name:            
; Defined at line: 67
; #Upvalues:       4
; #Parameters:     0
; Is_vararg:       0
; Max Stack Size:  3

  1 [-]: GETGLOBAL R0 K0        ; R0 := _T
  2 [-]: SETTABLE  R0 K1 K2     ; R0["gToolTip"] := nil
  3 [-]: GETGLOBAL R0 K0        ; R0 := _T
  4 [-]: SETTABLE  R0 K3 K2     ; R0["gToolTipCoords"] := nil
  5 [-]: GETUPVAL  R0 U0        ; R0 := U0
  6 [-]: TEST      R0 0         ; if not R0 then PC := 17
  7 [-]: JMP       17           ; PC := 17
  8 [-]: GETGLOBAL R0 K4        ; R0 := 0x7b998233
  9 [-]: GETGLOBAL R1 K0        ; R1 := _T
 10 [-]: GETTABLE  R1 R1 K5     ; R1 := R1["DisableUIInput"]
 11 [-]: CALL      R0 2 2       ; R0 := R0(R1)
 12 [-]: TEST      R0 1         ; if R0 then PC := 17
 13 [-]: JMP       17           ; PC := 17
 14 [-]: GETGLOBAL R0 K0        ; R0 := _T
 15 [-]: GETTABLE  R0 R0 K6     ; R0 := R0[0x80172c74]
 16 [-]: CALL      R0 1 1       ; R0()
 17 [-]: GETUPVAL  R0 U1        ; R0 := U1
 18 [-]: TEST      R0 1         ; if R0 then PC := 39
 19 [-]: JMP       39           ; PC := 39
 20 [-]: GETGLOBAL R0 K4        ; R0 := 0x7b998233
 21 [-]: GETUPVAL  R1 U2        ; R1 := U2
 22 [-]: CALL      R0 2 2       ; R0 := R0(R1)
 23 [-]: TEST      R0 1         ; if R0 then PC := 39
 24 [-]: JMP       39           ; PC := 39
 25 [-]: GETGLOBAL R0 K4        ; R0 := 0x7b998233
 26 [-]: GETGLOBAL R1 K0        ; R1 := _T
 27 [-]: GETUPVAL  R2 U2        ; R2 := U2
 28 [-]: GETTABLE  R1 R1 R2     ; R1 := R1[R2]
 29 [-]: CALL      R0 2 2       ; R0 := R0(R1)
 30 [-]: TEST      R0 1         ; if R0 then PC := 39
 31 [-]: JMP       39           ; PC := 39
 32 [-]: LOADBOOL  R0 1 0       ; R0 := true
 33 [-]: SETUPVAL  R0 U1        ; U82 := R1
 34 [-]: GETGLOBAL R0 K0        ; R0 := _T
 35 [-]: GETUPVAL  R1 U2        ; R1 := U2
 36 [-]: GETTABLE  R0 R0 R1     ; R0 := R0[R1]
 37 [-]: GETUPVAL  R1 U3        ; R1 := U3
 38 [-]: CALL      R0 2 1       ; R0(R1)
 39 [-]: RETURN    R0 1         ; return 


; Function #2:
;
; Name:            
; Defined at line: 81
; #Upvalues:       11
; #Parameters:     0
; Is_vararg:       0
; Max Stack Size:  9

  1 [-]: LOADBOOL  R0 1 0       ; R0 := true
  2 [-]: SETUPVAL  R0 U0        ; U82 := R0
  3 [-]: LOADBOOL  R0 1 0       ; R0 := true
  4 [-]: SETUPVAL  R0 U1        ; U82 := R1
  5 [-]: GETGLOBAL R0 K0        ; R0 := 0x7b998233
  6 [-]: GETGLOBAL R1 K1        ; R1 := _T
  7 [-]: GETTABLE  R1 R1 K2     ; R1 := R1["IsScreenOpen"]
  8 [-]: CALL      R0 2 2       ; R0 := R0(R1)
  9 [-]: TEST      R0 1         ; if R0 then PC := 36
 10 [-]: JMP       36           ; PC := 36
 11 [-]: GETGLOBAL R0 K1        ; R0 := _T
 12 [-]: GETTABLE  R0 R0 K3     ; R0 := R0[0x8e6a7b4e]
 13 [-]: LOADK     R1 K4        ; R1 := "DarvoDeal"
 14 [-]: CALL      R0 2 2       ; R0 := R0(R1)
 15 [-]: TEST      R0 0         ; if not R0 then PC := 36
 16 [-]: JMP       36           ; PC := 36
 17 [-]: GETGLOBAL R0 K0        ; R0 := 0x7b998233
 18 [-]: GETGLOBAL R1 K1        ; R1 := _T
 19 [-]: GETTABLE  R1 R1 K5     ; R1 := R1["ChangeHubVisCounter"]
 20 [-]: CALL      R0 2 2       ; R0 := R0(R1)
 21 [-]: TEST      R0 1         ; if R0 then PC := 27
 22 [-]: JMP       27           ; PC := 27
 23 [-]: GETGLOBAL R0 K1        ; R0 := _T
 24 [-]: GETTABLE  R0 R0 K6     ; R0 := R0[0x33cfa273]
 25 [-]: LOADK     R1 -1        ; R1 := -1.000000
 26 [-]: CALL      R0 2 1       ; R0(R1)
 27 [-]: GETGLOBAL R0 K0        ; R0 := 0x7b998233
 28 [-]: GETGLOBAL R1 K1        ; R1 := _T
 29 [-]: GETTABLE  R1 R1 K7     ; R1 := R1["ForceRestoreMiniMap"]
 30 [-]: CALL      R0 2 2       ; R0 := R0(R1)
 31 [-]: TEST      R0 1         ; if R0 then PC := 36
 32 [-]: JMP       36           ; PC := 36
 33 [-]: GETGLOBAL R0 K1        ; R0 := _T
 34 [-]: GETTABLE  R0 R0 K8     ; R0 := R0[0x6356c4e0]
 35 [-]: CALL      R0 1 1       ; R0()
 36 [-]: GETUPVAL  R0 U2        ; R0 := U2
 37 [-]: TEST      R0 0         ; if not R0 then PC := 58
 38 [-]: JMP       58           ; PC := 58
 39 [-]: GETGLOBAL R0 K0        ; R0 := 0x7b998233
 40 [-]: GETUPVAL  R1 U3        ; R1 := U3
 41 [-]: CALL      R0 2 2       ; R0 := R0(R1)
 42 [-]: TEST      R0 1         ; if R0 then PC := 58
 43 [-]: JMP       58           ; PC := 58
 44 [-]: GETGLOBAL R0 K0        ; R0 := 0x7b998233
 45 [-]: GETGLOBAL R1 K1        ; R1 := _T
 46 [-]: GETUPVAL  R2 U3        ; R2 := U3
 47 [-]: GETTABLE  R1 R1 R2     ; R1 := R1[R2]
 48 [-]: CALL      R0 2 2       ; R0 := R0(R1)
 49 [-]: TEST      R0 1         ; if R0 then PC := 58
 50 [-]: JMP       58           ; PC := 58
 51 [-]: LOADBOOL  R0 1 0       ; R0 := true
 52 [-]: SETUPVAL  R0 U4        ; U82 := R4
 53 [-]: GETGLOBAL R0 K1        ; R0 := _T
 54 [-]: GETUPVAL  R1 U3        ; R1 := U3
 55 [-]: GETTABLE  R0 R0 R1     ; R0 := R0[R1]
 56 [-]: GETUPVAL  R1 U5        ; R1 := U5
 57 [-]: CALL      R0 2 1       ; R0(R1)
 58 [-]: GETGLOBAL R0 K9        ; R0 := 0x25312c9b
 59 [-]: GETGLOBAL R1 K10       ; R1 := 0xae91e43b
 60 [-]: LOADK     R2 K11       ; R2 := "_root"
 61 [-]: LOADK     R3 0         ; R3 := 0.000000
 62 [-]: NEWTABLE  R4 1 0       ; R4 := {}
 63 [-]: LOADK     R5 10        ; R5 := 10.000000
 64 [-]: SETLIST   R4 1 1       ; R4[(1-1)*FPF+i] := R(4+i), 1 <= i <= 1
 65 [-]: NEWTABLE  R5 1 0       ; R5 := {}
 66 [-]: LOADK     R6 0         ; R6 := 0.000000
 67 [-]: SETLIST   R5 1 1       ; R5[(1-1)*FPF+i] := R(5+i), 1 <= i <= 1
 68 [-]: GETUPVAL  R6 U6        ; R6 := U6
 69 [-]: LOADK     R7 0         ; R7 := 0.000000
 70 [-]: CLOSURE   R8 0         ; R8 := closure(Function #2.1)
 71 [-]: GETUPVAL  R0 U7        ; R0 := U7
 72 [-]: GETUPVAL  R0 U8        ; R0 := U8
 73 [-]: GETUPVAL  R0 U4        ; R0 := U4
 74 [-]: GETUPVAL  R0 U3        ; R0 := U3
 75 [-]: GETUPVAL  R0 U5        ; R0 := U5
 76 [-]: GETUPVAL  R0 U9        ; R0 := U9
 77 [-]: GETUPVAL  R0 U10       ; R0 := U10
 78 [-]: CALL      R0 9 1       ; R0(R1,R2,R3,R4,R5,R6,R7,R8)
 79 [-]: RETURN    R0 1         ; return 


; Function #2.1:
;
; Name:            
; Defined at line: 98
; #Upvalues:       7
; #Parameters:     0
; Is_vararg:       0
; Max Stack Size:  10

  1 [-]: CLOSURE   R0 0         ; R0 := closure(Function #2.1.1)
  2 [-]: GETUPVAL  R0 U0        ; R0 := U0
  3 [-]: GETGLOBAL R1 K0        ; R1 := 0x25312c9b
  4 [-]: GETGLOBAL R2 K1        ; R2 := 0xae91e43b
  5 [-]: LOADK     R3 K2        ; R3 := "_root"
  6 [-]: LOADK     R4 0         ; R4 := 0.000000
  7 [-]: NEWTABLE  R5 1 0       ; R5 := {}
  8 [-]: MOVE      R6 R0        ; R6 := R0
  9 [-]: SETLIST   R5 1 1       ; R5[(1-1)*FPF+i] := R(5+i), 1 <= i <= 1
 10 [-]: NEWTABLE  R6 1 0       ; R6 := {}
 11 [-]: LOADK     R7 1         ; R7 := 1.000000
 12 [-]: SETLIST   R6 1 1       ; R6[(1-1)*FPF+i] := R(6+i), 1 <= i <= 1
 13 [-]: GETUPVAL  R7 U1        ; R7 := U1
 14 [-]: LOADK     R8 0         ; R8 := 0.000000
 15 [-]: CLOSURE   R9 1         ; R9 := closure(Function #2.1.2)
 16 [-]: GETUPVAL  R0 U2        ; R0 := U2
 17 [-]: GETUPVAL  R0 U3        ; R0 := U3
 18 [-]: GETUPVAL  R0 U4        ; R0 := U4
 19 [-]: GETUPVAL  R0 U5        ; R0 := U5
 20 [-]: GETUPVAL  R0 U6        ; R0 := U6
 21 [-]: CALL      R1 9 1       ; R1(R2,R3,R4,R5,R6,R7,R8,R9)
 22 [-]: RETURN    R0 1         ; return 


; Function #2.1.1:
;
; Name:            
; Defined at line: 100
; #Upvalues:       1
; #Parameters:     1
; Is_vararg:       0
; Max Stack Size:  5

  1 [-]: GETGLOBAL R1 K0        ; R1 := 0xae91e43b
  2 [-]: SELF      R1 R1 K1     ; R2 := R1; R1 := R1[0x58bec6d6]
  3 [-]: SUB       R3 K2 R0     ; R3 := 1.000000 - R0
  4 [-]: GETUPVAL  R4 U0        ; R4 := U0
  5 [-]: MUL       R3 R3 R4     ; R3 := R3 * R4
  6 [-]: CALL      R1 3 1       ; R1(R2,R3)
  7 [-]: RETURN    R0 1         ; return 


; Function #2.1.2:
;
; Name:            
; Defined at line: 104
; #Upvalues:       5
; #Parameters:     0
; Is_vararg:       0
; Max Stack Size:  3

  1 [-]: GETGLOBAL R0 K0        ; R0 := 0xae91e43b
  2 [-]: SELF      R0 R0 K1     ; R1 := R0; R0 := R0[0x32302b4a]
  3 [-]: CALL      R0 2 1       ; R0(R1)
  4 [-]: GETUPVAL  R0 U0        ; R0 := U0
  5 [-]: TEST      R0 1         ; if R0 then PC := 26
  6 [-]: JMP       26           ; PC := 26
  7 [-]: GETGLOBAL R0 K2        ; R0 := 0x7b998233
  8 [-]: GETUPVAL  R1 U1        ; R1 := U1
  9 [-]: CALL      R0 2 2       ; R0 := R0(R1)
 10 [-]: TEST      R0 1         ; if R0 then PC := 26
 11 [-]: JMP       26           ; PC := 26
 12 [-]: GETGLOBAL R0 K2        ; R0 := 0x7b998233
 13 [-]: GETGLOBAL R1 K3        ; R1 := _T
 14 [-]: GETUPVAL  R2 U1        ; R2 := U1
 15 [-]: GETTABLE  R1 R1 R2     ; R1 := R1[R2]
 16 [-]: CALL      R0 2 2       ; R0 := R0(R1)
 17 [-]: TEST      R0 1         ; if R0 then PC := 26
 18 [-]: JMP       26           ; PC := 26
 19 [-]: LOADBOOL  R0 1 0       ; R0 := true
 20 [-]: SETUPVAL  R0 U0        ; U82 := R0
 21 [-]: GETGLOBAL R0 K3        ; R0 := _T
 22 [-]: GETUPVAL  R1 U1        ; R1 := U1
 23 [-]: GETTABLE  R0 R0 R1     ; R0 := R0[R1]
 24 [-]: GETUPVAL  R1 U2        ; R1 := U2
 25 [-]: CALL      R0 2 1       ; R0(R1)
 26 [-]: LOADNIL   R0 R0        ; R0 := nil
 27 [-]: SETUPVAL  R0 U3        ; U82 := R3
 28 [-]: GETUPVAL  R0 U4        ; R0 := U4
 29 [-]: SELF      R0 R0 K4     ; R1 := R0; R0 := R0[0xea061e98]
 30 [-]: CLOSURE   R2 0         ; R2 := closure(Function #2.1.2.1)
 31 [-]: CALL      R0 3 1       ; R0(R1,R2)
 32 [-]: RETURN    R0 1         ; return 


; Function #2.1.2.1:
;
; Name:            
; Defined at line: 115
; #Upvalues:       0
; #Parameters:     1
; Is_vararg:       0
; Max Stack Size:  2

  1 [-]: SETTABLE  R0 K0 K1     ; R0["mSelected"] := nil
  2 [-]: RETURN    R0 1         ; return 


; Function #3:
;
; Name:            
; Defined at line: 122
; #Upvalues:       1
; #Parameters:     0
; Is_vararg:       0
; Max Stack Size:  2

  1 [-]: GETUPVAL  R0 U0        ; R0 := U0
  2 [-]: CALL      R0 1 1       ; R0()
  3 [-]: RETURN    R0 1         ; return 


; Function #4:
;
; Name:            
; Defined at line: 126
; #Upvalues:       2
; #Parameters:     0
; Is_vararg:       0
; Max Stack Size:  3

  1 [-]: GETUPVAL  R0 U0        ; R0 := U0
  2 [-]: GETTABLE  R0 R0 K0     ; R0 := R0[0x659d451f]
  3 [-]: GETGLOBAL R1 K1        ; R1 := 0x0032441c
  4 [-]: GETTABLE  R1 R1 K2     ; R1 := R1["UISound_WindowClose"]
  5 [-]: CALL      R0 2 1       ; R0(R1)
  6 [-]: LOADBOOL  R0 0 0       ; R0 := false
  7 [-]: GETGLOBAL R1 K3        ; R1 := _T
  8 [-]: GETTABLE  R1 R1 K4     ; R1 := R1["BackgroundMovie"]
  9 [-]: EQ        1 R1 K5      ; if R1 == nil then PC := 16
 10 [-]: JMP       16           ; PC := 16
 11 [-]: GETGLOBAL R1 K3        ; R1 := _T
 12 [-]: GETTABLE  R1 R1 K6     ; R1 := R1[0x1c5b5b33]
 13 [-]: LOADK     R2 K7        ; R2 := "ItemBrowsing"
 14 [-]: CALL      R1 2 2       ; R1 := R1(R2)
 15 [-]: MOVE      R0 R1        ; R0 := R1
 16 [-]: TEST      R0 0         ; if not R0 then PC := 22
 17 [-]: JMP       22           ; PC := 22
 18 [-]: GETGLOBAL R1 K3        ; R1 := _T
 19 [-]: GETTABLE  R1 R1 K8     ; R1 := R1[0x4e4e6b0c]
 20 [-]: CALL      R1 1 1       ; R1()
 21 [-]: JMP       24           ; PC := 24
 22 [-]: GETUPVAL  R1 U1        ; R1 := U1
 23 [-]: CALL      R1 1 1       ; R1()
 24 [-]: RETURN    R0 1         ; return 


; Function #5:
;
; Name:            
; Defined at line: 139
; #Upvalues:       2
; #Parameters:     0
; Is_vararg:       0
; Max Stack Size:  7

  1 [-]: GETUPVAL  R0 U0        ; R0 := U0
  2 [-]: GETTABLE  R0 R0 K0     ; R0 := R0[0x44537adf]
  3 [-]: GETGLOBAL R1 K1        ; R1 := 0xae91e43b
  4 [-]: CALL      R0 2 3       ; R0,R1 := R0(R1)
  5 [-]: GETGLOBAL R2 K1        ; R2 := 0xae91e43b
  6 [-]: SELF      R2 R2 K2     ; R3 := R2; R2 := R2[0x67bc869f]
  7 [-]: LOADK     R4 K3        ; R4 := "MouseCatcher"
  8 [-]: LOADK     R5 12        ; R5 := 12.000000
  9 [-]: MOVE      R6 R0        ; R6 := R0
 10 [-]: CALL      R2 5 1       ; R2(R3,R4,R5,R6)
 11 [-]: GETGLOBAL R2 K1        ; R2 := 0xae91e43b
 12 [-]: SELF      R2 R2 K2     ; R3 := R2; R2 := R2[0x67bc869f]
 13 [-]: LOADK     R4 K3        ; R4 := "MouseCatcher"
 14 [-]: LOADK     R5 13        ; R5 := 13.000000
 15 [-]: MOVE      R6 R1        ; R6 := R1
 16 [-]: CALL      R2 5 1       ; R2(R3,R4,R5,R6)
 17 [-]: GETGLOBAL R2 K4        ; R2 := 0x7b998233
 18 [-]: GETUPVAL  R3 U1        ; R3 := U1
 19 [-]: CALL      R2 2 2       ; R2 := R2(R3)
 20 [-]: TEST      R2 1         ; if R2 then PC := 31
 21 [-]: JMP       31           ; PC := 31
 22 [-]: GETUPVAL  R2 U1        ; R2 := U1
 23 [-]: SELF      R2 R2 K5     ; R3 := R2; R2 := R2[0xfaa69527]
 24 [-]: GETGLOBAL R4 K1        ; R4 := 0xae91e43b
 25 [-]: SELF      R4 R4 K6     ; R5 := R4; R4 := R4[0x6b837788]
 26 [-]: CALL      R4 2 2       ; R4 := R4(R5)
 27 [-]: GETGLOBAL R5 K1        ; R5 := 0xae91e43b
 28 [-]: SELF      R5 R5 K7     ; R6 := R5; R5 := R5[0xaf9fda9f]
 29 [-]: CALL      R5 2 0       ; R5,... := R5(R6)
 30 [-]: CALL      R2 0 1       ; R2(R3,...)
 31 [-]: RETURN    R0 1         ; return 


; Function #6:
;
; Name:            
; Defined at line: 150
; #Upvalues:       3
; #Parameters:     0
; Is_vararg:       0
; Max Stack Size:  14

  1 [-]: GETUPVAL  R0 U0        ; R0 := U0
  2 [-]: GETTABLE  R0 R0 K0     ; R0 := R0[0x5d10207d]
  3 [-]: LOADK     R1 2         ; R1 := 2.000000
  4 [-]: LOADBOOL  R2 1 0       ; R2 := true
  5 [-]: CALL      R0 3 2       ; R0 := R0(R1,R2)
  6 [-]: GETUPVAL  R1 U0        ; R1 := U0
  7 [-]: GETTABLE  R1 R1 K0     ; R1 := R1[0x5d10207d]
  8 [-]: LOADK     R2 3         ; R2 := 3.000000
  9 [-]: LOADBOOL  R3 1 0       ; R3 := true
 10 [-]: CALL      R1 3 2       ; R1 := R1(R2,R3)
 11 [-]: GETUPVAL  R2 U0        ; R2 := U0
 12 [-]: GETTABLE  R2 R2 K0     ; R2 := R2[0x5d10207d]
 13 [-]: LOADK     R3 9         ; R3 := 9.000000
 14 [-]: LOADBOOL  R4 1 0       ; R4 := true
 15 [-]: CALL      R2 3 2       ; R2 := R2(R3,R4)
 16 [-]: GETUPVAL  R3 U0        ; R3 := U0
 17 [-]: GETTABLE  R3 R3 K0     ; R3 := R3[0x5d10207d]
 18 [-]: LOADK     R4 6         ; R4 := 6.000000
 19 [-]: LOADBOOL  R5 1 0       ; R5 := true
 20 [-]: CALL      R3 3 2       ; R3 := R3(R4,R5)
 21 [-]: GETGLOBAL R4 K2        ; R4 := 0xae91e43b
 22 [-]: SELF      R4 R4 K3     ; R5 := R4; R4 := R4[0xc6a10ab1]
 23 [-]: MOVE      R6 R0        ; R6 := R0
 24 [-]: CALL      R4 3 1       ; R4(R5,R6)
 25 [-]: GETUPVAL  R4 U1        ; R4 := U1
 26 [-]: GETTABLE  R4 R4 K4     ; R4 := R4[0x8bcd12b6]
 27 [-]: MOVE      R5 R2        ; R5 := R2
 28 [-]: CALL      R4 2 2       ; R4 := R4(R5)
 29 [-]: GETUPVAL  R5 U1        ; R5 := U1
 30 [-]: GETTABLE  R5 R5 K4     ; R5 := R5[0x8bcd12b6]
 31 [-]: MOVE      R6 R0        ; R6 := R0
 32 [-]: CALL      R5 2 2       ; R5 := R5(R6)
 33 [-]: GETGLOBAL R6 K2        ; R6 := 0xae91e43b
 34 [-]: SELF      R6 R6 K5     ; R7 := R6; R6 := R6[0x91e13703]
 35 [-]: LOADK     R8 K6        ; R8 := "Container.BgFill"
 36 [-]: LOADK     R9 K7        ; R9 := "RectEdgeColor"
 37 [-]: GETTABLE  R10 R4 K8    ; R10 := R4["r"]
 38 [-]: GETTABLE  R11 R4 K9    ; R11 := R4["g"]
 39 [-]: GETTABLE  R12 R4 K10   ; R12 := R4["b"]
 40 [-]: LOADK     R13 K11      ; R13 := 0.300000
 41 [-]: CALL      R6 8 1       ; R6(R7,R8,R9,R10,R11,R12,R13)
 42 [-]: GETGLOBAL R6 K2        ; R6 := 0xae91e43b
 43 [-]: SELF      R6 R6 K5     ; R7 := R6; R6 := R6[0x91e13703]
 44 [-]: LOADK     R8 K6        ; R8 := "Container.BgFill"
 45 [-]: LOADK     R9 K12       ; R9 := "RectInnerColor"
 46 [-]: GETTABLE  R10 R5 K8    ; R10 := R5["r"]
 47 [-]: GETTABLE  R11 R5 K9    ; R11 := R5["g"]
 48 [-]: GETTABLE  R12 R5 K10   ; R12 := R5["b"]
 49 [-]: LOADK     R13 0        ; R13 := 0.750000
 50 [-]: CALL      R6 8 1       ; R6(R7,R8,R9,R10,R11,R12,R13)
 51 [-]: GETGLOBAL R6 K2        ; R6 := 0xae91e43b
 52 [-]: SELF      R6 R6 K13    ; R7 := R6; R6 := R6[0x67bc869f]
 53 [-]: LOADK     R8 K14       ; R8 := "Container.Title"
 54 [-]: LOADK     R9 9         ; R9 := 9.000000
 55 [-]: MOVE      R10 R2       ; R10 := R2
 56 [-]: CALL      R6 5 1       ; R6(R7,R8,R9,R10)
 57 [-]: GETGLOBAL R6 K2        ; R6 := 0xae91e43b
 58 [-]: SELF      R6 R6 K13    ; R7 := R6; R6 := R6[0x67bc869f]
 59 [-]: LOADK     R8 K14       ; R8 := "Container.Title"
 60 [-]: LOADK     R9 76        ; R9 := 76.000000
 61 [-]: MOVE      R10 R0       ; R10 := R0
 62 [-]: CALL      R6 5 1       ; R6(R7,R8,R9,R10)
 63 [-]: GETGLOBAL R6 K2        ; R6 := 0xae91e43b
 64 [-]: SELF      R6 R6 K13    ; R7 := R6; R6 := R6[0x67bc869f]
 65 [-]: LOADK     R8 K15       ; R8 := "Container.Underline"
 66 [-]: LOADK     R9 9         ; R9 := 9.000000
 67 [-]: MOVE      R10 R2       ; R10 := R2
 68 [-]: CALL      R6 5 1       ; R6(R7,R8,R9,R10)
 69 [-]: GETUPVAL  R6 U2        ; R6 := U2
 70 [-]: GETTABLE  R6 R6 K16    ; R6 := R6["mScrollBar"]
 71 [-]: SELF      R6 R6 K17    ; R7 := R6; R6 := R6[0x087cbd3f]
 72 [-]: CALL      R6 2 1       ; R6(R7)
 73 [-]: GETUPVAL  R6 U2        ; R6 := U2
 74 [-]: SELF      R6 R6 K18    ; R7 := R6; R6 := R6[0x741d078c]
 75 [-]: CLOSURE   R8 0         ; R8 := closure(Function #6.1)
 76 [-]: MOVE      R0 R3        ; R0 := R3
 77 [-]: CALL      R6 3 1       ; R6(R7,R8)
 78 [-]: RETURN    R0 1         ; return 


; Function #6.1:
;
; Name:            
; Defined at line: 169
; #Upvalues:       1
; #Parameters:     1
; Is_vararg:       0
; Max Stack Size:  8

  1 [-]: GETGLOBAL R1 K0        ; R1 := 0x3d106989
  2 [-]: GETTABLE  R2 R0 K1     ; R2 := R0["mClipName"]
  3 [-]: CALL      R1 2 1       ; R1(R2)
  4 [-]: GETTABLE  R1 R0 K2     ; R1 := R0["mButton"]
  5 [-]: TEST      R1 0         ; if not R1 then PC := 12
  6 [-]: JMP       12           ; PC := 12
  7 [-]: GETGLOBAL R2 K0        ; R2 := 0x3d106989
  8 [-]: LOADK     R3 K3        ; R3 := "update colors"
  9 [-]: CALL      R2 2 1       ; R2(R3)
 10 [-]: SELF      R2 R1 K4     ; R3 := R1; R2 := R1[0x087cbd3f]
 11 [-]: CALL      R2 2 1       ; R2(R3)
 12 [-]: GETGLOBAL R2 K5        ; R2 := 0xae91e43b
 13 [-]: SELF      R2 R2 K6     ; R3 := R2; R2 := R2[0xf64b7262]
 14 [-]: GETTABLE  R4 R0 K1     ; R4 := R0["mClipName"]
 15 [-]: LOADK     R5 K7        ; R5 := "RightText"
 16 [-]: LOADK     R6 9         ; R6 := 9.000000
 17 [-]: GETUPVAL  R7 U0        ; R7 := U0
 18 [-]: CALL      R2 6 1       ; R2(R3,R4,R5,R6,R7)
 19 [-]: RETURN    R0 1         ; return 


; Function #7:
;
; Name:            
; Defined at line: 182
; #Upvalues:       4
; #Parameters:     0
; Is_vararg:       0
; Max Stack Size:  10

  1 [-]: NEWTABLE  R0 0 0       ; R0 := {}
  2 [-]: GETGLOBAL R1 K0        ; R1 := 0x7b998233
  3 [-]: GETGLOBAL R2 K1        ; R2 := _T
  4 [-]: GETUPVAL  R3 U0        ; R3 := U0
  5 [-]: GETTABLE  R2 R2 R3     ; R2 := R2[R3]
  6 [-]: CALL      R1 2 2       ; R1 := R1(R2)
  7 [-]: TEST      R1 1         ; if R1 then PC := 43
  8 [-]: JMP       43           ; PC := 43
  9 [-]: GETGLOBAL R1 K1        ; R1 := _T
 10 [-]: GETUPVAL  R2 U0        ; R2 := U0
 11 [-]: GETTABLE  R1 R1 R2     ; R1 := R1[R2]
 12 [-]: GETUPVAL  R2 U1        ; R2 := U1
 13 [-]: CALL      R1 2 2       ; R1 := R1(R2)
 14 [-]: LOADK     R2 1         ; R2 := 1.000000
 15 [-]: LEN       R3 R1        ; R3 := # R1
 16 [-]: LOADK     R4 1         ; R4 := 1.000000
 17 [-]: FORPREP   R2 41        ; R2 -= R4; PC := 41
 18 [-]: GETGLOBAL R6 K2        ; R6 := 0x33bdd652
 19 [-]: GETTABLE  R6 R6 K3     ; R6 := R6[0x23d5322f]
 20 [-]: MOVE      R7 R0        ; R7 := R0
 21 [-]: NEWTABLE  R8 0 5       ; R8 := {}
 22 [-]: GETTABLE  R9 R1 R5     ; R9 := R1[R5]
 23 [-]: GETTABLE  R9 R9 K4     ; R9 := R9["Label"]
 24 [-]: SETTABLE  R8 K4 R9     ; R8["Label"] := R9
 25 [-]: CLOSURE   R9 0         ; R9 := closure(Function #7.1)
 26 [-]: MOVE      R0 R1        ; R0 := R1
 27 [-]: MOVE      R0 R5        ; R0 := R5
 28 [-]: GETUPVAL  R0 U1        ; R0 := U1
 29 [-]: SETTABLE  R8 K5 R9     ; R8["CallBack"] := R9
 30 [-]: GETTABLE  R9 R1 R5     ; R9 := R1[R5]
 31 [-]: GETTABLE  R9 R9 K6     ; R9 := R9["CallOut"]
 32 [-]: SETTABLE  R8 K6 R9     ; R8["CallOut"] := R9
 33 [-]: GETTABLE  R9 R1 R5     ; R9 := R1[R5]
 34 [-]: GETTABLE  R9 R9 K7     ; R9 := R9["Tips"]
 35 [-]: SETTABLE  R8 K7 R9     ; R8["Tips"] := R9
 36 [-]: GETTABLE  R9 R1 R5     ; R9 := R1[R5]
 37 [-]: GETTABLE  R9 R9 K8     ; R9 := R9["Padding"]
 38 [-]: SETTABLE  R8 K8 R9     ; R8["Padding"] := R9
 39 [-]: CALL      R6 3 1       ; R6(R7,R8)
 40 [-]: CLOSE     R5           ; SAVE R5,...
 41 [-]: FORLOOP   R2 18        ; R2 += R4; if R2 <= R3 then begin PC := 18; R5 := R2 end
 42 [-]: CLOSE     R1           ; SAVE R1,...
 43 [-]: GETUPVAL  R1 U2        ; R1 := U2
 44 [-]: TEST      R1 0         ; if not R1 then PC := 55
 45 [-]: JMP       55           ; PC := 55
 46 [-]: GETGLOBAL R1 K2        ; R1 := 0x33bdd652
 47 [-]: GETTABLE  R1 R1 K3     ; R1 := R1[0x23d5322f]
 48 [-]: MOVE      R2 R0        ; R2 := R0
 49 [-]: NEWTABLE  R3 0 3       ; R3 := {}
 50 [-]: SETTABLE  R3 K4 K9     ; R3["Label"] := "/Lotus/Language/Menu/Exit"
 51 [-]: GETUPVAL  R4 U3        ; R4 := U3
 52 [-]: SETTABLE  R3 K5 R4     ; R3["CallBack"] := R4
 53 [-]: SETTABLE  R3 K6 K10    ; R3["CallOut"] := "MENU_CANCEL"
 54 [-]: CALL      R1 3 1       ; R1(R2,R3)
 55 [-]: GETGLOBAL R1 K0        ; R1 := 0x7b998233
 56 [-]: GETGLOBAL R2 K1        ; R2 := _T
 57 [-]: GETTABLE  R2 R2 K11    ; R2 := R2["SetButtons"]
 58 [-]: CALL      R1 2 2       ; R1 := R1(R2)
 59 [-]: TEST      R1 1         ; if R1 then PC := 69
 60 [-]: JMP       69           ; PC := 69
 61 [-]: GETGLOBAL R1 K1        ; R1 := _T
 62 [-]: GETTABLE  R1 R1 K12    ; R1 := R1[0x1c5b546f]
 63 [-]: GETGLOBAL R2 K13       ; R2 := 0xae91e43b
 64 [-]: MOVE      R3 R0        ; R3 := R0
 65 [-]: GETGLOBAL R4 K14       ; R4 := 0xcd0165a3
 66 [-]: LOADK     R5 1         ; R5 := 1.000000
 67 [-]: CALL      R4 2 0       ; R4,... := R4(R5)
 68 [-]: CALL      R1 0 1       ; R1(R2,...)
 69 [-]: RETURN    R0 1         ; return 


; Function #7.1:
;
; Name:            
; Defined at line: 190
; #Upvalues:       3
; #Parameters:     0
; Is_vararg:       0
; Max Stack Size:  4

  1 [-]: GETGLOBAL R0 K0        ; R0 := 0x7b998233
  2 [-]: GETGLOBAL R1 K1        ; R1 := _T
  3 [-]: GETUPVAL  R2 U0        ; R2 := U0
  4 [-]: GETUPVAL  R3 U1        ; R3 := U1
  5 [-]: GETTABLE  R2 R2 R3     ; R2 := R2[R3]
  6 [-]: GETTABLE  R2 R2 K2     ; R2 := R2["CallBack"]
  7 [-]: GETTABLE  R1 R1 R2     ; R1 := R1[R2]
  8 [-]: CALL      R0 2 2       ; R0 := R0(R1)
  9 [-]: TEST      R0 1         ; if R0 then PC := 19
 10 [-]: JMP       19           ; PC := 19
 11 [-]: GETGLOBAL R0 K1        ; R0 := _T
 12 [-]: GETUPVAL  R1 U0        ; R1 := U0
 13 [-]: GETUPVAL  R2 U1        ; R2 := U1
 14 [-]: GETTABLE  R1 R1 R2     ; R1 := R1[R2]
 15 [-]: GETTABLE  R1 R1 K2     ; R1 := R1["CallBack"]
 16 [-]: GETTABLE  R0 R0 R1     ; R0 := R0[R1]
 17 [-]: GETUPVAL  R1 U2        ; R1 := U2
 18 [-]: CALL      R0 2 1       ; R0(R1)
 19 [-]: RETURN    R0 1         ; return 


; Function #8:
;
; Name:            
; Defined at line: 209
; #Upvalues:       1
; #Parameters:     0
; Is_vararg:       0
; Max Stack Size:  2

  1 [-]: GETUPVAL  R0 U0        ; R0 := U0
  2 [-]: CALL      R0 1 1       ; R0()
  3 [-]: RETURN    R0 1         ; return 


; Function #9:
;
; Name:            
; Defined at line: 213
; #Upvalues:       3
; #Parameters:     0
; Is_vararg:       0
; Max Stack Size:  3

  1 [-]: NEWTABLE  R0 0 0       ; R0 := {}
  2 [-]: SETUPVAL  R0 U0        ; U82 := R0
  3 [-]: GETUPVAL  R0 U1        ; R0 := U1
  4 [-]: SELF      R0 R0 K0     ; R1 := R0; R0 := R0[0xea061e98]
  5 [-]: CLOSURE   R2 0         ; R2 := closure(Function #9.1)
  6 [-]: GETUPVAL  R0 U0        ; R0 := U0
  7 [-]: CALL      R0 3 1       ; R0(R1,R2)
  8 [-]: GETUPVAL  R0 U2        ; R0 := U2
  9 [-]: CALL      R0 1 1       ; R0()
 10 [-]: RETURN    R0 1         ; return 


; Function #9.1:
;
; Name:            
; Defined at line: 217
; #Upvalues:       1
; #Parameters:     1
; Is_vararg:       0
; Max Stack Size:  4

  1 [-]: GETTABLE  R1 R0 K0     ; R1 := R0["mSelected"]
  2 [-]: TEST      R1 0         ; if not R1 then PC := 9
  3 [-]: JMP       9            ; PC := 9
  4 [-]: GETGLOBAL R1 K1        ; R1 := 0x33bdd652
  5 [-]: GETTABLE  R1 R1 K2     ; R1 := R1[0x23d5322f]
  6 [-]: GETUPVAL  R2 U0        ; R2 := U0
  7 [-]: MOVE      R3 R0        ; R3 := R0
  8 [-]: CALL      R1 3 1       ; R1(R2,R3)
  9 [-]: RETURN    R0 1         ; return 


; Function #10:
;
; Name:            
; Defined at line: 226
; #Upvalues:       2
; #Parameters:     1
; Is_vararg:       0
; Max Stack Size:  4

  1 [-]: EQ        0 R0 K1      ; if R0 ~= 4.000000 then PC := 6
  2 [-]: JMP       6            ; PC := 6
  3 [-]: GETUPVAL  R1 U0        ; R1 := U0
  4 [-]: CALL      R1 1 1       ; R1()
  5 [-]: JMP       10           ; PC := 10
  6 [-]: GETUPVAL  R1 U1        ; R1 := U1
  7 [-]: SELF      R1 R1 K2     ; R2 := R1; R1 := R1[0xea061e98]
  8 [-]: CLOSURE   R3 0         ; R3 := closure(Function #10.1)
  9 [-]: CALL      R1 3 1       ; R1(R2,R3)
 10 [-]: RETURN    R0 1         ; return 


; Function #10.1:
;
; Name:            
; Defined at line: 231
; #Upvalues:       0
; #Parameters:     1
; Is_vararg:       0
; Max Stack Size:  3

  1 [-]: GETTABLE  R1 R0 K0     ; R1 := R0["mSelected"]
  2 [-]: TEST      R1 0         ; if not R1 then PC := 16
  3 [-]: JMP       16           ; PC := 16
  4 [-]: GETGLOBAL R1 K1        ; R1 := 0x7b998233
  5 [-]: GETGLOBAL R2 K2        ; R2 := _T
  6 [-]: GETTABLE  R2 R2 K3     ; R2 := R2["MenuOnUnfocusedCallback"]
  7 [-]: CALL      R1 2 2       ; R1 := R1(R2)
  8 [-]: TEST      R1 1         ; if R1 then PC := 16
  9 [-]: JMP       16           ; PC := 16
 10 [-]: SETTABLE  R0 K0 K4     ; R0["mSelected"] := nil
 11 [-]: GETGLOBAL R1 K2        ; R1 := _T
 12 [-]: GETTABLE  R1 R1 K5     ; R1 := R1[0x2c660803]
 13 [-]: MOVE      R2 R0        ; R2 := R0
 14 [-]: CALL      R1 2 1       ; R1(R2)
 15 [-]: JMP       17           ; PC := 17
 16 [-]: SETTABLE  R0 K0 K4     ; R0["mSelected"] := nil
 17 [-]: RETURN    R0 1         ; return 


; Function #11:
;
; Name:            
; Defined at line: 242
; #Upvalues:       3
; #Parameters:     0
; Is_vararg:       0
; Max Stack Size:  3

  1 [-]: GETGLOBAL R0 K0        ; R0 := 0x7b998233
  2 [-]: GETUPVAL  R1 U0        ; R1 := U0
  3 [-]: CALL      R0 2 2       ; R0 := R0(R1)
  4 [-]: TEST      R0 1         ; if R0 then PC := 14
  5 [-]: JMP       14           ; PC := 14
  6 [-]: GETUPVAL  R0 U1        ; R0 := U1
  7 [-]: GETTABLE  R0 R0 K1     ; R0 := R0[0xf616a184]
  8 [-]: GETUPVAL  R1 U0        ; R1 := U0
  9 [-]: LOADK     R2 K2        ; R2 := "ConfirmSelection"
 10 [-]: CALL      R0 3 1       ; R0(R1,R2)
 11 [-]: LOADNIL   R0 R0        ; R0 := nil
 12 [-]: SETUPVAL  R0 U0        ; U82 := R0
 13 [-]: JMP       16           ; PC := 16
 14 [-]: GETUPVAL  R0 U2        ; R0 := U2
 15 [-]: CALL      R0 1 1       ; R0()
 16 [-]: RETURN    R0 1         ; return 


; Function #12:
;
; Name:            
; Defined at line: 251
; #Upvalues:       19
; #Parameters:     0
; Is_vararg:       0
; Max Stack Size:  6

  1 [-]: GETGLOBAL R0 K0        ; R0 := 0x3d106989
  2 [-]: LOADK     R1 K1        ; R1 := "InitializeSettings()"
  3 [-]: CALL      R0 2 1       ; R0(R1)
  4 [-]: GETGLOBAL R0 K2        ; R0 := 0x2d0fad09
  5 [-]: LOADK     R1 K3        ; R1 := "EE.Interface.Components.List"
  6 [-]: CALL      R0 2 2       ; R0 := R0(R1)
  7 [-]: GETTABLE  R1 R0 K4     ; R1 := R0[0x9383bc56]
  8 [-]: GETGLOBAL R2 K5        ; R2 := 0xae91e43b
  9 [-]: LOADK     R3 K6        ; R3 := "Container.ButtonContainer.Element"
 10 [-]: CALL      R1 3 2       ; R1 := R1(R2,R3)
 11 [-]: SETUPVAL  R1 U0        ; U82 := R0
 12 [-]: GETUPVAL  R1 U0        ; R1 := U0
 13 [-]: SELF      R1 R1 K7     ; R2 := R1; R1 := R1[0x1e5b5cfe]
 14 [-]: LOADK     R3 K8        ; R3 := "MenuEntryPressed"
 15 [-]: LOADK     R4 K9        ; R4 := "MenuEntryFocused"
 16 [-]: LOADK     R5 K10       ; R5 := "MenuEntryUnfocused"
 17 [-]: CALL      R1 5 1       ; R1(R2,R3,R4,R5)
 18 [-]: GETUPVAL  R1 U0        ; R1 := U0
 19 [-]: GETUPVAL  R2 U1        ; R2 := U1
 20 [-]: GETTABLE  R2 R2 K12    ; R2 := R2[0x06d055f9]
 21 [-]: GETUPVAL  R3 U2        ; R3 := U2
 22 [-]: LOADK     R4 32        ; R4 := 32.000000
 23 [-]: LOADK     R5 42        ; R5 := 42.000000
 24 [-]: CALL      R2 4 2       ; R2 := R2(R3,R4,R5)
 25 [-]: SETTABLE  R1 K11 R2    ; R1["mForcedVerticalSeparation"] := R2
 26 [-]: GETGLOBAL R1 K13       ; R1 := 0x34291f5c
 27 [-]: GETTABLE  R1 R1 K14    ; R1 := R1[0xe6b41adb]
 28 [-]: CALL      R1 1 2       ; R1 := R1()
 29 [-]: TEST      R1 1         ; if R1 then PC := 34
 30 [-]: JMP       34           ; PC := 34
 31 [-]: GETUPVAL  R1 U0        ; R1 := U0
 32 [-]: SETTABLE  R1 K15 K16   ; R1["mVisibleElements"] := 16.000000
 33 [-]: JMP       36           ; PC := 36
 34 [-]: GETUPVAL  R1 U0        ; R1 := U0
 35 [-]: SETTABLE  R1 K15 K17   ; R1["mVisibleElements"] := 10.000000
 36 [-]: GETUPVAL  R1 U0        ; R1 := U0
 37 [-]: SETTABLE  R1 K18 K19   ; R1["mElementTransitionTime"] := 0.000000
 38 [-]: GETUPVAL  R1 U0        ; R1 := U0
 39 [-]: SELF      R1 R1 K20    ; R2 := R1; R1 := R1[0x3bc79f4f]
 40 [-]: LOADK     R3 K21       ; R3 := "Container.ScrollBar"
 41 [-]: LOADK     R4 -4        ; R4 := -4.000000
 42 [-]: CALL      R1 4 1       ; R1(R2,R3,R4)
 43 [-]: GETUPVAL  R1 U0        ; R1 := U0
 44 [-]: CLOSURE   R2 0         ; R2 := closure(Function #12.1)
 45 [-]: SETTABLE  R1 K22 R2    ; R1["Print"] := R2
 46 [-]: GETUPVAL  R1 U0        ; R1 := U0
 47 [-]: CLOSURE   R2 1         ; R2 := closure(Function #12.2)
 48 [-]: GETUPVAL  R0 U3        ; R0 := U3
 49 [-]: GETUPVAL  R0 U4        ; R0 := U4
 50 [-]: GETUPVAL  R0 U1        ; R0 := U1
 51 [-]: GETUPVAL  R0 U5        ; R0 := U5
 52 [-]: GETUPVAL  R0 U6        ; R0 := U6
 53 [-]: GETUPVAL  R0 U7        ; R0 := U7
 54 [-]: SETTABLE  R1 K23 R2    ; R1["mOnFocusedCallback"] := R2
 55 [-]: GETUPVAL  R1 U0        ; R1 := U0
 56 [-]: CLOSURE   R2 2         ; R2 := closure(Function #12.3)
 57 [-]: GETUPVAL  R0 U8        ; R0 := U8
 58 [-]: SETTABLE  R1 K24 R2    ; R1["mOnUnfocusedCallback"] := R2
 59 [-]: GETUPVAL  R1 U0        ; R1 := U0
 60 [-]: CLOSURE   R2 3         ; R2 := closure(Function #12.4)
 61 [-]: GETUPVAL  R0 U3        ; R0 := U3
 62 [-]: GETUPVAL  R0 U9        ; R0 := U9
 63 [-]: GETUPVAL  R0 U0        ; R0 := U0
 64 [-]: GETUPVAL  R0 U10       ; R0 := U10
 65 [-]: GETUPVAL  R0 U11       ; R0 := U11
 66 [-]: GETUPVAL  R0 U12       ; R0 := U12
 67 [-]: GETUPVAL  R0 U13       ; R0 := U13
 68 [-]: GETUPVAL  R0 U1        ; R0 := U1
 69 [-]: SETTABLE  R1 K25 R2    ; R1["mOnSelectedCallback"] := R2
 70 [-]: GETUPVAL  R1 U0        ; R1 := U0
 71 [-]: CLOSURE   R2 4         ; R2 := closure(Function #12.5)
 72 [-]: SETTABLE  R1 K26 R2    ; R1["RepositionButton"] := R2
 73 [-]: GETUPVAL  R1 U0        ; R1 := U0
 74 [-]: CLOSURE   R2 5         ; R2 := closure(Function #12.6)
 75 [-]: GETUPVAL  R0 U2        ; R0 := U2
 76 [-]: GETUPVAL  R0 U14       ; R0 := U14
 77 [-]: SETTABLE  R1 K27 R2    ; R1["mClipCreatedCallback"] := R2
 78 [-]: GETUPVAL  R1 U0        ; R1 := U0
 79 [-]: CLOSURE   R2 6         ; R2 := closure(Function #12.7)
 80 [-]: GETUPVAL  R0 U2        ; R0 := U2
 81 [-]: GETUPVAL  R0 U15       ; R0 := U15
 82 [-]: GETUPVAL  R0 U1        ; R0 := U1
 83 [-]: GETUPVAL  R0 U16       ; R0 := U16
 84 [-]: GETUPVAL  R0 U0        ; R0 := U0
 85 [-]: GETUPVAL  R0 U17       ; R0 := U17
 86 [-]: GETUPVAL  R0 U18       ; R0 := U18
 87 [-]: SETTABLE  R1 K28 R2    ; R1["mElementDrawCallback"] := R2
 88 [-]: GETUPVAL  R1 U0        ; R1 := U0
 89 [-]: CLOSURE   R2 7         ; R2 := closure(Function #12.8)
 90 [-]: SETTABLE  R1 K29 R2    ; R1["ToggleFocusedElement"] := R2
 91 [-]: RETURN    R0 1         ; return 


; Function #12.1:
;
; Name:            
; Defined at line: 266
; #Upvalues:       0
; #Parameters:     2
; Is_vararg:       0
; Max Stack Size:  2

  1 [-]: RETURN    R0 1         ; return 


; Function #12.2:
;
; Name:            
; Defined at line: 270
; #Upvalues:       6
; #Parameters:     1
; Is_vararg:       0
; Max Stack Size:  7

  1 [-]: GETTABLE  R1 R0 K0     ; R1 := R0["mEnabled"]
  2 [-]: TEST      R1 0         ; if not R1 then PC := 7
  3 [-]: JMP       7            ; PC := 7
  4 [-]: GETUPVAL  R1 U0        ; R1 := U0
  5 [-]: TEST      R1 0         ; if not R1 then PC := 8
  6 [-]: JMP       8            ; PC := 8
  7 [-]: RETURN    R0 1         ; return 
  8 [-]: GETGLOBAL R1 K1        ; R1 := 0x7b998233
  9 [-]: GETUPVAL  R2 U1        ; R2 := U1
 10 [-]: CALL      R1 2 2       ; R1 := R1(R2)
 11 [-]: TEST      R1 1         ; if R1 then PC := 18
 12 [-]: JMP       18           ; PC := 18
 13 [-]: GETUPVAL  R1 U2        ; R1 := U2
 14 [-]: GETTABLE  R1 R1 K2     ; R1 := R1[0x659d451f]
 15 [-]: GETUPVAL  R2 U1        ; R2 := U1
 16 [-]: CALL      R1 2 1       ; R1(R2)
 17 [-]: JMP       23           ; PC := 23
 18 [-]: GETUPVAL  R1 U2        ; R1 := U2
 19 [-]: GETTABLE  R1 R1 K2     ; R1 := R1[0x659d451f]
 20 [-]: GETGLOBAL R2 K3        ; R2 := 0x0032441c
 21 [-]: GETTABLE  R2 R2 K4     ; R2 := R2["UISound_Focus"]
 22 [-]: CALL      R1 2 1       ; R1(R2)
 23 [-]: SETUPVAL  R0 U3        ; U82 := R3
 24 [-]: SETTABLE  R0 K5 K6     ; R0["mFocused"] := true
 25 [-]: GETTABLE  R1 R0 K7     ; R1 := R0["mClipName"]
 26 [-]: EQ        1 R1 K8      ; if R1 == nil then PC := 66
 27 [-]: JMP       66           ; PC := 66
 28 [-]: GETTABLE  R1 R0 K9     ; R1 := R0["mToolTip"]
 29 [-]: EQ        1 R1 K8      ; if R1 == nil then PC := 66
 30 [-]: JMP       66           ; PC := 66
 31 [-]: GETGLOBAL R1 K10       ; R1 := _T
 32 [-]: GETTABLE  R2 R0 K9     ; R2 := R0["mToolTip"]
 33 [-]: SETTABLE  R1 K11 R2    ; R1["gToolTip"] := R2
 34 [-]: GETGLOBAL R1 K12       ; R1 := 0x34291f5c
 35 [-]: GETTABLE  R1 R1 K13    ; R1 := R1[0x056bfe8b]
 36 [-]: CALL      R1 1 2       ; R1 := R1()
 37 [-]: TEST      R1 0         ; if not R1 then PC := 66
 38 [-]: JMP       66           ; PC := 66
 39 [-]: GETUPVAL  R1 U2        ; R1 := U2
 40 [-]: GETTABLE  R1 R1 K14    ; R1 := R1[0xb5be5d4a]
 41 [-]: GETGLOBAL R2 K15       ; R2 := 0xae91e43b
 42 [-]: GETTABLE  R3 R0 K7     ; R3 := R0["mClipName"]
 43 [-]: LOADK     R4 K16       ; R4 := ".Button"
 44 [-]: CONCAT    R3 R3 R4     ; R3 := R3 .. R4
 45 [-]: CALL      R1 3 3       ; R1,R2 := R1(R2,R3)
 46 [-]: EQ        1 R1 K17     ; if R1 == 0.000000 then PC := 66
 47 [-]: JMP       66           ; PC := 66
 48 [-]: EQ        1 R2 K17     ; if R2 == 0.000000 then PC := 66
 49 [-]: JMP       66           ; PC := 66
 50 [-]: GETUPVAL  R3 U4        ; R3 := U4
 51 [-]: ADD       R1 R1 R3     ; R1 := R1 + R3
 52 [-]: GETUPVAL  R3 U2        ; R3 := U2
 53 [-]: GETTABLE  R3 R3 K18    ; R3 := R3[0x6d7e6810]
 54 [-]: GETGLOBAL R4 K15       ; R4 := 0xae91e43b
 55 [-]: NEWTABLE  R5 0 2       ; R5 := {}
 56 [-]: SETTABLE  R5 K19 R1    ; R5["x"] := R1
 57 [-]: SETTABLE  R5 K20 R2    ; R5["y"] := R2
 58 [-]: CALL      R3 3 2       ; R3 := R3(R4,R5)
 59 [-]: GETGLOBAL R4 K10       ; R4 := _T
 60 [-]: NEWTABLE  R5 0 2       ; R5 := {}
 61 [-]: GETTABLE  R6 R3 K19    ; R6 := R3["x"]
 62 [-]: SETTABLE  R5 K19 R6    ; R5["x"] := R6
 63 [-]: GETTABLE  R6 R3 K20    ; R6 := R3["y"]
 64 [-]: SETTABLE  R5 K20 R6    ; R5["y"] := R6
 65 [-]: SETTABLE  R4 K21 R5    ; R4["gToolTipCoords"] := R5
 66 [-]: GETGLOBAL R4 K10       ; R4 := _T
 67 [-]: GETUPVAL  R5 U5        ; R5 := U5
 68 [-]: GETTABLE  R4 R4 R5     ; R4 := R4[R5]
 69 [-]: EQ        1 R4 K8      ; if R4 == nil then PC := 76
 70 [-]: JMP       76           ; PC := 76
 71 [-]: GETGLOBAL R4 K10       ; R4 := _T
 72 [-]: GETUPVAL  R5 U5        ; R5 := U5
 73 [-]: GETTABLE  R4 R4 R5     ; R4 := R4[R5]
 74 [-]: MOVE      R5 R0        ; R5 := R0
 75 [-]: CALL      R4 2 1       ; R4(R5)
 76 [-]: RETURN    R0 1         ; return 


; Function #12.3:
;
; Name:            
; Defined at line: 303
; #Upvalues:       1
; #Parameters:     1
; Is_vararg:       0
; Max Stack Size:  3

  1 [-]: SETTABLE  R0 K0 K1     ; R0["mFocused"] := false
  2 [-]: GETGLOBAL R1 K2        ; R1 := _T
  3 [-]: SETTABLE  R1 K3 K4     ; R1["gToolTip"] := nil
  4 [-]: GETGLOBAL R1 K2        ; R1 := _T
  5 [-]: SETTABLE  R1 K5 K4     ; R1["gToolTipCoords"] := nil
  6 [-]: GETGLOBAL R1 K2        ; R1 := _T
  7 [-]: GETUPVAL  R2 U0        ; R2 := U0
  8 [-]: GETTABLE  R1 R1 R2     ; R1 := R1[R2]
  9 [-]: EQ        1 R1 K4      ; if R1 == nil then PC := 16
 10 [-]: JMP       16           ; PC := 16
 11 [-]: GETGLOBAL R1 K2        ; R1 := _T
 12 [-]: GETUPVAL  R2 U0        ; R2 := U0
 13 [-]: GETTABLE  R1 R1 R2     ; R1 := R1[R2]
 14 [-]: MOVE      R2 R0        ; R2 := R0
 15 [-]: CALL      R1 2 1       ; R1(R2)
 16 [-]: RETURN    R0 1         ; return 


; Function #12.4:
;
; Name:            
; Defined at line: 313
; #Upvalues:       8
; #Parameters:     1
; Is_vararg:       0
; Max Stack Size:  4

  1 [-]: GETTABLE  R1 R0 K0     ; R1 := R0["mEnabled"]
  2 [-]: TEST      R1 0         ; if not R1 then PC := 7
  3 [-]: JMP       7            ; PC := 7
  4 [-]: GETUPVAL  R1 U0        ; R1 := U0
  5 [-]: TEST      R1 0         ; if not R1 then PC := 8
  6 [-]: JMP       8            ; PC := 8
  7 [-]: RETURN    R0 1         ; return 
  8 [-]: GETGLOBAL R1 K1        ; R1 := 0x7b998233
  9 [-]: GETGLOBAL R2 K2        ; R2 := _T
 10 [-]: GETUPVAL  R3 U1        ; R3 := U1
 11 [-]: GETTABLE  R2 R2 R3     ; R2 := R2[R3]
 12 [-]: CALL      R1 2 2       ; R1 := R1(R2)
 13 [-]: TEST      R1 1         ; if R1 then PC := 22
 14 [-]: JMP       22           ; PC := 22
 15 [-]: GETGLOBAL R1 K2        ; R1 := _T
 16 [-]: GETUPVAL  R2 U1        ; R2 := U1
 17 [-]: GETTABLE  R1 R1 R2     ; R1 := R1[R2]
 18 [-]: GETUPVAL  R2 U2        ; R2 := U2
 19 [-]: MOVE      R3 R0        ; R3 := R0
 20 [-]: CALL      R1 3 1       ; R1(R2,R3)
 21 [-]: RETURN    R0 1         ; return 
 22 [-]: GETGLOBAL R1 K3        ; R1 := 0x34291f5c
 23 [-]: GETTABLE  R1 R1 K4     ; R1 := R1[0x1467d5f4]
 24 [-]: CALL      R1 1 2       ; R1 := R1()
 25 [-]: TEST      R1 1         ; if R1 then PC := 44
 26 [-]: JMP       44           ; PC := 44
 27 [-]: GETTABLE  R1 R0 K5     ; R1 := R0["mSelected"]
 28 [-]: TEST      R1 0         ; if not R1 then PC := 41
 29 [-]: JMP       41           ; PC := 41
 30 [-]: GETGLOBAL R1 K6        ; R1 := 0x55156ff7
 31 [-]: CALL      R1 1 2       ; R1 := R1()
 32 [-]: GETUPVAL  R2 U3        ; R2 := U3
 33 [-]: SUB       R1 R1 R2     ; R1 := R1 - R2
 34 [-]: LT        0 R1 K7      ; if R1 >= 0.500000 then PC := 41
 35 [-]: JMP       41           ; PC := 41
 36 [-]: GETTABLE  R1 R0 K8     ; R1 := R0["mConfirmMsg"]
 37 [-]: SETUPVAL  R1 U4        ; U82 := R4
 38 [-]: GETUPVAL  R1 U5        ; R1 := U5
 39 [-]: CALL      R1 1 1       ; R1()
 40 [-]: RETURN    R0 1         ; return 
 41 [-]: GETGLOBAL R1 K6        ; R1 := 0x55156ff7
 42 [-]: CALL      R1 1 2       ; R1 := R1()
 43 [-]: SETUPVAL  R1 U3        ; U82 := R3
 44 [-]: GETGLOBAL R1 K1        ; R1 := 0x7b998233
 45 [-]: GETUPVAL  R2 U6        ; R2 := U6
 46 [-]: CALL      R1 2 2       ; R1 := R1(R2)
 47 [-]: TEST      R1 1         ; if R1 then PC := 54
 48 [-]: JMP       54           ; PC := 54
 49 [-]: GETUPVAL  R1 U7        ; R1 := U7
 50 [-]: GETTABLE  R1 R1 K9     ; R1 := R1[0x659d451f]
 51 [-]: GETUPVAL  R2 U6        ; R2 := U6
 52 [-]: CALL      R1 2 1       ; R1(R2)
 53 [-]: JMP       59           ; PC := 59
 54 [-]: GETUPVAL  R1 U7        ; R1 := U7
 55 [-]: GETTABLE  R1 R1 K9     ; R1 := R1[0x659d451f]
 56 [-]: GETGLOBAL R2 K10       ; R2 := 0x0032441c
 57 [-]: GETTABLE  R2 R2 K11    ; R2 := R2["UISound_ButtonSelect"]
 58 [-]: CALL      R1 2 1       ; R1(R2)
 59 [-]: GETTABLE  R1 R0 K5     ; R1 := R0["mSelected"]
 60 [-]: NOT       R1 R1        ; R1 := not R1
 61 [-]: SETTABLE  R0 K5 R1     ; R0["mSelected"] := R1
 62 [-]: GETUPVAL  R1 U2        ; R1 := U2
 63 [-]: GETTABLE  R1 R1 K12    ; R1 := R1[0xb15e6aca]
 64 [-]: MOVE      R2 R0        ; R2 := R0
 65 [-]: CALL      R1 2 1       ; R1(R2)
 66 [-]: GETTABLE  R1 R0 K5     ; R1 := R0["mSelected"]
 67 [-]: TEST      R1 0         ; if not R1 then PC := 73
 68 [-]: JMP       73           ; PC := 73
 69 [-]: GETTABLE  R1 R0 K8     ; R1 := R0["mConfirmMsg"]
 70 [-]: SETUPVAL  R1 U4        ; U82 := R4
 71 [-]: GETUPVAL  R1 U5        ; R1 := U5
 72 [-]: CALL      R1 1 1       ; R1()
 73 [-]: RETURN    R0 1         ; return 


; Function #12.5:
;
; Name:            
; Defined at line: 348
; #Upvalues:       0
; #Parameters:     2
; Is_vararg:       0
; Max Stack Size:  2

  1 [-]: RETURN    R0 1         ; return 


; Function #12.6:
;
; Name:            
; Defined at line: 352
; #Upvalues:       2
; #Parameters:     1
; Is_vararg:       0
; Max Stack Size:  7

  1 [-]: GETUPVAL  R1 U0        ; R1 := U0
  2 [-]: TEST      R1 1         ; if R1 then PC := 12
  3 [-]: JMP       12           ; PC := 12
  4 [-]: GETGLOBAL R1 K0        ; R1 := 0xae91e43b
  5 [-]: SELF      R1 R1 K1     ; R2 := R1; R1 := R1[0xf64b7262]
  6 [-]: MOVE      R3 R0        ; R3 := R0
  7 [-]: LOADK     R4 K2        ; R4 := "Button.Bg"
  8 [-]: LOADK     R5 12        ; R5 := 12.000000
  9 [-]: GETUPVAL  R6 U1        ; R6 := U1
 10 [-]: SUB       R6 R6 K3     ; R6 := R6 - 20.000000
 11 [-]: CALL      R1 6 1       ; R1(R2,R3,R4,R5,R6)
 12 [-]: GETGLOBAL R1 K0        ; R1 := 0xae91e43b
 13 [-]: SELF      R1 R1 K1     ; R2 := R1; R1 := R1[0xf64b7262]
 14 [-]: MOVE      R3 R0        ; R3 := R0
 15 [-]: LOADK     R4 K4        ; R4 := "Button.Btn"
 16 [-]: LOADK     R5 12        ; R5 := 12.000000
 17 [-]: GETUPVAL  R6 U1        ; R6 := U1
 18 [-]: SUB       R6 R6 K3     ; R6 := R6 - 20.000000
 19 [-]: CALL      R1 6 1       ; R1(R2,R3,R4,R5,R6)
 20 [-]: RETURN    R0 1         ; return 


; Function #12.7:
;
; Name:            
; Defined at line: 359
; #Upvalues:       7
; #Parameters:     1
; Is_vararg:       0
; Max Stack Size:  14

  1 [-]: GETTABLE  R1 R0 K0     ; R1 := R0["mClipName"]
  2 [-]: EQ        0 R1 K1      ; if R1 ~= nil then PC := 5
  3 [-]: JMP       5            ; PC := 5
  4 [-]: RETURN    R0 1         ; return 
  5 [-]: GETGLOBAL R2 K2        ; R2 := 0xae91e43b
  6 [-]: SELF      R2 R2 K3     ; R3 := R2; R2 := R2[0x42b04007]
  7 [-]: GETTABLE  R4 R0 K4     ; R4 := R0["mName"]
  8 [-]: LOADBOOL  R5 1 0       ; R5 := true
  9 [-]: CALL      R2 4 2       ; R2 := R2(R3,R4,R5)
 10 [-]: GETUPVAL  R3 U0        ; R3 := U0
 11 [-]: TEST      R3 0         ; if not R3 then PC := 21
 12 [-]: JMP       21           ; PC := 21
 13 [-]: GETGLOBAL R3 K2        ; R3 := 0xae91e43b
 14 [-]: SELF      R3 R3 K3     ; R4 := R3; R3 := R3[0x42b04007]
 15 [-]: LOADK     R5 K5        ; R5 := "<MINI_ARROW>"
 16 [-]: LOADBOOL  R6 1 0       ; R6 := true
 17 [-]: CALL      R3 4 2       ; R3 := R3(R4,R5,R6)
 18 [-]: LOADK     R4 K6        ; R4 := " "
 19 [-]: MOVE      R5 R2        ; R5 := R2
 20 [-]: CONCAT    R2 R3 R5     ; R2 := R3 .. R4 .. R5
 21 [-]: GETUPVAL  R3 U1        ; R3 := U1
 22 [-]: TEST      R3 0         ; if not R3 then PC := 28
 23 [-]: JMP       28           ; PC := 28
 24 [-]: GETGLOBAL R3 K7        ; R3 := 0x5f0788c4
 25 [-]: MOVE      R4 R2        ; R4 := R2
 26 [-]: CALL      R3 2 2       ; R3 := R3(R4)
 27 [-]: MOVE      R2 R3        ; R2 := R3
 28 [-]: GETGLOBAL R3 K2        ; R3 := 0xae91e43b
 29 [-]: SELF      R3 R3 K8     ; R4 := R3; R3 := R3[0xe261aa96]
 30 [-]: MOVE      R5 R1        ; R5 := R1
 31 [-]: LOADK     R6 K9        ; R6 := "RightText"
 32 [-]: LOADK     R7 29        ; R7 := 29.000000
 33 [-]: GETUPVAL  R8 U2        ; R8 := U2
 34 [-]: GETTABLE  R8 R8 K10    ; R8 := R8[0x06d055f9]
 35 [-]: GETTABLE  R9 R0 K11    ; R9 := R0["mRightText"]
 36 [-]: EQ        0 R9 K1      ; if R9 ~= nil then PC := 39
 37 [-]: JMP       39           ; PC := 39
 38 [-]: LOADBOOL  R9 0 1       ; R9 := false; PC := 39
 39 [-]: LOADBOOL  R9 1 0       ; R9 := true
 40 [-]: GETTABLE  R10 R0 K11   ; R10 := R0["mRightText"]
 41 [-]: LOADK     R11 K12      ; R11 := ""
 42 [-]: CALL      R8 4 0       ; R8,... := R8(R9,R10,R11)
 43 [-]: CALL      R3 0 1       ; R3(R4,...)
 44 [-]: GETGLOBAL R3 K2        ; R3 := 0xae91e43b
 45 [-]: SELF      R3 R3 K13    ; R4 := R3; R3 := R3[0x19ad3f57]
 46 [-]: MOVE      R5 R1        ; R5 := R1
 47 [-]: LOADK     R6 K14       ; R6 := "Button"
 48 [-]: LOADK     R7 K15       ; R7 := "Id"
 49 [-]: GETTABLE  R8 R0 K15    ; R8 := R0["Id"]
 50 [-]: CALL      R3 6 1       ; R3(R4,R5,R6,R7,R8)
 51 [-]: GETUPVAL  R3 U3        ; R3 := U3
 52 [-]: GETTABLE  R3 R3 K16    ; R3 := R3[0xae6791ba]
 53 [-]: GETGLOBAL R4 K2        ; R4 := 0xae91e43b
 54 [-]: MOVE      R5 R1        ; R5 := R1
 55 [-]: LOADK     R6 K17       ; R6 := ".Button"
 56 [-]: CONCAT    R5 R5 R6     ; R5 := R5 .. R6
 57 [-]: MOVE      R6 R2        ; R6 := R2
 58 [-]: LOADK     R7 K18       ; R7 := "invalidCallback"
 59 [-]: LOADK     R8 K19       ; R8 := "<MENU_SELECT>"
 60 [-]: LOADNIL   R9 R11       ; R9 := R10 := R11 := nil
 61 [-]: NEWTABLE  R12 0 1      ; R12 := {}
 62 [-]: GETUPVAL  R13 U4       ; R13 := U4
 63 [-]: GETTABLE  R13 R13 K21  ; R13 := R13["mButtonWidth"]
 64 [-]: SETTABLE  R12 K20 R13  ; R12["mMaxSize"] := R13
 65 [-]: CALL      R3 10 2      ; R3 := R3(R4,R5,R6,R7,R8,R9,R10,R11,R12)
 66 [-]: SETTABLE  R0 K22 R3    ; R0["mButton"] := R3
 67 [-]: SETTABLE  R3 K23 K24   ; R3["mUnderlineAlpha"] := 0.000000
 68 [-]: SETTABLE  R3 K25 K26   ; R3["mHeight"] := 36.000000
 69 [-]: GETTABLE  R4 R3 K28    ; R4 := R3["SetFocus"]
 70 [-]: SETTABLE  R3 K27 R4    ; R3["ButtonSetFocus"] := R4
 71 [-]: CLOSURE   R4 0         ; R4 := closure(Function #12.7.1)
 72 [-]: GETUPVAL  R0 U4        ; R0 := U4
 73 [-]: SETTABLE  R3 K28 R4    ; R3["SetFocus"] := R4
 74 [-]: GETTABLE  R4 R3 K30    ; R4 := R3["Pressed"]
 75 [-]: SETTABLE  R3 K29 R4    ; R3["ButtonPressed"] := R4
 76 [-]: CLOSURE   R4 1         ; R4 := closure(Function #12.7.2)
 77 [-]: GETUPVAL  R0 U4        ; R0 := U4
 78 [-]: SETTABLE  R3 K30 R4    ; R3["Pressed"] := R4
 79 [-]: GETTABLE  R4 R3 K32    ; R4 := R3["Resize"]
 80 [-]: SETTABLE  R3 K31 R4    ; R3["ButtonResize"] := R4
 81 [-]: CLOSURE   R4 2         ; R4 := closure(Function #12.7.3)
 82 [-]: MOVE      R0 R3        ; R0 := R3
 83 [-]: MOVE      R0 R1        ; R0 := R1
 84 [-]: SETTABLE  R3 K32 R4    ; R3["Resize"] := R4
 85 [-]: GETGLOBAL R4 K2        ; R4 := 0xae91e43b
 86 [-]: SELF      R4 R4 K8     ; R5 := R4; R4 := R4[0xe261aa96]
 87 [-]: GETTABLE  R6 R3 K0     ; R6 := R3["mClipName"]
 88 [-]: LOADK     R7 K33       ; R7 := "Label"
 89 [-]: LOADK     R8 38        ; R8 := 38.000000
 90 [-]: LOADK     R9 K34       ; R9 := "center"
 91 [-]: CALL      R4 6 1       ; R4(R5,R6,R7,R8,R9)
 92 [-]: GETGLOBAL R4 K2        ; R4 := 0xae91e43b
 93 [-]: SELF      R4 R4 K35    ; R5 := R4; R4 := R4[0xc0a3774b]
 94 [-]: GETTABLE  R6 R3 K0     ; R6 := R3["mClipName"]
 95 [-]: LOADK     R7 K33       ; R7 := "Label"
 96 [-]: LOADK     R8 46        ; R8 := 46.000000
 97 [-]: LOADBOOL  R9 1 0       ; R9 := true
 98 [-]: CALL      R4 6 1       ; R4(R5,R6,R7,R8,R9)
 99 [-]: GETUPVAL  R4 U0        ; R4 := U0
100 [-]: TEST      R4 0         ; if not R4 then PC := 106
101 [-]: JMP       106          ; PC := 106
102 [-]: SETTABLE  R3 K36 K24   ; R3["mInnerAlpha"] := 0.000000
103 [-]: SETTABLE  R3 K37 K24   ; R3["mEdgeAlpha"] := 0.000000
104 [-]: SETTABLE  R3 K38 K39   ; R3["mShowHighlight"] := false
105 [-]: SETTABLE  R3 K40 K39   ; R3["mShowUnderline"] := false
106 [-]: GETTABLE  R4 R0 K41    ; R4 := R0["Type"]
107 [-]: GETUPVAL  R5 U5        ; R5 := U5
108 [-]: GETTABLE  R5 R5 K42    ; R5 := R5["TITLE"]
109 [-]: EQ        1 R4 R5      ; if R4 == R5 then PC := 119
110 [-]: JMP       119          ; PC := 119
111 [-]: SETTABLE  R3 K43 K39   ; R3["mToUpper"] := false
112 [-]: SETTABLE  R3 K44 K46   ; R3["mUnfocusedEdgeColor"] := 9.000000
113 [-]: GETTABLE  R4 R0 K41    ; R4 := R0["Type"]
114 [-]: GETUPVAL  R5 U5        ; R5 := U5
115 [-]: GETTABLE  R5 R5 K47    ; R5 := R5["ICONBUTTON"]
116 [-]: EQ        0 R4 R5      ; if R4 ~= R5 then PC := 129
117 [-]: JMP       129          ; PC := 129
118 [-]: JMP       129          ; PC := 129
119 [-]: SETTABLE  R0 K48 K39   ; R0["mEnabled"] := false
120 [-]: SETTABLE  R3 K38 K39   ; R3["mShowHighlight"] := false
121 [-]: SETTABLE  R3 K40 K39   ; R3["mShowUnderline"] := false
122 [-]: SETTABLE  R3 K49 K50   ; R3["mInactiveAlpha"] := 100.000000
123 [-]: GETUPVAL  R4 U6        ; R4 := U6
124 [-]: GETTABLE  R4 R4 K52    ; R4 := R4[0x5d10207d]
125 [-]: LOADK     R5 6         ; R5 := 6.000000
126 [-]: LOADBOOL  R6 1 0       ; R6 := true
127 [-]: CALL      R4 3 2       ; R4 := R4(R5,R6)
128 [-]: SETTABLE  R3 K51 R4    ; R3["mInactiveColor"] := R4
129 [-]: GETUPVAL  R4 U4        ; R4 := U4
130 [-]: GETTABLE  R4 R4 K21    ; R4 := R4["mButtonWidth"]
131 [-]: EQ        1 R4 K1      ; if R4 == nil then PC := 159
132 [-]: JMP       159          ; PC := 159
133 [-]: GETUPVAL  R4 U4        ; R4 := U4
134 [-]: GETTABLE  R4 R4 K21    ; R4 := R4["mButtonWidth"]
135 [-]: SETTABLE  R3 K53 R4    ; R3["mMinSize"] := R4
136 [-]: GETUPVAL  R4 U4        ; R4 := U4
137 [-]: GETTABLE  R4 R4 K21    ; R4 := R4["mButtonWidth"]
138 [-]: SETTABLE  R3 K20 R4    ; R3["mMaxSize"] := R4
139 [-]: GETGLOBAL R4 K2        ; R4 := 0xae91e43b
140 [-]: SELF      R4 R4 K54    ; R5 := R4; R4 := R4[0xf64b7262]
141 [-]: MOVE      R6 R1        ; R6 := R1
142 [-]: LOADK     R7 K9        ; R7 := "RightText"
143 [-]: LOADK     R8 0         ; R8 := 0.000000
144 [-]: GETUPVAL  R9 U4        ; R9 := U4
145 [-]: GETTABLE  R9 R9 K21    ; R9 := R9["mButtonWidth"]
146 [-]: GETUPVAL  R10 U4       ; R10 := U4
147 [-]: GETTABLE  R10 R10 K55  ; R10 := R10["mCalloutWidth"]
148 [-]: SUB       R9 R9 R10    ; R9 := R9 - R10
149 [-]: SUB       R9 R9 K56    ; R9 := R9 - 5.000000
150 [-]: CALL      R4 6 1       ; R4(R5,R6,R7,R8,R9)
151 [-]: GETGLOBAL R4 K2        ; R4 := 0xae91e43b
152 [-]: SELF      R4 R4 K54    ; R5 := R4; R4 := R4[0xf64b7262]
153 [-]: MOVE      R6 R1        ; R6 := R1
154 [-]: LOADK     R7 K9        ; R7 := "RightText"
155 [-]: LOADK     R8 12        ; R8 := 12.000000
156 [-]: GETUPVAL  R9 U4        ; R9 := U4
157 [-]: GETTABLE  R9 R9 K55    ; R9 := R9["mCalloutWidth"]
158 [-]: CALL      R4 6 1       ; R4(R5,R6,R7,R8,R9)
159 [-]: GETTABLE  R4 R0 K41    ; R4 := R0["Type"]
160 [-]: EQ        0 R4 K1      ; if R4 ~= nil then PC := 167
161 [-]: JMP       167          ; PC := 167
162 [-]: GETTABLE  R4 R0 K57    ; R4 := R0["Bold"]
163 [-]: EQ        0 R4 K39     ; if R4 ~= false then PC := 167
164 [-]: JMP       167          ; PC := 167
165 [-]: SETTABLE  R3 K58 K59   ; R3["mFormatPrefix"] := "<p><font face=\"Roboto\">"
166 [-]: SETTABLE  R3 K60 K61   ; R3["mFormatSuffix"] := "</font></p>"
167 [-]: SETTABLE  R3 K62 K39   ; R3["mShowCallout"] := false
168 [-]: SELF      R4 R3 K63    ; R5 := R3; R4 := R3[0x1403231b]
169 [-]: GETTABLE  R6 R0 K15    ; R6 := R0["Id"]
170 [-]: CALL      R4 3 1       ; R4(R5,R6)
171 [-]: SELF      R4 R3 K64    ; R5 := R3; R4 := R3[0x6b2ab44e]
172 [-]: LOADK     R6 K65       ; R6 := "left"
173 [-]: CALL      R4 3 1       ; R4(R5,R6)
174 [-]: SELF      R4 R3 K66    ; R5 := R3; R4 := R3[0x46610c50]
175 [-]: GETTABLE  R6 R0 K48    ; R6 := R0["mEnabled"]
176 [-]: CALL      R4 3 1       ; R4(R5,R6)
177 [-]: SELF      R4 R3 K67    ; R5 := R3; R4 := R3[0x71e9ac81]
178 [-]: CALL      R4 2 1       ; R4(R5)
179 [-]: GETTABLE  R4 R0 K68    ; R4 := R0["mFocused"]
180 [-]: TEST      R4 1         ; if R4 then PC := 187
181 [-]: JMP       187          ; PC := 187
182 [-]: GETUPVAL  R4 U4        ; R4 := U4
183 [-]: GETTABLE  R4 R4 K69    ; R4 := R4[0xd838387b]
184 [-]: MOVE      R5 R0        ; R5 := R0
185 [-]: CALL      R4 2 1       ; R4(R5)
186 [-]: JMP       191          ; PC := 191
187 [-]: GETUPVAL  R4 U4        ; R4 := U4
188 [-]: GETTABLE  R4 R4 K70    ; R4 := R4[0xaf2cb9be]
189 [-]: MOVE      R5 R0        ; R5 := R0
190 [-]: CALL      R4 2 1       ; R4(R5)
191 [-]: RETURN    R0 1         ; return 


; Function #12.7.1:
;
; Name:            
; Defined at line: 384
; #Upvalues:       1
; #Parameters:     2
; Is_vararg:       0
; Max Stack Size:  5

  1 [-]: TEST      R1 0         ; if not R1 then PC := 8
  2 [-]: JMP       8            ; PC := 8
  3 [-]: GETUPVAL  R2 U0        ; R2 := U0
  4 [-]: SELF      R2 R2 K0     ; R3 := R2; R2 := R2[0xdf42446e]
  5 [-]: GETTABLE  R4 R0 K1     ; R4 := R0["mId"]
  6 [-]: CALL      R2 3 1       ; R2(R3,R4)
  7 [-]: JMP       12           ; PC := 12
  8 [-]: GETUPVAL  R2 U0        ; R2 := U0
  9 [-]: SELF      R2 R2 K2     ; R3 := R2; R2 := R2[0xbce5a201]
 10 [-]: GETTABLE  R4 R0 K1     ; R4 := R0["mId"]
 11 [-]: CALL      R2 3 1       ; R2(R3,R4)
 12 [-]: SELF      R2 R0 K3     ; R3 := R0; R2 := R0[0x297b0e2a]
 13 [-]: MOVE      R4 R1        ; R4 := R1
 14 [-]: CALL      R2 3 1       ; R2(R3,R4)
 15 [-]: RETURN    R0 1         ; return 


; Function #12.7.2:
;
; Name:            
; Defined at line: 394
; #Upvalues:       1
; #Parameters:     2
; Is_vararg:       0
; Max Stack Size:  5

  1 [-]: TEST      R1 0         ; if not R1 then PC := 7
  2 [-]: JMP       7            ; PC := 7
  3 [-]: GETUPVAL  R2 U0        ; R2 := U0
  4 [-]: SELF      R2 R2 K0     ; R3 := R2; R2 := R2[0x070daa5a]
  5 [-]: GETTABLE  R4 R0 K1     ; R4 := R0["mId"]
  6 [-]: CALL      R2 3 1       ; R2(R3,R4)
  7 [-]: SELF      R2 R0 K2     ; R3 := R0; R2 := R0[0x1a420534]
  8 [-]: MOVE      R4 R1        ; R4 := R1
  9 [-]: CALL      R2 3 1       ; R2(R3,R4)
 10 [-]: RETURN    R0 1         ; return 


; Function #12.7.3:
;
; Name:            
; Defined at line: 402
; #Upvalues:       2
; #Parameters:     1
; Is_vararg:       0
; Max Stack Size:  7

  1 [-]: GETUPVAL  R1 U0        ; R1 := U0
  2 [-]: SELF      R1 R1 K0     ; R2 := R1; R1 := R1[0x9703e512]
  3 [-]: CALL      R1 2 1       ; R1(R2)
  4 [-]: GETGLOBAL R1 K1        ; R1 := 0xae91e43b
  5 [-]: SELF      R1 R1 K2     ; R2 := R1; R1 := R1[0xf64b7262]
  6 [-]: GETUPVAL  R3 U1        ; R3 := U1
  7 [-]: LOADK     R4 K3        ; R4 := "RightText"
  8 [-]: LOADK     R5 1         ; R5 := 1.000000
  9 [-]: GETTABLE  R6 R0 K4     ; R6 := R0["mLabelY"]
 10 [-]: CALL      R1 6 1       ; R1(R2,R3,R4,R5,R6)
 11 [-]: RETURN    R0 1         ; return 


; Function #12.8:
;
; Name:            
; Defined at line: 457
; #Upvalues:       0
; #Parameters:     2
; Is_vararg:       0
; Max Stack Size:  11

  1 [-]: SELF      R2 R0 K0     ; R3 := R0; R2 := R0[0x975364e9]
  2 [-]: LOADK     R4 K1        ; R4 := "ToggleFocusedElement("
  3 [-]: GETGLOBAL R5 K2        ; R5 := 0x64fb1586
  4 [-]: MOVE      R6 R1        ; R6 := R1
  5 [-]: CALL      R5 2 2       ; R5 := R5(R6)
  6 [-]: LOADK     R6 K3        ; R6 := ")"
  7 [-]: CONCAT    R4 R4 R6     ; R4 := R4 .. R5 .. R6
  8 [-]: CALL      R2 3 1       ; R2(R3,R4)
  9 [-]: LOADK     R2 0         ; R2 := 0.000000
 10 [-]: GETGLOBAL R3 K4        ; R3 := 0x7b998233
 11 [-]: SELF      R4 R0 K5     ; R5 := R0; R4 := R0[0x9cb26453]
 12 [-]: CALL      R4 2 0       ; R4,... := R4(R5)
 13 [-]: CALL      R3 0 2       ; R3 := R3(R4,...)
 14 [-]: TEST      R3 1         ; if R3 then PC := 19
 15 [-]: JMP       19           ; PC := 19
 16 [-]: SELF      R3 R0 K5     ; R4 := R0; R3 := R0[0x9cb26453]
 17 [-]: CALL      R3 2 2       ; R3 := R3(R4)
 18 [-]: SUB       R2 R3 R1     ; R2 := R3 - R1
 19 [-]: GETGLOBAL R3 K4        ; R3 := 0x7b998233
 20 [-]: GETTABLE  R4 R0 K6     ; R4 := R0["mCurrentElementIndex"]
 21 [-]: CALL      R3 2 2       ; R3 := R3(R4)
 22 [-]: TEST      R3 1         ; if R3 then PC := 25
 23 [-]: JMP       25           ; PC := 25
 24 [-]: GETTABLE  R2 R0 K6     ; R2 := R0["mCurrentElementIndex"]
 25 [-]: LOADNIL   R3 R3        ; R3 := nil
 26 [-]: SELF      R4 R0 K7     ; R5 := R0; R4 := R0[0x5fbddc1a]
 27 [-]: CALL      R4 2 2       ; R4 := R4(R5)
 28 [-]: LOADK     R5 0         ; R5 := 0.000000
 29 [-]: EQ        1 R3 K8      ; if R3 == nil then PC := 39
 30 [-]: JMP       39           ; PC := 39
 31 [-]: GETGLOBAL R6 K9        ; R6 := 0x34291f5c
 32 [-]: GETTABLE  R6 R6 K10    ; R6 := R6[0x1467d5f4]
 33 [-]: CALL      R6 1 2       ; R6 := R6()
 34 [-]: TEST      R6 1         ; if R6 then PC := 66
 35 [-]: JMP       66           ; PC := 66
 36 [-]: GETTABLE  R6 R3 K11    ; R6 := R3["mEnabled"]
 37 [-]: TEST      R6 1         ; if R6 then PC := 66
 38 [-]: JMP       66           ; PC := 66
 39 [-]: LE        0 R4 R5      ; if R4 > R5 then PC := 42
 40 [-]: JMP       42           ; PC := 42
 41 [-]: JMP       66           ; PC := 66
 42 [-]: GETTABLE  R6 R0 K12    ; R6 := R0["mWrapAroundNavigation"]
 43 [-]: TEST      R6 0         ; if not R6 then PC := 54
 44 [-]: JMP       54           ; PC := 54
 45 [-]: GETTABLE  R6 R0 K13    ; R6 := R0["UTIL"]
 46 [-]: GETTABLE  R6 R6 K14    ; R6 := R6[0x38a41ce7]
 47 [-]: MOVE      R7 R2        ; R7 := R2
 48 [-]: MOVE      R8 R1        ; R8 := R1
 49 [-]: LOADK     R9 1         ; R9 := 1.000000
 50 [-]: MOVE      R10 R4       ; R10 := R4
 51 [-]: CALL      R6 5 2       ; R6 := R6(R7,R8,R9,R10)
 52 [-]: MOVE      R2 R6        ; R2 := R6
 53 [-]: JMP       60           ; PC := 60
 54 [-]: GETGLOBAL R6 K15       ; R6 := 0x42dcc9f5
 55 [-]: ADD       R7 R2 R1     ; R7 := R2 + R1
 56 [-]: LOADK     R8 1         ; R8 := 1.000000
 57 [-]: MOVE      R9 R4        ; R9 := R4
 58 [-]: CALL      R6 4 2       ; R6 := R6(R7,R8,R9)
 59 [-]: MOVE      R2 R6        ; R2 := R6
 60 [-]: SELF      R6 R0 K16    ; R7 := R0; R6 := R0[0x5465f8f3]
 61 [-]: MOVE      R8 R2        ; R8 := R2
 62 [-]: CALL      R6 3 2       ; R6 := R6(R7,R8)
 63 [-]: MOVE      R3 R6        ; R3 := R6
 64 [-]: ADD       R5 R5 K17    ; R5 := R5 + 1.000000
 65 [-]: JMP       29           ; PC := 29
 66 [-]: GETTABLE  R6 R0 K18    ; R6 := R0["mScrollBar"]
 67 [-]: EQ        1 R6 K8      ; if R6 == nil then PC := 104
 68 [-]: JMP       104          ; PC := 104
 69 [-]: GETTABLE  R6 R0 K19    ; R6 := R0["DOWN"]
 70 [-]: EQ        0 R1 R6      ; if R1 ~= R6 then PC := 89
 71 [-]: JMP       89           ; PC := 89
 72 [-]: SELF      R6 R0 K5     ; R7 := R0; R6 := R0[0x9cb26453]
 73 [-]: CALL      R6 2 2       ; R6 := R6(R7)
 74 [-]: SELF      R7 R0 K20    ; R8 := R0; R7 := R0[0xc419c8f6]
 75 [-]: CALL      R7 2 2       ; R7 := R7(R8)
 76 [-]: ADD       R6 R6 R7     ; R6 := R6 + R7
 77 [-]: SUB       R6 R6 K17    ; R6 := R6 - 1.000000
 78 [-]: EQ        0 R2 R6      ; if R2 ~= R6 then PC := 89
 79 [-]: JMP       89           ; PC := 89
 80 [-]: GETTABLE  R6 R0 K18    ; R6 := R0["mScrollBar"]
 81 [-]: SELF      R6 R6 K21    ; R7 := R6; R6 := R6[0x70fc2d50]
 82 [-]: CALL      R6 2 2       ; R6 := R6(R7)
 83 [-]: LT        0 R6 K17     ; if R6 >= 1.000000 then PC := 89
 84 [-]: JMP       89           ; PC := 89
 85 [-]: GETTABLE  R6 R0 K18    ; R6 := R0["mScrollBar"]
 86 [-]: SELF      R6 R6 K22    ; R7 := R6; R6 := R6[0x55c38f8b]
 87 [-]: CALL      R6 2 1       ; R6(R7)
 88 [-]: JMP       104          ; PC := 104
 89 [-]: GETTABLE  R6 R0 K23    ; R6 := R0["UP"]
 90 [-]: EQ        0 R1 R6      ; if R1 ~= R6 then PC := 104
 91 [-]: JMP       104          ; PC := 104
 92 [-]: SELF      R6 R0 K5     ; R7 := R0; R6 := R0[0x9cb26453]
 93 [-]: CALL      R6 2 2       ; R6 := R6(R7)
 94 [-]: EQ        0 R2 R6      ; if R2 ~= R6 then PC := 104
 95 [-]: JMP       104          ; PC := 104
 96 [-]: GETTABLE  R6 R0 K18    ; R6 := R0["mScrollBar"]
 97 [-]: SELF      R6 R6 K21    ; R7 := R6; R6 := R6[0x70fc2d50]
 98 [-]: CALL      R6 2 2       ; R6 := R6(R7)
 99 [-]: LT        0 K24 R6     ; if 0.000000 >= R6 then PC := 104
100 [-]: JMP       104          ; PC := 104
101 [-]: GETTABLE  R6 R0 K18    ; R6 := R0["mScrollBar"]
102 [-]: SELF      R6 R6 K25    ; R7 := R6; R6 := R6[0xd996dd2a]
103 [-]: CALL      R6 2 1       ; R6(R7)
104 [-]: SELF      R6 R0 K26    ; R7 := R0; R6 := R0[0x1e63ac7a]
105 [-]: MOVE      R8 R2        ; R8 := R2
106 [-]: CALL      R6 3 1       ; R6(R7,R8)
107 [-]: RETURN    R0 1         ; return 


; Function #13:
;
; Name:            
; Defined at line: 498
; #Upvalues:       7
; #Parameters:     2
; Is_vararg:       0
; Max Stack Size:  9

  1 [-]: GETUPVAL  R2 U0        ; R2 := U0
  2 [-]: EQ        1 R2 R0      ; if R2 == R0 then PC := 101
  3 [-]: JMP       101          ; PC := 101
  4 [-]: SETUPVAL  R0 U0        ; U82 := R0
  5 [-]: SETUPVAL  R0 U1        ; U82 := R1
  6 [-]: GETUPVAL  R2 U2        ; R2 := U2
  7 [-]: GETUPVAL  R3 U1        ; R3 := U1
  8 [-]: GETUPVAL  R4 U3        ; R4 := U3
  9 [-]: SUB       R3 R3 R4     ; R3 := R3 - R4
 10 [-]: SETTABLE  R2 K0 R3     ; R2["mButtonWidth"] := R3
 11 [-]: GETUPVAL  R2 U2        ; R2 := U2
 12 [-]: SELF      R2 R2 K1     ; R3 := R2; R2 := R2[0x71e9ac81]
 13 [-]: LOADNIL   R4 R4        ; R4 := nil
 14 [-]: LOADBOOL  R5 1 0       ; R5 := true
 15 [-]: MOVE      R6 R1        ; R6 := R1
 16 [-]: CALL      R2 5 1       ; R2(R3,R4,R5,R6)
 17 [-]: GETUPVAL  R2 U1        ; R2 := U1
 18 [-]: GETUPVAL  R3 U2        ; R3 := U2
 19 [-]: GETTABLE  R3 R3 K2     ; R3 := R3["mScrollBar"]
 20 [-]: GETTABLE  R3 R3 K3     ; R3 := R3["mEnabled"]
 21 [-]: TEST      R3 0         ; if not R3 then PC := 25
 22 [-]: JMP       25           ; PC := 25
 23 [-]: GETUPVAL  R3 U4        ; R3 := U4
 24 [-]: ADD       R2 R2 R3     ; R2 := R2 + R3
 25 [-]: GETUPVAL  R3 U5        ; R3 := U5
 26 [-]: GETTABLE  R3 R3 K4     ; R3 := R3[0x00fa676f]
 27 [-]: GETGLOBAL R4 K5        ; R4 := 0xae91e43b
 28 [-]: LOADK     R5 K6        ; R5 := "Container.Underline"
 29 [-]: SUB       R6 R2 K7     ; R6 := R2 - 20.000000
 30 [-]: CALL      R3 4 1       ; R3(R4,R5,R6)
 31 [-]: GETGLOBAL R3 K5        ; R3 := 0xae91e43b
 32 [-]: SELF      R3 R3 K8     ; R4 := R3; R3 := R3[0x67bc869f]
 33 [-]: LOADK     R5 K6        ; R5 := "Container.Underline"
 34 [-]: LOADK     R6 0         ; R6 := 0.000000
 35 [-]: UNM       R7 R2        ; R7 := ^ R2
 36 [-]: DIV       R7 R7 K9     ; R7 := R7 / 2.000000
 37 [-]: ADD       R7 R7 K10    ; R7 := R7 + 10.000000
 38 [-]: CALL      R3 5 1       ; R3(R4,R5,R6,R7)
 39 [-]: GETGLOBAL R3 K5        ; R3 := 0xae91e43b
 40 [-]: SELF      R3 R3 K8     ; R4 := R3; R3 := R3[0x67bc869f]
 41 [-]: LOADK     R5 K11       ; R5 := "Container.BgFill"
 42 [-]: LOADK     R6 12        ; R6 := 12.000000
 43 [-]: MOVE      R7 R2        ; R7 := R2
 44 [-]: CALL      R3 5 1       ; R3(R4,R5,R6,R7)
 45 [-]: GETGLOBAL R3 K5        ; R3 := 0xae91e43b
 46 [-]: SELF      R3 R3 K8     ; R4 := R3; R3 := R3[0x67bc869f]
 47 [-]: LOADK     R5 K12       ; R5 := "Container.Blurer"
 48 [-]: LOADK     R6 12        ; R6 := 12.000000
 49 [-]: MOVE      R7 R2        ; R7 := R2
 50 [-]: CALL      R3 5 1       ; R3(R4,R5,R6,R7)
 51 [-]: GETGLOBAL R3 K5        ; R3 := 0xae91e43b
 52 [-]: SELF      R3 R3 K8     ; R4 := R3; R3 := R3[0x67bc869f]
 53 [-]: LOADK     R5 K13       ; R5 := "Container.ButtonContainer"
 54 [-]: LOADK     R6 0         ; R6 := 0.000000
 55 [-]: UNM       R7 R2        ; R7 := ^ R2
 56 [-]: DIV       R7 R7 K9     ; R7 := R7 / 2.000000
 57 [-]: GETUPVAL  R8 U3        ; R8 := U3
 58 [-]: DIV       R8 R8 K9     ; R8 := R8 / 2.000000
 59 [-]: ADD       R7 R7 R8     ; R7 := R7 + R8
 60 [-]: CALL      R3 5 1       ; R3(R4,R5,R6,R7)
 61 [-]: GETGLOBAL R3 K5        ; R3 := 0xae91e43b
 62 [-]: SELF      R3 R3 K8     ; R4 := R3; R3 := R3[0x67bc869f]
 63 [-]: LOADK     R5 K14       ; R5 := "Container.ScrollBar"
 64 [-]: LOADK     R6 0         ; R6 := 0.000000
 65 [-]: DIV       R7 R2 K9     ; R7 := R2 / 2.000000
 66 [-]: GETUPVAL  R8 U4        ; R8 := U4
 67 [-]: DIV       R8 R8 K9     ; R8 := R8 / 2.000000
 68 [-]: ADD       R8 K15 R8    ; R8 := 6.000000 + R8
 69 [-]: SUB       R7 R7 R8     ; R7 := R7 - R8
 70 [-]: CALL      R3 5 1       ; R3(R4,R5,R6,R7)
 71 [-]: GETGLOBAL R3 K5        ; R3 := 0xae91e43b
 72 [-]: SELF      R3 R3 K8     ; R4 := R3; R3 := R3[0x67bc869f]
 73 [-]: LOADK     R5 K16       ; R5 := "Container.Title"
 74 [-]: LOADK     R6 0         ; R6 := 0.000000
 75 [-]: UNM       R7 R2        ; R7 := ^ R2
 76 [-]: DIV       R7 R7 K9     ; R7 := R7 / 2.000000
 77 [-]: ADD       R7 R7 K7     ; R7 := R7 + 20.000000
 78 [-]: CALL      R3 5 1       ; R3(R4,R5,R6,R7)
 79 [-]: GETGLOBAL R3 K17       ; R3 := 0x7b998233
 80 [-]: GETUPVAL  R4 U6        ; R4 := U6
 81 [-]: CALL      R3 2 2       ; R3 := R3(R4)
 82 [-]: TEST      R3 1         ; if R3 then PC := 101
 83 [-]: JMP       101          ; PC := 101
 84 [-]: GETUPVAL  R3 U6        ; R3 := U6
 85 [-]: SETTABLE  R3 K18 R2    ; R3["mMinSize"] := R2
 86 [-]: GETUPVAL  R3 U6        ; R3 := U6
 87 [-]: SETTABLE  R3 K19 R2    ; R3["mMaxSize"] := R2
 88 [-]: GETUPVAL  R3 U6        ; R3 := U6
 89 [-]: UNM       R4 R2        ; R4 := ^ R2
 90 [-]: DIV       R4 R4 K9     ; R4 := R4 / 2.000000
 91 [-]: SETTABLE  R3 K20 R4    ; R3["mX"] := R4
 92 [-]: GETUPVAL  R3 U6        ; R3 := U6
 93 [-]: SELF      R3 R3 K1     ; R4 := R3; R3 := R3[0x71e9ac81]
 94 [-]: CALL      R3 2 1       ; R3(R4)
 95 [-]: GETGLOBAL R3 K5        ; R3 := 0xae91e43b
 96 [-]: SELF      R3 R3 K21    ; R4 := R3; R3 := R3[0xaade900e]
 97 [-]: LOADK     R5 K22       ; R5 := "Container.SearchBox"
 98 [-]: LOADK     R6 11        ; R6 := 11.000000
 99 [-]: LOADBOOL  R7 1 0       ; R7 := true
100 [-]: CALL      R3 5 1       ; R3(R4,R5,R6,R7)
101 [-]: RETURN    R0 1         ; return 


; Function #14:
;
; Name:            
; Defined at line: 526
; #Upvalues:       3
; #Parameters:     0
; Is_vararg:       0
; Max Stack Size:  3

  1 [-]: GETUPVAL  R0 U0        ; R0 := U0
  2 [-]: TEST      R0 0         ; if not R0 then PC := 9
  3 [-]: JMP       9            ; PC := 9
  4 [-]: GETGLOBAL R0 K0        ; R0 := 0x7b998233
  5 [-]: GETGLOBAL R1 K1        ; R1 := 0xae91e43b
  6 [-]: CALL      R0 2 2       ; R0 := R0(R1)
  7 [-]: TEST      R0 0         ; if not R0 then PC := 10
  8 [-]: JMP       10           ; PC := 10
  9 [-]: RETURN    R0 1         ; return 
 10 [-]: GETGLOBAL R0 K1        ; R0 := 0xae91e43b
 11 [-]: SELF      R0 R0 K2     ; R1 := R0; R0 := R0[0x8a8c8d5a]
 12 [-]: GETGLOBAL R2 K3        ; R2 := 0xb693b6c1
 13 [-]: CALL      R2 1 0       ; R2,... := R2()
 14 [-]: CALL      R0 0 1       ; R0(R1,...)
 15 [-]: GETGLOBAL R0 K0        ; R0 := 0x7b998233
 16 [-]: GETUPVAL  R1 U1        ; R1 := U1
 17 [-]: CALL      R0 2 2       ; R0 := R0(R1)
 18 [-]: TEST      R0 1         ; if R0 then PC := 25
 19 [-]: JMP       25           ; PC := 25
 20 [-]: GETUPVAL  R0 U1        ; R0 := U1
 21 [-]: SELF      R0 R0 K4     ; R1 := R0; R0 := R0[0xfaa69527]
 22 [-]: GETGLOBAL R2 K3        ; R2 := 0xb693b6c1
 23 [-]: CALL      R2 1 0       ; R2,... := R2()
 24 [-]: CALL      R0 0 1       ; R0(R1,...)
 25 [-]: GETGLOBAL R0 K0        ; R0 := 0x7b998233
 26 [-]: GETUPVAL  R1 U2        ; R1 := U2
 27 [-]: CALL      R0 2 2       ; R0 := R0(R1)
 28 [-]: TEST      R0 1         ; if R0 then PC := 42
 29 [-]: JMP       42           ; PC := 42
 30 [-]: GETGLOBAL R0 K0        ; R0 := 0x7b998233
 31 [-]: GETUPVAL  R1 U2        ; R1 := U2
 32 [-]: GETTABLE  R1 R1 K5     ; R1 := R1["mScrollBar"]
 33 [-]: CALL      R0 2 2       ; R0 := R0(R1)
 34 [-]: TEST      R0 1         ; if R0 then PC := 42
 35 [-]: JMP       42           ; PC := 42
 36 [-]: GETUPVAL  R0 U2        ; R0 := U2
 37 [-]: GETTABLE  R0 R0 K5     ; R0 := R0["mScrollBar"]
 38 [-]: SELF      R0 R0 K4     ; R1 := R0; R0 := R0[0xfaa69527]
 39 [-]: GETGLOBAL R2 K3        ; R2 := 0xb693b6c1
 40 [-]: CALL      R2 1 0       ; R2,... := R2()
 41 [-]: CALL      R0 0 1       ; R0(R1,...)
 42 [-]: RETURN    R0 1         ; return 


; Function #15:
;
; Name:            
; Defined at line: 542
; #Upvalues:       5
; #Parameters:     1
; Is_vararg:       0
; Max Stack Size:  11

  1 [-]: GETUPVAL  R1 U0        ; R1 := U0
  2 [-]: EQ        0 R1 K0      ; if R1 ~= nil then PC := 60
  3 [-]: JMP       60           ; PC := 60
  4 [-]: GETUPVAL  R1 U1        ; R1 := U1
  5 [-]: ADD       R1 R1 K1     ; R1 := R1 + 1.000000
  6 [-]: SETUPVAL  R1 U1        ; U82 := R1
  7 [-]: GETUPVAL  R1 U1        ; R1 := U1
  8 [-]: LT        0 R1 K2      ; if R1 >= 10.000000 then PC := 16
  9 [-]: JMP       16           ; PC := 16
 10 [-]: GETUPVAL  R1 U2        ; R1 := U2
 11 [-]: SELF      R1 R1 K3     ; R2 := R1; R1 := R1[0xbd2e96ea]
 12 [-]: LOADK     R3 K4        ; R3 := 0.100000
 13 [-]: MOVE      R4 R0        ; R4 := R0
 14 [-]: CALL      R1 4 1       ; R1(R2,R3,R4)
 15 [-]: JMP       58           ; PC := 58
 16 [-]: LOADBOOL  R1 0 0       ; R1 := false
 17 [-]: TEST      R1 0         ; if not R1 then PC := 56
 18 [-]: JMP       56           ; PC := 56
 19 [-]: NEWTABLE  R1 0 0       ; R1 := {}
 20 [-]: LOADK     R2 1         ; R2 := 1.000000
 21 [-]: LOADK     R3 30        ; R3 := 30.000000
 22 [-]: LOADK     R4 1         ; R4 := 1.000000
 23 [-]: FORPREP   R2 40        ; R2 -= R4; PC := 40
 24 [-]: GETGLOBAL R6 K5        ; R6 := 0x33bdd652
 25 [-]: GETTABLE  R6 R6 K6     ; R6 := R6[0x23d5322f]
 26 [-]: MOVE      R7 R1        ; R7 := R1
 27 [-]: NEWTABLE  R8 0 5       ; R8 := {}
 28 [-]: LOADK     R9 K8        ; R9 := "Test"
 29 [-]: MOVE      R10 R5       ; R10 := R5
 30 [-]: CONCAT    R9 R9 R10    ; R9 := R9 .. R10
 31 [-]: SETTABLE  R8 K7 R9     ; R8["Label"] := R9
 32 [-]: MOVE      R9 R5        ; R9 := R5
 33 [-]: LOADK     R10 K8       ; R10 := "Test"
 34 [-]: CONCAT    R9 R9 R10    ; R9 := R9 .. R10
 35 [-]: SETTABLE  R8 K9 R9     ; R8["mName"] := R9
 36 [-]: SETTABLE  R8 K10 K11   ; R8["Action"] := "AIM_WEAPON"
 37 [-]: SETTABLE  R8 K12 K13   ; R8["ExcludePowers"] := true
 38 [-]: SETTABLE  R8 K14 K13   ; R8["AllowMelee2"] := true
 39 [-]: CALL      R6 3 1       ; R6(R7,R8)
 40 [-]: FORLOOP   R2 24        ; R2 += R4; if R2 <= R3 then begin PC := 24; R5 := R2 end
 41 [-]: GETTABLE  R6 R1 K1     ; R6 := R1[1.000000]
 42 [-]: GETUPVAL  R7 U3        ; R7 := U3
 43 [-]: GETTABLE  R7 R7 K16    ; R7 := R7["TITLE"]
 44 [-]: SETTABLE  R6 K15 R7    ; R6["Type"] := R7
 45 [-]: LOADK     R6 K17       ; R6 := "TestGetElementsFunction"
 46 [-]: SETUPVAL  R6 U0        ; U82 := R0
 47 [-]: GETGLOBAL R6 K18       ; R6 := _T
 48 [-]: GETUPVAL  R7 U0        ; R7 := U0
 49 [-]: CLOSURE   R8 0         ; R8 := closure(Function #15.1)
 50 [-]: MOVE      R0 R1        ; R0 := R1
 51 [-]: SETTABLE  R6 R7 R8     ; R6[R7] := R8
 52 [-]: LOADBOOL  R6 1 0       ; R6 := true
 53 [-]: RETURN    R6 2         ; return R6
 54 [-]: CLOSE     R1           ; SAVE R1,...
 55 [-]: JMP       58           ; PC := 58
 56 [-]: GETUPVAL  R1 U4        ; R1 := U4
 57 [-]: CALL      R1 1 1       ; R1()
 58 [-]: LOADBOOL  R1 0 0       ; R1 := false
 59 [-]: RETURN    R1 2         ; return R1
 60 [-]: LOADBOOL  R1 1 0       ; R1 := true
 61 [-]: RETURN    R1 2         ; return R1
 62 [-]: RETURN    R0 1         ; return 


; Function #15.1:
;
; Name:            
; Defined at line: 554
; #Upvalues:       1
; #Parameters:     0
; Is_vararg:       0
; Max Stack Size:  2

  1 [-]: GETUPVAL  R0 U0        ; R0 := U0
  2 [-]: RETURN    R0 2         ; return R0
  3 [-]: RETURN    R0 1         ; return 


; Function #16:
;
; Name:            
; Defined at line: 566
; #Upvalues:       4
; #Parameters:     0
; Is_vararg:       0
; Max Stack Size:  16

  1 [-]: GETUPVAL  R0 U0        ; R0 := U0
  2 [-]: GETUPVAL  R1 U1        ; R1 := U1
  3 [-]: CALL      R0 2 2       ; R0 := R0(R1)
  4 [-]: TEST      R0 1         ; if R0 then PC := 7
  5 [-]: JMP       7            ; PC := 7
  6 [-]: RETURN    R0 1         ; return 
  7 [-]: GETGLOBAL R0 K0        ; R0 := 0x7b998233
  8 [-]: GETGLOBAL R1 K1        ; R1 := _T
  9 [-]: GETUPVAL  R2 U2        ; R2 := U2
 10 [-]: GETTABLE  R1 R1 R2     ; R1 := R1[R2]
 11 [-]: CALL      R0 2 2       ; R0 := R0(R1)
 12 [-]: TEST      R0 1         ; if R0 then PC := 63
 13 [-]: JMP       63           ; PC := 63
 14 [-]: GETGLOBAL R0 K1        ; R0 := _T
 15 [-]: GETUPVAL  R1 U2        ; R1 := U2
 16 [-]: GETTABLE  R0 R0 R1     ; R0 := R0[R1]
 17 [-]: CALL      R0 1 2       ; R0 := R0()
 18 [-]: GETGLOBAL R1 K0        ; R1 := 0x7b998233
 19 [-]: GETUPVAL  R2 U3        ; R2 := U3
 20 [-]: CALL      R1 2 2       ; R1 := R1(R2)
 21 [-]: TEST      R1 1         ; if R1 then PC := 63
 22 [-]: JMP       63           ; PC := 63
 23 [-]: LOADK     R1 1         ; R1 := 1.000000
 24 [-]: LEN       R2 R0        ; R2 := # R0
 25 [-]: LOADK     R3 1         ; R3 := 1.000000
 26 [-]: FORPREP   R1 56        ; R1 -= R3; PC := 56
 27 [-]: GETUPVAL  R5 U3        ; R5 := U3
 28 [-]: SELF      R5 R5 K2     ; R6 := R5; R5 := R5[0xca30dfb6]
 29 [-]: MOVE      R7 R4        ; R7 := R4
 30 [-]: CALL      R5 3 2       ; R5 := R5(R6,R7)
 31 [-]: TEST      R5 0         ; if not R5 then PC := 41
 32 [-]: JMP       41           ; PC := 41
 33 [-]: GETGLOBAL R6 K3        ; R6 := 0xcfc01047
 34 [-]: GETTABLE  R7 R0 R4     ; R7 := R0[R4]
 35 [-]: CALL      R6 2 4       ; R6,R7,R8 := R6(R7)
 36 [-]: JMP       38           ; PC := 38
 37 [-]: SETTABLE  R5 R9 R10    ; R5[R9] := R10
 38 [-]: TFORLOOP  R6 2         ; R9,R10 :=  R6(R7,R8); if R9 ~= nil then begin PC = 37; R8 := R9 end
 39 [-]: JMP       37           ; PC := 37
 40 [-]: JMP       56           ; PC := 56
 41 [-]: GETTABLE  R11 R0 R4    ; R11 := R0[R4]
 42 [-]: GETGLOBAL R12 K5       ; R12 := 0x7f5022cf
 43 [-]: GETTABLE  R12 R12 K6   ; R12 := R12[0x3f3e4d12]
 44 [-]: GETGLOBAL R13 K7       ; R13 := 0x603636ad
 45 [-]: GETTABLE  R14 R0 R4    ; R14 := R0[R4]
 46 [-]: GETTABLE  R14 R14 K8   ; R14 := R14["mName"]
 47 [-]: NEWTABLE  R15 0 0      ; R15 := {}
 48 [-]: CALL      R13 3 0      ; R13,... := R13(R14,R15)
 49 [-]: CALL      R12 0 2      ; R12 := R12(R13,...)
 50 [-]: SETTABLE  R11 K4 R12   ; R11["mSearchTerm"] := R12
 51 [-]: GETUPVAL  R11 U3       ; R11 := U3
 52 [-]: SELF      R11 R11 K9   ; R12 := R11; R11 := R11[0xbad4316f]
 53 [-]: GETTABLE  R13 R0 R4    ; R13 := R0[R4]
 54 [-]: LOADBOOL  R14 1 0      ; R14 := true
 55 [-]: CALL      R11 4 1      ; R11(R12,R13,R14)
 56 [-]: FORLOOP   R1 27        ; R1 += R3; if R1 <= R2 then begin PC := 27; R4 := R1 end
 57 [-]: GETUPVAL  R11 U3       ; R11 := U3
 58 [-]: SELF      R11 R11 K10  ; R12 := R11; R11 := R11[0x71e9ac81]
 59 [-]: LOADNIL   R13 R13      ; R13 := nil
 60 [-]: LOADBOOL  R14 1 0      ; R14 := true
 61 [-]: LOADBOOL  R15 1 0      ; R15 := true
 62 [-]: CALL      R11 5 1      ; R11(R12,R13,R14,R15)
 63 [-]: RETURN    R0 1         ; return 


; Function #17:
;
; Name:            
; Defined at line: 594
; #Upvalues:       1
; #Parameters:     0
; Is_vararg:       0
; Max Stack Size:  2

  1 [-]: GETUPVAL  R0 U0        ; R0 := U0
  2 [-]: CALL      R0 1 1       ; R0()
  3 [-]: RETURN    R0 1         ; return 


; Function #18:
;
; Name:            
; Defined at line: 598
; #Upvalues:       3
; #Parameters:     1
; Is_vararg:       0
; Max Stack Size:  16

  1 [-]: GETGLOBAL R1 K0        ; R1 := 0x7b998233
  2 [-]: GETUPVAL  R2 U0        ; R2 := U0
  3 [-]: CALL      R1 2 2       ; R1 := R1(R2)
  4 [-]: TEST      R1 1         ; if R1 then PC := 16
  5 [-]: JMP       16           ; PC := 16
  6 [-]: GETGLOBAL R1 K0        ; R1 := 0x7b998233
  7 [-]: GETUPVAL  R2 U1        ; R2 := U1
  8 [-]: CALL      R1 2 2       ; R1 := R1(R2)
  9 [-]: TEST      R1 1         ; if R1 then PC := 16
 10 [-]: JMP       16           ; PC := 16
 11 [-]: GETUPVAL  R1 U1        ; R1 := U1
 12 [-]: GETTABLE  R1 R1 K1     ; R1 := R1["mUnfilteredElements"]
 13 [-]: LEN       R1 R1        ; R1 := # R1
 14 [-]: EQ        0 R1 K2      ; if R1 ~= 0.000000 then PC := 17
 15 [-]: JMP       17           ; PC := 17
 16 [-]: RETURN    R0 1         ; return 
 17 [-]: GETUPVAL  R1 U0        ; R1 := U0
 18 [-]: GETTABLE  R1 R1 K3     ; R1 := R1["mLabel"]
 19 [-]: GETGLOBAL R2 K4        ; R2 := 0x7f5022cf
 20 [-]: GETTABLE  R2 R2 K5     ; R2 := R2[0x3f3e4d12]
 21 [-]: MOVE      R3 R1        ; R3 := R1
 22 [-]: CALL      R2 2 2       ; R2 := R2(R3)
 23 [-]: SELF      R2 R2 K6     ; R3 := R2; R2 := R2[0x66edf04f]
 24 [-]: LOADK     R4 K7        ; R4 := "[%(%)%.%%%+%-%*%?%[%]%^%$]"
 25 [-]: LOADK     R5 K8        ; R5 := "%%%0"
 26 [-]: CALL      R2 4 2       ; R2 := R2(R3,R4,R5)
 27 [-]: SELF      R3 R0 K9     ; R4 := R0; R3 := R0[0xa5c556b9]
 28 [-]: MOVE      R5 R2        ; R5 := R2
 29 [-]: CALL      R3 3 2       ; R3 := R3(R4,R5)
 30 [-]: TEST      R3 0         ; if not R3 then PC := 36
 31 [-]: JMP       36           ; PC := 36
 32 [-]: EQ        0 R0 K10     ; if R0 ~= "" then PC := 35
 33 [-]: JMP       35           ; PC := 35
 34 [-]: LOADBOOL  R3 0 1       ; R3 := false; PC := 35
 35 [-]: LOADBOOL  R3 1 0       ; R3 := true
 36 [-]: TEST      R3 0         ; if not R3 then PC := 63
 37 [-]: JMP       63           ; PC := 63
 38 [-]: LOADK     R4 1         ; R4 := 1.000000
 39 [-]: GETUPVAL  R5 U1        ; R5 := U1
 40 [-]: GETTABLE  R5 R5 K11    ; R5 := R5["mElements"]
 41 [-]: LEN       R5 R5        ; R5 := # R5
 42 [-]: LE        0 R4 R5      ; if R4 > R5 then PC := 95
 43 [-]: JMP       95           ; PC := 95
 44 [-]: GETUPVAL  R5 U1        ; R5 := U1
 45 [-]: GETTABLE  R5 R5 K11    ; R5 := R5["mElements"]
 46 [-]: GETTABLE  R5 R5 R4     ; R5 := R5[R4]
 47 [-]: GETTABLE  R6 R5 K12    ; R6 := R5["mSearchTerm"]
 48 [-]: SELF      R6 R6 K9     ; R7 := R6; R6 := R6[0xa5c556b9]
 49 [-]: MOVE      R8 R2        ; R8 := R2
 50 [-]: CALL      R6 3 2       ; R6 := R6(R7,R8)
 51 [-]: TEST      R6 1         ; if R6 then PC := 60
 52 [-]: JMP       60           ; PC := 60
 53 [-]: GETUPVAL  R6 U1        ; R6 := U1
 54 [-]: SELF      R6 R6 K13    ; R7 := R6; R6 := R6[0x9ae7e2d2]
 55 [-]: GETTABLE  R8 R5 K14    ; R8 := R5["mIndex"]
 56 [-]: LOADBOOL  R9 1 0       ; R9 := true
 57 [-]: LOADBOOL  R10 1 0      ; R10 := true
 58 [-]: CALL      R6 5 1       ; R6(R7,R8,R9,R10)
 59 [-]: JMP       39           ; PC := 39
 60 [-]: ADD       R4 R4 K15    ; R4 := R4 + 1.000000
 61 [-]: JMP       39           ; PC := 39
 62 [-]: JMP       95           ; PC := 95
 63 [-]: GETUPVAL  R6 U1        ; R6 := U1
 64 [-]: SELF      R6 R6 K16    ; R7 := R6; R6 := R6[0x7c09c373]
 65 [-]: LOADBOOL  R8 1 0       ; R8 := true
 66 [-]: LOADBOOL  R9 1 0       ; R9 := true
 67 [-]: CALL      R6 4 1       ; R6(R7,R8,R9)
 68 [-]: LOADK     R6 1         ; R6 := 1.000000
 69 [-]: GETUPVAL  R7 U1        ; R7 := U1
 70 [-]: GETTABLE  R7 R7 K1     ; R7 := R7["mUnfilteredElements"]
 71 [-]: LEN       R7 R7        ; R7 := # R7
 72 [-]: LOADK     R8 1         ; R8 := 1.000000
 73 [-]: FORPREP   R6 94        ; R6 -= R8; PC := 94
 74 [-]: GETUPVAL  R10 U1       ; R10 := U1
 75 [-]: GETTABLE  R10 R10 K1   ; R10 := R10["mUnfilteredElements"]
 76 [-]: GETTABLE  R10 R10 R9   ; R10 := R10[R9]
 77 [-]: TEST      R10 0        ; if not R10 then PC := 94
 78 [-]: JMP       94           ; PC := 94
 79 [-]: GETTABLE  R11 R10 K12  ; R11 := R10["mSearchTerm"]
 80 [-]: SELF      R11 R11 K9   ; R12 := R11; R11 := R11[0xa5c556b9]
 81 [-]: MOVE      R13 R2       ; R13 := R2
 82 [-]: CALL      R11 3 2      ; R11 := R11(R12,R13)
 83 [-]: TEST      R11 0        ; if not R11 then PC := 94
 84 [-]: JMP       94           ; PC := 94
 85 [-]: GETUPVAL  R11 U1       ; R11 := U1
 86 [-]: SELF      R11 R11 K17  ; R12 := R11; R11 := R11[0xbad4316f]
 87 [-]: GETUPVAL  R13 U2       ; R13 := U2
 88 [-]: GETTABLE  R13 R13 K18  ; R13 := R13[0xae97c4f5]
 89 [-]: MOVE      R14 R10      ; R14 := R10
 90 [-]: CALL      R13 2 2      ; R13 := R13(R14)
 91 [-]: LOADBOOL  R14 1 0      ; R14 := true
 92 [-]: LOADBOOL  R15 1 0      ; R15 := true
 93 [-]: CALL      R11 5 1      ; R11(R12,R13,R14,R15)
 94 [-]: FORLOOP   R6 74        ; R6 += R8; if R6 <= R7 then begin PC := 74; R9 := R6 end
 95 [-]: GETUPVAL  R11 U1       ; R11 := U1
 96 [-]: SELF      R11 R11 K19  ; R12 := R11; R11 := R11[0x71e9ac81]
 97 [-]: LOADNIL   R13 R13      ; R13 := nil
 98 [-]: LOADBOOL  R14 1 0      ; R14 := true
 99 [-]: LOADBOOL  R15 1 0      ; R15 := true
100 [-]: CALL      R11 5 1      ; R11(R12,R13,R14,R15)
101 [-]: RETURN    R0 1         ; return 


; Function #19:
;
; Name:            
; Defined at line: 631
; #Upvalues:       24
; #Parameters:     2
; Is_vararg:       0
; Max Stack Size:  31

  1 [-]: GETUPVAL  R2 U0        ; R2 := U0
  2 [-]: GETUPVAL  R3 U1        ; R3 := U1
  3 [-]: CALL      R2 2 2       ; R2 := R2(R3)
  4 [-]: TEST      R2 1         ; if R2 then PC := 7
  5 [-]: JMP       7            ; PC := 7
  6 [-]: RETURN    R0 1         ; return 
  7 [-]: GETGLOBAL R2 K0        ; R2 := 0x7b998233
  8 [-]: GETGLOBAL R3 K1        ; R3 := _T
  9 [-]: GETUPVAL  R4 U2        ; R4 := U2
 10 [-]: GETTABLE  R3 R3 R4     ; R3 := R3[R4]
 11 [-]: CALL      R2 2 2       ; R2 := R2(R3)
 12 [-]: TEST      R2 1         ; if R2 then PC := 60
 13 [-]: JMP       60           ; PC := 60
 14 [-]: LOADBOOL  R2 0 0       ; R2 := false
 15 [-]: GETGLOBAL R3 K1        ; R3 := _T
 16 [-]: GETUPVAL  R4 U2        ; R4 := U2
 17 [-]: GETTABLE  R3 R3 R4     ; R3 := R3[R4]
 18 [-]: CALL      R3 1 2       ; R3 := R3()
 19 [-]: LOADK     R4 1         ; R4 := 1.000000
 20 [-]: LEN       R5 R3        ; R5 := # R3
 21 [-]: LOADK     R6 1         ; R6 := 1.000000
 22 [-]: FORPREP   R4 54        ; R4 -= R6; PC := 54
 23 [-]: GETGLOBAL R8 K2        ; R8 := 0xce225efa
 24 [-]: LOADK     R9 0         ; R9 := 0.000000
 25 [-]: CALL      R8 2 1       ; R8(R9)
 26 [-]: GETTABLE  R8 R3 R7     ; R8 := R3[R7]
 27 [-]: SETTABLE  R8 K3 R7     ; R8["Id"] := R7
 28 [-]: GETTABLE  R8 R3 R7     ; R8 := R3[R7]
 29 [-]: GETTABLE  R8 R8 K4     ; R8 := R8["mEnabled"]
 30 [-]: EQ        0 R8 K5      ; if R8 ~= nil then PC := 34
 31 [-]: JMP       34           ; PC := 34
 32 [-]: GETTABLE  R8 R3 R7     ; R8 := R3[R7]
 33 [-]: SETTABLE  R8 K4 K6     ; R8["mEnabled"] := true
 34 [-]: GETTABLE  R8 R3 R7     ; R8 := R3[R7]
 35 [-]: GETTABLE  R8 R8 K4     ; R8 := R8["mEnabled"]
 36 [-]: TEST      R8 0         ; if not R8 then PC := 39
 37 [-]: JMP       39           ; PC := 39
 38 [-]: LOADBOOL  R2 1 0       ; R2 := true
 39 [-]: GETTABLE  R8 R3 R7     ; R8 := R3[R7]
 40 [-]: GETGLOBAL R9 K8        ; R9 := 0x7f5022cf
 41 [-]: GETTABLE  R9 R9 K9     ; R9 := R9[0x3f3e4d12]
 42 [-]: GETGLOBAL R10 K10      ; R10 := 0x603636ad
 43 [-]: GETTABLE  R11 R3 R7    ; R11 := R3[R7]
 44 [-]: GETTABLE  R11 R11 K11  ; R11 := R11["mName"]
 45 [-]: NEWTABLE  R12 0 0      ; R12 := {}
 46 [-]: CALL      R10 3 0      ; R10,... := R10(R11,R12)
 47 [-]: CALL      R9 0 2       ; R9 := R9(R10,...)
 48 [-]: SETTABLE  R8 K7 R9     ; R8["mSearchTerm"] := R9
 49 [-]: GETUPVAL  R8 U3        ; R8 := U3
 50 [-]: SELF      R8 R8 K12    ; R9 := R8; R8 := R8[0xbad4316f]
 51 [-]: GETTABLE  R10 R3 R7    ; R10 := R3[R7]
 52 [-]: LOADBOOL  R11 1 0      ; R11 := true
 53 [-]: CALL      R8 4 1       ; R8(R9,R10,R11)
 54 [-]: FORLOOP   R4 23        ; R4 += R6; if R4 <= R5 then begin PC := 23; R7 := R4 end
 55 [-]: TEST      R2 1         ; if R2 then PC := 60
 56 [-]: JMP       60           ; PC := 60
 57 [-]: GETUPVAL  R8 U4        ; R8 := U4
 58 [-]: CALL      R8 1 1       ; R8()
 59 [-]: RETURN    R0 1         ; return 
 60 [-]: GETUPVAL  R8 U5        ; R8 := U5
 61 [-]: CALL      R8 1 1       ; R8()
 62 [-]: GETGLOBAL R8 K0        ; R8 := 0x7b998233
 63 [-]: GETUPVAL  R9 U6        ; R9 := U6
 64 [-]: CALL      R8 2 2       ; R8 := R8(R9)
 65 [-]: TEST      R8 1         ; if R8 then PC := 74
 66 [-]: JMP       74           ; PC := 74
 67 [-]: GETUPVAL  R8 U3        ; R8 := U3
 68 [-]: GETUPVAL  R9 U7        ; R9 := U7
 69 [-]: GETTABLE  R9 R9 K14    ; R9 := R9[0xd6ee7507]
 70 [-]: GETUPVAL  R10 U3       ; R10 := U3
 71 [-]: GETTABLE  R10 R10 K15  ; R10 := R10["mElements"]
 72 [-]: CALL      R9 2 2       ; R9 := R9(R10)
 73 [-]: SETTABLE  R8 K13 R9    ; R8["mUnfilteredElements"] := R9
 74 [-]: GETGLOBAL R8 K16       ; R8 := 0xae91e43b
 75 [-]: SELF      R8 R8 K17    ; R9 := R8; R8 := R8[0x091c120e]
 76 [-]: CALL      R8 2 2       ; R8 := R8(R9)
 77 [-]: MUL       R8 R8 K18    ; R8 := R8 * 0.800000
 78 [-]: GETUPVAL  R9 U3        ; R9 := U3
 79 [-]: GETTABLE  R9 R9 K19    ; R9 := R9["mClipName"]
 80 [-]: LOADK     R10 K20      ; R10 := ".Button.Label"
 81 [-]: CONCAT    R9 R9 R10    ; R9 := R9 .. R10
 82 [-]: GETGLOBAL R10 K16      ; R10 := 0xae91e43b
 83 [-]: SELF      R10 R10 K21  ; R11 := R10; R10 := R10[0x91a24e4b]
 84 [-]: LOADK     R12 K22      ; R12 := "Container.Title"
 85 [-]: LOADK     R13 33       ; R13 := 33.000000
 86 [-]: CALL      R10 4 2      ; R10 := R10(R11,R12,R13)
 87 [-]: ADD       R10 R10 K23  ; R10 := R10 + 38.000000
 88 [-]: GETGLOBAL R11 K24      ; R11 := 0x5bced4c4
 89 [-]: GETTABLE  R11 R11 K25  ; R11 := R11[0xac1b386a]
 90 [-]: GETGLOBAL R12 K24      ; R12 := 0x5bced4c4
 91 [-]: GETTABLE  R12 R12 K26  ; R12 := R12[0xb62ecfe0]
 92 [-]: GETUPVAL  R13 U8       ; R13 := U8
 93 [-]: MOVE      R14 R10      ; R14 := R10
 94 [-]: CALL      R12 3 2      ; R12 := R12(R13,R14)
 95 [-]: MOVE      R13 R8       ; R13 := R8
 96 [-]: CALL      R11 3 2      ; R11 := R11(R12,R13)
 97 [-]: LOADK     R12 0        ; R12 := 0.000000
 98 [-]: GETUPVAL  R13 U3       ; R13 := U3
 99 [-]: SELF      R13 R13 K27  ; R14 := R13; R13 := R13[0xea061e98]
100 [-]: CLOSURE   R15 0        ; R15 := closure(Function #19.1)
101 [-]: GETUPVAL  R0 U9        ; R0 := U9
102 [-]: MOVE      R0 R9        ; R0 := R9
103 [-]: MOVE      R0 R12       ; R0 := R12
104 [-]: MOVE      R0 R11       ; R0 := R11
105 [-]: MOVE      R0 R8        ; R0 := R8
106 [-]: CALL      R13 3 1      ; R13(R14,R15)
107 [-]: GETUPVAL  R13 U3       ; R13 := U3
108 [-]: SETTABLE  R13 K28 R12  ; R13["mCalloutWidth"] := R12
109 [-]: GETUPVAL  R13 U8       ; R13 := U8
110 [-]: EQ        0 R11 R13    ; if R11 ~= R13 then PC := 115
111 [-]: JMP       115          ; PC := 115
112 [-]: GETUPVAL  R13 U10      ; R13 := U10
113 [-]: EQ        0 R13 K29    ; if R13 ~= 0.000000 then PC := 120
114 [-]: JMP       120          ; PC := 120
115 [-]: GETUPVAL  R13 U11      ; R13 := U11
116 [-]: MOVE      R14 R11      ; R14 := R11
117 [-]: MOVE      R15 R0       ; R15 := R0
118 [-]: CALL      R13 3 1      ; R13(R14,R15)
119 [-]: JMP       131          ; PC := 131
120 [-]: GETUPVAL  R13 U3       ; R13 := U3
121 [-]: GETUPVAL  R14 U8       ; R14 := U8
122 [-]: GETUPVAL  R15 U12      ; R15 := U12
123 [-]: SUB       R14 R14 R15  ; R14 := R14 - R15
124 [-]: SETTABLE  R13 K30 R14  ; R13["mButtonWidth"] := R14
125 [-]: GETUPVAL  R13 U3       ; R13 := U3
126 [-]: SELF      R13 R13 K31  ; R14 := R13; R13 := R13[0x71e9ac81]
127 [-]: LOADNIL   R15 R15      ; R15 := nil
128 [-]: LOADBOOL  R16 1 0      ; R16 := true
129 [-]: MOVE      R17 R0       ; R17 := R0
130 [-]: CALL      R13 5 1      ; R13(R14,R15,R16,R17)
131 [-]: LOADK     R13 0        ; R13 := 0.000000
132 [-]: SETUPVAL  R13 U13      ; U82 := R13
133 [-]: GETUPVAL  R13 U3       ; R13 := U3
134 [-]: SELF      R13 R13 K32  ; R14 := R13; R13 := R13[0x741d078c]
135 [-]: CLOSURE   R15 1        ; R15 := closure(Function #19.2)
136 [-]: GETUPVAL  R0 U14       ; R0 := U14
137 [-]: GETUPVAL  R0 U13       ; R0 := U13
138 [-]: CALL      R13 3 1      ; R13(R14,R15)
139 [-]: GETUPVAL  R13 U13      ; R13 := U13
140 [-]: ADD       R13 R13 K33  ; R13 := R13 + 50.000000
141 [-]: SETUPVAL  R13 U13      ; U82 := R13
142 [-]: GETUPVAL  R13 U15      ; R13 := U15
143 [-]: EQ        1 R13 K5     ; if R13 == nil then PC := 148
144 [-]: JMP       148          ; PC := 148
145 [-]: LOADK     R13 54       ; R13 := 54.000000
146 [-]: TEST      R13 1        ; if R13 then PC := 149
147 [-]: JMP       149          ; PC := 149
148 [-]: LOADK     R13 -3       ; R13 := -3.000000
149 [-]: GETGLOBAL R14 K24      ; R14 := 0x5bced4c4
150 [-]: GETTABLE  R14 R14 K26  ; R14 := R14[0xb62ecfe0]
151 [-]: GETGLOBAL R15 K24      ; R15 := 0x5bced4c4
152 [-]: GETTABLE  R15 R15 K25  ; R15 := R15[0xac1b386a]
153 [-]: GETUPVAL  R16 U3       ; R16 := U3
154 [-]: SELF      R16 R16 K34  ; R17 := R16; R16 := R16[0x5fbddc1a]
155 [-]: CALL      R16 2 2      ; R16 := R16(R17)
156 [-]: GETUPVAL  R17 U3       ; R17 := U3
157 [-]: GETTABLE  R17 R17 K35  ; R17 := R17["mVisibleElements"]
158 [-]: CALL      R15 3 2      ; R15 := R15(R16,R17)
159 [-]: GETUPVAL  R16 U3       ; R16 := U3
160 [-]: GETTABLE  R16 R16 K36  ; R16 := R16["mForcedVerticalSeparation"]
161 [-]: MUL       R15 R15 R16  ; R15 := R15 * R16
162 [-]: ADD       R15 K37 R15  ; R15 := 98.000000 + R15
163 [-]: LOADK     R16 50       ; R16 := 50.000000
164 [-]: CALL      R14 3 2      ; R14 := R14(R15,R16)
165 [-]: GETUPVAL  R15 U9       ; R15 := U9
166 [-]: TEST      R15 0        ; if not R15 then PC := 176
167 [-]: JMP       176          ; PC := 176
168 [-]: GETUPVAL  R15 U3       ; R15 := U3
169 [-]: GETUPVAL  R16 U3       ; R16 := U3
170 [-]: GETTABLE  R16 R16 K38  ; R16 := R16["mInitialY"]
171 [-]: ADD       R16 R16 K39  ; R16 := R16 + 8.000000
172 [-]: SETTABLE  R15 K38 R16  ; R15["mInitialY"] := R16
173 [-]: ADD       R15 R14 K40  ; R15 := R14 + 19.000000
174 [-]: ADD       R14 R15 R13  ; R14 := R15 + R13
175 [-]: JMP       187          ; PC := 187
176 [-]: GETGLOBAL R15 K24      ; R15 := 0x5bced4c4
177 [-]: GETTABLE  R15 R15 K26  ; R15 := R15[0xb62ecfe0]
178 [-]: GETUPVAL  R16 U13      ; R16 := U13
179 [-]: GETUPVAL  R17 U16      ; R17 := U16
180 [-]: CALL      R15 3 2      ; R15 := R15(R16,R17)
181 [-]: SETUPVAL  R15 U13      ; U82 := R13
182 [-]: GETUPVAL  R15 U3       ; R15 := U3
183 [-]: SELF      R15 R15 K32  ; R16 := R15; R15 := R15[0x741d078c]
184 [-]: CLOSURE   R17 2        ; R17 := closure(Function #19.3)
185 [-]: GETUPVAL  R0 U13       ; R0 := U13
186 [-]: CALL      R15 3 1      ; R15(R16,R17)
187 [-]: GETUPVAL  R15 U3       ; R15 := U3
188 [-]: SELF      R15 R15 K32  ; R16 := R15; R15 := R15[0x741d078c]
189 [-]: CLOSURE   R17 3        ; R17 := closure(Function #19.4)
190 [-]: GETUPVAL  R0 U13       ; R0 := U13
191 [-]: CALL      R15 3 1      ; R15(R16,R17)
192 [-]: LOADK     R15 0        ; R15 := 0.000000
193 [-]: SETUPVAL  R15 U17      ; U82 := R17
194 [-]: GETUPVAL  R15 U18      ; R15 := U18
195 [-]: EQ        0 R15 K41    ; if R15 ~= "Top" then PC := 208
196 [-]: JMP       208          ; PC := 208
197 [-]: GETGLOBAL R15 K16      ; R15 := 0xae91e43b
198 [-]: SELF      R15 R15 K42  ; R16 := R15; R15 := R15[0x2cc9d281]
199 [-]: CALL      R15 2 2      ; R15 := R15(R16)
200 [-]: MUL       R15 R15 K43  ; R15 := R15 * 0.050000
201 [-]: ADD       R15 R15 K44  ; R15 := R15 + 86.000000
202 [-]: SETUPVAL  R15 U17      ; U82 := R17
203 [-]: GETGLOBAL R15 K16      ; R15 := 0xae91e43b
204 [-]: SELF      R15 R15 K45  ; R16 := R15; R15 := R15[0x1b8d05fd]
205 [-]: LOADK     R17 1        ; R17 := 1.000000
206 [-]: CALL      R15 3 1      ; R15(R16,R17)
207 [-]: JMP       238          ; PC := 238
208 [-]: GETUPVAL  R15 U18      ; R15 := U18
209 [-]: EQ        0 R15 K47    ; if R15 ~= "Middle" then PC := 225
210 [-]: JMP       225          ; PC := 225
211 [-]: GETUPVAL  R15 U7       ; R15 := U7
212 [-]: GETTABLE  R15 R15 K48  ; R15 := R15[0x74a11ec6]
213 [-]: GETGLOBAL R16 K16      ; R16 := 0xae91e43b
214 [-]: SELF      R16 R16 K42  ; R17 := R16; R16 := R16[0x2cc9d281]
215 [-]: CALL      R16 2 2      ; R16 := R16(R17)
216 [-]: SUB       R16 R16 R14  ; R16 := R16 - R14
217 [-]: DIV       R16 R16 K49  ; R16 := R16 / 2.000000
218 [-]: CALL      R15 2 2      ; R15 := R15(R16)
219 [-]: SETUPVAL  R15 U17      ; U82 := R17
220 [-]: GETGLOBAL R15 K16      ; R15 := 0xae91e43b
221 [-]: SELF      R15 R15 K45  ; R16 := R15; R15 := R15[0x1b8d05fd]
222 [-]: LOADK     R17 4        ; R17 := 4.000000
223 [-]: CALL      R15 3 1      ; R15(R16,R17)
224 [-]: JMP       238          ; PC := 238
225 [-]: GETUPVAL  R15 U18      ; R15 := U18
226 [-]: EQ        0 R15 K50    ; if R15 ~= "Bottom" then PC := 238
227 [-]: JMP       238          ; PC := 238
228 [-]: GETGLOBAL R15 K16      ; R15 := 0xae91e43b
229 [-]: SELF      R15 R15 K42  ; R16 := R15; R15 := R15[0x2cc9d281]
230 [-]: CALL      R15 2 2      ; R15 := R15(R16)
231 [-]: MUL       R15 R15 K51  ; R15 := R15 * 0.900000
232 [-]: SUB       R15 R15 R14  ; R15 := R15 - R14
233 [-]: SETUPVAL  R15 U17      ; U82 := R17
234 [-]: GETGLOBAL R15 K16      ; R15 := 0xae91e43b
235 [-]: SELF      R15 R15 K45  ; R16 := R15; R15 := R15[0x1b8d05fd]
236 [-]: LOADK     R17 7        ; R17 := 7.000000
237 [-]: CALL      R15 3 1      ; R15(R16,R17)
238 [-]: GETUPVAL  R15 U19      ; R15 := U19
239 [-]: CALL      R15 1 1      ; R15()
240 [-]: GETUPVAL  R15 U20      ; R15 := U20
241 [-]: GETUPVAL  R16 U7       ; R16 := U7
242 [-]: GETTABLE  R16 R16 K52  ; R16 := R16[0x06d055f9]
243 [-]: GETUPVAL  R17 U9       ; R17 := U9
244 [-]: SUB       R18 K53 R13  ; R18 := 6.000000 - R13
245 [-]: LOADK     R19 0        ; R19 := 0.000000
246 [-]: CALL      R16 4 2      ; R16 := R16(R17,R18,R19)
247 [-]: ADD       R15 R15 R16  ; R15 := R15 + R16
248 [-]: SUB       R16 R14 K54  ; R16 := R14 - 124.000000
249 [-]: GETUPVAL  R17 U3       ; R17 := U3
250 [-]: GETTABLE  R17 R17 K36  ; R17 := R17["mForcedVerticalSeparation"]
251 [-]: ADD       R16 R16 R17  ; R16 := R16 + R17
252 [-]: GETGLOBAL R17 K16      ; R17 := 0xae91e43b
253 [-]: SELF      R17 R17 K55  ; R18 := R17; R17 := R17[0x67bc869f]
254 [-]: LOADK     R19 K56      ; R19 := "Container.BgFill"
255 [-]: LOADK     R20 1        ; R20 := 1.000000
256 [-]: MOVE      R21 R15      ; R21 := R15
257 [-]: CALL      R17 5 1      ; R17(R18,R19,R20,R21)
258 [-]: GETGLOBAL R17 K16      ; R17 := 0xae91e43b
259 [-]: SELF      R17 R17 K55  ; R18 := R17; R17 := R17[0x67bc869f]
260 [-]: LOADK     R19 K56      ; R19 := "Container.BgFill"
261 [-]: LOADK     R20 13       ; R20 := 13.000000
262 [-]: MOVE      R21 R16      ; R21 := R16
263 [-]: CALL      R17 5 1      ; R17(R18,R19,R20,R21)
264 [-]: GETGLOBAL R17 K16      ; R17 := 0xae91e43b
265 [-]: SELF      R17 R17 K55  ; R18 := R17; R17 := R17[0x67bc869f]
266 [-]: LOADK     R19 K57      ; R19 := "Container.Blurer"
267 [-]: LOADK     R20 1        ; R20 := 1.000000
268 [-]: MOVE      R21 R15      ; R21 := R15
269 [-]: CALL      R17 5 1      ; R17(R18,R19,R20,R21)
270 [-]: GETGLOBAL R17 K16      ; R17 := 0xae91e43b
271 [-]: SELF      R17 R17 K55  ; R18 := R17; R17 := R17[0x67bc869f]
272 [-]: LOADK     R19 K57      ; R19 := "Container.Blurer"
273 [-]: LOADK     R20 13       ; R20 := 13.000000
274 [-]: MOVE      R21 R16      ; R21 := R16
275 [-]: CALL      R17 5 1      ; R17(R18,R19,R20,R21)
276 [-]: GETUPVAL  R17 U13      ; R17 := U13
277 [-]: GETUPVAL  R18 U7       ; R18 := U7
278 [-]: GETTABLE  R18 R18 K52  ; R18 := R18[0x06d055f9]
279 [-]: GETUPVAL  R19 U3       ; R19 := U3
280 [-]: SELF      R19 R19 K34  ; R20 := R19; R19 := R19[0x5fbddc1a]
281 [-]: CALL      R19 2 2      ; R19 := R19(R20)
282 [-]: GETUPVAL  R20 U3       ; R20 := U3
283 [-]: GETTABLE  R20 R20 K35  ; R20 := R20["mVisibleElements"]
284 [-]: LT        1 R20 R19    ; if R20 < R19 then PC := 287
285 [-]: JMP       287          ; PC := 287
286 [-]: LOADBOOL  R19 0 1      ; R19 := false; PC := 287
287 [-]: LOADBOOL  R19 1 0      ; R19 := true
288 [-]: LOADK     R20 15       ; R20 := 15.000000
289 [-]: LOADK     R21 0        ; R21 := 0.000000
290 [-]: CALL      R18 4 2      ; R18 := R18(R19,R20,R21)
291 [-]: ADD       R17 R17 R18  ; R17 := R17 + R18
292 [-]: GETUPVAL  R18 U21      ; R18 := U21
293 [-]: EQ        1 R18 K5     ; if R18 == nil then PC := 379
294 [-]: JMP       379          ; PC := 379
295 [-]: GETGLOBAL R18 K16      ; R18 := 0xae91e43b
296 [-]: SELF      R18 R18 K21  ; R19 := R18; R18 := R18[0x91a24e4b]
297 [-]: LOADK     R20 K58      ; R20 := "Container"
298 [-]: LOADK     R21 5        ; R21 := 5.000000
299 [-]: CALL      R18 4 2      ; R18 := R18(R19,R20,R21)
300 [-]: GETGLOBAL R19 K16      ; R19 := 0xae91e43b
301 [-]: SELF      R19 R19 K21  ; R20 := R19; R19 := R19[0x91a24e4b]
302 [-]: LOADK     R21 K58      ; R21 := "Container"
303 [-]: LOADK     R22 6        ; R22 := 6.000000
304 [-]: CALL      R19 4 2      ; R19 := R19(R20,R21,R22)
305 [-]: GETGLOBAL R20 K16      ; R20 := 0xae91e43b
306 [-]: SELF      R20 R20 K21  ; R21 := R20; R20 := R20[0x91a24e4b]
307 [-]: LOADK     R22 K22      ; R22 := "Container.Title"
308 [-]: LOADK     R23 1        ; R23 := 1.000000
309 [-]: CALL      R20 4 2      ; R20 := R20(R21,R22,R23)
310 [-]: SUB       R20 R15 R20  ; R20 := R15 - R20
311 [-]: ADD       R20 R20 K53  ; R20 := R20 + 6.000000
312 [-]: DIV       R21 R19 K59  ; R21 := R19 / 100.000000
313 [-]: MUL       R20 R20 R21  ; R20 := R20 * R21
314 [-]: GETGLOBAL R21 K16      ; R21 := 0xae91e43b
315 [-]: SELF      R21 R21 K21  ; R22 := R21; R21 := R21[0x91a24e4b]
316 [-]: LOADK     R23 K58      ; R23 := "Container"
317 [-]: LOADK     R24 12       ; R24 := 12.000000
318 [-]: CALL      R21 4 2      ; R21 := R21(R22,R23,R24)
319 [-]: DIV       R21 R21 K49  ; R21 := R21 / 2.000000
320 [-]: DIV       R22 R18 K59  ; R22 := R18 / 100.000000
321 [-]: MUL       R22 K60 R22  ; R22 := 14.000000 * R22
322 [-]: SUB       R21 R21 R22  ; R21 := R21 - R22
323 [-]: GETUPVAL  R22 U21      ; R22 := U21
324 [-]: GETTABLE  R22 R22 K61  ; R22 := R22["y"]
325 [-]: SUB       R22 R22 R20  ; R22 := R22 - R20
326 [-]: SUB       R23 R14 K62  ; R23 := R14 - 68.000000
327 [-]: DIV       R24 R19 K59  ; R24 := R19 / 100.000000
328 [-]: MUL       R23 R23 R24  ; R23 := R23 * R24
329 [-]: ADD       R22 R22 R23  ; R22 := R22 + R23
330 [-]: GETGLOBAL R23 K16      ; R23 := 0xae91e43b
331 [-]: SELF      R23 R23 K42  ; R24 := R23; R23 := R23[0x2cc9d281]
332 [-]: CALL      R23 2 2      ; R23 := R23(R24)
333 [-]: LT        0 R23 R22    ; if R23 >= R22 then PC := 344
334 [-]: JMP       344          ; PC := 344
335 [-]: GETUPVAL  R22 U21      ; R22 := U21
336 [-]: GETTABLE  R22 R22 K61  ; R22 := R22["y"]
337 [-]: SUB       R22 R22 R20  ; R22 := R22 - R20
338 [-]: SUB       R23 R14 K44  ; R23 := R14 - 86.000000
339 [-]: DIV       R24 R19 K59  ; R24 := R19 / 100.000000
340 [-]: MUL       R23 R23 R24  ; R23 := R23 * R24
341 [-]: SUB       R22 R22 R23  ; R22 := R22 - R23
342 [-]: SETUPVAL  R22 U17      ; U82 := R17
343 [-]: JMP       348          ; PC := 348
344 [-]: GETUPVAL  R22 U21      ; R22 := U21
345 [-]: GETTABLE  R22 R22 K61  ; R22 := R22["y"]
346 [-]: SUB       R22 R22 R20  ; R22 := R22 - R20
347 [-]: SETUPVAL  R22 U17      ; U82 := R17
348 [-]: GETUPVAL  R22 U21      ; R22 := U21
349 [-]: GETTABLE  R22 R22 K63  ; R22 := R22["x"]
350 [-]: DIV       R23 R18 K59  ; R23 := R18 / 100.000000
351 [-]: MUL       R23 R21 R23  ; R23 := R21 * R23
352 [-]: ADD       R22 R22 R23  ; R22 := R22 + R23
353 [-]: GETGLOBAL R23 K16      ; R23 := 0xae91e43b
354 [-]: SELF      R23 R23 K17  ; R24 := R23; R23 := R23[0x091c120e]
355 [-]: CALL      R23 2 2      ; R23 := R23(R24)
356 [-]: LT        0 R23 R22    ; if R23 >= R22 then PC := 370
357 [-]: JMP       370          ; PC := 370
358 [-]: GETGLOBAL R22 K16      ; R22 := 0xae91e43b
359 [-]: SELF      R22 R22 K55  ; R23 := R22; R22 := R22[0x67bc869f]
360 [-]: LOADK     R24 K58      ; R24 := "Container"
361 [-]: LOADK     R25 0        ; R25 := 0.000000
362 [-]: GETUPVAL  R26 U21      ; R26 := U21
363 [-]: GETTABLE  R26 R26 K63  ; R26 := R26["x"]
364 [-]: ADD       R26 R26 R21  ; R26 := R26 + R21
365 [-]: DIV       R27 R18 K59  ; R27 := R18 / 100.000000
366 [-]: MUL       R27 R17 R27  ; R27 := R17 * R27
367 [-]: SUB       R26 R26 R27  ; R26 := R26 - R27
368 [-]: CALL      R22 5 1      ; R22(R23,R24,R25,R26)
369 [-]: JMP       388          ; PC := 388
370 [-]: GETGLOBAL R22 K16      ; R22 := 0xae91e43b
371 [-]: SELF      R22 R22 K55  ; R23 := R22; R22 := R22[0x67bc869f]
372 [-]: LOADK     R24 K58      ; R24 := "Container"
373 [-]: LOADK     R25 0        ; R25 := 0.000000
374 [-]: GETUPVAL  R26 U21      ; R26 := U21
375 [-]: GETTABLE  R26 R26 K63  ; R26 := R26["x"]
376 [-]: ADD       R26 R26 R21  ; R26 := R26 + R21
377 [-]: CALL      R22 5 1      ; R22(R23,R24,R25,R26)
378 [-]: JMP       388          ; PC := 388
379 [-]: GETGLOBAL R22 K16      ; R22 := 0xae91e43b
380 [-]: SELF      R22 R22 K55  ; R23 := R22; R22 := R22[0x67bc869f]
381 [-]: LOADK     R24 K58      ; R24 := "Container"
382 [-]: LOADK     R25 0        ; R25 := 0.000000
383 [-]: GETGLOBAL R26 K16      ; R26 := 0xae91e43b
384 [-]: SELF      R26 R26 K17  ; R27 := R26; R26 := R26[0x091c120e]
385 [-]: CALL      R26 2 2      ; R26 := R26(R27)
386 [-]: MUL       R26 R26 K64  ; R26 := R26 * 0.500000
387 [-]: CALL      R22 5 1      ; R22(R23,R24,R25,R26)
388 [-]: GETGLOBAL R22 K16      ; R22 := 0xae91e43b
389 [-]: SELF      R22 R22 K55  ; R23 := R22; R22 := R22[0x67bc869f]
390 [-]: LOADK     R24 K58      ; R24 := "Container"
391 [-]: LOADK     R25 1        ; R25 := 1.000000
392 [-]: GETUPVAL  R26 U17      ; R26 := U17
393 [-]: ADD       R26 R26 R13  ; R26 := R26 + R13
394 [-]: CALL      R22 5 1      ; R22(R23,R24,R25,R26)
395 [-]: GETGLOBAL R22 K16      ; R22 := 0xae91e43b
396 [-]: SELF      R22 R22 K65  ; R23 := R22; R22 := R22[0xaade900e]
397 [-]: LOADK     R24 K66      ; R24 := "Container.Message"
398 [-]: LOADK     R25 11       ; R25 := 11.000000
399 [-]: GETUPVAL  R26 U3       ; R26 := U3
400 [-]: SELF      R26 R26 K34  ; R27 := R26; R26 := R26[0x5fbddc1a]
401 [-]: CALL      R26 2 2      ; R26 := R26(R27)
402 [-]: EQ        1 R26 K29    ; if R26 == 0.000000 then PC := 405
403 [-]: JMP       405          ; PC := 405
404 [-]: LOADBOOL  R26 0 1      ; R26 := false; PC := 405
405 [-]: LOADBOOL  R26 1 0      ; R26 := true
406 [-]: CALL      R22 5 1      ; R22(R23,R24,R25,R26)
407 [-]: GETGLOBAL R22 K1       ; R22 := _T
408 [-]: GETTABLE  R22 R22 K67  ; R22 := R22["GenericMenu_IdToSelect"]
409 [-]: EQ        1 R22 K5     ; if R22 == nil then PC := 415
410 [-]: JMP       415          ; PC := 415
411 [-]: GETGLOBAL R22 K1       ; R22 := _T
412 [-]: GETTABLE  R1 R22 K67   ; R1 := R22["GenericMenu_IdToSelect"]
413 [-]: GETGLOBAL R22 K1       ; R22 := _T
414 [-]: SETTABLE  R22 K67 K5   ; R22["GenericMenu_IdToSelect"] := nil
415 [-]: EQ        1 R1 K5      ; if R1 == nil then PC := 429
416 [-]: JMP       429          ; PC := 429
417 [-]: GETGLOBAL R22 K68      ; R22 := 0x42dcc9f5
418 [-]: MOVE      R23 R1       ; R23 := R1
419 [-]: LOADK     R24 1        ; R24 := 1.000000
420 [-]: GETUPVAL  R25 U3       ; R25 := U3
421 [-]: SELF      R25 R25 K34  ; R26 := R25; R25 := R25[0x5fbddc1a]
422 [-]: CALL      R25 2 0      ; R25,... := R25(R26)
423 [-]: CALL      R22 0 2      ; R22 := R22(R23,...)
424 [-]: MOVE      R1 R22       ; R1 := R22
425 [-]: GETUPVAL  R22 U3       ; R22 := U3
426 [-]: SELF      R22 R22 K69  ; R23 := R22; R22 := R22[0x1e63ac7a]
427 [-]: MOVE      R24 R1       ; R24 := R1
428 [-]: CALL      R22 3 1      ; R22(R23,R24)
429 [-]: GETUPVAL  R22 U3       ; R22 := U3
430 [-]: SELF      R22 R22 K31  ; R23 := R22; R22 := R22[0x71e9ac81]
431 [-]: LOADNIL   R24 R24      ; R24 := nil
432 [-]: LOADBOOL  R25 1 0      ; R25 := true
433 [-]: MOVE      R26 R0       ; R26 := R0
434 [-]: CALL      R22 5 1      ; R22(R23,R24,R25,R26)
435 [-]: TEST      R0 0         ; if not R0 then PC := 446
436 [-]: JMP       446          ; PC := 446
437 [-]: GETGLOBAL R22 K16      ; R22 := 0xae91e43b
438 [-]: SELF      R22 R22 K55  ; R23 := R22; R22 := R22[0x67bc869f]
439 [-]: LOADK     R24 K70      ; R24 := "_root"
440 [-]: LOADK     R25 10       ; R25 := 10.000000
441 [-]: LOADK     R26 100      ; R26 := 100.000000
442 [-]: CALL      R22 5 1      ; R22(R23,R24,R25,R26)
443 [-]: LOADBOOL  R22 0 0      ; R22 := false
444 [-]: SETUPVAL  R22 U22      ; U82 := R22
445 [-]: JMP       461          ; PC := 461
446 [-]: GETGLOBAL R22 K71      ; R22 := 0x25312c9b
447 [-]: GETGLOBAL R23 K16      ; R23 := 0xae91e43b
448 [-]: LOADK     R24 K70      ; R24 := "_root"
449 [-]: LOADK     R25 2        ; R25 := 2.000000
450 [-]: NEWTABLE  R26 1 0      ; R26 := {}
451 [-]: LOADK     R27 10       ; R27 := 10.000000
452 [-]: SETLIST   R26 1 1      ; R26[(1-1)*FPF+i] := R(26+i), 1 <= i <= 1
453 [-]: NEWTABLE  R27 1 0      ; R27 := {}
454 [-]: LOADK     R28 100      ; R28 := 100.000000
455 [-]: SETLIST   R27 1 1      ; R27[(1-1)*FPF+i] := R(27+i), 1 <= i <= 1
456 [-]: GETUPVAL  R28 U23      ; R28 := U23
457 [-]: LOADK     R29 0        ; R29 := 0.000000
458 [-]: CLOSURE   R30 4        ; R30 := closure(Function #19.5)
459 [-]: GETUPVAL  R0 U22       ; R0 := U22
460 [-]: CALL      R22 9 1      ; R22(R23,R24,R25,R26,R27,R28,R29,R30)
461 [-]: RETURN    R0 1         ; return 


; Function #19.1:
;
; Name:            
; Defined at line: 678
; #Upvalues:       5
; #Parameters:     1
; Is_vararg:       0
; Max Stack Size:  8

  1 [-]: GETGLOBAL R1 K0        ; R1 := 0x5f0788c4
  2 [-]: GETGLOBAL R2 K1        ; R2 := 0x603636ad
  3 [-]: GETTABLE  R3 R0 K2     ; R3 := R0["mName"]
  4 [-]: NEWTABLE  R4 0 0       ; R4 := {}
  5 [-]: CALL      R2 3 0       ; R2,... := R2(R3,R4)
  6 [-]: CALL      R1 0 2       ; R1 := R1(R2,...)
  7 [-]: GETUPVAL  R2 U0        ; R2 := U0
  8 [-]: TEST      R2 0         ; if not R2 then PC := 18
  9 [-]: JMP       18           ; PC := 18
 10 [-]: GETGLOBAL R2 K3        ; R2 := 0xae91e43b
 11 [-]: SELF      R2 R2 K4     ; R3 := R2; R2 := R2[0x42b04007]
 12 [-]: LOADK     R4 K5        ; R4 := "<MINI_ARROW>"
 13 [-]: LOADBOOL  R5 1 0       ; R5 := true
 14 [-]: CALL      R2 4 2       ; R2 := R2(R3,R4,R5)
 15 [-]: LOADK     R3 K6        ; R3 := " "
 16 [-]: MOVE      R4 R1        ; R4 := R1
 17 [-]: CONCAT    R1 R2 R4     ; R1 := R2 .. R3 .. R4
 18 [-]: GETGLOBAL R2 K3        ; R2 := 0xae91e43b
 19 [-]: SELF      R2 R2 K7     ; R3 := R2; R2 := R2[0x5f56eeab]
 20 [-]: GETUPVAL  R4 U1        ; R4 := U1
 21 [-]: LOADK     R5 29        ; R5 := 29.000000
 22 [-]: MOVE      R6 R1        ; R6 := R1
 23 [-]: CALL      R2 5 1       ; R2(R3,R4,R5,R6)
 24 [-]: GETGLOBAL R2 K3        ; R2 := 0xae91e43b
 25 [-]: SELF      R2 R2 K8     ; R3 := R2; R2 := R2[0x91a24e4b]
 26 [-]: GETUPVAL  R4 U1        ; R4 := U1
 27 [-]: LOADK     R5 33        ; R5 := 33.000000
 28 [-]: CALL      R2 4 2       ; R2 := R2(R3,R4,R5)
 29 [-]: GETTABLE  R3 R0 K9     ; R3 := R0["mRightText"]
 30 [-]: LEN       R3 R3        ; R3 := # R3
 31 [-]: LT        0 K10 R3     ; if 0.000000 >= R3 then PC := 52
 32 [-]: JMP       52           ; PC := 52
 33 [-]: GETGLOBAL R3 K3        ; R3 := 0xae91e43b
 34 [-]: SELF      R3 R3 K7     ; R4 := R3; R3 := R3[0x5f56eeab]
 35 [-]: GETUPVAL  R5 U1        ; R5 := U1
 36 [-]: LOADK     R6 29        ; R6 := 29.000000
 37 [-]: GETTABLE  R7 R0 K9     ; R7 := R0["mRightText"]
 38 [-]: CALL      R3 5 1       ; R3(R4,R5,R6,R7)
 39 [-]: GETGLOBAL R3 K3        ; R3 := 0xae91e43b
 40 [-]: SELF      R3 R3 K8     ; R4 := R3; R3 := R3[0x91a24e4b]
 41 [-]: GETUPVAL  R5 U1        ; R5 := U1
 42 [-]: LOADK     R6 33        ; R6 := 33.000000
 43 [-]: CALL      R3 4 2       ; R3 := R3(R4,R5,R6)
 44 [-]: ADD       R4 R2 K11    ; R4 := R2 + 10.000000
 45 [-]: ADD       R2 R4 R3     ; R2 := R4 + R3
 46 [-]: GETGLOBAL R4 K12       ; R4 := 0x5bced4c4
 47 [-]: GETTABLE  R4 R4 K13    ; R4 := R4[0xb62ecfe0]
 48 [-]: GETUPVAL  R5 U2        ; R5 := U2
 49 [-]: MOVE      R6 R3        ; R6 := R3
 50 [-]: CALL      R4 3 2       ; R4 := R4(R5,R6)
 51 [-]: SETUPVAL  R4 U2        ; U82 := R2
 52 [-]: ADD       R2 R2 K14    ; R2 := R2 + 50.000000
 53 [-]: GETGLOBAL R4 K12       ; R4 := 0x5bced4c4
 54 [-]: GETTABLE  R4 R4 K15    ; R4 := R4[0xac1b386a]
 55 [-]: GETGLOBAL R5 K12       ; R5 := 0x5bced4c4
 56 [-]: GETTABLE  R5 R5 K13    ; R5 := R5[0xb62ecfe0]
 57 [-]: GETUPVAL  R6 U3        ; R6 := U3
 58 [-]: MOVE      R7 R2        ; R7 := R2
 59 [-]: CALL      R5 3 2       ; R5 := R5(R6,R7)
 60 [-]: GETUPVAL  R6 U4        ; R6 := U4
 61 [-]: CALL      R4 3 2       ; R4 := R4(R5,R6)
 62 [-]: SETUPVAL  R4 U3        ; U82 := R3
 63 [-]: RETURN    R0 1         ; return 


; Function #19.2:
;
; Name:            
; Defined at line: 709
; #Upvalues:       2
; #Parameters:     1
; Is_vararg:       0
; Max Stack Size:  5

  1 [-]: GETTABLE  R1 R0 K0     ; R1 := R0["mClipName"]
  2 [-]: TEST      R1 0         ; if not R1 then PC := 21
  3 [-]: JMP       21           ; PC := 21
  4 [-]: GETGLOBAL R1 K1        ; R1 := 0xae91e43b
  5 [-]: SELF      R1 R1 K2     ; R2 := R1; R1 := R1[0x91a24e4b]
  6 [-]: GETTABLE  R3 R0 K0     ; R3 := R0["mClipName"]
  7 [-]: LOADK     R4 K3        ; R4 := ".Button.Label"
  8 [-]: CONCAT    R3 R3 R4     ; R3 := R3 .. R4
  9 [-]: LOADK     R4 33        ; R4 := 33.000000
 10 [-]: CALL      R1 4 2       ; R1 := R1(R2,R3,R4)
 11 [-]: GETTABLE  R2 R0 K4     ; R2 := R0["Type"]
 12 [-]: GETUPVAL  R3 U0        ; R3 := U0
 13 [-]: GETTABLE  R3 R3 K5     ; R3 := R3["ICONBUTTON"]
 14 [-]: EQ        0 R2 R3      ; if R2 ~= R3 then PC := 17
 15 [-]: JMP       17           ; PC := 17
 16 [-]: ADD       R1 R1 K6     ; R1 := R1 + 36.000000
 17 [-]: GETUPVAL  R2 U1        ; R2 := U1
 18 [-]: LT        0 R2 R1      ; if R2 >= R1 then PC := 21
 19 [-]: JMP       21           ; PC := 21
 20 [-]: SETUPVAL  R1 U1        ; U82 := R1
 21 [-]: RETURN    R0 1         ; return 


; Function #19.3:
;
; Name:            
; Defined at line: 731
; #Upvalues:       1
; #Parameters:     1
; Is_vararg:       0
; Max Stack Size:  7

  1 [-]: GETGLOBAL R1 K0        ; R1 := 0xae91e43b
  2 [-]: SELF      R1 R1 K1     ; R2 := R1; R1 := R1[0xf64b7262]
  3 [-]: GETTABLE  R3 R0 K2     ; R3 := R0["mClipName"]
  4 [-]: LOADK     R4 K3        ; R4 := "Button.Bg"
  5 [-]: LOADK     R5 12        ; R5 := 12.000000
  6 [-]: GETUPVAL  R6 U0        ; R6 := U0
  7 [-]: SUB       R6 R6 K4     ; R6 := R6 - 20.000000
  8 [-]: CALL      R1 6 1       ; R1(R2,R3,R4,R5,R6)
  9 [-]: RETURN    R0 1         ; return 


; Function #19.4:
;
; Name:            
; Defined at line: 737
; #Upvalues:       1
; #Parameters:     1
; Is_vararg:       0
; Max Stack Size:  7

  1 [-]: GETGLOBAL R1 K0        ; R1 := 0xae91e43b
  2 [-]: SELF      R1 R1 K1     ; R2 := R1; R1 := R1[0xf64b7262]
  3 [-]: GETTABLE  R3 R0 K2     ; R3 := R0["mClipName"]
  4 [-]: LOADK     R4 K3        ; R4 := "Button.Btn"
  5 [-]: LOADK     R5 12        ; R5 := 12.000000
  6 [-]: GETUPVAL  R6 U0        ; R6 := U0
  7 [-]: SUB       R6 R6 K4     ; R6 := R6 - 20.000000
  8 [-]: CALL      R1 6 1       ; R1(R2,R3,R4,R5,R6)
  9 [-]: RETURN    R0 1         ; return 


; Function #19.5:
;
; Name:            
; Defined at line: 801
; #Upvalues:       1
; #Parameters:     0
; Is_vararg:       0
; Max Stack Size:  2

  1 [-]: LOADBOOL  R0 0 0       ; R0 := false
  2 [-]: SETUPVAL  R0 U0        ; U82 := R0
  3 [-]: RETURN    R0 1         ; return 


; Function #20:
;
; Name:            
; Defined at line: 807
; #Upvalues:       16
; #Parameters:     0
; Is_vararg:       0
; Max Stack Size:  13

  1 [-]: GETGLOBAL R0 K0        ; R0 := 0x2d0fad09
  2 [-]: LOADK     R1 K1        ; R1 := "Lotus.Interface.Libs.TimerMgr"
  3 [-]: CALL      R0 2 2       ; R0 := R0(R1)
  4 [-]: GETTABLE  R1 R0 K2     ; R1 := R0[0xde474187]
  5 [-]: CALL      R1 1 2       ; R1 := R1()
  6 [-]: SETUPVAL  R1 U0        ; U82 := R0
  7 [-]: GETGLOBAL R1 K3        ; R1 := 0x7b998233
  8 [-]: GETGLOBAL R2 K4        ; R2 := _T
  9 [-]: GETTABLE  R2 R2 K5     ; R2 := R2["DialogOpenSound"]
 10 [-]: CALL      R1 2 2       ; R1 := R1(R2)
 11 [-]: TEST      R1 1         ; if R1 then PC := 22
 12 [-]: JMP       22           ; PC := 22
 13 [-]: GETGLOBAL R1 K6        ; R1 := 0xb009bbc6
 14 [-]: GETGLOBAL R2 K4        ; R2 := _T
 15 [-]: GETTABLE  R2 R2 K5     ; R2 := R2["DialogOpenSound"]
 16 [-]: CALL      R1 2 2       ; R1 := R1(R2)
 17 [-]: GETUPVAL  R2 U1        ; R2 := U1
 18 [-]: GETTABLE  R2 R2 K7     ; R2 := R2[0x659d451f]
 19 [-]: MOVE      R3 R1        ; R3 := R1
 20 [-]: CALL      R2 2 1       ; R2(R3)
 21 [-]: JMP       27           ; PC := 27
 22 [-]: GETUPVAL  R2 U1        ; R2 := U1
 23 [-]: GETTABLE  R2 R2 K7     ; R2 := R2[0x659d451f]
 24 [-]: GETGLOBAL R3 K8        ; R3 := 0x0032441c
 25 [-]: GETTABLE  R3 R3 K9     ; R3 := R3["UISound_WindowOpen"]
 26 [-]: CALL      R2 2 1       ; R2(R3)
 27 [-]: GETGLOBAL R2 K4        ; R2 := _T
 28 [-]: GETTABLE  R2 R2 K10    ; R2 := R2["UIInputEnabled"]
 29 [-]: TEST      R2 1         ; if R2 then PC := 38
 30 [-]: JMP       38           ; PC := 38
 31 [-]: GETGLOBAL R2 K4        ; R2 := _T
 32 [-]: GETTABLE  R2 R2 K11    ; R2 := R2[0x3b0face1]
 33 [-]: GETGLOBAL R3 K4        ; R3 := _T
 34 [-]: GETTABLE  R3 R3 K12    ; R3 := R3["GenericMenu_HideMoneyOverlay"]
 35 [-]: CALL      R2 2 1       ; R2(R3)
 36 [-]: LOADBOOL  R2 1 0       ; R2 := true
 37 [-]: SETUPVAL  R2 U2        ; U82 := R2
 38 [-]: GETGLOBAL R2 K4        ; R2 := _T
 39 [-]: SETTABLE  R2 K12 K13   ; R2["GenericMenu_HideMoneyOverlay"] := nil
 40 [-]: GETGLOBAL R2 K0        ; R2 := 0x2d0fad09
 41 [-]: LOADK     R3 K14       ; R3 := "EE.Interface.AnchorMgr"
 42 [-]: CALL      R2 2 2       ; R2 := R2(R3)
 43 [-]: GETTABLE  R3 R2 K15    ; R3 := R2[0xae6791ba]
 44 [-]: GETGLOBAL R4 K16       ; R4 := 0xae91e43b
 45 [-]: CALL      R3 2 2       ; R3 := R3(R4)
 46 [-]: SETUPVAL  R3 U3        ; U82 := R3
 47 [-]: GETUPVAL  R3 U3        ; R3 := U3
 48 [-]: SELF      R3 R3 K17    ; R4 := R3; R3 := R3[0x20ff29f7]
 49 [-]: GETGLOBAL R5 K16       ; R5 := 0xae91e43b
 50 [-]: LOADK     R6 K18       ; R6 := "MouseCatcher"
 51 [-]: NEWTABLE  R7 2 0       ; R7 := {}
 52 [-]: GETUPVAL  R8 U3        ; R8 := U3
 53 [-]: GETTABLE  R8 R8 K19    ; R8 := R8["ANCHOR_H_CENTRE"]
 54 [-]: GETUPVAL  R9 U3        ; R9 := U3
 55 [-]: GETTABLE  R9 R9 K20    ; R9 := R9["ANCHOR_V_CENTRE"]
 56 [-]: SETLIST   R7 2 1       ; R7[(1-1)*FPF+i] := R(7+i), 1 <= i <= 2
 57 [-]: CALL      R3 5 1       ; R3(R4,R5,R6,R7)
 58 [-]: GETGLOBAL R3 K16       ; R3 := 0xae91e43b
 59 [-]: SELF      R3 R3 K21    ; R4 := R3; R3 := R3[0x91a24e4b]
 60 [-]: LOADK     R5 K22       ; R5 := "Container.BgFill"
 61 [-]: LOADK     R6 1         ; R6 := 1.000000
 62 [-]: CALL      R3 4 2       ; R3 := R3(R4,R5,R6)
 63 [-]: SETUPVAL  R3 U4        ; U82 := R4
 64 [-]: GETGLOBAL R3 K16       ; R3 := 0xae91e43b
 65 [-]: SELF      R3 R3 K23    ; R4 := R3; R3 := R3[0x67bc869f]
 66 [-]: LOADK     R5 K24       ; R5 := "Container.ScrollBar"
 67 [-]: LOADK     R6 1         ; R6 := 1.000000
 68 [-]: LOADK     R7 52        ; R7 := 52.000000
 69 [-]: CALL      R3 5 1       ; R3(R4,R5,R6,R7)
 70 [-]: GETGLOBAL R3 K16       ; R3 := 0xae91e43b
 71 [-]: SELF      R3 R3 K25    ; R4 := R3; R3 := R3[0xaade900e]
 72 [-]: LOADK     R5 K26       ; R5 := "Container.SearchBox"
 73 [-]: LOADK     R6 11        ; R6 := 11.000000
 74 [-]: LOADBOOL  R7 0 0       ; R7 := false
 75 [-]: CALL      R3 5 1       ; R3(R4,R5,R6,R7)
 76 [-]: GETGLOBAL R3 K4        ; R3 := _T
 77 [-]: GETTABLE  R3 R3 K27    ; R3 := R3["DialogueMode"]
 78 [-]: EQ        1 R3 K28     ; if R3 == true then PC := 81
 79 [-]: JMP       81           ; PC := 81
 80 [-]: LOADBOOL  R3 0 1       ; R3 := false; PC := 81
 81 [-]: LOADBOOL  R3 1 0       ; R3 := true
 82 [-]: SETUPVAL  R3 U5        ; U82 := R5
 83 [-]: GETUPVAL  R3 U5        ; R3 := U5
 84 [-]: TEST      R3 0         ; if not R3 then PC := 88
 85 [-]: JMP       88           ; PC := 88
 86 [-]: LOADK     R3 -8        ; R3 := -8.000000
 87 [-]: SETUPVAL  R3 U6        ; U82 := R6
 88 [-]: GETGLOBAL R3 K16       ; R3 := 0xae91e43b
 89 [-]: SELF      R3 R3 K25    ; R4 := R3; R3 := R3[0xaade900e]
 90 [-]: LOADK     R5 K29       ; R5 := "Container.Underline"
 91 [-]: LOADK     R6 11        ; R6 := 11.000000
 92 [-]: GETUPVAL  R7 U5        ; R7 := U5
 93 [-]: CALL      R3 5 1       ; R3(R4,R5,R6,R7)
 94 [-]: GETGLOBAL R3 K16       ; R3 := 0xae91e43b
 95 [-]: SELF      R3 R3 K30    ; R4 := R3; R3 := R3[0xd5181643]
 96 [-]: LOADK     R5 K22       ; R5 := "Container.BgFill"
 97 [-]: GETGLOBAL R6 K8        ; R6 := 0x0032441c
 98 [-]: GETTABLE  R6 R6 K31    ; R6 := R6["UIMaterial_RectangleNoDepth"]
 99 [-]: CALL      R3 4 1       ; R3(R4,R5,R6)
100 [-]: GETGLOBAL R3 K16       ; R3 := 0xae91e43b
101 [-]: SELF      R3 R3 K32    ; R4 := R3; R3 := R3[0x0c33ebb2]
102 [-]: LOADK     R5 K22       ; R5 := "Container.BgFill"
103 [-]: LOADK     R6 K33       ; R6 := "noMenuSelection"
104 [-]: LOADBOOL  R7 1 0       ; R7 := true
105 [-]: CALL      R3 5 1       ; R3(R4,R5,R6,R7)
106 [-]: GETGLOBAL R3 K16       ; R3 := 0xae91e43b
107 [-]: SELF      R3 R3 K32    ; R4 := R3; R3 := R3[0x0c33ebb2]
108 [-]: LOADK     R5 K18       ; R5 := "MouseCatcher"
109 [-]: LOADK     R6 K33       ; R6 := "noMenuSelection"
110 [-]: LOADBOOL  R7 1 0       ; R7 := true
111 [-]: CALL      R3 5 1       ; R3(R4,R5,R6,R7)
112 [-]: GETGLOBAL R3 K16       ; R3 := 0xae91e43b
113 [-]: SELF      R3 R3 K34    ; R4 := R3; R3 := R3[0x1e5b5cfe]
114 [-]: LOADK     R5 K18       ; R5 := "MouseCatcher"
115 [-]: LOADNIL   R6 R8        ; R6 := R7 := R8 := nil
116 [-]: LOADK     R9 K35       ; R9 := "MouseCatcherPressed"
117 [-]: CALL      R3 7 1       ; R3(R4,R5,R6,R7,R8,R9)
118 [-]: GETGLOBAL R3 K16       ; R3 := 0xae91e43b
119 [-]: SELF      R3 R3 K36    ; R4 := R3; R3 := R3[0x2002e1dc]
120 [-]: GETGLOBAL R5 K4        ; R5 := _T
121 [-]: GETTABLE  R5 R5 K37    ; R5 := R5["RadialSolarMapOpen"]
122 [-]: EQ        1 R5 K28     ; if R5 == true then PC := 125
123 [-]: JMP       125          ; PC := 125
124 [-]: LOADBOOL  R5 0 1       ; R5 := false; PC := 125
125 [-]: LOADBOOL  R5 1 0       ; R5 := true
126 [-]: CALL      R3 3 1       ; R3(R4,R5)
127 [-]: GETUPVAL  R3 U5        ; R3 := U5
128 [-]: TEST      R3 0         ; if not R3 then PC := 132
129 [-]: JMP       132          ; PC := 132
130 [-]: LOADK     R3 100       ; R3 := 100.000000
131 [-]: SETUPVAL  R3 U7        ; U82 := R7
132 [-]: GETUPVAL  R3 U8        ; R3 := U8
133 [-]: CALL      R3 1 1       ; R3()
134 [-]: GETGLOBAL R3 K16       ; R3 := 0xae91e43b
135 [-]: SELF      R3 R3 K23    ; R4 := R3; R3 := R3[0x67bc869f]
136 [-]: LOADK     R5 K38       ; R5 := "_root"
137 [-]: LOADK     R6 10        ; R6 := 10.000000
138 [-]: LOADK     R7 0         ; R7 := 0.000000
139 [-]: CALL      R3 5 1       ; R3(R4,R5,R6,R7)
140 [-]: GETGLOBAL R3 K39       ; R3 := 0x34291f5c
141 [-]: GETTABLE  R3 R3 K40    ; R3 := R3[0xa7a2e381]
142 [-]: CALL      R3 1 2       ; R3 := R3()
143 [-]: TEST      R3 0         ; if not R3 then PC := 151
144 [-]: JMP       151          ; PC := 151
145 [-]: GETGLOBAL R3 K16       ; R3 := 0xae91e43b
146 [-]: SELF      R3 R3 K41    ; R4 := R3; R3 := R3[0x5f56eeab]
147 [-]: LOADK     R5 K42       ; R5 := "Container.Title"
148 [-]: LOADK     R6 41        ; R6 := 41.000000
149 [-]: LOADK     R7 K43       ; R7 := "Arial Unicode MS"
150 [-]: CALL      R3 5 1       ; R3(R4,R5,R6,R7)
151 [-]: GETGLOBAL R3 K16       ; R3 := 0xae91e43b
152 [-]: SELF      R3 R3 K41    ; R4 := R3; R3 := R3[0x5f56eeab]
153 [-]: LOADK     R5 K42       ; R5 := "Container.Title"
154 [-]: LOADK     R6 29        ; R6 := 29.000000
155 [-]: LOADK     R7 K44       ; R7 := ""
156 [-]: CALL      R3 5 1       ; R3(R4,R5,R6,R7)
157 [-]: CLOSURE   R3 0         ; R3 := closure(Function #20.1)
158 [-]: GETUPVAL  R0 U9        ; R0 := U9
159 [-]: GETGLOBAL R4 K45       ; R4 := 0x25312c9b
160 [-]: GETGLOBAL R5 K16       ; R5 := 0xae91e43b
161 [-]: LOADK     R6 K38       ; R6 := "_root"
162 [-]: LOADK     R7 0         ; R7 := 0.000000
163 [-]: NEWTABLE  R8 1 0       ; R8 := {}
164 [-]: MOVE      R9 R3        ; R9 := R3
165 [-]: SETLIST   R8 1 1       ; R8[(1-1)*FPF+i] := R(8+i), 1 <= i <= 1
166 [-]: NEWTABLE  R9 1 0       ; R9 := {}
167 [-]: LOADK     R10 1        ; R10 := 1.000000
168 [-]: SETLIST   R9 1 1       ; R9[(1-1)*FPF+i] := R(9+i), 1 <= i <= 1
169 [-]: GETUPVAL  R10 U10      ; R10 := U10
170 [-]: LOADK     R11 0        ; R11 := 0.000000
171 [-]: CLOSURE   R12 1        ; R12 := closure(Function #20.2)
172 [-]: GETUPVAL  R0 U11       ; R0 := U11
173 [-]: CALL      R4 9 1       ; R4(R5,R6,R7,R8,R9,R10,R11,R12)
174 [-]: GETUPVAL  R4 U12       ; R4 := U12
175 [-]: CALL      R4 1 1       ; R4()
176 [-]: GETGLOBAL R4 K3        ; R4 := 0x7b998233
177 [-]: GETGLOBAL R5 K4        ; R5 := _T
178 [-]: GETTABLE  R5 R5 K47    ; R5 := R5["IsScreenOpen"]
179 [-]: CALL      R4 2 2       ; R4 := R4(R5)
180 [-]: TEST      R4 1         ; if R4 then PC := 207
181 [-]: JMP       207          ; PC := 207
182 [-]: GETGLOBAL R4 K4        ; R4 := _T
183 [-]: GETTABLE  R4 R4 K48    ; R4 := R4[0x8e6a7b4e]
184 [-]: LOADK     R5 K49       ; R5 := "DarvoDeal"
185 [-]: CALL      R4 2 2       ; R4 := R4(R5)
186 [-]: TEST      R4 0         ; if not R4 then PC := 207
187 [-]: JMP       207          ; PC := 207
188 [-]: GETGLOBAL R4 K3        ; R4 := 0x7b998233
189 [-]: GETGLOBAL R5 K4        ; R5 := _T
190 [-]: GETTABLE  R5 R5 K50    ; R5 := R5["ChangeHubVisCounter"]
191 [-]: CALL      R4 2 2       ; R4 := R4(R5)
192 [-]: TEST      R4 1         ; if R4 then PC := 198
193 [-]: JMP       198          ; PC := 198
194 [-]: GETGLOBAL R4 K4        ; R4 := _T
195 [-]: GETTABLE  R4 R4 K51    ; R4 := R4[0x33cfa273]
196 [-]: LOADK     R5 1         ; R5 := 1.000000
197 [-]: CALL      R4 2 1       ; R4(R5)
198 [-]: GETGLOBAL R4 K3        ; R4 := 0x7b998233
199 [-]: GETGLOBAL R5 K4        ; R5 := _T
200 [-]: GETTABLE  R5 R5 K52    ; R5 := R5["ForceHideMiniMap"]
201 [-]: CALL      R4 2 2       ; R4 := R4(R5)
202 [-]: TEST      R4 1         ; if R4 then PC := 207
203 [-]: JMP       207          ; PC := 207
204 [-]: GETGLOBAL R4 K4        ; R4 := _T
205 [-]: GETTABLE  R4 R4 K53    ; R4 := R4[0x0981028c]
206 [-]: CALL      R4 1 1       ; R4()
207 [-]: GETUPVAL  R4 U13       ; R4 := U13
208 [-]: CALL      R4 1 1       ; R4()
209 [-]: GETUPVAL  R4 U14       ; R4 := U14
210 [-]: CALL      R4 1 1       ; R4()
211 [-]: LOADBOOL  R4 1 0       ; R4 := true
212 [-]: SETUPVAL  R4 U15       ; U82 := R15
213 [-]: RETURN    R0 1         ; return 


; Function #20.1:
;
; Name:            
; Defined at line: 861
; #Upvalues:       1
; #Parameters:     1
; Is_vararg:       0
; Max Stack Size:  4

  1 [-]: GETGLOBAL R1 K0        ; R1 := 0xae91e43b
  2 [-]: SELF      R1 R1 K1     ; R2 := R1; R1 := R1[0x58bec6d6]
  3 [-]: GETUPVAL  R3 U0        ; R3 := U0
  4 [-]: MUL       R3 R0 R3     ; R3 := R0 * R3
  5 [-]: CALL      R1 3 1       ; R1(R2,R3)
  6 [-]: RETURN    R0 1         ; return 


; Function #20.2:
;
; Name:            
; Defined at line: 865
; #Upvalues:       1
; #Parameters:     0
; Is_vararg:       0
; Max Stack Size:  2

  1 [-]: GETUPVAL  R0 U0        ; R0 := U0
  2 [-]: CALL      R0 1 1       ; R0()
  3 [-]: RETURN    R0 1         ; return 


; Function #21:
;
; Name:            
; Defined at line: 886
; #Upvalues:       4
; #Parameters:     0
; Is_vararg:       0
; Max Stack Size:  5

  1 [-]: GETUPVAL  R0 U0        ; R0 := U0
  2 [-]: TEST      R0 1         ; if R0 then PC := 5
  3 [-]: JMP       5            ; PC := 5
  4 [-]: RETURN    R0 1         ; return 
  5 [-]: GETUPVAL  R0 U1        ; R0 := U1
  6 [-]: GETTABLE  R0 R0 K0     ; R0 := R0["mCurrentElementIndex"]
  7 [-]: LOADBOOL  R1 1 0       ; R1 := true
  8 [-]: SETUPVAL  R1 U2        ; U82 := R2
  9 [-]: GETUPVAL  R1 U1        ; R1 := U1
 10 [-]: SELF      R1 R1 K1     ; R2 := R1; R1 := R1[0x7c09c373]
 11 [-]: LOADBOOL  R3 1 0       ; R3 := true
 12 [-]: LOADBOOL  R4 1 0       ; R4 := true
 13 [-]: CALL      R1 4 1       ; R1(R2,R3,R4)
 14 [-]: GETUPVAL  R1 U3        ; R1 := U3
 15 [-]: LOADBOOL  R2 1 0       ; R2 := true
 16 [-]: MOVE      R3 R0        ; R3 := R0
 17 [-]: CALL      R1 3 1       ; R1(R2,R3)
 18 [-]: RETURN    R0 1         ; return 


; Function #22:
;
; Name:            
; Defined at line: 897
; #Upvalues:       3
; #Parameters:     1
; Is_vararg:       0
; Max Stack Size:  6

  1 [-]: SETUPVAL  R0 U0        ; U82 := R0
  2 [-]: GETGLOBAL R1 K0        ; R1 := 0xae91e43b
  3 [-]: SELF      R1 R1 K1     ; R2 := R1; R1 := R1[0x42b04007]
  4 [-]: MOVE      R3 R0        ; R3 := R0
  5 [-]: LOADBOOL  R4 1 0       ; R4 := true
  6 [-]: CALL      R1 4 2       ; R1 := R1(R2,R3,R4)
  7 [-]: MOVE      R0 R1        ; R0 := R1
  8 [-]: GETGLOBAL R1 K0        ; R1 := 0xae91e43b
  9 [-]: SELF      R1 R1 K2     ; R2 := R1; R1 := R1[0xaade900e]
 10 [-]: LOADK     R3 K3        ; R3 := "Container.Underline"
 11 [-]: LOADK     R4 11        ; R4 := 11.000000
 12 [-]: GETUPVAL  R5 U1        ; R5 := U1
 13 [-]: TEST      R5 0         ; if not R5 then PC := 20
 14 [-]: JMP       20           ; PC := 20
 15 [-]: GETUPVAL  R5 U0        ; R5 := U0
 16 [-]: EQ        0 R5 K4      ; if R5 ~= nil then PC := 19
 17 [-]: JMP       19           ; PC := 19
 18 [-]: LOADBOOL  R5 0 1       ; R5 := false; PC := 19
 19 [-]: LOADBOOL  R5 1 0       ; R5 := true
 20 [-]: CALL      R1 5 1       ; R1(R2,R3,R4,R5)
 21 [-]: GETUPVAL  R1 U0        ; R1 := U0
 22 [-]: EQ        1 R1 K4      ; if R1 == nil then PC := 31
 23 [-]: JMP       31           ; PC := 31
 24 [-]: GETUPVAL  R1 U2        ; R1 := U2
 25 [-]: TEST      R1 0         ; if not R1 then PC := 31
 26 [-]: JMP       31           ; PC := 31
 27 [-]: GETGLOBAL R1 K5        ; R1 := 0x5f0788c4
 28 [-]: MOVE      R2 R0        ; R2 := R0
 29 [-]: CALL      R1 2 2       ; R1 := R1(R2)
 30 [-]: MOVE      R0 R1        ; R0 := R1
 31 [-]: GETGLOBAL R1 K0        ; R1 := 0xae91e43b
 32 [-]: SELF      R1 R1 K6     ; R2 := R1; R1 := R1[0x5f56eeab]
 33 [-]: LOADK     R3 K7        ; R3 := "Container.Title"
 34 [-]: LOADK     R4 29        ; R4 := 29.000000
 35 [-]: MOVE      R5 R0        ; R5 := R0
 36 [-]: CALL      R1 5 1       ; R1(R2,R3,R4,R5)
 37 [-]: RETURN    R0 1         ; return 


; Function #23:
;
; Name:            
; Defined at line: 907
; #Upvalues:       0
; #Parameters:     1
; Is_vararg:       0
; Max Stack Size:  6

  1 [-]: GETGLOBAL R1 K0        ; R1 := 0xae91e43b
  2 [-]: SELF      R1 R1 K1     ; R2 := R1; R1 := R1[0x5f56eeab]
  3 [-]: LOADK     R3 K2        ; R3 := "Container.Message"
  4 [-]: LOADK     R4 38        ; R4 := 38.000000
  5 [-]: LOADK     R5 K3        ; R5 := "center"
  6 [-]: CALL      R1 5 1       ; R1(R2,R3,R4,R5)
  7 [-]: GETGLOBAL R1 K0        ; R1 := 0xae91e43b
  8 [-]: SELF      R1 R1 K4     ; R2 := R1; R1 := R1[0x20b98db3]
  9 [-]: LOADK     R3 K5        ; R3 := "Container.Message.text"
 10 [-]: MOVE      R4 R0        ; R4 := R0
 11 [-]: CALL      R1 4 1       ; R1(R2,R3,R4)
 12 [-]: RETURN    R0 1         ; return 


; Function #24:
;
; Name:            
; Defined at line: 912
; #Upvalues:       1
; #Parameters:     1
; Is_vararg:       0
; Max Stack Size:  2

  1 [-]: SETUPVAL  R0 U0        ; U82 := R0
  2 [-]: RETURN    R0 1         ; return 


; Function #25:
;
; Name:            
; Defined at line: 916
; #Upvalues:       1
; #Parameters:     1
; Is_vararg:       0
; Max Stack Size:  2

  1 [-]: SETUPVAL  R0 U0        ; U82 := R0
  2 [-]: RETURN    R0 1         ; return 


; Function #26:
;
; Name:            
; Defined at line: 920
; #Upvalues:       3
; #Parameters:     0
; Is_vararg:       0
; Max Stack Size:  8

  1 [-]: GETGLOBAL R0 K0        ; R0 := 0xae91e43b
  2 [-]: SELF      R0 R0 K1     ; R1 := R0; R0 := R0[0x42b04007]
  3 [-]: LOADK     R2 K2        ; R2 := "/Lotus/Language/Menu/SearchPrompt"
  4 [-]: LOADBOOL  R3 0 0       ; R3 := false
  5 [-]: CALL      R0 4 2       ; R0 := R0(R1,R2,R3)
  6 [-]: GETGLOBAL R1 K3        ; R1 := 0x2d0fad09
  7 [-]: LOADK     R2 K4        ; R2 := "Lotus.Interface.Components.ThemedInputField"
  8 [-]: CALL      R1 2 2       ; R1 := R1(R2)
  9 [-]: GETTABLE  R2 R1 K5     ; R2 := R1[0xae6791ba]
 10 [-]: GETGLOBAL R3 K0        ; R3 := 0xae91e43b
 11 [-]: LOADK     R4 K6        ; R4 := "Container.SearchBox"
 12 [-]: LOADNIL   R5 R6        ; R5 := R6 := nil
 13 [-]: LOADK     R7 K7        ; R7 := "<MENU_LTHUMB>"
 14 [-]: CALL      R2 6 2       ; R2 := R2(R3,R4,R5,R6,R7)
 15 [-]: SETUPVAL  R2 U0        ; U82 := R0
 16 [-]: GETUPVAL  R2 U0        ; R2 := U0
 17 [-]: SELF      R2 R2 K8     ; R3 := R2; R2 := R2[0xf87811f6]
 18 [-]: GETUPVAL  R4 U0        ; R4 := U0
 19 [-]: GETTABLE  R4 R4 K9     ; R4 := R4["TYPE"]
 20 [-]: GETTABLE  R4 R4 K10    ; R4 := R4["PLAIN"]
 21 [-]: MOVE      R5 R0        ; R5 := R0
 22 [-]: MOVE      R6 R0        ; R6 := R0
 23 [-]: CALL      R2 5 1       ; R2(R3,R4,R5,R6)
 24 [-]: GETUPVAL  R2 U0        ; R2 := U0
 25 [-]: SETTABLE  R2 K11 K12   ; R2["mTextBuffer"] := 4.000000
 26 [-]: GETUPVAL  R2 U0        ; R2 := U0
 27 [-]: GETGLOBAL R3 K14       ; R3 := 0x0032441c
 28 [-]: GETTABLE  R3 R3 K15    ; R3 := R3["UITexture_Search"]
 29 [-]: SETTABLE  R2 K13 R3    ; R2["mAltButtonIcon"] := R3
 30 [-]: GETUPVAL  R2 U0        ; R2 := U0
 31 [-]: SETTABLE  R2 K16 K17   ; R2["mAltButtonVisible"] := true
 32 [-]: GETUPVAL  R2 U0        ; R2 := U0
 33 [-]: SETTABLE  R2 K18 K19   ; R2["mUnfocusedUnderlineColorOverride"] := nil
 34 [-]: GETUPVAL  R2 U0        ; R2 := U0
 35 [-]: GETUPVAL  R3 U0        ; R3 := U0
 36 [-]: GETTABLE  R3 R3 K21    ; R3 := R3["InputFieldTextChanged"]
 37 [-]: SETTABLE  R2 K20 R3    ; R2["BaseInputFieldTextChanged"] := R3
 38 [-]: GETUPVAL  R2 U0        ; R2 := U0
 39 [-]: CLOSURE   R3 0         ; R3 := closure(Function #26.1)
 40 [-]: GETUPVAL  R0 U1        ; R0 := U1
 41 [-]: GETUPVAL  R0 U2        ; R0 := U2
 42 [-]: SETTABLE  R2 K21 R3    ; R2["InputFieldTextChanged"] := R3
 43 [-]: GETUPVAL  R2 U0        ; R2 := U0
 44 [-]: GETUPVAL  R3 U0        ; R3 := U0
 45 [-]: GETTABLE  R3 R3 K23    ; R3 := R3["OnGamepadTransition"]
 46 [-]: SETTABLE  R2 K22 R3    ; R2["BaseOnGamepadTransition"] := R3
 47 [-]: GETUPVAL  R2 U0        ; R2 := U0
 48 [-]: CLOSURE   R3 1         ; R3 := closure(Function #26.2)
 49 [-]: SETTABLE  R2 K23 R3    ; R2["OnGamepadTransition"] := R3
 50 [-]: GETUPVAL  R2 U0        ; R2 := U0
 51 [-]: SELF      R2 R2 K24    ; R3 := R2; R2 := R2[0x6e6721d3]
 52 [-]: LOADK     R4 K2        ; R4 := "/Lotus/Language/Menu/SearchPrompt"
 53 [-]: CALL      R2 3 1       ; R2(R3,R4)
 54 [-]: RETURN    R0 1         ; return 


; Function #26.1:
;
; Name:            
; Defined at line: 931
; #Upvalues:       2
; #Parameters:     2
; Is_vararg:       0
; Max Stack Size:  8

  1 [-]: GETTABLE  R2 R0 K0     ; R2 := R0["mLabel"]
  2 [-]: SELF      R3 R0 K1     ; R4 := R0; R3 := R0[0x0ebd9e58]
  3 [-]: MOVE      R5 R1        ; R5 := R1
  4 [-]: CALL      R3 3 1       ; R3(R4,R5)
  5 [-]: GETTABLE  R3 R0 K0     ; R3 := R0["mLabel"]
  6 [-]: EQ        0 R3 K2      ; if R3 ~= "" then PC := 12
  7 [-]: JMP       12           ; PC := 12
  8 [-]: GETGLOBAL R3 K3        ; R3 := 0x0032441c
  9 [-]: GETTABLE  R3 R3 K4     ; R3 := R3["UITexture_Search"]
 10 [-]: TEST      R3 1         ; if R3 then PC := 14
 11 [-]: JMP       14           ; PC := 14
 12 [-]: GETGLOBAL R3 K3        ; R3 := 0x0032441c
 13 [-]: GETTABLE  R3 R3 K5     ; R3 := R3["UITexture_ClearSearch"]
 14 [-]: GETTABLE  R4 R0 K6     ; R4 := R0["mAltButtonicon"]
 15 [-]: EQ        1 R4 R3      ; if R4 == R3 then PC := 25
 16 [-]: JMP       25           ; PC := 25
 17 [-]: SETTABLE  R0 K6 R3     ; R0["mAltButtonicon"] := R3
 18 [-]: GETTABLE  R4 R0 K7     ; R4 := R0["mMovie"]
 19 [-]: SELF      R4 R4 K8     ; R5 := R4; R4 := R4[0x1cb415c1]
 20 [-]: GETTABLE  R6 R0 K9     ; R6 := R0["mClipName"]
 21 [-]: LOADK     R7 K10       ; R7 := ".BtnAlt"
 22 [-]: CONCAT    R6 R6 R7     ; R6 := R6 .. R7
 23 [-]: MOVE      R7 R3        ; R7 := R3
 24 [-]: CALL      R4 4 1       ; R4(R5,R6,R7)
 25 [-]: GETTABLE  R4 R0 K0     ; R4 := R0["mLabel"]
 26 [-]: EQ        1 R2 R4      ; if R2 == R4 then PC := 36
 27 [-]: JMP       36           ; PC := 36
 28 [-]: GETGLOBAL R4 K11       ; R4 := 0x7b998233
 29 [-]: GETUPVAL  R5 U0        ; R5 := U0
 30 [-]: CALL      R4 2 2       ; R4 := R4(R5)
 31 [-]: TEST      R4 1         ; if R4 then PC := 36
 32 [-]: JMP       36           ; PC := 36
 33 [-]: GETUPVAL  R4 U1        ; R4 := U1
 34 [-]: MOVE      R5 R2        ; R5 := R2
 35 [-]: CALL      R4 2 1       ; R4(R5)
 36 [-]: RETURN    R0 1         ; return 


; Function #26.2:
;
; Name:            
; Defined at line: 945
; #Upvalues:       0
; #Parameters:     1
; Is_vararg:       0
; Max Stack Size:  8

  1 [-]: SELF      R1 R0 K0     ; R2 := R0; R1 := R0[0x7e4d43ce]
  2 [-]: CALL      R1 2 1       ; R1(R2)
  3 [-]: GETGLOBAL R1 K1        ; R1 := 0x34291f5c
  4 [-]: GETTABLE  R1 R1 K2     ; R1 := R1[0x1467d5f4]
  5 [-]: CALL      R1 1 2       ; R1 := R1()
  6 [-]: NOT       R1 R1        ; R1 := not R1
  7 [-]: SETTABLE  R0 K3 R1     ; R0["mAltButtonVisible"] := R1
  8 [-]: GETGLOBAL R2 K4        ; R2 := 0xae91e43b
  9 [-]: SELF      R2 R2 K5     ; R3 := R2; R2 := R2[0xc0a3774b]
 10 [-]: GETTABLE  R4 R0 K6     ; R4 := R0["mClipName"]
 11 [-]: LOADK     R5 K7        ; R5 := "BtnAlt"
 12 [-]: LOADK     R6 11        ; R6 := 11.000000
 13 [-]: MOVE      R7 R1        ; R7 := R1
 14 [-]: CALL      R2 6 1       ; R2(R3,R4,R5,R6,R7)
 15 [-]: RETURN    R0 1         ; return 


; Function #27:
;
; Name:            
; Defined at line: 954
; #Upvalues:       1
; #Parameters:     0
; Is_vararg:       0
; Max Stack Size:  3

  1 [-]: GETUPVAL  R0 U0        ; R0 := U0
  2 [-]: TEST      R0 0         ; if not R0 then PC := 8
  3 [-]: JMP       8            ; PC := 8
  4 [-]: GETUPVAL  R0 U0        ; R0 := U0
  5 [-]: SELF      R0 R0 K0     ; R1 := R0; R0 := R0[0x043ef82f]
  6 [-]: LOADBOOL  R2 1 0       ; R2 := true
  7 [-]: CALL      R0 3 1       ; R0(R1,R2)
  8 [-]: RETURN    R0 1         ; return 


; Function #28:
;
; Name:            
; Defined at line: 960
; #Upvalues:       1
; #Parameters:     1
; Is_vararg:       0
; Max Stack Size:  2

  1 [-]: SETUPVAL  R0 U0        ; U82 := R0
  2 [-]: RETURN    R0 1         ; return 


; Function #29:
;
; Name:            
; Defined at line: 964
; #Upvalues:       1
; #Parameters:     0
; Is_vararg:       0
; Max Stack Size:  2

  1 [-]: GETUPVAL  R0 U0        ; R0 := U0
  2 [-]: CALL      R0 1 1       ; R0()
  3 [-]: RETURN    R0 1         ; return 


; Function #30:
;
; Name:            
; Defined at line: 968
; #Upvalues:       1
; #Parameters:     0
; Is_vararg:       0
; Max Stack Size:  2

  1 [-]: GETUPVAL  R0 U0        ; R0 := U0
  2 [-]: CALL      R0 1 1       ; R0()
  3 [-]: RETURN    R0 1         ; return 


; Function #31:
;
; Name:            
; Defined at line: 972
; #Upvalues:       1
; #Parameters:     0
; Is_vararg:       0
; Max Stack Size:  2

  1 [-]: GETUPVAL  R0 U0        ; R0 := U0
  2 [-]: CALL      R0 1 1       ; R0()
  3 [-]: RETURN    R0 1         ; return 


; Function #32:
;
; Name:            
; Defined at line: 976
; #Upvalues:       3
; #Parameters:     0
; Is_vararg:       0
; Max Stack Size:  4

  1 [-]: GETUPVAL  R0 U0        ; R0 := U0
  2 [-]: TEST      R0 1         ; if R0 then PC := 35
  3 [-]: JMP       35           ; PC := 35
  4 [-]: GETGLOBAL R0 K0        ; R0 := 0x7b998233
  5 [-]: GETUPVAL  R1 U1        ; R1 := U1
  6 [-]: CALL      R0 2 2       ; R0 := R0(R1)
  7 [-]: TEST      R0 1         ; if R0 then PC := 33
  8 [-]: JMP       33           ; PC := 33
  9 [-]: GETGLOBAL R0 K0        ; R0 := 0x7b998233
 10 [-]: GETUPVAL  R1 U2        ; R1 := U2
 11 [-]: CALL      R0 2 2       ; R0 := R0(R1)
 12 [-]: TEST      R0 1         ; if R0 then PC := 30
 13 [-]: JMP       30           ; PC := 30
 14 [-]: GETGLOBAL R0 K1        ; R0 := 0xae91e43b
 15 [-]: SELF      R0 R0 K2     ; R1 := R0; R0 := R0[0x40eb8ac7]
 16 [-]: CALL      R0 2 2       ; R0 := R0(R1)
 17 [-]: EQ        0 R0 K3      ; if R0 ~= "Label" then PC := 30
 18 [-]: JMP       30           ; PC := 30
 19 [-]: GETUPVAL  R0 U1        ; R0 := U1
 20 [-]: SELF      R0 R0 K4     ; R1 := R0; R0 := R0[0x5fbddc1a]
 21 [-]: CALL      R0 2 2       ; R0 := R0(R1)
 22 [-]: LT        0 K5 R0      ; if 0.000000 >= R0 then PC := 30
 23 [-]: JMP       30           ; PC := 30
 24 [-]: GETUPVAL  R0 U1        ; R0 := U1
 25 [-]: SELF      R0 R0 K6     ; R1 := R0; R0 := R0[0x77de11fe]
 26 [-]: LOADK     R2 1         ; R2 := 1.000000
 27 [-]: LOADBOOL  R3 1 0       ; R3 := true
 28 [-]: CALL      R0 4 1       ; R0(R1,R2,R3)
 29 [-]: JMP       33           ; PC := 33
 30 [-]: GETUPVAL  R0 U1        ; R0 := U1
 31 [-]: SELF      R0 R0 K7     ; R1 := R0; R0 := R0[0x8b24ce41]
 32 [-]: CALL      R0 2 1       ; R0(R1)
 33 [-]: LOADBOOL  R0 1 0       ; R0 := true
 34 [-]: RETURN    R0 2         ; return R0
 35 [-]: RETURN    R0 1         ; return 


; Function #33:
;
; Name:            
; Defined at line: 990
; #Upvalues:       1
; #Parameters:     2
; Is_vararg:       0
; Max Stack Size:  3

  1 [-]: GETUPVAL  R2 U0        ; R2 := U0
  2 [-]: CALL      R2 1 1       ; R2()
  3 [-]: RETURN    R0 1         ; return 


; Function #34:
;
; Name:            
; Defined at line: 994
; #Upvalues:       1
; #Parameters:     1
; Is_vararg:       0
; Max Stack Size:  5

  1 [-]: GETGLOBAL R1 K0        ; R1 := 0x7b998233
  2 [-]: GETUPVAL  R2 U0        ; R2 := U0
  3 [-]: CALL      R1 2 2       ; R1 := R1(R2)
  4 [-]: TEST      R1 1         ; if R1 then PC := 12
  5 [-]: JMP       12           ; PC := 12
  6 [-]: GETUPVAL  R1 U0        ; R1 := U0
  7 [-]: SELF      R1 R1 K1     ; R2 := R1; R1 := R1[0xdf42446e]
  8 [-]: GETGLOBAL R3 K2        ; R3 := 0x03f57322
  9 [-]: MOVE      R4 R0        ; R4 := R0
 10 [-]: CALL      R3 2 0       ; R3,... := R3(R4)
 11 [-]: CALL      R1 0 1       ; R1(R2,...)
 12 [-]: RETURN    R0 1         ; return 


; Function #35:
;
; Name:            
; Defined at line: 1000
; #Upvalues:       1
; #Parameters:     1
; Is_vararg:       0
; Max Stack Size:  5

  1 [-]: GETGLOBAL R1 K0        ; R1 := 0x7b998233
  2 [-]: GETUPVAL  R2 U0        ; R2 := U0
  3 [-]: CALL      R1 2 2       ; R1 := R1(R2)
  4 [-]: TEST      R1 1         ; if R1 then PC := 12
  5 [-]: JMP       12           ; PC := 12
  6 [-]: GETUPVAL  R1 U0        ; R1 := U0
  7 [-]: SELF      R1 R1 K1     ; R2 := R1; R1 := R1[0xbce5a201]
  8 [-]: GETGLOBAL R3 K2        ; R3 := 0x03f57322
  9 [-]: MOVE      R4 R0        ; R4 := R0
 10 [-]: CALL      R3 2 0       ; R3,... := R3(R4)
 11 [-]: CALL      R1 0 1       ; R1(R2,...)
 12 [-]: RETURN    R0 1         ; return 


; Function #36:
;
; Name:            
; Defined at line: 1006
; #Upvalues:       2
; #Parameters:     1
; Is_vararg:       0
; Max Stack Size:  5

  1 [-]: GETUPVAL  R1 U0        ; R1 := U0
  2 [-]: TEST      R1 1         ; if R1 then PC := 16
  3 [-]: JMP       16           ; PC := 16
  4 [-]: GETGLOBAL R1 K0        ; R1 := 0x7b998233
  5 [-]: GETUPVAL  R2 U1        ; R2 := U1
  6 [-]: CALL      R1 2 2       ; R1 := R1(R2)
  7 [-]: TEST      R1 1         ; if R1 then PC := 16
  8 [-]: JMP       16           ; PC := 16
  9 [-]: GETUPVAL  R1 U1        ; R1 := U1
 10 [-]: SELF      R1 R1 K1     ; R2 := R1; R1 := R1[0x070daa5a]
 11 [-]: GETGLOBAL R3 K2        ; R3 := 0x03f57322
 12 [-]: MOVE      R4 R0        ; R4 := R0
 13 [-]: CALL      R3 2 2       ; R3 := R3(R4)
 14 [-]: LOADBOOL  R4 1 0       ; R4 := true
 15 [-]: CALL      R1 4 1       ; R1(R2,R3,R4)
 16 [-]: RETURN    R0 1         ; return 


; Function #37:
;
; Name:            
; Defined at line: 1012
; #Upvalues:       3
; #Parameters:     0
; Is_vararg:       0
; Max Stack Size:  2

  1 [-]: GETUPVAL  R0 U0        ; R0 := U0
  2 [-]: TEST      R0 1         ; if R0 then PC := 7
  3 [-]: JMP       7            ; PC := 7
  4 [-]: GETUPVAL  R0 U1        ; R0 := U1
  5 [-]: TEST      R0 0         ; if not R0 then PC := 9
  6 [-]: JMP       9            ; PC := 9
  7 [-]: GETUPVAL  R0 U2        ; R0 := U2
  8 [-]: CALL      R0 1 1       ; R0()
  9 [-]: LOADBOOL  R0 1 0       ; R0 := true
 10 [-]: RETURN    R0 2         ; return R0
 11 [-]: RETURN    R0 1         ; return 


; Function #38:
;
; Name:            
; Defined at line: 1019
; #Upvalues:       1
; #Parameters:     0
; Is_vararg:       0
; Max Stack Size:  2

  1 [-]: GETUPVAL  R0 U0        ; R0 := U0
  2 [-]: GETTABLE  R0 R0 K0     ; R0 := R0[0x659d451f]
  3 [-]: GETGLOBAL R1 K1        ; R1 := 0x0032441c
  4 [-]: GETTABLE  R1 R1 K2     ; R1 := R1["UISound_Focus"]
  5 [-]: CALL      R0 2 1       ; R0(R1)
  6 [-]: RETURN    R0 1         ; return 


; Function #39:
;
; Name:            
; Defined at line: 1023
; #Upvalues:       2
; #Parameters:     2
; Is_vararg:       0
; Max Stack Size:  6

  1 [-]: GETUPVAL  R2 U0        ; R2 := U0
  2 [-]: TEST      R2 1         ; if R2 then PC := 19
  3 [-]: JMP       19           ; PC := 19
  4 [-]: GETGLOBAL R2 K0        ; R2 := 0x7b998233
  5 [-]: GETUPVAL  R3 U1        ; R3 := U1
  6 [-]: GETTABLE  R3 R3 K1     ; R3 := R3["mScrollBar"]
  7 [-]: CALL      R2 2 2       ; R2 := R2(R3)
  8 [-]: TEST      R2 1         ; if R2 then PC := 19
  9 [-]: JMP       19           ; PC := 19
 10 [-]: GETUPVAL  R2 U1        ; R2 := U1
 11 [-]: GETTABLE  R2 R2 K1     ; R2 := R2["mScrollBar"]
 12 [-]: SELF      R2 R2 K2     ; R3 := R2; R2 := R2[0x30456f58]
 13 [-]: GETGLOBAL R4 K3        ; R4 := 0x03f57322
 14 [-]: MOVE      R5 R1        ; R5 := R1
 15 [-]: CALL      R4 2 2       ; R4 := R4(R5)
 16 [-]: GETGLOBAL R5 K4        ; R5 := 0x0032441c
 17 [-]: GETTABLE  R5 R5 K5     ; R5 := R5["UISound_Scroll"]
 18 [-]: CALL      R2 4 1       ; R2(R3,R4,R5)
 19 [-]: RETURN    R0 1         ; return 


; Function #40:
;
; Name:            
; Defined at line: 1029
; #Upvalues:       3
; #Parameters:     0
; Is_vararg:       0
; Max Stack Size:  5

  1 [-]: GETGLOBAL R0 K0        ; R0 := 0x7b998233
  2 [-]: GETUPVAL  R1 U0        ; R1 := U0
  3 [-]: CALL      R0 2 2       ; R0 := R0(R1)
  4 [-]: TEST      R0 1         ; if R0 then PC := 36
  5 [-]: JMP       36           ; PC := 36
  6 [-]: GETGLOBAL R0 K0        ; R0 := 0x7b998233
  7 [-]: GETGLOBAL R1 K1        ; R1 := _T
  8 [-]: GETUPVAL  R2 U0        ; R2 := U0
  9 [-]: GETTABLE  R1 R1 R2     ; R1 := R1[R2]
 10 [-]: CALL      R0 2 2       ; R0 := R0(R1)
 11 [-]: TEST      R0 1         ; if R0 then PC := 36
 12 [-]: JMP       36           ; PC := 36
 13 [-]: GETUPVAL  R0 U1        ; R0 := U1
 14 [-]: TEST      R0 0         ; if not R0 then PC := 20
 15 [-]: JMP       20           ; PC := 20
 16 [-]: GETUPVAL  R0 U2        ; R0 := U2
 17 [-]: LEN       R0 R0        ; R0 := # R0
 18 [-]: EQ        0 R0 K2      ; if R0 ~= 0.000000 then PC := 36
 19 [-]: JMP       36           ; PC := 36
 20 [-]: GETGLOBAL R0 K3        ; R0 := 0xae91e43b
 21 [-]: SELF      R0 R0 K4     ; R1 := R0; R0 := R0[0x91a24e4b]
 22 [-]: LOADK     R2 K5        ; R2 := "_root"
 23 [-]: LOADK     R3 25        ; R3 := 25.000000
 24 [-]: CALL      R0 4 2       ; R0 := R0(R1,R2,R3)
 25 [-]: GETGLOBAL R1 K3        ; R1 := 0xae91e43b
 26 [-]: SELF      R1 R1 K4     ; R2 := R1; R1 := R1[0x91a24e4b]
 27 [-]: LOADK     R3 K5        ; R3 := "_root"
 28 [-]: LOADK     R4 26        ; R4 := 26.000000
 29 [-]: CALL      R1 4 2       ; R1 := R1(R2,R3,R4)
 30 [-]: GETGLOBAL R2 K1        ; R2 := _T
 31 [-]: GETUPVAL  R3 U0        ; R3 := U0
 32 [-]: GETTABLE  R2 R2 R3     ; R2 := R2[R3]
 33 [-]: MOVE      R3 R0        ; R3 := R0
 34 [-]: MOVE      R4 R1        ; R4 := R1
 35 [-]: CALL      R2 3 1       ; R2(R3,R4)
 36 [-]: RETURN    R0 1         ; return 


; Function #41:
;
; Name:            
; Defined at line: 1037
; #Upvalues:       1
; #Parameters:     0
; Is_vararg:       0
; Max Stack Size:  2

  1 [-]: GETUPVAL  R0 U0        ; R0 := U0
  2 [-]: RETURN    R0 2         ; return R0
  3 [-]: RETURN    R0 1         ; return 


; Function #42:
;
; Name:            
; Defined at line: 1041
; #Upvalues:       1
; #Parameters:     1
; Is_vararg:       0
; Max Stack Size:  3

  1 [-]: GETGLOBAL R1 K0        ; R1 := 0x03f57322
  2 [-]: MOVE      R2 R0        ; R2 := R0
  3 [-]: CALL      R1 2 2       ; R1 := R1(R2)
  4 [-]: SETUPVAL  R1 U0        ; U82 := R0
  5 [-]: RETURN    R0 1         ; return 


; Function #43:
;
; Name:            
; Defined at line: 1045
; #Upvalues:       0
; #Parameters:     1
; Is_vararg:       0
; Max Stack Size:  2

  1 [-]: RETURN    R0 1         ; return 


; Function #44:
;
; Name:            
; Defined at line: 1048
; #Upvalues:       1
; #Parameters:     1
; Is_vararg:       0
; Max Stack Size:  2

  1 [-]: EQ        1 R0 K0      ; if R0 == "true" then PC := 4
  2 [-]: JMP       4            ; PC := 4
  3 [-]: LOADBOOL  R1 0 1       ; R1 := false; PC := 4
  4 [-]: LOADBOOL  R1 1 0       ; R1 := true
  5 [-]: SETUPVAL  R1 U0        ; U82 := R0
  6 [-]: RETURN    R0 1         ; return 


; Function #45:
;
; Name:            
; Defined at line: 1052
; #Upvalues:       7
; #Parameters:     3
; Is_vararg:       0
; Max Stack Size:  15

  1 [-]: NEWTABLE  R3 0 2       ; R3 := {}
  2 [-]: SETTABLE  R3 K0 R0     ; R3["x"] := R0
  3 [-]: SETTABLE  R3 K1 R1     ; R3["y"] := R1
  4 [-]: SETUPVAL  R3 U0        ; U82 := R0
  5 [-]: EQ        0 R2 K2      ; if R2 ~= "true" then PC := 141
  6 [-]: JMP       141          ; PC := 141
  7 [-]: GETGLOBAL R3 K3        ; R3 := 0x5bced4c4
  8 [-]: GETTABLE  R3 R3 K4     ; R3 := R3[0xb62ecfe0]
  9 [-]: GETGLOBAL R4 K3        ; R4 := 0x5bced4c4
 10 [-]: GETTABLE  R4 R4 K5     ; R4 := R4[0xac1b386a]
 11 [-]: GETUPVAL  R5 U1        ; R5 := U1
 12 [-]: SELF      R5 R5 K6     ; R6 := R5; R5 := R5[0x5fbddc1a]
 13 [-]: CALL      R5 2 2       ; R5 := R5(R6)
 14 [-]: GETUPVAL  R6 U1        ; R6 := U1
 15 [-]: GETTABLE  R6 R6 K7     ; R6 := R6["mVisibleElements"]
 16 [-]: CALL      R4 3 2       ; R4 := R4(R5,R6)
 17 [-]: GETUPVAL  R5 U1        ; R5 := U1
 18 [-]: GETTABLE  R5 R5 K8     ; R5 := R5["mForcedVerticalSeparation"]
 19 [-]: MUL       R4 R4 R5     ; R4 := R4 * R5
 20 [-]: ADD       R4 K9 R4     ; R4 := 100.000000 + R4
 21 [-]: LOADK     R5 50        ; R5 := 50.000000
 22 [-]: CALL      R3 3 2       ; R3 := R3(R4,R5)
 23 [-]: GETUPVAL  R4 U2        ; R4 := U2
 24 [-]: GETUPVAL  R5 U3        ; R5 := U3
 25 [-]: GETTABLE  R5 R5 K10    ; R5 := R5[0x06d055f9]
 26 [-]: GETUPVAL  R6 U1        ; R6 := U1
 27 [-]: SELF      R6 R6 K6     ; R7 := R6; R6 := R6[0x5fbddc1a]
 28 [-]: CALL      R6 2 2       ; R6 := R6(R7)
 29 [-]: GETUPVAL  R7 U1        ; R7 := U1
 30 [-]: GETTABLE  R7 R7 K7     ; R7 := R7["mVisibleElements"]
 31 [-]: LT        1 R7 R6      ; if R7 < R6 then PC := 34
 32 [-]: JMP       34           ; PC := 34
 33 [-]: LOADBOOL  R6 0 1       ; R6 := false; PC := 34
 34 [-]: LOADBOOL  R6 1 0       ; R6 := true
 35 [-]: LOADK     R7 15        ; R7 := 15.000000
 36 [-]: LOADK     R8 0         ; R8 := 0.000000
 37 [-]: CALL      R5 4 2       ; R5 := R5(R6,R7,R8)
 38 [-]: ADD       R4 R4 R5     ; R4 := R4 + R5
 39 [-]: GETGLOBAL R5 K11       ; R5 := 0xae91e43b
 40 [-]: SELF      R5 R5 K12    ; R6 := R5; R5 := R5[0x91a24e4b]
 41 [-]: LOADK     R7 K13       ; R7 := "Container"
 42 [-]: LOADK     R8 5         ; R8 := 5.000000
 43 [-]: CALL      R5 4 2       ; R5 := R5(R6,R7,R8)
 44 [-]: GETGLOBAL R6 K11       ; R6 := 0xae91e43b
 45 [-]: SELF      R6 R6 K12    ; R7 := R6; R6 := R6[0x91a24e4b]
 46 [-]: LOADK     R8 K13       ; R8 := "Container"
 47 [-]: LOADK     R9 6         ; R9 := 6.000000
 48 [-]: CALL      R6 4 2       ; R6 := R6(R7,R8,R9)
 49 [-]: GETGLOBAL R7 K11       ; R7 := 0xae91e43b
 50 [-]: SELF      R7 R7 K12    ; R8 := R7; R7 := R7[0x91a24e4b]
 51 [-]: LOADK     R9 K14       ; R9 := "Container.BgFill"
 52 [-]: LOADK     R10 1        ; R10 := 1.000000
 53 [-]: CALL      R7 4 2       ; R7 := R7(R8,R9,R10)
 54 [-]: GETGLOBAL R8 K11       ; R8 := 0xae91e43b
 55 [-]: SELF      R8 R8 K12    ; R9 := R8; R8 := R8[0x91a24e4b]
 56 [-]: LOADK     R10 K15      ; R10 := "Container.Title"
 57 [-]: LOADK     R11 1        ; R11 := 1.000000
 58 [-]: CALL      R8 4 2       ; R8 := R8(R9,R10,R11)
 59 [-]: SUB       R7 R7 R8     ; R7 := R7 - R8
 60 [-]: ADD       R7 R7 K16    ; R7 := R7 + 6.000000
 61 [-]: DIV       R8 R6 K9     ; R8 := R6 / 100.000000
 62 [-]: MUL       R7 R7 R8     ; R7 := R7 * R8
 63 [-]: GETGLOBAL R8 K11       ; R8 := 0xae91e43b
 64 [-]: SELF      R8 R8 K12    ; R9 := R8; R8 := R8[0x91a24e4b]
 65 [-]: LOADK     R10 K13      ; R10 := "Container"
 66 [-]: LOADK     R11 12       ; R11 := 12.000000
 67 [-]: CALL      R8 4 2       ; R8 := R8(R9,R10,R11)
 68 [-]: DIV       R8 R8 K17    ; R8 := R8 / 2.000000
 69 [-]: DIV       R9 R5 K9     ; R9 := R5 / 100.000000
 70 [-]: MUL       R9 K18 R9    ; R9 := 14.000000 * R9
 71 [-]: SUB       R8 R8 R9     ; R8 := R8 - R9
 72 [-]: GETUPVAL  R9 U0        ; R9 := U0
 73 [-]: GETTABLE  R9 R9 K1     ; R9 := R9["y"]
 74 [-]: SUB       R9 R9 R7     ; R9 := R9 - R7
 75 [-]: SUB       R10 R3 K19   ; R10 := R3 - 68.000000
 76 [-]: DIV       R11 R6 K9    ; R11 := R6 / 100.000000
 77 [-]: MUL       R10 R10 R11  ; R10 := R10 * R11
 78 [-]: ADD       R9 R9 R10    ; R9 := R9 + R10
 79 [-]: GETGLOBAL R10 K11      ; R10 := 0xae91e43b
 80 [-]: SELF      R10 R10 K20  ; R11 := R10; R10 := R10[0x2cc9d281]
 81 [-]: CALL      R10 2 2      ; R10 := R10(R11)
 82 [-]: LT        0 R10 R9     ; if R10 >= R9 then PC := 93
 83 [-]: JMP       93           ; PC := 93
 84 [-]: GETUPVAL  R9 U0        ; R9 := U0
 85 [-]: GETTABLE  R9 R9 K1     ; R9 := R9["y"]
 86 [-]: SUB       R9 R9 R7     ; R9 := R9 - R7
 87 [-]: SUB       R10 R3 K21   ; R10 := R3 - 86.000000
 88 [-]: DIV       R11 R6 K9    ; R11 := R6 / 100.000000
 89 [-]: MUL       R10 R10 R11  ; R10 := R10 * R11
 90 [-]: SUB       R9 R9 R10    ; R9 := R9 - R10
 91 [-]: SETUPVAL  R9 U4        ; U82 := R4
 92 [-]: JMP       97           ; PC := 97
 93 [-]: GETUPVAL  R9 U0        ; R9 := U0
 94 [-]: GETTABLE  R9 R9 K1     ; R9 := R9["y"]
 95 [-]: SUB       R9 R9 R7     ; R9 := R9 - R7
 96 [-]: SETUPVAL  R9 U4        ; U82 := R4
 97 [-]: GETUPVAL  R9 U0        ; R9 := U0
 98 [-]: GETTABLE  R9 R9 K0     ; R9 := R9["x"]
 99 [-]: DIV       R10 R5 K9    ; R10 := R5 / 100.000000
100 [-]: MUL       R10 R8 R10   ; R10 := R8 * R10
101 [-]: ADD       R9 R9 R10    ; R9 := R9 + R10
102 [-]: GETGLOBAL R10 K11      ; R10 := 0xae91e43b
103 [-]: SELF      R10 R10 K22  ; R11 := R10; R10 := R10[0x091c120e]
104 [-]: CALL      R10 2 2      ; R10 := R10(R11)
105 [-]: LT        0 R10 R9     ; if R10 >= R9 then PC := 119
106 [-]: JMP       119          ; PC := 119
107 [-]: GETGLOBAL R9 K11       ; R9 := 0xae91e43b
108 [-]: SELF      R9 R9 K23    ; R10 := R9; R9 := R9[0x67bc869f]
109 [-]: LOADK     R11 K13      ; R11 := "Container"
110 [-]: LOADK     R12 0        ; R12 := 0.000000
111 [-]: GETUPVAL  R13 U0       ; R13 := U0
112 [-]: GETTABLE  R13 R13 K0   ; R13 := R13["x"]
113 [-]: ADD       R13 R13 R8   ; R13 := R13 + R8
114 [-]: DIV       R14 R5 K9    ; R14 := R5 / 100.000000
115 [-]: MUL       R14 R4 R14   ; R14 := R4 * R14
116 [-]: SUB       R13 R13 R14  ; R13 := R13 - R14
117 [-]: CALL      R9 5 1       ; R9(R10,R11,R12,R13)
118 [-]: JMP       127          ; PC := 127
119 [-]: GETGLOBAL R9 K11       ; R9 := 0xae91e43b
120 [-]: SELF      R9 R9 K23    ; R10 := R9; R9 := R9[0x67bc869f]
121 [-]: LOADK     R11 K13      ; R11 := "Container"
122 [-]: LOADK     R12 0        ; R12 := 0.000000
123 [-]: GETUPVAL  R13 U0       ; R13 := U0
124 [-]: GETTABLE  R13 R13 K0   ; R13 := R13["x"]
125 [-]: ADD       R13 R13 R8   ; R13 := R13 + R8
126 [-]: CALL      R9 5 1       ; R9(R10,R11,R12,R13)
127 [-]: GETGLOBAL R9 K11       ; R9 := 0xae91e43b
128 [-]: SELF      R9 R9 K23    ; R10 := R9; R9 := R9[0x67bc869f]
129 [-]: LOADK     R11 K13      ; R11 := "Container"
130 [-]: LOADK     R12 1        ; R12 := 1.000000
131 [-]: GETUPVAL  R13 U4       ; R13 := U4
132 [-]: CALL      R9 5 1       ; R9(R10,R11,R12,R13)
133 [-]: GETUPVAL  R9 U1        ; R9 := U1
134 [-]: SELF      R9 R9 K24    ; R10 := R9; R9 := R9[0x7c09c373]
135 [-]: LOADBOOL  R11 1 0      ; R11 := true
136 [-]: CALL      R9 3 1       ; R9(R10,R11)
137 [-]: GETUPVAL  R9 U5        ; R9 := U5
138 [-]: CALL      R9 1 1       ; R9()
139 [-]: LOADBOOL  R9 0 0       ; R9 := false
140 [-]: SETUPVAL  R9 U6        ; U82 := R6
141 [-]: RETURN    R0 1         ; return 


; Function #46:
;
; Name:            
; Defined at line: 1080
; #Upvalues:       1
; #Parameters:     1
; Is_vararg:       0
; Max Stack Size:  3

  1 [-]: GETGLOBAL R1 K0        ; R1 := 0x03f57322
  2 [-]: MOVE      R2 R0        ; R2 := R0
  3 [-]: CALL      R1 2 2       ; R1 := R1(R2)
  4 [-]: SETUPVAL  R1 U0        ; U82 := R0
  5 [-]: RETURN    R0 1         ; return 


; Function #47:
;
; Name:            
; Defined at line: 1084
; #Upvalues:       1
; #Parameters:     1
; Is_vararg:       0
; Max Stack Size:  2

  1 [-]: SETUPVAL  R0 U0        ; U82 := R0
  2 [-]: RETURN    R0 1         ; return 


; Function #48:
;
; Name:            
; Defined at line: 1088
; #Upvalues:       1
; #Parameters:     1
; Is_vararg:       0
; Max Stack Size:  2

  1 [-]: SETUPVAL  R0 U0        ; U82 := R0
  2 [-]: RETURN    R0 1         ; return 


; Function #49:
;
; Name:            
; Defined at line: 1092
; #Upvalues:       1
; #Parameters:     1
; Is_vararg:       0
; Max Stack Size:  2

  1 [-]: SETUPVAL  R0 U0        ; U82 := R0
  2 [-]: RETURN    R0 1         ; return 


; Function #50:
;
; Name:            
; Defined at line: 1096
; #Upvalues:       2
; #Parameters:     1
; Is_vararg:       0
; Max Stack Size:  2

  1 [-]: EQ        1 R0 K0      ; if R0 == "true" then PC := 4
  2 [-]: JMP       4            ; PC := 4
  3 [-]: LOADBOOL  R1 0 1       ; R1 := false; PC := 4
  4 [-]: LOADBOOL  R1 1 0       ; R1 := true
  5 [-]: SETUPVAL  R1 U0        ; U82 := R0
  6 [-]: GETUPVAL  R1 U1        ; R1 := U1
  7 [-]: CALL      R1 1 1       ; R1()
  8 [-]: RETURN    R0 1         ; return 


; Function #51:
;
; Name:            
; Defined at line: 1101
; #Upvalues:       0
; #Parameters:     1
; Is_vararg:       0
; Max Stack Size:  7

  1 [-]: GETGLOBAL R1 K0        ; R1 := 0xae91e43b
  2 [-]: SELF      R1 R1 K1     ; R2 := R1; R1 := R1[0x67bc869f]
  3 [-]: LOADK     R3 K2        ; R3 := "Container"
  4 [-]: LOADK     R4 5         ; R4 := 5.000000
  5 [-]: GETGLOBAL R5 K3        ; R5 := 0x03f57322
  6 [-]: MOVE      R6 R0        ; R6 := R0
  7 [-]: CALL      R5 2 0       ; R5,... := R5(R6)
  8 [-]: CALL      R1 0 1       ; R1(R2,...)
  9 [-]: GETGLOBAL R1 K0        ; R1 := 0xae91e43b
 10 [-]: SELF      R1 R1 K1     ; R2 := R1; R1 := R1[0x67bc869f]
 11 [-]: LOADK     R3 K2        ; R3 := "Container"
 12 [-]: LOADK     R4 6         ; R4 := 6.000000
 13 [-]: GETGLOBAL R5 K3        ; R5 := 0x03f57322
 14 [-]: MOVE      R6 R0        ; R6 := R0
 15 [-]: CALL      R5 2 0       ; R5,... := R5(R6)
 16 [-]: CALL      R1 0 1       ; R1(R2,...)
 17 [-]: RETURN    R0 1         ; return 


; Function #52:
;
; Name:            
; Defined at line: 1106
; #Upvalues:       1
; #Parameters:     1
; Is_vararg:       0
; Max Stack Size:  2

  1 [-]: SETUPVAL  R0 U0        ; U82 := R0
  2 [-]: RETURN    R0 1         ; return 


; Function #53:
;
; Name:            
; Defined at line: 1110
; #Upvalues:       1
; #Parameters:     1
; Is_vararg:       0
; Max Stack Size:  2

  1 [-]: SETUPVAL  R0 U0        ; U82 := R0
  2 [-]: RETURN    R0 1         ; return 


; Function #54:
;
; Name:            
; Defined at line: 1114
; #Upvalues:       1
; #Parameters:     1
; Is_vararg:       0
; Max Stack Size:  3

  1 [-]: GETGLOBAL R1 K0        ; R1 := 0xb009bbc6
  2 [-]: MOVE      R2 R0        ; R2 := R0
  3 [-]: CALL      R1 2 2       ; R1 := R1(R2)
  4 [-]: SETUPVAL  R1 U0        ; U82 := R0
  5 [-]: RETURN    R0 1         ; return 


; Function #55:
;
; Name:            
; Defined at line: 1118
; #Upvalues:       1
; #Parameters:     1
; Is_vararg:       0
; Max Stack Size:  3

  1 [-]: GETGLOBAL R1 K0        ; R1 := 0xb009bbc6
  2 [-]: MOVE      R2 R0        ; R2 := R0
  3 [-]: CALL      R1 2 2       ; R1 := R1(R2)
  4 [-]: SETUPVAL  R1 U0        ; U82 := R0
  5 [-]: RETURN    R0 1         ; return 


; Function #56:
;
; Name:            
; Defined at line: 1122
; #Upvalues:       3
; #Parameters:     3
; Is_vararg:       0
; Max Stack Size:  5

  1 [-]: GETGLOBAL R3 K0        ; R3 := 0x03f57322
  2 [-]: MOVE      R4 R0        ; R4 := R0
  3 [-]: CALL      R3 2 2       ; R3 := R3(R4)
  4 [-]: SETUPVAL  R3 U0        ; U82 := R0
  5 [-]: EQ        1 R1 K1      ; if R1 == nil then PC := 11
  6 [-]: JMP       11           ; PC := 11
  7 [-]: GETGLOBAL R3 K0        ; R3 := 0x03f57322
  8 [-]: MOVE      R4 R1        ; R4 := R1
  9 [-]: CALL      R3 2 2       ; R3 := R3(R4)
 10 [-]: SETUPVAL  R3 U1        ; U82 := R1
 11 [-]: EQ        1 R2 K1      ; if R2 == nil then PC := 17
 12 [-]: JMP       17           ; PC := 17
 13 [-]: GETGLOBAL R3 K0        ; R3 := 0x03f57322
 14 [-]: MOVE      R4 R1        ; R4 := R1
 15 [-]: CALL      R3 2 2       ; R3 := R3(R4)
 16 [-]: SETUPVAL  R3 U2        ; U82 := R2
 17 [-]: RETURN    R0 1         ; return 


; Function #57:
;
; Name:            
; Defined at line: 1132
; #Upvalues:       1
; #Parameters:     1
; Is_vararg:       0
; Max Stack Size:  2

  1 [-]: EQ        1 R0 K0      ; if R0 == "true" then PC := 4
  2 [-]: JMP       4            ; PC := 4
  3 [-]: LOADBOOL  R1 0 1       ; R1 := false; PC := 4
  4 [-]: LOADBOOL  R1 1 0       ; R1 := true
  5 [-]: SETUPVAL  R1 U0        ; U82 := R0
  6 [-]: RETURN    R0 1         ; return 


; Function #58:
;
; Name:            
; Defined at line: 1136
; #Upvalues:       2
; #Parameters:     2
; Is_vararg:       0
; Max Stack Size:  3

  1 [-]: EQ        1 R0 K0      ; if R0 == "true" then PC := 4
  2 [-]: JMP       4            ; PC := 4
  3 [-]: LOADBOOL  R2 0 1       ; R2 := false; PC := 4
  4 [-]: LOADBOOL  R2 1 0       ; R2 := true
  5 [-]: SETUPVAL  R2 U0        ; U82 := R0
  6 [-]: EQ        1 R1 K0      ; if R1 == "true" then PC := 10
  7 [-]: JMP       10           ; PC := 10
  8 [-]: GETUPVAL  R2 U0        ; R2 := U0
  9 [-]: SETUPVAL  R2 U1        ; U82 := R1
 10 [-]: RETURN    R0 1         ; return 


; Function #59:
;
; Name:            
; Defined at line: 1143
; #Upvalues:       3
; #Parameters:     1
; Is_vararg:       0
; Max Stack Size:  2

  1 [-]: GETUPVAL  R1 U0        ; R1 := U0
  2 [-]: TEST      R1 0         ; if not R1 then PC := 9
  3 [-]: JMP       9            ; PC := 9
  4 [-]: GETUPVAL  R1 U1        ; R1 := U1
  5 [-]: TEST      R1 1         ; if R1 then PC := 9
  6 [-]: JMP       9            ; PC := 9
  7 [-]: GETUPVAL  R1 U2        ; R1 := U2
  8 [-]: CALL      R1 1 1       ; R1()
  9 [-]: RETURN    R0 1         ; return 


; Function #60:
;
; Name:            
; Defined at line: 1149
; #Upvalues:       0
; #Parameters:     0
; Is_vararg:       0
; Max Stack Size:  2

  1 [-]: LOADBOOL  R0 1 0       ; R0 := true
  2 [-]: RETURN    R0 2         ; return R0
  3 [-]: RETURN    R0 1         ; return 


; Function #61:
;
; Name:            
; Defined at line: 1153
; #Upvalues:       1
; #Parameters:     0
; Is_vararg:       0
; Max Stack Size:  2

  1 [-]: GETUPVAL  R0 U0        ; R0 := U0
  2 [-]: CALL      R0 1 1       ; R0()
  3 [-]: RETURN    R0 1         ; return 


; Function #62:
;
; Name:            
; Defined at line: 1157
; #Upvalues:       2
; #Parameters:     1
; Is_vararg:       0
; Max Stack Size:  3

  1 [-]: LOADK     R1 0         ; R1 := 0.000000
  2 [-]: SETUPVAL  R1 U0        ; U82 := R0
  3 [-]: GETUPVAL  R1 U1        ; R1 := U1
  4 [-]: SELF      R1 R1 K0     ; R2 := R1; R1 := R1[0x71e9ac81]
  5 [-]: CALL      R1 2 1       ; R1(R2)
  6 [-]: RETURN    R0 1         ; return 


; Function #63:
;
; Name:            
; Defined at line: 1162
; #Upvalues:       0
; #Parameters:     0
; Is_vararg:       0
; Max Stack Size:  2

  1 [-]: RETURN    R0 1         ; return 


