; This file has been disassembled using luadec 2.0.2 by sztupy (modified by Reversive)

; Name:            
; Defined at line: 0
; #Upvalues:       0
; #Parameters:     0
; Is_vararg:       2
; Max Stack Size:  44

  1 [-]: GETGLOBAL R0 K0        ; R0 := 0x2d0fad09
  2 [-]: LOADK     R1 K1        ; R1 := "Lotus.Interface.LotusUtilities"
  3 [-]: CALL      R0 2 2       ; R0 := R0(R1)
  4 [-]: GETGLOBAL R1 K0        ; R1 := 0x2d0fad09
  5 [-]: LOADK     R2 K2        ; R2 := "EE.Interface.Utilities"
  6 [-]: CALL      R1 2 2       ; R1 := R1(R2)
  7 [-]: LOADNIL   R2 R2        ; R2 := nil
  8 [-]: LOADKB    R3 0 0       ; R3 := false
  9 [-]: LOADNIL   R4 R4        ; R4 := nil
 10 [-]: NEWTABLE  R5 0 0       ; R5 := {}
 11 [-]: LOADKB    R6 0 0       ; R6 := false
 12 [-]: CONST     R7 1         ; R7 := 1.000000
 13 [-]: LOADNIL   R8 R10       ; R8 := R9 := R10 := nil
 14 [-]: NEWTABLE  R11 0 0      ; R11 := {}
 15 [-]: NEWTABLE  R12 0 0      ; R12 := {}
 16 [-]: LOADNIL   R13 R13      ; R13 := nil
 17 [-]: LOADKB    R14 0 0      ; R14 := false
 18 [-]: NEWTABLE  R15 0 0      ; R15 := {}
 19 [-]: CONST     R16 1        ; R16 := 1.000000
 20 [-]: LOADKB    R17 0 0      ; R17 := false
 21 [-]: CONST     R18 0        ; R18 := 0.000000
 22 [-]: LOADK     R19 K3       ; R19 := 1.350000
 23 [-]: LOADKB    R20 0 0      ; R20 := false
 24 [-]: CLOSURE   R21 0        ; R21 := closure(Function #1)
 25 [-]: MOVE      R0 R7        ; R0 := R7
 26 [-]: CLOSURE   R22 1        ; R22 := closure(Function #2)
 27 [-]: MOVE      R0 R7        ; R0 := R7
 28 [-]: MOVE      R0 R20       ; R0 := R20
 29 [-]: MOVE      R0 R21       ; R0 := R21
 30 [-]: CLOSURE   R23 2        ; R23 := closure(Function #3)
 31 [-]: MOVE      R0 R21       ; R0 := R21
 32 [-]: SETGLOBAL R23 K4       ; onViewportSizeChanged := R23
 33 [-]: CLOSURE   R23 3        ; R23 := closure(Function #4)
 34 [-]: MOVE      R0 R3        ; R0 := R3
 35 [-]: MOVE      R0 R4        ; R0 := R4
 36 [-]: MOVE      R0 R6        ; R0 := R6
 37 [-]: MOVE      R0 R5        ; R0 := R5
 38 [-]: MOVE      R0 R8        ; R0 := R8
 39 [-]: MOVE      R0 R17       ; R0 := R17
 40 [-]: MOVE      R0 R18       ; R0 := R18
 41 [-]: MOVE      R0 R19       ; R0 := R19
 42 [-]: MOVE      R0 R16       ; R0 := R16
 43 [-]: MOVE      R0 R15       ; R0 := R15
 44 [-]: MOVE      R0 R0        ; R0 := R0
 45 [-]: MOVE      R0 R10       ; R0 := R10
 46 [-]: SETGLOBAL R23 K5       ; Update := R23
 47 [-]: CLOSURE   R23 4        ; R23 := closure(Function #5)
 48 [-]: MOVE      R0 R22       ; R0 := R22
 49 [-]: SETGLOBAL R23 K6       ; OnProfileSaved := R23
 50 [-]: CLOSURE   R23 5        ; R23 := closure(Function #6)
 51 [-]: MOVE      R0 R6        ; R0 := R6
 52 [-]: MOVE      R0 R5        ; R0 := R5
 53 [-]: CLOSURE   R24 6        ; R24 := closure(Function #7)
 54 [-]: MOVE      R0 R2        ; R0 := R2
 55 [-]: MOVE      R0 R20       ; R0 := R20
 56 [-]: SETGLOBAL R24 K7       ; Shutdown := R24
 57 [-]: CLOSURE   R24 7        ; R24 := closure(Function #8)
 58 [-]: MOVE      R0 R11       ; R0 := R11
 59 [-]: MOVE      R0 R12       ; R0 := R12
 60 [-]: CLOSURE   R25 8        ; R25 := closure(Function #9)
 61 [-]: MOVE      R0 R1        ; R0 := R1
 62 [-]: CLOSURE   R26 9        ; R26 := closure(Function #10)
 63 [-]: MOVE      R0 R9        ; R0 := R9
 64 [-]: CLOSURE   R27 10       ; R27 := closure(Function #11)
 65 [-]: CLOSURE   R28 11       ; R28 := closure(Function #12)
 66 [-]: CLOSURE   R29 12       ; R29 := closure(Function #13)
 67 [-]: MOVE      R0 R1        ; R0 := R1
 68 [-]: MOVE      R0 R15       ; R0 := R15
 69 [-]: CLOSURE   R30 13       ; R30 := closure(Function #14)
 70 [-]: MOVE      R0 R17       ; R0 := R17
 71 [-]: MOVE      R0 R16       ; R0 := R16
 72 [-]: MOVE      R0 R18       ; R0 := R18
 73 [-]: MOVE      R0 R15       ; R0 := R15
 74 [-]: MOVE      R0 R29       ; R0 := R29
 75 [-]: MOVE      R0 R2        ; R0 := R2
 76 [-]: MOVE      R0 R19       ; R0 := R19
 77 [-]: MOVE      R0 R1        ; R0 := R1
 78 [-]: CLOSURE   R31 14       ; R31 := closure(Function #15)
 79 [-]: CLOSURE   R32 15       ; R32 := closure(Function #16)
 80 [-]: CLOSURE   R33 16       ; R33 := closure(Function #17)
 81 [-]: CLOSURE   R34 17       ; R34 := closure(Function #18)
 82 [-]: CLOSURE   R35 18       ; R35 := closure(Function #19)
 83 [-]: MOVE      R0 R10       ; R0 := R10
 84 [-]: CLOSURE   R36 19       ; R36 := closure(Function #20)
 85 [-]: MOVE      R0 R10       ; R0 := R10
 86 [-]: MOVE      R0 R1        ; R0 := R1
 87 [-]: MOVE      R0 R2        ; R0 := R2
 88 [-]: MOVE      R0 R35       ; R0 := R35
 89 [-]: CLOSURE   R37 20       ; R37 := closure(Function #21)
 90 [-]: CLOSURE   R38 21       ; R38 := closure(Function #22)
 91 [-]: MOVE      R0 R13       ; R0 := R13
 92 [-]: MOVE      R0 R11       ; R0 := R11
 93 [-]: MOVE      R0 R12       ; R0 := R12
 94 [-]: MOVE      R0 R37       ; R0 := R37
 95 [-]: CLOSURE   R39 22       ; R39 := closure(Function #23)
 96 [-]: CLOSURE   R40 23       ; R40 := closure(Function #24)
 97 [-]: MOVE      R0 R14       ; R0 := R14
 98 [-]: CLOSURE   R41 24       ; R41 := closure(Function #25)
 99 [-]: MOVE      R0 R14       ; R0 := R14
100 [-]: CLOSURE   R42 25       ; R42 := closure(Function #26)
101 [-]: CLOSURE   R43 26       ; R43 := closure(Function #27)
102 [-]: MOVE      R0 R2        ; R0 := R2
103 [-]: MOVE      R0 R9        ; R0 := R9
104 [-]: MOVE      R0 R23       ; R0 := R23
105 [-]: MOVE      R0 R24       ; R0 := R24
106 [-]: MOVE      R0 R25       ; R0 := R25
107 [-]: MOVE      R0 R26       ; R0 := R26
108 [-]: MOVE      R0 R27       ; R0 := R27
109 [-]: MOVE      R0 R28       ; R0 := R28
110 [-]: MOVE      R0 R30       ; R0 := R30
111 [-]: MOVE      R0 R31       ; R0 := R31
112 [-]: MOVE      R0 R32       ; R0 := R32
113 [-]: MOVE      R0 R33       ; R0 := R33
114 [-]: MOVE      R0 R34       ; R0 := R34
115 [-]: MOVE      R0 R36       ; R0 := R36
116 [-]: MOVE      R0 R35       ; R0 := R35
117 [-]: MOVE      R0 R38       ; R0 := R38
118 [-]: MOVE      R0 R39       ; R0 := R39
119 [-]: MOVE      R0 R40       ; R0 := R40
120 [-]: MOVE      R0 R41       ; R0 := R41
121 [-]: MOVE      R0 R42       ; R0 := R42
122 [-]: MOVE      R0 R22       ; R0 := R22
123 [-]: MOVE      R0 R3        ; R0 := R3
124 [-]: SETGLOBAL R43 K8       ; Initialize := R43
125 [-]: CLOSURE   R43 27       ; R43 := closure(Function #28)
126 [-]: SETGLOBAL R43 K9       ; OnCountdownFrame := R43
127 [-]: RETURN    R0 1         ; return 


; Function #1:
;
; Name:            
; Defined at line: 30
; #Upvalues:       1
; #Parameters:     0
; Is_vararg:       0
; Max Stack Size:  9

  1 [-]: GETGLOBAL R0 K0        ; R0 := 0xae91e43b
  2 [-]: SELF      R0 R0 K1     ; R1 := R0; R0 := R0[0x6b837788]
  3 [-]: CALL      R0 2 2       ; R0 := R0(R1)
  4 [-]: GETGLOBAL R1 K0        ; R1 := 0xae91e43b
  5 [-]: SELF      R1 R1 K2     ; R2 := R1; R1 := R1[0xaf9fda9f]
  6 [-]: CALL      R1 2 2       ; R1 := R1(R2)
  7 [-]: GETGLOBAL R2 K0        ; R2 := 0xae91e43b
  8 [-]: SELF      R2 R2 K3     ; R3 := R2; R2 := R2[0x091c120e]
  9 [-]: CALL      R2 2 2       ; R2 := R2(R3)
 10 [-]: LT        1 R0 R2      ; if R0 < R2 then PC := 17
 11 [-]: JMP       17           ; PC := 17
 12 [-]: GETGLOBAL R2 K0        ; R2 := 0xae91e43b
 13 [-]: SELF      R2 R2 K4     ; R3 := R2; R2 := R2[0x2cc9d281]
 14 [-]: CALL      R2 2 2       ; R2 := R2(R3)
 15 [-]: LT        0 R1 R2      ; if R1 >= R2 then PC := 30
 16 [-]: JMP       30           ; PC := 30
 17 [-]: GETGLOBAL R2 K5        ; R2 := 0x34291f5c
 18 [-]: GETTABLE  R2 R2 K6     ; R2 := R2[0x056bfe8b]
 19 [-]: CALL      R2 1 2       ; R2 := R2()
 20 [-]: TEST      R2 1         ; if R2 then PC := 30
 21 [-]: JMP       30           ; PC := 30
 22 [-]: GETGLOBAL R2 K0        ; R2 := 0xae91e43b
 23 [-]: SELF      R2 R2 K3     ; R3 := R2; R2 := R2[0x091c120e]
 24 [-]: CALL      R2 2 2       ; R2 := R2(R3)
 25 [-]: MOVE      R0 R2        ; R0 := R2
 26 [-]: GETGLOBAL R2 K0        ; R2 := 0xae91e43b
 27 [-]: SELF      R2 R2 K4     ; R3 := R2; R2 := R2[0x2cc9d281]
 28 [-]: CALL      R2 2 2       ; R2 := R2(R3)
 29 [-]: MOVE      R1 R2        ; R1 := R2
 30 [-]: GETGLOBAL R2 K5        ; R2 := 0x34291f5c
 31 [-]: GETTABLE  R2 R2 K6     ; R2 := R2[0x056bfe8b]
 32 [-]: CALL      R2 1 2       ; R2 := R2()
 33 [-]: TEST      R2 0         ; if not R2 then PC := 43
 34 [-]: JMP       43           ; PC := 43
 35 [-]: GETGLOBAL R2 K0        ; R2 := 0xae91e43b
 36 [-]: SELF      R2 R2 K3     ; R3 := R2; R2 := R2[0x091c120e]
 37 [-]: CALL      R2 2 2       ; R2 := R2(R3)
 38 [-]: MOVE      R0 R2        ; R0 := R2
 39 [-]: GETGLOBAL R2 K0        ; R2 := 0xae91e43b
 40 [-]: SELF      R2 R2 K4     ; R3 := R2; R2 := R2[0x2cc9d281]
 41 [-]: CALL      R2 2 2       ; R2 := R2(R3)
 42 [-]: MOVE      R1 R2        ; R1 := R2
 43 [-]: GETGLOBAL R2 K0        ; R2 := 0xae91e43b
 44 [-]: SELF      R2 R2 K7     ; R3 := R2; R2 := R2[0x67bc869f]
 45 [-]: LOADK     R4 K8        ; R4 := "_root"
 46 [-]: CONST     R5 5         ; R5 := 5.000000
 47 [-]: GETUPVAL  R6 U0        ; R6 := U0
 48 [-]: MUL       R6 R6 K9     ; R6 := R6 * 100.000000
 49 [-]: CALL      R2 5 1       ; R2(R3,R4,R5,R6)
 50 [-]: GETGLOBAL R2 K0        ; R2 := 0xae91e43b
 51 [-]: SELF      R2 R2 K7     ; R3 := R2; R2 := R2[0x67bc869f]
 52 [-]: LOADK     R4 K8        ; R4 := "_root"
 53 [-]: CONST     R5 6         ; R5 := 6.000000
 54 [-]: GETUPVAL  R6 U0        ; R6 := U0
 55 [-]: MUL       R6 R6 K9     ; R6 := R6 * 100.000000
 56 [-]: CALL      R2 5 1       ; R2(R3,R4,R5,R6)
 57 [-]: GETUPVAL  R2 U0        ; R2 := U0
 58 [-]: SUB       R2 R2 K10    ; R2 := R2 - 1.000000
 59 [-]: MUL       R2 R2 R0     ; R2 := R2 * R0
 60 [-]: DIV       R2 R2 K11    ; R2 := R2 / 2.000000
 61 [-]: GETUPVAL  R3 U0        ; R3 := U0
 62 [-]: SUB       R3 R3 K10    ; R3 := R3 - 1.000000
 63 [-]: MUL       R3 R3 R1     ; R3 := R3 * R1
 64 [-]: DIV       R3 R3 K11    ; R3 := R3 / 2.000000
 65 [-]: GETGLOBAL R4 K0        ; R4 := 0xae91e43b
 66 [-]: SELF      R4 R4 K7     ; R5 := R4; R4 := R4[0x67bc869f]
 67 [-]: LOADK     R6 K8        ; R6 := "_root"
 68 [-]: CONST     R7 0         ; R7 := 0.000000
 69 [-]: UNM       R8 R2        ; R8 :=  R2
 70 [-]: CALL      R4 5 1       ; R4(R5,R6,R7,R8)
 71 [-]: GETGLOBAL R4 K0        ; R4 := 0xae91e43b
 72 [-]: SELF      R4 R4 K7     ; R5 := R4; R4 := R4[0x67bc869f]
 73 [-]: LOADK     R6 K8        ; R6 := "_root"
 74 [-]: CONST     R7 1         ; R7 := 1.000000
 75 [-]: UNM       R8 R3        ; R8 :=  R3
 76 [-]: CALL      R4 5 1       ; R4(R5,R6,R7,R8)
 77 [-]: GETGLOBAL R4 K12       ; R4 := 0x89326c93
 78 [-]: SELF      R4 R4 K13    ; R5 := R4; R4 := R4[0xb4364067]
 79 [-]: CALL      R4 2 2       ; R4 := R4(R5)
 80 [-]: GETGLOBAL R5 K14       ; R5 := 0x7b998233
 81 [-]: MOVE      R6 R4        ; R6 := R4
 82 [-]: CALL      R5 2 2       ; R5 := R5(R6)
 83 [-]: TEST      R5 1         ; if R5 then PC := 91
 84 [-]: JMP       91           ; PC := 91
 85 [-]: SELF      R5 R4 K15    ; R6 := R4; R5 := R4[0xfb1185f0]
 86 [-]: LOADK     R7 K16       ; R7 := 0.600000
 87 [-]: CALL      R5 3 1       ; R5(R6,R7)
 88 [-]: SELF      R5 R4 K17    ; R6 := R4; R5 := R4[0x79b9f121]
 89 [-]: LOADK     R7 K16       ; R7 := 0.600000
 90 [-]: CALL      R5 3 1       ; R5(R6,R7)
 91 [-]: RETURN    R0 1         ; return 


; Function #2:
;
; Name:            
; Defined at line: 59
; #Upvalues:       3
; #Parameters:     0
; Is_vararg:       0
; Max Stack Size:  7

  1 [-]: GETGLOBAL R0 K0        ; R0 := 0x76ea806b
  2 [-]: SELF      R0 R0 K1     ; R1 := R0; R0 := R0[0x3f3ae64c]
  3 [-]: CONST     R2 0         ; R2 := 0.000000
  4 [-]: CALL      R0 3 2       ; R0 := R0(R1,R2)
  5 [-]: GETGLOBAL R1 K2        ; R1 := 0x7b998233
  6 [-]: MOVE      R2 R0        ; R2 := R0
  7 [-]: CALL      R1 2 2       ; R1 := R1(R2)
  8 [-]: TEST      R1 0         ; if not R1 then PC := 11
  9 [-]: JMP       11           ; PC := 11
 10 [-]: RETURN    R0 1         ; return 
 11 [-]: SELF      R1 R0 K3     ; R2 := R0; R1 := R0[0x40e9c32b]
 12 [-]: CALL      R1 2 2       ; R1 := R1(R2)
 13 [-]: SELF      R2 R1 K4     ; R3 := R1; R2 := R1[0x21b2271b]
 14 [-]: CALL      R2 2 2       ; R2 := R2(R3)
 15 [-]: SETUPVAL  R2 U0        ; U82 := R0
 16 [-]: SELF      R2 R1 K5     ; R3 := R1; R2 := R1[0xe246126e]
 17 [-]: LOADK     R4 K6        ; R4 := "MELEE_CHANNEL"
 18 [-]: CALL      R2 3 2       ; R2 := R2(R3,R4)
 19 [-]: SETUPVAL  R2 U1        ; U82 := R1
 20 [-]: GETUPVAL  R2 U1        ; R2 := U1
 21 [-]: TEST      R2 0         ; if not R2 then PC := 28
 22 [-]: JMP       28           ; PC := 28
 23 [-]: SELF      R2 R1 K7     ; R3 := R1; R2 := R1[0x877d6616]
 24 [-]: LOADK     R4 K6        ; R4 := "MELEE_CHANNEL"
 25 [-]: LOADKB    R5 0 0       ; R5 := false
 26 [-]: LOADKB    R6 0 0       ; R6 := false
 27 [-]: CALL      R2 5 1       ; R2(R3,R4,R5,R6)
 28 [-]: GETUPVAL  R2 U2        ; R2 := U2
 29 [-]: CALL      R2 1 1       ; R2()
 30 [-]: RETURN    R0 1         ; return 


; Function #3:
;
; Name:            
; Defined at line: 77
; #Upvalues:       1
; #Parameters:     4
; Is_vararg:       0
; Max Stack Size:  5

  1 [-]: GETUPVAL  R4 U0        ; R4 := U0
  2 [-]: CALL      R4 1 1       ; R4()
  3 [-]: RETURN    R0 1         ; return 


; Function #4:
;
; Name:            
; Defined at line: 82
; #Upvalues:       12
; #Parameters:     0
; Is_vararg:       0
; Max Stack Size:  18

  1 [-]: GETGLOBAL R0 K0        ; R0 := 0x7b998233
  2 [-]: GETGLOBAL R1 K1        ; R1 := 0xae91e43b
  3 [-]: CALL      R0 2 2       ; R0 := R0(R1)
  4 [-]: TEST      R0 1         ; if R0 then PC := 9
  5 [-]: JMP       9            ; PC := 9
  6 [-]: GETUPVAL  R0 U0        ; R0 := U0
  7 [-]: TEST      R0 1         ; if R0 then PC := 10
  8 [-]: JMP       10           ; PC := 10
  9 [-]: RETURN    R0 1         ; return 
 10 [-]: GETGLOBAL R0 K2        ; R0 := 0x67652851
 11 [-]: CALL      R0 1 2       ; R0 := R0()
 12 [-]: GETGLOBAL R1 K1        ; R1 := 0xae91e43b
 13 [-]: SELF      R1 R1 K3     ; R2 := R1; R1 := R1[0x8a8c8d5a]
 14 [-]: MOVE      R3 R0        ; R3 := R0
 15 [-]: CALL      R1 3 1       ; R1(R2,R3)
 16 [-]: GETGLOBAL R1 K0        ; R1 := 0x7b998233
 17 [-]: GETUPVAL  R2 U1        ; R2 := U1
 18 [-]: CALL      R1 2 2       ; R1 := R1(R2)
 19 [-]: TEST      R1 0         ; if not R1 then PC := 87
 20 [-]: JMP       87           ; PC := 87
 21 [-]: GETGLOBAL R1 K0        ; R1 := 0x7b998233
 22 [-]: GETGLOBAL R2 K4        ; R2 := 0xbe190284
 23 [-]: CALL      R1 2 2       ; R1 := R1(R2)
 24 [-]: TEST      R1 1         ; if R1 then PC := 87
 25 [-]: JMP       87           ; PC := 87
 26 [-]: GETGLOBAL R1 K4        ; R1 := 0xbe190284
 27 [-]: SELF      R1 R1 K5     ; R2 := R1; R1 := R1[0x33307f92]
 28 [-]: CALL      R1 2 2       ; R1 := R1(R2)
 29 [-]: SETUPVAL  R1 U1        ; U82 := R1
 30 [-]: GETGLOBAL R1 K0        ; R1 := 0x7b998233
 31 [-]: GETUPVAL  R2 U1        ; R2 := U1
 32 [-]: CALL      R1 2 2       ; R1 := R1(R2)
 33 [-]: TEST      R1 1         ; if R1 then PC := 87
 34 [-]: JMP       87           ; PC := 87
 35 [-]: GETGLOBAL R1 K0        ; R1 := 0x7b998233
 36 [-]: GETGLOBAL R2 K6        ; R2 := _T
 37 [-]: GETTABLE  R2 R2 K7     ; R2 := R2["HideAbilityPanel"]
 38 [-]: CALL      R1 2 2       ; R1 := R1(R2)
 39 [-]: TEST      R1 1         ; if R1 then PC := 44
 40 [-]: JMP       44           ; PC := 44
 41 [-]: GETGLOBAL R1 K6        ; R1 := _T
 42 [-]: GETTABLE  R1 R1 K8     ; R1 := R1[0xf27431aa]
 43 [-]: CALL      R1 1 1       ; R1()
 44 [-]: GETUPVAL  R1 U1        ; R1 := U1
 45 [-]: SELF      R1 R1 K9     ; R2 := R1; R1 := R1[0xaade900e]
 46 [-]: LOADK     R3 K10       ; R3 := "MiniMapContainer.MissionCountdown"
 47 [-]: CONST     R4 11        ; R4 := 11.000000
 48 [-]: LOADKB    R5 0 0       ; R5 := false
 49 [-]: CALL      R1 5 1       ; R1(R2,R3,R4,R5)
 50 [-]: GETUPVAL  R1 U1        ; R1 := U1
 51 [-]: SELF      R1 R1 K11    ; R2 := R1; R1 := R1[0x5f56eeab]
 52 [-]: LOADK     R3 K12       ; R3 := "MiniMapContainer.MissionCountdown.Time"
 53 [-]: CONST     R4 29        ; R4 := 29.000000
 54 [-]: LOADK     R5 K13       ; R5 := ""
 55 [-]: CALL      R1 5 1       ; R1(R2,R3,R4,R5)
 56 [-]: GETUPVAL  R1 U1        ; R1 := U1
 57 [-]: SELF      R1 R1 K14    ; R2 := R1; R1 := R1[0x67bc869f]
 58 [-]: LOADK     R3 K15       ; R3 := "WeaponFrame"
 59 [-]: CONST     R4 10        ; R4 := 10.000000
 60 [-]: CONST     R5 0         ; R5 := 0.000000
 61 [-]: CALL      R1 5 1       ; R1(R2,R3,R4,R5)
 62 [-]: GETUPVAL  R1 U1        ; R1 := U1
 63 [-]: SELF      R1 R1 K14    ; R2 := R1; R1 := R1[0x67bc869f]
 64 [-]: LOADK     R3 K16       ; R3 := "HealthAndShield"
 65 [-]: CONST     R4 10        ; R4 := 10.000000
 66 [-]: CONST     R5 0         ; R5 := 0.000000
 67 [-]: CALL      R1 5 1       ; R1(R2,R3,R4,R5)
 68 [-]: GETUPVAL  R1 U1        ; R1 := U1
 69 [-]: SELF      R1 R1 K9     ; R2 := R1; R1 := R1[0xaade900e]
 70 [-]: LOADK     R3 K17       ; R3 := "reloadTimer"
 71 [-]: CONST     R4 11        ; R4 := 11.000000
 72 [-]: LOADKB    R5 0 0       ; R5 := false
 73 [-]: CALL      R1 5 1       ; R1(R2,R3,R4,R5)
 74 [-]: GETGLOBAL R1 K18       ; R1 := 0x3d106989
 75 [-]: LOADK     R2 K19       ; R2 := "ScopeDebug: Hide from HudLunaro"
 76 [-]: CALL      R1 2 1       ; R1(R2)
 77 [-]: GETUPVAL  R1 U1        ; R1 := U1
 78 [-]: SELF      R1 R1 K20    ; R2 := R1; R1 := R1[0xe4162eed]
 79 [-]: LOADK     R3 K21       ; R3 := "HideReticle"
 80 [-]: LOADK     R4 K13       ; R4 := ""
 81 [-]: CALL      R1 4 1       ; R1(R2,R3,R4)
 82 [-]: GETUPVAL  R1 U1        ; R1 := U1
 83 [-]: SELF      R1 R1 K20    ; R2 := R1; R1 := R1[0xe4162eed]
 84 [-]: LOADK     R3 K22       ; R3 := "HideAbilityDots"
 85 [-]: LOADK     R4 K13       ; R4 := ""
 86 [-]: CALL      R1 4 1       ; R1(R2,R3,R4)
 87 [-]: LOADKB    R1 1 0       ; R1 := true
 88 [-]: SETUPVAL  R1 U2        ; U82 := R2
 89 [-]: GETUPVAL  R1 U3        ; R1 := U3
 90 [-]: LEN       R1 R1        ; R1 := # R1
 91 [-]: LT        0 K23 R1     ; if 0.000000 >= R1 then PC := 123
 92 [-]: JMP       123          ; PC := 123
 93 [-]: CONST     R1 1         ; R1 := 1.000000
 94 [-]: GETUPVAL  R2 U3        ; R2 := U3
 95 [-]: LEN       R2 R2        ; R2 := # R2
 96 [-]: CONST     R3 1         ; R3 := 1.000000
 97 [-]: FORPREP   R1 120       ; R1 -= R3; PC := 120
 98 [-]: GETUPVAL  R5 U3        ; R5 := U3
 99 [-]: GETTABLE  R5 R5 R4     ; R5 := R5[R4]
100 [-]: GETTABLE  R5 R5 K24    ; R5 := R5[1.000000]
101 [-]: GETUPVAL  R6 U3        ; R6 := U3
102 [-]: GETTABLE  R6 R6 R4     ; R6 := R6[R4]
103 [-]: GETTABLE  R6 R6 K25    ; R6 := R6[2.000000]
104 [-]: GETUPVAL  R7 U3        ; R7 := U3
105 [-]: GETTABLE  R7 R7 R4     ; R7 := R7[R4]
106 [-]: GETTABLE  R7 R7 K26    ; R7 := R7[3.000000]
107 [-]: GETUPVAL  R8 U3        ; R8 := U3
108 [-]: GETTABLE  R8 R8 R4     ; R8 := R8[R4]
109 [-]: GETTABLE  R8 R8 K27    ; R8 := R8[4.000000]
110 [-]: GETUPVAL  R9 U3        ; R9 := U3
111 [-]: GETTABLE  R9 R9 R4     ; R9 := R9[R4]
112 [-]: GETTABLE  R9 R9 K28    ; R9 := R9[5.000000]
113 [-]: GETUPVAL  R10 U3       ; R10 := U3
114 [-]: GETTABLE  R10 R10 R4   ; R10 := R10[R4]
115 [-]: GETTABLE  R10 R10 K29  ; R10 := R10[6.000000]
116 [-]: GETUPVAL  R11 U3       ; R11 := U3
117 [-]: GETTABLE  R11 R11 R4   ; R11 := R11[R4]
118 [-]: GETTABLE  R11 R11 K30  ; R11 := R11[7.000000]
119 [-]: CALL      R5 7 1       ; R5(R6,R7,R8,R9,R10,R11)
120 [-]: FORLOOP   R1 98        ; R1 += R3; if R1 <= R2 then begin PC := 98; R4 := R1 end
121 [-]: NEWTABLE  R5 0 0       ; R5 := {}
122 [-]: SETUPVAL  R5 U3        ; U82 := R3
123 [-]: LOADKB    R5 0 0       ; R5 := false
124 [-]: SETUPVAL  R5 U2        ; U82 := R2
125 [-]: GETGLOBAL R5 K0        ; R5 := 0x7b998233
126 [-]: GETUPVAL  R6 U1        ; R6 := U1
127 [-]: CALL      R5 2 2       ; R5 := R5(R6)
128 [-]: TEST      R5 1         ; if R5 then PC := 145
129 [-]: JMP       145          ; PC := 145
130 [-]: GETUPVAL  R5 U1        ; R5 := U1
131 [-]: SELF      R5 R5 K31    ; R6 := R5; R5 := R5[0x91a24e4b]
132 [-]: LOADK     R7 K32       ; R7 := "_root"
133 [-]: CONST     R8 10        ; R8 := 10.000000
134 [-]: CALL      R5 4 2       ; R5 := R5(R6,R7,R8)
135 [-]: GETUPVAL  R6 U4        ; R6 := U4
136 [-]: EQ        1 R6 R5      ; if R6 == R5 then PC := 145
137 [-]: JMP       145          ; PC := 145
138 [-]: SETUPVAL  R5 U4        ; U82 := R4
139 [-]: GETGLOBAL R6 K1        ; R6 := 0xae91e43b
140 [-]: SELF      R6 R6 K14    ; R7 := R6; R6 := R6[0x67bc869f]
141 [-]: LOADK     R8 K32       ; R8 := "_root"
142 [-]: CONST     R9 10        ; R9 := 10.000000
143 [-]: MOVE      R10 R5       ; R10 := R5
144 [-]: CALL      R6 5 1       ; R6(R7,R8,R9,R10)
145 [-]: GETUPVAL  R6 U5        ; R6 := U5
146 [-]: TEST      R6 0         ; if not R6 then PC := 188
147 [-]: JMP       188          ; PC := 188
148 [-]: GETUPVAL  R6 U6        ; R6 := U6
149 [-]: ADD       R6 R6 R0     ; R6 := R6 + R0
150 [-]: SETUPVAL  R6 U6        ; U82 := R6
151 [-]: GETUPVAL  R6 U6        ; R6 := U6
152 [-]: GETUPVAL  R7 U7        ; R7 := U7
153 [-]: LT        0 R7 R6      ; if R7 >= R6 then PC := 173
154 [-]: JMP       173          ; PC := 173
155 [-]: CONST     R6 0         ; R6 := 0.000000
156 [-]: SETUPVAL  R6 U6        ; U82 := R6
157 [-]: GETUPVAL  R6 U8        ; R6 := U8
158 [-]: ADD       R6 R6 K24    ; R6 := R6 + 1.000000
159 [-]: SETUPVAL  R6 U8        ; U82 := R8
160 [-]: GETUPVAL  R6 U8        ; R6 := U8
161 [-]: GETUPVAL  R7 U9        ; R7 := U9
162 [-]: LEN       R7 R7        ; R7 := # R7
163 [-]: LT        0 R7 R6      ; if R7 >= R6 then PC := 173
164 [-]: JMP       173          ; PC := 173
165 [-]: CONST     R6 1         ; R6 := 1.000000
166 [-]: SETUPVAL  R6 U8        ; U82 := R8
167 [-]: GETUPVAL  R6 U9        ; R6 := U9
168 [-]: GETTABLE  R6 R6 K24    ; R6 := R6[1.000000]
169 [-]: NEWTABLE  R7 1 0       ; R7 := {}
170 [-]: MOVE      R8 R6        ; R8 := R6
171 [-]: SETLIST   R7 1 1       ; R7[(1-1)*FPF+i] := R(7+i), 1 <= i <= 1
172 [-]: SETUPVAL  R7 U9        ; U82 := R9
173 [-]: GETUPVAL  R7 U10       ; R7 := U10
174 [-]: GETTABLE  R7 R7 K33    ; R7 := R7[0x6be8b91b]
175 [-]: GETGLOBAL R8 K1        ; R8 := 0xae91e43b
176 [-]: GETUPVAL  R9 U9        ; R9 := U9
177 [-]: GETUPVAL  R10 U8       ; R10 := U8
178 [-]: GETTABLE  R9 R9 R10    ; R9 := R9[R10]
179 [-]: LOADK     R10 K34      ; R10 := "GoalCelebration.PlayerGoal.TextGradient"
180 [-]: LOADK     R11 K35      ; R11 := "GoalCelebration.PlayerGoal.Text"
181 [-]: LOADK     R12 K36      ; R12 := 12828308.000000
182 [-]: CONST     R13 16711680 ; R13 := 16711680.000000
183 [-]: LOADK     R14 K37      ; R14 := 8025934.000000
184 [-]: CONST     R15 -2       ; R15 := -2.000000
185 [-]: CONST     R16 0        ; R16 := 0.000000
186 [-]: CONST     R17 7        ; R17 := 7.000000
187 [-]: CALL      R7 11 1      ; R7(R8,R9,R10,R11,R12,R13,R14,R15,R16,R17)
188 [-]: GETUPVAL  R7 U11       ; R7 := U11
189 [-]: EQ        1 R7 K38     ; if R7 == nil then PC := 204
190 [-]: JMP       204          ; PC := 204
191 [-]: GETUPVAL  R7 U10       ; R7 := U10
192 [-]: GETTABLE  R7 R7 K33    ; R7 := R7[0x6be8b91b]
193 [-]: GETGLOBAL R8 K1        ; R8 := 0xae91e43b
194 [-]: GETUPVAL  R9 U11       ; R9 := U11
195 [-]: LOADK     R10 K39      ; R10 := "ClearZone.TextGradient"
196 [-]: LOADK     R11 K40      ; R11 := "ClearZone.Text"
197 [-]: LOADK     R12 K36      ; R12 := 12828308.000000
198 [-]: CONST     R13 16711680 ; R13 := 16711680.000000
199 [-]: LOADK     R14 K37      ; R14 := 8025934.000000
200 [-]: CONST     R15 2        ; R15 := 2.000000
201 [-]: CONST     R16 0        ; R16 := 0.000000
202 [-]: CONST     R17 3        ; R17 := 3.000000
203 [-]: CALL      R7 11 1      ; R7(R8,R9,R10,R11,R12,R13,R14,R15,R16,R17)
204 [-]: RETURN    R0 1         ; return 


; Function #5:
;
; Name:            
; Defined at line: 145
; #Upvalues:       1
; #Parameters:     0
; Is_vararg:       0
; Max Stack Size:  2

  1 [-]: GETUPVAL  R0 U0        ; R0 := U0
  2 [-]: CALL      R0 1 1       ; R0()
  3 [-]: RETURN    R0 1         ; return 


; Function #6:
;
; Name:            
; Defined at line: 149
; #Upvalues:       2
; #Parameters:     1
; Is_vararg:       3
; Max Stack Size:  7

  1 [-]: GETUPVAL  R2 U0        ; R2 := U0
  2 [-]: TEST      R2 0         ; if not R2 then PC := 8
  3 [-]: JMP       8            ; PC := 8
  4 [-]: MOVE      R2 R0        ; R2 := R0
  5 [-]: VARARG    R3 0         ; R3 := ...
  6 [-]: CALL      R2 0 1       ; R2(R3,...)
  7 [-]: JMP       16           ; PC := 16
  8 [-]: GETGLOBAL R2 K0        ; R2 := 0x33bdd652
  9 [-]: GETTABLE  R2 R2 K1     ; R2 := R2[0x23d5322f]
 10 [-]: GETUPVAL  R3 U1        ; R3 := U1
 11 [-]: NEWTABLE  R4 1 0       ; R4 := {}
 12 [-]: MOVE      R5 R0        ; R5 := R0
 13 [-]: VARARG    R6 0         ; R6 := ...
 14 [-]: SETLIST   R4 0 1       ; R4[(1-1)*FPF+i] := R(4+i), 1 <= i <= 0
 15 [-]: CALL      R2 3 1       ; R2(R3,R4)
 16 [-]: RETURN    R0 1         ; return 


; Function #7:
;
; Name:            
; Defined at line: 157
; #Upvalues:       2
; #Parameters:     0
; Is_vararg:       0
; Max Stack Size:  7

  1 [-]: GETGLOBAL R0 K0        ; R0 := _T
  2 [-]: SETTABLE  R0 K1 K2     ; R0["LunaroHud_SetTeamInfo"] := nil
  3 [-]: GETGLOBAL R0 K0        ; R0 := _T
  4 [-]: SETTABLE  R0 K3 K2     ; R0["LunaroHud_SetScoreVisible"] := nil
  5 [-]: GETGLOBAL R0 K0        ; R0 := _T
  6 [-]: SETTABLE  R0 K4 K2     ; R0["LunaroHud_SetScore"] := nil
  7 [-]: GETGLOBAL R0 K0        ; R0 := _T
  8 [-]: SETTABLE  R0 K5 K2     ; R0["LunaroHud_SetPeriodText"] := nil
  9 [-]: GETGLOBAL R0 K0        ; R0 := _T
 10 [-]: SETTABLE  R0 K6 K2     ; R0["LunaroHud_SetPeriodTextSpacing"] := nil
 11 [-]: GETGLOBAL R0 K0        ; R0 := _T
 12 [-]: SETTABLE  R0 K1 K2     ; R0["LunaroHud_SetTeamInfo"] := nil
 13 [-]: GETGLOBAL R0 K0        ; R0 := _T
 14 [-]: SETTABLE  R0 K7 K2     ; R0["LunaroHud_ShowScoreCelebration"] := nil
 15 [-]: GETGLOBAL R0 K0        ; R0 := _T
 16 [-]: SETTABLE  R0 K8 K2     ; R0["LunaroHud_ShowStartingCountdown"] := nil
 17 [-]: GETGLOBAL R0 K0        ; R0 := _T
 18 [-]: SETTABLE  R0 K9 K2     ; R0["LunaroHud_ShowHalftimeCountdown"] := nil
 19 [-]: GETGLOBAL R0 K0        ; R0 := _T
 20 [-]: SETTABLE  R0 K10 K2    ; R0["LunaroHud_StopCountdown"] := nil
 21 [-]: GETGLOBAL R0 K0        ; R0 := _T
 22 [-]: SETTABLE  R0 K11 K2    ; R0["LunaroHud_ResumeCountdown"] := nil
 23 [-]: GETGLOBAL R0 K0        ; R0 := _T
 24 [-]: SETTABLE  R0 K12 K2    ; R0["LunaroHud_ShowMessage"] := nil
 25 [-]: GETGLOBAL R0 K0        ; R0 := _T
 26 [-]: SETTABLE  R0 K13 K2    ; R0["LunaroHud_HideMessage"] := nil
 27 [-]: GETGLOBAL R0 K0        ; R0 := _T
 28 [-]: SETTABLE  R0 K14 K2    ; R0["LunaroHud_SetPossession"] := nil
 29 [-]: GETGLOBAL R0 K0        ; R0 := _T
 30 [-]: SETTABLE  R0 K15 K2    ; R0["LunaroHud_HideMissionTimer"] := nil
 31 [-]: GETGLOBAL R0 K0        ; R0 := _T
 32 [-]: SETTABLE  R0 K16 K2    ; R0["LunaroHud_SetPossessionReticle"] := nil
 33 [-]: GETGLOBAL R0 K0        ; R0 := _T
 34 [-]: SETTABLE  R0 K17 K2    ; R0["LunaroHud_GetPossessionReticle"] := nil
 35 [-]: GETGLOBAL R0 K0        ; R0 := _T
 36 [-]: SETTABLE  R0 K18 K2    ; R0["LunaroHud_SetTime"] := nil
 37 [-]: GETGLOBAL R0 K19       ; R0 := 0x7b998233
 38 [-]: GETGLOBAL R1 K0        ; R1 := _T
 39 [-]: GETTABLE  R1 R1 K20    ; R1 := R1["HUD_GetAnchorMgr"]
 40 [-]: CALL      R0 2 2       ; R0 := R0(R1)
 41 [-]: TEST      R0 1         ; if R0 then PC := 75
 42 [-]: JMP       75           ; PC := 75
 43 [-]: GETGLOBAL R0 K0        ; R0 := _T
 44 [-]: GETTABLE  R0 R0 K21    ; R0 := R0[0xf6b77431]
 45 [-]: CALL      R0 1 2       ; R0 := R0()
 46 [-]: SETUPVAL  R0 U0        ; U82 := R0
 47 [-]: GETUPVAL  R0 U0        ; R0 := U0
 48 [-]: EQ        1 R0 K2      ; if R0 == nil then PC := 75
 49 [-]: JMP       75           ; PC := 75
 50 [-]: GETUPVAL  R0 U0        ; R0 := U0
 51 [-]: SELF      R0 R0 K22    ; R1 := R0; R0 := R0[0x7f19c438]
 52 [-]: GETGLOBAL R2 K23       ; R2 := 0xae91e43b
 53 [-]: LOADK     R3 K24       ; R3 := "Scoreboard"
 54 [-]: CALL      R0 4 1       ; R0(R1,R2,R3)
 55 [-]: GETUPVAL  R0 U0        ; R0 := U0
 56 [-]: SELF      R0 R0 K22    ; R1 := R0; R0 := R0[0x7f19c438]
 57 [-]: GETGLOBAL R2 K23       ; R2 := 0xae91e43b
 58 [-]: LOADK     R3 K25       ; R3 := "Countdown"
 59 [-]: CALL      R0 4 1       ; R0(R1,R2,R3)
 60 [-]: GETUPVAL  R0 U0        ; R0 := U0
 61 [-]: SELF      R0 R0 K22    ; R1 := R0; R0 := R0[0x7f19c438]
 62 [-]: GETGLOBAL R2 K23       ; R2 := 0xae91e43b
 63 [-]: LOADK     R3 K26       ; R3 := "LunaroReticle"
 64 [-]: CALL      R0 4 1       ; R0(R1,R2,R3)
 65 [-]: GETUPVAL  R0 U0        ; R0 := U0
 66 [-]: SELF      R0 R0 K22    ; R1 := R0; R0 := R0[0x7f19c438]
 67 [-]: GETGLOBAL R2 K23       ; R2 := 0xae91e43b
 68 [-]: LOADK     R3 K27       ; R3 := "GoalScoreReplayTarget"
 69 [-]: CALL      R0 4 1       ; R0(R1,R2,R3)
 70 [-]: GETUPVAL  R0 U0        ; R0 := U0
 71 [-]: SELF      R0 R0 K22    ; R1 := R0; R0 := R0[0x7f19c438]
 72 [-]: GETGLOBAL R2 K23       ; R2 := 0xae91e43b
 73 [-]: LOADK     R3 K28       ; R3 := "ClearZone"
 74 [-]: CALL      R0 4 1       ; R0(R1,R2,R3)
 75 [-]: GETUPVAL  R0 U1        ; R0 := U1
 76 [-]: TEST      R0 0         ; if not R0 then PC := 94
 77 [-]: JMP       94           ; PC := 94
 78 [-]: GETGLOBAL R0 K29       ; R0 := 0x76ea806b
 79 [-]: SELF      R0 R0 K30    ; R1 := R0; R0 := R0[0x3f3ae64c]
 80 [-]: CONST     R2 0         ; R2 := 0.000000
 81 [-]: CALL      R0 3 2       ; R0 := R0(R1,R2)
 82 [-]: GETGLOBAL R1 K19       ; R1 := 0x7b998233
 83 [-]: MOVE      R2 R0        ; R2 := R0
 84 [-]: CALL      R1 2 2       ; R1 := R1(R2)
 85 [-]: TEST      R1 1         ; if R1 then PC := 94
 86 [-]: JMP       94           ; PC := 94
 87 [-]: SELF      R1 R0 K31    ; R2 := R0; R1 := R0[0x40e9c32b]
 88 [-]: CALL      R1 2 2       ; R1 := R1(R2)
 89 [-]: SELF      R2 R1 K32    ; R3 := R1; R2 := R1[0x877d6616]
 90 [-]: LOADK     R4 K33       ; R4 := "MELEE_CHANNEL"
 91 [-]: GETUPVAL  R5 U1        ; R5 := U1
 92 [-]: LOADKB    R6 0 0       ; R6 := false
 93 [-]: CALL      R2 5 1       ; R2(R3,R4,R5,R6)
 94 [-]: RETURN    R0 1         ; return 


; Function #8:
;
; Name:            
; Defined at line: 197
; #Upvalues:       2
; #Parameters:     4
; Is_vararg:       0
; Max Stack Size:  11

  1 [-]: LOADK     R4 K0        ; R4 := "Scoreboard.Score.Team"
  2 [-]: MOVE      R5 R0        ; R5 := R0
  3 [-]: LOADK     R6 K1        ; R6 := "Score"
  4 [-]: CONCAT    R4 R4 R6     ; R4 := R4 .. R5 .. R6
  5 [-]: GETGLOBAL R5 K2        ; R5 := 0xae91e43b
  6 [-]: SELF      R5 R5 K3     ; R6 := R5; R5 := R5[0x5f56eeab]
  7 [-]: MOVE      R7 R4        ; R7 := R4
  8 [-]: CONST     R8 29        ; R8 := 29.000000
  9 [-]: MOVE      R9 R1        ; R9 := R1
 10 [-]: CALL      R5 5 1       ; R5(R6,R7,R8,R9)
 11 [-]: GETGLOBAL R5 K2        ; R5 := 0xae91e43b
 12 [-]: SELF      R5 R5 K4     ; R6 := R5; R5 := R5[0x67bc869f]
 13 [-]: MOVE      R7 R4        ; R7 := R4
 14 [-]: CONST     R8 36        ; R8 := 36.000000
 15 [-]: MOVE      R9 R2        ; R9 := R2
 16 [-]: CALL      R5 5 1       ; R5(R6,R7,R8,R9)
 17 [-]: LOADK     R5 K5        ; R5 := "Scoreboard.Score.MiniEmblemTeam"
 18 [-]: MOVE      R6 R0        ; R6 := R0
 19 [-]: CONCAT    R5 R5 R6     ; R5 := R5 .. R6
 20 [-]: GETGLOBAL R6 K2        ; R6 := 0xae91e43b
 21 [-]: SELF      R6 R6 K6     ; R7 := R6; R6 := R6[0x1cb415c1]
 22 [-]: MOVE      R8 R5        ; R8 := R5
 23 [-]: MOVE      R9 R3        ; R9 := R3
 24 [-]: CALL      R6 4 1       ; R6(R7,R8,R9)
 25 [-]: GETGLOBAL R6 K2        ; R6 := 0xae91e43b
 26 [-]: SELF      R6 R6 K4     ; R7 := R6; R6 := R6[0x67bc869f]
 27 [-]: MOVE      R8 R5        ; R8 := R5
 28 [-]: CONST     R9 9         ; R9 := 9.000000
 29 [-]: MOVE      R10 R2       ; R10 := R2
 30 [-]: CALL      R6 5 1       ; R6(R7,R8,R9,R10)
 31 [-]: GETUPVAL  R6 U0        ; R6 := U0
 32 [-]: SETTABLE  R6 R0 R3     ; R6[R0] := R3
 33 [-]: GETUPVAL  R6 U1        ; R6 := U1
 34 [-]: SETTABLE  R6 R0 R2     ; R6[R0] := R2
 35 [-]: RETURN    R0 1         ; return 


; Function #9:
;
; Name:            
; Defined at line: 210
; #Upvalues:       1
; #Parameters:     3
; Is_vararg:       0
; Max Stack Size:  13

  1 [-]: EQ        0 R1 K0      ; if R1 ~= nil then PC := 4
  2 [-]: JMP       4            ; PC := 4
  3 [-]: LOADK     R1 K1        ; R1 := 0.450000
  4 [-]: EQ        0 R2 K0      ; if R2 ~= nil then PC := 7
  5 [-]: JMP       7            ; PC := 7
  6 [-]: CONST     R2 0         ; R2 := 0.000000
  7 [-]: GETGLOBAL R3 K2        ; R3 := 0x25312c9b
  8 [-]: GETGLOBAL R4 K3        ; R4 := 0xae91e43b
  9 [-]: LOADK     R5 K4        ; R5 := "Scoreboard"
 10 [-]: CONST     R6 0         ; R6 := 0.000000
 11 [-]: NEWTABLE  R7 1 0       ; R7 := {}
 12 [-]: CONST     R8 10        ; R8 := 10.000000
 13 [-]: SETLIST   R7 1 1       ; R7[(1-1)*FPF+i] := R(7+i), 1 <= i <= 1
 14 [-]: NEWTABLE  R8 0 0       ; R8 := {}
 15 [-]: GETUPVAL  R9 U0        ; R9 := U0
 16 [-]: GETTABLE  R9 R9 K6     ; R9 := R9[0x06d055f9]
 17 [-]: MOVE      R10 R0       ; R10 := R0
 18 [-]: CONST     R11 100      ; R11 := 100.000000
 19 [-]: CONST     R12 0        ; R12 := 0.000000
 20 [-]: CALL      R9 4 0       ; R9,... := R9(R10,R11,R12)
 21 [-]: SETLIST   R8 0 1       ; R8[(1-1)*FPF+i] := R(8+i), 1 <= i <= 0
 22 [-]: MOVE      R9 R1        ; R9 := R1
 23 [-]: MOVE      R10 R2       ; R10 := R2
 24 [-]: CALL      R3 8 1       ; R3(R4,R5,R6,R7,R8,R9,R10)
 25 [-]: RETURN    R0 1         ; return 


; Function #10:
;
; Name:            
; Defined at line: 220
; #Upvalues:       1
; #Parameters:     4
; Is_vararg:       0
; Max Stack Size:  10

  1 [-]: GETGLOBAL R4 K0        ; R4 := 0x7f5022cf
  2 [-]: GETTABLE  R4 R4 K1     ; R4 := R4[0xe8072ded]
  3 [-]: GETUPVAL  R5 U0        ; R5 := U0
  4 [-]: MOVE      R6 R2        ; R6 := R2
  5 [-]: MOVE      R7 R0        ; R7 := R0
  6 [-]: MOVE      R8 R3        ; R8 := R3
  7 [-]: MOVE      R9 R1        ; R9 := R1
  8 [-]: CALL      R4 6 2       ; R4 := R4(R5,R6,R7,R8,R9)
  9 [-]: GETGLOBAL R5 K2        ; R5 := 0xae91e43b
 10 [-]: SELF      R5 R5 K3     ; R6 := R5; R5 := R5[0x5f56eeab]
 11 [-]: LOADK     R7 K4        ; R7 := "Scoreboard.Score.Score"
 12 [-]: CONST     R8 29        ; R8 := 29.000000
 13 [-]: MOVE      R9 R4        ; R9 := R4
 14 [-]: CALL      R5 5 1       ; R5(R6,R7,R8,R9)
 15 [-]: RETURN    R0 1         ; return 


; Function #11:
;
; Name:            
; Defined at line: 225
; #Upvalues:       0
; #Parameters:     1
; Is_vararg:       0
; Max Stack Size:  6

  1 [-]: GETGLOBAL R1 K0        ; R1 := 0xae91e43b
  2 [-]: SELF      R1 R1 K1     ; R2 := R1; R1 := R1[0x5f56eeab]
  3 [-]: LOADK     R3 K2        ; R3 := "Scoreboard.PeriodText"
  4 [-]: CONST     R4 29        ; R4 := 29.000000
  5 [-]: MOVE      R5 R0        ; R5 := R0
  6 [-]: CALL      R1 5 1       ; R1(R2,R3,R4,R5)
  7 [-]: RETURN    R0 1         ; return 


; Function #12:
;
; Name:            
; Defined at line: 229
; #Upvalues:       0
; #Parameters:     1
; Is_vararg:       0
; Max Stack Size:  6

  1 [-]: GETGLOBAL R1 K0        ; R1 := 0xae91e43b
  2 [-]: SELF      R1 R1 K1     ; R2 := R1; R1 := R1[0x67bc869f]
  3 [-]: LOADK     R3 K2        ; R3 := "Scoreboard.PeriodText"
  4 [-]: CONST     R4 65        ; R4 := 65.000000
  5 [-]: MOVE      R5 R0        ; R5 := R0
  6 [-]: CALL      R1 5 1       ; R1(R2,R3,R4,R5)
  7 [-]: RETURN    R0 1         ; return 


; Function #13:
;
; Name:            
; Defined at line: 233
; #Upvalues:       2
; #Parameters:     0
; Is_vararg:       0
; Max Stack Size:  15

  1 [-]: GETUPVAL  R0 U0        ; R0 := U0
  2 [-]: GETTABLE  R0 R0 K0     ; R0 := R0[0x74a11ec6]
  3 [-]: GETGLOBAL R1 K1        ; R1 := 0xae91e43b
  4 [-]: SELF      R1 R1 K2     ; R2 := R1; R1 := R1[0x91a24e4b]
  5 [-]: LOADK     R3 K3        ; R3 := "GoalCelebration.TeamGoal.Text"
  6 [-]: CONST     R4 33        ; R4 := 33.000000
  7 [-]: CALL      R1 4 0       ; R1,... := R1(R2,R3,R4)
  8 [-]: CALL      R0 0 2       ; R0 := R0(R1,...)
  9 [-]: GETGLOBAL R1 K4        ; R1 := 0x5bced4c4
 10 [-]: GETTABLE  R1 R1 K5     ; R1 := R1[0xb62ecfe0]
 11 [-]: MOVE      R2 R0        ; R2 := R0
 12 [-]: CONST     R3 220       ; R3 := 220.000000
 13 [-]: CALL      R1 3 2       ; R1 := R1(R2,R3)
 14 [-]: MOVE      R0 R1        ; R0 := R1
 15 [-]: MOD       R1 R0 K6     ; R1 := R0 % 2.000000
 16 [-]: EQ        1 R1 K7      ; if R1 == 0.000000 then PC := 19
 17 [-]: JMP       19           ; PC := 19
 18 [-]: ADD       R0 R0 K8     ; R0 := R0 + 1.000000
 19 [-]: CONST     R1 32        ; R1 := 32.000000
 20 [-]: MOVE      R2 R0        ; R2 := R0
 21 [-]: GETGLOBAL R3 K1        ; R3 := 0xae91e43b
 22 [-]: SELF      R3 R3 K9     ; R4 := R3; R3 := R3[0x67bc869f]
 23 [-]: LOADK     R5 K10       ; R5 := "GoalCelebration.TeamGoal.TeamGoalPanelMiddle"
 24 [-]: CONST     R6 12        ; R6 := 12.000000
 25 [-]: MOVE      R7 R2        ; R7 := R2
 26 [-]: CALL      R3 5 1       ; R3(R4,R5,R6,R7)
 27 [-]: GETGLOBAL R3 K1        ; R3 := 0xae91e43b
 28 [-]: SELF      R3 R3 K9     ; R4 := R3; R3 := R3[0x67bc869f]
 29 [-]: LOADK     R5 K11       ; R5 := "GoalCelebration.TeamGoal.TeamGoalPanelLeft"
 30 [-]: CONST     R6 0         ; R6 := 0.000000
 31 [-]: UNM       R7 R1        ; R7 :=  R1
 32 [-]: MUL       R8 R2 K12    ; R8 := R2 * 0.500000
 33 [-]: SUB       R7 R7 R8     ; R7 := R7 - R8
 34 [-]: CALL      R3 5 1       ; R3(R4,R5,R6,R7)
 35 [-]: GETGLOBAL R3 K1        ; R3 := 0xae91e43b
 36 [-]: SELF      R3 R3 K9     ; R4 := R3; R3 := R3[0x67bc869f]
 37 [-]: LOADK     R5 K13       ; R5 := "GoalCelebration.TeamGoal.TeamGoalPanelRight"
 38 [-]: CONST     R6 0         ; R6 := 0.000000
 39 [-]: MUL       R7 R2 K12    ; R7 := R2 * 0.500000
 40 [-]: ADD       R7 R1 R7     ; R7 := R1 + R7
 41 [-]: CALL      R3 5 1       ; R3(R4,R5,R6,R7)
 42 [-]: CONST     R0 0         ; R0 := 0.000000
 43 [-]: GETGLOBAL R3 K14       ; R3 := 0xc8802016
 44 [-]: GETUPVAL  R4 U1        ; R4 := U1
 45 [-]: CALL      R3 2 4       ; R3,R4,R5 := R3(R4)
 46 [-]: JMP       64           ; PC := 64
 47 [-]: GETGLOBAL R8 K1        ; R8 := 0xae91e43b
 48 [-]: SELF      R8 R8 K15    ; R9 := R8; R8 := R8[0x5f56eeab]
 49 [-]: LOADK     R10 K16      ; R10 := "GoalCelebration.PlayerGoal.Text"
 50 [-]: CONST     R11 29       ; R11 := 29.000000
 51 [-]: MOVE      R12 R7       ; R12 := R7
 52 [-]: CALL      R8 5 1       ; R8(R9,R10,R11,R12)
 53 [-]: GETGLOBAL R8 K4        ; R8 := 0x5bced4c4
 54 [-]: GETTABLE  R8 R8 K5     ; R8 := R8[0xb62ecfe0]
 55 [-]: MOVE      R9 R0        ; R9 := R0
 56 [-]: GETGLOBAL R10 K1       ; R10 := 0xae91e43b
 57 [-]: SELF      R10 R10 K2   ; R11 := R10; R10 := R10[0x91a24e4b]
 58 [-]: LOADK     R12 K16      ; R12 := "GoalCelebration.PlayerGoal.Text"
 59 [-]: CONST     R13 33       ; R13 := 33.000000
 60 [-]: CALL      R10 4 2      ; R10 := R10(R11,R12,R13)
 61 [-]: ADD       R10 R10 K17  ; R10 := R10 + 20.000000
 62 [-]: CALL      R8 3 2       ; R8 := R8(R9,R10)
 63 [-]: MOVE      R0 R8        ; R0 := R8
 64 [-]: TFORLOOP  R3 2         ; R6,R7 :=  R3(R4,R5); if R6 ~= nil then begin PC = 47; R5 := R6 end
 65 [-]: JMP       47           ; PC := 47
 66 [-]: GETGLOBAL R8 K1        ; R8 := 0xae91e43b
 67 [-]: SELF      R8 R8 K2     ; R9 := R8; R8 := R8[0x91a24e4b]
 68 [-]: LOADK     R10 K16      ; R10 := "GoalCelebration.PlayerGoal.Text"
 69 [-]: CONST     R11 5        ; R11 := 5.000000
 70 [-]: CALL      R8 4 2       ; R8 := R8(R9,R10,R11)
 71 [-]: DIV       R8 R8 K18    ; R8 := R8 / 100.000000
 72 [-]: GETUPVAL  R9 U0        ; R9 := U0
 73 [-]: GETTABLE  R9 R9 K0     ; R9 := R9[0x74a11ec6]
 74 [-]: MUL       R10 R0 R8    ; R10 := R0 * R8
 75 [-]: CALL      R9 2 2       ; R9 := R9(R10)
 76 [-]: MOVE      R0 R9        ; R0 := R9
 77 [-]: GETGLOBAL R9 K4        ; R9 := 0x5bced4c4
 78 [-]: GETTABLE  R9 R9 K5     ; R9 := R9[0xb62ecfe0]
 79 [-]: MOVE      R10 R0       ; R10 := R0
 80 [-]: CONST     R11 360      ; R11 := 360.000000
 81 [-]: CALL      R9 3 2       ; R9 := R9(R10,R11)
 82 [-]: MOVE      R0 R9        ; R0 := R9
 83 [-]: MOD       R9 R0 K6     ; R9 := R0 % 2.000000
 84 [-]: EQ        1 R9 K7      ; if R9 == 0.000000 then PC := 87
 85 [-]: JMP       87           ; PC := 87
 86 [-]: ADD       R0 R0 K8     ; R0 := R0 + 1.000000
 87 [-]: CONST     R1 16        ; R1 := 16.000000
 88 [-]: MOVE      R2 R0        ; R2 := R0
 89 [-]: GETGLOBAL R9 K1        ; R9 := 0xae91e43b
 90 [-]: SELF      R9 R9 K9     ; R10 := R9; R9 := R9[0x67bc869f]
 91 [-]: LOADK     R11 K19      ; R11 := "GoalCelebration.PlayerGoal.GoalPanelMiddle"
 92 [-]: CONST     R12 12       ; R12 := 12.000000
 93 [-]: MOVE      R13 R2       ; R13 := R2
 94 [-]: CALL      R9 5 1       ; R9(R10,R11,R12,R13)
 95 [-]: GETGLOBAL R9 K1        ; R9 := 0xae91e43b
 96 [-]: SELF      R9 R9 K9     ; R10 := R9; R9 := R9[0x67bc869f]
 97 [-]: LOADK     R11 K20      ; R11 := "GoalCelebration.PlayerGoal.GoalPanelLeft"
 98 [-]: CONST     R12 0        ; R12 := 0.000000
 99 [-]: UNM       R13 R1       ; R13 :=  R1
100 [-]: MUL       R14 R2 K12   ; R14 := R2 * 0.500000
101 [-]: SUB       R13 R13 R14  ; R13 := R13 - R14
102 [-]: CALL      R9 5 1       ; R9(R10,R11,R12,R13)
103 [-]: GETGLOBAL R9 K1        ; R9 := 0xae91e43b
104 [-]: SELF      R9 R9 K9     ; R10 := R9; R9 := R9[0x67bc869f]
105 [-]: LOADK     R11 K21      ; R11 := "GoalCelebration.PlayerGoal.GoalPanelRight"
106 [-]: CONST     R12 0        ; R12 := 0.000000
107 [-]: MUL       R13 R2 K12   ; R13 := R2 * 0.500000
108 [-]: ADD       R13 R1 R13   ; R13 := R1 + R13
109 [-]: CALL      R9 5 1       ; R9(R10,R11,R12,R13)
110 [-]: RETURN    R0 1         ; return 


; Function #14:
;
; Name:            
; Defined at line: 265
; #Upvalues:       8
; #Parameters:     6
; Is_vararg:       0
; Max Stack Size:  18

  1 [-]: LOADKB    R6 1 0       ; R6 := true
  2 [-]: SETUPVAL  R6 U0        ; U82 := R0
  3 [-]: CONST     R6 1         ; R6 := 1.000000
  4 [-]: SETUPVAL  R6 U1        ; U82 := R1
  5 [-]: CONST     R6 0         ; R6 := 0.000000
  6 [-]: SETUPVAL  R6 U2        ; U82 := R2
  7 [-]: NEWTABLE  R6 0 0       ; R6 := {}
  8 [-]: SETUPVAL  R6 U3        ; U82 := R3
  9 [-]: GETUPVAL  R6 U3        ; R6 := U3
 10 [-]: SETTABLE  R6 K0 R0     ; R6[1.000000] := R0
 11 [-]: EQ        1 R1 K1      ; if R1 == nil then PC := 32
 12 [-]: JMP       32           ; PC := 32
 13 [-]: GETGLOBAL R6 K2        ; R6 := 0xae91e43b
 14 [-]: SELF      R6 R6 K3     ; R7 := R6; R6 := R6[0x5f56eeab]
 15 [-]: LOADK     R8 K4        ; R8 := "GoalCelebration.TeamGoal.Text"
 16 [-]: CONST     R9 29        ; R9 := 29.000000
 17 [-]: MOVE      R10 R1       ; R10 := R1
 18 [-]: CALL      R6 5 1       ; R6(R7,R8,R9,R10)
 19 [-]: GETGLOBAL R6 K2        ; R6 := 0xae91e43b
 20 [-]: SELF      R6 R6 K5     ; R7 := R6; R6 := R6[0x67bc869f]
 21 [-]: LOADK     R8 K4        ; R8 := "GoalCelebration.TeamGoal.Text"
 22 [-]: CONST     R9 36        ; R9 := 36.000000
 23 [-]: MOVE      R10 R3       ; R10 := R3
 24 [-]: CALL      R6 5 1       ; R6(R7,R8,R9,R10)
 25 [-]: GETGLOBAL R6 K2        ; R6 := 0xae91e43b
 26 [-]: SELF      R6 R6 K6     ; R7 := R6; R6 := R6[0xaade900e]
 27 [-]: LOADK     R8 K7        ; R8 := "GoalCelebration.TeamGoal"
 28 [-]: CONST     R9 11        ; R9 := 11.000000
 29 [-]: LOADKB    R10 1 0      ; R10 := true
 30 [-]: CALL      R6 5 1       ; R6(R7,R8,R9,R10)
 31 [-]: JMP       38           ; PC := 38
 32 [-]: GETGLOBAL R6 K2        ; R6 := 0xae91e43b
 33 [-]: SELF      R6 R6 K6     ; R7 := R6; R6 := R6[0xaade900e]
 34 [-]: LOADK     R8 K7        ; R8 := "GoalCelebration.TeamGoal"
 35 [-]: CONST     R9 11        ; R9 := 11.000000
 36 [-]: LOADKB    R10 0 0      ; R10 := false
 37 [-]: CALL      R6 5 1       ; R6(R7,R8,R9,R10)
 38 [-]: CONST     R6 0         ; R6 := 0.000000
 39 [-]: EQ        1 R1 K1      ; if R1 == nil then PC := 42
 40 [-]: JMP       42           ; PC := 42
 41 [-]: ADD       R6 R6 K0     ; R6 := R6 + 1.000000
 42 [-]: TEST      R4 0         ; if not R4 then PC := 54
 43 [-]: JMP       54           ; PC := 54
 44 [-]: ADD       R6 R6 K0     ; R6 := R6 + 1.000000
 45 [-]: GETGLOBAL R7 K8        ; R7 := 0x33bdd652
 46 [-]: GETTABLE  R7 R7 K9     ; R7 := R7[0x23d5322f]
 47 [-]: GETUPVAL  R8 U3        ; R8 := U3
 48 [-]: GETGLOBAL R9 K2        ; R9 := 0xae91e43b
 49 [-]: SELF      R9 R9 K10    ; R10 := R9; R9 := R9[0x42b04007]
 50 [-]: LOADK     R11 K11      ; R11 := "/Lotus/Language/Menu/LunaroCheckingScore"
 51 [-]: LOADKB    R12 0 0      ; R12 := false
 52 [-]: CALL      R9 4 0       ; R9,... := R9(R10,R11,R12)
 53 [-]: CALL      R7 0 1       ; R7(R8,...)
 54 [-]: TEST      R5 0         ; if not R5 then PC := 66
 55 [-]: JMP       66           ; PC := 66
 56 [-]: ADD       R6 R6 K0     ; R6 := R6 + 1.000000
 57 [-]: GETGLOBAL R7 K8        ; R7 := 0x33bdd652
 58 [-]: GETTABLE  R7 R7 K9     ; R7 := R7[0x23d5322f]
 59 [-]: GETUPVAL  R8 U3        ; R8 := U3
 60 [-]: GETGLOBAL R9 K2        ; R9 := 0xae91e43b
 61 [-]: SELF      R9 R9 K10    ; R10 := R9; R9 := R9[0x42b04007]
 62 [-]: LOADK     R11 K12      ; R11 := "/Lotus/Language/Menu/LunaroLongRangeScore"
 63 [-]: LOADKB    R12 0 0      ; R12 := false
 64 [-]: CALL      R9 4 0       ; R9,... := R9(R10,R11,R12)
 65 [-]: CALL      R7 0 1       ; R7(R8,...)
 66 [-]: GETGLOBAL R7 K2        ; R7 := 0xae91e43b
 67 [-]: SELF      R7 R7 K6     ; R8 := R7; R7 := R7[0xaade900e]
 68 [-]: LOADK     R9 K13       ; R9 := "GoalCelebration.ReplaySubtitle"
 69 [-]: CONST     R10 11       ; R10 := 11.000000
 70 [-]: LT        1 K14 R6     ; if 0.000000 < R6 then PC := 73
 71 [-]: JMP       73           ; PC := 73
 72 [-]: LOADKB    R11 0 1      ; R11 := false; PC := 73
 73 [-]: LOADKB    R11 1 0      ; R11 := true
 74 [-]: CALL      R7 5 1       ; R7(R8,R9,R10,R11)
 75 [-]: LT        0 K14 R6     ; if 0.000000 >= R6 then PC := 98
 76 [-]: JMP       98           ; PC := 98
 77 [-]: GETGLOBAL R7 K2        ; R7 := 0xae91e43b
 78 [-]: SELF      R7 R7 K5     ; R8 := R7; R7 := R7[0x67bc869f]
 79 [-]: LOADK     R9 K13       ; R9 := "GoalCelebration.ReplaySubtitle"
 80 [-]: CONST     R10 1        ; R10 := 1.000000
 81 [-]: CONST     R11 80       ; R11 := 80.000000
 82 [-]: CALL      R7 5 1       ; R7(R8,R9,R10,R11)
 83 [-]: EQ        0 R6 K0      ; if R6 ~= 1.000000 then PC := 91
 84 [-]: JMP       91           ; PC := 91
 85 [-]: GETGLOBAL R7 K2        ; R7 := 0xae91e43b
 86 [-]: SELF      R7 R7 K15    ; R8 := R7; R7 := R7[0x20b98db3]
 87 [-]: LOADK     R9 K16       ; R9 := "GoalCelebration.ReplaySubtitle.Text.text"
 88 [-]: LOADK     R10 K17      ; R10 := "/Lotus/Language/Menu/LunaroPointScored"
 89 [-]: CALL      R7 4 1       ; R7(R8,R9,R10)
 90 [-]: JMP       98           ; PC := 98
 91 [-]: GETGLOBAL R7 K2        ; R7 := 0xae91e43b
 92 [-]: SELF      R7 R7 K15    ; R8 := R7; R7 := R7[0x20b98db3]
 93 [-]: LOADK     R9 K16       ; R9 := "GoalCelebration.ReplaySubtitle.Text.text"
 94 [-]: LOADK     R10 K18      ; R10 := "/Lotus/Language/Menu/LunaroPointsScored"
 95 [-]: NEWTABLE  R11 0 1      ; R11 := {}
 96 [-]: SETTABLE  R11 K19 R6   ; R11["POINTS"] := R6
 97 [-]: CALL      R7 5 1       ; R7(R8,R9,R10,R11)
 98 [-]: GETUPVAL  R7 U4        ; R7 := U4
 99 [-]: CALL      R7 1 1       ; R7()
100 [-]: GETGLOBAL R7 K2        ; R7 := 0xae91e43b
101 [-]: SELF      R7 R7 K5     ; R8 := R7; R7 := R7[0x67bc869f]
102 [-]: LOADK     R9 K20       ; R9 := "GoalCelebration.PlayerGoal"
103 [-]: CONST     R10 5        ; R10 := 5.000000
104 [-]: CONST     R11 100      ; R11 := 100.000000
105 [-]: CALL      R7 5 1       ; R7(R8,R9,R10,R11)
106 [-]: GETGLOBAL R7 K2        ; R7 := 0xae91e43b
107 [-]: SELF      R7 R7 K5     ; R8 := R7; R7 := R7[0x67bc869f]
108 [-]: LOADK     R9 K20       ; R9 := "GoalCelebration.PlayerGoal"
109 [-]: CONST     R10 6        ; R10 := 6.000000
110 [-]: CONST     R11 100      ; R11 := 100.000000
111 [-]: CALL      R7 5 1       ; R7(R8,R9,R10,R11)
112 [-]: LOADK     R7 K21       ; R7 := "GoalCelebration.TeamEmblem.TeamEmblemIcon"
113 [-]: EQ        1 R2 K1      ; if R2 == nil then PC := 127
114 [-]: JMP       127          ; PC := 127
115 [-]: GETGLOBAL R8 K2        ; R8 := 0xae91e43b
116 [-]: SELF      R8 R8 K22    ; R9 := R8; R8 := R8[0x1cb415c1]
117 [-]: MOVE      R10 R7       ; R10 := R7
118 [-]: MOVE      R11 R2       ; R11 := R2
119 [-]: CALL      R8 4 1       ; R8(R9,R10,R11)
120 [-]: GETGLOBAL R8 K2        ; R8 := 0xae91e43b
121 [-]: SELF      R8 R8 K6     ; R9 := R8; R8 := R8[0xaade900e]
122 [-]: MOVE      R10 R7       ; R10 := R7
123 [-]: CONST     R11 11       ; R11 := 11.000000
124 [-]: LOADKB    R12 1 0      ; R12 := true
125 [-]: CALL      R8 5 1       ; R8(R9,R10,R11,R12)
126 [-]: JMP       133          ; PC := 133
127 [-]: GETGLOBAL R8 K2        ; R8 := 0xae91e43b
128 [-]: SELF      R8 R8 K6     ; R9 := R8; R8 := R8[0xaade900e]
129 [-]: MOVE      R10 R7       ; R10 := R7
130 [-]: CONST     R11 11       ; R11 := 11.000000
131 [-]: LOADKB    R12 0 0      ; R12 := false
132 [-]: CALL      R8 5 1       ; R8(R9,R10,R11,R12)
133 [-]: GETUPVAL  R8 U5        ; R8 := U5
134 [-]: SELF      R8 R8 K23    ; R9 := R8; R8 := R8[0x2de3d774]
135 [-]: LOADK     R10 K24      ; R10 := "Countdown"
136 [-]: CALL      R8 3 2       ; R8 := R8(R9,R10)
137 [-]: GETGLOBAL R9 K2        ; R9 := 0xae91e43b
138 [-]: SELF      R9 R9 K5     ; R10 := R9; R9 := R9[0x67bc869f]
139 [-]: LOADK     R11 K25      ; R11 := "GoalCelebration"
140 [-]: CONST     R12 0        ; R12 := 0.000000
141 [-]: GETTABLE  R13 R8 K26   ; R13 := R8["x"]
142 [-]: CALL      R9 5 1       ; R9(R10,R11,R12,R13)
143 [-]: GETGLOBAL R9 K2        ; R9 := 0xae91e43b
144 [-]: SELF      R9 R9 K5     ; R10 := R9; R9 := R9[0x67bc869f]
145 [-]: LOADK     R11 K25      ; R11 := "GoalCelebration"
146 [-]: CONST     R12 1        ; R12 := 1.000000
147 [-]: GETTABLE  R13 R8 K27   ; R13 := R8["y"]
148 [-]: CALL      R9 5 1       ; R9(R10,R11,R12,R13)
149 [-]: GETGLOBAL R9 K2        ; R9 := 0xae91e43b
150 [-]: SELF      R9 R9 K5     ; R10 := R9; R9 := R9[0x67bc869f]
151 [-]: LOADK     R11 K25      ; R11 := "GoalCelebration"
152 [-]: CONST     R12 5        ; R12 := 5.000000
153 [-]: CONST     R13 500      ; R13 := 500.000000
154 [-]: CALL      R9 5 1       ; R9(R10,R11,R12,R13)
155 [-]: GETGLOBAL R9 K2        ; R9 := 0xae91e43b
156 [-]: SELF      R9 R9 K5     ; R10 := R9; R9 := R9[0x67bc869f]
157 [-]: LOADK     R11 K25      ; R11 := "GoalCelebration"
158 [-]: CONST     R12 6        ; R12 := 6.000000
159 [-]: CONST     R13 500      ; R13 := 500.000000
160 [-]: CALL      R9 5 1       ; R9(R10,R11,R12,R13)
161 [-]: GETGLOBAL R9 K28       ; R9 := 0x25312c9b
162 [-]: GETGLOBAL R10 K2       ; R10 := 0xae91e43b
163 [-]: LOADK     R11 K29      ; R11 := "LunaroReticle"
164 [-]: CONST     R12 2        ; R12 := 2.000000
165 [-]: NEWTABLE  R13 1 0      ; R13 := {}
166 [-]: CONST     R14 10       ; R14 := 10.000000
167 [-]: SETLIST   R13 1 1      ; R13[(1-1)*FPF+i] := R(13+i), 1 <= i <= 1
168 [-]: NEWTABLE  R14 1 0      ; R14 := {}
169 [-]: CONST     R15 0        ; R15 := 0.000000
170 [-]: SETLIST   R14 1 1      ; R14[(1-1)*FPF+i] := R(14+i), 1 <= i <= 1
171 [-]: LOADK     R15 K31      ; R15 := 0.200000
172 [-]: CALL      R9 7 1       ; R9(R10,R11,R12,R13,R14,R15)
173 [-]: GETGLOBAL R9 K28       ; R9 := 0x25312c9b
174 [-]: GETGLOBAL R10 K2       ; R10 := 0xae91e43b
175 [-]: LOADK     R11 K25      ; R11 := "GoalCelebration"
176 [-]: CONST     R12 2        ; R12 := 2.000000
177 [-]: NEWTABLE  R13 3 0      ; R13 := {}
178 [-]: CONST     R14 10       ; R14 := 10.000000
179 [-]: CONST     R15 5        ; R15 := 5.000000
180 [-]: CONST     R16 6        ; R16 := 6.000000
181 [-]: SETLIST   R13 3 1      ; R13[(1-1)*FPF+i] := R(13+i), 1 <= i <= 3
182 [-]: NEWTABLE  R14 3 0      ; R14 := {}
183 [-]: CONST     R15 100      ; R15 := 100.000000
184 [-]: CONST     R16 100      ; R16 := 100.000000
185 [-]: CONST     R17 100      ; R17 := 100.000000
186 [-]: SETLIST   R14 3 1      ; R14[(1-1)*FPF+i] := R(14+i), 1 <= i <= 3
187 [-]: LOADK     R15 K32      ; R15 := 0.350000
188 [-]: CONST     R16 0        ; R16 := 0.000000
189 [-]: CLOSURE   R17 0        ; R17 := closure(Function #14.1)
190 [-]: MOVE      R0 R8        ; R0 := R8
191 [-]: GETUPVAL  R0 U5        ; R0 := U5
192 [-]: GETUPVAL  R0 U6        ; R0 := U6
193 [-]: GETUPVAL  R0 U3        ; R0 := U3
194 [-]: MOVE      R0 R6        ; R0 := R6
195 [-]: GETUPVAL  R0 U7        ; R0 := U7
196 [-]: GETUPVAL  R0 U0        ; R0 := U0
197 [-]: CALL      R9 9 1       ; R9(R10,R11,R12,R13,R14,R15,R16,R17)
198 [-]: RETURN    R0 1         ; return 


; Function #14.1:
;
; Name:            
; Defined at line: 322
; #Upvalues:       7
; #Parameters:     0
; Is_vararg:       0
; Max Stack Size:  13

  1 [-]: GETUPVAL  R0 U1        ; R0 := U1
  2 [-]: SELF      R0 R0 K0     ; R1 := R0; R0 := R0[0x2de3d774]
  3 [-]: LOADK     R2 K1        ; R2 := "GoalScoreReplayTarget"
  4 [-]: CALL      R0 3 2       ; R0 := R0(R1,R2)
  5 [-]: SETUPVAL  R0 U0        ; U82 := R0
  6 [-]: GETUPVAL  R0 U2        ; R0 := U2
  7 [-]: GETUPVAL  R1 U3        ; R1 := U3
  8 [-]: LEN       R1 R1        ; R1 := # R1
  9 [-]: MUL       R0 R0 R1     ; R0 := R0 * R1
 10 [-]: SUB       R0 R0 K2     ; R0 := R0 - 0.350000
 11 [-]: GETUPVAL  R1 U4        ; R1 := U4
 12 [-]: EQ        0 R1 K3      ; if R1 ~= 0.000000 then PC := 15
 13 [-]: JMP       15           ; PC := 15
 14 [-]: CONST     R0 2         ; R0 := 2.250000
 15 [-]: GETGLOBAL R1 K4        ; R1 := 0x25312c9b
 16 [-]: GETGLOBAL R2 K5        ; R2 := 0xae91e43b
 17 [-]: LOADK     R3 K6        ; R3 := "GoalCelebration.PlayerGoal"
 18 [-]: CONST     R4 2         ; R4 := 2.000000
 19 [-]: NEWTABLE  R5 2 0       ; R5 := {}
 20 [-]: CONST     R6 5         ; R6 := 5.000000
 21 [-]: CONST     R7 6         ; R7 := 6.000000
 22 [-]: SETLIST   R5 2 1       ; R5[(1-1)*FPF+i] := R(5+i), 1 <= i <= 2
 23 [-]: NEWTABLE  R6 2 0       ; R6 := {}
 24 [-]: CONST     R7 60        ; R7 := 60.000000
 25 [-]: CONST     R8 60        ; R8 := 60.000000
 26 [-]: SETLIST   R6 2 1       ; R6[(1-1)*FPF+i] := R(6+i), 1 <= i <= 2
 27 [-]: CONST     R7 0         ; R7 := 0.500000
 28 [-]: MOVE      R8 R0        ; R8 := R0
 29 [-]: CALL      R1 8 1       ; R1(R2,R3,R4,R5,R6,R7,R8)
 30 [-]: GETGLOBAL R1 K4        ; R1 := 0x25312c9b
 31 [-]: GETGLOBAL R2 K5        ; R2 := 0xae91e43b
 32 [-]: LOADK     R3 K8        ; R3 := "GoalCelebration.ReplaySubtitle"
 33 [-]: CONST     R4 2         ; R4 := 2.000000
 34 [-]: NEWTABLE  R5 1 0       ; R5 := {}
 35 [-]: CONST     R6 1         ; R6 := 1.000000
 36 [-]: SETLIST   R5 1 1       ; R5[(1-1)*FPF+i] := R(5+i), 1 <= i <= 1
 37 [-]: NEWTABLE  R6 1 0       ; R6 := {}
 38 [-]: CONST     R7 60        ; R7 := 60.000000
 39 [-]: SETLIST   R6 1 1       ; R6[(1-1)*FPF+i] := R(6+i), 1 <= i <= 1
 40 [-]: CONST     R7 0         ; R7 := 0.500000
 41 [-]: MOVE      R8 R0        ; R8 := R0
 42 [-]: CALL      R1 8 1       ; R1(R2,R3,R4,R5,R6,R7,R8)
 43 [-]: GETGLOBAL R1 K4        ; R1 := 0x25312c9b
 44 [-]: GETGLOBAL R2 K5        ; R2 := 0xae91e43b
 45 [-]: LOADK     R3 K9        ; R3 := "GoalCelebration"
 46 [-]: CONST     R4 2         ; R4 := 2.000000
 47 [-]: NEWTABLE  R5 3 0       ; R5 := {}
 48 [-]: CONST     R6 0         ; R6 := 0.000000
 49 [-]: CONST     R7 1         ; R7 := 1.000000
 50 [-]: CONST     R8 10        ; R8 := 10.000000
 51 [-]: SETLIST   R5 3 1       ; R5[(1-1)*FPF+i] := R(5+i), 1 <= i <= 3
 52 [-]: NEWTABLE  R6 2 0       ; R6 := {}
 53 [-]: GETUPVAL  R7 U0        ; R7 := U0
 54 [-]: GETTABLE  R7 R7 K10    ; R7 := R7["x"]
 55 [-]: GETUPVAL  R8 U0        ; R8 := U0
 56 [-]: GETTABLE  R8 R8 K11    ; R8 := R8["y"]
 57 [-]: GETUPVAL  R9 U5        ; R9 := U5
 58 [-]: GETTABLE  R9 R9 K12    ; R9 := R9[0x06d055f9]
 59 [-]: GETUPVAL  R10 U4       ; R10 := U4
 60 [-]: LT        1 K3 R10     ; if 0.000000 < R10 then PC := 63
 61 [-]: JMP       63           ; PC := 63
 62 [-]: LOADKB    R10 0 1      ; R10 := false; PC := 63
 63 [-]: LOADKB    R10 1 0      ; R10 := true
 64 [-]: CONST     R11 100      ; R11 := 100.000000
 65 [-]: CONST     R12 0        ; R12 := 0.000000
 66 [-]: CALL      R9 4 0       ; R9,... := R9(R10,R11,R12)
 67 [-]: SETLIST   R6 0 1       ; R6[(1-1)*FPF+i] := R(6+i), 1 <= i <= 0
 68 [-]: CONST     R7 0         ; R7 := 0.500000
 69 [-]: MOVE      R8 R0        ; R8 := R0
 70 [-]: CLOSURE   R9 0         ; R9 := closure(Function #14.1.1)
 71 [-]: MOVE      R0 R0        ; R0 := R0
 72 [-]: GETUPVAL  R0 U6        ; R0 := U6
 73 [-]: CALL      R1 9 1       ; R1(R2,R3,R4,R5,R6,R7,R8,R9)
 74 [-]: RETURN    R0 1         ; return 


; Function #14.1.1:
;
; Name:            
; Defined at line: 331
; #Upvalues:       2
; #Parameters:     0
; Is_vararg:       0
; Max Stack Size:  9

  1 [-]: GETGLOBAL R0 K0        ; R0 := 0x25312c9b
  2 [-]: GETGLOBAL R1 K1        ; R1 := 0xae91e43b
  3 [-]: LOADK     R2 K2        ; R2 := "GoalCelebration"
  4 [-]: CONST     R3 2         ; R3 := 2.000000
  5 [-]: NEWTABLE  R4 1 0       ; R4 := {}
  6 [-]: CONST     R5 10        ; R5 := 10.000000
  7 [-]: SETLIST   R4 1 1       ; R4[(1-1)*FPF+i] := R(4+i), 1 <= i <= 1
  8 [-]: NEWTABLE  R5 1 0       ; R5 := {}
  9 [-]: CONST     R6 0         ; R6 := 0.000000
 10 [-]: SETLIST   R5 1 1       ; R5[(1-1)*FPF+i] := R(5+i), 1 <= i <= 1
 11 [-]: CONST     R6 0         ; R6 := 0.500000
 12 [-]: GETUPVAL  R7 U0        ; R7 := U0
 13 [-]: SUB       R7 K4 R7     ; R7 := 5.250000 - R7
 14 [-]: CLOSURE   R8 0         ; R8 := closure(Function #14.1.1.1)
 15 [-]: GETUPVAL  R0 U1        ; R0 := U1
 16 [-]: CALL      R0 9 1       ; R0(R1,R2,R3,R4,R5,R6,R7,R8)
 17 [-]: RETURN    R0 1         ; return 


; Function #14.1.1.1:
;
; Name:            
; Defined at line: 333
; #Upvalues:       1
; #Parameters:     0
; Is_vararg:       0
; Max Stack Size:  7

  1 [-]: GETGLOBAL R0 K0        ; R0 := 0x25312c9b
  2 [-]: GETGLOBAL R1 K1        ; R1 := 0xae91e43b
  3 [-]: LOADK     R2 K2        ; R2 := "LunaroReticle"
  4 [-]: CONST     R3 2         ; R3 := 2.000000
  5 [-]: NEWTABLE  R4 1 0       ; R4 := {}
  6 [-]: CONST     R5 10        ; R5 := 10.000000
  7 [-]: SETLIST   R4 1 1       ; R4[(1-1)*FPF+i] := R(4+i), 1 <= i <= 1
  8 [-]: NEWTABLE  R5 1 0       ; R5 := {}
  9 [-]: CONST     R6 100       ; R6 := 100.000000
 10 [-]: SETLIST   R5 1 1       ; R5[(1-1)*FPF+i] := R(5+i), 1 <= i <= 1
 11 [-]: LOADK     R6 K4        ; R6 := 0.200000
 12 [-]: CALL      R0 7 1       ; R0(R1,R2,R3,R4,R5,R6)
 13 [-]: LOADKB    R0 0 0       ; R0 := false
 14 [-]: SETUPVAL  R0 U0        ; U82 := R0
 15 [-]: RETURN    R0 1         ; return 


; Function #15:
;
; Name:            
; Defined at line: 341
; #Upvalues:       0
; #Parameters:     0
; Is_vararg:       0
; Max Stack Size:  5

  1 [-]: GETGLOBAL R0 K0        ; R0 := 0xae91e43b
  2 [-]: SELF      R0 R0 K1     ; R1 := R0; R0 := R0[0x67bc869f]
  3 [-]: LOADK     R2 K2        ; R2 := "Countdown"
  4 [-]: CONST     R3 10        ; R3 := 10.000000
  5 [-]: CONST     R4 100       ; R4 := 100.000000
  6 [-]: CALL      R0 5 1       ; R0(R1,R2,R3,R4)
  7 [-]: GETGLOBAL R0 K3        ; R0 := 0x38f10e85
  8 [-]: GETGLOBAL R1 K0        ; R1 := 0xae91e43b
  9 [-]: LOADK     R2 K4        ; R2 := "Countdown.Time.gotoAndPlay"
 10 [-]: LOADK     R3 K5        ; R3 := "GameStartCountdown"
 11 [-]: CALL      R0 4 1       ; R0(R1,R2,R3)
 12 [-]: RETURN    R0 1         ; return 


; Function #16:
;
; Name:            
; Defined at line: 346
; #Upvalues:       0
; #Parameters:     0
; Is_vararg:       0
; Max Stack Size:  5

  1 [-]: GETGLOBAL R0 K0        ; R0 := 0xae91e43b
  2 [-]: SELF      R0 R0 K1     ; R1 := R0; R0 := R0[0x67bc869f]
  3 [-]: LOADK     R2 K2        ; R2 := "Countdown"
  4 [-]: CONST     R3 10        ; R3 := 10.000000
  5 [-]: CONST     R4 100       ; R4 := 100.000000
  6 [-]: CALL      R0 5 1       ; R0(R1,R2,R3,R4)
  7 [-]: GETGLOBAL R0 K3        ; R0 := 0x38f10e85
  8 [-]: GETGLOBAL R1 K0        ; R1 := 0xae91e43b
  9 [-]: LOADK     R2 K4        ; R2 := "Countdown.Time.gotoAndPlay"
 10 [-]: LOADK     R3 K5        ; R3 := "HalfTimeCountdown"
 11 [-]: CALL      R0 4 1       ; R0(R1,R2,R3)
 12 [-]: RETURN    R0 1         ; return 


; Function #17:
;
; Name:            
; Defined at line: 351
; #Upvalues:       0
; #Parameters:     0
; Is_vararg:       0
; Max Stack Size:  5

  1 [-]: GETGLOBAL R0 K0        ; R0 := 0x38f10e85
  2 [-]: GETGLOBAL R1 K1        ; R1 := 0xae91e43b
  3 [-]: LOADK     R2 K2        ; R2 := "Countdown.Time.stop"
  4 [-]: CALL      R0 3 1       ; R0(R1,R2)
  5 [-]: GETGLOBAL R0 K1        ; R0 := 0xae91e43b
  6 [-]: SELF      R0 R0 K3     ; R1 := R0; R0 := R0[0x67bc869f]
  7 [-]: LOADK     R2 K4        ; R2 := "Countdown"
  8 [-]: CONST     R3 10        ; R3 := 10.000000
  9 [-]: CONST     R4 0         ; R4 := 0.000000
 10 [-]: CALL      R0 5 1       ; R0(R1,R2,R3,R4)
 11 [-]: RETURN    R0 1         ; return 


; Function #18:
;
; Name:            
; Defined at line: 356
; #Upvalues:       0
; #Parameters:     0
; Is_vararg:       0
; Max Stack Size:  5

  1 [-]: GETGLOBAL R0 K0        ; R0 := 0xae91e43b
  2 [-]: SELF      R0 R0 K1     ; R1 := R0; R0 := R0[0x67bc869f]
  3 [-]: LOADK     R2 K2        ; R2 := "Countdown"
  4 [-]: CONST     R3 10        ; R3 := 10.000000
  5 [-]: CONST     R4 100       ; R4 := 100.000000
  6 [-]: CALL      R0 5 1       ; R0(R1,R2,R3,R4)
  7 [-]: GETGLOBAL R0 K3        ; R0 := 0x38f10e85
  8 [-]: GETGLOBAL R1 K0        ; R1 := 0xae91e43b
  9 [-]: LOADK     R2 K4        ; R2 := "Countdown.Time.play"
 10 [-]: CALL      R0 3 1       ; R0(R1,R2)
 11 [-]: RETURN    R0 1         ; return 


; Function #19:
;
; Name:            
; Defined at line: 361
; #Upvalues:       1
; #Parameters:     1
; Is_vararg:       0
; Max Stack Size:  10

  1 [-]: GETGLOBAL R1 K0        ; R1 := 0x25312c9b
  2 [-]: GETGLOBAL R2 K1        ; R2 := 0xae91e43b
  3 [-]: LOADK     R3 K2        ; R3 := "ClearZone"
  4 [-]: CONST     R4 2         ; R4 := 2.000000
  5 [-]: NEWTABLE  R5 1 0       ; R5 := {}
  6 [-]: CONST     R6 10        ; R6 := 10.000000
  7 [-]: SETLIST   R5 1 1       ; R5[(1-1)*FPF+i] := R(5+i), 1 <= i <= 1
  8 [-]: NEWTABLE  R6 1 0       ; R6 := {}
  9 [-]: CONST     R7 0         ; R7 := 0.000000
 10 [-]: SETLIST   R6 1 1       ; R6[(1-1)*FPF+i] := R(6+i), 1 <= i <= 1
 11 [-]: LOADK     R7 K4        ; R7 := 0.200000
 12 [-]: MOVE      R8 R0        ; R8 := R0
 13 [-]: CLOSURE   R9 0         ; R9 := closure(Function #19.1)
 14 [-]: GETUPVAL  R0 U0        ; R0 := U0
 15 [-]: CALL      R1 9 1       ; R1(R2,R3,R4,R5,R6,R7,R8,R9)
 16 [-]: RETURN    R0 1         ; return 


; Function #19.1:
;
; Name:            
; Defined at line: 363
; #Upvalues:       1
; #Parameters:     0
; Is_vararg:       0
; Max Stack Size:  2

  1 [-]: SETUPVAL  R0 U0        ; U82 := R0
  2 [-]: RETURN    R0 1         ; return 


; Function #20:
;
; Name:            
; Defined at line: 368
; #Upvalues:       4
; #Parameters:     4
; Is_vararg:       0
; Max Stack Size:  19

  1 [-]: SETUPVAL  R0 U0        ; U82 := R0
  2 [-]: GETGLOBAL R4 K0        ; R4 := 0xae91e43b
  3 [-]: SELF      R4 R4 K1     ; R5 := R4; R4 := R4[0x5f56eeab]
  4 [-]: LOADK     R6 K2        ; R6 := "ClearZone.Text"
  5 [-]: CONST     R7 29        ; R7 := 29.000000
  6 [-]: MOVE      R8 R0        ; R8 := R0
  7 [-]: CALL      R4 5 1       ; R4(R5,R6,R7,R8)
  8 [-]: GETUPVAL  R4 U1        ; R4 := U1
  9 [-]: GETTABLE  R4 R4 K3     ; R4 := R4[0x74a11ec6]
 10 [-]: GETGLOBAL R5 K0        ; R5 := 0xae91e43b
 11 [-]: SELF      R5 R5 K4     ; R6 := R5; R5 := R5[0x91a24e4b]
 12 [-]: LOADK     R7 K2        ; R7 := "ClearZone.Text"
 13 [-]: CONST     R8 33        ; R8 := 33.000000
 14 [-]: CALL      R5 4 0       ; R5,... := R5(R6,R7,R8)
 15 [-]: CALL      R4 0 2       ; R4 := R4(R5,...)
 16 [-]: ADD       R4 R4 K5     ; R4 := R4 + 20.000000
 17 [-]: GETGLOBAL R5 K6        ; R5 := 0x5bced4c4
 18 [-]: GETTABLE  R5 R5 K7     ; R5 := R5[0xb62ecfe0]
 19 [-]: MOVE      R6 R4        ; R6 := R4
 20 [-]: CONST     R7 350       ; R7 := 350.000000
 21 [-]: CALL      R5 3 2       ; R5 := R5(R6,R7)
 22 [-]: MOVE      R4 R5        ; R4 := R5
 23 [-]: MOD       R5 R4 K8     ; R5 := R4 % 2.000000
 24 [-]: EQ        1 R5 K9      ; if R5 == 0.000000 then PC := 27
 25 [-]: JMP       27           ; PC := 27
 26 [-]: ADD       R4 R4 K10    ; R4 := R4 + 1.000000
 27 [-]: CONST     R5 10        ; R5 := 10.000000
 28 [-]: MOVE      R6 R4        ; R6 := R4
 29 [-]: EQ        1 R2 K11     ; if R2 == true then PC := 32
 30 [-]: JMP       32           ; PC := 32
 31 [-]: LOADKB    R2 0 1       ; R2 := false; PC := 32
 32 [-]: LOADKB    R2 1 0       ; R2 := true
 33 [-]: TEST      R2 0         ; if not R2 then PC := 36
 34 [-]: JMP       36           ; PC := 36
 35 [-]: ADD       R6 R6 K12    ; R6 := R6 + 60.000000
 36 [-]: GETGLOBAL R7 K0        ; R7 := 0xae91e43b
 37 [-]: SELF      R7 R7 K13    ; R8 := R7; R7 := R7[0x67bc869f]
 38 [-]: LOADK     R9 K14       ; R9 := "ClearZone.ClearZonePanelMiddle"
 39 [-]: CONST     R10 12       ; R10 := 12.000000
 40 [-]: MOVE      R11 R6       ; R11 := R6
 41 [-]: CALL      R7 5 1       ; R7(R8,R9,R10,R11)
 42 [-]: GETGLOBAL R7 K0        ; R7 := 0xae91e43b
 43 [-]: SELF      R7 R7 K13    ; R8 := R7; R7 := R7[0x67bc869f]
 44 [-]: LOADK     R9 K15       ; R9 := "ClearZone.ClearZonePanelLeft"
 45 [-]: CONST     R10 0        ; R10 := 0.000000
 46 [-]: UNM       R11 R5       ; R11 :=  R5
 47 [-]: MUL       R12 R6 K16   ; R12 := R6 * 0.500000
 48 [-]: SUB       R11 R11 R12  ; R11 := R11 - R12
 49 [-]: CALL      R7 5 1       ; R7(R8,R9,R10,R11)
 50 [-]: GETGLOBAL R7 K0        ; R7 := 0xae91e43b
 51 [-]: SELF      R7 R7 K13    ; R8 := R7; R7 := R7[0x67bc869f]
 52 [-]: LOADK     R9 K17       ; R9 := "ClearZone.ClearZonePanelRight"
 53 [-]: CONST     R10 0        ; R10 := 0.000000
 54 [-]: MUL       R11 R6 K16   ; R11 := R6 * 0.500000
 55 [-]: ADD       R11 R5 R11   ; R11 := R5 + R11
 56 [-]: CALL      R7 5 1       ; R7(R8,R9,R10,R11)
 57 [-]: GETGLOBAL R7 K0        ; R7 := 0xae91e43b
 58 [-]: SELF      R7 R7 K18    ; R8 := R7; R7 := R7[0xaade900e]
 59 [-]: LOADK     R9 K19       ; R9 := "ClearZone.AlertIconLeft"
 60 [-]: CONST     R10 11       ; R10 := 11.000000
 61 [-]: MOVE      R11 R2       ; R11 := R2
 62 [-]: CALL      R7 5 1       ; R7(R8,R9,R10,R11)
 63 [-]: GETGLOBAL R7 K0        ; R7 := 0xae91e43b
 64 [-]: SELF      R7 R7 K18    ; R8 := R7; R7 := R7[0xaade900e]
 65 [-]: LOADK     R9 K20       ; R9 := "ClearZone.AlertIconRight"
 66 [-]: CONST     R10 11       ; R10 := 11.000000
 67 [-]: MOVE      R11 R2       ; R11 := R2
 68 [-]: CALL      R7 5 1       ; R7(R8,R9,R10,R11)
 69 [-]: TEST      R2 0         ; if not R2 then PC := 86
 70 [-]: JMP       86           ; PC := 86
 71 [-]: GETGLOBAL R7 K0        ; R7 := 0xae91e43b
 72 [-]: SELF      R7 R7 K13    ; R8 := R7; R7 := R7[0x67bc869f]
 73 [-]: LOADK     R9 K19       ; R9 := "ClearZone.AlertIconLeft"
 74 [-]: CONST     R10 0        ; R10 := 0.000000
 75 [-]: MUL       R11 R6 K16   ; R11 := R6 * 0.500000
 76 [-]: UNM       R11 R11      ; R11 :=  R11
 77 [-]: ADD       R11 R11 K21  ; R11 := R11 + 10.000000
 78 [-]: CALL      R7 5 1       ; R7(R8,R9,R10,R11)
 79 [-]: GETGLOBAL R7 K0        ; R7 := 0xae91e43b
 80 [-]: SELF      R7 R7 K13    ; R8 := R7; R7 := R7[0x67bc869f]
 81 [-]: LOADK     R9 K20       ; R9 := "ClearZone.AlertIconRight"
 82 [-]: CONST     R10 0        ; R10 := 0.000000
 83 [-]: MUL       R11 R6 K16   ; R11 := R6 * 0.500000
 84 [-]: SUB       R11 R11 K21  ; R11 := R11 - 10.000000
 85 [-]: CALL      R7 5 1       ; R7(R8,R9,R10,R11)
 86 [-]: CONST     R7 300       ; R7 := 300.000000
 87 [-]: CONST     R8 0         ; R8 := 0.000000
 88 [-]: TEST      R3 0         ; if not R3 then PC := 92
 89 [-]: JMP       92           ; PC := 92
 90 [-]: CONST     R7 500       ; R7 := 500.000000
 91 [-]: CONST     R8 300       ; R8 := 300.000000
 92 [-]: GETUPVAL  R9 U2        ; R9 := U2
 93 [-]: SELF      R9 R9 K22    ; R10 := R9; R9 := R9[0x2de3d774]
 94 [-]: LOADK     R11 K23      ; R11 := "ClearZone"
 95 [-]: CALL      R9 3 2       ; R9 := R9(R10,R11)
 96 [-]: GETGLOBAL R10 K0       ; R10 := 0xae91e43b
 97 [-]: SELF      R10 R10 K13  ; R11 := R10; R10 := R10[0x67bc869f]
 98 [-]: LOADK     R12 K23      ; R12 := "ClearZone"
 99 [-]: CONST     R13 1        ; R13 := 1.000000
100 [-]: GETTABLE  R14 R9 K24   ; R14 := R9["y"]
101 [-]: ADD       R14 R14 R7   ; R14 := R14 + R7
102 [-]: CALL      R10 5 1      ; R10(R11,R12,R13,R14)
103 [-]: GETGLOBAL R10 K25      ; R10 := 0x25312c9b
104 [-]: GETGLOBAL R11 K0       ; R11 := 0xae91e43b
105 [-]: LOADK     R12 K23      ; R12 := "ClearZone"
106 [-]: CONST     R13 2        ; R13 := 2.000000
107 [-]: NEWTABLE  R14 2 0      ; R14 := {}
108 [-]: CONST     R15 10       ; R15 := 10.000000
109 [-]: CONST     R16 1        ; R16 := 1.000000
110 [-]: SETLIST   R14 2 1      ; R14[(1-1)*FPF+i] := R(14+i), 1 <= i <= 2
111 [-]: NEWTABLE  R15 2 0      ; R15 := {}
112 [-]: CONST     R16 100      ; R16 := 100.000000
113 [-]: GETTABLE  R17 R9 K24   ; R17 := R9["y"]
114 [-]: ADD       R17 R17 R8   ; R17 := R17 + R8
115 [-]: SETLIST   R15 2 1      ; R15[(1-1)*FPF+i] := R(15+i), 1 <= i <= 2
116 [-]: LOADK     R16 K27      ; R16 := 0.350000
117 [-]: CONST     R17 0        ; R17 := 0.000000
118 [-]: CLOSURE   R18 0        ; R18 := closure(Function #20.1)
119 [-]: MOVE      R0 R1        ; R0 := R1
120 [-]: GETUPVAL  R0 U3        ; R0 := U3
121 [-]: CALL      R10 9 1      ; R10(R11,R12,R13,R14,R15,R16,R17,R18)
122 [-]: RETURN    R0 1         ; return 


; Function #20.1:
;
; Name:            
; Defined at line: 404
; #Upvalues:       2
; #Parameters:     0
; Is_vararg:       0
; Max Stack Size:  2

  1 [-]: GETUPVAL  R0 U0        ; R0 := U0
  2 [-]: EQ        1 R0 K0      ; if R0 == nil then PC := 7
  3 [-]: JMP       7            ; PC := 7
  4 [-]: GETUPVAL  R0 U1        ; R0 := U1
  5 [-]: GETUPVAL  R1 U0        ; R1 := U0
  6 [-]: CALL      R0 2 1       ; R0(R1)
  7 [-]: RETURN    R0 1         ; return 


; Function #21:
;
; Name:            
; Defined at line: 411
; #Upvalues:       0
; #Parameters:     2
; Is_vararg:       0
; Max Stack Size:  11

  1 [-]: GETGLOBAL R2 K0        ; R2 := 0x25312c9b
  2 [-]: GETGLOBAL R3 K1        ; R3 := 0xae91e43b
  3 [-]: MOVE      R4 R0        ; R4 := R0
  4 [-]: CONST     R5 0         ; R5 := 0.000000
  5 [-]: NEWTABLE  R6 1 0       ; R6 := {}
  6 [-]: CONST     R7 10        ; R7 := 10.000000
  7 [-]: SETLIST   R6 1 1       ; R6[(1-1)*FPF+i] := R(6+i), 1 <= i <= 1
  8 [-]: NEWTABLE  R7 1 0       ; R7 := {}
  9 [-]: CONST     R8 50        ; R8 := 50.000000
 10 [-]: SETLIST   R7 1 1       ; R7[(1-1)*FPF+i] := R(7+i), 1 <= i <= 1
 11 [-]: LOADK     R8 K3        ; R8 := 0.350000
 12 [-]: CONST     R9 0         ; R9 := 0.000000
 13 [-]: CLOSURE   R10 0        ; R10 := closure(Function #21.1)
 14 [-]: MOVE      R0 R0        ; R0 := R0
 15 [-]: MOVE      R0 R1        ; R0 := R1
 16 [-]: CALL      R2 9 1       ; R2(R3,R4,R5,R6,R7,R8,R9,R10)
 17 [-]: RETURN    R0 1         ; return 


; Function #21.1:
;
; Name:            
; Defined at line: 413
; #Upvalues:       2
; #Parameters:     0
; Is_vararg:       0
; Max Stack Size:  9

  1 [-]: GETGLOBAL R0 K0        ; R0 := 0x25312c9b
  2 [-]: GETGLOBAL R1 K1        ; R1 := 0xae91e43b
  3 [-]: GETUPVAL  R2 U0        ; R2 := U0
  4 [-]: CONST     R3 0         ; R3 := 0.000000
  5 [-]: NEWTABLE  R4 1 0       ; R4 := {}
  6 [-]: CONST     R5 10        ; R5 := 10.000000
  7 [-]: SETLIST   R4 1 1       ; R4[(1-1)*FPF+i] := R(4+i), 1 <= i <= 1
  8 [-]: NEWTABLE  R5 1 0       ; R5 := {}
  9 [-]: CONST     R6 100       ; R6 := 100.000000
 10 [-]: SETLIST   R5 1 1       ; R5[(1-1)*FPF+i] := R(5+i), 1 <= i <= 1
 11 [-]: LOADK     R6 K3        ; R6 := 0.350000
 12 [-]: CONST     R7 0         ; R7 := 0.000000
 13 [-]: CLOSURE   R8 0         ; R8 := closure(Function #21.1.1)
 14 [-]: GETUPVAL  R0 U1        ; R0 := U1
 15 [-]: GETUPVAL  R0 U0        ; R0 := U0
 16 [-]: CALL      R0 9 1       ; R0(R1,R2,R3,R4,R5,R6,R7,R8)
 17 [-]: RETURN    R0 1         ; return 


; Function #21.1.1:
;
; Name:            
; Defined at line: 415
; #Upvalues:       2
; #Parameters:     0
; Is_vararg:       0
; Max Stack Size:  3

  1 [-]: GETUPVAL  R0 U0        ; R0 := U0
  2 [-]: EQ        1 R0 K0      ; if R0 == nil then PC := 8
  3 [-]: JMP       8            ; PC := 8
  4 [-]: GETUPVAL  R0 U0        ; R0 := U0
  5 [-]: GETUPVAL  R1 U1        ; R1 := U1
  6 [-]: GETUPVAL  R2 U0        ; R2 := U0
  7 [-]: CALL      R0 3 1       ; R0(R1,R2)
  8 [-]: RETURN    R0 1         ; return 


; Function #22:
;
; Name:            
; Defined at line: 423
; #Upvalues:       4
; #Parameters:     1
; Is_vararg:       0
; Max Stack Size:  12

  1 [-]: GETUPVAL  R1 U0        ; R1 := U0
  2 [-]: EQ        1 R1 R0      ; if R1 == R0 then PC := 60
  3 [-]: JMP       60           ; PC := 60
  4 [-]: GETUPVAL  R1 U0        ; R1 := U0
  5 [-]: EQ        1 R1 K0      ; if R1 == nil then PC := 36
  6 [-]: JMP       36           ; PC := 36
  7 [-]: GETUPVAL  R1 U0        ; R1 := U0
  8 [-]: LOADK     R2 K1        ; R2 := "Scoreboard.Score.MiniEmblemTeam"
  9 [-]: MOVE      R3 R1        ; R3 := R1
 10 [-]: CONCAT    R2 R2 R3     ; R2 := R2 .. R3
 11 [-]: GETGLOBAL R3 K2        ; R3 := 0xae91e43b
 12 [-]: SELF      R3 R3 K3     ; R4 := R3; R3 := R3[0x67bc869f]
 13 [-]: MOVE      R5 R2        ; R5 := R2
 14 [-]: CONST     R6 10        ; R6 := 10.000000
 15 [-]: CONST     R7 100       ; R7 := 100.000000
 16 [-]: CALL      R3 5 1       ; R3(R4,R5,R6,R7)
 17 [-]: GETGLOBAL R3 K4        ; R3 := 0x25312c9b
 18 [-]: GETGLOBAL R4 K2        ; R4 := 0xae91e43b
 19 [-]: MOVE      R5 R2        ; R5 := R2
 20 [-]: CONST     R6 2         ; R6 := 2.000000
 21 [-]: NEWTABLE  R7 1 0       ; R7 := {}
 22 [-]: CONST     R8 15        ; R8 := 15.000000
 23 [-]: SETLIST   R7 1 1       ; R7[(1-1)*FPF+i] := R(7+i), 1 <= i <= 1
 24 [-]: NEWTABLE  R8 1 0       ; R8 := {}
 25 [-]: CONST     R9 -90       ; R9 := -90.000000
 26 [-]: SETLIST   R8 1 1       ; R8[(1-1)*FPF+i] := R(8+i), 1 <= i <= 1
 27 [-]: LOADK     R9 K6        ; R9 := 0.150000
 28 [-]: CONST     R10 0        ; R10 := 0.000000
 29 [-]: CLOSURE   R11 0        ; R11 := closure(Function #22.1)
 30 [-]: MOVE      R0 R2        ; R0 := R2
 31 [-]: GETUPVAL  R0 U1        ; R0 := U1
 32 [-]: MOVE      R0 R1        ; R0 := R1
 33 [-]: GETUPVAL  R0 U2        ; R0 := U2
 34 [-]: CALL      R3 9 1       ; R3(R4,R5,R6,R7,R8,R9,R10,R11)
 35 [-]: CLOSE     R1           ; SAVE R1,...
 36 [-]: SETUPVAL  R0 U0        ; U82 := R0
 37 [-]: GETUPVAL  R1 U0        ; R1 := U0
 38 [-]: EQ        1 R1 K0      ; if R1 == nil then PC := 60
 39 [-]: JMP       60           ; PC := 60
 40 [-]: LOADK     R1 K1        ; R1 := "Scoreboard.Score.MiniEmblemTeam"
 41 [-]: GETUPVAL  R2 U0        ; R2 := U0
 42 [-]: CONCAT    R1 R1 R2     ; R1 := R1 .. R2
 43 [-]: GETGLOBAL R2 K4        ; R2 := 0x25312c9b
 44 [-]: GETGLOBAL R3 K2        ; R3 := 0xae91e43b
 45 [-]: MOVE      R4 R1        ; R4 := R1
 46 [-]: CONST     R5 2         ; R5 := 2.000000
 47 [-]: NEWTABLE  R6 1 0       ; R6 := {}
 48 [-]: CONST     R7 15        ; R7 := 15.000000
 49 [-]: SETLIST   R6 1 1       ; R6[(1-1)*FPF+i] := R(6+i), 1 <= i <= 1
 50 [-]: NEWTABLE  R7 1 0       ; R7 := {}
 51 [-]: CONST     R8 90        ; R8 := 90.000000
 52 [-]: SETLIST   R7 1 1       ; R7[(1-1)*FPF+i] := R(7+i), 1 <= i <= 1
 53 [-]: LOADK     R8 K6        ; R8 := 0.150000
 54 [-]: CONST     R9 0         ; R9 := 0.000000
 55 [-]: CLOSURE   R10 1        ; R10 := closure(Function #22.2)
 56 [-]: MOVE      R0 R1        ; R0 := R1
 57 [-]: GETUPVAL  R0 U3        ; R0 := U3
 58 [-]: CALL      R2 9 1       ; R2(R3,R4,R5,R6,R7,R8,R9,R10)
 59 [-]: CLOSE     R1           ; SAVE R1,...
 60 [-]: RETURN    R0 1         ; return 


; Function #22.1:
;
; Name:            
; Defined at line: 430
; #Upvalues:       4
; #Parameters:     0
; Is_vararg:       0
; Max Stack Size:  7

  1 [-]: GETGLOBAL R0 K0        ; R0 := 0xae91e43b
  2 [-]: SELF      R0 R0 K1     ; R1 := R0; R0 := R0[0x1cb415c1]
  3 [-]: GETUPVAL  R2 U0        ; R2 := U0
  4 [-]: GETUPVAL  R3 U1        ; R3 := U1
  5 [-]: GETUPVAL  R4 U2        ; R4 := U2
  6 [-]: GETTABLE  R3 R3 R4     ; R3 := R3[R4]
  7 [-]: CALL      R0 4 1       ; R0(R1,R2,R3)
  8 [-]: GETGLOBAL R0 K0        ; R0 := 0xae91e43b
  9 [-]: SELF      R0 R0 K2     ; R1 := R0; R0 := R0[0x67bc869f]
 10 [-]: GETUPVAL  R2 U0        ; R2 := U0
 11 [-]: CONST     R3 9         ; R3 := 9.000000
 12 [-]: GETUPVAL  R4 U3        ; R4 := U3
 13 [-]: GETUPVAL  R5 U2        ; R5 := U2
 14 [-]: GETTABLE  R4 R4 R5     ; R4 := R4[R5]
 15 [-]: CALL      R0 5 1       ; R0(R1,R2,R3,R4)
 16 [-]: GETGLOBAL R0 K0        ; R0 := 0xae91e43b
 17 [-]: SELF      R0 R0 K2     ; R1 := R0; R0 := R0[0x67bc869f]
 18 [-]: GETUPVAL  R2 U0        ; R2 := U0
 19 [-]: CONST     R3 15        ; R3 := 15.000000
 20 [-]: CONST     R4 90        ; R4 := 90.000000
 21 [-]: CALL      R0 5 1       ; R0(R1,R2,R3,R4)
 22 [-]: GETGLOBAL R0 K3        ; R0 := 0x25312c9b
 23 [-]: GETGLOBAL R1 K0        ; R1 := 0xae91e43b
 24 [-]: GETUPVAL  R2 U0        ; R2 := U0
 25 [-]: CONST     R3 4         ; R3 := 4.000000
 26 [-]: NEWTABLE  R4 1 0       ; R4 := {}
 27 [-]: CONST     R5 15        ; R5 := 15.000000
 28 [-]: SETLIST   R4 1 1       ; R4[(1-1)*FPF+i] := R(4+i), 1 <= i <= 1
 29 [-]: NEWTABLE  R5 1 0       ; R5 := {}
 30 [-]: CONST     R6 0         ; R6 := 0.000000
 31 [-]: SETLIST   R5 1 1       ; R5[(1-1)*FPF+i] := R(5+i), 1 <= i <= 1
 32 [-]: LOADK     R6 K5        ; R6 := 0.350000
 33 [-]: CALL      R0 7 1       ; R0(R1,R2,R3,R4,R5,R6)
 34 [-]: RETURN    R0 1         ; return 


; Function #22.2:
;
; Name:            
; Defined at line: 442
; #Upvalues:       2
; #Parameters:     0
; Is_vararg:       0
; Max Stack Size:  9

  1 [-]: GETGLOBAL R0 K0        ; R0 := 0xae91e43b
  2 [-]: SELF      R0 R0 K1     ; R1 := R0; R0 := R0[0x1cb415c1]
  3 [-]: GETUPVAL  R2 U0        ; R2 := U0
  4 [-]: GETGLOBAL R3 K2        ; R3 := 0x889ddd8f
  5 [-]: CALL      R0 4 1       ; R0(R1,R2,R3)
  6 [-]: GETGLOBAL R0 K0        ; R0 := 0xae91e43b
  7 [-]: SELF      R0 R0 K3     ; R1 := R0; R0 := R0[0x67bc869f]
  8 [-]: GETUPVAL  R2 U0        ; R2 := U0
  9 [-]: CONST     R3 9         ; R3 := 9.000000
 10 [-]: GETGLOBAL R4 K4        ; R4 := 0x0032441c
 11 [-]: GETTABLE  R4 R4 K5     ; R4 := R4["UIColor_White"]
 12 [-]: CALL      R0 5 1       ; R0(R1,R2,R3,R4)
 13 [-]: GETGLOBAL R0 K0        ; R0 := 0xae91e43b
 14 [-]: SELF      R0 R0 K3     ; R1 := R0; R0 := R0[0x67bc869f]
 15 [-]: GETUPVAL  R2 U0        ; R2 := U0
 16 [-]: CONST     R3 15        ; R3 := 15.000000
 17 [-]: CONST     R4 -90       ; R4 := -90.000000
 18 [-]: CALL      R0 5 1       ; R0(R1,R2,R3,R4)
 19 [-]: GETGLOBAL R0 K6        ; R0 := 0x25312c9b
 20 [-]: GETGLOBAL R1 K0        ; R1 := 0xae91e43b
 21 [-]: GETUPVAL  R2 U0        ; R2 := U0
 22 [-]: CONST     R3 4         ; R3 := 4.000000
 23 [-]: NEWTABLE  R4 1 0       ; R4 := {}
 24 [-]: CONST     R5 15        ; R5 := 15.000000
 25 [-]: SETLIST   R4 1 1       ; R4[(1-1)*FPF+i] := R(4+i), 1 <= i <= 1
 26 [-]: NEWTABLE  R5 1 0       ; R5 := {}
 27 [-]: CONST     R6 0         ; R6 := 0.000000
 28 [-]: SETLIST   R5 1 1       ; R5[(1-1)*FPF+i] := R(5+i), 1 <= i <= 1
 29 [-]: LOADK     R6 K8        ; R6 := 0.350000
 30 [-]: CONST     R7 0         ; R7 := 0.000000
 31 [-]: CLOSURE   R8 0         ; R8 := closure(Function #22.2.1)
 32 [-]: GETUPVAL  R0 U1        ; R0 := U1
 33 [-]: GETUPVAL  R0 U0        ; R0 := U0
 34 [-]: CALL      R0 9 1       ; R0(R1,R2,R3,R4,R5,R6,R7,R8)
 35 [-]: RETURN    R0 1         ; return 


; Function #22.2.1:
;
; Name:            
; Defined at line: 447
; #Upvalues:       2
; #Parameters:     0
; Is_vararg:       0
; Max Stack Size:  3

  1 [-]: GETUPVAL  R0 U0        ; R0 := U0
  2 [-]: GETUPVAL  R1 U1        ; R1 := U1
  3 [-]: GETUPVAL  R2 U0        ; R2 := U0
  4 [-]: CALL      R0 3 1       ; R0(R1,R2)
  5 [-]: RETURN    R0 1         ; return 


; Function #23:
;
; Name:            
; Defined at line: 456
; #Upvalues:       0
; #Parameters:     0
; Is_vararg:       0
; Max Stack Size:  5

  1 [-]: GETGLOBAL R0 K0        ; R0 := 0xae91e43b
  2 [-]: SELF      R0 R0 K1     ; R1 := R0; R0 := R0[0xaade900e]
  3 [-]: LOADK     R2 K2        ; R2 := "Scoreboard.Time"
  4 [-]: CONST     R3 11        ; R3 := 11.000000
  5 [-]: LOADKB    R4 0 0       ; R4 := false
  6 [-]: CALL      R0 5 1       ; R0(R1,R2,R3,R4)
  7 [-]: RETURN    R0 1         ; return 


; Function #24:
;
; Name:            
; Defined at line: 460
; #Upvalues:       1
; #Parameters:     1
; Is_vararg:       0
; Max Stack Size:  5

  1 [-]: SETUPVAL  R0 U0        ; U82 := R0
  2 [-]: TEST      R0 0         ; if not R0 then PC := 10
  3 [-]: JMP       10           ; PC := 10
  4 [-]: GETGLOBAL R1 K0        ; R1 := 0x38f10e85
  5 [-]: GETGLOBAL R2 K1        ; R2 := 0xae91e43b
  6 [-]: LOADK     R3 K2        ; R3 := "LunaroReticle.gotoAndStop"
  7 [-]: LOADK     R4 K3        ; R4 := "Possession"
  8 [-]: CALL      R1 4 1       ; R1(R2,R3,R4)
  9 [-]: JMP       15           ; PC := 15
 10 [-]: GETGLOBAL R1 K0        ; R1 := 0x38f10e85
 11 [-]: GETGLOBAL R2 K1        ; R2 := 0xae91e43b
 12 [-]: LOADK     R3 K2        ; R3 := "LunaroReticle.gotoAndStop"
 13 [-]: LOADK     R4 K4        ; R4 := "Dispossession"
 14 [-]: CALL      R1 4 1       ; R1(R2,R3,R4)
 15 [-]: RETURN    R0 1         ; return 


; Function #25:
;
; Name:            
; Defined at line: 470
; #Upvalues:       1
; #Parameters:     0
; Is_vararg:       0
; Max Stack Size:  2

  1 [-]: GETUPVAL  R0 U0        ; R0 := U0
  2 [-]: RETURN    R0 2         ; return R0
  3 [-]: RETURN    R0 1         ; return 


; Function #26:
;
; Name:            
; Defined at line: 474
; #Upvalues:       0
; #Parameters:     1
; Is_vararg:       0
; Max Stack Size:  9

  1 [-]: GETGLOBAL R1 K0        ; R1 := 0x7b998233
  2 [-]: MOVE      R2 R0        ; R2 := R0
  3 [-]: CALL      R1 2 2       ; R1 := R1(R2)
  4 [-]: TEST      R1 0         ; if not R1 then PC := 7
  5 [-]: JMP       7            ; PC := 7
  6 [-]: RETURN    R0 1         ; return 
  7 [-]: GETGLOBAL R1 K1        ; R1 := 0x5bced4c4
  8 [-]: GETTABLE  R1 R1 K2     ; R1 := R1[0x55f27c30]
  9 [-]: DIV       R2 R0 K3     ; R2 := R0 / 60.000000
 10 [-]: CALL      R1 2 2       ; R1 := R1(R2)
 11 [-]: GETGLOBAL R2 K1        ; R2 := 0x5bced4c4
 12 [-]: GETTABLE  R2 R2 K4     ; R2 := R2[0x99675e23]
 13 [-]: GETGLOBAL R3 K1        ; R3 := 0x5bced4c4
 14 [-]: GETTABLE  R3 R3 K5     ; R3 := R3[0x71e5d13c]
 15 [-]: MOVE      R4 R0        ; R4 := R0
 16 [-]: CONST     R5 60        ; R5 := 60.000000
 17 [-]: CALL      R3 3 0       ; R3,... := R3(R4,R5)
 18 [-]: CALL      R2 0 2       ; R2 := R2(R3,...)
 19 [-]: GETGLOBAL R3 K6        ; R3 := 0x7f5022cf
 20 [-]: GETTABLE  R3 R3 K7     ; R3 := R3[0xe8072ded]
 21 [-]: LOADK     R4 K8        ; R4 := "%01.0f:%02.0f"
 22 [-]: MOVE      R5 R1        ; R5 := R1
 23 [-]: MOVE      R6 R2        ; R6 := R2
 24 [-]: CALL      R3 4 2       ; R3 := R3(R4,R5,R6)
 25 [-]: GETGLOBAL R4 K9        ; R4 := 0xae91e43b
 26 [-]: SELF      R4 R4 K10    ; R5 := R4; R4 := R4[0x5f56eeab]
 27 [-]: LOADK     R6 K11       ; R6 := "Scoreboard.Time.Text"
 28 [-]: CONST     R7 29        ; R7 := 29.000000
 29 [-]: MOVE      R8 R3        ; R8 := R3
 30 [-]: CALL      R4 5 1       ; R4(R5,R6,R7,R8)
 31 [-]: RETURN    R0 1         ; return 


; Function #27:
;
; Name:            
; Defined at line: 485
; #Upvalues:       22
; #Parameters:     0
; Is_vararg:       0
; Max Stack Size:  7

  1 [-]: GETGLOBAL R0 K0        ; R0 := _T
  2 [-]: SETTABLE  R0 K1 K2     ; R0["DisableMiniMap"] := true
  3 [-]: GETGLOBAL R0 K0        ; R0 := _T
  4 [-]: GETTABLE  R0 R0 K3     ; R0 := R0[0xf6b77431]
  5 [-]: CALL      R0 1 2       ; R0 := R0()
  6 [-]: SETUPVAL  R0 U0        ; U82 := R0
  7 [-]: GETUPVAL  R0 U0        ; R0 := U0
  8 [-]: SELF      R0 R0 K4     ; R1 := R0; R0 := R0[0x20ff29f7]
  9 [-]: GETGLOBAL R2 K5        ; R2 := 0xae91e43b
 10 [-]: LOADK     R3 K6        ; R3 := "Scoreboard"
 11 [-]: NEWTABLE  R4 2 0       ; R4 := {}
 12 [-]: GETUPVAL  R5 U0        ; R5 := U0
 13 [-]: GETTABLE  R5 R5 K7     ; R5 := R5["ANCHOR_V_TOP"]
 14 [-]: GETUPVAL  R6 U0        ; R6 := U0
 15 [-]: GETTABLE  R6 R6 K8     ; R6 := R6["ANCHOR_H_CENTRE"]
 16 [-]: SETLIST   R4 2 1       ; R4[(1-1)*FPF+i] := R(4+i), 1 <= i <= 2
 17 [-]: CALL      R0 5 1       ; R0(R1,R2,R3,R4)
 18 [-]: GETUPVAL  R0 U0        ; R0 := U0
 19 [-]: SELF      R0 R0 K4     ; R1 := R0; R0 := R0[0x20ff29f7]
 20 [-]: GETGLOBAL R2 K5        ; R2 := 0xae91e43b
 21 [-]: LOADK     R3 K9        ; R3 := "Countdown"
 22 [-]: NEWTABLE  R4 2 0       ; R4 := {}
 23 [-]: GETUPVAL  R5 U0        ; R5 := U0
 24 [-]: GETTABLE  R5 R5 K7     ; R5 := R5["ANCHOR_V_TOP"]
 25 [-]: GETUPVAL  R6 U0        ; R6 := U0
 26 [-]: GETTABLE  R6 R6 K8     ; R6 := R6["ANCHOR_H_CENTRE"]
 27 [-]: SETLIST   R4 2 1       ; R4[(1-1)*FPF+i] := R(4+i), 1 <= i <= 2
 28 [-]: CALL      R0 5 1       ; R0(R1,R2,R3,R4)
 29 [-]: GETUPVAL  R0 U0        ; R0 := U0
 30 [-]: SELF      R0 R0 K4     ; R1 := R0; R0 := R0[0x20ff29f7]
 31 [-]: GETGLOBAL R2 K5        ; R2 := 0xae91e43b
 32 [-]: LOADK     R3 K10       ; R3 := "LunaroReticle"
 33 [-]: NEWTABLE  R4 2 0       ; R4 := {}
 34 [-]: GETUPVAL  R5 U0        ; R5 := U0
 35 [-]: GETTABLE  R5 R5 K11    ; R5 := R5["ANCHOR_V_CENTRE"]
 36 [-]: GETUPVAL  R6 U0        ; R6 := U0
 37 [-]: GETTABLE  R6 R6 K8     ; R6 := R6["ANCHOR_H_CENTRE"]
 38 [-]: SETLIST   R4 2 1       ; R4[(1-1)*FPF+i] := R(4+i), 1 <= i <= 2
 39 [-]: CALL      R0 5 1       ; R0(R1,R2,R3,R4)
 40 [-]: GETUPVAL  R0 U0        ; R0 := U0
 41 [-]: SELF      R0 R0 K4     ; R1 := R0; R0 := R0[0x20ff29f7]
 42 [-]: GETGLOBAL R2 K5        ; R2 := 0xae91e43b
 43 [-]: LOADK     R3 K12       ; R3 := "GoalScoreReplayTarget"
 44 [-]: NEWTABLE  R4 2 0       ; R4 := {}
 45 [-]: GETUPVAL  R5 U0        ; R5 := U0
 46 [-]: GETTABLE  R5 R5 K13    ; R5 := R5["ANCHOR_V_BOTTOM"]
 47 [-]: GETUPVAL  R6 U0        ; R6 := U0
 48 [-]: GETTABLE  R6 R6 K8     ; R6 := R6["ANCHOR_H_CENTRE"]
 49 [-]: SETLIST   R4 2 1       ; R4[(1-1)*FPF+i] := R(4+i), 1 <= i <= 2
 50 [-]: CALL      R0 5 1       ; R0(R1,R2,R3,R4)
 51 [-]: GETUPVAL  R0 U0        ; R0 := U0
 52 [-]: SELF      R0 R0 K4     ; R1 := R0; R0 := R0[0x20ff29f7]
 53 [-]: GETGLOBAL R2 K5        ; R2 := 0xae91e43b
 54 [-]: LOADK     R3 K14       ; R3 := "ClearZone"
 55 [-]: NEWTABLE  R4 2 0       ; R4 := {}
 56 [-]: GETUPVAL  R5 U0        ; R5 := U0
 57 [-]: GETTABLE  R5 R5 K11    ; R5 := R5["ANCHOR_V_CENTRE"]
 58 [-]: GETUPVAL  R6 U0        ; R6 := U0
 59 [-]: GETTABLE  R6 R6 K8     ; R6 := R6["ANCHOR_H_CENTRE"]
 60 [-]: SETLIST   R4 2 1       ; R4[(1-1)*FPF+i] := R(4+i), 1 <= i <= 2
 61 [-]: CALL      R0 5 1       ; R0(R1,R2,R3,R4)
 62 [-]: GETUPVAL  R0 U0        ; R0 := U0
 63 [-]: SELF      R0 R0 K15    ; R1 := R0; R0 := R0[0xfaa69527]
 64 [-]: GETGLOBAL R2 K5        ; R2 := 0xae91e43b
 65 [-]: SELF      R2 R2 K16    ; R3 := R2; R2 := R2[0x6b837788]
 66 [-]: CALL      R2 2 2       ; R2 := R2(R3)
 67 [-]: GETGLOBAL R3 K5        ; R3 := 0xae91e43b
 68 [-]: SELF      R3 R3 K17    ; R4 := R3; R3 := R3[0xaf9fda9f]
 69 [-]: CALL      R3 2 2       ; R3 := R3(R4)
 70 [-]: LOADKB    R4 1 0       ; R4 := true
 71 [-]: GETUPVAL  R5 U0        ; R5 := U0
 72 [-]: GETTABLE  R5 R5 K18    ; R5 := R5["mHudScalePadding"]
 73 [-]: CALL      R0 6 1       ; R0(R1,R2,R3,R4,R5)
 74 [-]: GETGLOBAL R0 K19       ; R0 := 0x76ea806b
 75 [-]: SELF      R0 R0 K20    ; R1 := R0; R0 := R0[0x8792aaab]
 76 [-]: CALL      R0 2 2       ; R0 := R0(R1)
 77 [-]: TEST      R0 0         ; if not R0 then PC := 88
 78 [-]: JMP       88           ; PC := 88
 79 [-]: GETGLOBAL R0 K21       ; R0 := 0x11a19c5e
 80 [-]: GETGLOBAL R1 K19       ; R1 := 0x76ea806b
 81 [-]: SELF      R1 R1 K22    ; R2 := R1; R1 := R1[0x3f3ae64c]
 82 [-]: CONST     R3 0         ; R3 := 0.000000
 83 [-]: CALL      R1 3 2       ; R1 := R1(R2,R3)
 84 [-]: SELF      R1 R1 K23    ; R2 := R1; R1 := R1[0x80563238]
 85 [-]: CALL      R1 2 2       ; R1 := R1(R2)
 86 [-]: LOADK     R2 K24       ; R2 := "OnProfileSaved"
 87 [-]: CALL      R0 3 1       ; R0(R1,R2)
 88 [-]: GETGLOBAL R0 K25       ; R0 := 0x67513231
 89 [-]: CALL      R0 1 2       ; R0 := R0()
 90 [-]: SELF      R0 R0 K26    ; R1 := R0; R0 := R0[0x6d604ba7]
 91 [-]: CALL      R0 2 2       ; R0 := R0(R1)
 92 [-]: LOADK     R1 K27       ; R1 := "Lunaro"
 93 [-]: EQ        0 R0 K28     ; if R0 ~= "_ko" then PC := 97
 94 [-]: JMP       97           ; PC := 97
 95 [-]: LOADK     R1 K29       ; R1 := "Korean"
 96 [-]: JMP       108          ; PC := 108
 97 [-]: EQ        0 R0 K30     ; if R0 ~= "_ru" then PC := 101
 98 [-]: JMP       101          ; PC := 101
 99 [-]: LOADK     R1 K31       ; R1 := "Russian"
100 [-]: JMP       108          ; PC := 108
101 [-]: EQ        0 R0 K32     ; if R0 ~= "_zh" then PC := 105
102 [-]: JMP       105          ; PC := 105
103 [-]: LOADK     R1 K33       ; R1 := "Chinese"
104 [-]: JMP       108          ; PC := 108
105 [-]: EQ        0 R0 K34     ; if R0 ~= "_tc" then PC := 108
106 [-]: JMP       108          ; PC := 108
107 [-]: LOADK     R1 K35       ; R1 := "ChineseTrad"
108 [-]: GETGLOBAL R2 K36       ; R2 := 0x38f10e85
109 [-]: GETGLOBAL R3 K5        ; R3 := 0xae91e43b
110 [-]: LOADK     R4 K37       ; R4 := "Countdown.Time.LunaroText.gotoAndStop"
111 [-]: MOVE      R5 R1        ; R5 := R1
112 [-]: CALL      R2 4 1       ; R2(R3,R4,R5)
113 [-]: LOADK     R2 K38       ; R2 := "<p><font color=\"%s\">%s</font><font color=\"#FFFFFF\">-</font><font color=\"%s\">%s</font></p>"
114 [-]: SETUPVAL  R2 U1        ; U82 := R1
115 [-]: GETGLOBAL R2 K5        ; R2 := 0xae91e43b
116 [-]: SELF      R2 R2 K39    ; R3 := R2; R2 := R2[0x5f56eeab]
117 [-]: LOADK     R4 K40       ; R4 := "Scoreboard.Score.Score"
118 [-]: CONST     R5 29        ; R5 := 29.000000
119 [-]: LOADK     R6 K41       ; R6 := "-"
120 [-]: CALL      R2 5 1       ; R2(R3,R4,R5,R6)
121 [-]: GETGLOBAL R2 K0        ; R2 := _T
122 [-]: CLOSURE   R3 0         ; R3 := closure(Function #27.1)
123 [-]: GETUPVAL  R0 U2        ; R0 := U2
124 [-]: GETUPVAL  R0 U3        ; R0 := U3
125 [-]: SETTABLE  R2 K42 R3    ; R2["LunaroHud_SetTeamInfo"] := R3
126 [-]: GETGLOBAL R2 K0        ; R2 := _T
127 [-]: CLOSURE   R3 1         ; R3 := closure(Function #27.2)
128 [-]: GETUPVAL  R0 U2        ; R0 := U2
129 [-]: GETUPVAL  R0 U4        ; R0 := U4
130 [-]: SETTABLE  R2 K43 R3    ; R2["LunaroHud_SetScoreVisible"] := R3
131 [-]: GETGLOBAL R2 K0        ; R2 := _T
132 [-]: CLOSURE   R3 2         ; R3 := closure(Function #27.3)
133 [-]: GETUPVAL  R0 U2        ; R0 := U2
134 [-]: GETUPVAL  R0 U5        ; R0 := U5
135 [-]: SETTABLE  R2 K44 R3    ; R2["LunaroHud_SetScore"] := R3
136 [-]: GETGLOBAL R2 K0        ; R2 := _T
137 [-]: CLOSURE   R3 3         ; R3 := closure(Function #27.4)
138 [-]: GETUPVAL  R0 U2        ; R0 := U2
139 [-]: GETUPVAL  R0 U6        ; R0 := U6
140 [-]: SETTABLE  R2 K45 R3    ; R2["LunaroHud_SetPeriodText"] := R3
141 [-]: GETGLOBAL R2 K0        ; R2 := _T
142 [-]: CLOSURE   R3 4         ; R3 := closure(Function #27.5)
143 [-]: GETUPVAL  R0 U2        ; R0 := U2
144 [-]: GETUPVAL  R0 U7        ; R0 := U7
145 [-]: SETTABLE  R2 K46 R3    ; R2["LunaroHud_SetPeriodTextSpacing"] := R3
146 [-]: GETGLOBAL R2 K0        ; R2 := _T
147 [-]: CLOSURE   R3 5         ; R3 := closure(Function #27.6)
148 [-]: GETUPVAL  R0 U2        ; R0 := U2
149 [-]: GETUPVAL  R0 U8        ; R0 := U8
150 [-]: SETTABLE  R2 K47 R3    ; R2["LunaroHud_ShowScoreCelebration"] := R3
151 [-]: GETGLOBAL R2 K0        ; R2 := _T
152 [-]: CLOSURE   R3 6         ; R3 := closure(Function #27.7)
153 [-]: GETUPVAL  R0 U2        ; R0 := U2
154 [-]: GETUPVAL  R0 U9        ; R0 := U9
155 [-]: SETTABLE  R2 K48 R3    ; R2["LunaroHud_ShowStartingCountdown"] := R3
156 [-]: GETGLOBAL R2 K0        ; R2 := _T
157 [-]: CLOSURE   R3 7         ; R3 := closure(Function #27.8)
158 [-]: GETUPVAL  R0 U2        ; R0 := U2
159 [-]: GETUPVAL  R0 U10       ; R0 := U10
160 [-]: SETTABLE  R2 K49 R3    ; R2["LunaroHud_ShowHalftimeCountdown"] := R3
161 [-]: GETGLOBAL R2 K0        ; R2 := _T
162 [-]: CLOSURE   R3 8         ; R3 := closure(Function #27.9)
163 [-]: GETUPVAL  R0 U2        ; R0 := U2
164 [-]: GETUPVAL  R0 U11       ; R0 := U11
165 [-]: SETTABLE  R2 K50 R3    ; R2["LunaroHud_StopCountdown"] := R3
166 [-]: GETGLOBAL R2 K0        ; R2 := _T
167 [-]: CLOSURE   R3 9         ; R3 := closure(Function #27.10)
168 [-]: GETUPVAL  R0 U2        ; R0 := U2
169 [-]: GETUPVAL  R0 U12       ; R0 := U12
170 [-]: SETTABLE  R2 K51 R3    ; R2["LunaroHud_ResumeCountdown"] := R3
171 [-]: GETGLOBAL R2 K0        ; R2 := _T
172 [-]: CLOSURE   R3 10        ; R3 := closure(Function #27.11)
173 [-]: GETUPVAL  R0 U2        ; R0 := U2
174 [-]: GETUPVAL  R0 U13       ; R0 := U13
175 [-]: SETTABLE  R2 K52 R3    ; R2["LunaroHud_ShowMessage"] := R3
176 [-]: GETGLOBAL R2 K0        ; R2 := _T
177 [-]: CLOSURE   R3 11        ; R3 := closure(Function #27.12)
178 [-]: GETUPVAL  R0 U2        ; R0 := U2
179 [-]: GETUPVAL  R0 U14       ; R0 := U14
180 [-]: SETTABLE  R2 K53 R3    ; R2["LunaroHud_HideMessage"] := R3
181 [-]: GETGLOBAL R2 K0        ; R2 := _T
182 [-]: CLOSURE   R3 12        ; R3 := closure(Function #27.13)
183 [-]: GETUPVAL  R0 U2        ; R0 := U2
184 [-]: GETUPVAL  R0 U15       ; R0 := U15
185 [-]: SETTABLE  R2 K54 R3    ; R2["LunaroHud_SetPossession"] := R3
186 [-]: GETGLOBAL R2 K0        ; R2 := _T
187 [-]: CLOSURE   R3 13        ; R3 := closure(Function #27.14)
188 [-]: GETUPVAL  R0 U2        ; R0 := U2
189 [-]: GETUPVAL  R0 U16       ; R0 := U16
190 [-]: SETTABLE  R2 K55 R3    ; R2["LunaroHud_HideMissionTimer"] := R3
191 [-]: GETGLOBAL R2 K0        ; R2 := _T
192 [-]: CLOSURE   R3 14        ; R3 := closure(Function #27.15)
193 [-]: GETUPVAL  R0 U2        ; R0 := U2
194 [-]: GETUPVAL  R0 U17       ; R0 := U17
195 [-]: SETTABLE  R2 K56 R3    ; R2["LunaroHud_SetPossessionReticle"] := R3
196 [-]: GETGLOBAL R2 K0        ; R2 := _T
197 [-]: GETUPVAL  R3 U18       ; R3 := U18
198 [-]: SETTABLE  R2 K57 R3    ; R2["LunaroHud_GetPossessionReticle"] := R3
199 [-]: GETGLOBAL R2 K0        ; R2 := _T
200 [-]: CLOSURE   R3 15        ; R3 := closure(Function #27.16)
201 [-]: GETUPVAL  R0 U2        ; R0 := U2
202 [-]: GETUPVAL  R0 U19       ; R0 := U19
203 [-]: SETTABLE  R2 K58 R3    ; R2["LunaroHud_SetTime"] := R3
204 [-]: GETGLOBAL R2 K5        ; R2 := 0xae91e43b
205 [-]: SELF      R2 R2 K59    ; R3 := R2; R2 := R2[0x67bc869f]
206 [-]: LOADK     R4 K60       ; R4 := "GoalCelebration"
207 [-]: CONST     R5 10        ; R5 := 10.000000
208 [-]: CONST     R6 0         ; R6 := 0.000000
209 [-]: CALL      R2 5 1       ; R2(R3,R4,R5,R6)
210 [-]: GETGLOBAL R2 K5        ; R2 := 0xae91e43b
211 [-]: SELF      R2 R2 K59    ; R3 := R2; R2 := R2[0x67bc869f]
212 [-]: LOADK     R4 K6        ; R4 := "Scoreboard"
213 [-]: CONST     R5 10        ; R5 := 10.000000
214 [-]: CONST     R6 0         ; R6 := 0.000000
215 [-]: CALL      R2 5 1       ; R2(R3,R4,R5,R6)
216 [-]: GETGLOBAL R2 K5        ; R2 := 0xae91e43b
217 [-]: SELF      R2 R2 K59    ; R3 := R2; R2 := R2[0x67bc869f]
218 [-]: LOADK     R4 K9        ; R4 := "Countdown"
219 [-]: CONST     R5 10        ; R5 := 10.000000
220 [-]: CONST     R6 0         ; R6 := 0.000000
221 [-]: CALL      R2 5 1       ; R2(R3,R4,R5,R6)
222 [-]: GETGLOBAL R2 K5        ; R2 := 0xae91e43b
223 [-]: SELF      R2 R2 K59    ; R3 := R2; R2 := R2[0x67bc869f]
224 [-]: LOADK     R4 K61       ; R4 := "ActionNotification"
225 [-]: CONST     R5 10        ; R5 := 10.000000
226 [-]: CONST     R6 0         ; R6 := 0.000000
227 [-]: CALL      R2 5 1       ; R2(R3,R4,R5,R6)
228 [-]: GETGLOBAL R2 K5        ; R2 := 0xae91e43b
229 [-]: SELF      R2 R2 K59    ; R3 := R2; R2 := R2[0x67bc869f]
230 [-]: LOADK     R4 K14       ; R4 := "ClearZone"
231 [-]: CONST     R5 10        ; R5 := 10.000000
232 [-]: CONST     R6 0         ; R6 := 0.000000
233 [-]: CALL      R2 5 1       ; R2(R3,R4,R5,R6)
234 [-]: GETGLOBAL R2 K36       ; R2 := 0x38f10e85
235 [-]: GETGLOBAL R3 K5        ; R3 := 0xae91e43b
236 [-]: LOADK     R4 K62       ; R4 := "Countdown.Time.gotoAndStop"
237 [-]: LOADK     R5 K63       ; R5 := "HalfTimeCountdown"
238 [-]: CALL      R2 4 1       ; R2(R3,R4,R5)
239 [-]: GETGLOBAL R2 K5        ; R2 := 0xae91e43b
240 [-]: SELF      R2 R2 K64    ; R3 := R2; R2 := R2[0x5ee2cc30]
241 [-]: LOADK     R4 K65       ; R4 := "Countdown.Time"
242 [-]: LOADK     R5 K66       ; R5 := "OnCountdownFrame"
243 [-]: CALL      R2 4 1       ; R2(R3,R4,R5)
244 [-]: CLOSURE   R2 16        ; R2 := closure(Function #27.17)
245 [-]: GETUPVAL  R0 U15       ; R0 := U15
246 [-]: GETUPVAL  R3 U20       ; R3 := U20
247 [-]: CALL      R3 1 1       ; R3()
248 [-]: LOADKB    R3 1 0       ; R3 := true
249 [-]: SETUPVAL  R3 U21       ; U82 := R21
250 [-]: RETURN    R0 1         ; return 


; Function #27.1:
;
; Name:            
; Defined at line: 517
; #Upvalues:       2
; #Parameters:     0
; Is_vararg:       3
; Max Stack Size:  4

  1 [-]: GETUPVAL  R1 U0        ; R1 := U0
  2 [-]: GETUPVAL  R2 U1        ; R2 := U1
  3 [-]: VARARG    R3 0         ; R3 := ...
  4 [-]: CALL      R1 0 1       ; R1(R2,...)
  5 [-]: RETURN    R0 1         ; return 


; Function #27.2:
;
; Name:            
; Defined at line: 518
; #Upvalues:       2
; #Parameters:     0
; Is_vararg:       3
; Max Stack Size:  4

  1 [-]: GETUPVAL  R1 U0        ; R1 := U0
  2 [-]: GETUPVAL  R2 U1        ; R2 := U1
  3 [-]: VARARG    R3 0         ; R3 := ...
  4 [-]: CALL      R1 0 1       ; R1(R2,...)
  5 [-]: RETURN    R0 1         ; return 


; Function #27.3:
;
; Name:            
; Defined at line: 519
; #Upvalues:       2
; #Parameters:     0
; Is_vararg:       3
; Max Stack Size:  4

  1 [-]: GETUPVAL  R1 U0        ; R1 := U0
  2 [-]: GETUPVAL  R2 U1        ; R2 := U1
  3 [-]: VARARG    R3 0         ; R3 := ...
  4 [-]: CALL      R1 0 1       ; R1(R2,...)
  5 [-]: RETURN    R0 1         ; return 


; Function #27.4:
;
; Name:            
; Defined at line: 520
; #Upvalues:       2
; #Parameters:     0
; Is_vararg:       3
; Max Stack Size:  4

  1 [-]: GETUPVAL  R1 U0        ; R1 := U0
  2 [-]: GETUPVAL  R2 U1        ; R2 := U1
  3 [-]: VARARG    R3 0         ; R3 := ...
  4 [-]: CALL      R1 0 1       ; R1(R2,...)
  5 [-]: RETURN    R0 1         ; return 


; Function #27.5:
;
; Name:            
; Defined at line: 521
; #Upvalues:       2
; #Parameters:     0
; Is_vararg:       3
; Max Stack Size:  4

  1 [-]: GETUPVAL  R1 U0        ; R1 := U0
  2 [-]: GETUPVAL  R2 U1        ; R2 := U1
  3 [-]: VARARG    R3 0         ; R3 := ...
  4 [-]: CALL      R1 0 1       ; R1(R2,...)
  5 [-]: RETURN    R0 1         ; return 


; Function #27.6:
;
; Name:            
; Defined at line: 522
; #Upvalues:       2
; #Parameters:     0
; Is_vararg:       3
; Max Stack Size:  4

  1 [-]: GETUPVAL  R1 U0        ; R1 := U0
  2 [-]: GETUPVAL  R2 U1        ; R2 := U1
  3 [-]: VARARG    R3 0         ; R3 := ...
  4 [-]: CALL      R1 0 1       ; R1(R2,...)
  5 [-]: RETURN    R0 1         ; return 


; Function #27.7:
;
; Name:            
; Defined at line: 523
; #Upvalues:       2
; #Parameters:     0
; Is_vararg:       3
; Max Stack Size:  4

  1 [-]: GETUPVAL  R1 U0        ; R1 := U0
  2 [-]: GETUPVAL  R2 U1        ; R2 := U1
  3 [-]: VARARG    R3 0         ; R3 := ...
  4 [-]: CALL      R1 0 1       ; R1(R2,...)
  5 [-]: RETURN    R0 1         ; return 


; Function #27.8:
;
; Name:            
; Defined at line: 524
; #Upvalues:       2
; #Parameters:     0
; Is_vararg:       3
; Max Stack Size:  4

  1 [-]: GETUPVAL  R1 U0        ; R1 := U0
  2 [-]: GETUPVAL  R2 U1        ; R2 := U1
  3 [-]: VARARG    R3 0         ; R3 := ...
  4 [-]: CALL      R1 0 1       ; R1(R2,...)
  5 [-]: RETURN    R0 1         ; return 


; Function #27.9:
;
; Name:            
; Defined at line: 525
; #Upvalues:       2
; #Parameters:     0
; Is_vararg:       3
; Max Stack Size:  4

  1 [-]: GETUPVAL  R1 U0        ; R1 := U0
  2 [-]: GETUPVAL  R2 U1        ; R2 := U1
  3 [-]: VARARG    R3 0         ; R3 := ...
  4 [-]: CALL      R1 0 1       ; R1(R2,...)
  5 [-]: RETURN    R0 1         ; return 


; Function #27.10:
;
; Name:            
; Defined at line: 526
; #Upvalues:       2
; #Parameters:     0
; Is_vararg:       3
; Max Stack Size:  4

  1 [-]: GETUPVAL  R1 U0        ; R1 := U0
  2 [-]: GETUPVAL  R2 U1        ; R2 := U1
  3 [-]: VARARG    R3 0         ; R3 := ...
  4 [-]: CALL      R1 0 1       ; R1(R2,...)
  5 [-]: RETURN    R0 1         ; return 


; Function #27.11:
;
; Name:            
; Defined at line: 527
; #Upvalues:       2
; #Parameters:     0
; Is_vararg:       3
; Max Stack Size:  4

  1 [-]: GETUPVAL  R1 U0        ; R1 := U0
  2 [-]: GETUPVAL  R2 U1        ; R2 := U1
  3 [-]: VARARG    R3 0         ; R3 := ...
  4 [-]: CALL      R1 0 1       ; R1(R2,...)
  5 [-]: RETURN    R0 1         ; return 


; Function #27.12:
;
; Name:            
; Defined at line: 528
; #Upvalues:       2
; #Parameters:     0
; Is_vararg:       3
; Max Stack Size:  4

  1 [-]: GETUPVAL  R1 U0        ; R1 := U0
  2 [-]: GETUPVAL  R2 U1        ; R2 := U1
  3 [-]: VARARG    R3 0         ; R3 := ...
  4 [-]: CALL      R1 0 1       ; R1(R2,...)
  5 [-]: RETURN    R0 1         ; return 


; Function #27.13:
;
; Name:            
; Defined at line: 529
; #Upvalues:       2
; #Parameters:     0
; Is_vararg:       3
; Max Stack Size:  4

  1 [-]: GETUPVAL  R1 U0        ; R1 := U0
  2 [-]: GETUPVAL  R2 U1        ; R2 := U1
  3 [-]: VARARG    R3 0         ; R3 := ...
  4 [-]: CALL      R1 0 1       ; R1(R2,...)
  5 [-]: RETURN    R0 1         ; return 


; Function #27.14:
;
; Name:            
; Defined at line: 530
; #Upvalues:       2
; #Parameters:     0
; Is_vararg:       3
; Max Stack Size:  4

  1 [-]: GETUPVAL  R1 U0        ; R1 := U0
  2 [-]: GETUPVAL  R2 U1        ; R2 := U1
  3 [-]: VARARG    R3 0         ; R3 := ...
  4 [-]: CALL      R1 0 1       ; R1(R2,...)
  5 [-]: RETURN    R0 1         ; return 


; Function #27.15:
;
; Name:            
; Defined at line: 531
; #Upvalues:       2
; #Parameters:     0
; Is_vararg:       3
; Max Stack Size:  4

  1 [-]: GETUPVAL  R1 U0        ; R1 := U0
  2 [-]: GETUPVAL  R2 U1        ; R2 := U1
  3 [-]: VARARG    R3 0         ; R3 := ...
  4 [-]: CALL      R1 0 1       ; R1(R2,...)
  5 [-]: RETURN    R0 1         ; return 


; Function #27.16:
;
; Name:            
; Defined at line: 533
; #Upvalues:       2
; #Parameters:     0
; Is_vararg:       3
; Max Stack Size:  4

  1 [-]: GETUPVAL  R1 U0        ; R1 := U0
  2 [-]: GETUPVAL  R2 U1        ; R2 := U1
  3 [-]: VARARG    R3 0         ; R3 := ...
  4 [-]: CALL      R1 0 1       ; R1(R2,...)
  5 [-]: RETURN    R0 1         ; return 


; Function #27.17:
;
; Name:            
; Defined at line: 548
; #Upvalues:       1
; #Parameters:     1
; Is_vararg:       0
; Max Stack Size:  10

  1 [-]: GETGLOBAL R1 K0        ; R1 := 0x25312c9b
  2 [-]: GETGLOBAL R2 K1        ; R2 := 0xae91e43b
  3 [-]: LOADK     R3 K2        ; R3 := "_root"
  4 [-]: CONST     R4 0         ; R4 := 0.000000
  5 [-]: NEWTABLE  R5 1 0       ; R5 := {}
  6 [-]: CONST     R6 0         ; R6 := 0.000000
  7 [-]: SETLIST   R5 1 1       ; R5[(1-1)*FPF+i] := R(5+i), 1 <= i <= 1
  8 [-]: NEWTABLE  R6 1 0       ; R6 := {}
  9 [-]: CONST     R7 0         ; R7 := 0.000000
 10 [-]: SETLIST   R6 1 1       ; R6[(1-1)*FPF+i] := R(6+i), 1 <= i <= 1
 11 [-]: CONST     R7 5         ; R7 := 5.000000
 12 [-]: CONST     R8 0         ; R8 := 0.000000
 13 [-]: CLOSURE   R9 0         ; R9 := closure(Function #27.17.1)
 14 [-]: GETUPVAL  R0 U0        ; R0 := U0
 15 [-]: MOVE      R0 R0        ; R0 := R0
 16 [-]: CALL      R1 9 1       ; R1(R2,R3,R4,R5,R6,R7,R8,R9)
 17 [-]: RETURN    R0 1         ; return 


; Function #27.17.1:
;
; Name:            
; Defined at line: 550
; #Upvalues:       2
; #Parameters:     0
; Is_vararg:       0
; Max Stack Size:  9

  1 [-]: GETUPVAL  R0 U0        ; R0 := U0
  2 [-]: CONST     R1 1         ; R1 := 1.000000
  3 [-]: CALL      R0 2 1       ; R0(R1)
  4 [-]: GETGLOBAL R0 K0        ; R0 := 0x25312c9b
  5 [-]: GETGLOBAL R1 K1        ; R1 := 0xae91e43b
  6 [-]: LOADK     R2 K2        ; R2 := "_root"
  7 [-]: CONST     R3 0         ; R3 := 0.000000
  8 [-]: NEWTABLE  R4 1 0       ; R4 := {}
  9 [-]: CONST     R5 0         ; R5 := 0.000000
 10 [-]: SETLIST   R4 1 1       ; R4[(1-1)*FPF+i] := R(4+i), 1 <= i <= 1
 11 [-]: NEWTABLE  R5 1 0       ; R5 := {}
 12 [-]: CONST     R6 0         ; R6 := 0.000000
 13 [-]: SETLIST   R5 1 1       ; R5[(1-1)*FPF+i] := R(5+i), 1 <= i <= 1
 14 [-]: CONST     R6 3         ; R6 := 3.000000
 15 [-]: CONST     R7 0         ; R7 := 0.000000
 16 [-]: CLOSURE   R8 0         ; R8 := closure(Function #27.17.1.1)
 17 [-]: GETUPVAL  R0 U0        ; R0 := U0
 18 [-]: GETUPVAL  R0 U1        ; R0 := U1
 19 [-]: CALL      R0 9 1       ; R0(R1,R2,R3,R4,R5,R6,R7,R8)
 20 [-]: RETURN    R0 1         ; return 


; Function #27.17.1.1:
;
; Name:            
; Defined at line: 553
; #Upvalues:       2
; #Parameters:     0
; Is_vararg:       0
; Max Stack Size:  9

  1 [-]: GETUPVAL  R0 U0        ; R0 := U0
  2 [-]: CONST     R1 2         ; R1 := 2.000000
  3 [-]: CALL      R0 2 1       ; R0(R1)
  4 [-]: GETGLOBAL R0 K0        ; R0 := 0x25312c9b
  5 [-]: GETGLOBAL R1 K1        ; R1 := 0xae91e43b
  6 [-]: LOADK     R2 K2        ; R2 := "_root"
  7 [-]: CONST     R3 0         ; R3 := 0.000000
  8 [-]: NEWTABLE  R4 1 0       ; R4 := {}
  9 [-]: CONST     R5 0         ; R5 := 0.000000
 10 [-]: SETLIST   R4 1 1       ; R4[(1-1)*FPF+i] := R(4+i), 1 <= i <= 1
 11 [-]: NEWTABLE  R5 1 0       ; R5 := {}
 12 [-]: CONST     R6 0         ; R6 := 0.000000
 13 [-]: SETLIST   R5 1 1       ; R5[(1-1)*FPF+i] := R(5+i), 1 <= i <= 1
 14 [-]: CONST     R6 3         ; R6 := 3.000000
 15 [-]: CONST     R7 0         ; R7 := 0.000000
 16 [-]: CLOSURE   R8 0         ; R8 := closure(Function #27.17.1.1.1)
 17 [-]: GETUPVAL  R0 U0        ; R0 := U0
 18 [-]: GETUPVAL  R0 U1        ; R0 := U1
 19 [-]: CALL      R0 9 1       ; R0(R1,R2,R3,R4,R5,R6,R7,R8)
 20 [-]: RETURN    R0 1         ; return 


; Function #27.17.1.1.1:
;
; Name:            
; Defined at line: 556
; #Upvalues:       2
; #Parameters:     0
; Is_vararg:       0
; Max Stack Size:  2

  1 [-]: GETUPVAL  R0 U0        ; R0 := U0
  2 [-]: LOADNIL   R1 R1        ; R1 := nil
  3 [-]: CALL      R0 2 1       ; R0(R1)
  4 [-]: GETUPVAL  R0 U1        ; R0 := U1
  5 [-]: EQ        1 R0 K0      ; if R0 == nil then PC := 10
  6 [-]: JMP       10           ; PC := 10
  7 [-]: GETUPVAL  R0 U1        ; R0 := U1
  8 [-]: GETUPVAL  R1 U1        ; R1 := U1
  9 [-]: CALL      R0 2 1       ; R0(R1)
 10 [-]: RETURN    R0 1         ; return 


; Function #28:
;
; Name:            
; Defined at line: 572
; #Upvalues:       0
; #Parameters:     2
; Is_vararg:       0
; Max Stack Size:  7

  1 [-]: EQ        0 R1 K0      ; if R1 ~= "EndCountdown" then PC := 14
  2 [-]: JMP       14           ; PC := 14
  3 [-]: GETGLOBAL R2 K1        ; R2 := 0xae91e43b
  4 [-]: SELF      R2 R2 K2     ; R3 := R2; R2 := R2[0x67bc869f]
  5 [-]: LOADK     R4 K3        ; R4 := "Countdown"
  6 [-]: CONST     R5 10        ; R5 := 10.000000
  7 [-]: CONST     R6 0         ; R6 := 0.000000
  8 [-]: CALL      R2 5 1       ; R2(R3,R4,R5,R6)
  9 [-]: GETGLOBAL R2 K4        ; R2 := 0x38f10e85
 10 [-]: GETGLOBAL R3 K1        ; R3 := 0xae91e43b
 11 [-]: LOADK     R4 K5        ; R4 := "Countdown.Time.gotoAndStop"
 12 [-]: LOADK     R5 K6        ; R5 := "HalfTimeCountdown"
 13 [-]: CALL      R2 4 1       ; R2(R3,R4,R5)
 14 [-]: RETURN    R0 1         ; return 


