; Name:            
; Defined at line: 1
; #Upvalues:       0
; #Parameters:     0
; Is_vararg:       1
; Max Stack Size:  26

            1 [-]: GETIMPORT R0 1 [nil]
       2 [-]: LOADK R1 K2 ["EE.Interface.Utilities"]
       3 [-]: CALL R0 1 1  
       4 [-]: GETIMPORT R1 1 [nil]
       5 [-]: LOADK R2 K3 ["Lotus.Interface.LotusUtilities"]
       6 [-]: CALL R1 1 1  
       7 [-]: LOADB R2 0   
       8 [-]: LOADK R3 K4 [""]
       9 [-]: LOADK R4 K4 [""]
      10 [-]: LOADNIL R5   
      11 [-]: LOADB R6 0   
      12 [-]: LOADN R7 360 
      13 [-]: LOADB R8 0   
      14 [-]: LOADB R9 0   
      15 [-]: LOADB R10 0  
      16 [-]: LOADB R11 0  
      17 [-]: LOADK R12 K4 [""]
      18 [-]: LOADNIL R13  
      19 [-]: LOADB R14 0  
      20 [-]: LOADN R15 30 
      21 [-]: LOADN R16 12 
      22 [-]: LOADNIL R17  
      23 [-]: LOADNIL R18  
      24 [-]: LOADNIL R19  
      25 [-]: DUPCLOSURE R20 K5 []
      26 [-]: SETGLOBAL R20 K6 ["SetTitle"]
      27 [-]: NEWCLOSURE R20 P1
      28 [-]: MOVE R1 R3   
      29 [-]: MOVE R1 R6   
      30 [-]: NEWCLOSURE R21 P2
      31 [-]: MOVE R1 R10  
      32 [-]: MOVE R0 R0   
      33 [-]: MOVE R0 R1   
      34 [-]: NEWCLOSURE R22 P3
      35 [-]: MOVE R0 R21  
      36 [-]: MOVE R1 R10  
      37 [-]: SETGLOBAL R22 K7 ["SetVisible"]
      38 [-]: DUPCLOSURE R22 K8 []
      39 [-]: MOVE R0 R21  
      40 [-]: SETGLOBAL R22 K9 ["SetLiteMode"]
      41 [-]: NEWCLOSURE R22 P5
      42 [-]: MOVE R0 R0   
      43 [-]: MOVE R1 R10  
      44 [-]: SETGLOBAL R22 K10 ["HideBg"]
      45 [-]: DUPCLOSURE R22 K11 []
      46 [-]: MOVE R0 R0   
      47 [-]: DUPCLOSURE R23 K12 []
      48 [-]: MOVE R0 R22  
      49 [-]: NEWCLOSURE R24 P8
      50 [-]: MOVE R1 R8   
      51 [-]: MOVE R1 R9   
      52 [-]: MOVE R1 R7   
      53 [-]: SETGLOBAL R24 K13 ["SetMultilineWidth"]
      54 [-]: NEWCLOSURE R24 P9
      55 [-]: MOVE R1 R9   
      56 [-]: MOVE R1 R7   
      57 [-]: SETGLOBAL R24 K14 ["SetMultilineExpandUp"]
      58 [-]: NEWCLOSURE R19 P10
      59 [-]: MOVE R1 R17  
      60 [-]: MOVE R1 R18  
      61 [-]: MOVE R1 R4   
      62 [-]: MOVE R0 R23  
      63 [-]: MOVE R1 R3   
      64 [-]: MOVE R1 R6   
      65 [-]: MOVE R1 R15  
      66 [-]: MOVE R1 R16  
      67 [-]: MOVE R1 R8   
      68 [-]: MOVE R1 R9   
      69 [-]: MOVE R1 R7   
      70 [-]: MOVE R1 R2   
      71 [-]: NEWCLOSURE R24 P11
      72 [-]: MOVE R1 R19  
      73 [-]: SETGLOBAL R24 K15 ["SetMessage"]
      74 [-]: DUPCLOSURE R24 K16 []
      75 [-]: SETGLOBAL R24 K17 ["SetFont"]
      76 [-]: DUPCLOSURE R24 K18 []
      77 [-]: SETGLOBAL R24 K19 ["SetTextColor"]
      78 [-]: DUPCLOSURE R24 K20 []
      79 [-]: SETGLOBAL R24 K21 ["SetTextAlpha"]
      80 [-]: DUPCLOSURE R24 K22 []
      81 [-]: SETGLOBAL R24 K23 ["SetTextAlign"]
      82 [-]: DUPCLOSURE R24 K24 []
      83 [-]: SETGLOBAL R24 K25 ["SetVertexColors"]
      84 [-]: DUPCLOSURE R24 K26 []
      85 [-]: SETGLOBAL R24 K27 ["SetUserText"]
      86 [-]: DUPCLOSURE R24 K28 []
      87 [-]: SETGLOBAL R24 K29 ["SetFancyText"]
      88 [-]: NEWCLOSURE R24 P19
      89 [-]: MOVE R1 R6   
      90 [-]: MOVE R0 R0   
      91 [-]: MOVE R1 R3   
      92 [-]: SETGLOBAL R24 K30 ["SetOutOfService"]
      93 [-]: NEWCLOSURE R24 P20
      94 [-]: MOVE R1 R15  
      95 [-]: SETGLOBAL R24 K31 ["SetHorizontalPadding"]
      96 [-]: NEWCLOSURE R24 P21
      97 [-]: MOVE R1 R16  
      98 [-]: SETGLOBAL R24 K32 ["SetVerticalalPadding"]
      99 [-]: NEWCLOSURE R24 P22
     100 [-]: MOVE R1 R7   
     101 [-]: MOVE R0 R21  
     102 [-]: SETGLOBAL R24 K33 ["Initialize"]
     103 [-]: NEWCLOSURE R24 P23
     104 [-]: MOVE R1 R11  
     105 [-]: SETGLOBAL R24 K34 ["SetHiddenInBackgroundRegion"]
     106 [-]: NEWCLOSURE R24 P24
     107 [-]: MOVE R1 R12  
     108 [-]: SETGLOBAL R24 K35 ["SetComponentId"]
     109 [-]: NEWCLOSURE R24 P25
     110 [-]: MOVE R1 R12  
     111 [-]: MOVE R1 R13  
     112 [-]: MOVE R1 R14  
     113 [-]: NEWCLOSURE R25 P26
     114 [-]: MOVE R1 R11  
     115 [-]: MOVE R0 R24  
     116 [-]: MOVE R1 R5   
     117 [-]: SETGLOBAL R25 K36 ["Update"]
     118 [-]: DUPCLOSURE R25 K37 []
     119 [-]: SETGLOBAL R25 K38 ["Close"]
     120 [-]: NEWCLOSURE R25 P28
     121 [-]: MOVE R1 R19  
     122 [-]: MOVE R1 R4   
     123 [-]: SETGLOBAL R25 K39 ["IconCacheFlushed"]
     124 [-]: NEWCLOSURE R25 P29
     125 [-]: MOVE R1 R19  
     126 [-]: MOVE R1 R4   
     127 [-]: SETGLOBAL R25 K40 ["OnGamepadTransition"]
     128 [-]: DUPCLOSURE R25 K41 []
     129 [-]: SETGLOBAL R25 K42 ["DisplayInWorldText"]
     130 [-]: DUPCLOSURE R25 K43 []
     131 [-]: SETGLOBAL R25 K44 ["SetBGAlpha"]
     132 [-]: CLOSEUPVALS R2
     133 [-]: RETURN R0 0  


; Name:            
; Defined at line: 32
; #Upvalues:       0
; #Parameters:     1
; Is_vararg:       0
; Max Stack Size:  1

       0 [-]: RETURN R0 0  


; Name:            
; Defined at line: 35
; #Upvalues:       2
; #Parameters:     0
; Is_vararg:       0
; Max Stack Size:  6

       0 [-]: GETUPVAL R0 0
       1 [-]: GETUPVAL R1 1
       2 [-]: JUMPIFNOT R1 L0
       3 [-]: LOADK R1 K0 ["<p><font color=\"#444444\">"]
       4 [-]: MOVE R2 R0   
       5 [-]: LOADK R3 K1 ["</font></p>"]
       6 [-]: CONCAT R0 R1 R3
L 0:   7 [-]: GETIMPORT R1 3 [nil]
       8 [-]: LOADK R3 K4 ["Panel.Instruction"]
       9 [-]: LOADN R4 29  
      10 [-]: MOVE R5 R0   
      11 [-]: NAMECALL R1 R1 K5 [0x5F56EEAB]
      12 [-]: CALL R1 4 0  
      13 [-]: RETURN R0 0  


; Name:            
; Defined at line: 43
; #Upvalues:       3
; #Parameters:     1
; Is_vararg:       0
; Max Stack Size:  9

       0 [-]: SETUPVAL R0 0
       1 [-]: GETIMPORT R1 1 [nil]
       2 [-]: LOADK R3 K2 ["Panel"]
       3 [-]: LOADN R4 5   
       4 [-]: GETUPVAL R6 1
       5 [-]: GETTABLEKS R5 R6 K3 [0x06D055F9]
       6 [-]: MOVE R6 R0   
       7 [-]: LOADN R7 100 
       8 [-]: LOADN R8 600 
       9 [-]: CALL R5 3 -1 
      10 [-]: NAMECALL R1 R1 K4 [0x67BC869F]
      11 [-]: CALL R1 -1 0 
      12 [-]: GETIMPORT R1 1 [nil]
      13 [-]: LOADK R3 K2 ["Panel"]
      14 [-]: LOADN R4 6   
      15 [-]: GETUPVAL R6 1
      16 [-]: GETTABLEKS R5 R6 K3 [0x06D055F9]
      17 [-]: MOVE R6 R0   
      18 [-]: LOADN R7 100 
      19 [-]: LOADN R8 600 
      20 [-]: CALL R5 3 -1 
      21 [-]: NAMECALL R1 R1 K4 [0x67BC869F]
      22 [-]: CALL R1 -1 0 
      23 [-]: GETIMPORT R1 1 [nil]
      24 [-]: LOADK R3 K2 ["Panel"]
      25 [-]: GETUPVAL R5 1
      26 [-]: GETTABLEKS R4 R5 K3 [0x06D055F9]
      27 [-]: MOVE R5 R0   
      28 [-]: LOADK R6 K5 ["Bg"]
      29 [-]: LOADK R7 K6 ["LiteBg"]
      30 [-]: CALL R4 3 1  
      31 [-]: LOADN R5 11  
      32 [-]: LOADB R6 0   
      33 [-]: NAMECALL R1 R1 K7 [0xC0A3774B]
      34 [-]: CALL R1 5 0  
      35 [-]: GETIMPORT R1 1 [nil]
      36 [-]: LOADK R3 K2 ["Panel"]
      37 [-]: GETUPVAL R5 1
      38 [-]: GETTABLEKS R4 R5 K3 [0x06D055F9]
      39 [-]: MOVE R5 R0   
      40 [-]: LOADK R6 K6 ["LiteBg"]
      41 [-]: LOADK R7 K5 ["Bg"]
      42 [-]: CALL R4 3 1  
      43 [-]: LOADN R5 11  
      44 [-]: LOADB R6 1   
      45 [-]: NAMECALL R1 R1 K7 [0xC0A3774B]
      46 [-]: CALL R1 5 0  
      47 [-]: JUMPIFNOT R0 L0
      48 [-]: GETUPVAL R2 2
      49 [-]: GETTABLEKS R1 R2 K8 [0x2A28B53A]
      50 [-]: GETIMPORT R2 1 [nil]
      51 [-]: LOADK R3 K9 ["Panel.LiteBg"]
      52 [-]: CALL R1 2 0  
      53 [-]: GETIMPORT R1 1 [nil]
      54 [-]: LOADK R3 K10 ["Panel.LiteBg.Foreground"]
      55 [-]: LOADN R4 4   
      56 [-]: LOADN R5 0   
      57 [-]: NAMECALL R1 R1 K4 [0x67BC869F]
      58 [-]: CALL R1 4 0  
      59 [-]: GETIMPORT R1 1 [nil]
      60 [-]: LOADK R3 K11 ["Panel.LiteBg.Shadow"]
      61 [-]: LOADN R4 4   
      62 [-]: LOADN R5 0   
      63 [-]: NAMECALL R1 R1 K4 [0x67BC869F]
      64 [-]: CALL R1 4 0  
      65 [-]: GETIMPORT R1 1 [nil]
      66 [-]: LOADK R3 K12 ["Panel.LiteBg.BackShadow"]
      67 [-]: LOADN R4 4   
      68 [-]: LOADN R5 0   
      69 [-]: NAMECALL R1 R1 K4 [0x67BC869F]
      70 [-]: CALL R1 4 0  
      71 [-]: GETIMPORT R1 14 [nil]
      72 [-]: GETIMPORT R2 1 [nil]
      73 [-]: LOADK R3 K12 ["Panel.LiteBg.BackShadow"]
      74 [-]: LOADN R4 8   
      75 [-]: NEWTABLE R5 0 1
      76 [-]: LOADN R6 4   
      77 [-]: SETLIST R5 R6 1 [1]
      78 [-]: NEWTABLE R6 0 1
      79 [-]: LOADN R7 400 
      80 [-]: SETLIST R6 R7 1 [1]
      81 [-]: LOADK R7 K15 [0.25]
      82 [-]: LOADK R8 K15 [0.25]
      83 [-]: CALL R1 7 0  
      84 [-]: GETIMPORT R1 14 [nil]
      85 [-]: GETIMPORT R2 1 [nil]
      86 [-]: LOADK R3 K11 ["Panel.LiteBg.Shadow"]
      87 [-]: LOADN R4 8   
      88 [-]: NEWTABLE R5 0 1
      89 [-]: LOADN R6 4   
      90 [-]: SETLIST R5 R6 1 [1]
      91 [-]: NEWTABLE R6 0 1
      92 [-]: LOADN R7 200 
      93 [-]: SETLIST R6 R7 1 [1]
      94 [-]: LOADK R7 K15 [0.25]
      95 [-]: LOADK R8 K15 [0.25]
      96 [-]: CALL R1 7 0  
      97 [-]: JUMP L1
     
L 0:  98 [-]: GETIMPORT R1 1 [nil]
      99 [-]: LOADK R3 K16 ["ControllerHolder"]
     100 [-]: LOADN R4 5   
     101 [-]: LOADN R5 600 
     102 [-]: NAMECALL R1 R1 K4 [0x67BC869F]
     103 [-]: CALL R1 4 0  
     104 [-]: GETIMPORT R1 1 [nil]
     105 [-]: LOADK R3 K16 ["ControllerHolder"]
     106 [-]: LOADN R4 6   
     107 [-]: LOADN R5 600 
     108 [-]: NAMECALL R1 R1 K4 [0x67BC869F]
     109 [-]: CALL R1 4 0  
L 1: 110 [-]: JUMPIFNOT R0 L3
     111 [-]: GETIMPORT R2 18 [nil]
     112 [-]: FASTCALL1 62 R2 L2
     113 [-]: GETIMPORT R1 20 [nil]
     114 [-]: CALL R1 1 1  
L 2: 115 [-]: JUMPIF R1 L3 
     116 [-]: GETIMPORT R1 18 [nil]
     117 [-]: GETIMPORT R3 22 [nil]
     118 [-]: LOADK R4 K23 ["AAEdgeExtend"]
     119 [-]: CALL R3 1 1  
     120 [-]: LOADN R4 1   
     121 [-]: LOADN R5 0   
     122 [-]: LOADN R6 0   
     123 [-]: LOADN R7 0   
     124 [-]: NAMECALL R1 R1 K24 [0x830EEA67]
     125 [-]: CALL R1 6 0  
L 3: 126 [-]: RETURN R0 0  


; Name:            
; Defined at line: 70
; #Upvalues:       2
; #Parameters:     1
; Is_vararg:       0
; Max Stack Size:  6

       0 [-]: JUMPXEQKS R0 K0 L0 NOT ["true"]
       1 [-]: GETIMPORT R1 2 [nil]
       2 [-]: LOADK R3 K3 ["Panel.Instruction"]
       3 [-]: LOADN R4 11  
       4 [-]: LOADB R5 1   
       5 [-]: NAMECALL R1 R1 K4 [0xAADE900E]
       6 [-]: CALL R1 4 0  
       7 [-]: GETUPVAL R1 0
       8 [-]: GETUPVAL R2 1
       9 [-]: CALL R1 1 0  
      10 [-]: RETURN R0 0  
L 0:  11 [-]: GETIMPORT R1 2 [nil]
      12 [-]: LOADK R3 K3 ["Panel.Instruction"]
      13 [-]: LOADN R4 11  
      14 [-]: LOADB R5 0   
      15 [-]: NAMECALL R1 R1 K4 [0xAADE900E]
      16 [-]: CALL R1 4 0  
      17 [-]: GETIMPORT R1 2 [nil]
      18 [-]: LOADK R3 K5 ["Panel.Bg"]
      19 [-]: LOADN R4 11  
      20 [-]: LOADB R5 0   
      21 [-]: NAMECALL R1 R1 K4 [0xAADE900E]
      22 [-]: CALL R1 4 0  
      23 [-]: GETIMPORT R1 2 [nil]
      24 [-]: LOADK R3 K6 ["Panel.LiteBg"]
      25 [-]: LOADN R4 11  
      26 [-]: LOADB R5 0   
      27 [-]: NAMECALL R1 R1 K4 [0xAADE900E]
      28 [-]: CALL R1 4 0  
      29 [-]: RETURN R0 0  


; Name:            
; Defined at line: 81
; #Upvalues:       1
; #Parameters:     1
; Is_vararg:       0
; Max Stack Size:  3

       0 [-]: GETUPVAL R1 0
       1 [-]: JUMPXEQKS R0 K0 L0 ["true"]
       2 [-]: LOADB R2 0 +1
L 0:   3 [-]: LOADB R2 1   
L 1:   4 [-]: CALL R1 1 0  
       5 [-]: RETURN R0 0  


; Name:            
; Defined at line: 85
; #Upvalues:       2
; #Parameters:     1
; Is_vararg:       0
; Max Stack Size:  9

       0 [-]: JUMPXEQKS R0 K0 L0 ["true"]
       1 [-]: LOADB R1 0 +1
L 0:   2 [-]: LOADB R1 1   
L 1:   3 [-]: GETIMPORT R2 2 [nil]
       4 [-]: LOADK R4 K3 ["Panel"]
       5 [-]: GETUPVAL R6 0
       6 [-]: GETTABLEKS R5 R6 K4 [0x06D055F9]
       7 [-]: GETUPVAL R6 1
       8 [-]: LOADK R7 K5 ["LiteBg"]
       9 [-]: LOADK R8 K6 ["Bg"]
      10 [-]: CALL R5 3 1  
      11 [-]: LOADN R6 11  
      12 [-]: NOT R7 R1    
      13 [-]: NAMECALL R2 R2 K7 [0xC0A3774B]
      14 [-]: CALL R2 5 0  
      15 [-]: RETURN R0 0  


; Name:            
; Defined at line: 91
; #Upvalues:       1
; #Parameters:     0
; Is_vararg:       0
; Max Stack Size:  5

       0 [-]: GETIMPORT R0 1 [nil]
       1 [-]: LOADN R2 0   
       2 [-]: NAMECALL R0 R0 K2 [0x3F3AE64C]
       3 [-]: CALL R0 2 1  
       4 [-]: GETUPVAL R2 0
       5 [-]: GETTABLEKS R1 R2 K3 [0x06D055F9]
       6 [-]: FASTCALL1 62 R0 L0
       7 [-]: MOVE R4 R0   
       8 [-]: GETIMPORT R3 5 [nil]
       9 [-]: CALL R3 1 1  
L 0:  10 [-]: NOT R2 R3    
      11 [-]: NAMECALL R3 R0 K6 [0x40E9C32B]
      12 [-]: CALL R3 1 1  
      13 [-]: NAMECALL R3 R3 K7 [0x0C733035]
      14 [-]: CALL R3 1 1  
      15 [-]: LOADN R4 0   
      16 [-]: CALL R1 3 1  
      17 [-]: GETIMPORT R2 10 [nil]
      18 [-]: CALL R2 0 1  
      19 [-]: JUMPIFNOT R2 L2
      20 [-]: JUMPXEQKN R1 K11 L1 [1]
      21 [-]: LOADB R2 0 +1
L 1:  22 [-]: LOADB R2 1   
L 2:  23 [-]: RETURN R2 1  


; Name:            
; Defined at line: 97
; #Upvalues:       1
; #Parameters:     1
; Is_vararg:       0
; Max Stack Size:  8

       0 [-]: GETIMPORT R2 1 [nil]
       1 [-]: LOADN R4 0   
       2 [-]: NAMECALL R2 R2 K2 [0x3F3AE64C]
       3 [-]: CALL R2 2 1  
       4 [-]: FASTCALL1 62 R2 L0
       5 [-]: GETIMPORT R1 4 [nil]
       6 [-]: CALL R1 1 1  
L 0:   7 [-]: JUMPIFNOT R1 L1
       8 [-]: GETIMPORT R1 6 [nil]
       9 [-]: LOADK R2 K7 ["Profile == nil in ApplyGamepadBindingSubstitutions"]
      10 [-]: CALL R1 1 0  
      11 [-]: LOADK R1 K8 [""]
      12 [-]: RETURN R1 1  
L 1:  13 [-]: GETIMPORT R1 1 [nil]
      14 [-]: LOADN R3 0   
      15 [-]: NAMECALL R1 R1 K2 [0x3F3AE64C]
      16 [-]: CALL R1 2 1  
      17 [-]: NAMECALL R1 R1 K9 [0x40E9C32B]
      18 [-]: CALL R1 1 1  
      19 [-]: LOADK R3 K10 ["POWER_MODIFIER"]
      20 [-]: LOADB R4 0   
      21 [-]: GETIMPORT R5 12 [nil]
      22 [-]: NAMECALL R5 R5 K13 [0xAA3C124F]
      23 [-]: CALL R5 1 1  
      24 [-]: GETIMPORT R6 15 [nil]
      25 [-]: NAMECALL R1 R1 K16 [0x8FA32637]
      26 [-]: CALL R1 5 1  
      27 [-]: JUMPXEQKS R1 K8 L2 NOT [""]
      28 [-]: GETUPVAL R2 0
      29 [-]: CALL R2 0 1  
      30 [-]: JUMPIFNOT R2 L3
L 2:  31 [-]: GETIMPORT R2 19 [nil]
      32 [-]: MOVE R3 R0   
      33 [-]: LOADK R4 K20 ["TutorialUsePower"]
      34 [-]: CALL R2 2 1  
      35 [-]: JUMPIFNOT R2 L3
      36 [-]: GETIMPORT R2 22 [nil]
      37 [-]: MOVE R3 R0   
      38 [-]: LOADK R4 K23 ["Excal"]
      39 [-]: LOADK R5 K24 ["Generic"]
      40 [-]: CALL R2 3 1  
      41 [-]: MOVE R0 R2   
      42 [-]: GETIMPORT R2 22 [nil]
      43 [-]: MOVE R3 R0   
      44 [-]: LOADK R4 K25 ["Volt"]
      45 [-]: LOADK R5 K24 ["Generic"]
      46 [-]: CALL R2 3 1  
      47 [-]: MOVE R0 R2   
      48 [-]: GETIMPORT R2 22 [nil]
      49 [-]: MOVE R3 R0   
      50 [-]: LOADK R4 K26 ["Mag"]
      51 [-]: LOADK R5 K24 ["Generic"]
      52 [-]: CALL R2 3 1  
      53 [-]: MOVE R0 R2   
L 3:  54 [-]: GETIMPORT R2 28 [nil]
      55 [-]: MOVE R4 R0   
      56 [-]: LOADB R5 0   
      57 [-]: NAMECALL R2 R2 K29 [0x42B04007]
      58 [-]: CALL R2 3 1  
      59 [-]: MOVE R0 R2   
      60 [-]: GETUPVAL R2 0
      61 [-]: CALL R2 0 1  
      62 [-]: JUMPIFNOT R2 L5
      63 [-]: GETIMPORT R2 19 [nil]
      64 [-]: MOVE R3 R0   
      65 [-]: LOADK R4 K30 ["<ACTIVATE_ABILITY_[0-9]>"]
      66 [-]: CALL R2 2 1  
      67 [-]: JUMPIFNOT R2 L5
      68 [-]: GETIMPORT R2 28 [nil]
      69 [-]: LOADK R4 K31 ["ControllerHolder.SwipePadController"]
      70 [-]: NAMECALL R2 R2 K32 [0xA7EC3E8A]
      71 [-]: CALL R2 2 1  
      72 [-]: JUMPIF R2 L4 
      73 [-]: GETIMPORT R2 34 [nil]
      74 [-]: GETIMPORT R3 28 [nil]
      75 [-]: LOADK R4 K35 ["ControllerHolder.attachMovie"]
      76 [-]: LOADK R5 K36 ["PS4Controller_All"]
      77 [-]: LOADK R6 K37 ["SwipePadController"]
      78 [-]: LOADN R7 10  
      79 [-]: CALL R2 5 0  
L 4:  80 [-]: GETIMPORT R2 22 [nil]
      81 [-]: MOVE R3 R0   
      82 [-]: LOADK R4 K30 ["<ACTIVATE_ABILITY_[0-9]>"]
      83 [-]: LOADK R5 K8 [""]
      84 [-]: CALL R2 3 1  
      85 [-]: MOVE R0 R2   
L 5:  86 [-]: GETIMPORT R2 22 [nil]
      87 [-]: MOVE R3 R0   
      88 [-]: LOADK R4 K38 ["<MINI_INVENTORY_HOLD>"]
      89 [-]: LOADK R5 K39 ["<MINI_INVENTORY_TOGGLE>"]
      90 [-]: CALL R2 3 1  
      91 [-]: MOVE R0 R2   
      92 [-]: RETURN R0 1  


; Name:            
; Defined at line: 125
; #Upvalues:       3
; #Parameters:     1
; Is_vararg:       0
; Max Stack Size:  12

       0 [-]: LOADB R1 1   
       1 [-]: SETUPVAL R1 0
       2 [-]: GETIMPORT R1 1 [nil]
       3 [-]: LOADK R3 K2 ["Panel.Instruction"]
       4 [-]: LOADN R4 44  
       5 [-]: LOADB R5 1   
       6 [-]: NAMECALL R1 R1 K3 [0xAADE900E]
       7 [-]: CALL R1 4 0  
       8 [-]: GETIMPORT R2 1 [nil]
       9 [-]: LOADK R4 K2 ["Panel.Instruction"]
      10 [-]: LOADN R5 5   
      11 [-]: NAMECALL R2 R2 K5 [0x91A24E4B]
      12 [-]: CALL R2 3 1  
      13 [-]: DIVK R1 R2 K4 [100]
      14 [-]: DIVK R4 R0 K6 [2]
      15 [-]: MINUS R3 R4  
      16 [-]: MUL R2 R3 R1 
      17 [-]: GETIMPORT R3 1 [nil]
      18 [-]: LOADK R5 K2 ["Panel.Instruction"]
      19 [-]: LOADN R6 0   
      20 [-]: MOVE R7 R2   
      21 [-]: NAMECALL R3 R3 K7 [0x67BC869F]
      22 [-]: CALL R3 4 0  
      23 [-]: GETIMPORT R3 1 [nil]
      24 [-]: LOADK R5 K2 ["Panel.Instruction"]
      25 [-]: LOADN R6 12  
      26 [-]: MOVE R7 R0   
      27 [-]: NAMECALL R3 R3 K7 [0x67BC869F]
      28 [-]: CALL R3 4 0  
      29 [-]: GETUPVAL R3 1
      30 [-]: JUMPIFNOT R3 L0
      31 [-]: GETIMPORT R4 1 [nil]
      32 [-]: LOADK R6 K2 ["Panel.Instruction"]
      33 [-]: LOADN R7 34  
      34 [-]: NAMECALL R4 R4 K5 [0x91A24E4B]
      35 [-]: CALL R4 3 1  
      36 [-]: MUL R3 R4 R1 
      37 [-]: GETIMPORT R5 1 [nil]
      38 [-]: LOADK R7 K2 ["Panel.Instruction"]
      39 [-]: LOADN R8 42  
      40 [-]: NAMECALL R5 R5 K5 [0x91A24E4B]
      41 [-]: CALL R5 3 1  
      42 [-]: MUL R4 R5 R1 
      43 [-]: GETIMPORT R5 1 [nil]
      44 [-]: LOADK R7 K8 ["Panel"]
      45 [-]: LOADN R8 1   
      46 [-]: GETUPVAL R10 2
      47 [-]: SUB R11 R3 R4
      48 [-]: SUB R9 R10 R11
      49 [-]: NAMECALL R5 R5 K7 [0x67BC869F]
      50 [-]: CALL R5 4 0  
L 0:  51 [-]: RETURN R0 0  


; Name:            
; Defined at line: 140
; #Upvalues:       2
; #Parameters:     1
; Is_vararg:       0
; Max Stack Size:  11

       0 [-]: JUMPXEQKS R0 K0 L0 ["true"]
       1 [-]: LOADB R1 0 +1
L 0:   2 [-]: LOADB R1 1   
L 1:   3 [-]: SETUPVAL R1 0
       4 [-]: GETUPVAL R1 0
       5 [-]: JUMPIFNOT R1 L2
       6 [-]: GETIMPORT R2 3 [nil]
       7 [-]: LOADK R4 K4 ["Panel.Instruction"]
       8 [-]: LOADN R5 5   
       9 [-]: NAMECALL R2 R2 K5 [0x91A24E4B]
      10 [-]: CALL R2 3 1  
      11 [-]: DIVK R1 R2 K1 [100]
      12 [-]: GETIMPORT R3 3 [nil]
      13 [-]: LOADK R5 K4 ["Panel.Instruction"]
      14 [-]: LOADN R6 34  
      15 [-]: NAMECALL R3 R3 K5 [0x91A24E4B]
      16 [-]: CALL R3 3 1  
      17 [-]: MUL R2 R3 R1 
      18 [-]: GETIMPORT R4 3 [nil]
      19 [-]: LOADK R6 K4 ["Panel.Instruction"]
      20 [-]: LOADN R7 42  
      21 [-]: NAMECALL R4 R4 K5 [0x91A24E4B]
      22 [-]: CALL R4 3 1  
      23 [-]: MUL R3 R4 R1 
      24 [-]: GETIMPORT R4 3 [nil]
      25 [-]: LOADK R6 K6 ["Panel"]
      26 [-]: LOADN R7 1   
      27 [-]: GETUPVAL R9 1
      28 [-]: SUB R10 R2 R3
      29 [-]: SUB R8 R9 R10
      30 [-]: NAMECALL R4 R4 K7 [0x67BC869F]
      31 [-]: CALL R4 4 0  
      32 [-]: RETURN R0 0  
L 2:  33 [-]: GETIMPORT R1 3 [nil]
      34 [-]: LOADK R3 K6 ["Panel"]
      35 [-]: LOADN R4 1   
      36 [-]: GETUPVAL R5 1
      37 [-]: NAMECALL R1 R1 K7 [0x67BC869F]
      38 [-]: CALL R1 4 0  
      39 [-]: RETURN R0 0  


; Name:            
; Defined at line: 153
; #Upvalues:       12
; #Parameters:     1
; Is_vararg:       0
; Max Stack Size:  15

       0 [-]: GETIMPORT R2 1 [nil]
       1 [-]: FASTCALL1 62 R2 L0
       2 [-]: GETIMPORT R1 3 [nil]
       3 [-]: CALL R1 1 1  
L 0:   4 [-]: JUMPIFNOT R1 L1
       5 [-]: RETURN R0 0  
L 1:   6 [-]: GETUPVAL R2 0
       7 [-]: FASTCALL1 62 R2 L2
       8 [-]: GETIMPORT R1 3 [nil]
       9 [-]: CALL R1 1 1  
L 2:  10 [-]: JUMPIFNOT R1 L3
      11 [-]: GETIMPORT R1 1 [nil]
      12 [-]: LOADK R3 K4 ["Panel.Bg"]
      13 [-]: LOADN R4 1   
      14 [-]: NAMECALL R1 R1 K5 [0x91A24E4B]
      15 [-]: CALL R1 3 1  
      16 [-]: SETUPVAL R1 0
L 3:  17 [-]: GETUPVAL R2 1
      18 [-]: FASTCALL1 62 R2 L4
      19 [-]: GETIMPORT R1 3 [nil]
      20 [-]: CALL R1 1 1  
L 4:  21 [-]: JUMPIFNOT R1 L5
      22 [-]: GETIMPORT R1 1 [nil]
      23 [-]: LOADK R3 K6 ["Panel.LiteBg"]
      24 [-]: LOADN R4 1   
      25 [-]: NAMECALL R1 R1 K5 [0x91A24E4B]
      26 [-]: CALL R1 3 1  
      27 [-]: SETUPVAL R1 1
L 5:  28 [-]: JUMPXEQKNIL R0 L6 NOT
      29 [-]: LOADK R0 K7 [""]
      30 [-]: JUMP L7
     
L 6:  31 [-]: GETIMPORT R1 10 [nil]
      32 [-]: MOVE R2 R0   
      33 [-]: LOADK R3 K11 ["<COMMA>"]
      34 [-]: LOADK R4 K12 [","]
      35 [-]: CALL R1 3 1  
      36 [-]: MOVE R0 R1   
L 7:  37 [-]: GETIMPORT R1 15 [nil]
      38 [-]: JUMPIF R1 L8 
      39 [-]: GETIMPORT R1 17 [nil]
      40 [-]: GETIMPORT R2 1 [nil]
      41 [-]: LOADK R3 K18 ["Panel"]
      42 [-]: LOADN R4 8   
      43 [-]: NEWTABLE R5 0 1
      44 [-]: LOADN R6 10  
      45 [-]: SETLIST R5 R6 1 [1]
      46 [-]: NEWTABLE R6 0 1
      47 [-]: LOADN R7 100 
      48 [-]: SETLIST R6 R7 1 [1]
      49 [-]: LOADK R7 K19 [0.5]
      50 [-]: CALL R1 6 0  
L 8:  51 [-]: GETIMPORT R1 10 [nil]
      52 [-]: MOVE R2 R0   
      53 [-]: LOADK R3 K20 ["%["]
      54 [-]: LOADK R4 K7 [""]
      55 [-]: CALL R1 3 1  
      56 [-]: MOVE R0 R1   
      57 [-]: GETIMPORT R1 10 [nil]
      58 [-]: MOVE R2 R0   
      59 [-]: LOADK R3 K21 ["%]"]
      60 [-]: LOADK R4 K7 [""]
      61 [-]: CALL R1 3 1  
      62 [-]: MOVE R0 R1   
      63 [-]: SETUPVAL R0 2
      64 [-]: GETIMPORT R1 23 [nil]
      65 [-]: MOVE R2 R0   
      66 [-]: LOADK R3 K24 ["Tutorial"]
      67 [-]: CALL R1 2 1  
      68 [-]: JUMPIFNOT R1 L11
      69 [-]: GETIMPORT R1 23 [nil]
      70 [-]: MOVE R2 R0   
      71 [-]: LOADK R3 K25 ["_KBM"]
      72 [-]: CALL R1 2 1  
      73 [-]: JUMPIFNOT R1 L11
      74 [-]: GETIMPORT R1 28 [nil]
      75 [-]: CALL R1 0 1  
      76 [-]: GETIMPORT R2 30 [nil]
      77 [-]: CALL R2 0 1  
      78 [-]: JUMPIF R2 L9 
      79 [-]: GETIMPORT R2 32 [nil]
      80 [-]: CALL R2 0 1  
      81 [-]: JUMPIF R2 L9 
      82 [-]: GETIMPORT R2 34 [nil]
      83 [-]: CALL R2 0 1  
L 9:  84 [-]: JUMPIFNOT R2 L10
      85 [-]: JUMPIFNOT R1 L11
      86 [-]: GETIMPORT R3 10 [nil]
      87 [-]: MOVE R4 R0   
      88 [-]: LOADK R5 K25 ["_KBM"]
      89 [-]: LOADK R6 K35 ["_Windows"]
      90 [-]: CALL R3 3 1  
      91 [-]: MOVE R0 R3   
      92 [-]: JUMP L11
    
L10:  93 [-]: JUMPIFNOT R1 L11
      94 [-]: GETIMPORT R3 10 [nil]
      95 [-]: MOVE R4 R0   
      96 [-]: LOADK R5 K25 ["_KBM"]
      97 [-]: LOADK R6 K36 ["_XBone"]
      98 [-]: CALL R3 3 1  
      99 [-]: MOVE R0 R3   
L11: 100 [-]: GETIMPORT R1 28 [nil]
     101 [-]: CALL R1 0 1  
     102 [-]: JUMPIFNOT R1 L12
     103 [-]: GETUPVAL R1 3
     104 [-]: MOVE R2 R0   
     105 [-]: CALL R1 1 1  
     106 [-]: MOVE R0 R1   
L12: 107 [-]: GETIMPORT R1 1 [nil]
     108 [-]: MOVE R3 R0   
     109 [-]: LOADB R4 1   
     110 [-]: NAMECALL R1 R1 K37 [0x42B04007]
     111 [-]: CALL R1 3 1  
     112 [-]: SETUPVAL R1 4
     113 [-]: GETUPVAL R1 4
     114 [-]: GETUPVAL R2 5
     115 [-]: JUMPIFNOT R2 L13
     116 [-]: LOADK R2 K38 ["<p><font color=\"#444444\">"]
     117 [-]: MOVE R3 R1   
     118 [-]: LOADK R4 K39 ["</font></p>"]
     119 [-]: CONCAT R1 R2 R4
L13: 120 [-]: GETIMPORT R2 1 [nil]
     121 [-]: LOADK R4 K40 ["Panel.Instruction"]
     122 [-]: LOADN R5 29  
     123 [-]: MOVE R6 R1   
     124 [-]: NAMECALL R2 R2 K41 [0x5F56EEAB]
     125 [-]: CALL R2 4 0  
     126 [-]: GETIMPORT R2 1 [nil]
     127 [-]: LOADK R4 K40 ["Panel.Instruction"]
     128 [-]: LOADN R5 5   
     129 [-]: NAMECALL R2 R2 K5 [0x91A24E4B]
     130 [-]: CALL R2 3 1  
     131 [-]: DIVK R1 R2 K42 [100]
     132 [-]: GETIMPORT R3 1 [nil]
     133 [-]: LOADK R5 K40 ["Panel.Instruction"]
     134 [-]: LOADN R6 33  
     135 [-]: NAMECALL R3 R3 K5 [0x91A24E4B]
     136 [-]: CALL R3 3 1  
     137 [-]: MUL R2 R3 R1 
     138 [-]: GETUPVAL R3 6
     139 [-]: ADD R2 R2 R3 
     140 [-]: GETIMPORT R4 1 [nil]
     141 [-]: LOADK R6 K40 ["Panel.Instruction"]
     142 [-]: LOADN R7 34  
     143 [-]: NAMECALL R4 R4 K5 [0x91A24E4B]
     144 [-]: CALL R4 3 1  
     145 [-]: MUL R3 R4 R1 
     146 [-]: GETUPVAL R4 7
     147 [-]: ADD R3 R3 R4 
     148 [-]: GETIMPORT R4 1 [nil]
     149 [-]: LOADK R6 K4 ["Panel.Bg"]
     150 [-]: LOADN R7 12  
     151 [-]: MOVE R8 R2   
     152 [-]: NAMECALL R4 R4 K43 [0x67BC869F]
     153 [-]: CALL R4 4 0  
     154 [-]: GETIMPORT R4 1 [nil]
     155 [-]: LOADK R6 K6 ["Panel.LiteBg"]
     156 [-]: LOADN R7 12  
     157 [-]: MOVE R8 R2   
     158 [-]: NAMECALL R4 R4 K43 [0x67BC869F]
     159 [-]: CALL R4 4 0  
     160 [-]: GETIMPORT R4 1 [nil]
     161 [-]: LOADK R6 K4 ["Panel.Bg"]
     162 [-]: LOADN R7 13  
     163 [-]: MOVE R8 R3   
     164 [-]: NAMECALL R4 R4 K43 [0x67BC869F]
     165 [-]: CALL R4 4 0  
     166 [-]: GETIMPORT R4 1 [nil]
     167 [-]: LOADK R6 K6 ["Panel.LiteBg"]
     168 [-]: LOADN R7 13  
     169 [-]: MOVE R8 R3   
     170 [-]: NAMECALL R4 R4 K43 [0x67BC869F]
     171 [-]: CALL R4 4 0  
     172 [-]: GETIMPORT R4 1 [nil]
     173 [-]: LOADK R6 K4 ["Panel.Bg"]
     174 [-]: LOADN R7 1   
     175 [-]: GETUPVAL R9 0
     176 [-]: GETUPVAL R12 7
     177 [-]: SUBK R11 R12 K44 [12]
     178 [-]: MULK R10 R11 K19 [0.5]
     179 [-]: SUB R8 R9 R10
     180 [-]: NAMECALL R4 R4 K43 [0x67BC869F]
     181 [-]: CALL R4 4 0  
     182 [-]: GETIMPORT R4 1 [nil]
     183 [-]: LOADK R6 K6 ["Panel.LiteBg"]
     184 [-]: LOADN R7 1   
     185 [-]: GETUPVAL R9 1
     186 [-]: GETUPVAL R12 7
     187 [-]: SUBK R11 R12 K44 [12]
     188 [-]: MULK R10 R11 K19 [0.5]
     189 [-]: SUB R8 R9 R10
     190 [-]: NAMECALL R4 R4 K43 [0x67BC869F]
     191 [-]: CALL R4 4 0  
     192 [-]: GETUPVAL R4 8
     193 [-]: JUMPIFNOT R4 L14
     194 [-]: GETUPVAL R4 9
     195 [-]: JUMPIFNOT R4 L14
     196 [-]: GETIMPORT R5 1 [nil]
     197 [-]: LOADK R7 K40 ["Panel.Instruction"]
     198 [-]: LOADN R8 42  
     199 [-]: NAMECALL R5 R5 K5 [0x91A24E4B]
     200 [-]: CALL R5 3 1  
     201 [-]: MUL R4 R5 R1 
     202 [-]: GETIMPORT R5 1 [nil]
     203 [-]: LOADK R7 K18 ["Panel"]
     204 [-]: LOADN R8 1   
     205 [-]: GETUPVAL R10 10
     206 [-]: SUBK R12 R3 K44 [12]
     207 [-]: SUB R11 R12 R4
     208 [-]: SUB R9 R10 R11
     209 [-]: NAMECALL R5 R5 K43 [0x67BC869F]
     210 [-]: CALL R5 4 0  
L14: 211 [-]: GETUPVAL R4 11
     212 [-]: JUMPIF R4 L15
     213 [-]: GETIMPORT R4 1 [nil]
     214 [-]: LOADK R6 K45 ["ControllerHolder"]
     215 [-]: LOADN R7 1   
     216 [-]: GETIMPORT R9 1 [nil]
     217 [-]: LOADK R11 K45 ["ControllerHolder"]
     218 [-]: LOADN R12 1  
     219 [-]: NAMECALL R9 R9 K5 [0x91A24E4B]
     220 [-]: CALL R9 3 1  
     221 [-]: GETIMPORT R11 1 [nil]
     222 [-]: LOADK R13 K40 ["Panel.Instruction"]
     223 [-]: LOADN R14 34 
     224 [-]: NAMECALL R11 R11 K5 [0x91A24E4B]
     225 [-]: CALL R11 3 1 
     226 [-]: MULK R10 R11 K46 [2]
     227 [-]: SUB R8 R9 R10
     228 [-]: NAMECALL R4 R4 K43 [0x67BC869F]
     229 [-]: CALL R4 4 0  
     230 [-]: LOADB R4 1   
     231 [-]: SETUPVAL R4 11
L15: 232 [-]: LOADB R4 1   
     233 [-]: RETURN R4 1  


; Name:            
; Defined at line: 235
; #Upvalues:       1
; #Parameters:     1
; Is_vararg:       0
; Max Stack Size:  3

       0 [-]: GETUPVAL R1 0
       1 [-]: MOVE R2 R0   
       2 [-]: CALL R1 1 -1 
       3 [-]: RETURN R1 -1 


; Name:            
; Defined at line: 239
; #Upvalues:       0
; #Parameters:     1
; Is_vararg:       0
; Max Stack Size:  6

       0 [-]: GETIMPORT R1 1 [nil]
       1 [-]: LOADK R3 K2 ["Panel.Instruction"]
       2 [-]: LOADN R4 41  
       3 [-]: MOVE R5 R0   
       4 [-]: NAMECALL R1 R1 K3 [0x5F56EEAB]
       5 [-]: CALL R1 4 0  
       6 [-]: RETURN R0 0  


; Name:            
; Defined at line: 243
; #Upvalues:       0
; #Parameters:     1
; Is_vararg:       0
; Max Stack Size:  7

       0 [-]: GETIMPORT R1 1 [nil]
       1 [-]: LOADK R3 K2 ["Panel.Instruction"]
       2 [-]: LOADN R4 36  
       3 [-]: GETIMPORT R5 4 [nil]
       4 [-]: MOVE R6 R0   
       5 [-]: CALL R5 1 -1 
       6 [-]: NAMECALL R1 R1 K5 [0x67BC869F]
       7 [-]: CALL R1 -1 0 
       8 [-]: RETURN R0 0  


; Name:            
; Defined at line: 247
; #Upvalues:       0
; #Parameters:     1
; Is_vararg:       0
; Max Stack Size:  7

       0 [-]: GETIMPORT R1 1 [nil]
       1 [-]: LOADK R3 K2 ["Panel.Instruction"]
       2 [-]: LOADN R4 10  
       3 [-]: GETIMPORT R5 4 [nil]
       4 [-]: MOVE R6 R0   
       5 [-]: CALL R5 1 -1 
       6 [-]: NAMECALL R1 R1 K5 [0x67BC869F]
       7 [-]: CALL R1 -1 0 
       8 [-]: RETURN R0 0  


; Name:            
; Defined at line: 251
; #Upvalues:       0
; #Parameters:     1
; Is_vararg:       0
; Max Stack Size:  6

       0 [-]: GETIMPORT R1 1 [nil]
       1 [-]: LOADK R3 K2 ["Panel.Instruction"]
       2 [-]: LOADN R4 37  
       3 [-]: MOVE R5 R0   
       4 [-]: NAMECALL R1 R1 K3 [0x5F56EEAB]
       5 [-]: CALL R1 4 0  
       6 [-]: RETURN R0 0  


; Name:            
; Defined at line: 255
; #Upvalues:       0
; #Parameters:     2
; Is_vararg:       0
; Max Stack Size:  10

       0 [-]: GETIMPORT R2 1 [nil]
       1 [-]: GETIMPORT R3 3 [nil]
       2 [-]: LOADK R5 K4 ["Panel.Instruction"]
       3 [-]: LOADK R6 K5 [".setVertexColors"]
       4 [-]: CONCAT R4 R5 R6
       5 [-]: GETIMPORT R5 7 [nil]
       6 [-]: MOVE R6 R0   
       7 [-]: CALL R5 1 1  
       8 [-]: GETIMPORT R6 7 [nil]
       9 [-]: MOVE R7 R0   
      10 [-]: CALL R6 1 1  
      11 [-]: GETIMPORT R7 7 [nil]
      12 [-]: MOVE R8 R1   
      13 [-]: CALL R7 1 1  
      14 [-]: GETIMPORT R8 7 [nil]
      15 [-]: MOVE R9 R1   
      16 [-]: CALL R8 1 -1 
      17 [-]: CALL R2 -1 0 
      18 [-]: RETURN R0 0  


; Name:            
; Defined at line: 259
; #Upvalues:       0
; #Parameters:     0
; Is_vararg:       0
; Max Stack Size:  5

       0 [-]: GETIMPORT R0 1 [nil]
       1 [-]: LOADK R2 K2 ["Panel.Instruction"]
       2 [-]: LOADN R3 41  
       3 [-]: LOADK R4 K3 ["Arial Unicode MS"]
       4 [-]: NAMECALL R0 R0 K4 [0x5F56EEAB]
       5 [-]: CALL R0 4 0  
       6 [-]: GETIMPORT R0 1 [nil]
       7 [-]: GETIMPORT R2 6 [nil]
       8 [-]: NAMECALL R0 R0 K7 [0x97F16B44]
       9 [-]: CALL R0 2 0  
      10 [-]: RETURN R0 0  


; Name:            
; Defined at line: 265
; #Upvalues:       0
; #Parameters:     0
; Is_vararg:       0
; Max Stack Size:  3

       0 [-]: GETIMPORT R0 1 [nil]
       1 [-]: GETIMPORT R2 3 [nil]
       2 [-]: NAMECALL R0 R0 K4 [0x97F16B44]
       3 [-]: CALL R0 2 0  
       4 [-]: RETURN R0 0  


; Name:            
; Defined at line: 269
; #Upvalues:       3
; #Parameters:     1
; Is_vararg:       0
; Max Stack Size:  11

       0 [-]: JUMPXEQKS R0 K0 L0 ["true"]
       1 [-]: LOADB R1 0 +1
L 0:   2 [-]: LOADB R1 1   
L 1:   3 [-]: SETUPVAL R1 0
       4 [-]: GETIMPORT R1 2 [nil]
       5 [-]: GETIMPORT R2 4 [nil]
       6 [-]: LOADK R3 K5 ["Panel"]
       7 [-]: LOADN R4 8   
       8 [-]: NEWTABLE R5 0 1
       9 [-]: LOADN R6 10  
      10 [-]: SETLIST R5 R6 1 [1]
      11 [-]: NEWTABLE R6 0 1
      12 [-]: GETUPVAL R8 1
      13 [-]: GETTABLEKS R7 R8 K6 [0x06D055F9]
      14 [-]: GETUPVAL R8 0
      15 [-]: LOADN R9 90  
      16 [-]: LOADN R10 100
      17 [-]: CALL R7 3 -1 
      18 [-]: SETLIST R6 R7 -1 [1]
      19 [-]: LOADK R7 K7 [0.5]
      20 [-]: CALL R1 6 0  
      21 [-]: GETUPVAL R1 2
      22 [-]: GETUPVAL R2 0
      23 [-]: JUMPIFNOT R2 L2
      24 [-]: LOADK R2 K8 ["<p><font color=\"#444444\">"]
      25 [-]: MOVE R3 R1   
      26 [-]: LOADK R4 K9 ["</font></p>"]
      27 [-]: CONCAT R1 R2 R4
L 2:  28 [-]: GETIMPORT R2 4 [nil]
      29 [-]: LOADK R4 K10 ["Panel.Instruction"]
      30 [-]: LOADN R5 29  
      31 [-]: MOVE R6 R1   
      32 [-]: NAMECALL R2 R2 K11 [0x5F56EEAB]
      33 [-]: CALL R2 4 0  
      34 [-]: RETURN R0 0  


; Name:            
; Defined at line: 276
; #Upvalues:       1
; #Parameters:     1
; Is_vararg:       0
; Max Stack Size:  3

       0 [-]: GETIMPORT R1 1 [nil]
       1 [-]: MOVE R2 R0   
       2 [-]: CALL R1 1 1  
       3 [-]: SETUPVAL R1 0
       4 [-]: RETURN R0 0  


; Name:            
; Defined at line: 280
; #Upvalues:       1
; #Parameters:     1
; Is_vararg:       0
; Max Stack Size:  3

       0 [-]: GETIMPORT R1 1 [nil]
       1 [-]: MOVE R2 R0   
       2 [-]: CALL R1 1 1  
       3 [-]: SETUPVAL R1 0
       4 [-]: RETURN R0 0  


; Name:            
; Defined at line: 284
; #Upvalues:       2
; #Parameters:     0
; Is_vararg:       0
; Max Stack Size:  10

       0 [-]: GETIMPORT R0 1 [nil]
       1 [-]: LOADK R2 K2 ["Panel"]
       2 [-]: LOADN R3 10  
       3 [-]: LOADN R4 0   
       4 [-]: NAMECALL R0 R0 K3 [0x67BC869F]
       5 [-]: CALL R0 4 0  
       6 [-]: GETIMPORT R0 1 [nil]
       7 [-]: LOADK R2 K4 ["NotoLoader"]
       8 [-]: LOADN R3 29  
       9 [-]: LOADK R4 K5 [""]
      10 [-]: NAMECALL R0 R0 K6 [0x5F56EEAB]
      11 [-]: CALL R0 4 0  
      12 [-]: GETIMPORT R0 1 [nil]
      13 [-]: LOADK R2 K7 ["Panel.Instruction"]
      14 [-]: LOADN R3 44  
      15 [-]: LOADB R4 0   
      16 [-]: NAMECALL R0 R0 K8 [0xAADE900E]
      17 [-]: CALL R0 4 0  
      18 [-]: GETIMPORT R0 11 [nil]
      19 [-]: CALL R0 0 1  
      20 [-]: JUMPIFNOT R0 L0
      21 [-]: GETIMPORT R0 1 [nil]
      22 [-]: LOADK R2 K7 ["Panel.Instruction"]
      23 [-]: LOADN R3 41  
      24 [-]: LOADK R4 K12 ["Arial Unicode MS"]
      25 [-]: NAMECALL R0 R0 K6 [0x5F56EEAB]
      26 [-]: CALL R0 4 0  
      27 [-]: GETIMPORT R0 1 [nil]
      28 [-]: LOADK R2 K7 ["Panel.Instruction"]
      29 [-]: LOADN R3 42  
      30 [-]: LOADN R4 18  
      31 [-]: NAMECALL R0 R0 K3 [0x67BC869F]
      32 [-]: CALL R0 4 0  
      33 [-]: GETIMPORT R0 1 [nil]
      34 [-]: LOADK R2 K7 ["Panel.Instruction"]
      35 [-]: LOADN R3 12  
      36 [-]: NAMECALL R0 R0 K13 [0x91A24E4B]
      37 [-]: CALL R0 3 1  
      38 [-]: MULK R1 R0 K14 [1.5]
      39 [-]: GETIMPORT R2 1 [nil]
      40 [-]: LOADK R4 K7 ["Panel.Instruction"]
      41 [-]: LOADN R5 0   
      42 [-]: NAMECALL R2 R2 K13 [0x91A24E4B]
      43 [-]: CALL R2 3 1  
      44 [-]: GETIMPORT R3 1 [nil]
      45 [-]: LOADK R5 K7 ["Panel.Instruction"]
      46 [-]: LOADN R6 5   
      47 [-]: LOADN R7 150 
      48 [-]: NAMECALL R3 R3 K3 [0x67BC869F]
      49 [-]: CALL R3 4 0  
      50 [-]: GETIMPORT R3 1 [nil]
      51 [-]: LOADK R5 K7 ["Panel.Instruction"]
      52 [-]: LOADN R6 6   
      53 [-]: LOADN R7 150 
      54 [-]: NAMECALL R3 R3 K3 [0x67BC869F]
      55 [-]: CALL R3 4 0  
      56 [-]: GETIMPORT R3 1 [nil]
      57 [-]: LOADK R5 K7 ["Panel.Instruction"]
      58 [-]: LOADN R6 0   
      59 [-]: SUB R9 R1 R0 
      60 [-]: MULK R8 R9 K15 [0.80000000000000004]
      61 [-]: SUB R7 R2 R8 
      62 [-]: NAMECALL R3 R3 K3 [0x67BC869F]
      63 [-]: CALL R3 4 0  
      64 [-]: GETIMPORT R3 1 [nil]
      65 [-]: LOADK R5 K7 ["Panel.Instruction"]
      66 [-]: LOADN R6 1   
      67 [-]: LOADN R7 -20 
      68 [-]: NAMECALL R3 R3 K3 [0x67BC869F]
      69 [-]: CALL R3 4 0  
L 0:  70 [-]: GETIMPORT R0 1 [nil]
      71 [-]: LOADK R2 K2 ["Panel"]
      72 [-]: LOADN R3 1   
      73 [-]: NAMECALL R0 R0 K13 [0x91A24E4B]
      74 [-]: CALL R0 3 1  
      75 [-]: SETUPVAL R0 0
      76 [-]: GETUPVAL R0 1
      77 [-]: LOADB R1 0   
      78 [-]: CALL R0 1 0  
      79 [-]: RETURN R0 0  


; Name:            
; Defined at line: 309
; #Upvalues:       1
; #Parameters:     1
; Is_vararg:       0
; Max Stack Size:  2

       0 [-]: MOVE R1 R0   
       1 [-]: JUMPIF R1 L1 
       2 [-]: JUMPXEQKS R0 K0 L0 ["true"]
       3 [-]: LOADB R1 0 +1
L 0:   4 [-]: LOADB R1 1   
L 1:   5 [-]: SETUPVAL R1 0
       6 [-]: RETURN R0 0  


; Name:            
; Defined at line: 313
; #Upvalues:       1
; #Parameters:     1
; Is_vararg:       0
; Max Stack Size:  1

       0 [-]: SETUPVAL R0 0
       1 [-]: RETURN R0 0  


; Name:            
; Defined at line: 317
; #Upvalues:       3
; #Parameters:     0
; Is_vararg:       0
; Max Stack Size:  6

       0 [-]: GETUPVAL R0 0
       1 [-]: JUMPXEQKS R0 K0 L6 [""]
       2 [-]: GETIMPORT R1 3 [nil]
       3 [-]: FASTCALL1 62 R1 L0
       4 [-]: GETIMPORT R0 5 [nil]
       5 [-]: CALL R0 1 1  
L 0:   6 [-]: JUMPIF R0 L6 
       7 [-]: GETIMPORT R1 7 [nil]
       8 [-]: FASTCALL1 62 R1 L1
       9 [-]: GETIMPORT R0 5 [nil]
      10 [-]: CALL R0 1 1  
L 1:  11 [-]: JUMPIF R0 L6 
      12 [-]: GETIMPORT R1 7 [nil]
      13 [-]: NAMECALL R1 R1 K8 [0x78298275]
      14 [-]: CALL R1 1 1  
      15 [-]: FASTCALL1 62 R1 L2
      16 [-]: GETIMPORT R0 5 [nil]
      17 [-]: CALL R0 1 1  
L 2:  18 [-]: JUMPIF R0 L6 
      19 [-]: GETIMPORT R0 7 [nil]
      20 [-]: NAMECALL R0 R0 K8 [0x78298275]
      21 [-]: CALL R0 1 1  
      22 [-]: NAMECALL R0 R0 K9 [0xE79E7EF4]
      23 [-]: CALL R0 1 1  
      24 [-]: GETUPVAL R1 1
      25 [-]: JUMPIFEQ R0 R1 L5
      26 [-]: SETUPVAL R0 1
      27 [-]: LOADB R1 0   
      28 [-]: SETUPVAL R1 2
      29 [-]: GETIMPORT R2 11 [nil]
      30 [-]: GETUPVAL R3 0
      31 [-]: GETTABLE R1 R2 R3
      32 [-]: LOADN R4 1   
      33 [-]: LENGTH R2 R1 
      34 [-]: LOADN R3 1   
      35 [-]: FORNPREP R2 L6
L 3:  36 [-]: GETTABLE R5 R1 R4
      37 [-]: JUMPIFNOTEQ R0 R5 L4
      38 [-]: LOADB R5 1   
      39 [-]: SETUPVAL R5 2
      40 [-]: LOADB R5 1   
      41 [-]: RETURN R5 1  
L 4:  42 [-]: FORNLOOP R2 L3
      43 [-]: JUMP L6
     
L 5:  44 [-]: GETUPVAL R1 2
      45 [-]: RETURN R1 1  
L 6:  46 [-]: LOADB R0 1   
      47 [-]: RETURN R0 1  


; Name:            
; Defined at line: 337
; #Upvalues:       3
; #Parameters:     0
; Is_vararg:       0
; Max Stack Size:  4

       0 [-]: GETUPVAL R0 0
       1 [-]: JUMPIFNOT R0 L2
       2 [-]: GETIMPORT R1 1 [nil]
       3 [-]: FASTCALL1 62 R1 L0
       4 [-]: GETIMPORT R0 3 [nil]
       5 [-]: CALL R0 1 1  
L 0:   6 [-]: JUMPIFNOT R0 L1
       7 [-]: GETUPVAL R1 1
       8 [-]: CALL R1 0 1  
       9 [-]: MOVE R0 R1   
L 1:  10 [-]: GETUPVAL R1 2
      11 [-]: JUMPIFEQ R1 R0 L2
      12 [-]: SETUPVAL R0 2
      13 [-]: GETIMPORT R1 5 [nil]
      14 [-]: MOVE R3 R0   
      15 [-]: NAMECALL R1 R1 K6 [0x368AD758]
      16 [-]: CALL R1 2 0  
L 2:  17 [-]: GETIMPORT R0 5 [nil]
      18 [-]: GETIMPORT R2 8 [nil]
      19 [-]: CALL R2 0 -1 
      20 [-]: NAMECALL R0 R0 K9 [0x8A8C8D5A]
      21 [-]: CALL R0 -1 0 
      22 [-]: RETURN R0 0  


; Name:            
; Defined at line: 351
; #Upvalues:       0
; #Parameters:     0
; Is_vararg:       0
; Max Stack Size:  9

       0 [-]: GETIMPORT R0 1 [nil]
       1 [-]: GETIMPORT R1 3 [nil]
       2 [-]: LOADK R2 K4 ["Panel"]
       3 [-]: LOADN R3 8   
       4 [-]: NEWTABLE R4 0 1
       5 [-]: LOADN R5 10  
       6 [-]: SETLIST R4 R5 1 [1]
       7 [-]: NEWTABLE R5 0 1
       8 [-]: LOADN R6 0   
       9 [-]: SETLIST R5 R6 1 [1]
      10 [-]: LOADK R6 K5 [0.5]
      11 [-]: LOADN R7 0   
      12 [-]: DUPCLOSURE R8 K6 []
      13 [-]: CALL R0 8 0  
      14 [-]: RETURN R0 0  


; Name:            
; Defined at line: 355
; #Upvalues:       2
; #Parameters:     0
; Is_vararg:       0
; Max Stack Size:  2

       0 [-]: GETUPVAL R0 0
       1 [-]: GETUPVAL R1 1
       2 [-]: CALL R0 1 0  
       3 [-]: RETURN R0 0  


; Name:            
; Defined at line: 359
; #Upvalues:       2
; #Parameters:     1
; Is_vararg:       0
; Max Stack Size:  3

       0 [-]: GETUPVAL R1 0
       1 [-]: GETUPVAL R2 1
       2 [-]: CALL R1 1 0  
       3 [-]: RETURN R0 0  


; Name:            
; Defined at line: 363
; #Upvalues:       0
; #Parameters:     1
; Is_vararg:       0
; Max Stack Size:  8

       0 [-]: JUMPXEQKS R0 K0 L0 ["true"]
       1 [-]: LOADB R0 0 +1
L 0:   2 [-]: LOADB R0 1   
L 1:   3 [-]: JUMPIFNOT R0 L2
       4 [-]: GETIMPORT R1 2 [nil]
       5 [-]: GETIMPORT R2 4 [nil]
       6 [-]: LOADK R3 K5 ["_root"]
       7 [-]: LOADN R4 8   
       8 [-]: NEWTABLE R5 0 1
       9 [-]: LOADN R6 10  
      10 [-]: SETLIST R5 R6 1 [1]
      11 [-]: NEWTABLE R6 0 1
      12 [-]: LOADN R7 100 
      13 [-]: SETLIST R6 R7 1 [1]
      14 [-]: LOADK R7 K6 [0.5]
      15 [-]: CALL R1 6 0  
      16 [-]: RETURN R0 0  
L 2:  17 [-]: GETIMPORT R1 2 [nil]
      18 [-]: GETIMPORT R2 4 [nil]
      19 [-]: LOADK R3 K5 ["_root"]
      20 [-]: LOADN R4 8   
      21 [-]: NEWTABLE R5 0 1
      22 [-]: LOADN R6 10  
      23 [-]: SETLIST R5 R6 1 [1]
      24 [-]: NEWTABLE R6 0 1
      25 [-]: LOADN R7 0   
      26 [-]: SETLIST R6 R7 1 [1]
      27 [-]: LOADK R7 K6 [0.5]
      28 [-]: CALL R1 6 0  
      29 [-]: RETURN R0 0  


; Name:            
; Defined at line: 372
; #Upvalues:       0
; #Parameters:     1
; Is_vararg:       0
; Max Stack Size:  7

       0 [-]: GETIMPORT R1 1 [nil]
       1 [-]: LOADK R3 K2 ["Panel.Bg"]
       2 [-]: LOADN R4 10  
       3 [-]: GETIMPORT R5 4 [nil]
       4 [-]: MOVE R6 R0   
       5 [-]: CALL R5 1 -1 
       6 [-]: NAMECALL R1 R1 K5 [0x67BC869F]
       7 [-]: CALL R1 -1 0 
       8 [-]: RETURN R0 0  



