; This file has been disassembled using luadec 2.0.2 by sztupy (modified by Reversive)

; Name:            
; Defined at line: 0
; #Upvalues:       0
; #Parameters:     0
; Is_vararg:       2
; Max Stack Size:  168

  1 [-]: GETGLOBAL R0 K0        ; R0 := 0xaeabecda
  2 [-]: VARARG    R1 R2        ; R1 := R2 := ...
  3 [-]: GETGLOBAL R2 K1        ; R2 := package
  4 [-]: GETTABLE  R2 R2 K2     ; R2 := R2["seeall"]
  5 [-]: CALL      R0 3 1       ; R0(R1,R2)
  6 [-]: NEWTABLE  R0 21 0      ; R0 := {}
  7 [-]: LOADK     R1 K3        ; R1 := "DT_IMPACT"
  8 [-]: LOADK     R2 K4        ; R2 := "DT_PUNCTURE"
  9 [-]: LOADK     R3 K5        ; R3 := "DT_SLASH"
 10 [-]: LOADK     R4 K6        ; R4 := "DT_FIRE"
 11 [-]: LOADK     R5 K7        ; R5 := "DT_FREEZE"
 12 [-]: LOADK     R6 K8        ; R6 := "DT_ELECTRICITY"
 13 [-]: LOADK     R7 K9        ; R7 := "DT_POISON"
 14 [-]: LOADK     R8 K10       ; R8 := "DT_EXPLOSION"
 15 [-]: LOADK     R9 K11       ; R9 := "DT_RADIATION"
 16 [-]: LOADK     R10 K12      ; R10 := "DT_GAS"
 17 [-]: LOADK     R11 K13      ; R11 := "DT_MAGNETIC"
 18 [-]: LOADK     R12 K14      ; R12 := "DT_VIRAL"
 19 [-]: LOADK     R13 K15      ; R13 := "DT_CORROSIVE"
 20 [-]: LOADK     R14 K16      ; R14 := "DT_RADIANT"
 21 [-]: LOADK     R15 K17      ; R15 := "DT_SENTIENT"
 22 [-]: LOADK     R16 K18      ; R16 := "DT_CINEMATIC"
 23 [-]: LOADK     R17 K19      ; R17 := "DT_SHIELD_DRAIN"
 24 [-]: LOADK     R18 K20      ; R18 := "DT_HEALTH_DRAIN"
 25 [-]: LOADK     R19 K21      ; R19 := "DT_ENERGY_DRAIN"
 26 [-]: LOADK     R20 K22      ; R20 := "DT_FINISHER"
 27 [-]: LOADK     R21 K23      ; R21 := "DT_SUICIDE"
 28 [-]: LOADK     R22 K24      ; R22 := "DT_PHYSICAL"
 29 [-]: LOADK     R23 K25      ; R23 := "DT_INVALID"
 30 [-]: LOADK     R24 K26      ; R24 := "DT_BASE_ELEMENTAL"
 31 [-]: LOADK     R25 K27      ; R25 := "DT_COMPOUND_ELEMENTAL"
 32 [-]: LOADK     R26 K28      ; R26 := "DT_ANY"
 33 [-]: SETLIST   R0 26 1      ; R0[(1-1)*FPF+i] := R(0+i), 1 <= i <= 26
 34 [-]: NEWTABLE  R1 23 0      ; R1 := {}
 35 [-]: LOADK     R2 K29       ; R2 := "PT_KNOCKBACK"
 36 [-]: LOADK     R3 K30       ; R3 := "PT_FRAILTY"
 37 [-]: LOADK     R4 K31       ; R4 := "PT_BLEEDING"
 38 [-]: LOADK     R5 K32       ; R5 := "PT_IMMOLATION"
 39 [-]: LOADK     R6 K33       ; R6 := "PT_CHILLED"
 40 [-]: LOADK     R7 K34       ; R7 := "PT_ELECTROCUTION"
 41 [-]: LOADK     R8 K35       ; R8 := "PT_POISONED"
 42 [-]: LOADK     R9 K36       ; R9 := "PT_FLASHBANG"
 43 [-]: LOADK     R10 K37      ; R10 := "PT_RAD_TOX"
 44 [-]: LOADK     R11 K38      ; R11 := "PT_ASPHYXIATION"
 45 [-]: LOADK     R12 K39      ; R12 := "PT_MAGNETIZED"
 46 [-]: LOADK     R13 K40      ; R13 := "PT_INFECTED"
 47 [-]: LOADK     R14 K41      ; R14 := "PT_CAUSTIC_BURN"
 48 [-]: LOADK     R15 K42      ; R15 := "PT_RADIANT"
 49 [-]: LOADK     R16 K43      ; R16 := "PT_SENTIENT"
 50 [-]: LOADK     R17 K44      ; R17 := "PT_MICROWAVE_BURN"
 51 [-]: LOADK     R18 K45      ; R18 := "PT_STAGGERED"
 52 [-]: LOADK     R19 K46      ; R19 := "PT_BIG_STAGGER"
 53 [-]: LOADK     R20 K47      ; R20 := "PT_STUNNED"
 54 [-]: LOADK     R21 K48      ; R21 := "PT_KNOCKED_DOWN"
 55 [-]: LOADK     R22 K49      ; R22 := "PT_RAGDOLL"
 56 [-]: LOADK     R23 K50      ; R23 := "PT_PARRIED"
 57 [-]: LOADK     R24 K51      ; R24 := "PT_DISARMED"
 58 [-]: LOADK     R25 K52      ; R25 := "PT_SILENCED"
 59 [-]: LOADK     R26 K53      ; R26 := "PT_ROOTS"
 60 [-]: LOADK     R27 K54      ; R27 := "PT_VOID"
 61 [-]: LOADK     R28 K55      ; R28 := "PT_GLUE"
 62 [-]: LOADK     R29 K56      ; R29 := "PT_SLEEP"
 63 [-]: LOADK     R30 K57      ; R30 := "PT_LIFT_HIT"
 64 [-]: LOADK     R31 K58      ; R31 := "MAX_ProcType"
 65 [-]: SETLIST   R1 30 1      ; R1[(1-1)*FPF+i] := R(1+i), 1 <= i <= 30
 66 [-]: GETGLOBAL R2 K59       ; R2 := 0x60cce7b4
 67 [-]: LEN       R3 R0        ; R3 := # R0
 68 [-]: EQ        1 R3 K61     ; if R3 == 26.000000 then PC := 71
 69 [-]: JMP       71           ; PC := 71
 70 [-]: LOADBOOL  R3 0 1       ; R3 := false; PC := 71
 71 [-]: LOADBOOL  R3 1 0       ; R3 := true
 72 [-]: CALL      R2 2 1       ; R2(R3)
 73 [-]: GETGLOBAL R2 K59       ; R2 := 0x60cce7b4
 74 [-]: LEN       R3 R1        ; R3 := # R1
 75 [-]: EQ        1 R3 K62     ; if R3 == 30.000000 then PC := 78
 76 [-]: JMP       78           ; PC := 78
 77 [-]: LOADBOOL  R3 0 1       ; R3 := false; PC := 78
 78 [-]: LOADBOOL  R3 1 0       ; R3 := true
 79 [-]: CALL      R2 2 1       ; R2(R3)
 80 [-]: GETGLOBAL R2 K63       ; R2 := 0x7ed0a956
 81 [-]: LOADK     R3 K64       ; R3 := "/Lotus/Types/StoreItems/SuitCustomizations/ColourPickerDefaultsItemA"
 82 [-]: CALL      R2 2 2       ; R2 := R2(R3)
 83 [-]: GETGLOBAL R3 K63       ; R3 := 0x7ed0a956
 84 [-]: LOADK     R4 K65       ; R4 := "/Lotus/Upgrades/Mods/Fusers/UncommonModFuser"
 85 [-]: CALL      R3 2 2       ; R3 := R3(R4)
 86 [-]: GETGLOBAL R4 K63       ; R4 := 0x7ed0a956
 87 [-]: LOADK     R5 K66       ; R5 := "/Lotus/Upgrades/Mods/Fusers/RareModFuser"
 88 [-]: CALL      R4 2 2       ; R4 := R4(R5)
 89 [-]: GETGLOBAL R5 K63       ; R5 := 0x7ed0a956
 90 [-]: LOADK     R6 K67       ; R6 := "/Lotus/Types/Items/MiscItems/Elitium"
 91 [-]: CALL      R5 2 2       ; R5 := R5(R6)
 92 [-]: GETGLOBAL R6 K63       ; R6 := 0x7ed0a956
 93 [-]: LOADK     R7 K68       ; R7 := "/Lotus/Types/Game/OrokinGoldenMawAvatar"
 94 [-]: CALL      R6 2 2       ; R6 := R6(R7)
 95 [-]: GETGLOBAL R7 K63       ; R7 := 0x7ed0a956
 96 [-]: LOADK     R8 K69       ; R8 := "/Lotus/Types/Items/MiscItems/PhotoboothTile"
 97 [-]: CALL      R7 2 2       ; R7 := R7(R8)
 98 [-]: GETGLOBAL R8 K63       ; R8 := 0x7ed0a956
 99 [-]: LOADK     R9 K70       ; R9 := "/Lotus/Types/Items/ShipFeatureItems/ShipFeatureItem"
100 [-]: CALL      R8 2 2       ; R8 := R8(R9)
101 [-]: GETGLOBAL R9 K63       ; R9 := 0x7ed0a956
102 [-]: LOADK     R10 K71      ; R10 := "/Lotus/Types/Restoratives/LisetBaseAirSupportPower"
103 [-]: CALL      R9 2 2       ; R9 := R9(R10)
104 [-]: GETGLOBAL R10 K63      ; R10 := 0x7ed0a956
105 [-]: LOADK     R11 K72      ; R11 := "/Lotus/Weapons/Tenno/HackingDevices/TnHackingDevice/TnHackingDeviceWeapon"
106 [-]: CALL      R10 2 2      ; R10 := R10(R11)
107 [-]: GETGLOBAL R11 K63      ; R11 := 0x7ed0a956
108 [-]: LOADK     R12 K73      ; R12 := "/Lotus/Powersuits/Wraith/ReaperAvatar"
109 [-]: CALL      R11 2 2      ; R11 := R11(R12)
110 [-]: LOADK     R12 1        ; R12 := 1.000000
111 [-]: SETGLOBAL R12 K74      ; UI_MODE_IN_SPACE_SHIP := R12
112 [-]: LOADK     R12 2        ; R12 := 2.000000
113 [-]: SETGLOBAL R12 K75      ; UI_MODE_IN_SPACE_HUB := R12
114 [-]: LOADK     R12 3        ; R12 := 3.000000
115 [-]: SETGLOBAL R12 K76      ; UI_MODE_IN_DOJO := R12
116 [-]: LOADK     R12 4        ; R12 := 4.000000
117 [-]: SETGLOBAL R12 K77      ; UI_MODE_IN_GAME := R12
118 [-]: LOADK     R12 14       ; R12 := 14.000000
119 [-]: SETGLOBAL R12 K78      ; REGION_ID_DOJO := R12
120 [-]: LOADK     R12 15       ; R12 := 15.000000
121 [-]: SETGLOBAL R12 K79      ; REGION_ID_VOID := R12
122 [-]: LOADK     R12 17       ; R12 := 17.000000
123 [-]: SETGLOBAL R12 K80      ; REGION_ID_DERELICT := R12
124 [-]: LOADK     R12 18       ; R12 := 18.000000
125 [-]: SETGLOBAL R12 K81      ; REGION_ID_MOON := R12
126 [-]: LOADK     R12 19       ; R12 := 19.000000
127 [-]: SETGLOBAL R12 K82      ; REGION_ID_FORTRESS := R12
128 [-]: LOADK     R12 20       ; R12 := 20.000000
129 [-]: SETGLOBAL R12 K83      ; REGION_ID_DARK_SECTOR := R12
130 [-]: LOADK     R12 21       ; R12 := 21.000000
131 [-]: SETGLOBAL R12 K84      ; REGION_ID_DEEP_SPACE := R12
132 [-]: LOADK     R12 22       ; R12 := 22.000000
133 [-]: SETGLOBAL R12 K85      ; REGION_ID_ZARIMAN := R12
134 [-]: LOADK     R12 97       ; R12 := 97.000000
135 [-]: SETGLOBAL R12 K86      ; REGION_ID_DOJO_DUEL := R12
136 [-]: LOADK     R12 98       ; R12 := 98.000000
137 [-]: SETGLOBAL R12 K87      ; REGION_ID_CLAN_DOJO := R12
138 [-]: LOADK     R12 99       ; R12 := 99.000000
139 [-]: SETGLOBAL R12 K88      ; REGION_ID_PVP := R12
140 [-]: LOADK     R12 100      ; R12 := 100.000000
141 [-]: SETGLOBAL R12 K89      ; REGION_ID_PHOTOBOOTH := R12
142 [-]: LOADK     R12 101      ; R12 := 101.000000
143 [-]: SETGLOBAL R12 K90      ; REGION_ID_SIMULACRUM := R12
144 [-]: LOADK     R12 1        ; R12 := 1.000000
145 [-]: SETGLOBAL R12 K91      ; SLIDER := R12
146 [-]: LOADK     R12 2        ; R12 := 2.000000
147 [-]: SETGLOBAL R12 K92      ; CHECKBOX := R12
148 [-]: LOADK     R12 3        ; R12 := 3.000000
149 [-]: SETGLOBAL R12 K93      ; TOGGLE := R12
150 [-]: LOADK     R12 4        ; R12 := 4.000000
151 [-]: SETGLOBAL R12 K94      ; BUTTON := R12
152 [-]: LOADK     R12 5        ; R12 := 5.000000
153 [-]: SETGLOBAL R12 K95      ; TITLE := R12
154 [-]: LOADK     R12 6        ; R12 := 6.000000
155 [-]: SETGLOBAL R12 K96      ; INPUTBOX := R12
156 [-]: LOADK     R12 7        ; R12 := 7.000000
157 [-]: SETGLOBAL R12 K97      ; SPACER := R12
158 [-]: LOADK     R12 8        ; R12 := 8.000000
159 [-]: SETGLOBAL R12 K98      ; INPUTCOUNT := R12
160 [-]: LOADK     R12 9        ; R12 := 9.000000
161 [-]: SETGLOBAL R12 K99      ; ICONBUTTON := R12
162 [-]: LOADK     R12 10       ; R12 := 10.000000
163 [-]: SETGLOBAL R12 K100     ; CHOICE := R12
164 [-]: LOADK     R12 11       ; R12 := 11.000000
165 [-]: SETGLOBAL R12 K101     ; COLOR := R12
166 [-]: LOADK     R12 0        ; R12 := 0.000000
167 [-]: SETGLOBAL R12 K102     ; DECO_AREA_UNKNOWN := R12
168 [-]: LOADK     R12 1        ; R12 := 1.000000
169 [-]: SETGLOBAL R12 K103     ; DECO_AREA_SHIP := R12
170 [-]: LOADK     R12 2        ; R12 := 2.000000
171 [-]: SETGLOBAL R12 K104     ; DECO_AREA_APARTMENT := R12
172 [-]: LOADK     R12 3        ; R12 := 3.000000
173 [-]: SETGLOBAL R12 K105     ; DECO_AREA_COUNT := R12
174 [-]: LOADK     R12 1        ; R12 := 1.000000
175 [-]: SETGLOBAL R12 K106     ; REPORT_PLAYER := R12
176 [-]: LOADK     R12 2        ; R12 := 2.000000
177 [-]: SETGLOBAL R12 K107     ; REPORT_CLAN_AD := R12
178 [-]: NEWTABLE  R12 0 2      ; R12 := {}
179 [-]: GETGLOBAL R13 K110     ; R13 := 0x0469f296
180 [-]: LOADK     R14 K111     ; R14 := "OutsideRoom"
181 [-]: CALL      R13 2 2      ; R13 := R13(R14)
182 [-]: SETTABLE  R12 K109 R13 ; R12["Name"] := R13
183 [-]: SETTABLE  R12 K112 K113; R12["LocTag"] := "/Lotus/Language/UiElements/OutsideRoom"
184 [-]: SETGLOBAL R12 K108     ; OUTSIDE_THE_SHIP_ROOM := R12
185 [-]: NEWTABLE  R12 0 2      ; R12 := {}
186 [-]: GETGLOBAL R13 K110     ; R13 := 0x0469f296
187 [-]: LOADK     R14 K115     ; R14 := "LisetRoom"
188 [-]: CALL      R13 2 2      ; R13 := R13(R14)
189 [-]: SETTABLE  R12 K109 R13 ; R12["Name"] := R13
190 [-]: SETTABLE  R12 K112 K116; R12["LocTag"] := "/Lotus/Language/UiElements/ShipLisetRoom"
191 [-]: SETGLOBAL R12 K114     ; LISET_ROOM := R12
192 [-]: NEWTABLE  R12 5 0      ; R12 := {}
193 [-]: NEWTABLE  R13 0 2      ; R13 := {}
194 [-]: GETGLOBAL R14 K110     ; R14 := 0x0469f296
195 [-]: LOADK     R15 K118     ; R15 := "OperatorChamberRoom"
196 [-]: CALL      R14 2 2      ; R14 := R14(R15)
197 [-]: SETTABLE  R13 K109 R14 ; R13["Name"] := R14
198 [-]: SETTABLE  R13 K112 K119; R13["LocTag"] := "/Lotus/Language/UiElements/ShipOperatorChamberRoom"
199 [-]: NEWTABLE  R14 0 2      ; R14 := {}
200 [-]: GETGLOBAL R15 K110     ; R15 := 0x0469f296
201 [-]: LOADK     R16 K120     ; R16 := "AlchemyRoom"
202 [-]: CALL      R15 2 2      ; R15 := R15(R16)
203 [-]: SETTABLE  R14 K109 R15 ; R14["Name"] := R15
204 [-]: SETTABLE  R14 K112 K121; R14["LocTag"] := "/Lotus/Language/UiElements/ShipAlchemyRoom"
205 [-]: NEWTABLE  R15 0 2      ; R15 := {}
206 [-]: GETGLOBAL R16 K110     ; R16 := 0x0469f296
207 [-]: LOADK     R17 K122     ; R17 := "PersonalQuartersRoom"
208 [-]: CALL      R16 2 2      ; R16 := R16(R17)
209 [-]: SETTABLE  R15 K109 R16 ; R15["Name"] := R16
210 [-]: SETTABLE  R15 K112 K123; R15["LocTag"] := "/Lotus/Language/UiElements/ShipPersonalQuartersRoom"
211 [-]: NEWTABLE  R16 0 2      ; R16 := {}
212 [-]: GETGLOBAL R17 K110     ; R17 := 0x0469f296
213 [-]: LOADK     R18 K124     ; R18 := "BridgeRoom"
214 [-]: CALL      R17 2 2      ; R17 := R17(R18)
215 [-]: SETTABLE  R16 K109 R17 ; R16["Name"] := R17
216 [-]: SETTABLE  R16 K112 K125; R16["LocTag"] := "/Lotus/Language/UiElements/ShipBridgeRoom"
217 [-]: GETGLOBAL R17 K114     ; R17 := LISET_ROOM
218 [-]: SETLIST   R12 5 1      ; R12[(1-1)*FPF+i] := R(12+i), 1 <= i <= 5
219 [-]: SETGLOBAL R12 K117     ; SHIP_ROOMS := R12
220 [-]: NEWTABLE  R12 4 0      ; R12 := {}
221 [-]: NEWTABLE  R13 0 2      ; R13 := {}
222 [-]: GETGLOBAL R14 K110     ; R14 := 0x0469f296
223 [-]: LOADK     R15 K127     ; R15 := "ElevatorLanding"
224 [-]: CALL      R14 2 2      ; R14 := R14(R15)
225 [-]: SETTABLE  R13 K109 R14 ; R13["Name"] := R14
226 [-]: SETTABLE  R13 K112 K128; R13["LocTag"] := "/Lotus/Language/UiElements/ApartmentElevatorLanding"
227 [-]: NEWTABLE  R14 0 2      ; R14 := {}
228 [-]: GETGLOBAL R15 K110     ; R15 := 0x0469f296
229 [-]: LOADK     R16 K129     ; R16 := "ApartmentRoomA"
230 [-]: CALL      R15 2 2      ; R15 := R15(R16)
231 [-]: SETTABLE  R14 K109 R15 ; R14["Name"] := R15
232 [-]: SETTABLE  R14 K112 K130; R14["LocTag"] := "/Lotus/Language/UiElements/ApartmentRoomA"
233 [-]: NEWTABLE  R15 0 2      ; R15 := {}
234 [-]: GETGLOBAL R16 K110     ; R16 := 0x0469f296
235 [-]: LOADK     R17 K131     ; R17 := "ApartmentRoomB"
236 [-]: CALL      R16 2 2      ; R16 := R16(R17)
237 [-]: SETTABLE  R15 K109 R16 ; R15["Name"] := R16
238 [-]: SETTABLE  R15 K112 K132; R15["LocTag"] := "/Lotus/Language/UiElements/ApartmentRoomB"
239 [-]: NEWTABLE  R16 0 2      ; R16 := {}
240 [-]: GETGLOBAL R17 K110     ; R17 := 0x0469f296
241 [-]: LOADK     R18 K133     ; R18 := "ApartmentRoomC"
242 [-]: CALL      R17 2 2      ; R17 := R17(R18)
243 [-]: SETTABLE  R16 K109 R17 ; R16["Name"] := R17
244 [-]: SETTABLE  R16 K112 K134; R16["LocTag"] := "/Lotus/Language/UiElements/ApartmentRoomC"
245 [-]: SETLIST   R12 4 1      ; R12[(1-1)*FPF+i] := R(12+i), 1 <= i <= 4
246 [-]: SETGLOBAL R12 K126     ; APARTMENT_ROOMS := R12
247 [-]: NEWTABLE  R12 0 8      ; R12 := {}
248 [-]: SETTABLE  R12 K137 K138; R12[0.000000] := "WARFRAME_SLOT"
249 [-]: SETTABLE  R12 K139 K140; R12[1.000000] := "WEAPON_SLOT"
250 [-]: SETTABLE  R12 K141 K142; R12[2.000000] := "SENTINEL_SLOT"
251 [-]: SETTABLE  R12 K143 K144; R12[3.000000] := "SPACE_SUIT_SLOT"
252 [-]: SETTABLE  R12 K145 K146; R12[4.000000] := "SPACE_WEAPON_SLOT"
253 [-]: SETTABLE  R12 K147 K148; R12[8.000000] := "OPERATOR_AMP_SLOT"
254 [-]: SETTABLE  R12 K149 K150; R12[10.000000] := "MECH_SLOT"
255 [-]: SETTABLE  R12 K151 K152; R12[11.000000] := "CREW_MEMBER_SLOT"
256 [-]: SETGLOBAL R12 K135     ; SLOT_TYPES := R12
257 [-]: LOADK     R12 1        ; R12 := 1.000000
258 [-]: SETGLOBAL R12 K153     ; SOUND_SET_EIDOLON := R12
259 [-]: LOADK     R12 2        ; R12 := 2.000000
260 [-]: SETGLOBAL R12 K154     ; SOUND_SET_FORTUNA := R12
261 [-]: LOADK     R12 3        ; R12 := 3.000000
262 [-]: SETGLOBAL R12 K155     ; SOUND_SET_ORB_VALLIS := R12
263 [-]: LOADK     R12 4        ; R12 := 4.000000
264 [-]: SETGLOBAL R12 K156     ; SOUND_SET_RAILJACK := R12
265 [-]: LOADK     R12 5        ; R12 := 5.000000
266 [-]: SETGLOBAL R12 K157     ; SOUND_SET_OROKIN_TOWER := R12
267 [-]: LOADK     R12 6        ; R12 := 6.000000
268 [-]: SETGLOBAL R12 K158     ; SOUND_SET_ZARIMAN := R12
269 [-]: LOADK     R12 100      ; R12 := 100.000000
270 [-]: LOADK     R13 1000     ; R13 := 1000.000000
271 [-]: LOADK     R14 K159     ; R14 := 100000.000000
272 [-]: LOADK     R15 K161     ; R15 := "_"
273 [-]: SETGLOBAL R15 K160     ; TAG_SEPERATOR := R15
274 [-]: GETGLOBAL R15 K160     ; R15 := TAG_SEPERATOR
275 [-]: LOADK     R16 K163     ; R16 := "Alert"
276 [-]: CONCAT    R15 R15 R16  ; R15 := R15 .. R16
277 [-]: SETGLOBAL R15 K162     ; ALERT_TAG := R15
278 [-]: MUL       R15 K139 R14 ; R15 := 1.000000 * R14
279 [-]: SETGLOBAL R15 K164     ; ALERT_FLAG := R15
280 [-]: GETGLOBAL R15 K160     ; R15 := TAG_SEPERATOR
281 [-]: LOADK     R16 K166     ; R16 := "Nightmare"
282 [-]: CONCAT    R15 R15 R16  ; R15 := R15 .. R16
283 [-]: SETGLOBAL R15 K165     ; NIGHTMARE_TAG := R15
284 [-]: MUL       R15 K141 R14 ; R15 := 2.000000 * R14
285 [-]: SETGLOBAL R15 K167     ; NIGHTMARE_FLAG := R15
286 [-]: LOADK     R15 28800    ; R15 := 28800.000000
287 [-]: SETGLOBAL R15 K168     ; NIGHTMARE_MISSION_INTERVAL := R15
288 [-]: GETGLOBAL R15 K160     ; R15 := TAG_SEPERATOR
289 [-]: LOADK     R16 K170     ; R16 := "Event"
290 [-]: CONCAT    R15 R15 R16  ; R15 := R15 .. R16
291 [-]: SETGLOBAL R15 K169     ; EVENT_TAG := R15
292 [-]: MUL       R15 K143 R14 ; R15 := 3.000000 * R14
293 [-]: SETGLOBAL R15 K171     ; EVENT_FLAG := R15
294 [-]: GETGLOBAL R15 K160     ; R15 := TAG_SEPERATOR
295 [-]: LOADK     R16 K173     ; R16 := "PVP"
296 [-]: CONCAT    R15 R15 R16  ; R15 := R15 .. R16
297 [-]: SETGLOBAL R15 K172     ; PVP_TAG := R15
298 [-]: MUL       R15 K145 R14 ; R15 := 4.000000 * R14
299 [-]: SETGLOBAL R15 K174     ; PVP_FLAG := R15
300 [-]: GETGLOBAL R15 K160     ; R15 := TAG_SEPERATOR
301 [-]: LOADK     R16 K176     ; R16 := "InvasionAttacker"
302 [-]: CONCAT    R15 R15 R16  ; R15 := R15 .. R16
303 [-]: SETGLOBAL R15 K175     ; INVASION_ATTACKER_TAG := R15
304 [-]: MUL       R15 K178 R14 ; R15 := 5.000000 * R14
305 [-]: SETGLOBAL R15 K177     ; INVASION_ATTACKER_FLAG := R15
306 [-]: GETGLOBAL R15 K160     ; R15 := TAG_SEPERATOR
307 [-]: LOADK     R16 K180     ; R16 := "InvasionDefender"
308 [-]: CONCAT    R15 R15 R16  ; R15 := R15 .. R16
309 [-]: SETGLOBAL R15 K179     ; INVASION_DEFENDER_TAG := R15
310 [-]: MUL       R15 K182 R14 ; R15 := 6.000000 * R14
311 [-]: SETGLOBAL R15 K181     ; INVASION_DEFENDER_FLAG := R15
312 [-]: GETGLOBAL R15 K160     ; R15 := TAG_SEPERATOR
313 [-]: LOADK     R16 K184     ; R16 := "HUB"
314 [-]: CONCAT    R15 R15 R16  ; R15 := R15 .. R16
315 [-]: SETGLOBAL R15 K183     ; HUB_TAG := R15
316 [-]: MUL       R15 K186 R14 ; R15 := 7.000000 * R14
317 [-]: SETGLOBAL R15 K185     ; HUB_FLAG := R15
318 [-]: GETGLOBAL R15 K160     ; R15 := TAG_SEPERATOR
319 [-]: LOADK     R16 K188     ; R16 := "Syndicate"
320 [-]: CONCAT    R15 R15 R16  ; R15 := R15 .. R16
321 [-]: SETGLOBAL R15 K187     ; SYNDICATE_MISSION_TAG := R15
322 [-]: MUL       R15 K151 R14 ; R15 := 11.000000 * R14
323 [-]: SETGLOBAL R15 K189     ; SYNDICATE_MISSION_FLAG := R15
324 [-]: GETGLOBAL R15 K160     ; R15 := TAG_SEPERATOR
325 [-]: LOADK     R16 K191     ; R16 := "Key"
326 [-]: CONCAT    R15 R15 R16  ; R15 := R15 .. R16
327 [-]: SETGLOBAL R15 K190     ; KEY_TAG := R15
328 [-]: MUL       R15 K193 R14 ; R15 := 12.000000 * R14
329 [-]: SETGLOBAL R15 K192     ; KEY_FLAG := R15
330 [-]: GETGLOBAL R15 K160     ; R15 := TAG_SEPERATOR
331 [-]: LOADK     R16 K195     ; R16 := "Sortie"
332 [-]: CONCAT    R15 R15 R16  ; R15 := R15 .. R16
333 [-]: SETGLOBAL R15 K194     ; SORTIE_MISSION_TAG := R15
334 [-]: MUL       R15 K197 R14 ; R15 := 13.000000 * R14
335 [-]: SETGLOBAL R15 K196     ; SORTIE_MISSION_FLAG := R15
336 [-]: GETGLOBAL R15 K160     ; R15 := TAG_SEPERATOR
337 [-]: LOADK     R16 K199     ; R16 := "ActiveMission"
338 [-]: CONCAT    R15 R15 R16  ; R15 := R15 .. R16
339 [-]: SETGLOBAL R15 K198     ; ACTIVE_MISSION_TAG := R15
340 [-]: MUL       R15 K201 R14 ; R15 := 14.000000 * R14
341 [-]: SETGLOBAL R15 K200     ; ACTIVE_MISSION_FLAG := R15
342 [-]: GETGLOBAL R15 K110     ; R15 := 0x0469f296
343 [-]: LOADK     R16 K203     ; R16 := "GhostTower"
344 [-]: CALL      R15 2 2      ; R15 := R15(R16)
345 [-]: SETGLOBAL R15 K202     ; KUVA_TOWER_GOAL_TAG := R15
346 [-]: GETGLOBAL R15 K160     ; R15 := TAG_SEPERATOR
347 [-]: LOADK     R16 K203     ; R16 := "GhostTower"
348 [-]: CONCAT    R15 R15 R16  ; R15 := R15 .. R16
349 [-]: SETGLOBAL R15 K204     ; KUVA_TOWER_MISSION_TAG := R15
350 [-]: MUL       R15 K206 R14 ; R15 := 15.000000 * R14
351 [-]: SETGLOBAL R15 K205     ; KUVA_TOWER_MISSION_FLAG := R15
352 [-]: GETGLOBAL R15 K160     ; R15 := TAG_SEPERATOR
353 [-]: LOADK     R16 K208     ; R16 := "JUNCTION"
354 [-]: CONCAT    R15 R15 R16  ; R15 := R15 .. R16
355 [-]: SETGLOBAL R15 K207     ; JUNCTION_TAG := R15
356 [-]: MUL       R15 K210 R14 ; R15 := 16.000000 * R14
357 [-]: SETGLOBAL R15 K209     ; JUNCTION_FLAG := R15
358 [-]: GETGLOBAL R15 K160     ; R15 := TAG_SEPERATOR
359 [-]: LOADK     R16 K212     ; R16 := "Nemesis"
360 [-]: CONCAT    R15 R15 R16  ; R15 := R15 .. R16
361 [-]: SETGLOBAL R15 K211     ; NEMESIS_MISSION_TAG := R15
362 [-]: MUL       R15 K214 R14 ; R15 := 17.000000 * R14
363 [-]: SETGLOBAL R15 K213     ; NEMESIS_MISSION_FLAG := R15
364 [-]: GETGLOBAL R15 K160     ; R15 := TAG_SEPERATOR
365 [-]: LOADK     R16 K216     ; R16 := "EliteAlert"
366 [-]: CONCAT    R15 R15 R16  ; R15 := R15 .. R16
367 [-]: SETGLOBAL R15 K215     ; ELITE_ALERT_TAG := R15
368 [-]: MUL       R15 K218 R14 ; R15 := 18.000000 * R14
369 [-]: SETGLOBAL R15 K217     ; ELITE_ALERT_FLAG := R15
370 [-]: GETGLOBAL R15 K110     ; R15 := 0x0469f296
371 [-]: LOADK     R16 K216     ; R16 := "EliteAlert"
372 [-]: CALL      R15 2 2      ; R15 := R15(R16)
373 [-]: SETGLOBAL R15 K219     ; ELITE_ALERT_PERIODIC_MISSION_TAG := R15
374 [-]: GETGLOBAL R15 K110     ; R15 := 0x0469f296
375 [-]: LOADK     R16 K221     ; R16 := "EliteAlertB"
376 [-]: CALL      R15 2 2      ; R15 := R15(R16)
377 [-]: SETGLOBAL R15 K220     ; ELITE_ALERT_PERIODIC_MISSION_TAG_ALT := R15
378 [-]: LOADK     R15 3600     ; R15 := 3600.000000
379 [-]: SETGLOBAL R15 K222     ; ELITE_ALERT_MISSION_INTERVAL := R15
380 [-]: GETGLOBAL R15 K160     ; R15 := TAG_SEPERATOR
381 [-]: LOADK     R16 K224     ; R16 := "Scenario"
382 [-]: CONCAT    R15 R15 R16  ; R15 := R15 .. R16
383 [-]: SETGLOBAL R15 K223     ; SCENARIO_BEACON_TAG := R15
384 [-]: MUL       R15 K226 R14 ; R15 := 19.000000 * R14
385 [-]: SETGLOBAL R15 K225     ; SCENARIO_BEACON_FLAG := R15
386 [-]: GETGLOBAL R15 K160     ; R15 := TAG_SEPERATOR
387 [-]: LOADK     R16 K228     ; R16 := "Hard"
388 [-]: CONCAT    R15 R15 R16  ; R15 := R15 .. R16
389 [-]: SETGLOBAL R15 K227     ; HARD_MODE_TAG := R15
390 [-]: MUL       R15 K230 R14 ; R15 := 20.000000 * R14
391 [-]: SETGLOBAL R15 K229     ; HARD_MODE_FLAG := R15
392 [-]: LOADK     R15 100      ; R15 := 100.000000
393 [-]: SETGLOBAL R15 K231     ; HARD_MODE_LEVEL_MODIFIER := R15
394 [-]: LOADK     R15 50       ; R15 := 50.000000
395 [-]: SETGLOBAL R15 K232     ; HARD_MODE_ARCHWING_LEVEL_MODIFIER := R15
396 [-]: LOADK     R15 86400    ; R15 := 86400.000000
397 [-]: SETGLOBAL R15 K233     ; HARD_MODE_DAILY_MISSION_INTERVAL := R15
398 [-]: GETGLOBAL R15 K160     ; R15 := TAG_SEPERATOR
399 [-]: LOADK     R16 K235     ; R16 := "HardDaily"
400 [-]: CONCAT    R15 R15 R16  ; R15 := R15 .. R16
401 [-]: SETGLOBAL R15 K234     ; HARD_DAILY_TAG := R15
402 [-]: MUL       R15 K237 R14 ; R15 := 21.000000 * R14
403 [-]: SETGLOBAL R15 K236     ; HARD_DAILY_FLAG := R15
404 [-]: GETGLOBAL R15 K160     ; R15 := TAG_SEPERATOR
405 [-]: LOADK     R16 K239     ; R16 := "VoidStorm"
406 [-]: CONCAT    R15 R15 R16  ; R15 := R15 .. R16
407 [-]: SETGLOBAL R15 K238     ; VOID_STORM_TAG := R15
408 [-]: MUL       R15 K241 R14 ; R15 := 22.000000 * R14
409 [-]: SETGLOBAL R15 K240     ; VOID_STORM_FLAG := R15
410 [-]: GETGLOBAL R15 K160     ; R15 := TAG_SEPERATOR
411 [-]: LOADK     R16 K243     ; R16 := "LiteSortie"
412 [-]: CONCAT    R15 R15 R16  ; R15 := R15 .. R16
413 [-]: SETGLOBAL R15 K242     ; LITE_SORTIE_MISSION_TAG := R15
414 [-]: MUL       R15 K245 R14 ; R15 := 23.000000 * R14
415 [-]: SETGLOBAL R15 K244     ; LITE_SORTIE_MISSION_FLAG := R15
416 [-]: LOADK     R15 3600     ; R15 := 3600.000000
417 [-]: SETGLOBAL R15 K246     ; KUVA_TOWER_MISSION_INTERVAL := R15
418 [-]: LOADK     R15 K248     ; R15 := "OptionalGoal"
419 [-]: SETGLOBAL R15 K247     ; OPTIONAL_GOAL_PREFIX := R15
420 [-]: LOADK     R15 K250     ; R15 := "AnyNode"
421 [-]: SETGLOBAL R15 K249     ; ANY_NODE_PREFIX := R15
422 [-]: GETGLOBAL R15 K110     ; R15 := 0x0469f296
423 [-]: LOADK     R16 K252     ; R16 := "ZarimanHub"
424 [-]: CALL      R15 2 2      ; R15 := R15(R16)
425 [-]: SETGLOBAL R15 K251     ; ZARIMAN_NODE_TAG := R15
426 [-]: GETGLOBAL R15 K110     ; R15 := 0x0469f296
427 [-]: LOADK     R16 K254     ; R16 := "CetusHub4"
428 [-]: CALL      R15 2 2      ; R15 := R15(R16)
429 [-]: SETGLOBAL R15 K253     ; CETUS_NODE_TAG := R15
430 [-]: GETGLOBAL R15 K110     ; R15 := 0x0469f296
431 [-]: LOADK     R16 K256     ; R16 := "SolNode228"
432 [-]: CALL      R15 2 2      ; R15 := R15(R16)
433 [-]: SETGLOBAL R15 K255     ; PLAINS_NODE_TAG := R15
434 [-]: GETGLOBAL R15 K110     ; R15 := 0x0469f296
435 [-]: LOADK     R16 K258     ; R16 := "IronwakeHUB3"
436 [-]: CALL      R15 2 2      ; R15 := R15(R16)
437 [-]: SETGLOBAL R15 K257     ; IRON_WAKE_NODE_TAG := R15
438 [-]: GETGLOBAL R15 K110     ; R15 := 0x0469f296
439 [-]: LOADK     R16 K260     ; R16 := "SolarisUnitedHub1"
440 [-]: CALL      R15 2 2      ; R15 := R15(R16)
441 [-]: SETGLOBAL R15 K259     ; FORTUNA_NODE_TAG := R15
442 [-]: GETGLOBAL R15 K110     ; R15 := 0x0469f296
443 [-]: LOADK     R16 K262     ; R16 := "SolNode129"
444 [-]: CALL      R15 2 2      ; R15 := R15(R16)
445 [-]: SETGLOBAL R15 K261     ; ORB_VALLIS_NODE_TAG := R15
446 [-]: GETGLOBAL R15 K110     ; R15 := 0x0469f296
447 [-]: LOADK     R16 K264     ; R16 := "DeimosHub"
448 [-]: CALL      R15 2 2      ; R15 := R15(R16)
449 [-]: SETGLOBAL R15 K263     ; OROKIN_TOWER_NODE_TAG := R15
450 [-]: GETGLOBAL R15 K110     ; R15 := 0x0469f296
451 [-]: LOADK     R16 K266     ; R16 := "SolNode229"
452 [-]: CALL      R15 2 2      ; R15 := R15(R16)
453 [-]: SETGLOBAL R15 K265     ; ENTRATI_LANDSCAPE_NODE_TAG := R15
454 [-]: GETGLOBAL R15 K110     ; R15 := 0x0469f296
455 [-]: LOADK     R16 K268     ; R16 := "ScenarioEventHub5"
456 [-]: CALL      R15 2 2      ; R15 := R15(R16)
457 [-]: SETGLOBAL R15 K267     ; SCENARIO_EVENT_HUB_TAG := R15
458 [-]: GETGLOBAL R15 K110     ; R15 := 0x0469f296
459 [-]: LOADK     R16 K270     ; R16 := "SolNode234"
460 [-]: CALL      R15 2 2      ; R15 := R15(R16)
461 [-]: SETGLOBAL R15 K269     ; APARTMENT_NODE_TAG := R15
462 [-]: GETGLOBAL R15 K110     ; R15 := 0x0469f296
463 [-]: LOADK     R16 K272     ; R16 := "SolNode230"
464 [-]: CALL      R15 2 2      ; R15 := R15(R16)
465 [-]: SETGLOBAL R15 K271     ; ZARIMAN_MISSION_A_TAG := R15
466 [-]: GETGLOBAL R15 K110     ; R15 := 0x0469f296
467 [-]: LOADK     R16 K274     ; R16 := "SolNode231"
468 [-]: CALL      R15 2 2      ; R15 := R15(R16)
469 [-]: SETGLOBAL R15 K273     ; ZARIMAN_MISSION_B_TAG := R15
470 [-]: GETGLOBAL R15 K110     ; R15 := 0x0469f296
471 [-]: LOADK     R16 K276     ; R16 := "SolNode232"
472 [-]: CALL      R15 2 2      ; R15 := R15(R16)
473 [-]: SETGLOBAL R15 K275     ; ZARIMAN_MISSION_C_TAG := R15
474 [-]: GETGLOBAL R15 K110     ; R15 := 0x0469f296
475 [-]: LOADK     R16 K278     ; R16 := "SolNode233"
476 [-]: CALL      R15 2 2      ; R15 := R15(R16)
477 [-]: SETGLOBAL R15 K277     ; ZARIMAN_MISSION_D_TAG := R15
478 [-]: GETGLOBAL R15 K110     ; R15 := 0x0469f296
479 [-]: LOADK     R16 K280     ; R16 := "SolNode235"
480 [-]: CALL      R15 2 2      ; R15 := R15(R16)
481 [-]: SETGLOBAL R15 K279     ; ZARIMAN_MISSION_E_TAG := R15
482 [-]: GETGLOBAL R15 K110     ; R15 := 0x0469f296
483 [-]: LOADK     R16 K282     ; R16 := "/Lotus/Types/Keys/TestKeyForestOpLinkFragment"
484 [-]: CALL      R15 2 2      ; R15 := R15(R16)
485 [-]: SETGLOBAL R15 K281     ; SCENARIO_EVENT_GROUND_TAG := R15
486 [-]: GETGLOBAL R15 K110     ; R15 := 0x0469f296
487 [-]: LOADK     R16 K284     ; R16 := "/Lotus/Types/Keys/TestKeyCrewBattleSentientSquadLink"
488 [-]: CALL      R15 2 2      ; R15 := R15(R16)
489 [-]: SETGLOBAL R15 K283     ; SCENARIO_EVENT_SPACE_TAG := R15
490 [-]: LOADK     R15 0        ; R15 := 0.000000
491 [-]: SETGLOBAL R15 K285     ; PLAINS_ELO_IN_LISET := R15
492 [-]: LOADK     R15 1        ; R15 := 1.000000
493 [-]: SETGLOBAL R15 K286     ; PLAINS_ELO_INSIDE_SAFE_ZONE := R15
494 [-]: LOADK     R15 2        ; R15 := 2.000000
495 [-]: SETGLOBAL R15 K287     ; PLAINS_ELO_OUTSIDE_SAFE_ZONE := R15
496 [-]: LOADK     R15 3        ; R15 := 3.000000
497 [-]: SETGLOBAL R15 K288     ; PLAINS_ELO_BOUNTY_ACTIVE := R15
498 [-]: LOADK     R15 10       ; R15 := 10.000000
499 [-]: SETGLOBAL R15 K289     ; PLAINS_ELO_POST_NEW_WAR_OFFSET := R15
500 [-]: GETGLOBAL R15 K110     ; R15 := 0x0469f296
501 [-]: LOADK     R16 K290     ; R16 := "Darvo"
502 [-]: CALL      R15 2 2      ; R15 := R15(R16)
503 [-]: NEWTABLE  R16 8 0      ; R16 := {}
504 [-]: LOADK     R17 K292     ; R17 := "/Lotus/Language/Game/Faction_GrineerUC"
505 [-]: LOADK     R18 K293     ; R18 := "/Lotus/Language/Game/Faction_CorpusUC"
506 [-]: LOADK     R19 K294     ; R19 := "/Lotus/Language/Game/Faction_InfestationUC"
507 [-]: LOADK     R20 K295     ; R20 := "/Lotus/Language/Game/Faction_OrokinUC"
508 [-]: LOADK     R21 K296     ; R21 := "/Lotus/Language/Game/Faction_RedVeilUC"
509 [-]: LOADK     R22 K297     ; R22 := "/Lotus/Language/Game/Faction_SentientUC"
510 [-]: LOADK     R23 K298     ; R23 := "/Lotus/Language/Game/Faction_NarmerUC"
511 [-]: LOADK     R24 K299     ; R24 := ""
512 [-]: SETLIST   R16 8 1      ; R16[(1-1)*FPF+i] := R(16+i), 1 <= i <= 8
513 [-]: SETGLOBAL R16 K291     ; FactionNames := R16
514 [-]: LOADK     R16 K301     ; R16 := "???"
515 [-]: SETGLOBAL R16 K300     ; HIDDEN_PLAYER_NAME := R16
516 [-]: GETGLOBAL R16 K63      ; R16 := 0x7ed0a956
517 [-]: LOADK     R17 K303     ; R17 := "/Lotus/Types/Items/ShipFeatureItems/AlertsFeatureItem"
518 [-]: CALL      R16 2 2      ; R16 := R16(R17)
519 [-]: SETGLOBAL R16 K302     ; SF_ALERTS := R16
520 [-]: GETGLOBAL R16 K63      ; R16 := 0x7ed0a956
521 [-]: LOADK     R17 K305     ; R17 := "/Lotus/Types/Items/ShipFeatureItems/ArsenalFeatureItem"
522 [-]: CALL      R16 2 2      ; R16 := R16(R17)
523 [-]: SETGLOBAL R16 K304     ; SF_ARSENAL := R16
524 [-]: GETGLOBAL R16 K63      ; R16 := 0x7ed0a956
525 [-]: LOADK     R17 K307     ; R17 := "/Lotus/Types/Items/ShipFeatureItems/SocialMenuFeatureItem"
526 [-]: CALL      R16 2 2      ; R16 := R16(R17)
527 [-]: SETGLOBAL R16 K306     ; SF_CLAN := R16
528 [-]: GETGLOBAL R16 K63      ; R16 := 0x7ed0a956
529 [-]: LOADK     R17 K309     ; R17 := "/Lotus/Types/Items/ShipFeatureItems/FoundryFeatureItem"
530 [-]: CALL      R16 2 2      ; R16 := R16(R17)
531 [-]: SETGLOBAL R16 K308     ; SF_FOUNDRY := R16
532 [-]: GETGLOBAL R16 K63      ; R16 := 0x7ed0a956
533 [-]: LOADK     R17 K311     ; R17 := "/Lotus/Types/Items/ShipFeatureItems/FoundryVesselUpgradeFeatureItem"
534 [-]: CALL      R16 2 2      ; R16 := R16(R17)
535 [-]: SETGLOBAL R16 K310     ; SF_FOUNDRY_VESSEL_UPGRADE := R16
536 [-]: GETGLOBAL R16 K63      ; R16 := 0x7ed0a956
537 [-]: LOADK     R17 K313     ; R17 := "/Lotus/Types/Items/ShipFeatureItems/GeneticFoundryFeatureItem"
538 [-]: CALL      R16 2 2      ; R16 := R16(R17)
539 [-]: SETGLOBAL R16 K312     ; SF_GENETIC_FOUNDRY := R16
540 [-]: GETGLOBAL R16 K63      ; R16 := 0x7ed0a956
541 [-]: LOADK     R17 K315     ; R17 := "/Lotus/Types/Items/ShipFeatureItems/GeneticFoundryUpgradeFeatureItem"
542 [-]: CALL      R16 2 2      ; R16 := R16(R17)
543 [-]: SETGLOBAL R16 K314     ; SF_GENETIC_FOUNDRY_UPGRADE := R16
544 [-]: GETGLOBAL R16 K63      ; R16 := 0x7ed0a956
545 [-]: LOADK     R17 K317     ; R17 := "/Lotus/Types/Items/ShipFeatureItems/InfestedFoundryItem"
546 [-]: CALL      R16 2 2      ; R16 := R16(R17)
547 [-]: SETGLOBAL R16 K316     ; SF_INFESTED_FOUNDRY := R16
548 [-]: GETGLOBAL R16 K63      ; R16 := 0x7ed0a956
549 [-]: LOADK     R17 K307     ; R17 := "/Lotus/Types/Items/ShipFeatureItems/SocialMenuFeatureItem"
550 [-]: CALL      R16 2 2      ; R16 := R16(R17)
551 [-]: SETGLOBAL R16 K318     ; SF_MARKET_TIER_ONE := R16
552 [-]: GETGLOBAL R16 K63      ; R16 := 0x7ed0a956
553 [-]: LOADK     R17 K307     ; R17 := "/Lotus/Types/Items/ShipFeatureItems/SocialMenuFeatureItem"
554 [-]: CALL      R16 2 2      ; R16 := R16(R17)
555 [-]: SETGLOBAL R16 K319     ; SF_MARKET_TIER_TWO := R16
556 [-]: GETGLOBAL R16 K63      ; R16 := 0x7ed0a956
557 [-]: LOADK     R17 K321     ; R17 := "/Lotus/Types/Items/ShipFeatureItems/ModsFeatureItem"
558 [-]: CALL      R16 2 2      ; R16 := R16(R17)
559 [-]: SETGLOBAL R16 K320     ; SF_MODS := R16
560 [-]: GETGLOBAL R16 K63      ; R16 := 0x7ed0a956
561 [-]: LOADK     R17 K321     ; R17 := "/Lotus/Types/Items/ShipFeatureItems/ModsFeatureItem"
562 [-]: CALL      R16 2 2      ; R16 := R16(R17)
563 [-]: SETGLOBAL R16 K322     ; SF_MODS_FUSION := R16
564 [-]: GETGLOBAL R16 K63      ; R16 := 0x7ed0a956
565 [-]: LOADK     R17 K321     ; R17 := "/Lotus/Types/Items/ShipFeatureItems/ModsFeatureItem"
566 [-]: CALL      R16 2 2      ; R16 := R16(R17)
567 [-]: SETGLOBAL R16 K323     ; SF_MODS_TRANSMUTE := R16
568 [-]: GETGLOBAL R16 K63      ; R16 := 0x7ed0a956
569 [-]: LOADK     R17 K307     ; R17 := "/Lotus/Types/Items/ShipFeatureItems/SocialMenuFeatureItem"
570 [-]: CALL      R16 2 2      ; R16 := R16(R17)
571 [-]: SETGLOBAL R16 K324     ; SF_CONCLAVE := R16
572 [-]: GETGLOBAL R16 K63      ; R16 := 0x7ed0a956
573 [-]: LOADK     R17 K307     ; R17 := "/Lotus/Types/Items/ShipFeatureItems/SocialMenuFeatureItem"
574 [-]: CALL      R16 2 2      ; R16 := R16(R17)
575 [-]: SETGLOBAL R16 K325     ; SF_SOCIAL_MENU := R16
576 [-]: GETGLOBAL R16 K63      ; R16 := 0x7ed0a956
577 [-]: LOADK     R17 K327     ; R17 := "/Lotus/Types/Items/ShipFeatureItems/MercuryNavigationFeatureItem"
578 [-]: CALL      R16 2 2      ; R16 := R16(R17)
579 [-]: SETGLOBAL R16 K326     ; SF_SOLAR_CHART := R16
580 [-]: GETGLOBAL R16 K63      ; R16 := 0x7ed0a956
581 [-]: LOADK     R17 K329     ; R17 := "/Lotus/Types/Items/ShipFeatureItems/VoidProjectionFeatureItem"
582 [-]: CALL      R16 2 2      ; R16 := R16(R17)
583 [-]: SETGLOBAL R16 K328     ; SF_VOID_PROJECTION := R16
584 [-]: GETGLOBAL R16 K63      ; R16 := 0x7ed0a956
585 [-]: LOADK     R17 K331     ; R17 := "/Lotus/Types/Items/ShipFeatureItems/PersonalQuartersFeatureItem"
586 [-]: CALL      R16 2 2      ; R16 := R16(R17)
587 [-]: SETGLOBAL R16 K330     ; SF_PERSONAL_QUARTERS := R16
588 [-]: GETGLOBAL R16 K63      ; R16 := 0x7ed0a956
589 [-]: LOADK     R17 K333     ; R17 := "/Lotus/Types/Items/ShipFeatureItems/RailjackCephalonShipFeatureItem"
590 [-]: CALL      R16 2 2      ; R16 := R16(R17)
591 [-]: SETGLOBAL R16 K332     ; SF_RAILJACK_CEPHALON := R16
592 [-]: GETGLOBAL R16 K63      ; R16 := 0x7ed0a956
593 [-]: LOADK     R17 K335     ; R17 := "/Lotus/Types/Items/ShipFeatureItems/RailjackKeyShipFeatureItem"
594 [-]: CALL      R16 2 2      ; R16 := R16(R17)
595 [-]: SETGLOBAL R16 K334     ; SF_RAILJACK_KEY := R16
596 [-]: GETGLOBAL R16 K63      ; R16 := 0x7ed0a956
597 [-]: LOADK     R17 K337     ; R17 := "/Lotus/Types/Items/ShipFeatureItems/AdvancedOrdisFeatureItem"
598 [-]: CALL      R16 2 2      ; R16 := R16(R17)
599 [-]: SETGLOBAL R16 K336     ; SF_ADVANCED_ORDIS := R16
600 [-]: LOADK     R16 20       ; R16 := 20.000000
601 [-]: SETGLOBAL R16 K338     ; MAX_PVE_EXTRA_LOADOUTS := R16
602 [-]: LOADK     R16 20       ; R16 := 20.000000
603 [-]: SETGLOBAL R16 K339     ; MAX_PVP_LOADOUTS := R16
604 [-]: NEWTABLE  R16 0 5      ; R16 := {}
605 [-]: LOADK     R17 K341     ; R17 := "VoidT1"
606 [-]: GETGLOBAL R18 K63      ; R18 := 0x7ed0a956
607 [-]: LOADK     R19 K342     ; R19 := "/Lotus/Types/Game/Projections/T1VoidProjection"
608 [-]: CALL      R18 2 2      ; R18 := R18(R19)
609 [-]: SETTABLE  R16 R17 R18  ; R16[R17] := R18
610 [-]: LOADK     R17 K343     ; R17 := "VoidT2"
611 [-]: GETGLOBAL R18 K63      ; R18 := 0x7ed0a956
612 [-]: LOADK     R19 K344     ; R19 := "/Lotus/Types/Game/Projections/T2VoidProjection"
613 [-]: CALL      R18 2 2      ; R18 := R18(R19)
614 [-]: SETTABLE  R16 R17 R18  ; R16[R17] := R18
615 [-]: LOADK     R17 K345     ; R17 := "VoidT3"
616 [-]: GETGLOBAL R18 K63      ; R18 := 0x7ed0a956
617 [-]: LOADK     R19 K346     ; R19 := "/Lotus/Types/Game/Projections/T3VoidProjection"
618 [-]: CALL      R18 2 2      ; R18 := R18(R19)
619 [-]: SETTABLE  R16 R17 R18  ; R16[R17] := R18
620 [-]: LOADK     R17 K347     ; R17 := "VoidT4"
621 [-]: GETGLOBAL R18 K63      ; R18 := 0x7ed0a956
622 [-]: LOADK     R19 K348     ; R19 := "/Lotus/Types/Game/Projections/T4VoidProjection"
623 [-]: CALL      R18 2 2      ; R18 := R18(R19)
624 [-]: SETTABLE  R16 R17 R18  ; R16[R17] := R18
625 [-]: LOADK     R17 K349     ; R17 := "VoidT5"
626 [-]: GETGLOBAL R18 K63      ; R18 := 0x7ed0a956
627 [-]: LOADK     R19 K350     ; R19 := "/Lotus/Types/Game/Projections/T5VoidProjectionImmortal"
628 [-]: CALL      R18 2 2      ; R18 := R18(R19)
629 [-]: SETTABLE  R16 R17 R18  ; R16[R17] := R18
630 [-]: SETGLOBAL R16 K340     ; VOID_PROJECTION_ITEMS := R16
631 [-]: NEWTABLE  R16 0 4      ; R16 := {}
632 [-]: NEWTABLE  R17 0 2      ; R17 := {}
633 [-]: LOADK     R18 K352     ; R18 := "levelOverride"
634 [-]: GETGLOBAL R19 K63      ; R19 := 0x7ed0a956
635 [-]: LOADK     R20 K353     ; R20 := "/Lotus/Level