; This file has been disassembled using luadec 2.0.2 by sztupy (modified by Reversive)

; Name:            
; Defined at line: 0
; #Upvalues:       0
; #Parameters:     0
; Is_vararg:       2
; Max Stack Size:  101

  1 [-]: GETGLOBAL R0 K0        ; R0 := 0x2d0fad09
  2 [-]: LOADK     R1 K1        ; R1 := "EE.Interface.Utilities"
  3 [-]: CALL      R0 2 2       ; R0 := R0(R1)
  4 [-]: GETGLOBAL R1 K0        ; R1 := 0x2d0fad09
  5 [-]: LOADK     R2 K2        ; R2 := "Lotus.Interface.LotusUtilities"
  6 [-]: CALL      R1 2 2       ; R1 := R1(R2)
  7 [-]: GETGLOBAL R2 K0        ; R2 := 0x2d0fad09
  8 [-]: LOADK     R3 K3        ; R3 := "Lotus.Scripts.Libs.PlayerSkillsLib"
  9 [-]: CALL      R2 2 2       ; R2 := R2(R3)
 10 [-]: GETGLOBAL R3 K0        ; R3 := 0x2d0fad09
 11 [-]: LOADK     R4 K4        ; R4 := "EE.Interface.AnchorMgr"
 12 [-]: CALL      R3 2 2       ; R3 := R3(R4)
 13 [-]: LOADNIL   R4 R5        ; R4 := R5 := nil
 14 [-]: LOADKB    R6 1 0       ; R6 := true
 15 [-]: LOADKB    R7 0 0       ; R7 := false
 16 [-]: LOADKB    R8 0 0       ; R8 := false
 17 [-]: LOADKB    R9 0 0       ; R9 := false
 18 [-]: LOADNIL   R10 R13      ; R10 := R11 := R12 := R13 := nil
 19 [-]: LOADKB    R14 0 0      ; R14 := false
 20 [-]: LOADKB    R15 0 0      ; R15 := false
 21 [-]: LOADNIL   R16 R18      ; R16 := R17 := R18 := nil
 22 [-]: LOADKB    R19 0 0      ; R19 := false
 23 [-]: LOADKB    R20 1 0      ; R20 := true
 24 [-]: LOADKB    R21 0 0      ; R21 := false
 25 [-]: LOADKB    R22 0 0      ; R22 := false
 26 [-]: CONST     R23 1        ; R23 := 1.000000
 27 [-]: CONST     R24 0        ; R24 := 0.000000
 28 [-]: LOADKB    R25 1 0      ; R25 := true
 29 [-]: LOADKB    R26 0 0      ; R26 := false
 30 [-]: LOADKB    R27 1 0      ; R27 := true
 31 [-]: LOADNIL   R28 R28      ; R28 := nil
 32 [-]: LOADKB    R29 0 0      ; R29 := false
 33 [-]: CONST     R30 1600     ; R30 := 1600.000000
 34 [-]: CONST     R31 900      ; R31 := 900.000000
 35 [-]: LOADNIL   R32 R32      ; R32 := nil
 36 [-]: LOADKB    R33 0 0      ; R33 := false
 37 [-]: LOADNIL   R34 R37      ; R34 := R35 := R36 := R37 := nil
 38 [-]: LOADKB    R38 0 0      ; R38 := false
 39 [-]: LOADKB    R39 0 0      ; R39 := false
 40 [-]: NEWTABLE  R40 0 2      ; R40 := {}
 41 [-]: SETTABLE  R40 K5 K6    ; R40["x"] := 0.000000
 42 [-]: SETTABLE  R40 K7 K6    ; R40["y"] := 0.000000
 43 [-]: LOADNIL   R41 R41      ; R41 := nil
 44 [-]: GETGLOBAL R42 K8       ; R42 := 0x78ca68a2
 45 [-]: CONST     R43 2        ; R43 := 2.000000
 46 [-]: LOADK     R44 K9       ; R44 := 0.175000
 47 [-]: CALL      R42 3 2      ; R42 := R42(R43,R44)
 48 [-]: CONST     R43 0        ; R43 := 0.500000
 49 [-]: CONST     R44 4        ; R44 := 4.000000
 50 [-]: LOADKB    R45 1 0      ; R45 := true
 51 [-]: NEWTABLE  R46 0 2      ; R46 := {}
 52 [-]: SETTABLE  R46 K5 K6    ; R46["x"] := 0.000000
 53 [-]: SETTABLE  R46 K7 K6    ; R46["y"] := 0.000000
 54 [-]: CONST     R47 0        ; R47 := 0.000000
 55 [-]: LOADNIL   R48 R49      ; R48 := R49 := nil
 56 [-]: NEWTABLE  R50 0 0      ; R50 := {}
 57 [-]: LOADNIL   R51 R55      ; R51 := R52 := R53 := R54 := R55 := nil
 58 [-]: GETGLOBAL R56 K10      ; R56 := 0xa421af95
 59 [-]: CALL      R56 1 2      ; R56 := R56()
 60 [-]: GETGLOBAL R57 K10      ; R57 := 0xa421af95
 61 [-]: CALL      R57 1 2      ; R57 := R57()
 62 [-]: NEWTABLE  R58 0 3      ; R58 := {}
 63 [-]: GETGLOBAL R59 K12      ; R59 := 0x34291f5c
 64 [-]: GETTABLE  R59 R59 K13  ; R59 := R59[0x1467d5f4]
 65 [-]: CALL      R59 1 2      ; R59 := R59()
 66 [-]: SETTABLE  R58 K11 R59  ; R58["IsVisible"] := R59
 67 [-]: SETTABLE  R58 K14 K6   ; R58["X"] := 0.000000
 68 [-]: SETTABLE  R58 K15 K6   ; R58["Y"] := 0.000000
 69 [-]: LOADKB    R59 0 0      ; R59 := false
 70 [-]: LOADK     R60 K16      ; R60 := 0.100000
 71 [-]: CONST     R61 75       ; R61 := 75.000000
 72 [-]: NEWTABLE  R62 4 0      ; R62 := {}
 73 [-]: NEWTABLE  R63 0 3      ; R63 := {}
 74 [-]: SETTABLE  R63 K17 K6   ; R63["DAY"] := 0.000000
 75 [-]: SETTABLE  R63 K18 K19  ; R63["NIGHT"] := -179.000000
 76 [-]: SETTABLE  R63 K20 K6   ; R63["BACKER"] := 0.000000
 77 [-]: NEWTABLE  R64 0 3      ; R64 := {}
 78 [-]: SETTABLE  R64 K17 K21  ; R64["DAY"] := 20.000000
 79 [-]: SETTABLE  R64 K18 K22  ; R64["NIGHT"] := -20.000000
 80 [-]: SETTABLE  R64 K20 K23  ; R64["BACKER"] := 90.000000
 81 [-]: NEWTABLE  R65 0 3      ; R65 := {}
 82 [-]: SETTABLE  R65 K17 K24  ; R65["DAY"] := 179.000000
 83 [-]: SETTABLE  R65 K18 K6   ; R65["NIGHT"] := 0.000000
 84 [-]: SETTABLE  R65 K20 K25  ; R65["BACKER"] := 180.000000
 85 [-]: NEWTABLE  R66 0 3      ; R66 := {}
 86 [-]: SETTABLE  R66 K17 K21  ; R66["DAY"] := 20.000000
 87 [-]: SETTABLE  R66 K18 K22  ; R66["NIGHT"] := -20.000000
 88 [-]: SETTABLE  R66 K20 K23  ; R66["BACKER"] := 90.000000
 89 [-]: SETLIST   R62 4 1      ; R62[(1-1)*FPF+i] := R(62+i), 1 <= i <= 4
 90 [-]: LOADKB    R63 0 0      ; R63 := false
 91 [-]: LOADKB    R64 0 0      ; R64 := false
 92 [-]: LOADNIL   R65 R67      ; R65 := R66 := R67 := nil
 93 [-]: LOADKB    R68 0 0      ; R68 := false
 94 [-]: CLOSURE   R69 0        ; R69 := closure(Function #1)
 95 [-]: CLOSURE   R70 1        ; R70 := closure(Function #2)
 96 [-]: CLOSURE   R71 2        ; R71 := closure(Function #3)
 97 [-]: CLOSURE   R72 3        ; R72 := closure(Function #4)
 98 [-]: MOVE      R0 R58       ; R0 := R58
 99 [-]: CLOSURE   R73 4        ; R73 := closure(Function #5)
100 [-]: MOVE      R0 R0        ; R0 := R0
101 [-]: MOVE      R0 R58       ; R0 := R58
102 [-]: MOVE      R0 R71       ; R0 := R71
103 [-]: NEWTABLE  R74 0 0      ; R74 := {}
104 [-]: CLOSURE   R75 5        ; R75 := closure(Function #6)
105 [-]: MOVE      R0 R74       ; R0 := R74
106 [-]: SETGLOBAL R75 K26      ; ResetBuddyEffects := R75
107 [-]: CLOSURE   R75 6        ; R75 := closure(Function #7)
108 [-]: MOVE      R0 R15       ; R0 := R15
109 [-]: MOVE      R0 R74       ; R0 := R74
110 [-]: CLOSURE   R76 7        ; R76 := closure(Function #8)
111 [-]: MOVE      R0 R75       ; R0 := R75
112 [-]: MOVE      R0 R24       ; R0 := R24
113 [-]: CLOSURE   R77 8        ; R77 := closure(Function #9)
114 [-]: MOVE      R0 R36       ; R0 := R36
115 [-]: MOVE      R0 R30       ; R0 := R30
116 [-]: CLOSURE   R78 9        ; R78 := closure(Function #10)
117 [-]: MOVE      R0 R49       ; R0 := R49
118 [-]: MOVE      R0 R0        ; R0 := R0
119 [-]: MOVE      R0 R5        ; R0 := R5
120 [-]: MOVE      R0 R78       ; R0 := R78
121 [-]: CLOSURE   R79 10       ; R79 := closure(Function #11)
122 [-]: MOVE      R0 R6        ; R0 := R6
123 [-]: MOVE      R0 R36       ; R0 := R36
124 [-]: MOVE      R0 R78       ; R0 := R78
125 [-]: MOVE      R0 R39       ; R0 := R39
126 [-]: MOVE      R0 R0        ; R0 := R0
127 [-]: MOVE      R0 R18       ; R0 := R18
128 [-]: CLOSURE   R80 11       ; R80 := closure(Function #12)
129 [-]: MOVE      R0 R29       ; R0 := R29
130 [-]: MOVE      R0 R8        ; R0 := R8
131 [-]: MOVE      R0 R11       ; R0 := R11
132 [-]: MOVE      R0 R36       ; R0 := R36
133 [-]: MOVE      R0 R41       ; R0 := R41
134 [-]: MOVE      R0 R42       ; R0 := R42
135 [-]: MOVE      R0 R0        ; R0 := R0
136 [-]: MOVE      R0 R25       ; R0 := R25
137 [-]: MOVE      R0 R79       ; R0 := R79
138 [-]: CLOSURE   R81 12       ; R81 := closure(Function #13)
139 [-]: MOVE      R0 R21       ; R0 := R21
140 [-]: MOVE      R0 R22       ; R0 := R22
141 [-]: MOVE      R0 R23       ; R0 := R23
142 [-]: CLOSURE   R82 13       ; R82 := closure(Function #14)
143 [-]: MOVE      R0 R81       ; R0 := R81
144 [-]: SETGLOBAL R82 K27      ; OnProfileSaved := R82
145 [-]: CLOSURE   R82 14       ; R82 := closure(Function #15)
146 [-]: MOVE      R0 R58       ; R0 := R58
147 [-]: MOVE      R0 R0        ; R0 := R0
148 [-]: MOVE      R0 R30       ; R0 := R30
149 [-]: MOVE      R0 R31       ; R0 := R31
150 [-]: MOVE      R0 R36       ; R0 := R36
151 [-]: CLOSURE   R83 15       ; R83 := closure(Function #16)
152 [-]: MOVE      R0 R11       ; R0 := R11
153 [-]: MOVE      R0 R53       ; R0 := R53
154 [-]: MOVE      R0 R54       ; R0 := R54
155 [-]: MOVE      R0 R55       ; R0 := R55
156 [-]: MOVE      R0 R30       ; R0 := R30
157 [-]: MOVE      R0 R31       ; R0 := R31
158 [-]: MOVE      R0 R43       ; R0 := R43
159 [-]: MOVE      R0 R23       ; R0 := R23
160 [-]: MOVE      R0 R42       ; R0 := R42
161 [-]: MOVE      R0 R82       ; R0 := R82
162 [-]: MOVE      R0 R36       ; R0 := R36
163 [-]: MOVE      R0 R48       ; R0 := R48
164 [-]: MOVE      R0 R5        ; R0 := R5
165 [-]: MOVE      R0 R78       ; R0 := R78
166 [-]: CLOSURE   R84 16       ; R84 := closure(Function #17)
167 [-]: MOVE      R0 R41       ; R0 := R41
168 [-]: MOVE      R0 R11       ; R0 := R11
169 [-]: MOVE      R0 R45       ; R0 := R45
170 [-]: MOVE      R0 R56       ; R0 := R56
171 [-]: MOVE      R0 R57       ; R0 := R57
172 [-]: MOVE      R0 R53       ; R0 := R53
173 [-]: MOVE      R0 R54       ; R0 := R54
174 [-]: MOVE      R0 R55       ; R0 := R55
175 [-]: MOVE      R0 R31       ; R0 := R31
176 [-]: MOVE      R0 R30       ; R0 := R30
177 [-]: MOVE      R0 R58       ; R0 := R58
178 [-]: MOVE      R0 R42       ; R0 := R42
179 [-]: MOVE      R0 R43       ; R0 := R43
180 [-]: MOVE      R0 R0        ; R0 := R0
181 [-]: CLOSURE   R85 17       ; R85 := closure(Function #18)
182 [-]: MOVE      R0 R42       ; R0 := R42
183 [-]: MOVE      R0 R11       ; R0 := R11
184 [-]: MOVE      R0 R10       ; R0 := R10
185 [-]: MOVE      R0 R30       ; R0 := R30
186 [-]: MOVE      R0 R41       ; R0 := R41
187 [-]: MOVE      R0 R31       ; R0 := R31
188 [-]: CLOSURE   R86 18       ; R86 := closure(Function #19)
189 [-]: MOVE      R0 R10       ; R0 := R10
190 [-]: MOVE      R0 R13       ; R0 := R13
191 [-]: MOVE      R0 R12       ; R0 := R12
192 [-]: MOVE      R0 R14       ; R0 := R14
193 [-]: MOVE      R0 R15       ; R0 := R15
194 [-]: MOVE      R0 R81       ; R0 := R81
195 [-]: MOVE      R0 R77       ; R0 := R77
196 [-]: MOVE      R0 R11       ; R0 := R11
197 [-]: MOVE      R0 R83       ; R0 := R83
198 [-]: MOVE      R0 R84       ; R0 := R84
199 [-]: MOVE      R0 R80       ; R0 := R80
200 [-]: MOVE      R0 R9        ; R0 := R9
201 [-]: CLOSURE   R87 19       ; R87 := closure(Function #20)
202 [-]: MOVE      R0 R0        ; R0 := R0
203 [-]: CLOSURE   R88 20       ; R88 := closure(Function #21)
204 [-]: MOVE      R0 R1        ; R0 := R1
205 [-]: MOVE      R0 R35       ; R0 := R35
206 [-]: CLOSURE   R89 21       ; R89 := closure(Function #22)
207 [-]: MOVE      R0 R0        ; R0 := R0
208 [-]: CLOSURE   R90 22       ; R90 := closure(Function #23)
209 [-]: MOVE      R0 R5        ; R0 := R5
210 [-]: MOVE      R0 R4        ; R0 := R4
211 [-]: MOVE      R0 R3        ; R0 := R3
212 [-]: MOVE      R0 R30       ; R0 := R30
213 [-]: MOVE      R0 R31       ; R0 := R31
214 [-]: MOVE      R0 R87       ; R0 := R87
215 [-]: MOVE      R0 R88       ; R0 := R88
216 [-]: MOVE      R0 R72       ; R0 := R72
217 [-]: MOVE      R0 R58       ; R0 := R58
218 [-]: MOVE      R0 R2        ; R0 := R2
219 [-]: MOVE      R0 R1        ; R0 := R1
220 [-]: MOVE      R0 R39       ; R0 := R39
221 [-]: MOVE      R0 R38       ; R0 := R38
222 [-]: MOVE      R0 R37       ; R0 := R37
223 [-]: MOVE      R0 R64       ; R0 := R64
224 [-]: MOVE      R0 R63       ; R0 := R63
225 [-]: MOVE      R0 R89       ; R0 := R89
226 [-]: MOVE      R0 R7        ; R0 := R7
227 [-]: SETGLOBAL R90 K28      ; Initialize := R90
228 [-]: CLOSURE   R90 23       ; R90 := closure(Function #24)
229 [-]: MOVE      R0 R29       ; R0 := R29
230 [-]: MOVE      R0 R66       ; R0 := R66
231 [-]: MOVE      R0 R36       ; R0 := R36
232 [-]: MOVE      R0 R0        ; R0 := R0
233 [-]: MOVE      R0 R11       ; R0 := R11
234 [-]: MOVE      R0 R32       ; R0 := R32
235 [-]: MOVE      R0 R6        ; R0 := R6
236 [-]: MOVE      R0 R25       ; R0 := R25
237 [-]: MOVE      R0 R28       ; R0 := R28
238 [-]: MOVE      R0 R8        ; R0 := R8
239 [-]: CLOSURE   R91 24       ; R91 := closure(Function #25)
240 [-]: MOVE      R0 R90       ; R0 := R90
241 [-]: SETGLOBAL R91 K29      ; Close := R91
242 [-]: CLOSURE   R91 25       ; R91 := closure(Function #26)
243 [-]: MOVE      R0 R90       ; R0 := R90
244 [-]: MOVE      R0 R36       ; R0 := R36
245 [-]: SETGLOBAL R91 K30      ; Hide := R91
246 [-]: CLOSURE   R91 26       ; R91 := closure(Function #27)
247 [-]: MOVE      R0 R25       ; R0 := R25
248 [-]: MOVE      R0 R90       ; R0 := R90
249 [-]: MOVE      R0 R80       ; R0 := R80
250 [-]: SETGLOBAL R91 K31      ; ToggleVisibility := R91
251 [-]: CLOSURE   R66 27       ; R66 := closure(Function #28)
252 [-]: MOVE      R0 R29       ; R0 := R29
253 [-]: MOVE      R0 R36       ; R0 := R36
254 [-]: MOVE      R0 R90       ; R0 := R90
255 [-]: CLOSURE   R91 28       ; R91 := closure(Function #29)
256 [-]: MOVE      R0 R36       ; R0 := R36
257 [-]: MOVE      R0 R77       ; R0 := R77
258 [-]: MOVE      R0 R28       ; R0 := R28
259 [-]: MOVE      R0 R72       ; R0 := R72
260 [-]: MOVE      R0 R11       ; R0 := R11
261 [-]: MOVE      R0 R83       ; R0 := R83
262 [-]: MOVE      R0 R41       ; R0 := R41
263 [-]: MOVE      R0 R84       ; R0 := R84
264 [-]: MOVE      R0 R32       ; R0 := R32
265 [-]: MOVE      R0 R66       ; R0 := R66
266 [-]: MOVE      R0 R58       ; R0 := R58
267 [-]: MOVE      R0 R20       ; R0 := R20
268 [-]: MOVE      R0 R19       ; R0 := R19
269 [-]: MOVE      R0 R37       ; R0 := R37
270 [-]: MOVE      R0 R0        ; R0 := R0
271 [-]: CLOSURE   R92 29       ; R92 := closure(Function #30)
272 [-]: MOVE      R0 R29       ; R0 := R29
273 [-]: MOVE      R0 R36       ; R0 := R36
274 [-]: MOVE      R0 R91       ; R0 := R91
275 [-]: MOVE      R0 R11       ; R0 := R11
276 [-]: MOVE      R0 R28       ; R0 := R28
277 [-]: SETGLOBAL R92 K32      ; SetAdvancedMode := R92
278 [-]: CLOSURE   R92 30       ; R92 := closure(Function #31)
279 [-]: MOVE      R0 R11       ; R0 := R11
280 [-]: MOVE      R0 R51       ; R0 := R51
281 [-]: MOVE      R0 R52       ; R0 := R52
282 [-]: SETGLOBAL R92 K33      ; Shutdown := R92
283 [-]: CLOSURE   R92 31       ; R92 := closure(Function #32)
284 [-]: MOVE      R0 R65       ; R0 := R65
285 [-]: MOVE      R0 R62       ; R0 := R62
286 [-]: CLOSURE   R93 32       ; R93 := closure(Function #33)
287 [-]: MOVE      R0 R1        ; R0 := R1
288 [-]: MOVE      R0 R35       ; R0 := R35
289 [-]: MOVE      R0 R63       ; R0 := R63
290 [-]: MOVE      R0 R92       ; R0 := R92
291 [-]: MOVE      R0 R64       ; R0 := R64
292 [-]: MOVE      R0 R0        ; R0 := R0
293 [-]: CLOSURE   R94 33       ; R94 := closure(Function #34)
294 [-]: CLOSURE   R95 34       ; R95 := closure(Function #35)
295 [-]: MOVE      R0 R7        ; R0 := R7
296 [-]: MOVE      R0 R8        ; R0 := R8
297 [-]: MOVE      R0 R34       ; R0 := R34
298 [-]: MOVE      R0 R26       ; R0 := R26
299 [-]: MOVE      R0 R10       ; R0 := R10
300 [-]: MOVE      R0 R9        ; R0 := R9
301 [-]: MOVE      R0 R88       ; R0 := R88
302 [-]: MOVE      R0 R86       ; R0 := R86
303 [-]: MOVE      R0 R5        ; R0 := R5
304 [-]: MOVE      R0 R36       ; R0 := R36
305 [-]: MOVE      R0 R37       ; R0 := R37
306 [-]: MOVE      R0 R11       ; R0 := R11
307 [-]: MOVE      R0 R20       ; R0 := R20
308 [-]: MOVE      R0 R19       ; R0 := R19
309 [-]: MOVE      R0 R93       ; R0 := R93
310 [-]: MOVE      R0 R49       ; R0 := R49
311 [-]: MOVE      R0 R33       ; R0 := R33
312 [-]: MOVE      R0 R16       ; R0 := R16
313 [-]: MOVE      R0 R39       ; R0 := R39
314 [-]: MOVE      R0 R17       ; R0 := R17
315 [-]: MOVE      R0 R18       ; R0 := R18
316 [-]: MOVE      R0 R27       ; R0 := R27
317 [-]: MOVE      R0 R25       ; R0 := R25
318 [-]: MOVE      R0 R42       ; R0 := R42
319 [-]: MOVE      R0 R41       ; R0 := R41
320 [-]: MOVE      R0 R46       ; R0 := R46
321 [-]: MOVE      R0 R61       ; R0 := R61
322 [-]: MOVE      R0 R47       ; R0 := R47
323 [-]: MOVE      R0 R60       ; R0 := R60
324 [-]: MOVE      R0 R43       ; R0 := R43
325 [-]: MOVE      R0 R44       ; R0 := R44
326 [-]: MOVE      R0 R58       ; R0 := R58
327 [-]: MOVE      R0 R45       ; R0 := R45
328 [-]: MOVE      R0 R56       ; R0 := R56
329 [-]: MOVE      R0 R84       ; R0 := R84
330 [-]: MOVE      R0 R57       ; R0 := R57
331 [-]: MOVE      R0 R21       ; R0 := R21
332 [-]: MOVE      R0 R76       ; R0 := R76
333 [-]: MOVE      R0 R68       ; R0 := R68
334 [-]: SETGLOBAL R95 K34      ; Update := R95
335 [-]: CLOSURE   R95 35       ; R95 := closure(Function #36)
336 [-]: MOVE      R0 R77       ; R0 := R77
337 [-]: MOVE      R0 R4        ; R0 := R4
338 [-]: MOVE      R0 R87       ; R0 := R87
339 [-]: MOVE      R0 R89       ; R0 := R89
340 [-]: SETGLOBAL R95 K35      ; onViewportSizeChanged := R95
341 [-]: CLOSURE   R67 36       ; R67 := closure(Function #37)
342 [-]: MOVE      R0 R11       ; R0 := R11
343 [-]: MOVE      R0 R42       ; R0 := R42
344 [-]: MOVE      R0 R10       ; R0 := R10
345 [-]: MOVE      R0 R53       ; R0 := R53
346 [-]: MOVE      R0 R30       ; R0 := R30
347 [-]: MOVE      R0 R41       ; R0 := R41
348 [-]: MOVE      R0 R54       ; R0 := R54
349 [-]: MOVE      R0 R31       ; R0 := R31
350 [-]: CLOSURE   R95 37       ; R95 := closure(Function #38)
351 [-]: MOVE      R0 R11       ; R0 := R11
352 [-]: MOVE      R0 R51       ; R0 := R51
353 [-]: MOVE      R0 R52       ; R0 := R52
354 [-]: CLOSURE   R96 38       ; R96 := closure(Function #39)
355 [-]: MOVE      R0 R51       ; R0 := R51
356 [-]: MOVE      R0 R95       ; R0 := R95
357 [-]: MOVE      R0 R11       ; R0 := R11
358 [-]: MOVE      R0 R0        ; R0 := R0
359 [-]: MOVE      R0 R52       ; R0 := R52
360 [-]: CLOSURE   R97 39       ; R97 := closure(Function #40)
361 [-]: MOVE      R0 R96       ; R0 := R96
362 [-]: SETGLOBAL R97 K36      ; MarkerRollOverCallback := R97
363 [-]: CLOSURE   R97 40       ; R97 := closure(Function #41)
364 [-]: MOVE      R0 R95       ; R0 := R95
365 [-]: SETGLOBAL R97 K37      ; MarkerRollOutCallback := R97
366 [-]: CLOSURE   R97 41       ; R97 := closure(Function #42)
367 [-]: MOVE      R0 R51       ; R0 := R51
368 [-]: MOVE      R0 R0        ; R0 := R0
369 [-]: CLOSURE   R98 42       ; R98 := closure(Function #43)
370 [-]: MOVE      R0 R41       ; R0 := R41
371 [-]: MOVE      R0 R97       ; R0 := R97
372 [-]: SETGLOBAL R98 K38      ; MarkerSelectCallback := R98
373 [-]: CLOSURE   R98 43       ; R98 := closure(Function #44)
374 [-]: MOVE      R0 R51       ; R0 := R51
375 [-]: MOVE      R0 R96       ; R0 := R96
376 [-]: MOVE      R0 R97       ; R0 := R97
377 [-]: SETGLOBAL R98 K39      ; MarkerReleaseCallback := R98
378 [-]: CLOSURE   R98 44       ; R98 := closure(Function #45)
379 [-]: MOVE      R0 R97       ; R0 := R97
380 [-]: SETGLOBAL R98 K40      ; onKeyUp_MENU_SELECT := R98
381 [-]: CLOSURE   R98 45       ; R98 := closure(Function #46)
382 [-]: MOVE      R0 R6        ; R0 := R6
383 [-]: MOVE      R0 R90       ; R0 := R90
384 [-]: SETGLOBAL R98 K41      ; onKeyUp_MENU_CANCEL := R98
385 [-]: CLOSURE   R98 46       ; R98 := closure(Function #47)
386 [-]: MOVE      R0 R51       ; R0 := R51
387 [-]: MOVE      R0 R68       ; R0 := R68
388 [-]: MOVE      R0 R41       ; R0 := R41
389 [-]: SETGLOBAL R98 K42      ; onKeyDown_MENU_CLICK := R98
390 [-]: CLOSURE   R98 47       ; R98 := closure(Function #48)
391 [-]: MOVE      R0 R41       ; R0 := R41
392 [-]: MOVE      R0 R68       ; R0 := R68
393 [-]: MOVE      R0 R51       ; R0 := R51
394 [-]: SETGLOBAL R98 K43      ; onKeyUp_MENU_CLICK := R98
395 [-]: CLOSURE   R98 48       ; R98 := closure(Function #49)
396 [-]: MOVE      R0 R59       ; R0 := R59
397 [-]: SETGLOBAL R98 K44      ; onKeyDown_MENU_RIGHT_CLICK := R98
398 [-]: CLOSURE   R98 49       ; R98 := closure(Function #50)
399 [-]: MOVE      R0 R59       ; R0 := R59
400 [-]: MOVE      R0 R67       ; R0 := R67
401 [-]: MOVE      R0 R10       ; R0 := R10
402 [-]: MOVE      R0 R40       ; R0 := R40
403 [-]: MOVE      R0 R85       ; R0 := R85
404 [-]: MOVE      R0 R0        ; R0 := R0
405 [-]: SETGLOBAL R98 K45      ; onKeyUp_MENU_RIGHT_CLICK := R98
406 [-]: CLOSURE   R98 50       ; R98 := closure(Function #51)
407 [-]: MOVE      R0 R0        ; R0 := R0
408 [-]: MOVE      R0 R47       ; R0 := R47
409 [-]: SETGLOBAL R98 K46      ; onKeyDown_MENU_MOUSE_Z := R98
410 [-]: CLOSURE   R98 51       ; R98 := closure(Function #52)
411 [-]: MOVE      R0 R46       ; R0 := R46
412 [-]: MOVE      R0 R0        ; R0 := R0
413 [-]: CLOSURE   R99 52       ; R99 := closure(Function #53)
414 [-]: MOVE      R0 R46       ; R0 := R46
415 [-]: MOVE      R0 R0        ; R0 := R0
416 [-]: CLOSURE   R100 53      ; R100 := closure(Function #54)
417 [-]: MOVE      R0 R98       ; R0 := R98
418 [-]: SETGLOBAL R100 K47     ; onKeyDown_MENU_UP := R100
419 [-]: CLOSURE   R100 54      ; R100 := closure(Function #55)
420 [-]: MOVE      R0 R46       ; R0 := R46
421 [-]: MOVE      R0 R98       ; R0 := R98
422 [-]: SETGLOBAL R100 K48     ; onKeyUp_MENU_UP := R100
423 [-]: CLOSURE   R100 55      ; R100 := closure(Function #56)
424 [-]: MOVE      R0 R98       ; R0 := R98
425 [-]: SETGLOBAL R100 K49     ; onKeyDown_MENU_DOWN := R100
426 [-]: CLOSURE   R100 56      ; R100 := closure(Function #57)
427 [-]: MOVE      R0 R46       ; R0 := R46
428 [-]: MOVE      R0 R98       ; R0 := R98
429 [-]: SETGLOBAL R100 K50     ; onKeyUp_MENU_DOWN := R100
430 [-]: CLOSURE   R100 57      ; R100 := closure(Function #58)
431 [-]: MOVE      R0 R99       ; R0 := R99
432 [-]: SETGLOBAL R100 K51     ; onKeyDown_MENU_LEFT := R100
433 [-]: CLOSURE   R100 58      ; R100 := closure(Function #59)
434 [-]: MOVE      R0 R46       ; R0 := R46
435 [-]: MOVE      R0 R99       ; R0 := R99
436 [-]: SETGLOBAL R100 K52     ; onKeyUp_MENU_LEFT := R100
437 [-]: CLOSURE   R100 59      ; R100 := closure(Function #60)
438 [-]: MOVE      R0 R99       ; R0 := R99
439 [-]: SETGLOBAL R100 K53     ; onKeyDown_MENU_RIGHT := R100
440 [-]: CLOSURE   R100 60      ; R100 := closure(Function #61)
441 [-]: MOVE      R0 R46       ; R0 := R46
442 [-]: MOVE      R0 R99       ; R0 := R99
443 [-]: SETGLOBAL R100 K54     ; onKeyUp_MENU_RIGHT := R100
444 [-]: CLOSURE   R100 61      ; R100 := closure(Function #62)
445 [-]: MOVE      R0 R6        ; R0 := R6
446 [-]: MOVE      R0 R99       ; R0 := R99
447 [-]: SETGLOBAL R100 K55     ; onKeyDown_MENU_X := R100
448 [-]: CLOSURE   R100 62      ; R100 := closure(Function #63)
449 [-]: MOVE      R0 R6        ; R0 := R6
450 [-]: MOVE      R0 R99       ; R0 := R99
451 [-]: SETGLOBAL R100 K56     ; onKeyUp_MENU_X := R100
452 [-]: CLOSURE   R100 63      ; R100 := closure(Function #64)
453 [-]: MOVE      R0 R6        ; R0 := R6
454 [-]: MOVE      R0 R98       ; R0 := R98
455 [-]: SETGLOBAL R100 K57     ; onKeyDown_MENU_Y := R100
456 [-]: CLOSURE   R100 64      ; R100 := closure(Function #65)
457 [-]: MOVE      R0 R6        ; R0 := R6
458 [-]: MOVE      R0 R98       ; R0 := R98
459 [-]: SETGLOBAL R100 K58     ; onKeyUp_MENU_Y := R100
460 [-]: CLOSURE   R100 65      ; R100 := closure(Function #66)
461 [-]: MOVE      R0 R6        ; R0 := R6
462 [-]: MOVE      R0 R47       ; R0 := R47
463 [-]: SETGLOBAL R100 K59     ; onKeyDown_MENU_RIGHT_Y := R100
464 [-]: CLOSURE   R100 66      ; R100 := closure(Function #67)
465 [-]: MOVE      R0 R6        ; R0 := R6
466 [-]: MOVE      R0 R47       ; R0 := R47
467 [-]: SETGLOBAL R100 K60     ; onKeyUp_MENU_RIGHT_Y := R100
468 [-]: CLOSURE   R100 67      ; R100 := closure(Function #68)
469 [-]: MOVE      R0 R99       ; R0 := R99
470 [-]: MOVE      R0 R98       ; R0 := R98
471 [-]: SETGLOBAL R100 K61     ; onKeyDown_TOGGLE_CHAT_WINDOW := R100
472 [-]: CLOSURE   R100 68      ; R100 := closure(Function #69)
473 [-]: MOVE      R0 R99       ; R0 := R99
474 [-]: MOVE      R0 R98       ; R0 := R98
475 [-]: SETGLOBAL R100 K62     ; onKeyDown_TOGGLE_CHAT_WINDOW_ALT := R100
476 [-]: CLOSURE   R100 69      ; R100 := closure(Function #70)
477 [-]: MOVE      R0 R90       ; R0 := R90
478 [-]: SETGLOBAL R100 K63     ; onKeyDown_SHOW_LEVEL_MAP := R100
479 [-]: CLOSURE   R100 70      ; R100 := closure(Function #71)
480 [-]: MOVE      R0 R59       ; R0 := R59
481 [-]: SETGLOBAL R100 K64     ; onKeyDown_MENU_GENERIC1 := R100
482 [-]: CLOSURE   R100 71      ; R100 := closure(Function #72)
483 [-]: MOVE      R0 R59       ; R0 := R59
484 [-]: MOVE      R0 R6        ; R0 := R6
485 [-]: MOVE      R0 R67       ; R0 := R67
486 [-]: MOVE      R0 R10       ; R0 := R10
487 [-]: MOVE      R0 R40       ; R0 := R40
488 [-]: MOVE      R0 R85       ; R0 := R85
489 [-]: MOVE      R0 R0        ; R0 := R0
490 [-]: SETGLOBAL R100 K65     ; onKeyUp_MENU_GENERIC1 := R100
491 [-]: CLOSURE   R100 72      ; R100 := closure(Function #73)
492 [-]: MOVE      R0 R36       ; R0 := R36
493 [-]: MOVE      R0 R72       ; R0 := R72
494 [-]: MOVE      R0 R66       ; R0 := R66
495 [-]: SETGLOBAL R100 K66     ; OnGamepadTransition := R100
496 [-]: CLOSURE   R100 73      ; R100 := closure(Function #74)
497 [-]: MOVE      R0 R0        ; R0 := R0
498 [-]: MOVE      R0 R47       ; R0 := R47
499 [-]: SETGLOBAL R100 K67     ; onKeyDown_MENU_PINCH_DELTA := R100
500 [-]: CLOSURE   R100 74      ; R100 := closure(Function #75)
501 [-]: MOVE      R0 R0        ; R0 := R0
502 [-]: MOVE      R0 R41       ; R0 := R41
503 [-]: SETGLOBAL R100 K68     ; onRawInputEvent := R100
504 [-]: RETURN    R0 1         ; return 


; Function #1:
;
; Name:            
; Defined at line: 124
; #Upvalues:       0
; #Parameters:     2
; Is_vararg:       0
; Max Stack Size:  7

  1 [-]: GETGLOBAL R2 K0        ; R2 := 0xae91e43b
  2 [-]: SELF      R2 R2 K1     ; R3 := R2; R2 := R2[0x67bc869f]
  3 [-]: MOVE      R4 R0        ; R4 := R0
  4 [-]: CONST     R5 0         ; R5 := 0.000000
  5 [-]: GETTABLE  R6 R1 K2     ; R6 := R1["x"]
  6 [-]: CALL      R2 5 1       ; R2(R3,R4,R5,R6)
  7 [-]: GETGLOBAL R2 K0        ; R2 := 0xae91e43b
  8 [-]: SELF      R2 R2 K1     ; R3 := R2; R2 := R2[0x67bc869f]
  9 [-]: MOVE      R4 R0        ; R4 := R0
 10 [-]: CONST     R5 1         ; R5 := 1.000000
 11 [-]: GETTABLE  R6 R1 K3     ; R6 := R1["y"]
 12 [-]: CALL      R2 5 1       ; R2(R3,R4,R5,R6)
 13 [-]: RETURN    R0 1         ; return 


; Function #2:
;
; Name:            
; Defined at line: 130
; #Upvalues:       0
; #Parameters:     0
; Is_vararg:       0
; Max Stack Size:  6

  1 [-]: GETGLOBAL R0 K0        ; R0 := 0x7b998233
  2 [-]: GETGLOBAL R1 K1        ; R1 := 0x89326c93
  3 [-]: CALL      R0 2 2       ; R0 := R0(R1)
  4 [-]: TEST      R0 1         ; if R0 then PC := 34
  5 [-]: JMP       34           ; PC := 34
  6 [-]: GETGLOBAL R0 K1        ; R0 := 0x89326c93
  7 [-]: SELF      R0 R0 K2     ; R1 := R0; R0 := R0[0x78298275]
  8 [-]: CALL      R0 2 2       ; R0 := R0(R1)
  9 [-]: GETGLOBAL R1 K0        ; R1 := 0x7b998233
 10 [-]: MOVE      R2 R0        ; R2 := R0
 11 [-]: CALL      R1 2 2       ; R1 := R1(R2)
 12 [-]: TEST      R1 1         ; if R1 then PC := 34
 13 [-]: JMP       34           ; PC := 34
 14 [-]: GETGLOBAL R1 K0        ; R1 := 0x7b998233
 15 [-]: SELF      R2 R0 K3     ; R3 := R0; R2 := R0[0x5e651723]
 16 [-]: CALL      R2 2 0       ; R2,... := R2(R3)
 17 [-]: CALL      R1 0 2       ; R1 := R1(R2,...)
 18 [-]: TEST      R1 1         ; if R1 then PC := 34
 19 [-]: JMP       34           ; PC := 34
 20 [-]: GETGLOBAL R1 K4        ; R1 := 0xbe190284
 21 [-]: GETGLOBAL R2 K0        ; R2 := 0x7b998233
 22 [-]: MOVE      R3 R1        ; R3 := R1
 23 [-]: CALL      R2 2 2       ; R2 := R2(R3)
 24 [-]: TEST      R2 1         ; if R2 then PC := 34
 25 [-]: JMP       34           ; PC := 34
 26 [-]: SELF      R2 R0 K3     ; R3 := R0; R2 := R0[0x5e651723]
 27 [-]: CALL      R2 2 2       ; R2 := R2(R3)
 28 [-]: SELF      R2 R2 K5     ; R3 := R2; R2 := R2[0xad1e0b4b]
 29 [-]: CALL      R2 2 2       ; R2 := R2(R3)
 30 [-]: SELF      R3 R1 K6     ; R4 := R1; R3 := R1[0xaee0d08d]
 31 [-]: MOVE      R5 R2        ; R5 := R2
 32 [-]: TAILCALL  R3 3 0       ; R3,... := R3(R4,R5)
 33 [-]: RETURN    R3 0         ; return R3,...
 34 [-]: LOADNIL   R3 R3        ; R3 := nil
 35 [-]: RETURN    R3 2         ; return R3
 36 [-]: RETURN    R0 1         ; return 


; Function #3:
;
; Name:            
; Defined at line: 145
; #Upvalues:       0
; #Parameters:     2
; Is_vararg:       0
; Max Stack Size:  6

  1 [-]: GETGLOBAL R2 K0        ; R2 := 0x7b998233
  2 [-]: GETGLOBAL R3 K1        ; R3 := 0x89326c93
  3 [-]: CALL      R2 2 2       ; R2 := R2(R3)
  4 [-]: TEST      R2 1         ; if R2 then PC := 13
  5 [-]: JMP       13           ; PC := 13
  6 [-]: GETGLOBAL R2 K1        ; R2 := 0x89326c93
  7 [-]: SELF      R2 R2 K2     ; R3 := R2; R2 := R2[0xfb64e76c]
  8 [-]: CALL      R2 2 2       ; R2 := R2(R3)
  9 [-]: SELF      R2 R2 K3     ; R3 := R2; R2 := R2[0x014fd8c7]
 10 [-]: MOVE      R4 R0        ; R4 := R0
 11 [-]: MOVE      R5 R1        ; R5 := R1
 12 [-]: CALL      R2 4 1       ; R2(R3,R4,R5)
 13 [-]: RETURN    R0 1         ; return 


; Function #4:
;
; Name:            
; Defined at line: 151
; #Upvalues:       1
; #Parameters:     1
; Is_vararg:       0
; Max Stack Size:  6

  1 [-]: GETUPVAL  R1 U0        ; R1 := U0
  2 [-]: SETTABLE  R1 K0 R0     ; R1["IsVisible"] := R0
  3 [-]: GETGLOBAL R1 K1        ; R1 := 0xae91e43b
  4 [-]: SELF      R1 R1 K2     ; R2 := R1; R1 := R1[0xaade900e]
  5 [-]: LOADK     R3 K3        ; R3 := "Reticle"
  6 [-]: CONST     R4 11        ; R4 := 11.000000
  7 [-]: MOVE      R5 R0        ; R5 := R0
  8 [-]: CALL      R1 5 1       ; R1(R2,R3,R4,R5)
  9 [-]: GETGLOBAL R1 K1        ; R1 := 0xae91e43b
 10 [-]: SELF      R1 R1 K4     ; R2 := R1; R1 := R1[0x5477b639]
 11 [-]: NOT       R3 R0        ; R3 :=  R0
 12 [-]: CALL      R1 3 1       ; R1(R2,R3)
 13 [-]: GETGLOBAL R1 K5        ; R1 := 0x7b998233
 14 [-]: GETGLOBAL R2 K6        ; R2 := _T
 15 [-]: GETTABLE  R2 R2 K7     ; R2 := R2["ShowButtonBarCursor"]
 16 [-]: CALL      R1 2 2       ; R1 := R1(R2)
 17 [-]: TEST      R1 1         ; if R1 then PC := 23
 18 [-]: JMP       23           ; PC := 23
 19 [-]: GETGLOBAL R1 K6        ; R1 := _T
 20 [-]: GETTABLE  R1 R1 K8     ; R1 := R1[0xbfd7a316]
 21 [-]: NOT       R2 R0        ; R2 :=  R0
 22 [-]: CALL      R1 2 1       ; R1(R2)
 23 [-]: GETGLOBAL R1 K9        ; R1 := 0x89326c93
 24 [-]: SELF      R1 R1 K10    ; R2 := R1; R1 := R1[0xfb64e76c]
 25 [-]: CALL      R1 2 2       ; R1 := R1(R2)
 26 [-]: SELF      R1 R1 K11    ; R2 := R1; R1 := R1[0x014fd8c7]
 27 [-]: GETGLOBAL R3 K1        ; R3 := 0xae91e43b
 28 [-]: SELF      R3 R3 K12    ; R4 := R3; R3 := R3[0x6b837788]
 29 [-]: CALL      R3 2 2       ; R3 := R3(R4)
 30 [-]: DIV       R3 R3 K13    ; R3 := R3 / 2.000000
 31 [-]: GETGLOBAL R4 K1        ; R4 := 0xae91e43b
 32 [-]: SELF      R4 R4 K14    ; R5 := R4; R4 := R4[0xaf9fda9f]
 33 [-]: CALL      R4 2 2       ; R4 := R4(R5)
 34 [-]: DIV       R4 R4 K13    ; R4 := R4 / 2.000000
 35 [-]: CALL      R1 4 1       ; R1(R2,R3,R4)
 36 [-]: RETURN    R0 1         ; return 


; Function #5:
;
; Name:            
; Defined at line: 162
; #Upvalues:       3
; #Parameters:     0
; Is_vararg:       0
; Max Stack Size:  5

  1 [-]: GETUPVAL  R0 U0        ; R0 := U0
  2 [-]: GETTABLE  R0 R0 K0     ; R0 := R0[0x6d7e6810]
  3 [-]: GETGLOBAL R1 K1        ; R1 := 0xae91e43b
  4 [-]: NEWTABLE  R2 0 2       ; R2 := {}
  5 [-]: GETUPVAL  R3 U1        ; R3 := U1
  6 [-]: GETTABLE  R3 R3 K3     ; R3 := R3["X"]
  7 [-]: SETTABLE  R2 K2 R3     ; R2["x"] := R3
  8 [-]: GETUPVAL  R3 U1        ; R3 := U1
  9 [-]: GETTABLE  R3 R3 K5     ; R3 := R3["Y"]
 10 [-]: SETTABLE  R2 K4 R3     ; R2["y"] := R3
 11 [-]: CALL      R0 3 2       ; R0 := R0(R1,R2)
 12 [-]: GETGLOBAL R1 K6        ; R1 := 0x34291f5c
 13 [-]: GETTABLE  R1 R1 K7     ; R1 := R1[0x1467d5f4]
 14 [-]: CALL      R1 1 2       ; R1 := R1()
 15 [-]: TEST      R1 0         ; if not R1 then PC := 30
 16 [-]: JMP       30           ; PC := 30
 17 [-]: GETUPVAL  R1 U2        ; R1 := U2
 18 [-]: GETGLOBAL R2 K1        ; R2 := 0xae91e43b
 19 [-]: SELF      R2 R2 K8     ; R3 := R2; R2 := R2[0x091c120e]
 20 [-]: CALL      R2 2 2       ; R2 := R2(R3)
 21 [-]: GETTABLE  R3 R0 K2     ; R3 := R0["x"]
 22 [-]: MUL       R2 R2 R3     ; R2 := R2 * R3
 23 [-]: GETGLOBAL R3 K1        ; R3 := 0xae91e43b
 24 [-]: SELF      R3 R3 K9     ; R4 := R3; R3 := R3[0x2cc9d281]
 25 [-]: CALL      R3 2 2       ; R3 := R3(R4)
 26 [-]: GETTABLE  R4 R0 K4     ; R4 := R0["y"]
 27 [-]: MUL       R3 R3 R4     ; R3 := R3 * R4
 28 [-]: CALL      R1 3 1       ; R1(R2,R3)
 29 [-]: JMP       42           ; PC := 42
 30 [-]: GETUPVAL  R1 U2        ; R1 := U2
 31 [-]: GETGLOBAL R2 K1        ; R2 := 0xae91e43b
 32 [-]: SELF      R2 R2 K10    ; R3 := R2; R2 := R2[0x6b837788]
 33 [-]: CALL      R2 2 2       ; R2 := R2(R3)
 34 [-]: GETTABLE  R3 R0 K2     ; R3 := R0["x"]
 35 [-]: MUL       R2 R2 R3     ; R2 := R2 * R3
 36 [-]: GETGLOBAL R3 K1        ; R3 := 0xae91e43b
 37 [-]: SELF      R3 R3 K11    ; R4 := R3; R3 := R3[0xaf9fda9f]
 38 [-]: CALL      R3 2 2       ; R3 := R3(R4)
 39 [-]: GETTABLE  R4 R0 K4     ; R4 := R0["y"]
 40 [-]: MUL       R3 R3 R4     ; R3 := R3 * R4
 41 [-]: CALL      R1 3 1       ; R1(R2,R3)
 42 [-]: GETGLOBAL R1 K1        ; R1 := 0xae91e43b
 43 [-]: SELF      R1 R1 K12    ; R2 := R1; R1 := R1[0x5477b639]
 44 [-]: LOADKB    R3 0 0       ; R3 := false
 45 [-]: CALL      R1 3 1       ; R1(R2,R3)
 46 [-]: RETURN    R0 1         ; return 


; Function #6:
;
; Name:            
; Defined at line: 175
; #Upvalues:       1
; #Parameters:     0
; Is_vararg:       0
; Max Stack Size:  2

  1 [-]: NEWTABLE  R0 0 0       ; R0 := {}
  2 [-]: SETUPVAL  R0 U0        ; U82 := R0
  3 [-]: RETURN    R0 1         ; return 


; Function #7:
;
; Name:            
; Defined at line: 179
; #Upvalues:       2
; #Parameters:     3
; Is_vararg:       0
; Max Stack Size:  7

  1 [-]: SELF      R3 R1 K0     ; R4 := R1; R3 := R1[0xc9f6a7d7]
  2 [-]: GETGLOBAL R5 K1        ; R5 := 0x2127883b
  3 [-]: CALL      R3 3 2       ; R3 := R3(R4,R5)
  4 [-]: GETUPVAL  R4 U0        ; R4 := U0
  5 [-]: TEST      R4 0         ; if not R4 then PC := 27
  6 [-]: JMP       27           ; PC := 27
  7 [-]: SELF      R4 R0 K2     ; R5 := R0; R4 := R0[0xee0bc178]
  8 [-]: MOVE      R6 R1        ; R6 := R1
  9 [-]: CALL      R4 3 2       ; R4 := R4(R5,R6)
 10 [-]: TEST      R4 1         ; if R4 then PC := 27
 11 [-]: JMP       27           ; PC := 27
 12 [-]: GETGLOBAL R4 K3        ; R4 := 0x7b998233
 13 [-]: MOVE      R5 R3        ; R5 := R3
 14 [-]: CALL      R4 2 2       ; R4 := R4(R5)
 15 [-]: TEST      R4 1         ; if R4 then PC := 26
 16 [-]: JMP       26           ; PC := 26
 17 [-]: GETUPVAL  R4 U1        ; R4 := U1
 18 [-]: GETTABLE  R4 R4 R2     ; R4 := R4[R2]
 19 [-]: TEST      R4 1         ; if R4 then PC := 26
 20 [-]: JMP       26           ; PC := 26
 21 [-]: SELF      R4 R3 K4     ; R5 := R3; R4 := R3[0x9bd1b77c]
 22 [-]: CONST     R6 0         ; R6 := 0.500000
 23 [-]: CALL      R4 3 1       ; R4(R5,R6)
 24 [-]: GETUPVAL  R4 U1        ; R4 := U1
 25 [-]: SETTABLE  R4 R2 K5     ; R4[R2] := 1.000000
 26 [-]: RETURN    R0 1         ; return 
 27 [-]: RETURN    R0 1         ; return 


; Function #8:
;
; Name:            
; Defined at line: 195
; #Upvalues:       2
; #Parameters:     1
; Is_vararg:       0
; Max Stack Size:  12

  1 [-]: GETGLOBAL R1 K0        ; R1 := 0x7b998233
  2 [-]: GETGLOBAL R2 K1        ; R2 := 0x89326c93
  3 [-]: CALL      R1 2 2       ; R1 := R1(R2)
  4 [-]: TEST      R1 1         ; if R1 then PC := 31
  5 [-]: JMP       31           ; PC := 31
  6 [-]: GETGLOBAL R1 K1        ; R1 := 0x89326c93
  7 [-]: SELF      R1 R1 K2     ; R2 := R1; R1 := R1[0x7d108ddb]
  8 [-]: CALL      R1 2 2       ; R1 := R1(R2)
  9 [-]: CONST     R2 1         ; R2 := 1.000000
 10 [-]: LEN       R3 R1        ; R3 := # R1
 11 [-]: CONST     R4 1         ; R4 := 1.000000
 12 [-]: FORPREP   R2 30        ; R2 -= R4; PC := 30
 13 [-]: GETTABLE  R6 R1 R5     ; R6 := R1[R5]
 14 [-]: SELF      R6 R6 K3     ; R7 := R6; R6 := R6[0xbb610e5b]
 15 [-]: CALL      R6 2 2       ; R6 := R6(R7)
 16 [-]: GETGLOBAL R7 K0        ; R7 := 0x7b998233
 17 [-]: MOVE      R8 R6        ; R8 := R6
 18 [-]: CALL      R7 2 2       ; R7 := R7(R8)
 19 [-]: TEST      R7 1         ; if R7 then PC := 30
 20 [-]: JMP       30           ; PC := 30
 21 [-]: EQ        1 R6 R0      ; if R6 == R0 then PC := 30
 22 [-]: JMP       30           ; PC := 30
 23 [-]: GETUPVAL  R7 U0        ; R7 := U0
 24 [-]: MOVE      R8 R0        ; R8 := R0
 25 [-]: MOVE      R9 R6        ; R9 := R6
 26 [-]: GETTABLE  R10 R1 R5    ; R10 := R1[R5]
 27 [-]: SELF      R10 R10 K4   ; R11 := R10; R10 := R10[0x8b72b36e]
 28 [-]: CALL      R10 2 0      ; R10,... := R10(R11)
 29 [-]: CALL      R7 0 1       ; R7(R8,...)
 30 [-]: FORLOOP   R2 13        ; R2 += R4; if R2 <= R3 then begin PC := 13; R5 := R2 end
 31 [-]: SELF      R7 R0 K5     ; R8 := R0; R7 := R0[0x0e46e45b]
 32 [-]: CONST     R9 0         ; R9 := 0.000000
 33 [-]: CALL      R7 3 2       ; R7 := R7(R8,R9)
 34 [-]: TEST      R7 0         ; if not R7 then PC := 42
 35 [-]: JMP       42           ; PC := 42
 36 [-]: GETUPVAL  R7 U1        ; R7 := U1
 37 [-]: GETGLOBAL R8 K7        ; R8 := 0x67652851
 38 [-]: CALL      R8 1 2       ; R8 := R8()
 39 [-]: SUB       R7 R7 R8     ; R7 := R7 - R8
 40 [-]: SETUPVAL  R7 U1        ; U82 := R1
 41 [-]: JMP       47           ; PC := 47
 42 [-]: GETUPVAL  R7 U1        ; R7 := U1
 43 [-]: GETGLOBAL R8 K7        ; R8 := 0x67652851
 44 [-]: CALL      R8 1 2       ; R8 := R8()
 45 [-]: ADD       R7 R7 R8     ; R7 := R7 + R8
 46 [-]: SETUPVAL  R7 U1        ; U82 := R1
 47 [-]: GETGLOBAL R7 K8        ; R7 := 0x42dcc9f5
 48 [-]: GETUPVAL  R8 U1        ; R8 := U1
 49 [-]: CONST     R9 0         ; R9 := 0.000000
 50 [-]: CONST     R10 1        ; R10 := 1.000000
 51 [-]: CALL      R7 4 2       ; R7 := R7(R8,R9,R10)
 52 [-]: SETUPVAL  R7 U1        ; U82 := R1
 53 [-]: RETURN    R0 1         ; return 


; Function #9:
;
; Name:            
; Defined at line: 223
; #Upvalues:       2
; #Parameters:     0
; Is_vararg:       0
; Max Stack Size:  6

  1 [-]: GETUPVAL  R0 U0        ; R0 := U0
  2 [-]: TEST      R0 1         ; if R0 then PC := 22
  3 [-]: JMP       22           ; PC := 22
  4 [-]: GETUPVAL  R0 U1        ; R0 := U1
  5 [-]: DIV       R0 R0 K0     ; R0 := R0 / 2.000000
  6 [-]: GETUPVAL  R1 U1        ; R1 := U1
  7 [-]: MUL       R1 R1 K1     ; R1 := R1 * 0.200000
  8 [-]: ADD       R0 R0 R1     ; R0 := R0 + R1
  9 [-]: GETGLOBAL R1 K2        ; R1 := 0xae91e43b
 10 [-]: SELF      R1 R1 K3     ; R2 := R1; R1 := R1[0x67bc869f]
 11 [-]: LOADK     R3 K4        ; R3 := "MiniMapContainer"
 12 [-]: CONST     R4 0         ; R4 := 0.000000
 13 [-]: MOVE      R5 R0        ; R5 := R0
 14 [-]: CALL      R1 5 1       ; R1(R2,R3,R4,R5)
 15 [-]: GETGLOBAL R1 K2        ; R1 := 0xae91e43b
 16 [-]: SELF      R1 R1 K3     ; R2 := R1; R1 := R1[0x67bc869f]
 17 [-]: LOADK     R3 K5        ; R3 := "MiniMapOverlayMsg"
 18 [-]: CONST     R4 0         ; R4 := 0.000000
 19 [-]: MOVE      R5 R0        ; R5 := R0
 20 [-]: CALL      R1 5 1       ; R1(R2,R3,R4,R5)
 21 [-]: JMP       36           ; PC := 36
 22 [-]: GETGLOBAL R1 K2        ; R1 := 0xae91e43b
 23 [-]: SELF      R1 R1 K3     ; R2 := R1; R1 := R1[0x67bc869f]
 24 [-]: LOADK     R3 K4        ; R3 := "MiniMapContainer"
 25 [-]: CONST     R4 0         ; R4 := 0.000000
 26 [-]: GETUPVAL  R5 U1        ; R5 := U1
 27 [-]: DIV       R5 R5 K0     ; R5 := R5 / 2.000000
 28 [-]: CALL      R1 5 1       ; R1(R2,R3,R4,R5)
 29 [-]: GETGLOBAL R1 K2        ; R1 := 0xae91e43b
 30 [-]: SELF      R1 R1 K3     ; R2 := R1; R1 := R1[0x67bc869f]
 31 [-]: LOADK     R3 K5        ; R3 := "MiniMapOverlayMsg"
 32 [-]: CONST     R4 0         ; R4 := 0.000000
 33 [-]: GETUPVAL  R5 U1        ; R5 := U1
 34 [-]: DIV       R5 R5 K0     ; R5 := R5 / 2.000000
 35 [-]: CALL      R1 5 1       ; R1(R2,R3,R4,R5)
 36 [-]: RETURN    R0 1         ; return 


; Function #10:
;
; Name:            
; Defined at line: 235
; #Upvalues:       4
; #Parameters:     1
; Is_vararg:       0
; Max Stack Size:  8

  1 [-]: GETUPVAL  R1 U1        ; R1 := U1
  2 [-]: GETTABLE  R1 R1 K0     ; R1 := R1[0x310355a7]
  3 [-]: GETGLOBAL R2 K1        ; R2 := 0xae91e43b
  4 [-]: LOADK     R3 K2        ; R3 := "MiniMapContainer.MiniMapMarkers.PlayerArrow"
  5 [-]: GETGLOBAL R4 K3        ; R4 := 0xfcee12ce
  6 [-]: CONST     R5 0         ; R5 := 0.000000
  7 [-]: CONST     R6 0         ; R6 := 0.000000
  8 [-]: GETGLOBAL R7 K4        ; R7 := 0x1211d00f
  9 [-]: CALL      R1 7 2       ; R1 := R1(R2,R3,R4,R5,R6,R7)
 10 [-]: SETUPVAL  R1 U0        ; U82 := R0
 11 [-]: GETGLOBAL R1 K5        ; R1 := 0x7b998233
 12 [-]: GETUPVAL  R2 U0        ; R2 := U0
 13 [-]: CALL      R1 2 2       ; R1 := R1(R2)
 14 [-]: TEST      R1 1         ; if R1 then PC := 34
 15 [-]: JMP       34           ; PC := 34
 16 [-]: GETGLOBAL R1 K5        ; R1 := 0x7b998233
 17 [-]: GETUPVAL  R2 U0        ; R2 := U0
 18 [-]: GETTABLE  R2 R2 K6     ; R2 := R2["mInstance"]
 19 [-]: CALL      R1 2 2       ; R1 := R1(R2)
 20 [-]: TEST      R1 1         ; if R1 then PC := 34
 21 [-]: JMP       34           ; PC := 34
 22 [-]: GETGLOBAL R1 K1        ; R1 := 0xae91e43b
 23 [-]: SELF      R1 R1 K7     ; R2 := R1; R1 := R1[0x91a24e4b]
 24 [-]: LOADK     R3 K2        ; R3 := "MiniMapContainer.MiniMapMarkers.PlayerArrow"
 25 [-]: CONST     R4 14        ; R4 := 14.000000
 26 [-]: CALL      R1 4 2       ; R1 := R1(R2,R3,R4)
 27 [-]: DIV       R1 R1 K8     ; R1 := R1 / 180.000000
 28 [-]: GETUPVAL  R2 U0        ; R2 := U0
 29 [-]: GETTABLE  R2 R2 K6     ; R2 := R2["mInstance"]
 30 [-]: SELF      R2 R2 K9     ; R3 := R2; R2 := R2[0xf34553b1]
 31 [-]: MOVE      R4 R1        ; R4 := R1
 32 [-]: MOVE      R5 R1        ; R5 := R1
 33 [-]: CALL      R2 4 1       ; R2(R3,R4,R5)
 34 [-]: TEST      R0 0         ; if not R0 then PC := 48
 35 [-]: JMP       48           ; PC := 48
 36 [-]: GETGLOBAL R2 K10       ; R2 := 0x03f57322
 37 [-]: MOVE      R3 R0        ; R3 := R0
 38 [-]: CALL      R2 2 2       ; R2 := R2(R3)
 39 [-]: LT        0 K11 R2     ; if 0.000000 >= R2 then PC := 48
 40 [-]: JMP       48           ; PC := 48
 41 [-]: GETUPVAL  R2 U2        ; R2 := U2
 42 [-]: SELF      R2 R2 K12    ; R3 := R2; R2 := R2[0xbd2e96ea]
 43 [-]: LOADK     R4 K13       ; R4 := 0.800000
 44 [-]: GETUPVAL  R5 U3        ; R5 := U3
 45 [-]: LOADKB    R6 0 0       ; R6 := false
 46 [-]: SUB       R7 R0 K14    ; R7 := R0 - 1.000000
 47 [-]: CALL      R2 6 1       ; R2(R3,R4,R5,R6,R7)
 48 [-]: RETURN    R0 1         ; return 


; Function #11:
;
; Name:            
; Defined at line: 246
; #Upvalues:       6
; #Parameters:     0
; Is_vararg:       0
; Max Stack Size:  8

  1 [-]: LOADKB    R0 0 0       ; R0 := false
  2 [-]: SETUPVAL  R0 U0        ; U82 := R0
  3 [-]: GETUPVAL  R0 U1        ; R0 := U1
  4 [-]: TEST      R0 0         ; if not R0 then PC := 9
  5 [-]: JMP       9            ; PC := 9
  6 [-]: GETUPVAL  R0 U2        ; R0 := U2
  7 [-]: CONST     R1 1         ; R1 := 1.000000
  8 [-]: CALL      R0 2 1       ; R0(R1)
  9 [-]: GETUPVAL  R0 U3        ; R0 := U3
 10 [-]: TEST      R0 1         ; if R0 then PC := 23
 11 [-]: JMP       23           ; PC := 23
 12 [-]: GETGLOBAL R0 K0        ; R0 := 0xae91e43b
 13 [-]: SELF      R0 R0 K1     ; R1 := R0; R0 := R0[0x67bc869f]
 14 [-]: LOADK     R2 K2        ; R2 := "_root"
 15 [-]: CONST     R3 10        ; R3 := 10.000000
 16 [-]: GETUPVAL  R4 U4        ; R4 := U4
 17 [-]: GETTABLE  R4 R4 K3     ; R4 := R4[0x06d055f9]
 18 [-]: GETUPVAL  R5 U5        ; R5 := U5
 19 [-]: GETUPVAL  R6 U5        ; R6 := U5
 20 [-]: CONST     R7 0         ; R7 := 0.000000
 21 [-]: CALL      R4 4 0       ; R4,... := R4(R5,R6,R7)
 22 [-]: CALL      R0 0 1       ; R0(R1,...)
 23 [-]: RETURN    R0 1         ; return 


; Function #12:
;
; Name:            
; Defined at line: 256
; #Upvalues:       9
; #Parameters:     0
; Is_vararg:       0
; Max Stack Size:  9

  1 [-]: LOADKB    R0 0 0       ; R0 := false
  2 [-]: SETUPVAL  R0 U0        ; U82 := R0
  3 [-]: LOADKB    R0 0 0       ; R0 := false
  4 [-]: SETUPVAL  R0 U1        ; U82 := R1
  5 [-]: GETGLOBAL R0 K0        ; R0 := 0x7b998233
  6 [-]: GETUPVAL  R1 U2        ; R1 := U2
  7 [-]: CALL      R0 2 2       ; R0 := R0(R1)
  8 [-]: TEST      R0 1         ; if R0 then PC := 44
  9 [-]: JMP       44           ; PC := 44
 10 [-]: GETUPVAL  R0 U2        ; R0 := U2
 11 [-]: SELF      R0 R0 K1     ; R1 := R0; R0 := R0[0xbf5bcc4a]
 12 [-]: LOADKB    R2 1 0       ; R2 := true
 13 [-]: CALL      R0 3 1       ; R0(R1,R2)
 14 [-]: GETUPVAL  R0 U2        ; R0 := U2
 15 [-]: SELF      R0 R0 K2     ; R1 := R0; R0 := R0[0x8f83a362]
 16 [-]: GETUPVAL  R2 U3        ; R2 := U3
 17 [-]: EQ        1 R2 K3      ; if R2 == true then PC := 20
 18 [-]: JMP       20           ; PC := 20
 19 [-]: LOADKB    R2 0 1       ; R2 := false; PC := 20
 20 [-]: LOADKB    R2 1 0       ; R2 := true
 21 [-]: CALL      R0 3 1       ; R0(R1,R2)
 22 [-]: GETUPVAL  R0 U2        ; R0 := U2
 23 [-]: SELF      R0 R0 K4     ; R1 := R0; R0 := R0[0xc256d7cf]
 24 [-]: GETUPVAL  R2 U3        ; R2 := U3
 25 [-]: EQ        1 R2 K3      ; if R2 == true then PC := 28
 26 [-]: JMP       28           ; PC := 28
 27 [-]: LOADKB    R2 0 1       ; R2 := false; PC := 28
 28 [-]: LOADKB    R2 1 0       ; R2 := true
 29 [-]: CALL      R0 3 1       ; R0(R1,R2)
 30 [-]: GETUPVAL  R0 U4        ; R0 := U4
 31 [-]: TEST      R0 0         ; if not R0 then PC := 44
 32 [-]: JMP       44           ; PC := 44
 33 [-]: GETUPVAL  R0 U2        ; R0 := U2
 34 [-]: SELF      R0 R0 K5     ; R1 := R0; R0 := R0[0x08c73127]
 35 [-]: GETUPVAL  R2 U4        ; R2 := U4
 36 [-]: GETTABLE  R2 R2 K6     ; R2 := R2["mCurrentCoords"]
 37 [-]: GETTABLE  R2 R2 K7     ; R2 := R2["x"]
 38 [-]: GETUPVAL  R3 U4        ; R3 := U4
 39 [-]: GETTABLE  R3 R3 K6     ; R3 := R3["mCurrentCoords"]
 40 [-]: GETTABLE  R3 R3 K8     ; R3 := R3["y"]
 41 [-]: GETUPVAL  R4 U5        ; R4 := U5
 42 [-]: GETTABLE  R4 R4 K9     ; R4 := R4["mCurVal"]
 43 [-]: CALL      R0 5 1       ; R0(R1,R2,R3,R4)
 44 [-]: GETUPVAL  R0 U3        ; R0 := U3
 45 [-]: TEST      R0 0         ; if not R0 then PC := 51
 46 [-]: JMP       51           ; PC := 51
 47 [-]: GETUPVAL  R0 U6        ; R0 := U6
 48 [-]: GETTABLE  R0 R0 K10    ; R0 := R0[0x659d451f]
 49 [-]: GETGLOBAL R1 K11       ; R1 := 0x3bd7aecf
 50 [-]: CALL      R0 2 1       ; R0(R1)
 51 [-]: GETGLOBAL R0 K12       ; R0 := _T
 52 [-]: SETTABLE  R0 K13 K3    ; R0["OverlayMapVisible"] := true
 53 [-]: LOADKB    R0 1 0       ; R0 := true
 54 [-]: SETUPVAL  R0 U7        ; U82 := R7
 55 [-]: GETGLOBAL R0 K14       ; R0 := 0xae91e43b
 56 [-]: SELF      R0 R0 K15    ; R1 := R0; R0 := R0[0xaf5300dc]
 57 [-]: LOADK     R2 K16       ; R2 := "_root"
 58 [-]: CALL      R0 3 1       ; R0(R1,R2)
 59 [-]: GETGLOBAL R0 K17       ; R0 := 0x25312c9b
 60 [-]: GETGLOBAL R1 K14       ; R1 := 0xae91e43b
 61 [-]: LOADK     R2 K16       ; R2 := "_root"
 62 [-]: CONST     R3 2         ; R3 := 2.000000
 63 [-]: NEWTABLE  R4 2 0       ; R4 := {}
 64 [-]: CONST     R5 10        ; R5 := 10.000000
 65 [-]: CONST     R6 4         ; R6 := 4.000000
 66 [-]: SETLIST   R4 2 1       ; R4[(1-1)*FPF+i] := R(4+i), 1 <= i <= 2
 67 [-]: NEWTABLE  R5 2 0       ; R5 := {}
 68 [-]: CONST     R6 100       ; R6 := 100.000000
 69 [-]: CONST     R7 0         ; R7 := 0.000000
 70 [-]: SETLIST   R5 2 1       ; R5[(1-1)*FPF+i] := R(5+i), 1 <= i <= 2
 71 [-]: LOADK     R6 K19       ; R6 := 0.200000
 72 [-]: CONST     R7 0         ; R7 := 0.000000
 73 [-]: GETUPVAL  R8 U8        ; R8 := U8
 74 [-]: CALL      R0 9 1       ; R0(R1,R2,R3,R4,R5,R6,R7,R8)
 75 [-]: RETURN    R0 1         ; return 


; Function #13:
;
; Name:            
; Defined at line: 279
; #Upvalues:       3
; #Parameters:     0
; Is_vararg:       0
; Max Stack Size:  4

  1 [-]: GETGLOBAL R0 K0        ; R0 := 0x76ea806b
  2 [-]: SELF      R0 R0 K1     ; R1 := R0; R0 := R0[0x3f3ae64c]
  3 [-]: CONST     R2 0         ; R2 := 0.000000
  4 [-]: CALL      R0 3 2       ; R0 := R0(R1,R2)
  5 [-]: GETGLOBAL R1 K2        ; R1 := 0x7b998233
  6 [-]: MOVE      R2 R0        ; R2 := R0
  7 [-]: CALL      R1 2 2       ; R1 := R1(R2)
  8 [-]: TEST      R1 1         ; if R1 then PC := 21
  9 [-]: JMP       21           ; PC := 21
 10 [-]: SELF      R1 R0 K3     ; R2 := R0; R1 := R0[0x40e9c32b]
 11 [-]: CALL      R1 2 2       ; R1 := R1(R2)
 12 [-]: SELF      R2 R1 K4     ; R3 := R1; R2 := R1[0xb469567a]
 13 [-]: CALL      R2 2 2       ; R2 := R2(R3)
 14 [-]: SETUPVAL  R2 U0        ; U82 := R0
 15 [-]: SELF      R2 R1 K5     ; R3 := R1; R2 := R1[0x1534dba6]
 16 [-]: CALL      R2 2 2       ; R2 := R2(R3)
 17 [-]: SETUPVAL  R2 U1        ; U82 := R1
 18 [-]: SELF      R2 R1 K6     ; R3 := R1; R2 := R1[0xfc466ac5]
 19 [-]: CALL      R2 2 2       ; R2 := R2(R3)
 20 [-]: SETUPVAL  R2 U2        ; U82 := R2
 21 [-]: RETURN    R0 1         ; return 


; Function #14:
;
; Name:            
; Defined at line: 289
; #Upvalues:       1
; #Parameters:     0
; Is_vararg:       0
; Max Stack Size:  2

  1 [-]: GETUPVAL  R0 U0        ; R0 := U0
  2 [-]: CALL      R0 1 1       ; R0()
  3 [-]: RETURN    R0 1         ; return 


; Function #15:
;
; Name:            
; Defined at line: 293
; #Upvalues:       5
; #Parameters:     0
; Is_vararg:       0
; Max Stack Size:  5

  1 [-]: GETUPVAL  R0 U0        ; R0 := U0
  2 [-]: GETUPVAL  R1 U1        ; R1 := U1
  3 [-]: GETTABLE  R1 R1 K1     ; R1 := R1[0x74a11ec6]
  4 [-]: GETUPVAL  R2 U2        ; R2 := U2
  5 [-]: DIV       R2 R2 K2     ; R2 := R2 / 2.000000
  6 [-]: CALL      R1 2 2       ; R1 := R1(R2)
  7 [-]: SETTABLE  R0 K0 R1     ; R0["X"] := R1
  8 [-]: GETUPVAL  R0 U0        ; R0 := U0
  9 [-]: GETUPVAL  R1 U1        ; R1 := U1
 10 [-]: GETTABLE  R1 R1 K1     ; R1 := R1[0x74a11ec6]
 11 [-]: GETUPVAL  R2 U3        ; R2 := U3
 12 [-]: DIV       R2 R2 K2     ; R2 := R2 / 2.000000
 13 [-]: CALL      R1 2 2       ; R1 := R1(R2)
 14 [-]: SETTABLE  R0 K3 R1     ; R0["Y"] := R1
 15 [-]: GETGLOBAL R0 K4        ; R0 := 0xae91e43b
 16 [-]: SELF      R0 R0 K5     ; R1 := R0; R0 := R0[0x67bc869f]
 17 [-]: LOADK     R2 K6        ; R2 := "Reticle"
 18 [-]: CONST     R3 0         ; R3 := 0.000000
 19 [-]: GETUPVAL  R4 U0        ; R4 := U0
 20 [-]: GETTABLE  R4 R4 K0     ; R4 := R4["X"]
 21 [-]: CALL      R0 5 1       ; R0(R1,R2,R3,R4)
 22 [-]: GETGLOBAL R0 K4        ; R0 := 0xae91e43b
 23 [-]: SELF      R0 R0 K5     ; R1 := R0; R0 := R0[0x67bc869f]
 24 [-]: LOADK     R2 K6        ; R2 := "Reticle"
 25 [-]: CONST     R3 1         ; R3 := 1.000000
 26 [-]: GETUPVAL  R4 U0        ; R4 := U0
 27 [-]: GETTABLE  R4 R4 K3     ; R4 := R4["Y"]
 28 [-]: CALL      R0 5 1       ; R0(R1,R2,R3,R4)
 29 [-]: GETGLOBAL R0 K4        ; R0 := 0xae91e43b
 30 [-]: SELF      R0 R0 K7     ; R1 := R0; R0 := R0[0xaade900e]
 31 [-]: LOADK     R2 K6        ; R2 := "Reticle"
 32 [-]: CONST     R3 11        ; R3 := 11.000000
 33 [-]: GETUPVAL  R4 U4        ; R4 := U4
 34 [-]: EQ        0 R4 K8      ; if R4 ~= true then PC := 39
 35 [-]: JMP       39           ; PC := 39
 36 [-]: GETUPVAL  R4 U0        ; R4 := U0
 37 [-]: GETTABLE  R4 R4 K9     ; R4 := R4["IsVisible"]
 38 [-]: JMP       41           ; PC := 41
 39 [-]: LOADKB    R4 0 1       ; R4 := false; PC := 40
 40 [-]: LOADKB    R4 1 0       ; R4 := true
 41 [-]: CALL      R0 5 1       ; R0(R1,R2,R3,R4)
 42 [-]: RETURN    R0 1         ; return 


; Function #16:
;
; Name:            
; Defined at line: 303
; #Upvalues:       14
; #Parameters:     0
; Is_vararg:       0
; Max Stack Size:  11

  1 [-]: GETUPVAL  R0 U0        ; R0 := U0
  2 [-]: SELF      R0 R0 K0     ; R1 := R0; R0 := R0[0xa2f64285]
  3 [-]: CALL      R0 2 2       ; R0 := R0(R1)
  4 [-]: NEWTABLE  R1 0 3       ; R1 := {}
  5 [-]: SELF      R2 R0 K2     ; R3 := R0; R2 := R0[0x60acc5d6]
  6 [-]: CALL      R2 2 2       ; R2 := R2(R3)
  7 [-]: SUB       R2 R2 K3     ; R2 := R2 - 100.000000
  8 [-]: SETTABLE  R1 K1 R2     ; R1["x"] := R2
  9 [-]: SELF      R2 R0 K5     ; R3 := R0; R2 := R0[0x61acc769]
 10 [-]: CALL      R2 2 2       ; R2 := R2(R3)
 11 [-]: SETTABLE  R1 K4 R2     ; R1["y"] := R2
 12 [-]: SELF      R2 R0 K7     ; R3 := R0; R2 := R0[0x5eacc2b0]
 13 [-]: CALL      R2 2 2       ; R2 := R2(R3)
 14 [-]: SUB       R2 R2 K3     ; R2 := R2 - 100.000000
 15 [-]: SETTABLE  R1 K6 R2     ; R1["z"] := R2
 16 [-]: SETUPVAL  R1 U1        ; U82 := R1
 17 [-]: NEWTABLE  R1 0 3       ; R1 := {}
 18 [-]: SELF      R2 R0 K8     ; R3 := R0; R2 := R0[0xc3844dc8]
 19 [-]: CALL      R2 2 2       ; R2 := R2(R3)
 20 [-]: ADD       R2 R2 K3     ; R2 := R2 + 100.000000
 21 [-]: SETTABLE  R1 K1 R2     ; R1["x"] := R2
 22 [-]: SELF      R2 R0 K9     ; R3 := R0; R2 := R0[0xc4844f5b]
 23 [-]: CALL      R2 2 2       ; R2 := R2(R3)
 24 [-]: SETTABLE  R1 K4 R2     ; R1["y"] := R2
 25 [-]: SELF      R2 R0 K10    ; R3 := R0; R2 := R0[0xc58450ee]
 26 [-]: CALL      R2 2 2       ; R2 := R2(R3)
 27 [-]: ADD       R2 R2 K3     ; R2 := R2 + 100.000000
 28 [-]: SETTABLE  R1 K6 R2     ; R1["z"] := R2
 29 [-]: SETUPVAL  R1 U2        ; U82 := R2
 30 [-]: NEWTABLE  R1 0 3       ; R1 := {}
 31 [-]: GETUPVAL  R2 U2        ; R2 := U2
 32 [-]: GETTABLE  R2 R2 K1     ; R2 := R2["x"]
 33 [-]: GETUPVAL  R3 U1        ; R3 := U1
 34 [-]: GETTABLE  R3 R3 K1     ; R3 := R3["x"]
 35 [-]: SUB       R2 R2 R3     ; R2 := R2 - R3
 36 [-]: SETTABLE  R1 K1 R2     ; R1["x"] := R2
 37 [-]: GETUPVAL  R2 U2        ; R2 := U2
 38 [-]: GETTABLE  R2 R2 K4     ; R2 := R2["y"]
 39 [-]: GETUPVAL  R3 U1        ; R3 := U1
 40 [-]: GETTABLE  R3 R3 K4     ; R3 := R3["y"]
 41 [-]: SUB       R2 R2 R3     ; R2 := R2 - R3
 42 [-]: SETTABLE  R1 K4 R2     ; R1["y"] := R2
 43 [-]: GETUPVAL  R2 U2        ; R2 := U2
 44 [-]: GETTABLE  R2 R2 K6     ; R2 := R2["z"]
 45 [-]: GETUPVAL  R3 U1        ; R3 := U1
 46 [-]: GETTABLE  R3 R3 K6     ; R3 := R3["z"]
 47 [-]: SUB       R2 R2 R3     ; R2 := R2 - R3
 48 [-]: SETTABLE  R1 K6 R2     ; R1["z"] := R2
 49 [-]: SETUPVAL  R1 U3        ; U82 := R3
 50 [-]: GETGLOBAL R1 K11       ; R1 := 0xae91e43b
 51 [-]: SELF      R1 R1 K12    ; R2 := R1; R1 := R1[0x6b837788]
 52 [-]: CALL      R1 2 2       ; R1 := R1(R2)
 53 [-]: GETGLOBAL R2 K11       ; R2 := 0xae91e43b
 54 [-]: SELF      R2 R2 K13    ; R3 := R2; R2 := R2[0xaf9fda9f]
 55 [-]: CALL      R2 2 2       ; R2 := R2(R3)
 56 [-]: DIV       R1 R1 R2     ; R1 := R1 / R2
 57 [-]: GETUPVAL  R2 U4        ; R2 := U4
 58 [-]: GETUPVAL  R3 U5        ; R3 := U5
 59 [-]: DIV       R2 R2 R3     ; R2 := R2 / R3
 60 [-]: DIV       R1 R1 R2     ; R1 := R1 / R2
 61 [-]: GETUPVAL  R2 U0        ; R2 := U0
 62 [-]: SELF      R2 R2 K14    ; R3 := R2; R2 := R2[0x450e5a70]
 63 [-]: CALL      R2 2 2       ; R2 := R2(R3)
 64 [-]: GETUPVAL  R3 U2        ; R3 := U2
 65 [-]: GETTABLE  R3 R3 K6     ; R3 := R3["z"]
 66 [-]: GETUPVAL  R4 U1        ; R4 := U1
 67 [-]: GETTABLE  R4 R4 K6     ; R4 := R4["z"]
 68 [-]: SUB       R3 R3 R4     ; R3 := R3 - R4
 69 [-]: MUL       R2 R2 R3     ; R2 := R2 * R3
 70 [-]: GETUPVAL  R3 U5        ; R3 := U5
 71 [-]: DIV       R2 R2 R3     ; R2 := R2 / R3
 72 [-]: DIV       R2 K15 R2    ; R2 := 1.000000 / R2
 73 [-]: GETGLOBAL R3 K16       ; R3 := 0x5bced4c4
 74 [-]: GETTABLE  R3 R3 K17    ; R3 := R3[0xac1b386a]
 75 [-]: CONST     R4 1         ; R4 := 1.000000
 76 [-]: MOVE      R5 R1        ; R5 := R1
 77 [-]: CALL      R3 3 2       ; R3 := R3(R4,R5)
 78 [-]: DIV       R2 R2 R3     ; R2 := R2 / R3
 79 [-]: GETUPVAL  R3 U7        ; R3 := U7
 80 [-]: DIV       R3 K15 R3    ; R3 := 1.000000 / R3
 81 [-]: MUL       R2 R2 R3     ; R2 := R2 * R3
 82 [-]: SETUPVAL  R2 U6        ; U82 := R6
 83 [-]: GETUPVAL  R2 U8        ; R2 := U8
 84 [-]: SELF      R2 R2 K18    ; R3 := R2; R2 := R2[0xd0f998cd]
 85 [-]: GETUPVAL  R4 U6        ; R4 := U6
 86 [-]: CALL      R2 3 1       ; R2(R3,R4)
 87 [-]: GETUPVAL  R2 U9        ; R2 := U9
 88 [-]: CALL      R2 1 1       ; R2()
 89 [-]: GETUPVAL  R2 U10       ; R2 := U10
 90 [-]: TEST      R2 1         ; if R2 then PC := 111
 91 [-]: JMP       111          ; PC := 111
 92 [-]: GETUPVAL  R2 U0        ; R2 := U0
 93 [-]: SELF      R2 R2 K19    ; R3 := R2; R2 := R2[0xec943d0f]
 94 [-]: CALL      R2 2 2       ; R2 := R2(R3)
 95 [-]: TEST      R2 1         ; if R2 then PC := 111
 96 [-]: JMP       111          ; PC := 111
 97 [-]: GETGLOBAL R2 K20       ; R2 := 0x25312c9b
 98 [-]: GETGLOBAL R3 K11       ; R3 := 0xae91e43b
 99 [-]: LOADK     R4 K21       ; R4 := "MapHint"
100 [-]: CONST     R5 8         ; R5 := 8.000000
101 [-]: NEWTABLE  R6 1 0       ; R6 := {}
102 [-]: CONST     R7 10        ; R7 := 10.000000
103 [-]: SETLIST   R6 1 1       ; R6[(1-1)*FPF+i] := R(6+i), 1 <= i <= 1
104 [-]: NEWTABLE  R7 1 0       ; R7 := {}
105 [-]: CONST     R8 70        ; R8 := 70.000000
106 [-]: SETLIST   R7 1 1       ; R7[(1-1)*FPF+i] := R(7+i), 1 <= i <= 1
107 [-]: LOADK     R8 K23       ; R8 := 0.300000
108 [-]: LOADK     R9 K23       ; R9 := 0.300000
109 [-]: CLOSURE   R10 0        ; R10 := closure(Function #16.1)
110 [-]: CALL      R2 9 1       ; R2(R3,R4,R5,R6,R7,R8,R9,R10)
111 [-]: GETUPVAL  R2 U10       ; R2 := U10
112 [-]: TEST      R2 0         ; if not R2 then PC := 145
113 [-]: JMP       145          ; PC := 145
114 [-]: GETUPVAL  R2 U12       ; R2 := U12
115 [-]: SELF      R2 R2 K24    ; R3 := R2; R2 := R2[0xbd2e96ea]
116 [-]: GETGLOBAL R4 K25       ; R4 := 0x9bfd9d29
117 [-]: GETUPVAL  R5 U13       ; R5 := U13
118 [-]: LOADKB    R6 1 0       ; R6 := true
119 [-]: CONST     R7 1         ; R7 := 1.000000
120 [-]: CALL      R2 6 2       ; R2 := R2(R3,R4,R5,R6,R7)
121 [-]: SETUPVAL  R2 U11       ; U82 := R11
122 [-]: GETUPVAL  R2 U0        ; R2 := U0
123 [-]: SELF      R2 R2 K26    ; R3 := R2; R2 := R2[0xf5fc319f]
124 [-]: CALL      R2 2 1       ; R2(R3)
125 [-]: GETGLOBAL R2 K27       ; R2 := 0xda391727
126 [-]: LEN       R2 R2        ; R2 := # R2
127 [-]: LT        0 K28 R2     ; if 0.000000 >= R2 then PC := 133
128 [-]: JMP       133          ; PC := 133
129 [-]: GETUPVAL  R2 U0        ; R2 := U0
130 [-]: SELF      R2 R2 K29    ; R3 := R2; R2 := R2[0xfcf9f720]
131 [-]: GETGLOBAL R4 K27       ; R4 := 0xda391727
132 [-]: CALL      R2 3 1       ; R2(R3,R4)
133 [-]: GETGLOBAL R2 K30       ; R2 := 0x85898f0a
134 [-]: LEN       R2 R2        ; R2 := # R2
135 [-]: LT        0 K28 R2     ; if 0.000000 >= R2 then PC := 141
136 [-]: JMP       141          ; PC := 141
137 [-]: GETUPVAL  R2 U0        ; R2 := U0
138 [-]: SELF      R2 R2 K31    ; R3 := R2; R2 := R2[0x6c30503f]
139 [-]: GETGLOBAL R4 K30       ; R4 := 0x85898f0a
140 [-]: CALL      R2 3 1       ; R2(R3,R4)
141 [-]: GETUPVAL  R2 U0        ; R2 := U0
142 [-]: SELF      R2 R2 K32    ; R3 := R2; R2 := R2[0x76b07564]
143 [-]: LOADKB    R4 1 0       ; R4 := true
144 [-]: CALL      R2 3 1       ; R2(R3,R4)
145 [-]: RETURN    R0 1         ; return 


; Function #16.1:
;
; Name:            
; Defined at line: 319
; #Upvalues:       0
; #Parameters:     0
; Is_vararg:       0
; Max Stack Size:  8

  1 [-]: GETGLOBAL R0 K0        ; R0 := 0x25312c9b
  2 [-]: GETGLOBAL R1 K1        ; R1 := 0xae91e43b
  3 [-]: LOADK     R2 K2        ; R2 := "MapHint"
  4 [-]: CONST     R3 8         ; R3 := 8.000000
  5 [-]: NEWTABLE  R4 1 0       ; R4 := {}
  6 [-]: CONST     R5 10        ; R5 := 10.000000
  7 [-]: SETLIST   R4 1 1       ; R4[(1-1)*FPF+i] := R(4+i), 1 <= i <= 1
  8 [-]: NEWTABLE  R5 1 0       ; R5 := {}
  9 [-]: CONST     R6 0         ; R6 := 0.000000
 10 [-]: SETLIST   R5 1 1       ; R5[(1-1)*FPF+i] := R(5+i), 1 <= i <= 1
 11 [-]: LOADK     R6 K4        ; R6 := 0.300000
 12 [-]: CONST     R7 3         ; R7 := 3.000000
 13 [-]: CALL      R0 8 1       ; R0(R1,R2,R3,R4,R5,R6,R7)
 14 [-]: RETURN    R0 1         ; return 


; Function #17:
;
; Name:            
; Defined at line: 337
; #Upvalues:       14
; #Parameters:     0
; Is_vararg:       0
; Max Stack Size:  23

  1 [-]: GETUPVAL  R0 U0        ; R0 := U0
  2 [-]: TEST      R0 0         ; if not R0 then PC := 284
  3 [-]: JMP       284          ; PC := 284
  4 [-]: GETGLOBAL R0 K0        ; R0 := 0x7b998233
  5 [-]: GETUPVAL  R1 U1        ; R1 := U1
  6 [-]: CALL      R0 2 2       ; R0 := R0(R1)
  7 [-]: TEST      R0 1         ; if R0 then PC := 284
  8 [-]: JMP       284          ; PC := 284
  9 [-]: GETUPVAL  R0 U1        ; R0 := U1
 10 [-]: SELF      R0 R0 K1     ; R1 := R0; R0 := R0[0x450e5a70]
 11 [-]: CALL      R0 2 2       ; R0 := R0(R1)
 12 [-]: GETUPVAL  R1 U2        ; R1 := U2
 13 [-]: GETUPVAL  R2 U3        ; R2 := U3
 14 [-]: GETUPVAL  R3 U4        ; R3 := U4
 15 [-]: EQ        1 R2 R3      ; if R2 == R3 then PC := 18
 16 [-]: JMP       18           ; PC := 18
 17 [-]: LOADKB    R1 1 0       ; R1 := true
 18 [-]: GETUPVAL  R2 U3        ; R2 := U3
 19 [-]: GETTABLE  R2 R2 K2     ; R2 := R2["x"]
 20 [-]: GETUPVAL  R3 U5        ; R3 := U5
 21 [-]: GETTABLE  R3 R3 K2     ; R3 := R3["x"]
 22 [-]: SUB       R2 R2 R3     ; R2 := R2 - R3
 23 [-]: GETUPVAL  R3 U6        ; R3 := U6
 24 [-]: GETTABLE  R3 R3 K2     ; R3 := R3["x"]
 25 [-]: GETUPVAL  R4 U5        ; R4 := U5
 26 [-]: GETTABLE  R4 R4 K2     ; R4 := R4["x"]
 27 [-]: SUB       R3 R3 R4     ; R3 := R3 - R4
 28 [-]: DIV       R2 R2 R3     ; R2 := R2 / R3
 29 [-]: GETUPVAL  R3 U3        ; R3 := U3
 30 [-]: GETTABLE  R3 R3 K3     ; R3 := R3["z"]
 31 [-]: GETUPVAL  R4 U5        ; R4 := U5
 32 [-]: GETTABLE  R4 R4 K3     ; R4 := R4["z"]
 33 [-]: SUB       R3 R3 R4     ; R3 := R3 - R4
 34 [-]: GETUPVAL  R4 U6        ; R4 := U6
 35 [-]: GETTABLE  R4 R4 K3     ; R4 := R4["z"]
 36 [-]: GETUPVAL  R5 U5        ; R5 := U5
 37 [-]: GETTABLE  R5 R5 K3     ; R5 := R5["z"]
 38 [-]: SUB       R4 R4 R5     ; R4 := R4 - R5
 39 [-]: DIV       R3 R3 R4     ; R3 := R3 / R4
 40 [-]: GETUPVAL  R4 U7        ; R4 := U7
 41 [-]: GETTABLE  R4 R4 K2     ; R4 := R4["x"]
 42 [-]: MUL       R4 R4 R0     ; R4 := R4 * R0
 43 [-]: GETUPVAL  R5 U7        ; R5 := U7
 44 [-]: GETTABLE  R5 R5 K3     ; R5 := R5["z"]
 45 [-]: MUL       R5 R5 R0     ; R5 := R5 * R0
 46 [-]: DIV       R6 R5 K4     ; R6 := R5 / 2.000000
 47 [-]: GETUPVAL  R7 U8        ; R7 := U8
 48 [-]: DIV       R6 R6 R7     ; R6 := R6 / R7
 49 [-]: GETUPVAL  R7 U8        ; R7 := U8
 50 [-]: MUL       R7 R6 R7     ; R7 := R6 * R7
 51 [-]: GETUPVAL  R8 U9        ; R8 := U9
 52 [-]: MUL       R8 R6 R8     ; R8 := R6 * R8
 53 [-]: GETGLOBAL R9 K5        ; R9 := 0xae91e43b
 54 [-]: SELF      R9 R9 K6     ; R10 := R9; R9 := R9[0x6b837788]
 55 [-]: CALL      R9 2 2       ; R9 := R9(R10)
 56 [-]: GETGLOBAL R10 K5       ; R10 := 0xae91e43b
 57 [-]: SELF      R10 R10 K7   ; R11 := R10; R10 := R10[0xaf9fda9f]
 58 [-]: CALL      R10 2 2      ; R10 := R10(R11)
 59 [-]: DIV       R9 R9 R10    ; R9 := R9 / R10
 60 [-]: GETUPVAL  R10 U9       ; R10 := U9
 61 [-]: GETUPVAL  R11 U8       ; R11 := U8
 62 [-]: DIV       R10 R10 R11  ; R10 := R10 / R11
 63 [-]: DIV       R9 R9 R10    ; R9 := R9 / R10
 64 [-]: LT        0 R9 K8      ; if R9 >= 1.000000 then PC := 68
 65 [-]: JMP       68           ; PC := 68
 66 [-]: DIV       R7 R7 R9     ; R7 := R7 / R9
 67 [-]: JMP       69           ; PC := 69
 68 [-]: MUL       R8 R8 R9     ; R8 := R8 * R9
 69 [-]: GETUPVAL  R10 U10      ; R10 := U10
 70 [-]: GETTABLE  R10 R10 K9   ; R10 := R10["IsVisible"]
 71 [-]: TEST      R10 1        ; if R10 then PC := 112
 72 [-]: JMP       112          ; PC := 112
 73 [-]: GETUPVAL  R10 U11      ; R10 := U11
 74 [-]: GETTABLE  R10 R10 K10  ; R10 := R10["mCurVal"]
 75 [-]: GETUPVAL  R11 U0       ; R11 := U0
 76 [-]: GETTABLE  R11 R11 K11  ; R11 := R11["mMin"]
 77 [-]: UNM       R12 R4       ; R12 :=  R4
 78 [-]: SUB       R13 K8 R2    ; R13 := 1.000000 - R2
 79 [-]: MUL       R12 R12 R13  ; R12 := R12 * R13
 80 [-]: GETUPVAL  R13 U12      ; R13 := U12
 81 [-]: DIV       R13 R10 R13  ; R13 := R10 / R13
 82 [-]: DIV       R13 R8 R13   ; R13 := R8 / R13
 83 [-]: ADD       R12 R12 R13  ; R12 := R12 + R13
 84 [-]: SETTABLE  R11 K2 R12   ; R11["x"] := R12
 85 [-]: GETUPVAL  R11 U0       ; R11 := U0
 86 [-]: GETTABLE  R11 R11 K12  ; R11 := R11["mMax"]
 87 [-]: MUL       R12 R4 R2    ; R12 := R4 * R2
 88 [-]: GETUPVAL  R13 U12      ; R13 := U12
 89 [-]: DIV       R13 R10 R13  ; R13 := R10 / R13
 90 [-]: DIV       R13 R8 R13   ; R13 := R8 / R13
 91 [-]: SUB       R12 R12 R13  ; R12 := R12 - R13
 92 [-]: SETTABLE  R11 K2 R12   ; R11["x"] := R12
 93 [-]: GETUPVAL  R11 U0       ; R11 := U0
 94 [-]: GETTABLE  R11 R11 K11  ; R11 := R11["mMin"]
 95 [-]: UNM       R12 R5       ; R12 :=  R5
 96 [-]: MUL       R12 R12 R3   ; R12 := R12 * R3
 97 [-]: GETUPVAL  R13 U12      ; R13 := U12
 98 [-]: DIV       R13 R10 R13  ; R13 := R10 / R13
 99 [-]: DIV       R13 R7 R13   ; R13 := R7 / R13
100 [-]: ADD       R12 R12 R13  ; R12 := R12 + R13
101 [-]: SETTABLE  R11 K13 R12  ; R11["y"] := R12
102 [-]: GETUPVAL  R11 U0       ; R11 := U0
103 [-]: GETTABLE  R11 R11 K12  ; R11 := R11["mMax"]
104 [-]: SUB       R12 K8 R3    ; R12 := 1.000000 - R3
105 [-]: MUL       R12 R5 R12   ; R12 := R5 * R12
106 [-]: GETUPVAL  R13 U12      ; R13 := U12
107 [-]: DIV       R13 R10 R13  ; R13 := R10 / R13
108 [-]: DIV       R13 R7 R13   ; R13 := R7 / R13
109 [-]: SUB       R12 R12 R13  ; R12 := R12 - R13
110 [-]: SETTABLE  R11 K13 R12  ; R11["y"] := R12
111 [-]: JMP       140          ; PC := 140
112 [-]: GETUPVAL  R11 U0       ; R11 := U0
113 [-]: GETTABLE  R11 R11 K11  ; R11 := R11["mMin"]
114 [-]: UNM       R12 R4       ; R12 :=  R4
115 [-]: SUB       R13 K8 R2    ; R13 := 1.000000 - R2
116 [-]: MUL       R12 R12 R13  ; R12 := R12 * R13
117 [-]: GETGLOBAL R13 K14      ; R13 := 0x6d34258b
118 [-]: ADD       R12 R12 R13  ; R12 := R12 + R13
119 [-]: SETTABLE  R11 K2 R12   ; R11["x"] := R12
120 [-]: GETUPVAL  R11 U0       ; R11 := U0
121 [-]: GETTABLE  R11 R11 K12  ; R11 := R11["mMax"]
122 [-]: MUL       R12 R4 R2    ; R12 := R4 * R2
123 [-]: GETGLOBAL R13 K14      ; R13 := 0x6d34258b
124 [-]: SUB       R12 R12 R13  ; R12 := R12 - R13
125 [-]: SETTABLE  R11 K2 R12   ; R11["x"] := R12
126 [-]: GETUPVAL  R11 U0       ; R11 := U0
127 [-]: GETTABLE  R11 R11 K11  ; R11 := R11["mMin"]
128 [-]: UNM       R12 R5       ; R12 :=  R5
129 [-]: MUL       R12 R12 R3   ; R12 := R12 * R3
130 [-]: GETGLOBAL R13 K14      ; R13 := 0x6d34258b
131 [-]: ADD       R12 R12 R13  ; R12 := R12 + R13
132 [-]: SETTABLE  R11 K13 R12  ; R11["y"] := R12
133 [-]: GETUPVAL  R11 U0       ; R11 := U0
134 [-]: GETTABLE  R11 R11 K12  ; R11 := R11["mMax"]
135 [-]: SUB       R12 K8 R3    ; R12 := 1.000000 - R3
136 [-]: MUL       R12 R5 R12   ; R12 := R5 * R12
137 [-]: GETGLOBAL R13 K14      ; R13 := 0x6d34258b
138 [-]: SUB       R12 R12 R13  ; R12 := R12 - R13
139 [-]: SETTABLE  R11 K13 R12  ; R11["y"] := R12
140 [-]: GETUPVAL  R11 U0       ; R11 := U0
141 [-]: GETTABLE  R11 R11 K11  ; R11 := R11["mMin"]
142 [-]: GETTABLE  R11 R11 K2   ; R11 := R11["x"]
143 [-]: GETUPVAL  R12 U0       ; R12 := U0
144 [-]: GETTABLE  R12 R12 K12  ; R12 := R12["mMax"]
145 [-]: GETTABLE  R12 R12 K2   ; R12 := R12["x"]
146 [-]: LT        0 R12 R11    ; if R12 >= R11 then PC := 160
147 [-]: JMP       160          ; PC := 160
148 [-]: GETUPVAL  R11 U0       ; R11 := U0
149 [-]: GETTABLE  R11 R11 K11  ; R11 := R11["mMin"]
150 [-]: GETTABLE  R11 R11 K2   ; R11 := R11["x"]
151 [-]: GETUPVAL  R12 U0       ; R12 := U0
152 [-]: GETTABLE  R12 R12 K11  ; R12 := R12["mMin"]
153 [-]: GETUPVAL  R13 U0       ; R13 := U0
154 [-]: GETTABLE  R13 R13 K12  ; R13 := R13["mMax"]
155 [-]: GETTABLE  R13 R13 K2   ; R13 := R13["x"]
156 [-]: SETTABLE  R12 K2 R13   ; R12["x"] := R13
157 [-]: GETUPVAL  R12 U0       ; R12 := U0
158 [-]: GETTABLE  R12 R12 K12  ; R12 := R12["mMax"]
159 [-]: SETTABLE  R12 K2 R11   ; R12["x"] := R11
160 [-]: GETUPVAL  R12 U0       ; R12 := U0
161 [-]: GETTABLE  R12 R12 K11  ; R12 := R12["mMin"]
162 [-]: GETTABLE  R12 R12 K13  ; R12 := R12["y"]
163 [-]: GETUPVAL  R13 U0       ; R13 := U0
164 [-]: GETTABLE  R13 R13 K12  ; R13 := R13["mMax"]
165 [-]: GETTABLE  R13 R13 K13  ; R13 := R13["y"]
166 [-]: LT        0 R13 R12    ; if R13 >= R12 then PC := 180
167 [-]: JMP       180          ; PC := 180
168 [-]: GETUPVAL  R12 U0       ; R12 := U0
169 [-]: GETTABLE  R12 R12 K11  ; R12 := R12["mMin"]
170 [-]: GETTABLE  R12 R12 K13  ; R12 := R12["y"]
171 [-]: GETUPVAL  R13 U0       ; R13 := U0
172 [-]: GETTABLE  R13 R13 K11  ; R13 := R13["mMin"]
173 [-]: GETUPVAL  R14 U0       ; R14 := U0
174 [-]: GETTABLE  R14 R14 K12  ; R14 := R14["mMax"]
175 [-]: GETTABLE  R14 R14 K13  ; R14 := R14["y"]
176 [-]: SETTABLE  R13 K13 R14  ; R13["y"] := R14
177 [-]: GETUPVAL  R13 U0       ; R13 := U0
178 [-]: GETTABLE  R13 R13 K12  ; R13 := R13["mMax"]
179 [-]: SETTABLE  R13 K13 R12  ; R13["y"] := R12
180 [-]: GETUPVAL  R13 U0       ; R13 := U0
181 [-]: GETTABLE  R13 R13 K15  ; R13 := R13["mScrollRange"]
182 [-]: GETUPVAL  R14 U0       ; R14 := U0
183 [-]: GETTABLE  R14 R14 K11  ; R14 := R14["mMin"]
184 [-]: GETTABLE  R14 R14 K2   ; R14 := R14["x"]
185 [-]: GETUPVAL  R15 U0       ; R15 := U0
186 [-]: GETTABLE  R15 R15 K12  ; R15 := R15["mMax"]
187 [-]: GETTABLE  R15 R15 K2   ; R15 := R15["x"]
188 [-]: SUB       R14 R14 R15  ; R14 := R14 - R15
189 [-]: SETTABLE  R13 K2 R14   ; R13["x"] := R14
190 [-]: GETUPVAL  R13 U0       ; R13 := U0
191 [-]: GETTABLE  R13 R13 K15  ; R13 := R13["mScrollRange"]
192 [-]: GETUPVAL  R14 U0       ; R14 := U0
193 [-]: GETTABLE  R14 R14 K11  ; R14 := R14["mMin"]
194 [-]: GETTABLE  R14 R14 K13  ; R14 := R14["y"]
195 [-]: GETUPVAL  R15 U0       ; R15 := U0
196 [-]: GETTABLE  R15 R15 K12  ; R15 := R15["mMax"]
197 [-]: GETTABLE  R15 R15 K13  ; R15 := R15["y"]
198 [-]: SUB       R14 R14 R15  ; R14 := R14 - R15
199 [-]: SETTABLE  R13 K13 R14  ; R13["y"] := R14
200 [-]: GETUPVAL  R13 U0       ; R13 := U0
201 [-]: GETTABLE  R13 R13 K12  ; R13 := R13["mMax"]
202 [-]: GETTABLE  R13 R13 K13  ; R13 := R13["y"]
203 [-]: GETUPVAL  R14 U0       ; R14 := U0
204 [-]: GETTABLE  R14 R14 K11  ; R14 := R14["mMin"]
205 [-]: GETTABLE  R14 R14 K13  ; R14 := R14["y"]
206 [-]: SUB       R13 R13 R14  ; R13 := R13 - R14
207 [-]: GETUPVAL  R14 U0       ; R14 := U0
208 [-]: GETTABLE  R14 R14 K12  ; R14 := R14["mMax"]
209 [-]: GETTABLE  R14 R14 K2   ; R14 := R14["x"]
210 [-]: GETUPVAL  R15 U0       ; R15 := U0
211 [-]: GETTABLE  R15 R15 K11  ; R15 := R15["mMin"]
212 [-]: GETTABLE  R15 R15 K2   ; R15 := R15["x"]
213 [-]: SUB       R14 R14 R15  ; R14 := R14 - R15
214 [-]: GETGLOBAL R15 K16      ; R15 := 0x42dcc9f5
215 [-]: GETUPVAL  R16 U13      ; R16 := U13
216 [-]: GETTABLE  R16 R16 K17  ; R16 := R16[0x06d055f9]
217 [-]: EQ        0 R13 K18    ; if R13 ~= 0.000000 then PC := 220
218 [-]: JMP       220          ; PC := 220
219 [-]: LOADKB    R17 0 1      ; R17 := false; PC := 220
220 [-]: LOADKB    R17 1 0      ; R17 := true
221 [-]: GETUPVAL  R18 U0       ; R18 := U0
222 [-]: GETTABLE  R18 R18 K19  ; R18 := R18["mCurrentCoords"]
223 [-]: GETTABLE  R18 R18 K13  ; R18 := R18["y"]
224 [-]: GETUPVAL  R19 U0       ; R19 := U0
225 [-]: GETTABLE  R19 R19 K11  ; R19 := R19["mMin"]
226 [-]: GETTABLE  R19 R19 K13  ; R19 := R19["y"]
227 [-]: SUB       R18 R18 R19  ; R18 := R18 - R19
228 [-]: DIV       R18 R18 R13  ; R18 := R18 / R13
229 [-]: SUB       R18 K8 R18   ; R18 := 1.000000 - R18
230 [-]: CONST     R19 1        ; R19 := 1.000000
231 [-]: CALL      R16 4 2      ; R16 := R16(R17,R18,R19)
232 [-]: GETUPVAL  R17 U0       ; R17 := U0
233 [-]: GETTABLE  R17 R17 K20  ; R17 := R17["mLeeway"]
234 [-]: GETTABLE  R17 R17 K13  ; R17 := R17["y"]
235 [-]: SUB       R17 K18 R17  ; R17 := 0.000000 - R17
236 [-]: GETUPVAL  R18 U0       ; R18 := U0
237 [-]: GETTABLE  R18 R18 K20  ; R18 := R18["mLeeway"]
238 [-]: GETTABLE  R18 R18 K13  ; R18 := R18["y"]
239 [-]: ADD       R18 K8 R18   ; R18 := 1.000000 + R18
240 [-]: CALL      R15 4 2      ; R15 := R15(R16,R17,R18)
241 [-]: GETGLOBAL R16 K16      ; R16 := 0x42dcc9f5
242 [-]: GETUPVAL  R17 U13      ; R17 := U13
243 [-]: GETTABLE  R17 R17 K17  ; R17 := R17[0x06d055f9]
244 [-]: EQ        0 R14 K18    ; if R14 ~= 0.000000 then PC := 247
245 [-]: JMP       247          ; PC := 247
246 [-]: LOADKB    R18 0 1      ; R18 := false; PC := 247
247 [-]: LOADKB    R18 1 0      ; R18 := true
248 [-]: GETUPVAL  R19 U0       ; R19 := U0
249 [-]: GETTABLE  R19 R19 K19  ; R19 := R19["mCurrentCoords"]
250 [-]: GETTABLE  R19 R19 K2   ; R19 := R19["x"]
251 [-]: GETUPVAL  R20 U0       ; R20 := U0
252 [-]: GETTABLE  R20 R20 K11  ; R20 := R20["mMin"]
253 [-]: GETTABLE  R20 R20 K2   ; R20 := R20["x"]
254 [-]: SUB       R19 R19 R20  ; R19 := R19 - R20
255 [-]: DIV       R19 R19 R14  ; R19 := R19 / R14
256 [-]: SUB       R19 K8 R19   ; R19 := 1.000000 - R19
257 [-]: CONST     R20 1        ; R20 := 1.000000
258 [-]: CALL      R17 4 2      ; R17 := R17(R18,R19,R20)
259 [-]: GETUPVAL  R18 U0       ; R18 := U0
260 [-]: GETTABLE  R18 R18 K20  ; R18 := R18["mLeeway"]
261 [-]: GETTABLE  R18 R18 K2   ; R18 := R18["x"]
262 [-]: SUB       R18 K18 R18  ; R18 := 0.000000 - R18
263 [-]: GETUPVAL  R19 U0       ; R19 := U0
264 [-]: GETTABLE  R19 R19 K20  ; R19 := R19["mLeeway"]
265 [-]: GETTABLE  R19 R19 K2   ; R19 := R19["x"]
266 [-]: ADD       R19 K8 R19   ; R19 := 1.000000 + R19
267 [-]: CALL      R16 4 2      ; R16 := R16(R17,R18,R19)
268 [-]: GETUPVAL  R17 U0       ; R17 := U0
269 [-]: SELF      R17 R17 K21  ; R18 := R17; R17 := R17[0x4c4f8717]
270 [-]: LOADK     R19 K2       ; R19 := "x"
271 [-]: MOVE      R20 R16      ; R20 := R16
272 [-]: LOADNIL   R21 R21      ; R21 := nil
273 [-]: MOVE      R22 R1       ; R22 := R1
274 [-]: CALL      R17 6 1      ; R17(R18,R19,R20,R21,R22)
275 [-]: GETUPVAL  R17 U0       ; R17 := U0
276 [-]: SELF      R17 R17 K21  ; R18 := R17; R17 := R17[0x4c4f8717]
277 [-]: LOADK     R19 K13      ; R19 := "y"
278 [-]: MOVE      R20 R15      ; R20 := R15
279 [-]: LOADNIL   R21 R21      ; R21 := nil
280 [-]: MOVE      R22 R1       ; R22 := R1
281 [-]: CALL      R17 6 1      ; R17(R18,R19,R20,R21,R22)
282 [-]: LOADKB    R17 0 0      ; R17 := false
283 [-]: SETUPVAL  R17 U2       ; U82 := R2
284 [-]: RETURN    R0 1         ; return 


; Function #18:
;
; Name:            
; Defined at line: 398
; #Upvalues:       6
; #Parameters:     2
; Is_vararg:       0
; Max Stack Size:  9

  1 [-]: GETUPVAL  R2 U0        ; R2 := U0
  2 [-]: GETTABLE  R2 R2 K0     ; R2 := R2["mCurVal"]
  3 [-]: GETUPVAL  R3 U1        ; R3 := U1
  4 [-]: SELF      R3 R3 K1     ; R4 := R3; R3 := R3[0x450e5a70]
  5 [-]: CALL      R3 2 2       ; R3 := R3(R4)
  6 [-]: MUL       R3 R3 R2     ; R3 := R3 * R2
  7 [-]: GETUPVAL  R4 U2        ; R4 := U2
  8 [-]: SELF      R4 R4 K2     ; R5 := R4; R4 := R4[0xd1586535]
  9 [-]: CALL      R4 2 2       ; R4 := R4(R5)
 10 [-]: GETTABLE  R5 R4 K3     ; R5 := R4["x"]
 11 [-]: GETUPVAL  R6 U3        ; R6 := U3
 12 [-]: DIV       R6 R6 K4     ; R6 := R6 / 2.000000
 13 [-]: SUB       R6 R0 R6     ; R6 := R0 - R6
 14 [-]: GETUPVAL  R7 U4        ; R7 := U4
 15 [-]: GETTABLE  R7 R7 K5     ; R7 := R7["mCurrentCoords"]
 16 [-]: GETTABLE  R7 R7 K3     ; R7 := R7["x"]
 17 [-]: MUL       R7 R7 R2     ; R7 := R7 * R2
 18 [-]: SUB       R6 R6 R7     ; R6 := R6 - R7
 19 [-]: DIV       R6 R6 R3     ; R6 := R6 / R3
 20 [-]: ADD       R5 R5 R6     ; R5 := R5 + R6
 21 [-]: GETTABLE  R6 R4 K6     ; R6 := R4["z"]
 22 [-]: GETUPVAL  R7 U5        ; R7 := U5
 23 [-]: DIV       R7 R7 K4     ; R7 := R7 / 2.000000
 24 [-]: SUB       R7 R1 R7     ; R7 := R1 - R7
 25 [-]: GETUPVAL  R8 U4        ; R8 := U4
 26 [-]: GETTABLE  R8 R8 K5     ; R8 := R8["mCurrentCoords"]
 27 [-]: GETTABLE  R8 R8 K7     ; R8 := R8["y"]
 28 [-]: MUL       R8 R8 R2     ; R8 := R8 * R2
 29 [-]: SUB       R7 R7 R8     ; R7 := R7 - R8
 30 [-]: DIV       R7 R7 R3     ; R7 := R7 / R3
 31 [-]: SUB       R6 R6 R7     ; R6 := R6 - R7
 32 [-]: MOVE      R7 R5        ; R7 := R5
 33 [-]: MOVE      R8 R6        ; R8 := R6
 34 [-]: RETURN    R7 3         ; return R7,R8
 35 [-]: RETURN    R0 1         ; return 


; Function #19:
;
; Name:            
; Defined at line: 410
; #Upvalues:       12
; #Parameters:     0
; Is_vararg:       0
; Max Stack Size:  6

  1 [-]: GETGLOBAL R0 K0        ; R0 := 0x7b998233
  2 [-]: GETGLOBAL R1 K1        ; R1 := 0x89326c93
  3 [-]: CALL      R0 2 2       ; R0 := R0(R1)
  4 [-]: TEST      R0 1         ; if R0 then PC := 31
  5 [-]: JMP       31           ; PC := 31
  6 [-]: GETGLOBAL R0 K1        ; R0 := 0x89326c93
  7 [-]: SELF      R0 R0 K2     ; R1 := R0; R0 := R0[0xded7d5cd]
  8 [-]: CALL      R0 2 2       ; R0 := R0(R1)
  9 [-]: GETGLOBAL R1 K0        ; R1 := 0x7b998233
 10 [-]: MOVE      R2 R0        ; R2 := R0
 11 [-]: CALL      R1 2 2       ; R1 := R1(R2)
 12 [-]: TEST      R1 1         ; if R1 then PC := 31
 13 [-]: JMP       31           ; PC := 31
 14 [-]: GETGLOBAL R1 K0        ; R1 := 0x7b998233
 15 [-]: GETTABLE  R2 R0 K3     ; R2 := R0[1.000000]
 16 [-]: CALL      R1 2 2       ; R1 := R1(R2)
 17 [-]: TEST      R1 1         ; if R1 then PC := 31
 18 [-]: JMP       31           ; PC := 31
 19 [-]: GETTABLE  R1 R0 K3     ; R1 := R0[1.000000]
 20 [-]: SELF      R1 R1 K4     ; R2 := R1; R1 := R1[0xbb610e5b]
 21 [-]: CALL      R1 2 2       ; R1 := R1(R2)
 22 [-]: SETUPVAL  R1 U0        ; U82 := R0
 23 [-]: GETUPVAL  R1 U0        ; R1 := U0
 24 [-]: SELF      R1 R1 K5     ; R2 := R1; R1 := R1[0x5e651723]
 25 [-]: CALL      R1 2 2       ; R1 := R1(R2)
 26 [-]: SETUPVAL  R1 U1        ; U82 := R1
 27 [-]: GETUPVAL  R1 U1        ; R1 := U1
 28 [-]: SELF      R1 R1 K6     ; R2 := R1; R1 := R1[0x0803eee1]
 29 [-]: CALL      R1 2 2       ; R1 := R1(R2)
 30 [-]: SETUPVAL  R1 U2        ; U82 := R2
 31 [-]: GETGLOBAL R1 K0        ; R1 := 0x7b998233
 32 [-]: GETUPVAL  R2 U0        ; R2 := U0
 33 [-]: CALL      R1 2 2       ; R1 := R1(R2)
 34 [-]: TEST      R1 0         ; if not R1 then PC := 42
 35 [-]: JMP       42           ; PC := 42
 36 [-]: GETGLOBAL R1 K7        ; R1 := 0x3d106989
 37 [-]: LOADK     R2 K8        ; R2 := "ERROR: No avatar found!"
 38 [-]: CALL      R1 2 1       ; R1(R2)
 39 [-]: GETGLOBAL R1 K9        ; R1 := 0x60cce7b4
 40 [-]: LOADKB    R2 0 0       ; R2 := false
 41 [-]: CALL      R1 2 1       ; R1(R2)
 42 [-]: GETGLOBAL R1 K10       ; R1 := 0xbe190284
 43 [-]: GETGLOBAL R2 K0        ; R2 := 0x7b998233
 44 [-]: MOVE      R3 R1        ; R3 := R1
 45 [-]: CALL      R2 2 2       ; R2 := R2(R3)
 46 [-]: TEST      R2 1         ; if R2 then PC := 62
 47 [-]: JMP       62           ; PC := 62
 48 [-]: SELF      R2 R1 K11    ; R3 := R1; R2 := R1[0x99f38c13]
 49 [-]: CALL      R2 2 2       ; R2 := R2(R3)
 50 [-]: SETUPVAL  R2 U3        ; U82 := R3
 51 [-]: SELF      R2 R1 K12    ; R3 := R1; R2 := R1[0xf2deaf69]
 52 [-]: GETGLOBAL R4 K13       ; R4 := gLotusAttractModeGameRulesType
 53 [-]: CALL      R2 3 2       ; R2 := R2(R3,R4)
 54 [-]: TEST      R2 1         ; if R2 then PC := 59
 55 [-]: JMP       59           ; PC := 59
 56 [-]: SELF      R2 R1 K14    ; R3 := R1; R2 := R1[0x1a8ce866]
 57 [-]: CALL      R2 2 2       ; R2 := R2(R3)
 58 [-]: JMP       61           ; PC := 61
 59 [-]: LOADKB    R2 0 1       ; R2 := false; PC := 60
 60 [-]: LOADKB    R2 1 0       ; R2 := true
 61 [-]: SETUPVAL  R2 U4        ; U82 := R4
 62 [-]: GETUPVAL  R2 U5        ; R2 := U5
 63 [-]: CALL      R2 1 1       ; R2()
 64 [-]: GETGLOBAL R2 K0        ; R2 := 0x7b998233
 65 [-]: GETGLOBAL R3 K15       ; R3 := 0x76ea806b
 66 [-]: SELF      R3 R3 K16    ; R4 := R3; R3 := R3[0x3f3ae64c]
 67 [-]: CONST     R5 0         ; R5 := 0.000000
 68 [-]: CALL      R3 3 0       ; R3,... := R3(R4,R5)
 69 [-]: CALL      R2 0 2       ; R2 := R2(R3,...)
 70 [-]: TEST      R2 1         ; if R2 then PC := 82
 71 [-]: JMP       82           ; PC := 82
 72 [-]: GETGLOBAL R2 K17       ; R2 := 0x11a19c5e
 73 [-]: GETGLOBAL R3 K15       ; R3 := 0x76ea806b
 74 [-]: SELF      R3 R3 K16    ; R4 := R3; R3 := R3[0x3f3ae64c]
 75 [-]: CONST     R5 0         ; R5 := 0.000000
 76 [-]: CALL      R3 3 2       ; R3 := R3(R4,R5)
 77 [-]: SELF      R3 R3 K18    ; R4 := R3; R3 := R3[0x80563238]
 78 [-]: CALL      R3 2 2       ; R3 := R3(R4)
 79 [-]: LOADK     R4 K19       ; R4 := "OnProfileSaved"
 80 [-]: CALL      R2 3 1       ; R2(R3,R4)
 81 [-]: JMP       85           ; PC := 85
 82 [-]: GETGLOBAL R2 K7        ; R2 := 0x3d106989
 83 [-]: LOADK     R3 K20       ; R3 := "InitOnValidAvatarPlayer: no playerProfile"
 84 [-]: CALL      R2 2 1       ; R2(R3)
 85 [-]: GETUPVAL  R2 U6        ; R2 := U6
 86 [-]: CALL      R2 1 1       ; R2()
 87 [-]: GETUPVAL  R2 U0        ; R2 := U0
 88 [-]: SELF      R2 R2 K5     ; R3 := R2; R2 := R2[0x5e651723]
 89 [-]: CALL      R2 2 2       ; R2 := R2(R3)
 90 [-]: SELF      R2 R2 K21    ; R3 := R2; R2 := R2[0x474501e1]
 91 [-]: CALL      R2 2 2       ; R2 := R2(R3)
 92 [-]: SETUPVAL  R2 U7        ; U82 := R7
 93 [-]: GETUPVAL  R2 U8        ; R2 := U8
 94 [-]: CALL      R2 1 1       ; R2()
 95 [-]: GETUPVAL  R2 U9        ; R2 := U9
 96 [-]: CALL      R2 1 1       ; R2()
 97 [-]: GETUPVAL  R2 U10       ; R2 := U10
 98 [-]: CALL      R2 1 1       ; R2()
 99 [-]: LOADKB    R2 1 0       ; R2 := true
100 [-]: SETUPVAL  R2 U11       ; U82 := R11
101 [-]: RETURN    R0 1         ; return 


; Function #20:
;
; Name:            
; Defined at line: 454
; #Upvalues:       1
; #Parameters:     0
; Is_vararg:       0
; Max Stack Size:  7

  1 [-]: GETUPVAL  R0 U0        ; R0 := U0
  2 [-]: GETTABLE  R0 R0 K0     ; R0 := R0[0x44537adf]
  3 [-]: GETGLOBAL R1 K1        ; R1 := 0xae91e43b
  4 [-]: CALL      R0 2 3       ; R0,R1 := R0(R1)
  5 [-]: GETGLOBAL R2 K1        ; R2 := 0xae91e43b
  6 [-]: SELF      R2 R2 K2     ; R3 := R2; R2 := R2[0x67bc869f]
  7 [-]: LOADK     R4 K3        ; R4 := "Blurer"
  8 [-]: CONST     R5 12        ; R5 := 12.000000
  9 [-]: MOVE      R6 R0        ; R6 := R0
 10 [-]: CALL      R2 5 1       ; R2(R3,R4,R5,R6)
 11 [-]: GETGLOBAL R2 K1        ; R2 := 0xae91e43b
 12 [-]: SELF      R2 R2 K2     ; R3 := R2; R2 := R2[0x67bc869f]
 13 [-]: LOADK     R4 K3        ; R4 := "Blurer"
 14 [-]: CONST     R5 13        ; R5 := 13.000000
 15 [-]: MOVE      R6 R1        ; R6 := R1
 16 [-]: CALL      R2 5 1       ; R2(R3,R4,R5,R6)
 17 [-]: RETURN    R0 1         ; return 


; Function #21:
;
; Name:            
; Defined at line: 461
; #Upvalues:       2
; #Parameters:     0
; Is_vararg:       0
; Max Stack Size:  6

  1 [-]: GETUPVAL  R0 U0        ; R0 := U0
  2 [-]: GETTABLE  R0 R0 K0     ; R0 := R0[0xe2a93301]
  3 [-]: CALL      R0 1 2       ; R0 := R0()
  4 [-]: GETGLOBAL R1 K1        ; R1 := 0x7b998233
  5 [-]: GETGLOBAL R2 K2        ; R2 := 0xe52f0e49
  6 [-]: GETTABLE  R2 R2 R0     ; R2 := R2[R0]
  7 [-]: CALL      R1 2 2       ; R1 := R1(R2)
  8 [-]: TEST      R1 1         ; if R1 then PC := 67
  9 [-]: JMP       67           ; PC := 67
 10 [-]: GETUPVAL  R1 U0        ; R1 := U0
 11 [-]: GETTABLE  R1 R1 K3     ; R1 := R1["SOUND_SET_ZARIMAN"]
 12 [-]: EQ        0 R0 R1      ; if R0 ~= R1 then PC := 21
 13 [-]: JMP       21           ; PC := 21
 14 [-]: GETGLOBAL R1 K4        ; R1 := 0xae91e43b
 15 [-]: SELF      R1 R1 K5     ; R2 := R1; R1 := R1[0x1cb415c1]
 16 [-]: LOADK     R3 K6        ; R3 := "TimeOfDay.ZarimanCycler.Logo"
 17 [-]: GETGLOBAL R4 K2        ; R4 := 0xe52f0e49
 18 [-]: GETTABLE  R4 R4 R0     ; R4 := R4[R0]
 19 [-]: CALL      R1 4 1       ; R1(R2,R3,R4)
 20 [-]: JMP       27           ; PC := 27
 21 [-]: GETGLOBAL R1 K4        ; R1 := 0xae91e43b
 22 [-]: SELF      R1 R1 K5     ; R2 := R1; R1 := R1[0x1cb415c1]
 23 [-]: LOADK     R3 K7        ; R3 := "TimeOfDay.DayNight"
 24 [-]: GETGLOBAL R4 K2        ; R4 := 0xe52f0e49
 25 [-]: GETTABLE  R4 R4 R0     ; R4 := R4[R0]
 26 [-]: CALL      R1 4 1       ; R1(R2,R3,R4)
 27 [-]: GETGLOBAL R1 K4        ; R1 := 0xae91e43b
 28 [-]: SELF      R1 R1 K5     ; R2 := R1; R1 := R1[0x1cb415c1]
 29 [-]: LOADK     R3 K8        ; R3 := "TimeOfDay.DayNightcycler"
 30 [-]: GETGLOBAL R4 K9        ; R4 := 0x578b7428
 31 [-]: GETTABLE  R4 R4 R0     ; R4 := R4[R0]
 32 [-]: CALL      R1 4 1       ; R1(R2,R3,R4)
 33 [-]: GETGLOBAL R1 K4        ; R1 := 0xae91e43b
 34 [-]: SELF      R1 R1 K10    ; R2 := R1; R1 := R1[0xaade900e]
 35 [-]: LOADK     R3 K11       ; R3 := "TimeOfDay.Label"
 36 [-]: CONST     R4 11        ; R4 := 11.000000
 37 [-]: GETGLOBAL R5 K12       ; R5 := 0xf050e6d8
 38 [-]: GETTABLE  R5 R5 R0     ; R5 := R5[R0]
 39 [-]: CALL      R1 5 1       ; R1(R2,R3,R4,R5)
 40 [-]: GETUPVAL  R1 U0        ; R1 := U0
 41 [-]: GETTABLE  R1 R1 K13    ; R1 := R1["SOUND_SET_FORTUNA"]
 42 [-]: EQ        1 R0 R1      ; if R0 == R1 then PC := 48
 43 [-]: JMP       48           ; PC := 48
 44 [-]: GETUPVAL  R1 U0        ; R1 := U0
 45 [-]: GETTABLE  R1 R1 K14    ; R1 := R1["SOUND_SET_ORB_VALLIS"]
 46 [-]: EQ        0 R0 R1      ; if R0 ~= R1 then PC := 52
 47 [-]: JMP       52           ; PC := 52
 48 [-]: GETUPVAL  R1 U0        ; R1 := U0
 49 [-]: GETTABLE  R1 R1 K15    ; R1 := R1["ORB_VALLIS_NODE_TAG"]
 50 [-]: SETUPVAL  R1 U1        ; U82 := R1
 51 [-]: JMP       67           ; PC := 67
 52 [-]: GETUPVAL  R1 U0        ; R1 := U0
 53 [-]: GETTABLE  R1 R1 K16    ; R1 := R1["SOUND_SET_OROKIN_TOWER"]
 54 [-]: EQ        0 R0 R1      ; if R0 ~= R1 then PC := 60
 55 [-]: JMP       60           ; PC := 60
 56 [-]: GETUPVAL  R1 U0        ; R1 := U0
 57 [-]: GETTABLE  R1 R1 K17    ; R1 := R1["ENTRATI_LANDSCAPE_NODE_TAG"]
 58 [-]: SETUPVAL  R1 U1        ; U82 := R1
 59 [-]: JMP       67           ; PC := 67
 60 [-]: GETUPVAL  R1 U0        ; R1 := U0
 61 [-]: GETTABLE  R1 R1 K3     ; R1 := R1["SOUND_SET_ZARIMAN"]
 62 [-]: EQ        0 R0 R1      ; if R0 ~= R1 then PC := 67
 63 [-]: JMP       67           ; PC := 67
 64 [-]: GETUPVAL  R1 U0        ; R1 := U0
 65 [-]: GETTABLE  R1 R1 K18    ; R1 := R1["ZARIMAN_NODE_TAG"]
 66 [-]: SETUPVAL  R1 U1        ; U82 := R1
 67 [-]: RETURN    R0 1         ; return 


; Function #22:
;
; Name:            
; Defined at line: 482
; #Upvalues:       1
; #Parameters:     0
; Is_vararg:       0
; Max Stack Size:  13

  1 [-]: GETGLOBAL R0 K0        ; R0 := 0xae91e43b
  2 [-]: SELF      R0 R0 K1     ; R1 := R0; R0 := R0[0x91a24e4b]
  3 [-]: LOADK     R2 K2        ; R2 := "TimeOfDay"
  4 [-]: CONST     R3 1         ; R3 := 1.000000
  5 [-]: CALL      R0 4 2       ; R0 := R0(R1,R2,R3)
  6 [-]: CONST     R1 128       ; R1 := 128.000000
  7 [-]: GETUPVAL  R2 U0        ; R2 := U0
  8 [-]: GETTABLE  R2 R2 K3     ; R2 := R2[0xe5e5a417]
  9 [-]: GETGLOBAL R3 K0        ; R3 := 0xae91e43b
 10 [-]: SUB       R4 R0 R1     ; R4 := R0 - R1
 11 [-]: CALL      R2 3 2       ; R2 := R2(R3,R4)
 12 [-]: GETUPVAL  R3 U0        ; R3 := U0
 13 [-]: GETTABLE  R3 R3 K4     ; R3 := R3[0xd718f59b]
 14 [-]: GETGLOBAL R4 K0        ; R4 := 0xae91e43b
 15 [-]: MUL       R5 R1 K5     ; R5 := R1 * 2.000000
 16 [-]: CALL      R3 3 2       ; R3 := R3(R4,R5)
 17 [-]: GETUPVAL  R4 U0        ; R4 := U0
 18 [-]: GETTABLE  R4 R4 K6     ; R4 := R4[0x0db7934d]
 19 [-]: GETGLOBAL R5 K0        ; R5 := 0xae91e43b
 20 [-]: CONST     R6 40        ; R6 := 40.000000
 21 [-]: CALL      R4 3 2       ; R4 := R4(R5,R6)
 22 [-]: GETGLOBAL R5 K0        ; R5 := 0xae91e43b
 23 [-]: SELF      R5 R5 K7     ; R6 := R5; R5 := R5[0x91e13703]
 24 [-]: LOADK     R7 K8        ; R7 := "TimeOfDay.ZarimanCycler.Stroke"
 25 [-]: LOADK     R8 K9        ; R8 := "VisibilityCenter"
 26 [-]: MOVE      R9 R2        ; R9 := R2
 27 [-]: CONST     R10 0        ; R10 := 0.000000
 28 [-]: CONST     R11 0        ; R11 := 0.000000
 29 [-]: CONST     R12 0        ; R12 := 0.000000
 30 [-]: CALL      R5 8 1       ; R5(R6,R7,R8,R9,R10,R11,R12)
 31 [-]: GETGLOBAL R5 K0        ; R5 := 0xae91e43b
 32 [-]: SELF      R5 R5 K7     ; R6 := R5; R5 := R5[0x91e13703]
 33 [-]: LOADK     R7 K8        ; R7 := "TimeOfDay.ZarimanCycler.Stroke"
 34 [-]: LOADK     R8 K10       ; R8 := "VisibilitySize"
 35 [-]: MOVE      R9 R3        ; R9 := R3
 36 [-]: CONST     R10 0        ; R10 := 0.000000
 37 [-]: CONST     R11 0        ; R11 := 0.000000
 38 [-]: CONST     R12 0        ; R12 := 0.000000
 39 [-]: CALL      R5 8 1       ; R5(R6,R7,R8,R9,R10,R11,R12)
 40 [-]: GETGLOBAL R5 K0        ; R5 := 0xae91e43b
 41 [-]: SELF      R5 R5 K7     ; R6 := R5; R5 := R5[0x91e13703]
 42 [-]: LOADK     R7 K8        ; R7 := "TimeOfDay.ZarimanCycler.Stroke"
 43 [-]: LOADK     R8 K11       ; R8 := "VisibilityFadeSize"
 44 [-]: MOVE      R9 R4        ; R9 := R4
 45 [-]: CONST     R10 0        ; R10 := 0.000000
 46 [-]: CONST     R11 0        ; R11 := 0.000000
 47 [-]: CONST     R12 0        ; R12 := 0.000000
 48 [-]: CALL      R5 8 1       ; R5(R6,R7,R8,R9,R10,R11,R12)
 49 [-]: GETGLOBAL R5 K0        ; R5 := 0xae91e43b
 50 [-]: SELF      R5 R5 K7     ; R6 := R5; R5 := R5[0x91e13703]
 51 [-]: LOADK     R7 K12       ; R7 := "TimeOfDay.ZarimanCycler.Fill"
 52 [-]: LOADK     R8 K9        ; R8 := "VisibilityCenter"
 53 [-]: MOVE      R9 R2        ; R9 := R2
 54 [-]: CONST     R10 0        ; R10 := 0.000000
 55 [-]: CONST     R11 0        ; R11 := 0.000000
 56 [-]: CONST     R12 0        ; R12 := 0.000000
 57 [-]: CALL      R5 8 1       ; R5(R6,R7,R8,R9,R10,R11,R12)
 58 [-]: GETGLOBAL R5 K0        ; R5 := 0xae91e43b
 59 [-]: SELF      R5 R5 K7     ; R6 := R5; R5 := R5[0x91e13703]
 60 [-]: LOADK     R7 K12       ; R7 := "TimeOfDay.ZarimanCycler.Fill"
 61 [-]: LOADK     R8 K10       ; R8 := "VisibilitySize"
 62 [-]: MOVE      R9 R3        ; R9 := R3
 63 [-]: CONST     R10 0        ; R10 := 0.000000
 64 [-]: CONST     R11 0        ; R11 := 0.000000
 65 [-]: CONST     R12 0        ; R12 := 0.000000
 66 [-]: CALL      R5 8 1       ; R5(R6,R7,R8,R9,R10,R11,R12)
 67 [-]: GETGLOBAL R5 K0        ; R5 := 0xae91e43b
 68 [-]: SELF      R5 R5 K7     ; R6 := R5; R5 := R5[0x91e13703]
 69 [-]: LOADK     R7 K12       ; R7 := "TimeOfDay.ZarimanCycler.Fill"
 70 [-]: LOADK     R8 K11       ; R8 := "VisibilityFadeSize"
 71 [-]: MOVE      R9 R4        ; R9 := R4
 72 [-]: CONST     R10 0        ; R10 := 0.000000
 73 [-]: CONST     R11 0        ; R11 := 0.000000
 74 [-]: CONST     R12 0        ; R12 := 0.000000
 75 [-]: CALL      R5 8 1       ; R5(R6,R7,R8,R9,R10,R11,R12)
 76 [-]: RETURN    R0 1         ; return 


; Function #23:
;
; Name:            
; Defined at line: 497
; #Upvalues:       18
; #Parameters:     0
; Is_vararg:       0
; Max Stack Size:  17

  1 [-]: GETGLOBAL R0 K0        ; R0 := _T
  2 [-]: GETTABLE  R0 R0 K1     ; R0 := R0["TennoConHubActive"]
  3 [-]: TEST      R0 0         ; if not R0 then PC := 9
  4 [-]: JMP       9            ; PC := 9
  5 [-]: GETGLOBAL R0 K2        ; R0 := 0xae91e43b
  6 [-]: SELF      R0 R0 K3     ; R1 := R0; R0 := R0[0x32302b4a]
  7 [-]: CALL      R0 2 1       ; R0(R1)
  8 [-]: RETURN    R0 1         ; return 
  9 [-]: GETGLOBAL R0 K4        ; R0 := 0x34291f5c
 10 [-]: GETTABLE  R0 R0 K5     ; R0 := R0[0xe6b41adb]
 11 [-]: CALL      R0 1 2       ; R0 := R0()
 12 [-]: TEST      R0 0         ; if not R0 then PC := 77
 13 [-]: JMP       77           ; PC := 77
 14 [-]: GETGLOBAL R0 K6        ; R0 := 0x89326c93
 15 [-]: SELF      R0 R0 K7     ; R1 := R0; R0 := R0[0xfb64e76c]
 16 [-]: CALL      R0 2 2       ; R0 := R0(R1)
 17 [-]: SELF      R0 R0 K8     ; R1 := R0; R0 := R0[0x97c4ff93]
 18 [-]: LOADKB    R2 1 0       ; R2 := true
 19 [-]: CALL      R0 3 1       ; R0(R1,R2)
 20 [-]: GETGLOBAL R0 K2        ; R0 := 0xae91e43b
 21 [-]: SELF      R0 R0 K9     ; R1 := R0; R0 := R0[0x14396727]
 22 [-]: LOADKB    R2 0 0       ; R2 := false
 23 [-]: CALL      R0 3 1       ; R0(R1,R2)
 24 [-]: CONST     R0 125       ; R0 := 125.000000
 25 [-]: CONST     R1 125       ; R1 := 125.000000
 26 [-]: GETGLOBAL R2 K2        ; R2 := 0xae91e43b
 27 [-]: SELF      R2 R2 K10    ; R3 := R2; R2 := R2[0x67bc869f]
 28 [-]: LOADK     R4 K11       ; R4 := "MiniMapContainer"
 29 [-]: CONST     R5 5         ; R5 := 5.000000
 30 [-]: MOVE      R6 R0        ; R6 := R0
 31 [-]: CALL      R2 5 1       ; R2(R3,R4,R5,R6)
 32 [-]: GETGLOBAL R2 K2        ; R2 := 0xae91e43b
 33 [-]: SELF      R2 R2 K10    ; R3 := R2; R2 := R2[0x67bc869f]
 34 [-]: LOADK     R4 K12       ; R4 := "MiniMapOverlayMsg"
 35 [-]: CONST     R5 5         ; R5 := 5.000000
 36 [-]: MOVE      R6 R0        ; R6 := R0
 37 [-]: CALL      R2 5 1       ; R2(R3,R4,R5,R6)
 38 [-]: GETGLOBAL R2 K2        ; R2 := 0xae91e43b
 39 [-]: SELF      R2 R2 K10    ; R3 := R2; R2 := R2[0x67bc869f]
 40 [-]: LOADK     R4 K11       ; R4 := "MiniMapContainer"
 41 [-]: CONST     R5 6         ; R5 := 6.000000
 42 [-]: MOVE      R6 R0        ; R6 := R0
 43 [-]: CALL      R2 5 1       ; R2(R3,R4,R5,R6)
 44 [-]: GETGLOBAL R2 K2        ; R2 := 0xae91e43b
 45 [-]: SELF      R2 R2 K10    ; R3 := R2; R2 := R2[0x67bc869f]
 46 [-]: LOADK     R4 K12       ; R4 := "MiniMapOverlayMsg"
 47 [-]: CONST     R5 6         ; R5 := 6.000000
 48 [-]: MOVE      R6 R0        ; R6 := R0
 49 [-]: CALL      R2 5 1       ; R2(R3,R4,R5,R6)
 50 [-]: LOADK     R2 K13       ; R2 := "MiniMapContainer.MiniMapMarkers.Marker1.Btn"
 51 [-]: GETGLOBAL R3 K2        ; R3 := 0xae91e43b
 52 [-]: SELF      R3 R3 K10    ; R4 := R3; R3 := R3[0x67bc869f]
 53 [-]: MOVE      R5 R2        ; R5 := R2
 54 [-]: CONST     R6 5         ; R6 := 5.000000
 55 [-]: MOVE      R7 R1        ; R7 := R1
 56 [-]: CALL      R3 5 1       ; R3(R4,R5,R6,R7)
 57 [-]: GETGLOBAL R3 K2        ; R3 := 0xae91e43b
 58 [-]: SELF      R3 R3 K10    ; R4 := R3; R3 := R3[0x67bc869f]
 59 [-]: MOVE      R5 R2        ; R5 := R2
 60 [-]: CONST     R6 6         ; R6 := 6.000000
 61 [-]: MOVE      R7 R1        ; R7 := R1
 62 [-]: CALL      R3 5 1       ; R3(R4,R5,R6,R7)
 63 [-]: GETGLOBAL R3 K2        ; R3 := 0xae91e43b
 64 [-]: SELF      R3 R3 K14    ; R4 := R3; R3 := R3[0xf64b7262]
 65 [-]: LOADK     R5 K15       ; R5 := "MiniMapContainer.MiniMapMarkers.Marker1"
 66 [-]: LOADK     R6 K16       ; R6 := "Btn"
 67 [-]: CONST     R7 12        ; R7 := 12.000000
 68 [-]: MOVE      R8 R1        ; R8 := R1
 69 [-]: CALL      R3 6 1       ; R3(R4,R5,R6,R7,R8)
 70 [-]: GETGLOBAL R3 K2        ; R3 := 0xae91e43b
 71 [-]: SELF      R3 R3 K14    ; R4 := R3; R3 := R3[0xf64b7262]
 72 [-]: LOADK     R5 K15       ; R5 := "MiniMapContainer.MiniMapMarkers.Marker1"
 73 [-]: LOADK     R6 K16       ; R6 := "Btn"
 74 [-]: CONST     R7 13        ; R7 := 13.000000
 75 [-]: MOVE      R8 R1        ; R8 := R1
 76 [-]: CALL      R3 6 1       ; R3(R4,R5,R6,R7,R8)
 77 [-]: GETGLOBAL R3 K17       ; R3 := 0x2d0fad09
 78 [-]: LOADK     R4 K18       ; R4 := "Lotus.Interface.Libs.TimerMgr"
 79 [-]: CALL      R3 2 2       ; R3 := R3(R4)
 80 [-]: GETTABLE  R4 R3 K19    ; R4 := R3[0xde474187]
 81 [-]: CALL      R4 1 2       ; R4 := R4()
 82 [-]: SETUPVAL  R4 U0        ; U82 := R0
 83 [-]: GETUPVAL  R4 U2        ; R4 := U2
 84 [-]: GETTABLE  R4 R4 K20    ; R4 := R4[0xae6791ba]
 85 [-]: GETGLOBAL R5 K2        ; R5 := 0xae91e43b
 86 [-]: CALL      R4 2 2       ; R4 := R4(R5)
 87 [-]: SETUPVAL  R4 U1        ; U82 := R1
 88 [-]: GETUPVAL  R4 U1        ; R4 := U1
 89 [-]: SELF      R4 R4 K21    ; R5 := R4; R4 := R4[0x20ff29f7]
 90 [-]: GETGLOBAL R6 K2        ; R6 := 0xae91e43b
 91 [-]: LOADK     R7 K22       ; R7 := "TimeOfDay"
 92 [-]: NEWTABLE  R8 2 0       ; R8 := {}
 93 [-]: GETUPVAL  R9 U1        ; R9 := U1
 94 [-]: GETTABLE  R9 R9 K23    ; R9 := R9["ANCHOR_V_BOTTOM"]
 95 [-]: GETUPVAL  R10 U1       ; R10 := U1
 96 [-]: GETTABLE  R10 R10 K24  ; R10 := R10["ANCHOR_H_RIGHT"]
 97 [-]: SETLIST   R8 2 1       ; R8[(1-1)*FPF+i] := R(8+i), 1 <= i <= 2
 98 [-]: CALL      R4 5 1       ; R4(R5,R6,R7,R8)
 99 [-]: GETUPVAL  R4 U1        ; R4 := U1
100 [-]: SELF      R4 R4 K21    ; R5 := R4; R4 := R4[0x20ff29f7]
101 [-]: GETGLOBAL R6 K2        ; R6 := 0xae91e43b
102 [-]: LOADK     R7 K25       ; R7 := "MapHint"
103 [-]: NEWTABLE  R8 1 0       ; R8 := {}
104 [-]: GETUPVAL  R9 U1        ; R9 := U1
105 [-]: GETTABLE  R9 R9 K23    ; R9 := R9["ANCHOR_V_BOTTOM"]
106 [-]: SETLIST   R8 1 1       ; R8[(1-1)*FPF+i] := R(8+i), 1 <= i <= 1
107 [-]: CALL      R4 5 1       ; R4(R5,R6,R7,R8)
108 [-]: GETUPVAL  R4 U1        ; R4 := U1
109 [-]: SELF      R4 R4 K26    ; R5 := R4; R4 := R4[0xfaa69527]
110 [-]: GETGLOBAL R6 K2        ; R6 := 0xae91e43b
111 [-]: SELF      R6 R6 K27    ; R7 := R6; R6 := R6[0x6b837788]
112 [-]: CALL      R6 2 2       ; R6 := R6(R7)
113 [-]: GETGLOBAL R7 K2        ; R7 := 0xae91e43b
114 [-]: SELF      R7 R7 K28    ; R8 := R7; R7 := R7[0xaf9fda9f]
115 [-]: CALL      R7 2 0       ; R7,... := R7(R8)
116 [-]: CALL      R4 0 1       ; R4(R5,...)
117 [-]: GETGLOBAL R4 K2        ; R4 := 0xae91e43b
118 [-]: SELF      R4 R4 K29    ; R5 := R4; R4 := R4[0x091c120e]
119 [-]: CALL      R4 2 2       ; R4 := R4(R5)
120 [-]: SETUPVAL  R4 U3        ; U82 := R3
121 [-]: GETGLOBAL R4 K2        ; R4 := 0xae91e43b
122 [-]: SELF      R4 R4 K30    ; R5 := R4; R4 := R4[0x2cc9d281]
123 [-]: CALL      R4 2 2       ; R4 := R4(R5)
124 [-]: SETUPVAL  R4 U4        ; U82 := R4
125 [-]: GETGLOBAL R4 K2        ; R4 := 0xae91e43b
126 [-]: SELF      R4 R4 K31    ; R5 := R4; R4 := R4[0xbed40e9c]
127 [-]: LOADKB    R6 1 0       ; R6 := true
128 [-]: CALL      R4 3 1       ; R4(R5,R6)
129 [-]: GETGLOBAL R4 K2        ; R4 := 0xae91e43b
130 [-]: SELF      R4 R4 K10    ; R5 := R4; R4 := R4[0x67bc869f]
131 [-]: LOADK     R6 K32       ; R6 := "_root"
132 [-]: CONST     R7 10        ; R7 := 10.000000
133 [-]: CONST     R8 0         ; R8 := 0.000000
134 [-]: CALL      R4 5 1       ; R4(R5,R6,R7,R8)
135 [-]: GETGLOBAL R4 K2        ; R4 := 0xae91e43b
136 [-]: SELF      R4 R4 K10    ; R5 := R4; R4 := R4[0x67bc869f]
137 [-]: LOADK     R6 K32       ; R6 := "_root"
138 [-]: CONST     R7 4         ; R7 := 4.000000
139 [-]: LOADK     R8 K33       ; R8 := -15000.000000
140 [-]: CALL      R4 5 1       ; R4(R5,R6,R7,R8)
141 [-]: GETGLOBAL R4 K2        ; R4 := 0xae91e43b
142 [-]: SELF      R4 R4 K34    ; R5 := R4; R4 := R4[0xaade900e]
143 [-]: LOADK     R6 K35       ; R6 := "Reticle"
144 [-]: CONST     R7 11        ; R7 := 11.000000
145 [-]: LOADKB    R8 0 0       ; R8 := false
146 [-]: CALL      R4 5 1       ; R4(R5,R6,R7,R8)
147 [-]: GETGLOBAL R4 K2        ; R4 := 0xae91e43b
148 [-]: SELF      R4 R4 K10    ; R5 := R4; R4 := R4[0x67bc869f]
149 [-]: LOADK     R6 K22       ; R6 := "TimeOfDay"
150 [-]: CONST     R7 10        ; R7 := 10.000000
151 [-]: CONST     R8 0         ; R8 := 0.000000
152 [-]: CALL      R4 5 1       ; R4(R5,R6,R7,R8)
153 [-]: GETGLOBAL R4 K2        ; R4 := 0xae91e43b
154 [-]: SELF      R4 R4 K10    ; R5 := R4; R4 := R4[0x67bc869f]
155 [-]: LOADK     R6 K36       ; R6 := "Blurer"
156 [-]: CONST     R7 10        ; R7 := 10.000000
157 [-]: CONST     R8 0         ; R8 := 0.000000
158 [-]: CALL      R4 5 1       ; R4(R5,R6,R7,R8)
159 [-]: GETUPVAL  R4 U5        ; R4 := U5
160 [-]: CALL      R4 1 1       ; R4()
161 [-]: GETUPVAL  R4 U6        ; R4 := U6
162 [-]: CALL      R4 1 1       ; R4()
163 [-]: GETUPVAL  R4 U7        ; R4 := U7
164 [-]: GETUPVAL  R5 U8        ; R5 := U8
165 [-]: GETTABLE  R5 R5 K37    ; R5 := R5["IsVisible"]
166 [-]: CALL      R4 2 1       ; R4(R5)
167 [-]: GETGLOBAL R4 K2        ; R4 := 0xae91e43b
168 [-]: SELF      R4 R4 K10    ; R5 := R4; R4 := R4[0x67bc869f]
169 [-]: LOADK     R6 K15       ; R6 := "MiniMapContainer.MiniMapMarkers.Marker1"
170 [-]: CONST     R7 10        ; R7 := 10.000000
171 [-]: CONST     R8 0         ; R8 := 0.000000
172 [-]: CALL      R4 5 1       ; R4(R5,R6,R7,R8)
173 [-]: GETGLOBAL R4 K2        ; R4 := 0xae91e43b
174 [-]: SELF      R4 R4 K10    ; R5 := R4; R4 := R4[0x67bc869f]
175 [-]: LOADK     R6 K12       ; R6 := "MiniMapOverlayMsg"
176 [-]: CONST     R7 10        ; R7 := 10.000000
177 [-]: CONST     R8 0         ; R8 := 0.000000
178 [-]: CALL      R4 5 1       ; R4(R5,R6,R7,R8)
179 [-]: GETGLOBAL R4 K2        ; R4 := 0xae91e43b
180 [-]: SELF      R4 R4 K38    ; R5 := R4; R4 := R4[0xd5181643]
181 [-]: LOADK     R6 K39       ; R6 := "MiniMapOverlayMsg.Bg"
182 [-]: GETGLOBAL R7 K40       ; R7 := 0x0032441c
183 [-]: GETTABLE  R7 R7 K41    ; R7 := R7["UIMaterial_RectangleNoDepth"]
184 [-]: CALL      R4 4 1       ; R4(R5,R6,R7)
185 [-]: GETGLOBAL R4 K2        ; R4 := 0xae91e43b
186 [-]: SELF      R4 R4 K42    ; R5 := R4; R4 := R4[0x91e13703]
187 [-]: LOADK     R6 K39       ; R6 := "MiniMapOverlayMsg.Bg"
188 [-]: LOADK     R7 K43       ; R7 := "RectInnerColor"
189 [-]: GETGLOBAL R8 K40       ; R8 := 0x0032441c
190 [-]: GETTABLE  R8 R8 K44    ; R8 := R8["UIColorObject_Black"]
191 [-]: GETTABLE  R8 R8 K45    ; R8 := R8["r"]
192 [-]: GETGLOBAL R9 K40       ; R9 := 0x0032441c
193 [-]: GETTABLE  R9 R9 K44    ; R9 := R9["UIColorObject_Black"]
194 [-]: GETTABLE  R9 R9 K46    ; R9 := R9["g"]
195 [-]: GETGLOBAL R10 K40      ; R10 := 0x0032441c
196 [-]: GETTABLE  R10 R10 K44  ; R10 := R10["UIColorObject_Black"]
197 [-]: GETTABLE  R10 R10 K47  ; R10 := R10["b"]
198 [-]: LOADK     R11 K48      ; R11 := 0.400000
199 [-]: CALL      R4 8 1       ; R4(R5,R6,R7,R8,R9,R10,R11)
200 [-]: GETGLOBAL R4 K2        ; R4 := 0xae91e43b
201 [-]: SELF      R4 R4 K42    ; R5 := R4; R4 := R4[0x91e13703]
202 [-]: LOADK     R6 K39       ; R6 := "MiniMapOverlayMsg.Bg"
203 [-]: LOADK     R7 K49       ; R7 := "RectEdgeColor"
204 [-]: GETGLOBAL R8 K40       ; R8 := 0x0032441c
205 [-]: GETTABLE  R8 R8 K44    ; R8 := R8["UIColorObject_Black"]
206 [-]: GETTABLE  R8 R8 K45    ; R8 := R8["r"]
207 [-]: GETGLOBAL R9 K40       ; R9 := 0x0032441c
208 [-]: GETTABLE  R9 R9 K44    ; R9 := R9["UIColorObject_Black"]
209 [-]: GETTABLE  R9 R9 K46    ; R9 := R9["g"]
210 [-]: GETGLOBAL R10 K40      ; R10 := 0x0032441c
211 [-]: GETTABLE  R10 R10 K44  ; R10 := R10["UIColorObject_Black"]
212 [-]: GETTABLE  R10 R10 K47  ; R10 := R10["b"]
213 [-]: LOADK     R11 K48      ; R11 := 0.400000
214 [-]: CALL      R4 8 1       ; R4(R5,R6,R7,R8,R9,R10,R11)
215 [-]: GETGLOBAL R4 K2        ; R4 := 0xae91e43b
216 [-]: SELF      R4 R4 K50    ; R5 := R4; R4 := R4[0x20b98db3]
217 [-]: LOADK     R6 K51       ; R6 := "MiniMapOverlayMsg.Label.text"
218 [-]: LOADK     R7 K52       ; R7 := "/Lotus/Language/SystemMessages/MapJammed"
219 [-]: CALL      R4 4 1       ; R4(R5,R6,R7)
220 [-]: GETGLOBAL R4 K2        ; R4 := 0xae91e43b
221 [-]: SELF      R4 R4 K53    ; R5 := R4; R4 := R4[0x91a24e4b]
222 [-]: LOADK     R6 K54       ; R6 := "MiniMapOverlayMsg.Label"
223 [-]: CONST     R7 33        ; R7 := 33.000000
224 [-]: CALL      R4 4 2       ; R4 := R4(R5,R6,R7)
225 [-]: GETGLOBAL R5 K2        ; R5 := 0xae91e43b
226 [-]: SELF      R5 R5 K10    ; R6 := R5; R5 := R5[0x67bc869f]
227 [-]: LOADK     R7 K39       ; R7 := "MiniMapOverlayMsg.Bg"
228 [-]: CONST     R8 12        ; R8 := 12.000000
229 [-]: ADD       R9 R4 K55    ; R9 := R4 + 20.000000
230 [-]: CALL      R5 5 1       ; R5(R6,R7,R8,R9)
231 [-]: GETGLOBAL R5 K2        ; R5 := 0xae91e43b
232 [-]: SELF      R5 R5 K10    ; R6 := R5; R5 := R5[0x67bc869f]
233 [-]: LOADK     R7 K25       ; R7 := "MapHint"
234 [-]: CONST     R8 10        ; R8 := 10.000000
235 [-]: CONST     R9 0         ; R9 := 0.000000
236 [-]: CALL      R5 5 1       ; R5(R6,R7,R8,R9)
237 [-]: GETGLOBAL R5 K2        ; R5 := 0xae91e43b
238 [-]: SELF      R5 R5 K50    ; R6 := R5; R5 := R5[0x20b98db3]
239 [-]: LOADK     R7 K56       ; R7 := "MapHint.text"
240 [-]: LOADK     R8 K57       ; R8 := "/Lotus/Language/Menu/AdvancedMapHint"
241 [-]: CALL      R5 4 1       ; R5(R6,R7,R8)
242 [-]: GETGLOBAL R5 K58       ; R5 := 0x38f10e85
243 [-]: GETGLOBAL R6 K2        ; R6 := 0xae91e43b
244 [-]: LOADK     R7 K59       ; R7 := "MiniMapContainer.MiniMapMarkers.PlayerArrow.swapDepths"
245 [-]: CONST     R8 5000      ; R8 := 5000.000000
246 [-]: CALL      R5 4 1       ; R5(R6,R7,R8)
247 [-]: GETGLOBAL R5 K60       ; R5 := 0xbe190284
248 [-]: SELF      R5 R5 K61    ; R6 := R5; R5 := R5[0x5c390f04]
249 [-]: CALL      R5 2 2       ; R5 := R5(R6)
250 [-]: EQ        0 R5 K63     ; if R5 ~= 31.000000 then PC := 298
251 [-]: JMP       298          ; PC := 298
252 [-]: GETGLOBAL R5 K0        ; R5 := _T
253 [-]: GETTABLE  R5 R5 K64    ; R5 := R5["BlockTacticalMenu"]
254 [-]: TEST      R5 1         ; if R5 then PC := 298
255 [-]: JMP       298          ; PC := 298
256 [-]: GETGLOBAL R5 K6        ; R5 := 0x89326c93
257 [-]: SELF      R5 R5 K65    ; R6 := R5; R5 := R5[0x78298275]
258 [-]: CALL      R5 2 2       ; R5 := R5(R6)
259 [-]: GETGLOBAL R6 K66       ; R6 := 0x7b998233
260 [-]: MOVE      R7 R5        ; R7 := R5
261 [-]: CALL      R6 2 2       ; R6 := R6(R7)
262 [-]: TEST      R6 1         ; if R6 then PC := 298
263 [-]: JMP       298          ; PC := 298
264 [-]: SELF      R6 R5 K67    ; R7 := R5; R6 := R5[0xf7028472]
265 [-]: GETUPVAL  R8 U9        ; R8 := U9
266 [-]: GETTABLE  R8 R8 K68    ; R8 := R8["sSkillCommanderMap"]
267 [-]: CALL      R6 3 2       ; R6 := R6(R7,R8)
268 [-]: TEST      R6 0         ; if not R6 then PC := 298
269 [-]: JMP       298          ; PC := 298
270 [-]: LOADK     R7 K69       ; R7 := "<VIEW_RAILJACK_SYSTEMS>"
271 [-]: GETGLOBAL R8 K4        ; R8 := 0x34291f5c
272 [-]: GETTABLE  R8 R8 K70    ; R8 := R8[0x1467d5f4]
273 [-]: CALL      R8 1 2       ; R8 := R8()
274 [-]: TEST      R8 0         ; if not R8 then PC := 277
275 [-]: JMP       277          ; PC := 277
276 [-]: LOADK     R7 K71       ; R7 := "<POWER_MENU>+<VIEW_RAILJACK_SYSTEMS_MENU>"
277 [-]: GETGLOBAL R8 K2        ; R8 := 0xae91e43b
278 [-]: SELF      R8 R8 K50    ; R9 := R8; R8 := R8[0x20b98db3]
279 [-]: LOADK     R10 K56      ; R10 := "MapHint.text"
280 [-]: LOADK     R11 K72      ; R11 := "/Lotus/Language/Railjack/TacticalMapHint"
281 [-]: NEWTABLE  R12 0 1      ; R12 := {}
282 [-]: SETTABLE  R12 K73 R7   ; R12["CALLOUT"] := R7
283 [-]: CALL      R8 5 1       ; R8(R9,R10,R11,R12)
284 [-]: GETGLOBAL R8 K74       ; R8 := 0x25312c9b
285 [-]: GETGLOBAL R9 K2        ; R9 := 0xae91e43b
286 [-]: LOADK     R10 K25      ; R10 := "MapHint"
287 [-]: CONST     R11 8        ; R11 := 8.000000
288 [-]: NEWTABLE  R12 1 0      ; R12 := {}
289 [-]: CONST     R13 10       ; R13 := 10.000000
290 [-]: SETLIST   R12 1 1      ; R12[(1-1)*FPF+i] := R(12+i), 1 <= i <= 1
291 [-]: NEWTABLE  R13 1 0      ; R13 := {}
292 [-]: CONST     R14 70       ; R14 := 70.000000
293 [-]: SETLIST   R13 1 1      ; R13[(1-1)*FPF+i] := R(13+i), 1 <= i <= 1
294 [-]: LOADK     R14 K76      ; R14 := 0.300000
295 [-]: LOADK     R15 K76      ; R15 := 0.300000
296 [-]: CLOSURE   R16 0        ; R16 := closure(Function #23.1)
297 [-]: CALL      R8 9 1       ; R8(R9,R10,R11,R12,R13,R14,R15,R16)
298 [-]: GETUPVAL  R8 U10       ; R8 := U10
299 [-]: GETTABLE  R8 R8 K77    ; R8 := R8[0xf5b36237]
300 [-]: CALL      R8 1 2       ; R8 := R8()
301 [-]: TEST      R8 0         ; if not R8 then PC := 309
302 [-]: JMP       309          ; PC := 309
303 [-]: GETGLOBAL R8 K2        ; R8 := 0xae91e43b
304 [-]: SELF      R8 R8 K34    ; R9 := R8; R8 := R8[0xaade900e]
305 [-]: LOADK     R10 K25      ; R10 := "MapHint"
306 [-]: CONST     R11 11       ; R11 := 11.000000
307 [-]: LOADKB    R12 0 0      ; R12 := false
308 [-]: CALL      R8 5 1       ; R8(R9,R10,R11,R12)
309 [-]: GETGLOBAL R8 K60       ; R8 := 0xbe190284
310 [-]: SELF      R8 R8 K78    ; R9 := R8; R8 := R8[0xf2deaf69]
311 [-]: GETGLOBAL R10 K79      ; R10 := gLotusPhotoBoothGameRulesType
312 [-]: CALL      R8 3 2       ; R8 := R8(R9,R10)
313 [-]: SETUPVAL  R8 U11       ; U82 := R11
314 [-]: GETGLOBAL R8 K60       ; R8 := 0xbe190284
315 [-]: SELF      R8 R8 K80    ; R9 := R8; R8 := R8[0xb2cb9941]
316 [-]: CALL      R8 2 2       ; R8 := R8(R9)
317 [-]: SETUPVAL  R8 U12       ; U82 := R12
318 [-]: GETGLOBAL R8 K66       ; R8 := 0x7b998233
319 [-]: GETGLOBAL R9 K60       ; R9 := 0xbe190284
320 [-]: CALL      R8 2 2       ; R8 := R8(R9)
321 [-]: TEST      R8 1         ; if R8 then PC := 331
322 [-]: JMP       331          ; PC := 331
323 [-]: GETGLOBAL R8 K60       ; R8 := 0xbe190284
324 [-]: SELF      R8 R8 K81    ; R9 := R8; R8 := R8[0xef893aec]
325 [-]: CALL      R8 2 2       ; R8 := R8(R9)
326 [-]: GETTABLE  R8 R8 K82    ; R8 := R8["missionType"]
327 [-]: EQ        1 R8 K83     ; if R8 == 28.000000 then PC := 332
328 [-]: JMP       332          ; PC := 332
329 [-]: GETUPVAL  R8 U12       ; R8 := U12
330 [-]: JMP       333          ; PC := 333
331 [-]: LOADKB    R8 0 1       ; R8 := false; PC := 332
332 [-]: LOADKB    R8 1 0       ; R8 := true
333 [-]: SETUPVAL  R8 U13       ; U82 := R13
334 [-]: GETUPVAL  R8 U13       ; R8 := U13
335 [-]: TEST      R8 0         ; if not R8 then PC := 347
336 [-]: JMP       347          ; PC := 347
337 [-]: GETGLOBAL R8 K60       ; R8 := 0xbe190284
338 [-]: SELF      R8 R8 K81    ; R9 := R8; R8 := R8[0xef893aec]
339 [-]: CALL      R8 2 2       ; R8 := R8(R9)
340 [-]: GETTABLE  R8 R8 K84    ; R8 := R8["location"]
341 [-]: GETUPVAL  R9 U10       ; R9 := U10
342 [-]: GETTABLE  R9 R9 K85    ; R9 := R9["ZARIMAN_NODE_TAG"]
343 [-]: EQ        1 R8 R9      ; if R8 == R9 then PC := 346
344 [-]: JMP       346          ; PC := 346
345 [-]: LOADKB    R8 0 1       ; R8 := false; PC := 346
346 [-]: LOADKB    R8 1 0       ; R8 := true
347 [-]: SETUPVAL  R8 U14       ; U82 := R14
348 [-]: GETUPVAL  R8 U13       ; R8 := U13
349 [-]: TEST      R8 0         ; if not R8 then PC := 369
350 [-]: JMP       369          ; PC := 369
351 [-]: GETGLOBAL R8 K60       ; R8 := 0xbe190284
352 [-]: SELF      R8 R8 K81    ; R9 := R8; R8 := R8[0xef893aec]
353 [-]: CALL      R8 2 2       ; R8 := R8(R9)
354 [-]: GETTABLE  R8 R8 K84    ; R8 := R8["location"]
355 [-]: GETUPVAL  R9 U10       ; R9 := U10
356 [-]: GETTABLE  R9 R9 K86    ; R9 := R9["ENTRATI_LANDSCAPE_NODE_TAG"]
357 [-]: EQ        1 R8 R9      ; if R8 == R9 then PC := 368
358 [-]: JMP       368          ; PC := 368
359 [-]: GETGLOBAL R8 K60       ; R8 := 0xbe190284
360 [-]: SELF      R8 R8 K81    ; R9 := R8; R8 := R8[0xef893aec]
361 [-]: CALL      R8 2 2       ; R8 := R8(R9)
362 [-]: GETTABLE  R8 R8 K84    ; R8 := R8["location"]
363 [-]: GETUPVAL  R9 U10       ; R9 := U10
364 [-]: GETTABLE  R9 R9 K87    ; R9 := R9["OROKIN_TOWER_NODE_TAG"]
365 [-]: EQ        1 R8 R9      ; if R8 == R9 then PC := 368
366 [-]: JMP       368          ; PC := 368
367 [-]: LOADKB    R8 0 1       ; R8 := false; PC := 368
368 [-]: LOADKB    R8 1 0       ; R8 := true
369 [-]: SETUPVAL  R8 U15       ; U82 := R15
370 [-]: GETGLOBAL R8 K2        ; R8 := 0xae91e43b
371 [-]: SELF      R8 R8 K34    ; R9 := R8; R8 := R8[0xaade900e]
372 [-]: LOADK     R10 K88      ; R10 := "TimeOfDay.Hands"
373 [-]: CONST     R11 11       ; R11 := 11.000000
374 [-]: GETUPVAL  R12 U15      ; R12 := U15
375 [-]: CALL      R8 5 1       ; R8(R9,R10,R11,R12)
376 [-]: GETGLOBAL R8 K2        ; R8 := 0xae91e43b
377 [-]: SELF      R8 R8 K34    ; R9 := R8; R8 := R8[0xaade900e]
378 [-]: LOADK     R10 K89      ; R10 := "TimeOfDay.DayNight"
379 [-]: CONST     R11 11       ; R11 := 11.000000
380 [-]: GETUPVAL  R12 U14      ; R12 := U14
381 [-]: NOT       R12 R12      ; R12 :=  R12
382 [-]: CALL      R8 5 1       ; R8(R9,R10,R11,R12)
383 [-]: GETGLOBAL R8 K2        ; R8 := 0xae91e43b
384 [-]: SELF      R8 R8 K34    ; R9 := R8; R8 := R8[0xaade900e]
385 [-]: LOADK     R10 K90      ; R10 := "TimeOfDay.ZarimanCycler"
386 [-]: CONST     R11 11       ; R11 := 11.000000
387 [-]: GETUPVAL  R12 U14      ; R12 := U14
388 [-]: CALL      R8 5 1       ; R8(R9,R10,R11,R12)
389 [-]: GETUPVAL  R8 U14       ; R8 := U14
390 [-]: TEST      R8 0         ; if not R8 then PC := 441
391 [-]: JMP       441          ; PC := 441
392 [-]: GETGLOBAL R8 K2        ; R8 := 0xae91e43b
393 [-]: SELF      R8 R8 K38    ; R9 := R8; R8 := R8[0xd5181643]
394 [-]: LOADK     R10 K91      ; R10 := "TimeOfDay.ZarimanCycler.Stroke"
395 [-]: GETGLOBAL R11 K40      ; R11 := 0x0032441c
396 [-]: GETTABLE  R11 R11 K92  ; R11 := R11["UIMaterial_VerticalVisibilityRange"]
397 [-]: CALL      R8 4 1       ; R8(R9,R10,R11)
398 [-]: GETGLOBAL R8 K2        ; R8 := 0xae91e43b
399 [-]: SELF      R8 R8 K38    ; R9 := R8; R8 := R8[0xd5181643]
400 [-]: LOADK     R10 K93      ; R10 := "TimeOfDay.ZarimanCycler.Fill"
401 [-]: GETGLOBAL R11 K94      ; R11 := 0xfa600763
402 [-]: CALL      R8 4 1       ; R8(R9,R10,R11)
403 [-]: GETGLOBAL R8 K2        ; R8 := 0xae91e43b
404 [-]: SELF      R8 R8 K10    ; R9 := R8; R8 := R8[0x67bc869f]
405 [-]: LOADK     R10 K91      ; R10 := "TimeOfDay.ZarimanCycler.Stroke"
406 [-]: CONST     R11 10       ; R11 := 10.000000
407 [-]: CONST     R12 25       ; R12 := 25.000000
408 [-]: CALL      R8 5 1       ; R8(R9,R10,R11,R12)
409 [-]: GETGLOBAL R8 K2        ; R8 := 0xae91e43b
410 [-]: SELF      R8 R8 K42    ; R9 := R8; R8 := R8[0x91e13703]
411 [-]: LOADK     R10 K93      ; R10 := "TimeOfDay.ZarimanCycler.Fill"
412 [-]: LOADK     R11 K49      ; R11 := "RectEdgeColor"
413 [-]: CONST     R12 0        ; R12 := 0.000000
414 [-]: CONST     R13 0        ; R13 := 0.000000
415 [-]: CONST     R14 0        ; R14 := 0.000000
416 [-]: CONST     R15 0        ; R15 := 0.000000
417 [-]: CALL      R8 8 1       ; R8(R9,R10,R11,R12,R13,R14,R15)
418 [-]: GETGLOBAL R8 K2        ; R8 := 0xae91e43b
419 [-]: SELF      R8 R8 K42    ; R9 := R8; R8 := R8[0x91e13703]
420 [-]: LOADK     R10 K93      ; R10 := "TimeOfDay.ZarimanCycler.Fill"
421 [-]: LOADK     R11 K43      ; R11 := "RectInnerColor"
422 [-]: CONST     R12 0        ; R12 := 0.000000
423 [-]: CONST     R13 0        ; R13 := 0.000000
424 [-]: CONST     R14 0        ; R14 := 0.000000
425 [-]: CONST     R15 0        ; R15 := 0.250000
426 [-]: CALL      R8 8 1       ; R8(R9,R10,R11,R12,R13,R14,R15)
427 [-]: GETGLOBAL R8 K2        ; R8 := 0xae91e43b
428 [-]: SELF      R8 R8 K10    ; R9 := R8; R8 := R8[0x67bc869f]
429 [-]: LOADK     R10 K95      ; R10 := "TimeOfDay.Label"
430 [-]: CONST     R11 0        ; R11 := 0.000000
431 [-]: CONST     R12 -164     ; R12 := -164.000000
432 [-]: CALL      R8 5 1       ; R8(R9,R10,R11,R12)
433 [-]: GETGLOBAL R8 K2        ; R8 := 0xae91e43b
434 [-]: SELF      R8 R8 K10    ; R9 := R8; R8 := R8[0x67bc869f]
435 [-]: LOADK     R10 K95      ; R10 := "TimeOfDay.Label"
436 [-]: CONST     R11 1        ; R11 := 1.000000
437 [-]: CONST     R12 -30      ; R12 := -30.000000
438 [-]: CALL      R8 5 1       ; R8(R9,R10,R11,R12)
439 [-]: GETUPVAL  R8 U16       ; R8 := U16
440 [-]: CALL      R8 1 1       ; R8()
441 [-]: LOADKB    R8 1 0       ; R8 := true
442 [-]: SETUPVAL  R8 U17       ; U82 := R17
443 [-]: RETURN    R0 1         ; return 


; Function #23.1:
;
; Name:            
; Defined at line: 573
; #Upvalues:       0
; #Parameters:     0
; Is_vararg:       0
; Max Stack Size:  8

  1 [-]: GETGLOBAL R0 K0        ; R0 := 0x25312c9b
  2 [-]: GETGLOBAL R1 K1        ; R1 := 0xae91e43b
  3 [-]: LOADK     R2 K2        ; R2 := "MapHint"
  4 [-]: CONST     R3 8         ; R3 := 8.000000
  5 [-]: NEWTABLE  R4 1 0       ; R4 := {}
  6 [-]: CONST     R5 10        ; R5 := 10.000000
  7 [-]: SETLIST   R4 1 1       ; R4[(1-1)*FPF+i] := R(4+i), 1 <= i <= 1
  8 [-]: NEWTABLE  R5 1 0       ; R5 := {}
  9 [-]: CONST     R6 0         ; R6 := 0.000000
 10 [-]: SETLIST   R5 1 1       ; R5[(1-1)*FPF+i] := R(5+i), 1 <= i <= 1
 11 [-]: LOADK     R6 K4        ; R6 := 0.300000
 12 [-]: CONST     R7 3         ; R7 := 3.000000
 13 [-]: CALL      R0 8 1       ; R0(R1,R2,R3,R4,R5,R6,R7)
 14 [-]: RETURN    R0 1         ; return 


; Function #24:
;
; Name:            
; Defined at line: 610
; #Upvalues:       10
; #Parameters:     1
; Is_vararg:       0
; Max Stack Size:  11

  1 [-]: LOADKB    R1 1 0       ; R1 := true
  2 [-]: SETUPVAL  R1 U0        ; U82 := R0
  3 [-]: GETGLOBAL R1 K0        ; R1 := _T
  4 [-]: SETTABLE  R1 K1 K2     ; R1["gToolTip"] := nil
  5 [-]: GETGLOBAL R1 K0        ; R1 := _T
  6 [-]: SETTABLE  R1 K3 K4     ; R1["OverlayMapVisible"] := false
  7 [-]: GETUPVAL  R1 U1        ; R1 := U1
  8 [-]: CALL      R1 1 1       ; R1()
  9 [-]: GETUPVAL  R1 U2        ; R1 := U2
 10 [-]: TEST      R1 0         ; if not R1 then PC := 27
 11 [-]: JMP       27           ; PC := 27
 12 [-]: GETUPVAL  R1 U3        ; R1 := U3
 13 [-]: GETTABLE  R1 R1 K5     ; R1 := R1[0x659d451f]
 14 [-]: GETGLOBAL R2 K6        ; R2 := 0x095f7ad3
 15 [-]: CALL      R1 2 1       ; R1(R2)
 16 [-]: GETGLOBAL R1 K7        ; R1 := 0xae91e43b
 17 [-]: SELF      R1 R1 K8     ; R2 := R1; R1 := R1[0xbed40e9c]
 18 [-]: LOADKB    R3 1 0       ; R3 := true
 19 [-]: CALL      R1 3 1       ; R1(R2,R3)
 20 [-]: GETUPVAL  R1 U4        ; R1 := U4
 21 [-]: SELF      R1 R1 K9     ; R2 := R1; R1 := R1[0xf5fc319f]
 22 [-]: CALL      R1 2 1       ; R1(R2)
 23 [-]: GETUPVAL  R1 U4        ; R1 := U4
 24 [-]: SELF      R1 R1 K10    ; R2 := R1; R1 := R1[0x76b07564]
 25 [-]: LOADKB    R3 0 0       ; R3 := false
 26 [-]: CALL      R1 3 1       ; R1(R2,R3)
 27 [-]: LOADKB    R1 0 0       ; R1 := false
 28 [-]: SETUPVAL  R1 U2        ; U82 := R2
 29 [-]: GETUPVAL  R1 U5        ; R1 := U5
 30 [-]: EQ        1 R1 K2      ; if R1 == nil then PC := 46
 31 [-]: JMP       46           ; PC := 46
 32 [-]: GETGLOBAL R1 K11       ; R1 := 0xbe190284
 33 [-]: SELF      R1 R1 K12    ; R2 := R1; R1 := R1[0x33307f92]
 34 [-]: CALL      R1 2 2       ; R1 := R1(R2)
 35 [-]: GETGLOBAL R2 K13       ; R2 := 0x7b998233
 36 [-]: MOVE      R3 R1        ; R3 := R1
 37 [-]: CALL      R2 2 2       ; R2 := R2(R3)
 38 [-]: TEST      R2 1         ; if R2 then PC := 46
 39 [-]: JMP       46           ; PC := 46
 40 [-]: SELF      R2 R1 K14    ; R3 := R1; R2 := R1[0xaade900e]
 41 [-]: LOADK     R4 K15       ; R4 := "_root"
 42 [-]: CONST     R5 11        ; R5 := 11.000000
 43 [-]: GETUPVAL  R6 U5        ; R6 := U5
 44 [-]: CALL      R2 5 2       ; R2 := R2(R3,R4,R5,R6)
 45 [-]: SETUPVAL  R2 U5        ; U82 := R5
 46 [-]: GETGLOBAL R2 K13       ; R2 := 0x7b998233
 47 [-]: GETUPVAL  R3 U4        ; R3 := U4
 48 [-]: CALL      R2 2 2       ; R2 := R2(R3)
 49 [-]: TEST      R2 1         ; if R2 then PC := 63
 50 [-]: JMP       63           ; PC := 63
 51 [-]: GETUPVAL  R2 U4        ; R2 := U4
 52 [-]: SELF      R2 R2 K16    ; R3 := R2; R2 := R2[0xbf5bcc4a]
 53 [-]: LOADKB    R4 0 0       ; R4 := false
 54 [-]: CALL      R2 3 1       ; R2(R3,R4)
 55 [-]: GETUPVAL  R2 U4        ; R2 := U4
 56 [-]: SELF      R2 R2 K17    ; R3 := R2; R2 := R2[0x8f83a362]
 57 [-]: LOADKB    R4 0 0       ; R4 := false
 58 [-]: CALL      R2 3 1       ; R2(R3,R4)
 59 [-]: GETUPVAL  R2 U4        ; R2 := U4
 60 [-]: SELF      R2 R2 K18    ; R3 := R2; R2 := R2[0xc256d7cf]
 61 [-]: LOADKB    R4 0 0       ; R4 := false
 62 [-]: CALL      R2 3 1       ; R2(R3,R4)
 63 [-]: LOADKB    R2 1 0       ; R2 := true
 64 [-]: SETUPVAL  R2 U6        ; U82 := R6
 65 [-]: LOADKB    R2 0 0       ; R2 := false
 66 [-]: SETUPVAL  R2 U7        ; U82 := R7
 67 [-]: GETGLOBAL R2 K13       ; R2 := 0x7b998233
 68 [-]: GETUPVAL  R3 U8        ; R3 := U8
 69 [-]: CALL      R2 2 2       ; R2 := R2(R3)
 70 [-]: TEST      R2 1         ; if R2 then PC := 76
 71 [-]: JMP       76           ; PC := 76
 72 [-]: GETUPVAL  R2 U8        ; R2 := U8
 73 [-]: SELF      R2 R2 K19    ; R3 := R2; R2 := R2[0xa8abe17c]
 74 [-]: LOADKB    R4 1 0       ; R4 := true
 75 [-]: CALL      R2 3 1       ; R2(R3,R4)
 76 [-]: GETGLOBAL R2 K7        ; R2 := 0xae91e43b
 77 [-]: SELF      R2 R2 K20    ; R3 := R2; R2 := R2[0xaf5300dc]
 78 [-]: LOADK     R4 K15       ; R4 := "_root"
 79 [-]: CALL      R2 3 1       ; R2(R3,R4)
 80 [-]: GETGLOBAL R2 K21       ; R2 := 0x25312c9b
 81 [-]: GETGLOBAL R3 K7        ; R3 := 0xae91e43b
 82 [-]: LOADK     R4 K15       ; R4 := "_root"
 83 [-]: CONST     R5 2         ; R5 := 2.000000
 84 [-]: NEWTABLE  R6 2 0       ; R6 := {}
 85 [-]: CONST     R7 10        ; R7 := 10.000000
 86 [-]: CONST     R8 4         ; R8 := 4.000000
 87 [-]: SETLIST   R6 2 1       ; R6[(1-1)*FPF+i] := R(6+i), 1 <= i <= 2
 88 [-]: NEWTABLE  R7 2 0       ; R7 := {}
 89 [-]: CONST     R8 0         ; R8 := 0.000000
 90 [-]: LOADK     R9 K23       ; R9 := -15000.000000
 91 [-]: SETLIST   R7 2 1       ; R7[(1-1)*FPF+i] := R(7+i), 1 <= i <= 2
 92 [-]: LOADK     R8 K24       ; R8 := 0.350000
 93 [-]: CONST     R9 0         ; R9 := 0.000000
 94 [-]: CLOSURE   R10 0        ; R10 := closure(Function #24.1)
 95 [-]: GETUPVAL  R0 U9        ; R0 := U9
 96 [-]: MOVE      R0 R0        ; R0 := R0
 97 [-]: CALL      R2 9 1       ; R2(R3,R4,R5,R6,R7,R8,R9,R10)
 98 [-]: RETURN    R0 1         ; return 


; Function #24.1:
;
; Name:            
; Defined at line: 645
; #Upvalues:       2
; #Parameters:     0
; Is_vararg:       0
; Max Stack Size:  2

  1 [-]: GETUPVAL  R0 U1        ; R0 := U1
  2 [-]: SETUPVAL  R0 U0        ; U82 := R0
  3 [-]: RETURN    R0 1         ; return 


; Function #25:
;
; Name:            
; Defined at line: 650
; #Upvalues:       1
; #Parameters:     0
; Is_vararg:       0
; Max Stack Size:  3

  1 [-]: GETGLOBAL R0 K0        ; R0 := 0x34291f5c
  2 [-]: GETTABLE  R0 R0 K1     ; R0 := R0[0xe6b41adb]
  3 [-]: CALL      R0 1 2       ; R0 := R0()
  4 [-]: TEST      R0 0         ; if not R0 then PC := 12
  5 [-]: JMP       12           ; PC := 12
  6 [-]: GETGLOBAL R0 K2        ; R0 := 0x89326c93
  7 [-]: SELF      R0 R0 K3     ; R1 := R0; R0 := R0[0xfb64e76c]
  8 [-]: CALL      R0 2 2       ; R0 := R0(R1)
  9 [-]: SELF      R0 R0 K4     ; R1 := R0; R0 := R0[0x97c4ff93]
 10 [-]: LOADKB    R2 0 0       ; R2 := false
 11 [-]: CALL      R0 3 1       ; R0(R1,R2)
 12 [-]: GETUPVAL  R0 U0        ; R0 := U0
 13 [-]: LOADKB    R1 1 0       ; R1 := true
 14 [-]: CALL      R0 2 1       ; R0(R1)
 15 [-]: RETURN    R0 1         ; return 


; Function #26:
;
; Name:            
; Defined at line: 657
; #Upvalues:       2
; #Parameters:     0
; Is_vararg:       0
; Max Stack Size:  2

  1 [-]: GETUPVAL  R0 U0        ; R0 := U0
  2 [-]: GETUPVAL  R1 U1        ; R1 := U1
  3 [-]: EQ        1 R1 K0      ; if R1 == true then PC := 9
  4 [-]: JMP       9            ; PC := 9
  5 [-]: GETGLOBAL R1 K1        ; R1 := _T
  6 [-]: GETTABLE  R1 R1 K2     ; R1 := R1["HubShowRoomActive"]
  7 [-]: JMP       10           ; PC := 10
  8 [-]: LOADKB    R1 0 1       ; R1 := false; PC := 9
  9 [-]: LOADKB    R1 1 0       ; R1 := true
 10 [-]: CALL      R0 2 1       ; R0(R1)
 11 [-]: RETURN    R0 1         ; return 


; Function #27:
;
; Name:            
; Defined at line: 661
; #Upvalues:       3
; #Parameters:     0
; Is_vararg:       0
; Max Stack Size:  2

  1 [-]: GETUPVAL  R0 U0        ; R0 := U0
  2 [-]: TEST      R0 1         ; if R0 then PC := 8
  3 [-]: JMP       8            ; PC := 8
  4 [-]: GETGLOBAL R0 K0        ; R0 := _T
  5 [-]: GETTABLE  R0 R0 K1     ; R0 := R0["HubShowRoomActive"]
  6 [-]: TEST      R0 0         ; if not R0 then PC := 12
  7 [-]: JMP       12           ; PC := 12
  8 [-]: GETUPVAL  R0 U1        ; R0 := U1
  9 [-]: LOADKB    R1 1 0       ; R1 := true
 10 [-]: CALL      R0 2 1       ; R0(R1)
 11 [-]: JMP       14           ; PC := 14
 12 [-]: GETUPVAL  R0 U2        ; R0 := U2
 13 [-]: CALL      R0 1 1       ; R0()
 14 [-]: RETURN    R0 1         ; return 


; Function #28:
;
; Name:            
; Defined at line: 669
; #Upvalues:       3
; #Parameters:     0
; Is_vararg:       0
; Max Stack Size:  6

  1 [-]: NEWTABLE  R0 0 0       ; R0 := {}
  2 [-]: GETUPVAL  R1 U0        ; R1 := U0
  3 [-]: TEST      R1 1         ; if R1 then PC := 44
  4 [-]: JMP       44           ; PC := 44
  5 [-]: GETUPVAL  R1 U1        ; R1 := U1
  6 [-]: TEST      R1 0         ; if not R1 then PC := 44
  7 [-]: JMP       44           ; PC := 44
  8 [-]: GETGLOBAL R1 K0        ; R1 := 0x34291f5c
  9 [-]: GETTABLE  R1 R1 K1     ; R1 := R1[0x1467d5f4]
 10 [-]: CALL      R1 1 2       ; R1 := R1()
 11 [-]: TEST      R1 0         ; if not R1 then PC := 34
 12 [-]: JMP       34           ; PC := 34
 13 [-]: GETGLOBAL R1 K2        ; R1 := 0x33bdd652
 14 [-]: GETTABLE  R1 R1 K3     ; R1 := R1[0x23d5322f]
 15 [-]: MOVE      R2 R0        ; R2 := R0
 16 [-]: NEWTABLE  R3 0 2       ; R3 := {}
 17 [-]: SETTABLE  R3 K4 K5     ; R3["Label"] := "/Lotus/Language/Menu/Pan"
 18 [-]: SETTABLE  R3 K6 K7     ; R3["CallOut"] := "MENU_X"
 19 [-]: CALL      R1 3 1       ; R1(R2,R3)
 20 [-]: GETGLOBAL R1 K2        ; R1 := 0x33bdd652
 21 [-]: GETTABLE  R1 R1 K3     ; R1 := R1[0x23d5322f]
 22 [-]: MOVE      R2 R0        ; R2 := R0
 23 [-]: NEWTABLE  R3 0 2       ; R3 := {}
 24 [-]: SETTABLE  R3 K4 K8     ; R3["Label"] := "/Lotus/Language/Menu/Zoom"
 25 [-]: SETTABLE  R3 K6 K9     ; R3["CallOut"] := "MENU_RIGHT_X"
 26 [-]: CALL      R1 3 1       ; R1(R2,R3)
 27 [-]: GETGLOBAL R1 K2        ; R1 := 0x33bdd652
 28 [-]: GETTABLE  R1 R1 K3     ; R1 := R1[0x23d5322f]
 29 [-]: MOVE      R2 R0        ; R2 := R0
 30 [-]: NEWTABLE  R3 0 2       ; R3 := {}
 31 [-]: SETTABLE  R3 K4 K10    ; R3["Label"] := "/Lotus/Language/Menu/MapMarkerWaypoint"
 32 [-]: SETTABLE  R3 K6 K11    ; R3["CallOut"] := "MENU_GENERIC1"
 33 [-]: CALL      R1 3 1       ; R1(R2,R3)
 34 [-]: GETGLOBAL R1 K2        ; R1 := 0x33bdd652
 35 [-]: GETTABLE  R1 R1 K3     ; R1 := R1[0x23d5322f]
 36 [-]: MOVE      R2 R0        ; R2 := R0
 37 [-]: NEWTABLE  R3 0 3       ; R3 := {}
 38 [-]: SETTABLE  R3 K4 K12    ; R3["Label"] := "/Lotus/Language/Menu/Exit"
 39 [-]: CLOSURE   R4 0         ; R4 := closure(Function #28.1)
 40 [-]: GETUPVAL  R0 U2        ; R0 := U2
 41 [-]: SETTABLE  R3 K13 R4    ; R3["CallBack"] := R4
 42 [-]: SETTABLE  R3 K6 K14    ; R3["CallOut"] := "MENU_CANCEL"
 43 [-]: CALL      R1 3 1       ; R1(R2,R3)
 44 [-]: GETGLOBAL R1 K15       ; R1 := 0x7b998233
 45 [-]: GETGLOBAL R2 K16       ; R2 := _T
 46 [-]: GETTABLE  R2 R2 K17    ; R2 := R2["SetButtons"]
 47 [-]: CALL      R1 2 2       ; R1 := R1(R2)
 48 [-]: TEST      R1 1         ; if R1 then PC := 58
 49 [-]: JMP       58           ; PC := 58
 50 [-]: GETGLOBAL R1 K16       ; R1 := _T
 51 [-]: GETTABLE  R1 R1 K18    ; R1 := R1[0x1c5b546f]
 52 [-]: GETGLOBAL R2 K19       ; R2 := 0xae91e43b
 53 [-]: MOVE      R3 R0        ; R3 := R0
 54 [-]: GETGLOBAL R4 K20       ; R4 := 0xcd0165a3
 55 [-]: CONST     R5 1         ; R5 := 1.000000
 56 [-]: CALL      R4 2 0       ; R4,... := R4(R5)
 57 [-]: CALL      R1 0 1       ; R1(R2,...)
 58 [-]: RETURN    R0 1         ; return 


; Function #28.1:
;
; Name:            
; Defined at line: 677
; #Upvalues:       1
; #Parameters:     0
; Is_vararg:       0
; Max Stack Size:  2

  1 [-]: GETUPVAL  R0 U0        ; R0 := U0
  2 [-]: LOADKB    R1 1 0       ; R1 := true
  3 [-]: CALL      R0 2 1       ; R0(R1)
  4 [-]: RETURN    R0 1         ; return 


; Function #29:
;
; Name:            
; Defined at line: 684
; #Upvalues:       15
; #Parameters:     0
; Is_vararg:       0
; Max Stack Size:  14

  1 [-]: GETGLOBAL R0 K0        ; R0 := 0xae91e43b
  2 [-]: SELF      R0 R0 K1     ; R1 := R0; R0 := R0[0xbed40e9c]
  3 [-]: GETUPVAL  R2 U0        ; R2 := U0
  4 [-]: NOT       R2 R2        ; R2 :=  R2
  5 [-]: CALL      R0 3 1       ; R0(R1,R2)
  6 [-]: GETUPVAL  R0 U1        ; R0 := U1
  7 [-]: CALL      R0 1 1       ; R0()
  8 [-]: GETUPVAL  R0 U0        ; R0 := U0
  9 [-]: TEST      R0 0         ; if not R0 then PC := 100
 10 [-]: JMP       100          ; PC := 100
 11 [-]: GETGLOBAL R0 K2        ; R0 := 0x3d106989
 12 [-]: LOADK     R1 K3        ; R1 := "Map opened in advanced mode"
 13 [-]: CALL      R0 2 1       ; R0(R1)
 14 [-]: GETGLOBAL R0 K4        ; R0 := 0x7b998233
 15 [-]: GETGLOBAL R1 K5        ; R1 := 0x89326c93
 16 [-]: CALL      R0 2 2       ; R0 := R0(R1)
 17 [-]: TEST      R0 1         ; if R0 then PC := 30
 18 [-]: JMP       30           ; PC := 30
 19 [-]: GETGLOBAL R0 K5        ; R0 := 0x89326c93
 20 [-]: SELF      R0 R0 K6     ; R1 := R0; R0 := R0[0xfb64e76c]
 21 [-]: CALL      R0 2 2       ; R0 := R0(R1)
 22 [-]: GETGLOBAL R1 K4        ; R1 := 0x7b998233
 23 [-]: MOVE      R2 R0        ; R2 := R0
 24 [-]: CALL      R1 2 2       ; R1 := R1(R2)
 25 [-]: TEST      R1 1         ; if R1 then PC := 30
 26 [-]: JMP       30           ; PC := 30
 27 [-]: SELF      R1 R0 K7     ; R2 := R0; R1 := R0[0x6d7bfacb]
 28 [-]: CALL      R1 2 2       ; R1 := R1(R2)
 29 [-]: SETUPVAL  R1 U2        ; U82 := R2
 30 [-]: GETUPVAL  R1 U2        ; R1 := U2
 31 [-]: SELF      R1 R1 K8     ; R2 := R1; R1 := R1[0xa8abe17c]
 32 [-]: LOADKB    R3 0 0       ; R3 := false
 33 [-]: CALL      R1 3 1       ; R1(R2,R3)
 34 [-]: GETGLOBAL R1 K9        ; R1 := 0x34291f5c
 35 [-]: GETTABLE  R1 R1 K10    ; R1 := R1[0x1467d5f4]
 36 [-]: CALL      R1 1 2       ; R1 := R1()
 37 [-]: GETUPVAL  R2 U3        ; R2 := U3
 38 [-]: MOVE      R3 R1        ; R3 := R1
 39 [-]: CALL      R2 2 1       ; R2(R3)
 40 [-]: GETGLOBAL R2 K4        ; R2 := 0x7b998233
 41 [-]: GETUPVAL  R3 U4        ; R3 := U4
 42 [-]: CALL      R2 2 2       ; R2 := R2(R3)
 43 [-]: TEST      R2 1         ; if R2 then PC := 47
 44 [-]: JMP       47           ; PC := 47
 45 [-]: GETUPVAL  R2 U5        ; R2 := U5
 46 [-]: CALL      R2 1 1       ; R2()
 47 [-]: GETGLOBAL R2 K11       ; R2 := 0x2d0fad09
 48 [-]: LOADK     R3 K12       ; R3 := "EE.Interface.Components.DragScroll"
 49 [-]: CALL      R2 2 2       ; R2 := R2(R3)
 50 [-]: GETTABLE  R3 R2 K13    ; R3 := R2[0xae6791ba]
 51 [-]: GETGLOBAL R4 K0        ; R4 := 0xae91e43b
 52 [-]: LOADK     R5 K14       ; R5 := "Board"
 53 [-]: CONST     R6 -500      ; R6 := -500.000000
 54 [-]: CONST     R7 -500      ; R7 := -500.000000
 55 [-]: CONST     R8 500       ; R8 := 500.000000
 56 [-]: CONST     R9 500       ; R9 := 500.000000
 57 [-]: CALL      R3 7 2       ; R3 := R3(R4,R5,R6,R7,R8,R9)
 58 [-]: SETUPVAL  R3 U6        ; U82 := R6
 59 [-]: GETUPVAL  R3 U7        ; R3 := U7
 60 [-]: CALL      R3 1 1       ; R3()
 61 [-]: GETUPVAL  R3 U8        ; R3 := U8
 62 [-]: EQ        0 R3 K15     ; if R3 ~= nil then PC := 82
 63 [-]: JMP       82           ; PC := 82
 64 [-]: GETGLOBAL R3 K16       ; R3 := 0xbe190284
 65 [-]: SELF      R3 R3 K17    ; R4 := R3; R3 := R3[0x33307f92]
 66 [-]: CALL      R3 2 2       ; R3 := R3(R4)
 67 [-]: GETGLOBAL R4 K4        ; R4 := 0x7b998233
 68 [-]: MOVE      R5 R3        ; R5 := R3
 69 [-]: CALL      R4 2 2       ; R4 := R4(R5)
 70 [-]: TEST      R4 1         ; if R4 then PC := 82
 71 [-]: JMP       82           ; PC := 82
 72 [-]: SELF      R4 R3 K18    ; R5 := R3; R4 := R3[0x5b0290d2]
 73 [-]: LOADK     R6 K19       ; R6 := "_root"
 74 [-]: CONST     R7 11        ; R7 := 11.000000
 75 [-]: CALL      R4 4 2       ; R4 := R4(R5,R6,R7)
 76 [-]: SETUPVAL  R4 U8        ; U82 := R8
 77 [-]: SELF      R4 R3 K20    ; R5 := R3; R4 := R3[0xaade900e]
 78 [-]: LOADK     R6 K19       ; R6 := "_root"
 79 [-]: CONST     R7 11        ; R7 := 11.000000
 80 [-]: LOADKB    R8 0 0       ; R8 := false
 81 [-]: CALL      R4 5 1       ; R4(R5,R6,R7,R8)
 82 [-]: GETGLOBAL R4 K0        ; R4 := 0xae91e43b
 83 [-]: SELF      R4 R4 K21    ; R5 := R4; R4 := R4[0xaf5300dc]
 84 [-]: LOADK     R6 K22       ; R6 := "MapHint"
 85 [-]: CALL      R4 3 1       ; R4(R5,R6)
 86 [-]: GETGLOBAL R4 K23       ; R4 := 0x25312c9b
 87 [-]: GETGLOBAL R5 K0        ; R5 := 0xae91e43b
 88 [-]: LOADK     R6 K22       ; R6 := "MapHint"
 89 [-]: CONST     R7 8         ; R7 := 8.000000
 90 [-]: NEWTABLE  R8 1 0       ; R8 := {}
 91 [-]: CONST     R9 10        ; R9 := 10.000000
 92 [-]: SETLIST   R8 1 1       ; R8[(1-1)*FPF+i] := R(8+i), 1 <= i <= 1
 93 [-]: NEWTABLE  R9 1 0       ; R9 := {}
 94 [-]: CONST     R10 0        ; R10 := 0.000000
 95 [-]: SETLIST   R9 1 1       ; R9[(1-1)*FPF+i] := R(9+i), 1 <= i <= 1
 96 [-]: LOADK     R10 K25      ; R10 := 0.300000
 97 [-]: CALL      R4 7 1       ; R4(R5,R6,R7,R8,R9,R10)
 98 [-]: GETUPVAL  R4 U9        ; R4 := U9
 99 [-]: CALL      R4 1 1       ; R4()
100 [-]: GETGLOBAL R4 K0        ; R4 := 0xae91e43b
101 [-]: SELF      R4 R4 K20    ; R5 := R4; R4 := R4[0xaade900e]
102 [-]: LOADK     R6 K26       ; R6 := "Reticle"
103 [-]: CONST     R7 11        ; R7 := 11.000000
104 [-]: GETUPVAL  R8 U0        ; R8 := U0
105 [-]: TEST      R8 0         ; if not R8 then PC := 109
106 [-]: JMP       109          ; PC := 109
107 [-]: GETUPVAL  R8 U10       ; R8 := U10
108 [-]: GETTABLE  R8 R8 K27    ; R8 := R8["IsVisible"]
109 [-]: CALL      R4 5 1       ; R4(R5,R6,R7,R8)
110 [-]: GETGLOBAL R4 K28       ; R4 := 0x7f5022cf
111 [-]: GETTABLE  R4 R4 K29    ; R4 := R4[0xa5c556b9]
112 [-]: GETGLOBAL R5 K5        ; R5 := 0x89326c93
113 [-]: SELF      R5 R5 K30    ; R6 := R5; R5 := R5[0xca9ea368]
114 [-]: CALL      R5 2 2       ; R5 := R5(R6)
115 [-]: SELF      R5 R5 K31    ; R6 := R5; R5 := R5[0xed4e0128]
116 [-]: CALL      R5 2 2       ; R5 := R5(R6)
117 [-]: LOADK     R6 K32       ; R6 := "DuviriLandscape"
118 [-]: CALL      R4 3 2       ; R4 := R4(R5,R6)
119 [-]: EQ        1 R4 K15     ; if R4 == nil then PC := 122
120 [-]: JMP       122          ; PC := 122
121 [-]: LOADKB    R4 0 1       ; R4 := false; PC := 122
122 [-]: LOADKB    R4 1 0       ; R4 := true
123 [-]: SETUPVAL  R4 U11       ; U82 := R11
124 [-]: GETUPVAL  R4 U11       ; R4 := U11
125 [-]: TEST      R4 0         ; if not R4 then PC := 144
126 [-]: JMP       144          ; PC := 144
127 [-]: GETUPVAL  R4 U0        ; R4 := U0
128 [-]: TEST      R4 1         ; if R4 then PC := 144
129 [-]: JMP       144          ; PC := 144
130 [-]: GETUPVAL  R4 U13       ; R4 := U13
131 [-]: TEST      R4 0         ; if not R4 then PC := 144
132 [-]: JMP       144          ; PC := 144
133 [-]: GETGLOBAL R4 K4        ; R4 := 0x7b998233
134 [-]: GETUPVAL  R5 U4        ; R5 := U4
135 [-]: CALL      R4 2 2       ; R4 := R4(R5)
136 [-]: TEST      R4 1         ; if R4 then PC := 142
137 [-]: JMP       142          ; PC := 142
138 [-]: GETUPVAL  R4 U4        ; R4 := U4
139 [-]: SELF      R4 R4 K33    ; R5 := R4; R4 := R4[0xec943d0f]
140 [-]: CALL      R4 2 2       ; R4 := R4(R5)
141 [-]: JMP       144          ; PC := 144
142 [-]: LOADKB    R4 0 1       ; R4 := false; PC := 143
143 [-]: LOADKB    R4 1 0       ; R4 := true
144 [-]: SETUPVAL  R4 U12       ; U82 := R12
145 [-]: GETGLOBAL R4 K23       ; R4 := 0x25312c9b
146 [-]: GETGLOBAL R5 K0        ; R5 := 0xae91e43b
147 [-]: LOADK     R6 K34       ; R6 := "TimeOfDay"
148 [-]: CONST     R7 8         ; R7 := 8.000000
149 [-]: NEWTABLE  R8 1 0       ; R8 := {}
150 [-]: CONST     R9 10        ; R9 := 10.000000
151 [-]: SETLIST   R8 1 1       ; R8[(1-1)*FPF+i] := R(8+i), 1 <= i <= 1
152 [-]: NEWTABLE  R9 0 0       ; R9 := {}
153 [-]: GETUPVAL  R10 U14      ; R10 := U14
154 [-]: GETTABLE  R10 R10 K35  ; R10 := R10[0x06d055f9]
155 [-]: GETUPVAL  R11 U12      ; R11 := U12
156 [-]: CONST     R12 100      ; R12 := 100.000000
157 [-]: CONST     R13 0        ; R13 := 0.000000
158 [-]: CALL      R10 4 0      ; R10,... := R10(R11,R12,R13)
159 [-]: SETLIST   R9 0 1       ; R9[(1-1)*FPF+i] := R(9+i), 1 <= i <= 0
160 [-]: LOADK     R10 K25      ; R10 := 0.300000
161 [-]: CALL      R4 7 1       ; R4(R5,R6,R7,R8,R9,R10)
162 [-]: GETGLOBAL R4 K23       ; R4 := 0x25312c9b
163 [-]: GETGLOBAL R5 K0        ; R5 := 0xae91e43b
164 [-]: LOADK     R6 K36       ; R6 := "Blurer"
165 [-]: CONST     R7 8         ; R7 := 8.000000
166 [-]: NEWTABLE  R8 1 0       ; R8 := {}
167 [-]: CONST     R9 10        ; R9 := 10.000000
168 [-]: SETLIST   R8 1 1       ; R8[(1-1)*FPF+i] := R(8+i), 1 <= i <= 1
169 [-]: NEWTABLE  R9 0 0       ; R9 := {}
170 [-]: GETUPVAL  R10 U14      ; R10 := U14
171 [-]: GETTABLE  R10 R10 K35  ; R10 := R10[0x06d055f9]
172 [-]: GETUPVAL  R11 U0       ; R11 := U0
173 [-]: CONST     R12 100      ; R12 := 100.000000
174 [-]: CONST     R13 0        ; R13 := 0.000000
175 [-]: CALL      R10 4 0      ; R10,... := R10(R11,R12,R13)
176 [-]: SETLIST   R9 0 1       ; R9[(1-1)*FPF+i] := R(9+i), 1 <= i <= 0
177 [-]: LOADK     R10 K25      ; R10 := 0.300000
178 [-]: CALL      R4 7 1       ; R4(R5,R6,R7,R8,R9,R10)
179 [-]: RETURN    R0 1         ; return 


; Function #30:
;
; Name:            
; Defined at line: 729
; #Upvalues:       5
; #Parameters:     1
; Is_vararg:       0
; Max Stack Size:  9

  1 [-]: GETUPVAL  R1 U0        ; R1 := U0
  2 [-]: TEST      R1 0         ; if not R1 then PC := 5
  3 [-]: JMP       5            ; PC := 5
  4 [-]: RETURN    R0 1         ; return 
  5 [-]: EQ        1 R0 K0      ; if R0 == "true" then PC := 8
  6 [-]: JMP       8            ; PC := 8
  7 [-]: LOADKB    R0 0 1       ; R0 := false; PC := 8
  8 [-]: LOADKB    R0 1 0       ; R0 := true
  9 [-]: GETUPVAL  R1 U1        ; R1 := U1
 10 [-]: EQ        1 R1 R0      ; if R1 == R0 then PC := 74
 11 [-]: JMP       74           ; PC := 74
 12 [-]: SETUPVAL  R0 U1        ; U82 := R1
 13 [-]: GETUPVAL  R1 U2        ; R1 := U2
 14 [-]: CALL      R1 1 1       ; R1()
 15 [-]: GETGLOBAL R1 K1        ; R1 := 0x7b998233
 16 [-]: GETUPVAL  R2 U3        ; R2 := U3
 17 [-]: CALL      R1 2 2       ; R1 := R1(R2)
 18 [-]: TEST      R1 1         ; if R1 then PC := 28
 19 [-]: JMP       28           ; PC := 28
 20 [-]: GETUPVAL  R1 U3        ; R1 := U3
 21 [-]: SELF      R1 R1 K2     ; R2 := R1; R1 := R1[0x8f83a362]
 22 [-]: GETUPVAL  R3 U1        ; R3 := U1
 23 [-]: CALL      R1 3 1       ; R1(R2,R3)
 24 [-]: GETUPVAL  R1 U3        ; R1 := U3
 25 [-]: SELF      R1 R1 K3     ; R2 := R1; R1 := R1[0xc256d7cf]
 26 [-]: GETUPVAL  R3 U1        ; R3 := U1
 27 [-]: CALL      R1 3 1       ; R1(R2,R3)
 28 [-]: GETGLOBAL R1 K4        ; R1 := 0x34291f5c
 29 [-]: GETTABLE  R1 R1 K5     ; R1 := R1[0xe6b41adb]
 30 [-]: CALL      R1 1 2       ; R1 := R1()
 31 [-]: TEST      R1 0         ; if not R1 then PC := 74
 32 [-]: JMP       74           ; PC := 74
 33 [-]: TEST      R0 0         ; if not R0 then PC := 74
 34 [-]: JMP       74           ; PC := 74
 35 [-]: CONST     R1 100       ; R1 := 100.000000
 36 [-]: GETGLOBAL R2 K6        ; R2 := 0xae91e43b
 37 [-]: SELF      R2 R2 K7     ; R3 := R2; R2 := R2[0x67bc869f]
 38 [-]: LOADK     R4 K8        ; R4 := "MiniMapContainer"
 39 [-]: CONST     R5 5         ; R5 := 5.000000
 40 [-]: MOVE      R6 R1        ; R6 := R1
 41 [-]: CALL      R2 5 1       ; R2(R3,R4,R5,R6)
 42 [-]: GETGLOBAL R2 K6        ; R2 := 0xae91e43b
 43 [-]: SELF      R2 R2 K7     ; R3 := R2; R2 := R2[0x67bc869f]
 44 [-]: LOADK     R4 K9        ; R4 := "MiniMapOverlayMsg"
 45 [-]: CONST     R5 5         ; R5 := 5.000000
 46 [-]: MOVE      R6 R1        ; R6 := R1
 47 [-]: CALL      R2 5 1       ; R2(R3,R4,R5,R6)
 48 [-]: GETGLOBAL R2 K6        ; R2 := 0xae91e43b
 49 [-]: SELF      R2 R2 K7     ; R3 := R2; R2 := R2[0x67bc869f]
 50 [-]: LOADK     R4 K8        ; R4 := "MiniMapContainer"
 51 [-]: CONST     R5 6         ; R5 := 6.000000
 52 [-]: MOVE      R6 R1        ; R6 := R1
 53 [-]: CALL      R2 5 1       ; R2(R3,R4,R5,R6)
 54 [-]: GETGLOBAL R2 K6        ; R2 := 0xae91e43b
 55 [-]: SELF      R2 R2 K7     ; R3 := R2; R2 := R2[0x67bc869f]
 56 [-]: LOADK     R4 K9        ; R4 := "MiniMapOverlayMsg"
 57 [-]: CONST     R5 6         ; R5 := 6.000000
 58 [-]: MOVE      R6 R1        ; R6 := R1
 59 [-]: CALL      R2 5 1       ; R2(R3,R4,R5,R6)
 60 [-]: LOADK     R2 K10       ; R2 := "MiniMapContainer.MiniMapMarkers.Marker1"
 61 [-]: CONST     R3 125       ; R3 := 125.000000
 62 [-]: GETGLOBAL R4 K6        ; R4 := 0xae91e43b
 63 [-]: SELF      R4 R4 K7     ; R5 := R4; R4 := R4[0x67bc869f]
 64 [-]: MOVE      R6 R2        ; R6 := R2
 65 [-]: CONST     R7 5         ; R7 := 5.000000
 66 [-]: MOVE      R8 R3        ; R8 := R3
 67 [-]: CALL      R4 5 1       ; R4(R5,R6,R7,R8)
 68 [-]: GETGLOBAL R4 K6        ; R4 := 0xae91e43b
 69 [-]: SELF      R4 R4 K7     ; R5 := R4; R4 := R4[0x67bc869f]
 70 [-]: MOVE      R6 R2        ; R6 := R2
 71 [-]: CONST     R7 6         ; R7 := 6.000000
 72 [-]: MOVE      R8 R3        ; R8 := R3
 73 [-]: CALL      R4 5 1       ; R4(R5,R6,R7,R8)
 74 [-]: GETGLOBAL R4 K1        ; R4 := 0x7b998233
 75 [-]: GETUPVAL  R5 U4        ; R5 := U4
 76 [-]: CALL      R4 2 2       ; R4 := R4(R5)
 77 [-]: TEST      R4 1         ; if R4 then PC := 83
 78 [-]: JMP       83           ; PC := 83
 79 [-]: GETUPVAL  R4 U4        ; R4 := U4
 80 [-]: SELF      R4 R4 K11    ; R5 := R4; R4 := R4[0xa8abe17c]
 81 [-]: NOT       R6 R0        ; R6 :=  R0
 82 [-]: CALL      R4 3 1       ; R4(R5,R6)
 83 [-]: RETURN    R0 1         ; return 


; Function #31:
;
; Name:            
; Defined at line: 762
; #Upvalues:       3
; #Parameters:     0
; Is_vararg:       0
; Max Stack Size:  6

  1 [-]: GETGLOBAL R0 K0        ; R0 := 0x34291f5c
  2 [-]: GETTABLE  R0 R0 K1     ; R0 := R0[0xe6b41adb]
  3 [-]: CALL      R0 1 2       ; R0 := R0()
  4 [-]: TEST      R0 0         ; if not R0 then PC := 12
  5 [-]: JMP       12           ; PC := 12
  6 [-]: GETGLOBAL R0 K2        ; R0 := 0x89326c93
  7 [-]: SELF      R0 R0 K3     ; R1 := R0; R0 := R0[0xfb64e76c]
  8 [-]: CALL      R0 2 2       ; R0 := R0(R1)
  9 [-]: SELF      R0 R0 K4     ; R1 := R0; R0 := R0[0x97c4ff93]
 10 [-]: LOADKB    R2 0 0       ; R2 := false
 11 [-]: CALL      R0 3 1       ; R0(R1,R2)
 12 [-]: GETGLOBAL R0 K5        ; R0 := 0x7b998233
 13 [-]: GETGLOBAL R1 K6        ; R1 := _T
 14 [-]: GETTABLE  R1 R1 K7     ; R1 := R1["ShowButtonBarCursor"]
 15 [-]: CALL      R0 2 2       ; R0 := R0(R1)
 16 [-]: TEST      R0 1         ; if R0 then PC := 22
 17 [-]: JMP       22           ; PC := 22
 18 [-]: GETGLOBAL R0 K6        ; R0 := _T
 19 [-]: GETTABLE  R0 R0 K8     ; R0 := R0[0xbfd7a316]
 20 [-]: LOADKB    R1 1 0       ; R1 := true
 21 [-]: CALL      R0 2 1       ; R0(R1)
 22 [-]: GETGLOBAL R0 K5        ; R0 := 0x7b998233
 23 [-]: GETUPVAL  R1 U0        ; R1 := U0
 24 [-]: CALL      R0 2 2       ; R0 := R0(R1)
 25 [-]: TEST      R0 1         ; if R0 then PC := 60
 26 [-]: JMP       60           ; PC := 60
 27 [-]: GETGLOBAL R0 K5        ; R0 := 0x7b998233
 28 [-]: GETUPVAL  R1 U1        ; R1 := U1
 29 [-]: CALL      R0 2 2       ; R0 := R0(R1)
 30 [-]: TEST      R0 1         ; if R0 then PC := 53
 31 [-]: JMP       53           ; PC := 53
 32 [-]: GETUPVAL  R0 U1        ; R0 := U1
 33 [-]: GETTABLE  R0 R0 K9     ; R0 := R0["mEntity"]
 34 [-]: GETGLOBAL R1 K5        ; R1 := 0x7b998233
 35 [-]: MOVE      R2 R0        ; R2 := R0
 36 [-]: CALL      R1 2 2       ; R1 := R1(R2)
 37 [-]: TEST      R1 1         ; if R1 then PC := 53
 38 [-]: JMP       53           ; PC := 53
 39 [-]: SELF      R1 R0 K10    ; R2 := R0; R1 := R0[0xbe612609]
 40 [-]: CALL      R1 2 2       ; R1 := R1(R2)
 41 [-]: EQ        1 R1 K11     ; if R1 == 1.000000 then PC := 50
 42 [-]: JMP       50           ; PC := 50
 43 [-]: SELF      R2 R0 K12    ; R3 := R0; R2 := R0[0xe00b9ae7]
 44 [-]: CALL      R2 2 2       ; R2 := R2(R3)
 45 [-]: GETTABLE  R2 R2 K13    ; R2 := R2["x"]
 46 [-]: DIV       R2 R2 R1     ; R2 := R2 / R1
 47 [-]: SELF      R3 R0 K14    ; R4 := R0; R3 := R0[0x351bfdeb]
 48 [-]: MOVE      R5 R2        ; R5 := R2
 49 [-]: CALL      R3 3 1       ; R3(R4,R5)
 50 [-]: SELF      R3 R0 K15    ; R4 := R0; R3 := R0[0xffcb00d9]
 51 [-]: GETUPVAL  R5 U2        ; R5 := U2
 52 [-]: CALL      R3 3 1       ; R3(R4,R5)
 53 [-]: GETUPVAL  R3 U0        ; R3 := U0
 54 [-]: SELF      R3 R3 K16    ; R4 := R3; R3 := R3[0xf5fc319f]
 55 [-]: CALL      R3 2 1       ; R3(R4)
 56 [-]: GETUPVAL  R3 U0        ; R3 := U0
 57 [-]: SELF      R3 R3 K17    ; R4 := R3; R3 := R3[0x76b07564]
 58 [-]: LOADKB    R5 0 0       ; R5 := false
 59 [-]: CALL      R3 3 1       ; R3(R4,R5)
 60 [-]: RETURN    R0 1         ; return 


; Function #32:
;
; Name:            
; Defined at line: 788
; #Upvalues:       2
; #Parameters:     1
; Is_vararg:       0
; Max Stack Size:  10

  1 [-]: GETUPVAL  R1 U0        ; R1 := U0
  2 [-]: EQ        0 R1 R0      ; if R1 ~= R0 then PC := 5
  3 [-]: JMP       5            ; PC := 5
  4 [-]: RETURN    R0 1         ; return 
  5 [-]: SETUPVAL  R0 U0        ; U82 := R0
  6 [-]: GETGLOBAL R1 K0        ; R1 := 0x25312c9b
  7 [-]: GETGLOBAL R2 K1        ; R2 := 0xae91e43b
  8 [-]: LOADK     R3 K2        ; R3 := "TimeOfDay.Hands.Day"
  9 [-]: CONST     R4 2         ; R4 := 2.000000
 10 [-]: NEWTABLE  R5 1 0       ; R5 := {}
 11 [-]: CONST     R6 14        ; R6 := 14.000000
 12 [-]: SETLIST   R5 1 1       ; R5[(1-1)*FPF+i] := R(5+i), 1 <= i <= 1
 13 [-]: NEWTABLE  R6 1 0       ; R6 := {}
 14 [-]: GETUPVAL  R7 U1        ; R7 := U1
 15 [-]: GETTABLE  R7 R7 R0     ; R7 := R7[R0]
 16 [-]: GETTABLE  R7 R7 K4     ; R7 := R7["DAY"]
 17 [-]: SETLIST   R6 1 1       ; R6[(1-1)*FPF+i] := R(6+i), 1 <= i <= 1
 18 [-]: CONST     R7 0         ; R7 := 0.500000
 19 [-]: CALL      R1 7 1       ; R1(R2,R3,R4,R5,R6,R7)
 20 [-]: GETGLOBAL R1 K0        ; R1 := 0x25312c9b
 21 [-]: GETGLOBAL R2 K1        ; R2 := 0xae91e43b
 22 [-]: LOADK     R3 K5        ; R3 := "TimeOfDay.Hands.Night"
 23 [-]: CONST     R4 2         ; R4 := 2.000000
 24 [-]: NEWTABLE  R5 1 0       ; R5 := {}
 25 [-]: CONST     R6 14        ; R6 := 14.000000
 26 [-]: SETLIST   R5 1 1       ; R5[(1-1)*FPF+i] := R(5+i), 1 <= i <= 1
 27 [-]: NEWTABLE  R6 1 0       ; R6 := {}
 28 [-]: GETUPVAL  R7 U1        ; R7 := U1
 29 [-]: GETTABLE  R7 R7 R0     ; R7 := R7[R0]
 30 [-]: GETTABLE  R7 R7 K6     ; R7 := R7["NIGHT"]
 31 [-]: SETLIST   R6 1 1       ; R6[(1-1)*FPF+i] := R(6+i), 1 <= i <= 1
 32 [-]: CONST     R7 0         ; R7 := 0.500000
 33 [-]: CALL      R1 7 1       ; R1(R2,R3,R4,R5,R6,R7)
 34 [-]: GETGLOBAL R1 K0        ; R1 := 0x25312c9b
 35 [-]: GETGLOBAL R2 K1        ; R2 := 0xae91e43b
 36 [-]: LOADK     R3 K7        ; R3 := "TimeOfDay.DayNight"
 37 [-]: CONST     R4 2         ; R4 := 2.000000
 38 [-]: NEWTABLE  R5 1 0       ; R5 := {}
 39 [-]: CONST     R6 14        ; R6 := 14.000000
 40 [-]: SETLIST   R5 1 1       ; R5[(1-1)*FPF+i] := R(5+i), 1 <= i <= 1
 41 [-]: NEWTABLE  R6 1 0       ; R6 := {}
 42 [-]: GETUPVAL  R7 U1        ; R7 := U1
 43 [-]: GETTABLE  R7 R7 R0     ; R7 := R7[R0]
 44 [-]: GETTABLE  R7 R7 K8     ; R7 := R7["BACKER"]
 45 [-]: SETLIST   R6 1 1       ; R6[(1-1)*FPF+i] := R(6+i), 1 <= i <= 1
 46 [-]: CONST     R7 0         ; R7 := 0.500000
 47 [-]: CONST     R8 0         ; R8 := 0.000000
 48 [-]: CLOSURE   R9 0         ; R9 := closure(Function #32.1)
 49 [-]: CALL      R1 9 1       ; R1(R2,R3,R4,R5,R6,R7,R8,R9)
 50 [-]: RETURN    R0 1         ; return 


; Function #32.1:
;
; Name:            
; Defined at line: 797
; #Upvalues:       0
; #Parameters:     0
; Is_vararg:       0
; Max Stack Size:  2

  1 [-]: RETURN    R0 1         ; return 


; Function #33:
;
; Name:            
; Defined at line: 808
; #Upvalues:       6
; #Parameters:     0
; Is_vararg:       0
; Max Stack Size:  19

  1 [-]: GETGLOBAL R0 K0        ; R0 := 0x7b998233
  2 [-]: GETGLOBAL R1 K1        ; R1 := 0x89326c93
  3 [-]: CALL      R0 2 2       ; R0 := R0(R1)
  4 [-]: TEST      R0 1         ; if R0 then PC := 13
  5 [-]: JMP       13           ; PC := 13
  6 [-]: GETGLOBAL R0 K0        ; R0 := 0x7b998233
  7 [-]: GETGLOBAL R1 K1        ; R1 := 0x89326c93
  8 [-]: SELF      R1 R1 K2     ; R2 := R1; R1 := R1[0x7c1a0374]
  9 [-]: CALL      R1 2 0       ; R1,... := R1(R2)
 10 [-]: CALL      R0 0 2       ; R0 := R0(R1,...)
 11 [-]: TEST      R0 0         ; if not R0 then PC := 14
 12 [-]: JMP       14           ; PC := 14
 13 [-]: RETURN    R0 1         ; return 
 14 [-]: GETUPVAL  R0 U0        ; R0 := U0
 15 [-]: GETTABLE  R0 R0 K3     ; R0 := R0[0xe2a93301]
 16 [-]: CALL      R0 1 2       ; R0 := R0()
 17 [-]: LOADNIL   R1 R1        ; R1 := nil
 18 [-]: GETUPVAL  R2 U0        ; R2 := U0
 19 [-]: GETTABLE  R2 R2 K4     ; R2 := R2["SOUND_SET_FORTUNA"]
 20 [-]: EQ        0 R0 R2      ; if R0 ~= R2 then PC := 29
 21 [-]: JMP       29           ; PC := 29
 22 [-]: GETUPVAL  R2 U0        ; R2 := U0
 23 [-]: GETTABLE  R2 R2 K5     ; R2 := R2[0xb77ba3b0]
 24 [-]: GETUPVAL  R3 U0        ; R3 := U0
 25 [-]: GETTABLE  R3 R3 K6     ; R3 := R3["ORB_VALLIS_NODE_TAG"]
 26 [-]: CALL      R2 2 2       ; R2 := R2(R3)
 27 [-]: MOVE      R1 R2        ; R1 := R2
 28 [-]: JMP       57           ; PC := 57
 29 [-]: GETUPVAL  R2 U0        ; R2 := U0
 30 [-]: GETTABLE  R2 R2 K7     ; R2 := R2["SOUND_SET_OROKIN_TOWER"]
 31 [-]: EQ        0 R0 R2      ; if R0 ~= R2 then PC := 40
 32 [-]: JMP       40           ; PC := 40
 33 [-]: GETUPVAL  R2 U0        ; R2 := U0
 34 [-]: GETTABLE  R2 R2 K5     ; R2 := R2[0xb77ba3b0]
 35 [-]: GETUPVAL  R3 U0        ; R3 := U0
 36 [-]: GETTABLE  R3 R3 K8     ; R3 := R3["ENTRATI_LANDSCAPE_NODE_TAG"]
 37 [-]: CALL      R2 2 2       ; R2 := R2(R3)
 38 [-]: MOVE      R1 R2        ; R1 := R2
 39 [-]: JMP       57           ; PC := 57
 40 [-]: GETUPVAL  R2 U0        ; R2 := U0
 41 [-]: GETTABLE  R2 R2 K9     ; R2 := R2["SOUND_SET_ZARIMAN"]
 42 [-]: EQ        0 R0 R2      ; if R0 ~= R2 then PC := 51
 43 [-]: JMP       51           ; PC := 51
 44 [-]: GETUPVAL  R2 U0        ; R2 := U0
 45 [-]: GETTABLE  R2 R2 K5     ; R2 := R2[0xb77ba3b0]
 46 [-]: GETUPVAL  R3 U0        ; R3 := U0
 47 [-]: GETTABLE  R3 R3 K10    ; R3 := R3["ZARIMAN_NODE_TAG"]
 48 [-]: CALL      R2 2 2       ; R2 := R2(R3)
 49 [-]: MOVE      R1 R2        ; R1 := R2
 50 [-]: JMP       57           ; PC := 57
 51 [-]: GETGLOBAL R2 K1        ; R2 := 0x89326c93
 52 [-]: SELF      R2 R2 K2     ; R3 := R2; R2 := R2[0x7c1a0374]
 53 [-]: CALL      R2 2 2       ; R2 := R2(R3)
 54 [-]: SELF      R2 R2 K11    ; R3 := R2; R2 := R2[0x1622ab2c]
 55 [-]: CALL      R2 2 2       ; R2 := R2(R3)
 56 [-]: MOVE      R1 R2        ; R1 := R2
 57 [-]: GETUPVAL  R2 U0        ; R2 := U0
 58 [-]: GETTABLE  R2 R2 K12    ; R2 := R2[0xdef77cfa]
 59 [-]: MOVE      R3 R1        ; R3 := R1
 60 [-]: GETUPVAL  R4 U1        ; R4 := U1
 61 [-]: CALL      R2 3 4       ; R2,R3,R4 := R2(R3,R4)
 62 [-]: GETUPVAL  R5 U2        ; R5 := U2
 63 [-]: TEST      R5 0         ; if not R5 then PC := 90
 64 [-]: JMP       90           ; PC := 90
 65 [-]: GETUPVAL  R5 U0        ; R5 := U0
 66 [-]: GETTABLE  R5 R5 K13    ; R5 := R5["TimeOfDayConstants"]
 67 [-]: GETTABLE  R5 R5 K14    ; R5 := R5["TIME_OF_DAY_LABEL_FASS"]
 68 [-]: EQ        0 R2 R5      ; if R2 ~= R5 then PC := 80
 69 [-]: JMP       80           ; PC := 80
 70 [-]: LT        0 R4 K15     ; if R4 >= 60.000000 then PC := 76
 71 [-]: JMP       76           ; PC := 76
 72 [-]: GETUPVAL  R5 U3        ; R5 := U3
 73 [-]: CONST     R6 2         ; R6 := 2.000000
 74 [-]: CALL      R5 2 1       ; R5(R6)
 75 [-]: JMP       102          ; PC := 102
 76 [-]: GETUPVAL  R5 U3        ; R5 := U3
 77 [-]: CONST     R6 1         ; R6 := 1.000000
 78 [-]: CALL      R5 2 1       ; R5(R6)
 79 [-]: JMP       102          ; PC := 102
 80 [-]: LT        0 R4 K15     ; if R4 >= 60.000000 then PC := 86
 81 [-]: JMP       86           ; PC := 86
 82 [-]: GETUPVAL  R5 U3        ; R5 := U3
 83 [-]: CONST     R6 4         ; R6 := 4.000000
 84 [-]: CALL      R5 2 1       ; R5(R6)
 85 [-]: JMP       102          ; PC := 102
 86 [-]: GETUPVAL  R5 U3        ; R5 := U3
 87 [-]: CONST     R6 3         ; R6 := 3.000000
 88 [-]: CALL      R5 2 1       ; R5(R6)
 89 [-]: JMP       102          ; PC := 102
 90 [-]: SUB       R5 R1 K16    ; R5 := R1 - 12.000000
 91 [-]: DIV       R5 R5 K17    ; R5 := R5 / 24.000000
 92 [-]: MUL       R5 R5 K18    ; R5 := R5 * -360.000000
 93 [-]: GETGLOBAL R6 K19       ; R6 := 0xae91e43b
 94 [-]: SELF      R6 R6 K20    ; R7 := R6; R6 := R6[0x67bc869f]
 95 [-]: LOADK     R8 K21       ; R8 := "TimeOfDay.DayNight"
 96 [-]: CONST     R9 14        ; R9 := 14.000000
 97 [-]: GETGLOBAL R10 K22      ; R10 := 0xb693b6c1
 98 [-]: CALL      R10 1 2      ; R10 := R10()
 99 [-]: MUL       R10 R10 K23  ; R10 := R10 * 30.000000
100 [-]: ADD       R10 R5 R10   ; R10 := R5 + R10
101 [-]: CALL      R6 5 1       ; R6(R7,R8,R9,R10)
102 [-]: GETUPVAL  R6 U0        ; R6 := U0
103 [-]: GETTABLE  R6 R6 K24    ; R6 := R6[0x817b1503]
104 [-]: GETGLOBAL R7 K19       ; R7 := 0xae91e43b
105 [-]: MOVE      R8 R4        ; R8 := R4
106 [-]: LOADK     R9 K25       ; R9 := "CompactOne"
107 [-]: CALL      R6 4 2       ; R6 := R6(R7,R8,R9)
108 [-]: GETGLOBAL R7 K19       ; R7 := 0xae91e43b
109 [-]: SELF      R7 R7 K26    ; R8 := R7; R7 := R7[0x42b04007]
110 [-]: LOADK     R9 K27       ; R9 := "/Lotus/Language/SystemMessages/TimeUntil"
111 [-]: LOADKB    R10 0 0      ; R10 := false
112 [-]: NEWTABLE  R11 0 2      ; R11 := {}
113 [-]: GETGLOBAL R12 K29      ; R12 := 0x7f5022cf
114 [-]: GETTABLE  R12 R12 K30  ; R12 := R12[0x3f3e4d12]
115 [-]: GETGLOBAL R13 K19      ; R13 := 0xae91e43b
116 [-]: SELF      R13 R13 K26  ; R14 := R13; R13 := R13[0x42b04007]
117 [-]: MOVE      R15 R3       ; R15 := R3
118 [-]: LOADKB    R16 0 0      ; R16 := false
119 [-]: CALL      R13 4 0      ; R13,... := R13(R14,R15,R16)
120 [-]: CALL      R12 0 2      ; R12 := R12(R13,...)
121 [-]: SETTABLE  R11 K28 R12  ; R11["LABEL"] := R12
122 [-]: SETTABLE  R11 K31 R6   ; R11["TIME"] := R6
123 [-]: CALL      R7 5 2       ; R7 := R7(R8,R9,R10,R11)
124 [-]: GETGLOBAL R8 K32       ; R8 := _T
125 [-]: GETTABLE  R8 R8 K33    ; R8 := R8["timeToNext"]
126 [-]: TEST      R8 0         ; if not R8 then PC := 132
127 [-]: JMP       132          ; PC := 132
128 [-]: GETGLOBAL R8 K32       ; R8 := _T
129 [-]: GETTABLE  R8 R8 K33    ; R8 := R8["timeToNext"]
130 [-]: EQ        1 R8 R6      ; if R8 == R6 then PC := 149
131 [-]: JMP       149          ; PC := 149
132 [-]: GETGLOBAL R8 K34       ; R8 := 0x3d106989
133 [-]: LOADK     R9 K35       ; R9 := "Time to next: "
134 [-]: GETGLOBAL R10 K36      ; R10 := 0x64fb1586
135 [-]: MOVE      R11 R4       ; R11 := R4
136 [-]: CALL      R10 2 2      ; R10 := R10(R11)
137 [-]: LOADK     R11 K37      ; R11 := " -- "
138 [-]: GETGLOBAL R12 K36      ; R12 := 0x64fb1586
139 [-]: MOVE      R13 R6       ; R13 := R6
140 [-]: CALL      R12 2 2      ; R12 := R12(R13)
141 [-]: LOADK     R13 K37      ; R13 := " -- "
142 [-]: GETGLOBAL R14 K36      ; R14 := 0x64fb1586
143 [-]: MOVE      R15 R1       ; R15 := R1
144 [-]: CALL      R14 2 2      ; R14 := R14(R15)
145 [-]: CONCAT    R9 R9 R14    ; R9 := R9 .. R10 .. R11 .. R12 .. R13 .. R14
146 [-]: CALL      R8 2 1       ; R8(R9)
147 [-]: GETGLOBAL R8 K32       ; R8 := _T
148 [-]: SETTABLE  R8 K33 R6    ; R8["timeToNext"] := R6
149 [-]: GETUPVAL  R8 U4        ; R8 := U4
150 [-]: TEST      R8 0         ; if not R8 then PC := 229
151 [-]: JMP       229          ; PC := 229
152 [-]: GETGLOBAL R8 K38       ; R8 := 0x2d0fad09
153 [-]: LOADK     R9 K39       ; R9 := "Lotus.Interface.WorldStateUtilities"
154 [-]: CALL      R8 2 2       ; R8 := R8(R9)
155 [-]: GETTABLE  R9 R8 K40    ; R9 := R8[0x5273af13]
156 [-]: LOADK     R10 K41      ; R10 := "zmc"
157 [-]: CONST     R11 120      ; R11 := 120.000000
158 [-]: CALL      R9 3 2       ; R9 := R9(R10,R11)
159 [-]: GETGLOBAL R10 K32      ; R10 := _T
160 [-]: GETTABLE  R10 R10 K42  ; R10 := R10["CachedZarimanFactionIdx"]
161 [-]: TEST      R10 1        ; if R10 then PC := 164
162 [-]: JMP       164          ; PC := 164
163 [-]: CONST     R10 0        ; R10 := 0.000000
164 [-]: GETUPVAL  R11 U5       ; R11 := U5
165 [-]: GETTABLE  R11 R11 K44  ; R11 := R11[0x06d055f9]
166 [-]: EQ        1 R10 K45    ; if R10 == 0.000000 then PC := 169
167 [-]: JMP       169          ; PC := 169
168 [-]: LOADKB    R12 0 1      ; R12 := false; PC := 169
169 [-]: LOADKB    R12 1 0      ; R12 := true
170 [-]: LOADK     R13 K46      ; R13 := "/Lotus/Language/Zariman/ZarimanInfluenceGrineer"
171 [-]: LOADK     R14 K47      ; R14 := "/Lotus/Language/Zariman/ZarimanInfluenceCorpus"
172 [-]: CALL      R11 4 2      ; R11 := R11(R12,R13,R14)
173 [-]: GETGLOBAL R12 K32      ; R12 := _T
174 [-]: GETTABLE  R12 R12 K48  ; R12 := R12["ForceZarimanInfluence"]
175 [-]: EQ        1 R12 K49    ; if R12 == nil then PC := 179
176 [-]: JMP       179          ; PC := 179
177 [-]: GETGLOBAL R12 K32      ; R12 := _T
178 [-]: GETTABLE  R10 R12 K48  ; R10 := R12["ForceZarimanInfluence"]
179 [-]: GETGLOBAL R12 K19      ; R12 := 0xae91e43b
180 [-]: SELF      R12 R12 K50  ; R13 := R12; R12 := R12[0x1cb415c1]
181 [-]: LOADK     R14 K51      ; R14 := "TimeOfDay.ZarimanCycler.Influence"
182 [-]: GETGLOBAL R15 K52      ; R15 := 0x51a9daf5
183 [-]: ADD       R16 R10 K53  ; R16 := R10 + 1.000000
184 [-]: GETTABLE  R15 R15 R16  ; R15 := R15[R16]
185 [-]: CALL      R12 4 1      ; R12(R13,R14,R15)
186 [-]: LOADK     R12 K54      ; R12 := "<p><font color=\"#FFC674\" size=\"28\" face=\"roboto\">"
187 [-]: GETGLOBAL R13 K29      ; R13 := 0x7f5022cf
188 [-]: GETTABLE  R13 R13 K30  ; R13 := R13[0x3f3e4d12]
189 [-]: GETGLOBAL R14 K55      ; R14 := 0x603636ad
190 [-]: LOADK     R15 K56      ; R15 := "/Lotus/Language/Zariman/ZarimanStatus"
191 [-]: NEWTABLE  R16 0 0      ; R16 := {}
192 [-]: CALL      R14 3 0      ; R14,... := R14(R15,R16)
193 [-]: CALL      R13 0 2      ; R13 := R13(R14,...)
194 [-]: LOADK     R14 K57      ; R14 := "<br><font color=\"#FFD374\" size=\"32\"><b>"
195 [-]: GETGLOBAL R15 K29      ; R15 := 0x7f5022cf
196 [-]: GETTABLE  R15 R15 K30  ; R15 := R15[0x3f3e4d12]
197 [-]: GETGLOBAL R16 K55      ; R16 := 0x603636ad
198 [-]: MOVE      R17 R11      ; R17 := R11
199 [-]: NEWTABLE  R18 0 0      ; R18 := {}
200 [-]: CALL      R16 3 0      ; R16,... := R16(R17,R18)
201 [-]: CALL      R15 0 2      ; R15 := R15(R16,...)
202 [-]: LOADK     R16 K58      ; R16 := "</b></font></font></p>"
203 [-]: CONCAT    R11 R12 R16  ; R11 := R12 .. R13 .. R14 .. R15 .. R16
204 [-]: GETGLOBAL R12 K19      ; R12 := 0xae91e43b
205 [-]: SELF      R12 R12 K59  ; R13 := R12; R12 := R12[0x5f56eeab]
206 [-]: LOADK     R14 K60      ; R14 := "TimeOfDay.Label"
207 [-]: CONST     R15 29       ; R15 := 29.000000
208 [-]: MOVE      R16 R11      ; R16 := R11
209 [-]: CALL      R12 5 1      ; R12(R13,R14,R15,R16)
210 [-]: GETGLOBAL R12 K19      ; R12 := 0xae91e43b
211 [-]: SELF      R12 R12 K59  ; R13 := R12; R12 := R12[0x5f56eeab]
212 [-]: LOADK     R14 K60      ; R14 := "TimeOfDay.Label"
213 [-]: CONST     R15 38       ; R15 := 38.000000
214 [-]: LOADK     R16 K61      ; R16 := "center"
215 [-]: CALL      R12 5 1      ; R12(R13,R14,R15,R16)
216 [-]: GETGLOBAL R12 K19      ; R12 := 0xae91e43b
217 [-]: SELF      R12 R12 K59  ; R13 := R12; R12 := R12[0x5f56eeab]
218 [-]: LOADK     R14 K60      ; R14 := "TimeOfDay.Label"
219 [-]: CONST     R15 37       ; R15 := 37.000000
220 [-]: LOADK     R16 K62      ; R16 := "right"
221 [-]: CALL      R12 5 1      ; R12(R13,R14,R15,R16)
222 [-]: GETGLOBAL R12 K19      ; R12 := 0xae91e43b
223 [-]: SELF      R12 R12 K20  ; R13 := R12; R12 := R12[0x67bc869f]
224 [-]: LOADK     R14 K60      ; R14 := "TimeOfDay.Label"
225 [-]: CONST     R15 77       ; R15 := 77.000000
226 [-]: CONST     R16 100      ; R16 := 100.000000
227 [-]: CALL      R12 5 1      ; R12(R13,R14,R15,R16)
228 [-]: JMP       240          ; PC := 240
229 [-]: GETGLOBAL R12 K19      ; R12 := 0xae91e43b
230 [-]: SELF      R12 R12 K63  ; R13 := R12; R12 := R12[0x20b98db3]
231 [-]: LOADK     R14 K64      ; R14 := "TimeOfDay.Label.text"
232 [-]: MOVE      R15 R7       ; R15 := R7
233 [-]: CALL      R12 4 1      ; R12(R13,R14,R15)
234 [-]: GETGLOBAL R12 K19      ; R12 := 0xae91e43b
235 [-]: SELF      R12 R12 K20  ; R13 := R12; R12 := R12[0x67bc869f]
236 [-]: LOADK     R14 K60      ; R14 := "TimeOfDay.Label"
237 [-]: CONST     R15 77       ; R15 := 77.000000
238 [-]: CONST     R16 0        ; R16 := 0.000000
239 [-]: CALL      R12 5 1      ; R12(R13,R14,R15,R16)
240 [-]: RETURN    R0 1         ; return 


; Function #34:
;
; Name:            
; Defined at line: 876
; #Upvalues:       0
; #Parameters:     3
; Is_vararg:       0
; Max Stack Size:  10

  1 [-]: GETGLOBAL R3 K0        ; R3 := 0xae91e43b
  2 [-]: SELF      R3 R3 K1     ; R4 := R3; R3 := R3[0x91a24e4b]
  3 [-]: MOVE      R5 R0        ; R5 := R0
  4 [-]: CONST     R6 0         ; R6 := 0.000000
  5 [-]: CALL      R3 4 2       ; R3 := R3(R4,R5,R6)
  6 [-]: GETGLOBAL R4 K0        ; R4 := 0xae91e43b
  7 [-]: SELF      R4 R4 K1     ; R5 := R4; R4 := R4[0x91a24e4b]
  8 [-]: MOVE      R6 R0        ; R6 := R0
  9 [-]: CONST     R7 1         ; R7 := 1.000000
 10 [-]: CALL      R4 4 2       ; R4 := R4(R5,R6,R7)
 11 [-]: GETGLOBAL R5 K0        ; R5 := 0xae91e43b
 12 [-]: SELF      R5 R5 K1     ; R6 := R5; R5 := R5[0x91a24e4b]
 13 [-]: MOVE      R7 R0        ; R7 := R0
 14 [-]: CONST     R8 12        ; R8 := 12.000000
 15 [-]: CALL      R5 4 2       ; R5 := R5(R6,R7,R8)
 16 [-]: ADD       R5 R3 R5     ; R5 := R3 + R5
 17 [-]: GETGLOBAL R6 K0        ; R6 := 0xae91e43b
 18 [-]: SELF      R6 R6 K1     ; R7 := R6; R6 := R6[0x91a24e4b]
 19 [-]: MOVE      R8 R0        ; R8 := R0
 20 [-]: CONST     R9 13        ; R9 := 13.000000
 21 [-]: CALL      R6 4 2       ; R6 := R6(R7,R8,R9)
 22 [-]: ADD       R6 R4 R6     ; R6 := R4 + R6
 23 [-]: LE        0 R3 R1      ; if R3 > R1 then PC := 31
 24 [-]: JMP       31           ; PC := 31
 25 [-]: LE        0 R1 R5      ; if R1 > R5 then PC := 31
 26 [-]: JMP       31           ; PC := 31
 27 [-]: LE        0 R4 R2      ; if R4 > R2 then PC := 31
 28 [-]: JMP       31           ; PC := 31
 29 [-]: LE        1 R2 R6      ; if R2 <= R6 then PC := 32
 30 [-]: JMP       32           ; PC := 32
 31 [-]: LOADKB    R7 0 1       ; R7 := false; PC := 32
 32 [-]: LOADKB    R7 1 0       ; R7 := true
 33 [-]: RETURN    R7 2         ; return R7
 34 [-]: RETURN    R0 1         ; return 


; Function #35:
;
; Name:            
; Defined at line: 886
; #Upvalues:       39
; #Parameters:     0
; Is_vararg:       0
; Max Stack Size:  12

  1 [-]: GETGLOBAL R0 K0        ; R0 := 0x7b998233
  2 [-]: GETGLOBAL R1 K1        ; R1 := 0xae91e43b
  3 [-]: CALL      R0 2 2       ; R0 := R0(R1)
  4 [-]: TEST      R0 1         ; if R0 then PC := 9
  5 [-]: JMP       9            ; PC := 9
  6 [-]: GETUPVAL  R0 U0        ; R0 := U0
  7 [-]: TEST      R0 1         ; if R0 then PC := 10
  8 [-]: JMP       10           ; PC := 10
  9 [-]: RETURN    R0 1         ; return 
 10 [-]: GETUPVAL  R0 U1        ; R0 := U1
 11 [-]: TEST      R0 0         ; if not R0 then PC := 17
 12 [-]: JMP       17           ; PC := 17
 13 [-]: GETGLOBAL R0 K1        ; R0 := 0xae91e43b
 14 [-]: SELF      R0 R0 K2     ; R1 := R0; R0 := R0[0x32302b4a]
 15 [-]: CALL      R0 2 1       ; R0(R1)
 16 [-]: RETURN    R0 1         ; return 
 17 [-]: GETGLOBAL R0 K3        ; R0 := _T
 18 [-]: GETTABLE  R0 R0 K4     ; R0 := R0["ForceMinimap"]
 19 [-]: TEST      R0 0         ; if not R0 then PC := 36
 20 [-]: JMP       36           ; PC := 36
 21 [-]: GETGLOBAL R0 K0        ; R0 := 0x7b998233
 22 [-]: GETGLOBAL R1 K5        ; R1 := 0xbe190284
 23 [-]: CALL      R0 2 2       ; R0 := R0(R1)
 24 [-]: TEST      R0 1         ; if R0 then PC := 36
 25 [-]: JMP       36           ; PC := 36
 26 [-]: GETGLOBAL R0 K6        ; R0 := 0x3d106989
 27 [-]: LOADK     R1 K7        ; R1 := "Forcing regular minimap"
 28 [-]: CALL      R0 2 1       ; R0(R1)
 29 [-]: GETGLOBAL R0 K5        ; R0 := 0xbe190284
 30 [-]: SELF      R0 R0 K8     ; R1 := R0; R0 := R0[0x603d0ebe]
 31 [-]: CALL      R0 2 1       ; R0(R1)
 32 [-]: GETGLOBAL R0 K1        ; R0 := 0xae91e43b
 33 [-]: SELF      R0 R0 K2     ; R1 := R0; R0 := R0[0x32302b4a]
 34 [-]: CALL      R0 2 1       ; R0(R1)
 35 [-]: RETURN    R0 1         ; return 
 36 [-]: GETGLOBAL R0 K0        ; R0 := 0x7b998233
 37 [-]: GETGLOBAL R1 K3        ; R1 := _T
 38 [-]: GETTABLE  R1 R1 K9     ; R1 := R1["CommanderMap"]
 39 [-]: CALL      R0 2 2       ; R0 := R0(R1)
 40 [-]: NOT       R0 R0        ; R0 :=  R0
 41 [-]: GETUPVAL  R1 U2        ; R1 := U2
 42 [-]: EQ        1 R0 R1      ; if R0 == R1 then PC := 64
 43 [-]: JMP       64           ; PC := 64
 44 [-]: GETGLOBAL R0 K0        ; R0 := 0x7b998233
 45 [-]: GETGLOBAL R1 K3        ; R1 := _T
 46 [-]: GETTABLE  R1 R1 K9     ; R1 := R1["CommanderMap"]
 47 [-]: CALL      R0 2 2       ; R0 := R0(R1)
 48 [-]: NOT       R0 R0        ; R0 :=  R0
 49 [-]: SETUPVAL  R0 U2        ; U82 := R2
 50 [-]: GETGLOBAL R0 K1        ; R0 := 0xae91e43b
 51 [-]: SELF      R0 R0 K10    ; R1 := R0; R0 := R0[0xaade900e]
 52 [-]: LOADK     R2 K11       ; R2 := "_root"
 53 [-]: CONST     R3 11        ; R3 := 11.000000
 54 [-]: GETUPVAL  R4 U2        ; R4 := U2
 55 [-]: EQ        1 R4 K12     ; if R4 == true then PC := 61
 56 [-]: JMP       61           ; PC := 61
 57 [-]: GETGLOBAL R4 K3        ; R4 := _T
 58 [-]: GETTABLE  R4 R4 K13    ; R4 := R4["DisableMiniMap"]
 59 [-]: EQ        0 R4 K12     ; if R4 ~= true then PC := 62
 60 [-]: JMP       62           ; PC := 62
 61 [-]: LOADKB    R4 0 1       ; R4 := false; PC := 62
 62 [-]: LOADKB    R4 1 0       ; R4 := true
 63 [-]: CALL      R0 5 1       ; R0(R1,R2,R3,R4)
 64 [-]: GETUPVAL  R0 U2        ; R0 := U2
 65 [-]: EQ        0 R0 K12     ; if R0 ~= true then PC := 68
 66 [-]: JMP       68           ; PC := 68
 67 [-]: RETURN    R0 1         ; return 
 68 [-]: GETGLOBAL R0 K3        ; R0 := _T
 69 [-]: GETTABLE  R0 R0 K14    ; R0 := R0["ArsenalOpen"]
 70 [-]: TEST      R0 1         ; if R0 then PC := 94
 71 [-]: JMP       94           ; PC := 94
 72 [-]: GETGLOBAL R0 K3        ; R0 := _T
 73 [-]: GETTABLE  R0 R0 K15    ; R0 := R0["ArsenalUpgradeOpen"]
 74 [-]: TEST      R0 1         ; if R0 then PC := 94
 75 [-]: JMP       94           ; PC := 94
 76 [-]: GETGLOBAL R0 K3        ; R0 := _T
 77 [-]: GETTABLE  R0 R0 K16    ; R0 := R0["ModScreenOpen"]
 78 [-]: TEST      R0 1         ; if R0 then PC := 94
 79 [-]: JMP       94           ; PC := 94
 80 [-]: GETGLOBAL R0 K0        ; R0 := 0x7b998233
 81 [-]: GETGLOBAL R1 K17       ; R1 := 0x89326c93
 82 [-]: CALL      R0 2 2       ; R0 := R0(R1)
 83 [-]: TEST      R0 1         ; if R0 then PC := 92
 84 [-]: JMP       92           ; PC := 92
 85 [-]: GETGLOBAL R0 K0        ; R0 := 0x7b998233
 86 [-]: GETGLOBAL R1 K17       ; R1 := 0x89326c93
 87 [-]: SELF      R1 R1 K18    ; R2 := R1; R1 := R1[0xdd25e9d1]
 88 [-]: CALL      R1 2 0       ; R1,... := R1(R2)
 89 [-]: CALL      R0 0 2       ; R0 := R0(R1,...)
 90 [-]: NOT       R0 R0        ; R0 :=  R0
 91 [-]: JMP       94           ; PC := 94
 92 [-]: LOADKB    R0 0 1       ; R0 := false; PC := 93
 93 [-]: LOADKB    R0 1 0       ; R0 := true
 94 [-]: GETUPVAL  R1 U3        ; R1 := U3
 95 [-]: EQ        1 R0 R1      ; if R0 == R1 then PC := 102
 96 [-]: JMP       102          ; PC := 102
 97 [-]: SETUPVAL  R0 U3        ; U82 := R3
 98 [-]: GETGLOBAL R1 K1        ; R1 := 0xae91e43b
 99 [-]: SELF      R1 R1 K19    ; R2 := R1; R1 := R1[0x368ad758]
100 [-]: NOT       R3 R0        ; R3 :=  R0
101 [-]: CALL      R1 3 1       ; R1(R2,R3)
102 [-]: GETGLOBAL R1 K0        ; R1 := 0x7b998233
103 [-]: GETGLOBAL R2 K17       ; R2 := 0x89326c93
104 [-]: CALL      R1 2 2       ; R1 := R1(R2)
105 [-]: TEST      R1 1         ; if R1 then PC := 159
106 [-]: JMP       159          ; PC := 159
107 [-]: GETGLOBAL R1 K17       ; R1 := 0x89326c93
108 [-]: SELF      R1 R1 K18    ; R2 := R1; R1 := R1[0xdd25e9d1]
109 [-]: CALL      R1 2 2       ; R1 := R1(R2)
110 [-]: TEST      R1 0         ; if not R1 then PC := 113
111 [-]: JMP       113          ; PC := 113
112 [-]: RETURN    R0 1         ; return 
113 [-]: GETGLOBAL R1 K0        ; R1 := 0x7b998233
114 [-]: GETUPVAL  R2 U4        ; R2 := U4
115 [-]: CALL      R1 2 2       ; R1 := R1(R2)
116 [-]: TEST      R1 0         ; if not R1 then PC := 125
117 [-]: JMP       125          ; PC := 125
118 [-]: GETUPVAL  R1 U5        ; R1 := U5
119 [-]: TEST      R1 0         ; if not R1 then PC := 125
120 [-]: JMP       125          ; PC := 125
121 [-]: LOADKB    R1 0 0       ; R1 := false
122 [-]: SETUPVAL  R1 U5        ; U82 := R5
123 [-]: GETUPVAL  R1 U6        ; R1 := U6
124 [-]: CALL      R1 1 1       ; R1()
125 [-]: GETUPVAL  R1 U5        ; R1 := U5
126 [-]: TEST      R1 1         ; if R1 then PC := 159
127 [-]: JMP       159          ; PC := 159
128 [-]: GETGLOBAL R1 K17       ; R1 := 0x89326c93
129 [-]: SELF      R1 R1 K20    ; R2 := R1; R1 := R1[0xded7d5cd]
130 [-]: CALL      R1 2 2       ; R1 := R1(R2)
131 [-]: GETGLOBAL R2 K0        ; R2 := 0x7b998233
132 [-]: MOVE      R3 R1        ; R3 := R1
133 [-]: CALL      R2 2 2       ; R2 := R2(R3)
134 [-]: TEST      R2 1         ; if R2 then PC := 159
135 [-]: JMP       159          ; PC := 159
136 [-]: GETGLOBAL R2 K0        ; R2 := 0x7b998233
137 [-]: GETTABLE  R3 R1 K21    ; R3 := R1[1.000000]
138 [-]: CALL      R2 2 2       ; R2 := R2(R3)
139 [-]: TEST      R2 1         ; if R2 then PC := 159
140 [-]: JMP       159          ; PC := 159
141 [-]: GETTABLE  R2 R1 K21    ; R2 := R1[1.000000]
142 [-]: SELF      R2 R2 K22    ; R3 := R2; R2 := R2[0xbb610e5b]
143 [-]: CALL      R2 2 2       ; R2 := R2(R3)
144 [-]: SETUPVAL  R2 U4        ; U82 := R4
145 [-]: GETGLOBAL R2 K0        ; R2 := 0x7b998233
146 [-]: GETUPVAL  R3 U4        ; R3 := U4
147 [-]: CALL      R2 2 2       ; R2 := R2(R3)
148 [-]: TEST      R2 1         ; if R2 then PC := 159
149 [-]: JMP       159          ; PC := 159
150 [-]: GETGLOBAL R2 K0        ; R2 := 0x7b998233
151 [-]: GETUPVAL  R3 U4        ; R3 := U4
152 [-]: SELF      R3 R3 K23    ; R4 := R3; R3 := R3[0x5e651723]
153 [-]: CALL      R3 2 0       ; R3,... := R3(R4)
154 [-]: CALL      R2 0 2       ; R2 := R2(R3,...)
155 [-]: TEST      R2 1         ; if R2 then PC := 159
156 [-]: JMP       159          ; PC := 159
157 [-]: GETUPVAL  R2 U7        ; R2 := U7
158 [-]: CALL      R2 1 1       ; R2()
159 [-]: GETGLOBAL R2 K1        ; R2 := 0xae91e43b
160 [-]: SELF      R2 R2 K24    ; R3 := R2; R2 := R2[0x8a8c8d5a]
161 [-]: GETGLOBAL R4 K25       ; R4 := 0xb693b6c1
162 [-]: CALL      R4 1 0       ; R4,... := R4()
163 [-]: CALL      R2 0 1       ; R2(R3,...)
164 [-]: GETGLOBAL R2 K0        ; R2 := 0x7b998233
165 [-]: GETUPVAL  R3 U8        ; R3 := U8
166 [-]: CALL      R2 2 2       ; R2 := R2(R3)
167 [-]: TEST      R2 1         ; if R2 then PC := 174
168 [-]: JMP       174          ; PC := 174
169 [-]: GETUPVAL  R2 U8        ; R2 := U8
170 [-]: SELF      R2 R2 K26    ; R3 := R2; R2 := R2[0xfaa69527]
171 [-]: GETGLOBAL R4 K27       ; R4 := 0x67652851
172 [-]: CALL      R4 1 0       ; R4,... := R4()
173 [-]: CALL      R2 0 1       ; R2(R3,...)
174 [-]: GETUPVAL  R2 U9        ; R2 := U9
175 [-]: TEST      R2 1         ; if R2 then PC := 190
176 [-]: JMP       190          ; PC := 190
177 [-]: GETUPVAL  R2 U10       ; R2 := U10
178 [-]: TEST      R2 0         ; if not R2 then PC := 231
179 [-]: JMP       231          ; PC := 231
180 [-]: GETGLOBAL R2 K0        ; R2 := 0x7b998233
181 [-]: GETUPVAL  R3 U11       ; R3 := U11
182 [-]: CALL      R2 2 2       ; R2 := R2(R3)
183 [-]: TEST      R2 1         ; if R2 then PC := 231
184 [-]: JMP       231          ; PC := 231
185 [-]: GETUPVAL  R2 U11       ; R2 := U11
186 [-]: SELF      R2 R2 K28    ; R3 := R2; R2 := R2[0xec943d0f]
187 [-]: CALL      R2 2 2       ; R2 := R2(R3)
188 [-]: TEST      R2 0         ; if not R2 then PC := 231
189 [-]: JMP       231          ; PC := 231
190 [-]: GETUPVAL  R2 U12       ; R2 := U12
191 [-]: TEST      R2 0         ; if not R2 then PC := 215
192 [-]: JMP       215          ; PC := 215
193 [-]: GETUPVAL  R2 U9        ; R2 := U9
194 [-]: TEST      R2 1         ; if R2 then PC := 213
195 [-]: JMP       213          ; PC := 213
196 [-]: GETUPVAL  R2 U13       ; R2 := U13
197 [-]: TEST      R2 1         ; if R2 then PC := 213
198 [-]: JMP       213          ; PC := 213
199 [-]: LOADKB    R2 1 0       ; R2 := true
200 [-]: SETUPVAL  R2 U13       ; U82 := R13
201 [-]: GETGLOBAL R2 K29       ; R2 := 0x25312c9b
202 [-]: GETGLOBAL R3 K1        ; R3 := 0xae91e43b
203 [-]: LOADK     R4 K30       ; R4 := "TimeOfDay"
204 [-]: CONST     R5 8         ; R5 := 8.000000
205 [-]: NEWTABLE  R6 1 0       ; R6 := {}
206 [-]: CONST     R7 10        ; R7 := 10.000000
207 [-]: SETLIST   R6 1 1       ; R6[(1-1)*FPF+i] := R(6+i), 1 <= i <= 1
208 [-]: NEWTABLE  R7 1 0       ; R7 := {}
209 [-]: CONST     R8 100       ; R8 := 100.000000
210 [-]: SETLIST   R7 1 1       ; R7[(1-1)*FPF+i] := R(7+i), 1 <= i <= 1
211 [-]: LOADK     R8 K32       ; R8 := 0.300000
212 [-]: CALL      R2 7 1       ; R2(R3,R4,R5,R6,R7,R8)
213 [-]: GETUPVAL  R2 U14       ; R2 := U14
214 [-]: CALL      R2 1 1       ; R2()
215 [-]: GETGLOBAL R2 K0        ; R2 := 0x7b998233
216 [-]: GETUPVAL  R3 U15       ; R3 := U15
217 [-]: CALL      R2 2 2       ; R2 := R2(R3)
218 [-]: TEST      R2 1         ; if R2 then PC := 248
219 [-]: JMP       248          ; PC := 248
220 [-]: GETGLOBAL R2 K0        ; R2 := 0x7b998233
221 [-]: GETUPVAL  R3 U15       ; R3 := U15
222 [-]: GETTABLE  R3 R3 K33    ; R3 := R3["mInstance"]
223 [-]: CALL      R2 2 2       ; R2 := R2(R3)
224 [-]: TEST      R2 1         ; if R2 then PC := 248
225 [-]: JMP       248          ; PC := 248
226 [-]: GETUPVAL  R2 U15       ; R2 := U15
227 [-]: SELF      R2 R2 K26    ; R3 := R2; R2 := R2[0xfaa69527]
228 [-]: CONST     R4 0         ; R4 := 0.000000
229 [-]: CALL      R2 3 1       ; R2(R3,R4)
230 [-]: JMP       248          ; PC := 248
231 [-]: GETUPVAL  R2 U13       ; R2 := U13
232 [-]: TEST      R2 0         ; if not R2 then PC := 248
233 [-]: JMP       248          ; PC := 248
234 [-]: LOADKB    R2 0 0       ; R2 := false
235 [-]: SETUPVAL  R2 U13       ; U82 := R13
236 [-]: GETGLOBAL R2 K29       ; R2 := 0x25312c9b
237 [-]: GETGLOBAL R3 K1        ; R3 := 0xae91e43b
238 [-]: LOADK     R4 K30       ; R4 := "TimeOfDay"
239 [-]: CONST     R5 8         ; R5 := 8.000000
240 [-]: NEWTABLE  R6 1 0       ; R6 := {}
241 [-]: CONST     R7 10        ; R7 := 10.000000
242 [-]: SETLIST   R6 1 1       ; R6[(1-1)*FPF+i] := R(6+i), 1 <= i <= 1
243 [-]: NEWTABLE  R7 1 0       ; R7 := {}
244 [-]: CONST     R8 0         ; R8 := 0.000000
245 [-]: SETLIST   R7 1 1       ; R7[(1-1)*FPF+i] := R(7+i), 1 <= i <= 1
246 [-]: LOADK     R8 K32       ; R8 := 0.300000
247 [-]: CALL      R2 7 1       ; R2(R3,R4,R5,R6,R7,R8)
248 [-]: GETGLOBAL R2 K3        ; R2 := _T
249 [-]: GETTABLE  R2 R2 K13    ; R2 := R2["DisableMiniMap"]
250 [-]: GETUPVAL  R3 U16       ; R3 := U16
251 [-]: EQ        1 R3 R2      ; if R3 == R2 then PC := 263
252 [-]: JMP       263          ; PC := 263
253 [-]: SETUPVAL  R2 U16       ; U82 := R16
254 [-]: GETGLOBAL R3 K1        ; R3 := 0xae91e43b
255 [-]: SELF      R3 R3 K10    ; R4 := R3; R3 := R3[0xaade900e]
256 [-]: LOADK     R5 K11       ; R5 := "_root"
257 [-]: CONST     R6 11        ; R6 := 11.000000
258 [-]: EQ        0 R2 K12     ; if R2 ~= true then PC := 261
259 [-]: JMP       261          ; PC := 261
260 [-]: LOADKB    R7 0 1       ; R7 := false; PC := 261
261 [-]: LOADKB    R7 1 0       ; R7 := true
262 [-]: CALL      R3 5 1       ; R3(R4,R5,R6,R7)
263 [-]: TEST      R2 1         ; if R2 then PC := 319
264 [-]: JMP       319          ; PC := 319
265 [-]: GETGLOBAL R3 K0        ; R3 := 0x7b998233
266 [-]: GETUPVAL  R4 U17       ; R4 := U17
267 [-]: CALL      R3 2 2       ; R3 := R3(R4)
268 [-]: TEST      R3 0         ; if not R3 then PC := 279
269 [-]: JMP       279          ; PC := 279
270 [-]: GETGLOBAL R3 K0        ; R3 := 0x7b998233
271 [-]: GETGLOBAL R4 K5        ; R4 := 0xbe190284
272 [-]: CALL      R3 2 2       ; R3 := R3(R4)
273 [-]: TEST      R3 1         ; if R3 then PC := 279
274 [-]: JMP       279          ; PC := 279
275 [-]: GETGLOBAL R3 K5        ; R3 := 0xbe190284
276 [-]: SELF      R3 R3 K34    ; R4 := R3; R3 := R3[0x33307f92]
277 [-]: CALL      R3 2 2       ; R3 := R3(R4)
278 [-]: SETUPVAL  R3 U17       ; U82 := R17
279 [-]: GETGLOBAL R3 K0        ; R3 := 0x7b998233
280 [-]: GETUPVAL  R4 U17       ; R4 := U17
281 [-]: CALL      R3 2 2       ; R3 := R3(R4)
282 [-]: TEST      R3 1         ; if R3 then PC := 319
283 [-]: JMP       319          ; PC := 319
284 [-]: GETUPVAL  R3 U18       ; R3 := U18
285 [-]: TEST      R3 1         ; if R3 then PC := 319
286 [-]: JMP       319          ; PC := 319
287 [-]: GETUPVAL  R3 U17       ; R3 := U17
288 [-]: SELF      R3 R3 K35    ; R4 := R3; R3 := R3[0xd4cc05b4]
289 [-]: CALL      R3 2 2       ; R3 := R3(R4)
290 [-]: GETUPVAL  R4 U19       ; R4 := U19
291 [-]: EQ        1 R4 R3      ; if R4 == R3 then PC := 298
292 [-]: JMP       298          ; PC := 298
293 [-]: SETUPVAL  R3 U19       ; U82 := R19
294 [-]: GETGLOBAL R4 K1        ; R4 := 0xae91e43b
295 [-]: SELF      R4 R4 K19    ; R5 := R4; R4 := R4[0x368ad758]
296 [-]: GETUPVAL  R6 U19       ; R6 := U19
297 [-]: CALL      R4 3 1       ; R4(R5,R6)
298 [-]: GETUPVAL  R4 U17       ; R4 := U17
299 [-]: SELF      R4 R4 K36    ; R5 := R4; R4 := R4[0x91a24e4b]
300 [-]: LOADK     R6 K11       ; R6 := "_root"
301 [-]: CONST     R7 10        ; R7 := 10.000000
302 [-]: CALL      R4 4 2       ; R4 := R4(R5,R6,R7)
303 [-]: GETUPVAL  R5 U20       ; R5 := U20
304 [-]: EQ        1 R5 R4      ; if R5 == R4 then PC := 319
305 [-]: JMP       319          ; PC := 319
306 [-]: SETUPVAL  R4 U20       ; U82 := R20
307 [-]: GETGLOBAL R5 K1        ; R5 := 0xae91e43b
308 [-]: SELF      R5 R5 K37    ; R6 := R5; R5 := R5[0xbf8f0712]
309 [-]: LOADK     R7 K11       ; R7 := "_root"
310 [-]: CALL      R5 3 2       ; R5 := R5(R6,R7)
311 [-]: TEST      R5 1         ; if R5 then PC := 319
312 [-]: JMP       319          ; PC := 319
313 [-]: GETGLOBAL R5 K1        ; R5 := 0xae91e43b
314 [-]: SELF      R5 R5 K38    ; R6 := R5; R5 := R5[0x67bc869f]
315 [-]: LOADK     R7 K11       ; R7 := "_root"
316 [-]: CONST     R8 10        ; R8 := 10.000000
317 [-]: MOVE      R9 R4        ; R9 := R4
318 [-]: CALL      R5 5 1       ; R5(R6,R7,R8,R9)
319 [-]: GETUPVAL  R5 U21       ; R5 := U21
320 [-]: GETGLOBAL R6 K3        ; R6 := _T
321 [-]: GETTABLE  R6 R6 K39    ; R6 := R6["gSelectedNodeName"]
322 [-]: EQ        1 R6 K40     ; if R6 == "DojoHub_HUB" then PC := 325
323 [-]: JMP       325          ; PC := 325
324 [-]: LOADKB    R6 0 1       ; R6 := false; PC := 325
325 [-]: LOADKB    R6 1 0       ; R6 := true
326 [-]: EQ        0 R5 R6      ; if R5 ~= R6 then PC := 343
327 [-]: JMP       343          ; PC := 343
328 [-]: GETUPVAL  R5 U21       ; R5 := U21
329 [-]: NOT       R5 R5        ; R5 :=  R5
330 [-]: SETUPVAL  R5 U21       ; U82 := R21
331 [-]: GETGLOBAL R5 K1        ; R5 := 0xae91e43b
332 [-]: SELF      R5 R5 K10    ; R6 := R5; R5 := R5[0xaade900e]
333 [-]: LOADK     R7 K41       ; R7 := "MiniMapContainer"
334 [-]: CONST     R8 11        ; R8 := 11.000000
335 [-]: GETUPVAL  R9 U21       ; R9 := U21
336 [-]: CALL      R5 5 1       ; R5(R6,R7,R8,R9)
337 [-]: GETGLOBAL R5 K1        ; R5 := 0xae91e43b
338 [-]: SELF      R5 R5 K10    ; R6 := R5; R5 := R5[0xaade900e]
339 [-]: LOADK     R7 K42       ; R7 := "MiniMapOverlayMsg"
340 [-]: CONST     R8 11        ; R8 := 11.000000
341 [-]: GETUPVAL  R9 U21       ; R9 := U21
342 [-]: CALL      R5 5 1       ; R5(R6,R7,R8,R9)
343 [-]: GETUPVAL  R5 U22       ; R5 := U22
344 [-]: TEST      R5 0         ; if not R5 then PC := 475
345 [-]: JMP       475          ; PC := 475
346 [-]: GETGLOBAL R5 K0        ; R5 := 0x7b998233
347 [-]: GETUPVAL  R6 U11       ; R6 := U11
348 [-]: CALL      R5 2 2       ; R5 := R5(R6)
349 [-]: TEST      R5 1         ; if R5 then PC := 475
350 [-]: JMP       475          ; PC := 475
351 [-]: GETUPVAL  R5 U9        ; R5 := U9
352 [-]: TEST      R5 0         ; if not R5 then PC := 451
353 [-]: JMP       451          ; PC := 451
354 [-]: GETUPVAL  R5 U23       ; R5 := U23
355 [-]: GETTABLE  R5 R5 K43    ; R5 := R5["mCurVal"]
356 [-]: GETUPVAL  R6 U24       ; R6 := U24
357 [-]: DIV       R7 K21 R5    ; R7 := 1.000000 / R5
358 [-]: SETTABLE  R6 K44 R7    ; R6["mDragMultiplier"] := R7
359 [-]: GETUPVAL  R6 U24       ; R6 := U24
360 [-]: GETTABLE  R6 R6 K45    ; R6 := R6["mDragSpeed"]
361 [-]: GETUPVAL  R7 U25       ; R7 := U25
362 [-]: GETTABLE  R7 R7 K46    ; R7 := R7["x"]
363 [-]: GETUPVAL  R8 U26       ; R8 := U26
364 [-]: GETUPVAL  R9 U23       ; R9 := U23
365 [-]: GETTABLE  R9 R9 K43    ; R9 := R9["mCurVal"]
366 [-]: MUL       R8 R8 R9     ; R8 := R8 * R9
367 [-]: DIV       R7 R7 R8     ; R7 := R7 / R8
368 [-]: SETTABLE  R6 K46 R7    ; R6["x"] := R7
369 [-]: GETUPVAL  R6 U24       ; R6 := U24
370 [-]: GETTABLE  R6 R6 K45    ; R6 := R6["mDragSpeed"]
371 [-]: GETUPVAL  R7 U25       ; R7 := U25
372 [-]: GETTABLE  R7 R7 K47    ; R7 := R7["y"]
373 [-]: GETUPVAL  R8 U26       ; R8 := U26
374 [-]: GETUPVAL  R9 U23       ; R9 := U23
375 [-]: GETTABLE  R9 R9 K43    ; R9 := R9["mCurVal"]
376 [-]: MUL       R8 R8 R9     ; R8 := R8 * R9
377 [-]: DIV       R7 R7 R8     ; R7 := R7 / R8
378 [-]: SETTABLE  R6 K47 R7    ; R6["y"] := R7
379 [-]: GETUPVAL  R6 U24       ; R6 := U24
380 [-]: SELF      R6 R6 K26    ; R7 := R6; R6 := R6[0xfaa69527]
381 [-]: GETGLOBAL R8 K27       ; R8 := 0x67652851
382 [-]: CALL      R8 1 0       ; R8,... := R8()
383 [-]: CALL      R6 0 1       ; R6(R7,...)
384 [-]: GETUPVAL  R6 U27       ; R6 := U27
385 [-]: EQ        1 R6 K48     ; if R6 == 0.000000 then PC := 406
386 [-]: JMP       406          ; PC := 406
387 [-]: GETUPVAL  R6 U23       ; R6 := U23
388 [-]: SELF      R6 R6 K49    ; R7 := R6; R6 := R6[0x188e2bee]
389 [-]: GETGLOBAL R8 K50       ; R8 := 0x42dcc9f5
390 [-]: GETUPVAL  R9 U23       ; R9 := U23
391 [-]: GETTABLE  R9 R9 K51    ; R9 := R9["mTargetVal"]
392 [-]: GETUPVAL  R10 U28      ; R10 := U28
393 [-]: GETUPVAL  R11 U27      ; R11 := U27
394 [-]: MUL       R10 R10 R11  ; R10 := R10 * R11
395 [-]: SUB       R9 R9 R10    ; R9 := R9 - R10
396 [-]: GETUPVAL  R10 U29      ; R10 := U29
397 [-]: GETUPVAL  R11 U30      ; R11 := U30
398 [-]: CALL      R8 4 0       ; R8,... := R8(R9,R10,R11)
399 [-]: CALL      R6 0 1       ; R6(R7,...)
400 [-]: GETUPVAL  R6 U31       ; R6 := U31
401 [-]: GETTABLE  R6 R6 K52    ; R6 := R6["IsVisible"]
402 [-]: TEST      R6 1         ; if R6 then PC := 406
403 [-]: JMP       406          ; PC := 406
404 [-]: CONST     R6 0         ; R6 := 0.000000
405 [-]: SETUPVAL  R6 U27       ; U82 := R27
406 [-]: GETUPVAL  R6 U23       ; R6 := U23
407 [-]: SELF      R6 R6 K26    ; R7 := R6; R6 := R6[0xfaa69527]
408 [-]: GETGLOBAL R8 K27       ; R8 := 0x67652851
409 [-]: CALL      R8 1 0       ; R8,... := R8()
410 [-]: CALL      R6 0 1       ; R6(R7,...)
411 [-]: GETUPVAL  R6 U23       ; R6 := U23
412 [-]: GETTABLE  R6 R6 K43    ; R6 := R6["mCurVal"]
413 [-]: EQ        1 R6 R5      ; if R6 == R5 then PC := 417
414 [-]: JMP       417          ; PC := 417
415 [-]: LOADKB    R6 1 0       ; R6 := true
416 [-]: SETUPVAL  R6 U32       ; U82 := R32
417 [-]: GETGLOBAL R6 K0        ; R6 := 0x7b998233
418 [-]: GETUPVAL  R7 U4        ; R7 := U4
419 [-]: CALL      R6 2 2       ; R6 := R6(R7)
420 [-]: TEST      R6 1         ; if R6 then PC := 451
421 [-]: JMP       451          ; PC := 451
422 [-]: GETUPVAL  R6 U4        ; R6 := U4
423 [-]: SELF      R6 R6 K53    ; R7 := R6; R6 := R6[0x4078bbf8]
424 [-]: GETUPVAL  R8 U33       ; R8 := U33
425 [-]: CALL      R6 3 1       ; R6(R7,R8)
426 [-]: GETUPVAL  R6 U34       ; R6 := U34
427 [-]: CALL      R6 1 1       ; R6()
428 [-]: GETUPVAL  R6 U35       ; R6 := U35
429 [-]: GETUPVAL  R7 U33       ; R7 := U33
430 [-]: GETTABLE  R7 R7 K46    ; R7 := R7["x"]
431 [-]: SETTABLE  R6 K46 R7    ; R6["x"] := R7
432 [-]: GETUPVAL  R6 U35       ; R6 := U35
433 [-]: GETUPVAL  R7 U33       ; R7 := U33
434 [-]: GETTABLE  R7 R7 K47    ; R7 := R7["y"]
435 [-]: SETTABLE  R6 K47 R7    ; R6["y"] := R7
436 [-]: GETUPVAL  R6 U35       ; R6 := U35
437 [-]: GETUPVAL  R7 U33       ; R7 := U33
438 [-]: GETTABLE  R7 R7 K54    ; R7 := R7["z"]
439 [-]: SETTABLE  R6 K54 R7    ; R6["z"] := R7
440 [-]: GETUPVAL  R6 U11       ; R6 := U11
441 [-]: SELF      R6 R6 K55    ; R7 := R6; R6 := R6[0x08c73127]
442 [-]: GETUPVAL  R8 U24       ; R8 := U24
443 [-]: GETTABLE  R8 R8 K56    ; R8 := R8["mCurrentCoords"]
444 [-]: GETTABLE  R8 R8 K46    ; R8 := R8["x"]
445 [-]: GETUPVAL  R9 U24       ; R9 := U24
446 [-]: GETTABLE  R9 R9 K56    ; R9 := R9["mCurrentCoords"]
447 [-]: GETTABLE  R9 R9 K47    ; R9 := R9["y"]
448 [-]: GETUPVAL  R10 U23      ; R10 := U23
449 [-]: GETTABLE  R10 R10 K43  ; R10 := R10["mCurVal"]
450 [-]: CALL      R6 5 1       ; R6(R7,R8,R9,R10)
451 [-]: GETUPVAL  R6 U11       ; R6 := U11
452 [-]: SELF      R6 R6 K57    ; R7 := R6; R6 := R6[0x24d502bc]
453 [-]: GETUPVAL  R8 U36       ; R8 := U36
454 [-]: TEST      R8 1         ; if R8 then PC := 461
455 [-]: JMP       461          ; PC := 461
456 [-]: GETUPVAL  R8 U9        ; R8 := U9
457 [-]: EQ        1 R8 K12     ; if R8 == true then PC := 460
458 [-]: JMP       460          ; PC := 460
459 [-]: LOADKB    R8 0 1       ; R8 := false; PC := 460
460 [-]: LOADKB    R8 1 0       ; R8 := true
461 [-]: CALL      R6 3 1       ; R6(R7,R8)
462 [-]: GETUPVAL  R6 U11       ; R6 := U11
463 [-]: SELF      R6 R6 K58    ; R7 := R6; R6 := R6[0x68365ce7]
464 [-]: GETGLOBAL R8 K59       ; R8 := 0xde65e390
465 [-]: GETGLOBAL R9 K60       ; R9 := 0x8a46a849
466 [-]: CALL      R6 4 1       ; R6(R7,R8,R9)
467 [-]: GETGLOBAL R6 K0        ; R6 := 0x7b998233
468 [-]: GETUPVAL  R7 U4        ; R7 := U4
469 [-]: CALL      R6 2 2       ; R6 := R6(R7)
470 [-]: TEST      R6 1         ; if R6 then PC := 475
471 [-]: JMP       475          ; PC := 475
472 [-]: GETUPVAL  R6 U37       ; R6 := U37
473 [-]: GETUPVAL  R7 U4        ; R7 := U4
474 [-]: CALL      R6 2 1       ; R6(R7)
475 [-]: GETGLOBAL R6 K61       ; R6 := 0x34291f5c
476 [-]: GETTABLE  R6 R6 K62    ; R6 := R6[0xe6b41adb]
477 [-]: CALL      R6 1 2       ; R6 := R6()
478 [-]: TEST      R6 0         ; if not R6 then PC := 490
479 [-]: JMP       490          ; PC := 490
480 [-]: GETUPVAL  R6 U38       ; R6 := U38
481 [-]: TEST      R6 0         ; if not R6 then PC := 490
482 [-]: JMP       490          ; PC := 490
483 [-]: GETUPVAL  R6 U24       ; R6 := U24
484 [-]: GETTABLE  R6 R6 K63    ; R6 := R6["mDragging"]
485 [-]: EQ        0 R6 K64     ; if R6 ~= false then PC := 490
486 [-]: JMP       490          ; PC := 490
487 [-]: GETUPVAL  R6 U24       ; R6 := U24
488 [-]: SELF      R6 R6 K65    ; R7 := R6; R6 := R6[0xd033d908]
489 [-]: CALL      R6 2 1       ; R6(R7)
490 [-]: RETURN    R0 1         ; return 


; Function #36:
;
; Name:            
; Defined at line: 1038
; #Upvalues:       4
; #Parameters:     4
; Is_vararg:       0
; Max Stack Size:  8

  1 [-]: GETUPVAL  R4 U0        ; R4 := U0
  2 [-]: CALL      R4 1 1       ; R4()
  3 [-]: GETGLOBAL R4 K0        ; R4 := 0x7b998233
  4 [-]: GETUPVAL  R5 U1        ; R5 := U1
  5 [-]: CALL      R4 2 2       ; R4 := R4(R5)
  6 [-]: TEST      R4 1         ; if R4 then PC := 13
  7 [-]: JMP       13           ; PC := 13
  8 [-]: GETUPVAL  R4 U1        ; R4 := U1
  9 [-]: SELF      R4 R4 K1     ; R5 := R4; R4 := R4[0xfaa69527]
 10 [-]: MOVE      R6 R0        ; R6 := R0
 11 [-]: MOVE      R7 R1        ; R7 := R1
 12 [-]: CALL      R4 4 1       ; R4(R5,R6,R7)
 13 [-]: GETUPVAL  R4 U2        ; R4 := U2
 14 [-]: CALL      R4 1 1       ; R4()
 15 [-]: GETUPVAL  R4 U3        ; R4 := U3
 16 [-]: CALL      R4 1 1       ; R4()
 17 [-]: RETURN    R0 1         ; return 


; Function #37:
;
; Name:            
; Defined at line: 1049
; #Upvalues:       8
; #Parameters:     2
; Is_vararg:       0
; Max Stack Size:  12

  1 [-]: GETGLOBAL R2 K0        ; R2 := 0x7b998233
  2 [-]: GETUPVAL  R3 U0        ; R3 := U0
  3 [-]: CALL      R2 2 2       ; R2 := R2(R3)
  4 [-]: TEST      R2 1         ; if R2 then PC := 9
  5 [-]: JMP       9            ; PC := 9
  6 [-]: GETUPVAL  R2 U0        ; R2 := U0
  7 [-]: SELF      R2 R2 K1     ; R3 := R2; R2 := R2[0xec943d0f]
  8 [-]: CALL      R2 2 2       ; R2 := R2(R3)
  9 [-]: TEST      R2 1         ; if R2 then PC := 98
 10 [-]: JMP       98           ; PC := 98
 11 [-]: GETUPVAL  R3 U0        ; R3 := U0
 12 [-]: SELF      R3 R3 K2     ; R4 := R3; R3 := R3[0x450e5a70]
 13 [-]: CALL      R3 2 2       ; R3 := R3(R4)
 14 [-]: GETUPVAL  R4 U1        ; R4 := U1
 15 [-]: GETTABLE  R4 R4 K3     ; R4 := R4["mCurVal"]
 16 [-]: MUL       R3 R3 R4     ; R3 := R3 * R4
 17 [-]: GETUPVAL  R4 U1        ; R4 := U1
 18 [-]: GETTABLE  R4 R4 K3     ; R4 := R4["mCurVal"]
 19 [-]: GETGLOBAL R5 K4        ; R5 := 0xa421af95
 20 [-]: CALL      R5 1 2       ; R5 := R5()
 21 [-]: GETGLOBAL R6 K0        ; R6 := 0x7b998233
 22 [-]: GETUPVAL  R7 U2        ; R7 := U2
 23 [-]: CALL      R6 2 2       ; R6 := R6(R7)
 24 [-]: TEST      R6 1         ; if R6 then PC := 30
 25 [-]: JMP       30           ; PC := 30
 26 [-]: GETUPVAL  R6 U2        ; R6 := U2
 27 [-]: SELF      R6 R6 K5     ; R7 := R6; R6 := R6[0xd1586535]
 28 [-]: CALL      R6 2 2       ; R6 := R6(R7)
 29 [-]: MOVE      R5 R6        ; R5 := R6
 30 [-]: GETUPVAL  R6 U3        ; R6 := U3
 31 [-]: GETTABLE  R6 R6 K6     ; R6 := R6["x"]
 32 [-]: GETTABLE  R7 R5 K6     ; R7 := R5["x"]
 33 [-]: SUB       R6 R6 R7     ; R6 := R6 - R7
 34 [-]: MUL       R6 R3 R6     ; R6 := R3 * R6
 35 [-]: GETUPVAL  R7 U4        ; R7 := U4
 36 [-]: DIV       R7 R7 K7     ; R7 := R7 / 2.000000
 37 [-]: ADD       R6 R6 R7     ; R6 := R6 + R7
 38 [-]: GETUPVAL  R7 U5        ; R7 := U5
 39 [-]: GETTABLE  R7 R7 K8     ; R7 := R7["mCurrentCoords"]
 40 [-]: GETTABLE  R7 R7 K6     ; R7 := R7["x"]
 41 [-]: MUL       R7 R7 R4     ; R7 := R7 * R4
 42 [-]: ADD       R6 R6 R7     ; R6 := R6 + R7
 43 [-]: UNM       R7 R3        ; R7 :=  R3
 44 [-]: GETUPVAL  R8 U6        ; R8 := U6
 45 [-]: GETTABLE  R8 R8 K9     ; R8 := R8["z"]
 46 [-]: GETTABLE  R9 R5 K9     ; R9 := R5["z"]
 47 [-]: SUB       R8 R8 R9     ; R8 := R8 - R9
 48 [-]: MUL       R7 R7 R8     ; R7 := R7 * R8
 49 [-]: GETUPVAL  R8 U7        ; R8 := U7
 50 [-]: DIV       R8 R8 K7     ; R8 := R8 / 2.000000
 51 [-]: ADD       R7 R7 R8     ; R7 := R7 + R8
 52 [-]: GETUPVAL  R8 U5        ; R8 := U5
 53 [-]: GETTABLE  R8 R8 K8     ; R8 := R8["mCurrentCoords"]
 54 [-]: GETTABLE  R8 R8 K10    ; R8 := R8["y"]
 55 [-]: MUL       R8 R8 R4     ; R8 := R8 * R4
 56 [-]: ADD       R7 R7 R8     ; R7 := R7 + R8
 57 [-]: GETUPVAL  R8 U6        ; R8 := U6
 58 [-]: GETTABLE  R8 R8 K6     ; R8 := R8["x"]
 59 [-]: GETTABLE  R9 R5 K6     ; R9 := R5["x"]
 60 [-]: SUB       R8 R8 R9     ; R8 := R8 - R9
 61 [-]: MUL       R8 R3 R8     ; R8 := R3 * R8
 62 [-]: GETUPVAL  R9 U4        ; R9 := U4
 63 [-]: DIV       R9 R9 K7     ; R9 := R9 / 2.000000
 64 [-]: ADD       R8 R8 R9     ; R8 := R8 + R9
 65 [-]: GETUPVAL  R9 U5        ; R9 := U5
 66 [-]: GETTABLE  R9 R9 K8     ; R9 := R9["mCurrentCoords"]
 67 [-]: GETTABLE  R9 R9 K6     ; R9 := R9["x"]
 68 [-]: MUL       R9 R9 R4     ; R9 := R9 * R4
 69 [-]: ADD       R8 R8 R9     ; R8 := R8 + R9
 70 [-]: UNM       R9 R3        ; R9 :=  R3
 71 [-]: GETUPVAL  R10 U3       ; R10 := U3
 72 [-]: GETTABLE  R10 R10 K9   ; R10 := R10["z"]
 73 [-]: GETTABLE  R11 R5 K9    ; R11 := R5["z"]
 74 [-]: SUB       R10 R10 R11  ; R10 := R10 - R11
 75 [-]: MUL       R9 R9 R10    ; R9 := R9 * R10
 76 [-]: GETUPVAL  R10 U7       ; R10 := U7
 77 [-]: DIV       R10 R10 K7   ; R10 := R10 / 2.000000
 78 [-]: ADD       R9 R9 R10    ; R9 := R9 + R10
 79 [-]: GETUPVAL  R10 U5       ; R10 := U5
 80 [-]: GETTABLE  R10 R10 K8   ; R10 := R10["mCurrentCoords"]
 81 [-]: GETTABLE  R10 R10 K10  ; R10 := R10["y"]
 82 [-]: MUL       R10 R10 R4   ; R10 := R10 * R4
 83 [-]: ADD       R9 R9 R10    ; R9 := R9 + R10
 84 [-]: LT        1 R0 R6      ; if R0 < R6 then PC := 92
 85 [-]: JMP       92           ; PC := 92
 86 [-]: LT        1 R8 R0      ; if R8 < R0 then PC := 92
 87 [-]: JMP       92           ; PC := 92
 88 [-]: LT        1 R1 R7      ; if R1 < R7 then PC := 92
 89 [-]: JMP       92           ; PC := 92
 90 [-]: LT        0 R9 R1      ; if R9 >= R1 then PC := 95
 91 [-]: JMP       95           ; PC := 95
 92 [-]: LOADKB    R10 0 0      ; R10 := false
 93 [-]: RETURN    R10 2        ; return R10
 94 [-]: JMP       100          ; PC := 100
 95 [-]: LOADKB    R10 1 0      ; R10 := true
 96 [-]: RETURN    R10 2        ; return R10
 97 [-]: JMP       100          ; PC := 100
 98 [-]: LOADKB    R10 0 0      ; R10 := false
 99 [-]: RETURN    R10 2        ; return R10
100 [-]: RETURN    R0 1         ; return 


; Function #38:
;
; Name:            
; Defined at line: 1074
; #Upvalues:       3
; #Parameters:     1
; Is_vararg:       0
; Max Stack Size:  7

  1 [-]: GETGLOBAL R1 K0        ; R1 := 0x3d106989
  2 [-]: LOADK     R2 K1        ; R2 := "_MarkerRollOutCallback"
  3 [-]: MOVE      R3 R0        ; R3 := R0
  4 [-]: CONCAT    R2 R2 R3     ; R2 := R2 .. R3
  5 [-]: CALL      R1 2 1       ; R1(R2)
  6 [-]: GETGLOBAL R1 K2        ; R1 := 0x7b998233
  7 [-]: GETUPVAL  R2 U0        ; R2 := U0
  8 [-]: CALL      R1 2 2       ; R1 := R1(R2)
  9 [-]: TEST      R1 1         ; if R1 then PC := 46
 10 [-]: JMP       46           ; PC := 46
 11 [-]: GETGLOBAL R1 K2        ; R1 := 0x7b998233
 12 [-]: GETUPVAL  R2 U1        ; R2 := U1
 13 [-]: CALL      R1 2 2       ; R1 := R1(R2)
 14 [-]: TEST      R1 1         ; if R1 then PC := 46
 15 [-]: JMP       46           ; PC := 46
 16 [-]: GETUPVAL  R1 U1        ; R1 := U1
 17 [-]: GETTABLE  R1 R1 K3     ; R1 := R1["mEntity"]
 18 [-]: GETGLOBAL R2 K2        ; R2 := 0x7b998233
 19 [-]: MOVE      R3 R1        ; R3 := R1
 20 [-]: CALL      R2 2 2       ; R2 := R2(R3)
 21 [-]: TEST      R2 1         ; if R2 then PC := 46
 22 [-]: JMP       46           ; PC := 46
 23 [-]: SELF      R2 R1 K4     ; R3 := R1; R2 := R1[0xf2deaf69]
 24 [-]: GETGLOBAL R4 K5        ; R4 := gBaseMarkerInfoType
 25 [-]: CALL      R2 3 2       ; R2 := R2(R3,R4)
 26 [-]: TEST      R2 0         ; if not R2 then PC := 46
 27 [-]: JMP       46           ; PC := 46
 28 [-]: GETGLOBAL R2 K6        ; R2 := _T
 29 [-]: GETTABLE  R2 R2 K7     ; R2 := R2["DisableMarkerRollOutColor"]
 30 [-]: TEST      R2 1         ; if R2 then PC := 35
 31 [-]: JMP       35           ; PC := 35
 32 [-]: SELF      R2 R1 K8     ; R3 := R1; R2 := R1[0xffcb00d9]
 33 [-]: GETUPVAL  R4 U2        ; R4 := U2
 34 [-]: CALL      R2 3 1       ; R2(R3,R4)
 35 [-]: SELF      R2 R1 K9     ; R3 := R1; R2 := R1[0xbe612609]
 36 [-]: CALL      R2 2 2       ; R2 := R2(R3)
 37 [-]: EQ        1 R2 K10     ; if R2 == 1.000000 then PC := 46
 38 [-]: JMP       46           ; PC := 46
 39 [-]: SELF      R3 R1 K11    ; R4 := R1; R3 := R1[0xe00b9ae7]
 40 [-]: CALL      R3 2 2       ; R3 := R3(R4)
 41 [-]: GETTABLE  R3 R3 K12    ; R3 := R3["x"]
 42 [-]: DIV       R3 R3 R2     ; R3 := R3 / R2
 43 [-]: SELF      R4 R1 K13    ; R5 := R1; R4 := R1[0x351bfdeb]
 44 [-]: MOVE      R6 R3        ; R6 := R3
 45 [-]: CALL      R4 3 1       ; R4(R5,R6)
 46 [-]: GETGLOBAL R4 K6        ; R4 := _T
 47 [-]: SETTABLE  R4 K7 K14    ; R4["DisableMarkerRollOutColor"] := nil
 48 [-]: GETGLOBAL R4 K6        ; R4 := _T
 49 [-]: SETTABLE  R4 K15 K14   ; R4["gToolTip"] := nil
 50 [-]: LOADNIL   R4 R4        ; R4 := nil
 51 [-]: SETUPVAL  R4 U1        ; U82 := R1
 52 [-]: RETURN    R0 1         ; return 


; Function #39:
;
; Name:            
; Defined at line: 1095
; #Upvalues:       5
; #Parameters:     1
; Is_vararg:       0
; Max Stack Size:  10

  1 [-]: GETGLOBAL R1 K0        ; R1 := 0x34291f5c
  2 [-]: GETTABLE  R1 R1 K1     ; R1 := R1[0xe6b41adb]
  3 [-]: CALL      R1 1 2       ; R1 := R1()
  4 [-]: TEST      R1 0         ; if not R1 then PC := 14
  5 [-]: JMP       14           ; PC := 14
  6 [-]: GETGLOBAL R1 K2        ; R1 := 0x7b998233
  7 [-]: GETUPVAL  R2 U0        ; R2 := U0
  8 [-]: CALL      R1 2 2       ; R1 := R1(R2)
  9 [-]: TEST      R1 1         ; if R1 then PC := 14
 10 [-]: JMP       14           ; PC := 14
 11 [-]: GETUPVAL  R1 U1        ; R1 := U1
 12 [-]: MOVE      R2 R0        ; R2 := R0
 13 [-]: CALL      R1 2 1       ; R1(R2)
 14 [-]: GETGLOBAL R1 K2        ; R1 := 0x7b998233
 15 [-]: GETUPVAL  R2 U2        ; R2 := U2
 16 [-]: CALL      R1 2 2       ; R1 := R1(R2)
 17 [-]: TEST      R1 1         ; if R1 then PC := 73
 18 [-]: JMP       73           ; PC := 73
 19 [-]: GETUPVAL  R1 U2        ; R1 := U2
 20 [-]: SELF      R1 R1 K3     ; R2 := R1; R1 := R1[0x35786822]
 21 [-]: MOVE      R3 R0        ; R3 := R0
 22 [-]: CALL      R1 3 2       ; R1 := R1(R2,R3)
 23 [-]: GETTABLE  R2 R1 K4     ; R2 := R1["mVisible"]
 24 [-]: TEST      R2 0         ; if not R2 then PC := 73
 25 [-]: JMP       73           ; PC := 73
 26 [-]: SETUPVAL  R1 U0        ; U82 := R0
 27 [-]: GETUPVAL  R2 U3        ; R2 := U3
 28 [-]: GETTABLE  R2 R2 K5     ; R2 := R2[0x659d451f]
 29 [-]: GETGLOBAL R3 K6        ; R3 := 0x116f3965
 30 [-]: CALL      R2 2 1       ; R2(R3)
 31 [-]: GETTABLE  R2 R1 K7     ; R2 := R1["mEntity"]
 32 [-]: GETGLOBAL R3 K2        ; R3 := 0x7b998233
 33 [-]: MOVE      R4 R2        ; R4 := R2
 34 [-]: CALL      R3 2 2       ; R3 := R3(R4)
 35 [-]: TEST      R3 1         ; if R3 then PC := 73
 36 [-]: JMP       73           ; PC := 73
 37 [-]: SELF      R3 R2 K8     ; R4 := R2; R3 := R2[0xf2deaf69]
 38 [-]: GETGLOBAL R5 K9        ; R5 := gBaseMarkerInfoType
 39 [-]: CALL      R3 3 2       ; R3 := R3(R4,R5)
 40 [-]: TEST      R3 0         ; if not R3 then PC := 73
 41 [-]: JMP       73           ; PC := 73
 42 [-]: SELF      R3 R2 K10    ; R4 := R2; R3 := R2[0x99f7b4d5]
 43 [-]: CALL      R3 2 2       ; R3 := R3(R4)
 44 [-]: SETUPVAL  R3 U4        ; U82 := R4
 45 [-]: SELF      R3 R2 K11    ; R4 := R2; R3 := R2[0xffcb00d9]
 46 [-]: SELF      R5 R2 K12    ; R6 := R2; R5 := R2[0x1664c13c]
 47 [-]: CALL      R5 2 0       ; R5,... := R5(R6)
 48 [-]: CALL      R3 0 1       ; R3(R4,...)
 49 [-]: SELF      R3 R2 K13    ; R4 := R2; R3 := R2[0xbe612609]
 50 [-]: CALL      R3 2 2       ; R3 := R3(R4)
 51 [-]: EQ        1 R3 K14     ; if R3 == 1.000000 then PC := 60
 52 [-]: JMP       60           ; PC := 60
 53 [-]: SELF      R4 R2 K15    ; R5 := R2; R4 := R2[0xe00b9ae7]
 54 [-]: CALL      R4 2 2       ; R4 := R4(R5)
 55 [-]: GETTABLE  R4 R4 K16    ; R4 := R4["x"]
 56 [-]: MUL       R4 R4 R3     ; R4 := R4 * R3
 57 [-]: SELF      R5 R2 K17    ; R6 := R2; R5 := R2[0x351bfdeb]
 58 [-]: MOVE      R7 R4        ; R7 := R4
 59 [-]: CALL      R5 3 1       ; R5(R6,R7)
 60 [-]: SELF      R5 R2 K18    ; R6 := R2; R5 := R2[0x83ea6be7]
 61 [-]: CALL      R5 2 2       ; R5 := R5(R6)
 62 [-]: GETGLOBAL R6 K19       ; R6 := EMPTY_SYMBOL
 63 [-]: EQ        1 R5 R6      ; if R5 == R6 then PC := 73
 64 [-]: JMP       73           ; PC := 73
 65 [-]: GETGLOBAL R6 K20       ; R6 := _T
 66 [-]: GETGLOBAL R7 K22       ; R7 := 0x603636ad
 67 [-]: GETGLOBAL R8 K23       ; R8 := 0x64fb1586
 68 [-]: MOVE      R9 R5        ; R9 := R5
 69 [-]: CALL      R8 2 2       ; R8 := R8(R9)
 70 [-]: NEWTABLE  R9 0 0       ; R9 := {}
 71 [-]: CALL      R7 3 2       ; R7 := R7(R8,R9)
 72 [-]: SETTABLE  R6 K21 R7    ; R6["gToolTip"] := R7
 73 [-]: RETURN    R0 1         ; return 


; Function #40:
;
; Name:            
; Defined at line: 1122
; #Upvalues:       1
; #Parameters:     1
; Is_vararg:       0
; Max Stack Size:  3

  1 [-]: GETUPVAL  R1 U0        ; R1 := U0
  2 [-]: MOVE      R2 R0        ; R2 := R0
  3 [-]: CALL      R1 2 1       ; R1(R2)
  4 [-]: RETURN    R0 1         ; return 


; Function #41:
;
; Name:            
; Defined at line: 1126
; #Upvalues:       1
; #Parameters:     1
; Is_vararg:       0
; Max Stack Size:  3

  1 [-]: GETUPVAL  R1 U0        ; R1 := U0
  2 [-]: MOVE      R2 R0        ; R2 := R0
  3 [-]: CALL      R1 2 1       ; R1(R2)
  4 [-]: RETURN    R0 1         ; return 


; Function #42:
;
; Name:            
; Defined at line: 1130
; #Upvalues:       2
; #Parameters:     0
; Is_vararg:       0
; Max Stack Size:  4

  1 [-]: GETGLOBAL R0 K0        ; R0 := 0x7b998233
  2 [-]: GETUPVAL  R1 U0        ; R1 := U0
  3 [-]: CALL      R0 2 2       ; R0 := R0(R1)
  4 [-]: TEST      R0 1         ; if R0 then PC := 34
  5 [-]: JMP       34           ; PC := 34
  6 [-]: GETGLOBAL R0 K0        ; R0 := 0x7b998233
  7 [-]: GETGLOBAL R1 K1        ; R1 := _T
  8 [-]: GETTABLE  R1 R1 K2     ; R1 := R1["ActiveTacticalMarker"]
  9 [-]: CALL      R0 2 2       ; R0 := R0(R1)
 10 [-]: TEST      R0 0         ; if not R0 then PC := 34
 11 [-]: JMP       34           ; PC := 34
 12 [-]: GETUPVAL  R0 U1        ; R0 := U1
 13 [-]: GETTABLE  R0 R0 K3     ; R0 := R0[0x659d451f]
 14 [-]: GETGLOBAL R1 K4        ; R1 := 0x924390a3
 15 [-]: CALL      R0 2 1       ; R0(R1)
 16 [-]: GETUPVAL  R0 U0        ; R0 := U0
 17 [-]: GETTABLE  R0 R0 K5     ; R0 := R0["mEntity"]
 18 [-]: TEST      R0 0         ; if not R0 then PC := 34
 19 [-]: JMP       34           ; PC := 34
 20 [-]: SELF      R1 R0 K6     ; R2 := R0; R1 := R0[0xf2deaf69]
 21 [-]: GETGLOBAL R3 K7        ; R3 := gBaseMarkerInfoType
 22 [-]: CALL      R1 3 2       ; R1 := R1(R2,R3)
 23 [-]: TEST      R1 0         ; if not R1 then PC := 34
 24 [-]: JMP       34           ; PC := 34
 25 [-]: GETGLOBAL R1 K1        ; R1 := _T
 26 [-]: GETUPVAL  R2 U0        ; R2 := U0
 27 [-]: SETTABLE  R1 K2 R2     ; R1["ActiveTacticalMarker"] := R2
 28 [-]: SELF      R1 R0 K8     ; R2 := R0; R1 := R0[0x5191cbe0]
 29 [-]: CALL      R1 2 2       ; R1 := R1(R2)
 30 [-]: TEST      R1 1         ; if R1 then PC := 34
 31 [-]: JMP       34           ; PC := 34
 32 [-]: GETGLOBAL R1 K1        ; R1 := _T
 33 [-]: SETTABLE  R1 K2 K9     ; R1["ActiveTacticalMarker"] := nil
 34 [-]: RETURN    R0 1         ; return 


; Function #43:
;
; Name:            
; Defined at line: 1145
; #Upvalues:       2
; #Parameters:     1
; Is_vararg:       0
; Max Stack Size:  3

  1 [-]: GETGLOBAL R1 K0        ; R1 := 0x34291f5c
  2 [-]: GETTABLE  R1 R1 K1     ; R1 := R1[0xe6b41adb]
  3 [-]: CALL      R1 1 2       ; R1 := R1()
  4 [-]: TEST      R1 0         ; if not R1 then PC := 10
  5 [-]: JMP       10           ; PC := 10
  6 [-]: GETUPVAL  R1 U0        ; R1 := U0
  7 [-]: SELF      R1 R1 K2     ; R2 := R1; R1 := R1[0xcc5f3150]
  8 [-]: CALL      R1 2 1       ; R1(R2)
  9 [-]: RETURN    R0 1         ; return 
 10 [-]: GETUPVAL  R1 U1        ; R1 := U1
 11 [-]: CALL      R1 1 1       ; R1()
 12 [-]: RETURN    R0 1         ; return 


; Function #44:
;
; Name:            
; Defined at line: 1153
; #Upvalues:       3
; #Parameters:     1
; Is_vararg:       0
; Max Stack Size:  4

  1 [-]: GETGLOBAL R1 K0        ; R1 := 0x34291f5c
  2 [-]: GETTABLE  R1 R1 K1     ; R1 := R1[0xe6b41adb]
  3 [-]: CALL      R1 1 2       ; R1 := R1()
  4 [-]: TEST      R1 0         ; if not R1 then PC := 27
  5 [-]: JMP       27           ; PC := 27
  6 [-]: GETUPVAL  R1 U0        ; R1 := U0
  7 [-]: GETUPVAL  R2 U1        ; R2 := U1
  8 [-]: MOVE      R3 R0        ; R3 := R0
  9 [-]: CALL      R2 2 1       ; R2(R3)
 10 [-]: GETGLOBAL R2 K2        ; R2 := 0x7b998233
 11 [-]: GETUPVAL  R3 U0        ; R3 := U0
 12 [-]: CALL      R2 2 2       ; R2 := R2(R3)
 13 [-]: TEST      R2 1         ; if R2 then PC := 27
 14 [-]: JMP       27           ; PC := 27
 15 [-]: GETGLOBAL R2 K2        ; R2 := 0x7b998233
 16 [-]: MOVE      R3 R1        ; R3 := R1
 17 [-]: CALL      R2 2 2       ; R2 := R2(R3)
 18 [-]: TEST      R2 1         ; if R2 then PC := 27
 19 [-]: JMP       27           ; PC := 27
 20 [-]: GETUPVAL  R2 U0        ; R2 := U0
 21 [-]: GETTABLE  R2 R2 K3     ; R2 := R2["mEntity"]
 22 [-]: GETTABLE  R3 R1 K3     ; R3 := R1["mEntity"]
 23 [-]: EQ        0 R2 R3      ; if R2 ~= R3 then PC := 27
 24 [-]: JMP       27           ; PC := 27
 25 [-]: GETUPVAL  R2 U2        ; R2 := U2
 26 [-]: CALL      R2 1 1       ; R2()
 27 [-]: RETURN    R0 1         ; return 


; Function #45:
;
; Name:            
; Defined at line: 1163
; #Upvalues:       1
; #Parameters:     0
; Is_vararg:       0
; Max Stack Size:  2

  1 [-]: GETUPVAL  R0 U0        ; R0 := U0
  2 [-]: CALL      R0 1 1       ; R0()
  3 [-]: RETURN    R0 1         ; return 


; Function #46:
;
; Name:            
; Defined at line: 1167
; #Upvalues:       2
; #Parameters:     0
; Is_vararg:       0
; Max Stack Size:  2

  1 [-]: GETUPVAL  R0 U0        ; R0 := U0
  2 [-]: TEST      R0 1         ; if R0 then PC := 7
  3 [-]: JMP       7            ; PC := 7
  4 [-]: GETUPVAL  R0 U1        ; R0 := U1
  5 [-]: LOADKB    R1 1 0       ; R1 := true
  6 [-]: CALL      R0 2 1       ; R0(R1)
  7 [-]: RETURN    R0 1         ; return 


; Function #47:
;
; Name:            
; Defined at line: 1173
; #Upvalues:       3
; #Parameters:     0
; Is_vararg:       0
; Max Stack Size:  2

  1 [-]: GETGLOBAL R0 K0        ; R0 := 0x7b998233
  2 [-]: GETUPVAL  R1 U0        ; R1 := U0
  3 [-]: CALL      R0 2 2       ; R0 := R0(R1)
  4 [-]: TEST      R0 1         ; if R0 then PC := 8
  5 [-]: JMP       8            ; PC := 8
  6 [-]: LOADKB    R0 0 0       ; R0 := false
  7 [-]: RETURN    R0 2         ; return R0
  8 [-]: GETGLOBAL R0 K1        ; R0 := 0x34291f5c
  9 [-]: GETTABLE  R0 R0 K2     ; R0 := R0[0xe6b41adb]
 10 [-]: CALL      R0 1 2       ; R0 := R0()
 11 [-]: TEST      R0 0         ; if not R0 then PC := 17
 12 [-]: JMP       17           ; PC := 17
 13 [-]: LOADKB    R0 1 0       ; R0 := true
 14 [-]: SETUPVAL  R0 U1        ; U82 := R1
 15 [-]: LOADKB    R0 0 0       ; R0 := false
 16 [-]: RETURN    R0 2         ; return R0
 17 [-]: GETUPVAL  R0 U2        ; R0 := U2
 18 [-]: SELF      R0 R0 K3     ; R1 := R0; R0 := R0[0xd033d908]
 19 [-]: CALL      R0 2 1       ; R0(R1)
 20 [-]: LOADKB    R0 1 0       ; R0 := true
 21 [-]: RETURN    R0 2         ; return R0
 22 [-]: RETURN    R0 1         ; return 


; Function #48:
;
; Name:            
; Defined at line: 1185
; #Upvalues:       3
; #Parameters:     0
; Is_vararg:       0
; Max Stack Size:  2

  1 [-]: GETUPVAL  R0 U0        ; R0 := U0
  2 [-]: SELF      R0 R0 K0     ; R1 := R0; R0 := R0[0xcc5f3150]
  3 [-]: CALL      R0 2 1       ; R0(R1)
  4 [-]: GETGLOBAL R0 K1        ; R0 := 0x34291f5c
  5 [-]: GETTABLE  R0 R0 K2     ; R0 := R0[0xe6b41adb]
  6 [-]: CALL      R0 1 2       ; R0 := R0()
  7 [-]: TEST      R0 0         ; if not R0 then PC := 13
  8 [-]: JMP       13           ; PC := 13
  9 [-]: LOADKB    R0 0 0       ; R0 := false
 10 [-]: SETUPVAL  R0 U1        ; U82 := R1
 11 [-]: LOADKB    R0 0 0       ; R0 := false
 12 [-]: RETURN    R0 2         ; return R0
 13 [-]: GETGLOBAL R0 K3        ; R0 := 0x7b998233
 14 [-]: GETUPVAL  R1 U2        ; R1 := U2
 15 [-]: CALL      R0 2 2       ; R0 := R0(R1)
 16 [-]: RETURN    R0 2         ; return R0
 17 [-]: RETURN    R0 1         ; return 


; Function #49:
;
; Name:            
; Defined at line: 1194
; #Upvalues:       1
; #Parameters:     0
; Is_vararg:       0
; Max Stack Size:  2

  1 [-]: LOADKB    R0 1 0       ; R0 := true
  2 [-]: SETUPVAL  R0 U0        ; U82 := R0
  3 [-]: LOADKB    R0 1 0       ; R0 := true
  4 [-]: RETURN    R0 2         ; return R0
  5 [-]: RETURN    R0 1         ; return 


; Function #50:
;
; Name:            
; Defined at line: 1199
; #Upvalues:       6
; #Parameters:     0
; Is_vararg:       0
; Max Stack Size:  13

  1 [-]: GETUPVAL  R0 U0        ; R0 := U0
  2 [-]: TEST      R0 0         ; if not R0 then PC := 72
  3 [-]: JMP       72           ; PC := 72
  4 [-]: LOADKB    R0 0 0       ; R0 := false
  5 [-]: SETUPVAL  R0 U0        ; U82 := R0
  6 [-]: GETGLOBAL R0 K0        ; R0 := 0xae91e43b
  7 [-]: SELF      R0 R0 K1     ; R1 := R0; R0 := R0[0x91a24e4b]
  8 [-]: LOADK     R2 K2        ; R2 := "_root"
  9 [-]: CONST     R3 25        ; R3 := 25.000000
 10 [-]: CALL      R0 4 2       ; R0 := R0(R1,R2,R3)
 11 [-]: GETGLOBAL R1 K0        ; R1 := 0xae91e43b
 12 [-]: SELF      R1 R1 K1     ; R2 := R1; R1 := R1[0x91a24e4b]
 13 [-]: LOADK     R3 K2        ; R3 := "_root"
 14 [-]: CONST     R4 26        ; R4 := 26.000000
 15 [-]: CALL      R1 4 2       ; R1 := R1(R2,R3,R4)
 16 [-]: EQ        0 R0 K3      ; if R0 ~= -1000.000000 then PC := 21
 17 [-]: JMP       21           ; PC := 21
 18 [-]: EQ        0 R1 K3      ; if R1 ~= -1000.000000 then PC := 21
 19 [-]: JMP       21           ; PC := 21
 20 [-]: RETURN    R0 1         ; return 
 21 [-]: GETUPVAL  R2 U1        ; R2 := U1
 22 [-]: MOVE      R3 R0        ; R3 := R0
 23 [-]: MOVE      R4 R1        ; R4 := R1
 24 [-]: CALL      R2 3 2       ; R2 := R2(R3,R4)
 25 [-]: TEST      R2 0         ; if not R2 then PC := 48
 26 [-]: JMP       48           ; PC := 48
 27 [-]: GETGLOBAL R2 K4        ; R2 := 0x7b998233
 28 [-]: GETUPVAL  R3 U2        ; R3 := U2
 29 [-]: CALL      R2 2 2       ; R2 := R2(R3)
 30 [-]: TEST      R2 1         ; if R2 then PC := 48
 31 [-]: JMP       48           ; PC := 48
 32 [-]: GETUPVAL  R2 U3        ; R2 := U3
 33 [-]: SETTABLE  R2 K5 R0     ; R2["x"] := R0
 34 [-]: GETUPVAL  R2 U3        ; R2 := U3
 35 [-]: SETTABLE  R2 K6 R1     ; R2["y"] := R1
 36 [-]: GETUPVAL  R2 U4        ; R2 := U4
 37 [-]: GETUPVAL  R3 U3        ; R3 := U3
 38 [-]: GETTABLE  R3 R3 K5     ; R3 := R3["x"]
 39 [-]: GETUPVAL  R4 U3        ; R4 := U3
 40 [-]: GETTABLE  R4 R4 K6     ; R4 := R4["y"]
 41 [-]: CALL      R2 3 3       ; R2,R3 := R2(R3,R4)
 42 [-]: GETUPVAL  R4 U2        ; R4 := U2
 43 [-]: SELF      R4 R4 K7     ; R5 := R4; R4 := R4[0xd4f09e52]
 44 [-]: MOVE      R6 R2        ; R6 := R2
 45 [-]: MOVE      R7 R3        ; R7 := R3
 46 [-]: CALL      R4 4 1       ; R4(R5,R6,R7)
 47 [-]: JMP       72           ; PC := 72
 48 [-]: GETGLOBAL R4 K0        ; R4 := 0xae91e43b
 49 [-]: SELF      R4 R4 K8     ; R5 := R4; R4 := R4[0x20b98db3]
 50 [-]: LOADK     R6 K9        ; R6 := "MapHint.text"
 51 [-]: LOADK     R7 K10       ; R7 := "/Lotus/Language/Menu/MapMarkerDisabledZone"
 52 [-]: CALL      R4 4 1       ; R4(R5,R6,R7)
 53 [-]: GETUPVAL  R4 U5        ; R4 := U5
 54 [-]: GETTABLE  R4 R4 K11    ; R4 := R4[0x659d451f]
 55 [-]: GETGLOBAL R5 K12       ; R5 := 0x0032441c
 56 [-]: GETTABLE  R5 R5 K13    ; R5 := R5["UISound_Error"]
 57 [-]: CALL      R4 2 1       ; R4(R5)
 58 [-]: GETGLOBAL R4 K14       ; R4 := 0x25312c9b
 59 [-]: GETGLOBAL R5 K0        ; R5 := 0xae91e43b
 60 [-]: LOADK     R6 K15       ; R6 := "MapHint"
 61 [-]: CONST     R7 8         ; R7 := 8.000000
 62 [-]: NEWTABLE  R8 1 0       ; R8 := {}
 63 [-]: CONST     R9 10        ; R9 := 10.000000
 64 [-]: SETLIST   R8 1 1       ; R8[(1-1)*FPF+i] := R(8+i), 1 <= i <= 1
 65 [-]: NEWTABLE  R9 1 0       ; R9 := {}
 66 [-]: CONST     R10 70       ; R10 := 70.000000
 67 [-]: SETLIST   R9 1 1       ; R9[(1-1)*FPF+i] := R(9+i), 1 <= i <= 1
 68 [-]: LOADK     R10 K17      ; R10 := 0.150000
 69 [-]: CONST     R11 0        ; R11 := 0.000000
 70 [-]: CLOSURE   R12 0        ; R12 := closure(Function #50.1)
 71 [-]: CALL      R4 9 1       ; R4(R5,R6,R7,R8,R9,R10,R11,R12)
 72 [-]: LOADKB    R4 1 0       ; R4 := true
 73 [-]: RETURN    R4 2         ; return R4
 74 [-]: RETURN    R0 1         ; return 


; Function #50.1:
;
; Name:            
; Defined at line: 1217
; #Upvalues:       0
; #Parameters:     0
; Is_vararg:       0
; Max Stack Size:  8

  1 [-]: GETGLOBAL R0 K0        ; R0 := 0x25312c9b
  2 [-]: GETGLOBAL R1 K1        ; R1 := 0xae91e43b
  3 [-]: LOADK     R2 K2        ; R2 := "MapHint"
  4 [-]: CONST     R3 8         ; R3 := 8.000000
  5 [-]: NEWTABLE  R4 1 0       ; R4 := {}
  6 [-]: CONST     R5 10        ; R5 := 10.000000
  7 [-]: SETLIST   R4 1 1       ; R4[(1-1)*FPF+i] := R(4+i), 1 <= i <= 1
  8 [-]: NEWTABLE  R5 1 0       ; R5 := {}
  9 [-]: CONST     R6 0         ; R6 := 0.000000
 10 [-]: SETLIST   R5 1 1       ; R5[(1-1)*FPF+i] := R(5+i), 1 <= i <= 1
 11 [-]: LOADK     R6 K4        ; R6 := 0.150000
 12 [-]: CONST     R7 2         ; R7 := 2.000000
 13 [-]: CALL      R0 8 1       ; R0(R1,R2,R3,R4,R5,R6,R7)
 14 [-]: RETURN    R0 1         ; return 


; Function #51:
;
; Name:            
; Defined at line: 1225
; #Upvalues:       2
; #Parameters:     2
; Is_vararg:       0
; Max Stack Size:  4

  1 [-]: GETGLOBAL R2 K0        ; R2 := 0x03f57322
  2 [-]: MOVE      R3 R1        ; R3 := R1
  3 [-]: CALL      R2 2 2       ; R2 := R2(R3)
  4 [-]: LT        0 K1 R2      ; if 0.000000 >= R2 then PC := 9
  5 [-]: JMP       9            ; PC := 9
  6 [-]: GETUPVAL  R2 U0        ; R2 := U0
  7 [-]: GETTABLE  R1 R2 K2     ; R1 := R2["INCREMENT"]
  8 [-]: JMP       16           ; PC := 16
  9 [-]: GETGLOBAL R2 K0        ; R2 := 0x03f57322
 10 [-]: MOVE      R3 R1        ; R3 := R1
 11 [-]: CALL      R2 2 2       ; R2 := R2(R3)
 12 [-]: LT        0 R2 K1      ; if R2 >= 0.000000 then PC := 16
 13 [-]: JMP       16           ; PC := 16
 14 [-]: GETUPVAL  R2 U0        ; R2 := U0
 15 [-]: GETTABLE  R1 R2 K3     ; R1 := R2["DECREMENT"]
 16 [-]: SETUPVAL  R1 U1        ; U82 := R1
 17 [-]: LOADKB    R2 1 0       ; R2 := true
 18 [-]: RETURN    R2 2         ; return R2
 19 [-]: RETURN    R0 1         ; return 


; Function #52:
;
; Name:            
; Defined at line: 1235
; #Upvalues:       2
; #Parameters:     1
; Is_vararg:       0
; Max Stack Size:  7

  1 [-]: GETGLOBAL R1 K0        ; R1 := 0x5bced4c4
  2 [-]: GETTABLE  R1 R1 K1     ; R1 := R1[0xe4a5b3ca]
  3 [-]: MOVE      R2 R0        ; R2 := R0
  4 [-]: CALL      R1 2 2       ; R1 := R1(R2)
  5 [-]: GETGLOBAL R2 K2        ; R2 := 0x47dabf0a
  6 [-]: LE        1 R1 R2      ; if R1 <= R2 then PC := 9
  7 [-]: JMP       9            ; PC := 9
  8 [-]: LOADKB    R1 0 1       ; R1 := false; PC := 9
  9 [-]: LOADKB    R1 1 0       ; R1 := true
 10 [-]: GETUPVAL  R2 U0        ; R2 := U0
 11 [-]: GETUPVAL  R3 U1        ; R3 := U1
 12 [-]: GETTABLE  R3 R3 K4     ; R3 := R3[0x06d055f9]
 13 [-]: MOVE      R4 R1        ; R4 := R1
 14 [-]: CONST     R5 0         ; R5 := 0.000000
 15 [-]: UNM       R6 R0        ; R6 :=  R0
 16 [-]: CALL      R3 4 2       ; R3 := R3(R4,R5,R6)
 17 [-]: SETTABLE  R2 K3 R3     ; R2["y"] := R3
 18 [-]: RETURN    R0 1         ; return 


; Function #53:
;
; Name:            
; Defined at line: 1240
; #Upvalues:       2
; #Parameters:     1
; Is_vararg:       0
; Max Stack Size:  7

  1 [-]: GETGLOBAL R1 K0        ; R1 := 0x5bced4c4
  2 [-]: GETTABLE  R1 R1 K1     ; R1 := R1[0xe4a5b3ca]
  3 [-]: MOVE      R2 R0        ; R2 := R0
  4 [-]: CALL      R1 2 2       ; R1 := R1(R2)
  5 [-]: GETGLOBAL R2 K2        ; R2 := 0x47dabf0a
  6 [-]: LE        1 R1 R2      ; if R1 <= R2 then PC := 9
  7 [-]: JMP       9            ; PC := 9
  8 [-]: LOADKB    R1 0 1       ; R1 := false; PC := 9
  9 [-]: LOADKB    R1 1 0       ; R1 := true
 10 [-]: GETUPVAL  R2 U0        ; R2 := U0
 11 [-]: GETUPVAL  R3 U1        ; R3 := U1
 12 [-]: GETTABLE  R3 R3 K4     ; R3 := R3[0x06d055f9]
 13 [-]: MOVE      R4 R1        ; R4 := R1
 14 [-]: CONST     R5 0         ; R5 := 0.000000
 15 [-]: MOVE      R6 R0        ; R6 := R0
 16 [-]: CALL      R3 4 2       ; R3 := R3(R4,R5,R6)
 17 [-]: SETTABLE  R2 K3 R3     ; R2["x"] := R3
 18 [-]: RETURN    R0 1         ; return 


; Function #54:
;
; Name:            
; Defined at line: 1245
; #Upvalues:       1
; #Parameters:     0
; Is_vararg:       0
; Max Stack Size:  2

  1 [-]: GETUPVAL  R0 U0        ; R0 := U0
  2 [-]: CONST     R1 1         ; R1 := 1.000000
  3 [-]: CALL      R0 2 1       ; R0(R1)
  4 [-]: LOADKB    R0 1 0       ; R0 := true
  5 [-]: RETURN    R0 2         ; return R0
  6 [-]: RETURN    R0 1         ; return 


; Function #55:
;
; Name:            
; Defined at line: 1250
; #Upvalues:       2
; #Parameters:     0
; Is_vararg:       0
; Max Stack Size:  2

  1 [-]: GETUPVAL  R0 U0        ; R0 := U0
  2 [-]: GETTABLE  R0 R0 K0     ; R0 := R0["y"]
  3 [-]: LT        0 R0 K1      ; if R0 >= 0.000000 then PC := 8
  4 [-]: JMP       8            ; PC := 8
  5 [-]: GETUPVAL  R0 U1        ; R0 := U1
  6 [-]: CONST     R1 0         ; R1 := 0.000000
  7 [-]: CALL      R0 2 1       ; R0(R1)
  8 [-]: LOADKB    R0 1 0       ; R0 := true
  9 [-]: RETURN    R0 2         ; return R0
 10 [-]: RETURN    R0 1         ; return 


; Function #56:
;
; Name:            
; Defined at line: 1257
; #Upvalues:       1
; #Parameters:     0
; Is_vararg:       0
; Max Stack Size:  2

  1 [-]: GETUPVAL  R0 U0        ; R0 := U0
  2 [-]: CONST     R1 -1        ; R1 := -1.000000
  3 [-]: CALL      R0 2 1       ; R0(R1)
  4 [-]: LOADKB    R0 1 0       ; R0 := true
  5 [-]: RETURN    R0 2         ; return R0
  6 [-]: RETURN    R0 1         ; return 


; Function #57:
;
; Name:            
; Defined at line: 1262
; #Upvalues:       2
; #Parameters:     0
; Is_vararg:       0
; Max Stack Size:  2

  1 [-]: GETUPVAL  R0 U0        ; R0 := U0
  2 [-]: GETTABLE  R0 R0 K0     ; R0 := R0["y"]
  3 [-]: LT        0 K1 R0      ; if 0.000000 >= R0 then PC := 8
  4 [-]: JMP       8            ; PC := 8
  5 [-]: GETUPVAL  R0 U1        ; R0 := U1
  6 [-]: CONST     R1 0         ; R1 := 0.000000
  7 [-]: CALL      R0 2 1       ; R0(R1)
  8 [-]: LOADKB    R0 1 0       ; R0 := true
  9 [-]: RETURN    R0 2         ; return R0
 10 [-]: RETURN    R0 1         ; return 


; Function #58:
;
; Name:            
; Defined at line: 1269
; #Upvalues:       1
; #Parameters:     0
; Is_vararg:       0
; Max Stack Size:  2

  1 [-]: GETUPVAL  R0 U0        ; R0 := U0
  2 [-]: CONST     R1 -1        ; R1 := -1.000000
  3 [-]: CALL      R0 2 1       ; R0(R1)
  4 [-]: LOADKB    R0 1 0       ; R0 := true
  5 [-]: RETURN    R0 2         ; return R0
  6 [-]: RETURN    R0 1         ; return 


; Function #59:
;
; Name:            
; Defined at line: 1274
; #Upvalues:       2
; #Parameters:     0
; Is_vararg:       0
; Max Stack Size:  2

  1 [-]: GETUPVAL  R0 U0        ; R0 := U0
  2 [-]: GETTABLE  R0 R0 K0     ; R0 := R0["x"]
  3 [-]: LT        0 R0 K1      ; if R0 >= 0.000000 then PC := 8
  4 [-]: JMP       8            ; PC := 8
  5 [-]: GETUPVAL  R0 U1        ; R0 := U1
  6 [-]: CONST     R1 0         ; R1 := 0.000000
  7 [-]: CALL      R0 2 1       ; R0(R1)
  8 [-]: LOADKB    R0 1 0       ; R0 := true
  9 [-]: RETURN    R0 2         ; return R0
 10 [-]: RETURN    R0 1         ; return 


; Function #60:
;
; Name:            
; Defined at line: 1281
; #Upvalues:       1
; #Parameters:     0
; Is_vararg:       0
; Max Stack Size:  2

  1 [-]: GETUPVAL  R0 U0        ; R0 := U0
  2 [-]: CONST     R1 1         ; R1 := 1.000000
  3 [-]: CALL      R0 2 1       ; R0(R1)
  4 [-]: LOADKB    R0 1 0       ; R0 := true
  5 [-]: RETURN    R0 2         ; return R0
  6 [-]: RETURN    R0 1         ; return 


; Function #61:
;
; Name:            
; Defined at line: 1286
; #Upvalues:       2
; #Parameters:     0
; Is_vararg:       0
; Max Stack Size:  2

  1 [-]: GETUPVAL  R0 U0        ; R0 := U0
  2 [-]: GETTABLE  R0 R0 K0     ; R0 := R0["x"]
  3 [-]: LT        0 K1 R0      ; if 0.000000 >= R0 then PC := 8
  4 [-]: JMP       8            ; PC := 8
  5 [-]: GETUPVAL  R0 U1        ; R0 := U1
  6 [-]: CONST     R1 0         ; R1 := 0.000000
  7 [-]: CALL      R0 2 1       ; R0(R1)
  8 [-]: LOADKB    R0 1 0       ; R0 := true
  9 [-]: RETURN    R0 2         ; return R0
 10 [-]: RETURN    R0 1         ; return 


; Function #62:
;
; Name:            
; Defined at line: 1293
; #Upvalues:       2
; #Parameters:     2
; Is_vararg:       0
; Max Stack Size:  5

  1 [-]: GETUPVAL  R2 U0        ; R2 := U0
  2 [-]: TEST      R2 0         ; if not R2 then PC := 5
  3 [-]: JMP       5            ; PC := 5
  4 [-]: RETURN    R0 1         ; return 
  5 [-]: GETUPVAL  R2 U1        ; R2 := U1
  6 [-]: GETGLOBAL R3 K0        ; R3 := 0x03f57322
  7 [-]: MOVE      R4 R1        ; R4 := R1
  8 [-]: CALL      R3 2 2       ; R3 := R3(R4)
  9 [-]: GETGLOBAL R4 K1        ; R4 := 0x68afa458
 10 [-]: MUL       R3 R3 R4     ; R3 := R3 * R4
 11 [-]: CALL      R2 2 1       ; R2(R3)
 12 [-]: LOADKB    R2 1 0       ; R2 := true
 13 [-]: RETURN    R2 2         ; return R2
 14 [-]: RETURN    R0 1         ; return 


; Function #63:
;
; Name:            
; Defined at line: 1301
; #Upvalues:       2
; #Parameters:     2
; Is_vararg:       0
; Max Stack Size:  4

  1 [-]: GETUPVAL  R2 U0        ; R2 := U0
  2 [-]: TEST      R2 0         ; if not R2 then PC := 5
  3 [-]: JMP       5            ; PC := 5
  4 [-]: RETURN    R0 1         ; return 
  5 [-]: GETUPVAL  R2 U1        ; R2 := U1
  6 [-]: CONST     R3 0         ; R3 := 0.000000
  7 [-]: CALL      R2 2 1       ; R2(R3)
  8 [-]: LOADKB    R2 1 0       ; R2 := true
  9 [-]: RETURN    R2 2         ; return R2
 10 [-]: RETURN    R0 1         ; return 


; Function #64:
;
; Name:            
; Defined at line: 1309
; #Upvalues:       2
; #Parameters:     2
; Is_vararg:       0
; Max Stack Size:  5

  1 [-]: GETUPVAL  R2 U0        ; R2 := U0
  2 [-]: TEST      R2 0         ; if not R2 then PC := 5
  3 [-]: JMP       5            ; PC := 5
  4 [-]: RETURN    R0 1         ; return 
  5 [-]: GETUPVAL  R2 U1        ; R2 := U1
  6 [-]: GETGLOBAL R3 K0        ; R3 := 0x03f57322
  7 [-]: MOVE      R4 R1        ; R4 := R1
  8 [-]: CALL      R3 2 2       ; R3 := R3(R4)
  9 [-]: GETGLOBAL R4 K1        ; R4 := 0x68afa458
 10 [-]: MUL       R3 R3 R4     ; R3 := R3 * R4
 11 [-]: CALL      R2 2 1       ; R2(R3)
 12 [-]: LOADKB    R2 1 0       ; R2 := true
 13 [-]: RETURN    R2 2         ; return R2
 14 [-]: RETURN    R0 1         ; return 


; Function #65:
;
; Name:            
; Defined at line: 1317
; #Upvalues:       2
; #Parameters:     2
; Is_vararg:       0
; Max Stack Size:  4

  1 [-]: GETUPVAL  R2 U0        ; R2 := U0
  2 [-]: TEST      R2 0         ; if not R2 then PC := 5
  3 [-]: JMP       5            ; PC := 5
  4 [-]: RETURN    R0 1         ; return 
  5 [-]: GETUPVAL  R2 U1        ; R2 := U1
  6 [-]: CONST     R3 0         ; R3 := 0.000000
  7 [-]: CALL      R2 2 1       ; R2(R3)
  8 [-]: LOADKB    R2 1 0       ; R2 := true
  9 [-]: RETURN    R2 2         ; return R2
 10 [-]: RETURN    R0 1         ; return 


; Function #66:
;
; Name:            
; Defined at line: 1325
; #Upvalues:       2
; #Parameters:     2
; Is_vararg:       0
; Max Stack Size:  4

  1 [-]: GETUPVAL  R2 U0        ; R2 := U0
  2 [-]: TEST      R2 0         ; if not R2 then PC := 5
  3 [-]: JMP       5            ; PC := 5
  4 [-]: RETURN    R0 1         ; return 
  5 [-]: GETGLOBAL R2 K0        ; R2 := 0x03f57322
  6 [-]: MOVE      R3 R1        ; R3 := R1
  7 [-]: CALL      R2 2 2       ; R2 := R2(R3)
  8 [-]: UNM       R2 R2        ; R2 :=  R2
  9 [-]: MUL       R2 R2 K1     ; R2 := R2 * 0.400000
 10 [-]: SETUPVAL  R2 U1        ; U82 := R1
 11 [-]: LOADKB    R2 1 0       ; R2 := true
 12 [-]: RETURN    R2 2         ; return R2
 13 [-]: RETURN    R0 1         ; return 


; Function #67:
;
; Name:            
; Defined at line: 1333
; #Upvalues:       2
; #Parameters:     2
; Is_vararg:       0
; Max Stack Size:  3

  1 [-]: GETUPVAL  R2 U0        ; R2 := U0
  2 [-]: TEST      R2 0         ; if not R2 then PC := 5
  3 [-]: JMP       5            ; PC := 5
  4 [-]: RETURN    R0 1         ; return 
  5 [-]: CONST     R2 0         ; R2 := 0.000000
  6 [-]: SETUPVAL  R2 U1        ; U82 := R1
  7 [-]: LOADKB    R2 1 0       ; R2 := true
  8 [-]: RETURN    R2 2         ; return R2
  9 [-]: RETURN    R0 1         ; return 


; Function #68:
;
; Name:            
; Defined at line: 1341
; #Upvalues:       2
; #Parameters:     0
; Is_vararg:       0
; Max Stack Size:  2

  1 [-]: GETUPVAL  R0 U0        ; R0 := U0
  2 [-]: CONST     R1 0         ; R1 := 0.000000
  3 [-]: CALL      R0 2 1       ; R0(R1)
  4 [-]: GETUPVAL  R0 U1        ; R0 := U1
  5 [-]: CONST     R1 0         ; R1 := 0.000000
  6 [-]: CALL      R0 2 1       ; R0(R1)
  7 [-]: RETURN    R0 1         ; return 


; Function #69:
;
; Name:            
; Defined at line: 1346
; #Upvalues:       2
; #Parameters:     0
; Is_vararg:       0
; Max Stack Size:  2

  1 [-]: GETUPVAL  R0 U0        ; R0 := U0
  2 [-]: CONST     R1 0         ; R1 := 0.000000
  3 [-]: CALL      R0 2 1       ; R0(R1)
  4 [-]: GETUPVAL  R0 U1        ; R0 := U1
  5 [-]: CONST     R1 0         ; R1 := 0.000000
  6 [-]: CALL      R0 2 1       ; R0(R1)
  7 [-]: RETURN    R0 1         ; return 


; Function #70:
;
; Name:            
; Defined at line: 1351
; #Upvalues:       1
; #Parameters:     0
; Is_vararg:       0
; Max Stack Size:  2

  1 [-]: GETUPVAL  R0 U0        ; R0 := U0
  2 [-]: LOADKB    R1 1 0       ; R1 := true
  3 [-]: CALL      R0 2 1       ; R0(R1)
  4 [-]: LOADKB    R0 1 0       ; R0 := true
  5 [-]: RETURN    R0 2         ; return R0
  6 [-]: RETURN    R0 1         ; return 


; Function #71:
;
; Name:            
; Defined at line: 1356
; #Upvalues:       1
; #Parameters:     0
; Is_vararg:       0
; Max Stack Size:  2

  1 [-]: LOADKB    R0 1 0       ; R0 := true
  2 [-]: SETUPVAL  R0 U0        ; U82 := R0
  3 [-]: LOADKB    R0 1 0       ; R0 := true
  4 [-]: RETURN    R0 2         ; return R0
  5 [-]: RETURN    R0 1         ; return 


; Function #72:
;
; Name:            
; Defined at line: 1361
; #Upvalues:       7
; #Parameters:     0
; Is_vararg:       0
; Max Stack Size:  13

  1 [-]: GETUPVAL  R0 U0        ; R0 := U0
  2 [-]: TEST      R0 0         ; if not R0 then PC := 71
  3 [-]: JMP       71           ; PC := 71
  4 [-]: LOADKB    R0 0 0       ; R0 := false
  5 [-]: SETUPVAL  R0 U0        ; U82 := R0
  6 [-]: GETUPVAL  R0 U1        ; R0 := U1
  7 [-]: TEST      R0 0         ; if not R0 then PC := 10
  8 [-]: JMP       10           ; PC := 10
  9 [-]: RETURN    R0 1         ; return 
 10 [-]: GETGLOBAL R0 K0        ; R0 := 0xae91e43b
 11 [-]: SELF      R0 R0 K1     ; R1 := R0; R0 := R0[0x91a24e4b]
 12 [-]: LOADK     R2 K2        ; R2 := "Reticle"
 13 [-]: CONST     R3 0         ; R3 := 0.000000
 14 [-]: CALL      R0 4 2       ; R0 := R0(R1,R2,R3)
 15 [-]: GETGLOBAL R1 K0        ; R1 := 0xae91e43b
 16 [-]: SELF      R1 R1 K1     ; R2 := R1; R1 := R1[0x91a24e4b]
 17 [-]: LOADK     R3 K2        ; R3 := "Reticle"
 18 [-]: CONST     R4 1         ; R4 := 1.000000
 19 [-]: CALL      R1 4 2       ; R1 := R1(R2,R3,R4)
 20 [-]: GETUPVAL  R2 U2        ; R2 := U2
 21 [-]: MOVE      R3 R0        ; R3 := R0
 22 [-]: MOVE      R4 R1        ; R4 := R1
 23 [-]: CALL      R2 3 2       ; R2 := R2(R3,R4)
 24 [-]: TEST      R2 0         ; if not R2 then PC := 47
 25 [-]: JMP       47           ; PC := 47
 26 [-]: GETGLOBAL R2 K3        ; R2 := 0x7b998233
 27 [-]: GETUPVAL  R3 U3        ; R3 := U3
 28 [-]: CALL      R2 2 2       ; R2 := R2(R3)
 29 [-]: TEST      R2 1         ; if R2 then PC := 47
 30 [-]: JMP       47           ; PC := 47
 31 [-]: GETUPVAL  R2 U4        ; R2 := U4
 32 [-]: SETTABLE  R2 K4 R0     ; R2["x"] := R0
 33 [-]: GETUPVAL  R2 U4        ; R2 := U4
 34 [-]: SETTABLE  R2 K5 R1     ; R2["y"] := R1
 35 [-]: GETUPVAL  R2 U5        ; R2 := U5
 36 [-]: GETUPVAL  R3 U4        ; R3 := U4
 37 [-]: GETTABLE  R3 R3 K4     ; R3 := R3["x"]
 38 [-]: GETUPVAL  R4 U4        ; R4 := U4
 39 [-]: GETTABLE  R4 R4 K5     ; R4 := R4["y"]
 40 [-]: CALL      R2 3 3       ; R2,R3 := R2(R3,R4)
 41 [-]: GETUPVAL  R4 U3        ; R4 := U3
 42 [-]: SELF      R4 R4 K6     ; R5 := R4; R4 := R4[0xd4f09e52]
 43 [-]: MOVE      R6 R2        ; R6 := R2
 44 [-]: MOVE      R7 R3        ; R7 := R3
 45 [-]: CALL      R4 4 1       ; R4(R5,R6,R7)
 46 [-]: JMP       71           ; PC := 71
 47 [-]: GETGLOBAL R4 K0        ; R4 := 0xae91e43b
 48 [-]: SELF      R4 R4 K7     ; R5 := R4; R4 := R4[0x20b98db3]
 49 [-]: LOADK     R6 K8        ; R6 := "MapHint.text"
 50 [-]: LOADK     R7 K9        ; R7 := "/Lotus/Language/Menu/MapMarkerDisabledZone"
 51 [-]: CALL      R4 4 1       ; R4(R5,R6,R7)
 52 [-]: GETUPVAL  R4 U6        ; R4 := U6
 53 [-]: GETTABLE  R4 R4 K10    ; R4 := R4[0x659d451f]
 54 [-]: GETGLOBAL R5 K11       ; R5 := 0x0032441c
 55 [-]: GETTABLE  R5 R5 K12    ; R5 := R5["UISound_Error"]
 56 [-]: CALL      R4 2 1       ; R4(R5)
 57 [-]: GETGLOBAL R4 K13       ; R4 := 0x25312c9b
 58 [-]: GETGLOBAL R5 K0        ; R5 := 0xae91e43b
 59 [-]: LOADK     R6 K14       ; R6 := "MapHint"
 60 [-]: CONST     R7 8         ; R7 := 8.000000
 61 [-]: NEWTABLE  R8 1 0       ; R8 := {}
 62 [-]: CONST     R9 10        ; R9 := 10.000000
 63 [-]: SETLIST   R8 1 1       ; R8[(1-1)*FPF+i] := R(8+i), 1 <= i <= 1
 64 [-]: NEWTABLE  R9 1 0       ; R9 := {}
 65 [-]: CONST     R10 70       ; R10 := 70.000000
 66 [-]: SETLIST   R9 1 1       ; R9[(1-1)*FPF+i] := R(9+i), 1 <= i <= 1
 67 [-]: LOADK     R10 K16      ; R10 := 0.150000
 68 [-]: CONST     R11 0        ; R11 := 0.000000
 69 [-]: CLOSURE   R12 0        ; R12 := closure(Function #72.1)
 70 [-]: CALL      R4 9 1       ; R4(R5,R6,R7,R8,R9,R10,R11,R12)
 71 [-]: LOADKB    R4 1 0       ; R4 := true
 72 [-]: RETURN    R4 2         ; return R4
 73 [-]: RETURN    R0 1         ; return 


; Function #72.1:
;
; Name:            
; Defined at line: 1379
; #Upvalues:       0
; #Parameters:     0
; Is_vararg:       0
; Max Stack Size:  8

  1 [-]: GETGLOBAL R0 K0        ; R0 := 0x25312c9b
  2 [-]: GETGLOBAL R1 K1        ; R1 := 0xae91e43b
  3 [-]: LOADK     R2 K2        ; R2 := "MapHint"
  4 [-]: CONST     R3 8         ; R3 := 8.000000
  5 [-]: NEWTABLE  R4 1 0       ; R4 := {}
  6 [-]: CONST     R5 10        ; R5 := 10.000000
  7 [-]: SETLIST   R4 1 1       ; R4[(1-1)*FPF+i] := R(4+i), 1 <= i <= 1
  8 [-]: NEWTABLE  R5 1 0       ; R5 := {}
  9 [-]: CONST     R6 0         ; R6 := 0.000000
 10 [-]: SETLIST   R5 1 1       ; R5[(1-1)*FPF+i] := R(5+i), 1 <= i <= 1
 11 [-]: LOADK     R6 K4        ; R6 := 0.150000
 12 [-]: CONST     R7 2         ; R7 := 2.000000
 13 [-]: CALL      R0 8 1       ; R0(R1,R2,R3,R4,R5,R6,R7)
 14 [-]: RETURN    R0 1         ; return 


; Function #73:
;
; Name:            
; Defined at line: 1387
; #Upvalues:       3
; #Parameters:     1
; Is_vararg:       0
; Max Stack Size:  3

  1 [-]: EQ        1 R0 K0      ; if R0 == "true" then PC := 4
  2 [-]: JMP       4            ; PC := 4
  3 [-]: LOADKB    R0 0 1       ; R0 := false; PC := 4
  4 [-]: LOADKB    R0 1 0       ; R0 := true
  5 [-]: GETUPVAL  R1 U0        ; R1 := U0
  6 [-]: TEST      R1 0         ; if not R1 then PC := 13
  7 [-]: JMP       13           ; PC := 13
  8 [-]: GETUPVAL  R1 U1        ; R1 := U1
  9 [-]: NOT       R2 R0        ; R2 :=  R0
 10 [-]: CALL      R1 2 1       ; R1(R2)
 11 [-]: GETUPVAL  R1 U2        ; R1 := U2
 12 [-]: CALL      R1 1 1       ; R1()
 13 [-]: RETURN    R0 1         ; return 


; Function #74:
;
; Name:            
; Defined at line: 1395
; #Upvalues:       2
; #Parameters:     2
; Is_vararg:       0
; Max Stack Size:  4

  1 [-]: GETGLOBAL R2 K0        ; R2 := 0x03f57322
  2 [-]: MOVE      R3 R1        ; R3 := R1
  3 [-]: CALL      R2 2 2       ; R2 := R2(R3)
  4 [-]: LT        0 K1 R2      ; if 0.000000 >= R2 then PC := 9
  5 [-]: JMP       9            ; PC := 9
  6 [-]: GETUPVAL  R2 U0        ; R2 := U0
  7 [-]: GETTABLE  R1 R2 K2     ; R1 := R2["INCREMENT"]
  8 [-]: JMP       16           ; PC := 16
  9 [-]: GETGLOBAL R2 K0        ; R2 := 0x03f57322
 10 [-]: MOVE      R3 R1        ; R3 := R1
 11 [-]: CALL      R2 2 2       ; R2 := R2(R3)
 12 [-]: LT        0 R2 K1      ; if R2 >= 0.000000 then PC := 16
 13 [-]: JMP       16           ; PC := 16
 14 [-]: GETUPVAL  R2 U0        ; R2 := U0
 15 [-]: GETTABLE  R1 R2 K3     ; R1 := R2["DECREMENT"]
 16 [-]: SETUPVAL  R1 U1        ; U82 := R1
 17 [-]: LOADKB    R2 1 0       ; R2 := true
 18 [-]: RETURN    R2 2         ; return R2
 19 [-]: RETURN    R0 1         ; return 


; Function #75:
;
; Name:            
; Defined at line: 1405
; #Upvalues:       2
; #Parameters:     3
; Is_vararg:       0
; Max Stack Size:  7

  1 [-]: EQ        0 R1 K0      ; if R1 ~= "EN_TOUCH_PINCH" then PC := 17
  2 [-]: JMP       17           ; PC := 17
  3 [-]: GETUPVAL  R3 U0        ; R3 := U0
  4 [-]: GETTABLE  R3 R3 K1     ; R3 := R3[0x06d055f9]
  5 [-]: EQ        1 R2 K2      ; if R2 == "1" then PC := 8
  6 [-]: JMP       8            ; PC := 8
  7 [-]: LOADKB    R4 0 1       ; R4 := false; PC := 8
  8 [-]: LOADKB    R4 1 0       ; R4 := true
  9 [-]: LOADKB    R5 1 0       ; R5 := true
 10 [-]: LOADKB    R6 0 0       ; R6 := false
 11 [-]: CALL      R3 4 2       ; R3 := R3(R4,R5,R6)
 12 [-]: TEST      R3 1         ; if R3 then PC := 17
 13 [-]: JMP       17           ; PC := 17
 14 [-]: GETUPVAL  R4 U1        ; R4 := U1
 15 [-]: SELF      R4 R4 K3     ; R5 := R4; R4 := R4[0xcc5f3150]
 16 [-]: CALL      R4 2 1       ; R4(R5)
 17 [-]: RETURN    R0 1         ; return 


