; This file has been disassembled using luadec 2.0.2 by sztupy (modified by Reversive)

; Name:            
; Defined at line: 0
; #Upvalues:       0
; #Parameters:     0
; Is_vararg:       2
; Max Stack Size:  34

  1 [-]: GETGLOBAL R0 K0        ; R0 := 0x2d0fad09
  2 [-]: LOADK     R1 K1        ; R1 := "EE.Interface.Utilities"
  3 [-]: CALL      R0 2 2       ; R0 := R0(R1)
  4 [-]: GETGLOBAL R1 K0        ; R1 := 0x2d0fad09
  5 [-]: LOADK     R2 K2        ; R2 := "Lotus.Interface.LotusUtilities"
  6 [-]: CALL      R1 2 2       ; R1 := R1(R2)
  7 [-]: GETGLOBAL R2 K0        ; R2 := 0x2d0fad09
  8 [-]: LOADK     R3 K3        ; R3 := "Lotus.Interface.UIStyleUtilities"
  9 [-]: CALL      R2 2 2       ; R2 := R2(R3)
 10 [-]: NEWTABLE  R3 0 0       ; R3 := {}
 11 [-]: LOADKB    R4 0 0       ; R4 := false
 12 [-]: LOADKB    R5 0 0       ; R5 := false
 13 [-]: LOADNIL   R6 R10       ; R6 := R7 := R8 := R9 := R10 := nil
 14 [-]: CONST     R11 0        ; R11 := 0.000000
 15 [-]: CONST     R12 0        ; R12 := 0.000000
 16 [-]: CONST     R13 1        ; R13 := 1.000000
 17 [-]: LOADK     R14 K4       ; R14 := 0.350000
 18 [-]: GETGLOBAL R15 K5       ; R15 := 0x78ca68a2
 19 [-]: CONST     R16 0        ; R16 := 0.000000
 20 [-]: CONST     R17 0        ; R17 := 0.250000
 21 [-]: CALL      R15 3 2      ; R15 := R15(R16,R17)
 22 [-]: GETGLOBAL R16 K5       ; R16 := 0x78ca68a2
 23 [-]: CONST     R17 0        ; R17 := 0.000000
 24 [-]: CONST     R18 0        ; R18 := 0.250000
 25 [-]: CALL      R16 3 2      ; R16 := R16(R17,R18)
 26 [-]: LOADNIL   R17 R17      ; R17 := nil
 27 [-]: GETGLOBAL R18 K5       ; R18 := 0x78ca68a2
 28 [-]: CONST     R19 0        ; R19 := 0.000000
 29 [-]: CONST     R20 0        ; R20 := 0.250000
 30 [-]: CALL      R18 3 2      ; R18 := R18(R19,R20)
 31 [-]: GETGLOBAL R19 K6       ; R19 := 0xa421af95
 32 [-]: CONST     R20 1        ; R20 := 1.000000
 33 [-]: CONST     R21 1        ; R21 := 1.000000
 34 [-]: CONST     R22 1        ; R22 := 1.000000
 35 [-]: CALL      R19 4 2      ; R19 := R19(R20,R21,R22)
 36 [-]: LOADNIL   R20 R20      ; R20 := nil
 37 [-]: CONST     R21 1        ; R21 := 1.000000
 38 [-]: NEWTABLE  R22 0 2      ; R22 := {}
 39 [-]: SETTABLE  R22 K7 K8    ; R22["x"] := 0.000000
 40 [-]: SETTABLE  R22 K9 K8    ; R22["y"] := 0.000000
 41 [-]: NEWTABLE  R23 0 2      ; R23 := {}
 42 [-]: SETTABLE  R23 K7 K8    ; R23["x"] := 0.000000
 43 [-]: SETTABLE  R23 K9 K8    ; R23["y"] := 0.000000
 44 [-]: LOADNIL   R24 R24      ; R24 := nil
 45 [-]: CONST     R25 0        ; R25 := 0.000000
 46 [-]: CONST     R26 0        ; R26 := 0.000000
 47 [-]: CONST     R27 462      ; R27 := 462.000000
 48 [-]: CLOSURE   R28 0        ; R28 := closure(Function #1)
 49 [-]: MOVE      R0 R4        ; R0 := R4
 50 [-]: MOVE      R0 R3        ; R0 := R3
 51 [-]: CLOSURE   R29 1        ; R29 := closure(Function #2)
 52 [-]: MOVE      R0 R19       ; R0 := R19
 53 [-]: MOVE      R0 R8        ; R0 := R8
 54 [-]: MOVE      R0 R10       ; R0 := R10
 55 [-]: MOVE      R0 R6        ; R0 := R6
 56 [-]: MOVE      R0 R9        ; R0 := R9
 57 [-]: MOVE      R0 R20       ; R0 := R20
 58 [-]: MOVE      R0 R21       ; R0 := R21
 59 [-]: CLOSURE   R30 2        ; R30 := closure(Function #3)
 60 [-]: MOVE      R0 R27       ; R0 := R27
 61 [-]: MOVE      R0 R0        ; R0 := R0
 62 [-]: CLOSURE   R31 3        ; R31 := closure(Function #4)
 63 [-]: MOVE      R0 R25       ; R0 := R25
 64 [-]: MOVE      R0 R24       ; R0 := R24
 65 [-]: MOVE      R0 R27       ; R0 := R27
 66 [-]: MOVE      R0 R26       ; R0 := R26
 67 [-]: MOVE      R0 R2        ; R0 := R2
 68 [-]: MOVE      R0 R0        ; R0 := R0
 69 [-]: MOVE      R0 R30       ; R0 := R30
 70 [-]: MOVE      R0 R6        ; R0 := R6
 71 [-]: MOVE      R0 R28       ; R0 := R28
 72 [-]: MOVE      R0 R29       ; R0 := R29
 73 [-]: MOVE      R0 R17       ; R0 := R17
 74 [-]: MOVE      R0 R18       ; R0 := R18
 75 [-]: SETGLOBAL R31 K10      ; Initialize := R31
 76 [-]: CLOSURE   R31 4        ; R31 := closure(Function #5)
 77 [-]: MOVE      R0 R31       ; R0 := R31
 78 [-]: CLOSURE   R32 5        ; R32 := closure(Function #6)
 79 [-]: MOVE      R0 R4        ; R0 := R4
 80 [-]: MOVE      R0 R3        ; R0 := R3
 81 [-]: MOVE      R0 R31       ; R0 := R31
 82 [-]: MOVE      R0 R26       ; R0 := R26
 83 [-]: MOVE      R0 R27       ; R0 := R27
 84 [-]: MOVE      R0 R24       ; R0 := R24
 85 [-]: MOVE      R0 R0        ; R0 := R0
 86 [-]: MOVE      R0 R25       ; R0 := R25
 87 [-]: MOVE      R0 R23       ; R0 := R23
 88 [-]: MOVE      R0 R7        ; R0 := R7
 89 [-]: MOVE      R0 R8        ; R0 := R8
 90 [-]: MOVE      R0 R9        ; R0 := R9
 91 [-]: MOVE      R0 R18       ; R0 := R18
 92 [-]: MOVE      R0 R6        ; R0 := R6
 93 [-]: MOVE      R0 R17       ; R0 := R17
 94 [-]: MOVE      R0 R12       ; R0 := R12
 95 [-]: MOVE      R0 R22       ; R0 := R22
 96 [-]: MOVE      R0 R14       ; R0 := R14
 97 [-]: MOVE      R0 R11       ; R0 := R11
 98 [-]: MOVE      R0 R13       ; R0 := R13
 99 [-]: MOVE      R0 R15       ; R0 := R15
100 [-]: MOVE      R0 R16       ; R0 := R16
101 [-]: MOVE      R0 R10       ; R0 := R10
102 [-]: MOVE      R0 R19       ; R0 := R19
103 [-]: SETGLOBAL R32 K11      ; Update := R32
104 [-]: CLOSURE   R32 6        ; R32 := closure(Function #7)
105 [-]: MOVE      R0 R5        ; R0 := R5
106 [-]: MOVE      R0 R18       ; R0 := R18
107 [-]: MOVE      R0 R15       ; R0 := R15
108 [-]: MOVE      R0 R11       ; R0 := R11
109 [-]: MOVE      R0 R16       ; R0 := R16
110 [-]: MOVE      R0 R12       ; R0 := R12
111 [-]: MOVE      R0 R6        ; R0 := R6
112 [-]: MOVE      R0 R20       ; R0 := R20
113 [-]: MOVE      R0 R0        ; R0 := R0
114 [-]: MOVE      R0 R7        ; R0 := R7
115 [-]: CLOSURE   R33 7        ; R33 := closure(Function #8)
116 [-]: MOVE      R0 R5        ; R0 := R5
117 [-]: MOVE      R0 R11       ; R0 := R11
118 [-]: MOVE      R0 R13       ; R0 := R13
119 [-]: SETGLOBAL R33 K12      ; onKeyDown_MENU_MOUSE_X := R33
120 [-]: CLOSURE   R33 8        ; R33 := closure(Function #9)
121 [-]: MOVE      R0 R5        ; R0 := R5
122 [-]: MOVE      R0 R12       ; R0 := R12
123 [-]: MOVE      R0 R14       ; R0 := R14
124 [-]: SETGLOBAL R33 K13      ; onKeyDown_MENU_MOUSE_Y := R33
125 [-]: CLOSURE   R33 9        ; R33 := closure(Function #10)
126 [-]: MOVE      R0 R5        ; R0 := R5
127 [-]: MOVE      R0 R23       ; R0 := R23
128 [-]: SETGLOBAL R33 K14      ; onKeyDown_MENU_RIGHT_Y := R33
129 [-]: CLOSURE   R33 10       ; R33 := closure(Function #11)
130 [-]: MOVE      R0 R5        ; R0 := R5
131 [-]: MOVE      R0 R23       ; R0 := R23
132 [-]: SETGLOBAL R33 K15      ; onKeyUp_MENU_RIGHT_Y := R33
133 [-]: CLOSURE   R33 11       ; R33 := closure(Function #12)
134 [-]: MOVE      R0 R5        ; R0 := R5
135 [-]: MOVE      R0 R22       ; R0 := R22
136 [-]: SETGLOBAL R33 K16      ; onKeyDown_MENU_Y := R33
137 [-]: CLOSURE   R33 12       ; R33 := closure(Function #13)
138 [-]: MOVE      R0 R5        ; R0 := R5
139 [-]: MOVE      R0 R22       ; R0 := R22
140 [-]: SETGLOBAL R33 K17      ; onKeyUp_MENU_Y := R33
141 [-]: CLOSURE   R33 13       ; R33 := closure(Function #14)
142 [-]: MOVE      R0 R5        ; R0 := R5
143 [-]: MOVE      R0 R22       ; R0 := R22
144 [-]: SETGLOBAL R33 K18      ; onKeyDown_MENU_X := R33
145 [-]: CLOSURE   R33 14       ; R33 := closure(Function #15)
146 [-]: MOVE      R0 R5        ; R0 := R5
147 [-]: MOVE      R0 R22       ; R0 := R22
148 [-]: SETGLOBAL R33 K19      ; onKeyUp_MENU_X := R33
149 [-]: CLOSURE   R33 15       ; R33 := closure(Function #16)
150 [-]: MOVE      R0 R5        ; R0 := R5
151 [-]: MOVE      R0 R23       ; R0 := R23
152 [-]: SETGLOBAL R33 K20      ; onKeyDown_MENU_UP := R33
153 [-]: CLOSURE   R33 16       ; R33 := closure(Function #17)
154 [-]: MOVE      R0 R5        ; R0 := R5
155 [-]: MOVE      R0 R23       ; R0 := R23
156 [-]: SETGLOBAL R33 K21      ; onKeyUp_MENU_UP := R33
157 [-]: CLOSURE   R33 17       ; R33 := closure(Function #18)
158 [-]: MOVE      R0 R5        ; R0 := R5
159 [-]: MOVE      R0 R23       ; R0 := R23
160 [-]: SETGLOBAL R33 K22      ; onKeyDown_MENU_DOWN := R33
161 [-]: CLOSURE   R33 18       ; R33 := closure(Function #19)
162 [-]: MOVE      R0 R5        ; R0 := R5
163 [-]: MOVE      R0 R23       ; R0 := R23
164 [-]: SETGLOBAL R33 K23      ; onKeyUp_MENU_DOWN := R33
165 [-]: CLOSURE   R33 19       ; R33 := closure(Function #20)
166 [-]: MOVE      R0 R7        ; R0 := R7
167 [-]: SETGLOBAL R33 K24      ; SetTrigger := R33
168 [-]: CLOSURE   R33 20       ; R33 := closure(Function #21)
169 [-]: MOVE      R0 R5        ; R0 := R5
170 [-]: MOVE      R0 R32       ; R0 := R32
171 [-]: SETGLOBAL R33 K25      ; onKeyDown_MENU_CANCEL := R33
172 [-]: CLOSURE   R33 21       ; R33 := closure(Function #22)
173 [-]: MOVE      R0 R5        ; R0 := R5
174 [-]: MOVE      R0 R24       ; R0 := R24
175 [-]: SETGLOBAL R33 K26      ; onKeyDown_MENU_MOUSE_Z := R33
176 [-]: CLOSURE   R33 22       ; R33 := closure(Function #23)
177 [-]: MOVE      R0 R30       ; R0 := R30
178 [-]: SETGLOBAL R33 K27      ; onViewportSizeChanged := R33
179 [-]: CLOSURE   R33 23       ; R33 := closure(Function #24)
180 [-]: SETGLOBAL R33 K28      ; SupportsThemes := R33
181 [-]: RETURN    R0 1         ; return 


; Function #1:
;
; Name:            
; Defined at line: 36
; #Upvalues:       2
; #Parameters:     1
; Is_vararg:       3
; Max Stack Size:  7

  1 [-]: GETUPVAL  R2 U0        ; R2 := U0
  2 [-]: TEST      R2 0         ; if not R2 then PC := 8
  3 [-]: JMP       8            ; PC := 8
  4 [-]: MOVE      R2 R0        ; R2 := R0
  5 [-]: VARARG    R3 0         ; R3 := ...
  6 [-]: CALL      R2 0 1       ; R2(R3,...)
  7 [-]: JMP       16           ; PC := 16
  8 [-]: GETGLOBAL R2 K0        ; R2 := 0x33bdd652
  9 [-]: GETTABLE  R2 R2 K1     ; R2 := R2[0x23d5322f]
 10 [-]: GETUPVAL  R3 U1        ; R3 := U1
 11 [-]: NEWTABLE  R4 1 0       ; R4 := {}
 12 [-]: MOVE      R5 R0        ; R5 := R0
 13 [-]: VARARG    R6 0         ; R6 := ...
 14 [-]: SETLIST   R4 0 1       ; R4[(1-1)*FPF+i] := R(4+i), 1 <= i <= 0
 15 [-]: CALL      R2 3 1       ; R2(R3,R4)
 16 [-]: RETURN    R0 1         ; return 


; Function #2:
;
; Name:            
; Defined at line: 44
; #Upvalues:       7
; #Parameters:     4
; Is_vararg:       0
; Max Stack Size:  10

  1 [-]: EQ        0 R1 K0      ; if R1 ~= nil then PC := 4
  2 [-]: JMP       4            ; PC := 4
  3 [-]: GETGLOBAL R1 K1        ; R1 := ZERO_VECTOR
  4 [-]: EQ        0 R2 K0      ; if R2 ~= nil then PC := 7
  5 [-]: JMP       7            ; PC := 7
  6 [-]: GETGLOBAL R2 K1        ; R2 := ZERO_VECTOR
  7 [-]: EQ        0 R3 K0      ; if R3 ~= nil then PC := 10
  8 [-]: JMP       10           ; PC := 10
  9 [-]: LOADK     R3 K2        ; R3 := 0.550000
 10 [-]: SETUPVAL  R2 U0        ; U82 := R0
 11 [-]: SETUPVAL  R0 U1        ; U82 := R1
 12 [-]: GETGLOBAL R4 K3        ; R4 := 0x7b998233
 13 [-]: GETUPVAL  R5 U1        ; R5 := U1
 14 [-]: CALL      R4 2 2       ; R4 := R4(R5)
 15 [-]: TEST      R4 1         ; if R4 then PC := 56
 16 [-]: JMP       56           ; PC := 56
 17 [-]: GETUPVAL  R4 U1        ; R4 := U1
 18 [-]: SELF      R4 R4 K4     ; R5 := R4; R4 := R4[0xcb3851b8]
 19 [-]: CALL      R4 2 2       ; R4 := R4(R5)
 20 [-]: SETUPVAL  R4 U2        ; U82 := R2
 21 [-]: GETUPVAL  R4 U3        ; R4 := U3
 22 [-]: SELF      R4 R4 K5     ; R5 := R4; R4 := R4[0x0b4bcfb6]
 23 [-]: CALL      R4 2 2       ; R4 := R4(R5)
 24 [-]: SELF      R4 R4 K6     ; R5 := R4; R4 := R4[0x4f92e6fd]
 25 [-]: CALL      R4 2 2       ; R4 := R4(R5)
 26 [-]: GETGLOBAL R5 K7        ; R5 := 0x492c7f2a
 27 [-]: GETGLOBAL R6 K8        ; R6 := 0xa421af95
 28 [-]: LOADK     R7 K9        ; R7 := 0.300000
 29 [-]: CONST     R8 0         ; R8 := 0.000000
 30 [-]: CONST     R9 0         ; R9 := 0.000000
 31 [-]: CALL      R6 4 2       ; R6 := R6(R7,R8,R9)
 32 [-]: MOVE      R7 R4        ; R7 := R4
 33 [-]: CALL      R5 3 2       ; R5 := R5(R6,R7)
 34 [-]: GETUPVAL  R6 U1        ; R6 := U1
 35 [-]: SELF      R6 R6 K10    ; R7 := R6; R6 := R6[0xef8e8f7f]
 36 [-]: CALL      R6 2 2       ; R6 := R6(R7)
 37 [-]: ADD       R6 R6 R1     ; R6 := R6 + R1
 38 [-]: ADD       R6 R6 R5     ; R6 := R6 + R5
 39 [-]: SETUPVAL  R6 U4        ; U82 := R4
 40 [-]: GETUPVAL  R6 U1        ; R6 := U1
 41 [-]: SELF      R6 R6 K11    ; R7 := R6; R6 := R6[0xc1595bd5]
 42 [-]: GETGLOBAL R8 K12       ; R8 := 0x55ba2eeb
 43 [-]: CALL      R6 3 2       ; R6 := R6(R7,R8)
 44 [-]: SETUPVAL  R6 U5        ; U82 := R5
 45 [-]: GETGLOBAL R6 K3        ; R6 := 0x7b998233
 46 [-]: GETUPVAL  R7 U5        ; R7 := U5
 47 [-]: CALL      R6 2 2       ; R6 := R6(R7)
 48 [-]: TEST      R6 0         ; if not R6 then PC := 56
 49 [-]: JMP       56           ; PC := 56
 50 [-]: GETUPVAL  R6 U1        ; R6 := U1
 51 [-]: SELF      R6 R6 K13    ; R7 := R6; R6 := R6[0x47901f07]
 52 [-]: GETGLOBAL R8 K12       ; R8 := 0x55ba2eeb
 53 [-]: GETGLOBAL R9 K14       ; R9 := EMPTY_SYMBOL
 54 [-]: CALL      R6 4 2       ; R6 := R6(R7,R8,R9)
 55 [-]: SETUPVAL  R6 U5        ; U82 := R5
 56 [-]: SETUPVAL  R3 U6        ; U82 := R6
 57 [-]: GETUPVAL  R6 U3        ; R6 := U3
 58 [-]: SELF      R6 R6 K5     ; R7 := R6; R6 := R6[0x0b4bcfb6]
 59 [-]: CALL      R6 2 2       ; R6 := R6(R7)
 60 [-]: SELF      R6 R6 K15    ; R7 := R6; R6 := R6[0x47de28d6]
 61 [-]: GETUPVAL  R8 U6        ; R8 := U6
 62 [-]: LOADKB    R9 0 0       ; R9 := false
 63 [-]: CALL      R6 4 1       ; R6(R7,R8,R9)
 64 [-]: RETURN    R0 1         ; return 


; Function #3:
;
; Name:            
; Defined at line: 74
; #Upvalues:       2
; #Parameters:     0
; Is_vararg:       0
; Max Stack Size:  7

  1 [-]: GETGLOBAL R0 K0        ; R0 := 0xae91e43b
  2 [-]: SELF      R0 R0 K1     ; R1 := R0; R0 := R0[0x91a24e4b]
  3 [-]: LOADK     R2 K2        ; R2 := "Panel"
  4 [-]: CONST     R3 1         ; R3 := 1.000000
  5 [-]: CALL      R0 4 2       ; R0 := R0(R1,R2,R3)
  6 [-]: GETUPVAL  R1 U0        ; R1 := U0
  7 [-]: CONST     R2 45        ; R2 := 45.000000
  8 [-]: GETUPVAL  R3 U1        ; R3 := U1
  9 [-]: GETTABLE  R3 R3 K3     ; R3 := R3[0xe5e5a417]
 10 [-]: GETGLOBAL R4 K0        ; R4 := 0xae91e43b
 11 [-]: MOVE      R5 R0        ; R5 := R0
 12 [-]: CALL      R3 3 2       ; R3 := R3(R4,R5)
 13 [-]: MOVE      R0 R3        ; R0 := R3
 14 [-]: GETUPVAL  R3 U1        ; R3 := U1
 15 [-]: GETTABLE  R3 R3 K4     ; R3 := R3[0xd718f59b]
 16 [-]: GETGLOBAL R4 K0        ; R4 := 0xae91e43b
 17 [-]: MOVE      R5 R1        ; R5 := R1
 18 [-]: CALL      R3 3 2       ; R3 := R3(R4,R5)
 19 [-]: MOVE      R1 R3        ; R1 := R3
 20 [-]: GETUPVAL  R3 U1        ; R3 := U1
 21 [-]: GETTABLE  R3 R3 K5     ; R3 := R3[0x0db7934d]
 22 [-]: GETGLOBAL R4 K0        ; R4 := 0xae91e43b
 23 [-]: MOVE      R5 R2        ; R5 := R2
 24 [-]: CALL      R3 3 2       ; R3 := R3(R4,R5)
 25 [-]: MOVE      R2 R3        ; R2 := R3
 26 [-]: GETGLOBAL R3 K6        ; R3 := 0x033d19cd
 27 [-]: SELF      R3 R3 K7     ; R4 := R3; R3 := R3[0x830eea67]
 28 [-]: GETGLOBAL R5 K8        ; R5 := 0x6c97a788
 29 [-]: GETTABLE  R5 R5 K9     ; R5 := R5["VISIBILITY_CENTER"]
 30 [-]: MOVE      R6 R0        ; R6 := R0
 31 [-]: CALL      R3 4 1       ; R3(R4,R5,R6)
 32 [-]: GETGLOBAL R3 K6        ; R3 := 0x033d19cd
 33 [-]: SELF      R3 R3 K7     ; R4 := R3; R3 := R3[0x830eea67]
 34 [-]: GETGLOBAL R5 K8        ; R5 := 0x6c97a788
 35 [-]: GETTABLE  R5 R5 K10    ; R5 := R5["VISIBILITY_SIZE"]
 36 [-]: MOVE      R6 R1        ; R6 := R1
 37 [-]: CALL      R3 4 1       ; R3(R4,R5,R6)
 38 [-]: GETGLOBAL R3 K6        ; R3 := 0x033d19cd
 39 [-]: SELF      R3 R3 K7     ; R4 := R3; R3 := R3[0x830eea67]
 40 [-]: GETGLOBAL R5 K8        ; R5 := 0x6c97a788
 41 [-]: GETTABLE  R5 R5 K11    ; R5 := R5["VISIBILITY_FADE_SIZE"]
 42 [-]: MOVE      R6 R2        ; R6 := R2
 43 [-]: CALL      R3 4 1       ; R3(R4,R5,R6)
 44 [-]: RETURN    R0 1         ; return 


; Function #4:
;
; Name:            
; Defined at line: 88
; #Upvalues:       12
; #Parameters:     0
; Is_vararg:       0
; Max Stack Size:  16

  1 [-]: GETGLOBAL R0 K0        ; R0 := 0xae91e43b
  2 [-]: SELF      R0 R0 K1     ; R1 := R0; R0 := R0[0x824d113a]
  3 [-]: LOADKB    R2 1 0       ; R2 := true
  4 [-]: CALL      R0 3 1       ; R0(R1,R2)
  5 [-]: GETGLOBAL R0 K0        ; R0 := 0xae91e43b
  6 [-]: SELF      R0 R0 K2     ; R1 := R0; R0 := R0[0x91a24e4b]
  7 [-]: LOADK     R2 K3        ; R2 := "Panel.Description"
  8 [-]: CONST     R3 1         ; R3 := 1.000000
  9 [-]: CALL      R0 4 2       ; R0 := R0(R1,R2,R3)
 10 [-]: SETUPVAL  R0 U0        ; U82 := R0
 11 [-]: GETGLOBAL R0 K4        ; R0 := 0x2d0fad09
 12 [-]: LOADK     R1 K5        ; R1 := "EE.Interface.Components.ScrollBar"
 13 [-]: CALL      R0 2 2       ; R0 := R0(R1)
 14 [-]: GETTABLE  R1 R0 K6     ; R1 := R0[0x3b3ea08c]
 15 [-]: GETGLOBAL R2 K0        ; R2 := 0xae91e43b
 16 [-]: LOADK     R3 K7        ; R3 := "Panel.ScrollBar"
 17 [-]: GETUPVAL  R4 U2        ; R4 := U2
 18 [-]: CONST     R5 0         ; R5 := 0.500000
 19 [-]: CALL      R1 5 2       ; R1 := R1(R2,R3,R4,R5)
 20 [-]: SETUPVAL  R1 U1        ; U82 := R1
 21 [-]: GETUPVAL  R1 U1        ; R1 := U1
 22 [-]: SETTABLE  R1 K8 K9     ; R1["mEnableSmoothScroll"] := true
 23 [-]: GETUPVAL  R1 U1        ; R1 := U1
 24 [-]: CLOSURE   R2 0         ; R2 := closure(Function #4.1)
 25 [-]: GETUPVAL  R0 U0        ; R0 := U0
 26 [-]: GETUPVAL  R0 U3        ; R0 := U3
 27 [-]: GETUPVAL  R0 U2        ; R0 := U2
 28 [-]: SETTABLE  R1 K10 R2    ; R1["mScrollValueChangedCallback"] := R2
 29 [-]: GETUPVAL  R1 U1        ; R1 := U1
 30 [-]: SELF      R1 R1 K11    ; R2 := R1; R1 := R1[0x687ae094]
 31 [-]: CALL      R1 2 1       ; R1(R2)
 32 [-]: GETUPVAL  R1 U4        ; R1 := U4
 33 [-]: GETTABLE  R1 R1 K12    ; R1 := R1[0x5d10207d]
 34 [-]: CONST     R2 6         ; R2 := 6.000000
 35 [-]: LOADKB    R3 1 0       ; R3 := true
 36 [-]: CALL      R1 3 2       ; R1 := R1(R2,R3)
 37 [-]: GETUPVAL  R2 U4        ; R2 := U4
 38 [-]: GETTABLE  R2 R2 K12    ; R2 := R2[0x5d10207d]
 39 [-]: CONST     R3 1         ; R3 := 1.000000
 40 [-]: LOADKB    R4 1 0       ; R4 := true
 41 [-]: CALL      R2 3 2       ; R2 := R2(R3,R4)
 42 [-]: GETUPVAL  R3 U5        ; R3 := U5
 43 [-]: GETTABLE  R3 R3 K14    ; R3 := R3[0x8bcd12b6]
 44 [-]: MOVE      R4 R2        ; R4 := R2
 45 [-]: CALL      R3 2 2       ; R3 := R3(R4)
 46 [-]: GETUPVAL  R4 U5        ; R4 := U5
 47 [-]: GETTABLE  R4 R4 K14    ; R4 := R4[0x8bcd12b6]
 48 [-]: GETUPVAL  R5 U4        ; R5 := U4
 49 [-]: GETTABLE  R5 R5 K12    ; R5 := R5[0x5d10207d]
 50 [-]: CONST     R6 2         ; R6 := 2.000000
 51 [-]: LOADKB    R7 1 0       ; R7 := true
 52 [-]: CALL      R5 3 0       ; R5,... := R5(R6,R7)
 53 [-]: CALL      R4 0 2       ; R4 := R4(R5,...)
 54 [-]: GETGLOBAL R5 K0        ; R5 := 0xae91e43b
 55 [-]: SELF      R5 R5 K15    ; R6 := R5; R5 := R5[0x67bc869f]
 56 [-]: LOADK     R7 K16       ; R7 := "Panel.Flourish"
 57 [-]: CONST     R8 9         ; R8 := 9.000000
 58 [-]: MOVE      R9 R2        ; R9 := R2
 59 [-]: CALL      R5 5 1       ; R5(R6,R7,R8,R9)
 60 [-]: GETGLOBAL R5 K0        ; R5 := 0xae91e43b
 61 [-]: SELF      R5 R5 K15    ; R6 := R5; R5 := R5[0x67bc869f]
 62 [-]: LOADK     R7 K16       ; R7 := "Panel.Flourish"
 63 [-]: CONST     R8 10        ; R8 := 10.000000
 64 [-]: CONST     R9 70        ; R9 := 70.000000
 65 [-]: CALL      R5 5 1       ; R5(R6,R7,R8,R9)
 66 [-]: GETGLOBAL R5 K0        ; R5 := 0xae91e43b
 67 [-]: SELF      R5 R5 K17    ; R6 := R5; R5 := R5[0xd5181643]
 68 [-]: LOADK     R7 K18       ; R7 := "Panel.Bg"
 69 [-]: GETGLOBAL R8 K19       ; R8 := 0x0032441c
 70 [-]: GETTABLE  R8 R8 K20    ; R8 := R8["UIMaterial_RectangleNoDepth"]
 71 [-]: CALL      R5 4 1       ; R5(R6,R7,R8)
 72 [-]: GETGLOBAL R5 K0        ; R5 := 0xae91e43b
 73 [-]: SELF      R5 R5 K21    ; R6 := R5; R5 := R5[0x91e13703]
 74 [-]: LOADK     R7 K18       ; R7 := "Panel.Bg"
 75 [-]: LOADK     R8 K22       ; R8 := "RectEdgeColor"
 76 [-]: GETTABLE  R9 R3 K23    ; R9 := R3["r"]
 77 [-]: GETTABLE  R10 R3 K24   ; R10 := R3["g"]
 78 [-]: GETTABLE  R11 R3 K25   ; R11 := R3["b"]
 79 [-]: LOADK     R12 K26      ; R12 := 0.700000
 80 [-]: CALL      R5 8 1       ; R5(R6,R7,R8,R9,R10,R11,R12)
 81 [-]: GETGLOBAL R5 K0        ; R5 := 0xae91e43b
 82 [-]: SELF      R5 R5 K21    ; R6 := R5; R5 := R5[0x91e13703]
 83 [-]: LOADK     R7 K18       ; R7 := "Panel.Bg"
 84 [-]: LOADK     R8 K27       ; R8 := "RectInnerColor"
 85 [-]: GETTABLE  R9 R4 K23    ; R9 := R4["r"]
 86 [-]: GETTABLE  R10 R4 K24   ; R10 := R4["g"]
 87 [-]: GETTABLE  R11 R4 K25   ; R11 := R4["b"]
 88 [-]: GETUPVAL  R12 U5       ; R12 := U5
 89 [-]: GETTABLE  R12 R12 K28  ; R12 := R12[0x06d055f9]
 90 [-]: GETUPVAL  R13 U4       ; R13 := U4
 91 [-]: GETTABLE  R13 R13 K29  ; R13 := R13[0xad9f60aa]
 92 [-]: CALL      R13 1 2      ; R13 := R13()
 93 [-]: CONST     R14 0        ; R14 := 0.500000
 94 [-]: CONST     R15 0        ; R15 := 0.250000
 95 [-]: CALL      R12 4 0      ; R12,... := R12(R13,R14,R15)
 96 [-]: CALL      R5 0 1       ; R5(R6,...)
 97 [-]: GETGLOBAL R5 K0        ; R5 := 0xae91e43b
 98 [-]: SELF      R5 R5 K15    ; R6 := R5; R5 := R5[0x67bc869f]
 99 [-]: LOADK     R7 K3        ; R7 := "Panel.Description"
100 [-]: CONST     R8 36        ; R8 := 36.000000
101 [-]: MOVE      R9 R1        ; R9 := R1
102 [-]: CALL      R5 5 1       ; R5(R6,R7,R8,R9)
103 [-]: GETGLOBAL R5 K0        ; R5 := 0xae91e43b
104 [-]: SELF      R5 R5 K17    ; R6 := R5; R5 := R5[0xd5181643]
105 [-]: LOADK     R7 K3        ; R7 := "Panel.Description"
106 [-]: GETGLOBAL R8 K30       ; R8 := 0x033d19cd
107 [-]: CALL      R5 4 1       ; R5(R6,R7,R8)
108 [-]: GETGLOBAL R5 K0        ; R5 := 0xae91e43b
109 [-]: SELF      R5 R5 K15    ; R6 := R5; R5 := R5[0x67bc869f]
110 [-]: LOADK     R7 K31       ; R7 := "Panel"
111 [-]: CONST     R8 10        ; R8 := 10.000000
112 [-]: CONST     R9 0         ; R9 := 0.000000
113 [-]: CALL      R5 5 1       ; R5(R6,R7,R8,R9)
114 [-]: GETUPVAL  R5 U6        ; R5 := U6
115 [-]: CALL      R5 1 1       ; R5()
116 [-]: GETGLOBAL R5 K32       ; R5 := 0x89326c93
117 [-]: SELF      R5 R5 K33    ; R6 := R5; R5 := R5[0x78298275]
118 [-]: CALL      R5 2 2       ; R5 := R5(R6)
119 [-]: SETUPVAL  R5 U7        ; U82 := R7
120 [-]: GETGLOBAL R5 K34       ; R5 := _T
121 [-]: CLOSURE   R6 1         ; R6 := closure(Function #4.2)
122 [-]: GETUPVAL  R0 U8        ; R0 := U8
123 [-]: GETUPVAL  R0 U9        ; R0 := U9
124 [-]: SETTABLE  R5 K35 R6    ; R5["MUSEUM_SetupDeco"] := R6
125 [-]: GETUPVAL  R5 U7        ; R5 := U7
126 [-]: SELF      R5 R5 K36    ; R6 := R5; R5 := R5[0xeea7f8c4]
127 [-]: CALL      R5 2 2       ; R5 := R5(R6)
128 [-]: SETUPVAL  R5 U10       ; U82 := R10
129 [-]: GETUPVAL  R5 U11       ; R5 := U11
130 [-]: SELF      R5 R5 K37    ; R6 := R5; R5 := R5[0x188e2bee]
131 [-]: CONST     R7 1         ; R7 := 1.000000
132 [-]: CALL      R5 3 1       ; R5(R6,R7)
133 [-]: RETURN    R0 1         ; return 


; Function #4.1:
;
; Name:            
; Defined at line: 97
; #Upvalues:       3
; #Parameters:     2
; Is_vararg:       0
; Max Stack Size:  9

  1 [-]: GETGLOBAL R2 K0        ; R2 := 0x3d106989
  2 [-]: LOADK     R3 K1        ; R3 := "pNewScrollValue="
  3 [-]: MOVE      R4 R0        ; R4 := R0
  4 [-]: CONCAT    R3 R3 R4     ; R3 := R3 .. R4
  5 [-]: CALL      R2 2 1       ; R2(R3)
  6 [-]: GETGLOBAL R2 K2        ; R2 := 0xae91e43b
  7 [-]: SELF      R2 R2 K3     ; R3 := R2; R2 := R2[0x67bc869f]
  8 [-]: LOADK     R4 K4        ; R4 := "Panel.Description"
  9 [-]: CONST     R5 1         ; R5 := 1.000000
 10 [-]: GETUPVAL  R6 U0        ; R6 := U0
 11 [-]: GETUPVAL  R7 U1        ; R7 := U1
 12 [-]: GETUPVAL  R8 U2        ; R8 := U2
 13 [-]: SUB       R7 R7 R8     ; R7 := R7 - R8
 14 [-]: MUL       R7 R7 R0     ; R7 := R7 * R0
 15 [-]: SUB       R6 R6 R7     ; R6 := R6 - R7
 16 [-]: CALL      R2 5 1       ; R2(R3,R4,R5,R6)
 17 [-]: RETURN    R0 1         ; return 


; Function #4.2:
;
; Name:            
; Defined at line: 120
; #Upvalues:       2
; #Parameters:     0
; Is_vararg:       3
; Max Stack Size:  4

  1 [-]: GETUPVAL  R1 U0        ; R1 := U0
  2 [-]: GETUPVAL  R2 U1        ; R2 := U1
  3 [-]: VARARG    R3 0         ; R3 := ...
  4 [-]: CALL      R1 0 1       ; R1(R2,...)
  5 [-]: RETURN    R0 1         ; return 


; Function #5:
;
; Name:            
; Defined at line: 127
; #Upvalues:       1
; #Parameters:     1
; Is_vararg:       0
; Max Stack Size:  8

  1 [-]: LOADK     R1 K0        ; R1 := ""
  2 [-]: SELF      R2 R0 K1     ; R3 := R0; R2 := R0[0x076d502b]
  3 [-]: CALL      R2 2 2       ; R2 := R2(R3)
  4 [-]: GETGLOBAL R3 K2        ; R3 := 0x7b998233
  5 [-]: MOVE      R4 R2        ; R4 := R2
  6 [-]: CALL      R3 2 2       ; R3 := R3(R4)
  7 [-]: TEST      R3 1         ; if R3 then PC := 13
  8 [-]: JMP       13           ; PC := 13
  9 [-]: GETUPVAL  R3 U0        ; R3 := U0
 10 [-]: MOVE      R4 R2        ; R4 := R2
 11 [-]: CALL      R3 2 2       ; R3 := R3(R4)
 12 [-]: MOVE      R1 R3        ; R1 := R3
 13 [-]: EQ        1 R1 K0      ; if R1 == "" then PC := 18
 14 [-]: JMP       18           ; PC := 18
 15 [-]: LOADK     R3 K3        ; R3 := "\r\n"
 16 [-]: MOVE      R4 R1        ; R4 := R1
 17 [-]: CONCAT    R1 R3 R4     ; R1 := R3 .. R4
 18 [-]: GETGLOBAL R3 K4        ; R3 := 0x7f5022cf
 19 [-]: GETTABLE  R3 R3 K5     ; R3 := R3[0x66edf04f]
 20 [-]: GETGLOBAL R4 K6        ; R4 := 0xae91e43b
 21 [-]: SELF      R4 R4 K7     ; R5 := R4; R4 := R4[0x42b04007]
 22 [-]: SELF      R6 R0 K8     ; R7 := R0; R6 := R0[0xca33ff41]
 23 [-]: CALL      R6 2 2       ; R6 := R6(R7)
 24 [-]: SELF      R6 R6 K9     ; R7 := R6; R6 := R6[0x6d604ba7]
 25 [-]: CALL      R6 2 2       ; R6 := R6(R7)
 26 [-]: LOADKB    R7 0 0       ; R7 := false
 27 [-]: CALL      R4 4 2       ; R4 := R4(R5,R6,R7)
 28 [-]: LOADK     R5 K10       ; R5 := "^"
 29 [-]: LOADK     R6 K0        ; R6 := ""
 30 [-]: CALL      R3 4 2       ; R3 := R3(R4,R5,R6)
 31 [-]: GETGLOBAL R4 K4        ; R4 := 0x7f5022cf
 32 [-]: GETTABLE  R4 R4 K5     ; R4 := R4[0x66edf04f]
 33 [-]: MOVE      R5 R3        ; R5 := R3
 34 [-]: LOADK     R6 K11       ; R6 := "%[%d+%.%d+%]"
 35 [-]: LOADK     R7 K0        ; R7 := ""
 36 [-]: CALL      R4 4 2       ; R4 := R4(R5,R6,R7)
 37 [-]: MOVE      R3 R4        ; R3 := R4
 38 [-]: GETGLOBAL R4 K4        ; R4 := 0x7f5022cf
 39 [-]: GETTABLE  R4 R4 K12    ; R4 := R4[0x1a94c9cc]
 40 [-]: MOVE      R5 R3        ; R5 := R3
 41 [-]: CONST     R6 1         ; R6 := 1.000000
 42 [-]: CONST     R7 2         ; R7 := 2.000000
 43 [-]: CALL      R4 4 2       ; R4 := R4(R5,R6,R7)
 44 [-]: EQ        0 R4 K3      ; if R4 ~= "\r\n" then PC := 52
 45 [-]: JMP       52           ; PC := 52
 46 [-]: GETGLOBAL R4 K4        ; R4 := 0x7f5022cf
 47 [-]: GETTABLE  R4 R4 K12    ; R4 := R4[0x1a94c9cc]
 48 [-]: MOVE      R5 R3        ; R5 := R3
 49 [-]: CONST     R6 3         ; R6 := 3.000000
 50 [-]: CALL      R4 3 2       ; R4 := R4(R5,R6)
 51 [-]: MOVE      R3 R4        ; R3 := R4
 52 [-]: MOVE      R4 R3        ; R4 := R3
 53 [-]: MOVE      R5 R1        ; R5 := R1
 54 [-]: CONCAT    R1 R4 R5     ; R1 := R4 .. R5
 55 [-]: RETURN    R1 2         ; return R1
 56 [-]: RETURN    R0 1         ; return 


; Function #6:
;
; Name:            
; Defined at line: 150
; #Upvalues:       24
; #Parameters:     0
; Is_vararg:       0
; Max Stack Size:  21

  1 [-]: LOADKB    R0 1 0       ; R0 := true
  2 [-]: SETUPVAL  R0 U0        ; U82 := R0
  3 [-]: GETUPVAL  R0 U1        ; R0 := U1
  4 [-]: LEN       R0 R0        ; R0 := # R0
  5 [-]: LT        0 K0 R0      ; if 0.000000 >= R0 then PC := 31
  6 [-]: JMP       31           ; PC := 31
  7 [-]: CONST     R0 1         ; R0 := 1.000000
  8 [-]: GETUPVAL  R1 U1        ; R1 := U1
  9 [-]: LEN       R1 R1        ; R1 := # R1
 10 [-]: CONST     R2 1         ; R2 := 1.000000
 11 [-]: FORPREP   R0 28        ; R0 -= R2; PC := 28
 12 [-]: GETUPVAL  R4 U1        ; R4 := U1
 13 [-]: GETTABLE  R4 R4 R3     ; R4 := R4[R3]
 14 [-]: GETTABLE  R4 R4 K1     ; R4 := R4[1.000000]
 15 [-]: GETUPVAL  R5 U1        ; R5 := U1
 16 [-]: GETTABLE  R5 R5 R3     ; R5 := R5[R3]
 17 [-]: GETTABLE  R5 R5 K2     ; R5 := R5[2.000000]
 18 [-]: GETUPVAL  R6 U1        ; R6 := U1
 19 [-]: GETTABLE  R6 R6 R3     ; R6 := R6[R3]
 20 [-]: GETTABLE  R6 R6 K3     ; R6 := R6[3.000000]
 21 [-]: GETUPVAL  R7 U1        ; R7 := U1
 22 [-]: GETTABLE  R7 R7 R3     ; R7 := R7[R3]
 23 [-]: GETTABLE  R7 R7 K4     ; R7 := R7[4.000000]
 24 [-]: GETUPVAL  R8 U1        ; R8 := U1
 25 [-]: GETTABLE  R8 R8 R3     ; R8 := R8[R3]
 26 [-]: GETTABLE  R8 R8 K5     ; R8 := R8[5.000000]
 27 [-]: CALL      R4 5 1       ; R4(R5,R6,R7,R8)
 28 [-]: FORLOOP   R0 12        ; R0 += R2; if R0 <= R1 then begin PC := 12; R3 := R0 end
 29 [-]: NEWTABLE  R4 0 0       ; R4 := {}
 30 [-]: SETUPVAL  R4 U1        ; U82 := R1
 31 [-]: LOADKB    R4 0 0       ; R4 := false
 32 [-]: SETUPVAL  R4 U0        ; U82 := R0
 33 [-]: GETGLOBAL R4 K6        ; R4 := 0xae91e43b
 34 [-]: SELF      R4 R4 K7     ; R5 := R4; R4 := R4[0x8a8c8d5a]
 35 [-]: GETGLOBAL R6 K8        ; R6 := 0xb693b6c1
 36 [-]: CALL      R6 1 0       ; R6,... := R6()
 37 [-]: CALL      R4 0 1       ; R4(R5,...)
 38 [-]: GETGLOBAL R4 K9        ; R4 := 0x7b998233
 39 [-]: GETGLOBAL R5 K10       ; R5 := _T
 40 [-]: GETTABLE  R5 R5 K11    ; R5 := R5["MUSEUM_Transmission"]
 41 [-]: CALL      R4 2 2       ; R4 := R4(R5)
 42 [-]: TEST      R4 1         ; if R4 then PC := 165
 43 [-]: JMP       165          ; PC := 165
 44 [-]: GETUPVAL  R4 U2        ; R4 := U2
 45 [-]: GETGLOBAL R5 K10       ; R5 := _T
 46 [-]: GETTABLE  R5 R5 K11    ; R5 := R5["MUSEUM_Transmission"]
 47 [-]: CALL      R4 2 2       ; R4 := R4(R5)
 48 [-]: GETGLOBAL R5 K6        ; R5 := 0xae91e43b
 49 [-]: SELF      R5 R5 K12    ; R6 := R5; R5 := R5[0x20b98db3]
 50 [-]: LOADK     R7 K13       ; R7 := "Panel.Description.text"
 51 [-]: MOVE      R8 R4        ; R8 := R4
 52 [-]: CALL      R5 4 1       ; R5(R6,R7,R8)
 53 [-]: GETGLOBAL R5 K6        ; R5 := 0xae91e43b
 54 [-]: SELF      R5 R5 K14    ; R6 := R5; R5 := R5[0x91a24e4b]
 55 [-]: LOADK     R7 K15       ; R7 := "Panel.Description"
 56 [-]: CONST     R8 34        ; R8 := 34.000000
 57 [-]: CALL      R5 4 2       ; R5 := R5(R6,R7,R8)
 58 [-]: SETUPVAL  R5 U3        ; U82 := R3
 59 [-]: CONST     R5 50        ; R5 := 50.000000
 60 [-]: GETGLOBAL R6 K16       ; R6 := 0x5bced4c4
 61 [-]: GETTABLE  R6 R6 K17    ; R6 := R6[0xac1b386a]
 62 [-]: GETUPVAL  R7 U3        ; R7 := U3
 63 [-]: GETUPVAL  R8 U4        ; R8 := U4
 64 [-]: CALL      R6 3 2       ; R6 := R6(R7,R8)
 65 [-]: MUL       R7 R5 K2     ; R7 := R5 * 2.000000
 66 [-]: ADD       R6 R6 R7     ; R6 := R6 + R7
 67 [-]: GETUPVAL  R7 U3        ; R7 := U3
 68 [-]: GETUPVAL  R8 U4        ; R8 := U4
 69 [-]: LE        1 R8 R7      ; if R8 <= R7 then PC := 72
 70 [-]: JMP       72           ; PC := 72
 71 [-]: LOADKB    R7 0 1       ; R7 := false; PC := 72
 72 [-]: LOADKB    R7 1 0       ; R7 := true
 73 [-]: GETUPVAL  R8 U5        ; R8 := U5
 74 [-]: SELF      R8 R8 K18    ; R9 := R8; R8 := R8[0x0077d753]
 75 [-]: MOVE      R10 R7       ; R10 := R7
 76 [-]: CALL      R8 3 1       ; R8(R9,R10)
 77 [-]: GETGLOBAL R8 K6        ; R8 := 0xae91e43b
 78 [-]: SELF      R8 R8 K19    ; R9 := R8; R8 := R8[0x67bc869f]
 79 [-]: LOADK     R10 K20      ; R10 := "Panel.ScrollBar"
 80 [-]: CONST     R11 10       ; R11 := 10.000000
 81 [-]: GETUPVAL  R12 U6       ; R12 := U6
 82 [-]: GETTABLE  R12 R12 K21  ; R12 := R12[0x06d055f9]
 83 [-]: MOVE      R13 R7       ; R13 := R7
 84 [-]: CONST     R14 50       ; R14 := 50.000000
 85 [-]: CONST     R15 0        ; R15 := 0.000000
 86 [-]: CALL      R12 4 0      ; R12,... := R12(R13,R14,R15)
 87 [-]: CALL      R8 0 1       ; R8(R9,...)
 88 [-]: TEST      R7 0         ; if not R7 then PC := 115
 89 [-]: JMP       115          ; PC := 115
 90 [-]: GETUPVAL  R8 U5        ; R8 := U5
 91 [-]: SELF      R8 R8 K22    ; R9 := R8; R8 := R8[0x425b8f0d]
 92 [-]: ADD       R10 R6 K2    ; R10 := R6 + 2.000000
 93 [-]: CALL      R8 3 1       ; R8(R9,R10)
 94 [-]: GETUPVAL  R8 U5        ; R8 := U5
 95 [-]: GETUPVAL  R9 U4        ; R9 := U4
 96 [-]: GETUPVAL  R10 U3       ; R10 := U3
 97 [-]: DIV       R9 R9 R10    ; R9 := R9 / R10
 98 [-]: SETTABLE  R8 K23 R9    ; R8["mVisibleProp"] := R9
 99 [-]: GETUPVAL  R8 U5        ; R8 := U5
100 [-]: SELF      R8 R8 K24    ; R9 := R8; R8 := R8[0x44aa79ac]
101 [-]: CONST     R10 0        ; R10 := 0.000000
102 [-]: LOADNIL   R11 R11      ; R11 := nil
103 [-]: LOADKB    R12 1 0      ; R12 := true
104 [-]: CALL      R8 5 1       ; R8(R9,R10,R11,R12)
105 [-]: GETUPVAL  R8 U5        ; R8 := U5
106 [-]: GETUPVAL  R9 U3        ; R9 := U3
107 [-]: GETUPVAL  R10 U4       ; R10 := U4
108 [-]: SUB       R9 R9 R10    ; R9 := R9 - R10
109 [-]: DIV       R9 K1 R9     ; R9 := 1.000000 / R9
110 [-]: MUL       R9 R9 K26    ; R9 := R9 * 50.000000
111 [-]: SETTABLE  R8 K25 R9    ; R8["mScrollStep"] := R9
112 [-]: GETUPVAL  R8 U5        ; R8 := U5
113 [-]: SELF      R8 R8 K27    ; R9 := R8; R8 := R8[0xa8854625]
114 [-]: CALL      R8 2 1       ; R8(R9)
115 [-]: MUL       R8 R6 K28    ; R8 := R6 * -0.500000
116 [-]: ADD       R8 R8 R5     ; R8 := R8 + R5
117 [-]: SETUPVAL  R8 U7        ; U82 := R7
118 [-]: GETGLOBAL R8 K6        ; R8 := 0xae91e43b
119 [-]: SELF      R8 R8 K19    ; R9 := R8; R8 := R8[0x67bc869f]
120 [-]: LOADK     R10 K15      ; R10 := "Panel.Description"
121 [-]: CONST     R11 1        ; R11 := 1.000000
122 [-]: GETUPVAL  R12 U7       ; R12 := U7
123 [-]: CALL      R8 5 1       ; R8(R9,R10,R11,R12)
124 [-]: GETGLOBAL R8 K6        ; R8 := 0xae91e43b
125 [-]: SELF      R8 R8 K19    ; R9 := R8; R8 := R8[0x67bc869f]
126 [-]: LOADK     R10 K29      ; R10 := "Panel.Flourish"
127 [-]: CONST     R11 1        ; R11 := 1.000000
128 [-]: MUL       R12 R6 K28   ; R12 := R6 * -0.500000
129 [-]: CALL      R8 5 1       ; R8(R9,R10,R11,R12)
130 [-]: GETGLOBAL R8 K6        ; R8 := 0xae91e43b
131 [-]: SELF      R8 R8 K19    ; R9 := R8; R8 := R8[0x67bc869f]
132 [-]: LOADK     R10 K20      ; R10 := "Panel.ScrollBar"
133 [-]: CONST     R11 1        ; R11 := 1.000000
134 [-]: MUL       R12 R6 K28   ; R12 := R6 * -0.500000
135 [-]: ADD       R12 R12 K30  ; R12 := R12 + 7.000000
136 [-]: CALL      R8 5 1       ; R8(R9,R10,R11,R12)
137 [-]: GETGLOBAL R8 K6        ; R8 := 0xae91e43b
138 [-]: SELF      R8 R8 K19    ; R9 := R8; R8 := R8[0x67bc869f]
139 [-]: LOADK     R10 K31      ; R10 := "Panel.Bg"
140 [-]: CONST     R11 13       ; R11 := 13.000000
141 [-]: MOVE      R12 R6       ; R12 := R6
142 [-]: CALL      R8 5 1       ; R8(R9,R10,R11,R12)
143 [-]: GETGLOBAL R8 K6        ; R8 := 0xae91e43b
144 [-]: SELF      R8 R8 K19    ; R9 := R8; R8 := R8[0x67bc869f]
145 [-]: LOADK     R10 K32      ; R10 := "Panel.Blurer"
146 [-]: CONST     R11 13       ; R11 := 13.000000
147 [-]: MOVE      R12 R6       ; R12 := R6
148 [-]: CALL      R8 5 1       ; R8(R9,R10,R11,R12)
149 [-]: GETGLOBAL R8 K33       ; R8 := 0x25312c9b
150 [-]: GETGLOBAL R9 K6        ; R9 := 0xae91e43b
151 [-]: LOADK     R10 K34      ; R10 := "Panel"
152 [-]: CONST     R11 0        ; R11 := 0.000000
153 [-]: NEWTABLE  R12 1 0      ; R12 := {}
154 [-]: CONST     R13 10       ; R13 := 10.000000
155 [-]: SETLIST   R12 1 1      ; R12[(1-1)*FPF+i] := R(12+i), 1 <= i <= 1
156 [-]: NEWTABLE  R13 1 0      ; R13 := {}
157 [-]: CONST     R14 100      ; R14 := 100.000000
158 [-]: SETLIST   R13 1 1      ; R13[(1-1)*FPF+i] := R(13+i), 1 <= i <= 1
159 [-]: LOADK     R14 K36      ; R14 := 0.300000
160 [-]: CALL      R8 7 1       ; R8(R9,R10,R11,R12,R13,R14)
161 [-]: GETGLOBAL R8 K10       ; R8 := _T
162 [-]: SETTABLE  R8 K37 K38   ; R8["Transmissions_Visible"] := false
163 [-]: GETGLOBAL R8 K10       ; R8 := _T
164 [-]: SETTABLE  R8 K11 K39   ; R8["MUSEUM_Transmission"] := nil
165 [-]: GETUPVAL  R8 U5        ; R8 := U5
166 [-]: SELF      R8 R8 K40    ; R9 := R8; R8 := R8[0x30456f58]
167 [-]: GETGLOBAL R10 K41      ; R10 := 0x03f57322
168 [-]: GETUPVAL  R11 U8       ; R11 := U8
169 [-]: GETTABLE  R11 R11 K42  ; R11 := R11["y"]
170 [-]: CALL      R10 2 2      ; R10 := R10(R11)
171 [-]: DIV       R10 R10 K2   ; R10 := R10 / 2.000000
172 [-]: GETGLOBAL R11 K43      ; R11 := 0x0032441c
173 [-]: GETTABLE  R11 R11 K44  ; R11 := R11["UISound_Scroll"]
174 [-]: CALL      R8 4 1       ; R8(R9,R10,R11)
175 [-]: GETUPVAL  R8 U5        ; R8 := U5
176 [-]: SELF      R8 R8 K45    ; R9 := R8; R8 := R8[0xfaa69527]
177 [-]: CALL      R8 2 1       ; R8(R9)
178 [-]: GETUPVAL  R8 U9        ; R8 := U9
179 [-]: SELF      R8 R8 K46    ; R9 := R8; R8 := R8[0xd1586535]
180 [-]: CALL      R8 2 2       ; R8 := R8(R9)
181 [-]: GETGLOBAL R9 K47       ; R9 := 0xa421af95
182 [-]: CONST     R10 0        ; R10 := 0.000000
183 [-]: CONST     R11 0        ; R11 := 0.750000
184 [-]: LOADK     R12 K48      ; R12 := 0.550000
185 [-]: CALL      R9 4 2       ; R9 := R9(R10,R11,R12)
186 [-]: ADD       R8 R8 R9     ; R8 := R8 + R9
187 [-]: GETGLOBAL R9 K9        ; R9 := 0x7b998233
188 [-]: GETUPVAL  R10 U10      ; R10 := U10
189 [-]: CALL      R9 2 2       ; R9 := R9(R10)
190 [-]: TEST      R9 1         ; if R9 then PC := 193
191 [-]: JMP       193          ; PC := 193
192 [-]: GETUPVAL  R8 U11       ; R8 := U11
193 [-]: GETUPVAL  R9 U12       ; R9 := U12
194 [-]: SELF      R9 R9 K45    ; R10 := R9; R9 := R9[0xfaa69527]
195 [-]: GETGLOBAL R11 K8       ; R11 := 0xb693b6c1
196 [-]: CALL      R11 1 0      ; R11,... := R11()
197 [-]: CALL      R9 0 1       ; R9(R10,...)
198 [-]: GETGLOBAL R9 K49       ; R9 := 0x20b7f774
199 [-]: GETUPVAL  R10 U13      ; R10 := U13
200 [-]: SELF      R10 R10 K50  ; R11 := R10; R10 := R10[0xebfba9e4]
201 [-]: CALL      R10 2 2      ; R10 := R10(R11)
202 [-]: MOVE      R11 R8       ; R11 := R8
203 [-]: CALL      R9 3 2       ; R9 := R9(R10,R11)
204 [-]: GETGLOBAL R10 K51      ; R10 := 0x5e223e7d
205 [-]: GETUPVAL  R11 U14      ; R11 := U14
206 [-]: MOVE      R12 R9       ; R12 := R9
207 [-]: GETUPVAL  R13 U12      ; R13 := U12
208 [-]: SELF      R13 R13 K52  ; R14 := R13; R13 := R13[0x54ab95f9]
209 [-]: CALL      R13 2 0      ; R13,... := R13(R14)
210 [-]: CALL      R10 0 2      ; R10 := R10(R11,...)
211 [-]: GETUPVAL  R11 U13      ; R11 := U13
212 [-]: SELF      R11 R11 K53  ; R12 := R11; R11 := R11[0x020d4331]
213 [-]: CALL      R11 2 2      ; R11 := R11(R12)
214 [-]: SELF      R11 R11 K54  ; R12 := R11; R11 := R11[0x553549e8]
215 [-]: MOVE      R13 R10      ; R13 := R10
216 [-]: CALL      R11 3 1      ; R11(R12,R13)
217 [-]: GETUPVAL  R11 U13      ; R11 := U13
218 [-]: SELF      R11 R11 K55  ; R12 := R11; R11 := R11[0x89c6dbf7]
219 [-]: MOVE      R13 R10      ; R13 := R10
220 [-]: CALL      R11 3 1      ; R11(R12,R13)
221 [-]: GETGLOBAL R11 K9       ; R11 := 0x7b998233
222 [-]: GETUPVAL  R12 U10      ; R12 := U10
223 [-]: CALL      R11 2 2      ; R11 := R11(R12)
224 [-]: TEST      R11 1        ; if R11 then PC := 321
225 [-]: JMP       321          ; PC := 321
226 [-]: GETGLOBAL R11 K56      ; R11 := 0x34291f5c
227 [-]: GETTABLE  R11 R11 K57  ; R11 := R11[0x1467d5f4]
228 [-]: CALL      R11 1 2      ; R11 := R11()
229 [-]: TEST      R11 0        ; if not R11 then PC := 257
230 [-]: JMP       257          ; PC := 257
231 [-]: GETGLOBAL R11 K58      ; R11 := 0x42dcc9f5
232 [-]: GETUPVAL  R12 U15      ; R12 := U15
233 [-]: GETGLOBAL R13 K41      ; R13 := 0x03f57322
234 [-]: GETUPVAL  R14 U16      ; R14 := U16
235 [-]: GETTABLE  R14 R14 K42  ; R14 := R14["y"]
236 [-]: CALL      R13 2 2      ; R13 := R13(R14)
237 [-]: MUL       R13 R13 K59  ; R13 := R13 * 0.200000
238 [-]: SUB       R12 R12 R13  ; R12 := R12 - R13
239 [-]: GETUPVAL  R13 U17      ; R13 := U17
240 [-]: UNM       R13 R13      ; R13 :=  R13
241 [-]: GETUPVAL  R14 U17      ; R14 := U17
242 [-]: CALL      R11 4 2      ; R11 := R11(R12,R13,R14)
243 [-]: SETUPVAL  R11 U15      ; U82 := R15
244 [-]: GETGLOBAL R11 K58      ; R11 := 0x42dcc9f5
245 [-]: GETUPVAL  R12 U18      ; R12 := U18
246 [-]: GETGLOBAL R13 K41      ; R13 := 0x03f57322
247 [-]: GETUPVAL  R14 U16      ; R14 := U16
248 [-]: GETTABLE  R14 R14 K60  ; R14 := R14["x"]
249 [-]: CALL      R13 2 2      ; R13 := R13(R14)
250 [-]: MUL       R13 R13 K61  ; R13 := R13 * 0.050000
251 [-]: SUB       R12 R12 R13  ; R12 := R12 - R13
252 [-]: GETUPVAL  R13 U19      ; R13 := U19
253 [-]: UNM       R13 R13      ; R13 :=  R13
254 [-]: GETUPVAL  R14 U19      ; R14 := U19
255 [-]: CALL      R11 4 2      ; R11 := R11(R12,R13,R14)
256 [-]: SETUPVAL  R11 U18      ; U82 := R18
257 [-]: GETUPVAL  R11 U18      ; R11 := U18
258 [-]: GETUPVAL  R12 U15      ; R12 := U15
259 [-]: GETUPVAL  R13 U20      ; R13 := U20
260 [-]: SELF      R13 R13 K52  ; R14 := R13; R13 := R13[0x54ab95f9]
261 [-]: CALL      R13 2 2      ; R13 := R13(R14)
262 [-]: GETUPVAL  R14 U20      ; R14 := U20
263 [-]: SELF      R14 R14 K62  ; R15 := R14; R14 := R14[0x188e2bee]
264 [-]: MOVE      R16 R11      ; R16 := R11
265 [-]: CALL      R14 3 1      ; R14(R15,R16)
266 [-]: GETUPVAL  R14 U20      ; R14 := U20
267 [-]: SELF      R14 R14 K45  ; R15 := R14; R14 := R14[0xfaa69527]
268 [-]: GETGLOBAL R16 K8       ; R16 := 0xb693b6c1
269 [-]: CALL      R16 1 0      ; R16,... := R16()
270 [-]: CALL      R14 0 1      ; R14(R15,...)
271 [-]: GETUPVAL  R14 U20      ; R14 := U20
272 [-]: SELF      R14 R14 K52  ; R15 := R14; R14 := R14[0x54ab95f9]
273 [-]: CALL      R14 2 2      ; R14 := R14(R15)
274 [-]: MOVE      R11 R14      ; R11 := R14
275 [-]: GETUPVAL  R14 U21      ; R14 := U21
276 [-]: SELF      R14 R14 K52  ; R15 := R14; R14 := R14[0x54ab95f9]
277 [-]: CALL      R14 2 2      ; R14 := R14(R15)
278 [-]: GETUPVAL  R15 U21      ; R15 := U21
279 [-]: SELF      R15 R15 K62  ; R16 := R15; R15 := R15[0x188e2bee]
280 [-]: MOVE      R17 R12      ; R17 := R12
281 [-]: CALL      R15 3 1      ; R15(R16,R17)
282 [-]: GETUPVAL  R15 U21      ; R15 := U21
283 [-]: SELF      R15 R15 K45  ; R16 := R15; R15 := R15[0xfaa69527]
284 [-]: GETGLOBAL R17 K8       ; R17 := 0xb693b6c1
285 [-]: CALL      R17 1 0      ; R17,... := R17()
286 [-]: CALL      R15 0 1      ; R15(R16,...)
287 [-]: GETUPVAL  R15 U21      ; R15 := U21
288 [-]: SELF      R15 R15 K52  ; R16 := R15; R15 := R15[0x54ab95f9]
289 [-]: CALL      R15 2 2      ; R15 := R15(R16)
290 [-]: MOVE      R12 R15      ; R12 := R15
291 [-]: GETUPVAL  R15 U10      ; R15 := U10
292 [-]: SELF      R15 R15 K46  ; R16 := R15; R15 := R15[0xd1586535]
293 [-]: CALL      R15 2 2      ; R15 := R15(R16)
294 [-]: EQ        0 R13 R11    ; if R13 ~= R11 then PC := 298
295 [-]: JMP       298          ; PC := 298
296 [-]: EQ        1 R14 R12    ; if R14 == R12 then PC := 321
297 [-]: JMP       321          ; PC := 321
298 [-]: GETGLOBAL R16 K63      ; R16 := 0x00046924
299 [-]: GETUPVAL  R17 U22      ; R17 := U22
300 [-]: GETTABLE  R17 R17 K64  ; R17 := R17["heading"]
301 [-]: MUL       R18 R11 K65  ; R18 := R11 * 180.000000
302 [-]: GETUPVAL  R19 U23      ; R19 := U23
303 [-]: GETTABLE  R19 R19 K60  ; R19 := R19["x"]
304 [-]: MUL       R18 R18 R19  ; R18 := R18 * R19
305 [-]: ADD       R17 R17 R18  ; R17 := R17 + R18
306 [-]: GETUPVAL  R18 U22      ; R18 := U22
307 [-]: GETTABLE  R18 R18 K66  ; R18 := R18["pitch"]
308 [-]: MUL       R19 R12 K67  ; R19 := R12 * 90.000000
309 [-]: GETUPVAL  R20 U23      ; R20 := U23
310 [-]: GETTABLE  R20 R20 K42  ; R20 := R20["y"]
311 [-]: MUL       R19 R19 R20  ; R19 := R19 * R20
312 [-]: SUB       R18 R18 R19  ; R18 := R18 - R19
313 [-]: GETUPVAL  R19 U22      ; R19 := U22
314 [-]: GETTABLE  R19 R19 K68  ; R19 := R19["bank"]
315 [-]: CALL      R16 4 2      ; R16 := R16(R17,R18,R19)
316 [-]: GETUPVAL  R17 U10      ; R17 := U10
317 [-]: SELF      R17 R17 K69  ; R18 := R17; R17 := R17[0x589ef1c1]
318 [-]: MOVE      R19 R15      ; R19 := R15
319 [-]: MOVE      R20 R16      ; R20 := R16
320 [-]: CALL      R17 4 1      ; R17(R18,R19,R20)
321 [-]: RETURN    R0 1         ; return 


; Function #7:
;
; Name:            
; Defined at line: 233
; #Upvalues:       10
; #Parameters:     0
; Is_vararg:       0
; Max Stack Size:  12

  1 [-]: LOADKB    R0 1 0       ; R0 := true
  2 [-]: SETUPVAL  R0 U0        ; U82 := R0
  3 [-]: GETUPVAL  R0 U1        ; R0 := U1
  4 [-]: SELF      R0 R0 K0     ; R1 := R0; R0 := R0[0x54ab95f9]
  5 [-]: CALL      R0 2 2       ; R0 := R0(R1)
  6 [-]: GETGLOBAL R1 K1        ; R1 := 0x78ca68a2
  7 [-]: MOVE      R2 R0        ; R2 := R0
  8 [-]: LOADK     R3 K2        ; R3 := 0.100000
  9 [-]: CALL      R1 3 2       ; R1 := R1(R2,R3)
 10 [-]: SETUPVAL  R1 U1        ; U82 := R1
 11 [-]: GETUPVAL  R1 U1        ; R1 := U1
 12 [-]: SELF      R1 R1 K3     ; R2 := R1; R1 := R1[0x188e2bee]
 13 [-]: CONST     R3 0         ; R3 := 0.000000
 14 [-]: CALL      R1 3 1       ; R1(R2,R3)
 15 [-]: GETUPVAL  R1 U2        ; R1 := U2
 16 [-]: SELF      R1 R1 K0     ; R2 := R1; R1 := R1[0x54ab95f9]
 17 [-]: CALL      R1 2 2       ; R1 := R1(R2)
 18 [-]: GETGLOBAL R2 K1        ; R2 := 0x78ca68a2
 19 [-]: MOVE      R3 R1        ; R3 := R1
 20 [-]: LOADK     R4 K2        ; R4 := 0.100000
 21 [-]: CALL      R2 3 2       ; R2 := R2(R3,R4)
 22 [-]: SETUPVAL  R2 U2        ; U82 := R2
 23 [-]: CONST     R2 0         ; R2 := 0.000000
 24 [-]: SETUPVAL  R2 U3        ; U82 := R3
 25 [-]: GETUPVAL  R2 U4        ; R2 := U4
 26 [-]: SELF      R2 R2 K0     ; R3 := R2; R2 := R2[0x54ab95f9]
 27 [-]: CALL      R2 2 2       ; R2 := R2(R3)
 28 [-]: GETGLOBAL R3 K1        ; R3 := 0x78ca68a2
 29 [-]: MOVE      R4 R2        ; R4 := R2
 30 [-]: LOADK     R5 K2        ; R5 := 0.100000
 31 [-]: CALL      R3 3 2       ; R3 := R3(R4,R5)
 32 [-]: SETUPVAL  R3 U4        ; U82 := R4
 33 [-]: CONST     R3 0         ; R3 := 0.000000
 34 [-]: SETUPVAL  R3 U5        ; U82 := R5
 35 [-]: GETUPVAL  R3 U6        ; R3 := U6
 36 [-]: SELF      R3 R3 K4     ; R4 := R3; R3 := R3[0x0b4bcfb6]
 37 [-]: CALL      R3 2 2       ; R3 := R3(R4)
 38 [-]: SELF      R3 R3 K5     ; R4 := R3; R3 := R3[0x47de28d6]
 39 [-]: LOADK     R5 K6        ; R5 := 0.700000
 40 [-]: LOADKB    R6 0 0       ; R6 := false
 41 [-]: CALL      R3 4 1       ; R3(R4,R5,R6)
 42 [-]: GETGLOBAL R3 K7        ; R3 := 0x7b998233
 43 [-]: GETUPVAL  R4 U7        ; R4 := U7
 44 [-]: CALL      R3 2 2       ; R3 := R3(R4)
 45 [-]: TEST      R3 1         ; if R3 then PC := 50
 46 [-]: JMP       50           ; PC := 50
 47 [-]: GETUPVAL  R3 U7        ; R3 := U7
 48 [-]: SELF      R3 R3 K8     ; R4 := R3; R3 := R3[0xa2880940]
 49 [-]: CALL      R3 2 1       ; R3(R4)
 50 [-]: GETGLOBAL R3 K9        ; R3 := 0x25312c9b
 51 [-]: GETGLOBAL R4 K10       ; R4 := 0xae91e43b
 52 [-]: LOADK     R5 K11       ; R5 := "_root"
 53 [-]: CONST     R6 0         ; R6 := 0.000000
 54 [-]: NEWTABLE  R7 1 0       ; R7 := {}
 55 [-]: CONST     R8 10        ; R8 := 10.000000
 56 [-]: SETLIST   R7 1 1       ; R7[(1-1)*FPF+i] := R(7+i), 1 <= i <= 1
 57 [-]: NEWTABLE  R8 1 0       ; R8 := {}
 58 [-]: CONST     R9 0         ; R9 := 0.000000
 59 [-]: SETLIST   R8 1 1       ; R8[(1-1)*FPF+i] := R(8+i), 1 <= i <= 1
 60 [-]: LOADK     R9 K13       ; R9 := 0.300000
 61 [-]: CONST     R10 0        ; R10 := 0.000000
 62 [-]: CLOSURE   R11 0        ; R11 := closure(Function #7.1)
 63 [-]: GETUPVAL  R0 U8        ; R0 := U8
 64 [-]: GETUPVAL  R0 U9        ; R0 := U9
 65 [-]: CALL      R3 9 1       ; R3(R4,R5,R6,R7,R8,R9,R10,R11)
 66 [-]: RETURN    R0 1         ; return 


; Function #7.1:
;
; Name:            
; Defined at line: 254
; #Upvalues:       2
; #Parameters:     0
; Is_vararg:       0
; Max Stack Size:  3

  1 [-]: GETGLOBAL R0 K0        ; R0 := 0x7b998233
  2 [-]: GETGLOBAL R1 K1        ; R1 := 0x41b923dc
  3 [-]: CALL      R0 2 2       ; R0 := R0(R1)
  4 [-]: TEST      R0 1         ; if R0 then PC := 10
  5 [-]: JMP       10           ; PC := 10
  6 [-]: GETUPVAL  R0 U0        ; R0 := U0
  7 [-]: GETTABLE  R0 R0 K2     ; R0 := R0[0x659d451f]
  8 [-]: GETGLOBAL R1 K1        ; R1 := 0x41b923dc
  9 [-]: CALL      R0 2 1       ; R0(R1)
 10 [-]: GETGLOBAL R0 K3        ; R0 := _T
 11 [-]: SETTABLE  R0 K4 K5     ; R0["Transmissions_Visible"] := true
 12 [-]: GETUPVAL  R0 U1        ; R0 := U1
 13 [-]: SELF      R0 R0 K6     ; R1 := R0; R0 := R0[0x8eb2112d]
 14 [-]: LOADK     R2 K7        ; R2 := "Close"
 15 [-]: CALL      R0 3 1       ; R0(R1,R2)
 16 [-]: RETURN    R0 1         ; return 


; Function #8:
;
; Name:            
; Defined at line: 263
; #Upvalues:       3
; #Parameters:     2
; Is_vararg:       0
; Max Stack Size:  6

  1 [-]: GETUPVAL  R2 U0        ; R2 := U0
  2 [-]: TEST      R2 1         ; if R2 then PC := 16
  3 [-]: JMP       16           ; PC := 16
  4 [-]: GETGLOBAL R2 K0        ; R2 := 0x42dcc9f5
  5 [-]: GETUPVAL  R3 U1        ; R3 := U1
  6 [-]: GETGLOBAL R4 K1        ; R4 := 0x03f57322
  7 [-]: MOVE      R5 R1        ; R5 := R1
  8 [-]: CALL      R4 2 2       ; R4 := R4(R5)
  9 [-]: MUL       R4 R4 K2     ; R4 := R4 * 0.000500
 10 [-]: SUB       R3 R3 R4     ; R3 := R3 - R4
 11 [-]: GETUPVAL  R4 U2        ; R4 := U2
 12 [-]: UNM       R4 R4        ; R4 :=  R4
 13 [-]: GETUPVAL  R5 U2        ; R5 := U2
 14 [-]: CALL      R2 4 2       ; R2 := R2(R3,R4,R5)
 15 [-]: SETUPVAL  R2 U1        ; U82 := R1
 16 [-]: LOADKB    R2 1 0       ; R2 := true
 17 [-]: RETURN    R2 2         ; return R2
 18 [-]: RETURN    R0 1         ; return 


; Function #9:
;
; Name:            
; Defined at line: 270
; #Upvalues:       3
; #Parameters:     2
; Is_vararg:       0
; Max Stack Size:  6

  1 [-]: GETUPVAL  R2 U0        ; R2 := U0
  2 [-]: TEST      R2 1         ; if R2 then PC := 16
  3 [-]: JMP       16           ; PC := 16
  4 [-]: GETGLOBAL R2 K0        ; R2 := 0x42dcc9f5
  5 [-]: GETUPVAL  R3 U1        ; R3 := U1
  6 [-]: GETGLOBAL R4 K1        ; R4 := 0x03f57322
  7 [-]: MOVE      R5 R1        ; R5 := R1
  8 [-]: CALL      R4 2 2       ; R4 := R4(R5)
  9 [-]: MUL       R4 R4 K2     ; R4 := R4 * 0.002000
 10 [-]: SUB       R3 R3 R4     ; R3 := R3 - R4
 11 [-]: GETUPVAL  R4 U2        ; R4 := U2
 12 [-]: UNM       R4 R4        ; R4 :=  R4
 13 [-]: GETUPVAL  R5 U2        ; R5 := U2
 14 [-]: CALL      R2 4 2       ; R2 := R2(R3,R4,R5)
 15 [-]: SETUPVAL  R2 U1        ; U82 := R1
 16 [-]: LOADKB    R2 1 0       ; R2 := true
 17 [-]: RETURN    R2 2         ; return R2
 18 [-]: RETURN    R0 1         ; return 


; Function #10:
;
; Name:            
; Defined at line: 277
; #Upvalues:       2
; #Parameters:     2
; Is_vararg:       0
; Max Stack Size:  5

  1 [-]: GETUPVAL  R2 U0        ; R2 := U0
  2 [-]: TEST      R2 1         ; if R2 then PC := 10
  3 [-]: JMP       10           ; PC := 10
  4 [-]: GETUPVAL  R2 U1        ; R2 := U1
  5 [-]: GETGLOBAL R3 K1        ; R3 := 0x03f57322
  6 [-]: MOVE      R4 R1        ; R4 := R1
  7 [-]: CALL      R3 2 2       ; R3 := R3(R4)
  8 [-]: UNM       R3 R3        ; R3 :=  R3
  9 [-]: SETTABLE  R2 K0 R3     ; R2["y"] := R3
 10 [-]: RETURN    R0 1         ; return 


; Function #11:
;
; Name:            
; Defined at line: 283
; #Upvalues:       2
; #Parameters:     2
; Is_vararg:       0
; Max Stack Size:  5

  1 [-]: GETUPVAL  R2 U0        ; R2 := U0
  2 [-]: TEST      R2 1         ; if R2 then PC := 10
  3 [-]: JMP       10           ; PC := 10
  4 [-]: GETUPVAL  R2 U1        ; R2 := U1
  5 [-]: GETGLOBAL R3 K1        ; R3 := 0x03f57322
  6 [-]: MOVE      R4 R1        ; R4 := R1
  7 [-]: CALL      R3 2 2       ; R3 := R3(R4)
  8 [-]: UNM       R3 R3        ; R3 :=  R3
  9 [-]: SETTABLE  R2 K0 R3     ; R2["y"] := R3
 10 [-]: RETURN    R0 1         ; return 


; Function #12:
;
; Name:            
; Defined at line: 289
; #Upvalues:       2
; #Parameters:     2
; Is_vararg:       0
; Max Stack Size:  5

  1 [-]: GETUPVAL  R2 U0        ; R2 := U0
  2 [-]: TEST      R2 1         ; if R2 then PC := 9
  3 [-]: JMP       9            ; PC := 9
  4 [-]: GETUPVAL  R2 U1        ; R2 := U1
  5 [-]: GETGLOBAL R3 K1        ; R3 := 0x03f57322
  6 [-]: MOVE      R4 R1        ; R4 := R1
  7 [-]: CALL      R3 2 2       ; R3 := R3(R4)
  8 [-]: SETTABLE  R2 K0 R3     ; R2["y"] := R3
  9 [-]: RETURN    R0 1         ; return 


; Function #13:
;
; Name:            
; Defined at line: 295
; #Upvalues:       2
; #Parameters:     2
; Is_vararg:       0
; Max Stack Size:  5

  1 [-]: GETUPVAL  R2 U0        ; R2 := U0
  2 [-]: TEST      R2 1         ; if R2 then PC := 9
  3 [-]: JMP       9            ; PC := 9
  4 [-]: GETUPVAL  R2 U1        ; R2 := U1
  5 [-]: GETGLOBAL R3 K1        ; R3 := 0x03f57322
  6 [-]: MOVE      R4 R1        ; R4 := R1
  7 [-]: CALL      R3 2 2       ; R3 := R3(R4)
  8 [-]: SETTABLE  R2 K0 R3     ; R2["y"] := R3
  9 [-]: RETURN    R0 1         ; return 


; Function #14:
;
; Name:            
; Defined at line: 301
; #Upvalues:       2
; #Parameters:     2
; Is_vararg:       0
; Max Stack Size:  5

  1 [-]: GETUPVAL  R2 U0        ; R2 := U0
  2 [-]: TEST      R2 1         ; if R2 then PC := 9
  3 [-]: JMP       9            ; PC := 9
  4 [-]: GETUPVAL  R2 U1        ; R2 := U1
  5 [-]: GETGLOBAL R3 K1        ; R3 := 0x03f57322
  6 [-]: MOVE      R4 R1        ; R4 := R1
  7 [-]: CALL      R3 2 2       ; R3 := R3(R4)
  8 [-]: SETTABLE  R2 K0 R3     ; R2["x"] := R3
  9 [-]: LOADKB    R2 1 0       ; R2 := true
 10 [-]: RETURN    R2 2         ; return R2
 11 [-]: RETURN    R0 1         ; return 


; Function #15:
;
; Name:            
; Defined at line: 308
; #Upvalues:       2
; #Parameters:     2
; Is_vararg:       0
; Max Stack Size:  5

  1 [-]: GETUPVAL  R2 U0        ; R2 := U0
  2 [-]: TEST      R2 1         ; if R2 then PC := 9
  3 [-]: JMP       9            ; PC := 9
  4 [-]: GETUPVAL  R2 U1        ; R2 := U1
  5 [-]: GETGLOBAL R3 K1        ; R3 := 0x03f57322
  6 [-]: MOVE      R4 R1        ; R4 := R1
  7 [-]: CALL      R3 2 2       ; R3 := R3(R4)
  8 [-]: SETTABLE  R2 K0 R3     ; R2["x"] := R3
  9 [-]: LOADKB    R2 1 0       ; R2 := true
 10 [-]: RETURN    R2 2         ; return R2
 11 [-]: RETURN    R0 1         ; return 


; Function #16:
;
; Name:            
; Defined at line: 315
; #Upvalues:       2
; #Parameters:     2
; Is_vararg:       0
; Max Stack Size:  3

  1 [-]: GETUPVAL  R2 U0        ; R2 := U0
  2 [-]: TEST      R2 1         ; if R2 then PC := 6
  3 [-]: JMP       6            ; PC := 6
  4 [-]: GETUPVAL  R2 U1        ; R2 := U1
  5 [-]: SETTABLE  R2 K0 K1     ; R2["y"] := -0.500000
  6 [-]: LOADKB    R2 1 0       ; R2 := true
  7 [-]: RETURN    R2 2         ; return R2
  8 [-]: RETURN    R0 1         ; return 


; Function #17:
;
; Name:            
; Defined at line: 322
; #Upvalues:       2
; #Parameters:     2
; Is_vararg:       0
; Max Stack Size:  3

  1 [-]: GETUPVAL  R2 U0        ; R2 := U0
  2 [-]: TEST      R2 1         ; if R2 then PC := 6
  3 [-]: JMP       6            ; PC := 6
  4 [-]: GETUPVAL  R2 U1        ; R2 := U1
  5 [-]: SETTABLE  R2 K0 K1     ; R2["y"] := 0.000000
  6 [-]: LOADKB    R2 1 0       ; R2 := true
  7 [-]: RETURN    R2 2         ; return R2
  8 [-]: RETURN    R0 1         ; return 


; Function #18:
;
; Name:            
; Defined at line: 329
; #Upvalues:       2
; #Parameters:     0
; Is_vararg:       0
; Max Stack Size:  2

  1 [-]: GETUPVAL  R0 U0        ; R0 := U0
  2 [-]: TEST      R0 1         ; if R0 then PC := 6
  3 [-]: JMP       6            ; PC := 6
  4 [-]: GETUPVAL  R0 U1        ; R0 := U1
  5 [-]: SETTABLE  R0 K0 K1     ; R0["y"] := 0.500000
  6 [-]: LOADKB    R0 1 0       ; R0 := true
  7 [-]: RETURN    R0 2         ; return R0
  8 [-]: RETURN    R0 1         ; return 


; Function #19:
;
; Name:            
; Defined at line: 336
; #Upvalues:       2
; #Parameters:     0
; Is_vararg:       0
; Max Stack Size:  2

  1 [-]: GETUPVAL  R0 U0        ; R0 := U0
  2 [-]: TEST      R0 1         ; if R0 then PC := 6
  3 [-]: JMP       6            ; PC := 6
  4 [-]: GETUPVAL  R0 U1        ; R0 := U1
  5 [-]: SETTABLE  R0 K0 K1     ; R0["y"] := 0.000000
  6 [-]: LOADKB    R0 1 0       ; R0 := true
  7 [-]: RETURN    R0 2         ; return R0
  8 [-]: RETURN    R0 1         ; return 


; Function #20:
;
; Name:            
; Defined at line: 343
; #Upvalues:       1
; #Parameters:     1
; Is_vararg:       0
; Max Stack Size:  2

  1 [-]: SETUPVAL  R0 U0        ; U82 := R0
  2 [-]: RETURN    R0 1         ; return 


; Function #21:
;
; Name:            
; Defined at line: 347
; #Upvalues:       2
; #Parameters:     0
; Is_vararg:       0
; Max Stack Size:  2

  1 [-]: GETUPVAL  R0 U0        ; R0 := U0
  2 [-]: TEST      R0 1         ; if R0 then PC := 6
  3 [-]: JMP       6            ; PC := 6
  4 [-]: GETUPVAL  R0 U1        ; R0 := U1
  5 [-]: CALL      R0 1 1       ; R0()
  6 [-]: RETURN    R0 1         ; return 


; Function #22:
;
; Name:            
; Defined at line: 353
; #Upvalues:       2
; #Parameters:     2
; Is_vararg:       0
; Max Stack Size:  6

  1 [-]: GETUPVAL  R2 U0        ; R2 := U0
  2 [-]: TEST      R2 0         ; if not R2 then PC := 5
  3 [-]: JMP       5            ; PC := 5
  4 [-]: RETURN    R0 1         ; return 
  5 [-]: GETUPVAL  R2 U1        ; R2 := U1
  6 [-]: SELF      R2 R2 K0     ; R3 := R2; R2 := R2[0x30456f58]
  7 [-]: GETGLOBAL R4 K1        ; R4 := 0x03f57322
  8 [-]: MOVE      R5 R1        ; R5 := R1
  9 [-]: CALL      R4 2 2       ; R4 := R4(R5)
 10 [-]: GETGLOBAL R5 K2        ; R5 := 0x0032441c
 11 [-]: GETTABLE  R5 R5 K3     ; R5 := R5["UISound_Scroll"]
 12 [-]: CALL      R2 4 1       ; R2(R3,R4,R5)
 13 [-]: RETURN    R0 1         ; return 


; Function #23:
;
; Name:            
; Defined at line: 361
; #Upvalues:       1
; #Parameters:     2
; Is_vararg:       0
; Max Stack Size:  3

  1 [-]: GETUPVAL  R2 U0        ; R2 := U0
  2 [-]: CALL      R2 1 1       ; R2()
  3 [-]: RETURN    R0 1         ; return 


; Function #24:
;
; Name:            
; Defined at line: 365
; #Upvalues:       0
; #Parameters:     0
; Is_vararg:       0
; Max Stack Size:  2

  1 [-]: LOADKB    R0 1 0       ; R0 := true
  2 [-]: RETURN    R0 2         ; return R0
  3 [-]: RETURN    R0 1         ; return 


