; Name:            
; Defined at line: 1
; #Upvalues:       0
; #Parameters:     0
; Is_vararg:       1
; Max Stack Size:  42

       1 [-]: GETIMPORT R0 1; var0 = 0x2D0FAD09
       2 [-]: LOADK R1 K2  ; var1 = "EE.Interface.Utilities"
       3 [-]: CALL R0 2 2  ; var0 = var0(var1)
       4 [-]: GETIMPORT R1 1; var1 = 0x2D0FAD09
       5 [-]: LOADK R2 K3  ; var2 = "Lotus.Interface.UIStyleUtilities"
       6 [-]: CALL R1 2 2  ; var1 = var1(var2)
       7 [-]: GETIMPORT R2 1; var2 = 0x2D0FAD09
       8 [-]: LOADK R3 K4  ; var3 = "Lotus.Interface.LotusUtilities"
       9 [-]: CALL R2 2 2  ; var2 = var2(var3)
      10 [-]: GETIMPORT R3 1; var3 = 0x2D0FAD09
      11 [-]: LOADK R4 K5  ; var4 = "EE.Interface.AnchorMgr"
      12 [-]: CALL R3 2 2  ; var3 = var3(var4)
      13 [-]: LOADN R4 8   ; var4 = 8
      14 [-]: NEWTABLE R5 0 0; var5 = {}
      15 [-]: LOADNIL R6   ; var6 = nil
      16 [-]: LOADNIL R7   ; var7 = nil
      17 [-]: LOADB R8 0   ; var8 = false
      18 [-]: LOADB R9 0   ; var9 = false
      19 [-]: LOADB R10 0  ; var10 = false
      20 [-]: LOADB R11 0  ; var11 = false
      21 [-]: LOADK R12 K6 ; var12 = ""
      22 [-]: LOADB R13 0  ; var13 = false
      23 [-]: LOADNIL R14  ; var14 = nil
      24 [-]: LOADNIL R15  ; var15 = nil
      25 [-]: LOADNIL R16  ; var16 = nil
      26 [-]: LOADNIL R17  ; var17 = nil
      27 [-]: LOADNIL R18  ; var18 = nil
      28 [-]: GETIMPORT R19 8; var19 = 0x78CA68A2
      29 [-]: LOADN R20 1  ; var20 = 1
      30 [-]: LOADK R21 K9 ; var21 = 0.5
      31 [-]: CALL R19 3 2 ; var19 = var19(var20, var21)
      32 [-]: LOADNIL R20  ; var20 = nil
      33 [-]: LOADNIL R21  ; var21 = nil
      34 [-]: LOADNIL R22  ; var22 = nil
      35 [-]: LOADNIL R23  ; var23 = nil
      36 [-]: LOADNIL R24  ; var24 = nil
      37 [-]: LOADNIL R25  ; var25 = nil
      38 [-]: LOADNIL R26  ; var26 = nil
      39 [-]: LOADNIL R27  ; var27 = nil
      40 [-]: LOADNIL R28  ; var28 = nil
      41 [-]: LOADNIL R29  ; var29 = nil
      42 [-]: LOADNIL R30  ; var30 = nil
      43 [-]: LOADNIL R31  ; var31 = nil
      44 [-]: LOADNIL R32  ; var32 = nil
      45 [-]: LOADNIL R33  ; var33 = nil
      46 [-]: LOADNIL R34  ; var34 = nil
      47 [-]: NEWCLOSURE R35 P0; 
      48 [-]: CAPTURE VAL R1; 
      49 [-]: CAPTURE REF R8; 
      50 [-]: CAPTURE VAL R2; 
      51 [-]: CAPTURE REF R21; 
      52 [-]: CAPTURE REF R22; 
      53 [-]: CAPTURE REF R34; 
      54 [-]: CAPTURE REF R16; 
      55 [-]: SETGLOBAL R35 K10; "Shutdown" = var35
      56 [-]: NEWCLOSURE R35 P1; 
      57 [-]: CAPTURE REF R20; 
      58 [-]: CAPTURE VAL R0; 
      59 [-]: CAPTURE REF R27; 
      60 [-]: NEWCLOSURE R36 P2; 
      61 [-]: CAPTURE REF R17; 
      62 [-]: CAPTURE REF R15; 
      63 [-]: CAPTURE REF R14; 
      64 [-]: CAPTURE REF R20; 
      65 [-]: CAPTURE VAL R0; 
      66 [-]: CAPTURE REF R27; 
      67 [-]: SETGLOBAL R36 K11; "SelectPressCallback" = var36
      68 [-]: NEWCLOSURE R36 P3; 
      69 [-]: CAPTURE REF R34; 
      70 [-]: SETGLOBAL R36 K12; "SelectReleaseCallback" = var36
      71 [-]: NEWCLOSURE R36 P4; 
      72 [-]: CAPTURE REF R5; 
      73 [-]: CAPTURE VAL R0; 
      74 [-]: NEWCLOSURE R37 P5; 
      75 [-]: CAPTURE REF R11; 
      76 [-]: CAPTURE REF R13; 
      77 [-]: CAPTURE REF R33; 
      78 [-]: NEWCLOSURE R38 P6; 
      79 [-]: CAPTURE REF R11; 
      80 [-]: CAPTURE REF R13; 
      81 [-]: CAPTURE REF R33; 
      82 [-]: NEWCLOSURE R39 P7; 
      83 [-]: CAPTURE REF R11; 
      84 [-]: CAPTURE REF R13; 
      85 [-]: CAPTURE REF R33; 
      86 [-]: SETGLOBAL R39 K13; "CountdownDone" = var39
      87 [-]: NEWCLOSURE R39 P8; 
      88 [-]: CAPTURE REF R16; 
      89 [-]: CAPTURE REF R12; 
      90 [-]: DUPCLOSURE R40 K14; 
      91 [-]: SETGLOBAL R40 K15; "OnPopupFrameEnter" = var40
      92 [-]: NEWCLOSURE R40 P10; 
      93 [-]: CAPTURE REF R7; 
      94 [-]: CAPTURE VAL R1; 
      95 [-]: CAPTURE REF R5; 
      96 [-]: CAPTURE REF R6; 
      97 [-]: CAPTURE VAL R3; 
      98 [-]: CAPTURE REF R9; 
      99 [-]: CAPTURE REF R8; 
     100 [-]: CAPTURE REF R10; 
     101 [-]: CAPTURE REF R12; 
     102 [-]: CAPTURE VAL R0; 
     103 [-]: CAPTURE REF R23; 
     104 [-]: CAPTURE REF R24; 
     105 [-]: CAPTURE REF R25; 
     106 [-]: CAPTURE REF R26; 
     107 [-]: CAPTURE REF R27; 
     108 [-]: CAPTURE REF R28; 
     109 [-]: CAPTURE REF R29; 
     110 [-]: CAPTURE REF R30; 
     111 [-]: CAPTURE REF R31; 
     112 [-]: CAPTURE REF R32; 
     113 [-]: CAPTURE REF R21; 
     114 [-]: CAPTURE REF R22; 
     115 [-]: CAPTURE VAL R2; 
     116 [-]: CAPTURE REF R4; 
     117 [-]: CAPTURE VAL R37; 
     118 [-]: CAPTURE REF R14; 
     119 [-]: CAPTURE VAL R36; 
     120 [-]: CAPTURE VAL R38; 
     121 [-]: CAPTURE REF R15; 
     122 [-]: SETGLOBAL R40 K16; "Initialize" = var40
     123 [-]: NEWCLOSURE R40 P11; 
     124 [-]: CAPTURE REF R15; 
     125 [-]: CAPTURE REF R14; 
     126 [-]: CAPTURE REF R11; 
     127 [-]: CAPTURE VAL R0; 
     128 [-]: CAPTURE REF R31; 
     129 [-]: CAPTURE REF R17; 
     130 [-]: CAPTURE REF R18; 
     131 [-]: CAPTURE VAL R19; 
     132 [-]: NEWCLOSURE R41 P12; 
     133 [-]: CAPTURE REF R7; 
     134 [-]: CAPTURE VAL R40; 
     135 [-]: SETGLOBAL R41 K17; "Update" = var41
     136 [-]: DUPCLOSURE R41 K18; 
     137 [-]: SETGLOBAL R41 K19; "onVieportSizeChanged" = var41
     138 [-]: NEWCLOSURE R33 P14; 
     139 [-]: CAPTURE REF R11; 
     140 [-]: CAPTURE REF R15; 
     141 [-]: CAPTURE REF R13; 
     142 [-]: CAPTURE REF R14; 
     143 [-]: CAPTURE VAL R0; 
     144 [-]: CAPTURE REF R16; 
     145 [-]: CAPTURE REF R8; 
     146 [-]: NEWCLOSURE R41 P15; 
     147 [-]: CAPTURE REF R33; 
     148 [-]: CAPTURE REF R25; 
     149 [-]: CAPTURE VAL R0; 
     150 [-]: SETGLOBAL R41 K20; "TransitionOut" = var41
     151 [-]: NEWCLOSURE R41 P16; 
     152 [-]: CAPTURE REF R8; 
     153 [-]: CAPTURE REF R12; 
     154 [-]: CAPTURE REF R10; 
     155 [-]: CAPTURE VAL R0; 
     156 [-]: CAPTURE VAL R39; 
     157 [-]: CAPTURE REF R7; 
     158 [-]: CAPTURE REF R4; 
     159 [-]: SETGLOBAL R41 K21; "AssassinatedTextUp" = var41
     160 [-]: NEWCLOSURE R41 P17; 
     161 [-]: CAPTURE REF R6; 
     162 [-]: SETGLOBAL R41 K22; "onViewportSizeChanged" = var41
     163 [-]: DUPCLOSURE R41 K23; 
     164 [-]: SETGLOBAL R41 K24; "SupportsThemes" = var41
     165 [-]: NEWCLOSURE R34 P19; 
     166 [-]: CAPTURE REF R17; 
     167 [-]: CAPTURE REF R20; 
     168 [-]: NEWCLOSURE R41 P20; 
     169 [-]: CAPTURE REF R17; 
     170 [-]: CAPTURE REF R15; 
     171 [-]: CAPTURE REF R20; 
     172 [-]: CAPTURE VAL R0; 
     173 [-]: CAPTURE REF R27; 
     174 [-]: SETGLOBAL R41 K25; "onKeyDown_MENU_RIGHT" = var41
     175 [-]: NEWCLOSURE R41 P21; 
     176 [-]: CAPTURE REF R17; 
     177 [-]: CAPTURE REF R15; 
     178 [-]: CAPTURE REF R34; 
     179 [-]: SETGLOBAL R41 K26; "onKeyUp_MENU_RIGHT" = var41
     180 [-]: NEWCLOSURE R41 P22; 
     181 [-]: CAPTURE REF R17; 
     182 [-]: CAPTURE REF R14; 
     183 [-]: CAPTURE REF R20; 
     184 [-]: CAPTURE VAL R0; 
     185 [-]: CAPTURE REF R27; 
     186 [-]: SETGLOBAL R41 K27; "onKeyDown_MENU_LEFT" = var41
     187 [-]: NEWCLOSURE R41 P23; 
     188 [-]: CAPTURE REF R17; 
     189 [-]: CAPTURE REF R14; 
     190 [-]: CAPTURE REF R34; 
     191 [-]: SETGLOBAL R41 K28; "onKeyUp_MENU_LEFT" = var41
     192 [-]: CLOSEUPVALS R4; 
     193 [-]: RETURN R0 0  ; 


; Name:            
; Defined at line: 75
; #Upvalues:       7
; #Parameters:     0
; Is_vararg:       0
; Max Stack Size:  3

       0 [-]: GETIMPORT R0 1; var0 = _T
       1 [-]: LOADB R1 0   ; var1 = false
       2 [-]: SETTABLEKS R1 R0 K2; var1["NemesisPopup_RankUpVisible"] = var0
       3 [-]: GETUPVAL R1 0; var1 = upvalues[0]
       4 [-]: GETTABLEKS R0 R1 K3; var0 = var1[0x1146D233]
       5 [-]: CALL R0 1 1  ; var0()
       6 [-]: GETUPVAL R0 1; var0 = upvalues[1]
       7 [-]: JUMPIFNOT R0 L0; goto L0 if not var0
       8 [-]: GETUPVAL R1 2; var1 = upvalues[2]
       9 [-]: GETTABLEKS R0 R1 K4; var0 = var1[0x9E3D3434]
      10 [-]: LOADB R1 0   ; var1 = false
      11 [-]: CALL R0 2 1  ; var0(var1)
L 0:  12 [-]: GETUPVAL R1 3; var1 = upvalues[3]
      13 [-]: FASTCALL1 64 R1 L1; 
      14 [-]: GETIMPORT R0 6; var0 = 0x7B998233
      15 [-]: CALL R0 2 2  ; var0 = var0(var1)
L 1:  16 [-]: JUMPIF R0 L2 ; goto L2 if var0
      17 [-]: GETUPVAL R0 3; var0 = upvalues[3]
      18 [-]: LOADB R2 1   ; var2 = true
      19 [-]: NAMECALL R0 R0 K7; var1 = var0; var0 = var0[0x6CF1E476]
      20 [-]: CALL R0 3 1  ; var0(var1, var2)
L 2:  21 [-]: GETUPVAL R1 4; var1 = upvalues[4]
      22 [-]: FASTCALL1 64 R1 L3; 
      23 [-]: GETIMPORT R0 6; var0 = 0x7B998233
      24 [-]: CALL R0 2 2  ; var0 = var0(var1)
L 3:  25 [-]: JUMPIF R0 L4 ; goto L4 if var0
      26 [-]: GETUPVAL R0 4; var0 = upvalues[4]
      27 [-]: LOADB R2 1   ; var2 = true
      28 [-]: NAMECALL R0 R0 K7; var1 = var0; var0 = var0[0x6CF1E476]
      29 [-]: CALL R0 3 1  ; var0(var1, var2)
L 4:  30 [-]: GETUPVAL R0 5; var0 = upvalues[5]
      31 [-]: CALL R0 1 1  ; var0()
      32 [-]: GETUPVAL R1 6; var1 = upvalues[6]
      33 [-]: FASTCALL1 64 R1 L5; 
      34 [-]: GETIMPORT R0 6; var0 = 0x7B998233
      35 [-]: CALL R0 2 2  ; var0 = var0(var1)
L 5:  36 [-]: JUMPIF R0 L6 ; goto L6 if var0
      37 [-]: GETUPVAL R0 6; var0 = upvalues[6]
      38 [-]: NAMECALL R0 R0 K8; var1 = var0; var0 = var0[0x32302B4A]
      39 [-]: CALL R0 2 1  ; var0(var1)
L 6:  40 [-]: RETURN R0 0  ; 


; Name:            
; Defined at line: 100
; #Upvalues:       3
; #Parameters:     0
; Is_vararg:       0
; Max Stack Size:  2

       0 [-]: GETUPVAL R1 0; var1 = upvalues[0]
       1 [-]: FASTCALL1 64 R1 L0; 
       2 [-]: GETIMPORT R0 1; var0 = 0x7B998233
       3 [-]: CALL R0 2 2  ; var0 = var0(var1)
L 0:   4 [-]: JUMPIFNOT R0 L1; goto L1 if not var0
       5 [-]: GETUPVAL R1 1; var1 = upvalues[1]
       6 [-]: GETTABLEKS R0 R1 K2; var0 = var1[0x659D451F]
       7 [-]: GETUPVAL R1 2; var1 = upvalues[2]
       8 [-]: CALL R0 2 2  ; var0 = var0(var1)
       9 [-]: SETUPVAL R0 0; upvalues[0] = var0
L 1:  10 [-]: RETURN R0 0  ; 


; Name:            
; Defined at line: 106
; #Upvalues:       6
; #Parameters:     3
; Is_vararg:       0
; Max Stack Size:  5

       0 [-]: JUMPXEQKS R1 K0 L0 NOT; 
       1 [-]: GETUPVAL R3 1; var3 = upvalues[1]
       2 [-]: SETUPVAL R3 0; upvalues[3] = var0
       3 [-]: JUMP L1      ; goto L1
L 0:   4 [-]: JUMPXEQKS R1 K1 L1 NOT; 
       5 [-]: GETUPVAL R3 2; var3 = upvalues[2]
       6 [-]: SETUPVAL R3 0; upvalues[3] = var0
L 1:   7 [-]: GETUPVAL R4 3; var4 = upvalues[3]
       8 [-]: FASTCALL1 64 R4 L2; 
       9 [-]: GETIMPORT R3 3; var3 = 0x7B998233
      10 [-]: CALL R3 2 2  ; var3 = var3(var4)
L 2:  11 [-]: JUMPIFNOT R3 L3; goto L3 if not var3
      12 [-]: GETUPVAL R4 4; var4 = upvalues[4]
      13 [-]: GETTABLEKS R3 R4 K4; var3 = var4[0x659D451F]
      14 [-]: GETUPVAL R4 5; var4 = upvalues[5]
      15 [-]: CALL R3 2 2  ; var3 = var3(var4)
      16 [-]: SETUPVAL R3 3; upvalues[3] = var3
L 3:  17 [-]: RETURN R0 0  ; 


; Name:            
; Defined at line: 116
; #Upvalues:       1
; #Parameters:     3
; Is_vararg:       0
; Max Stack Size:  4

       0 [-]: GETUPVAL R3 0; var3 = upvalues[0]
       1 [-]: CALL R3 1 1  ; var3()
       2 [-]: RETURN R0 0  ; 


; Name:            
; Defined at line: 120
; #Upvalues:       2
; #Parameters:     2
; Is_vararg:       0
; Max Stack Size:  12

       0 [-]: GETIMPORT R2 1; var2 = 0xAE91E43B
       1 [-]: LOADK R4 K2  ; var4 = "/Lotus/Language/Kingpins/Choice_Callout"
       2 [-]: LOADB R5 1   ; var5 = true
       3 [-]: DUPTABLE R6 4; 
       4 [-]: GETTABLEKS R7 R1 K5; var7 = var1["BtnCallout"]
       5 [-]: SETTABLEKS R7 R6 K3; var7["CALLOUT"] = var6
       6 [-]: NAMECALL R2 R2 K6; var3 = var2; var2 = var2[0x42B04007]
       7 [-]: CALL R2 5 2  ; var2 = var2(var3, var4, var5, var6)
       8 [-]: GETIMPORT R3 1; var3 = 0xAE91E43B
       9 [-]: MOVE R5 R0   ; var5 = var0
      10 [-]: LOADK R6 K7  ; var6 = "Callout.Tf"
      11 [-]: LOADN R7 31  ; var7 = 31
      12 [-]: MOVE R8 R2   ; var8 = var2
      13 [-]: NAMECALL R3 R3 K8; var4 = var3; var3 = var3[0xE261AA96]
      14 [-]: CALL R3 6 1  ; var3(var4, var5, var6, var7, var8)
      15 [-]: GETIMPORT R3 1; var3 = 0xAE91E43B
      16 [-]: MOVE R6 R0   ; var6 = var0
      17 [-]: LOADK R7 K9  ; var7 = ".Label.Tf.text"
      18 [-]: CONCAT R5 R6 R7; var5 = var6 .. var7
      19 [-]: GETTABLEKS R6 R1 K10; var6 = var1["BtnLabel"]
      20 [-]: NAMECALL R3 R3 K11; var4 = var3; var3 = var3[0x20B98DB3]
      21 [-]: CALL R3 4 1  ; var3(var4, var5, var6)
      22 [-]: GETIMPORT R3 1; var3 = 0xAE91E43B
      23 [-]: MOVE R5 R0   ; var5 = var0
      24 [-]: LOADK R6 K12 ; var6 = "Label.Tf"
      25 [-]: LOADN R7 38  ; var7 = 38
      26 [-]: GETUPVAL R9 0; var9 = upvalues[0]
      27 [-]: GETTABLEKS R8 R9 K13; var8 = var9["FloatingContent"]
      28 [-]: NAMECALL R3 R3 K14; var4 = var3; var3 = var3[0xF64B7262]
      29 [-]: CALL R3 6 1  ; var3(var4, var5, var6, var7, var8)
      30 [-]: GETIMPORT R3 1; var3 = 0xAE91E43B
      31 [-]: MOVE R5 R0   ; var5 = var0
      32 [-]: LOADK R6 K7  ; var6 = "Callout.Tf"
      33 [-]: LOADN R7 38  ; var7 = 38
      34 [-]: GETUPVAL R9 0; var9 = upvalues[0]
      35 [-]: GETTABLEKS R8 R9 K13; var8 = var9["FloatingContent"]
      36 [-]: NAMECALL R3 R3 K14; var4 = var3; var3 = var3[0xF64B7262]
      37 [-]: CALL R3 6 1  ; var3(var4, var5, var6, var7, var8)
      38 [-]: GETIMPORT R3 1; var3 = 0xAE91E43B
      39 [-]: MOVE R5 R0   ; var5 = var0
      40 [-]: LOADK R6 K15 ; var6 = "Lines"
      41 [-]: LOADN R7 9   ; var7 = 9
      42 [-]: GETUPVAL R9 0; var9 = upvalues[0]
      43 [-]: GETTABLEKS R8 R9 K13; var8 = var9["FloatingContent"]
      44 [-]: NAMECALL R3 R3 K14; var4 = var3; var3 = var3[0xF64B7262]
      45 [-]: CALL R3 6 1  ; var3(var4, var5, var6, var7, var8)
      46 [-]: GETIMPORT R3 1; var3 = 0xAE91E43B
      47 [-]: MOVE R6 R0   ; var6 = var0
      48 [-]: LOADK R7 K16 ; var7 = ".Lines"
      49 [-]: CONCAT R5 R6 R7; var5 = var6 .. var7
      50 [-]: GETIMPORT R7 18; var7 = 0x0032441C
      51 [-]: GETTABLEKS R6 R7 K19; var6 = var7["UIMaterial_VitruvianLines"]
      52 [-]: NAMECALL R3 R3 K20; var4 = var3; var3 = var3[0xD5181643]
      53 [-]: CALL R3 4 1  ; var3(var4, var5, var6)
      54 [-]: GETIMPORT R3 1; var3 = 0xAE91E43B
      55 [-]: MOVE R5 R0   ; var5 = var0
      56 [-]: LOADK R6 K21 ; var6 = "Divider"
      57 [-]: LOADN R7 9   ; var7 = 9
      58 [-]: GETUPVAL R9 0; var9 = upvalues[0]
      59 [-]: GETTABLEKS R8 R9 K13; var8 = var9["FloatingContent"]
      60 [-]: NAMECALL R3 R3 K14; var4 = var3; var3 = var3[0xF64B7262]
      61 [-]: CALL R3 6 1  ; var3(var4, var5, var6, var7, var8)
      62 [-]: GETIMPORT R3 1; var3 = 0xAE91E43B
      63 [-]: MOVE R6 R0   ; var6 = var0
      64 [-]: LOADK R7 K22 ; var7 = ".Icon"
      65 [-]: CONCAT R5 R6 R7; var5 = var6 .. var7
      66 [-]: GETTABLEKS R6 R1 K23; var6 = var1["Icon"]
      67 [-]: GETIMPORT R8 18; var8 = 0x0032441C
      68 [-]: GETTABLEKS R7 R8 K19; var7 = var8["UIMaterial_VitruvianLines"]
      69 [-]: NAMECALL R3 R3 K24; var4 = var3; var3 = var3[0xEF99134F]
      70 [-]: CALL R3 5 1  ; var3(var4, var5, var6, var7)
      71 [-]: GETIMPORT R3 1; var3 = 0xAE91E43B
      72 [-]: MOVE R6 R0   ; var6 = var0
      73 [-]: LOADK R7 K25 ; var7 = ".Shadow"
      74 [-]: CONCAT R5 R6 R7; var5 = var6 .. var7
      75 [-]: GETIMPORT R6 27; var6 = 0xD2F4E481
      76 [-]: NAMECALL R3 R3 K28; var4 = var3; var3 = var3[0x1CB415C1]
      77 [-]: CALL R3 4 1  ; var3(var4, var5, var6)
      78 [-]: GETUPVAL R4 1; var4 = upvalues[1]
      79 [-]: GETTABLEKS R3 R4 K29; var3 = var4[0x8BCD12B6]
      80 [-]: LOADK R4 K30 ; var4 = 6831395
      81 [-]: CALL R3 2 2  ; var3 = var3(var4)
      82 [-]: GETIMPORT R4 1; var4 = 0xAE91E43B
      83 [-]: MOVE R7 R0   ; var7 = var0
      84 [-]: LOADK R8 K22 ; var8 = ".Icon"
      85 [-]: CONCAT R6 R7 R8; var6 = var7 .. var8
      86 [-]: LOADK R7 K31 ; var7 = "RipplesColor"
      87 [-]: GETTABLEKS R8 R3 K32; var8 = var3["r"]
      88 [-]: GETTABLEKS R9 R3 K33; var9 = var3["g"]
      89 [-]: GETTABLEKS R10 R3 K34; var10 = var3["b"]
      90 [-]: LOADN R11 1  ; var11 = 1
      91 [-]: NAMECALL R4 R4 K35; var5 = var4; var4 = var4[0x91E13703]
      92 [-]: CALL R4 8 1  ; var4(var5, var6, var7, var8, var9, var10, var11)
      93 [-]: GETIMPORT R4 38; var4 = 0x34291F5C[0xE6B41ADB]
      94 [-]: CALL R4 1 2  ; var4 = var4()
      95 [-]: JUMPIFNOT R4 L0; goto L0 if not var4
      96 [-]: GETIMPORT R4 1; var4 = 0xAE91E43B
      97 [-]: MOVE R6 R0   ; var6 = var0
      98 [-]: LOADNIL R7   ; var7 = nil
      99 [-]: LOADK R8 K39 ; var8 = "SelectReleaseCallback"
     100 [-]: LOADK R9 K39 ; var9 = "SelectReleaseCallback"
     101 [-]: LOADK R10 K40; var10 = "SelectPressCallback"
     102 [-]: NAMECALL R4 R4 K41; var5 = var4; var4 = var4[0x1E5B5CFE]
     103 [-]: CALL R4 7 1  ; var4(var5, var6, var7, var8, var9, var10)
L 0: 104 [-]: SETTABLEKS R0 R1 K42; var0["ClipName"] = var1
     105 [-]: LOADN R4 0   ; var4 = 0
     106 [-]: SETTABLEKS R4 R1 K43; var4["Hold"] = var1
     107 [-]: GETIMPORT R4 45; var4 = 0x78CA68A2
     108 [-]: LOADN R5 100 ; var5 = 100
     109 [-]: LOADK R6 K46 ; var6 = 0.15000000596046448
     110 [-]: CALL R4 3 2  ; var4 = var4(var5, var6)
     111 [-]: SETTABLEKS R4 R1 K47; var4["SmoothScale"] = var1
     112 [-]: RETURN R1 1  ; 


; Name:            
; Defined at line: 146
; #Upvalues:       3
; #Parameters:     0
; Is_vararg:       0
; Max Stack Size:  1

       0 [-]: LOADB R0 1   ; var0 = true
       1 [-]: SETUPVAL R0 0; upvalues[0] = var0
       2 [-]: LOADB R0 0   ; var0 = false
       3 [-]: SETUPVAL R0 1; upvalues[0] = var1
       4 [-]: GETUPVAL R0 2; var0 = upvalues[2]
       5 [-]: CALL R0 1 1  ; var0()
       6 [-]: RETURN R0 0  ; 


; Name:            
; Defined at line: 152
; #Upvalues:       3
; #Parameters:     0
; Is_vararg:       0
; Max Stack Size:  1

       0 [-]: LOADB R0 1   ; var0 = true
       1 [-]: SETUPVAL R0 0; upvalues[0] = var0
       2 [-]: LOADB R0 1   ; var0 = true
       3 [-]: SETUPVAL R0 1; upvalues[0] = var1
       4 [-]: GETUPVAL R0 2; var0 = upvalues[2]
       5 [-]: CALL R0 1 1  ; var0()
       6 [-]: RETURN R0 0  ; 


; Name:            
; Defined at line: 158
; #Upvalues:       3
; #Parameters:     0
; Is_vararg:       0
; Max Stack Size:  1

       0 [-]: GETUPVAL R0 0; var0 = upvalues[0]
       1 [-]: JUMPIF R0 L0 ; goto L0 if var0
       2 [-]: LOADB R0 1   ; var0 = true
       3 [-]: SETUPVAL R0 0; upvalues[0] = var0
       4 [-]: LOADB R0 1   ; var0 = true
       5 [-]: SETUPVAL R0 1; upvalues[0] = var1
       6 [-]: GETUPVAL R0 2; var0 = upvalues[2]
       7 [-]: CALL R0 1 1  ; var0()
L 0:   8 [-]: RETURN R0 0  ; 


; Name:            
; Defined at line: 165
; #Upvalues:       2
; #Parameters:     0
; Is_vararg:       0
; Max Stack Size:  4

       0 [-]: GETIMPORT R1 1; var1 = 0xFE28B417
       1 [-]: FASTCALL1 64 R1 L0; 
       2 [-]: GETIMPORT R0 3; var0 = 0x7B998233
       3 [-]: CALL R0 2 2  ; var0 = var0(var1)
L 0:   4 [-]: JUMPIFNOT R0 L1; goto L1 if not var0
       5 [-]: RETURN R0 0  ; 
L 1:   6 [-]: GETIMPORT R0 5; var0 = 0xAE91E43B
       7 [-]: GETIMPORT R2 1; var2 = 0xFE28B417
       8 [-]: NAMECALL R0 R0 K6; var1 = var0; var0 = var0[0x1FD6ABD0]
       9 [-]: CALL R0 3 2  ; var0 = var0(var1, var2)
      10 [-]: SETUPVAL R0 0; upvalues[0] = var0
      11 [-]: GETUPVAL R1 0; var1 = upvalues[0]
      12 [-]: FASTCALL1 64 R1 L2; 
      13 [-]: GETIMPORT R0 3; var0 = 0x7B998233
      14 [-]: CALL R0 2 2  ; var0 = var0(var1)
L 2:  15 [-]: JUMPIF R0 L3 ; goto L3 if var0
      16 [-]: GETUPVAL R0 0; var0 = upvalues[0]
      17 [-]: LOADB R2 1   ; var2 = true
      18 [-]: NAMECALL R0 R0 K7; var1 = var0; var0 = var0[0x9275DA44]
      19 [-]: CALL R0 3 1  ; var0(var1, var2)
      20 [-]: GETUPVAL R0 0; var0 = upvalues[0]
      21 [-]: LOADK R2 K8  ; var2 = "SetCountdownSoundThreshold"
      22 [-]: LOADK R3 K9  ; var3 = "20"
      23 [-]: NAMECALL R0 R0 K10; var1 = var0; var0 = var0[0xE4162EED]
      24 [-]: CALL R0 4 1  ; var0(var1, var2, var3)
      25 [-]: GETUPVAL R0 0; var0 = upvalues[0]
      26 [-]: LOADK R2 K11 ; var2 = "SetCountdown"
      27 [-]: LOADK R3 K12 ; var3 = "20,CountdownDone"
      28 [-]: NAMECALL R0 R0 K10; var1 = var0; var0 = var0[0xE4162EED]
      29 [-]: CALL R0 4 1  ; var0(var1, var2, var3)
      30 [-]: GETUPVAL R0 0; var0 = upvalues[0]
      31 [-]: LOADK R2 K13 ; var2 = "SetScale"
      32 [-]: LOADK R3 K14 ; var3 = "150,150"
      33 [-]: NAMECALL R0 R0 K10; var1 = var0; var0 = var0[0xE4162EED]
      34 [-]: CALL R0 4 1  ; var0(var1, var2, var3)
      35 [-]: GETUPVAL R0 0; var0 = upvalues[0]
      36 [-]: LOADK R2 K15 ; var2 = "SetPosition"
      37 [-]: LOADK R3 K16 ; var3 = "800,790,3,4"
      38 [-]: NAMECALL R0 R0 K10; var1 = var0; var0 = var0[0xE4162EED]
      39 [-]: CALL R0 4 1  ; var0(var1, var2, var3)
      40 [-]: GETUPVAL R0 1; var0 = upvalues[1]
      41 [-]: LOADN R1 1   ; var1 = 1
      42 [-]: JUMPIFNOTEQ R0 R1 L3; goto L3 if var0 ~= var60
      43 [-]: GETUPVAL R0 0; var0 = upvalues[0]
      44 [-]: LOADK R2 K17 ; var2 = "SetCorpus"
      45 [-]: LOADK R3 K18 ; var3 = ""
      46 [-]: NAMECALL R0 R0 K10; var1 = var0; var0 = var0[0xE4162EED]
      47 [-]: CALL R0 4 1  ; var0(var1, var2, var3)
L 3:  48 [-]: RETURN R0 0  ; 


; Name:            
; Defined at line: 183
; #Upvalues:       0
; #Parameters:     2
; Is_vararg:       0
; Max Stack Size:  6

       0 [-]: JUMPXEQKS R1 K0 L0 NOT; 
       1 [-]: GETIMPORT R2 2; var2 = 0xAE91E43B
       2 [-]: LOADK R4 K0  ; var4 = "AssassinatedTextUp"
       3 [-]: LOADK R5 K3  ; var5 = ""
       4 [-]: NAMECALL R2 R2 K4; var3 = var2; var2 = var2[0xE4162EED]
       5 [-]: CALL R2 4 1  ; var2(var3, var4, var5)
       6 [-]: JUMPXEQKS R0 K5 L0 NOT; 
       7 [-]: GETIMPORT R2 7; var2 = 0x38F10E85
       8 [-]: GETIMPORT R3 2; var3 = 0xAE91E43B
       9 [-]: LOADK R4 K8  ; var4 = "CrpPopup.Rank.gotoAndPlay"
      10 [-]: LOADN R5 1   ; var5 = 1
      11 [-]: CALL R2 4 1  ; var2(var3, var4, var5)
L 0:  12 [-]: RETURN R0 0  ; 


; Name:            
; Defined at line: 192
; #Upvalues:       29
; #Parameters:     0
; Is_vararg:       0
; Max Stack Size:  13

       0 [-]: GETIMPORT R0 1; var0 = 0x2D0FAD09
       1 [-]: LOADK R1 K2  ; var1 = "Lotus.Interface.Libs.TimerMgr"
       2 [-]: CALL R0 2 2  ; var0 = var0(var1)
       3 [-]: GETTABLEKS R1 R0 K3; var1 = var0[0xDE474187]
       4 [-]: CALL R1 1 2  ; var1 = var1()
       5 [-]: SETUPVAL R1 0; upvalues[1] = var0
       6 [-]: GETUPVAL R2 1; var2 = upvalues[1]
       7 [-]: GETTABLEKS R1 R2 K4; var1 = var2[0x1146D233]
       8 [-]: GETIMPORT R2 6; var2 = 0x969B72CB
       9 [-]: CALL R1 2 1  ; var1(var2)
      10 [-]: DUPTABLE R1 8; 
      11 [-]: GETUPVAL R3 1; var3 = upvalues[1]
      12 [-]: GETTABLEKS R2 R3 K9; var2 = var3[0x5D10207D]
      13 [-]: LOADN R3 9   ; var3 = 9
      14 [-]: LOADB R4 1   ; var4 = true
      15 [-]: CALL R2 3 2  ; var2 = var2(var3, var4)
      16 [-]: SETTABLEKS R2 R1 K7; var2["FloatingContent"] = var1
      17 [-]: SETUPVAL R1 2; upvalues[1] = var2
      18 [-]: GETUPVAL R2 4; var2 = upvalues[4]
      19 [-]: GETTABLEKS R1 R2 K10; var1 = var2[0xAE6791BA]
      20 [-]: GETIMPORT R2 12; var2 = 0xAE91E43B
      21 [-]: CALL R1 2 2  ; var1 = var1(var2)
      22 [-]: SETUPVAL R1 3; upvalues[1] = var3
      23 [-]: GETUPVAL R1 3; var1 = upvalues[3]
      24 [-]: GETIMPORT R3 12; var3 = 0xAE91E43B
      25 [-]: LOADK R4 K13 ; var4 = "Convert"
      26 [-]: NEWTABLE R5 0 2; var5 = {}
      27 [-]: GETUPVAL R7 3; var7 = upvalues[3]
      28 [-]: GETTABLEKS R6 R7 K14; var6 = var7["ANCHOR_V_CENTRE"]
      29 [-]: GETUPVAL R8 3; var8 = upvalues[3]
      30 [-]: GETTABLEKS R7 R8 K15; var7 = var8["ANCHOR_H_LEFT"]
      31 [-]: SETLIST R5 R6 2 [1]; var5[1] = var6; var5[2] = var7; var5[3] = var8; 
      32 [-]: NAMECALL R1 R1 K16; var2 = var1; var1 = var1[0x20FF29F7]
      33 [-]: CALL R1 5 1  ; var1(var2, var3, var4, var5)
      34 [-]: GETUPVAL R1 3; var1 = upvalues[3]
      35 [-]: GETIMPORT R3 12; var3 = 0xAE91E43B
      36 [-]: LOADK R4 K17 ; var4 = "Kill"
      37 [-]: NEWTABLE R5 0 2; var5 = {}
      38 [-]: GETUPVAL R7 3; var7 = upvalues[3]
      39 [-]: GETTABLEKS R6 R7 K14; var6 = var7["ANCHOR_V_CENTRE"]
      40 [-]: GETUPVAL R8 3; var8 = upvalues[3]
      41 [-]: GETTABLEKS R7 R8 K18; var7 = var8["ANCHOR_H_RIGHT"]
      42 [-]: SETLIST R5 R6 2 [1]; var5[1] = var6; var5[2] = var7; var5[3] = var8; 
      43 [-]: NAMECALL R1 R1 K16; var2 = var1; var1 = var1[0x20FF29F7]
      44 [-]: CALL R1 5 1  ; var1(var2, var3, var4, var5)
      45 [-]: GETUPVAL R1 3; var1 = upvalues[3]
      46 [-]: GETIMPORT R3 12; var3 = 0xAE91E43B
      47 [-]: LOADK R4 K19 ; var4 = "Popup"
      48 [-]: NEWTABLE R5 0 2; var5 = {}
      49 [-]: GETUPVAL R7 3; var7 = upvalues[3]
      50 [-]: GETTABLEKS R6 R7 K20; var6 = var7["ANCHOR_V_BOTTOM"]
      51 [-]: GETUPVAL R8 3; var8 = upvalues[3]
      52 [-]: GETTABLEKS R7 R8 K21; var7 = var8["ANCHOR_H_CENTRE"]
      53 [-]: SETLIST R5 R6 2 [1]; var5[1] = var6; var5[2] = var7; var5[3] = var8; 
      54 [-]: NAMECALL R1 R1 K16; var2 = var1; var1 = var1[0x20FF29F7]
      55 [-]: CALL R1 5 1  ; var1(var2, var3, var4, var5)
      56 [-]: GETUPVAL R1 3; var1 = upvalues[3]
      57 [-]: GETIMPORT R3 12; var3 = 0xAE91E43B
      58 [-]: LOADK R4 K22 ; var4 = "CrpPopup"
      59 [-]: NEWTABLE R5 0 2; var5 = {}
      60 [-]: GETUPVAL R7 3; var7 = upvalues[3]
      61 [-]: GETTABLEKS R6 R7 K20; var6 = var7["ANCHOR_V_BOTTOM"]
      62 [-]: GETUPVAL R8 3; var8 = upvalues[3]
      63 [-]: GETTABLEKS R7 R8 K21; var7 = var8["ANCHOR_H_CENTRE"]
      64 [-]: SETLIST R5 R6 2 [1]; var5[1] = var6; var5[2] = var7; var5[3] = var8; 
      65 [-]: NAMECALL R1 R1 K16; var2 = var1; var1 = var1[0x20FF29F7]
      66 [-]: CALL R1 5 1  ; var1(var2, var3, var4, var5)
      67 [-]: GETUPVAL R1 3; var1 = upvalues[3]
      68 [-]: GETIMPORT R3 12; var3 = 0xAE91E43B
      69 [-]: NAMECALL R3 R3 K23; var4 = var3; var3 = var3[0x6B837788]
      70 [-]: CALL R3 2 2  ; var3 = var3(var4)
      71 [-]: GETIMPORT R4 12; var4 = 0xAE91E43B
      72 [-]: NAMECALL R4 R4 K24; var5 = var4; var4 = var4[0xAF9FDA9F]
      73 [-]: CALL R4 2 0  ; var4, ... = var4(var5)
      74 [-]: NAMECALL R1 R1 K25; var2 = var1; var1 = var1[0xFAA69527]
      75 [-]: CALL R1 0 1  ; var1(var2, ...)
      76 [-]: LOADK R1 K26 ; var1 = ""
      77 [-]: LOADK R2 K26 ; var2 = ""
      78 [-]: GETIMPORT R4 28; var4 = 0x0032441C
      79 [-]: GETTABLEKS R3 R4 K29; var3 = var4["NemesisPopup_Info"]
      80 [-]: JUMPXEQKNIL R3 L8; 
      81 [-]: LOADB R3 0   ; var3 = false
      82 [-]: GETIMPORT R6 28; var6 = 0x0032441C
      83 [-]: GETTABLEKS R5 R6 K29; var5 = var6["NemesisPopup_Info"]
      84 [-]: GETTABLEKS R4 R5 K30; var4 = var5["IsCreationPopup"]
      85 [-]: JUMPXEQKNIL R4 L0; 
      86 [-]: GETIMPORT R5 28; var5 = 0x0032441C
      87 [-]: GETTABLEKS R4 R5 K29; var4 = var5["NemesisPopup_Info"]
      88 [-]: GETTABLEKS R3 R4 K30; var3 = var4["IsCreationPopup"]
L 0:  89 [-]: SETUPVAL R3 5; upvalues[3] = var5
      90 [-]: LOADB R3 0   ; var3 = false
      91 [-]: GETIMPORT R6 28; var6 = 0x0032441C
      92 [-]: GETTABLEKS R5 R6 K29; var5 = var6["NemesisPopup_Info"]
      93 [-]: GETTABLEKS R4 R5 K31; var4 = var5["IsChoice"]
      94 [-]: JUMPXEQKNIL R4 L1; 
      95 [-]: GETIMPORT R5 28; var5 = 0x0032441C
      96 [-]: GETTABLEKS R4 R5 K29; var4 = var5["NemesisPopup_Info"]
      97 [-]: GETTABLEKS R3 R4 K31; var3 = var4["IsChoice"]
L 1:  98 [-]: SETUPVAL R3 6; upvalues[3] = var6
      99 [-]: LOADB R3 0   ; var3 = false
     100 [-]: GETIMPORT R6 28; var6 = 0x0032441C
     101 [-]: GETTABLEKS R5 R6 K29; var5 = var6["NemesisPopup_Info"]
     102 [-]: GETTABLEKS R4 R5 K32; var4 = var5["IsRankUp"]
     103 [-]: JUMPXEQKNIL R4 L2; 
     104 [-]: GETIMPORT R5 28; var5 = 0x0032441C
     105 [-]: GETTABLEKS R4 R5 K29; var4 = var5["NemesisPopup_Info"]
     106 [-]: GETTABLEKS R3 R4 K32; var3 = var4["IsRankUp"]
L 2: 107 [-]: SETUPVAL R3 7; upvalues[3] = var7
     108 [-]: GETIMPORT R4 35; var4 = _T["gNemesis"]
     109 [-]: FASTCALL1 64 R4 L3; 
     110 [-]: GETIMPORT R3 37; var3 = 0x7B998233
     111 [-]: CALL R3 2 2  ; var3 = var3(var4)
L 3: 112 [-]: JUMPIF R3 L5 ; goto L5 if var3
     113 [-]: GETIMPORT R4 39; var4 = _T["gNemesis"]["properties"]
     114 [-]: FASTCALL1 64 R4 L4; 
     115 [-]: GETIMPORT R3 37; var3 = 0x7B998233
     116 [-]: CALL R3 2 2  ; var3 = var3(var4)
L 4: 117 [-]: JUMPIF R3 L5 ; goto L5 if var3
     118 [-]: GETIMPORT R4 39; var4 = _T["gNemesis"]["properties"]
     119 [-]: GETTABLEKS R3 R4 K40; var3 = var4["faction"]
     120 [-]: SETUPVAL R3 8; upvalues[3] = var8
     121 [-]: JUMP L7      ; goto L7
L 5: 122 [-]: GETIMPORT R6 28; var6 = 0x0032441C
     123 [-]: GETTABLEKS R5 R6 K29; var5 = var6["NemesisPopup_Info"]
     124 [-]: GETTABLEKS R4 R5 K41; var4 = var5["FactionId"]
     125 [-]: FASTCALL1 64 R4 L6; 
     126 [-]: GETIMPORT R3 37; var3 = 0x7B998233
     127 [-]: CALL R3 2 2  ; var3 = var3(var4)
L 6: 128 [-]: JUMPIF R3 L7 ; goto L7 if var3
     129 [-]: GETIMPORT R5 28; var5 = 0x0032441C
     130 [-]: GETTABLEKS R4 R5 K29; var4 = var5["NemesisPopup_Info"]
     131 [-]: GETTABLEKS R3 R4 K41; var3 = var4["FactionId"]
     132 [-]: SETUPVAL R3 8; upvalues[3] = var8
L 7: 133 [-]: GETIMPORT R4 28; var4 = 0x0032441C
     134 [-]: GETTABLEKS R3 R4 K29; var3 = var4["NemesisPopup_Info"]
     135 [-]: GETTABLEKS R1 R3 K42; var1 = var3["Header"]
     136 [-]: GETUPVAL R4 9; var4 = upvalues[9]
     137 [-]: GETTABLEKS R3 R4 K43; var3 = var4[0x06D055F9]
     138 [-]: GETUPVAL R4 6; var4 = upvalues[6]
     139 [-]: LOADK R5 K26 ; var5 = ""
     140 [-]: GETIMPORT R8 28; var8 = 0x0032441C
     141 [-]: GETTABLEKS R7 R8 K29; var7 = var8["NemesisPopup_Info"]
     142 [-]: GETTABLEKS R6 R7 K44; var6 = var7["Name"]
     143 [-]: CALL R3 4 2  ; var3 = var3(var4, var5, var6)
     144 [-]: MOVE R2 R3   ; var2 = var3
L 8: 145 [-]: GETUPVAL R3 8; var3 = upvalues[8]
     146 [-]: LOADN R4 1   ; var4 = 1
     147 [-]: JUMPIFNOTEQ R3 R4 L9; goto L9 if var3 ~= var3015457
     148 [-]: GETIMPORT R3 46; var3 = 0x6377AFAA
     149 [-]: SETUPVAL R3 10; upvalues[3] = var10
     150 [-]: GETIMPORT R3 48; var3 = 0x90CD1640
     151 [-]: SETUPVAL R3 11; upvalues[3] = var11
     152 [-]: GETIMPORT R3 50; var3 = 0x03EC786F
     153 [-]: SETUPVAL R3 12; upvalues[3] = var12
     154 [-]: GETIMPORT R3 52; var3 = 0xEB43C2D4
     155 [-]: SETUPVAL R3 13; upvalues[3] = var13
     156 [-]: GETIMPORT R3 54; var3 = 0xA10EC4E2
     157 [-]: SETUPVAL R3 14; upvalues[3] = var14
     158 [-]: GETIMPORT R3 56; var3 = 0xA721CF2C
     159 [-]: SETUPVAL R3 15; upvalues[3] = var15
     160 [-]: GETIMPORT R3 58; var3 = 0xF9A36301
     161 [-]: SETUPVAL R3 16; upvalues[3] = var16
     162 [-]: GETIMPORT R3 60; var3 = 0x68F6612E
     163 [-]: SETUPVAL R3 17; upvalues[3] = var17
     164 [-]: GETIMPORT R3 62; var3 = 0xDC141C71
     165 [-]: SETUPVAL R3 18; upvalues[3] = var18
     166 [-]: GETIMPORT R3 64; var3 = 0xE7954088
     167 [-]: SETUPVAL R3 19; upvalues[3] = var19
     168 [-]: JUMP L10     ; goto L10
L 9: 169 [-]: GETIMPORT R3 66; var3 = 0x0E058AD6
     170 [-]: SETUPVAL R3 10; upvalues[3] = var10
     171 [-]: GETIMPORT R3 68; var3 = 0x66B928F4
     172 [-]: SETUPVAL R3 11; upvalues[3] = var11
     173 [-]: GETIMPORT R3 70; var3 = 0x4976AF33
     174 [-]: SETUPVAL R3 12; upvalues[3] = var12
     175 [-]: GETIMPORT R3 72; var3 = 0xC960C770
     176 [-]: SETUPVAL R3 13; upvalues[3] = var13
     177 [-]: GETIMPORT R3 74; var3 = 0xBC2E0B06
     178 [-]: SETUPVAL R3 14; upvalues[3] = var14
     179 [-]: GETIMPORT R3 76; var3 = 0x78F385E8
     180 [-]: SETUPVAL R3 15; upvalues[3] = var15
     181 [-]: GETIMPORT R3 78; var3 = 0xA5B0BE2D
     182 [-]: SETUPVAL R3 16; upvalues[3] = var16
     183 [-]: GETIMPORT R3 80; var3 = 0x61402B52
     184 [-]: SETUPVAL R3 17; upvalues[3] = var17
     185 [-]: GETIMPORT R3 82; var3 = 0x9F39E155
     186 [-]: SETUPVAL R3 18; upvalues[3] = var18
     187 [-]: GETIMPORT R3 84; var3 = 0x5DA68934
     188 [-]: SETUPVAL R3 19; upvalues[3] = var19
L10: 189 [-]: GETUPVAL R3 5; var3 = upvalues[5]
     190 [-]: JUMPIFNOT R3 L12; goto L12 if not var3
     191 [-]: GETUPVAL R4 10; var4 = upvalues[10]
     192 [-]: FASTCALL1 64 R4 L11; 
     193 [-]: GETIMPORT R3 37; var3 = 0x7B998233
     194 [-]: CALL R3 2 2  ; var3 = var3(var4)
L11: 195 [-]: JUMPIF R3 L12; goto L12 if var3
     196 [-]: GETUPVAL R4 9; var4 = upvalues[9]
     197 [-]: GETTABLEKS R3 R4 K85; var3 = var4[0x659D451F]
     198 [-]: GETUPVAL R4 10; var4 = upvalues[10]
     199 [-]: CALL R3 2 1  ; var3(var4)
     200 [-]: JUMP L16     ; goto L16
L12: 201 [-]: GETUPVAL R3 6; var3 = upvalues[6]
     202 [-]: JUMPIFNOT R3 L16; goto L16 if not var3
     203 [-]: GETUPVAL R4 13; var4 = upvalues[13]
     204 [-]: FASTCALL1 64 R4 L13; 
     205 [-]: GETIMPORT R3 37; var3 = 0x7B998233
     206 [-]: CALL R3 2 2  ; var3 = var3(var4)
L13: 207 [-]: JUMPIF R3 L14; goto L14 if var3
     208 [-]: GETUPVAL R4 9; var4 = upvalues[9]
     209 [-]: GETTABLEKS R3 R4 K85; var3 = var4[0x659D451F]
     210 [-]: GETUPVAL R4 13; var4 = upvalues[13]
     211 [-]: CALL R3 2 2  ; var3 = var3(var4)
     212 [-]: SETUPVAL R3 20; upvalues[3] = var20
L14: 213 [-]: GETUPVAL R4 17; var4 = upvalues[17]
     214 [-]: FASTCALL1 64 R4 L15; 
     215 [-]: GETIMPORT R3 37; var3 = 0x7B998233
     216 [-]: CALL R3 2 2  ; var3 = var3(var4)
L15: 217 [-]: JUMPIF R3 L16; goto L16 if var3
     218 [-]: GETUPVAL R4 9; var4 = upvalues[9]
     219 [-]: GETTABLEKS R3 R4 K85; var3 = var4[0x659D451F]
     220 [-]: GETUPVAL R4 17; var4 = upvalues[17]
     221 [-]: CALL R3 2 2  ; var3 = var3(var4)
     222 [-]: SETUPVAL R3 21; upvalues[3] = var21
L16: 223 [-]: GETUPVAL R3 6; var3 = upvalues[6]
     224 [-]: JUMPIFNOT R3 L17; goto L17 if not var3
     225 [-]: GETUPVAL R4 22; var4 = upvalues[22]
     226 [-]: GETTABLEKS R3 R4 K86; var3 = var4[0x9E3D3434]
     227 [-]: LOADB R4 1   ; var4 = true
     228 [-]: CALL R3 2 1  ; var3(var4)
L17: 229 [-]: GETIMPORT R3 12; var3 = 0xAE91E43B
     230 [-]: LOADK R5 K22 ; var5 = "CrpPopup"
     231 [-]: LOADK R6 K87 ; var6 = "OnPopupFrameEnter"
     232 [-]: NAMECALL R3 R3 K88; var4 = var3; var3 = var3[0x5EE2CC30]
     233 [-]: CALL R3 4 1  ; var3(var4, var5, var6)
     234 [-]: GETIMPORT R3 12; var3 = 0xAE91E43B
     235 [-]: LOADK R5 K19 ; var5 = "Popup"
     236 [-]: LOADK R6 K87 ; var6 = "OnPopupFrameEnter"
     237 [-]: NAMECALL R3 R3 K88; var4 = var3; var3 = var3[0x5EE2CC30]
     238 [-]: CALL R3 4 1  ; var3(var4, var5, var6)
     239 [-]: GETUPVAL R3 8; var3 = upvalues[8]
     240 [-]: LOADN R4 1   ; var4 = 1
     241 [-]: JUMPIFNOTEQ R3 R4 L19; goto L19 if var3 ~= var787233
     242 [-]: GETIMPORT R3 12; var3 = 0xAE91E43B
     243 [-]: LOADK R5 K19 ; var5 = "Popup"
     244 [-]: LOADN R6 11  ; var6 = 11
     245 [-]: LOADB R7 0   ; var7 = false
     246 [-]: NAMECALL R3 R3 K89; var4 = var3; var3 = var3[0xAADE900E]
     247 [-]: CALL R3 5 1  ; var3(var4, var5, var6, var7)
     248 [-]: GETIMPORT R3 12; var3 = 0xAE91E43B
     249 [-]: LOADK R5 K22 ; var5 = "CrpPopup"
     250 [-]: LOADN R6 11  ; var6 = 11
     251 [-]: LOADB R7 1   ; var7 = true
     252 [-]: NAMECALL R3 R3 K89; var4 = var3; var3 = var3[0xAADE900E]
     253 [-]: CALL R3 5 1  ; var3(var4, var5, var6, var7)
     254 [-]: GETIMPORT R3 12; var3 = 0xAE91E43B
     255 [-]: LOADK R5 K90 ; var5 = "CrpPopup.Rank"
     256 [-]: LOADN R6 11  ; var6 = 11
     257 [-]: GETUPVAL R7 7; var7 = upvalues[7]
     258 [-]: NAMECALL R3 R3 K89; var4 = var3; var3 = var3[0xAADE900E]
     259 [-]: CALL R3 5 1  ; var3(var4, var5, var6, var7)
     260 [-]: GETUPVAL R3 7; var3 = upvalues[7]
     261 [-]: JUMPIFNOT R3 L18; goto L18 if not var3
     262 [-]: GETIMPORT R3 91; var3 = _T
     263 [-]: LOADB R4 1   ; var4 = true
     264 [-]: SETTABLEKS R4 R3 K92; var4["NemesisPopup_RankUpVisible"] = var3
     265 [-]: GETIMPORT R3 12; var3 = 0xAE91E43B
     266 [-]: LOADK R5 K93 ; var5 = "CrpPopup.Rank.Label"
     267 [-]: LOADN R6 31  ; var6 = 31
     268 [-]: GETIMPORT R9 28; var9 = 0x0032441C
     269 [-]: GETTABLEKS R8 R9 K29; var8 = var9["NemesisPopup_Info"]
     270 [-]: GETTABLEKS R7 R8 K94; var7 = var8["Rank"]
     271 [-]: NAMECALL R3 R3 K95; var4 = var3; var3 = var3[0x5F56EEAB]
     272 [-]: CALL R3 5 1  ; var3(var4, var5, var6, var7)
     273 [-]: GETIMPORT R3 12; var3 = 0xAE91E43B
     274 [-]: LOADK R5 K96 ; var5 = "CrpPopup.Rank.Cloud"
     275 [-]: GETIMPORT R6 98; var6 = 0x4067A96E
     276 [-]: NAMECALL R3 R3 K99; var4 = var3; var3 = var3[0xD5181643]
     277 [-]: CALL R3 4 1  ; var3(var4, var5, var6)
     278 [-]: GETUPVAL R4 9; var4 = upvalues[9]
     279 [-]: GETTABLEKS R3 R4 K85; var3 = var4[0x659D451F]
     280 [-]: GETUPVAL R4 19; var4 = upvalues[19]
     281 [-]: CALL R3 2 1  ; var3(var4)
     282 [-]: LOADN R3 6   ; var3 = 6
     283 [-]: SETUPVAL R3 23; upvalues[3] = var23
L18: 284 [-]: GETIMPORT R3 12; var3 = 0xAE91E43B
     285 [-]: LOADK R5 K100; var5 = "CrpPopup.Name.Name.text"
     286 [-]: MOVE R6 R2   ; var6 = var2
     287 [-]: NAMECALL R3 R3 K101; var4 = var3; var3 = var3[0x20B98DB3]
     288 [-]: CALL R3 4 1  ; var3(var4, var5, var6)
     289 [-]: GETIMPORT R3 12; var3 = 0xAE91E43B
     290 [-]: LOADK R5 K102; var5 = "CrpPopup.BottomText"
     291 [-]: LOADN R6 10  ; var6 = 10
     292 [-]: LOADN R7 0   ; var7 = 0
     293 [-]: NAMECALL R3 R3 K103; var4 = var3; var3 = var3[0x67BC869F]
     294 [-]: CALL R3 5 1  ; var3(var4, var5, var6, var7)
     295 [-]: GETIMPORT R3 12; var3 = 0xAE91E43B
     296 [-]: LOADK R5 K102; var5 = "CrpPopup.BottomText"
     297 [-]: LOADN R6 38  ; var6 = 38
     298 [-]: GETUPVAL R8 2; var8 = upvalues[2]
     299 [-]: GETTABLEKS R7 R8 K7; var7 = var8["FloatingContent"]
     300 [-]: NAMECALL R3 R3 K103; var4 = var3; var3 = var3[0x67BC869F]
     301 [-]: CALL R3 5 1  ; var3(var4, var5, var6, var7)
     302 [-]: GETIMPORT R3 12; var3 = 0xAE91E43B
     303 [-]: LOADK R5 K104; var5 = "CrpPopup.BottomText.text"
     304 [-]: LOADK R6 K105; var6 = "/Lotus/Language/Kingpins/Choice_DecideLabel"
     305 [-]: NAMECALL R3 R3 K101; var4 = var3; var3 = var3[0x20B98DB3]
     306 [-]: CALL R3 4 1  ; var3(var4, var5, var6)
     307 [-]: GETUPVAL R3 0; var3 = upvalues[0]
     308 [-]: LOADK R5 K106; var5 = 1.5
     309 [-]: NEWCLOSURE R6 P0; 
     310 [-]: CAPTURE UPVAL U11; 
     311 [-]: CAPTURE UPVAL U9; 
     312 [-]: NAMECALL R3 R3 K107; var4 = var3; var3 = var3[0xBD2E96EA]
     313 [-]: CALL R3 4 1  ; var3(var4, var5, var6)
     314 [-]: GETUPVAL R4 22; var4 = upvalues[22]
     315 [-]: GETTABLEKS R3 R4 K108; var3 = var4[0xF1AF786F]
     316 [-]: GETIMPORT R4 12; var4 = 0xAE91E43B
     317 [-]: LOADK R5 K109; var5 = "CrpPopup.Name.Name"
     318 [-]: CALL R3 3 1  ; var3(var4, var5)
     319 [-]: JUMP L21     ; goto L21
L19: 320 [-]: GETIMPORT R3 12; var3 = 0xAE91E43B
     321 [-]: LOADK R5 K19 ; var5 = "Popup"
     322 [-]: LOADN R6 11  ; var6 = 11
     323 [-]: LOADB R7 1   ; var7 = true
     324 [-]: NAMECALL R3 R3 K89; var4 = var3; var3 = var3[0xAADE900E]
     325 [-]: CALL R3 5 1  ; var3(var4, var5, var6, var7)
     326 [-]: GETIMPORT R3 12; var3 = 0xAE91E43B
     327 [-]: LOADK R5 K22 ; var5 = "CrpPopup"
     328 [-]: LOADN R6 11  ; var6 = 11
     329 [-]: LOADB R7 0   ; var7 = false
     330 [-]: NAMECALL R3 R3 K89; var4 = var3; var3 = var3[0xAADE900E]
     331 [-]: CALL R3 5 1  ; var3(var4, var5, var6, var7)
     332 [-]: GETIMPORT R3 12; var3 = 0xAE91E43B
     333 [-]: LOADK R5 K110; var5 = "Popup.Rank"
     334 [-]: LOADN R6 11  ; var6 = 11
     335 [-]: GETUPVAL R7 7; var7 = upvalues[7]
     336 [-]: NAMECALL R3 R3 K89; var4 = var3; var3 = var3[0xAADE900E]
     337 [-]: CALL R3 5 1  ; var3(var4, var5, var6, var7)
     338 [-]: GETUPVAL R3 7; var3 = upvalues[7]
     339 [-]: JUMPIFNOT R3 L20; goto L20 if not var3
     340 [-]: GETIMPORT R3 91; var3 = _T
     341 [-]: LOADB R4 1   ; var4 = true
     342 [-]: SETTABLEKS R4 R3 K92; var4["NemesisPopup_RankUpVisible"] = var3
     343 [-]: GETIMPORT R3 12; var3 = 0xAE91E43B
     344 [-]: LOADK R5 K111; var5 = "Popup.Rank.Label"
     345 [-]: LOADN R6 31  ; var6 = 31
     346 [-]: GETIMPORT R9 28; var9 = 0x0032441C
     347 [-]: GETTABLEKS R8 R9 K29; var8 = var9["NemesisPopup_Info"]
     348 [-]: GETTABLEKS R7 R8 K94; var7 = var8["Rank"]
     349 [-]: NAMECALL R3 R3 K95; var4 = var3; var3 = var3[0x5F56EEAB]
     350 [-]: CALL R3 5 1  ; var3(var4, var5, var6, var7)
     351 [-]: GETIMPORT R3 12; var3 = 0xAE91E43B
     352 [-]: LOADK R5 K112; var5 = "Popup.Rank.Leaf"
     353 [-]: LOADN R6 9   ; var6 = 9
     354 [-]: GETIMPORT R8 28; var8 = 0x0032441C
     355 [-]: GETTABLEKS R7 R8 K113; var7 = var8["UIColor_Black"]
     356 [-]: NAMECALL R3 R3 K103; var4 = var3; var3 = var3[0x67BC869F]
     357 [-]: CALL R3 5 1  ; var3(var4, var5, var6, var7)
     358 [-]: GETIMPORT R3 12; var3 = 0xAE91E43B
     359 [-]: LOADK R5 K114; var5 = "Popup.Rank.Cloud"
     360 [-]: GETIMPORT R6 98; var6 = 0x4067A96E
     361 [-]: NAMECALL R3 R3 K99; var4 = var3; var3 = var3[0xD5181643]
     362 [-]: CALL R3 4 1  ; var3(var4, var5, var6)
     363 [-]: GETUPVAL R4 9; var4 = upvalues[9]
     364 [-]: GETTABLEKS R3 R4 K85; var3 = var4[0x659D451F]
     365 [-]: GETUPVAL R4 19; var4 = upvalues[19]
     366 [-]: CALL R3 2 1  ; var3(var4)
     367 [-]: LOADN R3 6   ; var3 = 6
     368 [-]: SETUPVAL R3 23; upvalues[3] = var23
L20: 369 [-]: GETIMPORT R3 12; var3 = 0xAE91E43B
     370 [-]: LOADK R5 K115; var5 = "Popup.BottomText"
     371 [-]: LOADN R6 10  ; var6 = 10
     372 [-]: LOADN R7 0   ; var7 = 0
     373 [-]: NAMECALL R3 R3 K103; var4 = var3; var3 = var3[0x67BC869F]
     374 [-]: CALL R3 5 1  ; var3(var4, var5, var6, var7)
     375 [-]: GETIMPORT R3 12; var3 = 0xAE91E43B
     376 [-]: LOADK R5 K115; var5 = "Popup.BottomText"
     377 [-]: LOADN R6 38  ; var6 = 38
     378 [-]: GETUPVAL R8 2; var8 = upvalues[2]
     379 [-]: GETTABLEKS R7 R8 K7; var7 = var8["FloatingContent"]
     380 [-]: NAMECALL R3 R3 K103; var4 = var3; var3 = var3[0x67BC869F]
     381 [-]: CALL R3 5 1  ; var3(var4, var5, var6, var7)
     382 [-]: GETIMPORT R3 12; var3 = 0xAE91E43B
     383 [-]: LOADK R5 K116; var5 = "Popup.BottomText.text"
     384 [-]: LOADK R6 K105; var6 = "/Lotus/Language/Kingpins/Choice_DecideLabel"
     385 [-]: NAMECALL R3 R3 K101; var4 = var3; var3 = var3[0x20B98DB3]
     386 [-]: CALL R3 4 1  ; var3(var4, var5, var6)
     387 [-]: GETIMPORT R3 12; var3 = 0xAE91E43B
     388 [-]: LOADK R5 K117; var5 = "Popup.Name"
     389 [-]: LOADN R6 1   ; var6 = 1
     390 [-]: LOADN R8 62  ; var8 = 62
     391 [-]: GETUPVAL R10 9; var10 = upvalues[9]
     392 [-]: GETTABLEKS R9 R10 K43; var9 = var10[0x06D055F9]
     393 [-]: GETUPVAL R10 6; var10 = upvalues[6]
     394 [-]: LOADN R11 -25; var11 = -25
     395 [-]: LOADN R12 0  ; var12 = 0
     396 [-]: CALL R9 4 2  ; var9 = var9(var10, var11, var12)
     397 [-]: ADD R7 R8 R9 ; var7 = var8 + var9
     398 [-]: NAMECALL R3 R3 K103; var4 = var3; var3 = var3[0x67BC869F]
     399 [-]: CALL R3 5 1  ; var3(var4, var5, var6, var7)
     400 [-]: GETIMPORT R3 12; var3 = 0xAE91E43B
     401 [-]: LOADK R5 K118; var5 = "Popup.Name.Name.text"
     402 [-]: MOVE R6 R2   ; var6 = var2
     403 [-]: NAMECALL R3 R3 K101; var4 = var3; var3 = var3[0x20B98DB3]
     404 [-]: CALL R3 4 1  ; var3(var4, var5, var6)
     405 [-]: GETIMPORT R3 120; var3 = 0x38F10E85
     406 [-]: GETIMPORT R4 12; var4 = 0xAE91E43B
     407 [-]: LOADK R5 K121; var5 = "Popup.Name.Name.setVertexColors"
     408 [-]: LOADK R6 K122; var6 = 16711680
     409 [-]: LOADK R7 K122; var7 = 16711680
     410 [-]: LOADK R8 K123; var8 = 11141120
     411 [-]: LOADK R9 K123; var9 = 11141120
     412 [-]: CALL R3 7 1  ; var3(var4, var5, var6, var7, var8, var9)
     413 [-]: GETUPVAL R3 0; var3 = upvalues[0]
     414 [-]: LOADK R5 K106; var5 = 1.5
     415 [-]: NEWCLOSURE R6 P1; 
     416 [-]: CAPTURE UPVAL U11; 
     417 [-]: CAPTURE UPVAL U9; 
     418 [-]: NAMECALL R3 R3 K107; var4 = var3; var3 = var3[0xBD2E96EA]
     419 [-]: CALL R3 4 1  ; var3(var4, var5, var6)
     420 [-]: GETUPVAL R4 22; var4 = upvalues[22]
     421 [-]: GETTABLEKS R3 R4 K108; var3 = var4[0xF1AF786F]
     422 [-]: GETIMPORT R4 12; var4 = 0xAE91E43B
     423 [-]: LOADK R5 K124; var5 = "Popup.Name.Name"
     424 [-]: CALL R3 3 1  ; var3(var4, var5)
L21: 425 [-]: GETIMPORT R3 12; var3 = 0xAE91E43B
     426 [-]: GETUPVAL R6 6; var6 = upvalues[6]
     427 [-]: NOT R5 R6    ; var5 = not var6
     428 [-]: NAMECALL R3 R3 K125; var4 = var3; var3 = var3[0xBED40E9C]
     429 [-]: CALL R3 3 1  ; var3(var4, var5)
     430 [-]: GETIMPORT R3 12; var3 = 0xAE91E43B
     431 [-]: LOADK R5 K13 ; var5 = "Convert"
     432 [-]: LOADN R6 11  ; var6 = 11
     433 [-]: GETUPVAL R7 6; var7 = upvalues[6]
     434 [-]: NAMECALL R3 R3 K89; var4 = var3; var3 = var3[0xAADE900E]
     435 [-]: CALL R3 5 1  ; var3(var4, var5, var6, var7)
     436 [-]: GETIMPORT R3 12; var3 = 0xAE91E43B
     437 [-]: LOADK R5 K17 ; var5 = "Kill"
     438 [-]: LOADN R6 11  ; var6 = 11
     439 [-]: GETUPVAL R7 6; var7 = upvalues[6]
     440 [-]: NAMECALL R3 R3 K89; var4 = var3; var3 = var3[0xAADE900E]
     441 [-]: CALL R3 5 1  ; var3(var4, var5, var6, var7)
     442 [-]: GETUPVAL R3 6; var3 = upvalues[6]
     443 [-]: JUMPIFNOT R3 L22; goto L22 if not var3
     444 [-]: DUPTABLE R3 133; 
     445 [-]: GETIMPORT R4 135; var4 = 0x820956A8
     446 [-]: SETTABLEKS R4 R3 K126; var4["Icon"] = var3
     447 [-]: LOADK R4 K136; var4 = "/Lotus/Language/Kingpins/Choice_ConvertDesc"
     448 [-]: SETTABLEKS R4 R3 K127; var4["Label"] = var3
     449 [-]: LOADK R4 K137; var4 = "/Lotus/Language/Kingpins/Choice_ConvertLabel"
     450 [-]: SETTABLEKS R4 R3 K128; var4["BtnLabel"] = var3
     451 [-]: GETUPVAL R4 24; var4 = upvalues[24]
     452 [-]: SETTABLEKS R4 R3 K129; var4["BtnCallback"] = var3
     453 [-]: GETUPVAL R4 16; var4 = upvalues[16]
     454 [-]: SETTABLEKS R4 R3 K130; var4["BtnSound"] = var3
     455 [-]: LOADK R4 K138; var4 = "<MENU_LEFT>"
     456 [-]: SETTABLEKS R4 R3 K131; var4["BtnCallout"] = var3
     457 [-]: LOADN R4 150 ; var4 = 150
     458 [-]: SETTABLEKS R4 R3 K132; var4["FxXOffset"] = var3
     459 [-]: GETUPVAL R4 26; var4 = upvalues[26]
     460 [-]: LOADK R5 K13 ; var5 = "Convert"
     461 [-]: MOVE R6 R3   ; var6 = var3
     462 [-]: CALL R4 3 2  ; var4 = var4(var5, var6)
     463 [-]: SETUPVAL R4 25; upvalues[4] = var25
     464 [-]: DUPTABLE R4 133; 
     465 [-]: GETIMPORT R5 140; var5 = 0x344ABFAF
     466 [-]: SETTABLEKS R5 R4 K126; var5["Icon"] = var4
     467 [-]: LOADK R5 K141; var5 = "/Lotus/Language/Kingpins/Choice_KillDesc"
     468 [-]: SETTABLEKS R5 R4 K127; var5["Label"] = var4
     469 [-]: LOADK R5 K142; var5 = "/Lotus/Language/Kingpins/Choice_KillLabel"
     470 [-]: SETTABLEKS R5 R4 K128; var5["BtnLabel"] = var4
     471 [-]: GETUPVAL R5 27; var5 = upvalues[27]
     472 [-]: SETTABLEKS R5 R4 K129; var5["BtnCallback"] = var4
     473 [-]: GETUPVAL R5 15; var5 = upvalues[15]
     474 [-]: SETTABLEKS R5 R4 K130; var5["BtnSound"] = var4
     475 [-]: LOADK R5 K143; var5 = "<MENU_RIGHT>"
     476 [-]: SETTABLEKS R5 R4 K131; var5["BtnCallout"] = var4
     477 [-]: LOADN R5 -150; var5 = -150
     478 [-]: SETTABLEKS R5 R4 K132; var5["FxXOffset"] = var4
     479 [-]: GETUPVAL R5 26; var5 = upvalues[26]
     480 [-]: LOADK R6 K17 ; var6 = "Kill"
     481 [-]: MOVE R7 R4   ; var7 = var4
     482 [-]: CALL R5 3 2  ; var5 = var5(var6, var7)
     483 [-]: SETUPVAL R5 28; upvalues[5] = var28
L22: 484 [-]: GETUPVAL R3 8; var3 = upvalues[8]
     485 [-]: LOADN R4 1   ; var4 = 1
     486 [-]: JUMPIFEQ R3 R4 L23; goto L23 if var3 == var787233
     487 [-]: GETIMPORT R3 12; var3 = 0xAE91E43B
     488 [-]: LOADK R5 K144; var5 = "Popup.CloudTop"
     489 [-]: GETIMPORT R6 98; var6 = 0x4067A96E
     490 [-]: NAMECALL R3 R3 K99; var4 = var3; var3 = var3[0xD5181643]
     491 [-]: CALL R3 4 1  ; var3(var4, var5, var6)
     492 [-]: GETIMPORT R3 12; var3 = 0xAE91E43B
     493 [-]: LOADK R5 K145; var5 = "Popup.CloudBottom"
     494 [-]: GETIMPORT R6 98; var6 = 0x4067A96E
     495 [-]: NAMECALL R3 R3 K99; var4 = var3; var3 = var3[0xD5181643]
     496 [-]: CALL R3 4 1  ; var3(var4, var5, var6)
     497 [-]: GETIMPORT R3 12; var3 = 0xAE91E43B
     498 [-]: LOADK R5 K146; var5 = "Popup.CloudDots"
     499 [-]: GETIMPORT R6 148; var6 = 0xBD8FB492
     500 [-]: NAMECALL R3 R3 K99; var4 = var3; var3 = var3[0xD5181643]
     501 [-]: CALL R3 4 1  ; var3(var4, var5, var6)
     502 [-]: GETIMPORT R3 12; var3 = 0xAE91E43B
     503 [-]: LOADK R5 K146; var5 = "Popup.CloudDots"
     504 [-]: LOADN R6 9   ; var6 = 9
     505 [-]: LOADK R7 K122; var7 = 16711680
     506 [-]: NAMECALL R3 R3 K103; var4 = var3; var3 = var3[0x67BC869F]
     507 [-]: CALL R3 5 1  ; var3(var4, var5, var6, var7)
L23: 508 [-]: RETURN R0 0  ; 


; Name:            
; Defined at line: 361
; #Upvalues:       8
; #Parameters:     0
; Is_vararg:       0
; Max Stack Size:  10

       0 [-]: GETUPVAL R0 0; var0 = upvalues[0]
       1 [-]: JUMPXEQKNIL R0 L0; 
       2 [-]: GETUPVAL R0 1; var0 = upvalues[1]
       3 [-]: JUMPXEQKNIL R0 L0; 
       4 [-]: GETUPVAL R0 2; var0 = upvalues[2]
       5 [-]: JUMPIFNOT R0 L1; goto L1 if not var0
L 0:   6 [-]: RETURN R0 0  ; 
L 1:   7 [-]: NEWCLOSURE R0 P0; 
       8 [-]: CAPTURE UPVAL U3; 
       9 [-]: CAPTURE UPVAL U4; 
      10 [-]: GETUPVAL R2 5; var2 = upvalues[5]
      11 [-]: GETUPVAL R3 0; var3 = upvalues[0]
      12 [-]: JUMPIFEQ R2 R3 L2; goto L2 if var2 == var16777478
      13 [-]: LOADB R1 0 +1; var1 = false
L 2:  14 [-]: LOADB R1 1   ; var1 = true
L 3:  15 [-]: GETUPVAL R3 5; var3 = upvalues[5]
      16 [-]: GETUPVAL R4 1; var4 = upvalues[1]
      17 [-]: JUMPIFEQ R3 R4 L4; goto L4 if var3 == var16777734
      18 [-]: LOADB R2 0 +1; var2 = false
L 4:  19 [-]: LOADB R2 1   ; var2 = true
L 5:  20 [-]: MOVE R3 R0   ; var3 = var0
      21 [-]: GETUPVAL R4 0; var4 = upvalues[0]
      22 [-]: MOVE R5 R1   ; var5 = var1
      23 [-]: GETUPVAL R6 1; var6 = upvalues[1]
      24 [-]: CALL R3 4 1  ; var3(var4, var5, var6)
      25 [-]: MOVE R3 R0   ; var3 = var0
      26 [-]: GETUPVAL R4 1; var4 = upvalues[1]
      27 [-]: MOVE R5 R2   ; var5 = var2
      28 [-]: GETUPVAL R6 0; var6 = upvalues[0]
      29 [-]: CALL R3 4 1  ; var3(var4, var5, var6)
      30 [-]: GETUPVAL R4 6; var4 = upvalues[6]
      31 [-]: FASTCALL1 64 R4 L6; 
      32 [-]: GETIMPORT R3 1; var3 = 0x7B998233
      33 [-]: CALL R3 2 2  ; var3 = var3(var4)
L 6:  34 [-]: JUMPIFNOT R3 L8; goto L8 if not var3
      35 [-]: GETIMPORT R4 3; var4 = 0x89326C93
      36 [-]: NAMECALL R4 R4 K4; var5 = var4; var4 = var4[0x78298275]
      37 [-]: CALL R4 2 0  ; var4, ... = var4(var5)
      38 [-]: FASTCALL 64 L7; 
      39 [-]: GETIMPORT R3 1; var3 = 0x7B998233
      40 [-]: CALL R3 0 2  ; var3 = var3(var4, ...)
L 7:  41 [-]: JUMPIF R3 L8 ; goto L8 if var3
      42 [-]: GETIMPORT R3 3; var3 = 0x89326C93
      43 [-]: NAMECALL R3 R3 K4; var4 = var3; var3 = var3[0x78298275]
      44 [-]: CALL R3 2 2  ; var3 = var3(var4)
      45 [-]: NAMECALL R3 R3 K5; var4 = var3; var3 = var3[0x0B4BCFB6]
      46 [-]: CALL R3 2 2  ; var3 = var3(var4)
      47 [-]: SETUPVAL R3 6; upvalues[3] = var6
L 8:  48 [-]: GETUPVAL R4 6; var4 = upvalues[6]
      49 [-]: FASTCALL1 64 R4 L9; 
      50 [-]: GETIMPORT R3 1; var3 = 0x7B998233
      51 [-]: CALL R3 2 2  ; var3 = var3(var4)
L 9:  52 [-]: JUMPIF R3 L12; goto L12 if var3
      53 [-]: LOADN R4 1   ; var4 = 1
      54 [-]: GETUPVAL R8 0; var8 = upvalues[0]
      55 [-]: GETTABLEKS R7 R8 K7; var7 = var8["Hold"]
      56 [-]: GETUPVAL R9 1; var9 = upvalues[1]
      57 [-]: GETTABLEKS R8 R9 K7; var8 = var9["Hold"]
      58 [-]: FASTCALL2 18 R7 R8 L10; 
      59 [-]: GETIMPORT R6 10; var6 = 0x5BCED4C4[0xB62ECFE0]
      60 [-]: CALL R6 3 2  ; var6 = var6(var7, var8)
L10:  61 [-]: MULK R5 R6 K6; var5 = var6 * 0.25
      62 [-]: SUB R3 R4 R5 ; var3 = var4 - var5
      63 [-]: GETUPVAL R4 7; var4 = upvalues[7]
      64 [-]: NAMECALL R4 R4 K11; var5 = var4; var4 = var4[0x54AB95F9]
      65 [-]: CALL R4 2 2  ; var4 = var4(var5)
      66 [-]: GETUPVAL R5 7; var5 = upvalues[7]
      67 [-]: MOVE R7 R3   ; var7 = var3
      68 [-]: NAMECALL R5 R5 K12; var6 = var5; var5 = var5[0x188E2BEE]
      69 [-]: CALL R5 3 1  ; var5(var6, var7)
      70 [-]: GETUPVAL R5 7; var5 = upvalues[7]
      71 [-]: GETIMPORT R7 14; var7 = 0x67652851
      72 [-]: CALL R7 1 0  ; var7, ... = var7()
      73 [-]: NAMECALL R5 R5 K15; var6 = var5; var5 = var5[0xFAA69527]
      74 [-]: CALL R5 0 1  ; var5(var6, ...)
      75 [-]: GETUPVAL R5 7; var5 = upvalues[7]
      76 [-]: NAMECALL R5 R5 K11; var6 = var5; var5 = var5[0x54AB95F9]
      77 [-]: CALL R5 2 2  ; var5 = var5(var6)
      78 [-]: JUMPIFEQ R4 R5 L12; goto L12 if var4 == var132412
      79 [-]: GETUPVAL R5 2; var5 = upvalues[2]
      80 [-]: JUMPIF R5 L11; goto L11 if var5
      81 [-]: GETUPVAL R5 6; var5 = upvalues[6]
      82 [-]: GETUPVAL R7 7; var7 = upvalues[7]
      83 [-]: NAMECALL R7 R7 K11; var8 = var7; var7 = var7[0x54AB95F9]
      84 [-]: CALL R7 2 2  ; var7 = var7(var8)
      85 [-]: LOADB R8 1   ; var8 = true
      86 [-]: NAMECALL R5 R5 K16; var6 = var5; var5 = var5[0x47DE28D6]
      87 [-]: CALL R5 4 1  ; var5(var6, var7, var8)
      88 [-]: RETURN R0 0  ; 
L11:  89 [-]: GETUPVAL R5 6; var5 = upvalues[6]
      90 [-]: LOADN R7 1   ; var7 = 1
      91 [-]: LOADB R8 0   ; var8 = false
      92 [-]: NAMECALL R5 R5 K16; var6 = var5; var5 = var5[0x47DE28D6]
      93 [-]: CALL R5 4 1  ; var5(var6, var7, var8)
L12:  94 [-]: RETURN R0 0  ; 


; Name:            
; Defined at line: 424
; #Upvalues:       2
; #Parameters:     0
; Is_vararg:       0
; Max Stack Size:  4

       0 [-]: GETIMPORT R0 1; var0 = 0xB693B6C1
       1 [-]: CALL R0 1 2  ; var0 = var0()
       2 [-]: GETIMPORT R1 3; var1 = 0xAE91E43B
       3 [-]: MOVE R3 R0   ; var3 = var0
       4 [-]: NAMECALL R1 R1 K4; var2 = var1; var1 = var1[0x8A8C8D5A]
       5 [-]: CALL R1 3 1  ; var1(var2, var3)
       6 [-]: GETUPVAL R2 0; var2 = upvalues[0]
       7 [-]: FASTCALL1 64 R2 L0; 
       8 [-]: GETIMPORT R1 6; var1 = 0x7B998233
       9 [-]: CALL R1 2 2  ; var1 = var1(var2)
L 0:  10 [-]: JUMPIF R1 L1 ; goto L1 if var1
      11 [-]: GETUPVAL R1 0; var1 = upvalues[0]
      12 [-]: MOVE R3 R0   ; var3 = var0
      13 [-]: NAMECALL R1 R1 K7; var2 = var1; var1 = var1[0xFAA69527]
      14 [-]: CALL R1 3 1  ; var1(var2, var3)
L 1:  15 [-]: GETUPVAL R1 1; var1 = upvalues[1]
      16 [-]: CALL R1 1 1  ; var1()
      17 [-]: RETURN R0 0  ; 


; Name:            
; Defined at line: 435
; #Upvalues:       0
; #Parameters:     0
; Is_vararg:       0
; Max Stack Size:  0

       0 [-]: RETURN R0 0  ; 


; Name:            
; Defined at line: 438
; #Upvalues:       7
; #Parameters:     0
; Is_vararg:       0
; Max Stack Size:  9

       0 [-]: GETUPVAL R0 0; var0 = upvalues[0]
       1 [-]: JUMPIFNOT R0 L3; goto L3 if not var0
       2 [-]: GETUPVAL R1 1; var1 = upvalues[1]
       3 [-]: GETTABLEKS R0 R1 K0; var0 = var1["BtnSound"]
       4 [-]: GETUPVAL R1 2; var1 = upvalues[2]
       5 [-]: JUMPIF R1 L0 ; goto L0 if var1
       6 [-]: GETUPVAL R1 3; var1 = upvalues[3]
       7 [-]: GETTABLEKS R0 R1 K0; var0 = var1["BtnSound"]
L 0:   8 [-]: FASTCALL1 64 R0 L1; 
       9 [-]: MOVE R2 R0   ; var2 = var0
      10 [-]: GETIMPORT R1 2; var1 = 0x7B998233
      11 [-]: CALL R1 2 2  ; var1 = var1(var2)
L 1:  12 [-]: JUMPIF R1 L2 ; goto L2 if var1
      13 [-]: GETUPVAL R2 4; var2 = upvalues[4]
      14 [-]: GETTABLEKS R1 R2 K3; var1 = var2[0x659D451F]
      15 [-]: MOVE R2 R0   ; var2 = var0
      16 [-]: CALL R1 2 1  ; var1(var2)
L 2:  17 [-]: GETIMPORT R1 5; var1 = 0x0032441C
      18 [-]: GETUPVAL R2 2; var2 = upvalues[2]
      19 [-]: SETTABLEKS R2 R1 K6; var2["NemesisKillChoiceMade"] = var1
L 3:  20 [-]: GETUPVAL R1 5; var1 = upvalues[5]
      21 [-]: FASTCALL1 64 R1 L4; 
      22 [-]: GETIMPORT R0 2; var0 = 0x7B998233
      23 [-]: CALL R0 2 2  ; var0 = var0(var1)
L 4:  24 [-]: JUMPIF R0 L5 ; goto L5 if var0
      25 [-]: GETUPVAL R0 5; var0 = upvalues[5]
      26 [-]: NAMECALL R0 R0 K7; var1 = var0; var0 = var0[0x32302B4A]
      27 [-]: CALL R0 2 1  ; var0(var1)
L 5:  28 [-]: GETIMPORT R0 9; var0 = 0x25312C9B
      29 [-]: GETIMPORT R1 11; var1 = 0xAE91E43B
      30 [-]: LOADK R2 K12 ; var2 = "_root"
      31 [-]: LOADN R3 8   ; var3 = 8
      32 [-]: NEWTABLE R4 0 1; var4 = {}
      33 [-]: LOADN R5 10  ; var5 = 10
      34 [-]: SETLIST R4 R5 1 [1]; var4[1] = var5; var4[2] = var6; 
      35 [-]: NEWTABLE R5 0 1; var5 = {}
      36 [-]: LOADN R6 0   ; var6 = 0
      37 [-]: SETLIST R5 R6 1 [1]; var5[1] = var6; var5[2] = var7; 
      38 [-]: LOADK R6 K13 ; var6 = 0.75
      39 [-]: LOADN R7 0   ; var7 = 0
      40 [-]: NEWCLOSURE R8 P0; 
      41 [-]: CAPTURE UPVAL U6; 
      42 [-]: CAPTURE UPVAL U0; 
      43 [-]: CAPTURE UPVAL U2; 
      44 [-]: CALL R0 9 1  ; var0(var1, var2, var3, var4, var5, var6, var7, var8)
      45 [-]: RETURN R0 0  ; 


; Name:            
; Defined at line: 466
; #Upvalues:       3
; #Parameters:     0
; Is_vararg:       0
; Max Stack Size:  2

       0 [-]: GETUPVAL R0 0; var0 = upvalues[0]
       1 [-]: CALL R0 1 1  ; var0()
       2 [-]: GETUPVAL R1 1; var1 = upvalues[1]
       3 [-]: FASTCALL1 64 R1 L0; 
       4 [-]: GETIMPORT R0 1; var0 = 0x7B998233
       5 [-]: CALL R0 2 2  ; var0 = var0(var1)
L 0:   6 [-]: JUMPIF R0 L1 ; goto L1 if var0
       7 [-]: GETUPVAL R1 2; var1 = upvalues[2]
       8 [-]: GETTABLEKS R0 R1 K2; var0 = var1[0x659D451F]
       9 [-]: GETUPVAL R1 1; var1 = upvalues[1]
      10 [-]: CALL R0 2 1  ; var0(var1)
L 1:  11 [-]: RETURN R0 0  ; 


; Name:            
; Defined at line: 473
; #Upvalues:       7
; #Parameters:     0
; Is_vararg:       0
; Max Stack Size:  11

       0 [-]: LOADK R0 K0  ; var0 = ""
       1 [-]: GETIMPORT R2 2; var2 = 0x0032441C
       2 [-]: GETTABLEKS R1 R2 K3; var1 = var2["NemesisPopup_Info"]
       3 [-]: JUMPXEQKNIL R1 L0; 
       4 [-]: GETUPVAL R1 0; var1 = upvalues[0]
       5 [-]: JUMPIF R1 L0 ; goto L0 if var1
       6 [-]: GETIMPORT R2 2; var2 = 0x0032441C
       7 [-]: GETTABLEKS R1 R2 K3; var1 = var2["NemesisPopup_Info"]
       8 [-]: GETTABLEKS R0 R1 K4; var0 = var1["Description"]
L 0:   9 [-]: GETUPVAL R1 1; var1 = upvalues[1]
      10 [-]: LOADN R2 1   ; var2 = 1
      11 [-]: JUMPIFNOTEQ R1 R2 L3; goto L3 if var1 ~= var393505
      12 [-]: GETIMPORT R1 6; var1 = 0xAE91E43B
      13 [-]: LOADK R3 K7  ; var3 = "CrpPopup.AssassinatedText.Label.text"
      14 [-]: MOVE R4 R0   ; var4 = var0
      15 [-]: NAMECALL R1 R1 K8; var2 = var1; var1 = var1[0x20B98DB3]
      16 [-]: CALL R1 4 1  ; var1(var2, var3, var4)
      17 [-]: GETIMPORT R1 6; var1 = 0xAE91E43B
      18 [-]: LOADK R3 K9  ; var3 = "CrpPopup.AssassinatedText.Label"
      19 [-]: LOADN R4 67  ; var4 = 67
      20 [-]: LOADN R5 0   ; var5 = 0
      21 [-]: NAMECALL R1 R1 K10; var2 = var1; var1 = var1[0x67BC869F]
      22 [-]: CALL R1 5 1  ; var1(var2, var3, var4, var5)
      23 [-]: GETUPVAL R1 2; var1 = upvalues[2]
      24 [-]: JUMPIFNOT R1 L1; goto L1 if not var1
      25 [-]: GETUPVAL R2 3; var2 = upvalues[3]
      26 [-]: GETTABLEKS R1 R2 K11; var1 = var2[0xF76783E5]
      27 [-]: GETIMPORT R2 6; var2 = 0xAE91E43B
      28 [-]: LOADK R3 K12 ; var3 = "CrpPopup.Rank"
      29 [-]: GETIMPORT R4 14; var4 = 0xEBDD460B
      30 [-]: CALL R1 4 1  ; var1(var2, var3, var4)
L 1:  31 [-]: GETUPVAL R1 0; var1 = upvalues[0]
      32 [-]: JUMPIFNOT R1 L2; goto L2 if not var1
      33 [-]: GETIMPORT R1 16; var1 = 0x25312C9B
      34 [-]: GETIMPORT R2 6; var2 = 0xAE91E43B
      35 [-]: LOADK R3 K17 ; var3 = "CrpPopup.BottomText"
      36 [-]: LOADN R4 8   ; var4 = 8
      37 [-]: NEWTABLE R5 0 1; var5 = {}
      38 [-]: LOADN R6 10  ; var6 = 10
      39 [-]: SETLIST R5 R6 1 [1]; var5[1] = var6; var5[2] = var7; 
      40 [-]: NEWTABLE R6 0 1; var6 = {}
      41 [-]: LOADN R7 100 ; var7 = 100
      42 [-]: SETLIST R6 R7 1 [1]; var6[1] = var7; var6[2] = var8; 
      43 [-]: LOADK R7 K18 ; var7 = 1.5
      44 [-]: CALL R1 7 1  ; var1(var2, var3, var4, var5, var6, var7)
L 2:  45 [-]: GETIMPORT R1 16; var1 = 0x25312C9B
      46 [-]: GETIMPORT R2 6; var2 = 0xAE91E43B
      47 [-]: LOADK R3 K9  ; var3 = "CrpPopup.AssassinatedText.Label"
      48 [-]: LOADN R4 8   ; var4 = 8
      49 [-]: NEWTABLE R5 0 1; var5 = {}
      50 [-]: LOADN R6 67  ; var6 = 67
      51 [-]: SETLIST R5 R6 1 [1]; var5[1] = var6; var5[2] = var7; 
      52 [-]: NEWTABLE R6 0 1; var6 = {}
      53 [-]: LOADN R7 10  ; var7 = 10
      54 [-]: SETLIST R6 R7 1 [1]; var6[1] = var7; var6[2] = var8; 
      55 [-]: LOADK R7 K19 ; var7 = 0.34999999403953552
      56 [-]: LOADN R8 0   ; var8 = 0
      57 [-]: DUPCLOSURE R9 K20; 
      58 [-]: CALL R1 9 1  ; var1(var2, var3, var4, var5, var6, var7, var8, var9)
      59 [-]: JUMP L6      ; goto L6
L 3:  60 [-]: GETIMPORT R1 6; var1 = 0xAE91E43B
      61 [-]: LOADK R3 K21 ; var3 = "Popup.AssassinatedText"
      62 [-]: LOADN R4 1   ; var4 = 1
      63 [-]: LOADN R6 115 ; var6 = 115
      64 [-]: GETUPVAL R8 3; var8 = upvalues[3]
      65 [-]: GETTABLEKS R7 R8 K22; var7 = var8[0x06D055F9]
      66 [-]: GETUPVAL R8 0; var8 = upvalues[0]
      67 [-]: LOADN R9 -25 ; var9 = -25
      68 [-]: LOADN R10 0  ; var10 = 0
      69 [-]: CALL R7 4 2  ; var7 = var7(var8, var9, var10)
      70 [-]: ADD R5 R6 R7 ; var5 = var6 + var7
      71 [-]: NAMECALL R1 R1 K10; var2 = var1; var1 = var1[0x67BC869F]
      72 [-]: CALL R1 5 1  ; var1(var2, var3, var4, var5)
      73 [-]: GETIMPORT R1 6; var1 = 0xAE91E43B
      74 [-]: LOADK R3 K23 ; var3 = "Popup.AssassinatedText.Label.text"
      75 [-]: MOVE R4 R0   ; var4 = var0
      76 [-]: NAMECALL R1 R1 K8; var2 = var1; var1 = var1[0x20B98DB3]
      77 [-]: CALL R1 4 1  ; var1(var2, var3, var4)
      78 [-]: GETIMPORT R1 6; var1 = 0xAE91E43B
      79 [-]: LOADK R3 K24 ; var3 = "Popup.AssassinatedText.Label"
      80 [-]: LOADN R4 67  ; var4 = 67
      81 [-]: LOADN R5 0   ; var5 = 0
      82 [-]: NAMECALL R1 R1 K10; var2 = var1; var1 = var1[0x67BC869F]
      83 [-]: CALL R1 5 1  ; var1(var2, var3, var4, var5)
      84 [-]: GETUPVAL R1 2; var1 = upvalues[2]
      85 [-]: JUMPIFNOT R1 L4; goto L4 if not var1
      86 [-]: GETUPVAL R2 3; var2 = upvalues[3]
      87 [-]: GETTABLEKS R1 R2 K11; var1 = var2[0xF76783E5]
      88 [-]: GETIMPORT R2 6; var2 = 0xAE91E43B
      89 [-]: LOADK R3 K25 ; var3 = "Popup.Rank"
      90 [-]: GETIMPORT R4 27; var4 = 0x6A5782D6
      91 [-]: CALL R1 4 1  ; var1(var2, var3, var4)
L 4:  92 [-]: GETUPVAL R1 0; var1 = upvalues[0]
      93 [-]: JUMPIFNOT R1 L5; goto L5 if not var1
      94 [-]: GETIMPORT R1 16; var1 = 0x25312C9B
      95 [-]: GETIMPORT R2 6; var2 = 0xAE91E43B
      96 [-]: LOADK R3 K28 ; var3 = "Popup.BottomText"
      97 [-]: LOADN R4 8   ; var4 = 8
      98 [-]: NEWTABLE R5 0 1; var5 = {}
      99 [-]: LOADN R6 10  ; var6 = 10
     100 [-]: SETLIST R5 R6 1 [1]; var5[1] = var6; var5[2] = var7; 
     101 [-]: NEWTABLE R6 0 1; var6 = {}
     102 [-]: LOADN R7 100 ; var7 = 100
     103 [-]: SETLIST R6 R7 1 [1]; var6[1] = var7; var6[2] = var8; 
     104 [-]: LOADK R7 K18 ; var7 = 1.5
     105 [-]: CALL R1 7 1  ; var1(var2, var3, var4, var5, var6, var7)
L 5: 106 [-]: GETIMPORT R1 16; var1 = 0x25312C9B
     107 [-]: GETIMPORT R2 6; var2 = 0xAE91E43B
     108 [-]: LOADK R3 K24 ; var3 = "Popup.AssassinatedText.Label"
     109 [-]: LOADN R4 8   ; var4 = 8
     110 [-]: NEWTABLE R5 0 1; var5 = {}
     111 [-]: LOADN R6 67  ; var6 = 67
     112 [-]: SETLIST R5 R6 1 [1]; var5[1] = var6; var5[2] = var7; 
     113 [-]: NEWTABLE R6 0 1; var6 = {}
     114 [-]: LOADN R7 10  ; var7 = 10
     115 [-]: SETLIST R6 R7 1 [1]; var6[1] = var7; var6[2] = var8; 
     116 [-]: LOADK R7 K19 ; var7 = 0.34999999403953552
     117 [-]: LOADN R8 0   ; var8 = 0
     118 [-]: DUPCLOSURE R9 K29; 
     119 [-]: CALL R1 9 1  ; var1(var2, var3, var4, var5, var6, var7, var8, var9)
L 6: 120 [-]: GETUPVAL R1 0; var1 = upvalues[0]
     121 [-]: JUMPIFNOT R1 L7; goto L7 if not var1
     122 [-]: GETUPVAL R1 4; var1 = upvalues[4]
     123 [-]: CALL R1 1 1  ; var1()
     124 [-]: RETURN R0 0  ; 
L 7: 125 [-]: GETUPVAL R1 5; var1 = upvalues[5]
     126 [-]: GETUPVAL R3 6; var3 = upvalues[6]
     127 [-]: DUPCLOSURE R4 K30; 
     128 [-]: NAMECALL R1 R1 K31; var2 = var1; var1 = var1[0xBD2E96EA]
     129 [-]: CALL R1 4 1  ; var1(var2, var3, var4)
     130 [-]: RETURN R0 0  ; 


; Name:            
; Defined at line: 521
; #Upvalues:       1
; #Parameters:     4
; Is_vararg:       0
; Max Stack Size:  8

       0 [-]: GETUPVAL R5 0; var5 = upvalues[0]
       1 [-]: FASTCALL1 64 R5 L0; 
       2 [-]: GETIMPORT R4 1; var4 = 0x7B998233
       3 [-]: CALL R4 2 2  ; var4 = var4(var5)
L 0:   4 [-]: JUMPIF R4 L1 ; goto L1 if var4
       5 [-]: GETUPVAL R4 0; var4 = upvalues[0]
       6 [-]: MOVE R6 R0   ; var6 = var0
       7 [-]: MOVE R7 R1   ; var7 = var1
       8 [-]: NAMECALL R4 R4 K2; var5 = var4; var4 = var4[0xFAA69527]
       9 [-]: CALL R4 4 1  ; var4(var5, var6, var7)
L 1:  10 [-]: RETURN R0 0  ; 


; Name:            
; Defined at line: 527
; #Upvalues:       0
; #Parameters:     0
; Is_vararg:       0
; Max Stack Size:  1

       0 [-]: LOADB R0 1   ; var0 = true
       1 [-]: RETURN R0 1  ; 


; Name:            
; Defined at line: 531
; #Upvalues:       2
; #Parameters:     0
; Is_vararg:       0
; Max Stack Size:  3

       0 [-]: LOADNIL R0   ; var0 = nil
       1 [-]: SETUPVAL R0 0; upvalues[0] = var0
       2 [-]: GETUPVAL R1 1; var1 = upvalues[1]
       3 [-]: FASTCALL1 64 R1 L0; 
       4 [-]: GETIMPORT R0 1; var0 = 0x7B998233
       5 [-]: CALL R0 2 2  ; var0 = var0(var1)
L 0:   6 [-]: JUMPIF R0 L1 ; goto L1 if var0
       7 [-]: GETUPVAL R0 1; var0 = upvalues[1]
       8 [-]: LOADB R2 0   ; var2 = false
       9 [-]: NAMECALL R0 R0 K2; var1 = var0; var0 = var0[0x6CF1E476]
      10 [-]: CALL R0 3 1  ; var0(var1, var2)
      11 [-]: LOADNIL R0   ; var0 = nil
      12 [-]: SETUPVAL R0 1; upvalues[0] = var1
L 1:  13 [-]: RETURN R0 0  ; 


; Name:            
; Defined at line: 540
; #Upvalues:       5
; #Parameters:     0
; Is_vararg:       0
; Max Stack Size:  2

       0 [-]: GETUPVAL R0 1; var0 = upvalues[1]
       1 [-]: SETUPVAL R0 0; upvalues[0] = var0
       2 [-]: GETUPVAL R1 2; var1 = upvalues[2]
       3 [-]: FASTCALL1 64 R1 L0; 
       4 [-]: GETIMPORT R0 1; var0 = 0x7B998233
       5 [-]: CALL R0 2 2  ; var0 = var0(var1)
L 0:   6 [-]: JUMPIFNOT R0 L1; goto L1 if not var0
       7 [-]: GETUPVAL R1 3; var1 = upvalues[3]
       8 [-]: GETTABLEKS R0 R1 K2; var0 = var1[0x659D451F]
       9 [-]: GETUPVAL R1 4; var1 = upvalues[4]
      10 [-]: CALL R0 2 2  ; var0 = var0(var1)
      11 [-]: SETUPVAL R0 2; upvalues[0] = var2
L 1:  12 [-]: RETURN R0 0  ; 


; Name:            
; Defined at line: 545
; #Upvalues:       3
; #Parameters:     0
; Is_vararg:       0
; Max Stack Size:  2

       0 [-]: GETUPVAL R0 0; var0 = upvalues[0]
       1 [-]: GETUPVAL R1 1; var1 = upvalues[1]
       2 [-]: JUMPIFNOTEQ R0 R1 L0; goto L0 if var0 ~= var131132
       3 [-]: GETUPVAL R0 2; var0 = upvalues[2]
       4 [-]: CALL R0 1 1  ; var0()
L 0:   5 [-]: RETURN R0 0  ; 


; Name:            
; Defined at line: 550
; #Upvalues:       5
; #Parameters:     0
; Is_vararg:       0
; Max Stack Size:  2

       0 [-]: GETUPVAL R0 1; var0 = upvalues[1]
       1 [-]: SETUPVAL R0 0; upvalues[0] = var0
       2 [-]: GETUPVAL R1 2; var1 = upvalues[2]
       3 [-]: FASTCALL1 64 R1 L0; 
       4 [-]: GETIMPORT R0 1; var0 = 0x7B998233
       5 [-]: CALL R0 2 2  ; var0 = var0(var1)
L 0:   6 [-]: JUMPIFNOT R0 L1; goto L1 if not var0
       7 [-]: GETUPVAL R1 3; var1 = upvalues[3]
       8 [-]: GETTABLEKS R0 R1 K2; var0 = var1[0x659D451F]
       9 [-]: GETUPVAL R1 4; var1 = upvalues[4]
      10 [-]: CALL R0 2 2  ; var0 = var0(var1)
      11 [-]: SETUPVAL R0 2; upvalues[0] = var2
L 1:  12 [-]: RETURN R0 0  ; 


; Name:            
; Defined at line: 555
; #Upvalues:       3
; #Parameters:     0
; Is_vararg:       0
; Max Stack Size:  2

       0 [-]: GETUPVAL R0 0; var0 = upvalues[0]
       1 [-]: GETUPVAL R1 1; var1 = upvalues[1]
       2 [-]: JUMPIFNOTEQ R0 R1 L0; goto L0 if var0 ~= var131132
       3 [-]: GETUPVAL R0 2; var0 = upvalues[2]
       4 [-]: CALL R0 1 1  ; var0()
L 0:   5 [-]: RETURN R0 0  ; 



