; Name:            
; Defined at line: 1
; #Upvalues:       0
; #Parameters:     0
; Is_vararg:       1
; Max Stack Size:  20

       1 [-]: GETIMPORT R0 1; var0 = 0x2D0FAD09
       2 [-]: LOADK R1 K2  ; var1 = "Lotus.Interface.UIUtilities"
       3 [-]: CALL R0 2 2  ; var0 = var0(var1)
       4 [-]: GETIMPORT R1 1; var1 = 0x2D0FAD09
       5 [-]: LOADK R2 K3  ; var2 = "EE.Interface.Utilities"
       6 [-]: CALL R1 2 2  ; var1 = var1(var2)
       7 [-]: LOADNIL R2   ; var2 = nil
       8 [-]: LOADB R3 0   ; var3 = false
       9 [-]: LOADB R4 0   ; var4 = false
      10 [-]: DUPTABLE R5 5; 
      11 [-]: LOADN R6 0   ; var6 = 0
      12 [-]: SETTABLEKS R6 R5 K4; var6["WaitingOnTrans"] = var5
      13 [-]: LOADN R6 1   ; var6 = 1
      14 [-]: LOADNIL R7   ; var7 = nil
      15 [-]: NEWTABLE R8 0 10; var8 = {}
      16 [-]: DUPTABLE R9 8; 
      17 [-]: LOADK R10 K9 ; var10 = "Stop1"
      18 [-]: SETTABLEKS R10 R9 K6; var10["Frame"] = var9
      19 [-]: LOADK R10 K10; var10 = "Slide1"
      20 [-]: SETTABLEKS R10 R9 K7; var10["Tag"] = var9
      21 [-]: DUPTABLE R10 8; 
      22 [-]: LOADK R11 K11; var11 = "Slide2"
      23 [-]: SETTABLEKS R11 R10 K6; var11["Frame"] = var10
      24 [-]: LOADK R11 K11; var11 = "Slide2"
      25 [-]: SETTABLEKS R11 R10 K7; var11["Tag"] = var10
      26 [-]: DUPTABLE R11 8; 
      27 [-]: LOADK R12 K12; var12 = "Slide3"
      28 [-]: SETTABLEKS R12 R11 K6; var12["Frame"] = var11
      29 [-]: LOADK R12 K12; var12 = "Slide3"
      30 [-]: SETTABLEKS R12 R11 K7; var12["Tag"] = var11
      31 [-]: DUPTABLE R12 8; 
      32 [-]: LOADK R13 K13; var13 = "Slide4"
      33 [-]: SETTABLEKS R13 R12 K6; var13["Frame"] = var12
      34 [-]: LOADK R13 K13; var13 = "Slide4"
      35 [-]: SETTABLEKS R13 R12 K7; var13["Tag"] = var12
      36 [-]: DUPTABLE R13 8; 
      37 [-]: LOADK R14 K14; var14 = "Slide5"
      38 [-]: SETTABLEKS R14 R13 K6; var14["Frame"] = var13
      39 [-]: LOADK R14 K14; var14 = "Slide5"
      40 [-]: SETTABLEKS R14 R13 K7; var14["Tag"] = var13
      41 [-]: DUPTABLE R14 8; 
      42 [-]: LOADK R15 K15; var15 = "Slide6"
      43 [-]: SETTABLEKS R15 R14 K6; var15["Frame"] = var14
      44 [-]: LOADK R15 K15; var15 = "Slide6"
      45 [-]: SETTABLEKS R15 R14 K7; var15["Tag"] = var14
      46 [-]: DUPTABLE R15 18; 
      47 [-]: LOADK R16 K19; var16 = "Slide7"
      48 [-]: SETTABLEKS R16 R15 K6; var16["Frame"] = var15
      49 [-]: LOADK R16 K19; var16 = "Slide7"
      50 [-]: SETTABLEKS R16 R15 K7; var16["Tag"] = var15
      51 [-]: LOADN R16 3  ; var16 = 3
      52 [-]: SETTABLEKS R16 R15 K16; var16["Timer"] = var15
      53 [-]: LOADN R16 1  ; var16 = 1
      54 [-]: SETTABLEKS R16 R15 K17; var16["SoundIndex"] = var15
      55 [-]: DUPTABLE R16 8; 
      56 [-]: LOADK R17 K20; var17 = "Slide8"
      57 [-]: SETTABLEKS R17 R16 K6; var17["Frame"] = var16
      58 [-]: LOADK R17 K20; var17 = "Slide8"
      59 [-]: SETTABLEKS R17 R16 K7; var17["Tag"] = var16
      60 [-]: DUPTABLE R17 8; 
      61 [-]: LOADK R18 K21; var18 = "Slide9"
      62 [-]: SETTABLEKS R18 R17 K6; var18["Frame"] = var17
      63 [-]: LOADK R18 K21; var18 = "Slide9"
      64 [-]: SETTABLEKS R18 R17 K7; var18["Tag"] = var17
      65 [-]: DUPTABLE R18 8; 
      66 [-]: LOADK R19 K22; var19 = "Slide10"
      67 [-]: SETTABLEKS R19 R18 K6; var19["Frame"] = var18
      68 [-]: LOADK R19 K22; var19 = "Slide10"
      69 [-]: SETTABLEKS R19 R18 K7; var19["Tag"] = var18
      70 [-]: SETLIST R8 R9 10 [1]; var8[1] = var9; var8[2] = var10; var8[3] = var11; var8[4] = var12; var8[5] = var13; var8[6] = var14; var8[7] = var15; var8[8] = var16; var8[9] = var17; var8[10] = var18; var8[11] = var19; 
      71 [-]: LOADNIL R9   ; var9 = nil
      72 [-]: LOADNIL R10  ; var10 = nil
      73 [-]: NEWCLOSURE R11 P0; 
      74 [-]: CAPTURE REF R6; 
      75 [-]: CAPTURE REF R10; 
      76 [-]: NEWCLOSURE R12 P1; 
      77 [-]: CAPTURE REF R9; 
      78 [-]: CAPTURE REF R7; 
      79 [-]: NEWCLOSURE R13 P2; 
      80 [-]: CAPTURE REF R4; 
      81 [-]: CAPTURE VAL R5; 
      82 [-]: CAPTURE VAL R1; 
      83 [-]: CAPTURE REF R6; 
      84 [-]: CAPTURE VAL R8; 
      85 [-]: NEWCLOSURE R10 P3; 
      86 [-]: CAPTURE VAL R8; 
      87 [-]: CAPTURE REF R6; 
      88 [-]: CAPTURE REF R2; 
      89 [-]: CAPTURE VAL R11; 
      90 [-]: CAPTURE VAL R5; 
      91 [-]: CAPTURE VAL R0; 
      92 [-]: CAPTURE VAL R13; 
      93 [-]: NEWCLOSURE R14 P4; 
      94 [-]: CAPTURE REF R3; 
      95 [-]: CAPTURE VAL R1; 
      96 [-]: CAPTURE REF R2; 
      97 [-]: CAPTURE REF R4; 
      98 [-]: CAPTURE REF R7; 
      99 [-]: CAPTURE REF R10; 
     100 [-]: SETGLOBAL R14 K23; "Initialize" = var14
     101 [-]: NEWCLOSURE R14 P5; 
     102 [-]: CAPTURE REF R2; 
     103 [-]: CAPTURE VAL R5; 
     104 [-]: CAPTURE VAL R13; 
     105 [-]: SETGLOBAL R14 K24; "Update" = var14
     106 [-]: DUPCLOSURE R14 K25; 
     107 [-]: SETGLOBAL R14 K26; "Shutdown" = var14
     108 [-]: NEWCLOSURE R14 P7; 
     109 [-]: CAPTURE REF R9; 
     110 [-]: CAPTURE VAL R13; 
     111 [-]: SETGLOBAL R14 K27; "SetCallBack" = var14
     112 [-]: DUPCLOSURE R14 K28; 
     113 [-]: SETGLOBAL R14 K29; "TestOpen" = var14
     114 [-]: NEWCLOSURE R14 P9; 
     115 [-]: CAPTURE REF R6; 
     116 [-]: DUPCLOSURE R15 K30; 
     117 [-]: CAPTURE VAL R14; 
     118 [-]: SETGLOBAL R15 K31; "OnFrameEnter" = var15
     119 [-]: NEWCLOSURE R15 P11; 
     120 [-]: CAPTURE VAL R5; 
     121 [-]: CAPTURE VAL R1; 
     122 [-]: CAPTURE REF R6; 
     123 [-]: CAPTURE VAL R8; 
     124 [-]: CAPTURE VAL R11; 
     125 [-]: CAPTURE VAL R12; 
     126 [-]: DUPCLOSURE R16 K32; 
     127 [-]: CAPTURE VAL R15; 
     128 [-]: SETGLOBAL R16 K33; "onKeyUp_MENU_SELECT" = var16
     129 [-]: DUPCLOSURE R16 K34; 
     130 [-]: CAPTURE VAL R15; 
     131 [-]: SETGLOBAL R16 K35; "onKeyUp_MENU_CLICK" = var16
     132 [-]: DUPCLOSURE R16 K36; 
     133 [-]: SETGLOBAL R16 K37; "onKeyUp_MENU_RTRIGGER2" = var16
     134 [-]: DUPCLOSURE R16 K38; 
     135 [-]: CAPTURE VAL R13; 
     136 [-]: SETGLOBAL R16 K39; "OnGamepadTransition" = var16
     137 [-]: DUPCLOSURE R16 K40; 
     138 [-]: CAPTURE VAL R15; 
     139 [-]: SETGLOBAL R16 K41; "onRawInputEvent" = var16
     140 [-]: CLOSEUPVALS R2; 
     141 [-]: RETURN R0 0  ; 


; Name:            
; Defined at line: 71
; #Upvalues:       2
; #Parameters:     0
; Is_vararg:       0
; Max Stack Size:  2

       0 [-]: GETUPVAL R1 0; var1 = upvalues[0]
       1 [-]: ADDK R0 R1 K0; var0 = var1 + 1
       2 [-]: SETUPVAL R0 0; upvalues[0] = var0
       3 [-]: GETUPVAL R0 1; var0 = upvalues[1]
       4 [-]: CALL R0 1 1  ; var0()
       5 [-]: RETURN R0 0  ; 


; Name:            
; Defined at line: 77
; #Upvalues:       2
; #Parameters:     0
; Is_vararg:       0
; Max Stack Size:  5

       0 [-]: GETUPVAL R1 0; var1 = upvalues[0]
       1 [-]: FASTCALL1 62 R1 L0; 
       2 [-]: GETIMPORT R0 1; var0 = 0x7B998233
       3 [-]: CALL R0 2 2  ; var0 = var0(var1)
L 0:   4 [-]: JUMPIF R0 L2 ; goto L2 if var0
       5 [-]: GETIMPORT R2 3; var2 = _T
       6 [-]: GETUPVAL R3 0; var3 = upvalues[0]
       7 [-]: GETTABLE R1 R2 R3; var1 = var2[var3]
       8 [-]: FASTCALL1 62 R1 L1; 
       9 [-]: GETIMPORT R0 1; var0 = 0x7B998233
      10 [-]: CALL R0 2 2  ; var0 = var0(var1)
L 1:  11 [-]: JUMPIF R0 L2 ; goto L2 if var0
      12 [-]: GETIMPORT R1 3; var1 = _T
      13 [-]: GETUPVAL R2 0; var2 = upvalues[0]
      14 [-]: GETTABLE R0 R1 R2; var0 = var1[var2]
      15 [-]: CALL R0 1 1  ; var0()
L 2:  16 [-]: GETUPVAL R1 1; var1 = upvalues[1]
      17 [-]: FASTCALL1 62 R1 L3; 
      18 [-]: GETIMPORT R0 1; var0 = 0x7B998233
      19 [-]: CALL R0 2 2  ; var0 = var0(var1)
L 3:  20 [-]: JUMPIF R0 L4 ; goto L4 if var0
      21 [-]: GETUPVAL R0 1; var0 = upvalues[1]
      22 [-]: LOADB R2 0   ; var2 = false
      23 [-]: NAMECALL R0 R0 K4; var1 = var0; var0 = var0[0x6CF1E476]
      24 [-]: CALL R0 3 1  ; var0(var1, var2)
L 4:  25 [-]: GETIMPORT R0 6; var0 = 0x89326C93
      26 [-]: GETIMPORT R2 8; var2 = 0x0469F296
      27 [-]: LOADK R3 K9  ; var3 = "LessonScreen"
      28 [-]: CALL R2 2 0  ; var2, ... = var2(var3)
      29 [-]: NAMECALL R0 R0 K10; var1 = var0; var0 = var0[0x46A0EBF5]
      30 [-]: CALL R0 0 2  ; var0 = var0(var1, ...)
      31 [-]: FASTCALL1 62 R0 L5; 
      32 [-]: MOVE R2 R0   ; var2 = var0
      33 [-]: GETIMPORT R1 1; var1 = 0x7B998233
      34 [-]: CALL R1 2 2  ; var1 = var1(var2)
L 5:  35 [-]: JUMPIF R1 L6 ; goto L6 if var1
      36 [-]: GETIMPORT R3 12; var3 = 0xB607EFE1
      37 [-]: LOADB R4 0   ; var4 = false
      38 [-]: NAMECALL R1 R0 K13; var2 = var0; var1 = var0[0x659D451F]
      39 [-]: CALL R1 4 1  ; var1(var2, var3, var4)
L 6:  40 [-]: GETIMPORT R1 15; var1 = 0xAE91E43B
      41 [-]: NAMECALL R1 R1 K16; var2 = var1; var1 = var1[0x32302B4A]
      42 [-]: CALL R1 2 1  ; var1(var2)
      43 [-]: RETURN R0 0  ; 


; Name:            
; Defined at line: 94
; #Upvalues:       5
; #Parameters:     0
; Is_vararg:       0
; Max Stack Size:  12

       0 [-]: NEWTABLE R0 0 0; var0 = {}
       1 [-]: GETUPVAL R1 0; var1 = upvalues[0]
       2 [-]: JUMPIFNOT R1 L0; goto L0 if not var1
       3 [-]: RETURN R0 0  ; 
L 0:   4 [-]: LOADN R1 0   ; var1 = 0
       5 [-]: GETUPVAL R3 1; var3 = upvalues[1]
       6 [-]: GETTABLEKS R2 R3 K0; var2 = var3["WaitingOnTrans"]
       7 [-]: JUMPXEQKN R2 K1 L3 NOT; 
       8 [-]: GETIMPORT R2 3; var2 = 0xAE91E43B
       9 [-]: GETUPVAL R5 2; var5 = upvalues[2]
      10 [-]: GETTABLEKS R4 R5 K4; var4 = var5[0x06D055F9]
      11 [-]: GETIMPORT R5 7; var5 = 0x34291F5C[0x1467D5F4]
      12 [-]: CALL R5 1 2  ; var5 = var5()
      13 [-]: LOADK R6 K8  ; var6 = "<MENU_SELECT>"
      14 [-]: LOADK R7 K9  ; var7 = "<MINI_GAME_SELECT>"
      15 [-]: CALL R4 4 2  ; var4 = var4(var5, var6, var7)
      16 [-]: LOADB R5 1   ; var5 = true
      17 [-]: NAMECALL R2 R2 K10; var3 = var2; var2 = var2[0x42B04007]
      18 [-]: CALL R2 4 2  ; var2 = var2(var3, var4, var5)
      19 [-]: GETIMPORT R3 3; var3 = 0xAE91E43B
      20 [-]: LOADK R6 K11 ; var6 = "/Lotus/Language/Menu/"
      21 [-]: GETUPVAL R8 2; var8 = upvalues[2]
      22 [-]: GETTABLEKS R7 R8 K4; var7 = var8[0x06D055F9]
      23 [-]: GETUPVAL R9 3; var9 = upvalues[3]
      24 [-]: GETUPVAL R11 4; var11 = upvalues[4]
      25 [-]: LENGTH R10 R11; var10 = #var11
      26 [-]: JUMPIFLT R9 R10 L1; goto L1 if var9 < var16779291
      27 [-]: LOADB R8 0 +1; var8 = false
L 1:  28 [-]: LOADB R8 1   ; var8 = true
L 2:  29 [-]: LOADK R9 K12 ; var9 = "UpdateHistory_Next"
      30 [-]: LOADK R10 K13; var10 = "MissionStats_Done"
      31 [-]: CALL R7 4 2  ; var7 = var7(var8, var9, var10)
      32 [-]: CONCAT R5 R6 R7; var5 = var6 .. var7
      33 [-]: LOADB R6 0   ; var6 = false
      34 [-]: NAMECALL R3 R3 K10; var4 = var3; var3 = var3[0x42B04007]
      35 [-]: CALL R3 4 2  ; var3 = var3(var4, var5, var6)
      36 [-]: GETIMPORT R4 3; var4 = 0xAE91E43B
      37 [-]: LOADK R6 K14 ; var6 = "Arrow.Next"
      38 [-]: LOADN R7 29  ; var7 = 29
      39 [-]: MOVE R9 R2   ; var9 = var2
      40 [-]: LOADK R10 K15; var10 = " "
      41 [-]: MOVE R11 R3  ; var11 = var3
      42 [-]: CONCAT R8 R9 R11; var8 = var9 .. var11
      43 [-]: NAMECALL R4 R4 K16; var5 = var4; var4 = var4[0x5F56EEAB]
      44 [-]: CALL R4 5 1  ; var4(var5, var6, var7, var8)
      45 [-]: LOADN R1 100 ; var1 = 100
L 3:  46 [-]: GETIMPORT R2 18; var2 = 0x25312C9B
      47 [-]: GETIMPORT R3 3; var3 = 0xAE91E43B
      48 [-]: LOADK R4 K19 ; var4 = "Arrow"
      49 [-]: LOADN R5 0   ; var5 = 0
      50 [-]: NEWTABLE R6 0 1; var6 = {}
      51 [-]: LOADN R7 10  ; var7 = 10
      52 [-]: SETLIST R6 R7 1 [1]; var6[1] = var7; var6[2] = var8; 
      53 [-]: NEWTABLE R7 0 1; var7 = {}
      54 [-]: MOVE R8 R1   ; var8 = var1
      55 [-]: SETLIST R7 R8 1 [1]; var7[1] = var8; var7[2] = var9; 
      56 [-]: LOADK R8 K20 ; var8 = 0.25
      57 [-]: CALL R2 7 1  ; var2(var3, var4, var5, var6, var7, var8)
      58 [-]: GETIMPORT R3 23; var3 = _T["SetButtons"]
      59 [-]: FASTCALL1 62 R3 L4; 
      60 [-]: GETIMPORT R2 25; var2 = 0x7B998233
      61 [-]: CALL R2 2 2  ; var2 = var2(var3)
L 4:  62 [-]: JUMPIF R2 L5 ; goto L5 if var2
      63 [-]: GETIMPORT R2 23; var2 = _T["SetButtons"]
      64 [-]: GETIMPORT R3 3; var3 = 0xAE91E43B
      65 [-]: MOVE R4 R0   ; var4 = var0
      66 [-]: GETIMPORT R5 27; var5 = 0xCD0165A3
      67 [-]: LOADN R6 1   ; var6 = 1
      68 [-]: CALL R5 2 2  ; var5 = var5(var6)
      69 [-]: LOADNIL R6   ; var6 = nil
      70 [-]: LOADB R7 1   ; var7 = true
      71 [-]: CALL R2 6 1  ; var2(var3, var4, var5, var6, var7)
L 5:  72 [-]: RETURN R0 0  ; 


; Name:            
; Defined at line: 123
; #Upvalues:       7
; #Parameters:     0
; Is_vararg:       0
; Max Stack Size:  7

       0 [-]: GETUPVAL R1 0; var1 = upvalues[0]
       1 [-]: GETUPVAL R2 1; var2 = upvalues[1]
       2 [-]: GETTABLE R0 R1 R2; var0 = var1[var2]
       3 [-]: GETTABLEKS R2 R0 K0; var2 = var0["Frame"]
       4 [-]: FASTCALL1 62 R2 L0; 
       5 [-]: GETIMPORT R1 2; var1 = 0x7B998233
       6 [-]: CALL R1 2 2  ; var1 = var1(var2)
L 0:   7 [-]: JUMPIF R1 L1 ; goto L1 if var1
       8 [-]: GETIMPORT R1 4; var1 = 0x38F10E85
       9 [-]: GETIMPORT R2 6; var2 = 0xAE91E43B
      10 [-]: LOADK R3 K7  ; var3 = "_root.gotoAndStop"
      11 [-]: GETTABLEKS R4 R0 K0; var4 = var0["Frame"]
      12 [-]: CALL R1 4 1  ; var1(var2, var3, var4)
      13 [-]: GETIMPORT R1 6; var1 = 0xAE91E43B
      14 [-]: GETTABLEKS R3 R0 K8; var3 = var0["Tag"]
      15 [-]: LOADK R4 K9  ; var4 = "OnFrameEnter"
      16 [-]: NAMECALL R1 R1 K10; var2 = var1; var1 = var1[0x5EE2CC30]
      17 [-]: CALL R1 4 1  ; var1(var2, var3, var4)
L 1:  18 [-]: GETTABLEKS R2 R0 K11; var2 = var0["SoundIndex"]
      19 [-]: FASTCALL1 62 R2 L2; 
      20 [-]: GETIMPORT R1 2; var1 = 0x7B998233
      21 [-]: CALL R1 2 2  ; var1 = var1(var2)
L 2:  22 [-]: JUMPIF R1 L5 ; goto L5 if var1
      23 [-]: GETIMPORT R3 13; var3 = 0x783030E3
      24 [-]: GETTABLEKS R4 R0 K11; var4 = var0["SoundIndex"]
      25 [-]: GETTABLE R2 R3 R4; var2 = var3[var4]
      26 [-]: FASTCALL1 62 R2 L3; 
      27 [-]: GETIMPORT R1 2; var1 = 0x7B998233
      28 [-]: CALL R1 2 2  ; var1 = var1(var2)
L 3:  29 [-]: JUMPIF R1 L5 ; goto L5 if var1
      30 [-]: GETIMPORT R1 15; var1 = 0x89326C93
      31 [-]: GETIMPORT R3 17; var3 = 0x0469F296
      32 [-]: LOADK R4 K18 ; var4 = "LessonScreen"
      33 [-]: CALL R3 2 0  ; var3, ... = var3(var4)
      34 [-]: NAMECALL R1 R1 K19; var2 = var1; var1 = var1[0x46A0EBF5]
      35 [-]: CALL R1 0 2  ; var1 = var1(var2, ...)
      36 [-]: FASTCALL1 62 R1 L4; 
      37 [-]: MOVE R3 R1   ; var3 = var1
      38 [-]: GETIMPORT R2 2; var2 = 0x7B998233
      39 [-]: CALL R2 2 2  ; var2 = var2(var3)
L 4:  40 [-]: JUMPIF R2 L5 ; goto L5 if var2
      41 [-]: GETIMPORT R5 13; var5 = 0x783030E3
      42 [-]: GETTABLEKS R6 R0 K11; var6 = var0["SoundIndex"]
      43 [-]: GETTABLE R4 R5 R6; var4 = var5[var6]
      44 [-]: LOADB R5 0   ; var5 = false
      45 [-]: NAMECALL R2 R1 K20; var3 = var1; var2 = var1[0x659D451F]
      46 [-]: CALL R2 4 1  ; var2(var3, var4, var5)
L 5:  47 [-]: GETTABLEKS R1 R0 K21; var1 = var0["Timer"]
      48 [-]: JUMPXEQKNIL R1 L6; 
      49 [-]: GETUPVAL R1 2; var1 = upvalues[2]
      50 [-]: GETTABLEKS R3 R0 K21; var3 = var0["Timer"]
      51 [-]: GETUPVAL R4 3; var4 = upvalues[3]
      52 [-]: NAMECALL R1 R1 K22; var2 = var1; var1 = var1[0xBD2E96EA]
      53 [-]: CALL R1 4 1  ; var1(var2, var3, var4)
      54 [-]: GETUPVAL R1 4; var1 = upvalues[4]
      55 [-]: LOADN R2 3   ; var2 = 3
      56 [-]: SETTABLEKS R2 R1 K23; var2["WaitingOnTrans"] = var1
      57 [-]: JUMP L10     ; goto L10
L 6:  58 [-]: GETTABLEKS R2 R0 K8; var2 = var0["Tag"]
      59 [-]: FASTCALL1 62 R2 L7; 
      60 [-]: GETIMPORT R1 2; var1 = 0x7B998233
      61 [-]: CALL R1 2 2  ; var1 = var1(var2)
L 7:  62 [-]: JUMPIF R1 L9 ; goto L9 if var1
      63 [-]: GETIMPORT R2 25; var2 = 0x08AEE1A4
      64 [-]: GETIMPORT R4 17; var4 = 0x0469F296
      65 [-]: GETTABLEKS R5 R0 K8; var5 = var0["Tag"]
      66 [-]: CALL R4 2 0  ; var4, ... = var4(var5)
      67 [-]: NAMECALL R2 R2 K26; var3 = var2; var2 = var2[0x10C9EEF2]
      68 [-]: CALL R2 0 2  ; var2 = var2(var3, ...)
      69 [-]: FASTCALL1 62 R2 L8; 
      70 [-]: GETIMPORT R1 2; var1 = 0x7B998233
      71 [-]: CALL R1 2 2  ; var1 = var1(var2)
L 8:  72 [-]: JUMPIF R1 L9 ; goto L9 if var1
      73 [-]: GETUPVAL R2 5; var2 = upvalues[5]
      74 [-]: GETTABLEKS R1 R2 K27; var1 = var2[0x947DE44C]
      75 [-]: GETIMPORT R2 25; var2 = 0x08AEE1A4
      76 [-]: GETIMPORT R3 17; var3 = 0x0469F296
      77 [-]: GETTABLEKS R4 R0 K8; var4 = var0["Tag"]
      78 [-]: CALL R3 2 2  ; var3 = var3(var4)
      79 [-]: LOADB R4 1   ; var4 = true
      80 [-]: CALL R1 4 1  ; var1(var2, var3, var4)
      81 [-]: GETUPVAL R1 4; var1 = upvalues[4]
      82 [-]: LOADN R2 1   ; var2 = 1
      83 [-]: SETTABLEKS R2 R1 K23; var2["WaitingOnTrans"] = var1
      84 [-]: JUMP L10     ; goto L10
L 9:  85 [-]: GETUPVAL R1 4; var1 = upvalues[4]
      86 [-]: LOADN R2 2   ; var2 = 2
      87 [-]: SETTABLEKS R2 R1 K23; var2["WaitingOnTrans"] = var1
L10:  88 [-]: GETUPVAL R1 6; var1 = upvalues[6]
      89 [-]: CALL R1 1 1  ; var1()
      90 [-]: RETURN R0 0  ; 


; Name:            
; Defined at line: 151
; #Upvalues:       6
; #Parameters:     0
; Is_vararg:       0
; Max Stack Size:  7

       0 [-]: GETIMPORT R2 2; var2 = _T["NewWarLesson_AttachInfo"]
       1 [-]: FASTCALL1 62 R2 L0; 
       2 [-]: GETIMPORT R1 4; var1 = 0x7B998233
       3 [-]: CALL R1 2 2  ; var1 = var1(var2)
L 0:   4 [-]: NOT R0 R1    ; var0 = not var1
       5 [-]: SETUPVAL R0 0; upvalues[0] = var0
       6 [-]: GETIMPORT R0 6; var0 = 0xAE91E43B
       7 [-]: LOADB R2 1   ; var2 = true
       8 [-]: NAMECALL R0 R0 K7; var1 = var0; var0 = var0[0x767C0947]
       9 [-]: CALL R0 3 1  ; var0(var1, var2)
      10 [-]: GETIMPORT R0 6; var0 = 0xAE91E43B
      11 [-]: LOADB R2 0   ; var2 = false
      12 [-]: NAMECALL R0 R0 K8; var1 = var0; var0 = var0[0xAA503602]
      13 [-]: CALL R0 3 1  ; var0(var1, var2)
      14 [-]: GETIMPORT R0 6; var0 = 0xAE91E43B
      15 [-]: GETUPVAL R3 1; var3 = upvalues[1]
      16 [-]: GETTABLEKS R2 R3 K9; var2 = var3[0x06D055F9]
      17 [-]: GETUPVAL R3 0; var3 = upvalues[0]
      18 [-]: LOADN R4 0   ; var4 = 0
      19 [-]: LOADN R5 100 ; var5 = 100
      20 [-]: CALL R2 4 0  ; var2, ... = var2(var3, var4, var5)
      21 [-]: NAMECALL R0 R0 K10; var1 = var0; var0 = var0[0x58BEC6D6]
      22 [-]: CALL R0 0 1  ; var0(var1, ...)
      23 [-]: GETIMPORT R0 12; var0 = 0x2D0FAD09
      24 [-]: LOADK R1 K13 ; var1 = "Lotus.Interface.Libs.TimerMgr"
      25 [-]: CALL R0 2 2  ; var0 = var0(var1)
      26 [-]: GETTABLEKS R1 R0 K14; var1 = var0[0xDE474187]
      27 [-]: CALL R1 1 2  ; var1 = var1()
      28 [-]: SETUPVAL R1 2; upvalues[1] = var2
      29 [-]: GETUPVAL R1 0; var1 = upvalues[0]
      30 [-]: JUMPIFNOT R1 L3; goto L3 if not var1
      31 [-]: GETIMPORT R2 16; var2 = _T["NewWarLesson_AttachInfo"]["NoInput"]
      32 [-]: JUMPXEQKB R2 1 L1; 
      33 [-]: LOADB R1 0 +1; var1 = false
L 1:  34 [-]: LOADB R1 1   ; var1 = true
L 2:  35 [-]: SETUPVAL R1 3; upvalues[1] = var3
      36 [-]: GETIMPORT R1 6; var1 = 0xAE91E43B
      37 [-]: GETIMPORT R3 18; var3 = _T["NewWarLesson_AttachInfo"]["AttachEntity"]
      38 [-]: GETIMPORT R4 20; var4 = _T["NewWarLesson_AttachInfo"]["Offset"]
      39 [-]: GETIMPORT R5 22; var5 = _T["NewWarLesson_AttachInfo"]["Rotation"]
      40 [-]: GETIMPORT R6 24; var6 = _T["NewWarLesson_AttachInfo"]["Scale"]
      41 [-]: NAMECALL R1 R1 K25; var2 = var1; var1 = var1[0xE395D771]
      42 [-]: CALL R1 6 1  ; var1(var2, var3, var4, var5, var6)
      43 [-]: GETIMPORT R1 26; var1 = _T
      44 [-]: LOADNIL R2   ; var2 = nil
      45 [-]: SETTABLEKS R2 R1 K1; var2["NewWarLesson_AttachInfo"] = var1
L 3:  46 [-]: GETIMPORT R1 6; var1 = 0xAE91E43B
      47 [-]: GETUPVAL R3 3; var3 = upvalues[3]
      48 [-]: NAMECALL R1 R1 K27; var2 = var1; var1 = var1[0xBED40E9C]
      49 [-]: CALL R1 3 1  ; var1(var2, var3)
      50 [-]: GETUPVAL R1 4; var1 = upvalues[4]
      51 [-]: JUMPXEQKNIL R1 L5 NOT; 
      52 [-]: GETIMPORT R1 29; var1 = 0x89326C93
      53 [-]: GETIMPORT R3 31; var3 = 0x0469F296
      54 [-]: LOADK R4 K32 ; var4 = "LessonScreen"
      55 [-]: CALL R3 2 0  ; var3, ... = var3(var4)
      56 [-]: NAMECALL R1 R1 K33; var2 = var1; var1 = var1[0x46A0EBF5]
      57 [-]: CALL R1 0 2  ; var1 = var1(var2, ...)
      58 [-]: FASTCALL1 62 R1 L4; 
      59 [-]: MOVE R3 R1   ; var3 = var1
      60 [-]: GETIMPORT R2 4; var2 = 0x7B998233
      61 [-]: CALL R2 2 2  ; var2 = var2(var3)
L 4:  62 [-]: JUMPIF R2 L5 ; goto L5 if var2
      63 [-]: GETIMPORT R4 35; var4 = 0x3D7EA73B
      64 [-]: LOADB R5 0   ; var5 = false
      65 [-]: NAMECALL R2 R1 K36; var3 = var1; var2 = var1[0x659D451F]
      66 [-]: CALL R2 4 2  ; var2 = var2(var3, var4, var5)
      67 [-]: SETUPVAL R2 4; upvalues[2] = var4
L 5:  68 [-]: GETIMPORT R1 6; var1 = 0xAE91E43B
      69 [-]: LOADK R3 K37 ; var3 = "_root"
      70 [-]: LOADN R4 10  ; var4 = 10
      71 [-]: LOADN R5 75  ; var5 = 75
      72 [-]: NAMECALL R1 R1 K38; var2 = var1; var1 = var1[0x67BC869F]
      73 [-]: CALL R1 5 1  ; var1(var2, var3, var4, var5)
      74 [-]: GETIMPORT R1 6; var1 = 0xAE91E43B
      75 [-]: LOADK R3 K39 ; var3 = "Arrow"
      76 [-]: LOADN R4 10  ; var4 = 10
      77 [-]: LOADN R5 0   ; var5 = 0
      78 [-]: NAMECALL R1 R1 K38; var2 = var1; var1 = var1[0x67BC869F]
      79 [-]: CALL R1 5 1  ; var1(var2, var3, var4, var5)
      80 [-]: GETUPVAL R1 5; var1 = upvalues[5]
      81 [-]: CALL R1 1 1  ; var1()
      82 [-]: RETURN R0 0  ; 


; Name:            
; Defined at line: 182
; #Upvalues:       3
; #Parameters:     0
; Is_vararg:       0
; Max Stack Size:  3

       0 [-]: GETIMPORT R0 1; var0 = 0xAE91E43B
       1 [-]: GETIMPORT R2 3; var2 = 0xB693B6C1
       2 [-]: CALL R2 1 0  ; var2, ... = var2()
       3 [-]: NAMECALL R0 R0 K4; var1 = var0; var0 = var0[0x8A8C8D5A]
       4 [-]: CALL R0 0 1  ; var0(var1, ...)
       5 [-]: GETUPVAL R1 0; var1 = upvalues[0]
       6 [-]: FASTCALL1 62 R1 L0; 
       7 [-]: GETIMPORT R0 6; var0 = 0x7B998233
       8 [-]: CALL R0 2 2  ; var0 = var0(var1)
L 0:   9 [-]: JUMPIF R0 L1 ; goto L1 if var0
      10 [-]: GETUPVAL R0 0; var0 = upvalues[0]
      11 [-]: GETIMPORT R2 8; var2 = 0x67652851
      12 [-]: CALL R2 1 0  ; var2, ... = var2()
      13 [-]: NAMECALL R0 R0 K9; var1 = var0; var0 = var0[0xFAA69527]
      14 [-]: CALL R0 0 1  ; var0(var1, ...)
L 1:  15 [-]: GETUPVAL R1 1; var1 = upvalues[1]
      16 [-]: GETTABLEKS R0 R1 K10; var0 = var1["WaitingOnTrans"]
      17 [-]: JUMPXEQKN R0 K11 L3 NOT; 
      18 [-]: GETIMPORT R1 14; var1 = _T["curTransmission"]
      19 [-]: FASTCALL1 62 R1 L2; 
      20 [-]: GETIMPORT R0 6; var0 = 0x7B998233
      21 [-]: CALL R0 2 2  ; var0 = var0(var1)
L 2:  22 [-]: JUMPIF R0 L3 ; goto L3 if var0
      23 [-]: GETUPVAL R0 1; var0 = upvalues[1]
      24 [-]: LOADN R1 2   ; var1 = 2
      25 [-]: SETTABLEKS R1 R0 K10; var1["WaitingOnTrans"] = var0
      26 [-]: RETURN R0 0  ; 
L 3:  27 [-]: GETUPVAL R1 1; var1 = upvalues[1]
      28 [-]: GETTABLEKS R0 R1 K10; var0 = var1["WaitingOnTrans"]
      29 [-]: JUMPXEQKN R0 K15 L5 NOT; 
      30 [-]: GETIMPORT R1 14; var1 = _T["curTransmission"]
      31 [-]: FASTCALL1 62 R1 L4; 
      32 [-]: GETIMPORT R0 6; var0 = 0x7B998233
      33 [-]: CALL R0 2 2  ; var0 = var0(var1)
L 4:  34 [-]: JUMPIFNOT R0 L5; goto L5 if not var0
      35 [-]: GETUPVAL R0 1; var0 = upvalues[1]
      36 [-]: LOADN R1 0   ; var1 = 0
      37 [-]: SETTABLEKS R1 R0 K10; var1["WaitingOnTrans"] = var0
      38 [-]: GETUPVAL R0 2; var0 = upvalues[2]
      39 [-]: CALL R0 1 1  ; var0()
L 5:  40 [-]: RETURN R0 0  ; 


; Name:            
; Defined at line: 198
; #Upvalues:       0
; #Parameters:     0
; Is_vararg:       0
; Max Stack Size:  0

       0 [-]: RETURN R0 0  ; 


; Name:            
; Defined at line: 201
; #Upvalues:       2
; #Parameters:     1
; Is_vararg:       0
; Max Stack Size:  2

       0 [-]: SETUPVAL R0 0; upvalues[0] = var0
       1 [-]: GETUPVAL R1 1; var1 = upvalues[1]
       2 [-]: CALL R1 1 1  ; var1()
       3 [-]: RETURN R0 0  ; 


; Name:            
; Defined at line: 207
; #Upvalues:       0
; #Parameters:     0
; Is_vararg:       0
; Max Stack Size:  7

       0 [-]: GETIMPORT R0 1; var0 = 0x89326C93
       1 [-]: GETIMPORT R2 3; var2 = 0x0469F296
       2 [-]: LOADK R3 K4  ; var3 = "LessonScreen"
       3 [-]: CALL R2 2 0  ; var2, ... = var2(var3)
       4 [-]: NAMECALL R0 R0 K5; var1 = var0; var0 = var0[0x46A0EBF5]
       5 [-]: CALL R0 0 2  ; var0 = var0(var1, ...)
       6 [-]: FASTCALL1 62 R0 L0; 
       7 [-]: MOVE R2 R0   ; var2 = var0
       8 [-]: GETIMPORT R1 7; var1 = 0x7B998233
       9 [-]: CALL R1 2 2  ; var1 = var1(var2)
L 0:  10 [-]: JUMPIF R1 L1 ; goto L1 if var1
      11 [-]: GETIMPORT R1 9; var1 = _T
      12 [-]: DUPTABLE R2 15; 
      13 [-]: GETIMPORT R3 17; var3 = 0xAC9CE333
      14 [-]: SETTABLEKS R3 R2 K10; var3["NoInput"] = var2
      15 [-]: SETTABLEKS R0 R2 K11; var0["AttachEntity"] = var2
      16 [-]: GETIMPORT R3 19; var3 = 0xA421AF95
      17 [-]: LOADN R4 0   ; var4 = 0
      18 [-]: LOADK R5 K20 ; var5 = 1.8
      19 [-]: LOADK R6 K21 ; var6 = -0.5
      20 [-]: CALL R3 4 2  ; var3 = var3(var4, var5, var6)
      21 [-]: SETTABLEKS R3 R2 K12; var3["Offset"] = var2
      22 [-]: GETIMPORT R3 23; var3 = 0x00046924
      23 [-]: LOADN R4 -90 ; var4 = -90
      24 [-]: LOADN R5 0   ; var5 = 0
      25 [-]: LOADN R6 0   ; var6 = 0
      26 [-]: CALL R3 4 2  ; var3 = var3(var4, var5, var6)
      27 [-]: SETTABLEKS R3 R2 K13; var3["Rotation"] = var2
      28 [-]: GETIMPORT R3 19; var3 = 0xA421AF95
      29 [-]: LOADK R4 K24 ; var4 = 1.5
      30 [-]: LOADK R5 K24 ; var5 = 1.5
      31 [-]: LOADK R6 K24 ; var6 = 1.5
      32 [-]: CALL R3 4 2  ; var3 = var3(var4, var5, var6)
      33 [-]: SETTABLEKS R3 R2 K14; var3["Scale"] = var2
      34 [-]: SETTABLEKS R2 R1 K25; var2["NewWarLesson_AttachInfo"] = var1
L 1:  35 [-]: GETIMPORT R1 27; var1 = 0x9BA7909F
      36 [-]: GETIMPORT R3 29; var3 = 0x7ED0A956
      37 [-]: LOADK R4 K30 ; var4 = "/Lotus/Interface/NewWarClassDisplay.swf"
      38 [-]: CALL R3 2 0  ; var3, ... = var3(var4)
      39 [-]: NAMECALL R1 R1 K31; var2 = var1; var1 = var1[0xCFBA257F]
      40 [-]: CALL R1 0 1  ; var1(var2, ...)
      41 [-]: RETURN R0 0  ; 


; Name:            
; Defined at line: 223
; #Upvalues:       1
; #Parameters:     2
; Is_vararg:       0
; Max Stack Size:  10

       0 [-]: LOADK R3 K0  ; var3 = "/Lotus/Language/NewWar/Slide"
       1 [-]: GETIMPORT R7 2; var7 = 0x64FB1586
       2 [-]: GETUPVAL R8 0; var8 = upvalues[0]
       3 [-]: CALL R7 2 2  ; var7 = var7(var8)
       4 [-]: MOVE R4 R7   ; var4 = var7
       5 [-]: LOADK R5 K3  ; var5 = "Heading"
       6 [-]: MOVE R6 R1   ; var6 = var1
       7 [-]: CONCAT R2 R3 R6; var2 = var3 .. var6
       8 [-]: GETIMPORT R3 5; var3 = 0xAE91E43B
       9 [-]: MOVE R6 R0   ; var6 = var0
      10 [-]: LOADK R7 K6  ; var7 = ".Heading"
      11 [-]: MOVE R8 R1   ; var8 = var1
      12 [-]: LOADK R9 K7  ; var9 = ".Text.text"
      13 [-]: CONCAT R5 R6 R9; var5 = var6 .. var9
      14 [-]: MOVE R6 R2   ; var6 = var2
      15 [-]: NAMECALL R3 R3 K8; var4 = var3; var3 = var3[0x20B98DB3]
      16 [-]: CALL R3 4 1  ; var3(var4, var5, var6)
      17 [-]: GETIMPORT R3 5; var3 = 0xAE91E43B
      18 [-]: MOVE R6 R0   ; var6 = var0
      19 [-]: LOADK R7 K6  ; var7 = ".Heading"
      20 [-]: MOVE R8 R1   ; var8 = var1
      21 [-]: LOADK R9 K9  ; var9 = "DropShadow.Text.text"
      22 [-]: CONCAT R5 R6 R9; var5 = var6 .. var9
      23 [-]: MOVE R6 R2   ; var6 = var2
      24 [-]: NAMECALL R3 R3 K8; var4 = var3; var3 = var3[0x20B98DB3]
      25 [-]: CALL R3 4 1  ; var3(var4, var5, var6)
      26 [-]: RETURN R0 0  ; 


; Name:            
; Defined at line: 230
; #Upvalues:       1
; #Parameters:     2
; Is_vararg:       0
; Max Stack Size:  7

       0 [-]: GETIMPORT R2 2; var2 = 0x7F5022CF[0xA5C556B9]
       1 [-]: MOVE R3 R1   ; var3 = var1
       2 [-]: LOADK R4 K3  ; var4 = "Heading"
       3 [-]: CALL R2 3 2  ; var2 = var2(var3, var4)
       4 [-]: JUMPXEQKNIL R2 L0; 
       5 [-]: GETTABLEKS R3 R1 K4; var3 = var1["sub"]
       6 [-]: MOVE R4 R1   ; var4 = var1
       7 [-]: ADDK R5 R2 K5; var5 = var2 + 7
       8 [-]: CALL R3 3 2  ; var3 = var3(var4, var5)
       9 [-]: GETUPVAL R4 0; var4 = upvalues[0]
      10 [-]: MOVE R5 R0   ; var5 = var0
      11 [-]: MOVE R6 R3   ; var6 = var3
      12 [-]: CALL R4 3 1  ; var4(var5, var6)
      13 [-]: RETURN R0 0  ; 
L 0:  14 [-]: JUMPXEQKS R0 K6 L1 NOT; 
      15 [-]: JUMPXEQKS R1 K7 L1 NOT; 
      16 [-]: GETUPVAL R3 0; var3 = upvalues[0]
      17 [-]: MOVE R4 R0   ; var4 = var0
      18 [-]: LOADK R5 K8  ; var5 = "1"
      19 [-]: CALL R3 3 1  ; var3(var4, var5)
      20 [-]: GETUPVAL R3 0; var3 = upvalues[0]
      21 [-]: MOVE R4 R0   ; var4 = var0
      22 [-]: LOADK R5 K9  ; var5 = "2"
      23 [-]: CALL R3 3 1  ; var3(var4, var5)
      24 [-]: RETURN R0 0  ; 
L 1:  25 [-]: JUMPXEQKS R0 K10 L2 NOT; 
      26 [-]: JUMPXEQKS R1 K11 L2 NOT; 
      27 [-]: GETIMPORT R3 13; var3 = 0xAE91E43B
      28 [-]: LOADK R5 K14 ; var5 = "Slide2.Nebula"
      29 [-]: GETIMPORT R6 16; var6 = 0x88F8AC38
      30 [-]: NAMECALL R3 R3 K17; var4 = var3; var3 = var3[0xD5181643]
      31 [-]: CALL R3 4 1  ; var3(var4, var5, var6)
      32 [-]: RETURN R0 0  ; 
L 2:  33 [-]: JUMPXEQKS R0 K18 L3 NOT; 
      34 [-]: JUMPXEQKS R1 K19 L3 NOT; 
      35 [-]: GETIMPORT R3 13; var3 = 0xAE91E43B
      36 [-]: LOADK R5 K20 ; var5 = "Slide7.Rays"
      37 [-]: GETIMPORT R6 22; var6 = 0x2EBF6549
      38 [-]: NAMECALL R3 R3 K17; var4 = var3; var3 = var3[0xD5181643]
      39 [-]: CALL R3 4 1  ; var3(var4, var5, var6)
      40 [-]: GETUPVAL R3 0; var3 = upvalues[0]
      41 [-]: MOVE R4 R0   ; var4 = var0
      42 [-]: LOADK R5 K8  ; var5 = "1"
      43 [-]: CALL R3 3 1  ; var3(var4, var5)
      44 [-]: RETURN R0 0  ; 
L 3:  45 [-]: JUMPXEQKS R0 K23 L4 NOT; 
      46 [-]: JUMPXEQKS R1 K11 L4 NOT; 
      47 [-]: GETIMPORT R3 13; var3 = 0xAE91E43B
      48 [-]: LOADK R5 K24 ; var5 = "Slide8.Nebula"
      49 [-]: GETIMPORT R6 16; var6 = 0x88F8AC38
      50 [-]: NAMECALL R3 R3 K17; var4 = var3; var3 = var3[0xD5181643]
      51 [-]: CALL R3 4 1  ; var3(var4, var5, var6)
L 4:  52 [-]: RETURN R0 0  ; 


; Name:            
; Defined at line: 248
; #Upvalues:       6
; #Parameters:     0
; Is_vararg:       0
; Max Stack Size:  3

       0 [-]: GETUPVAL R1 0; var1 = upvalues[0]
       1 [-]: GETTABLEKS R0 R1 K0; var0 = var1["WaitingOnTrans"]
       2 [-]: JUMPXEQKN R0 K1 L0; 
       3 [-]: RETURN R0 0  ; 
L 0:   4 [-]: GETUPVAL R1 1; var1 = upvalues[1]
       5 [-]: GETTABLEKS R0 R1 K2; var0 = var1[0x659D451F]
       6 [-]: GETIMPORT R1 4; var1 = 0xB5CB553B
       7 [-]: CALL R0 2 1  ; var0(var1)
       8 [-]: GETUPVAL R0 2; var0 = upvalues[2]
       9 [-]: GETUPVAL R2 3; var2 = upvalues[3]
      10 [-]: LENGTH R1 R2 ; var1 = #var2
      11 [-]: JUMPIFNOTLT R0 R1 L1; goto L1 if var0 >= var262151
      12 [-]: GETUPVAL R0 4; var0 = upvalues[4]
      13 [-]: CALL R0 1 1  ; var0()
      14 [-]: RETURN R0 0  ; 
L 1:  15 [-]: GETUPVAL R0 5; var0 = upvalues[5]
      16 [-]: CALL R0 1 1  ; var0()
      17 [-]: RETURN R0 0  ; 


; Name:            
; Defined at line: 262
; #Upvalues:       1
; #Parameters:     0
; Is_vararg:       0
; Max Stack Size:  1

       0 [-]: GETUPVAL R0 0; var0 = upvalues[0]
       1 [-]: CALL R0 1 1  ; var0()
       2 [-]: RETURN R0 0  ; 


; Name:            
; Defined at line: 266
; #Upvalues:       1
; #Parameters:     0
; Is_vararg:       0
; Max Stack Size:  1

       0 [-]: GETIMPORT R0 2; var0 = 0x34291F5C[0xE6B41ADB]
       1 [-]: CALL R0 1 2  ; var0 = var0()
       2 [-]: JUMPIFNOT R0 L0; goto L0 if not var0
       3 [-]: GETUPVAL R0 0; var0 = upvalues[0]
       4 [-]: CALL R0 1 1  ; var0()
L 0:   5 [-]: RETURN R0 0  ; 


; Name:            
; Defined at line: 272
; #Upvalues:       0
; #Parameters:     0
; Is_vararg:       0
; Max Stack Size:  0

       0 [-]: RETURN R0 0  ; 


; Name:            
; Defined at line: 278
; #Upvalues:       1
; #Parameters:     1
; Is_vararg:       0
; Max Stack Size:  2

       0 [-]: GETUPVAL R1 0; var1 = upvalues[0]
       1 [-]: CALL R1 1 1  ; var1()
       2 [-]: RETURN R0 0  ; 


; Name:            
; Defined at line: 282
; #Upvalues:       1
; #Parameters:     3
; Is_vararg:       0
; Max Stack Size:  6

       0 [-]: GETIMPORT R3 2; var3 = 0x7F5022CF[0xA5C556B9]
       1 [-]: MOVE R4 R1   ; var4 = var1
       2 [-]: LOADK R5 K3  ; var5 = "_SPACE"
       3 [-]: CALL R3 3 2  ; var3 = var3(var4, var5)
       4 [-]: JUMPXEQKNIL R3 L0; 
       5 [-]: JUMPIFNOT R2 L0; goto L0 if not var2
       6 [-]: GETUPVAL R3 0; var3 = upvalues[0]
       7 [-]: CALL R3 1 1  ; var3()
       8 [-]: LOADN R3 1   ; var3 = 1
       9 [-]: RETURN R3 1  ; 
L 0:  10 [-]: LOADNIL R3   ; var3 = nil
      11 [-]: RETURN R3 1  ; 



