; Name:            
; Defined at line: 1
; #Upvalues:       0
; #Parameters:     0
; Is_vararg:       1
; Max Stack Size:  33

            1 [-]: GETIMPORT R0 1 [nil]
       2 [-]: LOADK R1 K2 ["EE.Interface.Utilities"]
       3 [-]: CALL R0 1 1  
       4 [-]: GETIMPORT R1 1 [nil]
       5 [-]: LOADK R2 K3 ["Lotus.Interface.LotusUtilities"]
       6 [-]: CALL R1 1 1  
       7 [-]: GETIMPORT R2 1 [nil]
       8 [-]: LOADK R3 K4 ["Lotus.Interface.CardUtilitiesRedux"]
       9 [-]: CALL R2 1 1  
      10 [-]: GETIMPORT R3 1 [nil]
      11 [-]: LOADK R4 K5 ["Lotus.Interface.LoadoutUtilities"]
      12 [-]: CALL R3 1 1  
      13 [-]: LOADNIL R4   
      14 [-]: LOADB R5 1   
      15 [-]: LOADN R6 5   
      16 [-]: LOADN R7 2   
      17 [-]: LOADN R8 9   
      18 [-]: LOADN R9 0   
      19 [-]: LOADNIL R10  
      20 [-]: LOADNIL R11  
      21 [-]: LOADNIL R12  
      22 [-]: LOADB R13 0  
      23 [-]: LOADK R14 K6 ["nil"]
      24 [-]: LOADNIL R15  
      25 [-]: LOADNIL R16  
      26 [-]: LOADB R17 0  
      27 [-]: LOADNIL R18  
      28 [-]: LOADB R19 0  
      29 [-]: LOADNIL R20  
      30 [-]: GETIMPORT R21 8 [nil]
      31 [-]: LOADK R22 K9 ["/Lotus/Types/Items/MiscItems/FormaOmega"]
      32 [-]: CALL R21 1 1 
      33 [-]: GETIMPORT R22 8 [nil]
      34 [-]: LOADK R23 K10 ["/Lotus/Types/Items/MiscItems/FormaUmbra"]
      35 [-]: CALL R22 1 1 
      36 [-]: GETIMPORT R23 8 [nil]
      37 [-]: LOADK R24 K11 ["/Lotus/Powersuits/Khora/Kavat/KhoraKavatPowerSuit"]
      38 [-]: CALL R23 1 1 
      39 [-]: LOADB R24 0  
      40 [-]: NEWCLOSURE R25 P0
      41 [-]: MOVE R1 R5   
      42 [-]: SETGLOBAL R25 K12 ["IsInputBlocked"]
      43 [-]: DUPCLOSURE R25 K13 []
      44 [-]: SETGLOBAL R25 K14 ["GetCards"]
      45 [-]: DUPCLOSURE R25 K15 []
      46 [-]: SETGLOBAL R25 K16 ["GetSelectedCards"]
      47 [-]: DUPCLOSURE R25 K17 []
      48 [-]: SETGLOBAL R25 K18 ["GetSelectedElement"]
      49 [-]: DUPCLOSURE R25 K19 []
      50 [-]: SETGLOBAL R25 K20 ["IsFusionMode"]
      51 [-]: NEWCLOSURE R25 P5
      52 [-]: MOVE R1 R5   
      53 [-]: MOVE R1 R4   
      54 [-]: SETGLOBAL R25 K21 ["Pressed"]
      55 [-]: NEWCLOSURE R25 P6
      56 [-]: MOVE R1 R5   
      57 [-]: MOVE R1 R4   
      58 [-]: SETGLOBAL R25 K22 ["Selected"]
      59 [-]: NEWCLOSURE R25 P7
      60 [-]: MOVE R1 R5   
      61 [-]: MOVE R1 R4   
      62 [-]: SETGLOBAL R25 K23 ["Focused"]
      63 [-]: NEWCLOSURE R25 P8
      64 [-]: MOVE R1 R5   
      65 [-]: MOVE R1 R4   
      66 [-]: SETGLOBAL R25 K24 ["Unfocused"]
      67 [-]: DUPCLOSURE R25 K25 []
      68 [-]: NEWCLOSURE R26 P10
      69 [-]: MOVE R0 R3   
      70 [-]: MOVE R1 R12  
      71 [-]: NEWCLOSURE R27 P11
      72 [-]: MOVE R0 R3   
      73 [-]: MOVE R1 R12  
      74 [-]: NEWCLOSURE R28 P12
      75 [-]: MOVE R0 R25  
      76 [-]: MOVE R1 R8   
      77 [-]: MOVE R0 R26  
      78 [-]: MOVE R0 R3   
      79 [-]: MOVE R1 R12  
      80 [-]: MOVE R0 R27  
      81 [-]: MOVE R0 R0   
      82 [-]: NEWCLOSURE R29 P13
      83 [-]: MOVE R1 R4   
      84 [-]: MOVE R1 R7   
      85 [-]: MOVE R1 R6   
      86 [-]: MOVE R0 R3   
      87 [-]: MOVE R1 R9   
      88 [-]: MOVE R0 R26  
      89 [-]: MOVE R1 R24  
      90 [-]: MOVE R1 R12  
      91 [-]: MOVE R1 R5   
      92 [-]: MOVE R0 R2   
      93 [-]: MOVE R1 R17  
      94 [-]: MOVE R0 R28  
      95 [-]: MOVE R0 R0   
      96 [-]: MOVE R1 R10  
      97 [-]: MOVE R1 R15  
      98 [-]: MOVE R1 R16  
      99 [-]: MOVE R1 R19  
     100 [-]: MOVE R1 R20  
     101 [-]: MOVE R0 R22  
     102 [-]: MOVE R0 R27  
     103 [-]: MOVE R0 R23  
     104 [-]: MOVE R0 R1   
     105 [-]: NEWCLOSURE R30 P14
     106 [-]: MOVE R0 R29  
     107 [-]: MOVE R1 R4   
     108 [-]: MOVE R0 R25  
     109 [-]: MOVE R1 R9   
     110 [-]: MOVE R1 R11  
     111 [-]: MOVE R1 R5   
     112 [-]: NEWCLOSURE R31 P15
     113 [-]: MOVE R0 R0   
     114 [-]: MOVE R1 R10  
     115 [-]: MOVE R1 R18  
     116 [-]: MOVE R0 R25  
     117 [-]: MOVE R1 R8   
     118 [-]: MOVE R1 R12  
     119 [-]: MOVE R1 R11  
     120 [-]: MOVE R0 R26  
     121 [-]: MOVE R0 R27  
     122 [-]: MOVE R1 R9   
     123 [-]: MOVE R1 R20  
     124 [-]: MOVE R0 R21  
     125 [-]: MOVE R0 R30  
     126 [-]: SETGLOBAL R31 K26 ["Initialize"]
     127 [-]: NEWCLOSURE R31 P16
     128 [-]: MOVE R1 R13  
     129 [-]: MOVE R1 R10  
     130 [-]: MOVE R1 R18  
     131 [-]: SETGLOBAL R31 K27 ["Update"]
     132 [-]: NEWCLOSURE R31 P17
     133 [-]: MOVE R1 R5   
     134 [-]: MOVE R1 R13  
     135 [-]: DUPCLOSURE R32 K28 []
     136 [-]: MOVE R0 R31  
     137 [-]: SETGLOBAL R32 K29 ["TransitionOut"]
     138 [-]: NEWCLOSURE R32 P19
     139 [-]: MOVE R1 R14  
     140 [-]: MOVE R0 R0   
     141 [-]: MOVE R0 R31  
     142 [-]: SETGLOBAL R32 K30 ["Cancel"]
     143 [-]: NEWCLOSURE R32 P20
     144 [-]: MOVE R1 R19  
     145 [-]: MOVE R0 R0   
     146 [-]: MOVE R1 R10  
     147 [-]: MOVE R0 R25  
     148 [-]: MOVE R1 R11  
     149 [-]: MOVE R1 R4   
     150 [-]: MOVE R1 R14  
     151 [-]: MOVE R0 R31  
     152 [-]: SETGLOBAL R32 K31 ["ApplyChanges"]
     153 [-]: NEWCLOSURE R32 P21
     154 [-]: MOVE R1 R14  
     155 [-]: SETGLOBAL R32 K32 ["SetCallback"]
     156 [-]: NEWCLOSURE R32 P22
     157 [-]: MOVE R1 R5   
     158 [-]: MOVE R1 R4   
     159 [-]: SETGLOBAL R32 K33 ["onKeyUp_MENU_SELECT"]
     160 [-]: NEWCLOSURE R32 P23
     161 [-]: MOVE R1 R17  
     162 [-]: SETGLOBAL R32 K34 ["SetSwapMode"]
     163 [-]: DUPCLOSURE R32 K35 []
     164 [-]: SETGLOBAL R32 K36 ["SetDescOverride"]
     165 [-]: NEWCLOSURE R32 P25
     166 [-]: MOVE R1 R24  
     167 [-]: SETGLOBAL R32 K37 ["SetiOSMode"]
     168 [-]: CLOSEUPVALS R4
     169 [-]: RETURN R0 0  


; Name:            
; Defined at line: 35
; #Upvalues:       1
; #Parameters:     0
; Is_vararg:       0
; Max Stack Size:  1

       0 [-]: GETUPVAL R0 0
       1 [-]: RETURN R0 1  


; Name:            
; Defined at line: 39
; #Upvalues:       0
; #Parameters:     0
; Is_vararg:       0
; Max Stack Size:  1

       0 [-]: LOADNIL R0   
       1 [-]: RETURN R0 1  


; Name:            
; Defined at line: 43
; #Upvalues:       0
; #Parameters:     0
; Is_vararg:       0
; Max Stack Size:  1

       0 [-]: NEWTABLE R0 0 0
       1 [-]: RETURN R0 1  


; Name:            
; Defined at line: 48
; #Upvalues:       0
; #Parameters:     0
; Is_vararg:       0
; Max Stack Size:  1

       0 [-]: LOADNIL R0   
       1 [-]: RETURN R0 1  


; Name:            
; Defined at line: 52
; #Upvalues:       0
; #Parameters:     0
; Is_vararg:       0
; Max Stack Size:  1

       0 [-]: LOADB R0 0   
       1 [-]: RETURN R0 1  


; Name:            
; Defined at line: 57
; #Upvalues:       2
; #Parameters:     1
; Is_vararg:       0
; Max Stack Size:  5

       0 [-]: GETUPVAL R1 0
       1 [-]: JUMPXEQKB R1 0 L0 NOT
       2 [-]: GETUPVAL R1 1
       3 [-]: GETIMPORT R3 1 [nil]
       4 [-]: MOVE R4 R0   
       5 [-]: CALL R3 1 -1 
       6 [-]: NAMECALL R1 R1 K2 [0xAF5319DC]
       7 [-]: CALL R1 -1 0 
L 0:   8 [-]: RETURN R0 0  


; Name:            
; Defined at line: 63
; #Upvalues:       2
; #Parameters:     1
; Is_vararg:       0
; Max Stack Size:  5

       0 [-]: GETUPVAL R1 0
       1 [-]: JUMPXEQKB R1 0 L0 NOT
       2 [-]: GETUPVAL R1 1
       3 [-]: GETIMPORT R3 1 [nil]
       4 [-]: MOVE R4 R0   
       5 [-]: CALL R3 1 -1 
       6 [-]: NAMECALL R1 R1 K2 [0x070DAA5A]
       7 [-]: CALL R1 -1 0 
L 0:   8 [-]: RETURN R0 0  


; Name:            
; Defined at line: 69
; #Upvalues:       2
; #Parameters:     1
; Is_vararg:       0
; Max Stack Size:  5

       0 [-]: GETUPVAL R1 0
       1 [-]: JUMPXEQKB R1 0 L0 NOT
       2 [-]: GETUPVAL R1 1
       3 [-]: GETIMPORT R3 1 [nil]
       4 [-]: MOVE R4 R0   
       5 [-]: CALL R3 1 -1 
       6 [-]: NAMECALL R1 R1 K2 [0xDF42446E]
       7 [-]: CALL R1 -1 0 
L 0:   8 [-]: RETURN R0 0  


; Name:            
; Defined at line: 75
; #Upvalues:       2
; #Parameters:     1
; Is_vararg:       0
; Max Stack Size:  5

       0 [-]: GETUPVAL R1 0
       1 [-]: JUMPXEQKB R1 0 L0 NOT
       2 [-]: GETUPVAL R1 1
       3 [-]: GETIMPORT R3 1 [nil]
       4 [-]: MOVE R4 R0   
       5 [-]: CALL R3 1 -1 
       6 [-]: NAMECALL R1 R1 K2 [0xBCE5A201]
       7 [-]: CALL R1 -1 0 
L 0:   8 [-]: RETURN R0 0  


; Name:            
; Defined at line: 81
; #Upvalues:       0
; #Parameters:     0
; Is_vararg:       0
; Max Stack Size:  3

       0 [-]: GETIMPORT R1 2 [nil]
       1 [-]: LOADN R2 49  
       2 [-]: JUMPIFEQ R1 R2 L0
       3 [-]: LOADB R0 0 +1
L 0:   4 [-]: LOADB R0 1   
L 1:   5 [-]: RETURN R0 1  


; Name:            
; Defined at line: 85
; #Upvalues:       2
; #Parameters:     0
; Is_vararg:       0
; Max Stack Size:  3

       0 [-]: GETUPVAL R1 0
       1 [-]: GETTABLEKS R0 R1 K0 [0x28A3740B]
       2 [-]: GETIMPORT R1 3 [nil]
       3 [-]: GETUPVAL R2 1
       4 [-]: CALL R0 2 -1 
       5 [-]: RETURN R0 -1 


; Name:            
; Defined at line: 89
; #Upvalues:       2
; #Parameters:     0
; Is_vararg:       0
; Max Stack Size:  3

       0 [-]: GETUPVAL R1 0
       1 [-]: GETTABLEKS R0 R1 K0 [0x1B42E1C8]
       2 [-]: GETIMPORT R1 3 [nil]
       3 [-]: GETUPVAL R2 1
       4 [-]: CALL R0 2 -1 
       5 [-]: RETURN R0 -1 


; Name:            
; Defined at line: 93
; #Upvalues:       7
; #Parameters:     2
; Is_vararg:       0
; Max Stack Size:  7

       0 [-]: LOADNIL R2   
       1 [-]: GETUPVAL R3 0
       2 [-]: CALL R3 0 1  
       3 [-]: JUMPIFNOT R3 L0
       4 [-]: GETTABLEKS R3 R0 K0 ["mSlotIndex"]
       5 [-]: GETUPVAL R4 1
       6 [-]: JUMPIFNOTEQ R3 R4 L0
       7 [-]: LOADK R2 K1 ["/Lotus/Language/Menu/Loadout_AuraSlotSwapWarning"]
       8 [-]: JUMP L6
     
L 0:   9 [-]: GETIMPORT R3 4 [nil]
      10 [-]: LOADN R4 0   
      11 [-]: JUMPIFEQ R3 R4 L1
      12 [-]: GETIMPORT R3 4 [nil]
      13 [-]: LOADN R4 3   
      14 [-]: JUMPIFNOTEQ R3 R4 L6
L 1:  15 [-]: GETIMPORT R3 6 [nil]
      16 [-]: LOADN R4 0   
      17 [-]: JUMPIFEQ R3 R4 L2
      18 [-]: GETUPVAL R3 2
      19 [-]: CALL R3 0 1  
      20 [-]: JUMPIFNOT R3 L3
L 2:  21 [-]: GETTABLEKS R3 R0 K0 ["mSlotIndex"]
      22 [-]: GETUPVAL R4 1
      23 [-]: JUMPIFNOTEQ R3 R4 L3
      24 [-]: LOADK R2 K1 ["/Lotus/Language/Menu/Loadout_AuraSlotSwapWarning"]
      25 [-]: JUMP L6
     
L 3:  26 [-]: GETUPVAL R4 3
      27 [-]: GETTABLEKS R3 R4 K7 [0xBA7A0A82]
      28 [-]: GETUPVAL R6 4
      29 [-]: GETTABLEKS R5 R6 K8 ["info"]
      30 [-]: GETTABLEKS R4 R5 K9 ["mItemType"]
      31 [-]: GETTABLEKS R5 R0 K0 ["mSlotIndex"]
      32 [-]: CALL R3 2 1  
      33 [-]: JUMPIFNOT R3 L4
      34 [-]: LOADK R2 K10 ["/Lotus/Language/Menu/Loadout_UtilitySlotSwapWarning"]
      35 [-]: JUMP L6
     
L 4:  36 [-]: GETIMPORT R3 6 [nil]
      37 [-]: LOADN R4 3   
      38 [-]: JUMPIFEQ R3 R4 L5
      39 [-]: GETUPVAL R3 5
      40 [-]: CALL R3 0 1  
      41 [-]: JUMPIFNOT R3 L6
L 5:  42 [-]: GETTABLEKS R3 R0 K0 ["mSlotIndex"]
      43 [-]: GETUPVAL R4 1
      44 [-]: JUMPIFNOTEQ R3 R4 L6
      45 [-]: LOADK R2 K11 ["/Lotus/Language/Menu/Loadout_StanceSlotSwapWarning"]
L 6:  46 [-]: JUMPXEQKNIL R2 L8
      47 [-]: JUMPIF R1 L7 
      48 [-]: GETUPVAL R4 6
      49 [-]: GETTABLEKS R3 R4 K12 [0x659D451F]
      50 [-]: GETIMPORT R5 14 [nil]
      51 [-]: GETTABLEKS R4 R5 K15 ["UISound_Error"]
      52 [-]: CALL R3 1 0  
      53 [-]: GETUPVAL R4 6
      54 [-]: GETTABLEKS R3 R4 K16 [0xE0CBA3CA]
      55 [-]: MOVE R4 R2   
      56 [-]: CALL R3 1 0  
L 7:  57 [-]: LOADB R3 1   
      58 [-]: RETURN R3 1  
L 8:  59 [-]: LOADB R3 0   
      60 [-]: RETURN R3 1  


; Name:            
; Defined at line: 119
; #Upvalues:       22
; #Parameters:     0
; Is_vararg:       0
; Max Stack Size:  12

       0 [-]: GETIMPORT R0 1 [nil]
       1 [-]: LOADK R1 K2 ["EE.Interface.Components.Grid"]
       2 [-]: CALL R0 1 1  
       3 [-]: GETUPVAL R1 0
       4 [-]: JUMPXEQKNIL R1 L0
       5 [-]: GETUPVAL R1 0
       6 [-]: NAMECALL R1 R1 K3 [0x6F56E33A]
       7 [-]: CALL R1 1 0  
L 0:   8 [-]: GETUPVAL R2 3
       9 [-]: GETTABLEKS R1 R2 K4 [0xEDDFDFAA]
      10 [-]: GETIMPORT R2 7 [nil]
      11 [-]: GETIMPORT R3 10 [nil]
      12 [-]: GETIMPORT R4 12 [nil]
      13 [-]: CALL R1 3 2  
      14 [-]: SETUPVAL R1 1
      15 [-]: SETUPVAL R2 2
      16 [-]: LOADN R1 406 
      17 [-]: GETUPVAL R2 4
      18 [-]: LOADN R3 10  
      19 [-]: JUMPIFNOTLE R3 R2 L1
      20 [-]: GETIMPORT R2 7 [nil]
      21 [-]: LOADN R3 3   
      22 [-]: JUMPIFEQ R2 R3 L1
      23 [-]: GETUPVAL R2 5
      24 [-]: CALL R2 0 1  
      25 [-]: JUMPIF R2 L1 
      26 [-]: LOADN R1 542 
L 1:  27 [-]: LOADN R2 350 
      28 [-]: GETUPVAL R3 4
      29 [-]: JUMPXEQKN R3 K13 L2 [11]
      30 [-]: GETUPVAL R3 4
      31 [-]: JUMPXEQKN R3 K14 L2 [9]
      32 [-]: GETIMPORT R3 7 [nil]
      33 [-]: LOADN R4 3   
      34 [-]: JUMPIFEQ R3 R4 L2
      35 [-]: GETUPVAL R3 5
      36 [-]: CALL R3 0 1  
      37 [-]: JUMPIFNOT R3 L3
L 2:  38 [-]: LOADN R2 400 
L 3:  39 [-]: GETUPVAL R3 6
      40 [-]: JUMPIFNOT R3 L4
      41 [-]: GETIMPORT R3 16 [nil]
      42 [-]: LOADK R5 K17 ["Installed"]
      43 [-]: LOADN R6 5   
      44 [-]: LOADN R7 110 
      45 [-]: NAMECALL R3 R3 K18 [0x67BC869F]
      46 [-]: CALL R3 4 0  
      47 [-]: GETIMPORT R3 16 [nil]
      48 [-]: LOADK R5 K17 ["Installed"]
      49 [-]: LOADN R6 6   
      50 [-]: LOADN R7 110 
      51 [-]: NAMECALL R3 R3 K18 [0x67BC869F]
      52 [-]: CALL R3 4 0  
      53 [-]: GETIMPORT R3 16 [nil]
      54 [-]: LOADK R5 K19 ["Installed.Title"]
      55 [-]: LOADN R6 5   
      56 [-]: LOADN R7 160 
      57 [-]: NAMECALL R3 R3 K18 [0x67BC869F]
      58 [-]: CALL R3 4 0  
      59 [-]: GETIMPORT R3 16 [nil]
      60 [-]: LOADK R5 K19 ["Installed.Title"]
      61 [-]: LOADN R6 6   
      62 [-]: LOADN R7 160 
      63 [-]: NAMECALL R3 R3 K18 [0x67BC869F]
      64 [-]: CALL R3 4 0  
      65 [-]: GETIMPORT R3 16 [nil]
      66 [-]: LOADK R5 K19 ["Installed.Title"]
      67 [-]: LOADN R6 0   
      68 [-]: GETIMPORT R8 16 [nil]
      69 [-]: LOADK R10 K19 ["Installed.Title"]
      70 [-]: LOADN R11 0  
      71 [-]: NAMECALL R8 R8 K21 [0x91A24E4B]
      72 [-]: CALL R8 3 1  
      73 [-]: SUBK R7 R8 K20 [100]
      74 [-]: NAMECALL R3 R3 K18 [0x67BC869F]
      75 [-]: CALL R3 4 0  
      76 [-]: GETIMPORT R3 16 [nil]
      77 [-]: LOADK R5 K19 ["Installed.Title"]
      78 [-]: LOADN R6 1   
      79 [-]: LOADN R7 -40 
      80 [-]: NAMECALL R3 R3 K18 [0x67BC869F]
      81 [-]: CALL R3 4 0  
      82 [-]: GETIMPORT R3 16 [nil]
      83 [-]: LOADK R5 K22 ["Description"]
      84 [-]: LOADN R6 0   
      85 [-]: GETIMPORT R8 16 [nil]
      86 [-]: LOADK R10 K22 ["Description"]
      87 [-]: LOADN R11 0  
      88 [-]: NAMECALL R8 R8 K21 [0x91A24E4B]
      89 [-]: CALL R8 3 1  
      90 [-]: SUBK R7 R8 K23 [440]
      91 [-]: NAMECALL R3 R3 K18 [0x67BC869F]
      92 [-]: CALL R3 4 0  
      93 [-]: GETIMPORT R3 16 [nil]
      94 [-]: LOADK R5 K22 ["Description"]
      95 [-]: LOADN R6 1   
      96 [-]: GETIMPORT R7 16 [nil]
      97 [-]: LOADK R9 K22 ["Description"]
      98 [-]: LOADN R10 1  
      99 [-]: NAMECALL R7 R7 K21 [0x91A24E4B]
     100 [-]: CALL R7 3 -1 
     101 [-]: NAMECALL R3 R3 K18 [0x67BC869F]
     102 [-]: CALL R3 -1 0 
     103 [-]: GETIMPORT R3 16 [nil]
     104 [-]: LOADK R5 K22 ["Description"]
     105 [-]: LOADN R6 12  
     106 [-]: LOADN R7 1000
     107 [-]: NAMECALL R3 R3 K18 [0x67BC869F]
     108 [-]: CALL R3 4 0  
     109 [-]: GETIMPORT R3 16 [nil]
     110 [-]: LOADK R5 K22 ["Description"]
     111 [-]: LOADN R6 6   
     112 [-]: LOADN R7 150 
     113 [-]: NAMECALL R3 R3 K18 [0x67BC869F]
     114 [-]: CALL R3 4 0  
     115 [-]: GETIMPORT R3 16 [nil]
     116 [-]: LOADK R5 K22 ["Description"]
     117 [-]: LOADN R6 5   
     118 [-]: LOADN R7 150 
     119 [-]: NAMECALL R3 R3 K18 [0x67BC869F]
     120 [-]: CALL R3 4 0  
L 4: 121 [-]: GETTABLEKS R3 R0 K24 [0xDA0C93A2]
     122 [-]: GETIMPORT R4 16 [nil]
     123 [-]: LOADK R5 K25 ["Installed.Card1"]
     124 [-]: LOADNIL R6   
     125 [-]: GETUPVAL R7 2
     126 [-]: GETUPVAL R8 1
     127 [-]: CALL R3 5 1  
     128 [-]: SETUPVAL R3 0
     129 [-]: GETUPVAL R3 0
     130 [-]: SETTABLEKS R1 R3 K26 ["mInitialX"]
     131 [-]: GETUPVAL R3 0
     132 [-]: SETTABLEKS R2 R3 K27 ["mInitialY"]
     133 [-]: GETUPVAL R4 3
     134 [-]: GETTABLEKS R3 R4 K28 [0x5D93CF60]
     135 [-]: GETUPVAL R4 0
     136 [-]: GETIMPORT R5 7 [nil]
     137 [-]: GETIMPORT R6 30 [nil]
     138 [-]: GETUPVAL R7 7
     139 [-]: LOADB R8 0   
     140 [-]: CALL R3 5 0  
     141 [-]: GETUPVAL R4 3
     142 [-]: GETTABLEKS R3 R4 K31 [0x9CEBE2A3]
     143 [-]: GETUPVAL R4 0
     144 [-]: GETIMPORT R5 7 [nil]
     145 [-]: GETIMPORT R6 30 [nil]
     146 [-]: GETUPVAL R7 7
     147 [-]: LOADB R8 0   
     148 [-]: CALL R3 5 0  
     149 [-]: GETUPVAL R3 0
     150 [-]: LOADK R5 K32 ["Selected"]
     151 [-]: LOADK R6 K33 ["Focused"]
     152 [-]: LOADK R7 K34 ["Unfocused"]
     153 [-]: LOADK R8 K35 ["Pressed"]
     154 [-]: NAMECALL R3 R3 K36 [0x1E5B5CFE]
     155 [-]: CALL R3 5 0  
     156 [-]: GETUPVAL R3 0
     157 [-]: LOADK R4 K37 [0.01]
     158 [-]: SETTABLEKS R4 R3 K38 ["mElementDelayTime"]
     159 [-]: GETUPVAL R3 0
     160 [-]: LOADK R4 K39 [0.050000000000000003]
     161 [-]: SETTABLEKS R4 R3 K40 ["mElementTransitionTime"]
     162 [-]: GETUPVAL R3 0
     163 [-]: LOADN R4 -272
     164 [-]: SETTABLEKS R4 R3 K41 ["mColumnSeparation"]
     165 [-]: GETUPVAL R3 0
     166 [-]: LOADN R4 -150
     167 [-]: SETTABLEKS R4 R3 K42 ["mRowSeparation"]
     168 [-]: GETUPVAL R3 0
     169 [-]: NEWCLOSURE R4 P0
     170 [-]: MOVE R2 R8   
     171 [-]: MOVE R2 R9   
     172 [-]: SETTABLEKS R4 R3 K43 ["mOnFocusedCallback"]
     173 [-]: GETUPVAL R3 0
     174 [-]: NEWCLOSURE R4 P1
     175 [-]: MOVE R2 R8   
     176 [-]: MOVE R2 R9   
     177 [-]: SETTABLEKS R4 R3 K44 ["mOnUnfocusedCallback"]
     178 [-]: GETUPVAL R3 0
     179 [-]: NEWCLOSURE R4 P2
     180 [-]: MOVE R2 R8   
     181 [-]: MOVE R2 R10  
     182 [-]: MOVE R2 R11  
     183 [-]: MOVE R2 R3   
     184 [-]: MOVE R2 R7   
     185 [-]: MOVE R2 R12  
     186 [-]: MOVE R2 R13  
     187 [-]: MOVE R2 R14  
     188 [-]: MOVE R2 R15  
     189 [-]: MOVE R2 R16  
     190 [-]: MOVE R2 R9   
     191 [-]: MOVE R2 R17  
     192 [-]: MOVE R2 R18  
     193 [-]: MOVE R2 R5   
     194 [-]: MOVE R2 R19  
     195 [-]: MOVE R2 R20  
     196 [-]: MOVE R2 R21  
     197 [-]: SETTABLEKS R4 R3 K45 ["mOnPressedCallback"]
     198 [-]: GETUPVAL R3 0
     199 [-]: NEWCLOSURE R4 P3
     200 [-]: MOVE R2 R8   
     201 [-]: MOVE R2 R13  
     202 [-]: SETTABLEKS R4 R3 K46 ["mOnSelectedCallback"]
     203 [-]: GETUPVAL R3 0
     204 [-]: NEWCLOSURE R4 P4
     205 [-]: MOVE R2 R9   
     206 [-]: MOVE R2 R0   
     207 [-]: MOVE R2 R10  
     208 [-]: MOVE R2 R11  
     209 [-]: SETTABLEKS R4 R3 K47 ["mElementDrawCallback"]
     210 [-]: RETURN R0 0  


; Name:            
; Defined at line: 332
; #Upvalues:       6
; #Parameters:     0
; Is_vararg:       0
; Max Stack Size:  10

       0 [-]: GETUPVAL R0 0
       1 [-]: CALL R0 0 0  
       2 [-]: GETUPVAL R0 1
       3 [-]: NAMECALL R0 R0 K0 [0x7C09C373]
       4 [-]: CALL R0 1 0  
       5 [-]: LOADN R0 1   
       6 [-]: GETUPVAL R1 2
       7 [-]: CALL R1 0 1  
       8 [-]: JUMPIFNOT R1 L0
       9 [-]: LOADN R0 7   
L 0:  10 [-]: MOVE R3 R0   
      11 [-]: GETUPVAL R1 3
      12 [-]: LOADN R2 1   
      13 [-]: FORNPREP R1 L2
L 1:  14 [-]: DUPTABLE R4 4
      15 [-]: SETTABLEKS R3 R4 K1 ["mSlot"]
      16 [-]: GETUPVAL R6 4
      17 [-]: GETTABLE R5 R6 R3
      18 [-]: SETTABLEKS R5 R4 K2 ["mValue"]
      19 [-]: SETTABLEKS R3 R4 K3 ["mOriginalSlot"]
      20 [-]: GETUPVAL R5 1
      21 [-]: DUPTABLE R7 11
      22 [-]: LOADN R8 -1  
      23 [-]: SETTABLEKS R8 R7 K5 ["mCardIndex"]
      24 [-]: GETUPVAL R9 4
      25 [-]: GETTABLE R8 R9 R3
      26 [-]: SETTABLEKS R8 R7 K6 ["mPolarity"]
      27 [-]: GETUPVAL R9 4
      28 [-]: GETTABLE R8 R9 R3
      29 [-]: SETTABLEKS R8 R7 K7 ["mNewPolarity"]
      30 [-]: GETUPVAL R9 4
      31 [-]: GETTABLE R8 R9 R3
      32 [-]: SETTABLEKS R8 R7 K8 ["mOriginalPolarity"]
      33 [-]: SETTABLEKS R3 R7 K9 ["mSlotIndex"]
      34 [-]: SETTABLEKS R4 R7 K10 ["mSlotData"]
      35 [-]: LOADB R8 1   
      36 [-]: NAMECALL R5 R5 K12 [0xBAD4316F]
      37 [-]: CALL R5 3 0  
      38 [-]: FORNLOOP R1 L1
L 2:  39 [-]: GETUPVAL R1 1
      40 [-]: NEWCLOSURE R3 P0
      41 [-]: MOVE R2 R5   
      42 [-]: NAMECALL R1 R1 K13 [0x71E9AC81]
      43 [-]: CALL R1 2 0  
      44 [-]: RETURN R0 0  


; Name:            
; Defined at line: 353
; #Upvalues:       13
; #Parameters:     0
; Is_vararg:       0
; Max Stack Size:  12

       0 [-]: GETUPVAL R1 0
       1 [-]: GETTABLEKS R0 R1 K0 [0x659D451F]
       2 [-]: GETIMPORT R2 2 [nil]
       3 [-]: GETTABLEKS R1 R2 K3 ["UISound_WindowOpen"]
       4 [-]: CALL R0 1 0  
       5 [-]: GETIMPORT R0 5 [nil]
       6 [-]: LOADK R2 K6 ["Card1"]
       7 [-]: LOADN R3 11  
       8 [-]: LOADB R4 0   
       9 [-]: NAMECALL R0 R0 K7 [0xAADE900E]
      10 [-]: CALL R0 4 0  
      11 [-]: GETIMPORT R0 9 [nil]
      12 [-]: LOADNIL R1   
      13 [-]: SETTABLEKS R1 R0 K10 ["gToolTip"]
      14 [-]: GETIMPORT R0 9 [nil]
      15 [-]: LOADNIL R1   
      16 [-]: SETTABLEKS R1 R0 K11 ["PolaritySwaps"]
      17 [-]: LOADNIL R0   
      18 [-]: SETUPVAL R0 1
      19 [-]: GETIMPORT R0 13 [nil]
      20 [-]: LOADN R2 0   
      21 [-]: NAMECALL R0 R0 K14 [0x3F3AE64C]
      22 [-]: CALL R0 2 1  
      23 [-]: GETIMPORT R1 16 [nil]
      24 [-]: LOADK R2 K17 ["Lotus.Interface.Libs.TimerMgr"]
      25 [-]: CALL R1 1 1  
      26 [-]: GETTABLEKS R2 R1 K18 [0xDE474187]
      27 [-]: CALL R2 0 1  
      28 [-]: SETUPVAL R2 2
      29 [-]: FASTCALL1 62 R0 L0
      30 [-]: MOVE R3 R0   
      31 [-]: GETIMPORT R2 20 [nil]
      32 [-]: CALL R2 1 1  
L 0:  33 [-]: JUMPIFNOT R2 L1
      34 [-]: GETIMPORT R2 22 [nil]
      35 [-]: LOADK R3 K23 ["NULL PLAYER PROFILE WHAT TO DO"]
      36 [-]: CALL R2 1 0  
      37 [-]: GETIMPORT R2 25 [nil]
      38 [-]: CALL R2 0 0  
      39 [-]: RETURN R0 0  
L 1:  40 [-]: GETUPVAL R2 3
      41 [-]: CALL R2 0 1  
      42 [-]: JUMPIFNOT R2 L2
      43 [-]: LOADN R2 15  
      44 [-]: SETUPVAL R2 4
L 2:  45 [-]: LOADN R2 30  
      46 [-]: GETIMPORT R4 27 [nil]
      47 [-]: FASTCALL1 62 R4 L3
      48 [-]: GETIMPORT R3 20 [nil]
      49 [-]: CALL R3 1 1  
L 3:  50 [-]: JUMPIF R3 L14
      51 [-]: GETIMPORT R3 27 [nil]
      52 [-]: SETUPVAL R3 5
      53 [-]: GETUPVAL R4 5
      54 [-]: GETTABLEKS R3 R4 K28 ["info"]
      55 [-]: NAMECALL R3 R3 K29 [0xFA86E69D]
      56 [-]: CALL R3 1 1  
      57 [-]: SETUPVAL R3 6
      58 [-]: LOADN R3 0   
      59 [-]: GETIMPORT R4 31 [nil]
      60 [-]: GETIMPORT R5 33 [nil]
      61 [-]: JUMPXEQKNIL R4 L13
      62 [-]: JUMPXEQKNIL R5 L13
      63 [-]: LOADN R6 0   
      64 [-]: JUMPIFEQ R4 R6 L4
      65 [-]: LOADN R6 3   
      66 [-]: JUMPIFNOTEQ R4 R6 L13
L 4:  67 [-]: LOADN R6 0   
      68 [-]: JUMPIFEQ R5 R6 L5
      69 [-]: GETUPVAL R6 7
      70 [-]: CALL R6 0 1  
      71 [-]: JUMPIFNOT R6 L6
L 5:  72 [-]: LOADN R3 2   
      73 [-]: JUMP L8
     
L 6:  74 [-]: LOADN R6 3   
      75 [-]: JUMPIFEQ R5 R6 L7
      76 [-]: GETUPVAL R6 8
      77 [-]: CALL R6 0 1  
      78 [-]: JUMPIF R6 L7 
      79 [-]: LOADN R6 2   
      80 [-]: JUMPIFEQ R5 R6 L7
      81 [-]: LOADN R6 1   
      82 [-]: JUMPIFNOTEQ R5 R6 L8
L 7:  83 [-]: GETUPVAL R9 5
      84 [-]: GETTABLEKS R8 R9 K28 ["info"]
      85 [-]: GETTABLEKS R7 R8 K34 ["mModularParts"]
      86 [-]: LENGTH R6 R7 
      87 [-]: LOADN R7 0   
      88 [-]: JUMPIFNOTLT R7 R6 L8
      89 [-]: LOADN R3 1   
L 8:  90 [-]: GETUPVAL R8 5
      91 [-]: GETTABLEKS R7 R8 K35 ["item"]
      92 [-]: FASTCALL1 62 R7 L9
      93 [-]: GETIMPORT R6 20 [nil]
      94 [-]: CALL R6 1 1  
L 9:  95 [-]: JUMPIF R6 L11
      96 [-]: GETUPVAL R8 5
      97 [-]: GETTABLEKS R7 R8 K35 ["item"]
      98 [-]: NAMECALL R7 R7 K36 [0xD17BF72C]
      99 [-]: CALL R7 1 1  
     100 [-]: FASTCALL1 62 R7 L10
     101 [-]: GETIMPORT R6 20 [nil]
     102 [-]: CALL R6 1 1  
L10: 103 [-]: JUMPIFNOT R6 L12
L11: 104 [-]: GETUPVAL R7 5
     105 [-]: GETTABLEKS R6 R7 K37 ["hasApertureSlot"]
     106 [-]: JUMPXEQKNIL R6 L13
     107 [-]: GETUPVAL R7 5
     108 [-]: GETTABLEKS R6 R7 K37 ["hasApertureSlot"]
     109 [-]: JUMPIFNOT R6 L13
L12: 110 [-]: ADDK R3 R3 K38 [1]
L13: 111 [-]: GETUPVAL R8 6
     112 [-]: LENGTH R7 R8 
     113 [-]: SUB R6 R7 R3 
     114 [-]: SETUPVAL R6 9
     115 [-]: GETIMPORT R6 40 [nil]
     116 [-]: GETUPVAL R10 5
     117 [-]: GETTABLEKS R9 R10 K28 ["info"]
     118 [-]: GETTABLEKS R8 R9 K41 ["mItemType"]
     119 [-]: GETUPVAL R11 5
     120 [-]: GETTABLEKS R10 R11 K28 ["info"]
     121 [-]: GETTABLEKS R9 R10 K42 ["mPolarized"]
     122 [-]: NAMECALL R6 R6 K43 [0x84FB4327]
     123 [-]: CALL R6 3 1  
     124 [-]: MOVE R2 R6   
L14: 125 [-]: NEWTABLE R3 0 0
     126 [-]: DUPTABLE R6 47
     127 [-]: LOADK R7 K48 ["/Lotus/Language/Menu/Loadout_Apply"]
     128 [-]: SETTABLEKS R7 R6 K44 ["Label"]
     129 [-]: DUPCLOSURE R7 K49 []
     130 [-]: SETTABLEKS R7 R6 K45 ["CallBack"]
     131 [-]: LOADK R7 K50 ["MENU_GENERIC1"]
     132 [-]: SETTABLEKS R7 R6 K46 ["CallOut"]
     133 [-]: FASTCALL2 52 R3 R6 L15
     134 [-]: MOVE R5 R3   
     135 [-]: GETIMPORT R4 53 [nil]
     136 [-]: CALL R4 2 0  
L15: 137 [-]: DUPTABLE R6 47
     138 [-]: LOADK R7 K54 ["/Lotus/Language/Menu/Loadout_Cancel"]
     139 [-]: SETTABLEKS R7 R6 K44 ["Label"]
     140 [-]: DUPCLOSURE R7 K55 []
     141 [-]: SETTABLEKS R7 R6 K45 ["CallBack"]
     142 [-]: LOADK R7 K56 ["MENU_CANCEL"]
     143 [-]: SETTABLEKS R7 R6 K46 ["CallOut"]
     144 [-]: FASTCALL2 52 R3 R6 L16
     145 [-]: MOVE R5 R3   
     146 [-]: GETIMPORT R4 53 [nil]
     147 [-]: CALL R4 2 0  
L16: 148 [-]: GETIMPORT R4 58 [nil]
     149 [-]: GETIMPORT R5 5 [nil]
     150 [-]: MOVE R6 R3   
     151 [-]: GETIMPORT R7 60 [nil]
     152 [-]: LOADN R8 1   
     153 [-]: CALL R7 1 -1 
     154 [-]: CALL R4 -1 0 
     155 [-]: GETIMPORT R4 5 [nil]
     156 [-]: LOADK R6 K61 ["Installed.Title.text"]
     157 [-]: LOADK R7 K62 ["/Lotus/Language/Menu/Loadout_SelectPolarize"]
     158 [-]: NAMECALL R4 R4 K63 [0x20B98DB3]
     159 [-]: CALL R4 3 0  
     160 [-]: GETIMPORT R4 65 [nil]
     161 [-]: SETUPVAL R4 10
     162 [-]: GETIMPORT R4 9 [nil]
     163 [-]: LOADNIL R5   
     164 [-]: SETTABLEKS R5 R4 K64 ["chosenForma"]
     165 [-]: LOADK R4 K66 [""]
     166 [-]: GETUPVAL R5 3
     167 [-]: CALL R5 0 1  
     168 [-]: JUMPIFNOT R5 L17
     169 [-]: GETIMPORT R7 5 [nil]
     170 [-]: LOADK R9 K67 ["/Lotus/Language/Railjack/PolarizeHarnessHint"]
     171 [-]: LOADB R10 0  
     172 [-]: NAMECALL R7 R7 K68 [0x42B04007]
     173 [-]: CALL R7 3 1  
     174 [-]: MOVE R5 R7   
     175 [-]: LOADK R6 K69 ["\r\n\r\n"]
     176 [-]: CONCAT R4 R5 R6
L17: 177 [-]: GETUPVAL R5 10
     178 [-]: GETUPVAL R6 11
     179 [-]: JUMPIFNOTEQ R5 R6 L18
     180 [-]: MOVE R5 R4   
     181 [-]: GETIMPORT R6 5 [nil]
     182 [-]: LOADK R8 K70 ["/Lotus/Language/Menu/Loadout_PolarizeNoRankDesc"]
     183 [-]: LOADB R9 1   
     184 [-]: DUPTABLE R10 72
     185 [-]: SETTABLEKS R2 R10 K71 ["RANK"]
     186 [-]: NAMECALL R6 R6 K68 [0x42B04007]
     187 [-]: CALL R6 4 1  
     188 [-]: CONCAT R4 R5 R6
     189 [-]: JUMP L19
    
L18: 190 [-]: MOVE R5 R4   
     191 [-]: GETIMPORT R6 5 [nil]
     192 [-]: LOADK R8 K73 ["/Lotus/Language/Menu/Loadout_PolarizeDesc"]
     193 [-]: LOADB R9 1   
     194 [-]: DUPTABLE R10 72
     195 [-]: SETTABLEKS R2 R10 K71 ["RANK"]
     196 [-]: NAMECALL R6 R6 K68 [0x42B04007]
     197 [-]: CALL R6 4 1  
     198 [-]: CONCAT R4 R5 R6
L19: 199 [-]: GETIMPORT R5 5 [nil]
     200 [-]: LOADK R7 K74 ["Description"]
     201 [-]: LOADN R8 29  
     202 [-]: MOVE R9 R4   
     203 [-]: NAMECALL R5 R5 K75 [0x5F56EEAB]
     204 [-]: CALL R5 4 0  
     205 [-]: GETIMPORT R5 5 [nil]
     206 [-]: LOADK R7 K76 ["_root"]
     207 [-]: LOADN R8 10  
     208 [-]: LOADN R9 0   
     209 [-]: NAMECALL R5 R5 K77 [0x67BC869F]
     210 [-]: CALL R5 4 0  
     211 [-]: GETIMPORT R5 79 [nil]
     212 [-]: GETIMPORT R6 5 [nil]
     213 [-]: LOADK R7 K76 ["_root"]
     214 [-]: LOADN R8 7   
     215 [-]: NEWTABLE R9 0 1
     216 [-]: LOADN R10 10 
     217 [-]: SETLIST R9 R10 1 [1]
     218 [-]: NEWTABLE R10 0 1
     219 [-]: LOADN R11 100
     220 [-]: SETLIST R10 R11 1 [1]
     221 [-]: LOADK R11 K80 [0.5]
     222 [-]: CALL R5 6 0  
     223 [-]: GETIMPORT R5 9 [nil]
     224 [-]: DUPTABLE R6 83
     225 [-]: LOADN R7 -1  
     226 [-]: SETTABLEKS R7 R6 K81 ["mSlotIndex"]
     227 [-]: LOADN R7 0   
     228 [-]: SETTABLEKS R7 R6 K82 ["mPolarity"]
     229 [-]: SETTABLEKS R6 R5 K84 ["Polarized"]
     230 [-]: GETIMPORT R5 9 [nil]
     231 [-]: LOADNIL R6   
     232 [-]: SETTABLEKS R6 R5 K11 ["PolaritySwaps"]
     233 [-]: GETUPVAL R5 2
     234 [-]: LOADN R7 0   
     235 [-]: GETUPVAL R8 12
     236 [-]: NAMECALL R5 R5 K85 [0xBD2E96EA]
     237 [-]: CALL R5 3 0  
     238 [-]: RETURN R0 0  


; Name:            
; Defined at line: 434
; #Upvalues:       3
; #Parameters:     0
; Is_vararg:       0
; Max Stack Size:  3

       0 [-]: GETIMPORT R1 1 [nil]
       1 [-]: FASTCALL1 62 R1 L0
       2 [-]: GETIMPORT R0 3 [nil]
       3 [-]: CALL R0 1 1  
L 0:   4 [-]: JUMPIFNOT R0 L1
       5 [-]: RETURN R0 0  
L 1:   6 [-]: GETUPVAL R0 0
       7 [-]: JUMPIFNOT R0 L2
       8 [-]: GETIMPORT R0 1 [nil]
       9 [-]: NAMECALL R0 R0 K4 [0x32302B4A]
      10 [-]: CALL R0 1 0  
      11 [-]: RETURN R0 0  
L 2:  12 [-]: GETIMPORT R0 1 [nil]
      13 [-]: GETIMPORT R2 6 [nil]
      14 [-]: CALL R2 0 -1 
      15 [-]: NAMECALL R0 R0 K7 [0x8A8C8D5A]
      16 [-]: CALL R0 -1 0 
      17 [-]: GETUPVAL R0 1
      18 [-]: JUMPIFNOT R0 L3
L 3:  19 [-]: GETUPVAL R1 2
      20 [-]: FASTCALL1 62 R1 L4
      21 [-]: GETIMPORT R0 3 [nil]
      22 [-]: CALL R0 1 1  
L 4:  23 [-]: JUMPIF R0 L5 
      24 [-]: GETUPVAL R0 2
      25 [-]: GETIMPORT R2 6 [nil]
      26 [-]: CALL R2 0 -1 
      27 [-]: NAMECALL R0 R0 K8 [0xFAA69527]
      28 [-]: CALL R0 -1 0 
L 5:  29 [-]: RETURN R0 0  


; Name:            
; Defined at line: 459
; #Upvalues:       2
; #Parameters:     0
; Is_vararg:       0
; Max Stack Size:  9

       0 [-]: GETUPVAL R0 0
       1 [-]: JUMPIFNOT R0 L0
       2 [-]: RETURN R0 0  
L 0:   3 [-]: LOADB R0 1   
       4 [-]: SETUPVAL R0 0
       5 [-]: GETIMPORT R0 1 [nil]
       6 [-]: GETIMPORT R1 3 [nil]
       7 [-]: LOADK R2 K4 ["_root"]
       8 [-]: LOADN R3 0   
       9 [-]: NEWTABLE R4 0 1
      10 [-]: LOADN R5 10  
      11 [-]: SETLIST R4 R5 1 [1]
      12 [-]: NEWTABLE R5 0 1
      13 [-]: LOADN R6 0   
      14 [-]: SETLIST R5 R6 1 [1]
      15 [-]: LOADK R6 K5 [0.20000000000000001]
      16 [-]: LOADN R7 0   
      17 [-]: NEWCLOSURE R8 P0
      18 [-]: MOVE R2 R1   
      19 [-]: CALL R0 8 0  
      20 [-]: RETURN R0 0  


; Name:            
; Defined at line: 467
; #Upvalues:       1
; #Parameters:     0
; Is_vararg:       0
; Max Stack Size:  1

       0 [-]: GETUPVAL R0 0
       1 [-]: CALL R0 0 0  
       2 [-]: RETURN R0 0  


; Name:            
; Defined at line: 471
; #Upvalues:       3
; #Parameters:     0
; Is_vararg:       0
; Max Stack Size:  4

       0 [-]: GETIMPORT R0 1 [nil]
       1 [-]: NAMECALL R0 R0 K2 [0x33ABEE92]
       2 [-]: CALL R0 1 1  
       3 [-]: GETUPVAL R2 0
       4 [-]: LOADK R3 K3 ["No"]
       5 [-]: NAMECALL R0 R0 K4 [0xE4162EED]
       6 [-]: CALL R0 3 0  
       7 [-]: GETUPVAL R1 1
       8 [-]: GETTABLEKS R0 R1 K5 [0x659D451F]
       9 [-]: GETIMPORT R2 7 [nil]
      10 [-]: GETTABLEKS R1 R2 K8 ["UISound_WindowClose"]
      11 [-]: CALL R0 1 0  
      12 [-]: GETUPVAL R0 2
      13 [-]: CALL R0 0 0  
      14 [-]: RETURN R0 0  


; Name:            
; Defined at line: 477
; #Upvalues:       8
; #Parameters:     0
; Is_vararg:       0
; Max Stack Size:  12

       0 [-]: GETUPVAL R0 0
       1 [-]: JUMPIFNOT R0 L0
       2 [-]: GETUPVAL R1 1
       3 [-]: GETTABLEKS R0 R1 K0 [0x659D451F]
       4 [-]: GETIMPORT R2 2 [nil]
       5 [-]: GETTABLEKS R1 R2 K3 ["UISound_Error"]
       6 [-]: CALL R0 1 0  
       7 [-]: GETUPVAL R1 1
       8 [-]: GETTABLEKS R0 R1 K4 [0xE0CBA3CA]
       9 [-]: LOADK R1 K5 ["/Lotus/Language/Menu/Polarize_SwapIncompleteWarning"]
      10 [-]: CALL R0 1 0  
      11 [-]: RETURN R0 0  
L 0:  12 [-]: GETUPVAL R0 2
      13 [-]: JUMPIFNOT R0 L1
      14 [-]: GETUPVAL R0 2
      15 [-]: GETUPVAL R2 2
      16 [-]: GETTABLEKS R1 R2 K6 ["mNewPolarity"]
      17 [-]: SETTABLEKS R1 R0 K7 ["mPolarity"]
L 1:  18 [-]: NEWTABLE R0 0 0
      19 [-]: GETUPVAL R1 3
      20 [-]: CALL R1 0 1  
      21 [-]: JUMPIFNOT R1 L4
      22 [-]: LOADN R3 1   
      23 [-]: LOADN R1 6   
      24 [-]: LOADN R2 1   
      25 [-]: FORNPREP R1 L4
L 2:  26 [-]: DUPTABLE R6 10
      27 [-]: SUBK R7 R3 K11 [1]
      28 [-]: SETTABLEKS R7 R6 K8 ["mSlot"]
      29 [-]: GETUPVAL R8 4
      30 [-]: GETTABLE R7 R8 R3
      31 [-]: SETTABLEKS R7 R6 K9 ["mValue"]
      32 [-]: FASTCALL2 52 R0 R6 L3
      33 [-]: MOVE R5 R0   
      34 [-]: GETIMPORT R4 14 [nil]
      35 [-]: CALL R4 2 0  
L 3:  36 [-]: FORNLOOP R1 L2
L 4:  37 [-]: GETIMPORT R1 16 [nil]
      38 [-]: GETUPVAL R4 5
      39 [-]: GETTABLEKS R2 R4 K17 ["mElements"]
      40 [-]: CALL R1 1 3  
      41 [-]: FORGPREP_INEXT R1 L6
L 5:  42 [-]: DUPTABLE R8 10
      43 [-]: GETTABLEKS R11 R5 K18 ["mSlotData"]
      44 [-]: GETTABLEKS R10 R11 K19 ["mOriginalSlot"]
      45 [-]: SUBK R9 R10 K11 [1]
      46 [-]: SETTABLEKS R9 R8 K8 ["mSlot"]
      47 [-]: GETTABLEKS R10 R5 K18 ["mSlotData"]
      48 [-]: GETTABLEKS R9 R10 K9 ["mValue"]
      49 [-]: SETTABLEKS R9 R8 K9 ["mValue"]
      50 [-]: FASTCALL2 52 R0 R8 L6
      51 [-]: MOVE R7 R0   
      52 [-]: GETIMPORT R6 14 [nil]
      53 [-]: CALL R6 2 0  
L 6:  54 [-]: FORGLOOP R1 L5 2 [inext]
      55 [-]: GETIMPORT R1 21 [nil]
      56 [-]: SETTABLEKS R0 R1 K22 ["PolaritySwaps"]
      57 [-]: GETIMPORT R1 24 [nil]
      58 [-]: NAMECALL R1 R1 K25 [0x33ABEE92]
      59 [-]: CALL R1 1 1  
      60 [-]: GETUPVAL R3 6
      61 [-]: LOADK R4 K26 ["Yes"]
      62 [-]: NAMECALL R1 R1 K27 [0xE4162EED]
      63 [-]: CALL R1 3 0  
      64 [-]: GETUPVAL R1 1
      65 [-]: GETTABLEKS R0 R1 K0 [0x659D451F]
      66 [-]: GETIMPORT R2 2 [nil]
      67 [-]: GETTABLEKS R1 R2 K28 ["UISound_SweetnerTwo"]
      68 [-]: CALL R0 1 0  
      69 [-]: GETUPVAL R0 7
      70 [-]: CALL R0 0 0  
      71 [-]: RETURN R0 0  


; Name:            
; Defined at line: 506
; #Upvalues:       1
; #Parameters:     1
; Is_vararg:       0
; Max Stack Size:  1

       0 [-]: SETUPVAL R0 0
       1 [-]: RETURN R0 0  


; Name:            
; Defined at line: 510
; #Upvalues:       2
; #Parameters:     0
; Is_vararg:       0
; Max Stack Size:  3

       0 [-]: GETUPVAL R0 0
       1 [-]: JUMPIF R0 L1 
       2 [-]: GETUPVAL R1 1
       3 [-]: FASTCALL1 62 R1 L0
       4 [-]: GETIMPORT R0 1 [nil]
       5 [-]: CALL R0 1 1  
L 0:   6 [-]: JUMPIF R0 L1 
       7 [-]: GETUPVAL R0 1
       8 [-]: NAMECALL R0 R0 K2 [0xED1AB921]
       9 [-]: CALL R0 1 1  
      10 [-]: JUMPXEQKNIL R0 L1
      11 [-]: GETUPVAL R1 1
      12 [-]: GETTABLEKS R0 R1 K3 ["mOnPressedCallback"]
      13 [-]: GETUPVAL R1 1
      14 [-]: NAMECALL R1 R1 K2 [0xED1AB921]
      15 [-]: CALL R1 1 -1 
      16 [-]: CALL R0 -1 0 
L 1:  17 [-]: RETURN R0 0  


; Name:            
; Defined at line: 516
; #Upvalues:       1
; #Parameters:     1
; Is_vararg:       0
; Max Stack Size:  5

       0 [-]: SETUPVAL R0 0
       1 [-]: GETIMPORT R1 1 [nil]
       2 [-]: LOADK R3 K2 ["Installed.Title.text"]
       3 [-]: LOADK R4 K3 ["/Lotus/Language/Menu/Loadout_SwapPolarizeSlots"]
       4 [-]: NAMECALL R1 R1 K4 [0x20B98DB3]
       5 [-]: CALL R1 3 0  
       6 [-]: GETIMPORT R1 1 [nil]
       7 [-]: LOADK R3 K5 ["Description.text"]
       8 [-]: LOADK R4 K6 ["/Lotus/Language/Menu/Loadout_SwapPolarizationSlotsDesc"]
       9 [-]: NAMECALL R1 R1 K4 [0x20B98DB3]
      10 [-]: CALL R1 3 0  
      11 [-]: RETURN R0 0  


; Name:            
; Defined at line: 522
; #Upvalues:       0
; #Parameters:     1
; Is_vararg:       0
; Max Stack Size:  5

       0 [-]: GETIMPORT R1 1 [nil]
       1 [-]: LOADK R3 K2 ["Description.text"]
       2 [-]: MOVE R4 R0   
       3 [-]: NAMECALL R1 R1 K3 [0x20B98DB3]
       4 [-]: CALL R1 3 0  
       5 [-]: RETURN R0 0  


; Name:            
; Defined at line: 527
; #Upvalues:       1
; #Parameters:     1
; Is_vararg:       0
; Max Stack Size:  2

       0 [-]: JUMPXEQKS R0 K0 L0 ["true"]
       1 [-]: LOADB R1 0 +1
L 0:   2 [-]: LOADB R1 1   
L 1:   3 [-]: SETUPVAL R1 0
       4 [-]: RETURN R0 0  



