; Name:            
; Defined at line: 1
; #Upvalues:       0
; #Parameters:     0
; Is_vararg:       1
; Max Stack Size:  97

       1 [-]: GETIMPORT R0 1 [0x2D0FAD09]
       2 [-]: LOADK R1 K2 ["Lotus.Interface.CardUtilitiesRedux"]
       3 [-]: CALL R0 1 1  
       4 [-]: GETIMPORT R1 1 [0x2D0FAD09]
       5 [-]: LOADK R2 K3 ["EE.Interface.Utilities"]
       6 [-]: CALL R1 1 1  
       7 [-]: GETIMPORT R2 1 [0x2D0FAD09]
       8 [-]: LOADK R3 K4 ["Lotus.Interface.LotusUtilities"]
       9 [-]: CALL R2 1 1  
      10 [-]: GETIMPORT R3 1 [0x2D0FAD09]
      11 [-]: LOADK R4 K5 ["Lotus.Interface.UIUtilities"]
      12 [-]: CALL R3 1 1  
      13 [-]: GETIMPORT R4 1 [0x2D0FAD09]
      14 [-]: LOADK R5 K6 ["Lotus.Interface.UIStyleUtilities"]
      15 [-]: CALL R4 1 1  
      16 [-]: DUPTABLE R5 12
      17 [-]: LOADN R6 1   
      18 [-]: SETTABLEKS R6 R5 K7 ["NARAMON"]
      19 [-]: LOADN R6 2   
      20 [-]: SETTABLEKS R6 R5 K8 ["ZENURIK"]
      21 [-]: LOADN R6 3   
      22 [-]: SETTABLEKS R6 R5 K9 ["VAZARIN"]
      23 [-]: LOADN R6 4   
      24 [-]: SETTABLEKS R6 R5 K10 ["UNAIRU"]
      25 [-]: LOADN R6 5   
      26 [-]: SETTABLEKS R6 R5 K11 ["MADURAI"]
      27 [-]: GETIMPORT R6 1 [0x2D0FAD09]
      28 [-]: LOADK R7 K13 ["EE.Interface.AnchorMgr"]
      29 [-]: CALL R6 1 1  
      30 [-]: LOADNIL R7   
      31 [-]: LOADB R8 0   
      32 [-]: LOADB R9 1   
      33 [-]: LOADNIL R10  
      34 [-]: LOADNIL R11  
      35 [-]: LOADNIL R12  
      36 [-]: LOADNIL R13  
      37 [-]: LOADNIL R14  
      38 [-]: LOADNIL R15  
      39 [-]: LOADNIL R16  
      40 [-]: LOADB R17 0  
      41 [-]: LOADNIL R18  
      42 [-]: LOADNIL R19  
      43 [-]: LOADNIL R20  
      44 [-]: LOADNIL R21  
      45 [-]: LOADNIL R22  
      46 [-]: LOADK R23 K14 ["/Lotus/Language/TennoWay/Naramon"]
      47 [-]: LOADK R24 K15 [""]
      48 [-]: GETTABLEKS R25 R5 K7 ["NARAMON"]
      49 [-]: LOADN R26 0  
      50 [-]: LOADN R27 12345
      51 [-]: LOADN R28 0  
      52 [-]: LOADN R29 0  
      53 [-]: NEWTABLE R30 0 0
      54 [-]: NEWTABLE R31 0 0
      55 [-]: LOADB R32 0  
      56 [-]: LOADB R33 0  
      57 [-]: NEWTABLE R34 0 0
      58 [-]: NEWTABLE R35 0 5
      59 [-]: LOADK R36 K16 ["AP_TACTIC"]
      60 [-]: SETTABLEN R36 R35 1
      61 [-]: LOADK R36 K17 ["AP_POWER"]
      62 [-]: SETTABLEN R36 R35 2
      63 [-]: LOADK R36 K18 ["AP_DEFENSE"]
      64 [-]: SETTABLEN R36 R35 3
      65 [-]: LOADK R36 K19 ["AP_WARD"]
      66 [-]: SETTABLEN R36 R35 4
      67 [-]: LOADK R36 K20 ["AP_ATTACK"]
      68 [-]: SETTABLEN R36 R35 5
      69 [-]: LOADNIL R36  
      70 [-]: LOADN R37 0  
      71 [-]: LOADNIL R38  
      72 [-]: NEWTABLE R39 4 0
      73 [-]: LOADNIL R40  
      74 [-]: LOADB R41 0  
      75 [-]: LOADN R42 1  
      76 [-]: LOADN R43 1  
      77 [-]: NEWTABLE R44 0 0
      78 [-]: GETIMPORT R45 22 [0x78CA68A2]
      79 [-]: LOADN R46 0  
      80 [-]: LOADK R47 K23 [0.14999999999999999]
      81 [-]: CALL R45 2 1 
      82 [-]: LOADN R46 0  
      83 [-]: LOADN R47 0  
      84 [-]: DUPTABLE R48 26
      85 [-]: LOADN R49 0  
      86 [-]: SETTABLEKS R49 R48 K24 ["x"]
      87 [-]: LOADN R49 0  
      88 [-]: SETTABLEKS R49 R48 K25 ["y"]
      89 [-]: LOADB R49 0  
      90 [-]: LOADB R50 0  
      91 [-]: LOADK R51 K15 [""]
      92 [-]: LOADN R52 0  
      93 [-]: LOADNIL R53  
      94 [-]: GETIMPORT R54 29 [0x1467D5F4]
      95 [-]: CALL R54 0 1 
      96 [-]: LOADNIL R55  
      97 [-]: LOADNIL R56  
      98 [-]: LOADNIL R57  
      99 [-]: LOADN R58 0  
     100 [-]: LOADNIL R59  
     101 [-]: LOADNIL R60  
     102 [-]: NEWCLOSURE R61 P0
     103 [-]: MOVE R1 R59  
     104 [-]: MOVE R0 R4   
     105 [-]: MOVE R0 R1   
     106 [-]: MOVE R1 R20  
     107 [-]: MOVE R1 R21  
     108 [-]: NEWCLOSURE R62 P1
     109 [-]: MOVE R1 R53  
     110 [-]: SETGLOBAL R62 K30 ["Shutdown"]
     111 [-]: NEWCLOSURE R62 P2
     112 [-]: MOVE R1 R30  
     113 [-]: MOVE R1 R31  
     114 [-]: MOVE R0 R1   
     115 [-]: NEWCLOSURE R63 P3
     116 [-]: MOVE R1 R30  
     117 [-]: MOVE R1 R33  
     118 [-]: MOVE R1 R29  
     119 [-]: NEWCLOSURE R64 P4
     120 [-]: MOVE R1 R30  
     121 [-]: MOVE R0 R1   
     122 [-]: MOVE R1 R33  
     123 [-]: MOVE R1 R29  
     124 [-]: NEWCLOSURE R65 P5
     125 [-]: MOVE R1 R31  
     126 [-]: MOVE R1 R33  
     127 [-]: MOVE R1 R29  
     128 [-]: NEWCLOSURE R66 P6
     129 [-]: MOVE R0 R62  
     130 [-]: MOVE R0 R1   
     131 [-]: MOVE R1 R30  
     132 [-]: MOVE R1 R31  
     133 [-]: MOVE R1 R29  
     134 [-]: MOVE R1 R34  
     135 [-]: MOVE R1 R32  
     136 [-]: MOVE R1 R55  
     137 [-]: MOVE R1 R39  
     138 [-]: MOVE R1 R33  
     139 [-]: SETGLOBAL R66 K31 ["OnFocusCommitted"]
     140 [-]: NEWCLOSURE R66 P7
     141 [-]: MOVE R1 R18  
     142 [-]: DUPCLOSURE R67 K32 []
     143 [-]: MOVE R0 R66  
     144 [-]: NEWCLOSURE R68 P9
     145 [-]: MOVE R1 R29  
     146 [-]: MOVE R1 R32  
     147 [-]: MOVE R0 R66  
     148 [-]: MOVE R1 R55  
     149 [-]: MOVE R0 R63  
     150 [-]: MOVE R0 R64  
     151 [-]: MOVE R0 R65  
     152 [-]: NEWCLOSURE R69 P10
     153 [-]: MOVE R0 R35  
     154 [-]: MOVE R1 R25  
     155 [-]: MOVE R1 R30  
     156 [-]: MOVE R1 R34  
     157 [-]: MOVE R1 R32  
     158 [-]: MOVE R0 R68  
     159 [-]: MOVE R1 R29  
     160 [-]: MOVE R1 R55  
     161 [-]: MOVE R1 R15  
     162 [-]: SETGLOBAL R69 K33 ["OnConfirmCommitFocusChanges"]
     163 [-]: DUPCLOSURE R69 K34 []
     164 [-]: MOVE R0 R62  
     165 [-]: MOVE R0 R1   
     166 [-]: SETGLOBAL R69 K35 ["ConfirmCommitFocusChanges"]
     167 [-]: NEWCLOSURE R55 P12
     168 [-]: MOVE R1 R29  
     169 [-]: MOVE R1 R9   
     170 [-]: MOVE R0 R1   
     171 [-]: MOVE R1 R22  
     172 [-]: MOVE R1 R13  
     173 [-]: MOVE R1 R15  
     174 [-]: NEWCLOSURE R69 P13
     175 [-]: MOVE R1 R55  
     176 [-]: SETGLOBAL R69 K36 ["TransitionOut"]
     177 [-]: NEWCLOSURE R69 P14
     178 [-]: MOVE R1 R55  
     179 [-]: NEWCLOSURE R70 P15
     180 [-]: MOVE R1 R16  
     181 [-]: MOVE R1 R53  
     182 [-]: MOVE R1 R27  
     183 [-]: MOVE R1 R25  
     184 [-]: MOVE R1 R23  
     185 [-]: MOVE R0 R3   
     186 [-]: MOVE R1 R7   
     187 [-]: MOVE R1 R60  
     188 [-]: MOVE R1 R57  
     189 [-]: MOVE R1 R59  
     190 [-]: MOVE R1 R24  
     191 [-]: MOVE R0 R1   
     192 [-]: SETGLOBAL R70 K37 ["OpenFocusStore"]
     193 [-]: NEWCLOSURE R70 P16
     194 [-]: MOVE R1 R16  
     195 [-]: MOVE R1 R23  
     196 [-]: SETGLOBAL R70 K38 ["ShowFocusStoreTip"]
     197 [-]: DUPCLOSURE R70 K39 []
     198 [-]: SETGLOBAL R70 K40 ["HideFocusStoreTip"]
     199 [-]: NEWCLOSURE R70 P18
     200 [-]: MOVE R0 R3   
     201 [-]: MOVE R1 R50  
     202 [-]: MOVE R1 R16  
     203 [-]: MOVE R0 R67  
     204 [-]: MOVE R0 R1   
     205 [-]: MOVE R1 R25  
     206 [-]: MOVE R1 R55  
     207 [-]: DUPCLOSURE R71 K41 []
     208 [-]: NEWCLOSURE R72 P20
     209 [-]: MOVE R1 R51  
     210 [-]: MOVE R1 R59  
     211 [-]: MOVE R1 R52  
     212 [-]: NEWCLOSURE R73 P21
     213 [-]: MOVE R1 R18  
     214 [-]: NEWCLOSURE R74 P22
     215 [-]: MOVE R1 R30  
     216 [-]: MOVE R1 R29  
     217 [-]: DUPCLOSURE R75 K42 []
     218 [-]: MOVE R0 R44  
     219 [-]: NEWCLOSURE R76 P24
     220 [-]: MOVE R0 R1   
     221 [-]: MOVE R1 R38  
     222 [-]: NEWCLOSURE R57 P25
     223 [-]: MOVE R1 R27  
     224 [-]: MOVE R1 R26  
     225 [-]: MOVE R0 R1   
     226 [-]: NEWCLOSURE R77 P26
     227 [-]: MOVE R1 R17  
     228 [-]: MOVE R0 R45  
     229 [-]: MOVE R1 R58  
     230 [-]: MOVE R1 R7   
     231 [-]: NEWCLOSURE R78 P27
     232 [-]: MOVE R1 R30  
     233 [-]: MOVE R0 R0   
     234 [-]: NEWCLOSURE R79 P28
     235 [-]: MOVE R1 R9   
     236 [-]: MOVE R1 R20  
     237 [-]: MOVE R1 R27  
     238 [-]: MOVE R0 R76  
     239 [-]: MOVE R1 R11  
     240 [-]: MOVE R1 R46  
     241 [-]: MOVE R1 R47  
     242 [-]: MOVE R1 R57  
     243 [-]: MOVE R0 R1   
     244 [-]: MOVE R0 R2   
     245 [-]: MOVE R0 R45  
     246 [-]: MOVE R0 R71  
     247 [-]: MOVE R0 R74  
     248 [-]: MOVE R0 R78  
     249 [-]: MOVE R0 R72  
     250 [-]: MOVE R0 R77  
     251 [-]: SETGLOBAL R79 K43 ["StartRankUp"]
     252 [-]: NEWCLOSURE R79 P29
     253 [-]: MOVE R1 R11  
     254 [-]: NEWCLOSURE R80 P30
     255 [-]: MOVE R1 R21  
     256 [-]: MOVE R1 R15  
     257 [-]: MOVE R1 R55  
     258 [-]: SETGLOBAL R80 K44 ["GotoPolarity"]
     259 [-]: NEWCLOSURE R80 P31
     260 [-]: MOVE R0 R1   
     261 [-]: MOVE R0 R70  
     262 [-]: MOVE R1 R59  
     263 [-]: MOVE R0 R72  
     264 [-]: MOVE R1 R50  
     265 [-]: MOVE R1 R23  
     266 [-]: MOVE R1 R12  
     267 [-]: MOVE R1 R31  
     268 [-]: MOVE R0 R2   
     269 [-]: MOVE R1 R51  
     270 [-]: MOVE R0 R3   
     271 [-]: MOVE R1 R49  
     272 [-]: NEWCLOSURE R81 P32
     273 [-]: MOVE R1 R42  
     274 [-]: MOVE R1 R43  
     275 [-]: NEWCLOSURE R82 P33
     276 [-]: MOVE R0 R1   
     277 [-]: MOVE R0 R81  
     278 [-]: MOVE R1 R10  
     279 [-]: DUPCLOSURE R83 K45 []
     280 [-]: MOVE R0 R1   
     281 [-]: NEWCLOSURE R84 P35
     282 [-]: MOVE R0 R1   
     283 [-]: MOVE R1 R18  
     284 [-]: MOVE R0 R0   
     285 [-]: MOVE R0 R83  
     286 [-]: MOVE R1 R19  
     287 [-]: MOVE R0 R71  
     288 [-]: NEWCLOSURE R56 P36
     289 [-]: MOVE R1 R56  
     290 [-]: NEWCLOSURE R85 P37
     291 [-]: MOVE R1 R28  
     292 [-]: MOVE R0 R1   
     293 [-]: MOVE R0 R85  
     294 [-]: NEWCLOSURE R86 P38
     295 [-]: MOVE R1 R50  
     296 [-]: NEWCLOSURE R87 P39
     297 [-]: MOVE R1 R25  
     298 [-]: MOVE R0 R86  
     299 [-]: MOVE R1 R18  
     300 [-]: MOVE R0 R84  
     301 [-]: MOVE R1 R19  
     302 [-]: MOVE R0 R73  
     303 [-]: MOVE R1 R20  
     304 [-]: MOVE R1 R28  
     305 [-]: MOVE R1 R56  
     306 [-]: MOVE R0 R85  
     307 [-]: MOVE R1 R21  
     308 [-]: NEWCLOSURE R88 P40
     309 [-]: MOVE R1 R18  
     310 [-]: MOVE R1 R11  
     311 [-]: MOVE R1 R41  
     312 [-]: MOVE R1 R20  
     313 [-]: MOVE R0 R79  
     314 [-]: MOVE R1 R21  
     315 [-]: NEWCLOSURE R89 P41
     316 [-]: MOVE R1 R36  
     317 [-]: MOVE R1 R9   
     318 [-]: NEWCLOSURE R90 P42
     319 [-]: MOVE R1 R27  
     320 [-]: MOVE R1 R37  
     321 [-]: MOVE R1 R57  
     322 [-]: MOVE R0 R1   
     323 [-]: MOVE R1 R36  
     324 [-]: MOVE R1 R9   
     325 [-]: SETGLOBAL R90 K46 ["OnShardsConverted"]
     326 [-]: DUPCLOSURE R90 K47 []
     327 [-]: MOVE R0 R89  
     328 [-]: SETGLOBAL R90 K48 ["OnConvertConfirm"]
     329 [-]: NEWCLOSURE R90 P44
     330 [-]: MOVE R1 R37  
     331 [-]: MOVE R1 R36  
     332 [-]: MOVE R0 R1   
     333 [-]: MOVE R1 R23  
     334 [-]: SETGLOBAL R90 K49 ["ShowShardConversion"]
     335 [-]: NEWCLOSURE R60 P45
     336 [-]: MOVE R1 R13  
     337 [-]: MOVE R1 R14  
     338 [-]: NEWCLOSURE R90 P46
     339 [-]: MOVE R1 R53  
     340 [-]: MOVE R1 R60  
     341 [-]: NEWCLOSURE R91 P47
     342 [-]: MOVE R1 R12  
     343 [-]: MOVE R0 R3   
     344 [-]: MOVE R1 R31  
     345 [-]: MOVE R0 R1   
     346 [-]: MOVE R0 R90  
     347 [-]: MOVE R1 R36  
     348 [-]: MOVE R1 R53  
     349 [-]: SETGLOBAL R91 K50 ["ConvertShards"]
     350 [-]: NEWCLOSURE R91 P48
     351 [-]: MOVE R1 R13  
     352 [-]: MOVE R1 R18  
     353 [-]: MOVE R0 R1   
     354 [-]: SETGLOBAL R91 K51 ["SetWayActive"]
     355 [-]: NEWCLOSURE R91 P49
     356 [-]: MOVE R0 R86  
     357 [-]: MOVE R1 R25  
     358 [-]: MOVE R0 R70  
     359 [-]: SETGLOBAL R91 K52 ["ActiveWayChanged"]
     360 [-]: DUPCLOSURE R91 K53 []
     361 [-]: MOVE R0 R45  
     362 [-]: NEWCLOSURE R92 P51
     363 [-]: MOVE R1 R8   
     364 [-]: MOVE R1 R7   
     365 [-]: MOVE R1 R32  
     366 [-]: MOVE R1 R33  
     367 [-]: MOVE R0 R68  
     368 [-]: MOVE R1 R11  
     369 [-]: MOVE R0 R48  
     370 [-]: MOVE R1 R41  
     371 [-]: MOVE R1 R43  
     372 [-]: MOVE R1 R42  
     373 [-]: MOVE R0 R75  
     374 [-]: MOVE R0 R91  
     375 [-]: MOVE R1 R38  
     376 [-]: MOVE R1 R59  
     377 [-]: MOVE R1 R54  
     378 [-]: MOVE R1 R20  
     379 [-]: SETGLOBAL R92 K54 ["Update"]
     380 [-]: NEWCLOSURE R92 P52
     381 [-]: MOVE R1 R17  
     382 [-]: MOVE R1 R11  
     383 [-]: SETGLOBAL R92 K55 ["onKeyDown_MENU_CLICK"]
     384 [-]: NEWCLOSURE R92 P53
     385 [-]: MOVE R1 R11  
     386 [-]: SETGLOBAL R92 K56 ["onKeyUp_MENU_CLICK"]
     387 [-]: NEWCLOSURE R92 P54
     388 [-]: MOVE R0 R1   
     389 [-]: MOVE R1 R9   
     390 [-]: NEWCLOSURE R93 P55
     391 [-]: MOVE R1 R50  
     392 [-]: MOVE R0 R61  
     393 [-]: MOVE R1 R12  
     394 [-]: MOVE R1 R7   
     395 [-]: MOVE R1 R10  
     396 [-]: MOVE R0 R6   
     397 [-]: MOVE R1 R13  
     398 [-]: MOVE R1 R14  
     399 [-]: MOVE R0 R1   
     400 [-]: MOVE R0 R82  
     401 [-]: MOVE R1 R52  
     402 [-]: MOVE R1 R25  
     403 [-]: MOVE R0 R5   
     404 [-]: MOVE R1 R23  
     405 [-]: MOVE R1 R24  
     406 [-]: MOVE R1 R59  
     407 [-]: MOVE R1 R57  
     408 [-]: MOVE R1 R20  
     409 [-]: MOVE R0 R80  
     410 [-]: MOVE R1 R21  
     411 [-]: MOVE R0 R87  
     412 [-]: MOVE R0 R88  
     413 [-]: MOVE R0 R70  
     414 [-]: MOVE R0 R92  
     415 [-]: MOVE R1 R8   
     416 [-]: SETGLOBAL R93 K57 ["Initialize"]
     417 [-]: NEWCLOSURE R93 P56
     418 [-]: MOVE R1 R22  
     419 [-]: SETGLOBAL R93 K58 ["SetCallBack"]
     420 [-]: NEWCLOSURE R93 P57
     421 [-]: MOVE R1 R55  
     422 [-]: SETGLOBAL R93 K59 ["Close"]
     423 [-]: DUPCLOSURE R93 K60 []
     424 [-]: MOVE R0 R69  
     425 [-]: SETGLOBAL R93 K61 ["ExitScreen"]
     426 [-]: NEWCLOSURE R93 P59
     427 [-]: MOVE R1 R9   
     428 [-]: MOVE R1 R20  
     429 [-]: SETGLOBAL R93 K62 ["onKeyUp_MENU_SELECT"]
     430 [-]: DUPCLOSURE R93 K63 []
     431 [-]: MOVE R0 R82  
     432 [-]: SETGLOBAL R93 K64 ["onViewportSizeChanged"]
     433 [-]: NEWCLOSURE R93 P61
     434 [-]: MOVE R1 R20  
     435 [-]: SETGLOBAL R93 K65 ["NodeFocused"]
     436 [-]: NEWCLOSURE R93 P62
     437 [-]: MOVE R1 R20  
     438 [-]: SETGLOBAL R93 K66 ["NodeUnfocused"]
     439 [-]: NEWCLOSURE R93 P63
     440 [-]: MOVE R1 R9   
     441 [-]: MOVE R1 R20  
     442 [-]: SETGLOBAL R93 K67 ["NodeSelected"]
     443 [-]: NEWCLOSURE R93 P64
     444 [-]: MOVE R1 R9   
     445 [-]: MOVE R1 R20  
     446 [-]: SETGLOBAL R93 K68 ["NodePressed"]
     447 [-]: NEWCLOSURE R93 P65
     448 [-]: MOVE R1 R21  
     449 [-]: SETGLOBAL R93 K69 ["UniversalNodeFocused"]
     450 [-]: NEWCLOSURE R93 P66
     451 [-]: MOVE R1 R21  
     452 [-]: SETGLOBAL R93 K70 ["UniversalNodeUnfocused"]
     453 [-]: NEWCLOSURE R93 P67
     454 [-]: MOVE R1 R9   
     455 [-]: MOVE R1 R21  
     456 [-]: SETGLOBAL R93 K71 ["UniversalNodeSelected"]
     457 [-]: NEWCLOSURE R93 P68
     458 [-]: MOVE R1 R9   
     459 [-]: MOVE R1 R21  
     460 [-]: SETGLOBAL R93 K72 ["UniversalNodePressed"]
     461 [-]: NEWCLOSURE R93 P69
     462 [-]: MOVE R1 R20  
     463 [-]: SETGLOBAL R93 K73 ["SelectFocusedNode"]
     464 [-]: NEWCLOSURE R93 P70
     465 [-]: MOVE R1 R9   
     466 [-]: MOVE R1 R20  
     467 [-]: SETGLOBAL R93 K74 ["RankUpButtonReleased"]
     468 [-]: NEWCLOSURE R93 P71
     469 [-]: MOVE R1 R39  
     470 [-]: MOVE R1 R31  
     471 [-]: MOVE R1 R29  
     472 [-]: MOVE R1 R27  
     473 [-]: MOVE R1 R57  
     474 [-]: MOVE R1 R20  
     475 [-]: MOVE R0 R1   
     476 [-]: MOVE R0 R2   
     477 [-]: MOVE R1 R7   
     478 [-]: MOVE R0 R77  
     479 [-]: SETGLOBAL R93 K75 ["OnConfirmUniversalizeUpgrade"]
     480 [-]: NEWCLOSURE R93 P72
     481 [-]: MOVE R1 R9   
     482 [-]: MOVE R1 R20  
     483 [-]: MOVE R1 R52  
     484 [-]: MOVE R0 R1   
     485 [-]: MOVE R1 R27  
     486 [-]: MOVE R0 R76  
     487 [-]: MOVE R0 R74  
     488 [-]: MOVE R1 R57  
     489 [-]: MOVE R0 R2   
     490 [-]: MOVE R0 R45  
     491 [-]: MOVE R1 R7   
     492 [-]: MOVE R0 R77  
     493 [-]: MOVE R0 R70  
     494 [-]: SETGLOBAL R93 K76 ["UnlockUpgrade"]
     495 [-]: NEWCLOSURE R93 P73
     496 [-]: MOVE R1 R39  
     497 [-]: MOVE R0 R1   
     498 [-]: NEWCLOSURE R94 P74
     499 [-]: MOVE R1 R40  
     500 [-]: MOVE R0 R93  
     501 [-]: SETGLOBAL R94 K77 ["OnUniversalResourceSelected"]
     502 [-]: NEWCLOSURE R94 P75
     503 [-]: MOVE R1 R9   
     504 [-]: MOVE R1 R20  
     505 [-]: MOVE R1 R27  
     506 [-]: MOVE R0 R1   
     507 [-]: MOVE R1 R12  
     508 [-]: MOVE R1 R31  
     509 [-]: MOVE R1 R39  
     510 [-]: MOVE R0 R93  
     511 [-]: MOVE R0 R90  
     512 [-]: MOVE R1 R40  
     513 [-]: MOVE R1 R53  
     514 [-]: SETGLOBAL R94 K78 ["Universalize"]
     515 [-]: NEWCLOSURE R94 P76
     516 [-]: MOVE R1 R55  
     517 [-]: SETGLOBAL R94 K79 ["onKeyDown_HIDE_PAUSE_MENU"]
     518 [-]: DUPCLOSURE R94 K80 []
     519 [-]: MOVE R0 R1   
     520 [-]: SETGLOBAL R94 K81 ["RollOver"]
     521 [-]: LOADNIL R94  
     522 [-]: NEWCLOSURE R95 P78
     523 [-]: MOVE R1 R17  
     524 [-]: MOVE R1 R58  
     525 [-]: MOVE R1 R94  
     526 [-]: MOVE R0 R45  
     527 [-]: MOVE R0 R91  
     528 [-]: DUPCLOSURE R96 K82 []
     529 [-]: MOVE R0 R95  
     530 [-]: SETGLOBAL R96 K83 ["onKeyDown_MENU_MOUSE_Z"]
     531 [-]: DUPCLOSURE R96 K84 []
     532 [-]: MOVE R0 R95  
     533 [-]: SETGLOBAL R96 K85 ["onKeyDown_MENU_PINCH_DELTA"]
     534 [-]: NEWCLOSURE R96 P81
     535 [-]: MOVE R1 R9   
     536 [-]: SETGLOBAL R96 K86 ["IsInputBlocked"]
     537 [-]: DUPCLOSURE R96 K87 []
     538 [-]: MOVE R0 R48  
     539 [-]: SETGLOBAL R96 K88 ["onKeyDown_MENU_RIGHT_X"]
     540 [-]: DUPCLOSURE R96 K89 []
     541 [-]: MOVE R0 R48  
     542 [-]: SETGLOBAL R96 K90 ["onKeyUp_MENU_RIGHT_X"]
     543 [-]: DUPCLOSURE R96 K91 []
     544 [-]: MOVE R0 R48  
     545 [-]: SETGLOBAL R96 K92 ["onKeyDown_MENU_RIGHT_Y"]
     546 [-]: DUPCLOSURE R96 K93 []
     547 [-]: MOVE R0 R48  
     548 [-]: SETGLOBAL R96 K94 ["onKeyUp_MENU_RIGHT_Y"]
     549 [-]: NEWCLOSURE R96 P86
     550 [-]: MOVE R0 R70  
     551 [-]: MOVE R1 R20  
     552 [-]: MOVE R0 R78  
     553 [-]: MOVE R1 R21  
     554 [-]: SETGLOBAL R96 K95 ["OnGamepadTransition"]
     555 [-]: DUPCLOSURE R96 K96 []
     556 [-]: SETGLOBAL R96 K97 ["SupportsThemes"]
     557 [-]: DUPCLOSURE R96 K98 []
     558 [-]: MOVE R0 R61  
     559 [-]: SETGLOBAL R96 K99 ["OnStyleChangedCallback"]
     560 [-]: CLOSEUPVALS R7
     561 [-]: RETURN R0 0  


; Name:            
; Defined at line: 133
; #Upvalues:       5
; #Parameters:     0
; Is_vararg:       0
; Max Stack Size:  9

       0 [-]: DUPTABLE R0 7
       1 [-]: GETUPVAL R2 1
       2 [-]: GETTABLEKS R1 R2 K8 [0x5D10207D]
       3 [-]: LOADN R2 10  
       4 [-]: LOADB R3 0   
       5 [-]: CALL R1 2 1  
       6 [-]: SETTABLEKS R1 R0 K0 ["FloatingContentHighlightColor"]
       7 [-]: GETUPVAL R2 1
       8 [-]: GETTABLEKS R1 R2 K8 [0x5D10207D]
       9 [-]: LOADN R2 12  
      10 [-]: LOADB R3 0   
      11 [-]: CALL R1 2 1  
      12 [-]: SETTABLEKS R1 R0 K1 ["NegativeColor"]
      13 [-]: GETUPVAL R2 1
      14 [-]: GETTABLEKS R1 R2 K8 [0x5D10207D]
      15 [-]: LOADN R2 9   
      16 [-]: LOADB R3 1   
      17 [-]: CALL R1 2 1  
      18 [-]: SETTABLEKS R1 R0 K2 ["FloatingContent"]
      19 [-]: GETUPVAL R2 1
      20 [-]: GETTABLEKS R1 R2 K8 [0x5D10207D]
      21 [-]: LOADN R2 6   
      22 [-]: LOADB R3 1   
      23 [-]: CALL R1 2 1  
      24 [-]: SETTABLEKS R1 R0 K3 ["Content"]
      25 [-]: GETUPVAL R2 1
      26 [-]: GETTABLEKS R1 R2 K8 [0x5D10207D]
      27 [-]: LOADN R2 2   
      28 [-]: LOADB R3 1   
      29 [-]: CALL R1 2 1  
      30 [-]: SETTABLEKS R1 R0 K4 ["Background1"]
      31 [-]: GETUPVAL R2 1
      32 [-]: GETTABLEKS R1 R2 K8 [0x5D10207D]
      33 [-]: LOADN R2 4   
      34 [-]: LOADB R3 1   
      35 [-]: CALL R1 2 1  
      36 [-]: SETTABLEKS R1 R0 K5 ["Background3"]
      37 [-]: GETUPVAL R2 1
      38 [-]: GETTABLEKS R1 R2 K8 [0x5D10207D]
      39 [-]: LOADN R2 5   
      40 [-]: LOADB R3 1   
      41 [-]: CALL R1 2 1  
      42 [-]: SETTABLEKS R1 R0 K6 ["Background4"]
      43 [-]: SETUPVAL R0 0
      44 [-]: GETUPVAL R0 0
      45 [-]: GETUPVAL R2 0
      46 [-]: GETTABLEKS R1 R2 K0 ["FloatingContentHighlightColor"]
      47 [-]: NAMECALL R1 R1 K9 [0xA5D5C8F6]
      48 [-]: CALL R1 1 1  
      49 [-]: SETTABLEKS R1 R0 K10 ["FloatingContentHighlight"]
      50 [-]: GETUPVAL R0 0
      51 [-]: GETUPVAL R2 0
      52 [-]: GETTABLEKS R1 R2 K1 ["NegativeColor"]
      53 [-]: NAMECALL R1 R1 K9 [0xA5D5C8F6]
      54 [-]: CALL R1 1 1  
      55 [-]: SETTABLEKS R1 R0 K11 ["Negative"]
      56 [-]: GETUPVAL R0 0
      57 [-]: GETUPVAL R2 2
      58 [-]: GETTABLEKS R1 R2 K12 [0x9F57DD7D]
      59 [-]: GETUPVAL R3 0
      60 [-]: GETTABLEKS R2 R3 K2 ["FloatingContent"]
      61 [-]: CALL R1 1 1  
      62 [-]: SETTABLEKS R1 R0 K13 ["FloatingContentHex"]
      63 [-]: GETUPVAL R0 0
      64 [-]: GETUPVAL R2 2
      65 [-]: GETTABLEKS R1 R2 K12 [0x9F57DD7D]
      66 [-]: GETUPVAL R3 0
      67 [-]: GETTABLEKS R2 R3 K10 ["FloatingContentHighlight"]
      68 [-]: CALL R1 1 1  
      69 [-]: SETTABLEKS R1 R0 K14 ["FloatingContentHighlightHex"]
      70 [-]: GETUPVAL R0 0
      71 [-]: GETUPVAL R2 2
      72 [-]: GETTABLEKS R1 R2 K12 [0x9F57DD7D]
      73 [-]: GETUPVAL R3 0
      74 [-]: GETTABLEKS R2 R3 K3 ["Content"]
      75 [-]: CALL R1 1 1  
      76 [-]: SETTABLEKS R1 R0 K15 ["ContentHex"]
      77 [-]: GETUPVAL R0 0
      78 [-]: GETUPVAL R2 2
      79 [-]: GETTABLEKS R1 R2 K12 [0x9F57DD7D]
      80 [-]: GETUPVAL R3 0
      81 [-]: GETTABLEKS R2 R3 K11 ["Negative"]
      82 [-]: CALL R1 1 1  
      83 [-]: SETTABLEKS R1 R0 K16 ["NegativeHex"]
      84 [-]: GETUPVAL R0 0
      85 [-]: GETUPVAL R2 2
      86 [-]: GETTABLEKS R1 R2 K17 [0x8BCD12B6]
      87 [-]: GETUPVAL R3 0
      88 [-]: GETTABLEKS R2 R3 K5 ["Background3"]
      89 [-]: CALL R1 1 1  
      90 [-]: SETTABLEKS R1 R0 K18 ["Background1RGB"]
      91 [-]: GETUPVAL R0 0
      92 [-]: GETUPVAL R2 2
      93 [-]: GETTABLEKS R1 R2 K17 [0x8BCD12B6]
      94 [-]: GETUPVAL R3 1
      95 [-]: GETTABLEKS R2 R3 K8 [0x5D10207D]
      96 [-]: LOADN R3 3   
      97 [-]: LOADB R4 1   
      98 [-]: CALL R2 2 -1 
      99 [-]: CALL R1 -1 1 
     100 [-]: SETTABLEKS R1 R0 K19 ["Background2RGB"]
     101 [-]: GETUPVAL R0 0
     102 [-]: GETUPVAL R2 2
     103 [-]: GETTABLEKS R1 R2 K17 [0x8BCD12B6]
     104 [-]: GETUPVAL R3 0
     105 [-]: GETTABLEKS R2 R3 K4 ["Background1"]
     106 [-]: CALL R1 1 1  
     107 [-]: SETTABLEKS R1 R0 K20 ["Background3RGB"]
     108 [-]: GETUPVAL R0 0
     109 [-]: GETUPVAL R2 0
     110 [-]: GETTABLEKS R1 R2 K5 ["Background3"]
     111 [-]: SETTABLEKS R1 R0 K21 ["InkColor"]
     112 [-]: GETIMPORT R2 23 [0x0032441C]
     113 [-]: GETTABLEKS R1 R2 K24 ["CurrStyle"]
     114 [-]: FASTCALL1 62 R1 L0
     115 [-]: GETIMPORT R0 26 [0x7B998233]
     116 [-]: CALL R0 1 1  
L 0: 117 [-]: JUMPIF R0 L3 
     118 [-]: GETIMPORT R3 23 [0x0032441C]
     119 [-]: GETTABLEKS R2 R3 K24 ["CurrStyle"]
     120 [-]: GETTABLEKS R1 R2 K27 ["Style"]
     121 [-]: FASTCALL1 62 R1 L1
     122 [-]: GETIMPORT R0 26 [0x7B998233]
     123 [-]: CALL R0 1 1  
L 1: 124 [-]: JUMPIF R0 L3 
     125 [-]: GETIMPORT R2 23 [0x0032441C]
     126 [-]: GETTABLEKS R1 R2 K24 ["CurrStyle"]
     127 [-]: GETTABLEKS R0 R1 K27 ["Style"]
     128 [-]: NAMECALL R0 R0 K28 [0xED4E0128]
     129 [-]: CALL R0 1 1  
     130 [-]: JUMPXEQKS R0 K29 L2 ["/Lotus/Interface/Graphics/CustomUI/NidusStyle"]
     131 [-]: GETIMPORT R2 23 [0x0032441C]
     132 [-]: GETTABLEKS R1 R2 K24 ["CurrStyle"]
     133 [-]: GETTABLEKS R0 R1 K27 ["Style"]
     134 [-]: NAMECALL R0 R0 K28 [0xED4E0128]
     135 [-]: CALL R0 1 1  
     136 [-]: JUMPXEQKS R0 K30 L3 NOT ["/Lotus/Interface/Graphics/CustomUI/TennoStyle"]
L 2: 137 [-]: GETUPVAL R0 0
     138 [-]: GETUPVAL R2 0
     139 [-]: GETTABLEKS R1 R2 K6 ["Background4"]
     140 [-]: SETTABLEKS R1 R0 K21 ["InkColor"]
L 3: 141 [-]: GETIMPORT R0 32 [0xAE91E43B]
     142 [-]: GETUPVAL R3 0
     143 [-]: GETTABLEKS R2 R3 K4 ["Background1"]
     144 [-]: NAMECALL R0 R0 K33 [0xC6A10AB1]
     145 [-]: CALL R0 2 0  
     146 [-]: GETIMPORT R0 32 [0xAE91E43B]
     147 [-]: LOADK R2 K34 ["Bg"]
     148 [-]: LOADN R3 9   
     149 [-]: GETUPVAL R5 0
     150 [-]: GETTABLEKS R4 R5 K4 ["Background1"]
     151 [-]: NAMECALL R0 R0 K35 [0x67BC869F]
     152 [-]: CALL R0 4 0  
     153 [-]: GETIMPORT R0 32 [0xAE91E43B]
     154 [-]: LOADK R2 K36 ["Vignette"]
     155 [-]: LOADN R3 9   
     156 [-]: GETUPVAL R5 0
     157 [-]: GETTABLEKS R4 R5 K5 ["Background3"]
     158 [-]: NAMECALL R0 R0 K35 [0x67BC869F]
     159 [-]: CALL R0 4 0  
     160 [-]: GETIMPORT R0 32 [0xAE91E43B]
     161 [-]: LOADK R2 K34 ["Bg"]
     162 [-]: LOADK R3 K37 ["TintColor"]
     163 [-]: GETUPVAL R6 0
     164 [-]: GETTABLEKS R5 R6 K19 ["Background2RGB"]
     165 [-]: GETTABLEKS R4 R5 K38 ["r"]
     166 [-]: GETUPVAL R7 0
     167 [-]: GETTABLEKS R6 R7 K19 ["Background2RGB"]
     168 [-]: GETTABLEKS R5 R6 K39 ["g"]
     169 [-]: GETUPVAL R8 0
     170 [-]: GETTABLEKS R7 R8 K19 ["Background2RGB"]
     171 [-]: GETTABLEKS R6 R7 K40 ["b"]
     172 [-]: LOADN R7 1   
     173 [-]: NAMECALL R0 R0 K41 [0x91E13703]
     174 [-]: CALL R0 7 0  
     175 [-]: GETIMPORT R0 32 [0xAE91E43B]
     176 [-]: LOADK R2 K42 ["Title.Way"]
     177 [-]: LOADN R3 9   
     178 [-]: GETUPVAL R5 0
     179 [-]: GETTABLEKS R4 R5 K3 ["Content"]
     180 [-]: NAMECALL R0 R0 K35 [0x67BC869F]
     181 [-]: CALL R0 4 0  
     182 [-]: GETIMPORT R0 32 [0xAE91E43B]
     183 [-]: LOADK R2 K43 ["Title.CapTag"]
     184 [-]: LOADN R3 9   
     185 [-]: GETUPVAL R5 0
     186 [-]: GETTABLEKS R4 R5 K3 ["Content"]
     187 [-]: NAMECALL R0 R0 K35 [0x67BC869F]
     188 [-]: CALL R0 4 0  
     189 [-]: GETIMPORT R0 32 [0xAE91E43B]
     190 [-]: LOADK R2 K44 ["Title.Count"]
     191 [-]: LOADN R3 36  
     192 [-]: GETUPVAL R5 0
     193 [-]: GETTABLEKS R4 R5 K2 ["FloatingContent"]
     194 [-]: NAMECALL R0 R0 K35 [0x67BC869F]
     195 [-]: CALL R0 4 0  
     196 [-]: GETIMPORT R0 32 [0xAE91E43B]
     197 [-]: LOADK R2 K45 ["Title.Underline"]
     198 [-]: LOADN R3 9   
     199 [-]: GETUPVAL R5 0
     200 [-]: GETTABLEKS R4 R5 K2 ["FloatingContent"]
     201 [-]: NAMECALL R0 R0 K35 [0x67BC869F]
     202 [-]: CALL R0 4 0  
     203 [-]: GETIMPORT R0 32 [0xAE91E43B]
     204 [-]: LOADK R2 K46 ["Title.State"]
     205 [-]: LOADN R3 36  
     206 [-]: GETUPVAL R5 0
     207 [-]: GETTABLEKS R4 R5 K10 ["FloatingContentHighlight"]
     208 [-]: NAMECALL R0 R0 K35 [0x67BC869F]
     209 [-]: CALL R0 4 0  
     210 [-]: GETIMPORT R0 32 [0xAE91E43B]
     211 [-]: LOADK R2 K47 ["Title.Icon"]
     212 [-]: LOADN R3 9   
     213 [-]: GETUPVAL R5 0
     214 [-]: GETTABLEKS R4 R5 K10 ["FloatingContentHighlight"]
     215 [-]: NAMECALL R0 R0 K35 [0x67BC869F]
     216 [-]: CALL R0 4 0  
     217 [-]: GETIMPORT R0 32 [0xAE91E43B]
     218 [-]: LOADK R2 K48 ["Title.Watermark"]
     219 [-]: LOADN R3 9   
     220 [-]: GETUPVAL R5 0
     221 [-]: GETTABLEKS R4 R5 K5 ["Background3"]
     222 [-]: NAMECALL R0 R0 K35 [0x67BC869F]
     223 [-]: CALL R0 4 0  
     224 [-]: GETIMPORT R0 32 [0xAE91E43B]
     225 [-]: LOADK R2 K49 ["Title.Backer"]
     226 [-]: LOADN R3 9   
     227 [-]: GETUPVAL R5 0
     228 [-]: GETTABLEKS R4 R5 K4 ["Background1"]
     229 [-]: NAMECALL R0 R0 K35 [0x67BC869F]
     230 [-]: CALL R0 4 0  
     231 [-]: GETIMPORT R0 32 [0xAE91E43B]
     232 [-]: LOADK R2 K50 ["Tree.Image"]
     233 [-]: LOADN R3 9   
     234 [-]: GETUPVAL R5 0
     235 [-]: GETTABLEKS R4 R5 K5 ["Background3"]
     236 [-]: NAMECALL R0 R0 K35 [0x67BC869F]
     237 [-]: CALL R0 4 0  
     238 [-]: GETIMPORT R0 32 [0xAE91E43B]
     239 [-]: LOADK R2 K51 ["RightContainer.UniversalList.Title"]
     240 [-]: LOADN R3 9   
     241 [-]: GETUPVAL R5 0
     242 [-]: GETTABLEKS R4 R5 K3 ["Content"]
     243 [-]: NAMECALL R0 R0 K35 [0x67BC869F]
     244 [-]: CALL R0 4 0  
     245 [-]: GETIMPORT R0 32 [0xAE91E43B]
     246 [-]: LOADK R2 K52 ["RightContainer.UniversalList.Lines"]
     247 [-]: LOADN R3 9   
     248 [-]: GETUPVAL R5 0
     249 [-]: GETTABLEKS R4 R5 K2 ["FloatingContent"]
     250 [-]: NAMECALL R0 R0 K35 [0x67BC869F]
     251 [-]: CALL R0 4 0  
     252 [-]: GETIMPORT R0 32 [0xAE91E43B]
     253 [-]: LOADK R2 K53 ["RightContainer.UniversalList.Background"]
     254 [-]: LOADN R3 9   
     255 [-]: GETUPVAL R5 0
     256 [-]: GETTABLEKS R4 R5 K4 ["Background1"]
     257 [-]: NAMECALL R0 R0 K35 [0x67BC869F]
     258 [-]: CALL R0 4 0  
     259 [-]: GETIMPORT R0 32 [0xAE91E43B]
     260 [-]: LOADK R2 K54 ["RightContainer.UniversalList.Backer"]
     261 [-]: LOADK R3 K55 ["StartColor"]
     262 [-]: GETUPVAL R6 0
     263 [-]: GETTABLEKS R5 R6 K20 ["Background3RGB"]
     264 [-]: GETTABLEKS R4 R5 K38 ["r"]
     265 [-]: GETUPVAL R7 0
     266 [-]: GETTABLEKS R6 R7 K20 ["Background3RGB"]
     267 [-]: GETTABLEKS R5 R6 K39 ["g"]
     268 [-]: GETUPVAL R8 0
     269 [-]: GETTABLEKS R7 R8 K20 ["Background3RGB"]
     270 [-]: GETTABLEKS R6 R7 K40 ["b"]
     271 [-]: LOADK R7 K56 [0.84999999999999998]
     272 [-]: NAMECALL R0 R0 K41 [0x91E13703]
     273 [-]: CALL R0 7 0  
     274 [-]: GETIMPORT R0 32 [0xAE91E43B]
     275 [-]: LOADK R2 K54 ["RightContainer.UniversalList.Backer"]
     276 [-]: LOADK R3 K57 ["EndColor"]
     277 [-]: GETUPVAL R6 0
     278 [-]: GETTABLEKS R5 R6 K19 ["Background2RGB"]
     279 [-]: GETTABLEKS R4 R5 K38 ["r"]
     280 [-]: GETUPVAL R7 0
     281 [-]: GETTABLEKS R6 R7 K19 ["Background2RGB"]
     282 [-]: GETTABLEKS R5 R6 K39 ["g"]
     283 [-]: GETUPVAL R8 0
     284 [-]: GETTABLEKS R7 R8 K19 ["Background2RGB"]
     285 [-]: GETTABLEKS R6 R7 K40 ["b"]
     286 [-]: LOADN R7 1   
     287 [-]: NAMECALL R0 R0 K41 [0x91E13703]
     288 [-]: CALL R0 7 0  
     289 [-]: GETUPVAL R1 3
     290 [-]: FASTCALL1 62 R1 L4
     291 [-]: GETIMPORT R0 26 [0x7B998233]
     292 [-]: CALL R0 1 1  
L 4: 293 [-]: JUMPIF R0 L5 
     294 [-]: GETUPVAL R0 3
     295 [-]: GETUPVAL R3 3
     296 [-]: GETTABLEKS R2 R3 K58 ["UpdateElementColor"]
     297 [-]: NAMECALL R0 R0 K59 [0xEA061E98]
     298 [-]: CALL R0 2 0  
L 5: 299 [-]: GETUPVAL R1 4
     300 [-]: FASTCALL1 62 R1 L6
     301 [-]: GETIMPORT R0 26 [0x7B998233]
     302 [-]: CALL R0 1 1  
L 6: 303 [-]: JUMPIF R0 L7 
     304 [-]: GETUPVAL R0 4
     305 [-]: GETUPVAL R3 4
     306 [-]: GETTABLEKS R2 R3 K58 ["UpdateElementColor"]
     307 [-]: NAMECALL R0 R0 K59 [0xEA061E98]
     308 [-]: CALL R0 2 0  
L 7: 309 [-]: RETURN R0 0  


; Name:            
; Defined at line: 198
; #Upvalues:       1
; #Parameters:     0
; Is_vararg:       0
; Max Stack Size:  3

       0 [-]: GETIMPORT R0 2 [0xE6B41ADB]
       1 [-]: CALL R0 0 1  
       2 [-]: JUMPIFNOT R0 L0
       3 [-]: GETIMPORT R0 4 [0x89326C93]
       4 [-]: NAMECALL R0 R0 K5 [0xFB64E76C]
       5 [-]: CALL R0 1 1  
       6 [-]: LOADB R2 0   
       7 [-]: NAMECALL R0 R0 K6 [0x97C4FF93]
       8 [-]: CALL R0 2 0  
L 0:   9 [-]: GETIMPORT R1 8 [0xBE190284]
      10 [-]: FASTCALL1 62 R1 L1
      11 [-]: GETIMPORT R0 10 [0x7B998233]
      12 [-]: CALL R0 1 1  
L 1:  13 [-]: JUMPIF R0 L2 
      14 [-]: GETIMPORT R0 8 [0xBE190284]
      15 [-]: LOADB R2 0   
      16 [-]: NAMECALL R0 R0 K11 [0xC02F2CB8]
      17 [-]: CALL R0 2 0  
L 2:  18 [-]: GETUPVAL R1 0
      19 [-]: FASTCALL1 62 R1 L3
      20 [-]: GETIMPORT R0 10 [0x7B998233]
      21 [-]: CALL R0 1 1  
L 3:  22 [-]: JUMPIF R0 L4 
      23 [-]: GETUPVAL R0 0
      24 [-]: NAMECALL R0 R0 K12 [0x32302B4A]
      25 [-]: CALL R0 1 0  
L 4:  26 [-]: GETIMPORT R0 14 ["_T"]
      27 [-]: LOADNIL R1   
      28 [-]: SETTABLEKS R1 R0 K15 ["gToolTip"]
      29 [-]: GETIMPORT R0 14 ["_T"]
      30 [-]: LOADNIL R1   
      31 [-]: SETTABLEKS R1 R0 K16 ["InfoPopup_Data"]
      32 [-]: GETIMPORT R0 14 ["_T"]
      33 [-]: LOADNIL R1   
      34 [-]: SETTABLEKS R1 R0 K17 ["InfoPopup_Grid"]
      35 [-]: RETURN R0 0  


; Name:            
; Defined at line: 215
; #Upvalues:       3
; #Parameters:     1
; Is_vararg:       0
; Max Stack Size:  21

       0 [-]: LOADK R1 K0 [""]
       1 [-]: NEWTABLE R2 0 0
       2 [-]: GETIMPORT R3 2 [0xCFC01047]
       3 [-]: GETUPVAL R4 0
       4 [-]: CALL R3 1 3  
       5 [-]: FORGPREP_NEXT R3 L2
L 0:   6 [-]: GETTABLEKS R8 R7 K3 ["Committed"]
       7 [-]: JUMPIFNOT R8 L1
       8 [-]: JUMPIF R0 L2 
L 1:   9 [-]: DUPTABLE R8 6
      10 [-]: GETTABLEKS R9 R7 K4 ["Focus"]
      11 [-]: SETTABLEKS R9 R8 K4 ["Focus"]
      12 [-]: GETTABLEKS R9 R7 K5 ["Name"]
      13 [-]: SETTABLEKS R9 R8 K5 ["Name"]
      14 [-]: FASTCALL2 52 R2 R8 L2
      15 [-]: MOVE R10 R2  
      16 [-]: MOVE R11 R8  
      17 [-]: GETIMPORT R9 9 [0x23D5322F]
      18 [-]: CALL R9 2 0  
L 2:  19 [-]: FORGLOOP R3 L0 2
      20 [-]: GETIMPORT R3 2 [0xCFC01047]
      21 [-]: GETUPVAL R4 1
      22 [-]: CALL R3 1 3  
      23 [-]: FORGPREP_NEXT R3 L7
L 3:  24 [-]: LOADB R8 0   
      25 [-]: LOADN R11 1  
      26 [-]: LENGTH R9 R2 
      27 [-]: LOADN R10 1  
      28 [-]: FORNPREP R9 L6
L 4:  29 [-]: GETTABLE R13 R2 R11
      30 [-]: GETTABLEKS R12 R13 K5 ["Name"]
      31 [-]: GETTABLEKS R13 R7 K5 ["Name"]
      32 [-]: JUMPIFNOTEQ R12 R13 L5
      33 [-]: GETTABLE R12 R2 R11
      34 [-]: GETTABLE R15 R2 R11
      35 [-]: GETTABLEKS R14 R15 K4 ["Focus"]
      36 [-]: GETTABLEKS R15 R7 K10 ["PointCost"]
      37 [-]: ADD R13 R14 R15
      38 [-]: SETTABLEKS R13 R12 K4 ["Focus"]
      39 [-]: LOADB R8 1   
      40 [-]: JUMP L6
     
L 5:  41 [-]: FORNLOOP R9 L4
L 6:  42 [-]: JUMPIF R8 L7 
      43 [-]: DUPTABLE R9 6
      44 [-]: GETTABLEKS R10 R7 K10 ["PointCost"]
      45 [-]: SETTABLEKS R10 R9 K4 ["Focus"]
      46 [-]: GETTABLEKS R10 R7 K5 ["Name"]
      47 [-]: SETTABLEKS R10 R9 K5 ["Name"]
      48 [-]: FASTCALL2 52 R2 R9 L7
      49 [-]: MOVE R11 R2  
      50 [-]: MOVE R12 R9  
      51 [-]: GETIMPORT R10 9 [0x23D5322F]
      52 [-]: CALL R10 2 0 
L 7:  53 [-]: FORGLOOP R3 L3 2
      54 [-]: GETIMPORT R3 2 [0xCFC01047]
      55 [-]: MOVE R4 R2   
      56 [-]: CALL R3 1 3  
      57 [-]: FORGPREP_NEXT R3 L9
L 8:  58 [-]: MOVE R8 R1   
      59 [-]: GETIMPORT R11 12 [0xAE91E43B]
      60 [-]: LOADK R13 K13 ["/Lotus/Language/TennoWay/CommitChangesLine"]
      61 [-]: LOADB R14 1  
      62 [-]: DUPTABLE R15 16
      63 [-]: GETUPVAL R17 2
      64 [-]: GETTABLEKS R16 R17 K17 [0x1142C7A8]
      65 [-]: GETTABLEKS R17 R7 K4 ["Focus"]
      66 [-]: LOADN R18 0  
      67 [-]: CALL R16 2 1 
      68 [-]: SETTABLEKS R16 R15 K14 ["NUM"]
      69 [-]: GETIMPORT R16 19 [0x5F0788C4]
      70 [-]: GETTABLEKS R17 R7 K5 ["Name"]
      71 [-]: CALL R16 1 1 
      72 [-]: SETTABLEKS R16 R15 K15 ["NAME"]
      73 [-]: NAMECALL R11 R11 K20 [0x42B04007]
      74 [-]: CALL R11 4 1 
      75 [-]: MOVE R9 R11  
      76 [-]: LOADK R10 K21 ["\r\n"]
      77 [-]: CONCAT R1 R8 R10
L 9:  78 [-]: FORGLOOP R3 L8 2
      79 [-]: NEWTABLE R3 0 0
      80 [-]: GETIMPORT R4 2 [0xCFC01047]
      81 [-]: GETUPVAL R5 1
      82 [-]: CALL R4 1 3  
      83 [-]: FORGPREP_NEXT R4 L14
L10:  84 [-]: LOADB R9 0   
      85 [-]: LOADN R12 1  
      86 [-]: LENGTH R10 R3
      87 [-]: LOADN R11 1  
      88 [-]: FORNPREP R10 L13
L11:  89 [-]: GETTABLEKS R13 R8 K22 ["resourceType"]
      90 [-]: GETTABLE R15 R3 R12
      91 [-]: GETTABLEKS R14 R15 K23 ["Type"]
      92 [-]: JUMPIFNOTEQ R13 R14 L12
      93 [-]: LOADB R9 1   
      94 [-]: GETTABLE R13 R3 R12
      95 [-]: GETTABLE R16 R3 R12
      96 [-]: GETTABLEKS R15 R16 K24 ["ItemCount"]
      97 [-]: GETTABLEKS R16 R8 K25 ["ResourceCost"]
      98 [-]: ADD R14 R15 R16
      99 [-]: SETTABLEKS R14 R13 K24 ["ItemCount"]
     100 [-]: JUMP L13
    
L12: 101 [-]: FORNLOOP R10 L11
L13: 102 [-]: JUMPIF R9 L14
     103 [-]: DUPTABLE R10 26
     104 [-]: GETTABLEKS R11 R8 K27 ["ResourceType"]
     105 [-]: SETTABLEKS R11 R10 K23 ["Type"]
     106 [-]: GETTABLEKS R11 R8 K25 ["ResourceCost"]
     107 [-]: SETTABLEKS R11 R10 K24 ["ItemCount"]
     108 [-]: GETTABLEKS R11 R8 K28 ["ResourceName"]
     109 [-]: SETTABLEKS R11 R10 K5 ["Name"]
     110 [-]: FASTCALL2 52 R3 R10 L14
     111 [-]: MOVE R12 R3  
     112 [-]: MOVE R13 R10 
     113 [-]: GETIMPORT R11 9 [0x23D5322F]
     114 [-]: CALL R11 2 0 
L14: 115 [-]: FORGLOOP R4 L10 2
     116 [-]: GETIMPORT R4 2 [0xCFC01047]
     117 [-]: MOVE R5 R3   
     118 [-]: CALL R4 1 3  
     119 [-]: FORGPREP_NEXT R4 L16
L15: 120 [-]: MOVE R9 R1   
     121 [-]: LOADK R10 K29 ["-"]
     122 [-]: GETIMPORT R17 31 [0x64FB1586]
     123 [-]: GETTABLEKS R18 R8 K24 ["ItemCount"]
     124 [-]: CALL R17 1 1 
     125 [-]: MOVE R11 R17 
     126 [-]: LOADK R12 K32 [" "]
     127 [-]: GETIMPORT R17 12 [0xAE91E43B]
     128 [-]: GETTABLEKS R19 R8 K5 ["Name"]
     129 [-]: LOADB R20 1  
     130 [-]: NAMECALL R17 R17 K20 [0x42B04007]
     131 [-]: CALL R17 3 1 
     132 [-]: MOVE R13 R17 
     133 [-]: LOADK R14 K32 [" "]
     134 [-]: GETIMPORT R17 12 [0xAE91E43B]
     135 [-]: LOADK R19 K33 ["/Lotus/Language/TennoWay/ForUniversal"]
     136 [-]: LOADB R20 0  
     137 [-]: NAMECALL R17 R17 K20 [0x42B04007]
     138 [-]: CALL R17 3 1 
     139 [-]: MOVE R15 R17 
     140 [-]: LOADK R16 K21 ["\r\n"]
     141 [-]: CONCAT R1 R9 R16
L16: 142 [-]: FORGLOOP R4 L15 2
     143 [-]: RETURN R1 1  


; Name:            
; Defined at line: 275
; #Upvalues:       3
; #Parameters:     0
; Is_vararg:       0
; Max Stack Size:  9

       0 [-]: NEWTABLE R0 0 0
       1 [-]: GETIMPORT R1 1 [0xCFC01047]
       2 [-]: GETUPVAL R2 0
       3 [-]: CALL R1 1 3  
       4 [-]: FORGPREP_NEXT R1 L2
L 0:   5 [-]: GETTABLEKS R6 R5 K2 ["Purchase"]
       6 [-]: JUMPIFNOT R6 L2
       7 [-]: GETTABLEKS R6 R5 K3 ["Purchased"]
       8 [-]: JUMPIF R6 L2 
       9 [-]: GETTABLEKS R8 R5 K4 ["Type"]
      10 [-]: FASTCALL2 52 R0 R8 L1
      11 [-]: MOVE R7 R0   
      12 [-]: GETIMPORT R6 7 [0x23D5322F]
      13 [-]: CALL R6 2 0  
L 1:  14 [-]: LOADB R6 1   
      15 [-]: SETTABLEKS R6 R5 K3 ["Purchased"]
L 2:  16 [-]: FORGLOOP R1 L0 2
      17 [-]: LENGTH R1 R0 
      18 [-]: LOADN R2 0   
      19 [-]: JUMPIFNOTLT R2 R1 L3
      20 [-]: GETIMPORT R1 9 [0x25D99D89]
      21 [-]: MOVE R3 R0   
      22 [-]: LOADK R4 K10 ["OnFocusCommitted"]
      23 [-]: NAMECALL R1 R1 K11 [0x926545CE]
      24 [-]: CALL R1 3 0  
      25 [-]: LOADB R1 1   
      26 [-]: SETUPVAL R1 1
      27 [-]: GETUPVAL R2 2
      28 [-]: LENGTH R3 R0 
      29 [-]: SUB R1 R2 R3 
      30 [-]: SETUPVAL R1 2
      31 [-]: LOADB R1 1   
      32 [-]: RETURN R1 1  
L 3:  33 [-]: LOADB R1 0   
      34 [-]: RETURN R1 1  


; Name:            
; Defined at line: 294
; #Upvalues:       4
; #Parameters:     0
; Is_vararg:       0
; Max Stack Size:  11

       0 [-]: NEWTABLE R0 0 0
       1 [-]: GETIMPORT R1 1 [0xCFC01047]
       2 [-]: GETUPVAL R2 0
       3 [-]: CALL R1 1 3  
       4 [-]: FORGPREP_NEXT R1 L2
L 0:   5 [-]: GETUPVAL R7 1
       6 [-]: GETTABLEKS R6 R7 K2 [0x74A11EC6]
       7 [-]: GETTABLEKS R7 R5 K3 ["Focus"]
       8 [-]: CALL R6 1 1  
       9 [-]: GETTABLEKS R7 R5 K4 ["Purchase"]
      10 [-]: JUMPIFNOT R7 L1
      11 [-]: GETTABLEKS R7 R5 K5 ["PurchaseCost"]
      12 [-]: SUB R6 R6 R7 
L 1:  13 [-]: LOADN R7 0   
      14 [-]: JUMPIFNOTLT R7 R6 L2
      15 [-]: GETIMPORT R7 8 [0x6E840F42]
      16 [-]: CALL R7 0 1  
      17 [-]: GETTABLEKS R8 R5 K9 ["Type"]
      18 [-]: SETTABLEKS R8 R7 K10 ["mItemType"]
      19 [-]: GETTABLEKS R8 R5 K11 ["Lvl"]
      20 [-]: SETTABLEKS R8 R7 K12 ["mLevel"]
      21 [-]: SETTABLEKS R6 R7 K13 ["mFocusXpCost"]
      22 [-]: FASTCALL2 52 R0 R7 L2
      23 [-]: MOVE R9 R0   
      24 [-]: MOVE R10 R7  
      25 [-]: GETIMPORT R8 16 [0x23D5322F]
      26 [-]: CALL R8 2 0  
L 2:  27 [-]: FORGLOOP R1 L0 2
      28 [-]: LENGTH R1 R0 
      29 [-]: LOADN R2 0   
      30 [-]: JUMPIFNOTLT R2 R1 L3
      31 [-]: GETIMPORT R1 18 [0x25D99D89]
      32 [-]: MOVE R3 R0   
      33 [-]: LOADK R4 K19 ["OnFocusCommitted"]
      34 [-]: NAMECALL R1 R1 K20 [0x1BA96361]
      35 [-]: CALL R1 3 0  
      36 [-]: LOADB R1 1   
      37 [-]: SETUPVAL R1 2
      38 [-]: GETUPVAL R2 3
      39 [-]: LENGTH R3 R0 
      40 [-]: SUB R1 R2 R3 
      41 [-]: SETUPVAL R1 3
      42 [-]: NEWTABLE R1 0 0
      43 [-]: SETUPVAL R1 0
      44 [-]: LOADB R1 1   
      45 [-]: RETURN R1 1  
L 3:  46 [-]: LOADB R1 0   
      47 [-]: RETURN R1 1  


; Name:            
; Defined at line: 323
; #Upvalues:       3
; #Parameters:     0
; Is_vararg:       0
; Max Stack Size:  10

       0 [-]: NEWTABLE R0 0 0
       1 [-]: NEWTABLE R1 0 0
       2 [-]: GETIMPORT R2 1 [0xCFC01047]
       3 [-]: GETUPVAL R3 0
       4 [-]: CALL R2 1 3  
       5 [-]: FORGPREP_NEXT R2 L2
L 0:   6 [-]: GETTABLEKS R9 R6 K2 ["Upgrade"]
       7 [-]: FASTCALL2 52 R1 R9 L1
       8 [-]: MOVE R8 R1   
       9 [-]: GETIMPORT R7 5 [0x23D5322F]
      10 [-]: CALL R7 2 0  
L 1:  11 [-]: GETTABLEKS R9 R6 K6 ["ResourceType"]
      12 [-]: FASTCALL2 52 R0 R9 L2
      13 [-]: MOVE R8 R0   
      14 [-]: GETIMPORT R7 5 [0x23D5322F]
      15 [-]: CALL R7 2 0  
L 2:  16 [-]: FORGLOOP R2 L0 2
      17 [-]: LENGTH R2 R1 
      18 [-]: LOADN R3 0   
      19 [-]: JUMPIFNOTLT R3 R2 L3
      20 [-]: GETIMPORT R2 8 [0x25D99D89]
      21 [-]: MOVE R4 R0   
      22 [-]: MOVE R5 R1   
      23 [-]: LOADK R6 K9 ["OnFocusCommitted"]
      24 [-]: NAMECALL R2 R2 K10 [0x92BAB8C4]
      25 [-]: CALL R2 4 0  
      26 [-]: LOADB R2 1   
      27 [-]: SETUPVAL R2 1
      28 [-]: GETUPVAL R3 2
      29 [-]: SUBK R2 R3 K11 [1]
      30 [-]: SETUPVAL R2 2
      31 [-]: LOADB R2 1   
      32 [-]: RETURN R2 1  
L 3:  33 [-]: LOADB R2 0   
      34 [-]: RETURN R2 1  


; Name:            
; Defined at line: 341
; #Upvalues:       10
; #Parameters:     2
; Is_vararg:       0
; Max Stack Size:  9

       0 [-]: JUMPIF R0 L1 
       1 [-]: GETUPVAL R2 0
       2 [-]: LOADB R3 1   
       3 [-]: CALL R2 1 1  
       4 [-]: GETUPVAL R4 1
       5 [-]: GETTABLEKS R3 R4 K0 [0xE0CBA3CA]
       6 [-]: GETIMPORT R4 2 [0xAE91E43B]
       7 [-]: LOADK R6 K3 ["/Lotus/Language/TennoWay/CommitFailed"]
       8 [-]: LOADB R7 0   
       9 [-]: DUPTABLE R8 5
      10 [-]: SETTABLEKS R2 R8 K4 ["LIST"]
      11 [-]: NAMECALL R4 R4 K6 [0x42B04007]
      12 [-]: CALL R4 4 -1 
      13 [-]: CALL R3 -1 0 
      14 [-]: NEWTABLE R3 0 0
      15 [-]: SETUPVAL R3 2
      16 [-]: NEWTABLE R3 0 0
      17 [-]: SETUPVAL R3 3
      18 [-]: LOADN R3 0   
      19 [-]: SETUPVAL R3 4
      20 [-]: NEWTABLE R3 0 0
      21 [-]: SETUPVAL R3 5
      22 [-]: GETIMPORT R3 9 ["BackgroundMovie"]
      23 [-]: JUMPXEQKNIL R3 L0
      24 [-]: GETIMPORT R3 9 ["BackgroundMovie"]
      25 [-]: LOADK R5 K10 ["ShowBlockingMessage"]
      26 [-]: LOADK R6 K11 ["0"]
      27 [-]: NAMECALL R3 R3 K12 [0xE4162EED]
      28 [-]: CALL R3 3 0  
L 0:  29 [-]: LOADB R3 0   
      30 [-]: SETUPVAL R3 6
      31 [-]: GETUPVAL R3 7
      32 [-]: CALL R3 0 0  
L 1:  33 [-]: NEWTABLE R2 0 0
      34 [-]: SETUPVAL R2 8
      35 [-]: LOADB R2 0   
      36 [-]: SETUPVAL R2 9
      37 [-]: RETURN R0 0  


; Name:            
; Defined at line: 364
; #Upvalues:       1
; #Parameters:     2
; Is_vararg:       0
; Max Stack Size:  11

       0 [-]: LOADN R2 0   
       1 [-]: LOADN R3 0   
       2 [-]: LOADN R6 1   
       3 [-]: GETUPVAL R7 0
       4 [-]: LENGTH R4 R7 
       5 [-]: LOADN R5 1   
       6 [-]: FORNPREP R4 L5
L 0:   7 [-]: JUMPIFNOT R0 L1
       8 [-]: GETUPVAL R9 0
       9 [-]: GETTABLE R8 R9 R6
      10 [-]: GETTABLEKS R7 R8 K0 ["mOtherPolarity"]
      11 [-]: JUMPIF R7 L4 
L 1:  12 [-]: GETUPVAL R9 0
      13 [-]: GETTABLE R8 R9 R6
      14 [-]: GETTABLEKS R7 R8 K1 ["mLocked"]
      15 [-]: JUMPIF R7 L3 
      16 [-]: JUMPIFNOT R1 L2
      17 [-]: GETUPVAL R9 0
      18 [-]: GETTABLE R8 R9 R6
      19 [-]: GETTABLEKS R7 R8 K2 ["mRank"]
      20 [-]: GETUPVAL R10 0
      21 [-]: GETTABLE R9 R10 R6
      22 [-]: GETTABLEKS R8 R9 K3 ["mMaxRank"]
      23 [-]: JUMPIFNOTEQ R7 R8 L3
L 2:  24 [-]: ADDK R2 R2 K4 [1]
L 3:  25 [-]: ADDK R3 R3 K4 [1]
L 4:  26 [-]: FORNLOOP R4 L0
L 5:  27 [-]: RETURN R2 2  


; Name:            
; Defined at line: 379
; #Upvalues:       1
; #Parameters:     0
; Is_vararg:       0
; Max Stack Size:  5

       0 [-]: LOADN R0 0   
       1 [-]: LOADN R1 0   
       2 [-]: GETUPVAL R2 0
       3 [-]: LOADB R3 1   
       4 [-]: LOADB R4 1   
       5 [-]: CALL R2 2 2  
       6 [-]: MOVE R1 R2   
       7 [-]: MOVE R0 R3   
       8 [-]: DIV R3 R1 R0 
       9 [-]: MULK R2 R3 K0 [100]
      10 [-]: RETURN R2 1  


; Name:            
; Defined at line: 387
; #Upvalues:       7
; #Parameters:     0
; Is_vararg:       0
; Max Stack Size:  8

       0 [-]: GETUPVAL R0 0
       1 [-]: JUMPXEQKN R0 K0 L4 NOT [0]
       2 [-]: LOADB R0 0   
       3 [-]: SETUPVAL R0 1
       4 [-]: GETIMPORT R0 3 ["BackgroundMovie"]
       5 [-]: JUMPXEQKNIL R0 L0
       6 [-]: GETIMPORT R0 3 ["BackgroundMovie"]
       7 [-]: LOADK R2 K4 ["ShowBlockingMessage"]
       8 [-]: LOADK R3 K5 ["0"]
       9 [-]: NAMECALL R0 R0 K6 [0xE4162EED]
      10 [-]: CALL R0 3 0  
L 0:  11 [-]: GETIMPORT R1 8 [0x89326C93]
      12 [-]: NAMECALL R1 R1 K9 [0xDED7D5CD]
      13 [-]: CALL R1 1 1  
      14 [-]: GETTABLEN R0 R1 1
      15 [-]: FASTCALL1 62 R0 L1
      16 [-]: MOVE R2 R0   
      17 [-]: GETIMPORT R1 11 [0x7B998233]
      18 [-]: CALL R1 1 1  
L 1:  19 [-]: JUMPIF R1 L3 
      20 [-]: LOADN R1 0   
      21 [-]: LOADN R2 0   
      22 [-]: GETUPVAL R3 2
      23 [-]: LOADB R4 0   
      24 [-]: CALL R3 1 2  
      25 [-]: MOVE R2 R3   
      26 [-]: MOVE R1 R4   
      27 [-]: GETIMPORT R3 14 [0x9AD21AE9]
      28 [-]: CALL R3 0 1  
      29 [-]: JUMPIFNOT R3 L2
      30 [-]: JUMPIFNOTEQ R2 R1 L2
      31 [-]: ADDK R2 R2 K15 [1]
L 2:  32 [-]: GETIMPORT R3 17 [0xBA7DFCD2]
      33 [-]: MOVE R5 R0   
      34 [-]: GETIMPORT R6 19 [0x0469F296]
      35 [-]: LOADK R7 K20 ["FOCUS_TREE_UNLOCK_COUNT"]
      36 [-]: CALL R6 1 1  
      37 [-]: MOVE R7 R2   
      38 [-]: NAMECALL R3 R3 K21 [0xDECE6848]
      39 [-]: CALL R3 4 0  
L 3:  40 [-]: GETIMPORT R1 22 ["_T"]
      41 [-]: LOADNIL R2   
      42 [-]: SETTABLEKS R2 R1 K23 ["Notifications_RefreshPolarities"]
      43 [-]: GETUPVAL R1 3
      44 [-]: CALL R1 0 0  
      45 [-]: RETURN R0 0  
L 4:  46 [-]: GETUPVAL R0 4
      47 [-]: CALL R0 0 1  
      48 [-]: JUMPIFNOT R0 L5
      49 [-]: RETURN R0 0  
L 5:  50 [-]: GETUPVAL R0 5
      51 [-]: CALL R0 0 1  
      52 [-]: JUMPIFNOT R0 L6
      53 [-]: RETURN R0 0  
L 6:  54 [-]: GETUPVAL R0 6
      55 [-]: CALL R0 0 1  
      56 [-]: JUMPIFNOT R0 L7
      57 [-]: RETURN R0 0  
L 7:  58 [-]: LOADN R0 0   
      59 [-]: SETUPVAL R0 0
      60 [-]: RETURN R0 0  


; Name:            
; Defined at line: 436
; #Upvalues:       9
; #Parameters:     1
; Is_vararg:       0
; Max Stack Size:  13

       0 [-]: GETIMPORT R1 1 [0x03F57322]
       1 [-]: MOVE R2 R0   
       2 [-]: CALL R1 1 1  
       3 [-]: LOADN R2 4   
       4 [-]: JUMPIFNOTEQ R1 R2 L7
       5 [-]: GETIMPORT R1 4 ["BackgroundMovie"]
       6 [-]: JUMPXEQKNIL R1 L0
       7 [-]: GETIMPORT R1 4 ["BackgroundMovie"]
       8 [-]: LOADK R3 K5 ["ShowBlockingMessage"]
       9 [-]: LOADK R4 K6 ["1"]
      10 [-]: NAMECALL R1 R1 K7 [0xE4162EED]
      11 [-]: CALL R1 3 0  
L 0:  12 [-]: GETUPVAL R2 0
      13 [-]: GETUPVAL R3 1
      14 [-]: GETTABLE R1 R2 R3
      15 [-]: GETIMPORT R2 9 [0xCFC01047]
      16 [-]: GETUPVAL R3 2
      17 [-]: CALL R2 1 3  
      18 [-]: FORGPREP_NEXT R2 L4
L 1:  19 [-]: GETTABLEKS R7 R6 K10 ["Purchase"]
      20 [-]: JUMPIF R7 L2 
      21 [-]: GETTABLEKS R7 R6 K11 ["Upgraded"]
      22 [-]: JUMPIFNOT R7 L4
L 2:  23 [-]: GETUPVAL R8 3
      24 [-]: GETTABLE R7 R8 R1
      25 [-]: JUMPXEQKNIL R7 L3 NOT
      26 [-]: GETUPVAL R7 3
      27 [-]: LOADN R8 0   
      28 [-]: SETTABLE R8 R7 R1
L 3:  29 [-]: GETUPVAL R7 3
      30 [-]: GETUPVAL R10 3
      31 [-]: GETTABLE R9 R10 R1
      32 [-]: GETTABLEKS R10 R6 K12 ["Focus"]
      33 [-]: ADD R8 R9 R10
      34 [-]: SETTABLE R8 R7 R1
L 4:  35 [-]: FORGLOOP R2 L1 2
      36 [-]: LOADB R2 1   
      37 [-]: SETUPVAL R2 4
      38 [-]: GETUPVAL R2 5
      39 [-]: CALL R2 0 0  
      40 [-]: GETIMPORT R2 13 ["_T"]
      41 [-]: LOADB R3 1   
      42 [-]: SETTABLEKS R3 R2 K14 ["LoadoutSaveRequired"]
      43 [-]: GETIMPORT R2 16 [0x25D99D89]
      44 [-]: NAMECALL R2 R2 K17 [0xCBD24335]
      45 [-]: CALL R2 1 0  
      46 [-]: GETIMPORT R2 19 [0x4EC73E73]
      47 [-]: GETUPVAL R3 3
      48 [-]: CALL R2 1 1  
      49 [-]: JUMPXEQKNIL R2 L9
      50 [-]: GETIMPORT R2 9 [0xCFC01047]
      51 [-]: GETUPVAL R3 3
      52 [-]: CALL R2 1 3  
      53 [-]: FORGPREP_NEXT R2 L6
L 5:  54 [-]: GETIMPORT R7 21 [0xCB79539E]
      55 [-]: GETIMPORT R9 23 [0x0469F296]
      56 [-]: LOADK R10 K24 ["FOCUS_SPENT"]
      57 [-]: CALL R9 1 1  
      58 [-]: MOVE R10 R5  
      59 [-]: LOADK R11 K25 [""]
      60 [-]: MOVE R12 R6  
      61 [-]: NAMECALL R7 R7 K26 [0x8B8FB8B7]
      62 [-]: CALL R7 5 0  
L 6:  63 [-]: FORGLOOP R2 L5 2
      64 [-]: RETURN R0 0  
L 7:  65 [-]: GETIMPORT R1 1 [0x03F57322]
      66 [-]: MOVE R2 R0   
      67 [-]: CALL R1 1 1  
      68 [-]: LOADN R2 6   
      69 [-]: JUMPIFNOTEQ R1 R2 L8
      70 [-]: LOADN R1 0   
      71 [-]: SETUPVAL R1 6
      72 [-]: GETIMPORT R1 16 [0x25D99D89]
      73 [-]: NAMECALL R1 R1 K17 [0xCBD24335]
      74 [-]: CALL R1 1 0  
      75 [-]: GETUPVAL R1 7
      76 [-]: CALL R1 0 0  
      77 [-]: RETURN R0 0  
L 8:  78 [-]: LOADNIL R1   
      79 [-]: SETUPVAL R1 8
L 9:  80 [-]: RETURN R0 0  


; Name:            
; Defined at line: 475
; #Upvalues:       2
; #Parameters:     0
; Is_vararg:       0
; Max Stack Size:  6

       0 [-]: GETUPVAL R0 0
       1 [-]: CALL R0 0 1  
       2 [-]: GETIMPORT R1 1 [0xAE91E43B]
       3 [-]: LOADK R3 K2 ["/Lotus/Language/TennoWay/CommitChanges"]
       4 [-]: LOADB R4 0   
       5 [-]: DUPTABLE R5 4
       6 [-]: SETTABLEKS R0 R5 K3 ["LIST"]
       7 [-]: NAMECALL R1 R1 K5 [0x42B04007]
       8 [-]: CALL R1 4 1  
       9 [-]: GETIMPORT R2 8 [0xE27B35BB]
      10 [-]: CALL R2 0 1  
      11 [-]: LOADN R3 5   
      12 [-]: SETTABLEKS R3 R2 K9 ["dialogType"]
      13 [-]: SETTABLEKS R1 R2 K10 ["locString"]
      14 [-]: LOADK R3 K11 ["/Menu/Confirm_Item_Yes"]
      15 [-]: SETTABLEKS R3 R2 K12 ["firstString"]
      16 [-]: LOADK R3 K13 ["/Menu/Confirm_Item_No"]
      17 [-]: SETTABLEKS R3 R2 K14 ["secondString"]
      18 [-]: LOADK R3 K15 ["/Lotus/Language/Menu/Loadout_Cancel"]
      19 [-]: SETTABLEKS R3 R2 K16 ["thirdString"]
      20 [-]: LOADK R5 K17 ["OnConfirmCommitFocusChanges"]
      21 [-]: NAMECALL R3 R2 K18 [0xE6CCC5B9]
      22 [-]: CALL R3 2 0  
      23 [-]: GETUPVAL R4 1
      24 [-]: GETTABLEKS R3 R4 K19 [0xE99B84E7]
      25 [-]: MOVE R4 R2   
      26 [-]: CALL R3 1 0  
      27 [-]: RETURN R0 0  


; Name:            
; Defined at line: 491
; #Upvalues:       6
; #Parameters:     0
; Is_vararg:       0
; Max Stack Size:  9

       0 [-]: GETUPVAL R0 0
       1 [-]: LOADN R1 0   
       2 [-]: JUMPIFNOTLT R1 R0 L0
       3 [-]: GETIMPORT R0 1 [0xAE91E43B]
       4 [-]: LOADK R2 K2 ["ConfirmCommitFocusChanges"]
       5 [-]: LOADK R3 K3 [""]
       6 [-]: NAMECALL R0 R0 K4 [0xE4162EED]
       7 [-]: CALL R0 3 0  
       8 [-]: RETURN R0 0  
L 0:   9 [-]: LOADB R0 1   
      10 [-]: SETUPVAL R0 1
      11 [-]: GETUPVAL R1 2
      12 [-]: GETTABLEKS R0 R1 K5 [0x659D451F]
      13 [-]: GETIMPORT R1 7 [0xB607EFE1]
      14 [-]: CALL R0 1 0  
      15 [-]: GETIMPORT R0 9 [0x25312C9B]
      16 [-]: GETIMPORT R1 1 [0xAE91E43B]
      17 [-]: LOADK R2 K10 ["_root"]
      18 [-]: LOADN R3 0   
      19 [-]: NEWTABLE R4 0 1
      20 [-]: LOADN R5 10  
      21 [-]: SETLIST R4 R5 1 [1]
      22 [-]: NEWTABLE R5 0 1
      23 [-]: LOADN R6 0   
      24 [-]: SETLIST R5 R6 1 [1]
      25 [-]: LOADK R6 K11 [0.55000000000000004]
      26 [-]: LOADN R7 0   
      27 [-]: NEWCLOSURE R8 P0
      28 [-]: MOVE R2 R3   
      29 [-]: MOVE R2 R4   
      30 [-]: MOVE R2 R2   
      31 [-]: MOVE R2 R5   
      32 [-]: CALL R0 8 0  
      33 [-]: RETURN R0 0  


; Name:            
; Defined at line: 521
; #Upvalues:       1
; #Parameters:     0
; Is_vararg:       0
; Max Stack Size:  1

       0 [-]: GETUPVAL R0 0
       1 [-]: CALL R0 0 0  
       2 [-]: RETURN R0 0  


; Name:            
; Defined at line: 525
; #Upvalues:       1
; #Parameters:     0
; Is_vararg:       0
; Max Stack Size:  1

       0 [-]: GETUPVAL R0 0
       1 [-]: CALL R0 0 0  
       2 [-]: RETURN R0 0  


; Name:            
; Defined at line: 529
; #Upvalues:       12
; #Parameters:     0
; Is_vararg:       0
; Max Stack Size:  6

       0 [-]: GETUPVAL R0 0
       1 [-]: JUMPXEQKNIL R0 L0
       2 [-]: GETUPVAL R0 0
       3 [-]: JUMPXEQKN R0 K0 L0 [100]
       4 [-]: RETURN R0 0  
L 0:   5 [-]: GETIMPORT R0 2 ["_T"]
       6 [-]: LOADN R1 192 
       7 [-]: SETTABLEKS R1 R0 K3 ["GenericVendor_ItemGridDims"]
       8 [-]: GETIMPORT R0 2 ["_T"]
       9 [-]: LOADN R1 0   
      10 [-]: SETTABLEKS R1 R0 K4 ["GenericVendor_ShowBgFadeTime"]
      11 [-]: GETIMPORT R0 6 [0xAE91E43B]
      12 [-]: GETIMPORT R2 8 [0x8E040D88]
      13 [-]: NAMECALL R0 R0 K9 [0x1FD6ABD0]
      14 [-]: CALL R0 2 1  
      15 [-]: SETUPVAL R0 1
      16 [-]: GETUPVAL R1 1
      17 [-]: FASTCALL1 62 R1 L1
      18 [-]: GETIMPORT R0 11 [0x7B998233]
      19 [-]: CALL R0 1 1  
L 1:  20 [-]: JUMPIF R0 L2 
      21 [-]: GETIMPORT R0 2 ["_T"]
      22 [-]: GETUPVAL R1 2
      23 [-]: SETTABLEKS R1 R0 K12 ["TennoWay_CurrentFocus"]
      24 [-]: GETIMPORT R0 14 [0x25D99D89]
      25 [-]: GETIMPORT R2 16 ["PolarityTree"]
      26 [-]: NAMECALL R0 R0 K17 [0xAD94D866]
      27 [-]: CALL R0 2 1  
      28 [-]: GETIMPORT R2 19 [0x70E77CD5]
      29 [-]: GETUPVAL R3 3
      30 [-]: GETTABLE R1 R2 R3
      31 [-]: GETIMPORT R2 2 ["_T"]
      32 [-]: NEWCLOSURE R3 P0
      33 [-]: MOVE R2 R4   
      34 [-]: MOVE R0 R1   
      35 [-]: MOVE R2 R5   
      36 [-]: SETTABLEKS R3 R2 K20 ["TennoWay_GetVendorInfo"]
      37 [-]: GETUPVAL R2 1
      38 [-]: LOADK R4 K21 ["SetVendorInfoFunction"]
      39 [-]: LOADK R5 K20 ["TennoWay_GetVendorInfo"]
      40 [-]: NAMECALL R2 R2 K22 [0xE4162EED]
      41 [-]: CALL R2 3 0  
      42 [-]: GETIMPORT R2 2 ["_T"]
      43 [-]: NEWCLOSURE R3 P1
      44 [-]: MOVE R0 R1   
      45 [-]: SETTABLEKS R3 R2 K23 ["TennoWay_BuyVendorItem"]
      46 [-]: GETUPVAL R2 1
      47 [-]: LOADK R4 K24 ["SetBuyItemFunction"]
      48 [-]: LOADK R5 K23 ["TennoWay_BuyVendorItem"]
      49 [-]: NAMECALL R2 R2 K22 [0xE4162EED]
      50 [-]: CALL R2 3 0  
      51 [-]: GETIMPORT R2 2 ["_T"]
      52 [-]: NEWCLOSURE R3 P2
      53 [-]: MOVE R1 R0   
      54 [-]: MOVE R2 R2   
      55 [-]: SETTABLEKS R3 R2 K25 ["TennoWay_OnBuyVendorItem"]
      56 [-]: GETUPVAL R2 1
      57 [-]: LOADK R4 K26 ["SetOnBuyItemFunction"]
      58 [-]: LOADK R5 K25 ["TennoWay_OnBuyVendorItem"]
      59 [-]: NAMECALL R2 R2 K22 [0xE4162EED]
      60 [-]: CALL R2 3 0  
      61 [-]: GETIMPORT R2 2 ["_T"]
      62 [-]: NEWCLOSURE R3 P3
      63 [-]: MOVE R2 R6   
      64 [-]: MOVE R2 R7   
      65 [-]: MOVE R2 R8   
      66 [-]: SETTABLEKS R3 R2 K27 ["TennoWay_OnCloseFunction"]
      67 [-]: GETUPVAL R2 1
      68 [-]: LOADK R4 K28 ["SetOnCloseFunction"]
      69 [-]: LOADK R5 K27 ["TennoWay_OnCloseFunction"]
      70 [-]: NAMECALL R2 R2 K22 [0xE4162EED]
      71 [-]: CALL R2 3 0  
      72 [-]: GETIMPORT R2 2 ["_T"]
      73 [-]: NEWCLOSURE R3 P4
      74 [-]: MOVE R2 R3   
      75 [-]: MOVE R2 R9   
      76 [-]: MOVE R2 R4   
      77 [-]: MOVE R2 R10  
      78 [-]: MOVE R2 R11  
      79 [-]: MOVE R2 R2   
      80 [-]: SETTABLEKS R3 R2 K29 ["TennoWay_UpdateInfoPanel"]
      81 [-]: GETUPVAL R2 1
      82 [-]: LOADK R4 K30 ["SetInfoPanelUpdateFunction"]
      83 [-]: LOADK R5 K29 ["TennoWay_UpdateInfoPanel"]
      84 [-]: NAMECALL R2 R2 K22 [0xE4162EED]
      85 [-]: CALL R2 3 0  
      86 [-]: GETUPVAL R2 7
      87 [-]: LOADB R3 1   
      88 [-]: CALL R2 1 0  
      89 [-]: CLOSEUPVALS R0
L 2:  90 [-]: RETURN R0 0  


; Name:            
; Defined at line: 645
; #Upvalues:       2
; #Parameters:     0
; Is_vararg:       0
; Max Stack Size:  7

       0 [-]: GETUPVAL R0 0
       1 [-]: JUMPXEQKNIL R0 L0
       2 [-]: GETUPVAL R0 0
       3 [-]: LOADN R1 100 
       4 [-]: JUMPIFNOTLT R0 R1 L0
       5 [-]: GETIMPORT R0 1 ["_T"]
       6 [-]: GETIMPORT R1 3 [0x603636AD]
       7 [-]: LOADK R2 K4 ["/Lotus/Language/TennoWay/RepresentWayLocked"]
       8 [-]: DUPTABLE R3 6
       9 [-]: GETIMPORT R4 3 [0x603636AD]
      10 [-]: GETUPVAL R5 1
      11 [-]: NEWTABLE R6 0 0
      12 [-]: CALL R4 2 1  
      13 [-]: SETTABLEKS R4 R3 K5 ["NAME"]
      14 [-]: CALL R1 2 1  
      15 [-]: SETTABLEKS R1 R0 K7 ["gToolTip"]
      16 [-]: LOADB R0 0   
      17 [-]: RETURN R0 1  
L 0:  18 [-]: RETURN R0 0  


; Name:            
; Defined at line: 652
; #Upvalues:       0
; #Parameters:     0
; Is_vararg:       0
; Max Stack Size:  2

       0 [-]: GETIMPORT R0 1 ["_T"]
       1 [-]: LOADNIL R1   
       2 [-]: SETTABLEKS R1 R0 K2 ["gToolTip"]
       3 [-]: RETURN R0 0  


; Name:            
; Defined at line: 656
; #Upvalues:       7
; #Parameters:     0
; Is_vararg:       0
; Max Stack Size:  8

       0 [-]: NEWTABLE R0 0 0
       1 [-]: DUPTABLE R3 3
       2 [-]: GETIMPORT R4 5 [0xAE91E43B]
       3 [-]: LOADK R6 K6 ["<WARNING>"]
       4 [-]: LOADB R7 1   
       5 [-]: NAMECALL R4 R4 K7 [0x42B04007]
       6 [-]: CALL R4 3 1  
       7 [-]: SETTABLEKS R4 R3 K0 ["Label"]
       8 [-]: GETUPVAL R5 0
       9 [-]: GETTABLEKS R4 R5 K8 [0xA7D904B8]
      10 [-]: GETIMPORT R5 5 [0xAE91E43B]
      11 [-]: LOADK R6 K9 ["/Lotus/Language/FocusHints/TennoWayTree_"]
      12 [-]: CALL R4 2 1  
      13 [-]: SETTABLEKS R4 R3 K1 ["Tips"]
      14 [-]: LOADN R4 -10 
      15 [-]: SETTABLEKS R4 R3 K2 ["Padding"]
      16 [-]: FASTCALL2 52 R0 R3 L0
      17 [-]: MOVE R2 R0   
      18 [-]: GETIMPORT R1 12 [0x23D5322F]
      19 [-]: CALL R1 2 0  
L 0:  20 [-]: GETUPVAL R1 1
      21 [-]: JUMPIF R1 L7 
      22 [-]: GETUPVAL R1 2
      23 [-]: JUMPXEQKNIL R1 L1 NOT
      24 [-]: GETUPVAL R1 3
      25 [-]: CALL R1 0 1  
      26 [-]: SETUPVAL R1 2
L 1:  27 [-]: GETUPVAL R1 2
      28 [-]: LOADN R2 60  
      29 [-]: JUMPIFNOTLE R2 R1 L5
      30 [-]: GETIMPORT R1 5 [0xAE91E43B]
      31 [-]: LOADK R3 K13 ["/Lotus/Language/TennoWay/RepresentWayNoName"]
      32 [-]: LOADB R4 0   
      33 [-]: NAMECALL R1 R1 K7 [0x42B04007]
      34 [-]: CALL R1 3 1  
      35 [-]: GETUPVAL R2 2
      36 [-]: LOADN R3 100 
      37 [-]: JUMPIFNOTLT R2 R3 L2
      38 [-]: GETIMPORT R4 5 [0xAE91E43B]
      39 [-]: LOADK R6 K14 ["<LOCKED>"]
      40 [-]: LOADB R7 1   
      41 [-]: NAMECALL R4 R4 K7 [0x42B04007]
      42 [-]: CALL R4 3 1  
      43 [-]: MOVE R2 R4   
      44 [-]: MOVE R3 R1   
      45 [-]: CONCAT R1 R2 R3
L 2:  46 [-]: DUPTABLE R2 20
      47 [-]: SETTABLEKS R1 R2 K0 ["Label"]
      48 [-]: DUPCLOSURE R3 K21 []
      49 [-]: SETTABLEKS R3 R2 K15 ["FocusCallback"]
      50 [-]: DUPCLOSURE R3 K22 []
      51 [-]: SETTABLEKS R3 R2 K16 ["UnfocusCallback"]
      52 [-]: DUPCLOSURE R3 K23 []
      53 [-]: SETTABLEKS R3 R2 K17 ["CallBack"]
      54 [-]: LOADK R3 K24 ["MENU_GENERIC1"]
      55 [-]: SETTABLEKS R3 R2 K18 ["CallOut"]
      56 [-]: GETUPVAL R4 4
      57 [-]: GETTABLEKS R3 R4 K25 [0x06D055F9]
      58 [-]: GETUPVAL R5 2
      59 [-]: LOADN R6 100 
      60 [-]: JUMPIFLT R5 R6 L3
      61 [-]: LOADB R4 0 +1
L 3:  62 [-]: LOADB R4 1   
L 4:  63 [-]: LOADN R5 60  
      64 [-]: LOADN R6 100 
      65 [-]: CALL R3 3 1  
      66 [-]: SETTABLEKS R3 R2 K19 ["Alpha"]
      67 [-]: FASTCALL2 52 R0 R2 L5
      68 [-]: MOVE R4 R0   
      69 [-]: MOVE R5 R2   
      70 [-]: GETIMPORT R3 12 [0x23D5322F]
      71 [-]: CALL R3 2 0  
L 5:  72 [-]: GETIMPORT R2 27 [0xCB00102D]
      73 [-]: GETUPVAL R3 5
      74 [-]: GETTABLE R1 R2 R3
      75 [-]: GETIMPORT R2 29 [0x25D99D89]
      76 [-]: NAMECALL R2 R2 K30 [0xA340C0E2]
      77 [-]: CALL R2 1 1  
      78 [-]: JUMPIFEQ R2 R1 L6
      79 [-]: DUPTABLE R4 31
      80 [-]: LOADK R5 K32 ["/Lotus/Language/TennoWay/SetSchoolActive"]
      81 [-]: SETTABLEKS R5 R4 K0 ["Label"]
      82 [-]: DUPCLOSURE R5 K33 []
      83 [-]: SETTABLEKS R5 R4 K17 ["CallBack"]
      84 [-]: LOADK R5 K34 ["MENU_RTHUMB"]
      85 [-]: SETTABLEKS R5 R4 K18 ["CallOut"]
      86 [-]: FASTCALL2 52 R0 R4 L6
      87 [-]: MOVE R3 R0   
      88 [-]: GETIMPORT R2 12 [0x23D5322F]
      89 [-]: CALL R2 2 0  
L 6:  90 [-]: DUPTABLE R4 31
      91 [-]: LOADK R5 K35 ["/Lotus/Language/TennoWay/ConvertShards"]
      92 [-]: SETTABLEKS R5 R4 K0 ["Label"]
      93 [-]: DUPCLOSURE R5 K36 []
      94 [-]: SETTABLEKS R5 R4 K17 ["CallBack"]
      95 [-]: LOADK R5 K37 ["MENU_RTRIGGER2"]
      96 [-]: SETTABLEKS R5 R4 K18 ["CallOut"]
      97 [-]: FASTCALL2 52 R0 R4 L7
      98 [-]: MOVE R3 R0   
      99 [-]: GETIMPORT R2 12 [0x23D5322F]
     100 [-]: CALL R2 2 0  
L 7: 101 [-]: DUPTABLE R3 31
     102 [-]: LOADK R4 K38 ["/Lotus/Language/Menu/Back"]
     103 [-]: SETTABLEKS R4 R3 K0 ["Label"]
     104 [-]: GETUPVAL R4 6
     105 [-]: SETTABLEKS R4 R3 K17 ["CallBack"]
     106 [-]: LOADK R4 K39 ["MENU_CANCEL"]
     107 [-]: SETTABLEKS R4 R3 K18 ["CallOut"]
     108 [-]: FASTCALL2 52 R0 R3 L8
     109 [-]: MOVE R2 R0   
     110 [-]: GETIMPORT R1 12 [0x23D5322F]
     111 [-]: CALL R1 2 0  
L 8: 112 [-]: GETIMPORT R2 42 ["SetButtons"]
     113 [-]: FASTCALL1 62 R2 L9
     114 [-]: GETIMPORT R1 44 [0x7B998233]
     115 [-]: CALL R1 1 1  
L 9: 116 [-]: JUMPIF R1 L10
     117 [-]: GETIMPORT R1 42 ["SetButtons"]
     118 [-]: GETIMPORT R2 5 [0xAE91E43B]
     119 [-]: MOVE R3 R0   
     120 [-]: GETIMPORT R4 46 [0xCD0165A3]
     121 [-]: LOADN R5 1   
     122 [-]: CALL R4 1 -1 
     123 [-]: CALL R1 -1 0 
L10: 124 [-]: RETURN R0 0  


; Name:            
; Defined at line: 712
; #Upvalues:       0
; #Parameters:     1
; Is_vararg:       0
; Max Stack Size:  12

       0 [-]: FASTCALL1 62 R0 L0
       1 [-]: MOVE R2 R0   
       2 [-]: GETIMPORT R1 1 [0x7B998233]
       3 [-]: CALL R1 1 1  
L 0:   4 [-]: JUMPIF R1 L2 
       5 [-]: GETTABLEKS R2 R0 K2 ["mCard"]
       6 [-]: FASTCALL1 62 R2 L1
       7 [-]: GETIMPORT R1 1 [0x7B998233]
       8 [-]: CALL R1 1 1  
L 1:   9 [-]: JUMPIFNOT R1 L3
L 2:  10 [-]: LOADN R1 0   
      11 [-]: RETURN R1 1  
L 3:  12 [-]: NEWTABLE R1 0 4
      13 [-]: LOADN R2 1   
      14 [-]: LOADN R3 2   
      15 [-]: LOADN R4 3   
      16 [-]: LOADN R5 4   
      17 [-]: SETLIST R1 R2 4 [1]
      18 [-]: GETTABLEKS R5 R0 K2 ["mCard"]
      19 [-]: GETTABLEKS R4 R5 K4 ["mRarity"]
      20 [-]: ADDK R3 R4 K3 [1]
      21 [-]: GETTABLE R2 R1 R3
      22 [-]: GETTABLEKS R4 R0 K5 ["mRank"]
      23 [-]: ADDK R3 R4 K3 [1]
      24 [-]: LOADN R9 18200
      25 [-]: MUL R8 R9 R2 
      26 [-]: LOADN R10 2  
      27 [-]: MUL R11 R3 R3
      28 [-]: ADD R9 R10 R11
      29 [-]: MUL R7 R8 R9 
      30 [-]: DIVK R6 R7 K6 [5000]
      31 [-]: FASTCALL1 12 R6 L4
      32 [-]: GETIMPORT R5 9 [0x55F27C30]
      33 [-]: CALL R5 1 1  
L 4:  34 [-]: MULK R4 R5 K6 [5000]
      35 [-]: RETURN R4 1  


; Name:            
; Defined at line: 726
; #Upvalues:       3
; #Parameters:     2
; Is_vararg:       0
; Max Stack Size:  17

       0 [-]: LOADK R3 K0 ["<p><font color=\""]
       1 [-]: GETUPVAL R6 1
       2 [-]: GETTABLEKS R4 R6 K1 ["ContentHex"]
       3 [-]: LOADK R5 K2 ["\">"]
       4 [-]: CONCAT R2 R3 R5
       5 [-]: SETUPVAL R2 0
       6 [-]: LOADB R2 1   
       7 [-]: GETTABLEKS R3 R0 K3 ["mRank"]
       8 [-]: GETTABLEKS R4 R0 K4 ["mMaxRank"]
       9 [-]: JUMPIFEQ R3 R4 L1
      10 [-]: GETTABLEKS R2 R0 K5 ["mCanBeUniversal"]
      11 [-]: JUMPIFNOT R2 L1
      12 [-]: GETTABLEKS R3 R0 K3 ["mRank"]
      13 [-]: GETTABLEKS R5 R0 K4 ["mMaxRank"]
      14 [-]: SUBK R4 R5 K6 [1]
      15 [-]: JUMPIFEQ R3 R4 L0
      16 [-]: LOADB R2 0 +1
L 0:  17 [-]: LOADB R2 1   
L 1:  18 [-]: MOVE R3 R1   
      19 [-]: JUMPIFNOT R3 L2
      20 [-]: LOADB R3 0   
      21 [-]: GETTABLEKS R4 R0 K7 ["mNextLvlDesc"]
      22 [-]: JUMPXEQKS R4 K8 L2 [""]
      23 [-]: NOT R3 R2    
L 2:  24 [-]: GETUPVAL R5 0
      25 [-]: LOADK R6 K9 ["<font color=\""]
      26 [-]: GETUPVAL R9 1
      27 [-]: GETTABLEKS R7 R9 K10 ["FloatingContentHex"]
      28 [-]: LOADK R8 K2 ["\">"]
      29 [-]: CONCAT R4 R5 R8
      30 [-]: SETUPVAL R4 0
      31 [-]: GETTABLEKS R4 R0 K11 ["mOtherPolarity"]
      32 [-]: JUMPIFNOT R4 L4
      33 [-]: GETTABLEKS R4 R0 K12 ["mUniversal"]
      34 [-]: JUMPIFNOT R4 L3
      35 [-]: GETUPVAL R5 0
      36 [-]: GETIMPORT R6 15 [0x3F3E4D12]
      37 [-]: GETIMPORT R7 17 [0xAE91E43B]
      38 [-]: LOADK R9 K18 ["/Lotus/Language/TennoWay/Universal"]
      39 [-]: LOADB R10 0  
      40 [-]: NAMECALL R7 R7 K19 [0x42B04007]
      41 [-]: CALL R7 3 -1 
      42 [-]: CALL R6 -1 1 
      43 [-]: CONCAT R4 R5 R6
      44 [-]: SETUPVAL R4 0
      45 [-]: JUMP L10
    
L 3:  46 [-]: GETUPVAL R5 0
      47 [-]: GETIMPORT R6 17 [0xAE91E43B]
      48 [-]: LOADK R8 K20 ["/Lotus/Language/TennoWay/WayBoundMaxRankPreview"]
      49 [-]: LOADB R9 1   
      50 [-]: NAMECALL R6 R6 K19 [0x42B04007]
      51 [-]: CALL R6 3 1  
      52 [-]: CONCAT R4 R5 R6
      53 [-]: SETUPVAL R4 0
      54 [-]: JUMP L10
    
L 4:  55 [-]: GETTABLEKS R4 R0 K21 ["mLocked"]
      56 [-]: JUMPIFNOT R4 L5
      57 [-]: GETUPVAL R5 0
      58 [-]: GETIMPORT R8 17 [0xAE91E43B]
      59 [-]: LOADK R10 K22 ["<LOCKED> "]
      60 [-]: LOADB R11 1  
      61 [-]: NAMECALL R8 R8 K19 [0x42B04007]
      62 [-]: CALL R8 3 1  
      63 [-]: MOVE R6 R8   
      64 [-]: GETIMPORT R7 15 [0x3F3E4D12]
      65 [-]: GETIMPORT R8 17 [0xAE91E43B]
      66 [-]: LOADK R10 K23 ["/Lotus/Language/Menu/MissionLocked"]
      67 [-]: LOADB R11 0  
      68 [-]: NAMECALL R8 R8 K19 [0x42B04007]
      69 [-]: CALL R8 3 -1 
      70 [-]: CALL R7 -1 1 
      71 [-]: CONCAT R4 R5 R7
      72 [-]: SETUPVAL R4 0
      73 [-]: JUMP L10
    
L 5:  74 [-]: GETTABLEKS R4 R0 K3 ["mRank"]
      75 [-]: GETTABLEKS R5 R0 K4 ["mMaxRank"]
      76 [-]: JUMPIFEQ R4 R5 L6
      77 [-]: GETTABLEKS R4 R0 K5 ["mCanBeUniversal"]
      78 [-]: JUMPIFNOT R4 L8
      79 [-]: GETTABLEKS R4 R0 K3 ["mRank"]
      80 [-]: GETTABLEKS R6 R0 K4 ["mMaxRank"]
      81 [-]: SUBK R5 R6 K6 [1]
      82 [-]: JUMPIFNOTEQ R4 R5 L8
L 6:  83 [-]: GETTABLEKS R4 R0 K5 ["mCanBeUniversal"]
      84 [-]: JUMPIFNOT R4 L7
      85 [-]: GETTABLEKS R4 R0 K12 ["mUniversal"]
      86 [-]: JUMPIFNOT R4 L7
      87 [-]: GETUPVAL R5 0
      88 [-]: GETIMPORT R6 15 [0x3F3E4D12]
      89 [-]: GETIMPORT R7 17 [0xAE91E43B]
      90 [-]: LOADK R9 K18 ["/Lotus/Language/TennoWay/Universal"]
      91 [-]: LOADB R10 0  
      92 [-]: NAMECALL R7 R7 K19 [0x42B04007]
      93 [-]: CALL R7 3 -1 
      94 [-]: CALL R6 -1 1 
      95 [-]: CONCAT R4 R5 R6
      96 [-]: SETUPVAL R4 0
      97 [-]: JUMP L10
    
L 7:  98 [-]: GETUPVAL R5 0
      99 [-]: GETIMPORT R6 15 [0x3F3E4D12]
     100 [-]: GETIMPORT R7 17 [0xAE91E43B]
     101 [-]: LOADK R9 K24 ["/Lotus/Language/Ranks/MaxRank"]
     102 [-]: LOADB R10 0  
     103 [-]: NAMECALL R7 R7 K19 [0x42B04007]
     104 [-]: CALL R7 3 -1 
     105 [-]: CALL R6 -1 1 
     106 [-]: CONCAT R4 R5 R6
     107 [-]: SETUPVAL R4 0
     108 [-]: JUMP L10
    
L 8: 109 [-]: GETTABLEKS R4 R0 K3 ["mRank"]
     110 [-]: JUMPIFNOT R3 L9
     111 [-]: MOVE R5 R4   
     112 [-]: LOADK R6 K9 ["<font color=\""]
     113 [-]: GETUPVAL R11 1
     114 [-]: GETTABLEKS R7 R11 K25 ["FloatingContentHighlightHex"]
     115 [-]: LOADK R8 K26 ["\"><MINI_ARROW>"]
     116 [-]: GETTABLEKS R11 R0 K3 ["mRank"]
     117 [-]: ADDK R9 R11 K6 [1]
     118 [-]: LOADK R10 K27 ["</font>"]
     119 [-]: CONCAT R4 R5 R10
L 9: 120 [-]: GETUPVAL R6 0
     121 [-]: GETIMPORT R7 17 [0xAE91E43B]
     122 [-]: LOADK R9 K28 ["/Lotus/Language/Menu/Global_FormattedRankCaps"]
     123 [-]: LOADB R10 1  
     124 [-]: DUPTABLE R11 30
     125 [-]: SETTABLEKS R4 R11 K29 ["RANK"]
     126 [-]: NAMECALL R7 R7 K19 [0x42B04007]
     127 [-]: CALL R7 4 1  
     128 [-]: CONCAT R5 R6 R7
     129 [-]: SETUPVAL R5 0
L10: 130 [-]: GETUPVAL R5 0
     131 [-]: LOADK R6 K31 ["<br></font>"]
     132 [-]: CONCAT R4 R5 R6
     133 [-]: SETUPVAL R4 0
     134 [-]: JUMPIFNOT R3 L11
     135 [-]: GETIMPORT R4 33 [0x66EDF04F]
     136 [-]: GETTABLEKS R5 R0 K7 ["mNextLvlDesc"]
     137 [-]: LOADK R6 K34 ["|OPEN_COLOR|"]
     138 [-]: LOADK R8 K9 ["<font color=\""]
     139 [-]: GETUPVAL R11 1
     140 [-]: GETTABLEKS R9 R11 K25 ["FloatingContentHighlightHex"]
     141 [-]: LOADK R10 K2 ["\">"]
     142 [-]: CONCAT R7 R8 R10
     143 [-]: CALL R4 3 1  
     144 [-]: GETIMPORT R5 33 [0x66EDF04F]
     145 [-]: MOVE R6 R4   
     146 [-]: LOADK R7 K35 ["|CLOSE_COLOR|"]
     147 [-]: LOADK R8 K27 ["</font>"]
     148 [-]: CALL R5 3 1  
     149 [-]: MOVE R4 R5   
     150 [-]: GETUPVAL R6 0
     151 [-]: MOVE R7 R4   
     152 [-]: CONCAT R5 R6 R7
     153 [-]: SETUPVAL R5 0
     154 [-]: JUMP L16
    
L11: 155 [-]: GETUPVAL R5 0
     156 [-]: GETTABLEKS R6 R0 K36 ["mDescription"]
     157 [-]: CONCAT R4 R5 R6
     158 [-]: SETUPVAL R4 0
     159 [-]: LOADK R4 K8 [""]
     160 [-]: GETTABLEKS R5 R0 K21 ["mLocked"]
     161 [-]: JUMPIFNOT R5 L15
     162 [-]: GETTABLEKS R7 R0 K37 ["mCard"]
     163 [-]: GETTABLEKS R6 R7 K38 ["mUpgrade"]
     164 [-]: GETTABLEKS R5 R6 K39 ["mInstance"]
     165 [-]: GETUPVAL R8 2
     166 [-]: NAMECALL R6 R5 K40 [0x6AD7E1A4]
     167 [-]: CALL R6 2 1  
     168 [-]: JUMPIF R6 L12
     169 [-]: MOVE R7 R4   
     170 [-]: LOADK R8 K41 ["<br>"]
     171 [-]: GETIMPORT R9 17 [0xAE91E43B]
     172 [-]: LOADK R11 K42 ["/Lotus/Language/TennoWay/UnlockAbilityOpTypeRequired"]
     173 [-]: LOADB R12 0  
     174 [-]: NAMECALL R9 R9 K19 [0x42B04007]
     175 [-]: CALL R9 3 1  
     176 [-]: CONCAT R4 R7 R9
L12: 177 [-]: NAMECALL R7 R5 K43 [0x9ED94A63]
     178 [-]: CALL R7 1 1  
     179 [-]: GETIMPORT R9 45 [0x25D99D89]
     180 [-]: NAMECALL R9 R9 K46 [0xEFEE6C91]
     181 [-]: CALL R9 1 1  
     182 [-]: JUMPIFLT R9 R7 L13
     183 [-]: LOADB R8 0 +1
L13: 184 [-]: LOADB R8 1   
L14: 185 [-]: JUMPIFNOT R8 L15
     186 [-]: MOVE R9 R4   
     187 [-]: LOADK R10 K41 ["<br>"]
     188 [-]: GETIMPORT R11 17 [0xAE91E43B]
     189 [-]: LOADK R13 K47 ["/Lotus/Language/TennoWay/UnlockAbilityMRRequired"]
     190 [-]: LOADB R14 0  
     191 [-]: DUPTABLE R15 30
     192 [-]: SETTABLEKS R7 R15 K29 ["RANK"]
     193 [-]: NAMECALL R11 R11 K19 [0x42B04007]
     194 [-]: CALL R11 4 1 
     195 [-]: CONCAT R4 R9 R11
L15: 196 [-]: LENGTH R5 R4 
     197 [-]: LOADN R6 0   
     198 [-]: JUMPIFNOTLT R6 R5 L16
     199 [-]: GETUPVAL R6 0
     200 [-]: LOADK R7 K48 ["<br><br>"]
     201 [-]: CONCAT R5 R6 R7
     202 [-]: SETUPVAL R5 0
     203 [-]: GETUPVAL R6 0
     204 [-]: LOADK R7 K9 ["<font color=\""]
     205 [-]: GETUPVAL R12 1
     206 [-]: GETTABLEKS R8 R12 K10 ["FloatingContentHex"]
     207 [-]: LOADK R9 K2 ["\">"]
     208 [-]: GETIMPORT R12 15 [0x3F3E4D12]
     209 [-]: GETIMPORT R13 17 [0xAE91E43B]
     210 [-]: LOADK R15 K49 ["/Lotus/Language/TennoWay/UnlockRequirements"]
     211 [-]: LOADB R16 0  
     212 [-]: NAMECALL R13 R13 K19 [0x42B04007]
     213 [-]: CALL R13 3 -1
     214 [-]: CALL R12 -1 1
     215 [-]: MOVE R10 R12 
     216 [-]: LOADK R11 K27 ["</font>"]
     217 [-]: CONCAT R5 R6 R11
     218 [-]: SETUPVAL R5 0
     219 [-]: GETUPVAL R6 0
     220 [-]: MOVE R7 R4   
     221 [-]: CONCAT R5 R6 R7
     222 [-]: SETUPVAL R5 0
L16: 223 [-]: GETUPVAL R5 0
     224 [-]: LOADK R6 K50 ["</font></p>"]
     225 [-]: CONCAT R4 R5 R6
     226 [-]: SETUPVAL R4 0
     227 [-]: RETURN R0 0  


; Name:            
; Defined at line: 787
; #Upvalues:       1
; #Parameters:     1
; Is_vararg:       0
; Max Stack Size:  7

       0 [-]: LOADN R3 1   
       1 [-]: GETUPVAL R4 0
       2 [-]: LENGTH R1 R4 
       3 [-]: LOADN R2 1   
       4 [-]: FORNPREP R1 L2
L 0:   5 [-]: GETUPVAL R6 0
       6 [-]: GETTABLE R5 R6 R3
       7 [-]: GETTABLEKS R4 R5 K0 ["mUniqueId"]
       8 [-]: JUMPIFNOTEQ R4 R0 L1
       9 [-]: GETUPVAL R5 0
      10 [-]: GETTABLE R4 R5 R3
      11 [-]: RETURN R4 1  
L 1:  12 [-]: FORNLOOP R1 L0
L 2:  13 [-]: LOADNIL R1   
      14 [-]: RETURN R1 1  


; Name:            
; Defined at line: 796
; #Upvalues:       2
; #Parameters:     3
; Is_vararg:       0
; Max Stack Size:  10

       0 [-]: GETUPVAL R4 0
       1 [-]: GETTABLEKS R5 R0 K0 ["mUniqueId"]
       2 [-]: GETTABLE R3 R4 R5
       3 [-]: JUMPXEQKNIL R3 L0 NOT
       4 [-]: GETUPVAL R3 0
       5 [-]: GETTABLEKS R4 R0 K0 ["mUniqueId"]
       6 [-]: DUPTABLE R5 10
       7 [-]: LOADB R6 0   
       8 [-]: SETTABLEKS R6 R5 K1 ["Upgraded"]
       9 [-]: SETTABLEKS R2 R5 K2 ["Purchase"]
      10 [-]: LOADB R6 0   
      11 [-]: SETTABLEKS R6 R5 K3 ["Purchased"]
      12 [-]: LOADB R6 0   
      13 [-]: SETTABLEKS R6 R5 K4 ["Committing"]
      14 [-]: LOADB R6 0   
      15 [-]: SETTABLEKS R6 R5 K5 ["Committed"]
      16 [-]: GETTABLEKS R6 R0 K11 ["mName"]
      17 [-]: SETTABLEKS R6 R5 K6 ["Name"]
      18 [-]: GETTABLEKS R8 R0 K12 ["mCard"]
      19 [-]: GETTABLEKS R7 R8 K13 ["mUpgrade"]
      20 [-]: GETTABLEKS R6 R7 K14 ["mItemType"]
      21 [-]: SETTABLEKS R6 R5 K7 ["Type"]
      22 [-]: LOADN R6 0   
      23 [-]: SETTABLEKS R6 R5 K8 ["Focus"]
      24 [-]: LOADN R6 0   
      25 [-]: SETTABLEKS R6 R5 K9 ["Lvl"]
      26 [-]: SETTABLE R5 R3 R4
L 0:  27 [-]: JUMPIFNOT R2 L1
      28 [-]: GETUPVAL R4 1
      29 [-]: ADDK R3 R4 K15 [1]
      30 [-]: SETUPVAL R3 1
      31 [-]: JUMP L2
     
L 1:  32 [-]: GETUPVAL R5 0
      33 [-]: GETTABLEKS R6 R0 K0 ["mUniqueId"]
      34 [-]: GETTABLE R4 R5 R6
      35 [-]: GETTABLEKS R3 R4 K1 ["Upgraded"]
      36 [-]: JUMPIF R3 L2 
      37 [-]: GETUPVAL R4 1
      38 [-]: ADDK R3 R4 K15 [1]
      39 [-]: SETUPVAL R3 1
      40 [-]: GETUPVAL R4 0
      41 [-]: GETTABLEKS R5 R0 K0 ["mUniqueId"]
      42 [-]: GETTABLE R3 R4 R5
      43 [-]: LOADB R4 1   
      44 [-]: SETTABLEKS R4 R3 K1 ["Upgraded"]
L 2:  45 [-]: JUMPIFNOT R2 L3
      46 [-]: GETUPVAL R4 0
      47 [-]: GETTABLEKS R5 R0 K0 ["mUniqueId"]
      48 [-]: GETTABLE R3 R4 R5
      49 [-]: SETTABLEKS R1 R3 K16 ["PurchaseCost"]
L 3:  50 [-]: GETUPVAL R4 0
      51 [-]: GETTABLEKS R5 R0 K0 ["mUniqueId"]
      52 [-]: GETTABLE R3 R4 R5
      53 [-]: GETUPVAL R7 0
      54 [-]: GETTABLEKS R8 R0 K0 ["mUniqueId"]
      55 [-]: GETTABLE R6 R7 R8
      56 [-]: GETTABLEKS R5 R6 K8 ["Focus"]
      57 [-]: ADD R4 R5 R1 
      58 [-]: SETTABLEKS R4 R3 K8 ["Focus"]
      59 [-]: JUMPIF R2 L5 
      60 [-]: GETTABLEKS R3 R0 K17 ["mRank"]
      61 [-]: GETTABLEKS R5 R0 K18 ["mMaxRank"]
      62 [-]: GETTABLEKS R8 R0 K19 ["mNextRankCurrent"]
      63 [-]: GETTABLEKS R9 R0 K20 ["mNextRankTarget"]
      64 [-]: DIV R7 R8 R9 
      65 [-]: ADD R6 R3 R7 
      66 [-]: FASTCALL2 19 R5 R6 L4
      67 [-]: GETIMPORT R4 23 [0xAC1B386A]
      68 [-]: CALL R4 2 1  
L 4:  69 [-]: MOVE R3 R4   
      70 [-]: GETUPVAL R5 0
      71 [-]: GETTABLEKS R6 R0 K0 ["mUniqueId"]
      72 [-]: GETTABLE R4 R5 R6
      73 [-]: SETTABLEKS R3 R4 K9 ["Lvl"]
      74 [-]: RETURN R0 0  
L 5:  75 [-]: GETUPVAL R4 0
      76 [-]: GETTABLEKS R5 R0 K0 ["mUniqueId"]
      77 [-]: GETTABLE R3 R4 R5
      78 [-]: LOADN R4 0   
      79 [-]: SETTABLEKS R4 R3 K9 ["Lvl"]
      80 [-]: RETURN R0 0  


; Name:            
; Defined at line: 825
; #Upvalues:       1
; #Parameters:     0
; Is_vararg:       0
; Max Stack Size:  17

       0 [-]: NEWTABLE R0 0 0
       1 [-]: GETIMPORT R1 1 [0xC8802016]
       2 [-]: GETUPVAL R2 0
       3 [-]: CALL R1 1 3  
       4 [-]: FORGPREP_INEXT R1 L7
L 0:   5 [-]: GETTABLEKS R7 R5 K2 ["Life"]
       6 [-]: GETIMPORT R8 4 [0x67652851]
       7 [-]: CALL R8 0 1  
       8 [-]: ADD R6 R7 R8 
       9 [-]: SETTABLEKS R6 R5 K2 ["Life"]
      10 [-]: GETTABLEKS R6 R5 K2 ["Life"]
      11 [-]: GETTABLEKS R8 R5 K6 ["TravelTime"]
      12 [-]: ADDK R7 R8 K5 [0.29999999999999999]
      13 [-]: JUMPIFLT R7 R6 L2
      14 [-]: GETTABLEKS R7 R5 K7 ["Effect"]
      15 [-]: FASTCALL1 62 R7 L1
      16 [-]: GETIMPORT R6 9 [0x7B998233]
      17 [-]: CALL R6 1 1  
L 1:  18 [-]: JUMPIFNOT R6 L4
L 2:  19 [-]: FASTCALL2 52 R0 R4 L3
      20 [-]: MOVE R7 R0   
      21 [-]: MOVE R8 R4   
      22 [-]: GETIMPORT R6 12 [0x23D5322F]
      23 [-]: CALL R6 2 0  
L 3:  24 [-]: JUMP L7
     
L 4:  25 [-]: LOADN R7 1   
      26 [-]: GETTABLEKS R9 R5 K2 ["Life"]
      27 [-]: GETTABLEKS R10 R5 K6 ["TravelTime"]
      28 [-]: DIV R8 R9 R10
      29 [-]: FASTCALL2 19 R7 R8 L5
      30 [-]: GETIMPORT R6 15 [0xAC1B386A]
      31 [-]: CALL R6 2 1  
L 5:  32 [-]: GETIMPORT R7 17 [0xA421AF95]
      33 [-]: GETTABLEKS R9 R5 K18 ["Distance"]
      34 [-]: MUL R8 R9 R6 
      35 [-]: LOADK R10 K19 [0.01]
      36 [-]: GETTABLEKS R13 R5 K20 ["BaseAngle"]
      37 [-]: LOADK R16 K22 [3.1415927410125732]
      38 [-]: MUL R15 R6 R16
      39 [-]: MULK R14 R15 K21 [2]
      40 [-]: ADD R12 R13 R14
      41 [-]: FASTCALL1 24 R12 L6
      42 [-]: GETIMPORT R11 24 [0x3EDA26FC]
      43 [-]: CALL R11 1 1 
L 6:  44 [-]: MUL R9 R10 R11
      45 [-]: LOADN R10 0  
      46 [-]: CALL R7 3 1  
      47 [-]: GETIMPORT R8 26 [0x492C7F2A]
      48 [-]: MOVE R9 R7   
      49 [-]: GETIMPORT R10 28 [0x00046924]
      50 [-]: LOADN R11 0  
      51 [-]: LOADN R12 0  
      52 [-]: GETTABLEKS R13 R5 K29 ["Angle"]
      53 [-]: CALL R10 3 -1
      54 [-]: CALL R8 -1 1 
      55 [-]: MOVE R7 R8   
      56 [-]: GETTABLEKS R8 R5 K7 ["Effect"]
      57 [-]: MOVE R10 R7  
      58 [-]: NAMECALL R8 R8 K30 [0x119B677C]
      59 [-]: CALL R8 2 0  
L 7:  60 [-]: FORGLOOP R1 L0 2 [inext]
      61 [-]: LENGTH R3 R0 
      62 [-]: LOADN R1 1   
      63 [-]: LOADN R2 -1  
      64 [-]: FORNPREP R1 L11
L 8:  65 [-]: GETUPVAL R6 0
      66 [-]: GETTABLE R7 R0 R3
      67 [-]: GETTABLE R5 R6 R7
      68 [-]: GETTABLEKS R4 R5 K7 ["Effect"]
      69 [-]: FASTCALL1 62 R4 L9
      70 [-]: MOVE R6 R4   
      71 [-]: GETIMPORT R5 9 [0x7B998233]
      72 [-]: CALL R5 1 1  
L 9:  73 [-]: JUMPIF R5 L10
      74 [-]: NAMECALL R5 R4 K31 [0xA2880940]
      75 [-]: CALL R5 1 0  
L10:  76 [-]: GETIMPORT R5 33 [0x9C1F3B5A]
      77 [-]: GETUPVAL R6 0
      78 [-]: GETTABLE R7 R0 R3
      79 [-]: CALL R5 2 0  
      80 [-]: FORNLOOP R1 L8
L11:  81 [-]: RETURN R0 0  


; Name:            
; Defined at line: 848
; #Upvalues:       2
; #Parameters:     0
; Is_vararg:       0
; Max Stack Size:  3

       0 [-]: GETUPVAL R1 0
       1 [-]: GETTABLEKS R0 R1 K0 [0x659D451F]
       2 [-]: GETIMPORT R2 2 [0x0032441C]
       3 [-]: GETTABLEKS R1 R2 K3 ["UISound_Error"]
       4 [-]: CALL R0 1 0  
       5 [-]: GETUPVAL R0 1
       6 [-]: JUMPIF R0 L0 
       7 [-]: NEWTABLE R0 0 0
       8 [-]: SETUPVAL R0 1
L 0:   9 [-]: GETUPVAL R0 1
      10 [-]: LOADN R1 1   
      11 [-]: SETTABLEN R1 R0 1
      12 [-]: GETUPVAL R1 1
      13 [-]: FASTCALL2K 52 R1 K4 L1 ["Title.Count"]
      14 [-]: LOADK R2 K4 ["Title.Count"]
      15 [-]: GETIMPORT R0 7 [0x23D5322F]
      16 [-]: CALL R0 2 0  
L 1:  17 [-]: RETURN R0 0  


; Name:            
; Defined at line: 858
; #Upvalues:       3
; #Parameters:     1
; Is_vararg:       0
; Max Stack Size:  12

       0 [-]: JUMPIFNOT R0 L1
       1 [-]: GETIMPORT R2 2 ["PolarityTree"]
       2 [-]: FASTCALL1 62 R2 L0
       3 [-]: GETIMPORT R1 4 [0x7B998233]
       4 [-]: CALL R1 1 1  
L 0:   5 [-]: JUMPIF R1 L1 
       6 [-]: GETIMPORT R1 6 [0x25D99D89]
       7 [-]: GETIMPORT R3 2 ["PolarityTree"]
       8 [-]: NAMECALL R1 R1 K7 [0xAD94D866]
       9 [-]: CALL R1 2 1  
      10 [-]: SETUPVAL R1 0
L 1:  11 [-]: GETUPVAL R1 1
      12 [-]: GETUPVAL R2 0
      13 [-]: SETUPVAL R2 1
      14 [-]: GETIMPORT R2 9 [0x25312C9B]
      15 [-]: GETIMPORT R3 11 [0xAE91E43B]
      16 [-]: LOADK R4 K12 ["Title.Count"]
      17 [-]: LOADN R5 2   
      18 [-]: NEWTABLE R6 0 1
      19 [-]: NEWCLOSURE R7 P0
      20 [-]: MOVE R2 R2   
      21 [-]: MOVE R0 R1   
      22 [-]: MOVE R2 R0   
      23 [-]: SETLIST R6 R7 1 [1]
      24 [-]: NEWTABLE R7 0 1
      25 [-]: LOADN R8 1   
      26 [-]: SETLIST R7 R8 1 [1]
      27 [-]: GETUPVAL R9 2
      28 [-]: GETTABLEKS R8 R9 K13 [0x06D055F9]
      29 [-]: MOVE R9 R0   
      30 [-]: LOADN R10 0  
      31 [-]: LOADK R11 K14 [0.59999999999999998]
      32 [-]: CALL R8 3 -1 
      33 [-]: CALL R2 -1 0 
      34 [-]: GETIMPORT R2 11 [0xAE91E43B]
      35 [-]: LOADK R4 K12 ["Title.Count"]
      36 [-]: LOADN R5 33  
      37 [-]: NAMECALL R2 R2 K15 [0x91A24E4B]
      38 [-]: CALL R2 3 1  
      39 [-]: GETIMPORT R6 11 [0xAE91E43B]
      40 [-]: LOADK R8 K17 ["Title.Way"]
      41 [-]: LOADN R9 33  
      42 [-]: NAMECALL R6 R6 K15 [0x91A24E4B]
      43 [-]: CALL R6 3 1  
      44 [-]: ADDK R5 R6 K16 [64]
      45 [-]: FASTCALL2 18 R2 R5 L2
      46 [-]: MOVE R4 R2   
      47 [-]: GETIMPORT R3 20 [0xB62ECFE0]
      48 [-]: CALL R3 2 1  
L 2:  49 [-]: MOVE R2 R3   
      50 [-]: MOVE R4 R2   
      51 [-]: GETIMPORT R5 11 [0xAE91E43B]
      52 [-]: LOADK R7 K21 ["Title.State"]
      53 [-]: LOADN R8 33  
      54 [-]: NAMECALL R5 R5 K15 [0x91A24E4B]
      55 [-]: CALL R5 3 -1 
      56 [-]: FASTCALL 18 L3
      57 [-]: GETIMPORT R3 20 [0xB62ECFE0]
      58 [-]: CALL R3 -1 1 
L 3:  59 [-]: MOVE R2 R3   
      60 [-]: GETIMPORT R3 11 [0xAE91E43B]
      61 [-]: LOADK R5 K22 ["Title.Backer"]
      62 [-]: LOADN R6 12  
      63 [-]: DIVK R7 R2 K23 [0.69999999999999996]
      64 [-]: NAMECALL R3 R3 K24 [0x67BC869F]
      65 [-]: CALL R3 4 0  
      66 [-]: GETIMPORT R3 11 [0xAE91E43B]
      67 [-]: LOADK R5 K22 ["Title.Backer"]
      68 [-]: LOADN R6 0   
      69 [-]: DIVK R7 R2 K25 [2]
      70 [-]: NAMECALL R3 R3 K24 [0x67BC869F]
      71 [-]: CALL R3 4 0  
      72 [-]: GETIMPORT R3 11 [0xAE91E43B]
      73 [-]: LOADK R5 K26 ["Title.Watermark"]
      74 [-]: LOADN R6 0   
      75 [-]: DIVK R7 R2 K25 [2]
      76 [-]: NAMECALL R3 R3 K24 [0x67BC869F]
      77 [-]: CALL R3 4 0  
      78 [-]: RETURN R0 0  


; Name:            
; Defined at line: 880
; #Upvalues:       4
; #Parameters:     0
; Is_vararg:       0
; Max Stack Size:  4

       0 [-]: LOADB R0 1   
       1 [-]: SETUPVAL R0 0
       2 [-]: GETUPVAL R0 1
       3 [-]: LOADK R1 K0 [0.050000000000000003]
       4 [-]: SETTABLEKS R1 R0 K1 ["mSmoothTime"]
       5 [-]: GETUPVAL R0 1
       6 [-]: GETUPVAL R3 2
       7 [-]: ADDK R2 R3 K2 [0.029999999999999999]
       8 [-]: NAMECALL R0 R0 K3 [0x188E2BEE]
       9 [-]: CALL R0 2 0  
      10 [-]: GETUPVAL R0 3
      11 [-]: LOADK R2 K0 [0.050000000000000003]
      12 [-]: NEWCLOSURE R3 P0
      13 [-]: MOVE R2 R1   
      14 [-]: MOVE R2 R2   
      15 [-]: MOVE R2 R3   
      16 [-]: MOVE R2 R0   
      17 [-]: NAMECALL R0 R0 K4 [0xBD2E96EA]
      18 [-]: CALL R0 3 0  
      19 [-]: RETURN R0 0  


; Name:            
; Defined at line: 895
; #Upvalues:       2
; #Parameters:     1
; Is_vararg:       0
; Max Stack Size:  7

       0 [-]: GETTABLEKS R2 R0 K0 ["mCard"]
       1 [-]: GETTABLEKS R1 R2 K1 ["mUpgrade"]
       2 [-]: GETUPVAL R3 0
       3 [-]: GETTABLEKS R4 R0 K2 ["mUniqueId"]
       4 [-]: GETTABLE R2 R3 R4
       5 [-]: FASTCALL1 62 R2 L0
       6 [-]: MOVE R4 R2   
       7 [-]: GETIMPORT R3 4 [0x7B998233]
       8 [-]: CALL R3 1 1  
L 0:   9 [-]: JUMPIF R3 L1 
      10 [-]: GETTABLEKS R3 R1 K5 ["mInstance"]
      11 [-]: GETTABLEKS R5 R2 K6 ["Lvl"]
      12 [-]: NAMECALL R3 R3 K7 [0x86BA2663]
      13 [-]: CALL R3 2 1  
      14 [-]: SETTABLEKS R3 R1 K8 ["mUpgradeFingerprint"]
      15 [-]: JUMP L2
     
L 1:  16 [-]: GETTABLEKS R3 R1 K5 ["mInstance"]
      17 [-]: LOADN R5 0   
      18 [-]: NAMECALL R3 R3 K7 [0x86BA2663]
      19 [-]: CALL R3 2 1  
      20 [-]: SETTABLEKS R3 R1 K8 ["mUpgradeFingerprint"]
L 2:  21 [-]: GETUPVAL R4 1
      22 [-]: GETTABLEKS R3 R4 K9 [0xFC31B69E]
      23 [-]: MOVE R4 R1   
      24 [-]: GETTABLEKS R6 R0 K0 ["mCard"]
      25 [-]: GETTABLEKS R5 R6 K10 ["mId"]
      26 [-]: CALL R3 2 1  
      27 [-]: SETTABLEKS R3 R0 K0 ["mCard"]
      28 [-]: GETTABLEKS R4 R0 K0 ["mCard"]
      29 [-]: GETTABLEKS R3 R4 K11 ["mDesc"]
      30 [-]: SETTABLEKS R3 R0 K12 ["mDescription"]
      31 [-]: GETTABLEKS R4 R0 K0 ["mCard"]
      32 [-]: GETTABLEKS R3 R4 K13 ["mNextLvlDesc"]
      33 [-]: SETTABLEKS R3 R0 K13 ["mNextLvlDesc"]
      34 [-]: RETURN R0 0  


; Name:            
; Defined at line: 910
; #Upvalues:       16
; #Parameters:     1
; Is_vararg:       0
; Max Stack Size:  11

       0 [-]: GETUPVAL R1 0
       1 [-]: JUMPIFNOT R1 L0
       2 [-]: RETURN R0 0  
L 0:   3 [-]: GETIMPORT R1 1 [0x03F57322]
       4 [-]: MOVE R2 R0   
       5 [-]: CALL R1 1 1  
       6 [-]: MOVE R0 R1   
       7 [-]: JUMPXEQKNIL R0 L1 NOT
       8 [-]: RETURN R0 0  
L 1:   9 [-]: GETUPVAL R1 1
      10 [-]: MOVE R3 R0   
      11 [-]: NAMECALL R1 R1 K2 [0xCA30DFB6]
      12 [-]: CALL R1 2 1  
      13 [-]: JUMPXEQKNIL R1 L3
      14 [-]: GETTABLEKS R3 R1 K3 ["mCard"]
      15 [-]: FASTCALL1 62 R3 L2
      16 [-]: GETIMPORT R2 5 [0x7B998233]
      17 [-]: CALL R2 1 1  
L 2:  18 [-]: JUMPIFNOT R2 L4
L 3:  19 [-]: RETURN R0 0  
L 4:  20 [-]: GETTABLEKS R2 R1 K6 ["mNextRankTarget"]
      21 [-]: GETUPVAL R4 2
      22 [-]: SUB R3 R4 R2 
      23 [-]: LOADN R4 0   
      24 [-]: JUMPIFNOTLE R3 R4 L5
      25 [-]: GETUPVAL R3 3
      26 [-]: CALL R3 0 0  
      27 [-]: RETURN R0 0  
L 5:  28 [-]: GETUPVAL R3 4
      29 [-]: NAMECALL R3 R3 K7 [0xCC5F3150]
      30 [-]: CALL R3 1 0  
      31 [-]: GETIMPORT R3 9 [0xAE91E43B]
      32 [-]: LOADK R5 K10 ["_root"]
      33 [-]: LOADN R6 25  
      34 [-]: NAMECALL R3 R3 K11 [0x91A24E4B]
      35 [-]: CALL R3 3 1  
      36 [-]: SETUPVAL R3 5
      37 [-]: GETIMPORT R3 9 [0xAE91E43B]
      38 [-]: LOADK R5 K10 ["_root"]
      39 [-]: LOADN R6 26  
      40 [-]: NAMECALL R3 R3 K11 [0x91A24E4B]
      41 [-]: CALL R3 3 1  
      42 [-]: SETUPVAL R3 6
      43 [-]: SETTABLEKS R2 R1 K12 ["mNextRankCurrent"]
      44 [-]: GETUPVAL R4 2
      45 [-]: SUB R3 R4 R2 
      46 [-]: SETUPVAL R3 2
      47 [-]: GETUPVAL R3 7
      48 [-]: CALL R3 0 0  
      49 [-]: GETUPVAL R4 8
      50 [-]: GETTABLEKS R3 R4 K13 [0xF76783E5]
      51 [-]: GETIMPORT R4 9 [0xAE91E43B]
      52 [-]: GETTABLEKS R5 R1 K14 ["mClipName"]
      53 [-]: GETIMPORT R6 16 [0x23428253]
      54 [-]: CALL R3 3 1  
      55 [-]: FASTCALL1 62 R3 L6
      56 [-]: MOVE R5 R3   
      57 [-]: GETIMPORT R4 5 [0x7B998233]
      58 [-]: CALL R4 1 1  
L 6:  59 [-]: JUMPIF R4 L7 
      60 [-]: GETUPVAL R5 9
      61 [-]: GETTABLEKS R4 R5 K17 [0xCD10B8A9]
      62 [-]: MOVE R5 R3   
      63 [-]: CALL R4 1 0  
      64 [-]: LOADK R5 K18 [0.029999999999999999]
      65 [-]: LOADN R7 1   
      66 [-]: GETUPVAL R8 10
      67 [-]: NAMECALL R8 R8 K19 [0x54AB95F9]
      68 [-]: CALL R8 1 1  
      69 [-]: ADD R6 R7 R8 
      70 [-]: MUL R4 R5 R6 
      71 [-]: MULK R7 R4 K20 [0.80000000000000004]
      72 [-]: MOVE R8 R4   
      73 [-]: LOADB R9 1   
      74 [-]: NAMECALL R5 R3 K21 [0xCBF89887]
      75 [-]: CALL R5 4 0  
L 7:  76 [-]: GETTABLEKS R5 R1 K23 ["mRank"]
      77 [-]: ADDK R4 R5 K22 [1]
      78 [-]: SETTABLEKS R4 R1 K23 ["mRank"]
      79 [-]: GETIMPORT R5 25 [0x582EFE65]
      80 [-]: GETTABLEKS R6 R1 K23 ["mRank"]
      81 [-]: GETTABLE R4 R5 R6
      82 [-]: FASTCALL1 62 R4 L8
      83 [-]: MOVE R6 R4   
      84 [-]: GETIMPORT R5 5 [0x7B998233]
      85 [-]: CALL R5 1 1  
L 8:  86 [-]: JUMPIF R5 L9 
      87 [-]: GETUPVAL R6 8
      88 [-]: GETTABLEKS R5 R6 K26 [0x659D451F]
      89 [-]: MOVE R6 R4   
      90 [-]: CALL R5 1 0  
L 9:  91 [-]: GETUPVAL R6 8
      92 [-]: GETTABLEKS R5 R6 K13 [0xF76783E5]
      93 [-]: GETIMPORT R6 9 [0xAE91E43B]
      94 [-]: GETTABLEKS R8 R1 K14 ["mClipName"]
      95 [-]: LOADK R9 K27 [".Rings.Ring"]
      96 [-]: GETTABLEKS R10 R1 K23 ["mRank"]
      97 [-]: CONCAT R7 R8 R10
      98 [-]: GETIMPORT R8 29 [0xC7E3953E]
      99 [-]: CALL R5 3 1  
     100 [-]: MOVE R3 R5   
     101 [-]: GETUPVAL R6 9
     102 [-]: GETTABLEKS R5 R6 K17 [0xCD10B8A9]
     103 [-]: MOVE R6 R3   
     104 [-]: CALL R5 1 0  
     105 [-]: GETTABLEKS R5 R1 K30 ["mUniversal"]
     106 [-]: JUMPIFNOT R5 L10
     107 [-]: GETTABLEKS R5 R1 K23 ["mRank"]
     108 [-]: GETTABLEKS R7 R1 K31 ["mMaxRank"]
     109 [-]: SUBK R6 R7 K22 [1]
     110 [-]: JUMPIFNOTEQ R5 R6 L10
     111 [-]: GETTABLEKS R6 R1 K23 ["mRank"]
     112 [-]: ADDK R5 R6 K22 [1]
     113 [-]: SETTABLEKS R5 R1 K23 ["mRank"]
L10: 114 [-]: GETUPVAL R5 11
     115 [-]: MOVE R6 R1   
     116 [-]: CALL R5 1 1  
     117 [-]: SETTABLEKS R5 R1 K6 ["mNextRankTarget"]
     118 [-]: GETTABLEKS R5 R1 K23 ["mRank"]
     119 [-]: GETTABLEKS R6 R1 K31 ["mMaxRank"]
     120 [-]: JUMPIFNOTEQ R5 R6 L11
     121 [-]: GETTABLEKS R5 R1 K6 ["mNextRankTarget"]
     122 [-]: SETTABLEKS R5 R1 K12 ["mNextRankCurrent"]
     123 [-]: JUMP L12
    
L11: 124 [-]: LOADN R5 0   
     125 [-]: SETTABLEKS R5 R1 K12 ["mNextRankCurrent"]
L12: 126 [-]: GETUPVAL R6 1
     127 [-]: GETTABLEKS R5 R6 K32 ["mUpdateRank"]
     128 [-]: MOVE R6 R1   
     129 [-]: CALL R5 1 0  
     130 [-]: GETUPVAL R5 12
     131 [-]: MOVE R6 R1   
     132 [-]: MOVE R7 R2   
     133 [-]: CALL R5 2 0  
     134 [-]: GETUPVAL R5 13
     135 [-]: MOVE R6 R1   
     136 [-]: CALL R5 1 0  
     137 [-]: GETUPVAL R5 14
     138 [-]: MOVE R6 R1   
     139 [-]: LOADB R7 1   
     140 [-]: CALL R5 2 0  
     141 [-]: GETUPVAL R6 1
     142 [-]: GETTABLEKS R5 R6 K33 ["ShowNodeInfo"]
     143 [-]: MOVE R6 R1   
     144 [-]: LOADB R7 1   
     145 [-]: CALL R5 2 0  
     146 [-]: GETUPVAL R5 15
     147 [-]: CALL R5 0 0  
     148 [-]: RETURN R0 0  


; Name:            
; Defined at line: 980
; #Upvalues:       1
; #Parameters:     1
; Is_vararg:       0
; Max Stack Size:  9

       0 [-]: GETUPVAL R3 0
       1 [-]: GETTABLEKS R2 R3 K0 ["mMaxNodeX"]
       2 [-]: GETUPVAL R4 0
       3 [-]: GETTABLEKS R3 R4 K1 ["mMinNodeX"]
       4 [-]: SUB R1 R2 R3 
       5 [-]: LOADN R3 1   
       6 [-]: GETUPVAL R8 0
       7 [-]: GETTABLEKS R7 R8 K0 ["mMaxNodeX"]
       8 [-]: GETTABLEKS R8 R0 K2 ["mX"]
       9 [-]: SUB R6 R7 R8 
      10 [-]: DIV R5 R6 R1 
      11 [-]: FASTCALL1 2 R5 L0
      12 [-]: GETIMPORT R4 5 [0xE4A5B3CA]
      13 [-]: CALL R4 1 1  
L 0:  14 [-]: SUB R2 R3 R4 
      15 [-]: GETUPVAL R5 0
      16 [-]: GETTABLEKS R4 R5 K6 ["mMaxNodeY"]
      17 [-]: GETUPVAL R6 0
      18 [-]: GETTABLEKS R5 R6 K7 ["mMinNodeY"]
      19 [-]: SUB R3 R4 R5 
      20 [-]: GETUPVAL R8 0
      21 [-]: GETTABLEKS R7 R8 K7 ["mMinNodeY"]
      22 [-]: GETTABLEKS R8 R0 K8 ["mY"]
      23 [-]: SUB R6 R7 R8 
      24 [-]: DIV R5 R6 R3 
      25 [-]: FASTCALL1 2 R5 L1
      26 [-]: GETIMPORT R4 5 [0xE4A5B3CA]
      27 [-]: CALL R4 1 1  
L 1:  28 [-]: DUPTABLE R5 11
      29 [-]: SETTABLEKS R2 R5 K9 ["x"]
      30 [-]: SETTABLEKS R4 R5 K10 ["y"]
      31 [-]: RETURN R5 1  


; Name:            
; Defined at line: 989
; #Upvalues:       3
; #Parameters:     0
; Is_vararg:       0
; Max Stack Size:  3

       0 [-]: GETUPVAL R0 0
       1 [-]: NAMECALL R0 R0 K0 [0xED1AB921]
       2 [-]: CALL R0 1 1  
       3 [-]: FASTCALL1 62 R0 L0
       4 [-]: MOVE R2 R0   
       5 [-]: GETIMPORT R1 2 [0x7B998233]
       6 [-]: CALL R1 1 1  
L 0:   7 [-]: JUMPIFNOT R1 L1
       8 [-]: RETURN R0 0  
L 1:   9 [-]: GETTABLEKS R1 R0 K3 ["mPolarity"]
      10 [-]: SETUPVAL R1 1
      11 [-]: GETUPVAL R1 2
      12 [-]: CALL R1 0 0  
      13 [-]: RETURN R0 0  


; Name:            
; Defined at line: 999
; #Upvalues:       12
; #Parameters:     2
; Is_vararg:       0
; Max Stack Size:  10

       0 [-]: GETIMPORT R2 1 [0x2D0FAD09]
       1 [-]: LOADK R3 K2 ["EE.Interface.Components.List"]
       2 [-]: CALL R2 1 1  
       3 [-]: GETTABLEKS R3 R2 K3 [0x9383BC56]
       4 [-]: GETIMPORT R4 5 [0xAE91E43B]
       5 [-]: MOVE R5 R0   
       6 [-]: CALL R3 2 1  
       7 [-]: JUMPIFNOT R1 L0
       8 [-]: LOADK R6 K6 ["UniversalNodeSelected"]
       9 [-]: LOADK R7 K7 ["UniversalNodeFocused"]
      10 [-]: LOADK R8 K8 ["UniversalNodeUnfocused"]
      11 [-]: LOADK R9 K9 ["UniversalNodePressed"]
      12 [-]: NAMECALL R4 R3 K10 [0x1E5B5CFE]
      13 [-]: CALL R4 5 0  
      14 [-]: JUMP L2
     
L 0:  15 [-]: GETIMPORT R4 13 [0x781669D7]
      16 [-]: CALL R4 0 1  
      17 [-]: JUMPIFNOT R4 L1
      18 [-]: LOADK R6 K14 ["NodePressed"]
      19 [-]: LOADK R7 K15 ["NodeFocused"]
      20 [-]: LOADK R8 K16 ["NodeUnfocused"]
      21 [-]: LOADK R9 K17 ["NodeSelected"]
      22 [-]: NAMECALL R4 R3 K10 [0x1E5B5CFE]
      23 [-]: CALL R4 5 0  
      24 [-]: JUMP L2
     
L 1:  25 [-]: LOADK R6 K17 ["NodeSelected"]
      26 [-]: LOADK R7 K15 ["NodeFocused"]
      27 [-]: LOADK R8 K16 ["NodeUnfocused"]
      28 [-]: LOADK R9 K14 ["NodePressed"]
      29 [-]: NAMECALL R4 R3 K10 [0x1E5B5CFE]
      30 [-]: CALL R4 5 0  
L 2:  31 [-]: GETUPVAL R5 0
      32 [-]: GETTABLEKS R4 R5 K18 [0x06D055F9]
      33 [-]: MOVE R5 R1   
      34 [-]: LOADN R6 85  
      35 [-]: LOADN R7 0   
      36 [-]: CALL R4 3 1  
      37 [-]: SETTABLEKS R4 R3 K19 ["mForcedVerticalSeparation"]
      38 [-]: LOADN R4 0   
      39 [-]: SETTABLEKS R4 R3 K20 ["mForcedHorizontalSeparation"]
      40 [-]: LOADN R4 0   
      41 [-]: SETTABLEKS R4 R3 K21 ["mElementTransitionTime"]
      42 [-]: LOADN R4 5000
      43 [-]: SETTABLEKS R4 R3 K22 ["mInitialDepth"]
      44 [-]: GETIMPORT R4 5 [0xAE91E43B]
      45 [-]: LOADK R6 K23 ["Tree.Node.Rings"]
      46 [-]: LOADN R7 1   
      47 [-]: NAMECALL R4 R4 K24 [0x91A24E4B]
      48 [-]: CALL R4 3 1  
      49 [-]: SETTABLEKS R4 R3 K25 ["mOrigRingsYPos"]
      50 [-]: DUPCLOSURE R4 K26 []
      51 [-]: SETTABLEKS R4 R3 K27 ["Print"]
      52 [-]: NEWCLOSURE R4 P1
      53 [-]: MOVE R0 R3   
      54 [-]: MOVE R2 R0   
      55 [-]: MOVE R0 R1   
      56 [-]: MOVE R2 R1   
      57 [-]: SETTABLEKS R4 R3 K28 ["mOnFocusedCallback"]
      58 [-]: NEWCLOSURE R4 P2
      59 [-]: MOVE R0 R3   
      60 [-]: SETTABLEKS R4 R3 K29 ["mOnUnfocusedCallback"]
      61 [-]: NEWCLOSURE R4 P3
      62 [-]: MOVE R2 R0   
      63 [-]: MOVE R2 R2   
      64 [-]: MOVE R2 R3   
      65 [-]: SETTABLEKS R4 R3 K30 ["UpdateElementColor"]
      66 [-]: NEWCLOSURE R4 P4
      67 [-]: MOVE R0 R3   
      68 [-]: SETTABLEKS R4 R3 K31 ["mOnPressedCallback"]
      69 [-]: NEWCLOSURE R4 P5
      70 [-]: MOVE R2 R4   
      71 [-]: MOVE R0 R3   
      72 [-]: SETTABLEKS R4 R3 K32 ["mOnSelectedCallback"]
      73 [-]: NEWCLOSURE R4 P6
      74 [-]: MOVE R2 R0   
      75 [-]: MOVE R2 R5   
      76 [-]: MOVE R2 R6   
      77 [-]: MOVE R2 R7   
      78 [-]: MOVE R2 R8   
      79 [-]: MOVE R2 R4   
      80 [-]: MOVE R0 R3   
      81 [-]: SETTABLEKS R4 R3 K33 ["mUpdateRank"]
      82 [-]: NEWCLOSURE R4 P7
      83 [-]: MOVE R0 R3   
      84 [-]: MOVE R0 R1   
      85 [-]: MOVE R2 R0   
      86 [-]: MOVE R2 R2   
      87 [-]: SETTABLEKS R4 R3 K34 ["mElementDrawCallback"]
      88 [-]: JUMPIF R1 L3 
      89 [-]: DUPCLOSURE R4 K35 []
      90 [-]: SETTABLEKS R4 R3 K36 ["CalculateX"]
      91 [-]: DUPCLOSURE R4 K37 []
      92 [-]: SETTABLEKS R4 R3 K38 ["CalculateY"]
L 3:  93 [-]: DUPCLOSURE R4 K39 []
      94 [-]: SETTABLEKS R4 R3 K40 ["SetupPreInterpolationValues"]
      95 [-]: DUPCLOSURE R4 K41 []
      96 [-]: MOVE R2 R1   
      97 [-]: SETTABLEKS R4 R3 K42 ["SetFocusNode"]
      98 [-]: DUPCLOSURE R4 K43 []
      99 [-]: MOVE R2 R0   
     100 [-]: SETTABLEKS R4 R3 K44 ["PreviewCalloutFunction"]
     101 [-]: NEWCLOSURE R4 P13
     102 [-]: MOVE R2 R3   
     103 [-]: MOVE R2 R9   
     104 [-]: MOVE R0 R3   
     105 [-]: MOVE R2 R0   
     106 [-]: MOVE R0 R1   
     107 [-]: MOVE R2 R10  
     108 [-]: SETTABLEKS R4 R3 K45 ["ShowNodeInfo"]
     109 [-]: NEWCLOSURE R4 P14
     110 [-]: MOVE R0 R3   
     111 [-]: MOVE R2 R11  
     112 [-]: MOVE R2 R0   
     113 [-]: MOVE R2 R2   
     114 [-]: MOVE R2 R1   
     115 [-]: SETTABLEKS R4 R3 K46 ["ShowNode"]
     116 [-]: NEWCLOSURE R4 P15
     117 [-]: MOVE R2 R2   
     118 [-]: MOVE R2 R0   
     119 [-]: MOVE R0 R1   
     120 [-]: SETTABLEKS R4 R3 K47 ["HideNode"]
     121 [-]: NEWCLOSURE R4 P16
     122 [-]: MOVE R0 R3   
     123 [-]: SETTABLEKS R4 R3 K48 ["SelectNode"]
     124 [-]: RETURN R3 1  


; Name:            
; Defined at line: 1449
; #Upvalues:       2
; #Parameters:     2
; Is_vararg:       0
; Max Stack Size:  12

       0 [-]: DIVK R2 R0 K0 [220]
       1 [-]: DIVK R3 R1 K0 [220]
       2 [-]: DIV R4 R2 R0 
       3 [-]: SETUPVAL R4 0
       4 [-]: DIV R4 R3 R1 
       5 [-]: SETUPVAL R4 1
       6 [-]: GETIMPORT R4 2 [0xAE91E43B]
       7 [-]: LOADK R6 K3 ["Bg"]
       8 [-]: LOADN R7 12  
       9 [-]: MOVE R8 R0   
      10 [-]: NAMECALL R4 R4 K4 [0x67BC869F]
      11 [-]: CALL R4 4 0  
      12 [-]: GETIMPORT R4 2 [0xAE91E43B]
      13 [-]: LOADK R6 K3 ["Bg"]
      14 [-]: LOADN R7 13  
      15 [-]: MOVE R8 R1   
      16 [-]: NAMECALL R4 R4 K4 [0x67BC869F]
      17 [-]: CALL R4 4 0  
      18 [-]: GETIMPORT R4 2 [0xAE91E43B]
      19 [-]: LOADK R6 K3 ["Bg"]
      20 [-]: LOADK R7 K5 ["TileRepeats"]
      21 [-]: MOVE R8 R2   
      22 [-]: MOVE R9 R3   
      23 [-]: LOADN R10 0  
      24 [-]: LOADN R11 0  
      25 [-]: NAMECALL R4 R4 K6 [0x91E13703]
      26 [-]: CALL R4 7 0  
      27 [-]: GETIMPORT R4 2 [0xAE91E43B]
      28 [-]: LOADK R6 K7 ["Vignette"]
      29 [-]: LOADN R7 12  
      30 [-]: MOVE R8 R0   
      31 [-]: NAMECALL R4 R4 K4 [0x67BC869F]
      32 [-]: CALL R4 4 0  
      33 [-]: GETIMPORT R4 2 [0xAE91E43B]
      34 [-]: LOADK R6 K7 ["Vignette"]
      35 [-]: LOADN R7 13  
      36 [-]: MOVE R8 R1   
      37 [-]: NAMECALL R4 R4 K4 [0x67BC869F]
      38 [-]: CALL R4 4 0  
      39 [-]: RETURN R0 0  


; Name:            
; Defined at line: 1466
; #Upvalues:       3
; #Parameters:     0
; Is_vararg:       0
; Max Stack Size:  7

       0 [-]: GETUPVAL R1 0
       1 [-]: GETTABLEKS R0 R1 K0 [0x44537ADF]
       2 [-]: GETIMPORT R1 2 [0xAE91E43B]
       3 [-]: CALL R0 1 2  
       4 [-]: GETUPVAL R2 1
       5 [-]: MOVE R3 R0   
       6 [-]: MOVE R4 R1   
       7 [-]: CALL R2 2 0  
       8 [-]: GETUPVAL R2 2
       9 [-]: JUMPXEQKNIL R2 L0
      10 [-]: GETUPVAL R2 2
      11 [-]: GETIMPORT R4 2 [0xAE91E43B]
      12 [-]: NAMECALL R4 R4 K3 [0x6B837788]
      13 [-]: CALL R4 1 1  
      14 [-]: GETIMPORT R5 2 [0xAE91E43B]
      15 [-]: NAMECALL R5 R5 K4 [0xAF9FDA9F]
      16 [-]: CALL R5 1 -1 
      17 [-]: NAMECALL R2 R2 K5 [0xFAA69527]
      18 [-]: CALL R2 -1 0 
L 0:  19 [-]: RETURN R0 0  


; Name:            
; Defined at line: 1474
; #Upvalues:       1
; #Parameters:     2
; Is_vararg:       0
; Max Stack Size:  8

       0 [-]: LOADN R2 1   
       1 [-]: LOADN R3 1   
       2 [-]: JUMPIFNOTEQ R0 R3 L0
       3 [-]: LOADN R2 5   
       4 [-]: JUMP L4
     
L 0:   5 [-]: LOADN R3 2   
       6 [-]: JUMPIFNOTEQ R0 R3 L1
       7 [-]: LOADN R2 3   
       8 [-]: JUMP L4
     
L 1:   9 [-]: LOADN R3 4   
      10 [-]: JUMPIFNOTEQ R0 R3 L2
      11 [-]: LOADN R2 2   
      12 [-]: JUMP L4
     
L 2:  13 [-]: LOADN R3 3   
      14 [-]: JUMPIFNOTEQ R0 R3 L3
      15 [-]: LOADN R2 1   
      16 [-]: JUMP L4
     
L 3:  17 [-]: LOADN R3 7   
      18 [-]: JUMPIFNOTEQ R0 R3 L4
      19 [-]: LOADN R2 4   
L 4:  20 [-]: GETUPVAL R4 0
      21 [-]: GETTABLEKS R3 R4 K0 [0x06D055F9]
      22 [-]: MOVE R4 R1   
      23 [-]: GETIMPORT R6 2 [0xFABFC9BC]
      24 [-]: GETTABLE R5 R6 R2
      25 [-]: GETIMPORT R7 4 [0x520895D9]
      26 [-]: GETTABLE R6 R7 R2
      27 [-]: CALL R3 3 -1 
      28 [-]: RETURN R3 -1 


; Name:            
; Defined at line: 1492
; #Upvalues:       6
; #Parameters:     5
; Is_vararg:       0
; Max Stack Size:  18

       0 [-]: GETIMPORT R5 1 [0x25D99D89]
       1 [-]: MOVE R7 R1   
       2 [-]: NAMECALL R5 R5 K2 [0x9DE9471A]
       3 [-]: CALL R5 2 1  
       4 [-]: GETIMPORT R6 5 [0x1ABA4D9E]
       5 [-]: CALL R6 0 1  
       6 [-]: SETTABLEKS R1 R6 K6 ["mItemType"]
       7 [-]: GETTABLEKS R7 R6 K7 ["mInstance"]
       8 [-]: LOADK R9 K8 [""]
       9 [-]: NAMECALL R7 R7 K9 [0xC6B8B3F2]
      10 [-]: CALL R7 2 1  
      11 [-]: JUMPIFNOTEQ R7 R4 L0
      12 [-]: LOADB R8 0 +1
L 0:  13 [-]: LOADB R8 1   
L 1:  14 [-]: LOADN R9 0   
      15 [-]: GETUPVAL R11 0
      16 [-]: GETTABLEKS R10 R11 K10 [0x06D055F9]
      17 [-]: GETTABLEKS R13 R5 K6 ["mItemType"]
      18 [-]: FASTCALL1 62 R13 L2
      19 [-]: GETIMPORT R12 12 [0x7B998233]
      20 [-]: CALL R12 1 1 
L 2:  21 [-]: NOT R11 R12  
      22 [-]: GETTABLEKS R12 R5 K13 ["mLevel"]
      23 [-]: LOADN R13 0  
      24 [-]: CALL R10 3 1 
      25 [-]: MOVE R9 R10  
      26 [-]: JUMPIFNOT R8 L3
      27 [-]: GETTABLEKS R10 R6 K7 ["mInstance"]
      28 [-]: LOADK R12 K8 [""]
      29 [-]: NAMECALL R10 R10 K14 [0x91FB01D5]
      30 [-]: CALL R10 2 1 
      31 [-]: MOVE R9 R10  
L 3:  32 [-]: GETTABLEKS R10 R6 K7 ["mInstance"]
      33 [-]: MOVE R12 R9  
      34 [-]: NAMECALL R10 R10 K15 [0x86BA2663]
      35 [-]: CALL R10 2 1 
      36 [-]: SETTABLEKS R10 R6 K16 ["mUpgradeFingerprint"]
      37 [-]: LOADN R10 0  
      38 [-]: SETTABLEKS R10 R6 K17 ["mItemCount"]
      39 [-]: GETTABLEKS R10 R6 K18 ["mItemId"]
      40 [-]: LOADK R11 K8 [""]
      41 [-]: SETTABLEKS R11 R10 K19 ["mId"]
      42 [-]: NEWTABLE R10 32 0
      43 [-]: GETTABLEKS R12 R5 K6 ["mItemType"]
      44 [-]: FASTCALL1 62 R12 L4
      45 [-]: GETIMPORT R11 12 [0x7B998233]
      46 [-]: CALL R11 1 1 
L 4:  47 [-]: SETTABLEKS R11 R10 K20 ["mLocked"]
      48 [-]: GETTABLEKS R11 R10 K20 ["mLocked"]
      49 [-]: SETTABLEKS R11 R10 K21 ["mUniversalLocked"]
      50 [-]: GETTABLEKS R11 R6 K7 ["mInstance"]
      51 [-]: NAMECALL R11 R11 K22 [0xF22AFCAE]
      52 [-]: CALL R11 1 1 
      53 [-]: SETTABLEKS R11 R10 K23 ["mMinOpType"]
      54 [-]: SETTABLEKS R0 R10 K24 ["mUniqueId"]
      55 [-]: GETUPVAL R13 1
      56 [-]: LENGTH R12 R13
      57 [-]: JUMPXEQKN R12 K25 L5 [0]
      58 [-]: LOADB R11 0 +1
L 5:  59 [-]: LOADB R11 1  
L 6:  60 [-]: SETTABLEKS R11 R10 K26 ["mRootNode"]
      61 [-]: GETUPVAL R12 2
      62 [-]: GETTABLEKS R11 R12 K27 [0xFC31B69E]
      63 [-]: MOVE R12 R6  
      64 [-]: GETUPVAL R15 1
      65 [-]: LENGTH R14 R15
      66 [-]: ADDK R13 R14 K28 [1]
      67 [-]: CALL R11 2 1 
      68 [-]: SETTABLEKS R11 R10 K29 ["mCard"]
      69 [-]: GETTABLEKS R11 R10 K29 ["mCard"]
      70 [-]: SETTABLEKS R9 R11 K30 ["mLevelFloat"]
      71 [-]: GETTABLEKS R11 R6 K7 ["mInstance"]
      72 [-]: NAMECALL R11 R11 K31 [0x517C8079]
      73 [-]: CALL R11 1 1 
      74 [-]: SETTABLEKS R11 R10 K32 ["mPassive"]
      75 [-]: GETTABLEKS R11 R6 K7 ["mInstance"]
      76 [-]: NAMECALL R11 R11 K33 [0x030AE5E5]
      77 [-]: CALL R11 1 1 
      78 [-]: SETTABLEKS R11 R10 K34 ["mApplyToLoc"]
      79 [-]: GETTABLEKS R11 R6 K7 ["mInstance"]
      80 [-]: NAMECALL R11 R11 K35 [0xCC9058AA]
      81 [-]: CALL R11 1 1 
      82 [-]: SETTABLEKS R11 R10 K36 ["mCanBeUniversal"]
      83 [-]: GETTABLEKS R11 R5 K37 ["mIsUniversal"]
      84 [-]: SETTABLEKS R11 R10 K38 ["mUniversal"]
      85 [-]: GETTABLEKS R11 R10 K36 ["mCanBeUniversal"]
      86 [-]: JUMPIFNOT R11 L7
      87 [-]: GETTABLEKS R11 R10 K38 ["mUniversal"]
      88 [-]: JUMPIF R11 L7
      89 [-]: GETTABLEKS R11 R6 K7 ["mInstance"]
      90 [-]: NAMECALL R11 R11 K39 [0x127B1376]
      91 [-]: CALL R11 1 1 
      92 [-]: SETTABLEKS R11 R10 K40 ["mUniversalCost"]
L 7:  93 [-]: GETTABLEKS R12 R10 K29 ["mCard"]
      94 [-]: GETTABLEKS R11 R12 K41 ["mName"]
      95 [-]: SETTABLEKS R11 R10 K41 ["mName"]
      96 [-]: GETTABLEKS R12 R10 K29 ["mCard"]
      97 [-]: GETTABLEKS R11 R12 K42 ["mIcon"]
      98 [-]: SETTABLEKS R11 R10 K42 ["mIcon"]
      99 [-]: GETTABLEKS R12 R10 K29 ["mCard"]
     100 [-]: GETTABLEKS R11 R12 K43 ["mDesc"]
     101 [-]: SETTABLEKS R11 R10 K44 ["mDescription"]
     102 [-]: GETTABLEKS R12 R10 K29 ["mCard"]
     103 [-]: GETTABLEKS R11 R12 K45 ["mNextLvlDesc"]
     104 [-]: SETTABLEKS R11 R10 K45 ["mNextLvlDesc"]
     105 [-]: GETTABLEKS R12 R10 K29 ["mCard"]
     106 [-]: GETTABLEKS R11 R12 K46 ["mLevelLimit"]
     107 [-]: SETTABLEKS R11 R10 K47 ["mMaxRank"]
     108 [-]: GETUPVAL R12 0
     109 [-]: GETTABLEKS R11 R12 K10 [0x06D055F9]
     110 [-]: GETTABLEKS R14 R5 K6 ["mItemType"]
     111 [-]: FASTCALL1 62 R14 L8
     112 [-]: GETIMPORT R13 12 [0x7B998233]
     113 [-]: CALL R13 1 1 
L 8: 114 [-]: NOT R12 R13  
     115 [-]: GETTABLEKS R13 R5 K13 ["mLevel"]
     116 [-]: LOADN R14 0  
     117 [-]: CALL R11 3 1 
     118 [-]: SETTABLEKS R11 R10 K48 ["mRank"]
     119 [-]: GETTABLEKS R11 R10 K36 ["mCanBeUniversal"]
     120 [-]: JUMPIFNOT R11 L9
     121 [-]: GETUPVAL R11 3
     122 [-]: MOVE R12 R7  
     123 [-]: LOADB R13 1  
     124 [-]: CALL R11 2 1 
     125 [-]: SETTABLEKS R11 R10 K49 ["mPolarityIcon"]
L 9: 126 [-]: JUMPIFNOT R8 L12
     127 [-]: LOADB R11 1  
     128 [-]: SETTABLEKS R11 R10 K50 ["mOtherPolarity"]
     129 [-]: GETTABLEKS R12 R10 K38 ["mUniversal"]
     130 [-]: NOT R11 R12  
     131 [-]: SETTABLEKS R11 R10 K20 ["mLocked"]
     132 [-]: SETTABLEKS R7 R10 K51 ["mPolarity"]
     133 [-]: SETTABLEKS R2 R10 K52 ["mGraphVisX"]
     134 [-]: SETTABLEKS R3 R10 K53 ["mGraphVisY"]
     135 [-]: GETTABLEKS R12 R10 K52 ["mGraphVisX"]
     136 [-]: MULK R11 R12 K54 [350]
     137 [-]: SETTABLEKS R11 R10 K55 ["mLocalX"]
     138 [-]: GETTABLEKS R12 R10 K53 ["mGraphVisY"]
     139 [-]: MULK R11 R12 K54 [350]
     140 [-]: SETTABLEKS R11 R10 K56 ["mLocalY"]
     141 [-]: GETUPVAL R11 4
     142 [-]: JUMPXEQKNIL R11 L10 NOT
     143 [-]: NEWTABLE R11 0 0
     144 [-]: SETUPVAL R11 4
L10: 145 [-]: GETUPVAL R12 4
     146 [-]: FASTCALL2 52 R12 R10 L11
     147 [-]: MOVE R13 R10 
     148 [-]: GETIMPORT R11 59 [0x23D5322F]
     149 [-]: CALL R11 2 0 
L11: 150 [-]: GETTABLEKS R11 R10 K36 ["mCanBeUniversal"]
     151 [-]: JUMPIF R11 L12
     152 [-]: RETURN R0 0  
L12: 153 [-]: GETTABLEKS R11 R10 K38 ["mUniversal"]
     154 [-]: JUMPIFNOT R11 L13
     155 [-]: GETTABLEKS R11 R10 K48 ["mRank"]
     156 [-]: JUMPXEQKNIL R11 L13
     157 [-]: GETTABLEKS R11 R10 K48 ["mRank"]
     158 [-]: GETTABLEKS R12 R10 K47 ["mMaxRank"]
     159 [-]: JUMPIFNOTEQ R11 R12 L13
     160 [-]: GETTABLEKS R12 R10 K48 ["mRank"]
     161 [-]: ADDK R11 R12 K28 [1]
     162 [-]: SETTABLEKS R11 R10 K48 ["mRank"]
L13: 163 [-]: GETTABLEKS R11 R10 K36 ["mCanBeUniversal"]
     164 [-]: JUMPIFNOT R11 L14
     165 [-]: GETTABLEKS R12 R10 K47 ["mMaxRank"]
     166 [-]: ADDK R11 R12 K28 [1]
     167 [-]: SETTABLEKS R11 R10 K47 ["mMaxRank"]
L14: 168 [-]: GETTABLEKS R11 R10 K48 ["mRank"]
     169 [-]: JUMPXEQKNIL R11 L18
     170 [-]: GETUPVAL R11 5
     171 [-]: MOVE R12 R10 
     172 [-]: CALL R11 1 1 
     173 [-]: SETTABLEKS R11 R10 K60 ["mNextRankTarget"]
     174 [-]: GETTABLEKS R11 R10 K48 ["mRank"]
     175 [-]: GETTABLEKS R12 R10 K47 ["mMaxRank"]
     176 [-]: JUMPIFNOTEQ R11 R12 L15
     177 [-]: GETTABLEKS R11 R10 K60 ["mNextRankTarget"]
     178 [-]: SETTABLEKS R11 R10 K61 ["mNextRankCurrent"]
     179 [-]: JUMP L18
    
L15: 180 [-]: GETUPVAL R12 0
     181 [-]: GETTABLEKS R11 R12 K10 [0x06D055F9]
     182 [-]: GETTABLEKS R14 R10 K29 ["mCard"]
     183 [-]: GETTABLEKS R13 R14 K13 ["mLevel"]
     184 [-]: JUMPXEQKN R13 K25 L16 [0]
     185 [-]: LOADB R12 0 +1
L16: 186 [-]: LOADB R12 1  
L17: 187 [-]: GETTABLEKS R14 R10 K29 ["mCard"]
     188 [-]: GETTABLEKS R13 R14 K30 ["mLevelFloat"]
     189 [-]: GETIMPORT R14 64 [0xC62A6BE2]
     190 [-]: GETTABLEKS R16 R10 K29 ["mCard"]
     191 [-]: GETTABLEKS R15 R16 K30 ["mLevelFloat"]
     192 [-]: GETTABLEKS R17 R10 K29 ["mCard"]
     193 [-]: GETTABLEKS R16 R17 K13 ["mLevel"]
     194 [-]: CALL R14 2 -1
     195 [-]: CALL R11 -1 1
     196 [-]: GETTABLEKS R13 R10 K60 ["mNextRankTarget"]
     197 [-]: MUL R12 R11 R13
     198 [-]: SETTABLEKS R12 R10 K61 ["mNextRankCurrent"]
L18: 199 [-]: LOADNIL R11  
     200 [-]: SETTABLEKS R11 R10 K65 ["mParent"]
     201 [-]: NEWTABLE R11 0 0
     202 [-]: SETTABLEKS R11 R10 K66 ["mChildren"]
     203 [-]: SETTABLEKS R2 R10 K52 ["mGraphVisX"]
     204 [-]: SETTABLEKS R3 R10 K53 ["mGraphVisY"]
     205 [-]: GETTABLEKS R12 R10 K52 ["mGraphVisX"]
     206 [-]: MULK R11 R12 K54 [350]
     207 [-]: SETTABLEKS R11 R10 K55 ["mLocalX"]
     208 [-]: GETTABLEKS R12 R10 K53 ["mGraphVisY"]
     209 [-]: MULK R11 R12 K54 [350]
     210 [-]: SETTABLEKS R11 R10 K56 ["mLocalY"]
     211 [-]: GETUPVAL R12 1
     212 [-]: FASTCALL2 52 R12 R10 L19
     213 [-]: MOVE R13 R10 
     214 [-]: GETIMPORT R11 59 [0x23D5322F]
     215 [-]: CALL R11 2 0 
L19: 216 [-]: RETURN R0 0  


; Name:            
; Defined at line: 1585
; #Upvalues:       1
; #Parameters:     2
; Is_vararg:       0
; Max Stack Size:  10

       0 [-]: JUMPIFNOT R1 L0
       1 [-]: GETTABLEKS R3 R0 K1 ["mGraphVisX"]
       2 [-]: MULK R2 R3 K0 [350]
       3 [-]: SETTABLEKS R2 R0 K2 ["mLocalX"]
       4 [-]: GETTABLEKS R3 R0 K3 ["mGraphVisY"]
       5 [-]: MULK R2 R3 K0 [350]
       6 [-]: SETTABLEKS R2 R0 K4 ["mLocalY"]
L 0:   7 [-]: GETTABLEKS R2 R0 K2 ["mLocalX"]
       8 [-]: GETTABLEKS R3 R0 K4 ["mLocalY"]
       9 [-]: GETTABLEKS R4 R0 K5 ["mParent"]
      10 [-]: JUMPXEQKNIL R4 L1
      11 [-]: GETTABLEKS R5 R0 K5 ["mParent"]
      12 [-]: GETTABLEKS R4 R5 K6 ["mX"]
      13 [-]: ADD R2 R4 R2 
      14 [-]: GETTABLEKS R5 R0 K5 ["mParent"]
      15 [-]: GETTABLEKS R4 R5 K7 ["mY"]
      16 [-]: ADD R3 R4 R3 
L 1:  17 [-]: SETTABLEKS R2 R0 K6 ["mX"]
      18 [-]: SETTABLEKS R3 R0 K7 ["mY"]
      19 [-]: LOADN R6 1   
      20 [-]: GETTABLEKS R7 R0 K8 ["mChildren"]
      21 [-]: LENGTH R4 R7 
      22 [-]: LOADN R5 1   
      23 [-]: FORNPREP R4 L3
L 2:  24 [-]: GETUPVAL R7 0
      25 [-]: GETTABLEKS R9 R0 K8 ["mChildren"]
      26 [-]: GETTABLE R8 R9 R6
      27 [-]: MOVE R9 R1   
      28 [-]: CALL R7 2 0  
      29 [-]: FORNLOOP R4 L2
L 3:  30 [-]: RETURN R0 0  


; Name:            
; Defined at line: 1607
; #Upvalues:       3
; #Parameters:     1
; Is_vararg:       0
; Max Stack Size:  15

       0 [-]: LOADNIL R1   
       1 [-]: LOADN R4 1   
       2 [-]: GETTABLEKS R5 R0 K0 ["mChildren"]
       3 [-]: LENGTH R2 R5 
       4 [-]: LOADN R3 1   
       5 [-]: FORNPREP R2 L4
L 0:   6 [-]: GETUPVAL R6 0
       7 [-]: ADDK R5 R6 K1 [1]
       8 [-]: SETUPVAL R5 0
       9 [-]: LOADK R5 K2 ["Tree.Line"]
      10 [-]: GETUPVAL R6 0
      11 [-]: CONCAT R1 R5 R6
      12 [-]: GETIMPORT R5 4 [0xAE91E43B]
      13 [-]: MOVE R7 R1   
      14 [-]: NAMECALL R5 R5 K5 [0xA7EC3E8A]
      15 [-]: CALL R5 2 1  
      16 [-]: JUMPIF R5 L1 
      17 [-]: GETIMPORT R5 7 [0x015284CD]
      18 [-]: LOADK R6 K8 ["."]
      19 [-]: MOVE R7 R1   
      20 [-]: CALL R5 2 1  
      21 [-]: GETIMPORT R6 10 [0x38F10E85]
      22 [-]: GETIMPORT R7 4 [0xAE91E43B]
      23 [-]: LOADK R8 K11 ["Tree.Line1.duplicateMovieClip"]
      24 [-]: LENGTH R10 R5
      25 [-]: GETTABLE R9 R5 R10
      26 [-]: LOADN R11 1000
      27 [-]: GETUPVAL R12 0
      28 [-]: ADD R10 R11 R12
      29 [-]: CALL R6 4 0  
L 1:  30 [-]: GETIMPORT R5 4 [0xAE91E43B]
      31 [-]: MOVE R7 R1   
      32 [-]: LOADN R8 0   
      33 [-]: GETTABLEKS R9 R0 K12 ["mX"]
      34 [-]: NAMECALL R5 R5 K13 [0x67BC869F]
      35 [-]: CALL R5 4 0  
      36 [-]: GETIMPORT R5 4 [0xAE91E43B]
      37 [-]: MOVE R7 R1   
      38 [-]: LOADN R8 1   
      39 [-]: GETTABLEKS R9 R0 K14 ["mY"]
      40 [-]: NAMECALL R5 R5 K13 [0x67BC869F]
      41 [-]: CALL R5 4 0  
      42 [-]: GETUPVAL R6 1
      43 [-]: GETTABLEKS R5 R6 K15 [0xD4EA5665]
      44 [-]: GETUPVAL R7 1
      45 [-]: GETTABLEKS R6 R7 K16 [0x538CF9D0]
      46 [-]: GETTABLEKS R9 R0 K0 ["mChildren"]
      47 [-]: GETTABLE R8 R9 R4
      48 [-]: GETTABLEKS R7 R8 K12 ["mX"]
      49 [-]: GETTABLEKS R10 R0 K0 ["mChildren"]
      50 [-]: GETTABLE R9 R10 R4
      51 [-]: GETTABLEKS R8 R9 K14 ["mY"]
      52 [-]: GETTABLEKS R9 R0 K12 ["mX"]
      53 [-]: GETTABLEKS R10 R0 K14 ["mY"]
      54 [-]: CALL R6 4 -1 
      55 [-]: CALL R5 -1 1 
      56 [-]: GETIMPORT R6 4 [0xAE91E43B]
      57 [-]: MOVE R8 R1   
      58 [-]: LOADN R9 14  
      59 [-]: MINUS R11 R5 
      60 [-]: ADDK R10 R11 K17 [180]
      61 [-]: NAMECALL R6 R6 K13 [0x67BC869F]
      62 [-]: CALL R6 4 0  
      63 [-]: LOADN R6 60  
      64 [-]: GETUPVAL R8 1
      65 [-]: GETTABLEKS R7 R8 K18 [0x91ED4068]
      66 [-]: DUPTABLE R8 21
      67 [-]: GETTABLEKS R9 R0 K12 ["mX"]
      68 [-]: SETTABLEKS R9 R8 K19 ["X"]
      69 [-]: GETTABLEKS R9 R0 K14 ["mY"]
      70 [-]: SETTABLEKS R9 R8 K20 ["Y"]
      71 [-]: DUPTABLE R9 21
      72 [-]: GETTABLEKS R12 R0 K0 ["mChildren"]
      73 [-]: GETTABLE R11 R12 R4
      74 [-]: GETTABLEKS R10 R11 K12 ["mX"]
      75 [-]: SETTABLEKS R10 R9 K19 ["X"]
      76 [-]: GETTABLEKS R12 R0 K0 ["mChildren"]
      77 [-]: GETTABLE R11 R12 R4
      78 [-]: GETTABLEKS R10 R11 K14 ["mY"]
      79 [-]: SETTABLEKS R10 R9 K20 ["Y"]
      80 [-]: CALL R7 2 1  
      81 [-]: LOADN R8 0   
      82 [-]: JUMPXEQKN R5 K22 L3 [90]
      83 [-]: JUMPXEQKN R5 K23 L3 [270]
      84 [-]: JUMPXEQKN R5 K17 L2 NOT [180]
      85 [-]: LOADN R6 30  
L 2:  86 [-]: SUB R7 R7 R6 
      87 [-]: LOADN R9 90  
      88 [-]: JUMPIFNOTLT R9 R5 L3
      89 [-]: LOADN R9 270 
      90 [-]: JUMPIFNOTLT R5 R9 L3
      91 [-]: MOVE R8 R6   
L 3:  92 [-]: GETIMPORT R9 4 [0xAE91E43B]
      93 [-]: MOVE R11 R1  
      94 [-]: LOADK R12 K24 ["InnerLine"]
      95 [-]: LOADN R13 13 
      96 [-]: SUBK R14 R7 K25 [40]
      97 [-]: NAMECALL R9 R9 K26 [0xF64B7262]
      98 [-]: CALL R9 5 0  
      99 [-]: GETIMPORT R9 4 [0xAE91E43B]
     100 [-]: MOVE R11 R1  
     101 [-]: LOADK R12 K24 ["InnerLine"]
     102 [-]: LOADN R13 1  
     103 [-]: ADDK R14 R8 K27 [20]
     104 [-]: NAMECALL R9 R9 K26 [0xF64B7262]
     105 [-]: CALL R9 5 0  
     106 [-]: GETTABLEKS R10 R0 K0 ["mChildren"]
     107 [-]: GETTABLE R9 R10 R4
     108 [-]: SETTABLEKS R1 R9 K28 ["mLineClipName"]
     109 [-]: GETUPVAL R9 2
     110 [-]: GETTABLEKS R11 R0 K0 ["mChildren"]
     111 [-]: GETTABLE R10 R11 R4
     112 [-]: CALL R9 1 0  
     113 [-]: FORNLOOP R2 L0
L 4: 114 [-]: RETURN R0 0  


; Name:            
; Defined at line: 1643
; #Upvalues:       1
; #Parameters:     1
; Is_vararg:       0
; Max Stack Size:  11

       0 [-]: LOADK R1 K0 ["/Lotus/Language/OstronCrafting/Crafting_Preview_NoIcon"]
       1 [-]: GETUPVAL R2 0
       2 [-]: JUMPIF R2 L1 
       3 [-]: GETIMPORT R2 2 [0x25D99D89]
       4 [-]: NAMECALL R2 R2 K3 [0xA340C0E2]
       5 [-]: CALL R2 1 1  
       6 [-]: JUMPIFNOTEQ R2 R0 L0
       7 [-]: LOADK R1 K4 ["/Lotus/Language/Menu/FocusPrimary"]
       8 [-]: JUMP L1
     
L 0:   9 [-]: LOADK R1 K5 ["/Lotus/Language/Menu/FocusSecondary"]
L 1:  10 [-]: GETIMPORT R2 7 [0xAE91E43B]
      11 [-]: LOADK R4 K8 ["Title.State"]
      12 [-]: LOADN R5 29  
      13 [-]: GETIMPORT R6 11 [0x3F3E4D12]
      14 [-]: GETIMPORT R7 7 [0xAE91E43B]
      15 [-]: MOVE R9 R1   
      16 [-]: LOADB R10 0  
      17 [-]: NAMECALL R7 R7 K12 [0x42B04007]
      18 [-]: CALL R7 3 -1 
      19 [-]: CALL R6 -1 -1
      20 [-]: NAMECALL R2 R2 K13 [0x5F56EEAB]
      21 [-]: CALL R2 -1 0 
      22 [-]: RETURN R0 0  


; Name:            
; Defined at line: 1655
; #Upvalues:       11
; #Parameters:     0
; Is_vararg:       0
; Max Stack Size:  17

       0 [-]: GETIMPORT R1 1 [0xCB00102D]
       1 [-]: GETUPVAL R2 0
       2 [-]: GETTABLE R0 R1 R2
       3 [-]: GETIMPORT R3 3 [0x25D99D89]
       4 [-]: NAMECALL R3 R3 K4 [0x62C81B76]
       5 [-]: CALL R3 1 -1 
       6 [-]: NAMECALL R1 R0 K5 [0x2D13148B]
       7 [-]: CALL R1 -1 0 
       8 [-]: NAMECALL R1 R0 K6 [0xDF3589C6]
       9 [-]: CALL R1 1 1  
      10 [-]: NAMECALL R2 R1 K7 [0x9CB57E2B]
      11 [-]: CALL R2 1 1  
      12 [-]: LOADK R5 K8 [""]
      13 [-]: NAMECALL R3 R0 K9 [0xC6B8B3F2]
      14 [-]: CALL R3 2 1  
      15 [-]: GETUPVAL R4 1
      16 [-]: MOVE R5 R0   
      17 [-]: CALL R4 1 0  
      18 [-]: NEWTABLE R4 0 0
      19 [-]: SETUPVAL R4 2
      20 [-]: GETIMPORT R4 11 [0xC8802016]
      21 [-]: GETTABLEKS R5 R2 K12 ["nodes"]
      22 [-]: CALL R4 1 3  
      23 [-]: FORGPREP_INEXT R4 L1
L 0:  24 [-]: MOVE R11 R7  
      25 [-]: NAMECALL R9 R2 K13 [0x79E008A0]
      26 [-]: CALL R9 2 1  
      27 [-]: GETTABLEKS R11 R2 K14 ["nodeTypes"]
      28 [-]: GETTABLE R10 R11 R7
      29 [-]: GETIMPORT R13 16 ["gLotusArtifactUpgradeType"]
      30 [-]: NAMECALL R11 R10 K17 [0xF2DEAF69]
      31 [-]: CALL R11 2 1 
      32 [-]: JUMPIFNOT R11 L1
      33 [-]: GETIMPORT R13 19 ["gLotusFocusAbilityType"]
      34 [-]: NAMECALL R11 R10 K17 [0xF2DEAF69]
      35 [-]: CALL R11 2 1 
      36 [-]: JUMPIF R11 L1
      37 [-]: GETUPVAL R11 3
      38 [-]: MOVE R12 R8  
      39 [-]: MOVE R13 R10 
      40 [-]: GETTABLEKS R14 R9 K20 ["x"]
      41 [-]: GETTABLEKS R15 R9 K21 ["y"]
      42 [-]: MOVE R16 R3  
      43 [-]: CALL R11 5 0 
L 1:  44 [-]: FORGLOOP R4 L0 2 [inext]
      45 [-]: GETUPVAL R4 4
      46 [-]: JUMPXEQKNIL R4 L12
      47 [-]: NEWTABLE R4 0 0
      48 [-]: LOADN R7 1   
      49 [-]: GETUPVAL R8 4
      50 [-]: LENGTH R5 R8 
      51 [-]: LOADN R6 1   
      52 [-]: FORNPREP R5 L4
L 2:  53 [-]: GETUPVAL R10 4
      54 [-]: GETTABLE R9 R10 R7
      55 [-]: GETTABLEKS R8 R9 K22 ["mUniversal"]
      56 [-]: JUMPIFNOT R8 L3
      57 [-]: DUPTABLE R8 28
      58 [-]: GETUPVAL R11 4
      59 [-]: GETTABLE R10 R11 R7
      60 [-]: GETTABLEKS R9 R10 K23 ["mName"]
      61 [-]: SETTABLEKS R9 R8 K23 ["mName"]
      62 [-]: GETUPVAL R11 4
      63 [-]: GETTABLE R10 R11 R7
      64 [-]: GETTABLEKS R9 R10 K24 ["mGraphVisX"]
      65 [-]: SETTABLEKS R9 R8 K24 ["mGraphVisX"]
      66 [-]: GETUPVAL R11 4
      67 [-]: GETTABLE R10 R11 R7
      68 [-]: GETTABLEKS R9 R10 K25 ["mGraphVisY"]
      69 [-]: SETTABLEKS R9 R8 K25 ["mGraphVisY"]
      70 [-]: GETUPVAL R11 4
      71 [-]: GETTABLE R10 R11 R7
      72 [-]: GETTABLEKS R9 R10 K26 ["mLocalX"]
      73 [-]: SETTABLEKS R9 R8 K26 ["mLocalX"]
      74 [-]: GETUPVAL R11 4
      75 [-]: GETTABLE R10 R11 R7
      76 [-]: GETTABLEKS R9 R10 K27 ["mLocalY"]
      77 [-]: SETTABLEKS R9 R8 K27 ["mLocalY"]
      78 [-]: FASTCALL2 52 R4 R8 L3
      79 [-]: MOVE R10 R4  
      80 [-]: MOVE R11 R8  
      81 [-]: GETIMPORT R9 31 [0x23D5322F]
      82 [-]: CALL R9 2 0  
L 3:  83 [-]: FORNLOOP R5 L2
L 4:  84 [-]: LOADN R7 1   
      85 [-]: LENGTH R5 R4 
      86 [-]: LOADN R6 1   
      87 [-]: FORNPREP R5 L6
L 5:  88 [-]: GETTABLE R8 R4 R7
      89 [-]: GETUPVAL R11 4
      90 [-]: GETTABLE R10 R11 R7
      91 [-]: GETTABLEKS R9 R10 K24 ["mGraphVisX"]
      92 [-]: SETTABLEKS R9 R8 K24 ["mGraphVisX"]
      93 [-]: GETTABLE R8 R4 R7
      94 [-]: GETUPVAL R11 4
      95 [-]: GETTABLE R10 R11 R7
      96 [-]: GETTABLEKS R9 R10 K25 ["mGraphVisY"]
      97 [-]: SETTABLEKS R9 R8 K25 ["mGraphVisY"]
      98 [-]: GETTABLE R8 R4 R7
      99 [-]: GETUPVAL R11 4
     100 [-]: GETTABLE R10 R11 R7
     101 [-]: GETTABLEKS R9 R10 K26 ["mLocalX"]
     102 [-]: SETTABLEKS R9 R8 K26 ["mLocalX"]
     103 [-]: GETTABLE R8 R4 R7
     104 [-]: GETUPVAL R11 4
     105 [-]: GETTABLE R10 R11 R7
     106 [-]: GETTABLEKS R9 R10 K27 ["mLocalY"]
     107 [-]: SETTABLEKS R9 R8 K27 ["mLocalY"]
     108 [-]: FORNLOOP R5 L5
L 6: 109 [-]: LOADN R7 1   
     110 [-]: LENGTH R5 R4 
     111 [-]: LOADN R6 1   
     112 [-]: FORNPREP R5 L11
L 7: 113 [-]: GETTABLE R9 R4 R7
     114 [-]: GETTABLEKS R8 R9 K23 ["mName"]
     115 [-]: LOADN R11 1  
     116 [-]: GETUPVAL R12 2
     117 [-]: LENGTH R9 R12
     118 [-]: LOADN R10 1  
     119 [-]: FORNPREP R9 L10
L 8: 120 [-]: GETUPVAL R14 2
     121 [-]: GETTABLE R13 R14 R11
     122 [-]: GETTABLEKS R12 R13 K23 ["mName"]
     123 [-]: JUMPIFNOTEQ R12 R8 L9
     124 [-]: GETUPVAL R13 2
     125 [-]: GETTABLE R12 R13 R11
     126 [-]: GETTABLE R14 R4 R7
     127 [-]: GETTABLEKS R13 R14 K24 ["mGraphVisX"]
     128 [-]: SETTABLEKS R13 R12 K24 ["mGraphVisX"]
     129 [-]: GETUPVAL R13 2
     130 [-]: GETTABLE R12 R13 R11
     131 [-]: GETTABLE R14 R4 R7
     132 [-]: GETTABLEKS R13 R14 K25 ["mGraphVisY"]
     133 [-]: SETTABLEKS R13 R12 K25 ["mGraphVisY"]
     134 [-]: GETUPVAL R13 2
     135 [-]: GETTABLE R12 R13 R11
     136 [-]: GETTABLE R14 R4 R7
     137 [-]: GETTABLEKS R13 R14 K26 ["mLocalX"]
     138 [-]: SETTABLEKS R13 R12 K26 ["mLocalX"]
     139 [-]: GETUPVAL R13 2
     140 [-]: GETTABLE R12 R13 R11
     141 [-]: GETTABLE R14 R4 R7
     142 [-]: GETTABLEKS R13 R14 K27 ["mLocalY"]
     143 [-]: SETTABLEKS R13 R12 K27 ["mLocalY"]
     144 [-]: GETUPVAL R13 2
     145 [-]: GETTABLE R12 R13 R11
     146 [-]: LOADB R13 0  
     147 [-]: SETTABLEKS R13 R12 K32 ["mRankUpBtnReleased"]
     148 [-]: JUMP L10
    
L 9: 149 [-]: FORNLOOP R9 L8
L10: 150 [-]: FORNLOOP R5 L7
L11: 151 [-]: LOADNIL R5   
     152 [-]: SETUPVAL R5 4
L12: 153 [-]: LOADN R6 1   
     154 [-]: GETTABLEKS R7 R2 K33 ["edgePairs"]
     155 [-]: LENGTH R4 R7 
     156 [-]: LOADN R5 2   
     157 [-]: FORNPREP R4 L16
L13: 158 [-]: GETUPVAL R7 5
     159 [-]: GETTABLEKS R9 R2 K33 ["edgePairs"]
     160 [-]: GETTABLE R8 R9 R6
     161 [-]: CALL R7 1 1  
     162 [-]: JUMPXEQKNIL R7 L15
     163 [-]: GETUPVAL R8 5
     164 [-]: GETTABLEKS R10 R2 K33 ["edgePairs"]
     165 [-]: ADDK R11 R6 K34 [1]
     166 [-]: GETTABLE R9 R10 R11
     167 [-]: CALL R8 1 1  
     168 [-]: JUMPXEQKNIL R8 L15
     169 [-]: GETTABLEKS R10 R7 K35 ["mChildren"]
     170 [-]: FASTCALL2 52 R10 R8 L14
     171 [-]: MOVE R11 R8  
     172 [-]: GETIMPORT R9 31 [0x23D5322F]
     173 [-]: CALL R9 2 0  
L14: 174 [-]: SETTABLEKS R7 R8 K36 ["mParent"]
L15: 175 [-]: FORNLOOP R4 L13
L16: 176 [-]: GETIMPORT R4 38 [0x38F10E85]
     177 [-]: GETIMPORT R5 40 [0xAE91E43B]
     178 [-]: LOADK R6 K41 ["Tree.Node.swapDepths"]
     179 [-]: GETUPVAL R8 6
     180 [-]: GETTABLEKS R7 R8 K42 ["mInitialDepth"]
     181 [-]: CALL R4 3 0  
     182 [-]: LOADN R4 0   
     183 [-]: SETUPVAL R4 7
     184 [-]: LOADB R4 0   
     185 [-]: GETUPVAL R6 2
     186 [-]: GETTABLEN R5 R6 1
     187 [-]: JUMPXEQKNIL R5 L21
     188 [-]: GETUPVAL R5 8
     189 [-]: GETUPVAL R7 2
     190 [-]: GETTABLEN R6 R7 1
     191 [-]: LOADB R7 0   
     192 [-]: CALL R5 2 0  
     193 [-]: GETUPVAL R5 9
     194 [-]: GETUPVAL R7 2
     195 [-]: GETTABLEN R6 R7 1
     196 [-]: CALL R5 1 0  
     197 [-]: GETUPVAL R5 6
     198 [-]: GETUPVAL R8 2
     199 [-]: GETTABLEN R7 R8 1
     200 [-]: LOADB R8 1   
     201 [-]: NAMECALL R5 R5 K43 [0xBAD4316F]
     202 [-]: CALL R5 3 0  
     203 [-]: LOADN R7 2   
     204 [-]: GETUPVAL R8 2
     205 [-]: LENGTH R5 R8 
     206 [-]: LOADN R6 1   
     207 [-]: FORNPREP R5 L21
L17: 208 [-]: GETUPVAL R10 2
     209 [-]: GETTABLE R9 R10 R7
     210 [-]: GETTABLEKS R8 R9 K44 ["mOtherPolarity"]
     211 [-]: JUMPIFNOT R8 L19
     212 [-]: MOVE R8 R4   
     213 [-]: JUMPIF R8 L18
     214 [-]: GETUPVAL R11 2
     215 [-]: GETTABLE R10 R11 R7
     216 [-]: GETTABLEKS R9 R10 K45 ["mUniversalLocked"]
     217 [-]: NOT R8 R9    
L18: 218 [-]: MOVE R4 R8   
     219 [-]: GETUPVAL R8 10
     220 [-]: GETUPVAL R11 2
     221 [-]: GETTABLE R10 R11 R7
     222 [-]: LOADB R11 1  
     223 [-]: NAMECALL R8 R8 K43 [0xBAD4316F]
     224 [-]: CALL R8 3 0  
     225 [-]: JUMP L20
    
L19: 226 [-]: GETUPVAL R8 6
     227 [-]: GETUPVAL R11 2
     228 [-]: GETTABLE R10 R11 R7
     229 [-]: LOADB R11 1  
     230 [-]: NAMECALL R8 R8 K43 [0xBAD4316F]
     231 [-]: CALL R8 3 0  
L20: 232 [-]: FORNLOOP R5 L17
L21: 233 [-]: GETUPVAL R5 6
     234 [-]: NAMECALL R5 R5 K46 [0x71E9AC81]
     235 [-]: CALL R5 1 0  
     236 [-]: GETUPVAL R5 10
     237 [-]: SETTABLEKS R4 R5 K47 ["mVisible"]
     238 [-]: JUMPIFNOT R4 L22
     239 [-]: GETUPVAL R5 10
     240 [-]: NAMECALL R5 R5 K46 [0x71E9AC81]
     241 [-]: CALL R5 1 0  
     242 [-]: RETURN R0 0  
L22: 243 [-]: GETIMPORT R5 40 [0xAE91E43B]
     244 [-]: LOADK R7 K48 ["RightContainer.UniversalList"]
     245 [-]: LOADN R8 11  
     246 [-]: LOADB R9 0   
     247 [-]: NAMECALL R5 R5 K49 [0xAADE900E]
     248 [-]: CALL R5 4 0  
     249 [-]: RETURN R0 0  


; Name:            
; Defined at line: 1747
; #Upvalues:       6
; #Parameters:     0
; Is_vararg:       0
; Max Stack Size:  14

       0 [-]: GETIMPORT R0 1 [0xAE91E43B]
       1 [-]: LOADK R2 K2 ["Tree"]
       2 [-]: LOADN R3 0   
       3 [-]: NAMECALL R0 R0 K3 [0x91A24E4B]
       4 [-]: CALL R0 3 1  
       5 [-]: GETIMPORT R1 1 [0xAE91E43B]
       6 [-]: LOADK R3 K2 ["Tree"]
       7 [-]: LOADN R4 1   
       8 [-]: NAMECALL R1 R1 K3 [0x91A24E4B]
       9 [-]: CALL R1 3 1  
      10 [-]: LOADN R2 0   
      11 [-]: LOADN R3 0   
      12 [-]: LOADN R4 0   
      13 [-]: LOADN R5 0   
      14 [-]: GETIMPORT R6 5 [0xC8802016]
      15 [-]: GETUPVAL R7 0
      16 [-]: CALL R6 1 3  
      17 [-]: FORGPREP_INEXT R6 L4
L 0:  18 [-]: GETTABLEKS R11 R10 K6 ["mX"]
      19 [-]: JUMPXEQKNIL R11 L4
      20 [-]: GETTABLEKS R11 R10 K7 ["mY"]
      21 [-]: JUMPXEQKNIL R11 L4
      22 [-]: GETTABLEKS R11 R10 K6 ["mX"]
      23 [-]: JUMPIFNOTLT R11 R2 L1
      24 [-]: GETTABLEKS R2 R10 K6 ["mX"]
L 1:  25 [-]: GETTABLEKS R11 R10 K6 ["mX"]
      26 [-]: JUMPIFNOTLT R3 R11 L2
      27 [-]: GETTABLEKS R3 R10 K6 ["mX"]
L 2:  28 [-]: GETTABLEKS R11 R10 K7 ["mY"]
      29 [-]: JUMPIFNOTLT R11 R4 L3
      30 [-]: GETTABLEKS R4 R10 K7 ["mY"]
L 3:  31 [-]: GETTABLEKS R11 R10 K7 ["mY"]
      32 [-]: JUMPIFNOTLT R5 R11 L4
      33 [-]: GETTABLEKS R5 R10 K7 ["mY"]
L 4:  34 [-]: FORGLOOP R6 L0 2 [inext]
      35 [-]: GETIMPORT R6 9 [0x2D0FAD09]
      36 [-]: LOADK R7 K10 ["EE.Interface.Components.DragScroll"]
      37 [-]: CALL R6 1 1  
      38 [-]: GETTABLEKS R7 R6 K11 [0xAE6791BA]
      39 [-]: GETIMPORT R8 1 [0xAE91E43B]
      40 [-]: LOADK R9 K2 ["Tree"]
      41 [-]: SUB R10 R0 R3
      42 [-]: SUB R11 R1 R5
      43 [-]: SUB R12 R0 R2
      44 [-]: SUB R13 R1 R4
      45 [-]: CALL R7 6 1  
      46 [-]: SETUPVAL R7 1
      47 [-]: GETUPVAL R7 1
      48 [-]: SETTABLEKS R2 R7 K12 ["mMinNodeX"]
      49 [-]: GETUPVAL R7 1
      50 [-]: SETTABLEKS R3 R7 K13 ["mMaxNodeX"]
      51 [-]: GETUPVAL R7 1
      52 [-]: SETTABLEKS R4 R7 K14 ["mMinNodeY"]
      53 [-]: GETUPVAL R7 1
      54 [-]: SETTABLEKS R5 R7 K15 ["mMaxNodeY"]
      55 [-]: GETUPVAL R7 1
      56 [-]: NEWCLOSURE R8 P0
      57 [-]: MOVE R2 R2   
      58 [-]: SETTABLEKS R8 R7 K16 ["OnScroll"]
      59 [-]: GETUPVAL R7 1
      60 [-]: NEWCLOSURE R8 P1
      61 [-]: MOVE R2 R1   
      62 [-]: MOVE R2 R3   
      63 [-]: SETTABLEKS R8 R7 K17 ["mOnStopDrag"]
      64 [-]: GETUPVAL R7 1
      65 [-]: NEWCLOSURE R8 P2
      66 [-]: MOVE R2 R3   
      67 [-]: MOVE R2 R1   
      68 [-]: SETTABLEKS R8 R7 K18 ["mOnDeselectCallback"]
      69 [-]: GETUPVAL R7 4
      70 [-]: GETUPVAL R9 0
      71 [-]: GETTABLEN R8 R9 1
      72 [-]: CALL R7 1 1  
      73 [-]: GETUPVAL R9 5
      74 [-]: GETTABLEKS R8 R9 K19 ["mVisible"]
      75 [-]: JUMPIFNOT R8 L5
      76 [-]: LOADK R8 K20 [0.68999999999999995]
      77 [-]: SETTABLEKS R8 R7 K21 ["x"]
L 5:  78 [-]: GETUPVAL R8 1
      79 [-]: LOADK R10 K21 ["x"]
      80 [-]: GETTABLEKS R11 R7 K21 ["x"]
      81 [-]: NAMECALL R8 R8 K22 [0x4C4F8717]
      82 [-]: CALL R8 3 0  
      83 [-]: GETUPVAL R8 1
      84 [-]: LOADK R10 K23 ["y"]
      85 [-]: GETTABLEKS R11 R7 K23 ["y"]
      86 [-]: NAMECALL R8 R8 K22 [0x4C4F8717]
      87 [-]: CALL R8 3 0  
      88 [-]: RETURN R0 0  


; Name:            
; Defined at line: 1808
; #Upvalues:       2
; #Parameters:     0
; Is_vararg:       0
; Max Stack Size:  9

       0 [-]: GETUPVAL R1 0
       1 [-]: LENGTH R0 R1 
       2 [-]: LOADN R1 1   
       3 [-]: JUMPIFNOTLT R0 R1 L0
       4 [-]: LOADB R0 0   
       5 [-]: RETURN R0 1  
L 0:   6 [-]: NEWTABLE R0 0 0
       7 [-]: LOADN R3 1   
       8 [-]: GETUPVAL R4 0
       9 [-]: LENGTH R1 R4 
      10 [-]: LOADN R2 1   
      11 [-]: FORNPREP R1 L3
L 1:  12 [-]: GETIMPORT R4 2 [0x925E2BBB]
      13 [-]: GETUPVAL R7 0
      14 [-]: GETTABLE R6 R7 R3
      15 [-]: GETTABLEKS R5 R6 K3 ["StoreItem"]
      16 [-]: NAMECALL R5 R5 K4 [0xF278F8A1]
      17 [-]: CALL R5 1 1  
      18 [-]: GETUPVAL R8 0
      19 [-]: GETTABLE R7 R8 R3
      20 [-]: GETTABLEKS R6 R7 K5 ["Count"]
      21 [-]: CALL R4 2 1  
      22 [-]: FASTCALL2 52 R0 R4 L2
      23 [-]: MOVE R6 R0   
      24 [-]: MOVE R7 R4   
      25 [-]: GETIMPORT R5 8 [0x23D5322F]
      26 [-]: CALL R5 2 0  
L 2:  27 [-]: FORNLOOP R1 L1
L 3:  28 [-]: GETIMPORT R1 10 [0x25D99D89]
      29 [-]: MOVE R3 R0   
      30 [-]: GETIMPORT R4 13 ["PolarityTree"]
      31 [-]: LOADK R5 K14 ["OnShardsConverted"]
      32 [-]: NAMECALL R1 R1 K15 [0xCB5761A7]
      33 [-]: CALL R1 4 0  
      34 [-]: LOADB R1 1   
      35 [-]: SETUPVAL R1 1
      36 [-]: LOADB R1 1   
      37 [-]: RETURN R1 1  


; Name:            
; Defined at line: 1826
; #Upvalues:       6
; #Parameters:     2
; Is_vararg:       0
; Max Stack Size:  8

       0 [-]: JUMPIFNOT R0 L2
       1 [-]: GETUPVAL R3 0
       2 [-]: GETUPVAL R4 1
       3 [-]: ADD R2 R3 R4 
       4 [-]: SETUPVAL R2 0
       5 [-]: GETUPVAL R2 2
       6 [-]: LOADB R3 0   
       7 [-]: CALL R2 1 0  
       8 [-]: GETIMPORT R3 1 [0x5D3751F8]
       9 [-]: FASTCALL1 62 R3 L0
      10 [-]: GETIMPORT R2 3 [0x7B998233]
      11 [-]: CALL R2 1 1  
L 0:  12 [-]: JUMPIF R2 L1 
      13 [-]: GETUPVAL R3 3
      14 [-]: GETTABLEKS R2 R3 K4 [0x659D451F]
      15 [-]: GETIMPORT R3 1 [0x5D3751F8]
      16 [-]: CALL R2 1 0  
L 1:  17 [-]: GETUPVAL R3 3
      18 [-]: GETTABLEKS R2 R3 K5 [0xF76783E5]
      19 [-]: GETIMPORT R3 7 [0xAE91E43B]
      20 [-]: LOADK R4 K8 ["Title.Count"]
      21 [-]: GETIMPORT R5 10 [0xBC1C19E8]
      22 [-]: LOADN R6 100 
      23 [-]: LOADN R7 13  
      24 [-]: CALL R2 5 0  
      25 [-]: JUMP L3
     
L 2:  26 [-]: GETUPVAL R3 3
      27 [-]: GETTABLEKS R2 R3 K11 [0xE0CBA3CA]
      28 [-]: GETIMPORT R3 7 [0xAE91E43B]
      29 [-]: LOADK R5 K12 ["/Lotus/Language/TennoWay/ShardConvertFailed"]
      30 [-]: LOADB R6 0   
      31 [-]: NAMECALL R3 R3 K13 [0x42B04007]
      32 [-]: CALL R3 3 -1 
      33 [-]: CALL R2 -1 0 
L 3:  34 [-]: GETIMPORT R2 16 ["BackgroundMovie"]
      35 [-]: JUMPXEQKNIL R2 L4
      36 [-]: GETIMPORT R2 16 ["BackgroundMovie"]
      37 [-]: LOADK R4 K17 ["ShowBlockingMessage"]
      38 [-]: LOADK R5 K18 ["0"]
      39 [-]: NAMECALL R2 R2 K19 [0xE4162EED]
      40 [-]: CALL R2 3 0  
L 4:  41 [-]: LOADN R2 0   
      42 [-]: SETUPVAL R2 1
      43 [-]: LOADNIL R2   
      44 [-]: SETUPVAL R2 4
      45 [-]: LOADB R2 0   
      46 [-]: SETUPVAL R2 5
      47 [-]: RETURN R0 0  


; Name:            
; Defined at line: 1849
; #Upvalues:       1
; #Parameters:     1
; Is_vararg:       0
; Max Stack Size:  5

       0 [-]: GETIMPORT R1 1 [0x03F57322]
       1 [-]: MOVE R2 R0   
       2 [-]: CALL R1 1 1  
       3 [-]: LOADN R2 4   
       4 [-]: JUMPIFNOTEQ R1 R2 L0
       5 [-]: GETUPVAL R1 0
       6 [-]: CALL R1 0 1  
       7 [-]: JUMPIFNOT R1 L0
       8 [-]: GETIMPORT R1 4 ["BackgroundMovie"]
       9 [-]: JUMPXEQKNIL R1 L0
      10 [-]: GETIMPORT R1 4 ["BackgroundMovie"]
      11 [-]: LOADK R3 K5 ["ShowBlockingMessage"]
      12 [-]: LOADK R4 K6 ["1"]
      13 [-]: NAMECALL R1 R1 K7 [0xE4162EED]
      14 [-]: CALL R1 3 0  
L 0:  15 [-]: RETURN R0 0  


; Name:            
; Defined at line: 1855
; #Upvalues:       4
; #Parameters:     0
; Is_vararg:       0
; Max Stack Size:  17

       0 [-]: LOADK R0 K0 ["\r"]
       1 [-]: LOADN R1 0   
       2 [-]: SETUPVAL R1 0
       3 [-]: LOADN R3 1   
       4 [-]: GETUPVAL R4 1
       5 [-]: LENGTH R1 R4 
       6 [-]: LOADN R2 1   
       7 [-]: FORNPREP R1 L1
L 0:   8 [-]: GETUPVAL R5 1
       9 [-]: GETTABLE R4 R5 R3
      10 [-]: GETTABLEKS R5 R4 K1 ["Name"]
      11 [-]: GETTABLEKS R6 R4 K2 ["Count"]
      12 [-]: GETTABLEKS R7 R4 K3 ["SpecialPrice"]
      13 [-]: MOVE R8 R0   
      14 [-]: LOADK R9 K0 ["\r"]
      15 [-]: GETIMPORT R10 5 [0xAE91E43B]
      16 [-]: LOADK R12 K6 ["/Lotus/Language/TennoWay/SimpleConvertConfirmItem"]
      17 [-]: LOADB R13 1  
      18 [-]: DUPTABLE R14 10
      19 [-]: SETTABLEKS R6 R14 K7 ["NUM"]
      20 [-]: SETTABLEKS R5 R14 K8 ["ITEM"]
      21 [-]: GETUPVAL R16 2
      22 [-]: GETTABLEKS R15 R16 K11 [0x1142C7A8]
      23 [-]: MOVE R16 R7  
      24 [-]: CALL R15 1 1 
      25 [-]: SETTABLEKS R15 R14 K9 ["FOCUS"]
      26 [-]: NAMECALL R10 R10 K12 [0x42B04007]
      27 [-]: CALL R10 4 1 
      28 [-]: CONCAT R0 R8 R10
      29 [-]: GETUPVAL R9 0
      30 [-]: MUL R10 R6 R7
      31 [-]: ADD R8 R9 R10
      32 [-]: SETUPVAL R8 0
      33 [-]: FORNLOOP R1 L0
L 1:  34 [-]: MOVE R1 R0   
      35 [-]: LOADK R2 K13 ["\r\r"]
      36 [-]: CONCAT R0 R1 R2
      37 [-]: GETIMPORT R1 5 [0xAE91E43B]
      38 [-]: LOADK R3 K14 ["/Lotus/Language/TennoWay/SimpleConvertConfirm"]
      39 [-]: LOADB R4 1   
      40 [-]: DUPTABLE R5 16
      41 [-]: SETTABLEKS R0 R5 K8 ["ITEM"]
      42 [-]: GETUPVAL R7 2
      43 [-]: GETTABLEKS R6 R7 K11 [0x1142C7A8]
      44 [-]: GETUPVAL R7 0
      45 [-]: CALL R6 1 1  
      46 [-]: SETTABLEKS R6 R5 K9 ["FOCUS"]
      47 [-]: GETIMPORT R6 5 [0xAE91E43B]
      48 [-]: GETUPVAL R8 3
      49 [-]: LOADB R9 0   
      50 [-]: NAMECALL R6 R6 K12 [0x42B04007]
      51 [-]: CALL R6 3 1  
      52 [-]: SETTABLEKS R6 R5 K15 ["WAY"]
      53 [-]: NAMECALL R1 R1 K12 [0x42B04007]
      54 [-]: CALL R1 4 1  
      55 [-]: GETUPVAL R3 2
      56 [-]: GETTABLEKS R2 R3 K17 [0xDEDFDED7]
      57 [-]: MOVE R3 R1   
      58 [-]: LOADK R4 K18 ["OnConvertConfirm"]
      59 [-]: CALL R2 2 0  
      60 [-]: RETURN R0 0  


; Name:            
; Defined at line: 1871
; #Upvalues:       2
; #Parameters:     1
; Is_vararg:       0
; Max Stack Size:  4

       0 [-]: GETUPVAL R2 0
       1 [-]: FASTCALL1 62 R2 L0
       2 [-]: GETIMPORT R1 1 [0x7B998233]
       3 [-]: CALL R1 1 1  
L 0:   4 [-]: JUMPIF R1 L1 
       5 [-]: GETUPVAL R1 0
       6 [-]: NOT R3 R0    
       7 [-]: NAMECALL R1 R1 K2 [0x368AD758]
       8 [-]: CALL R1 2 0  
L 1:   9 [-]: GETUPVAL R2 1
      10 [-]: FASTCALL1 62 R2 L2
      11 [-]: GETIMPORT R1 1 [0x7B998233]
      12 [-]: CALL R1 1 1  
L 2:  13 [-]: JUMPIF R1 L3 
      14 [-]: GETUPVAL R1 1
      15 [-]: NOT R3 R0    
      16 [-]: NAMECALL R1 R1 K3 [0x044B7BE8]
      17 [-]: CALL R1 2 0  
L 3:  18 [-]: RETURN R0 0  


; Name:            
; Defined at line: 1881
; #Upvalues:       2
; #Parameters:     2
; Is_vararg:       0
; Max Stack Size:  6

       0 [-]: JUMPIFNOT R0 L0
       1 [-]: GETIMPORT R2 1 [0xAE91E43B]
       2 [-]: MOVE R4 R1   
       3 [-]: NAMECALL R2 R2 K2 [0x1FD6ABD0]
       4 [-]: CALL R2 2 1  
       5 [-]: SETUPVAL R2 0
       6 [-]: GETUPVAL R2 0
       7 [-]: LOADK R4 K3 ["SetRequiredSelections"]
       8 [-]: LOADK R5 K4 ["1"]
       9 [-]: NAMECALL R2 R2 K5 [0xE4162EED]
      10 [-]: CALL R2 3 0  
L 0:  11 [-]: GETUPVAL R2 1
      12 [-]: MOVE R3 R0   
      13 [-]: CALL R2 1 0  
      14 [-]: RETURN R0 0  


; Name:            
; Defined at line: 1890
; #Upvalues:       7
; #Parameters:     0
; Is_vararg:       0
; Max Stack Size:  17

       0 [-]: GETIMPORT R0 1 [0x25D99D89]
       1 [-]: NAMECALL R0 R0 K2 [0x25A6E75E]
       2 [-]: CALL R0 1 1  
       3 [-]: NEWTABLE R1 0 0
       4 [-]: LOADN R2 0   
       5 [-]: LOADN R5 1   
       6 [-]: GETIMPORT R6 4 [0x9F46B2BE]
       7 [-]: LENGTH R3 R6 
       8 [-]: LOADN R4 1   
       9 [-]: FORNPREP R3 L6
L 0:  10 [-]: GETIMPORT R7 4 [0x9F46B2BE]
      11 [-]: GETTABLE R6 R7 R5
      12 [-]: DUPTABLE R7 6
      13 [-]: LOADN R8 0   
      14 [-]: SETTABLEKS R8 R7 K5 ["mItemCount"]
      15 [-]: GETUPVAL R8 0
      16 [-]: MOVE R10 R6  
      17 [-]: NAMECALL R8 R8 K7 [0x105074FB]
      18 [-]: CALL R8 2 1  
      19 [-]: SETTABLEKS R8 R7 K8 ["StoreItem"]
      20 [-]: GETIMPORT R8 10 [0xAE91E43B]
      21 [-]: GETTABLEKS R10 R7 K8 ["StoreItem"]
      22 [-]: NAMECALL R10 R10 K11 [0xD3A9D01F]
      23 [-]: CALL R10 1 1 
      24 [-]: NAMECALL R10 R10 K12 [0x6D604BA7]
      25 [-]: CALL R10 1 1 
      26 [-]: LOADB R11 0  
      27 [-]: NAMECALL R8 R8 K13 [0x42B04007]
      28 [-]: CALL R8 3 1  
      29 [-]: SETTABLEKS R8 R7 K14 ["Name"]
      30 [-]: GETTABLEKS R8 R7 K8 ["StoreItem"]
      31 [-]: NAMECALL R8 R8 K15 [0x9887D887]
      32 [-]: CALL R8 1 1  
      33 [-]: SETTABLEKS R8 R7 K16 ["SpecialPrice"]
      34 [-]: GETUPVAL R9 1
      35 [-]: GETTABLEKS R8 R9 K17 ["LABEL_TYPE_FOCUS"]
      36 [-]: SETTABLEKS R8 R7 K18 ["PriceLabelType"]
      37 [-]: MOVE R10 R6  
      38 [-]: NAMECALL R8 R0 K19 [0x51B30E60]
      39 [-]: CALL R8 2 1  
      40 [-]: LOADN R9 0   
      41 [-]: JUMPIFNOTLT R9 R8 L1
      42 [-]: SETTABLEKS R8 R7 K5 ["mItemCount"]
      43 [-]: SETTABLEKS R6 R7 K20 ["mItemType"]
L 1:  44 [-]: GETIMPORT R9 22 [0xCFC01047]
      45 [-]: GETUPVAL R10 2
      46 [-]: CALL R9 1 3  
      47 [-]: FORGPREP_NEXT R9 L3
L 2:  48 [-]: GETTABLEKS R14 R13 K23 ["ResourceType"]
      49 [-]: JUMPIFNOTEQ R14 R6 L3
      50 [-]: GETTABLEKS R15 R7 K5 ["mItemCount"]
      51 [-]: GETTABLEKS R16 R13 K24 ["ResourceCost"]
      52 [-]: SUB R14 R15 R16
      53 [-]: SETTABLEKS R14 R7 K5 ["mItemCount"]
L 3:  54 [-]: FORGLOOP R9 L2 2
      55 [-]: FASTCALL2 52 R1 R7 L4
      56 [-]: MOVE R10 R1  
      57 [-]: MOVE R11 R7  
      58 [-]: GETIMPORT R9 27 [0x23D5322F]
      59 [-]: CALL R9 2 0  
L 4:  60 [-]: GETTABLEKS R9 R7 K5 ["mItemCount"]
      61 [-]: LOADN R10 0  
      62 [-]: JUMPIFNOTLT R10 R9 L5
      63 [-]: ADDK R2 R2 K28 [1]
L 5:  64 [-]: FORNLOOP R3 L0
L 6:  65 [-]: JUMPXEQKN R2 K29 L11 NOT [0]
      66 [-]: LOADK R3 K30 [""]
      67 [-]: LOADN R6 1   
      68 [-]: LENGTH R4 R1 
      69 [-]: LOADN R5 1   
      70 [-]: FORNPREP R4 L10
L 7:  71 [-]: MOVE R7 R3   
      72 [-]: GETTABLE R10 R1 R6
      73 [-]: GETTABLEKS R8 R10 K14 ["Name"]
      74 [-]: GETUPVAL R10 3
      75 [-]: GETTABLEKS R9 R10 K31 [0x06D055F9]
      76 [-]: LENGTH R11 R1
      77 [-]: JUMPIFNOTEQ R6 R11 L8
      78 [-]: LOADB R10 0 +1
L 8:  79 [-]: LOADB R10 1  
L 9:  80 [-]: LOADK R11 K32 ["\r\n"]
      81 [-]: LOADK R12 K30 [""]
      82 [-]: CALL R9 3 1  
      83 [-]: CONCAT R3 R7 R9
      84 [-]: FORNLOOP R4 L7
L10:  85 [-]: GETUPVAL R5 3
      86 [-]: GETTABLEKS R4 R5 K33 [0xA53F5E12]
      87 [-]: GETIMPORT R5 10 [0xAE91E43B]
      88 [-]: LOADK R7 K34 ["/Lotus/Language/TennoWay/NoShards"]
      89 [-]: LOADB R8 0   
      90 [-]: DUPTABLE R9 36
      91 [-]: SETTABLEKS R3 R9 K35 ["ITEMS"]
      92 [-]: NAMECALL R5 R5 K13 [0x42B04007]
      93 [-]: CALL R5 4 -1 
      94 [-]: CALL R4 -1 0 
      95 [-]: RETURN R0 0  
L11:  96 [-]: GETIMPORT R3 38 ["_T"]
      97 [-]: LOADB R4 1   
      98 [-]: SETTABLEKS R4 R3 K39 ["InvShardConvertMode"]
      99 [-]: GETIMPORT R3 38 ["_T"]
     100 [-]: NEWCLOSURE R4 P0
     101 [-]: MOVE R0 R1   
     102 [-]: SETTABLEKS R4 R3 K40 ["GetShards"]
     103 [-]: GETIMPORT R3 38 ["_T"]
     104 [-]: NEWCLOSURE R4 P1
     105 [-]: MOVE R2 R4   
     106 [-]: MOVE R2 R5   
     107 [-]: SETTABLEKS R4 R3 K41 ["ShardSelected"]
     108 [-]: GETUPVAL R3 4
     109 [-]: LOADB R4 1   
     110 [-]: GETIMPORT R5 43 [0x6BB68D1C]
     111 [-]: CALL R3 2 0  
     112 [-]: GETUPVAL R3 6
     113 [-]: LOADK R5 K44 ["SetTitle"]
     114 [-]: GETIMPORT R6 10 [0xAE91E43B]
     115 [-]: LOADK R8 K45 ["/Lotus/Language/TennoWay/ConvertShardSelect"]
     116 [-]: LOADB R9 0   
     117 [-]: NAMECALL R6 R6 K13 [0x42B04007]
     118 [-]: CALL R6 3 -1 
     119 [-]: NAMECALL R3 R3 K46 [0xE4162EED]
     120 [-]: CALL R3 -1 0 
     121 [-]: GETUPVAL R3 6
     122 [-]: LOADK R5 K47 ["SetCallBack"]
     123 [-]: LOADK R6 K41 ["ShardSelected"]
     124 [-]: NAMECALL R3 R3 K46 [0xE4162EED]
     125 [-]: CALL R3 3 0  
     126 [-]: GETUPVAL R3 6
     127 [-]: LOADK R5 K48 ["SetElementsFunction"]
     128 [-]: LOADK R6 K40 ["GetShards"]
     129 [-]: NAMECALL R3 R3 K46 [0xE4162EED]
     130 [-]: CALL R3 3 0  
     131 [-]: RETURN R0 0  


; Name:            
; Defined at line: 1965
; #Upvalues:       3
; #Parameters:     0
; Is_vararg:       0
; Max Stack Size:  8

       0 [-]: GETUPVAL R1 0
       1 [-]: FASTCALL1 62 R1 L0
       2 [-]: GETIMPORT R0 1 [0x7B998233]
       3 [-]: CALL R0 1 1  
L 0:   4 [-]: JUMPIF R0 L4 
       5 [-]: LOADN R2 1   
       6 [-]: GETUPVAL R3 1
       7 [-]: LENGTH R0 R3 
       8 [-]: LOADN R1 1   
       9 [-]: FORNPREP R0 L3
L 1:  10 [-]: GETUPVAL R5 1
      11 [-]: GETTABLE R4 R5 R2
      12 [-]: GETTABLEKS R3 R4 K2 ["mClipEnabled"]
      13 [-]: JUMPIFNOT R3 L2
      14 [-]: GETUPVAL R4 2
      15 [-]: GETTABLEKS R3 R4 K3 [0xF76783E5]
      16 [-]: GETIMPORT R4 5 [0xAE91E43B]
      17 [-]: GETUPVAL R7 1
      18 [-]: GETTABLE R6 R7 R2
      19 [-]: GETTABLEKS R5 R6 K6 ["mClipName"]
      20 [-]: GETIMPORT R6 8 [0xBC1C19E8]
      21 [-]: CALL R3 3 0  
L 2:  22 [-]: FORNLOOP R0 L1
L 3:  23 [-]: GETUPVAL R0 0
      24 [-]: LOADK R2 K9 ["SetZoomedPrimary"]
      25 [-]: LOADK R3 K10 [""]
      26 [-]: NAMECALL R0 R0 K11 [0xE4162EED]
      27 [-]: CALL R0 3 0  
L 4:  28 [-]: RETURN R0 0  


; Name:            
; Defined at line: 1976
; #Upvalues:       3
; #Parameters:     0
; Is_vararg:       0
; Max Stack Size:  4

       0 [-]: GETUPVAL R0 0
       1 [-]: GETIMPORT R2 1 [0xCB00102D]
       2 [-]: GETUPVAL R3 1
       3 [-]: GETTABLE R1 R2 R3
       4 [-]: CALL R0 1 0  
       5 [-]: GETUPVAL R0 2
       6 [-]: CALL R0 0 0  
       7 [-]: RETURN R0 0  


; Name:            
; Defined at line: 1981
; #Upvalues:       1
; #Parameters:     0
; Is_vararg:       0
; Max Stack Size:  7

       0 [-]: GETUPVAL R0 0
       1 [-]: GETIMPORT R2 1 [0xB693B6C1]
       2 [-]: CALL R2 0 -1 
       3 [-]: NAMECALL R0 R0 K2 [0xFAA69527]
       4 [-]: CALL R0 -1 0 
       5 [-]: GETUPVAL R0 0
       6 [-]: NAMECALL R0 R0 K3 [0x54AB95F9]
       7 [-]: CALL R0 1 1  
       8 [-]: LOADN R2 100 
       9 [-]: LOADN R4 1   
      10 [-]: ADD R3 R4 R0 
      11 [-]: MUL R1 R2 R3 
      12 [-]: GETIMPORT R2 5 [0xAE91E43B]
      13 [-]: LOADK R4 K6 ["Tree"]
      14 [-]: LOADN R5 5   
      15 [-]: MOVE R6 R1   
      16 [-]: NAMECALL R2 R2 K7 [0x67BC869F]
      17 [-]: CALL R2 4 0  
      18 [-]: GETIMPORT R2 5 [0xAE91E43B]
      19 [-]: LOADK R4 K6 ["Tree"]
      20 [-]: LOADN R5 6   
      21 [-]: MOVE R6 R1   
      22 [-]: NAMECALL R2 R2 K7 [0x67BC869F]
      23 [-]: CALL R2 4 0  
      24 [-]: RETURN R0 0  


; Name:            
; Defined at line: 1990
; #Upvalues:       16
; #Parameters:     0
; Is_vararg:       0
; Max Stack Size:  14

       0 [-]: GETUPVAL R0 0
       1 [-]: JUMPIFNOT R0 L1
       2 [-]: GETIMPORT R1 1 [0xAE91E43B]
       3 [-]: FASTCALL1 62 R1 L0
       4 [-]: GETIMPORT R0 3 [0x7B998233]
       5 [-]: CALL R0 1 1  
L 0:   6 [-]: JUMPIFNOT R0 L2
L 1:   7 [-]: RETURN R0 0  
L 2:   8 [-]: GETIMPORT R0 5 [0xB693B6C1]
       9 [-]: CALL R0 0 1  
      10 [-]: GETIMPORT R1 1 [0xAE91E43B]
      11 [-]: MOVE R3 R0   
      12 [-]: NAMECALL R1 R1 K6 [0x8A8C8D5A]
      13 [-]: CALL R1 2 0  
      14 [-]: GETUPVAL R2 1
      15 [-]: FASTCALL1 62 R2 L3
      16 [-]: GETIMPORT R1 3 [0x7B998233]
      17 [-]: CALL R1 1 1  
L 3:  18 [-]: JUMPIF R1 L4 
      19 [-]: GETUPVAL R1 1
      20 [-]: MOVE R3 R0   
      21 [-]: NAMECALL R1 R1 K7 [0xFAA69527]
      22 [-]: CALL R1 2 0  
L 4:  23 [-]: GETUPVAL R1 2
      24 [-]: JUMPIFNOT R1 L6
      25 [-]: GETUPVAL R1 3
      26 [-]: JUMPIF R1 L5 
      27 [-]: GETUPVAL R1 4
      28 [-]: CALL R1 0 0  
L 5:  29 [-]: RETURN R0 0  
L 6:  30 [-]: GETUPVAL R1 5
      31 [-]: JUMPXEQKNIL R1 L8
      32 [-]: GETIMPORT R1 10 [0x1467D5F4]
      33 [-]: CALL R1 0 1  
      34 [-]: JUMPIFNOT R1 L7
      35 [-]: GETUPVAL R2 5
      36 [-]: GETTABLEKS R1 R2 K11 ["mDragSpeed"]
      37 [-]: GETUPVAL R4 6
      38 [-]: GETTABLEKS R3 R4 K13 ["x"]
      39 [-]: MULK R2 R3 K12 [0.014999999999999999]
      40 [-]: SETTABLEKS R2 R1 K13 ["x"]
      41 [-]: GETUPVAL R2 5
      42 [-]: GETTABLEKS R1 R2 K11 ["mDragSpeed"]
      43 [-]: GETUPVAL R4 6
      44 [-]: GETTABLEKS R3 R4 K14 ["y"]
      45 [-]: MULK R2 R3 K12 [0.014999999999999999]
      46 [-]: SETTABLEKS R2 R1 K14 ["y"]
L 7:  47 [-]: GETUPVAL R1 5
      48 [-]: MOVE R3 R0   
      49 [-]: NAMECALL R1 R1 K7 [0xFAA69527]
      50 [-]: CALL R1 2 0  
L 8:  51 [-]: GETUPVAL R1 7
      52 [-]: JUMPIFNOT R1 L9
      53 [-]: LOADB R1 0   
      54 [-]: SETUPVAL R1 7
      55 [-]: GETUPVAL R4 5
      56 [-]: GETTABLEKS R3 R4 K15 ["mOriginalCoords"]
      57 [-]: GETTABLEKS R2 R3 K13 ["x"]
      58 [-]: GETUPVAL R5 5
      59 [-]: GETTABLEKS R4 R5 K16 ["mCurrentCoords"]
      60 [-]: GETTABLEKS R3 R4 K13 ["x"]
      61 [-]: SUB R1 R2 R3 
      62 [-]: GETUPVAL R5 5
      63 [-]: GETTABLEKS R4 R5 K15 ["mOriginalCoords"]
      64 [-]: GETTABLEKS R3 R4 K14 ["y"]
      65 [-]: GETUPVAL R6 5
      66 [-]: GETTABLEKS R5 R6 K16 ["mCurrentCoords"]
      67 [-]: GETTABLEKS R4 R5 K14 ["y"]
      68 [-]: SUB R2 R3 R4 
      69 [-]: GETIMPORT R3 1 [0xAE91E43B]
      70 [-]: LOADK R5 K17 ["Bg"]
      71 [-]: LOADK R6 K18 ["TileOffset"]
      72 [-]: GETUPVAL R8 8
      73 [-]: MUL R7 R8 R1 
      74 [-]: GETUPVAL R9 9
      75 [-]: MUL R8 R9 R2 
      76 [-]: LOADN R9 0   
      77 [-]: LOADN R10 0  
      78 [-]: NAMECALL R3 R3 K19 [0x91E13703]
      79 [-]: CALL R3 7 0  
L 9:  80 [-]: GETUPVAL R1 10
      81 [-]: CALL R1 0 0  
      82 [-]: GETUPVAL R1 11
      83 [-]: CALL R1 0 0  
      84 [-]: GETUPVAL R1 12
      85 [-]: JUMPIFNOT R1 L14
      86 [-]: GETUPVAL R1 12
      87 [-]: GETUPVAL R4 12
      88 [-]: GETTABLEN R3 R4 1
      89 [-]: SUB R2 R3 R0 
      90 [-]: SETTABLEN R2 R1 1
      91 [-]: GETUPVAL R1 12
      92 [-]: LOADN R3 0   
      93 [-]: GETUPVAL R5 12
      94 [-]: GETTABLEN R4 R5 1
      95 [-]: FASTCALL2 18 R3 R4 L10
      96 [-]: GETIMPORT R2 22 [0xB62ECFE0]
      97 [-]: CALL R2 2 1  
L10:  98 [-]: SETTABLEN R2 R1 1
      99 [-]: GETUPVAL R2 13
     100 [-]: GETTABLEKS R1 R2 K23 ["NegativeColor"]
     101 [-]: GETUPVAL R3 13
     102 [-]: GETTABLEKS R2 R3 K24 ["FloatingContentHighlightColor"]
     103 [-]: GETIMPORT R6 28 [0x107BF6DA]
     104 [-]: GETUPVAL R9 12
     105 [-]: GETTABLEN R8 R9 1
     106 [-]: MULK R7 R8 K29 [3]
     107 [-]: CALL R6 1 1  
     108 [-]: MULK R5 R6 K26 [2]
     109 [-]: SUBK R4 R5 K25 [1]
     110 [-]: FASTCALL1 2 R4 L11
     111 [-]: GETIMPORT R3 31 [0xE4A5B3CA]
     112 [-]: CALL R3 1 1  
L11: 113 [-]: MOVE R6 R2   
     114 [-]: MOVE R7 R3   
     115 [-]: NAMECALL R4 R1 K32 [0x9BAFFFE3]
     116 [-]: CALL R4 3 1  
     117 [-]: MOVE R1 R4   
     118 [-]: LOADN R6 2   
     119 [-]: GETUPVAL R7 12
     120 [-]: LENGTH R4 R7 
     121 [-]: LOADN R5 1   
     122 [-]: FORNPREP R4 L13
L12: 123 [-]: GETUPVAL R8 12
     124 [-]: GETTABLE R7 R8 R6
     125 [-]: GETIMPORT R8 1 [0xAE91E43B]
     126 [-]: MOVE R10 R7  
     127 [-]: LOADN R11 36 
     128 [-]: NAMECALL R12 R1 K33 [0xA5D5C8F6]
     129 [-]: CALL R12 1 -1
     130 [-]: NAMECALL R8 R8 K34 [0x67BC869F]
     131 [-]: CALL R8 -1 0 
     132 [-]: FORNLOOP R4 L12
L13: 133 [-]: GETUPVAL R5 12
     134 [-]: GETTABLEN R4 R5 1
     135 [-]: LOADN R5 0   
     136 [-]: JUMPIFNOTLE R4 R5 L14
     137 [-]: LOADNIL R4   
     138 [-]: SETUPVAL R4 12
L14: 139 [-]: GETUPVAL R2 5
     140 [-]: GETTABLEKS R1 R2 K35 ["PendingStartDrag"]
     141 [-]: JUMPIFNOT R1 L15
     142 [-]: GETUPVAL R1 5
     143 [-]: LOADB R2 0   
     144 [-]: SETTABLEKS R2 R1 K35 ["PendingStartDrag"]
     145 [-]: GETUPVAL R1 5
     146 [-]: NAMECALL R1 R1 K36 [0xD033D908]
     147 [-]: CALL R1 1 0  
L15: 148 [-]: GETIMPORT R1 38 [0xE6B41ADB]
     149 [-]: CALL R1 0 1  
     150 [-]: JUMPIFNOT R1 L17
     151 [-]: GETIMPORT R1 10 [0x1467D5F4]
     152 [-]: CALL R1 0 1  
     153 [-]: GETUPVAL R2 14
     154 [-]: JUMPIFEQ R2 R1 L17
     155 [-]: JUMPIFNOT R1 L16
     156 [-]: GETUPVAL R3 15
     157 [-]: GETTABLEKS R2 R3 K39 ["mFocusedNode"]
     158 [-]: JUMPIFNOT R2 L16
     159 [-]: GETUPVAL R3 15
     160 [-]: GETTABLEKS R2 R3 K40 ["HideNode"]
     161 [-]: GETUPVAL R4 15
     162 [-]: GETTABLEKS R3 R4 K39 ["mFocusedNode"]
     163 [-]: CALL R2 1 0  
     164 [-]: GETUPVAL R2 15
     165 [-]: LOADNIL R4   
     166 [-]: NAMECALL R2 R2 K41 [0xB6DB5906]
     167 [-]: CALL R2 2 0  
L16: 168 [-]: SETUPVAL R1 14
L17: 169 [-]: RETURN R0 0  


; Name:            
; Defined at line: 2068
; #Upvalues:       2
; #Parameters:     0
; Is_vararg:       0
; Max Stack Size:  2

       0 [-]: GETUPVAL R0 0
       1 [-]: JUMPIFNOT R0 L0
       2 [-]: RETURN R0 0  
L 0:   3 [-]: GETIMPORT R0 2 [0xE6B41ADB]
       4 [-]: CALL R0 0 1  
       5 [-]: JUMPIF R0 L1 
       6 [-]: GETUPVAL R0 1
       7 [-]: NAMECALL R0 R0 K3 [0xD033D908]
       8 [-]: CALL R0 1 0  
       9 [-]: RETURN R0 0  
L 1:  10 [-]: GETUPVAL R0 1
      11 [-]: LOADB R1 1   
      12 [-]: SETTABLEKS R1 R0 K4 ["PendingStartDrag"]
      13 [-]: RETURN R0 0  


; Name:            
; Defined at line: 2081
; #Upvalues:       1
; #Parameters:     0
; Is_vararg:       0
; Max Stack Size:  2

       0 [-]: GETUPVAL R0 0
       1 [-]: NAMECALL R0 R0 K0 [0xCC5F3150]
       2 [-]: CALL R0 1 0  
       3 [-]: RETURN R0 0  


; Name:            
; Defined at line: 2085
; #Upvalues:       2
; #Parameters:     0
; Is_vararg:       0
; Max Stack Size:  9

       0 [-]: GETUPVAL R1 0
       1 [-]: GETTABLEKS R0 R1 K0 [0x4C232AFC]
       2 [-]: GETIMPORT R1 2 [0xAE91E43B]
       3 [-]: LOADN R2 1   
       4 [-]: LOADK R3 K3 [0.25]
       5 [-]: LOADK R4 K3 [0.25]
       6 [-]: CALL R0 4 0  
       7 [-]: GETIMPORT R0 5 [0x25312C9B]
       8 [-]: GETIMPORT R1 2 [0xAE91E43B]
       9 [-]: LOADK R2 K6 ["Tree"]
      10 [-]: LOADN R3 2   
      11 [-]: NEWTABLE R4 0 2
      12 [-]: LOADN R5 5   
      13 [-]: LOADN R6 6   
      14 [-]: SETLIST R4 R5 2 [1]
      15 [-]: NEWTABLE R5 0 2
      16 [-]: LOADN R6 100 
      17 [-]: LOADN R7 100 
      18 [-]: SETLIST R5 R6 2 [1]
      19 [-]: LOADK R6 K7 [0.34999999999999998]
      20 [-]: LOADK R7 K8 [0.14999999999999999]
      21 [-]: CALL R0 7 0  
      22 [-]: GETIMPORT R0 5 [0x25312C9B]
      23 [-]: GETIMPORT R1 2 [0xAE91E43B]
      24 [-]: LOADK R2 K9 ["Bg"]
      25 [-]: LOADN R3 2   
      26 [-]: NEWTABLE R4 0 1
      27 [-]: LOADN R5 10  
      28 [-]: SETLIST R4 R5 1 [1]
      29 [-]: NEWTABLE R5 0 1
      30 [-]: LOADN R6 100 
      31 [-]: SETLIST R5 R6 1 [1]
      32 [-]: LOADK R6 K3 [0.25]
      33 [-]: LOADK R7 K3 [0.25]
      34 [-]: CALL R0 7 0  
      35 [-]: GETIMPORT R0 5 [0x25312C9B]
      36 [-]: GETIMPORT R1 2 [0xAE91E43B]
      37 [-]: LOADK R2 K10 ["_root"]
      38 [-]: LOADN R3 2   
      39 [-]: NEWTABLE R4 0 3
      40 [-]: LOADN R5 10  
      41 [-]: LOADN R6 5   
      42 [-]: LOADN R7 6   
      43 [-]: SETLIST R4 R5 3 [1]
      44 [-]: NEWTABLE R5 0 3
      45 [-]: LOADN R6 100 
      46 [-]: LOADN R7 100 
      47 [-]: LOADN R8 100 
      48 [-]: SETLIST R5 R6 3 [1]
      49 [-]: LOADK R6 K7 [0.34999999999999998]
      50 [-]: LOADK R7 K8 [0.14999999999999999]
      51 [-]: NEWCLOSURE R8 P0
      52 [-]: MOVE R2 R1   
      53 [-]: CALL R0 8 0  
      54 [-]: RETURN R0 0  


; Name:            
; Defined at line: 2100
; #Upvalues:       25
; #Parameters:     0
; Is_vararg:       0
; Max Stack Size:  18

       0 [-]: GETIMPORT R0 2 [0xE6B41ADB]
       1 [-]: CALL R0 0 1  
       2 [-]: JUMPIFNOT R0 L0
       3 [-]: GETIMPORT R0 4 [0x89326C93]
       4 [-]: NAMECALL R0 R0 K5 [0xFB64E76C]
       5 [-]: CALL R0 1 1  
       6 [-]: LOADB R2 1   
       7 [-]: NAMECALL R0 R0 K6 [0x97C4FF93]
       8 [-]: CALL R0 2 0  
L 0:   9 [-]: GETIMPORT R0 9 ["TreeLocked"]
      10 [-]: JUMPIFNOT R0 L1
      11 [-]: LOADB R0 1   
      12 [-]: SETUPVAL R0 0
L 1:  13 [-]: GETUPVAL R0 1
      14 [-]: CALL R0 0 0  
      15 [-]: GETIMPORT R0 11 [0xBE190284]
      16 [-]: NAMECALL R0 R0 K12 [0xA1C390FE]
      17 [-]: CALL R0 1 1  
      18 [-]: SETUPVAL R0 2
      19 [-]: GETIMPORT R0 11 [0xBE190284]
      20 [-]: LOADB R2 1   
      21 [-]: NAMECALL R0 R0 K13 [0xC02F2CB8]
      22 [-]: CALL R0 2 0  
      23 [-]: GETIMPORT R0 15 [0x2D0FAD09]
      24 [-]: LOADK R1 K16 ["Lotus.Interface.Libs.TimerMgr"]
      25 [-]: CALL R0 1 1  
      26 [-]: GETTABLEKS R1 R0 K17 [0xDE474187]
      27 [-]: CALL R1 0 1  
      28 [-]: SETUPVAL R1 3
      29 [-]: GETUPVAL R2 5
      30 [-]: GETTABLEKS R1 R2 K18 [0xAE6791BA]
      31 [-]: GETIMPORT R2 20 [0xAE91E43B]
      32 [-]: CALL R1 1 1  
      33 [-]: SETUPVAL R1 4
      34 [-]: GETUPVAL R1 4
      35 [-]: GETIMPORT R3 20 [0xAE91E43B]
      36 [-]: LOADK R4 K21 ["Title"]
      37 [-]: NEWTABLE R5 0 2
      38 [-]: GETUPVAL R7 4
      39 [-]: GETTABLEKS R6 R7 K22 ["ANCHOR_V_TOP"]
      40 [-]: GETUPVAL R8 4
      41 [-]: GETTABLEKS R7 R8 K23 ["ANCHOR_H_LEFT"]
      42 [-]: SETLIST R5 R6 2 [1]
      43 [-]: NAMECALL R1 R1 K24 [0x20FF29F7]
      44 [-]: CALL R1 4 0  
      45 [-]: GETUPVAL R1 4
      46 [-]: GETIMPORT R3 20 [0xAE91E43B]
      47 [-]: LOADK R4 K25 ["RightContainer"]
      48 [-]: NEWTABLE R5 0 2
      49 [-]: GETUPVAL R7 4
      50 [-]: GETTABLEKS R6 R7 K22 ["ANCHOR_V_TOP"]
      51 [-]: GETUPVAL R8 4
      52 [-]: GETTABLEKS R7 R8 K26 ["ANCHOR_H_RIGHT"]
      53 [-]: SETLIST R5 R6 2 [1]
      54 [-]: NAMECALL R1 R1 K24 [0x20FF29F7]
      55 [-]: CALL R1 4 0  
      56 [-]: GETUPVAL R1 4
      57 [-]: GETIMPORT R3 20 [0xAE91E43B]
      58 [-]: NAMECALL R3 R3 K27 [0x6B837788]
      59 [-]: CALL R3 1 1  
      60 [-]: GETIMPORT R4 20 [0xAE91E43B]
      61 [-]: NAMECALL R4 R4 K28 [0xAF9FDA9F]
      62 [-]: CALL R4 1 -1 
      63 [-]: NAMECALL R1 R1 K29 [0xFAA69527]
      64 [-]: CALL R1 -1 0 
      65 [-]: GETIMPORT R1 20 [0xAE91E43B]
      66 [-]: LOADB R3 1   
      67 [-]: NAMECALL R1 R1 K30 [0x824D113A]
      68 [-]: CALL R1 2 0  
      69 [-]: GETIMPORT R1 20 [0xAE91E43B]
      70 [-]: NAMECALL R1 R1 K31 [0x33ABEE92]
      71 [-]: CALL R1 1 1  
      72 [-]: SETUPVAL R1 6
      73 [-]: GETIMPORT R1 4 [0x89326C93]
      74 [-]: NAMECALL R1 R1 K5 [0xFB64E76C]
      75 [-]: CALL R1 1 1  
      76 [-]: FASTCALL1 62 R1 L2
      77 [-]: MOVE R3 R1   
      78 [-]: GETIMPORT R2 33 [0x7B998233]
      79 [-]: CALL R2 1 1  
L 2:  80 [-]: JUMPIF R2 L3 
      81 [-]: NAMECALL R2 R1 K34 [0x5578D98B]
      82 [-]: CALL R2 1 1  
      83 [-]: SETUPVAL R2 7
L 3:  84 [-]: GETUPVAL R3 7
      85 [-]: FASTCALL1 62 R3 L4
      86 [-]: GETIMPORT R2 33 [0x7B998233]
      87 [-]: CALL R2 1 1  
L 4:  88 [-]: JUMPIFNOT R2 L5
      89 [-]: GETIMPORT R2 36 ["MenuSuitAvatar"]
      90 [-]: SETUPVAL R2 7
L 5:  91 [-]: GETUPVAL R3 8
      92 [-]: GETTABLEKS R2 R3 K37 [0x659D451F]
      93 [-]: GETIMPORT R3 39 [0x0856E17D]
      94 [-]: CALL R2 1 0  
      95 [-]: GETUPVAL R2 9
      96 [-]: CALL R2 0 0  
      97 [-]: GETIMPORT R3 41 [0x25D99D89]
      98 [-]: FASTCALL1 62 R3 L6
      99 [-]: GETIMPORT R2 33 [0x7B998233]
     100 [-]: CALL R2 1 1  
L 6: 101 [-]: JUMPIF R2 L7 
     102 [-]: GETIMPORT R2 41 [0x25D99D89]
     103 [-]: NAMECALL R2 R2 K42 [0x5963DABA]
     104 [-]: CALL R2 1 1  
     105 [-]: SETUPVAL R2 10
L 7: 106 [-]: GETIMPORT R2 44 ["PolarityTree"]
     107 [-]: JUMPXEQKNIL R2 L12
     108 [-]: GETIMPORT R2 44 ["PolarityTree"]
     109 [-]: LOADN R3 1   
     110 [-]: JUMPIFNOTEQ R2 R3 L8
     111 [-]: GETUPVAL R3 12
     112 [-]: GETTABLEKS R2 R3 K45 ["MADURAI"]
     113 [-]: SETUPVAL R2 11
     114 [-]: LOADK R2 K46 ["/Lotus/Language/TennoWay/Madurai"]
     115 [-]: SETUPVAL R2 13
     116 [-]: LOADK R2 K47 ["/Lotus/Language/TennoWay/MaduraiDescription"]
     117 [-]: SETUPVAL R2 14
     118 [-]: JUMP L12
    
L 8: 119 [-]: GETIMPORT R2 44 ["PolarityTree"]
     120 [-]: LOADN R3 2   
     121 [-]: JUMPIFNOTEQ R2 R3 L9
     122 [-]: GETUPVAL R3 12
     123 [-]: GETTABLEKS R2 R3 K48 ["VAZARIN"]
     124 [-]: SETUPVAL R2 11
     125 [-]: LOADK R2 K49 ["/Lotus/Language/TennoWay/Vazarin"]
     126 [-]: SETUPVAL R2 13
     127 [-]: LOADK R2 K50 ["/Lotus/Language/TennoWay/VazarinDescription"]
     128 [-]: SETUPVAL R2 14
     129 [-]: JUMP L12
    
L 9: 130 [-]: GETIMPORT R2 44 ["PolarityTree"]
     131 [-]: LOADN R3 3   
     132 [-]: JUMPIFNOTEQ R2 R3 L10
     133 [-]: GETUPVAL R3 12
     134 [-]: GETTABLEKS R2 R3 K51 ["NARAMON"]
     135 [-]: SETUPVAL R2 11
     136 [-]: LOADK R2 K52 ["/Lotus/Language/TennoWay/Naramon"]
     137 [-]: SETUPVAL R2 13
     138 [-]: LOADK R2 K53 ["/Lotus/Language/TennoWay/NaramonDescription"]
     139 [-]: SETUPVAL R2 14
     140 [-]: JUMP L12
    
L10: 141 [-]: GETIMPORT R2 44 ["PolarityTree"]
     142 [-]: LOADN R3 4   
     143 [-]: JUMPIFNOTEQ R2 R3 L11
     144 [-]: GETUPVAL R3 12
     145 [-]: GETTABLEKS R2 R3 K54 ["ZENURIK"]
     146 [-]: SETUPVAL R2 11
     147 [-]: LOADK R2 K55 ["/Lotus/Language/TennoWay/Zenurik"]
     148 [-]: SETUPVAL R2 13
     149 [-]: LOADK R2 K56 ["/Lotus/Language/TennoWay/ZenurikDescription"]
     150 [-]: SETUPVAL R2 14
     151 [-]: JUMP L12
    
L11: 152 [-]: GETIMPORT R2 44 ["PolarityTree"]
     153 [-]: LOADN R3 7   
     154 [-]: JUMPIFNOTEQ R2 R3 L12
     155 [-]: GETUPVAL R3 12
     156 [-]: GETTABLEKS R2 R3 K57 ["UNAIRU"]
     157 [-]: SETUPVAL R2 11
     158 [-]: LOADK R2 K58 ["/Lotus/Language/TennoWay/Unairu"]
     159 [-]: SETUPVAL R2 13
     160 [-]: LOADK R2 K59 ["/Lotus/Language/TennoWay/UnairuDescription"]
     161 [-]: SETUPVAL R2 14
L12: 162 [-]: GETIMPORT R2 20 [0xAE91E43B]
     163 [-]: LOADN R4 0   
     164 [-]: NAMECALL R2 R2 K60 [0x58BEC6D6]
     165 [-]: CALL R2 2 0  
     166 [-]: GETIMPORT R2 20 [0xAE91E43B]
     167 [-]: LOADK R4 K61 ["_root"]
     168 [-]: LOADN R5 10  
     169 [-]: LOADN R6 0   
     170 [-]: NAMECALL R2 R2 K62 [0x67BC869F]
     171 [-]: CALL R2 4 0  
     172 [-]: GETIMPORT R2 20 [0xAE91E43B]
     173 [-]: LOADK R4 K63 ["Bg"]
     174 [-]: LOADN R5 10  
     175 [-]: LOADN R6 0   
     176 [-]: NAMECALL R2 R2 K62 [0x67BC869F]
     177 [-]: CALL R2 4 0  
     178 [-]: GETIMPORT R2 20 [0xAE91E43B]
     179 [-]: LOADK R4 K64 ["Vignette"]
     180 [-]: LOADN R5 10  
     181 [-]: LOADN R6 30  
     182 [-]: NAMECALL R2 R2 K62 [0x67BC869F]
     183 [-]: CALL R2 4 0  
     184 [-]: GETIMPORT R2 20 [0xAE91E43B]
     185 [-]: LOADK R4 K63 ["Bg"]
     186 [-]: GETIMPORT R5 66 [0x3B3EEBE4]
     187 [-]: NAMECALL R2 R2 K67 [0xD5181643]
     188 [-]: CALL R2 3 0  
     189 [-]: GETIMPORT R2 20 [0xAE91E43B]
     190 [-]: LOADK R4 K68 ["Tree"]
     191 [-]: LOADN R5 5   
     192 [-]: LOADN R6 10  
     193 [-]: NAMECALL R2 R2 K62 [0x67BC869F]
     194 [-]: CALL R2 4 0  
     195 [-]: GETIMPORT R2 20 [0xAE91E43B]
     196 [-]: LOADK R4 K68 ["Tree"]
     197 [-]: LOADN R5 6   
     198 [-]: LOADN R6 10  
     199 [-]: NAMECALL R2 R2 K62 [0x67BC869F]
     200 [-]: CALL R2 4 0  
     201 [-]: GETIMPORT R2 20 [0xAE91E43B]
     202 [-]: LOADK R4 K68 ["Tree"]
     203 [-]: LOADN R5 0   
     204 [-]: GETIMPORT R7 20 [0xAE91E43B]
     205 [-]: NAMECALL R7 R7 K70 [0x091C120E]
     206 [-]: CALL R7 1 1  
     207 [-]: MULK R6 R7 K69 [0.5]
     208 [-]: NAMECALL R2 R2 K62 [0x67BC869F]
     209 [-]: CALL R2 4 0  
     210 [-]: GETIMPORT R2 20 [0xAE91E43B]
     211 [-]: LOADK R4 K68 ["Tree"]
     212 [-]: LOADN R5 1   
     213 [-]: GETIMPORT R7 20 [0xAE91E43B]
     214 [-]: NAMECALL R7 R7 K72 [0x2CC9D281]
     215 [-]: CALL R7 1 1  
     216 [-]: MULK R6 R7 K71 [0.44]
     217 [-]: NAMECALL R2 R2 K62 [0x67BC869F]
     218 [-]: CALL R2 4 0  
     219 [-]: GETIMPORT R2 20 [0xAE91E43B]
     220 [-]: LOADK R4 K73 ["Tree.Image"]
     221 [-]: LOADN R5 10  
     222 [-]: LOADN R6 25  
     223 [-]: NAMECALL R2 R2 K62 [0x67BC869F]
     224 [-]: CALL R2 4 0  
     225 [-]: GETIMPORT R2 20 [0xAE91E43B]
     226 [-]: LOADK R4 K73 ["Tree.Image"]
     227 [-]: LOADN R5 12  
     228 [-]: LOADN R6 1024
     229 [-]: NAMECALL R2 R2 K62 [0x67BC869F]
     230 [-]: CALL R2 4 0  
     231 [-]: GETIMPORT R2 20 [0xAE91E43B]
     232 [-]: LOADK R4 K73 ["Tree.Image"]
     233 [-]: LOADN R5 13  
     234 [-]: LOADN R6 1024
     235 [-]: NAMECALL R2 R2 K62 [0x67BC869F]
     236 [-]: CALL R2 4 0  
     237 [-]: GETIMPORT R2 20 [0xAE91E43B]
     238 [-]: LOADK R4 K74 ["Tree.Line"]
     239 [-]: LOADN R5 10  
     240 [-]: LOADN R6 0   
     241 [-]: NAMECALL R2 R2 K62 [0x67BC869F]
     242 [-]: CALL R2 4 0  
     243 [-]: GETIMPORT R2 20 [0xAE91E43B]
     244 [-]: LOADK R4 K73 ["Tree.Image"]
     245 [-]: GETIMPORT R6 76 [0xCC9CA930]
     246 [-]: GETUPVAL R7 11
     247 [-]: GETTABLE R5 R6 R7
     248 [-]: NAMECALL R2 R2 K77 [0x1CB415C1]
     249 [-]: CALL R2 3 0  
     250 [-]: GETIMPORT R2 20 [0xAE91E43B]
     251 [-]: LOADK R4 K78 ["RightContainer.UniversalList.Title"]
     252 [-]: LOADN R5 29  
     253 [-]: GETIMPORT R6 81 [0x3F3E4D12]
     254 [-]: GETIMPORT R7 83 [0x603636AD]
     255 [-]: LOADK R8 K84 ["/Lotus/Language/TennoWay/Universable"]
     256 [-]: NEWTABLE R9 0 0
     257 [-]: CALL R7 2 -1 
     258 [-]: CALL R6 -1 -1
     259 [-]: NAMECALL R2 R2 K85 [0x5F56EEAB]
     260 [-]: CALL R2 -1 0 
     261 [-]: GETIMPORT R2 20 [0xAE91E43B]
     262 [-]: LOADK R4 K78 ["RightContainer.UniversalList.Title"]
     263 [-]: LOADN R5 34  
     264 [-]: NAMECALL R2 R2 K86 [0x91A24E4B]
     265 [-]: CALL R2 3 1  
     266 [-]: GETIMPORT R4 20 [0xAE91E43B]
     267 [-]: LOADK R6 K78 ["RightContainer.UniversalList.Title"]
     268 [-]: LOADN R7 33  
     269 [-]: NAMECALL R4 R4 K86 [0x91A24E4B]
     270 [-]: CALL R4 3 1  
     271 [-]: ADDK R3 R4 K87 [5]
     272 [-]: GETIMPORT R4 20 [0xAE91E43B]
     273 [-]: LOADK R6 K88 ["RightContainer.UniversalList.Underline"]
     274 [-]: LOADN R7 12  
     275 [-]: MOVE R8 R3   
     276 [-]: NAMECALL R4 R4 K62 [0x67BC869F]
     277 [-]: CALL R4 4 0  
     278 [-]: GETIMPORT R4 20 [0xAE91E43B]
     279 [-]: LOADK R6 K88 ["RightContainer.UniversalList.Underline"]
     280 [-]: LOADN R7 0   
     281 [-]: LOADN R9 -138
     282 [-]: DIVK R10 R3 K89 [2]
     283 [-]: SUB R8 R9 R10
     284 [-]: NAMECALL R4 R4 K62 [0x67BC869F]
     285 [-]: CALL R4 4 0  
     286 [-]: GETIMPORT R4 20 [0xAE91E43B]
     287 [-]: LOADK R6 K88 ["RightContainer.UniversalList.Underline"]
     288 [-]: LOADN R7 1   
     289 [-]: LOADN R9 22  
     290 [-]: ADD R8 R9 R2 
     291 [-]: NAMECALL R4 R4 K62 [0x67BC869F]
     292 [-]: CALL R4 4 0  
     293 [-]: GETIMPORT R4 20 [0xAE91E43B]
     294 [-]: LOADK R6 K88 ["RightContainer.UniversalList.Underline"]
     295 [-]: LOADN R7 9   
     296 [-]: GETUPVAL R9 15
     297 [-]: GETTABLEKS R8 R9 K90 ["FloatingContent"]
     298 [-]: NAMECALL R4 R4 K62 [0x67BC869F]
     299 [-]: CALL R4 4 0  
     300 [-]: GETIMPORT R4 20 [0xAE91E43B]
     301 [-]: LOADK R6 K91 ["RightContainer.UniversalList.Nodes"]
     302 [-]: LOADN R7 1   
     303 [-]: LOADN R9 45  
     304 [-]: GETIMPORT R10 20 [0xAE91E43B]
     305 [-]: LOADK R12 K78 ["RightContainer.UniversalList.Title"]
     306 [-]: LOADN R13 34 
     307 [-]: NAMECALL R10 R10 K86 [0x91A24E4B]
     308 [-]: CALL R10 3 1 
     309 [-]: ADD R8 R9 R10
     310 [-]: NAMECALL R4 R4 K62 [0x67BC869F]
     311 [-]: CALL R4 4 0  
     312 [-]: GETIMPORT R4 20 [0xAE91E43B]
     313 [-]: LOADK R6 K92 ["RightContainer.UniversalList.Backer"]
     314 [-]: GETIMPORT R7 94 [0x1011BC64]
     315 [-]: GETIMPORT R8 96 [0xD374E950]
     316 [-]: NAMECALL R4 R4 K97 [0xEF99134F]
     317 [-]: CALL R4 4 0  
     318 [-]: GETIMPORT R4 20 [0xAE91E43B]
     319 [-]: LOADK R6 K98 ["RightContainer.UniversalList.Background"]
     320 [-]: GETIMPORT R7 100 [0x21E58C64]
     321 [-]: NAMECALL R4 R4 K67 [0xD5181643]
     322 [-]: CALL R4 3 0  
     323 [-]: GETIMPORT R4 20 [0xAE91E43B]
     324 [-]: LOADK R6 K101 ["RightContainer.UniversalList.Lines.Left"]
     325 [-]: GETIMPORT R7 100 [0x21E58C64]
     326 [-]: NAMECALL R4 R4 K67 [0xD5181643]
     327 [-]: CALL R4 3 0  
     328 [-]: GETIMPORT R4 20 [0xAE91E43B]
     329 [-]: LOADK R6 K102 ["RightContainer.UniversalList.Lines.Right"]
     330 [-]: GETIMPORT R7 100 [0x21E58C64]
     331 [-]: NAMECALL R4 R4 K67 [0xD5181643]
     332 [-]: CALL R4 3 0  
     333 [-]: GETIMPORT R4 20 [0xAE91E43B]
     334 [-]: LOADK R6 K103 ["Title.Way"]
     335 [-]: LOADN R7 29  
     336 [-]: GETIMPORT R8 81 [0x3F3E4D12]
     337 [-]: GETIMPORT R9 20 [0xAE91E43B]
     338 [-]: GETUPVAL R11 13
     339 [-]: LOADB R12 0  
     340 [-]: NAMECALL R9 R9 K104 [0x42B04007]
     341 [-]: CALL R9 3 -1 
     342 [-]: CALL R8 -1 -1
     343 [-]: NAMECALL R4 R4 K85 [0x5F56EEAB]
     344 [-]: CALL R4 -1 0 
     345 [-]: GETIMPORT R4 20 [0xAE91E43B]
     346 [-]: LOADK R6 K105 ["Title.Watermark"]
     347 [-]: LOADN R7 10  
     348 [-]: LOADN R8 20  
     349 [-]: NAMECALL R4 R4 K62 [0x67BC869F]
     350 [-]: CALL R4 4 0  
     351 [-]: GETIMPORT R4 20 [0xAE91E43B]
     352 [-]: LOADK R6 K106 ["Title.Underline"]
     353 [-]: LOADN R7 0   
     354 [-]: LOADN R8 1   
     355 [-]: NAMECALL R4 R4 K62 [0x67BC869F]
     356 [-]: CALL R4 4 0  
     357 [-]: GETIMPORT R4 20 [0xAE91E43B]
     358 [-]: LOADK R6 K106 ["Title.Underline"]
     359 [-]: LOADN R7 12  
     360 [-]: GETIMPORT R9 20 [0xAE91E43B]
     361 [-]: LOADK R11 K103 ["Title.Way"]
     362 [-]: LOADN R12 33 
     363 [-]: NAMECALL R9 R9 K86 [0x91A24E4B]
     364 [-]: CALL R9 3 1  
     365 [-]: ADDK R8 R9 K107 [64]
     366 [-]: NAMECALL R4 R4 K62 [0x67BC869F]
     367 [-]: CALL R4 4 0  
     368 [-]: GETIMPORT R4 20 [0xAE91E43B]
     369 [-]: LOADK R6 K108 ["Title.Icon"]
     370 [-]: GETIMPORT R8 110 [0x520895D9]
     371 [-]: GETUPVAL R9 11
     372 [-]: GETTABLE R7 R8 R9
     373 [-]: NAMECALL R4 R4 K77 [0x1CB415C1]
     374 [-]: CALL R4 3 0  
     375 [-]: GETIMPORT R4 20 [0xAE91E43B]
     376 [-]: LOADK R6 K105 ["Title.Watermark"]
     377 [-]: GETIMPORT R8 112 [0x6D74BF9A]
     378 [-]: GETUPVAL R9 11
     379 [-]: GETTABLE R7 R8 R9
     380 [-]: NAMECALL R4 R4 K77 [0x1CB415C1]
     381 [-]: CALL R4 3 0  
     382 [-]: GETUPVAL R4 16
     383 [-]: LOADB R5 1   
     384 [-]: CALL R4 1 0  
     385 [-]: GETUPVAL R4 18
     386 [-]: LOADK R5 K113 ["Tree.Node"]
     387 [-]: CALL R4 1 1  
     388 [-]: SETUPVAL R4 17
     389 [-]: GETUPVAL R4 18
     390 [-]: LOADK R5 K114 ["RightContainer.UniversalList.Nodes.Node"]
     391 [-]: LOADB R6 1   
     392 [-]: CALL R4 2 1  
     393 [-]: SETUPVAL R4 19
     394 [-]: GETUPVAL R4 20
     395 [-]: CALL R4 0 0  
     396 [-]: GETUPVAL R4 21
     397 [-]: CALL R4 0 0  
     398 [-]: GETUPVAL R4 22
     399 [-]: CALL R4 0 0  
     400 [-]: GETUPVAL R4 23
     401 [-]: CALL R4 0 0  
     402 [-]: GETUPVAL R4 1
     403 [-]: CALL R4 0 0  
     404 [-]: GETIMPORT R6 20 [0xAE91E43B]
     405 [-]: LOADK R8 K91 ["RightContainer.UniversalList.Nodes"]
     406 [-]: LOADN R9 1   
     407 [-]: NAMECALL R6 R6 K86 [0x91A24E4B]
     408 [-]: CALL R6 3 1  
     409 [-]: GETIMPORT R7 20 [0xAE91E43B]
     410 [-]: LOADK R9 K91 ["RightContainer.UniversalList.Nodes"]
     411 [-]: LOADN R10 13 
     412 [-]: NAMECALL R7 R7 K86 [0x91A24E4B]
     413 [-]: CALL R7 3 1  
     414 [-]: ADD R5 R6 R7 
     415 [-]: SUBK R4 R5 K115 [20]
     416 [-]: GETIMPORT R5 20 [0xAE91E43B]
     417 [-]: LOADK R7 K116 ["RightContainer.UniversalList.Lines"]
     418 [-]: LOADN R8 13  
     419 [-]: MOVE R9 R4   
     420 [-]: NAMECALL R5 R5 K62 [0x67BC869F]
     421 [-]: CALL R5 4 0  
     422 [-]: GETIMPORT R5 20 [0xAE91E43B]
     423 [-]: LOADK R7 K92 ["RightContainer.UniversalList.Backer"]
     424 [-]: LOADN R8 13  
     425 [-]: MOVE R9 R4   
     426 [-]: NAMECALL R5 R5 K62 [0x67BC869F]
     427 [-]: CALL R5 4 0  
     428 [-]: GETIMPORT R5 20 [0xAE91E43B]
     429 [-]: LOADK R7 K98 ["RightContainer.UniversalList.Background"]
     430 [-]: LOADN R8 13  
     431 [-]: MOVE R9 R4   
     432 [-]: NAMECALL R5 R5 K62 [0x67BC869F]
     433 [-]: CALL R5 4 0  
     434 [-]: GETUPVAL R6 8
     435 [-]: GETTABLEKS R5 R6 K117 [0xE5E5A417]
     436 [-]: GETIMPORT R6 20 [0xAE91E43B]
     437 [-]: GETIMPORT R8 20 [0xAE91E43B]
     438 [-]: LOADK R10 K25 ["RightContainer"]
     439 [-]: LOADN R11 1  
     440 [-]: NAMECALL R8 R8 K86 [0x91A24E4B]
     441 [-]: CALL R8 3 1  
     442 [-]: DIVK R9 R4 K89 [2]
     443 [-]: ADD R7 R8 R9 
     444 [-]: CALL R5 2 1  
     445 [-]: GETUPVAL R7 8
     446 [-]: GETTABLEKS R6 R7 K118 [0xD718F59B]
     447 [-]: GETIMPORT R7 20 [0xAE91E43B]
     448 [-]: MULK R8 R4 K119 [0.80000000000000004]
     449 [-]: CALL R6 2 1  
     450 [-]: GETUPVAL R8 8
     451 [-]: GETTABLEKS R7 R8 K120 [0x0DB7934D]
     452 [-]: GETIMPORT R8 20 [0xAE91E43B]
     453 [-]: MULK R9 R4 K121 [0.10000000000000001]
     454 [-]: CALL R7 2 1  
     455 [-]: NEWTABLE R8 0 2
     456 [-]: GETIMPORT R9 96 [0xD374E950]
     457 [-]: GETIMPORT R10 100 [0x21E58C64]
     458 [-]: SETLIST R8 R9 2 [1]
     459 [-]: GETIMPORT R9 123 [0xCFC01047]
     460 [-]: MOVE R10 R8  
     461 [-]: CALL R9 1 3  
     462 [-]: FORGPREP_NEXT R9 L15
L13: 463 [-]: FASTCALL1 62 R13 L14
     464 [-]: MOVE R15 R13 
     465 [-]: GETIMPORT R14 33 [0x7B998233]
     466 [-]: CALL R14 1 1 
L14: 467 [-]: JUMPIF R14 L15
     468 [-]: GETIMPORT R16 126 ["VISIBILITY_CENTER"]
     469 [-]: MOVE R17 R5  
     470 [-]: NAMECALL R14 R13 K127 [0x830EEA67]
     471 [-]: CALL R14 3 0 
     472 [-]: GETIMPORT R16 129 ["VISIBILITY_SIZE"]
     473 [-]: MOVE R17 R6  
     474 [-]: NAMECALL R14 R13 K127 [0x830EEA67]
     475 [-]: CALL R14 3 0 
     476 [-]: GETIMPORT R16 131 ["VISIBILITY_FADE_SIZE"]
     477 [-]: MOVE R17 R7  
     478 [-]: NAMECALL R14 R13 K127 [0x830EEA67]
     479 [-]: CALL R14 3 0 
L15: 480 [-]: FORGLOOP R9 L13 2
     481 [-]: LOADB R9 1   
     482 [-]: SETUPVAL R9 24
     483 [-]: RETURN R0 0  


; Name:            
; Defined at line: 2230
; #Upvalues:       1
; #Parameters:     1
; Is_vararg:       0
; Max Stack Size:  1

       0 [-]: SETUPVAL R0 0
       1 [-]: RETURN R0 0  


; Name:            
; Defined at line: 2234
; #Upvalues:       1
; #Parameters:     0
; Is_vararg:       0
; Max Stack Size:  1

       0 [-]: GETUPVAL R0 0
       1 [-]: CALL R0 0 0  
       2 [-]: RETURN R0 0  


; Name:            
; Defined at line: 2238
; #Upvalues:       1
; #Parameters:     0
; Is_vararg:       0
; Max Stack Size:  1

       0 [-]: GETUPVAL R0 0
       1 [-]: CALL R0 0 0  
       2 [-]: RETURN R0 0  


; Name:            
; Defined at line: 2242
; #Upvalues:       2
; #Parameters:     0
; Is_vararg:       0
; Max Stack Size:  2

       0 [-]: GETUPVAL R0 0
       1 [-]: JUMPIF R0 L1 
       2 [-]: GETUPVAL R1 1
       3 [-]: FASTCALL1 62 R1 L0
       4 [-]: GETIMPORT R0 1 [0x7B998233]
       5 [-]: CALL R0 1 1  
L 0:   6 [-]: JUMPIF R0 L1 
       7 [-]: GETUPVAL R0 1
       8 [-]: NAMECALL R0 R0 K2 [0x8B24CE41]
       9 [-]: CALL R0 1 0  
L 1:  10 [-]: RETURN R0 0  


; Name:            
; Defined at line: 2250
; #Upvalues:       1
; #Parameters:     2
; Is_vararg:       0
; Max Stack Size:  3

       0 [-]: GETUPVAL R2 0
       1 [-]: CALL R2 0 0  
       2 [-]: RETURN R0 0  


; Name:            
; Defined at line: 2254
; #Upvalues:       1
; #Parameters:     1
; Is_vararg:       0
; Max Stack Size:  5

       0 [-]: GETUPVAL R2 0
       1 [-]: FASTCALL1 62 R2 L0
       2 [-]: GETIMPORT R1 1 [0x7B998233]
       3 [-]: CALL R1 1 1  
L 0:   4 [-]: JUMPIF R1 L1 
       5 [-]: GETUPVAL R1 0
       6 [-]: GETIMPORT R3 3 [0x03F57322]
       7 [-]: MOVE R4 R0   
       8 [-]: CALL R3 1 -1 
       9 [-]: NAMECALL R1 R1 K4 [0xDF42446E]
      10 [-]: CALL R1 -1 0 
L 1:  11 [-]: RETURN R0 0  


; Name:            
; Defined at line: 2260
; #Upvalues:       1
; #Parameters:     1
; Is_vararg:       0
; Max Stack Size:  5

       0 [-]: GETUPVAL R2 0
       1 [-]: FASTCALL1 62 R2 L0
       2 [-]: GETIMPORT R1 1 [0x7B998233]
       3 [-]: CALL R1 1 1  
L 0:   4 [-]: JUMPIF R1 L1 
       5 [-]: GETUPVAL R1 0
       6 [-]: GETIMPORT R3 3 [0x03F57322]
       7 [-]: MOVE R4 R0   
       8 [-]: CALL R3 1 -1 
       9 [-]: NAMECALL R1 R1 K4 [0xBCE5A201]
      10 [-]: CALL R1 -1 0 
L 1:  11 [-]: RETURN R0 0  


; Name:            
; Defined at line: 2266
; #Upvalues:       2
; #Parameters:     1
; Is_vararg:       0
; Max Stack Size:  5

       0 [-]: GETUPVAL R1 0
       1 [-]: JUMPIF R1 L1 
       2 [-]: GETUPVAL R2 1
       3 [-]: FASTCALL1 62 R2 L0
       4 [-]: GETIMPORT R1 1 [0x7B998233]
       5 [-]: CALL R1 1 1  
L 0:   6 [-]: JUMPIF R1 L1 
       7 [-]: GETUPVAL R1 1
       8 [-]: GETIMPORT R3 3 [0x03F57322]
       9 [-]: MOVE R4 R0   
      10 [-]: CALL R3 1 1  
      11 [-]: LOADB R4 1   
      12 [-]: NAMECALL R1 R1 K4 [0x070DAA5A]
      13 [-]: CALL R1 3 0  
L 1:  14 [-]: RETURN R0 0  


; Name:            
; Defined at line: 2272
; #Upvalues:       2
; #Parameters:     1
; Is_vararg:       0
; Max Stack Size:  5

       0 [-]: GETUPVAL R1 0
       1 [-]: JUMPIF R1 L1 
       2 [-]: GETUPVAL R2 1
       3 [-]: FASTCALL1 62 R2 L0
       4 [-]: GETIMPORT R1 1 [0x7B998233]
       5 [-]: CALL R1 1 1  
L 0:   6 [-]: JUMPIF R1 L1 
       7 [-]: GETUPVAL R1 1
       8 [-]: GETIMPORT R3 3 [0x03F57322]
       9 [-]: MOVE R4 R0   
      10 [-]: CALL R3 1 1  
      11 [-]: LOADB R4 1   
      12 [-]: NAMECALL R1 R1 K4 [0xAF5319DC]
      13 [-]: CALL R1 3 0  
L 1:  14 [-]: RETURN R0 0  


; Name:            
; Defined at line: 2278
; #Upvalues:       1
; #Parameters:     1
; Is_vararg:       0
; Max Stack Size:  5

       0 [-]: GETUPVAL R2 0
       1 [-]: FASTCALL1 62 R2 L0
       2 [-]: GETIMPORT R1 1 [0x7B998233]
       3 [-]: CALL R1 1 1  
L 0:   4 [-]: JUMPIF R1 L1 
       5 [-]: GETUPVAL R1 0
       6 [-]: GETIMPORT R3 3 [0x03F57322]
       7 [-]: MOVE R4 R0   
       8 [-]: CALL R3 1 -1 
       9 [-]: NAMECALL R1 R1 K4 [0xDF42446E]
      10 [-]: CALL R1 -1 0 
L 1:  11 [-]: RETURN R0 0  


; Name:            
; Defined at line: 2284
; #Upvalues:       1
; #Parameters:     1
; Is_vararg:       0
; Max Stack Size:  5

       0 [-]: GETUPVAL R2 0
       1 [-]: FASTCALL1 62 R2 L0
       2 [-]: GETIMPORT R1 1 [0x7B998233]
       3 [-]: CALL R1 1 1  
L 0:   4 [-]: JUMPIF R1 L1 
       5 [-]: GETUPVAL R1 0
       6 [-]: GETIMPORT R3 3 [0x03F57322]
       7 [-]: MOVE R4 R0   
       8 [-]: CALL R3 1 -1 
       9 [-]: NAMECALL R1 R1 K4 [0xBCE5A201]
      10 [-]: CALL R1 -1 0 
L 1:  11 [-]: RETURN R0 0  


; Name:            
; Defined at line: 2290
; #Upvalues:       2
; #Parameters:     1
; Is_vararg:       0
; Max Stack Size:  5

       0 [-]: GETUPVAL R1 0
       1 [-]: JUMPIF R1 L1 
       2 [-]: GETUPVAL R2 1
       3 [-]: FASTCALL1 62 R2 L0
       4 [-]: GETIMPORT R1 1 [0x7B998233]
       5 [-]: CALL R1 1 1  
L 0:   6 [-]: JUMPIF R1 L1 
       7 [-]: GETUPVAL R1 1
       8 [-]: GETIMPORT R3 3 [0x03F57322]
       9 [-]: MOVE R4 R0   
      10 [-]: CALL R3 1 1  
      11 [-]: LOADB R4 1   
      12 [-]: NAMECALL R1 R1 K4 [0x070DAA5A]
      13 [-]: CALL R1 3 0  
L 1:  14 [-]: RETURN R0 0  


; Name:            
; Defined at line: 2296
; #Upvalues:       2
; #Parameters:     1
; Is_vararg:       0
; Max Stack Size:  5

       0 [-]: GETUPVAL R1 0
       1 [-]: JUMPIF R1 L1 
       2 [-]: GETUPVAL R2 1
       3 [-]: FASTCALL1 62 R2 L0
       4 [-]: GETIMPORT R1 1 [0x7B998233]
       5 [-]: CALL R1 1 1  
L 0:   6 [-]: JUMPIF R1 L1 
       7 [-]: GETUPVAL R1 1
       8 [-]: GETIMPORT R3 3 [0x03F57322]
       9 [-]: MOVE R4 R0   
      10 [-]: CALL R3 1 1  
      11 [-]: LOADB R4 1   
      12 [-]: NAMECALL R1 R1 K4 [0xAF5319DC]
      13 [-]: CALL R1 3 0  
L 1:  14 [-]: RETURN R0 0  


; Name:            
; Defined at line: 2302
; #Upvalues:       1
; #Parameters:     0
; Is_vararg:       0
; Max Stack Size:  3

       0 [-]: GETUPVAL R1 0
       1 [-]: GETTABLEKS R0 R1 K0 ["mFocusedNode"]
       2 [-]: JUMPIFNOT R0 L0
       3 [-]: GETUPVAL R1 0
       4 [-]: GETTABLEKS R0 R1 K1 ["SelectNode"]
       5 [-]: GETUPVAL R2 0
       6 [-]: GETTABLEKS R1 R2 K0 ["mFocusedNode"]
       7 [-]: CALL R0 1 0  
L 0:   8 [-]: RETURN R0 0  


; Name:            
; Defined at line: 2308
; #Upvalues:       2
; #Parameters:     1
; Is_vararg:       0
; Max Stack Size:  5

       0 [-]: GETUPVAL R1 0
       1 [-]: JUMPIF R1 L0 
       2 [-]: GETUPVAL R1 1
       3 [-]: GETIMPORT R3 1 [0x03F57322]
       4 [-]: MOVE R4 R0   
       5 [-]: CALL R3 1 -1 
       6 [-]: NAMECALL R1 R1 K2 [0xCA30DFB6]
       7 [-]: CALL R1 -1 1 
       8 [-]: JUMPXEQKNIL R1 L0
       9 [-]: LOADB R2 1   
      10 [-]: SETTABLEKS R2 R1 K3 ["mRankUpBtnReleased"]
L 0:  11 [-]: RETURN R0 0  


; Name:            
; Defined at line: 2318
; #Upvalues:       10
; #Parameters:     1
; Is_vararg:       0
; Max Stack Size:  7

       0 [-]: GETIMPORT R1 1 [0x03F57322]
       1 [-]: MOVE R2 R0   
       2 [-]: CALL R1 1 1  
       3 [-]: LOADN R2 4   
       4 [-]: JUMPIFNOTEQ R1 R2 L7
       5 [-]: GETUPVAL R2 0
       6 [-]: FASTCALL1 62 R2 L0
       7 [-]: GETIMPORT R1 3 [0x7B998233]
       8 [-]: CALL R1 1 1  
L 0:   9 [-]: JUMPIF R1 L7 
      10 [-]: GETUPVAL R2 1
      11 [-]: LENGTH R1 R2 
      12 [-]: JUMPXEQKN R1 K4 L1 NOT [0]
      13 [-]: GETUPVAL R2 2
      14 [-]: ADDK R1 R2 K5 [1]
      15 [-]: SETUPVAL R1 2
L 1:  16 [-]: GETUPVAL R2 1
      17 [-]: GETUPVAL R3 0
      18 [-]: FASTCALL2 52 R2 R3 L2
      19 [-]: GETIMPORT R1 8 [0x23D5322F]
      20 [-]: CALL R1 2 0  
L 2:  21 [-]: GETUPVAL R2 3
      22 [-]: GETUPVAL R4 0
      23 [-]: GETTABLEKS R3 R4 K9 ["PointCost"]
      24 [-]: SUB R1 R2 R3 
      25 [-]: SETUPVAL R1 3
      26 [-]: GETUPVAL R1 4
      27 [-]: LOADB R2 0   
      28 [-]: CALL R1 1 0  
      29 [-]: GETUPVAL R1 5
      30 [-]: GETUPVAL R4 0
      31 [-]: GETTABLEKS R3 R4 K10 ["Id"]
      32 [-]: NAMECALL R1 R1 K11 [0xCA30DFB6]
      33 [-]: CALL R1 2 1  
      34 [-]: FASTCALL1 62 R1 L3
      35 [-]: MOVE R3 R1   
      36 [-]: GETIMPORT R2 3 [0x7B998233]
      37 [-]: CALL R2 1 1  
L 3:  38 [-]: JUMPIF R2 L7 
      39 [-]: GETUPVAL R3 6
      40 [-]: GETTABLEKS R2 R3 K12 [0xF76783E5]
      41 [-]: GETIMPORT R3 14 [0xAE91E43B]
      42 [-]: GETTABLEKS R4 R1 K15 ["mClipName"]
      43 [-]: GETIMPORT R5 17 [0x23428253]
      44 [-]: CALL R2 3 1  
      45 [-]: GETUPVAL R4 7
      46 [-]: GETTABLEKS R3 R4 K18 [0xCD10B8A9]
      47 [-]: MOVE R4 R2   
      48 [-]: CALL R3 1 0  
      49 [-]: GETIMPORT R4 20 [0x46D2126A]
      50 [-]: FASTCALL1 62 R4 L4
      51 [-]: GETIMPORT R3 3 [0x7B998233]
      52 [-]: CALL R3 1 1  
L 4:  53 [-]: JUMPIF R3 L5 
      54 [-]: GETUPVAL R4 6
      55 [-]: GETTABLEKS R3 R4 K21 [0x659D451F]
      56 [-]: GETIMPORT R4 20 [0x46D2126A]
      57 [-]: CALL R3 1 0  
L 5:  58 [-]: LOADB R3 1   
      59 [-]: SETTABLEKS R3 R1 K22 ["mUniversal"]
      60 [-]: GETTABLEKS R4 R1 K23 ["mRank"]
      61 [-]: ADDK R3 R4 K5 [1]
      62 [-]: SETTABLEKS R3 R1 K23 ["mRank"]
      63 [-]: GETUPVAL R4 5
      64 [-]: GETTABLEKS R3 R4 K24 ["mElementDrawCallback"]
      65 [-]: MOVE R4 R1   
      66 [-]: CALL R3 1 0  
      67 [-]: GETIMPORT R3 27 [0x1467D5F4]
      68 [-]: CALL R3 0 1  
      69 [-]: JUMPIFNOT R3 L6
      70 [-]: GETUPVAL R3 8
      71 [-]: LOADK R5 K28 [0.10000000000000001]
      72 [-]: NEWCLOSURE R6 P0
      73 [-]: MOVE R2 R5   
      74 [-]: MOVE R0 R1   
      75 [-]: NAMECALL R3 R3 K29 [0xBD2E96EA]
      76 [-]: CALL R3 3 0  
L 6:  77 [-]: GETUPVAL R3 9
      78 [-]: CALL R3 0 0  
L 7:  79 [-]: NEWTABLE R1 0 0
      80 [-]: SETUPVAL R1 0
      81 [-]: RETURN R0 0  


; Name:            
; Defined at line: 2357
; #Upvalues:       13
; #Parameters:     1
; Is_vararg:       0
; Max Stack Size:  13

       0 [-]: GETUPVAL R1 0
       1 [-]: JUMPIFNOT R1 L0
       2 [-]: RETURN R0 0  
L 0:   3 [-]: GETIMPORT R1 1 [0x03F57322]
       4 [-]: MOVE R2 R0   
       5 [-]: CALL R1 1 1  
       6 [-]: MOVE R0 R1   
       7 [-]: JUMPXEQKNIL R0 L1 NOT
       8 [-]: RETURN R0 0  
L 1:   9 [-]: GETUPVAL R1 1
      10 [-]: MOVE R3 R0   
      11 [-]: NAMECALL R1 R1 K2 [0xCA30DFB6]
      12 [-]: CALL R1 2 1  
      13 [-]: JUMPXEQKNIL R1 L3
      14 [-]: GETTABLEKS R3 R1 K3 ["mCard"]
      15 [-]: FASTCALL1 62 R3 L2
      16 [-]: GETIMPORT R2 5 [0x7B998233]
      17 [-]: CALL R2 1 1  
L 2:  18 [-]: JUMPIFNOT R2 L4
L 3:  19 [-]: RETURN R0 0  
L 4:  20 [-]: GETTABLEKS R4 R1 K3 ["mCard"]
      21 [-]: GETTABLEKS R3 R4 K6 ["mUpgrade"]
      22 [-]: GETTABLEKS R2 R3 K7 ["mInstance"]
      23 [-]: GETUPVAL R4 2
      24 [-]: NAMECALL R2 R2 K8 [0x6AD7E1A4]
      25 [-]: CALL R2 2 1  
      26 [-]: JUMPIF R2 L5 
      27 [-]: GETUPVAL R3 3
      28 [-]: GETTABLEKS R2 R3 K9 [0xE0CBA3CA]
      29 [-]: GETIMPORT R3 11 [0xAE91E43B]
      30 [-]: LOADK R5 K12 ["/Lotus/Language/TennoWay/UnlockAbilityInsufficientOperator"]
      31 [-]: LOADB R6 0   
      32 [-]: DUPTABLE R7 14
      33 [-]: GETIMPORT R8 16 [0x5F0788C4]
      34 [-]: GETTABLEKS R9 R1 K17 ["mName"]
      35 [-]: CALL R8 1 1  
      36 [-]: SETTABLEKS R8 R7 K13 ["NAME"]
      37 [-]: NAMECALL R3 R3 K18 [0x42B04007]
      38 [-]: CALL R3 4 -1 
      39 [-]: CALL R2 -1 0 
      40 [-]: RETURN R0 0  
L 5:  41 [-]: GETTABLEKS R4 R1 K3 ["mCard"]
      42 [-]: GETTABLEKS R3 R4 K6 ["mUpgrade"]
      43 [-]: GETTABLEKS R2 R3 K7 ["mInstance"]
      44 [-]: NAMECALL R2 R2 K19 [0x9ED94A63]
      45 [-]: CALL R2 1 1  
      46 [-]: GETIMPORT R3 21 [0x25D99D89]
      47 [-]: NAMECALL R3 R3 K22 [0xEFEE6C91]
      48 [-]: CALL R3 1 1  
      49 [-]: JUMPIFNOTLT R3 R2 L6
      50 [-]: GETUPVAL R4 3
      51 [-]: GETTABLEKS R3 R4 K9 [0xE0CBA3CA]
      52 [-]: GETIMPORT R4 11 [0xAE91E43B]
      53 [-]: LOADK R6 K23 ["/Lotus/Language/TennoWay/UnlockAbilityInsufficientMastery"]
      54 [-]: LOADB R7 0   
      55 [-]: DUPTABLE R8 25
      56 [-]: SETTABLEKS R2 R8 K24 ["RANK"]
      57 [-]: GETIMPORT R9 16 [0x5F0788C4]
      58 [-]: GETTABLEKS R10 R1 K17 ["mName"]
      59 [-]: CALL R9 1 1  
      60 [-]: SETTABLEKS R9 R8 K13 ["NAME"]
      61 [-]: NAMECALL R4 R4 K18 [0x42B04007]
      62 [-]: CALL R4 4 -1 
      63 [-]: CALL R3 -1 0 
      64 [-]: RETURN R0 0  
L 6:  65 [-]: GETTABLEKS R5 R1 K3 ["mCard"]
      66 [-]: GETTABLEKS R4 R5 K6 ["mUpgrade"]
      67 [-]: GETTABLEKS R3 R4 K7 ["mInstance"]
      68 [-]: NAMECALL R3 R3 K26 [0x4E7E3738]
      69 [-]: CALL R3 1 1  
      70 [-]: GETUPVAL R4 4
      71 [-]: JUMPIFNOTLT R4 R3 L7
      72 [-]: GETUPVAL R4 5
      73 [-]: CALL R4 0 0  
      74 [-]: RETURN R0 0  
L 7:  75 [-]: GETTABLEKS R5 R1 K27 ["mParent"]
      76 [-]: FASTCALL1 62 R5 L8
      77 [-]: GETIMPORT R4 5 [0x7B998233]
      78 [-]: CALL R4 1 1  
L 8:  79 [-]: JUMPIF R4 L9 
      80 [-]: GETTABLEKS R5 R1 K27 ["mParent"]
      81 [-]: GETTABLEKS R4 R5 K28 ["mLocked"]
      82 [-]: JUMPIFNOT R4 L9
      83 [-]: GETUPVAL R5 3
      84 [-]: GETTABLEKS R4 R5 K9 [0xE0CBA3CA]
      85 [-]: GETIMPORT R5 11 [0xAE91E43B]
      86 [-]: LOADK R7 K29 ["/Lotus/Language/TennoWay/UnlockAbilityParentFirst"]
      87 [-]: LOADB R8 0   
      88 [-]: DUPTABLE R9 31
      89 [-]: GETIMPORT R10 16 [0x5F0788C4]
      90 [-]: GETTABLEKS R12 R1 K27 ["mParent"]
      91 [-]: GETTABLEKS R11 R12 K17 ["mName"]
      92 [-]: CALL R10 1 1 
      93 [-]: SETTABLEKS R10 R9 K30 ["PARENT"]
      94 [-]: GETIMPORT R10 16 [0x5F0788C4]
      95 [-]: GETTABLEKS R11 R1 K17 ["mName"]
      96 [-]: CALL R10 1 1 
      97 [-]: SETTABLEKS R10 R9 K13 ["NAME"]
      98 [-]: NAMECALL R5 R5 K18 [0x42B04007]
      99 [-]: CALL R5 4 -1 
     100 [-]: CALL R4 -1 0 
     101 [-]: RETURN R0 0  
L 9: 102 [-]: GETUPVAL R4 6
     103 [-]: MOVE R5 R1   
     104 [-]: MOVE R6 R3   
     105 [-]: LOADB R7 1   
     106 [-]: CALL R4 3 0  
     107 [-]: GETUPVAL R5 4
     108 [-]: SUB R4 R5 R3 
     109 [-]: SETUPVAL R4 4
     110 [-]: GETUPVAL R4 7
     111 [-]: LOADB R5 0   
     112 [-]: CALL R4 1 0  
     113 [-]: FASTCALL1 62 R1 L10
     114 [-]: MOVE R5 R1   
     115 [-]: GETIMPORT R4 5 [0x7B998233]
     116 [-]: CALL R4 1 1  
L10: 117 [-]: JUMPIF R4 L16
     118 [-]: GETUPVAL R5 3
     119 [-]: GETTABLEKS R4 R5 K32 [0xF76783E5]
     120 [-]: GETIMPORT R5 11 [0xAE91E43B]
     121 [-]: GETTABLEKS R6 R1 K33 ["mClipName"]
     122 [-]: GETIMPORT R7 35 [0x23428253]
     123 [-]: CALL R4 3 1  
     124 [-]: FASTCALL1 62 R4 L11
     125 [-]: MOVE R6 R4   
     126 [-]: GETIMPORT R5 5 [0x7B998233]
     127 [-]: CALL R5 1 1  
L11: 128 [-]: JUMPIF R5 L12
     129 [-]: GETUPVAL R6 8
     130 [-]: GETTABLEKS R5 R6 K36 [0xCD10B8A9]
     131 [-]: MOVE R6 R4   
     132 [-]: CALL R5 1 0  
     133 [-]: LOADK R6 K37 [0.029999999999999999]
     134 [-]: LOADN R8 1   
     135 [-]: GETUPVAL R9 9
     136 [-]: NAMECALL R9 R9 K38 [0x54AB95F9]
     137 [-]: CALL R9 1 1  
     138 [-]: ADD R7 R8 R9 
     139 [-]: MUL R5 R6 R7 
     140 [-]: MULK R8 R5 K39 [0.80000000000000004]
     141 [-]: MOVE R9 R5   
     142 [-]: LOADB R10 1  
     143 [-]: NAMECALL R6 R4 K40 [0xCBF89887]
     144 [-]: CALL R6 4 0  
L12: 145 [-]: GETIMPORT R6 42 [0x556BB911]
     146 [-]: FASTCALL1 62 R6 L13
     147 [-]: GETIMPORT R5 5 [0x7B998233]
     148 [-]: CALL R5 1 1  
L13: 149 [-]: JUMPIF R5 L14
     150 [-]: GETUPVAL R6 3
     151 [-]: GETTABLEKS R5 R6 K43 [0x659D451F]
     152 [-]: GETIMPORT R6 42 [0x556BB911]
     153 [-]: CALL R5 1 0  
L14: 154 [-]: LOADB R5 0   
     155 [-]: SETTABLEKS R5 R1 K28 ["mLocked"]
     156 [-]: GETUPVAL R6 1
     157 [-]: GETTABLEKS R5 R6 K44 ["mElementDrawCallback"]
     158 [-]: MOVE R6 R1   
     159 [-]: CALL R5 1 0  
     160 [-]: GETIMPORT R5 11 [0xAE91E43B]
     161 [-]: GETTABLEKS R7 R1 K33 ["mClipName"]
     162 [-]: NAMECALL R5 R5 K45 [0xAF5300DC]
     163 [-]: CALL R5 2 0  
     164 [-]: GETIMPORT R5 11 [0xAE91E43B]
     165 [-]: GETTABLEKS R7 R1 K33 ["mClipName"]
     166 [-]: LOADN R8 10  
     167 [-]: LOADN R9 100 
     168 [-]: NAMECALL R5 R5 K46 [0x67BC869F]
     169 [-]: CALL R5 4 0  
     170 [-]: GETIMPORT R5 49 [0x1467D5F4]
     171 [-]: CALL R5 0 1  
     172 [-]: JUMPIFNOT R5 L15
     173 [-]: GETUPVAL R5 10
     174 [-]: LOADK R7 K50 [0.10000000000000001]
     175 [-]: NEWCLOSURE R8 P0
     176 [-]: MOVE R2 R1   
     177 [-]: MOVE R0 R1   
     178 [-]: NAMECALL R5 R5 K51 [0xBD2E96EA]
     179 [-]: CALL R5 3 0  
L15: 180 [-]: GETUPVAL R5 11
     181 [-]: CALL R5 0 0  
L16: 182 [-]: GETUPVAL R4 12
     183 [-]: CALL R4 0 0  
     184 [-]: RETURN R0 0  


; Name:            
; Defined at line: 2433
; #Upvalues:       2
; #Parameters:     1
; Is_vararg:       0
; Max Stack Size:  10

       0 [-]: GETUPVAL R1 0
       1 [-]: GETTABLEKS R2 R0 K0 ["StoreItem"]
       2 [-]: NAMECALL R2 R2 K1 [0xF278F8A1]
       3 [-]: CALL R2 1 1  
       4 [-]: SETTABLEKS R2 R1 K2 ["ResourceType"]
       5 [-]: GETUPVAL R1 0
       6 [-]: GETTABLEKS R2 R0 K3 ["Req"]
       7 [-]: SETTABLEKS R2 R1 K4 ["ResourceCost"]
       8 [-]: GETUPVAL R1 0
       9 [-]: GETIMPORT R2 6 [0xAE91E43B]
      10 [-]: GETTABLEKS R4 R0 K0 ["StoreItem"]
      11 [-]: NAMECALL R4 R4 K7 [0xD3A9D01F]
      12 [-]: CALL R4 1 1  
      13 [-]: NAMECALL R4 R4 K8 [0x6D604BA7]
      14 [-]: CALL R4 1 1  
      15 [-]: LOADB R5 1   
      16 [-]: NAMECALL R2 R2 K9 [0x42B04007]
      17 [-]: CALL R2 3 1  
      18 [-]: SETTABLEKS R2 R1 K10 ["ResourceName"]
      19 [-]: GETIMPORT R5 12 [0x64FB1586]
      20 [-]: GETUPVAL R7 0
      21 [-]: GETTABLEKS R6 R7 K4 ["ResourceCost"]
      22 [-]: CALL R5 1 1  
      23 [-]: MOVE R2 R5   
      24 [-]: LOADK R3 K13 [" "]
      25 [-]: GETUPVAL R5 0
      26 [-]: GETTABLEKS R4 R5 K10 ["ResourceName"]
      27 [-]: CONCAT R1 R2 R4
      28 [-]: GETIMPORT R2 6 [0xAE91E43B]
      29 [-]: LOADK R4 K14 ["/Lotus/Language/TennoWay/UniversalConfirm"]
      30 [-]: LOADB R5 1   
      31 [-]: DUPTABLE R6 18
      32 [-]: GETIMPORT R7 20 [0x5F0788C4]
      33 [-]: GETTABLEKS R8 R0 K21 ["NodeName"]
      34 [-]: CALL R7 1 1  
      35 [-]: SETTABLEKS R7 R6 K15 ["NAME"]
      36 [-]: SETTABLEKS R1 R6 K16 ["RESOURCES"]
      37 [-]: GETUPVAL R8 1
      38 [-]: GETTABLEKS R7 R8 K22 [0x1142C7A8]
      39 [-]: GETTABLEKS R8 R0 K23 ["NodeCost"]
      40 [-]: LOADN R9 0   
      41 [-]: CALL R7 2 1  
      42 [-]: SETTABLEKS R7 R6 K17 ["COST"]
      43 [-]: NAMECALL R2 R2 K9 [0x42B04007]
      44 [-]: CALL R2 4 1  
      45 [-]: GETUPVAL R4 1
      46 [-]: GETTABLEKS R3 R4 K24 [0xF616A184]
      47 [-]: MOVE R4 R2   
      48 [-]: LOADK R5 K25 ["OnConfirmUniversalizeUpgrade"]
      49 [-]: CALL R3 2 0  
      50 [-]: RETURN R0 0  


; Name:            
; Defined at line: 2443
; #Upvalues:       2
; #Parameters:     0
; Is_vararg:       0
; Max Stack Size:  2

       0 [-]: GETUPVAL R1 0
       1 [-]: FASTCALL1 62 R1 L0
       2 [-]: GETIMPORT R0 1 [0x7B998233]
       3 [-]: CALL R0 1 1  
L 0:   4 [-]: JUMPIF R0 L1 
       5 [-]: GETUPVAL R0 1
       6 [-]: GETUPVAL R1 0
       7 [-]: CALL R0 1 0  
L 1:   8 [-]: RETURN R0 0  


; Name:            
; Defined at line: 2449
; #Upvalues:       11
; #Parameters:     1
; Is_vararg:       0
; Max Stack Size:  17

       0 [-]: GETUPVAL R1 0
       1 [-]: JUMPIFNOT R1 L0
       2 [-]: RETURN R0 0  
L 0:   3 [-]: GETIMPORT R1 1 [0x03F57322]
       4 [-]: MOVE R2 R0   
       5 [-]: CALL R1 1 1  
       6 [-]: MOVE R0 R1   
       7 [-]: JUMPXEQKNIL R0 L1 NOT
       8 [-]: RETURN R0 0  
L 1:   9 [-]: GETUPVAL R1 1
      10 [-]: MOVE R3 R0   
      11 [-]: NAMECALL R1 R1 K2 [0xCA30DFB6]
      12 [-]: CALL R1 2 1  
      13 [-]: JUMPXEQKNIL R1 L17
      14 [-]: GETTABLEKS R3 R1 K3 ["mCard"]
      15 [-]: FASTCALL1 62 R3 L2
      16 [-]: GETIMPORT R2 5 [0x7B998233]
      17 [-]: CALL R2 1 1  
L 2:  18 [-]: JUMPIF R2 L17
      19 [-]: GETTABLEKS R3 R1 K6 ["mRankUpBtnReleased"]
      20 [-]: FASTCALL1 62 R3 L3
      21 [-]: GETIMPORT R2 5 [0x7B998233]
      22 [-]: CALL R2 1 1  
L 3:  23 [-]: JUMPIF R2 L4 
      24 [-]: GETTABLEKS R2 R1 K6 ["mRankUpBtnReleased"]
      25 [-]: JUMPIFNOT R2 L4
      26 [-]: LOADB R2 0   
      27 [-]: SETTABLEKS R2 R1 K6 ["mRankUpBtnReleased"]
      28 [-]: RETURN R0 0  
L 4:  29 [-]: GETUPVAL R2 2
      30 [-]: GETTABLEKS R4 R1 K7 ["mUniversalCost"]
      31 [-]: GETTABLEKS R3 R4 K8 ["mFocusPointCost"]
      32 [-]: JUMPIFNOTLT R2 R3 L5
      33 [-]: GETUPVAL R3 3
      34 [-]: GETTABLEKS R2 R3 K9 [0xE0CBA3CA]
      35 [-]: GETIMPORT R3 11 [0xAE91E43B]
      36 [-]: LOADK R5 K12 ["/Lotus/Language/TennoWay/UniversalPointsError"]
      37 [-]: LOADB R6 1   
      38 [-]: DUPTABLE R7 15
      39 [-]: GETUPVAL R9 3
      40 [-]: GETTABLEKS R8 R9 K16 [0x1142C7A8]
      41 [-]: GETTABLEKS R10 R1 K7 ["mUniversalCost"]
      42 [-]: GETTABLEKS R9 R10 K8 ["mFocusPointCost"]
      43 [-]: LOADN R10 0  
      44 [-]: CALL R8 2 1  
      45 [-]: SETTABLEKS R8 R7 K13 ["COST"]
      46 [-]: GETIMPORT R8 18 [0x5F0788C4]
      47 [-]: GETTABLEKS R9 R1 K19 ["mName"]
      48 [-]: CALL R8 1 1  
      49 [-]: SETTABLEKS R8 R7 K14 ["NAME"]
      50 [-]: NAMECALL R3 R3 K20 [0x42B04007]
      51 [-]: CALL R3 4 -1 
      52 [-]: CALL R2 -1 0 
      53 [-]: RETURN R0 0  
L 5:  54 [-]: GETIMPORT R2 22 [0x25D99D89]
      55 [-]: NAMECALL R2 R2 K23 [0x25A6E75E]
      56 [-]: CALL R2 1 1  
      57 [-]: NEWTABLE R3 0 0
      58 [-]: LOADN R4 0   
      59 [-]: LOADN R7 1   
      60 [-]: GETTABLEKS R9 R1 K7 ["mUniversalCost"]
      61 [-]: GETTABLEKS R8 R9 K24 ["mResourceCost"]
      62 [-]: LENGTH R5 R8 
      63 [-]: LOADN R6 1   
      64 [-]: FORNPREP R5 L12
L 6:  65 [-]: GETTABLEKS R11 R1 K7 ["mUniversalCost"]
      66 [-]: GETTABLEKS R10 R11 K24 ["mResourceCost"]
      67 [-]: GETTABLE R9 R10 R7
      68 [-]: GETTABLEKS R8 R9 K25 ["mItemType"]
      69 [-]: DUPTABLE R9 31
      70 [-]: GETUPVAL R10 4
      71 [-]: MOVE R12 R8  
      72 [-]: NAMECALL R10 R10 K32 [0x105074FB]
      73 [-]: CALL R10 2 1 
      74 [-]: SETTABLEKS R10 R9 K26 ["StoreItem"]
      75 [-]: LOADN R10 0  
      76 [-]: SETTABLEKS R10 R9 K27 ["Count"]
      77 [-]: GETTABLEKS R13 R1 K7 ["mUniversalCost"]
      78 [-]: GETTABLEKS R12 R13 K24 ["mResourceCost"]
      79 [-]: GETTABLE R11 R12 R7
      80 [-]: GETTABLEKS R10 R11 K33 ["mItemCount"]
      81 [-]: SETTABLEKS R10 R9 K28 ["Req"]
      82 [-]: GETTABLEKS R10 R1 K19 ["mName"]
      83 [-]: SETTABLEKS R10 R9 K29 ["NodeName"]
      84 [-]: GETTABLEKS R11 R1 K7 ["mUniversalCost"]
      85 [-]: GETTABLEKS R10 R11 K8 ["mFocusPointCost"]
      86 [-]: SETTABLEKS R10 R9 K30 ["NodeCost"]
      87 [-]: LOADN R10 0  
      88 [-]: LOADN R13 1  
      89 [-]: GETUPVAL R14 5
      90 [-]: LENGTH R11 R14
      91 [-]: LOADN R12 1  
      92 [-]: FORNPREP R11 L9
L 7:  93 [-]: GETUPVAL R16 5
      94 [-]: GETTABLE R15 R16 R13
      95 [-]: GETTABLEKS R14 R15 K34 ["ResourceType"]
      96 [-]: JUMPIFNOTEQ R14 R8 L8
      97 [-]: GETUPVAL R16 5
      98 [-]: GETTABLE R15 R16 R13
      99 [-]: GETTABLEKS R14 R15 K35 ["ResourceCost"]
     100 [-]: ADD R10 R10 R14
L 8: 101 [-]: FORNLOOP R11 L7
L 9: 102 [-]: MOVE R14 R8  
     103 [-]: NAMECALL R12 R2 K36 [0x51B30E60]
     104 [-]: CALL R12 2 1 
     105 [-]: SUB R11 R12 R10
     106 [-]: SETTABLEKS R11 R9 K27 ["Count"]
     107 [-]: GETTABLEKS R11 R9 K27 ["Count"]
     108 [-]: GETTABLEKS R12 R9 K28 ["Req"]
     109 [-]: JUMPIFNOTLE R12 R11 L10
     110 [-]: ADDK R4 R4 K37 [1]
L10: 111 [-]: FASTCALL2 52 R3 R9 L11
     112 [-]: MOVE R12 R3  
     113 [-]: MOVE R13 R9  
     114 [-]: GETIMPORT R11 40 [0x23D5322F]
     115 [-]: CALL R11 2 0 
L11: 116 [-]: FORNLOOP R5 L6
L12: 117 [-]: JUMPXEQKN R4 K41 L13 NOT [0]
     118 [-]: GETUPVAL R6 3
     119 [-]: GETTABLEKS R5 R6 K9 [0xE0CBA3CA]
     120 [-]: GETIMPORT R6 11 [0xAE91E43B]
     121 [-]: LOADK R8 K42 ["/Lotus/Language/TennoWay/UniversalResourcesError"]
     122 [-]: LOADB R9 1   
     123 [-]: DUPTABLE R10 43
     124 [-]: GETIMPORT R11 18 [0x5F0788C4]
     125 [-]: GETTABLEKS R12 R1 K19 ["mName"]
     126 [-]: CALL R11 1 1 
     127 [-]: SETTABLEKS R11 R10 K14 ["NAME"]
     128 [-]: NAMECALL R6 R6 K20 [0x42B04007]
     129 [-]: CALL R6 4 -1 
     130 [-]: CALL R5 -1 0 
     131 [-]: RETURN R0 0  
L13: 132 [-]: DUPTABLE R5 48
     133 [-]: GETTABLEKS R7 R1 K7 ["mUniversalCost"]
     134 [-]: GETTABLEKS R6 R7 K8 ["mFocusPointCost"]
     135 [-]: SETTABLEKS R6 R5 K44 ["PointCost"]
     136 [-]: GETTABLEKS R8 R1 K3 ["mCard"]
     137 [-]: GETTABLEKS R7 R8 K49 ["mUpgrade"]
     138 [-]: GETTABLEKS R6 R7 K25 ["mItemType"]
     139 [-]: SETTABLEKS R6 R5 K45 ["Upgrade"]
     140 [-]: SETTABLEKS R0 R5 K46 ["Id"]
     141 [-]: GETTABLEKS R6 R1 K19 ["mName"]
     142 [-]: SETTABLEKS R6 R5 K47 ["Name"]
     143 [-]: SETUPVAL R5 6
     144 [-]: JUMPXEQKN R4 K37 L16 NOT [1]
     145 [-]: LOADN R7 1   
     146 [-]: LENGTH R5 R3 
     147 [-]: LOADN R6 1   
     148 [-]: FORNPREP R5 L17
L14: 149 [-]: GETTABLE R9 R3 R7
     150 [-]: GETTABLEKS R8 R9 K27 ["Count"]
     151 [-]: GETTABLE R10 R3 R7
     152 [-]: GETTABLEKS R9 R10 K28 ["Req"]
     153 [-]: JUMPIFNOTLE R9 R8 L15
     154 [-]: GETUPVAL R8 7
     155 [-]: GETTABLE R9 R3 R7
     156 [-]: CALL R8 1 0  
L15: 157 [-]: FORNLOOP R5 L14
     158 [-]: RETURN R0 0  
L16: 159 [-]: GETIMPORT R5 51 ["_T"]
     160 [-]: NEWCLOSURE R6 P0
     161 [-]: MOVE R0 R3   
     162 [-]: SETTABLEKS R6 R5 K52 ["GetResources"]
     163 [-]: GETIMPORT R5 51 ["_T"]
     164 [-]: NEWCLOSURE R6 P1
     165 [-]: MOVE R2 R8   
     166 [-]: MOVE R2 R9   
     167 [-]: SETTABLEKS R6 R5 K53 ["ResourceSelected"]
     168 [-]: GETUPVAL R5 8
     169 [-]: LOADB R6 1   
     170 [-]: GETIMPORT R8 55 [0x0032441C]
     171 [-]: GETTABLEKS R7 R8 K56 ["UIMovie_ItemBrowsingMovie"]
     172 [-]: CALL R5 2 0  
     173 [-]: GETUPVAL R5 10
     174 [-]: LOADK R7 K57 ["SetTitle"]
     175 [-]: GETIMPORT R8 11 [0xAE91E43B]
     176 [-]: LOADK R10 K58 ["/Lotus/Language/TennoWay/UniversalResourceSelect"]
     177 [-]: LOADB R11 0  
     178 [-]: NAMECALL R8 R8 K20 [0x42B04007]
     179 [-]: CALL R8 3 -1 
     180 [-]: NAMECALL R5 R5 K59 [0xE4162EED]
     181 [-]: CALL R5 -1 0 
     182 [-]: GETUPVAL R5 10
     183 [-]: LOADK R7 K60 ["SetCallBack"]
     184 [-]: LOADK R8 K53 ["ResourceSelected"]
     185 [-]: NAMECALL R5 R5 K59 [0xE4162EED]
     186 [-]: CALL R5 3 0  
     187 [-]: GETUPVAL R5 10
     188 [-]: LOADK R7 K61 ["SetElementsFunction"]
     189 [-]: LOADK R8 K52 ["GetResources"]
     190 [-]: NAMECALL R5 R5 K59 [0xE4162EED]
     191 [-]: CALL R5 3 0  
L17: 192 [-]: RETURN R0 0  


; Name:            
; Defined at line: 2544
; #Upvalues:       1
; #Parameters:     0
; Is_vararg:       0
; Max Stack Size:  1

       0 [-]: GETUPVAL R0 0
       1 [-]: CALL R0 0 0  
       2 [-]: LOADB R0 1   
       3 [-]: RETURN R0 1  


; Name:            
; Defined at line: 2549
; #Upvalues:       1
; #Parameters:     0
; Is_vararg:       0
; Max Stack Size:  3

       0 [-]: GETUPVAL R1 0
       1 [-]: GETTABLEKS R0 R1 K0 [0x659D451F]
       2 [-]: GETIMPORT R2 2 [0x0032441C]
       3 [-]: GETTABLEKS R1 R2 K3 ["UISound_Focus"]
       4 [-]: CALL R0 1 0  
       5 [-]: RETURN R0 0  


; Name:            
; Defined at line: 2554
; #Upvalues:       5
; #Parameters:     1
; Is_vararg:       0
; Max Stack Size:  5

       0 [-]: GETUPVAL R1 0
       1 [-]: JUMPIF R1 L1 
       2 [-]: GETUPVAL R1 1
       3 [-]: JUMPXEQKN R1 K0 L0 NOT [-0.5]
       4 [-]: LOADN R1 0   
       5 [-]: JUMPIFLT R1 R0 L1
L 0:   6 [-]: GETUPVAL R1 1
       7 [-]: JUMPXEQKN R1 K1 L2 NOT [1.5]
       8 [-]: LOADN R1 0   
       9 [-]: JUMPIFNOTLT R0 R1 L2
L 1:  10 [-]: RETURN R0 0  
L 2:  11 [-]: GETUPVAL R4 1
      12 [-]: SUBK R3 R4 K0 [-0.5]
      13 [-]: ADDK R2 R3 K3 [1]
      14 [-]: MUL R1 R2 R0 
      15 [-]: MULK R0 R1 K2 [0.10000000000000001]
      16 [-]: GETIMPORT R1 5 [0x42DCC9F5]
      17 [-]: GETUPVAL R3 1
      18 [-]: SUB R2 R3 R0 
      19 [-]: LOADK R3 K0 [-0.5]
      20 [-]: LOADK R4 K1 [1.5]
      21 [-]: CALL R1 3 1  
      22 [-]: SETUPVAL R1 1
      23 [-]: GETUPVAL R1 2
      24 [-]: JUMPIFEQ R1 R0 L3
      25 [-]: SETUPVAL R0 2
      26 [-]: GETUPVAL R1 3
      27 [-]: GETUPVAL R3 3
      28 [-]: NAMECALL R3 R3 K6 [0x54AB95F9]
      29 [-]: CALL R3 1 -1 
      30 [-]: NAMECALL R1 R1 K7 [0xD0F998CD]
      31 [-]: CALL R1 -1 0 
L 3:  32 [-]: GETUPVAL R1 3
      33 [-]: GETUPVAL R3 1
      34 [-]: NAMECALL R1 R1 K8 [0x188E2BEE]
      35 [-]: CALL R1 2 0  
      36 [-]: GETUPVAL R1 4
      37 [-]: CALL R1 0 0  
      38 [-]: RETURN R0 0  


; Name:            
; Defined at line: 2568
; #Upvalues:       1
; #Parameters:     2
; Is_vararg:       0
; Max Stack Size:  5

       0 [-]: GETUPVAL R2 0
       1 [-]: GETIMPORT R3 1 [0x03F57322]
       2 [-]: MOVE R4 R1   
       3 [-]: CALL R3 1 -1 
       4 [-]: CALL R2 -1 0 
       5 [-]: RETURN R0 0  


; Name:            
; Defined at line: 2572
; #Upvalues:       1
; #Parameters:     2
; Is_vararg:       0
; Max Stack Size:  4

       0 [-]: LOADN R2 1   
       1 [-]: SUB R1 R2 R1 
       2 [-]: GETUPVAL R2 0
       3 [-]: MOVE R3 R1   
       4 [-]: CALL R2 1 0  
       5 [-]: RETURN R0 0  


; Name:            
; Defined at line: 2577
; #Upvalues:       1
; #Parameters:     0
; Is_vararg:       0
; Max Stack Size:  1

       0 [-]: GETUPVAL R0 0
       1 [-]: RETURN R0 1  


; Name:            
; Defined at line: 2581
; #Upvalues:       1
; #Parameters:     2
; Is_vararg:       0
; Max Stack Size:  3

       0 [-]: GETUPVAL R2 0
       1 [-]: SETTABLEKS R1 R2 K0 ["x"]
       2 [-]: LOADB R2 1   
       3 [-]: RETURN R2 1  


; Name:            
; Defined at line: 2586
; #Upvalues:       1
; #Parameters:     2
; Is_vararg:       0
; Max Stack Size:  3

       0 [-]: GETUPVAL R2 0
       1 [-]: SETTABLEKS R1 R2 K0 ["x"]
       2 [-]: LOADB R2 1   
       3 [-]: RETURN R2 1  


; Name:            
; Defined at line: 2591
; #Upvalues:       1
; #Parameters:     2
; Is_vararg:       0
; Max Stack Size:  4

       0 [-]: GETUPVAL R2 0
       1 [-]: MINUS R3 R1  
       2 [-]: SETTABLEKS R3 R2 K0 ["y"]
       3 [-]: LOADB R2 1   
       4 [-]: RETURN R2 1  


; Name:            
; Defined at line: 2596
; #Upvalues:       1
; #Parameters:     2
; Is_vararg:       0
; Max Stack Size:  3

       0 [-]: GETUPVAL R2 0
       1 [-]: SETTABLEKS R1 R2 K0 ["y"]
       2 [-]: LOADB R2 1   
       3 [-]: RETURN R2 1  


; Name:            
; Defined at line: 2601
; #Upvalues:       4
; #Parameters:     1
; Is_vararg:       0
; Max Stack Size:  5

       0 [-]: GETUPVAL R1 0
       1 [-]: CALL R1 0 0  
       2 [-]: GETUPVAL R2 1
       3 [-]: FASTCALL1 62 R2 L0
       4 [-]: GETIMPORT R1 1 [0x7B998233]
       5 [-]: CALL R1 1 1  
L 0:   6 [-]: JUMPIF R1 L2 
       7 [-]: GETUPVAL R1 1
       8 [-]: NAMECALL R1 R1 K2 [0xED1AB921]
       9 [-]: CALL R1 1 1  
      10 [-]: FASTCALL1 62 R1 L1
      11 [-]: MOVE R3 R1   
      12 [-]: GETIMPORT R2 1 [0x7B998233]
      13 [-]: CALL R2 1 1  
L 1:  14 [-]: JUMPIF R2 L2 
      15 [-]: GETUPVAL R2 2
      16 [-]: MOVE R3 R1   
      17 [-]: CALL R2 1 0  
      18 [-]: GETUPVAL R3 1
      19 [-]: GETTABLEKS R2 R3 K3 ["ShowNodeInfo"]
      20 [-]: MOVE R3 R1   
      21 [-]: LOADB R4 1   
      22 [-]: CALL R2 2 0  
L 2:  23 [-]: GETUPVAL R2 3
      24 [-]: FASTCALL1 62 R2 L3
      25 [-]: GETIMPORT R1 1 [0x7B998233]
      26 [-]: CALL R1 1 1  
L 3:  27 [-]: JUMPIF R1 L5 
      28 [-]: GETUPVAL R1 3
      29 [-]: NAMECALL R1 R1 K2 [0xED1AB921]
      30 [-]: CALL R1 1 1  
      31 [-]: FASTCALL1 62 R1 L4
      32 [-]: MOVE R3 R1   
      33 [-]: GETIMPORT R2 1 [0x7B998233]
      34 [-]: CALL R2 1 1  
L 4:  35 [-]: JUMPIF R2 L5 
      36 [-]: GETUPVAL R2 2
      37 [-]: MOVE R3 R1   
      38 [-]: CALL R2 1 0  
      39 [-]: GETUPVAL R3 3
      40 [-]: GETTABLEKS R2 R3 K3 ["ShowNodeInfo"]
      41 [-]: MOVE R3 R1   
      42 [-]: LOADB R4 1   
      43 [-]: CALL R2 2 0  
L 5:  44 [-]: RETURN R0 0  


; Name:            
; Defined at line: 2621
; #Upvalues:       0
; #Parameters:     0
; Is_vararg:       0
; Max Stack Size:  1

       0 [-]: LOADB R0 1   
       1 [-]: RETURN R0 1  


; Name:            
; Defined at line: 2625
; #Upvalues:       1
; #Parameters:     0
; Is_vararg:       0
; Max Stack Size:  1

       0 [-]: GETUPVAL R0 0
       1 [-]: CALL R0 0 0  
       2 [-]: RETURN R0 0  



