; Name:            
; Defined at line: 1
; #Upvalues:       0
; #Parameters:     0
; Is_vararg:       1
; Max Stack Size:  36

       1 [-]: GETIMPORT R0 1; var0 = 0x2D0FAD09
       2 [-]: LOADK R1 K2  ; var1 = "EE.Interface.Utilities"
       3 [-]: CALL R0 2 2  ; var0 = var0(var1)
       4 [-]: GETIMPORT R1 1; var1 = 0x2D0FAD09
       5 [-]: LOADK R2 K3  ; var2 = "Lotus.Interface.LotusUtilities"
       6 [-]: CALL R1 2 2  ; var1 = var1(var2)
       7 [-]: GETIMPORT R2 1; var2 = 0x2D0FAD09
       8 [-]: LOADK R3 K4  ; var3 = "Lotus.Interface.Components.ThemedCustomizationButton"
       9 [-]: CALL R2 2 2  ; var2 = var2(var3)
      10 [-]: GETIMPORT R3 1; var3 = 0x2D0FAD09
      11 [-]: LOADK R4 K5  ; var4 = "Lotus.Scripts.Effects.EffectsColorUtilities"
      12 [-]: CALL R3 2 2  ; var3 = var3(var4)
      13 [-]: GETIMPORT R4 7; var4 = 0x7ED0A956
      14 [-]: LOADK R5 K8  ; var5 = "/Lotus/Interface/DecorationsHud.swf"
      15 [-]: CALL R4 2 2  ; var4 = var4(var5)
      16 [-]: LOADNIL R5   ; var5 = nil
      17 [-]: LOADNIL R6   ; var6 = nil
      18 [-]: LOADNIL R7   ; var7 = nil
      19 [-]: LOADNIL R8   ; var8 = nil
      20 [-]: LOADNIL R9   ; var9 = nil
      21 [-]: LOADB R10 1  ; var10 = true
      22 [-]: LOADNIL R11  ; var11 = nil
      23 [-]: LOADNIL R12  ; var12 = nil
      24 [-]: LOADNIL R13  ; var13 = nil
      25 [-]: LOADNIL R14  ; var14 = nil
      26 [-]: LOADNIL R15  ; var15 = nil
      27 [-]: LOADNIL R16  ; var16 = nil
      28 [-]: LOADNIL R17  ; var17 = nil
      29 [-]: NEWCLOSURE R18 P0; 
      30 [-]: CAPTURE REF R10; 
      31 [-]: SETGLOBAL R18 K9; "IsInputBlocked" = var18
      32 [-]: DUPCLOSURE R18 K10; 
      33 [-]: SETGLOBAL R18 K11; "SupportsThemes" = var18
      34 [-]: NEWCLOSURE R18 P2; 
      35 [-]: CAPTURE REF R6; 
      36 [-]: SETGLOBAL R18 K12; "OnInfoSaved" = var18
      37 [-]: NEWCLOSURE R18 P3; 
      38 [-]: CAPTURE REF R11; 
      39 [-]: CAPTURE REF R5; 
      40 [-]: CAPTURE REF R6; 
      41 [-]: CAPTURE VAL R1; 
      42 [-]: CAPTURE REF R7; 
      43 [-]: DUPCLOSURE R19 K13; 
      44 [-]: CAPTURE VAL R18; 
      45 [-]: SETGLOBAL R19 K14; "Back" = var19
      46 [-]: NEWCLOSURE R19 P5; 
      47 [-]: CAPTURE REF R11; 
      48 [-]: DUPCLOSURE R20 K15; 
      49 [-]: CAPTURE VAL R19; 
      50 [-]: SETGLOBAL R20 K16; "UpdateButtons" = var20
      51 [-]: NEWCLOSURE R20 P7; 
      52 [-]: CAPTURE REF R14; 
      53 [-]: DUPCLOSURE R21 K17; 
      54 [-]: NEWCLOSURE R22 P9; 
      55 [-]: CAPTURE VAL R4; 
      56 [-]: CAPTURE REF R14; 
      57 [-]: CAPTURE VAL R21; 
      58 [-]: SETGLOBAL R22 K18; "Shutdown" = var22
      59 [-]: DUPCLOSURE R22 K19; 
      60 [-]: CAPTURE VAL R3; 
      61 [-]: DUPCLOSURE R23 K20; 
      62 [-]: NEWCLOSURE R24 P12; 
      63 [-]: CAPTURE REF R6; 
      64 [-]: CAPTURE VAL R22; 
      65 [-]: CAPTURE VAL R23; 
      66 [-]: CAPTURE REF R12; 
      67 [-]: CAPTURE VAL R0; 
      68 [-]: CAPTURE VAL R3; 
      69 [-]: NEWCLOSURE R25 P13; 
      70 [-]: CAPTURE REF R6; 
      71 [-]: CAPTURE VAL R22; 
      72 [-]: CAPTURE VAL R23; 
      73 [-]: CAPTURE REF R12; 
      74 [-]: CAPTURE VAL R0; 
      75 [-]: CAPTURE VAL R3; 
      76 [-]: NEWCLOSURE R26 P14; 
      77 [-]: CAPTURE REF R15; 
      78 [-]: CAPTURE REF R12; 
      79 [-]: CAPTURE REF R6; 
      80 [-]: DUPCLOSURE R27 K21; 
      81 [-]: NEWCLOSURE R28 P16; 
      82 [-]: CAPTURE REF R16; 
      83 [-]: CAPTURE REF R12; 
      84 [-]: CAPTURE VAL R27; 
      85 [-]: CAPTURE REF R6; 
      86 [-]: NEWCLOSURE R29 P17; 
      87 [-]: CAPTURE REF R6; 
      88 [-]: NEWCLOSURE R30 P18; 
      89 [-]: CAPTURE VAL R27; 
      90 [-]: CAPTURE REF R16; 
      91 [-]: CAPTURE REF R6; 
      92 [-]: NEWCLOSURE R31 P19; 
      93 [-]: CAPTURE VAL R0; 
      94 [-]: CAPTURE REF R6; 
      95 [-]: DUPCLOSURE R32 K22; 
      96 [-]: CAPTURE VAL R31; 
      97 [-]: SETGLOBAL R32 K23; "OnTextSet" = var32
      98 [-]: DUPCLOSURE R32 K24; 
      99 [-]: CAPTURE VAL R31; 
     100 [-]: SETGLOBAL R32 K25; "OSKOnTextSet" = var32
     101 [-]: NEWCLOSURE R32 P22; 
     102 [-]: CAPTURE VAL R1; 
     103 [-]: CAPTURE REF R6; 
     104 [-]: NEWCLOSURE R33 P23; 
     105 [-]: CAPTURE REF R11; 
     106 [-]: CAPTURE VAL R24; 
     107 [-]: CAPTURE VAL R25; 
     108 [-]: CAPTURE REF R13; 
     109 [-]: CAPTURE VAL R19; 
     110 [-]: NEWCLOSURE R17 P24; 
     111 [-]: CAPTURE REF R11; 
     112 [-]: CAPTURE VAL R2; 
     113 [-]: CAPTURE REF R12; 
     114 [-]: CAPTURE REF R6; 
     115 [-]: CAPTURE VAL R26; 
     116 [-]: CAPTURE REF R16; 
     117 [-]: CAPTURE VAL R28; 
     118 [-]: CAPTURE VAL R32; 
     119 [-]: CAPTURE VAL R29; 
     120 [-]: CAPTURE VAL R30; 
     121 [-]: CAPTURE VAL R19; 
     122 [-]: NEWCLOSURE R34 P25; 
     123 [-]: CAPTURE REF R13; 
     124 [-]: CAPTURE REF R6; 
     125 [-]: NEWCLOSURE R35 P26; 
     126 [-]: CAPTURE VAL R4; 
     127 [-]: CAPTURE REF R7; 
     128 [-]: CAPTURE REF R8; 
     129 [-]: CAPTURE VAL R21; 
     130 [-]: CAPTURE REF R12; 
     131 [-]: CAPTURE REF R15; 
     132 [-]: CAPTURE REF R16; 
     133 [-]: CAPTURE REF R6; 
     134 [-]: CAPTURE REF R5; 
     135 [-]: CAPTURE REF R9; 
     136 [-]: CAPTURE VAL R20; 
     137 [-]: CAPTURE VAL R34; 
     138 [-]: CAPTURE VAL R33; 
     139 [-]: CAPTURE REF R17; 
     140 [-]: CAPTURE REF R10; 
     141 [-]: SETGLOBAL R35 K26; "Initialize" = var35
     142 [-]: NEWCLOSURE R35 P27; 
     143 [-]: CAPTURE REF R11; 
     144 [-]: SETGLOBAL R35 K27; "Update" = var35
     145 [-]: DUPCLOSURE R35 K28; 
     146 [-]: CAPTURE VAL R22; 
     147 [-]: CAPTURE VAL R23; 
     148 [-]: CAPTURE VAL R27; 
     149 [-]: SETGLOBAL R35 K29; "RefreshTextMovie" = var35
     150 [-]: NEWCLOSURE R35 P29; 
     151 [-]: CAPTURE REF R10; 
     152 [-]: CAPTURE VAL R18; 
     153 [-]: SETGLOBAL R35 K30; "onKeyDown_HIDE_PAUSE_MENU" = var35
     154 [-]: CLOSEUPVALS R5; 
     155 [-]: RETURN R0 0  ; 


; Name:            
; Defined at line: 36
; #Upvalues:       1
; #Parameters:     0
; Is_vararg:       0
; Max Stack Size:  1

       0 [-]: GETUPVAL R0 0; var0 = upvalues[0]
       1 [-]: RETURN R0 1  ; 


; Name:            
; Defined at line: 40
; #Upvalues:       0
; #Parameters:     0
; Is_vararg:       0
; Max Stack Size:  1

       0 [-]: LOADB R0 1   ; var0 = true
       1 [-]: RETURN R0 1  ; 


; Name:            
; Defined at line: 44
; #Upvalues:       1
; #Parameters:     2
; Is_vararg:       0
; Max Stack Size:  6

       0 [-]: GETIMPORT R3 2; var3 = _T["BackgroundMovie"]
       1 [-]: FASTCALL1 64 R3 L0; 
       2 [-]: GETIMPORT R2 4; var2 = 0x7B998233
       3 [-]: CALL R2 2 2  ; var2 = var2(var3)
L 0:   4 [-]: JUMPIF R2 L1 ; goto L1 if var2
       5 [-]: GETIMPORT R2 2; var2 = _T["BackgroundMovie"]
       6 [-]: LOADK R4 K5  ; var4 = "ShowBlockingMessage"
       7 [-]: LOADK R5 K6  ; var5 = "0"
       8 [-]: NAMECALL R2 R2 K7; var3 = var2; var2 = var2[0xE4162EED]
       9 [-]: CALL R2 4 1  ; var2(var3, var4, var5)
L 1:  10 [-]: JUMPIFNOT R0 L3; goto L3 if not var0
      11 [-]: GETIMPORT R3 9; var3 = _T["LightDeco"]
      12 [-]: FASTCALL1 64 R3 L2; 
      13 [-]: GETIMPORT R2 4; var2 = 0x7B998233
      14 [-]: CALL R2 2 2  ; var2 = var2(var3)
L 2:  15 [-]: JUMPIF R2 L4 ; goto L4 if var2
      16 [-]: GETIMPORT R2 9; var2 = _T["LightDeco"]
      17 [-]: GETUPVAL R4 0; var4 = upvalues[0]
      18 [-]: LOADB R5 0   ; var5 = false
      19 [-]: NAMECALL R2 R2 K10; var3 = var2; var2 = var2[0xCA17A6F2]
      20 [-]: CALL R2 4 1  ; var2(var3, var4, var5)
      21 [-]: GETIMPORT R2 12; var2 = 0xBE190284
      22 [-]: GETIMPORT R4 14; var4 = gLotusAttractModeGameRulesType
      23 [-]: NAMECALL R2 R2 K15; var3 = var2; var2 = var2[0xF2DEAF69]
      24 [-]: CALL R2 3 2  ; var2 = var2(var3, var4)
      25 [-]: JUMPIFNOT R2 L4; goto L4 if not var2
      26 [-]: GETIMPORT R2 12; var2 = 0xBE190284
      27 [-]: GETIMPORT R4 9; var4 = _T["LightDeco"]
      28 [-]: NAMECALL R2 R2 K16; var3 = var2; var2 = var2[0xC3053781]
      29 [-]: CALL R2 3 1  ; var2(var3, var4)
      30 [-]: JUMP L4      ; goto L4
L 3:  31 [-]: GETIMPORT R2 18; var2 = 0x3D106989
      32 [-]: LOADK R3 K19 ; var3 = "Failed to update light info!"
      33 [-]: CALL R2 2 1  ; var2(var3)
L 4:  34 [-]: GETIMPORT R2 21; var2 = 0xAE91E43B
      35 [-]: NAMECALL R2 R2 K22; var3 = var2; var2 = var2[0x32302B4A]
      36 [-]: CALL R2 2 1  ; var2(var3)
      37 [-]: RETURN R0 0  ; 


; Name:            
; Defined at line: 64
; #Upvalues:       5
; #Parameters:     0
; Is_vararg:       0
; Max Stack Size:  11

       0 [-]: GETUPVAL R1 0; var1 = upvalues[0]
       1 [-]: FASTCALL1 64 R1 L0; 
       2 [-]: GETIMPORT R0 1; var0 = 0x7B998233
       3 [-]: CALL R0 2 2  ; var0 = var0(var1)
L 0:   4 [-]: JUMPIF R0 L1 ; goto L1 if var0
       5 [-]: GETUPVAL R0 0; var0 = upvalues[0]
       6 [-]: NAMECALL R0 R0 K2; var1 = var0; var0 = var0[0x09C8A77D]
       7 [-]: CALL R0 2 2  ; var0 = var0(var1)
       8 [-]: JUMPIFNOT R0 L1; goto L1 if not var0
       9 [-]: RETURN R0 0  ; 
L 1:  10 [-]: GETIMPORT R1 5; var1 = _T["LightDeco"]
      11 [-]: FASTCALL1 64 R1 L2; 
      12 [-]: GETIMPORT R0 1; var0 = 0x7B998233
      13 [-]: CALL R0 2 2  ; var0 = var0(var1)
L 2:  14 [-]: JUMPIF R0 L10; goto L10 if var0
      15 [-]: GETUPVAL R1 1; var1 = upvalues[1]
      16 [-]: GETTABLEKS R0 R1 K6; var0 = var1["mColorCorrection"]
      17 [-]: GETUPVAL R2 2; var2 = upvalues[2]
      18 [-]: GETTABLEKS R1 R2 K6; var1 = var2["mColorCorrection"]
      19 [-]: JUMPIFNOTEQ R0 R1 L3; goto L3 if var0 ~= var65852
      20 [-]: GETUPVAL R1 1; var1 = upvalues[1]
      21 [-]: GETTABLEKS R0 R1 K7; var0 = var1["mXOffset"]
      22 [-]: GETUPVAL R2 2; var2 = upvalues[2]
      23 [-]: GETTABLEKS R1 R2 K7; var1 = var2["mXOffset"]
      24 [-]: JUMPIFNOTEQ R0 R1 L3; goto L3 if var0 ~= var65852
      25 [-]: GETUPVAL R1 1; var1 = upvalues[1]
      26 [-]: GETTABLEKS R0 R1 K8; var0 = var1["mYOffset"]
      27 [-]: GETUPVAL R2 2; var2 = upvalues[2]
      28 [-]: GETTABLEKS R1 R2 K8; var1 = var2["mYOffset"]
      29 [-]: JUMPIFNOTEQ R0 R1 L3; goto L3 if var0 ~= var65852
      30 [-]: GETUPVAL R1 1; var1 = upvalues[1]
      31 [-]: GETTABLEKS R0 R1 K9; var0 = var1["mText"]
      32 [-]: GETUPVAL R2 2; var2 = upvalues[2]
      33 [-]: GETTABLEKS R1 R2 K9; var1 = var2["mText"]
      34 [-]: JUMPIFNOTEQ R0 R1 L3; goto L3 if var0 ~= var65852
      35 [-]: GETUPVAL R1 1; var1 = upvalues[1]
      36 [-]: GETTABLEKS R0 R1 K10; var0 = var1["mTextScale"]
      37 [-]: GETUPVAL R2 2; var2 = upvalues[2]
      38 [-]: GETTABLEKS R1 R2 K10; var1 = var2["mTextScale"]
      39 [-]: JUMPIFNOTEQ R0 R1 L3; goto L3 if var0 ~= var65852
      40 [-]: GETUPVAL R1 1; var1 = upvalues[1]
      41 [-]: GETTABLEKS R0 R1 K11; var0 = var1["mTextColorA"]
      42 [-]: GETUPVAL R2 2; var2 = upvalues[2]
      43 [-]: GETTABLEKS R1 R2 K11; var1 = var2["mTextColorA"]
      44 [-]: JUMPIFNOTEQ R0 R1 L3; goto L3 if var0 ~= var65852
      45 [-]: GETUPVAL R1 1; var1 = upvalues[1]
      46 [-]: GETTABLEKS R0 R1 K12; var0 = var1["mTextColorB"]
      47 [-]: GETUPVAL R2 2; var2 = upvalues[2]
      48 [-]: GETTABLEKS R1 R2 K12; var1 = var2["mTextColorB"]
      49 [-]: JUMPIFNOTEQ R0 R1 L3; goto L3 if var0 ~= var65852
      50 [-]: GETUPVAL R1 1; var1 = upvalues[1]
      51 [-]: GETTABLEKS R0 R1 K13; var0 = var1["mTextOrientation"]
      52 [-]: GETUPVAL R2 2; var2 = upvalues[2]
      53 [-]: GETTABLEKS R1 R2 K13; var1 = var2["mTextOrientation"]
      54 [-]: JUMPIFEQ R0 R1 L10; goto L10 if var0 == var983073
L 3:  55 [-]: GETIMPORT R0 15; var0 = _T["DojoMgr"]
      56 [-]: JUMPXEQKNIL R0 L6 NOT; 
      57 [-]: GETIMPORT R0 5; var0 = _T["LightDeco"]
      58 [-]: NAMECALL R0 R0 K16; var1 = var0; var0 = var0[0x0682D093]
      59 [-]: CALL R0 2 2  ; var0 = var0(var1)
      60 [-]: GETUPVAL R3 3; var3 = upvalues[3]
      61 [-]: GETTABLEKS R2 R3 K17; var2 = var3[0x93219F62]
      62 [-]: MOVE R3 R0   ; var3 = var0
      63 [-]: CALL R2 2 2  ; var2 = var2(var3)
      64 [-]: GETUPVAL R4 3; var4 = upvalues[3]
      65 [-]: GETTABLEKS R3 R4 K18; var3 = var4["DECO_AREA_APARTMENT"]
      66 [-]: JUMPIFEQ R2 R3 L4; goto L4 if var2 == var16777478
      67 [-]: LOADB R1 0 +1; var1 = false
L 4:  68 [-]: LOADB R1 1   ; var1 = true
L 5:  69 [-]: GETUPVAL R2 4; var2 = upvalues[4]
      70 [-]: GETIMPORT R4 5; var4 = _T["LightDeco"]
      71 [-]: NAMECALL R4 R4 K19; var5 = var4; var4 = var4[0xCDE10C4A]
      72 [-]: CALL R4 2 2  ; var4 = var4(var5)
      73 [-]: GETIMPORT R5 5; var5 = _T["LightDeco"]
      74 [-]: NAMECALL R5 R5 K20; var6 = var5; var5 = var5[0xF537CFC7]
      75 [-]: CALL R5 2 2  ; var5 = var5(var6)
      76 [-]: LOADK R6 K21 ; var6 = ""
      77 [-]: MOVE R7 R0   ; var7 = var0
      78 [-]: MOVE R8 R1   ; var8 = var1
      79 [-]: GETUPVAL R9 2; var9 = upvalues[2]
      80 [-]: LOADK R10 K22; var10 = "OnInfoSaved"
      81 [-]: NAMECALL R2 R2 K23; var3 = var2; var2 = var2[0x1C94E7B8]
      82 [-]: CALL R2 9 1  ; var2(var3, var4, var5, var6, var7, var8, var9, var10)
      83 [-]: JUMP L7      ; goto L7
L 6:  84 [-]: GETIMPORT R0 25; var0 = 0x89326C93
      85 [-]: NAMECALL R0 R0 K26; var1 = var0; var0 = var0[0x78298275]
      86 [-]: CALL R0 2 2  ; var0 = var0(var1)
      87 [-]: NAMECALL R0 R0 K27; var1 = var0; var0 = var0[0xE79E7EF4]
      88 [-]: CALL R0 2 2  ; var0 = var0(var1)
      89 [-]: NAMECALL R0 R0 K28; var1 = var0; var0 = var0[0x7D05E45F]
      90 [-]: CALL R0 2 2  ; var0 = var0(var1)
      91 [-]: GETIMPORT R2 15; var2 = _T["DojoMgr"]
      92 [-]: MOVE R4 R0   ; var4 = var0
      93 [-]: NAMECALL R2 R2 K29; var3 = var2; var2 = var2[0xD1964243]
      94 [-]: CALL R2 3 2  ; var2 = var2(var3, var4)
      95 [-]: GETTABLEKS R1 R2 K30; var1 = var2["id"]
      96 [-]: GETIMPORT R2 32; var2 = _T["DojoMgr"]["mJsonProcLevelHelper"]
      97 [-]: GETIMPORT R4 5; var4 = _T["LightDeco"]
      98 [-]: NAMECALL R4 R4 K19; var5 = var4; var4 = var4[0xCDE10C4A]
      99 [-]: CALL R4 2 2  ; var4 = var4(var5)
     100 [-]: GETIMPORT R5 5; var5 = _T["LightDeco"]
     101 [-]: NAMECALL R5 R5 K20; var6 = var5; var5 = var5[0xF537CFC7]
     102 [-]: CALL R5 2 2  ; var5 = var5(var6)
     103 [-]: MOVE R6 R1   ; var6 = var1
     104 [-]: GETUPVAL R7 2; var7 = upvalues[2]
     105 [-]: LOADK R8 K22 ; var8 = "OnInfoSaved"
     106 [-]: NAMECALL R2 R2 K23; var3 = var2; var2 = var2[0x1C94E7B8]
     107 [-]: CALL R2 7 1  ; var2(var3, var4, var5, var6, var7, var8)
L 7: 108 [-]: GETIMPORT R1 34; var1 = _T["BackgroundMovie"]
     109 [-]: FASTCALL1 64 R1 L8; 
     110 [-]: GETIMPORT R0 1; var0 = 0x7B998233
     111 [-]: CALL R0 2 2  ; var0 = var0(var1)
L 8: 112 [-]: JUMPIF R0 L9 ; goto L9 if var0
     113 [-]: GETIMPORT R0 34; var0 = _T["BackgroundMovie"]
     114 [-]: LOADK R2 K35 ; var2 = "ShowBlockingMessage"
     115 [-]: LOADK R3 K36 ; var3 = "2"
     116 [-]: NAMECALL R0 R0 K37; var1 = var0; var0 = var0[0xE4162EED]
     117 [-]: CALL R0 4 1  ; var0(var1, var2, var3)
L 9: 118 [-]: RETURN R0 0  ; 
L10: 119 [-]: GETIMPORT R0 39; var0 = _T["SetButtons"]
     120 [-]: GETIMPORT R1 41; var1 = 0xAE91E43B
     121 [-]: LOADNIL R2   ; var2 = nil
     122 [-]: CALL R0 3 1  ; var0(var1, var2)
     123 [-]: GETIMPORT R0 41; var0 = 0xAE91E43B
     124 [-]: NAMECALL R0 R0 K42; var1 = var0; var0 = var0[0x32302B4A]
     125 [-]: CALL R0 2 1  ; var0(var1)
     126 [-]: RETURN R0 0  ; 


; Name:            
; Defined at line: 101
; #Upvalues:       1
; #Parameters:     0
; Is_vararg:       0
; Max Stack Size:  1

       0 [-]: GETUPVAL R0 0; var0 = upvalues[0]
       1 [-]: CALL R0 1 1  ; var0()
       2 [-]: RETURN R0 0  ; 


; Name:            
; Defined at line: 105
; #Upvalues:       1
; #Parameters:     0
; Is_vararg:       0
; Max Stack Size:  10

       0 [-]: NEWTABLE R0 0 0; var0 = {}
       1 [-]: GETUPVAL R2 0; var2 = upvalues[0]
       2 [-]: FASTCALL1 64 R2 L0; 
       3 [-]: GETIMPORT R1 1; var1 = 0x7B998233
       4 [-]: CALL R1 2 2  ; var1 = var1(var2)
L 0:   5 [-]: JUMPIF R1 L3 ; goto L3 if var1
       6 [-]: GETUPVAL R1 0; var1 = upvalues[0]
       7 [-]: NAMECALL R1 R1 K2; var2 = var1; var1 = var1[0x1B34B1EC]
       8 [-]: CALL R1 2 2  ; var1 = var1(var2)
       9 [-]: GETIMPORT R2 4; var2 = 0xCFC01047
      10 [-]: MOVE R3 R1   ; var3 = var1
      11 [-]: CALL R2 2 4  ; var2, var3, var4 = var2(var3)
      12 [-]: FORGPREP_NEXT R2 L2; 
L 1:  13 [-]: GETTABLEKS R7 R6 K5; var7 = var6["Label"]
      14 [-]: JUMPXEQKS R7 K6 L2; 
      15 [-]: FASTCALL2 52 R0 R6 L2; 
      16 [-]: MOVE R8 R0   ; var8 = var0
      17 [-]: MOVE R9 R6   ; var9 = var6
      18 [-]: GETIMPORT R7 9; var7 = 0x33BDD652[0x23D5322F]
      19 [-]: CALL R7 3 1  ; var7(var8, var9)
L 2:  20 [-]: FORGLOOP R2 L1 2; 
L 3:  21 [-]: LOADK R1 K10 ; var1 = ""
      22 [-]: GETUPVAL R3 0; var3 = upvalues[0]
      23 [-]: GETTABLEKS R2 R3 K11; var2 = var3["mState"]
      24 [-]: GETUPVAL R5 0; var5 = upvalues[0]
      25 [-]: GETTABLEKS R4 R5 K12; var4 = var5["State"]
      26 [-]: GETTABLEKS R3 R4 K13; var3 = var4["CUSTOMIZATION"]
      27 [-]: JUMPIFNOTEQ R2 R3 L4; goto L4 if var2 ~= var917831
      28 [-]: LOADK R1 K14 ; var1 = "/Lotus/Language/Menu/MissionStats_Done"
      29 [-]: JUMP L5      ; goto L5
L 4:  30 [-]: LOADK R1 K15 ; var1 = "/Lotus/Language/Menu/Global_Back"
L 5:  31 [-]: DUPTABLE R4 18; 
      32 [-]: SETTABLEKS R1 R4 K5; var1["Label"] = var4
      33 [-]: DUPCLOSURE R5 K19; 
      34 [-]: SETTABLEKS R5 R4 K16; var5["CallBack"] = var4
      35 [-]: LOADK R5 K20 ; var5 = "MENU_CANCEL"
      36 [-]: SETTABLEKS R5 R4 K17; var5["CallOut"] = var4
      37 [-]: FASTCALL2 52 R0 R4 L6; 
      38 [-]: MOVE R3 R0   ; var3 = var0
      39 [-]: GETIMPORT R2 9; var2 = 0x33BDD652[0x23D5322F]
      40 [-]: CALL R2 3 1  ; var2(var3, var4)
L 6:  41 [-]: GETIMPORT R2 23; var2 = _T["SetButtons"]
      42 [-]: GETIMPORT R3 25; var3 = 0xAE91E43B
      43 [-]: MOVE R4 R0   ; var4 = var0
      44 [-]: GETIMPORT R5 27; var5 = 0xCD0165A3
      45 [-]: LOADN R6 1   ; var6 = 1
      46 [-]: CALL R5 2 0  ; var5, ... = var5(var6)
      47 [-]: CALL R2 0 1  ; var2(var3, ...)
      48 [-]: RETURN R0 0  ; 


; Name:            
; Defined at line: 129
; #Upvalues:       1
; #Parameters:     0
; Is_vararg:       0
; Max Stack Size:  1

       0 [-]: GETUPVAL R0 0; var0 = upvalues[0]
       1 [-]: CALL R0 1 1  ; var0()
       2 [-]: RETURN R0 0  ; 


; Name:            
; Defined at line: 133
; #Upvalues:       1
; #Parameters:     0
; Is_vararg:       0
; Max Stack Size:  4

       0 [-]: GETIMPORT R0 1; var0 = 0x9BA7909F
       1 [-]: GETIMPORT R2 3; var2 = 0x6E48C770
       2 [-]: NAMECALL R0 R0 K4; var1 = var0; var0 = var0[0xBCFB64AB]
       3 [-]: CALL R0 3 2  ; var0 = var0(var1, var2)
       4 [-]: SETUPVAL R0 0; upvalues[0] = var0
       5 [-]: GETUPVAL R1 0; var1 = upvalues[0]
       6 [-]: FASTCALL1 64 R1 L0; 
       7 [-]: GETIMPORT R0 6; var0 = 0x7B998233
       8 [-]: CALL R0 2 2  ; var0 = var0(var1)
L 0:   9 [-]: JUMPIFNOT R0 L1; goto L1 if not var0
      10 [-]: GETIMPORT R0 1; var0 = 0x9BA7909F
      11 [-]: GETIMPORT R2 3; var2 = 0x6E48C770
      12 [-]: NAMECALL R0 R0 K7; var1 = var0; var0 = var0[0xCFBA257F]
      13 [-]: CALL R0 3 2  ; var0 = var0(var1, var2)
      14 [-]: SETUPVAL R0 0; upvalues[0] = var0
L 1:  15 [-]: GETUPVAL R1 0; var1 = upvalues[0]
      16 [-]: FASTCALL1 64 R1 L2; 
      17 [-]: GETIMPORT R0 6; var0 = 0x7B998233
      18 [-]: CALL R0 2 2  ; var0 = var0(var1)
L 2:  19 [-]: JUMPIF R0 L3 ; goto L3 if var0
      20 [-]: GETUPVAL R0 0; var0 = upvalues[0]
      21 [-]: LOADK R2 K8  ; var2 = "EnableColorCorrection"
      22 [-]: LOADK R3 K9  ; var3 = "false"
      23 [-]: NAMECALL R0 R0 K10; var1 = var0; var0 = var0[0xE4162EED]
      24 [-]: CALL R0 4 1  ; var0(var1, var2, var3)
      25 [-]: GETUPVAL R0 0; var0 = upvalues[0]
      26 [-]: LOADK R2 K11 ; var2 = "SetHideHud"
      27 [-]: LOADK R3 K9  ; var3 = "false"
      28 [-]: NAMECALL R0 R0 K10; var1 = var0; var0 = var0[0xE4162EED]
      29 [-]: CALL R0 4 1  ; var0(var1, var2, var3)
      30 [-]: GETUPVAL R0 0; var0 = upvalues[0]
      31 [-]: LOADK R2 K8  ; var2 = "EnableColorCorrection"
      32 [-]: LOADK R3 K9  ; var3 = "false"
      33 [-]: NAMECALL R0 R0 K10; var1 = var0; var0 = var0[0xE4162EED]
      34 [-]: CALL R0 4 1  ; var0(var1, var2, var3)
      35 [-]: GETUPVAL R0 0; var0 = upvalues[0]
      36 [-]: LOADK R2 K12 ; var2 = "EnableBackgroundFade"
      37 [-]: LOADK R3 K9  ; var3 = "false"
      38 [-]: NAMECALL R0 R0 K10; var1 = var0; var0 = var0[0xE4162EED]
      39 [-]: CALL R0 4 1  ; var0(var1, var2, var3)
      40 [-]: GETUPVAL R0 0; var0 = upvalues[0]
      41 [-]: LOADK R2 K13 ; var2 = "EnableBackgroundBlur"
      42 [-]: LOADK R3 K9  ; var3 = "false"
      43 [-]: NAMECALL R0 R0 K10; var1 = var0; var0 = var0[0xE4162EED]
      44 [-]: CALL R0 4 1  ; var0(var1, var2, var3)
      45 [-]: GETUPVAL R0 0; var0 = upvalues[0]
      46 [-]: LOADK R2 K14 ; var2 = "SetAlpha"
      47 [-]: LOADK R3 K15 ; var3 = "50,80"
      48 [-]: NAMECALL R0 R0 K10; var1 = var0; var0 = var0[0xE4162EED]
      49 [-]: CALL R0 4 1  ; var0(var1, var2, var3)
L 3:  50 [-]: RETURN R0 0  ; 


; Name:            
; Defined at line: 148
; #Upvalues:       0
; #Parameters:     1
; Is_vararg:       0
; Max Stack Size:  6

       0 [-]: GETIMPORT R2 1; var2 = 0x89326C93
       1 [-]: FASTCALL1 64 R2 L0; 
       2 [-]: GETIMPORT R1 3; var1 = 0x7B998233
       3 [-]: CALL R1 2 2  ; var1 = var1(var2)
L 0:   4 [-]: JUMPIF R1 L3 ; goto L3 if var1
       5 [-]: GETIMPORT R1 1; var1 = 0x89326C93
       6 [-]: NAMECALL R1 R1 K4; var2 = var1; var1 = var1[0x78298275]
       7 [-]: CALL R1 2 2  ; var1 = var1(var2)
       8 [-]: FASTCALL1 64 R1 L1; 
       9 [-]: MOVE R3 R1   ; var3 = var1
      10 [-]: GETIMPORT R2 3; var2 = 0x7B998233
      11 [-]: CALL R2 2 2  ; var2 = var2(var3)
L 1:  12 [-]: JUMPIF R2 L3 ; goto L3 if var2
      13 [-]: NAMECALL R2 R1 K5; var3 = var1; var2 = var1[0x59E42E1B]
      14 [-]: CALL R2 2 2  ; var2 = var2(var3)
      15 [-]: NAMECALL R2 R2 K6; var3 = var2; var2 = var2[0xC348FCEB]
      16 [-]: CALL R2 2 2  ; var2 = var2(var3)
      17 [-]: FASTCALL1 64 R2 L2; 
      18 [-]: MOVE R4 R2   ; var4 = var2
      19 [-]: GETIMPORT R3 3; var3 = 0x7B998233
      20 [-]: CALL R3 2 2  ; var3 = var3(var4)
L 2:  21 [-]: JUMPIF R3 L3 ; goto L3 if var3
      22 [-]: GETIMPORT R5 8; var5 = gDecoModeActionType
      23 [-]: NAMECALL R3 R2 K9; var4 = var2; var3 = var2[0xF2DEAF69]
      24 [-]: CALL R3 3 2  ; var3 = var3(var4, var5)
      25 [-]: JUMPIFNOT R3 L3; goto L3 if not var3
      26 [-]: MOVE R5 R0   ; var5 = var0
      27 [-]: NAMECALL R3 R2 K10; var4 = var2; var3 = var2[0x0B6EF828]
      28 [-]: CALL R3 3 1  ; var3(var4, var5)
L 3:  29 [-]: RETURN R0 0  ; 


; Name:            
; Defined at line: 160
; #Upvalues:       3
; #Parameters:     0
; Is_vararg:       0
; Max Stack Size:  6

       0 [-]: GETIMPORT R1 1; var1 = 0x9BA7909F
       1 [-]: FASTCALL1 64 R1 L0; 
       2 [-]: GETIMPORT R0 3; var0 = 0x7B998233
       3 [-]: CALL R0 2 2  ; var0 = var0(var1)
L 0:   4 [-]: JUMPIF R0 L2 ; goto L2 if var0
       5 [-]: GETIMPORT R0 1; var0 = 0x9BA7909F
       6 [-]: GETUPVAL R2 0; var2 = upvalues[0]
       7 [-]: NAMECALL R0 R0 K4; var1 = var0; var0 = var0[0xBCFB64AB]
       8 [-]: CALL R0 3 2  ; var0 = var0(var1, var2)
       9 [-]: FASTCALL1 64 R0 L1; 
      10 [-]: MOVE R2 R0   ; var2 = var0
      11 [-]: GETIMPORT R1 3; var1 = 0x7B998233
      12 [-]: CALL R1 2 2  ; var1 = var1(var2)
L 1:  13 [-]: JUMPIF R1 L2 ; goto L2 if var1
      14 [-]: LOADK R3 K5  ; var3 = "Show"
      15 [-]: LOADK R4 K6  ; var4 = ""
      16 [-]: NAMECALL R1 R0 K7; var2 = var0; var1 = var0[0xE4162EED]
      17 [-]: CALL R1 4 1  ; var1(var2, var3, var4)
L 2:  18 [-]: GETIMPORT R0 10; var0 = _T["ChangeHubVisCounter"]
      19 [-]: JUMPXEQKNIL R0 L3; 
      20 [-]: GETIMPORT R0 10; var0 = _T["ChangeHubVisCounter"]
      21 [-]: LOADN R1 -1  ; var1 = -1
      22 [-]: CALL R0 2 1  ; var0(var1)
L 3:  23 [-]: GETUPVAL R1 1; var1 = upvalues[1]
      24 [-]: FASTCALL1 64 R1 L4; 
      25 [-]: GETIMPORT R0 3; var0 = 0x7B998233
      26 [-]: CALL R0 2 2  ; var0 = var0(var1)
L 4:  27 [-]: JUMPIFNOT R0 L5; goto L5 if not var0
      28 [-]: GETIMPORT R0 1; var0 = 0x9BA7909F
      29 [-]: GETIMPORT R2 12; var2 = 0x6E48C770
      30 [-]: NAMECALL R0 R0 K4; var1 = var0; var0 = var0[0xBCFB64AB]
      31 [-]: CALL R0 3 2  ; var0 = var0(var1, var2)
      32 [-]: SETUPVAL R0 1; upvalues[0] = var1
L 5:  33 [-]: GETUPVAL R1 1; var1 = upvalues[1]
      34 [-]: FASTCALL1 64 R1 L6; 
      35 [-]: GETIMPORT R0 3; var0 = 0x7B998233
      36 [-]: CALL R0 2 2  ; var0 = var0(var1)
L 6:  37 [-]: JUMPIF R0 L7 ; goto L7 if var0
      38 [-]: GETUPVAL R0 1; var0 = upvalues[1]
      39 [-]: LOADK R2 K13 ; var2 = "TransitionOut"
      40 [-]: NEWTABLE R3 0 2; var3 = {}
      41 [-]: LOADK R4 K6  ; var4 = ""
      42 [-]: LOADK R5 K14 ; var5 = "false"
      43 [-]: SETLIST R3 R4 2 [1]; var3[1] = var4; var3[2] = var5; var3[3] = var6; 
      44 [-]: NAMECALL R0 R0 K15; var1 = var0; var0 = var0[0xF56F3887]
      45 [-]: CALL R0 4 1  ; var0(var1, var2, var3)
L 7:  46 [-]: GETIMPORT R1 17; var1 = _T["ClearSquadOverlayTitle"]
      47 [-]: FASTCALL1 64 R1 L8; 
      48 [-]: GETIMPORT R0 3; var0 = 0x7B998233
      49 [-]: CALL R0 2 2  ; var0 = var0(var1)
L 8:  50 [-]: JUMPIF R0 L9 ; goto L9 if var0
      51 [-]: GETIMPORT R0 17; var0 = _T["ClearSquadOverlayTitle"]
      52 [-]: CALL R0 1 1  ; var0()
L 9:  53 [-]: LOADNIL R1   ; var1 = nil
      54 [-]: FASTCALL1 64 R1 L10; 
      55 [-]: GETIMPORT R0 3; var0 = 0x7B998233
      56 [-]: CALL R0 2 2  ; var0 = var0(var1)
L10:  57 [-]: JUMPIF R0 L11; goto L11 if var0
      58 [-]: LOADNIL R0   ; var0 = nil
      59 [-]: NAMECALL R0 R0 K18; var1 = var0; var0 = var0[0x32302B4A]
      60 [-]: CALL R0 2 1  ; var0(var1)
L11:  61 [-]: GETUPVAL R0 2; var0 = upvalues[2]
      62 [-]: LOADB R1 0   ; var1 = false
      63 [-]: CALL R0 2 1  ; var0(var1)
      64 [-]: RETURN R0 0  ; 


; Name:            
; Defined at line: 190
; #Upvalues:       1
; #Parameters:     1
; Is_vararg:       0
; Max Stack Size:  5

       0 [-]: GETIMPORT R1 1; var1 = 0x60130201
       1 [-]: MOVE R2 R0   ; var2 = var0
       2 [-]: CALL R1 2 2  ; var1 = var1(var2)
       3 [-]: GETUPVAL R3 0; var3 = upvalues[0]
       4 [-]: GETTABLEKS R2 R3 K2; var2 = var3[0x4DBFB382]
       5 [-]: MOVE R3 R1   ; var3 = var1
       6 [-]: CALL R2 2 2  ; var2 = var2(var3)
       7 [-]: NAMECALL R3 R2 K3; var4 = var2; var3 = var2[0xA5D5C8F6]
       8 [-]: CALL R3 2 2  ; var3 = var3(var4)
       9 [-]: RETURN R3 1  ; 


; Name:            
; Defined at line: 197
; #Upvalues:       0
; #Parameters:     1
; Is_vararg:       0
; Max Stack Size:  2

       0 [-]: JUMPXEQKN R0 K0 L0 NOT; 
       1 [-]: LOADK R1 K1  ; var1 = 16711422
       2 [-]: RETURN R1 1  ; 
L 0:   3 [-]: RETURN R0 1  ; 


; Name:            
; Defined at line: 204
; #Upvalues:       6
; #Parameters:     2
; Is_vararg:       0
; Max Stack Size:  13

       0 [-]: GETTABLEKS R2 R0 K0; var2 = var0["DefaultColor"]
       1 [-]: GETTABLEKS R3 R0 K1; var3 = var0["CurrColor"]
       2 [-]: JUMPXEQKNIL R3 L0; 
       3 [-]: GETTABLEKS R2 R0 K1; var2 = var0["CurrColor"]
L 0:   4 [-]: GETTABLEKS R3 R0 K2; var3 = var0["ColorOp"]
       5 [-]: JUMPXEQKN R3 K3 L3 NOT; 
       6 [-]: GETUPVAL R3 0; var3 = upvalues[0]
       7 [-]: NAMECALL R4 R2 K4; var5 = var2; var4 = var2[0xA5D5C8F6]
       8 [-]: CALL R4 2 2  ; var4 = var4(var5)
       9 [-]: SETTABLEKS R4 R3 K5; var4["mTextColorA"] = var3
      10 [-]: GETUPVAL R3 1; var3 = upvalues[1]
      11 [-]: GETUPVAL R5 0; var5 = upvalues[0]
      12 [-]: GETTABLEKS R4 R5 K5; var4 = var5["mTextColorA"]
      13 [-]: CALL R3 2 2  ; var3 = var3(var4)
      14 [-]: GETUPVAL R4 1; var4 = upvalues[1]
      15 [-]: GETUPVAL R6 0; var6 = upvalues[0]
      16 [-]: GETTABLEKS R5 R6 K6; var5 = var6["mTextColorB"]
      17 [-]: CALL R4 2 2  ; var4 = var4(var5)
      18 [-]: GETUPVAL R5 2; var5 = upvalues[2]
      19 [-]: MOVE R6 R3   ; var6 = var3
      20 [-]: CALL R5 2 2  ; var5 = var5(var6)
      21 [-]: MOVE R3 R5   ; var3 = var5
      22 [-]: GETUPVAL R5 2; var5 = upvalues[2]
      23 [-]: MOVE R6 R4   ; var6 = var4
      24 [-]: CALL R5 2 2  ; var5 = var5(var6)
      25 [-]: MOVE R4 R5   ; var4 = var5
      26 [-]: GETIMPORT R5 9; var5 = _T["TextLightMovie"]
      27 [-]: LOADK R7 K10 ; var7 = "SetVertexColors"
      28 [-]: NEWTABLE R8 0 2; var8 = {}
      29 [-]: FASTCALL1 63 R3 L1; 
      30 [-]: MOVE R10 R3  ; var10 = var3
      31 [-]: GETIMPORT R9 12; var9 = 0x64FB1586
      32 [-]: CALL R9 2 2  ; var9 = var9(var10)
L 1:  33 [-]: FASTCALL1 63 R4 L2; 
      34 [-]: MOVE R11 R4  ; var11 = var4
      35 [-]: GETIMPORT R10 12; var10 = 0x64FB1586
      36 [-]: CALL R10 2 2 ; var10 = var10(var11)
L 2:  37 [-]: SETLIST R8 R9 2 [1]; var8[1] = var9; var8[2] = var10; var8[3] = var11; 
      38 [-]: NAMECALL R5 R5 K13; var6 = var5; var5 = var5[0xF56F3887]
      39 [-]: CALL R5 4 1  ; var5(var6, var7, var8)
      40 [-]: RETURN R0 0  ; 
L 3:  41 [-]: GETTABLEKS R3 R0 K2; var3 = var0["ColorOp"]
      42 [-]: JUMPXEQKN R3 K14 L6 NOT; 
      43 [-]: GETUPVAL R3 0; var3 = upvalues[0]
      44 [-]: NAMECALL R4 R2 K4; var5 = var2; var4 = var2[0xA5D5C8F6]
      45 [-]: CALL R4 2 2  ; var4 = var4(var5)
      46 [-]: SETTABLEKS R4 R3 K6; var4["mTextColorB"] = var3
      47 [-]: GETUPVAL R3 1; var3 = upvalues[1]
      48 [-]: GETUPVAL R5 0; var5 = upvalues[0]
      49 [-]: GETTABLEKS R4 R5 K5; var4 = var5["mTextColorA"]
      50 [-]: CALL R3 2 2  ; var3 = var3(var4)
      51 [-]: GETUPVAL R4 1; var4 = upvalues[1]
      52 [-]: GETUPVAL R6 0; var6 = upvalues[0]
      53 [-]: GETTABLEKS R5 R6 K6; var5 = var6["mTextColorB"]
      54 [-]: CALL R4 2 2  ; var4 = var4(var5)
      55 [-]: GETUPVAL R5 2; var5 = upvalues[2]
      56 [-]: MOVE R6 R3   ; var6 = var3
      57 [-]: CALL R5 2 2  ; var5 = var5(var6)
      58 [-]: MOVE R3 R5   ; var3 = var5
      59 [-]: GETUPVAL R5 2; var5 = upvalues[2]
      60 [-]: MOVE R6 R4   ; var6 = var4
      61 [-]: CALL R5 2 2  ; var5 = var5(var6)
      62 [-]: MOVE R4 R5   ; var4 = var5
      63 [-]: GETIMPORT R5 9; var5 = _T["TextLightMovie"]
      64 [-]: LOADK R7 K10 ; var7 = "SetVertexColors"
      65 [-]: NEWTABLE R8 0 2; var8 = {}
      66 [-]: FASTCALL1 63 R3 L4; 
      67 [-]: MOVE R10 R3  ; var10 = var3
      68 [-]: GETIMPORT R9 12; var9 = 0x64FB1586
      69 [-]: CALL R9 2 2  ; var9 = var9(var10)
L 4:  70 [-]: FASTCALL1 63 R4 L5; 
      71 [-]: MOVE R11 R4  ; var11 = var4
      72 [-]: GETIMPORT R10 12; var10 = 0x64FB1586
      73 [-]: CALL R10 2 2 ; var10 = var10(var11)
L 5:  74 [-]: SETLIST R8 R9 2 [1]; var8[1] = var9; var8[2] = var10; var8[3] = var11; 
      75 [-]: NAMECALL R5 R5 K13; var6 = var5; var5 = var5[0xF56F3887]
      76 [-]: CALL R5 4 1  ; var5(var6, var7, var8)
      77 [-]: RETURN R0 0  ; 
L 6:  78 [-]: GETUPVAL R4 3; var4 = upvalues[3]
      79 [-]: FASTCALL1 64 R4 L7; 
      80 [-]: GETIMPORT R3 16; var3 = 0x7B998233
      81 [-]: CALL R3 2 2  ; var3 = var3(var4)
L 7:  82 [-]: JUMPIF R3 L8 ; goto L8 if var3
      83 [-]: GETUPVAL R3 3; var3 = upvalues[3]
      84 [-]: MOVE R5 R2   ; var5 = var2
      85 [-]: NAMECALL R3 R3 K17; var4 = var3; var3 = var3[0xA3927FE9]
      86 [-]: CALL R3 3 1  ; var3(var4, var5)
      87 [-]: GETUPVAL R4 4; var4 = upvalues[4]
      88 [-]: GETTABLEKS R3 R4 K18; var3 = var4[0x8BCD12B6]
      89 [-]: NAMECALL R4 R2 K4; var5 = var2; var4 = var2[0xA5D5C8F6]
      90 [-]: CALL R4 2 0  ; var4, ... = var4(var5)
      91 [-]: CALL R3 0 2  ; var3 = var3(var4, ...)
      92 [-]: GETIMPORT R4 20; var4 = _T["LightDeco"]
      93 [-]: GETIMPORT R6 22; var6 = 0x0469F296
      94 [-]: LOADK R7 K23 ; var7 = "EmissiveTintColor"
      95 [-]: CALL R6 2 2  ; var6 = var6(var7)
      96 [-]: GETUPVAL R8 5; var8 = upvalues[5]
      97 [-]: GETTABLEKS R7 R8 K24; var7 = var8[0x021DC4BE]
      98 [-]: LOADN R9 255 ; var9 = 255
      99 [-]: GETTABLEKS R10 R3 K25; var10 = var3["r"]
     100 [-]: MUL R8 R9 R10; var8 = var9 * var10
     101 [-]: CALL R7 2 2  ; var7 = var7(var8)
     102 [-]: GETUPVAL R9 5; var9 = upvalues[5]
     103 [-]: GETTABLEKS R8 R9 K24; var8 = var9[0x021DC4BE]
     104 [-]: LOADN R10 255; var10 = 255
     105 [-]: GETTABLEKS R11 R3 K26; var11 = var3["g"]
     106 [-]: MUL R9 R10 R11; var9 = var10 * var11
     107 [-]: CALL R8 2 2  ; var8 = var8(var9)
     108 [-]: GETUPVAL R10 5; var10 = upvalues[5]
     109 [-]: GETTABLEKS R9 R10 K24; var9 = var10[0x021DC4BE]
     110 [-]: LOADN R11 255; var11 = 255
     111 [-]: GETTABLEKS R12 R3 K27; var12 = var3["b"]
     112 [-]: MUL R10 R11 R12; var10 = var11 * var12
     113 [-]: CALL R9 2 2  ; var9 = var9(var10)
     114 [-]: LOADN R10 1  ; var10 = 1
     115 [-]: LOADB R11 1  ; var11 = true
     116 [-]: NAMECALL R4 R4 K28; var5 = var4; var4 = var4[0x986D2AB8]
     117 [-]: CALL R4 8 1  ; var4(var5, var6, var7, var8, var9, var10, var11)
L 8: 118 [-]: GETUPVAL R3 0; var3 = upvalues[0]
     119 [-]: NAMECALL R4 R2 K4; var5 = var2; var4 = var2[0xA5D5C8F6]
     120 [-]: CALL R4 2 2  ; var4 = var4(var5)
     121 [-]: SETTABLEKS R4 R3 K29; var4["mColorCorrection"] = var3
     122 [-]: RETURN R0 0  ; 


; Name:            
; Defined at line: 237
; #Upvalues:       6
; #Parameters:     4
; Is_vararg:       0
; Max Stack Size:  14

       0 [-]: FASTCALL1 64 R1 L0; 
       1 [-]: MOVE R5 R1   ; var5 = var1
       2 [-]: GETIMPORT R4 1; var4 = 0x7B998233
       3 [-]: CALL R4 2 2  ; var4 = var4(var5)
L 0:   4 [-]: JUMPIF R4 L9 ; goto L9 if var4
       5 [-]: GETIMPORT R4 3; var4 = 0x60130201
       6 [-]: MOVE R5 R1   ; var5 = var1
       7 [-]: CALL R4 2 2  ; var4 = var4(var5)
       8 [-]: MOVE R1 R4   ; var1 = var4
       9 [-]: LOADN R4 0   ; var4 = 0
      10 [-]: JUMPIFNOTEQ R0 R4 L3; goto L3 if var0 ~= var1084
      11 [-]: GETUPVAL R4 0; var4 = upvalues[0]
      12 [-]: NAMECALL R5 R1 K4; var6 = var1; var5 = var1[0xA5D5C8F6]
      13 [-]: CALL R5 2 2  ; var5 = var5(var6)
      14 [-]: SETTABLEKS R5 R4 K5; var5["mTextColorA"] = var4
      15 [-]: GETUPVAL R4 1; var4 = upvalues[1]
      16 [-]: GETUPVAL R6 0; var6 = upvalues[0]
      17 [-]: GETTABLEKS R5 R6 K5; var5 = var6["mTextColorA"]
      18 [-]: CALL R4 2 2  ; var4 = var4(var5)
      19 [-]: GETUPVAL R5 1; var5 = upvalues[1]
      20 [-]: GETUPVAL R7 0; var7 = upvalues[0]
      21 [-]: GETTABLEKS R6 R7 K6; var6 = var7["mTextColorB"]
      22 [-]: CALL R5 2 2  ; var5 = var5(var6)
      23 [-]: GETUPVAL R6 2; var6 = upvalues[2]
      24 [-]: MOVE R7 R4   ; var7 = var4
      25 [-]: CALL R6 2 2  ; var6 = var6(var7)
      26 [-]: MOVE R4 R6   ; var4 = var6
      27 [-]: GETUPVAL R6 2; var6 = upvalues[2]
      28 [-]: MOVE R7 R5   ; var7 = var5
      29 [-]: CALL R6 2 2  ; var6 = var6(var7)
      30 [-]: MOVE R5 R6   ; var5 = var6
      31 [-]: GETIMPORT R6 9; var6 = _T["TextLightMovie"]
      32 [-]: LOADK R8 K10 ; var8 = "SetVertexColors"
      33 [-]: NEWTABLE R9 0 2; var9 = {}
      34 [-]: FASTCALL1 63 R4 L1; 
      35 [-]: MOVE R11 R4  ; var11 = var4
      36 [-]: GETIMPORT R10 12; var10 = 0x64FB1586
      37 [-]: CALL R10 2 2 ; var10 = var10(var11)
L 1:  38 [-]: FASTCALL1 63 R5 L2; 
      39 [-]: MOVE R12 R5  ; var12 = var5
      40 [-]: GETIMPORT R11 12; var11 = 0x64FB1586
      41 [-]: CALL R11 2 2 ; var11 = var11(var12)
L 2:  42 [-]: SETLIST R9 R10 2 [1]; var9[1] = var10; var9[2] = var11; var9[3] = var12; 
      43 [-]: NAMECALL R6 R6 K13; var7 = var6; var6 = var6[0xF56F3887]
      44 [-]: CALL R6 4 1  ; var6(var7, var8, var9)
      45 [-]: RETURN R0 0  ; 
L 3:  46 [-]: LOADN R4 1   ; var4 = 1
      47 [-]: JUMPIFNOTEQ R0 R4 L6; goto L6 if var0 ~= var1084
      48 [-]: GETUPVAL R4 0; var4 = upvalues[0]
      49 [-]: NAMECALL R5 R1 K4; var6 = var1; var5 = var1[0xA5D5C8F6]
      50 [-]: CALL R5 2 2  ; var5 = var5(var6)
      51 [-]: SETTABLEKS R5 R4 K6; var5["mTextColorB"] = var4
      52 [-]: GETUPVAL R4 1; var4 = upvalues[1]
      53 [-]: GETUPVAL R6 0; var6 = upvalues[0]
      54 [-]: GETTABLEKS R5 R6 K5; var5 = var6["mTextColorA"]
      55 [-]: CALL R4 2 2  ; var4 = var4(var5)
      56 [-]: GETUPVAL R5 1; var5 = upvalues[1]
      57 [-]: GETUPVAL R7 0; var7 = upvalues[0]
      58 [-]: GETTABLEKS R6 R7 K6; var6 = var7["mTextColorB"]
      59 [-]: CALL R5 2 2  ; var5 = var5(var6)
      60 [-]: GETUPVAL R6 2; var6 = upvalues[2]
      61 [-]: MOVE R7 R4   ; var7 = var4
      62 [-]: CALL R6 2 2  ; var6 = var6(var7)
      63 [-]: MOVE R4 R6   ; var4 = var6
      64 [-]: GETUPVAL R6 2; var6 = upvalues[2]
      65 [-]: MOVE R7 R5   ; var7 = var5
      66 [-]: CALL R6 2 2  ; var6 = var6(var7)
      67 [-]: MOVE R5 R6   ; var5 = var6
      68 [-]: GETIMPORT R6 9; var6 = _T["TextLightMovie"]
      69 [-]: LOADK R8 K10 ; var8 = "SetVertexColors"
      70 [-]: NEWTABLE R9 0 2; var9 = {}
      71 [-]: FASTCALL1 63 R4 L4; 
      72 [-]: MOVE R11 R4  ; var11 = var4
      73 [-]: GETIMPORT R10 12; var10 = 0x64FB1586
      74 [-]: CALL R10 2 2 ; var10 = var10(var11)
L 4:  75 [-]: FASTCALL1 63 R5 L5; 
      76 [-]: MOVE R12 R5  ; var12 = var5
      77 [-]: GETIMPORT R11 12; var11 = 0x64FB1586
      78 [-]: CALL R11 2 2 ; var11 = var11(var12)
L 5:  79 [-]: SETLIST R9 R10 2 [1]; var9[1] = var10; var9[2] = var11; var9[3] = var12; 
      80 [-]: NAMECALL R6 R6 K13; var7 = var6; var6 = var6[0xF56F3887]
      81 [-]: CALL R6 4 1  ; var6(var7, var8, var9)
      82 [-]: RETURN R0 0  ; 
L 6:  83 [-]: GETUPVAL R5 3; var5 = upvalues[3]
      84 [-]: FASTCALL1 64 R5 L7; 
      85 [-]: GETIMPORT R4 1; var4 = 0x7B998233
      86 [-]: CALL R4 2 2  ; var4 = var4(var5)
L 7:  87 [-]: JUMPIF R4 L8 ; goto L8 if var4
      88 [-]: GETUPVAL R4 3; var4 = upvalues[3]
      89 [-]: MOVE R6 R1   ; var6 = var1
      90 [-]: NAMECALL R4 R4 K14; var5 = var4; var4 = var4[0xA3927FE9]
      91 [-]: CALL R4 3 1  ; var4(var5, var6)
      92 [-]: GETUPVAL R5 4; var5 = upvalues[4]
      93 [-]: GETTABLEKS R4 R5 K15; var4 = var5[0x8BCD12B6]
      94 [-]: NAMECALL R5 R1 K4; var6 = var1; var5 = var1[0xA5D5C8F6]
      95 [-]: CALL R5 2 0  ; var5, ... = var5(var6)
      96 [-]: CALL R4 0 2  ; var4 = var4(var5, ...)
      97 [-]: GETIMPORT R5 17; var5 = _T["LightDeco"]
      98 [-]: GETIMPORT R7 19; var7 = 0x0469F296
      99 [-]: LOADK R8 K20 ; var8 = "EmissiveTintColor"
     100 [-]: CALL R7 2 2  ; var7 = var7(var8)
     101 [-]: GETUPVAL R9 5; var9 = upvalues[5]
     102 [-]: GETTABLEKS R8 R9 K21; var8 = var9[0x021DC4BE]
     103 [-]: LOADN R10 255; var10 = 255
     104 [-]: GETTABLEKS R11 R4 K22; var11 = var4["r"]
     105 [-]: MUL R9 R10 R11; var9 = var10 * var11
     106 [-]: CALL R8 2 2  ; var8 = var8(var9)
     107 [-]: GETUPVAL R10 5; var10 = upvalues[5]
     108 [-]: GETTABLEKS R9 R10 K21; var9 = var10[0x021DC4BE]
     109 [-]: LOADN R11 255; var11 = 255
     110 [-]: GETTABLEKS R12 R4 K23; var12 = var4["g"]
     111 [-]: MUL R10 R11 R12; var10 = var11 * var12
     112 [-]: CALL R9 2 2  ; var9 = var9(var10)
     113 [-]: GETUPVAL R11 5; var11 = upvalues[5]
     114 [-]: GETTABLEKS R10 R11 K21; var10 = var11[0x021DC4BE]
     115 [-]: LOADN R12 255; var12 = 255
     116 [-]: GETTABLEKS R13 R4 K24; var13 = var4["b"]
     117 [-]: MUL R11 R12 R13; var11 = var12 * var13
     118 [-]: CALL R10 2 2 ; var10 = var10(var11)
     119 [-]: LOADN R11 1  ; var11 = 1
     120 [-]: LOADB R12 1  ; var12 = true
     121 [-]: NAMECALL R5 R5 K25; var6 = var5; var5 = var5[0x986D2AB8]
     122 [-]: CALL R5 8 1  ; var5(var6, var7, var8, var9, var10, var11, var12)
L 8: 123 [-]: GETUPVAL R4 0; var4 = upvalues[0]
     124 [-]: NAMECALL R5 R1 K4; var6 = var1; var5 = var1[0xA5D5C8F6]
     125 [-]: CALL R5 2 2  ; var5 = var5(var6)
     126 [-]: SETTABLEKS R5 R4 K26; var5["mColorCorrection"] = var4
L 9: 127 [-]: RETURN R0 0  ; 


; Name:            
; Defined at line: 268
; #Upvalues:       3
; #Parameters:     1
; Is_vararg:       0
; Max Stack Size:  10

       0 [-]: GETUPVAL R1 0; var1 = upvalues[0]
       1 [-]: GETTABLEKS R3 R0 K0; var3 = var0["mLabel"]
       2 [-]: NAMECALL R1 R1 K1; var2 = var1; var1 = var1[0x70596BFE]
       3 [-]: CALL R1 3 2  ; var1 = var1(var2, var3)
       4 [-]: GETUPVAL R3 1; var3 = upvalues[1]
       5 [-]: FASTCALL1 64 R3 L0; 
       6 [-]: GETIMPORT R2 3; var2 = 0x7B998233
       7 [-]: CALL R2 2 2  ; var2 = var2(var3)
L 0:   8 [-]: JUMPIF R2 L1 ; goto L1 if var2
       9 [-]: GETUPVAL R2 1; var2 = upvalues[1]
      10 [-]: MOVE R4 R1   ; var4 = var1
      11 [-]: NAMECALL R2 R2 K4; var3 = var2; var2 = var2[0xFE7C3B0C]
      12 [-]: CALL R2 3 1  ; var2(var3, var4)
L 1:  13 [-]: GETIMPORT R3 7; var3 = _T["LightDeco"]
      14 [-]: FASTCALL1 64 R3 L2; 
      15 [-]: GETIMPORT R2 3; var2 = 0x7B998233
      16 [-]: CALL R2 2 2  ; var2 = var2(var3)
L 2:  17 [-]: JUMPIF R2 L3 ; goto L3 if var2
      18 [-]: GETIMPORT R2 7; var2 = _T["LightDeco"]
      19 [-]: GETIMPORT R4 9; var4 = 0x0469F296
      20 [-]: LOADK R5 K10 ; var5 = "EmissiveMapAtten"
      21 [-]: CALL R4 2 2  ; var4 = var4(var5)
      22 [-]: LOADK R6 K11 ; var6 = 0.25
      23 [-]: LOADN R8 4   ; var8 = 4
      24 [-]: GETTABLEKS R9 R0 K0; var9 = var0["mLabel"]
      25 [-]: MUL R7 R8 R9 ; var7 = var8 * var9
      26 [-]: ADD R5 R6 R7 ; var5 = var6 + var7
      27 [-]: LOADN R6 0   ; var6 = 0
      28 [-]: LOADN R7 0   ; var7 = 0
      29 [-]: LOADN R8 0   ; var8 = 0
      30 [-]: LOADB R9 1   ; var9 = true
      31 [-]: NAMECALL R2 R2 K12; var3 = var2; var2 = var2[0x986D2AB8]
      32 [-]: CALL R2 8 1  ; var2(var3, var4, var5, var6, var7, var8, var9)
L 3:  33 [-]: GETUPVAL R2 2; var2 = upvalues[2]
      34 [-]: GETTABLEKS R3 R0 K0; var3 = var0["mLabel"]
      35 [-]: SETTABLEKS R3 R2 K13; var3["mXOffset"] = var2
      36 [-]: RETURN R0 0  ; 


; Name:            
; Defined at line: 281
; #Upvalues:       0
; #Parameters:     3
; Is_vararg:       0
; Max Stack Size:  15

       0 [-]: FASTCALL1 64 R0 L0; 
       1 [-]: MOVE R4 R0   ; var4 = var0
       2 [-]: GETIMPORT R3 1; var3 = 0x7B998233
       3 [-]: CALL R3 2 2  ; var3 = var3(var4)
L 0:   4 [-]: JUMPIF R3 L5 ; goto L5 if var3
       5 [-]: NAMECALL R3 R0 K2; var4 = var0; var3 = var0[0x2B54251B]
       6 [-]: CALL R3 2 2  ; var3 = var3(var4)
       7 [-]: NAMECALL R4 R3 K3; var5 = var3; var4 = var3[0xED4E0128]
       8 [-]: CALL R4 2 2  ; var4 = var4(var5)
       9 [-]: FASTCALL1 64 R3 L1; 
      10 [-]: MOVE R6 R3   ; var6 = var3
      11 [-]: GETIMPORT R5 1; var5 = 0x7B998233
      12 [-]: CALL R5 2 2  ; var5 = var5(var6)
L 1:  13 [-]: JUMPIF R5 L4 ; goto L4 if var5
      14 [-]: GETIMPORT R6 6; var6 = _T["UserDecoText"]
      15 [-]: FASTCALL1 64 R6 L2; 
      16 [-]: GETIMPORT R5 1; var5 = 0x7B998233
      17 [-]: CALL R5 2 2  ; var5 = var5(var6)
L 2:  18 [-]: JUMPIF R5 L4 ; goto L4 if var5
      19 [-]: GETIMPORT R7 6; var7 = _T["UserDecoText"]
      20 [-]: GETTABLE R6 R7 R4; var6 = var7[var4]
      21 [-]: FASTCALL1 64 R6 L3; 
      22 [-]: GETIMPORT R5 1; var5 = 0x7B998233
      23 [-]: CALL R5 2 2  ; var5 = var5(var6)
L 3:  24 [-]: JUMPIF R5 L4 ; goto L4 if var5
      25 [-]: GETIMPORT R6 6; var6 = _T["UserDecoText"]
      26 [-]: GETTABLE R5 R6 R4; var5 = var6[var4]
      27 [-]: GETIMPORT R6 8; var6 = 0xA421AF95
      28 [-]: GETTABLEKS R9 R5 K9; var9 = var5["pos"]
      29 [-]: GETTABLEKS R8 R9 K10; var8 = var9["x"]
      30 [-]: GETTABLEKS R11 R5 K11; var11 = var5["dir"]
      31 [-]: GETTABLEKS R10 R11 K10; var10 = var11["x"]
      32 [-]: MUL R9 R10 R1; var9 = var10 * var1
      33 [-]: ADD R7 R8 R9 ; var7 = var8 + var9
      34 [-]: GETTABLEKS R10 R5 K9; var10 = var5["pos"]
      35 [-]: GETTABLEKS R9 R10 K12; var9 = var10["y"]
      36 [-]: GETTABLEKS R12 R5 K11; var12 = var5["dir"]
      37 [-]: GETTABLEKS R11 R12 K12; var11 = var12["y"]
      38 [-]: MUL R10 R11 R1; var10 = var11 * var1
      39 [-]: ADD R8 R9 R10; var8 = var9 + var10
      40 [-]: GETTABLEKS R11 R5 K9; var11 = var5["pos"]
      41 [-]: GETTABLEKS R10 R11 K13; var10 = var11["z"]
      42 [-]: GETTABLEKS R13 R5 K11; var13 = var5["dir"]
      43 [-]: GETTABLEKS R12 R13 K13; var12 = var13["z"]
      44 [-]: MUL R11 R12 R1; var11 = var12 * var1
      45 [-]: ADD R9 R10 R11; var9 = var10 + var11
      46 [-]: CALL R6 4 2  ; var6 = var6(var7, var8, var9)
      47 [-]: MOVE R9 R6   ; var9 = var6
      48 [-]: GETIMPORT R10 15; var10 = 0x00046924
      49 [-]: GETTABLEKS R12 R5 K16; var12 = var5["rot"]
      50 [-]: GETTABLEKS R11 R12 K17; var11 = var12["heading"]
      51 [-]: GETTABLEKS R14 R5 K16; var14 = var5["rot"]
      52 [-]: GETTABLEKS R13 R14 K18; var13 = var14["pitch"]
      53 [-]: ADD R12 R13 R2; var12 = var13 + var2
      54 [-]: GETTABLEKS R14 R5 K16; var14 = var5["rot"]
      55 [-]: GETTABLEKS R13 R14 K19; var13 = var14["bank"]
      56 [-]: CALL R10 4 0 ; var10, ... = var10(var11, var12, var13)
      57 [-]: NAMECALL R7 R0 K20; var8 = var0; var7 = var0[0xE28AA928]
      58 [-]: CALL R7 0 1  ; var7(var8, ...)
      59 [-]: RETURN R0 0  ; 
L 4:  60 [-]: GETIMPORT R7 8; var7 = 0xA421AF95
      61 [-]: LOADN R8 0   ; var8 = 0
      62 [-]: MOVE R9 R1   ; var9 = var1
      63 [-]: LOADN R10 0  ; var10 = 0
      64 [-]: CALL R7 4 2  ; var7 = var7(var8, var9, var10)
      65 [-]: GETIMPORT R8 15; var8 = 0x00046924
      66 [-]: LOADN R9 0   ; var9 = 0
      67 [-]: MOVE R10 R2  ; var10 = var2
      68 [-]: LOADN R11 0  ; var11 = 0
      69 [-]: CALL R8 4 0  ; var8, ... = var8(var9, var10, var11)
      70 [-]: NAMECALL R5 R0 K20; var6 = var0; var5 = var0[0xE28AA928]
      71 [-]: CALL R5 0 1  ; var5(var6, ...)
L 5:  72 [-]: RETURN R0 0  ; 


; Name:            
; Defined at line: 295
; #Upvalues:       4
; #Parameters:     1
; Is_vararg:       0
; Max Stack Size:  9

       0 [-]: GETUPVAL R1 0; var1 = upvalues[0]
       1 [-]: GETTABLEKS R3 R0 K0; var3 = var0["mLabel"]
       2 [-]: NAMECALL R1 R1 K1; var2 = var1; var1 = var1[0x3B93153D]
       3 [-]: CALL R1 3 2  ; var1 = var1(var2, var3)
       4 [-]: GETTABLEKS R2 R0 K0; var2 = var0["mLabel"]
       5 [-]: GETUPVAL R4 1; var4 = upvalues[1]
       6 [-]: FASTCALL1 64 R4 L0; 
       7 [-]: GETIMPORT R3 3; var3 = 0x7B998233
       8 [-]: CALL R3 2 2  ; var3 = var3(var4)
L 0:   9 [-]: JUMPIF R3 L1 ; goto L1 if var3
      10 [-]: GETUPVAL R3 1; var3 = upvalues[1]
      11 [-]: MOVE R5 R2   ; var5 = var2
      12 [-]: NAMECALL R3 R3 K4; var4 = var3; var3 = var3[0xCE539692]
      13 [-]: CALL R3 3 1  ; var3(var4, var5)
L 1:  14 [-]: GETIMPORT R4 7; var4 = _T["TextLightMovie"]
      15 [-]: FASTCALL1 64 R4 L2; 
      16 [-]: GETIMPORT R3 3; var3 = 0x7B998233
      17 [-]: CALL R3 2 2  ; var3 = var3(var4)
L 2:  18 [-]: JUMPIF R3 L3 ; goto L3 if var3
      19 [-]: GETIMPORT R3 7; var3 = _T["TextLightMovie"]
      20 [-]: NAMECALL R3 R3 K8; var4 = var3; var3 = var3[0xA1653871]
      21 [-]: CALL R3 2 2  ; var3 = var3(var4)
      22 [-]: GETUPVAL R4 2; var4 = upvalues[2]
      23 [-]: MOVE R5 R3   ; var5 = var3
      24 [-]: MOVE R6 R2   ; var6 = var2
      25 [-]: GETUPVAL R8 3; var8 = upvalues[3]
      26 [-]: GETTABLEKS R7 R8 K9; var7 = var8["mTextOrientation"]
      27 [-]: CALL R4 4 1  ; var4(var5, var6, var7)
L 3:  28 [-]: GETUPVAL R3 3; var3 = upvalues[3]
      29 [-]: SETTABLEKS R1 R3 K10; var1["mYOffset"] = var3
      30 [-]: RETURN R0 0  ; 


; Name:            
; Defined at line: 310
; #Upvalues:       1
; #Parameters:     1
; Is_vararg:       0
; Max Stack Size:  6

       0 [-]: GETTABLEKS R1 R0 K0; var1 = var0["mLabel"]
       1 [-]: GETIMPORT R2 3; var2 = _T["TextLightMovie"]
       2 [-]: NAMECALL R2 R2 K4; var3 = var2; var2 = var2[0xA1653871]
       3 [-]: CALL R2 2 2  ; var2 = var2(var3)
       4 [-]: FASTCALL1 64 R2 L0; 
       5 [-]: MOVE R4 R2   ; var4 = var2
       6 [-]: GETIMPORT R3 6; var3 = 0x7B998233
       7 [-]: CALL R3 2 2  ; var3 = var3(var4)
L 0:   8 [-]: JUMPIF R3 L1 ; goto L1 if var3
       9 [-]: MOVE R5 R1   ; var5 = var1
      10 [-]: NAMECALL R3 R2 K7; var4 = var2; var3 = var2[0x2D9BA74F]
      11 [-]: CALL R3 3 1  ; var3(var4, var5)
L 1:  12 [-]: GETUPVAL R3 0; var3 = upvalues[0]
      13 [-]: SETTABLEKS R1 R3 K8; var1["mTextScale"] = var3
      14 [-]: RETURN R0 0  ; 


; Name:            
; Defined at line: 320
; #Upvalues:       3
; #Parameters:     1
; Is_vararg:       0
; Max Stack Size:  9

       0 [-]: GETTABLEKS R1 R0 K0; var1 = var0["mLabel"]
       1 [-]: GETIMPORT R2 3; var2 = _T["TextLightMovie"]
       2 [-]: NAMECALL R2 R2 K4; var3 = var2; var2 = var2[0xA1653871]
       3 [-]: CALL R2 2 2  ; var2 = var2(var3)
       4 [-]: FASTCALL1 64 R2 L0; 
       5 [-]: MOVE R4 R2   ; var4 = var2
       6 [-]: GETIMPORT R3 6; var3 = 0x7B998233
       7 [-]: CALL R3 2 2  ; var3 = var3(var4)
L 0:   8 [-]: JUMPIF R3 L1 ; goto L1 if var3
       9 [-]: GETUPVAL R3 0; var3 = upvalues[0]
      10 [-]: MOVE R4 R2   ; var4 = var2
      11 [-]: GETUPVAL R5 1; var5 = upvalues[1]
      12 [-]: GETUPVAL R8 2; var8 = upvalues[2]
      13 [-]: GETTABLEKS R7 R8 K7; var7 = var8["mYOffset"]
      14 [-]: NAMECALL R5 R5 K8; var6 = var5; var5 = var5[0x70596BFE]
      15 [-]: CALL R5 3 2  ; var5 = var5(var6, var7)
      16 [-]: MOVE R6 R1   ; var6 = var1
      17 [-]: CALL R3 4 1  ; var3(var4, var5, var6)
L 1:  18 [-]: GETUPVAL R3 2; var3 = upvalues[2]
      19 [-]: SETTABLEKS R1 R3 K9; var1["mTextOrientation"] = var3
      20 [-]: RETURN R0 0  ; 


; Name:            
; Defined at line: 330
; #Upvalues:       2
; #Parameters:     1
; Is_vararg:       0
; Max Stack Size:  11

       0 [-]: GETIMPORT R1 1; var1 = 0x09423272
       1 [-]: MOVE R2 R0   ; var2 = var0
       2 [-]: LOADN R3 1   ; var3 = 1
       3 [-]: CALL R1 3 2  ; var1 = var1(var2, var3)
       4 [-]: GETIMPORT R2 3; var2 = 0x09C87793
       5 [-]: MOVE R3 R1   ; var3 = var1
       6 [-]: LOADNIL R4   ; var4 = nil
       7 [-]: CALL R2 3 2  ; var2 = var2(var3, var4)
       8 [-]: LOADN R3 0   ; var3 = 0
       9 [-]: JUMPIFNOTLT R3 R2 L0; goto L0 if var3 >= var1084
      10 [-]: GETUPVAL R4 0; var4 = upvalues[0]
      11 [-]: GETTABLEKS R3 R4 K4; var3 = var4[0xA53F5E12]
      12 [-]: GETIMPORT R7 6; var7 = 0xAE91E43B
      13 [-]: LOADK R9 K7  ; var9 = "/Lotus/Language/Menu/SocialOverlay_InvalidCharacter"
      14 [-]: LOADB R10 0  ; var10 = false
      15 [-]: NAMECALL R7 R7 K8; var8 = var7; var7 = var7[0x42B04007]
      16 [-]: CALL R7 4 2  ; var7 = var7(var8, var9, var10)
      17 [-]: MOVE R5 R7   ; var5 = var7
      18 [-]: GETIMPORT R6 10; var6 = 0x68B0AFB4
      19 [-]: MOVE R7 R1   ; var7 = var1
      20 [-]: MOVE R8 R2   ; var8 = var2
      21 [-]: MOVE R9 R2   ; var9 = var2
      22 [-]: CALL R6 4 2  ; var6 = var6(var7, var8, var9)
      23 [-]: CONCAT R4 R5 R6; var4 = var5 .. var6
      24 [-]: CALL R3 2 1  ; var3(var4)
      25 [-]: RETURN R0 0  ; 
L 0:  26 [-]: JUMPIFEQ R1 R0 L1; goto L1 if var1 == var1084
      27 [-]: GETUPVAL R4 0; var4 = upvalues[0]
      28 [-]: GETTABLEKS R3 R4 K4; var3 = var4[0xA53F5E12]
      29 [-]: LOADK R4 K11 ; var4 = "/Lotus/Language/SystemMessages/LightDeco_ProfanityError"
      30 [-]: CALL R3 2 1  ; var3(var4)
      31 [-]: RETURN R0 0  ; 
L 1:  32 [-]: GETUPVAL R3 1; var3 = upvalues[1]
      33 [-]: SETTABLEKS R0 R3 K12; var0["mText"] = var3
      34 [-]: LOADK R5 K13 ; var5 = ","
      35 [-]: LOADK R6 K14 ; var6 = "<COMMA>"
      36 [-]: NAMECALL R3 R0 K15; var4 = var0; var3 = var0[0x66EDF04F]
      37 [-]: CALL R3 4 2  ; var3 = var3(var4, var5, var6)
      38 [-]: MOVE R0 R3   ; var0 = var3
      39 [-]: GETIMPORT R3 18; var3 = _T["TextLightMovie"]
      40 [-]: LOADK R5 K19 ; var5 = "SetMessage"
      41 [-]: MOVE R6 R0   ; var6 = var0
      42 [-]: NAMECALL R3 R3 K20; var4 = var3; var3 = var3[0xE4162EED]
      43 [-]: CALL R3 4 1  ; var3(var4, var5, var6)
      44 [-]: RETURN R0 0  ; 


; Name:            
; Defined at line: 351
; #Upvalues:       1
; #Parameters:     3
; Is_vararg:       0
; Max Stack Size:  5

       0 [-]: FASTCALL1 62 R2 L0; 
       1 [-]: MOVE R4 R2   ; var4 = var2
       2 [-]: GETIMPORT R3 1; var3 = 0x03F57322
       3 [-]: CALL R3 2 2  ; var3 = var3(var4)
L 0:   4 [-]: LOADN R4 4   ; var4 = 4
       5 [-]: JUMPIFNOTEQ R3 R4 L1; goto L1 if var3 ~= var828
       6 [-]: GETUPVAL R3 0; var3 = upvalues[0]
       7 [-]: MOVE R4 R0   ; var4 = var0
       8 [-]: CALL R3 2 1  ; var3(var4)
L 1:   9 [-]: RETURN R0 0  ; 


; Name:            
; Defined at line: 357
; #Upvalues:       1
; #Parameters:     2
; Is_vararg:       0
; Max Stack Size:  4

       0 [-]: JUMPIF R0 L0 ; goto L0 if var0
       1 [-]: GETUPVAL R2 0; var2 = upvalues[0]
       2 [-]: MOVE R3 R1   ; var3 = var1
       3 [-]: CALL R2 2 1  ; var2(var3)
L 0:   4 [-]: RETURN R0 0  ; 


; Name:            
; Defined at line: 363
; #Upvalues:       2
; #Parameters:     0
; Is_vararg:       0
; Max Stack Size:  7

       0 [-]: GETUPVAL R1 0; var1 = upvalues[0]
       1 [-]: GETTABLEKS R0 R1 K0; var0 = var1[0xEF3E3165]
       2 [-]: GETIMPORT R1 2; var1 = 0xAE91E43B
       3 [-]: LOADK R2 K3  ; var2 = "/Lotus/Language/Menu/Photobooth_SetText"
       4 [-]: GETUPVAL R4 1; var4 = upvalues[1]
       5 [-]: GETTABLEKS R3 R4 K4; var3 = var4["mText"]
       6 [-]: LOADN R4 30  ; var4 = 30
       7 [-]: LOADK R5 K5  ; var5 = "OnTextSet"
       8 [-]: LOADK R6 K6  ; var6 = "OSKOnTextSet"
       9 [-]: CALL R0 7 1  ; var0(var1, var2, var3, var4, var5, var6)
      10 [-]: RETURN R0 0  ; 


; Name:            
; Defined at line: 367
; #Upvalues:       5
; #Parameters:     0
; Is_vararg:       0
; Max Stack Size:  4

       0 [-]: GETIMPORT R0 1; var0 = 0x2D0FAD09
       1 [-]: LOADK R1 K2  ; var1 = "Lotus.Interface.Components.ThemedCustomizationList"
       2 [-]: CALL R0 2 2  ; var0 = var0(var1)
       3 [-]: GETTABLEKS R1 R0 K3; var1 = var0[0xAE6791BA]
       4 [-]: GETIMPORT R2 5; var2 = 0xAE91E43B
       5 [-]: LOADK R3 K6  ; var3 = "AreaPicker"
       6 [-]: CALL R1 3 2  ; var1 = var1(var2, var3)
       7 [-]: SETUPVAL R1 0; upvalues[1] = var0
       8 [-]: GETUPVAL R1 0; var1 = upvalues[0]
       9 [-]: GETUPVAL R2 1; var2 = upvalues[1]
      10 [-]: SETTABLEKS R2 R1 K7; var2["SetColorCallback"] = var1
      11 [-]: GETUPVAL R1 0; var1 = upvalues[0]
      12 [-]: LOADB R2 1   ; var2 = true
      13 [-]: SETTABLEKS R2 R1 K8; var2["mShowCosmeticButtons"] = var1
      14 [-]: GETUPVAL R2 0; var2 = upvalues[0]
      15 [-]: GETTABLEKS R1 R2 K9; var1 = var2["CustomizationList"]
      16 [-]: GETUPVAL R2 2; var2 = upvalues[2]
      17 [-]: SETTABLEKS R2 R1 K10; var2["mApplyColorCallback"] = var1
      18 [-]: GETUPVAL R2 0; var2 = upvalues[0]
      19 [-]: GETTABLEKS R1 R2 K9; var1 = var2["CustomizationList"]
      20 [-]: GETUPVAL R2 3; var2 = upvalues[3]
      21 [-]: SETTABLEKS R2 R1 K11; var2["mActiveColors"] = var1
      22 [-]: GETUPVAL R2 0; var2 = upvalues[0]
      23 [-]: GETTABLEKS R1 R2 K9; var1 = var2["CustomizationList"]
      24 [-]: LOADN R2 42  ; var2 = 42
      25 [-]: SETTABLEKS R2 R1 K12; var2["mElementHeight"] = var1
      26 [-]: GETUPVAL R2 0; var2 = upvalues[0]
      27 [-]: GETTABLEKS R1 R2 K9; var1 = var2["CustomizationList"]
      28 [-]: LOADN R2 -35 ; var2 = -35
      29 [-]: SETTABLEKS R2 R1 K13; var2["mInitialY"] = var1
      30 [-]: GETUPVAL R2 0; var2 = upvalues[0]
      31 [-]: GETTABLEKS R1 R2 K9; var1 = var2["CustomizationList"]
      32 [-]: LOADN R2 45  ; var2 = 45
      33 [-]: SETTABLEKS R2 R1 K14; var2["mForcedVerticalSeparation"] = var1
      34 [-]: GETUPVAL R2 0; var2 = upvalues[0]
      35 [-]: GETTABLEKS R1 R2 K9; var1 = var2["CustomizationList"]
      36 [-]: LOADK R2 K15 ; var2 = "/Lotus/Language/Menu/Cosmetics_None"
      37 [-]: SETTABLEKS R2 R1 K16; var2["mNoneTextOverride"] = var1
      38 [-]: GETUPVAL R1 0; var1 = upvalues[0]
      39 [-]: DUPCLOSURE R2 K17; 
      40 [-]: CAPTURE UPVAL U4; 
      41 [-]: SETTABLEKS R2 R1 K18; var2["StateChangedCallBack"] = var1
      42 [-]: GETUPVAL R2 0; var2 = upvalues[0]
      43 [-]: GETTABLEKS R1 R2 K19; var1 = var2["ItemSelectionGrid"]
      44 [-]: NAMECALL R1 R1 K20; var2 = var1; var1 = var1[0xA0ED0E4C]
      45 [-]: CALL R1 2 1  ; var1(var2)
      46 [-]: RETURN R0 0  ; 


; Name:            
; Defined at line: 385
; #Upvalues:       11
; #Parameters:     0
; Is_vararg:       0
; Max Stack Size:  15

       0 [-]: GETUPVAL R1 0; var1 = upvalues[0]
       1 [-]: GETTABLEKS R0 R1 K0; var0 = var1["CustomizationList"]
       2 [-]: LOADB R2 1   ; var2 = true
       3 [-]: LOADB R3 1   ; var3 = true
       4 [-]: NAMECALL R0 R0 K1; var1 = var0; var0 = var0[0x7C09C373]
       5 [-]: CALL R0 4 1  ; var0(var1, var2, var3)
       6 [-]: NEWTABLE R0 0 10; var0 = {}
       7 [-]: DUPTABLE R1 5; 
       8 [-]: GETUPVAL R4 1; var4 = upvalues[1]
       9 [-]: GETTABLEKS R3 R4 K6; var3 = var4["Types"]
      10 [-]: GETTABLEKS R2 R3 K7; var2 = var3["TITLE"]
      11 [-]: SETTABLEKS R2 R1 K2; var2["Type"] = var1
      12 [-]: LOADK R2 K8  ; var2 = "/Lotus/Language/SystemMessages/Light"
      13 [-]: SETTABLEKS R2 R1 K3; var2["NameTag"] = var1
      14 [-]: LOADB R2 1   ; var2 = true
      15 [-]: SETTABLEKS R2 R1 K4; var2["UseBookends"] = var1
      16 [-]: DUPTABLE R2 11; 
      17 [-]: GETUPVAL R5 1; var5 = upvalues[1]
      18 [-]: GETTABLEKS R4 R5 K6; var4 = var5["Types"]
      19 [-]: GETTABLEKS R3 R4 K12; var3 = var4["COLOR"]
      20 [-]: SETTABLEKS R3 R2 K2; var3["Type"] = var2
      21 [-]: LOADK R3 K13 ; var3 = "/Lotus/Language/Menu/Color"
      22 [-]: SETTABLEKS R3 R2 K3; var3["NameTag"] = var2
      23 [-]: NEWTABLE R3 0 1; var3 = {}
      24 [-]: LOADN R4 4   ; var4 = 4
      25 [-]: SETLIST R3 R4 1 [1]; var3[1] = var4; var3[2] = var5; 
      26 [-]: SETTABLEKS R3 R2 K9; var3["mColorRegions"] = var2
      27 [-]: GETUPVAL R3 2; var3 = upvalues[2]
      28 [-]: NAMECALL R3 R3 K14; var4 = var3; var3 = var3[0x6199AEC6]
      29 [-]: CALL R3 2 2  ; var3 = var3(var4)
      30 [-]: NAMECALL R3 R3 K15; var4 = var3; var3 = var3[0xA5D5C8F6]
      31 [-]: CALL R3 2 2  ; var3 = var3(var4)
      32 [-]: SETTABLEKS R3 R2 K10; var3["mDefaultColor"] = var2
      33 [-]: DUPTABLE R3 23; 
      34 [-]: GETUPVAL R6 1; var6 = upvalues[1]
      35 [-]: GETTABLEKS R5 R6 K6; var5 = var6["Types"]
      36 [-]: GETTABLEKS R4 R5 K24; var4 = var5["VALUE_SELECTOR"]
      37 [-]: SETTABLEKS R4 R3 K2; var4["Type"] = var3
      38 [-]: LOADK R4 K25 ; var4 = "/Lotus/Language/SystemMessages/Intensity"
      39 [-]: SETTABLEKS R4 R3 K3; var4["NameTag"] = var3
      40 [-]: GETUPVAL R5 3; var5 = upvalues[3]
      41 [-]: GETTABLEKS R4 R5 K26; var4 = var5["mXOffset"]
      42 [-]: SETTABLEKS R4 R3 K16; var4["mInitialValue"] = var3
      43 [-]: LOADN R4 0   ; var4 = 0
      44 [-]: SETTABLEKS R4 R3 K17; var4["mMinValue"] = var3
      45 [-]: LOADN R4 1   ; var4 = 1
      46 [-]: SETTABLEKS R4 R3 K18; var4["mMaxValue"] = var3
      47 [-]: LOADN R4 2   ; var4 = 2
      48 [-]: SETTABLEKS R4 R3 K19; var4["mDecimals"] = var3
      49 [-]: LOADK R4 K27 ; var4 = 0.10000000149011612
      50 [-]: SETTABLEKS R4 R3 K20; var4["mSteps"] = var3
      51 [-]: LOADK R4 K28 ; var4 = 0.5
      52 [-]: SETTABLEKS R4 R3 K21; var4["mDefaultValue"] = var3
      53 [-]: GETUPVAL R4 4; var4 = upvalues[4]
      54 [-]: SETTABLEKS R4 R3 K22; var4["mValueChangedCallback"] = var3
      55 [-]: DUPTABLE R4 23; 
      56 [-]: GETUPVAL R7 1; var7 = upvalues[1]
      57 [-]: GETTABLEKS R6 R7 K6; var6 = var7["Types"]
      58 [-]: GETTABLEKS R5 R6 K24; var5 = var6["VALUE_SELECTOR"]
      59 [-]: SETTABLEKS R5 R4 K2; var5["Type"] = var4
      60 [-]: LOADK R5 K29 ; var5 = "/Lotus/Language/Game/ABILITY_LENGTH_NO_UNIT"
      61 [-]: SETTABLEKS R5 R4 K3; var5["NameTag"] = var4
      62 [-]: GETUPVAL R5 5; var5 = upvalues[5]
      63 [-]: GETUPVAL R8 3; var8 = upvalues[3]
      64 [-]: GETTABLEKS R7 R8 K30; var7 = var8["mYOffset"]
      65 [-]: NAMECALL R5 R5 K31; var6 = var5; var5 = var5[0x70596BFE]
      66 [-]: CALL R5 3 2  ; var5 = var5(var6, var7)
      67 [-]: SETTABLEKS R5 R4 K16; var5["mInitialValue"] = var4
      68 [-]: GETUPVAL R6 5; var6 = upvalues[5]
      69 [-]: GETTABLEKS R5 R6 K32; var5 = var6["minValue"]
      70 [-]: SETTABLEKS R5 R4 K17; var5["mMinValue"] = var4
      71 [-]: GETUPVAL R6 5; var6 = upvalues[5]
      72 [-]: GETTABLEKS R5 R6 K33; var5 = var6["maxValue"]
      73 [-]: SETTABLEKS R5 R4 K18; var5["mMaxValue"] = var4
      74 [-]: LOADN R5 2   ; var5 = 2
      75 [-]: SETTABLEKS R5 R4 K19; var5["mDecimals"] = var4
      76 [-]: LOADK R5 K27 ; var5 = 0.10000000149011612
      77 [-]: SETTABLEKS R5 R4 K20; var5["mSteps"] = var4
      78 [-]: LOADK R5 K34 ; var5 = 1.3999999761581421
      79 [-]: SETTABLEKS R5 R4 K21; var5["mDefaultValue"] = var4
      80 [-]: GETUPVAL R5 6; var5 = upvalues[6]
      81 [-]: SETTABLEKS R5 R4 K22; var5["mValueChangedCallback"] = var4
      82 [-]: DUPTABLE R5 5; 
      83 [-]: GETUPVAL R8 1; var8 = upvalues[1]
      84 [-]: GETTABLEKS R7 R8 K6; var7 = var8["Types"]
      85 [-]: GETTABLEKS R6 R7 K7; var6 = var7["TITLE"]
      86 [-]: SETTABLEKS R6 R5 K2; var6["Type"] = var5
      87 [-]: LOADK R6 K35 ; var6 = "/Lotus/Language/Menu/Photobooth_TextTitle"
      88 [-]: SETTABLEKS R6 R5 K3; var6["NameTag"] = var5
      89 [-]: LOADB R6 1   ; var6 = true
      90 [-]: SETTABLEKS R6 R5 K4; var6["UseBookends"] = var5
      91 [-]: DUPTABLE R6 38; 
      92 [-]: GETUPVAL R9 1; var9 = upvalues[1]
      93 [-]: GETTABLEKS R8 R9 K6; var8 = var9["Types"]
      94 [-]: GETTABLEKS R7 R8 K39; var7 = var8["BUTTON"]
      95 [-]: SETTABLEKS R7 R6 K2; var7["Type"] = var6
      96 [-]: LOADK R7 K40 ; var7 = "/Lotus/Language/SystemMessages/EditText"
      97 [-]: SETTABLEKS R7 R6 K3; var7["NameTag"] = var6
      98 [-]: GETUPVAL R7 7; var7 = upvalues[7]
      99 [-]: SETTABLEKS R7 R6 K36; var7["mOnReleasedCallback"] = var6
     100 [-]: GETIMPORT R8 43; var8 = _T["TextLightMovie"]
     101 [-]: FASTCALL1 64 R8 L0; 
     102 [-]: GETIMPORT R7 45; var7 = 0x7B998233
     103 [-]: CALL R7 2 2  ; var7 = var7(var8)
L 0: 104 [-]: SETTABLEKS R7 R6 K37; var7["HideSetting"] = var6
     105 [-]: DUPTABLE R7 46; 
     106 [-]: GETUPVAL R10 1; var10 = upvalues[1]
     107 [-]: GETTABLEKS R9 R10 K6; var9 = var10["Types"]
     108 [-]: GETTABLEKS R8 R9 K24; var8 = var9["VALUE_SELECTOR"]
     109 [-]: SETTABLEKS R8 R7 K2; var8["Type"] = var7
     110 [-]: LOADK R8 K47 ; var8 = "/Lotus/Language/SystemMessages/Scale"
     111 [-]: SETTABLEKS R8 R7 K3; var8["NameTag"] = var7
     112 [-]: GETUPVAL R9 3; var9 = upvalues[3]
     113 [-]: GETTABLEKS R8 R9 K48; var8 = var9["mTextScale"]
     114 [-]: SETTABLEKS R8 R7 K16; var8["mInitialValue"] = var7
     115 [-]: GETUPVAL R8 8; var8 = upvalues[8]
     116 [-]: SETTABLEKS R8 R7 K22; var8["mValueChangedCallback"] = var7
     117 [-]: LOADN R8 2   ; var8 = 2
     118 [-]: SETTABLEKS R8 R7 K19; var8["mDecimals"] = var7
     119 [-]: LOADK R8 K27 ; var8 = 0.10000000149011612
     120 [-]: SETTABLEKS R8 R7 K20; var8["mSteps"] = var7
     121 [-]: LOADK R8 K49 ; var8 = 0.20000000298023224
     122 [-]: SETTABLEKS R8 R7 K17; var8["mMinValue"] = var7
     123 [-]: LOADN R8 2   ; var8 = 2
     124 [-]: SETTABLEKS R8 R7 K18; var8["mMaxValue"] = var7
     125 [-]: LOADN R8 1   ; var8 = 1
     126 [-]: SETTABLEKS R8 R7 K21; var8["mDefaultValue"] = var7
     127 [-]: GETIMPORT R9 43; var9 = _T["TextLightMovie"]
     128 [-]: FASTCALL1 64 R9 L1; 
     129 [-]: GETIMPORT R8 45; var8 = 0x7B998233
     130 [-]: CALL R8 2 2  ; var8 = var8(var9)
L 1: 131 [-]: SETTABLEKS R8 R7 K37; var8["HideSetting"] = var7
     132 [-]: DUPTABLE R8 50; 
     133 [-]: GETUPVAL R11 1; var11 = upvalues[1]
     134 [-]: GETTABLEKS R10 R11 K6; var10 = var11["Types"]
     135 [-]: GETTABLEKS R9 R10 K12; var9 = var10["COLOR"]
     136 [-]: SETTABLEKS R9 R8 K2; var9["Type"] = var8
     137 [-]: LOADK R9 K51 ; var9 = "/Lotus/Language/Menu/TennoCustomization_MarkingColor1"
     138 [-]: SETTABLEKS R9 R8 K3; var9["NameTag"] = var8
     139 [-]: NEWTABLE R9 0 1; var9 = {}
     140 [-]: LOADN R10 0  ; var10 = 0
     141 [-]: SETLIST R9 R10 1 [1]; var9[1] = var10; var9[2] = var11; 
     142 [-]: SETTABLEKS R9 R8 K9; var9["mColorRegions"] = var8
     143 [-]: GETIMPORT R9 53; var9 = 0x60130201
     144 [-]: LOADN R10 239; var10 = 239
     145 [-]: LOADN R11 239; var11 = 239
     146 [-]: LOADN R12 239; var12 = 239
     147 [-]: LOADN R13 0  ; var13 = 0
     148 [-]: CALL R9 5 2  ; var9 = var9(var10, var11, var12, var13)
     149 [-]: NAMECALL R9 R9 K15; var10 = var9; var9 = var9[0xA5D5C8F6]
     150 [-]: CALL R9 2 2  ; var9 = var9(var10)
     151 [-]: SETTABLEKS R9 R8 K10; var9["mDefaultColor"] = var8
     152 [-]: GETIMPORT R10 43; var10 = _T["TextLightMovie"]
     153 [-]: FASTCALL1 64 R10 L2; 
     154 [-]: GETIMPORT R9 45; var9 = 0x7B998233
     155 [-]: CALL R9 2 2  ; var9 = var9(var10)
L 2: 156 [-]: SETTABLEKS R9 R8 K37; var9["HideSetting"] = var8
     157 [-]: DUPTABLE R9 50; 
     158 [-]: GETUPVAL R12 1; var12 = upvalues[1]
     159 [-]: GETTABLEKS R11 R12 K6; var11 = var12["Types"]
     160 [-]: GETTABLEKS R10 R11 K12; var10 = var11["COLOR"]
     161 [-]: SETTABLEKS R10 R9 K2; var10["Type"] = var9
     162 [-]: LOADK R10 K54; var10 = "/Lotus/Language/Menu/TennoCustomization_MarkingColor2"
     163 [-]: SETTABLEKS R10 R9 K3; var10["NameTag"] = var9
     164 [-]: NEWTABLE R10 0 1; var10 = {}
     165 [-]: LOADN R11 1  ; var11 = 1
     166 [-]: SETLIST R10 R11 1 [1]; var10[1] = var11; var10[2] = var12; 
     167 [-]: SETTABLEKS R10 R9 K9; var10["mColorRegions"] = var9
     168 [-]: GETIMPORT R10 53; var10 = 0x60130201
     169 [-]: LOADN R11 239; var11 = 239
     170 [-]: LOADN R12 239; var12 = 239
     171 [-]: LOADN R13 239; var13 = 239
     172 [-]: LOADN R14 0  ; var14 = 0
     173 [-]: CALL R10 5 2 ; var10 = var10(var11, var12, var13, var14)
     174 [-]: NAMECALL R10 R10 K15; var11 = var10; var10 = var10[0xA5D5C8F6]
     175 [-]: CALL R10 2 2 ; var10 = var10(var11)
     176 [-]: SETTABLEKS R10 R9 K10; var10["mDefaultColor"] = var9
     177 [-]: GETIMPORT R11 43; var11 = _T["TextLightMovie"]
     178 [-]: FASTCALL1 64 R11 L3; 
     179 [-]: GETIMPORT R10 45; var10 = 0x7B998233
     180 [-]: CALL R10 2 2 ; var10 = var10(var11)
L 3: 181 [-]: SETTABLEKS R10 R9 K37; var10["HideSetting"] = var9
     182 [-]: DUPTABLE R10 55; 
     183 [-]: GETUPVAL R13 1; var13 = upvalues[1]
     184 [-]: GETTABLEKS R12 R13 K6; var12 = var13["Types"]
     185 [-]: GETTABLEKS R11 R12 K24; var11 = var12["VALUE_SELECTOR"]
     186 [-]: SETTABLEKS R11 R10 K2; var11["Type"] = var10
     187 [-]: LOADK R11 K56; var11 = "/Lotus/Language/Menu/Cosmetics_Rotation"
     188 [-]: SETTABLEKS R11 R10 K3; var11["NameTag"] = var10
     189 [-]: GETUPVAL R12 3; var12 = upvalues[3]
     190 [-]: GETTABLEKS R11 R12 K57; var11 = var12["mTextOrientation"]
     191 [-]: SETTABLEKS R11 R10 K16; var11["mInitialValue"] = var10
     192 [-]: GETUPVAL R11 9; var11 = upvalues[9]
     193 [-]: SETTABLEKS R11 R10 K22; var11["mValueChangedCallback"] = var10
     194 [-]: LOADN R11 0  ; var11 = 0
     195 [-]: SETTABLEKS R11 R10 K17; var11["mMinValue"] = var10
     196 [-]: LOADN R11 360; var11 = 360
     197 [-]: SETTABLEKS R11 R10 K18; var11["mMaxValue"] = var10
     198 [-]: LOADN R11 0  ; var11 = 0
     199 [-]: SETTABLEKS R11 R10 K21; var11["mDefaultValue"] = var10
     200 [-]: LOADN R11 0  ; var11 = 0
     201 [-]: SETTABLEKS R11 R10 K19; var11["mDecimals"] = var10
     202 [-]: GETIMPORT R12 43; var12 = _T["TextLightMovie"]
     203 [-]: FASTCALL1 64 R12 L4; 
     204 [-]: GETIMPORT R11 45; var11 = 0x7B998233
     205 [-]: CALL R11 2 2 ; var11 = var11(var12)
L 4: 206 [-]: SETTABLEKS R11 R10 K37; var11["HideSetting"] = var10
     207 [-]: SETLIST R0 R1 10 [1]; var0[1] = var1; var0[2] = var2; var0[3] = var3; var0[4] = var4; var0[5] = var5; var0[6] = var6; var0[7] = var7; var0[8] = var8; var0[9] = var9; var0[10] = var10; var0[11] = var11; 
     208 [-]: GETIMPORT R1 59; var1 = 0xC8802016
     209 [-]: MOVE R2 R0   ; var2 = var0
     210 [-]: CALL R1 2 4  ; var1, var2, var3 = var1(var2)
     211 [-]: FORGPREP_INEXT R1 L7; 
L 5: 212 [-]: GETTABLEKS R6 R5 K37; var6 = var5["HideSetting"]
     213 [-]: JUMPIF R6 L7 ; goto L7 if var6
     214 [-]: GETTABLEKS R6 R5 K2; var6 = var5["Type"]
     215 [-]: GETUPVAL R9 1; var9 = upvalues[1]
     216 [-]: GETTABLEKS R8 R9 K6; var8 = var9["Types"]
     217 [-]: GETTABLEKS R7 R8 K24; var7 = var8["VALUE_SELECTOR"]
     218 [-]: JUMPIFNOTEQ R6 R7 L6; goto L6 if var6 ~= var67078
     219 [-]: LOADB R6 1   ; var6 = true
     220 [-]: SETTABLEKS R6 R5 K60; var6["Initialized"] = var5
     221 [-]: LOADB R6 0   ; var6 = false
     222 [-]: SETTABLEKS R6 R5 K61; var6["Pending"] = var5
L 6: 223 [-]: GETUPVAL R7 0; var7 = upvalues[0]
     224 [-]: GETTABLEKS R6 R7 K0; var6 = var7["CustomizationList"]
     225 [-]: MOVE R8 R5   ; var8 = var5
     226 [-]: LOADB R9 1   ; var9 = true
     227 [-]: NAMECALL R6 R6 K62; var7 = var6; var6 = var6[0xBAD4316F]
     228 [-]: CALL R6 4 1  ; var6(var7, var8, var9)
L 7: 229 [-]: FORGLOOP R1 L5 2 [inext]; 
     230 [-]: GETUPVAL R2 0; var2 = upvalues[0]
     231 [-]: GETTABLEKS R1 R2 K0; var1 = var2["CustomizationList"]
     232 [-]: NAMECALL R1 R1 K63; var2 = var1; var1 = var1[0x71E9AC81]
     233 [-]: CALL R1 2 1  ; var1(var2)
     234 [-]: GETIMPORT R1 66; var1 = 0x34291F5C[0x1467D5F4]
     235 [-]: CALL R1 1 2  ; var1 = var1()
     236 [-]: JUMPIFNOT R1 L8; goto L8 if not var1
     237 [-]: GETUPVAL R2 0; var2 = upvalues[0]
     238 [-]: GETTABLEKS R1 R2 K0; var1 = var2["CustomizationList"]
     239 [-]: LOADN R3 1   ; var3 = 1
     240 [-]: NAMECALL R1 R1 K67; var2 = var1; var1 = var1[0x1E63AC7A]
     241 [-]: CALL R1 3 1  ; var1(var2, var3)
L 8: 242 [-]: GETUPVAL R1 10; var1 = upvalues[10]
     243 [-]: CALL R1 1 1  ; var1()
     244 [-]: RETURN R0 0  ; 


; Name:            
; Defined at line: 492
; #Upvalues:       2
; #Parameters:     0
; Is_vararg:       0
; Max Stack Size:  6

       0 [-]: GETIMPORT R0 2; var0 = 0x6C97A788[0xC5329145]
       1 [-]: CALL R0 1 2  ; var0 = var0()
       2 [-]: SETUPVAL R0 0; upvalues[0] = var0
       3 [-]: GETUPVAL R0 0; var0 = upvalues[0]
       4 [-]: LOADN R2 4   ; var2 = 4
       5 [-]: GETIMPORT R3 4; var3 = 0x60130201
       6 [-]: GETUPVAL R5 1; var5 = upvalues[1]
       7 [-]: GETTABLEKS R4 R5 K5; var4 = var5["mColorCorrection"]
       8 [-]: CALL R3 2 0  ; var3, ... = var3(var4)
       9 [-]: NAMECALL R0 R0 K6; var1 = var0; var0 = var0[0xA3927FE9]
      10 [-]: CALL R0 0 1  ; var0(var1, ...)
      11 [-]: GETUPVAL R0 0; var0 = upvalues[0]
      12 [-]: LOADN R2 4   ; var2 = 4
      13 [-]: LOADB R3 1   ; var3 = true
      14 [-]: NAMECALL R0 R0 K7; var1 = var0; var0 = var0[0xFC5D7158]
      15 [-]: CALL R0 4 1  ; var0(var1, var2, var3)
      16 [-]: GETUPVAL R0 0; var0 = upvalues[0]
      17 [-]: LOADN R2 0   ; var2 = 0
      18 [-]: GETIMPORT R3 4; var3 = 0x60130201
      19 [-]: GETUPVAL R5 1; var5 = upvalues[1]
      20 [-]: GETTABLEKS R4 R5 K8; var4 = var5["mTextColorA"]
      21 [-]: CALL R3 2 0  ; var3, ... = var3(var4)
      22 [-]: NAMECALL R0 R0 K6; var1 = var0; var0 = var0[0xA3927FE9]
      23 [-]: CALL R0 0 1  ; var0(var1, ...)
      24 [-]: GETUPVAL R0 0; var0 = upvalues[0]
      25 [-]: LOADN R2 0   ; var2 = 0
      26 [-]: LOADB R3 1   ; var3 = true
      27 [-]: NAMECALL R0 R0 K7; var1 = var0; var0 = var0[0xFC5D7158]
      28 [-]: CALL R0 4 1  ; var0(var1, var2, var3)
      29 [-]: GETUPVAL R0 0; var0 = upvalues[0]
      30 [-]: LOADN R2 1   ; var2 = 1
      31 [-]: GETIMPORT R3 4; var3 = 0x60130201
      32 [-]: GETUPVAL R5 1; var5 = upvalues[1]
      33 [-]: GETTABLEKS R4 R5 K9; var4 = var5["mTextColorB"]
      34 [-]: CALL R3 2 0  ; var3, ... = var3(var4)
      35 [-]: NAMECALL R0 R0 K6; var1 = var0; var0 = var0[0xA3927FE9]
      36 [-]: CALL R0 0 1  ; var0(var1, ...)
      37 [-]: GETUPVAL R0 0; var0 = upvalues[0]
      38 [-]: LOADN R2 1   ; var2 = 1
      39 [-]: LOADB R3 1   ; var3 = true
      40 [-]: NAMECALL R0 R0 K7; var1 = var0; var0 = var0[0xFC5D7158]
      41 [-]: CALL R0 4 1  ; var0(var1, var2, var3)
      42 [-]: RETURN R0 0  ; 


; Name:            
; Defined at line: 505
; #Upvalues:       15
; #Parameters:     0
; Is_vararg:       0
; Max Stack Size:  9

       0 [-]: GETIMPORT R0 1; var0 = 0x9BA7909F
       1 [-]: GETUPVAL R2 0; var2 = upvalues[0]
       2 [-]: NAMECALL R0 R0 K2; var1 = var0; var0 = var0[0xBCFB64AB]
       3 [-]: CALL R0 3 2  ; var0 = var0(var1, var2)
       4 [-]: FASTCALL1 64 R0 L0; 
       5 [-]: MOVE R2 R0   ; var2 = var0
       6 [-]: GETIMPORT R1 4; var1 = 0x7B998233
       7 [-]: CALL R1 2 2  ; var1 = var1(var2)
L 0:   8 [-]: JUMPIF R1 L1 ; goto L1 if var1
       9 [-]: LOADK R3 K5  ; var3 = "Hide"
      10 [-]: LOADK R4 K6  ; var4 = ""
      11 [-]: NAMECALL R1 R0 K7; var2 = var0; var1 = var0[0xE4162EED]
      12 [-]: CALL R1 4 1  ; var1(var2, var3, var4)
L 1:  13 [-]: GETIMPORT R1 10; var1 = _T["ChangeHubVisCounter"]
      14 [-]: JUMPXEQKNIL R1 L2; 
      15 [-]: GETIMPORT R1 10; var1 = _T["ChangeHubVisCounter"]
      16 [-]: LOADN R2 1   ; var2 = 1
      17 [-]: CALL R1 2 1  ; var1(var2)
L 2:  18 [-]: GETIMPORT R2 12; var2 = _T["SetSquadOverlayTitle"]
      19 [-]: FASTCALL1 64 R2 L3; 
      20 [-]: GETIMPORT R1 4; var1 = 0x7B998233
      21 [-]: CALL R1 2 2  ; var1 = var1(var2)
L 3:  22 [-]: JUMPIF R1 L4 ; goto L4 if var1
      23 [-]: GETIMPORT R1 12; var1 = _T["SetSquadOverlayTitle"]
      24 [-]: GETIMPORT R2 14; var2 = 0xAE91E43B
      25 [-]: LOADK R4 K15 ; var4 = "/Lotus/Language/PersonalQuarters/TextCustomizationTitle"
      26 [-]: LOADB R5 0   ; var5 = false
      27 [-]: NAMECALL R2 R2 K16; var3 = var2; var2 = var2[0x42B04007]
      28 [-]: CALL R2 4 0  ; var2, ... = var2(var3, var4, var5)
      29 [-]: CALL R1 0 1  ; var1(var2, ...)
L 4:  30 [-]: GETIMPORT R1 18; var1 = 0x76EA806B
      31 [-]: LOADN R3 0   ; var3 = 0
      32 [-]: NAMECALL R1 R1 K19; var2 = var1; var1 = var1[0x3F3AE64C]
      33 [-]: CALL R1 3 2  ; var1 = var1(var2, var3)
      34 [-]: FASTCALL1 64 R1 L5; 
      35 [-]: MOVE R3 R1   ; var3 = var1
      36 [-]: GETIMPORT R2 4; var2 = 0x7B998233
      37 [-]: CALL R2 2 2  ; var2 = var2(var3)
L 5:  38 [-]: JUMPIF R2 L6 ; goto L6 if var2
      39 [-]: NAMECALL R2 R1 K20; var3 = var1; var2 = var1[0x80563238]
      40 [-]: CALL R2 2 2  ; var2 = var2(var3)
      41 [-]: SETUPVAL R2 1; upvalues[2] = var1
      42 [-]: GETUPVAL R2 1; var2 = upvalues[1]
      43 [-]: NAMECALL R2 R2 K21; var3 = var2; var2 = var2[0x25A6E75E]
      44 [-]: CALL R2 2 2  ; var2 = var2(var3)
      45 [-]: SETUPVAL R2 2; upvalues[2] = var2
L 6:  46 [-]: GETUPVAL R2 3; var2 = upvalues[3]
      47 [-]: LOADB R3 1   ; var3 = true
      48 [-]: CALL R2 2 1  ; var2(var3)
      49 [-]: GETIMPORT R3 23; var3 = _T["LightDeco"]
      50 [-]: FASTCALL1 64 R3 L7; 
      51 [-]: GETIMPORT R2 4; var2 = 0x7B998233
      52 [-]: CALL R2 2 2  ; var2 = var2(var3)
L 7:  53 [-]: JUMPIF R2 L11; goto L11 if var2
      54 [-]: GETIMPORT R2 23; var2 = _T["LightDeco"]
      55 [-]: NAMECALL R2 R2 K24; var3 = var2; var2 = var2[0x905BB2BD]
      56 [-]: CALL R2 2 2  ; var2 = var2(var3)
      57 [-]: LOADN R5 1   ; var5 = 1
      58 [-]: LENGTH R3 R2 ; var3 = #var2
      59 [-]: LOADN R4 1   ; var4 = 1
      60 [-]: FORNPREP R3 L10; nforprep start - [escape at L10] -- var3 = iterator
L 8:  61 [-]: GETTABLE R6 R2 R5; var6 = var2[var5]
      62 [-]: GETIMPORT R8 26; var8 = gLightType
      63 [-]: NAMECALL R6 R6 K27; var7 = var6; var6 = var6[0xF2DEAF69]
      64 [-]: CALL R6 3 2  ; var6 = var6(var7, var8)
      65 [-]: JUMPIFNOT R6 L9; goto L9 if not var6
      66 [-]: GETTABLE R6 R2 R5; var6 = var2[var5]
      67 [-]: SETUPVAL R6 4; upvalues[6] = var4
      68 [-]: GETUPVAL R6 4; var6 = upvalues[4]
      69 [-]: NAMECALL R6 R6 K28; var7 = var6; var6 = var6[0x2B0E7C40]
      70 [-]: CALL R6 2 2  ; var6 = var6(var7)
      71 [-]: SETUPVAL R6 5; upvalues[6] = var5
      72 [-]: GETUPVAL R6 4; var6 = upvalues[4]
      73 [-]: NAMECALL R6 R6 K29; var7 = var6; var6 = var6[0x225ACBBB]
      74 [-]: CALL R6 2 2  ; var6 = var6(var7)
      75 [-]: SETUPVAL R6 6; upvalues[6] = var6
      76 [-]: JUMP L10     ; goto L10
L 9:  77 [-]: FORNLOOP R3 L8; nforloop end - iterate + goto L8
L10:  78 [-]: GETIMPORT R3 23; var3 = _T["LightDeco"]
      79 [-]: NAMECALL R3 R3 K30; var4 = var3; var3 = var3[0x5760DA8D]
      80 [-]: CALL R3 2 2  ; var3 = var3(var4)
      81 [-]: SETUPVAL R3 7; upvalues[3] = var7
      82 [-]: GETUPVAL R3 7; var3 = upvalues[7]
      83 [-]: NAMECALL R3 R3 K31; var4 = var3; var3 = var3[0x8F89D633]
      84 [-]: CALL R3 2 2  ; var3 = var3(var4)
      85 [-]: SETUPVAL R3 8; upvalues[3] = var8
      86 [-]: GETIMPORT R3 33; var3 = _T["PlacingCustomizableDeco"]
      87 [-]: JUMPIFNOT R3 L11; goto L11 if not var3
      88 [-]: GETUPVAL R3 7; var3 = upvalues[7]
      89 [-]: GETUPVAL R4 4; var4 = upvalues[4]
      90 [-]: NAMECALL R4 R4 K34; var5 = var4; var4 = var4[0x5D10207D]
      91 [-]: CALL R4 2 2  ; var4 = var4(var5)
      92 [-]: NAMECALL R4 R4 K35; var5 = var4; var4 = var4[0xA5D5C8F6]
      93 [-]: CALL R4 2 2  ; var4 = var4(var5)
      94 [-]: SETTABLEKS R4 R3 K36; var4["mColorCorrection"] = var3
      95 [-]: GETUPVAL R3 7; var3 = upvalues[7]
      96 [-]: GETUPVAL R4 5; var4 = upvalues[5]
      97 [-]: GETUPVAL R6 4; var6 = upvalues[4]
      98 [-]: NAMECALL R6 R6 K37; var7 = var6; var6 = var6[0xE43E4088]
      99 [-]: CALL R6 2 0  ; var6, ... = var6(var7)
     100 [-]: NAMECALL R4 R4 K38; var5 = var4; var4 = var4[0x3B93153D]
     101 [-]: CALL R4 0 2  ; var4 = var4(var5, ...)
     102 [-]: SETTABLEKS R4 R3 K39; var4["mXOffset"] = var3
     103 [-]: GETUPVAL R3 7; var3 = upvalues[7]
     104 [-]: GETUPVAL R4 6; var4 = upvalues[6]
     105 [-]: GETUPVAL R6 4; var6 = upvalues[4]
     106 [-]: NAMECALL R6 R6 K40; var7 = var6; var6 = var6[0xA1F65ECE]
     107 [-]: CALL R6 2 0  ; var6, ... = var6(var7)
     108 [-]: NAMECALL R4 R4 K38; var5 = var4; var4 = var4[0x3B93153D]
     109 [-]: CALL R4 0 2  ; var4 = var4(var5, ...)
     110 [-]: SETTABLEKS R4 R3 K41; var4["mYOffset"] = var3
L11: 111 [-]: GETIMPORT R2 43; var2 = 0xBE190284
     112 [-]: NAMECALL R2 R2 K44; var3 = var2; var2 = var2[0xA1C390FE]
     113 [-]: CALL R2 2 2  ; var2 = var2(var3)
     114 [-]: SETUPVAL R2 9; upvalues[2] = var9
     115 [-]: GETIMPORT R2 14; var2 = 0xAE91E43B
     116 [-]: LOADK R4 K45 ; var4 = "Bg"
     117 [-]: GETIMPORT R5 47; var5 = 0x3B3EEBE4
     118 [-]: NAMECALL R2 R2 K48; var3 = var2; var2 = var2[0xD5181643]
     119 [-]: CALL R2 4 1  ; var2(var3, var4, var5)
     120 [-]: GETIMPORT R2 14; var2 = 0xAE91E43B
     121 [-]: LOADK R4 K49 ; var4 = "Blurer"
     122 [-]: GETIMPORT R5 47; var5 = 0x3B3EEBE4
     123 [-]: NAMECALL R2 R2 K48; var3 = var2; var2 = var2[0xD5181643]
     124 [-]: CALL R2 4 1  ; var2(var3, var4, var5)
     125 [-]: GETIMPORT R2 14; var2 = 0xAE91E43B
     126 [-]: LOADK R4 K45 ; var4 = "Bg"
     127 [-]: LOADN R5 9   ; var5 = 9
     128 [-]: GETIMPORT R7 51; var7 = 0x0032441C
     129 [-]: GETTABLEKS R6 R7 K52; var6 = var7["UIColor_Black"]
     130 [-]: NAMECALL R2 R2 K53; var3 = var2; var2 = var2[0x67BC869F]
     131 [-]: CALL R2 5 1  ; var2(var3, var4, var5, var6)
     132 [-]: GETIMPORT R2 14; var2 = 0xAE91E43B
     133 [-]: LOADK R4 K45 ; var4 = "Bg"
     134 [-]: LOADN R5 10  ; var5 = 10
     135 [-]: LOADN R6 50  ; var6 = 50
     136 [-]: NAMECALL R2 R2 K53; var3 = var2; var2 = var2[0x67BC869F]
     137 [-]: CALL R2 5 1  ; var2(var3, var4, var5, var6)
     138 [-]: GETUPVAL R2 10; var2 = upvalues[10]
     139 [-]: CALL R2 1 1  ; var2()
     140 [-]: GETUPVAL R2 11; var2 = upvalues[11]
     141 [-]: CALL R2 1 1  ; var2()
     142 [-]: GETUPVAL R2 12; var2 = upvalues[12]
     143 [-]: CALL R2 1 1  ; var2()
     144 [-]: GETUPVAL R2 13; var2 = upvalues[13]
     145 [-]: CALL R2 1 1  ; var2()
     146 [-]: LOADB R2 0   ; var2 = false
     147 [-]: SETUPVAL R2 14; upvalues[2] = var14
     148 [-]: RETURN R0 0  ; 


; Name:            
; Defined at line: 564
; #Upvalues:       1
; #Parameters:     0
; Is_vararg:       0
; Max Stack Size:  4

       0 [-]: GETIMPORT R0 1; var0 = 0xB693B6C1
       1 [-]: CALL R0 1 2  ; var0 = var0()
       2 [-]: GETIMPORT R1 3; var1 = 0xAE91E43B
       3 [-]: MOVE R3 R0   ; var3 = var0
       4 [-]: NAMECALL R1 R1 K4; var2 = var1; var1 = var1[0x8A8C8D5A]
       5 [-]: CALL R1 3 1  ; var1(var2, var3)
       6 [-]: GETUPVAL R2 0; var2 = upvalues[0]
       7 [-]: FASTCALL1 64 R2 L0; 
       8 [-]: GETIMPORT R1 6; var1 = 0x7B998233
       9 [-]: CALL R1 2 2  ; var1 = var1(var2)
L 0:  10 [-]: JUMPIF R1 L1 ; goto L1 if var1
      11 [-]: GETUPVAL R2 0; var2 = upvalues[0]
      12 [-]: GETTABLEKS R1 R2 K7; var1 = var2["CustomizationList"]
      13 [-]: MOVE R3 R0   ; var3 = var0
      14 [-]: NAMECALL R1 R1 K8; var2 = var1; var1 = var1[0xFAA69527]
      15 [-]: CALL R1 3 1  ; var1(var2, var3)
L 1:  16 [-]: RETURN R0 0  ; 


; Name:            
; Defined at line: 576
; #Upvalues:       3
; #Parameters:     1
; Is_vararg:       0
; Max Stack Size:  18

       0 [-]: GETIMPORT R1 1; var1 = 0x7ED0A956
       1 [-]: LOADK R2 K2  ; var2 = "/Lotus/Types/Game/DojoPlaceableDecorations/ShipPlaceableTextLight"
       2 [-]: CALL R1 2 2  ; var1 = var1(var2)
       3 [-]: FASTCALL1 64 R0 L0; 
       4 [-]: MOVE R3 R0   ; var3 = var0
       5 [-]: GETIMPORT R2 4; var2 = 0x7B998233
       6 [-]: CALL R2 2 2  ; var2 = var2(var3)
L 0:   7 [-]: JUMPIF R2 L9 ; goto L9 if var2
       8 [-]: MOVE R4 R1   ; var4 = var1
       9 [-]: NAMECALL R2 R0 K5; var3 = var0; var2 = var0[0xF2DEAF69]
      10 [-]: CALL R2 3 2  ; var2 = var2(var3, var4)
      11 [-]: JUMPIFNOT R2 L9; goto L9 if not var2
      12 [-]: NAMECALL R2 R0 K6; var3 = var0; var2 = var0[0x801404D2]
      13 [-]: CALL R2 2 2  ; var2 = var2(var3)
      14 [-]: NAMECALL R3 R0 K7; var4 = var0; var3 = var0[0x5760DA8D]
      15 [-]: CALL R3 2 2  ; var3 = var3(var4)
      16 [-]: FASTCALL1 64 R2 L1; 
      17 [-]: MOVE R5 R2   ; var5 = var2
      18 [-]: GETIMPORT R4 4; var4 = 0x7B998233
      19 [-]: CALL R4 2 2  ; var4 = var4(var5)
L 1:  20 [-]: JUMPIF R4 L9 ; goto L9 if var4
      21 [-]: FASTCALL1 64 R3 L2; 
      22 [-]: MOVE R5 R3   ; var5 = var3
      23 [-]: GETIMPORT R4 4; var4 = 0x7B998233
      24 [-]: CALL R4 2 2  ; var4 = var4(var5)
L 2:  25 [-]: JUMPIF R4 L9 ; goto L9 if var4
      26 [-]: GETUPVAL R4 0; var4 = upvalues[0]
      27 [-]: GETTABLEKS R5 R3 K8; var5 = var3["mTextColorA"]
      28 [-]: CALL R4 2 2  ; var4 = var4(var5)
      29 [-]: GETUPVAL R5 0; var5 = upvalues[0]
      30 [-]: GETTABLEKS R6 R3 K9; var6 = var3["mTextColorB"]
      31 [-]: CALL R5 2 2  ; var5 = var5(var6)
      32 [-]: GETUPVAL R6 1; var6 = upvalues[1]
      33 [-]: MOVE R7 R4   ; var7 = var4
      34 [-]: CALL R6 2 2  ; var6 = var6(var7)
      35 [-]: MOVE R4 R6   ; var4 = var6
      36 [-]: GETUPVAL R6 1; var6 = upvalues[1]
      37 [-]: MOVE R7 R5   ; var7 = var5
      38 [-]: CALL R6 2 2  ; var6 = var6(var7)
      39 [-]: MOVE R5 R6   ; var5 = var6
      40 [-]: LOADK R8 K10 ; var8 = "SetVertexColors"
      41 [-]: NEWTABLE R9 0 2; var9 = {}
      42 [-]: FASTCALL1 63 R4 L3; 
      43 [-]: MOVE R11 R4  ; var11 = var4
      44 [-]: GETIMPORT R10 12; var10 = 0x64FB1586
      45 [-]: CALL R10 2 2 ; var10 = var10(var11)
L 3:  46 [-]: FASTCALL1 63 R5 L4; 
      47 [-]: MOVE R12 R5  ; var12 = var5
      48 [-]: GETIMPORT R11 12; var11 = 0x64FB1586
      49 [-]: CALL R11 2 2 ; var11 = var11(var12)
L 4:  50 [-]: SETLIST R9 R10 2 [1]; var9[1] = var10; var9[2] = var11; var9[3] = var12; 
      51 [-]: NAMECALL R6 R2 K13; var7 = var2; var6 = var2[0xF56F3887]
      52 [-]: CALL R6 4 1  ; var6(var7, var8, var9)
      53 [-]: NAMECALL R6 R2 K14; var7 = var2; var6 = var2[0xA1653871]
      54 [-]: CALL R6 2 2  ; var6 = var6(var7)
      55 [-]: FASTCALL1 64 R6 L5; 
      56 [-]: MOVE R8 R6   ; var8 = var6
      57 [-]: GETIMPORT R7 4; var7 = 0x7B998233
      58 [-]: CALL R7 2 2  ; var7 = var7(var8)
L 5:  59 [-]: JUMPIF R7 L8 ; goto L8 if var7
      60 [-]: GETTABLEKS R9 R3 K15; var9 = var3["mTextScale"]
      61 [-]: NAMECALL R7 R6 K16; var8 = var6; var7 = var6[0x2D9BA74F]
      62 [-]: CALL R7 3 1  ; var7(var8, var9)
      63 [-]: NAMECALL R7 R0 K17; var8 = var0; var7 = var0[0x905BB2BD]
      64 [-]: CALL R7 2 2  ; var7 = var7(var8)
      65 [-]: LOADN R10 1  ; var10 = 1
      66 [-]: LENGTH R8 R7 ; var8 = #var7
      67 [-]: LOADN R9 1   ; var9 = 1
      68 [-]: FORNPREP R8 L8; nforprep start - [escape at L8] -- var8 = iterator
L 6:  69 [-]: GETTABLE R11 R7 R10; var11 = var7[var10]
      70 [-]: GETIMPORT R13 19; var13 = gLightType
      71 [-]: NAMECALL R11 R11 K5; var12 = var11; var11 = var11[0xF2DEAF69]
      72 [-]: CALL R11 3 2 ; var11 = var11(var12, var13)
      73 [-]: JUMPIFNOT R11 L7; goto L7 if not var11
      74 [-]: GETTABLE R11 R7 R10; var11 = var7[var10]
      75 [-]: NAMECALL R12 R11 K20; var13 = var11; var12 = var11[0x225ACBBB]
      76 [-]: CALL R12 2 2 ; var12 = var12(var13)
      77 [-]: GETUPVAL R13 2; var13 = upvalues[2]
      78 [-]: MOVE R14 R6  ; var14 = var6
      79 [-]: GETTABLEKS R17 R3 K21; var17 = var3["mYOffset"]
      80 [-]: NAMECALL R15 R12 K22; var16 = var12; var15 = var12[0x70596BFE]
      81 [-]: CALL R15 3 2 ; var15 = var15(var16, var17)
      82 [-]: GETTABLEKS R16 R3 K23; var16 = var3["mTextOrientation"]
      83 [-]: CALL R13 4 1 ; var13(var14, var15, var16)
      84 [-]: JUMP L8      ; goto L8
L 7:  85 [-]: FORNLOOP R8 L6; nforloop end - iterate + goto L6
L 8:  86 [-]: LOADK R9 K24 ; var9 = "SetMessage"
      87 [-]: GETTABLEKS R10 R3 K25; var10 = var3["mText"]
      88 [-]: NAMECALL R7 R2 K26; var8 = var2; var7 = var2[0xE4162EED]
      89 [-]: CALL R7 4 1  ; var7(var8, var9, var10)
L 9:  90 [-]: RETURN R0 0  ; 


; Name:            
; Defined at line: 615
; #Upvalues:       2
; #Parameters:     0
; Is_vararg:       0
; Max Stack Size:  1

       0 [-]: GETUPVAL R0 0; var0 = upvalues[0]
       1 [-]: JUMPIF R0 L0 ; goto L0 if var0
       2 [-]: GETUPVAL R0 1; var0 = upvalues[1]
       3 [-]: CALL R0 1 1  ; var0()
       4 [-]: LOADB R0 1   ; var0 = true
       5 [-]: RETURN R0 1  ; 
L 0:   6 [-]: RETURN R0 0  ; 



