; This file has been disassembled using luadec 2.0.2 by sztupy (modified by Reversive)

; Name:            
; Defined at line: 0
; #Upvalues:       0
; #Parameters:     0
; Is_vararg:       2
; Max Stack Size:  31

  1 [-]: GETGLOBAL R0 K0        ; R0 := 0x2d0fad09
  2 [-]: LOADK     R1 K1        ; R1 := "Lotus.Interface.UIStyleUtilities"
  3 [-]: CALL      R0 2 2       ; R0 := R0(R1)
  4 [-]: GETGLOBAL R1 K0        ; R1 := 0x2d0fad09
  5 [-]: LOADK     R2 K2        ; R2 := "Lotus.Interface.LotusUtilities"
  6 [-]: CALL      R1 2 2       ; R1 := R1(R2)
  7 [-]: GETGLOBAL R2 K0        ; R2 := 0x2d0fad09
  8 [-]: LOADK     R3 K3        ; R3 := "Lotus.Interface.UIUtilities"
  9 [-]: CALL      R2 2 2       ; R2 := R2(R3)
 10 [-]: GETGLOBAL R3 K0        ; R3 := 0x2d0fad09
 11 [-]: LOADK     R4 K4        ; R4 := "Lotus.Interface.StoreItemUtilities"
 12 [-]: CALL      R3 2 2       ; R3 := R3(R4)
 13 [-]: GETGLOBAL R4 K0        ; R4 := 0x2d0fad09
 14 [-]: LOADK     R5 K5        ; R5 := "EE.Interface.Utilities"
 15 [-]: CALL      R4 2 2       ; R4 := R4(R5)
 16 [-]: LOADBOOL  R5 0 0       ; R5 := false
 17 [-]: LOADNIL   R6 R8        ; R6 := R7 := R8 := nil
 18 [-]: LOADBOOL  R9 0 0       ; R9 := false
 19 [-]: NEWTABLE  R10 0 0      ; R10 := {}
 20 [-]: LOADNIL   R11 R11      ; R11 := nil
 21 [-]: LOADBOOL  R12 0 0      ; R12 := false
 22 [-]: LOADK     R13 100      ; R13 := 100.000000
 23 [-]: LOADK     R14 0        ; R14 := 0.000000
 24 [-]: LOADBOOL  R15 0 0      ; R15 := false
 25 [-]: LOADK     R16 0        ; R16 := 0.000000
 26 [-]: LOADK     R17 0        ; R17 := 0.000000
 27 [-]: LOADK     R18 0        ; R18 := 0.000000
 28 [-]: LOADBOOL  R19 0 0      ; R19 := false
 29 [-]: LOADK     R20 2        ; R20 := 2.000000
 30 [-]: CLOSURE   R21 0        ; R21 := closure(Function #1)
 31 [-]: CLOSURE   R22 1        ; R22 := closure(Function #2)
 32 [-]: MOVE      R0 R21       ; R0 := R21
 33 [-]: SETGLOBAL R22 K6       ; Close := R22
 34 [-]: CLOSURE   R22 2        ; R22 := closure(Function #3)
 35 [-]: MOVE      R0 R2        ; R0 := R2
 36 [-]: SETGLOBAL R22 K7       ; Shutdown := R22
 37 [-]: CLOSURE   R22 3        ; R22 := closure(Function #4)
 38 [-]: MOVE      R0 R10       ; R0 := R10
 39 [-]: MOVE      R0 R0        ; R0 := R0
 40 [-]: MOVE      R0 R4        ; R0 := R4
 41 [-]: MOVE      R0 R11       ; R0 := R11
 42 [-]: CLOSURE   R23 4        ; R23 := closure(Function #5)
 43 [-]: MOVE      R0 R11       ; R0 := R11
 44 [-]: MOVE      R0 R7        ; R0 := R7
 45 [-]: MOVE      R0 R10       ; R0 := R10
 46 [-]: MOVE      R0 R4        ; R0 := R4
 47 [-]: MOVE      R0 R2        ; R0 := R2
 48 [-]: MOVE      R0 R8        ; R0 := R8
 49 [-]: MOVE      R0 R1        ; R0 := R1
 50 [-]: CLOSURE   R24 5        ; R24 := closure(Function #6)
 51 [-]: MOVE      R0 R8        ; R0 := R8
 52 [-]: MOVE      R0 R13       ; R0 := R13
 53 [-]: MOVE      R0 R4        ; R0 := R4
 54 [-]: MOVE      R0 R14       ; R0 := R14
 55 [-]: CLOSURE   R25 6        ; R25 := closure(Function #7)
 56 [-]: MOVE      R0 R16       ; R0 := R16
 57 [-]: MOVE      R0 R18       ; R0 := R18
 58 [-]: MOVE      R0 R20       ; R0 := R20
 59 [-]: MOVE      R0 R17       ; R0 := R17
 60 [-]: MOVE      R0 R19       ; R0 := R19
 61 [-]: CLOSURE   R26 7        ; R26 := closure(Function #8)
 62 [-]: MOVE      R0 R6        ; R0 := R6
 63 [-]: MOVE      R0 R1        ; R0 := R1
 64 [-]: MOVE      R0 R8        ; R0 := R8
 65 [-]: MOVE      R0 R3        ; R0 := R3
 66 [-]: MOVE      R0 R15       ; R0 := R15
 67 [-]: MOVE      R0 R16       ; R0 := R16
 68 [-]: MOVE      R0 R17       ; R0 := R17
 69 [-]: MOVE      R0 R18       ; R0 := R18
 70 [-]: MOVE      R0 R19       ; R0 := R19
 71 [-]: MOVE      R0 R24       ; R0 := R24
 72 [-]: MOVE      R0 R2        ; R0 := R2
 73 [-]: MOVE      R0 R7        ; R0 := R7
 74 [-]: MOVE      R0 R4        ; R0 := R4
 75 [-]: MOVE      R0 R9        ; R0 := R9
 76 [-]: CLOSURE   R27 8        ; R27 := closure(Function #9)
 77 [-]: MOVE      R0 R13       ; R0 := R13
 78 [-]: MOVE      R0 R14       ; R0 := R14
 79 [-]: MOVE      R0 R4        ; R0 := R4
 80 [-]: MOVE      R0 R12       ; R0 := R12
 81 [-]: CLOSURE   R28 9        ; R28 := closure(Function #10)
 82 [-]: MOVE      R0 R6        ; R0 := R6
 83 [-]: MOVE      R0 R1        ; R0 := R1
 84 [-]: MOVE      R0 R22       ; R0 := R22
 85 [-]: MOVE      R0 R17       ; R0 := R17
 86 [-]: MOVE      R0 R4        ; R0 := R4
 87 [-]: MOVE      R0 R23       ; R0 := R23
 88 [-]: MOVE      R0 R26       ; R0 := R26
 89 [-]: MOVE      R0 R27       ; R0 := R27
 90 [-]: SETGLOBAL R28 K8       ; Initialize := R28
 91 [-]: CLOSURE   R28 10       ; R28 := closure(Function #11)
 92 [-]: MOVE      R0 R15       ; R0 := R15
 93 [-]: MOVE      R0 R19       ; R0 := R19
 94 [-]: MOVE      R0 R25       ; R0 := R25
 95 [-]: MOVE      R0 R21       ; R0 := R21
 96 [-]: SETGLOBAL R28 K9       ; Update := R28
 97 [-]: CLOSURE   R28 11       ; R28 := closure(Function #12)
 98 [-]: MOVE      R0 R5        ; R0 := R5
 99 [-]: MOVE      R0 R21       ; R0 := R21
100 [-]: CLOSURE   R29 12       ; R29 := closure(Function #13)
101 [-]: MOVE      R0 R4        ; R0 := R4
102 [-]: MOVE      R0 R28       ; R0 := R28
103 [-]: CLOSURE   R30 13       ; R30 := closure(Function #14)
104 [-]: MOVE      R0 R5        ; R0 := R5
105 [-]: MOVE      R0 R29       ; R0 := R29
106 [-]: SETGLOBAL R30 K10      ; onKeyUp_MENU_CANCEL := R30
107 [-]: CLOSURE   R30 14       ; R30 := closure(Function #15)
108 [-]: MOVE      R0 R11       ; R0 := R11
109 [-]: MOVE      R0 R22       ; R0 := R22
110 [-]: SETGLOBAL R30 K11      ; SetTrigger := R30
111 [-]: CLOSURE   R30 15       ; R30 := closure(Function #16)
112 [-]: MOVE      R0 R12       ; R0 := R12
113 [-]: MOVE      R0 R27       ; R0 := R27
114 [-]: SETGLOBAL R30 K12      ; SetRightAligned := R30
115 [-]: CLOSURE   R30 16       ; R30 := closure(Function #17)
116 [-]: MOVE      R0 R27       ; R0 := R27
117 [-]: SETGLOBAL R30 K13      ; onViewportSizeChanged := R30
118 [-]: CLOSURE   R30 17       ; R30 := closure(Function #18)
119 [-]: MOVE      R0 R7        ; R0 := R7
120 [-]: MOVE      R0 R26       ; R0 := R26
121 [-]: SETGLOBAL R30 K14      ; OnWorldStateChanged := R30
122 [-]: RETURN    R0 1         ; return 


; Function #1:
;
; Name:            
; Defined at line: 44
; #Upvalues:       0
; #Parameters:     0
; Is_vararg:       0
; Max Stack Size:  2

  1 [-]: GETGLOBAL R0 K0        ; R0 := _T
  2 [-]: SETTABLE  R0 K1 K2     ; R0["JunctionTasksRelayReconstruction"] := nil
  3 [-]: GETGLOBAL R0 K3        ; R0 := 0x7b998233
  4 [-]: GETGLOBAL R1 K4        ; R1 := 0xae91e43b
  5 [-]: CALL      R0 2 2       ; R0 := R0(R1)
  6 [-]: TEST      R0 1         ; if R0 then PC := 11
  7 [-]: JMP       11           ; PC := 11
  8 [-]: GETGLOBAL R0 K4        ; R0 := 0xae91e43b
  9 [-]: SELF      R0 R0 K5     ; R1 := R0; R0 := R0[0x32302b4a]
 10 [-]: CALL      R0 2 1       ; R0(R1)
 11 [-]: RETURN    R0 1         ; return 


; Function #2:
;
; Name:            
; Defined at line: 52
; #Upvalues:       1
; #Parameters:     0
; Is_vararg:       0
; Max Stack Size:  2

  1 [-]: GETUPVAL  R0 U0        ; R0 := U0
  2 [-]: CALL      R0 1 1       ; R0()
  3 [-]: RETURN    R0 1         ; return 


; Function #3:
;
; Name:            
; Defined at line: 56
; #Upvalues:       1
; #Parameters:     0
; Is_vararg:       0
; Max Stack Size:  2

  1 [-]: GETUPVAL  R0 U0        ; R0 := U0
  2 [-]: GETTABLE  R0 R0 K0     ; R0 := R0[0xc4b927cd]
  3 [-]: CALL      R0 1 1       ; R0()
  4 [-]: RETURN    R0 1         ; return 


; Function #4:
;
; Name:            
; Defined at line: 60
; #Upvalues:       4
; #Parameters:     0
; Is_vararg:       0
; Max Stack Size:  9

  1 [-]: GETUPVAL  R0 U0        ; R0 := U0
  2 [-]: GETUPVAL  R1 U1        ; R1 := U1
  3 [-]: GETTABLE  R1 R1 K1     ; R1 := R1[0x5d10207d]
  4 [-]: LOADK     R2 2         ; R2 := 2.000000
  5 [-]: LOADBOOL  R3 1 0       ; R3 := true
  6 [-]: CALL      R1 3 2       ; R1 := R1(R2,R3)
  7 [-]: SETTABLE  R0 K0 R1     ; R0["Background1"] := R1
  8 [-]: GETUPVAL  R0 U0        ; R0 := U0
  9 [-]: GETUPVAL  R1 U2        ; R1 := U2
 10 [-]: GETTABLE  R1 R1 K4     ; R1 := R1[0x8bcd12b6]
 11 [-]: GETUPVAL  R2 U0        ; R2 := U0
 12 [-]: GETTABLE  R2 R2 K0     ; R2 := R2["Background1"]
 13 [-]: CALL      R1 2 2       ; R1 := R1(R2)
 14 [-]: SETTABLE  R0 K3 R1     ; R0["Background1Object"] := R1
 15 [-]: GETUPVAL  R0 U0        ; R0 := U0
 16 [-]: GETUPVAL  R1 U1        ; R1 := U1
 17 [-]: GETTABLE  R1 R1 K1     ; R1 := R1[0x5d10207d]
 18 [-]: LOADK     R2 5         ; R2 := 5.000000
 19 [-]: LOADBOOL  R3 1 0       ; R3 := true
 20 [-]: CALL      R1 3 2       ; R1 := R1(R2,R3)
 21 [-]: SETTABLE  R0 K5 R1     ; R0["Background4"] := R1
 22 [-]: GETUPVAL  R0 U0        ; R0 := U0
 23 [-]: GETUPVAL  R1 U1        ; R1 := U1
 24 [-]: GETTABLE  R1 R1 K1     ; R1 := R1[0x5d10207d]
 25 [-]: LOADK     R2 6         ; R2 := 6.000000
 26 [-]: LOADBOOL  R3 1 0       ; R3 := true
 27 [-]: CALL      R1 3 2       ; R1 := R1(R2,R3)
 28 [-]: SETTABLE  R0 K6 R1     ; R0["Content"] := R1
 29 [-]: GETUPVAL  R0 U0        ; R0 := U0
 30 [-]: GETUPVAL  R1 U1        ; R1 := U1
 31 [-]: GETTABLE  R1 R1 K1     ; R1 := R1[0x5d10207d]
 32 [-]: LOADK     R2 9         ; R2 := 9.000000
 33 [-]: LOADBOOL  R3 1 0       ; R3 := true
 34 [-]: CALL      R1 3 2       ; R1 := R1(R2,R3)
 35 [-]: SETTABLE  R0 K7 R1     ; R0["FloatingContent"] := R1
 36 [-]: GETUPVAL  R0 U0        ; R0 := U0
 37 [-]: GETUPVAL  R1 U2        ; R1 := U2
 38 [-]: GETTABLE  R1 R1 K4     ; R1 := R1[0x8bcd12b6]
 39 [-]: GETUPVAL  R2 U0        ; R2 := U0
 40 [-]: GETTABLE  R2 R2 K7     ; R2 := R2["FloatingContent"]
 41 [-]: CALL      R1 2 2       ; R1 := R1(R2)
 42 [-]: SETTABLE  R0 K8 R1     ; R0["FloatingContentObject"] := R1
 43 [-]: GETUPVAL  R0 U0        ; R0 := U0
 44 [-]: GETUPVAL  R1 U1        ; R1 := U1
 45 [-]: GETTABLE  R1 R1 K1     ; R1 := R1[0x5d10207d]
 46 [-]: LOADK     R2 10        ; R2 := 10.000000
 47 [-]: LOADBOOL  R3 1 0       ; R3 := true
 48 [-]: CALL      R1 3 2       ; R1 := R1(R2,R3)
 49 [-]: SETTABLE  R0 K9 R1     ; R0["FloatingContentHighlight"] := R1
 50 [-]: GETUPVAL  R0 U0        ; R0 := U0
 51 [-]: GETUPVAL  R1 U2        ; R1 := U2
 52 [-]: GETTABLE  R1 R1 K4     ; R1 := R1[0x8bcd12b6]
 53 [-]: GETUPVAL  R2 U0        ; R2 := U0
 54 [-]: GETTABLE  R2 R2 K9     ; R2 := R2["FloatingContentHighlight"]
 55 [-]: CALL      R1 2 2       ; R1 := R1(R2)
 56 [-]: SETTABLE  R0 K10 R1    ; R0["FloatingContentHighlightObject"] := R1
 57 [-]: GETUPVAL  R0 U0        ; R0 := U0
 58 [-]: GETUPVAL  R1 U1        ; R1 := U1
 59 [-]: GETTABLE  R1 R1 K1     ; R1 := R1[0x5d10207d]
 60 [-]: LOADK     R2 1         ; R2 := 1.000000
 61 [-]: LOADBOOL  R3 1 0       ; R3 := true
 62 [-]: CALL      R1 3 2       ; R1 := R1(R2,R3)
 63 [-]: SETTABLE  R0 K11 R1    ; R0["BackerHighlight"] := R1
 64 [-]: GETUPVAL  R0 U0        ; R0 := U0
 65 [-]: GETUPVAL  R1 U1        ; R1 := U1
 66 [-]: GETTABLE  R1 R1 K1     ; R1 := R1[0x5d10207d]
 67 [-]: LOADK     R2 12        ; R2 := 12.000000
 68 [-]: LOADBOOL  R3 1 0       ; R3 := true
 69 [-]: CALL      R1 3 2       ; R1 := R1(R2,R3)
 70 [-]: SETTABLE  R0 K12 R1    ; R0["Negative"] := R1
 71 [-]: GETGLOBAL R0 K13       ; R0 := 0x0032441c
 72 [-]: GETTABLE  R0 R0 K14    ; R0 := R0["UIMaterial_RectangleNoDepth"]
 73 [-]: GETGLOBAL R1 K15       ; R1 := 0x7b998233
 74 [-]: GETUPVAL  R2 U3        ; R2 := U3
 75 [-]: CALL      R1 2 2       ; R1 := R1(R2)
 76 [-]: TEST      R1 1         ; if R1 then PC := 80
 77 [-]: JMP       80           ; PC := 80
 78 [-]: GETGLOBAL R1 K13       ; R1 := 0x0032441c
 79 [-]: GETTABLE  R0 R1 K16    ; R0 := R1["UIMaterial_Rectangle"]
 80 [-]: GETGLOBAL R1 K17       ; R1 := 0xae91e43b
 81 [-]: SELF      R1 R1 K18    ; R2 := R1; R1 := R1[0xd5181643]
 82 [-]: LOADK     R3 K19       ; R3 := "Junction.Bg"
 83 [-]: MOVE      R4 R0        ; R4 := R0
 84 [-]: CALL      R1 4 1       ; R1(R2,R3,R4)
 85 [-]: GETGLOBAL R1 K17       ; R1 := 0xae91e43b
 86 [-]: SELF      R1 R1 K20    ; R2 := R1; R1 := R1[0x91e13703]
 87 [-]: LOADK     R3 K19       ; R3 := "Junction.Bg"
 88 [-]: LOADK     R4 K21       ; R4 := "RectInnerColor"
 89 [-]: GETUPVAL  R5 U0        ; R5 := U0
 90 [-]: GETTABLE  R5 R5 K3     ; R5 := R5["Background1Object"]
 91 [-]: GETTABLE  R5 R5 K22    ; R5 := R5["r"]
 92 [-]: GETUPVAL  R6 U0        ; R6 := U0
 93 [-]: GETTABLE  R6 R6 K3     ; R6 := R6["Background1Object"]
 94 [-]: GETTABLE  R6 R6 K23    ; R6 := R6["g"]
 95 [-]: GETUPVAL  R7 U0        ; R7 := U0
 96 [-]: GETTABLE  R7 R7 K3     ; R7 := R7["Background1Object"]
 97 [-]: GETTABLE  R7 R7 K24    ; R7 := R7["b"]
 98 [-]: LOADK     R8 K25       ; R8 := 0.900000
 99 [-]: CALL      R1 8 1       ; R1(R2,R3,R4,R5,R6,R7,R8)
100 [-]: GETGLOBAL R1 K17       ; R1 := 0xae91e43b
101 [-]: SELF      R1 R1 K20    ; R2 := R1; R1 := R1[0x91e13703]
102 [-]: LOADK     R3 K19       ; R3 := "Junction.Bg"
103 [-]: LOADK     R4 K26       ; R4 := "RectEdgeColor"
104 [-]: GETUPVAL  R5 U0        ; R5 := U0
105 [-]: GETTABLE  R5 R5 K8     ; R5 := R5["FloatingContentObject"]
106 [-]: GETTABLE  R5 R5 K22    ; R5 := R5["r"]
107 [-]: GETUPVAL  R6 U0        ; R6 := U0
108 [-]: GETTABLE  R6 R6 K8     ; R6 := R6["FloatingContentObject"]
109 [-]: GETTABLE  R6 R6 K23    ; R6 := R6["g"]
110 [-]: GETUPVAL  R7 U0        ; R7 := U0
111 [-]: GETTABLE  R7 R7 K8     ; R7 := R7["FloatingContentObject"]
112 [-]: GETTABLE  R7 R7 K24    ; R7 := R7["b"]
113 [-]: LOADK     R8 K27       ; R8 := 0.600000
114 [-]: CALL      R1 8 1       ; R1(R2,R3,R4,R5,R6,R7,R8)
115 [-]: GETGLOBAL R1 K17       ; R1 := 0xae91e43b
116 [-]: SELF      R1 R1 K28    ; R2 := R1; R1 := R1[0x67bc869f]
117 [-]: LOADK     R3 K29       ; R3 := "Junction.JunctionIcon"
118 [-]: LOADK     R4 9         ; R4 := 9.000000
119 [-]: GETUPVAL  R5 U0        ; R5 := U0
120 [-]: GETTABLE  R5 R5 K9     ; R5 := R5["FloatingContentHighlight"]
121 [-]: CALL      R1 5 1       ; R1(R2,R3,R4,R5)
122 [-]: GETGLOBAL R1 K17       ; R1 := 0xae91e43b
123 [-]: SELF      R1 R1 K28    ; R2 := R1; R1 := R1[0x67bc869f]
124 [-]: LOADK     R3 K30       ; R3 := "Junction.JunctionName"
125 [-]: LOADK     R4 36        ; R4 := 36.000000
126 [-]: GETUPVAL  R5 U0        ; R5 := U0
127 [-]: GETTABLE  R5 R5 K9     ; R5 := R5["FloatingContentHighlight"]
128 [-]: CALL      R1 5 1       ; R1(R2,R3,R4,R5)
129 [-]: GETGLOBAL R1 K17       ; R1 := 0xae91e43b
130 [-]: SELF      R1 R1 K28    ; R2 := R1; R1 := R1[0x67bc869f]
131 [-]: LOADK     R3 K31       ; R3 := "Junction.JunctionDesc"
132 [-]: LOADK     R4 36        ; R4 := 36.000000
133 [-]: GETUPVAL  R5 U0        ; R5 := U0
134 [-]: GETTABLE  R5 R5 K7     ; R5 := R5["FloatingContent"]
135 [-]: CALL      R1 5 1       ; R1(R2,R3,R4,R5)
136 [-]: GETGLOBAL R1 K17       ; R1 := 0xae91e43b
137 [-]: SELF      R1 R1 K28    ; R2 := R1; R1 := R1[0x67bc869f]
138 [-]: LOADK     R3 K32       ; R3 := "Junction.TitleSeparator"
139 [-]: LOADK     R4 9         ; R4 := 9.000000
140 [-]: GETUPVAL  R5 U0        ; R5 := U0
141 [-]: GETTABLE  R5 R5 K9     ; R5 := R5["FloatingContentHighlight"]
142 [-]: CALL      R1 5 1       ; R1(R2,R3,R4,R5)
143 [-]: GETGLOBAL R1 K17       ; R1 := 0xae91e43b
144 [-]: SELF      R1 R1 K28    ; R2 := R1; R1 := R1[0x67bc869f]
145 [-]: LOADK     R3 K33       ; R3 := "Junction.TitleBanner"
146 [-]: LOADK     R4 9         ; R4 := 9.000000
147 [-]: GETUPVAL  R5 U0        ; R5 := U0
148 [-]: GETTABLE  R5 R5 K7     ; R5 := R5["FloatingContent"]
149 [-]: CALL      R1 5 1       ; R1(R2,R3,R4,R5)
150 [-]: GETGLOBAL R1 K17       ; R1 := 0xae91e43b
151 [-]: SELF      R1 R1 K28    ; R2 := R1; R1 := R1[0x67bc869f]
152 [-]: LOADK     R3 K33       ; R3 := "Junction.TitleBanner"
153 [-]: LOADK     R4 10        ; R4 := 10.000000
154 [-]: LOADK     R5 15        ; R5 := 15.000000
155 [-]: CALL      R1 5 1       ; R1(R2,R3,R4,R5)
156 [-]: GETGLOBAL R1 K17       ; R1 := 0xae91e43b
157 [-]: SELF      R1 R1 K18    ; R2 := R1; R1 := R1[0xd5181643]
158 [-]: LOADK     R3 K34       ; R3 := "Junction.Rewards.Header.Bg"
159 [-]: MOVE      R4 R0        ; R4 := R0
160 [-]: CALL      R1 4 1       ; R1(R2,R3,R4)
161 [-]: GETGLOBAL R1 K17       ; R1 := 0xae91e43b
162 [-]: SELF      R1 R1 K20    ; R2 := R1; R1 := R1[0x91e13703]
163 [-]: LOADK     R3 K34       ; R3 := "Junction.Rewards.Header.Bg"
164 [-]: LOADK     R4 K21       ; R4 := "RectInnerColor"
165 [-]: GETUPVAL  R5 U0        ; R5 := U0
166 [-]: GETTABLE  R5 R5 K3     ; R5 := R5["Background1Object"]
167 [-]: GETTABLE  R5 R5 K22    ; R5 := R5["r"]
168 [-]: GETUPVAL  R6 U0        ; R6 := U0
169 [-]: GETTABLE  R6 R6 K3     ; R6 := R6["Background1Object"]
170 [-]: GETTABLE  R6 R6 K23    ; R6 := R6["g"]
171 [-]: GETUPVAL  R7 U0        ; R7 := U0
172 [-]: GETTABLE  R7 R7 K3     ; R7 := R7["Background1Object"]
173 [-]: GETTABLE  R7 R7 K24    ; R7 := R7["b"]
174 [-]: LOADK     R8 K35       ; R8 := 0.700000
175 [-]: CALL      R1 8 1       ; R1(R2,R3,R4,R5,R6,R7,R8)
176 [-]: GETGLOBAL R1 K17       ; R1 := 0xae91e43b
177 [-]: SELF      R1 R1 K20    ; R2 := R1; R1 := R1[0x91e13703]
178 [-]: LOADK     R3 K34       ; R3 := "Junction.Rewards.Header.Bg"
179 [-]: LOADK     R4 K26       ; R4 := "RectEdgeColor"
180 [-]: GETUPVAL  R5 U0        ; R5 := U0
181 [-]: GETTABLE  R5 R5 K8     ; R5 := R5["FloatingContentObject"]
182 [-]: GETTABLE  R5 R5 K22    ; R5 := R5["r"]
183 [-]: GETUPVAL  R6 U0        ; R6 := U0
184 [-]: GETTABLE  R6 R6 K8     ; R6 := R6["FloatingContentObject"]
185 [-]: GETTABLE  R6 R6 K23    ; R6 := R6["g"]
186 [-]: GETUPVAL  R7 U0        ; R7 := U0
187 [-]: GETTABLE  R7 R7 K8     ; R7 := R7["FloatingContentObject"]
188 [-]: GETTABLE  R7 R7 K24    ; R7 := R7["b"]
189 [-]: LOADK     R8 K36       ; R8 := 0.050000
190 [-]: CALL      R1 8 1       ; R1(R2,R3,R4,R5,R6,R7,R8)
191 [-]: GETGLOBAL R1 K17       ; R1 := 0xae91e43b
192 [-]: SELF      R1 R1 K28    ; R2 := R1; R1 := R1[0x67bc869f]
193 [-]: LOADK     R3 K37       ; R3 := "Junction.Rewards.Header.Banner"
194 [-]: LOADK     R4 9         ; R4 := 9.000000
195 [-]: GETUPVAL  R5 U0        ; R5 := U0
196 [-]: GETTABLE  R5 R5 K7     ; R5 := R5["FloatingContent"]
197 [-]: CALL      R1 5 1       ; R1(R2,R3,R4,R5)
198 [-]: GETGLOBAL R1 K17       ; R1 := 0xae91e43b
199 [-]: SELF      R1 R1 K28    ; R2 := R1; R1 := R1[0x67bc869f]
200 [-]: LOADK     R3 K37       ; R3 := "Junction.Rewards.Header.Banner"
201 [-]: LOADK     R4 10        ; R4 := 10.000000
202 [-]: LOADK     R5 15        ; R5 := 15.000000
203 [-]: CALL      R1 5 1       ; R1(R2,R3,R4,R5)
204 [-]: GETGLOBAL R1 K17       ; R1 := 0xae91e43b
205 [-]: SELF      R1 R1 K28    ; R2 := R1; R1 := R1[0x67bc869f]
206 [-]: LOADK     R3 K38       ; R3 := "Junction.Rewards.Header.Title"
207 [-]: LOADK     R4 36        ; R4 := 36.000000
208 [-]: GETUPVAL  R5 U0        ; R5 := U0
209 [-]: GETTABLE  R5 R5 K7     ; R5 := R5["FloatingContent"]
210 [-]: CALL      R1 5 1       ; R1(R2,R3,R4,R5)
211 [-]: GETGLOBAL R1 K17       ; R1 := 0xae91e43b
212 [-]: SELF      R1 R1 K28    ; R2 := R1; R1 := R1[0x67bc869f]
213 [-]: LOADK     R3 K39       ; R3 := "Junction.Rewards.Header.RewardCount"
214 [-]: LOADK     R4 36        ; R4 := 36.000000
215 [-]: GETUPVAL  R5 U0        ; R5 := U0
216 [-]: GETTABLE  R5 R5 K7     ; R5 := R5["FloatingContent"]
217 [-]: CALL      R1 5 1       ; R1(R2,R3,R4,R5)
218 [-]: GETGLOBAL R1 K17       ; R1 := 0xae91e43b
219 [-]: SELF      R1 R1 K28    ; R2 := R1; R1 := R1[0x67bc869f]
220 [-]: LOADK     R3 K40       ; R3 := "Junction.Rewards.Header.RewardCountOutline"
221 [-]: LOADK     R4 9         ; R4 := 9.000000
222 [-]: GETUPVAL  R5 U0        ; R5 := U0
223 [-]: GETTABLE  R5 R5 K7     ; R5 := R5["FloatingContent"]
224 [-]: CALL      R1 5 1       ; R1(R2,R3,R4,R5)
225 [-]: GETGLOBAL R1 K17       ; R1 := 0xae91e43b
226 [-]: SELF      R1 R1 K28    ; R2 := R1; R1 := R1[0x67bc869f]
227 [-]: LOADK     R3 K40       ; R3 := "Junction.Rewards.Header.RewardCountOutline"
228 [-]: LOADK     R4 10        ; R4 := 10.000000
229 [-]: LOADK     R5 50        ; R5 := 50.000000
230 [-]: CALL      R1 5 1       ; R1(R2,R3,R4,R5)
231 [-]: GETGLOBAL R1 K17       ; R1 := 0xae91e43b
232 [-]: SELF      R1 R1 K28    ; R2 := R1; R1 := R1[0x67bc869f]
233 [-]: LOADK     R3 K41       ; R3 := "Junction.Rewards.BgLineLeft"
234 [-]: LOADK     R4 9         ; R4 := 9.000000
235 [-]: GETUPVAL  R5 U0        ; R5 := U0
236 [-]: GETTABLE  R5 R5 K7     ; R5 := R5["FloatingContent"]
237 [-]: CALL      R1 5 1       ; R1(R2,R3,R4,R5)
238 [-]: GETGLOBAL R1 K17       ; R1 := 0xae91e43b
239 [-]: SELF      R1 R1 K28    ; R2 := R1; R1 := R1[0x67bc869f]
240 [-]: LOADK     R3 K42       ; R3 := "Junction.Rewards.BgLineRight"
241 [-]: LOADK     R4 9         ; R4 := 9.000000
242 [-]: GETUPVAL  R5 U0        ; R5 := U0
243 [-]: GETTABLE  R5 R5 K7     ; R5 := R5["FloatingContent"]
244 [-]: CALL      R1 5 1       ; R1(R2,R3,R4,R5)
245 [-]: RETURN    R0 1         ; return 


; Function #5:
;
; Name:            
; Defined at line: 100
; #Upvalues:       7
; #Parameters:     0
; Is_vararg:       0
; Max Stack Size:  11

  1 [-]: GETGLOBAL R0 K0        ; R0 := 0x0032441c
  2 [-]: GETTABLE  R0 R0 K1     ; R0 := R0["UIMaterial_RectangleNoDepth"]
  3 [-]: GETGLOBAL R1 K2        ; R1 := 0x7b998233
  4 [-]: GETUPVAL  R2 U0        ; R2 := U0
  5 [-]: CALL      R1 2 2       ; R1 := R1(R2)
  6 [-]: TEST      R1 1         ; if R1 then PC := 10
  7 [-]: JMP       10           ; PC := 10
  8 [-]: GETGLOBAL R1 K0        ; R1 := 0x0032441c
  9 [-]: GETTABLE  R0 R1 K3     ; R0 := R1["UIMaterial_Rectangle"]
 10 [-]: GETGLOBAL R1 K4        ; R1 := 0x2d0fad09
 11 [-]: LOADK     R2 K5        ; R2 := "EE.Interface.Components.List"
 12 [-]: CALL      R1 2 2       ; R1 := R1(R2)
 13 [-]: GETTABLE  R2 R1 K6     ; R2 := R1[0x9383bc56]
 14 [-]: GETGLOBAL R3 K7        ; R3 := 0xae91e43b
 15 [-]: LOADK     R4 K8        ; R4 := "Junction.MissionTaskList.MissionTask"
 16 [-]: CALL      R2 3 2       ; R2 := R2(R3,R4)
 17 [-]: SETUPVAL  R2 U1        ; U82 := R1
 18 [-]: GETUPVAL  R2 U1        ; R2 := U1
 19 [-]: SETTABLE  R2 K9 K10    ; R2["mVisibleElements"] := 6.000000
 20 [-]: GETUPVAL  R2 U1        ; R2 := U1
 21 [-]: CLOSURE   R3 0         ; R3 := closure(Function #5.1)
 22 [-]: MOVE      R0 R0        ; R0 := R0
 23 [-]: GETUPVAL  R0 U2        ; R0 := U2
 24 [-]: GETUPVAL  R0 U3        ; R0 := U3
 25 [-]: GETUPVAL  R0 U0        ; R0 := U0
 26 [-]: SETTABLE  R2 K11 R3    ; R2["mClipCreatedCallback"] := R3
 27 [-]: GETUPVAL  R2 U1        ; R2 := U1
 28 [-]: CLOSURE   R3 1         ; R3 := closure(Function #5.2)
 29 [-]: GETUPVAL  R0 U3        ; R0 := U3
 30 [-]: GETUPVAL  R0 U4        ; R0 := U4
 31 [-]: GETUPVAL  R0 U0        ; R0 := U0
 32 [-]: GETUPVAL  R0 U2        ; R0 := U2
 33 [-]: SETTABLE  R2 K12 R3    ; R2["mElementDrawCallback"] := R3
 34 [-]: GETUPVAL  R2 U1        ; R2 := U1
 35 [-]: CLOSURE   R3 2         ; R3 := closure(Function #5.3)
 36 [-]: SETTABLE  R2 K13 R3    ; R2["GetHeight"] := R3
 37 [-]: GETUPVAL  R2 U1        ; R2 := U1
 38 [-]: CLOSURE   R3 3         ; R3 := closure(Function #5.4)
 39 [-]: SETTABLE  R2 K14 R3    ; R2["CalculateY"] := R3
 40 [-]: GETGLOBAL R2 K7        ; R2 := 0xae91e43b
 41 [-]: SELF      R2 R2 K15    ; R3 := R2; R2 := R2[0x20b98db3]
 42 [-]: LOADK     R4 K16       ; R4 := "Junction.Rewards.Header.Title.text"
 43 [-]: LOADK     R5 K17       ; R5 := "/Lotus/Language/Menu/MissionStats_Rewards"
 44 [-]: CALL      R2 4 1       ; R2(R3,R4,R5)
 45 [-]: GETGLOBAL R2 K2        ; R2 := 0x7b998233
 46 [-]: GETUPVAL  R3 U0        ; R3 := U0
 47 [-]: CALL      R2 2 2       ; R2 := R2(R3)
 48 [-]: NOT       R2 R2        ; R2 := not R2
 49 [-]: GETGLOBAL R3 K4        ; R3 := 0x2d0fad09
 50 [-]: LOADK     R4 K18       ; R4 := "Lotus.Interface.Components.CategorizedGrid"
 51 [-]: CALL      R3 2 2       ; R3 := R3(R4)
 52 [-]: GETTABLE  R4 R3 K19    ; R4 := R3[0x67d7b715]
 53 [-]: GETGLOBAL R5 K7        ; R5 := 0xae91e43b
 54 [-]: LOADK     R6 K20       ; R6 := "Junction.Rewards.RewardGrid.RewardItem"
 55 [-]: LOADK     R7 1         ; R7 := 1.000000
 56 [-]: LOADK     R8 4         ; R8 := 4.000000
 57 [-]: LOADNIL   R9 R10       ; R9 := R10 := nil
 58 [-]: CALL      R4 7 2       ; R4 := R4(R5,R6,R7,R8,R9,R10)
 59 [-]: SETUPVAL  R4 U5        ; U82 := R5
 60 [-]: GETUPVAL  R4 U5        ; R4 := U5
 61 [-]: SETTABLE  R4 K21 K10   ; R4["ElementDimBuffer"] := 6.000000
 62 [-]: GETUPVAL  R4 U5        ; R4 := U5
 63 [-]: SETTABLE  R4 K22 K23   ; R4["ElementWidth"] := 142.000000
 64 [-]: GETUPVAL  R4 U5        ; R4 := U5
 65 [-]: SETTABLE  R4 K24 K23   ; R4["ElementHeight"] := 142.000000
 66 [-]: GETUPVAL  R4 U5        ; R4 := U5
 67 [-]: SETTABLE  R4 K25 K26   ; R4["Width"] := 2003.000000
 68 [-]: GETUPVAL  R4 U5        ; R4 := U5
 69 [-]: SETTABLE  R4 K27 K23   ; R4["Height"] := 142.000000
 70 [-]: GETUPVAL  R4 U5        ; R4 := U5
 71 [-]: SETTABLE  R4 K28 K29   ; R4["mSelectedScale"] := 100.000000
 72 [-]: GETUPVAL  R4 U5        ; R4 := U5
 73 [-]: SETTABLE  R4 K30 K31   ; R4["mAddFillerElements"] := false
 74 [-]: GETUPVAL  R4 U5        ; R4 := U5
 75 [-]: SETTABLE  R4 K32 K33   ; R4["Horizontal"] := true
 76 [-]: GETUPVAL  R4 U5        ; R4 := U5
 77 [-]: GETUPVAL  R5 U3        ; R5 := U3
 78 [-]: GETTABLE  R5 R5 K35    ; R5 := R5[0x06d055f9]
 79 [-]: MOVE      R6 R2        ; R6 := R2
 80 [-]: GETGLOBAL R7 K36       ; R7 := 0xb3da39c4
 81 [-]: GETGLOBAL R8 K37       ; R8 := 0x76fb6f6c
 82 [-]: CALL      R5 4 2       ; R5 := R5(R6,R7,R8)
 83 [-]: SETTABLE  R4 K34 R5    ; R4["RectangleVisibleRangeMaterial"] := R5
 84 [-]: GETUPVAL  R4 U5        ; R4 := U5
 85 [-]: GETUPVAL  R5 U3        ; R5 := U3
 86 [-]: GETTABLE  R5 R5 K35    ; R5 := R5[0x06d055f9]
 87 [-]: MOVE      R6 R2        ; R6 := R2
 88 [-]: GETGLOBAL R7 K39       ; R7 := 0xf60baa1f
 89 [-]: GETGLOBAL R8 K40       ; R8 := 0x9741db59
 90 [-]: CALL      R5 4 2       ; R5 := R5(R6,R7,R8)
 91 [-]: SETTABLE  R4 K38 R5    ; R4["VisibleRangeMaterial"] := R5
 92 [-]: GETUPVAL  R4 U5        ; R4 := U5
 93 [-]: GETUPVAL  R5 U3        ; R5 := U3
 94 [-]: GETTABLE  R5 R5 K35    ; R5 := R5[0x06d055f9]
 95 [-]: MOVE      R6 R2        ; R6 := R2
 96 [-]: GETGLOBAL R7 K42       ; R7 := 0xc3c874b4
 97 [-]: GETGLOBAL R8 K43       ; R8 := 0x1518ebbc
 98 [-]: CALL      R5 4 2       ; R5 := R5(R6,R7,R8)
 99 [-]: SETTABLE  R4 K41 R5    ; R4["TextVisibleRangeMaterial"] := R5
100 [-]: GETUPVAL  R4 U5        ; R4 := U5
101 [-]: GETUPVAL  R5 U3        ; R5 := U3
102 [-]: GETTABLE  R5 R5 K35    ; R5 := R5[0x06d055f9]
103 [-]: MOVE      R6 R2        ; R6 := R2
104 [-]: GETGLOBAL R7 K45       ; R7 := 0xb4686125
105 [-]: GETGLOBAL R8 K46       ; R8 := 0xe436cb13
106 [-]: CALL      R5 4 2       ; R5 := R5(R6,R7,R8)
107 [-]: SETTABLE  R4 K44 R5    ; R4["FlareVisibleRangeMaterial"] := R5
108 [-]: GETUPVAL  R4 U5        ; R4 := U5
109 [-]: GETUPVAL  R5 U6        ; R5 := U6
110 [-]: GETTABLE  R5 R5 K48    ; R5 := R5[0x0fcacd1a]
111 [-]: CALL      R5 1 2       ; R5 := R5()
112 [-]: SETTABLE  R4 K47 R5    ; R4["PurchasedItems"] := R5
113 [-]: GETUPVAL  R4 U4        ; R4 := U4
114 [-]: GETTABLE  R4 R4 K49    ; R4 := R4[0x27658fab]
115 [-]: GETGLOBAL R5 K7        ; R5 := 0xae91e43b
116 [-]: GETUPVAL  R6 U5        ; R6 := U5
117 [-]: CALL      R4 3 1       ; R4(R5,R6)
118 [-]: GETUPVAL  R4 U5        ; R4 := U5
119 [-]: CLOSURE   R5 4         ; R5 := closure(Function #5.5)
120 [-]: SETTABLE  R4 K50 R5    ; R4[0xae91e43b] := R5
121 [-]: GETUPVAL  R4 U5        ; R4 := U5
122 [-]: CLOSURE   R5 5         ; R5 := closure(Function #5.6)
123 [-]: SETTABLE  R4 K14 R5    ; R4["CalculateY"] := R5
124 [-]: GETUPVAL  R4 U5        ; R4 := U5
125 [-]: CLOSURE   R5 6         ; R5 := closure(Function #5.7)
126 [-]: GETUPVAL  R0 U4        ; R0 := U4
127 [-]: GETUPVAL  R0 U5        ; R0 := U5
128 [-]: SETTABLE  R4 K11 R5    ; R4["mClipCreatedCallback"] := R5
129 [-]: GETUPVAL  R4 U5        ; R4 := U5
130 [-]: CLOSURE   R5 7         ; R5 := closure(Function #5.8)
131 [-]: MOVE      R0 R2        ; R0 := R2
132 [-]: GETUPVAL  R0 U4        ; R0 := U4
133 [-]: GETUPVAL  R0 U5        ; R0 := U5
134 [-]: SETTABLE  R4 K12 R5    ; R4["mElementDrawCallback"] := R5
135 [-]: RETURN    R0 1         ; return 


; Function #5.1:
;
; Name:            
; Defined at line: 110
; #Upvalues:       4
; #Parameters:     1
; Is_vararg:       0
; Max Stack Size:  9

  1 [-]: GETGLOBAL R1 K0        ; R1 := 0xae91e43b
  2 [-]: SELF      R1 R1 K1     ; R2 := R1; R1 := R1[0xd5181643]
  3 [-]: MOVE      R3 R0        ; R3 := R0
  4 [-]: LOADK     R4 K2        ; R4 := ".Bg"
  5 [-]: CONCAT    R3 R3 R4     ; R3 := R3 .. R4
  6 [-]: GETUPVAL  R4 U0        ; R4 := U0
  7 [-]: CALL      R1 4 1       ; R1(R2,R3,R4)
  8 [-]: GETGLOBAL R1 K0        ; R1 := 0xae91e43b
  9 [-]: SELF      R1 R1 K3     ; R2 := R1; R1 := R1[0x91e13703]
 10 [-]: MOVE      R3 R0        ; R3 := R0
 11 [-]: LOADK     R4 K2        ; R4 := ".Bg"
 12 [-]: CONCAT    R3 R3 R4     ; R3 := R3 .. R4
 13 [-]: LOADK     R4 K4        ; R4 := "RectInnerColor"
 14 [-]: GETUPVAL  R5 U1        ; R5 := U1
 15 [-]: GETTABLE  R5 R5 K5     ; R5 := R5["Background1Object"]
 16 [-]: GETTABLE  R5 R5 K6     ; R5 := R5["r"]
 17 [-]: GETUPVAL  R6 U1        ; R6 := U1
 18 [-]: GETTABLE  R6 R6 K5     ; R6 := R6["Background1Object"]
 19 [-]: GETTABLE  R6 R6 K7     ; R6 := R6["g"]
 20 [-]: GETUPVAL  R7 U1        ; R7 := U1
 21 [-]: GETTABLE  R7 R7 K5     ; R7 := R7["Background1Object"]
 22 [-]: GETTABLE  R7 R7 K8     ; R7 := R7["b"]
 23 [-]: LOADK     R8 K9        ; R8 := 0.700000
 24 [-]: CALL      R1 8 1       ; R1(R2,R3,R4,R5,R6,R7,R8)
 25 [-]: GETGLOBAL R1 K0        ; R1 := 0xae91e43b
 26 [-]: SELF      R1 R1 K3     ; R2 := R1; R1 := R1[0x91e13703]
 27 [-]: MOVE      R3 R0        ; R3 := R0
 28 [-]: LOADK     R4 K2        ; R4 := ".Bg"
 29 [-]: CONCAT    R3 R3 R4     ; R3 := R3 .. R4
 30 [-]: LOADK     R4 K10       ; R4 := "RectEdgeColor"
 31 [-]: GETUPVAL  R5 U1        ; R5 := U1
 32 [-]: GETTABLE  R5 R5 K11    ; R5 := R5["FloatingContentObject"]
 33 [-]: GETTABLE  R5 R5 K6     ; R5 := R5["r"]
 34 [-]: GETUPVAL  R6 U1        ; R6 := U1
 35 [-]: GETTABLE  R6 R6 K11    ; R6 := R6["FloatingContentObject"]
 36 [-]: GETTABLE  R6 R6 K7     ; R6 := R6["g"]
 37 [-]: GETUPVAL  R7 U1        ; R7 := U1
 38 [-]: GETTABLE  R7 R7 K11    ; R7 := R7["FloatingContentObject"]
 39 [-]: GETTABLE  R7 R7 K8     ; R7 := R7["b"]
 40 [-]: LOADK     R8 K12       ; R8 := 0.050000
 41 [-]: CALL      R1 8 1       ; R1(R2,R3,R4,R5,R6,R7,R8)
 42 [-]: GETGLOBAL R1 K0        ; R1 := 0xae91e43b
 43 [-]: SELF      R1 R1 K1     ; R2 := R1; R1 := R1[0xd5181643]
 44 [-]: MOVE      R3 R0        ; R3 := R0
 45 [-]: LOADK     R4 K13       ; R4 := ".ProgressBgIcon"
 46 [-]: CONCAT    R3 R3 R4     ; R3 := R3 .. R4
 47 [-]: GETUPVAL  R4 U2        ; R4 := U2
 48 [-]: GETTABLE  R4 R4 K14    ; R4 := R4[0x06d055f9]
 49 [-]: GETGLOBAL R5 K15       ; R5 := 0x7b998233
 50 [-]: GETUPVAL  R6 U3        ; R6 := U3
 51 [-]: CALL      R5 2 2       ; R5 := R5(R6)
 52 [-]: GETGLOBAL R6 K16       ; R6 := 0x3ff65fe6
 53 [-]: GETGLOBAL R7 K17       ; R7 := 0xe318b932
 54 [-]: CALL      R4 4 0       ; R4,... := R4(R5,R6,R7)
 55 [-]: CALL      R1 0 1       ; R1(R2,...)
 56 [-]: GETGLOBAL R1 K0        ; R1 := 0xae91e43b
 57 [-]: SELF      R1 R1 K18    ; R2 := R1; R1 := R1[0x67bc869f]
 58 [-]: MOVE      R3 R0        ; R3 := R0
 59 [-]: LOADK     R4 K13       ; R4 := ".ProgressBgIcon"
 60 [-]: CONCAT    R3 R3 R4     ; R3 := R3 .. R4
 61 [-]: LOADK     R4 9         ; R4 := 9.000000
 62 [-]: GETUPVAL  R5 U1        ; R5 := U1
 63 [-]: GETTABLE  R5 R5 K19    ; R5 := R5["FloatingContent"]
 64 [-]: CALL      R1 5 1       ; R1(R2,R3,R4,R5)
 65 [-]: GETGLOBAL R1 K0        ; R1 := 0xae91e43b
 66 [-]: SELF      R1 R1 K3     ; R2 := R1; R1 := R1[0x91e13703]
 67 [-]: MOVE      R3 R0        ; R3 := R0
 68 [-]: LOADK     R4 K13       ; R4 := ".ProgressBgIcon"
 69 [-]: CONCAT    R3 R3 R4     ; R3 := R3 .. R4
 70 [-]: LOADK     R4 K20       ; R4 := "RipplesColor"
 71 [-]: GETUPVAL  R5 U1        ; R5 := U1
 72 [-]: GETTABLE  R5 R5 K21    ; R5 := R5["FloatingContentHighlightObject"]
 73 [-]: GETTABLE  R5 R5 K6     ; R5 := R5["r"]
 74 [-]: GETUPVAL  R6 U1        ; R6 := U1
 75 [-]: GETTABLE  R6 R6 K21    ; R6 := R6["FloatingContentHighlightObject"]
 76 [-]: GETTABLE  R6 R6 K7     ; R6 := R6["g"]
 77 [-]: GETUPVAL  R7 U1        ; R7 := U1
 78 [-]: GETTABLE  R7 R7 K21    ; R7 := R7["FloatingContentHighlightObject"]
 79 [-]: GETTABLE  R7 R7 K8     ; R7 := R7["b"]
 80 [-]: LOADK     R8 0         ; R8 := 0.500000
 81 [-]: CALL      R1 8 1       ; R1(R2,R3,R4,R5,R6,R7,R8)
 82 [-]: GETGLOBAL R1 K0        ; R1 := 0xae91e43b
 83 [-]: SELF      R1 R1 K22    ; R2 := R1; R1 := R1[0xf64b7262]
 84 [-]: MOVE      R3 R0        ; R3 := R0
 85 [-]: LOADK     R4 K23       ; R4 := "Progress"
 86 [-]: LOADK     R5 36        ; R5 := 36.000000
 87 [-]: GETUPVAL  R6 U1        ; R6 := U1
 88 [-]: GETTABLE  R6 R6 K19    ; R6 := R6["FloatingContent"]
 89 [-]: CALL      R1 6 1       ; R1(R2,R3,R4,R5,R6)
 90 [-]: GETGLOBAL R1 K0        ; R1 := 0xae91e43b
 91 [-]: SELF      R1 R1 K22    ; R2 := R1; R1 := R1[0xf64b7262]
 92 [-]: MOVE      R3 R0        ; R3 := R0
 93 [-]: LOADK     R4 K24       ; R4 := "Desc"
 94 [-]: LOADK     R5 36        ; R5 := 36.000000
 95 [-]: GETUPVAL  R6 U1        ; R6 := U1
 96 [-]: GETTABLE  R6 R6 K25    ; R6 := R6["FloatingContentHighlight"]
 97 [-]: CALL      R1 6 1       ; R1(R2,R3,R4,R5,R6)
 98 [-]: GETGLOBAL R1 K0        ; R1 := 0xae91e43b
 99 [-]: SELF      R1 R1 K22    ; R2 := R1; R1 := R1[0xf64b7262]
100 [-]: MOVE      R3 R0        ; R3 := R0
101 [-]: LOADK     R4 K26       ; R4 := "Hint"
102 [-]: LOADK     R5 36        ; R5 := 36.000000
103 [-]: GETUPVAL  R6 U1        ; R6 := U1
104 [-]: GETTABLE  R6 R6 K27    ; R6 := R6["Content"]
105 [-]: CALL      R1 6 1       ; R1(R2,R3,R4,R5,R6)
106 [-]: GETGLOBAL R1 K0        ; R1 := 0xae91e43b
107 [-]: SELF      R1 R1 K22    ; R2 := R1; R1 := R1[0xf64b7262]
108 [-]: MOVE      R3 R0        ; R3 := R0
109 [-]: LOADK     R4 K26       ; R4 := "Hint"
110 [-]: LOADK     R5 10        ; R5 := 10.000000
111 [-]: LOADK     R6 80        ; R6 := 80.000000
112 [-]: CALL      R1 6 1       ; R1(R2,R3,R4,R5,R6)
113 [-]: GETGLOBAL R1 K0        ; R1 := 0xae91e43b
114 [-]: SELF      R1 R1 K22    ; R2 := R1; R1 := R1[0xf64b7262]
115 [-]: MOVE      R3 R0        ; R3 := R0
116 [-]: LOADK     R4 K28       ; R4 := "ProgressSeparator"
117 [-]: LOADK     R5 9         ; R5 := 9.000000
118 [-]: GETUPVAL  R6 U1        ; R6 := U1
119 [-]: GETTABLE  R6 R6 K19    ; R6 := R6["FloatingContent"]
120 [-]: CALL      R1 6 1       ; R1(R2,R3,R4,R5,R6)
121 [-]: GETGLOBAL R1 K0        ; R1 := 0xae91e43b
122 [-]: SELF      R1 R1 K18    ; R2 := R1; R1 := R1[0x67bc869f]
123 [-]: MOVE      R3 R0        ; R3 := R0
124 [-]: LOADK     R4 4         ; R4 := 4.000000
125 [-]: LOADK     R5 -40       ; R5 := -40.000000
126 [-]: CALL      R1 5 1       ; R1(R2,R3,R4,R5)
127 [-]: GETGLOBAL R1 K0        ; R1 := 0xae91e43b
128 [-]: SELF      R1 R1 K22    ; R2 := R1; R1 := R1[0xf64b7262]
129 [-]: MOVE      R3 R0        ; R3 := R0
130 [-]: LOADK     R4 K24       ; R4 := "Desc"
131 [-]: LOADK     R5 4         ; R5 := 4.000000
132 [-]: LOADK     R6 -16       ; R6 := -16.000000
133 [-]: CALL      R1 6 1       ; R1(R2,R3,R4,R5,R6)
134 [-]: GETGLOBAL R1 K0        ; R1 := 0xae91e43b
135 [-]: SELF      R1 R1 K22    ; R2 := R1; R1 := R1[0xf64b7262]
136 [-]: MOVE      R3 R0        ; R3 := R0
137 [-]: LOADK     R4 K26       ; R4 := "Hint"
138 [-]: LOADK     R5 4         ; R5 := 4.000000
139 [-]: LOADK     R6 -16       ; R6 := -16.000000
140 [-]: CALL      R1 6 1       ; R1(R2,R3,R4,R5,R6)
141 [-]: GETGLOBAL R1 K0        ; R1 := 0xae91e43b
142 [-]: SELF      R1 R1 K22    ; R2 := R1; R1 := R1[0xf64b7262]
143 [-]: MOVE      R3 R0        ; R3 := R0
144 [-]: LOADK     R4 K23       ; R4 := "Progress"
145 [-]: LOADK     R5 4         ; R5 := 4.000000
146 [-]: LOADK     R6 -16       ; R6 := -16.000000
147 [-]: CALL      R1 6 1       ; R1(R2,R3,R4,R5,R6)
148 [-]: GETGLOBAL R1 K0        ; R1 := 0xae91e43b
149 [-]: SELF      R1 R1 K22    ; R2 := R1; R1 := R1[0xf64b7262]
150 [-]: MOVE      R3 R0        ; R3 := R0
151 [-]: LOADK     R4 K29       ; R4 := "Status"
152 [-]: LOADK     R5 4         ; R5 := 4.000000
153 [-]: LOADK     R6 -16       ; R6 := -16.000000
154 [-]: CALL      R1 6 1       ; R1(R2,R3,R4,R5,R6)
155 [-]: RETURN    R0 1         ; return 


; Function #5.2:
;
; Name:            
; Defined at line: 132
; #Upvalues:       4
; #Parameters:     1
; Is_vararg:       0
; Max Stack Size:  18

  1 [-]: GETTABLE  R1 R0 K0     ; R1 := R0["mClipName"]
  2 [-]: EQ        0 R1 K1      ; if R1 ~= nil then PC := 5
  3 [-]: JMP       5            ; PC := 5
  4 [-]: RETURN    R0 1         ; return 
  5 [-]: GETGLOBAL R1 K2        ; R1 := 0xae91e43b
  6 [-]: SELF      R1 R1 K3     ; R2 := R1; R1 := R1[0x42b04007]
  7 [-]: GETTABLE  R3 R0 K4     ; R3 := R0["Desc"]
  8 [-]: LOADBOOL  R4 1 0       ; R4 := true
  9 [-]: CALL      R1 4 2       ; R1 := R1(R2,R3,R4)
 10 [-]: LOADK     R2 K5        ; R2 := ""
 11 [-]: GETGLOBAL R3 K2        ; R3 := 0xae91e43b
 12 [-]: SELF      R3 R3 K3     ; R4 := R3; R3 := R3[0x42b04007]
 13 [-]: GETTABLE  R5 R0 K6     ; R5 := R0["Hint"]
 14 [-]: LOADBOOL  R6 1 0       ; R6 := true
 15 [-]: NEWTABLE  R7 0 2       ; R7 := {}
 16 [-]: SETTABLE  R7 K7 K5     ; R7["COLOR"] := ""
 17 [-]: SETTABLE  R7 K8 K5     ; R7["NO_COLOR"] := ""
 18 [-]: CALL      R3 5 2       ; R3 := R3(R4,R5,R6,R7)
 19 [-]: LEN       R4 R3        ; R4 := # R3
 20 [-]: LT        0 K9 R4      ; if 0.000000 >= R4 then PC := 33
 21 [-]: JMP       33           ; PC := 33
 22 [-]: GETGLOBAL R4 K10       ; R4 := 0x7f5022cf
 23 [-]: GETTABLE  R4 R4 K11    ; R4 := R4[0x1a94c9cc]
 24 [-]: MOVE      R5 R3        ; R5 := R3
 25 [-]: LOADK     R6 1         ; R6 := 1.000000
 26 [-]: LOADK     R7 1         ; R7 := 1.000000
 27 [-]: CALL      R4 4 2       ; R4 := R4(R5,R6,R7)
 28 [-]: EQ        1 R4 K12     ; if R4 == "/" then PC := 33
 29 [-]: JMP       33           ; PC := 33
 30 [-]: LOADK     R4 K13       ; R4 := "\r\n"
 31 [-]: MOVE      R5 R3        ; R5 := R3
 32 [-]: CONCAT    R2 R4 R5     ; R2 := R4 .. R5
 33 [-]: GETGLOBAL R4 K2        ; R4 := 0xae91e43b
 34 [-]: SELF      R4 R4 K14    ; R5 := R4; R4 := R4[0xe261aa96]
 35 [-]: GETTABLE  R6 R0 K0     ; R6 := R0["mClipName"]
 36 [-]: LOADK     R7 K4        ; R7 := "Desc"
 37 [-]: LOADK     R8 29        ; R8 := 29.000000
 38 [-]: MOVE      R9 R1        ; R9 := R1
 39 [-]: CALL      R4 6 1       ; R4(R5,R6,R7,R8,R9)
 40 [-]: GETGLOBAL R4 K2        ; R4 := 0xae91e43b
 41 [-]: SELF      R4 R4 K14    ; R5 := R4; R4 := R4[0xe261aa96]
 42 [-]: GETTABLE  R6 R0 K0     ; R6 := R0["mClipName"]
 43 [-]: LOADK     R7 K6        ; R7 := "Hint"
 44 [-]: LOADK     R8 29        ; R8 := 29.000000
 45 [-]: MOVE      R9 R2        ; R9 := R2
 46 [-]: CALL      R4 6 1       ; R4(R5,R6,R7,R8,R9)
 47 [-]: GETGLOBAL R4 K2        ; R4 := 0xae91e43b
 48 [-]: SELF      R4 R4 K15    ; R5 := R4; R4 := R4[0x2ce15376]
 49 [-]: GETTABLE  R6 R0 K0     ; R6 := R0["mClipName"]
 50 [-]: LOADK     R7 K4        ; R7 := "Desc"
 51 [-]: LOADK     R8 34        ; R8 := 34.000000
 52 [-]: CALL      R4 5 2       ; R4 := R4(R5,R6,R7,R8)
 53 [-]: GETUPVAL  R5 U0        ; R5 := U0
 54 [-]: GETTABLE  R5 R5 K16    ; R5 := R5[0x06d055f9]
 55 [-]: EQ        1 R2 K5      ; if R2 == "" then PC := 58
 56 [-]: JMP       58           ; PC := 58
 57 [-]: LOADBOOL  R6 0 1       ; R6 := false; PC := 58
 58 [-]: LOADBOOL  R6 1 0       ; R6 := true
 59 [-]: LOADK     R7 4         ; R7 := 4.000000
 60 [-]: GETGLOBAL R8 K2        ; R8 := 0xae91e43b
 61 [-]: SELF      R8 R8 K15    ; R9 := R8; R8 := R8[0x2ce15376]
 62 [-]: GETTABLE  R10 R0 K0    ; R10 := R0["mClipName"]
 63 [-]: LOADK     R11 K6       ; R11 := "Hint"
 64 [-]: LOADK     R12 34       ; R12 := 34.000000
 65 [-]: CALL      R8 5 0       ; R8,... := R8(R9,R10,R11,R12)
 66 [-]: CALL      R5 0 2       ; R5 := R5(R6,...)
 67 [-]: ADD       R6 R4 R5     ; R6 := R4 + R5
 68 [-]: ADD       R6 R6 K17    ; R6 := R6 + 6.000000
 69 [-]: GETGLOBAL R7 K18       ; R7 := 0x5bced4c4
 70 [-]: GETTABLE  R7 R7 K19    ; R7 := R7[0xb62ecfe0]
 71 [-]: MOVE      R8 R6        ; R8 := R6
 72 [-]: LOADK     R9 60        ; R9 := 60.000000
 73 [-]: CALL      R7 3 2       ; R7 := R7(R8,R9)
 74 [-]: ADD       R7 R7 K20    ; R7 := R7 + 16.000000
 75 [-]: ADD       R8 R7 K21    ; R8 := R7 + 10.000000
 76 [-]: GETGLOBAL R9 K2        ; R9 := 0xae91e43b
 77 [-]: SELF      R9 R9 K22    ; R10 := R9; R9 := R9[0xf64b7262]
 78 [-]: GETTABLE  R11 R0 K0    ; R11 := R0["mClipName"]
 79 [-]: LOADK     R12 K4       ; R12 := "Desc"
 80 [-]: LOADK     R13 1        ; R13 := 1.000000
 81 [-]: DIV       R14 R8 K23   ; R14 := R8 / 2.000000
 82 [-]: DIV       R15 R6 K23   ; R15 := R6 / 2.000000
 83 [-]: SUB       R14 R14 R15  ; R14 := R14 - R15
 84 [-]: CALL      R9 6 1       ; R9(R10,R11,R12,R13,R14)
 85 [-]: GETGLOBAL R9 K2        ; R9 := 0xae91e43b
 86 [-]: SELF      R9 R9 K22    ; R10 := R9; R9 := R9[0xf64b7262]
 87 [-]: GETTABLE  R11 R0 K0    ; R11 := R0["mClipName"]
 88 [-]: LOADK     R12 K6       ; R12 := "Hint"
 89 [-]: LOADK     R13 1        ; R13 := 1.000000
 90 [-]: DIV       R14 R8 K23   ; R14 := R8 / 2.000000
 91 [-]: DIV       R15 R6 K23   ; R15 := R6 / 2.000000
 92 [-]: SUB       R14 R14 R15  ; R14 := R14 - R15
 93 [-]: ADD       R14 R14 R4   ; R14 := R14 + R4
 94 [-]: SUB       R14 R14 K21  ; R14 := R14 - 10.000000
 95 [-]: CALL      R9 6 1       ; R9(R10,R11,R12,R13,R14)
 96 [-]: GETGLOBAL R9 K2        ; R9 := 0xae91e43b
 97 [-]: SELF      R9 R9 K22    ; R10 := R9; R9 := R9[0xf64b7262]
 98 [-]: GETTABLE  R11 R0 K0    ; R11 := R0["mClipName"]
 99 [-]: LOADK     R12 K24      ; R12 := "Bg"
100 [-]: LOADK     R13 13       ; R13 := 13.000000
101 [-]: MOVE      R14 R7       ; R14 := R7
102 [-]: CALL      R9 6 1       ; R9(R10,R11,R12,R13,R14)
103 [-]: GETGLOBAL R9 K2        ; R9 := 0xae91e43b
104 [-]: SELF      R9 R9 K22    ; R10 := R9; R9 := R9[0xf64b7262]
105 [-]: GETTABLE  R11 R0 K0    ; R11 := R0["mClipName"]
106 [-]: LOADK     R12 K25      ; R12 := "ProgressBgIconMask"
107 [-]: LOADK     R13 13       ; R13 := 13.000000
108 [-]: SUB       R14 R7 K26   ; R14 := R7 - 4.000000
109 [-]: CALL      R9 6 1       ; R9(R10,R11,R12,R13,R14)
110 [-]: GETGLOBAL R9 K2        ; R9 := 0xae91e43b
111 [-]: SELF      R9 R9 K22    ; R10 := R9; R9 := R9[0xf64b7262]
112 [-]: GETTABLE  R11 R0 K0    ; R11 := R0["mClipName"]
113 [-]: LOADK     R12 K27      ; R12 := "ProgressBgIcon"
114 [-]: LOADK     R13 1        ; R13 := 1.000000
115 [-]: DIV       R14 R7 K23   ; R14 := R7 / 2.000000
116 [-]: SUB       R14 R14 K28  ; R14 := R14 - 108.000000
117 [-]: CALL      R9 6 1       ; R9(R10,R11,R12,R13,R14)
118 [-]: GETGLOBAL R9 K2        ; R9 := 0xae91e43b
119 [-]: SELF      R9 R9 K22    ; R10 := R9; R9 := R9[0xf64b7262]
120 [-]: GETTABLE  R11 R0 K0    ; R11 := R0["mClipName"]
121 [-]: LOADK     R12 K29      ; R12 := "Status"
122 [-]: LOADK     R13 1        ; R13 := 1.000000
123 [-]: DIV       R14 R7 K23   ; R14 := R7 / 2.000000
124 [-]: SUB       R14 R14 K30  ; R14 := R14 - 13.000000
125 [-]: CALL      R9 6 1       ; R9(R10,R11,R12,R13,R14)
126 [-]: GETGLOBAL R9 K2        ; R9 := 0xae91e43b
127 [-]: SELF      R9 R9 K22    ; R10 := R9; R9 := R9[0xf64b7262]
128 [-]: GETTABLE  R11 R0 K0    ; R11 := R0["mClipName"]
129 [-]: LOADK     R12 K31      ; R12 := "Progress"
130 [-]: LOADK     R13 1        ; R13 := 1.000000
131 [-]: DIV       R14 R7 K23   ; R14 := R7 / 2.000000
132 [-]: ADD       R14 R14 K17  ; R14 := R14 + 6.000000
133 [-]: CALL      R9 6 1       ; R9(R10,R11,R12,R13,R14)
134 [-]: GETUPVAL  R9 U1        ; R9 := U1
135 [-]: GETTABLE  R9 R9 K32    ; R9 := R9[0x00fa676f]
136 [-]: GETGLOBAL R10 K2       ; R10 := 0xae91e43b
137 [-]: GETTABLE  R11 R0 K0    ; R11 := R0["mClipName"]
138 [-]: LOADK     R12 K33      ; R12 := ".ProgressSeparator"
139 [-]: CONCAT    R11 R11 R12  ; R11 := R11 .. R12
140 [-]: SUB       R12 R7 K17   ; R12 := R7 - 6.000000
141 [-]: CALL      R9 4 1       ; R9(R10,R11,R12)
142 [-]: GETUPVAL  R9 U0        ; R9 := U0
143 [-]: GETTABLE  R9 R9 K16    ; R9 := R9[0x06d055f9]
144 [-]: GETTABLE  R10 R0 K34   ; R10 := R0["Completed"]
145 [-]: GETTABLE  R11 R0 K35   ; R11 := R0["RequiredCount"]
146 [-]: GETTABLE  R12 R0 K31   ; R12 := R0["Progress"]
147 [-]: CALL      R9 4 2       ; R9 := R9(R10,R11,R12)
148 [-]: GETTABLE  R10 R0 K35   ; R10 := R0["RequiredCount"]
149 [-]: EQ        0 R9 R10     ; if R9 ~= R10 then PC := 200
150 [-]: JMP       200          ; PC := 200
151 [-]: GETGLOBAL R10 K2       ; R10 := 0xae91e43b
152 [-]: SELF      R10 R10 K36  ; R11 := R10; R10 := R10[0xd5181643]
153 [-]: GETTABLE  R12 R0 K0    ; R12 := R0["mClipName"]
154 [-]: LOADK     R13 K37      ; R13 := ".Status"
155 [-]: CONCAT    R12 R12 R13  ; R12 := R12 .. R13
156 [-]: GETUPVAL  R13 U0       ; R13 := U0
157 [-]: GETTABLE  R13 R13 K16  ; R13 := R13[0x06d055f9]
158 [-]: GETGLOBAL R14 K38      ; R14 := 0x7b998233
159 [-]: GETUPVAL  R15 U2       ; R15 := U2
160 [-]: CALL      R14 2 2      ; R14 := R14(R15)
161 [-]: GETGLOBAL R15 K39      ; R15 := 0x3ff65fe6
162 [-]: GETGLOBAL R16 K40      ; R16 := 0xe318b932
163 [-]: CALL      R13 4 0      ; R13,... := R13(R14,R15,R16)
164 [-]: CALL      R10 0 1      ; R10(R11,...)
165 [-]: GETGLOBAL R10 K2       ; R10 := 0xae91e43b
166 [-]: SELF      R10 R10 K41  ; R11 := R10; R10 := R10[0x67bc869f]
167 [-]: GETTABLE  R12 R0 K0    ; R12 := R0["mClipName"]
168 [-]: LOADK     R13 K37      ; R13 := ".Status"
169 [-]: CONCAT    R12 R12 R13  ; R12 := R12 .. R13
170 [-]: LOADK     R13 9        ; R13 := 9.000000
171 [-]: GETUPVAL  R14 U3       ; R14 := U3
172 [-]: GETTABLE  R14 R14 K42  ; R14 := R14["FloatingContentHighlight"]
173 [-]: CALL      R10 5 1      ; R10(R11,R12,R13,R14)
174 [-]: GETGLOBAL R10 K2       ; R10 := 0xae91e43b
175 [-]: SELF      R10 R10 K41  ; R11 := R10; R10 := R10[0x67bc869f]
176 [-]: GETTABLE  R12 R0 K0    ; R12 := R0["mClipName"]
177 [-]: LOADK     R13 K37      ; R13 := ".Status"
178 [-]: CONCAT    R12 R12 R13  ; R12 := R12 .. R13
179 [-]: LOADK     R13 10       ; R13 := 10.000000
180 [-]: LOADK     R14 100      ; R14 := 100.000000
181 [-]: CALL      R10 5 1      ; R10(R11,R12,R13,R14)
182 [-]: GETGLOBAL R10 K2       ; R10 := 0xae91e43b
183 [-]: SELF      R10 R10 K43  ; R11 := R10; R10 := R10[0x91e13703]
184 [-]: GETTABLE  R12 R0 K0    ; R12 := R0["mClipName"]
185 [-]: LOADK     R13 K37      ; R13 := ".Status"
186 [-]: CONCAT    R12 R12 R13  ; R12 := R12 .. R13
187 [-]: LOADK     R13 K44      ; R13 := "RipplesColor"
188 [-]: GETUPVAL  R14 U3       ; R14 := U3
189 [-]: GETTABLE  R14 R14 K45  ; R14 := R14["FloatingContentHighlightObject"]
190 [-]: GETTABLE  R14 R14 K46  ; R14 := R14["r"]
191 [-]: GETUPVAL  R15 U3       ; R15 := U3
192 [-]: GETTABLE  R15 R15 K45  ; R15 := R15["FloatingContentHighlightObject"]
193 [-]: GETTABLE  R15 R15 K47  ; R15 := R15["g"]
194 [-]: GETUPVAL  R16 U3       ; R16 := U3
195 [-]: GETTABLE  R16 R16 K45  ; R16 := R16["FloatingContentHighlightObject"]
196 [-]: GETTABLE  R16 R16 K48  ; R16 := R16["b"]
197 [-]: LOADK     R17 0        ; R17 := 0.500000
198 [-]: CALL      R10 8 1      ; R10(R11,R12,R13,R14,R15,R16,R17)
199 [-]: JMP       217          ; PC := 217
200 [-]: GETGLOBAL R10 K2       ; R10 := 0xae91e43b
201 [-]: SELF      R10 R10 K41  ; R11 := R10; R10 := R10[0x67bc869f]
202 [-]: GETTABLE  R12 R0 K0    ; R12 := R0["mClipName"]
203 [-]: LOADK     R13 K37      ; R13 := ".Status"
204 [-]: CONCAT    R12 R12 R13  ; R12 := R12 .. R13
205 [-]: LOADK     R13 9        ; R13 := 9.000000
206 [-]: GETUPVAL  R14 U3       ; R14 := U3
207 [-]: GETTABLE  R14 R14 K49  ; R14 := R14["FloatingContent"]
208 [-]: CALL      R10 5 1      ; R10(R11,R12,R13,R14)
209 [-]: GETGLOBAL R10 K2       ; R10 := 0xae91e43b
210 [-]: SELF      R10 R10 K41  ; R11 := R10; R10 := R10[0x67bc869f]
211 [-]: GETTABLE  R12 R0 K0    ; R12 := R0["mClipName"]
212 [-]: LOADK     R13 K37      ; R13 := ".Status"
213 [-]: CONCAT    R12 R12 R13  ; R12 := R12 .. R13
214 [-]: LOADK     R13 10       ; R13 := 10.000000
215 [-]: LOADK     R14 20       ; R14 := 20.000000
216 [-]: CALL      R10 5 1      ; R10(R11,R12,R13,R14)
217 [-]: GETGLOBAL R10 K2       ; R10 := 0xae91e43b
218 [-]: SELF      R10 R10 K50  ; R11 := R10; R10 := R10[0xc0a3774b]
219 [-]: GETTABLE  R12 R0 K0    ; R12 := R0["mClipName"]
220 [-]: LOADK     R13 K31      ; R13 := "Progress"
221 [-]: LOADK     R14 46       ; R14 := 46.000000
222 [-]: LOADBOOL  R15 1 0      ; R15 := true
223 [-]: CALL      R10 6 1      ; R10(R11,R12,R13,R14,R15)
224 [-]: GETGLOBAL R10 K2       ; R10 := 0xae91e43b
225 [-]: SELF      R10 R10 K14  ; R11 := R10; R10 := R10[0xe261aa96]
226 [-]: GETTABLE  R12 R0 K0    ; R12 := R0["mClipName"]
227 [-]: LOADK     R13 K31      ; R13 := "Progress"
228 [-]: LOADK     R14 29       ; R14 := 29.000000
229 [-]: MOVE      R15 R9       ; R15 := R9
230 [-]: LOADK     R16 K12      ; R16 := "/"
231 [-]: GETTABLE  R17 R0 K35   ; R17 := R0["RequiredCount"]
232 [-]: CONCAT    R15 R15 R17  ; R15 := R15 .. R16 .. R17
233 [-]: CALL      R10 6 1      ; R10(R11,R12,R13,R14,R15)
234 [-]: RETURN    R0 1         ; return 


; Function #5.3:
;
; Name:            
; Defined at line: 177
; #Upvalues:       0
; #Parameters:     2
; Is_vararg:       0
; Max Stack Size:  13

  1 [-]: LOADK     R2 0         ; R2 := 0.000000
  2 [-]: LOADK     R3 1         ; R3 := 1.000000
  3 [-]: GETTABLE  R4 R0 K0     ; R4 := R0["mElements"]
  4 [-]: LEN       R4 R4        ; R4 := # R4
  5 [-]: LOADK     R5 1         ; R5 := 1.000000
  6 [-]: FORPREP   R3 17        ; R3 -= R5; PC := 17
  7 [-]: GETTABLE  R7 R0 K0     ; R7 := R0["mElements"]
  8 [-]: GETTABLE  R7 R7 R6     ; R7 := R7[R6]
  9 [-]: GETTABLE  R8 R0 K1     ; R8 := R0["mMovie"]
 10 [-]: SELF      R8 R8 K2     ; R9 := R8; R8 := R8[0x2ce15376]
 11 [-]: GETTABLE  R10 R7 K3    ; R10 := R7["mClipName"]
 12 [-]: LOADK     R11 K4       ; R11 := "Bg"
 13 [-]: LOADK     R12 13       ; R12 := 13.000000
 14 [-]: CALL      R8 5 2       ; R8 := R8(R9,R10,R11,R12)
 15 [-]: ADD       R8 R2 R8     ; R8 := R2 + R8
 16 [-]: ADD       R2 R8 K5     ; R2 := R8 + 2.000000
 17 [-]: FORLOOP   R3 7         ; R3 += R5; if R3 <= R4 then begin PC := 7; R6 := R3 end
 18 [-]: RETURN    R2 2         ; return R2
 19 [-]: RETURN    R0 1         ; return 


; Function #5.4:
;
; Name:            
; Defined at line: 188
; #Upvalues:       0
; #Parameters:     2
; Is_vararg:       0
; Max Stack Size:  12

  1 [-]: GETTABLE  R2 R0 K0     ; R2 := R0["mInitialY"]
  2 [-]: LOADK     R3 1         ; R3 := 1.000000
  3 [-]: GETTABLE  R4 R1 K1     ; R4 := R1["Id"]
  4 [-]: SUB       R4 R4 K2     ; R4 := R4 - 1.000000
  5 [-]: LOADK     R5 1         ; R5 := 1.000000
  6 [-]: FORPREP   R3 17        ; R3 -= R5; PC := 17
  7 [-]: GETTABLE  R7 R0 K3     ; R7 := R0["mMovie"]
  8 [-]: SELF      R7 R7 K4     ; R8 := R7; R7 := R7[0x2ce15376]
  9 [-]: GETTABLE  R9 R0 K5     ; R9 := R0["mElements"]
 10 [-]: GETTABLE  R9 R9 R6     ; R9 := R9[R6]
 11 [-]: GETTABLE  R9 R9 K6     ; R9 := R9["mClipName"]
 12 [-]: LOADK     R10 K7       ; R10 := "Bg"
 13 [-]: LOADK     R11 13       ; R11 := 13.000000
 14 [-]: CALL      R7 5 2       ; R7 := R7(R8,R9,R10,R11)
 15 [-]: ADD       R7 R2 R7     ; R7 := R2 + R7
 16 [-]: ADD       R2 R7 K8     ; R2 := R7 + 2.000000
 17 [-]: FORLOOP   R3 7         ; R3 += R5; if R3 <= R4 then begin PC := 7; R6 := R3 end
 18 [-]: RETURN    R2 2         ; return R2
 19 [-]: RETURN    R0 1         ; return 


; Function #5.5:
;
; Name:            
; Defined at line: 219
; #Upvalues:       0
; #Parameters:     2
; Is_vararg:       0
; Max Stack Size:  7

  1 [-]: SELF      R2 R0 K0     ; R3 := R0; R2 := R0[0x5fbddc1a]
  2 [-]: CALL      R2 2 2       ; R2 := R2(R3)
  3 [-]: LOADK     R3 0         ; R3 := 0.000000
  4 [-]: LE        0 R2 K1      ; if R2 > 3.000000 then PC := 16
  5 [-]: JMP       16           ; PC := 16
  6 [-]: GETTABLE  R4 R0 K2     ; R4 := R0["mInitialX"]
  7 [-]: GETTABLE  R5 R1 K3     ; R5 := R1["mIndex"]
  8 [-]: SUB       R5 R5 K4     ; R5 := R5 - 1.000000
  9 [-]: GETTABLE  R6 R0 K5     ; R6 := R0["mColumnSeparation"]
 10 [-]: MUL       R5 R5 R6     ; R5 := R5 * R6
 11 [-]: ADD       R4 R4 R5     ; R4 := R4 + R5
 12 [-]: SUB       R5 K6 R2     ; R5 := 4.000000 - R2
 13 [-]: MUL       R5 R5 K7     ; R5 := R5 * 71.000000
 14 [-]: ADD       R3 R4 R5     ; R3 := R4 + R5
 15 [-]: JMP       22           ; PC := 22
 16 [-]: GETTABLE  R4 R0 K2     ; R4 := R0["mInitialX"]
 17 [-]: GETTABLE  R5 R1 K3     ; R5 := R1["mIndex"]
 18 [-]: SUB       R5 R5 K4     ; R5 := R5 - 1.000000
 19 [-]: GETTABLE  R6 R0 K5     ; R6 := R0["mColumnSeparation"]
 20 [-]: MUL       R5 R5 R6     ; R5 := R5 * R6
 21 [-]: ADD       R3 R4 R5     ; R3 := R4 + R5
 22 [-]: RETURN    R3 2         ; return R3
 23 [-]: RETURN    R0 1         ; return 


; Function #5.6:
;
; Name:            
; Defined at line: 230
; #Upvalues:       0
; #Parameters:     2
; Is_vararg:       0
; Max Stack Size:  3

  1 [-]: GETTABLE  R2 R0 K0     ; R2 := R0["mInitialY"]
  2 [-]: RETURN    R2 2         ; return R2
  3 [-]: RETURN    R0 1         ; return 


; Function #5.7:
;
; Name:            
; Defined at line: 234
; #Upvalues:       2
; #Parameters:     1
; Is_vararg:       0
; Max Stack Size:  6

  1 [-]: GETUPVAL  R1 U0        ; R1 := U0
  2 [-]: GETTABLE  R1 R1 K0     ; R1 := R1[0xbf9f30a4]
  3 [-]: GETGLOBAL R2 K1        ; R2 := 0xae91e43b
  4 [-]: GETUPVAL  R3 U1        ; R3 := U1
  5 [-]: MOVE      R4 R0        ; R4 := R0
  6 [-]: CALL      R1 4 1       ; R1(R2,R3,R4)
  7 [-]: GETGLOBAL R1 K1        ; R1 := 0xae91e43b
  8 [-]: SELF      R1 R1 K2     ; R2 := R1; R1 := R1[0x67bc869f]
  9 [-]: MOVE      R3 R0        ; R3 := R0
 10 [-]: LOADK     R4 4         ; R4 := 4.000000
 11 [-]: LOADK     R5 -35       ; R5 := -35.000000
 12 [-]: CALL      R1 5 1       ; R1(R2,R3,R4,R5)
 13 [-]: RETURN    R0 1         ; return 


; Function #5.8:
;
; Name:            
; Defined at line: 239
; #Upvalues:       3
; #Parameters:     1
; Is_vararg:       0
; Max Stack Size:  7

  1 [-]: EQ        1 R0 K0      ; if R0 == nil then PC := 6
  2 [-]: JMP       6            ; PC := 6
  3 [-]: GETTABLE  R1 R0 K1     ; R1 := R0["mClipName"]
  4 [-]: EQ        0 R1 K0      ; if R1 ~= nil then PC := 7
  5 [-]: JMP       7            ; PC := 7
  6 [-]: RETURN    R0 1         ; return 
  7 [-]: NEWTABLE  R1 0 6       ; R1 := {}
  8 [-]: SETTABLE  R1 K2 K3     ; R1["HideCountThreshold"] := 0.000000
  9 [-]: SETTABLE  R1 K4 K5     ; R1["HideOwned"] := true
 10 [-]: SETTABLE  R1 K6 K5     ; R1["HidePrice"] := true
 11 [-]: SETTABLE  R1 K7 K5     ; R1["DisableSaturation"] := true
 12 [-]: GETTABLE  R2 R0 K8     ; R2 := R0["NameOverride"]
 13 [-]: SETTABLE  R1 K8 R2     ; R1["NameOverride"] := R2
 14 [-]: GETUPVAL  R2 U0        ; R2 := U0
 15 [-]: SETTABLE  R1 K9 R2     ; R1["DepthTest"] := R2
 16 [-]: GETUPVAL  R2 U1        ; R2 := U1
 17 [-]: GETTABLE  R2 R2 K10    ; R2 := R2[0xc339daf7]
 18 [-]: GETGLOBAL R3 K11       ; R3 := 0xae91e43b
 19 [-]: GETUPVAL  R4 U2        ; R4 := U2
 20 [-]: MOVE      R5 R0        ; R5 := R0
 21 [-]: MOVE      R6 R1        ; R6 := R1
 22 [-]: CALL      R2 5 1       ; R2(R3,R4,R5,R6)
 23 [-]: RETURN    R0 1         ; return 


; Function #6:
;
; Name:            
; Defined at line: 250
; #Upvalues:       4
; #Parameters:     0
; Is_vararg:       0
; Max Stack Size:  41

  1 [-]: NEWTABLE  R0 8 0       ; R0 := {}
  2 [-]: GETGLOBAL R1 K0        ; R1 := 0xf60baa1f
  3 [-]: GETGLOBAL R2 K1        ; R2 := 0xb3da39c4
  4 [-]: GETGLOBAL R3 K2        ; R3 := 0xc3c874b4
  5 [-]: GETGLOBAL R4 K3        ; R4 := 0xb4686125
  6 [-]: GETGLOBAL R5 K4        ; R5 := 0x9741db59
  7 [-]: GETGLOBAL R6 K5        ; R6 := 0x76fb6f6c
  8 [-]: GETGLOBAL R7 K6        ; R7 := 0x1518ebbc
  9 [-]: GETGLOBAL R8 K7        ; R8 := 0xe436cb13
 10 [-]: SETLIST   R0 8 1       ; R0[(1-1)*FPF+i] := R(0+i), 1 <= i <= 8
 11 [-]: GETGLOBAL R1 K8        ; R1 := 0xcfc01047
 12 [-]: GETGLOBAL R2 K9        ; R2 := 0x0032441c
 13 [-]: GETTABLE  R2 R2 K10    ; R2 := R2["UIMaterial_Mods"]
 14 [-]: CALL      R1 2 4       ; R1,R2,R3 := R1(R2)
 15 [-]: JMP       27           ; PC := 27
 16 [-]: GETGLOBAL R6 K8        ; R6 := 0xcfc01047
 17 [-]: MOVE      R7 R5        ; R7 := R5
 18 [-]: CALL      R6 2 4       ; R6,R7,R8 := R6(R7)
 19 [-]: JMP       25           ; PC := 25
 20 [-]: GETGLOBAL R11 K11      ; R11 := 0x33bdd652
 21 [-]: GETTABLE  R11 R11 K12  ; R11 := R11[0x23d5322f]
 22 [-]: MOVE      R12 R0       ; R12 := R0
 23 [-]: MOVE      R13 R10      ; R13 := R10
 24 [-]: CALL      R11 3 1      ; R11(R12,R13)
 25 [-]: TFORLOOP  R6 2         ; R9,R10 :=  R6(R7,R8); if R9 ~= nil then begin PC = 20; R8 := R9 end
 26 [-]: JMP       20           ; PC := 20
 27 [-]: TFORLOOP  R1 2         ; R4,R5 :=  R1(R2,R3); if R4 ~= nil then begin PC = 16; R3 := R4 end
 28 [-]: JMP       16           ; PC := 16
 29 [-]: GETGLOBAL R11 K8       ; R11 := 0xcfc01047
 30 [-]: GETGLOBAL R12 K9       ; R12 := 0x0032441c
 31 [-]: GETTABLE  R12 R12 K13  ; R12 := R12["UIMaterial_ModsSyndicateIcons"]
 32 [-]: CALL      R11 2 4      ; R11,R12,R13 := R11(R12)
 33 [-]: JMP       45           ; PC := 45
 34 [-]: GETGLOBAL R16 K8       ; R16 := 0xcfc01047
 35 [-]: MOVE      R17 R15      ; R17 := R15
 36 [-]: CALL      R16 2 4      ; R16,R17,R18 := R16(R17)
 37 [-]: JMP       43           ; PC := 43
 38 [-]: GETGLOBAL R21 K11      ; R21 := 0x33bdd652
 39 [-]: GETTABLE  R21 R21 K12  ; R21 := R21[0x23d5322f]
 40 [-]: MOVE      R22 R0       ; R22 := R0
 41 [-]: MOVE      R23 R20      ; R23 := R20
 42 [-]: CALL      R21 3 1      ; R21(R22,R23)
 43 [-]: TFORLOOP  R16 2        ; R19,R20 :=  R16(R17,R18); if R19 ~= nil then begin PC = 38; R18 := R19 end
 44 [-]: JMP       38           ; PC := 38
 45 [-]: TFORLOOP  R11 2        ; R14,R15 :=  R11(R12,R13); if R14 ~= nil then begin PC = 34; R13 := R14 end
 46 [-]: JMP       34           ; PC := 34
 47 [-]: GETGLOBAL R21 K8       ; R21 := 0xcfc01047
 48 [-]: GETGLOBAL R22 K9       ; R22 := 0x0032441c
 49 [-]: GETTABLE  R22 R22 K14  ; R22 := R22["UIMaterial_CosmeticEnhancersStoreHorizontal"]
 50 [-]: CALL      R21 2 4      ; R21,R22,R23 := R21(R22)
 51 [-]: JMP       57           ; PC := 57
 52 [-]: GETGLOBAL R26 K11      ; R26 := 0x33bdd652
 53 [-]: GETTABLE  R26 R26 K12  ; R26 := R26[0x23d5322f]
 54 [-]: MOVE      R27 R0       ; R27 := R0
 55 [-]: MOVE      R28 R25      ; R28 := R25
 56 [-]: CALL      R26 3 1      ; R26(R27,R28)
 57 [-]: TFORLOOP  R21 2        ; R24,R25 :=  R21(R22,R23); if R24 ~= nil then begin PC = 52; R23 := R24 end
 58 [-]: JMP       52           ; PC := 52
 59 [-]: LOADBOOL  R26 0 0      ; R26 := false
 60 [-]: GETGLOBAL R27 K15      ; R27 := 0x7b998233
 61 [-]: GETUPVAL  R28 U0       ; R28 := U0
 62 [-]: CALL      R27 2 2      ; R27 := R27(R28)
 63 [-]: TEST      R27 1        ; if R27 then PC := 71
 64 [-]: JMP       71           ; PC := 71
 65 [-]: GETUPVAL  R27 U0       ; R27 := U0
 66 [-]: SELF      R27 R27 K16  ; R28 := R27; R27 := R27[0x5fbddc1a]
 67 [-]: CALL      R27 2 2      ; R27 := R27(R28)
 68 [-]: LE        0 K17 R27    ; if 4.000000 > R27 then PC := 71
 69 [-]: JMP       71           ; PC := 71
 70 [-]: LOADBOOL  R26 1 0      ; R26 := true
 71 [-]: GETUPVAL  R27 U1       ; R27 := U1
 72 [-]: GETUPVAL  R28 U2       ; R28 := U2
 73 [-]: GETTABLE  R28 R28 K18  ; R28 := R28[0x06d055f9]
 74 [-]: MOVE      R29 R26      ; R29 := R26
 75 [-]: LOADK     R30 -100     ; R30 := -100.000000
 76 [-]: LOADK     R31 0        ; R31 := 0.000000
 77 [-]: CALL      R28 4 2      ; R28 := R28(R29,R30,R31)
 78 [-]: ADD       R27 R27 R28  ; R27 := R27 + R28
 79 [-]: GETUPVAL  R28 U3       ; R28 := U3
 80 [-]: GETUPVAL  R29 U2       ; R29 := U2
 81 [-]: GETTABLE  R29 R29 K19  ; R29 := R29[0xe5e5a417]
 82 [-]: GETGLOBAL R30 K20      ; R30 := 0xae91e43b
 83 [-]: MOVE      R31 R28      ; R31 := R28
 84 [-]: LOADBOOL  R32 1 0      ; R32 := true
 85 [-]: CALL      R29 4 2      ; R29 := R29(R30,R31,R32)
 86 [-]: GETUPVAL  R30 U2       ; R30 := U2
 87 [-]: GETTABLE  R30 R30 K21  ; R30 := R30[0xd718f59b]
 88 [-]: GETGLOBAL R31 K20      ; R31 := 0xae91e43b
 89 [-]: MOVE      R32 R27      ; R32 := R27
 90 [-]: LOADBOOL  R33 1 0      ; R33 := true
 91 [-]: CALL      R30 4 2      ; R30 := R30(R31,R32,R33)
 92 [-]: GETUPVAL  R31 U2       ; R31 := U2
 93 [-]: GETTABLE  R31 R31 K22  ; R31 := R31[0x0db7934d]
 94 [-]: GETGLOBAL R32 K20      ; R32 := 0xae91e43b
 95 [-]: GETUPVAL  R33 U2       ; R33 := U2
 96 [-]: GETTABLE  R33 R33 K18  ; R33 := R33[0x06d055f9]
 97 [-]: MOVE      R34 R26      ; R34 := R26
 98 [-]: LOADK     R35 26       ; R35 := 26.000000
 99 [-]: LOADK     R36 0        ; R36 := 0.000000
100 [-]: CALL      R33 4 0      ; R33,... := R33(R34,R35,R36)
101 [-]: CALL      R31 0 2      ; R31 := R31(R32,...)
102 [-]: GETGLOBAL R32 K8       ; R32 := 0xcfc01047
103 [-]: MOVE      R33 R0       ; R33 := R0
104 [-]: CALL      R32 2 4      ; R32,R33,R34 := R32(R33)
105 [-]: JMP       121          ; PC := 121
106 [-]: SELF      R37 R36 K23  ; R38 := R36; R37 := R36[0x830eea67]
107 [-]: GETGLOBAL R39 K24      ; R39 := 0x6c97a788
108 [-]: GETTABLE  R39 R39 K25  ; R39 := R39["VISIBILITY_CENTER"]
109 [-]: MOVE      R40 R29      ; R40 := R29
110 [-]: CALL      R37 4 1      ; R37(R38,R39,R40)
111 [-]: SELF      R37 R36 K23  ; R38 := R36; R37 := R36[0x830eea67]
112 [-]: GETGLOBAL R39 K24      ; R39 := 0x6c97a788
113 [-]: GETTABLE  R39 R39 K26  ; R39 := R39["VISIBILITY_SIZE"]
114 [-]: MOVE      R40 R30      ; R40 := R30
115 [-]: CALL      R37 4 1      ; R37(R38,R39,R40)
116 [-]: SELF      R37 R36 K23  ; R38 := R36; R37 := R36[0x830eea67]
117 [-]: GETGLOBAL R39 K24      ; R39 := 0x6c97a788
118 [-]: GETTABLE  R39 R39 K27  ; R39 := R39["VISIBILITY_FADE_SIZE"]
119 [-]: MOVE      R40 R31      ; R40 := R31
120 [-]: CALL      R37 4 1      ; R37(R38,R39,R40)
121 [-]: TFORLOOP  R32 2        ; R35,R36 :=  R32(R33,R34); if R35 ~= nil then begin PC = 106; R34 := R35 end
122 [-]: JMP       106          ; PC := 106
123 [-]: RETURN    R0 1         ; return 


; Function #7:
;
; Name:            
; Defined at line: 287
; #Upvalues:       5
; #Parameters:     0
; Is_vararg:       0
; Max Stack Size:  9

  1 [-]: GETGLOBAL R0 K0        ; R0 := 0x25312c9b
  2 [-]: GETGLOBAL R1 K1        ; R1 := 0xae91e43b
  3 [-]: LOADK     R2 K2        ; R2 := "Junction.Rewards.RewardGrid"
  4 [-]: LOADK     R3 0         ; R3 := 0.000000
  5 [-]: NEWTABLE  R4 1 0       ; R4 := {}
  6 [-]: LOADK     R5 0         ; R5 := 0.000000
  7 [-]: SETLIST   R4 1 1       ; R4[(1-1)*FPF+i] := R(4+i), 1 <= i <= 1
  8 [-]: NEWTABLE  R5 1 0       ; R5 := {}
  9 [-]: GETUPVAL  R6 U0        ; R6 := U0
 10 [-]: SETLIST   R5 1 1       ; R5[(1-1)*FPF+i] := R(5+i), 1 <= i <= 1
 11 [-]: GETUPVAL  R6 U1        ; R6 := U1
 12 [-]: GETUPVAL  R7 U2        ; R7 := U2
 13 [-]: CLOSURE   R8 0         ; R8 := closure(Function #7.1)
 14 [-]: GETUPVAL  R0 U2        ; R0 := U2
 15 [-]: GETUPVAL  R0 U3        ; R0 := U3
 16 [-]: GETUPVAL  R0 U4        ; R0 := U4
 17 [-]: CALL      R0 9 1       ; R0(R1,R2,R3,R4,R5,R6,R7,R8)
 18 [-]: RETURN    R0 1         ; return 


; Function #7.1:
;
; Name:            
; Defined at line: 289
; #Upvalues:       3
; #Parameters:     0
; Is_vararg:       0
; Max Stack Size:  9

  1 [-]: GETGLOBAL R0 K0        ; R0 := 0x25312c9b
  2 [-]: GETGLOBAL R1 K1        ; R1 := 0xae91e43b
  3 [-]: LOADK     R2 K2        ; R2 := "Junction.Rewards.RewardGrid"
  4 [-]: LOADK     R3 0         ; R3 := 0.000000
  5 [-]: NEWTABLE  R4 1 0       ; R4 := {}
  6 [-]: LOADK     R5 10        ; R5 := 10.000000
  7 [-]: SETLIST   R4 1 1       ; R4[(1-1)*FPF+i] := R(4+i), 1 <= i <= 1
  8 [-]: NEWTABLE  R5 1 0       ; R5 := {}
  9 [-]: LOADK     R6 0         ; R6 := 0.000000
 10 [-]: SETLIST   R5 1 1       ; R5[(1-1)*FPF+i] := R(5+i), 1 <= i <= 1
 11 [-]: LOADK     R6 0         ; R6 := 0.500000
 12 [-]: GETUPVAL  R7 U0        ; R7 := U0
 13 [-]: CLOSURE   R8 0         ; R8 := closure(Function #7.1.1)
 14 [-]: GETUPVAL  R0 U1        ; R0 := U1
 15 [-]: GETUPVAL  R0 U2        ; R0 := U2
 16 [-]: CALL      R0 9 1       ; R0(R1,R2,R3,R4,R5,R6,R7,R8)
 17 [-]: RETURN    R0 1         ; return 


; Function #7.1.1:
;
; Name:            
; Defined at line: 291
; #Upvalues:       2
; #Parameters:     0
; Is_vararg:       0
; Max Stack Size:  9

  1 [-]: GETGLOBAL R0 K0        ; R0 := 0xae91e43b
  2 [-]: SELF      R0 R0 K1     ; R1 := R0; R0 := R0[0x67bc869f]
  3 [-]: LOADK     R2 K2        ; R2 := "Junction.Rewards.RewardGrid"
  4 [-]: LOADK     R3 0         ; R3 := 0.000000
  5 [-]: GETUPVAL  R4 U0        ; R4 := U0
  6 [-]: CALL      R0 5 1       ; R0(R1,R2,R3,R4)
  7 [-]: GETGLOBAL R0 K3        ; R0 := 0x25312c9b
  8 [-]: GETGLOBAL R1 K0        ; R1 := 0xae91e43b
  9 [-]: LOADK     R2 K2        ; R2 := "Junction.Rewards.RewardGrid"
 10 [-]: LOADK     R3 0         ; R3 := 0.000000
 11 [-]: NEWTABLE  R4 1 0       ; R4 := {}
 12 [-]: LOADK     R5 10        ; R5 := 10.000000
 13 [-]: SETLIST   R4 1 1       ; R4[(1-1)*FPF+i] := R(4+i), 1 <= i <= 1
 14 [-]: NEWTABLE  R5 1 0       ; R5 := {}
 15 [-]: LOADK     R6 100       ; R6 := 100.000000
 16 [-]: SETLIST   R5 1 1       ; R5[(1-1)*FPF+i] := R(5+i), 1 <= i <= 1
 17 [-]: LOADK     R6 0         ; R6 := 0.500000
 18 [-]: LOADK     R7 K5        ; R7 := 0.100000
 19 [-]: CLOSURE   R8 0         ; R8 := closure(Function #7.1.1.1)
 20 [-]: GETUPVAL  R0 U1        ; R0 := U1
 21 [-]: CALL      R0 9 1       ; R0(R1,R2,R3,R4,R5,R6,R7,R8)
 22 [-]: RETURN    R0 1         ; return 


; Function #7.1.1.1:
;
; Name:            
; Defined at line: 294
; #Upvalues:       1
; #Parameters:     0
; Is_vararg:       0
; Max Stack Size:  2

  1 [-]: LOADBOOL  R0 1 0       ; R0 := true
  2 [-]: SETUPVAL  R0 U0        ; U82 := R0
  3 [-]: RETURN    R0 1         ; return 


; Function #8:
;
; Name:            
; Defined at line: 301
; #Upvalues:       14
; #Parameters:     0
; Is_vararg:       0
; Max Stack Size:  58

  1 [-]: NEWTABLE  R1 0 0       ; R1 := {}
  2 [-]: LOADK     R2 K0        ; R2 := ""
  3 [-]: LOADK     R3 K1        ; R3 := "/Lotus/Language/Junction/RegionDesc"
  4 [-]: LOADBOOL  R4 0 0       ; R4 := false
  5 [-]: GETGLOBAL R5 K2        ; R5 := _T
  6 [-]: GETTABLE  R5 R5 K3     ; R5 := R5["JunctionTasksUIRadialSector"]
  7 [-]: TEST      R5 0         ; if not R5 then PC := 12
  8 [-]: JMP       12           ; PC := 12
  9 [-]: GETGLOBAL R5 K2        ; R5 := _T
 10 [-]: GETTABLE  R0 R5 K3     ; R0 := R5["JunctionTasksUIRadialSector"]
 11 [-]: JMP       20           ; PC := 20
 12 [-]: GETUPVAL  R5 U0        ; R5 := U0
 13 [-]: SELF      R5 R5 K4     ; R6 := R5; R5 := R5[0x3ad9ed31]
 14 [-]: GETGLOBAL R7 K5        ; R7 := 0xbe190284
 15 [-]: SELF      R7 R7 K6     ; R8 := R7; R7 := R7[0xef893aec]
 16 [-]: CALL      R7 2 2       ; R7 := R7(R8)
 17 [-]: GETTABLE  R7 R7 K7     ; R7 := R7["location"]
 18 [-]: CALL      R5 3 2       ; R5 := R5(R6,R7)
 19 [-]: MOVE      R0 R5        ; R0 := R5
 20 [-]: GETGLOBAL R5 K8        ; R5 := 0x603636ad
 21 [-]: GETTABLE  R6 R0 K9     ; R6 := R0["locTag"]
 22 [-]: SELF      R6 R6 K10    ; R7 := R6; R6 := R6[0x6d604ba7]
 23 [-]: CALL      R6 2 2       ; R6 := R6(R7)
 24 [-]: LOADNIL   R7 R7        ; R7 := nil
 25 [-]: CALL      R5 3 2       ; R5 := R5(R6,R7)
 26 [-]: MOVE      R2 R5        ; R2 := R5
 27 [-]: GETTABLE  R5 R0 K11    ; R5 := R0["mission"]
 28 [-]: GETTABLE  R1 R0 K12    ; R1 := R0["challenges"]
 29 [-]: GETGLOBAL R6 K13       ; R6 := 0x7b998233
 30 [-]: MOVE      R7 R1        ; R7 := R1
 31 [-]: CALL      R6 2 2       ; R6 := R6(R7)
 32 [-]: TEST      R6 1         ; if R6 then PC := 40
 33 [-]: JMP       40           ; PC := 40
 34 [-]: GETGLOBAL R6 K13       ; R6 := 0x7b998233
 35 [-]: GETGLOBAL R7 K2        ; R7 := _T
 36 [-]: GETTABLE  R7 R7 K14    ; R7 := R7["JunctionTasksRelayReconstruction"]
 37 [-]: CALL      R6 2 2       ; R6 := R6(R7)
 38 [-]: TEST      R6 1         ; if R6 then PC := 87
 39 [-]: JMP       87           ; PC := 87
 40 [-]: NEWTABLE  R6 0 0       ; R6 := {}
 41 [-]: NEWTABLE  R7 0 0       ; R7 := {}
 42 [-]: MOVE      R1 R7        ; R1 := R7
 43 [-]: GETGLOBAL R7 K13       ; R7 := 0x7b998233
 44 [-]: GETGLOBAL R8 K2        ; R8 := _T
 45 [-]: GETTABLE  R8 R8 K14    ; R8 := R8["JunctionTasksRelayReconstruction"]
 46 [-]: CALL      R7 2 2       ; R7 := R7(R8)
 47 [-]: TEST      R7 1         ; if R7 then PC := 53
 48 [-]: JMP       53           ; PC := 53
 49 [-]: GETGLOBAL R7 K2        ; R7 := _T
 50 [-]: GETTABLE  R7 R7 K14    ; R7 := R7["JunctionTasksRelayReconstruction"]
 51 [-]: GETTABLE  R6 R7 K15    ; R6 := R7["mTasks"]
 52 [-]: JMP       69           ; PC := 69
 53 [-]: GETGLOBAL R7 K2        ; R7 := _T
 54 [-]: GETTABLE  R7 R7 K16    ; R7 := R7["CachedConstructionProjects"]
 55 [-]: LOADK     R8 1         ; R8 := 1.000000
 56 [-]: LEN       R9 R7        ; R9 := # R7
 57 [-]: LOADK     R10 1        ; R10 := 1.000000
 58 [-]: FORPREP   R8 68        ; R8 -= R10; PC := 68
 59 [-]: GETTABLE  R12 R7 R11   ; R12 := R7[R11]
 60 [-]: GETTABLE  R12 R12 K17  ; R12 := R12["rebuildNode"]
 61 [-]: GETTABLE  R13 R0 K18   ; R13 := R0["name"]
 62 [-]: EQ        0 R12 R13    ; if R12 ~= R13 then PC := 68
 63 [-]: JMP       68           ; PC := 68
 64 [-]: GETTABLE  R13 R7 R11   ; R13 := R7[R11]
 65 [-]: GETTABLE  R13 R13 K19  ; R13 := R13["info"]
 66 [-]: GETTABLE  R6 R13 K15   ; R6 := R13["mTasks"]
 67 [-]: JMP       69           ; PC := 69
 68 [-]: FORLOOP   R8 59        ; R8 += R10; if R8 <= R9 then begin PC := 59; R11 := R8 end
 69 [-]: LEN       R13 R6       ; R13 := # R6
 70 [-]: LT        0 K20 R13    ; if 0.000000 >= R13 then PC := 74
 71 [-]: JMP       74           ; PC := 74
 72 [-]: LOADBOOL  R4 1 0       ; R4 := true
 73 [-]: LOADK     R3 K21       ; R3 := "/Lotus/Language/Junction/RelayReconDesc"
 74 [-]: GETGLOBAL R13 K22      ; R13 := 0xc8802016
 75 [-]: MOVE      R14 R6       ; R14 := R6
 76 [-]: CALL      R13 2 4      ; R13,R14,R15 := R13(R14)
 77 [-]: JMP       85           ; PC := 85
 78 [-]: GETGLOBAL R18 K23      ; R18 := 0x33bdd652
 79 [-]: GETTABLE  R18 R18 K24  ; R18 := R18[0x23d5322f]
 80 [-]: MOVE      R19 R1       ; R19 := R1
 81 [-]: GETGLOBAL R20 K25      ; R20 := 0xb009bbc6
 82 [-]: MOVE      R21 R17      ; R21 := R17
 83 [-]: CALL      R20 2 0      ; R20,... := R20(R21)
 84 [-]: CALL      R18 0 1      ; R18(R19,...)
 85 [-]: TFORLOOP  R13 2        ; R16,R17 :=  R13(R14,R15); if R16 ~= nil then begin PC = 78; R15 := R16 end
 86 [-]: JMP       78           ; PC := 78
 87 [-]: GETUPVAL  R18 U1       ; R18 := U1
 88 [-]: GETTABLE  R18 R18 K26  ; R18 := R18[0xda041955]
 89 [-]: GETTABLE  R19 R5 K27   ; R19 := R5["missionReward"]
 90 [-]: CALL      R18 2 2      ; R18 := R18(R19)
 91 [-]: GETUPVAL  R19 U2       ; R19 := U2
 92 [-]: SELF      R19 R19 K28  ; R20 := R19; R19 := R19[0x7c09c373]
 93 [-]: LOADBOOL  R21 1 0      ; R21 := true
 94 [-]: LOADBOOL  R22 1 0      ; R22 := true
 95 [-]: CALL      R19 4 1      ; R19(R20,R21,R22)
 96 [-]: LOADK     R19 1        ; R19 := 1.000000
 97 [-]: LEN       R20 R18      ; R20 := # R18
 98 [-]: LOADK     R21 1        ; R21 := 1.000000
 99 [-]: FORPREP   R19 159      ; R19 -= R21; PC := 159
100 [-]: LOADNIL   R23 R23      ; R23 := nil
101 [-]: GETGLOBAL R24 K13      ; R24 := 0x7b998233
102 [-]: GETTABLE  R25 R18 R22  ; R25 := R18[R22]
103 [-]: GETTABLE  R25 R25 K29  ; R25 := R25["StoreItem"]
104 [-]: CALL      R24 2 2      ; R24 := R24(R25)
105 [-]: TEST      R24 1        ; if R24 then PC := 117
106 [-]: JMP       117          ; PC := 117
107 [-]: GETUPVAL  R24 U3       ; R24 := U3
108 [-]: GETTABLE  R24 R24 K30  ; R24 := R24[0x08681f50]
109 [-]: GETGLOBAL R25 K31      ; R25 := 0xae91e43b
110 [-]: GETTABLE  R26 R18 R22  ; R26 := R18[R22]
111 [-]: GETTABLE  R26 R26 K29  ; R26 := R26["StoreItem"]
112 [-]: LOADNIL   R27 R29      ; R27 := R28 := R29 := nil
113 [-]: LOADBOOL  R30 1 0      ; R30 := true
114 [-]: CALL      R24 7 2      ; R24 := R24(R25,R26,R27,R28,R29,R30)
115 [-]: MOVE      R23 R24      ; R23 := R24
116 [-]: JMP       147          ; PC := 147
117 [-]: GETGLOBAL R24 K13      ; R24 := 0x7b998233
118 [-]: GETTABLE  R25 R18 R22  ; R25 := R18[R22]
119 [-]: GETTABLE  R25 R25 K32  ; R25 := R25["ItemType"]
120 [-]: CALL      R24 2 2      ; R24 := R24(R25)
121 [-]: TEST      R24 1        ; if R24 then PC := 133
122 [-]: JMP       133          ; PC := 133
123 [-]: GETUPVAL  R24 U3       ; R24 := U3
124 [-]: GETTABLE  R24 R24 K33  ; R24 := R24[0x4eec6d11]
125 [-]: GETGLOBAL R25 K31      ; R25 := 0xae91e43b
126 [-]: GETTABLE  R26 R18 R22  ; R26 := R18[R22]
127 [-]: GETTABLE  R26 R26 K32  ; R26 := R26["ItemType"]
128 [-]: LOADNIL   R27 R27      ; R27 := nil
129 [-]: LOADBOOL  R28 1 0      ; R28 := true
130 [-]: CALL      R24 5 2      ; R24 := R24(R25,R26,R27,R28)
131 [-]: MOVE      R23 R24      ; R23 := R24
132 [-]: JMP       147          ; PC := 147
133 [-]: GETGLOBAL R24 K13      ; R24 := 0x7b998233
134 [-]: GETTABLE  R25 R18 R22  ; R25 := R18[R22]
135 [-]: GETTABLE  R25 R25 K34  ; R25 := R25["Icon"]
136 [-]: CALL      R24 2 2      ; R24 := R24(R25)
137 [-]: TEST      R24 1        ; if R24 then PC := 147
138 [-]: JMP       147          ; PC := 147
139 [-]: NEWTABLE  R24 0 2      ; R24 := {}
140 [-]: GETTABLE  R25 R18 R22  ; R25 := R18[R22]
141 [-]: GETTABLE  R25 R25 K34  ; R25 := R25["Icon"]
142 [-]: SETTABLE  R24 K34 R25  ; R24["Icon"] := R25
143 [-]: GETTABLE  R25 R18 R22  ; R25 := R18[R22]
144 [-]: GETTABLE  R25 R25 K35  ; R25 := R25["Themed"]
145 [-]: SETTABLE  R24 K35 R25  ; R24["Themed"] := R25
146 [-]: MOVE      R23 R24      ; R23 := R24
147 [-]: EQ        1 R23 K36    ; if R23 == nil then PC := 159
148 [-]: JMP       159          ; PC := 159
149 [-]: GETTABLE  R24 R18 R22  ; R24 := R18[R22]
150 [-]: GETTABLE  R24 R24 K37  ; R24 := R24["NameOverride"]
151 [-]: SETTABLE  R23 K37 R24  ; R23["NameOverride"] := R24
152 [-]: GETTABLE  R24 R18 R22  ; R24 := R18[R22]
153 [-]: GETTABLE  R24 R24 K38  ; R24 := R24["SkipTitleCase"]
154 [-]: SETTABLE  R23 K38 R24  ; R23["SkipTitleCase"] := R24
155 [-]: GETUPVAL  R24 U2       ; R24 := U2
156 [-]: SELF      R24 R24 K39  ; R25 := R24; R24 := R24[0xbad4316f]
157 [-]: MOVE      R26 R23      ; R26 := R23
158 [-]: CALL      R24 3 1      ; R24(R25,R26)
159 [-]: FORLOOP   R19 100      ; R19 += R21; if R19 <= R20 then begin PC := 100; R22 := R19 end
160 [-]: GETUPVAL  R24 U2       ; R24 := U2
161 [-]: SELF      R24 R24 K40  ; R25 := R24; R24 := R24[0x71e9ac81]
162 [-]: LOADNIL   R26 R26      ; R26 := nil
163 [-]: LOADBOOL  R27 1 0      ; R27 := true
164 [-]: LOADBOOL  R28 1 0      ; R28 := true
165 [-]: CALL      R24 5 1      ; R24(R25,R26,R27,R28)
166 [-]: GETUPVAL  R24 U2       ; R24 := U2
167 [-]: SELF      R24 R24 K41  ; R25 := R24; R24 := R24[0x5fbddc1a]
168 [-]: CALL      R24 2 2      ; R24 := R24(R25)
169 [-]: GETGLOBAL R25 K31      ; R25 := 0xae91e43b
170 [-]: SELF      R25 R25 K42  ; R26 := R25; R25 := R25[0x5f56eeab]
171 [-]: LOADK     R27 K43      ; R27 := "Junction.Rewards.Header.RewardCount"
172 [-]: LOADK     R28 29       ; R28 := 29.000000
173 [-]: MOVE      R29 R24      ; R29 := R24
174 [-]: CALL      R25 5 1      ; R25(R26,R27,R28,R29)
175 [-]: LT        1 K44 R24    ; if 3.000000 < R24 then PC := 178
176 [-]: JMP       178          ; PC := 178
177 [-]: LOADBOOL  R25 0 1      ; R25 := false; PC := 178
178 [-]: LOADBOOL  R25 1 0      ; R25 := true
179 [-]: SETUPVAL  R25 U4       ; U82 := R4
180 [-]: GETUPVAL  R25 U4       ; R25 := U4
181 [-]: TEST      R25 0        ; if not R25 then PC := 199
182 [-]: JMP       199          ; PC := 199
183 [-]: GETUPVAL  R25 U6       ; R25 := U6
184 [-]: SUB       R26 R24 K45  ; R26 := R24 - 4.000000
185 [-]: GETUPVAL  R27 U2       ; R27 := U2
186 [-]: GETTABLE  R27 R27 K46  ; R27 := R27["ElementDimBuffer"]
187 [-]: GETUPVAL  R28 U2       ; R28 := U2
188 [-]: GETTABLE  R28 R28 K47  ; R28 := R28["ElementWidth"]
189 [-]: ADD       R27 R27 R28  ; R27 := R27 + R28
190 [-]: MUL       R26 R26 R27  ; R26 := R26 * R27
191 [-]: SUB       R25 R25 R26  ; R25 := R25 - R26
192 [-]: SUB       R25 R25 K48  ; R25 := R25 - 22.000000
193 [-]: SETUPVAL  R25 U5       ; U82 := R5
194 [-]: SUB       R25 R24 K49  ; R25 := R24 - 3.800000
195 [-]: MUL       R25 R25 K50  ; R25 := R25 * 2.000000
196 [-]: SETUPVAL  R25 U7       ; U82 := R7
197 [-]: LOADBOOL  R25 1 0      ; R25 := true
198 [-]: SETUPVAL  R25 U8       ; U82 := R8
199 [-]: GETGLOBAL R25 K31      ; R25 := 0xae91e43b
200 [-]: SELF      R25 R25 K51  ; R26 := R25; R25 := R25[0xaade900e]
201 [-]: LOADK     R27 K52      ; R27 := "Junction.Rewards.BgLineLeft"
202 [-]: LOADK     R28 11       ; R28 := 11.000000
203 [-]: LT        0 K20 R24    ; if 0.000000 >= R24 then PC := 207
204 [-]: JMP       207          ; PC := 207
205 [-]: LT        1 R24 K45    ; if R24 < 4.000000 then PC := 208
206 [-]: JMP       208          ; PC := 208
207 [-]: LOADBOOL  R29 0 1      ; R29 := false; PC := 208
208 [-]: LOADBOOL  R29 1 0      ; R29 := true
209 [-]: CALL      R25 5 1      ; R25(R26,R27,R28,R29)
210 [-]: GETGLOBAL R25 K31      ; R25 := 0xae91e43b
211 [-]: SELF      R25 R25 K51  ; R26 := R25; R25 := R25[0xaade900e]
212 [-]: LOADK     R27 K53      ; R27 := "Junction.Rewards.BgLineRight"
213 [-]: LOADK     R28 11       ; R28 := 11.000000
214 [-]: LT        0 K20 R24    ; if 0.000000 >= R24 then PC := 218
215 [-]: JMP       218          ; PC := 218
216 [-]: LT        1 R24 K45    ; if R24 < 4.000000 then PC := 219
217 [-]: JMP       219          ; PC := 219
218 [-]: LOADBOOL  R29 0 1      ; R29 := false; PC := 219
219 [-]: LOADBOOL  R29 1 0      ; R29 := true
220 [-]: CALL      R25 5 1      ; R25(R26,R27,R28,R29)
221 [-]: GETUPVAL  R25 U9       ; R25 := U9
222 [-]: CALL      R25 1 1      ; R25()
223 [-]: GETGLOBAL R25 K31      ; R25 := 0xae91e43b
224 [-]: SELF      R25 R25 K51  ; R26 := R25; R25 := R25[0xaade900e]
225 [-]: LOADK     R27 K54      ; R27 := "Junction.Rewards"
226 [-]: LOADK     R28 11       ; R28 := 11.000000
227 [-]: TEST      R4 1         ; if R4 then PC := 231
228 [-]: JMP       231          ; PC := 231
229 [-]: LT        1 K20 R24    ; if 0.000000 < R24 then PC := 232
230 [-]: JMP       232          ; PC := 232
231 [-]: LOADBOOL  R29 0 1      ; R29 := false; PC := 232
232 [-]: LOADBOOL  R29 1 0      ; R29 := true
233 [-]: CALL      R25 5 1      ; R25(R26,R27,R28,R29)
234 [-]: GETGLOBAL R25 K31      ; R25 := 0xae91e43b
235 [-]: SELF      R25 R25 K42  ; R26 := R25; R25 := R25[0x5f56eeab]
236 [-]: LOADK     R27 K55      ; R27 := "Junction.JunctionName"
237 [-]: LOADK     R28 38       ; R28 := 38.000000
238 [-]: LOADK     R29 K56      ; R29 := "center"
239 [-]: CALL      R25 5 1      ; R25(R26,R27,R28,R29)
240 [-]: GETGLOBAL R25 K31      ; R25 := 0xae91e43b
241 [-]: SELF      R25 R25 K57  ; R26 := R25; R25 := R25[0x20b98db3]
242 [-]: LOADK     R27 K58      ; R27 := "Junction.JunctionName.text"
243 [-]: GETGLOBAL R28 K59      ; R28 := 0x7f5022cf
244 [-]: GETTABLE  R28 R28 K60  ; R28 := R28[0x3f3e4d12]
245 [-]: MOVE      R29 R2       ; R29 := R2
246 [-]: CALL      R28 2 0      ; R28,... := R28(R29)
247 [-]: CALL      R25 0 1      ; R25(R26,...)
248 [-]: GETGLOBAL R25 K31      ; R25 := 0xae91e43b
249 [-]: SELF      R25 R25 K61  ; R26 := R25; R25 := R25[0x91a24e4b]
250 [-]: LOADK     R27 K55      ; R27 := "Junction.JunctionName"
251 [-]: LOADK     R28 33       ; R28 := 33.000000
252 [-]: CALL      R25 4 2      ; R25 := R25(R26,R27,R28)
253 [-]: GETGLOBAL R26 K31      ; R26 := 0xae91e43b
254 [-]: SELF      R26 R26 K61  ; R27 := R26; R26 := R26[0x91a24e4b]
255 [-]: LOADK     R28 K62      ; R28 := "Junction.JunctionIcon"
256 [-]: LOADK     R29 12       ; R29 := 12.000000
257 [-]: CALL      R26 4 2      ; R26 := R26(R27,R28,R29)
258 [-]: SUB       R26 R26 K63  ; R26 := R26 - 10.000000
259 [-]: GETGLOBAL R27 K31      ; R27 := 0xae91e43b
260 [-]: SELF      R27 R27 K61  ; R28 := R27; R27 := R27[0x91a24e4b]
261 [-]: LOADK     R29 K64      ; R29 := "Junction.Bg"
262 [-]: LOADK     R30 0        ; R30 := 0.000000
263 [-]: CALL      R27 4 2      ; R27 := R27(R28,R29,R30)
264 [-]: GETGLOBAL R28 K31      ; R28 := 0xae91e43b
265 [-]: SELF      R28 R28 K65  ; R29 := R28; R28 := R28[0x67bc869f]
266 [-]: LOADK     R30 K55      ; R30 := "Junction.JunctionName"
267 [-]: LOADK     R31 0        ; R31 := 0.000000
268 [-]: DIV       R32 R25 K50  ; R32 := R25 / 2.000000
269 [-]: SUB       R32 R27 R32  ; R32 := R27 - R32
270 [-]: DIV       R33 R26 K50  ; R33 := R26 / 2.000000
271 [-]: ADD       R32 R32 R33  ; R32 := R32 + R33
272 [-]: ADD       R32 R32 K66  ; R32 := R32 + 5.000000
273 [-]: CALL      R28 5 1      ; R28(R29,R30,R31,R32)
274 [-]: GETGLOBAL R28 K31      ; R28 := 0xae91e43b
275 [-]: SELF      R28 R28 K65  ; R29 := R28; R28 := R28[0x67bc869f]
276 [-]: LOADK     R30 K62      ; R30 := "Junction.JunctionIcon"
277 [-]: LOADK     R31 0        ; R31 := 0.000000
278 [-]: DIV       R32 R25 K50  ; R32 := R25 / 2.000000
279 [-]: SUB       R32 R27 R32  ; R32 := R27 - R32
280 [-]: SUB       R32 R32 K66  ; R32 := R32 - 5.000000
281 [-]: CALL      R28 5 1      ; R28(R29,R30,R31,R32)
282 [-]: GETGLOBAL R28 K31      ; R28 := 0xae91e43b
283 [-]: SELF      R28 R28 K42  ; R29 := R28; R28 := R28[0x5f56eeab]
284 [-]: LOADK     R30 K67      ; R30 := "Junction.JunctionDesc"
285 [-]: LOADK     R31 38       ; R31 := 38.000000
286 [-]: LOADK     R32 K56      ; R32 := "center"
287 [-]: CALL      R28 5 1      ; R28(R29,R30,R31,R32)
288 [-]: GETGLOBAL R28 K31      ; R28 := 0xae91e43b
289 [-]: SELF      R28 R28 K57  ; R29 := R28; R28 := R28[0x20b98db3]
290 [-]: LOADK     R30 K68      ; R30 := "Junction.JunctionDesc.text"
291 [-]: MOVE      R31 R3       ; R31 := R3
292 [-]: CALL      R28 4 1      ; R28(R29,R30,R31)
293 [-]: GETGLOBAL R28 K31      ; R28 := 0xae91e43b
294 [-]: SELF      R28 R28 K69  ; R29 := R28; R28 := R28[0x1cb415c1]
295 [-]: LOADK     R30 K62      ; R30 := "Junction.JunctionIcon"
296 [-]: GETGLOBAL R31 K70      ; R31 := 0x926c1cf3
297 [-]: CALL      R28 4 1      ; R28(R29,R30,R31)
298 [-]: GETUPVAL  R28 U10      ; R28 := U10
299 [-]: GETTABLE  R28 R28 K71  ; R28 := R28[0x00fa676f]
300 [-]: GETGLOBAL R29 K31      ; R29 := 0xae91e43b
301 [-]: LOADK     R30 K72      ; R30 := "Junction.TitleSeparator"
302 [-]: LOADK     R31 563      ; R31 := 563.000000
303 [-]: CALL      R28 4 1      ; R28(R29,R30,R31)
304 [-]: GETUPVAL  R28 U11      ; R28 := U11
305 [-]: SELF      R28 R28 K28  ; R29 := R28; R28 := R28[0x7c09c373]
306 [-]: LOADBOOL  R30 1 0      ; R30 := true
307 [-]: LOADBOOL  R31 1 0      ; R31 := true
308 [-]: CALL      R28 4 1      ; R28(R29,R30,R31)
309 [-]: LOADK     R28 0        ; R28 := 0.000000
310 [-]: LOADK     R29 0        ; R29 := 0.000000
311 [-]: LOADK     R30 1        ; R30 := 1.000000
312 [-]: LEN       R31 R1       ; R31 := # R1
313 [-]: LOADK     R32 1        ; R32 := 1.000000
314 [-]: FORPREP   R30 426      ; R30 -= R32; PC := 426
315 [-]: GETTABLE  R34 R1 R33   ; R34 := R1[R33]
316 [-]: SELF      R34 R34 K73  ; R35 := R34; R34 := R34[0x38a90c33]
317 [-]: CALL      R34 2 2      ; R34 := R34(R35)
318 [-]: LEN       R35 R34      ; R35 := # R34
319 [-]: EQ        0 R35 K20    ; if R35 ~= 0.000000 then PC := 426
320 [-]: JMP       426          ; PC := 426
321 [-]: ADD       R29 R29 K74  ; R29 := R29 + 1.000000
322 [-]: LOADBOOL  R35 1 0      ; R35 := true
323 [-]: GETTABLE  R36 R1 R33   ; R36 := R1[R33]
324 [-]: SELF      R36 R36 K75  ; R37 := R36; R36 := R36[0x4077a684]
325 [-]: CALL      R36 2 2      ; R36 := R36(R37)
326 [-]: GETGLOBAL R37 K76      ; R37 := 0xcfc01047
327 [-]: MOVE      R38 R36      ; R38 := R36
328 [-]: CALL      R37 2 4      ; R37,R38,R39 := R37(R38)
329 [-]: JMP       341          ; PC := 341
330 [-]: GETGLOBAL R42 K77      ; R42 := 0xba7dfcd2
331 [-]: SELF      R42 R42 K78  ; R43 := R42; R42 := R42[0xd87c0114]
332 [-]: SELF      R44 R41 K79  ; R45 := R41; R44 := R41[0xe223e2b1]
333 [-]: CALL      R44 2 0      ; R44,... := R44(R45)
334 [-]: CALL      R42 0 2      ; R42 := R42(R43,...)
335 [-]: SELF      R43 R41 K80  ; R44 := R41; R43 := R41[0x2f5d21d2]
336 [-]: CALL      R43 2 2      ; R43 := R43(R44)
337 [-]: LT        0 R42 R43    ; if R42 >= R43 then PC := 341
338 [-]: JMP       341          ; PC := 341
339 [-]: LOADBOOL  R35 0 0      ; R35 := false
340 [-]: JMP       343          ; PC := 343
341 [-]: TFORLOOP  R37 2        ; R40,R41 :=  R37(R38,R39); if R40 ~= nil then begin PC = 330; R39 := R40 end
342 [-]: JMP       330          ; PC := 330
343 [-]: TEST      R35 0        ; if not R35 then PC := 426
344 [-]: JMP       426          ; PC := 426
345 [-]: GETTABLE  R42 R1 R33   ; R42 := R1[R33]
346 [-]: SELF      R42 R42 K79  ; R43 := R42; R42 := R42[0xe223e2b1]
347 [-]: CALL      R42 2 2      ; R42 := R42(R43)
348 [-]: GETGLOBAL R43 K77      ; R43 := 0xba7dfcd2
349 [-]: SELF      R43 R43 K78  ; R44 := R43; R43 := R43[0xd87c0114]
350 [-]: MOVE      R45 R42      ; R45 := R42
351 [-]: CALL      R43 3 2      ; R43 := R43(R44,R45)
352 [-]: GETTABLE  R44 R1 R33   ; R44 := R1[R33]
353 [-]: SELF      R44 R44 K80  ; R45 := R44; R44 := R44[0x2f5d21d2]
354 [-]: CALL      R44 2 2      ; R44 := R44(R45)
355 [-]: LE        1 R44 R43    ; if R44 <= R43 then PC := 358
356 [-]: JMP       358          ; PC := 358
357 [-]: LOADBOOL  R45 0 1      ; R45 := false; PC := 358
358 [-]: LOADBOOL  R45 1 0      ; R45 := true
359 [-]: GETUPVAL  R46 U12      ; R46 := U12
360 [-]: GETTABLE  R46 R46 K81  ; R46 := R46[0x06d055f9]
361 [-]: MOVE      R47 R45      ; R47 := R45
362 [-]: ADD       R48 R28 K74  ; R48 := R28 + 1.000000
363 [-]: MOVE      R49 R28      ; R49 := R28
364 [-]: CALL      R46 4 2      ; R46 := R46(R47,R48,R49)
365 [-]: MOVE      R28 R46      ; R28 := R46
366 [-]: LOADK     R46 K82      ; R46 := "/Lotus/Language/Challenges/Challenge_"
367 [-]: MOVE      R47 R42      ; R47 := R42
368 [-]: LOADK     R48 K83      ; R48 := "_Hint"
369 [-]: CONCAT    R46 R46 R48  ; R46 := R46 .. R47 .. R48
370 [-]: GETGLOBAL R47 K31      ; R47 := 0xae91e43b
371 [-]: SELF      R47 R47 K84  ; R48 := R47; R47 := R47[0x42b04007]
372 [-]: MOVE      R49 R46      ; R49 := R46
373 [-]: LOADBOOL  R50 0 0      ; R50 := false
374 [-]: CALL      R47 4 2      ; R47 := R47(R48,R49,R50)
375 [-]: LEN       R48 R47      ; R48 := # R47
376 [-]: EQ        1 R48 K20    ; if R48 == 0.000000 then PC := 386
377 [-]: JMP       386          ; PC := 386
378 [-]: GETGLOBAL R48 K59      ; R48 := 0x7f5022cf
379 [-]: GETTABLE  R48 R48 K85  ; R48 := R48[0x1a94c9cc]
380 [-]: MOVE      R49 R47      ; R49 := R47
381 [-]: LOADK     R50 1        ; R50 := 1.000000
382 [-]: LOADK     R51 1        ; R51 := 1.000000
383 [-]: CALL      R48 4 2      ; R48 := R48(R49,R50,R51)
384 [-]: EQ        0 R48 K86    ; if R48 ~= "/" then PC := 412
385 [-]: JMP       412          ; PC := 412
386 [-]: LOADK     R48 K82      ; R48 := "/Lotus/Language/Challenges/Challenge_"
387 [-]: GETGLOBAL R49 K59      ; R49 := 0x7f5022cf
388 [-]: GETTABLE  R49 R49 K85  ; R49 := R49[0x1a94c9cc]
389 [-]: MOVE      R50 R42      ; R50 := R42
390 [-]: LOADK     R51 3        ; R51 := 3.000000
391 [-]: CALL      R49 3 2      ; R49 := R49(R50,R51)
392 [-]: LOADK     R50 K83      ; R50 := "_Hint"
393 [-]: CONCAT    R48 R48 R50  ; R48 := R48 .. R49 .. R50
394 [-]: GETGLOBAL R49 K31      ; R49 := 0xae91e43b
395 [-]: SELF      R49 R49 K84  ; R50 := R49; R49 := R49[0x42b04007]
396 [-]: MOVE      R51 R48      ; R51 := R48
397 [-]: LOADBOOL  R52 0 0      ; R52 := false
398 [-]: CALL      R49 4 2      ; R49 := R49(R50,R51,R52)
399 [-]: MOVE      R47 R49      ; R47 := R49
400 [-]: LEN       R49 R47      ; R49 := # R47
401 [-]: LT        0 K20 R49    ; if 0.000000 >= R49 then PC := 412
402 [-]: JMP       412          ; PC := 412
403 [-]: GETGLOBAL R49 K59      ; R49 := 0x7f5022cf
404 [-]: GETTABLE  R49 R49 K85  ; R49 := R49[0x1a94c9cc]
405 [-]: MOVE      R50 R47      ; R50 := R47
406 [-]: LOADK     R51 1        ; R51 := 1.000000
407 [-]: LOADK     R52 1        ; R52 := 1.000000
408 [-]: CALL      R49 4 2      ; R49 := R49(R50,R51,R52)
409 [-]: EQ        1 R49 K86    ; if R49 == "/" then PC := 412
410 [-]: JMP       412          ; PC := 412
411 [-]: MOVE      R46 R48      ; R46 := R48
412 [-]: GETUPVAL  R49 U11      ; R49 := U11
413 [-]: SELF      R49 R49 K39  ; R50 := R49; R49 := R49[0xbad4316f]
414 [-]: NEWTABLE  R51 0 5      ; R51 := {}
415 [-]: LOADK     R52 K82      ; R52 := "/Lotus/Language/Challenges/Challenge_"
416 [-]: MOVE      R53 R42      ; R53 := R42
417 [-]: LOADK     R54 K88      ; R54 := "_Name"
418 [-]: CONCAT    R52 R52 R54  ; R52 := R52 .. R53 .. R54
419 [-]: SETTABLE  R51 K87 R52  ; R51["Desc"] := R52
420 [-]: SETTABLE  R51 K89 R43  ; R51["Progress"] := R43
421 [-]: SETTABLE  R51 K90 R44  ; R51["RequiredCount"] := R44
422 [-]: SETTABLE  R51 K91 R45  ; R51["Completed"] := R45
423 [-]: SETTABLE  R51 K92 R46  ; R51["Hint"] := R46
424 [-]: LOADBOOL  R52 1 0      ; R52 := true
425 [-]: CALL      R49 4 1      ; R49(R50,R51,R52)
426 [-]: FORLOOP   R30 315      ; R30 += R32; if R30 <= R31 then begin PC := 315; R33 := R30 end
427 [-]: LE        1 R29 R28    ; if R29 <= R28 then PC := 432
428 [-]: JMP       432          ; PC := 432
429 [-]: LOADBOOL  R49 0 0      ; R49 := false
430 [-]: TEST      R49 0        ; if not R49 then PC := 434
431 [-]: JMP       434          ; PC := 434
432 [-]: LOADBOOL  R49 1 0      ; R49 := true
433 [-]: SETUPVAL  R49 U13      ; U82 := R13
434 [-]: GETUPVAL  R49 U13      ; R49 := U13
435 [-]: TEST      R49 0        ; if not R49 then PC := 451
436 [-]: JMP       451          ; PC := 451
437 [-]: GETGLOBAL R49 K93      ; R49 := 0x89326c93
438 [-]: SELF      R49 R49 K94  ; R50 := R49; R49 := R49[0x46a0ebf5]
439 [-]: GETGLOBAL R51 K95      ; R51 := 0x0469f296
440 [-]: LOADK     R52 K96      ; R52 := "JunctionTasksComplete"
441 [-]: CALL      R51 2 0      ; R51,... := R51(R52)
442 [-]: CALL      R49 0 2      ; R49 := R49(R50,...)
443 [-]: GETGLOBAL R50 K13      ; R50 := 0x7b998233
444 [-]: MOVE      R51 R49      ; R51 := R49
445 [-]: CALL      R50 2 2      ; R50 := R50(R51)
446 [-]: TEST      R50 1        ; if R50 then PC := 451
447 [-]: JMP       451          ; PC := 451
448 [-]: SELF      R50 R49 K97  ; R51 := R49; R50 := R49[0x8eb2112d]
449 [-]: LOADK     R52 K98      ; R52 := "TriggerPort"
450 [-]: CALL      R50 3 1      ; R50(R51,R52)
451 [-]: GETUPVAL  R50 U11      ; R50 := U11
452 [-]: SELF      R50 R50 K40  ; R51 := R50; R50 := R50[0x71e9ac81]
453 [-]: LOADNIL   R52 R53      ; R52 := R53 := nil
454 [-]: LOADBOOL  R54 1 0      ; R54 := true
455 [-]: CALL      R50 5 1      ; R50(R51,R52,R53,R54)
456 [-]: GETGLOBAL R50 K31      ; R50 := 0xae91e43b
457 [-]: SELF      R50 R50 K61  ; R51 := R50; R50 := R50[0x91a24e4b]
458 [-]: LOADK     R52 K99      ; R52 := "Junction.MissionTaskList"
459 [-]: LOADK     R53 1        ; R53 := 1.000000
460 [-]: CALL      R50 4 2      ; R50 := R50(R51,R52,R53)
461 [-]: GETUPVAL  R51 U11      ; R51 := U11
462 [-]: SELF      R51 R51 K100 ; R52 := R51; R51 := R51[0xf95e8229]
463 [-]: CALL      R51 2 2      ; R51 := R51(R52)
464 [-]: GETGLOBAL R52 K31      ; R52 := 0xae91e43b
465 [-]: SELF      R52 R52 K65  ; R53 := R52; R52 := R52[0x67bc869f]
466 [-]: LOADK     R54 K54      ; R54 := "Junction.Rewards"
467 [-]: LOADK     R55 1        ; R55 := 1.000000
468 [-]: ADD       R56 R50 R51  ; R56 := R50 + R51
469 [-]: SUB       R56 R56 K101 ; R56 := R56 - 6.000000
470 [-]: CALL      R52 5 1      ; R52(R53,R54,R55,R56)
471 [-]: ADD       R52 R50 R51  ; R52 := R50 + R51
472 [-]: GETUPVAL  R53 U2       ; R53 := U2
473 [-]: GETTABLE  R53 R53 K102 ; R53 := R53["Height"]
474 [-]: ADD       R52 R52 R53  ; R52 := R52 + R53
475 [-]: ADD       R52 R52 K103 ; R52 := R52 + 42.000000
476 [-]: GETGLOBAL R53 K31      ; R53 := 0xae91e43b
477 [-]: SELF      R53 R53 K65  ; R54 := R53; R53 := R53[0x67bc869f]
478 [-]: LOADK     R55 K64      ; R55 := "Junction.Bg"
479 [-]: LOADK     R56 13       ; R56 := 13.000000
480 [-]: ADD       R57 R52 K66  ; R57 := R52 + 5.000000
481 [-]: CALL      R53 5 1      ; R53(R54,R55,R56,R57)
482 [-]: GETGLOBAL R53 K31      ; R53 := 0xae91e43b
483 [-]: SELF      R53 R53 K65  ; R54 := R53; R53 := R53[0x67bc869f]
484 [-]: LOADK     R55 K104     ; R55 := "Junction.Blurer"
485 [-]: LOADK     R56 13       ; R56 := 13.000000
486 [-]: MOVE      R57 R52      ; R57 := R52
487 [-]: CALL      R53 5 1      ; R53(R54,R55,R56,R57)
488 [-]: RETURN    R0 1         ; return 


; Function #9:
;
; Name:            
; Defined at line: 465
; #Upvalues:       4
; #Parameters:     0
; Is_vararg:       0
; Max Stack Size:  5

  1 [-]: GETGLOBAL R0 K0        ; R0 := 0xae91e43b
  2 [-]: SELF      R0 R0 K1     ; R1 := R0; R0 := R0[0x91a24e4b]
  3 [-]: LOADK     R2 K2        ; R2 := "Junction.Bg"
  4 [-]: LOADK     R3 12        ; R3 := 12.000000
  5 [-]: CALL      R0 4 2       ; R0 := R0(R1,R2,R3)
  6 [-]: SETUPVAL  R0 U0        ; U82 := R0
  7 [-]: GETUPVAL  R0 U2        ; R0 := U2
  8 [-]: GETTABLE  R0 R0 K3     ; R0 := R0[0x06d055f9]
  9 [-]: GETUPVAL  R1 U3        ; R1 := U3
 10 [-]: GETGLOBAL R2 K0        ; R2 := 0xae91e43b
 11 [-]: SELF      R2 R2 K4     ; R3 := R2; R2 := R2[0x091c120e]
 12 [-]: CALL      R2 2 2       ; R2 := R2(R3)
 13 [-]: GETUPVAL  R3 U0        ; R3 := U0
 14 [-]: DIV       R3 R3 K5     ; R3 := R3 / 2.000000
 15 [-]: ADD       R3 R3 K6     ; R3 := R3 + 80.000000
 16 [-]: SUB       R2 R2 R3     ; R2 := R2 - R3
 17 [-]: GETUPVAL  R3 U0        ; R3 := U0
 18 [-]: DIV       R3 R3 K5     ; R3 := R3 / 2.000000
 19 [-]: ADD       R3 R3 K6     ; R3 := R3 + 80.000000
 20 [-]: CALL      R0 4 2       ; R0 := R0(R1,R2,R3)
 21 [-]: SETUPVAL  R0 U1        ; U82 := R1
 22 [-]: GETGLOBAL R0 K0        ; R0 := 0xae91e43b
 23 [-]: SELF      R0 R0 K7     ; R1 := R0; R0 := R0[0x67bc869f]
 24 [-]: LOADK     R2 K8        ; R2 := "Junction"
 25 [-]: LOADK     R3 0         ; R3 := 0.000000
 26 [-]: GETUPVAL  R4 U1        ; R4 := U1
 27 [-]: CALL      R0 5 1       ; R0(R1,R2,R3,R4)
 28 [-]: RETURN    R0 1         ; return 


; Function #10:
;
; Name:            
; Defined at line: 472
; #Upvalues:       8
; #Parameters:     0
; Is_vararg:       0
; Max Stack Size:  12

  1 [-]: GETGLOBAL R0 K0        ; R0 := 0x3d106989
  2 [-]: LOADK     R1 K1        ; R1 := "JunctionTasks initialize"
  3 [-]: CALL      R0 2 1       ; R0(R1)
  4 [-]: GETUPVAL  R0 U1        ; R0 := U1
  5 [-]: GETTABLE  R0 R0 K2     ; R0 := R0[0x5e35d4d6]
  6 [-]: CALL      R0 1 2       ; R0 := R0()
  7 [-]: SETUPVAL  R0 U0        ; U82 := R0
  8 [-]: GETGLOBAL R0 K3        ; R0 := 0xae91e43b
  9 [-]: SELF      R0 R0 K4     ; R1 := R0; R0 := R0[0x67bc869f]
 10 [-]: LOADK     R2 K5        ; R2 := "Junction.JunctionIcon"
 11 [-]: LOADK     R3 4         ; R3 := 4.000000
 12 [-]: LOADK     R4 -60       ; R4 := -60.000000
 13 [-]: CALL      R0 5 1       ; R0(R1,R2,R3,R4)
 14 [-]: GETGLOBAL R0 K3        ; R0 := 0xae91e43b
 15 [-]: SELF      R0 R0 K4     ; R1 := R0; R0 := R0[0x67bc869f]
 16 [-]: LOADK     R2 K6        ; R2 := "Junction.JunctionName"
 17 [-]: LOADK     R3 4         ; R3 := 4.000000
 18 [-]: LOADK     R4 -60       ; R4 := -60.000000
 19 [-]: CALL      R0 5 1       ; R0(R1,R2,R3,R4)
 20 [-]: GETGLOBAL R0 K3        ; R0 := 0xae91e43b
 21 [-]: SELF      R0 R0 K4     ; R1 := R0; R0 := R0[0x67bc869f]
 22 [-]: LOADK     R2 K7        ; R2 := "Junction.JunctionDesc"
 23 [-]: LOADK     R3 4         ; R3 := 4.000000
 24 [-]: LOADK     R4 -30       ; R4 := -30.000000
 25 [-]: CALL      R0 5 1       ; R0(R1,R2,R3,R4)
 26 [-]: GETGLOBAL R0 K3        ; R0 := 0xae91e43b
 27 [-]: SELF      R0 R0 K4     ; R1 := R0; R0 := R0[0x67bc869f]
 28 [-]: LOADK     R2 K8        ; R2 := "Junction.Rewards"
 29 [-]: LOADK     R3 4         ; R3 := 4.000000
 30 [-]: LOADK     R4 -15       ; R4 := -15.000000
 31 [-]: CALL      R0 5 1       ; R0(R1,R2,R3,R4)
 32 [-]: GETUPVAL  R0 U2        ; R0 := U2
 33 [-]: CALL      R0 1 1       ; R0()
 34 [-]: GETUPVAL  R0 U1        ; R0 := U1
 35 [-]: GETTABLE  R0 R0 K9     ; R0 := R0[0xb73d420f]
 36 [-]: CALL      R0 1 2       ; R0 := R0()
 37 [-]: GETGLOBAL R1 K10       ; R1 := 0x0032441c
 38 [-]: GETTABLE  R1 R1 K11    ; R1 := R1["UIMaterial_DepthTestText"]
 39 [-]: GETUPVAL  R2 U1        ; R2 := U1
 40 [-]: GETTABLE  R2 R2 K12    ; R2 := R2["UI_MODE_IN_SPACE_SHIP"]
 41 [-]: EQ        0 R0 R2      ; if R0 ~= R2 then PC := 45
 42 [-]: JMP       45           ; PC := 45
 43 [-]: GETGLOBAL R2 K10       ; R2 := 0x0032441c
 44 [-]: GETTABLE  R1 R2 K13    ; R1 := R2["UIMaterial_PlainText"]
 45 [-]: GETGLOBAL R2 K3        ; R2 := 0xae91e43b
 46 [-]: SELF      R2 R2 K14    ; R3 := R2; R2 := R2[0x97f16b44]
 47 [-]: MOVE      R4 R1        ; R4 := R1
 48 [-]: CALL      R2 3 1       ; R2(R3,R4)
 49 [-]: GETGLOBAL R2 K3        ; R2 := 0xae91e43b
 50 [-]: SELF      R2 R2 K15    ; R3 := R2; R2 := R2[0xf5f4e9ac]
 51 [-]: MOVE      R4 R1        ; R4 := R1
 52 [-]: CALL      R2 3 1       ; R2(R3,R4)
 53 [-]: GETGLOBAL R2 K3        ; R2 := 0xae91e43b
 54 [-]: SELF      R2 R2 K16    ; R3 := R2; R2 := R2[0x91a24e4b]
 55 [-]: LOADK     R4 K17       ; R4 := "Junction.Rewards.RewardGrid"
 56 [-]: LOADK     R5 0         ; R5 := 0.000000
 57 [-]: CALL      R2 4 2       ; R2 := R2(R3,R4,R5)
 58 [-]: SETUPVAL  R2 U3        ; U82 := R3
 59 [-]: GETGLOBAL R2 K3        ; R2 := 0xae91e43b
 60 [-]: SELF      R2 R2 K4     ; R3 := R2; R2 := R2[0x67bc869f]
 61 [-]: LOADK     R4 K18       ; R4 := "_root"
 62 [-]: LOADK     R5 10        ; R5 := 10.000000
 63 [-]: LOADK     R6 0         ; R6 := 0.000000
 64 [-]: CALL      R2 5 1       ; R2(R3,R4,R5,R6)
 65 [-]: GETGLOBAL R2 K19       ; R2 := 0x25312c9b
 66 [-]: GETGLOBAL R3 K3        ; R3 := 0xae91e43b
 67 [-]: LOADK     R4 K18       ; R4 := "_root"
 68 [-]: LOADK     R5 8         ; R5 := 8.000000
 69 [-]: NEWTABLE  R6 1 0       ; R6 := {}
 70 [-]: LOADK     R7 10        ; R7 := 10.000000
 71 [-]: SETLIST   R6 1 1       ; R6[(1-1)*FPF+i] := R(6+i), 1 <= i <= 1
 72 [-]: NEWTABLE  R7 0 0       ; R7 := {}
 73 [-]: GETUPVAL  R8 U4        ; R8 := U4
 74 [-]: GETTABLE  R8 R8 K21    ; R8 := R8[0x06d055f9]
 75 [-]: GETGLOBAL R9 K22       ; R9 := _T
 76 [-]: GETTABLE  R9 R9 K23    ; R9 := R9["JunctionTasksInstant"]
 77 [-]: LOADK     R10 100      ; R10 := 100.000000
 78 [-]: LOADK     R11 0        ; R11 := 0.000000
 79 [-]: CALL      R8 4 0       ; R8,... := R8(R9,R10,R11)
 80 [-]: SETLIST   R7 0 1       ; R7[(1-1)*FPF+i] := R(7+i), 1 <= i <= 0
 81 [-]: LOADK     R8 K24       ; R8 := 0.010000
 82 [-]: LOADK     R9 0         ; R9 := 0.000000
 83 [-]: CLOSURE   R10 0        ; R10 := closure(Function #10.1)
 84 [-]: GETUPVAL  R0 U5        ; R0 := U5
 85 [-]: GETUPVAL  R0 U6        ; R0 := U6
 86 [-]: CALL      R2 9 1       ; R2(R3,R4,R5,R6,R7,R8,R9,R10)
 87 [-]: GETUPVAL  R2 U7        ; R2 := U7
 88 [-]: CALL      R2 1 1       ; R2()
 89 [-]: RETURN    R0 1         ; return 


; Function #10.1:
;
; Name:            
; Defined at line: 496
; #Upvalues:       2
; #Parameters:     0
; Is_vararg:       0
; Max Stack Size:  7

  1 [-]: GETGLOBAL R0 K0        ; R0 := _T
  2 [-]: GETTABLE  R0 R0 K1     ; R0 := R0["JunctionTasksInstant"]
  3 [-]: TEST      R0 1         ; if R0 then PC := 17
  4 [-]: JMP       17           ; PC := 17
  5 [-]: GETGLOBAL R0 K2        ; R0 := 0x25312c9b
  6 [-]: GETGLOBAL R1 K3        ; R1 := 0xae91e43b
  7 [-]: LOADK     R2 K4        ; R2 := "_root"
  8 [-]: LOADK     R3 8         ; R3 := 8.000000
  9 [-]: NEWTABLE  R4 1 0       ; R4 := {}
 10 [-]: LOADK     R5 10        ; R5 := 10.000000
 11 [-]: SETLIST   R4 1 1       ; R4[(1-1)*FPF+i] := R(4+i), 1 <= i <= 1
 12 [-]: NEWTABLE  R5 1 0       ; R5 := {}
 13 [-]: LOADK     R6 100       ; R6 := 100.000000
 14 [-]: SETLIST   R5 1 1       ; R5[(1-1)*FPF+i] := R(5+i), 1 <= i <= 1
 15 [-]: LOADK     R6 K6        ; R6 := 0.200000
 16 [-]: CALL      R0 7 1       ; R0(R1,R2,R3,R4,R5,R6)
 17 [-]: GETUPVAL  R0 U0        ; R0 := U0
 18 [-]: CALL      R0 1 1       ; R0()
 19 [-]: GETUPVAL  R0 U1        ; R0 := U1
 20 [-]: CALL      R0 1 1       ; R0()
 21 [-]: RETURN    R0 1         ; return 


; Function #11:
;
; Name:            
; Defined at line: 507
; #Upvalues:       4
; #Parameters:     0
; Is_vararg:       0
; Max Stack Size:  3

  1 [-]: GETGLOBAL R0 K0        ; R0 := 0xae91e43b
  2 [-]: SELF      R0 R0 K1     ; R1 := R0; R0 := R0[0x8a8c8d5a]
  3 [-]: GETGLOBAL R2 K2        ; R2 := 0xb693b6c1
  4 [-]: CALL      R2 1 0       ; R2,... := R2()
  5 [-]: CALL      R0 0 1       ; R0(R1,...)
  6 [-]: GETUPVAL  R0 U0        ; R0 := U0
  7 [-]: TEST      R0 0         ; if not R0 then PC := 16
  8 [-]: JMP       16           ; PC := 16
  9 [-]: GETUPVAL  R0 U1        ; R0 := U1
 10 [-]: TEST      R0 0         ; if not R0 then PC := 16
 11 [-]: JMP       16           ; PC := 16
 12 [-]: LOADBOOL  R0 0 0       ; R0 := false
 13 [-]: SETUPVAL  R0 U1        ; U82 := R1
 14 [-]: GETUPVAL  R0 U2        ; R0 := U2
 15 [-]: CALL      R0 1 1       ; R0()
 16 [-]: GETGLOBAL R0 K3        ; R0 := _T
 17 [-]: GETTABLE  R0 R0 K4     ; R0 := R0[0x8e6a7b4e]
 18 [-]: LOADK     R1 K5        ; R1 := "Inbox"
 19 [-]: CALL      R0 2 2       ; R0 := R0(R1)
 20 [-]: TEST      R0 0         ; if not R0 then PC := 24
 21 [-]: JMP       24           ; PC := 24
 22 [-]: GETUPVAL  R0 U3        ; R0 := U3
 23 [-]: CALL      R0 1 1       ; R0()
 24 [-]: RETURN    R0 1         ; return 


; Function #12:
;
; Name:            
; Defined at line: 521
; #Upvalues:       2
; #Parameters:     0
; Is_vararg:       0
; Max Stack Size:  2

  1 [-]: LOADBOOL  R0 1 0       ; R0 := true
  2 [-]: SETUPVAL  R0 U0        ; U82 := R0
  3 [-]: GETUPVAL  R0 U1        ; R0 := U1
  4 [-]: CALL      R0 1 1       ; R0()
  5 [-]: RETURN    R0 1         ; return 


; Function #13:
;
; Name:            
; Defined at line: 526
; #Upvalues:       2
; #Parameters:     0
; Is_vararg:       0
; Max Stack Size:  2

  1 [-]: GETUPVAL  R0 U0        ; R0 := U0
  2 [-]: GETTABLE  R0 R0 K0     ; R0 := R0[0x659d451f]
  3 [-]: GETGLOBAL R1 K1        ; R1 := 0x0032441c
  4 [-]: GETTABLE  R1 R1 K2     ; R1 := R1["UISound_Close"]
  5 [-]: CALL      R0 2 1       ; R0(R1)
  6 [-]: GETUPVAL  R0 U1        ; R0 := U1
  7 [-]: CALL      R0 1 1       ; R0()
  8 [-]: RETURN    R0 1         ; return 


; Function #14:
;
; Name:            
; Defined at line: 531
; #Upvalues:       2
; #Parameters:     0
; Is_vararg:       0
; Max Stack Size:  2

  1 [-]: GETUPVAL  R0 U0        ; R0 := U0
  2 [-]: TEST      R0 1         ; if R0 then PC := 6
  3 [-]: JMP       6            ; PC := 6
  4 [-]: GETUPVAL  R0 U1        ; R0 := U1
  5 [-]: CALL      R0 1 1       ; R0()
  6 [-]: LOADBOOL  R0 1 0       ; R0 := true
  7 [-]: RETURN    R0 2         ; return R0
  8 [-]: RETURN    R0 1         ; return 


; Function #15:
;
; Name:            
; Defined at line: 539
; #Upvalues:       2
; #Parameters:     1
; Is_vararg:       0
; Max Stack Size:  4

  1 [-]: GETGLOBAL R1 K0        ; R1 := 0x3d106989
  2 [-]: LOADK     R2 K1        ; R2 := "JunctionTasks:SetTrigger"
  3 [-]: CALL      R1 2 1       ; R1(R2)
  4 [-]: SETUPVAL  R0 U0        ; U82 := R0
  5 [-]: GETGLOBAL R1 K2        ; R1 := 0xae91e43b
  6 [-]: SELF      R1 R1 K3     ; R2 := R1; R1 := R1[0x2d6bad65]
  7 [-]: GETGLOBAL R3 K4        ; R3 := 0xada7e97a
  8 [-]: CALL      R1 3 1       ; R1(R2,R3)
  9 [-]: GETUPVAL  R1 U1        ; R1 := U1
 10 [-]: CALL      R1 1 1       ; R1()
 11 [-]: LOADBOOL  R1 1 0       ; R1 := true
 12 [-]: RETURN    R1 2         ; return R1
 13 [-]: RETURN    R0 1         ; return 


; Function #16:
;
; Name:            
; Defined at line: 550
; #Upvalues:       2
; #Parameters:     1
; Is_vararg:       0
; Max Stack Size:  2

  1 [-]: EQ        1 R0 K0      ; if R0 == "true" then PC := 4
  2 [-]: JMP       4            ; PC := 4
  3 [-]: LOADBOOL  R1 0 1       ; R1 := false; PC := 4
  4 [-]: LOADBOOL  R1 1 0       ; R1 := true
  5 [-]: SETUPVAL  R1 U0        ; U82 := R0
  6 [-]: GETUPVAL  R1 U1        ; R1 := U1
  7 [-]: CALL      R1 1 1       ; R1()
  8 [-]: RETURN    R0 1         ; return 


; Function #17:
;
; Name:            
; Defined at line: 556
; #Upvalues:       1
; #Parameters:     0
; Is_vararg:       0
; Max Stack Size:  2

  1 [-]: GETUPVAL  R0 U0        ; R0 := U0
  2 [-]: CALL      R0 1 1       ; R0()
  3 [-]: RETURN    R0 1         ; return 


; Function #18:
;
; Name:            
; Defined at line: 560
; #Upvalues:       2
; #Parameters:     0
; Is_vararg:       0
; Max Stack Size:  2

  1 [-]: GETGLOBAL R0 K0        ; R0 := 0x7b998233
  2 [-]: GETUPVAL  R1 U0        ; R1 := U0
  3 [-]: CALL      R0 2 2       ; R0 := R0(R1)
  4 [-]: TEST      R0 1         ; if R0 then PC := 8
  5 [-]: JMP       8            ; PC := 8
  6 [-]: GETUPVAL  R0 U1        ; R0 := U1
  7 [-]: CALL      R0 1 1       ; R0()
  8 [-]: RETURN    R0 1         ; return 


