; Name:            
; Defined at line: 1
; #Upvalues:       0
; #Parameters:     0
; Is_vararg:       1
; Max Stack Size:  66

       1 [-]: GETIMPORT R0 1; var0 = 0x2D0FAD09
       2 [-]: LOADK R1 K2  ; var1 = "Lotus.Interface.LotusUtilities"
       3 [-]: CALL R0 2 2  ; var0 = var0(var1)
       4 [-]: GETIMPORT R1 1; var1 = 0x2D0FAD09
       5 [-]: LOADK R2 K3  ; var2 = "EE.Interface.Utilities"
       6 [-]: CALL R1 2 2  ; var1 = var1(var2)
       7 [-]: GETIMPORT R2 1; var2 = 0x2D0FAD09
       8 [-]: LOADK R3 K4  ; var3 = "Lotus.Interface.UIUtilities"
       9 [-]: CALL R2 2 2  ; var2 = var2(var3)
      10 [-]: GETIMPORT R3 1; var3 = 0x2D0FAD09
      11 [-]: LOADK R4 K5  ; var4 = "Lotus.Interface.UIStyleUtilities"
      12 [-]: CALL R3 2 2  ; var3 = var3(var4)
      13 [-]: GETIMPORT R4 1; var4 = 0x2D0FAD09
      14 [-]: LOADK R5 K6  ; var5 = "Lotus.Interface.TextSuggest"
      15 [-]: CALL R4 2 2  ; var4 = var4(var5)
      16 [-]: GETIMPORT R5 1; var5 = 0x2D0FAD09
      17 [-]: LOADK R6 K7  ; var6 = "Lotus.Interface.Components.ThemedCheckbox"
      18 [-]: CALL R5 2 2  ; var5 = var5(var6)
      19 [-]: GETIMPORT R6 1; var6 = 0x2D0FAD09
      20 [-]: LOADK R7 K8  ; var7 = "Lotus.Interface.Components.ThemedToggle"
      21 [-]: CALL R6 2 2  ; var6 = var6(var7)
      22 [-]: GETIMPORT R7 1; var7 = 0x2D0FAD09
      23 [-]: LOADK R8 K9  ; var8 = "Lotus.Interface.Components.ThemedInputField"
      24 [-]: CALL R7 2 2  ; var7 = var7(var8)
      25 [-]: GETIMPORT R8 1; var8 = 0x2D0FAD09
      26 [-]: LOADK R9 K10 ; var9 = "Lotus.Interface.Components.ThemedButton"
      27 [-]: CALL R8 2 2  ; var8 = var8(var9)
      28 [-]: LOADNIL R9   ; var9 = nil
      29 [-]: LOADB R10 0  ; var10 = false
      30 [-]: LOADB R11 1  ; var11 = true
      31 [-]: LOADNIL R12  ; var12 = nil
      32 [-]: LOADK R13 K11; var13 = "/Lotus/Language/Menu/Global_Confirm"
      33 [-]: LOADB R14 0  ; var14 = false
      34 [-]: LOADNIL R15  ; var15 = nil
      35 [-]: LOADNIL R16  ; var16 = nil
      36 [-]: LOADNIL R17  ; var17 = nil
      37 [-]: LOADNIL R18  ; var18 = nil
      38 [-]: LOADB R19 0  ; var19 = false
      39 [-]: LOADNIL R20  ; var20 = nil
      40 [-]: NEWTABLE R21 0 0; var21 = {}
      41 [-]: LOADN R22 0  ; var22 = 0
      42 [-]: LOADNIL R23  ; var23 = nil
      43 [-]: LOADB R24 0  ; var24 = false
      44 [-]: LOADK R25 K12; var25 = ""
      45 [-]: DUPTABLE R26 16; 
      46 [-]: NEWTABLE R27 0 0; var27 = {}
      47 [-]: SETTABLEKS R27 R26 K13; var27["Real"] = var26
      48 [-]: NEWTABLE R27 0 0; var27 = {}
      49 [-]: SETTABLEKS R27 R26 K14; var27["Tags"] = var26
      50 [-]: NEWTABLE R27 0 0; var27 = {}
      51 [-]: SETTABLEKS R27 R26 K15; var27["Indexer"] = var26
      52 [-]: NEWTABLE R27 8 0; var27 = {}
      53 [-]: LOADNIL R28  ; var28 = nil
      54 [-]: LOADN R29 0  ; var29 = 0
      55 [-]: LOADN R30 0  ; var30 = 0
      56 [-]: LOADNIL R31  ; var31 = nil
      57 [-]: LOADN R32 0  ; var32 = 0
      58 [-]: LOADB R33 0  ; var33 = false
      59 [-]: LOADB R34 0  ; var34 = false
      60 [-]: LOADB R35 0  ; var35 = false
      61 [-]: LOADB R36 1  ; var36 = true
      62 [-]: LOADNIL R37  ; var37 = nil
      63 [-]: LOADNIL R38  ; var38 = nil
      64 [-]: NEWTABLE R39 2 0; var39 = {}
      65 [-]: NEWTABLE R40 4 0; var40 = {}
      66 [-]: LOADN R41 0  ; var41 = 0
      67 [-]: LOADB R42 0  ; var42 = false
      68 [-]: NEWTABLE R43 0 11; var43 = {}
      69 [-]: LOADN R44 44 ; var44 = 44
      70 [-]: LOADN R45 44 ; var45 = 44
      71 [-]: LOADN R46 44 ; var46 = 44
      72 [-]: LOADN R47 44 ; var47 = 44
      73 [-]: LOADN R48 24 ; var48 = 24
      74 [-]: LOADN R49 108; var49 = 108
      75 [-]: LOADN R50 8  ; var50 = 8
      76 [-]: LOADN R51 44 ; var51 = 44
      77 [-]: LOADN R52 87 ; var52 = 87
      78 [-]: LOADN R53 84 ; var53 = 84
      79 [-]: LOADN R54 44 ; var54 = 44
      80 [-]: SETLIST R43 R44 11 [1]; var43[1] = var44; var43[2] = var45; var43[3] = var46; var43[4] = var47; var43[5] = var48; var43[6] = var49; var43[7] = var50; var43[8] = var51; var43[9] = var52; var43[10] = var53; var43[11] = var54; var43[12] = var55; 
      81 [-]: LOADNIL R44  ; var44 = nil
      82 [-]: LOADNIL R45  ; var45 = nil
      83 [-]: NEWCLOSURE R46 P0; 
      84 [-]: CAPTURE REF R23; 
      85 [-]: CAPTURE REF R24; 
      86 [-]: CAPTURE VAL R4; 
      87 [-]: CAPTURE REF R19; 
      88 [-]: CAPTURE REF R18; 
      89 [-]: CAPTURE REF R21; 
      90 [-]: SETGLOBAL R46 K17; "Shutdown" = var46
      91 [-]: DUPCLOSURE R46 K18; 
      92 [-]: NEWCLOSURE R47 P2; 
      93 [-]: CAPTURE REF R36; 
      94 [-]: CAPTURE REF R11; 
      95 [-]: CAPTURE REF R21; 
      96 [-]: CAPTURE VAL R1; 
      97 [-]: CAPTURE REF R19; 
      98 [-]: CAPTURE REF R18; 
      99 [-]: DUPCLOSURE R48 K19; 
     100 [-]: CAPTURE VAL R47; 
     101 [-]: SETGLOBAL R48 K20; "TransitionOut" = var48
     102 [-]: NEWCLOSURE R48 P4; 
     103 [-]: CAPTURE REF R21; 
     104 [-]: CAPTURE REF R12; 
     105 [-]: CAPTURE VAL R0; 
     106 [-]: CAPTURE VAL R1; 
     107 [-]: NEWCLOSURE R49 P5; 
     108 [-]: CAPTURE REF R36; 
     109 [-]: CAPTURE VAL R48; 
     110 [-]: CAPTURE VAL R1; 
     111 [-]: CAPTURE VAL R47; 
     112 [-]: DUPCLOSURE R50 K21; 
     113 [-]: CAPTURE VAL R48; 
     114 [-]: CAPTURE VAL R47; 
     115 [-]: DUPCLOSURE R51 K22; 
     116 [-]: CAPTURE VAL R27; 
     117 [-]: CAPTURE VAL R3; 
     118 [-]: CAPTURE VAL R1; 
     119 [-]: DUPCLOSURE R52 K23; 
     120 [-]: CAPTURE VAL R40; 
     121 [-]: SETGLOBAL R52 K24; "OnCustomButtonPressed" = var52
     122 [-]: NEWCLOSURE R52 P9; 
     123 [-]: CAPTURE REF R41; 
     124 [-]: CAPTURE VAL R1; 
     125 [-]: NEWCLOSURE R53 P10; 
     126 [-]: CAPTURE REF R41; 
     127 [-]: CAPTURE REF R35; 
     128 [-]: CAPTURE REF R34; 
     129 [-]: CAPTURE VAL R40; 
     130 [-]: CAPTURE VAL R8; 
     131 [-]: CAPTURE REF R13; 
     132 [-]: CAPTURE REF R37; 
     133 [-]: CAPTURE VAL R39; 
     134 [-]: CAPTURE REF R38; 
     135 [-]: CAPTURE REF R36; 
     136 [-]: CAPTURE REF R45; 
     137 [-]: CAPTURE VAL R52; 
     138 [-]: NEWCLOSURE R54 P11; 
     139 [-]: CAPTURE REF R15; 
     140 [-]: CAPTURE REF R16; 
     141 [-]: CAPTURE REF R35; 
     142 [-]: CAPTURE REF R20; 
     143 [-]: CAPTURE VAL R53; 
     144 [-]: NEWCLOSURE R55 P12; 
     145 [-]: CAPTURE VAL R54; 
     146 [-]: CAPTURE REF R15; 
     147 [-]: CAPTURE REF R12; 
     148 [-]: NEWCLOSURE R45 P13; 
     149 [-]: CAPTURE REF R12; 
     150 [-]: CAPTURE REF R42; 
     151 [-]: CAPTURE VAL R0; 
     152 [-]: CAPTURE VAL R1; 
     153 [-]: CAPTURE REF R41; 
     154 [-]: NEWCLOSURE R56 P14; 
     155 [-]: CAPTURE REF R12; 
     156 [-]: CAPTURE REF R15; 
     157 [-]: CAPTURE VAL R0; 
     158 [-]: CAPTURE VAL R1; 
     159 [-]: CAPTURE VAL R27; 
     160 [-]: CAPTURE VAL R54; 
     161 [-]: CAPTURE VAL R5; 
     162 [-]: CAPTURE VAL R6; 
     163 [-]: CAPTURE VAL R7; 
     164 [-]: CAPTURE VAL R8; 
     165 [-]: CAPTURE VAL R43; 
     166 [-]: NEWCLOSURE R57 P15; 
     167 [-]: CAPTURE REF R12; 
     168 [-]: CAPTURE REF R31; 
     169 [-]: CAPTURE REF R32; 
     170 [-]: CAPTURE VAL R1; 
     171 [-]: CAPTURE VAL R54; 
     172 [-]: NEWCLOSURE R58 P16; 
     173 [-]: CAPTURE REF R15; 
     174 [-]: CAPTURE REF R25; 
     175 [-]: CAPTURE VAL R26; 
     176 [-]: CAPTURE REF R16; 
     177 [-]: CAPTURE VAL R4; 
     178 [-]: CAPTURE REF R23; 
     179 [-]: NEWCLOSURE R59 P17; 
     180 [-]: CAPTURE VAL R4; 
     181 [-]: CAPTURE REF R23; 
     182 [-]: CAPTURE REF R25; 
     183 [-]: CAPTURE REF R16; 
     184 [-]: CAPTURE VAL R54; 
     185 [-]: NEWCLOSURE R60 P18; 
     186 [-]: CAPTURE REF R10; 
     187 [-]: CAPTURE REF R9; 
     188 [-]: CAPTURE REF R12; 
     189 [-]: CAPTURE REF R28; 
     190 [-]: CAPTURE REF R30; 
     191 [-]: CAPTURE REF R29; 
     192 [-]: CAPTURE VAL R46; 
     193 [-]: CAPTURE REF R15; 
     194 [-]: CAPTURE REF R44; 
     195 [-]: CAPTURE REF R33; 
     196 [-]: CAPTURE VAL R57; 
     197 [-]: CAPTURE REF R23; 
     198 [-]: CAPTURE VAL R0; 
     199 [-]: CAPTURE VAL R4; 
     200 [-]: CAPTURE VAL R59; 
     201 [-]: CAPTURE VAL R58; 
     202 [-]: SETGLOBAL R60 K25; "Update" = var60
     203 [-]: NEWCLOSURE R60 P19; 
     204 [-]: CAPTURE REF R17; 
     205 [-]: CAPTURE REF R22; 
     206 [-]: CAPTURE REF R9; 
     207 [-]: CAPTURE VAL R60; 
     208 [-]: CAPTURE VAL R47; 
     209 [-]: CAPTURE REF R12; 
     210 [-]: CAPTURE REF R45; 
     211 [-]: CAPTURE REF R11; 
     212 [-]: CAPTURE VAL R53; 
     213 [-]: DUPCLOSURE R61 K26; 
     214 [-]: NEWCLOSURE R62 P21; 
     215 [-]: CAPTURE REF R9; 
     216 [-]: CAPTURE VAL R1; 
     217 [-]: CAPTURE VAL R61; 
     218 [-]: CAPTURE VAL R51; 
     219 [-]: CAPTURE VAL R56; 
     220 [-]: CAPTURE VAL R60; 
     221 [-]: CAPTURE VAL R53; 
     222 [-]: CAPTURE REF R10; 
     223 [-]: SETGLOBAL R62 K27; "Initialize" = var62
     224 [-]: NEWCLOSURE R62 P22; 
     225 [-]: CAPTURE REF R12; 
     226 [-]: SETGLOBAL R62 K28; "SetTitle" = var62
     227 [-]: NEWCLOSURE R62 P23; 
     228 [-]: CAPTURE REF R13; 
     229 [-]: CAPTURE VAL R53; 
     230 [-]: SETGLOBAL R62 K29; "SetConfirmButtonLabel" = var62
     231 [-]: NEWCLOSURE R62 P24; 
     232 [-]: CAPTURE REF R34; 
     233 [-]: SETGLOBAL R62 K30; "SetConfirmButtonVisibleWhenInactive" = var62
     234 [-]: NEWCLOSURE R62 P25; 
     235 [-]: CAPTURE REF R14; 
     236 [-]: CAPTURE REF R35; 
     237 [-]: CAPTURE VAL R53; 
     238 [-]: SETGLOBAL R62 K31; "SetConfirmButtonActive" = var62
     239 [-]: NEWCLOSURE R62 P26; 
     240 [-]: CAPTURE REF R35; 
     241 [-]: CAPTURE VAL R53; 
     242 [-]: SETGLOBAL R62 K32; "SetConfirmButtonActiveOverride" = var62
     243 [-]: NEWCLOSURE R62 P27; 
     244 [-]: CAPTURE REF R36; 
     245 [-]: CAPTURE VAL R53; 
     246 [-]: SETGLOBAL R62 K33; "SetCancelButtonActive" = var62
     247 [-]: DUPCLOSURE R62 K34; 
     248 [-]: SETGLOBAL R62 K35; "SetNoElementsMessage" = var62
     249 [-]: NEWCLOSURE R62 P29; 
     250 [-]: CAPTURE REF R17; 
     251 [-]: SETGLOBAL R62 K36; "SetElementsFunction" = var62
     252 [-]: NEWCLOSURE R62 P30; 
     253 [-]: CAPTURE REF R37; 
     254 [-]: SETGLOBAL R62 K37; "SetCustomButtonFunction" = var62
     255 [-]: NEWCLOSURE R62 P31; 
     256 [-]: CAPTURE REF R38; 
     257 [-]: SETGLOBAL R62 K38; "OnCustomButtonConfirmation" = var62
     258 [-]: DUPCLOSURE R62 K39; 
     259 [-]: CAPTURE VAL R1; 
     260 [-]: CAPTURE VAL R39; 
     261 [-]: SETGLOBAL R62 K40; "ShowCustomButtonConfirmation" = var62
     262 [-]: NEWCLOSURE R62 P33; 
     263 [-]: CAPTURE REF R18; 
     264 [-]: SETGLOBAL R62 K41; "SetCallBack" = var62
     265 [-]: NEWCLOSURE R62 P34; 
     266 [-]: CAPTURE REF R20; 
     267 [-]: SETGLOBAL R62 K42; "SetValueChangedCallBack" = var62
     268 [-]: NEWCLOSURE R62 P35; 
     269 [-]: CAPTURE REF R23; 
     270 [-]: CAPTURE REF R24; 
     271 [-]: CAPTURE VAL R26; 
     272 [-]: SETGLOBAL R62 K43; "EnableHints" = var62
     273 [-]: NEWCLOSURE R62 P36; 
     274 [-]: CAPTURE REF R11; 
     275 [-]: CAPTURE VAL R4; 
     276 [-]: CAPTURE VAL R59; 
     277 [-]: CAPTURE REF R23; 
     278 [-]: CAPTURE REF R15; 
     279 [-]: SETGLOBAL R62 K44; "onRawInputEvent" = var62
     280 [-]: DUPCLOSURE R62 K45; 
     281 [-]: CAPTURE VAL R47; 
     282 [-]: SETGLOBAL R62 K46; "Close" = var62
     283 [-]: DUPCLOSURE R62 K47; 
     284 [-]: CAPTURE VAL R49; 
     285 [-]: SETGLOBAL R62 K48; "ExitScreen" = var62
     286 [-]: DUPCLOSURE R62 K49; 
     287 [-]: CAPTURE VAL R50; 
     288 [-]: SETGLOBAL R62 K50; "FinishSelection" = var62
     289 [-]: NEWCLOSURE R62 P40; 
     290 [-]: CAPTURE REF R11; 
     291 [-]: CAPTURE REF R12; 
     292 [-]: SETGLOBAL R62 K51; "onKeyUp_MENU_SELECT" = var62
     293 [-]: NEWCLOSURE R62 P41; 
     294 [-]: CAPTURE REF R11; 
     295 [-]: SETGLOBAL R62 K52; "IsInputBlocked" = var62
     296 [-]: DUPCLOSURE R62 K53; 
     297 [-]: CAPTURE VAL R61; 
     298 [-]: SETGLOBAL R62 K54; "onViewportSizeChanged" = var62
     299 [-]: NEWCLOSURE R62 P43; 
     300 [-]: CAPTURE REF R12; 
     301 [-]: SETGLOBAL R62 K55; "MenuEntryFocused" = var62
     302 [-]: NEWCLOSURE R62 P44; 
     303 [-]: CAPTURE REF R12; 
     304 [-]: SETGLOBAL R62 K56; "MenuEntryUnfocused" = var62
     305 [-]: NEWCLOSURE R62 P45; 
     306 [-]: CAPTURE REF R11; 
     307 [-]: CAPTURE REF R12; 
     308 [-]: CAPTURE VAL R1; 
     309 [-]: SETGLOBAL R62 K57; "MenuEntryPressed" = var62
     310 [-]: NEWCLOSURE R62 P46; 
     311 [-]: CAPTURE REF R11; 
     312 [-]: CAPTURE REF R12; 
     313 [-]: SETGLOBAL R62 K58; "onKeyDown_MENU_MOUSE_Z" = var62
     314 [-]: NEWCLOSURE R62 P47; 
     315 [-]: CAPTURE REF R15; 
     316 [-]: CAPTURE VAL R54; 
     317 [-]: SETGLOBAL R62 K59; "OSKInputBoxCallback" = var62
     318 [-]: NEWCLOSURE R44 P48; 
     319 [-]: CAPTURE REF R15; 
     320 [-]: CAPTURE VAL R1; 
     321 [-]: CAPTURE VAL R54; 
     322 [-]: NEWCLOSURE R62 P49; 
     323 [-]: CAPTURE REF R11; 
     324 [-]: CAPTURE REF R15; 
     325 [-]: CAPTURE VAL R0; 
     326 [-]: CAPTURE REF R44; 
     327 [-]: CAPTURE REF R28; 
     328 [-]: CAPTURE REF R29; 
     329 [-]: CAPTURE REF R30; 
     330 [-]: NEWCLOSURE R63 P50; 
     331 [-]: CAPTURE REF R11; 
     332 [-]: CAPTURE REF R15; 
     333 [-]: CAPTURE VAL R0; 
     334 [-]: CAPTURE REF R44; 
     335 [-]: CAPTURE REF R28; 
     336 [-]: CAPTURE REF R29; 
     337 [-]: CAPTURE REF R30; 
     338 [-]: NEWCLOSURE R64 P51; 
     339 [-]: CAPTURE REF R28; 
     340 [-]: DUPCLOSURE R65 K60; 
     341 [-]: CAPTURE VAL R62; 
     342 [-]: SETGLOBAL R65 K61; "IncreaseCount" = var65
     343 [-]: DUPCLOSURE R65 K62; 
     344 [-]: CAPTURE VAL R63; 
     345 [-]: SETGLOBAL R65 K63; "DecreaseCount" = var65
     346 [-]: DUPCLOSURE R65 K64; 
     347 [-]: CAPTURE VAL R64; 
     348 [-]: SETGLOBAL R65 K65; "ConcludeCount" = var65
     349 [-]: NEWCLOSURE R65 P55; 
     350 [-]: CAPTURE REF R12; 
     351 [-]: CAPTURE REF R33; 
     352 [-]: CAPTURE REF R31; 
     353 [-]: CAPTURE REF R32; 
     354 [-]: SETGLOBAL R65 K66; "CountFieldFocused" = var65
     355 [-]: NEWCLOSURE R65 P56; 
     356 [-]: CAPTURE REF R33; 
     357 [-]: CAPTURE VAL R57; 
     358 [-]: CAPTURE REF R12; 
     359 [-]: SETGLOBAL R65 K67; "CountFieldUnfocused" = var65
     360 [-]: NEWCLOSURE R65 P57; 
     361 [-]: CAPTURE REF R11; 
     362 [-]: CAPTURE REF R15; 
     363 [-]: CAPTURE VAL R0; 
     364 [-]: CAPTURE VAL R62; 
     365 [-]: SETGLOBAL R65 K68; "onKeyDown_MENU_RTRIGGER2" = var65
     366 [-]: NEWCLOSURE R65 P58; 
     367 [-]: CAPTURE REF R11; 
     368 [-]: CAPTURE REF R15; 
     369 [-]: CAPTURE VAL R0; 
     370 [-]: CAPTURE VAL R63; 
     371 [-]: SETGLOBAL R65 K69; "onKeyDown_MENU_LTRIGGER2" = var65
     372 [-]: DUPCLOSURE R65 K70; 
     373 [-]: CAPTURE VAL R64; 
     374 [-]: SETGLOBAL R65 K71; "onKeyUp_MENU_LTRIGGER2" = var65
     375 [-]: DUPCLOSURE R65 K72; 
     376 [-]: CAPTURE VAL R64; 
     377 [-]: SETGLOBAL R65 K73; "onKeyUp_MENU_RTRIGGER2" = var65
     378 [-]: DUPCLOSURE R65 K74; 
     379 [-]: CAPTURE VAL R47; 
     380 [-]: SETGLOBAL R65 K75; "onKeyUp_HIDE_PAUSE_MENU" = var65
     381 [-]: DUPCLOSURE R65 K76; 
     382 [-]: SETGLOBAL R65 K77; "ConfirmPopup" = var65
     383 [-]: DUPCLOSURE R65 K78; 
     384 [-]: CAPTURE VAL R1; 
     385 [-]: CAPTURE VAL R2; 
     386 [-]: SETGLOBAL R65 K79; "ShowHyperlinkItem" = var65
     387 [-]: DUPCLOSURE R65 K80; 
     388 [-]: CAPTURE VAL R54; 
     389 [-]: SETGLOBAL R65 K81; "YesButton" = var65
     390 [-]: DUPCLOSURE R65 K82; 
     391 [-]: CAPTURE VAL R54; 
     392 [-]: SETGLOBAL R65 K83; "NoButton" = var65
     393 [-]: DUPCLOSURE R65 K84; 
     394 [-]: SETGLOBAL R65 K85; "SetScale" = var65
     395 [-]: DUPCLOSURE R65 K86; 
     396 [-]: CAPTURE VAL R1; 
     397 [-]: SETGLOBAL R65 K87; "InputBoxTextLimited" = var65
     398 [-]: NEWCLOSURE R65 P68; 
     399 [-]: CAPTURE REF R42; 
     400 [-]: SETGLOBAL R65 K88; "CenterTitles" = var65
     401 [-]: DUPCLOSURE R65 K89; 
     402 [-]: SETGLOBAL R65 K90; "SupportsThemes" = var65
     403 [-]: CLOSEUPVALS R9; 
     404 [-]: RETURN R0 0  ; 


; Name:            
; Defined at line: 166
; #Upvalues:       6
; #Parameters:     0
; Is_vararg:       0
; Max Stack Size:  4

       0 [-]: GETIMPORT R0 1; var0 = _T
       1 [-]: LOADNIL R1   ; var1 = nil
       2 [-]: SETTABLEKS R1 R0 K2; var1["gToolTip"] = var0
       3 [-]: GETUPVAL R1 0; var1 = upvalues[0]
       4 [-]: FASTCALL1 62 R1 L0; 
       5 [-]: GETIMPORT R0 4; var0 = 0x7B998233
       6 [-]: CALL R0 2 2  ; var0 = var0(var1)
L 0:   7 [-]: JUMPIF R0 L2 ; goto L2 if var0
       8 [-]: GETUPVAL R0 1; var0 = upvalues[1]
       9 [-]: JUMPIFNOT R0 L1; goto L1 if not var0
      10 [-]: GETUPVAL R0 0; var0 = upvalues[0]
      11 [-]: NAMECALL R0 R0 K5; var1 = var0; var0 = var0[0x32302B4A]
      12 [-]: CALL R0 2 1  ; var0(var1)
      13 [-]: JUMP L2      ; goto L2
L 1:  14 [-]: GETUPVAL R1 2; var1 = upvalues[2]
      15 [-]: GETTABLEKS R0 R1 K6; var0 = var1[0xD4CC05B4]
      16 [-]: CALL R0 1 2  ; var0 = var0()
      17 [-]: JUMPIFNOT R0 L2; goto L2 if not var0
      18 [-]: GETUPVAL R1 2; var1 = upvalues[2]
      19 [-]: GETTABLEKS R0 R1 K7; var0 = var1[0xC074491B]
      20 [-]: GETUPVAL R1 0; var1 = upvalues[0]
      21 [-]: CALL R0 2 1  ; var0(var1)
L 2:  22 [-]: GETUPVAL R0 3; var0 = upvalues[3]
      23 [-]: JUMPIF R0 L5 ; goto L5 if var0
      24 [-]: GETUPVAL R1 4; var1 = upvalues[4]
      25 [-]: FASTCALL1 62 R1 L3; 
      26 [-]: GETIMPORT R0 4; var0 = 0x7B998233
      27 [-]: CALL R0 2 2  ; var0 = var0(var1)
L 3:  28 [-]: JUMPIF R0 L5 ; goto L5 if var0
      29 [-]: GETIMPORT R2 1; var2 = _T
      30 [-]: GETUPVAL R3 4; var3 = upvalues[4]
      31 [-]: GETTABLE R1 R2 R3; var1 = var2[var3]
      32 [-]: FASTCALL1 62 R1 L4; 
      33 [-]: GETIMPORT R0 4; var0 = 0x7B998233
      34 [-]: CALL R0 2 2  ; var0 = var0(var1)
L 4:  35 [-]: JUMPIF R0 L5 ; goto L5 if var0
      36 [-]: LOADB R0 1   ; var0 = true
      37 [-]: SETUPVAL R0 3; upvalues[0] = var3
      38 [-]: GETIMPORT R1 1; var1 = _T
      39 [-]: GETUPVAL R2 4; var2 = upvalues[4]
      40 [-]: GETTABLE R0 R1 R2; var0 = var1[var2]
      41 [-]: GETUPVAL R1 5; var1 = upvalues[5]
      42 [-]: LOADB R2 1   ; var2 = true
      43 [-]: CALL R0 3 1  ; var0(var1, var2)
L 5:  44 [-]: RETURN R0 0  ; 


; Name:            
; Defined at line: 183
; #Upvalues:       0
; #Parameters:     1
; Is_vararg:       0
; Max Stack Size:  4

       0 [-]: GETIMPORT R2 1; var2 = 0x64FB1586
       1 [-]: MOVE R3 R0   ; var3 = var0
       2 [-]: CALL R2 2 2  ; var2 = var2(var3)
       3 [-]: FASTCALL1 43 R2 L0; 
       4 [-]: GETIMPORT R1 4; var1 = 0x7F5022CF[0x41E2AE25]
       5 [-]: CALL R1 2 2  ; var1 = var1(var2)
L 0:   6 [-]: RETURN R1 1  ; 


; Name:            
; Defined at line: 187
; #Upvalues:       6
; #Parameters:     1
; Is_vararg:       0
; Max Stack Size:  11

       0 [-]: GETUPVAL R1 0; var1 = upvalues[0]
       1 [-]: JUMPIF R1 L0 ; goto L0 if var1
       2 [-]: JUMPIFNOT R0 L0; goto L0 if not var0
       3 [-]: RETURN R0 0  ; 
L 0:   4 [-]: LOADB R1 1   ; var1 = true
       5 [-]: SETUPVAL R1 1; upvalues[1] = var1
       6 [-]: GETIMPORT R1 1; var1 = 0xC8802016
       7 [-]: GETUPVAL R2 2; var2 = upvalues[2]
       8 [-]: CALL R1 2 4  ; var1, var2, var3 = var1(var2)
       9 [-]: FORGPREP_INEXT R1 L4; 
L 1:  10 [-]: GETTABLEKS R6 R5 K2; var6 = var5["mChanged"]
      11 [-]: JUMPIFNOT R6 L4; goto L4 if not var6
      12 [-]: GETTABLEKS R7 R5 K3; var7 = var5["mOnValidateSetting"]
      13 [-]: FASTCALL1 62 R7 L2; 
      14 [-]: GETIMPORT R6 5; var6 = 0x7B998233
      15 [-]: CALL R6 2 2  ; var6 = var6(var7)
L 2:  16 [-]: JUMPIF R6 L4 ; goto L4 if var6
      17 [-]: FASTCALL1 62 R0 L3; 
      18 [-]: MOVE R7 R0   ; var7 = var0
      19 [-]: GETIMPORT R6 5; var6 = 0x7B998233
      20 [-]: CALL R6 2 2  ; var6 = var6(var7)
L 3:  21 [-]: JUMPIFNOT R6 L4; goto L4 if not var6
      22 [-]: GETTABLEKS R6 R5 K3; var6 = var5["mOnValidateSetting"]
      23 [-]: CALL R6 1 3  ; var6, var7 = var6()
      24 [-]: JUMPIF R6 L4 ; goto L4 if var6
      25 [-]: GETUPVAL R9 3; var9 = upvalues[3]
      26 [-]: GETTABLEKS R8 R9 K6; var8 = var9[0xE0CBA3CA]
      27 [-]: MOVE R9 R7   ; var9 = var7
      28 [-]: CALL R8 2 1  ; var8(var9)
      29 [-]: LOADB R8 0   ; var8 = false
      30 [-]: SETUPVAL R8 1; upvalues[8] = var1
      31 [-]: RETURN R0 0  ; 
L 4:  32 [-]: FORGLOOP R1 L1 2 [inext]; 
      33 [-]: GETIMPORT R1 8; var1 = 0x25312C9B
      34 [-]: GETIMPORT R2 10; var2 = 0xAE91E43B
      35 [-]: LOADK R3 K11 ; var3 = "_root"
      36 [-]: LOADN R4 0   ; var4 = 0
      37 [-]: NEWTABLE R5 0 1; var5 = {}
      38 [-]: LOADN R6 10  ; var6 = 10
      39 [-]: SETLIST R5 R6 1 [1]; var5[1] = var6; var5[2] = var7; 
      40 [-]: NEWTABLE R6 0 1; var6 = {}
      41 [-]: LOADN R7 0   ; var7 = 0
      42 [-]: SETLIST R6 R7 1 [1]; var6[1] = var7; var6[2] = var8; 
      43 [-]: LOADK R7 K12 ; var7 = 0.20000000000000001
      44 [-]: CALL R1 7 1  ; var1(var2, var3, var4, var5, var6, var7)
      45 [-]: DUPCLOSURE R1 K13; 
      46 [-]: GETIMPORT R2 8; var2 = 0x25312C9B
      47 [-]: GETIMPORT R3 10; var3 = 0xAE91E43B
      48 [-]: LOADK R4 K14 ; var4 = "_level0"
      49 [-]: LOADN R5 0   ; var5 = 0
      50 [-]: NEWTABLE R6 0 1; var6 = {}
      51 [-]: MOVE R7 R1   ; var7 = var1
      52 [-]: SETLIST R6 R7 1 [1]; var6[1] = var7; var6[2] = var8; 
      53 [-]: NEWTABLE R7 0 1; var7 = {}
      54 [-]: LOADN R8 1   ; var8 = 1
      55 [-]: SETLIST R7 R8 1 [1]; var7[1] = var8; var7[2] = var9; 
      56 [-]: LOADK R8 K15 ; var8 = 0.29999999999999999
      57 [-]: LOADK R9 K16 ; var9 = 0.10000000000000001
      58 [-]: NEWCLOSURE R10 P1; 
      59 [-]: CAPTURE UPVAL U4; 
      60 [-]: CAPTURE UPVAL U5; 
      61 [-]: CAPTURE UPVAL U2; 
      62 [-]: CAPTURE VAL R0; 
      63 [-]: CALL R2 9 1  ; var2(var3, var4, var5, var6, var7, var8, var9, var10)
      64 [-]: RETURN R0 0  ; 


; Name:            
; Defined at line: 219
; #Upvalues:       1
; #Parameters:     0
; Is_vararg:       0
; Max Stack Size:  1

       0 [-]: GETUPVAL R0 0; var0 = upvalues[0]
       1 [-]: CALL R0 1 1  ; var0()
       2 [-]: RETURN R0 0  ; 


; Name:            
; Defined at line: 223
; #Upvalues:       4
; #Parameters:     0
; Is_vararg:       0
; Max Stack Size:  3

       0 [-]: NEWTABLE R0 0 0; var0 = {}
       1 [-]: SETUPVAL R0 0; upvalues[0] = var0
       2 [-]: GETUPVAL R0 1; var0 = upvalues[1]
       3 [-]: NEWCLOSURE R2 P0; 
       4 [-]: CAPTURE UPVAL U2; 
       5 [-]: CAPTURE UPVAL U3; 
       6 [-]: CAPTURE UPVAL U0; 
       7 [-]: NAMECALL R0 R0 K0; var1 = var0; var0 = var0[0xEA061E98]
       8 [-]: CALL R0 3 1  ; var0(var1, var2)
       9 [-]: RETURN R0 0  ; 


; Name:            
; Defined at line: 246
; #Upvalues:       4
; #Parameters:     0
; Is_vararg:       0
; Max Stack Size:  4

       0 [-]: GETUPVAL R0 0; var0 = upvalues[0]
       1 [-]: JUMPIF R0 L0 ; goto L0 if var0
       2 [-]: RETURN R0 0  ; 
L 0:   3 [-]: GETUPVAL R0 1; var0 = upvalues[1]
       4 [-]: CALL R0 1 1  ; var0()
       5 [-]: LOADB R0 0   ; var0 = false
       6 [-]: GETUPVAL R2 2; var2 = upvalues[2]
       7 [-]: GETTABLEKS R1 R2 K0; var1 = var2[0x659D451F]
       8 [-]: GETIMPORT R3 2; var3 = 0x0032441C
       9 [-]: GETTABLEKS R2 R3 K3; var2 = var3["UISound_WindowClose"]
      10 [-]: CALL R1 2 1  ; var1(var2)
      11 [-]: GETIMPORT R1 6; var1 = _T["BackgroundMovie"]
      12 [-]: JUMPXEQKNIL R1 L1; 
      13 [-]: GETIMPORT R1 8; var1 = _T["IsInScreenStack"]
      14 [-]: LOADK R2 K9  ; var2 = "ItemBrowsing"
      15 [-]: CALL R1 2 2  ; var1 = var1(var2)
      16 [-]: MOVE R0 R1   ; var0 = var1
L 1:  17 [-]: JUMPIFNOT R0 L2; goto L2 if not var0
      18 [-]: GETIMPORT R1 11; var1 = _T["GoToPreviousScreen"]
      19 [-]: CALL R1 1 1  ; var1()
      20 [-]: RETURN R0 0  ; 
L 2:  21 [-]: GETUPVAL R1 3; var1 = upvalues[3]
      22 [-]: LOADB R2 1   ; var2 = true
      23 [-]: CALL R1 2 1  ; var1(var2)
      24 [-]: RETURN R0 0  ; 


; Name:            
; Defined at line: 264
; #Upvalues:       2
; #Parameters:     0
; Is_vararg:       0
; Max Stack Size:  1

       0 [-]: GETUPVAL R0 0; var0 = upvalues[0]
       1 [-]: CALL R0 1 1  ; var0()
       2 [-]: GETUPVAL R0 1; var0 = upvalues[1]
       3 [-]: CALL R0 1 1  ; var0()
       4 [-]: RETURN R0 0  ; 


; Name:            
; Defined at line: 270
; #Upvalues:       3
; #Parameters:     0
; Is_vararg:       0
; Max Stack Size:  14

       0 [-]: GETUPVAL R0 0; var0 = upvalues[0]
       1 [-]: GETUPVAL R2 1; var2 = upvalues[1]
       2 [-]: GETTABLEKS R1 R2 K0; var1 = var2[0x5D10207D]
       3 [-]: LOADN R2 9   ; var2 = 9
       4 [-]: LOADB R3 1   ; var3 = true
       5 [-]: CALL R1 3 2  ; var1 = var1(var2, var3)
       6 [-]: SETTABLEKS R1 R0 K1; var1["FloatingContent"] = var0
       7 [-]: GETUPVAL R0 0; var0 = upvalues[0]
       8 [-]: GETUPVAL R2 1; var2 = upvalues[1]
       9 [-]: GETTABLEKS R1 R2 K0; var1 = var2[0x5D10207D]
      10 [-]: LOADN R2 10  ; var2 = 10
      11 [-]: LOADB R3 1   ; var3 = true
      12 [-]: CALL R1 3 2  ; var1 = var1(var2, var3)
      13 [-]: SETTABLEKS R1 R0 K2; var1["FloatingContentHighlight"] = var0
      14 [-]: GETUPVAL R0 0; var0 = upvalues[0]
      15 [-]: GETUPVAL R2 1; var2 = upvalues[1]
      16 [-]: GETTABLEKS R1 R2 K0; var1 = var2[0x5D10207D]
      17 [-]: LOADN R2 2   ; var2 = 2
      18 [-]: LOADB R3 1   ; var3 = true
      19 [-]: CALL R1 3 2  ; var1 = var1(var2, var3)
      20 [-]: SETTABLEKS R1 R0 K3; var1["Background"] = var0
      21 [-]: GETUPVAL R0 0; var0 = upvalues[0]
      22 [-]: GETUPVAL R2 1; var2 = upvalues[1]
      23 [-]: GETTABLEKS R1 R2 K0; var1 = var2[0x5D10207D]
      24 [-]: LOADN R2 6   ; var2 = 6
      25 [-]: LOADB R3 1   ; var3 = true
      26 [-]: CALL R1 3 2  ; var1 = var1(var2, var3)
      27 [-]: SETTABLEKS R1 R0 K4; var1["Content"] = var0
      28 [-]: GETUPVAL R0 0; var0 = upvalues[0]
      29 [-]: GETUPVAL R2 2; var2 = upvalues[2]
      30 [-]: GETTABLEKS R1 R2 K5; var1 = var2[0x8BCD12B6]
      31 [-]: GETUPVAL R3 0; var3 = upvalues[0]
      32 [-]: GETTABLEKS R2 R3 K3; var2 = var3["Background"]
      33 [-]: CALL R1 2 2  ; var1 = var1(var2)
      34 [-]: SETTABLEKS R1 R0 K6; var1["BackgroundProcedural"] = var0
      35 [-]: GETUPVAL R0 0; var0 = upvalues[0]
      36 [-]: GETUPVAL R2 2; var2 = upvalues[2]
      37 [-]: GETTABLEKS R1 R2 K5; var1 = var2[0x8BCD12B6]
      38 [-]: GETUPVAL R3 0; var3 = upvalues[0]
      39 [-]: GETTABLEKS R2 R3 K1; var2 = var3["FloatingContent"]
      40 [-]: CALL R1 2 2  ; var1 = var1(var2)
      41 [-]: SETTABLEKS R1 R0 K7; var1["FloatingContentProcedural"] = var0
      42 [-]: GETUPVAL R0 0; var0 = upvalues[0]
      43 [-]: GETUPVAL R2 2; var2 = upvalues[2]
      44 [-]: GETTABLEKS R1 R2 K5; var1 = var2[0x8BCD12B6]
      45 [-]: GETUPVAL R3 0; var3 = upvalues[0]
      46 [-]: GETTABLEKS R2 R3 K2; var2 = var3["FloatingContentHighlight"]
      47 [-]: CALL R1 2 2  ; var1 = var1(var2)
      48 [-]: SETTABLEKS R1 R0 K8; var1["FloatingContentHighlightProcedural"] = var0
      49 [-]: GETUPVAL R0 0; var0 = upvalues[0]
      50 [-]: GETUPVAL R2 2; var2 = upvalues[2]
      51 [-]: GETTABLEKS R1 R2 K5; var1 = var2[0x8BCD12B6]
      52 [-]: GETUPVAL R3 0; var3 = upvalues[0]
      53 [-]: GETTABLEKS R2 R3 K4; var2 = var3["Content"]
      54 [-]: CALL R1 2 2  ; var1 = var1(var2)
      55 [-]: SETTABLEKS R1 R0 K9; var1["ContentHighlightProcedural"] = var0
      56 [-]: GETIMPORT R0 11; var0 = 0xAE91E43B
      57 [-]: LOADK R2 K12 ; var2 = "Container.Title"
      58 [-]: LOADN R3 36  ; var3 = 36
      59 [-]: GETUPVAL R5 0; var5 = upvalues[0]
      60 [-]: GETTABLEKS R4 R5 K1; var4 = var5["FloatingContent"]
      61 [-]: NAMECALL R0 R0 K13; var1 = var0; var0 = var0[0x67BC869F]
      62 [-]: CALL R0 5 1  ; var0(var1, var2, var3, var4)
      63 [-]: GETIMPORT R0 11; var0 = 0xAE91E43B
      64 [-]: LOADK R2 K14 ; var2 = "BgFill"
      65 [-]: GETIMPORT R4 16; var4 = 0x0032441C
      66 [-]: GETTABLEKS R3 R4 K17; var3 = var4["UIMaterial_RectangleNoDepth"]
      67 [-]: NAMECALL R0 R0 K18; var1 = var0; var0 = var0[0xD5181643]
      68 [-]: CALL R0 4 1  ; var0(var1, var2, var3)
      69 [-]: GETIMPORT R0 11; var0 = 0xAE91E43B
      70 [-]: LOADK R2 K14 ; var2 = "BgFill"
      71 [-]: LOADK R3 K19 ; var3 = "RectInnerColor"
      72 [-]: GETUPVAL R6 0; var6 = upvalues[0]
      73 [-]: GETTABLEKS R5 R6 K6; var5 = var6["BackgroundProcedural"]
      74 [-]: GETTABLEKS R4 R5 K20; var4 = var5["r"]
      75 [-]: GETUPVAL R7 0; var7 = upvalues[0]
      76 [-]: GETTABLEKS R6 R7 K6; var6 = var7["BackgroundProcedural"]
      77 [-]: GETTABLEKS R5 R6 K21; var5 = var6["g"]
      78 [-]: GETUPVAL R8 0; var8 = upvalues[0]
      79 [-]: GETTABLEKS R7 R8 K6; var7 = var8["BackgroundProcedural"]
      80 [-]: GETTABLEKS R6 R7 K22; var6 = var7["b"]
      81 [-]: LOADK R7 K23 ; var7 = 0.80000000000000004
      82 [-]: NAMECALL R0 R0 K24; var1 = var0; var0 = var0[0x91E13703]
      83 [-]: CALL R0 8 1  ; var0(var1, var2, var3, var4, var5, var6, var7)
      84 [-]: GETIMPORT R0 11; var0 = 0xAE91E43B
      85 [-]: LOADK R2 K14 ; var2 = "BgFill"
      86 [-]: LOADK R3 K25 ; var3 = "RectEdgeColor"
      87 [-]: GETUPVAL R6 0; var6 = upvalues[0]
      88 [-]: GETTABLEKS R5 R6 K7; var5 = var6["FloatingContentProcedural"]
      89 [-]: GETTABLEKS R4 R5 K20; var4 = var5["r"]
      90 [-]: GETUPVAL R7 0; var7 = upvalues[0]
      91 [-]: GETTABLEKS R6 R7 K7; var6 = var7["FloatingContentProcedural"]
      92 [-]: GETTABLEKS R5 R6 K21; var5 = var6["g"]
      93 [-]: GETUPVAL R8 0; var8 = upvalues[0]
      94 [-]: GETTABLEKS R7 R8 K7; var7 = var8["FloatingContentProcedural"]
      95 [-]: GETTABLEKS R6 R7 K22; var6 = var7["b"]
      96 [-]: LOADK R7 K26 ; var7 = 0.10000000000000001
      97 [-]: NAMECALL R0 R0 K24; var1 = var0; var0 = var0[0x91E13703]
      98 [-]: CALL R0 8 1  ; var0(var1, var2, var3, var4, var5, var6, var7)
      99 [-]: GETIMPORT R0 11; var0 = 0xAE91E43B
     100 [-]: GETUPVAL R3 0; var3 = upvalues[0]
     101 [-]: GETTABLEKS R2 R3 K3; var2 = var3["Background"]
     102 [-]: NAMECALL R0 R0 K27; var1 = var0; var0 = var0[0xC6A10AB1]
     103 [-]: CALL R0 3 1  ; var0(var1, var2)
     104 [-]: NEWTABLE R0 0 8; var0 = {}
     105 [-]: LOADK R1 K28 ; var1 = "FancyBits.LeftLines"
     106 [-]: LOADK R2 K29 ; var2 = "FancyBits.RightLines"
     107 [-]: LOADK R3 K30 ; var3 = "FancyBits.LeftSideLine.FadeLineTop"
     108 [-]: LOADK R4 K31 ; var4 = "FancyBits.LeftSideLine.FadeLineMiddle"
     109 [-]: LOADK R5 K32 ; var5 = "FancyBits.LeftSideLine.FadeLineBottom"
     110 [-]: LOADK R6 K33 ; var6 = "FancyBits.RightSideLine.FadeLineTop"
     111 [-]: LOADK R7 K34 ; var7 = "FancyBits.RightSideLine.FadeLineMiddle"
     112 [-]: LOADK R8 K35 ; var8 = "FancyBits.RightSideLine.FadeLineBottom"
     113 [-]: SETLIST R0 R1 8 [1]; var0[1] = var1; var0[2] = var2; var0[3] = var3; var0[4] = var4; var0[5] = var5; var0[6] = var6; var0[7] = var7; var0[8] = var8; var0[9] = var9; 
     114 [-]: LOADN R3 1   ; var3 = 1
     115 [-]: LENGTH R1 R0 ; var1 = #var0
     116 [-]: LOADN R2 1   ; var2 = 1
     117 [-]: FORNPREP R1 L1; nforprep start - [escape at L1] -- var1 = iterator
L 0: 118 [-]: GETTABLE R4 R0 R3; var4 = var0[var3]
     119 [-]: GETIMPORT R5 11; var5 = 0xAE91E43B
     120 [-]: MOVE R7 R4   ; var7 = var4
     121 [-]: LOADN R8 9   ; var8 = 9
     122 [-]: GETUPVAL R10 0; var10 = upvalues[0]
     123 [-]: GETTABLEKS R9 R10 K1; var9 = var10["FloatingContent"]
     124 [-]: NAMECALL R5 R5 K13; var6 = var5; var5 = var5[0x67BC869F]
     125 [-]: CALL R5 5 1  ; var5(var6, var7, var8, var9)
     126 [-]: GETIMPORT R5 11; var5 = 0xAE91E43B
     127 [-]: MOVE R7 R4   ; var7 = var4
     128 [-]: LOADK R8 K36 ; var8 = "RipplesColor"
     129 [-]: GETUPVAL R11 0; var11 = upvalues[0]
     130 [-]: GETTABLEKS R10 R11 K9; var10 = var11["ContentHighlightProcedural"]
     131 [-]: GETTABLEKS R9 R10 K20; var9 = var10["r"]
     132 [-]: GETUPVAL R12 0; var12 = upvalues[0]
     133 [-]: GETTABLEKS R11 R12 K9; var11 = var12["ContentHighlightProcedural"]
     134 [-]: GETTABLEKS R10 R11 K21; var10 = var11["g"]
     135 [-]: GETUPVAL R13 0; var13 = upvalues[0]
     136 [-]: GETTABLEKS R12 R13 K9; var12 = var13["ContentHighlightProcedural"]
     137 [-]: GETTABLEKS R11 R12 K22; var11 = var12["b"]
     138 [-]: LOADK R12 K37; var12 = 0.90000000000000002
     139 [-]: NAMECALL R5 R5 K24; var6 = var5; var5 = var5[0x91E13703]
     140 [-]: CALL R5 8 1  ; var5(var6, var7, var8, var9, var10, var11, var12)
     141 [-]: FORNLOOP R1 L0; nforloop end - iterate + goto L0
L 1: 142 [-]: RETURN R0 0  ; 


; Name:            
; Defined at line: 300
; #Upvalues:       1
; #Parameters:     0
; Is_vararg:       0
; Max Stack Size:  4

       0 [-]: GETUPVAL R2 0; var2 = upvalues[0]
       1 [-]: GETTABLEKS R1 R2 K0; var1 = var2["CustomBtn"]
       2 [-]: FASTCALL1 62 R1 L0; 
       3 [-]: GETIMPORT R0 2; var0 = 0x7B998233
       4 [-]: CALL R0 2 2  ; var0 = var0(var1)
L 0:   5 [-]: JUMPIFNOT R0 L1; goto L1 if not var0
       6 [-]: RETURN R0 0  ; 
L 1:   7 [-]: GETUPVAL R2 0; var2 = upvalues[0]
       8 [-]: GETTABLEKS R1 R2 K0; var1 = var2["CustomBtn"]
       9 [-]: GETTABLEKS R0 R1 K3; var0 = var1["Confirm"]
      10 [-]: JUMPIFNOT R0 L2; goto L2 if not var0
      11 [-]: GETIMPORT R0 5; var0 = 0xAE91E43B
      12 [-]: LOADK R2 K6  ; var2 = "ShowCustomButtonConfirmation"
      13 [-]: LOADK R3 K7  ; var3 = ""
      14 [-]: NAMECALL R0 R0 K8; var1 = var0; var0 = var0[0xE4162EED]
      15 [-]: CALL R0 4 1  ; var0(var1, var2, var3)
      16 [-]: RETURN R0 0  ; 
L 2:  17 [-]: GETUPVAL R2 0; var2 = upvalues[0]
      18 [-]: GETTABLEKS R1 R2 K0; var1 = var2["CustomBtn"]
      19 [-]: GETTABLEKS R0 R1 K9; var0 = var1["CallBack"]
      20 [-]: CALL R0 1 1  ; var0()
      21 [-]: RETURN R0 0  ; 


; Name:            
; Defined at line: 312
; #Upvalues:       2
; #Parameters:     2
; Is_vararg:       0
; Max Stack Size:  12

       0 [-]: GETUPVAL R2 0; var2 = upvalues[0]
       1 [-]: JUMPXEQKN R2 K0 L0 NOT; 
       2 [-]: DIVK R5 R1 K1; var5 = var1 / 2
       3 [-]: GETTABLEKS R7 R0 K2; var7 = var0["mMaxSize"]
       4 [-]: DIVK R6 R7 K1; var6 = var7 / 2
       5 [-]: SUB R4 R5 R6 ; var4 = var5 - var6
       6 [-]: NAMECALL R2 R0 K3; var3 = var0; var2 = var0[0x9307AA51]
       7 [-]: CALL R2 3 1  ; var2(var3, var4)
       8 [-]: RETURN R0 0  ; 
L 0:   9 [-]: GETUPVAL R2 0; var2 = upvalues[0]
      10 [-]: JUMPXEQKN R2 K1 L3 NOT; 
      11 [-]: DIVK R5 R1 K1; var5 = var1 / 2
      12 [-]: GETUPVAL R7 1; var7 = upvalues[1]
      13 [-]: GETTABLEKS R6 R7 K4; var6 = var7[0x06D055F9]
      14 [-]: GETTABLEKS R8 R0 K5; var8 = var0["PositionIdx"]
      15 [-]: JUMPXEQKN R8 K0 L1; 
      16 [-]: LOADB R7 0 +1; var7 = false
L 1:  17 [-]: LOADB R7 1   ; var7 = true
L 2:  18 [-]: GETTABLEKS R10 R0 K2; var10 = var0["mMaxSize"]
      19 [-]: MINUS R9 R10 ; 
      20 [-]: SUBK R8 R9 K6; var8 = var9 - 5
      21 [-]: LOADN R9 5   ; var9 = 5
      22 [-]: CALL R6 4 2  ; var6 = var6(var7, var8, var9)
      23 [-]: ADD R4 R5 R6 ; var4 = var5 + var6
      24 [-]: NAMECALL R2 R0 K3; var3 = var0; var2 = var0[0x9307AA51]
      25 [-]: CALL R2 3 1  ; var2(var3, var4)
      26 [-]: RETURN R0 0  ; 
L 3:  27 [-]: GETUPVAL R2 0; var2 = upvalues[0]
      28 [-]: JUMPXEQKN R2 K7 L7 NOT; 
      29 [-]: GETTABLEKS R2 R0 K5; var2 = var0["PositionIdx"]
      30 [-]: JUMPXEQKN R2 K1 L4 NOT; 
      31 [-]: DIVK R5 R1 K1; var5 = var1 / 2
      32 [-]: GETTABLEKS R7 R0 K2; var7 = var0["mMaxSize"]
      33 [-]: DIVK R6 R7 K1; var6 = var7 / 2
      34 [-]: SUB R4 R5 R6 ; var4 = var5 - var6
      35 [-]: NAMECALL R2 R0 K3; var3 = var0; var2 = var0[0x9307AA51]
      36 [-]: CALL R2 3 1  ; var2(var3, var4)
      37 [-]: RETURN R0 0  ; 
L 4:  38 [-]: DIVK R5 R1 K1; var5 = var1 / 2
      39 [-]: GETUPVAL R7 1; var7 = upvalues[1]
      40 [-]: GETTABLEKS R6 R7 K4; var6 = var7[0x06D055F9]
      41 [-]: GETTABLEKS R8 R0 K5; var8 = var0["PositionIdx"]
      42 [-]: JUMPXEQKN R8 K0 L5; 
      43 [-]: LOADB R7 0 +1; var7 = false
L 5:  44 [-]: LOADB R7 1   ; var7 = true
L 6:  45 [-]: GETTABLEKS R11 R0 K2; var11 = var0["mMaxSize"]
      46 [-]: MINUS R10 R11; 
      47 [-]: MULK R9 R10 K9; var9 = var10 * 1.5
      48 [-]: SUBK R8 R9 K8; var8 = var9 - 10
      49 [-]: GETTABLEKS R11 R0 K2; var11 = var0["mMaxSize"]
      50 [-]: DIVK R10 R11 K1; var10 = var11 / 2
      51 [-]: ADDK R9 R10 K8; var9 = var10 + 10
      52 [-]: CALL R6 4 2  ; var6 = var6(var7, var8, var9)
      53 [-]: ADD R4 R5 R6 ; var4 = var5 + var6
      54 [-]: NAMECALL R2 R0 K3; var3 = var0; var2 = var0[0x9307AA51]
      55 [-]: CALL R2 3 1  ; var2(var3, var4)
L 7:  56 [-]: RETURN R0 0  ; 


; Name:            
; Defined at line: 326
; #Upvalues:       12
; #Parameters:     0
; Is_vararg:       0
; Max Stack Size:  11

       0 [-]: LOADN R0 0   ; var0 = 0
       1 [-]: SETUPVAL R0 0; upvalues[0] = var0
       2 [-]: GETUPVAL R0 1; var0 = upvalues[1]
       3 [-]: JUMPIF R0 L0 ; goto L0 if var0
       4 [-]: GETUPVAL R0 2; var0 = upvalues[2]
       5 [-]: JUMPIFNOT R0 L2; goto L2 if not var0
L 0:   6 [-]: GETIMPORT R0 1; var0 = 0xAE91E43B
       7 [-]: LOADK R2 K2  ; var2 = "Container.ButtonContainer.ConfirmButton"
       8 [-]: LOADN R3 11  ; var3 = 11
       9 [-]: LOADB R4 1   ; var4 = true
      10 [-]: NAMECALL R0 R0 K3; var1 = var0; var0 = var0[0xAADE900E]
      11 [-]: CALL R0 5 1  ; var0(var1, var2, var3, var4)
      12 [-]: GETUPVAL R1 3; var1 = upvalues[3]
      13 [-]: GETTABLEKS R0 R1 K4; var0 = var1["ConfirmBtn"]
      14 [-]: JUMPXEQKNIL R0 L1 NOT; 
      15 [-]: GETUPVAL R0 3; var0 = upvalues[3]
      16 [-]: GETUPVAL R2 4; var2 = upvalues[4]
      17 [-]: GETTABLEKS R1 R2 K5; var1 = var2[0xAE6791BA]
      18 [-]: GETIMPORT R2 1; var2 = 0xAE91E43B
      19 [-]: LOADK R3 K2  ; var3 = "Container.ButtonContainer.ConfirmButton"
      20 [-]: GETUPVAL R4 5; var4 = upvalues[5]
      21 [-]: LOADK R5 K6  ; var5 = "FinishSelection"
      22 [-]: LOADK R6 K7  ; var6 = "<MENU_GENERIC1>"
      23 [-]: CALL R1 6 2  ; var1 = var1(var2, var3, var4, var5, var6)
      24 [-]: SETTABLEKS R1 R0 K4; var1["ConfirmBtn"] = var0
L 1:  25 [-]: GETUPVAL R1 3; var1 = upvalues[3]
      26 [-]: GETTABLEKS R0 R1 K4; var0 = var1["ConfirmBtn"]
      27 [-]: GETUPVAL R2 1; var2 = upvalues[1]
      28 [-]: NAMECALL R0 R0 K8; var1 = var0; var0 = var0[0x46610C50]
      29 [-]: CALL R0 3 1  ; var0(var1, var2)
      30 [-]: GETUPVAL R1 0; var1 = upvalues[0]
      31 [-]: ADDK R0 R1 K9; var0 = var1 + 1
      32 [-]: SETUPVAL R0 0; upvalues[0] = var0
      33 [-]: GETUPVAL R1 3; var1 = upvalues[3]
      34 [-]: GETTABLEKS R0 R1 K4; var0 = var1["ConfirmBtn"]
      35 [-]: GETUPVAL R1 0; var1 = upvalues[0]
      36 [-]: SETTABLEKS R1 R0 K10; var1["PositionIdx"] = var0
      37 [-]: JUMP L3      ; goto L3
L 2:  38 [-]: GETUPVAL R0 3; var0 = upvalues[3]
      39 [-]: LOADNIL R1   ; var1 = nil
      40 [-]: SETTABLEKS R1 R0 K4; var1["ConfirmBtn"] = var0
      41 [-]: GETIMPORT R0 1; var0 = 0xAE91E43B
      42 [-]: LOADK R2 K2  ; var2 = "Container.ButtonContainer.ConfirmButton"
      43 [-]: LOADN R3 11  ; var3 = 11
      44 [-]: LOADB R4 0   ; var4 = false
      45 [-]: NAMECALL R0 R0 K3; var1 = var0; var0 = var0[0xAADE900E]
      46 [-]: CALL R0 5 1  ; var0(var1, var2, var3, var4)
L 3:  47 [-]: GETUPVAL R1 6; var1 = upvalues[6]
      48 [-]: FASTCALL1 62 R1 L4; 
      49 [-]: GETIMPORT R0 12; var0 = 0x7B998233
      50 [-]: CALL R0 2 2  ; var0 = var0(var1)
L 4:  51 [-]: JUMPIF R0 L10; goto L10 if var0
      52 [-]: GETIMPORT R2 14; var2 = _T
      53 [-]: GETUPVAL R3 6; var3 = upvalues[6]
      54 [-]: GETTABLE R1 R2 R3; var1 = var2[var3]
      55 [-]: FASTCALL1 62 R1 L5; 
      56 [-]: GETIMPORT R0 12; var0 = 0x7B998233
      57 [-]: CALL R0 2 2  ; var0 = var0(var1)
L 5:  58 [-]: JUMPIF R0 L10; goto L10 if var0
      59 [-]: GETIMPORT R1 14; var1 = _T
      60 [-]: GETUPVAL R2 6; var2 = upvalues[6]
      61 [-]: GETTABLE R0 R1 R2; var0 = var1[var2]
      62 [-]: CALL R0 1 2  ; var0 = var0()
      63 [-]: GETUPVAL R2 3; var2 = upvalues[3]
      64 [-]: GETTABLEKS R1 R2 K15; var1 = var2["CustomBtn"]
      65 [-]: JUMPXEQKNIL R1 L6 NOT; 
      66 [-]: GETUPVAL R1 3; var1 = upvalues[3]
      67 [-]: GETUPVAL R3 4; var3 = upvalues[4]
      68 [-]: GETTABLEKS R2 R3 K5; var2 = var3[0xAE6791BA]
      69 [-]: GETIMPORT R3 1; var3 = 0xAE91E43B
      70 [-]: LOADK R4 K16 ; var4 = "Container.ButtonContainer.CustomButton"
      71 [-]: GETTABLEKS R5 R0 K17; var5 = var0["Label"]
      72 [-]: LOADK R6 K18 ; var6 = "OnCustomButtonPressed"
      73 [-]: LOADK R8 K19 ; var8 = "<"
      74 [-]: GETTABLEKS R9 R0 K20; var9 = var0["CallOut"]
      75 [-]: LOADK R10 K21; var10 = ">"
      76 [-]: CONCAT R7 R8 R10; var7 = var8 .. var10
      77 [-]: CALL R2 6 2  ; var2 = var2(var3, var4, var5, var6, var7)
      78 [-]: SETTABLEKS R2 R1 K15; var2["CustomBtn"] = var1
L 6:  79 [-]: GETTABLEKS R2 R0 K22; var2 = var0["ConfirmCallback"]
      80 [-]: FASTCALL1 62 R2 L7; 
      81 [-]: GETIMPORT R1 12; var1 = 0x7B998233
      82 [-]: CALL R1 2 2  ; var1 = var1(var2)
L 7:  83 [-]: JUMPIF R1 L8 ; goto L8 if var1
      84 [-]: GETUPVAL R1 7; var1 = upvalues[7]
      85 [-]: GETTABLEKS R2 R0 K23; var2 = var0["ConfirmLabel"]
      86 [-]: SETTABLEKS R2 R1 K23; var2["ConfirmLabel"] = var1
      87 [-]: GETTABLEKS R1 R0 K22; var1 = var0["ConfirmCallback"]
      88 [-]: SETUPVAL R1 8; upvalues[1] = var8
      89 [-]: GETUPVAL R2 3; var2 = upvalues[3]
      90 [-]: GETTABLEKS R1 R2 K15; var1 = var2["CustomBtn"]
      91 [-]: LOADB R2 1   ; var2 = true
      92 [-]: SETTABLEKS R2 R1 K24; var2["Confirm"] = var1
      93 [-]: JUMP L9      ; goto L9
L 8:  94 [-]: GETUPVAL R2 3; var2 = upvalues[3]
      95 [-]: GETTABLEKS R1 R2 K15; var1 = var2["CustomBtn"]
      96 [-]: LOADNIL R2   ; var2 = nil
      97 [-]: SETTABLEKS R2 R1 K24; var2["Confirm"] = var1
      98 [-]: GETUPVAL R2 3; var2 = upvalues[3]
      99 [-]: GETTABLEKS R1 R2 K15; var1 = var2["CustomBtn"]
     100 [-]: GETTABLEKS R2 R0 K25; var2 = var0["CallBack"]
     101 [-]: SETTABLEKS R2 R1 K25; var2["CallBack"] = var1
L 9: 102 [-]: GETUPVAL R1 7; var1 = upvalues[7]
     103 [-]: GETTABLEKS R2 R0 K17; var2 = var0["Label"]
     104 [-]: SETTABLEKS R2 R1 K17; var2["Label"] = var1
     105 [-]: GETUPVAL R2 0; var2 = upvalues[0]
     106 [-]: ADDK R1 R2 K9; var1 = var2 + 1
     107 [-]: SETUPVAL R1 0; upvalues[1] = var0
     108 [-]: GETUPVAL R2 3; var2 = upvalues[3]
     109 [-]: GETTABLEKS R1 R2 K15; var1 = var2["CustomBtn"]
     110 [-]: GETUPVAL R2 0; var2 = upvalues[0]
     111 [-]: SETTABLEKS R2 R1 K10; var2["PositionIdx"] = var1
     112 [-]: GETIMPORT R1 1; var1 = 0xAE91E43B
     113 [-]: LOADK R3 K16 ; var3 = "Container.ButtonContainer.CustomButton"
     114 [-]: LOADN R4 11  ; var4 = 11
     115 [-]: LOADB R5 1   ; var5 = true
     116 [-]: NAMECALL R1 R1 K3; var2 = var1; var1 = var1[0xAADE900E]
     117 [-]: CALL R1 5 1  ; var1(var2, var3, var4, var5)
     118 [-]: JUMP L11     ; goto L11
L10: 119 [-]: GETUPVAL R0 3; var0 = upvalues[3]
     120 [-]: LOADNIL R1   ; var1 = nil
     121 [-]: SETTABLEKS R1 R0 K15; var1["CustomBtn"] = var0
     122 [-]: GETIMPORT R0 1; var0 = 0xAE91E43B
     123 [-]: LOADK R2 K16 ; var2 = "Container.ButtonContainer.CustomButton"
     124 [-]: LOADN R3 11  ; var3 = 11
     125 [-]: LOADB R4 0   ; var4 = false
     126 [-]: NAMECALL R0 R0 K3; var1 = var0; var0 = var0[0xAADE900E]
     127 [-]: CALL R0 5 1  ; var0(var1, var2, var3, var4)
L11: 128 [-]: GETUPVAL R0 9; var0 = upvalues[9]
     129 [-]: JUMPIFNOT R0 L13; goto L13 if not var0
     130 [-]: GETUPVAL R1 3; var1 = upvalues[3]
     131 [-]: GETTABLEKS R0 R1 K26; var0 = var1["CancelBtn"]
     132 [-]: JUMPXEQKNIL R0 L12 NOT; 
     133 [-]: GETUPVAL R0 3; var0 = upvalues[3]
     134 [-]: GETUPVAL R2 4; var2 = upvalues[4]
     135 [-]: GETTABLEKS R1 R2 K5; var1 = var2[0xAE6791BA]
     136 [-]: GETIMPORT R2 1; var2 = 0xAE91E43B
     137 [-]: LOADK R3 K27 ; var3 = "Container.ButtonContainer.CancelButton"
     138 [-]: LOADK R4 K28 ; var4 = "/Menu/Confirm_Item_Cancel"
     139 [-]: LOADK R5 K29 ; var5 = "ExitScreen"
     140 [-]: LOADK R6 K30 ; var6 = "<MENU_CANCEL>"
     141 [-]: CALL R1 6 2  ; var1 = var1(var2, var3, var4, var5, var6)
     142 [-]: SETTABLEKS R1 R0 K26; var1["CancelBtn"] = var0
L12: 143 [-]: GETUPVAL R1 0; var1 = upvalues[0]
     144 [-]: ADDK R0 R1 K9; var0 = var1 + 1
     145 [-]: SETUPVAL R0 0; upvalues[0] = var0
     146 [-]: GETUPVAL R1 3; var1 = upvalues[3]
     147 [-]: GETTABLEKS R0 R1 K26; var0 = var1["CancelBtn"]
     148 [-]: GETUPVAL R1 0; var1 = upvalues[0]
     149 [-]: SETTABLEKS R1 R0 K10; var1["PositionIdx"] = var0
     150 [-]: GETIMPORT R0 1; var0 = 0xAE91E43B
     151 [-]: LOADK R2 K27 ; var2 = "Container.ButtonContainer.CancelButton"
     152 [-]: LOADN R3 11  ; var3 = 11
     153 [-]: LOADB R4 1   ; var4 = true
     154 [-]: NAMECALL R0 R0 K3; var1 = var0; var0 = var0[0xAADE900E]
     155 [-]: CALL R0 5 1  ; var0(var1, var2, var3, var4)
     156 [-]: JUMP L14     ; goto L14
L13: 157 [-]: GETUPVAL R0 3; var0 = upvalues[3]
     158 [-]: LOADNIL R1   ; var1 = nil
     159 [-]: SETTABLEKS R1 R0 K26; var1["CancelBtn"] = var0
     160 [-]: GETIMPORT R0 1; var0 = 0xAE91E43B
     161 [-]: LOADK R2 K27 ; var2 = "Container.ButtonContainer.CancelButton"
     162 [-]: LOADN R3 11  ; var3 = 11
     163 [-]: LOADB R4 0   ; var4 = false
     164 [-]: NAMECALL R0 R0 K3; var1 = var0; var0 = var0[0xAADE900E]
     165 [-]: CALL R0 5 1  ; var0(var1, var2, var3, var4)
L14: 166 [-]: GETUPVAL R0 10; var0 = upvalues[10]
     167 [-]: CALL R0 1 1  ; var0()
     168 [-]: GETUPVAL R0 0; var0 = upvalues[0]
     169 [-]: LOADN R1 0   ; var1 = 0
     170 [-]: JUMPIFNOTLT R1 R0 L17; goto L17 if var1 >= var65614
     171 [-]: GETIMPORT R0 1; var0 = 0xAE91E43B
     172 [-]: LOADK R2 K31 ; var2 = "BgFill"
     173 [-]: LOADN R3 12  ; var3 = 12
     174 [-]: NAMECALL R0 R0 K32; var1 = var0; var0 = var0[0x91A24E4B]
     175 [-]: CALL R0 4 2  ; var0 = var0(var1, var2, var3)
     176 [-]: GETUPVAL R3 0; var3 = upvalues[0]
     177 [-]: ADDK R2 R3 K9; var2 = var3 + 1
     178 [-]: DIV R1 R0 R2 ; var1 = var0 / var2
     179 [-]: GETIMPORT R2 34; var2 = 0xCFC01047
     180 [-]: GETUPVAL R3 3; var3 = upvalues[3]
     181 [-]: CALL R2 2 4  ; var2, var3, var4 = var2(var3)
     182 [-]: FORGPREP_NEXT R2 L16; 
L15: 183 [-]: MOVE R9 R1   ; var9 = var1
     184 [-]: NAMECALL R7 R6 K35; var8 = var6; var7 = var6[0x8D77B2B2]
     185 [-]: CALL R7 3 1  ; var7(var8, var9)
     186 [-]: GETUPVAL R7 11; var7 = upvalues[11]
     187 [-]: MOVE R8 R6   ; var8 = var6
     188 [-]: MOVE R9 R0   ; var9 = var0
     189 [-]: CALL R7 3 1  ; var7(var8, var9)
L16: 190 [-]: FORGLOOP R2 L15 2; 
L17: 191 [-]: GETIMPORT R0 37; var0 = _T["SetButtons"]
     192 [-]: GETIMPORT R1 1; var1 = 0xAE91E43B
     193 [-]: LOADNIL R2   ; var2 = nil
     194 [-]: CALL R0 3 1  ; var0(var1, var2)
     195 [-]: RETURN R0 0  ; 


; Name:            
; Defined at line: 396
; #Upvalues:       5
; #Parameters:     0
; Is_vararg:       0
; Max Stack Size:  4

       0 [-]: GETUPVAL R0 0; var0 = upvalues[0]
       1 [-]: JUMPXEQKNIL R0 L0 NOT; 
       2 [-]: RETURN R0 0  ; 
L 0:   3 [-]: GETUPVAL R0 0; var0 = upvalues[0]
       4 [-]: LOADB R1 1   ; var1 = true
       5 [-]: SETTABLEKS R1 R0 K0; var1["mChanged"] = var0
       6 [-]: GETUPVAL R0 1; var0 = upvalues[1]
       7 [-]: JUMPXEQKNIL R0 L1; 
       8 [-]: GETUPVAL R0 1; var0 = upvalues[1]
       9 [-]: LOADB R1 1   ; var1 = true
      10 [-]: SETTABLEKS R1 R0 K0; var1["mChanged"] = var0
L 1:  11 [-]: LOADB R0 1   ; var0 = true
      12 [-]: SETUPVAL R0 2; upvalues[0] = var2
      13 [-]: GETUPVAL R1 3; var1 = upvalues[3]
      14 [-]: FASTCALL1 62 R1 L2; 
      15 [-]: GETIMPORT R0 2; var0 = 0x7B998233
      16 [-]: CALL R0 2 2  ; var0 = var0(var1)
L 2:  17 [-]: JUMPIF R0 L4 ; goto L4 if var0
      18 [-]: GETIMPORT R2 4; var2 = _T
      19 [-]: GETUPVAL R3 3; var3 = upvalues[3]
      20 [-]: GETTABLE R1 R2 R3; var1 = var2[var3]
      21 [-]: FASTCALL1 62 R1 L3; 
      22 [-]: GETIMPORT R0 2; var0 = 0x7B998233
      23 [-]: CALL R0 2 2  ; var0 = var0(var1)
L 3:  24 [-]: JUMPIF R0 L4 ; goto L4 if var0
      25 [-]: GETIMPORT R1 4; var1 = _T
      26 [-]: GETUPVAL R2 3; var2 = upvalues[3]
      27 [-]: GETTABLE R0 R1 R2; var0 = var1[var2]
      28 [-]: GETUPVAL R2 0; var2 = upvalues[0]
      29 [-]: GETTABLEKS R1 R2 K5; var1 = var2["mValue"]
      30 [-]: CALL R0 2 1  ; var0(var1)
L 4:  31 [-]: GETUPVAL R0 4; var0 = upvalues[4]
      32 [-]: CALL R0 1 1  ; var0()
      33 [-]: RETURN R0 0  ; 


; Name:            
; Defined at line: 413
; #Upvalues:       3
; #Parameters:     1
; Is_vararg:       0
; Max Stack Size:  3

       0 [-]: GETUPVAL R1 0; var1 = upvalues[0]
       1 [-]: CALL R1 1 1  ; var1()
       2 [-]: GETUPVAL R1 1; var1 = upvalues[1]
       3 [-]: SETTABLEKS R0 R1 K0; var0["mValue"] = var1
       4 [-]: GETUPVAL R2 1; var2 = upvalues[1]
       5 [-]: GETTABLEKS R1 R2 K1; var1 = var2["mCallback"]
       6 [-]: JUMPIFNOT R1 L0; goto L0 if not var1
       7 [-]: GETUPVAL R2 1; var2 = upvalues[1]
       8 [-]: GETTABLEKS R1 R2 K1; var1 = var2["mCallback"]
       9 [-]: MOVE R2 R0   ; var2 = var0
      10 [-]: CALL R1 2 1  ; var1(var2)
L 0:  11 [-]: GETUPVAL R2 2; var2 = upvalues[2]
      12 [-]: GETTABLEKS R1 R2 K2; var1 = var2["mElementDrawCallback"]
      13 [-]: GETUPVAL R2 1; var2 = upvalues[1]
      14 [-]: CALL R1 2 1  ; var1(var2)
      15 [-]: RETURN R0 0  ; 


; Name:            
; Defined at line: 463
; #Upvalues:       5
; #Parameters:     0
; Is_vararg:       0
; Max Stack Size:  17

       0 [-]: GETIMPORT R0 1; var0 = 0xAE91E43B
       1 [-]: LOADK R2 K2  ; var2 = "Container.Title"
       2 [-]: LOADN R3 34  ; var3 = 34
       3 [-]: NAMECALL R0 R0 K3; var1 = var0; var0 = var0[0x91A24E4B]
       4 [-]: CALL R0 4 2  ; var0 = var0(var1, var2, var3)
       5 [-]: ADDK R1 R0 K4; var1 = var0 + 15
       6 [-]: LOADN R2 0   ; var2 = 0
       7 [-]: LOADN R3 0   ; var3 = 0
       8 [-]: GETUPVAL R4 0; var4 = upvalues[0]
       9 [-]: NEWCLOSURE R6 P0; 
      10 [-]: CAPTURE REF R1; 
      11 [-]: CAPTURE UPVAL U0; 
      12 [-]: CAPTURE REF R2; 
      13 [-]: CAPTURE REF R3; 
      14 [-]: NAMECALL R4 R4 K5; var5 = var4; var4 = var4[0xEA061E98]
      15 [-]: CALL R4 3 1  ; var4(var5, var6)
      16 [-]: LOADN R6 10  ; var6 = 10
      17 [-]: ADD R5 R6 R1 ; var5 = var6 + var1
      18 [-]: FASTCALL2K 18 R5 K6 L0; 
      19 [-]: LOADK R6 K6  ; var6 = 100
      20 [-]: GETIMPORT R4 9; var4 = 0x5BCED4C4[0xB62ECFE0]
      21 [-]: CALL R4 3 2  ; var4 = var4(var5, var6)
L 0:  22 [-]: LOADN R7 40  ; var7 = 40
      23 [-]: ADD R6 R7 R2 ; var6 = var7 + var2
      24 [-]: FASTCALL2K 18 R6 K6 L1; 
      25 [-]: LOADK R7 K6  ; var7 = 100
      26 [-]: GETIMPORT R5 9; var5 = 0x5BCED4C4[0xB62ECFE0]
      27 [-]: CALL R5 3 2  ; var5 = var5(var6, var7)
L 1:  28 [-]: GETUPVAL R6 1; var6 = upvalues[1]
      29 [-]: JUMPIFNOT R6 L2; goto L2 if not var6
      30 [-]: JUMPXEQKN R3 K10 L2; 
      31 [-]: SUB R7 R5 R3 ; var7 = var5 - var3
      32 [-]: DIVK R6 R7 K11; var6 = var7 / 2
      33 [-]: GETUPVAL R7 0; var7 = upvalues[0]
      34 [-]: NEWCLOSURE R9 P1; 
      35 [-]: CAPTURE UPVAL U2; 
      36 [-]: CAPTURE VAL R6; 
      37 [-]: CAPTURE REF R3; 
      38 [-]: NAMECALL R7 R7 K5; var8 = var7; var7 = var7[0xEA061E98]
      39 [-]: CALL R7 3 1  ; var7(var8, var9)
L 2:  40 [-]: GETUPVAL R7 3; var7 = upvalues[3]
      41 [-]: GETTABLEKS R6 R7 K12; var6 = var7[0x74A11EC6]
      42 [-]: GETIMPORT R9 1; var9 = 0xAE91E43B
      43 [-]: NAMECALL R9 R9 K13; var10 = var9; var9 = var9[0x2CC9D281]
      44 [-]: CALL R9 2 2  ; var9 = var9(var10)
      45 [-]: SUB R8 R9 R4 ; var8 = var9 - var4
      46 [-]: DIVK R7 R8 K11; var7 = var8 / 2
      47 [-]: CALL R6 2 2  ; var6 = var6(var7)
      48 [-]: GETUPVAL R8 3; var8 = upvalues[3]
      49 [-]: GETTABLEKS R7 R8 K12; var7 = var8[0x74A11EC6]
      50 [-]: GETIMPORT R10 1; var10 = 0xAE91E43B
      51 [-]: NAMECALL R10 R10 K14; var11 = var10; var10 = var10[0x091C120E]
      52 [-]: CALL R10 2 2 ; var10 = var10(var11)
      53 [-]: SUB R9 R10 R5; var9 = var10 - var5
      54 [-]: DIVK R8 R9 K11; var8 = var9 / 2
      55 [-]: CALL R7 2 2  ; var7 = var7(var8)
      56 [-]: GETUPVAL R9 3; var9 = upvalues[3]
      57 [-]: GETTABLEKS R8 R9 K15; var8 = var9[0x06D055F9]
      58 [-]: GETUPVAL R10 4; var10 = upvalues[4]
      59 [-]: LOADN R11 0  ; var11 = 0
      60 [-]: JUMPIFLT R11 R10 L3; goto L3 if var11 < var16779547
      61 [-]: LOADB R9 0 +1; var9 = false
L 3:  62 [-]: LOADB R9 1   ; var9 = true
L 4:  63 [-]: LOADN R10 52 ; var10 = 52
      64 [-]: LOADN R11 0  ; var11 = 0
      65 [-]: CALL R8 4 2  ; var8 = var8(var9, var10, var11)
      66 [-]: GETIMPORT R9 1; var9 = 0xAE91E43B
      67 [-]: LOADK R11 K16; var11 = "Container.ButtonContainer"
      68 [-]: LOADN R12 1  ; var12 = 1
      69 [-]: ADD R13 R1 R8; var13 = var1 + var8
      70 [-]: NAMECALL R9 R9 K17; var10 = var9; var9 = var9[0x67BC869F]
      71 [-]: CALL R9 5 1  ; var9(var10, var11, var12, var13)
      72 [-]: GETIMPORT R9 1; var9 = 0xAE91E43B
      73 [-]: LOADK R11 K18; var11 = "BgFill"
      74 [-]: LOADN R12 0  ; var12 = 0
      75 [-]: MOVE R13 R7  ; var13 = var7
      76 [-]: NAMECALL R9 R9 K17; var10 = var9; var9 = var9[0x67BC869F]
      77 [-]: CALL R9 5 1  ; var9(var10, var11, var12, var13)
      78 [-]: GETIMPORT R9 1; var9 = 0xAE91E43B
      79 [-]: LOADK R11 K18; var11 = "BgFill"
      80 [-]: LOADN R12 1  ; var12 = 1
      81 [-]: SUBK R14 R6 K19; var14 = var6 - 32
      82 [-]: DIVK R15 R8 K11; var15 = var8 / 2
      83 [-]: SUB R13 R14 R15; var13 = var14 - var15
      84 [-]: NAMECALL R9 R9 K17; var10 = var9; var9 = var9[0x67BC869F]
      85 [-]: CALL R9 5 1  ; var9(var10, var11, var12, var13)
      86 [-]: GETIMPORT R9 1; var9 = 0xAE91E43B
      87 [-]: LOADK R11 K18; var11 = "BgFill"
      88 [-]: LOADN R12 13 ; var12 = 13
      89 [-]: ADDK R14 R4 K20; var14 = var4 + 48
      90 [-]: ADD R13 R14 R8; var13 = var14 + var8
      91 [-]: NAMECALL R9 R9 K17; var10 = var9; var9 = var9[0x67BC869F]
      92 [-]: CALL R9 5 1  ; var9(var10, var11, var12, var13)
      93 [-]: GETIMPORT R9 1; var9 = 0xAE91E43B
      94 [-]: LOADK R11 K18; var11 = "BgFill"
      95 [-]: LOADN R12 12 ; var12 = 12
      96 [-]: MOVE R13 R5  ; var13 = var5
      97 [-]: NAMECALL R9 R9 K17; var10 = var9; var9 = var9[0x67BC869F]
      98 [-]: CALL R9 5 1  ; var9(var10, var11, var12, var13)
      99 [-]: GETIMPORT R9 1; var9 = 0xAE91E43B
     100 [-]: LOADK R11 K2 ; var11 = "Container.Title"
     101 [-]: LOADN R12 12 ; var12 = 12
     102 [-]: MOVE R13 R5  ; var13 = var5
     103 [-]: NAMECALL R9 R9 K17; var10 = var9; var9 = var9[0x67BC869F]
     104 [-]: CALL R9 5 1  ; var9(var10, var11, var12, var13)
     105 [-]: GETIMPORT R9 1; var9 = 0xAE91E43B
     106 [-]: LOADK R11 K21; var11 = "Container"
     107 [-]: LOADN R12 0  ; var12 = 0
     108 [-]: SUBK R13 R7 K22; var13 = var7 - 3
     109 [-]: NAMECALL R9 R9 K17; var10 = var9; var9 = var9[0x67BC869F]
     110 [-]: CALL R9 5 1  ; var9(var10, var11, var12, var13)
     111 [-]: GETIMPORT R9 1; var9 = 0xAE91E43B
     112 [-]: LOADK R11 K21; var11 = "Container"
     113 [-]: LOADN R12 1  ; var12 = 1
     114 [-]: SUBK R14 R6 K23; var14 = var6 - 20
     115 [-]: DIVK R15 R8 K11; var15 = var8 / 2
     116 [-]: SUB R13 R14 R15; var13 = var14 - var15
     117 [-]: NAMECALL R9 R9 K17; var10 = var9; var9 = var9[0x67BC869F]
     118 [-]: CALL R9 5 1  ; var9(var10, var11, var12, var13)
     119 [-]: DIVK R9 R5 K11; var9 = var5 / 2
     120 [-]: ADDK R12 R6 K24; var12 = var6 + 16
     121 [-]: DIVK R13 R4 K11; var13 = var4 / 2
     122 [-]: ADD R11 R12 R13; var11 = var12 + var13
     123 [-]: DIVK R12 R8 K11; var12 = var8 / 2
     124 [-]: SUB R10 R11 R12; var10 = var11 - var12
     125 [-]: GETIMPORT R11 1; var11 = 0xAE91E43B
     126 [-]: LOADK R13 K25; var13 = "FancyBits"
     127 [-]: LOADN R14 1  ; var14 = 1
     128 [-]: MOVE R15 R10 ; var15 = var10
     129 [-]: NAMECALL R11 R11 K17; var12 = var11; var11 = var11[0x67BC869F]
     130 [-]: CALL R11 5 1 ; var11(var12, var13, var14, var15)
     131 [-]: GETIMPORT R11 1; var11 = 0xAE91E43B
     132 [-]: LOADK R13 K26; var13 = "FancyBits.LeftLines"
     133 [-]: LOADN R14 0  ; var14 = 0
     134 [-]: MINUS R16 R9 ; 
     135 [-]: ADDK R15 R16 K27; var15 = var16 + 1
     136 [-]: NAMECALL R11 R11 K17; var12 = var11; var11 = var11[0x67BC869F]
     137 [-]: CALL R11 5 1 ; var11(var12, var13, var14, var15)
     138 [-]: GETIMPORT R11 1; var11 = 0xAE91E43B
     139 [-]: LOADK R13 K28; var13 = "FancyBits.RightLines"
     140 [-]: LOADN R14 0  ; var14 = 0
     141 [-]: SUBK R15 R9 K27; var15 = var9 - 1
     142 [-]: NAMECALL R11 R11 K17; var12 = var11; var11 = var11[0x67BC869F]
     143 [-]: CALL R11 5 1 ; var11(var12, var13, var14, var15)
     144 [-]: GETIMPORT R11 1; var11 = 0xAE91E43B
     145 [-]: LOADK R13 K29; var13 = "FancyBits.LeftSideLine"
     146 [-]: LOADN R14 0  ; var14 = 0
     147 [-]: MINUS R16 R9 ; 
     148 [-]: ADDK R15 R16 K11; var15 = var16 + 2
     149 [-]: NAMECALL R11 R11 K17; var12 = var11; var11 = var11[0x67BC869F]
     150 [-]: CALL R11 5 1 ; var11(var12, var13, var14, var15)
     151 [-]: GETIMPORT R11 1; var11 = 0xAE91E43B
     152 [-]: LOADK R13 K30; var13 = "FancyBits.RightSideLine"
     153 [-]: LOADN R14 0  ; var14 = 0
     154 [-]: SUBK R15 R9 K27; var15 = var9 - 1
     155 [-]: NAMECALL R11 R11 K17; var12 = var11; var11 = var11[0x67BC869F]
     156 [-]: CALL R11 5 1 ; var11(var12, var13, var14, var15)
     157 [-]: CLOSEUPVALS R1; 
     158 [-]: RETURN R0 0  ; 


; Name:            
; Defined at line: 518
; #Upvalues:       11
; #Parameters:     0
; Is_vararg:       0
; Max Stack Size:  6

       0 [-]: GETIMPORT R0 1; var0 = 0x3D106989
       1 [-]: LOADK R1 K2  ; var1 = "InitializeSettings()"
       2 [-]: CALL R0 2 1  ; var0(var1)
       3 [-]: GETIMPORT R0 4; var0 = 0x2D0FAD09
       4 [-]: LOADK R1 K5  ; var1 = "EE.Interface.Components.List"
       5 [-]: CALL R0 2 2  ; var0 = var0(var1)
       6 [-]: GETTABLEKS R1 R0 K6; var1 = var0[0x9383BC56]
       7 [-]: GETIMPORT R2 8; var2 = 0xAE91E43B
       8 [-]: LOADK R3 K9  ; var3 = "Container.MenuEntry1"
       9 [-]: CALL R1 3 2  ; var1 = var1(var2, var3)
      10 [-]: SETUPVAL R1 0; upvalues[1] = var0
      11 [-]: GETUPVAL R1 0; var1 = upvalues[0]
      12 [-]: LOADK R3 K10 ; var3 = "MenuEntryPressed"
      13 [-]: LOADK R4 K11 ; var4 = "MenuEntryFocused"
      14 [-]: LOADK R5 K12 ; var5 = "MenuEntryUnfocused"
      15 [-]: NAMECALL R1 R1 K13; var2 = var1; var1 = var1[0x1E5B5CFE]
      16 [-]: CALL R1 5 1  ; var1(var2, var3, var4, var5)
      17 [-]: GETUPVAL R1 0; var1 = upvalues[0]
      18 [-]: LOADNIL R2   ; var2 = nil
      19 [-]: SETTABLEKS R2 R1 K14; var2["mForcedVerticalSeparation"] = var1
      20 [-]: GETUPVAL R1 0; var1 = upvalues[0]
      21 [-]: LOADN R2 10  ; var2 = 10
      22 [-]: SETTABLEKS R2 R1 K15; var2["mVisibleElements"] = var1
      23 [-]: GETUPVAL R1 0; var1 = upvalues[0]
      24 [-]: LOADN R2 0   ; var2 = 0
      25 [-]: SETTABLEKS R2 R1 K16; var2["mElementTransitionTime"] = var1
      26 [-]: GETUPVAL R1 0; var1 = upvalues[0]
      27 [-]: LOADN R2 0   ; var2 = 0
      28 [-]: SETTABLEKS R2 R1 K17; var2["totalY"] = var1
      29 [-]: GETIMPORT R1 8; var1 = 0xAE91E43B
      30 [-]: LOADK R3 K18 ; var3 = "Container.ScrollBar"
      31 [-]: LOADN R4 11  ; var4 = 11
      32 [-]: LOADB R5 0   ; var5 = false
      33 [-]: NAMECALL R1 R1 K19; var2 = var1; var1 = var1[0xAADE900E]
      34 [-]: CALL R1 5 1  ; var1(var2, var3, var4, var5)
      35 [-]: GETUPVAL R1 0; var1 = upvalues[0]
      36 [-]: DUPCLOSURE R2 K20; 
      37 [-]: SETTABLEKS R2 R1 K21; var2["Print"] = var1
      38 [-]: GETUPVAL R1 0; var1 = upvalues[0]
      39 [-]: NEWCLOSURE R2 P1; 
      40 [-]: CAPTURE UPVAL U1; 
      41 [-]: CAPTURE UPVAL U2; 
      42 [-]: CAPTURE UPVAL U3; 
      43 [-]: CAPTURE UPVAL U4; 
      44 [-]: SETTABLEKS R2 R1 K22; var2["mOnFocusedCallback"] = var1
      45 [-]: GETUPVAL R1 0; var1 = upvalues[0]
      46 [-]: DUPCLOSURE R2 K23; 
      47 [-]: CAPTURE UPVAL U2; 
      48 [-]: CAPTURE UPVAL U4; 
      49 [-]: SETTABLEKS R2 R1 K24; var2["mOnUnfocusedCallback"] = var1
      50 [-]: GETUPVAL R1 0; var1 = upvalues[0]
      51 [-]: NEWCLOSURE R2 P3; 
      52 [-]: CAPTURE UPVAL U2; 
      53 [-]: CAPTURE UPVAL U5; 
      54 [-]: CAPTURE UPVAL U0; 
      55 [-]: SETTABLEKS R2 R1 K25; var2["mOnSelectedCallback"] = var1
      56 [-]: GETUPVAL R1 0; var1 = upvalues[0]
      57 [-]: NEWCLOSURE R2 P4; 
      58 [-]: CAPTURE UPVAL U2; 
      59 [-]: CAPTURE UPVAL U3; 
      60 [-]: CAPTURE UPVAL U6; 
      61 [-]: CAPTURE UPVAL U5; 
      62 [-]: CAPTURE UPVAL U7; 
      63 [-]: CAPTURE UPVAL U0; 
      64 [-]: CAPTURE UPVAL U8; 
      65 [-]: CAPTURE UPVAL U1; 
      66 [-]: CAPTURE UPVAL U4; 
      67 [-]: CAPTURE UPVAL U9; 
      68 [-]: SETTABLEKS R2 R1 K26; var2["mElementDrawCallback"] = var1
      69 [-]: GETUPVAL R1 0; var1 = upvalues[0]
      70 [-]: DUPCLOSURE R2 K27; 
      71 [-]: CAPTURE UPVAL U2; 
      72 [-]: CAPTURE UPVAL U3; 
      73 [-]: CAPTURE UPVAL U10; 
      74 [-]: SETTABLEKS R2 R1 K28; var2["CalculateHeight"] = var1
      75 [-]: GETUPVAL R1 0; var1 = upvalues[0]
      76 [-]: DUPCLOSURE R2 K29; 
      77 [-]: SETTABLEKS R2 R1 K30; var2["CalculateWidth"] = var1
      78 [-]: GETUPVAL R1 0; var1 = upvalues[0]
      79 [-]: GETUPVAL R3 0; var3 = upvalues[0]
      80 [-]: GETTABLEKS R2 R3 K31; var2 = var3["CalculateX"]
      81 [-]: SETTABLEKS R2 R1 K32; var2["_GenericSettings_CalculateX"] = var1
      82 [-]: GETUPVAL R1 0; var1 = upvalues[0]
      83 [-]: NEWCLOSURE R2 P7; 
      84 [-]: CAPTURE UPVAL U0; 
      85 [-]: SETTABLEKS R2 R1 K31; var2["CalculateX"] = var1
      86 [-]: GETUPVAL R1 0; var1 = upvalues[0]
      87 [-]: NEWCLOSURE R2 P8; 
      88 [-]: CAPTURE UPVAL U0; 
      89 [-]: SETTABLEKS R2 R1 K33; var2["CalculateY"] = var1
      90 [-]: RETURN R0 0  ; 


; Name:            
; Defined at line: 1013
; #Upvalues:       5
; #Parameters:     0
; Is_vararg:       0
; Max Stack Size:  9

       0 [-]: GETUPVAL R0 0; var0 = upvalues[0]
       1 [-]: GETUPVAL R2 1; var2 = upvalues[1]
       2 [-]: NAMECALL R0 R0 K0; var1 = var0; var0 = var0[0x1D246732]
       3 [-]: CALL R0 3 2  ; var0 = var0(var1, var2)
       4 [-]: FASTCALL1 62 R0 L0; 
       5 [-]: MOVE R2 R0   ; var2 = var0
       6 [-]: GETIMPORT R1 2; var1 = 0x7B998233
       7 [-]: CALL R1 2 2  ; var1 = var1(var2)
L 0:   8 [-]: JUMPIF R1 L7 ; goto L7 if var1
       9 [-]: GETUPVAL R1 0; var1 = upvalues[0]
      10 [-]: MOVE R3 R0   ; var3 = var0
      11 [-]: NAMECALL R1 R1 K3; var2 = var1; var1 = var1[0x5465F8F3]
      12 [-]: CALL R1 3 2  ; var1 = var1(var2, var3)
      13 [-]: GETIMPORT R2 5; var2 = 0xAE91E43B
      14 [-]: GETTABLEKS R5 R1 K6; var5 = var1["mClipName"]
      15 [-]: LOADK R6 K7  ; var6 = ".Count"
      16 [-]: CONCAT R4 R5 R6; var4 = var5 .. var6
      17 [-]: LOADN R5 29  ; var5 = 29
      18 [-]: NAMECALL R2 R2 K8; var3 = var2; var2 = var2[0x54A95D6F]
      19 [-]: CALL R2 4 2  ; var2 = var2(var3, var4, var5)
      20 [-]: GETUPVAL R3 2; var3 = upvalues[2]
      21 [-]: JUMPIFEQ R3 R2 L7; goto L7 if var3 == var131594
      22 [-]: SETUPVAL R2 2; upvalues[2] = var2
      23 [-]: GETIMPORT R3 11; var3 = 0x7F5022CF[0x66EDF04F]
      24 [-]: GETUPVAL R4 2; var4 = upvalues[2]
      25 [-]: GETIMPORT R5 5; var5 = 0xAE91E43B
      26 [-]: LOADK R7 K12 ; var7 = "<CREDITS>"
      27 [-]: LOADB R8 1   ; var8 = true
      28 [-]: NAMECALL R5 R5 K13; var6 = var5; var5 = var5[0x42B04007]
      29 [-]: CALL R5 4 2  ; var5 = var5(var6, var7, var8)
      30 [-]: LOADK R6 K14 ; var6 = ""
      31 [-]: CALL R3 4 2  ; var3 = var3(var4, var5, var6)
      32 [-]: GETUPVAL R5 3; var5 = upvalues[3]
      33 [-]: GETTABLEKS R4 R5 K15; var4 = var5[0x06D055F9]
      34 [-]: FASTCALL1 43 R3 L1; 
      35 [-]: MOVE R7 R3   ; var7 = var3
      36 [-]: GETIMPORT R6 17; var6 = 0x7F5022CF[0x41E2AE25]
      37 [-]: CALL R6 2 2  ; var6 = var6(var7)
L 1:  38 [-]: JUMPXEQKN R6 K18 L2; 
      39 [-]: LOADB R5 0 +1; var5 = false
L 2:  40 [-]: LOADB R5 1   ; var5 = true
L 3:  41 [-]: LOADN R6 0   ; var6 = 0
      42 [-]: GETIMPORT R7 20; var7 = 0x03F57322
      43 [-]: MOVE R8 R3   ; var8 = var3
      44 [-]: CALL R7 2 0  ; var7, ... = var7(var8)
      45 [-]: CALL R4 0 2  ; var4 = var4(var5, ...)
      46 [-]: JUMPXEQKNIL R4 L4 NOT; 
      47 [-]: LOADN R4 0   ; var4 = 0
L 4:  48 [-]: GETTABLEKS R5 R1 K21; var5 = var1["mMaxCount"]
      49 [-]: JUMPXEQKNIL R5 L5; 
      50 [-]: GETTABLEKS R5 R1 K21; var5 = var1["mMaxCount"]
      51 [-]: JUMPIFNOTLT R5 R4 L5; goto L5 if var5 >= var1258357788
      52 [-]: GETTABLEKS R4 R1 K21; var4 = var1["mMaxCount"]
L 5:  53 [-]: GETTABLEKS R5 R1 K22; var5 = var1["mMinCount"]
      54 [-]: JUMPXEQKNIL R5 L6; 
      55 [-]: GETTABLEKS R5 R1 K22; var5 = var1["mMinCount"]
      56 [-]: JUMPIFNOTLT R4 R5 L6; goto L6 if var4 >= var-1862204388
      57 [-]: GETTABLEKS R4 R1 K22; var4 = var1["mMinCount"]
L 6:  58 [-]: GETUPVAL R5 4; var5 = upvalues[4]
      59 [-]: CALL R5 1 1  ; var5()
      60 [-]: SETTABLEKS R4 R1 K23; var4["mCount"] = var1
      61 [-]: GETTABLEKS R5 R1 K24; var5 = var1["mCallback"]
      62 [-]: JUMPXEQKNIL R5 L7; 
      63 [-]: GETTABLEKS R5 R1 K24; var5 = var1["mCallback"]
      64 [-]: GETTABLEKS R6 R1 K23; var6 = var1["mCount"]
      65 [-]: CALL R5 2 1  ; var5(var6)
L 7:  66 [-]: RETURN R0 0  ; 


; Name:            
; Defined at line: 1044
; #Upvalues:       6
; #Parameters:     0
; Is_vararg:       0
; Max Stack Size:  23

       0 [-]: GETUPVAL R1 0; var1 = upvalues[0]
       1 [-]: GETTABLEKS R0 R1 K0; var0 = var1["InputField"]
       2 [-]: JUMPXEQKNIL R0 L0 NOT; 
       3 [-]: RETURN R0 0  ; 
L 0:   4 [-]: GETIMPORT R0 2; var0 = 0xAE91E43B
       5 [-]: GETUPVAL R4 0; var4 = upvalues[0]
       6 [-]: GETTABLEKS R3 R4 K0; var3 = var4["InputField"]
       7 [-]: GETTABLEKS R2 R3 K3; var2 = var3["mLabelClipName"]
       8 [-]: LOADN R3 29  ; var3 = 29
       9 [-]: NAMECALL R0 R0 K4; var1 = var0; var0 = var0[0x54A95D6F]
      10 [-]: CALL R0 4 2  ; var0 = var0(var1, var2, var3)
      11 [-]: GETIMPORT R2 2; var2 = 0xAE91E43B
      12 [-]: GETUPVAL R6 0; var6 = upvalues[0]
      13 [-]: GETTABLEKS R5 R6 K0; var5 = var6["InputField"]
      14 [-]: GETTABLEKS R4 R5 K3; var4 = var5["mLabelClipName"]
      15 [-]: LOADN R5 71  ; var5 = 71
      16 [-]: NAMECALL R2 R2 K6; var3 = var2; var2 = var2[0x91A24E4B]
      17 [-]: CALL R2 4 2  ; var2 = var2(var3, var4, var5)
      18 [-]: ORK R1 R2 K5 ; var1 = var2 or 0
      19 [-]: MOVE R3 R0   ; var3 = var0
      20 [-]: LOADN R4 1   ; var4 = 1
      21 [-]: MOVE R5 R1   ; var5 = var1
      22 [-]: FASTCALL 45 L1; 
      23 [-]: GETIMPORT R2 9; var2 = 0x7F5022CF[0x1A94C9CC]
      24 [-]: CALL R2 4 2  ; var2 = var2(var3, var4, var5)
L 1:  25 [-]: GETIMPORT R3 11; var3 = 0x7F5022CF[0xA5C556B9]
      26 [-]: GETIMPORT R4 13; var4 = 0x7F5022CF[0x62F9FB80]
      27 [-]: MOVE R5 R2   ; var5 = var2
      28 [-]: CALL R4 2 2  ; var4 = var4(var5)
      29 [-]: LOADK R5 K14 ; var5 = ","
      30 [-]: CALL R3 3 2  ; var3 = var3(var4, var5)
      31 [-]: JUMPXEQKNIL R3 L3; 
      32 [-]: FASTCALL1 43 R2 L2; 
      33 [-]: MOVE R6 R2   ; var6 = var2
      34 [-]: GETIMPORT R5 17; var5 = 0x7F5022CF[0x41E2AE25]
      35 [-]: CALL R5 2 2  ; var5 = var5(var6)
L 2:  36 [-]: SUB R4 R5 R3 ; var4 = var5 - var3
      37 [-]: ADDK R3 R4 K15; var3 = var4 + 1
L 3:  38 [-]: JUMPXEQKNIL R3 L4; 
      39 [-]: JUMPIFNOTLT R1 R3 L5; goto L5 if var1 >= var839
L 4:  40 [-]: LOADN R3 0   ; var3 = 0
L 5:  41 [-]: GETIMPORT R4 11; var4 = 0x7F5022CF[0xA5C556B9]
      42 [-]: MOVE R5 R0   ; var5 = var0
      43 [-]: LOADK R6 K14 ; var6 = ","
      44 [-]: ADDK R7 R1 K15; var7 = var1 + 1
      45 [-]: CALL R4 4 2  ; var4 = var4(var5, var6, var7)
      46 [-]: MOVE R6 R0   ; var6 = var0
      47 [-]: MOVE R7 R3   ; var7 = var3
      48 [-]: MOVE R8 R4   ; var8 = var4
      49 [-]: FASTCALL 45 L6; 
      50 [-]: GETIMPORT R5 9; var5 = 0x7F5022CF[0x1A94C9CC]
      51 [-]: CALL R5 4 2  ; var5 = var5(var6, var7, var8)
L 6:  52 [-]: MOVE R0 R5   ; var0 = var5
      53 [-]: GETIMPORT R5 19; var5 = 0x7F5022CF[0x66EDF04F]
      54 [-]: MOVE R6 R0   ; var6 = var0
      55 [-]: LOADK R7 K20 ; var7 = "[, ]"
      56 [-]: LOADK R8 K21 ; var8 = ""
      57 [-]: CALL R5 4 2  ; var5 = var5(var6, var7, var8)
      58 [-]: MOVE R0 R5   ; var0 = var5
      59 [-]: GETIMPORT R5 23; var5 = 0x7F5022CF[0x04981AB3]
      60 [-]: MOVE R6 R0   ; var6 = var0
      61 [-]: CALL R5 2 2  ; var5 = var5(var6)
      62 [-]: MOVE R0 R5   ; var0 = var5
      63 [-]: LOADB R5 0   ; var5 = false
      64 [-]: GETUPVAL R6 1; var6 = upvalues[1]
      65 [-]: JUMPIFNOTEQ R0 R6 L7; goto L7 if var0 ~= var65581
      66 [-]: RETURN R0 0  ; 
L 7:  67 [-]: SETUPVAL R0 1; upvalues[0] = var1
      68 [-]: LOADK R6 K21 ; var6 = ""
      69 [-]: LOADN R7 0   ; var7 = 0
      70 [-]: JUMPXEQKS R0 K21 L15; 
      71 [-]: LOADK R8 K21 ; var8 = ""
      72 [-]: FASTCALL1 43 R0 L8; 
      73 [-]: MOVE R10 R0  ; var10 = var0
      74 [-]: GETIMPORT R9 17; var9 = 0x7F5022CF[0x41E2AE25]
      75 [-]: CALL R9 2 2  ; var9 = var9(var10)
L 8:  76 [-]: MOVE R11 R0  ; var11 = var0
      77 [-]: LOADN R12 1  ; var12 = 1
      78 [-]: LOADN R13 1  ; var13 = 1
      79 [-]: FASTCALL 45 L9; 
      80 [-]: GETIMPORT R10 9; var10 = 0x7F5022CF[0x1A94C9CC]
      81 [-]: CALL R10 4 2 ; var10 = var10(var11, var12, var13)
L 9:  82 [-]: GETUPVAL R13 2; var13 = upvalues[2]
      83 [-]: GETTABLEKS R12 R13 K24; var12 = var13["Indexer"]
      84 [-]: GETTABLE R11 R12 R10; var11 = var12[var10]
      85 [-]: JUMPXEQKNIL R11 L15; 
      86 [-]: GETUPVAL R14 2; var14 = upvalues[2]
      87 [-]: GETTABLEKS R13 R14 K25; var13 = var14["Tags"]
      88 [-]: LENGTH R12 R13; var12 = #var13
      89 [-]: MOVE R15 R11 ; var15 = var11
      90 [-]: MOVE R13 R12 ; var13 = var12
      91 [-]: LOADN R14 1  ; var14 = 1
      92 [-]: FORNPREP R13 L15; nforprep start - [escape at L15] -- var13 = iterator
L10:  93 [-]: GETUPVAL R18 2; var18 = upvalues[2]
      94 [-]: GETTABLEKS R17 R18 K25; var17 = var18["Tags"]
      95 [-]: GETTABLE R16 R17 R15; var16 = var17[var15]
      96 [-]: MOVE R18 R16 ; var18 = var16
      97 [-]: LOADN R19 1  ; var19 = 1
      98 [-]: MOVE R20 R9  ; var20 = var9
      99 [-]: FASTCALL 45 L11; 
     100 [-]: GETIMPORT R17 9; var17 = 0x7F5022CF[0x1A94C9CC]
     101 [-]: CALL R17 4 2 ; var17 = var17(var18, var19, var20)
L11: 102 [-]: JUMPIFNOTEQ R17 R0 L12; goto L12 if var17 ~= var136199
     103 [-]: GETUPVAL R20 2; var20 = upvalues[2]
     104 [-]: GETTABLEKS R19 R20 K26; var19 = var20["Real"]
     105 [-]: GETTABLE R18 R19 R15; var18 = var19[var15]
     106 [-]: JUMPIFEQ R8 R18 L12; goto L12 if var8 == var66843
     107 [-]: LOADB R5 1   ; var5 = true
     108 [-]: MOVE R18 R6  ; var18 = var6
     109 [-]: GETUPVAL R22 2; var22 = upvalues[2]
     110 [-]: GETTABLEKS R21 R22 K26; var21 = var22["Real"]
     111 [-]: GETTABLE R19 R21 R15; var19 = var21[var15]
     112 [-]: LOADK R20 K27; var20 = "|"
     113 [-]: CONCAT R6 R18 R20; var6 = var18 .. var20
     114 [-]: ADDK R7 R7 K15; var7 = var7 + 1
     115 [-]: GETUPVAL R19 2; var19 = upvalues[2]
     116 [-]: GETTABLEKS R18 R19 K26; var18 = var19["Real"]
     117 [-]: GETTABLE R8 R18 R15; var8 = var18[var15]
     118 [-]: LOADN R18 8  ; var18 = 8
     119 [-]: JUMPIFLE R18 R7 L15; goto L15 if var18 <= var589888
     120 [-]: JUMP L14     ; goto L14
L12: 121 [-]: MOVE R19 R16 ; var19 = var16
     122 [-]: LOADN R20 1  ; var20 = 1
     123 [-]: LOADN R21 1  ; var21 = 1
     124 [-]: FASTCALL 45 L13; 
     125 [-]: GETIMPORT R18 9; var18 = 0x7F5022CF[0x1A94C9CC]
     126 [-]: CALL R18 4 2 ; var18 = var18(var19, var20, var21)
L13: 127 [-]: JUMPIFNOTEQ R10 R18 L15; goto L15 if var10 ~= var-3011320
L14: 128 [-]: FORNLOOP R13 L10; nforloop end - iterate + goto L10
L15: 129 [-]: JUMPIFNOT R5 L17; goto L17 if not var5
     130 [-]: MOVE R8 R6   ; var8 = var6
     131 [-]: GETUPVAL R9 1; var9 = upvalues[1]
     132 [-]: CONCAT R6 R8 R9; var6 = var8 .. var9
     133 [-]: GETUPVAL R8 0; var8 = upvalues[0]
     134 [-]: SETUPVAL R8 3; upvalues[8] = var3
     135 [-]: GETUPVAL R9 4; var9 = upvalues[4]
     136 [-]: GETTABLEKS R8 R9 K28; var8 = var9[0x638926F7]
     137 [-]: GETUPVAL R9 5; var9 = upvalues[5]
     138 [-]: CALL R8 2 1  ; var8(var9)
     139 [-]: GETUPVAL R9 4; var9 = upvalues[4]
     140 [-]: GETTABLEKS R8 R9 K29; var8 = var9[0xFC6541B2]
     141 [-]: GETUPVAL R9 1; var9 = upvalues[1]
     142 [-]: GETUPVAL R10 5; var10 = upvalues[5]
     143 [-]: CALL R8 3 1  ; var8(var9, var10)
     144 [-]: GETUPVAL R9 4; var9 = upvalues[4]
     145 [-]: GETTABLEKS R8 R9 K30; var8 = var9[0xADD16FB0]
     146 [-]: GETUPVAL R10 1; var10 = upvalues[1]
     147 [-]: FASTCALL1 43 R10 L16; 
     148 [-]: GETIMPORT R9 17; var9 = 0x7F5022CF[0x41E2AE25]
     149 [-]: CALL R9 2 2  ; var9 = var9(var10)
L16: 150 [-]: GETUPVAL R10 5; var10 = upvalues[5]
     151 [-]: CALL R8 3 1  ; var8(var9, var10)
     152 [-]: GETUPVAL R9 4; var9 = upvalues[4]
     153 [-]: GETTABLEKS R8 R9 K31; var8 = var9[0x088839FD]
     154 [-]: MOVE R9 R6   ; var9 = var6
     155 [-]: GETUPVAL R10 5; var10 = upvalues[5]
     156 [-]: LOADB R11 0  ; var11 = false
     157 [-]: CALL R8 4 1  ; var8(var9, var10, var11)
     158 [-]: GETIMPORT R8 2; var8 = 0xAE91E43B
     159 [-]: GETUPVAL R12 0; var12 = upvalues[0]
     160 [-]: GETTABLEKS R11 R12 K0; var11 = var12["InputField"]
     161 [-]: GETTABLEKS R10 R11 K3; var10 = var11["mLabelClipName"]
     162 [-]: LOADN R11 73 ; var11 = 73
     163 [-]: LOADB R12 1  ; var12 = true
     164 [-]: NAMECALL R8 R8 K32; var9 = var8; var8 = var8[0xAADE900E]
     165 [-]: CALL R8 5 1  ; var8(var9, var10, var11, var12)
     166 [-]: RETURN R0 0  ; 
L17: 167 [-]: GETUPVAL R9 4; var9 = upvalues[4]
     168 [-]: GETTABLEKS R8 R9 K31; var8 = var9[0x088839FD]
     169 [-]: LOADK R9 K21 ; var9 = ""
     170 [-]: GETUPVAL R10 5; var10 = upvalues[5]
     171 [-]: LOADB R11 0  ; var11 = false
     172 [-]: CALL R8 4 1  ; var8(var9, var10, var11)
     173 [-]: GETUPVAL R9 4; var9 = upvalues[4]
     174 [-]: GETTABLEKS R8 R9 K33; var8 = var9[0xC074491B]
     175 [-]: GETUPVAL R9 5; var9 = upvalues[5]
     176 [-]: CALL R8 2 1  ; var8(var9)
     177 [-]: GETIMPORT R8 2; var8 = 0xAE91E43B
     178 [-]: GETUPVAL R12 0; var12 = upvalues[0]
     179 [-]: GETTABLEKS R11 R12 K0; var11 = var12["InputField"]
     180 [-]: GETTABLEKS R10 R11 K3; var10 = var11["mLabelClipName"]
     181 [-]: LOADN R11 73 ; var11 = 73
     182 [-]: LOADB R12 0  ; var12 = false
     183 [-]: NAMECALL R8 R8 K32; var9 = var8; var8 = var8[0xAADE900E]
     184 [-]: CALL R8 5 1  ; var8(var9, var10, var11, var12)
     185 [-]: LOADNIL R8   ; var8 = nil
     186 [-]: SETUPVAL R8 3; upvalues[8] = var3
     187 [-]: RETURN R0 0  ; 


; Name:            
; Defined at line: 1114
; #Upvalues:       5
; #Parameters:     0
; Is_vararg:       0
; Max Stack Size:  16

       0 [-]: GETUPVAL R1 0; var1 = upvalues[0]
       1 [-]: GETTABLEKS R0 R1 K0; var0 = var1[0x2FFD43FF]
       2 [-]: GETUPVAL R1 1; var1 = upvalues[1]
       3 [-]: CALL R0 2 2  ; var0 = var0(var1)
       4 [-]: SETUPVAL R0 2; upvalues[0] = var2
       5 [-]: GETIMPORT R2 3; var2 = 0xAE91E43B
       6 [-]: GETUPVAL R6 3; var6 = upvalues[3]
       7 [-]: GETTABLEKS R5 R6 K4; var5 = var6["InputField"]
       8 [-]: GETTABLEKS R4 R5 K5; var4 = var5["mLabelClipName"]
       9 [-]: LOADN R5 71  ; var5 = 71
      10 [-]: NAMECALL R2 R2 K6; var3 = var2; var2 = var2[0x91A24E4B]
      11 [-]: CALL R2 4 2  ; var2 = var2(var3, var4, var5)
      12 [-]: ORK R1 R2 K1 ; var1 = var2 or 0
      13 [-]: GETIMPORT R2 3; var2 = 0xAE91E43B
      14 [-]: GETUPVAL R6 3; var6 = upvalues[3]
      15 [-]: GETTABLEKS R5 R6 K4; var5 = var6["InputField"]
      16 [-]: GETTABLEKS R4 R5 K5; var4 = var5["mLabelClipName"]
      17 [-]: LOADN R5 29  ; var5 = 29
      18 [-]: NAMECALL R2 R2 K7; var3 = var2; var2 = var2[0x54A95D6F]
      19 [-]: CALL R2 4 2  ; var2 = var2(var3, var4, var5)
      20 [-]: MOVE R4 R2   ; var4 = var2
      21 [-]: LOADN R5 1   ; var5 = 1
      22 [-]: MOVE R6 R1   ; var6 = var1
      23 [-]: FASTCALL 45 L0; 
      24 [-]: GETIMPORT R3 10; var3 = 0x7F5022CF[0x1A94C9CC]
      25 [-]: CALL R3 4 2  ; var3 = var3(var4, var5, var6)
L 0:  26 [-]: GETIMPORT R4 12; var4 = 0x7F5022CF[0xA5C556B9]
      27 [-]: GETIMPORT R5 14; var5 = 0x7F5022CF[0x62F9FB80]
      28 [-]: MOVE R6 R3   ; var6 = var3
      29 [-]: CALL R5 2 2  ; var5 = var5(var6)
      30 [-]: LOADK R6 K15 ; var6 = ","
      31 [-]: CALL R4 3 2  ; var4 = var4(var5, var6)
      32 [-]: LOADK R5 K16 ; var5 = ""
      33 [-]: JUMPXEQKNIL R4 L3; 
      34 [-]: FASTCALL1 43 R3 L1; 
      35 [-]: MOVE R8 R3   ; var8 = var3
      36 [-]: GETIMPORT R7 19; var7 = 0x7F5022CF[0x41E2AE25]
      37 [-]: CALL R7 2 2  ; var7 = var7(var8)
L 1:  38 [-]: SUB R6 R7 R4 ; var6 = var7 - var4
      39 [-]: ADDK R4 R6 K17; var4 = var6 + 1
      40 [-]: JUMPIFNOTLT R4 R1 L3; goto L3 if var4 >= var133398
      41 [-]: MOVE R9 R2   ; var9 = var2
      42 [-]: LOADN R10 1  ; var10 = 1
      43 [-]: MOVE R11 R4  ; var11 = var4
      44 [-]: FASTCALL 45 L2; 
      45 [-]: GETIMPORT R8 10; var8 = 0x7F5022CF[0x1A94C9CC]
      46 [-]: CALL R8 4 2  ; var8 = var8(var9, var10, var11)
L 2:  47 [-]: MOVE R6 R8   ; var6 = var8
      48 [-]: LOADK R7 K20 ; var7 = " "
      49 [-]: CONCAT R5 R6 R7; var5 = var6 .. var7
L 3:  50 [-]: GETIMPORT R6 12; var6 = 0x7F5022CF[0xA5C556B9]
      51 [-]: MOVE R7 R2   ; var7 = var2
      52 [-]: LOADK R8 K15 ; var8 = ","
      53 [-]: MOVE R9 R1   ; var9 = var1
      54 [-]: CALL R6 4 2  ; var6 = var6(var7, var8, var9)
      55 [-]: LOADK R7 K21 ; var7 = ", "
      56 [-]: MOVE R10 R5  ; var10 = var5
      57 [-]: MOVE R11 R0  ; var11 = var0
      58 [-]: MOVE R12 R7  ; var12 = var7
      59 [-]: CONCAT R9 R10 R12; var9 = var10 .. var12
      60 [-]: FASTCALL1 43 R9 L4; 
      61 [-]: GETIMPORT R8 19; var8 = 0x7F5022CF[0x41E2AE25]
      62 [-]: CALL R8 2 2  ; var8 = var8(var9)
L 4:  63 [-]: MOVE R1 R8   ; var1 = var8
      64 [-]: JUMPXEQKNIL R6 L7; 
      65 [-]: FASTCALL2 45 R2 R6 L5; 
      66 [-]: MOVE R9 R2   ; var9 = var2
      67 [-]: MOVE R10 R6  ; var10 = var6
      68 [-]: GETIMPORT R8 10; var8 = 0x7F5022CF[0x1A94C9CC]
      69 [-]: CALL R8 3 2  ; var8 = var8(var9, var10)
L 5:  70 [-]: MOVE R7 R8   ; var7 = var8
      71 [-]: MOVE R10 R5  ; var10 = var5
      72 [-]: MOVE R11 R0  ; var11 = var0
      73 [-]: CONCAT R9 R10 R11; var9 = var10 .. var11
      74 [-]: FASTCALL1 43 R9 L6; 
      75 [-]: GETIMPORT R8 19; var8 = 0x7F5022CF[0x41E2AE25]
      76 [-]: CALL R8 2 2  ; var8 = var8(var9)
L 6:  77 [-]: MOVE R1 R8   ; var1 = var8
L 7:  78 [-]: GETIMPORT R8 3; var8 = 0xAE91E43B
      79 [-]: GETUPVAL R12 3; var12 = upvalues[3]
      80 [-]: GETTABLEKS R11 R12 K4; var11 = var12["InputField"]
      81 [-]: GETTABLEKS R10 R11 K5; var10 = var11["mLabelClipName"]
      82 [-]: LOADN R11 29 ; var11 = 29
      83 [-]: MOVE R13 R5  ; var13 = var5
      84 [-]: MOVE R14 R0  ; var14 = var0
      85 [-]: MOVE R15 R7  ; var15 = var7
      86 [-]: CONCAT R12 R13 R15; var12 = var13 .. var15
      87 [-]: NAMECALL R8 R8 K22; var9 = var8; var8 = var8[0x5F56EEAB]
      88 [-]: CALL R8 5 1  ; var8(var9, var10, var11, var12)
      89 [-]: GETIMPORT R8 3; var8 = 0xAE91E43B
      90 [-]: GETUPVAL R12 3; var12 = upvalues[3]
      91 [-]: GETTABLEKS R11 R12 K4; var11 = var12["InputField"]
      92 [-]: GETTABLEKS R10 R11 K5; var10 = var11["mLabelClipName"]
      93 [-]: LOADN R11 71 ; var11 = 71
      94 [-]: MOVE R12 R1  ; var12 = var1
      95 [-]: NAMECALL R8 R8 K23; var9 = var8; var8 = var8[0x67BC869F]
      96 [-]: CALL R8 5 1  ; var8(var9, var10, var11, var12)
      97 [-]: GETUPVAL R9 0; var9 = upvalues[0]
      98 [-]: GETTABLEKS R8 R9 K24; var8 = var9[0xC074491B]
      99 [-]: GETUPVAL R9 1; var9 = upvalues[1]
     100 [-]: CALL R8 2 1  ; var8(var9)
     101 [-]: GETUPVAL R9 0; var9 = upvalues[0]
     102 [-]: GETTABLEKS R8 R9 K25; var8 = var9[0x2E84930F]
     103 [-]: LOADN R9 1   ; var9 = 1
     104 [-]: GETUPVAL R10 1; var10 = upvalues[1]
     105 [-]: CALL R8 3 1  ; var8(var9, var10)
     106 [-]: GETIMPORT R8 3; var8 = 0xAE91E43B
     107 [-]: GETUPVAL R12 3; var12 = upvalues[3]
     108 [-]: GETTABLEKS R11 R12 K4; var11 = var12["InputField"]
     109 [-]: GETTABLEKS R10 R11 K5; var10 = var11["mLabelClipName"]
     110 [-]: LOADN R11 73 ; var11 = 73
     111 [-]: LOADB R12 0  ; var12 = false
     112 [-]: NAMECALL R8 R8 K26; var9 = var8; var8 = var8[0xAADE900E]
     113 [-]: CALL R8 5 1  ; var8(var9, var10, var11, var12)
     114 [-]: LOADNIL R8   ; var8 = nil
     115 [-]: SETUPVAL R8 3; upvalues[8] = var3
     116 [-]: GETUPVAL R8 4; var8 = upvalues[4]
     117 [-]: CALL R8 1 1  ; var8()
     118 [-]: RETURN R0 0  ; 


; Name:            
; Defined at line: 1146
; #Upvalues:       16
; #Parameters:     0
; Is_vararg:       0
; Max Stack Size:  7

       0 [-]: GETUPVAL R0 0; var0 = upvalues[0]
       1 [-]: JUMPIFNOT R0 L1; goto L1 if not var0
       2 [-]: GETIMPORT R1 1; var1 = 0xAE91E43B
       3 [-]: FASTCALL1 62 R1 L0; 
       4 [-]: GETIMPORT R0 3; var0 = 0x7B998233
       5 [-]: CALL R0 2 2  ; var0 = var0(var1)
L 0:   6 [-]: JUMPIFNOT R0 L2; goto L2 if not var0
L 1:   7 [-]: RETURN R0 0  ; 
L 2:   8 [-]: GETIMPORT R0 1; var0 = 0xAE91E43B
       9 [-]: GETIMPORT R2 5; var2 = 0xB693B6C1
      10 [-]: CALL R2 1 0  ; var2, ... = var2()
      11 [-]: NAMECALL R0 R0 K6; var1 = var0; var0 = var0[0x8A8C8D5A]
      12 [-]: CALL R0 0 1  ; var0(var1, ...)
      13 [-]: GETUPVAL R1 1; var1 = upvalues[1]
      14 [-]: FASTCALL1 62 R1 L3; 
      15 [-]: GETIMPORT R0 3; var0 = 0x7B998233
      16 [-]: CALL R0 2 2  ; var0 = var0(var1)
L 3:  17 [-]: JUMPIF R0 L4 ; goto L4 if var0
      18 [-]: GETUPVAL R0 1; var0 = upvalues[1]
      19 [-]: GETIMPORT R2 5; var2 = 0xB693B6C1
      20 [-]: CALL R2 1 0  ; var2, ... = var2()
      21 [-]: NAMECALL R0 R0 K7; var1 = var0; var0 = var0[0xFAA69527]
      22 [-]: CALL R0 0 1  ; var0(var1, ...)
L 4:  23 [-]: GETUPVAL R2 2; var2 = upvalues[2]
      24 [-]: GETTABLEKS R1 R2 K8; var1 = var2["mScrollBar"]
      25 [-]: FASTCALL1 62 R1 L5; 
      26 [-]: GETIMPORT R0 3; var0 = 0x7B998233
      27 [-]: CALL R0 2 2  ; var0 = var0(var1)
L 5:  28 [-]: JUMPIF R0 L6 ; goto L6 if var0
      29 [-]: GETUPVAL R1 2; var1 = upvalues[2]
      30 [-]: GETTABLEKS R0 R1 K8; var0 = var1["mScrollBar"]
      31 [-]: GETIMPORT R2 5; var2 = 0xB693B6C1
      32 [-]: CALL R2 1 0  ; var2, ... = var2()
      33 [-]: NAMECALL R0 R0 K7; var1 = var0; var0 = var0[0xFAA69527]
      34 [-]: CALL R0 0 1  ; var0(var1, ...)
L 6:  35 [-]: GETUPVAL R1 3; var1 = upvalues[3]
      36 [-]: FASTCALL1 62 R1 L7; 
      37 [-]: GETIMPORT R0 3; var0 = 0x7B998233
      38 [-]: CALL R0 2 2  ; var0 = var0(var1)
L 7:  39 [-]: JUMPIF R0 L11; goto L11 if var0
      40 [-]: GETUPVAL R1 4; var1 = upvalues[4]
      41 [-]: GETIMPORT R2 5; var2 = 0xB693B6C1
      42 [-]: CALL R2 1 2  ; var2 = var2()
      43 [-]: SUB R0 R1 R2 ; var0 = var1 - var2
      44 [-]: SETUPVAL R0 4; upvalues[0] = var4
      45 [-]: GETUPVAL R0 4; var0 = upvalues[4]
      46 [-]: LOADN R1 0   ; var1 = 0
      47 [-]: JUMPIFNOTLE R0 R1 L11; goto L11 if var0 > var327687
      48 [-]: GETUPVAL R0 5; var0 = upvalues[5]
      49 [-]: GETUPVAL R2 6; var2 = upvalues[6]
      50 [-]: GETUPVAL R4 7; var4 = upvalues[7]
      51 [-]: GETTABLEKS R3 R4 K10; var3 = var4["mMaxCount"]
      52 [-]: CALL R2 2 2  ; var2 = var2(var3)
      53 [-]: SUBK R1 R2 K9; var1 = var2 - 1
      54 [-]: JUMPIFNOTLT R0 R1 L8; goto L8 if var0 >= var327943
      55 [-]: GETUPVAL R1 5; var1 = upvalues[5]
      56 [-]: ADDK R0 R1 K11; var0 = var1 + 0.20000000000000001
      57 [-]: SETUPVAL R0 5; upvalues[0] = var5
L 8:  58 [-]: LOADK R0 K12 ; var0 = 0.25
      59 [-]: SETUPVAL R0 4; upvalues[0] = var4
      60 [-]: GETUPVAL R0 8; var0 = upvalues[8]
      61 [-]: GETUPVAL R2 3; var2 = upvalues[3]
      62 [-]: LOADN R4 10  ; var4 = 10
      63 [-]: GETUPVAL R6 5; var6 = upvalues[5]
      64 [-]: FASTCALL1 12 R6 L9; 
      65 [-]: GETIMPORT R5 15; var5 = 0x5BCED4C4[0x55F27C30]
      66 [-]: CALL R5 2 2  ; var5 = var5(var6)
L 9:  67 [-]: FASTCALL2 21 R4 R5 L10; 
      68 [-]: GETIMPORT R3 17; var3 = 0x5BCED4C4[0xA40531D8]
      69 [-]: CALL R3 3 2  ; var3 = var3(var4, var5)
L10:  70 [-]: MUL R1 R2 R3 ; var1 = var2 * var3
      71 [-]: CALL R0 2 1  ; var0(var1)
L11:  72 [-]: GETUPVAL R0 2; var0 = upvalues[2]
      73 [-]: DUPCLOSURE R2 K18; 
      74 [-]: NAMECALL R0 R0 K19; var1 = var0; var0 = var0[0xEA061E98]
      75 [-]: CALL R0 3 1  ; var0(var1, var2)
      76 [-]: GETUPVAL R0 9; var0 = upvalues[9]
      77 [-]: JUMPIFNOT R0 L12; goto L12 if not var0
      78 [-]: GETUPVAL R0 10; var0 = upvalues[10]
      79 [-]: CALL R0 1 1  ; var0()
L12:  80 [-]: GETIMPORT R0 21; var0 = 0x9BA7909F
      81 [-]: NAMECALL R0 R0 K22; var1 = var0; var0 = var0[0x8FE6BE1D]
      82 [-]: CALL R0 2 2  ; var0 = var0(var1)
      83 [-]: JUMPIF R0 L16; goto L16 if var0
      84 [-]: GETUPVAL R1 11; var1 = upvalues[11]
      85 [-]: FASTCALL1 62 R1 L13; 
      86 [-]: GETIMPORT R0 3; var0 = 0x7B998233
      87 [-]: CALL R0 2 2  ; var0 = var0(var1)
L13:  88 [-]: JUMPIF R0 L16; goto L16 if var0
      89 [-]: GETUPVAL R0 7; var0 = upvalues[7]
      90 [-]: JUMPXEQKNIL R0 L15; 
      91 [-]: GETUPVAL R1 7; var1 = upvalues[7]
      92 [-]: GETTABLEKS R0 R1 K23; var0 = var1["mType"]
      93 [-]: GETUPVAL R2 12; var2 = upvalues[12]
      94 [-]: GETTABLEKS R1 R2 K24; var1 = var2["INPUTBOX"]
      95 [-]: JUMPIFNOTEQ R0 R1 L15; goto L15 if var0 ~= var852231
      96 [-]: GETUPVAL R1 13; var1 = upvalues[13]
      97 [-]: GETTABLEKS R0 R1 K25; var0 = var1[0x742BABAC]
      98 [-]: CALL R0 1 2  ; var0 = var0()
      99 [-]: JUMPIFNOT R0 L14; goto L14 if not var0
     100 [-]: GETUPVAL R0 14; var0 = upvalues[14]
     101 [-]: CALL R0 1 1  ; var0()
L14: 102 [-]: GETUPVAL R0 15; var0 = upvalues[15]
     103 [-]: CALL R0 1 1  ; var0()
L15: 104 [-]: GETUPVAL R1 13; var1 = upvalues[13]
     105 [-]: GETTABLEKS R0 R1 K7; var0 = var1[0xFAA69527]
     106 [-]: GETUPVAL R1 11; var1 = upvalues[11]
     107 [-]: CALL R0 2 1  ; var0(var1)
L16: 108 [-]: RETURN R0 0  ; 


; Name:            
; Defined at line: 1195
; #Upvalues:       9
; #Parameters:     0
; Is_vararg:       0
; Max Stack Size:  9

       0 [-]: GETUPVAL R0 0; var0 = upvalues[0]
       1 [-]: JUMPXEQKNIL R0 L1 NOT; 
       2 [-]: GETUPVAL R1 1; var1 = upvalues[1]
       3 [-]: ADDK R0 R1 K0; var0 = var1 + 1
       4 [-]: SETUPVAL R0 1; upvalues[0] = var1
       5 [-]: GETUPVAL R0 1; var0 = upvalues[1]
       6 [-]: LOADN R1 10  ; var1 = 10
       7 [-]: JUMPIFNOTLT R0 R1 L0; goto L0 if var0 >= var131079
       8 [-]: GETUPVAL R0 2; var0 = upvalues[2]
       9 [-]: LOADK R2 K1  ; var2 = 0.10000000000000001
      10 [-]: GETUPVAL R3 3; var3 = upvalues[3]
      11 [-]: NAMECALL R0 R0 K2; var1 = var0; var0 = var0[0xBD2E96EA]
      12 [-]: CALL R0 4 1  ; var0(var1, var2, var3)
      13 [-]: RETURN R0 0  ; 
L 0:  14 [-]: GETUPVAL R0 4; var0 = upvalues[4]
      15 [-]: CALL R0 1 1  ; var0()
      16 [-]: RETURN R0 0  ; 
L 1:  17 [-]: GETIMPORT R2 4; var2 = _T
      18 [-]: GETUPVAL R3 0; var3 = upvalues[0]
      19 [-]: GETTABLE R1 R2 R3; var1 = var2[var3]
      20 [-]: FASTCALL1 62 R1 L2; 
      21 [-]: GETIMPORT R0 6; var0 = 0x7B998233
      22 [-]: CALL R0 2 2  ; var0 = var0(var1)
L 2:  23 [-]: JUMPIF R0 L5 ; goto L5 if var0
      24 [-]: GETIMPORT R1 4; var1 = _T
      25 [-]: GETUPVAL R2 0; var2 = upvalues[0]
      26 [-]: GETTABLE R0 R1 R2; var0 = var1[var2]
      27 [-]: CALL R0 1 2  ; var0 = var0()
      28 [-]: LOADN R3 1   ; var3 = 1
      29 [-]: LENGTH R1 R0 ; var1 = #var0
      30 [-]: LOADN R2 1   ; var2 = 1
      31 [-]: FORNPREP R1 L5; nforprep start - [escape at L5] -- var1 = iterator
L 3:  32 [-]: GETIMPORT R4 8; var4 = 0xCE225EFA
      33 [-]: LOADN R5 0   ; var5 = 0
      34 [-]: CALL R4 2 1  ; var4(var5)
      35 [-]: GETTABLE R4 R0 R3; var4 = var0[var3]
      36 [-]: SETTABLEKS R3 R4 K9; var3["Id"] = var4
      37 [-]: GETTABLE R4 R0 R3; var4 = var0[var3]
      38 [-]: GETTABLE R6 R0 R3; var6 = var0[var3]
      39 [-]: GETTABLEKS R5 R6 K10; var5 = var6["mValue"]
      40 [-]: SETTABLEKS R5 R4 K11; var5["mOriginalValue"] = var4
      41 [-]: GETTABLE R5 R0 R3; var5 = var0[var3]
      42 [-]: GETTABLEKS R4 R5 K11; var4 = var5["mOriginalValue"]
      43 [-]: JUMPXEQKNIL R4 L4 NOT; 
      44 [-]: GETTABLE R4 R0 R3; var4 = var0[var3]
      45 [-]: GETTABLE R6 R0 R3; var6 = var0[var3]
      46 [-]: GETTABLEKS R5 R6 K12; var5 = var6["mContent"]
      47 [-]: SETTABLEKS R5 R4 K11; var5["mOriginalValue"] = var4
L 4:  48 [-]: GETUPVAL R4 5; var4 = upvalues[5]
      49 [-]: GETTABLE R6 R0 R3; var6 = var0[var3]
      50 [-]: LOADB R7 1   ; var7 = true
      51 [-]: NAMECALL R4 R4 K13; var5 = var4; var4 = var4[0xBAD4316F]
      52 [-]: CALL R4 4 1  ; var4(var5, var6, var7)
      53 [-]: FORNLOOP R1 L3; nforloop end - iterate + goto L3
L 5:  54 [-]: GETUPVAL R0 5; var0 = upvalues[5]
      55 [-]: NAMECALL R0 R0 K14; var1 = var0; var0 = var0[0x71E9AC81]
      56 [-]: CALL R0 2 1  ; var0(var1)
      57 [-]: GETUPVAL R0 6; var0 = upvalues[6]
      58 [-]: CALL R0 1 1  ; var0()
      59 [-]: GETIMPORT R0 16; var0 = 0xAE91E43B
      60 [-]: LOADK R2 K17 ; var2 = "Container.Message"
      61 [-]: LOADN R3 11  ; var3 = 11
      62 [-]: GETUPVAL R5 5; var5 = upvalues[5]
      63 [-]: NAMECALL R5 R5 K18; var6 = var5; var5 = var5[0x5FBDDC1A]
      64 [-]: CALL R5 2 2  ; var5 = var5(var6)
      65 [-]: JUMPXEQKN R5 K19 L6; 
      66 [-]: LOADB R4 0 +1; var4 = false
L 6:  67 [-]: LOADB R4 1   ; var4 = true
L 7:  68 [-]: NAMECALL R0 R0 K20; var1 = var0; var0 = var0[0xAADE900E]
      69 [-]: CALL R0 5 1  ; var0(var1, var2, var3, var4)
      70 [-]: GETIMPORT R0 22; var0 = 0x25312C9B
      71 [-]: GETIMPORT R1 16; var1 = 0xAE91E43B
      72 [-]: LOADK R2 K23 ; var2 = "_root"
      73 [-]: LOADN R3 2   ; var3 = 2
      74 [-]: NEWTABLE R4 0 2; var4 = {}
      75 [-]: LOADN R5 10  ; var5 = 10
      76 [-]: LOADN R6 4   ; var6 = 4
      77 [-]: SETLIST R4 R5 2 [1]; var4[1] = var5; var4[2] = var6; var4[3] = var7; 
      78 [-]: NEWTABLE R5 0 2; var5 = {}
      79 [-]: LOADN R6 100 ; var6 = 100
      80 [-]: LOADN R7 0   ; var7 = 0
      81 [-]: SETLIST R5 R6 2 [1]; var5[1] = var6; var5[2] = var7; var5[3] = var8; 
      82 [-]: LOADK R6 K24 ; var6 = 0.20000000000000001
      83 [-]: LOADN R7 0   ; var7 = 0
      84 [-]: NEWCLOSURE R8 P0; 
      85 [-]: CAPTURE UPVAL U7; 
      86 [-]: CALL R0 9 1  ; var0(var1, var2, var3, var4, var5, var6, var7, var8)
      87 [-]: GETUPVAL R0 8; var0 = upvalues[8]
      88 [-]: CALL R0 1 1  ; var0()
      89 [-]: RETURN R0 0  ; 


; Name:            
; Defined at line: 1233
; #Upvalues:       0
; #Parameters:     0
; Is_vararg:       0
; Max Stack Size:  6

       0 [-]: GETIMPORT R0 1; var0 = 0xAE91E43B
       1 [-]: LOADK R2 K2  ; var2 = "MouseCatcherBtn"
       2 [-]: LOADN R3 12  ; var3 = 12
       3 [-]: GETIMPORT R4 1; var4 = 0xAE91E43B
       4 [-]: NAMECALL R4 R4 K3; var5 = var4; var4 = var4[0x6B837788]
       5 [-]: CALL R4 2 0  ; var4, ... = var4(var5)
       6 [-]: NAMECALL R0 R0 K4; var1 = var0; var0 = var0[0x67BC869F]
       7 [-]: CALL R0 0 1  ; var0(var1, ...)
       8 [-]: GETIMPORT R0 1; var0 = 0xAE91E43B
       9 [-]: LOADK R2 K2  ; var2 = "MouseCatcherBtn"
      10 [-]: LOADN R3 13  ; var3 = 13
      11 [-]: GETIMPORT R4 1; var4 = 0xAE91E43B
      12 [-]: NAMECALL R4 R4 K5; var5 = var4; var4 = var4[0xAF9FDA9F]
      13 [-]: CALL R4 2 0  ; var4, ... = var4(var5)
      14 [-]: NAMECALL R0 R0 K4; var1 = var0; var0 = var0[0x67BC869F]
      15 [-]: CALL R0 0 1  ; var0(var1, ...)
      16 [-]: RETURN R0 0  ; 


; Name:            
; Defined at line: 1238
; #Upvalues:       8
; #Parameters:     0
; Is_vararg:       0
; Max Stack Size:  12

       0 [-]: GETIMPORT R0 1; var0 = 0x2D0FAD09
       1 [-]: LOADK R1 K2  ; var1 = "Lotus.Interface.Libs.TimerMgr"
       2 [-]: CALL R0 2 2  ; var0 = var0(var1)
       3 [-]: GETTABLEKS R1 R0 K3; var1 = var0[0xDE474187]
       4 [-]: CALL R1 1 2  ; var1 = var1()
       5 [-]: SETUPVAL R1 0; upvalues[1] = var0
       6 [-]: GETUPVAL R2 1; var2 = upvalues[1]
       7 [-]: GETTABLEKS R1 R2 K4; var1 = var2[0x659D451F]
       8 [-]: GETIMPORT R3 6; var3 = 0x0032441C
       9 [-]: GETTABLEKS R2 R3 K7; var2 = var3["UISound_WindowOpen"]
      10 [-]: CALL R1 2 1  ; var1(var2)
      11 [-]: GETIMPORT R1 9; var1 = 0xAE91E43B
      12 [-]: GETIMPORT R4 12; var4 = _T["RadialSolarMapOpen"]
      13 [-]: JUMPXEQKB R4 1 L0; 
      14 [-]: LOADB R3 0 +1; var3 = false
L 0:  15 [-]: LOADB R3 1   ; var3 = true
L 1:  16 [-]: NAMECALL R1 R1 K13; var2 = var1; var1 = var1[0x2002E1DC]
      17 [-]: CALL R1 3 1  ; var1(var2, var3)
      18 [-]: GETIMPORT R1 9; var1 = 0xAE91E43B
      19 [-]: LOADK R3 K14 ; var3 = "MouseCatcherBtn"
      20 [-]: LOADK R4 K15 ; var4 = "noMenuSelection"
      21 [-]: LOADB R5 1   ; var5 = true
      22 [-]: NAMECALL R1 R1 K16; var2 = var1; var1 = var1[0x0C33EBB2]
      23 [-]: CALL R1 5 1  ; var1(var2, var3, var4, var5)
      24 [-]: GETUPVAL R1 2; var1 = upvalues[2]
      25 [-]: CALL R1 1 1  ; var1()
      26 [-]: NEWTABLE R1 0 4; var1 = {}
      27 [-]: LOADK R2 K17 ; var2 = "FancyBits.LeftLines"
      28 [-]: LOADK R3 K18 ; var3 = "FancyBits.LeftSideLine.FadeLineTop"
      29 [-]: LOADK R4 K19 ; var4 = "FancyBits.LeftSideLine.FadeLineMiddle"
      30 [-]: LOADK R5 K20 ; var5 = "FancyBits.LeftSideLine.FadeLineBottom"
      31 [-]: SETLIST R1 R2 4 [1]; var1[1] = var2; var1[2] = var3; var1[3] = var4; var1[4] = var5; var1[5] = var6; 
      32 [-]: LOADN R4 1   ; var4 = 1
      33 [-]: LENGTH R2 R1 ; var2 = #var1
      34 [-]: LOADN R3 1   ; var3 = 1
      35 [-]: FORNPREP R2 L3; nforprep start - [escape at L3] -- var2 = iterator
L 2:  36 [-]: GETIMPORT R5 9; var5 = 0xAE91E43B
      37 [-]: GETTABLE R7 R1 R4; var7 = var1[var4]
      38 [-]: GETIMPORT R8 22; var8 = 0x996808CC
      39 [-]: NAMECALL R5 R5 K23; var6 = var5; var5 = var5[0xD5181643]
      40 [-]: CALL R5 4 1  ; var5(var6, var7, var8)
      41 [-]: FORNLOOP R2 L2; nforloop end - iterate + goto L2
L 3:  42 [-]: NEWTABLE R2 0 4; var2 = {}
      43 [-]: LOADK R3 K24 ; var3 = "FancyBits.RightLines"
      44 [-]: LOADK R4 K25 ; var4 = "FancyBits.RightSideLine.FadeLineTop"
      45 [-]: LOADK R5 K26 ; var5 = "FancyBits.RightSideLine.FadeLineMiddle"
      46 [-]: LOADK R6 K27 ; var6 = "FancyBits.RightSideLine.FadeLineBottom"
      47 [-]: SETLIST R2 R3 4 [1]; var2[1] = var3; var2[2] = var4; var2[3] = var5; var2[4] = var6; var2[5] = var7; 
      48 [-]: MOVE R1 R2   ; var1 = var2
      49 [-]: LOADN R4 1   ; var4 = 1
      50 [-]: LENGTH R2 R1 ; var2 = #var1
      51 [-]: LOADN R3 1   ; var3 = 1
      52 [-]: FORNPREP R2 L5; nforprep start - [escape at L5] -- var2 = iterator
L 4:  53 [-]: GETIMPORT R5 9; var5 = 0xAE91E43B
      54 [-]: GETTABLE R7 R1 R4; var7 = var1[var4]
      55 [-]: GETIMPORT R8 29; var8 = 0xC9E06D1B
      56 [-]: NAMECALL R5 R5 K23; var6 = var5; var5 = var5[0xD5181643]
      57 [-]: CALL R5 4 1  ; var5(var6, var7, var8)
      58 [-]: FORNLOOP R2 L4; nforloop end - iterate + goto L4
L 5:  59 [-]: GETUPVAL R2 3; var2 = upvalues[3]
      60 [-]: CALL R2 1 1  ; var2()
      61 [-]: GETUPVAL R2 4; var2 = upvalues[4]
      62 [-]: CALL R2 1 1  ; var2()
      63 [-]: GETIMPORT R2 9; var2 = 0xAE91E43B
      64 [-]: LOADK R4 K14 ; var4 = "MouseCatcherBtn"
      65 [-]: LOADNIL R5   ; var5 = nil
      66 [-]: LOADNIL R6   ; var6 = nil
      67 [-]: LOADNIL R7   ; var7 = nil
      68 [-]: LOADK R8 K30 ; var8 = "MouseCatcherPressed"
      69 [-]: NAMECALL R2 R2 K31; var3 = var2; var2 = var2[0x1E5B5CFE]
      70 [-]: CALL R2 7 1  ; var2(var3, var4, var5, var6, var7, var8)
      71 [-]: GETIMPORT R2 9; var2 = 0xAE91E43B
      72 [-]: LOADB R4 1   ; var4 = true
      73 [-]: NAMECALL R2 R2 K32; var3 = var2; var2 = var2[0x767C0947]
      74 [-]: CALL R2 3 1  ; var2(var3, var4)
      75 [-]: GETIMPORT R2 9; var2 = 0xAE91E43B
      76 [-]: LOADK R4 K33 ; var4 = "_root"
      77 [-]: LOADN R5 10  ; var5 = 10
      78 [-]: LOADN R6 0   ; var6 = 0
      79 [-]: NAMECALL R2 R2 K34; var3 = var2; var2 = var2[0x67BC869F]
      80 [-]: CALL R2 5 1  ; var2(var3, var4, var5, var6)
      81 [-]: GETIMPORT R2 9; var2 = 0xAE91E43B
      82 [-]: LOADK R4 K33 ; var4 = "_root"
      83 [-]: LOADN R5 4   ; var5 = 4
      84 [-]: LOADN R6 -15000; var6 = -15000
      85 [-]: NAMECALL R2 R2 K34; var3 = var2; var2 = var2[0x67BC869F]
      86 [-]: CALL R2 5 1  ; var2(var3, var4, var5, var6)
      87 [-]: DUPCLOSURE R2 K35; 
      88 [-]: MOVE R3 R2   ; var3 = var2
      89 [-]: LOADN R4 0   ; var4 = 0
      90 [-]: CALL R3 2 1  ; var3(var4)
      91 [-]: GETIMPORT R3 37; var3 = 0x25312C9B
      92 [-]: GETIMPORT R4 9; var4 = 0xAE91E43B
      93 [-]: LOADK R5 K33 ; var5 = "_root"
      94 [-]: LOADN R6 0   ; var6 = 0
      95 [-]: NEWTABLE R7 0 1; var7 = {}
      96 [-]: MOVE R8 R2   ; var8 = var2
      97 [-]: SETLIST R7 R8 1 [1]; var7[1] = var8; var7[2] = var9; 
      98 [-]: NEWTABLE R8 0 1; var8 = {}
      99 [-]: LOADN R9 1   ; var9 = 1
     100 [-]: SETLIST R8 R9 1 [1]; var8[1] = var9; var8[2] = var10; 
     101 [-]: LOADK R9 K38 ; var9 = 0.14999999999999999
     102 [-]: LOADN R10 0  ; var10 = 0
     103 [-]: DUPCLOSURE R11 K39; 
     104 [-]: CAPTURE UPVAL U5; 
     105 [-]: CALL R3 9 1  ; var3(var4, var5, var6, var7, var8, var9, var10, var11)
     106 [-]: GETUPVAL R3 6; var3 = upvalues[6]
     107 [-]: CALL R3 1 1  ; var3()
     108 [-]: LOADB R3 1   ; var3 = true
     109 [-]: SETUPVAL R3 7; upvalues[3] = var7
     110 [-]: RETURN R0 0  ; 


; Name:            
; Defined at line: 1281
; #Upvalues:       1
; #Parameters:     1
; Is_vararg:       0
; Max Stack Size:  6

       0 [-]: GETIMPORT R1 1; var1 = 0xAE91E43B
       1 [-]: LOADK R3 K2  ; var3 = "Container.Title.text"
       2 [-]: MOVE R4 R0   ; var4 = var0
       3 [-]: NAMECALL R1 R1 K3; var2 = var1; var1 = var1[0x20B98DB3]
       4 [-]: CALL R1 4 1  ; var1(var2, var3, var4)
       5 [-]: GETUPVAL R2 0; var2 = upvalues[0]
       6 [-]: FASTCALL1 62 R2 L0; 
       7 [-]: GETIMPORT R1 5; var1 = 0x7B998233
       8 [-]: CALL R1 2 2  ; var1 = var1(var2)
L 0:   9 [-]: JUMPIF R1 L1 ; goto L1 if var1
      10 [-]: GETIMPORT R1 1; var1 = 0xAE91E43B
      11 [-]: LOADK R3 K6  ; var3 = "Container.Title"
      12 [-]: LOADN R4 34  ; var4 = 34
      13 [-]: NAMECALL R1 R1 K7; var2 = var1; var1 = var1[0x91A24E4B]
      14 [-]: CALL R1 4 2  ; var1 = var1(var2, var3, var4)
      15 [-]: GETIMPORT R2 1; var2 = 0xAE91E43B
      16 [-]: LOADK R4 K6  ; var4 = "Container.Title"
      17 [-]: LOADN R5 1   ; var5 = 1
      18 [-]: NAMECALL R2 R2 K7; var3 = var2; var2 = var2[0x91A24E4B]
      19 [-]: CALL R2 4 2  ; var2 = var2(var3, var4, var5)
      20 [-]: GETUPVAL R3 0; var3 = upvalues[0]
      21 [-]: ADD R5 R2 R1 ; var5 = var2 + var1
      22 [-]: ADDK R4 R5 K8; var4 = var5 + 55
      23 [-]: SETTABLEKS R4 R3 K9; var4["mInitialY"] = var3
L 1:  24 [-]: RETURN R0 0  ; 


; Name:            
; Defined at line: 1291
; #Upvalues:       2
; #Parameters:     1
; Is_vararg:       0
; Max Stack Size:  2

       0 [-]: SETUPVAL R0 0; upvalues[0] = var0
       1 [-]: GETUPVAL R1 1; var1 = upvalues[1]
       2 [-]: CALL R1 1 1  ; var1()
       3 [-]: RETURN R0 0  ; 


; Name:            
; Defined at line: 1296
; #Upvalues:       1
; #Parameters:     1
; Is_vararg:       0
; Max Stack Size:  2

       0 [-]: JUMPXEQKS R0 K0 L0; 
       1 [-]: LOADB R1 0 +1; var1 = false
L 0:   2 [-]: LOADB R1 1   ; var1 = true
L 1:   3 [-]: SETUPVAL R1 0; upvalues[1] = var0
       4 [-]: RETURN R0 0  ; 


; Name:            
; Defined at line: 1300
; #Upvalues:       3
; #Parameters:     1
; Is_vararg:       0
; Max Stack Size:  2

       0 [-]: JUMPXEQKS R0 K0 L0; 
       1 [-]: LOADB R1 0 +1; var1 = false
L 0:   2 [-]: LOADB R1 1   ; var1 = true
L 1:   3 [-]: SETUPVAL R1 0; upvalues[1] = var0
       4 [-]: GETUPVAL R1 1; var1 = upvalues[1]
       5 [-]: JUMPIF R1 L2 ; goto L2 if var1
       6 [-]: GETUPVAL R1 0; var1 = upvalues[0]
L 2:   7 [-]: SETUPVAL R1 1; upvalues[1] = var1
       8 [-]: GETUPVAL R1 2; var1 = upvalues[2]
       9 [-]: CALL R1 1 1  ; var1()
      10 [-]: RETURN R0 0  ; 


; Name:            
; Defined at line: 1306
; #Upvalues:       2
; #Parameters:     1
; Is_vararg:       0
; Max Stack Size:  2

       0 [-]: JUMPXEQKS R0 K0 L0; 
       1 [-]: LOADB R1 0 +1; var1 = false
L 0:   2 [-]: LOADB R1 1   ; var1 = true
L 1:   3 [-]: SETUPVAL R1 0; upvalues[1] = var0
       4 [-]: GETUPVAL R1 1; var1 = upvalues[1]
       5 [-]: CALL R1 1 1  ; var1()
       6 [-]: RETURN R0 0  ; 


; Name:            
; Defined at line: 1311
; #Upvalues:       2
; #Parameters:     1
; Is_vararg:       0
; Max Stack Size:  2

       0 [-]: JUMPXEQKS R0 K0 L0; 
       1 [-]: LOADB R1 0 +1; var1 = false
L 0:   2 [-]: LOADB R1 1   ; var1 = true
L 1:   3 [-]: SETUPVAL R1 0; upvalues[1] = var0
       4 [-]: GETUPVAL R1 1; var1 = upvalues[1]
       5 [-]: CALL R1 1 1  ; var1()
       6 [-]: RETURN R0 0  ; 


; Name:            
; Defined at line: 1316
; #Upvalues:       0
; #Parameters:     1
; Is_vararg:       0
; Max Stack Size:  6

       0 [-]: GETIMPORT R1 1; var1 = 0xAE91E43B
       1 [-]: LOADK R3 K2  ; var3 = "Container.Message"
       2 [-]: LOADN R4 38  ; var4 = 38
       3 [-]: LOADK R5 K3  ; var5 = "center"
       4 [-]: NAMECALL R1 R1 K4; var2 = var1; var1 = var1[0x5F56EEAB]
       5 [-]: CALL R1 5 1  ; var1(var2, var3, var4, var5)
       6 [-]: GETIMPORT R1 1; var1 = 0xAE91E43B
       7 [-]: LOADK R3 K5  ; var3 = "Container.Message.text"
       8 [-]: MOVE R4 R0   ; var4 = var0
       9 [-]: NAMECALL R1 R1 K6; var2 = var1; var1 = var1[0x20B98DB3]
      10 [-]: CALL R1 4 1  ; var1(var2, var3, var4)
      11 [-]: RETURN R0 0  ; 


; Name:            
; Defined at line: 1321
; #Upvalues:       1
; #Parameters:     1
; Is_vararg:       0
; Max Stack Size:  1

       0 [-]: SETUPVAL R0 0; upvalues[0] = var0
       1 [-]: RETURN R0 0  ; 


; Name:            
; Defined at line: 1325
; #Upvalues:       1
; #Parameters:     1
; Is_vararg:       0
; Max Stack Size:  1

       0 [-]: SETUPVAL R0 0; upvalues[0] = var0
       1 [-]: RETURN R0 0  ; 


; Name:            
; Defined at line: 1329
; #Upvalues:       1
; #Parameters:     1
; Is_vararg:       0
; Max Stack Size:  5

       0 [-]: GETUPVAL R1 0; var1 = upvalues[0]
       1 [-]: JUMPIFNOT R1 L2; goto L2 if not var1
       2 [-]: GETUPVAL R1 0; var1 = upvalues[0]
       3 [-]: GETIMPORT R3 1; var3 = 0x03F57322
       4 [-]: MOVE R4 R0   ; var4 = var0
       5 [-]: CALL R3 2 2  ; var3 = var3(var4)
       6 [-]: LOADN R4 4   ; var4 = 4
       7 [-]: JUMPIFEQ R3 R4 L0; goto L0 if var3 == var16777755
       8 [-]: LOADB R2 0 +1; var2 = false
L 0:   9 [-]: LOADB R2 1   ; var2 = true
L 1:  10 [-]: CALL R1 2 1  ; var1(var2)
L 2:  11 [-]: RETURN R0 0  ; 


; Name:            
; Defined at line: 1335
; #Upvalues:       2
; #Parameters:     0
; Is_vararg:       0
; Max Stack Size:  3

       0 [-]: GETUPVAL R1 0; var1 = upvalues[0]
       1 [-]: GETTABLEKS R0 R1 K0; var0 = var1[0xF616A184]
       2 [-]: GETUPVAL R2 1; var2 = upvalues[1]
       3 [-]: GETTABLEKS R1 R2 K1; var1 = var2["ConfirmLabel"]
       4 [-]: LOADK R2 K2  ; var2 = "OnCustomButtonConfirmation"
       5 [-]: CALL R0 3 1  ; var0(var1, var2)
       6 [-]: RETURN R0 0  ; 


; Name:            
; Defined at line: 1339
; #Upvalues:       1
; #Parameters:     1
; Is_vararg:       0
; Max Stack Size:  1

       0 [-]: SETUPVAL R0 0; upvalues[0] = var0
       1 [-]: RETURN R0 0  ; 


; Name:            
; Defined at line: 1343
; #Upvalues:       1
; #Parameters:     1
; Is_vararg:       0
; Max Stack Size:  1

       0 [-]: SETUPVAL R0 0; upvalues[0] = var0
       1 [-]: RETURN R0 0  ; 


; Name:            
; Defined at line: 1347
; #Upvalues:       3
; #Parameters:     0
; Is_vararg:       0
; Max Stack Size:  10

       0 [-]: GETIMPORT R0 2; var0 = 0x34291F5C[0x056BFE8B]
       1 [-]: CALL R0 1 2  ; var0 = var0()
       2 [-]: JUMPIF R0 L10; goto L10 if var0
       3 [-]: GETIMPORT R0 4; var0 = 0x9BA7909F
       4 [-]: GETIMPORT R2 6; var2 = 0x16A51607
       5 [-]: NAMECALL R0 R0 K7; var1 = var0; var0 = var0[0xBCFB64AB]
       6 [-]: CALL R0 3 2  ; var0 = var0(var1, var2)
       7 [-]: SETUPVAL R0 0; upvalues[0] = var0
       8 [-]: GETUPVAL R1 0; var1 = upvalues[0]
       9 [-]: FASTCALL1 62 R1 L0; 
      10 [-]: GETIMPORT R0 9; var0 = 0x7B998233
      11 [-]: CALL R0 2 2  ; var0 = var0(var1)
L 0:  12 [-]: JUMPIFNOT R0 L2; goto L2 if not var0
      13 [-]: GETIMPORT R1 6; var1 = 0x16A51607
      14 [-]: FASTCALL1 62 R1 L1; 
      15 [-]: GETIMPORT R0 9; var0 = 0x7B998233
      16 [-]: CALL R0 2 2  ; var0 = var0(var1)
L 1:  17 [-]: JUMPIF R0 L2 ; goto L2 if var0
      18 [-]: GETIMPORT R0 11; var0 = 0xAE91E43B
      19 [-]: GETIMPORT R2 6; var2 = 0x16A51607
      20 [-]: NAMECALL R0 R0 K12; var1 = var0; var0 = var0[0x1FD6ABD0]
      21 [-]: CALL R0 3 2  ; var0 = var0(var1, var2)
      22 [-]: SETUPVAL R0 0; upvalues[0] = var0
      23 [-]: LOADB R0 1   ; var0 = true
      24 [-]: SETUPVAL R0 1; upvalues[0] = var1
L 2:  25 [-]: GETUPVAL R1 0; var1 = upvalues[0]
      26 [-]: FASTCALL1 62 R1 L3; 
      27 [-]: GETIMPORT R0 9; var0 = 0x7B998233
      28 [-]: CALL R0 2 2  ; var0 = var0(var1)
L 3:  29 [-]: JUMPIF R0 L10; goto L10 if var0
      30 [-]: GETUPVAL R0 2; var0 = upvalues[2]
      31 [-]: NEWTABLE R1 0 0; var1 = {}
      32 [-]: SETTABLEKS R1 R0 K13; var1["Real"] = var0
      33 [-]: GETUPVAL R0 2; var0 = upvalues[2]
      34 [-]: NEWTABLE R1 0 0; var1 = {}
      35 [-]: SETTABLEKS R1 R0 K14; var1["Tags"] = var0
      36 [-]: GETUPVAL R0 2; var0 = upvalues[2]
      37 [-]: NEWTABLE R1 0 0; var1 = {}
      38 [-]: SETTABLEKS R1 R0 K15; var1["Indexer"] = var0
      39 [-]: GETIMPORT R0 17; var0 = 0xC8802016
      40 [-]: GETIMPORT R1 19; var1 = 0x25D99D89
      41 [-]: NAMECALL R1 R1 K20; var2 = var1; var1 = var1[0x2E37A704]
      42 [-]: CALL R1 2 0  ; var1, ... = var1(var2)
      43 [-]: CALL R0 0 4  ; var0, var1, var2 = var0(var1, ...)
      44 [-]: FORGPREP_INEXT R0 L5; 
L 4:  45 [-]: GETUPVAL R7 2; var7 = upvalues[2]
      46 [-]: GETTABLEKS R6 R7 K13; var6 = var7["Real"]
      47 [-]: GETTABLEKS R7 R4 K21; var7 = var4["mDisplayName"]
      48 [-]: FASTCALL2 52 R6 R7 L5; 
      49 [-]: GETIMPORT R5 24; var5 = 0x33BDD652[0x23D5322F]
      50 [-]: CALL R5 3 1  ; var5(var6, var7)
L 5:  51 [-]: FORGLOOP R0 L4 2 [inext]; 
      52 [-]: GETIMPORT R0 26; var0 = 0x33BDD652[0xF21B1D8E]
      53 [-]: GETUPVAL R2 2; var2 = upvalues[2]
      54 [-]: GETTABLEKS R1 R2 K13; var1 = var2["Real"]
      55 [-]: DUPCLOSURE R2 K27; 
      56 [-]: CALL R0 3 1  ; var0(var1, var2)
      57 [-]: LOADNIL R0   ; var0 = nil
      58 [-]: LOADN R3 1   ; var3 = 1
      59 [-]: GETUPVAL R5 2; var5 = upvalues[2]
      60 [-]: GETTABLEKS R4 R5 K13; var4 = var5["Real"]
      61 [-]: LENGTH R1 R4 ; var1 = #var4
      62 [-]: LOADN R2 1   ; var2 = 1
      63 [-]: FORNPREP R1 L10; nforprep start - [escape at L10] -- var1 = iterator
L 6:  64 [-]: GETUPVAL R6 2; var6 = upvalues[2]
      65 [-]: GETTABLEKS R5 R6 K14; var5 = var6["Tags"]
      66 [-]: GETIMPORT R6 30; var6 = 0x7F5022CF[0x04981AB3]
      67 [-]: GETUPVAL R9 2; var9 = upvalues[2]
      68 [-]: GETTABLEKS R8 R9 K13; var8 = var9["Real"]
      69 [-]: GETTABLE R7 R8 R3; var7 = var8[var3]
      70 [-]: CALL R6 2 0  ; var6, ... = var6(var7)
      71 [-]: FASTCALL 52 L7; 
      72 [-]: GETIMPORT R4 24; var4 = 0x33BDD652[0x23D5322F]
      73 [-]: CALL R4 0 1  ; var4(var5, ...)
L 7:  74 [-]: GETUPVAL R7 2; var7 = upvalues[2]
      75 [-]: GETTABLEKS R6 R7 K14; var6 = var7["Tags"]
      76 [-]: GETTABLE R5 R6 R3; var5 = var6[var3]
      77 [-]: LOADN R6 1   ; var6 = 1
      78 [-]: LOADN R7 1   ; var7 = 1
      79 [-]: FASTCALL 45 L8; 
      80 [-]: GETIMPORT R4 32; var4 = 0x7F5022CF[0x1A94C9CC]
      81 [-]: CALL R4 4 2  ; var4 = var4(var5, var6, var7)
L 8:  82 [-]: JUMPIFEQ R4 R0 L9; goto L9 if var4 == var262166
      83 [-]: MOVE R0 R4   ; var0 = var4
      84 [-]: GETUPVAL R6 2; var6 = upvalues[2]
      85 [-]: GETTABLEKS R5 R6 K15; var5 = var6["Indexer"]
      86 [-]: SETTABLE R3 R5 R4; var3[var5] = var4
L 9:  87 [-]: FORNLOOP R1 L6; nforloop end - iterate + goto L6
L10:  88 [-]: RETURN R0 0  ; 


; Name:            
; Defined at line: 1378
; #Upvalues:       5
; #Parameters:     3
; Is_vararg:       0
; Max Stack Size:  12

       0 [-]: JUMPXEQKS R2 K0 L5 NOT; 
       1 [-]: GETUPVAL R3 0; var3 = upvalues[0]
       2 [-]: JUMPIF R3 L5 ; goto L5 if var3
       3 [-]: GETUPVAL R4 1; var4 = upvalues[1]
       4 [-]: GETTABLEKS R3 R4 K1; var3 = var4[0xD4CC05B4]
       5 [-]: CALL R3 1 2  ; var3 = var3()
       6 [-]: JUMPIFNOT R3 L1; goto L1 if not var3
       7 [-]: GETUPVAL R5 1; var5 = upvalues[1]
       8 [-]: GETTABLEKS R4 R5 K2; var4 = var5["mTargetMovie"]
       9 [-]: GETIMPORT R5 4; var5 = 0xAE91E43B
      10 [-]: JUMPIFEQ R4 R5 L0; goto L0 if var4 == var16778011
      11 [-]: LOADB R3 0 +1; var3 = false
L 0:  12 [-]: LOADB R3 1   ; var3 = true
L 1:  13 [-]: GETIMPORT R4 7; var4 = 0x7F5022CF[0xA5C556B9]
      14 [-]: MOVE R5 R1   ; var5 = var1
      15 [-]: LOADK R6 K8  ; var6 = "_ENTER"
      16 [-]: CALL R4 3 2  ; var4 = var4(var5, var6)
      17 [-]: JUMPXEQKNIL R4 L2; 
      18 [-]: GETIMPORT R4 10; var4 = 0x9BA7909F
      19 [-]: GETIMPORT R7 12; var7 = 0x0032441C
      20 [-]: GETTABLEKS R6 R7 K13; var6 = var7["UIMovie_ConfirmMovie"]
      21 [-]: NAMECALL R4 R4 K14; var5 = var4; var4 = var4[0x5374B92E]
      22 [-]: CALL R4 3 2  ; var4 = var4(var5, var6)
      23 [-]: JUMPIF R4 L5 ; goto L5 if var4
      24 [-]: JUMPIFNOT R3 L5; goto L5 if not var3
      25 [-]: GETUPVAL R4 2; var4 = upvalues[2]
      26 [-]: CALL R4 1 1  ; var4()
      27 [-]: RETURN R0 0  ; 
L 2:  28 [-]: JUMPIFNOT R3 L5; goto L5 if not var3
      29 [-]: LOADN R4 0   ; var4 = 0
      30 [-]: GETIMPORT R5 7; var5 = 0x7F5022CF[0xA5C556B9]
      31 [-]: MOVE R6 R1   ; var6 = var1
      32 [-]: LOADK R7 K15 ; var7 = "EN_LEFT"
      33 [-]: CALL R5 3 2  ; var5 = var5(var6, var7)
      34 [-]: JUMPIFNOT R5 L3; goto L3 if not var5
      35 [-]: LOADN R4 -1  ; var4 = -1
      36 [-]: JUMP L4      ; goto L4
L 3:  37 [-]: GETIMPORT R5 7; var5 = 0x7F5022CF[0xA5C556B9]
      38 [-]: MOVE R6 R1   ; var6 = var1
      39 [-]: LOADK R7 K16 ; var7 = "EN_RIGHT"
      40 [-]: CALL R5 3 2  ; var5 = var5(var6, var7)
      41 [-]: JUMPIFNOT R5 L4; goto L4 if not var5
      42 [-]: LOADN R4 1   ; var4 = 1
L 4:  43 [-]: JUMPXEQKN R4 K17 L5; 
      44 [-]: GETIMPORT R5 19; var5 = 0x03F57322
      45 [-]: GETUPVAL R7 1; var7 = upvalues[1]
      46 [-]: GETTABLEKS R6 R7 K20; var6 = var7[0x2DA0D9A2]
      47 [-]: GETUPVAL R7 3; var7 = upvalues[3]
      48 [-]: CALL R6 2 0  ; var6, ... = var6(var7)
      49 [-]: CALL R5 0 2  ; var5 = var5(var6, ...)
      50 [-]: GETUPVAL R7 1; var7 = upvalues[1]
      51 [-]: GETTABLEKS R6 R7 K21; var6 = var7[0x2E84930F]
      52 [-]: ADD R7 R5 R4 ; var7 = var5 + var4
      53 [-]: GETUPVAL R8 3; var8 = upvalues[3]
      54 [-]: CALL R6 3 2  ; var6 = var6(var7, var8)
      55 [-]: JUMPIF R6 L5 ; goto L5 if var6
      56 [-]: GETIMPORT R7 4; var7 = 0xAE91E43B
      57 [-]: GETUPVAL R11 4; var11 = upvalues[4]
      58 [-]: GETTABLEKS R10 R11 K22; var10 = var11["InputField"]
      59 [-]: GETTABLEKS R9 R10 K23; var9 = var10["mLabelClipName"]
      60 [-]: LOADN R10 71 ; var10 = 71
      61 [-]: NAMECALL R7 R7 K24; var8 = var7; var7 = var7[0x91A24E4B]
      62 [-]: CALL R7 4 2  ; var7 = var7(var8, var9, var10)
      63 [-]: ORK R6 R7 K17; var6 = var7 or 0
      64 [-]: GETIMPORT R7 4; var7 = 0xAE91E43B
      65 [-]: GETUPVAL R11 4; var11 = upvalues[4]
      66 [-]: GETTABLEKS R10 R11 K22; var10 = var11["InputField"]
      67 [-]: GETTABLEKS R9 R10 K23; var9 = var10["mLabelClipName"]
      68 [-]: LOADN R10 71 ; var10 = 71
      69 [-]: ADD R11 R6 R4; var11 = var6 + var4
      70 [-]: NAMECALL R7 R7 K25; var8 = var7; var7 = var7[0x67BC869F]
      71 [-]: CALL R7 5 1  ; var7(var8, var9, var10, var11)
L 5:  72 [-]: RETURN R0 0  ; 


; Name:            
; Defined at line: 1403
; #Upvalues:       1
; #Parameters:     0
; Is_vararg:       0
; Max Stack Size:  1

       0 [-]: GETUPVAL R0 0; var0 = upvalues[0]
       1 [-]: CALL R0 1 1  ; var0()
       2 [-]: RETURN R0 0  ; 


; Name:            
; Defined at line: 1407
; #Upvalues:       1
; #Parameters:     0
; Is_vararg:       0
; Max Stack Size:  1

       0 [-]: GETUPVAL R0 0; var0 = upvalues[0]
       1 [-]: CALL R0 1 1  ; var0()
       2 [-]: RETURN R0 0  ; 


; Name:            
; Defined at line: 1411
; #Upvalues:       1
; #Parameters:     0
; Is_vararg:       0
; Max Stack Size:  1

       0 [-]: GETUPVAL R0 0; var0 = upvalues[0]
       1 [-]: CALL R0 1 1  ; var0()
       2 [-]: RETURN R0 0  ; 


; Name:            
; Defined at line: 1415
; #Upvalues:       2
; #Parameters:     0
; Is_vararg:       0
; Max Stack Size:  2

       0 [-]: GETUPVAL R0 0; var0 = upvalues[0]
       1 [-]: JUMPIF R0 L1 ; goto L1 if var0
       2 [-]: GETUPVAL R1 1; var1 = upvalues[1]
       3 [-]: FASTCALL1 62 R1 L0; 
       4 [-]: GETIMPORT R0 1; var0 = 0x7B998233
       5 [-]: CALL R0 2 2  ; var0 = var0(var1)
L 0:   6 [-]: JUMPIF R0 L1 ; goto L1 if var0
       7 [-]: GETUPVAL R0 1; var0 = upvalues[1]
       8 [-]: NAMECALL R0 R0 K2; var1 = var0; var0 = var0[0x8B24CE41]
       9 [-]: CALL R0 2 1  ; var0(var1)
L 1:  10 [-]: RETURN R0 0  ; 


; Name:            
; Defined at line: 1423
; #Upvalues:       1
; #Parameters:     0
; Is_vararg:       0
; Max Stack Size:  1

       0 [-]: GETUPVAL R0 0; var0 = upvalues[0]
       1 [-]: RETURN R0 1  ; 


; Name:            
; Defined at line: 1427
; #Upvalues:       1
; #Parameters:     2
; Is_vararg:       0
; Max Stack Size:  3

       0 [-]: GETUPVAL R2 0; var2 = upvalues[0]
       1 [-]: CALL R2 1 1  ; var2()
       2 [-]: RETURN R0 0  ; 


; Name:            
; Defined at line: 1431
; #Upvalues:       1
; #Parameters:     1
; Is_vararg:       0
; Max Stack Size:  5

       0 [-]: GETUPVAL R2 0; var2 = upvalues[0]
       1 [-]: FASTCALL1 62 R2 L0; 
       2 [-]: GETIMPORT R1 1; var1 = 0x7B998233
       3 [-]: CALL R1 2 2  ; var1 = var1(var2)
L 0:   4 [-]: JUMPIF R1 L1 ; goto L1 if var1
       5 [-]: GETUPVAL R1 0; var1 = upvalues[0]
       6 [-]: GETIMPORT R3 3; var3 = 0x03F57322
       7 [-]: MOVE R4 R0   ; var4 = var0
       8 [-]: CALL R3 2 0  ; var3, ... = var3(var4)
       9 [-]: NAMECALL R1 R1 K4; var2 = var1; var1 = var1[0xDF42446E]
      10 [-]: CALL R1 0 1  ; var1(var2, ...)
L 1:  11 [-]: RETURN R0 0  ; 


; Name:            
; Defined at line: 1437
; #Upvalues:       1
; #Parameters:     1
; Is_vararg:       0
; Max Stack Size:  3

       0 [-]: GETUPVAL R2 0; var2 = upvalues[0]
       1 [-]: FASTCALL1 62 R2 L0; 
       2 [-]: GETIMPORT R1 1; var1 = 0x7B998233
       3 [-]: CALL R1 2 2  ; var1 = var1(var2)
L 0:   4 [-]: JUMPIF R1 L1 ; goto L1 if var1
L 1:   5 [-]: RETURN R0 0  ; 


; Name:            
; Defined at line: 1443
; #Upvalues:       3
; #Parameters:     1
; Is_vararg:       0
; Max Stack Size:  5

       0 [-]: GETUPVAL R1 0; var1 = upvalues[0]
       1 [-]: JUMPIF R1 L1 ; goto L1 if var1
       2 [-]: GETUPVAL R2 1; var2 = upvalues[1]
       3 [-]: FASTCALL1 62 R2 L0; 
       4 [-]: GETIMPORT R1 1; var1 = 0x7B998233
       5 [-]: CALL R1 2 2  ; var1 = var1(var2)
L 0:   6 [-]: JUMPIF R1 L1 ; goto L1 if var1
       7 [-]: GETUPVAL R1 1; var1 = upvalues[1]
       8 [-]: GETIMPORT R3 3; var3 = 0x03F57322
       9 [-]: MOVE R4 R0   ; var4 = var0
      10 [-]: CALL R3 2 2  ; var3 = var3(var4)
      11 [-]: LOADB R4 1   ; var4 = true
      12 [-]: NAMECALL R1 R1 K4; var2 = var1; var1 = var1[0x070DAA5A]
      13 [-]: CALL R1 4 1  ; var1(var2, var3, var4)
      14 [-]: GETUPVAL R2 2; var2 = upvalues[2]
      15 [-]: GETTABLEKS R1 R2 K5; var1 = var2[0x659D451F]
      16 [-]: GETIMPORT R3 7; var3 = 0x0032441C
      17 [-]: GETTABLEKS R2 R3 K8; var2 = var3["UISound_Select"]
      18 [-]: CALL R1 2 1  ; var1(var2)
L 1:  19 [-]: RETURN R0 0  ; 


; Name:            
; Defined at line: 1479
; #Upvalues:       2
; #Parameters:     2
; Is_vararg:       0
; Max Stack Size:  7

       0 [-]: GETUPVAL R2 0; var2 = upvalues[0]
       1 [-]: JUMPIF R2 L1 ; goto L1 if var2
       2 [-]: GETUPVAL R4 1; var4 = upvalues[1]
       3 [-]: GETTABLEKS R3 R4 K0; var3 = var4["mScrollBar"]
       4 [-]: FASTCALL1 62 R3 L0; 
       5 [-]: GETIMPORT R2 2; var2 = 0x7B998233
       6 [-]: CALL R2 2 2  ; var2 = var2(var3)
L 0:   7 [-]: JUMPIF R2 L1 ; goto L1 if var2
       8 [-]: GETUPVAL R3 1; var3 = upvalues[1]
       9 [-]: GETTABLEKS R2 R3 K0; var2 = var3["mScrollBar"]
      10 [-]: GETIMPORT R4 4; var4 = 0x03F57322
      11 [-]: MOVE R5 R1   ; var5 = var1
      12 [-]: CALL R4 2 2  ; var4 = var4(var5)
      13 [-]: GETIMPORT R6 6; var6 = 0x0032441C
      14 [-]: GETTABLEKS R5 R6 K7; var5 = var6["UISound_Scroll"]
      15 [-]: NAMECALL R2 R2 K8; var3 = var2; var2 = var2[0x30456F58]
      16 [-]: CALL R2 4 1  ; var2(var3, var4, var5)
L 1:  17 [-]: RETURN R0 0  ; 


; Name:            
; Defined at line: 1485
; #Upvalues:       2
; #Parameters:     2
; Is_vararg:       0
; Max Stack Size:  7

       0 [-]: JUMPIF R0 L0 ; goto L0 if var0
       1 [-]: GETIMPORT R2 1; var2 = 0xAE91E43B
       2 [-]: GETUPVAL R6 0; var6 = upvalues[0]
       3 [-]: GETTABLEKS R5 R6 K2; var5 = var6["InputField"]
       4 [-]: GETTABLEKS R4 R5 K3; var4 = var5["mLabelClipName"]
       5 [-]: LOADN R5 29  ; var5 = 29
       6 [-]: MOVE R6 R1   ; var6 = var1
       7 [-]: NAMECALL R2 R2 K4; var3 = var2; var2 = var2[0x5F56EEAB]
       8 [-]: CALL R2 5 1  ; var2(var3, var4, var5, var6)
       9 [-]: GETUPVAL R2 0; var2 = upvalues[0]
      10 [-]: SETTABLEKS R1 R2 K5; var1["mContent"] = var2
      11 [-]: GETUPVAL R2 1; var2 = upvalues[1]
      12 [-]: CALL R2 1 1  ; var2()
L 0:  13 [-]: RETURN R0 0  ; 


; Name:            
; Defined at line: 1493
; #Upvalues:       3
; #Parameters:     1
; Is_vararg:       0
; Max Stack Size:  12

       0 [-]: GETIMPORT R2 1; var2 = 0x03F57322
       1 [-]: GETUPVAL R4 0; var4 = upvalues[0]
       2 [-]: GETTABLEKS R3 R4 K2; var3 = var4["mCount"]
       3 [-]: CALL R2 2 2  ; var2 = var2(var3)
       4 [-]: GETIMPORT R3 1; var3 = 0x03F57322
       5 [-]: MOVE R4 R0   ; var4 = var0
       6 [-]: CALL R3 2 2  ; var3 = var3(var4)
       7 [-]: ADD R1 R2 R3 ; var1 = var2 + var3
       8 [-]: LOADN R2 0   ; var2 = 0
       9 [-]: GETUPVAL R4 0; var4 = upvalues[0]
      10 [-]: GETTABLEKS R3 R4 K3; var3 = var4["mMinCount"]
      11 [-]: JUMPXEQKNIL R3 L0; 
      12 [-]: GETIMPORT R3 1; var3 = 0x03F57322
      13 [-]: GETUPVAL R5 0; var5 = upvalues[0]
      14 [-]: GETTABLEKS R4 R5 K3; var4 = var5["mMinCount"]
      15 [-]: CALL R3 2 2  ; var3 = var3(var4)
      16 [-]: MOVE R2 R3   ; var2 = var3
L 0:  17 [-]: JUMPIFNOTLT R1 R2 L1; goto L1 if var1 >= var131350
      18 [-]: MOVE R1 R2   ; var1 = var2
L 1:  19 [-]: GETIMPORT R3 1; var3 = 0x03F57322
      20 [-]: GETUPVAL R5 0; var5 = upvalues[0]
      21 [-]: GETTABLEKS R4 R5 K4; var4 = var5["mMaxCount"]
      22 [-]: CALL R3 2 2  ; var3 = var3(var4)
      23 [-]: JUMPIFNOTLT R3 R1 L2; goto L2 if var3 >= var775
      24 [-]: GETUPVAL R3 0; var3 = upvalues[0]
      25 [-]: GETTABLEKS R1 R3 K4; var1 = var3["mMaxCount"]
L 2:  26 [-]: GETIMPORT R3 7; var3 = 0x34291F5C[0x1467D5F4]
      27 [-]: CALL R3 1 2  ; var3 = var3()
      28 [-]: JUMPIFNOT R3 L7; goto L7 if not var3
      29 [-]: GETUPVAL R4 1; var4 = upvalues[1]
      30 [-]: GETTABLEKS R3 R4 K8; var3 = var4[0xF76783E5]
      31 [-]: GETIMPORT R4 10; var4 = 0xAE91E43B
      32 [-]: GETUPVAL R9 0; var9 = upvalues[0]
      33 [-]: GETTABLEKS R6 R9 K11; var6 = var9["mClipName"]
      34 [-]: LOADK R7 K12 ; var7 = ".Callouts."
      35 [-]: GETUPVAL R9 1; var9 = upvalues[1]
      36 [-]: GETTABLEKS R8 R9 K13; var8 = var9[0x06D055F9]
      37 [-]: LOADN R10 0  ; var10 = 0
      38 [-]: JUMPIFLT R10 R0 L3; goto L3 if var10 < var16779547
      39 [-]: LOADB R9 0 +1; var9 = false
L 3:  40 [-]: LOADB R9 1   ; var9 = true
L 4:  41 [-]: LOADK R10 K14; var10 = "Right"
      42 [-]: LOADK R11 K15; var11 = "Left"
      43 [-]: CALL R8 4 2  ; var8 = var8(var9, var10, var11)
      44 [-]: CONCAT R5 R6 R8; var5 = var6 .. var8
      45 [-]: GETUPVAL R7 1; var7 = upvalues[1]
      46 [-]: GETTABLEKS R6 R7 K13; var6 = var7[0x06D055F9]
      47 [-]: LOADN R8 0   ; var8 = 0
      48 [-]: JUMPIFLT R8 R0 L5; goto L5 if var8 < var16779035
      49 [-]: LOADB R7 0 +1; var7 = false
L 5:  50 [-]: LOADB R7 1   ; var7 = true
L 6:  51 [-]: GETIMPORT R9 17; var9 = 0x0032441C
      52 [-]: GETTABLEKS R8 R9 K18; var8 = var9["UIFx_RightBumperPress"]
      53 [-]: GETIMPORT R10 17; var10 = 0x0032441C
      54 [-]: GETTABLEKS R9 R10 K19; var9 = var10["UIFx_LeftBumperPress"]
      55 [-]: CALL R6 4 2  ; var6 = var6(var7, var8, var9)
      56 [-]: LOADN R7 0   ; var7 = 0
      57 [-]: LOADN R8 0   ; var8 = 0
      58 [-]: CALL R3 6 1  ; var3(var4, var5, var6, var7, var8)
L 7:  59 [-]: GETUPVAL R3 0; var3 = upvalues[0]
      60 [-]: SETTABLEKS R1 R3 K2; var1["mCount"] = var3
      61 [-]: GETIMPORT R3 10; var3 = 0xAE91E43B
      62 [-]: GETUPVAL R8 0; var8 = upvalues[0]
      63 [-]: GETTABLEKS R6 R8 K11; var6 = var8["mClipName"]
      64 [-]: LOADK R7 K20 ; var7 = ".Count"
      65 [-]: CONCAT R5 R6 R7; var5 = var6 .. var7
      66 [-]: LOADN R6 29  ; var6 = 29
      67 [-]: GETUPVAL R8 1; var8 = upvalues[1]
      68 [-]: GETTABLEKS R7 R8 K21; var7 = var8[0x1142C7A8]
      69 [-]: GETUPVAL R9 0; var9 = upvalues[0]
      70 [-]: GETTABLEKS R8 R9 K2; var8 = var9["mCount"]
      71 [-]: LOADN R9 0   ; var9 = 0
      72 [-]: CALL R7 3 0  ; var7, ... = var7(var8, var9)
      73 [-]: NAMECALL R3 R3 K22; var4 = var3; var3 = var3[0x5F56EEAB]
      74 [-]: CALL R3 0 1  ; var3(var4, ...)
      75 [-]: GETUPVAL R4 0; var4 = upvalues[0]
      76 [-]: GETTABLEKS R3 R4 K23; var3 = var4["mCallback"]
      77 [-]: JUMPXEQKNIL R3 L8; 
      78 [-]: GETUPVAL R4 0; var4 = upvalues[0]
      79 [-]: GETTABLEKS R3 R4 K23; var3 = var4["mCallback"]
      80 [-]: MOVE R4 R1   ; var4 = var1
      81 [-]: CALL R3 2 1  ; var3(var4)
L 8:  82 [-]: GETUPVAL R3 2; var3 = upvalues[2]
      83 [-]: CALL R3 1 1  ; var3()
      84 [-]: RETURN R0 0  ; 


; Name:            
; Defined at line: 1522
; #Upvalues:       7
; #Parameters:     1
; Is_vararg:       0
; Max Stack Size:  4

       0 [-]: GETUPVAL R1 0; var1 = upvalues[0]
       1 [-]: JUMPIF R1 L0 ; goto L0 if var1
       2 [-]: GETUPVAL R2 1; var2 = upvalues[1]
       3 [-]: GETTABLEKS R1 R2 K0; var1 = var2["mType"]
       4 [-]: GETUPVAL R3 2; var3 = upvalues[2]
       5 [-]: GETTABLEKS R2 R3 K1; var2 = var3["INPUTCOUNT"]
       6 [-]: JUMPIFNOTEQ R1 R2 L0; goto L0 if var1 ~= var196871
       7 [-]: GETUPVAL R1 3; var1 = upvalues[3]
       8 [-]: LOADN R2 1   ; var2 = 1
       9 [-]: CALL R1 2 1  ; var1(var2)
      10 [-]: LOADN R1 1   ; var1 = 1
      11 [-]: SETUPVAL R1 4; upvalues[1] = var4
      12 [-]: LOADN R1 0   ; var1 = 0
      13 [-]: SETUPVAL R1 5; upvalues[1] = var5
      14 [-]: LOADK R1 K2  ; var1 = 0.59999999999999998
      15 [-]: SETUPVAL R1 6; upvalues[1] = var6
L 0:  16 [-]: RETURN R0 0  ; 


; Name:            
; Defined at line: 1532
; #Upvalues:       7
; #Parameters:     1
; Is_vararg:       0
; Max Stack Size:  4

       0 [-]: GETUPVAL R1 0; var1 = upvalues[0]
       1 [-]: JUMPIF R1 L0 ; goto L0 if var1
       2 [-]: GETUPVAL R2 1; var2 = upvalues[1]
       3 [-]: GETTABLEKS R1 R2 K0; var1 = var2["mType"]
       4 [-]: GETUPVAL R3 2; var3 = upvalues[2]
       5 [-]: GETTABLEKS R2 R3 K1; var2 = var3["INPUTCOUNT"]
       6 [-]: JUMPIFNOTEQ R1 R2 L0; goto L0 if var1 ~= var196871
       7 [-]: GETUPVAL R1 3; var1 = upvalues[3]
       8 [-]: LOADN R2 -1  ; var2 = -1
       9 [-]: CALL R1 2 1  ; var1(var2)
      10 [-]: LOADN R1 -1  ; var1 = -1
      11 [-]: SETUPVAL R1 4; upvalues[1] = var4
      12 [-]: LOADN R1 0   ; var1 = 0
      13 [-]: SETUPVAL R1 5; upvalues[1] = var5
      14 [-]: LOADK R1 K2  ; var1 = 0.59999999999999998
      15 [-]: SETUPVAL R1 6; upvalues[1] = var6
L 0:  16 [-]: RETURN R0 0  ; 


; Name:            
; Defined at line: 1542
; #Upvalues:       1
; #Parameters:     0
; Is_vararg:       0
; Max Stack Size:  1

       0 [-]: LOADNIL R0   ; var0 = nil
       1 [-]: SETUPVAL R0 0; upvalues[0] = var0
       2 [-]: RETURN R0 0  ; 


; Name:            
; Defined at line: 1546
; #Upvalues:       1
; #Parameters:     1
; Is_vararg:       0
; Max Stack Size:  4

       0 [-]: GETUPVAL R1 0; var1 = upvalues[0]
       1 [-]: GETIMPORT R2 1; var2 = 0x03F57322
       2 [-]: MOVE R3 R0   ; var3 = var0
       3 [-]: CALL R2 2 0  ; var2, ... = var2(var3)
       4 [-]: CALL R1 0 1  ; var1(var2, ...)
       5 [-]: RETURN R0 0  ; 


; Name:            
; Defined at line: 1550
; #Upvalues:       1
; #Parameters:     1
; Is_vararg:       0
; Max Stack Size:  4

       0 [-]: GETUPVAL R1 0; var1 = upvalues[0]
       1 [-]: GETIMPORT R2 1; var2 = 0x03F57322
       2 [-]: MOVE R3 R0   ; var3 = var0
       3 [-]: CALL R2 2 0  ; var2, ... = var2(var3)
       4 [-]: CALL R1 0 1  ; var1(var2, ...)
       5 [-]: RETURN R0 0  ; 


; Name:            
; Defined at line: 1554
; #Upvalues:       1
; #Parameters:     0
; Is_vararg:       0
; Max Stack Size:  1

       0 [-]: GETUPVAL R0 0; var0 = upvalues[0]
       1 [-]: CALL R0 1 1  ; var0()
       2 [-]: RETURN R0 0  ; 


; Name:            
; Defined at line: 1558
; #Upvalues:       4
; #Parameters:     1
; Is_vararg:       0
; Max Stack Size:  9

       0 [-]: GETUPVAL R1 0; var1 = upvalues[0]
       1 [-]: GETIMPORT R3 1; var3 = 0x03F57322
       2 [-]: MOVE R4 R0   ; var4 = var0
       3 [-]: CALL R3 2 0  ; var3, ... = var3(var4)
       4 [-]: NAMECALL R1 R1 K2; var2 = var1; var1 = var1[0x1D246732]
       5 [-]: CALL R1 0 2  ; var1 = var1(var2, ...)
       6 [-]: FASTCALL1 62 R1 L0; 
       7 [-]: MOVE R3 R1   ; var3 = var1
       8 [-]: GETIMPORT R2 4; var2 = 0x7B998233
       9 [-]: CALL R2 2 2  ; var2 = var2(var3)
L 0:  10 [-]: JUMPIF R2 L1 ; goto L1 if var2
      11 [-]: GETUPVAL R2 0; var2 = upvalues[0]
      12 [-]: GETIMPORT R4 1; var4 = 0x03F57322
      13 [-]: MOVE R5 R0   ; var5 = var0
      14 [-]: CALL R4 2 0  ; var4, ... = var4(var5)
      15 [-]: NAMECALL R2 R2 K5; var3 = var2; var2 = var2[0xDF42446E]
      16 [-]: CALL R2 0 1  ; var2(var3, ...)
      17 [-]: LOADB R2 1   ; var2 = true
      18 [-]: SETUPVAL R2 1; upvalues[2] = var1
      19 [-]: GETUPVAL R2 0; var2 = upvalues[0]
      20 [-]: MOVE R4 R1   ; var4 = var1
      21 [-]: NAMECALL R2 R2 K6; var3 = var2; var2 = var2[0x5465F8F3]
      22 [-]: CALL R2 3 2  ; var2 = var2(var3, var4)
      23 [-]: GETIMPORT R3 8; var3 = 0xAE91E43B
      24 [-]: GETTABLEKS R6 R2 K9; var6 = var2["mClipName"]
      25 [-]: LOADK R7 K10 ; var7 = ".Count"
      26 [-]: CONCAT R5 R6 R7; var5 = var6 .. var7
      27 [-]: LOADN R6 29  ; var6 = 29
      28 [-]: NAMECALL R3 R3 K11; var4 = var3; var3 = var3[0x54A95D6F]
      29 [-]: CALL R3 4 2  ; var3 = var3(var4, var5, var6)
      30 [-]: GETIMPORT R4 1; var4 = 0x03F57322
      31 [-]: MOVE R5 R0   ; var5 = var0
      32 [-]: CALL R4 2 2  ; var4 = var4(var5)
      33 [-]: SETUPVAL R4 2; upvalues[4] = var2
      34 [-]: SETUPVAL R3 3; upvalues[3] = var3
      35 [-]: GETIMPORT R4 1; var4 = 0x03F57322
      36 [-]: MOVE R5 R3   ; var5 = var3
      37 [-]: CALL R4 2 2  ; var4 = var4(var5)
      38 [-]: JUMPXEQKN R4 K12 L1 NOT; 
      39 [-]: GETIMPORT R4 8; var4 = 0xAE91E43B
      40 [-]: GETTABLEKS R7 R2 K9; var7 = var2["mClipName"]
      41 [-]: LOADK R8 K10 ; var8 = ".Count"
      42 [-]: CONCAT R6 R7 R8; var6 = var7 .. var8
      43 [-]: LOADN R7 29  ; var7 = 29
      44 [-]: LOADK R8 K13 ; var8 = ""
      45 [-]: NAMECALL R4 R4 K14; var5 = var4; var4 = var4[0x5F56EEAB]
      46 [-]: CALL R4 5 1  ; var4(var5, var6, var7, var8)
      47 [-]: LOADK R4 K13 ; var4 = ""
      48 [-]: SETUPVAL R4 3; upvalues[4] = var3
L 1:  49 [-]: RETURN R0 0  ; 


; Name:            
; Defined at line: 1575
; #Upvalues:       3
; #Parameters:     1
; Is_vararg:       0
; Max Stack Size:  9

       0 [-]: LOADB R1 0   ; var1 = false
       1 [-]: SETUPVAL R1 0; upvalues[1] = var0
       2 [-]: GETUPVAL R1 1; var1 = upvalues[1]
       3 [-]: CALL R1 1 1  ; var1()
       4 [-]: GETUPVAL R1 2; var1 = upvalues[2]
       5 [-]: GETIMPORT R3 1; var3 = 0x03F57322
       6 [-]: MOVE R4 R0   ; var4 = var0
       7 [-]: CALL R3 2 0  ; var3, ... = var3(var4)
       8 [-]: NAMECALL R1 R1 K2; var2 = var1; var1 = var1[0x1D246732]
       9 [-]: CALL R1 0 2  ; var1 = var1(var2, ...)
      10 [-]: FASTCALL1 62 R1 L0; 
      11 [-]: MOVE R3 R1   ; var3 = var1
      12 [-]: GETIMPORT R2 4; var2 = 0x7B998233
      13 [-]: CALL R2 2 2  ; var2 = var2(var3)
L 0:  14 [-]: JUMPIF R2 L2 ; goto L2 if var2
      15 [-]: GETUPVAL R2 2; var2 = upvalues[2]
      16 [-]: MOVE R4 R1   ; var4 = var1
      17 [-]: NAMECALL R2 R2 K5; var3 = var2; var2 = var2[0x5465F8F3]
      18 [-]: CALL R2 3 2  ; var2 = var2(var3, var4)
      19 [-]: GETIMPORT R3 7; var3 = 0xAE91E43B
      20 [-]: GETTABLEKS R6 R2 K8; var6 = var2["mClipName"]
      21 [-]: LOADK R7 K9  ; var7 = ".Count"
      22 [-]: CONCAT R5 R6 R7; var5 = var6 .. var7
      23 [-]: LOADN R6 29  ; var6 = 29
      24 [-]: NAMECALL R3 R3 K10; var4 = var3; var3 = var3[0x54A95D6F]
      25 [-]: CALL R3 4 2  ; var3 = var3(var4, var5, var6)
      26 [-]: JUMPXEQKS R3 K11 L1 NOT; 
      27 [-]: GETIMPORT R4 7; var4 = 0xAE91E43B
      28 [-]: GETTABLEKS R7 R2 K8; var7 = var2["mClipName"]
      29 [-]: LOADK R8 K9  ; var8 = ".Count"
      30 [-]: CONCAT R6 R7 R8; var6 = var7 .. var8
      31 [-]: LOADN R7 29  ; var7 = 29
      32 [-]: LOADK R8 K12 ; var8 = "0"
      33 [-]: NAMECALL R4 R4 K13; var5 = var4; var4 = var4[0x5F56EEAB]
      34 [-]: CALL R4 5 1  ; var4(var5, var6, var7, var8)
L 1:  35 [-]: GETTABLEKS R4 R2 K14; var4 = var2["mCallback"]
      36 [-]: JUMPXEQKNIL R4 L2; 
      37 [-]: GETTABLEKS R4 R2 K14; var4 = var2["mCallback"]
      38 [-]: GETTABLEKS R5 R2 K15; var5 = var2["mCount"]
      39 [-]: CALL R4 2 1  ; var4(var5)
L 2:  40 [-]: RETURN R0 0  ; 


; Name:            
; Defined at line: 1592
; #Upvalues:       4
; #Parameters:     0
; Is_vararg:       0
; Max Stack Size:  3

       0 [-]: GETUPVAL R0 0; var0 = upvalues[0]
       1 [-]: JUMPIF R0 L1 ; goto L1 if var0
       2 [-]: GETUPVAL R1 1; var1 = upvalues[1]
       3 [-]: FASTCALL1 62 R1 L0; 
       4 [-]: GETIMPORT R0 1; var0 = 0x7B998233
       5 [-]: CALL R0 2 2  ; var0 = var0(var1)
L 0:   6 [-]: JUMPIF R0 L1 ; goto L1 if var0
       7 [-]: GETUPVAL R1 1; var1 = upvalues[1]
       8 [-]: GETTABLEKS R0 R1 K2; var0 = var1["mType"]
       9 [-]: GETUPVAL R2 2; var2 = upvalues[2]
      10 [-]: GETTABLEKS R1 R2 K3; var1 = var2["INPUTCOUNT"]
      11 [-]: JUMPIFNOTEQ R0 R1 L1; goto L1 if var0 ~= var196615
      12 [-]: GETUPVAL R0 3; var0 = upvalues[3]
      13 [-]: GETUPVAL R2 1; var2 = upvalues[1]
      14 [-]: GETTABLEKS R1 R2 K4; var1 = var2["Id"]
      15 [-]: CALL R0 2 1  ; var0(var1)
L 1:  16 [-]: LOADB R0 1   ; var0 = true
      17 [-]: RETURN R0 1  ; 


; Name:            
; Defined at line: 1599
; #Upvalues:       4
; #Parameters:     0
; Is_vararg:       0
; Max Stack Size:  3

       0 [-]: GETUPVAL R0 0; var0 = upvalues[0]
       1 [-]: JUMPIF R0 L1 ; goto L1 if var0
       2 [-]: GETUPVAL R1 1; var1 = upvalues[1]
       3 [-]: FASTCALL1 62 R1 L0; 
       4 [-]: GETIMPORT R0 1; var0 = 0x7B998233
       5 [-]: CALL R0 2 2  ; var0 = var0(var1)
L 0:   6 [-]: JUMPIF R0 L1 ; goto L1 if var0
       7 [-]: GETUPVAL R1 1; var1 = upvalues[1]
       8 [-]: GETTABLEKS R0 R1 K2; var0 = var1["mType"]
       9 [-]: GETUPVAL R2 2; var2 = upvalues[2]
      10 [-]: GETTABLEKS R1 R2 K3; var1 = var2["INPUTCOUNT"]
      11 [-]: JUMPIFNOTEQ R0 R1 L1; goto L1 if var0 ~= var196615
      12 [-]: GETUPVAL R0 3; var0 = upvalues[3]
      13 [-]: GETUPVAL R2 1; var2 = upvalues[1]
      14 [-]: GETTABLEKS R1 R2 K4; var1 = var2["Id"]
      15 [-]: CALL R0 2 1  ; var0(var1)
L 1:  16 [-]: LOADB R0 1   ; var0 = true
      17 [-]: RETURN R0 1  ; 


; Name:            
; Defined at line: 1606
; #Upvalues:       1
; #Parameters:     0
; Is_vararg:       0
; Max Stack Size:  1

       0 [-]: GETUPVAL R0 0; var0 = upvalues[0]
       1 [-]: CALL R0 1 1  ; var0()
       2 [-]: LOADB R0 1   ; var0 = true
       3 [-]: RETURN R0 1  ; 


; Name:            
; Defined at line: 1611
; #Upvalues:       1
; #Parameters:     0
; Is_vararg:       0
; Max Stack Size:  1

       0 [-]: GETUPVAL R0 0; var0 = upvalues[0]
       1 [-]: CALL R0 1 1  ; var0()
       2 [-]: LOADB R0 1   ; var0 = true
       3 [-]: RETURN R0 1  ; 


; Name:            
; Defined at line: 1616
; #Upvalues:       1
; #Parameters:     0
; Is_vararg:       0
; Max Stack Size:  2

       0 [-]: GETUPVAL R0 0; var0 = upvalues[0]
       1 [-]: LOADB R1 1   ; var1 = true
       2 [-]: CALL R0 2 1  ; var0(var1)
       3 [-]: LOADB R0 1   ; var0 = true
       4 [-]: RETURN R0 1  ; 


; Name:            
; Defined at line: 1621
; #Upvalues:       0
; #Parameters:     1
; Is_vararg:       0
; Max Stack Size:  1

       0 [-]: RETURN R0 0  ; 


; Name:            
; Defined at line: 1624
; #Upvalues:       2
; #Parameters:     1
; Is_vararg:       0
; Max Stack Size:  3

       0 [-]: GETUPVAL R2 0; var2 = upvalues[0]
       1 [-]: GETTABLEKS R1 R2 K0; var1 = var2[0x2C2FDF05]
       2 [-]: MOVE R2 R0   ; var2 = var0
       3 [-]: CALL R1 2 1  ; var1(var2)
       4 [-]: GETUPVAL R2 1; var2 = upvalues[1]
       5 [-]: GETTABLEKS R1 R2 K1; var1 = var2[0x90CA007F]
       6 [-]: GETIMPORT R2 3; var2 = 0xAE91E43B
       7 [-]: CALL R1 2 1  ; var1(var2)
       8 [-]: RETURN R0 0  ; 


; Name:            
; Defined at line: 1629
; #Upvalues:       1
; #Parameters:     1
; Is_vararg:       0
; Max Stack Size:  11

       0 [-]: FASTCALL1 62 R0 L0; 
       1 [-]: MOVE R2 R0   ; var2 = var0
       2 [-]: GETIMPORT R1 1; var1 = 0x7B998233
       3 [-]: CALL R1 2 2  ; var1 = var1(var2)
L 0:   4 [-]: JUMPIF R1 L1 ; goto L1 if var1
       5 [-]: GETIMPORT R1 3; var1 = 0xAE91E43B
       6 [-]: LOADK R3 K4  ; var3 = "<CHECKMARK>"
       7 [-]: LOADB R4 1   ; var4 = true
       8 [-]: NAMECALL R1 R1 K5; var2 = var1; var1 = var1[0x42B04007]
       9 [-]: CALL R1 4 2  ; var1 = var1(var2, var3, var4)
      10 [-]: GETIMPORT R2 3; var2 = 0xAE91E43B
      11 [-]: LOADK R4 K6  ; var4 = "<CHECKMARK_OUTLINE>"
      12 [-]: LOADB R5 1   ; var5 = true
      13 [-]: NAMECALL R2 R2 K5; var3 = var2; var2 = var2[0x42B04007]
      14 [-]: CALL R2 4 2  ; var2 = var2(var3, var4, var5)
      15 [-]: GETTABLEKS R3 R0 K7; var3 = var0["Parent"]
      16 [-]: LOADB R4 1   ; var4 = true
      17 [-]: SETTABLEKS R4 R3 K8; var4["mValue"] = var3
      18 [-]: MOVE R6 R1   ; var6 = var1
      19 [-]: LOADK R7 K9  ; var7 = " "
      20 [-]: GETTABLEKS R8 R0 K10; var8 = var0["mBaseLabel"]
      21 [-]: CONCAT R5 R6 R8; var5 = var6 .. var8
      22 [-]: NAMECALL R3 R0 K11; var4 = var0; var3 = var0[0x9B71E815]
      23 [-]: CALL R3 3 1  ; var3(var4, var5)
      24 [-]: GETTABLEKS R4 R0 K7; var4 = var0["Parent"]
      25 [-]: GETTABLEKS R3 R4 K12; var3 = var4["NoBtn"]
      26 [-]: MOVE R6 R2   ; var6 = var2
      27 [-]: LOADK R7 K9  ; var7 = " "
      28 [-]: GETTABLEKS R10 R0 K7; var10 = var0["Parent"]
      29 [-]: GETTABLEKS R9 R10 K12; var9 = var10["NoBtn"]
      30 [-]: GETTABLEKS R8 R9 K10; var8 = var9["mBaseLabel"]
      31 [-]: CONCAT R5 R6 R8; var5 = var6 .. var8
      32 [-]: NAMECALL R3 R3 K11; var4 = var3; var3 = var3[0x9B71E815]
      33 [-]: CALL R3 3 1  ; var3(var4, var5)
      34 [-]: GETUPVAL R3 0; var3 = upvalues[0]
      35 [-]: CALL R3 1 1  ; var3()
L 1:  36 [-]: RETURN R0 0  ; 


; Name:            
; Defined at line: 1640
; #Upvalues:       1
; #Parameters:     1
; Is_vararg:       0
; Max Stack Size:  11

       0 [-]: FASTCALL1 62 R0 L0; 
       1 [-]: MOVE R2 R0   ; var2 = var0
       2 [-]: GETIMPORT R1 1; var1 = 0x7B998233
       3 [-]: CALL R1 2 2  ; var1 = var1(var2)
L 0:   4 [-]: JUMPIF R1 L1 ; goto L1 if var1
       5 [-]: GETIMPORT R1 3; var1 = 0xAE91E43B
       6 [-]: LOADK R3 K4  ; var3 = "<CHECKMARK>"
       7 [-]: LOADB R4 1   ; var4 = true
       8 [-]: NAMECALL R1 R1 K5; var2 = var1; var1 = var1[0x42B04007]
       9 [-]: CALL R1 4 2  ; var1 = var1(var2, var3, var4)
      10 [-]: GETIMPORT R2 3; var2 = 0xAE91E43B
      11 [-]: LOADK R4 K6  ; var4 = "<CHECKMARK_OUTLINE>"
      12 [-]: LOADB R5 1   ; var5 = true
      13 [-]: NAMECALL R2 R2 K5; var3 = var2; var2 = var2[0x42B04007]
      14 [-]: CALL R2 4 2  ; var2 = var2(var3, var4, var5)
      15 [-]: GETTABLEKS R3 R0 K7; var3 = var0["Parent"]
      16 [-]: LOADB R4 0   ; var4 = false
      17 [-]: SETTABLEKS R4 R3 K8; var4["mValue"] = var3
      18 [-]: MOVE R6 R1   ; var6 = var1
      19 [-]: LOADK R7 K9  ; var7 = " "
      20 [-]: GETTABLEKS R8 R0 K10; var8 = var0["mBaseLabel"]
      21 [-]: CONCAT R5 R6 R8; var5 = var6 .. var8
      22 [-]: NAMECALL R3 R0 K11; var4 = var0; var3 = var0[0x9B71E815]
      23 [-]: CALL R3 3 1  ; var3(var4, var5)
      24 [-]: GETTABLEKS R4 R0 K7; var4 = var0["Parent"]
      25 [-]: GETTABLEKS R3 R4 K12; var3 = var4["YesBtn"]
      26 [-]: MOVE R6 R2   ; var6 = var2
      27 [-]: LOADK R7 K9  ; var7 = " "
      28 [-]: GETTABLEKS R10 R0 K7; var10 = var0["Parent"]
      29 [-]: GETTABLEKS R9 R10 K12; var9 = var10["YesBtn"]
      30 [-]: GETTABLEKS R8 R9 K10; var8 = var9["mBaseLabel"]
      31 [-]: CONCAT R5 R6 R8; var5 = var6 .. var8
      32 [-]: NAMECALL R3 R3 K11; var4 = var3; var3 = var3[0x9B71E815]
      33 [-]: CALL R3 3 1  ; var3(var4, var5)
      34 [-]: GETUPVAL R3 0; var3 = upvalues[0]
      35 [-]: CALL R3 1 1  ; var3()
L 1:  36 [-]: RETURN R0 0  ; 


; Name:            
; Defined at line: 1651
; #Upvalues:       0
; #Parameters:     1
; Is_vararg:       0
; Max Stack Size:  15

       0 [-]: GETIMPORT R1 1; var1 = 0x03F57322
       1 [-]: MOVE R2 R0   ; var2 = var0
       2 [-]: CALL R1 2 2  ; var1 = var1(var2)
       3 [-]: MOVE R0 R1   ; var0 = var1
       4 [-]: GETIMPORT R1 3; var1 = 0xAE91E43B
       5 [-]: LOADK R3 K4  ; var3 = "_root"
       6 [-]: LOADN R4 0   ; var4 = 0
       7 [-]: NAMECALL R1 R1 K5; var2 = var1; var1 = var1[0x91A24E4B]
       8 [-]: CALL R1 4 2  ; var1 = var1(var2, var3, var4)
       9 [-]: GETIMPORT R2 3; var2 = 0xAE91E43B
      10 [-]: LOADK R4 K4  ; var4 = "_root"
      11 [-]: LOADN R5 1   ; var5 = 1
      12 [-]: NAMECALL R2 R2 K5; var3 = var2; var2 = var2[0x91A24E4B]
      13 [-]: CALL R2 4 2  ; var2 = var2(var3, var4, var5)
      14 [-]: GETIMPORT R3 3; var3 = 0xAE91E43B
      15 [-]: LOADK R5 K4  ; var5 = "_root"
      16 [-]: LOADN R6 12  ; var6 = 12
      17 [-]: NAMECALL R3 R3 K5; var4 = var3; var3 = var3[0x91A24E4B]
      18 [-]: CALL R3 4 2  ; var3 = var3(var4, var5, var6)
      19 [-]: GETIMPORT R4 3; var4 = 0xAE91E43B
      20 [-]: LOADK R6 K4  ; var6 = "_root"
      21 [-]: LOADN R7 13  ; var7 = 13
      22 [-]: NAMECALL R4 R4 K5; var5 = var4; var4 = var4[0x91A24E4B]
      23 [-]: CALL R4 4 2  ; var4 = var4(var5, var6, var7)
      24 [-]: GETIMPORT R5 3; var5 = 0xAE91E43B
      25 [-]: LOADK R7 K4  ; var7 = "_root"
      26 [-]: LOADN R8 5   ; var8 = 5
      27 [-]: MOVE R9 R0   ; var9 = var0
      28 [-]: NAMECALL R5 R5 K6; var6 = var5; var5 = var5[0x67BC869F]
      29 [-]: CALL R5 5 1  ; var5(var6, var7, var8, var9)
      30 [-]: GETIMPORT R5 3; var5 = 0xAE91E43B
      31 [-]: LOADK R7 K4  ; var7 = "_root"
      32 [-]: LOADN R8 6   ; var8 = 6
      33 [-]: MOVE R9 R0   ; var9 = var0
      34 [-]: NAMECALL R5 R5 K6; var6 = var5; var5 = var5[0x67BC869F]
      35 [-]: CALL R5 5 1  ; var5(var6, var7, var8, var9)
      36 [-]: GETIMPORT R5 3; var5 = 0xAE91E43B
      37 [-]: LOADK R7 K4  ; var7 = "_root"
      38 [-]: LOADN R8 0   ; var8 = 0
      39 [-]: DIVK R13 R0 K8; var13 = var0 / 100
      40 [-]: MUL R12 R3 R13; var12 = var3 * var13
      41 [-]: SUB R11 R12 R3; var11 = var12 - var3
      42 [-]: DIVK R10 R11 K7; var10 = var11 / 2
      43 [-]: SUB R9 R1 R10; var9 = var1 - var10
      44 [-]: NAMECALL R5 R5 K6; var6 = var5; var5 = var5[0x67BC869F]
      45 [-]: CALL R5 5 1  ; var5(var6, var7, var8, var9)
      46 [-]: GETIMPORT R5 3; var5 = 0xAE91E43B
      47 [-]: LOADK R7 K4  ; var7 = "_root"
      48 [-]: LOADN R8 1   ; var8 = 1
      49 [-]: DIVK R14 R0 K8; var14 = var0 / 100
      50 [-]: MUL R13 R4 R14; var13 = var4 * var14
      51 [-]: SUB R12 R13 R4; var12 = var13 - var4
      52 [-]: DIVK R11 R12 K7; var11 = var12 / 2
      53 [-]: SUB R10 R2 R11; var10 = var2 - var11
      54 [-]: SUBK R9 R10 K9; var9 = var10 - 30
      55 [-]: NAMECALL R5 R5 K6; var6 = var5; var5 = var5[0x67BC869F]
      56 [-]: CALL R5 5 1  ; var5(var6, var7, var8, var9)
      57 [-]: RETURN R0 0  ; 


; Name:            
; Defined at line: 1666
; #Upvalues:       1
; #Parameters:     1
; Is_vararg:       0
; Max Stack Size:  4

       0 [-]: GETUPVAL R2 0; var2 = upvalues[0]
       1 [-]: GETTABLEKS R1 R2 K0; var1 = var2[0x659D451F]
       2 [-]: GETIMPORT R3 2; var3 = 0x0032441C
       3 [-]: GETTABLEKS R2 R3 K3; var2 = var3["UISound_Error"]
       4 [-]: CALL R1 2 1  ; var1(var2)
       5 [-]: RETURN R0 0  ; 


; Name:            
; Defined at line: 1670
; #Upvalues:       1
; #Parameters:     1
; Is_vararg:       0
; Max Stack Size:  2

       0 [-]: JUMPXEQKS R0 K0 L0; 
       1 [-]: LOADB R1 0 +1; var1 = false
L 0:   2 [-]: LOADB R1 1   ; var1 = true
L 1:   3 [-]: SETUPVAL R1 0; upvalues[1] = var0
       4 [-]: RETURN R0 0  ; 


; Name:            
; Defined at line: 1674
; #Upvalues:       0
; #Parameters:     0
; Is_vararg:       0
; Max Stack Size:  1

       0 [-]: LOADB R0 1   ; var0 = true
       1 [-]: RETURN R0 1  ; 



