; Name:            
; Defined at line: 1
; #Upvalues:       0
; #Parameters:     0
; Is_vararg:       1
; Max Stack Size:  37

            1 [-]: GETIMPORT R0 1 [nil]
       2 [-]: LOADK R1 K2 ["EE.Interface.Utilities"]
       3 [-]: CALL R0 1 1  
       4 [-]: GETIMPORT R1 1 [nil]
       5 [-]: LOADK R2 K3 ["Lotus.Interface.UIStyleUtilities"]
       6 [-]: CALL R1 1 1  
       7 [-]: GETIMPORT R2 1 [nil]
       8 [-]: LOADK R3 K4 ["Lotus.Interface.UIUtilities"]
       9 [-]: CALL R2 1 1  
      10 [-]: GETIMPORT R3 1 [nil]
      11 [-]: LOADK R4 K5 ["Lotus.Interface.Libs.DuviriUtil"]
      12 [-]: CALL R3 1 1  
      13 [-]: LOADNIL R4   
      14 [-]: LOADNIL R5   
      15 [-]: LOADB R6 0   
      16 [-]: LOADNIL R7   
      17 [-]: LOADNIL R8   
      18 [-]: LOADNIL R9   
      19 [-]: LOADN R10 1  
      20 [-]: LOADNIL R11  
      21 [-]: LOADNIL R12  
      22 [-]: LOADNIL R13  
      23 [-]: NEWTABLE R14 0 0
      24 [-]: LOADB R15 0  
      25 [-]: LOADK R16 K6 [""]
      26 [-]: NEWTABLE R17 0 5
      27 [-]: LOADK R18 K7 ["Abilities"]
      28 [-]: LOADK R19 K8 ["Description"]
      29 [-]: LOADK R20 K9 ["Passive"]
      30 [-]: LOADK R21 K10 ["SuitList"]
      31 [-]: LOADK R22 K11 ["ConfirmBtn"]
      32 [-]: SETLIST R17 R18 5 [1]
      33 [-]: LOADNIL R18  
      34 [-]: LOADNIL R19  
      35 [-]: LOADNIL R20  
      36 [-]: NEWCLOSURE R21 P0
      37 [-]: MOVE R0 R0   
      38 [-]: MOVE R1 R4   
      39 [-]: MOVE R0 R2   
      40 [-]: MOVE R1 R11  
      41 [-]: MOVE R1 R12  
      42 [-]: DUPCLOSURE R22 K12 []
      43 [-]: MOVE R0 R21  
      44 [-]: SETGLOBAL R22 K13 ["onViewportSizeChanged"]
      45 [-]: NEWCLOSURE R22 P2
      46 [-]: MOVE R1 R16  
      47 [-]: MOVE R0 R0   
      48 [-]: DUPCLOSURE R23 K14 []
      49 [-]: MOVE R0 R2   
      50 [-]: NEWCLOSURE R24 P4
      51 [-]: MOVE R1 R11  
      52 [-]: MOVE R0 R0   
      53 [-]: MOVE R1 R9   
      54 [-]: MOVE R1 R12  
      55 [-]: MOVE R0 R23  
      56 [-]: NEWCLOSURE R25 P5
      57 [-]: MOVE R0 R1   
      58 [-]: MOVE R1 R12  
      59 [-]: MOVE R0 R0   
      60 [-]: NEWCLOSURE R26 P6
      61 [-]: MOVE R1 R7   
      62 [-]: MOVE R1 R5   
      63 [-]: MOVE R1 R15  
      64 [-]: DUPCLOSURE R27 K15 []
      65 [-]: MOVE R0 R3   
      66 [-]: NEWCLOSURE R28 P8
      67 [-]: MOVE R1 R6   
      68 [-]: MOVE R1 R15  
      69 [-]: MOVE R0 R0   
      70 [-]: MOVE R1 R13  
      71 [-]: MOVE R0 R3   
      72 [-]: MOVE R1 R19  
      73 [-]: MOVE R1 R20  
      74 [-]: MOVE R1 R10  
      75 [-]: MOVE R0 R17  
      76 [-]: DUPCLOSURE R29 K16 []
      77 [-]: MOVE R0 R28  
      78 [-]: SETGLOBAL R29 K17 ["Confirm"]
      79 [-]: NEWCLOSURE R29 P10
      80 [-]: MOVE R0 R26  
      81 [-]: MOVE R1 R10  
      82 [-]: NEWCLOSURE R30 P11
      83 [-]: MOVE R1 R10  
      84 [-]: MOVE R0 R14  
      85 [-]: MOVE R0 R26  
      86 [-]: DUPCLOSURE R31 K18 []
      87 [-]: MOVE R0 R0   
      88 [-]: MOVE R0 R30  
      89 [-]: SETGLOBAL R31 K19 ["PreviewSuit"]
      90 [-]: NEWCLOSURE R31 P13
      91 [-]: MOVE R1 R10  
      92 [-]: MOVE R0 R14  
      93 [-]: NEWCLOSURE R32 P14
      94 [-]: MOVE R1 R11  
      95 [-]: NEWCLOSURE R33 P15
      96 [-]: MOVE R1 R5   
      97 [-]: MOVE R1 R8   
      98 [-]: MOVE R1 R9   
      99 [-]: MOVE R0 R3   
     100 [-]: MOVE R0 R0   
     101 [-]: MOVE R0 R26  
     102 [-]: MOVE R1 R10  
     103 [-]: MOVE R1 R13  
     104 [-]: MOVE R0 R31  
     105 [-]: MOVE R1 R11  
     106 [-]: MOVE R1 R4   
     107 [-]: MOVE R0 R25  
     108 [-]: MOVE R0 R21  
     109 [-]: MOVE R0 R17  
     110 [-]: SETGLOBAL R33 K20 ["Initialize"]
     111 [-]: NEWCLOSURE R33 P16
     112 [-]: MOVE R1 R18  
     113 [-]: SETGLOBAL R33 K21 ["Shutdown"]
     114 [-]: DUPCLOSURE R33 K22 []
     115 [-]: NEWCLOSURE R34 P18
     116 [-]: MOVE R1 R8   
     117 [-]: MOVE R1 R5   
     118 [-]: MOVE R1 R10  
     119 [-]: MOVE R1 R16  
     120 [-]: MOVE R0 R22  
     121 [-]: MOVE R0 R24  
     122 [-]: MOVE R0 R3   
     123 [-]: MOVE R1 R19  
     124 [-]: MOVE R0 R0   
     125 [-]: MOVE R1 R20  
     126 [-]: MOVE R1 R18  
     127 [-]: MOVE R0 R25  
     128 [-]: MOVE R0 R21  
     129 [-]: MOVE R1 R15  
     130 [-]: NEWCLOSURE R35 P19
     131 [-]: MOVE R1 R8   
     132 [-]: MOVE R1 R11  
     133 [-]: MOVE R0 R34  
     134 [-]: SETGLOBAL R35 K23 ["Update"]
     135 [-]: NEWCLOSURE R35 P20
     136 [-]: MOVE R1 R10  
     137 [-]: MOVE R0 R14  
     138 [-]: MOVE R0 R30  
     139 [-]: NEWCLOSURE R36 P21
     140 [-]: MOVE R0 R0   
     141 [-]: MOVE R1 R10  
     142 [-]: MOVE R0 R14  
     143 [-]: MOVE R0 R30  
     144 [-]: SETGLOBAL R36 K24 ["onKeyDown_MENU_LTRIGGER2"]
     145 [-]: NEWCLOSURE R36 P22
     146 [-]: MOVE R0 R0   
     147 [-]: MOVE R1 R10  
     148 [-]: MOVE R0 R14  
     149 [-]: MOVE R0 R30  
     150 [-]: SETGLOBAL R36 K25 ["onKeyDown_MENU_RTRIGGER2"]
     151 [-]: NEWCLOSURE R36 P23
     152 [-]: MOVE R1 R15  
     153 [-]: SETGLOBAL R36 K26 ["IsInputBlocked"]
     154 [-]: DUPCLOSURE R36 K27 []
     155 [-]: SETGLOBAL R36 K28 ["onKeyDown_HIDE_PAUSE_MENU"]
     156 [-]: NEWCLOSURE R36 P25
     157 [-]: MOVE R1 R12  
     158 [-]: MOVE R0 R25  
     159 [-]: SETGLOBAL R36 K29 ["PassiveFocused"]
     160 [-]: NEWCLOSURE R36 P26
     161 [-]: MOVE R1 R12  
     162 [-]: MOVE R0 R25  
     163 [-]: SETGLOBAL R36 K30 ["PassiveUnfocused"]
     164 [-]: DUPCLOSURE R36 K31 []
     165 [-]: SETGLOBAL R36 K32 ["PassivePressed"]
     166 [-]: DUPCLOSURE R36 K33 []
     167 [-]: SETGLOBAL R36 K34 ["PassiveReleased"]
     168 [-]: NEWCLOSURE R36 P29
     169 [-]: MOVE R1 R15  
     170 [-]: MOVE R1 R11  
     171 [-]: SETGLOBAL R36 K35 ["AbilityPressed"]
     172 [-]: NEWCLOSURE R36 P30
     173 [-]: MOVE R1 R11  
     174 [-]: SETGLOBAL R36 K36 ["AbilityFocused"]
     175 [-]: NEWCLOSURE R36 P31
     176 [-]: MOVE R1 R11  
     177 [-]: SETGLOBAL R36 K37 ["AbilityUnfocused"]
     178 [-]: DUPCLOSURE R36 K38 []
     179 [-]: SETGLOBAL R36 K39 ["SupportsThemes"]
     180 [-]: DUPCLOSURE R36 K40 []
     181 [-]: MOVE R0 R25  
     182 [-]: SETGLOBAL R36 K41 ["OnStyleChangedCallback"]
     183 [-]: NEWCLOSURE R36 P34
     184 [-]: MOVE R1 R13  
     185 [-]: SETGLOBAL R36 K42 ["OnGamepadTransition"]
     186 [-]: CLOSEUPVALS R4
     187 [-]: RETURN R0 0  


; Name:            
; Defined at line: 46
; #Upvalues:       5
; #Parameters:     2
; Is_vararg:       0
; Max Stack Size:  13

       0 [-]: GETUPVAL R3 0
       1 [-]: GETTABLEKS R2 R3 K0 [0x44537ADF]
       2 [-]: GETIMPORT R3 2 [nil]
       3 [-]: CALL R2 1 2  
       4 [-]: GETUPVAL R5 1
       5 [-]: FASTCALL1 62 R5 L0
       6 [-]: GETIMPORT R4 4 [nil]
       7 [-]: CALL R4 1 1  
L 0:   8 [-]: JUMPIF R4 L1 
       9 [-]: GETUPVAL R4 1
      10 [-]: MOVE R6 R0   
      11 [-]: MOVE R7 R1   
      12 [-]: NAMECALL R4 R4 K5 [0xFAA69527]
      13 [-]: CALL R4 3 0  
L 1:  14 [-]: GETIMPORT R4 2 [nil]
      15 [-]: LOADK R6 K6 ["Abilities.Underline"]
      16 [-]: LOADN R7 0   
      17 [-]: MINUS R9 R2  
      18 [-]: DIVK R8 R9 K7 [2]
      19 [-]: NAMECALL R4 R4 K8 [0x67BC869F]
      20 [-]: CALL R4 4 0  
      21 [-]: GETUPVAL R5 2
      22 [-]: GETTABLEKS R4 R5 K9 [0x00FA676F]
      23 [-]: GETIMPORT R5 2 [nil]
      24 [-]: LOADK R6 K6 ["Abilities.Underline"]
      25 [-]: MOVE R7 R2   
      26 [-]: CALL R4 3 0  
      27 [-]: GETUPVAL R5 3
      28 [-]: FASTCALL1 62 R5 L2
      29 [-]: GETIMPORT R4 4 [nil]
      30 [-]: CALL R4 1 1  
L 2:  31 [-]: JUMPIF R4 L3 
      32 [-]: GETUPVAL R4 3
      33 [-]: DUPCLOSURE R6 K10 []
      34 [-]: MOVE R2 R0   
      35 [-]: NAMECALL R4 R4 K11 [0xEA061E98]
      36 [-]: CALL R4 2 0  
      37 [-]: GETUPVAL R4 3
      38 [-]: NAMECALL R4 R4 K12 [0x4859E88D]
      39 [-]: CALL R4 1 0  
L 3:  40 [-]: GETUPVAL R5 4
      41 [-]: FASTCALL1 62 R5 L4
      42 [-]: GETIMPORT R4 4 [nil]
      43 [-]: CALL R4 1 1  
L 4:  44 [-]: JUMPIF R4 L5 
      45 [-]: GETUPVAL R5 0
      46 [-]: GETTABLEKS R4 R5 K13 [0x6D7E6810]
      47 [-]: GETIMPORT R5 2 [nil]
      48 [-]: DUPTABLE R6 16
      49 [-]: GETIMPORT R7 2 [nil]
      50 [-]: GETUPVAL R12 4
      51 [-]: GETTABLEKS R10 R12 K17 ["ClipName"]
      52 [-]: LOADK R11 K18 [".Icon"]
      53 [-]: CONCAT R9 R10 R11
      54 [-]: LOADN R10 2  
      55 [-]: NAMECALL R7 R7 K19 [0x91A24E4B]
      56 [-]: CALL R7 3 1  
      57 [-]: SETTABLEKS R7 R6 K14 ["x"]
      58 [-]: GETIMPORT R7 2 [nil]
      59 [-]: GETUPVAL R12 4
      60 [-]: GETTABLEKS R10 R12 K17 ["ClipName"]
      61 [-]: LOADK R11 K18 [".Icon"]
      62 [-]: CONCAT R9 R10 R11
      63 [-]: LOADN R10 3  
      64 [-]: NAMECALL R7 R7 K19 [0x91A24E4B]
      65 [-]: CALL R7 3 1  
      66 [-]: SETTABLEKS R7 R6 K15 ["y"]
      67 [-]: CALL R4 2 1  
      68 [-]: GETUPVAL R6 4
      69 [-]: GETTABLEKS R5 R6 K20 ["Rect"]
      70 [-]: GETTABLEKS R6 R4 K14 ["x"]
      71 [-]: SETTABLEKS R6 R5 K21 ["X"]
      72 [-]: GETUPVAL R6 4
      73 [-]: GETTABLEKS R5 R6 K20 ["Rect"]
      74 [-]: GETTABLEKS R6 R4 K15 ["y"]
      75 [-]: SETTABLEKS R6 R5 K22 ["Y"]
L 5:  76 [-]: RETURN R0 0  


; Name:            
; Defined at line: 82
; #Upvalues:       1
; #Parameters:     2
; Is_vararg:       0
; Max Stack Size:  5

       0 [-]: GETUPVAL R2 0
       1 [-]: MOVE R3 R0   
       2 [-]: MOVE R4 R1   
       3 [-]: CALL R2 2 0  
       4 [-]: RETURN R0 0  


; Name:            
; Defined at line: 86
; #Upvalues:       2
; #Parameters:     3
; Is_vararg:       0
; Max Stack Size:  11

       0 [-]: JUMPIF R1 L0 
       1 [-]: RETURN R0 0  
L 0:   2 [-]: JUMPXEQKNIL R2 L1 NOT
       3 [-]: LOADK R2 K0 ["#FFFFFF"]
L 1:   4 [-]: JUMPXEQKS R0 K1 L4 [""]
       5 [-]: LOADK R5 K2 ["%:"]
       6 [-]: LOADK R6 K1 [""]
       7 [-]: NAMECALL R3 R0 K3 [0x66EDF04F]
       8 [-]: CALL R3 3 1  
       9 [-]: MOVE R0 R3   
      10 [-]: GETUPVAL R4 0
      11 [-]: LOADK R5 K4 ["<font color=\"#999999\">"]
      12 [-]: MOVE R6 R0   
      13 [-]: GETUPVAL R8 1
      14 [-]: GETTABLEKS R7 R8 K5 [0x06D055F9]
      15 [-]: JUMPXEQKS R1 K1 L2 [""]
      16 [-]: LOADB R8 0 +1
L 2:  17 [-]: LOADB R8 1   
L 3:  18 [-]: LOADK R9 K6 ["</font>"]
      19 [-]: LOADK R10 K7 [": </font>"]
      20 [-]: CALL R7 3 1  
      21 [-]: CONCAT R3 R4 R7
      22 [-]: SETUPVAL R3 0
L 4:  23 [-]: GETUPVAL R4 0
      24 [-]: LOADK R5 K8 ["<font color=\""]
      25 [-]: MOVE R6 R2   
      26 [-]: LOADK R7 K9 ["\">"]
      27 [-]: MOVE R8 R1   
      28 [-]: LOADK R9 K10 ["<br></font>"]
      29 [-]: CONCAT R3 R4 R9
      30 [-]: SETUPVAL R3 0
      31 [-]: RETURN R0 0  


; Name:            
; Defined at line: 100
; #Upvalues:       1
; #Parameters:     5
; Is_vararg:       0
; Max Stack Size:  16

       0 [-]: MOVE R5 R4   
       1 [-]: JUMPIF R5 L0 
       2 [-]: NEWTABLE R5 0 0
L 0:   3 [-]: LOADB R6 1   
       4 [-]: SETTABLEKS R6 R5 K0 ["CustomEntry"]
       5 [-]: SETTABLEKS R0 R5 K1 ["ClipName"]
       6 [-]: ORK R6 R3 K2 [64]
       7 [-]: SETTABLEKS R6 R5 K3 ["IconSize"]
       8 [-]: LOADB R6 0   
       9 [-]: SETTABLEKS R6 R5 K4 ["Focused"]
      10 [-]: GETTABLEKS R6 R5 K5 ["Name"]
      11 [-]: JUMPIF R6 L1 
      12 [-]: GETIMPORT R6 8 [nil]
      13 [-]: GETIMPORT R7 10 [nil]
      14 [-]: MOVE R9 R1   
      15 [-]: LOADB R10 1  
      16 [-]: NAMECALL R7 R7 K11 [0x42B04007]
      17 [-]: CALL R7 3 -1 
      18 [-]: CALL R6 -1 1 
L 1:  19 [-]: SETTABLEKS R6 R5 K5 ["Name"]
      20 [-]: GETUPVAL R7 0
      21 [-]: GETTABLEKS R6 R7 K12 [0xFC3FED1F]
      22 [-]: GETIMPORT R7 10 [nil]
      23 [-]: MOVE R8 R5   
      24 [-]: GETIMPORT R9 10 [nil]
      25 [-]: MOVE R12 R0  
      26 [-]: LOADK R13 K13 [".Icon"]
      27 [-]: CONCAT R11 R12 R13
      28 [-]: LOADN R12 2  
      29 [-]: NAMECALL R9 R9 K14 [0x91A24E4B]
      30 [-]: CALL R9 3 1  
      31 [-]: GETIMPORT R10 10 [nil]
      32 [-]: MOVE R13 R0  
      33 [-]: LOADK R14 K13 [".Icon"]
      34 [-]: CONCAT R12 R13 R14
      35 [-]: LOADN R13 3  
      36 [-]: NAMECALL R10 R10 K14 [0x91A24E4B]
      37 [-]: CALL R10 3 1 
      38 [-]: LOADN R11 110
      39 [-]: LOADN R12 64 
      40 [-]: CALL R6 6 0  
      41 [-]: GETIMPORT R6 10 [nil]
      42 [-]: MOVE R8 R0   
      43 [-]: LOADN R9 11  
      44 [-]: LOADB R10 1  
      45 [-]: NAMECALL R6 R6 K15 [0xAADE900E]
      46 [-]: CALL R6 4 0  
      47 [-]: GETIMPORT R6 10 [nil]
      48 [-]: MOVE R8 R0   
      49 [-]: LOADK R9 K16 ["Icon"]
      50 [-]: LOADN R10 12 
      51 [-]: GETTABLEKS R11 R5 K3 ["IconSize"]
      52 [-]: NAMECALL R6 R6 K17 [0xF64B7262]
      53 [-]: CALL R6 5 0  
      54 [-]: GETIMPORT R6 10 [nil]
      55 [-]: MOVE R8 R0   
      56 [-]: LOADK R9 K16 ["Icon"]
      57 [-]: LOADN R10 13 
      58 [-]: GETTABLEKS R11 R5 K3 ["IconSize"]
      59 [-]: NAMECALL R6 R6 K17 [0xF64B7262]
      60 [-]: CALL R6 5 0  
      61 [-]: GETIMPORT R6 10 [nil]
      62 [-]: MOVE R8 R0   
      63 [-]: LOADK R9 K18 ["Label"]
      64 [-]: LOADN R10 29 
      65 [-]: GETIMPORT R11 8 [nil]
      66 [-]: GETIMPORT R12 10 [nil]
      67 [-]: MOVE R14 R1  
      68 [-]: LOADB R15 1  
      69 [-]: NAMECALL R12 R12 K11 [0x42B04007]
      70 [-]: CALL R12 3 -1
      71 [-]: CALL R11 -1 -1
      72 [-]: NAMECALL R6 R6 K19 [0xE261AA96]
      73 [-]: CALL R6 -1 0 
      74 [-]: GETIMPORT R6 10 [nil]
      75 [-]: MOVE R9 R0   
      76 [-]: LOADK R10 K13 [".Icon"]
      77 [-]: CONCAT R8 R9 R10
      78 [-]: MOVE R9 R2   
      79 [-]: NAMECALL R6 R6 K20 [0x1CB415C1]
      80 [-]: CALL R6 3 0  
      81 [-]: RETURN R5 1  


; Name:            
; Defined at line: 123
; #Upvalues:       5
; #Parameters:     1
; Is_vararg:       0
; Max Stack Size:  10

       0 [-]: GETUPVAL R1 0
       1 [-]: MOVE R3 R0   
       2 [-]: LOADB R4 0   
       3 [-]: LOADB R5 0   
       4 [-]: LOADB R6 0   
       5 [-]: LOADB R7 1   
       6 [-]: NAMECALL R1 R1 K0 [0x431E8984]
       7 [-]: CALL R1 6 0  
       8 [-]: GETUPVAL R5 0
       9 [-]: GETTABLEKS R4 R5 K2 ["mForcedHorizontalSeparation"]
      10 [-]: GETUPVAL R5 0
      11 [-]: NAMECALL R5 R5 K3 [0x5FBDDC1A]
      12 [-]: CALL R5 1 1  
      13 [-]: MUL R3 R4 R5 
      14 [-]: DIVK R2 R3 K1 [2]
      15 [-]: MINUS R1 R2  
      16 [-]: GETUPVAL R4 0
      17 [-]: GETTABLEKS R3 R4 K2 ["mForcedHorizontalSeparation"]
      18 [-]: DIVK R2 R3 K1 [2]
      19 [-]: ADD R1 R1 R2 
      20 [-]: GETIMPORT R2 5 [nil]
      21 [-]: GETUPVAL R5 0
      22 [-]: GETTABLEKS R4 R5 K6 ["mParentClipName"]
      23 [-]: LOADN R5 0   
      24 [-]: GETUPVAL R7 1
      25 [-]: GETTABLEKS R6 R7 K7 [0x74A11EC6]
      26 [-]: MOVE R7 R1   
      27 [-]: CALL R6 1 -1 
      28 [-]: NAMECALL R2 R2 K8 [0x67BC869F]
      29 [-]: CALL R2 -1 0 
      30 [-]: GETIMPORT R2 5 [nil]
      31 [-]: LOADK R4 K9 ["Abilities"]
      32 [-]: LOADN R5 11  
      33 [-]: LOADB R6 1   
      34 [-]: NAMECALL R2 R2 K10 [0xAADE900E]
      35 [-]: CALL R2 4 0  
      36 [-]: NAMECALL R2 R0 K11 [0xD175ECC5]
      37 [-]: CALL R2 1 1  
      38 [-]: NAMECALL R2 R2 K12 [0x6D604BA7]
      39 [-]: CALL R2 1 1  
      40 [-]: JUMPXEQKS R2 K13 L4 [""]
      41 [-]: GETIMPORT R3 15 [nil]
      42 [-]: LOADNIL R4   
      43 [-]: SETTABLEKS R4 R3 K16 ["PassiveInfo"]
      44 [-]: GETUPVAL R4 2
      45 [-]: FASTCALL1 62 R4 L0
      46 [-]: GETIMPORT R3 18 [nil]
      47 [-]: CALL R3 1 1  
L 0:  48 [-]: JUMPIFNOT R3 L1
      49 [-]: GETIMPORT R3 20 [nil]
      50 [-]: NAMECALL R3 R3 K21 [0x78298275]
      51 [-]: CALL R3 1 1  
      52 [-]: SETUPVAL R3 2
L 1:  53 [-]: GETUPVAL R4 2
      54 [-]: FASTCALL1 62 R4 L2
      55 [-]: GETIMPORT R3 18 [nil]
      56 [-]: CALL R3 1 1  
L 2:  57 [-]: JUMPIF R3 L3 
      58 [-]: GETUPVAL R3 2
      59 [-]: NAMECALL R5 R0 K22 [0xE4182CD4]
      60 [-]: CALL R5 1 1  
      61 [-]: GETIMPORT R6 24 [nil]
      62 [-]: LOADK R7 K25 ["GetPassiveInfo"]
      63 [-]: CALL R6 1 1  
      64 [-]: LOADB R7 0   
      65 [-]: NAMECALL R3 R3 K26 [0x2494B830]
      66 [-]: CALL R3 4 0  
L 3:  67 [-]: GETIMPORT R3 5 [nil]
      68 [-]: MOVE R5 R2   
      69 [-]: LOADB R6 1   
      70 [-]: GETIMPORT R7 27 [nil]
      71 [-]: NAMECALL R3 R3 K28 [0x42B04007]
      72 [-]: CALL R3 4 1  
      73 [-]: MOVE R2 R3   
      74 [-]: GETUPVAL R3 4
      75 [-]: LOADK R4 K29 ["Passive"]
      76 [-]: LOADK R5 K30 ["/Lotus/Language/Menu/Ability_Passive"]
      77 [-]: GETIMPORT R6 32 [nil]
      78 [-]: LOADN R7 56  
      79 [-]: DUPTABLE R8 34
      80 [-]: SETTABLEKS R2 R8 K33 ["LocalizedDesc"]
      81 [-]: CALL R3 5 1  
      82 [-]: SETUPVAL R3 3
      83 [-]: GETIMPORT R3 5 [nil]
      84 [-]: LOADK R5 K29 ["Passive"]
      85 [-]: LOADK R6 K35 ["PassiveFocused"]
      86 [-]: LOADK R7 K36 ["PassiveUnfocused"]
      87 [-]: LOADK R8 K37 ["PassiveReleased"]
      88 [-]: LOADK R9 K38 ["PassivePressed"]
      89 [-]: NAMECALL R3 R3 K39 [0x1E5B5CFE]
      90 [-]: CALL R3 6 0  
L 4:  91 [-]: RETURN R0 0  


; Name:            
; Defined at line: 146
; #Upvalues:       3
; #Parameters:     0
; Is_vararg:       0
; Max Stack Size:  16

       0 [-]: GETUPVAL R1 0
       1 [-]: GETTABLEKS R0 R1 K0 [0x5D10207D]
       2 [-]: LOADN R1 2   
       3 [-]: CALL R0 1 1  
       4 [-]: NAMECALL R1 R0 K1 [0xA5D5C8F6]
       5 [-]: CALL R1 1 1  
       6 [-]: GETUPVAL R3 0
       7 [-]: GETTABLEKS R2 R3 K0 [0x5D10207D]
       8 [-]: LOADN R3 6   
       9 [-]: LOADB R4 1   
      10 [-]: CALL R2 2 1  
      11 [-]: GETUPVAL R4 0
      12 [-]: GETTABLEKS R3 R4 K0 [0x5D10207D]
      13 [-]: LOADN R4 9   
      14 [-]: LOADB R5 1   
      15 [-]: CALL R3 2 1  
      16 [-]: GETUPVAL R5 0
      17 [-]: GETTABLEKS R4 R5 K0 [0x5D10207D]
      18 [-]: LOADN R5 10  
      19 [-]: LOADB R6 1   
      20 [-]: CALL R4 2 1  
      21 [-]: LOADB R5 0   
      22 [-]: GETUPVAL R6 1
      23 [-]: JUMPXEQKNIL R6 L0
      24 [-]: GETUPVAL R6 1
      25 [-]: GETTABLEKS R5 R6 K2 ["Focused"]
L 0:  26 [-]: JUMPIFNOT R5 L1
      27 [-]: MOVE R6 R4   
      28 [-]: JUMPIF R6 L2 
L 1:  29 [-]: MOVE R6 R3   
L 2:  30 [-]: GETIMPORT R7 4 [nil]
      31 [-]: LOADK R9 K5 ["Description.Label"]
      32 [-]: LOADN R10 36 
      33 [-]: MOVE R11 R2  
      34 [-]: NAMECALL R7 R7 K6 [0x67BC869F]
      35 [-]: CALL R7 4 0  
      36 [-]: GETIMPORT R7 4 [nil]
      37 [-]: LOADK R9 K7 ["Description.Backer"]
      38 [-]: LOADN R10 9  
      39 [-]: MOVE R11 R1  
      40 [-]: NAMECALL R7 R7 K6 [0x67BC869F]
      41 [-]: CALL R7 4 0  
      42 [-]: GETIMPORT R7 4 [nil]
      43 [-]: LOADK R9 K7 ["Description.Backer"]
      44 [-]: LOADN R10 10 
      45 [-]: LOADN R11 70 
      46 [-]: NAMECALL R7 R7 K6 [0x67BC869F]
      47 [-]: CALL R7 4 0  
      48 [-]: GETIMPORT R7 4 [nil]
      49 [-]: LOADK R9 K8 ["Passive.Icon"]
      50 [-]: LOADN R10 9  
      51 [-]: MOVE R11 R6  
      52 [-]: NAMECALL R7 R7 K6 [0x67BC869F]
      53 [-]: CALL R7 4 0  
      54 [-]: GETIMPORT R7 4 [nil]
      55 [-]: LOADK R9 K9 ["Passive.Label"]
      56 [-]: LOADN R10 9  
      57 [-]: MOVE R11 R6  
      58 [-]: NAMECALL R7 R7 K6 [0x67BC869F]
      59 [-]: CALL R7 4 0  
      60 [-]: GETIMPORT R7 4 [nil]
      61 [-]: LOADK R9 K10 ["Passive.Arrow"]
      62 [-]: LOADN R10 9  
      63 [-]: MOVE R11 R6  
      64 [-]: NAMECALL R7 R7 K6 [0x67BC869F]
      65 [-]: CALL R7 4 0  
      66 [-]: GETIMPORT R7 4 [nil]
      67 [-]: LOADK R9 K11 ["Passive.Backer"]
      68 [-]: LOADN R10 9  
      69 [-]: MOVE R11 R1  
      70 [-]: NAMECALL R7 R7 K6 [0x67BC869F]
      71 [-]: CALL R7 4 0  
      72 [-]: GETUPVAL R8 0
      73 [-]: GETTABLEKS R7 R8 K12 [0xAD9F60AA]
      74 [-]: CALL R7 0 1  
      75 [-]: GETIMPORT R8 4 [nil]
      76 [-]: LOADK R10 K13 ["Abilities.Underline"]
      77 [-]: LOADN R11 9  
      78 [-]: MOVE R12 R3  
      79 [-]: NAMECALL R8 R8 K6 [0x67BC869F]
      80 [-]: CALL R8 4 0  
      81 [-]: GETIMPORT R8 4 [nil]
      82 [-]: LOADK R10 K14 ["Abilities.Backer"]
      83 [-]: LOADN R11 9  
      84 [-]: MOVE R12 R1  
      85 [-]: NAMECALL R8 R8 K6 [0x67BC869F]
      86 [-]: CALL R8 4 0  
      87 [-]: GETIMPORT R8 4 [nil]
      88 [-]: LOADK R10 K14 ["Abilities.Backer"]
      89 [-]: LOADN R11 10 
      90 [-]: GETUPVAL R13 2
      91 [-]: GETTABLEKS R12 R13 K15 [0x06D055F9]
      92 [-]: MOVE R13 R7  
      93 [-]: LOADN R14 70 
      94 [-]: LOADN R15 100
      95 [-]: CALL R12 3 -1
      96 [-]: NAMECALL R8 R8 K6 [0x67BC869F]
      97 [-]: CALL R8 -1 0 
      98 [-]: GETIMPORT R8 4 [nil]
      99 [-]: LOADK R10 K14 ["Abilities.Backer"]
     100 [-]: LOADN R11 6  
     101 [-]: GETUPVAL R13 2
     102 [-]: GETTABLEKS R12 R13 K15 [0x06D055F9]
     103 [-]: MOVE R13 R7  
     104 [-]: LOADN R14 180
     105 [-]: LOADN R15 280
     106 [-]: CALL R12 3 -1
     107 [-]: NAMECALL R8 R8 K6 [0x67BC869F]
     108 [-]: CALL R8 -1 0 
     109 [-]: GETIMPORT R8 4 [nil]
     110 [-]: LOADK R10 K16 ["Abilities.Blurer"]
     111 [-]: LOADN R11 6  
     112 [-]: GETUPVAL R13 2
     113 [-]: GETTABLEKS R12 R13 K15 [0x06D055F9]
     114 [-]: MOVE R13 R7  
     115 [-]: LOADN R14 180
     116 [-]: LOADN R15 280
     117 [-]: CALL R12 3 -1
     118 [-]: NAMECALL R8 R8 K6 [0x67BC869F]
     119 [-]: CALL R8 -1 0 
     120 [-]: RETURN R0 0  


; Name:            
; Defined at line: 172
; #Upvalues:       3
; #Parameters:     1
; Is_vararg:       0
; Max Stack Size:  13

       0 [-]: NAMECALL R1 R0 K0 [0x9B4BBE31]
       1 [-]: CALL R1 1 1  
       2 [-]: FASTCALL1 62 R1 L0
       3 [-]: MOVE R3 R1   
       4 [-]: GETIMPORT R2 2 [nil]
       5 [-]: CALL R2 1 1  
L 0:   6 [-]: JUMPIFNOT R2 L1
       7 [-]: RETURN R0 0  
L 1:   8 [-]: GETUPVAL R2 0
       9 [-]: JUMPIFNOTEQ R1 R2 L2
      10 [-]: RETURN R0 0  
L 2:  11 [-]: SETUPVAL R1 0
      12 [-]: GETUPVAL R2 1
      13 [-]: LOADB R3 0   
      14 [-]: SETTABLEKS R3 R2 K3 ["mSyncAvatars"]
      15 [-]: DUPCLOSURE R2 K4 []
      16 [-]: NEWCLOSURE R3 P1
      17 [-]: MOVE R2 R1   
      18 [-]: MOVE R2 R0   
      19 [-]: GETUPVAL R4 2
      20 [-]: JUMPIF R4 L3 
      21 [-]: GETIMPORT R4 6 [nil]
      22 [-]: GETIMPORT R5 8 [nil]
      23 [-]: LOADK R6 K9 ["_root"]
      24 [-]: LOADN R7 8   
      25 [-]: NEWTABLE R8 0 1
      26 [-]: MOVE R9 R2   
      27 [-]: SETLIST R8 R9 1 [1]
      28 [-]: NEWTABLE R9 0 1
      29 [-]: LOADN R10 1  
      30 [-]: SETLIST R9 R10 1 [1]
      31 [-]: LOADK R10 K10 [0.5]
      32 [-]: LOADN R11 0  
      33 [-]: MOVE R12 R3  
      34 [-]: CALL R4 8 0  
      35 [-]: JUMP L4
     
L 3:  36 [-]: GETUPVAL R4 1
      37 [-]: NAMECALL R4 R4 K11 [0xCFD9CD76]
      38 [-]: CALL R4 1 1  
      39 [-]: JUMPIFNOT R4 L4
      40 [-]: GETUPVAL R4 1
      41 [-]: NAMECALL R4 R4 K12 [0xEF25E404]
      42 [-]: CALL R4 1 0  
      43 [-]: GETUPVAL R4 1
      44 [-]: GETUPVAL R6 0
      45 [-]: NAMECALL R4 R4 K13 [0x522B2215]
      46 [-]: CALL R4 2 0  
L 4:  47 [-]: LOADB R4 1   
      48 [-]: SETUPVAL R4 2
      49 [-]: RETURN R0 0  


; Name:            
; Defined at line: 210
; #Upvalues:       1
; #Parameters:     0
; Is_vararg:       0
; Max Stack Size:  4

       0 [-]: GETIMPORT R1 1 [nil]
       1 [-]: FASTCALL1 62 R1 L0
       2 [-]: GETIMPORT R0 3 [nil]
       3 [-]: CALL R0 1 1  
L 0:   4 [-]: JUMPIF R0 L1 
       5 [-]: GETIMPORT R0 1 [nil]
       6 [-]: GETIMPORT R2 5 [nil]
       7 [-]: NAMECALL R0 R0 K6 [0xF2DEAF69]
       8 [-]: CALL R0 2 1  
       9 [-]: JUMPIFNOT R0 L1
      10 [-]: GETIMPORT R0 1 [nil]
      11 [-]: GETUPVAL R3 0
      12 [-]: GETTABLEKS R2 R3 K7 ["NV_CURRENT_MOOD"]
      13 [-]: LOADN R3 0   
      14 [-]: NAMECALL R0 R0 K8 [0x0EB34C69]
      15 [-]: CALL R0 3 -1 
      16 [-]: RETURN R0 -1 
L 1:  17 [-]: RETURN R0 0  


; Name:            
; Defined at line: 217
; #Upvalues:       9
; #Parameters:     0
; Is_vararg:       0
; Max Stack Size:  17

       0 [-]: GETUPVAL R0 0
       1 [-]: JUMPIF R0 L0 
       2 [-]: GETUPVAL R0 1
       3 [-]: JUMPIFNOT R0 L1
L 0:   4 [-]: RETURN R0 0  
L 1:   5 [-]: GETUPVAL R1 2
       6 [-]: GETTABLEKS R0 R1 K0 [0xF76783E5]
       7 [-]: GETIMPORT R1 2 [nil]
       8 [-]: LOADK R2 K3 ["ConfirmBtn"]
       9 [-]: GETIMPORT R3 5 [nil]
      10 [-]: GETUPVAL R6 3
      11 [-]: GETTABLEKS R5 R6 K7 ["mWidth"]
      12 [-]: DIVK R4 R5 K6 [2]
      13 [-]: GETUPVAL R7 3
      14 [-]: GETTABLEKS R6 R7 K8 ["mHeight"]
      15 [-]: DIVK R5 R6 K6 [2]
      16 [-]: GETIMPORT R6 10 [nil]
      17 [-]: CALL R0 6 0  
      18 [-]: GETIMPORT R2 12 [nil]
      19 [-]: FASTCALL1 62 R2 L2
      20 [-]: GETIMPORT R1 14 [nil]
      21 [-]: CALL R1 1 1  
L 2:  22 [-]: JUMPIF R1 L3 
      23 [-]: GETIMPORT R1 12 [nil]
      24 [-]: GETIMPORT R3 16 [nil]
      25 [-]: NAMECALL R1 R1 K17 [0xF2DEAF69]
      26 [-]: CALL R1 2 1  
      27 [-]: JUMPIFNOT R1 L3
      28 [-]: GETIMPORT R0 12 [nil]
      29 [-]: GETUPVAL R3 4
      30 [-]: GETTABLEKS R2 R3 K18 ["NV_CURRENT_MOOD"]
      31 [-]: LOADN R3 0   
      32 [-]: NAMECALL R0 R0 K19 [0x0EB34C69]
      33 [-]: CALL R0 3 1  
      34 [-]: JUMP L4
     
L 3:  35 [-]: LOADNIL R0   
L 4:  36 [-]: FASTCALL1 62 R0 L5
      37 [-]: MOVE R2 R0   
      38 [-]: GETIMPORT R1 14 [nil]
      39 [-]: CALL R1 1 1  
L 5:  40 [-]: JUMPIF R1 L9 
      41 [-]: GETUPVAL R2 2
      42 [-]: GETTABLEKS R1 R2 K20 [0x659D451F]
      43 [-]: GETIMPORT R2 22 [nil]
      44 [-]: CALL R1 1 0  
      45 [-]: GETUPVAL R2 5
      46 [-]: FASTCALL1 62 R2 L6
      47 [-]: GETIMPORT R1 14 [nil]
      48 [-]: CALL R1 1 1  
L 6:  49 [-]: JUMPIF R1 L7 
      50 [-]: GETUPVAL R1 5
      51 [-]: LOADB R3 0   
      52 [-]: NAMECALL R1 R1 K23 [0x6CF1E476]
      53 [-]: CALL R1 2 0  
L 7:  54 [-]: GETUPVAL R2 6
      55 [-]: FASTCALL1 62 R2 L8
      56 [-]: GETIMPORT R1 14 [nil]
      57 [-]: CALL R1 1 1  
L 8:  58 [-]: JUMPIF R1 L10
      59 [-]: GETUPVAL R1 6
      60 [-]: LOADB R3 0   
      61 [-]: NAMECALL R1 R1 K23 [0x6CF1E476]
      62 [-]: CALL R1 2 0  
      63 [-]: JUMP L10
    
L 9:  64 [-]: GETUPVAL R2 2
      65 [-]: GETTABLEKS R1 R2 K20 [0x659D451F]
      66 [-]: GETIMPORT R3 25 [nil]
      67 [-]: GETTABLEKS R2 R3 K26 ["UISound_Purchase"]
      68 [-]: CALL R1 1 0  
L10:  69 [-]: GETGLOBAL R2 K27 [0x946FEA28]
      70 [-]: GETUPVAL R3 7
      71 [-]: GETTABLE R1 R2 R3
      72 [-]: LOADB R2 1   
      73 [-]: SETUPVAL R2 0
      74 [-]: GETIMPORT R2 29 [nil]
      75 [-]: LOADN R4 0   
      76 [-]: NAMECALL R2 R2 K30 [0x3F3AE64C]
      77 [-]: CALL R2 2 1  
      78 [-]: NAMECALL R3 R2 K31 [0x80563238]
      79 [-]: CALL R3 1 1  
      80 [-]: NAMECALL R4 R3 K32 [0x5F914391]
      81 [-]: CALL R4 1 0  
      82 [-]: GETIMPORT R5 34 [nil]
      83 [-]: NAMECALL R5 R5 K35 [0x8B5B1F58]
      84 [-]: CALL R5 1 1  
      85 [-]: GETTABLEN R4 R5 1
      86 [-]: GETIMPORT R5 38 [nil]
      87 [-]: JUMPIFNOT R5 L11
      88 [-]: GETIMPORT R5 38 [nil]
      89 [-]: MOVE R6 R1   
      90 [-]: CALL R5 1 0  
      91 [-]: JUMP L12
    
L11:  92 [-]: MOVE R7 R1   
      93 [-]: LOADB R8 1   
      94 [-]: NAMECALL R5 R4 K39 [0x511D26B8]
      95 [-]: CALL R5 3 1  
      96 [-]: LOADN R8 0   
      97 [-]: NAMECALL R6 R5 K40 [0xE227A53E]
      98 [-]: CALL R6 2 0  
L12:  99 [-]: DUPCLOSURE R5 K41 []
     100 [-]: MOVE R2 R8   
     101 [-]: GETIMPORT R6 43 [nil]
     102 [-]: GETIMPORT R7 2 [nil]
     103 [-]: LOADK R8 K3 ["ConfirmBtn"]
     104 [-]: LOADN R9 8   
     105 [-]: NEWTABLE R10 0 1
     106 [-]: LOADN R11 10 
     107 [-]: SETLIST R10 R11 1 [1]
     108 [-]: NEWTABLE R11 0 1
     109 [-]: LOADN R12 0  
     110 [-]: SETLIST R11 R12 1 [1]
     111 [-]: LOADK R12 K44 [0.20000000000000001]
     112 [-]: CALL R6 6 0  
     113 [-]: DUPCLOSURE R6 K45 []
     114 [-]: DUPCLOSURE R7 K46 []
     115 [-]: MOVE R0 R6   
     116 [-]: LOADB R8 1   
     117 [-]: SETUPVAL R8 1
     118 [-]: GETIMPORT R8 43 [nil]
     119 [-]: GETIMPORT R9 2 [nil]
     120 [-]: LOADK R10 K47 ["_root"]
     121 [-]: LOADN R11 0  
     122 [-]: NEWTABLE R12 0 1
     123 [-]: MOVE R13 R5  
     124 [-]: SETLIST R12 R13 1 [1]
     125 [-]: NEWTABLE R13 0 1
     126 [-]: LOADN R14 1  
     127 [-]: SETLIST R13 R14 1 [1]
     128 [-]: LOADN R14 1  
     129 [-]: LOADN R15 0  
     130 [-]: MOVE R16 R7  
     131 [-]: CALL R8 8 0  
     132 [-]: RETURN R0 0  


; Name:            
; Defined at line: 291
; #Upvalues:       1
; #Parameters:     0
; Is_vararg:       0
; Max Stack Size:  1

       0 [-]: GETUPVAL R0 0
       1 [-]: CALL R0 0 0  
       2 [-]: RETURN R0 0  


; Name:            
; Defined at line: 296
; #Upvalues:       2
; #Parameters:     0
; Is_vararg:       0
; Max Stack Size:  4

       0 [-]: GETUPVAL R0 0
       1 [-]: GETGLOBAL R2 K0 [0x946FEA28]
       2 [-]: GETUPVAL R3 1
       3 [-]: GETTABLE R1 R2 R3
       4 [-]: CALL R0 1 0  
       5 [-]: RETURN R0 0  


; Name:            
; Defined at line: 300
; #Upvalues:       3
; #Parameters:     1
; Is_vararg:       0
; Max Stack Size:  5

       0 [-]: JUMPXEQKNIL R0 L0
       1 [-]: GETUPVAL R1 0
       2 [-]: JUMPIFNOTEQ R1 R0 L1
L 0:   3 [-]: RETURN R0 0  
L 1:   4 [-]: GETUPVAL R2 1
       5 [-]: GETUPVAL R3 0
       6 [-]: GETTABLE R1 R2 R3
       7 [-]: LOADB R2 0   
       8 [-]: SETTABLEKS R2 R1 K0 ["mSelected"]
       9 [-]: GETUPVAL R2 1
      10 [-]: GETUPVAL R3 0
      11 [-]: GETTABLE R1 R2 R3
      12 [-]: LOADB R2 0   
      13 [-]: SETTABLEKS R2 R1 K1 ["mFocused"]
      14 [-]: GETUPVAL R2 1
      15 [-]: GETUPVAL R3 0
      16 [-]: GETTABLE R1 R2 R3
      17 [-]: NAMECALL R1 R1 K2 [0x087CBD3F]
      18 [-]: CALL R1 1 0  
      19 [-]: GETUPVAL R2 1
      20 [-]: GETUPVAL R3 0
      21 [-]: GETTABLE R1 R2 R3
      22 [-]: NAMECALL R1 R1 K3 [0xB678E4BD]
      23 [-]: CALL R1 1 0  
      24 [-]: SETUPVAL R0 0
      25 [-]: GETUPVAL R2 1
      26 [-]: GETUPVAL R3 0
      27 [-]: GETTABLE R1 R2 R3
      28 [-]: LOADB R2 1   
      29 [-]: SETTABLEKS R2 R1 K0 ["mSelected"]
      30 [-]: GETUPVAL R2 1
      31 [-]: GETUPVAL R3 0
      32 [-]: GETTABLE R1 R2 R3
      33 [-]: NAMECALL R1 R1 K2 [0x087CBD3F]
      34 [-]: CALL R1 1 0  
      35 [-]: GETUPVAL R1 2
      36 [-]: GETGLOBAL R3 K4 [0x946FEA28]
      37 [-]: GETUPVAL R4 0
      38 [-]: GETTABLE R2 R3 R4
      39 [-]: CALL R1 1 0  
      40 [-]: RETURN R0 0  


; Name:            
; Defined at line: 316
; #Upvalues:       2
; #Parameters:     1
; Is_vararg:       0
; Max Stack Size:  4

       0 [-]: GETUPVAL R2 0
       1 [-]: GETTABLEKS R1 R2 K0 [0x659D451F]
       2 [-]: GETIMPORT R3 2 [nil]
       3 [-]: GETTABLEKS R2 R3 K3 ["UISound_Select"]
       4 [-]: CALL R1 1 0  
       5 [-]: GETUPVAL R1 1
       6 [-]: GETTABLEKS R2 R0 K4 ["Id"]
       7 [-]: CALL R1 1 0  
       8 [-]: RETURN R0 0  


; Name:            
; Defined at line: 321
; #Upvalues:       2
; #Parameters:     0
; Is_vararg:       0
; Max Stack Size:  14

       0 [-]: GETIMPORT R0 1 [nil]
       1 [-]: LOADK R1 K2 ["Lotus.Interface.Components.ThemedButton"]
       2 [-]: CALL R0 1 1  
       3 [-]: LOADN R1 0   
       4 [-]: LOADN R4 1   
       5 [-]: GETGLOBAL R5 K3 [0x946FEA28]
       6 [-]: LENGTH R2 R5 
       7 [-]: LOADN R3 1   
       8 [-]: FORNPREP R2 L4
L 0:   9 [-]: LOADK R6 K4 ["SuitList.Button"]
      10 [-]: MOVE R7 R4   
      11 [-]: CONCAT R5 R6 R7
      12 [-]: GETIMPORT R6 6 [nil]
      13 [-]: MOVE R8 R5   
      14 [-]: NAMECALL R6 R6 K7 [0xA7EC3E8A]
      15 [-]: CALL R6 2 1  
      16 [-]: JUMPIF R6 L1 
      17 [-]: GETIMPORT R6 9 [nil]
      18 [-]: GETIMPORT R7 6 [nil]
      19 [-]: LOADK R9 K4 ["SuitList.Button"]
      20 [-]: LOADK R10 K10 [".duplicateMovieClip"]
      21 [-]: CONCAT R8 R9 R10
      22 [-]: LOADK R10 K11 ["Button"]
      23 [-]: MOVE R11 R4  
      24 [-]: CONCAT R9 R10 R11
      25 [-]: LOADN R11 1000
      26 [-]: ADD R10 R11 R4
      27 [-]: CALL R6 4 0  
L 1:  28 [-]: GETIMPORT R6 6 [nil]
      29 [-]: MOVE R8 R5   
      30 [-]: LOADN R9 1   
      31 [-]: MOVE R10 R1  
      32 [-]: NAMECALL R6 R6 K12 [0x67BC869F]
      33 [-]: CALL R6 4 0  
      34 [-]: GETTABLEKS R6 R0 K13 [0xAE6791BA]
      35 [-]: GETIMPORT R7 6 [nil]
      36 [-]: MOVE R8 R5   
      37 [-]: GETGLOBAL R10 K3 [0x946FEA28]
      38 [-]: GETTABLE R9 R10 R4
      39 [-]: NAMECALL R9 R9 K14 [0xD3A9D01F]
      40 [-]: CALL R9 1 1  
      41 [-]: NAMECALL R9 R9 K15 [0x6D604BA7]
      42 [-]: CALL R9 1 1  
      43 [-]: LOADK R10 K16 ["PreviewSuit"]
      44 [-]: LOADNIL R11  
      45 [-]: LOADNIL R12  
      46 [-]: LOADB R13 1  
      47 [-]: CALL R6 7 1  
      48 [-]: GETTABLEKS R7 R6 K17 ["SetFocus"]
      49 [-]: SETTABLEKS R7 R6 K18 ["BaseSetFocus"]
      50 [-]: DUPCLOSURE R7 K19 []
      51 [-]: SETTABLEKS R7 R6 K17 ["SetFocus"]
      52 [-]: NAMECALL R7 R6 K20 [0x4E86C602]
      53 [-]: CALL R7 1 0  
      54 [-]: LOADN R9 250 
      55 [-]: NAMECALL R7 R6 K21 [0x8D77B2B2]
      56 [-]: CALL R7 2 0  
      57 [-]: GETTABLEKS R8 R6 K23 ["mHeight"]
      58 [-]: ADD R7 R1 R8 
      59 [-]: ADDK R1 R7 K22 [10]
      60 [-]: LOADN R7 90  
      61 [-]: SETTABLEKS R7 R6 K24 ["mInnerAlpha"]
      62 [-]: SETTABLEKS R4 R6 K25 ["Id"]
      63 [-]: LOADB R9 1   
      64 [-]: NAMECALL R7 R6 K26 [0x46610C50]
      65 [-]: CALL R7 2 0  
      66 [-]: NAMECALL R7 R6 K27 [0x71E9AC81]
      67 [-]: CALL R7 1 0  
      68 [-]: GETUPVAL R7 0
      69 [-]: JUMPIFNOTEQ R7 R4 L2
      70 [-]: LOADB R7 1   
      71 [-]: SETTABLEKS R7 R6 K28 ["mSelected"]
      72 [-]: LOADB R9 1   
      73 [-]: NAMECALL R7 R6 K29 [0x0417AD4A]
      74 [-]: CALL R7 2 0  
L 2:  75 [-]: GETUPVAL R8 1
      76 [-]: FASTCALL2 52 R8 R6 L3
      77 [-]: MOVE R9 R6   
      78 [-]: GETIMPORT R7 32 [nil]
      79 [-]: CALL R7 2 0  
L 3:  80 [-]: FORNLOOP R2 L0
L 4:  81 [-]: RETURN R0 0  


; Name:            
; Defined at line: 360
; #Upvalues:       1
; #Parameters:     0
; Is_vararg:       0
; Max Stack Size:  4

       0 [-]: GETIMPORT R0 1 [nil]
       1 [-]: LOADK R1 K2 ["Lotus.Interface.Components.AbilityList"]
       2 [-]: CALL R0 1 1  
       3 [-]: GETTABLEKS R1 R0 K3 [0xAE6791BA]
       4 [-]: GETIMPORT R2 5 [nil]
       5 [-]: LOADK R3 K6 ["Abilities.AbilityList"]
       6 [-]: CALL R1 2 1  
       7 [-]: SETUPVAL R1 0
       8 [-]: GETUPVAL R1 0
       9 [-]: LOADB R2 0   
      10 [-]: SETTABLEKS R2 R1 K7 ["mShowRank"]
      11 [-]: GETUPVAL R1 0
      12 [-]: LOADB R2 0   
      13 [-]: SETTABLEKS R2 R1 K8 ["mShowRankUp"]
      14 [-]: GETUPVAL R1 0
      15 [-]: NAMECALL R1 R1 K9 [0x4859E88D]
      16 [-]: CALL R1 1 0  
      17 [-]: RETURN R0 0  


; Name:            
; Defined at line: 368
; #Upvalues:       14
; #Parameters:     0
; Is_vararg:       0
; Max Stack Size:  17

       0 [-]: GETIMPORT R0 1 [nil]
       1 [-]: LOADK R1 K2 ["Lotus.Interface.Libs.DioramaLoader"]
       2 [-]: CALL R0 1 1  
       3 [-]: GETTABLEKS R1 R0 K3 [0xBEC1F4EE]
       4 [-]: GETIMPORT R2 5 [nil]
       5 [-]: CALL R1 1 1  
       6 [-]: SETUPVAL R1 0
       7 [-]: GETIMPORT R1 1 [nil]
       8 [-]: LOADK R2 K6 ["Lotus.Interface.Components.ThemedSpinner"]
       9 [-]: CALL R1 1 1  
      10 [-]: GETTABLEKS R2 R1 K7 [0xAE6791BA]
      11 [-]: GETIMPORT R3 5 [nil]
      12 [-]: LOADK R4 K8 ["Spinner"]
      13 [-]: CALL R2 2 1  
      14 [-]: SETUPVAL R2 1
      15 [-]: GETIMPORT R2 10 [nil]
      16 [-]: NAMECALL R2 R2 K11 [0x78298275]
      17 [-]: CALL R2 1 1  
      18 [-]: SETUPVAL R2 2
      19 [-]: GETIMPORT R4 13 [nil]
      20 [-]: FASTCALL1 62 R4 L0
      21 [-]: GETIMPORT R3 15 [nil]
      22 [-]: CALL R3 1 1  
L 0:  23 [-]: JUMPIF R3 L1 
      24 [-]: GETIMPORT R3 13 [nil]
      25 [-]: GETIMPORT R5 17 [nil]
      26 [-]: NAMECALL R3 R3 K18 [0xF2DEAF69]
      27 [-]: CALL R3 2 1  
      28 [-]: JUMPIFNOT R3 L1
      29 [-]: GETIMPORT R2 13 [nil]
      30 [-]: GETUPVAL R5 3
      31 [-]: GETTABLEKS R4 R5 K19 ["NV_CURRENT_MOOD"]
      32 [-]: LOADN R5 0   
      33 [-]: NAMECALL R2 R2 K20 [0x0EB34C69]
      34 [-]: CALL R2 3 1  
      35 [-]: JUMP L2
     
L 1:  36 [-]: LOADNIL R2   
L 2:  37 [-]: FASTCALL1 62 R2 L3
      38 [-]: MOVE R4 R2   
      39 [-]: GETIMPORT R3 15 [nil]
      40 [-]: CALL R3 1 1  
L 3:  41 [-]: JUMPIF R3 L4 
      42 [-]: GETUPVAL R4 4
      43 [-]: GETTABLEKS R3 R4 K21 [0x659D451F]
      44 [-]: GETIMPORT R4 23 [nil]
      45 [-]: CALL R3 1 0  
L 4:  46 [-]: GETIMPORT R3 5 [nil]
      47 [-]: LOADK R5 K24 ["Passive"]
      48 [-]: LOADN R6 11  
      49 [-]: LOADB R7 0   
      50 [-]: NAMECALL R3 R3 K25 [0xAADE900E]
      51 [-]: CALL R3 4 0  
      52 [-]: GETIMPORT R3 5 [nil]
      53 [-]: LOADK R5 K26 ["Abilities"]
      54 [-]: LOADN R6 11  
      55 [-]: LOADB R7 0   
      56 [-]: NAMECALL R3 R3 K25 [0xAADE900E]
      57 [-]: CALL R3 4 0  
      58 [-]: GETIMPORT R3 5 [nil]
      59 [-]: LOADK R5 K27 ["SuitList.Button"]
      60 [-]: LOADN R6 11  
      61 [-]: LOADB R7 0   
      62 [-]: NAMECALL R3 R3 K25 [0xAADE900E]
      63 [-]: CALL R3 4 0  
      64 [-]: GETIMPORT R3 29 [nil]
      65 [-]: NAMECALL R3 R3 K30 [0xB21930E8]
      66 [-]: CALL R3 1 0  
      67 [-]: GETUPVAL R3 5
      68 [-]: GETGLOBAL R5 K31 [0x946FEA28]
      69 [-]: GETUPVAL R6 6
      70 [-]: GETTABLE R4 R5 R6
      71 [-]: CALL R3 1 0  
      72 [-]: GETIMPORT R3 5 [nil]
      73 [-]: LOADN R5 0   
      74 [-]: NAMECALL R3 R3 K32 [0xC6A10AB1]
      75 [-]: CALL R3 2 0  
      76 [-]: GETIMPORT R3 5 [nil]
      77 [-]: LOADN R5 1   
      78 [-]: NAMECALL R3 R3 K33 [0x58BEC6D6]
      79 [-]: CALL R3 2 0  
      80 [-]: GETIMPORT R3 5 [nil]
      81 [-]: LOADK R5 K34 ["ConfirmBtn"]
      82 [-]: LOADN R6 0   
      83 [-]: LOADN R7 1514
      84 [-]: NAMECALL R3 R3 K35 [0x67BC869F]
      85 [-]: CALL R3 4 0  
      86 [-]: GETIMPORT R3 1 [nil]
      87 [-]: LOADK R4 K36 ["Lotus.Interface.Components.ThemedButton"]
      88 [-]: CALL R3 1 1  
      89 [-]: GETTABLEKS R4 R3 K7 [0xAE6791BA]
      90 [-]: GETIMPORT R5 5 [nil]
      91 [-]: LOADK R6 K34 ["ConfirmBtn"]
      92 [-]: LOADK R7 K37 ["/Lotus/Language/Menu/Global_Confirm"]
      93 [-]: LOADK R8 K38 ["Confirm"]
      94 [-]: LOADK R9 K39 ["<MENU_GENERIC1>"]
      95 [-]: LOADNIL R10  
      96 [-]: LOADB R11 1  
      97 [-]: CALL R4 7 1  
      98 [-]: SETUPVAL R4 7
      99 [-]: GETUPVAL R4 7
     100 [-]: NAMECALL R4 R4 K40 [0x4E86C602]
     101 [-]: CALL R4 1 0  
     102 [-]: GETUPVAL R4 7
     103 [-]: LOADN R5 100 
     104 [-]: SETTABLEKS R5 R4 K41 ["mInnerAlpha"]
     105 [-]: GETUPVAL R4 7
     106 [-]: GETUPVAL R7 4
     107 [-]: GETTABLEKS R6 R7 K42 ["RIGHT_ALIGNED"]
     108 [-]: NAMECALL R4 R4 K43 [0x240F1807]
     109 [-]: CALL R4 2 0  
     110 [-]: GETUPVAL R4 7
     111 [-]: LOADB R6 1   
     112 [-]: NAMECALL R4 R4 K44 [0x46610C50]
     113 [-]: CALL R4 2 0  
     114 [-]: GETUPVAL R4 7
     115 [-]: NAMECALL R4 R4 K45 [0x71E9AC81]
     116 [-]: CALL R4 1 0  
     117 [-]: GETUPVAL R4 8
     118 [-]: CALL R4 0 0  
     119 [-]: GETIMPORT R4 1 [nil]
     120 [-]: LOADK R5 K46 ["Lotus.Interface.Components.AbilityList"]
     121 [-]: CALL R4 1 1  
     122 [-]: GETTABLEKS R5 R4 K7 [0xAE6791BA]
     123 [-]: GETIMPORT R6 5 [nil]
     124 [-]: LOADK R7 K47 ["Abilities.AbilityList"]
     125 [-]: CALL R5 2 1  
     126 [-]: SETUPVAL R5 9
     127 [-]: GETUPVAL R5 9
     128 [-]: LOADB R6 0   
     129 [-]: SETTABLEKS R6 R5 K48 ["mShowRank"]
     130 [-]: GETUPVAL R5 9
     131 [-]: LOADB R6 0   
     132 [-]: SETTABLEKS R6 R5 K49 ["mShowRankUp"]
     133 [-]: GETUPVAL R5 9
     134 [-]: NAMECALL R5 R5 K50 [0x4859E88D]
     135 [-]: CALL R5 1 0  
     136 [-]: GETIMPORT R4 1 [nil]
     137 [-]: LOADK R5 K51 ["EE.Interface.AnchorMgr"]
     138 [-]: CALL R4 1 1  
     139 [-]: GETTABLEKS R5 R4 K7 [0xAE6791BA]
     140 [-]: GETIMPORT R6 5 [nil]
     141 [-]: CALL R5 1 1  
     142 [-]: SETUPVAL R5 10
     143 [-]: GETUPVAL R5 10
     144 [-]: GETIMPORT R7 5 [nil]
     145 [-]: LOADK R8 K24 ["Passive"]
     146 [-]: NEWTABLE R9 0 2
     147 [-]: GETUPVAL R11 10
     148 [-]: GETTABLEKS R10 R11 K52 ["ANCHOR_H_LEFT"]
     149 [-]: GETUPVAL R12 10
     150 [-]: GETTABLEKS R11 R12 K53 ["ANCHOR_V_BOTTOM"]
     151 [-]: SETLIST R9 R10 2 [1]
     152 [-]: NAMECALL R5 R5 K54 [0x20FF29F7]
     153 [-]: CALL R5 4 0  
     154 [-]: GETUPVAL R5 10
     155 [-]: GETIMPORT R7 5 [nil]
     156 [-]: LOADK R8 K26 ["Abilities"]
     157 [-]: NEWTABLE R9 0 2
     158 [-]: GETUPVAL R11 10
     159 [-]: GETTABLEKS R10 R11 K55 ["ANCHOR_H_CENTRE"]
     160 [-]: GETUPVAL R12 10
     161 [-]: GETTABLEKS R11 R12 K53 ["ANCHOR_V_BOTTOM"]
     162 [-]: SETLIST R9 R10 2 [1]
     163 [-]: NAMECALL R5 R5 K54 [0x20FF29F7]
     164 [-]: CALL R5 4 0  
     165 [-]: GETUPVAL R5 10
     166 [-]: GETIMPORT R7 5 [nil]
     167 [-]: LOADK R8 K8 ["Spinner"]
     168 [-]: NEWTABLE R9 0 2
     169 [-]: GETUPVAL R11 10
     170 [-]: GETTABLEKS R10 R11 K56 ["ANCHOR_H_RIGHT"]
     171 [-]: GETUPVAL R12 10
     172 [-]: GETTABLEKS R11 R12 K57 ["ANCHOR_V_TOP"]
     173 [-]: SETLIST R9 R10 2 [1]
     174 [-]: NAMECALL R5 R5 K54 [0x20FF29F7]
     175 [-]: CALL R5 4 0  
     176 [-]: GETUPVAL R5 10
     177 [-]: GETIMPORT R7 5 [nil]
     178 [-]: LOADK R8 K58 ["SuitList"]
     179 [-]: NEWTABLE R9 0 2
     180 [-]: GETUPVAL R11 10
     181 [-]: GETTABLEKS R10 R11 K52 ["ANCHOR_H_LEFT"]
     182 [-]: GETUPVAL R12 10
     183 [-]: GETTABLEKS R11 R12 K57 ["ANCHOR_V_TOP"]
     184 [-]: SETLIST R9 R10 2 [1]
     185 [-]: NAMECALL R5 R5 K54 [0x20FF29F7]
     186 [-]: CALL R5 4 0  
     187 [-]: GETUPVAL R5 10
     188 [-]: GETIMPORT R7 5 [nil]
     189 [-]: LOADK R8 K59 ["Description"]
     190 [-]: NEWTABLE R9 0 2
     191 [-]: GETUPVAL R11 10
     192 [-]: GETTABLEKS R10 R11 K56 ["ANCHOR_H_RIGHT"]
     193 [-]: GETUPVAL R12 10
     194 [-]: GETTABLEKS R11 R12 K57 ["ANCHOR_V_TOP"]
     195 [-]: SETLIST R9 R10 2 [1]
     196 [-]: NAMECALL R5 R5 K54 [0x20FF29F7]
     197 [-]: CALL R5 4 0  
     198 [-]: GETUPVAL R5 10
     199 [-]: GETIMPORT R7 5 [nil]
     200 [-]: LOADK R8 K34 ["ConfirmBtn"]
     201 [-]: NEWTABLE R9 0 2
     202 [-]: GETUPVAL R11 10
     203 [-]: GETTABLEKS R10 R11 K56 ["ANCHOR_H_RIGHT"]
     204 [-]: GETUPVAL R12 10
     205 [-]: GETTABLEKS R11 R12 K53 ["ANCHOR_V_BOTTOM"]
     206 [-]: SETLIST R9 R10 2 [1]
     207 [-]: NAMECALL R5 R5 K54 [0x20FF29F7]
     208 [-]: CALL R5 4 0  
     209 [-]: GETUPVAL R5 11
     210 [-]: CALL R5 0 0  
     211 [-]: GETUPVAL R5 12
     212 [-]: GETIMPORT R6 5 [nil]
     213 [-]: NAMECALL R6 R6 K60 [0x6B837788]
     214 [-]: CALL R6 1 1  
     215 [-]: GETIMPORT R7 5 [nil]
     216 [-]: NAMECALL R7 R7 K61 [0xAF9FDA9F]
     217 [-]: CALL R7 1 -1 
     218 [-]: CALL R5 -1 0 
     219 [-]: GETIMPORT R6 64 [nil]
     220 [-]: FASTCALL1 62 R6 L5
     221 [-]: GETIMPORT R5 15 [nil]
     222 [-]: CALL R5 1 1  
L 5: 223 [-]: JUMPIF R5 L6 
     224 [-]: GETIMPORT R5 64 [nil]
     225 [-]: GETIMPORT R6 5 [nil]
     226 [-]: LOADK R8 K65 ["/Lotus/Language/Menu/ChooseWarframe"]
     227 [-]: LOADB R9 0   
     228 [-]: NAMECALL R6 R6 K66 [0x42B04007]
     229 [-]: CALL R6 3 -1 
     230 [-]: CALL R5 -1 0 
L 6: 231 [-]: LOADN R7 1   
     232 [-]: GETUPVAL R8 13
     233 [-]: LENGTH R5 R8 
     234 [-]: LOADN R6 1   
     235 [-]: FORNPREP R5 L8
L 7: 236 [-]: GETIMPORT R8 5 [nil]
     237 [-]: GETUPVAL R11 13
     238 [-]: GETTABLE R10 R11 R7
     239 [-]: LOADN R11 10 
     240 [-]: LOADN R12 0  
     241 [-]: NAMECALL R8 R8 K35 [0x67BC869F]
     242 [-]: CALL R8 4 0  
     243 [-]: FORNLOOP R5 L7
L 8: 244 [-]: LOADN R7 1   
     245 [-]: GETUPVAL R8 13
     246 [-]: LENGTH R5 R8 
     247 [-]: LOADN R6 1   
     248 [-]: FORNPREP R5 L10
L 9: 249 [-]: GETIMPORT R8 68 [nil]
     250 [-]: GETIMPORT R9 5 [nil]
     251 [-]: GETUPVAL R11 13
     252 [-]: GETTABLE R10 R11 R7
     253 [-]: LOADN R11 8  
     254 [-]: NEWTABLE R12 0 1
     255 [-]: LOADN R13 10 
     256 [-]: SETLIST R12 R13 1 [1]
     257 [-]: NEWTABLE R13 0 1
     258 [-]: LOADN R14 100
     259 [-]: SETLIST R13 R14 1 [1]
     260 [-]: LOADN R14 1  
     261 [-]: LOADN R15 0  
     262 [-]: LOADB R16 0  
     263 [-]: CALL R8 8 0  
     264 [-]: FORNLOOP R5 L9
L10: 265 [-]: GETIMPORT R5 69 [nil]
     266 [-]: GETIMPORT R8 73 [nil]
     267 [-]: ORK R7 R8 K71 [0]
     268 [-]: ADDK R6 R7 K70 [1]
     269 [-]: SETTABLEKS R6 R5 K72 ["HideHud"]
     270 [-]: RETURN R0 0  


; Name:            
; Defined at line: 444
; #Upvalues:       1
; #Parameters:     0
; Is_vararg:       0
; Max Stack Size:  5

       0 [-]: GETIMPORT R1 2 [nil]
       1 [-]: FASTCALL1 62 R1 L0
       2 [-]: GETIMPORT R0 4 [nil]
       3 [-]: CALL R0 1 1  
L 0:   4 [-]: JUMPIF R0 L1 
       5 [-]: GETIMPORT R0 2 [nil]
       6 [-]: CALL R0 0 0  
L 1:   7 [-]: GETUPVAL R1 0
       8 [-]: FASTCALL1 62 R1 L2
       9 [-]: GETIMPORT R0 4 [nil]
      10 [-]: CALL R0 1 1  
L 2:  11 [-]: JUMPIF R0 L3 
      12 [-]: GETUPVAL R0 0
      13 [-]: LOADB R2 0   
      14 [-]: NAMECALL R0 R0 K5 [0x6CF1E476]
      15 [-]: CALL R0 2 0  
L 3:  16 [-]: GETIMPORT R1 7 [nil]
      17 [-]: FASTCALL1 62 R1 L4
      18 [-]: GETIMPORT R0 4 [nil]
      19 [-]: CALL R0 1 1  
L 4:  20 [-]: JUMPIF R0 L6 
      21 [-]: GETIMPORT R0 7 [nil]
      22 [-]: NAMECALL R0 R0 K8 [0x78298275]
      23 [-]: CALL R0 1 1  
      24 [-]: FASTCALL1 62 R0 L5
      25 [-]: MOVE R2 R0   
      26 [-]: GETIMPORT R1 4 [nil]
      27 [-]: CALL R1 1 1  
L 5:  28 [-]: JUMPIF R1 L6 
      29 [-]: GETIMPORT R3 10 [nil]
      30 [-]: LOADB R4 0   
      31 [-]: NAMECALL R1 R0 K11 [0x511D26B8]
      32 [-]: CALL R1 3 0  
L 6:  33 [-]: GETIMPORT R0 12 [nil]
      34 [-]: LOADNIL R1   
      35 [-]: SETTABLEKS R1 R0 K13 ["InfoPopup_Data"]
      36 [-]: RETURN R0 0  


; Name:            
; Defined at line: 464
; #Upvalues:       0
; #Parameters:     0
; Is_vararg:       0
; Max Stack Size:  0

       0 [-]: RETURN R0 0  


; Name:            
; Defined at line: 467
; #Upvalues:       14
; #Parameters:     0
; Is_vararg:       0
; Max Stack Size:  11

       0 [-]: GETUPVAL R1 0
       1 [-]: FASTCALL1 62 R1 L0
       2 [-]: GETIMPORT R0 1 [nil]
       3 [-]: CALL R0 1 1  
L 0:   4 [-]: JUMPIF R0 L1 
       5 [-]: GETUPVAL R0 0
       6 [-]: GETUPVAL R2 1
       7 [-]: NAMECALL R2 R2 K2 [0xCFD9CD76]
       8 [-]: CALL R2 1 -1 
       9 [-]: NAMECALL R0 R0 K3 [0x46610C50]
      10 [-]: CALL R0 -1 0 
L 1:  11 [-]: GETUPVAL R0 1
      12 [-]: NAMECALL R0 R0 K2 [0xCFD9CD76]
      13 [-]: CALL R0 1 1  
      14 [-]: JUMPIFNOT R0 L21
      15 [-]: GETUPVAL R0 1
      16 [-]: NAMECALL R0 R0 K4 [0x842BDEF9]
      17 [-]: CALL R0 1 1  
      18 [-]: JUMPIFNOT R0 L21
      19 [-]: GETUPVAL R0 1
      20 [-]: NAMECALL R0 R0 K5 [0xA4497305]
      21 [-]: CALL R0 1 0  
      22 [-]: GETGLOBAL R1 K6 [0x946FEA28]
      23 [-]: GETUPVAL R2 2
      24 [-]: GETTABLE R0 R1 R2
      25 [-]: LOADK R1 K7 ["<p>"]
      26 [-]: SETUPVAL R1 3
      27 [-]: GETUPVAL R1 4
      28 [-]: LOADK R2 K8 [""]
      29 [-]: GETIMPORT R3 10 [nil]
      30 [-]: NAMECALL R5 R0 K11 [0x5BA460AC]
      31 [-]: CALL R5 1 1  
      32 [-]: NAMECALL R5 R5 K12 [0x6D604BA7]
      33 [-]: CALL R5 1 1  
      34 [-]: LOADB R6 0   
      35 [-]: NAMECALL R3 R3 K13 [0x42B04007]
      36 [-]: CALL R3 3 -1 
      37 [-]: CALL R1 -1 0 
      38 [-]: GETUPVAL R1 5
      39 [-]: MOVE R2 R0   
      40 [-]: CALL R1 1 0  
      41 [-]: GETUPVAL R2 3
      42 [-]: LOADK R3 K14 ["</p>"]
      43 [-]: CONCAT R1 R2 R3
      44 [-]: SETUPVAL R1 3
      45 [-]: GETIMPORT R1 10 [nil]
      46 [-]: LOADK R3 K15 ["Description.Label"]
      47 [-]: LOADN R4 29  
      48 [-]: GETUPVAL R5 3
      49 [-]: NAMECALL R1 R1 K16 [0x5F56EEAB]
      50 [-]: CALL R1 4 0  
      51 [-]: GETIMPORT R2 10 [nil]
      52 [-]: LOADK R4 K15 ["Description.Label"]
      53 [-]: LOADN R5 34  
      54 [-]: NAMECALL R2 R2 K18 [0x91A24E4B]
      55 [-]: CALL R2 3 1  
      56 [-]: ADDK R1 R2 K17 [5]
      57 [-]: GETIMPORT R2 10 [nil]
      58 [-]: LOADK R4 K19 ["Description.Backer"]
      59 [-]: LOADN R5 13  
      60 [-]: MOVE R6 R1   
      61 [-]: NAMECALL R2 R2 K20 [0x67BC869F]
      62 [-]: CALL R2 4 0  
      63 [-]: GETIMPORT R2 10 [nil]
      64 [-]: LOADK R4 K21 ["Description.Blurer"]
      65 [-]: LOADN R5 13  
      66 [-]: MOVE R6 R1   
      67 [-]: NAMECALL R2 R2 K20 [0x67BC869F]
      68 [-]: CALL R2 4 0  
      69 [-]: GETIMPORT R4 23 [nil]
      70 [-]: FASTCALL1 62 R4 L2
      71 [-]: GETIMPORT R3 1 [nil]
      72 [-]: CALL R3 1 1  
L 2:  73 [-]: JUMPIF R3 L3 
      74 [-]: GETIMPORT R3 23 [nil]
      75 [-]: GETIMPORT R5 25 [nil]
      76 [-]: NAMECALL R3 R3 K26 [0xF2DEAF69]
      77 [-]: CALL R3 2 1  
      78 [-]: JUMPIFNOT R3 L3
      79 [-]: GETIMPORT R2 23 [nil]
      80 [-]: GETUPVAL R5 6
      81 [-]: GETTABLEKS R4 R5 K27 ["NV_CURRENT_MOOD"]
      82 [-]: LOADN R5 0   
      83 [-]: NAMECALL R2 R2 K28 [0x0EB34C69]
      84 [-]: CALL R2 3 1  
      85 [-]: JUMP L4
     
L 3:  86 [-]: LOADNIL R2   
L 4:  87 [-]: FASTCALL1 62 R2 L5
      88 [-]: MOVE R4 R2   
      89 [-]: GETIMPORT R3 1 [nil]
      90 [-]: CALL R3 1 1  
L 5:  91 [-]: JUMPIF R3 L13
      92 [-]: GETUPVAL R4 7
      93 [-]: FASTCALL1 62 R4 L6
      94 [-]: GETIMPORT R3 1 [nil]
      95 [-]: CALL R3 1 1  
L 6:  96 [-]: JUMPIFNOT R3 L7
      97 [-]: GETUPVAL R4 8
      98 [-]: GETTABLEKS R3 R4 K29 [0x659D451F]
      99 [-]: GETIMPORT R4 31 [nil]
     100 [-]: CALL R3 1 1  
     101 [-]: SETUPVAL R3 7
L 7: 102 [-]: GETUPVAL R4 9
     103 [-]: FASTCALL1 62 R4 L8
     104 [-]: GETIMPORT R3 1 [nil]
     105 [-]: CALL R3 1 1  
L 8: 106 [-]: JUMPIFNOT R3 L9
     107 [-]: GETUPVAL R4 8
     108 [-]: GETTABLEKS R3 R4 K29 [0x659D451F]
     109 [-]: GETIMPORT R4 33 [nil]
     110 [-]: CALL R3 1 1  
     111 [-]: SETUPVAL R3 9
L 9: 112 [-]: GETIMPORT R3 35 [nil]
     113 [-]: GETIMPORT R5 37 [nil]
     114 [-]: LOADK R6 K38 ["/EE/Types/Engine/Sequencer"]
     115 [-]: CALL R5 1 -1 
     116 [-]: NAMECALL R3 R3 K39 [0xFB669000]
     117 [-]: CALL R3 -1 1 
     118 [-]: FASTCALL1 62 R3 L10
     119 [-]: MOVE R5 R3   
     120 [-]: GETIMPORT R4 1 [nil]
     121 [-]: CALL R4 1 1  
L10: 122 [-]: JUMPIF R4 L20
     123 [-]: GETIMPORT R4 41 [nil]
     124 [-]: MOVE R5 R3   
     125 [-]: CALL R4 1 3  
     126 [-]: FORGPREP_INEXT R4 L12
L11: 127 [-]: NAMECALL R9 R8 K42 [0xF4E253B6]
     128 [-]: CALL R9 1 0  
L12: 129 [-]: FORGLOOP R4 L11 2 [inext]
     130 [-]: JUMP L20
    
L13: 131 [-]: GETIMPORT R4 35 [nil]
     132 [-]: FASTCALL1 62 R4 L14
     133 [-]: GETIMPORT R3 1 [nil]
     134 [-]: CALL R3 1 1  
L14: 135 [-]: JUMPIF R3 L20
     136 [-]: GETUPVAL R4 10
     137 [-]: FASTCALL1 62 R4 L15
     138 [-]: GETIMPORT R3 1 [nil]
     139 [-]: CALL R3 1 1  
L15: 140 [-]: JUMPIFNOT R3 L16
     141 [-]: GETIMPORT R3 35 [nil]
     142 [-]: GETIMPORT R5 44 [nil]
     143 [-]: GETIMPORT R6 46 [nil]
     144 [-]: CALL R6 0 1  
     145 [-]: LOADB R7 0   
     146 [-]: LOADN R8 1   
     147 [-]: NAMECALL R3 R3 K29 [0x659D451F]
     148 [-]: CALL R3 5 1  
     149 [-]: SETUPVAL R3 10
L16: 150 [-]: GETIMPORT R3 35 [nil]
     151 [-]: GETIMPORT R5 37 [nil]
     152 [-]: LOADK R6 K38 ["/EE/Types/Engine/Sequencer"]
     153 [-]: CALL R5 1 -1 
     154 [-]: NAMECALL R3 R3 K39 [0xFB669000]
     155 [-]: CALL R3 -1 1 
     156 [-]: FASTCALL1 62 R3 L17
     157 [-]: MOVE R5 R3   
     158 [-]: GETIMPORT R4 1 [nil]
     159 [-]: CALL R4 1 1  
L17: 160 [-]: JUMPIF R4 L20
     161 [-]: GETIMPORT R4 41 [nil]
     162 [-]: MOVE R5 R3   
     163 [-]: CALL R4 1 3  
     164 [-]: FORGPREP_INEXT R4 L19
L18: 165 [-]: NAMECALL R9 R8 K42 [0xF4E253B6]
     166 [-]: CALL R9 1 0  
L19: 167 [-]: FORGLOOP R4 L18 2 [inext]
L20: 168 [-]: DUPCLOSURE R3 K47 []
     169 [-]: GETIMPORT R4 49 [nil]
     170 [-]: GETIMPORT R5 10 [nil]
     171 [-]: LOADK R6 K50 ["_root"]
     172 [-]: LOADN R7 0   
     173 [-]: NEWTABLE R8 0 1
     174 [-]: MOVE R9 R3   
     175 [-]: SETLIST R8 R9 1 [1]
     176 [-]: NEWTABLE R9 0 1
     177 [-]: LOADN R10 1  
     178 [-]: SETLIST R9 R10 1 [1]
     179 [-]: LOADN R10 1  
     180 [-]: CALL R4 6 0  
     181 [-]: GETUPVAL R4 11
     182 [-]: CALL R4 0 0  
     183 [-]: GETUPVAL R4 12
     184 [-]: GETIMPORT R5 10 [nil]
     185 [-]: NAMECALL R5 R5 K51 [0x6B837788]
     186 [-]: CALL R5 1 1  
     187 [-]: GETIMPORT R6 10 [nil]
     188 [-]: NAMECALL R6 R6 K52 [0xAF9FDA9F]
     189 [-]: CALL R6 1 -1 
     190 [-]: CALL R4 -1 0 
     191 [-]: LOADB R4 0   
     192 [-]: SETUPVAL R4 13
L21: 193 [-]: RETURN R0 0  


; Name:            
; Defined at line: 531
; #Upvalues:       3
; #Parameters:     0
; Is_vararg:       0
; Max Stack Size:  3

       0 [-]: GETIMPORT R0 1 [nil]
       1 [-]: GETIMPORT R2 3 [nil]
       2 [-]: CALL R2 0 -1 
       3 [-]: NAMECALL R0 R0 K4 [0x8A8C8D5A]
       4 [-]: CALL R0 -1 0 
       5 [-]: GETUPVAL R1 0
       6 [-]: FASTCALL1 62 R1 L0
       7 [-]: GETIMPORT R0 6 [nil]
       8 [-]: CALL R0 1 1  
L 0:   9 [-]: JUMPIF R0 L1 
      10 [-]: GETUPVAL R0 0
      11 [-]: NAMECALL R0 R0 K7 [0xFAA69527]
      12 [-]: CALL R0 1 0  
L 1:  13 [-]: GETUPVAL R1 1
      14 [-]: FASTCALL1 62 R1 L2
      15 [-]: GETIMPORT R0 6 [nil]
      16 [-]: CALL R0 1 1  
L 2:  17 [-]: JUMPIF R0 L3 
      18 [-]: GETUPVAL R0 1
      19 [-]: NAMECALL R0 R0 K7 [0xFAA69527]
      20 [-]: CALL R0 1 0  
L 3:  21 [-]: GETUPVAL R0 2
      22 [-]: CALL R0 0 0  
      23 [-]: RETURN R0 0  


; Name:            
; Defined at line: 545
; #Upvalues:       3
; #Parameters:     1
; Is_vararg:       0
; Max Stack Size:  6

       0 [-]: GETUPVAL R2 0
       1 [-]: ADD R1 R2 R0 
       2 [-]: SUBK R3 R1 K0 [1]
       3 [-]: GETUPVAL R5 1
       4 [-]: LENGTH R4 R5 
       5 [-]: MOD R2 R3 R4 
       6 [-]: ADDK R1 R2 K0 [1]
       7 [-]: GETUPVAL R2 2
       8 [-]: MOVE R3 R1   
       9 [-]: CALL R2 1 0  
      10 [-]: GETUPVAL R3 1
      11 [-]: GETUPVAL R4 0
      12 [-]: GETTABLE R2 R3 R4
      13 [-]: LOADB R4 1   
      14 [-]: NAMECALL R2 R2 K1 [0x0417AD4A]
      15 [-]: CALL R2 2 0  
      16 [-]: RETURN R0 0  


; Name:            
; Defined at line: 552
; #Upvalues:       4
; #Parameters:     0
; Is_vararg:       0
; Max Stack Size:  6

       0 [-]: GETUPVAL R1 0
       1 [-]: GETTABLEKS R0 R1 K0 ["DECREMENT"]
       2 [-]: GETUPVAL R2 1
       3 [-]: ADD R1 R2 R0 
       4 [-]: SUBK R3 R1 K1 [1]
       5 [-]: GETUPVAL R5 2
       6 [-]: LENGTH R4 R5 
       7 [-]: MOD R2 R3 R4 
       8 [-]: ADDK R1 R2 K1 [1]
       9 [-]: GETUPVAL R2 3
      10 [-]: MOVE R3 R1   
      11 [-]: CALL R2 1 0  
      12 [-]: GETUPVAL R3 2
      13 [-]: GETUPVAL R4 1
      14 [-]: GETTABLE R2 R3 R4
      15 [-]: LOADB R4 1   
      16 [-]: NAMECALL R2 R2 K2 [0x0417AD4A]
      17 [-]: CALL R2 2 0  
      18 [-]: LOADB R0 1   
      19 [-]: RETURN R0 1  


; Name:            
; Defined at line: 557
; #Upvalues:       4
; #Parameters:     0
; Is_vararg:       0
; Max Stack Size:  6

       0 [-]: GETUPVAL R1 0
       1 [-]: GETTABLEKS R0 R1 K0 ["INCREMENT"]
       2 [-]: GETUPVAL R2 1
       3 [-]: ADD R1 R2 R0 
       4 [-]: SUBK R3 R1 K1 [1]
       5 [-]: GETUPVAL R5 2
       6 [-]: LENGTH R4 R5 
       7 [-]: MOD R2 R3 R4 
       8 [-]: ADDK R1 R2 K1 [1]
       9 [-]: GETUPVAL R2 3
      10 [-]: MOVE R3 R1   
      11 [-]: CALL R2 1 0  
      12 [-]: GETUPVAL R3 2
      13 [-]: GETUPVAL R4 1
      14 [-]: GETTABLE R2 R3 R4
      15 [-]: LOADB R4 1   
      16 [-]: NAMECALL R2 R2 K2 [0x0417AD4A]
      17 [-]: CALL R2 2 0  
      18 [-]: LOADB R0 1   
      19 [-]: RETURN R0 1  


; Name:            
; Defined at line: 562
; #Upvalues:       1
; #Parameters:     0
; Is_vararg:       0
; Max Stack Size:  1

       0 [-]: GETUPVAL R0 0
       1 [-]: RETURN R0 1  


; Name:            
; Defined at line: 566
; #Upvalues:       0
; #Parameters:     0
; Is_vararg:       0
; Max Stack Size:  1

       0 [-]: LOADB R0 1   
       1 [-]: RETURN R0 1  


; Name:            
; Defined at line: 570
; #Upvalues:       2
; #Parameters:     0
; Is_vararg:       0
; Max Stack Size:  2

       0 [-]: GETUPVAL R0 0
       1 [-]: LOADB R1 1   
       2 [-]: SETTABLEKS R1 R0 K0 ["Focused"]
       3 [-]: GETIMPORT R0 2 [nil]
       4 [-]: GETUPVAL R1 0
       5 [-]: SETTABLEKS R1 R0 K3 ["InfoPopup_Data"]
       6 [-]: GETUPVAL R0 1
       7 [-]: CALL R0 0 0  
       8 [-]: RETURN R0 0  


; Name:            
; Defined at line: 576
; #Upvalues:       2
; #Parameters:     0
; Is_vararg:       0
; Max Stack Size:  2

       0 [-]: GETUPVAL R0 0
       1 [-]: LOADB R1 0   
       2 [-]: SETTABLEKS R1 R0 K0 ["Focused"]
       3 [-]: GETIMPORT R0 2 [nil]
       4 [-]: LOADNIL R1   
       5 [-]: SETTABLEKS R1 R0 K3 ["InfoPopup_Data"]
       6 [-]: GETUPVAL R0 1
       7 [-]: CALL R0 0 0  
       8 [-]: RETURN R0 0  


; Name:            
; Defined at line: 582
; #Upvalues:       0
; #Parameters:     0
; Is_vararg:       0
; Max Stack Size:  0

       0 [-]: RETURN R0 0  


; Name:            
; Defined at line: 585
; #Upvalues:       0
; #Parameters:     0
; Is_vararg:       0
; Max Stack Size:  0

       0 [-]: RETURN R0 0  


; Name:            
; Defined at line: 588
; #Upvalues:       2
; #Parameters:     1
; Is_vararg:       0
; Max Stack Size:  5

       0 [-]: GETUPVAL R1 0
       1 [-]: JUMPIF R1 L1 
       2 [-]: GETUPVAL R2 1
       3 [-]: FASTCALL1 62 R2 L0
       4 [-]: GETIMPORT R1 1 [nil]
       5 [-]: CALL R1 1 1  
L 0:   6 [-]: JUMPIF R1 L1 
       7 [-]: GETUPVAL R1 1
       8 [-]: GETIMPORT R3 3 [nil]
       9 [-]: MOVE R4 R0   
      10 [-]: CALL R3 1 1  
      11 [-]: LOADB R4 1   
      12 [-]: NAMECALL R1 R1 K4 [0x070DAA5A]
      13 [-]: CALL R1 3 0  
L 1:  14 [-]: RETURN R0 0  


; Name:            
; Defined at line: 594
; #Upvalues:       1
; #Parameters:     1
; Is_vararg:       0
; Max Stack Size:  5

       0 [-]: GETUPVAL R2 0
       1 [-]: FASTCALL1 62 R2 L0
       2 [-]: GETIMPORT R1 1 [nil]
       3 [-]: CALL R1 1 1  
L 0:   4 [-]: JUMPIF R1 L1 
       5 [-]: GETUPVAL R1 0
       6 [-]: GETIMPORT R3 3 [nil]
       7 [-]: MOVE R4 R0   
       8 [-]: CALL R3 1 1  
       9 [-]: LOADB R4 1   
      10 [-]: NAMECALL R1 R1 K4 [0xDF42446E]
      11 [-]: CALL R1 3 0  
L 1:  12 [-]: RETURN R0 0  


; Name:            
; Defined at line: 600
; #Upvalues:       1
; #Parameters:     1
; Is_vararg:       0
; Max Stack Size:  5

       0 [-]: GETUPVAL R2 0
       1 [-]: FASTCALL1 62 R2 L0
       2 [-]: GETIMPORT R1 1 [nil]
       3 [-]: CALL R1 1 1  
L 0:   4 [-]: JUMPIF R1 L1 
       5 [-]: GETUPVAL R1 0
       6 [-]: GETIMPORT R3 3 [nil]
       7 [-]: MOVE R4 R0   
       8 [-]: CALL R3 1 1  
       9 [-]: LOADB R4 1   
      10 [-]: NAMECALL R1 R1 K4 [0xBCE5A201]
      11 [-]: CALL R1 3 0  
L 1:  12 [-]: RETURN R0 0  


; Name:            
; Defined at line: 606
; #Upvalues:       0
; #Parameters:     0
; Is_vararg:       0
; Max Stack Size:  1

       0 [-]: LOADB R0 1   
       1 [-]: RETURN R0 1  


; Name:            
; Defined at line: 610
; #Upvalues:       1
; #Parameters:     0
; Is_vararg:       0
; Max Stack Size:  1

       0 [-]: GETUPVAL R0 0
       1 [-]: CALL R0 0 0  
       2 [-]: RETURN R0 0  


; Name:            
; Defined at line: 614
; #Upvalues:       1
; #Parameters:     1
; Is_vararg:       0
; Max Stack Size:  3

       0 [-]: GETUPVAL R1 0
       1 [-]: NAMECALL R1 R1 K0 [0x557B7601]
       2 [-]: CALL R1 1 0  
       3 [-]: RETURN R0 0  



