; Name:            
; Defined at line: 1
; #Upvalues:       0
; #Parameters:     0
; Is_vararg:       1
; Max Stack Size:  61

       1 [-]: LOADNIL R0   ; var0 = nil
       2 [-]: LOADNIL R1   ; var1 = nil
       3 [-]: LOADNIL R2   ; var2 = nil
       4 [-]: LOADNIL R3   ; var3 = nil
       5 [-]: LOADNIL R4   ; var4 = nil
       6 [-]: LOADNIL R5   ; var5 = nil
       7 [-]: LOADNIL R6   ; var6 = nil
       8 [-]: LOADNIL R7   ; var7 = nil
       9 [-]: LOADNIL R8   ; var8 = nil
      10 [-]: LOADNIL R9   ; var9 = nil
      11 [-]: LOADNIL R10  ; var10 = nil
      12 [-]: LOADNIL R11  ; var11 = nil
      13 [-]: GETIMPORT R12 1; var12 = EMPTY_SYMBOL
      14 [-]: LOADNIL R13  ; var13 = nil
      15 [-]: LOADNIL R14  ; var14 = nil
      16 [-]: LOADNIL R15  ; var15 = nil
      17 [-]: LOADNIL R16  ; var16 = nil
      18 [-]: LOADNIL R17  ; var17 = nil
      19 [-]: LOADB R18 0  ; var18 = false
      20 [-]: LOADB R19 0  ; var19 = false
      21 [-]: GETIMPORT R20 3; var20 = 0x0469F296
      22 [-]: LOADK R21 K4 ; var21 = "AngelArenaTag"
      23 [-]: CALL R20 2 2 ; var20 = var20(var21)
      24 [-]: GETIMPORT R21 6; var21 = 0xB009BBC6
      25 [-]: LOADK R22 K7 ; var22 = "/Lotus/Types/Gameplay/Minigames/Investigation/InvestigationBlockingInputFilter"
      26 [-]: CALL R21 2 2 ; var21 = var21(var22)
      27 [-]: GETIMPORT R22 9; var22 = 0x7ED0A956
      28 [-]: LOADK R23 K10; var23 = "/Lotus/Powersuits/PowersuitAbilities/OperatorTransferenceAbility"
      29 [-]: CALL R22 2 2 ; var22 = var22(var23)
      30 [-]: GETIMPORT R23 3; var23 = 0x0469F296
      31 [-]: LOADK R24 K11; var24 = "VoidArenaLogic"
      32 [-]: CALL R23 2 2 ; var23 = var23(var24)
      33 [-]: GETIMPORT R24 3; var24 = 0x0469F296
      34 [-]: LOADK R25 K12; var25 = "VoidAngelInteriorHint"
      35 [-]: CALL R24 2 2 ; var24 = var24(var25)
      36 [-]: GETIMPORT R25 3; var25 = 0x0469F296
      37 [-]: LOADK R26 K13; var26 = "VoidAngelPreDeath"
      38 [-]: CALL R25 2 2 ; var25 = var25(var26)
      39 [-]: GETIMPORT R26 3; var26 = 0x0469F296
      40 [-]: LOADK R27 K14; var27 = "VoidAngelPreDeathWait"
      41 [-]: CALL R26 2 2 ; var26 = var26(var27)
      42 [-]: GETIMPORT R27 3; var27 = 0x0469F296
      43 [-]: LOADK R28 K15; var28 = "GAME_C1_SPINE2"
      44 [-]: CALL R27 2 2 ; var27 = var27(var28)
      45 [-]: GETIMPORT R28 3; var28 = 0x0469F296
      46 [-]: LOADK R29 K16; var29 = "VoidAngelCorruption"
      47 [-]: CALL R28 2 2 ; var28 = var28(var29)
      48 [-]: GETIMPORT R29 3; var29 = 0x0469F296
      49 [-]: LOADK R30 K17; var30 = "VoidAngelFallTrigger"
      50 [-]: CALL R29 2 2 ; var29 = var29(var30)
      51 [-]: GETIMPORT R30 3; var30 = 0x0469F296
      52 [-]: LOADK R31 K18; var31 = "VoidAngelTeleport"
      53 [-]: CALL R30 2 2 ; var30 = var30(var31)
      54 [-]: GETIMPORT R31 3; var31 = 0x0469F296
      55 [-]: LOADK R32 K19; var32 = "DZarArmQKiraInvul0900Cavalero"
      56 [-]: CALL R31 2 2 ; var31 = var31(var32)
      57 [-]: GETIMPORT R32 3; var32 = 0x0469F296
      58 [-]: LOADK R33 K20; var33 = "DZarArmAngelFirstEthQuest0830Cavalero"
      59 [-]: CALL R32 2 2 ; var32 = var32(var33)
      60 [-]: GETIMPORT R33 3; var33 = 0x0469F296
      61 [-]: LOADK R34 K21; var34 = "DZarArmAngelHealHalfQuest0840Cavalero"
      62 [-]: CALL R33 2 2 ; var33 = var33(var34)
      63 [-]: GETIMPORT R34 3; var34 = 0x0469F296
      64 [-]: LOADK R35 K22; var35 = "DZarArmAngelInvul4870Cavalero"
      65 [-]: CALL R34 2 2 ; var34 = var34(var35)
      66 [-]: GETIMPORT R35 3; var35 = 0x0469F296
      67 [-]: LOADK R36 K23; var36 = "DZarArmAngelFirstEth4880Cavalero"
      68 [-]: CALL R35 2 2 ; var35 = var35(var36)
      69 [-]: GETIMPORT R36 3; var36 = 0x0469F296
      70 [-]: LOADK R37 K24; var37 = "DZarArmAngelHealHalf4890Cavalero"
      71 [-]: CALL R36 2 2 ; var36 = var36(var37)
      72 [-]: GETIMPORT R37 3; var37 = 0x0469F296
      73 [-]: LOADK R38 K25; var38 = "DZarArmAngelFullHeal4910Cavalero"
      74 [-]: CALL R37 2 2 ; var37 = var37(var38)
      75 [-]: GETIMPORT R38 3; var38 = 0x0469F296
      76 [-]: LOADK R39 K26; var39 = "DZarArmAngelEthDestroy4920Cavalero"
      77 [-]: CALL R38 2 2 ; var38 = var38(var39)
      78 [-]: GETIMPORT R39 3; var39 = 0x0469F296
      79 [-]: LOADK R40 K27; var40 = "GargoyleEvent_VoidAngelRetreat"
      80 [-]: CALL R39 2 2 ; var39 = var39(var40)
      81 [-]: GETIMPORT R40 3; var40 = 0x0469F296
      82 [-]: LOADK R41 K28; var41 = "GargoyleEvent_VoidAngelKilled"
      83 [-]: CALL R40 2 2 ; var40 = var40(var41)
      84 [-]: GETIMPORT R41 3; var41 = 0x0469F296
      85 [-]: LOADK R42 K29; var42 = "EntratiEvent"
      86 [-]: CALL R41 2 2 ; var41 = var41(var42)
      87 [-]: LOADB R42 0  ; var42 = false
      88 [-]: LOADB R43 0  ; var43 = false
      89 [-]: LOADB R44 0  ; var44 = false
      90 [-]: LOADB R45 0  ; var45 = false
      91 [-]: GETIMPORT R46 31; var46 = 0x2D0FAD09
      92 [-]: LOADK R47 K32; var47 = "Lotus.Interface.LotusUtilities"
      93 [-]: CALL R46 2 2 ; var46 = var46(var47)
      94 [-]: GETIMPORT R47 31; var47 = 0x2D0FAD09
      95 [-]: LOADK R48 K33; var48 = "Lotus.Scripts.Libs.RailjackUtilities"
      96 [-]: CALL R47 2 2 ; var47 = var47(var48)
      97 [-]: GETIMPORT R48 31; var48 = 0x2D0FAD09
      98 [-]: LOADK R49 K34; var49 = "Lotus.Interface.Libs.TimerMgr"
      99 [-]: CALL R48 2 2 ; var48 = var48(var49)
     100 [-]: GETIMPORT R49 31; var49 = 0x2D0FAD09
     101 [-]: LOADK R50 K35; var50 = "Lotus.Scripts.Libs.TransmissionSet"
     102 [-]: CALL R49 2 2 ; var49 = var49(var50)
     103 [-]: NEWCLOSURE R50 P0; 
     104 [-]: CAPTURE REF R19; 
     105 [-]: CAPTURE VAL R49; 
     106 [-]: DUPCLOSURE R51 K36; 
     107 [-]: DUPCLOSURE R52 K37; 
     108 [-]: DUPCLOSURE R53 K38; 
     109 [-]: DUPCLOSURE R54 K39; 
     110 [-]: CAPTURE VAL R21; 
     111 [-]: CAPTURE VAL R27; 
     112 [-]: CAPTURE VAL R51; 
     113 [-]: DUPCLOSURE R55 K40; 
     114 [-]: CAPTURE VAL R22; 
     115 [-]: CAPTURE VAL R21; 
     116 [-]: CAPTURE VAL R27; 
     117 [-]: CAPTURE VAL R51; 
     118 [-]: CAPTURE VAL R20; 
     119 [-]: SETGLOBAL R55 K41; "TeleportClientIn" = var55
     120 [-]: DUPCLOSURE R55 K42; 
     121 [-]: CAPTURE VAL R52; 
     122 [-]: CAPTURE VAL R21; 
     123 [-]: CAPTURE VAL R27; 
     124 [-]: CAPTURE VAL R51; 
     125 [-]: CAPTURE VAL R20; 
     126 [-]: CAPTURE VAL R22; 
     127 [-]: SETGLOBAL R55 K43; "TeleportClientOut" = var55
     128 [-]: NEWCLOSURE R55 P7; 
     129 [-]: CAPTURE VAL R47; 
     130 [-]: CAPTURE VAL R22; 
     131 [-]: CAPTURE VAL R54; 
     132 [-]: CAPTURE VAL R20; 
     133 [-]: CAPTURE REF R44; 
     134 [-]: CAPTURE REF R18; 
     135 [-]: CAPTURE VAL R32; 
     136 [-]: CAPTURE REF R19; 
     137 [-]: CAPTURE VAL R49; 
     138 [-]: CAPTURE VAL R35; 
     139 [-]: NEWCLOSURE R56 P8; 
     140 [-]: CAPTURE VAL R54; 
     141 [-]: CAPTURE VAL R22; 
     142 [-]: CAPTURE VAL R52; 
     143 [-]: CAPTURE REF R16; 
     144 [-]: CAPTURE VAL R20; 
     145 [-]: DUPCLOSURE R57 K44; 
     146 [-]: CAPTURE VAL R55; 
     147 [-]: DUPCLOSURE R58 K45; 
     148 [-]: SETGLOBAL R58 K46; "VoidPortal" = var58
     149 [-]: DUPCLOSURE R58 K47; 
     150 [-]: CAPTURE VAL R27; 
     151 [-]: SETGLOBAL R58 K48; "SpawnPreDeathPortal" = var58
     152 [-]: NEWCLOSURE R58 P12; 
     153 [-]: CAPTURE REF R4; 
     154 [-]: CAPTURE VAL R47; 
     155 [-]: CAPTURE REF R18; 
     156 [-]: CAPTURE REF R19; 
     157 [-]: CAPTURE VAL R25; 
     158 [-]: CAPTURE VAL R27; 
     159 [-]: CAPTURE REF R42; 
     160 [-]: CAPTURE VAL R31; 
     161 [-]: CAPTURE VAL R49; 
     162 [-]: CAPTURE VAL R39; 
     163 [-]: CAPTURE VAL R34; 
     164 [-]: CAPTURE REF R43; 
     165 [-]: CAPTURE VAL R37; 
     166 [-]: CAPTURE VAL R26; 
     167 [-]: CAPTURE VAL R38; 
     168 [-]: CAPTURE VAL R57; 
     169 [-]: CAPTURE REF R45; 
     170 [-]: CAPTURE VAL R33; 
     171 [-]: CAPTURE VAL R36; 
     172 [-]: CAPTURE VAL R30; 
     173 [-]: CAPTURE VAL R28; 
     174 [-]: CAPTURE VAL R40; 
     175 [-]: SETGLOBAL R58 K49; "VoidAngel" = var58
     176 [-]: DUPCLOSURE R58 K50; 
     177 [-]: SETGLOBAL R58 K51; "EtherealAngel" = var58
     178 [-]: NEWCLOSURE R58 P14; 
     179 [-]: CAPTURE REF R0; 
     180 [-]: SETGLOBAL R58 K52; "VoidAngelReady" = var58
     181 [-]: NEWCLOSURE R58 P15; 
     182 [-]: CAPTURE REF R0; 
     183 [-]: SETGLOBAL R58 K53; "SpawnVoidAngel" = var58
     184 [-]: DUPCLOSURE R58 K54; 
     185 [-]: CAPTURE VAL R23; 
     186 [-]: CAPTURE VAL R24; 
     187 [-]: SETGLOBAL R58 K55; "VoidAngelInteriorSetup" = var58
     188 [-]: NEWCLOSURE R58 P17; 
     189 [-]: CAPTURE REF R10; 
     190 [-]: CAPTURE REF R1; 
     191 [-]: CAPTURE REF R8; 
     192 [-]: CAPTURE REF R12; 
     193 [-]: CAPTURE REF R7; 
     194 [-]: CAPTURE REF R6; 
     195 [-]: CAPTURE REF R4; 
     196 [-]: CAPTURE REF R17; 
     197 [-]: CAPTURE VAL R25; 
     198 [-]: CAPTURE REF R13; 
     199 [-]: CAPTURE VAL R46; 
     200 [-]: CAPTURE REF R3; 
     201 [-]: CAPTURE VAL R56; 
     202 [-]: CAPTURE VAL R47; 
     203 [-]: CAPTURE VAL R20; 
     204 [-]: CAPTURE REF R16; 
     205 [-]: CAPTURE REF R14; 
     206 [-]: NEWCLOSURE R59 P18; 
     207 [-]: CAPTURE REF R1; 
     208 [-]: CAPTURE REF R2; 
     209 [-]: CAPTURE VAL R48; 
     210 [-]: CAPTURE REF R3; 
     211 [-]: CAPTURE REF R4; 
     212 [-]: CAPTURE VAL R47; 
     213 [-]: CAPTURE REF R5; 
     214 [-]: CAPTURE REF R8; 
     215 [-]: CAPTURE REF R9; 
     216 [-]: CAPTURE REF R10; 
     217 [-]: CAPTURE REF R17; 
     218 [-]: CAPTURE REF R11; 
     219 [-]: CAPTURE REF R12; 
     220 [-]: CAPTURE REF R6; 
     221 [-]: CAPTURE REF R7; 
     222 [-]: CAPTURE VAL R20; 
     223 [-]: CAPTURE REF R15; 
     224 [-]: CAPTURE VAL R29; 
     225 [-]: CAPTURE REF R16; 
     226 [-]: NEWCLOSURE R60 P19; 
     227 [-]: CAPTURE VAL R59; 
     228 [-]: CAPTURE REF R4; 
     229 [-]: CAPTURE REF R3; 
     230 [-]: CAPTURE VAL R47; 
     231 [-]: CAPTURE VAL R56; 
     232 [-]: CAPTURE VAL R58; 
     233 [-]: CAPTURE REF R6; 
     234 [-]: CAPTURE REF R17; 
     235 [-]: CAPTURE REF R13; 
     236 [-]: CAPTURE REF R14; 
     237 [-]: CAPTURE REF R2; 
     238 [-]: CAPTURE REF R15; 
     239 [-]: CAPTURE REF R16; 
     240 [-]: SETGLOBAL R60 K56; "StartVoidArena" = var60
     241 [-]: NEWCLOSURE R60 P20; 
     242 [-]: CAPTURE VAL R20; 
     243 [-]: CAPTURE VAL R22; 
     244 [-]: CAPTURE VAL R52; 
     245 [-]: CAPTURE REF R16; 
     246 [-]: SETGLOBAL R60 K57; "OperatorArenaMonitor" = var60
     247 [-]: DUPCLOSURE R60 K58; 
     248 [-]: CAPTURE VAL R20; 
     249 [-]: CAPTURE VAL R22; 
     250 [-]: CAPTURE VAL R52; 
     251 [-]: SETGLOBAL R60 K59; "ClientOperatorArenaMonitor" = var60
     252 [-]: CLOSEUPVALS R0; 
     253 [-]: RETURN R0 0  ; 


; Name:            
; Defined at line: 116
; #Upvalues:       2
; #Parameters:     1
; Is_vararg:       0
; Max Stack Size:  4

       0 [-]: GETUPVAL R1 0; var1 = upvalues[0]
       1 [-]: JUMPIF R1 L0 ; goto L0 if var1
       2 [-]: GETUPVAL R2 1; var2 = upvalues[1]
       3 [-]: GETTABLEKS R1 R2 K0; var1 = var2[0x9742B85B]
       4 [-]: GETIMPORT R2 2; var2 = 0x4430F697
       5 [-]: MOVE R3 R0   ; var3 = var0
       6 [-]: CALL R1 3 1  ; var1(var2, var3)
L 0:   7 [-]: RETURN R0 0  ; 


; Name:            
; Defined at line: 122
; #Upvalues:       0
; #Parameters:     3
; Is_vararg:       0
; Max Stack Size:  11

       0 [-]: FASTCALL1 64 R0 L0; 
       1 [-]: MOVE R4 R0   ; var4 = var0
       2 [-]: GETIMPORT R3 1; var3 = 0x7B998233
       3 [-]: CALL R3 2 2  ; var3 = var3(var4)
L 0:   4 [-]: JUMPIF R3 L2 ; goto L2 if var3
       5 [-]: NAMECALL R4 R0 K2; var5 = var0; var4 = var0[0x5B89142C]
       6 [-]: CALL R4 2 0  ; var4, ... = var4(var5)
       7 [-]: FASTCALL 64 L1; 
       8 [-]: GETIMPORT R3 1; var3 = 0x7B998233
       9 [-]: CALL R3 0 2  ; var3 = var3(var4, ...)
L 1:  10 [-]: JUMPIFNOT R3 L3; goto L3 if not var3
L 2:  11 [-]: RETURN R0 0  ; 
L 3:  12 [-]: GETIMPORT R3 4; var3 = 0xCBD666E1
      13 [-]: LOADK R4 K5  ; var4 = 0.0099999997764825821
      14 [-]: CALL R3 2 1  ; var3(var4)
      15 [-]: GETIMPORT R3 7; var3 = 0x89326C93
      16 [-]: NAMECALL R3 R3 K8; var4 = var3; var3 = var3[0x7C1A0374]
      17 [-]: CALL R3 2 2  ; var3 = var3(var4)
      18 [-]: NAMECALL R4 R3 K9; var5 = var3; var4 = var3[0x65C7544C]
      19 [-]: CALL R4 2 2  ; var4 = var4(var5)
      20 [-]: LOADN R5 0   ; var5 = 0
      21 [-]: LOADNIL R6   ; var6 = nil
      22 [-]: GETIMPORT R7 11; var7 = _T
      23 [-]: LOADB R8 0   ; var8 = false
      24 [-]: SETTABLEKS R8 R7 K12; var8["InterruptRunningFade"] = var7
L 4:  25 [-]: LOADN R7 1   ; var7 = 1
      26 [-]: JUMPIFNOTLT R5 R7 L6; goto L6 if var5 >= var853793
      27 [-]: GETIMPORT R7 13; var7 = _T["InterruptRunningFade"]
      28 [-]: JUMPIFNOT R7 L5; goto L5 if not var7
      29 [-]: RETURN R0 0  ; 
L 5:  30 [-]: GETIMPORT R7 15; var7 = 0x9BAFFFE3
      31 [-]: MOVE R8 R4   ; var8 = var4
      32 [-]: MOVE R9 R2   ; var9 = var2
      33 [-]: MOVE R10 R5  ; var10 = var5
      34 [-]: CALL R7 4 2  ; var7 = var7(var8, var9, var10)
      35 [-]: MOVE R6 R7   ; var6 = var7
      36 [-]: MOVE R9 R6   ; var9 = var6
      37 [-]: NAMECALL R7 R3 K16; var8 = var3; var7 = var3[0xB6DF3E50]
      38 [-]: CALL R7 3 1  ; var7(var8, var9)
      39 [-]: GETIMPORT R8 18; var8 = 0x67652851
      40 [-]: CALL R8 1 2  ; var8 = var8()
      41 [-]: DIV R7 R8 R1 ; var7 = var8 / var1
      42 [-]: ADD R5 R5 R7 ; var5 = var5 + var7
      43 [-]: GETIMPORT R7 4; var7 = 0xCBD666E1
      44 [-]: LOADN R8 0   ; var8 = 0
      45 [-]: CALL R7 2 1  ; var7(var8)
      46 [-]: JUMPBACK L4  ; goto L4
L 6:  47 [-]: MOVE R9 R2   ; var9 = var2
      48 [-]: NAMECALL R7 R3 K16; var8 = var3; var7 = var3[0xB6DF3E50]
      49 [-]: CALL R7 3 1  ; var7(var8, var9)
      50 [-]: GETIMPORT R7 11; var7 = _T
      51 [-]: LOADNIL R8   ; var8 = nil
      52 [-]: SETTABLEKS R8 R7 K12; var8["InterruptRunningFade"] = var7
      53 [-]: GETIMPORT R7 4; var7 = 0xCBD666E1
      54 [-]: LOADN R8 0   ; var8 = 0
      55 [-]: CALL R7 2 1  ; var7(var8)
      56 [-]: RETURN R0 0  ; 


; Name:            
; Defined at line: 151
; #Upvalues:       0
; #Parameters:     1
; Is_vararg:       0
; Max Stack Size:  8

       0 [-]: FASTCALL1 64 R0 L0; 
       1 [-]: MOVE R2 R0   ; var2 = var0
       2 [-]: GETIMPORT R1 1; var1 = 0x7B998233
       3 [-]: CALL R1 2 2  ; var1 = var1(var2)
L 0:   4 [-]: JUMPIF R1 L2 ; goto L2 if var1
       5 [-]: NAMECALL R1 R0 K2; var2 = var0; var1 = var0[0x055478B1]
       6 [-]: CALL R1 2 2  ; var1 = var1(var2)
       7 [-]: LOADN R2 0   ; var2 = 0
       8 [-]: JUMPIFNOTLT R2 R1 L1; goto L1 if var2 >= var2113929548
       9 [-]: NAMECALL R1 R0 K3; var2 = var0; var1 = var0[0xD016E07E]
      10 [-]: CALL R1 2 1  ; var1(var2)
      11 [-]: GETIMPORT R3 5; var3 = 0xE1BC2F89
      12 [-]: GETIMPORT R4 7; var4 = EMPTY_SYMBOL
      13 [-]: GETIMPORT R5 9; var5 = ZERO_VECTOR
      14 [-]: GETIMPORT R6 11; var6 = ZERO_ROTATION
      15 [-]: MOVE R7 R0   ; var7 = var0
      16 [-]: NAMECALL R1 R0 K12; var2 = var0; var1 = var0[0x47901F07]
      17 [-]: CALL R1 7 1  ; var1(var2, var3, var4, var5, var6, var7)
L 1:  18 [-]: LOADB R3 0   ; var3 = false
      19 [-]: NAMECALL R1 R0 K13; var2 = var0; var1 = var0[0xF5B56484]
      20 [-]: CALL R1 3 1  ; var1(var2, var3)
L 2:  21 [-]: RETURN R0 0  ; 


; Name:            
; Defined at line: 161
; #Upvalues:       0
; #Parameters:     1
; Is_vararg:       0
; Max Stack Size:  6

       0 [-]: GETTABLEKS R3 R0 K0; var3 = var0["levelOverride"]
       1 [-]: FASTCALL1 64 R3 L0; 
       2 [-]: GETIMPORT R2 2; var2 = 0x7B998233
       3 [-]: CALL R2 2 2  ; var2 = var2(var3)
L 0:   4 [-]: NOT R1 R2    ; var1 = not var2
       5 [-]: JUMPIFNOT R1 L4; goto L4 if not var1
       6 [-]: GETTABLEKS R2 R0 K3; var2 = var0["keyChainName"]
       7 [-]: FASTCALL1 64 R2 L1; 
       8 [-]: GETIMPORT R1 2; var1 = 0x7B998233
       9 [-]: CALL R1 2 2  ; var1 = var1(var2)
L 1:  10 [-]: JUMPIFNOT R1 L4; goto L4 if not var1
      11 [-]: GETIMPORT R2 6; var2 = 0x7F5022CF[0xA5C556B9]
      12 [-]: GETTABLEKS R4 R0 K0; var4 = var0["levelOverride"]
      13 [-]: NAMECALL R4 R4 K7; var5 = var4; var4 = var4[0xED4E0128]
      14 [-]: CALL R4 2 0  ; var4, ... = var4(var5)
      15 [-]: FASTCALL 63 L2; 
      16 [-]: GETIMPORT R3 9; var3 = 0x64FB1586
      17 [-]: CALL R3 0 2  ; var3 = var3(var4, ...)
L 2:  18 [-]: LOADK R4 K10 ; var4 = "Entrati"
      19 [-]: CALL R2 3 2  ; var2 = var2(var3, var4)
      20 [-]: JUMPXEQKNIL R2 L3 NOT; 
      21 [-]: LOADB R1 0 +1; var1 = false
L 3:  22 [-]: LOADB R1 1   ; var1 = true
L 4:  23 [-]: JUMPIFNOT R1 L5; goto L5 if not var1
      24 [-]: LOADB R2 1   ; var2 = true
      25 [-]: RETURN R2 1  ; 
L 5:  26 [-]: LOADB R2 0   ; var2 = false
      27 [-]: RETURN R2 1  ; 


; Name:            
; Defined at line: 170
; #Upvalues:       3
; #Parameters:     3
; Is_vararg:       0
; Max Stack Size:  11

       0 [-]: NAMECALL R3 R0 K0; var4 = var0; var3 = var0[0x5B89142C]
       1 [-]: CALL R3 2 2  ; var3 = var3(var4)
       2 [-]: FASTCALL1 64 R3 L0; 
       3 [-]: MOVE R5 R3   ; var5 = var3
       4 [-]: GETIMPORT R4 2; var4 = 0x7B998233
       5 [-]: CALL R4 2 2  ; var4 = var4(var5)
L 0:   6 [-]: JUMPIF R4 L9 ; goto L9 if var4
       7 [-]: NAMECALL R4 R3 K3; var5 = var3; var4 = var3[0x420402A9]
       8 [-]: CALL R4 2 2  ; var4 = var4(var5)
       9 [-]: JUMPIFNOT R4 L9; goto L9 if not var4
      10 [-]: GETIMPORT R5 5; var5 = _T
      11 [-]: LOADB R6 1   ; var6 = true
      12 [-]: SETTABLEKS R6 R5 K6; var6["TeleportAndFadeActive"] = var5
      13 [-]: GETIMPORT R5 8; var5 = 0xBE190284
      14 [-]: FASTCALL1 64 R5 L1; 
      15 [-]: MOVE R7 R5   ; var7 = var5
      16 [-]: GETIMPORT R6 2; var6 = 0x7B998233
      17 [-]: CALL R6 2 2  ; var6 = var6(var7)
L 1:  18 [-]: JUMPIF R6 L2 ; goto L2 if var6
      19 [-]: LOADB R8 1   ; var8 = true
      20 [-]: NAMECALL R6 R5 K9; var7 = var5; var6 = var5[0xC02F2CB8]
      21 [-]: CALL R6 3 1  ; var6(var7, var8)
      22 [-]: GETIMPORT R6 8; var6 = 0xBE190284
      23 [-]: NAMECALL R6 R6 K10; var7 = var6; var6 = var6[0xAEB5AA53]
      24 [-]: CALL R6 2 1  ; var6(var7)
L 2:  25 [-]: GETUPVAL R8 0; var8 = upvalues[0]
      26 [-]: NAMECALL R6 R0 K11; var7 = var0; var6 = var0[0x89F5ABE4]
      27 [-]: CALL R6 3 1  ; var6(var7, var8)
      28 [-]: LOADB R8 0   ; var8 = false
      29 [-]: NAMECALL R6 R0 K12; var7 = var0; var6 = var0[0x2C13654D]
      30 [-]: CALL R6 3 1  ; var6(var7, var8)
      31 [-]: GETIMPORT R8 14; var8 = 0x75FEBF51
      32 [-]: GETUPVAL R9 1; var9 = upvalues[1]
      33 [-]: NAMECALL R6 R0 K15; var7 = var0; var6 = var0[0x47901F07]
      34 [-]: CALL R6 4 1  ; var6(var7, var8, var9)
      35 [-]: GETUPVAL R6 2; var6 = upvalues[2]
      36 [-]: MOVE R7 R0   ; var7 = var0
      37 [-]: LOADK R8 K16 ; var8 = 0.75
      38 [-]: LOADN R9 1   ; var9 = 1
      39 [-]: CALL R6 4 1  ; var6(var7, var8, var9)
      40 [-]: MOVE R8 R1   ; var8 = var1
      41 [-]: MOVE R9 R2   ; var9 = var2
      42 [-]: LOADB R10 1  ; var10 = true
      43 [-]: NAMECALL R6 R0 K17; var7 = var0; var6 = var0[0x589EF1C1]
      44 [-]: CALL R6 5 1  ; var6(var7, var8, var9, var10)
      45 [-]: NAMECALL R6 R0 K18; var7 = var0; var6 = var0[0x283A8730]
      46 [-]: CALL R6 2 1  ; var6(var7)
      47 [-]: FASTCALL1 64 R0 L3; 
      48 [-]: MOVE R7 R0   ; var7 = var0
      49 [-]: GETIMPORT R6 2; var6 = 0x7B998233
      50 [-]: CALL R6 2 2  ; var6 = var6(var7)
L 3:  51 [-]: JUMPIFNOT R6 L4; goto L4 if not var6
      52 [-]: RETURN R0 0  ; 
L 4:  53 [-]: GETIMPORT R6 20; var6 = 0xCBD666E1
      54 [-]: LOADN R7 1   ; var7 = 1
      55 [-]: CALL R6 2 1  ; var6(var7)
      56 [-]: FASTCALL1 64 R0 L5; 
      57 [-]: MOVE R7 R0   ; var7 = var0
      58 [-]: GETIMPORT R6 2; var6 = 0x7B998233
      59 [-]: CALL R6 2 2  ; var6 = var6(var7)
L 5:  60 [-]: JUMPIFNOT R6 L6; goto L6 if not var6
      61 [-]: RETURN R0 0  ; 
L 6:  62 [-]: MOVE R8 R2   ; var8 = var2
      63 [-]: NAMECALL R6 R0 K21; var7 = var0; var6 = var0[0xB41A4158]
      64 [-]: CALL R6 3 1  ; var6(var7, var8)
      65 [-]: NAMECALL R6 R0 K22; var7 = var0; var6 = var0[0x020D4331]
      66 [-]: CALL R6 2 2  ; var6 = var6(var7)
      67 [-]: MOVE R8 R2   ; var8 = var2
      68 [-]: NAMECALL R6 R6 K23; var7 = var6; var6 = var6[0x553549E8]
      69 [-]: CALL R6 3 1  ; var6(var7, var8)
      70 [-]: GETUPVAL R6 2; var6 = upvalues[2]
      71 [-]: MOVE R7 R0   ; var7 = var0
      72 [-]: LOADK R8 K16 ; var8 = 0.75
      73 [-]: LOADN R9 0   ; var9 = 0
      74 [-]: CALL R6 4 1  ; var6(var7, var8, var9)
      75 [-]: GETIMPORT R8 14; var8 = 0x75FEBF51
      76 [-]: GETUPVAL R9 1; var9 = upvalues[1]
      77 [-]: NAMECALL R6 R0 K15; var7 = var0; var6 = var0[0x47901F07]
      78 [-]: CALL R6 4 1  ; var6(var7, var8, var9)
      79 [-]: GETUPVAL R8 0; var8 = upvalues[0]
      80 [-]: NAMECALL R6 R0 K24; var7 = var0; var6 = var0[0xAF7C1D8D]
      81 [-]: CALL R6 3 1  ; var6(var7, var8)
      82 [-]: FASTCALL1 64 R5 L7; 
      83 [-]: MOVE R7 R5   ; var7 = var5
      84 [-]: GETIMPORT R6 2; var6 = 0x7B998233
      85 [-]: CALL R6 2 2  ; var6 = var6(var7)
L 7:  86 [-]: JUMPIF R6 L8 ; goto L8 if var6
      87 [-]: LOADB R8 0   ; var8 = false
      88 [-]: NAMECALL R6 R5 K9; var7 = var5; var6 = var5[0xC02F2CB8]
      89 [-]: CALL R6 3 1  ; var6(var7, var8)
L 8:  90 [-]: GETIMPORT R6 5; var6 = _T
      91 [-]: LOADNIL R7   ; var7 = nil
      92 [-]: SETTABLEKS R7 R6 K6; var7["TeleportAndFadeActive"] = var6
L 9:  93 [-]: RETURN R0 0  ; 


; Name:            
; Defined at line: 218
; #Upvalues:       5
; #Parameters:     1
; Is_vararg:       0
; Max Stack Size:  11

       0 [-]: NAMECALL R1 R0 K0; var2 = var0; var1 = var0[0xED324116]
       1 [-]: CALL R1 2 2  ; var1 = var1(var2)
       2 [-]: FASTCALL1 64 R1 L0; 
       3 [-]: MOVE R3 R1   ; var3 = var1
       4 [-]: GETIMPORT R2 2; var2 = 0x7B998233
       5 [-]: CALL R2 2 2  ; var2 = var2(var3)
L 0:   6 [-]: JUMPIFNOT R2 L1; goto L1 if not var2
       7 [-]: RETURN R0 0  ; 
L 1:   8 [-]: NAMECALL R2 R1 K3; var3 = var1; var2 = var1[0x5B89142C]
       9 [-]: CALL R2 2 2  ; var2 = var2(var3)
      10 [-]: FASTCALL1 64 R2 L2; 
      11 [-]: MOVE R4 R2   ; var4 = var2
      12 [-]: GETIMPORT R3 2; var3 = 0x7B998233
      13 [-]: CALL R3 2 2  ; var3 = var3(var4)
L 2:  14 [-]: JUMPIF R3 L16; goto L16 if var3
      15 [-]: NAMECALL R3 R2 K4; var4 = var2; var3 = var2[0x420402A9]
      16 [-]: CALL R3 2 2  ; var3 = var3(var4)
      17 [-]: JUMPIFNOT R3 L16; goto L16 if not var3
      18 [-]: FASTCALL1 64 R1 L3; 
      19 [-]: MOVE R5 R1   ; var5 = var1
      20 [-]: GETIMPORT R4 2; var4 = 0x7B998233
      21 [-]: CALL R4 2 2  ; var4 = var4(var5)
L 3:  22 [-]: JUMPIF R4 L7 ; goto L7 if var4
      23 [-]: GETIMPORT R6 6; var6 = gLotusOperatorAvatarType
      24 [-]: NAMECALL R4 R1 K7; var5 = var1; var4 = var1[0xF2DEAF69]
      25 [-]: CALL R4 3 2  ; var4 = var4(var5, var6)
      26 [-]: JUMPIFNOT R4 L7; goto L7 if not var4
      27 [-]: NAMECALL R4 R1 K8; var5 = var1; var4 = var1[0xDE321E6F]
      28 [-]: CALL R4 2 2  ; var4 = var4(var5)
      29 [-]: NAMECALL R4 R4 K9; var5 = var4; var4 = var4[0xF7D48EE0]
      30 [-]: CALL R4 2 2  ; var4 = var4(var5)
      31 [-]: FASTCALL1 64 R4 L4; 
      32 [-]: MOVE R6 R4   ; var6 = var4
      33 [-]: GETIMPORT R5 2; var5 = 0x7B998233
      34 [-]: CALL R5 2 2  ; var5 = var5(var6)
L 4:  35 [-]: JUMPIF R5 L6 ; goto L6 if var5
      36 [-]: GETUPVAL R7 0; var7 = upvalues[0]
      37 [-]: NAMECALL R5 R4 K10; var6 = var4; var5 = var4[0x689412A5]
      38 [-]: CALL R5 3 2  ; var5 = var5(var6, var7)
      39 [-]: FASTCALL1 64 R5 L5; 
      40 [-]: MOVE R7 R5   ; var7 = var5
      41 [-]: GETIMPORT R6 2; var6 = 0x7B998233
      42 [-]: CALL R6 2 2  ; var6 = var6(var7)
L 5:  43 [-]: JUMPIF R6 L6 ; goto L6 if var6
      44 [-]: LOADB R8 1   ; var8 = true
      45 [-]: NAMECALL R6 R5 K11; var7 = var5; var6 = var5[0xA74EA8AC]
      46 [-]: CALL R6 3 1  ; var6(var7, var8)
L 6:  47 [-]: LOADB R7 0   ; var7 = false
      48 [-]: NAMECALL R5 R1 K12; var6 = var1; var5 = var1[0x7CD1BACF]
      49 [-]: CALL R5 3 1  ; var5(var6, var7)
L 7:  50 [-]: GETIMPORT R4 14; var4 = _T
      51 [-]: LOADB R5 1   ; var5 = true
      52 [-]: SETTABLEKS R5 R4 K15; var5["TeleportAndFadeActive"] = var4
      53 [-]: GETIMPORT R4 17; var4 = 0xBE190284
      54 [-]: FASTCALL1 64 R4 L8; 
      55 [-]: MOVE R6 R4   ; var6 = var4
      56 [-]: GETIMPORT R5 2; var5 = 0x7B998233
      57 [-]: CALL R5 2 2  ; var5 = var5(var6)
L 8:  58 [-]: JUMPIF R5 L9 ; goto L9 if var5
      59 [-]: LOADB R7 1   ; var7 = true
      60 [-]: NAMECALL R5 R4 K18; var6 = var4; var5 = var4[0xC02F2CB8]
      61 [-]: CALL R5 3 1  ; var5(var6, var7)
      62 [-]: GETIMPORT R5 17; var5 = 0xBE190284
      63 [-]: NAMECALL R5 R5 K19; var6 = var5; var5 = var5[0xAEB5AA53]
      64 [-]: CALL R5 2 1  ; var5(var6)
L 9:  65 [-]: GETUPVAL R7 1; var7 = upvalues[1]
      66 [-]: NAMECALL R5 R1 K20; var6 = var1; var5 = var1[0x89F5ABE4]
      67 [-]: CALL R5 3 1  ; var5(var6, var7)
      68 [-]: LOADB R7 0   ; var7 = false
      69 [-]: NAMECALL R5 R1 K21; var6 = var1; var5 = var1[0x2C13654D]
      70 [-]: CALL R5 3 1  ; var5(var6, var7)
      71 [-]: GETIMPORT R7 23; var7 = 0x75FEBF51
      72 [-]: GETUPVAL R8 2; var8 = upvalues[2]
      73 [-]: NAMECALL R5 R1 K24; var6 = var1; var5 = var1[0x47901F07]
      74 [-]: CALL R5 4 1  ; var5(var6, var7, var8)
      75 [-]: GETUPVAL R5 3; var5 = upvalues[3]
      76 [-]: MOVE R6 R1   ; var6 = var1
      77 [-]: LOADK R7 K25 ; var7 = 0.75
      78 [-]: LOADN R8 1   ; var8 = 1
      79 [-]: CALL R5 4 1  ; var5(var6, var7, var8)
      80 [-]: GETIMPORT R5 27; var5 = 0xCBD666E1
      81 [-]: LOADN R6 1   ; var6 = 1
      82 [-]: CALL R5 2 1  ; var5(var6)
      83 [-]: FASTCALL1 64 R1 L10; 
      84 [-]: MOVE R6 R1   ; var6 = var1
      85 [-]: GETIMPORT R5 2; var5 = 0x7B998233
      86 [-]: CALL R5 2 2  ; var5 = var5(var6)
L10:  87 [-]: JUMPIFNOT R5 L11; goto L11 if not var5
      88 [-]: RETURN R0 0  ; 
L11:  89 [-]: GETUPVAL R5 3; var5 = upvalues[3]
      90 [-]: MOVE R6 R1   ; var6 = var1
      91 [-]: LOADK R7 K25 ; var7 = 0.75
      92 [-]: LOADN R8 0   ; var8 = 0
      93 [-]: CALL R5 4 1  ; var5(var6, var7, var8)
      94 [-]: GETIMPORT R7 23; var7 = 0x75FEBF51
      95 [-]: GETUPVAL R8 2; var8 = upvalues[2]
      96 [-]: NAMECALL R5 R1 K24; var6 = var1; var5 = var1[0x47901F07]
      97 [-]: CALL R5 4 1  ; var5(var6, var7, var8)
      98 [-]: GETUPVAL R7 1; var7 = upvalues[1]
      99 [-]: NAMECALL R5 R1 K28; var6 = var1; var5 = var1[0xAF7C1D8D]
     100 [-]: CALL R5 3 1  ; var5(var6, var7)
     101 [-]: FASTCALL1 64 R4 L12; 
     102 [-]: MOVE R6 R4   ; var6 = var4
     103 [-]: GETIMPORT R5 2; var5 = 0x7B998233
     104 [-]: CALL R5 2 2  ; var5 = var5(var6)
L12: 105 [-]: JUMPIF R5 L13; goto L13 if var5
     106 [-]: LOADB R7 0   ; var7 = false
     107 [-]: NAMECALL R5 R4 K18; var6 = var4; var5 = var4[0xC02F2CB8]
     108 [-]: CALL R5 3 1  ; var5(var6, var7)
L13: 109 [-]: GETIMPORT R5 14; var5 = _T
     110 [-]: LOADNIL R6   ; var6 = nil
     111 [-]: SETTABLEKS R6 R5 K15; var6["TeleportAndFadeActive"] = var5
     112 [-]: GETIMPORT R5 30; var5 = 0x89326C93
     113 [-]: GETIMPORT R7 32; var7 = 0x0469F296
     114 [-]: LOADK R8 K33 ; var8 = "VoidAngelPPVol"
     115 [-]: CALL R7 2 2  ; var7 = var7(var8)
     116 [-]: NAMECALL R8 R1 K34; var9 = var1; var8 = var1[0xD1586535]
     117 [-]: CALL R8 2 2  ; var8 = var8(var9)
     118 [-]: LOADN R9 0   ; var9 = 0
     119 [-]: LOADN R10 100; var10 = 100
     120 [-]: NAMECALL R5 R5 K35; var6 = var5; var5 = var5[0x462C251C]
     121 [-]: CALL R5 6 2  ; var5 = var5(var6, var7, var8, var9, var10)
     122 [-]: FASTCALL1 64 R5 L14; 
     123 [-]: MOVE R7 R5   ; var7 = var5
     124 [-]: GETIMPORT R6 2; var6 = 0x7B998233
     125 [-]: CALL R6 2 2  ; var6 = var6(var7)
L14: 126 [-]: JUMPIF R6 L15; goto L15 if var6
     127 [-]: NAMECALL R6 R5 K36; var7 = var5; var6 = var5[0x383D2E7D]
     128 [-]: CALL R6 2 1  ; var6(var7)
L15: 129 [-]: GETUPVAL R8 4; var8 = upvalues[4]
     130 [-]: NAMECALL R6 R1 K37; var7 = var1; var6 = var1[0xB6FD75DB]
     131 [-]: CALL R6 3 1  ; var6(var7, var8)
     132 [-]: GETIMPORT R8 32; var8 = 0x0469F296
     133 [-]: LOADK R9 K38 ; var9 = "ClientOperatorArenaMonitor"
     134 [-]: CALL R8 2 2  ; var8 = var8(var9)
     135 [-]: LOADB R9 0   ; var9 = false
     136 [-]: NAMECALL R6 R1 K39; var7 = var1; var6 = var1[0xD5F7912B]
     137 [-]: CALL R6 4 1  ; var6(var7, var8, var9)
     138 [-]: NAMECALL R6 R0 K40; var7 = var0; var6 = var0[0xA2880940]
     139 [-]: CALL R6 2 1  ; var6(var7)
L16: 140 [-]: RETURN R0 0  ; 


; Name:            
; Defined at line: 282
; #Upvalues:       6
; #Parameters:     1
; Is_vararg:       0
; Max Stack Size:  12

       0 [-]: NAMECALL R1 R0 K0; var2 = var0; var1 = var0[0xED324116]
       1 [-]: CALL R1 2 2  ; var1 = var1(var2)
       2 [-]: FASTCALL1 64 R1 L0; 
       3 [-]: MOVE R3 R1   ; var3 = var1
       4 [-]: GETIMPORT R2 2; var2 = 0x7B998233
       5 [-]: CALL R2 2 2  ; var2 = var2(var3)
L 0:   6 [-]: JUMPIFNOT R2 L1; goto L1 if not var2
       7 [-]: RETURN R0 0  ; 
L 1:   8 [-]: GETIMPORT R4 4; var4 = gLotusOperatorAvatarType
       9 [-]: NAMECALL R2 R1 K5; var3 = var1; var2 = var1[0xF2DEAF69]
      10 [-]: CALL R2 3 2  ; var2 = var2(var3, var4)
      11 [-]: JUMPIFNOT R2 L2; goto L2 if not var2
      12 [-]: GETUPVAL R2 0; var2 = upvalues[0]
      13 [-]: MOVE R3 R1   ; var3 = var1
      14 [-]: CALL R2 2 1  ; var2(var3)
L 2:  15 [-]: NAMECALL R2 R1 K6; var3 = var1; var2 = var1[0x5B89142C]
      16 [-]: CALL R2 2 2  ; var2 = var2(var3)
      17 [-]: FASTCALL1 64 R2 L3; 
      18 [-]: MOVE R4 R2   ; var4 = var2
      19 [-]: GETIMPORT R3 2; var3 = 0x7B998233
      20 [-]: CALL R3 2 2  ; var3 = var3(var4)
L 3:  21 [-]: JUMPIF R3 L19; goto L19 if var3
      22 [-]: NAMECALL R3 R2 K7; var4 = var2; var3 = var2[0x420402A9]
      23 [-]: CALL R3 2 2  ; var3 = var3(var4)
      24 [-]: JUMPIFNOT R3 L19; goto L19 if not var3
      25 [-]: GETIMPORT R4 9; var4 = _T
      26 [-]: LOADB R5 1   ; var5 = true
      27 [-]: SETTABLEKS R5 R4 K10; var5["TeleportAndFadeActive"] = var4
      28 [-]: GETIMPORT R4 12; var4 = 0x89326C93
      29 [-]: GETIMPORT R6 14; var6 = 0x0469F296
      30 [-]: LOADK R7 K15 ; var7 = "VoidAngelPPVol"
      31 [-]: CALL R6 2 2  ; var6 = var6(var7)
      32 [-]: NAMECALL R7 R1 K16; var8 = var1; var7 = var1[0xD1586535]
      33 [-]: CALL R7 2 2  ; var7 = var7(var8)
      34 [-]: LOADN R8 0   ; var8 = 0
      35 [-]: LOADN R9 100 ; var9 = 100
      36 [-]: NAMECALL R4 R4 K17; var5 = var4; var4 = var4[0x462C251C]
      37 [-]: CALL R4 6 2  ; var4 = var4(var5, var6, var7, var8, var9)
      38 [-]: FASTCALL1 64 R4 L4; 
      39 [-]: MOVE R6 R4   ; var6 = var4
      40 [-]: GETIMPORT R5 2; var5 = 0x7B998233
      41 [-]: CALL R5 2 2  ; var5 = var5(var6)
L 4:  42 [-]: JUMPIF R5 L5 ; goto L5 if var5
      43 [-]: NAMECALL R5 R4 K18; var6 = var4; var5 = var4[0xF4E253B6]
      44 [-]: CALL R5 2 1  ; var5(var6)
L 5:  45 [-]: GETIMPORT R5 20; var5 = 0xBE190284
      46 [-]: FASTCALL1 64 R5 L6; 
      47 [-]: MOVE R7 R5   ; var7 = var5
      48 [-]: GETIMPORT R6 2; var6 = 0x7B998233
      49 [-]: CALL R6 2 2  ; var6 = var6(var7)
L 6:  50 [-]: JUMPIF R6 L7 ; goto L7 if var6
      51 [-]: LOADB R8 1   ; var8 = true
      52 [-]: NAMECALL R6 R5 K21; var7 = var5; var6 = var5[0xC02F2CB8]
      53 [-]: CALL R6 3 1  ; var6(var7, var8)
      54 [-]: GETIMPORT R6 20; var6 = 0xBE190284
      55 [-]: NAMECALL R6 R6 K22; var7 = var6; var6 = var6[0xAEB5AA53]
      56 [-]: CALL R6 2 1  ; var6(var7)
L 7:  57 [-]: GETUPVAL R8 1; var8 = upvalues[1]
      58 [-]: NAMECALL R6 R1 K23; var7 = var1; var6 = var1[0x89F5ABE4]
      59 [-]: CALL R6 3 1  ; var6(var7, var8)
      60 [-]: LOADB R8 0   ; var8 = false
      61 [-]: NAMECALL R6 R1 K24; var7 = var1; var6 = var1[0x2C13654D]
      62 [-]: CALL R6 3 1  ; var6(var7, var8)
      63 [-]: GETIMPORT R8 26; var8 = 0x75FEBF51
      64 [-]: GETUPVAL R9 2; var9 = upvalues[2]
      65 [-]: NAMECALL R6 R1 K27; var7 = var1; var6 = var1[0x47901F07]
      66 [-]: CALL R6 4 1  ; var6(var7, var8, var9)
      67 [-]: GETUPVAL R6 3; var6 = upvalues[3]
      68 [-]: MOVE R7 R1   ; var7 = var1
      69 [-]: LOADK R8 K28 ; var8 = 0.75
      70 [-]: LOADN R9 1   ; var9 = 1
      71 [-]: CALL R6 4 1  ; var6(var7, var8, var9)
      72 [-]: GETIMPORT R6 30; var6 = 0xCBD666E1
      73 [-]: LOADN R7 1   ; var7 = 1
      74 [-]: CALL R6 2 1  ; var6(var7)
      75 [-]: FASTCALL1 64 R1 L8; 
      76 [-]: MOVE R7 R1   ; var7 = var1
      77 [-]: GETIMPORT R6 2; var6 = 0x7B998233
      78 [-]: CALL R6 2 2  ; var6 = var6(var7)
L 8:  79 [-]: JUMPIFNOT R6 L9; goto L9 if not var6
      80 [-]: RETURN R0 0  ; 
L 9:  81 [-]: GETUPVAL R6 3; var6 = upvalues[3]
      82 [-]: MOVE R7 R1   ; var7 = var1
      83 [-]: LOADK R8 K28 ; var8 = 0.75
      84 [-]: LOADN R9 0   ; var9 = 0
      85 [-]: CALL R6 4 1  ; var6(var7, var8, var9)
      86 [-]: GETIMPORT R8 26; var8 = 0x75FEBF51
      87 [-]: GETUPVAL R9 2; var9 = upvalues[2]
      88 [-]: NAMECALL R6 R1 K27; var7 = var1; var6 = var1[0x47901F07]
      89 [-]: CALL R6 4 1  ; var6(var7, var8, var9)
      90 [-]: GETUPVAL R8 1; var8 = upvalues[1]
      91 [-]: NAMECALL R6 R1 K31; var7 = var1; var6 = var1[0xAF7C1D8D]
      92 [-]: CALL R6 3 1  ; var6(var7, var8)
      93 [-]: FASTCALL1 64 R5 L10; 
      94 [-]: MOVE R7 R5   ; var7 = var5
      95 [-]: GETIMPORT R6 2; var6 = 0x7B998233
      96 [-]: CALL R6 2 2  ; var6 = var6(var7)
L10:  97 [-]: JUMPIF R6 L11; goto L11 if var6
      98 [-]: LOADB R8 0   ; var8 = false
      99 [-]: NAMECALL R6 R5 K21; var7 = var5; var6 = var5[0xC02F2CB8]
     100 [-]: CALL R6 3 1  ; var6(var7, var8)
L11: 101 [-]: GETIMPORT R6 9; var6 = _T
     102 [-]: LOADNIL R7   ; var7 = nil
     103 [-]: SETTABLEKS R7 R6 K10; var7["TeleportAndFadeActive"] = var6
     104 [-]: GETUPVAL R8 4; var8 = upvalues[4]
     105 [-]: NAMECALL R6 R1 K32; var7 = var1; var6 = var1[0xA3A0F1C2]
     106 [-]: CALL R6 3 1  ; var6(var7, var8)
     107 [-]: MOVE R6 R1   ; var6 = var1
     108 [-]: FASTCALL1 64 R6 L12; 
     109 [-]: MOVE R8 R6   ; var8 = var6
     110 [-]: GETIMPORT R7 2; var7 = 0x7B998233
     111 [-]: CALL R7 2 2  ; var7 = var7(var8)
L12: 112 [-]: JUMPIF R7 L13; goto L13 if var7
     113 [-]: GETIMPORT R9 4; var9 = gLotusOperatorAvatarType
     114 [-]: NAMECALL R7 R6 K5; var8 = var6; var7 = var6[0xF2DEAF69]
     115 [-]: CALL R7 3 2  ; var7 = var7(var8, var9)
     116 [-]: JUMPIF R7 L13; goto L13 if var7
     117 [-]: NAMECALL R7 R2 K33; var8 = var2; var7 = var2[0x5578D98B]
     118 [-]: CALL R7 2 2  ; var7 = var7(var8)
     119 [-]: MOVE R6 R7   ; var6 = var7
L13: 120 [-]: FASTCALL1 64 R6 L14; 
     121 [-]: MOVE R8 R6   ; var8 = var6
     122 [-]: GETIMPORT R7 2; var7 = 0x7B998233
     123 [-]: CALL R7 2 2  ; var7 = var7(var8)
L14: 124 [-]: JUMPIF R7 L18; goto L18 if var7
     125 [-]: GETIMPORT R9 4; var9 = gLotusOperatorAvatarType
     126 [-]: NAMECALL R7 R6 K5; var8 = var6; var7 = var6[0xF2DEAF69]
     127 [-]: CALL R7 3 2  ; var7 = var7(var8, var9)
     128 [-]: JUMPIFNOT R7 L18; goto L18 if not var7
     129 [-]: NAMECALL R7 R6 K34; var8 = var6; var7 = var6[0xDE321E6F]
     130 [-]: CALL R7 2 2  ; var7 = var7(var8)
     131 [-]: NAMECALL R7 R7 K35; var8 = var7; var7 = var7[0xF7D48EE0]
     132 [-]: CALL R7 2 2  ; var7 = var7(var8)
     133 [-]: FASTCALL1 64 R7 L15; 
     134 [-]: MOVE R9 R7   ; var9 = var7
     135 [-]: GETIMPORT R8 2; var8 = 0x7B998233
     136 [-]: CALL R8 2 2  ; var8 = var8(var9)
L15: 137 [-]: JUMPIF R8 L17; goto L17 if var8
     138 [-]: GETUPVAL R10 5; var10 = upvalues[5]
     139 [-]: NAMECALL R8 R7 K36; var9 = var7; var8 = var7[0x689412A5]
     140 [-]: CALL R8 3 2  ; var8 = var8(var9, var10)
     141 [-]: FASTCALL1 64 R8 L16; 
     142 [-]: MOVE R10 R8  ; var10 = var8
     143 [-]: GETIMPORT R9 2; var9 = 0x7B998233
     144 [-]: CALL R9 2 2  ; var9 = var9(var10)
L16: 145 [-]: JUMPIF R9 L17; goto L17 if var9
     146 [-]: NAMECALL R9 R8 K37; var10 = var8; var9 = var8[0x30F46140]
     147 [-]: CALL R9 2 2  ; var9 = var9(var10)
     148 [-]: JUMPIFNOT R9 L17; goto L17 if not var9
     149 [-]: LOADB R11 0  ; var11 = false
     150 [-]: NAMECALL R9 R8 K38; var10 = var8; var9 = var8[0xA74EA8AC]
     151 [-]: CALL R9 3 1  ; var9(var10, var11)
L17: 152 [-]: GETUPVAL R8 0; var8 = upvalues[0]
     153 [-]: MOVE R9 R6   ; var9 = var6
     154 [-]: CALL R8 2 1  ; var8(var9)
     155 [-]: LOADB R10 1  ; var10 = true
     156 [-]: NAMECALL R8 R6 K39; var9 = var6; var8 = var6[0x7CD1BACF]
     157 [-]: CALL R8 3 1  ; var8(var9, var10)
L18: 158 [-]: NAMECALL R7 R0 K40; var8 = var0; var7 = var0[0xA2880940]
     159 [-]: CALL R7 2 1  ; var7(var8)
L19: 160 [-]: RETURN R0 0  ; 


; Name:            
; Defined at line: 356
; #Upvalues:       10
; #Parameters:     3
; Is_vararg:       0
; Max Stack Size:  15

       0 [-]: NAMECALL R3 R0 K0; var4 = var0; var3 = var0[0x388577D5]
       1 [-]: CALL R3 2 2  ; var3 = var3(var4)
       2 [-]: GETUPVAL R5 0; var5 = upvalues[0]
       3 [-]: GETTABLEKS R4 R5 K1; var4 = var5[0x2DF8B2BA]
       4 [-]: GETIMPORT R5 3; var5 = 0x0469F296
       5 [-]: LOADK R6 K4  ; var6 = "VoidArenaPlayerSpawn"
       6 [-]: CALL R5 2 2  ; var5 = var5(var6)
       7 [-]: MOVE R6 R1   ; var6 = var1
       8 [-]: CALL R4 3 2  ; var4 = var4(var5, var6)
       9 [-]: FASTCALL1 64 R4 L0; 
      10 [-]: MOVE R6 R4   ; var6 = var4
      11 [-]: GETIMPORT R5 6; var5 = 0x7B998233
      12 [-]: CALL R5 2 2  ; var5 = var5(var6)
L 0:  13 [-]: JUMPIFNOT R5 L1; goto L1 if not var5
      14 [-]: RETURN R0 0  ; 
L 1:  15 [-]: NAMECALL R5 R2 K7; var6 = var2; var5 = var2[0xDE321E6F]
      16 [-]: CALL R5 2 2  ; var5 = var5(var6)
      17 [-]: FASTCALL1 64 R5 L2; 
      18 [-]: MOVE R7 R5   ; var7 = var5
      19 [-]: GETIMPORT R6 6; var6 = 0x7B998233
      20 [-]: CALL R6 2 2  ; var6 = var6(var7)
L 2:  21 [-]: JUMPIF R6 L3 ; goto L3 if var6
      22 [-]: GETIMPORT R8 9; var8 = gLotusInventoryControllerType
      23 [-]: NAMECALL R6 R5 K10; var7 = var5; var6 = var5[0xF2DEAF69]
      24 [-]: CALL R6 3 2  ; var6 = var6(var7, var8)
      25 [-]: JUMPIFNOT R6 L3; goto L3 if not var6
      26 [-]: GETIMPORT R6 12; var6 = 0x89326C93
      27 [-]: NAMECALL R6 R6 K13; var7 = var6; var6 = var6[0x18D05D30]
      28 [-]: CALL R6 2 2  ; var6 = var6(var7)
      29 [-]: JUMPIFNOT R6 L3; goto L3 if not var6
      30 [-]: NAMECALL R6 R5 K14; var7 = var5; var6 = var5[0xC4F3A35F]
      31 [-]: CALL R6 2 1  ; var6(var7)
L 3:  32 [-]: GETIMPORT R8 16; var8 = gLotusVehicleAvatarType
      33 [-]: NAMECALL R6 R2 K10; var7 = var2; var6 = var2[0xF2DEAF69]
      34 [-]: CALL R6 3 2  ; var6 = var6(var7, var8)
      35 [-]: JUMPIFNOT R6 L6; goto L6 if not var6
      36 [-]: NAMECALL R6 R2 K17; var7 = var2; var6 = var2[0xFF005826]
      37 [-]: CALL R6 2 2  ; var6 = var6(var7)
      38 [-]: FASTCALL1 64 R6 L4; 
      39 [-]: MOVE R8 R6   ; var8 = var6
      40 [-]: GETIMPORT R7 6; var7 = 0x7B998233
      41 [-]: CALL R7 2 2  ; var7 = var7(var8)
L 4:  42 [-]: JUMPIF R7 L6 ; goto L6 if var7
      43 [-]: GETIMPORT R9 19; var9 = gBaseAvatarType
      44 [-]: NAMECALL R7 R6 K10; var8 = var6; var7 = var6[0xF2DEAF69]
      45 [-]: CALL R7 3 2  ; var7 = var7(var8, var9)
      46 [-]: JUMPIFNOT R7 L6; goto L6 if not var7
      47 [-]: NAMECALL R7 R6 K7; var8 = var6; var7 = var6[0xDE321E6F]
      48 [-]: CALL R7 2 2  ; var7 = var7(var8)
      49 [-]: FASTCALL1 64 R7 L5; 
      50 [-]: MOVE R9 R7   ; var9 = var7
      51 [-]: GETIMPORT R8 6; var8 = 0x7B998233
      52 [-]: CALL R8 2 2  ; var8 = var8(var9)
L 5:  53 [-]: JUMPIF R8 L6 ; goto L6 if var8
      54 [-]: GETIMPORT R10 9; var10 = gLotusInventoryControllerType
      55 [-]: NAMECALL R8 R7 K10; var9 = var7; var8 = var7[0xF2DEAF69]
      56 [-]: CALL R8 3 2  ; var8 = var8(var9, var10)
      57 [-]: JUMPIFNOT R8 L6; goto L6 if not var8
      58 [-]: GETIMPORT R8 12; var8 = 0x89326C93
      59 [-]: NAMECALL R8 R8 K13; var9 = var8; var8 = var8[0x18D05D30]
      60 [-]: CALL R8 2 2  ; var8 = var8(var9)
      61 [-]: JUMPIFNOT R8 L6; goto L6 if not var8
      62 [-]: NAMECALL R8 R7 K14; var9 = var7; var8 = var7[0xC4F3A35F]
      63 [-]: CALL R8 2 1  ; var8(var9)
L 6:  64 [-]: NAMECALL R6 R2 K20; var7 = var2; var6 = var2[0x5E651723]
      65 [-]: CALL R6 2 2  ; var6 = var6(var7)
      66 [-]: GETIMPORT R9 22; var9 = gLotusOperatorAvatarType
      67 [-]: NAMECALL R7 R2 K10; var8 = var2; var7 = var2[0xF2DEAF69]
      68 [-]: CALL R7 3 2  ; var7 = var7(var8, var9)
      69 [-]: JUMPIF R7 L12; goto L12 if var7
      70 [-]: NAMECALL R7 R2 K23; var8 = var2; var7 = var2[0x18F03C5D]
      71 [-]: CALL R7 2 1  ; var7(var8)
L 7:  72 [-]: FASTCALL1 64 R2 L8; 
      73 [-]: MOVE R8 R2   ; var8 = var2
      74 [-]: GETIMPORT R7 6; var7 = 0x7B998233
      75 [-]: CALL R7 2 2  ; var7 = var7(var8)
L 8:  76 [-]: JUMPIF R7 L9 ; goto L9 if var7
      77 [-]: NAMECALL R7 R2 K24; var8 = var2; var7 = var2[0x449C4562]
      78 [-]: CALL R7 2 2  ; var7 = var7(var8)
      79 [-]: JUMPIFNOT R7 L9; goto L9 if not var7
      80 [-]: GETIMPORT R7 26; var7 = 0xCBD666E1
      81 [-]: LOADN R8 0   ; var8 = 0
      82 [-]: CALL R7 2 1  ; var7(var8)
      83 [-]: JUMPBACK L7  ; goto L7
L 9:  84 [-]: FASTCALL1 64 R6 L10; 
      85 [-]: MOVE R8 R6   ; var8 = var6
      86 [-]: GETIMPORT R7 6; var7 = 0x7B998233
      87 [-]: CALL R7 2 2  ; var7 = var7(var8)
L10:  88 [-]: JUMPIFNOT R7 L11; goto L11 if not var7
      89 [-]: RETURN R0 0  ; 
L11:  90 [-]: NAMECALL R7 R6 K27; var8 = var6; var7 = var6[0xBB610E5B]
      91 [-]: CALL R7 2 2  ; var7 = var7(var8)
      92 [-]: MOVE R2 R7   ; var2 = var7
L12:  93 [-]: GETIMPORT R10 30; var10 = _T["VoidAngels"]
      94 [-]: GETTABLE R9 R10 R3; var9 = var10[var3]
      95 [-]: GETTABLEKS R8 R9 K31; var8 = var9["activePlayers"]
      96 [-]: FASTCALL2 52 R8 R2 L13; 
      97 [-]: MOVE R9 R2   ; var9 = var2
      98 [-]: GETIMPORT R7 34; var7 = 0x33BDD652[0x23D5322F]
      99 [-]: CALL R7 3 1  ; var7(var8, var9)
L13: 100 [-]: GETIMPORT R9 36; var9 = 0x3A5FD321
     101 [-]: LOADB R10 0  ; var10 = false
     102 [-]: NAMECALL R7 R2 K37; var8 = var2; var7 = var2[0x659D451F]
     103 [-]: CALL R7 4 1  ; var7(var8, var9, var10)
     104 [-]: NAMECALL R7 R2 K38; var8 = var2; var7 = var2[0x5B89142C]
     105 [-]: CALL R7 2 2  ; var7 = var7(var8)
     106 [-]: MOVE R6 R7   ; var6 = var7
     107 [-]: FASTCALL1 64 R6 L14; 
     108 [-]: MOVE R8 R6   ; var8 = var6
     109 [-]: GETIMPORT R7 6; var7 = 0x7B998233
     110 [-]: CALL R7 2 2  ; var7 = var7(var8)
L14: 111 [-]: JUMPIF R7 L24; goto L24 if var7
     112 [-]: NAMECALL R7 R6 K39; var8 = var6; var7 = var6[0x420402A9]
     113 [-]: CALL R7 2 2  ; var7 = var7(var8)
     114 [-]: JUMPIFNOT R7 L22; goto L22 if not var7
     115 [-]: FASTCALL1 64 R2 L15; 
     116 [-]: MOVE R9 R2   ; var9 = var2
     117 [-]: GETIMPORT R8 6; var8 = 0x7B998233
     118 [-]: CALL R8 2 2  ; var8 = var8(var9)
L15: 119 [-]: JUMPIF R8 L19; goto L19 if var8
     120 [-]: GETIMPORT R10 22; var10 = gLotusOperatorAvatarType
     121 [-]: NAMECALL R8 R2 K10; var9 = var2; var8 = var2[0xF2DEAF69]
     122 [-]: CALL R8 3 2  ; var8 = var8(var9, var10)
     123 [-]: JUMPIFNOT R8 L19; goto L19 if not var8
     124 [-]: NAMECALL R8 R2 K7; var9 = var2; var8 = var2[0xDE321E6F]
     125 [-]: CALL R8 2 2  ; var8 = var8(var9)
     126 [-]: NAMECALL R8 R8 K40; var9 = var8; var8 = var8[0xF7D48EE0]
     127 [-]: CALL R8 2 2  ; var8 = var8(var9)
     128 [-]: FASTCALL1 64 R8 L16; 
     129 [-]: MOVE R10 R8  ; var10 = var8
     130 [-]: GETIMPORT R9 6; var9 = 0x7B998233
     131 [-]: CALL R9 2 2  ; var9 = var9(var10)
L16: 132 [-]: JUMPIF R9 L18; goto L18 if var9
     133 [-]: GETUPVAL R11 1; var11 = upvalues[1]
     134 [-]: NAMECALL R9 R8 K41; var10 = var8; var9 = var8[0x689412A5]
     135 [-]: CALL R9 3 2  ; var9 = var9(var10, var11)
     136 [-]: FASTCALL1 64 R9 L17; 
     137 [-]: MOVE R11 R9  ; var11 = var9
     138 [-]: GETIMPORT R10 6; var10 = 0x7B998233
     139 [-]: CALL R10 2 2 ; var10 = var10(var11)
L17: 140 [-]: JUMPIF R10 L18; goto L18 if var10
     141 [-]: LOADB R12 1  ; var12 = true
     142 [-]: NAMECALL R10 R9 K42; var11 = var9; var10 = var9[0xA74EA8AC]
     143 [-]: CALL R10 3 1 ; var10(var11, var12)
L18: 144 [-]: LOADB R11 0  ; var11 = false
     145 [-]: NAMECALL R9 R2 K43; var10 = var2; var9 = var2[0xF5B56484]
     146 [-]: CALL R9 3 1  ; var9(var10, var11)
     147 [-]: LOADB R11 0  ; var11 = false
     148 [-]: NAMECALL R9 R2 K44; var10 = var2; var9 = var2[0x7CD1BACF]
     149 [-]: CALL R9 3 1  ; var9(var10, var11)
L19: 150 [-]: GETIMPORT R8 12; var8 = 0x89326C93
     151 [-]: GETIMPORT R10 3; var10 = 0x0469F296
     152 [-]: LOADK R11 K45; var11 = "VoidAngelPPVol"
     153 [-]: CALL R10 2 2 ; var10 = var10(var11)
     154 [-]: NAMECALL R11 R4 K46; var12 = var4; var11 = var4[0xD1586535]
     155 [-]: CALL R11 2 2 ; var11 = var11(var12)
     156 [-]: LOADN R12 0  ; var12 = 0
     157 [-]: LOADN R13 100; var13 = 100
     158 [-]: NAMECALL R8 R8 K47; var9 = var8; var8 = var8[0x462C251C]
     159 [-]: CALL R8 6 2  ; var8 = var8(var9, var10, var11, var12, var13)
     160 [-]: FASTCALL1 64 R8 L20; 
     161 [-]: MOVE R10 R8  ; var10 = var8
     162 [-]: GETIMPORT R9 6; var9 = 0x7B998233
     163 [-]: CALL R9 2 2  ; var9 = var9(var10)
L20: 164 [-]: JUMPIF R9 L21; goto L21 if var9
     165 [-]: NAMECALL R9 R8 K48; var10 = var8; var9 = var8[0x383D2E7D]
     166 [-]: CALL R9 2 1  ; var9(var10)
L21: 167 [-]: GETUPVAL R9 2; var9 = upvalues[2]
     168 [-]: MOVE R10 R2  ; var10 = var2
     169 [-]: NAMECALL R11 R4 K46; var12 = var4; var11 = var4[0xD1586535]
     170 [-]: CALL R11 2 2 ; var11 = var11(var12)
     171 [-]: NAMECALL R12 R4 K49; var13 = var4; var12 = var4[0xCB3851B8]
     172 [-]: CALL R12 2 0 ; var12, ... = var12(var13)
     173 [-]: CALL R9 0 1  ; var9(var10, ...)
     174 [-]: JUMP L24     ; goto L24
L22: 175 [-]: GETIMPORT R8 12; var8 = 0x89326C93
     176 [-]: NAMECALL R8 R8 K13; var9 = var8; var8 = var8[0x18D05D30]
     177 [-]: CALL R8 2 2  ; var8 = var8(var9)
     178 [-]: JUMPIFNOT R8 L24; goto L24 if not var8
     179 [-]: GETIMPORT R10 51; var10 = 0x43930D9D
     180 [-]: GETIMPORT R11 53; var11 = EMPTY_SYMBOL
     181 [-]: GETIMPORT R12 55; var12 = ZERO_VECTOR
     182 [-]: GETIMPORT R13 57; var13 = ZERO_ROTATION
     183 [-]: MOVE R14 R2  ; var14 = var2
     184 [-]: NAMECALL R8 R2 K58; var9 = var2; var8 = var2[0x47901F07]
     185 [-]: CALL R8 7 1  ; var8(var9, var10, var11, var12, var13, var14)
     186 [-]: GETIMPORT R8 26; var8 = 0xCBD666E1
     187 [-]: LOADK R9 K59 ; var9 = 0.75
     188 [-]: CALL R8 2 1  ; var8(var9)
     189 [-]: FASTCALL1 64 R2 L23; 
     190 [-]: MOVE R9 R2   ; var9 = var2
     191 [-]: GETIMPORT R8 6; var8 = 0x7B998233
     192 [-]: CALL R8 2 2  ; var8 = var8(var9)
L23: 193 [-]: JUMPIF R8 L24; goto L24 if var8
     194 [-]: NAMECALL R10 R4 K46; var11 = var4; var10 = var4[0xD1586535]
     195 [-]: CALL R10 2 2 ; var10 = var10(var11)
     196 [-]: NAMECALL R11 R4 K49; var12 = var4; var11 = var4[0xCB3851B8]
     197 [-]: CALL R11 2 2 ; var11 = var11(var12)
     198 [-]: LOADB R12 1  ; var12 = true
     199 [-]: NAMECALL R8 R2 K60; var9 = var2; var8 = var2[0x589EF1C1]
     200 [-]: CALL R8 5 1  ; var8(var9, var10, var11, var12)
     201 [-]: NAMECALL R8 R2 K61; var9 = var2; var8 = var2[0x283A8730]
     202 [-]: CALL R8 2 1  ; var8(var9)
L24: 203 [-]: NAMECALL R7 R2 K62; var8 = var2; var7 = var2[0x1AC1655C]
     204 [-]: CALL R7 2 2  ; var7 = var7(var8)
     205 [-]: FASTCALL1 64 R7 L25; 
     206 [-]: MOVE R9 R7   ; var9 = var7
     207 [-]: GETIMPORT R8 6; var8 = 0x7B998233
     208 [-]: CALL R8 2 2  ; var8 = var8(var9)
L25: 209 [-]: JUMPIF R8 L27; goto L27 if var8
     210 [-]: NAMECALL R8 R7 K63; var9 = var7; var8 = var7[0x3DF4C10F]
     211 [-]: CALL R8 2 2  ; var8 = var8(var9)
     212 [-]: JUMPIFNOT R8 L26; goto L26 if not var8
     213 [-]: GETIMPORT R10 65; var10 = 0x8942B94A
     214 [-]: NAMECALL R8 R7 K66; var9 = var7; var8 = var7[0x897990EF]
     215 [-]: CALL R8 3 1  ; var8(var9, var10)
     216 [-]: JUMP L27     ; goto L27
L26: 217 [-]: GETIMPORT R10 65; var10 = 0x8942B94A
     218 [-]: GETIMPORT R11 65; var11 = 0x8942B94A
     219 [-]: NAMECALL R8 R7 K67; var9 = var7; var8 = var7[0x4A9DA24C]
     220 [-]: CALL R8 4 1  ; var8(var9, var10, var11)
L27: 221 [-]: FASTCALL1 64 R2 L28; 
     222 [-]: MOVE R9 R2   ; var9 = var2
     223 [-]: GETIMPORT R8 6; var8 = 0x7B998233
     224 [-]: CALL R8 2 2  ; var8 = var8(var9)
L28: 225 [-]: JUMPIF R8 L29; goto L29 if var8
     226 [-]: GETUPVAL R10 3; var10 = upvalues[3]
     227 [-]: NAMECALL R8 R2 K68; var9 = var2; var8 = var2[0x08DB51DE]
     228 [-]: CALL R8 3 2  ; var8 = var8(var9, var10)
     229 [-]: JUMPIF R8 L29; goto L29 if var8
     230 [-]: GETUPVAL R10 3; var10 = upvalues[3]
     231 [-]: NAMECALL R8 R2 K69; var9 = var2; var8 = var2[0xB6FD75DB]
     232 [-]: CALL R8 3 1  ; var8(var9, var10)
     233 [-]: GETIMPORT R10 3; var10 = 0x0469F296
     234 [-]: LOADK R11 K70; var11 = "OperatorArenaMonitor"
     235 [-]: CALL R10 2 2 ; var10 = var10(var11)
     236 [-]: LOADB R11 0  ; var11 = false
     237 [-]: NAMECALL R8 R2 K71; var9 = var2; var8 = var2[0xD5F7912B]
     238 [-]: CALL R8 4 1  ; var8(var9, var10, var11)
L29: 239 [-]: GETUPVAL R8 4; var8 = upvalues[4]
     240 [-]: JUMPIF R8 L32; goto L32 if var8
     241 [-]: GETUPVAL R8 5; var8 = upvalues[5]
     242 [-]: JUMPIFNOT R8 L30; goto L30 if not var8
     243 [-]: GETUPVAL R8 6; var8 = upvalues[6]
     244 [-]: GETUPVAL R9 7; var9 = upvalues[7]
     245 [-]: JUMPIF R9 L31; goto L31 if var9
     246 [-]: GETUPVAL R10 8; var10 = upvalues[8]
     247 [-]: GETTABLEKS R9 R10 K72; var9 = var10[0x9742B85B]
     248 [-]: GETIMPORT R10 74; var10 = 0x4430F697
     249 [-]: MOVE R11 R8  ; var11 = var8
     250 [-]: CALL R9 3 1  ; var9(var10, var11)
     251 [-]: JUMP L31     ; goto L31
L30: 252 [-]: GETUPVAL R8 9; var8 = upvalues[9]
     253 [-]: GETUPVAL R9 7; var9 = upvalues[7]
     254 [-]: JUMPIF R9 L31; goto L31 if var9
     255 [-]: GETUPVAL R10 8; var10 = upvalues[8]
     256 [-]: GETTABLEKS R9 R10 K72; var9 = var10[0x9742B85B]
     257 [-]: GETIMPORT R10 74; var10 = 0x4430F697
     258 [-]: MOVE R11 R8  ; var11 = var8
     259 [-]: CALL R9 3 1  ; var9(var10, var11)
L31: 260 [-]: LOADB R8 1   ; var8 = true
     261 [-]: SETUPVAL R8 4; upvalues[8] = var4
L32: 262 [-]: RETURN R0 0  ; 


; Name:            
; Defined at line: 455
; #Upvalues:       5
; #Parameters:     2
; Is_vararg:       0
; Max Stack Size:  14

       0 [-]: GETIMPORT R2 1; var2 = 0x89326C93
       1 [-]: NAMECALL R2 R2 K2; var3 = var2; var2 = var2[0x29EF273D]
       2 [-]: CALL R2 2 2  ; var2 = var2(var3)
       3 [-]: NAMECALL R2 R2 K3; var3 = var2; var2 = var2[0x66905CB0]
       4 [-]: CALL R2 2 2  ; var2 = var2(var3)
       5 [-]: NAMECALL R5 R1 K4; var6 = var1; var5 = var1[0xF6EBD926]
       6 [-]: CALL R5 2 2  ; var5 = var5(var6)
       7 [-]: LOADN R6 4   ; var6 = 4
       8 [-]: LOADN R7 10  ; var7 = 10
       9 [-]: LOADB R8 1   ; var8 = true
      10 [-]: LOADN R9 3   ; var9 = 3
      11 [-]: NAMECALL R3 R2 K5; var4 = var2; var3 = var2[0x96930263]
      12 [-]: CALL R3 7 2  ; var3 = var3(var4, var5, var6, var7, var8, var9)
      13 [-]: MOVE R6 R3   ; var6 = var3
      14 [-]: NAMECALL R4 R2 K6; var5 = var2; var4 = var2[0x0E8C38E5]
      15 [-]: CALL R4 3 2  ; var4 = var4(var5, var6)
      16 [-]: MOVE R3 R4   ; var3 = var4
      17 [-]: FASTCALL1 64 R0 L0; 
      18 [-]: MOVE R5 R0   ; var5 = var0
      19 [-]: GETIMPORT R4 8; var4 = 0x7B998233
      20 [-]: CALL R4 2 2  ; var4 = var4(var5)
L 0:  21 [-]: JUMPIF R4 L1 ; goto L1 if var4
      22 [-]: GETIMPORT R6 10; var6 = 0x7EEE9E23
      23 [-]: LOADB R7 0   ; var7 = false
      24 [-]: NAMECALL R4 R0 K11; var5 = var0; var4 = var0[0x659D451F]
      25 [-]: CALL R4 4 1  ; var4(var5, var6, var7)
L 1:  26 [-]: NAMECALL R4 R0 K12; var5 = var0; var4 = var0[0x5E651723]
      27 [-]: CALL R4 2 2  ; var4 = var4(var5)
      28 [-]: FASTCALL1 64 R4 L2; 
      29 [-]: MOVE R6 R4   ; var6 = var4
      30 [-]: GETIMPORT R5 8; var5 = 0x7B998233
      31 [-]: CALL R5 2 2  ; var5 = var5(var6)
L 2:  32 [-]: JUMPIF R5 L13; goto L13 if var5
      33 [-]: NAMECALL R5 R4 K13; var6 = var4; var5 = var4[0x420402A9]
      34 [-]: CALL R5 2 2  ; var5 = var5(var6)
      35 [-]: JUMPIFNOT R5 L11; goto L11 if not var5
      36 [-]: GETIMPORT R6 1; var6 = 0x89326C93
      37 [-]: GETIMPORT R8 15; var8 = 0x0469F296
      38 [-]: LOADK R9 K16 ; var9 = "VoidAngelPPVol"
      39 [-]: CALL R8 2 2  ; var8 = var8(var9)
      40 [-]: NAMECALL R9 R0 K17; var10 = var0; var9 = var0[0xD1586535]
      41 [-]: CALL R9 2 2  ; var9 = var9(var10)
      42 [-]: LOADN R10 0  ; var10 = 0
      43 [-]: LOADN R11 100; var11 = 100
      44 [-]: NAMECALL R6 R6 K18; var7 = var6; var6 = var6[0x462C251C]
      45 [-]: CALL R6 6 2  ; var6 = var6(var7, var8, var9, var10, var11)
      46 [-]: FASTCALL1 64 R6 L3; 
      47 [-]: MOVE R8 R6   ; var8 = var6
      48 [-]: GETIMPORT R7 8; var7 = 0x7B998233
      49 [-]: CALL R7 2 2  ; var7 = var7(var8)
L 3:  50 [-]: JUMPIF R7 L4 ; goto L4 if var7
      51 [-]: NAMECALL R7 R6 K19; var8 = var6; var7 = var6[0xF4E253B6]
      52 [-]: CALL R7 2 1  ; var7(var8)
L 4:  53 [-]: GETUPVAL R7 0; var7 = upvalues[0]
      54 [-]: MOVE R8 R0   ; var8 = var0
      55 [-]: MOVE R9 R3   ; var9 = var3
      56 [-]: GETIMPORT R10 21; var10 = 0x20B7F774
      57 [-]: MOVE R11 R3  ; var11 = var3
      58 [-]: NAMECALL R12 R1 K4; var13 = var1; var12 = var1[0xF6EBD926]
      59 [-]: CALL R12 2 0 ; var12, ... = var12(var13)
      60 [-]: CALL R10 0 0 ; var10, ... = var10(var11, ...)
      61 [-]: CALL R7 0 1  ; var7(var8, ...)
      62 [-]: MOVE R7 R0   ; var7 = var0
      63 [-]: FASTCALL1 64 R7 L5; 
      64 [-]: MOVE R9 R7   ; var9 = var7
      65 [-]: GETIMPORT R8 8; var8 = 0x7B998233
      66 [-]: CALL R8 2 2  ; var8 = var8(var9)
L 5:  67 [-]: JUMPIF R8 L6 ; goto L6 if var8
      68 [-]: GETIMPORT R10 23; var10 = gLotusOperatorAvatarType
      69 [-]: NAMECALL R8 R7 K24; var9 = var7; var8 = var7[0xF2DEAF69]
      70 [-]: CALL R8 3 2  ; var8 = var8(var9, var10)
      71 [-]: JUMPIF R8 L6 ; goto L6 if var8
      72 [-]: NAMECALL R8 R4 K25; var9 = var4; var8 = var4[0x5578D98B]
      73 [-]: CALL R8 2 2  ; var8 = var8(var9)
      74 [-]: MOVE R7 R8   ; var7 = var8
L 6:  75 [-]: FASTCALL1 64 R7 L7; 
      76 [-]: MOVE R9 R7   ; var9 = var7
      77 [-]: GETIMPORT R8 8; var8 = 0x7B998233
      78 [-]: CALL R8 2 2  ; var8 = var8(var9)
L 7:  79 [-]: JUMPIF R8 L13; goto L13 if var8
      80 [-]: GETIMPORT R10 23; var10 = gLotusOperatorAvatarType
      81 [-]: NAMECALL R8 R7 K24; var9 = var7; var8 = var7[0xF2DEAF69]
      82 [-]: CALL R8 3 2  ; var8 = var8(var9, var10)
      83 [-]: JUMPIFNOT R8 L13; goto L13 if not var8
      84 [-]: NAMECALL R8 R7 K26; var9 = var7; var8 = var7[0xDE321E6F]
      85 [-]: CALL R8 2 2  ; var8 = var8(var9)
      86 [-]: NAMECALL R8 R8 K27; var9 = var8; var8 = var8[0xF7D48EE0]
      87 [-]: CALL R8 2 2  ; var8 = var8(var9)
      88 [-]: FASTCALL1 64 R8 L8; 
      89 [-]: MOVE R10 R8  ; var10 = var8
      90 [-]: GETIMPORT R9 8; var9 = 0x7B998233
      91 [-]: CALL R9 2 2  ; var9 = var9(var10)
L 8:  92 [-]: JUMPIF R9 L10; goto L10 if var9
      93 [-]: GETUPVAL R11 1; var11 = upvalues[1]
      94 [-]: NAMECALL R9 R8 K28; var10 = var8; var9 = var8[0x689412A5]
      95 [-]: CALL R9 3 2  ; var9 = var9(var10, var11)
      96 [-]: FASTCALL1 64 R9 L9; 
      97 [-]: MOVE R11 R9  ; var11 = var9
      98 [-]: GETIMPORT R10 8; var10 = 0x7B998233
      99 [-]: CALL R10 2 2 ; var10 = var10(var11)
L 9: 100 [-]: JUMPIF R10 L10; goto L10 if var10
     101 [-]: NAMECALL R10 R9 K29; var11 = var9; var10 = var9[0x30F46140]
     102 [-]: CALL R10 2 2 ; var10 = var10(var11)
     103 [-]: JUMPIFNOT R10 L10; goto L10 if not var10
     104 [-]: LOADB R12 0  ; var12 = false
     105 [-]: NAMECALL R10 R9 K30; var11 = var9; var10 = var9[0xA74EA8AC]
     106 [-]: CALL R10 3 1 ; var10(var11, var12)
L10: 107 [-]: GETUPVAL R9 2; var9 = upvalues[2]
     108 [-]: MOVE R10 R7  ; var10 = var7
     109 [-]: CALL R9 2 1  ; var9(var10)
     110 [-]: LOADB R11 1  ; var11 = true
     111 [-]: NAMECALL R9 R7 K31; var10 = var7; var9 = var7[0x7CD1BACF]
     112 [-]: CALL R9 3 1  ; var9(var10, var11)
     113 [-]: JUMP L13     ; goto L13
L11: 114 [-]: GETIMPORT R6 1; var6 = 0x89326C93
     115 [-]: NAMECALL R6 R6 K32; var7 = var6; var6 = var6[0x18D05D30]
     116 [-]: CALL R6 2 2  ; var6 = var6(var7)
     117 [-]: JUMPIFNOT R6 L13; goto L13 if not var6
     118 [-]: GETIMPORT R8 34; var8 = 0x171F7DA6
     119 [-]: GETIMPORT R9 36; var9 = EMPTY_SYMBOL
     120 [-]: GETIMPORT R10 38; var10 = ZERO_VECTOR
     121 [-]: GETIMPORT R11 40; var11 = ZERO_ROTATION
     122 [-]: MOVE R12 R0  ; var12 = var0
     123 [-]: NAMECALL R6 R0 K41; var7 = var0; var6 = var0[0x47901F07]
     124 [-]: CALL R6 7 1  ; var6(var7, var8, var9, var10, var11, var12)
     125 [-]: GETIMPORT R6 43; var6 = 0xCBD666E1
     126 [-]: LOADK R7 K44 ; var7 = 0.75
     127 [-]: CALL R6 2 1  ; var6(var7)
     128 [-]: FASTCALL1 64 R0 L12; 
     129 [-]: MOVE R7 R0   ; var7 = var0
     130 [-]: GETIMPORT R6 8; var6 = 0x7B998233
     131 [-]: CALL R6 2 2  ; var6 = var6(var7)
L12: 132 [-]: JUMPIF R6 L13; goto L13 if var6
     133 [-]: MOVE R8 R3   ; var8 = var3
     134 [-]: GETIMPORT R9 21; var9 = 0x20B7F774
     135 [-]: MOVE R10 R3  ; var10 = var3
     136 [-]: NAMECALL R11 R1 K4; var12 = var1; var11 = var1[0xF6EBD926]
     137 [-]: CALL R11 2 0 ; var11, ... = var11(var12)
     138 [-]: CALL R9 0 2  ; var9 = var9(var10, ...)
     139 [-]: LOADB R10 1  ; var10 = true
     140 [-]: NAMECALL R6 R0 K45; var7 = var0; var6 = var0[0x589EF1C1]
     141 [-]: CALL R6 5 1  ; var6(var7, var8, var9, var10)
     142 [-]: NAMECALL R6 R0 K46; var7 = var0; var6 = var0[0x283A8730]
     143 [-]: CALL R6 2 1  ; var6(var7)
     144 [-]: GETIMPORT R8 23; var8 = gLotusOperatorAvatarType
     145 [-]: NAMECALL R6 R0 K24; var7 = var0; var6 = var0[0xF2DEAF69]
     146 [-]: CALL R6 3 2  ; var6 = var6(var7, var8)
     147 [-]: JUMPIFNOT R6 L13; goto L13 if not var6
     148 [-]: GETUPVAL R6 2; var6 = upvalues[2]
     149 [-]: MOVE R7 R0   ; var7 = var0
     150 [-]: CALL R6 2 1  ; var6(var7)
L13: 151 [-]: NAMECALL R5 R0 K47; var6 = var0; var5 = var0[0x1AC1655C]
     152 [-]: CALL R5 2 2  ; var5 = var5(var6)
     153 [-]: FASTCALL1 64 R5 L14; 
     154 [-]: MOVE R7 R5   ; var7 = var5
     155 [-]: GETIMPORT R6 8; var6 = 0x7B998233
     156 [-]: CALL R6 2 2  ; var6 = var6(var7)
L14: 157 [-]: JUMPIF R6 L16; goto L16 if var6
     158 [-]: NAMECALL R6 R5 K48; var7 = var5; var6 = var5[0x3DF4C10F]
     159 [-]: CALL R6 2 2  ; var6 = var6(var7)
     160 [-]: JUMPIFNOT R6 L15; goto L15 if not var6
     161 [-]: GETIMPORT R8 50; var8 = 0x8942B94A
     162 [-]: NAMECALL R6 R5 K51; var7 = var5; var6 = var5[0x897990EF]
     163 [-]: CALL R6 3 1  ; var6(var7, var8)
     164 [-]: JUMP L16     ; goto L16
L15: 165 [-]: GETIMPORT R8 50; var8 = 0x8942B94A
     166 [-]: GETIMPORT R9 50; var9 = 0x8942B94A
     167 [-]: NAMECALL R6 R5 K52; var7 = var5; var6 = var5[0x4A9DA24C]
     168 [-]: CALL R6 4 1  ; var6(var7, var8, var9)
L16: 169 [-]: GETUPVAL R7 3; var7 = upvalues[3]
     170 [-]: FASTCALL1 64 R7 L17; 
     171 [-]: GETIMPORT R6 8; var6 = 0x7B998233
     172 [-]: CALL R6 2 2  ; var6 = var6(var7)
L17: 173 [-]: JUMPIF R6 L20; goto L20 if var6
     174 [-]: GETUPVAL R9 3; var9 = upvalues[3]
     175 [-]: LENGTH R8 R9 ; var8 = #var9
     176 [-]: LOADN R6 1   ; var6 = 1
     177 [-]: LOADN R7 -1  ; var7 = -1
     178 [-]: FORNPREP R6 L20; nforprep start - [escape at L20] -- var6 = iterator
L18: 179 [-]: GETUPVAL R10 3; var10 = upvalues[3]
     180 [-]: GETTABLE R9 R10 R8; var9 = var10[var8]
     181 [-]: JUMPIFNOTEQ R0 R9 L19; goto L19 if var0 ~= var3606817
     182 [-]: GETIMPORT R9 55; var9 = 0x33BDD652[0x9C1F3B5A]
     183 [-]: GETUPVAL R10 3; var10 = upvalues[3]
     184 [-]: MOVE R11 R8  ; var11 = var8
     185 [-]: CALL R9 3 1  ; var9(var10, var11)
     186 [-]: JUMP L20     ; goto L20
L19: 187 [-]: FORNLOOP R6 L18; nforloop end - iterate + goto L18
L20: 188 [-]: FASTCALL1 64 R0 L21; 
     189 [-]: MOVE R7 R0   ; var7 = var0
     190 [-]: GETIMPORT R6 8; var6 = 0x7B998233
     191 [-]: CALL R6 2 2  ; var6 = var6(var7)
L21: 192 [-]: JUMPIF R6 L22; goto L22 if var6
     193 [-]: GETUPVAL R8 4; var8 = upvalues[4]
     194 [-]: NAMECALL R6 R0 K56; var7 = var0; var6 = var0[0xA3A0F1C2]
     195 [-]: CALL R6 3 1  ; var6(var7, var8)
L22: 196 [-]: RETURN R0 0  ; 


; Name:            
; Defined at line: 529
; #Upvalues:       1
; #Parameters:     2
; Is_vararg:       0
; Max Stack Size:  17

       0 [-]: FASTCALL1 64 R1 L0; 
       1 [-]: MOVE R3 R1   ; var3 = var1
       2 [-]: GETIMPORT R2 1; var2 = 0x7B998233
       3 [-]: CALL R2 2 2  ; var2 = var2(var3)
L 0:   4 [-]: JUMPIFNOT R2 L1; goto L1 if not var2
       5 [-]: RETURN R0 0  ; 
L 1:   6 [-]: FASTCALL1 64 R0 L2; 
       7 [-]: MOVE R3 R0   ; var3 = var0
       8 [-]: GETIMPORT R2 1; var2 = 0x7B998233
       9 [-]: CALL R2 2 2  ; var2 = var2(var3)
L 2:  10 [-]: JUMPIF R2 L3 ; goto L3 if var2
      11 [-]: NAMECALL R2 R0 K2; var3 = var0; var2 = var0[0x2047CFE7]
      12 [-]: CALL R2 2 2  ; var2 = var2(var3)
      13 [-]: JUMPIFNOT R2 L4; goto L4 if not var2
L 3:  14 [-]: RETURN R0 0  ; 
L 4:  15 [-]: NAMECALL R2 R0 K3; var3 = var0; var2 = var0[0x388577D5]
      16 [-]: CALL R2 2 2  ; var2 = var2(var3)
      17 [-]: NAMECALL R3 R0 K4; var4 = var0; var3 = var0[0x73901ACF]
      18 [-]: CALL R3 2 2  ; var3 = var3(var4)
      19 [-]: JUMPIF R3 L5 ; goto L5 if var3
      20 [-]: RETURN R0 0  ; 
L 5:  21 [-]: NAMECALL R3 R0 K5; var4 = var0; var3 = var0[0xDE321E6F]
      22 [-]: CALL R3 2 2  ; var3 = var3(var4)
      23 [-]: NAMECALL R3 R3 K6; var4 = var3; var3 = var3[0xF7D48EE0]
      24 [-]: CALL R3 2 2  ; var3 = var3(var4)
      25 [-]: FASTCALL1 64 R3 L6; 
      26 [-]: MOVE R5 R3   ; var5 = var3
      27 [-]: GETIMPORT R4 1; var4 = 0x7B998233
      28 [-]: CALL R4 2 2  ; var4 = var4(var5)
L 6:  29 [-]: JUMPIFNOT R4 L7; goto L7 if not var4
      30 [-]: RETURN R0 0  ; 
L 7:  31 [-]: NAMECALL R4 R1 K7; var5 = var1; var4 = var1[0x0D09D3C0]
      32 [-]: CALL R4 2 2  ; var4 = var4(var5)
      33 [-]: LOADN R7 1   ; var7 = 1
      34 [-]: LENGTH R5 R4 ; var5 = #var4
      35 [-]: LOADN R6 1   ; var6 = 1
      36 [-]: FORNPREP R5 L16; nforprep start - [escape at L16] -- var5 = iterator
L 8:  37 [-]: GETTABLE R8 R4 R7; var8 = var4[var7]
      38 [-]: FASTCALL1 64 R8 L9; 
      39 [-]: MOVE R10 R8  ; var10 = var8
      40 [-]: GETIMPORT R9 1; var9 = 0x7B998233
      41 [-]: CALL R9 2 2  ; var9 = var9(var10)
L 9:  42 [-]: JUMPIF R9 L15; goto L15 if var9
      43 [-]: LOADB R9 0   ; var9 = false
      44 [-]: GETIMPORT R13 10; var13 = _T["VoidAngels"]
      45 [-]: GETTABLE R12 R13 R2; var12 = var13[var2]
      46 [-]: GETTABLEKS R11 R12 K11; var11 = var12["activePlayers"]
      47 [-]: FASTCALL1 64 R11 L10; 
      48 [-]: GETIMPORT R10 1; var10 = 0x7B998233
      49 [-]: CALL R10 2 2 ; var10 = var10(var11)
L10:  50 [-]: JUMPIF R10 L15; goto L15 if var10
      51 [-]: LOADN R12 1  ; var12 = 1
      52 [-]: GETIMPORT R15 10; var15 = _T["VoidAngels"]
      53 [-]: GETTABLE R14 R15 R2; var14 = var15[var2]
      54 [-]: GETTABLEKS R13 R14 K11; var13 = var14["activePlayers"]
      55 [-]: LENGTH R10 R13; var10 = #var13
      56 [-]: LOADN R11 1  ; var11 = 1
      57 [-]: FORNPREP R10 L13; nforprep start - [escape at L13] -- var10 = iterator
L11:  58 [-]: GETIMPORT R16 10; var16 = _T["VoidAngels"]
      59 [-]: GETTABLE R15 R16 R2; var15 = var16[var2]
      60 [-]: GETTABLEKS R14 R15 K11; var14 = var15["activePlayers"]
      61 [-]: GETTABLE R13 R14 R12; var13 = var14[var12]
      62 [-]: JUMPIFNOTEQ R8 R13 L12; goto L12 if var8 ~= var67846
      63 [-]: LOADB R9 1   ; var9 = true
      64 [-]: JUMP L13     ; goto L13
L12:  65 [-]: FORNLOOP R10 L11; nforloop end - iterate + goto L11
L13:  66 [-]: JUMPIF R9 L15; goto L15 if var9
      67 [-]: GETIMPORT R12 13; var12 = gTennoAvatarType
      68 [-]: NAMECALL R10 R8 K14; var11 = var8; var10 = var8[0xF2DEAF69]
      69 [-]: CALL R10 3 2 ; var10 = var10(var11, var12)
      70 [-]: JUMPIFNOT R10 L15; goto L15 if not var10
      71 [-]: NAMECALL R11 R8 K15; var12 = var8; var11 = var8[0x5E651723]
      72 [-]: CALL R11 2 0 ; var11, ... = var11(var12)
      73 [-]: FASTCALL 64 L14; 
      74 [-]: GETIMPORT R10 1; var10 = 0x7B998233
      75 [-]: CALL R10 0 2 ; var10 = var10(var11, ...)
L14:  76 [-]: JUMPIF R10 L15; goto L15 if var10
      77 [-]: GETUPVAL R10 0; var10 = upvalues[0]
      78 [-]: MOVE R11 R0  ; var11 = var0
      79 [-]: MOVE R12 R3  ; var12 = var3
      80 [-]: MOVE R13 R8  ; var13 = var8
      81 [-]: CALL R10 4 1 ; var10(var11, var12, var13)
L15:  82 [-]: FORNLOOP R5 L8; nforloop end - iterate + goto L8
L16:  83 [-]: RETURN R0 0  ; 


; Name:            
; Defined at line: 572
; #Upvalues:       0
; #Parameters:     1
; Is_vararg:       0
; Max Stack Size:  8

       0 [-]: NAMECALL R1 R0 K0; var2 = var0; var1 = var0[0xED324116]
       1 [-]: CALL R1 2 2  ; var1 = var1(var2)
       2 [-]: FASTCALL1 64 R1 L0; 
       3 [-]: MOVE R3 R1   ; var3 = var1
       4 [-]: GETIMPORT R2 2; var2 = 0x7B998233
       5 [-]: CALL R2 2 2  ; var2 = var2(var3)
L 0:   6 [-]: JUMPIFNOT R2 L1; goto L1 if not var2
       7 [-]: NAMECALL R2 R0 K3; var3 = var0; var2 = var0[0x1DB57C6B]
       8 [-]: CALL R2 2 1  ; var2(var3)
       9 [-]: RETURN R0 0  ; 
L 1:  10 [-]: GETIMPORT R2 5; var2 = 0x89326C93
      11 [-]: NAMECALL R2 R2 K6; var3 = var2; var2 = var2[0x18D05D30]
      12 [-]: CALL R2 2 2  ; var2 = var2(var3)
      13 [-]: JUMPIFNOT R2 L4; goto L4 if not var2
      14 [-]: GETIMPORT R4 8; var4 = 0x29B3117E
      15 [-]: GETIMPORT R5 10; var5 = EMPTY_SYMBOL
      16 [-]: NAMECALL R2 R0 K11; var3 = var0; var2 = var0[0x47901F07]
      17 [-]: CALL R2 4 2  ; var2 = var2(var3, var4, var5)
      18 [-]: NAMECALL R3 R1 K12; var4 = var1; var3 = var1[0x388577D5]
      19 [-]: CALL R3 2 2  ; var3 = var3(var4)
      20 [-]: GETIMPORT R7 15; var7 = _T["VoidAngels"]
      21 [-]: GETTABLE R6 R7 R3; var6 = var7[var3]
      22 [-]: GETTABLEKS R5 R6 K16; var5 = var6["voidPortals"]
      23 [-]: FASTCALL1 64 R5 L2; 
      24 [-]: GETIMPORT R4 2; var4 = 0x7B998233
      25 [-]: CALL R4 2 2  ; var4 = var4(var5)
L 2:  26 [-]: JUMPIFNOT R4 L3; goto L3 if not var4
      27 [-]: GETIMPORT R5 15; var5 = _T["VoidAngels"]
      28 [-]: GETTABLE R4 R5 R3; var4 = var5[var3]
      29 [-]: NEWTABLE R5 0 0; var5 = {}
      30 [-]: SETTABLEKS R5 R4 K16; var5["voidPortals"] = var4
L 3:  31 [-]: GETIMPORT R7 15; var7 = _T["VoidAngels"]
      32 [-]: GETTABLE R6 R7 R3; var6 = var7[var3]
      33 [-]: GETTABLEKS R5 R6 K16; var5 = var6["voidPortals"]
      34 [-]: DUPTABLE R6 20; 
      35 [-]: SETTABLEKS R0 R6 K17; var0["deco"] = var6
      36 [-]: SETTABLEKS R2 R6 K18; var2["trigger"] = var6
      37 [-]: GETIMPORT R7 22; var7 = 0xCD25CDAF
      38 [-]: SETTABLEKS R7 R6 K19; var7["timer"] = var6
      39 [-]: FASTCALL2 52 R5 R6 L4; 
      40 [-]: GETIMPORT R4 25; var4 = 0x33BDD652[0x23D5322F]
      41 [-]: CALL R4 3 1  ; var4(var5, var6)
L 4:  42 [-]: RETURN R0 0  ; 


; Name:            
; Defined at line: 590
; #Upvalues:       1
; #Parameters:     1
; Is_vararg:       0
; Max Stack Size:  14

       0 [-]: NAMECALL R1 R0 K0; var2 = var0; var1 = var0[0xFA9E477F]
       1 [-]: CALL R1 2 2  ; var1 = var1(var2)
       2 [-]: FASTCALL1 64 R1 L0; 
       3 [-]: MOVE R3 R1   ; var3 = var1
       4 [-]: GETIMPORT R2 2; var2 = 0x7B998233
       5 [-]: CALL R2 2 2  ; var2 = var2(var3)
L 0:   6 [-]: JUMPIF R2 L1 ; goto L1 if var2
       7 [-]: GETIMPORT R4 4; var4 = 0x0469F296
       8 [-]: LOADK R5 K5  ; var5 = "BlockVoidPortal"
       9 [-]: CALL R4 2 0  ; var4, ... = var4(var5)
      10 [-]: NAMECALL R2 R1 K6; var3 = var1; var2 = var1[0x870F0ADF]
      11 [-]: CALL R2 0 2  ; var2 = var2(var3, ...)
      12 [-]: JUMPXEQKN R2 K7 L2 NOT; 
L 1:  13 [-]: RETURN R0 0  ; 
L 2:  14 [-]: GETIMPORT R2 9; var2 = 0x89326C93
      15 [-]: NAMECALL R2 R2 K10; var3 = var2; var2 = var2[0x29EF273D]
      16 [-]: CALL R2 2 2  ; var2 = var2(var3)
      17 [-]: GETIMPORT R3 12; var3 = 0xA421AF95
      18 [-]: LOADN R4 5   ; var4 = 5
      19 [-]: LOADN R5 0   ; var5 = 0
      20 [-]: LOADN R6 0   ; var6 = 0
      21 [-]: CALL R3 4 2  ; var3 = var3(var4, var5, var6)
      22 [-]: GETIMPORT R4 14; var4 = 0x492C7F2A
      23 [-]: MOVE R5 R3   ; var5 = var3
      24 [-]: GETIMPORT R6 16; var6 = 0x00046924
      25 [-]: GETIMPORT R7 18; var7 = 0xDD6E4CF8
      26 [-]: LOADN R8 0   ; var8 = 0
      27 [-]: LOADN R9 360 ; var9 = 360
      28 [-]: CALL R7 3 2  ; var7 = var7(var8, var9)
      29 [-]: LOADN R8 0   ; var8 = 0
      30 [-]: LOADN R9 0   ; var9 = 0
      31 [-]: CALL R6 4 0  ; var6, ... = var6(var7, var8, var9)
      32 [-]: CALL R4 0 2  ; var4 = var4(var5, ...)
      33 [-]: MOVE R3 R4   ; var3 = var4
      34 [-]: NAMECALL R5 R0 K19; var6 = var0; var5 = var0[0xD1586535]
      35 [-]: CALL R5 2 2  ; var5 = var5(var6)
      36 [-]: ADD R4 R5 R3 ; var4 = var5 + var3
      37 [-]: JUMPIFNOT R2 L3; goto L3 if not var2
      38 [-]: MOVE R7 R4   ; var7 = var4
      39 [-]: LOADN R8 5   ; var8 = 5
      40 [-]: NAMECALL R5 R2 K20; var6 = var2; var5 = var2[0x40F8914B]
      41 [-]: CALL R5 4 1  ; var5(var6, var7, var8)
L 3:  42 [-]: GETTABLEKS R6 R4 K21; var6 = var4["y"]
      43 [-]: GETIMPORT R7 23; var7 = 0x0C5E62F9
      44 [-]: LOADN R8 2   ; var8 = 2
      45 [-]: LOADN R9 4   ; var9 = 4
      46 [-]: CALL R7 3 2  ; var7 = var7(var8, var9)
      47 [-]: ADD R5 R6 R7 ; var5 = var6 + var7
      48 [-]: SETTABLEKS R5 R4 K21; var5["y"] = var4
      49 [-]: GETIMPORT R5 25; var5 = 0x20B7F774
      50 [-]: NAMECALL R6 R0 K19; var7 = var0; var6 = var0[0xD1586535]
      51 [-]: CALL R6 2 2  ; var6 = var6(var7)
      52 [-]: MOVE R7 R4   ; var7 = var4
      53 [-]: CALL R5 3 2  ; var5 = var5(var6, var7)
      54 [-]: GETIMPORT R6 9; var6 = 0x89326C93
      55 [-]: MOVE R8 R4   ; var8 = var4
      56 [-]: LOADN R9 20  ; var9 = 20
      57 [-]: NAMECALL R6 R6 K26; var7 = var6; var6 = var6[0x50A314F9]
      58 [-]: CALL R6 4 2  ; var6 = var6(var7, var8, var9)
      59 [-]: FASTCALL1 64 R6 L4; 
      60 [-]: MOVE R8 R6   ; var8 = var6
      61 [-]: GETIMPORT R7 2; var7 = 0x7B998233
      62 [-]: CALL R7 2 2  ; var7 = var7(var8)
L 4:  63 [-]: JUMPIF R7 L5 ; goto L5 if var7
      64 [-]: GETIMPORT R7 25; var7 = 0x20B7F774
      65 [-]: MOVE R8 R4   ; var8 = var4
      66 [-]: GETUPVAL R11 0; var11 = upvalues[0]
      67 [-]: NAMECALL R9 R6 K27; var10 = var6; var9 = var6[0x003C792F]
      68 [-]: CALL R9 3 0  ; var9, ... = var9(var10, var11)
      69 [-]: CALL R7 0 2  ; var7 = var7(var8, ...)
      70 [-]: MOVE R5 R7   ; var5 = var7
L 5:  71 [-]: GETIMPORT R7 9; var7 = 0x89326C93
      72 [-]: GETIMPORT R9 29; var9 = 0x9C52D9C8
      73 [-]: MOVE R10 R4  ; var10 = var4
      74 [-]: MOVE R11 R5  ; var11 = var5
      75 [-]: MOVE R12 R0  ; var12 = var0
      76 [-]: MOVE R13 R0  ; var13 = var0
      77 [-]: NAMECALL R7 R7 K30; var8 = var7; var7 = var7[0x05909209]
      78 [-]: CALL R7 7 1  ; var7(var8, var9, var10, var11, var12, var13)
      79 [-]: RETURN R0 0  ; 


; Name:            
; Defined at line: 614
; #Upvalues:       22
; #Parameters:     1
; Is_vararg:       0
; Max Stack Size:  39

       0 [-]: GETIMPORT R1 1; var1 = 0x89326C93
       1 [-]: NAMECALL R1 R1 K2; var2 = var1; var1 = var1[0x18D05D30]
       2 [-]: CALL R1 2 2  ; var1 = var1(var2)
       3 [-]: JUMPIFNOT R1 L20; goto L20 if not var1
       4 [-]: NAMECALL R1 R0 K3; var2 = var0; var1 = var0[0x388577D5]
       5 [-]: CALL R1 2 2  ; var1 = var1(var2)
       6 [-]: GETIMPORT R3 6; var3 = _T["VoidAngels"]
       7 [-]: FASTCALL1 64 R3 L0; 
       8 [-]: GETIMPORT R2 8; var2 = 0x7B998233
       9 [-]: CALL R2 2 2  ; var2 = var2(var3)
L 0:  10 [-]: JUMPIFNOT R2 L1; goto L1 if not var2
      11 [-]: GETIMPORT R2 9; var2 = _T
      12 [-]: NEWTABLE R3 0 0; var3 = {}
      13 [-]: SETTABLEKS R3 R2 K5; var3["VoidAngels"] = var2
L 1:  14 [-]: GETIMPORT R4 6; var4 = _T["VoidAngels"]
      15 [-]: GETTABLE R3 R4 R1; var3 = var4[var1]
      16 [-]: FASTCALL1 64 R3 L2; 
      17 [-]: GETIMPORT R2 8; var2 = 0x7B998233
      18 [-]: CALL R2 2 2  ; var2 = var2(var3)
L 2:  19 [-]: JUMPIFNOT R2 L3; goto L3 if not var2
      20 [-]: GETIMPORT R2 6; var2 = _T["VoidAngels"]
      21 [-]: DUPTABLE R3 13; 
      22 [-]: SETTABLEKS R0 R3 K10; var0["avatar"] = var3
      23 [-]: NEWTABLE R4 0 0; var4 = {}
      24 [-]: SETTABLEKS R4 R3 K11; var4["voidPortals"] = var3
      25 [-]: NEWTABLE R4 0 0; var4 = {}
      26 [-]: SETTABLEKS R4 R3 K12; var4["activePlayers"] = var3
      27 [-]: SETTABLE R3 R2 R1; var3[var2] = var1
L 3:  28 [-]: LOADNIL R2   ; var2 = nil
L 4:  29 [-]: FASTCALL1 64 R2 L5; 
      30 [-]: MOVE R4 R2   ; var4 = var2
      31 [-]: GETIMPORT R3 8; var3 = 0x7B998233
      32 [-]: CALL R3 2 2  ; var3 = var3(var4)
L 5:  33 [-]: JUMPIFNOT R3 L6; goto L6 if not var3
      34 [-]: NAMECALL R3 R0 K14; var4 = var0; var3 = var0[0xFA9E477F]
      35 [-]: CALL R3 2 2  ; var3 = var3(var4)
      36 [-]: MOVE R2 R3   ; var2 = var3
      37 [-]: GETIMPORT R3 16; var3 = 0xCBD666E1
      38 [-]: LOADN R4 0   ; var4 = 0
      39 [-]: CALL R3 2 1  ; var3(var4)
      40 [-]: JUMPBACK L4  ; goto L4
L 6:  41 [-]: GETIMPORT R5 18; var5 = 0x0469F296
      42 [-]: LOADK R6 K19 ; var6 = "ZarOptInAngel"
      43 [-]: CALL R5 2 0  ; var5, ... = var5(var6)
      44 [-]: NAMECALL R3 R2 K20; var4 = var2; var3 = var2[0x5E81FE30]
      45 [-]: CALL R3 0 2  ; var3 = var3(var4, ...)
      46 [-]: JUMPIFNOT R3 L7; goto L7 if not var3
      47 [-]: GETIMPORT R3 16; var3 = 0xCBD666E1
      48 [-]: LOADN R4 0   ; var4 = 0
      49 [-]: CALL R3 2 1  ; var3(var4)
      50 [-]: JUMPBACK L6  ; goto L6
L 7:  51 [-]: SETUPVAL R0 0; upvalues[0] = var0
      52 [-]: NAMECALL R3 R0 K21; var4 = var0; var3 = var0[0x1AC1655C]
      53 [-]: CALL R3 2 2  ; var3 = var3(var4)
      54 [-]: FASTCALL1 64 R3 L8; 
      55 [-]: MOVE R5 R3   ; var5 = var3
      56 [-]: GETIMPORT R4 8; var4 = 0x7B998233
      57 [-]: CALL R4 2 2  ; var4 = var4(var5)
L 8:  58 [-]: JUMPIF R4 L9 ; goto L9 if var4
      59 [-]: GETIMPORT R6 18; var6 = 0x0469F296
      60 [-]: LOADK R7 K22 ; var7 = "AngelSetupInvul"
      61 [-]: CALL R6 2 2  ; var6 = var6(var7)
      62 [-]: LOADN R7 25  ; var7 = 25
      63 [-]: LOADN R8 6   ; var8 = 6
      64 [-]: LOADN R9 0   ; var9 = 0
      65 [-]: NAMECALL R4 R3 K23; var5 = var3; var4 = var3[0xA383DE31]
      66 [-]: CALL R4 6 1  ; var4(var5, var6, var7, var8, var9)
L 9:  67 [-]: NAMECALL R4 R0 K24; var5 = var0; var4 = var0[0xDE321E6F]
      68 [-]: CALL R4 2 2  ; var4 = var4(var5)
      69 [-]: NAMECALL R4 R4 K25; var5 = var4; var4 = var4[0xF7D48EE0]
      70 [-]: CALL R4 2 2  ; var4 = var4(var5)
L10:  71 [-]: FASTCALL1 64 R4 L11; 
      72 [-]: MOVE R6 R4   ; var6 = var4
      73 [-]: GETIMPORT R5 8; var5 = 0x7B998233
      74 [-]: CALL R5 2 2  ; var5 = var5(var6)
L11:  75 [-]: JUMPIFNOT R5 L12; goto L12 if not var5
      76 [-]: NAMECALL R5 R0 K24; var6 = var0; var5 = var0[0xDE321E6F]
      77 [-]: CALL R5 2 2  ; var5 = var5(var6)
      78 [-]: NAMECALL R5 R5 K25; var6 = var5; var5 = var5[0xF7D48EE0]
      79 [-]: CALL R5 2 2  ; var5 = var5(var6)
      80 [-]: MOVE R4 R5   ; var4 = var5
      81 [-]: GETIMPORT R5 16; var5 = 0xCBD666E1
      82 [-]: LOADN R6 0   ; var6 = 0
      83 [-]: CALL R5 2 1  ; var5(var6)
      84 [-]: JUMPBACK L10 ; goto L10
L12:  85 [-]: GETUPVAL R6 1; var6 = upvalues[1]
      86 [-]: GETTABLEKS R5 R6 K26; var5 = var6[0x6696A66C]
      87 [-]: MOVE R6 R4   ; var6 = var4
      88 [-]: CALL R5 2 2  ; var5 = var5(var6)
      89 [-]: LOADN R8 1   ; var8 = 1
      90 [-]: LENGTH R6 R5 ; var6 = #var5
      91 [-]: LOADN R7 1   ; var7 = 1
      92 [-]: FORNPREP R6 L19; nforprep start - [escape at L19] -- var6 = iterator
L13:  93 [-]: GETTABLE R9 R5 R8; var9 = var5[var8]
      94 [-]: FASTCALL1 64 R9 L14; 
      95 [-]: MOVE R11 R9  ; var11 = var9
      96 [-]: GETIMPORT R10 8; var10 = 0x7B998233
      97 [-]: CALL R10 2 2 ; var10 = var10(var11)
L14:  98 [-]: JUMPIF R10 L18; goto L18 if var10
      99 [-]: LOADB R10 0  ; var10 = false
     100 [-]: LOADN R13 1  ; var13 = 1
     101 [-]: GETIMPORT R16 6; var16 = _T["VoidAngels"]
     102 [-]: GETTABLE R15 R16 R1; var15 = var16[var1]
     103 [-]: GETTABLEKS R14 R15 K12; var14 = var15["activePlayers"]
     104 [-]: LENGTH R11 R14; var11 = #var14
     105 [-]: LOADN R12 1  ; var12 = 1
     106 [-]: FORNPREP R11 L17; nforprep start - [escape at L17] -- var11 = iterator
L15: 107 [-]: GETIMPORT R17 6; var17 = _T["VoidAngels"]
     108 [-]: GETTABLE R16 R17 R1; var16 = var17[var1]
     109 [-]: GETTABLEKS R15 R16 K12; var15 = var16["activePlayers"]
     110 [-]: GETTABLE R14 R15 R13; var14 = var15[var13]
     111 [-]: JUMPIFNOTEQ R9 R14 L16; goto L16 if var9 ~= var68102
     112 [-]: LOADB R10 1  ; var10 = true
     113 [-]: JUMP L17     ; goto L17
L16: 114 [-]: FORNLOOP R11 L15; nforloop end - iterate + goto L15
L17: 115 [-]: JUMPIF R10 L18; goto L18 if var10
     116 [-]: GETIMPORT R14 6; var14 = _T["VoidAngels"]
     117 [-]: GETTABLE R13 R14 R1; var13 = var14[var1]
     118 [-]: GETTABLEKS R12 R13 K12; var12 = var13["activePlayers"]
     119 [-]: FASTCALL2 52 R12 R9 L18; 
     120 [-]: MOVE R13 R9  ; var13 = var9
     121 [-]: GETIMPORT R11 29; var11 = 0x33BDD652[0x23D5322F]
     122 [-]: CALL R11 3 1 ; var11(var12, var13)
L18: 123 [-]: FORNLOOP R6 L13; nforloop end - iterate + goto L13
L19: 124 [-]: NAMECALL R6 R0 K30; var7 = var0; var6 = var0[0x73901ACF]
     125 [-]: CALL R6 2 2  ; var6 = var6(var7)
     126 [-]: JUMPIF R6 L20; goto L20 if var6
     127 [-]: LOADN R8 0   ; var8 = 0
     128 [-]: NAMECALL R6 R3 K31; var7 = var3; var6 = var3[0x57369B8B]
     129 [-]: CALL R6 3 1  ; var6(var7, var8)
L20: 130 [-]: NAMECALL R1 R0 K21; var2 = var0; var1 = var0[0x1AC1655C]
     131 [-]: CALL R1 2 2  ; var1 = var1(var2)
     132 [-]: GETIMPORT R2 33; var2 = 0xBE190284
     133 [-]: NAMECALL R2 R2 K34; var3 = var2; var2 = var2[0xEF893AEC]
     134 [-]: CALL R2 2 2  ; var2 = var2(var3)
     135 [-]: GETTABLEKS R5 R2 K35; var5 = var2["levelOverride"]
     136 [-]: FASTCALL1 64 R5 L21; 
     137 [-]: GETIMPORT R4 8; var4 = 0x7B998233
     138 [-]: CALL R4 2 2  ; var4 = var4(var5)
L21: 139 [-]: NOT R3 R4    ; var3 = not var4
     140 [-]: JUMPIFNOT R3 L25; goto L25 if not var3
     141 [-]: GETTABLEKS R4 R2 K36; var4 = var2["keyChainName"]
     142 [-]: FASTCALL1 64 R4 L22; 
     143 [-]: GETIMPORT R3 8; var3 = 0x7B998233
     144 [-]: CALL R3 2 2  ; var3 = var3(var4)
L22: 145 [-]: JUMPIFNOT R3 L25; goto L25 if not var3
     146 [-]: GETIMPORT R4 39; var4 = 0x7F5022CF[0xA5C556B9]
     147 [-]: GETTABLEKS R6 R2 K35; var6 = var2["levelOverride"]
     148 [-]: NAMECALL R6 R6 K40; var7 = var6; var6 = var6[0xED4E0128]
     149 [-]: CALL R6 2 0  ; var6, ... = var6(var7)
     150 [-]: FASTCALL 63 L23; 
     151 [-]: GETIMPORT R5 42; var5 = 0x64FB1586
     152 [-]: CALL R5 0 2  ; var5 = var5(var6, ...)
L23: 153 [-]: LOADK R6 K43 ; var6 = "Entrati"
     154 [-]: CALL R4 3 2  ; var4 = var4(var5, var6)
     155 [-]: JUMPXEQKNIL R4 L24 NOT; 
     156 [-]: LOADB R3 0 +1; var3 = false
L24: 157 [-]: LOADB R3 1   ; var3 = true
L25: 158 [-]: JUMPIFNOT R3 L26; goto L26 if not var3
     159 [-]: GETIMPORT R6 18; var6 = 0x0469F296
     160 [-]: LOADK R7 K44 ; var7 = "EmissiveTintColorHi"
     161 [-]: CALL R6 2 2  ; var6 = var6(var7)
     162 [-]: LOADN R7 2   ; var7 = 2
     163 [-]: LOADN R8 2   ; var8 = 2
     164 [-]: LOADN R9 2   ; var9 = 2
     165 [-]: LOADN R10 1  ; var10 = 1
     166 [-]: NAMECALL R4 R0 K45; var5 = var0; var4 = var0[0x986D2AB8]
     167 [-]: CALL R4 7 1  ; var4(var5, var6, var7, var8, var9, var10)
     168 [-]: GETIMPORT R6 18; var6 = 0x0469F296
     169 [-]: LOADK R7 K46 ; var7 = "EmissiveTintColorLo"
     170 [-]: CALL R6 2 2  ; var6 = var6(var7)
     171 [-]: LOADK R7 K47 ; var7 = 0.10000000149011612
     172 [-]: LOADK R8 K48 ; var8 = 1.5
     173 [-]: LOADK R9 K48 ; var9 = 1.5
     174 [-]: LOADN R10 1  ; var10 = 1
     175 [-]: NAMECALL R4 R0 K45; var5 = var0; var4 = var0[0x986D2AB8]
     176 [-]: CALL R4 7 1  ; var4(var5, var6, var7, var8, var9, var10)
L26: 177 [-]: GETIMPORT R4 16; var4 = 0xCBD666E1
     178 [-]: LOADN R5 0   ; var5 = 0
     179 [-]: CALL R4 2 1  ; var4(var5)
     180 [-]: GETIMPORT R4 50; var4 = 0x790BF517
     181 [-]: LOADN R5 0   ; var5 = 0
     182 [-]: GETIMPORT R7 33; var7 = 0xBE190284
     183 [-]: FASTCALL1 64 R7 L27; 
     184 [-]: GETIMPORT R6 8; var6 = 0x7B998233
     185 [-]: CALL R6 2 2  ; var6 = var6(var7)
L27: 186 [-]: JUMPIF R6 L28; goto L28 if var6
     187 [-]: GETIMPORT R6 33; var6 = 0xBE190284
     188 [-]: GETIMPORT R8 18; var8 = 0x0469F296
     189 [-]: LOADK R9 K51 ; var9 = "VoidAngelPhases"
     190 [-]: CALL R8 2 0  ; var8, ... = var8(var9)
     191 [-]: NAMECALL R6 R6 K52; var7 = var6; var6 = var6[0x0EB34C69]
     192 [-]: CALL R6 0 2  ; var6 = var6(var7, ...)
     193 [-]: MOVE R5 R6   ; var5 = var6
L28: 194 [-]: LOADN R6 0   ; var6 = 0
     195 [-]: JUMPIFNOTLT R6 R5 L29; goto L29 if var6 >= var328750
     196 [-]: MOVE R4 R5   ; var4 = var5
     197 [-]: JUMP L31     ; goto L31
L29: 198 [-]: GETIMPORT R7 33; var7 = 0xBE190284
     199 [-]: FASTCALL1 64 R7 L30; 
     200 [-]: GETIMPORT R6 8; var6 = 0x7B998233
     201 [-]: CALL R6 2 2  ; var6 = var6(var7)
L30: 202 [-]: JUMPIF R6 L31; goto L31 if var6
     203 [-]: GETIMPORT R6 33; var6 = 0xBE190284
     204 [-]: GETIMPORT R8 18; var8 = 0x0469F296
     205 [-]: LOADK R9 K51 ; var9 = "VoidAngelPhases"
     206 [-]: CALL R8 2 2  ; var8 = var8(var9)
     207 [-]: GETIMPORT R9 50; var9 = 0x790BF517
     208 [-]: NAMECALL R6 R6 K53; var7 = var6; var6 = var6[0x751F061D]
     209 [-]: CALL R6 4 1  ; var6(var7, var8, var9)
L31: 210 [-]: NAMECALL R6 R0 K24; var7 = var0; var6 = var0[0xDE321E6F]
     211 [-]: CALL R6 2 2  ; var6 = var6(var7)
     212 [-]: NAMECALL R6 R6 K25; var7 = var6; var6 = var6[0xF7D48EE0]
     213 [-]: CALL R6 2 2  ; var6 = var6(var7)
     214 [-]: GETIMPORT R7 55; var7 = 0x7D7E836F
L32: 215 [-]: FASTCALL1 64 R6 L33; 
     216 [-]: MOVE R9 R6   ; var9 = var6
     217 [-]: GETIMPORT R8 8; var8 = 0x7B998233
     218 [-]: CALL R8 2 2  ; var8 = var8(var9)
L33: 219 [-]: JUMPIFNOT R8 L34; goto L34 if not var8
     220 [-]: LOADN R8 0   ; var8 = 0
     221 [-]: JUMPIFNOTLT R8 R7 L34; goto L34 if var8 >= var1050657
     222 [-]: GETIMPORT R8 16; var8 = 0xCBD666E1
     223 [-]: LOADN R9 0   ; var9 = 0
     224 [-]: CALL R8 2 1  ; var8(var9)
     225 [-]: NAMECALL R8 R0 K24; var9 = var0; var8 = var0[0xDE321E6F]
     226 [-]: CALL R8 2 2  ; var8 = var8(var9)
     227 [-]: NAMECALL R8 R8 K25; var9 = var8; var8 = var8[0xF7D48EE0]
     228 [-]: CALL R8 2 2  ; var8 = var8(var9)
     229 [-]: MOVE R6 R8   ; var6 = var8
     230 [-]: GETIMPORT R8 57; var8 = 0x67652851
     231 [-]: CALL R8 1 2  ; var8 = var8()
     232 [-]: SUB R7 R7 R8 ; var7 = var7 - var8
     233 [-]: JUMPBACK L32 ; goto L32
L34: 234 [-]: GETIMPORT R9 59; var9 = _T["SetupBossAvatar"]
     235 [-]: FASTCALL1 64 R9 L35; 
     236 [-]: GETIMPORT R8 8; var8 = 0x7B998233
     237 [-]: CALL R8 2 2  ; var8 = var8(var9)
L35: 238 [-]: JUMPIF R8 L37; goto L37 if var8
     239 [-]: GETIMPORT R9 33; var9 = 0xBE190284
     240 [-]: FASTCALL1 64 R9 L36; 
     241 [-]: GETIMPORT R8 8; var8 = 0x7B998233
     242 [-]: CALL R8 2 2  ; var8 = var8(var9)
L36: 243 [-]: JUMPIF R8 L37; goto L37 if var8
     244 [-]: GETIMPORT R8 59; var8 = _T["SetupBossAvatar"]
     245 [-]: MOVE R9 R0   ; var9 = var0
     246 [-]: ADDK R10 R4 K60; var10 = var4 + 1
     247 [-]: LOADNIL R11  ; var11 = nil
     248 [-]: LOADNIL R12  ; var12 = nil
     249 [-]: LOADB R13 1  ; var13 = true
     250 [-]: CALL R8 6 1  ; var8(var9, var10, var11, var12, var13)
L37: 251 [-]: GETIMPORT R8 1; var8 = 0x89326C93
     252 [-]: NAMECALL R8 R8 K2; var9 = var8; var8 = var8[0x18D05D30]
     253 [-]: CALL R8 2 2  ; var8 = var8(var9)
     254 [-]: JUMPIF R8 L38; goto L38 if var8
     255 [-]: RETURN R0 0  ; 
L38: 256 [-]: NAMECALL R8 R0 K61; var9 = var0; var8 = var0[0xB40C191A]
     257 [-]: CALL R8 2 2  ; var8 = var8(var9)
     258 [-]: NAMECALL R9 R0 K24; var10 = var0; var9 = var0[0xDE321E6F]
     259 [-]: CALL R9 2 2  ; var9 = var9(var10)
     260 [-]: NAMECALL R9 R9 K25; var10 = var9; var9 = var9[0xF7D48EE0]
     261 [-]: CALL R9 2 2  ; var9 = var9(var10)
     262 [-]: GETTABLEKS R10 R2 K62; var10 = var2["syndicateTag"]
     263 [-]: LOADB R11 0  ; var11 = false
     264 [-]: GETIMPORT R12 64; var12 = EMPTY_SYMBOL
     265 [-]: JUMPIFNOTEQ R10 R12 L43; goto L43 if var10 ~= var788663615
     266 [-]: GETTABLEKS R13 R2 K35; var13 = var2["levelOverride"]
     267 [-]: FASTCALL1 64 R13 L39; 
     268 [-]: GETIMPORT R12 8; var12 = 0x7B998233
     269 [-]: CALL R12 2 2 ; var12 = var12(var13)
L39: 270 [-]: NOT R11 R12  ; var11 = not var12
     271 [-]: JUMPIFNOT R11 L43; goto L43 if not var11
     272 [-]: GETTABLEKS R12 R2 K36; var12 = var2["keyChainName"]
     273 [-]: FASTCALL1 64 R12 L40; 
     274 [-]: GETIMPORT R11 8; var11 = 0x7B998233
     275 [-]: CALL R11 2 2 ; var11 = var11(var12)
L40: 276 [-]: JUMPIFNOT R11 L43; goto L43 if not var11
     277 [-]: GETIMPORT R12 39; var12 = 0x7F5022CF[0xA5C556B9]
     278 [-]: GETTABLEKS R14 R2 K35; var14 = var2["levelOverride"]
     279 [-]: NAMECALL R14 R14 K40; var15 = var14; var14 = var14[0xED4E0128]
     280 [-]: CALL R14 2 0 ; var14, ... = var14(var15)
     281 [-]: FASTCALL 63 L41; 
     282 [-]: GETIMPORT R13 42; var13 = 0x64FB1586
     283 [-]: CALL R13 0 2 ; var13 = var13(var14, ...)
L41: 284 [-]: LOADK R14 K43; var14 = "Entrati"
     285 [-]: CALL R12 3 2 ; var12 = var12(var13, var14)
     286 [-]: JUMPXEQKNIL R12 L42 NOT; 
     287 [-]: LOADB R11 0 +1; var11 = false
L42: 288 [-]: LOADB R11 1  ; var11 = true
L43: 289 [-]: GETIMPORT R12 33; var12 = 0xBE190284
     290 [-]: NAMECALL R12 R12 K65; var13 = var12; var12 = var12[0xABF50B1C]
     291 [-]: CALL R12 2 2 ; var12 = var12(var13)
     292 [-]: FASTCALL1 64 R12 L44; 
     293 [-]: MOVE R14 R12 ; var14 = var12
     294 [-]: GETIMPORT R13 8; var13 = 0x7B998233
     295 [-]: CALL R13 2 2 ; var13 = var13(var14)
L44: 296 [-]: JUMPIF R13 L45; goto L45 if var13
     297 [-]: JUMPIF R11 L45; goto L45 if var11
     298 [-]: MOVE R15 R0  ; var15 = var0
     299 [-]: LOADB R16 1  ; var16 = true
     300 [-]: LOADN R17 1000; var17 = 1000
     301 [-]: LOADN R18 7  ; var18 = 7
     302 [-]: NAMECALL R13 R12 K66; var14 = var12; var13 = var12[0x208E54F9]
     303 [-]: CALL R13 6 1 ; var13(var14, var15, var16, var17, var18)
L45: 304 [-]: LOADN R13 0  ; var13 = 0
     305 [-]: GETIMPORT R15 33; var15 = 0xBE190284
     306 [-]: FASTCALL1 64 R15 L46; 
     307 [-]: GETIMPORT R14 8; var14 = 0x7B998233
     308 [-]: CALL R14 2 2 ; var14 = var14(var15)
L46: 309 [-]: JUMPIF R14 L47; goto L47 if var14
     310 [-]: GETIMPORT R14 33; var14 = 0xBE190284
     311 [-]: GETIMPORT R16 18; var16 = 0x0469F296
     312 [-]: LOADK R17 K67; var17 = "VoidAngelHealth"
     313 [-]: CALL R16 2 0 ; var16, ... = var16(var17)
     314 [-]: NAMECALL R14 R14 K52; var15 = var14; var14 = var14[0x0EB34C69]
     315 [-]: CALL R14 0 2 ; var14 = var14(var15, ...)
     316 [-]: MOVE R13 R14 ; var13 = var14
L47: 317 [-]: JUMPXEQKN R13 K68 L49; 
     318 [-]: LOADN R17 1  ; var17 = 1
          320 [-]: MUL R19 R8 R20; var19 = var8 * var20
     321 [-]: MULK R20 R8 K70; var20 = var8 * 0.019999999552965164
     322 [-]: ADD R18 R19 R20; var18 = var19 + var20
     323 [-]: FASTCALL2 18 R17 R18 L48; 
     324 [-]: GETIMPORT R16 73; var16 = 0x5BCED4C4[0xB62ECFE0]
     325 [-]: CALL R16 3 2 ; var16 = var16(var17, var18)
L48: 326 [-]: NAMECALL R14 R0 K74; var15 = var0; var14 = var0[0x014DB014]
     327 [-]: CALL R14 3 1 ; var14(var15, var16)
     328 [-]: GETIMPORT R14 16; var14 = 0xCBD666E1
     329 [-]: LOADN R15 0  ; var15 = 0
     330 [-]: CALL R14 2 1 ; var14(var15)
L49: 331 [-]: NAMECALL R14 R0 K75; var15 = var0; var14 = var0[0xC8442850]
     332 [-]: CALL R14 2 2 ; var14 = var14(var15)
     333 [-]: LOADN R15 1  ; var15 = 1
     334 [-]: LOADN R16 -1 ; var16 = -1
     335 [-]: LOADB R17 0  ; var17 = false
     336 [-]: LOADB R18 0  ; var18 = false
     337 [-]: GETIMPORT R20 77; var20 = _T["HardModeAngel"]
     338 [-]: FASTCALL1 64 R20 L50; 
     339 [-]: GETIMPORT R19 8; var19 = 0x7B998233
     340 [-]: CALL R19 2 2 ; var19 = var19(var20)
L50: 341 [-]: JUMPIF R19 L51; goto L51 if var19
     342 [-]: GETIMPORT R18 77; var18 = _T["HardModeAngel"]
L51: 343 [-]: LOADN R19 0  ; var19 = 0
     344 [-]: JUMPIFNOTLT R19 R4 L52; goto L52 if var19 >= var70448
     345 [-]: LOADN R19 1  ; var19 = 1
     346 [-]: ADDK R20 R4 K60; var20 = var4 + 1
     347 [-]: DIV R16 R19 R20; var16 = var19 / var20
     348 [-]: SUB R15 R15 R16; var15 = var15 - var16
     349 [-]: JUMP L53     ; goto L53
L52: 350 [-]: LOADN R15 0  ; var15 = 0
L53: 351 [-]: LOADN R19 0  ; var19 = 0
     352 [-]: JUMPIFNOTLE R15 R19 L54; goto L54 if var15 > var5382
     353 [-]: LOADB R21 0  ; var21 = false
     354 [-]: NAMECALL R19 R1 K78; var20 = var1; var19 = var1[0x35577788]
     355 [-]: CALL R19 3 1 ; var19(var20, var21)
     356 [-]: JUMP L56     ; goto L56
L54: 357 [-]: JUMPIFNOTLT R14 R15 L55; goto L55 if var14 >= var269422353
     358 [-]: SUB R15 R15 R16; var15 = var15 - var16
     359 [-]: LOADB R17 1  ; var17 = true
     360 [-]: JUMPBACK L54 ; goto L54
L55: 361 [-]: MUL R21 R8 R15; var21 = var8 * var15
     362 [-]: NAMECALL R19 R1 K79; var20 = var1; var19 = var1[0xCCF4FF18]
     363 [-]: CALL R19 3 1 ; var19(var20, var21)
L56: 364 [-]: GETIMPORT R21 18; var21 = 0x0469F296
     365 [-]: LOADK R22 K22; var22 = "AngelSetupInvul"
     366 [-]: CALL R21 2 0 ; var21, ... = var21(var22)
     367 [-]: NAMECALL R19 R1 K80; var20 = var1; var19 = var1[0x8E3E343E]
     368 [-]: CALL R19 0 1 ; var19(var20, ...)
     369 [-]: LOADB R19 0  ; var19 = false
     370 [-]: LOADNIL R20  ; var20 = nil
     371 [-]: NAMECALL R21 R0 K81; var22 = var0; var21 = var0[0xF6EBD926]
     372 [-]: CALL R21 2 2 ; var21 = var21(var22)
     373 [-]: GETIMPORT R22 83; var22 = 0xC200E769
     374 [-]: GETIMPORT R23 85; var23 = 0x53FCE73B
     375 [-]: GETIMPORT R24 87; var24 = 0x7960CF12
     376 [-]: GETIMPORT R25 85; var25 = 0x53FCE73B
     377 [-]: NAMECALL R27 R9 K88; var28 = var9; var27 = var9[0xDED54C60]
     378 [-]: CALL R27 2 2 ; var27 = var27(var28)
     379 [-]: DIV R26 R27 R24; var26 = var27 / var24
     380 [-]: LOADN R27 0  ; var27 = 0
     381 [-]: LOADNIL R28  ; var28 = nil
     382 [-]: LOADNIL R29  ; var29 = nil
     383 [-]: GETIMPORT R30 33; var30 = 0xBE190284
     384 [-]: NAMECALL R30 R30 K34; var31 = var30; var30 = var30[0xEF893AEC]
     385 [-]: CALL R30 2 2 ; var30 = var30(var31)
     386 [-]: FASTCALL1 64 R30 L57; 
     387 [-]: MOVE R32 R30 ; var32 = var30
     388 [-]: GETIMPORT R31 8; var31 = 0x7B998233
     389 [-]: CALL R31 2 2 ; var31 = var31(var32)
L57: 390 [-]: JUMPIF R31 L67; goto L67 if var31
     391 [-]: GETTABLEKS R32 R30 K89; var32 = var30["goalTag"]
     392 [-]: GETIMPORT R33 18; var33 = 0x0469F296
     393 [-]: LOADK R34 K90; var34 = "ZarimanMissionFour"
     394 [-]: CALL R33 2 2 ; var33 = var33(var34)
     395 [-]: JUMPIFEQ R32 R33 L58; goto L58 if var32 == var16785158
     396 [-]: LOADB R31 0 +1; var31 = false
L58: 397 [-]: LOADB R31 1  ; var31 = true
L59: 398 [-]: SETUPVAL R31 2; upvalues[31] = var2
     399 [-]: GETTABLEKS R34 R30 K35; var34 = var30["levelOverride"]
     400 [-]: FASTCALL1 64 R34 L60; 
     401 [-]: GETIMPORT R33 8; var33 = 0x7B998233
     402 [-]: CALL R33 2 2 ; var33 = var33(var34)
L60: 403 [-]: NOT R32 R33  ; var32 = not var33
     404 [-]: JUMPIFNOT R32 L64; goto L64 if not var32
     405 [-]: GETTABLEKS R33 R30 K36; var33 = var30["keyChainName"]
     406 [-]: FASTCALL1 64 R33 L61; 
     407 [-]: GETIMPORT R32 8; var32 = 0x7B998233
     408 [-]: CALL R32 2 2 ; var32 = var32(var33)
L61: 409 [-]: JUMPIFNOT R32 L64; goto L64 if not var32
     410 [-]: GETIMPORT R33 39; var33 = 0x7F5022CF[0xA5C556B9]
     411 [-]: GETTABLEKS R35 R30 K35; var35 = var30["levelOverride"]
     412 [-]: NAMECALL R35 R35 K40; var36 = var35; var35 = var35[0xED4E0128]
     413 [-]: CALL R35 2 0 ; var35, ... = var35(var36)
     414 [-]: FASTCALL 63 L62; 
     415 [-]: GETIMPORT R34 42; var34 = 0x64FB1586
     416 [-]: CALL R34 0 2 ; var34 = var34(var35, ...)
L62: 417 [-]: LOADK R35 K43; var35 = "Entrati"
     418 [-]: CALL R33 3 2 ; var33 = var33(var34, var35)
     419 [-]: JUMPXEQKNIL R33 L63 NOT; 
     420 [-]: LOADB R32 0 +1; var32 = false
L63: 421 [-]: LOADB R32 1  ; var32 = true
L64: 422 [-]: JUMPIFNOT R32 L65; goto L65 if not var32
     423 [-]: LOADB R31 1  ; var31 = true
     424 [-]: JUMP L66     ; goto L66
L65: 425 [-]: LOADB R31 0  ; var31 = false
L66: 426 [-]: SETUPVAL R31 3; upvalues[31] = var3
L67: 427 [-]: FASTCALL1 64 R0 L68; 
     428 [-]: MOVE R32 R0  ; var32 = var0
     429 [-]: GETIMPORT R31 8; var31 = 0x7B998233
     430 [-]: CALL R31 2 2 ; var31 = var31(var32)
L68: 431 [-]: JUMPIF R31 L111; goto L111 if var31
     432 [-]: NAMECALL R31 R0 K91; var32 = var0; var31 = var0[0x2047CFE7]
     433 [-]: CALL R31 2 2 ; var31 = var31(var32)
     434 [-]: JUMPIF R31 L111; goto L111 if var31
     435 [-]: FASTCALL1 64 R9 L69; 
     436 [-]: MOVE R32 R9  ; var32 = var9
     437 [-]: GETIMPORT R31 8; var31 = 0x7B998233
     438 [-]: CALL R31 2 2 ; var31 = var31(var32)
L69: 439 [-]: JUMPIF R31 L111; goto L111 if var31
     440 [-]: GETIMPORT R32 33; var32 = 0xBE190284
     441 [-]: FASTCALL1 64 R32 L70; 
     442 [-]: GETIMPORT R31 8; var31 = 0x7B998233
     443 [-]: CALL R31 2 2 ; var31 = var31(var32)
L70: 444 [-]: JUMPIF R31 L71; goto L71 if var31
     445 [-]: GETIMPORT R31 33; var31 = 0xBE190284
     446 [-]: GETIMPORT R33 18; var33 = 0x0469F296
     447 [-]: LOADK R34 K67; var34 = "VoidAngelHealth"
     448 [-]: CALL R33 2 2 ; var33 = var33(var34)
     449 [-]: NAMECALL R35 R0 K75; var36 = var0; var35 = var0[0xC8442850]
     450 [-]: CALL R35 2 2 ; var35 = var35(var36)
     451 [-]: MULK R34 R35 K69; var34 = var35 * 100
     452 [-]: NAMECALL R31 R31 K53; var32 = var31; var31 = var31[0x751F061D]
     453 [-]: CALL R31 4 1 ; var31(var32, var33, var34)
L71: 454 [-]: NAMECALL R31 R0 K30; var32 = var0; var31 = var0[0x73901ACF]
     455 [-]: CALL R31 2 2 ; var31 = var31(var32)
     456 [-]: JUMPIFNOT R31 L77; goto L77 if not var31
     457 [-]: JUMPIF R19 L77; goto L77 if var19
     458 [-]: LOADB R33 0  ; var33 = false
     459 [-]: NAMECALL R31 R9 K92; var32 = var9; var31 = var9[0x1BF26251]
     460 [-]: CALL R31 3 1 ; var31(var32, var33)
     461 [-]: NAMECALL R31 R1 K93; var32 = var1; var31 = var1[0x47CB4A02]
     462 [-]: CALL R31 2 1 ; var31(var32)
     463 [-]: GETUPVAL R33 4; var33 = upvalues[4]
     464 [-]: LOADN R34 25 ; var34 = 25
     465 [-]: LOADN R35 6  ; var35 = 6
     466 [-]: LOADN R36 0  ; var36 = 0
     467 [-]: NAMECALL R31 R1 K23; var32 = var1; var31 = var1[0xA383DE31]
     468 [-]: CALL R31 6 1 ; var31(var32, var33, var34, var35, var36)
     469 [-]: GETUPVAL R33 4; var33 = upvalues[4]
     470 [-]: NAMECALL R31 R1 K94; var32 = var1; var31 = var1[0x857557DE]
     471 [-]: CALL R31 3 1 ; var31(var32, var33)
     472 [-]: LOADN R33 0  ; var33 = 0
     473 [-]: GETUPVAL R34 4; var34 = upvalues[4]
     474 [-]: NAMECALL R31 R0 K95; var32 = var0; var31 = var0[0xFFC58A04]
     475 [-]: CALL R31 4 1 ; var31(var32, var33, var34)
     476 [-]: LOADB R33 1  ; var33 = true
     477 [-]: NAMECALL R31 R0 K96; var32 = var0; var31 = var0[0x069D881F]
     478 [-]: CALL R31 3 1 ; var31(var32, var33)
     479 [-]: LOADN R33 0  ; var33 = 0
     480 [-]: LOADB R34 1  ; var34 = true
     481 [-]: NAMECALL R31 R9 K97; var32 = var9; var31 = var9[0x6E19D3FE]
     482 [-]: CALL R31 4 1 ; var31(var32, var33, var34)
     483 [-]: GETIMPORT R33 99; var33 = 0x9E24FD3C
     484 [-]: GETUPVAL R34 5; var34 = upvalues[5]
     485 [-]: GETIMPORT R35 101; var35 = ZERO_VECTOR
     486 [-]: GETIMPORT R36 103; var36 = ZERO_ROTATION
     487 [-]: MOVE R37 R0  ; var37 = var0
     488 [-]: NAMECALL R31 R0 K104; var32 = var0; var31 = var0[0x47901F07]
     489 [-]: CALL R31 7 2 ; var31 = var31(var32, var33, var34, var35, var36, var37)
     490 [-]: MOVE R20 R31 ; var20 = var31
     491 [-]: FASTCALL1 64 R0 L72; 
     492 [-]: MOVE R32 R0  ; var32 = var0
     493 [-]: GETIMPORT R31 8; var31 = 0x7B998233
     494 [-]: CALL R31 2 2 ; var31 = var31(var32)
L72: 495 [-]: JUMPIFNOT R31 L73; goto L73 if not var31
     496 [-]: RETURN R0 0  ; 
L73: 497 [-]: NAMECALL R31 R0 K81; var32 = var0; var31 = var0[0xF6EBD926]
     498 [-]: CALL R31 2 2 ; var31 = var31(var32)
     499 [-]: GETIMPORT R32 1; var32 = 0x89326C93
     500 [-]: GETIMPORT R34 106; var34 = 0xDE256C46
     501 [-]: GETIMPORT R35 108; var35 = 0xA421AF95
     502 [-]: GETTABLEKS R36 R31 K109; var36 = var31["x"]
     503 [-]: GETTABLEKS R38 R31 K111; var38 = var31["y"]
     504 [-]: ADDK R37 R38 K110; var37 = var38 + 4
     505 [-]: GETTABLEKS R38 R31 K112; var38 = var31["z"]
     506 [-]: CALL R35 4 2 ; var35 = var35(var36, var37, var38)
     507 [-]: NAMECALL R36 R0 K113; var37 = var0; var36 = var0[0xCB3851B8]
     508 [-]: CALL R36 2 2 ; var36 = var36(var37)
     509 [-]: MOVE R37 R0  ; var37 = var0
     510 [-]: MOVE R38 R0  ; var38 = var0
     511 [-]: NAMECALL R32 R32 K114; var33 = var32; var32 = var32[0x05909209]
     512 [-]: CALL R32 7 2 ; var32 = var32(var33, var34, var35, var36, var37, var38)
     513 [-]: MOVE R28 R32 ; var28 = var32
     514 [-]: GETIMPORT R32 1; var32 = 0x89326C93
     515 [-]: GETIMPORT R34 116; var34 = 0x29B3117E
     516 [-]: GETIMPORT R35 108; var35 = 0xA421AF95
     517 [-]: GETTABLEKS R36 R31 K109; var36 = var31["x"]
     518 [-]: GETTABLEKS R38 R31 K111; var38 = var31["y"]
     519 [-]: ADDK R37 R38 K117; var37 = var38 + 3.5
     520 [-]: GETTABLEKS R38 R31 K112; var38 = var31["z"]
     521 [-]: CALL R35 4 2 ; var35 = var35(var36, var37, var38)
     522 [-]: NAMECALL R36 R0 K113; var37 = var0; var36 = var0[0xCB3851B8]
     523 [-]: CALL R36 2 2 ; var36 = var36(var37)
     524 [-]: MOVE R37 R0  ; var37 = var0
     525 [-]: MOVE R38 R0  ; var38 = var0
     526 [-]: NAMECALL R32 R32 K114; var33 = var32; var32 = var32[0x05909209]
     527 [-]: CALL R32 7 2 ; var32 = var32(var33, var34, var35, var36, var37, var38)
     528 [-]: MOVE R29 R32 ; var29 = var32
     529 [-]: GETIMPORT R32 87; var32 = 0x7960CF12
     530 [-]: LOADN R34 60 ; var34 = 60
     531 [-]: MUL R33 R34 R27; var33 = var34 * var27
     532 [-]: ADD R24 R32 R33; var24 = var32 + var33
     533 [-]: NAMECALL R32 R9 K88; var33 = var9; var32 = var9[0xDED54C60]
     534 [-]: CALL R32 2 2 ; var32 = var32(var33)
     535 [-]: DIV R26 R32 R24; var26 = var32 / var24
     536 [-]: LOADB R19 1  ; var19 = true
     537 [-]: GETUPVAL R32 6; var32 = upvalues[6]
     538 [-]: JUMPIF R32 L110; goto L110 if var32
     539 [-]: GETUPVAL R32 2; var32 = upvalues[2]
     540 [-]: JUMPIFNOT R32 L74; goto L74 if not var32
     541 [-]: GETUPVAL R32 7; var32 = upvalues[7]
     542 [-]: GETUPVAL R33 3; var33 = upvalues[3]
     543 [-]: JUMPIF R33 L76; goto L76 if var33
     544 [-]: GETUPVAL R34 8; var34 = upvalues[8]
     545 [-]: GETTABLEKS R33 R34 K118; var33 = var34[0x9742B85B]
     546 [-]: GETIMPORT R34 120; var34 = 0x4430F697
     547 [-]: MOVE R35 R32 ; var35 = var32
     548 [-]: CALL R33 3 1 ; var33(var34, var35)
     549 [-]: JUMP L76     ; goto L76
L74: 550 [-]: GETUPVAL R32 3; var32 = upvalues[3]
     551 [-]: JUMPIFNOT R32 L75; goto L75 if not var32
     552 [-]: GETUPVAL R33 8; var33 = upvalues[8]
     553 [-]: GETTABLEKS R32 R33 K118; var32 = var33[0x9742B85B]
     554 [-]: GETIMPORT R33 122; var33 = _T["GargoyleEventTransmissionSet"]
     555 [-]: GETUPVAL R34 9; var34 = upvalues[9]
     556 [-]: CALL R32 3 1 ; var32(var33, var34)
     557 [-]: JUMP L76     ; goto L76
L75: 558 [-]: GETUPVAL R32 10; var32 = upvalues[10]
     559 [-]: GETUPVAL R33 3; var33 = upvalues[3]
     560 [-]: JUMPIF R33 L76; goto L76 if var33
     561 [-]: GETUPVAL R34 8; var34 = upvalues[8]
     562 [-]: GETTABLEKS R33 R34 K118; var33 = var34[0x9742B85B]
     563 [-]: GETIMPORT R34 120; var34 = 0x4430F697
     564 [-]: MOVE R35 R32 ; var35 = var32
     565 [-]: CALL R33 3 1 ; var33(var34, var35)
L76: 566 [-]: LOADB R32 1  ; var32 = true
     567 [-]: SETUPVAL R32 6; upvalues[32] = var6
     568 [-]: JUMP L110    ; goto L110
L77: 569 [-]: NAMECALL R31 R0 K30; var32 = var0; var31 = var0[0x73901ACF]
     570 [-]: CALL R31 2 2 ; var31 = var31(var32)
     571 [-]: JUMPIFNOT R31 L106; goto L106 if not var31
     572 [-]: JUMPIFNOT R19 L106; goto L106 if not var19
     573 [-]: LOADN R31 0  ; var31 = 0
     574 [-]: JUMPIFNOTLE R24 R31 L88; goto L88 if var24 > var1611211084
     575 [-]: NAMECALL R33 R9 K88; var34 = var9; var33 = var9[0xDED54C60]
     576 [-]: CALL R33 2 2 ; var33 = var33(var34)
     577 [-]: LOADB R34 1  ; var34 = true
     578 [-]: NAMECALL R31 R9 K97; var32 = var9; var31 = var9[0x6E19D3FE]
     579 [-]: CALL R31 4 1 ; var31(var32, var33, var34)
     580 [-]: NAMECALL R34 R0 K61; var35 = var0; var34 = var0[0xB40C191A]
     581 [-]: CALL R34 2 2 ; var34 = var34(var35)
     582 [-]: LOADN R36 1  ; var36 = 1
     583 [-]: ADD R37 R15 R16; var37 = var15 + var16
     584 [-]: FASTCALL2 19 R36 R37 L78; 
     585 [-]: GETIMPORT R35 124; var35 = 0x5BCED4C4[0xAC1B386A]
     586 [-]: CALL R35 3 2 ; var35 = var35(var36, var37)
L78: 587 [-]: MUL R33 R34 R35; var33 = var34 * var35
     588 [-]: NAMECALL R31 R0 K74; var32 = var0; var31 = var0[0x014DB014]
     589 [-]: CALL R31 3 1 ; var31(var32, var33)
     590 [-]: FASTCALL1 64 R20 L79; 
     591 [-]: MOVE R32 R20 ; var32 = var20
     592 [-]: GETIMPORT R31 8; var31 = 0x7B998233
     593 [-]: CALL R31 2 2 ; var31 = var31(var32)
L79: 594 [-]: JUMPIF R31 L80; goto L80 if var31
     595 [-]: NAMECALL R31 R20 K125; var32 = var20; var31 = var20[0x1DB57C6B]
     596 [-]: CALL R31 2 1 ; var31(var32)
L80: 597 [-]: FASTCALL1 64 R28 L81; 
     598 [-]: MOVE R32 R28 ; var32 = var28
     599 [-]: GETIMPORT R31 8; var31 = 0x7B998233
     600 [-]: CALL R31 2 2 ; var31 = var31(var32)
L81: 601 [-]: JUMPIF R31 L82; goto L82 if var31
     602 [-]: NAMECALL R31 R28 K125; var32 = var28; var31 = var28[0x1DB57C6B]
     603 [-]: CALL R31 2 1 ; var31(var32)
L82: 604 [-]: FASTCALL1 64 R29 L83; 
     605 [-]: MOVE R32 R29 ; var32 = var29
     606 [-]: GETIMPORT R31 8; var31 = 0x7B998233
     607 [-]: CALL R31 2 2 ; var31 = var31(var32)
L83: 608 [-]: JUMPIF R31 L84; goto L84 if var31
     609 [-]: NAMECALL R31 R29 K126; var32 = var29; var31 = var29[0xA2880940]
     610 [-]: CALL R31 2 1 ; var31(var32)
L84: 611 [-]: GETIMPORT R31 16; var31 = 0xCBD666E1
     612 [-]: LOADN R32 1  ; var32 = 1
     613 [-]: CALL R31 2 1 ; var31(var32)
     614 [-]: FASTCALL1 64 R0 L85; 
     615 [-]: MOVE R32 R0  ; var32 = var0
     616 [-]: GETIMPORT R31 8; var31 = 0x7B998233
     617 [-]: CALL R31 2 2 ; var31 = var31(var32)
L85: 618 [-]: JUMPIF R31 L111; goto L111 if var31
     619 [-]: FASTCALL1 64 R9 L86; 
     620 [-]: MOVE R32 R9  ; var32 = var9
     621 [-]: GETIMPORT R31 8; var31 = 0x7B998233
     622 [-]: CALL R31 2 2 ; var31 = var31(var32)
L86: 623 [-]: JUMPIF R31 L111; goto L111 if var31
     624 [-]: GETUPVAL R33 4; var33 = upvalues[4]
     625 [-]: NAMECALL R31 R1 K80; var32 = var1; var31 = var1[0x8E3E343E]
     626 [-]: CALL R31 3 1 ; var31(var32, var33)
     627 [-]: GETUPVAL R33 4; var33 = upvalues[4]
     628 [-]: NAMECALL R31 R1 K127; var32 = var1; var31 = var1[0x571105C9]
     629 [-]: CALL R31 3 1 ; var31(var32, var33)
     630 [-]: LOADN R33 0  ; var33 = 0
     631 [-]: GETUPVAL R34 4; var34 = upvalues[4]
     632 [-]: NAMECALL R31 R0 K128; var32 = var0; var31 = var0[0x250A9055]
     633 [-]: CALL R31 4 1 ; var31(var32, var33, var34)
     634 [-]: LOADB R33 0  ; var33 = false
     635 [-]: NAMECALL R31 R0 K96; var32 = var0; var31 = var0[0x069D881F]
     636 [-]: CALL R31 3 1 ; var31(var32, var33)
     637 [-]: LOADB R33 1  ; var33 = true
     638 [-]: NAMECALL R31 R9 K92; var32 = var9; var31 = var9[0x1BF26251]
     639 [-]: CALL R31 3 1 ; var31(var32, var33)
     640 [-]: LOADB R19 0  ; var19 = false
     641 [-]: ADDK R27 R27 K60; var27 = var27 + 1
     642 [-]: LOADN R33 0  ; var33 = 0
     643 [-]: LOADB R34 1  ; var34 = true
     644 [-]: NAMECALL R31 R9 K97; var32 = var9; var31 = var9[0x6E19D3FE]
     645 [-]: CALL R31 4 1 ; var31(var32, var33, var34)
     646 [-]: LOADN R33 0  ; var33 = 0
     647 [-]: NAMECALL R31 R1 K31; var32 = var1; var31 = var1[0x57369B8B]
     648 [-]: CALL R31 3 1 ; var31(var32, var33)
     649 [-]: GETUPVAL R31 11; var31 = upvalues[11]
     650 [-]: JUMPIF R31 L103; goto L103 if var31
     651 [-]: GETUPVAL R31 12; var31 = upvalues[12]
     652 [-]: GETUPVAL R32 3; var32 = upvalues[3]
     653 [-]: JUMPIF R32 L87; goto L87 if var32
     654 [-]: GETUPVAL R33 8; var33 = upvalues[8]
     655 [-]: GETTABLEKS R32 R33 K118; var32 = var33[0x9742B85B]
     656 [-]: GETIMPORT R33 120; var33 = 0x4430F697
     657 [-]: MOVE R34 R31 ; var34 = var31
     658 [-]: CALL R32 3 1 ; var32(var33, var34)
L87: 659 [-]: LOADB R31 1  ; var31 = true
     660 [-]: SETUPVAL R31 11; upvalues[31] = var11
     661 [-]: JUMP L103    ; goto L103
L88: 662 [-]: GETUPVAL R33 4; var33 = upvalues[4]
     663 [-]: NAMECALL R31 R1 K129; var32 = var1; var31 = var1[0x8733746A]
     664 [-]: CALL R31 3 2 ; var31 = var31(var32, var33)
     665 [-]: JUMPIF R31 L102; goto L102 if var31
     666 [-]: LOADN R33 0  ; var33 = 0
     667 [-]: LOADB R34 1  ; var34 = true
     668 [-]: NAMECALL R31 R9 K97; var32 = var9; var31 = var9[0x6E19D3FE]
     669 [-]: CALL R31 4 1 ; var31(var32, var33, var34)
     670 [-]: LOADN R33 0  ; var33 = 0
     671 [-]: NAMECALL R31 R1 K31; var32 = var1; var31 = var1[0x57369B8B]
     672 [-]: CALL R31 3 1 ; var31(var32, var33)
     673 [-]: FASTCALL1 64 R20 L89; 
     674 [-]: MOVE R32 R20 ; var32 = var20
     675 [-]: GETIMPORT R31 8; var31 = 0x7B998233
     676 [-]: CALL R31 2 2 ; var31 = var31(var32)
L89: 677 [-]: JUMPIF R31 L90; goto L90 if var31
     678 [-]: NAMECALL R31 R20 K125; var32 = var20; var31 = var20[0x1DB57C6B]
     679 [-]: CALL R31 2 1 ; var31(var32)
L90: 680 [-]: FASTCALL1 64 R28 L91; 
     681 [-]: MOVE R32 R28 ; var32 = var28
     682 [-]: GETIMPORT R31 8; var31 = 0x7B998233
     683 [-]: CALL R31 2 2 ; var31 = var31(var32)
L91: 684 [-]: JUMPIF R31 L92; goto L92 if var31
     685 [-]: NAMECALL R31 R28 K125; var32 = var28; var31 = var28[0x1DB57C6B]
     686 [-]: CALL R31 2 1 ; var31(var32)
L92: 687 [-]: FASTCALL1 64 R29 L93; 
     688 [-]: MOVE R32 R29 ; var32 = var29
     689 [-]: GETIMPORT R31 8; var31 = 0x7B998233
     690 [-]: CALL R31 2 2 ; var31 = var31(var32)
L93: 691 [-]: JUMPIF R31 L94; goto L94 if var31
     692 [-]: NAMECALL R31 R29 K126; var32 = var29; var31 = var29[0xA2880940]
     693 [-]: CALL R31 2 1 ; var31(var32)
L94: 694 [-]: GETIMPORT R31 1; var31 = 0x89326C93
     695 [-]: GETIMPORT R33 131; var33 = 0x7103C6A5
     696 [-]: GETUPVAL R36 5; var36 = upvalues[5]
     697 [-]: NAMECALL R34 R0 K132; var35 = var0; var34 = var0[0x003C792F]
     698 [-]: CALL R34 3 2 ; var34 = var34(var35, var36)
     699 [-]: NAMECALL R35 R0 K113; var36 = var0; var35 = var0[0xCB3851B8]
     700 [-]: CALL R35 2 2 ; var35 = var35(var36)
     701 [-]: MOVE R36 R0  ; var36 = var0
     702 [-]: MOVE R37 R0  ; var37 = var0
     703 [-]: NAMECALL R31 R31 K114; var32 = var31; var31 = var31[0x05909209]
     704 [-]: CALL R31 7 1 ; var31(var32, var33, var34, var35, var36, var37)
     705 [-]: GETUPVAL R33 13; var33 = upvalues[13]
     706 [-]: LOADN R34 25 ; var34 = 25
     707 [-]: LOADN R35 6  ; var35 = 6
     708 [-]: LOADN R36 0  ; var36 = 0
     709 [-]: NAMECALL R31 R1 K23; var32 = var1; var31 = var1[0xA383DE31]
     710 [-]: CALL R31 6 1 ; var31(var32, var33, var34, var35, var36)
     711 [-]: MOVE R31 R15 ; var31 = var15
     712 [-]: LOADN R33 0  ; var33 = 0
     713 [-]: SUB R34 R15 R16; var34 = var15 - var16
     714 [-]: FASTCALL2 18 R33 R34 L95; 
     715 [-]: GETIMPORT R32 73; var32 = 0x5BCED4C4[0xB62ECFE0]
     716 [-]: CALL R32 3 2 ; var32 = var32(var33, var34)
L95: 717 [-]: MOVE R15 R32 ; var15 = var32
     718 [-]: LOADN R32 0  ; var32 = 0
     719 [-]: JUMPIFNOTLE R15 R32 L96; goto L96 if var15 > var-56784
     720 [-]: LOADN R34 -1 ; var34 = -1
     721 [-]: NAMECALL R32 R1 K79; var33 = var1; var32 = var1[0xCCF4FF18]
     722 [-]: CALL R32 3 1 ; var32(var33, var34)
     723 [-]: LOADB R34 0  ; var34 = false
     724 [-]: NAMECALL R32 R1 K78; var33 = var1; var32 = var1[0x35577788]
     725 [-]: CALL R32 3 1 ; var32(var33, var34)
     726 [-]: JUMP L97     ; goto L97
L96: 727 [-]: MUL R34 R8 R15; var34 = var8 * var15
     728 [-]: NAMECALL R32 R1 K79; var33 = var1; var32 = var1[0xCCF4FF18]
     729 [-]: CALL R32 3 1 ; var32(var33, var34)
L97: 730 [-]: NAMECALL R35 R0 K61; var36 = var0; var35 = var0[0xB40C191A]
     731 [-]: CALL R35 2 2 ; var35 = var35(var36)
     732 [-]: MUL R34 R35 R31; var34 = var35 * var31
     733 [-]: NAMECALL R32 R0 K74; var33 = var0; var32 = var0[0x014DB014]
     734 [-]: CALL R32 3 1 ; var32(var33, var34)
     735 [-]: GETIMPORT R32 16; var32 = 0xCBD666E1
     736 [-]: LOADN R33 1  ; var33 = 1
     737 [-]: CALL R32 2 1 ; var32(var33)
     738 [-]: FASTCALL1 64 R0 L98; 
     739 [-]: MOVE R33 R0  ; var33 = var0
     740 [-]: GETIMPORT R32 8; var32 = 0x7B998233
     741 [-]: CALL R32 2 2 ; var32 = var32(var33)
L98: 742 [-]: JUMPIF R32 L111; goto L111 if var32
     743 [-]: FASTCALL1 64 R9 L99; 
     744 [-]: MOVE R33 R9  ; var33 = var9
     745 [-]: GETIMPORT R32 8; var32 = 0x7B998233
     746 [-]: CALL R32 2 2 ; var32 = var32(var33)
L99: 747 [-]: JUMPIF R32 L111; goto L111 if var32
     748 [-]: GETIMPORT R34 134; var34 = 0xD6FED0EE
     749 [-]: LOADB R35 1  ; var35 = true
     750 [-]: LOADN R36 2  ; var36 = 2
     751 [-]: LOADN R37 1  ; var37 = 1
     752 [-]: LOADB R38 1  ; var38 = true
     753 [-]: NAMECALL R32 R0 K135; var33 = var0; var32 = var0[0x5D985C7E]
     754 [-]: CALL R32 7 1 ; var32(var33, var34, var35, var36, var37, var38)
     755 [-]: FASTCALL1 64 R0 L100; 
     756 [-]: MOVE R33 R0  ; var33 = var0
     757 [-]: GETIMPORT R32 8; var32 = 0x7B998233
     758 [-]: CALL R32 2 2 ; var32 = var32(var33)
L100: 759 [-]: JUMPIFNOT R32 L101; goto L101 if not var32
     760 [-]: RETURN R0 0  ; 
L101: 761 [-]: GETUPVAL R34 13; var34 = upvalues[13]
     762 [-]: NAMECALL R32 R1 K80; var33 = var1; var32 = var1[0x8E3E343E]
     763 [-]: CALL R32 3 1 ; var32(var33, var34)
     764 [-]: GETUPVAL R34 4; var34 = upvalues[4]
     765 [-]: NAMECALL R32 R1 K127; var33 = var1; var32 = var1[0x571105C9]
     766 [-]: CALL R32 3 1 ; var32(var33, var34)
     767 [-]: LOADN R34 0  ; var34 = 0
     768 [-]: GETUPVAL R35 4; var35 = upvalues[4]
     769 [-]: NAMECALL R32 R0 K128; var33 = var0; var32 = var0[0x250A9055]
     770 [-]: CALL R32 4 1 ; var32(var33, var34, var35)
     771 [-]: LOADB R34 0  ; var34 = false
     772 [-]: NAMECALL R32 R0 K96; var33 = var0; var32 = var0[0x069D881F]
     773 [-]: CALL R32 3 1 ; var32(var33, var34)
     774 [-]: LOADB R34 1  ; var34 = true
     775 [-]: NAMECALL R32 R9 K92; var33 = var9; var32 = var9[0x1BF26251]
     776 [-]: CALL R32 3 1 ; var32(var33, var34)
     777 [-]: LOADB R19 0  ; var19 = false
     778 [-]: LOADB R17 1  ; var17 = true
     779 [-]: LOADN R27 0  ; var27 = 0
     780 [-]: GETUPVAL R32 2; var32 = upvalues[2]
     781 [-]: JUMPIF R32 L102; goto L102 if var32
     782 [-]: GETUPVAL R32 14; var32 = upvalues[14]
     783 [-]: GETUPVAL R33 3; var33 = upvalues[3]
     784 [-]: JUMPIF R33 L102; goto L102 if var33
     785 [-]: GETUPVAL R34 8; var34 = upvalues[8]
     786 [-]: GETTABLEKS R33 R34 K118; var33 = var34[0x9742B85B]
     787 [-]: GETIMPORT R34 120; var34 = 0x4430F697
     788 [-]: MOVE R35 R32 ; var35 = var32
     789 [-]: CALL R33 3 1 ; var33(var34, var35)
L102: 790 [-]: LOADN R31 0  ; var31 = 0
     791 [-]: JUMPIFNOTLE R25 R31 L103; goto L103 if var25 > var1188129
     792 [-]: GETIMPORT R33 18; var33 = 0x0469F296
     793 [-]: LOADK R34 K136; var34 = "SpawnPreDeathPortal"
     794 [-]: CALL R33 2 2 ; var33 = var33(var34)
     795 [-]: LOADB R34 0  ; var34 = false
     796 [-]: NAMECALL R31 R0 K137; var32 = var0; var31 = var0[0xD5F7912B]
     797 [-]: CALL R31 4 1 ; var31(var32, var33, var34)
     798 [-]: GETIMPORT R25 85; var25 = 0x53FCE73B
L103: 799 [-]: GETUPVAL R31 15; var31 = upvalues[15]
     800 [-]: MOVE R32 R0  ; var32 = var0
     801 [-]: MOVE R33 R29 ; var33 = var29
     802 [-]: CALL R31 3 1 ; var31(var32, var33)
     803 [-]: NAMECALL R34 R9 K138; var35 = var9; var34 = var9[0x58A4D5AC]
     804 [-]: CALL R34 2 2 ; var34 = var34(var35)
     805 [-]: GETIMPORT R36 57; var36 = 0x67652851
     806 [-]: CALL R36 1 2 ; var36 = var36()
     807 [-]: MUL R35 R26 R36; var35 = var26 * var36
     808 [-]: ADD R33 R34 R35; var33 = var34 + var35
     809 [-]: LOADB R34 1  ; var34 = true
     810 [-]: NAMECALL R31 R9 K97; var32 = var9; var31 = var9[0x6E19D3FE]
     811 [-]: CALL R31 4 1 ; var31(var32, var33, var34)
     812 [-]: GETIMPORT R31 57; var31 = 0x67652851
     813 [-]: CALL R31 1 2 ; var31 = var31()
     814 [-]: SUB R25 R25 R31; var25 = var25 - var31
     815 [-]: GETIMPORT R31 57; var31 = 0x67652851
     816 [-]: CALL R31 1 2 ; var31 = var31()
     817 [-]: SUB R24 R24 R31; var24 = var24 - var31
     818 [-]: GETIMPORT R32 87; var32 = 0x7960CF12
          820 [-]: JUMPIFNOTLT R24 R31 L110; goto L110 if var24 >= var1056572
     821 [-]: GETUPVAL R31 16; var31 = upvalues[16]
     822 [-]: JUMPIF R31 L110; goto L110 if var31
     823 [-]: GETUPVAL R31 2; var31 = upvalues[2]
     824 [-]: JUMPIFNOT R31 L104; goto L104 if not var31
     825 [-]: GETUPVAL R31 17; var31 = upvalues[17]
     826 [-]: GETUPVAL R32 3; var32 = upvalues[3]
     827 [-]: JUMPIF R32 L105; goto L105 if var32
     828 [-]: GETUPVAL R33 8; var33 = upvalues[8]
     829 [-]: GETTABLEKS R32 R33 K118; var32 = var33[0x9742B85B]
     830 [-]: GETIMPORT R33 120; var33 = 0x4430F697
     831 [-]: MOVE R34 R31 ; var34 = var31
     832 [-]: CALL R32 3 1 ; var32(var33, var34)
     833 [-]: JUMP L105    ; goto L105
L104: 834 [-]: GETUPVAL R31 18; var31 = upvalues[18]
     835 [-]: GETUPVAL R32 3; var32 = upvalues[3]
     836 [-]: JUMPIF R32 L105; goto L105 if var32
     837 [-]: GETUPVAL R33 8; var33 = upvalues[8]
     838 [-]: GETTABLEKS R32 R33 K118; var32 = var33[0x9742B85B]
     839 [-]: GETIMPORT R33 120; var33 = 0x4430F697
     840 [-]: MOVE R34 R31 ; var34 = var31
     841 [-]: CALL R32 3 1 ; var32(var33, var34)
L105: 842 [-]: LOADB R31 1  ; var31 = true
     843 [-]: SETUPVAL R31 16; upvalues[31] = var16
     844 [-]: JUMP L110    ; goto L110
L106: 845 [-]: NAMECALL R31 R0 K30; var32 = var0; var31 = var0[0x73901ACF]
     846 [-]: CALL R31 2 2 ; var31 = var31(var32)
     847 [-]: JUMPIF R31 L110; goto L110 if var31
     848 [-]: LOADN R31 0  ; var31 = 0
     849 [-]: JUMPIFNOTLE R22 R31 L109; goto L109 if var22 > var2625812
     850 [-]: JUMPIFNOT R17 L109; goto L109 if not var17
     851 [-]: GETUPVAL R33 19; var33 = upvalues[19]
     852 [-]: NAMECALL R31 R1 K129; var32 = var1; var31 = var1[0x8733746A]
     853 [-]: CALL R31 3 2 ; var31 = var31(var32, var33)
     854 [-]: JUMPIF R31 L109; goto L109 if var31
     855 [-]: GETIMPORT R32 1; var32 = 0x89326C93
     856 [-]: GETUPVAL R34 20; var34 = upvalues[20]
     857 [-]: NAMECALL R35 R0 K81; var36 = var0; var35 = var0[0xF6EBD926]
     858 [-]: CALL R35 2 2 ; var35 = var35(var36)
     859 [-]: LOADN R36 0  ; var36 = 0
     860 [-]: GETIMPORT R37 141; var37 = 0xDD9CDABC
     861 [-]: NAMECALL R32 R32 K142; var33 = var32; var32 = var32[0x462C251C]
     862 [-]: CALL R32 6 0 ; var32, ... = var32(var33, var34, var35, var36, var37)
     863 [-]: FASTCALL 64 L107; 
     864 [-]: GETIMPORT R31 8; var31 = 0x7B998233
     865 [-]: CALL R31 0 2 ; var31 = var31(var32, ...)
L107: 866 [-]: JUMPIFNOT R31 L108; goto L108 if not var31
     867 [-]: NAMECALL R31 R0 K81; var32 = var0; var31 = var0[0xF6EBD926]
     868 [-]: CALL R31 2 2 ; var31 = var31(var32)
     869 [-]: MOVE R21 R31 ; var21 = var31
     870 [-]: GETIMPORT R31 1; var31 = 0x89326C93
     871 [-]: GETIMPORT R33 144; var33 = 0x4171F3EF
     872 [-]: MOVE R34 R21 ; var34 = var21
     873 [-]: GETIMPORT R35 103; var35 = ZERO_ROTATION
     874 [-]: MOVE R36 R0  ; var36 = var0
     875 [-]: MOVE R37 R0  ; var37 = var0
     876 [-]: NAMECALL R31 R31 K114; var32 = var31; var31 = var31[0x05909209]
     877 [-]: CALL R31 7 1 ; var31(var32, var33, var34, var35, var36, var37)
L108: 878 [-]: GETIMPORT R22 83; var22 = 0xC200E769
L109: 879 [-]: LOADN R31 0  ; var31 = 0
     880 [-]: JUMPIFNOTLE R23 R31 L110; goto L110 if var23 > var987668
     881 [-]: JUMPIFNOT R18 L110; goto L110 if not var18
     882 [-]: GETUPVAL R33 19; var33 = upvalues[19]
     883 [-]: NAMECALL R31 R1 K129; var32 = var1; var31 = var1[0x8733746A]
     884 [-]: CALL R31 3 2 ; var31 = var31(var32, var33)
     885 [-]: JUMPIF R31 L110; goto L110 if var31
     886 [-]: GETIMPORT R33 18; var33 = 0x0469F296
     887 [-]: LOADK R34 K136; var34 = "SpawnPreDeathPortal"
     888 [-]: CALL R33 2 2 ; var33 = var33(var34)
     889 [-]: LOADB R34 0  ; var34 = false
     890 [-]: NAMECALL R31 R0 K137; var32 = var0; var31 = var0[0xD5F7912B]
     891 [-]: CALL R31 4 1 ; var31(var32, var33, var34)
     892 [-]: GETIMPORT R23 85; var23 = 0x53FCE73B
L110: 893 [-]: GETIMPORT R31 57; var31 = 0x67652851
     894 [-]: CALL R31 1 2 ; var31 = var31()
     895 [-]: SUB R23 R23 R31; var23 = var23 - var31
     896 [-]: GETIMPORT R31 57; var31 = 0x67652851
     897 [-]: CALL R31 1 2 ; var31 = var31()
     898 [-]: SUB R22 R22 R31; var22 = var22 - var31
     899 [-]: GETIMPORT R31 16; var31 = 0xCBD666E1
     900 [-]: LOADN R32 0  ; var32 = 0
     901 [-]: CALL R31 2 1 ; var31(var32)
     902 [-]: JUMPBACK L67 ; goto L67
L111: 903 [-]: GETIMPORT R32 33; var32 = 0xBE190284
     904 [-]: FASTCALL1 64 R32 L112; 
     905 [-]: GETIMPORT R31 8; var31 = 0x7B998233
     906 [-]: CALL R31 2 2 ; var31 = var31(var32)
L112: 907 [-]: JUMPIF R31 L113; goto L113 if var31
     908 [-]: GETIMPORT R31 33; var31 = 0xBE190284
     909 [-]: GETIMPORT R33 18; var33 = 0x0469F296
     910 [-]: LOADK R34 K67; var34 = "VoidAngelHealth"
     911 [-]: CALL R33 2 0 ; var33, ... = var33(var34)
     912 [-]: NAMECALL R31 R31 K145; var32 = var31; var31 = var31[0xB9BFD47C]
     913 [-]: CALL R31 0 1 ; var31(var32, ...)
L113: 914 [-]: GETIMPORT R33 147; var33 = 0x4A6A6C13
     915 [-]: LOADB R34 0  ; var34 = false
     916 [-]: NAMECALL R31 R0 K148; var32 = var0; var31 = var0[0x659D451F]
     917 [-]: CALL R31 4 1 ; var31(var32, var33, var34)
     918 [-]: GETUPVAL R31 3; var31 = upvalues[3]
     919 [-]: JUMPIFNOT R31 L114; goto L114 if not var31
     920 [-]: GETUPVAL R32 8; var32 = upvalues[8]
     921 [-]: GETTABLEKS R31 R32 K118; var31 = var32[0x9742B85B]
     922 [-]: GETIMPORT R32 122; var32 = _T["GargoyleEventTransmissionSet"]
     923 [-]: GETUPVAL R33 21; var33 = upvalues[21]
     924 [-]: CALL R31 3 1 ; var31(var32, var33)
L114: 925 [-]: FASTCALL1 64 R12 L115; 
     926 [-]: MOVE R32 R12 ; var32 = var12
     927 [-]: GETIMPORT R31 8; var31 = 0x7B998233
     928 [-]: CALL R31 2 2 ; var31 = var31(var32)
L115: 929 [-]: JUMPIF R31 L116; goto L116 if var31
     930 [-]: JUMPIF R11 L116; goto L116 if var11
     931 [-]: MOVE R33 R0  ; var33 = var0
     932 [-]: LOADB R34 1  ; var34 = true
     933 [-]: LOADN R35 0  ; var35 = 0
     934 [-]: LOADN R36 7  ; var36 = 7
     935 [-]: NAMECALL R31 R12 K66; var32 = var12; var31 = var12[0x208E54F9]
     936 [-]: CALL R31 6 1 ; var31(var32, var33, var34, var35, var36)
L116: 937 [-]: GETIMPORT R31 1; var31 = 0x89326C93
     938 [-]: NAMECALL R31 R31 K2; var32 = var31; var31 = var31[0x18D05D30]
     939 [-]: CALL R31 2 2 ; var31 = var31(var32)
     940 [-]: JUMPIFNOT R31 L119; goto L119 if not var31
     941 [-]: GETIMPORT R31 150; var31 = 0x79023541
     942 [-]: LOADN R32 0  ; var32 = 0
     943 [-]: JUMPIFNOTLT R32 R31 L119; goto L119 if var32 >= var50348093
     944 [-]: FASTCALL1 64 R0 L117; 
     945 [-]: MOVE R32 R0  ; var32 = var0
     946 [-]: GETIMPORT R31 8; var31 = 0x7B998233
     947 [-]: CALL R31 2 2 ; var31 = var31(var32)
L117: 948 [-]: JUMPIF R31 L119; goto L119 if var31
     949 [-]: NAMECALL R31 R0 K91; var32 = var0; var31 = var0[0x2047CFE7]
     950 [-]: CALL R31 2 2 ; var31 = var31(var32)
     951 [-]: JUMPIFNOT R31 L119; goto L119 if not var31
     952 [-]: GETIMPORT R31 16; var31 = 0xCBD666E1
     953 [-]: GETIMPORT R32 152; var32 = 0x8D1C6947
     954 [-]: CALL R31 2 1 ; var31(var32)
     955 [-]: FASTCALL1 64 R0 L118; 
     956 [-]: MOVE R32 R0  ; var32 = var0
     957 [-]: GETIMPORT R31 8; var31 = 0x7B998233
     958 [-]: CALL R31 2 2 ; var31 = var31(var32)
L118: 959 [-]: JUMPIF R31 L119; goto L119 if var31
     960 [-]: GETIMPORT R33 150; var33 = 0x79023541
     961 [-]: NAMECALL R31 R0 K153; var32 = var0; var31 = var0[0x259B9467]
     962 [-]: CALL R31 3 1 ; var31(var32, var33)
L119: 963 [-]: RETURN R0 0  ; 


; Name:            
; Defined at line: 977
; #Upvalues:       0
; #Parameters:     1
; Is_vararg:       0
; Max Stack Size:  11

       0 [-]: LOADB R3 0   ; var3 = false
       1 [-]: NAMECALL R1 R0 K0; var2 = var0; var1 = var0[0xD749DA12]
       2 [-]: CALL R1 3 1  ; var1(var2, var3)
       3 [-]: GETIMPORT R1 2; var1 = 0xBE190284
       4 [-]: NAMECALL R1 R1 K3; var2 = var1; var1 = var1[0xEF893AEC]
       5 [-]: CALL R1 2 2  ; var1 = var1(var2)
       6 [-]: GETTABLEKS R2 R1 K4; var2 = var1["syndicateTag"]
       7 [-]: LOADB R3 0   ; var3 = false
       8 [-]: GETIMPORT R4 6; var4 = EMPTY_SYMBOL
       9 [-]: JUMPIFNOTEQ R2 R4 L4; goto L4 if var2 ~= var788596031
      10 [-]: GETTABLEKS R5 R1 K7; var5 = var1["levelOverride"]
      11 [-]: FASTCALL1 64 R5 L0; 
      12 [-]: GETIMPORT R4 9; var4 = 0x7B998233
      13 [-]: CALL R4 2 2  ; var4 = var4(var5)
L 0:  14 [-]: NOT R3 R4    ; var3 = not var4
      15 [-]: JUMPIFNOT R3 L4; goto L4 if not var3
      16 [-]: GETTABLEKS R4 R1 K10; var4 = var1["keyChainName"]
      17 [-]: FASTCALL1 64 R4 L1; 
      18 [-]: GETIMPORT R3 9; var3 = 0x7B998233
      19 [-]: CALL R3 2 2  ; var3 = var3(var4)
L 1:  20 [-]: JUMPIFNOT R3 L4; goto L4 if not var3
      21 [-]: GETIMPORT R4 13; var4 = 0x7F5022CF[0xA5C556B9]
      22 [-]: GETTABLEKS R6 R1 K7; var6 = var1["levelOverride"]
      23 [-]: NAMECALL R6 R6 K14; var7 = var6; var6 = var6[0xED4E0128]
      24 [-]: CALL R6 2 0  ; var6, ... = var6(var7)
      25 [-]: FASTCALL 63 L2; 
      26 [-]: GETIMPORT R5 16; var5 = 0x64FB1586
      27 [-]: CALL R5 0 2  ; var5 = var5(var6, ...)
L 2:  28 [-]: LOADK R6 K17 ; var6 = "Entrati"
      29 [-]: CALL R4 3 2  ; var4 = var4(var5, var6)
      30 [-]: JUMPXEQKNIL R4 L3 NOT; 
      31 [-]: LOADB R3 0 +1; var3 = false
L 3:  32 [-]: LOADB R3 1   ; var3 = true
L 4:  33 [-]: GETIMPORT R5 2; var5 = 0xBE190284
      34 [-]: FASTCALL1 64 R5 L5; 
      35 [-]: GETIMPORT R4 9; var4 = 0x7B998233
      36 [-]: CALL R4 2 2  ; var4 = var4(var5)
L 5:  37 [-]: JUMPIF R4 L7 ; goto L7 if var4
      38 [-]: JUMPIF R3 L7 ; goto L7 if var3
      39 [-]: GETIMPORT R4 2; var4 = 0xBE190284
      40 [-]: NAMECALL R4 R4 K18; var5 = var4; var4 = var4[0xABF50B1C]
      41 [-]: CALL R4 2 2  ; var4 = var4(var5)
      42 [-]: FASTCALL1 64 R4 L6; 
      43 [-]: MOVE R6 R4   ; var6 = var4
      44 [-]: GETIMPORT R5 9; var5 = 0x7B998233
      45 [-]: CALL R5 2 2  ; var5 = var5(var6)
L 6:  46 [-]: JUMPIF R5 L7 ; goto L7 if var5
      47 [-]: MOVE R7 R0   ; var7 = var0
      48 [-]: LOADB R8 1   ; var8 = true
      49 [-]: LOADN R9 1000; var9 = 1000
      50 [-]: LOADN R10 7  ; var10 = 7
      51 [-]: NAMECALL R5 R4 K19; var6 = var4; var5 = var4[0x208E54F9]
      52 [-]: CALL R5 6 1  ; var5(var6, var7, var8, var9, var10)
L 7:  53 [-]: RETURN R0 0  ; 


; Name:            
; Defined at line: 993
; #Upvalues:       1
; #Parameters:     1
; Is_vararg:       0
; Max Stack Size:  3

       0 [-]: FASTCALL1 64 R0 L0; 
       1 [-]: MOVE R2 R0   ; var2 = var0
       2 [-]: GETIMPORT R1 1; var1 = 0x7B998233
       3 [-]: CALL R1 2 2  ; var1 = var1(var2)
L 0:   4 [-]: JUMPIF R1 L1 ; goto L1 if var1
       5 [-]: SETUPVAL R0 0; upvalues[0] = var0
       6 [-]: RETURN R0 0  ; 
L 1:   7 [-]: LOADB R1 0   ; var1 = false
       8 [-]: SETUPVAL R1 0; upvalues[1] = var0
       9 [-]: RETURN R0 0  ; 


; Name:            
; Defined at line: 1001
; #Upvalues:       1
; #Parameters:     0
; Is_vararg:       0
; Max Stack Size:  9

L 0:   0 [-]: GETIMPORT R1 1; var1 = 0x89326C93
       1 [-]: NAMECALL R1 R1 K2; var2 = var1; var1 = var1[0xFB64E76C]
       2 [-]: CALL R1 2 0  ; var1, ... = var1(var2)
       3 [-]: FASTCALL 64 L1; 
       4 [-]: GETIMPORT R0 4; var0 = 0x7B998233
       5 [-]: CALL R0 0 2  ; var0 = var0(var1, ...)
L 1:   6 [-]: JUMPIFNOT R0 L2; goto L2 if not var0
       7 [-]: GETIMPORT R0 6; var0 = 0xCBD666E1
       8 [-]: LOADN R1 1   ; var1 = 1
       9 [-]: CALL R0 2 1  ; var0(var1)
      10 [-]: JUMPBACK L0  ; goto L0
L 2:  11 [-]: GETIMPORT R0 1; var0 = 0x89326C93
      12 [-]: NAMECALL R0 R0 K7; var1 = var0; var0 = var0[0x29EF273D]
      13 [-]: CALL R0 2 2  ; var0 = var0(var1)
      14 [-]: NAMECALL R0 R0 K8; var1 = var0; var0 = var0[0x66905CB0]
      15 [-]: CALL R0 2 2  ; var0 = var0(var1)
      16 [-]: GETIMPORT R1 10; var1 = 0xBE190284
      17 [-]: NAMECALL R1 R1 K11; var2 = var1; var1 = var1[0xD7D79B74]
      18 [-]: CALL R1 2 2  ; var1 = var1(var2)
      19 [-]: LOADN R4 1   ; var4 = 1
      20 [-]: NAMECALL R2 R0 K12; var3 = var0; var2 = var0[0xE2809E87]
      21 [-]: CALL R2 3 1  ; var2(var3, var4)
      22 [-]: FASTCALL1 64 R1 L3; 
      23 [-]: MOVE R3 R1   ; var3 = var1
      24 [-]: GETIMPORT R2 4; var2 = 0x7B998233
      25 [-]: CALL R2 2 2  ; var2 = var2(var3)
L 3:  26 [-]: JUMPIFNOT R2 L4; goto L4 if not var2
      27 [-]: RETURN R0 0  ; 
L 4:  28 [-]: GETIMPORT R4 14; var4 = 0xF55ACB1C
      29 [-]: LOADNIL R5   ; var5 = nil
      30 [-]: LOADB R6 0   ; var6 = false
      31 [-]: LOADB R7 0   ; var7 = false
      32 [-]: LOADK R8 K15 ; var8 = "VoidAngelReady"
      33 [-]: NAMECALL R2 R1 K16; var3 = var1; var2 = var1[0xE091CA15]
      34 [-]: CALL R2 7 1  ; var2(var3, var4, var5, var6, var7, var8)
      35 [-]: GETIMPORT R2 1; var2 = 0x89326C93
      36 [-]: GETIMPORT R4 18; var4 = 0x0469F296
      37 [-]: LOADK R5 K19 ; var5 = "VoidAngelTestSpawn"
      38 [-]: CALL R4 2 0  ; var4, ... = var4(var5)
      39 [-]: NAMECALL R2 R2 K20; var3 = var2; var2 = var2[0x46A0EBF5]
      40 [-]: CALL R2 0 2  ; var2 = var2(var3, ...)
      41 [-]: NAMECALL R2 R2 K21; var3 = var2; var2 = var2[0xD1586535]
      42 [-]: CALL R2 2 2  ; var2 = var2(var3)
      43 [-]: FASTCALL1 64 R2 L5; 
      44 [-]: MOVE R4 R2   ; var4 = var2
      45 [-]: GETIMPORT R3 4; var3 = 0x7B998233
      46 [-]: CALL R3 2 2  ; var3 = var3(var4)
L 5:  47 [-]: JUMPIFNOT R3 L6; goto L6 if not var3
      48 [-]: GETIMPORT R3 1; var3 = 0x89326C93
      49 [-]: NAMECALL R3 R3 K22; var4 = var3; var3 = var3[0x78298275]
      50 [-]: CALL R3 2 2  ; var3 = var3(var4)
      51 [-]: NAMECALL R3 R3 K21; var4 = var3; var3 = var3[0xD1586535]
      52 [-]: CALL R3 2 2  ; var3 = var3(var4)
      53 [-]: MOVE R2 R3   ; var2 = var3
L 6:  54 [-]: GETUPVAL R3 0; var3 = upvalues[0]
      55 [-]: JUMPXEQKNIL R3 L7 NOT; 
      56 [-]: GETIMPORT R3 6; var3 = 0xCBD666E1
      57 [-]: LOADN R4 0   ; var4 = 0
      58 [-]: CALL R3 2 1  ; var3(var4)
      59 [-]: JUMPBACK L6  ; goto L6
L 7:  60 [-]: GETUPVAL R3 0; var3 = upvalues[0]
      61 [-]: NAMECALL R3 R3 K23; var4 = var3; var3 = var3[0x5163741E]
      62 [-]: CALL R3 2 2  ; var3 = var3(var4)
      63 [-]: LOADN R5 50  ; var5 = 50
      64 [-]: NAMECALL R3 R3 K24; var4 = var3; var3 = var3[0x8623CF14]
      65 [-]: CALL R3 3 1  ; var3(var4, var5)
      66 [-]: GETUPVAL R3 0; var3 = upvalues[0]
      67 [-]: NAMECALL R3 R3 K23; var4 = var3; var3 = var3[0x5163741E]
      68 [-]: CALL R3 2 2  ; var3 = var3(var4)
      69 [-]: MOVE R5 R2   ; var5 = var2
      70 [-]: GETIMPORT R6 26; var6 = 0x00046924
      71 [-]: CALL R6 1 0  ; var6, ... = var6()
      72 [-]: NAMECALL R3 R3 K27; var4 = var3; var3 = var3[0x589EF1C1]
      73 [-]: CALL R3 0 1  ; var3(var4, ...)
      74 [-]: RETURN R0 0  ; 


; Name:            
; Defined at line: 1034
; #Upvalues:       2
; #Parameters:     1
; Is_vararg:       0
; Max Stack Size:  15

       0 [-]: GETIMPORT R1 1; var1 = 0x89326C93
       1 [-]: NAMECALL R1 R1 K2; var2 = var1; var1 = var1[0x29EF273D]
       2 [-]: CALL R1 2 2  ; var1 = var1(var2)
L 0:   3 [-]: NAMECALL R2 R1 K3; var3 = var1; var2 = var1[0x4BDE2087]
       4 [-]: CALL R2 2 2  ; var2 = var2(var3)
       5 [-]: JUMPIF R2 L1 ; goto L1 if var2
       6 [-]: GETIMPORT R2 5; var2 = 0xCBD666E1
       7 [-]: LOADK R3 K6  ; var3 = 0.10000000149011612
       8 [-]: CALL R2 2 1  ; var2(var3)
       9 [-]: JUMPBACK L0  ; goto L0
L 1:  10 [-]: GETIMPORT R2 1; var2 = 0x89326C93
      11 [-]: NAMECALL R2 R2 K2; var3 = var2; var2 = var2[0x29EF273D]
      12 [-]: CALL R2 2 2  ; var2 = var2(var3)
      13 [-]: NAMECALL R2 R2 K7; var3 = var2; var2 = var2[0x66905CB0]
      14 [-]: CALL R2 2 2  ; var2 = var2(var3)
      15 [-]: GETIMPORT R3 1; var3 = 0x89326C93
      16 [-]: GETUPVAL R5 0; var5 = upvalues[0]
      17 [-]: NAMECALL R3 R3 K8; var4 = var3; var3 = var3[0xC7FCADA9]
      18 [-]: CALL R3 3 2  ; var3 = var3(var4, var5)
      19 [-]: LOADNIL R4   ; var4 = nil
      20 [-]: GETIMPORT R5 10; var5 = 0xC8802016
      21 [-]: MOVE R6 R3   ; var6 = var3
      22 [-]: CALL R5 2 4  ; var5, var6, var7 = var5(var6)
      23 [-]: FORGPREP_INEXT R5 L4; 
L 2:  24 [-]: NAMECALL R10 R9 K11; var11 = var9; var10 = var9[0xE79E7EF4]
      25 [-]: CALL R10 2 2 ; var10 = var10(var11)
      26 [-]: MOVE R4 R10  ; var4 = var10
      27 [-]: FASTCALL1 64 R4 L3; 
      28 [-]: MOVE R11 R4  ; var11 = var4
      29 [-]: GETIMPORT R10 13; var10 = 0x7B998233
      30 [-]: CALL R10 2 2 ; var10 = var10(var11)
L 3:  31 [-]: JUMPIF R10 L4; goto L4 if var10
      32 [-]: NAMECALL R10 R4 K14; var11 = var4; var10 = var4[0xB06572DA]
      33 [-]: CALL R10 2 2 ; var10 = var10(var11)
      34 [-]: NAMECALL R12 R0 K16; var13 = var0; var12 = var0[0x26E191C7]
      35 [-]: CALL R12 2 2 ; var12 = var12(var13)
      36 [-]: ADDK R11 R12 K15; var11 = var12 + 1
      37 [-]: JUMPIFNOTEQ R10 R11 L4; goto L4 if var10 ~= var1117255
      38 [-]: LOADK R12 K17; var12 = "Execute"
      39 [-]: NAMECALL R10 R9 K18; var11 = var9; var10 = var9[0x8EB2112D]
      40 [-]: CALL R10 3 1 ; var10(var11, var12)
L 4:  41 [-]: FORGLOOP R5 L2 2 [inext]; 
      42 [-]: GETIMPORT R6 20; var6 = 0x46F77903
      43 [-]: FASTCALL1 64 R6 L5; 
      44 [-]: GETIMPORT R5 13; var5 = 0x7B998233
      45 [-]: CALL R5 2 2  ; var5 = var5(var6)
L 5:  46 [-]: JUMPIF R5 L8 ; goto L8 if var5
      47 [-]: NAMECALL R5 R2 K21; var6 = var2; var5 = var2[0x5E895E79]
      48 [-]: CALL R5 2 2  ; var5 = var5(var6)
      49 [-]: JUMPIFNOT R5 L8; goto L8 if not var5
      50 [-]: GETIMPORT R5 1; var5 = 0x89326C93
      51 [-]: GETUPVAL R7 1; var7 = upvalues[1]
      52 [-]: NAMECALL R5 R5 K8; var6 = var5; var5 = var5[0xC7FCADA9]
      53 [-]: CALL R5 3 2  ; var5 = var5(var6, var7)
      54 [-]: GETIMPORT R6 10; var6 = 0xC8802016
      55 [-]: MOVE R7 R5   ; var7 = var5
      56 [-]: CALL R6 2 4  ; var6, var7, var8 = var6(var7)
      57 [-]: FORGPREP_INEXT R6 L7; 
L 6:  58 [-]: MOVE R13 R10 ; var13 = var10
      59 [-]: NAMECALL R11 R0 K22; var12 = var0; var11 = var0[0x7941D56E]
      60 [-]: CALL R11 3 2 ; var11 = var11(var12, var13)
      61 [-]: JUMPIFNOT R11 L7; goto L7 if not var11
      62 [-]: NAMECALL R11 R10 K23; var12 = var10; var11 = var10[0xD8140B94]
      63 [-]: CALL R11 2 2 ; var11 = var11(var12)
      64 [-]: JUMPIF R11 L7; goto L7 if var11
      65 [-]: MOVE R13 R10 ; var13 = var10
      66 [-]: NAMECALL R11 R2 K24; var12 = var2; var11 = var2[0xE6069BBF]
      67 [-]: CALL R11 3 1 ; var11(var12, var13)
      68 [-]: MOVE R13 R10 ; var13 = var10
      69 [-]: GETIMPORT R14 20; var14 = 0x46F77903
      70 [-]: NAMECALL R11 R2 K25; var12 = var2; var11 = var2[0x79275474]
      71 [-]: CALL R11 4 1 ; var11(var12, var13, var14)
L 7:  72 [-]: FORGLOOP R6 L6 2 [inext]; 
L 8:  73 [-]: RETURN R0 0  ; 


; Name:            
; Defined at line: 1067
; #Upvalues:       17
; #Parameters:     1
; Is_vararg:       0
; Max Stack Size:  14

       0 [-]: GETIMPORT R1 1; var1 = 0xCBD666E1
       1 [-]: LOADN R2 0   ; var2 = 0
       2 [-]: CALL R1 2 1  ; var1(var2)
       3 [-]: NAMECALL R1 R0 K2; var2 = var0; var1 = var0[0x53C3399F]
       4 [-]: CALL R1 2 2  ; var1 = var1(var2)
       5 [-]: JUMPXEQKN R1 K3 L0 NOT; 
       6 [-]: RETURN R0 0  ; 
L 0:   7 [-]: JUMPXEQKN R1 K4 L4 NOT; 
       8 [-]: GETIMPORT R2 6; var2 = 0x89326C93
       9 [-]: NAMECALL R2 R2 K7; var3 = var2; var2 = var2[0x18D05D30]
      10 [-]: CALL R2 2 2  ; var2 = var2(var3)
      11 [-]: JUMPIFNOT R2 L33; goto L33 if not var2
      12 [-]: GETUPVAL R3 0; var3 = upvalues[0]
      13 [-]: GETTABLEKS R2 R3 K8; var2 = var3["maxValue"]
      14 [-]: GETIMPORT R3 11; var3 = _T["EtherealAngelLevelOverride"]
      15 [-]: JUMPIFNOT R3 L1; goto L1 if not var3
      16 [-]: GETIMPORT R2 11; var2 = _T["EtherealAngelLevelOverride"]
L 1:  17 [-]: GETUPVAL R3 1; var3 = upvalues[1]
      18 [-]: GETIMPORT R5 13; var5 = 0x5F88F07D
      19 [-]: GETUPVAL R6 2; var6 = upvalues[2]
      20 [-]: GETUPVAL R7 3; var7 = upvalues[3]
      21 [-]: MOVE R8 R2   ; var8 = var2
      22 [-]: NAMECALL R3 R3 K14; var4 = var3; var3 = var3[0x33FC842F]
      23 [-]: CALL R3 6 2  ; var3 = var3(var4, var5, var6, var7, var8)
      24 [-]: FASTCALL1 64 R3 L2; 
      25 [-]: MOVE R5 R3   ; var5 = var3
      26 [-]: GETIMPORT R4 16; var4 = 0x7B998233
      27 [-]: CALL R4 2 2  ; var4 = var4(var5)
L 2:  28 [-]: JUMPIF R4 L3 ; goto L3 if var4
      29 [-]: NAMECALL R4 R3 K17; var5 = var3; var4 = var3[0xBB610E5B]
      30 [-]: CALL R4 2 2  ; var4 = var4(var5)
      31 [-]: GETIMPORT R5 19; var5 = 0x11A19C5E
      32 [-]: MOVE R6 R4   ; var6 = var4
      33 [-]: LOADK R7 K20 ; var7 = "OnKilled"
      34 [-]: CALL R5 3 1  ; var5(var6, var7)
      35 [-]: GETUPVAL R7 2; var7 = upvalues[2]
      36 [-]: NAMECALL R7 R7 K21; var8 = var7; var7 = var7[0xD1586535]
      37 [-]: CALL R7 2 2  ; var7 = var7(var8)
      38 [-]: LOADB R8 0   ; var8 = false
      39 [-]: NAMECALL R5 R4 K22; var6 = var4; var5 = var4[0x589EF1C1]
      40 [-]: CALL R5 4 1  ; var5(var6, var7, var8)
      41 [-]: SETUPVAL R3 4; upvalues[3] = var4
      42 [-]: SETUPVAL R4 5; upvalues[4] = var5
      43 [-]: GETUPVAL R5 6; var5 = upvalues[6]
      44 [-]: NAMECALL R5 R5 K23; var6 = var5; var5 = var5[0x1AC1655C]
      45 [-]: CALL R5 2 2  ; var5 = var5(var6)
      46 [-]: GETUPVAL R7 7; var7 = upvalues[7]
      47 [-]: NAMECALL R5 R5 K24; var6 = var5; var5 = var5[0x57369B8B]
      48 [-]: CALL R5 3 1  ; var5(var6, var7)
      49 [-]: RETURN R0 0  ; 
L 3:  50 [-]: GETIMPORT R4 26; var4 = 0x3D106989
      51 [-]: LOADK R5 K27 ; var5 = "failed to spawn Ethereal Angel"
      52 [-]: CALL R4 2 1  ; var4(var5)
      53 [-]: RETURN R0 0  ; 
L 4:  54 [-]: JUMPXEQKN R1 K28 L5 NOT; 
      55 [-]: RETURN R0 0  ; 
L 5:  56 [-]: JUMPXEQKN R1 K29 L10 NOT; 
      57 [-]: GETIMPORT R2 26; var2 = 0x3D106989
      58 [-]: LOADK R3 K30 ; var3 = "Ethereal Angel destroyed, removing Angel buff"
      59 [-]: CALL R2 2 1  ; var2(var3)
      60 [-]: GETUPVAL R3 6; var3 = upvalues[6]
      61 [-]: FASTCALL1 64 R3 L6; 
      62 [-]: GETIMPORT R2 16; var2 = 0x7B998233
      63 [-]: CALL R2 2 2  ; var2 = var2(var3)
L 6:  64 [-]: JUMPIF R2 L33; goto L33 if var2
      65 [-]: GETUPVAL R2 6; var2 = upvalues[6]
      66 [-]: NAMECALL R2 R2 K23; var3 = var2; var2 = var2[0x1AC1655C]
      67 [-]: CALL R2 2 2  ; var2 = var2(var3)
      68 [-]: GETUPVAL R4 8; var4 = upvalues[8]
      69 [-]: NAMECALL R2 R2 K31; var3 = var2; var2 = var2[0x8733746A]
      70 [-]: CALL R2 3 2  ; var2 = var2(var3, var4)
      71 [-]: JUMPIFNOT R2 L7; goto L7 if not var2
      72 [-]: GETUPVAL R2 6; var2 = upvalues[6]
      73 [-]: NAMECALL R2 R2 K23; var3 = var2; var2 = var2[0x1AC1655C]
      74 [-]: CALL R2 2 2  ; var2 = var2(var3)
      75 [-]: GETUPVAL R4 8; var4 = upvalues[8]
      76 [-]: NAMECALL R2 R2 K32; var3 = var2; var2 = var2[0x8E3E343E]
      77 [-]: CALL R2 3 1  ; var2(var3, var4)
L 7:  78 [-]: GETIMPORT R2 6; var2 = 0x89326C93
      79 [-]: GETIMPORT R4 34; var4 = 0x0469F296
      80 [-]: LOADK R5 K35 ; var5 = "MeltdownEffect"
      81 [-]: CALL R4 2 0  ; var4, ... = var4(var5)
      82 [-]: NAMECALL R2 R2 K36; var3 = var2; var2 = var2[0x46A0EBF5]
      83 [-]: CALL R2 0 2  ; var2 = var2(var3, ...)
      84 [-]: FASTCALL1 64 R2 L8; 
      85 [-]: MOVE R4 R2   ; var4 = var2
      86 [-]: GETIMPORT R3 16; var3 = 0x7B998233
      87 [-]: CALL R3 2 2  ; var3 = var3(var4)
L 8:  88 [-]: JUMPIF R3 L9 ; goto L9 if var3
      89 [-]: LOADK R5 K37 ; var5 = "Enable"
      90 [-]: NAMECALL R3 R2 K38; var4 = var2; var3 = var2[0x8EB2112D]
      91 [-]: CALL R3 3 1  ; var3(var4, var5)
L 9:  92 [-]: GETIMPORT R3 40; var3 = _T["AddHudTracker"]
      93 [-]: LOADK R5 K41 ; var5 = "MeltdownTracker"
      94 [-]: GETUPVAL R6 6; var6 = upvalues[6]
      95 [-]: NAMECALL R6 R6 K42; var7 = var6; var6 = var6[0x388577D5]
      96 [-]: CALL R6 2 2  ; var6 = var6(var7)
      97 [-]: CONCAT R4 R5 R6; var4 = var5 .. var6
      98 [-]: GETUPVAL R6 10; var6 = upvalues[10]
      99 [-]: GETTABLEKS R5 R6 K43; var5 = var6["HT_TIMER"]
     100 [-]: CALL R3 3 2  ; var3 = var3(var4, var5)
     101 [-]: SETUPVAL R3 9; upvalues[3] = var9
     102 [-]: GETUPVAL R4 9; var4 = upvalues[9]
     103 [-]: GETTABLEKS R3 R4 K44; var3 = var4["SetVisible"]
     104 [-]: LOADB R4 1   ; var4 = true
     105 [-]: LOADB R5 1   ; var5 = true
     106 [-]: CALL R3 3 1  ; var3(var4, var5)
     107 [-]: GETUPVAL R4 9; var4 = upvalues[9]
     108 [-]: GETTABLEKS R3 R4 K45; var3 = var4["SetLabel"]
     109 [-]: LOADK R4 K46 ; var4 = "/Lotus/Language/Zariman/VoidArenaPurge"
     110 [-]: CALL R3 2 1  ; var3(var4)
     111 [-]: GETUPVAL R4 9; var4 = upvalues[9]
     112 [-]: GETTABLEKS R3 R4 K47; var3 = var4["StartTimer"]
     113 [-]: LOADN R4 1   ; var4 = 1
     114 [-]: LOADB R5 0   ; var5 = false
     115 [-]: CALL R3 3 1  ; var3(var4, var5)
     116 [-]: GETUPVAL R4 9; var4 = upvalues[9]
     117 [-]: GETTABLEKS R3 R4 K48; var3 = var4["SetLocation"]
     118 [-]: DUPTABLE R4 50; 
     119 [-]: GETUPVAL R6 11; var6 = upvalues[11]
     120 [-]: NAMECALL R6 R6 K51; var7 = var6; var6 = var6[0x26E191C7]
     121 [-]: CALL R6 2 2  ; var6 = var6(var7)
     122 [-]: ADDK R5 R6 K4; var5 = var6 + 1
     123 [-]: SETTABLEKS R5 R4 K49; var5["allowed"] = var4
     124 [-]: CALL R3 2 1  ; var3(var4)
     125 [-]: GETIMPORT R3 52; var3 = _T
     126 [-]: LOADB R4 1   ; var4 = true
     127 [-]: SETTABLEKS R4 R3 K53; var4["AngelHasBeenKilled"] = var3
     128 [-]: RETURN R0 0  ; 
L10: 129 [-]: JUMPXEQKN R1 K54 L31 NOT; 
     130 [-]: GETUPVAL R2 6; var2 = upvalues[6]
     131 [-]: NAMECALL R2 R2 K42; var3 = var2; var2 = var2[0x388577D5]
     132 [-]: CALL R2 2 2  ; var2 = var2(var3)
     133 [-]: GETIMPORT R8 56; var8 = _T["VoidAngels"]
     134 [-]: GETTABLE R7 R8 R2; var7 = var8[var2]
     135 [-]: GETTABLEKS R6 R7 K57; var6 = var7["activePlayers"]
     136 [-]: LENGTH R5 R6 ; var5 = #var6
     137 [-]: LOADN R3 1   ; var3 = 1
     138 [-]: LOADN R4 -1  ; var4 = -1
     139 [-]: FORNPREP R3 L15; nforprep start - [escape at L15] -- var3 = iterator
L11: 140 [-]: GETIMPORT R9 56; var9 = _T["VoidAngels"]
     141 [-]: GETTABLE R8 R9 R2; var8 = var9[var2]
     142 [-]: GETTABLEKS R7 R8 K57; var7 = var8["activePlayers"]
     143 [-]: GETTABLE R6 R7 R5; var6 = var7[var5]
     144 [-]: FASTCALL1 64 R6 L12; 
     145 [-]: MOVE R8 R6   ; var8 = var6
     146 [-]: GETIMPORT R7 16; var7 = 0x7B998233
     147 [-]: CALL R7 2 2  ; var7 = var7(var8)
L12: 148 [-]: JUMPIF R7 L14; goto L14 if var7
     149 [-]: NAMECALL R8 R6 K58; var9 = var6; var8 = var6[0x5E651723]
     150 [-]: CALL R8 2 0  ; var8, ... = var8(var9)
     151 [-]: FASTCALL 64 L13; 
     152 [-]: GETIMPORT R7 16; var7 = 0x7B998233
     153 [-]: CALL R7 0 2  ; var7 = var7(var8, ...)
L13: 154 [-]: JUMPIF R7 L14; goto L14 if var7
     155 [-]: GETUPVAL R7 12; var7 = upvalues[12]
     156 [-]: MOVE R8 R6   ; var8 = var6
     157 [-]: GETUPVAL R9 6; var9 = upvalues[6]
     158 [-]: CALL R7 3 1  ; var7(var8, var9)
L14: 159 [-]: GETIMPORT R7 61; var7 = 0x33BDD652[0x9C1F3B5A]
     160 [-]: GETIMPORT R10 56; var10 = _T["VoidAngels"]
     161 [-]: GETTABLE R9 R10 R2; var9 = var10[var2]
     162 [-]: GETTABLEKS R8 R9 K57; var8 = var9["activePlayers"]
     163 [-]: MOVE R9 R5   ; var9 = var5
     164 [-]: CALL R7 3 1  ; var7(var8, var9)
     165 [-]: FORNLOOP R3 L11; nforloop end - iterate + goto L11
L15: 166 [-]: GETUPVAL R4 13; var4 = upvalues[13]
     167 [-]: GETTABLEKS R3 R4 K62; var3 = var4[0x6696A66C]
     168 [-]: GETUPVAL R4 11; var4 = upvalues[11]
     169 [-]: CALL R3 2 2  ; var3 = var3(var4)
     170 [-]: LENGTH R6 R3 ; var6 = #var3
     171 [-]: LOADN R4 1   ; var4 = 1
     172 [-]: LOADN R5 -1  ; var5 = -1
     173 [-]: FORNPREP R4 L22; nforprep start - [escape at L22] -- var4 = iterator
L16: 174 [-]: GETTABLE R7 R3 R6; var7 = var3[var6]
     175 [-]: FASTCALL1 64 R7 L17; 
     176 [-]: MOVE R9 R7   ; var9 = var7
     177 [-]: GETIMPORT R8 16; var8 = 0x7B998233
     178 [-]: CALL R8 2 2  ; var8 = var8(var9)
L17: 179 [-]: JUMPIF R8 L21; goto L21 if var8
     180 [-]: GETUPVAL R10 14; var10 = upvalues[14]
     181 [-]: NAMECALL R8 R7 K63; var9 = var7; var8 = var7[0xA3A0F1C2]
     182 [-]: CALL R8 3 1  ; var8(var9, var10)
     183 [-]: GETUPVAL R8 12; var8 = upvalues[12]
     184 [-]: MOVE R9 R7   ; var9 = var7
     185 [-]: GETUPVAL R10 6; var10 = upvalues[6]
     186 [-]: CALL R8 3 1  ; var8(var9, var10)
     187 [-]: GETUPVAL R9 15; var9 = upvalues[15]
     188 [-]: FASTCALL1 64 R9 L18; 
     189 [-]: GETIMPORT R8 16; var8 = 0x7B998233
     190 [-]: CALL R8 2 2  ; var8 = var8(var9)
L18: 191 [-]: JUMPIF R8 L21; goto L21 if var8
     192 [-]: GETUPVAL R11 15; var11 = upvalues[15]
     193 [-]: LENGTH R10 R11; var10 = #var11
     194 [-]: LOADN R8 1   ; var8 = 1
     195 [-]: LOADN R9 -1  ; var9 = -1
     196 [-]: FORNPREP R8 L21; nforprep start - [escape at L21] -- var8 = iterator
L19: 197 [-]: GETUPVAL R12 15; var12 = upvalues[15]
     198 [-]: GETTABLE R11 R12 R10; var11 = var12[var10]
     199 [-]: JUMPIFNOTEQ R7 R11 L20; goto L20 if var7 ~= var4000545
     200 [-]: GETIMPORT R11 61; var11 = 0x33BDD652[0x9C1F3B5A]
     201 [-]: GETUPVAL R12 15; var12 = upvalues[15]
     202 [-]: MOVE R13 R10 ; var13 = var10
     203 [-]: CALL R11 3 1 ; var11(var12, var13)
     204 [-]: JUMP L21     ; goto L21
L20: 205 [-]: FORNLOOP R8 L19; nforloop end - iterate + goto L19
L21: 206 [-]: FORNLOOP R4 L16; nforloop end - iterate + goto L16
L22: 207 [-]: GETIMPORT R5 65; var5 = _T["VoidAngelWingClipShields"]
     208 [-]: FASTCALL1 64 R5 L23; 
     209 [-]: GETIMPORT R4 16; var4 = 0x7B998233
     210 [-]: CALL R4 2 2  ; var4 = var4(var5)
L23: 211 [-]: JUMPIF R4 L28; goto L28 if var4
     212 [-]: GETIMPORT R7 65; var7 = _T["VoidAngelWingClipShields"]
     213 [-]: LENGTH R6 R7 ; var6 = #var7
     214 [-]: LOADN R4 1   ; var4 = 1
     215 [-]: LOADN R5 -1  ; var5 = -1
     216 [-]: FORNPREP R4 L27; nforprep start - [escape at L27] -- var4 = iterator
L24: 217 [-]: GETIMPORT R9 65; var9 = _T["VoidAngelWingClipShields"]
     218 [-]: GETTABLE R8 R9 R6; var8 = var9[var6]
     219 [-]: FASTCALL1 64 R8 L25; 
     220 [-]: GETIMPORT R7 16; var7 = 0x7B998233
     221 [-]: CALL R7 2 2  ; var7 = var7(var8)
L25: 222 [-]: JUMPIF R7 L26; goto L26 if var7
     223 [-]: GETIMPORT R8 65; var8 = _T["VoidAngelWingClipShields"]
     224 [-]: GETTABLE R7 R8 R6; var7 = var8[var6]
     225 [-]: NAMECALL R7 R7 K66; var8 = var7; var7 = var7[0xA2880940]
     226 [-]: CALL R7 2 1  ; var7(var8)
L26: 227 [-]: GETIMPORT R7 61; var7 = 0x33BDD652[0x9C1F3B5A]
     228 [-]: GETIMPORT R8 65; var8 = _T["VoidAngelWingClipShields"]
     229 [-]: MOVE R9 R6   ; var9 = var6
     230 [-]: CALL R7 3 1  ; var7(var8, var9)
     231 [-]: FORNLOOP R4 L24; nforloop end - iterate + goto L24
L27: 232 [-]: GETIMPORT R4 52; var4 = _T
     233 [-]: LOADNIL R5   ; var5 = nil
     234 [-]: SETTABLEKS R5 R4 K64; var5["VoidAngelWingClipShields"] = var4
L28: 235 [-]: GETUPVAL R5 5; var5 = upvalues[5]
     236 [-]: FASTCALL1 64 R5 L29; 
     237 [-]: GETIMPORT R4 16; var4 = 0x7B998233
     238 [-]: CALL R4 2 2  ; var4 = var4(var5)
L29: 239 [-]: JUMPIF R4 L30; goto L30 if var4
     240 [-]: GETUPVAL R4 5; var4 = upvalues[5]
     241 [-]: NAMECALL R4 R4 K66; var5 = var4; var4 = var4[0xA2880940]
     242 [-]: CALL R4 2 1  ; var4(var5)
L30: 243 [-]: GETIMPORT R4 40; var4 = _T["AddHudTracker"]
     244 [-]: LOADK R6 K41 ; var6 = "MeltdownTracker"
     245 [-]: GETUPVAL R7 6; var7 = upvalues[6]
     246 [-]: NAMECALL R7 R7 K42; var8 = var7; var7 = var7[0x388577D5]
     247 [-]: CALL R7 2 2  ; var7 = var7(var8)
     248 [-]: CONCAT R5 R6 R7; var5 = var6 .. var7
     249 [-]: GETUPVAL R7 10; var7 = upvalues[10]
     250 [-]: GETTABLEKS R6 R7 K43; var6 = var7["HT_TIMER"]
     251 [-]: CALL R4 3 2  ; var4 = var4(var5, var6)
     252 [-]: SETUPVAL R4 16; upvalues[4] = var16
     253 [-]: GETUPVAL R5 16; var5 = upvalues[16]
     254 [-]: GETTABLEKS R4 R5 K44; var4 = var5["SetVisible"]
     255 [-]: LOADB R5 0   ; var5 = false
     256 [-]: LOADB R6 0   ; var6 = false
     257 [-]: CALL R4 3 1  ; var4(var5, var6)
     258 [-]: GETUPVAL R5 16; var5 = upvalues[16]
     259 [-]: GETTABLEKS R4 R5 K45; var4 = var5["SetLabel"]
     260 [-]: LOADK R5 K46 ; var5 = "/Lotus/Language/Zariman/VoidArenaPurge"
     261 [-]: CALL R4 2 1  ; var4(var5)
     262 [-]: GETUPVAL R5 16; var5 = upvalues[16]
     263 [-]: GETTABLEKS R4 R5 K47; var4 = var5["StartTimer"]
     264 [-]: LOADN R5 2   ; var5 = 2
     265 [-]: LOADB R6 0   ; var6 = false
     266 [-]: CALL R4 3 1  ; var4(var5, var6)
     267 [-]: GETUPVAL R5 16; var5 = upvalues[16]
     268 [-]: GETTABLEKS R4 R5 K48; var4 = var5["SetLocation"]
     269 [-]: DUPTABLE R5 50; 
     270 [-]: GETUPVAL R7 11; var7 = upvalues[11]
     271 [-]: NAMECALL R7 R7 K51; var8 = var7; var7 = var7[0x26E191C7]
     272 [-]: CALL R7 2 2  ; var7 = var7(var8)
     273 [-]: ADDK R6 R7 K4; var6 = var7 + 1
     274 [-]: SETTABLEKS R6 R5 K49; var6["allowed"] = var5
     275 [-]: CALL R4 2 1  ; var4(var5)
     276 [-]: RETURN R0 0  ; 
L31: 277 [-]: JUMPXEQKN R1 K67 L32 NOT; 
     278 [-]: RETURN R0 0  ; 
L32: 279 [-]: JUMPXEQKN R1 K68 L33 NOT; 
     280 [-]: GETIMPORT R2 26; var2 = 0x3D106989
     281 [-]: GETUPVAL R6 6; var6 = upvalues[6]
     282 [-]: NAMECALL R6 R6 K69; var7 = var6; var6 = var6[0xED4E0128]
     283 [-]: CALL R6 2 2  ; var6 = var6(var7)
     284 [-]: MOVE R4 R6   ; var4 = var6
     285 [-]: LOADK R5 K70 ; var5 = " instantly destroyed!"
     286 [-]: CONCAT R3 R4 R5; var3 = var4 .. var5
     287 [-]: CALL R2 2 1  ; var2(var3)
L33: 288 [-]: RETURN R0 0  ; 


; Name:            
; Defined at line: 1173
; #Upvalues:       19
; #Parameters:     1
; Is_vararg:       0
; Max Stack Size:  16

       0 [-]: GETIMPORT R1 1; var1 = 0x89326C93
       1 [-]: NAMECALL R1 R1 K2; var2 = var1; var1 = var1[0x29EF273D]
       2 [-]: CALL R1 2 2  ; var1 = var1(var2)
       3 [-]: NAMECALL R1 R1 K3; var2 = var1; var1 = var1[0x66905CB0]
       4 [-]: CALL R1 2 2  ; var1 = var1(var2)
       5 [-]: SETUPVAL R1 0; upvalues[1] = var0
       6 [-]: GETUPVAL R2 2; var2 = upvalues[2]
       7 [-]: GETTABLEKS R1 R2 K4; var1 = var2[0xDE474187]
       8 [-]: CALL R1 1 2  ; var1 = var1()
       9 [-]: SETUPVAL R1 1; upvalues[1] = var1
      10 [-]: GETUPVAL R2 5; var2 = upvalues[5]
      11 [-]: GETTABLEKS R1 R2 K5; var1 = var2[0xD91017EA]
      12 [-]: MOVE R2 R0   ; var2 = var0
      13 [-]: CALL R1 2 3  ; var1, var2 = var1(var2)
      14 [-]: SETUPVAL R1 3; upvalues[1] = var3
      15 [-]: SETUPVAL R2 4; upvalues[2] = var4
      16 [-]: GETUPVAL R2 3; var2 = upvalues[3]
      17 [-]: FASTCALL1 64 R2 L0; 
      18 [-]: GETIMPORT R1 7; var1 = 0x7B998233
      19 [-]: CALL R1 2 2  ; var1 = var1(var2)
L 0:  20 [-]: JUMPIF R1 L2 ; goto L2 if var1
      21 [-]: GETUPVAL R2 4; var2 = upvalues[4]
      22 [-]: FASTCALL1 64 R2 L1; 
      23 [-]: GETIMPORT R1 7; var1 = 0x7B998233
      24 [-]: CALL R1 2 2  ; var1 = var1(var2)
L 1:  25 [-]: JUMPIFNOT R1 L3; goto L3 if not var1
L 2:  26 [-]: RETURN R0 0  ; 
L 3:  27 [-]: GETUPVAL R1 4; var1 = upvalues[4]
      28 [-]: NAMECALL R1 R1 K8; var2 = var1; var1 = var1[0xFA9E477F]
      29 [-]: CALL R1 2 2  ; var1 = var1(var2)
      30 [-]: SETUPVAL R1 6; upvalues[1] = var6
      31 [-]: GETUPVAL R2 5; var2 = upvalues[5]
      32 [-]: GETTABLEKS R1 R2 K9; var1 = var2[0x2DF8B2BA]
      33 [-]: GETIMPORT R2 11; var2 = 0x0469F296
      34 [-]: LOADK R3 K12 ; var3 = "VoidArenaAngelSpawn"
      35 [-]: CALL R2 2 2  ; var2 = var2(var3)
      36 [-]: GETUPVAL R3 3; var3 = upvalues[3]
      37 [-]: CALL R1 3 2  ; var1 = var1(var2, var3)
      38 [-]: SETUPVAL R1 7; upvalues[1] = var7
      39 [-]: GETUPVAL R2 5; var2 = upvalues[5]
      40 [-]: GETTABLEKS R1 R2 K9; var1 = var2[0x2DF8B2BA]
      41 [-]: GETIMPORT R2 11; var2 = 0x0469F296
      42 [-]: LOADK R3 K13 ; var3 = "VoidArenaPlayerSpawn"
      43 [-]: CALL R2 2 2  ; var2 = var2(var3)
      44 [-]: GETUPVAL R3 3; var3 = upvalues[3]
      45 [-]: CALL R1 3 2  ; var1 = var1(var2, var3)
      46 [-]: SETUPVAL R1 8; upvalues[1] = var8
      47 [-]: GETIMPORT R1 15; var1 = 0xB7CBD06B
      48 [-]: GETUPVAL R2 0; var2 = upvalues[0]
      49 [-]: NAMECALL R2 R2 K16; var3 = var2; var2 = var2[0xCEA36880]
      50 [-]: CALL R2 2 2  ; var2 = var2(var3)
      51 [-]: GETUPVAL R3 0; var3 = upvalues[0]
      52 [-]: NAMECALL R3 R3 K17; var4 = var3; var3 = var3[0x6968EA36]
      53 [-]: CALL R3 2 0  ; var3, ... = var3(var4)
      54 [-]: CALL R1 0 2  ; var1 = var1(var2, ...)
      55 [-]: SETUPVAL R1 9; upvalues[1] = var9
      56 [-]: GETUPVAL R2 9; var2 = upvalues[9]
      57 [-]: GETTABLEKS R1 R2 K18; var1 = var2["minValue"]
      58 [-]: JUMPXEQKN R1 K19 L4 NOT; 
      59 [-]: GETUPVAL R2 9; var2 = upvalues[9]
      60 [-]: GETTABLEKS R1 R2 K20; var1 = var2["maxValue"]
      61 [-]: JUMPXEQKN R1 K19 L4 NOT; 
      62 [-]: GETUPVAL R1 9; var1 = upvalues[9]
      63 [-]: LOADN R2 50  ; var2 = 50
      64 [-]: SETTABLEKS R2 R1 K18; var2["minValue"] = var1
      65 [-]: GETUPVAL R1 9; var1 = upvalues[9]
      66 [-]: LOADN R2 50  ; var2 = 50
      67 [-]: SETTABLEKS R2 R1 K20; var2["maxValue"] = var1
L 4:  68 [-]: GETUPVAL R1 4; var1 = upvalues[4]
      69 [-]: NAMECALL R1 R1 K21; var2 = var1; var1 = var1[0x1AC1655C]
      70 [-]: CALL R1 2 2  ; var1 = var1(var2)
      71 [-]: NAMECALL R1 R1 K22; var2 = var1; var1 = var1[0xB87F958D]
      72 [-]: CALL R1 2 2  ; var1 = var1(var2)
      73 [-]: SETUPVAL R1 10; upvalues[1] = var10
      74 [-]: GETUPVAL R1 4; var1 = upvalues[4]
      75 [-]: LOADK R3 K23 ; var3 = "OnPreDeath"
      76 [-]: NAMECALL R1 R1 K24; var2 = var1; var1 = var1[0x54420AF8]
      77 [-]: CALL R1 3 1  ; var1(var2, var3)
      78 [-]: GETUPVAL R1 4; var1 = upvalues[4]
      79 [-]: NAMECALL R1 R1 K25; var2 = var1; var1 = var1[0xED4E0128]
      80 [-]: CALL R1 2 2  ; var1 = var1(var2)
      81 [-]: SETUPVAL R1 11; upvalues[1] = var11
      82 [-]: GETIMPORT R1 11; var1 = 0x0469F296
      83 [-]: GETUPVAL R2 11; var2 = upvalues[11]
      84 [-]: CALL R1 2 2  ; var1 = var1(var2)
      85 [-]: SETUPVAL R1 12; upvalues[1] = var12
      86 [-]: GETUPVAL R2 5; var2 = upvalues[5]
      87 [-]: GETTABLEKS R1 R2 K9; var1 = var2[0x2DF8B2BA]
      88 [-]: GETIMPORT R2 11; var2 = 0x0469F296
      89 [-]: LOADK R3 K26 ; var3 = "VoidAngelEthereal"
      90 [-]: CALL R2 2 2  ; var2 = var2(var3)
      91 [-]: GETUPVAL R3 3; var3 = upvalues[3]
      92 [-]: CALL R1 3 2  ; var1 = var1(var2, var3)
      93 [-]: SETUPVAL R1 13; upvalues[1] = var13
      94 [-]: GETUPVAL R2 13; var2 = upvalues[13]
      95 [-]: FASTCALL1 64 R2 L5; 
      96 [-]: GETIMPORT R1 7; var1 = 0x7B998233
      97 [-]: CALL R1 2 2  ; var1 = var1(var2)
L 5:  98 [-]: JUMPIF R1 L6 ; goto L6 if var1
      99 [-]: GETUPVAL R1 13; var1 = upvalues[13]
     100 [-]: NAMECALL R1 R1 K8; var2 = var1; var1 = var1[0xFA9E477F]
     101 [-]: CALL R1 2 2  ; var1 = var1(var2)
     102 [-]: SETUPVAL R1 14; upvalues[1] = var14
L 6: 103 [-]: GETUPVAL R1 4; var1 = upvalues[4]
     104 [-]: NAMECALL R1 R1 K27; var2 = var1; var1 = var1[0x388577D5]
     105 [-]: CALL R1 2 2  ; var1 = var1(var2)
     106 [-]: GETUPVAL R3 5; var3 = upvalues[5]
     107 [-]: GETTABLEKS R2 R3 K28; var2 = var3[0x6696A66C]
     108 [-]: GETUPVAL R3 3; var3 = upvalues[3]
     109 [-]: CALL R2 2 2  ; var2 = var2(var3)
     110 [-]: LOADN R5 1   ; var5 = 1
     111 [-]: LENGTH R3 R2 ; var3 = #var2
     112 [-]: LOADN R4 1   ; var4 = 1
     113 [-]: FORNPREP R3 L15; nforprep start - [escape at L15] -- var3 = iterator
L 7: 114 [-]: GETTABLE R6 R2 R5; var6 = var2[var5]
     115 [-]: FASTCALL1 64 R6 L8; 
     116 [-]: MOVE R8 R6   ; var8 = var6
     117 [-]: GETIMPORT R7 7; var7 = 0x7B998233
     118 [-]: CALL R7 2 2  ; var7 = var7(var8)
L 8: 119 [-]: JUMPIF R7 L14; goto L14 if var7
     120 [-]: LOADB R7 0   ; var7 = false
     121 [-]: LOADN R10 1  ; var10 = 1
     122 [-]: GETIMPORT R13 31; var13 = _T["VoidAngels"]
     123 [-]: GETTABLE R12 R13 R1; var12 = var13[var1]
     124 [-]: GETTABLEKS R11 R12 K32; var11 = var12["activePlayers"]
     125 [-]: LENGTH R8 R11; var8 = #var11
     126 [-]: LOADN R9 1   ; var9 = 1
     127 [-]: FORNPREP R8 L12; nforprep start - [escape at L12] -- var8 = iterator
L 9: 128 [-]: GETIMPORT R15 31; var15 = _T["VoidAngels"]
     129 [-]: GETTABLE R14 R15 R1; var14 = var15[var1]
     130 [-]: GETTABLEKS R13 R14 K32; var13 = var14["activePlayers"]
     131 [-]: GETTABLE R12 R13 R10; var12 = var13[var10]
     132 [-]: FASTCALL1 64 R12 L10; 
     133 [-]: GETIMPORT R11 7; var11 = 0x7B998233
     134 [-]: CALL R11 2 2 ; var11 = var11(var12)
L10: 135 [-]: JUMPIF R11 L11; goto L11 if var11
     136 [-]: GETIMPORT R14 31; var14 = _T["VoidAngels"]
     137 [-]: GETTABLE R13 R14 R1; var13 = var14[var1]
     138 [-]: GETTABLEKS R12 R13 K32; var12 = var13["activePlayers"]
     139 [-]: GETTABLE R11 R12 R10; var11 = var12[var10]
     140 [-]: JUMPIFNOTEQ R11 R6 L11; goto L11 if var11 ~= var67334
     141 [-]: LOADB R7 1   ; var7 = true
     142 [-]: JUMP L12     ; goto L12
L11: 143 [-]: FORNLOOP R8 L9; nforloop end - iterate + goto L9
L12: 144 [-]: JUMPIF R7 L14; goto L14 if var7
     145 [-]: GETUPVAL R10 15; var10 = upvalues[15]
     146 [-]: NAMECALL R8 R6 K33; var9 = var6; var8 = var6[0x08DB51DE]
     147 [-]: CALL R8 3 2  ; var8 = var8(var9, var10)
     148 [-]: JUMPIF R8 L13; goto L13 if var8
     149 [-]: GETUPVAL R10 15; var10 = upvalues[15]
     150 [-]: NAMECALL R8 R6 K34; var9 = var6; var8 = var6[0xB6FD75DB]
     151 [-]: CALL R8 3 1  ; var8(var9, var10)
L13: 152 [-]: GETIMPORT R11 31; var11 = _T["VoidAngels"]
     153 [-]: GETTABLE R10 R11 R1; var10 = var11[var1]
     154 [-]: GETTABLEKS R9 R10 K32; var9 = var10["activePlayers"]
     155 [-]: FASTCALL2 52 R9 R6 L14; 
     156 [-]: MOVE R10 R6  ; var10 = var6
     157 [-]: GETIMPORT R8 37; var8 = 0x33BDD652[0x23D5322F]
     158 [-]: CALL R8 3 1  ; var8(var9, var10)
L14: 159 [-]: FORNLOOP R3 L7; nforloop end - iterate + goto L7
L15: 160 [-]: GETUPVAL R4 5; var4 = upvalues[5]
     161 [-]: GETTABLEKS R3 R4 K38; var3 = var4[0xDE6C4F3E]
     162 [-]: GETUPVAL R4 17; var4 = upvalues[17]
     163 [-]: GETUPVAL R5 3; var5 = upvalues[3]
     164 [-]: CALL R3 3 2  ; var3 = var3(var4, var5)
     165 [-]: SETUPVAL R3 16; upvalues[3] = var16
     166 [-]: NEWTABLE R3 0 0; var3 = {}
     167 [-]: SETUPVAL R3 18; upvalues[3] = var18
     168 [-]: RETURN R0 0  ; 


; Name:            
; Defined at line: 1233
; #Upvalues:       13
; #Parameters:     1
; Is_vararg:       0
; Max Stack Size:  19

       0 [-]: FASTCALL1 64 R0 L0; 
       1 [-]: MOVE R2 R0   ; var2 = var0
       2 [-]: GETIMPORT R1 1; var1 = 0x7B998233
       3 [-]: CALL R1 2 2  ; var1 = var1(var2)
L 0:   4 [-]: JUMPIFNOT R1 L1; goto L1 if not var1
       5 [-]: RETURN R0 0  ; 
L 1:   6 [-]: GETIMPORT R1 3; var1 = 0x89326C93
       7 [-]: NAMECALL R1 R1 K4; var2 = var1; var1 = var1[0x18D05D30]
       8 [-]: CALL R1 2 2  ; var1 = var1(var2)
       9 [-]: JUMPIF R1 L2 ; goto L2 if var1
      10 [-]: RETURN R0 0  ; 
L 2:  11 [-]: GETUPVAL R1 0; var1 = upvalues[0]
      12 [-]: MOVE R2 R0   ; var2 = var0
      13 [-]: CALL R1 2 1  ; var1(var2)
      14 [-]: GETUPVAL R1 1; var1 = upvalues[1]
      15 [-]: NAMECALL R1 R1 K5; var2 = var1; var1 = var1[0x388577D5]
      16 [-]: CALL R1 2 2  ; var1 = var1(var2)
      17 [-]: LOADN R2 -1  ; var2 = -1
L 3:  18 [-]: GETIMPORT R3 7; var3 = 0xBE190284
      19 [-]: NAMECALL R3 R3 K8; var4 = var3; var3 = var3[0x3790D299]
      20 [-]: CALL R3 2 2  ; var3 = var3(var4)
      21 [-]: JUMPIF R3 L53; goto L53 if var3
      22 [-]: GETIMPORT R3 7; var3 = 0xBE190284
      23 [-]: NAMECALL R3 R3 K9; var4 = var3; var3 = var3[0x5D204145]
      24 [-]: CALL R3 2 2  ; var3 = var3(var4)
      25 [-]: JUMPIF R3 L53; goto L53 if var3
      26 [-]: GETUPVAL R4 2; var4 = upvalues[2]
      27 [-]: FASTCALL1 64 R4 L4; 
      28 [-]: GETIMPORT R3 1; var3 = 0x7B998233
      29 [-]: CALL R3 2 2  ; var3 = var3(var4)
L 4:  30 [-]: JUMPIF R3 L53; goto L53 if var3
      31 [-]: GETUPVAL R4 3; var4 = upvalues[3]
      32 [-]: GETTABLEKS R3 R4 K10; var3 = var4[0x6696A66C]
      33 [-]: GETUPVAL R4 2; var4 = upvalues[2]
      34 [-]: CALL R3 2 2  ; var3 = var3(var4)
      35 [-]: LOADN R6 1   ; var6 = 1
      36 [-]: LENGTH R4 R3 ; var4 = #var3
      37 [-]: LOADN R5 1   ; var5 = 1
      38 [-]: FORNPREP R4 L12; nforprep start - [escape at L12] -- var4 = iterator
L 5:  39 [-]: GETTABLE R7 R3 R6; var7 = var3[var6]
      40 [-]: FASTCALL1 64 R7 L6; 
      41 [-]: MOVE R9 R7   ; var9 = var7
      42 [-]: GETIMPORT R8 1; var8 = 0x7B998233
      43 [-]: CALL R8 2 2  ; var8 = var8(var9)
L 6:  44 [-]: JUMPIF R8 L11; goto L11 if var8
      45 [-]: LOADB R8 0   ; var8 = false
      46 [-]: LOADN R11 1  ; var11 = 1
      47 [-]: GETIMPORT R14 13; var14 = _T["VoidAngels"]
      48 [-]: GETTABLE R13 R14 R1; var13 = var14[var1]
      49 [-]: GETTABLEKS R12 R13 K14; var12 = var13["activePlayers"]
      50 [-]: LENGTH R9 R12; var9 = #var12
      51 [-]: LOADN R10 1  ; var10 = 1
      52 [-]: FORNPREP R9 L10; nforprep start - [escape at L10] -- var9 = iterator
L 7:  53 [-]: GETIMPORT R16 13; var16 = _T["VoidAngels"]
      54 [-]: GETTABLE R15 R16 R1; var15 = var16[var1]
      55 [-]: GETTABLEKS R14 R15 K14; var14 = var15["activePlayers"]
      56 [-]: GETTABLE R13 R14 R11; var13 = var14[var11]
      57 [-]: FASTCALL1 64 R13 L8; 
      58 [-]: GETIMPORT R12 1; var12 = 0x7B998233
      59 [-]: CALL R12 2 2 ; var12 = var12(var13)
L 8:  60 [-]: JUMPIF R12 L9; goto L9 if var12
      61 [-]: GETIMPORT R15 13; var15 = _T["VoidAngels"]
      62 [-]: GETTABLE R14 R15 R1; var14 = var15[var1]
      63 [-]: GETTABLEKS R13 R14 K14; var13 = var14["activePlayers"]
      64 [-]: GETTABLE R12 R13 R11; var12 = var13[var11]
      65 [-]: JUMPIFNOTEQ R12 R7 L9; goto L9 if var12 ~= var67590
      66 [-]: LOADB R8 1   ; var8 = true
      67 [-]: JUMP L10     ; goto L10
L 9:  68 [-]: FORNLOOP R9 L7; nforloop end - iterate + goto L7
L10:  69 [-]: JUMPIF R8 L11; goto L11 if var8
      70 [-]: GETUPVAL R9 4; var9 = upvalues[4]
      71 [-]: MOVE R10 R7  ; var10 = var7
      72 [-]: GETUPVAL R11 1; var11 = upvalues[1]
      73 [-]: CALL R9 3 1  ; var9(var10, var11)
L11:  74 [-]: FORNLOOP R4 L5; nforloop end - iterate + goto L5
L12:  75 [-]: NAMECALL R4 R0 K15; var5 = var0; var4 = var0[0x53C3399F]
      76 [-]: CALL R4 2 2  ; var4 = var4(var5)
      77 [-]: MOVE R2 R4   ; var2 = var4
      78 [-]: JUMPXEQKN R2 K16 L13 NOT; 
      79 [-]: LENGTH R4 R3 ; var4 = #var3
      80 [-]: LOADN R5 0   ; var5 = 0
      81 [-]: JUMPIFNOTLT R5 R4 L33; goto L33 if var5 >= var67120
      82 [-]: LOADN R6 1   ; var6 = 1
      83 [-]: NAMECALL R4 R0 K17; var5 = var0; var4 = var0[0x05EEB9DB]
      84 [-]: CALL R4 3 1  ; var4(var5, var6)
      85 [-]: GETUPVAL R4 5; var4 = upvalues[5]
      86 [-]: MOVE R5 R0   ; var5 = var0
      87 [-]: CALL R4 2 1  ; var4(var5)
      88 [-]: JUMP L33     ; goto L33
L13:  89 [-]: JUMPXEQKN R2 K18 L14 NOT; 
      90 [-]: LOADN R6 2   ; var6 = 2
      91 [-]: NAMECALL R4 R0 K17; var5 = var0; var4 = var0[0x05EEB9DB]
      92 [-]: CALL R4 3 1  ; var4(var5, var6)
      93 [-]: GETUPVAL R4 5; var4 = upvalues[5]
      94 [-]: MOVE R5 R0   ; var5 = var0
      95 [-]: CALL R4 2 1  ; var4(var5)
      96 [-]: JUMP L33     ; goto L33
L14:  97 [-]: JUMPXEQKN R2 K19 L25 NOT; 
      98 [-]: GETUPVAL R5 6; var5 = upvalues[6]
      99 [-]: FASTCALL1 64 R5 L15; 
     100 [-]: GETIMPORT R4 1; var4 = 0x7B998233
     101 [-]: CALL R4 2 2  ; var4 = var4(var5)
L15: 102 [-]: JUMPIF R4 L16; goto L16 if var4
     103 [-]: GETUPVAL R4 6; var4 = upvalues[6]
     104 [-]: NAMECALL R4 R4 K20; var5 = var4; var4 = var4[0x2047CFE7]
     105 [-]: CALL R4 2 2  ; var4 = var4(var5)
     106 [-]: JUMPIFNOT R4 L17; goto L17 if not var4
L16: 107 [-]: LOADN R6 3   ; var6 = 3
     108 [-]: NAMECALL R4 R0 K17; var5 = var0; var4 = var0[0x05EEB9DB]
     109 [-]: CALL R4 3 1  ; var4(var5, var6)
     110 [-]: GETUPVAL R4 5; var4 = upvalues[5]
     111 [-]: MOVE R5 R0   ; var5 = var0
     112 [-]: CALL R4 2 1  ; var4(var5)
     113 [-]: JUMP L22     ; goto L22
L17: 114 [-]: GETUPVAL R5 6; var5 = upvalues[6]
     115 [-]: FASTCALL1 64 R5 L18; 
     116 [-]: GETIMPORT R4 1; var4 = 0x7B998233
     117 [-]: CALL R4 2 2  ; var4 = var4(var5)
L18: 118 [-]: JUMPIF R4 L22; goto L22 if var4
     119 [-]: GETUPVAL R5 1; var5 = upvalues[1]
     120 [-]: FASTCALL1 64 R5 L19; 
     121 [-]: GETIMPORT R4 1; var4 = 0x7B998233
     122 [-]: CALL R4 2 2  ; var4 = var4(var5)
L19: 123 [-]: JUMPIF R4 L22; goto L22 if var4
     124 [-]: GETUPVAL R5 1; var5 = upvalues[1]
     125 [-]: NAMECALL R5 R5 K21; var6 = var5; var5 = var5[0xDE321E6F]
     126 [-]: CALL R5 2 2  ; var5 = var5(var6)
     127 [-]: NAMECALL R5 R5 K22; var6 = var5; var5 = var5[0xF7D48EE0]
     128 [-]: CALL R5 2 0  ; var5, ... = var5(var6)
     129 [-]: FASTCALL 64 L20; 
     130 [-]: GETIMPORT R4 1; var4 = 0x7B998233
     131 [-]: CALL R4 0 2  ; var4 = var4(var5, ...)
L20: 132 [-]: JUMPIF R4 L22; goto L22 if var4
     133 [-]: GETUPVAL R4 1; var4 = upvalues[1]
     134 [-]: NAMECALL R4 R4 K21; var5 = var4; var4 = var4[0xDE321E6F]
     135 [-]: CALL R4 2 2  ; var4 = var4(var5)
     136 [-]: NAMECALL R4 R4 K22; var5 = var4; var4 = var4[0xF7D48EE0]
     137 [-]: CALL R4 2 2  ; var4 = var4(var5)
     138 [-]: NAMECALL R4 R4 K23; var5 = var4; var4 = var4[0x58A4D5AC]
     139 [-]: CALL R4 2 2  ; var4 = var4(var5)
     140 [-]: GETUPVAL R5 1; var5 = upvalues[1]
     141 [-]: NAMECALL R5 R5 K21; var6 = var5; var5 = var5[0xDE321E6F]
     142 [-]: CALL R5 2 2  ; var5 = var5(var6)
     143 [-]: NAMECALL R5 R5 K22; var6 = var5; var5 = var5[0xF7D48EE0]
     144 [-]: CALL R5 2 2  ; var5 = var5(var6)
     145 [-]: NAMECALL R5 R5 K24; var6 = var5; var5 = var5[0xDED54C60]
     146 [-]: CALL R5 2 2  ; var5 = var5(var6)
     147 [-]: JUMPIFLE R5 R4 L21; goto L21 if var5 <= var66620
     148 [-]: GETUPVAL R4 1; var4 = upvalues[1]
     149 [-]: NAMECALL R4 R4 K25; var5 = var4; var4 = var4[0x73901ACF]
     150 [-]: CALL R4 2 2  ; var4 = var4(var5)
     151 [-]: JUMPIF R4 L22; goto L22 if var4
L21: 152 [-]: LOADN R6 4   ; var6 = 4
     153 [-]: NAMECALL R4 R0 K17; var5 = var0; var4 = var0[0x05EEB9DB]
     154 [-]: CALL R4 3 1  ; var4(var5, var6)
     155 [-]: GETUPVAL R4 5; var4 = upvalues[5]
     156 [-]: MOVE R5 R0   ; var5 = var0
     157 [-]: CALL R4 2 1  ; var4(var5)
L22: 158 [-]: GETUPVAL R5 6; var5 = upvalues[6]
     159 [-]: FASTCALL1 64 R5 L23; 
     160 [-]: GETIMPORT R4 1; var4 = 0x7B998233
     161 [-]: CALL R4 2 2  ; var4 = var4(var5)
L23: 162 [-]: JUMPIF R4 L33; goto L33 if var4
     163 [-]: GETUPVAL R5 1; var5 = upvalues[1]
     164 [-]: FASTCALL1 64 R5 L24; 
     165 [-]: GETIMPORT R4 1; var4 = 0x7B998233
     166 [-]: CALL R4 2 2  ; var4 = var4(var5)
L24: 167 [-]: JUMPIF R4 L33; goto L33 if var4
     168 [-]: GETUPVAL R4 1; var4 = upvalues[1]
     169 [-]: NAMECALL R4 R4 K25; var5 = var4; var4 = var4[0x73901ACF]
     170 [-]: CALL R4 2 2  ; var4 = var4(var5)
     171 [-]: JUMPIFNOT R4 L33; goto L33 if not var4
     172 [-]: GETUPVAL R4 1; var4 = upvalues[1]
     173 [-]: NAMECALL R4 R4 K26; var5 = var4; var4 = var4[0x1AC1655C]
     174 [-]: CALL R4 2 2  ; var4 = var4(var5)
     175 [-]: GETUPVAL R7 6; var7 = upvalues[6]
     176 [-]: NAMECALL R7 R7 K27; var8 = var7; var7 = var7[0xC8442850]
     177 [-]: CALL R7 2 2  ; var7 = var7(var8)
     178 [-]: GETUPVAL R8 7; var8 = upvalues[7]
     179 [-]: MUL R6 R7 R8 ; var6 = var7 * var8
     180 [-]: NAMECALL R4 R4 K28; var5 = var4; var4 = var4[0x57369B8B]
     181 [-]: CALL R4 3 1  ; var4(var5, var6)
     182 [-]: GETIMPORT R4 30; var4 = 0xCBD666E1
     183 [-]: LOADN R5 0   ; var5 = 0
     184 [-]: CALL R4 2 1  ; var4(var5)
     185 [-]: JUMP L33     ; goto L33
L25: 186 [-]: JUMPXEQKN R2 K31 L28 NOT; 
     187 [-]: GETUPVAL R5 8; var5 = upvalues[8]
     188 [-]: FASTCALL1 64 R5 L26; 
     189 [-]: GETIMPORT R4 1; var4 = 0x7B998233
     190 [-]: CALL R4 2 2  ; var4 = var4(var5)
L26: 191 [-]: JUMPIFNOT R4 L27; goto L27 if not var4
     192 [-]: LOADN R6 4   ; var6 = 4
     193 [-]: NAMECALL R4 R0 K17; var5 = var0; var4 = var0[0x05EEB9DB]
     194 [-]: CALL R4 3 1  ; var4(var5, var6)
     195 [-]: GETUPVAL R4 5; var4 = upvalues[5]
     196 [-]: MOVE R5 R0   ; var5 = var0
     197 [-]: CALL R4 2 1  ; var4(var5)
     198 [-]: JUMP L33     ; goto L33
L27: 199 [-]: GETUPVAL R6 8; var6 = upvalues[8]
     200 [-]: GETTABLEKS R5 R6 K32; var5 = var6["Data"]
     201 [-]: GETTABLEKS R4 R5 K33; var4 = var5["Time"]
     202 [-]: LOADN R5 0   ; var5 = 0
     203 [-]: JUMPIFNOTLE R4 R5 L33; goto L33 if var4 > var2294817
     204 [-]: GETIMPORT R4 35; var4 = _T["RemoveHudTracker"]
     205 [-]: GETUPVAL R5 8; var5 = upvalues[8]
     206 [-]: CALL R4 2 1  ; var4(var5)
     207 [-]: LOADN R6 4   ; var6 = 4
     208 [-]: NAMECALL R4 R0 K17; var5 = var0; var4 = var0[0x05EEB9DB]
     209 [-]: CALL R4 3 1  ; var4(var5, var6)
     210 [-]: GETUPVAL R4 5; var4 = upvalues[5]
     211 [-]: MOVE R5 R0   ; var5 = var0
     212 [-]: CALL R4 2 1  ; var4(var5)
     213 [-]: JUMP L33     ; goto L33
L28: 214 [-]: JUMPXEQKN R2 K36 L31 NOT; 
     215 [-]: GETUPVAL R5 9; var5 = upvalues[9]
     216 [-]: FASTCALL1 64 R5 L29; 
     217 [-]: GETIMPORT R4 1; var4 = 0x7B998233
     218 [-]: CALL R4 2 2  ; var4 = var4(var5)
L29: 219 [-]: JUMPIFNOT R4 L30; goto L30 if not var4
     220 [-]: LOADN R6 5   ; var6 = 5
     221 [-]: NAMECALL R4 R0 K17; var5 = var0; var4 = var0[0x05EEB9DB]
     222 [-]: CALL R4 3 1  ; var4(var5, var6)
     223 [-]: GETUPVAL R4 5; var4 = upvalues[5]
     224 [-]: MOVE R5 R0   ; var5 = var0
     225 [-]: CALL R4 2 1  ; var4(var5)
     226 [-]: JUMP L33     ; goto L33
L30: 227 [-]: GETUPVAL R6 9; var6 = upvalues[9]
     228 [-]: GETTABLEKS R5 R6 K32; var5 = var6["Data"]
     229 [-]: GETTABLEKS R4 R5 K33; var4 = var5["Time"]
     230 [-]: LOADN R5 0   ; var5 = 0
     231 [-]: JUMPIFNOTLE R4 R5 L33; goto L33 if var4 > var2294817
     232 [-]: GETIMPORT R4 35; var4 = _T["RemoveHudTracker"]
     233 [-]: GETUPVAL R5 9; var5 = upvalues[9]
     234 [-]: CALL R4 2 1  ; var4(var5)
     235 [-]: LOADN R6 5   ; var6 = 5
     236 [-]: NAMECALL R4 R0 K17; var5 = var0; var4 = var0[0x05EEB9DB]
     237 [-]: CALL R4 3 1  ; var4(var5, var6)
     238 [-]: GETUPVAL R4 5; var4 = upvalues[5]
     239 [-]: MOVE R5 R0   ; var5 = var0
     240 [-]: CALL R4 2 1  ; var4(var5)
     241 [-]: JUMP L33     ; goto L33
L31: 242 [-]: JUMPXEQKN R2 K37 L33 NOT; 
     243 [-]: GETUPVAL R5 1; var5 = upvalues[1]
     244 [-]: FASTCALL1 64 R5 L32; 
     245 [-]: GETIMPORT R4 1; var4 = 0x7B998233
     246 [-]: CALL R4 2 2  ; var4 = var4(var5)
L32: 247 [-]: JUMPIF R4 L33; goto L33 if var4
     248 [-]: GETUPVAL R4 1; var4 = upvalues[1]
     249 [-]: NAMECALL R4 R4 K25; var5 = var4; var4 = var4[0x73901ACF]
     250 [-]: CALL R4 2 2  ; var4 = var4(var5)
     251 [-]: JUMPIFNOT R4 L33; goto L33 if not var4
     252 [-]: LOADN R6 0   ; var6 = 0
     253 [-]: NAMECALL R4 R0 K17; var5 = var0; var4 = var0[0x05EEB9DB]
     254 [-]: CALL R4 3 1  ; var4(var5, var6)
     255 [-]: GETUPVAL R4 5; var4 = upvalues[5]
     256 [-]: MOVE R5 R0   ; var5 = var0
     257 [-]: CALL R4 2 1  ; var4(var5)
L33: 258 [-]: GETUPVAL R5 1; var5 = upvalues[1]
     259 [-]: FASTCALL1 64 R5 L34; 
     260 [-]: GETIMPORT R4 1; var4 = 0x7B998233
     261 [-]: CALL R4 2 2  ; var4 = var4(var5)
L34: 262 [-]: JUMPIF R4 L35; goto L35 if var4
     263 [-]: GETUPVAL R4 1; var4 = upvalues[1]
     264 [-]: NAMECALL R4 R4 K20; var5 = var4; var4 = var4[0x2047CFE7]
     265 [-]: CALL R4 2 2  ; var4 = var4(var5)
     266 [-]: JUMPIF R4 L35; goto L35 if var4
     267 [-]: GETUPVAL R4 10; var4 = upvalues[10]
     268 [-]: GETIMPORT R6 39; var6 = 0x67652851
     269 [-]: CALL R6 1 0  ; var6, ... = var6()
     270 [-]: NAMECALL R4 R4 K40; var5 = var4; var4 = var4[0xFAA69527]
     271 [-]: CALL R4 0 1  ; var4(var5, ...)
L35: 272 [-]: GETUPVAL R5 11; var5 = upvalues[11]
     273 [-]: FASTCALL1 64 R5 L36; 
     274 [-]: GETIMPORT R4 1; var4 = 0x7B998233
     275 [-]: CALL R4 2 2  ; var4 = var4(var5)
L36: 276 [-]: JUMPIF R4 L52; goto L52 if var4
     277 [-]: NEWTABLE R4 0 0; var4 = {}
     278 [-]: LOADN R7 1   ; var7 = 1
     279 [-]: GETUPVAL R8 11; var8 = upvalues[11]
     280 [-]: LENGTH R5 R8 ; var5 = #var8
     281 [-]: LOADN R6 1   ; var6 = 1
     282 [-]: FORNPREP R5 L42; nforprep start - [escape at L42] -- var5 = iterator
L37: 283 [-]: GETUPVAL R9 11; var9 = upvalues[11]
     284 [-]: GETTABLE R8 R9 R7; var8 = var9[var7]
     285 [-]: NAMECALL R8 R8 K41; var9 = var8; var8 = var8[0x0D09D3C0]
     286 [-]: CALL R8 2 2  ; var8 = var8(var9)
     287 [-]: LOADN R11 1  ; var11 = 1
     288 [-]: LENGTH R9 R8 ; var9 = #var8
     289 [-]: LOADN R10 1  ; var10 = 1
     290 [-]: FORNPREP R9 L41; nforprep start - [escape at L41] -- var9 = iterator
L38: 291 [-]: GETTABLE R13 R8 R11; var13 = var8[var11]
     292 [-]: FASTCALL1 64 R13 L39; 
     293 [-]: GETIMPORT R12 1; var12 = 0x7B998233
     294 [-]: CALL R12 2 2 ; var12 = var12(var13)
L39: 295 [-]: JUMPIF R12 L40; goto L40 if var12
     296 [-]: GETTABLE R14 R8 R11; var14 = var8[var11]
     297 [-]: FASTCALL2 52 R4 R14 L40; 
     298 [-]: MOVE R13 R4  ; var13 = var4
     299 [-]: GETIMPORT R12 44; var12 = 0x33BDD652[0x23D5322F]
     300 [-]: CALL R12 3 1 ; var12(var13, var14)
L40: 301 [-]: FORNLOOP R9 L38; nforloop end - iterate + goto L38
L41: 302 [-]: FORNLOOP R5 L37; nforloop end - iterate + goto L37
L42: 303 [-]: LOADN R7 1   ; var7 = 1
     304 [-]: LENGTH R5 R4 ; var5 = #var4
     305 [-]: LOADN R6 1   ; var6 = 1
     306 [-]: FORNPREP R5 L52; nforprep start - [escape at L52] -- var5 = iterator
L43: 307 [-]: GETTABLE R8 R4 R7; var8 = var4[var7]
     308 [-]: GETIMPORT R11 46; var11 = gTennoAvatarType
     309 [-]: NAMECALL R9 R8 K47; var10 = var8; var9 = var8[0xF2DEAF69]
     310 [-]: CALL R9 3 2  ; var9 = var9(var10, var11)
     311 [-]: JUMPIFNOT R9 L51; goto L51 if not var9
     312 [-]: LOADB R9 0   ; var9 = false
     313 [-]: LOADN R12 1  ; var12 = 1
     314 [-]: GETUPVAL R13 12; var13 = upvalues[12]
     315 [-]: LENGTH R10 R13; var10 = #var13
     316 [-]: LOADN R11 1  ; var11 = 1
     317 [-]: FORNPREP R10 L46; nforprep start - [escape at L46] -- var10 = iterator
L44: 318 [-]: GETUPVAL R14 12; var14 = upvalues[12]
     319 [-]: GETTABLE R13 R14 R12; var13 = var14[var12]
     320 [-]: JUMPIFNOTEQ R8 R13 L45; goto L45 if var8 ~= var67846
     321 [-]: LOADB R9 1   ; var9 = true
     322 [-]: JUMP L46     ; goto L46
L45: 323 [-]: FORNLOOP R10 L44; nforloop end - iterate + goto L44
L46: 324 [-]: JUMPIF R9 L51; goto L51 if var9
     325 [-]: GETUPVAL R11 12; var11 = upvalues[12]
     326 [-]: FASTCALL2 52 R11 R8 L47; 
     327 [-]: MOVE R12 R8  ; var12 = var8
     328 [-]: GETIMPORT R10 44; var10 = 0x33BDD652[0x23D5322F]
     329 [-]: CALL R10 3 1 ; var10(var11, var12)
L47: 330 [-]: LOADB R10 0  ; var10 = false
     331 [-]: GETIMPORT R16 13; var16 = _T["VoidAngels"]
     332 [-]: GETTABLE R15 R16 R1; var15 = var16[var1]
     333 [-]: GETTABLEKS R14 R15 K14; var14 = var15["activePlayers"]
     334 [-]: LENGTH R13 R14; var13 = #var14
     335 [-]: LOADN R11 1  ; var11 = 1
     336 [-]: LOADN R12 -1 ; var12 = -1
     337 [-]: FORNPREP R11 L50; nforprep start - [escape at L50] -- var11 = iterator
L48: 338 [-]: GETIMPORT R17 13; var17 = _T["VoidAngels"]
     339 [-]: GETTABLE R16 R17 R1; var16 = var17[var1]
     340 [-]: GETTABLEKS R15 R16 K14; var15 = var16["activePlayers"]
     341 [-]: GETTABLE R14 R15 R13; var14 = var15[var13]
     342 [-]: JUMPIFNOTEQ R14 R8 L49; goto L49 if var14 ~= var266044
     343 [-]: GETUPVAL R15 4; var15 = upvalues[4]
     344 [-]: MOVE R16 R14 ; var16 = var14
     345 [-]: GETUPVAL R17 1; var17 = upvalues[1]
     346 [-]: CALL R15 3 1 ; var15(var16, var17)
     347 [-]: LOADB R10 1  ; var10 = true
     348 [-]: GETIMPORT R15 49; var15 = 0x33BDD652[0x9C1F3B5A]
     349 [-]: GETIMPORT R18 13; var18 = _T["VoidAngels"]
     350 [-]: GETTABLE R17 R18 R1; var17 = var18[var1]
     351 [-]: GETTABLEKS R16 R17 K14; var16 = var17["activePlayers"]
     352 [-]: MOVE R17 R13 ; var17 = var13
     353 [-]: CALL R15 3 1 ; var15(var16, var17)
     354 [-]: JUMP L50     ; goto L50
L49: 355 [-]: FORNLOOP R11 L48; nforloop end - iterate + goto L48
L50: 356 [-]: JUMPIF R10 L51; goto L51 if var10
     357 [-]: GETUPVAL R11 4; var11 = upvalues[4]
     358 [-]: MOVE R12 R8  ; var12 = var8
     359 [-]: GETUPVAL R13 1; var13 = upvalues[1]
     360 [-]: CALL R11 3 1 ; var11(var12, var13)
L51: 361 [-]: FORNLOOP R5 L43; nforloop end - iterate + goto L43
L52: 362 [-]: GETIMPORT R4 30; var4 = 0xCBD666E1
     363 [-]: LOADN R5 0   ; var5 = 0
     364 [-]: CALL R4 2 1  ; var4(var5)
     365 [-]: JUMPBACK L3  ; goto L3
L53: 366 [-]: RETURN R0 0  ; 


; Name:            
; Defined at line: 1373
; #Upvalues:       4
; #Parameters:     1
; Is_vararg:       0
; Max Stack Size:  15

L 0:   0 [-]: GETUPVAL R3 0; var3 = upvalues[0]
       1 [-]: NAMECALL R1 R0 K0; var2 = var0; var1 = var0[0x08DB51DE]
       2 [-]: CALL R1 3 2  ; var1 = var1(var2, var3)
       3 [-]: JUMPIFNOT R1 L18; goto L18 if not var1
       4 [-]: NAMECALL R1 R0 K1; var2 = var0; var1 = var0[0x5E651723]
       5 [-]: CALL R1 2 2  ; var1 = var1(var2)
       6 [-]: JUMPIF R1 L17; goto L17 if var1
       7 [-]: NAMECALL R1 R0 K2; var2 = var0; var1 = var0[0xDE321E6F]
       8 [-]: CALL R1 2 2  ; var1 = var1(var2)
       9 [-]: NAMECALL R1 R1 K3; var2 = var1; var1 = var1[0xF7D48EE0]
      10 [-]: CALL R1 2 2  ; var1 = var1(var2)
      11 [-]: FASTCALL1 64 R1 L1; 
      12 [-]: MOVE R3 R1   ; var3 = var1
      13 [-]: GETIMPORT R2 5; var2 = 0x7B998233
      14 [-]: CALL R2 2 2  ; var2 = var2(var3)
L 1:  15 [-]: JUMPIF R2 L4 ; goto L4 if var2
      16 [-]: GETUPVAL R4 1; var4 = upvalues[1]
      17 [-]: NAMECALL R2 R1 K6; var3 = var1; var2 = var1[0x689412A5]
      18 [-]: CALL R2 3 2  ; var2 = var2(var3, var4)
      19 [-]: FASTCALL1 64 R2 L2; 
      20 [-]: MOVE R4 R2   ; var4 = var2
      21 [-]: GETIMPORT R3 5; var3 = 0x7B998233
      22 [-]: CALL R3 2 2  ; var3 = var3(var4)
L 2:  23 [-]: JUMPIF R3 L3 ; goto L3 if var3
      24 [-]: NAMECALL R3 R2 K7; var4 = var2; var3 = var2[0x30F46140]
      25 [-]: CALL R3 2 2  ; var3 = var3(var4)
      26 [-]: JUMPIFNOT R3 L3; goto L3 if not var3
      27 [-]: LOADB R5 0   ; var5 = false
      28 [-]: NAMECALL R3 R2 K8; var4 = var2; var3 = var2[0xA74EA8AC]
      29 [-]: CALL R3 3 1  ; var3(var4, var5)
L 3:  30 [-]: GETIMPORT R5 10; var5 = gLotusOperatorAvatarType
      31 [-]: NAMECALL R3 R0 K11; var4 = var0; var3 = var0[0xF2DEAF69]
      32 [-]: CALL R3 3 2  ; var3 = var3(var4, var5)
      33 [-]: JUMPIFNOT R3 L4; goto L4 if not var3
      34 [-]: GETUPVAL R3 2; var3 = upvalues[2]
      35 [-]: MOVE R4 R0   ; var4 = var0
      36 [-]: CALL R3 2 1  ; var3(var4)
      37 [-]: LOADB R5 1   ; var5 = true
      38 [-]: NAMECALL R3 R0 K12; var4 = var0; var3 = var0[0x7CD1BACF]
      39 [-]: CALL R3 3 1  ; var3(var4, var5)
L 4:  40 [-]: GETUPVAL R3 3; var3 = upvalues[3]
      41 [-]: FASTCALL1 64 R3 L5; 
      42 [-]: GETIMPORT R2 5; var2 = 0x7B998233
      43 [-]: CALL R2 2 2  ; var2 = var2(var3)
L 5:  44 [-]: JUMPIF R2 L8 ; goto L8 if var2
      45 [-]: GETUPVAL R5 3; var5 = upvalues[3]
      46 [-]: LENGTH R4 R5 ; var4 = #var5
      47 [-]: LOADN R2 1   ; var2 = 1
      48 [-]: LOADN R3 -1  ; var3 = -1
      49 [-]: FORNPREP R2 L8; nforprep start - [escape at L8] -- var2 = iterator
L 6:  50 [-]: GETUPVAL R6 3; var6 = upvalues[3]
      51 [-]: GETTABLE R5 R6 R4; var5 = var6[var4]
      52 [-]: JUMPIFNOTEQ R0 R5 L7; goto L7 if var0 ~= var984353
      53 [-]: GETIMPORT R5 15; var5 = 0x33BDD652[0x9C1F3B5A]
      54 [-]: GETUPVAL R6 3; var6 = upvalues[3]
      55 [-]: MOVE R7 R4   ; var7 = var4
      56 [-]: CALL R5 3 1  ; var5(var6, var7)
      57 [-]: JUMP L8      ; goto L8
L 7:  58 [-]: FORNLOOP R2 L6; nforloop end - iterate + goto L6
L 8:  59 [-]: LOADB R2 0   ; var2 = false
      60 [-]: GETIMPORT R3 17; var3 = 0xCFC01047
      61 [-]: GETIMPORT R4 20; var4 = _T["VoidAngels"]
      62 [-]: CALL R3 2 4  ; var3, var4, var5 = var3(var4)
      63 [-]: FORGPREP_NEXT R3 L15; 
L 9:  64 [-]: GETTABLEKS R11 R7 K21; var11 = var7["activePlayers"]
      65 [-]: LENGTH R10 R11; var10 = #var11
      66 [-]: LOADN R8 1   ; var8 = 1
      67 [-]: LOADN R9 -1  ; var9 = -1
      68 [-]: FORNPREP R8 L14; nforprep start - [escape at L14] -- var8 = iterator
L10:  69 [-]: GETTABLEKS R13 R7 K21; var13 = var7["activePlayers"]
      70 [-]: GETTABLE R12 R13 R10; var12 = var13[var10]
      71 [-]: FASTCALL1 64 R12 L11; 
      72 [-]: GETIMPORT R11 5; var11 = 0x7B998233
      73 [-]: CALL R11 2 2 ; var11 = var11(var12)
L11:  74 [-]: JUMPIF R11 L13; goto L13 if var11
      75 [-]: GETTABLEKS R12 R7 K21; var12 = var7["activePlayers"]
      76 [-]: GETTABLE R11 R12 R10; var11 = var12[var10]
      77 [-]: FASTCALL1 64 R11 L12; 
      78 [-]: MOVE R13 R11 ; var13 = var11
      79 [-]: GETIMPORT R12 5; var12 = 0x7B998233
      80 [-]: CALL R12 2 2 ; var12 = var12(var13)
L12:  81 [-]: JUMPIF R12 L13; goto L13 if var12
      82 [-]: JUMPIFNOTEQ R11 R0 L13; goto L13 if var11 ~= var986145
      83 [-]: GETIMPORT R12 15; var12 = 0x33BDD652[0x9C1F3B5A]
      84 [-]: GETTABLEKS R13 R7 K21; var13 = var7["activePlayers"]
      85 [-]: MOVE R14 R10 ; var14 = var10
      86 [-]: CALL R12 3 1 ; var12(var13, var14)
      87 [-]: LOADB R2 1   ; var2 = true
      88 [-]: JUMP L14     ; goto L14
L13:  89 [-]: FORNLOOP R8 L10; nforloop end - iterate + goto L10
L14:  90 [-]: JUMPIF R2 L16; goto L16 if var2
L15:  91 [-]: FORGLOOP R3 L9 2; 
L16:  92 [-]: GETUPVAL R5 0; var5 = upvalues[0]
      93 [-]: NAMECALL R3 R0 K22; var4 = var0; var3 = var0[0xA3A0F1C2]
      94 [-]: CALL R3 3 1  ; var3(var4, var5)
      95 [-]: RETURN R0 0  ; 
L17:  96 [-]: GETIMPORT R1 24; var1 = 0xCBD666E1
      97 [-]: LOADN R2 0   ; var2 = 0
      98 [-]: CALL R1 2 1  ; var1(var2)
      99 [-]: JUMPBACK L0  ; goto L0
L18: 100 [-]: RETURN R0 0  ; 


; Name:            
; Defined at line: 1425
; #Upvalues:       3
; #Parameters:     1
; Is_vararg:       0
; Max Stack Size:  9

L 0:   0 [-]: FASTCALL1 64 R0 L1; 
       1 [-]: MOVE R2 R0   ; var2 = var0
       2 [-]: GETIMPORT R1 1; var1 = 0x7B998233
       3 [-]: CALL R1 2 2  ; var1 = var1(var2)
L 1:   4 [-]: JUMPIF R1 L9 ; goto L9 if var1
       5 [-]: GETUPVAL R3 0; var3 = upvalues[0]
       6 [-]: NAMECALL R1 R0 K2; var2 = var0; var1 = var0[0x08DB51DE]
       7 [-]: CALL R1 3 2  ; var1 = var1(var2, var3)
       8 [-]: JUMPIFNOT R1 L9; goto L9 if not var1
       9 [-]: NAMECALL R1 R0 K3; var2 = var0; var1 = var0[0xD1586535]
      10 [-]: CALL R1 2 2  ; var1 = var1(var2)
      11 [-]: NAMECALL R2 R0 K4; var3 = var0; var2 = var0[0x5E651723]
      12 [-]: CALL R2 2 2  ; var2 = var2(var3)
      13 [-]: JUMPIF R2 L8 ; goto L8 if var2
      14 [-]: NAMECALL R2 R0 K5; var3 = var0; var2 = var0[0xDE321E6F]
      15 [-]: CALL R2 2 2  ; var2 = var2(var3)
      16 [-]: NAMECALL R2 R2 K6; var3 = var2; var2 = var2[0xF7D48EE0]
      17 [-]: CALL R2 2 2  ; var2 = var2(var3)
      18 [-]: FASTCALL1 64 R2 L2; 
      19 [-]: MOVE R4 R2   ; var4 = var2
      20 [-]: GETIMPORT R3 1; var3 = 0x7B998233
      21 [-]: CALL R3 2 2  ; var3 = var3(var4)
L 2:  22 [-]: JUMPIF R3 L5 ; goto L5 if var3
      23 [-]: GETUPVAL R5 1; var5 = upvalues[1]
      24 [-]: NAMECALL R3 R2 K7; var4 = var2; var3 = var2[0x689412A5]
      25 [-]: CALL R3 3 2  ; var3 = var3(var4, var5)
      26 [-]: FASTCALL1 64 R3 L3; 
      27 [-]: MOVE R5 R3   ; var5 = var3
      28 [-]: GETIMPORT R4 1; var4 = 0x7B998233
      29 [-]: CALL R4 2 2  ; var4 = var4(var5)
L 3:  30 [-]: JUMPIF R4 L4 ; goto L4 if var4
      31 [-]: NAMECALL R4 R3 K8; var5 = var3; var4 = var3[0x30F46140]
      32 [-]: CALL R4 2 2  ; var4 = var4(var5)
      33 [-]: JUMPIFNOT R4 L4; goto L4 if not var4
      34 [-]: LOADB R6 0   ; var6 = false
      35 [-]: NAMECALL R4 R3 K9; var5 = var3; var4 = var3[0xA74EA8AC]
      36 [-]: CALL R4 3 1  ; var4(var5, var6)
L 4:  37 [-]: GETIMPORT R6 11; var6 = gLotusOperatorAvatarType
      38 [-]: NAMECALL R4 R0 K12; var5 = var0; var4 = var0[0xF2DEAF69]
      39 [-]: CALL R4 3 2  ; var4 = var4(var5, var6)
      40 [-]: JUMPIFNOT R4 L5; goto L5 if not var4
      41 [-]: GETUPVAL R4 2; var4 = upvalues[2]
      42 [-]: MOVE R5 R0   ; var5 = var0
      43 [-]: CALL R4 2 1  ; var4(var5)
      44 [-]: LOADB R6 1   ; var6 = true
      45 [-]: NAMECALL R4 R0 K13; var5 = var0; var4 = var0[0x7CD1BACF]
      46 [-]: CALL R4 3 1  ; var4(var5, var6)
L 5:  47 [-]: GETIMPORT R3 15; var3 = 0x89326C93
      48 [-]: GETIMPORT R5 17; var5 = 0x0469F296
      49 [-]: LOADK R6 K18 ; var6 = "VoidAngelPPVol"
      50 [-]: CALL R5 2 2  ; var5 = var5(var6)
      51 [-]: MOVE R6 R1   ; var6 = var1
      52 [-]: LOADN R7 0   ; var7 = 0
      53 [-]: LOADN R8 100 ; var8 = 100
      54 [-]: NAMECALL R3 R3 K19; var4 = var3; var3 = var3[0x462C251C]
      55 [-]: CALL R3 6 2  ; var3 = var3(var4, var5, var6, var7, var8)
      56 [-]: FASTCALL1 64 R3 L6; 
      57 [-]: MOVE R5 R3   ; var5 = var3
      58 [-]: GETIMPORT R4 1; var4 = 0x7B998233
      59 [-]: CALL R4 2 2  ; var4 = var4(var5)
L 6:  60 [-]: JUMPIF R4 L7 ; goto L7 if var4
      61 [-]: NAMECALL R4 R3 K20; var5 = var3; var4 = var3[0xF4E253B6]
      62 [-]: CALL R4 2 1  ; var4(var5)
L 7:  63 [-]: GETUPVAL R6 0; var6 = upvalues[0]
      64 [-]: NAMECALL R4 R0 K21; var5 = var0; var4 = var0[0xA3A0F1C2]
      65 [-]: CALL R4 3 1  ; var4(var5, var6)
      66 [-]: RETURN R0 0  ; 
L 8:  67 [-]: GETIMPORT R2 23; var2 = 0xCBD666E1
      68 [-]: LOADN R3 0   ; var3 = 0
      69 [-]: CALL R2 2 1  ; var2(var3)
      70 [-]: JUMPBACK L0  ; goto L0
L 9:  71 [-]: RETURN R0 0  ; 



