; Name:            
; Defined at line: 1
; #Upvalues:       0
; #Parameters:     0
; Is_vararg:       1
; Max Stack Size:  28

       1 [-]: GETIMPORT R0 1; var0 = 0x2D0FAD09
       2 [-]: LOADK R1 K2  ; var1 = "Lotus.Interface.LotusUtilities"
       3 [-]: CALL R0 2 2  ; var0 = var0(var1)
       4 [-]: GETIMPORT R1 1; var1 = 0x2D0FAD09
       5 [-]: LOADK R2 K3  ; var2 = "EE.Interface.Utilities"
       6 [-]: CALL R1 2 2  ; var1 = var1(var2)
       7 [-]: LOADB R2 0   ; var2 = false
       8 [-]: LOADB R3 0   ; var3 = false
       9 [-]: LOADNIL R4   ; var4 = nil
      10 [-]: LOADNIL R5   ; var5 = nil
      11 [-]: LOADNIL R6   ; var6 = nil
      12 [-]: NEWTABLE R7 0 15; var7 = {}
      13 [-]: LOADK R8 K4  ; var8 = "<DT_IMPACT>"
      14 [-]: LOADK R9 K5  ; var9 = "<DT_PUNCTURE>"
      15 [-]: LOADK R10 K6 ; var10 = "<DT_SLASH>"
      16 [-]: LOADK R11 K7 ; var11 = "<DT_FIRE>"
      17 [-]: LOADK R12 K8 ; var12 = "<DT_FREEZE>"
      18 [-]: LOADK R13 K9 ; var13 = "<DT_ELECTRICITY>"
      19 [-]: LOADK R14 K10; var14 = "<DT_POISON>"
      20 [-]: LOADK R15 K11; var15 = "<DT_EXPLOSION>"
      21 [-]: LOADK R16 K12; var16 = "<DT_RADIATION>"
      22 [-]: LOADK R17 K13; var17 = "<DT_GAS>"
      23 [-]: LOADK R18 K14; var18 = "<DT_MAGNETIC>"
      24 [-]: LOADK R19 K15; var19 = "<DT_VIRAL>"
      25 [-]: LOADK R20 K16; var20 = "<DT_CORROSIVE>"
      26 [-]: LOADK R21 K17; var21 = "<DT_RADIANT>"
      27 [-]: LOADK R22 K18; var22 = "<DT_SENTIENT>"
      28 [-]: SETLIST R7 R8 15 [1]; var7[1] = var8; var7[2] = var9; var7[3] = var10; var7[4] = var11; var7[5] = var12; var7[6] = var13; var7[7] = var14; var7[8] = var15; var7[9] = var16; var7[10] = var17; var7[11] = var18; var7[12] = var19; var7[13] = var20; var7[14] = var21; var7[15] = var22; var7[16] = var23; 
      29 [-]: NEWTABLE R8 0 17; var8 = {}
      30 [-]: LOADK R9 K19 ; var9 = "/Lotus/Language/Game/RK_NONE"
      31 [-]: LOADK R10 K20; var10 = "/Lotus/Language/Game/RK_FLESH"
      32 [-]: LOADK R11 K21; var11 = "/Lotus/Language/Game/RK_CLONED_FLESH"
      33 [-]: LOADK R12 K22; var12 = "/Lotus/Language/Game/RK_INFESTED_FLESH"
      34 [-]: LOADK R13 K23; var13 = "/Lotus/Language/Game/RK_TENNO_FLESH"
      35 [-]: LOADK R14 K24; var14 = "/Lotus/Language/Game/RK_ROBOTIC"
      36 [-]: LOADK R15 K25; var15 = "/Lotus/Language/Game/RK_MACHINERY"
      37 [-]: LOADK R16 K26; var16 = "/Lotus/Language/Game/RK_INFESTED"
      38 [-]: LOADK R17 K27; var17 = "/Lotus/Language/Game/RK_FOSSILIZED"
      39 [-]: LOADK R18 K28; var18 = "/Lotus/Language/Game/RK_ARMOR"
      40 [-]: LOADK R19 K29; var19 = "/Lotus/Language/Game/RK_HULKING_ARMOR"
      41 [-]: LOADK R20 K30; var20 = "/Lotus/Language/Game/RK_INFESTED_ARMOUR"
      42 [-]: LOADK R21 K31; var21 = "/Lotus/Language/Game/RK_TENNO_ARMOUR"
      43 [-]: LOADK R22 K32; var22 = "/Lotus/Language/Game/RK_SHIELD"
      44 [-]: LOADK R23 K33; var23 = "/Lotus/Language/Game/RK_HEAVY_SHIELD"
      45 [-]: LOADK R24 K34; var24 = "/Lotus/Language/Game/RK_TENNO_SHIELD"
      46 [-]: SETLIST R8 R9 16 [1]; var8[1] = var9; var8[2] = var10; var8[3] = var11; var8[4] = var12; var8[5] = var13; var8[6] = var14; var8[7] = var15; var8[8] = var16; var8[9] = var17; var8[10] = var18; var8[11] = var19; var8[12] = var20; var8[13] = var21; var8[14] = var22; var8[15] = var23; var8[16] = var24; var8[17] = var25; 
      47 [-]: LOADK R9 K35 ; var9 = "/Lotus/Language/Codex/RK_OVERGUARD"
      48 [-]: SETLIST R8 R9 1 [17]; var8[17] = var9; var8[18] = var10; 
      49 [-]: GETIMPORT R9 37; var9 = 0x78CA68A2
      50 [-]: LOADN R10 0  ; var10 = 0
      51 [-]: LOADK R11 K38; var11 = 0.050000000000000003
      52 [-]: CALL R9 3 2  ; var9 = var9(var10, var11)
      53 [-]: LOADNIL R10  ; var10 = nil
      54 [-]: LOADNIL R11  ; var11 = nil
      55 [-]: LOADNIL R12  ; var12 = nil
      56 [-]: GETIMPORT R13 40; var13 = 0x0469F296
      57 [-]: LOADK R14 K41; var14 = "Reticle"
      58 [-]: CALL R13 2 2 ; var13 = var13(var14)
      59 [-]: GETIMPORT R14 40; var14 = 0x0469F296
      60 [-]: LOADK R15 K42; var15 = "CollectorTarget"
      61 [-]: CALL R14 2 2 ; var14 = var14(var15)
      62 [-]: LOADNIL R15  ; var15 = nil
      63 [-]: LOADNIL R16  ; var16 = nil
      64 [-]: LOADNIL R17  ; var17 = nil
      65 [-]: DUPTABLE R18 44; 
      66 [-]: NEWTABLE R19 0 0; var19 = {}
      67 [-]: SETTABLEKS R19 R18 K43; var19["Resistances"] = var18
      68 [-]: DUPTABLE R19 51; 
      69 [-]: LOADN R20 0  ; var20 = 0
      70 [-]: SETTABLEKS R20 R19 K45; var20["mLastScans"] = var19
      71 [-]: LOADB R20 1  ; var20 = true
      72 [-]: SETTABLEKS R20 R19 K46; var20["mPriorCanScan"] = var19
      73 [-]: LOADNIL R20  ; var20 = nil
      74 [-]: SETTABLEKS R20 R19 K47; var20["mScanningTag"] = var19
      75 [-]: LOADN R20 0  ; var20 = 0
      76 [-]: SETTABLEKS R20 R19 K48; var20["Lerp"] = var19
      77 [-]: GETIMPORT R20 53; var20 = 0x60130201
      78 [-]: LOADN R21 255; var21 = 255
      79 [-]: LOADN R22 255; var22 = 255
      80 [-]: LOADN R23 255; var23 = 255
      81 [-]: CALL R20 4 2 ; var20 = var20(var21, var22, var23)
      82 [-]: SETTABLEKS R20 R19 K49; var20["ColorA"] = var19
      83 [-]: GETIMPORT R20 53; var20 = 0x60130201
      84 [-]: LOADN R21 255; var21 = 255
      85 [-]: LOADN R22 0  ; var22 = 0
      86 [-]: LOADN R23 0  ; var23 = 0
      87 [-]: CALL R20 4 2 ; var20 = var20(var21, var22, var23)
      88 [-]: SETTABLEKS R20 R19 K50; var20["ColorB"] = var19
      89 [-]: DUPCLOSURE R20 K54; 
      90 [-]: CAPTURE VAL R0; 
      91 [-]: NEWCLOSURE R21 P1; 
      92 [-]: CAPTURE REF R11; 
      93 [-]: CAPTURE VAL R20; 
      94 [-]: NEWCLOSURE R22 P2; 
      95 [-]: CAPTURE REF R2; 
      96 [-]: CAPTURE REF R5; 
      97 [-]: CAPTURE REF R3; 
      98 [-]: CAPTURE REF R6; 
      99 [-]: CAPTURE VAL R9; 
     100 [-]: CAPTURE VAL R1; 
     101 [-]: SETGLOBAL R22 K55; "Update" = var22
     102 [-]: DUPCLOSURE R22 K56; 
     103 [-]: SETGLOBAL R22 K57; "OnProfileSaved" = var22
     104 [-]: NEWCLOSURE R22 P4; 
     105 [-]: CAPTURE REF R10; 
     106 [-]: CAPTURE VAL R1; 
     107 [-]: CAPTURE REF R11; 
     108 [-]: DUPCLOSURE R23 K58; 
     109 [-]: CAPTURE VAL R1; 
     110 [-]: NEWCLOSURE R24 P6; 
     111 [-]: CAPTURE REF R6; 
     112 [-]: CAPTURE VAL R22; 
     113 [-]: CAPTURE VAL R23; 
     114 [-]: CAPTURE VAL R7; 
     115 [-]: CAPTURE VAL R8; 
     116 [-]: CAPTURE REF R2; 
     117 [-]: SETGLOBAL R24 K59; "Initialize" = var24
     118 [-]: NEWCLOSURE R24 P7; 
     119 [-]: CAPTURE REF R4; 
     120 [-]: SETGLOBAL R24 K60; "SetWeapon" = var24
     121 [-]: NEWCLOSURE R24 P8; 
     122 [-]: CAPTURE VAL R1; 
     123 [-]: CAPTURE VAL R13; 
     124 [-]: CAPTURE VAL R0; 
     125 [-]: CAPTURE REF R3; 
     126 [-]: DUPCLOSURE R25 K61; 
     127 [-]: CAPTURE VAL R24; 
     128 [-]: SETGLOBAL R25 K62; "SetAiming" = var25
     129 [-]: NEWCLOSURE R25 P10; 
     130 [-]: CAPTURE REF R3; 
     131 [-]: SETGLOBAL R25 K63; "IsAiming" = var25
     132 [-]: DUPCLOSURE R25 K64; 
     133 [-]: CAPTURE VAL R24; 
     134 [-]: SETGLOBAL R25 K65; "SetEnabled" = var25
     135 [-]: DUPCLOSURE R25 K66; 
     136 [-]: SETGLOBAL R25 K67; "OnFire" = var25
     137 [-]: DUPCLOSURE R25 K68; 
     138 [-]: CAPTURE VAL R9; 
     139 [-]: SETGLOBAL R25 K69; "SetScanProgress" = var25
     140 [-]: NEWCLOSURE R25 P14; 
     141 [-]: CAPTURE REF R11; 
     142 [-]: CAPTURE VAL R20; 
     143 [-]: SETGLOBAL R25 K70; "BonusScanProc" = var25
     144 [-]: DUPCLOSURE R25 K71; 
     145 [-]: SETGLOBAL R25 K72; "SetFloatingMarker" = var25
     146 [-]: NEWCLOSURE R25 P16; 
     147 [-]: CAPTURE REF R12; 
     148 [-]: SETGLOBAL R25 K73; "SetFloatingMarkerPosition" = var25
     149 [-]: DUPCLOSURE R25 K74; 
     150 [-]: CAPTURE VAL R0; 
     151 [-]: SETGLOBAL R25 K75; "SetScanPointDestroyed" = var25
     152 [-]: DUPCLOSURE R25 K76; 
     153 [-]: CAPTURE VAL R0; 
     154 [-]: SETGLOBAL R25 K77; "SetScanTargetAlert" = var25
     155 [-]: DUPCLOSURE R25 K78; 
     156 [-]: SETGLOBAL R25 K79; "AnimateFloatingMarker" = var25
     157 [-]: DUPCLOSURE R25 K80; 
     158 [-]: CAPTURE VAL R13; 
     159 [-]: SETGLOBAL R25 K81; "ClearCustomReticleAiming" = var25
     160 [-]: DUPCLOSURE R25 K82; 
     161 [-]: SETGLOBAL R25 K83; "UpdateRangeFinder" = var25
     162 [-]: DUPCLOSURE R25 K84; 
     163 [-]: CAPTURE VAL R8; 
     164 [-]: DUPCLOSURE R26 K85; 
     165 [-]: CAPTURE VAL R18; 
     166 [-]: CAPTURE VAL R7; 
     167 [-]: CAPTURE VAL R25; 
     168 [-]: NEWCLOSURE R27 P24; 
     169 [-]: CAPTURE VAL R14; 
     170 [-]: CAPTURE VAL R0; 
     171 [-]: CAPTURE REF R15; 
     172 [-]: CAPTURE REF R16; 
     173 [-]: CAPTURE VAL R19; 
     174 [-]: CAPTURE VAL R1; 
     175 [-]: CAPTURE VAL R26; 
     176 [-]: CAPTURE REF R17; 
     177 [-]: SETGLOBAL R27 K86; "ScanUpdate" = var27
     178 [-]: DUPCLOSURE R27 K87; 
     179 [-]: CAPTURE VAL R23; 
     180 [-]: SETGLOBAL R27 K88; "onViewportSizeChanged" = var27
     181 [-]: DUPCLOSURE R27 K89; 
     182 [-]: CAPTURE VAL R0; 
     183 [-]: SETGLOBAL R27 K90; "Shutdown" = var27
     184 [-]: CLOSEUPVALS R2; 
     185 [-]: RETURN R0 0  ; 


; Name:            
; Defined at line: 88
; #Upvalues:       1
; #Parameters:     4
; Is_vararg:       0
; Max Stack Size:  13

       0 [-]: FASTCALL1 62 R1 L0; 
       1 [-]: MOVE R5 R1   ; var5 = var1
       2 [-]: GETIMPORT R4 1; var4 = 0x7B998233
       3 [-]: CALL R4 2 2  ; var4 = var4(var5)
L 0:   4 [-]: JUMPIF R4 L2 ; goto L2 if var4
       5 [-]: JUMPXEQKNIL R2 L1 NOT; 
       6 [-]: LOADN R2 0   ; var2 = 0
L 1:   7 [-]: GETUPVAL R5 0; var5 = upvalues[0]
       8 [-]: GETTABLEKS R4 R5 K2; var4 = var5[0xB5BE5D4A]
       9 [-]: GETIMPORT R5 4; var5 = 0xAE91E43B
      10 [-]: MOVE R6 R0   ; var6 = var0
      11 [-]: CALL R4 3 3  ; var4, var5 = var4(var5, var6)
      12 [-]: GETUPVAL R7 0; var7 = upvalues[0]
      13 [-]: GETTABLEKS R6 R7 K5; var6 = var7[0x5A22D251]
      14 [-]: GETIMPORT R7 4; var7 = 0xAE91E43B
      15 [-]: MOVE R8 R1   ; var8 = var1
      16 [-]: MOVE R9 R4   ; var9 = var4
      17 [-]: ADD R10 R5 R2; var10 = var5 + var2
      18 [-]: CALL R6 5 1  ; var6(var7, var8, var9, var10)
L 2:  19 [-]: JUMPXEQKNIL R3 L3 NOT; 
      20 [-]: LOADN R3 1   ; var3 = 1
L 3:  21 [-]: GETIMPORT R4 4; var4 = 0xAE91E43B
      22 [-]: MOVE R6 R0   ; var6 = var0
      23 [-]: LOADN R7 10  ; var7 = 10
      24 [-]: LOADN R8 0   ; var8 = 0
      25 [-]: NAMECALL R4 R4 K6; var5 = var4; var4 = var4[0x67BC869F]
      26 [-]: CALL R4 5 1  ; var4(var5, var6, var7, var8)
      27 [-]: GETIMPORT R4 4; var4 = 0xAE91E43B
      28 [-]: MOVE R6 R0   ; var6 = var0
      29 [-]: LOADN R7 5   ; var7 = 5
      30 [-]: LOADN R8 200 ; var8 = 200
      31 [-]: NAMECALL R4 R4 K6; var5 = var4; var4 = var4[0x67BC869F]
      32 [-]: CALL R4 5 1  ; var4(var5, var6, var7, var8)
      33 [-]: GETIMPORT R4 4; var4 = 0xAE91E43B
      34 [-]: MOVE R6 R0   ; var6 = var0
      35 [-]: LOADN R7 6   ; var7 = 6
      36 [-]: LOADN R8 200 ; var8 = 200
      37 [-]: NAMECALL R4 R4 K6; var5 = var4; var4 = var4[0x67BC869F]
      38 [-]: CALL R4 5 1  ; var4(var5, var6, var7, var8)
      39 [-]: GETIMPORT R4 8; var4 = 0x25312C9B
      40 [-]: GETIMPORT R5 4; var5 = 0xAE91E43B
      41 [-]: MOVE R6 R0   ; var6 = var0
      42 [-]: LOADN R7 2   ; var7 = 2
      43 [-]: NEWTABLE R8 0 3; var8 = {}
      44 [-]: LOADN R9 10  ; var9 = 10
      45 [-]: LOADN R10 5  ; var10 = 5
      46 [-]: LOADN R11 6  ; var11 = 6
      47 [-]: SETLIST R8 R9 3 [1]; var8[1] = var9; var8[2] = var10; var8[3] = var11; var8[4] = var12; 
      48 [-]: NEWTABLE R9 0 3; var9 = {}
      49 [-]: LOADN R10 100; var10 = 100
      50 [-]: LOADN R11 100; var11 = 100
      51 [-]: LOADN R12 100; var12 = 100
      52 [-]: SETLIST R9 R10 3 [1]; var9[1] = var10; var9[2] = var11; var9[3] = var12; var9[4] = var13; 
      53 [-]: LOADK R10 K9 ; var10 = 0.14999999999999999
      54 [-]: LOADN R11 0  ; var11 = 0
      55 [-]: NEWCLOSURE R12 P0; 
      56 [-]: CAPTURE VAL R0; 
      57 [-]: CAPTURE REF R3; 
      58 [-]: CALL R4 9 1  ; var4(var5, var6, var7, var8, var9, var10, var11, var12)
      59 [-]: CLOSEUPVALS R3; 
      60 [-]: RETURN R0 0  ; 


; Name:            
; Defined at line: 110
; #Upvalues:       2
; #Parameters:     0
; Is_vararg:       0
; Max Stack Size:  5

       0 [-]: GETUPVAL R0 0; var0 = upvalues[0]
       1 [-]: JUMPXEQKNIL R0 L0; 
       2 [-]: GETUPVAL R0 1; var0 = upvalues[1]
       3 [-]: GETUPVAL R2 0; var2 = upvalues[0]
       4 [-]: LOADK R3 K0  ; var3 = ".Notification"
       5 [-]: CONCAT R1 R2 R3; var1 = var2 .. var3
       6 [-]: GETIMPORT R2 2; var2 = 0x124946BD
       7 [-]: LOADN R3 -145; var3 = -145
       8 [-]: LOADN R4 3   ; var4 = 3
       9 [-]: CALL R0 5 1  ; var0(var1, var2, var3, var4)
L 0:  10 [-]: RETURN R0 0  ; 


; Name:            
; Defined at line: 116
; #Upvalues:       6
; #Parameters:     0
; Is_vararg:       0
; Max Stack Size:  10

       0 [-]: GETIMPORT R1 1; var1 = 0xAE91E43B
       1 [-]: FASTCALL1 62 R1 L0; 
       2 [-]: GETIMPORT R0 3; var0 = 0x7B998233
       3 [-]: CALL R0 2 2  ; var0 = var0(var1)
L 0:   4 [-]: JUMPIF R0 L1 ; goto L1 if var0
       5 [-]: GETUPVAL R0 0; var0 = upvalues[0]
       6 [-]: JUMPIF R0 L2 ; goto L2 if var0
L 1:   7 [-]: RETURN R0 0  ; 
L 2:   8 [-]: GETIMPORT R0 5; var0 = 0x67652851
       9 [-]: CALL R0 1 2  ; var0 = var0()
      10 [-]: GETIMPORT R1 1; var1 = 0xAE91E43B
      11 [-]: MOVE R3 R0   ; var3 = var0
      12 [-]: NAMECALL R1 R1 K6; var2 = var1; var1 = var1[0x8A8C8D5A]
      13 [-]: CALL R1 3 1  ; var1(var2, var3)
      14 [-]: GETUPVAL R2 1; var2 = upvalues[1]
      15 [-]: FASTCALL1 62 R2 L3; 
      16 [-]: GETIMPORT R1 3; var1 = 0x7B998233
      17 [-]: CALL R1 2 2  ; var1 = var1(var2)
L 3:  18 [-]: JUMPIFNOT R1 L4; goto L4 if not var1
      19 [-]: GETIMPORT R1 8; var1 = 0xBE190284
      20 [-]: NAMECALL R1 R1 K9; var2 = var1; var1 = var1[0x33307F92]
      21 [-]: CALL R1 2 2  ; var1 = var1(var2)
      22 [-]: SETUPVAL R1 1; upvalues[1] = var1
L 4:  23 [-]: GETUPVAL R1 2; var1 = upvalues[2]
      24 [-]: JUMPIFNOT R1 L5; goto L5 if not var1
      25 [-]: GETIMPORT R1 1; var1 = 0xAE91E43B
      26 [-]: LOADK R3 K10 ; var3 = "ReticleSniper.TheReticle.Left"
      27 [-]: LOADN R4 2   ; var4 = 2
      28 [-]: NAMECALL R1 R1 K11; var2 = var1; var1 = var1[0x91A24E4B]
      29 [-]: CALL R1 4 2  ; var1 = var1(var2, var3, var4)
      30 [-]: GETIMPORT R2 1; var2 = 0xAE91E43B
      31 [-]: LOADK R4 K12 ; var4 = "ReticleSniper.RemainingCharges"
      32 [-]: LOADN R5 0   ; var5 = 0
      33 [-]: GETUPVAL R8 3; var8 = upvalues[3]
      34 [-]: SUB R7 R1 R8 ; var7 = var1 - var8
      35 [-]: ADDK R6 R7 K13; var6 = var7 + 170
      36 [-]: NAMECALL R2 R2 K14; var3 = var2; var2 = var2[0x67BC869F]
      37 [-]: CALL R2 5 1  ; var2(var3, var4, var5, var6)
      38 [-]: GETIMPORT R2 1; var2 = 0xAE91E43B
      39 [-]: LOADK R4 K15 ; var4 = "ReticleSniper.TheReticle.Right"
      40 [-]: LOADN R5 2   ; var5 = 2
      41 [-]: NAMECALL R2 R2 K11; var3 = var2; var2 = var2[0x91A24E4B]
      42 [-]: CALL R2 4 2  ; var2 = var2(var3, var4, var5)
      43 [-]: GETIMPORT R3 1; var3 = 0xAE91E43B
      44 [-]: LOADK R5 K16 ; var5 = "ReticleSniper.ScansTaken"
      45 [-]: LOADN R6 0   ; var6 = 0
      46 [-]: GETUPVAL R9 3; var9 = upvalues[3]
      47 [-]: SUB R8 R2 R9 ; var8 = var2 - var9
      48 [-]: SUBK R7 R8 K13; var7 = var8 - 170
      49 [-]: NAMECALL R3 R3 K14; var4 = var3; var3 = var3[0x67BC869F]
      50 [-]: CALL R3 5 1  ; var3(var4, var5, var6, var7)
L 5:  51 [-]: GETUPVAL R1 4; var1 = upvalues[4]
      52 [-]: NAMECALL R1 R1 K17; var2 = var1; var1 = var1[0x54AB95F9]
      53 [-]: CALL R1 2 2  ; var1 = var1(var2)
      54 [-]: GETUPVAL R2 4; var2 = upvalues[4]
      55 [-]: GETIMPORT R4 19; var4 = 0xB693B6C1
      56 [-]: CALL R4 1 0  ; var4, ... = var4()
      57 [-]: NAMECALL R2 R2 K20; var3 = var2; var2 = var2[0xFAA69527]
      58 [-]: CALL R2 0 1  ; var2(var3, ...)
      59 [-]: GETUPVAL R2 4; var2 = upvalues[4]
      60 [-]: NAMECALL R2 R2 K17; var3 = var2; var2 = var2[0x54AB95F9]
      61 [-]: CALL R2 2 2  ; var2 = var2(var3)
      62 [-]: JUMPIFEQ R1 R2 L6; goto L6 if var1 == var1442382
      63 [-]: GETIMPORT R2 22; var2 = 0x9BAFFFE3
      64 [-]: LOADN R3 1   ; var3 = 1
      65 [-]: GETIMPORT R4 1; var4 = 0xAE91E43B
      66 [-]: LOADK R6 K23 ; var6 = "ReticleSniper.Scanning.Progress"
      67 [-]: LOADN R7 8   ; var7 = 8
      68 [-]: NAMECALL R4 R4 K11; var5 = var4; var4 = var4[0x91A24E4B]
      69 [-]: CALL R4 4 2  ; var4 = var4(var5, var6, var7)
      70 [-]: MOVE R5 R1   ; var5 = var1
      71 [-]: CALL R2 4 2  ; var2 = var2(var3, var4, var5)
      72 [-]: GETUPVAL R4 5; var4 = upvalues[5]
      73 [-]: GETTABLEKS R3 R4 K24; var3 = var4[0x74A11EC6]
      74 [-]: MOVE R4 R2   ; var4 = var2
      75 [-]: CALL R3 2 2  ; var3 = var3(var4)
      76 [-]: MOVE R2 R3   ; var2 = var3
      77 [-]: GETIMPORT R3 26; var3 = 0x38F10E85
      78 [-]: GETIMPORT R4 1; var4 = 0xAE91E43B
      79 [-]: LOADK R5 K27 ; var5 = "ReticleSniper.Scanning.Progress.gotoAndStop"
      80 [-]: MOVE R6 R2   ; var6 = var2
      81 [-]: CALL R3 4 1  ; var3(var4, var5, var6)
L 6:  82 [-]: RETURN R0 0  ; 


; Name:            
; Defined at line: 146
; #Upvalues:       0
; #Parameters:     0
; Is_vararg:       0
; Max Stack Size:  0

       0 [-]: RETURN R0 0  ; 


; Name:            
; Defined at line: 149
; #Upvalues:       3
; #Parameters:     0
; Is_vararg:       0
; Max Stack Size:  16

       0 [-]: GETIMPORT R0 1; var0 = 0x2D0FAD09
       1 [-]: LOADK R1 K2  ; var1 = "EE.Interface.Components.List"
       2 [-]: CALL R0 2 2  ; var0 = var0(var1)
       3 [-]: GETTABLEKS R1 R0 K3; var1 = var0[0x9383BC56]
       4 [-]: GETIMPORT R2 5; var2 = 0xAE91E43B
       5 [-]: LOADK R3 K6  ; var3 = "ReticleSniper.Upgrade"
       6 [-]: CALL R1 3 2  ; var1 = var1(var2, var3)
       7 [-]: SETUPVAL R1 0; upvalues[1] = var0
       8 [-]: GETUPVAL R1 0; var1 = upvalues[0]
       9 [-]: LOADN R2 0   ; var2 = 0
      10 [-]: SETTABLEKS R2 R1 K7; var2["mForcedVerticalSeparation"] = var1
      11 [-]: GETUPVAL R1 0; var1 = upvalues[0]
      12 [-]: LOADN R2 120 ; var2 = 120
      13 [-]: SETTABLEKS R2 R1 K8; var2["mForcedHorizontalSeparation"] = var1
      14 [-]: GETUPVAL R1 0; var1 = upvalues[0]
      15 [-]: NEWCLOSURE R2 P0; 
      16 [-]: CAPTURE UPVAL U1; 
      17 [-]: CAPTURE UPVAL U2; 
      18 [-]: SETTABLEKS R2 R1 K9; var2["mElementDrawCallback"] = var1
      19 [-]: GETUPVAL R1 0; var1 = upvalues[0]
      20 [-]: GETUPVAL R3 0; var3 = upvalues[0]
      21 [-]: GETTABLEKS R2 R3 K10; var2 = var3["CalculateX"]
      22 [-]: SETTABLEKS R2 R1 K11; var2["_UpgradeMenu_CalculateX"] = var1
      23 [-]: GETUPVAL R1 0; var1 = upvalues[0]
      24 [-]: NEWCLOSURE R2 P1; 
      25 [-]: CAPTURE UPVAL U0; 
      26 [-]: SETTABLEKS R2 R1 K10; var2["CalculateX"] = var1
      27 [-]: LOADNIL R1   ; var1 = nil
      28 [-]: GETIMPORT R3 13; var3 = 0x76EA806B
      29 [-]: LOADN R5 0   ; var5 = 0
      30 [-]: NAMECALL R3 R3 K14; var4 = var3; var3 = var3[0x3F3AE64C]
      31 [-]: CALL R3 3 2  ; var3 = var3(var4, var5)
      32 [-]: FASTCALL1 62 R3 L0; 
      33 [-]: GETIMPORT R2 16; var2 = 0x7B998233
      34 [-]: CALL R2 2 2  ; var2 = var2(var3)
L 0:  35 [-]: JUMPIF R2 L1 ; goto L1 if var2
      36 [-]: GETIMPORT R2 13; var2 = 0x76EA806B
      37 [-]: LOADN R4 0   ; var4 = 0
      38 [-]: NAMECALL R2 R2 K14; var3 = var2; var2 = var2[0x3F3AE64C]
      39 [-]: CALL R2 3 2  ; var2 = var2(var3, var4)
      40 [-]: NAMECALL R2 R2 K17; var3 = var2; var2 = var2[0x80563238]
      41 [-]: CALL R2 2 2  ; var2 = var2(var3)
      42 [-]: NAMECALL R3 R2 K18; var4 = var2; var3 = var2[0x25A6E75E]
      43 [-]: CALL R3 2 2  ; var3 = var3(var4)
      44 [-]: NAMECALL R3 R3 K19; var4 = var3; var3 = var3[0xF4045B7E]
      45 [-]: CALL R3 2 2  ; var3 = var3(var4)
      46 [-]: MOVE R1 R3   ; var1 = var3
L 1:  47 [-]: GETIMPORT R2 21; var2 = 0xC8802016
      48 [-]: GETIMPORT R3 23; var3 = 0x3226EC24
      49 [-]: CALL R2 2 4  ; var2, var3, var4 = var2(var3)
      50 [-]: FORGPREP_INEXT R2 L6; 
L 2:  51 [-]: NEWTABLE R7 4 0; var7 = {}
      52 [-]: NAMECALL R8 R6 K24; var9 = var6; var8 = var6[0x056DCF06]
      53 [-]: CALL R8 2 2  ; var8 = var8(var9)
      54 [-]: SETTABLEKS R8 R7 K25; var8["Icon"] = var7
      55 [-]: NAMECALL R8 R6 K26; var9 = var6; var8 = var6[0xF278F8A1]
      56 [-]: CALL R8 2 2  ; var8 = var8(var9)
      57 [-]: SETTABLEKS R8 R7 K27; var8["ItemType"] = var7
      58 [-]: LOADB R8 0   ; var8 = false
      59 [-]: GETIMPORT R9 21; var9 = 0xC8802016
      60 [-]: MOVE R10 R1  ; var10 = var1
      61 [-]: CALL R9 2 4  ; var9, var10, var11 = var9(var10)
      62 [-]: FORGPREP_INEXT R9 L4; 
L 3:  63 [-]: GETTABLEKS R14 R13 K28; var14 = var13["mItemCount"]
      64 [-]: LOADN R15 0  ; var15 = 0
      65 [-]: JUMPIFNOTLT R15 R14 L4; goto L4 if var15 >= var-787673572
      66 [-]: GETTABLEKS R14 R13 K29; var14 = var13["mItemType"]
      67 [-]: GETTABLEKS R15 R7 K27; var15 = var7["ItemType"]
      68 [-]: JUMPIFNOTEQ R14 R15 L4; goto L4 if var14 ~= var67611
      69 [-]: LOADB R8 1   ; var8 = true
      70 [-]: JUMP L5      ; goto L5
L 4:  71 [-]: FORGLOOP R9 L3 2 [inext]; 
L 5:  72 [-]: SETTABLEKS R8 R7 K30; var8["Acquired"] = var7
      73 [-]: GETUPVAL R9 0; var9 = upvalues[0]
      74 [-]: MOVE R11 R7  ; var11 = var7
      75 [-]: LOADB R12 1  ; var12 = true
      76 [-]: NAMECALL R9 R9 K31; var10 = var9; var9 = var9[0xBAD4316F]
      77 [-]: CALL R9 4 1  ; var9(var10, var11, var12)
L 6:  78 [-]: FORGLOOP R2 L2 2 [inext]; 
      79 [-]: GETUPVAL R2 0; var2 = upvalues[0]
      80 [-]: NAMECALL R2 R2 K32; var3 = var2; var2 = var2[0x71E9AC81]
      81 [-]: CALL R2 2 1  ; var2(var3)
      82 [-]: RETURN R0 0  ; 


; Name:            
; Defined at line: 203
; #Upvalues:       1
; #Parameters:     0
; Is_vararg:       0
; Max Stack Size:  7

       0 [-]: GETIMPORT R0 2; var0 = 0x34291F5C[0x1467D5F4]
       1 [-]: CALL R0 1 2  ; var0 = var0()
       2 [-]: JUMPIFNOT R0 L0; goto L0 if not var0
       3 [-]: RETURN R0 0  ; 
L 0:   4 [-]: GETUPVAL R1 0; var1 = upvalues[0]
       5 [-]: GETTABLEKS R0 R1 K3; var0 = var1[0x44537ADF]
       6 [-]: GETIMPORT R1 5; var1 = 0xAE91E43B
       7 [-]: CALL R0 2 3  ; var0, var1 = var0(var1)
       8 [-]: GETIMPORT R2 5; var2 = 0xAE91E43B
       9 [-]: LOADK R4 K6  ; var4 = "ReticleSniper.BlackBg"
      10 [-]: LOADN R5 12  ; var5 = 12
      11 [-]: MOVE R6 R0   ; var6 = var0
      12 [-]: NAMECALL R2 R2 K7; var3 = var2; var2 = var2[0x67BC869F]
      13 [-]: CALL R2 5 1  ; var2(var3, var4, var5, var6)
      14 [-]: GETIMPORT R2 5; var2 = 0xAE91E43B
      15 [-]: LOADK R4 K6  ; var4 = "ReticleSniper.BlackBg"
      16 [-]: LOADN R5 13  ; var5 = 13
      17 [-]: MOVE R6 R1   ; var6 = var1
      18 [-]: NAMECALL R2 R2 K7; var3 = var2; var2 = var2[0x67BC869F]
      19 [-]: CALL R2 5 1  ; var2(var3, var4, var5, var6)
      20 [-]: RETURN R0 0  ; 


; Name:            
; Defined at line: 214
; #Upvalues:       6
; #Parameters:     0
; Is_vararg:       0
; Max Stack Size:  10

       0 [-]: GETIMPORT R0 1; var0 = 0xAE91E43B
       1 [-]: LOADK R2 K2  ; var2 = "FloatingMarker"
       2 [-]: LOADN R3 11  ; var3 = 11
       3 [-]: LOADB R4 0   ; var4 = false
       4 [-]: NAMECALL R0 R0 K3; var1 = var0; var0 = var0[0xAADE900E]
       5 [-]: CALL R0 5 1  ; var0(var1, var2, var3, var4)
       6 [-]: GETIMPORT R0 1; var0 = 0xAE91E43B
       7 [-]: LOADK R2 K4  ; var2 = "ReticleSniper"
       8 [-]: LOADN R3 10  ; var3 = 10
       9 [-]: LOADN R4 0   ; var4 = 0
      10 [-]: NAMECALL R0 R0 K5; var1 = var0; var0 = var0[0x67BC869F]
      11 [-]: CALL R0 5 1  ; var0(var1, var2, var3, var4)
      12 [-]: GETIMPORT R0 1; var0 = 0xAE91E43B
      13 [-]: LOADK R2 K4  ; var2 = "ReticleSniper"
      14 [-]: LOADN R3 4   ; var3 = 4
      15 [-]: LOADN R4 -5000; var4 = -5000
      16 [-]: NAMECALL R0 R0 K5; var1 = var0; var0 = var0[0x67BC869F]
      17 [-]: CALL R0 5 1  ; var0(var1, var2, var3, var4)
      18 [-]: GETIMPORT R0 1; var0 = 0xAE91E43B
      19 [-]: LOADK R2 K4  ; var2 = "ReticleSniper"
      20 [-]: GETIMPORT R3 7; var3 = 0xCC5A0280
      21 [-]: NAMECALL R0 R0 K8; var1 = var0; var0 = var0[0xD5181643]
      22 [-]: CALL R0 4 1  ; var0(var1, var2, var3)
      23 [-]: GETIMPORT R0 1; var0 = 0xAE91E43B
      24 [-]: LOADK R2 K9  ; var2 = "ReticleSniper.Scanning.Dot"
      25 [-]: LOADN R3 9   ; var3 = 9
      26 [-]: LOADK R4 K10 ; var4 = 16753408
      27 [-]: NAMECALL R0 R0 K5; var1 = var0; var0 = var0[0x67BC869F]
      28 [-]: CALL R0 5 1  ; var0(var1, var2, var3, var4)
      29 [-]: GETIMPORT R0 1; var0 = 0xAE91E43B
      30 [-]: LOADK R2 K4  ; var2 = "ReticleSniper"
      31 [-]: LOADN R3 0   ; var3 = 0
      32 [-]: NAMECALL R0 R0 K11; var1 = var0; var0 = var0[0x91A24E4B]
      33 [-]: CALL R0 4 2  ; var0 = var0(var1, var2, var3)
      34 [-]: SETUPVAL R0 0; upvalues[0] = var0
      35 [-]: GETIMPORT R0 1; var0 = 0xAE91E43B
      36 [-]: LOADK R2 K12 ; var2 = "/Lotus/Language/Menu/HUD_ScansTaken"
      37 [-]: LOADB R3 0   ; var3 = false
      38 [-]: NAMECALL R0 R0 K13; var1 = var0; var0 = var0[0x42B04007]
      39 [-]: CALL R0 4 2  ; var0 = var0(var1, var2, var3)
      40 [-]: GETIMPORT R1 16; var1 = 0x7F5022CF[0x3F3E4D12]
      41 [-]: MOVE R2 R0   ; var2 = var0
      42 [-]: CALL R1 2 2  ; var1 = var1(var2)
      43 [-]: MOVE R0 R1   ; var0 = var1
      44 [-]: GETIMPORT R1 18; var1 = 0x7F5022CF[0x66EDF04F]
      45 [-]: MOVE R2 R0   ; var2 = var0
      46 [-]: LOADK R3 K19 ; var3 = " "
      47 [-]: LOADK R4 K20 ; var4 = "\n\r"
      48 [-]: LOADN R5 1   ; var5 = 1
      49 [-]: CALL R1 5 2  ; var1 = var1(var2, var3, var4, var5)
      50 [-]: MOVE R0 R1   ; var0 = var1
      51 [-]: GETIMPORT R1 1; var1 = 0xAE91E43B
      52 [-]: LOADK R3 K21 ; var3 = "ReticleSniper.ScansTaken.Label"
      53 [-]: LOADN R4 29  ; var4 = 29
      54 [-]: MOVE R5 R0   ; var5 = var0
      55 [-]: NAMECALL R1 R1 K22; var2 = var1; var1 = var1[0x5F56EEAB]
      56 [-]: CALL R1 5 1  ; var1(var2, var3, var4, var5)
      57 [-]: GETIMPORT R1 1; var1 = 0xAE91E43B
      58 [-]: LOADK R3 K23 ; var3 = "/Lotus/Language/Menu/HUD_ScansRemaining"
      59 [-]: LOADB R4 0   ; var4 = false
      60 [-]: NAMECALL R1 R1 K13; var2 = var1; var1 = var1[0x42B04007]
      61 [-]: CALL R1 4 2  ; var1 = var1(var2, var3, var4)
      62 [-]: GETIMPORT R2 16; var2 = 0x7F5022CF[0x3F3E4D12]
      63 [-]: MOVE R3 R1   ; var3 = var1
      64 [-]: CALL R2 2 2  ; var2 = var2(var3)
      65 [-]: MOVE R1 R2   ; var1 = var2
      66 [-]: GETIMPORT R2 18; var2 = 0x7F5022CF[0x66EDF04F]
      67 [-]: MOVE R3 R1   ; var3 = var1
      68 [-]: LOADK R4 K19 ; var4 = " "
      69 [-]: LOADK R5 K20 ; var5 = "\n\r"
      70 [-]: LOADN R6 1   ; var6 = 1
      71 [-]: CALL R2 5 2  ; var2 = var2(var3, var4, var5, var6)
      72 [-]: MOVE R1 R2   ; var1 = var2
      73 [-]: GETIMPORT R2 1; var2 = 0xAE91E43B
      74 [-]: LOADK R4 K24 ; var4 = "ReticleSniper.RemainingCharges.Label"
      75 [-]: LOADN R5 29  ; var5 = 29
      76 [-]: MOVE R6 R1   ; var6 = var1
      77 [-]: NAMECALL R2 R2 K22; var3 = var2; var2 = var2[0x5F56EEAB]
      78 [-]: CALL R2 5 1  ; var2(var3, var4, var5, var6)
      79 [-]: GETIMPORT R2 1; var2 = 0xAE91E43B
      80 [-]: LOADK R4 K25 ; var4 = "ReticleSniper.RemainingCharges.Count"
      81 [-]: LOADN R5 75  ; var5 = 75
      82 [-]: LOADB R6 1   ; var6 = true
      83 [-]: NAMECALL R2 R2 K3; var3 = var2; var2 = var2[0xAADE900E]
      84 [-]: CALL R2 5 1  ; var2(var3, var4, var5, var6)
      85 [-]: GETIMPORT R2 1; var2 = 0xAE91E43B
      86 [-]: LOADK R4 K26 ; var4 = "ReticleSniper.Scanning.ScanName"
      87 [-]: LOADN R5 38  ; var5 = 38
      88 [-]: LOADK R6 K27 ; var6 = "center"
      89 [-]: NAMECALL R2 R2 K22; var3 = var2; var2 = var2[0x5F56EEAB]
      90 [-]: CALL R2 5 1  ; var2(var3, var4, var5, var6)
      91 [-]: GETIMPORT R2 1; var2 = 0xAE91E43B
      92 [-]: LOADK R4 K26 ; var4 = "ReticleSniper.Scanning.ScanName"
      93 [-]: LOADN R5 29  ; var5 = 29
      94 [-]: LOADK R6 K28 ; var6 = ""
      95 [-]: NAMECALL R2 R2 K22; var3 = var2; var2 = var2[0x5F56EEAB]
      96 [-]: CALL R2 5 1  ; var2(var3, var4, var5, var6)
      97 [-]: GETIMPORT R2 1; var2 = 0xAE91E43B
      98 [-]: LOADK R4 K29 ; var4 = "ReticleSniper.ScansTaken.TargetDetails"
      99 [-]: LOADN R5 29  ; var5 = 29
     100 [-]: LOADK R6 K28 ; var6 = ""
     101 [-]: NAMECALL R2 R2 K22; var3 = var2; var2 = var2[0x5F56EEAB]
     102 [-]: CALL R2 5 1  ; var2(var3, var4, var5, var6)
     103 [-]: GETIMPORT R2 1; var2 = 0xAE91E43B
     104 [-]: LOADK R4 K29 ; var4 = "ReticleSniper.ScansTaken.TargetDetails"
     105 [-]: LOADN R5 75  ; var5 = 75
     106 [-]: LOADB R6 1   ; var6 = true
     107 [-]: NAMECALL R2 R2 K3; var3 = var2; var2 = var2[0xAADE900E]
     108 [-]: CALL R2 5 1  ; var2(var3, var4, var5, var6)
     109 [-]: GETIMPORT R2 1; var2 = 0xAE91E43B
     110 [-]: LOADK R4 K30 ; var4 = "StandingGain"
     111 [-]: LOADN R5 10  ; var5 = 10
     112 [-]: LOADN R6 0   ; var6 = 0
     113 [-]: NAMECALL R2 R2 K5; var3 = var2; var2 = var2[0x67BC869F]
     114 [-]: CALL R2 5 1  ; var2(var3, var4, var5, var6)
     115 [-]: GETIMPORT R2 1; var2 = 0xAE91E43B
     116 [-]: LOADK R4 K31 ; var4 = "StandingGain.Label"
     117 [-]: LOADN R5 75  ; var5 = 75
     118 [-]: LOADB R6 1   ; var6 = true
     119 [-]: NAMECALL R2 R2 K3; var3 = var2; var2 = var2[0xAADE900E]
     120 [-]: CALL R2 5 1  ; var2(var3, var4, var5, var6)
     121 [-]: GETUPVAL R2 1; var2 = upvalues[1]
     122 [-]: CALL R2 1 1  ; var2()
     123 [-]: GETUPVAL R2 2; var2 = upvalues[2]
     124 [-]: CALL R2 1 1  ; var2()
     125 [-]: LOADN R4 1   ; var4 = 1
     126 [-]: GETUPVAL R5 3; var5 = upvalues[3]
     127 [-]: LENGTH R2 R5 ; var2 = #var5
     128 [-]: LOADN R3 1   ; var3 = 1
     129 [-]: FORNPREP R2 L1; nforprep start - [escape at L1] -- var2 = iterator
L 0: 130 [-]: GETUPVAL R5 3; var5 = upvalues[3]
     131 [-]: GETIMPORT R6 1; var6 = 0xAE91E43B
     132 [-]: GETUPVAL R9 3; var9 = upvalues[3]
     133 [-]: GETTABLE R8 R9 R4; var8 = var9[var4]
     134 [-]: LOADB R9 1   ; var9 = true
     135 [-]: NAMECALL R6 R6 K13; var7 = var6; var6 = var6[0x42B04007]
     136 [-]: CALL R6 4 2  ; var6 = var6(var7, var8, var9)
     137 [-]: SETTABLE R6 R5 R4; var6[var5] = var4
     138 [-]: FORNLOOP R2 L0; nforloop end - iterate + goto L0
L 1: 139 [-]: LOADN R4 1   ; var4 = 1
     140 [-]: GETUPVAL R5 4; var5 = upvalues[4]
     141 [-]: LENGTH R2 R5 ; var2 = #var5
     142 [-]: LOADN R3 1   ; var3 = 1
     143 [-]: FORNPREP R2 L3; nforprep start - [escape at L3] -- var2 = iterator
L 2: 144 [-]: GETUPVAL R5 4; var5 = upvalues[4]
     145 [-]: GETIMPORT R6 1; var6 = 0xAE91E43B
     146 [-]: GETUPVAL R9 4; var9 = upvalues[4]
     147 [-]: GETTABLE R8 R9 R4; var8 = var9[var4]
     148 [-]: LOADB R9 0   ; var9 = false
     149 [-]: NAMECALL R6 R6 K13; var7 = var6; var6 = var6[0x42B04007]
     150 [-]: CALL R6 4 2  ; var6 = var6(var7, var8, var9)
     151 [-]: SETTABLE R6 R5 R4; var6[var5] = var4
     152 [-]: FORNLOOP R2 L2; nforloop end - iterate + goto L2
L 3: 153 [-]: LOADB R2 1   ; var2 = true
     154 [-]: SETUPVAL R2 5; upvalues[2] = var5
     155 [-]: RETURN R0 0  ; 


; Name:            
; Defined at line: 260
; #Upvalues:       1
; #Parameters:     1
; Is_vararg:       0
; Max Stack Size:  4

       0 [-]: SETUPVAL R0 0; upvalues[0] = var0
       1 [-]: FASTCALL1 62 R0 L0; 
       2 [-]: MOVE R3 R0   ; var3 = var0
       3 [-]: GETIMPORT R2 1; var2 = 0x7B998233
       4 [-]: CALL R2 2 2  ; var2 = var2(var3)
L 0:   5 [-]: NOT R1 R2    ; var1 = not var2
       6 [-]: RETURN R1 1  ; 


; Name:            
; Defined at line: 265
; #Upvalues:       4
; #Parameters:     2
; Is_vararg:       0
; Max Stack Size:  13

       0 [-]: JUMPXEQKS R0 K0 L0; 
       1 [-]: LOADB R0 0 +1; var0 = false
L 0:   2 [-]: LOADB R0 1   ; var0 = true
L 1:   3 [-]: GETUPVAL R3 0; var3 = upvalues[0]
       4 [-]: GETTABLEKS R2 R3 K1; var2 = var3[0x06D055F9]
       5 [-]: MOVE R3 R0   ; var3 = var0
       6 [-]: LOADN R4 100 ; var4 = 100
       7 [-]: LOADN R5 0   ; var5 = 0
       8 [-]: CALL R2 4 2  ; var2 = var2(var3, var4, var5)
       9 [-]: GETUPVAL R4 0; var4 = upvalues[0]
      10 [-]: GETTABLEKS R3 R4 K1; var3 = var4[0x06D055F9]
      11 [-]: MOVE R4 R0   ; var4 = var0
      12 [-]: LOADN R5 0   ; var5 = 0
      13 [-]: LOADN R6 -5000; var6 = -5000
      14 [-]: CALL R3 4 2  ; var3 = var3(var4, var5, var6)
      15 [-]: GETIMPORT R4 3; var4 = 0x25312C9B
      16 [-]: GETIMPORT R5 5; var5 = 0xAE91E43B
      17 [-]: LOADK R6 K6  ; var6 = "ReticleSniper"
      18 [-]: LOADN R7 2   ; var7 = 2
      19 [-]: NEWTABLE R8 0 2; var8 = {}
      20 [-]: LOADN R9 10  ; var9 = 10
      21 [-]: LOADN R10 4  ; var10 = 4
      22 [-]: SETLIST R8 R9 2 [1]; var8[1] = var9; var8[2] = var10; var8[3] = var11; 
      23 [-]: NEWTABLE R9 0 2; var9 = {}
      24 [-]: MOVE R10 R2  ; var10 = var2
      25 [-]: MOVE R11 R3  ; var11 = var3
      26 [-]: SETLIST R9 R10 2 [1]; var9[1] = var10; var9[2] = var11; var9[3] = var12; 
      27 [-]: LOADK R10 K7 ; var10 = 0.25
      28 [-]: LOADN R11 0  ; var11 = 0
      29 [-]: NEWCLOSURE R12 P0; 
      30 [-]: CAPTURE VAL R1; 
      31 [-]: CALL R4 9 1  ; var4(var5, var6, var7, var8, var9, var10, var11, var12)
      32 [-]: GETIMPORT R4 9; var4 = 0x89326C93
      33 [-]: NAMECALL R4 R4 K10; var5 = var4; var4 = var4[0x78298275]
      34 [-]: CALL R4 2 2  ; var4 = var4(var5)
      35 [-]: GETIMPORT R5 12; var5 = 0x0F3E8EE9
      36 [-]: LOADN R6 0   ; var6 = 0
      37 [-]: JUMPIFNOTLT R6 R5 L5; goto L5 if var6 >= var50609739
      38 [-]: FASTCALL1 62 R4 L2; 
      39 [-]: MOVE R6 R4   ; var6 = var4
      40 [-]: GETIMPORT R5 14; var5 = 0x7B998233
      41 [-]: CALL R5 2 2  ; var5 = var5(var6)
L 2:  42 [-]: JUMPIF R5 L5 ; goto L5 if var5
      43 [-]: NAMECALL R5 R4 K15; var6 = var4; var5 = var4[0x0B4BCFB6]
      44 [-]: CALL R5 2 2  ; var5 = var5(var6)
      45 [-]: FASTCALL1 62 R5 L3; 
      46 [-]: MOVE R7 R5   ; var7 = var5
      47 [-]: GETIMPORT R6 14; var6 = 0x7B998233
      48 [-]: CALL R6 2 2  ; var6 = var6(var7)
L 3:  49 [-]: JUMPIF R6 L5 ; goto L5 if var6
      50 [-]: JUMPIFNOT R0 L4; goto L4 if not var0
      51 [-]: GETIMPORT R8 12; var8 = 0x0F3E8EE9
      52 [-]: GETIMPORT R9 17; var9 = 0x844D6F76
      53 [-]: GETIMPORT R10 19; var10 = 0x854D7109
      54 [-]: GETIMPORT R11 21; var11 = 0xFF7E7BF8
      55 [-]: GETUPVAL R12 1; var12 = upvalues[1]
      56 [-]: NAMECALL R6 R5 K22; var7 = var5; var6 = var5[0xD8BCB169]
      57 [-]: CALL R6 7 1  ; var6(var7, var8, var9, var10, var11, var12)
      58 [-]: JUMP L5      ; goto L5
L 4:  59 [-]: GETUPVAL R8 1; var8 = upvalues[1]
      60 [-]: NAMECALL R6 R5 K23; var7 = var5; var6 = var5[0xD343428D]
      61 [-]: CALL R6 3 1  ; var6(var7, var8)
L 5:  62 [-]: GETUPVAL R6 2; var6 = upvalues[2]
      63 [-]: GETTABLEKS R5 R6 K24; var5 = var6[0x29B96AD5]
      64 [-]: MOVE R6 R4   ; var6 = var4
      65 [-]: GETUPVAL R8 0; var8 = upvalues[0]
      66 [-]: GETTABLEKS R7 R8 K1; var7 = var8[0x06D055F9]
      67 [-]: MOVE R8 R0   ; var8 = var0
      68 [-]: LOADK R9 K25 ; var9 = 0.90000000000000002
      69 [-]: LOADN R10 0  ; var10 = 0
      70 [-]: CALL R7 4 0  ; var7, ... = var7(var8, var9, var10)
      71 [-]: CALL R5 0 1  ; var5(var6, ...)
      72 [-]: SETUPVAL R0 3; upvalues[0] = var3
      73 [-]: RETURN R0 0  ; 


; Name:            
; Defined at line: 292
; #Upvalues:       1
; #Parameters:     1
; Is_vararg:       0
; Max Stack Size:  3

       0 [-]: GETUPVAL R1 0; var1 = upvalues[0]
       1 [-]: MOVE R2 R0   ; var2 = var0
       2 [-]: CALL R1 2 1  ; var1(var2)
       3 [-]: RETURN R0 0  ; 


; Name:            
; Defined at line: 296
; #Upvalues:       1
; #Parameters:     0
; Is_vararg:       0
; Max Stack Size:  1

       0 [-]: GETUPVAL R0 0; var0 = upvalues[0]
       1 [-]: RETURN R0 1  ; 


; Name:            
; Defined at line: 300
; #Upvalues:       1
; #Parameters:     2
; Is_vararg:       0
; Max Stack Size:  7

       0 [-]: JUMPXEQKS R0 K0 L0; 
       1 [-]: LOADB R0 0 +1; var0 = false
L 0:   2 [-]: LOADB R0 1   ; var0 = true
L 1:   3 [-]: JUMPIFNOT R0 L2; goto L2 if not var0
       4 [-]: GETIMPORT R2 2; var2 = 0xAE91E43B
       5 [-]: LOADK R4 K3  ; var4 = "_root"
       6 [-]: LOADN R5 11  ; var5 = 11
       7 [-]: LOADB R6 1   ; var6 = true
       8 [-]: NAMECALL R2 R2 K4; var3 = var2; var2 = var2[0xAADE900E]
       9 [-]: CALL R2 5 1  ; var2(var3, var4, var5, var6)
L 2:  10 [-]: GETUPVAL R2 0; var2 = upvalues[0]
      11 [-]: MOVE R3 R1   ; var3 = var1
      12 [-]: MOVE R4 R0   ; var4 = var0
      13 [-]: CALL R2 3 1  ; var2(var3, var4)
      14 [-]: RETURN R0 0  ; 


; Name:            
; Defined at line: 308
; #Upvalues:       0
; #Parameters:     0
; Is_vararg:       0
; Max Stack Size:  0

       0 [-]: RETURN R0 0  ; 


; Name:            
; Defined at line: 311
; #Upvalues:       1
; #Parameters:     1
; Is_vararg:       0
; Max Stack Size:  5

       0 [-]: GETUPVAL R1 0; var1 = upvalues[0]
       1 [-]: GETIMPORT R3 1; var3 = 0x03F57322
       2 [-]: MOVE R4 R0   ; var4 = var0
       3 [-]: CALL R3 2 0  ; var3, ... = var3(var4)
       4 [-]: NAMECALL R1 R1 K2; var2 = var1; var1 = var1[0x188E2BEE]
       5 [-]: CALL R1 0 1  ; var1(var2, ...)
       6 [-]: RETURN R0 0  ; 


; Name:            
; Defined at line: 315
; #Upvalues:       2
; #Parameters:     0
; Is_vararg:       0
; Max Stack Size:  5

       0 [-]: GETUPVAL R0 0; var0 = upvalues[0]
       1 [-]: JUMPXEQKNIL R0 L0; 
       2 [-]: GETUPVAL R0 1; var0 = upvalues[1]
       3 [-]: GETUPVAL R2 0; var2 = upvalues[0]
       4 [-]: LOADK R3 K0  ; var3 = ".Notification"
       5 [-]: CONCAT R1 R2 R3; var1 = var2 .. var3
       6 [-]: GETIMPORT R2 2; var2 = 0x124946BD
       7 [-]: LOADN R3 -145; var3 = -145
       8 [-]: LOADN R4 3   ; var4 = 3
       9 [-]: CALL R0 5 1  ; var0(var1, var2, var3, var4)
L 0:  10 [-]: RETURN R0 0  ; 


; Name:            
; Defined at line: 319
; #Upvalues:       0
; #Parameters:     1
; Is_vararg:       0
; Max Stack Size:  6

       0 [-]: GETIMPORT R1 1; var1 = 0xAE91E43B
       1 [-]: LOADK R3 K2  ; var3 = "FloatingMarker"
       2 [-]: LOADN R4 11  ; var4 = 11
       3 [-]: JUMPXEQKS R0 K3 L0; 
       4 [-]: LOADB R5 0 +1; var5 = false
L 0:   5 [-]: LOADB R5 1   ; var5 = true
L 1:   6 [-]: NAMECALL R1 R1 K4; var2 = var1; var1 = var1[0xAADE900E]
       7 [-]: CALL R1 5 1  ; var1(var2, var3, var4, var5)
       8 [-]: RETURN R0 0  ; 


; Name:            
; Defined at line: 323
; #Upvalues:       1
; #Parameters:     0
; Is_vararg:       0
; Max Stack Size:  6

       0 [-]: GETUPVAL R0 0; var0 = upvalues[0]
       1 [-]: JUMPIF R0 L1 ; goto L1 if var0
       2 [-]: GETIMPORT R0 1; var0 = 0x89326C93
       3 [-]: NAMECALL R0 R0 K2; var1 = var0; var0 = var0[0x78298275]
       4 [-]: CALL R0 2 2  ; var0 = var0(var1)
       5 [-]: FASTCALL1 62 R0 L0; 
       6 [-]: MOVE R2 R0   ; var2 = var0
       7 [-]: GETIMPORT R1 4; var1 = 0x7B998233
       8 [-]: CALL R1 2 2  ; var1 = var1(var2)
L 0:   9 [-]: JUMPIF R1 L1 ; goto L1 if var1
      10 [-]: NAMECALL R1 R0 K5; var2 = var0; var1 = var0[0x5E651723]
      11 [-]: CALL R1 2 2  ; var1 = var1(var2)
      12 [-]: NAMECALL R1 R1 K6; var2 = var1; var1 = var1[0x0803EEE1]
      13 [-]: CALL R1 2 2  ; var1 = var1(var2)
      14 [-]: SETUPVAL R1 0; upvalues[1] = var0
L 1:  15 [-]: GETUPVAL R0 0; var0 = upvalues[0]
      16 [-]: NAMECALL R0 R0 K7; var1 = var0; var0 = var0[0x3FF8C1FB]
      17 [-]: CALL R0 2 2  ; var0 = var0(var1)
      18 [-]: GETIMPORT R1 9; var1 = 0xAE91E43B
      19 [-]: LOADK R3 K10 ; var3 = "FloatingMarker"
      20 [-]: LOADN R4 0   ; var4 = 0
      21 [-]: GETTABLEKS R5 R0 K11; var5 = var0["x"]
      22 [-]: NAMECALL R1 R1 K12; var2 = var1; var1 = var1[0x67BC869F]
      23 [-]: CALL R1 5 1  ; var1(var2, var3, var4, var5)
      24 [-]: GETIMPORT R1 9; var1 = 0xAE91E43B
      25 [-]: LOADK R3 K10 ; var3 = "FloatingMarker"
      26 [-]: LOADN R4 1   ; var4 = 1
      27 [-]: GETTABLEKS R5 R0 K13; var5 = var0["y"]
      28 [-]: NAMECALL R1 R1 K12; var2 = var1; var1 = var1[0x67BC869F]
      29 [-]: CALL R1 5 1  ; var1(var2, var3, var4, var5)
      30 [-]: RETURN R0 0  ; 


; Name:            
; Defined at line: 335
; #Upvalues:       1
; #Parameters:     1
; Is_vararg:       0
; Max Stack Size:  9

       0 [-]: GETUPVAL R2 0; var2 = upvalues[0]
       1 [-]: GETTABLEKS R1 R2 K0; var1 = var2[0xF6F4F1CA]
       2 [-]: CALL R1 1 2  ; var1 = var1()
       3 [-]: LOADN R4 1   ; var4 = 1
       4 [-]: LENGTH R2 R1 ; var2 = #var1
       5 [-]: LOADN R3 1   ; var3 = 1
       6 [-]: FORNPREP R2 L2; nforprep start - [escape at L2] -- var2 = iterator
L 0:   7 [-]: GETTABLE R5 R1 R4; var5 = var1[var4]
       8 [-]: NAMECALL R5 R5 K1; var6 = var5; var5 = var5[0x6D604BA7]
       9 [-]: CALL R5 2 2  ; var5 = var5(var6)
      10 [-]: JUMPIFNOTEQ R5 R0 L1; goto L1 if var5 ~= var197966
      11 [-]: GETIMPORT R5 3; var5 = 0xBE190284
      12 [-]: SUBK R7 R4 K4; var7 = var4 - 1
      13 [-]: LOADN R8 4   ; var8 = 4
      14 [-]: NAMECALL R5 R5 K5; var6 = var5; var5 = var5[0x11281BDD]
      15 [-]: CALL R5 4 1  ; var5(var6, var7, var8)
      16 [-]: GETIMPORT R5 3; var5 = 0xBE190284
      17 [-]: NAMECALL R5 R5 K6; var6 = var5; var5 = var5[0x35906BE4]
      18 [-]: CALL R5 2 2  ; var5 = var5(var6)
      19 [-]: GETIMPORT R7 8; var7 = 0x2AEE328F
      20 [-]: GETTABLE R8 R1 R4; var8 = var1[var4]
      21 [-]: NAMECALL R5 R5 K9; var6 = var5; var5 = var5[0x47901F07]
      22 [-]: CALL R5 4 2  ; var5 = var5(var6, var7, var8)
      23 [-]: RETURN R0 0  ; 
L 1:  24 [-]: FORNLOOP R2 L0; nforloop end - iterate + goto L0
L 2:  25 [-]: RETURN R0 0  ; 


; Name:            
; Defined at line: 346
; #Upvalues:       1
; #Parameters:     0
; Is_vararg:       0
; Max Stack Size:  7

       0 [-]: GETUPVAL R1 0; var1 = upvalues[0]
       1 [-]: GETTABLEKS R0 R1 K0; var0 = var1[0xB73D420F]
       2 [-]: CALL R0 1 2  ; var0 = var0()
       3 [-]: GETUPVAL R2 0; var2 = upvalues[0]
       4 [-]: GETTABLEKS R1 R2 K1; var1 = var2["UI_MODE_IN_SPACE_SHIP"]
       5 [-]: JUMPIFEQ R0 R1 L5; goto L5 if var0 == var263
       6 [-]: GETUPVAL R1 0; var1 = upvalues[0]
       7 [-]: GETTABLEKS R0 R1 K0; var0 = var1[0xB73D420F]
       8 [-]: CALL R0 1 2  ; var0 = var0()
       9 [-]: GETUPVAL R2 0; var2 = upvalues[0]
      10 [-]: GETTABLEKS R1 R2 K2; var1 = var2["UI_MODE_IN_DOJO"]
      11 [-]: JUMPIFEQ R0 R1 L5; goto L5 if var0 == var262222
      12 [-]: GETIMPORT R0 4; var0 = 0xBE190284
      13 [-]: NAMECALL R0 R0 K5; var1 = var0; var0 = var0[0x35906BE4]
      14 [-]: CALL R0 2 2  ; var0 = var0(var1)
      15 [-]: FASTCALL1 62 R0 L0; 
      16 [-]: MOVE R2 R0   ; var2 = var0
      17 [-]: GETIMPORT R1 7; var1 = 0x7B998233
      18 [-]: CALL R1 2 2  ; var1 = var1(var2)
L 0:  19 [-]: JUMPIF R1 L5 ; goto L5 if var1
      20 [-]: NAMECALL R1 R0 K8; var2 = var0; var1 = var0[0xFA9E477F]
      21 [-]: CALL R1 2 2  ; var1 = var1(var2)
      22 [-]: FASTCALL1 62 R1 L1; 
      23 [-]: MOVE R3 R1   ; var3 = var1
      24 [-]: GETIMPORT R2 7; var2 = 0x7B998233
      25 [-]: CALL R2 2 2  ; var2 = var2(var3)
L 1:  26 [-]: JUMPIF R2 L5 ; goto L5 if var2
      27 [-]: NAMECALL R2 R1 K9; var3 = var1; var2 = var1[0xA39BB54B]
      28 [-]: CALL R2 2 2  ; var2 = var2(var3)
      29 [-]: GETTABLEKS R4 R2 K10; var4 = var2["entity"]
      30 [-]: FASTCALL1 62 R4 L2; 
      31 [-]: GETIMPORT R3 7; var3 = 0x7B998233
      32 [-]: CALL R3 2 2  ; var3 = var3(var4)
L 2:  33 [-]: JUMPIFNOT R3 L5; goto L5 if not var3
      34 [-]: GETIMPORT R3 12; var3 = 0x89326C93
      35 [-]: NAMECALL R5 R0 K13; var6 = var0; var5 = var0[0xD1586535]
      36 [-]: CALL R5 2 2  ; var5 = var5(var6)
      37 [-]: LOADK R6 K14 ; var6 = 3.4028234663852886e+38
      38 [-]: NAMECALL R3 R3 K15; var4 = var3; var3 = var3[0x50A314F9]
      39 [-]: CALL R3 4 2  ; var3 = var3(var4, var5, var6)
      40 [-]: FASTCALL1 62 R3 L3; 
      41 [-]: MOVE R5 R3   ; var5 = var3
      42 [-]: GETIMPORT R4 7; var4 = 0x7B998233
      43 [-]: CALL R4 2 2  ; var4 = var4(var5)
L 3:  44 [-]: JUMPIF R4 L4 ; goto L4 if var4
      45 [-]: MOVE R6 R3   ; var6 = var3
      46 [-]: NAMECALL R4 R1 K16; var5 = var1; var4 = var1[0x6AD018DE]
      47 [-]: CALL R4 3 1  ; var4(var5, var6)
L 4:  48 [-]: NAMECALL R4 R1 K17; var5 = var1; var4 = var1[0x9E21E394]
      49 [-]: CALL R4 2 1  ; var4(var5)
      50 [-]: NAMECALL R4 R1 K18; var5 = var1; var4 = var1[0xAC41835F]
      51 [-]: CALL R4 2 1  ; var4(var5)
L 5:  52 [-]: RETURN R0 0  ; 


; Name:            
; Defined at line: 367
; #Upvalues:       0
; #Parameters:     0
; Is_vararg:       0
; Max Stack Size:  9

       0 [-]: GETIMPORT R0 1; var0 = 0x25312C9B
       1 [-]: GETIMPORT R1 3; var1 = 0xAE91E43B
       2 [-]: LOADK R2 K4  ; var2 = "_root"
       3 [-]: LOADN R3 8   ; var3 = 8
       4 [-]: NEWTABLE R4 0 2; var4 = {}
       5 [-]: LOADN R5 12  ; var5 = 12
       6 [-]: LOADN R6 13  ; var6 = 13
       7 [-]: SETLIST R4 R5 2 [1]; var4[1] = var5; var4[2] = var6; var4[3] = var7; 
       8 [-]: NEWTABLE R5 0 2; var5 = {}
       9 [-]: LOADN R6 0   ; var6 = 0
      10 [-]: LOADN R7 0   ; var7 = 0
      11 [-]: SETLIST R5 R6 2 [1]; var5[1] = var6; var5[2] = var7; var5[3] = var8; 
      12 [-]: LOADK R6 K5  ; var6 = 0.20000000000000001
      13 [-]: LOADN R7 0   ; var7 = 0
      14 [-]: DUPCLOSURE R8 K6; 
      15 [-]: CALL R0 9 1  ; var0(var1, var2, var3, var4, var5, var6, var7, var8)
      16 [-]: RETURN R0 0  ; 


; Name:            
; Defined at line: 374
; #Upvalues:       1
; #Parameters:     0
; Is_vararg:       0
; Max Stack Size:  5

       0 [-]: GETIMPORT R0 1; var0 = 0x89326C93
       1 [-]: NAMECALL R0 R0 K2; var1 = var0; var0 = var0[0x78298275]
       2 [-]: CALL R0 2 2  ; var0 = var0(var1)
       3 [-]: NAMECALL R1 R0 K3; var2 = var0; var1 = var0[0x0B4BCFB6]
       4 [-]: CALL R1 2 2  ; var1 = var1(var2)
       5 [-]: FASTCALL1 62 R1 L0; 
       6 [-]: MOVE R3 R1   ; var3 = var1
       7 [-]: GETIMPORT R2 5; var2 = 0x7B998233
       8 [-]: CALL R2 2 2  ; var2 = var2(var3)
L 0:   9 [-]: JUMPIF R2 L1 ; goto L1 if var2
      10 [-]: GETUPVAL R4 0; var4 = upvalues[0]
      11 [-]: NAMECALL R2 R1 K6; var3 = var1; var2 = var1[0xD343428D]
      12 [-]: CALL R2 3 1  ; var2(var3, var4)
      13 [-]: GETIMPORT R4 8; var4 = 0xB37905D5
      14 [-]: NAMECALL R2 R1 K9; var3 = var1; var2 = var1[0xBD5007D9]
      15 [-]: CALL R2 3 1  ; var2(var3, var4)
L 1:  16 [-]: RETURN R0 0  ; 


; Name:            
; Defined at line: 383
; #Upvalues:       0
; #Parameters:     2
; Is_vararg:       0
; Max Stack Size:  15

       0 [-]: GETIMPORT R2 1; var2 = 0xAE91E43B
       1 [-]: LOADK R4 K2  ; var4 = "ReticleSniper.Scanning.ScanData"
       2 [-]: LOADN R5 29  ; var5 = 29
       3 [-]: GETIMPORT R6 1; var6 = 0xAE91E43B
       4 [-]: LOADK R8 K3  ; var8 = "/Lotus/Language/Game/UNIT_METER"
       5 [-]: LOADB R9 0   ; var9 = false
       6 [-]: DUPTABLE R10 5; 
       7 [-]: MOVE R12 R0  ; var12 = var0
       8 [-]: LOADK R13 K6 ; var13 = "."
       9 [-]: MOVE R14 R1  ; var14 = var1
      10 [-]: CONCAT R11 R12 R14; var11 = var12 .. var14
      11 [-]: SETTABLEKS R11 R10 K4; var11["COUNT"] = var10
      12 [-]: NAMECALL R6 R6 K7; var7 = var6; var6 = var6[0x42B04007]
      13 [-]: CALL R6 5 0  ; var6, ... = var6(var7, var8, var9, var10)
      14 [-]: NAMECALL R2 R2 K8; var3 = var2; var2 = var2[0x5F56EEAB]
      15 [-]: CALL R2 0 1  ; var2(var3, ...)
      16 [-]: RETURN R0 0  ; 


; Name:            
; Defined at line: 387
; #Upvalues:       1
; #Parameters:     5
; Is_vararg:       0
; Max Stack Size:  13

       0 [-]: MOVE R5 R0   ; var5 = var0
       1 [-]: LOADK R6 K0  ; var6 = "<font color=\"#ffad43\" size=\"14\">"
       2 [-]: GETUPVAL R9 0; var9 = upvalues[0]
       3 [-]: ADDK R10 R3 K1; var10 = var3 + 1
       4 [-]: GETTABLE R7 R9 R10; var7 = var9[var10]
       5 [-]: LOADK R8 K2  ; var8 = "<br></font>"
       6 [-]: CONCAT R0 R5 R8; var0 = var5 .. var8
       7 [-]: MOVE R5 R0   ; var5 = var0
       8 [-]: LOADK R6 K3  ; var6 = "<font color=\"#43a035\">"
       9 [-]: CONCAT R0 R5 R6; var0 = var5 .. var6
      10 [-]: LOADN R7 1   ; var7 = 1
      11 [-]: GETTABLE R8 R1 R4; var8 = var1[var4]
      12 [-]: LENGTH R5 R8 ; var5 = #var8
      13 [-]: LOADN R6 1   ; var6 = 1
      14 [-]: FORNPREP R5 L5; nforprep start - [escape at L5] -- var5 = iterator
L 0:  15 [-]: GETTABLE R11 R1 R4; var11 = var1[var4]
      16 [-]: GETTABLE R10 R11 R7; var10 = var11[var7]
      17 [-]: GETTABLEKS R9 R10 K4; var9 = var10["icon"]
      18 [-]: FASTCALL1 62 R9 L1; 
      19 [-]: GETIMPORT R8 6; var8 = 0x7B998233
      20 [-]: CALL R8 2 2  ; var8 = var8(var9)
L 1:  21 [-]: JUMPIF R8 L4 ; goto L4 if var8
      22 [-]: MOVE R8 R0   ; var8 = var0
      23 [-]: GETTABLE R11 R1 R4; var11 = var1[var4]
      24 [-]: GETTABLE R10 R11 R7; var10 = var11[var7]
      25 [-]: GETTABLEKS R9 R10 K4; var9 = var10["icon"]
      26 [-]: CONCAT R0 R8 R9; var0 = var8 .. var9
      27 [-]: LOADN R10 1  ; var10 = 1
      28 [-]: GETTABLE R12 R1 R4; var12 = var1[var4]
      29 [-]: GETTABLE R11 R12 R7; var11 = var12[var7]
      30 [-]: GETTABLEKS R8 R11 K7; var8 = var11["numSigns"]
      31 [-]: LOADN R9 1   ; var9 = 1
      32 [-]: FORNPREP R8 L3; nforprep start - [escape at L3] -- var8 = iterator
L 2:  33 [-]: MOVE R11 R0  ; var11 = var0
      34 [-]: LOADK R12 K8 ; var12 = " +"
      35 [-]: CONCAT R0 R11 R12; var0 = var11 .. var12
      36 [-]: FORNLOOP R8 L2; nforloop end - iterate + goto L2
L 3:  37 [-]: MOVE R8 R0   ; var8 = var0
      38 [-]: LOADK R9 K9  ; var9 = "   "
      39 [-]: CONCAT R0 R8 R9; var0 = var8 .. var9
L 4:  40 [-]: FORNLOOP R5 L0; nforloop end - iterate + goto L0
L 5:  41 [-]: MOVE R5 R0   ; var5 = var0
      42 [-]: LOADK R6 K2  ; var6 = "<br></font>"
      43 [-]: CONCAT R0 R5 R6; var0 = var5 .. var6
      44 [-]: MOVE R5 R0   ; var5 = var0
      45 [-]: LOADK R6 K10 ; var6 = "<font color=\"#cd2830\">"
      46 [-]: CONCAT R0 R5 R6; var0 = var5 .. var6
      47 [-]: LOADN R7 1   ; var7 = 1
      48 [-]: GETTABLE R8 R2 R4; var8 = var2[var4]
      49 [-]: LENGTH R5 R8 ; var5 = #var8
      50 [-]: LOADN R6 1   ; var6 = 1
      51 [-]: FORNPREP R5 L11; nforprep start - [escape at L11] -- var5 = iterator
L 6:  52 [-]: GETTABLE R11 R2 R4; var11 = var2[var4]
      53 [-]: GETTABLE R10 R11 R7; var10 = var11[var7]
      54 [-]: GETTABLEKS R9 R10 K4; var9 = var10["icon"]
      55 [-]: FASTCALL1 62 R9 L7; 
      56 [-]: GETIMPORT R8 6; var8 = 0x7B998233
      57 [-]: CALL R8 2 2  ; var8 = var8(var9)
L 7:  58 [-]: JUMPIF R8 L10; goto L10 if var8
      59 [-]: MOVE R8 R0   ; var8 = var0
      60 [-]: GETTABLE R11 R2 R4; var11 = var2[var4]
      61 [-]: GETTABLE R10 R11 R7; var10 = var11[var7]
      62 [-]: GETTABLEKS R9 R10 K4; var9 = var10["icon"]
      63 [-]: CONCAT R0 R8 R9; var0 = var8 .. var9
      64 [-]: LOADN R10 1  ; var10 = 1
      65 [-]: GETTABLE R12 R2 R4; var12 = var2[var4]
      66 [-]: GETTABLE R11 R12 R7; var11 = var12[var7]
      67 [-]: GETTABLEKS R8 R11 K7; var8 = var11["numSigns"]
      68 [-]: LOADN R9 1   ; var9 = 1
      69 [-]: FORNPREP R8 L9; nforprep start - [escape at L9] -- var8 = iterator
L 8:  70 [-]: MOVE R11 R0  ; var11 = var0
      71 [-]: LOADK R12 K11; var12 = " -"
      72 [-]: CONCAT R0 R11 R12; var0 = var11 .. var12
      73 [-]: FORNLOOP R8 L8; nforloop end - iterate + goto L8
L 9:  74 [-]: MOVE R8 R0   ; var8 = var0
      75 [-]: LOADK R9 K9  ; var9 = "   "
      76 [-]: CONCAT R0 R8 R9; var0 = var8 .. var9
L10:  77 [-]: FORNLOOP R5 L6; nforloop end - iterate + goto L6
L11:  78 [-]: MOVE R5 R0   ; var5 = var0
      79 [-]: LOADK R6 K2  ; var6 = "<br></font>"
      80 [-]: CONCAT R0 R5 R6; var0 = var5 .. var6
      81 [-]: RETURN R0 1  ; 


; Name:            
; Defined at line: 417
; #Upvalues:       3
; #Parameters:     0
; Is_vararg:       0
; Max Stack Size:  28

       0 [-]: LOADK R0 K0  ; var0 = ""
       1 [-]: GETIMPORT R2 4; var2 = _T["ScanUpdateParms"]["CurrentTarget"]
       2 [-]: GETTABLEKS R1 R2 K5; var1 = var2["mAvatar"]
       3 [-]: FASTCALL1 62 R1 L0; 
       4 [-]: MOVE R3 R1   ; var3 = var1
       5 [-]: GETIMPORT R2 7; var2 = 0x7B998233
       6 [-]: CALL R2 2 2  ; var2 = var2(var3)
L 0:   7 [-]: JUMPIF R2 L26; goto L26 if var2
       8 [-]: NAMECALL R2 R1 K8; var3 = var1; var2 = var1[0x1AC1655C]
       9 [-]: CALL R2 2 2  ; var2 = var2(var3)
      10 [-]: FASTCALL1 62 R2 L1; 
      11 [-]: MOVE R4 R2   ; var4 = var2
      12 [-]: GETIMPORT R3 7; var3 = 0x7B998233
      13 [-]: CALL R3 2 2  ; var3 = var3(var4)
L 1:  14 [-]: JUMPIF R3 L26; goto L26 if var3
      15 [-]: GETIMPORT R5 10; var5 = 0xC401C2CE
      16 [-]: NAMECALL R3 R2 K11; var4 = var2; var3 = var2[0xF2DEAF69]
      17 [-]: CALL R3 3 2  ; var3 = var3(var4, var5)
      18 [-]: JUMPIF R3 L26; goto L26 if var3
      19 [-]: NAMECALL R3 R2 K12; var4 = var2; var3 = var2[0xCC4C5538]
      20 [-]: CALL R3 2 2  ; var3 = var3(var4)
      21 [-]: LENGTH R4 R3 ; var4 = #var3
      22 [-]: GETUPVAL R6 0; var6 = upvalues[0]
      23 [-]: GETTABLEKS R5 R6 K13; var5 = var6["Resistances"]
      24 [-]: GETUPVAL R8 0; var8 = upvalues[0]
      25 [-]: GETTABLEKS R7 R8 K13; var7 = var8["Resistances"]
      26 [-]: LENGTH R6 R7 ; var6 = #var7
      27 [-]: LOADB R7 1   ; var7 = true
      28 [-]: JUMPXEQKN R6 K14 L4; 
      29 [-]: GETUPVAL R9 0; var9 = upvalues[0]
      30 [-]: GETTABLEKS R8 R9 K15; var8 = var9["Avatar"]
      31 [-]: FASTCALL1 62 R8 L2; 
      32 [-]: GETIMPORT R7 7; var7 = 0x7B998233
      33 [-]: CALL R7 2 2  ; var7 = var7(var8)
L 2:  34 [-]: JUMPIF R7 L4 ; goto L4 if var7
      35 [-]: GETUPVAL R9 0; var9 = upvalues[0]
      36 [-]: GETTABLEKS R8 R9 K15; var8 = var9["Avatar"]
      37 [-]: JUMPIFNOTEQ R8 R1 L3; goto L3 if var8 ~= var16779035
      38 [-]: LOADB R7 0 +1; var7 = false
L 3:  39 [-]: LOADB R7 1   ; var7 = true
L 4:  40 [-]: JUMPIF R7 L8 ; goto L8 if var7
      41 [-]: LOADN R10 1  ; var10 = 1
      42 [-]: MOVE R8 R6   ; var8 = var6
      43 [-]: LOADN R9 1   ; var9 = 1
      44 [-]: FORNPREP R8 L8; nforprep start - [escape at L8] -- var8 = iterator
L 5:  45 [-]: JUMPIFLT R4 R10 L6; goto L6 if var4 < var168102711
      46 [-]: GETTABLE R11 R5 R10; var11 = var5[var10]
      47 [-]: GETTABLE R12 R3 R10; var12 = var3[var10]
      48 [-]: JUMPIFEQ R11 R12 L7; goto L7 if var11 == var67355
L 6:  49 [-]: LOADB R7 1   ; var7 = true
      50 [-]: JUMP L8      ; goto L8
L 7:  51 [-]: FORNLOOP R8 L5; nforloop end - iterate + goto L5
L 8:  52 [-]: JUMPIF R7 L9 ; goto L9 if var7
      53 [-]: RETURN R0 1  ; 
L 9:  54 [-]: GETUPVAL R8 0; var8 = upvalues[0]
      55 [-]: SETTABLEKS R3 R8 K13; var3["Resistances"] = var8
      56 [-]: GETUPVAL R8 0; var8 = upvalues[0]
      57 [-]: SETTABLEKS R1 R8 K15; var1["Avatar"] = var8
      58 [-]: LOADK R0 K16 ; var0 = "<p>"
      59 [-]: NEWTABLE R8 0 4; var8 = {}
      60 [-]: NEWTABLE R9 0 0; var9 = {}
      61 [-]: NEWTABLE R10 0 0; var10 = {}
      62 [-]: NEWTABLE R11 0 0; var11 = {}
      63 [-]: NEWTABLE R12 0 0; var12 = {}
      64 [-]: SETLIST R8 R9 4 [1]; var8[1] = var9; var8[2] = var10; var8[3] = var11; var8[4] = var12; var8[5] = var13; 
      65 [-]: NEWTABLE R9 0 4; var9 = {}
      66 [-]: NEWTABLE R10 0 0; var10 = {}
      67 [-]: NEWTABLE R11 0 0; var11 = {}
      68 [-]: NEWTABLE R12 0 0; var12 = {}
      69 [-]: NEWTABLE R13 0 0; var13 = {}
      70 [-]: SETLIST R9 R10 4 [1]; var9[1] = var10; var9[2] = var11; var9[3] = var12; var9[4] = var13; var9[5] = var14; 
      71 [-]: LOADN R10 0  ; var10 = 0
      72 [-]: LOADN R11 1  ; var11 = 1
      73 [-]: GETUPVAL R13 1; var13 = upvalues[1]
      74 [-]: LENGTH R12 R13; var12 = #var13
      75 [-]: LOADN R15 1  ; var15 = 1
      76 [-]: MOVE R13 R4  ; var13 = var4
      77 [-]: LOADN R14 1  ; var14 = 1
      78 [-]: FORNPREP R13 L21; nforprep start - [escape at L21] -- var13 = iterator
L10:  79 [-]: MOVE R10 R15 ; var10 = var15
      80 [-]: LOADN R16 15 ; var16 = 15
      81 [-]: JUMPIFNOTLT R16 R15 L11; goto L11 if var16 >= var1970247
      82 [-]: LOADN R16 30 ; var16 = 30
      83 [-]: JUMPIFNOTLT R15 R16 L11; goto L11 if var15 >= var133959
      84 [-]: LOADN R11 2  ; var11 = 2
      85 [-]: SUBK R10 R10 K17; var10 = var10 - 15
      86 [-]: JUMP L13     ; goto L13
L11:  87 [-]: LOADN R16 30 ; var16 = 30
      88 [-]: JUMPIFNOTLE R16 R15 L12; goto L12 if var16 > var2953287
      89 [-]: LOADN R16 45 ; var16 = 45
      90 [-]: JUMPIFNOTLT R15 R16 L12; goto L12 if var15 >= var199495
      91 [-]: LOADN R11 3  ; var11 = 3
      92 [-]: SUBK R10 R10 K18; var10 = var10 - 30
      93 [-]: JUMP L13     ; goto L13
L12:  94 [-]: LOADN R16 45 ; var16 = 45
      95 [-]: JUMPIFNOTLE R16 R15 L13; goto L13 if var16 > var265031
      96 [-]: LOADN R11 4  ; var11 = 4
      97 [-]: SUBK R10 R10 K19; var10 = var10 - 45
L13:  98 [-]: JUMPIFNOTLE R10 R12 L20; goto L20 if var10 > var70215
      99 [-]: LOADN R18 1  ; var18 = 1
     100 [-]: LOADN R20 3  ; var20 = 3
     101 [-]: GETTABLE R23 R3 R15; var23 = var3[var15]
     102 [-]: FASTCALL1 2 R23 L14; 
     103 [-]: GETIMPORT R22 23; var22 = 0x5BCED4C4[0xE4A5B3CA]
     104 [-]: CALL R22 2 2 ; var22 = var22(var23)
L14: 105 [-]: DIVK R21 R22 K20; var21 = var22 / 0.25
     106 [-]: FASTCALL2 19 R20 R21 L15; 
     107 [-]: GETIMPORT R19 25; var19 = 0x5BCED4C4[0xAC1B386A]
     108 [-]: CALL R19 3 2 ; var19 = var19(var20, var21)
L15: 109 [-]: FASTCALL2 18 R18 R19 L16; 
     110 [-]: GETIMPORT R17 27; var17 = 0x5BCED4C4[0xB62ECFE0]
     111 [-]: CALL R17 3 2 ; var17 = var17(var18, var19)
L16: 112 [-]: FASTCALL1 12 R17 L17; 
     113 [-]: GETIMPORT R16 29; var16 = 0x5BCED4C4[0x55F27C30]
     114 [-]: CALL R16 2 2 ; var16 = var16(var17)
L17: 115 [-]: DUPTABLE R17 32; 
     116 [-]: SETTABLEKS R16 R17 K30; var16["numSigns"] = var17
     117 [-]: GETUPVAL R19 1; var19 = upvalues[1]
     118 [-]: GETTABLE R18 R19 R10; var18 = var19[var10]
     119 [-]: SETTABLEKS R18 R17 K31; var18["icon"] = var17
     120 [-]: GETTABLE R18 R3 R15; var18 = var3[var15]
     121 [-]: LOADN R19 0  ; var19 = 0
     122 [-]: JUMPIFNOTLT R19 R18 L19; goto L19 if var19 >= var185078583
     123 [-]: GETTABLE R19 R8 R11; var19 = var8[var11]
     124 [-]: FASTCALL2 52 R19 R17 L18; 
     125 [-]: MOVE R20 R17 ; var20 = var17
     126 [-]: GETIMPORT R18 35; var18 = 0x33BDD652[0x23D5322F]
     127 [-]: CALL R18 3 1 ; var18(var19, var20)
L18: 128 [-]: JUMP L20     ; goto L20
L19: 129 [-]: GETTABLE R18 R3 R15; var18 = var3[var15]
     130 [-]: LOADN R19 0  ; var19 = 0
     131 [-]: JUMPIFNOTLT R18 R19 L20; goto L20 if var18 >= var185144119
     132 [-]: GETTABLE R19 R9 R11; var19 = var9[var11]
     133 [-]: FASTCALL2 52 R19 R17 L20; 
     134 [-]: MOVE R20 R17 ; var20 = var17
     135 [-]: GETIMPORT R18 35; var18 = 0x33BDD652[0x23D5322F]
     136 [-]: CALL R18 3 1 ; var18(var19, var20)
L20: 137 [-]: FORNLOOP R13 L10; nforloop end - iterate + goto L10
L21: 138 [-]: NAMECALL R13 R2 K36; var14 = var2; var13 = var2[0x23D4ABF5]
     139 [-]: CALL R13 2 2 ; var13 = var13(var14)
     140 [-]: NAMECALL R14 R2 K37; var15 = var2; var14 = var2[0xD2DEB31E]
     141 [-]: CALL R14 2 2 ; var14 = var14(var15)
     142 [-]: NAMECALL R15 R2 K38; var16 = var2; var15 = var2[0xE6C96384]
     143 [-]: CALL R15 2 2 ; var15 = var15(var16)
     144 [-]: NAMECALL R16 R2 K39; var17 = var2; var16 = var2[0xBBF395CB]
     145 [-]: CALL R16 2 2 ; var16 = var16(var17)
     146 [-]: NAMECALL R17 R2 K40; var18 = var2; var17 = var2[0xB87F958D]
     147 [-]: CALL R17 2 2 ; var17 = var17(var18)
     148 [-]: NAMECALL R18 R2 K41; var19 = var2; var18 = var2[0x76AA1E1B]
     149 [-]: CALL R18 2 2 ; var18 = var18(var19)
     150 [-]: NAMECALL R19 R1 K42; var20 = var1; var19 = var1[0xB40C191A]
     151 [-]: CALL R19 2 2 ; var19 = var19(var20)
     152 [-]: NAMECALL R20 R2 K43; var21 = var2; var20 = var2[0x4514B1E1]
     153 [-]: CALL R20 2 2 ; var20 = var20(var21)
     154 [-]: DUPCLOSURE R21 K44; 
     155 [-]: LOADN R22 0  ; var22 = 0
     156 [-]: JUMPIFNOTLT R22 R16 L22; goto L22 if var22 >= var5703
     157 [-]: LOADN R22 0  ; var22 = 0
     158 [-]: JUMPIFNOTLT R22 R20 L22; goto L22 if var22 >= var3020366
     159 [-]: GETIMPORT R22 46; var22 = 0x33BDD652[0xF21B1D8E]
     160 [-]: GETTABLEN R23 R8 4; var23 = var8[4]
     161 [-]: MOVE R24 R21 ; var24 = var21
     162 [-]: CALL R22 3 1 ; var22(var23, var24)
     163 [-]: GETIMPORT R22 46; var22 = 0x33BDD652[0xF21B1D8E]
     164 [-]: GETTABLEN R23 R9 4; var23 = var9[4]
     165 [-]: MOVE R24 R21 ; var24 = var21
     166 [-]: CALL R22 3 1 ; var22(var23, var24)
     167 [-]: GETUPVAL R22 2; var22 = upvalues[2]
     168 [-]: MOVE R23 R0  ; var23 = var0
     169 [-]: MOVE R24 R9  ; var24 = var9
     170 [-]: MOVE R25 R8  ; var25 = var8
     171 [-]: MOVE R26 R16 ; var26 = var16
     172 [-]: LOADN R27 4  ; var27 = 4
     173 [-]: CALL R22 6 2 ; var22 = var22(var23, var24, var25, var26, var27)
     174 [-]: MOVE R0 R22  ; var0 = var22
L22: 175 [-]: LOADN R22 0  ; var22 = 0
     176 [-]: JUMPIFNOTLT R22 R13 L23; goto L23 if var22 >= var5703
     177 [-]: LOADN R22 0  ; var22 = 0
     178 [-]: JUMPIFNOTLT R22 R17 L23; goto L23 if var22 >= var3020366
     179 [-]: GETIMPORT R22 46; var22 = 0x33BDD652[0xF21B1D8E]
     180 [-]: GETTABLEN R23 R8 1; var23 = var8[1]
     181 [-]: MOVE R24 R21 ; var24 = var21
     182 [-]: CALL R22 3 1 ; var22(var23, var24)
     183 [-]: GETIMPORT R22 46; var22 = 0x33BDD652[0xF21B1D8E]
     184 [-]: GETTABLEN R23 R9 1; var23 = var9[1]
     185 [-]: MOVE R24 R21 ; var24 = var21
     186 [-]: CALL R22 3 1 ; var22(var23, var24)
     187 [-]: GETUPVAL R22 2; var22 = upvalues[2]
     188 [-]: MOVE R23 R0  ; var23 = var0
     189 [-]: MOVE R24 R9  ; var24 = var9
     190 [-]: MOVE R25 R8  ; var25 = var8
     191 [-]: MOVE R26 R13 ; var26 = var13
     192 [-]: LOADN R27 1  ; var27 = 1
     193 [-]: CALL R22 6 2 ; var22 = var22(var23, var24, var25, var26, var27)
     194 [-]: MOVE R0 R22  ; var0 = var22
L23: 195 [-]: LOADN R22 0  ; var22 = 0
     196 [-]: JUMPIFNOTLT R22 R14 L24; goto L24 if var22 >= var5703
     197 [-]: LOADN R22 0  ; var22 = 0
     198 [-]: JUMPIFNOTLT R22 R18 L24; goto L24 if var22 >= var3020366
     199 [-]: GETIMPORT R22 46; var22 = 0x33BDD652[0xF21B1D8E]
     200 [-]: GETTABLEN R23 R8 2; var23 = var8[2]
     201 [-]: MOVE R24 R21 ; var24 = var21
     202 [-]: CALL R22 3 1 ; var22(var23, var24)
     203 [-]: GETIMPORT R22 46; var22 = 0x33BDD652[0xF21B1D8E]
     204 [-]: GETTABLEN R23 R9 2; var23 = var9[2]
     205 [-]: MOVE R24 R21 ; var24 = var21
     206 [-]: CALL R22 3 1 ; var22(var23, var24)
     207 [-]: GETUPVAL R22 2; var22 = upvalues[2]
     208 [-]: MOVE R23 R0  ; var23 = var0
     209 [-]: MOVE R24 R9  ; var24 = var9
     210 [-]: MOVE R25 R8  ; var25 = var8
     211 [-]: MOVE R26 R14 ; var26 = var14
     212 [-]: LOADN R27 2  ; var27 = 2
     213 [-]: CALL R22 6 2 ; var22 = var22(var23, var24, var25, var26, var27)
     214 [-]: MOVE R0 R22  ; var0 = var22
L24: 215 [-]: LOADN R22 0  ; var22 = 0
     216 [-]: JUMPIFNOTLT R22 R15 L25; goto L25 if var22 >= var5703
     217 [-]: LOADN R22 0  ; var22 = 0
     218 [-]: JUMPIFNOTLT R22 R19 L25; goto L25 if var22 >= var3020366
     219 [-]: GETIMPORT R22 46; var22 = 0x33BDD652[0xF21B1D8E]
     220 [-]: GETTABLEN R23 R8 3; var23 = var8[3]
     221 [-]: MOVE R24 R21 ; var24 = var21
     222 [-]: CALL R22 3 1 ; var22(var23, var24)
     223 [-]: GETIMPORT R22 46; var22 = 0x33BDD652[0xF21B1D8E]
     224 [-]: GETTABLEN R23 R9 3; var23 = var9[3]
     225 [-]: MOVE R24 R21 ; var24 = var21
     226 [-]: CALL R22 3 1 ; var22(var23, var24)
     227 [-]: GETUPVAL R22 2; var22 = upvalues[2]
     228 [-]: MOVE R23 R0  ; var23 = var0
     229 [-]: MOVE R24 R9  ; var24 = var9
     230 [-]: MOVE R25 R8  ; var25 = var8
     231 [-]: MOVE R26 R15 ; var26 = var15
     232 [-]: LOADN R27 3  ; var27 = 3
     233 [-]: CALL R22 6 2 ; var22 = var22(var23, var24, var25, var26, var27)
     234 [-]: MOVE R0 R22  ; var0 = var22
L25: 235 [-]: MOVE R22 R0  ; var22 = var0
     236 [-]: LOADK R23 K47; var23 = "</p>"
     237 [-]: CONCAT R0 R22 R23; var0 = var22 .. var23
L26: 238 [-]: RETURN R0 1  ; 


; Name:            
; Defined at line: 521
; #Upvalues:       8
; #Parameters:     0
; Is_vararg:       0
; Max Stack Size:  15

       0 [-]: GETIMPORT R1 3; var1 = _T["ScanUpdateParms"]["ActiveTargetIndex"]
       1 [-]: FASTCALL1 62 R1 L0; 
       2 [-]: GETIMPORT R0 5; var0 = 0x7B998233
       3 [-]: CALL R0 2 2  ; var0 = var0(var1)
L 0:   4 [-]: JUMPIF R0 L2 ; goto L2 if var0
       5 [-]: GETIMPORT R2 7; var2 = _T["ScanUpdateParms"]["CurrentTarget"]
       6 [-]: GETTABLEKS R1 R2 K8; var1 = var2["mPtr"]
       7 [-]: FASTCALL1 62 R1 L1; 
       8 [-]: GETIMPORT R0 5; var0 = 0x7B998233
       9 [-]: CALL R0 2 2  ; var0 = var0(var1)
L 1:  10 [-]: JUMPIF R0 L2 ; goto L2 if var0
      11 [-]: GETIMPORT R0 10; var0 = 0xBE190284
      12 [-]: NAMECALL R0 R0 K11; var1 = var0; var0 = var0[0xD37C53CE]
      13 [-]: CALL R0 2 2  ; var0 = var0(var1)
      14 [-]: LOADN R1 3   ; var1 = 3
      15 [-]: JUMPIFNOTEQ R0 R1 L2; goto L2 if var0 ~= var459086
      16 [-]: GETIMPORT R1 7; var1 = _T["ScanUpdateParms"]["CurrentTarget"]
      17 [-]: GETTABLEKS R0 R1 K8; var0 = var1["mPtr"]
      18 [-]: NAMECALL R0 R0 K12; var1 = var0; var0 = var0[0x22DA1852]
      19 [-]: CALL R0 2 2  ; var0 = var0(var1)
      20 [-]: GETUPVAL R1 0; var1 = upvalues[0]
      21 [-]: JUMPIFNOTEQ R0 R1 L2; goto L2 if var0 ~= var65799
      22 [-]: GETUPVAL R1 1; var1 = upvalues[1]
      23 [-]: GETTABLEKS R0 R1 K13; var0 = var1[0x89928096]
      24 [-]: GETIMPORT R1 15; var1 = _T["ScanUpdateParms"]["Avatar"]
      25 [-]: CALL R0 2 2  ; var0 = var0(var1)
      26 [-]: JUMPIFNOT R0 L2; goto L2 if not var0
      27 [-]: GETIMPORT R1 7; var1 = _T["ScanUpdateParms"]["CurrentTarget"]
      28 [-]: SETTABLEKS R0 R1 K8; var0["mPtr"] = var1
L 2:  29 [-]: GETIMPORT R1 17; var1 = _T["ScanUpdateParms"]["Weapon"]
      30 [-]: GETTABLEKS R0 R1 K18; var0 = var1["impactBehavior"]
      31 [-]: FASTCALL1 62 R0 L3; 
      32 [-]: MOVE R2 R0   ; var2 = var0
      33 [-]: GETIMPORT R1 5; var1 = 0x7B998233
      34 [-]: CALL R1 2 2  ; var1 = var1(var2)
L 3:  35 [-]: JUMPIF R1 L5 ; goto L5 if var1
      36 [-]: GETIMPORT R3 20; var3 = 0xE6344D8D
      37 [-]: NAMECALL R1 R0 K21; var2 = var0; var1 = var0[0xF2DEAF69]
      38 [-]: CALL R1 3 2  ; var1 = var1(var2, var3)
      39 [-]: JUMPIFNOT R1 L5; goto L5 if not var1
      40 [-]: GETIMPORT R2 15; var2 = _T["ScanUpdateParms"]["Avatar"]
      41 [-]: FASTCALL1 62 R2 L4; 
      42 [-]: GETIMPORT R1 5; var1 = 0x7B998233
      43 [-]: CALL R1 2 2  ; var1 = var1(var2)
L 4:  44 [-]: JUMPIF R1 L7 ; goto L7 if var1
      45 [-]: GETIMPORT R1 15; var1 = _T["ScanUpdateParms"]["Avatar"]
      46 [-]: LOADN R3 0   ; var3 = 0
      47 [-]: NAMECALL R1 R1 K22; var2 = var1; var1 = var1[0x0E46E45B]
      48 [-]: CALL R1 3 2  ; var1 = var1(var2, var3)
      49 [-]: JUMPXEQKB R1 0 L7 NOT; 
L 5:  50 [-]: GETIMPORT R2 17; var2 = _T["ScanUpdateParms"]["Weapon"]
      51 [-]: GETTABLEKS R1 R2 K23; var1 = var2["wasScanning"]
      52 [-]: JUMPIFNOT R1 L6; goto L6 if not var1
      53 [-]: GETIMPORT R1 25; var1 = 0xAE91E43B
      54 [-]: LOADK R3 K26 ; var3 = "ReticleSniper"
      55 [-]: LOADN R4 11  ; var4 = 11
      56 [-]: LOADB R5 0   ; var5 = false
      57 [-]: NAMECALL R1 R1 K27; var2 = var1; var1 = var1[0xAADE900E]
      58 [-]: CALL R1 5 1  ; var1(var2, var3, var4, var5)
      59 [-]: GETIMPORT R1 17; var1 = _T["ScanUpdateParms"]["Weapon"]
      60 [-]: LOADB R2 0   ; var2 = false
      61 [-]: SETTABLEKS R2 R1 K23; var2["wasScanning"] = var1
      62 [-]: GETIMPORT R2 29; var2 = _T["ScanUpdateParms"]["Controllers"]
      63 [-]: GETTABLEKS R1 R2 K30; var1 = var2["CameraController"]
      64 [-]: GETIMPORT R3 32; var3 = 0xB37905D5
      65 [-]: NAMECALL R1 R1 K33; var2 = var1; var1 = var1[0xBD5007D9]
      66 [-]: CALL R1 3 1  ; var1(var2, var3)
L 6:  67 [-]: RETURN R0 0  ; 
L 7:  68 [-]: GETIMPORT R2 17; var2 = _T["ScanUpdateParms"]["Weapon"]
      69 [-]: GETTABLEKS R1 R2 K23; var1 = var2["wasScanning"]
      70 [-]: JUMPIF R1 L8 ; goto L8 if var1
      71 [-]: GETIMPORT R1 25; var1 = 0xAE91E43B
      72 [-]: LOADK R3 K26 ; var3 = "ReticleSniper"
      73 [-]: LOADN R4 11  ; var4 = 11
      74 [-]: LOADB R5 1   ; var5 = true
      75 [-]: NAMECALL R1 R1 K27; var2 = var1; var1 = var1[0xAADE900E]
      76 [-]: CALL R1 5 1  ; var1(var2, var3, var4, var5)
      77 [-]: GETIMPORT R1 17; var1 = _T["ScanUpdateParms"]["Weapon"]
      78 [-]: LOADB R2 1   ; var2 = true
      79 [-]: SETTABLEKS R2 R1 K23; var2["wasScanning"] = var1
      80 [-]: GETIMPORT R2 29; var2 = _T["ScanUpdateParms"]["Controllers"]
      81 [-]: GETTABLEKS R1 R2 K30; var1 = var2["CameraController"]
      82 [-]: GETIMPORT R3 32; var3 = 0xB37905D5
      83 [-]: LOADN R4 0   ; var4 = 0
      84 [-]: LOADN R5 -1  ; var5 = -1
      85 [-]: LOADN R6 0   ; var6 = 0
      86 [-]: NAMECALL R1 R1 K34; var2 = var1; var1 = var1[0x758C046D]
      87 [-]: CALL R1 6 1  ; var1(var2, var3, var4, var5, var6)
L 8:  88 [-]: LOADN R1 0   ; var1 = 0
      89 [-]: GETIMPORT R3 3; var3 = _T["ScanUpdateParms"]["ActiveTargetIndex"]
      90 [-]: FASTCALL1 62 R3 L9; 
      91 [-]: GETIMPORT R2 5; var2 = 0x7B998233
      92 [-]: CALL R2 2 2  ; var2 = var2(var3)
L 9:  93 [-]: JUMPIF R2 L10; goto L10 if var2
      94 [-]: GETIMPORT R5 7; var5 = _T["ScanUpdateParms"]["CurrentTarget"]
      95 [-]: GETTABLEKS R4 R5 K8; var4 = var5["mPtr"]
      96 [-]: NAMECALL R2 R0 K35; var3 = var0; var2 = var0[0x020D3C80]
      97 [-]: CALL R2 3 2  ; var2 = var2(var3, var4)
      98 [-]: MOVE R1 R2   ; var1 = var2
L10:  99 [-]: GETUPVAL R2 2; var2 = upvalues[2]
     100 [-]: JUMPXEQKNIL R2 L17 NOT; 
     101 [-]: GETIMPORT R2 37; var2 = 0x76EA806B
     102 [-]: LOADN R4 0   ; var4 = 0
     103 [-]: NAMECALL R2 R2 K38; var3 = var2; var2 = var2[0x3F3AE64C]
     104 [-]: CALL R2 3 2  ; var2 = var2(var3, var4)
     105 [-]: FASTCALL1 62 R2 L11; 
     106 [-]: MOVE R4 R2   ; var4 = var2
     107 [-]: GETIMPORT R3 5; var3 = 0x7B998233
     108 [-]: CALL R3 2 2  ; var3 = var3(var4)
L11: 109 [-]: JUMPIF R3 L17; goto L17 if var3
     110 [-]: NAMECALL R3 R2 K39; var4 = var2; var3 = var2[0x80563238]
     111 [-]: CALL R3 2 2  ; var3 = var3(var4)
     112 [-]: FASTCALL1 62 R3 L12; 
     113 [-]: MOVE R5 R3   ; var5 = var3
     114 [-]: GETIMPORT R4 5; var4 = 0x7B998233
     115 [-]: CALL R4 2 2  ; var4 = var4(var5)
L12: 116 [-]: JUMPIF R4 L17; goto L17 if var4
     117 [-]: NAMECALL R4 R3 K40; var5 = var3; var4 = var3[0x25A6E75E]
     118 [-]: CALL R4 2 2  ; var4 = var4(var5)
     119 [-]: NAMECALL R4 R4 K41; var5 = var4; var4 = var4[0xF4045B7E]
     120 [-]: CALL R4 2 2  ; var4 = var4(var5)
     121 [-]: LOADB R5 0   ; var5 = false
     122 [-]: SETUPVAL R5 2; upvalues[5] = var2
     123 [-]: LOADB R5 0   ; var5 = false
     124 [-]: SETUPVAL R5 3; upvalues[5] = var3
     125 [-]: GETIMPORT R5 43; var5 = 0xC8802016
     126 [-]: MOVE R6 R4   ; var6 = var4
     127 [-]: CALL R5 2 4  ; var5, var6, var7 = var5(var6)
     128 [-]: FORGPREP_INEXT R5 L16; 
L13: 129 [-]: GETTABLEKS R10 R9 K44; var10 = var9["mItemCount"]
     130 [-]: LOADN R11 0  ; var11 = 0
     131 [-]: JUMPIFNOTLT R11 R10 L16; goto L16 if var11 >= var-787936740
     132 [-]: GETTABLEKS R10 R9 K45; var10 = var9["mItemType"]
     133 [-]: GETIMPORT R11 47; var11 = 0xB2D1F6E0
     134 [-]: JUMPIFNOTEQ R10 R11 L14; goto L14 if var10 ~= var68123
     135 [-]: LOADB R10 1  ; var10 = true
     136 [-]: SETUPVAL R10 2; upvalues[10] = var2
     137 [-]: JUMP L15     ; goto L15
L14: 138 [-]: GETTABLEKS R10 R9 K45; var10 = var9["mItemType"]
     139 [-]: GETIMPORT R11 49; var11 = 0x8F533984
     140 [-]: JUMPIFNOTEQ R10 R11 L15; goto L15 if var10 ~= var68123
     141 [-]: LOADB R10 1  ; var10 = true
     142 [-]: SETUPVAL R10 3; upvalues[10] = var3
L15: 143 [-]: GETUPVAL R10 2; var10 = upvalues[2]
     144 [-]: JUMPIFNOT R10 L16; goto L16 if not var10
     145 [-]: GETUPVAL R10 3; var10 = upvalues[3]
     146 [-]: JUMPIF R10 L17; goto L17 if var10
L16: 147 [-]: FORGLOOP R5 L13 2 [inext]; 
L17: 148 [-]: LOADN R2 0   ; var2 = 0
     149 [-]: GETIMPORT R4 3; var4 = _T["ScanUpdateParms"]["ActiveTargetIndex"]
     150 [-]: FASTCALL1 62 R4 L18; 
     151 [-]: GETIMPORT R3 5; var3 = 0x7B998233
     152 [-]: CALL R3 2 2  ; var3 = var3(var4)
L18: 153 [-]: JUMPIF R3 L19; goto L19 if var3
     154 [-]: GETIMPORT R4 29; var4 = _T["ScanUpdateParms"]["Controllers"]
     155 [-]: GETTABLEKS R3 R4 K50; var3 = var4["InventoryController"]
     156 [-]: GETIMPORT R6 7; var6 = _T["ScanUpdateParms"]["CurrentTarget"]
     157 [-]: GETTABLEKS R5 R6 K8; var5 = var6["mPtr"]
     158 [-]: NAMECALL R3 R3 K51; var4 = var3; var3 = var3[0xF4A5E26A]
     159 [-]: CALL R3 3 2  ; var3 = var3(var4, var5)
     160 [-]: MOVE R2 R3   ; var2 = var3
L19: 161 [-]: LOADB R3 1   ; var3 = true
     162 [-]: LOADN R4 8   ; var4 = 8
     163 [-]: JUMPIFEQ R2 R4 L21; goto L21 if var2 == var66331
     164 [-]: LOADB R3 1   ; var3 = true
     165 [-]: LOADN R4 3   ; var4 = 3
     166 [-]: JUMPIFEQ R2 R4 L21; goto L21 if var2 == var66331
     167 [-]: LOADB R3 1   ; var3 = true
     168 [-]: LOADN R4 5   ; var4 = 5
     169 [-]: JUMPIFEQ R2 R4 L21; goto L21 if var2 == var394311
     170 [-]: LOADN R4 6   ; var4 = 6
     171 [-]: JUMPIFEQ R2 R4 L20; goto L20 if var2 == var16778011
     172 [-]: LOADB R3 0 +1; var3 = false
L20: 173 [-]: LOADB R3 1   ; var3 = true
L21: 174 [-]: JUMPIFNOT R3 L22; goto L22 if not var3
     175 [-]: GETUPVAL R4 4; var4 = upvalues[4]
     176 [-]: GETIMPORT R6 7; var6 = _T["ScanUpdateParms"]["CurrentTarget"]
     177 [-]: GETTABLEKS R5 R6 K52; var5 = var6["mName"]
     178 [-]: SETTABLEKS R5 R4 K53; var5["mScanningTag"] = var4
     179 [-]: JUMP L31     ; goto L31
L22: 180 [-]: GETIMPORT R4 3; var4 = _T["ScanUpdateParms"]["ActiveTargetIndex"]
     181 [-]: JUMPIFNOT R4 L27; goto L27 if not var4
     182 [-]: GETIMPORT R5 7; var5 = _T["ScanUpdateParms"]["CurrentTarget"]
     183 [-]: GETTABLEKS R4 R5 K52; var4 = var5["mName"]
     184 [-]: GETUPVAL R6 4; var6 = upvalues[4]
     185 [-]: GETTABLEKS R5 R6 K53; var5 = var6["mScanningTag"]
     186 [-]: JUMPIFEQ R4 R5 L27; goto L27 if var4 == var460110
     187 [-]: GETIMPORT R5 7; var5 = _T["ScanUpdateParms"]["CurrentTarget"]
     188 [-]: GETTABLEKS R4 R5 K54; var4 = var5["mActive"]
     189 [-]: JUMPIFNOT R4 L27; goto L27 if not var4
     190 [-]: GETUPVAL R4 4; var4 = upvalues[4]
     191 [-]: GETIMPORT R6 7; var6 = _T["ScanUpdateParms"]["CurrentTarget"]
     192 [-]: GETTABLEKS R5 R6 K52; var5 = var6["mName"]
     193 [-]: SETTABLEKS R5 R4 K53; var5["mScanningTag"] = var4
     194 [-]: GETIMPORT R4 25; var4 = 0xAE91E43B
     195 [-]: LOADK R6 K55 ; var6 = "ReticleSniper.Scanning.ScanName"
     196 [-]: LOADN R7 10  ; var7 = 10
     197 [-]: LOADN R8 100 ; var8 = 100
     198 [-]: NAMECALL R4 R4 K56; var5 = var4; var4 = var4[0x67BC869F]
     199 [-]: CALL R4 5 1  ; var4(var5, var6, var7, var8)
     200 [-]: LOADNIL R4   ; var4 = nil
     201 [-]: LOADN R5 1   ; var5 = 1
     202 [-]: JUMPIFNOTEQ R2 R5 L23; goto L23 if var2 ~= var1639758
     203 [-]: GETIMPORT R5 25; var5 = 0xAE91E43B
     204 [-]: LOADK R7 K57 ; var7 = "/Lotus/Language/Menu/HUD_AlreadyScanned"
     205 [-]: LOADB R8 0   ; var8 = false
     206 [-]: NAMECALL R5 R5 K58; var6 = var5; var5 = var5[0x42B04007]
     207 [-]: CALL R5 4 2  ; var5 = var5(var6, var7, var8)
     208 [-]: MOVE R4 R5   ; var4 = var5
     209 [-]: JUMP L26     ; goto L26
L23: 210 [-]: LOADN R5 4   ; var5 = 4
     211 [-]: JUMPIFNOTEQ R2 R5 L24; goto L24 if var2 ~= var656974
     212 [-]: GETIMPORT R6 10; var6 = 0xBE190284
     213 [-]: NAMECALL R6 R6 K60; var7 = var6; var6 = var6[0xE32D351D]
     214 [-]: CALL R6 2 2  ; var6 = var6(var7)
     215 [-]: MULK R5 R6 K59; var5 = var6 * 100
     216 [-]: GETIMPORT R6 25; var6 = 0xAE91E43B
     217 [-]: LOADK R8 K61 ; var8 = "/Lotus/Language/Menu/HUD_TargetAboveThreshold"
     218 [-]: LOADB R9 0   ; var9 = false
     219 [-]: DUPTABLE R10 63; 
     220 [-]: SETTABLEKS R5 R10 K62; var5["PERCENTAGE"] = var10
     221 [-]: NAMECALL R6 R6 K58; var7 = var6; var6 = var6[0x42B04007]
     222 [-]: CALL R6 5 2  ; var6 = var6(var7, var8, var9, var10)
     223 [-]: MOVE R4 R6   ; var4 = var6
     224 [-]: JUMP L26     ; goto L26
L24: 225 [-]: LOADN R5 2   ; var5 = 2
     226 [-]: JUMPIFNOTEQ R2 R5 L25; goto L25 if var2 ~= var1639758
     227 [-]: GETIMPORT R5 25; var5 = 0xAE91E43B
     228 [-]: LOADK R7 K64 ; var7 = "/Lotus/Language/Menu/HUD_CodexFilled"
     229 [-]: LOADB R8 0   ; var8 = false
     230 [-]: NAMECALL R5 R5 K58; var6 = var5; var5 = var5[0x42B04007]
     231 [-]: CALL R5 4 2  ; var5 = var5(var6, var7, var8)
     232 [-]: MOVE R4 R5   ; var4 = var5
     233 [-]: JUMP L26     ; goto L26
L25: 234 [-]: LOADK R4 K65 ; var4 = ""
L26: 235 [-]: GETUPVAL R6 5; var6 = upvalues[5]
     236 [-]: GETTABLEKS R5 R6 K66; var5 = var6[0xF6E70FB6]
     237 [-]: GETIMPORT R6 25; var6 = 0xAE91E43B
     238 [-]: LOADNIL R7   ; var7 = nil
     239 [-]: LOADK R8 K55 ; var8 = "ReticleSniper.Scanning.ScanName"
     240 [-]: MOVE R9 R4   ; var9 = var4
     241 [-]: LOADNIL R10  ; var10 = nil
     242 [-]: CALL R5 6 1  ; var5(var6, var7, var8, var9, var10)
     243 [-]: JUMP L31     ; goto L31
L27: 244 [-]: GETIMPORT R4 3; var4 = _T["ScanUpdateParms"]["ActiveTargetIndex"]
     245 [-]: JUMPIF R4 L28; goto L28 if var4
     246 [-]: GETUPVAL R5 4; var5 = upvalues[4]
     247 [-]: GETTABLEKS R4 R5 K53; var4 = var5["mScanningTag"]
     248 [-]: JUMPIF R4 L30; goto L30 if var4
L28: 249 [-]: GETIMPORT R5 3; var5 = _T["ScanUpdateParms"]["ActiveTargetIndex"]
     250 [-]: FASTCALL1 62 R5 L29; 
     251 [-]: GETIMPORT R4 5; var4 = 0x7B998233
     252 [-]: CALL R4 2 2  ; var4 = var4(var5)
L29: 253 [-]: JUMPIF R4 L31; goto L31 if var4
     254 [-]: GETIMPORT R5 7; var5 = _T["ScanUpdateParms"]["CurrentTarget"]
     255 [-]: GETTABLEKS R4 R5 K52; var4 = var5["mName"]
     256 [-]: JUMPIF R4 L31; goto L31 if var4
     257 [-]: GETUPVAL R5 4; var5 = upvalues[4]
     258 [-]: GETTABLEKS R4 R5 K53; var4 = var5["mScanningTag"]
     259 [-]: JUMPIFNOT R4 L31; goto L31 if not var4
L30: 260 [-]: GETUPVAL R4 4; var4 = upvalues[4]
     261 [-]: LOADNIL R5   ; var5 = nil
     262 [-]: SETTABLEKS R5 R4 K53; var5["mScanningTag"] = var4
     263 [-]: GETIMPORT R4 68; var4 = 0x25312C9B
     264 [-]: GETIMPORT R5 25; var5 = 0xAE91E43B
     265 [-]: LOADK R6 K55 ; var6 = "ReticleSniper.Scanning.ScanName"
     266 [-]: LOADN R7 8   ; var7 = 8
     267 [-]: NEWTABLE R8 0 1; var8 = {}
     268 [-]: LOADN R9 10  ; var9 = 10
     269 [-]: SETLIST R8 R9 1 [1]; var8[1] = var9; var8[2] = var10; 
     270 [-]: NEWTABLE R9 0 1; var9 = {}
     271 [-]: LOADN R10 0  ; var10 = 0
     272 [-]: SETLIST R9 R10 1 [1]; var9[1] = var10; var9[2] = var11; 
     273 [-]: LOADK R10 K69; var10 = 0.5
     274 [-]: CALL R4 7 1  ; var4(var5, var6, var7, var8, var9, var10)
L31: 275 [-]: GETUPVAL R4 3; var4 = upvalues[3]
     276 [-]: JUMPIFNOT R4 L37; goto L37 if not var4
     277 [-]: GETIMPORT R6 7; var6 = _T["ScanUpdateParms"]["CurrentTarget"]
     278 [-]: GETTABLEKS R5 R6 K70; var5 = var6["mAvatar"]
     279 [-]: FASTCALL1 62 R5 L32; 
     280 [-]: GETIMPORT R4 5; var4 = 0x7B998233
     281 [-]: CALL R4 2 2  ; var4 = var4(var5)
L32: 282 [-]: JUMPIF R4 L34; goto L34 if var4
     283 [-]: GETUPVAL R4 6; var4 = upvalues[6]
     284 [-]: CALL R4 1 2  ; var4 = var4()
     285 [-]: JUMPXEQKS R4 K65 L33; 
     286 [-]: GETIMPORT R5 25; var5 = 0xAE91E43B
     287 [-]: LOADK R7 K71 ; var7 = "ReticleSniper.ScansTaken.TargetDetails"
     288 [-]: LOADN R8 29  ; var8 = 29
     289 [-]: MOVE R9 R4   ; var9 = var4
     290 [-]: NAMECALL R5 R5 K72; var6 = var5; var5 = var5[0x5F56EEAB]
     291 [-]: CALL R5 5 1  ; var5(var6, var7, var8, var9)
L33: 292 [-]: GETUPVAL R5 7; var5 = upvalues[7]
     293 [-]: JUMPIF R5 L35; goto L35 if var5
     294 [-]: GETIMPORT R5 68; var5 = 0x25312C9B
     295 [-]: GETIMPORT R6 25; var6 = 0xAE91E43B
     296 [-]: LOADK R7 K71 ; var7 = "ReticleSniper.ScansTaken.TargetDetails"
     297 [-]: LOADN R8 8   ; var8 = 8
     298 [-]: NEWTABLE R9 0 1; var9 = {}
     299 [-]: LOADN R10 10 ; var10 = 10
     300 [-]: SETLIST R9 R10 1 [1]; var9[1] = var10; var9[2] = var11; 
     301 [-]: NEWTABLE R10 0 1; var10 = {}
     302 [-]: LOADN R11 100; var11 = 100
     303 [-]: SETLIST R10 R11 1 [1]; var10[1] = var11; var10[2] = var12; 
     304 [-]: LOADK R11 K73; var11 = 0.10000000000000001
     305 [-]: LOADN R12 0  ; var12 = 0
     306 [-]: CALL R5 8 1  ; var5(var6, var7, var8, var9, var10, var11, var12)
     307 [-]: JUMP L35     ; goto L35
L34: 308 [-]: GETUPVAL R4 7; var4 = upvalues[7]
     309 [-]: JUMPIFNOT R4 L35; goto L35 if not var4
     310 [-]: GETIMPORT R4 68; var4 = 0x25312C9B
     311 [-]: GETIMPORT R5 25; var5 = 0xAE91E43B
     312 [-]: LOADK R6 K71 ; var6 = "ReticleSniper.ScansTaken.TargetDetails"
     313 [-]: LOADN R7 8   ; var7 = 8
     314 [-]: NEWTABLE R8 0 1; var8 = {}
     315 [-]: LOADN R9 10  ; var9 = 10
     316 [-]: SETLIST R8 R9 1 [1]; var8[1] = var9; var8[2] = var10; 
     317 [-]: NEWTABLE R9 0 1; var9 = {}
     318 [-]: LOADN R10 0  ; var10 = 0
     319 [-]: SETLIST R9 R10 1 [1]; var9[1] = var10; var9[2] = var11; 
     320 [-]: LOADK R10 K73; var10 = 0.10000000000000001
     321 [-]: LOADK R11 K74; var11 = 2.5
     322 [-]: CALL R4 8 1  ; var4(var5, var6, var7, var8, var9, var10, var11)
L35: 323 [-]: GETIMPORT R7 7; var7 = _T["ScanUpdateParms"]["CurrentTarget"]
     324 [-]: GETTABLEKS R6 R7 K70; var6 = var7["mAvatar"]
     325 [-]: FASTCALL1 62 R6 L36; 
     326 [-]: GETIMPORT R5 5; var5 = 0x7B998233
     327 [-]: CALL R5 2 2  ; var5 = var5(var6)
L36: 328 [-]: NOT R4 R5    ; var4 = not var5
     329 [-]: SETUPVAL R4 7; upvalues[4] = var7
L37: 330 [-]: JUMPIF R3 L38; goto L38 if var3
     331 [-]: LOADN R1 0   ; var1 = 0
L38: 332 [-]: LOADN R4 5   ; var4 = 5
     333 [-]: JUMPIFNOTEQ R2 R4 L39; goto L39 if var2 ~= var394311
     334 [-]: LOADN R4 6   ; var4 = 6
     335 [-]: JUMPIFNOTEQ R2 R4 L40; goto L40 if var2 ~= var1639502
L39: 336 [-]: GETIMPORT R4 25; var4 = 0xAE91E43B
     337 [-]: LOADK R6 K75 ; var6 = "SetScanProgress"
     338 [-]: MOVE R7 R1   ; var7 = var1
     339 [-]: NAMECALL R4 R4 K76; var5 = var4; var4 = var4[0xE4162EED]
     340 [-]: CALL R4 4 1  ; var4(var5, var6, var7)
L40: 341 [-]: GETIMPORT R4 25; var4 = 0xAE91E43B
     342 [-]: LOADK R6 K77 ; var6 = "ReticleSniper.Scanning.C1"
     343 [-]: LOADN R7 11  ; var7 = 11
     344 [-]: MOVE R8 R3   ; var8 = var3
     345 [-]: NAMECALL R4 R4 K27; var5 = var4; var4 = var4[0xAADE900E]
     346 [-]: CALL R4 5 1  ; var4(var5, var6, var7, var8)
     347 [-]: GETIMPORT R4 25; var4 = 0xAE91E43B
     348 [-]: LOADK R6 K78 ; var6 = "ReticleSniper.ReticleTennoSniper"
     349 [-]: LOADN R7 9   ; var7 = 9
     350 [-]: GETUPVAL R9 5; var9 = upvalues[5]
     351 [-]: GETTABLEKS R8 R9 K79; var8 = var9[0x06D055F9]
     352 [-]: MOVE R9 R3   ; var9 = var3
     353 [-]: LOADK R10 K80; var10 = 16732416
     354 [-]: LOADK R11 K81; var11 = 16777215
     355 [-]: CALL R8 4 0  ; var8, ... = var8(var9, var10, var11)
     356 [-]: NAMECALL R4 R4 K56; var5 = var4; var4 = var4[0x67BC869F]
     357 [-]: CALL R4 0 1  ; var4(var5, ...)
     358 [-]: GETUPVAL R5 4; var5 = upvalues[4]
     359 [-]: GETTABLEKS R4 R5 K82; var4 = var5["mPriorCanScan"]
     360 [-]: JUMPIFEQ R3 R4 L41; goto L41 if var3 == var263175
     361 [-]: GETUPVAL R4 4; var4 = upvalues[4]
     362 [-]: SETTABLEKS R3 R4 K82; var3["mPriorCanScan"] = var4
     363 [-]: GETUPVAL R5 5; var5 = upvalues[5]
     364 [-]: GETTABLEKS R4 R5 K79; var4 = var5[0x06D055F9]
     365 [-]: MOVE R5 R3   ; var5 = var3
     366 [-]: LOADN R6 100 ; var6 = 100
     367 [-]: LOADN R7 120 ; var7 = 120
     368 [-]: CALL R4 4 2  ; var4 = var4(var5, var6, var7)
     369 [-]: GETIMPORT R5 68; var5 = 0x25312C9B
     370 [-]: GETIMPORT R6 25; var6 = 0xAE91E43B
     371 [-]: LOADK R7 K83 ; var7 = "ReticleSniper.ReticleTennoSniper.TheReticle"
     372 [-]: LOADN R8 8   ; var8 = 8
     373 [-]: NEWTABLE R9 0 2; var9 = {}
     374 [-]: LOADN R10 5  ; var10 = 5
     375 [-]: LOADN R11 6  ; var11 = 6
     376 [-]: SETLIST R9 R10 2 [1]; var9[1] = var10; var9[2] = var11; var9[3] = var12; 
     377 [-]: NEWTABLE R10 0 2; var10 = {}
     378 [-]: MOVE R11 R4  ; var11 = var4
     379 [-]: MOVE R12 R4  ; var12 = var4
     380 [-]: SETLIST R10 R11 2 [1]; var10[1] = var11; var10[2] = var12; var10[3] = var13; 
     381 [-]: LOADK R11 K84; var11 = 0.20000000000000001
     382 [-]: CALL R5 7 1  ; var5(var6, var7, var8, var9, var10, var11)
     383 [-]: GETIMPORT R5 68; var5 = 0x25312C9B
     384 [-]: GETIMPORT R6 25; var6 = 0xAE91E43B
     385 [-]: LOADK R7 K77 ; var7 = "ReticleSniper.Scanning.C1"
     386 [-]: LOADN R8 8   ; var8 = 8
     387 [-]: NEWTABLE R9 0 1; var9 = {}
     388 [-]: LOADN R10 10 ; var10 = 10
     389 [-]: SETLIST R9 R10 1 [1]; var9[1] = var10; var9[2] = var11; 
     390 [-]: NEWTABLE R10 0 1; var10 = {}
     391 [-]: GETUPVAL R12 5; var12 = upvalues[5]
     392 [-]: GETTABLEKS R11 R12 K79; var11 = var12[0x06D055F9]
     393 [-]: MOVE R12 R3  ; var12 = var3
     394 [-]: LOADN R13 100; var13 = 100
     395 [-]: LOADN R14 0  ; var14 = 0
     396 [-]: CALL R11 4 0 ; var11, ... = var11(var12, var13, var14)
     397 [-]: SETLIST R10 R11 -1 [1]; 
     398 [-]: LOADK R11 K84; var11 = 0.20000000000000001
     399 [-]: CALL R5 7 1  ; var5(var6, var7, var8, var9, var10, var11)
L41: 400 [-]: GETIMPORT R5 17; var5 = _T["ScanUpdateParms"]["Weapon"]
     401 [-]: GETTABLEKS R4 R5 K85; var4 = var5["ptr"]
     402 [-]: NAMECALL R4 R4 K86; var5 = var4; var4 = var4[0x7A7373F5]
     403 [-]: CALL R4 2 2  ; var4 = var4(var5)
     404 [-]: GETUPVAL R5 2; var5 = upvalues[2]
     405 [-]: JUMPIFNOT R5 L42; goto L42 if not var5
     406 [-]: GETIMPORT R5 25; var5 = 0xAE91E43B
     407 [-]: LOADK R7 K87 ; var7 = "<INFINITE>"
     408 [-]: LOADB R8 1   ; var8 = true
     409 [-]: NAMECALL R5 R5 K58; var6 = var5; var5 = var5[0x42B04007]
     410 [-]: CALL R5 4 2  ; var5 = var5(var6, var7, var8)
     411 [-]: MOVE R4 R5   ; var4 = var5
L42: 412 [-]: GETIMPORT R5 25; var5 = 0xAE91E43B
     413 [-]: LOADK R7 K88 ; var7 = "ReticleSniper.RemainingCharges.Count"
     414 [-]: LOADN R8 29  ; var8 = 29
     415 [-]: MOVE R9 R4   ; var9 = var4
     416 [-]: NAMECALL R5 R5 K72; var6 = var5; var5 = var5[0x5F56EEAB]
     417 [-]: CALL R5 5 1  ; var5(var6, var7, var8, var9)
     418 [-]: GETIMPORT R5 25; var5 = 0xAE91E43B
     419 [-]: LOADK R7 K89 ; var7 = "ReticleSniper.RemainingCharges.Label"
     420 [-]: LOADN R8 0   ; var8 = 0
     421 [-]: GETIMPORT R11 25; var11 = 0xAE91E43B
     422 [-]: LOADK R13 K88; var13 = "ReticleSniper.RemainingCharges.Count"
     423 [-]: LOADN R14 33 ; var14 = 33
     424 [-]: NAMECALL R11 R11 K91; var12 = var11; var11 = var11[0x91A24E4B]
     425 [-]: CALL R11 4 2 ; var11 = var11(var12, var13, var14)
     426 [-]: MINUS R10 R11; 
     427 [-]: SUBK R9 R10 K90; var9 = var10 - 119
     428 [-]: NAMECALL R5 R5 K56; var6 = var5; var5 = var5[0x67BC869F]
     429 [-]: CALL R5 5 1  ; var5(var6, var7, var8, var9)
     430 [-]: GETIMPORT R5 25; var5 = 0xAE91E43B
     431 [-]: LOADK R7 K92 ; var7 = "ReticleSniper.ScansTaken.Count"
     432 [-]: LOADN R8 29  ; var8 = 29
     433 [-]: GETIMPORT R10 29; var10 = _T["ScanUpdateParms"]["Controllers"]
     434 [-]: GETTABLEKS R9 R10 K50; var9 = var10["InventoryController"]
     435 [-]: NAMECALL R9 R9 K93; var10 = var9; var9 = var9[0x3DCC362A]
     436 [-]: CALL R9 2 0  ; var9, ... = var9(var10)
     437 [-]: NAMECALL R5 R5 K72; var6 = var5; var5 = var5[0x5F56EEAB]
     438 [-]: CALL R5 0 1  ; var5(var6, ...)
     439 [-]: GETIMPORT R5 25; var5 = 0xAE91E43B
     440 [-]: LOADK R7 K94 ; var7 = "ReticleSniper.ScansTaken.Label"
     441 [-]: LOADN R8 0   ; var8 = 0
     442 [-]: GETIMPORT R10 25; var10 = 0xAE91E43B
     443 [-]: LOADK R12 K92; var12 = "ReticleSniper.ScansTaken.Count"
     444 [-]: LOADN R13 33 ; var13 = 33
     445 [-]: NAMECALL R10 R10 K91; var11 = var10; var10 = var10[0x91A24E4B]
     446 [-]: CALL R10 4 2 ; var10 = var10(var11, var12, var13)
     447 [-]: ADDK R9 R10 K95; var9 = var10 + 5
     448 [-]: NAMECALL R5 R5 K56; var6 = var5; var5 = var5[0x67BC869F]
     449 [-]: CALL R5 5 1  ; var5(var6, var7, var8, var9)
     450 [-]: RETURN R0 0  ; 


; Name:            
; Defined at line: 652
; #Upvalues:       1
; #Parameters:     4
; Is_vararg:       0
; Max Stack Size:  5

       0 [-]: GETUPVAL R4 0; var4 = upvalues[0]
       1 [-]: CALL R4 1 1  ; var4()
       2 [-]: RETURN R0 0  ; 


; Name:            
; Defined at line: 656
; #Upvalues:       1
; #Parameters:     0
; Is_vararg:       0
; Max Stack Size:  3

       0 [-]: GETUPVAL R1 0; var1 = upvalues[0]
       1 [-]: GETTABLEKS R0 R1 K0; var0 = var1[0x29B96AD5]
       2 [-]: GETIMPORT R1 2; var1 = 0x89326C93
       3 [-]: NAMECALL R1 R1 K3; var2 = var1; var1 = var1[0x78298275]
       4 [-]: CALL R1 2 2  ; var1 = var1(var2)
       5 [-]: LOADN R2 0   ; var2 = 0
       6 [-]: CALL R0 3 1  ; var0(var1, var2)
       7 [-]: RETURN R0 0  ; 



