; This file has been disassembled using luadec 2.0.2 by sztupy (modified by Reversive)

; Name:            
; Defined at line: 0
; #Upvalues:       0
; #Parameters:     0
; Is_vararg:       2
; Max Stack Size:  36

  1 [-]: GETGLOBAL R0 K0        ; R0 := 0x2d0fad09
  2 [-]: LOADK     R1 K1        ; R1 := "Lotus.Interface.LotusUtilities"
  3 [-]: CALL      R0 2 2       ; R0 := R0(R1)
  4 [-]: GETGLOBAL R1 K0        ; R1 := 0x2d0fad09
  5 [-]: LOADK     R2 K2        ; R2 := "Lotus.Interface.UIUtilities"
  6 [-]: CALL      R1 2 2       ; R1 := R1(R2)
  7 [-]: GETGLOBAL R2 K0        ; R2 := 0x2d0fad09
  8 [-]: LOADK     R3 K3        ; R3 := "EE.Interface.Utilities"
  9 [-]: CALL      R2 2 2       ; R2 := R2(R3)
 10 [-]: GETGLOBAL R3 K0        ; R3 := 0x2d0fad09
 11 [-]: LOADK     R4 K4        ; R4 := "EE.Interface.AnchorMgr"
 12 [-]: CALL      R3 2 2       ; R3 := R3(R4)
 13 [-]: LOADKB    R4 0 0       ; R4 := false
 14 [-]: LOADKB    R5 1 0       ; R5 := true
 15 [-]: LOADNIL   R6 R7        ; R6 := R7 := nil
 16 [-]: CONST     R8 0         ; R8 := 0.000000
 17 [-]: CONST     R9 0         ; R9 := 0.000000
 18 [-]: LOADNIL   R10 R15      ; R10 := R11 := R12 := R13 := R14 := R15 := nil
 19 [-]: GETGLOBAL R16 K5       ; R16 := 0x60130201
 20 [-]: CALL      R16 1 2      ; R16 := R16()
 21 [-]: CONST     R17 0        ; R17 := 0.000000
 22 [-]: CONST     R18 0        ; R18 := 0.000000
 23 [-]: CONST     R19 0        ; R19 := 0.000000
 24 [-]: CONST     R20 0        ; R20 := 0.000000
 25 [-]: CONST     R21 1        ; R21 := 1.000000
 26 [-]: LOADNIL   R22 R22      ; R22 := nil
 27 [-]: LOADKB    R23 0 0      ; R23 := false
 28 [-]: LOADKB    R24 0 0      ; R24 := false
 29 [-]: LOADKB    R25 0 0      ; R25 := false
 30 [-]: LOADKB    R26 0 0      ; R26 := false
 31 [-]: LOADKB    R27 0 0      ; R27 := false
 32 [-]: LOADK     R28 K6       ; R28 := 0.200000
 33 [-]: LOADK     R29 K7       ; R29 := 0.030000
 34 [-]: CONST     R30 6        ; R30 := 6.000000
 35 [-]: CLOSURE   R31 0        ; R31 := closure(Function #1)
 36 [-]: CLOSURE   R32 1        ; R32 := closure(Function #2)
 37 [-]: MOVE      R0 R17       ; R0 := R17
 38 [-]: MOVE      R0 R18       ; R0 := R18
 39 [-]: MOVE      R0 R29       ; R0 := R29
 40 [-]: MOVE      R0 R28       ; R0 := R28
 41 [-]: MOVE      R0 R2        ; R0 := R2
 42 [-]: MOVE      R0 R31       ; R0 := R31
 43 [-]: CLOSURE   R33 2        ; R33 := closure(Function #3)
 44 [-]: MOVE      R0 R20       ; R0 := R20
 45 [-]: MOVE      R0 R2        ; R0 := R2
 46 [-]: MOVE      R0 R30       ; R0 := R30
 47 [-]: MOVE      R0 R21       ; R0 := R21
 48 [-]: MOVE      R0 R27       ; R0 := R27
 49 [-]: CLOSURE   R34 3        ; R34 := closure(Function #4)
 50 [-]: MOVE      R0 R12       ; R0 := R12
 51 [-]: MOVE      R0 R22       ; R0 := R22
 52 [-]: CLOSURE   R35 4        ; R35 := closure(Function #5)
 53 [-]: MOVE      R0 R4        ; R0 := R4
 54 [-]: MOVE      R0 R15       ; R0 := R15
 55 [-]: MOVE      R0 R1        ; R0 := R1
 56 [-]: MOVE      R0 R12       ; R0 := R12
 57 [-]: MOVE      R0 R27       ; R0 := R27
 58 [-]: MOVE      R0 R5        ; R0 := R5
 59 [-]: MOVE      R0 R2        ; R0 := R2
 60 [-]: MOVE      R0 R7        ; R0 := R7
 61 [-]: MOVE      R0 R9        ; R0 := R9
 62 [-]: MOVE      R0 R8        ; R0 := R8
 63 [-]: MOVE      R0 R18       ; R0 := R18
 64 [-]: MOVE      R0 R24       ; R0 := R24
 65 [-]: MOVE      R0 R25       ; R0 := R25
 66 [-]: MOVE      R0 R32       ; R0 := R32
 67 [-]: MOVE      R0 R23       ; R0 := R23
 68 [-]: MOVE      R0 R33       ; R0 := R33
 69 [-]: MOVE      R0 R19       ; R0 := R19
 70 [-]: MOVE      R0 R11       ; R0 := R11
 71 [-]: MOVE      R0 R26       ; R0 := R26
 72 [-]: MOVE      R0 R34       ; R0 := R34
 73 [-]: MOVE      R0 R10       ; R0 := R10
 74 [-]: MOVE      R0 R13       ; R0 := R13
 75 [-]: MOVE      R0 R14       ; R0 := R14
 76 [-]: SETGLOBAL R35 K8       ; Update := R35
 77 [-]: CLOSURE   R35 5        ; R35 := closure(Function #6)
 78 [-]: SETGLOBAL R35 K9       ; OnProfileSaved := R35
 79 [-]: CLOSURE   R35 6        ; R35 := closure(Function #7)
 80 [-]: MOVE      R0 R6        ; R0 := R6
 81 [-]: SETGLOBAL R35 K10      ; onViewportSizeChanged := R35
 82 [-]: CLOSURE   R35 7        ; R35 := closure(Function #8)
 83 [-]: SETGLOBAL R35 K11      ; Shutdown := R35
 84 [-]: CLOSURE   R35 8        ; R35 := closure(Function #9)
 85 [-]: MOVE      R0 R6        ; R0 := R6
 86 [-]: MOVE      R0 R3        ; R0 := R3
 87 [-]: MOVE      R0 R4        ; R0 := R4
 88 [-]: SETGLOBAL R35 K12      ; Initialize := R35
 89 [-]: CLOSURE   R35 9        ; R35 := closure(Function #10)
 90 [-]: MOVE      R0 R7        ; R0 := R7
 91 [-]: MOVE      R0 R0        ; R0 := R0
 92 [-]: MOVE      R0 R9        ; R0 := R9
 93 [-]: MOVE      R0 R8        ; R0 := R8
 94 [-]: MOVE      R0 R16       ; R0 := R16
 95 [-]: MOVE      R0 R18       ; R0 := R18
 96 [-]: MOVE      R0 R2        ; R0 := R2
 97 [-]: MOVE      R0 R27       ; R0 := R27
 98 [-]: MOVE      R0 R32       ; R0 := R32
 99 [-]: MOVE      R0 R31       ; R0 := R31
100 [-]: SETGLOBAL R35 K13      ; SetWeapon := R35
101 [-]: CLOSURE   R35 10       ; R35 := closure(Function #11)
102 [-]: MOVE      R0 R23       ; R0 := R23
103 [-]: MOVE      R0 R19       ; R0 := R19
104 [-]: MOVE      R0 R20       ; R0 := R20
105 [-]: MOVE      R0 R2        ; R0 := R2
106 [-]: MOVE      R0 R27       ; R0 := R27
107 [-]: MOVE      R0 R24       ; R0 := R24
108 [-]: MOVE      R0 R26       ; R0 := R26
109 [-]: MOVE      R0 R33       ; R0 := R33
110 [-]: MOVE      R0 R25       ; R0 := R25
111 [-]: SETGLOBAL R35 K14      ; SetAiming := R35
112 [-]: CLOSURE   R35 11       ; R35 := closure(Function #12)
113 [-]: SETGLOBAL R35 K15      ; SetEnabled := R35
114 [-]: CLOSURE   R35 12       ; R35 := closure(Function #13)
115 [-]: SETGLOBAL R35 K16      ; OnFire := R35
116 [-]: CLOSURE   R35 13       ; R35 := closure(Function #14)
117 [-]: SETGLOBAL R35 K17      ; ClearCustomReticleAiming := R35
118 [-]: CLOSURE   R35 14       ; R35 := closure(Function #15)
119 [-]: SETGLOBAL R35 K18      ; UpdateRangeFinder := R35
120 [-]: CLOSURE   R35 15       ; R35 := closure(Function #16)
121 [-]: SETGLOBAL R35 K19      ; ScanUpdate := R35
122 [-]: CLOSURE   R35 16       ; R35 := closure(Function #17)
123 [-]: SETGLOBAL R35 K20      ; HitNotificationAlwaysEnabled := R35
124 [-]: CLOSURE   R35 17       ; R35 := closure(Function #18)
125 [-]: MOVE      R0 R15       ; R0 := R15
126 [-]: SETGLOBAL R35 K21      ; HandleHudScale := R35
127 [-]: RETURN    R0 1         ; return 


; Function #1:
;
; Name:            
; Defined at line: 38
; #Upvalues:       0
; #Parameters:     0
; Is_vararg:       0
; Max Stack Size:  5

  1 [-]: GETGLOBAL R0 K0        ; R0 := 0xae91e43b
  2 [-]: SELF      R0 R0 K1     ; R1 := R0; R0 := R0[0x67bc869f]
  3 [-]: LOADK     R2 K2        ; R2 := "Charge.Bg"
  4 [-]: CONST     R3 9         ; R3 := 9.000000
  5 [-]: GETGLOBAL R4 K3        ; R4 := 0x0032441c
  6 [-]: GETTABLE  R4 R4 K4     ; R4 := R4["UIColor_DarkGrey"]
  7 [-]: CALL      R0 5 1       ; R0(R1,R2,R3,R4)
  8 [-]: GETGLOBAL R0 K0        ; R0 := 0xae91e43b
  9 [-]: SELF      R0 R0 K1     ; R1 := R0; R0 := R0[0x67bc869f]
 10 [-]: LOADK     R2 K5        ; R2 := "Charge.Fill"
 11 [-]: CONST     R3 9         ; R3 := 9.000000
 12 [-]: GETGLOBAL R4 K3        ; R4 := 0x0032441c
 13 [-]: GETTABLE  R4 R4 K6     ; R4 := R4["UIColor_White"]
 14 [-]: CALL      R0 5 1       ; R0(R1,R2,R3,R4)
 15 [-]: GETGLOBAL R0 K0        ; R0 := 0xae91e43b
 16 [-]: SELF      R0 R0 K1     ; R1 := R0; R0 := R0[0x67bc869f]
 17 [-]: LOADK     R2 K7        ; R2 := "Charge.ChargeGlow"
 18 [-]: CONST     R3 9         ; R3 := 9.000000
 19 [-]: GETGLOBAL R4 K3        ; R4 := 0x0032441c
 20 [-]: GETTABLE  R4 R4 K6     ; R4 := R4["UIColor_White"]
 21 [-]: CALL      R0 5 1       ; R0(R1,R2,R3,R4)
 22 [-]: GETGLOBAL R0 K0        ; R0 := 0xae91e43b
 23 [-]: SELF      R0 R0 K8     ; R1 := R0; R0 := R0[0xd5181643]
 24 [-]: LOADK     R2 K7        ; R2 := "Charge.ChargeGlow"
 25 [-]: GETGLOBAL R3 K9        ; R3 := 0xa16da3a2
 26 [-]: CALL      R0 4 1       ; R0(R1,R2,R3)
 27 [-]: RETURN    R0 1         ; return 


; Function #2:
;
; Name:            
; Defined at line: 45
; #Upvalues:       6
; #Parameters:     1
; Is_vararg:       0
; Max Stack Size:  7

  1 [-]: GETUPVAL  R1 U0        ; R1 := U0
  2 [-]: GETUPVAL  R2 U1        ; R2 := U1
  3 [-]: EQ        1 R1 R2      ; if R1 == R2 then PC := 45
  4 [-]: JMP       45           ; PC := 45
  5 [-]: GETUPVAL  R1 U1        ; R1 := U1
  6 [-]: GETUPVAL  R2 U0        ; R2 := U0
  7 [-]: SUB       R1 R1 R2     ; R1 := R1 - R2
  8 [-]: TEST      R0 1         ; if R0 then PC := 17
  9 [-]: JMP       17           ; PC := 17
 10 [-]: GETGLOBAL R2 K0        ; R2 := 0x5bced4c4
 11 [-]: GETTABLE  R2 R2 K1     ; R2 := R2[0xe4a5b3ca]
 12 [-]: MOVE      R3 R1        ; R3 := R1
 13 [-]: CALL      R2 2 2       ; R2 := R2(R3)
 14 [-]: GETUPVAL  R3 U2        ; R3 := U2
 15 [-]: LE        0 R2 R3      ; if R2 > R3 then PC := 20
 16 [-]: JMP       20           ; PC := 20
 17 [-]: GETUPVAL  R2 U1        ; R2 := U1
 18 [-]: SETUPVAL  R2 U0        ; U82 := R0
 19 [-]: JMP       25           ; PC := 25
 20 [-]: GETUPVAL  R2 U0        ; R2 := U0
 21 [-]: GETUPVAL  R3 U3        ; R3 := U3
 22 [-]: MUL       R3 R1 R3     ; R3 := R1 * R3
 23 [-]: ADD       R2 R2 R3     ; R2 := R2 + R3
 24 [-]: SETUPVAL  R2 U0        ; U82 := R0
 25 [-]: GETGLOBAL R2 K2        ; R2 := 0x42dcc9f5
 26 [-]: GETUPVAL  R3 U4        ; R3 := U4
 27 [-]: GETTABLE  R3 R3 K3     ; R3 := R3[0x74a11ec6]
 28 [-]: GETUPVAL  R4 U0        ; R4 := U0
 29 [-]: MUL       R4 R4 K4     ; R4 := R4 * 100.000000
 30 [-]: CALL      R3 2 2       ; R3 := R3(R4)
 31 [-]: CONST     R4 1         ; R4 := 1.000000
 32 [-]: CONST     R5 100       ; R5 := 100.000000
 33 [-]: CALL      R2 4 2       ; R2 := R2(R3,R4,R5)
 34 [-]: GETGLOBAL R3 K5        ; R3 := 0x38f10e85
 35 [-]: GETGLOBAL R4 K6        ; R4 := 0xae91e43b
 36 [-]: LOADK     R5 K7        ; R5 := "Charge.gotoAndStop"
 37 [-]: MOVE      R6 R2        ; R6 := R2
 38 [-]: CALL      R3 4 1       ; R3(R4,R5,R6)
 39 [-]: EQ        1 R2 K8      ; if R2 == 1.000000 then PC := 43
 40 [-]: JMP       43           ; PC := 43
 41 [-]: EQ        0 R2 K4      ; if R2 ~= 100.000000 then PC := 45
 42 [-]: JMP       45           ; PC := 45
 43 [-]: GETUPVAL  R3 U5        ; R3 := U5
 44 [-]: CALL      R3 1 1       ; R3()
 45 [-]: RETURN    R0 1         ; return 


; Function #3:
;
; Name:            
; Defined at line: 63
; #Upvalues:       5
; #Parameters:     1
; Is_vararg:       0
; Max Stack Size:  6

  1 [-]: GETGLOBAL R1 K0        ; R1 := 0x42dcc9f5
  2 [-]: GETUPVAL  R2 U0        ; R2 := U0
  3 [-]: ADD       R2 R2 R0     ; R2 := R2 + R0
  4 [-]: CONST     R3 0         ; R3 := 0.000000
  5 [-]: CONST     R4 1         ; R4 := 1.000000
  6 [-]: CALL      R1 4 2       ; R1 := R1(R2,R3,R4)
  7 [-]: SETUPVAL  R1 U0        ; U82 := R0
  8 [-]: GETUPVAL  R1 U1        ; R1 := U1
  9 [-]: GETTABLE  R1 R1 K1     ; R1 := R1[0x74a11ec6]
 10 [-]: GETUPVAL  R2 U0        ; R2 := U0
 11 [-]: GETUPVAL  R3 U2        ; R3 := U2
 12 [-]: SUB       R3 R3 K2     ; R3 := R3 - 1.000000
 13 [-]: MUL       R2 R2 R3     ; R2 := R2 * R3
 14 [-]: CALL      R1 2 2       ; R1 := R1(R2)
 15 [-]: ADD       R1 K2 R1     ; R1 := 1.000000 + R1
 16 [-]: GETUPVAL  R2 U3        ; R2 := U3
 17 [-]: EQ        1 R1 R2      ; if R1 == R2 then PC := 34
 18 [-]: JMP       34           ; PC := 34
 19 [-]: GETUPVAL  R2 U4        ; R2 := U4
 20 [-]: TEST      R2 0         ; if not R2 then PC := 28
 21 [-]: JMP       28           ; PC := 28
 22 [-]: GETGLOBAL R2 K3        ; R2 := 0x38f10e85
 23 [-]: GETGLOBAL R3 K4        ; R3 := 0xae91e43b
 24 [-]: LOADK     R4 K5        ; R4 := "ReticleArchwing.gotoAndStop"
 25 [-]: MOVE      R5 R1        ; R5 := R1
 26 [-]: CALL      R2 4 1       ; R2(R3,R4,R5)
 27 [-]: JMP       33           ; PC := 33
 28 [-]: GETGLOBAL R2 K3        ; R2 := 0x38f10e85
 29 [-]: GETGLOBAL R3 K4        ; R3 := 0xae91e43b
 30 [-]: LOADK     R4 K6        ; R4 := "ReticleNormal.gotoAndStop"
 31 [-]: MOVE      R5 R1        ; R5 := R1
 32 [-]: CALL      R2 4 1       ; R2(R3,R4,R5)
 33 [-]: SETUPVAL  R1 U3        ; U82 := R3
 34 [-]: RETURN    R0 1         ; return 


; Function #4:
;
; Name:            
; Defined at line: 76
; #Upvalues:       2
; #Parameters:     0
; Is_vararg:       0
; Max Stack Size:  7

  1 [-]: GETGLOBAL R0 K0        ; R0 := 0x7b998233
  2 [-]: GETUPVAL  R1 U0        ; R1 := U0
  3 [-]: CALL      R0 2 2       ; R0 := R0(R1)
  4 [-]: TEST      R0 0         ; if not R0 then PC := 7
  5 [-]: JMP       7            ; PC := 7
  6 [-]: RETURN    R0 1         ; return 
  7 [-]: GETUPVAL  R0 U0        ; R0 := U0
  8 [-]: SELF      R0 R0 K1     ; R1 := R0; R0 := R0[0xde321e6f]
  9 [-]: CALL      R0 2 2       ; R0 := R0(R1)
 10 [-]: SELF      R0 R0 K2     ; R1 := R0; R0 := R0[0x7c09e541]
 11 [-]: CALL      R0 2 2       ; R0 := R0(R1)
 12 [-]: GETGLOBAL R1 K3        ; R1 := 0x0032441c
 13 [-]: GETTABLE  R1 R1 K4     ; R1 := R1["UIColor_White"]
 14 [-]: GETGLOBAL R2 K0        ; R2 := 0x7b998233
 15 [-]: MOVE      R3 R0        ; R3 := R0
 16 [-]: CALL      R2 2 2       ; R2 := R2(R3)
 17 [-]: TEST      R2 1         ; if R2 then PC := 39
 18 [-]: JMP       39           ; PC := 39
 19 [-]: SELF      R2 R0 K5     ; R3 := R0; R2 := R0[0xf2deaf69]
 20 [-]: GETGLOBAL R4 K6        ; R4 := gBaseAvatarType
 21 [-]: CALL      R2 3 2       ; R2 := R2(R3,R4)
 22 [-]: TEST      R2 0         ; if not R2 then PC := 39
 23 [-]: JMP       39           ; PC := 39
 24 [-]: SELF      R2 R0 K7     ; R3 := R0; R2 := R0[0x827a46e3]
 25 [-]: CALL      R2 2 2       ; R2 := R2(R3)
 26 [-]: TEST      R2 1         ; if R2 then PC := 39
 27 [-]: JMP       39           ; PC := 39
 28 [-]: SELF      R2 R0 K8     ; R3 := R0; R2 := R0[0x808b79e6]
 29 [-]: CALL      R2 2 2       ; R2 := R2(R3)
 30 [-]: GETUPVAL  R3 U0        ; R3 := U0
 31 [-]: SELF      R3 R3 K8     ; R4 := R3; R3 := R3[0x808b79e6]
 32 [-]: CALL      R3 2 2       ; R3 := R3(R4)
 33 [-]: EQ        0 R2 R3      ; if R2 ~= R3 then PC := 37
 34 [-]: JMP       37           ; PC := 37
 35 [-]: LOADK     R1 K9        ; R1 := 431318.000000
 36 [-]: JMP       39           ; PC := 39
 37 [-]: GETGLOBAL R2 K3        ; R2 := 0x0032441c
 38 [-]: GETTABLE  R1 R2 K10    ; R1 := R2["UIColor_Red"]
 39 [-]: GETUPVAL  R2 U1        ; R2 := U1
 40 [-]: EQ        1 R1 R2      ; if R1 == R2 then PC := 67
 41 [-]: JMP       67           ; PC := 67
 42 [-]: SETUPVAL  R1 U1        ; U82 := R1
 43 [-]: GETGLOBAL R2 K11       ; R2 := 0xae91e43b
 44 [-]: SELF      R2 R2 K12    ; R3 := R2; R2 := R2[0x67bc869f]
 45 [-]: LOADK     R4 K13       ; R4 := "ReticleNormal"
 46 [-]: CONST     R5 9         ; R5 := 9.000000
 47 [-]: MOVE      R6 R1        ; R6 := R1
 48 [-]: CALL      R2 5 1       ; R2(R3,R4,R5,R6)
 49 [-]: GETGLOBAL R2 K11       ; R2 := 0xae91e43b
 50 [-]: SELF      R2 R2 K12    ; R3 := R2; R2 := R2[0x67bc869f]
 51 [-]: LOADK     R4 K14       ; R4 := "ReticleArchwing"
 52 [-]: CONST     R5 9         ; R5 := 9.000000
 53 [-]: MOVE      R6 R1        ; R6 := R1
 54 [-]: CALL      R2 5 1       ; R2(R3,R4,R5,R6)
 55 [-]: GETGLOBAL R2 K11       ; R2 := 0xae91e43b
 56 [-]: SELF      R2 R2 K12    ; R3 := R2; R2 := R2[0x67bc869f]
 57 [-]: LOADK     R4 K15       ; R4 := "ReticleLockOn.LockedOnXRight"
 58 [-]: CONST     R5 9         ; R5 := 9.000000
 59 [-]: MOVE      R6 R1        ; R6 := R1
 60 [-]: CALL      R2 5 1       ; R2(R3,R4,R5,R6)
 61 [-]: GETGLOBAL R2 K11       ; R2 := 0xae91e43b
 62 [-]: SELF      R2 R2 K12    ; R3 := R2; R2 := R2[0x67bc869f]
 63 [-]: LOADK     R4 K16       ; R4 := "ReticleLockOn.LockedOnXLeft"
 64 [-]: CONST     R5 9         ; R5 := 9.000000
 65 [-]: MOVE      R6 R1        ; R6 := R1
 66 [-]: CALL      R2 5 1       ; R2(R3,R4,R5,R6)
 67 [-]: RETURN    R0 1         ; return 


; Function #5:
;
; Name:            
; Defined at line: 103
; #Upvalues:       23
; #Parameters:     0
; Is_vararg:       0
; Max Stack Size:  23

  1 [-]: GETGLOBAL R0 K0        ; R0 := 0x7b998233
  2 [-]: GETGLOBAL R1 K1        ; R1 := 0xae91e43b
  3 [-]: CALL      R0 2 2       ; R0 := R0(R1)
  4 [-]: TEST      R0 1         ; if R0 then PC := 9
  5 [-]: JMP       9            ; PC := 9
  6 [-]: GETUPVAL  R0 U0        ; R0 := U0
  7 [-]: TEST      R0 1         ; if R0 then PC := 10
  8 [-]: JMP       10           ; PC := 10
  9 [-]: RETURN    R0 1         ; return 
 10 [-]: GETGLOBAL R0 K2        ; R0 := 0x67652851
 11 [-]: CALL      R0 1 2       ; R0 := R0()
 12 [-]: GETGLOBAL R1 K1        ; R1 := 0xae91e43b
 13 [-]: SELF      R1 R1 K3     ; R2 := R1; R1 := R1[0x8a8c8d5a]
 14 [-]: MOVE      R3 R0        ; R3 := R0
 15 [-]: CALL      R1 3 1       ; R1(R2,R3)
 16 [-]: GETUPVAL  R1 U1        ; R1 := U1
 17 [-]: EQ        1 R1 K4      ; if R1 == nil then PC := 26
 18 [-]: JMP       26           ; PC := 26
 19 [-]: GETUPVAL  R1 U2        ; R1 := U2
 20 [-]: GETTABLE  R1 R1 K5     ; R1 := R1[0xfa221145]
 21 [-]: GETGLOBAL R2 K1        ; R2 := 0xae91e43b
 22 [-]: GETUPVAL  R3 U1        ; R3 := U1
 23 [-]: CALL      R1 3 1       ; R1(R2,R3)
 24 [-]: LOADNIL   R1 R1        ; R1 := nil
 25 [-]: SETUPVAL  R1 U1        ; U82 := R1
 26 [-]: GETGLOBAL R1 K0        ; R1 := 0x7b998233
 27 [-]: GETUPVAL  R2 U3        ; R2 := U3
 28 [-]: CALL      R1 2 2       ; R1 := R1(R2)
 29 [-]: TEST      R1 0         ; if not R1 then PC := 35
 30 [-]: JMP       35           ; PC := 35
 31 [-]: GETGLOBAL R1 K6        ; R1 := 0x89326c93
 32 [-]: SELF      R1 R1 K7     ; R2 := R1; R1 := R1[0x78298275]
 33 [-]: CALL      R1 2 2       ; R1 := R1(R2)
 34 [-]: SETUPVAL  R1 U3        ; U82 := R3
 35 [-]: LOADNIL   R1 R4        ; R1 := R2 := R3 := R4 := nil
 36 [-]: GETGLOBAL R5 K0        ; R5 := 0x7b998233
 37 [-]: GETUPVAL  R6 U3        ; R6 := U3
 38 [-]: CALL      R5 2 2       ; R5 := R5(R6)
 39 [-]: TEST      R5 1         ; if R5 then PC := 69
 40 [-]: JMP       69           ; PC := 69
 41 [-]: GETUPVAL  R5 U3        ; R5 := U3
 42 [-]: SELF      R5 R5 K8     ; R6 := R5; R5 := R5[0xde321e6f]
 43 [-]: CALL      R5 2 2       ; R5 := R5(R6)
 44 [-]: SELF      R5 R5 K9     ; R6 := R5; R5 := R5[0xac03381f]
 45 [-]: CALL      R5 2 2       ; R5 := R5(R6)
 46 [-]: GETUPVAL  R6 U4        ; R6 := U4
 47 [-]: EQ        0 R5 R6      ; if R5 ~= R6 then PC := 52
 48 [-]: JMP       52           ; PC := 52
 49 [-]: GETUPVAL  R6 U5        ; R6 := U5
 50 [-]: TEST      R6 0         ; if not R6 then PC := 69
 51 [-]: JMP       69           ; PC := 69
 52 [-]: LOADKB    R6 0 0       ; R6 := false
 53 [-]: SETUPVAL  R6 U5        ; U82 := R5
 54 [-]: SETUPVAL  R5 U4        ; U82 := R4
 55 [-]: GETUPVAL  R6 U6        ; R6 := U6
 56 [-]: GETTABLE  R6 R6 K10    ; R6 := R6[0x06d055f9]
 57 [-]: GETUPVAL  R7 U4        ; R7 := U4
 58 [-]: CONST     R8 0         ; R8 := 0.000000
 59 [-]: CONST     R9 100       ; R9 := 100.000000
 60 [-]: CALL      R6 4 2       ; R6 := R6(R7,R8,R9)
 61 [-]: MOVE      R1 R6        ; R1 := R6
 62 [-]: GETUPVAL  R6 U6        ; R6 := U6
 63 [-]: GETTABLE  R6 R6 K10    ; R6 := R6[0x06d055f9]
 64 [-]: GETUPVAL  R7 U4        ; R7 := U4
 65 [-]: CONST     R8 100       ; R8 := 100.000000
 66 [-]: CONST     R9 0         ; R9 := 0.000000
 67 [-]: CALL      R6 4 2       ; R6 := R6(R7,R8,R9)
 68 [-]: MOVE      R2 R6        ; R2 := R6
 69 [-]: GETGLOBAL R6 K0        ; R6 := 0x7b998233
 70 [-]: GETUPVAL  R7 U7        ; R7 := U7
 71 [-]: CALL      R6 2 2       ; R6 := R6(R7)
 72 [-]: TEST      R6 1         ; if R6 then PC := 177
 73 [-]: JMP       177          ; PC := 177
 74 [-]: GETUPVAL  R6 U7        ; R6 := U7
 75 [-]: SELF      R6 R6 K11    ; R7 := R6; R6 := R6[0xb6fe179b]
 76 [-]: CALL      R6 2 2       ; R6 := R6(R7)
 77 [-]: GETUPVAL  R7 U7        ; R7 := U7
 78 [-]: SELF      R7 R7 K12    ; R8 := R7; R7 := R7[0x189cf7d1]
 79 [-]: CALL      R7 2 2       ; R7 := R7(R8)
 80 [-]: SETUPVAL  R7 U8        ; U82 := R8
 81 [-]: GETUPVAL  R7 U9        ; R7 := U9
 82 [-]: EQ        1 R7 R6      ; if R7 == R6 then PC := 88
 83 [-]: JMP       88           ; PC := 88
 84 [-]: GETUPVAL  R7 U8        ; R7 := U8
 85 [-]: DIV       R7 R6 R7     ; R7 := R6 / R7
 86 [-]: SETUPVAL  R7 U10       ; U82 := R10
 87 [-]: SETUPVAL  R6 U9        ; U82 := R9
 88 [-]: GETUPVAL  R7 U7        ; R7 := U7
 89 [-]: SELF      R7 R7 K13    ; R8 := R7; R7 := R7[0x6bb20d05]
 90 [-]: CALL      R7 2 2       ; R7 := R7(R8)
 91 [-]: GETUPVAL  R8 U11       ; R8 := U11
 92 [-]: EQ        1 R7 R8      ; if R7 == R8 then PC := 130
 93 [-]: JMP       130          ; PC := 130
 94 [-]: SETUPVAL  R7 U11       ; U82 := R11
 95 [-]: GETUPVAL  R8 U6        ; R8 := U6
 96 [-]: GETTABLE  R8 R8 K10    ; R8 := R8[0x06d055f9]
 97 [-]: GETUPVAL  R9 U11       ; R9 := U11
 98 [-]: CONST     R10 100      ; R10 := 100.000000
 99 [-]: CONST     R11 0        ; R11 := 0.000000
100 [-]: CALL      R8 4 2       ; R8 := R8(R9,R10,R11)
101 [-]: MOVE      R3 R8        ; R3 := R8
102 [-]: GETUPVAL  R8 U6        ; R8 := U6
103 [-]: GETTABLE  R8 R8 K10    ; R8 := R8[0x06d055f9]
104 [-]: GETUPVAL  R9 U11       ; R9 := U11
105 [-]: TEST      R9 1         ; if R9 then PC := 108
106 [-]: JMP       108          ; PC := 108
107 [-]: GETUPVAL  R9 U4        ; R9 := U4
108 [-]: CONST     R10 0        ; R10 := 0.000000
109 [-]: CONST     R11 100      ; R11 := 100.000000
110 [-]: CALL      R8 4 2       ; R8 := R8(R9,R10,R11)
111 [-]: MOVE      R1 R8        ; R1 := R8
112 [-]: GETUPVAL  R8 U6        ; R8 := U6
113 [-]: GETTABLE  R8 R8 K10    ; R8 := R8[0x06d055f9]
114 [-]: GETUPVAL  R9 U11       ; R9 := U11
115 [-]: TEST      R9 1         ; if R9 then PC := 119
116 [-]: JMP       119          ; PC := 119
117 [-]: GETUPVAL  R9 U4        ; R9 := U4
118 [-]: NOT       R9 R9        ; R9 :=  R9
119 [-]: CONST     R10 0        ; R10 := 0.000000
120 [-]: CONST     R11 100      ; R11 := 100.000000
121 [-]: CALL      R8 4 2       ; R8 := R8(R9,R10,R11)
122 [-]: MOVE      R2 R8        ; R2 := R8
123 [-]: GETUPVAL  R8 U6        ; R8 := U6
124 [-]: GETTABLE  R8 R8 K10    ; R8 := R8[0x06d055f9]
125 [-]: GETUPVAL  R9 U11       ; R9 := U11
126 [-]: CONST     R10 0        ; R10 := 0.000000
127 [-]: CONST     R11 100      ; R11 := 100.000000
128 [-]: CALL      R8 4 2       ; R8 := R8(R9,R10,R11)
129 [-]: MOVE      R4 R8        ; R4 := R8
130 [-]: GETUPVAL  R8 U7        ; R8 := U7
131 [-]: SELF      R8 R8 K14    ; R9 := R8; R8 := R8[0x5869a941]
132 [-]: CALL      R8 2 2       ; R8 := R8(R9)
133 [-]: GETUPVAL  R9 U12       ; R9 := U12
134 [-]: EQ        1 R8 R9      ; if R8 == R9 then PC := 175
135 [-]: JMP       175          ; PC := 175
136 [-]: SETUPVAL  R8 U12       ; U82 := R12
137 [-]: GETUPVAL  R9 U6        ; R9 := U6
138 [-]: GETTABLE  R9 R9 K10    ; R9 := R9[0x06d055f9]
139 [-]: GETUPVAL  R10 U12      ; R10 := U12
140 [-]: TEST      R10 1        ; if R10 then PC := 146
141 [-]: JMP       146          ; PC := 146
142 [-]: GETUPVAL  R10 U11      ; R10 := U11
143 [-]: TEST      R10 1        ; if R10 then PC := 146
144 [-]: JMP       146          ; PC := 146
145 [-]: GETUPVAL  R10 U4       ; R10 := U4
146 [-]: CONST     R11 0        ; R11 := 0.000000
147 [-]: CONST     R12 100      ; R12 := 100.000000
148 [-]: CALL      R9 4 2       ; R9 := R9(R10,R11,R12)
149 [-]: MOVE      R1 R9        ; R1 := R9
150 [-]: GETUPVAL  R9 U6        ; R9 := U6
151 [-]: GETTABLE  R9 R9 K10    ; R9 := R9[0x06d055f9]
152 [-]: GETUPVAL  R10 U12      ; R10 := U12
153 [-]: TEST      R10 1        ; if R10 then PC := 160
154 [-]: JMP       160          ; PC := 160
155 [-]: GETUPVAL  R10 U11      ; R10 := U11
156 [-]: TEST      R10 1        ; if R10 then PC := 160
157 [-]: JMP       160          ; PC := 160
158 [-]: GETUPVAL  R10 U4       ; R10 := U4
159 [-]: NOT       R10 R10      ; R10 :=  R10
160 [-]: CONST     R11 0        ; R11 := 0.000000
161 [-]: CONST     R12 100      ; R12 := 100.000000
162 [-]: CALL      R9 4 2       ; R9 := R9(R10,R11,R12)
163 [-]: MOVE      R2 R9        ; R2 := R9
164 [-]: GETUPVAL  R9 U6        ; R9 := U6
165 [-]: GETTABLE  R9 R9 K10    ; R9 := R9[0x06d055f9]
166 [-]: GETUPVAL  R10 U12      ; R10 := U12
167 [-]: TEST      R10 1        ; if R10 then PC := 171
168 [-]: JMP       171          ; PC := 171
169 [-]: GETUPVAL  R10 U11      ; R10 := U11
170 [-]: NOT       R10 R10      ; R10 :=  R10
171 [-]: CONST     R11 0        ; R11 := 0.000000
172 [-]: CONST     R12 100      ; R12 := 100.000000
173 [-]: CALL      R9 4 2       ; R9 := R9(R10,R11,R12)
174 [-]: MOVE      R3 R9        ; R3 := R9
175 [-]: GETUPVAL  R9 U13       ; R9 := U13
176 [-]: CALL      R9 1 1       ; R9()
177 [-]: EQ        1 R1 K4      ; if R1 == nil then PC := 201
178 [-]: JMP       201          ; PC := 201
179 [-]: GETGLOBAL R9 K1        ; R9 := 0xae91e43b
180 [-]: SELF      R9 R9 K15    ; R10 := R9; R9 := R9[0xaf5300dc]
181 [-]: LOADK     R11 K16      ; R11 := "ReticleNormal"
182 [-]: CALL      R9 3 1       ; R9(R10,R11)
183 [-]: GETUPVAL  R9 U14       ; R9 := U14
184 [-]: TEST      R9 0         ; if not R9 then PC := 191
185 [-]: JMP       191          ; PC := 191
186 [-]: GETUPVAL  R9 U15       ; R9 := U15
187 [-]: GETUPVAL  R10 U16      ; R10 := U16
188 [-]: SUB       R10 K17 R10  ; R10 := 1.000000 - R10
189 [-]: CALL      R9 2 1       ; R9(R10)
190 [-]: JMP       195          ; PC := 195
191 [-]: GETUPVAL  R9 U15       ; R9 := U15
192 [-]: GETUPVAL  R10 U16      ; R10 := U16
193 [-]: UNM       R10 R10      ; R10 :=  R10
194 [-]: CALL      R9 2 1       ; R9(R10)
195 [-]: GETGLOBAL R9 K1        ; R9 := 0xae91e43b
196 [-]: SELF      R9 R9 K18    ; R10 := R9; R9 := R9[0x67bc869f]
197 [-]: LOADK     R11 K16      ; R11 := "ReticleNormal"
198 [-]: CONST     R12 10       ; R12 := 10.000000
199 [-]: MOVE      R13 R1       ; R13 := R1
200 [-]: CALL      R9 5 1       ; R9(R10,R11,R12,R13)
201 [-]: EQ        1 R2 K4      ; if R2 == nil then PC := 225
202 [-]: JMP       225          ; PC := 225
203 [-]: GETGLOBAL R9 K1        ; R9 := 0xae91e43b
204 [-]: SELF      R9 R9 K15    ; R10 := R9; R9 := R9[0xaf5300dc]
205 [-]: LOADK     R11 K19      ; R11 := "ReticleArchwing"
206 [-]: CALL      R9 3 1       ; R9(R10,R11)
207 [-]: GETUPVAL  R9 U14       ; R9 := U14
208 [-]: TEST      R9 0         ; if not R9 then PC := 215
209 [-]: JMP       215          ; PC := 215
210 [-]: GETUPVAL  R9 U15       ; R9 := U15
211 [-]: GETUPVAL  R10 U16      ; R10 := U16
212 [-]: SUB       R10 K17 R10  ; R10 := 1.000000 - R10
213 [-]: CALL      R9 2 1       ; R9(R10)
214 [-]: JMP       219          ; PC := 219
215 [-]: GETUPVAL  R9 U15       ; R9 := U15
216 [-]: GETUPVAL  R10 U16      ; R10 := U16
217 [-]: UNM       R10 R10      ; R10 :=  R10
218 [-]: CALL      R9 2 1       ; R9(R10)
219 [-]: GETGLOBAL R9 K1        ; R9 := 0xae91e43b
220 [-]: SELF      R9 R9 K18    ; R10 := R9; R9 := R9[0x67bc869f]
221 [-]: LOADK     R11 K19      ; R11 := "ReticleArchwing"
222 [-]: CONST     R12 10       ; R12 := 10.000000
223 [-]: MOVE      R13 R2       ; R13 := R2
224 [-]: CALL      R9 5 1       ; R9(R10,R11,R12,R13)
225 [-]: EQ        1 R3 K4      ; if R3 == nil then PC := 237
226 [-]: JMP       237          ; PC := 237
227 [-]: GETGLOBAL R9 K1        ; R9 := 0xae91e43b
228 [-]: SELF      R9 R9 K15    ; R10 := R9; R9 := R9[0xaf5300dc]
229 [-]: LOADK     R11 K20      ; R11 := "ReticleLockOn"
230 [-]: CALL      R9 3 1       ; R9(R10,R11)
231 [-]: GETGLOBAL R9 K1        ; R9 := 0xae91e43b
232 [-]: SELF      R9 R9 K18    ; R10 := R9; R9 := R9[0x67bc869f]
233 [-]: LOADK     R11 K20      ; R11 := "ReticleLockOn"
234 [-]: CONST     R12 10       ; R12 := 10.000000
235 [-]: MOVE      R13 R3       ; R13 := R3
236 [-]: CALL      R9 5 1       ; R9(R10,R11,R12,R13)
237 [-]: EQ        1 R4 K4      ; if R4 == nil then PC := 245
238 [-]: JMP       245          ; PC := 245
239 [-]: GETGLOBAL R9 K1        ; R9 := 0xae91e43b
240 [-]: SELF      R9 R9 K18    ; R10 := R9; R9 := R9[0x67bc869f]
241 [-]: LOADK     R11 K21      ; R11 := "Charge"
242 [-]: CONST     R12 10       ; R12 := 10.000000
243 [-]: MOVE      R13 R4       ; R13 := R4
244 [-]: CALL      R9 5 1       ; R9(R10,R11,R12,R13)
245 [-]: GETGLOBAL R9 K0        ; R9 := 0x7b998233
246 [-]: GETUPVAL  R10 U17      ; R10 := U17
247 [-]: CALL      R9 2 2       ; R9 := R9(R10)
248 [-]: TEST      R9 0         ; if not R9 then PC := 261
249 [-]: JMP       261          ; PC := 261
250 [-]: GETGLOBAL R9 K6        ; R9 := 0x89326c93
251 [-]: SELF      R9 R9 K22    ; R10 := R9; R9 := R9[0xfb64e76c]
252 [-]: CALL      R9 2 2       ; R9 := R9(R10)
253 [-]: GETGLOBAL R10 K0       ; R10 := 0x7b998233
254 [-]: MOVE      R11 R9       ; R11 := R9
255 [-]: CALL      R10 2 2      ; R10 := R10(R11)
256 [-]: TEST      R10 1        ; if R10 then PC := 261
257 [-]: JMP       261          ; PC := 261
258 [-]: SELF      R10 R9 K23   ; R11 := R9; R10 := R9[0x0803eee1]
259 [-]: CALL      R10 2 2      ; R10 := R10(R11)
260 [-]: SETUPVAL  R10 U17      ; U82 := R17
261 [-]: GETGLOBAL R10 K0       ; R10 := 0x7b998233
262 [-]: GETUPVAL  R11 U17      ; R11 := U17
263 [-]: CALL      R10 2 2      ; R10 := R10(R11)
264 [-]: TEST      R10 1        ; if R10 then PC := 408
265 [-]: JMP       408          ; PC := 408
266 [-]: GETUPVAL  R10 U17      ; R10 := U17
267 [-]: SELF      R10 R10 K24  ; R11 := R10; R10 := R10[0x2caa2b4e]
268 [-]: CALL      R10 2 2      ; R10 := R10(R11)
269 [-]: GETUPVAL  R11 U18      ; R11 := U18
270 [-]: EQ        1 R10 R11    ; if R10 == R11 then PC := 408
271 [-]: JMP       408          ; PC := 408
272 [-]: SETUPVAL  R10 U18      ; U82 := R18
273 [-]: GETGLOBAL R11 K1       ; R11 := 0xae91e43b
274 [-]: SELF      R11 R11 K15  ; R12 := R11; R11 := R11[0xaf5300dc]
275 [-]: LOADK     R13 K16      ; R13 := "ReticleNormal"
276 [-]: CALL      R11 3 1      ; R11(R12,R13)
277 [-]: GETGLOBAL R11 K1       ; R11 := 0xae91e43b
278 [-]: SELF      R11 R11 K15  ; R12 := R11; R11 := R11[0xaf5300dc]
279 [-]: LOADK     R13 K19      ; R13 := "ReticleArchwing"
280 [-]: CALL      R11 3 1      ; R11(R12,R13)
281 [-]: GETGLOBAL R11 K1       ; R11 := 0xae91e43b
282 [-]: SELF      R11 R11 K15  ; R12 := R11; R11 := R11[0xaf5300dc]
283 [-]: LOADK     R13 K20      ; R13 := "ReticleLockOn"
284 [-]: CALL      R11 3 1      ; R11(R12,R13)
285 [-]: GETGLOBAL R11 K25      ; R11 := 0x38f10e85
286 [-]: GETGLOBAL R12 K1       ; R12 := 0xae91e43b
287 [-]: LOADK     R13 K26      ; R13 := "ReticleNormal.gotoAndStop"
288 [-]: CONST     R14 1        ; R14 := 1.000000
289 [-]: CALL      R11 4 1      ; R11(R12,R13,R14)
290 [-]: GETUPVAL  R11 U11      ; R11 := U11
291 [-]: TEST      R11 0        ; if not R11 then PC := 311
292 [-]: JMP       311          ; PC := 311
293 [-]: GETGLOBAL R11 K27      ; R11 := 0x25312c9b
294 [-]: GETGLOBAL R12 K1       ; R12 := 0xae91e43b
295 [-]: LOADK     R13 K20      ; R13 := "ReticleLockOn"
296 [-]: CONST     R14 0        ; R14 := 0.000000
297 [-]: NEWTABLE  R15 1 0      ; R15 := {}
298 [-]: CONST     R16 10       ; R16 := 10.000000
299 [-]: SETLIST   R15 1 1      ; R15[(1-1)*FPF+i] := R(15+i), 1 <= i <= 1
300 [-]: NEWTABLE  R16 0 0      ; R16 := {}
301 [-]: GETUPVAL  R17 U6       ; R17 := U6
302 [-]: GETTABLE  R17 R17 K10  ; R17 := R17[0x06d055f9]
303 [-]: GETUPVAL  R18 U18      ; R18 := U18
304 [-]: CONST     R19 25       ; R19 := 25.000000
305 [-]: CONST     R20 100      ; R20 := 100.000000
306 [-]: CALL      R17 4 0      ; R17,... := R17(R18,R19,R20)
307 [-]: SETLIST   R16 0 1      ; R16[(1-1)*FPF+i] := R(16+i), 1 <= i <= 0
308 [-]: CONST     R17 0        ; R17 := 0.500000
309 [-]: CALL      R11 7 1      ; R11(R12,R13,R14,R15,R16,R17)
310 [-]: JMP       408          ; PC := 408
311 [-]: GETUPVAL  R11 U6       ; R11 := U6
312 [-]: GETTABLE  R11 R11 K10  ; R11 := R11[0x06d055f9]
313 [-]: GETUPVAL  R12 U4       ; R12 := U4
314 [-]: LOADK     R13 K19      ; R13 := "ReticleArchwing"
315 [-]: LOADK     R14 K16      ; R14 := "ReticleNormal"
316 [-]: CALL      R11 4 2      ; R11 := R11(R12,R13,R14)
317 [-]: GETUPVAL  R12 U12      ; R12 := U12
318 [-]: TEST      R12 0        ; if not R12 then PC := 347
319 [-]: JMP       347          ; PC := 347
320 [-]: GETGLOBAL R12 K27      ; R12 := 0x25312c9b
321 [-]: GETGLOBAL R13 K1       ; R13 := 0xae91e43b
322 [-]: MOVE      R14 R11      ; R14 := R11
323 [-]: CONST     R15 0        ; R15 := 0.000000
324 [-]: NEWTABLE  R16 1 0      ; R16 := {}
325 [-]: GETUPVAL  R17 U15      ; R17 := U15
326 [-]: SETLIST   R16 1 1      ; R16[(1-1)*FPF+i] := R(16+i), 1 <= i <= 1
327 [-]: NEWTABLE  R17 1 0      ; R17 := {}
328 [-]: GETUPVAL  R18 U16      ; R18 := U16
329 [-]: SUB       R18 K17 R18  ; R18 := 1.000000 - R18
330 [-]: SETLIST   R17 1 1      ; R17[(1-1)*FPF+i] := R(17+i), 1 <= i <= 1
331 [-]: CONST     R18 1        ; R18 := 1.000000
332 [-]: CALL      R12 7 1      ; R12(R13,R14,R15,R16,R17,R18)
333 [-]: GETGLOBAL R12 K27      ; R12 := 0x25312c9b
334 [-]: GETGLOBAL R13 K1       ; R13 := 0xae91e43b
335 [-]: MOVE      R14 R11      ; R14 := R11
336 [-]: CONST     R15 0        ; R15 := 0.000000
337 [-]: NEWTABLE  R16 1 0      ; R16 := {}
338 [-]: GETUPVAL  R17 U15      ; R17 := U15
339 [-]: SETLIST   R16 1 1      ; R16[(1-1)*FPF+i] := R(16+i), 1 <= i <= 1
340 [-]: NEWTABLE  R17 1 0      ; R17 := {}
341 [-]: GETUPVAL  R18 U16      ; R18 := U16
342 [-]: UNM       R18 R18      ; R18 :=  R18
343 [-]: SETLIST   R17 1 1      ; R17[(1-1)*FPF+i] := R(17+i), 1 <= i <= 1
344 [-]: CONST     R18 1        ; R18 := 1.000000
345 [-]: CALL      R12 7 1      ; R12(R13,R14,R15,R16,R17,R18)
346 [-]: JMP       391          ; PC := 391
347 [-]: GETUPVAL  R12 U14      ; R12 := U14
348 [-]: TEST      R12 0        ; if not R12 then PC := 371
349 [-]: JMP       371          ; PC := 371
350 [-]: GETGLOBAL R12 K27      ; R12 := 0x25312c9b
351 [-]: GETGLOBAL R13 K1       ; R13 := 0xae91e43b
352 [-]: MOVE      R14 R11      ; R14 := R11
353 [-]: CONST     R15 0        ; R15 := 0.000000
354 [-]: NEWTABLE  R16 2 0      ; R16 := {}
355 [-]: GETUPVAL  R17 U15      ; R17 := U15
356 [-]: CONST     R18 10       ; R18 := 10.000000
357 [-]: SETLIST   R16 2 1      ; R16[(1-1)*FPF+i] := R(16+i), 1 <= i <= 2
358 [-]: NEWTABLE  R17 1 0      ; R17 := {}
359 [-]: GETUPVAL  R18 U16      ; R18 := U16
360 [-]: SUB       R18 K17 R18  ; R18 := 1.000000 - R18
361 [-]: GETUPVAL  R19 U6       ; R19 := U6
362 [-]: GETTABLE  R19 R19 K10  ; R19 := R19[0x06d055f9]
363 [-]: GETUPVAL  R20 U18      ; R20 := U18
364 [-]: CONST     R21 25       ; R21 := 25.000000
365 [-]: CONST     R22 100      ; R22 := 100.000000
366 [-]: CALL      R19 4 0      ; R19,... := R19(R20,R21,R22)
367 [-]: SETLIST   R17 0 1      ; R17[(1-1)*FPF+i] := R(17+i), 1 <= i <= 0
368 [-]: CONST     R18 0        ; R18 := 0.500000
369 [-]: CALL      R12 7 1      ; R12(R13,R14,R15,R16,R17,R18)
370 [-]: JMP       391          ; PC := 391
371 [-]: GETGLOBAL R12 K27      ; R12 := 0x25312c9b
372 [-]: GETGLOBAL R13 K1       ; R13 := 0xae91e43b
373 [-]: MOVE      R14 R11      ; R14 := R11
374 [-]: CONST     R15 0        ; R15 := 0.000000
375 [-]: NEWTABLE  R16 2 0      ; R16 := {}
376 [-]: GETUPVAL  R17 U15      ; R17 := U15
377 [-]: CONST     R18 10       ; R18 := 10.000000
378 [-]: SETLIST   R16 2 1      ; R16[(1-1)*FPF+i] := R(16+i), 1 <= i <= 2
379 [-]: NEWTABLE  R17 1 0      ; R17 := {}
380 [-]: GETUPVAL  R18 U16      ; R18 := U16
381 [-]: UNM       R18 R18      ; R18 :=  R18
382 [-]: GETUPVAL  R19 U6       ; R19 := U6
383 [-]: GETTABLE  R19 R19 K10  ; R19 := R19[0x06d055f9]
384 [-]: GETUPVAL  R20 U18      ; R20 := U18
385 [-]: CONST     R21 25       ; R21 := 25.000000
386 [-]: CONST     R22 100      ; R22 := 100.000000
387 [-]: CALL      R19 4 0      ; R19,... := R19(R20,R21,R22)
388 [-]: SETLIST   R17 0 1      ; R17[(1-1)*FPF+i] := R(17+i), 1 <= i <= 0
389 [-]: CONST     R18 0        ; R18 := 0.500000
390 [-]: CALL      R12 7 1      ; R12(R13,R14,R15,R16,R17,R18)
391 [-]: GETGLOBAL R12 K27      ; R12 := 0x25312c9b
392 [-]: GETGLOBAL R13 K1       ; R13 := 0xae91e43b
393 [-]: LOADK     R14 K21      ; R14 := "Charge"
394 [-]: CONST     R15 0        ; R15 := 0.000000
395 [-]: NEWTABLE  R16 1 0      ; R16 := {}
396 [-]: CONST     R17 10       ; R17 := 10.000000
397 [-]: SETLIST   R16 1 1      ; R16[(1-1)*FPF+i] := R(16+i), 1 <= i <= 1
398 [-]: NEWTABLE  R17 0 0      ; R17 := {}
399 [-]: GETUPVAL  R18 U6       ; R18 := U6
400 [-]: GETTABLE  R18 R18 K10  ; R18 := R18[0x06d055f9]
401 [-]: GETUPVAL  R19 U18      ; R19 := U18
402 [-]: CONST     R20 25       ; R20 := 25.000000
403 [-]: CONST     R21 100      ; R21 := 100.000000
404 [-]: CALL      R18 4 0      ; R18,... := R18(R19,R20,R21)
405 [-]: SETLIST   R17 0 1      ; R17[(1-1)*FPF+i] := R(17+i), 1 <= i <= 0
406 [-]: CONST     R18 0        ; R18 := 0.500000
407 [-]: CALL      R12 7 1      ; R12(R13,R14,R15,R16,R17,R18)
408 [-]: GETUPVAL  R12 U19      ; R12 := U19
409 [-]: CALL      R12 1 1      ; R12()
410 [-]: GETGLOBAL R12 K0       ; R12 := 0x7b998233
411 [-]: GETUPVAL  R13 U20      ; R13 := U20
412 [-]: CALL      R12 2 2      ; R12 := R12(R13)
413 [-]: TEST      R12 0        ; if not R12 then PC := 419
414 [-]: JMP       419          ; PC := 419
415 [-]: GETGLOBAL R12 K29      ; R12 := 0xbe190284
416 [-]: SELF      R12 R12 K30  ; R13 := R12; R12 := R12[0x33307f92]
417 [-]: CALL      R12 2 2      ; R12 := R12(R13)
418 [-]: SETUPVAL  R12 U20      ; U82 := R20
419 [-]: GETGLOBAL R12 K0       ; R12 := 0x7b998233
420 [-]: GETUPVAL  R13 U20      ; R13 := U20
421 [-]: CALL      R12 2 2      ; R12 := R12(R13)
422 [-]: TEST      R12 1        ; if R12 then PC := 464
423 [-]: JMP       464          ; PC := 464
424 [-]: GETUPVAL  R12 U20      ; R12 := U20
425 [-]: SELF      R12 R12 K31  ; R13 := R12; R12 := R12[0xd4cc05b4]
426 [-]: CALL      R12 2 2      ; R12 := R12(R13)
427 [-]: TEST      R12 0        ; if not R12 then PC := 441
428 [-]: JMP       441          ; PC := 441
429 [-]: GETUPVAL  R12 U4       ; R12 := U4
430 [-]: TEST      R12 1        ; if R12 then PC := 441
431 [-]: JMP       441          ; PC := 441
432 [-]: GETGLOBAL R12 K32      ; R12 := _T
433 [-]: GETTABLE  R12 R12 K33  ; R12 := R12["reticleState"]
434 [-]: EQ        1 R12 K4     ; if R12 == nil then PC := 440
435 [-]: JMP       440          ; PC := 440
436 [-]: GETGLOBAL R12 K32      ; R12 := _T
437 [-]: GETTABLE  R12 R12 K33  ; R12 := R12["reticleState"]
438 [-]: JMP       441          ; PC := 441
439 [-]: LOADKB    R12 0 1      ; R12 := false; PC := 440
440 [-]: LOADKB    R12 1 0      ; R12 := true
441 [-]: GETUPVAL  R13 U21      ; R13 := U21
442 [-]: EQ        1 R13 R12    ; if R13 == R12 then PC := 449
443 [-]: JMP       449          ; PC := 449
444 [-]: SETUPVAL  R12 U21      ; U82 := R21
445 [-]: GETGLOBAL R13 K1       ; R13 := 0xae91e43b
446 [-]: SELF      R13 R13 K34  ; R14 := R13; R13 := R13[0x368ad758]
447 [-]: GETUPVAL  R15 U21      ; R15 := U21
448 [-]: CALL      R13 3 1      ; R13(R14,R15)
449 [-]: GETUPVAL  R13 U20      ; R13 := U20
450 [-]: SELF      R13 R13 K35  ; R14 := R13; R13 := R13[0x91a24e4b]
451 [-]: LOADK     R15 K36      ; R15 := "_root"
452 [-]: CONST     R16 10       ; R16 := 10.000000
453 [-]: CALL      R13 4 2      ; R13 := R13(R14,R15,R16)
454 [-]: GETUPVAL  R14 U22      ; R14 := U22
455 [-]: EQ        1 R14 R13    ; if R14 == R13 then PC := 464
456 [-]: JMP       464          ; PC := 464
457 [-]: SETUPVAL  R13 U22      ; U82 := R22
458 [-]: GETGLOBAL R14 K1       ; R14 := 0xae91e43b
459 [-]: SELF      R14 R14 K18  ; R15 := R14; R14 := R14[0x67bc869f]
460 [-]: LOADK     R16 K36      ; R16 := "_root"
461 [-]: CONST     R17 10       ; R17 := 10.000000
462 [-]: MOVE      R18 R13      ; R18 := R13
463 [-]: CALL      R14 5 1      ; R14(R15,R16,R17,R18)
464 [-]: RETURN    R0 1         ; return 


; Function #6:
;
; Name:            
; Defined at line: 249
; #Upvalues:       0
; #Parameters:     0
; Is_vararg:       0
; Max Stack Size:  2

  1 [-]: RETURN    R0 1         ; return 


; Function #7:
;
; Name:            
; Defined at line: 252
; #Upvalues:       1
; #Parameters:     4
; Is_vararg:       0
; Max Stack Size:  8

  1 [-]: GETGLOBAL R4 K0        ; R4 := 0x7b998233
  2 [-]: GETUPVAL  R5 U0        ; R5 := U0
  3 [-]: CALL      R4 2 2       ; R4 := R4(R5)
  4 [-]: TEST      R4 1         ; if R4 then PC := 11
  5 [-]: JMP       11           ; PC := 11
  6 [-]: GETUPVAL  R4 U0        ; R4 := U0
  7 [-]: SELF      R4 R4 K1     ; R5 := R4; R4 := R4[0xfaa69527]
  8 [-]: MOVE      R6 R0        ; R6 := R0
  9 [-]: MOVE      R7 R1        ; R7 := R1
 10 [-]: CALL      R4 4 1       ; R4(R5,R6,R7)
 11 [-]: RETURN    R0 1         ; return 


; Function #8:
;
; Name:            
; Defined at line: 258
; #Upvalues:       0
; #Parameters:     0
; Is_vararg:       0
; Max Stack Size:  2

  1 [-]: GETGLOBAL R0 K0        ; R0 := _T
  2 [-]: SETTABLE  R0 K1 K2     ; R0["SpecialReticleMovie"] := nil
  3 [-]: RETURN    R0 1         ; return 


; Function #9:
;
; Name:            
; Defined at line: 262
; #Upvalues:       3
; #Parameters:     0
; Is_vararg:       0
; Max Stack Size:  7

  1 [-]: GETGLOBAL R0 K0        ; R0 := 0xae91e43b
  2 [-]: SELF      R0 R0 K1     ; R1 := R0; R0 := R0[0x368ad758]
  3 [-]: LOADKB    R2 0 0       ; R2 := false
  4 [-]: CALL      R0 3 1       ; R0(R1,R2)
  5 [-]: GETGLOBAL R0 K0        ; R0 := 0xae91e43b
  6 [-]: SELF      R0 R0 K2     ; R1 := R0; R0 := R0[0x67bc869f]
  7 [-]: LOADK     R2 K3        ; R2 := "Charge.Bg"
  8 [-]: CONST     R3 9         ; R3 := 9.000000
  9 [-]: GETGLOBAL R4 K4        ; R4 := 0x0032441c
 10 [-]: GETTABLE  R4 R4 K5     ; R4 := R4["UIColor_DarkGrey"]
 11 [-]: CALL      R0 5 1       ; R0(R1,R2,R3,R4)
 12 [-]: GETGLOBAL R0 K0        ; R0 := 0xae91e43b
 13 [-]: SELF      R0 R0 K2     ; R1 := R0; R0 := R0[0x67bc869f]
 14 [-]: LOADK     R2 K3        ; R2 := "Charge.Bg"
 15 [-]: CONST     R3 10        ; R3 := 10.000000
 16 [-]: CONST     R4 50        ; R4 := 50.000000
 17 [-]: CALL      R0 5 1       ; R0(R1,R2,R3,R4)
 18 [-]: GETGLOBAL R0 K0        ; R0 := 0xae91e43b
 19 [-]: SELF      R0 R0 K2     ; R1 := R0; R0 := R0[0x67bc869f]
 20 [-]: LOADK     R2 K6        ; R2 := "ReticleLockOn"
 21 [-]: CONST     R3 10        ; R3 := 10.000000
 22 [-]: CONST     R4 0         ; R4 := 0.000000
 23 [-]: CALL      R0 5 1       ; R0(R1,R2,R3,R4)
 24 [-]: GETGLOBAL R0 K0        ; R0 := 0xae91e43b
 25 [-]: SELF      R0 R0 K2     ; R1 := R0; R0 := R0[0x67bc869f]
 26 [-]: LOADK     R2 K7        ; R2 := "ReticleNormal"
 27 [-]: CONST     R3 10        ; R3 := 10.000000
 28 [-]: CONST     R4 0         ; R4 := 0.000000
 29 [-]: CALL      R0 5 1       ; R0(R1,R2,R3,R4)
 30 [-]: GETGLOBAL R0 K0        ; R0 := 0xae91e43b
 31 [-]: SELF      R0 R0 K2     ; R1 := R0; R0 := R0[0x67bc869f]
 32 [-]: LOADK     R2 K8        ; R2 := "ReticleArchwing"
 33 [-]: CONST     R3 10        ; R3 := 10.000000
 34 [-]: CONST     R4 0         ; R4 := 0.000000
 35 [-]: CALL      R0 5 1       ; R0(R1,R2,R3,R4)
 36 [-]: GETGLOBAL R0 K9        ; R0 := _T
 37 [-]: GETGLOBAL R1 K0        ; R1 := 0xae91e43b
 38 [-]: SETTABLE  R0 K10 R1    ; R0["SpecialReticleMovie"] := R1
 39 [-]: GETUPVAL  R0 U1        ; R0 := U1
 40 [-]: GETTABLE  R0 R0 K11    ; R0 := R0[0xae6791ba]
 41 [-]: GETGLOBAL R1 K0        ; R1 := 0xae91e43b
 42 [-]: CALL      R0 2 2       ; R0 := R0(R1)
 43 [-]: SETUPVAL  R0 U0        ; U82 := R0
 44 [-]: GETUPVAL  R0 U0        ; R0 := U0
 45 [-]: SELF      R0 R0 K12    ; R1 := R0; R0 := R0[0x20ff29f7]
 46 [-]: GETGLOBAL R2 K0        ; R2 := 0xae91e43b
 47 [-]: LOADK     R3 K7        ; R3 := "ReticleNormal"
 48 [-]: NEWTABLE  R4 2 0       ; R4 := {}
 49 [-]: GETUPVAL  R5 U0        ; R5 := U0
 50 [-]: GETTABLE  R5 R5 K13    ; R5 := R5["ANCHOR_V_CENTRE"]
 51 [-]: GETUPVAL  R6 U0        ; R6 := U0
 52 [-]: GETTABLE  R6 R6 K14    ; R6 := R6["ANCHOR_H_CENTRE"]
 53 [-]: SETLIST   R4 2 1       ; R4[(1-1)*FPF+i] := R(4+i), 1 <= i <= 2
 54 [-]: CALL      R0 5 1       ; R0(R1,R2,R3,R4)
 55 [-]: GETUPVAL  R0 U0        ; R0 := U0
 56 [-]: SELF      R0 R0 K12    ; R1 := R0; R0 := R0[0x20ff29f7]
 57 [-]: GETGLOBAL R2 K0        ; R2 := 0xae91e43b
 58 [-]: LOADK     R3 K6        ; R3 := "ReticleLockOn"
 59 [-]: NEWTABLE  R4 2 0       ; R4 := {}
 60 [-]: GETUPVAL  R5 U0        ; R5 := U0
 61 [-]: GETTABLE  R5 R5 K13    ; R5 := R5["ANCHOR_V_CENTRE"]
 62 [-]: GETUPVAL  R6 U0        ; R6 := U0
 63 [-]: GETTABLE  R6 R6 K14    ; R6 := R6["ANCHOR_H_CENTRE"]
 64 [-]: SETLIST   R4 2 1       ; R4[(1-1)*FPF+i] := R(4+i), 1 <= i <= 2
 65 [-]: CALL      R0 5 1       ; R0(R1,R2,R3,R4)
 66 [-]: GETUPVAL  R0 U0        ; R0 := U0
 67 [-]: SELF      R0 R0 K12    ; R1 := R0; R0 := R0[0x20ff29f7]
 68 [-]: GETGLOBAL R2 K0        ; R2 := 0xae91e43b
 69 [-]: LOADK     R3 K8        ; R3 := "ReticleArchwing"
 70 [-]: NEWTABLE  R4 2 0       ; R4 := {}
 71 [-]: GETUPVAL  R5 U0        ; R5 := U0
 72 [-]: GETTABLE  R5 R5 K13    ; R5 := R5["ANCHOR_V_CENTRE"]
 73 [-]: GETUPVAL  R6 U0        ; R6 := U0
 74 [-]: GETTABLE  R6 R6 K14    ; R6 := R6["ANCHOR_H_CENTRE"]
 75 [-]: SETLIST   R4 2 1       ; R4[(1-1)*FPF+i] := R(4+i), 1 <= i <= 2
 76 [-]: CALL      R0 5 1       ; R0(R1,R2,R3,R4)
 77 [-]: GETUPVAL  R0 U0        ; R0 := U0
 78 [-]: SELF      R0 R0 K12    ; R1 := R0; R0 := R0[0x20ff29f7]
 79 [-]: GETGLOBAL R2 K0        ; R2 := 0xae91e43b
 80 [-]: LOADK     R3 K15       ; R3 := "Charge"
 81 [-]: NEWTABLE  R4 2 0       ; R4 := {}
 82 [-]: GETUPVAL  R5 U0        ; R5 := U0
 83 [-]: GETTABLE  R5 R5 K13    ; R5 := R5["ANCHOR_V_CENTRE"]
 84 [-]: GETUPVAL  R6 U0        ; R6 := U0
 85 [-]: GETTABLE  R6 R6 K14    ; R6 := R6["ANCHOR_H_CENTRE"]
 86 [-]: SETLIST   R4 2 1       ; R4[(1-1)*FPF+i] := R(4+i), 1 <= i <= 2
 87 [-]: CALL      R0 5 1       ; R0(R1,R2,R3,R4)
 88 [-]: GETUPVAL  R0 U0        ; R0 := U0
 89 [-]: SELF      R0 R0 K16    ; R1 := R0; R0 := R0[0xfaa69527]
 90 [-]: GETGLOBAL R2 K0        ; R2 := 0xae91e43b
 91 [-]: SELF      R2 R2 K17    ; R3 := R2; R2 := R2[0x6b837788]
 92 [-]: CALL      R2 2 2       ; R2 := R2(R3)
 93 [-]: GETGLOBAL R3 K0        ; R3 := 0xae91e43b
 94 [-]: SELF      R3 R3 K18    ; R4 := R3; R3 := R3[0xaf9fda9f]
 95 [-]: CALL      R3 2 2       ; R3 := R3(R4)
 96 [-]: LOADKB    R4 1 0       ; R4 := true
 97 [-]: GETUPVAL  R5 U0        ; R5 := U0
 98 [-]: GETTABLE  R5 R5 K19    ; R5 := R5["mHudScalePadding"]
 99 [-]: CALL      R0 6 1       ; R0(R1,R2,R3,R4,R5)
100 [-]: LOADKB    R0 1 0       ; R0 := true
101 [-]: SETUPVAL  R0 U2        ; U82 := R2
102 [-]: RETURN    R0 1         ; return 


; Function #10:
;
; Name:            
; Defined at line: 282
; #Upvalues:       10
; #Parameters:     1
; Is_vararg:       0
; Max Stack Size:  10

  1 [-]: GETUPVAL  R1 U0        ; R1 := U0
  2 [-]: EQ        0 R1 R0      ; if R1 ~= R0 then PC := 5
  3 [-]: JMP       5            ; PC := 5
  4 [-]: LOADKB    R1 0 1       ; R1 := false; PC := 5
  5 [-]: LOADKB    R1 1 0       ; R1 := true
  6 [-]: SETUPVAL  R0 U0        ; U82 := R0
  7 [-]: GETGLOBAL R2 K0        ; R2 := 0x7b998233
  8 [-]: GETUPVAL  R3 U0        ; R3 := U0
  9 [-]: CALL      R2 2 2       ; R2 := R2(R3)
 10 [-]: TEST      R2 1         ; if R2 then PC := 87
 11 [-]: JMP       87           ; PC := 87
 12 [-]: TEST      R1 0         ; if not R1 then PC := 87
 13 [-]: JMP       87           ; PC := 87
 14 [-]: GETUPVAL  R2 U1        ; R2 := U1
 15 [-]: GETTABLE  R2 R2 K1     ; R2 := R2[0xb73d420f]
 16 [-]: CALL      R2 1 2       ; R2 := R2()
 17 [-]: GETUPVAL  R3 U1        ; R3 := U1
 18 [-]: GETTABLE  R3 R3 K2     ; R3 := R3["UI_MODE_IN_GAME"]
 19 [-]: EQ        0 R2 R3      ; if R2 ~= R3 then PC := 87
 20 [-]: JMP       87           ; PC := 87
 21 [-]: GETUPVAL  R2 U0        ; R2 := U0
 22 [-]: SELF      R2 R2 K3     ; R3 := R2; R2 := R2[0x189cf7d1]
 23 [-]: CALL      R2 2 2       ; R2 := R2(R3)
 24 [-]: SETUPVAL  R2 U2        ; U82 := R2
 25 [-]: GETUPVAL  R2 U0        ; R2 := U0
 26 [-]: SELF      R2 R2 K4     ; R3 := R2; R2 := R2[0xb6fe179b]
 27 [-]: CALL      R2 2 2       ; R2 := R2(R3)
 28 [-]: SETUPVAL  R2 U3        ; U82 := R3
 29 [-]: GETUPVAL  R2 U0        ; R2 := U0
 30 [-]: SELF      R2 R2 K5     ; R3 := R2; R2 := R2[0xa3ef5d65]
 31 [-]: GETUPVAL  R4 U4        ; R4 := U4
 32 [-]: LOADKB    R5 1 0       ; R5 := true
 33 [-]: CALL      R2 4 1       ; R2(R3,R4,R5)
 34 [-]: GETUPVAL  R2 U3        ; R2 := U3
 35 [-]: GETUPVAL  R3 U2        ; R3 := U2
 36 [-]: DIV       R2 R2 R3     ; R2 := R2 / R3
 37 [-]: SETUPVAL  R2 U5        ; U82 := R5
 38 [-]: GETGLOBAL R2 K6        ; R2 := 0xae91e43b
 39 [-]: SELF      R2 R2 K7     ; R3 := R2; R2 := R2[0x67bc869f]
 40 [-]: LOADK     R4 K8        ; R4 := "ReticleNormal"
 41 [-]: CONST     R5 10        ; R5 := 10.000000
 42 [-]: GETUPVAL  R6 U6        ; R6 := U6
 43 [-]: GETTABLE  R6 R6 K9     ; R6 := R6[0x06d055f9]
 44 [-]: GETUPVAL  R7 U7        ; R7 := U7
 45 [-]: CONST     R8 0         ; R8 := 0.000000
 46 [-]: CONST     R9 100       ; R9 := 100.000000
 47 [-]: CALL      R6 4 0       ; R6,... := R6(R7,R8,R9)
 48 [-]: CALL      R2 0 1       ; R2(R3,...)
 49 [-]: GETGLOBAL R2 K6        ; R2 := 0xae91e43b
 50 [-]: SELF      R2 R2 K7     ; R3 := R2; R2 := R2[0x67bc869f]
 51 [-]: LOADK     R4 K10       ; R4 := "ReticleArchwing"
 52 [-]: CONST     R5 10        ; R5 := 10.000000
 53 [-]: GETUPVAL  R6 U6        ; R6 := U6
 54 [-]: GETTABLE  R6 R6 K9     ; R6 := R6[0x06d055f9]
 55 [-]: GETUPVAL  R7 U7        ; R7 := U7
 56 [-]: CONST     R8 100       ; R8 := 100.000000
 57 [-]: CONST     R9 0         ; R9 := 0.000000
 58 [-]: CALL      R6 4 0       ; R6,... := R6(R7,R8,R9)
 59 [-]: CALL      R2 0 1       ; R2(R3,...)
 60 [-]: GETGLOBAL R2 K6        ; R2 := 0xae91e43b
 61 [-]: SELF      R2 R2 K7     ; R3 := R2; R2 := R2[0x67bc869f]
 62 [-]: LOADK     R4 K11       ; R4 := "ReticleLockOn"
 63 [-]: CONST     R5 10        ; R5 := 10.000000
 64 [-]: CONST     R6 0         ; R6 := 0.000000
 65 [-]: CALL      R2 5 1       ; R2(R3,R4,R5,R6)
 66 [-]: GETUPVAL  R2 U8        ; R2 := U8
 67 [-]: LOADKB    R3 1 0       ; R3 := true
 68 [-]: CALL      R2 2 1       ; R2(R3)
 69 [-]: GETUPVAL  R2 U9        ; R2 := U9
 70 [-]: CALL      R2 1 1       ; R2()
 71 [-]: GETGLOBAL R2 K6        ; R2 := 0xae91e43b
 72 [-]: SELF      R2 R2 K7     ; R3 := R2; R2 := R2[0x67bc869f]
 73 [-]: LOADK     R4 K12       ; R4 := "ReticleLockOn.LockedOnEdgeRight"
 74 [-]: CONST     R5 9         ; R5 := 9.000000
 75 [-]: GETUPVAL  R6 U4        ; R6 := U4
 76 [-]: SELF      R6 R6 K13    ; R7 := R6; R6 := R6[0xa5d5c8f6]
 77 [-]: CALL      R6 2 0       ; R6,... := R6(R7)
 78 [-]: CALL      R2 0 1       ; R2(R3,...)
 79 [-]: GETGLOBAL R2 K6        ; R2 := 0xae91e43b
 80 [-]: SELF      R2 R2 K7     ; R3 := R2; R2 := R2[0x67bc869f]
 81 [-]: LOADK     R4 K14       ; R4 := "ReticleLockOn.LockedOnEdgeLeft"
 82 [-]: CONST     R5 9         ; R5 := 9.000000
 83 [-]: GETUPVAL  R6 U4        ; R6 := U4
 84 [-]: SELF      R6 R6 K13    ; R7 := R6; R6 := R6[0xa5d5c8f6]
 85 [-]: CALL      R6 2 0       ; R6,... := R6(R7)
 86 [-]: CALL      R2 0 1       ; R2(R3,...)
 87 [-]: GETGLOBAL R2 K0        ; R2 := 0x7b998233
 88 [-]: MOVE      R3 R0        ; R3 := R0
 89 [-]: CALL      R2 2 2       ; R2 := R2(R3)
 90 [-]: NOT       R2 R2        ; R2 :=  R2
 91 [-]: RETURN    R2 2         ; return R2
 92 [-]: RETURN    R0 1         ; return 


; Function #11:
;
; Name:            
; Defined at line: 303
; #Upvalues:       9
; #Parameters:     1
; Is_vararg:       0
; Max Stack Size:  13

  1 [-]: EQ        1 R0 K0      ; if R0 == "true" then PC := 4
  2 [-]: JMP       4            ; PC := 4
  3 [-]: LOADKB    R1 0 1       ; R1 := false; PC := 4
  4 [-]: LOADKB    R1 1 0       ; R1 := true
  5 [-]: SETUPVAL  R1 U0        ; U82 := R0
  6 [-]: GETUPVAL  R1 U2        ; R1 := U2
  7 [-]: SETUPVAL  R1 U1        ; U82 := R1
  8 [-]: GETUPVAL  R1 U3        ; R1 := U3
  9 [-]: GETTABLE  R1 R1 K1     ; R1 := R1[0x06d055f9]
 10 [-]: GETUPVAL  R2 U4        ; R2 := U4
 11 [-]: LOADK     R3 K2        ; R3 := "ReticleArchwing"
 12 [-]: LOADK     R4 K3        ; R4 := "ReticleNormal"
 13 [-]: CALL      R1 4 2       ; R1 := R1(R2,R3,R4)
 14 [-]: GETGLOBAL R2 K4        ; R2 := 0xae91e43b
 15 [-]: SELF      R2 R2 K5     ; R3 := R2; R2 := R2[0xaf5300dc]
 16 [-]: MOVE      R4 R1        ; R4 := R1
 17 [-]: CALL      R2 3 1       ; R2(R3,R4)
 18 [-]: GETUPVAL  R2 U5        ; R2 := U5
 19 [-]: TEST      R2 0         ; if not R2 then PC := 65
 20 [-]: JMP       65           ; PC := 65
 21 [-]: GETGLOBAL R2 K6        ; R2 := 0x25312c9b
 22 [-]: GETGLOBAL R3 K4        ; R3 := 0xae91e43b
 23 [-]: LOADK     R4 K7        ; R4 := "ReticleLockOn"
 24 [-]: CONST     R5 0         ; R5 := 0.000000
 25 [-]: NEWTABLE  R6 1 0       ; R6 := {}
 26 [-]: CONST     R7 10        ; R7 := 10.000000
 27 [-]: SETLIST   R6 1 1       ; R6[(1-1)*FPF+i] := R(6+i), 1 <= i <= 1
 28 [-]: NEWTABLE  R7 0 0       ; R7 := {}
 29 [-]: GETUPVAL  R8 U3        ; R8 := U3
 30 [-]: GETTABLE  R8 R8 K1     ; R8 := R8[0x06d055f9]
 31 [-]: GETUPVAL  R9 U6        ; R9 := U6
 32 [-]: CONST     R10 25       ; R10 := 25.000000
 33 [-]: CONST     R11 100      ; R11 := 100.000000
 34 [-]: CALL      R8 4 0       ; R8,... := R8(R9,R10,R11)
 35 [-]: SETLIST   R7 0 1       ; R7[(1-1)*FPF+i] := R(7+i), 1 <= i <= 0
 36 [-]: CONST     R8 0         ; R8 := 0.500000
 37 [-]: CALL      R2 7 1       ; R2(R3,R4,R5,R6,R7,R8)
 38 [-]: GETGLOBAL R2 K6        ; R2 := 0x25312c9b
 39 [-]: GETGLOBAL R3 K4        ; R3 := 0xae91e43b
 40 [-]: MOVE      R4 R1        ; R4 := R1
 41 [-]: CONST     R5 0         ; R5 := 0.000000
 42 [-]: NEWTABLE  R6 1 0       ; R6 := {}
 43 [-]: GETUPVAL  R7 U7        ; R7 := U7
 44 [-]: SETLIST   R6 1 1       ; R6[(1-1)*FPF+i] := R(6+i), 1 <= i <= 1
 45 [-]: NEWTABLE  R7 1 0       ; R7 := {}
 46 [-]: GETUPVAL  R8 U1        ; R8 := U1
 47 [-]: SUB       R8 K9 R8     ; R8 := 1.000000 - R8
 48 [-]: SETLIST   R7 1 1       ; R7[(1-1)*FPF+i] := R(7+i), 1 <= i <= 1
 49 [-]: CONST     R8 1         ; R8 := 1.000000
 50 [-]: CALL      R2 7 1       ; R2(R3,R4,R5,R6,R7,R8)
 51 [-]: GETGLOBAL R2 K6        ; R2 := 0x25312c9b
 52 [-]: GETGLOBAL R3 K4        ; R3 := 0xae91e43b
 53 [-]: MOVE      R4 R1        ; R4 := R1
 54 [-]: CONST     R5 0         ; R5 := 0.000000
 55 [-]: NEWTABLE  R6 1 0       ; R6 := {}
 56 [-]: GETUPVAL  R7 U7        ; R7 := U7
 57 [-]: SETLIST   R6 1 1       ; R6[(1-1)*FPF+i] := R(6+i), 1 <= i <= 1
 58 [-]: NEWTABLE  R7 1 0       ; R7 := {}
 59 [-]: GETUPVAL  R8 U1        ; R8 := U1
 60 [-]: UNM       R8 R8        ; R8 :=  R8
 61 [-]: SETLIST   R7 1 1       ; R7[(1-1)*FPF+i] := R(7+i), 1 <= i <= 1
 62 [-]: CONST     R8 1         ; R8 := 1.000000
 63 [-]: CALL      R2 7 1       ; R2(R3,R4,R5,R6,R7,R8)
 64 [-]: JMP       139          ; PC := 139
 65 [-]: GETUPVAL  R2 U8        ; R2 := U8
 66 [-]: TEST      R2 0         ; if not R2 then PC := 95
 67 [-]: JMP       95           ; PC := 95
 68 [-]: GETGLOBAL R2 K6        ; R2 := 0x25312c9b
 69 [-]: GETGLOBAL R3 K4        ; R3 := 0xae91e43b
 70 [-]: MOVE      R4 R1        ; R4 := R1
 71 [-]: CONST     R5 0         ; R5 := 0.000000
 72 [-]: NEWTABLE  R6 1 0       ; R6 := {}
 73 [-]: GETUPVAL  R7 U7        ; R7 := U7
 74 [-]: SETLIST   R6 1 1       ; R6[(1-1)*FPF+i] := R(6+i), 1 <= i <= 1
 75 [-]: NEWTABLE  R7 1 0       ; R7 := {}
 76 [-]: GETUPVAL  R8 U1        ; R8 := U1
 77 [-]: SUB       R8 K9 R8     ; R8 := 1.000000 - R8
 78 [-]: SETLIST   R7 1 1       ; R7[(1-1)*FPF+i] := R(7+i), 1 <= i <= 1
 79 [-]: CONST     R8 1         ; R8 := 1.000000
 80 [-]: CALL      R2 7 1       ; R2(R3,R4,R5,R6,R7,R8)
 81 [-]: GETGLOBAL R2 K6        ; R2 := 0x25312c9b
 82 [-]: GETGLOBAL R3 K4        ; R3 := 0xae91e43b
 83 [-]: MOVE      R4 R1        ; R4 := R1
 84 [-]: CONST     R5 0         ; R5 := 0.000000
 85 [-]: NEWTABLE  R6 1 0       ; R6 := {}
 86 [-]: GETUPVAL  R7 U7        ; R7 := U7
 87 [-]: SETLIST   R6 1 1       ; R6[(1-1)*FPF+i] := R(6+i), 1 <= i <= 1
 88 [-]: NEWTABLE  R7 1 0       ; R7 := {}
 89 [-]: GETUPVAL  R8 U1        ; R8 := U1
 90 [-]: UNM       R8 R8        ; R8 :=  R8
 91 [-]: SETLIST   R7 1 1       ; R7[(1-1)*FPF+i] := R(7+i), 1 <= i <= 1
 92 [-]: CONST     R8 1         ; R8 := 1.000000
 93 [-]: CALL      R2 7 1       ; R2(R3,R4,R5,R6,R7,R8)
 94 [-]: JMP       139          ; PC := 139
 95 [-]: GETUPVAL  R2 U0        ; R2 := U0
 96 [-]: TEST      R2 0         ; if not R2 then PC := 119
 97 [-]: JMP       119          ; PC := 119
 98 [-]: GETGLOBAL R2 K6        ; R2 := 0x25312c9b
 99 [-]: GETGLOBAL R3 K4        ; R3 := 0xae91e43b
100 [-]: MOVE      R4 R1        ; R4 := R1
101 [-]: CONST     R5 0         ; R5 := 0.000000
102 [-]: NEWTABLE  R6 2 0       ; R6 := {}
103 [-]: GETUPVAL  R7 U7        ; R7 := U7
104 [-]: CONST     R8 10        ; R8 := 10.000000
105 [-]: SETLIST   R6 2 1       ; R6[(1-1)*FPF+i] := R(6+i), 1 <= i <= 2
106 [-]: NEWTABLE  R7 1 0       ; R7 := {}
107 [-]: GETUPVAL  R8 U1        ; R8 := U1
108 [-]: SUB       R8 K9 R8     ; R8 := 1.000000 - R8
109 [-]: GETUPVAL  R9 U3        ; R9 := U3
110 [-]: GETTABLE  R9 R9 K1     ; R9 := R9[0x06d055f9]
111 [-]: GETUPVAL  R10 U6       ; R10 := U6
112 [-]: CONST     R11 25       ; R11 := 25.000000
113 [-]: CONST     R12 100      ; R12 := 100.000000
114 [-]: CALL      R9 4 0       ; R9,... := R9(R10,R11,R12)
115 [-]: SETLIST   R7 0 1       ; R7[(1-1)*FPF+i] := R(7+i), 1 <= i <= 0
116 [-]: CONST     R8 1         ; R8 := 1.000000
117 [-]: CALL      R2 7 1       ; R2(R3,R4,R5,R6,R7,R8)
118 [-]: JMP       139          ; PC := 139
119 [-]: GETGLOBAL R2 K6        ; R2 := 0x25312c9b
120 [-]: GETGLOBAL R3 K4        ; R3 := 0xae91e43b
121 [-]: MOVE      R4 R1        ; R4 := R1
122 [-]: CONST     R5 0         ; R5 := 0.000000
123 [-]: NEWTABLE  R6 2 0       ; R6 := {}
124 [-]: GETUPVAL  R7 U7        ; R7 := U7
125 [-]: CONST     R8 10        ; R8 := 10.000000
126 [-]: SETLIST   R6 2 1       ; R6[(1-1)*FPF+i] := R(6+i), 1 <= i <= 2
127 [-]: NEWTABLE  R7 1 0       ; R7 := {}
128 [-]: GETUPVAL  R8 U1        ; R8 := U1
129 [-]: UNM       R8 R8        ; R8 :=  R8
130 [-]: GETUPVAL  R9 U3        ; R9 := U3
131 [-]: GETTABLE  R9 R9 K1     ; R9 := R9[0x06d055f9]
132 [-]: GETUPVAL  R10 U6       ; R10 := U6
133 [-]: CONST     R11 25       ; R11 := 25.000000
134 [-]: CONST     R12 100      ; R12 := 100.000000
135 [-]: CALL      R9 4 0       ; R9,... := R9(R10,R11,R12)
136 [-]: SETLIST   R7 0 1       ; R7[(1-1)*FPF+i] := R(7+i), 1 <= i <= 0
137 [-]: CONST     R8 1         ; R8 := 1.000000
138 [-]: CALL      R2 7 1       ; R2(R3,R4,R5,R6,R7,R8)
139 [-]: RETURN    R0 1         ; return 


; Function #12:
;
; Name:            
; Defined at line: 324
; #Upvalues:       0
; #Parameters:     1
; Is_vararg:       0
; Max Stack Size:  6

  1 [-]: GETGLOBAL R1 K0        ; R1 := 0xae91e43b
  2 [-]: SELF      R1 R1 K1     ; R2 := R1; R1 := R1[0xaade900e]
  3 [-]: LOADK     R3 K2        ; R3 := "_root"
  4 [-]: CONST     R4 11        ; R4 := 11.000000
  5 [-]: EQ        1 R0 K3      ; if R0 == "true" then PC := 8
  6 [-]: JMP       8            ; PC := 8
  7 [-]: LOADKB    R5 0 1       ; R5 := false; PC := 8
  8 [-]: LOADKB    R5 1 0       ; R5 := true
  9 [-]: CALL      R1 5 1       ; R1(R2,R3,R4,R5)
 10 [-]: RETURN    R0 1         ; return 


; Function #13:
;
; Name:            
; Defined at line: 328
; #Upvalues:       0
; #Parameters:     0
; Is_vararg:       0
; Max Stack Size:  2

  1 [-]: RETURN    R0 1         ; return 


; Function #14:
;
; Name:            
; Defined at line: 331
; #Upvalues:       0
; #Parameters:     0
; Is_vararg:       0
; Max Stack Size:  2

  1 [-]: RETURN    R0 1         ; return 


; Function #15:
;
; Name:            
; Defined at line: 334
; #Upvalues:       0
; #Parameters:     2
; Is_vararg:       0
; Max Stack Size:  2

  1 [-]: RETURN    R0 1         ; return 


; Function #16:
;
; Name:            
; Defined at line: 337
; #Upvalues:       0
; #Parameters:     0
; Is_vararg:       0
; Max Stack Size:  2

  1 [-]: RETURN    R0 1         ; return 


; Function #17:
;
; Name:            
; Defined at line: 340
; #Upvalues:       0
; #Parameters:     0
; Is_vararg:       0
; Max Stack Size:  2

  1 [-]: LOADKB    R0 1 0       ; R0 := true
  2 [-]: RETURN    R0 2         ; return R0
  3 [-]: RETURN    R0 1         ; return 


; Function #18:
;
; Name:            
; Defined at line: 344
; #Upvalues:       1
; #Parameters:     1
; Is_vararg:       0
; Max Stack Size:  3

  1 [-]: GETGLOBAL R1 K0        ; R1 := 0x03f57322
  2 [-]: MOVE      R2 R0        ; R2 := R0
  3 [-]: CALL      R1 2 2       ; R1 := R1(R2)
  4 [-]: SETUPVAL  R1 U0        ; U82 := R0
  5 [-]: RETURN    R0 1         ; return 


