; Name:            
; Defined at line: 1
; #Upvalues:       0
; #Parameters:     0
; Is_vararg:       1
; Max Stack Size:  38

       1 [-]: GETIMPORT R0 1; var0 = 0x2D0FAD09
       2 [-]: LOADK R1 K2  ; var1 = "EE.Interface.Utilities"
       3 [-]: CALL R0 2 2  ; var0 = var0(var1)
       4 [-]: GETIMPORT R1 1; var1 = 0x2D0FAD09
       5 [-]: LOADK R2 K3  ; var2 = "Lotus.Scripts.Libs.LandscapeLib"
       6 [-]: CALL R1 2 2  ; var1 = var1(var2)
       7 [-]: GETIMPORT R2 1; var2 = 0x2D0FAD09
       8 [-]: LOADK R3 K4  ; var3 = "Lotus.Scripts.Libs.TransmissionSet"
       9 [-]: CALL R2 2 2  ; var2 = var2(var3)
      10 [-]: GETIMPORT R3 1; var3 = 0x2D0FAD09
      11 [-]: LOADK R4 K5  ; var4 = "Lotus.Scripts.Libs.ObjectiveText"
      12 [-]: CALL R3 2 2  ; var3 = var3(var4)
      13 [-]: GETIMPORT R4 1; var4 = 0x2D0FAD09
      14 [-]: LOADK R5 K6  ; var5 = "Lotus.Scripts.Libs.CommonGamemodeFunctions"
      15 [-]: CALL R4 2 2  ; var4 = var4(var5)
      16 [-]: GETIMPORT R5 8; var5 = 0x0469F296
      17 [-]: LOADK R6 K9  ; var6 = "HeistB3ConsoleAActivated"
      18 [-]: CALL R5 2 2  ; var5 = var5(var6)
      19 [-]: GETIMPORT R6 8; var6 = 0x0469F296
      20 [-]: LOADK R7 K10 ; var7 = "HeistB3ConsoleBActivated"
      21 [-]: CALL R6 2 2  ; var6 = var6(var7)
      22 [-]: GETIMPORT R7 8; var7 = 0x0469F296
      23 [-]: LOADK R8 K11 ; var8 = "HeistB3ConsoleTimer"
      24 [-]: CALL R7 2 2  ; var7 = var7(var8)
      25 [-]: GETIMPORT R8 8; var8 = 0x0469F296
      26 [-]: LOADK R9 K12 ; var9 = "HeistB3FightTimer"
      27 [-]: CALL R8 2 2  ; var8 = var8(var9)
      28 [-]: LOADNIL R9   ; var9 = nil
      29 [-]: LOADNIL R10  ; var10 = nil
      30 [-]: LOADNIL R11  ; var11 = nil
      31 [-]: LOADNIL R12  ; var12 = nil
      32 [-]: LOADNIL R13  ; var13 = nil
      33 [-]: LOADNIL R14  ; var14 = nil
      34 [-]: DUPTABLE R15 17; 
      35 [-]: LOADNIL R16  ; var16 = nil
      36 [-]: SETTABLEKS R16 R15 K13; var16["instance"] = var15
      37 [-]: LOADNIL R16  ; var16 = nil
      38 [-]: SETTABLEKS R16 R15 K14; var16["pos"] = var15
      39 [-]: LOADNIL R16  ; var16 = nil
      40 [-]: SETTABLEKS R16 R15 K15; var16["radius"] = var15
      41 [-]: LOADNIL R16  ; var16 = nil
      42 [-]: SETTABLEKS R16 R15 K16; var16["name"] = var15
      43 [-]: LOADNIL R16  ; var16 = nil
      44 [-]: LOADNIL R17  ; var17 = nil
      45 [-]: LOADNIL R18  ; var18 = nil
      46 [-]: LOADNIL R19  ; var19 = nil
      47 [-]: LOADNIL R20  ; var20 = nil
      48 [-]: LOADNIL R21  ; var21 = nil
      49 [-]: LOADNIL R22  ; var22 = nil
      50 [-]: LOADNIL R23  ; var23 = nil
      51 [-]: NEWTABLE R24 8 0; var24 = {}
      52 [-]: DUPTABLE R25 20; 
      53 [-]: LOADK R26 K21; var26 = 0.10000000149011612
      54 [-]: SETTABLEKS R26 R25 K18; var26["time"] = var25
      55 [-]: LOADN R26 1  ; var26 = 1
      56 [-]: SETTABLEKS R26 R25 K19; var26["alert"] = var25
      57 [-]: SETTABLEN R25 R24 31; SETTABLEN R25 R24 31
      58 [-]: DUPTABLE R25 20; 
      59 [-]: LOADK R26 K22; var26 = 0.25
      60 [-]: SETTABLEKS R26 R25 K18; var26["time"] = var25
      61 [-]: LOADN R26 2  ; var26 = 2
      62 [-]: SETTABLEKS R26 R25 K19; var26["alert"] = var25
      63 [-]: SETTABLEN R25 R24 33; SETTABLEN R25 R24 33
      64 [-]: DUPTABLE R25 20; 
      65 [-]: LOADK R26 K23; var26 = 0.44999998807907104
      66 [-]: SETTABLEKS R26 R25 K18; var26["time"] = var25
      67 [-]: LOADN R26 2  ; var26 = 2
      68 [-]: SETTABLEKS R26 R25 K19; var26["alert"] = var25
      69 [-]: SETTABLEN R25 R24 35; SETTABLEN R25 R24 35
      70 [-]: DUPTABLE R25 20; 
      71 [-]: LOADK R26 K24; var26 = 0.64999997615814209
      72 [-]: SETTABLEKS R26 R25 K18; var26["time"] = var25
      73 [-]: LOADN R26 3  ; var26 = 3
      74 [-]: SETTABLEKS R26 R25 K19; var26["alert"] = var25
      75 [-]: SETTABLEN R25 R24 40; SETTABLEN R25 R24 40
      76 [-]: DUPTABLE R25 20; 
      77 [-]: LOADK R26 K25; var26 = 0.75
      78 [-]: SETTABLEKS R26 R25 K18; var26["time"] = var25
      79 [-]: LOADN R26 4  ; var26 = 4
      80 [-]: SETTABLEKS R26 R25 K19; var26["alert"] = var25
      81 [-]: SETTABLEN R25 R24 42; SETTABLEN R25 R24 42
      82 [-]: DUPTABLE R25 20; 
      83 [-]: LOADN R26 1  ; var26 = 1
      84 [-]: SETTABLEKS R26 R25 K18; var26["time"] = var25
      85 [-]: LOADN R26 4  ; var26 = 4
      86 [-]: SETTABLEKS R26 R25 K19; var26["alert"] = var25
      87 [-]: SETTABLEN R25 R24 44; SETTABLEN R25 R24 44
      88 [-]: DUPCLOSURE R25 K26; 
      89 [-]: NEWCLOSURE R26 P1; 
      90 [-]: CAPTURE VAL R15; 
      91 [-]: CAPTURE VAL R25; 
      92 [-]: CAPTURE REF R10; 
      93 [-]: DUPCLOSURE R27 K27; 
      94 [-]: DUPCLOSURE R28 K28; 
      95 [-]: DUPCLOSURE R29 K29; 
      96 [-]: DUPCLOSURE R30 K30; 
      97 [-]: NEWCLOSURE R31 P6; 
      98 [-]: CAPTURE REF R14; 
      99 [-]: NEWCLOSURE R32 P7; 
     100 [-]: CAPTURE REF R16; 
     101 [-]: CAPTURE REF R20; 
     102 [-]: CAPTURE VAL R3; 
     103 [-]: CAPTURE REF R14; 
     104 [-]: CAPTURE VAL R4; 
     105 [-]: CAPTURE VAL R2; 
     106 [-]: CAPTURE REF R12; 
     107 [-]: CAPTURE REF R13; 
     108 [-]: CAPTURE REF R18; 
     109 [-]: CAPTURE REF R19; 
     110 [-]: CAPTURE REF R9; 
     111 [-]: CAPTURE VAL R5; 
     112 [-]: CAPTURE VAL R6; 
     113 [-]: CAPTURE REF R22; 
     114 [-]: CAPTURE VAL R7; 
     115 [-]: CAPTURE REF R21; 
     116 [-]: CAPTURE VAL R15; 
     117 [-]: NEWCLOSURE R33 P8; 
     118 [-]: CAPTURE REF R16; 
     119 [-]: CAPTURE VAL R4; 
     120 [-]: CAPTURE VAL R15; 
     121 [-]: CAPTURE VAL R2; 
     122 [-]: CAPTURE REF R12; 
     123 [-]: CAPTURE VAL R28; 
     124 [-]: CAPTURE REF R9; 
     125 [-]: CAPTURE REF R13; 
     126 [-]: CAPTURE VAL R3; 
     127 [-]: NEWCLOSURE R34 P9; 
     128 [-]: CAPTURE REF R23; 
     129 [-]: CAPTURE VAL R3; 
     130 [-]: CAPTURE REF R16; 
     131 [-]: CAPTURE VAL R4; 
     132 [-]: CAPTURE VAL R15; 
     133 [-]: CAPTURE VAL R2; 
     134 [-]: CAPTURE REF R12; 
     135 [-]: CAPTURE REF R13; 
     136 [-]: CAPTURE VAL R24; 
     137 [-]: CAPTURE VAL R28; 
     138 [-]: NEWCLOSURE R35 P10; 
     139 [-]: CAPTURE REF R13; 
     140 [-]: CAPTURE VAL R3; 
     141 [-]: CAPTURE VAL R32; 
     142 [-]: CAPTURE VAL R33; 
     143 [-]: CAPTURE VAL R34; 
     144 [-]: CAPTURE REF R16; 
     145 [-]: CAPTURE REF R11; 
     146 [-]: CAPTURE VAL R27; 
     147 [-]: CAPTURE VAL R4; 
     148 [-]: NEWCLOSURE R36 P11; 
     149 [-]: CAPTURE REF R10; 
     150 [-]: CAPTURE REF R9; 
     151 [-]: CAPTURE REF R11; 
     152 [-]: CAPTURE REF R12; 
     153 [-]: CAPTURE REF R14; 
     154 [-]: CAPTURE REF R22; 
     155 [-]: CAPTURE VAL R7; 
     156 [-]: CAPTURE REF R23; 
     157 [-]: CAPTURE VAL R8; 
     158 [-]: CAPTURE REF R13; 
     159 [-]: CAPTURE VAL R1; 
     160 [-]: CAPTURE VAL R35; 
     161 [-]: CAPTURE VAL R5; 
     162 [-]: CAPTURE VAL R6; 
     163 [-]: CAPTURE REF R21; 
     164 [-]: CAPTURE REF R18; 
     165 [-]: CAPTURE REF R19; 
     166 [-]: CAPTURE VAL R15; 
     167 [-]: CAPTURE REF R20; 
     168 [-]: CAPTURE REF R17; 
     169 [-]: CAPTURE VAL R27; 
     170 [-]: CAPTURE VAL R0; 
     171 [-]: NEWCLOSURE R37 P12; 
     172 [-]: CAPTURE VAL R36; 
     173 [-]: CAPTURE REF R14; 
     174 [-]: CAPTURE REF R18; 
     175 [-]: CAPTURE REF R23; 
     176 [-]: CAPTURE REF R13; 
     177 [-]: CAPTURE REF R10; 
     178 [-]: CAPTURE VAL R3; 
     179 [-]: CAPTURE REF R9; 
     180 [-]: CAPTURE VAL R5; 
     181 [-]: CAPTURE REF R22; 
     182 [-]: CAPTURE VAL R6; 
     183 [-]: CAPTURE VAL R7; 
     184 [-]: CAPTURE VAL R26; 
     185 [-]: CAPTURE REF R17; 
     186 [-]: CAPTURE VAL R8; 
     187 [-]: CAPTURE VAL R24; 
     188 [-]: SETGLOBAL R37 K31; "Start" = var37
     189 [-]: DUPCLOSURE R37 K32; 
     190 [-]: CAPTURE VAL R5; 
     191 [-]: SETGLOBAL R37 K33; "AntennaConsoleInterior" = var37
     192 [-]: DUPCLOSURE R37 K34; 
     193 [-]: CAPTURE VAL R6; 
     194 [-]: SETGLOBAL R37 K35; "AntennaConsoleExterior" = var37
     195 [-]: NEWCLOSURE R37 P15; 
     196 [-]: CAPTURE REF R14; 
     197 [-]: SETGLOBAL R37 K36; "OnPlayersChanged" = var37
     198 [-]: NEWCLOSURE R37 P16; 
     199 [-]: CAPTURE VAL R1; 
     200 [-]: CAPTURE REF R11; 
     201 [-]: SETGLOBAL R37 K37; "PlayersLeaving" = var37
     202 [-]: NEWCLOSURE R37 P17; 
     203 [-]: CAPTURE VAL R1; 
     204 [-]: CAPTURE REF R11; 
     205 [-]: SETGLOBAL R37 K38; "PlayersReturning" = var37
     206 [-]: DUPCLOSURE R37 K39; 
     207 [-]: CAPTURE VAL R28; 
     208 [-]: SETGLOBAL R37 K40; "TestMortar" = var37
     209 [-]: CLOSEUPVALS R9; 
     210 [-]: RETURN R0 0  ; 


; Name:            
; Defined at line: 93
; #Upvalues:       0
; #Parameters:     0
; Is_vararg:       0
; Max Stack Size:  10

       0 [-]: GETIMPORT R0 1; var0 = 0x64855CED
       1 [-]: LOADN R1 0   ; var1 = 0
       2 [-]: LOADN R4 1   ; var4 = 1
       3 [-]: LENGTH R2 R0 ; var2 = #var0
       4 [-]: LOADN R3 1   ; var3 = 1
       5 [-]: FORNPREP R2 L1; nforprep start - [escape at L1] -- var2 = iterator
L 0:   6 [-]: GETTABLE R5 R0 R4; var5 = var0[var4]
       7 [-]: ADD R1 R1 R5 ; var1 = var1 + var5
       8 [-]: FORNLOOP R2 L0; nforloop end - iterate + goto L0
L 1:   9 [-]: GETIMPORT R2 4; var2 = 0x5BCED4C4[0x3630E649]
      10 [-]: CALL R2 1 2  ; var2 = var2()
      11 [-]: LOADN R5 1   ; var5 = 1
      12 [-]: LENGTH R3 R0 ; var3 = #var0
      13 [-]: LOADN R4 1   ; var4 = 1
      14 [-]: FORNPREP R3 L6; nforprep start - [escape at L6] -- var3 = iterator
L 2:  15 [-]: LOADN R6 0   ; var6 = 0
      16 [-]: LOADN R7 1   ; var7 = 1
      17 [-]: JUMPIFNOTLT R7 R5 L3; goto L3 if var7 >= var84215810
      18 [-]: SUBK R8 R5 K5; var8 = var5 - 1
      19 [-]: GETTABLE R7 R0 R8; var7 = var0[var8]
      20 [-]: DIV R6 R7 R1 ; var6 = var7 / var1
L 3:  21 [-]: LOADK R7 K6  ; var7 = 1.1000000238418579
      22 [-]: LENGTH R8 R0 ; var8 = #var0
      23 [-]: JUMPIFNOTLT R5 R8 L4; goto L4 if var5 >= var84216072
      24 [-]: ADDK R9 R5 K5; var9 = var5 + 1
      25 [-]: GETTABLE R8 R0 R9; var8 = var0[var9]
      26 [-]: DIV R7 R8 R1 ; var7 = var8 / var1
L 4:  27 [-]: JUMPIFNOTLE R6 R2 L5; goto L5 if var6 > var328256
      28 [-]: JUMPIFNOTLT R2 R7 L5; goto L5 if var2 >= var526625
      29 [-]: GETIMPORT R9 8; var9 = 0xCC240205
      30 [-]: GETTABLE R8 R9 R5; var8 = var9[var5]
      31 [-]: RETURN R8 1  ; 
L 5:  32 [-]: FORNLOOP R3 L2; nforloop end - iterate + goto L2
L 6:  33 [-]: RETURN R0 0  ; 


; Name:            
; Defined at line: 116
; #Upvalues:       3
; #Parameters:     0
; Is_vararg:       0
; Max Stack Size:  19

       0 [-]: GETUPVAL R1 0; var1 = upvalues[0]
       1 [-]: GETTABLEKS R0 R1 K0; var0 = var1["inst"]
       2 [-]: NAMECALL R0 R0 K1; var1 = var0; var0 = var0[0xD8140B94]
       3 [-]: CALL R0 2 2  ; var0 = var0(var1)
       4 [-]: GETUPVAL R2 0; var2 = upvalues[0]
       5 [-]: GETTABLEKS R1 R2 K0; var1 = var2["inst"]
       6 [-]: NAMECALL R1 R1 K2; var2 = var1; var1 = var1[0xBE21D4F6]
       7 [-]: CALL R1 2 2  ; var1 = var1(var2)
       8 [-]: GETUPVAL R3 0; var3 = upvalues[0]
       9 [-]: GETTABLEKS R2 R3 K0; var2 = var3["inst"]
      10 [-]: NAMECALL R2 R2 K3; var3 = var2; var2 = var2[0x1E0AEEEC]
      11 [-]: CALL R2 2 2  ; var2 = var2(var3)
      12 [-]: JUMPIFNOT R0 L0; goto L0 if not var0
      13 [-]: JUMPIF R1 L0 ; goto L0 if var1
      14 [-]: JUMPIFNOT R2 L3; goto L3 if not var2
L 0:  15 [-]: GETUPVAL R4 0; var4 = upvalues[0]
      16 [-]: GETTABLEKS R3 R4 K0; var3 = var4["inst"]
      17 [-]: NAMECALL R3 R3 K4; var4 = var3; var3 = var3[0x39E33D94]
      18 [-]: CALL R3 2 2  ; var3 = var3(var4)
      19 [-]: LOADN R4 10  ; var4 = 10
      20 [-]: JUMPIFNOTLT R3 R4 L3; goto L3 if var3 >= var66608
      21 [-]: LOADN R4 1   ; var4 = 1
      22 [-]: LOADN R5 5   ; var5 = 5
      23 [-]: JUMPIFNOTLE R3 R5 L1; goto L1 if var3 > var132144
      24 [-]: LOADN R4 2   ; var4 = 2
L 1:  25 [-]: LOADN R7 1   ; var7 = 1
      26 [-]: MOVE R5 R4   ; var5 = var4
      27 [-]: LOADN R6 1   ; var6 = 1
      28 [-]: FORNPREP R5 L3; nforprep start - [escape at L3] -- var5 = iterator
L 2:  29 [-]: GETUPVAL R8 1; var8 = upvalues[1]
      30 [-]: CALL R8 1 2  ; var8 = var8()
      31 [-]: GETUPVAL R9 2; var9 = upvalues[2]
      32 [-]: GETUPVAL R12 0; var12 = upvalues[0]
      33 [-]: GETTABLEKS R11 R12 K5; var11 = var12["pos"]
      34 [-]: LOADN R12 20 ; var12 = 20
      35 [-]: LOADN R13 80 ; var13 = 80
      36 [-]: MOVE R14 R8  ; var14 = var8
      37 [-]: LOADN R15 2  ; var15 = 2
      38 [-]: LOADN R16 2  ; var16 = 2
      39 [-]: GETUPVAL R18 0; var18 = upvalues[0]
      40 [-]: GETTABLEKS R17 R18 K0; var17 = var18["inst"]
      41 [-]: NAMECALL R9 R9 K6; var10 = var9; var9 = var9[0xA3871690]
      42 [-]: CALL R9 9 1  ; var9(var10, var11, var12, var13, var14, var15, var16, var17)
      43 [-]: GETIMPORT R9 8; var9 = 0x3D106989
      44 [-]: LOADK R10 K9 ; var10 = "Heist: B3: Reinforcements triggered"
      45 [-]: CALL R9 2 1  ; var9(var10)
      46 [-]: FORNLOOP R5 L2; nforloop end - iterate + goto L2
L 3:  47 [-]: RETURN R0 0  ; 


; Name:            
; Defined at line: 138
; #Upvalues:       0
; #Parameters:     1
; Is_vararg:       0
; Max Stack Size:  11

       0 [-]: LOADK R1 K0  ; var1 = "Enable"
       1 [-]: JUMPIF R0 L0 ; goto L0 if var0
       2 [-]: LOADK R1 K1  ; var1 = "Disable"
L 0:   3 [-]: GETIMPORT R2 3; var2 = 0x89326C93
       4 [-]: GETIMPORT R4 5; var4 = 0x0469F296
       5 [-]: LOADK R5 K6  ; var5 = "HeistB3VentAction"
       6 [-]: CALL R4 2 0  ; var4, ... = var4(var5)
       7 [-]: NAMECALL R2 R2 K7; var3 = var2; var2 = var2[0xC7FCADA9]
       8 [-]: CALL R2 0 2  ; var2 = var2(var3, ...)
       9 [-]: GETIMPORT R3 9; var3 = 0xC8802016
      10 [-]: MOVE R4 R2   ; var4 = var2
      11 [-]: CALL R3 2 4  ; var3, var4, var5 = var3(var4)
      12 [-]: FORGPREP_INEXT R3 L2; 
L 1:  13 [-]: MOVE R10 R1  ; var10 = var1
      14 [-]: NAMECALL R8 R7 K10; var9 = var7; var8 = var7[0x8EB2112D]
      15 [-]: CALL R8 3 1  ; var8(var9, var10)
L 2:  16 [-]: FORGLOOP R3 L1 2 [inext]; 
      17 [-]: RETURN R0 0  ; 


; Name:            
; Defined at line: 150
; #Upvalues:       0
; #Parameters:     3
; Is_vararg:       0
; Max Stack Size:  17

       0 [-]: GETIMPORT R3 1; var3 = 0x89326C93
       1 [-]: GETIMPORT R5 3; var5 = 0x0469F296
       2 [-]: LOADK R6 K4  ; var6 = "FortunaMortarWaypoint"
       3 [-]: CALL R5 2 0  ; var5, ... = var5(var6)
       4 [-]: NAMECALL R3 R3 K5; var4 = var3; var3 = var3[0x46A0EBF5]
       5 [-]: CALL R3 0 2  ; var3 = var3(var4, ...)
       6 [-]: LOADNIL R4   ; var4 = nil
       7 [-]: FASTCALL1 64 R3 L0; 
       8 [-]: MOVE R6 R3   ; var6 = var3
       9 [-]: GETIMPORT R5 7; var5 = 0x7B998233
      10 [-]: CALL R5 2 2  ; var5 = var5(var6)
L 0:  11 [-]: JUMPIF R5 L10; goto L10 if var5
      12 [-]: NAMECALL R5 R3 K8; var6 = var3; var5 = var3[0xD1586535]
      13 [-]: CALL R5 2 2  ; var5 = var5(var6)
      14 [-]: GETIMPORT R6 1; var6 = 0x89326C93
      15 [-]: GETIMPORT R8 3; var8 = 0x0469F296
      16 [-]: LOADK R9 K9  ; var9 = "BizMortarDeco"
      17 [-]: CALL R8 2 2  ; var8 = var8(var9)
      18 [-]: MOVE R9 R5   ; var9 = var5
      19 [-]: NAMECALL R6 R6 K10; var7 = var6; var6 = var6[0xC7B81E8D]
      20 [-]: CALL R6 4 2  ; var6 = var6(var7, var8, var9)
      21 [-]: FASTCALL1 64 R6 L1; 
      22 [-]: MOVE R8 R6   ; var8 = var6
      23 [-]: GETIMPORT R7 7; var7 = 0x7B998233
      24 [-]: CALL R7 2 2  ; var7 = var7(var8)
L 1:  25 [-]: JUMPIF R7 L2 ; goto L2 if var7
      26 [-]: LOADB R9 1   ; var9 = true
      27 [-]: LOADB R10 1  ; var10 = true
      28 [-]: NAMECALL R7 R6 K11; var8 = var6; var7 = var6[0x768274D6]
      29 [-]: CALL R7 4 1  ; var7(var8, var9, var10)
L 2:  30 [-]: GETIMPORT R8 14; var8 = _T["ArtilleryOrbAvatar"]
      31 [-]: FASTCALL1 64 R8 L3; 
      32 [-]: GETIMPORT R7 7; var7 = 0x7B998233
      33 [-]: CALL R7 2 2  ; var7 = var7(var8)
L 3:  34 [-]: JUMPIF R7 L4 ; goto L4 if var7
      35 [-]: GETIMPORT R7 14; var7 = _T["ArtilleryOrbAvatar"]
      36 [-]: NAMECALL R7 R7 K15; var8 = var7; var7 = var7[0xF6EBD926]
      37 [-]: CALL R7 2 2  ; var7 = var7(var8)
      38 [-]: MOVE R4 R7   ; var4 = var7
L 4:  39 [-]: FASTCALL1 64 R0 L5; 
      40 [-]: MOVE R8 R0   ; var8 = var0
      41 [-]: GETIMPORT R7 7; var7 = 0x7B998233
      42 [-]: CALL R7 2 2  ; var7 = var7(var8)
L 5:  43 [-]: JUMPIF R7 L6 ; goto L6 if var7
      44 [-]: NAMECALL R7 R0 K8; var8 = var0; var7 = var0[0xD1586535]
      45 [-]: CALL R7 2 2  ; var7 = var7(var8)
      46 [-]: MOVE R4 R7   ; var4 = var7
L 6:  47 [-]: LOADN R9 1   ; var9 = 1
      48 [-]: MOVE R7 R1   ; var7 = var1
      49 [-]: LOADN R8 1   ; var8 = 1
      50 [-]: FORNPREP R7 L9; nforprep start - [escape at L9] -- var7 = iterator
L 7:  51 [-]: LOADN R10 1  ; var10 = 1
      52 [-]: JUMPIFNOTLT R10 R9 L8; goto L8 if var10 >= var-1694233793
      53 [-]: GETTABLEKS R11 R4 K16; var11 = var4["z"]
      54 [-]: GETIMPORT R12 18; var12 = 0xC163F229
      55 [-]: MINUS R13 R2 ; 
      56 [-]: MOVE R14 R2  ; var14 = var2
      57 [-]: CALL R12 3 2 ; var12 = var12(var13, var14)
      58 [-]: ADD R10 R11 R12; var10 = var11 + var12
      59 [-]: SETTABLEKS R10 R4 K16; var10["z"] = var4
      60 [-]: GETTABLEKS R11 R4 K19; var11 = var4["x"]
      61 [-]: GETIMPORT R12 18; var12 = 0xC163F229
      62 [-]: MINUS R13 R2 ; 
      63 [-]: MOVE R14 R2  ; var14 = var2
      64 [-]: CALL R12 3 2 ; var12 = var12(var13, var14)
      65 [-]: ADD R10 R11 R12; var10 = var11 + var12
      66 [-]: SETTABLEKS R10 R4 K19; var10["x"] = var4
L 8:  67 [-]: GETIMPORT R10 22; var10 = 0x34291F5C[0xD96DCC3B]
      68 [-]: MOVE R11 R5  ; var11 = var5
      69 [-]: MOVE R12 R4  ; var12 = var4
      70 [-]: GETIMPORT R13 24; var13 = 0x483CD80C
      71 [-]: LOADB R14 0  ; var14 = false
      72 [-]: CALL R10 5 2 ; var10 = var10(var11, var12, var13, var14)
      73 [-]: GETIMPORT R11 1; var11 = 0x89326C93
      74 [-]: GETIMPORT R13 24; var13 = 0x483CD80C
      75 [-]: MOVE R14 R5  ; var14 = var5
      76 [-]: MOVE R15 R10 ; var15 = var10
      77 [-]: LOADNIL R16  ; var16 = nil
      78 [-]: NAMECALL R11 R11 K25; var12 = var11; var11 = var11[0x05909209]
      79 [-]: CALL R11 6 2 ; var11 = var11(var12, var13, var14, var15, var16)
      80 [-]: GETIMPORT R12 1; var12 = 0x89326C93
      81 [-]: GETIMPORT R14 27; var14 = 0xABE067C8
      82 [-]: MOVE R15 R5  ; var15 = var5
      83 [-]: MOVE R16 R10 ; var16 = var10
      84 [-]: NAMECALL R12 R12 K25; var13 = var12; var12 = var12[0x05909209]
      85 [-]: CALL R12 5 1 ; var12(var13, var14, var15, var16)
      86 [-]: MOVE R14 R4  ; var14 = var4
      87 [-]: GETTABLEKS R15 R10 K28; var15 = var10["pitch"]
      88 [-]: NAMECALL R12 R11 K29; var13 = var11; var12 = var11[0xFB8735AB]
      89 [-]: CALL R12 4 1 ; var12(var13, var14, var15)
      90 [-]: GETIMPORT R12 31; var12 = 0xCBD666E1
      91 [-]: LOADK R13 K32; var13 = 0.5
      92 [-]: CALL R12 2 1 ; var12(var13)
      93 [-]: FORNLOOP R7 L7; nforloop end - iterate + goto L7
L 9:  94 [-]: GETIMPORT R7 34; var7 = 0x3D106989
      95 [-]: LOADK R8 K35 ; var8 = "Heist: B3: Mortar launched"
      96 [-]: CALL R7 2 1  ; var7(var8)
L10:  97 [-]: RETURN R0 0  ; 


; Name:            
; Defined at line: 189
; #Upvalues:       0
; #Parameters:     1
; Is_vararg:       0
; Max Stack Size:  3

       0 [-]: FASTCALL1 64 R0 L0; 
       1 [-]: MOVE R2 R0   ; var2 = var0
       2 [-]: GETIMPORT R1 1; var1 = 0x7B998233
       3 [-]: CALL R1 2 2  ; var1 = var1(var2)
L 0:   4 [-]: JUMPIF R1 L1 ; goto L1 if var1
       5 [-]: NAMECALL R1 R0 K2; var2 = var0; var1 = var0[0xA2880940]
       6 [-]: CALL R1 2 1  ; var1(var2)
L 1:   7 [-]: RETURN R0 0  ; 


; Name:            
; Defined at line: 195
; #Upvalues:       0
; #Parameters:     2
; Is_vararg:       0
; Max Stack Size:  7

       0 [-]: LOADN R3 10  ; var3 = 10
       1 [-]: ORK R4 R1 K0 ; var4 = var1 or 0
       2 [-]: POW R2 R3 R4 ; var2 = var3 ^ var4
       3 [-]: MUL R6 R0 R2 ; var6 = var0 * var2
       4 [-]: ADDK R5 R6 K1; var5 = var6 + 0.5
       5 [-]: FASTCALL1 12 R5 L0; 
       6 [-]: GETIMPORT R4 4; var4 = 0x5BCED4C4[0x55F27C30]
       7 [-]: CALL R4 2 2  ; var4 = var4(var5)
L 0:   8 [-]: DIV R3 R4 R2 ; var3 = var4 / var2
       9 [-]: RETURN R3 1  ; 


; Name:            
; Defined at line: 200
; #Upvalues:       1
; #Parameters:     0
; Is_vararg:       0
; Max Stack Size:  5

       0 [-]: GETUPVAL R1 0; var1 = upvalues[0]
       1 [-]: FASTCALL1 64 R1 L0; 
       2 [-]: GETIMPORT R0 1; var0 = 0x7B998233
       3 [-]: CALL R0 2 2  ; var0 = var0(var1)
L 0:   4 [-]: JUMPIF R0 L1 ; goto L1 if var0
       5 [-]: GETUPVAL R2 0; var2 = upvalues[0]
       6 [-]: LENGTH R1 R2 ; var1 = #var2
       7 [-]: GETIMPORT R2 3; var2 = 0x9BA7909F
       8 [-]: LOADK R4 K4  ; var4 = "Server.NumVirtualTestClients"
       9 [-]: NAMECALL R2 R2 K5; var3 = var2; var2 = var2[0x8151451D]
      10 [-]: CALL R2 3 2  ; var2 = var2(var3, var4)
      11 [-]: ADD R0 R1 R2 ; var0 = var1 + var2
      12 [-]: RETURN R0 1  ; 
L 1:  13 [-]: RETURN R0 0  ; 


; Name:            
; Defined at line: 208
; #Upvalues:       17
; #Parameters:     1
; Is_vararg:       0
; Max Stack Size:  9

       0 [-]: JUMPXEQKN R0 K0 L4 NOT; 
       1 [-]: GETIMPORT R1 2; var1 = 0x3D106989
       2 [-]: LOADK R2 K3  ; var2 = "Heist: B3: Stage 1: Base infiltration"
       3 [-]: CALL R1 2 1  ; var1(var2)
       4 [-]: GETIMPORT R1 5; var1 = 0x89326C93
       5 [-]: GETIMPORT R3 7; var3 = 0x0469F296
       6 [-]: LOADK R4 K8  ; var4 = "VentTeleportWaypointDestOutside"
       7 [-]: CALL R3 2 0  ; var3, ... = var3(var4)
       8 [-]: NAMECALL R1 R1 K9; var2 = var1; var1 = var1[0x46A0EBF5]
       9 [-]: CALL R1 0 2  ; var1 = var1(var2, ...)
      10 [-]: GETIMPORT R2 5; var2 = 0x89326C93
      11 [-]: GETIMPORT R4 11; var4 = 0x449A0EE7
      12 [-]: NAMECALL R5 R1 K12; var6 = var1; var5 = var1[0xD1586535]
      13 [-]: CALL R5 2 2  ; var5 = var5(var6)
      14 [-]: GETIMPORT R6 14; var6 = ZERO_ROTATION
      15 [-]: NAMECALL R2 R2 K15; var3 = var2; var2 = var2[0x05909209]
      16 [-]: CALL R2 5 2  ; var2 = var2(var3, var4, var5, var6)
      17 [-]: SETUPVAL R2 0; upvalues[2] = var0
      18 [-]: GETUPVAL R2 0; var2 = upvalues[0]
      19 [-]: LOADN R4 2   ; var4 = 2
      20 [-]: NAMECALL R2 R2 K16; var3 = var2; var2 = var2[0xBF4030D2]
      21 [-]: CALL R2 3 1  ; var2(var3, var4)
      22 [-]: GETUPVAL R2 0; var2 = upvalues[0]
      23 [-]: LOADB R4 0   ; var4 = false
      24 [-]: NAMECALL R2 R2 K17; var3 = var2; var2 = var2[0xA69CE1E5]
      25 [-]: CALL R2 3 1  ; var2(var3, var4)
      26 [-]: GETUPVAL R2 0; var2 = upvalues[0]
      27 [-]: GETIMPORT R4 19; var4 = 0xB7CBD06B
      28 [-]: LOADN R5 6   ; var5 = 6
      29 [-]: LOADN R6 5000; var6 = 5000
      30 [-]: CALL R4 3 0  ; var4, ... = var4(var5, var6)
      31 [-]: NAMECALL R2 R2 K20; var3 = var2; var2 = var2[0x53BC0559]
      32 [-]: CALL R2 0 1  ; var2(var3, ...)
      33 [-]: GETUPVAL R2 1; var2 = upvalues[1]
      34 [-]: LOADK R4 K21 ; var4 = "Lock"
      35 [-]: NAMECALL R2 R2 K22; var3 = var2; var2 = var2[0x8EB2112D]
      36 [-]: CALL R2 3 1  ; var2(var3, var4)
      37 [-]: GETUPVAL R3 2; var3 = upvalues[2]
      38 [-]: GETTABLEKS R2 R3 K23; var2 = var3[0xA1DF01D6]
      39 [-]: LOADK R3 K24 ; var3 = "/Lotus/Language/SolarisHeists/ProfitTakerBountyThreeAVent"
      40 [-]: CALL R2 2 1  ; var2(var3)
      41 [-]: GETUPVAL R4 3; var4 = upvalues[3]
      42 [-]: FASTCALL1 64 R4 L0; 
      43 [-]: GETIMPORT R3 26; var3 = 0x7B998233
      44 [-]: CALL R3 2 2  ; var3 = var3(var4)
L 0:  45 [-]: JUMPIF R3 L1 ; goto L1 if var3
      46 [-]: GETUPVAL R4 3; var4 = upvalues[3]
      47 [-]: LENGTH R3 R4 ; var3 = #var4
      48 [-]: GETIMPORT R4 28; var4 = 0x9BA7909F
      49 [-]: LOADK R6 K29 ; var6 = "Server.NumVirtualTestClients"
      50 [-]: NAMECALL R4 R4 K30; var5 = var4; var4 = var4[0x8151451D]
      51 [-]: CALL R4 3 2  ; var4 = var4(var5, var6)
      52 [-]: ADD R2 R3 R4 ; var2 = var3 + var4
      53 [-]: JUMP L2      ; goto L2
L 1:  54 [-]: LOADNIL R2   ; var2 = nil
L 2:  55 [-]: LOADN R3 1   ; var3 = 1
      56 [-]: JUMPIFNOTLT R3 R2 L3; goto L3 if var3 >= var132156
      57 [-]: GETUPVAL R4 2; var4 = upvalues[2]
      58 [-]: GETTABLEKS R3 R4 K31; var3 = var4[0x118E5C26]
      59 [-]: LOADK R4 K32 ; var4 = "/Lotus/Language/SolarisHeists/ProfitTakerBountyThreeAVentSec"
      60 [-]: LOADN R5 0   ; var5 = 0
      61 [-]: LOADK R7 K33 ; var7 = " 0 / "
      62 [-]: MOVE R8 R2   ; var8 = var2
      63 [-]: CONCAT R6 R7 R8; var6 = var7 .. var8
      64 [-]: CALL R3 4 1  ; var3(var4, var5, var6)
L 3:  65 [-]: GETUPVAL R4 4; var4 = upvalues[4]
      66 [-]: GETTABLEKS R3 R4 K34; var3 = var4[0xC474A99E]
      67 [-]: GETIMPORT R4 7; var4 = 0x0469F296
      68 [-]: LOADK R5 K35 ; var5 = "HeistB3BaseSetup"
      69 [-]: CALL R4 2 2  ; var4 = var4(var5)
      70 [-]: LOADK R5 K36 ; var5 = "TriggerPort"
      71 [-]: CALL R3 3 1  ; var3(var4, var5)
      72 [-]: GETUPVAL R4 4; var4 = upvalues[4]
      73 [-]: GETTABLEKS R3 R4 K34; var3 = var4[0xC474A99E]
      74 [-]: GETIMPORT R4 7; var4 = 0x0469F296
      75 [-]: LOADK R5 K37 ; var5 = "ResearchFacilityAgentTypeSelector"
      76 [-]: CALL R4 2 2  ; var4 = var4(var5)
      77 [-]: LOADK R5 K38 ; var5 = "Disable"
      78 [-]: CALL R3 3 1  ; var3(var4, var5)
      79 [-]: GETUPVAL R4 4; var4 = upvalues[4]
      80 [-]: GETTABLEKS R3 R4 K34; var3 = var4[0xC474A99E]
      81 [-]: GETIMPORT R4 7; var4 = 0x0469F296
      82 [-]: LOADK R5 K39 ; var5 = "ResFacProfitTakerAgentTypeVolume"
      83 [-]: CALL R4 2 2  ; var4 = var4(var5)
      84 [-]: LOADK R5 K40 ; var5 = "Enable"
      85 [-]: CALL R3 3 1  ; var3(var4, var5)
      86 [-]: GETUPVAL R4 5; var4 = upvalues[5]
      87 [-]: GETTABLEKS R3 R4 K41; var3 = var4[0x9742B85B]
      88 [-]: GETUPVAL R4 6; var4 = upvalues[6]
      89 [-]: GETIMPORT R5 7; var5 = 0x0469F296
      90 [-]: LOADK R6 K42 ; var6 = "InfiltrateLab"
      91 [-]: CALL R5 2 0  ; var5, ... = var5(var6)
      92 [-]: CALL R3 0 1  ; var3(var4, ...)
      93 [-]: RETURN R0 0  ; 
L 4:  94 [-]: JUMPXEQKN R0 K43 L7 NOT; 
      95 [-]: GETIMPORT R1 2; var1 = 0x3D106989
      96 [-]: LOADK R2 K44 ; var2 = "Heist: B3: Stage 1: Antenna hack setup"
      97 [-]: CALL R1 2 1  ; var1(var2)
      98 [-]: GETUPVAL R1 0; var1 = upvalues[0]
      99 [-]: FASTCALL1 64 R1 L5; 
     100 [-]: MOVE R3 R1   ; var3 = var1
     101 [-]: GETIMPORT R2 26; var2 = 0x7B998233
     102 [-]: CALL R2 2 2  ; var2 = var2(var3)
L 5: 103 [-]: JUMPIF R2 L6 ; goto L6 if var2
     104 [-]: NAMECALL R2 R1 K45; var3 = var1; var2 = var1[0xA2880940]
     105 [-]: CALL R2 2 1  ; var2(var3)
L 6: 106 [-]: GETUPVAL R2 5; var2 = upvalues[5]
     107 [-]: GETTABLEKS R1 R2 K41; var1 = var2[0x9742B85B]
     108 [-]: GETUPVAL R2 6; var2 = upvalues[6]
     109 [-]: GETIMPORT R3 7; var3 = 0x0469F296
     110 [-]: LOADK R4 K46 ; var4 = "HackTheConsole"
     111 [-]: CALL R3 2 0  ; var3, ... = var3(var4)
     112 [-]: CALL R1 0 1  ; var1(var2, ...)
     113 [-]: GETUPVAL R2 5; var2 = upvalues[5]
     114 [-]: GETTABLEKS R1 R2 K47; var1 = var2[0xFC87A231]
     115 [-]: CALL R1 1 1  ; var1()
     116 [-]: GETUPVAL R1 7; var1 = upvalues[7]
     117 [-]: LOADN R3 12  ; var3 = 12
     118 [-]: NAMECALL R1 R1 K48; var2 = var1; var1 = var1[0x8ABFF40E]
     119 [-]: CALL R1 3 1  ; var1(var2, var3)
     120 [-]: RETURN R0 0  ; 
L 7: 121 [-]: JUMPXEQKN R0 K49 L8 NOT; 
     122 [-]: GETIMPORT R1 2; var1 = 0x3D106989
     123 [-]: LOADK R2 K50 ; var2 = "Heist: B3: Stage 1: Waiting for first console hack"
     124 [-]: CALL R1 2 1  ; var1(var2)
     125 [-]: GETUPVAL R2 2; var2 = upvalues[2]
     126 [-]: GETTABLEKS R1 R2 K23; var1 = var2[0xA1DF01D6]
     127 [-]: LOADK R2 K51 ; var2 = "/Lotus/Language/SolarisHeists/ProfitTakerBountyThreeAUnlock"
     128 [-]: CALL R1 2 1  ; var1(var2)
     129 [-]: GETUPVAL R2 2; var2 = upvalues[2]
     130 [-]: GETTABLEKS R1 R2 K52; var1 = var2[0xF94B7537]
     131 [-]: CALL R1 1 1  ; var1()
     132 [-]: GETUPVAL R1 8; var1 = upvalues[8]
     133 [-]: LOADK R3 K40 ; var3 = "Enable"
     134 [-]: NAMECALL R1 R1 K22; var2 = var1; var1 = var1[0x8EB2112D]
     135 [-]: CALL R1 3 1  ; var1(var2, var3)
     136 [-]: GETIMPORT R1 54; var1 = 0x492C7F2A
     137 [-]: GETUPVAL R2 8; var2 = upvalues[8]
     138 [-]: NAMECALL R2 R2 K55; var3 = var2; var2 = var2[0xA02EE9EF]
     139 [-]: CALL R2 2 2  ; var2 = var2(var3)
     140 [-]: GETUPVAL R3 8; var3 = upvalues[8]
     141 [-]: NAMECALL R3 R3 K56; var4 = var3; var3 = var3[0xCB3851B8]
     142 [-]: CALL R3 2 0  ; var3, ... = var3(var4)
     143 [-]: CALL R1 0 2  ; var1 = var1(var2, ...)
     144 [-]: GETIMPORT R2 5; var2 = 0x89326C93
     145 [-]: GETIMPORT R4 11; var4 = 0x449A0EE7
     146 [-]: GETUPVAL R6 8; var6 = upvalues[8]
     147 [-]: NAMECALL R6 R6 K12; var7 = var6; var6 = var6[0xD1586535]
     148 [-]: CALL R6 2 2  ; var6 = var6(var7)
     149 [-]: ADD R5 R6 R1 ; var5 = var6 + var1
     150 [-]: GETIMPORT R6 14; var6 = ZERO_ROTATION
     151 [-]: NAMECALL R2 R2 K15; var3 = var2; var2 = var2[0x05909209]
     152 [-]: CALL R2 5 2  ; var2 = var2(var3, var4, var5, var6)
     153 [-]: SETUPVAL R2 0; upvalues[2] = var0
     154 [-]: RETURN R0 0  ; 
L 8: 155 [-]: JUMPXEQKN R0 K57 L11 NOT; 
     156 [-]: GETIMPORT R1 2; var1 = 0x3D106989
     157 [-]: LOADK R2 K58 ; var2 = "Heist: B3: Stage 1: First console hacked"
     158 [-]: CALL R1 2 1  ; var1(var2)
     159 [-]: GETUPVAL R1 8; var1 = upvalues[8]
     160 [-]: LOADK R3 K38 ; var3 = "Disable"
     161 [-]: NAMECALL R1 R1 K22; var2 = var1; var1 = var1[0x8EB2112D]
     162 [-]: CALL R1 3 1  ; var1(var2, var3)
     163 [-]: GETUPVAL R1 0; var1 = upvalues[0]
     164 [-]: FASTCALL1 64 R1 L9; 
     165 [-]: MOVE R3 R1   ; var3 = var1
     166 [-]: GETIMPORT R2 26; var2 = 0x7B998233
     167 [-]: CALL R2 2 2  ; var2 = var2(var3)
L 9: 168 [-]: JUMPIF R2 L10; goto L10 if var2
     169 [-]: NAMECALL R2 R1 K45; var3 = var1; var2 = var1[0xA2880940]
     170 [-]: CALL R2 2 1  ; var2(var3)
L10: 171 [-]: GETUPVAL R2 2; var2 = upvalues[2]
     172 [-]: GETTABLEKS R1 R2 K59; var1 = var2[0xDC3B2033]
     173 [-]: CALL R1 1 1  ; var1()
     174 [-]: GETUPVAL R2 5; var2 = upvalues[5]
     175 [-]: GETTABLEKS R1 R2 K41; var1 = var2[0x9742B85B]
     176 [-]: GETUPVAL R2 6; var2 = upvalues[6]
     177 [-]: GETIMPORT R3 7; var3 = 0x0469F296
     178 [-]: LOADK R4 K60 ; var4 = "HackedInsideConsole"
     179 [-]: CALL R3 2 0  ; var3, ... = var3(var4)
     180 [-]: CALL R1 0 1  ; var1(var2, ...)
     181 [-]: GETIMPORT R1 62; var1 = 0xCBD666E1
     182 [-]: LOADN R2 3   ; var2 = 3
     183 [-]: CALL R1 2 1  ; var1(var2)
     184 [-]: GETUPVAL R2 4; var2 = upvalues[4]
     185 [-]: GETTABLEKS R1 R2 K34; var1 = var2[0xC474A99E]
     186 [-]: GETIMPORT R2 7; var2 = 0x0469F296
     187 [-]: LOADK R3 K63 ; var3 = "HeistB3ConsoleDeniedSeq"
     188 [-]: CALL R2 2 2  ; var2 = var2(var3)
     189 [-]: LOADK R3 K40 ; var3 = "Enable"
     190 [-]: CALL R1 3 1  ; var1(var2, var3)
     191 [-]: GETUPVAL R2 5; var2 = upvalues[5]
     192 [-]: GETTABLEKS R1 R2 K47; var1 = var2[0xFC87A231]
     193 [-]: CALL R1 1 1  ; var1()
     194 [-]: GETUPVAL R2 2; var2 = upvalues[2]
     195 [-]: GETTABLEKS R1 R2 K23; var1 = var2[0xA1DF01D6]
     196 [-]: LOADK R2 K51 ; var2 = "/Lotus/Language/SolarisHeists/ProfitTakerBountyThreeAUnlock"
     197 [-]: GETUPVAL R4 2; var4 = upvalues[2]
     198 [-]: GETTABLEKS R3 R4 K64; var3 = var4["LETTER_ICON_A"]
     199 [-]: CALL R1 3 1  ; var1(var2, var3)
     200 [-]: GETUPVAL R2 4; var2 = upvalues[4]
     201 [-]: GETTABLEKS R1 R2 K34; var1 = var2[0xC474A99E]
     202 [-]: GETIMPORT R2 7; var2 = 0x0469F296
     203 [-]: LOADK R3 K65 ; var3 = "HeistB3ConsoleMarker"
     204 [-]: CALL R2 2 2  ; var2 = var2(var3)
     205 [-]: LOADK R3 K40 ; var3 = "Enable"
     206 [-]: CALL R1 3 1  ; var1(var2, var3)
     207 [-]: GETUPVAL R1 7; var1 = upvalues[7]
     208 [-]: LOADN R3 15  ; var3 = 15
     209 [-]: NAMECALL R1 R1 K48; var2 = var1; var1 = var1[0x8ABFF40E]
     210 [-]: CALL R1 3 1  ; var1(var2, var3)
     211 [-]: RETURN R0 0  ; 
L11: 212 [-]: JUMPXEQKN R0 K66 L12 NOT; 
     213 [-]: GETIMPORT R1 2; var1 = 0x3D106989
     214 [-]: LOADK R2 K67 ; var2 = "Heist: B3: Stage 1: Consoles reset"
     215 [-]: CALL R1 2 1  ; var1(var2)
     216 [-]: GETUPVAL R2 2; var2 = upvalues[2]
     217 [-]: GETTABLEKS R1 R2 K68; var1 = var2[0x18DD08AC]
     218 [-]: CALL R1 1 1  ; var1()
     219 [-]: GETUPVAL R2 2; var2 = upvalues[2]
     220 [-]: GETTABLEKS R1 R2 K23; var1 = var2[0xA1DF01D6]
     221 [-]: LOADK R2 K51 ; var2 = "/Lotus/Language/SolarisHeists/ProfitTakerBountyThreeAUnlock"
     222 [-]: GETUPVAL R4 2; var4 = upvalues[2]
     223 [-]: GETTABLEKS R3 R4 K64; var3 = var4["LETTER_ICON_A"]
     224 [-]: CALL R1 3 1  ; var1(var2, var3)
     225 [-]: GETUPVAL R2 2; var2 = upvalues[2]
     226 [-]: GETTABLEKS R1 R2 K52; var1 = var2[0xF94B7537]
     227 [-]: CALL R1 1 1  ; var1()
     228 [-]: GETUPVAL R2 4; var2 = upvalues[4]
     229 [-]: GETTABLEKS R1 R2 K34; var1 = var2[0xC474A99E]
     230 [-]: GETIMPORT R2 7; var2 = 0x0469F296
     231 [-]: LOADK R3 K63 ; var3 = "HeistB3ConsoleDeniedSeq"
     232 [-]: CALL R2 2 2  ; var2 = var2(var3)
     233 [-]: LOADK R3 K40 ; var3 = "Enable"
     234 [-]: CALL R1 3 1  ; var1(var2, var3)
     235 [-]: GETUPVAL R2 5; var2 = upvalues[5]
     236 [-]: GETTABLEKS R1 R2 K41; var1 = var2[0x9742B85B]
     237 [-]: GETUPVAL R2 6; var2 = upvalues[6]
     238 [-]: GETIMPORT R3 7; var3 = 0x0469F296
     239 [-]: LOADK R4 K69 ; var4 = "HackedConsoleRestarted"
     240 [-]: CALL R3 2 0  ; var3, ... = var3(var4)
     241 [-]: CALL R1 0 1  ; var1(var2, ...)
     242 [-]: GETUPVAL R2 5; var2 = upvalues[5]
     243 [-]: GETTABLEKS R1 R2 K47; var1 = var2[0xFC87A231]
     244 [-]: CALL R1 1 1  ; var1()
     245 [-]: GETUPVAL R1 7; var1 = upvalues[7]
     246 [-]: LOADN R3 15  ; var3 = 15
     247 [-]: NAMECALL R1 R1 K48; var2 = var1; var1 = var1[0x8ABFF40E]
     248 [-]: CALL R1 3 1  ; var1(var2, var3)
     249 [-]: RETURN R0 0  ; 
L12: 250 [-]: JUMPXEQKN R0 K70 L16 NOT; 
     251 [-]: GETIMPORT R1 2; var1 = 0x3D106989
     252 [-]: LOADK R2 K71 ; var2 = "Heist: B3: Stage 1: Waiting for console hack"
     253 [-]: CALL R1 2 1  ; var1(var2)
     254 [-]: GETUPVAL R1 8; var1 = upvalues[8]
     255 [-]: LOADK R3 K40 ; var3 = "Enable"
     256 [-]: NAMECALL R1 R1 K22; var2 = var1; var1 = var1[0x8EB2112D]
     257 [-]: CALL R1 3 1  ; var1(var2, var3)
     258 [-]: GETUPVAL R1 9; var1 = upvalues[9]
     259 [-]: LOADK R3 K38 ; var3 = "Disable"
     260 [-]: NAMECALL R1 R1 K22; var2 = var1; var1 = var1[0x8EB2112D]
     261 [-]: CALL R1 3 1  ; var1(var2, var3)
     262 [-]: GETUPVAL R2 5; var2 = upvalues[5]
     263 [-]: GETTABLEKS R1 R2 K41; var1 = var2[0x9742B85B]
     264 [-]: GETUPVAL R2 6; var2 = upvalues[6]
     265 [-]: GETIMPORT R3 7; var3 = 0x0469F296
     266 [-]: LOADK R4 K72 ; var4 = "OrbIntro"
     267 [-]: CALL R3 2 0  ; var3, ... = var3(var4)
     268 [-]: CALL R1 0 1  ; var1(var2, ...)
     269 [-]: GETUPVAL R1 10; var1 = upvalues[10]
     270 [-]: GETUPVAL R3 11; var3 = upvalues[11]
     271 [-]: LOADN R4 0   ; var4 = 0
     272 [-]: NAMECALL R1 R1 K73; var2 = var1; var1 = var1[0x751F061D]
     273 [-]: CALL R1 4 1  ; var1(var2, var3, var4)
     274 [-]: GETUPVAL R1 10; var1 = upvalues[10]
     275 [-]: GETUPVAL R3 12; var3 = upvalues[12]
     276 [-]: LOADN R4 0   ; var4 = 0
     277 [-]: NAMECALL R1 R1 K73; var2 = var1; var1 = var1[0x751F061D]
     278 [-]: CALL R1 4 1  ; var1(var2, var3, var4)
     279 [-]: GETIMPORT R1 5; var1 = 0x89326C93
     280 [-]: NAMECALL R1 R1 K74; var2 = var1; var1 = var1[0x7D108DDB]
     281 [-]: CALL R1 2 2  ; var1 = var1(var2)
     282 [-]: LENGTH R2 R1 ; var2 = #var1
     283 [-]: JUMPXEQKN R2 K75 L13 NOT; 
     284 [-]: LOADN R2 45  ; var2 = 45
     285 [-]: SETUPVAL R2 13; upvalues[2] = var13
     286 [-]: JUMP L14     ; goto L14
L13: 287 [-]: LOADN R2 5   ; var2 = 5
     288 [-]: SETUPVAL R2 13; upvalues[2] = var13
L14: 289 [-]: GETUPVAL R2 10; var2 = upvalues[10]
     290 [-]: GETUPVAL R4 14; var4 = upvalues[14]
     291 [-]: GETUPVAL R5 13; var5 = upvalues[13]
     292 [-]: NAMECALL R2 R2 K73; var3 = var2; var2 = var2[0x751F061D]
     293 [-]: CALL R2 4 1  ; var2(var3, var4, var5)
     294 [-]: GETUPVAL R3 15; var3 = upvalues[15]
     295 [-]: FASTCALL1 64 R3 L15; 
     296 [-]: GETIMPORT R2 26; var2 = 0x7B998233
     297 [-]: CALL R2 2 2  ; var2 = var2(var3)
L15: 298 [-]: JUMPIF R2 L23; goto L23 if var2
     299 [-]: GETUPVAL R2 15; var2 = upvalues[15]
     300 [-]: LOADN R4 0   ; var4 = 0
     301 [-]: NAMECALL R2 R2 K76; var3 = var2; var2 = var2[0x8CFF1D7A]
     302 [-]: CALL R2 3 1  ; var2(var3, var4)
     303 [-]: GETUPVAL R2 15; var2 = upvalues[15]
     304 [-]: LOADB R4 1   ; var4 = true
     305 [-]: NAMECALL R2 R2 K77; var3 = var2; var2 = var2[0x543A0B5E]
     306 [-]: CALL R2 3 1  ; var2(var3, var4)
     307 [-]: RETURN R0 0  ; 
L16: 308 [-]: JUMPXEQKN R0 K78 L18 NOT; 
     309 [-]: GETIMPORT R1 2; var1 = 0x3D106989
     310 [-]: LOADK R2 K79 ; var2 = "Heist: B3: Stage 1: Console countdown"
     311 [-]: CALL R1 2 1  ; var1(var2)
     312 [-]: GETUPVAL R2 2; var2 = upvalues[2]
     313 [-]: GETTABLEKS R1 R2 K80; var1 = var2[0xE8FA0E68]
     314 [-]: GETUPVAL R2 13; var2 = upvalues[13]
     315 [-]: LOADB R3 0   ; var3 = false
     316 [-]: LOADB R4 1   ; var4 = true
     317 [-]: LOADB R5 0   ; var5 = false
     318 [-]: GETUPVAL R7 2; var7 = upvalues[2]
     319 [-]: GETTABLEKS R6 R7 K81; var6 = var7["TIMELIMIT_STRING"]
     320 [-]: CALL R1 6 1  ; var1(var2, var3, var4, var5, var6)
     321 [-]: GETUPVAL R2 2; var2 = upvalues[2]
     322 [-]: GETTABLEKS R1 R2 K23; var1 = var2[0xA1DF01D6]
     323 [-]: LOADK R2 K82 ; var2 = "/Lotus/Language/SolarisHeists/ProfitTakerBountyThreeAHack"
     324 [-]: GETUPVAL R4 2; var4 = upvalues[2]
     325 [-]: GETTABLEKS R3 R4 K83; var3 = var4["LETTER_ICON_B"]
     326 [-]: CALL R1 3 1  ; var1(var2, var3)
     327 [-]: GETUPVAL R1 9; var1 = upvalues[9]
     328 [-]: LOADK R3 K40 ; var3 = "Enable"
     329 [-]: NAMECALL R1 R1 K22; var2 = var1; var1 = var1[0x8EB2112D]
     330 [-]: CALL R1 3 1  ; var1(var2, var3)
     331 [-]: GETUPVAL R1 1; var1 = upvalues[1]
     332 [-]: LOADK R3 K84 ; var3 = "Unlock"
     333 [-]: NAMECALL R1 R1 K22; var2 = var1; var1 = var1[0x8EB2112D]
     334 [-]: CALL R1 3 1  ; var1(var2, var3)
     335 [-]: GETUPVAL R2 15; var2 = upvalues[15]
     336 [-]: FASTCALL1 64 R2 L17; 
     337 [-]: GETIMPORT R1 26; var1 = 0x7B998233
     338 [-]: CALL R1 2 2  ; var1 = var1(var2)
L17: 339 [-]: JUMPIF R1 L23; goto L23 if var1
     340 [-]: GETUPVAL R1 15; var1 = upvalues[15]
     341 [-]: LOADN R3 0   ; var3 = 0
     342 [-]: NAMECALL R1 R1 K76; var2 = var1; var1 = var1[0x8CFF1D7A]
     343 [-]: CALL R1 3 1  ; var1(var2, var3)
     344 [-]: GETUPVAL R1 15; var1 = upvalues[15]
     345 [-]: LOADB R3 0   ; var3 = false
     346 [-]: NAMECALL R1 R1 K77; var2 = var1; var1 = var1[0x543A0B5E]
     347 [-]: CALL R1 3 1  ; var1(var2, var3)
     348 [-]: RETURN R0 0  ; 
L18: 349 [-]: JUMPXEQKN R0 K85 L23 NOT; 
     350 [-]: GETIMPORT R1 2; var1 = 0x3D106989
     351 [-]: LOADK R2 K86 ; var2 = "Heist: B3: Stage 1: Consoles stage completed"
     352 [-]: CALL R1 2 1  ; var1(var2)
     353 [-]: GETUPVAL R2 2; var2 = upvalues[2]
     354 [-]: GETTABLEKS R1 R2 K68; var1 = var2[0x18DD08AC]
     355 [-]: CALL R1 1 1  ; var1()
     356 [-]: GETUPVAL R2 2; var2 = upvalues[2]
     357 [-]: GETTABLEKS R1 R2 K59; var1 = var2[0xDC3B2033]
     358 [-]: CALL R1 1 1  ; var1()
     359 [-]: GETUPVAL R1 0; var1 = upvalues[0]
     360 [-]: FASTCALL1 64 R1 L19; 
     361 [-]: MOVE R3 R1   ; var3 = var1
     362 [-]: GETIMPORT R2 26; var2 = 0x7B998233
     363 [-]: CALL R2 2 2  ; var2 = var2(var3)
L19: 364 [-]: JUMPIF R2 L20; goto L20 if var2
     365 [-]: NAMECALL R2 R1 K45; var3 = var1; var2 = var1[0xA2880940]
     366 [-]: CALL R2 2 1  ; var2(var3)
L20: 367 [-]: GETUPVAL R2 4; var2 = upvalues[4]
     368 [-]: GETTABLEKS R1 R2 K87; var1 = var2[0xCDCBD25D]
     369 [-]: GETIMPORT R2 89; var2 = 0x1D376DF1
     370 [-]: GETUPVAL R4 16; var4 = upvalues[16]
     371 [-]: GETTABLEKS R3 R4 K90; var3 = var4["pos"]
     372 [-]: GETUPVAL R5 16; var5 = upvalues[16]
     373 [-]: GETTABLEKS R4 R5 K91; var4 = var5["radius"]
     374 [-]: CALL R1 4 2  ; var1 = var1(var2, var3, var4)
     375 [-]: SETUPVAL R1 0; upvalues[1] = var0
     376 [-]: GETUPVAL R1 8; var1 = upvalues[8]
     377 [-]: LOADK R3 K38 ; var3 = "Disable"
     378 [-]: NAMECALL R1 R1 K22; var2 = var1; var1 = var1[0x8EB2112D]
     379 [-]: CALL R1 3 1  ; var1(var2, var3)
     380 [-]: GETUPVAL R1 9; var1 = upvalues[9]
     381 [-]: LOADK R3 K38 ; var3 = "Disable"
     382 [-]: NAMECALL R1 R1 K22; var2 = var1; var1 = var1[0x8EB2112D]
     383 [-]: CALL R1 3 1  ; var1(var2, var3)
     384 [-]: GETUPVAL R2 4; var2 = upvalues[4]
     385 [-]: GETTABLEKS R1 R2 K34; var1 = var2[0xC474A99E]
     386 [-]: GETIMPORT R2 7; var2 = 0x0469F296
     387 [-]: LOADK R3 K92 ; var3 = "HeistB3BaseShutdown"
     388 [-]: CALL R2 2 2  ; var2 = var2(var3)
     389 [-]: LOADK R3 K36 ; var3 = "TriggerPort"
     390 [-]: CALL R1 3 1  ; var1(var2, var3)
     391 [-]: GETUPVAL R2 4; var2 = upvalues[4]
     392 [-]: GETTABLEKS R1 R2 K34; var1 = var2[0xC474A99E]
     393 [-]: GETIMPORT R2 7; var2 = 0x0469F296
     394 [-]: LOADK R3 K65 ; var3 = "HeistB3ConsoleMarker"
     395 [-]: CALL R2 2 2  ; var2 = var2(var3)
     396 [-]: LOADK R3 K38 ; var3 = "Disable"
     397 [-]: CALL R1 3 1  ; var1(var2, var3)
     398 [-]: GETUPVAL R2 5; var2 = upvalues[5]
     399 [-]: GETTABLEKS R1 R2 K41; var1 = var2[0x9742B85B]
     400 [-]: GETUPVAL R2 6; var2 = upvalues[6]
     401 [-]: GETIMPORT R3 7; var3 = 0x0469F296
     402 [-]: LOADK R4 K93 ; var4 = "HackDone"
     403 [-]: CALL R3 2 0  ; var3, ... = var3(var4)
     404 [-]: CALL R1 0 1  ; var1(var2, ...)
     405 [-]: GETUPVAL R2 5; var2 = upvalues[5]
     406 [-]: GETTABLEKS R1 R2 K47; var1 = var2[0xFC87A231]
     407 [-]: CALL R1 1 1  ; var1()
     408 [-]: GETUPVAL R2 15; var2 = upvalues[15]
     409 [-]: FASTCALL1 64 R2 L21; 
     410 [-]: GETIMPORT R1 26; var1 = 0x7B998233
     411 [-]: CALL R1 2 2  ; var1 = var1(var2)
L21: 412 [-]: JUMPIF R1 L22; goto L22 if var1
     413 [-]: GETUPVAL R1 15; var1 = upvalues[15]
     414 [-]: LOADN R3 0   ; var3 = 0
     415 [-]: NAMECALL R1 R1 K76; var2 = var1; var1 = var1[0x8CFF1D7A]
     416 [-]: CALL R1 3 1  ; var1(var2, var3)
     417 [-]: GETUPVAL R1 15; var1 = upvalues[15]
     418 [-]: LOADB R3 1   ; var3 = true
     419 [-]: NAMECALL R1 R1 K77; var2 = var1; var1 = var1[0x543A0B5E]
     420 [-]: CALL R1 3 1  ; var1(var2, var3)
L22: 421 [-]: GETUPVAL R1 7; var1 = upvalues[7]
     422 [-]: LOADN R3 20  ; var3 = 20
     423 [-]: NAMECALL R1 R1 K48; var2 = var1; var1 = var1[0x8ABFF40E]
     424 [-]: CALL R1 3 1  ; var1(var2, var3)
L23: 425 [-]: RETURN R0 0  ; 


; Name:            
; Defined at line: 333
; #Upvalues:       9
; #Parameters:     1
; Is_vararg:       0
; Max Stack Size:  7

       0 [-]: GETUPVAL R2 0; var2 = upvalues[0]
       1 [-]: FASTCALL1 64 R2 L0; 
       2 [-]: GETIMPORT R1 1; var1 = 0x7B998233
       3 [-]: CALL R1 2 2  ; var1 = var1(var2)
L 0:   4 [-]: JUMPIFNOT R1 L1; goto L1 if not var1
       5 [-]: GETUPVAL R2 1; var2 = upvalues[1]
       6 [-]: GETTABLEKS R1 R2 K2; var1 = var2[0xCDCBD25D]
       7 [-]: GETIMPORT R2 4; var2 = 0x1D376DF1
       8 [-]: GETUPVAL R4 2; var4 = upvalues[2]
       9 [-]: GETTABLEKS R3 R4 K5; var3 = var4["pos"]
      10 [-]: GETUPVAL R5 2; var5 = upvalues[2]
      11 [-]: GETTABLEKS R4 R5 K6; var4 = var5["radius"]
      12 [-]: CALL R1 4 2  ; var1 = var1(var2, var3, var4)
      13 [-]: SETUPVAL R1 0; upvalues[1] = var0
L 1:  14 [-]: JUMPXEQKN R0 K7 L4 NOT; 
      15 [-]: GETIMPORT R1 9; var1 = 0x3D106989
      16 [-]: LOADK R2 K10 ; var2 = "Heist: B3: Stage 2: Mortar strike"
      17 [-]: CALL R1 2 1  ; var1(var2)
      18 [-]: GETUPVAL R2 3; var2 = upvalues[3]
      19 [-]: GETTABLEKS R1 R2 K11; var1 = var2[0x9742B85B]
      20 [-]: GETUPVAL R2 4; var2 = upvalues[4]
      21 [-]: GETIMPORT R3 13; var3 = 0x0469F296
      22 [-]: LOADK R4 K14 ; var4 = "OrbMortarIncoming"
      23 [-]: CALL R3 2 0  ; var3, ... = var3(var4)
      24 [-]: CALL R1 0 1  ; var1(var2, ...)
      25 [-]: GETUPVAL R2 1; var2 = upvalues[1]
      26 [-]: GETTABLEKS R1 R2 K15; var1 = var2[0xC474A99E]
      27 [-]: GETIMPORT R2 13; var2 = 0x0469F296
      28 [-]: LOADK R3 K16 ; var3 = "HeistB3MortarLaunchSeq"
      29 [-]: CALL R2 2 2  ; var2 = var2(var3)
      30 [-]: LOADK R3 K17 ; var3 = "Enable"
      31 [-]: CALL R1 3 1  ; var1(var2, var3)
      32 [-]: GETIMPORT R1 19; var1 = 0x89326C93
      33 [-]: GETIMPORT R3 13; var3 = 0x0469F296
      34 [-]: LOADK R4 K20 ; var4 = "FortunaMortarTarget"
      35 [-]: CALL R3 2 0  ; var3, ... = var3(var4)
      36 [-]: NAMECALL R1 R1 K21; var2 = var1; var1 = var1[0x46A0EBF5]
      37 [-]: CALL R1 0 2  ; var1 = var1(var2, ...)
      38 [-]: GETUPVAL R2 5; var2 = upvalues[5]
      39 [-]: MOVE R3 R1   ; var3 = var1
      40 [-]: LOADN R4 8   ; var4 = 8
      41 [-]: LOADN R5 10  ; var5 = 10
      42 [-]: CALL R2 4 1  ; var2(var3, var4, var5)
      43 [-]: LOADN R2 0   ; var2 = 0
L 2:  44 [-]: GETIMPORT R3 24; var3 = _T["CamperOrbDamaged"]
      45 [-]: JUMPIF R3 L3 ; goto L3 if var3
      46 [-]: LOADN R3 10  ; var3 = 10
      47 [-]: JUMPIFNOTLT R2 R3 L3; goto L3 if var2 >= var1704737
      48 [-]: GETIMPORT R3 26; var3 = 0xFFF641AF
      49 [-]: CALL R3 1 2  ; var3 = var3()
      50 [-]: ADD R2 R2 R3 ; var2 = var2 + var3
      51 [-]: GETIMPORT R3 28; var3 = 0xCBD666E1
      52 [-]: LOADN R4 0   ; var4 = 0
      53 [-]: CALL R3 2 1  ; var3(var4)
      54 [-]: JUMPBACK L2  ; goto L2
L 3:  55 [-]: GETUPVAL R3 6; var3 = upvalues[6]
      56 [-]: GETIMPORT R5 13; var5 = 0x0469F296
      57 [-]: LOADK R6 K29 ; var6 = "ArtilleryHeistStage"
      58 [-]: CALL R5 2 2  ; var5 = var5(var6)
      59 [-]: LOADN R6 2   ; var6 = 2
      60 [-]: NAMECALL R3 R3 K30; var4 = var3; var3 = var3[0x751F061D]
      61 [-]: CALL R3 4 1  ; var3(var4, var5, var6)
      62 [-]: GETUPVAL R4 3; var4 = upvalues[3]
      63 [-]: GETTABLEKS R3 R4 K11; var3 = var4[0x9742B85B]
      64 [-]: GETUPVAL R4 4; var4 = upvalues[4]
      65 [-]: GETIMPORT R5 13; var5 = 0x0469F296
      66 [-]: LOADK R6 K31 ; var6 = "OrbMortarHit"
      67 [-]: CALL R5 2 0  ; var5, ... = var5(var6)
      68 [-]: CALL R3 0 1  ; var3(var4, ...)
      69 [-]: GETUPVAL R4 3; var4 = upvalues[3]
      70 [-]: GETTABLEKS R3 R4 K32; var3 = var4[0xFC87A231]
      71 [-]: CALL R3 1 1  ; var3()
      72 [-]: GETUPVAL R3 7; var3 = upvalues[7]
      73 [-]: LOADN R5 21  ; var5 = 21
      74 [-]: NAMECALL R3 R3 K33; var4 = var3; var3 = var3[0x8ABFF40E]
      75 [-]: CALL R3 3 1  ; var3(var4, var5)
      76 [-]: RETURN R0 0  ; 
L 4:  77 [-]: JUMPXEQKN R0 K34 L5 NOT; 
      78 [-]: GETIMPORT R1 9; var1 = 0x3D106989
      79 [-]: LOADK R2 K35 ; var2 = "Heist: B3: Stage 2: Mortar strike completed"
      80 [-]: CALL R1 2 1  ; var1(var2)
      81 [-]: GETUPVAL R2 8; var2 = upvalues[8]
      82 [-]: GETTABLEKS R1 R2 K36; var1 = var2[0xDC3B2033]
      83 [-]: CALL R1 1 1  ; var1()
      84 [-]: GETUPVAL R2 3; var2 = upvalues[3]
      85 [-]: GETTABLEKS R1 R2 K11; var1 = var2[0x9742B85B]
      86 [-]: GETUPVAL R2 4; var2 = upvalues[4]
      87 [-]: GETIMPORT R3 13; var3 = 0x0469F296
      88 [-]: LOADK R4 K37 ; var4 = "OrbFightStarted"
      89 [-]: CALL R3 2 0  ; var3, ... = var3(var4)
      90 [-]: CALL R1 0 1  ; var1(var2, ...)
      91 [-]: GETUPVAL R2 3; var2 = upvalues[3]
      92 [-]: GETTABLEKS R1 R2 K32; var1 = var2[0xFC87A231]
      93 [-]: CALL R1 1 1  ; var1()
      94 [-]: GETIMPORT R1 38; var1 = _T
      95 [-]: LOADB R2 0   ; var2 = false
      96 [-]: SETTABLEKS R2 R1 K23; var2["CamperOrbDamaged"] = var1
      97 [-]: GETUPVAL R1 7; var1 = upvalues[7]
      98 [-]: LOADN R3 30  ; var3 = 30
      99 [-]: NAMECALL R1 R1 K33; var2 = var1; var1 = var1[0x8ABFF40E]
     100 [-]: CALL R1 3 1  ; var1(var2, var3)
L 5: 101 [-]: RETURN R0 0  ; 


; Name:            
; Defined at line: 373
; #Upvalues:       10
; #Parameters:     1
; Is_vararg:       0
; Max Stack Size:  13

       0 [-]: GETUPVAL R2 0; var2 = upvalues[0]
       1 [-]: FASTCALL1 64 R2 L0; 
       2 [-]: GETIMPORT R1 1; var1 = 0x7B998233
       3 [-]: CALL R1 2 2  ; var1 = var1(var2)
L 0:   4 [-]: JUMPIFNOT R1 L1; goto L1 if not var1
       5 [-]: LOADN R1 0   ; var1 = 0
       6 [-]: SETUPVAL R1 0; upvalues[1] = var0
L 1:   7 [-]: GETUPVAL R3 1; var3 = upvalues[1]
       8 [-]: GETTABLEKS R2 R3 K2; var2 = var3[0x01CE6573]
       9 [-]: CALL R2 1 0  ; var2, ... = var2()
      10 [-]: FASTCALL 64 L2; 
      11 [-]: GETIMPORT R1 1; var1 = 0x7B998233
      12 [-]: CALL R1 0 2  ; var1 = var1(var2, ...)
L 2:  13 [-]: JUMPIFNOT R1 L5; goto L5 if not var1
      14 [-]: GETUPVAL R5 0; var5 = upvalues[0]
           16 [-]: MULK R7 R4 K5; var7 = var4 * 10
      17 [-]: ADDK R6 R7 K6; var6 = var7 + 0.5
      18 [-]: FASTCALL1 12 R6 L3; 
      19 [-]: GETIMPORT R5 9; var5 = 0x5BCED4C4[0x55F27C30]
      20 [-]: CALL R5 2 2  ; var5 = var5(var6)
L 3:       22 [-]: MULK R2 R3 K3; var2 = var3 * 100
      23 [-]: FASTCALL2K 19 R2 K3 L4; 
      24 [-]: LOADK R3 K3  ; var3 = 100
      25 [-]: GETIMPORT R1 11; var1 = 0x5BCED4C4[0xAC1B386A]
      26 [-]: CALL R1 3 2  ; var1 = var1(var2, var3)
L 4:  27 [-]: GETUPVAL R3 1; var3 = upvalues[1]
      28 [-]: GETTABLEKS R2 R3 K12; var2 = var3[0xEA753E99]
      29 [-]: LOADK R3 K13 ; var3 = "/Lotus/Language/SolarisHeists/ProfitTakerBountyThreeCDataGathered"
      30 [-]: MOVE R4 R1   ; var4 = var1
      31 [-]: LOADN R5 100 ; var5 = 100
      32 [-]: LOADNIL R6   ; var6 = nil
      33 [-]: LOADB R7 1   ; var7 = true
      34 [-]: CALL R2 6 1  ; var2(var3, var4, var5, var6, var7)
L 5:  35 [-]: GETUPVAL R2 2; var2 = upvalues[2]
      36 [-]: FASTCALL1 64 R2 L6; 
      37 [-]: GETIMPORT R1 1; var1 = 0x7B998233
      38 [-]: CALL R1 2 2  ; var1 = var1(var2)
L 6:  39 [-]: JUMPIFNOT R1 L7; goto L7 if not var1
      40 [-]: LOADN R1 44  ; var1 = 44
      41 [-]: JUMPIFNOTLT R0 R1 L7; goto L7 if var0 >= var197180
      42 [-]: GETUPVAL R2 3; var2 = upvalues[3]
      43 [-]: GETTABLEKS R1 R2 K14; var1 = var2[0xCDCBD25D]
      44 [-]: GETIMPORT R2 16; var2 = 0x1D376DF1
      45 [-]: GETUPVAL R4 4; var4 = upvalues[4]
      46 [-]: GETTABLEKS R3 R4 K17; var3 = var4["pos"]
      47 [-]: GETUPVAL R5 4; var5 = upvalues[4]
      48 [-]: GETTABLEKS R4 R5 K18; var4 = var5["radius"]
      49 [-]: CALL R1 4 2  ; var1 = var1(var2, var3, var4)
      50 [-]: SETUPVAL R1 2; upvalues[1] = var2
L 7:  51 [-]: NEWTABLE R1 0 5; var1 = {}
      52 [-]: LOADN R2 31  ; var2 = 31
      53 [-]: LOADN R3 33  ; var3 = 33
      54 [-]: LOADN R4 35  ; var4 = 35
      55 [-]: LOADN R5 40  ; var5 = 40
      56 [-]: LOADN R6 42  ; var6 = 42
      57 [-]: SETLIST R1 R2 5 [1]; var1[1] = var2; var1[2] = var3; var1[3] = var4; var1[4] = var5; var1[5] = var6; var1[6] = var7; 
      58 [-]: NEWTABLE R2 0 5; var2 = {}
      59 [-]: LOADK R3 K19 ; var3 = "A"
      60 [-]: LOADK R4 K20 ; var4 = "B"
      61 [-]: LOADK R5 K21 ; var5 = "C"
      62 [-]: LOADK R6 K22 ; var6 = "D"
      63 [-]: LOADK R7 K23 ; var7 = "E"
      64 [-]: SETLIST R2 R3 5 [1]; var2[1] = var3; var2[2] = var4; var2[3] = var5; var2[4] = var6; var2[5] = var7; var2[6] = var8; 
      65 [-]: GETIMPORT R3 25; var3 = 0xC8802016
      66 [-]: MOVE R4 R1   ; var4 = var1
      67 [-]: CALL R3 2 4  ; var3, var4, var5 = var3(var4)
      68 [-]: FORGPREP_INEXT R3 L9; 
L 8:  69 [-]: JUMPIFNOTEQ R0 R7 L9; goto L9 if var0 ~= var1771553
      70 [-]: GETIMPORT R8 27; var8 = 0x0469F296
      71 [-]: LOADK R10 K28; var10 = "OrbFightProgress"
      72 [-]: GETTABLE R11 R2 R6; var11 = var2[var6]
      73 [-]: CONCAT R9 R10 R11; var9 = var10 .. var11
      74 [-]: CALL R8 2 2  ; var8 = var8(var9)
      75 [-]: GETUPVAL R10 5; var10 = upvalues[5]
      76 [-]: GETTABLEKS R9 R10 K29; var9 = var10[0x9742B85B]
      77 [-]: GETUPVAL R10 6; var10 = upvalues[6]
      78 [-]: MOVE R11 R8  ; var11 = var8
      79 [-]: CALL R9 3 1  ; var9(var10, var11)
      80 [-]: GETIMPORT R9 31; var9 = 0x3D106989
      81 [-]: LOADK R11 K32; var11 = "Heist: B3: Stage 3: Dialog "
      82 [-]: GETTABLE R12 R2 R6; var12 = var2[var6]
      83 [-]: CONCAT R10 R11 R12; var10 = var11 .. var12
      84 [-]: CALL R9 2 1  ; var9(var10)
      85 [-]: GETUPVAL R9 7; var9 = upvalues[7]
      86 [-]: ADDK R11 R7 K33; var11 = var7 + 1
      87 [-]: NAMECALL R9 R9 K34; var10 = var9; var9 = var9[0x8ABFF40E]
      88 [-]: CALL R9 3 1  ; var9(var10, var11)
      89 [-]: RETURN R0 0  ; 
L 9:  90 [-]: FORGLOOP R3 L8 2 [inext]; 
      91 [-]: LOADN R3 41  ; var3 = 41
      92 [-]: JUMPIFNOTLT R0 R3 L10; goto L10 if var0 >= var66620
      93 [-]: GETUPVAL R4 1; var4 = upvalues[1]
      94 [-]: GETTABLEKS R3 R4 K35; var3 = var4[0xA1DF01D6]
      95 [-]: LOADK R4 K36 ; var4 = "/Lotus/Language/SolarisHeists/ProfitTakerBountyThreeCDataObj"
      96 [-]: CALL R3 2 1  ; var3(var4)
      97 [-]: RETURN R0 0  ; 
L10:  98 [-]: LOADN R3 41  ; var3 = 41
      99 [-]: JUMPIFNOTLE R3 R0 L18; goto L18 if var3 > var2884400
     100 [-]: LOADN R3 44  ; var3 = 44
     101 [-]: JUMPIFNOTLT R0 R3 L18; goto L18 if var0 >= var2032417
     102 [-]: GETIMPORT R3 31; var3 = 0x3D106989
     103 [-]: LOADK R4 K37 ; var4 = "Heist: B3: Stage 3: Collect data"
     104 [-]: CALL R3 2 1  ; var3(var4)
     105 [-]: GETUPVAL R4 1; var4 = upvalues[1]
     106 [-]: GETTABLEKS R3 R4 K35; var3 = var4[0xA1DF01D6]
     107 [-]: LOADK R4 K38 ; var4 = "/Lotus/Language/SolarisHeists/ProfitTakerBountyThreeCOrb"
     108 [-]: GETUPVAL R6 1; var6 = upvalues[1]
     109 [-]: GETTABLEKS R5 R6 K39; var5 = var6["ATTACK_ICON"]
     110 [-]: CALL R3 3 1  ; var3(var4, var5)
     111 [-]: GETUPVAL R6 8; var6 = upvalues[8]
     112 [-]: GETTABLEN R5 R6 40; var5 = var6[40]
     113 [-]: GETTABLEKS R4 R5 K40; var4 = var5["time"]
     114 [-]: MULK R3 R4 K3; var3 = var4 * 100
     115 [-]: GETUPVAL R5 0; var5 = upvalues[0]
     116 [-]: MULK R4 R5 K3; var4 = var5 * 100
     117 [-]: ADDK R5 R3 K33; var5 = var3 + 1
     118 [-]: JUMPIFNOTLT R4 R5 L11; goto L11 if var4 >= var67132
     119 [-]: GETUPVAL R6 1; var6 = upvalues[1]
     120 [-]: GETTABLEKS R5 R6 K41; var5 = var6[0x03FC64EF]
     121 [-]: MOVE R6 R3   ; var6 = var3
     122 [-]: CALL R5 2 1  ; var5(var6)
L11: 123 [-]: GETIMPORT R6 44; var6 = _T["ArtilleryOrbAvatar"]
     124 [-]: GETIMPORT R8 46; var8 = gBaseMarkerInfoType
     125 [-]: NAMECALL R6 R6 K47; var7 = var6; var6 = var6[0xC9F6A7D7]
     126 [-]: CALL R6 3 0  ; var6, ... = var6(var7, var8)
     127 [-]: FASTCALL 64 L12; 
     128 [-]: GETIMPORT R5 1; var5 = 0x7B998233
     129 [-]: CALL R5 0 2  ; var5 = var5(var6, ...)
L12: 130 [-]: JUMPIFNOT R5 L15; goto L15 if not var5
     131 [-]: GETUPVAL R5 2; var5 = upvalues[2]
     132 [-]: FASTCALL1 64 R5 L13; 
     133 [-]: MOVE R7 R5   ; var7 = var5
     134 [-]: GETIMPORT R6 1; var6 = 0x7B998233
     135 [-]: CALL R6 2 2  ; var6 = var6(var7)
L13: 136 [-]: JUMPIF R6 L14; goto L14 if var6
     137 [-]: NAMECALL R6 R5 K48; var7 = var5; var6 = var5[0xA2880940]
     138 [-]: CALL R6 2 1  ; var6(var7)
L14: 139 [-]: GETIMPORT R5 44; var5 = _T["ArtilleryOrbAvatar"]
     140 [-]: GETIMPORT R7 50; var7 = 0xC76CF990
     141 [-]: GETIMPORT R8 27; var8 = 0x0469F296
     142 [-]: LOADK R9 K51 ; var9 = "FX_C1_EYE"
     143 [-]: CALL R8 2 0  ; var8, ... = var8(var9)
     144 [-]: NAMECALL R5 R5 K52; var6 = var5; var5 = var5[0x47901F07]
     145 [-]: CALL R5 0 2  ; var5 = var5(var6, ...)
     146 [-]: SETUPVAL R5 2; upvalues[5] = var2
     147 [-]: GETUPVAL R5 2; var5 = upvalues[2]
     148 [-]: GETIMPORT R7 54; var7 = 0xB7CBD06B
     149 [-]: LOADN R8 100 ; var8 = 100
     150 [-]: LOADN R9 5000; var9 = 5000
     151 [-]: CALL R7 3 0  ; var7, ... = var7(var8, var9)
     152 [-]: NAMECALL R5 R5 K55; var6 = var5; var5 = var5[0x53BC0559]
     153 [-]: CALL R5 0 1  ; var5(var6, ...)
L15: 154 [-]: GETIMPORT R6 57; var6 = _T["BaseReinforcements"]
     155 [-]: FASTCALL1 64 R6 L16; 
     156 [-]: GETIMPORT R5 1; var5 = 0x7B998233
     157 [-]: CALL R5 2 2  ; var5 = var5(var6)
L16: 158 [-]: JUMPIF R5 L26; goto L26 if var5
     159 [-]: GETIMPORT R7 57; var7 = _T["BaseReinforcements"]
     160 [-]: GETUPVAL R9 4; var9 = upvalues[4]
     161 [-]: GETTABLEKS R8 R9 K58; var8 = var9["name"]
     162 [-]: GETTABLE R6 R7 R8; var6 = var7[var8]
     163 [-]: FASTCALL1 64 R6 L17; 
     164 [-]: GETIMPORT R5 1; var5 = 0x7B998233
     165 [-]: CALL R5 2 2  ; var5 = var5(var6)
L17: 166 [-]: JUMPIF R5 L26; goto L26 if var5
     167 [-]: GETIMPORT R7 57; var7 = _T["BaseReinforcements"]
     168 [-]: GETUPVAL R9 4; var9 = upvalues[4]
     169 [-]: GETTABLEKS R8 R9 K58; var8 = var9["name"]
     170 [-]: GETTABLE R6 R7 R8; var6 = var7[var8]
     171 [-]: GETTABLEKS R5 R6 K59; var5 = var6["Start"]
     172 [-]: CALL R5 1 1  ; var5()
     173 [-]: RETURN R0 0  ; 
L18: 174 [-]: JUMPXEQKN R0 K60 L26 NOT; 
     175 [-]: GETIMPORT R3 31; var3 = 0x3D106989
     176 [-]: LOADK R4 K61 ; var4 = "Heist: B3: Stage 3: Damage the shields"
     177 [-]: CALL R3 2 1  ; var3(var4)
     178 [-]: GETUPVAL R4 1; var4 = upvalues[1]
     179 [-]: GETTABLEKS R3 R4 K62; var3 = var4[0xDC3B2033]
     180 [-]: CALL R3 1 1  ; var3()
     181 [-]: GETUPVAL R4 1; var4 = upvalues[1]
     182 [-]: GETTABLEKS R3 R4 K63; var3 = var4[0xBD3CE95D]
     183 [-]: CALL R3 1 1  ; var3()
     184 [-]: GETUPVAL R4 5; var4 = upvalues[5]
     185 [-]: GETTABLEKS R3 R4 K29; var3 = var4[0x9742B85B]
     186 [-]: GETUPVAL R4 6; var4 = upvalues[6]
     187 [-]: GETIMPORT R5 27; var5 = 0x0469F296
     188 [-]: LOADK R6 K64 ; var6 = "LeaveTheArea"
     189 [-]: CALL R5 2 0  ; var5, ... = var5(var6)
     190 [-]: CALL R3 0 1  ; var3(var4, ...)
     191 [-]: GETIMPORT R3 44; var3 = _T["ArtilleryOrbAvatar"]
     192 [-]: GETIMPORT R5 46; var5 = gBaseMarkerInfoType
     193 [-]: NAMECALL R3 R3 K47; var4 = var3; var3 = var3[0xC9F6A7D7]
     194 [-]: CALL R3 3 2  ; var3 = var3(var4, var5)
     195 [-]: FASTCALL1 64 R3 L19; 
     196 [-]: MOVE R5 R3   ; var5 = var3
     197 [-]: GETIMPORT R4 1; var4 = 0x7B998233
     198 [-]: CALL R4 2 2  ; var4 = var4(var5)
L19: 199 [-]: JUMPIF R4 L20; goto L20 if var4
     200 [-]: NAMECALL R4 R3 K48; var5 = var3; var4 = var3[0xA2880940]
     201 [-]: CALL R4 2 1  ; var4(var5)
L20: 202 [-]: GETUPVAL R5 2; var5 = upvalues[2]
     203 [-]: FASTCALL1 64 R5 L21; 
     204 [-]: GETIMPORT R4 1; var4 = 0x7B998233
     205 [-]: CALL R4 2 2  ; var4 = var4(var5)
L21: 206 [-]: JUMPIF R4 L22; goto L22 if var4
     207 [-]: GETUPVAL R4 2; var4 = upvalues[2]
     208 [-]: NAMECALL R4 R4 K48; var5 = var4; var4 = var4[0xA2880940]
     209 [-]: CALL R4 2 1  ; var4(var5)
L22: 210 [-]: GETIMPORT R5 57; var5 = _T["BaseReinforcements"]
     211 [-]: FASTCALL1 64 R5 L23; 
     212 [-]: GETIMPORT R4 1; var4 = 0x7B998233
     213 [-]: CALL R4 2 2  ; var4 = var4(var5)
L23: 214 [-]: JUMPIF R4 L25; goto L25 if var4
     215 [-]: GETIMPORT R6 57; var6 = _T["BaseReinforcements"]
     216 [-]: GETUPVAL R8 4; var8 = upvalues[4]
     217 [-]: GETTABLEKS R7 R8 K58; var7 = var8["name"]
     218 [-]: GETTABLE R5 R6 R7; var5 = var6[var7]
     219 [-]: FASTCALL1 64 R5 L24; 
     220 [-]: GETIMPORT R4 1; var4 = 0x7B998233
     221 [-]: CALL R4 2 2  ; var4 = var4(var5)
L24: 222 [-]: JUMPIF R4 L25; goto L25 if var4
     223 [-]: GETIMPORT R6 57; var6 = _T["BaseReinforcements"]
     224 [-]: GETUPVAL R8 4; var8 = upvalues[4]
     225 [-]: GETTABLEKS R7 R8 K58; var7 = var8["name"]
     226 [-]: GETTABLE R5 R6 R7; var5 = var6[var7]
     227 [-]: GETTABLEKS R4 R5 K65; var4 = var5["Stop"]
     228 [-]: CALL R4 1 1  ; var4()
L25: 229 [-]: GETIMPORT R4 67; var4 = 0xCBD666E1
     230 [-]: LOADN R5 3   ; var5 = 3
     231 [-]: CALL R4 2 1  ; var4(var5)
     232 [-]: GETIMPORT R4 69; var4 = 0x89326C93
     233 [-]: GETIMPORT R6 27; var6 = 0x0469F296
     234 [-]: LOADK R7 K70 ; var7 = "FortunaMortarWaypointCourtyard"
     235 [-]: CALL R6 2 0  ; var6, ... = var6(var7)
     236 [-]: NAMECALL R4 R4 K71; var5 = var4; var4 = var4[0x46A0EBF5]
     237 [-]: CALL R4 0 2  ; var4 = var4(var5, ...)
     238 [-]: GETUPVAL R5 9; var5 = upvalues[9]
     239 [-]: MOVE R6 R4   ; var6 = var4
     240 [-]: LOADN R7 12  ; var7 = 12
     241 [-]: LOADN R8 30  ; var8 = 30
     242 [-]: CALL R5 4 1  ; var5(var6, var7, var8)
     243 [-]: GETIMPORT R5 67; var5 = 0xCBD666E1
     244 [-]: LOADN R6 8   ; var6 = 8
     245 [-]: CALL R5 2 1  ; var5(var6)
     246 [-]: GETUPVAL R6 5; var6 = upvalues[5]
     247 [-]: GETTABLEKS R5 R6 K29; var5 = var6[0x9742B85B]
     248 [-]: GETUPVAL R6 6; var6 = upvalues[6]
     249 [-]: GETIMPORT R7 27; var7 = 0x0469F296
     250 [-]: LOADK R8 K72 ; var8 = "Completed"
     251 [-]: CALL R7 2 0  ; var7, ... = var7(var8)
     252 [-]: CALL R5 0 1  ; var5(var6, ...)
     253 [-]: GETUPVAL R6 5; var6 = upvalues[5]
     254 [-]: GETTABLEKS R5 R6 K73; var5 = var6[0xFC87A231]
     255 [-]: CALL R5 1 1  ; var5()
     256 [-]: GETUPVAL R5 7; var5 = upvalues[7]
     257 [-]: LOADN R7 100 ; var7 = 100
     258 [-]: NAMECALL R5 R5 K34; var6 = var5; var5 = var5[0x8ABFF40E]
     259 [-]: CALL R5 3 1  ; var5(var6, var7)
L26: 260 [-]: RETURN R0 0  ; 


; Name:            
; Defined at line: 454
; #Upvalues:       9
; #Parameters:     0
; Is_vararg:       0
; Max Stack Size:  5

       0 [-]: GETUPVAL R0 0; var0 = upvalues[0]
       1 [-]: NAMECALL R0 R0 K0; var1 = var0; var0 = var0[0x209398C2]
       2 [-]: CALL R0 2 2  ; var0 = var0(var1)
       3 [-]: GETUPVAL R2 1; var2 = upvalues[1]
       4 [-]: GETTABLEKS R1 R2 K1; var1 = var2[0x2BEB71D2]
       5 [-]: LOADK R3 K2  ; var3 = "[DEBUG] STAGE "
       6 [-]: MOVE R4 R0   ; var4 = var0
       7 [-]: CONCAT R2 R3 R4; var2 = var3 .. var4
       8 [-]: CALL R1 2 1  ; var1(var2)
       9 [-]: GETIMPORT R1 4; var1 = 0x3D106989
      10 [-]: LOADK R3 K5  ; var3 = "Heist: B3: STAGE ID "
      11 [-]: MOVE R4 R0   ; var4 = var0
      12 [-]: CONCAT R2 R3 R4; var2 = var3 .. var4
      13 [-]: CALL R1 2 1  ; var1(var2)
      14 [-]: LOADN R1 10  ; var1 = 10
      15 [-]: JUMPIFNOTLE R1 R0 L0; goto L0 if var1 > var1114416
      16 [-]: LOADN R1 17  ; var1 = 17
      17 [-]: JUMPIFNOTLE R0 R1 L0; goto L0 if var0 > var131388
      18 [-]: GETUPVAL R1 2; var1 = upvalues[2]
      19 [-]: MOVE R2 R0   ; var2 = var0
      20 [-]: CALL R1 2 1  ; var1(var2)
      21 [-]: JUMP L5      ; goto L5
L 0:  22 [-]: LOADN R1 20  ; var1 = 20
      23 [-]: JUMPIFNOTLE R1 R0 L1; goto L1 if var1 > var1376560
      24 [-]: LOADN R1 21  ; var1 = 21
      25 [-]: JUMPIFNOTLE R0 R1 L1; goto L1 if var0 > var196924
      26 [-]: GETUPVAL R1 3; var1 = upvalues[3]
      27 [-]: MOVE R2 R0   ; var2 = var0
      28 [-]: CALL R1 2 1  ; var1(var2)
      29 [-]: JUMP L5      ; goto L5
L 1:  30 [-]: LOADN R1 30  ; var1 = 30
      31 [-]: JUMPIFNOTLE R1 R0 L2; goto L2 if var1 > var2883888
      32 [-]: LOADN R1 44  ; var1 = 44
      33 [-]: JUMPIFNOTLE R0 R1 L2; goto L2 if var0 > var262460
      34 [-]: GETUPVAL R1 4; var1 = upvalues[4]
      35 [-]: MOVE R2 R0   ; var2 = var0
      36 [-]: CALL R1 2 1  ; var1(var2)
      37 [-]: JUMP L5      ; goto L5
L 2:  38 [-]: JUMPXEQKN R0 K6 L5 NOT; 
      39 [-]: GETIMPORT R1 4; var1 = 0x3D106989
      40 [-]: LOADK R2 K7  ; var2 = "Heist: B3: Stage 3: Completed, return to Fortuna"
      41 [-]: CALL R1 2 1  ; var1(var2)
      42 [-]: GETUPVAL R2 1; var2 = upvalues[1]
      43 [-]: GETTABLEKS R1 R2 K8; var1 = var2[0xA1DF01D6]
      44 [-]: LOADK R2 K9  ; var2 = "/Lotus/Language/SolarisQuest/ReturnToSolaris"
      45 [-]: CALL R1 2 1  ; var1(var2)
      46 [-]: GETIMPORT R1 11; var1 = 0x89326C93
      47 [-]: GETIMPORT R3 13; var3 = 0x0469F296
      48 [-]: LOADK R4 K14 ; var4 = "EnterTownMarker"
      49 [-]: CALL R3 2 0  ; var3, ... = var3(var4)
      50 [-]: NAMECALL R1 R1 K15; var2 = var1; var1 = var1[0x46A0EBF5]
      51 [-]: CALL R1 0 2  ; var1 = var1(var2, ...)
      52 [-]: SETUPVAL R1 5; upvalues[1] = var5
      53 [-]: GETUPVAL R2 5; var2 = upvalues[5]
      54 [-]: FASTCALL1 64 R2 L3; 
      55 [-]: GETIMPORT R1 17; var1 = 0x7B998233
      56 [-]: CALL R1 2 2  ; var1 = var1(var2)
L 3:  57 [-]: JUMPIF R1 L4 ; goto L4 if var1
      58 [-]: GETUPVAL R1 5; var1 = upvalues[5]
      59 [-]: NAMECALL R1 R1 K18; var2 = var1; var1 = var1[0x383D2E7D]
      60 [-]: CALL R1 2 1  ; var1(var2)
L 4:  61 [-]: GETUPVAL R1 6; var1 = upvalues[6]
      62 [-]: LOADN R3 4   ; var3 = 4
      63 [-]: NAMECALL R1 R1 K19; var2 = var1; var1 = var1[0xFE9DC265]
      64 [-]: CALL R1 3 1  ; var1(var2, var3)
L 5:  65 [-]: LOADN R1 100 ; var1 = 100
      66 [-]: JUMPIFNOTLE R1 R0 L6; goto L6 if var1 > var66108
      67 [-]: GETUPVAL R2 1; var2 = upvalues[1]
      68 [-]: GETTABLEKS R1 R2 K20; var1 = var2[0xF94B7537]
      69 [-]: CALL R1 1 1  ; var1()
      70 [-]: GETUPVAL R2 1; var2 = upvalues[1]
      71 [-]: GETTABLEKS R1 R2 K21; var1 = var2[0xF158D74D]
      72 [-]: CALL R1 1 1  ; var1()
      73 [-]: GETUPVAL R1 7; var1 = upvalues[7]
      74 [-]: LOADB R2 0   ; var2 = false
      75 [-]: CALL R1 2 1  ; var1(var2)
      76 [-]: GETUPVAL R2 8; var2 = upvalues[8]
      77 [-]: GETTABLEKS R1 R2 K22; var1 = var2[0xC474A99E]
      78 [-]: GETIMPORT R2 13; var2 = 0x0469F296
      79 [-]: LOADK R3 K23 ; var3 = "ResearchFacilityAgentTypeSelector"
      80 [-]: CALL R2 2 2  ; var2 = var2(var3)
      81 [-]: LOADK R3 K24 ; var3 = "Enable"
      82 [-]: CALL R1 3 1  ; var1(var2, var3)
      83 [-]: GETUPVAL R2 8; var2 = upvalues[8]
      84 [-]: GETTABLEKS R1 R2 K22; var1 = var2[0xC474A99E]
      85 [-]: GETIMPORT R2 13; var2 = 0x0469F296
      86 [-]: LOADK R3 K25 ; var3 = "ResFacProfitTakerAgentTypeVolume"
      87 [-]: CALL R2 2 2  ; var2 = var2(var3)
      88 [-]: LOADK R3 K26 ; var3 = "Disable"
      89 [-]: CALL R1 3 1  ; var1(var2, var3)
L 6:  90 [-]: RETURN R0 0  ; 


; Name:            
; Defined at line: 488
; #Upvalues:       22
; #Parameters:     1
; Is_vararg:       0
; Max Stack Size:  9

       0 [-]: GETIMPORT R1 1; var1 = 0x89326C93
       1 [-]: NAMECALL R1 R1 K2; var2 = var1; var1 = var1[0x29EF273D]
       2 [-]: CALL R1 2 2  ; var1 = var1(var2)
       3 [-]: NAMECALL R1 R1 K3; var2 = var1; var1 = var1[0x66905CB0]
       4 [-]: CALL R1 2 2  ; var1 = var1(var2)
       5 [-]: SETUPVAL R1 0; upvalues[1] = var0
L 0:   6 [-]: GETUPVAL R1 0; var1 = upvalues[0]
       7 [-]: NAMECALL R1 R1 K4; var2 = var1; var1 = var1[0xA2D83ED4]
       8 [-]: CALL R1 2 2  ; var1 = var1(var2)
       9 [-]: JUMPIF R1 L1 ; goto L1 if var1
      10 [-]: GETIMPORT R1 6; var1 = 0xCBD666E1
      11 [-]: LOADN R2 0   ; var2 = 0
      12 [-]: CALL R1 2 1  ; var1(var2)
      13 [-]: JUMPBACK L0  ; goto L0
L 1:  14 [-]: GETIMPORT R1 8; var1 = 0xBE190284
      15 [-]: SETUPVAL R1 1; upvalues[1] = var1
      16 [-]: SETUPVAL R0 2; upvalues[0] = var2
      17 [-]: NAMECALL R1 R0 K9; var2 = var0; var1 = var0[0x4C976EDA]
      18 [-]: CALL R1 2 2  ; var1 = var1(var2)
      19 [-]: NAMECALL R1 R1 K10; var2 = var1; var1 = var1[0xE4C355E2]
      20 [-]: CALL R1 2 2  ; var1 = var1(var2)
      21 [-]: SETUPVAL R1 3; upvalues[1] = var3
      22 [-]: GETIMPORT R1 1; var1 = 0x89326C93
      23 [-]: LOADK R3 K11 ; var3 = "OnPlayersChanged"
      24 [-]: NAMECALL R1 R1 K12; var2 = var1; var1 = var1[0xB7D33840]
      25 [-]: CALL R1 3 1  ; var1(var2, var3)
      26 [-]: GETIMPORT R1 1; var1 = 0x89326C93
      27 [-]: NAMECALL R1 R1 K13; var2 = var1; var1 = var1[0x8B5B1F58]
      28 [-]: CALL R1 2 2  ; var1 = var1(var2)
      29 [-]: SETUPVAL R1 4; upvalues[1] = var4
      30 [-]: GETUPVAL R1 1; var1 = upvalues[1]
      31 [-]: GETUPVAL R3 6; var3 = upvalues[6]
      32 [-]: NAMECALL R1 R1 K14; var2 = var1; var1 = var1[0x0EB34C69]
      33 [-]: CALL R1 3 2  ; var1 = var1(var2, var3)
      34 [-]: SETUPVAL R1 5; upvalues[1] = var5
      35 [-]: GETUPVAL R1 1; var1 = upvalues[1]
      36 [-]: GETUPVAL R3 8; var3 = upvalues[8]
      37 [-]: NAMECALL R1 R1 K14; var2 = var1; var1 = var1[0x0EB34C69]
      38 [-]: CALL R1 3 2  ; var1 = var1(var2, var3)
      39 [-]: SETUPVAL R1 7; upvalues[1] = var7
      40 [-]: GETUPVAL R2 10; var2 = upvalues[10]
      41 [-]: GETTABLEKS R1 R2 K15; var1 = var2[0xC9013731]
      42 [-]: GETUPVAL R2 11; var2 = upvalues[11]
      43 [-]: GETUPVAL R3 2; var3 = upvalues[2]
      44 [-]: NEWTABLE R4 0 4; var4 = {}
      45 [-]: GETUPVAL R5 12; var5 = upvalues[12]
      46 [-]: GETUPVAL R6 13; var6 = upvalues[13]
      47 [-]: GETUPVAL R7 6; var7 = upvalues[6]
      48 [-]: GETUPVAL R8 8; var8 = upvalues[8]
      49 [-]: SETLIST R4 R5 4 [1]; var4[1] = var5; var4[2] = var6; var4[3] = var7; var4[4] = var8; var4[5] = var9; 
      50 [-]: CALL R1 4 2  ; var1 = var1(var2, var3, var4)
      51 [-]: SETUPVAL R1 9; upvalues[1] = var9
      52 [-]: GETUPVAL R1 1; var1 = upvalues[1]
      53 [-]: NAMECALL R1 R1 K16; var2 = var1; var1 = var1[0xABF50B1C]
      54 [-]: CALL R1 2 2  ; var1 = var1(var2)
      55 [-]: SETUPVAL R1 14; upvalues[1] = var14
      56 [-]: LOADK R3 K17 ; var3 = "PlayersLeaving"
      57 [-]: GETIMPORT R4 19; var4 = 0x0469F296
      58 [-]: LOADK R5 K20 ; var5 = "LeavingCB"
      59 [-]: CALL R4 2 0  ; var4, ... = var4(var5)
      60 [-]: NAMECALL R1 R0 K21; var2 = var0; var1 = var0[0xE19C3F44]
      61 [-]: CALL R1 0 1  ; var1(var2, ...)
      62 [-]: LOADK R3 K22 ; var3 = "PlayersReturning"
      63 [-]: GETIMPORT R4 19; var4 = 0x0469F296
      64 [-]: LOADK R5 K23 ; var5 = "ReturningCB"
      65 [-]: CALL R4 2 0  ; var4, ... = var4(var5)
      66 [-]: NAMECALL R1 R0 K24; var2 = var0; var1 = var0[0x3F86F5A0]
      67 [-]: CALL R1 0 1  ; var1(var2, ...)
      68 [-]: GETIMPORT R1 1; var1 = 0x89326C93
      69 [-]: GETIMPORT R3 19; var3 = 0x0469F296
      70 [-]: LOADK R4 K25 ; var4 = "HeistResearchConsoleA"
      71 [-]: CALL R3 2 0  ; var3, ... = var3(var4)
      72 [-]: NAMECALL R1 R1 K26; var2 = var1; var1 = var1[0x46A0EBF5]
      73 [-]: CALL R1 0 2  ; var1 = var1(var2, ...)
      74 [-]: SETUPVAL R1 15; upvalues[1] = var15
      75 [-]: GETIMPORT R1 1; var1 = 0x89326C93
      76 [-]: GETIMPORT R3 19; var3 = 0x0469F296
      77 [-]: LOADK R4 K27 ; var4 = "HeistResearchConsoleB"
      78 [-]: CALL R3 2 0  ; var3, ... = var3(var4)
      79 [-]: NAMECALL R1 R1 K26; var2 = var1; var1 = var1[0x46A0EBF5]
      80 [-]: CALL R1 0 2  ; var1 = var1(var2, ...)
      81 [-]: SETUPVAL R1 16; upvalues[1] = var16
      82 [-]: GETUPVAL R1 17; var1 = upvalues[17]
      83 [-]: GETIMPORT R2 1; var2 = 0x89326C93
      84 [-]: GETIMPORT R4 19; var4 = 0x0469F296
      85 [-]: LOADK R5 K28 ; var5 = "ResearchFacilityCourtyard"
      86 [-]: CALL R4 2 0  ; var4, ... = var4(var5)
      87 [-]: NAMECALL R2 R2 K26; var3 = var2; var2 = var2[0x46A0EBF5]
      88 [-]: CALL R2 0 2  ; var2 = var2(var3, ...)
      89 [-]: SETTABLEKS R2 R1 K29; var2["inst"] = var1
      90 [-]: GETUPVAL R1 17; var1 = upvalues[17]
      91 [-]: GETUPVAL R3 17; var3 = upvalues[17]
      92 [-]: GETTABLEKS R2 R3 K29; var2 = var3["inst"]
      93 [-]: NAMECALL R2 R2 K30; var3 = var2; var2 = var2[0xD1586535]
      94 [-]: CALL R2 2 2  ; var2 = var2(var3)
      95 [-]: SETTABLEKS R2 R1 K31; var2["pos"] = var1
      96 [-]: GETUPVAL R1 17; var1 = upvalues[17]
      97 [-]: GETUPVAL R4 17; var4 = upvalues[17]
      98 [-]: GETTABLEKS R3 R4 K29; var3 = var4["inst"]
      99 [-]: NAMECALL R3 R3 K33; var4 = var3; var3 = var3[0xF6CF204F]
     100 [-]: CALL R3 2 2  ; var3 = var3(var4)
     101 [-]: MULK R2 R3 K32; var2 = var3 * 2
     102 [-]: SETTABLEKS R2 R1 K34; var2["radius"] = var1
     103 [-]: GETUPVAL R1 17; var1 = upvalues[17]
     104 [-]: GETUPVAL R3 17; var3 = upvalues[17]
     105 [-]: GETTABLEKS R2 R3 K29; var2 = var3["inst"]
     106 [-]: NAMECALL R2 R2 K35; var3 = var2; var2 = var2[0xED4E0128]
     107 [-]: CALL R2 2 2  ; var2 = var2(var3)
     108 [-]: SETTABLEKS R2 R1 K36; var2["name"] = var1
     109 [-]: GETIMPORT R1 1; var1 = 0x89326C93
     110 [-]: GETIMPORT R3 19; var3 = 0x0469F296
     111 [-]: LOADK R4 K37 ; var4 = "ResearchFacilityDoorHint"
     112 [-]: CALL R3 2 0  ; var3, ... = var3(var4)
     113 [-]: NAMECALL R1 R1 K26; var2 = var1; var1 = var1[0x46A0EBF5]
     114 [-]: CALL R1 0 2  ; var1 = var1(var2, ...)
     115 [-]: SETUPVAL R1 18; upvalues[1] = var18
     116 [-]: GETIMPORT R1 40; var1 = _T["ArtilleryOrbAvatar"]
     117 [-]: NAMECALL R1 R1 K41; var2 = var1; var1 = var1[0x1AC1655C]
     118 [-]: CALL R1 2 2  ; var1 = var1(var2)
     119 [-]: SETUPVAL R1 19; upvalues[1] = var19
     120 [-]: GETUPVAL R1 20; var1 = upvalues[20]
     121 [-]: LOADB R2 1   ; var2 = true
     122 [-]: CALL R1 2 1  ; var1(var2)
     123 [-]: GETUPVAL R1 2; var1 = upvalues[2]
     124 [-]: NAMECALL R1 R1 K42; var2 = var1; var1 = var1[0xABE61691]
     125 [-]: CALL R1 2 2  ; var1 = var1(var2)
     126 [-]: GETUPVAL R2 9; var2 = upvalues[9]
     127 [-]: GETUPVAL R5 21; var5 = upvalues[21]
     128 [-]: GETTABLEKS R4 R5 K43; var4 = var5[0x06D055F9]
     129 [-]: JUMPXEQKN R1 K44 L2; 
     130 [-]: LOADB R5 0 +1; var5 = false
L 2: 131 [-]: LOADB R5 1   ; var5 = true
L 3: 132 [-]: LOADN R6 10  ; var6 = 10
     133 [-]: MOVE R7 R1   ; var7 = var1
     134 [-]: CALL R4 4 0  ; var4, ... = var4(var5, var6, var7)
     135 [-]: NAMECALL R2 R2 K45; var3 = var2; var2 = var2[0x8ABFF40E]
     136 [-]: CALL R2 0 1  ; var2(var3, ...)
     137 [-]: NAMECALL R2 R0 K46; var3 = var0; var2 = var0[0xEFE6CAD1]
     138 [-]: CALL R2 2 2  ; var2 = var2(var3)
     139 [-]: LOADN R3 1   ; var3 = 1
     140 [-]: JUMPIFNOTEQ R2 R3 L4; goto L4 if var2 ~= var132144
     141 [-]: LOADN R4 2   ; var4 = 2
     142 [-]: NAMECALL R2 R0 K47; var3 = var0; var2 = var0[0xFE9DC265]
     143 [-]: CALL R2 3 1  ; var2(var3, var4)
L 4: 144 [-]: RETURN R0 0  ; 


; Name:            
; Defined at line: 531
; #Upvalues:       16
; #Parameters:     1
; Is_vararg:       0
; Max Stack Size:  23

       0 [-]: GETUPVAL R1 0; var1 = upvalues[0]
       1 [-]: MOVE R2 R0   ; var2 = var0
       2 [-]: CALL R1 2 1  ; var1(var2)
       3 [-]: LOADN R1 10  ; var1 = 10
       4 [-]: LOADN R2 0   ; var2 = 0
       5 [-]: LOADN R3 0   ; var3 = 0
       6 [-]: LOADNIL R4   ; var4 = nil
       7 [-]: GETUPVAL R7 1; var7 = upvalues[1]
       8 [-]: FASTCALL1 64 R7 L0; 
       9 [-]: GETIMPORT R6 1; var6 = 0x7B998233
      10 [-]: CALL R6 2 2  ; var6 = var6(var7)
L 0:  11 [-]: JUMPIF R6 L1 ; goto L1 if var6
      12 [-]: GETUPVAL R7 1; var7 = upvalues[1]
      13 [-]: LENGTH R6 R7 ; var6 = #var7
      14 [-]: GETIMPORT R7 3; var7 = 0x9BA7909F
      15 [-]: LOADK R9 K4  ; var9 = "Server.NumVirtualTestClients"
      16 [-]: NAMECALL R7 R7 K5; var8 = var7; var7 = var7[0x8151451D]
      17 [-]: CALL R7 3 2  ; var7 = var7(var8, var9)
      18 [-]: ADD R5 R6 R7 ; var5 = var6 + var7
      19 [-]: JUMP L2      ; goto L2
L 1:  20 [-]: LOADNIL R5   ; var5 = nil
L 2:  21 [-]: LOADN R6 0   ; var6 = 0
      22 [-]: LOADN R7 0   ; var7 = 0
      23 [-]: GETUPVAL R8 2; var8 = upvalues[2]
      24 [-]: NAMECALL R8 R8 K6; var9 = var8; var8 = var8[0xE79E7EF4]
      25 [-]: CALL R8 2 2  ; var8 = var8(var9)
      26 [-]: NAMECALL R8 R8 K7; var9 = var8; var8 = var8[0x9435EB6D]
      27 [-]: CALL R8 2 2  ; var8 = var8(var9)
      28 [-]: LOADN R9 9999; var9 = 9999
      29 [-]: LOADNIL R10  ; var10 = nil
      30 [-]: LOADNIL R11  ; var11 = nil
      31 [-]: GETUPVAL R13 3; var13 = upvalues[3]
     L 3:  33 [-]: NAMECALL R13 R0 K9; var14 = var0; var13 = var0[0xEFE6CAD1]
      34 [-]: CALL R13 2 2 ; var13 = var13(var14)
      35 [-]: LOADN R14 4  ; var14 = 4
      36 [-]: JUMPIFNOTLT R13 R14 L44; goto L44 if var13 >= var724257
      37 [-]: GETIMPORT R13 11; var13 = 0xFFF641AF
      38 [-]: CALL R13 1 2 ; var13 = var13()
      39 [-]: MOVE R2 R13  ; var2 = var13
      40 [-]: GETUPVAL R13 4; var13 = upvalues[4]
      41 [-]: NAMECALL R13 R13 K12; var14 = var13; var13 = var13[0x209398C2]
      42 [-]: CALL R13 2 2 ; var13 = var13(var14)
      43 [-]: MOVE R3 R13  ; var3 = var13
      44 [-]: GETUPVAL R13 5; var13 = upvalues[5]
      45 [-]: NAMECALL R13 R13 K13; var14 = var13; var13 = var13[0x78072CA1]
      46 [-]: CALL R13 2 2 ; var13 = var13(var14)
      47 [-]: MOVE R4 R13  ; var4 = var13
      48 [-]: GETIMPORT R13 15; var13 = 0x89326C93
      49 [-]: NAMECALL R13 R13 K16; var14 = var13; var13 = var13[0x8B5B1F58]
      50 [-]: CALL R13 2 2 ; var13 = var13(var14)
      51 [-]: SETUPVAL R13 1; upvalues[13] = var1
      52 [-]: LOADN R13 10 ; var13 = 10
      53 [-]: JUMPIFNOTLE R13 R3 L24; goto L24 if var13 > var1117488
      54 [-]: LOADN R13 17 ; var13 = 17
      55 [-]: JUMPIFNOTLE R3 R13 L24; goto L24 if var3 > var5964598
      56 [-]: JUMPXEQKN R3 K17 L17 NOT; 
      57 [-]: LOADN R13 0  ; var13 = 0
      58 [-]: GETUPVAL R16 1; var16 = upvalues[1]
      59 [-]: FASTCALL1 64 R16 L4; 
      60 [-]: GETIMPORT R15 1; var15 = 0x7B998233
      61 [-]: CALL R15 2 2 ; var15 = var15(var16)
L 4:  62 [-]: JUMPIF R15 L5; goto L5 if var15
      63 [-]: GETUPVAL R16 1; var16 = upvalues[1]
      64 [-]: LENGTH R15 R16; var15 = #var16
      65 [-]: GETIMPORT R16 3; var16 = 0x9BA7909F
      66 [-]: LOADK R18 K4 ; var18 = "Server.NumVirtualTestClients"
      67 [-]: NAMECALL R16 R16 K5; var17 = var16; var16 = var16[0x8151451D]
      68 [-]: CALL R16 3 2 ; var16 = var16(var17, var18)
      69 [-]: ADD R14 R15 R16; var14 = var15 + var16
      70 [-]: JUMP L6      ; goto L6
L 5:  71 [-]: LOADNIL R14  ; var14 = nil
L 6:  72 [-]: GETIMPORT R15 19; var15 = 0xC8802016
      73 [-]: GETUPVAL R16 1; var16 = upvalues[1]
      74 [-]: CALL R15 2 4 ; var15, var16, var17 = var15(var16)
      75 [-]: FORGPREP_INEXT R15 L9; 
L 7:  76 [-]: NAMECALL R20 R19 K6; var21 = var19; var20 = var19[0xE79E7EF4]
      77 [-]: CALL R20 2 2 ; var20 = var20(var21)
      78 [-]: FASTCALL1 64 R20 L8; 
      79 [-]: MOVE R22 R20 ; var22 = var20
      80 [-]: GETIMPORT R21 1; var21 = 0x7B998233
      81 [-]: CALL R21 2 2 ; var21 = var21(var22)
L 8:  82 [-]: JUMPIF R21 L9; goto L9 if var21
      83 [-]: NAMECALL R21 R20 K7; var22 = var20; var21 = var20[0x9435EB6D]
      84 [-]: CALL R21 2 2 ; var21 = var21(var22)
      85 [-]: JUMPIFNOTEQ R21 R8 L9; goto L9 if var21 ~= var336399624
      86 [-]: ADDK R13 R13 K20; var13 = var13 + 1
L 9:  87 [-]: FORGLOOP R15 L7 2 [inext]; 
      88 [-]: LOADN R15 1  ; var15 = 1
      89 [-]: JUMPIFNOTLT R15 R14 L11; goto L11 if var15 >= var199959
      90 [-]: JUMPIFNOTEQ R13 R6 L10; goto L10 if var13 ~= var1117740
      91 [-]: JUMPIFEQ R14 R5 L12; goto L12 if var14 == var397372
L10:  92 [-]: GETUPVAL R16 6; var16 = upvalues[6]
      93 [-]: GETTABLEKS R15 R16 K21; var15 = var16[0x118E5C26]
      94 [-]: LOADK R16 K22; var16 = "/Lotus/Language/SolarisHeists/ProfitTakerBountyThreeAVentSec"
      95 [-]: LOADN R17 0  ; var17 = 0
      96 [-]: LOADK R19 K23; var19 = ": "
      97 [-]: MOVE R20 R13 ; var20 = var13
      98 [-]: LOADK R21 K24; var21 = " / "
      99 [-]: MOVE R22 R14 ; var22 = var14
     100 [-]: CONCAT R18 R19 R22; var18 = var19 .. var22
     101 [-]: CALL R15 4 1 ; var15(var16, var17, var18)
     102 [-]: JUMP L12     ; goto L12
L11: 103 [-]: GETUPVAL R16 6; var16 = upvalues[6]
     104 [-]: GETTABLEKS R15 R16 K25; var15 = var16[0xF94B7537]
     105 [-]: CALL R15 1 1 ; var15()
L12: 106 [-]: GETUPVAL R17 1; var17 = upvalues[1]
     107 [-]: FASTCALL1 64 R17 L13; 
     108 [-]: GETIMPORT R16 1; var16 = 0x7B998233
     109 [-]: CALL R16 2 2 ; var16 = var16(var17)
L13: 110 [-]: JUMPIF R16 L14; goto L14 if var16
     111 [-]: GETUPVAL R17 1; var17 = upvalues[1]
     112 [-]: LENGTH R16 R17; var16 = #var17
     113 [-]: GETIMPORT R17 3; var17 = 0x9BA7909F
     114 [-]: LOADK R19 K4 ; var19 = "Server.NumVirtualTestClients"
     115 [-]: NAMECALL R17 R17 K5; var18 = var17; var17 = var17[0x8151451D]
     116 [-]: CALL R17 3 2 ; var17 = var17(var18, var19)
     117 [-]: ADD R15 R16 R17; var15 = var16 + var17
     118 [-]: JUMP L15     ; goto L15
L14: 119 [-]: LOADNIL R15  ; var15 = nil
L15: 120 [-]: JUMPIFNOTEQ R13 R15 L16; goto L16 if var13 ~= var266044
     121 [-]: GETUPVAL R15 4; var15 = upvalues[4]
     122 [-]: LOADN R17 11 ; var17 = 11
     123 [-]: NAMECALL R15 R15 K26; var16 = var15; var15 = var15[0x8ABFF40E]
     124 [-]: CALL R15 3 1 ; var15(var16, var17)
L16: 125 [-]: MOVE R5 R14  ; var5 = var14
     126 [-]: MOVE R6 R13  ; var6 = var13
     127 [-]: JUMP L43     ; goto L43
L17: 128 [-]: JUMPXEQKN R3 K27 L18 NOT; 
     129 [-]: GETUPVAL R13 7; var13 = upvalues[7]
     130 [-]: GETUPVAL R15 8; var15 = upvalues[8]
     131 [-]: NAMECALL R13 R13 K28; var14 = var13; var13 = var13[0x0EB34C69]
     132 [-]: CALL R13 3 2 ; var13 = var13(var14, var15)
     133 [-]: LOADN R14 0  ; var14 = 0
     134 [-]: JUMPIFNOTLT R14 R13 L43; goto L43 if var14 >= var265532
     135 [-]: GETUPVAL R13 4; var13 = upvalues[4]
     136 [-]: LOADN R15 13 ; var15 = 13
     137 [-]: NAMECALL R13 R13 K26; var14 = var13; var13 = var13[0x8ABFF40E]
     138 [-]: CALL R13 3 1 ; var13(var14, var15)
     139 [-]: JUMP L43     ; goto L43
L18: 140 [-]: JUMPXEQKN R3 K29 L19 NOT; 
     141 [-]: GETUPVAL R13 7; var13 = upvalues[7]
     142 [-]: GETUPVAL R15 8; var15 = upvalues[8]
     143 [-]: NAMECALL R13 R13 K28; var14 = var13; var13 = var13[0x0EB34C69]
     144 [-]: CALL R13 3 2 ; var13 = var13(var14, var15)
     145 [-]: LOADN R14 0  ; var14 = 0
     146 [-]: JUMPIFNOTLT R14 R13 L43; goto L43 if var14 >= var265532
     147 [-]: GETUPVAL R13 4; var13 = upvalues[4]
     148 [-]: LOADN R15 16 ; var15 = 16
     149 [-]: NAMECALL R13 R13 K26; var14 = var13; var13 = var13[0x8ABFF40E]
     150 [-]: CALL R13 3 1 ; var13(var14, var15)
     151 [-]: JUMP L43     ; goto L43
L19: 152 [-]: JUMPXEQKN R3 K30 L43 NOT; 
     153 [-]: GETUPVAL R14 6; var14 = upvalues[6]
     154 [-]: GETTABLEKS R13 R14 K31; var13 = var14[0x826F2CA6]
     155 [-]: CALL R13 1 2 ; var13 = var13()
     156 [-]: SETUPVAL R13 9; upvalues[13] = var9
     157 [-]: GETUPVAL R13 9; var13 = upvalues[9]
     158 [-]: JUMPXEQKN R13 K32 L20 NOT; 
     159 [-]: GETUPVAL R13 4; var13 = upvalues[4]
     160 [-]: LOADN R15 14 ; var15 = 14
     161 [-]: NAMECALL R13 R13 K26; var14 = var13; var13 = var13[0x8ABFF40E]
     162 [-]: CALL R13 3 1 ; var13(var14, var15)
     163 [-]: JUMP L21     ; goto L21
L20: 164 [-]: GETUPVAL R13 7; var13 = upvalues[7]
     165 [-]: GETUPVAL R15 10; var15 = upvalues[10]
     166 [-]: NAMECALL R13 R13 K28; var14 = var13; var13 = var13[0x0EB34C69]
     167 [-]: CALL R13 3 2 ; var13 = var13(var14, var15)
     168 [-]: JUMPXEQKN R13 K20 L21 NOT; 
     169 [-]: GETUPVAL R13 4; var13 = upvalues[4]
     170 [-]: LOADN R15 17 ; var15 = 17
     171 [-]: NAMECALL R13 R13 K26; var14 = var13; var13 = var13[0x8ABFF40E]
     172 [-]: CALL R13 3 1 ; var13(var14, var15)
L21: 173 [-]: GETUPVAL R13 7; var13 = upvalues[7]
     174 [-]: GETUPVAL R15 11; var15 = upvalues[11]
     175 [-]: GETUPVAL R18 9; var18 = upvalues[9]
     176 [-]: FASTCALL1 7 R18 L22; 
     177 [-]: GETIMPORT R17 35; var17 = 0x5BCED4C4[0x99675E23]
     178 [-]: CALL R17 2 2 ; var17 = var17(var18)
L22: 179 [-]: FASTCALL2K 18 R17 K32 L23; 
     180 [-]: LOADK R18 K32; var18 = 0
     181 [-]: GETIMPORT R16 37; var16 = 0x5BCED4C4[0xB62ECFE0]
     182 [-]: CALL R16 3 2 ; var16 = var16(var17, var18)
L23: 183 [-]: NAMECALL R13 R13 K38; var14 = var13; var13 = var13[0x751F061D]
     184 [-]: CALL R13 4 1 ; var13(var14, var15, var16)
     185 [-]: JUMP L43     ; goto L43
L24: 186 [-]: LOADN R13 30 ; var13 = 30
     187 [-]: JUMPIFNOTLE R13 R3 L43; goto L43 if var13 > var2886960
     188 [-]: LOADN R13 44 ; var13 = 44
     189 [-]: JUMPIFNOTLT R3 R13 L43; goto L43 if var3 >= var525110
     190 [-]: JUMPXEQKN R3 K39 L25 NOT; 
     191 [-]: SUB R1 R1 R2 ; var1 = var1 - var2
     192 [-]: LOADN R13 0  ; var13 = 0
     193 [-]: JUMPIFNOTLE R1 R13 L25; goto L25 if var1 > var789820
     194 [-]: GETUPVAL R13 12; var13 = upvalues[12]
     195 [-]: CALL R13 1 1 ; var13()
     196 [-]: LOADN R1 6   ; var1 = 6
L25: 197 [-]: JUMPIFNOTLT R4 R7 L26; goto L26 if var4 >= var331068
     198 [-]: GETUPVAL R13 5; var13 = upvalues[5]
     199 [-]: MOVE R15 R7  ; var15 = var7
     200 [-]: NAMECALL R13 R13 K40; var14 = var13; var13 = var13[0x27D04ADD]
     201 [-]: CALL R13 3 1 ; var13(var14, var15)
L26: 202 [-]: GETUPVAL R13 13; var13 = upvalues[13]
     203 [-]: NAMECALL R13 R13 K41; var14 = var13; var13 = var13[0xF456C2D7]
     204 [-]: CALL R13 2 2 ; var13 = var13(var14)
     205 [-]: FASTCALL1 64 R11 L27; 
     206 [-]: MOVE R15 R11 ; var15 = var11
     207 [-]: GETIMPORT R14 1; var14 = 0x7B998233
     208 [-]: CALL R14 2 2 ; var14 = var14(var15)
L27: 209 [-]: JUMPIFNOT R14 L28; goto L28 if not var14
     210 [-]: GETUPVAL R14 13; var14 = upvalues[13]
     211 [-]: NAMECALL R14 R14 K42; var15 = var14; var14 = var14[0xB87F958D]
     212 [-]: CALL R14 2 2 ; var14 = var14(var15)
     213 [-]: MOVE R11 R14 ; var11 = var14
L28: 214 [-]: FASTCALL1 64 R10 L29; 
     215 [-]: MOVE R15 R10 ; var15 = var10
     216 [-]: GETIMPORT R14 1; var14 = 0x7B998233
     217 [-]: CALL R14 2 2 ; var14 = var14(var15)
L29: 218 [-]: JUMPIFNOT R14 L30; goto L30 if not var14
     219 [-]: MOVE R10 R11 ; var10 = var11
L30: 220 [-]: GETIMPORT R14 45; var14 = _T["CamperOrbDamaged"]
     221 [-]: JUMPIFNOT R14 L32; goto L32 if not var14
     222 [-]: LOADN R14 41 ; var14 = 41
     223 [-]: JUMPIFLT R3 R14 L31; goto L31 if var3 < var2690608
     224 [-]: LOADN R14 41 ; var14 = 41
     225 [-]: JUMPIFNOTLE R14 R3 L32; goto L32 if var14 > var593216
     226 [-]: JUMPIFNOTLT R13 R10 L32; goto L32 if var13 >= var2352
L31: 227 [-]: LOADN R9 0   ; var9 = 0
     228 [-]: GETIMPORT R14 46; var14 = _T
     229 [-]: LOADB R15 0  ; var15 = false
     230 [-]: SETTABLEKS R15 R14 K44; var15["CamperOrbDamaged"] = var14
     231 [-]: MOVE R10 R13 ; var10 = var13
     232 [-]: JUMP L33     ; goto L33
L32: 233 [-]: ADD R9 R9 R2 ; var9 = var9 + var2
L33: 234 [-]: LOADK R14 K47; var14 = 2.5
     235 [-]: JUMPIFLE R9 R14 L34; goto L34 if var9 <= var3149383
     236 [-]: LOADK R14 K48; var14 = 0.94999998807907104
     237 [-]: JUMPIFNOTLE R14 R12 L38; goto L38 if var14 > var200508
L34: 238 [-]: GETUPVAL R15 3; var15 = upvalues[3]
     239 [-]: ADD R14 R15 R2; var14 = var15 + var2
     240 [-]: SETUPVAL R14 3; upvalues[14] = var3
     241 [-]: GETUPVAL R14 3; var14 = upvalues[3]
          243 [-]: GETIMPORT R14 50; var14 = 0xBE190284
     244 [-]: GETUPVAL R16 14; var16 = upvalues[14]
     245 [-]: GETUPVAL R18 3; var18 = upvalues[3]
     246 [-]: FASTCALL1 12 R18 L35; 
     247 [-]: GETIMPORT R17 52; var17 = 0x5BCED4C4[0x55F27C30]
     248 [-]: CALL R17 2 2 ; var17 = var17(var18)
L35: 249 [-]: NAMECALL R14 R14 K38; var15 = var14; var14 = var14[0x751F061D]
     250 [-]: CALL R14 4 1 ; var14(var15, var16, var17)
     251 [-]: MULK R16 R12 K53; var16 = var12 * 100
     252 [-]: MULK R19 R16 K53; var19 = var16 * 100
     253 [-]: ADDK R18 R19 K54; var18 = var19 + 0.5
     254 [-]: FASTCALL1 12 R18 L36; 
     255 [-]: GETIMPORT R17 52; var17 = 0x5BCED4C4[0x55F27C30]
     256 [-]: CALL R17 2 2 ; var17 = var17(var18)
L36:      258 [-]: FASTCALL2K 19 R15 K53 L37; 
     259 [-]: LOADK R16 K53; var16 = 100
     260 [-]: GETIMPORT R14 56; var14 = 0x5BCED4C4[0xAC1B386A]
     261 [-]: CALL R14 3 2 ; var14 = var14(var15, var16)
L37: 262 [-]: GETUPVAL R16 6; var16 = upvalues[6]
     263 [-]: GETTABLEKS R15 R16 K57; var15 = var16[0x03FC64EF]
     264 [-]: MOVE R16 R14 ; var16 = var14
     265 [-]: CALL R15 2 1 ; var15(var16)
L38: 266 [-]: MULK R14 R11 K54; var14 = var11 * 0.5
     267 [-]: JUMPIFNOTLT R13 R14 L39; goto L39 if var13 >= var855612
     268 [-]: GETUPVAL R14 13; var14 = upvalues[13]
     269 [-]: MULK R16 R11 K58; var16 = var11 * 0.75
     270 [-]: NAMECALL R14 R14 K59; var15 = var14; var14 = var14[0x57369B8B]
     271 [-]: CALL R14 3 1 ; var14(var15, var16)
     272 [-]: MULK R13 R11 K58; var13 = var11 * 0.75
     273 [-]: MOVE R10 R13 ; var10 = var13
L39: 274 [-]: LOADN R16 31 ; var16 = 31
     275 [-]: LOADN R14 44 ; var14 = 44
     276 [-]: LOADN R15 1  ; var15 = 1
     277 [-]: FORNPREP R14 L43; nforprep start - [escape at L43] -- var14 = iterator
L40: 278 [-]: JUMPIFNOTLT R3 R16 L42; goto L42 if var3 >= var987964
     279 [-]: GETUPVAL R19 15; var19 = upvalues[15]
     280 [-]: GETTABLE R18 R19 R16; var18 = var19[var16]
     281 [-]: FASTCALL1 64 R18 L41; 
     282 [-]: GETIMPORT R17 1; var17 = 0x7B998233
     283 [-]: CALL R17 2 2 ; var17 = var17(var18)
L41: 284 [-]: JUMPIF R17 L42; goto L42 if var17
     285 [-]: GETUPVAL R19 15; var19 = upvalues[15]
     286 [-]: GETTABLE R18 R19 R16; var18 = var19[var16]
     287 [-]: GETTABLEKS R17 R18 K60; var17 = var18["time"]
     288 [-]: JUMPIFNOTLE R17 R12 L42; goto L42 if var17 > var266556
     289 [-]: GETUPVAL R17 4; var17 = upvalues[4]
     290 [-]: MOVE R19 R16 ; var19 = var16
     291 [-]: NAMECALL R17 R17 K26; var18 = var17; var17 = var17[0x8ABFF40E]
     292 [-]: CALL R17 3 1 ; var17(var18, var19)
     293 [-]: GETUPVAL R18 15; var18 = upvalues[15]
     294 [-]: GETTABLE R17 R18 R16; var17 = var18[var16]
     295 [-]: GETTABLEKS R7 R17 K61; var7 = var17["alert"]
L42: 296 [-]: FORNLOOP R14 L40; nforloop end - iterate + goto L40
L43: 297 [-]: GETIMPORT R13 63; var13 = 0xCBD666E1
     298 [-]: LOADN R14 0  ; var14 = 0
     299 [-]: CALL R13 2 1 ; var13(var14)
     300 [-]: JUMPBACK L3  ; goto L3
L44: 301 [-]: GETIMPORT R15 65; var15 = 0x0469F296
     302 [-]: LOADK R16 K66; var16 = "LeavingCB"
     303 [-]: CALL R15 2 0 ; var15, ... = var15(var16)
     304 [-]: NAMECALL R13 R0 K67; var14 = var0; var13 = var0[0x3D412E0D]
     305 [-]: CALL R13 0 1 ; var13(var14, ...)
     306 [-]: GETIMPORT R15 65; var15 = 0x0469F296
     307 [-]: LOADK R16 K68; var16 = "ReturningCB"
     308 [-]: CALL R15 2 0 ; var15, ... = var15(var16)
     309 [-]: NAMECALL R13 R0 K69; var14 = var0; var13 = var0[0x136A027D]
     310 [-]: CALL R13 0 1 ; var13(var14, ...)
     311 [-]: GETUPVAL R13 4; var13 = upvalues[4]
     312 [-]: NAMECALL R13 R13 K70; var14 = var13; var13 = var13[0x588ED000]
     313 [-]: CALL R13 2 1 ; var13(var14)
     314 [-]: RETURN R0 0  ; 


; Name:            
; Defined at line: 688
; #Upvalues:       1
; #Parameters:     3
; Is_vararg:       0
; Max Stack Size:  7

       0 [-]: FASTCALL1 64 R0 L0; 
       1 [-]: MOVE R4 R0   ; var4 = var0
       2 [-]: GETIMPORT R3 1; var3 = 0x7B998233
       3 [-]: CALL R3 2 2  ; var3 = var3(var4)
L 0:   4 [-]: JUMPIFNOT R3 L1; goto L1 if not var3
       5 [-]: RETURN R0 0  ; 
L 1:   6 [-]: NAMECALL R4 R0 K2; var5 = var0; var4 = var0[0xFA9E477F]
       7 [-]: CALL R4 2 0  ; var4, ... = var4(var5)
       8 [-]: FASTCALL 64 L2; 
       9 [-]: GETIMPORT R3 1; var3 = 0x7B998233
      10 [-]: CALL R3 0 2  ; var3 = var3(var4, ...)
L 2:  11 [-]: JUMPIFNOT R3 L3; goto L3 if not var3
      12 [-]: JUMPXEQKNIL R1 L4 NOT; 
L 3:  13 [-]: LOADN R1 1   ; var1 = 1
L 4:  14 [-]: JUMPXEQKN R1 K3 L5 NOT; 
      15 [-]: GETIMPORT R3 5; var3 = 0xBE190284
      16 [-]: GETUPVAL R5 0; var5 = upvalues[0]
      17 [-]: LOADN R6 1   ; var6 = 1
      18 [-]: NAMECALL R3 R3 K6; var4 = var3; var3 = var3[0x751F061D]
      19 [-]: CALL R3 4 1  ; var3(var4, var5, var6)
      20 [-]: LOADK R5 K7  ; var5 = "Disable"
      21 [-]: NAMECALL R3 R2 K8; var4 = var2; var3 = var2[0x8EB2112D]
      22 [-]: CALL R3 3 1  ; var3(var4, var5)
L 5:  23 [-]: RETURN R0 0  ; 


; Name:            
; Defined at line: 701
; #Upvalues:       1
; #Parameters:     3
; Is_vararg:       0
; Max Stack Size:  7

       0 [-]: GETIMPORT R3 1; var3 = 0xBE190284
       1 [-]: GETUPVAL R5 0; var5 = upvalues[0]
       2 [-]: LOADN R6 1   ; var6 = 1
       3 [-]: NAMECALL R3 R3 K2; var4 = var3; var3 = var3[0x751F061D]
       4 [-]: CALL R3 4 1  ; var3(var4, var5, var6)
       5 [-]: RETURN R0 0  ; 


; Name:            
; Defined at line: 706
; #Upvalues:       1
; #Parameters:     0
; Is_vararg:       0
; Max Stack Size:  2

       0 [-]: GETIMPORT R0 1; var0 = 0x89326C93
       1 [-]: NAMECALL R0 R0 K2; var1 = var0; var0 = var0[0x8B5B1F58]
       2 [-]: CALL R0 2 2  ; var0 = var0(var1)
       3 [-]: SETUPVAL R0 0; upvalues[0] = var0
       4 [-]: RETURN R0 0  ; 


; Name:            
; Defined at line: 710
; #Upvalues:       2
; #Parameters:     0
; Is_vararg:       0
; Max Stack Size:  3

       0 [-]: GETUPVAL R1 0; var1 = upvalues[0]
       1 [-]: GETTABLEKS R0 R1 K0; var0 = var1[0x7E8A976A]
       2 [-]: GETUPVAL R1 1; var1 = upvalues[1]
       3 [-]: LOADB R2 1   ; var2 = true
       4 [-]: CALL R0 3 1  ; var0(var1, var2)
       5 [-]: RETURN R0 0  ; 


; Name:            
; Defined at line: 714
; #Upvalues:       2
; #Parameters:     0
; Is_vararg:       0
; Max Stack Size:  3

       0 [-]: GETUPVAL R1 0; var1 = upvalues[0]
       1 [-]: GETTABLEKS R0 R1 K0; var0 = var1[0x7E8A976A]
       2 [-]: GETUPVAL R1 1; var1 = upvalues[1]
       3 [-]: LOADB R2 0   ; var2 = false
       4 [-]: CALL R0 3 1  ; var0(var1, var2)
       5 [-]: RETURN R0 0  ; 


; Name:            
; Defined at line: 718
; #Upvalues:       1
; #Parameters:     1
; Is_vararg:       0
; Max Stack Size:  5

       0 [-]: GETUPVAL R1 0; var1 = upvalues[0]
       1 [-]: MOVE R2 R0   ; var2 = var0
       2 [-]: LOADN R3 5   ; var3 = 5
       3 [-]: LOADN R4 10  ; var4 = 10
       4 [-]: CALL R1 4 1  ; var1(var2, var3, var4)
       5 [-]: RETURN R0 0  ; 



