; This file has been disassembled using luadec 2.0.2 by sztupy (modified by Reversive)

; Name:            
; Defined at line: 0
; #Upvalues:       0
; #Parameters:     0
; Is_vararg:       2
; Max Stack Size:  61

  1 [-]: GETGLOBAL R0 K0        ; R0 := 0x2d0fad09
  2 [-]: LOADK     R1 K1        ; R1 := "Lotus.Interface.LotusUtilities"
  3 [-]: CALL      R0 2 2       ; R0 := R0(R1)
  4 [-]: GETGLOBAL R1 K0        ; R1 := 0x2d0fad09
  5 [-]: LOADK     R2 K2        ; R2 := "EE.Interface.Utilities"
  6 [-]: CALL      R1 2 2       ; R1 := R1(R2)
  7 [-]: GETGLOBAL R2 K0        ; R2 := 0x2d0fad09
  8 [-]: LOADK     R3 K3        ; R3 := "Lotus.Interface.UIStyleUtilities"
  9 [-]: CALL      R2 2 2       ; R2 := R2(R3)
 10 [-]: GETGLOBAL R3 K0        ; R3 := 0x2d0fad09
 11 [-]: LOADK     R4 K4        ; R4 := "EE.Interface.AnchorMgr"
 12 [-]: CALL      R3 2 2       ; R3 := R3(R4)
 13 [-]: LOADKB    R4 0 0       ; R4 := false
 14 [-]: LOADKB    R5 1 0       ; R5 := true
 15 [-]: LOADNIL   R6 R7        ; R6 := R7 := nil
 16 [-]: CONST     R8 0         ; R8 := 0.000000
 17 [-]: LOADKB    R9 0 0       ; R9 := false
 18 [-]: LOADKB    R10 0 0      ; R10 := false
 19 [-]: LOADKB    R11 0 0      ; R11 := false
 20 [-]: LOADKB    R12 0 0      ; R12 := false
 21 [-]: LOADNIL   R13 R13      ; R13 := nil
 22 [-]: LOADKB    R14 0 0      ; R14 := false
 23 [-]: LOADKB    R15 0 0      ; R15 := false
 24 [-]: LOADKB    R16 0 0      ; R16 := false
 25 [-]: NEWTABLE  R17 0 3      ; R17 := {}
 26 [-]: SETTABLE  R17 K5 K6    ; R17["InitialName"] := ""
 27 [-]: SETTABLE  R17 K7 K8    ; R17["CurrName"] := nil
 28 [-]: SETTABLE  R17 K9 K10   ; R17["CurrLines"] := 0.000000
 29 [-]: NEWTABLE  R18 0 3      ; R18 := {}
 30 [-]: SETTABLE  R18 K11 K6   ; R18["InitialMessage"] := ""
 31 [-]: SETTABLE  R18 K12 K8   ; R18["CurrMessage"] := nil
 32 [-]: SETTABLE  R18 K9 K10   ; R18["CurrLines"] := 0.000000
 33 [-]: NEWTABLE  R19 0 0      ; R19 := {}
 34 [-]: LOADNIL   R20 R21      ; R20 := R21 := nil
 35 [-]: LOADK     R22 K6       ; R22 := ""
 36 [-]: NEWTABLE  R23 0 0      ; R23 := {}
 37 [-]: NEWTABLE  R24 0 3      ; R24 := {}
 38 [-]: SETTABLE  R24 K13 K14  ; R24["Visible"] := false
 39 [-]: SETTABLE  R24 K15 K10  ; R24["TotalTime"] := 0.000000
 40 [-]: SETTABLE  R24 K16 K10  ; R24["TimeLeft"] := 0.000000
 41 [-]: LOADNIL   R25 R25      ; R25 := nil
 42 [-]: LOADKB    R26 0 0      ; R26 := false
 43 [-]: LOADKB    R27 0 0      ; R27 := false
 44 [-]: GETGLOBAL R28 K17      ; R28 := 0x7ed0a956
 45 [-]: LOADK     R29 K18      ; R29 := "/Lotus/Objects/Tenno/Props/TnoPaintBotDojoDeco"
 46 [-]: CALL      R28 2 2      ; R28 := R28(R29)
 47 [-]: CLOSURE   R29 0        ; R29 := closure(Function #1)
 48 [-]: MOVE      R0 R5        ; R0 := R5
 49 [-]: MOVE      R0 R14       ; R0 := R14
 50 [-]: MOVE      R0 R1        ; R0 := R1
 51 [-]: MOVE      R0 R23       ; R0 := R23
 52 [-]: CLOSURE   R30 1        ; R30 := closure(Function #2)
 53 [-]: MOVE      R0 R29       ; R0 := R29
 54 [-]: CLOSURE   R31 2        ; R31 := closure(Function #3)
 55 [-]: CLOSURE   R32 3        ; R32 := closure(Function #4)
 56 [-]: MOVE      R0 R6        ; R0 := R6
 57 [-]: MOVE      R0 R31       ; R0 := R31
 58 [-]: MOVE      R0 R7        ; R0 := R7
 59 [-]: CLOSURE   R33 4        ; R33 := closure(Function #5)
 60 [-]: MOVE      R0 R7        ; R0 := R7
 61 [-]: MOVE      R0 R26       ; R0 := R26
 62 [-]: CLOSURE   R34 5        ; R34 := closure(Function #6)
 63 [-]: MOVE      R0 R20       ; R0 := R20
 64 [-]: MOVE      R0 R24       ; R0 := R24
 65 [-]: CLOSURE   R35 6        ; R35 := closure(Function #7)
 66 [-]: MOVE      R0 R7        ; R0 := R7
 67 [-]: MOVE      R0 R11       ; R0 := R11
 68 [-]: MOVE      R0 R14       ; R0 := R14
 69 [-]: MOVE      R0 R29       ; R0 := R29
 70 [-]: MOVE      R0 R27       ; R0 := R27
 71 [-]: MOVE      R0 R26       ; R0 := R26
 72 [-]: MOVE      R0 R20       ; R0 := R20
 73 [-]: MOVE      R0 R15       ; R0 := R15
 74 [-]: MOVE      R0 R0        ; R0 := R0
 75 [-]: MOVE      R0 R18       ; R0 := R18
 76 [-]: MOVE      R0 R17       ; R0 := R17
 77 [-]: MOVE      R0 R1        ; R0 := R1
 78 [-]: MOVE      R0 R21       ; R0 := R21
 79 [-]: MOVE      R0 R22       ; R0 := R22
 80 [-]: MOVE      R0 R24       ; R0 := R24
 81 [-]: MOVE      R0 R6        ; R0 := R6
 82 [-]: MOVE      R0 R10       ; R0 := R10
 83 [-]: MOVE      R0 R9        ; R0 := R9
 84 [-]: MOVE      R0 R33       ; R0 := R33
 85 [-]: MOVE      R0 R34       ; R0 := R34
 86 [-]: CLOSURE   R36 7        ; R36 := closure(Function #8)
 87 [-]: MOVE      R0 R0        ; R0 := R0
 88 [-]: MOVE      R0 R6        ; R0 := R6
 89 [-]: MOVE      R0 R35       ; R0 := R35
 90 [-]: MOVE      R0 R27       ; R0 := R27
 91 [-]: MOVE      R0 R16       ; R0 := R16
 92 [-]: SETGLOBAL R36 K19      ; Shutdown := R36
 93 [-]: CLOSURE   R36 8        ; R36 := closure(Function #9)
 94 [-]: MOVE      R0 R11       ; R0 := R11
 95 [-]: MOVE      R0 R1        ; R0 := R1
 96 [-]: MOVE      R0 R18       ; R0 := R18
 97 [-]: CLOSURE   R37 9        ; R37 := closure(Function #10)
 98 [-]: MOVE      R0 R11       ; R0 := R11
 99 [-]: MOVE      R0 R1        ; R0 := R1
100 [-]: MOVE      R0 R17       ; R0 := R17
101 [-]: MOVE      R0 R18       ; R0 := R18
102 [-]: CLOSURE   R38 10       ; R38 := closure(Function #11)
103 [-]: CLOSURE   R39 11       ; R39 := closure(Function #12)
104 [-]: CLOSURE   R40 12       ; R40 := closure(Function #13)
105 [-]: MOVE      R0 R38       ; R0 := R38
106 [-]: SETGLOBAL R40 K20      ; OSKMsgCallback := R40
107 [-]: CLOSURE   R40 13       ; R40 := closure(Function #14)
108 [-]: MOVE      R0 R39       ; R0 := R39
109 [-]: SETGLOBAL R40 K21      ; OSKNameCallback := R40
110 [-]: CLOSURE   R40 14       ; R40 := closure(Function #15)
111 [-]: MOVE      R0 R38       ; R0 := R38
112 [-]: SETGLOBAL R40 K22      ; InputDialogMsgCallback := R40
113 [-]: CLOSURE   R40 15       ; R40 := closure(Function #16)
114 [-]: MOVE      R0 R39       ; R0 := R39
115 [-]: SETGLOBAL R40 K23      ; InputDialogNameCallback := R40
116 [-]: CLOSURE   R40 16       ; R40 := closure(Function #17)
117 [-]: MOVE      R0 R11       ; R0 := R11
118 [-]: MOVE      R0 R7        ; R0 := R7
119 [-]: MOVE      R0 R36       ; R0 := R36
120 [-]: SETGLOBAL R40 K24      ; UpdateMessageConfirm := R40
121 [-]: CLOSURE   R40 17       ; R40 := closure(Function #18)
122 [-]: MOVE      R0 R11       ; R0 := R11
123 [-]: MOVE      R0 R7        ; R0 := R7
124 [-]: MOVE      R0 R37       ; R0 := R37
125 [-]: SETGLOBAL R40 K25      ; UpdateNameConfirm := R40
126 [-]: CLOSURE   R40 18       ; R40 := closure(Function #19)
127 [-]: MOVE      R0 R11       ; R0 := R11
128 [-]: MOVE      R0 R1        ; R0 := R1
129 [-]: SETGLOBAL R40 K26      ; UpdateMessage := R40
130 [-]: CLOSURE   R40 19       ; R40 := closure(Function #20)
131 [-]: MOVE      R0 R11       ; R0 := R11
132 [-]: MOVE      R0 R1        ; R0 := R1
133 [-]: SETGLOBAL R40 K27      ; UpdateName := R40
134 [-]: CLOSURE   R40 20       ; R40 := closure(Function #21)
135 [-]: MOVE      R0 R15       ; R0 := R15
136 [-]: MOVE      R0 R26       ; R0 := R26
137 [-]: MOVE      R0 R0        ; R0 := R0
138 [-]: SETGLOBAL R40 K28      ; EditMessageCallback := R40
139 [-]: CLOSURE   R40 21       ; R40 := closure(Function #22)
140 [-]: MOVE      R0 R15       ; R0 := R15
141 [-]: MOVE      R0 R26       ; R0 := R26
142 [-]: MOVE      R0 R0        ; R0 := R0
143 [-]: SETGLOBAL R40 K29      ; RoomNameCallback := R40
144 [-]: CLOSURE   R40 22       ; R40 := closure(Function #23)
145 [-]: MOVE      R0 R1        ; R0 := R1
146 [-]: SETGLOBAL R40 K30      ; OnResetLeaderboardResult := R40
147 [-]: CLOSURE   R40 23       ; R40 := closure(Function #24)
148 [-]: MOVE      R0 R6        ; R0 := R6
149 [-]: CLOSURE   R41 24       ; R41 := closure(Function #25)
150 [-]: MOVE      R0 R40       ; R0 := R40
151 [-]: SETGLOBAL R41 K31      ; ResetLeaderboard := R41
152 [-]: CLOSURE   R41 25       ; R41 := closure(Function #26)
153 [-]: MOVE      R0 R1        ; R0 := R1
154 [-]: CLOSURE   R42 26       ; R42 := closure(Function #27)
155 [-]: MOVE      R0 R6        ; R0 := R6
156 [-]: MOVE      R0 R41       ; R0 := R41
157 [-]: CLOSURE   R43 27       ; R43 := closure(Function #28)
158 [-]: MOVE      R0 R42       ; R0 := R42
159 [-]: SETGLOBAL R43 K32      ; ResetObstacleCourseReallyConfirm := R43
160 [-]: CLOSURE   R43 28       ; R43 := closure(Function #29)
161 [-]: MOVE      R0 R11       ; R0 := R11
162 [-]: MOVE      R0 R1        ; R0 := R1
163 [-]: SETGLOBAL R43 K33      ; ResetObstacleCourseConfirm := R43
164 [-]: CLOSURE   R43 29       ; R43 := closure(Function #30)
165 [-]: MOVE      R0 R11       ; R0 := R11
166 [-]: MOVE      R0 R1        ; R0 := R1
167 [-]: SETGLOBAL R43 K34      ; ResetObstacleCourse := R43
168 [-]: CLOSURE   R43 30       ; R43 := closure(Function #31)
169 [-]: MOVE      R0 R1        ; R0 := R1
170 [-]: CLOSURE   R44 31       ; R44 := closure(Function #32)
171 [-]: MOVE      R0 R6        ; R0 := R6
172 [-]: MOVE      R0 R7        ; R0 := R7
173 [-]: MOVE      R0 R43       ; R0 := R43
174 [-]: SETGLOBAL R44 K35      ; ToggleAllowOperatorMode := R44
175 [-]: CLOSURE   R44 32       ; R44 := closure(Function #33)
176 [-]: MOVE      R0 R7        ; R0 := R7
177 [-]: CLOSURE   R45 33       ; R45 := closure(Function #34)
178 [-]: MOVE      R0 R6        ; R0 := R6
179 [-]: MOVE      R0 R7        ; R0 := R7
180 [-]: MOVE      R0 R44       ; R0 := R44
181 [-]: CLOSURE   R46 34       ; R46 := closure(Function #35)
182 [-]: MOVE      R0 R45       ; R0 := R45
183 [-]: SETGLOBAL R46 K36      ; SetOpenSpaceBackdrop := R46
184 [-]: CLOSURE   R46 35       ; R46 := closure(Function #36)
185 [-]: MOVE      R0 R1        ; R0 := R1
186 [-]: MOVE      R0 R45       ; R0 := R45
187 [-]: SETGLOBAL R46 K37      ; OpenBackdropSelect := R46
188 [-]: CLOSURE   R46 36       ; R46 := closure(Function #37)
189 [-]: MOVE      R0 R11       ; R0 := R11
190 [-]: MOVE      R0 R29       ; R0 := R29
191 [-]: CLOSURE   R47 37       ; R47 := closure(Function #38)
192 [-]: MOVE      R0 R46       ; R0 := R46
193 [-]: SETGLOBAL R47 K38      ; ConfirmationReviewed := R47
194 [-]: CLOSURE   R47 38       ; R47 := closure(Function #39)
195 [-]: MOVE      R0 R6        ; R0 := R6
196 [-]: MOVE      R0 R11       ; R0 := R11
197 [-]: MOVE      R0 R29       ; R0 := R29
198 [-]: SETGLOBAL R47 K39      ; HasChildConfirmationReviewed := R47
199 [-]: LOADNIL   R47 R48      ; R47 := R48 := nil
200 [-]: CLOSURE   R49 39       ; R49 := closure(Function #40)
201 [-]: MOVE      R0 R47       ; R0 := R47
202 [-]: MOVE      R0 R11       ; R0 := R11
203 [-]: MOVE      R0 R25       ; R0 := R25
204 [-]: MOVE      R0 R1        ; R0 := R1
205 [-]: SETGLOBAL R49 K40      ; ComponentDestructionQueued := R49
206 [-]: CLOSURE   R49 40       ; R49 := closure(Function #41)
207 [-]: MOVE      R0 R47       ; R0 := R47
208 [-]: MOVE      R0 R48       ; R0 := R48
209 [-]: CLOSURE   R50 41       ; R50 := closure(Function #42)
210 [-]: MOVE      R0 R11       ; R0 := R11
211 [-]: MOVE      R0 R7        ; R0 := R7
212 [-]: MOVE      R0 R32       ; R0 := R32
213 [-]: MOVE      R0 R6        ; R0 := R6
214 [-]: MOVE      R0 R1        ; R0 := R1
215 [-]: MOVE      R0 R49       ; R0 := R49
216 [-]: SETGLOBAL R50 K41      ; DestroyRoom := R50
217 [-]: CLOSURE   R50 42       ; R50 := closure(Function #43)
218 [-]: MOVE      R0 R11       ; R0 := R11
219 [-]: MOVE      R0 R1        ; R0 := R1
220 [-]: CLOSURE   R51 43       ; R51 := closure(Function #44)
221 [-]: MOVE      R0 R11       ; R0 := R11
222 [-]: MOVE      R0 R50       ; R0 := R50
223 [-]: SETGLOBAL R51 K42      ; ConfirmRoomConvert := R51
224 [-]: CLOSURE   R51 44       ; R51 := closure(Function #45)
225 [-]: MOVE      R0 R11       ; R0 := R11
226 [-]: MOVE      R0 R7        ; R0 := R7
227 [-]: MOVE      R0 R1        ; R0 := R1
228 [-]: SETGLOBAL R51 K43      ; ChangeRoom := R51
229 [-]: CLOSURE   R51 45       ; R51 := closure(Function #46)
230 [-]: MOVE      R0 R11       ; R0 := R11
231 [-]: MOVE      R0 R9        ; R0 := R9
232 [-]: MOVE      R0 R40       ; R0 := R40
233 [-]: MOVE      R0 R6        ; R0 := R6
234 [-]: MOVE      R0 R49       ; R0 := R49
235 [-]: SETGLOBAL R51 K44      ; ConfirmQueueDestruction := R51
236 [-]: CLOSURE   R51 46       ; R51 := closure(Function #47)
237 [-]: MOVE      R0 R47       ; R0 := R47
238 [-]: MOVE      R0 R11       ; R0 := R11
239 [-]: MOVE      R0 R1        ; R0 := R1
240 [-]: SETGLOBAL R51 K45      ; ComponentDestructionCancelled := R51
241 [-]: CLOSURE   R51 47       ; R51 := closure(Function #48)
242 [-]: MOVE      R0 R47       ; R0 := R47
243 [-]: MOVE      R0 R48       ; R0 := R48
244 [-]: CLOSURE   R52 48       ; R52 := closure(Function #49)
245 [-]: MOVE      R0 R11       ; R0 := R11
246 [-]: MOVE      R0 R1        ; R0 := R1
247 [-]: SETGLOBAL R52 K46      ; CancelDestruction := R52
248 [-]: CLOSURE   R52 49       ; R52 := closure(Function #50)
249 [-]: MOVE      R0 R11       ; R0 := R11
250 [-]: MOVE      R0 R10       ; R0 := R10
251 [-]: MOVE      R0 R6        ; R0 := R6
252 [-]: MOVE      R0 R51       ; R0 := R51
253 [-]: SETGLOBAL R52 K47      ; ConfirmDestructionCancel := R52
254 [-]: CLOSURE   R52 50       ; R52 := closure(Function #51)
255 [-]: MOVE      R0 R29       ; R0 := R29
256 [-]: SETGLOBAL R52 K48      ; OnErrorExitConsole := R52
257 [-]: CLOSURE   R52 51       ; R52 := closure(Function #52)
258 [-]: MOVE      R0 R1        ; R0 := R1
259 [-]: MOVE      R0 R6        ; R0 := R6
260 [-]: MOVE      R0 R16       ; R0 := R16
261 [-]: MOVE      R0 R29       ; R0 := R29
262 [-]: SETGLOBAL R52 K49      ; EnterDecorationMode := R52
263 [-]: CLOSURE   R52 52       ; R52 := closure(Function #53)
264 [-]: MOVE      R0 R28       ; R0 := R28
265 [-]: SETGLOBAL R52 K50      ; _EnterPreviewMode := R52
266 [-]: CLOSURE   R52 53       ; R52 := closure(Function #54)
267 [-]: MOVE      R0 R29       ; R0 := R29
268 [-]: MOVE      R0 R1        ; R0 := R1
269 [-]: SETGLOBAL R52 K51      ; EnterPreviewMode := R52
270 [-]: CLOSURE   R52 54       ; R52 := closure(Function #55)
271 [-]: MOVE      R0 R29       ; R0 := R29
272 [-]: SETGLOBAL R52 K52      ; ExitPreviewMode := R52
273 [-]: CLOSURE   R52 55       ; R52 := closure(Function #56)
274 [-]: MOVE      R0 R11       ; R0 := R11
275 [-]: MOVE      R0 R1        ; R0 := R1
276 [-]: CLOSURE   R53 56       ; R53 := closure(Function #57)
277 [-]: MOVE      R0 R11       ; R0 := R11
278 [-]: MOVE      R0 R6        ; R0 := R6
279 [-]: MOVE      R0 R52       ; R0 := R52
280 [-]: MOVE      R0 R46       ; R0 := R46
281 [-]: SETGLOBAL R53 K53      ; ConfirmSpawnRoomChange := R53
282 [-]: CLOSURE   R53 57       ; R53 := closure(Function #58)
283 [-]: MOVE      R0 R11       ; R0 := R11
284 [-]: MOVE      R0 R1        ; R0 := R1
285 [-]: SETGLOBAL R53 K54      ; MakeSpawnRoom := R53
286 [-]: CLOSURE   R53 58       ; R53 := closure(Function #59)
287 [-]: MOVE      R0 R23       ; R0 := R23
288 [-]: MOVE      R0 R1        ; R0 := R1
289 [-]: MOVE      R0 R12       ; R0 := R12
290 [-]: CLOSURE   R54 59       ; R54 := closure(Function #60)
291 [-]: MOVE      R0 R4        ; R0 := R4
292 [-]: MOVE      R0 R25       ; R0 := R25
293 [-]: MOVE      R0 R1        ; R0 := R1
294 [-]: MOVE      R0 R7        ; R0 := R7
295 [-]: MOVE      R0 R8        ; R0 := R8
296 [-]: MOVE      R0 R12       ; R0 := R12
297 [-]: MOVE      R0 R23       ; R0 := R23
298 [-]: MOVE      R0 R53       ; R0 := R53
299 [-]: MOVE      R0 R15       ; R0 := R15
300 [-]: MOVE      R0 R18       ; R0 := R18
301 [-]: MOVE      R0 R34       ; R0 := R34
302 [-]: MOVE      R0 R17       ; R0 := R17
303 [-]: MOVE      R0 R24       ; R0 := R24
304 [-]: SETGLOBAL R54 K55      ; Update := R54
305 [-]: CLOSURE   R54 60       ; R54 := closure(Function #61)
306 [-]: MOVE      R0 R19       ; R0 := R19
307 [-]: MOVE      R0 R1        ; R0 := R1
308 [-]: CLOSURE   R55 61       ; R55 := closure(Function #62)
309 [-]: MOVE      R0 R20       ; R0 := R20
310 [-]: CLOSURE   R56 62       ; R56 := closure(Function #63)
311 [-]: MOVE      R0 R19       ; R0 := R19
312 [-]: CLOSURE   R57 63       ; R57 := closure(Function #64)
313 [-]: MOVE      R0 R0        ; R0 := R0
314 [-]: MOVE      R0 R26       ; R0 := R26
315 [-]: MOVE      R0 R19       ; R0 := R19
316 [-]: MOVE      R0 R2        ; R0 := R2
317 [-]: MOVE      R0 R13       ; R0 := R13
318 [-]: MOVE      R0 R3        ; R0 := R3
319 [-]: MOVE      R0 R54       ; R0 := R54
320 [-]: MOVE      R0 R55       ; R0 := R55
321 [-]: MOVE      R0 R56       ; R0 := R56
322 [-]: MOVE      R0 R30       ; R0 := R30
323 [-]: MOVE      R0 R1        ; R0 := R1
324 [-]: MOVE      R0 R12       ; R0 := R12
325 [-]: MOVE      R0 R4        ; R0 := R4
326 [-]: SETGLOBAL R57 K56      ; Initialize := R57
327 [-]: CLOSURE   R57 64       ; R57 := closure(Function #65)
328 [-]: MOVE      R0 R29       ; R0 := R29
329 [-]: SETGLOBAL R57 K57      ; Close := R57
330 [-]: CLOSURE   R57 65       ; R57 := closure(Function #66)
331 [-]: MOVE      R0 R29       ; R0 := R29
332 [-]: SETGLOBAL R57 K58      ; ContributionResultReviewed := R57
333 [-]: CLOSURE   R57 66       ; R57 := closure(Function #67)
334 [-]: MOVE      R0 R6        ; R0 := R6
335 [-]: MOVE      R0 R35       ; R0 := R35
336 [-]: MOVE      R0 R23       ; R0 := R23
337 [-]: MOVE      R0 R12       ; R0 := R12
338 [-]: MOVE      R0 R53       ; R0 := R53
339 [-]: MOVE      R0 R5        ; R0 := R5
340 [-]: SETGLOBAL R57 K59      ; ReadDojoVars := R57
341 [-]: CLOSURE   R57 67       ; R57 := closure(Function #68)
342 [-]: MOVE      R0 R5        ; R0 := R5
343 [-]: MOVE      R0 R29       ; R0 := R29
344 [-]: SETGLOBAL R57 K60      ; onKeyDown_MENU_CANCEL := R57
345 [-]: CLOSURE   R57 68       ; R57 := closure(Function #69)
346 [-]: MOVE      R0 R1        ; R0 := R1
347 [-]: MOVE      R0 R19       ; R0 := R19
348 [-]: CLOSURE   R58 69       ; R58 := closure(Function #70)
349 [-]: MOVE      R0 R57       ; R0 := R57
350 [-]: SETGLOBAL R58 K61      ; EditMessageActionFocused := R58
351 [-]: CLOSURE   R58 70       ; R58 := closure(Function #71)
352 [-]: MOVE      R0 R57       ; R0 := R57
353 [-]: SETGLOBAL R58 K62      ; RoomNameActionFocused := R58
354 [-]: CLOSURE   R58 71       ; R58 := closure(Function #72)
355 [-]: MOVE      R0 R19       ; R0 := R19
356 [-]: CLOSURE   R59 72       ; R59 := closure(Function #73)
357 [-]: MOVE      R0 R58       ; R0 := R58
358 [-]: SETGLOBAL R59 K63      ; EditMessageActionUnfocused := R59
359 [-]: CLOSURE   R59 73       ; R59 := closure(Function #74)
360 [-]: MOVE      R0 R58       ; R0 := R58
361 [-]: SETGLOBAL R59 K64      ; RoomNameActionUnfocused := R59
362 [-]: CLOSURE   R59 74       ; R59 := closure(Function #75)
363 [-]: MOVE      R0 R1        ; R0 := R1
364 [-]: CLOSURE   R60 75       ; R60 := closure(Function #76)
365 [-]: MOVE      R0 R59       ; R0 := R59
366 [-]: SETGLOBAL R60 K65      ; EditMessageActionPressed := R60
367 [-]: CLOSURE   R60 76       ; R60 := closure(Function #77)
368 [-]: MOVE      R0 R59       ; R0 := R59
369 [-]: SETGLOBAL R60 K66      ; RoomNameActionPressed := R60
370 [-]: CLOSURE   R60 77       ; R60 := closure(Function #78)
371 [-]: MOVE      R0 R1        ; R0 := R1
372 [-]: MOVE      R0 R19       ; R0 := R19
373 [-]: MOVE      R0 R22       ; R0 := R22
374 [-]: SETGLOBAL R60 K67      ; DeleteFocused := R60
375 [-]: CLOSURE   R60 78       ; R60 := closure(Function #79)
376 [-]: MOVE      R0 R19       ; R0 := R19
377 [-]: SETGLOBAL R60 K68      ; DeleteUnfocused := R60
378 [-]: CLOSURE   R60 79       ; R60 := closure(Function #80)
379 [-]: MOVE      R0 R21       ; R0 := R21
380 [-]: SETGLOBAL R60 K69      ; DeletePressed := R60
381 [-]: CLOSURE   R60 80       ; R60 := closure(Function #81)
382 [-]: MOVE      R0 R13       ; R0 := R13
383 [-]: SETGLOBAL R60 K70      ; onViewportSizeChanged := R60
384 [-]: CLOSURE   R60 81       ; R60 := closure(Function #82)
385 [-]: MOVE      R0 R1        ; R0 := R1
386 [-]: SETGLOBAL R60 K71      ; OnGamepadTransition := R60
387 [-]: CLOSURE   R60 82       ; R60 := closure(Function #83)
388 [-]: SETGLOBAL R60 K72      ; SupportsThemes := R60
389 [-]: RETURN    R0 1         ; return 


; Function #1:
;
; Name:            
; Defined at line: 46
; #Upvalues:       4
; #Parameters:     0
; Is_vararg:       0
; Max Stack Size:  7

  1 [-]: LOADKB    R0 1 0       ; R0 := true
  2 [-]: SETUPVAL  R0 U0        ; U82 := R0
  3 [-]: LOADKB    R0 1 0       ; R0 := true
  4 [-]: SETUPVAL  R0 U1        ; U82 := R1
  5 [-]: GETUPVAL  R0 U2        ; R0 := U2
  6 [-]: GETTABLE  R0 R0 K0     ; R0 := R0[0x659d451f]
  7 [-]: GETGLOBAL R1 K1        ; R1 := 0x0032441c
  8 [-]: GETTABLE  R1 R1 K2     ; R1 := R1["UISound_GridOpenTwo"]
  9 [-]: CALL      R0 2 1       ; R0(R1)
 10 [-]: GETGLOBAL R0 K3        ; R0 := 0x25312c9b
 11 [-]: GETGLOBAL R1 K4        ; R1 := 0xae91e43b
 12 [-]: LOADK     R2 K5        ; R2 := "_root"
 13 [-]: CONST     R3 8         ; R3 := 8.000000
 14 [-]: NEWTABLE  R4 1 0       ; R4 := {}
 15 [-]: CONST     R5 10        ; R5 := 10.000000
 16 [-]: SETLIST   R4 1 1       ; R4[(1-1)*FPF+i] := R(4+i), 1 <= i <= 1
 17 [-]: NEWTABLE  R5 1 0       ; R5 := {}
 18 [-]: CONST     R6 0         ; R6 := 0.000000
 19 [-]: SETLIST   R5 1 1       ; R5[(1-1)*FPF+i] := R(5+i), 1 <= i <= 1
 20 [-]: CONST     R6 0         ; R6 := 0.250000
 21 [-]: CALL      R0 7 1       ; R0(R1,R2,R3,R4,R5,R6)
 22 [-]: GETUPVAL  R0 U2        ; R0 := U2
 23 [-]: GETTABLE  R0 R0 K7     ; R0 := R0[0x4c232afc]
 24 [-]: GETGLOBAL R1 K4        ; R1 := 0xae91e43b
 25 [-]: CONST     R2 1         ; R2 := 1.000000
 26 [-]: CONST     R3 0         ; R3 := 0.250000
 27 [-]: CONST     R4 0         ; R4 := 0.000000
 28 [-]: CLOSURE   R5 0         ; R5 := closure(Function #1.1)
 29 [-]: GETUPVAL  R0 U3        ; R0 := U3
 30 [-]: GETUPVAL  R0 U2        ; R0 := U2
 31 [-]: CALL      R0 6 1       ; R0(R1,R2,R3,R4,R5)
 32 [-]: RETURN    R0 1         ; return 


; Function #1.1:
;
; Name:            
; Defined at line: 54
; #Upvalues:       2
; #Parameters:     0
; Is_vararg:       0
; Max Stack Size:  8

  1 [-]: GETGLOBAL R0 K0        ; R0 := 0x89326c93
  2 [-]: SELF      R0 R0 K1     ; R1 := R0; R0 := R0[0x78298275]
  3 [-]: CALL      R0 2 2       ; R0 := R0(R1)
  4 [-]: GETGLOBAL R1 K2        ; R1 := 0x7b998233
  5 [-]: MOVE      R2 R0        ; R2 := R0
  6 [-]: CALL      R1 2 2       ; R1 := R1(R2)
  7 [-]: TEST      R1 1         ; if R1 then PC := 16
  8 [-]: JMP       16           ; PC := 16
  9 [-]: SELF      R1 R0 K3     ; R2 := R0; R1 := R0[0x0b4bcfb6]
 10 [-]: CALL      R1 2 2       ; R1 := R1(R2)
 11 [-]: SELF      R2 R1 K4     ; R3 := R1; R2 := R1[0x14c7f7dd]
 12 [-]: GETUPVAL  R4 U0        ; R4 := U0
 13 [-]: GETTABLE  R4 R4 K5     ; R4 := R4["OldSpot"]
 14 [-]: LOADK     R5 K6        ; R5 := 0.010000
 15 [-]: CALL      R2 4 1       ; R2(R3,R4,R5)
 16 [-]: GETUPVAL  R2 U1        ; R2 := U1
 17 [-]: GETTABLE  R2 R2 K7     ; R2 := R2[0x4c232afc]
 18 [-]: GETGLOBAL R3 K8        ; R3 := 0xae91e43b
 19 [-]: CONST     R4 0         ; R4 := 0.000000
 20 [-]: CONST     R5 0         ; R5 := 0.250000
 21 [-]: CONST     R6 0         ; R6 := 0.000000
 22 [-]: CLOSURE   R7 0         ; R7 := closure(Function #1.1.1)
 23 [-]: CALL      R2 6 1       ; R2(R3,R4,R5,R6,R7)
 24 [-]: RETURN    R0 1         ; return 


; Function #1.1.1:
;
; Name:            
; Defined at line: 62
; #Upvalues:       0
; #Parameters:     0
; Is_vararg:       0
; Max Stack Size:  2

  1 [-]: GETGLOBAL R0 K0        ; R0 := 0xae91e43b
  2 [-]: SELF      R0 R0 K1     ; R1 := R0; R0 := R0[0x32302b4a]
  3 [-]: CALL      R0 2 1       ; R0(R1)
  4 [-]: RETURN    R0 1         ; return 


; Function #2:
;
; Name:            
; Defined at line: 68
; #Upvalues:       1
; #Parameters:     0
; Is_vararg:       0
; Max Stack Size:  6

  1 [-]: NEWTABLE  R0 0 0       ; R0 := {}
  2 [-]: GETGLOBAL R1 K0        ; R1 := 0x33bdd652
  3 [-]: GETTABLE  R1 R1 K1     ; R1 := R1[0x23d5322f]
  4 [-]: MOVE      R2 R0        ; R2 := R0
  5 [-]: NEWTABLE  R3 0 3       ; R3 := {}
  6 [-]: SETTABLE  R3 K2 K3     ; R3["Label"] := "/Lotus/Language/Menu/Exit"
  7 [-]: GETUPVAL  R4 U0        ; R4 := U0
  8 [-]: SETTABLE  R3 K4 R4     ; R3["CallBack"] := R4
  9 [-]: SETTABLE  R3 K5 K6     ; R3["CallOut"] := "MENU_CANCEL"
 10 [-]: CALL      R1 3 1       ; R1(R2,R3)
 11 [-]: GETGLOBAL R1 K7        ; R1 := 0x7b998233
 12 [-]: GETGLOBAL R2 K8        ; R2 := _T
 13 [-]: GETTABLE  R2 R2 K9     ; R2 := R2["SetButtons"]
 14 [-]: CALL      R1 2 2       ; R1 := R1(R2)
 15 [-]: TEST      R1 1         ; if R1 then PC := 25
 16 [-]: JMP       25           ; PC := 25
 17 [-]: GETGLOBAL R1 K8        ; R1 := _T
 18 [-]: GETTABLE  R1 R1 K10    ; R1 := R1[0x1c5b546f]
 19 [-]: GETGLOBAL R2 K11       ; R2 := 0xae91e43b
 20 [-]: MOVE      R3 R0        ; R3 := R0
 21 [-]: GETGLOBAL R4 K12       ; R4 := 0xcd0165a3
 22 [-]: CONST     R5 1         ; R5 := 1.000000
 23 [-]: CALL      R4 2 0       ; R4,... := R4(R5)
 24 [-]: CALL      R1 0 1       ; R1(R2,...)
 25 [-]: RETURN    R0 1         ; return 


; Function #3:
;
; Name:            
; Defined at line: 77
; #Upvalues:       0
; #Parameters:     2
; Is_vararg:       0
; Max Stack Size:  13

  1 [-]: CONST     R2 1         ; R2 := 1.000000
  2 [-]: CONST     R3 50        ; R3 := 50.000000
  3 [-]: CONST     R4 1         ; R4 := 1.000000
  4 [-]: FORPREP   R2 21        ; R2 -= R4; PC := 21
  5 [-]: SELF      R6 R0 K1     ; R7 := R0; R6 := R0[0x7b01f73c]
  6 [-]: MOVE      R8 R5        ; R8 := R5
  7 [-]: CALL      R6 3 2       ; R6 := R6(R7,R8)
  8 [-]: CONST     R7 1         ; R7 := 1.000000
  9 [-]: LEN       R8 R6        ; R8 := # R6
 10 [-]: CONST     R9 1         ; R9 := 1.000000
 11 [-]: FORPREP   R7 20        ; R7 -= R9; PC := 20
 12 [-]: GETTABLE  R11 R6 R10   ; R11 := R6[R10]
 13 [-]: GETTABLE  R11 R11 K2   ; R11 := R11["mParentRoom"]
 14 [-]: SELF      R11 R11 K3   ; R12 := R11; R11 := R11[0xf537cfc7]
 15 [-]: CALL      R11 2 2      ; R11 := R11(R12)
 16 [-]: EQ        0 R11 R1     ; if R11 ~= R1 then PC := 20
 17 [-]: JMP       20           ; PC := 20
 18 [-]: LOADKB    R11 1 0      ; R11 := true
 19 [-]: RETURN    R11 2        ; return R11
 20 [-]: FORLOOP   R7 12        ; R7 += R9; if R7 <= R8 then begin PC := 12; R10 := R7 end
 21 [-]: FORLOOP   R2 5         ; R2 += R4; if R2 <= R3 then begin PC := 5; R5 := R2 end
 22 [-]: LOADKB    R11 0 0      ; R11 := false
 23 [-]: RETURN    R11 2        ; return R11
 24 [-]: RETURN    R0 1         ; return 


; Function #4:
;
; Name:            
; Defined at line: 90
; #Upvalues:       3
; #Parameters:     2
; Is_vararg:       0
; Max Stack Size:  33

  1 [-]: GETGLOBAL R2 K0        ; R2 := _T
  2 [-]: GETTABLE  R2 R2 K1     ; R2 := R2["DojoMgr"]
  3 [-]: GETTABLE  R2 R2 K2     ; R2 := R2["mDojo"]
  4 [-]: SELF      R2 R2 K3     ; R3 := R2; R2 := R2[0x7365d8b2]
  5 [-]: CALL      R2 2 2       ; R2 := R2(R3)
  6 [-]: SELF      R3 R1 K3     ; R4 := R1; R3 := R1[0x7365d8b2]
  7 [-]: CALL      R3 2 2       ; R3 := R3(R4)
  8 [-]: SUB       R2 R2 R3     ; R2 := R2 - R3
  9 [-]: LT        0 R2 K4      ; if R2 >= 0.000000 then PC := 13
 10 [-]: JMP       13           ; PC := 13
 11 [-]: CONST     R2 4         ; R2 := 4.000000
 12 [-]: RETURN    R2 2         ; return R2
 13 [-]: GETGLOBAL R2 K0        ; R2 := _T
 14 [-]: GETTABLE  R2 R2 K1     ; R2 := R2["DojoMgr"]
 15 [-]: GETTABLE  R2 R2 K2     ; R2 := R2["mDojo"]
 16 [-]: SELF      R2 R2 K6     ; R3 := R2; R2 := R2[0xa5d48ec6]
 17 [-]: CALL      R2 2 2       ; R2 := R2(R3)
 18 [-]: SELF      R3 R1 K6     ; R4 := R1; R3 := R1[0xa5d48ec6]
 19 [-]: CALL      R3 2 2       ; R3 := R3(R4)
 20 [-]: SUB       R2 R2 R3     ; R2 := R2 - R3
 21 [-]: LT        0 R2 K4      ; if R2 >= 0.000000 then PC := 25
 22 [-]: JMP       25           ; PC := 25
 23 [-]: CONST     R2 5         ; R2 := 5.000000
 24 [-]: RETURN    R2 2         ; return R2
 25 [-]: GETGLOBAL R2 K0        ; R2 := _T
 26 [-]: GETTABLE  R2 R2 K1     ; R2 := R2["DojoMgr"]
 27 [-]: GETTABLE  R2 R2 K2     ; R2 := R2["mDojo"]
 28 [-]: SELF      R2 R2 K7     ; R3 := R2; R2 := R2[0x43c3090e]
 29 [-]: CALL      R2 2 2       ; R2 := R2(R3)
 30 [-]: LEN       R3 R2        ; R3 := # R2
 31 [-]: EQ        0 R3 K8      ; if R3 ~= 1.000000 then PC := 35
 32 [-]: JMP       35           ; PC := 35
 33 [-]: CONST     R3 15        ; R3 := 15.000000
 34 [-]: RETURN    R3 2         ; return R3
 35 [-]: GETGLOBAL R3 K0        ; R3 := _T
 36 [-]: GETTABLE  R3 R3 K1     ; R3 := R3["DojoMgr"]
 37 [-]: GETTABLE  R3 R3 K2     ; R3 := R3["mDojo"]
 38 [-]: SELF      R3 R3 K9     ; R4 := R3; R3 := R3[0xb5c06923]
 39 [-]: GETUPVAL  R5 U0        ; R5 := U0
 40 [-]: CALL      R3 3 2       ; R3 := R3(R4,R5)
 41 [-]: TEST      R3 0         ; if not R3 then PC := 45
 42 [-]: JMP       45           ; PC := 45
 43 [-]: CONST     R3 13        ; R3 := 13.000000
 44 [-]: RETURN    R3 2         ; return R3
 45 [-]: GETGLOBAL R3 K10       ; R3 := 0x76ea806b
 46 [-]: SELF      R3 R3 K11    ; R4 := R3; R3 := R3[0x3f3ae64c]
 47 [-]: CONST     R5 0         ; R5 := 0.000000
 48 [-]: CALL      R3 3 2       ; R3 := R3(R4,R5)
 49 [-]: SELF      R3 R3 K12    ; R4 := R3; R3 := R3[0x80563238]
 50 [-]: CALL      R3 2 2       ; R3 := R3(R4)
 51 [-]: GETUPVAL  R4 U1        ; R4 := U1
 52 [-]: SELF      R5 R3 K13    ; R6 := R3; R5 := R3[0xf39284cf]
 53 [-]: CALL      R5 2 2       ; R5 := R5(R6)
 54 [-]: GETTABLE  R6 R0 K14    ; R6 := R0["id"]
 55 [-]: CALL      R4 3 2       ; R4 := R4(R5,R6)
 56 [-]: TEST      R4 1         ; if R4 then PC := 69
 57 [-]: JMP       69           ; PC := 69
 58 [-]: SELF      R4 R3 K15    ; R5 := R3; R4 := R3[0xf9d7598e]
 59 [-]: CALL      R4 2 2       ; R4 := R4(R5)
 60 [-]: EQ        1 R4 K16     ; if R4 == "" then PC := 71
 61 [-]: JMP       71           ; PC := 71
 62 [-]: GETUPVAL  R4 U1        ; R4 := U1
 63 [-]: SELF      R5 R3 K17    ; R6 := R3; R5 := R3[0x8233dda5]
 64 [-]: CALL      R5 2 2       ; R5 := R5(R6)
 65 [-]: GETTABLE  R6 R0 K14    ; R6 := R0["id"]
 66 [-]: CALL      R4 3 2       ; R4 := R4(R5,R6)
 67 [-]: TEST      R4 0         ; if not R4 then PC := 71
 68 [-]: JMP       71           ; PC := 71
 69 [-]: CONST     R4 8         ; R4 := 8.000000
 70 [-]: RETURN    R4 2         ; return R4
 71 [-]: NEWTABLE  R4 0 0       ; R4 := {}
 72 [-]: NEWTABLE  R5 0 0       ; R5 := {}
 73 [-]: CONST     R6 1         ; R6 := 1.000000
 74 [-]: LEN       R7 R2        ; R7 := # R2
 75 [-]: CONST     R8 1         ; R8 := 1.000000
 76 [-]: FORPREP   R6 111       ; R6 -= R8; PC := 111
 77 [-]: GETTABLE  R10 R2 R9    ; R10 := R2[R9]
 78 [-]: SELF      R10 R10 K18  ; R11 := R10; R10 := R10[0x3f724bc7]
 79 [-]: CALL      R10 2 2      ; R10 := R10(R11)
 80 [-]: TEST      R10 0        ; if not R10 then PC := 97
 81 [-]: JMP       97           ; PC := 97
 82 [-]: GETTABLE  R10 R2 R9    ; R10 := R2[R9]
 83 [-]: GETTABLE  R10 R10 K19  ; R10 := R10["prefab"]
 84 [-]: SELF      R10 R10 K20  ; R11 := R10; R10 := R10[0xed4e0128]
 85 [-]: CALL      R10 2 2      ; R10 := R10(R11)
 86 [-]: GETGLOBAL R11 K21      ; R11 := 0x7b998233
 87 [-]: GETTABLE  R12 R4 R10   ; R12 := R4[R10]
 88 [-]: CALL      R11 2 2      ; R11 := R11(R12)
 89 [-]: TEST      R11 0        ; if not R11 then PC := 93
 90 [-]: JMP       93           ; PC := 93
 91 [-]: SETTABLE  R4 R10 K8    ; R4[R10] := 1.000000
 92 [-]: JMP       111          ; PC := 111
 93 [-]: GETTABLE  R11 R4 R10   ; R11 := R4[R10]
 94 [-]: ADD       R11 R11 K8   ; R11 := R11 + 1.000000
 95 [-]: SETTABLE  R4 R10 R11   ; R4[R10] := R11
 96 [-]: JMP       111          ; PC := 111
 97 [-]: GETTABLE  R11 R2 R9    ; R11 := R2[R9]
 98 [-]: GETTABLE  R11 R11 K19  ; R11 := R11["prefab"]
 99 [-]: SELF      R11 R11 K20  ; R12 := R11; R11 := R11[0xed4e0128]
100 [-]: CALL      R11 2 2      ; R11 := R11(R12)
101 [-]: GETGLOBAL R12 K21      ; R12 := 0x7b998233
102 [-]: GETTABLE  R13 R5 R11   ; R13 := R5[R11]
103 [-]: CALL      R12 2 2      ; R12 := R12(R13)
104 [-]: TEST      R12 0        ; if not R12 then PC := 108
105 [-]: JMP       108          ; PC := 108
106 [-]: SETTABLE  R5 R11 K8    ; R5[R11] := 1.000000
107 [-]: JMP       111          ; PC := 111
108 [-]: GETTABLE  R12 R5 R11   ; R12 := R5[R11]
109 [-]: ADD       R12 R12 K8   ; R12 := R12 + 1.000000
110 [-]: SETTABLE  R5 R11 R12   ; R5[R11] := R12
111 [-]: FORLOOP   R6 77        ; R6 += R8; if R6 <= R7 then begin PC := 77; R9 := R6 end
112 [-]: SELF      R12 R1 K22   ; R13 := R1; R12 := R1[0x5dafcb6d]
113 [-]: CALL      R12 2 2      ; R12 := R12(R13)
114 [-]: GETGLOBAL R13 K23      ; R13 := 0x59462acb
115 [-]: SELF      R13 R13 K24  ; R14 := R13; R13 := R13[0xb55e96a3]
116 [-]: GETUPVAL  R15 U2       ; R15 := U2
117 [-]: GETTABLE  R15 R15 K19  ; R15 := R15["prefab"]
118 [-]: CALL      R13 3 2      ; R13 := R13(R14,R15)
119 [-]: CONST     R14 1        ; R14 := 1.000000
120 [-]: LEN       R15 R13      ; R15 := # R13
121 [-]: CONST     R16 1        ; R16 := 1.000000
122 [-]: FORPREP   R14 192      ; R14 -= R16; PC := 192
123 [-]: GETGLOBAL R18 K21      ; R18 := 0x7b998233
124 [-]: GETTABLE  R19 R13 R17  ; R19 := R13[R17]
125 [-]: SELF      R19 R19 K20  ; R20 := R19; R19 := R19[0xed4e0128]
126 [-]: CALL      R19 2 2      ; R19 := R19(R20)
127 [-]: GETTABLE  R19 R4 R19   ; R19 := R4[R19]
128 [-]: CALL      R18 2 2      ; R18 := R18(R19)
129 [-]: TEST      R18 0        ; if not R18 then PC := 139
130 [-]: JMP       139          ; PC := 139
131 [-]: GETGLOBAL R18 K21      ; R18 := 0x7b998233
132 [-]: GETTABLE  R19 R13 R17  ; R19 := R13[R17]
133 [-]: SELF      R19 R19 K20  ; R20 := R19; R19 := R19[0xed4e0128]
134 [-]: CALL      R19 2 2      ; R19 := R19(R20)
135 [-]: GETTABLE  R19 R5 R19   ; R19 := R5[R19]
136 [-]: CALL      R18 2 2      ; R18 := R18(R19)
137 [-]: TEST      R18 1        ; if R18 then PC := 192
138 [-]: JMP       192          ; PC := 192
139 [-]: GETGLOBAL R18 K23      ; R18 := 0x59462acb
140 [-]: SELF      R18 R18 K25  ; R19 := R18; R18 := R18[0x56595420]
141 [-]: GETTABLE  R20 R13 R17  ; R20 := R13[R17]
142 [-]: CALL      R18 3 2      ; R18 := R18(R19,R20)
143 [-]: SELF      R19 R18 K26  ; R20 := R18; R19 := R18[0x74de725d]
144 [-]: CALL      R19 2 2      ; R19 := R19(R20)
145 [-]: LEN       R20 R19      ; R20 := # R19
146 [-]: LT        0 K4 R20     ; if 0.000000 >= R20 then PC := 192
147 [-]: JMP       192          ; PC := 192
148 [-]: CONST     R20 1        ; R20 := 1.000000
149 [-]: LEN       R21 R19      ; R21 := # R19
150 [-]: CONST     R22 1        ; R22 := 1.000000
151 [-]: FORPREP   R20 191      ; R20 -= R22; PC := 191
152 [-]: GETTABLE  R24 R19 R23  ; R24 := R19[R23]
153 [-]: LOADKB    R25 0 0      ; R25 := false
154 [-]: CONST     R26 1        ; R26 := 1.000000
155 [-]: LEN       R27 R24      ; R27 := # R24
156 [-]: CONST     R28 1        ; R28 := 1.000000
157 [-]: FORPREP   R26 186      ; R26 -= R28; PC := 186
158 [-]: GETGLOBAL R30 K21      ; R30 := 0x7b998233
159 [-]: GETTABLE  R31 R24 R29  ; R31 := R24[R29]
160 [-]: SELF      R31 R31 K20  ; R32 := R31; R31 := R31[0xed4e0128]
161 [-]: CALL      R31 2 2      ; R31 := R31(R32)
162 [-]: GETTABLE  R31 R4 R31   ; R31 := R4[R31]
163 [-]: CALL      R30 2 2      ; R30 := R30(R31)
164 [-]: TEST      R30 1        ; if R30 then PC := 186
165 [-]: JMP       186          ; PC := 186
166 [-]: GETTABLE  R30 R24 R29  ; R30 := R24[R29]
167 [-]: EQ        0 R30 R12    ; if R30 ~= R12 then PC := 178
168 [-]: JMP       178          ; PC := 178
169 [-]: GETTABLE  R30 R24 R29  ; R30 := R24[R29]
170 [-]: SELF      R30 R30 K20  ; R31 := R30; R30 := R30[0xed4e0128]
171 [-]: CALL      R30 2 2      ; R30 := R30(R31)
172 [-]: GETTABLE  R30 R4 R30   ; R30 := R4[R30]
173 [-]: LE        0 K27 R30    ; if 2.000000 > R30 then PC := 186
174 [-]: JMP       186          ; PC := 186
175 [-]: LOADKB    R25 1 0      ; R25 := true
176 [-]: JMP       187          ; PC := 187
177 [-]: JMP       186          ; PC := 186
178 [-]: GETTABLE  R30 R24 R29  ; R30 := R24[R29]
179 [-]: SELF      R30 R30 K20  ; R31 := R30; R30 := R30[0xed4e0128]
180 [-]: CALL      R30 2 2      ; R30 := R30(R31)
181 [-]: GETTABLE  R30 R4 R30   ; R30 := R4[R30]
182 [-]: LE        0 K8 R30     ; if 1.000000 > R30 then PC := 186
183 [-]: JMP       186          ; PC := 186
184 [-]: LOADKB    R25 1 0      ; R25 := true
185 [-]: JMP       187          ; PC := 187
186 [-]: FORLOOP   R26 158      ; R26 += R28; if R26 <= R27 then begin PC := 158; R29 := R26 end
187 [-]: TEST      R25 1        ; if R25 then PC := 191
188 [-]: JMP       191          ; PC := 191
189 [-]: CONST     R30 6        ; R30 := 6.000000
190 [-]: RETURN    R30 2        ; return R30
191 [-]: FORLOOP   R20 152      ; R20 += R22; if R20 <= R21 then begin PC := 152; R23 := R20 end
192 [-]: FORLOOP   R14 123      ; R14 += R16; if R14 <= R15 then begin PC := 123; R17 := R14 end
193 [-]: CONST     R30 0        ; R30 := 0.000000
194 [-]: RETURN    R30 2        ; return R30
195 [-]: RETURN    R0 1         ; return 


; Function #5:
;
; Name:            
; Defined at line: 177
; #Upvalues:       2
; #Parameters:     0
; Is_vararg:       0
; Max Stack Size:  4

  1 [-]: GETUPVAL  R0 U0        ; R0 := U0
  2 [-]: SELF      R0 R0 K0     ; R1 := R0; R0 := R0[0x4f14d68d]
  3 [-]: CALL      R0 2 2       ; R0 := R0(R1)
  4 [-]: GETUPVAL  R1 U1        ; R1 := U1
  5 [-]: TEST      R1 0         ; if not R1 then PC := 12
  6 [-]: JMP       12           ; PC := 12
  7 [-]: GETGLOBAL R1 K1        ; R1 := 0x09423272
  8 [-]: MOVE      R2 R0        ; R2 := R0
  9 [-]: CONST     R3 0         ; R3 := 0.000000
 10 [-]: CALL      R1 3 2       ; R1 := R1(R2,R3)
 11 [-]: MOVE      R0 R1        ; R0 := R1
 12 [-]: GETGLOBAL R1 K3        ; R1 := cjson
 13 [-]: GETTABLE  R1 R1 K4     ; R1 := R1[0x7ab914d8]
 14 [-]: MOVE      R2 R0        ; R2 := R0
 15 [-]: CALL      R1 2 2       ; R1 := R1(R2)
 16 [-]: MOVE      R0 R1        ; R0 := R1
 17 [-]: GETGLOBAL R1 K5        ; R1 := 0x7b998233
 18 [-]: MOVE      R2 R0        ; R2 := R0
 19 [-]: CALL      R1 2 2       ; R1 := R1(R2)
 20 [-]: TEST      R1 1         ; if R1 then PC := 33
 21 [-]: JMP       33           ; PC := 33
 22 [-]: GETTABLE  R1 R0 K6     ; R1 := R0["courseMode"]
 23 [-]: EQ        1 R1 K7      ; if R1 == nil then PC := 28
 24 [-]: JMP       28           ; PC := 28
 25 [-]: GETTABLE  R1 R0 K6     ; R1 := R0["courseMode"]
 26 [-]: EQ        0 R1 K9      ; if R1 ~= 0.000000 then PC := 33
 27 [-]: JMP       33           ; PC := 33
 28 [-]: GETGLOBAL R1 K10       ; R1 := 0x603636ad
 29 [-]: LOADK     R2 K11       ; R2 := "/Lotus/Language/Dojo/CustomObstacleCourseOperatorPlayNotAllowed"
 30 [-]: NEWTABLE  R3 0 0       ; R3 := {}
 31 [-]: TAILCALL  R1 3 0       ; R1,... := R1(R2,R3)
 32 [-]: RETURN    R1 0         ; return R1,...
 33 [-]: GETGLOBAL R1 K10       ; R1 := 0x603636ad
 34 [-]: LOADK     R2 K12       ; R2 := "/Lotus/Language/Dojo/CustomObstacleCourseOperatorPlayAllowed"
 35 [-]: NEWTABLE  R3 0 0       ; R3 := {}
 36 [-]: TAILCALL  R1 3 0       ; R1,... := R1(R2,R3)
 37 [-]: RETURN    R1 0         ; return R1,...
 38 [-]: RETURN    R0 1         ; return 


; Function #6:
;
; Name:            
; Defined at line: 192
; #Upvalues:       2
; #Parameters:     0
; Is_vararg:       0
; Max Stack Size:  11

  1 [-]: GETGLOBAL R0 K0        ; R0 := 0xae91e43b
  2 [-]: SELF      R0 R0 K1     ; R1 := R0; R0 := R0[0x91a24e4b]
  3 [-]: LOADK     R2 K2        ; R2 := "Options.EditMessage"
  4 [-]: CONST     R3 1         ; R3 := 1.000000
  5 [-]: CALL      R0 4 2       ; R0 := R0(R1,R2,R3)
  6 [-]: CONST     R1 0         ; R1 := 0.000000
  7 [-]: GETGLOBAL R2 K0        ; R2 := 0xae91e43b
  8 [-]: SELF      R2 R2 K3     ; R3 := R2; R2 := R2[0x5b0290d2]
  9 [-]: LOADK     R4 K2        ; R4 := "Options.EditMessage"
 10 [-]: CONST     R5 11        ; R5 := 11.000000
 11 [-]: CALL      R2 4 2       ; R2 := R2(R3,R4,R5)
 12 [-]: TEST      R2 0         ; if not R2 then PC := 21
 13 [-]: JMP       21           ; PC := 21
 14 [-]: GETGLOBAL R3 K0        ; R3 := 0xae91e43b
 15 [-]: SELF      R3 R3 K1     ; R4 := R3; R3 := R3[0x91a24e4b]
 16 [-]: LOADK     R5 K4        ; R5 := "Options.EditMessage.Bg"
 17 [-]: CONST     R6 13        ; R6 := 13.000000
 18 [-]: CALL      R3 4 2       ; R3 := R3(R4,R5,R6)
 19 [-]: ADD       R4 R1 R3     ; R4 := R1 + R3
 20 [-]: ADD       R1 R4 K5     ; R1 := R4 + 30.000000
 21 [-]: GETGLOBAL R4 K0        ; R4 := 0xae91e43b
 22 [-]: SELF      R4 R4 K6     ; R5 := R4; R4 := R4[0x67bc869f]
 23 [-]: LOADK     R6 K7        ; R6 := "Options.RoomName"
 24 [-]: CONST     R7 1         ; R7 := 1.000000
 25 [-]: ADD       R8 R0 R1     ; R8 := R0 + R1
 26 [-]: CALL      R4 5 1       ; R4(R5,R6,R7,R8)
 27 [-]: GETGLOBAL R4 K0        ; R4 := 0xae91e43b
 28 [-]: SELF      R4 R4 K3     ; R5 := R4; R4 := R4[0x5b0290d2]
 29 [-]: LOADK     R6 K7        ; R6 := "Options.RoomName"
 30 [-]: CONST     R7 11        ; R7 := 11.000000
 31 [-]: CALL      R4 4 2       ; R4 := R4(R5,R6,R7)
 32 [-]: TEST      R4 0         ; if not R4 then PC := 41
 33 [-]: JMP       41           ; PC := 41
 34 [-]: GETGLOBAL R5 K0        ; R5 := 0xae91e43b
 35 [-]: SELF      R5 R5 K1     ; R6 := R5; R5 := R5[0x91a24e4b]
 36 [-]: LOADK     R7 K8        ; R7 := "Options.RoomName.Bg"
 37 [-]: CONST     R8 13        ; R8 := 13.000000
 38 [-]: CALL      R5 4 2       ; R5 := R5(R6,R7,R8)
 39 [-]: ADD       R6 R1 R5     ; R6 := R1 + R5
 40 [-]: ADD       R1 R6 K5     ; R1 := R6 + 30.000000
 41 [-]: GETGLOBAL R6 K0        ; R6 := 0xae91e43b
 42 [-]: SELF      R6 R6 K6     ; R7 := R6; R6 := R6[0x67bc869f]
 43 [-]: LOADK     R8 K9        ; R8 := "Options.ButtonList"
 44 [-]: CONST     R9 1         ; R9 := 1.000000
 45 [-]: ADD       R10 R0 R1    ; R10 := R0 + R1
 46 [-]: CALL      R6 5 1       ; R6(R7,R8,R9,R10)
 47 [-]: GETUPVAL  R6 U0        ; R6 := U0
 48 [-]: SELF      R6 R6 K10    ; R7 := R6; R6 := R6[0x5fbddc1a]
 49 [-]: CALL      R6 2 2       ; R6 := R6(R7)
 50 [-]: GETUPVAL  R7 U0        ; R7 := U0
 51 [-]: GETTABLE  R7 R7 K11    ; R7 := R7["mForcedVerticalSeparation"]
 52 [-]: MUL       R6 R6 R7     ; R6 := R6 * R7
 53 [-]: ADD       R1 R1 R6     ; R1 := R1 + R6
 54 [-]: GETGLOBAL R6 K0        ; R6 := 0xae91e43b
 55 [-]: SELF      R6 R6 K6     ; R7 := R6; R6 := R6[0x67bc869f]
 56 [-]: LOADK     R8 K12       ; R8 := "Options.DestroyTimer"
 57 [-]: CONST     R9 1         ; R9 := 1.000000
 58 [-]: ADD       R10 R0 R1    ; R10 := R0 + R1
 59 [-]: ADD       R10 R10 K13  ; R10 := R10 + 10.000000
 60 [-]: CALL      R6 5 1       ; R6(R7,R8,R9,R10)
 61 [-]: GETUPVAL  R6 U1        ; R6 := U1
 62 [-]: GETTABLE  R6 R6 K14    ; R6 := R6["Visible"]
 63 [-]: TEST      R6 0         ; if not R6 then PC := 66
 64 [-]: JMP       66           ; PC := 66
 65 [-]: ADD       R1 R1 K15    ; R1 := R1 + 70.000000
 66 [-]: GETGLOBAL R6 K0        ; R6 := 0xae91e43b
 67 [-]: SELF      R6 R6 K6     ; R7 := R6; R6 := R6[0x67bc869f]
 68 [-]: LOADK     R8 K16       ; R8 := "Options.Hint"
 69 [-]: CONST     R9 1         ; R9 := 1.000000
 70 [-]: ADD       R10 R0 R1    ; R10 := R0 + R1
 71 [-]: ADD       R10 R10 K13  ; R10 := R10 + 10.000000
 72 [-]: CALL      R6 5 1       ; R6(R7,R8,R9,R10)
 73 [-]: GETGLOBAL R6 K0        ; R6 := 0xae91e43b
 74 [-]: SELF      R6 R6 K6     ; R7 := R6; R6 := R6[0x67bc869f]
 75 [-]: LOADK     R8 K17       ; R8 := "Options.Destroy"
 76 [-]: CONST     R9 1         ; R9 := 1.000000
 77 [-]: ADD       R10 R0 R1    ; R10 := R0 + R1
 78 [-]: ADD       R10 R10 K13  ; R10 := R10 + 10.000000
 79 [-]: CALL      R6 5 1       ; R6(R7,R8,R9,R10)
 80 [-]: GETGLOBAL R6 K0        ; R6 := 0xae91e43b
 81 [-]: SELF      R6 R6 K6     ; R7 := R6; R6 := R6[0x67bc869f]
 82 [-]: LOADK     R8 K18       ; R8 := "Options.CornerBg"
 83 [-]: CONST     R9 13        ; R9 := 13.000000
 84 [-]: ADD       R10 R1 K19   ; R10 := R1 + 500.000000
 85 [-]: CALL      R6 5 1       ; R6(R7,R8,R9,R10)
 86 [-]: RETURN    R0 1         ; return 


; Function #7:
;
; Name:            
; Defined at line: 222
; #Upvalues:       20
; #Parameters:     1
; Is_vararg:       0
; Max Stack Size:  29

  1 [-]: SETUPVAL  R0 U0        ; U82 := R0
  2 [-]: GETUPVAL  R1 U1        ; R1 := U1
  3 [-]: TEST      R1 1         ; if R1 then PC := 8
  4 [-]: JMP       8            ; PC := 8
  5 [-]: GETUPVAL  R1 U2        ; R1 := U2
  6 [-]: TEST      R1 0         ; if not R1 then PC := 9
  7 [-]: JMP       9            ; PC := 9
  8 [-]: RETURN    R0 1         ; return 
  9 [-]: GETGLOBAL R1 K0        ; R1 := 0x25d99d89
 10 [-]: GETUPVAL  R2 U0        ; R2 := U0
 11 [-]: SELF      R2 R2 K1     ; R3 := R2; R2 := R2[0x56c01834]
 12 [-]: CALL      R2 2 2       ; R2 := R2(R3)
 13 [-]: TEST      R2 0         ; if not R2 then PC := 441
 14 [-]: JMP       441          ; PC := 441
 15 [-]: GETGLOBAL R2 K2        ; R2 := 0x7b998233
 16 [-]: MOVE      R3 R1        ; R3 := R1
 17 [-]: CALL      R2 2 2       ; R2 := R2(R3)
 18 [-]: TEST      R2 1         ; if R2 then PC := 441
 19 [-]: JMP       441          ; PC := 441
 20 [-]: GETGLOBAL R2 K2        ; R2 := 0x7b998233
 21 [-]: GETGLOBAL R3 K3        ; R3 := 0x59462acb
 22 [-]: CALL      R2 2 2       ; R2 := R2(R3)
 23 [-]: TEST      R2 1         ; if R2 then PC := 441
 24 [-]: JMP       441          ; PC := 441
 25 [-]: GETGLOBAL R2 K3        ; R2 := 0x59462acb
 26 [-]: SELF      R2 R2 K4     ; R3 := R2; R2 := R2[0x56595420]
 27 [-]: GETUPVAL  R4 U0        ; R4 := U0
 28 [-]: GETTABLE  R4 R4 K5     ; R4 := R4["prefab"]
 29 [-]: CALL      R2 3 2       ; R2 := R2(R3,R4)
 30 [-]: GETGLOBAL R3 K2        ; R3 := 0x7b998233
 31 [-]: MOVE      R4 R2        ; R4 := R2
 32 [-]: CALL      R3 2 2       ; R3 := R3(R4)
 33 [-]: TEST      R3 0         ; if not R3 then PC := 38
 34 [-]: JMP       38           ; PC := 38
 35 [-]: GETUPVAL  R3 U3        ; R3 := U3
 36 [-]: CALL      R3 1 1       ; R3()
 37 [-]: RETURN    R0 1         ; return 
 38 [-]: GETGLOBAL R3 K2        ; R3 := 0x7b998233
 39 [-]: GETGLOBAL R4 K6        ; R4 := _T
 40 [-]: GETTABLE  R4 R4 K7     ; R4 := R4["SetSquadOverlayTitle"]
 41 [-]: CALL      R3 2 2       ; R3 := R3(R4)
 42 [-]: TEST      R3 1         ; if R3 then PC := 64
 43 [-]: JMP       64           ; PC := 64
 44 [-]: GETGLOBAL R3 K8        ; R3 := 0xae91e43b
 45 [-]: SELF      R3 R3 K9     ; R4 := R3; R3 := R3[0x42b04007]
 46 [-]: LOADK     R5 K10       ; R5 := "/Lotus/Language/Dojo/UpgradesAndDestructionTitle"
 47 [-]: LOADKB    R6 0 0       ; R6 := false
 48 [-]: CALL      R3 4 2       ; R3 := R3(R4,R5,R6)
 49 [-]: GETGLOBAL R4 K6        ; R4 := _T
 50 [-]: GETTABLE  R4 R4 K11    ; R4 := R4[0xdf29a9d6]
 51 [-]: MOVE      R5 R3        ; R5 := R3
 52 [-]: GETGLOBAL R6 K8        ; R6 := 0xae91e43b
 53 [-]: SELF      R6 R6 K9     ; R7 := R6; R6 := R6[0x42b04007]
 54 [-]: SELF      R8 R2 K12    ; R9 := R2; R8 := R2[0xd3a9d01f]
 55 [-]: CALL      R8 2 2       ; R8 := R8(R9)
 56 [-]: SELF      R8 R8 K13    ; R9 := R8; R8 := R8[0x6d604ba7]
 57 [-]: CALL      R8 2 2       ; R8 := R8(R9)
 58 [-]: LOADKB    R9 0 0       ; R9 := false
 59 [-]: CALL      R6 4 2       ; R6 := R6(R7,R8,R9)
 60 [-]: GETUPVAL  R7 U4        ; R7 := U4
 61 [-]: CALL      R4 4 1       ; R4(R5,R6,R7)
 62 [-]: LOADKB    R4 1 0       ; R4 := true
 63 [-]: SETUPVAL  R4 U4        ; U82 := R4
 64 [-]: GETUPVAL  R4 U0        ; R4 := U0
 65 [-]: SELF      R4 R4 K14    ; R5 := R4; R4 := R4[0xe834b831]
 66 [-]: CALL      R4 2 2       ; R4 := R4(R5)
 67 [-]: GETUPVAL  R5 U0        ; R5 := U0
 68 [-]: GETTABLE  R5 R5 K15    ; R5 := R5["name"]
 69 [-]: GETUPVAL  R6 U5        ; R6 := U5
 70 [-]: TEST      R6 0         ; if not R6 then PC := 82
 71 [-]: JMP       82           ; PC := 82
 72 [-]: GETGLOBAL R6 K16       ; R6 := 0x09423272
 73 [-]: MOVE      R7 R4        ; R7 := R4
 74 [-]: CONST     R8 0         ; R8 := 0.000000
 75 [-]: CALL      R6 3 2       ; R6 := R6(R7,R8)
 76 [-]: MOVE      R4 R6        ; R4 := R6
 77 [-]: GETGLOBAL R6 K16       ; R6 := 0x09423272
 78 [-]: MOVE      R7 R5        ; R7 := R5
 79 [-]: CONST     R8 0         ; R8 := 0.000000
 80 [-]: CALL      R6 3 2       ; R6 := R6(R7,R8)
 81 [-]: MOVE      R5 R6        ; R5 := R6
 82 [-]: GETUPVAL  R6 U6        ; R6 := U6
 83 [-]: SELF      R6 R6 K18    ; R7 := R6; R6 := R6[0x7c09c373]
 84 [-]: LOADKB    R8 1 0       ; R8 := true
 85 [-]: LOADKB    R9 1 0       ; R9 := true
 86 [-]: CALL      R6 4 1       ; R6(R7,R8,R9)
 87 [-]: GETGLOBAL R6 K6        ; R6 := _T
 88 [-]: GETTABLE  R6 R6 K19    ; R6 := R6["gPreviewMode"]
 89 [-]: EQ        0 R6 K20     ; if R6 ~= nil then PC := 106
 90 [-]: JMP       106          ; PC := 106
 91 [-]: GETUPVAL  R6 U6        ; R6 := U6
 92 [-]: SELF      R6 R6 K21    ; R7 := R6; R6 := R6[0xbad4316f]
 93 [-]: NEWTABLE  R8 0 2       ; R8 := {}
 94 [-]: SETTABLE  R8 K22 K23   ; R8["Label"] := "/Lotus/Language/Dojo/DecorationMode"
 95 [-]: SETTABLE  R8 K24 K25   ; R8["Callback"] := "EnterDecorationMode"
 96 [-]: LOADKB    R9 1 0       ; R9 := true
 97 [-]: CALL      R6 4 1       ; R6(R7,R8,R9)
 98 [-]: GETUPVAL  R6 U6        ; R6 := U6
 99 [-]: SELF      R6 R6 K21    ; R7 := R6; R6 := R6[0xbad4316f]
100 [-]: NEWTABLE  R8 0 2       ; R8 := {}
101 [-]: SETTABLE  R8 K22 K26   ; R8["Label"] := "/Lotus/Language/Dojo/PreviewDecorations"
102 [-]: SETTABLE  R8 K24 K27   ; R8["Callback"] := "EnterPreviewMode"
103 [-]: LOADKB    R9 1 0       ; R9 := true
104 [-]: CALL      R6 4 1       ; R6(R7,R8,R9)
105 [-]: JMP       113          ; PC := 113
106 [-]: GETUPVAL  R6 U6        ; R6 := U6
107 [-]: SELF      R6 R6 K21    ; R7 := R6; R6 := R6[0xbad4316f]
108 [-]: NEWTABLE  R8 0 2       ; R8 := {}
109 [-]: SETTABLE  R8 K22 K28   ; R8["Label"] := "/Lotus/Language/Dojo/CancelPreviewDecorations"
110 [-]: SETTABLE  R8 K24 K29   ; R8["Callback"] := "ExitPreviewMode"
111 [-]: LOADKB    R9 1 0       ; R9 := true
112 [-]: CALL      R6 4 1       ; R6(R7,R8,R9)
113 [-]: GETUPVAL  R6 U8        ; R6 := U8
114 [-]: GETTABLE  R6 R6 K30    ; R6 := R6[0x334af2b4]
115 [-]: LOADKB    R7 0 0       ; R7 := false
116 [-]: CALL      R6 2 2       ; R6 := R6(R7)
117 [-]: SETUPVAL  R6 U7        ; U82 := R7
118 [-]: GETGLOBAL R6 K8        ; R6 := 0xae91e43b
119 [-]: SELF      R6 R6 K31    ; R7 := R6; R6 := R6[0xaade900e]
120 [-]: LOADK     R8 K32       ; R8 := "Options.Hint"
121 [-]: CONST     R9 11        ; R9 := 11.000000
122 [-]: GETUPVAL  R10 U7       ; R10 := U7
123 [-]: NOT       R10 R10      ; R10 :=  R10
124 [-]: CALL      R6 5 1       ; R6(R7,R8,R9,R10)
125 [-]: GETUPVAL  R6 U7        ; R6 := U7
126 [-]: TEST      R6 0         ; if not R6 then PC := 433
127 [-]: JMP       433          ; PC := 433
128 [-]: GETUPVAL  R6 U9        ; R6 := U9
129 [-]: SETTABLE  R6 K33 R4    ; R6["InitialMessage"] := R4
130 [-]: GETGLOBAL R6 K8        ; R6 := 0xae91e43b
131 [-]: SELF      R6 R6 K34    ; R7 := R6; R6 := R6[0x5f56eeab]
132 [-]: LOADK     R8 K35       ; R8 := "Options.EditMessage.Message"
133 [-]: CONST     R9 29        ; R9 := 29.000000
134 [-]: MOVE      R10 R4       ; R10 := R4
135 [-]: CALL      R6 5 1       ; R6(R7,R8,R9,R10)
136 [-]: GETUPVAL  R6 U10       ; R6 := U10
137 [-]: SETTABLE  R6 K36 R5    ; R6["InitialName"] := R5
138 [-]: GETGLOBAL R6 K8        ; R6 := 0xae91e43b
139 [-]: SELF      R6 R6 K34    ; R7 := R6; R6 := R6[0x5f56eeab]
140 [-]: LOADK     R8 K37       ; R8 := "Options.RoomName.Message"
141 [-]: CONST     R9 29        ; R9 := 29.000000
142 [-]: MOVE      R10 R5       ; R10 := R5
143 [-]: CALL      R6 5 1       ; R6(R7,R8,R9,R10)
144 [-]: GETGLOBAL R6 K38       ; R6 := 0x34291f5c
145 [-]: GETTABLE  R6 R6 K39    ; R6 := R6[0x9ad21ae9]
146 [-]: CALL      R6 1 2       ; R6 := R6()
147 [-]: TEST      R6 0         ; if not R6 then PC := 155
148 [-]: JMP       155          ; PC := 155
149 [-]: GETUPVAL  R6 U11       ; R6 := U11
150 [-]: GETTABLE  R6 R6 K40    ; R6 := R6[0x23a862e6]
151 [-]: CALL      R6 1 2       ; R6 := R6()
152 [-]: NOT       R6 R6        ; R6 :=  R6
153 [-]: JMP       156          ; PC := 156
154 [-]: LOADKB    R6 0 1       ; R6 := false; PC := 155
155 [-]: LOADKB    R6 1 0       ; R6 := true
156 [-]: GETGLOBAL R7 K8        ; R7 := 0xae91e43b
157 [-]: SELF      R7 R7 K31    ; R8 := R7; R7 := R7[0xaade900e]
158 [-]: LOADK     R9 K41       ; R9 := "Options.EditMessage"
159 [-]: CONST     R10 11       ; R10 := 11.000000
160 [-]: MOVE      R11 R6       ; R11 := R6
161 [-]: CALL      R7 5 1       ; R7(R8,R9,R10,R11)
162 [-]: GETGLOBAL R7 K8        ; R7 := 0xae91e43b
163 [-]: SELF      R7 R7 K31    ; R8 := R7; R7 := R7[0xaade900e]
164 [-]: LOADK     R9 K42       ; R9 := "Options.RoomName"
165 [-]: CONST     R10 11       ; R10 := 11.000000
166 [-]: MOVE      R11 R6       ; R11 := R6
167 [-]: CALL      R7 5 1       ; R7(R8,R9,R10,R11)
168 [-]: GETGLOBAL R7 K43       ; R7 := 0xbf2ae52b
169 [-]: LOADK     R8 K44       ; R8 := ""
170 [-]: LOADNIL   R9 R9        ; R9 := nil
171 [-]: SETUPVAL  R9 U12       ; U82 := R12
172 [-]: LOADK     R9 K44       ; R9 := ""
173 [-]: SETUPVAL  R9 U13       ; U82 := R13
174 [-]: GETUPVAL  R9 U14       ; R9 := U14
175 [-]: SETTABLE  R9 K45 K46   ; R9["Visible"] := false
176 [-]: GETGLOBAL R9 K6        ; R9 := _T
177 [-]: GETTABLE  R9 R9 K47    ; R9 := R9["DojoMgr"]
178 [-]: GETTABLE  R9 R9 K48    ; R9 := R9["mDojo"]
179 [-]: SELF      R9 R9 K49    ; R10 := R9; R9 := R9[0x3b04a85d]
180 [-]: GETUPVAL  R11 U15      ; R11 := U15
181 [-]: GETTABLE  R11 R11 K50  ; R11 := R11["id"]
182 [-]: CALL      R9 3 2       ; R9 := R9(R10,R11)
183 [-]: TEST      R9 0         ; if not R9 then PC := 192
184 [-]: JMP       192          ; PC := 192
185 [-]: LOADK     R9 K51       ; R9 := "ChangeRoom"
186 [-]: SETUPVAL  R9 U12       ; U82 := R12
187 [-]: LOADK     R8 K52       ; R8 := "/Lotus/Language/Dojo/ConvertRoom"
188 [-]: GETGLOBAL R7 K53       ; R7 := 0x820956a8
189 [-]: LOADK     R9 K54       ; R9 := "/Lotus/Language/Dojo/ConvertRoomDesc"
190 [-]: SETUPVAL  R9 U13       ; U82 := R13
191 [-]: JMP       229          ; PC := 229
192 [-]: GETUPVAL  R9 U16       ; R9 := U16
193 [-]: TEST      R9 1         ; if R9 then PC := 204
194 [-]: JMP       204          ; PC := 204
195 [-]: GETUPVAL  R9 U0        ; R9 := U0
196 [-]: SELF      R9 R9 K55    ; R10 := R9; R9 := R9[0x9e1e1929]
197 [-]: CALL      R9 2 2       ; R9 := R9(R10)
198 [-]: TEST      R9 1         ; if R9 then PC := 204
199 [-]: JMP       204          ; PC := 204
200 [-]: LOADK     R9 K56       ; R9 := "DestroyRoom"
201 [-]: SETUPVAL  R9 U12       ; U82 := R12
202 [-]: LOADK     R8 K57       ; R8 := "/Lotus/Language/Dojo/DestroyRoom"
203 [-]: JMP       229          ; PC := 229
204 [-]: GETUPVAL  R9 U17       ; R9 := U17
205 [-]: TEST      R9 1         ; if R9 then PC := 229
206 [-]: JMP       229          ; PC := 229
207 [-]: GETUPVAL  R9 U16       ; R9 := U16
208 [-]: TEST      R9 1         ; if R9 then PC := 229
209 [-]: JMP       229          ; PC := 229
210 [-]: GETUPVAL  R9 U0        ; R9 := U0
211 [-]: SELF      R9 R9 K55    ; R10 := R9; R9 := R9[0x9e1e1929]
212 [-]: CALL      R9 2 2       ; R9 := R9(R10)
213 [-]: TEST      R9 0         ; if not R9 then PC := 229
214 [-]: JMP       229          ; PC := 229
215 [-]: LOADK     R9 K58       ; R9 := "CancelDestruction"
216 [-]: SETUPVAL  R9 U12       ; U82 := R12
217 [-]: LOADK     R8 K59       ; R8 := "/Lotus/Language/Dojo/CancelDestruction"
218 [-]: GETUPVAL  R9 U14       ; R9 := U14
219 [-]: SETTABLE  R9 K45 K60   ; R9["Visible"] := true
220 [-]: GETUPVAL  R9 U14       ; R9 := U14
221 [-]: SELF      R10 R2 K62   ; R11 := R2; R10 := R2[0xa1ddf837]
222 [-]: CALL      R10 2 2      ; R10 := R10(R11)
223 [-]: SETTABLE  R9 K61 R10   ; R9["TotalTime"] := R10
224 [-]: GETUPVAL  R9 U14       ; R9 := U14
225 [-]: GETUPVAL  R10 U0       ; R10 := U0
226 [-]: SELF      R10 R10 K64  ; R11 := R10; R10 := R10[0x0daac366]
227 [-]: CALL      R10 2 2      ; R10 := R10(R11)
228 [-]: SETTABLE  R9 K63 R10   ; R9["TimeLeft"] := R10
229 [-]: GETGLOBAL R9 K8        ; R9 := 0xae91e43b
230 [-]: SELF      R9 R9 K65    ; R10 := R9; R9 := R9[0x1cb415c1]
231 [-]: LOADK     R11 K66      ; R11 := "Options.Destroy.Icon"
232 [-]: MOVE      R12 R7       ; R12 := R7
233 [-]: CALL      R9 4 1       ; R9(R10,R11,R12)
234 [-]: GETGLOBAL R9 K67       ; R9 := 0x5f0788c4
235 [-]: GETGLOBAL R10 K8       ; R10 := 0xae91e43b
236 [-]: SELF      R10 R10 K9   ; R11 := R10; R10 := R10[0x42b04007]
237 [-]: MOVE      R12 R8       ; R12 := R8
238 [-]: LOADKB    R13 0 0      ; R13 := false
239 [-]: CALL      R10 4 0      ; R10,... := R10(R11,R12,R13)
240 [-]: CALL      R9 0 2       ; R9 := R9(R10,...)
241 [-]: MOVE      R8 R9        ; R8 := R9
242 [-]: GETGLOBAL R9 K8        ; R9 := 0xae91e43b
243 [-]: SELF      R9 R9 K34    ; R10 := R9; R9 := R9[0x5f56eeab]
244 [-]: LOADK     R11 K68      ; R11 := "Options.Destroy.Label"
245 [-]: CONST     R12 29       ; R12 := 29.000000
246 [-]: MOVE      R13 R8       ; R13 := R8
247 [-]: CALL      R9 5 1       ; R9(R10,R11,R12,R13)
248 [-]: GETGLOBAL R9 K8        ; R9 := 0xae91e43b
249 [-]: SELF      R9 R9 K31    ; R10 := R9; R9 := R9[0xaade900e]
250 [-]: LOADK     R11 K69      ; R11 := "Options.Destroy"
251 [-]: CONST     R12 11       ; R12 := 11.000000
252 [-]: GETUPVAL  R13 U12      ; R13 := U12
253 [-]: EQ        0 R13 K20    ; if R13 ~= nil then PC := 256
254 [-]: JMP       256          ; PC := 256
255 [-]: LOADKB    R13 0 1      ; R13 := false; PC := 256
256 [-]: LOADKB    R13 1 0      ; R13 := true
257 [-]: CALL      R9 5 1       ; R9(R10,R11,R12,R13)
258 [-]: GETGLOBAL R9 K8        ; R9 := 0xae91e43b
259 [-]: SELF      R9 R9 K31    ; R10 := R9; R9 := R9[0xaade900e]
260 [-]: LOADK     R11 K70      ; R11 := "Options.DestroyTimer"
261 [-]: CONST     R12 11       ; R12 := 11.000000
262 [-]: GETUPVAL  R13 U14      ; R13 := U14
263 [-]: GETTABLE  R13 R13 K45  ; R13 := R13["Visible"]
264 [-]: CALL      R9 5 1       ; R9(R10,R11,R12,R13)
265 [-]: GETGLOBAL R9 K67       ; R9 := 0x5f0788c4
266 [-]: GETGLOBAL R10 K8       ; R10 := 0xae91e43b
267 [-]: SELF      R10 R10 K9   ; R11 := R10; R10 := R10[0x42b04007]
268 [-]: LOADK     R12 K71      ; R12 := "/Lotus/Language/Dojo/PortalStatusBeingDestroyed"
269 [-]: LOADKB    R13 0 0      ; R13 := false
270 [-]: CALL      R10 4 0      ; R10,... := R10(R11,R12,R13)
271 [-]: CALL      R9 0 2       ; R9 := R9(R10,...)
272 [-]: GETGLOBAL R10 K8       ; R10 := 0xae91e43b
273 [-]: SELF      R10 R10 K34  ; R11 := R10; R10 := R10[0x5f56eeab]
274 [-]: LOADK     R12 K72      ; R12 := "Options.DestroyTimer.Label"
275 [-]: CONST     R13 29       ; R13 := 29.000000
276 [-]: MOVE      R14 R9       ; R14 := R9
277 [-]: CALL      R10 5 1      ; R10(R11,R12,R13,R14)
278 [-]: GETGLOBAL R10 K6       ; R10 := _T
279 [-]: GETTABLE  R10 R10 K47  ; R10 := R10["DojoMgr"]
280 [-]: GETTABLE  R10 R10 K48  ; R10 := R10["mDojo"]
281 [-]: SELF      R10 R10 K73  ; R11 := R10; R10 := R10[0x5c69b193]
282 [-]: GETUPVAL  R12 U15      ; R12 := U15
283 [-]: CALL      R10 3 2      ; R10 := R10(R11,R12)
284 [-]: GETGLOBAL R11 K6       ; R11 := _T
285 [-]: GETTABLE  R11 R11 K47  ; R11 := R11["DojoMgr"]
286 [-]: GETTABLE  R11 R11 K74  ; R11 := R11["mJsonProcLevelHelper"]
287 [-]: SELF      R11 R11 K75  ; R12 := R11; R11 := R11[0x05b62db2]
288 [-]: CALL      R11 2 2      ; R11 := R11(R12)
289 [-]: SELF      R11 R11 K76  ; R12 := R11; R11 := R11[0xcde10c4a]
290 [-]: CALL      R11 2 2      ; R11 := R11(R12)
291 [-]: GETGLOBAL R12 K3       ; R12 := 0x59462acb
292 [-]: SELF      R12 R12 K77  ; R13 := R12; R12 := R12[0x776a0d4d]
293 [-]: MOVE      R14 R11      ; R14 := R11
294 [-]: CALL      R12 3 2      ; R12 := R12(R13,R14)
295 [-]: LOADKB    R13 0 0      ; R13 := false
296 [-]: CONST     R14 1        ; R14 := 1.000000
297 [-]: LEN       R15 R12      ; R15 := # R12
298 [-]: CONST     R16 1        ; R16 := 1.000000
299 [-]: FORPREP   R14 318      ; R14 -= R16; PC := 318
300 [-]: GETGLOBAL R18 K2       ; R18 := 0x7b998233
301 [-]: GETTABLE  R19 R12 R17  ; R19 := R12[R17]
302 [-]: CALL      R18 2 2      ; R18 := R18(R19)
303 [-]: TEST      R18 1        ; if R18 then PC := 318
304 [-]: JMP       318          ; PC := 318
305 [-]: GETTABLE  R18 R12 R17  ; R18 := R12[R17]
306 [-]: SELF      R18 R18 K78  ; R19 := R18; R18 := R18[0x684aa402]
307 [-]: CALL      R18 2 2      ; R18 := R18(R19)
308 [-]: TEST      R18 0        ; if not R18 then PC := 318
309 [-]: JMP       318          ; PC := 318
310 [-]: GETTABLE  R18 R12 R17  ; R18 := R12[R17]
311 [-]: SELF      R18 R18 K79  ; R19 := R18; R18 := R18[0x2f7e523f]
312 [-]: GETTABLE  R20 R10 K5   ; R20 := R10["prefab"]
313 [-]: CALL      R18 3 2      ; R18 := R18(R19,R20)
314 [-]: TEST      R18 0        ; if not R18 then PC := 318
315 [-]: JMP       318          ; PC := 318
316 [-]: LOADKB    R13 1 0      ; R13 := true
317 [-]: JMP       319          ; PC := 319
318 [-]: FORLOOP   R14 300      ; R14 += R16; if R14 <= R15 then begin PC := 300; R17 := R14 end
319 [-]: TEST      R13 1        ; if R13 then PC := 361
320 [-]: JMP       361          ; PC := 361
321 [-]: GETGLOBAL R18 K2       ; R18 := 0x7b998233
322 [-]: MOVE      R19 R1       ; R19 := R1
323 [-]: CALL      R18 2 2      ; R18 := R18(R19)
324 [-]: TEST      R18 1        ; if R18 then PC := 361
325 [-]: JMP       361          ; PC := 361
326 [-]: SELF      R18 R1 K80   ; R19 := R1; R18 := R1[0xf39284cf]
327 [-]: CALL      R18 2 2      ; R18 := R18(R19)
328 [-]: CONST     R19 1        ; R19 := 1.000000
329 [-]: GETTABLE  R20 R18 K81  ; R20 := R18["mDecoRecipes"]
330 [-]: LEN       R20 R20      ; R20 := # R20
331 [-]: CONST     R21 1        ; R21 := 1.000000
332 [-]: FORPREP   R19 360      ; R19 -= R21; PC := 360
333 [-]: GETGLOBAL R23 K82      ; R23 := 0xb009bbc6
334 [-]: GETTABLE  R24 R18 K81  ; R24 := R18["mDecoRecipes"]
335 [-]: GETTABLE  R24 R24 R22  ; R24 := R24[R22]
336 [-]: GETTABLE  R24 R24 K83  ; R24 := R24["mItemType"]
337 [-]: CALL      R23 2 2      ; R23 := R23(R24)
338 [-]: GETGLOBAL R24 K2       ; R24 := 0x7b998233
339 [-]: MOVE      R25 R23      ; R25 := R23
340 [-]: CALL      R24 2 2      ; R24 := R24(R25)
341 [-]: TEST      R24 1        ; if R24 then PC := 360
342 [-]: JMP       360          ; PC := 360
343 [-]: GETTABLE  R24 R18 K81  ; R24 := R18["mDecoRecipes"]
344 [-]: GETTABLE  R24 R24 R22  ; R24 := R24[R22]
345 [-]: GETTABLE  R24 R24 K84  ; R24 := R24["mItemCount"]
346 [-]: LT        0 K85 R24    ; if 0.000000 >= R24 then PC := 360
347 [-]: JMP       360          ; PC := 360
348 [-]: SELF      R24 R23 K79  ; R25 := R23; R24 := R23[0x2f7e523f]
349 [-]: GETTABLE  R26 R10 K5   ; R26 := R10["prefab"]
350 [-]: CALL      R24 3 2      ; R24 := R24(R25,R26)
351 [-]: TEST      R24 0        ; if not R24 then PC := 360
352 [-]: JMP       360          ; PC := 360
353 [-]: SELF      R24 R23 K86  ; R25 := R23; R24 := R23[0xc24e5c3a]
354 [-]: MOVE      R26 R11      ; R26 := R11
355 [-]: CALL      R24 3 2      ; R24 := R24(R25,R26)
356 [-]: TEST      R24 0        ; if not R24 then PC := 360
357 [-]: JMP       360          ; PC := 360
358 [-]: LOADKB    R13 1 0      ; R13 := true
359 [-]: JMP       361          ; PC := 361
360 [-]: FORLOOP   R19 333      ; R19 += R21; if R19 <= R20 then begin PC := 333; R22 := R19 end
361 [-]: GETTABLE  R24 R10 K5   ; R24 := R10["prefab"]
362 [-]: GETGLOBAL R25 K87      ; R25 := 0xe502eecf
363 [-]: EQ        1 R24 R25    ; if R24 == R25 then PC := 380
364 [-]: JMP       380          ; PC := 380
365 [-]: GETGLOBAL R24 K6       ; R24 := _T
366 [-]: GETTABLE  R24 R24 K47  ; R24 := R24["DojoMgr"]
367 [-]: GETTABLE  R24 R24 K48  ; R24 := R24["mDojo"]
368 [-]: SELF      R24 R24 K88  ; R25 := R24; R24 := R24[0x57394da5]
369 [-]: MOVE      R26 R10      ; R26 := R10
370 [-]: CALL      R24 3 2      ; R24 := R24(R25,R26)
371 [-]: TEST      R24 0        ; if not R24 then PC := 380
372 [-]: JMP       380          ; PC := 380
373 [-]: GETUPVAL  R24 U6       ; R24 := U6
374 [-]: SELF      R24 R24 K21  ; R25 := R24; R24 := R24[0xbad4316f]
375 [-]: NEWTABLE  R26 0 2      ; R26 := {}
376 [-]: SETTABLE  R26 K22 K89  ; R26["Label"] := "/Lotus/Language/Dojo/MakeSpawnRoom"
377 [-]: SETTABLE  R26 K24 K90  ; R26["Callback"] := "MakeSpawnRoom"
378 [-]: LOADKB    R27 1 0      ; R27 := true
379 [-]: CALL      R24 4 1      ; R24(R25,R26,R27)
380 [-]: GETGLOBAL R24 K2       ; R24 := 0x7b998233
381 [-]: GETUPVAL  R25 U15      ; R25 := U15
382 [-]: CALL      R24 2 2      ; R24 := R24(R25)
383 [-]: TEST      R24 1        ; if R24 then PC := 433
384 [-]: JMP       433          ; PC := 433
385 [-]: GETGLOBAL R24 K6       ; R24 := _T
386 [-]: GETTABLE  R24 R24 K47  ; R24 := R24["DojoMgr"]
387 [-]: GETTABLE  R24 R24 K48  ; R24 := R24["mDojo"]
388 [-]: SELF      R24 R24 K73  ; R25 := R24; R24 := R24[0x5c69b193]
389 [-]: GETUPVAL  R26 U15      ; R26 := U15
390 [-]: CALL      R24 3 2      ; R24 := R24(R25,R26)
391 [-]: MOVE      R10 R24      ; R10 := R24
392 [-]: GETTABLE  R24 R10 K5   ; R24 := R10["prefab"]
393 [-]: GETGLOBAL R25 K87      ; R25 := 0xe502eecf
394 [-]: EQ        0 R24 R25    ; if R24 ~= R25 then PC := 419
395 [-]: JMP       419          ; PC := 419
396 [-]: GETUPVAL  R24 U6       ; R24 := U6
397 [-]: SELF      R24 R24 K21  ; R25 := R24; R24 := R24[0xbad4316f]
398 [-]: NEWTABLE  R26 0 2      ; R26 := {}
399 [-]: SETTABLE  R26 K22 K91  ; R26["Label"] := "/Lotus/Language/Dojo/CustomObstacleCourseResetLeaderboard"
400 [-]: SETTABLE  R26 K24 K92  ; R26["Callback"] := "ResetLeaderboard"
401 [-]: LOADKB    R27 1 0      ; R27 := true
402 [-]: CALL      R24 4 1      ; R24(R25,R26,R27)
403 [-]: GETUPVAL  R24 U6       ; R24 := U6
404 [-]: SELF      R24 R24 K21  ; R25 := R24; R24 := R24[0xbad4316f]
405 [-]: NEWTABLE  R26 0 2      ; R26 := {}
406 [-]: SETTABLE  R26 K22 K93  ; R26["Label"] := "/Lotus/Language/Dojo/CustomObstacleCourseResetRoom"
407 [-]: SETTABLE  R26 K24 K94  ; R26["Callback"] := "ResetObstacleCourse"
408 [-]: LOADKB    R27 1 0      ; R27 := true
409 [-]: CALL      R24 4 1      ; R24(R25,R26,R27)
410 [-]: GETUPVAL  R24 U6       ; R24 := U6
411 [-]: SELF      R24 R24 K21  ; R25 := R24; R24 := R24[0xbad4316f]
412 [-]: NEWTABLE  R26 0 2      ; R26 := {}
413 [-]: GETUPVAL  R27 U18      ; R27 := U18
414 [-]: CALL      R27 1 2      ; R27 := R27()
415 [-]: SETTABLE  R26 K22 R27  ; R26["Label"] := R27
416 [-]: SETTABLE  R26 K24 K95  ; R26["Callback"] := "ToggleAllowOperatorMode"
417 [-]: LOADKB    R27 1 0      ; R27 := true
418 [-]: CALL      R24 4 1      ; R24(R25,R26,R27)
419 [-]: GETGLOBAL R24 K6       ; R24 := _T
420 [-]: GETTABLE  R24 R24 K47  ; R24 := R24["DojoMgr"]
421 [-]: SELF      R24 R24 K96  ; R25 := R24; R24 := R24[0x94d66f0d]
422 [-]: MOVE      R26 R10      ; R26 := R10
423 [-]: CALL      R24 3 2      ; R24 := R24(R25,R26)
424 [-]: TEST      R24 0        ; if not R24 then PC := 433
425 [-]: JMP       433          ; PC := 433
426 [-]: GETUPVAL  R24 U6       ; R24 := U6
427 [-]: SELF      R24 R24 K21  ; R25 := R24; R24 := R24[0xbad4316f]
428 [-]: NEWTABLE  R26 0 2      ; R26 := {}
429 [-]: SETTABLE  R26 K22 K97  ; R26["Label"] := "/Lotus/Language/Dojo/SelectBackdrop"
430 [-]: SETTABLE  R26 K24 K98  ; R26["Callback"] := "OpenBackdropSelect"
431 [-]: LOADKB    R27 1 0      ; R27 := true
432 [-]: CALL      R24 4 1      ; R24(R25,R26,R27)
433 [-]: GETUPVAL  R24 U6       ; R24 := U6
434 [-]: SELF      R24 R24 K99  ; R25 := R24; R24 := R24[0x71e9ac81]
435 [-]: LOADNIL   R26 R27      ; R26 := R27 := nil
436 [-]: LOADKB    R28 1 0      ; R28 := true
437 [-]: CALL      R24 5 1      ; R24(R25,R26,R27,R28)
438 [-]: GETUPVAL  R24 U19      ; R24 := U19
439 [-]: CALL      R24 1 1      ; R24()
440 [-]: JMP       443          ; PC := 443
441 [-]: GETUPVAL  R24 U3       ; R24 := U3
442 [-]: CALL      R24 1 1      ; R24()
443 [-]: RETURN    R0 1         ; return 


; Function #8:
;
; Name:            
; Defined at line: 357
; #Upvalues:       5
; #Parameters:     0
; Is_vararg:       0
; Max Stack Size:  15

  1 [-]: GETGLOBAL R0 K0        ; R0 := _T
  2 [-]: SETTABLE  R0 K1 K2     ; R0["gToolTip"] := nil
  3 [-]: GETGLOBAL R0 K3        ; R0 := 0x7b998233
  4 [-]: GETGLOBAL R1 K0        ; R1 := _T
  5 [-]: GETTABLE  R1 R1 K4     ; R1 := R1["ChangeHubVisCounter"]
  6 [-]: CALL      R0 2 2       ; R0 := R0(R1)
  7 [-]: TEST      R0 1         ; if R0 then PC := 13
  8 [-]: JMP       13           ; PC := 13
  9 [-]: GETGLOBAL R0 K0        ; R0 := _T
 10 [-]: GETTABLE  R0 R0 K5     ; R0 := R0[0x33cfa273]
 11 [-]: CONST     R1 -1        ; R1 := -1.000000
 12 [-]: CALL      R0 2 1       ; R0(R1)
 13 [-]: GETGLOBAL R0 K3        ; R0 := 0x7b998233
 14 [-]: GETGLOBAL R1 K6        ; R1 := 0xbe190284
 15 [-]: CALL      R0 2 2       ; R0 := R0(R1)
 16 [-]: TEST      R0 1         ; if R0 then PC := 22
 17 [-]: JMP       22           ; PC := 22
 18 [-]: GETGLOBAL R0 K6        ; R0 := 0xbe190284
 19 [-]: SELF      R0 R0 K7     ; R1 := R0; R0 := R0[0xc02f2cb8]
 20 [-]: LOADKB    R2 0 0       ; R2 := false
 21 [-]: CALL      R0 3 1       ; R0(R1,R2)
 22 [-]: GETUPVAL  R0 U0        ; R0 := U0
 23 [-]: GETTABLE  R0 R0 K8     ; R0 := R0[0x9e3d3434]
 24 [-]: LOADKB    R1 0 0       ; R1 := false
 25 [-]: CALL      R0 2 1       ; R0(R1)
 26 [-]: GETGLOBAL R0 K3        ; R0 := 0x7b998233
 27 [-]: GETGLOBAL R1 K0        ; R1 := _T
 28 [-]: GETTABLE  R1 R1 K9     ; R1 := R1["DojoMgr"]
 29 [-]: CALL      R0 2 2       ; R0 := R0(R1)
 30 [-]: TEST      R0 1         ; if R0 then PC := 44
 31 [-]: JMP       44           ; PC := 44
 32 [-]: GETGLOBAL R0 K3        ; R0 := 0x7b998233
 33 [-]: GETUPVAL  R1 U1        ; R1 := U1
 34 [-]: CALL      R0 2 2       ; R0 := R0(R1)
 35 [-]: TEST      R0 1         ; if R0 then PC := 44
 36 [-]: JMP       44           ; PC := 44
 37 [-]: GETGLOBAL R0 K0        ; R0 := _T
 38 [-]: GETTABLE  R0 R0 K9     ; R0 := R0["DojoMgr"]
 39 [-]: SELF      R0 R0 K10    ; R1 := R0; R0 := R0[0x8dc3f8eb]
 40 [-]: GETUPVAL  R2 U1        ; R2 := U1
 41 [-]: GETTABLE  R2 R2 K11    ; R2 := R2["id"]
 42 [-]: GETUPVAL  R3 U2        ; R3 := U2
 43 [-]: CALL      R0 4 1       ; R0(R1,R2,R3)
 44 [-]: GETUPVAL  R0 U3        ; R0 := U3
 45 [-]: TEST      R0 0         ; if not R0 then PC := 56
 46 [-]: JMP       56           ; PC := 56
 47 [-]: GETGLOBAL R0 K3        ; R0 := 0x7b998233
 48 [-]: GETGLOBAL R1 K0        ; R1 := _T
 49 [-]: GETTABLE  R1 R1 K12    ; R1 := R1["SetSquadOverlayTitle"]
 50 [-]: CALL      R0 2 2       ; R0 := R0(R1)
 51 [-]: TEST      R0 1         ; if R0 then PC := 56
 52 [-]: JMP       56           ; PC := 56
 53 [-]: GETGLOBAL R0 K0        ; R0 := _T
 54 [-]: GETTABLE  R0 R0 K13    ; R0 := R0[0xdf29a9d6]
 55 [-]: CALL      R0 1 1       ; R0()
 56 [-]: GETUPVAL  R0 U4        ; R0 := U4
 57 [-]: TEST      R0 0         ; if not R0 then PC := 204
 58 [-]: JMP       204          ; PC := 204
 59 [-]: GETGLOBAL R0 K14       ; R0 := 0x89326c93
 60 [-]: SELF      R0 R0 K15    ; R1 := R0; R0 := R0[0x78298275]
 61 [-]: CALL      R0 2 2       ; R0 := R0(R1)
 62 [-]: GETGLOBAL R1 K3        ; R1 := 0x7b998233
 63 [-]: MOVE      R2 R0        ; R2 := R0
 64 [-]: CALL      R1 2 2       ; R1 := R1(R2)
 65 [-]: TEST      R1 1         ; if R1 then PC := 204
 66 [-]: JMP       204          ; PC := 204
 67 [-]: SELF      R1 R0 K16    ; R2 := R0; R1 := R0[0x5e651723]
 68 [-]: CALL      R1 2 2       ; R1 := R1(R2)
 69 [-]: GETGLOBAL R2 K3        ; R2 := 0x7b998233
 70 [-]: MOVE      R3 R1        ; R3 := R1
 71 [-]: CALL      R2 2 2       ; R2 := R2(R3)
 72 [-]: TEST      R2 1         ; if R2 then PC := 189
 73 [-]: JMP       189          ; PC := 189
 74 [-]: SELF      R2 R1 K17    ; R3 := R1; R2 := R1[0xf08bc0f9]
 75 [-]: CALL      R2 2 2       ; R2 := R2(R3)
 76 [-]: TEST      R2 1         ; if R2 then PC := 86
 77 [-]: JMP       86           ; PC := 86
 78 [-]: SELF      R2 R1 K18    ; R3 := R1; R2 := R1[0x262c60e3]
 79 [-]: CALL      R2 2 1       ; R2(R3)
 80 [-]: SELF      R2 R1 K19    ; R3 := R1; R2 := R1[0x3421742c]
 81 [-]: LOADKB    R4 1 0       ; R4 := true
 82 [-]: CALL      R2 3 1       ; R2(R3,R4)
 83 [-]: SELF      R2 R1 K20    ; R3 := R1; R2 := R1[0x2a1779ef]
 84 [-]: LOADKB    R4 1 0       ; R4 := true
 85 [-]: CALL      R2 3 1       ; R2(R3,R4)
 86 [-]: GETGLOBAL R2 K6        ; R2 := 0xbe190284
 87 [-]: SELF      R2 R2 K21    ; R3 := R2; R2 := R2[0x2adb4822]
 88 [-]: CALL      R2 2 2       ; R2 := R2(R3)
 89 [-]: SELF      R3 R0 K22    ; R4 := R0; R3 := R0[0xc9f6a7d7]
 90 [-]: MOVE      R5 R2        ; R5 := R2
 91 [-]: CALL      R3 3 2       ; R3 := R3(R4,R5)
 92 [-]: GETGLOBAL R4 K3        ; R4 := 0x7b998233
 93 [-]: MOVE      R5 R3        ; R5 := R3
 94 [-]: CALL      R4 2 2       ; R4 := R4(R5)
 95 [-]: TEST      R4 0         ; if not R4 then PC := 102
 96 [-]: JMP       102          ; PC := 102
 97 [-]: SELF      R4 R0 K23    ; R5 := R0; R4 := R0[0x47901f07]
 98 [-]: MOVE      R6 R2        ; R6 := R2
 99 [-]: GETGLOBAL R7 K24       ; R7 := EMPTY_SYMBOL
100 [-]: CALL      R4 4 2       ; R4 := R4(R5,R6,R7)
101 [-]: MOVE      R3 R4        ; R3 := R4
102 [-]: GETGLOBAL R4 K3        ; R4 := 0x7b998233
103 [-]: MOVE      R5 R3        ; R5 := R3
104 [-]: CALL      R4 2 2       ; R4 := R4(R5)
105 [-]: TEST      R4 1         ; if R4 then PC := 115
106 [-]: JMP       115          ; PC := 115
107 [-]: SELF      R4 R0 K25    ; R5 := R0; R4 := R0[0x96603f61]
108 [-]: MOVE      R6 R3        ; R6 := R3
109 [-]: LOADKB    R7 1 0       ; R7 := true
110 [-]: CALL      R4 4 1       ; R4(R5,R6,R7)
111 [-]: SELF      R4 R3 K26    ; R5 := R3; R4 := R3[0x2e7b28d0]
112 [-]: GETUPVAL  R6 U1        ; R6 := U1
113 [-]: GETTABLE  R6 R6 K11    ; R6 := R6["id"]
114 [-]: CALL      R4 3 1       ; R4(R5,R6)
115 [-]: GETGLOBAL R4 K27       ; R4 := 0x603636ad
116 [-]: LOADK     R5 K28       ; R5 := "/Lotus/Language/Labels/DecorationHeaderFreeCamera"
117 [-]: LOADNIL   R6 R6        ; R6 := nil
118 [-]: CALL      R4 3 2       ; R4 := R4(R5,R6)
119 [-]: LOADK     R5 K29       ; R5 := "\r\n"
120 [-]: GETGLOBAL R6 K27       ; R6 := 0x603636ad
121 [-]: LOADK     R7 K30       ; R7 := "/Lotus/Language/Labels/DecorationModePlacement"
122 [-]: LOADNIL   R8 R8        ; R8 := nil
123 [-]: CALL      R6 3 2       ; R6 := R6(R7,R8)
124 [-]: CONCAT    R4 R4 R6     ; R4 := R4 .. R5 .. R6
125 [-]: GETGLOBAL R5 K3        ; R5 := 0x7b998233
126 [-]: GETGLOBAL R6 K0        ; R6 := _T
127 [-]: GETTABLE  R6 R6 K31    ; R6 := R6["PrevPlacedDecoInfo"]
128 [-]: CALL      R5 2 2       ; R5 := R5(R6)
129 [-]: TEST      R5 1         ; if R5 then PC := 148
130 [-]: JMP       148          ; PC := 148
131 [-]: LOADK     R5 K32       ; R5 := ""
132 [-]: GETGLOBAL R6 K33       ; R6 := 0x34291f5c
133 [-]: GETTABLE  R6 R6 K34    ; R6 := R6[0x1467d5f4]
134 [-]: CALL      R6 1 2       ; R6 := R6()
135 [-]: TEST      R6 0         ; if not R6 then PC := 138
136 [-]: JMP       138          ; PC := 138
137 [-]: LOADK     R5 K35       ; R5 := "Console"
138 [-]: GETGLOBAL R6 K27       ; R6 := 0x603636ad
139 [-]: LOADK     R7 K36       ; R7 := "/Lotus/Language/Dojo/DecoPlacePrevious"
140 [-]: MOVE      R8 R5        ; R8 := R5
141 [-]: CONCAT    R7 R7 R8     ; R7 := R7 .. R8
142 [-]: LOADNIL   R8 R8        ; R8 := nil
143 [-]: CALL      R6 3 2       ; R6 := R6(R7,R8)
144 [-]: MOVE      R7 R4        ; R7 := R4
145 [-]: LOADK     R8 K29       ; R8 := "\r\n"
146 [-]: MOVE      R9 R6        ; R9 := R6
147 [-]: CONCAT    R4 R7 R9     ; R4 := R7 .. R8 .. R9
148 [-]: MOVE      R7 R4        ; R7 := R4
149 [-]: LOADK     R8 K29       ; R8 := "\r\n"
150 [-]: GETGLOBAL R9 K27       ; R9 := 0x603636ad
151 [-]: LOADK     R10 K37      ; R10 := "/Lotus/Language/Labels/DecorationModeHelp"
152 [-]: LOADNIL   R11 R11      ; R11 := nil
153 [-]: CALL      R9 3 2       ; R9 := R9(R10,R11)
154 [-]: LOADK     R10 K29      ; R10 := "\r\n"
155 [-]: GETGLOBAL R11 K27      ; R11 := 0x603636ad
156 [-]: LOADK     R12 K38      ; R12 := "/Lotus/Language/Labels/DecorationModeExit"
157 [-]: LOADNIL   R13 R13      ; R13 := nil
158 [-]: CALL      R11 3 2      ; R11 := R11(R12,R13)
159 [-]: CONCAT    R7 R7 R11    ; R7 := R7 .. R8 .. R9 .. R10 .. R11
160 [-]: MOVE      R8 R4        ; R8 := R4
161 [-]: LOADK     R9 K29       ; R9 := "\r\n"
162 [-]: GETGLOBAL R10 K27      ; R10 := 0x603636ad
163 [-]: LOADK     R11 K38      ; R11 := "/Lotus/Language/Labels/DecorationModeExit"
164 [-]: LOADNIL   R12 R12      ; R12 := nil
165 [-]: CALL      R10 3 2      ; R10 := R10(R11,R12)
166 [-]: CONCAT    R8 R8 R10    ; R8 := R8 .. R9 .. R10
167 [-]: SELF      R9 R1 K39    ; R10 := R1; R9 := R1[0x0803eee1]
168 [-]: CALL      R9 2 2       ; R9 := R9(R10)
169 [-]: SELF      R9 R9 K40    ; R10 := R9; R9 := R9[0x89212ed6]
170 [-]: MOVE      R11 R7       ; R11 := R7
171 [-]: LOADK     R12 K41      ; R12 := "{A}"
172 [-]: MOVE      R13 R8       ; R13 := R8
173 [-]: CONCAT    R11 R11 R13  ; R11 := R11 .. R12 .. R13
174 [-]: CALL      R9 3 1       ; R9(R10,R11)
175 [-]: GETGLOBAL R9 K33       ; R9 := 0x34291f5c
176 [-]: GETTABLE  R9 R9 K42    ; R9 := R9[0xe6b41adb]
177 [-]: CALL      R9 1 2       ; R9 := R9()
178 [-]: TEST      R9 0         ; if not R9 then PC := 189
179 [-]: JMP       189          ; PC := 189
180 [-]: GETGLOBAL R9 K0        ; R9 := _T
181 [-]: GETTABLE  R9 R9 K43    ; R9 := R9["SetDecoControls"]
182 [-]: TEST      R9 0         ; if not R9 then PC := 189
183 [-]: JMP       189          ; PC := 189
184 [-]: GETGLOBAL R9 K0        ; R9 := _T
185 [-]: GETTABLE  R9 R9 K44    ; R9 := R9[0x2aa7b1c5]
186 [-]: NEWTABLE  R10 0 1      ; R10 := {}
187 [-]: SETTABLE  R10 K45 K46  ; R10["ShipDecoGeneral"] := true
188 [-]: CALL      R9 2 1       ; R9(R10)
189 [-]: GETGLOBAL R9 K47       ; R9 := 0x9ba7909f
190 [-]: SELF      R9 R9 K48    ; R10 := R9; R9 := R9[0xcfba257f]
191 [-]: GETGLOBAL R11 K49      ; R11 := 0x0032441c
192 [-]: GETTABLE  R11 R11 K50  ; R11 := R11["UIMovie_ShipDecoHUD"]
193 [-]: CALL      R9 3 2       ; R9 := R9(R10,R11)
194 [-]: GETGLOBAL R10 K3       ; R10 := 0x7b998233
195 [-]: MOVE      R11 R9       ; R11 := R9
196 [-]: CALL      R10 2 2      ; R10 := R10(R11)
197 [-]: TEST      R10 1        ; if R10 then PC := 204
198 [-]: JMP       204          ; PC := 204
199 [-]: SELF      R10 R9 K51   ; R11 := R9; R10 := R9[0xaade900e]
200 [-]: LOADK     R12 K52      ; R12 := "Reticle"
201 [-]: CONST     R13 11       ; R13 := 11.000000
202 [-]: LOADKB    R14 1 0      ; R14 := true
203 [-]: CALL      R10 5 1      ; R10(R11,R12,R13,R14)
204 [-]: RETURN    R0 1         ; return 


; Function #9:
;
; Name:            
; Defined at line: 428
; #Upvalues:       3
; #Parameters:     2
; Is_vararg:       0
; Max Stack Size:  6

  1 [-]: TEST      R0 1         ; if R0 then PC := 10
  2 [-]: JMP       10           ; PC := 10
  3 [-]: LOADKB    R2 1 0       ; R2 := true
  4 [-]: SETUPVAL  R2 U0        ; U82 := R0
  5 [-]: GETUPVAL  R2 U1        ; R2 := U1
  6 [-]: GETTABLE  R2 R2 K0     ; R2 := R2[0xe0cba3ca]
  7 [-]: LOADK     R3 K1        ; R3 := "/Lotus/Language/Dojo/SetComponentMessageFailed"
  8 [-]: CALL      R2 2 1       ; R2(R3)
  9 [-]: JMP       16           ; PC := 16
 10 [-]: GETUPVAL  R2 U2        ; R2 := U2
 11 [-]: GETUPVAL  R3 U2        ; R3 := U2
 12 [-]: GETTABLE  R3 R3 K3     ; R3 := R3["CurrMessage"]
 13 [-]: SETTABLE  R2 K2 R3     ; R2["InitialMessage"] := R3
 14 [-]: GETUPVAL  R2 U2        ; R2 := U2
 15 [-]: SETTABLE  R2 K3 K4     ; R2["CurrMessage"] := nil
 16 [-]: GETGLOBAL R2 K5        ; R2 := _T
 17 [-]: GETTABLE  R2 R2 K6     ; R2 := R2["BackgroundMovie"]
 18 [-]: SELF      R2 R2 K7     ; R3 := R2; R2 := R2[0xe4162eed]
 19 [-]: LOADK     R4 K8        ; R4 := "ShowBlockingMessage"
 20 [-]: LOADK     R5 K9        ; R5 := "0"
 21 [-]: CALL      R2 4 1       ; R2(R3,R4,R5)
 22 [-]: RETURN    R0 1         ; return 


; Function #10:
;
; Name:            
; Defined at line: 441
; #Upvalues:       4
; #Parameters:     2
; Is_vararg:       0
; Max Stack Size:  6

  1 [-]: TEST      R0 1         ; if R0 then PC := 10
  2 [-]: JMP       10           ; PC := 10
  3 [-]: LOADKB    R2 1 0       ; R2 := true
  4 [-]: SETUPVAL  R2 U0        ; U82 := R0
  5 [-]: GETUPVAL  R2 U1        ; R2 := U1
  6 [-]: GETTABLE  R2 R2 K0     ; R2 := R2[0xe0cba3ca]
  7 [-]: LOADK     R3 K1        ; R3 := "/Lotus/Language/Dojo/SetComponentNameFailed"
  8 [-]: CALL      R2 2 1       ; R2(R3)
  9 [-]: JMP       16           ; PC := 16
 10 [-]: GETUPVAL  R2 U2        ; R2 := U2
 11 [-]: GETUPVAL  R3 U3        ; R3 := U3
 12 [-]: GETTABLE  R3 R3 K3     ; R3 := R3["CurrName"]
 13 [-]: SETTABLE  R2 K2 R3     ; R2["InitialName"] := R3
 14 [-]: GETUPVAL  R2 U2        ; R2 := U2
 15 [-]: SETTABLE  R2 K3 K4     ; R2["CurrName"] := nil
 16 [-]: GETGLOBAL R2 K5        ; R2 := _T
 17 [-]: GETTABLE  R2 R2 K6     ; R2 := R2["BackgroundMovie"]
 18 [-]: SELF      R2 R2 K7     ; R3 := R2; R2 := R2[0xe4162eed]
 19 [-]: LOADK     R4 K8        ; R4 := "ShowBlockingMessage"
 20 [-]: LOADK     R5 K9        ; R5 := "0"
 21 [-]: CALL      R2 4 1       ; R2(R3,R4,R5)
 22 [-]: RETURN    R0 1         ; return 


; Function #11:
;
; Name:            
; Defined at line: 454
; #Upvalues:       0
; #Parameters:     2
; Is_vararg:       0
; Max Stack Size:  7

  1 [-]: TEST      R0 0         ; if not R0 then PC := 7
  2 [-]: JMP       7            ; PC := 7
  3 [-]: GETGLOBAL R2 K0        ; R2 := 0x3d106989
  4 [-]: LOADK     R3 K1        ; R3 := "cancelled by user"
  5 [-]: CALL      R2 2 1       ; R2(R3)
  6 [-]: JMP       13           ; PC := 13
  7 [-]: GETGLOBAL R2 K2        ; R2 := 0xae91e43b
  8 [-]: SELF      R2 R2 K3     ; R3 := R2; R2 := R2[0x5f56eeab]
  9 [-]: LOADK     R4 K4        ; R4 := "Options.EditMessage.Message"
 10 [-]: CONST     R5 29        ; R5 := 29.000000
 11 [-]: MOVE      R6 R1        ; R6 := R1
 12 [-]: CALL      R2 5 1       ; R2(R3,R4,R5,R6)
 13 [-]: RETURN    R0 1         ; return 


; Function #12:
;
; Name:            
; Defined at line: 462
; #Upvalues:       0
; #Parameters:     2
; Is_vararg:       0
; Max Stack Size:  7

  1 [-]: TEST      R0 0         ; if not R0 then PC := 7
  2 [-]: JMP       7            ; PC := 7
  3 [-]: GETGLOBAL R2 K0        ; R2 := 0x3d106989
  4 [-]: LOADK     R3 K1        ; R3 := "cancelled by user"
  5 [-]: CALL      R2 2 1       ; R2(R3)
  6 [-]: JMP       13           ; PC := 13
  7 [-]: GETGLOBAL R2 K2        ; R2 := 0xae91e43b
  8 [-]: SELF      R2 R2 K3     ; R3 := R2; R2 := R2[0x5f56eeab]
  9 [-]: LOADK     R4 K4        ; R4 := "Options.RoomName.Message"
 10 [-]: CONST     R5 29        ; R5 := 29.000000
 11 [-]: MOVE      R6 R1        ; R6 := R1
 12 [-]: CALL      R2 5 1       ; R2(R3,R4,R5,R6)
 13 [-]: RETURN    R0 1         ; return 


; Function #13:
;
; Name:            
; Defined at line: 470
; #Upvalues:       1
; #Parameters:     2
; Is_vararg:       0
; Max Stack Size:  5

  1 [-]: GETUPVAL  R2 U0        ; R2 := U0
  2 [-]: MOVE      R3 R0        ; R3 := R0
  3 [-]: MOVE      R4 R1        ; R4 := R1
  4 [-]: CALL      R2 3 1       ; R2(R3,R4)
  5 [-]: RETURN    R0 1         ; return 


; Function #14:
;
; Name:            
; Defined at line: 474
; #Upvalues:       1
; #Parameters:     2
; Is_vararg:       0
; Max Stack Size:  5

  1 [-]: GETUPVAL  R2 U0        ; R2 := U0
  2 [-]: MOVE      R3 R0        ; R3 := R0
  3 [-]: MOVE      R4 R1        ; R4 := R1
  4 [-]: CALL      R2 3 1       ; R2(R3,R4)
  5 [-]: RETURN    R0 1         ; return 


; Function #15:
;
; Name:            
; Defined at line: 478
; #Upvalues:       1
; #Parameters:     3
; Is_vararg:       0
; Max Stack Size:  6

  1 [-]: GETUPVAL  R3 U0        ; R3 := U0
  2 [-]: GETGLOBAL R4 K0        ; R4 := 0x03f57322
  3 [-]: MOVE      R5 R2        ; R5 := R2
  4 [-]: CALL      R4 2 2       ; R4 := R4(R5)
  5 [-]: EQ        0 R4 K2      ; if R4 ~= 4.000000 then PC := 8
  6 [-]: JMP       8            ; PC := 8
  7 [-]: LOADKB    R4 0 1       ; R4 := false; PC := 8
  8 [-]: LOADKB    R4 1 0       ; R4 := true
  9 [-]: MOVE      R5 R0        ; R5 := R0
 10 [-]: CALL      R3 3 1       ; R3(R4,R5)
 11 [-]: RETURN    R0 1         ; return 


; Function #16:
;
; Name:            
; Defined at line: 482
; #Upvalues:       1
; #Parameters:     3
; Is_vararg:       0
; Max Stack Size:  6

  1 [-]: GETUPVAL  R3 U0        ; R3 := U0
  2 [-]: GETGLOBAL R4 K0        ; R4 := 0x03f57322
  3 [-]: MOVE      R5 R2        ; R5 := R2
  4 [-]: CALL      R4 2 2       ; R4 := R4(R5)
  5 [-]: EQ        0 R4 K2      ; if R4 ~= 4.000000 then PC := 8
  6 [-]: JMP       8            ; PC := 8
  7 [-]: LOADKB    R4 0 1       ; R4 := false; PC := 8
  8 [-]: LOADKB    R4 1 0       ; R4 := true
  9 [-]: MOVE      R5 R0        ; R5 := R0
 10 [-]: CALL      R3 3 1       ; R3(R4,R5)
 11 [-]: RETURN    R0 1         ; return 


; Function #17:
;
; Name:            
; Defined at line: 486
; #Upvalues:       3
; #Parameters:     1
; Is_vararg:       0
; Max Stack Size:  8

  1 [-]: LOADKB    R1 0 0       ; R1 := false
  2 [-]: SETUPVAL  R1 U0        ; U82 := R0
  3 [-]: GETGLOBAL R1 K0        ; R1 := 0x03f57322
  4 [-]: MOVE      R2 R0        ; R2 := R0
  5 [-]: CALL      R1 2 2       ; R1 := R1(R2)
  6 [-]: EQ        0 R1 K2      ; if R1 ~= 4.000000 then PC := 27
  7 [-]: JMP       27           ; PC := 27
  8 [-]: GETGLOBAL R1 K3        ; R1 := _T
  9 [-]: GETTABLE  R1 R1 K4     ; R1 := R1["BackgroundMovie"]
 10 [-]: SELF      R1 R1 K5     ; R2 := R1; R1 := R1[0xe4162eed]
 11 [-]: LOADK     R3 K6        ; R3 := "ShowBlockingMessage"
 12 [-]: LOADK     R4 K7        ; R4 := "1"
 13 [-]: CALL      R1 4 1       ; R1(R2,R3,R4)
 14 [-]: GETGLOBAL R1 K3        ; R1 := _T
 15 [-]: GETTABLE  R1 R1 K8     ; R1 := R1["DojoMgr"]
 16 [-]: SELF      R1 R1 K9     ; R2 := R1; R1 := R1[0x2d8b1a74]
 17 [-]: GETUPVAL  R3 U1        ; R3 := U1
 18 [-]: GETTABLE  R3 R3 K10    ; R3 := R3["id"]
 19 [-]: GETTABLE  R3 R3 K11    ; R3 := R3["mId"]
 20 [-]: GETGLOBAL R4 K12       ; R4 := 0xae91e43b
 21 [-]: SELF      R4 R4 K13    ; R5 := R4; R4 := R4[0x54a95d6f]
 22 [-]: LOADK     R6 K14       ; R6 := "Options.EditMessage.Message"
 23 [-]: CONST     R7 29        ; R7 := 29.000000
 24 [-]: CALL      R4 4 2       ; R4 := R4(R5,R6,R7)
 25 [-]: GETUPVAL  R5 U2        ; R5 := U2
 26 [-]: CALL      R1 5 1       ; R1(R2,R3,R4,R5)
 27 [-]: RETURN    R0 1         ; return 


; Function #18:
;
; Name:            
; Defined at line: 494
; #Upvalues:       3
; #Parameters:     1
; Is_vararg:       0
; Max Stack Size:  8

  1 [-]: LOADKB    R1 0 0       ; R1 := false
  2 [-]: SETUPVAL  R1 U0        ; U82 := R0
  3 [-]: GETGLOBAL R1 K0        ; R1 := 0x03f57322
  4 [-]: MOVE      R2 R0        ; R2 := R0
  5 [-]: CALL      R1 2 2       ; R1 := R1(R2)
  6 [-]: EQ        0 R1 K2      ; if R1 ~= 4.000000 then PC := 27
  7 [-]: JMP       27           ; PC := 27
  8 [-]: GETGLOBAL R1 K3        ; R1 := _T
  9 [-]: GETTABLE  R1 R1 K4     ; R1 := R1["BackgroundMovie"]
 10 [-]: SELF      R1 R1 K5     ; R2 := R1; R1 := R1[0xe4162eed]
 11 [-]: LOADK     R3 K6        ; R3 := "ShowBlockingMessage"
 12 [-]: LOADK     R4 K7        ; R4 := "1"
 13 [-]: CALL      R1 4 1       ; R1(R2,R3,R4)
 14 [-]: GETGLOBAL R1 K3        ; R1 := _T
 15 [-]: GETTABLE  R1 R1 K8     ; R1 := R1["DojoMgr"]
 16 [-]: SELF      R1 R1 K9     ; R2 := R1; R1 := R1[0x298e6716]
 17 [-]: GETUPVAL  R3 U1        ; R3 := U1
 18 [-]: GETTABLE  R3 R3 K10    ; R3 := R3["id"]
 19 [-]: GETTABLE  R3 R3 K11    ; R3 := R3["mId"]
 20 [-]: GETGLOBAL R4 K12       ; R4 := 0xae91e43b
 21 [-]: SELF      R4 R4 K13    ; R5 := R4; R4 := R4[0x54a95d6f]
 22 [-]: LOADK     R6 K14       ; R6 := "Options.RoomName.Message"
 23 [-]: CONST     R7 29        ; R7 := 29.000000
 24 [-]: CALL      R4 4 2       ; R4 := R4(R5,R6,R7)
 25 [-]: GETUPVAL  R5 U2        ; R5 := U2
 26 [-]: CALL      R1 5 1       ; R1(R2,R3,R4,R5)
 27 [-]: RETURN    R0 1         ; return 


; Function #19:
;
; Name:            
; Defined at line: 502
; #Upvalues:       2
; #Parameters:     0
; Is_vararg:       0
; Max Stack Size:  4

  1 [-]: LOADKB    R0 1 0       ; R0 := true
  2 [-]: SETUPVAL  R0 U0        ; U82 := R0
  3 [-]: GETUPVAL  R0 U1        ; R0 := U1
  4 [-]: GETTABLE  R0 R0 K0     ; R0 := R0[0xe0cba3ca]
  5 [-]: LOADK     R1 K1        ; R1 := "/Lotus/Language/Dojo/UpdateMessageConfirm"
  6 [-]: LOADK     R2 K2        ; R2 := "UpdateMessageConfirm"
  7 [-]: CONST     R3 1         ; R3 := 1.000000
  8 [-]: CALL      R0 4 1       ; R0(R1,R2,R3)
  9 [-]: RETURN    R0 1         ; return 


; Function #20:
;
; Name:            
; Defined at line: 507
; #Upvalues:       2
; #Parameters:     0
; Is_vararg:       0
; Max Stack Size:  4

  1 [-]: LOADKB    R0 1 0       ; R0 := true
  2 [-]: SETUPVAL  R0 U0        ; U82 := R0
  3 [-]: GETUPVAL  R0 U1        ; R0 := U1
  4 [-]: GETTABLE  R0 R0 K0     ; R0 := R0[0xe0cba3ca]
  5 [-]: LOADK     R1 K1        ; R1 := "/Lotus/Language/Dojo/UpdateNameConfirm"
  6 [-]: LOADK     R2 K2        ; R2 := "UpdateNameConfirm"
  7 [-]: CONST     R3 1         ; R3 := 1.000000
  8 [-]: CALL      R0 4 1       ; R0(R1,R2,R3)
  9 [-]: RETURN    R0 1         ; return 


; Function #21:
;
; Name:            
; Defined at line: 512
; #Upvalues:       3
; #Parameters:     0
; Is_vararg:       0
; Max Stack Size:  9

  1 [-]: GETGLOBAL R0 K0        ; R0 := 0x34291f5c
  2 [-]: GETTABLE  R0 R0 K1     ; R0 := R0[0x1467d5f4]
  3 [-]: CALL      R0 1 2       ; R0 := R0()
  4 [-]: TEST      R0 0         ; if not R0 then PC := 36
  5 [-]: JMP       36           ; PC := 36
  6 [-]: GETUPVAL  R0 U0        ; R0 := U0
  7 [-]: TEST      R0 0         ; if not R0 then PC := 36
  8 [-]: JMP       36           ; PC := 36
  9 [-]: GETGLOBAL R0 K2        ; R0 := 0xae91e43b
 10 [-]: SELF      R0 R0 K3     ; R1 := R0; R0 := R0[0x42b04007]
 11 [-]: LOADK     R2 K4        ; R2 := "/Lotus/Language/Dojo/DojoRoomMessage"
 12 [-]: LOADKB    R3 0 0       ; R3 := false
 13 [-]: CALL      R0 4 2       ; R0 := R0(R1,R2,R3)
 14 [-]: GETGLOBAL R1 K2        ; R1 := 0xae91e43b
 15 [-]: SELF      R1 R1 K5     ; R2 := R1; R1 := R1[0x54a95d6f]
 16 [-]: LOADK     R3 K6        ; R3 := "Options.EditMessage.Message"
 17 [-]: CONST     R4 29        ; R4 := 29.000000
 18 [-]: CALL      R1 4 2       ; R1 := R1(R2,R3,R4)
 19 [-]: GETUPVAL  R2 U1        ; R2 := U1
 20 [-]: TEST      R2 0         ; if not R2 then PC := 27
 21 [-]: JMP       27           ; PC := 27
 22 [-]: GETGLOBAL R2 K7        ; R2 := 0x09423272
 23 [-]: MOVE      R3 R1        ; R3 := R1
 24 [-]: CONST     R4 0         ; R4 := 0.000000
 25 [-]: CALL      R2 3 2       ; R2 := R2(R3,R4)
 26 [-]: MOVE      R1 R2        ; R1 := R2
 27 [-]: GETUPVAL  R2 U2        ; R2 := U2
 28 [-]: GETTABLE  R2 R2 K9     ; R2 := R2[0xef3e3165]
 29 [-]: GETGLOBAL R3 K2        ; R3 := 0xae91e43b
 30 [-]: MOVE      R4 R0        ; R4 := R0
 31 [-]: MOVE      R5 R1        ; R5 := R1
 32 [-]: CONST     R6 0         ; R6 := 0.000000
 33 [-]: LOADK     R7 K10       ; R7 := "InputDialogMsgCallback"
 34 [-]: LOADK     R8 K11       ; R8 := "OSKMsgCallback"
 35 [-]: CALL      R2 7 1       ; R2(R3,R4,R5,R6,R7,R8)
 36 [-]: RETURN    R0 1         ; return 


; Function #22:
;
; Name:            
; Defined at line: 524
; #Upvalues:       3
; #Parameters:     0
; Is_vararg:       0
; Max Stack Size:  9

  1 [-]: GETGLOBAL R0 K0        ; R0 := 0x34291f5c
  2 [-]: GETTABLE  R0 R0 K1     ; R0 := R0[0x1467d5f4]
  3 [-]: CALL      R0 1 2       ; R0 := R0()
  4 [-]: TEST      R0 0         ; if not R0 then PC := 36
  5 [-]: JMP       36           ; PC := 36
  6 [-]: GETUPVAL  R0 U0        ; R0 := U0
  7 [-]: TEST      R0 0         ; if not R0 then PC := 36
  8 [-]: JMP       36           ; PC := 36
  9 [-]: GETGLOBAL R0 K2        ; R0 := 0xae91e43b
 10 [-]: SELF      R0 R0 K3     ; R1 := R0; R0 := R0[0x42b04007]
 11 [-]: LOADK     R2 K4        ; R2 := "/Lotus/Language/Dojo/DojoRoomName"
 12 [-]: LOADKB    R3 0 0       ; R3 := false
 13 [-]: CALL      R0 4 2       ; R0 := R0(R1,R2,R3)
 14 [-]: GETGLOBAL R1 K2        ; R1 := 0xae91e43b
 15 [-]: SELF      R1 R1 K5     ; R2 := R1; R1 := R1[0x54a95d6f]
 16 [-]: LOADK     R3 K6        ; R3 := "Options.RoomName.Message"
 17 [-]: CONST     R4 29        ; R4 := 29.000000
 18 [-]: CALL      R1 4 2       ; R1 := R1(R2,R3,R4)
 19 [-]: GETUPVAL  R2 U1        ; R2 := U1
 20 [-]: TEST      R2 0         ; if not R2 then PC := 27
 21 [-]: JMP       27           ; PC := 27
 22 [-]: GETGLOBAL R2 K7        ; R2 := 0x09423272
 23 [-]: MOVE      R3 R1        ; R3 := R1
 24 [-]: CONST     R4 0         ; R4 := 0.000000
 25 [-]: CALL      R2 3 2       ; R2 := R2(R3,R4)
 26 [-]: MOVE      R1 R2        ; R1 := R2
 27 [-]: GETUPVAL  R2 U2        ; R2 := U2
 28 [-]: GETTABLE  R2 R2 K9     ; R2 := R2[0xef3e3165]
 29 [-]: GETGLOBAL R3 K2        ; R3 := 0xae91e43b
 30 [-]: MOVE      R4 R0        ; R4 := R0
 31 [-]: MOVE      R5 R1        ; R5 := R1
 32 [-]: CONST     R6 0         ; R6 := 0.000000
 33 [-]: LOADK     R7 K10       ; R7 := "InputDialogNameCallback"
 34 [-]: LOADK     R8 K11       ; R8 := "OSKNameCallback"
 35 [-]: CALL      R2 7 1       ; R2(R3,R4,R5,R6,R7,R8)
 36 [-]: RETURN    R0 1         ; return 


; Function #23:
;
; Name:            
; Defined at line: 536
; #Upvalues:       1
; #Parameters:     2
; Is_vararg:       0
; Max Stack Size:  4

  1 [-]: TEST      R0 0         ; if not R0 then PC := 8
  2 [-]: JMP       8            ; PC := 8
  3 [-]: GETUPVAL  R2 U0        ; R2 := U0
  4 [-]: GETTABLE  R2 R2 K0     ; R2 := R2[0xe0cba3ca]
  5 [-]: LOADK     R3 K1        ; R3 := "/Lotus/Language/Dojo/CustomObstacleCourseResetLeaderboardSuccess"
  6 [-]: CALL      R2 2 1       ; R2(R3)
  7 [-]: JMP       12           ; PC := 12
  8 [-]: GETUPVAL  R2 U0        ; R2 := U0
  9 [-]: GETTABLE  R2 R2 K0     ; R2 := R2[0xe0cba3ca]
 10 [-]: LOADK     R3 K2        ; R3 := "/Lotus/Language/Dojo/CustomObstacleCourseResetLeaderboardFail"
 11 [-]: CALL      R2 2 1       ; R2(R3)
 12 [-]: RETURN    R0 1         ; return 


; Function #24:
;
; Name:            
; Defined at line: 544
; #Upvalues:       1
; #Parameters:     0
; Is_vararg:       0
; Max Stack Size:  9

  1 [-]: GETGLOBAL R0 K0        ; R0 := 0x7b998233
  2 [-]: GETGLOBAL R1 K1        ; R1 := _T
  3 [-]: GETTABLE  R1 R1 K2     ; R1 := R1["DojoMgr"]
  4 [-]: CALL      R0 2 2       ; R0 := R0(R1)
  5 [-]: TEST      R0 1         ; if R0 then PC := 35
  6 [-]: JMP       35           ; PC := 35
  7 [-]: GETGLOBAL R0 K1        ; R0 := _T
  8 [-]: GETTABLE  R0 R0 K2     ; R0 := R0["DojoMgr"]
  9 [-]: GETTABLE  R0 R0 K3     ; R0 := R0["mDojo"]
 10 [-]: SELF      R0 R0 K4     ; R1 := R0; R0 := R0[0x5c69b193]
 11 [-]: GETUPVAL  R2 U0        ; R2 := U0
 12 [-]: CALL      R0 3 2       ; R0 := R0(R1,R2)
 13 [-]: GETTABLE  R1 R0 K5     ; R1 := R0["prefab"]
 14 [-]: GETGLOBAL R2 K6        ; R2 := 0xe502eecf
 15 [-]: EQ        0 R1 R2      ; if R1 ~= R2 then PC := 35
 16 [-]: JMP       35           ; PC := 35
 17 [-]: GETGLOBAL R1 K1        ; R1 := _T
 18 [-]: GETTABLE  R1 R1 K2     ; R1 := R1["DojoMgr"]
 19 [-]: GETTABLE  R1 R1 K7     ; R1 := R1["mGameRules"]
 20 [-]: SELF      R1 R1 K8     ; R2 := R1; R1 := R1[0x713ce380]
 21 [-]: CALL      R1 2 2       ; R1 := R1(R2)
 22 [-]: GETUPVAL  R2 U0        ; R2 := U0
 23 [-]: GETTABLE  R2 R2 K9     ; R2 := R2["id"]
 24 [-]: GETGLOBAL R3 K10       ; R3 := 0x76ea806b
 25 [-]: SELF      R3 R3 K11    ; R4 := R3; R3 := R3[0x3f3ae64c]
 26 [-]: CONST     R5 0         ; R5 := 0.000000
 27 [-]: CALL      R3 3 2       ; R3 := R3(R4,R5)
 28 [-]: SELF      R3 R3 K12    ; R4 := R3; R3 := R3[0x80563238]
 29 [-]: CALL      R3 2 2       ; R3 := R3(R4)
 30 [-]: SELF      R4 R3 K13    ; R5 := R3; R4 := R3[0xd701d9a9]
 31 [-]: MOVE      R6 R1        ; R6 := R1
 32 [-]: MOVE      R7 R2        ; R7 := R2
 33 [-]: LOADK     R8 K14       ; R8 := "OnResetLeaderboardResult"
 34 [-]: CALL      R4 5 1       ; R4(R5,R6,R7,R8)
 35 [-]: RETURN    R0 1         ; return 


; Function #25:
;
; Name:            
; Defined at line: 556
; #Upvalues:       1
; #Parameters:     0
; Is_vararg:       0
; Max Stack Size:  2

  1 [-]: GETUPVAL  R0 U0        ; R0 := U0
  2 [-]: CALL      R0 1 1       ; R0()
  3 [-]: RETURN    R0 1         ; return 


; Function #26:
;
; Name:            
; Defined at line: 561
; #Upvalues:       1
; #Parameters:     2
; Is_vararg:       0
; Max Stack Size:  4

  1 [-]: EQ        0 R0 K1      ; if R0 ~= 0.000000 then PC := 8
  2 [-]: JMP       8            ; PC := 8
  3 [-]: GETUPVAL  R2 U0        ; R2 := U0
  4 [-]: GETTABLE  R2 R2 K2     ; R2 := R2[0xe0cba3ca]
  5 [-]: LOADK     R3 K3        ; R3 := "/Lotus/Language/Dojo/CustomObstacleCourseRoomResetSuccess"
  6 [-]: CALL      R2 2 1       ; R2(R3)
  7 [-]: JMP       33           ; PC := 33
  8 [-]: EQ        0 R0 K4      ; if R0 ~= -1.000000 then PC := 15
  9 [-]: JMP       15           ; PC := 15
 10 [-]: GETUPVAL  R2 U0        ; R2 := U0
 11 [-]: GETTABLE  R2 R2 K2     ; R2 := R2[0xe0cba3ca]
 12 [-]: LOADK     R3 K5        ; R3 := "/Lotus/Language/Dojo/Generic_INVALID_PERMISSION"
 13 [-]: CALL      R2 2 1       ; R2(R3)
 14 [-]: JMP       33           ; PC := 33
 15 [-]: EQ        0 R0 K6      ; if R0 ~= 14.000000 then PC := 22
 16 [-]: JMP       22           ; PC := 22
 17 [-]: GETUPVAL  R2 U0        ; R2 := U0
 18 [-]: GETTABLE  R2 R2 K2     ; R2 := R2[0xe0cba3ca]
 19 [-]: LOADK     R3 K7        ; R3 := "/Lotus/Language/Dojo/DecoDestructionFail_DESTRUCTION_ALREADY_QUEUED"
 20 [-]: CALL      R2 2 1       ; R2(R3)
 21 [-]: JMP       33           ; PC := 33
 22 [-]: EQ        0 R0 K8      ; if R0 ~= 2.000000 then PC := 29
 23 [-]: JMP       29           ; PC := 29
 24 [-]: GETUPVAL  R2 U0        ; R2 := U0
 25 [-]: GETTABLE  R2 R2 K2     ; R2 := R2[0xe0cba3ca]
 26 [-]: LOADK     R3 K9        ; R3 := "/Lotus/Language/Dojo/DecoDestructionFail_PARENT_NO_LONGER_EXISTS"
 27 [-]: CALL      R2 2 1       ; R2(R3)
 28 [-]: JMP       33           ; PC := 33
 29 [-]: GETUPVAL  R2 U0        ; R2 := U0
 30 [-]: GETTABLE  R2 R2 K2     ; R2 := R2[0xe0cba3ca]
 31 [-]: LOADK     R3 K10       ; R3 := "/Lotus/Language/Dojo/DecoDestructionFail_UNKNOWN_ERROR"
 32 [-]: CALL      R2 2 1       ; R2(R3)
 33 [-]: RETURN    R0 1         ; return 


; Function #27:
;
; Name:            
; Defined at line: 578
; #Upvalues:       2
; #Parameters:     0
; Is_vararg:       0
; Max Stack Size:  5

  1 [-]: GETGLOBAL R0 K0        ; R0 := 0x7b998233
  2 [-]: GETGLOBAL R1 K1        ; R1 := _T
  3 [-]: GETTABLE  R1 R1 K2     ; R1 := R1["DojoMgr"]
  4 [-]: CALL      R0 2 2       ; R0 := R0(R1)
  5 [-]: TEST      R0 1         ; if R0 then PC := 27
  6 [-]: JMP       27           ; PC := 27
  7 [-]: GETGLOBAL R0 K1        ; R0 := _T
  8 [-]: GETTABLE  R0 R0 K2     ; R0 := R0["DojoMgr"]
  9 [-]: GETTABLE  R0 R0 K3     ; R0 := R0["mDojo"]
 10 [-]: SELF      R0 R0 K4     ; R1 := R0; R0 := R0[0x5c69b193]
 11 [-]: GETUPVAL  R2 U0        ; R2 := U0
 12 [-]: CALL      R0 3 2       ; R0 := R0(R1,R2)
 13 [-]: GETTABLE  R1 R0 K5     ; R1 := R0["prefab"]
 14 [-]: GETGLOBAL R2 K6        ; R2 := 0xe502eecf
 15 [-]: EQ        0 R1 R2      ; if R1 ~= R2 then PC := 27
 16 [-]: JMP       27           ; PC := 27
 17 [-]: GETUPVAL  R1 U0        ; R1 := U0
 18 [-]: GETTABLE  R1 R1 K7     ; R1 := R1["id"]
 19 [-]: GETGLOBAL R2 K1        ; R2 := _T
 20 [-]: GETTABLE  R2 R2 K2     ; R2 := R2["DojoMgr"]
 21 [-]: SETTABLE  R2 K8 R1     ; R2["mPendingDestroyDecoComponentId"] := R1
 22 [-]: GETGLOBAL R2 K1        ; R2 := _T
 23 [-]: GETTABLE  R2 R2 K2     ; R2 := R2["DojoMgr"]
 24 [-]: SELF      R2 R2 K9     ; R3 := R2; R2 := R2[0xdc52139a]
 25 [-]: GETUPVAL  R4 U1        ; R4 := U1
 26 [-]: CALL      R2 3 1       ; R2(R3,R4)
 27 [-]: RETURN    R0 1         ; return 


; Function #28:
;
; Name:            
; Defined at line: 589
; #Upvalues:       1
; #Parameters:     1
; Is_vararg:       0
; Max Stack Size:  2

  1 [-]: EQ        0 R0 K1      ; if R0 ~= 4.000000 then PC := 5
  2 [-]: JMP       5            ; PC := 5
  3 [-]: GETUPVAL  R1 U0        ; R1 := U0
  4 [-]: CALL      R1 1 1       ; R1()
  5 [-]: RETURN    R0 1         ; return 


; Function #29:
;
; Name:            
; Defined at line: 595
; #Upvalues:       2
; #Parameters:     1
; Is_vararg:       0
; Max Stack Size:  5

  1 [-]: EQ        0 R0 K1      ; if R0 ~= 4.000000 then PC := 11
  2 [-]: JMP       11           ; PC := 11
  3 [-]: LOADKB    R1 1 0       ; R1 := true
  4 [-]: SETUPVAL  R1 U0        ; U82 := R0
  5 [-]: GETUPVAL  R1 U1        ; R1 := U1
  6 [-]: GETTABLE  R1 R1 K2     ; R1 := R1[0xe0cba3ca]
  7 [-]: LOADK     R2 K3        ; R2 := "/Lotus/Language/Dojo/CustomObstacleCourseResetRoomReallyConfirm"
  8 [-]: LOADK     R3 K4        ; R3 := "ResetObstacleCourseReallyConfirm"
  9 [-]: CONST     R4 1         ; R4 := 1.000000
 10 [-]: CALL      R1 4 1       ; R1(R2,R3,R4)
 11 [-]: RETURN    R0 1         ; return 


; Function #30:
;
; Name:            
; Defined at line: 602
; #Upvalues:       2
; #Parameters:     0
; Is_vararg:       0
; Max Stack Size:  4

  1 [-]: LOADKB    R0 1 0       ; R0 := true
  2 [-]: SETUPVAL  R0 U0        ; U82 := R0
  3 [-]: GETUPVAL  R0 U1        ; R0 := U1
  4 [-]: GETTABLE  R0 R0 K0     ; R0 := R0[0xe0cba3ca]
  5 [-]: LOADK     R1 K1        ; R1 := "/Lotus/Language/Dojo/CustomObstacleCourseResetRoomConfirm"
  6 [-]: LOADK     R2 K2        ; R2 := "ResetObstacleCourseConfirm"
  7 [-]: CONST     R3 1         ; R3 := 1.000000
  8 [-]: CALL      R0 4 1       ; R0(R1,R2,R3)
  9 [-]: RETURN    R0 1         ; return 


; Function #31:
;
; Name:            
; Defined at line: 607
; #Upvalues:       1
; #Parameters:     2
; Is_vararg:       0
; Max Stack Size:  4

  1 [-]: EQ        0 R0 K1      ; if R0 ~= -1.000000 then PC := 8
  2 [-]: JMP       8            ; PC := 8
  3 [-]: GETUPVAL  R2 U0        ; R2 := U0
  4 [-]: GETTABLE  R2 R2 K2     ; R2 := R2[0xe0cba3ca]
  5 [-]: LOADK     R3 K3        ; R3 := "/Lotus/Language/Dojo/Generic_INVALID_PERMISSION"
  6 [-]: CALL      R2 2 1       ; R2(R3)
  7 [-]: JMP       28           ; PC := 28
  8 [-]: EQ        0 R0 K4      ; if R0 ~= 14.000000 then PC := 15
  9 [-]: JMP       15           ; PC := 15
 10 [-]: GETUPVAL  R2 U0        ; R2 := U0
 11 [-]: GETTABLE  R2 R2 K2     ; R2 := R2[0xe0cba3ca]
 12 [-]: LOADK     R3 K5        ; R3 := "/Lotus/Language/Dojo/DecoDestructionFail_DESTRUCTION_ALREADY_QUEUED"
 13 [-]: CALL      R2 2 1       ; R2(R3)
 14 [-]: JMP       28           ; PC := 28
 15 [-]: EQ        0 R0 K6      ; if R0 ~= 2.000000 then PC := 22
 16 [-]: JMP       22           ; PC := 22
 17 [-]: GETUPVAL  R2 U0        ; R2 := U0
 18 [-]: GETTABLE  R2 R2 K2     ; R2 := R2[0xe0cba3ca]
 19 [-]: LOADK     R3 K7        ; R3 := "/Lotus/Language/Dojo/DecoDestructionFail_PARENT_NO_LONGER_EXISTS"
 20 [-]: CALL      R2 2 1       ; R2(R3)
 21 [-]: JMP       28           ; PC := 28
 22 [-]: EQ        1 R0 K8      ; if R0 == 0.000000 then PC := 28
 23 [-]: JMP       28           ; PC := 28
 24 [-]: GETUPVAL  R2 U0        ; R2 := U0
 25 [-]: GETTABLE  R2 R2 K2     ; R2 := R2[0xe0cba3ca]
 26 [-]: LOADK     R3 K9        ; R3 := "/Lotus/Language/Dojo/DecoDestructionFail_UNKNOWN_ERROR"
 27 [-]: CALL      R2 2 1       ; R2(R3)
 28 [-]: RETURN    R0 1         ; return 


; Function #32:
;
; Name:            
; Defined at line: 619
; #Upvalues:       3
; #Parameters:     0
; Is_vararg:       0
; Max Stack Size:  8

  1 [-]: GETGLOBAL R0 K0        ; R0 := 0x7b998233
  2 [-]: GETGLOBAL R1 K1        ; R1 := _T
  3 [-]: GETTABLE  R1 R1 K2     ; R1 := R1["DojoMgr"]
  4 [-]: CALL      R0 2 2       ; R0 := R0(R1)
  5 [-]: TEST      R0 1         ; if R0 then PC := 53
  6 [-]: JMP       53           ; PC := 53
  7 [-]: GETGLOBAL R0 K1        ; R0 := _T
  8 [-]: GETTABLE  R0 R0 K2     ; R0 := R0["DojoMgr"]
  9 [-]: GETTABLE  R0 R0 K3     ; R0 := R0["mDojo"]
 10 [-]: SELF      R0 R0 K4     ; R1 := R0; R0 := R0[0x5c69b193]
 11 [-]: GETUPVAL  R2 U0        ; R2 := U0
 12 [-]: CALL      R0 3 2       ; R0 := R0(R1,R2)
 13 [-]: GETTABLE  R1 R0 K5     ; R1 := R0["prefab"]
 14 [-]: GETGLOBAL R2 K6        ; R2 := 0xe502eecf
 15 [-]: EQ        0 R1 R2      ; if R1 ~= R2 then PC := 53
 16 [-]: JMP       53           ; PC := 53
 17 [-]: GETUPVAL  R1 U1        ; R1 := U1
 18 [-]: SELF      R1 R1 K7     ; R2 := R1; R1 := R1[0x4f14d68d]
 19 [-]: CALL      R1 2 2       ; R1 := R1(R2)
 20 [-]: GETGLOBAL R2 K8        ; R2 := cjson
 21 [-]: GETTABLE  R2 R2 K9     ; R2 := R2[0x7ab914d8]
 22 [-]: MOVE      R3 R1        ; R3 := R1
 23 [-]: CALL      R2 2 2       ; R2 := R2(R3)
 24 [-]: EQ        1 R2 K10     ; if R2 == nil then PC := 36
 25 [-]: JMP       36           ; PC := 36
 26 [-]: GETTABLE  R3 R2 K11    ; R3 := R2["courseMode"]
 27 [-]: EQ        1 R3 K10     ; if R3 == nil then PC := 32
 28 [-]: JMP       32           ; PC := 32
 29 [-]: GETTABLE  R3 R2 K11    ; R3 := R2["courseMode"]
 30 [-]: EQ        0 R3 K13     ; if R3 ~= 0.000000 then PC := 34
 31 [-]: JMP       34           ; PC := 34
 32 [-]: SETTABLE  R2 K11 K14   ; R2["courseMode"] := 1.000000
 33 [-]: JMP       39           ; PC := 39
 34 [-]: SETTABLE  R2 K11 K13   ; R2["courseMode"] := 0.000000
 35 [-]: JMP       39           ; PC := 39
 36 [-]: NEWTABLE  R3 0 1       ; R3 := {}
 37 [-]: SETTABLE  R3 K11 K13   ; R3["courseMode"] := 0.000000
 38 [-]: MOVE      R2 R3        ; R2 := R3
 39 [-]: GETGLOBAL R3 K8        ; R3 := cjson
 40 [-]: GETTABLE  R3 R3 K15    ; R3 := R3[0xb139d7bc]
 41 [-]: MOVE      R4 R2        ; R4 := R2
 42 [-]: CALL      R3 2 2       ; R3 := R3(R4)
 43 [-]: MOVE      R1 R3        ; R1 := R3
 44 [-]: GETGLOBAL R3 K1        ; R3 := _T
 45 [-]: GETTABLE  R3 R3 K2     ; R3 := R3["DojoMgr"]
 46 [-]: SELF      R3 R3 K16    ; R4 := R3; R3 := R3[0xe9e57538]
 47 [-]: GETUPVAL  R5 U1        ; R5 := U1
 48 [-]: GETTABLE  R5 R5 K17    ; R5 := R5["id"]
 49 [-]: GETTABLE  R5 R5 K18    ; R5 := R5["mId"]
 50 [-]: MOVE      R6 R1        ; R6 := R1
 51 [-]: GETUPVAL  R7 U2        ; R7 := U2
 52 [-]: CALL      R3 5 1       ; R3(R4,R5,R6,R7)
 53 [-]: RETURN    R0 1         ; return 


; Function #33:
;
; Name:            
; Defined at line: 640
; #Upvalues:       1
; #Parameters:     2
; Is_vararg:       0
; Max Stack Size:  6

  1 [-]: EQ        0 R0 K1      ; if R0 ~= 0.000000 then PC := 22
  2 [-]: JMP       22           ; PC := 22
  3 [-]: GETGLOBAL R2 K2        ; R2 := 0x7b998233
  4 [-]: GETGLOBAL R3 K3        ; R3 := _T
  5 [-]: GETTABLE  R3 R3 K4     ; R3 := R3["DojoMgr"]
  6 [-]: CALL      R2 2 2       ; R2 := R2(R3)
  7 [-]: TEST      R2 1         ; if R2 then PC := 22
  8 [-]: JMP       22           ; PC := 22
  9 [-]: GETGLOBAL R2 K3        ; R2 := _T
 10 [-]: GETTABLE  R2 R2 K4     ; R2 := R2["DojoMgr"]
 11 [-]: SELF      R2 R2 K5     ; R3 := R2; R2 := R2[0xe161086b]
 12 [-]: GETGLOBAL R4 K3        ; R4 := _T
 13 [-]: GETTABLE  R4 R4 K6     ; R4 := R4["OpenSpaceBackdropId"]
 14 [-]: GETUPVAL  R5 U0        ; R5 := U0
 15 [-]: GETTABLE  R5 R5 K7     ; R5 := R5["id"]
 16 [-]: GETTABLE  R5 R5 K8     ; R5 := R5["mId"]
 17 [-]: GETTABLE  R4 R4 R5     ; R4 := R4[R5]
 18 [-]: GETUPVAL  R5 U0        ; R5 := U0
 19 [-]: GETTABLE  R5 R5 K7     ; R5 := R5["id"]
 20 [-]: GETTABLE  R5 R5 K8     ; R5 := R5["mId"]
 21 [-]: CALL      R2 4 1       ; R2(R3,R4,R5)
 22 [-]: RETURN    R0 1         ; return 


; Function #34:
;
; Name:            
; Defined at line: 646
; #Upvalues:       3
; #Parameters:     1
; Is_vararg:       0
; Max Stack Size:  10

  1 [-]: GETGLOBAL R1 K0        ; R1 := 0x7b998233
  2 [-]: GETGLOBAL R2 K1        ; R2 := _T
  3 [-]: GETTABLE  R2 R2 K2     ; R2 := R2["DojoMgr"]
  4 [-]: CALL      R1 2 2       ; R1 := R1(R2)
  5 [-]: TEST      R1 1         ; if R1 then PC := 60
  6 [-]: JMP       60           ; PC := 60
  7 [-]: GETGLOBAL R1 K1        ; R1 := _T
  8 [-]: GETTABLE  R1 R1 K2     ; R1 := R1["DojoMgr"]
  9 [-]: GETTABLE  R1 R1 K3     ; R1 := R1["mDojo"]
 10 [-]: SELF      R1 R1 K4     ; R2 := R1; R1 := R1[0x5c69b193]
 11 [-]: GETUPVAL  R3 U0        ; R3 := U0
 12 [-]: CALL      R1 3 2       ; R1 := R1(R2,R3)
 13 [-]: GETGLOBAL R2 K1        ; R2 := _T
 14 [-]: GETTABLE  R2 R2 K2     ; R2 := R2["DojoMgr"]
 15 [-]: SELF      R2 R2 K5     ; R3 := R2; R2 := R2[0x94d66f0d]
 16 [-]: MOVE      R4 R1        ; R4 := R1
 17 [-]: CALL      R2 3 2       ; R2 := R2(R3,R4)
 18 [-]: TEST      R2 0         ; if not R2 then PC := 60
 19 [-]: JMP       60           ; PC := 60
 20 [-]: GETTABLE  R2 R1 K6     ; R2 := R1["id"]
 21 [-]: GETTABLE  R2 R2 K7     ; R2 := R2["mId"]
 22 [-]: GETUPVAL  R3 U1        ; R3 := U1
 23 [-]: SELF      R3 R3 K8     ; R4 := R3; R3 := R3[0x4f14d68d]
 24 [-]: CALL      R3 2 2       ; R3 := R3(R4)
 25 [-]: GETGLOBAL R4 K9        ; R4 := cjson
 26 [-]: GETTABLE  R4 R4 K10    ; R4 := R4[0x7ab914d8]
 27 [-]: MOVE      R5 R3        ; R5 := R3
 28 [-]: CALL      R4 2 2       ; R4 := R4(R5)
 29 [-]: EQ        1 R4 K11     ; if R4 == nil then PC := 33
 30 [-]: JMP       33           ; PC := 33
 31 [-]: SETTABLE  R4 K12 R0    ; R4["backdropId"] := R0
 32 [-]: JMP       36           ; PC := 36
 33 [-]: NEWTABLE  R5 0 1       ; R5 := {}
 34 [-]: SETTABLE  R5 K12 R0    ; R5["backdropId"] := R0
 35 [-]: MOVE      R4 R5        ; R4 := R5
 36 [-]: GETGLOBAL R5 K9        ; R5 := cjson
 37 [-]: GETTABLE  R5 R5 K13    ; R5 := R5[0xb139d7bc]
 38 [-]: MOVE      R6 R4        ; R6 := R4
 39 [-]: CALL      R5 2 2       ; R5 := R5(R6)
 40 [-]: MOVE      R3 R5        ; R3 := R5
 41 [-]: GETGLOBAL R5 K1        ; R5 := _T
 42 [-]: GETTABLE  R5 R5 K14    ; R5 := R5["OpenSpaceBackdropId"]
 43 [-]: EQ        0 R5 K11     ; if R5 ~= nil then PC := 48
 44 [-]: JMP       48           ; PC := 48
 45 [-]: GETGLOBAL R5 K1        ; R5 := _T
 46 [-]: NEWTABLE  R6 0 0       ; R6 := {}
 47 [-]: SETTABLE  R5 K14 R6    ; R5["OpenSpaceBackdropId"] := R6
 48 [-]: GETGLOBAL R5 K1        ; R5 := _T
 49 [-]: GETTABLE  R5 R5 K14    ; R5 := R5["OpenSpaceBackdropId"]
 50 [-]: SETTABLE  R5 R2 R0     ; R5[R2] := R0
 51 [-]: GETGLOBAL R5 K1        ; R5 := _T
 52 [-]: GETTABLE  R5 R5 K2     ; R5 := R5["DojoMgr"]
 53 [-]: SELF      R5 R5 K15    ; R6 := R5; R5 := R5[0xe9e57538]
 54 [-]: GETUPVAL  R7 U1        ; R7 := U1
 55 [-]: GETTABLE  R7 R7 K6     ; R7 := R7["id"]
 56 [-]: GETTABLE  R7 R7 K7     ; R7 := R7["mId"]
 57 [-]: MOVE      R8 R3        ; R8 := R3
 58 [-]: GETUPVAL  R9 U2        ; R9 := U2
 59 [-]: CALL      R5 5 1       ; R5(R6,R7,R8,R9)
 60 [-]: RETURN    R0 1         ; return 


; Function #35:
;
; Name:            
; Defined at line: 668
; #Upvalues:       1
; #Parameters:     1
; Is_vararg:       0
; Max Stack Size:  3

  1 [-]: GETUPVAL  R1 U0        ; R1 := U0
  2 [-]: MOVE      R2 R0        ; R2 := R0
  3 [-]: CALL      R1 2 1       ; R1(R2)
  4 [-]: RETURN    R0 1         ; return 


; Function #36:
;
; Name:            
; Defined at line: 672
; #Upvalues:       2
; #Parameters:     0
; Is_vararg:       0
; Max Stack Size:  22

  1 [-]: GETGLOBAL R0 K0        ; R0 := 0xae91e43b
  2 [-]: SELF      R0 R0 K1     ; R1 := R0; R0 := R0[0x42b04007]
  3 [-]: LOADK     R2 K2        ; R2 := "/Lotus/Language/Dojo/NoBackdrops"
  4 [-]: LOADKB    R3 0 0       ; R3 := false
  5 [-]: CALL      R0 4 2       ; R0 := R0(R1,R2,R3)
  6 [-]: GETGLOBAL R1 K3        ; R1 := 0x76ea806b
  7 [-]: SELF      R1 R1 K4     ; R2 := R1; R1 := R1[0x3f3ae64c]
  8 [-]: CONST     R3 0         ; R3 := 0.000000
  9 [-]: CALL      R1 3 2       ; R1 := R1(R2,R3)
 10 [-]: SELF      R1 R1 K5     ; R2 := R1; R1 := R1[0x80563238]
 11 [-]: CALL      R1 2 2       ; R1 := R1(R2)
 12 [-]: GETGLOBAL R2 K6        ; R2 := 0x7b998233
 13 [-]: MOVE      R3 R1        ; R3 := R1
 14 [-]: CALL      R2 2 2       ; R2 := R2(R3)
 15 [-]: TEST      R2 0         ; if not R2 then PC := 22
 16 [-]: JMP       22           ; PC := 22
 17 [-]: GETUPVAL  R2 U0        ; R2 := U0
 18 [-]: GETTABLE  R2 R2 K7     ; R2 := R2[0xe0cba3ca]
 19 [-]: MOVE      R3 R0        ; R3 := R0
 20 [-]: CALL      R2 2 1       ; R2(R3)
 21 [-]: RETURN    R0 1         ; return 
 22 [-]: NEWTABLE  R2 0 0       ; R2 := {}
 23 [-]: LOADKB    R3 1 0       ; R3 := true
 24 [-]: GETGLOBAL R4 K8        ; R4 := 0x59462acb
 25 [-]: SELF      R4 R4 K9     ; R5 := R4; R4 := R4[0xa2bbbcd1]
 26 [-]: CALL      R4 2 2       ; R4 := R4(R5)
 27 [-]: GETGLOBAL R5 K10       ; R5 := 0xbe190284
 28 [-]: SELF      R5 R5 K11    ; R6 := R5; R5 := R5[0xa1c390fe]
 29 [-]: CALL      R5 2 2       ; R5 := R5(R6)
 30 [-]: LOADKB    R6 0 0       ; R6 := false
 31 [-]: GETGLOBAL R7 K12       ; R7 := 0x33bdd652
 32 [-]: GETTABLE  R7 R7 K13    ; R7 := R7[0x23d5322f]
 33 [-]: MOVE      R8 R2        ; R8 := R2
 34 [-]: NEWTABLE  R9 0 2       ; R9 := {}
 35 [-]: GETGLOBAL R10 K0       ; R10 := 0xae91e43b
 36 [-]: SELF      R10 R10 K1   ; R11 := R10; R10 := R10[0x42b04007]
 37 [-]: LOADK     R12 K15      ; R12 := "/Lotus/Language/DojoPaints/DefaultBackdrop"
 38 [-]: LOADKB    R13 0 0      ; R13 := false
 39 [-]: CALL      R10 4 2      ; R10 := R10(R11,R12,R13)
 40 [-]: SETTABLE  R9 K14 R10   ; R9["Name"] := R10
 41 [-]: SETTABLE  R9 K16 K17   ; R9["ZoneId"] := ""
 42 [-]: CALL      R7 3 1       ; R7(R8,R9)
 43 [-]: CONST     R7 1         ; R7 := 1.000000
 44 [-]: LEN       R8 R4        ; R8 := # R4
 45 [-]: CONST     R9 1         ; R9 := 1.000000
 46 [-]: FORPREP   R7 115       ; R7 -= R9; PC := 115
 47 [-]: GETTABLE  R11 R4 R10   ; R11 := R4[R10]
 48 [-]: GETGLOBAL R12 K6       ; R12 := 0x7b998233
 49 [-]: MOVE      R13 R11      ; R13 := R11
 50 [-]: CALL      R12 2 2      ; R12 := R12(R13)
 51 [-]: TEST      R12 1        ; if R12 then PC := 115
 52 [-]: JMP       115          ; PC := 115
 53 [-]: SELF      R12 R5 K18   ; R13 := R5; R12 := R5[0x5458ba4c]
 54 [-]: GETGLOBAL R14 K19      ; R14 := 0x7ed0a956
 55 [-]: SELF      R15 R11 K20  ; R16 := R11; R15 := R11[0xed4e0128]
 56 [-]: CALL      R15 2 0      ; R15,... := R15(R16)
 57 [-]: CALL      R14 0 0      ; R14,... := R14(R15,...)
 58 [-]: CALL      R12 0 2      ; R12 := R12(R13,...)
 59 [-]: TEST      R3 0         ; if not R3 then PC := 73
 60 [-]: JMP       73           ; PC := 73
 61 [-]: GETGLOBAL R13 K21      ; R13 := _T
 62 [-]: GETTABLE  R13 R13 K22  ; R13 := R13["DojoMgr"]
 63 [-]: GETTABLE  R13 R13 K23  ; R13 := R13["mGameRules"]
 64 [-]: SELF      R13 R13 K24  ; R14 := R13; R13 := R13[0x953e625c]
 65 [-]: MOVE      R15 R11      ; R15 := R11
 66 [-]: CALL      R13 3 2      ; R13 := R13(R14,R15)
 67 [-]: TEST      R13 1        ; if R13 then PC := 74
 68 [-]: JMP       74           ; PC := 74
 69 [-]: SELF      R13 R12 K25  ; R14 := R12; R13 := R12[0x31e559d2]
 70 [-]: CALL      R13 2 2      ; R13 := R13(R14)
 71 [-]: JMP       74           ; PC := 74
 72 [-]: LOADKB    R13 0 1      ; R13 := false; PC := 73
 73 [-]: LOADKB    R13 1 0      ; R13 := true
 74 [-]: NEWTABLE  R14 0 11     ; R14 := {}
 75 [-]: GETGLOBAL R15 K0       ; R15 := 0xae91e43b
 76 [-]: SELF      R15 R15 K1   ; R16 := R15; R15 := R15[0x42b04007]
 77 [-]: SELF      R17 R12 K26  ; R18 := R12; R17 := R12[0xd3a9d01f]
 78 [-]: CALL      R17 2 2      ; R17 := R17(R18)
 79 [-]: SELF      R17 R17 K27  ; R18 := R17; R17 := R17[0x6d604ba7]
 80 [-]: CALL      R17 2 2      ; R17 := R17(R18)
 81 [-]: LOADKB    R18 0 0      ; R18 := false
 82 [-]: CALL      R15 4 2      ; R15 := R15(R16,R17,R18)
 83 [-]: SETTABLE  R14 K14 R15  ; R14["Name"] := R15
 84 [-]: SETTABLE  R14 K28 R11  ; R14["Type"] := R11
 85 [-]: SETTABLE  R14 K29 R12  ; R14["StoreItem"] := R12
 86 [-]: SETTABLE  R14 K30 K31  ; R14["HideOwnedTag"] := true
 87 [-]: SETTABLE  R14 K32 K17  ; R14["TileString"] := ""
 88 [-]: NOT       R15 R13      ; R15 :=  R13
 89 [-]: SETTABLE  R14 K33 R15  ; R14["Locked"] := R15
 90 [-]: SETTABLE  R14 K34 K35  ; R14["LockedTag"] := "/Lotus/Language/Menu/FocusLocked"
 91 [-]: SELF      R15 R12 K37  ; R16 := R12; R15 := R12[0x582843bc]
 92 [-]: CALL      R15 2 2      ; R15 := R15(R16)
 93 [-]: SELF      R15 R15 K27  ; R16 := R15; R15 := R15[0x6d604ba7]
 94 [-]: CALL      R15 2 2      ; R15 := R15(R16)
 95 [-]: SETTABLE  R14 K36 R15  ; R14[0xae91e43b] := R15
 96 [-]: SELF      R15 R11 K38  ; R16 := R11; R15 := R11[0x3fa26d2d]
 97 [-]: CALL      R15 2 2      ; R15 := R15(R16)
 98 [-]: SELF      R15 R15 K27  ; R16 := R15; R15 := R15[0x6d604ba7]
 99 [-]: CALL      R15 2 2      ; R15 := R15(R16)
100 [-]: SETTABLE  R14 K16 R15  ; R14["ZoneId"] := R15
101 [-]: SETTABLE  R14 K39 K31  ; R14["HidePrice"] := true
102 [-]: SETTABLE  R14 K40 K31  ; R14["HideRecipe"] := true
103 [-]: GETTABLE  R15 R14 K33  ; R15 := R14["Locked"]
104 [-]: TEST      R15 0        ; if not R15 then PC := 108
105 [-]: JMP       108          ; PC := 108
106 [-]: SETTABLE  R14 K41 K42  ; R14["Description"] := "/Lotus/Language/Dojo/BackdropLockedDesc"
107 [-]: JMP       110          ; PC := 110
108 [-]: LOADKB    R6 1 0       ; R6 := true
109 [-]: SETTABLE  R14 K41 K43  ; R14["Description"] := "/Lotus/Language/Dojo/BackdropOwnedDesc"
110 [-]: GETGLOBAL R15 K12      ; R15 := 0x33bdd652
111 [-]: GETTABLE  R15 R15 K13  ; R15 := R15[0x23d5322f]
112 [-]: MOVE      R16 R2       ; R16 := R2
113 [-]: MOVE      R17 R14      ; R17 := R14
114 [-]: CALL      R15 3 1      ; R15(R16,R17)
115 [-]: FORLOOP   R7 47        ; R7 += R9; if R7 <= R8 then begin PC := 47; R10 := R7 end
116 [-]: TEST      R6 1         ; if R6 then PC := 123
117 [-]: JMP       123          ; PC := 123
118 [-]: GETUPVAL  R15 U0       ; R15 := U0
119 [-]: GETTABLE  R15 R15 K7   ; R15 := R15[0xe0cba3ca]
120 [-]: LOADK     R16 K44      ; R16 := "/Lotus/Language/Dojo/BackdropSelectionLockedHint"
121 [-]: CALL      R15 2 1      ; R15(R16)
122 [-]: RETURN    R0 1         ; return 
123 [-]: GETGLOBAL R15 K0       ; R15 := 0xae91e43b
124 [-]: SELF      R15 R15 K45  ; R16 := R15; R15 := R15[0x1fd6abd0]
125 [-]: GETGLOBAL R17 K46      ; R17 := 0x0032441c
126 [-]: GETTABLE  R17 R17 K47  ; R17 := R17["UIMovie_ItemBrowsingMovie"]
127 [-]: CALL      R15 3 2      ; R15 := R15(R16,R17)
128 [-]: SELF      R16 R15 K48  ; R17 := R15; R16 := R15[0xe4162eed]
129 [-]: LOADK     R18 K49      ; R18 := "SetTitle"
130 [-]: GETGLOBAL R19 K50      ; R19 := 0x603636ad
131 [-]: LOADK     R20 K51      ; R20 := "/Lotus/Language/Dojo/BackdropSelectionTitle"
132 [-]: NEWTABLE  R21 0 0      ; R21 := {}
133 [-]: CALL      R19 3 0      ; R19,... := R19(R20,R21)
134 [-]: CALL      R16 0 1      ; R16(R17,...)
135 [-]: SELF      R16 R15 K48  ; R17 := R15; R16 := R15[0xe4162eed]
136 [-]: LOADK     R18 K52      ; R18 := "SetRequiredSelections"
137 [-]: CONST     R19 1        ; R19 := 1.000000
138 [-]: CALL      R16 4 1      ; R16(R17,R18,R19)
139 [-]: SELF      R16 R15 K48  ; R17 := R15; R16 := R15[0xe4162eed]
140 [-]: LOADK     R18 K53      ; R18 := "SetRequiresConfirmation"
141 [-]: LOADK     R19 K54      ; R19 := "false"
142 [-]: CALL      R16 4 1      ; R16(R17,R18,R19)
143 [-]: SELF      R16 R15 K48  ; R17 := R15; R16 := R15[0xe4162eed]
144 [-]: LOADK     R18 K55      ; R18 := "SetExitCallout"
145 [-]: LOADK     R19 K56      ; R19 := "/Lotus/Language/Menu/PhotoBoothSelection"
146 [-]: CALL      R16 4 1      ; R16(R17,R18,R19)
147 [-]: SELF      R16 R15 K48  ; R17 := R15; R16 := R15[0xe4162eed]
148 [-]: LOADK     R18 K57      ; R18 := "SetUseCornerForSelected"
149 [-]: LOADK     R19 K54      ; R19 := "false"
150 [-]: CALL      R16 4 1      ; R16(R17,R18,R19)
151 [-]: GETGLOBAL R16 K21      ; R16 := _T
152 [-]: CLOSURE   R17 0        ; R17 := closure(Function #36.1)
153 [-]: GETUPVAL  R0 U1        ; R0 := U1
154 [-]: SETTABLE  R16 K58 R17  ; R16["BrowseDone"] := R17
155 [-]: SELF      R16 R15 K48  ; R17 := R15; R16 := R15[0xe4162eed]
156 [-]: LOADK     R18 K59      ; R18 := "SetCallBack"
157 [-]: LOADK     R19 K58      ; R19 := "BrowseDone"
158 [-]: CALL      R16 4 1      ; R16(R17,R18,R19)
159 [-]: GETGLOBAL R16 K21      ; R16 := _T
160 [-]: CLOSURE   R17 1        ; R17 := closure(Function #36.2)
161 [-]: SETTABLE  R16 K60 R17  ; R16["GetBackdropSorting"] := R17
162 [-]: SELF      R16 R15 K48  ; R17 := R15; R16 := R15[0xe4162eed]
163 [-]: LOADK     R18 K61      ; R18 := "SetSortByFunction"
164 [-]: LOADK     R19 K60      ; R19 := "GetBackdropSorting"
165 [-]: CALL      R16 4 1      ; R16(R17,R18,R19)
166 [-]: GETGLOBAL R16 K21      ; R16 := _T
167 [-]: CLOSURE   R17 2        ; R17 := closure(Function #36.3)
168 [-]: MOVE      R0 R2        ; R0 := R2
169 [-]: SETTABLE  R16 K62 R17  ; R16["GetAllTiles"] := R17
170 [-]: SELF      R16 R15 K48  ; R17 := R15; R16 := R15[0xe4162eed]
171 [-]: LOADK     R18 K63      ; R18 := "SetElementsFunction"
172 [-]: LOADK     R19 K62      ; R19 := "GetAllTiles"
173 [-]: CALL      R16 4 1      ; R16(R17,R18,R19)
174 [-]: GETGLOBAL R16 K21      ; R16 := _T
175 [-]: CLOSURE   R17 3        ; R17 := closure(Function #36.4)
176 [-]: SETTABLE  R16 K64 R17  ; R16["ValidateSelection"] := R17
177 [-]: SELF      R16 R15 K48  ; R17 := R15; R16 := R15[0xe4162eed]
178 [-]: LOADK     R18 K65      ; R18 := "SetValidationFunction"
179 [-]: LOADK     R19 K64      ; R19 := "ValidateSelection"
180 [-]: CALL      R16 4 1      ; R16(R17,R18,R19)
181 [-]: RETURN    R15 2        ; return R15
182 [-]: RETURN    R0 1         ; return 


; Function #36.1:
;
; Name:            
; Defined at line: 732
; #Upvalues:       1
; #Parameters:     1
; Is_vararg:       0
; Max Stack Size:  4

  1 [-]: GETGLOBAL R1 K0        ; R1 := _T
  2 [-]: SETTABLE  R1 K1 K2     ; R1["ValidateTile"] := nil
  3 [-]: GETGLOBAL R1 K0        ; R1 := _T
  4 [-]: SETTABLE  R1 K3 K2     ; R1["BrowseDone"] := nil
  5 [-]: GETGLOBAL R1 K0        ; R1 := _T
  6 [-]: SETTABLE  R1 K4 K2     ; R1["GetAllTiles"] := nil
  7 [-]: GETGLOBAL R1 K0        ; R1 := _T
  8 [-]: SETTABLE  R1 K5 K2     ; R1["GetTileSorting"] := nil
  9 [-]: GETGLOBAL R1 K0        ; R1 := _T
 10 [-]: SETTABLE  R1 K6 K2     ; R1["ValidateSelection"] := nil
 11 [-]: GETGLOBAL R1 K0        ; R1 := _T
 12 [-]: SETTABLE  R1 K7 K2     ; R1["GetBackdropSorting"] := nil
 13 [-]: EQ        1 R0 K2      ; if R0 == nil then PC := 30
 14 [-]: JMP       30           ; PC := 30
 15 [-]: GETTABLE  R1 R0 K8     ; R1 := R0[1.000000]
 16 [-]: EQ        1 R1 K2      ; if R1 == nil then PC := 30
 17 [-]: JMP       30           ; PC := 30
 18 [-]: GETTABLE  R1 R0 K8     ; R1 := R0[1.000000]
 19 [-]: GETTABLE  R1 R1 K9     ; R1 := R1["Locked"]
 20 [-]: TEST      R1 1         ; if R1 then PC := 30
 21 [-]: JMP       30           ; PC := 30
 22 [-]: GETTABLE  R1 R0 K8     ; R1 := R0[1.000000]
 23 [-]: GETTABLE  R1 R1 K10    ; R1 := R1["ZoneId"]
 24 [-]: GETGLOBAL R2 K11       ; R2 := 0xd644c2f1
 25 [-]: MOVE      R3 R1        ; R3 := R1
 26 [-]: CALL      R2 2 1       ; R2(R3)
 27 [-]: GETUPVAL  R2 U0        ; R2 := U0
 28 [-]: MOVE      R3 R1        ; R3 := R1
 29 [-]: CALL      R2 2 1       ; R2(R3)
 30 [-]: RETURN    R0 1         ; return 


; Function #36.2:
;
; Name:            
; Defined at line: 750
; #Upvalues:       0
; #Parameters:     0
; Is_vararg:       0
; Max Stack Size:  5

  1 [-]: NEWTABLE  R0 0 0       ; R0 := {}
  2 [-]: GETGLOBAL R1 K0        ; R1 := 0x33bdd652
  3 [-]: GETTABLE  R1 R1 K1     ; R1 := R1[0x23d5322f]
  4 [-]: MOVE      R2 R0        ; R2 := R0
  5 [-]: NEWTABLE  R3 0 3       ; R3 := {}
  6 [-]: SETTABLE  R3 K2 K3     ; R3["Name"] := "NAME"
  7 [-]: SETTABLE  R3 K4 K3     ; R3["SortId"] := "NAME"
  8 [-]: CLOSURE   R4 0         ; R4 := closure(Function #36.2.1)
  9 [-]: SETTABLE  R3 K5 R4     ; R3["Attribute"] := R4
 10 [-]: CALL      R1 3 1       ; R1(R2,R3)
 11 [-]: MOVE      R1 R0        ; R1 := R0
 12 [-]: LOADK     R2 K3        ; R2 := "NAME"
 13 [-]: RETURN    R1 3         ; return R1,R2
 14 [-]: RETURN    R0 1         ; return 


; Function #36.2.1:
;
; Name:            
; Defined at line: 753
; #Upvalues:       0
; #Parameters:     2
; Is_vararg:       0
; Max Stack Size:  4

  1 [-]: GETTABLE  R2 R0 K0     ; R2 := R0["ZoneId"]
  2 [-]: EQ        0 R2 K1      ; if R2 ~= "" then PC := 7
  3 [-]: JMP       7            ; PC := 7
  4 [-]: LOADKB    R2 1 0       ; R2 := true
  5 [-]: RETURN    R2 2         ; return R2
  6 [-]: JMP       12           ; PC := 12
  7 [-]: GETTABLE  R2 R1 K0     ; R2 := R1["ZoneId"]
  8 [-]: EQ        0 R2 K1      ; if R2 ~= "" then PC := 12
  9 [-]: JMP       12           ; PC := 12
 10 [-]: LOADKB    R2 0 0       ; R2 := false
 11 [-]: RETURN    R2 2         ; return R2
 12 [-]: GETTABLE  R2 R0 K2     ; R2 := R0["Name"]
 13 [-]: GETTABLE  R3 R1 K2     ; R3 := R1["Name"]
 14 [-]: LT        1 R2 R3      ; if R2 < R3 then PC := 17
 15 [-]: JMP       17           ; PC := 17
 16 [-]: LOADKB    R2 0 1       ; R2 := false; PC := 17
 17 [-]: LOADKB    R2 1 0       ; R2 := true
 18 [-]: RETURN    R2 2         ; return R2
 19 [-]: RETURN    R0 1         ; return 


; Function #36.3:
;
; Name:            
; Defined at line: 767
; #Upvalues:       1
; #Parameters:     0
; Is_vararg:       0
; Max Stack Size:  2

  1 [-]: GETUPVAL  R0 U0        ; R0 := U0
  2 [-]: RETURN    R0 2         ; return R0
  3 [-]: RETURN    R0 1         ; return 


; Function #36.4:
;
; Name:            
; Defined at line: 773
; #Upvalues:       0
; #Parameters:     1
; Is_vararg:       0
; Max Stack Size:  3

  1 [-]: GETTABLE  R1 R0 K0     ; R1 := R0[1.000000]
  2 [-]: GETTABLE  R1 R1 K1     ; R1 := R1["Locked"]
  3 [-]: TEST      R1 0         ; if not R1 then PC := 7
  4 [-]: JMP       7            ; PC := 7
  5 [-]: LOADKB    R1 0 0       ; R1 := false
  6 [-]: RETURN    R1 2         ; return R1
  7 [-]: LOADKB    R1 1 0       ; R1 := true
  8 [-]: LOADK     R2 K2        ; R2 := ""
  9 [-]: RETURN    R1 3         ; return R1,R2
 10 [-]: RETURN    R0 1         ; return 


; Function #37:
;
; Name:            
; Defined at line: 784
; #Upvalues:       2
; #Parameters:     0
; Is_vararg:       0
; Max Stack Size:  2

  1 [-]: LOADKB    R0 0 0       ; R0 := false
  2 [-]: SETUPVAL  R0 U0        ; U82 := R0
  3 [-]: GETUPVAL  R0 U1        ; R0 := U1
  4 [-]: CALL      R0 1 1       ; R0()
  5 [-]: RETURN    R0 1         ; return 


; Function #38:
;
; Name:            
; Defined at line: 789
; #Upvalues:       1
; #Parameters:     0
; Is_vararg:       0
; Max Stack Size:  2

  1 [-]: GETUPVAL  R0 U0        ; R0 := U0
  2 [-]: CALL      R0 1 1       ; R0()
  3 [-]: RETURN    R0 1         ; return 


; Function #39:
;
; Name:            
; Defined at line: 793
; #Upvalues:       3
; #Parameters:     1
; Is_vararg:       0
; Max Stack Size:  19

  1 [-]: GETGLOBAL R1 K0        ; R1 := 0x03f57322
  2 [-]: MOVE      R2 R0        ; R2 := R0
  3 [-]: CALL      R1 2 2       ; R1 := R1(R2)
  4 [-]: EQ        0 R1 K2      ; if R1 ~= 4.000000 then PC := 57
  5 [-]: JMP       57           ; PC := 57
  6 [-]: GETGLOBAL R1 K3        ; R1 := _T
  7 [-]: GETTABLE  R1 R1 K4     ; R1 := R1["DojoMgr"]
  8 [-]: GETTABLE  R1 R1 K5     ; R1 := R1["mDojo"]
  9 [-]: SELF      R1 R1 K6     ; R2 := R1; R1 := R1[0x60d11ab9]
 10 [-]: GETUPVAL  R3 U0        ; R3 := U0
 11 [-]: CALL      R1 3 2       ; R1 := R1(R2,R3)
 12 [-]: NEWTABLE  R2 0 0       ; R2 := {}
 13 [-]: GETGLOBAL R3 K7        ; R3 := 0x89326c93
 14 [-]: SELF      R3 R3 K8     ; R4 := R3; R3 := R3[0xfb669000]
 15 [-]: GETGLOBAL R5 K9        ; R5 := 0x269759b4
 16 [-]: CALL      R3 3 2       ; R3 := R3(R4,R5)
 17 [-]: CONST     R4 1         ; R4 := 1.000000
 18 [-]: LEN       R5 R3        ; R5 := # R3
 19 [-]: CONST     R6 1         ; R6 := 1.000000
 20 [-]: FORPREP   R4 39        ; R4 -= R6; PC := 39
 21 [-]: GETTABLE  R8 R3 R7     ; R8 := R3[R7]
 22 [-]: GETGLOBAL R9 K3        ; R9 := _T
 23 [-]: GETTABLE  R9 R9 K4     ; R9 := R9["DojoMgr"]
 24 [-]: SELF      R9 R9 K10    ; R10 := R9; R9 := R9[0xd1964243]
 25 [-]: MOVE      R11 R8       ; R11 := R8
 26 [-]: CALL      R9 3 2       ; R9 := R9(R10,R11)
 27 [-]: GETTABLE  R10 R9 K11   ; R10 := R9["id"]
 28 [-]: SETTABLE  R2 R10 R8    ; R2[R10] := R8
 29 [-]: SELF      R10 R8 K12   ; R11 := R8; R10 := R8[0xc9f6a7d7]
 30 [-]: GETGLOBAL R12 K13      ; R12 := 0x98d8a736
 31 [-]: CALL      R10 3 2      ; R10 := R10(R11,R12)
 32 [-]: GETGLOBAL R11 K14      ; R11 := 0x7b998233
 33 [-]: MOVE      R12 R10      ; R12 := R10
 34 [-]: CALL      R11 2 2      ; R11 := R11(R12)
 35 [-]: TEST      R11 1        ; if R11 then PC := 39
 36 [-]: JMP       39           ; PC := 39
 37 [-]: SELF      R11 R10 K15  ; R12 := R10; R11 := R10[0xa2880940]
 38 [-]: CALL      R11 2 1      ; R11(R12)
 39 [-]: FORLOOP   R4 21        ; R4 += R6; if R4 <= R5 then begin PC := 21; R7 := R4 end
 40 [-]: CONST     R11 1        ; R11 := 1.000000
 41 [-]: LEN       R12 R1       ; R12 := # R1
 42 [-]: CONST     R13 1        ; R13 := 1.000000
 43 [-]: FORPREP   R11 56       ; R11 -= R13; PC := 56
 44 [-]: GETGLOBAL R15 K14      ; R15 := 0x7b998233
 45 [-]: GETTABLE  R16 R1 R14   ; R16 := R1[R14]
 46 [-]: GETTABLE  R16 R2 R16   ; R16 := R2[R16]
 47 [-]: CALL      R15 2 2      ; R15 := R15(R16)
 48 [-]: TEST      R15 1        ; if R15 then PC := 56
 49 [-]: JMP       56           ; PC := 56
 50 [-]: GETTABLE  R15 R1 R14   ; R15 := R1[R14]
 51 [-]: GETTABLE  R15 R2 R15   ; R15 := R2[R15]
 52 [-]: SELF      R15 R15 K16  ; R16 := R15; R15 := R15[0x47901f07]
 53 [-]: GETGLOBAL R17 K13      ; R17 := 0x98d8a736
 54 [-]: GETGLOBAL R18 K17      ; R18 := EMPTY_SYMBOL
 55 [-]: CALL      R15 4 1      ; R15(R16,R17,R18)
 56 [-]: FORLOOP   R11 44       ; R11 += R13; if R11 <= R12 then begin PC := 44; R14 := R11 end
 57 [-]: LOADKB    R15 0 0      ; R15 := false
 58 [-]: SETUPVAL  R15 U1       ; U82 := R1
 59 [-]: GETUPVAL  R15 U2       ; R15 := U2
 60 [-]: CALL      R15 1 1      ; R15()
 61 [-]: RETURN    R0 1         ; return 


; Function #40:
;
; Name:            
; Defined at line: 823
; #Upvalues:       4
; #Parameters:     0
; Is_vararg:       0
; Max Stack Size:  6

  1 [-]: GETUPVAL  R0 U0        ; R0 := U0
  2 [-]: LOADKB    R1 0 0       ; R1 := false
  3 [-]: LOADKB    R2 1 0       ; R2 := true
  4 [-]: SETUPVAL  R2 U1        ; U82 := R1
  5 [-]: LOADK     R2 K0        ; R2 := ""
  6 [-]: EQ        0 R0 K2      ; if R0 ~= 0.000000 then PC := 10
  7 [-]: JMP       10           ; PC := 10
  8 [-]: LOADK     R2 K3        ; R2 := "/Lotus/Language/Dojo/QueueDestructionSuccess"
  9 [-]: JMP       48           ; PC := 48
 10 [-]: EQ        0 R0 K4      ; if R0 ~= -1.000000 then PC := 14
 11 [-]: JMP       14           ; PC := 14
 12 [-]: LOADK     R2 K5        ; R2 := "/Lotus/Language/Dojo/Generic_INVALID_PERMISSION"
 13 [-]: JMP       48           ; PC := 48
 14 [-]: EQ        0 R0 K6      ; if R0 ~= 7.000000 then PC := 18
 15 [-]: JMP       18           ; PC := 18
 16 [-]: LOADK     R2 K7        ; R2 := "/Lotus/Language/Dojo/QueueDestructionFail_COMPONENT_NOT_FOUND"
 17 [-]: JMP       48           ; PC := 48
 18 [-]: EQ        0 R0 K8      ; if R0 ~= 4.000000 then PC := 22
 19 [-]: JMP       22           ; PC := 22
 20 [-]: LOADK     R2 K9        ; R2 := "/Lotus/Language/Dojo/QueueDestructionFail_INSUFFICIENT_ENERGY"
 21 [-]: JMP       48           ; PC := 48
 22 [-]: EQ        0 R0 K10     ; if R0 ~= 5.000000 then PC := 26
 23 [-]: JMP       26           ; PC := 26
 24 [-]: LOADK     R2 K11       ; R2 := "/Lotus/Language/Dojo/QueueDestructionFail_INSUFFICIENT_CAPACITY"
 25 [-]: JMP       48           ; PC := 48
 26 [-]: EQ        0 R0 K12     ; if R0 ~= 6.000000 then PC := 30
 27 [-]: JMP       30           ; PC := 30
 28 [-]: LOADK     R2 K13       ; R2 := "/Lotus/Language/Dojo/QueueDestructionFail_MISSING_PREREQ"
 29 [-]: JMP       48           ; PC := 48
 30 [-]: EQ        0 R0 K14     ; if R0 ~= 13.000000 then PC := 35
 31 [-]: JMP       35           ; PC := 35
 32 [-]: LOADK     R2 K15       ; R2 := "/Lotus/Language/Dojo/QueueDestructionFail_HAS_CHILD"
 33 [-]: LOADKB    R1 1 0       ; R1 := true
 34 [-]: JMP       48           ; PC := 48
 35 [-]: EQ        0 R0 K16     ; if R0 ~= 14.000000 then PC := 39
 36 [-]: JMP       39           ; PC := 39
 37 [-]: LOADK     R2 K17       ; R2 := "/Lotus/Language/Dojo/QueueDestructionFail_DESTRUCTION_ALREADY_QUEUED"
 38 [-]: JMP       48           ; PC := 48
 39 [-]: EQ        0 R0 K18     ; if R0 ~= 15.000000 then PC := 43
 40 [-]: JMP       43           ; PC := 43
 41 [-]: LOADK     R2 K19       ; R2 := "/Lotus/Language/Dojo/QueueDestructionFail_NOT_QUEUED_FOR_DESTRUCTION"
 42 [-]: JMP       48           ; PC := 48
 43 [-]: EQ        0 R0 K20     ; if R0 ~= 8.000000 then PC := 47
 44 [-]: JMP       47           ; PC := 47
 45 [-]: LOADK     R2 K21       ; R2 := "/Lotus/Language/Dojo/QueueDestructionFail_CONSTRUCTION_STARTED"
 46 [-]: JMP       48           ; PC := 48
 47 [-]: LOADK     R2 K22       ; R2 := "/Lotus/Language/Dojo/QueueDestructionFail_UNKNOWN_ERROR"
 48 [-]: GETGLOBAL R3 K23       ; R3 := 0x7f5022cf
 49 [-]: GETTABLE  R3 R3 K24    ; R3 := R3[0x41e2ae25]
 50 [-]: MOVE      R4 R2        ; R4 := R2
 51 [-]: CALL      R3 2 2       ; R3 := R3(R4)
 52 [-]: LT        0 K2 R3      ; if 0.000000 >= R3 then PC := 63
 53 [-]: JMP       63           ; PC := 63
 54 [-]: TEST      R1 0         ; if not R1 then PC := 58
 55 [-]: JMP       58           ; PC := 58
 56 [-]: SETUPVAL  R2 U2        ; U82 := R2
 57 [-]: JMP       63           ; PC := 63
 58 [-]: GETUPVAL  R3 U3        ; R3 := U3
 59 [-]: GETTABLE  R3 R3 K25    ; R3 := R3[0xe0cba3ca]
 60 [-]: MOVE      R4 R2        ; R4 := R2
 61 [-]: LOADK     R5 K26       ; R5 := "ConfirmationReviewed"
 62 [-]: CALL      R3 3 1       ; R3(R4,R5)
 63 [-]: RETURN    R0 1         ; return 


; Function #41:
;
; Name:            
; Defined at line: 867
; #Upvalues:       2
; #Parameters:     2
; Is_vararg:       0
; Max Stack Size:  6

  1 [-]: SETUPVAL  R0 U0        ; U82 := R0
  2 [-]: SETUPVAL  R1 U1        ; U82 := R1
  3 [-]: GETGLOBAL R2 K0        ; R2 := 0xae91e43b
  4 [-]: SELF      R2 R2 K1     ; R3 := R2; R2 := R2[0xe4162eed]
  5 [-]: LOADK     R4 K2        ; R4 := "ComponentDestructionQueued"
  6 [-]: LOADK     R5 K3        ; R5 := ""
  7 [-]: CALL      R2 4 1       ; R2(R3,R4,R5)
  8 [-]: RETURN    R0 1         ; return 


; Function #42:
;
; Name:            
; Defined at line: 873
; #Upvalues:       6
; #Parameters:     0
; Is_vararg:       0
; Max Stack Size:  9

  1 [-]: LOADKB    R0 1 0       ; R0 := true
  2 [-]: SETUPVAL  R0 U0        ; U82 := R0
  3 [-]: GETGLOBAL R0 K0        ; R0 := 0x59462acb
  4 [-]: SELF      R0 R0 K1     ; R1 := R0; R0 := R0[0x56595420]
  5 [-]: GETUPVAL  R2 U1        ; R2 := U1
  6 [-]: GETTABLE  R2 R2 K2     ; R2 := R2["prefab"]
  7 [-]: CALL      R0 3 2       ; R0 := R0(R1,R2)
  8 [-]: GETUPVAL  R1 U2        ; R1 := U2
  9 [-]: GETUPVAL  R2 U3        ; R2 := U3
 10 [-]: MOVE      R3 R0        ; R3 := R0
 11 [-]: CALL      R1 3 2       ; R1 := R1(R2,R3)
 12 [-]: EQ        0 R1 K4      ; if R1 ~= 0.000000 then PC := 39
 13 [-]: JMP       39           ; PC := 39
 14 [-]: SELF      R2 R0 K5     ; R3 := R0; R2 := R0[0xe6a4276c]
 15 [-]: CALL      R2 2 2       ; R2 := R2(R3)
 16 [-]: EQ        0 R2 K6      ; if R2 ~= 1.000000 then PC := 25
 17 [-]: JMP       25           ; PC := 25
 18 [-]: GETUPVAL  R3 U4        ; R3 := U4
 19 [-]: GETTABLE  R3 R3 K7     ; R3 := R3[0xe0cba3ca]
 20 [-]: LOADK     R4 K8        ; R4 := "/Lotus/Language/Dojo/QueueDestructionConfirmFullRefund"
 21 [-]: LOADK     R5 K9        ; R5 := "ConfirmQueueDestruction"
 22 [-]: CONST     R6 1         ; R6 := 1.000000
 23 [-]: CALL      R3 4 1       ; R3(R4,R5,R6)
 24 [-]: JMP       52           ; PC := 52
 25 [-]: NEWTABLE  R3 0 1       ; R3 := {}
 26 [-]: MUL       R4 R2 K12    ; R4 := R2 * 100.000000
 27 [-]: SETTABLE  R3 K11 R4    ; R3["PERCENT"] := R4
 28 [-]: GETGLOBAL R4 K13       ; R4 := 0x603636ad
 29 [-]: LOADK     R5 K14       ; R5 := "/Lotus/Language/Dojo/QueueDestructionConfirmWithRefundPercentage"
 30 [-]: MOVE      R6 R3        ; R6 := R3
 31 [-]: CALL      R4 3 2       ; R4 := R4(R5,R6)
 32 [-]: GETUPVAL  R5 U4        ; R5 := U4
 33 [-]: GETTABLE  R5 R5 K7     ; R5 := R5[0xe0cba3ca]
 34 [-]: MOVE      R6 R4        ; R6 := R4
 35 [-]: LOADK     R7 K9        ; R7 := "ConfirmQueueDestruction"
 36 [-]: CONST     R8 1         ; R8 := 1.000000
 37 [-]: CALL      R5 4 1       ; R5(R6,R7,R8)
 38 [-]: JMP       52           ; PC := 52
 39 [-]: EQ        0 R1 K15     ; if R1 ~= 8.000000 then PC := 48
 40 [-]: JMP       48           ; PC := 48
 41 [-]: GETUPVAL  R5 U4        ; R5 := U4
 42 [-]: GETTABLE  R5 R5 K7     ; R5 := R5[0xe0cba3ca]
 43 [-]: LOADK     R6 K16       ; R6 := "/Lotus/Language/Dojo/QueueDestructionConfirmSolarRailRefund"
 44 [-]: LOADK     R7 K9        ; R7 := "ConfirmQueueDestruction"
 45 [-]: CONST     R8 1         ; R8 := 1.000000
 46 [-]: CALL      R5 4 1       ; R5(R6,R7,R8)
 47 [-]: JMP       52           ; PC := 52
 48 [-]: GETUPVAL  R5 U5        ; R5 := U5
 49 [-]: MOVE      R6 R1        ; R6 := R1
 50 [-]: LOADK     R7 K17       ; R7 := ""
 51 [-]: CALL      R5 3 1       ; R5(R6,R7)
 52 [-]: RETURN    R0 1         ; return 


; Function #43:
;
; Name:            
; Defined at line: 895
; #Upvalues:       2
; #Parameters:     2
; Is_vararg:       0
; Max Stack Size:  6

  1 [-]: EQ        1 R0 K1      ; if R0 == 0.000000 then PC := 34
  2 [-]: JMP       34           ; PC := 34
  3 [-]: LOADKB    R2 1 0       ; R2 := true
  4 [-]: SETUPVAL  R2 U0        ; U82 := R0
  5 [-]: LOADK     R2 K2        ; R2 := ""
  6 [-]: EQ        0 R0 K3      ; if R0 ~= -1.000000 then PC := 10
  7 [-]: JMP       10           ; PC := 10
  8 [-]: LOADK     R2 K4        ; R2 := "/Lotus/Language/Dojo/Generic_INVALID_PERMISSION"
  9 [-]: JMP       23           ; PC := 23
 10 [-]: EQ        0 R0 K5      ; if R0 ~= 6.000000 then PC := 14
 11 [-]: JMP       14           ; PC := 14
 12 [-]: LOADK     R2 K6        ; R2 := "/Lotus/Language/Dojo/ConvertRoomFail_MISSING_PREREQ"
 13 [-]: JMP       23           ; PC := 23
 14 [-]: EQ        0 R0 K7      ; if R0 ~= 12.000000 then PC := 18
 15 [-]: JMP       18           ; PC := 18
 16 [-]: LOADK     R2 K8        ; R2 := "/Lotus/Language/Dojo/ConvertRoomFail_ALREADY_COMPLETED"
 17 [-]: JMP       23           ; PC := 23
 18 [-]: EQ        0 R0 K9      ; if R0 ~= 13.000000 then PC := 22
 19 [-]: JMP       22           ; PC := 22
 20 [-]: LOADK     R2 K10       ; R2 := "/Lotus/Language/Dojo/ConvertRoomFail_HAS_CHILD"
 21 [-]: JMP       23           ; PC := 23
 22 [-]: LOADK     R2 K11       ; R2 := "/Lotus/Language/Dojo/ConvertRoomFail_UNKNOWN_ERROR"
 23 [-]: GETGLOBAL R3 K12       ; R3 := 0x7f5022cf
 24 [-]: GETTABLE  R3 R3 K13    ; R3 := R3[0x41e2ae25]
 25 [-]: MOVE      R4 R2        ; R4 := R2
 26 [-]: CALL      R3 2 2       ; R3 := R3(R4)
 27 [-]: LT        0 K1 R3      ; if 0.000000 >= R3 then PC := 34
 28 [-]: JMP       34           ; PC := 34
 29 [-]: GETUPVAL  R3 U1        ; R3 := U1
 30 [-]: GETTABLE  R3 R3 K14    ; R3 := R3[0xe0cba3ca]
 31 [-]: MOVE      R4 R2        ; R4 := R2
 32 [-]: LOADK     R5 K15       ; R5 := "ConfirmationReviewed"
 33 [-]: CALL      R3 3 1       ; R3(R4,R5)
 34 [-]: RETURN    R0 1         ; return 


; Function #44:
;
; Name:            
; Defined at line: 919
; #Upvalues:       2
; #Parameters:     1
; Is_vararg:       0
; Max Stack Size:  4

  1 [-]: LOADKB    R1 0 0       ; R1 := false
  2 [-]: SETUPVAL  R1 U0        ; U82 := R0
  3 [-]: GETGLOBAL R1 K0        ; R1 := 0x03f57322
  4 [-]: MOVE      R2 R0        ; R2 := R0
  5 [-]: CALL      R1 2 2       ; R1 := R1(R2)
  6 [-]: EQ        0 R1 K2      ; if R1 ~= 4.000000 then PC := 13
  7 [-]: JMP       13           ; PC := 13
  8 [-]: GETGLOBAL R1 K3        ; R1 := _T
  9 [-]: GETTABLE  R1 R1 K4     ; R1 := R1["DojoMgr"]
 10 [-]: SELF      R1 R1 K5     ; R2 := R1; R1 := R1[0xeba59743]
 11 [-]: GETUPVAL  R3 U1        ; R3 := U1
 12 [-]: CALL      R1 3 1       ; R1(R2,R3)
 13 [-]: RETURN    R0 1         ; return 


; Function #45:
;
; Name:            
; Defined at line: 926
; #Upvalues:       3
; #Parameters:     0
; Is_vararg:       0
; Max Stack Size:  4

  1 [-]: LOADKB    R0 1 0       ; R0 := true
  2 [-]: SETUPVAL  R0 U0        ; U82 := R0
  3 [-]: GETUPVAL  R0 U1        ; R0 := U1
  4 [-]: GETTABLE  R0 R0 K0     ; R0 := R0["placedDecos"]
  5 [-]: LEN       R0 R0        ; R0 := # R0
  6 [-]: LT        0 K1 R0      ; if 0.000000 >= R0 then PC := 14
  7 [-]: JMP       14           ; PC := 14
  8 [-]: GETUPVAL  R0 U2        ; R0 := U2
  9 [-]: GETTABLE  R0 R0 K2     ; R0 := R0[0xe0cba3ca]
 10 [-]: LOADK     R1 K3        ; R1 := "/Lotus/Language/Dojo/ConvertRoomFail_MISSING_PREREQ"
 11 [-]: LOADK     R2 K4        ; R2 := "ConfirmationReviewed"
 12 [-]: CALL      R0 3 1       ; R0(R1,R2)
 13 [-]: JMP       20           ; PC := 20
 14 [-]: GETUPVAL  R0 U2        ; R0 := U2
 15 [-]: GETTABLE  R0 R0 K2     ; R0 := R0[0xe0cba3ca]
 16 [-]: LOADK     R1 K5        ; R1 := "/Lotus/Language/Dojo/ConvertRoomConfirm"
 17 [-]: LOADK     R2 K6        ; R2 := "ConfirmRoomConvert"
 18 [-]: CONST     R3 1         ; R3 := 1.000000
 19 [-]: CALL      R0 4 1       ; R0(R1,R2,R3)
 20 [-]: RETURN    R0 1         ; return 


; Function #46:
;
; Name:            
; Defined at line: 936
; #Upvalues:       5
; #Parameters:     1
; Is_vararg:       0
; Max Stack Size:  5

  1 [-]: LOADKB    R1 0 0       ; R1 := false
  2 [-]: SETUPVAL  R1 U0        ; U82 := R0
  3 [-]: GETGLOBAL R1 K0        ; R1 := 0x03f57322
  4 [-]: MOVE      R2 R0        ; R2 := R0
  5 [-]: CALL      R1 2 2       ; R1 := R1(R2)
  6 [-]: EQ        0 R1 K2      ; if R1 ~= 4.000000 then PC := 19
  7 [-]: JMP       19           ; PC := 19
  8 [-]: LOADKB    R1 1 0       ; R1 := true
  9 [-]: SETUPVAL  R1 U1        ; U82 := R1
 10 [-]: GETUPVAL  R1 U2        ; R1 := U2
 11 [-]: CALL      R1 1 1       ; R1()
 12 [-]: GETGLOBAL R1 K3        ; R1 := _T
 13 [-]: GETTABLE  R1 R1 K4     ; R1 := R1["DojoMgr"]
 14 [-]: SELF      R1 R1 K5     ; R2 := R1; R1 := R1[0xfa19f3c0]
 15 [-]: GETUPVAL  R3 U3        ; R3 := U3
 16 [-]: GETTABLE  R3 R3 K6     ; R3 := R3["id"]
 17 [-]: GETUPVAL  R4 U4        ; R4 := U4
 18 [-]: CALL      R1 4 1       ; R1(R2,R3,R4)
 19 [-]: RETURN    R0 1         ; return 


; Function #47:
;
; Name:            
; Defined at line: 945
; #Upvalues:       3
; #Parameters:     0
; Is_vararg:       0
; Max Stack Size:  5

  1 [-]: GETUPVAL  R0 U0        ; R0 := U0
  2 [-]: LOADKB    R1 1 0       ; R1 := true
  3 [-]: SETUPVAL  R1 U1        ; U82 := R1
  4 [-]: LOADK     R1 K0        ; R1 := ""
  5 [-]: EQ        0 R0 K2      ; if R0 ~= 0.000000 then PC := 9
  6 [-]: JMP       9            ; PC := 9
  7 [-]: LOADK     R1 K3        ; R1 := "/Lotus/Language/Dojo/DestructionCancelSuccess"
  8 [-]: JMP       26           ; PC := 26
  9 [-]: EQ        0 R0 K4      ; if R0 ~= -1.000000 then PC := 13
 10 [-]: JMP       13           ; PC := 13
 11 [-]: LOADK     R1 K5        ; R1 := "/Lotus/Language/Dojo/Generic_INVALID_PERMISSION"
 12 [-]: JMP       26           ; PC := 26
 13 [-]: EQ        0 R0 K6      ; if R0 ~= 7.000000 then PC := 17
 14 [-]: JMP       17           ; PC := 17
 15 [-]: LOADK     R1 K7        ; R1 := "/Lotus/Language/Dojo/QueueDestructionFail_COMPONENT_NOT_FOUND"
 16 [-]: JMP       26           ; PC := 26
 17 [-]: EQ        0 R0 K8      ; if R0 ~= 15.000000 then PC := 21
 18 [-]: JMP       21           ; PC := 21
 19 [-]: LOADK     R1 K9        ; R1 := "/Lotus/Language/Dojo/DestructionCancelFail_NOT_QUEUED_FOR_DESTRUCTION"
 20 [-]: JMP       26           ; PC := 26
 21 [-]: EQ        0 R0 K10     ; if R0 ~= 16.000000 then PC := 25
 22 [-]: JMP       25           ; PC := 25
 23 [-]: LOADK     R1 K11       ; R1 := "/Lotus/Language/Dojo/DestructionCancelFail_COMPONENT_DESTROYED"
 24 [-]: JMP       26           ; PC := 26
 25 [-]: LOADK     R1 K12       ; R1 := "/Lotus/Language/Dojo/DestructionCancelFail_UNKNOWN_ERROR"
 26 [-]: GETGLOBAL R2 K13       ; R2 := 0x7f5022cf
 27 [-]: GETTABLE  R2 R2 K14    ; R2 := R2[0x41e2ae25]
 28 [-]: MOVE      R3 R1        ; R3 := R1
 29 [-]: CALL      R2 2 2       ; R2 := R2(R3)
 30 [-]: LT        0 K2 R2      ; if 0.000000 >= R2 then PC := 37
 31 [-]: JMP       37           ; PC := 37
 32 [-]: GETUPVAL  R2 U2        ; R2 := U2
 33 [-]: GETTABLE  R2 R2 K15    ; R2 := R2[0xe0cba3ca]
 34 [-]: MOVE      R3 R1        ; R3 := R1
 35 [-]: LOADK     R4 K16       ; R4 := "ConfirmationReviewed"
 36 [-]: CALL      R2 3 1       ; R2(R3,R4)
 37 [-]: RETURN    R0 1         ; return 


; Function #48:
;
; Name:            
; Defined at line: 972
; #Upvalues:       2
; #Parameters:     2
; Is_vararg:       0
; Max Stack Size:  6

  1 [-]: SETUPVAL  R0 U0        ; U82 := R0
  2 [-]: SETUPVAL  R1 U1        ; U82 := R1
  3 [-]: GETGLOBAL R2 K0        ; R2 := 0xae91e43b
  4 [-]: SELF      R2 R2 K1     ; R3 := R2; R2 := R2[0xe4162eed]
  5 [-]: LOADK     R4 K2        ; R4 := "ComponentDestructionCancelled"
  6 [-]: LOADK     R5 K3        ; R5 := ""
  7 [-]: CALL      R2 4 1       ; R2(R3,R4,R5)
  8 [-]: RETURN    R0 1         ; return 


; Function #49:
;
; Name:            
; Defined at line: 978
; #Upvalues:       2
; #Parameters:     0
; Is_vararg:       0
; Max Stack Size:  4

  1 [-]: LOADKB    R0 1 0       ; R0 := true
  2 [-]: SETUPVAL  R0 U0        ; U82 := R0
  3 [-]: GETUPVAL  R0 U1        ; R0 := U1
  4 [-]: GETTABLE  R0 R0 K0     ; R0 := R0[0xe0cba3ca]
  5 [-]: LOADK     R1 K1        ; R1 := "/Lotus/Language/Dojo/CancelDestructionConfirm"
  6 [-]: LOADK     R2 K2        ; R2 := "ConfirmDestructionCancel"
  7 [-]: CONST     R3 1         ; R3 := 1.000000
  8 [-]: CALL      R0 4 1       ; R0(R1,R2,R3)
  9 [-]: RETURN    R0 1         ; return 


; Function #50:
;
; Name:            
; Defined at line: 983
; #Upvalues:       4
; #Parameters:     1
; Is_vararg:       0
; Max Stack Size:  5

  1 [-]: LOADKB    R1 0 0       ; R1 := false
  2 [-]: SETUPVAL  R1 U0        ; U82 := R0
  3 [-]: GETGLOBAL R1 K0        ; R1 := 0x03f57322
  4 [-]: MOVE      R2 R0        ; R2 := R0
  5 [-]: CALL      R1 2 2       ; R1 := R1(R2)
  6 [-]: EQ        0 R1 K2      ; if R1 ~= 4.000000 then PC := 17
  7 [-]: JMP       17           ; PC := 17
  8 [-]: LOADKB    R1 1 0       ; R1 := true
  9 [-]: SETUPVAL  R1 U1        ; U82 := R1
 10 [-]: GETGLOBAL R1 K3        ; R1 := _T
 11 [-]: GETTABLE  R1 R1 K4     ; R1 := R1["DojoMgr"]
 12 [-]: SELF      R1 R1 K5     ; R2 := R1; R1 := R1[0x712365e9]
 13 [-]: GETUPVAL  R3 U2        ; R3 := U2
 14 [-]: GETTABLE  R3 R3 K6     ; R3 := R3["id"]
 15 [-]: GETUPVAL  R4 U3        ; R4 := U3
 16 [-]: CALL      R1 4 1       ; R1(R2,R3,R4)
 17 [-]: RETURN    R0 1         ; return 


; Function #51:
;
; Name:            
; Defined at line: 991
; #Upvalues:       1
; #Parameters:     0
; Is_vararg:       0
; Max Stack Size:  2

  1 [-]: GETUPVAL  R0 U0        ; R0 := U0
  2 [-]: CALL      R0 1 1       ; R0()
  3 [-]: RETURN    R0 1         ; return 


; Function #52:
;
; Name:            
; Defined at line: 995
; #Upvalues:       4
; #Parameters:     0
; Is_vararg:       0
; Max Stack Size:  3

  1 [-]: GETGLOBAL R0 K0        ; R0 := 0x7b998233
  2 [-]: GETGLOBAL R1 K1        ; R1 := _T
  3 [-]: GETTABLE  R1 R1 K2     ; R1 := R1["DojoMgr"]
  4 [-]: CALL      R0 2 2       ; R0 := R0(R1)
  5 [-]: TEST      R0 0         ; if not R0 then PC := 13
  6 [-]: JMP       13           ; PC := 13
  7 [-]: GETUPVAL  R0 U0        ; R0 := U0
  8 [-]: GETTABLE  R0 R0 K3     ; R0 := R0[0xe0cba3ca]
  9 [-]: LOADK     R1 K4        ; R1 := "/Lotus/Language/Dojo/UnableToUseConsole"
 10 [-]: LOADK     R2 K5        ; R2 := "OnErrorExitConsole"
 11 [-]: CALL      R0 3 1       ; R0(R1,R2)
 12 [-]: RETURN    R0 1         ; return 
 13 [-]: GETGLOBAL R0 K1        ; R0 := _T
 14 [-]: GETTABLE  R0 R0 K2     ; R0 := R0["DojoMgr"]
 15 [-]: GETTABLE  R0 R0 K6     ; R0 := R0["mDojo"]
 16 [-]: SELF      R0 R0 K7     ; R1 := R0; R0 := R0[0x5c69b193]
 17 [-]: GETUPVAL  R2 U1        ; R2 := U1
 18 [-]: CALL      R0 3 2       ; R0 := R0(R1,R2)
 19 [-]: GETTABLE  R1 R0 K8     ; R1 := R0["prefab"]
 20 [-]: GETGLOBAL R2 K9        ; R2 := 0x68d4b882
 21 [-]: EQ        0 R1 R2      ; if R1 ~= R2 then PC := 28
 22 [-]: JMP       28           ; PC := 28
 23 [-]: GETUPVAL  R1 U0        ; R1 := U0
 24 [-]: GETTABLE  R1 R1 K3     ; R1 := R1[0xe0cba3ca]
 25 [-]: LOADK     R2 K10       ; R2 := "/Lotus/Language/Dojo/NoDecorationsInObstacleCourse"
 26 [-]: CALL      R1 2 1       ; R1(R2)
 27 [-]: RETURN    R0 1         ; return 
 28 [-]: GETGLOBAL R1 K1        ; R1 := _T
 29 [-]: SETTABLE  R1 K11 K12   ; R1["ShowShipDecos"] := false
 30 [-]: GETGLOBAL R1 K1        ; R1 := _T
 31 [-]: SETTABLE  R1 K13 K12   ; R1["VaultDeco"] := false
 32 [-]: LOADKB    R1 1 0       ; R1 := true
 33 [-]: SETUPVAL  R1 U2        ; U82 := R2
 34 [-]: GETUPVAL  R1 U3        ; R1 := U3
 35 [-]: CALL      R1 1 1       ; R1()
 36 [-]: RETURN    R0 1         ; return 


; Function #53:
;
; Name:            
; Defined at line: 1013
; #Upvalues:       1
; #Parameters:     1
; Is_vararg:       0
; Max Stack Size:  34

  1 [-]: SELF      R1 R0 K0     ; R2 := R0; R1 := R0[0xe79e7ef4]
  2 [-]: CALL      R1 2 2       ; R1 := R1(R2)
  3 [-]: SELF      R1 R1 K1     ; R2 := R1; R1 := R1[0x7d05e45f]
  4 [-]: CALL      R1 2 2       ; R1 := R1(R2)
  5 [-]: GETGLOBAL R2 K2        ; R2 := _T
  6 [-]: GETTABLE  R2 R2 K3     ; R2 := R2["DojoMgr"]
  7 [-]: SELF      R2 R2 K4     ; R3 := R2; R2 := R2[0xd1964243]
  8 [-]: MOVE      R4 R1        ; R4 := R1
  9 [-]: CALL      R2 3 2       ; R2 := R2(R3,R4)
 10 [-]: GETTABLE  R3 R2 K5     ; R3 := R2["id"]
 11 [-]: SELF      R4 R0 K6     ; R5 := R0; R4 := R0[0x5b89142c]
 12 [-]: CALL      R4 2 2       ; R4 := R4(R5)
 13 [-]: GETGLOBAL R5 K7        ; R5 := 0xcfc01047
 14 [-]: GETGLOBAL R6 K2        ; R6 := _T
 15 [-]: GETTABLE  R6 R6 K3     ; R6 := R6["DojoMgr"]
 16 [-]: GETTABLE  R6 R6 K8     ; R6 := R6["mIdToPlacedDecos"]
 17 [-]: GETTABLE  R6 R6 R3     ; R6 := R6[R3]
 18 [-]: CALL      R5 2 4       ; R5,R6,R7 := R5(R6)
 19 [-]: JMP       68           ; PC := 68
 20 [-]: GETGLOBAL R10 K9       ; R10 := 0x7b998233
 21 [-]: MOVE      R11 R9       ; R11 := R9
 22 [-]: CALL      R10 2 2      ; R10 := R10(R11)
 23 [-]: TEST      R10 1        ; if R10 then PC := 68
 24 [-]: JMP       68           ; PC := 68
 25 [-]: GETGLOBAL R10 K2       ; R10 := _T
 26 [-]: GETTABLE  R10 R10 K3   ; R10 := R10["DojoMgr"]
 27 [-]: GETTABLE  R10 R10 K10  ; R10 := R10["mDojo"]
 28 [-]: SELF      R10 R10 K11  ; R11 := R10; R10 := R10[0x40063309]
 29 [-]: MOVE      R12 R3       ; R12 := R3
 30 [-]: CALL      R10 3 2      ; R10 := R10(R11,R12)
 31 [-]: SELF      R10 R10 K12  ; R11 := R10; R10 := R10[0x656c098f]
 32 [-]: MOVE      R12 R8       ; R12 := R8
 33 [-]: CALL      R10 3 2      ; R10 := R10(R11,R12)
 34 [-]: SELF      R11 R10 K13  ; R12 := R10; R11 := R10[0x3ae915ba]
 35 [-]: CALL      R11 2 2      ; R11 := R11(R12)
 36 [-]: TEST      R11 1        ; if R11 then PC := 42
 37 [-]: JMP       42           ; PC := 42
 38 [-]: SELF      R11 R10 K14  ; R12 := R10; R11 := R10[0x04de00e9]
 39 [-]: CALL      R11 2 2      ; R11 := R11(R12)
 40 [-]: TEST      R11 0        ; if not R11 then PC := 68
 41 [-]: JMP       68           ; PC := 68
 42 [-]: SELF      R11 R9 K15   ; R12 := R9; R11 := R9[0x5acae14c]
 43 [-]: CONST     R13 4        ; R13 := 4.000000
 44 [-]: CONST     R14 1        ; R14 := 1.000000
 45 [-]: LOADKB    R15 1 0      ; R15 := true
 46 [-]: LOADNIL   R16 R16      ; R16 := nil
 47 [-]: CALL      R11 6 1      ; R11(R12,R13,R14,R15,R16)
 48 [-]: SELF      R11 R9 K17   ; R12 := R9; R11 := R9[0xf2deaf69]
 49 [-]: GETUPVAL  R13 U0       ; R13 := U0
 50 [-]: CALL      R11 3 2      ; R11 := R11(R12,R13)
 51 [-]: TEST      R11 1        ; if R11 then PC := 68
 52 [-]: JMP       68           ; PC := 68
 53 [-]: SELF      R11 R9 K18   ; R12 := R9; R11 := R9[0x905bb2bd]
 54 [-]: CALL      R11 2 2      ; R11 := R11(R12)
 55 [-]: CONST     R12 1        ; R12 := 1.000000
 56 [-]: LEN       R13 R11      ; R13 := # R11
 57 [-]: CONST     R14 1        ; R14 := 1.000000
 58 [-]: FORPREP   R12 67       ; R12 -= R14; PC := 67
 59 [-]: GETTABLE  R16 R11 R15  ; R16 := R11[R15]
 60 [-]: SELF      R17 R16 K17  ; R18 := R16; R17 := R16[0xf2deaf69]
 61 [-]: GETGLOBAL R19 K19      ; R19 := gTriggerType
 62 [-]: CALL      R17 3 2      ; R17 := R17(R18,R19)
 63 [-]: TEST      R17 0        ; if not R17 then PC := 67
 64 [-]: JMP       67           ; PC := 67
 65 [-]: SELF      R17 R16 K20  ; R18 := R16; R17 := R16[0xf4e253b6]
 66 [-]: CALL      R17 2 1      ; R17(R18)
 67 [-]: FORLOOP   R12 59       ; R12 += R14; if R12 <= R13 then begin PC := 59; R15 := R12 end
 68 [-]: TFORLOOP  R5 2         ; R8,R9 :=  R5(R6,R7); if R8 ~= nil then begin PC = 20; R7 := R8 end
 69 [-]: JMP       20           ; PC := 20
 70 [-]: CONST     R17 60       ; R17 := 60.000000
 71 [-]: LT        0 K21 R17    ; if 0.000000 >= R17 then PC := 100
 72 [-]: JMP       100          ; PC := 100
 73 [-]: GETGLOBAL R18 K2       ; R18 := _T
 74 [-]: GETTABLE  R18 R18 K22  ; R18 := R18["gPreviewMode"]
 75 [-]: EQ        0 R18 K23    ; if R18 ~= nil then PC := 78
 76 [-]: JMP       78           ; PC := 78
 77 [-]: JMP       100          ; PC := 100
 78 [-]: SELF      R18 R4 K24   ; R19 := R4; R18 := R4[0x0803eee1]
 79 [-]: CALL      R18 2 2      ; R18 := R18(R19)
 80 [-]: SELF      R18 R18 K25  ; R19 := R18; R18 := R18[0x89212ed6]
 81 [-]: GETGLOBAL R20 K26      ; R20 := 0x603636ad
 82 [-]: LOADK     R21 K27      ; R21 := "/Lotus/Language/Dojo/PreviewDecorationsActive"
 83 [-]: NEWTABLE  R22 0 1      ; R22 := {}
 84 [-]: GETGLOBAL R23 K29      ; R23 := 0x5bced4c4
 85 [-]: GETTABLE  R23 R23 K30  ; R23 := R23[0x55f27c30]
 86 [-]: MOVE      R24 R17      ; R24 := R17
 87 [-]: CALL      R23 2 2      ; R23 := R23(R24)
 88 [-]: SETTABLE  R22 K28 R23  ; R22["TIME"] := R23
 89 [-]: CALL      R20 3 0      ; R20,... := R20(R21,R22)
 90 [-]: CALL      R18 0 1      ; R18(R19,...)
 91 [-]: GETGLOBAL R18 K31      ; R18 := 0xcbd666e1
 92 [-]: CONST     R19 0        ; R19 := 0.000000
 93 [-]: CALL      R18 2 1      ; R18(R19)
 94 [-]: GETGLOBAL R18 K32      ; R18 := 0x67652851
 95 [-]: CALL      R18 1 2      ; R18 := R18()
 96 [-]: SUB       R17 R17 R18  ; R17 := R17 - R18
 97 [-]: GETGLOBAL R18 K2       ; R18 := _T
 98 [-]: SETTABLE  R18 K33 K34  ; R18["GenericMessageNoAnimateTyping"] := true
 99 [-]: JMP       71           ; PC := 71
100 [-]: GETGLOBAL R18 K2       ; R18 := _T
101 [-]: SETTABLE  R18 K33 K35  ; R18["GenericMessageNoAnimateTyping"] := false
102 [-]: SELF      R18 R4 K24   ; R19 := R4; R18 := R4[0x0803eee1]
103 [-]: CALL      R18 2 2      ; R18 := R18(R19)
104 [-]: SELF      R18 R18 K25  ; R19 := R18; R18 := R18[0x89212ed6]
105 [-]: LOADK     R20 K36      ; R20 := ""
106 [-]: CALL      R18 3 1      ; R18(R19,R20)
107 [-]: GETGLOBAL R18 K7       ; R18 := 0xcfc01047
108 [-]: GETGLOBAL R19 K2       ; R19 := _T
109 [-]: GETTABLE  R19 R19 K3   ; R19 := R19["DojoMgr"]
110 [-]: GETTABLE  R19 R19 K8   ; R19 := R19["mIdToPlacedDecos"]
111 [-]: GETTABLE  R19 R19 R3   ; R19 := R19[R3]
112 [-]: CALL      R18 2 4      ; R18,R19,R20 := R18(R19)
113 [-]: JMP       157          ; PC := 157
114 [-]: GETGLOBAL R23 K9       ; R23 := 0x7b998233
115 [-]: MOVE      R24 R22      ; R24 := R22
116 [-]: CALL      R23 2 2      ; R23 := R23(R24)
117 [-]: TEST      R23 1        ; if R23 then PC := 157
118 [-]: JMP       157          ; PC := 157
119 [-]: CONST     R23 1        ; R23 := 1.000000
120 [-]: LOADKB    R24 0 0      ; R24 := false
121 [-]: LOADNIL   R25 R25      ; R25 := nil
122 [-]: CONST     R26 4        ; R26 := 4.000000
123 [-]: GETGLOBAL R27 K2       ; R27 := _T
124 [-]: GETTABLE  R27 R27 K3   ; R27 := R27["DojoMgr"]
125 [-]: GETTABLE  R27 R27 K10  ; R27 := R27["mDojo"]
126 [-]: SELF      R27 R27 K11  ; R28 := R27; R27 := R27[0x40063309]
127 [-]: MOVE      R29 R3       ; R29 := R3
128 [-]: CALL      R27 3 2      ; R27 := R27(R28,R29)
129 [-]: SELF      R27 R27 K12  ; R28 := R27; R27 := R27[0x656c098f]
130 [-]: MOVE      R29 R21      ; R29 := R21
131 [-]: CALL      R27 3 2      ; R27 := R27(R28,R29)
132 [-]: SELF      R28 R27 K13  ; R29 := R27; R28 := R27[0x3ae915ba]
133 [-]: CALL      R28 2 2      ; R28 := R28(R29)
134 [-]: TEST      R28 0        ; if not R28 then PC := 142
135 [-]: JMP       142          ; PC := 142
136 [-]: CONST     R23 2        ; R23 := 2.000000
137 [-]: GETGLOBAL R28 K2       ; R28 := _T
138 [-]: GETTABLE  R28 R28 K3   ; R28 := R28["DojoMgr"]
139 [-]: GETTABLE  R25 R28 K37  ; R25 := R28["mDecoConstructionQueuedMaterialOverride"]
140 [-]: CONST     R26 2        ; R26 := 2.000000
141 [-]: JMP       151          ; PC := 151
142 [-]: SELF      R28 R27 K14  ; R29 := R27; R28 := R27[0x04de00e9]
143 [-]: CALL      R28 2 2      ; R28 := R28(R29)
144 [-]: TEST      R28 0        ; if not R28 then PC := 151
145 [-]: JMP       151          ; PC := 151
146 [-]: CONST     R23 2        ; R23 := 2.000000
147 [-]: GETGLOBAL R28 K2       ; R28 := _T
148 [-]: GETTABLE  R28 R28 K3   ; R28 := R28["DojoMgr"]
149 [-]: GETTABLE  R25 R28 K38  ; R25 := R28["mDecoUnderConstructionMaterialOverride"]
150 [-]: CONST     R26 3        ; R26 := 3.000000
151 [-]: SELF      R28 R22 K15  ; R29 := R22; R28 := R22[0x5acae14c]
152 [-]: MOVE      R30 R26      ; R30 := R26
153 [-]: MOVE      R31 R23      ; R31 := R23
154 [-]: MOVE      R32 R24      ; R32 := R24
155 [-]: MOVE      R33 R25      ; R33 := R25
156 [-]: CALL      R28 6 1      ; R28(R29,R30,R31,R32,R33)
157 [-]: TFORLOOP  R18 2        ; R21,R22 :=  R18(R19,R20); if R21 ~= nil then begin PC = 114; R20 := R21 end
158 [-]: JMP       114          ; PC := 114
159 [-]: GETGLOBAL R28 K2       ; R28 := _T
160 [-]: SETTABLE  R28 K22 K23  ; R28["gPreviewMode"] := nil
161 [-]: RETURN    R0 1         ; return 


; Function #54:
;
; Name:            
; Defined at line: 1082
; #Upvalues:       2
; #Parameters:     0
; Is_vararg:       0
; Max Stack Size:  4

  1 [-]: GETUPVAL  R0 U0        ; R0 := U0
  2 [-]: CALL      R0 1 1       ; R0()
  3 [-]: GETGLOBAL R0 K0        ; R0 := _T
  4 [-]: GETTABLE  R0 R0 K1     ; R0 := R0["gPreviewMode"]
  5 [-]: EQ        0 R0 K2      ; if R0 ~= nil then PC := 19
  6 [-]: JMP       19           ; PC := 19
  7 [-]: GETGLOBAL R0 K0        ; R0 := _T
  8 [-]: SETTABLE  R0 K1 K3     ; R0["gPreviewMode"] := true
  9 [-]: GETGLOBAL R0 K4        ; R0 := 0x89326c93
 10 [-]: SELF      R0 R0 K5     ; R1 := R0; R0 := R0[0x78298275]
 11 [-]: CALL      R0 2 2       ; R0 := R0(R1)
 12 [-]: SELF      R0 R0 K6     ; R1 := R0; R0 := R0[0xd5f7912b]
 13 [-]: GETGLOBAL R2 K7        ; R2 := 0x0469f296
 14 [-]: LOADK     R3 K8        ; R3 := "_EnterPreviewMode"
 15 [-]: CALL      R2 2 2       ; R2 := R2(R3)
 16 [-]: LOADKB    R3 0 0       ; R3 := false
 17 [-]: CALL      R0 4 1       ; R0(R1,R2,R3)
 18 [-]: JMP       23           ; PC := 23
 19 [-]: GETUPVAL  R0 U1        ; R0 := U1
 20 [-]: GETTABLE  R0 R0 K9     ; R0 := R0[0xe0cba3ca]
 21 [-]: LOADK     R1 K10       ; R1 := "/Lotus/Language/Dojo/PreviewModeAlreadyActive"
 22 [-]: CALL      R0 2 1       ; R0(R1)
 23 [-]: RETURN    R0 1         ; return 


; Function #55:
;
; Name:            
; Defined at line: 1092
; #Upvalues:       1
; #Parameters:     0
; Is_vararg:       0
; Max Stack Size:  2

  1 [-]: GETUPVAL  R0 U0        ; R0 := U0
  2 [-]: CALL      R0 1 1       ; R0()
  3 [-]: GETGLOBAL R0 K0        ; R0 := _T
  4 [-]: SETTABLE  R0 K1 K2     ; R0["gPreviewMode"] := nil
  5 [-]: RETURN    R0 1         ; return 


; Function #56:
;
; Name:            
; Defined at line: 1097
; #Upvalues:       2
; #Parameters:     2
; Is_vararg:       0
; Max Stack Size:  6

  1 [-]: EQ        1 R0 K1      ; if R0 == 0.000000 then PC := 30
  2 [-]: JMP       30           ; PC := 30
  3 [-]: LOADKB    R2 1 0       ; R2 := true
  4 [-]: SETUPVAL  R2 U0        ; U82 := R0
  5 [-]: LOADK     R2 K2        ; R2 := ""
  6 [-]: EQ        0 R0 K3      ; if R0 ~= -1.000000 then PC := 10
  7 [-]: JMP       10           ; PC := 10
  8 [-]: LOADK     R2 K4        ; R2 := "/Lotus/Language/Dojo/Generic_INVALID_PERMISSION"
  9 [-]: JMP       19           ; PC := 19
 10 [-]: EQ        0 R0 K5      ; if R0 ~= 1.000000 then PC := 14
 11 [-]: JMP       14           ; PC := 14
 12 [-]: LOADK     R2 K6        ; R2 := "/Lotus/Language/Dojo/ChangeSpawnRoomFail_REVISION_NOT_LATEST"
 13 [-]: JMP       19           ; PC := 19
 14 [-]: EQ        0 R0 K7      ; if R0 ~= 14.000000 then PC := 18
 15 [-]: JMP       18           ; PC := 18
 16 [-]: LOADK     R2 K8        ; R2 := "/Lotus/Language/Dojo/ChangeSpawnRoomFail_DESTRUCTION_ALREADY_QUEUED"
 17 [-]: JMP       19           ; PC := 19
 18 [-]: LOADK     R2 K9        ; R2 := "/Lotus/Language/Dojo/ChangeSpawnRoomFail_UNKNOWN_ERROR"
 19 [-]: GETGLOBAL R3 K10       ; R3 := 0x7f5022cf
 20 [-]: GETTABLE  R3 R3 K11    ; R3 := R3[0x41e2ae25]
 21 [-]: MOVE      R4 R2        ; R4 := R2
 22 [-]: CALL      R3 2 2       ; R3 := R3(R4)
 23 [-]: LT        0 K1 R3      ; if 0.000000 >= R3 then PC := 30
 24 [-]: JMP       30           ; PC := 30
 25 [-]: GETUPVAL  R3 U1        ; R3 := U1
 26 [-]: GETTABLE  R3 R3 K12    ; R3 := R3[0xe0cba3ca]
 27 [-]: MOVE      R4 R2        ; R4 := R2
 28 [-]: LOADK     R5 K13       ; R5 := "ConfirmationReviewed"
 29 [-]: CALL      R3 3 1       ; R3(R4,R5)
 30 [-]: RETURN    R0 1         ; return 


; Function #57:
;
; Name:            
; Defined at line: 1119
; #Upvalues:       4
; #Parameters:     1
; Is_vararg:       0
; Max Stack Size:  7

  1 [-]: LOADKB    R1 0 0       ; R1 := false
  2 [-]: SETUPVAL  R1 U0        ; U82 := R0
  3 [-]: GETGLOBAL R1 K0        ; R1 := 0x03f57322
  4 [-]: MOVE      R2 R0        ; R2 := R0
  5 [-]: CALL      R1 2 2       ; R1 := R1(R2)
  6 [-]: EQ        0 R1 K2      ; if R1 ~= 4.000000 then PC := 21
  7 [-]: JMP       21           ; PC := 21
  8 [-]: GETGLOBAL R1 K3        ; R1 := _T
  9 [-]: GETTABLE  R1 R1 K4     ; R1 := R1["DojoMgr"]
 10 [-]: GETTABLE  R1 R1 K5     ; R1 := R1["mDojo"]
 11 [-]: SELF      R1 R1 K6     ; R2 := R1; R1 := R1[0x5c69b193]
 12 [-]: GETUPVAL  R3 U1        ; R3 := U1
 13 [-]: CALL      R1 3 2       ; R1 := R1(R2,R3)
 14 [-]: GETGLOBAL R2 K3        ; R2 := _T
 15 [-]: GETTABLE  R2 R2 K4     ; R2 := R2["DojoMgr"]
 16 [-]: SELF      R2 R2 K7     ; R3 := R2; R2 := R2[0x27a95aee]
 17 [-]: MOVE      R4 R1        ; R4 := R1
 18 [-]: GETUPVAL  R5 U2        ; R5 := U2
 19 [-]: GETUPVAL  R6 U3        ; R6 := U3
 20 [-]: CALL      R2 5 1       ; R2(R3,R4,R5,R6)
 21 [-]: RETURN    R0 1         ; return 


; Function #58:
;
; Name:            
; Defined at line: 1127
; #Upvalues:       2
; #Parameters:     0
; Is_vararg:       0
; Max Stack Size:  4

  1 [-]: LOADKB    R0 1 0       ; R0 := true
  2 [-]: SETUPVAL  R0 U0        ; U82 := R0
  3 [-]: GETUPVAL  R0 U1        ; R0 := U1
  4 [-]: GETTABLE  R0 R0 K0     ; R0 := R0[0xe0cba3ca]
  5 [-]: LOADK     R1 K1        ; R1 := "/Lotus/Language/Dojo/ChangeSpawnRoomConfirm"
  6 [-]: LOADK     R2 K2        ; R2 := "ConfirmSpawnRoomChange"
  7 [-]: CONST     R3 1         ; R3 := 1.000000
  8 [-]: CALL      R0 4 1       ; R0(R1,R2,R3)
  9 [-]: RETURN    R0 1         ; return 


; Function #59:
;
; Name:            
; Defined at line: 1132
; #Upvalues:       3
; #Parameters:     0
; Is_vararg:       0
; Max Stack Size:  6

  1 [-]: GETGLOBAL R0 K0        ; R0 := 0x89326c93
  2 [-]: SELF      R0 R0 K1     ; R1 := R0; R0 := R0[0x78298275]
  3 [-]: CALL      R0 2 2       ; R0 := R0(R1)
  4 [-]: SELF      R1 R0 K2     ; R2 := R0; R1 := R0[0x0b4bcfb6]
  5 [-]: CALL      R1 2 2       ; R1 := R1(R2)
  6 [-]: GETUPVAL  R2 U0        ; R2 := U0
  7 [-]: SELF      R3 R1 K4     ; R4 := R1; R3 := R1[0x02bb4ff1]
  8 [-]: CALL      R3 2 2       ; R3 := R3(R4)
  9 [-]: SETTABLE  R2 K3 R3     ; R2["OldSpot"] := R3
 10 [-]: SELF      R2 R1 K5     ; R3 := R1; R2 := R1[0x14c7f7dd]
 11 [-]: GETUPVAL  R4 U0        ; R4 := U0
 12 [-]: GETTABLE  R4 R4 K6     ; R4 := R4["Spot"]
 13 [-]: LOADK     R5 K7        ; R5 := 0.010000
 14 [-]: CALL      R2 4 1       ; R2(R3,R4,R5)
 15 [-]: GETUPVAL  R2 U1        ; R2 := U1
 16 [-]: GETTABLE  R2 R2 K8     ; R2 := R2[0x4c232afc]
 17 [-]: GETGLOBAL R3 K9        ; R3 := 0xae91e43b
 18 [-]: CONST     R4 0         ; R4 := 0.000000
 19 [-]: CONST     R5 0         ; R5 := 0.250000
 20 [-]: CALL      R2 4 1       ; R2(R3,R4,R5)
 21 [-]: LOADKB    R2 0 0       ; R2 := false
 22 [-]: SETUPVAL  R2 U2        ; U82 := R2
 23 [-]: RETURN    R0 1         ; return 


; Function #60:
;
; Name:            
; Defined at line: 1143
; #Upvalues:       13
; #Parameters:     0
; Is_vararg:       0
; Max Stack Size:  15

  1 [-]: GETUPVAL  R0 U0        ; R0 := U0
  2 [-]: TEST      R0 0         ; if not R0 then PC := 9
  3 [-]: JMP       9            ; PC := 9
  4 [-]: GETGLOBAL R0 K0        ; R0 := 0x7b998233
  5 [-]: GETGLOBAL R1 K1        ; R1 := 0xae91e43b
  6 [-]: CALL      R0 2 2       ; R0 := R0(R1)
  7 [-]: TEST      R0 0         ; if not R0 then PC := 10
  8 [-]: JMP       10           ; PC := 10
  9 [-]: RETURN    R0 1         ; return 
 10 [-]: GETGLOBAL R0 K1        ; R0 := 0xae91e43b
 11 [-]: SELF      R0 R0 K2     ; R1 := R0; R0 := R0[0x8a8c8d5a]
 12 [-]: GETGLOBAL R2 K3        ; R2 := 0x67652851
 13 [-]: CALL      R2 1 0       ; R2,... := R2()
 14 [-]: CALL      R0 0 1       ; R0(R1,...)
 15 [-]: GETGLOBAL R0 K0        ; R0 := 0x7b998233
 16 [-]: GETUPVAL  R1 U1        ; R1 := U1
 17 [-]: CALL      R0 2 2       ; R0 := R0(R1)
 18 [-]: TEST      R0 1         ; if R0 then PC := 27
 19 [-]: JMP       27           ; PC := 27
 20 [-]: GETUPVAL  R0 U2        ; R0 := U2
 21 [-]: GETTABLE  R0 R0 K4     ; R0 := R0[0xf616a184]
 22 [-]: GETUPVAL  R1 U1        ; R1 := U1
 23 [-]: LOADK     R2 K5        ; R2 := "HasChildConfirmationReviewed"
 24 [-]: CALL      R0 3 1       ; R0(R1,R2)
 25 [-]: LOADNIL   R0 R0        ; R0 := nil
 26 [-]: SETUPVAL  R0 U1        ; U82 := R1
 27 [-]: GETGLOBAL R0 K0        ; R0 := 0x7b998233
 28 [-]: GETGLOBAL R1 K6        ; R1 := 0x59462acb
 29 [-]: CALL      R0 2 2       ; R0 := R0(R1)
 30 [-]: TEST      R0 1         ; if R0 then PC := 37
 31 [-]: JMP       37           ; PC := 37
 32 [-]: GETGLOBAL R0 K0        ; R0 := 0x7b998233
 33 [-]: GETUPVAL  R1 U3        ; R1 := U3
 34 [-]: CALL      R0 2 2       ; R0 := R0(R1)
 35 [-]: TEST      R0 0         ; if not R0 then PC := 47
 36 [-]: JMP       47           ; PC := 47
 37 [-]: GETUPVAL  R0 U4        ; R0 := U4
 38 [-]: ADD       R0 R0 K7     ; R0 := R0 + 1.000000
 39 [-]: SETUPVAL  R0 U4        ; U82 := R4
 40 [-]: GETUPVAL  R0 U4        ; R0 := U4
 41 [-]: LT        0 K8 R0      ; if 5.000000 >= R0 then PC := 46
 42 [-]: JMP       46           ; PC := 46
 43 [-]: GETGLOBAL R0 K1        ; R0 := 0xae91e43b
 44 [-]: SELF      R0 R0 K9     ; R1 := R0; R0 := R0[0x32302b4a]
 45 [-]: CALL      R0 2 1       ; R0(R1)
 46 [-]: RETURN    R0 1         ; return 
 47 [-]: GETUPVAL  R0 U5        ; R0 := U5
 48 [-]: TEST      R0 0         ; if not R0 then PC := 56
 49 [-]: JMP       56           ; PC := 56
 50 [-]: GETUPVAL  R0 U6        ; R0 := U6
 51 [-]: GETTABLE  R0 R0 K10    ; R0 := R0["Spot"]
 52 [-]: EQ        1 R0 K11     ; if R0 == nil then PC := 56
 53 [-]: JMP       56           ; PC := 56
 54 [-]: GETUPVAL  R0 U7        ; R0 := U7
 55 [-]: CALL      R0 1 1       ; R0()
 56 [-]: GETUPVAL  R0 U8        ; R0 := U8
 57 [-]: TEST      R0 0         ; if not R0 then PC := 196
 58 [-]: JMP       196          ; PC := 196
 59 [-]: GETGLOBAL R0 K1        ; R0 := 0xae91e43b
 60 [-]: SELF      R0 R0 K12    ; R1 := R0; R0 := R0[0x54a95d6f]
 61 [-]: LOADK     R2 K13       ; R2 := "Options.EditMessage.Message"
 62 [-]: CONST     R3 29        ; R3 := 29.000000
 63 [-]: CALL      R0 4 2       ; R0 := R0(R1,R2,R3)
 64 [-]: GETUPVAL  R1 U9        ; R1 := U9
 65 [-]: GETTABLE  R1 R1 K14    ; R1 := R1["CurrMessage"]
 66 [-]: EQ        1 R1 K11     ; if R1 == nil then PC := 72
 67 [-]: JMP       72           ; PC := 72
 68 [-]: GETUPVAL  R1 U9        ; R1 := U9
 69 [-]: GETTABLE  R1 R1 K14    ; R1 := R1["CurrMessage"]
 70 [-]: EQ        1 R0 R1      ; if R0 == R1 then PC := 143
 71 [-]: JMP       143          ; PC := 143
 72 [-]: EQ        1 R0 K15     ; if R0 == "" then PC := 75
 73 [-]: JMP       75           ; PC := 75
 74 [-]: LOADKB    R1 0 1       ; R1 := false; PC := 75
 75 [-]: LOADKB    R1 1 0       ; R1 := true
 76 [-]: GETGLOBAL R2 K1        ; R2 := 0xae91e43b
 77 [-]: SELF      R2 R2 K16    ; R3 := R2; R2 := R2[0xaade900e]
 78 [-]: LOADK     R4 K17       ; R4 := "Options.EditMessage.Hint"
 79 [-]: CONST     R5 11        ; R5 := 11.000000
 80 [-]: MOVE      R6 R1        ; R6 := R1
 81 [-]: CALL      R2 5 1       ; R2(R3,R4,R5,R6)
 82 [-]: GETGLOBAL R2 K1        ; R2 := 0xae91e43b
 83 [-]: SELF      R2 R2 K16    ; R3 := R2; R2 := R2[0xaade900e]
 84 [-]: LOADK     R4 K18       ; R4 := "Options.EditMessage.EditAction1"
 85 [-]: CONST     R5 11        ; R5 := 11.000000
 86 [-]: NOT       R6 R1        ; R6 :=  R1
 87 [-]: CALL      R2 5 1       ; R2(R3,R4,R5,R6)
 88 [-]: GETGLOBAL R2 K1        ; R2 := 0xae91e43b
 89 [-]: SELF      R2 R2 K16    ; R3 := R2; R2 := R2[0xaade900e]
 90 [-]: LOADK     R4 K19       ; R4 := "Options.EditMessage.EditAction2"
 91 [-]: CONST     R5 11        ; R5 := 11.000000
 92 [-]: GETUPVAL  R6 U9        ; R6 := U9
 93 [-]: GETTABLE  R6 R6 K20    ; R6 := R6["InitialMessage"]
 94 [-]: EQ        0 R0 R6      ; if R0 ~= R6 then PC := 97
 95 [-]: JMP       97           ; PC := 97
 96 [-]: LOADKB    R6 0 1       ; R6 := false; PC := 97
 97 [-]: LOADKB    R6 1 0       ; R6 := true
 98 [-]: CALL      R2 5 1       ; R2(R3,R4,R5,R6)
 99 [-]: GETGLOBAL R2 K1        ; R2 := 0xae91e43b
100 [-]: SELF      R2 R2 K21    ; R3 := R2; R2 := R2[0x67bc869f]
101 [-]: LOADK     R4 K19       ; R4 := "Options.EditMessage.EditAction2"
102 [-]: CONST     R5 0         ; R5 := 0.000000
103 [-]: GETUPVAL  R6 U2        ; R6 := U2
104 [-]: GETTABLE  R6 R6 K22    ; R6 := R6[0x06d055f9]
105 [-]: NOT       R7 R1        ; R7 :=  R1
106 [-]: CONST     R8 553       ; R8 := 553.000000
107 [-]: CONST     R9 501       ; R9 := 501.000000
108 [-]: CALL      R6 4 0       ; R6,... := R6(R7,R8,R9)
109 [-]: CALL      R2 0 1       ; R2(R3,...)
110 [-]: GETGLOBAL R2 K1        ; R2 := 0xae91e43b
111 [-]: SELF      R2 R2 K23    ; R3 := R2; R2 := R2[0x91a24e4b]
112 [-]: LOADK     R4 K13       ; R4 := "Options.EditMessage.Message"
113 [-]: CONST     R5 35        ; R5 := 35.000000
114 [-]: CALL      R2 4 2       ; R2 := R2(R3,R4,R5)
115 [-]: GETUPVAL  R3 U9        ; R3 := U9
116 [-]: GETTABLE  R3 R3 K24    ; R3 := R3["CurrLines"]
117 [-]: EQ        1 R2 R3      ; if R2 == R3 then PC := 141
118 [-]: JMP       141          ; PC := 141
119 [-]: GETGLOBAL R3 K25       ; R3 := 0x5bced4c4
120 [-]: GETTABLE  R3 R3 K26    ; R3 := R3[0xb62ecfe0]
121 [-]: CONST     R4 3         ; R4 := 3.000000
122 [-]: MOVE      R5 R2        ; R5 := R2
123 [-]: CALL      R3 3 2       ; R3 := R3(R4,R5)
124 [-]: MUL       R4 R3 K27    ; R4 := R3 * 23.000000
125 [-]: GETGLOBAL R5 K1        ; R5 := 0xae91e43b
126 [-]: SELF      R5 R5 K21    ; R6 := R5; R5 := R5[0x67bc869f]
127 [-]: LOADK     R7 K13       ; R7 := "Options.EditMessage.Message"
128 [-]: CONST     R8 13        ; R8 := 13.000000
129 [-]: MOVE      R9 R4        ; R9 := R4
130 [-]: CALL      R5 5 1       ; R5(R6,R7,R8,R9)
131 [-]: GETGLOBAL R5 K1        ; R5 := 0xae91e43b
132 [-]: SELF      R5 R5 K21    ; R6 := R5; R5 := R5[0x67bc869f]
133 [-]: LOADK     R7 K28       ; R7 := "Options.EditMessage.Bg"
134 [-]: CONST     R8 13        ; R8 := 13.000000
135 [-]: ADD       R9 R4 K29    ; R9 := R4 + 25.000000
136 [-]: CALL      R5 5 1       ; R5(R6,R7,R8,R9)
137 [-]: GETUPVAL  R5 U10       ; R5 := U10
138 [-]: CALL      R5 1 1       ; R5()
139 [-]: GETUPVAL  R5 U9        ; R5 := U9
140 [-]: SETTABLE  R5 K24 R2    ; R5["CurrLines"] := R2
141 [-]: GETUPVAL  R5 U9        ; R5 := U9
142 [-]: SETTABLE  R5 K14 R0    ; R5[0x0032441c] := R0
143 [-]: GETGLOBAL R5 K1        ; R5 := 0xae91e43b
144 [-]: SELF      R5 R5 K12    ; R6 := R5; R5 := R5[0x54a95d6f]
145 [-]: LOADK     R7 K30       ; R7 := "Options.RoomName.Message"
146 [-]: CONST     R8 29        ; R8 := 29.000000
147 [-]: CALL      R5 4 2       ; R5 := R5(R6,R7,R8)
148 [-]: GETUPVAL  R6 U11       ; R6 := U11
149 [-]: GETTABLE  R6 R6 K31    ; R6 := R6["CurrName"]
150 [-]: EQ        1 R6 K11     ; if R6 == nil then PC := 156
151 [-]: JMP       156          ; PC := 156
152 [-]: GETUPVAL  R6 U11       ; R6 := U11
153 [-]: GETTABLE  R6 R6 K31    ; R6 := R6["CurrName"]
154 [-]: EQ        1 R5 R6      ; if R5 == R6 then PC := 196
155 [-]: JMP       196          ; PC := 196
156 [-]: EQ        1 R5 K15     ; if R5 == "" then PC := 159
157 [-]: JMP       159          ; PC := 159
158 [-]: LOADKB    R6 0 1       ; R6 := false; PC := 159
159 [-]: LOADKB    R6 1 0       ; R6 := true
160 [-]: GETGLOBAL R7 K1        ; R7 := 0xae91e43b
161 [-]: SELF      R7 R7 K16    ; R8 := R7; R7 := R7[0xaade900e]
162 [-]: LOADK     R9 K32       ; R9 := "Options.RoomName.Hint"
163 [-]: CONST     R10 11       ; R10 := 11.000000
164 [-]: MOVE      R11 R6       ; R11 := R6
165 [-]: CALL      R7 5 1       ; R7(R8,R9,R10,R11)
166 [-]: GETGLOBAL R7 K1        ; R7 := 0xae91e43b
167 [-]: SELF      R7 R7 K16    ; R8 := R7; R7 := R7[0xaade900e]
168 [-]: LOADK     R9 K33       ; R9 := "Options.RoomName.EditAction1"
169 [-]: CONST     R10 11       ; R10 := 11.000000
170 [-]: NOT       R11 R6       ; R11 :=  R6
171 [-]: CALL      R7 5 1       ; R7(R8,R9,R10,R11)
172 [-]: GETGLOBAL R7 K1        ; R7 := 0xae91e43b
173 [-]: SELF      R7 R7 K16    ; R8 := R7; R7 := R7[0xaade900e]
174 [-]: LOADK     R9 K34       ; R9 := "Options.RoomName.EditAction2"
175 [-]: CONST     R10 11       ; R10 := 11.000000
176 [-]: GETUPVAL  R11 U11      ; R11 := U11
177 [-]: GETTABLE  R11 R11 K35  ; R11 := R11["InitialName"]
178 [-]: EQ        0 R5 R11     ; if R5 ~= R11 then PC := 181
179 [-]: JMP       181          ; PC := 181
180 [-]: LOADKB    R11 0 1      ; R11 := false; PC := 181
181 [-]: LOADKB    R11 1 0      ; R11 := true
182 [-]: CALL      R7 5 1       ; R7(R8,R9,R10,R11)
183 [-]: GETGLOBAL R7 K1        ; R7 := 0xae91e43b
184 [-]: SELF      R7 R7 K21    ; R8 := R7; R7 := R7[0x67bc869f]
185 [-]: LOADK     R9 K34       ; R9 := "Options.RoomName.EditAction2"
186 [-]: CONST     R10 0        ; R10 := 0.000000
187 [-]: GETUPVAL  R11 U2       ; R11 := U2
188 [-]: GETTABLE  R11 R11 K22  ; R11 := R11[0x06d055f9]
189 [-]: NOT       R12 R6       ; R12 :=  R6
190 [-]: CONST     R13 553      ; R13 := 553.000000
191 [-]: CONST     R14 501      ; R14 := 501.000000
192 [-]: CALL      R11 4 0      ; R11,... := R11(R12,R13,R14)
193 [-]: CALL      R7 0 1       ; R7(R8,...)
194 [-]: GETUPVAL  R7 U11       ; R7 := U11
195 [-]: SETTABLE  R7 K31 R5    ; R7[0x06d055f9] := R5
196 [-]: GETUPVAL  R7 U12       ; R7 := U12
197 [-]: GETTABLE  R7 R7 K36    ; R7 := R7["Visible"]
198 [-]: TEST      R7 0         ; if not R7 then PC := 236
199 [-]: JMP       236          ; PC := 236
200 [-]: GETGLOBAL R7 K37       ; R7 := 0xb693b6c1
201 [-]: CALL      R7 1 2       ; R7 := R7()
202 [-]: GETUPVAL  R8 U12       ; R8 := U12
203 [-]: GETGLOBAL R9 K25       ; R9 := 0x5bced4c4
204 [-]: GETTABLE  R9 R9 K26    ; R9 := R9[0xb62ecfe0]
205 [-]: GETUPVAL  R10 U12      ; R10 := U12
206 [-]: GETTABLE  R10 R10 K38  ; R10 := R10["TimeLeft"]
207 [-]: SUB       R10 R10 R7   ; R10 := R10 - R7
208 [-]: CONST     R11 0        ; R11 := 0.000000
209 [-]: CALL      R9 3 2       ; R9 := R9(R10,R11)
210 [-]: SETTABLE  R8 K38 R9    ; R8[0x20b98db3] := R9
211 [-]: GETUPVAL  R8 U12       ; R8 := U12
212 [-]: GETTABLE  R8 R8 K38    ; R8 := R8["TimeLeft"]
213 [-]: GETUPVAL  R9 U12       ; R9 := U12
214 [-]: GETTABLE  R9 R9 K39    ; R9 := R9["TotalTime"]
215 [-]: DIV       R8 R8 R9     ; R8 := R8 / R9
216 [-]: SUB       R8 K7 R8     ; R8 := 1.000000 - R8
217 [-]: GETGLOBAL R9 K1        ; R9 := 0xae91e43b
218 [-]: SELF      R9 R9 K40    ; R10 := R9; R9 := R9[0x5f56eeab]
219 [-]: LOADK     R11 K41      ; R11 := "Options.DestroyTimer.TimeLeft"
220 [-]: CONST     R12 29       ; R12 := 29.000000
221 [-]: GETUPVAL  R13 U2       ; R13 := U2
222 [-]: GETTABLE  R13 R13 K42  ; R13 := R13[0x74a11ec6]
223 [-]: MUL       R14 R8 K43   ; R14 := R8 * 100.000000
224 [-]: CALL      R13 2 2      ; R13 := R13(R14)
225 [-]: LOADK     R14 K44      ; R14 := "%"
226 [-]: CONCAT    R13 R13 R14  ; R13 := R13 .. R14
227 [-]: CALL      R9 5 1       ; R9(R10,R11,R12,R13)
228 [-]: GETGLOBAL R9 K45       ; R9 := 0x38f10e85
229 [-]: GETGLOBAL R10 K1       ; R10 := 0xae91e43b
230 [-]: LOADK     R11 K46      ; R11 := "Options.DestroyTimer.Outline.gotoAndStop"
231 [-]: GETUPVAL  R12 U2       ; R12 := U2
232 [-]: GETTABLE  R12 R12 K42  ; R12 := R12[0x74a11ec6]
233 [-]: MUL       R13 R8 K47   ; R13 := R8 * 1000.000000
234 [-]: CALL      R12 2 0      ; R12,... := R12(R13)
235 [-]: CALL      R9 0 1       ; R9(R10,...)
236 [-]: RETURN    R0 1         ; return 


; Function #61:
;
; Name:            
; Defined at line: 1213
; #Upvalues:       2
; #Parameters:     2
; Is_vararg:       0
; Max Stack Size:  14

  1 [-]: LOADK     R2 K0        ; R2 := "Options."
  2 [-]: MOVE      R3 R0        ; R3 := R0
  3 [-]: CONCAT    R2 R2 R3     ; R2 := R2 .. R3
  4 [-]: GETGLOBAL R3 K1        ; R3 := 0xae91e43b
  5 [-]: SELF      R3 R3 K2     ; R4 := R3; R3 := R3[0xaade900e]
  6 [-]: MOVE      R5 R2        ; R5 := R2
  7 [-]: CONST     R6 11        ; R6 := 11.000000
  8 [-]: LOADKB    R7 0 0       ; R7 := false
  9 [-]: CALL      R3 5 1       ; R3(R4,R5,R6,R7)
 10 [-]: GETGLOBAL R3 K1        ; R3 := 0xae91e43b
 11 [-]: SELF      R3 R3 K3     ; R4 := R3; R3 := R3[0xd5181643]
 12 [-]: MOVE      R5 R2        ; R5 := R2
 13 [-]: LOADK     R6 K4        ; R6 := ".Bg"
 14 [-]: CONCAT    R5 R5 R6     ; R5 := R5 .. R6
 15 [-]: GETGLOBAL R6 K5        ; R6 := 0x0032441c
 16 [-]: GETTABLE  R6 R6 K6     ; R6 := R6["UIMaterial_RectangleNoDepth"]
 17 [-]: CALL      R3 4 1       ; R3(R4,R5,R6)
 18 [-]: GETGLOBAL R3 K1        ; R3 := 0xae91e43b
 19 [-]: SELF      R3 R3 K7     ; R4 := R3; R3 := R3[0x1e5b5cfe]
 20 [-]: MOVE      R5 R2        ; R5 := R2
 21 [-]: LOADK     R6 K4        ; R6 := ".Bg"
 22 [-]: CONCAT    R5 R5 R6     ; R5 := R5 .. R6
 23 [-]: LOADNIL   R6 R8        ; R6 := R7 := R8 := nil
 24 [-]: MOVE      R9 R0        ; R9 := R0
 25 [-]: LOADK     R10 K8       ; R10 := "Callback"
 26 [-]: CONCAT    R9 R9 R10    ; R9 := R9 .. R10
 27 [-]: CALL      R3 7 1       ; R3(R4,R5,R6,R7,R8,R9)
 28 [-]: GETUPVAL  R3 U0        ; R3 := U0
 29 [-]: GETTABLE  R3 R3 K9     ; R3 := R3["FloatingContentObject"]
 30 [-]: GETUPVAL  R4 U0        ; R4 := U0
 31 [-]: GETTABLE  R4 R4 K10    ; R4 := R4["Background1Object"]
 32 [-]: GETGLOBAL R5 K1        ; R5 := 0xae91e43b
 33 [-]: SELF      R5 R5 K11    ; R6 := R5; R5 := R5[0x91e13703]
 34 [-]: MOVE      R7 R2        ; R7 := R2
 35 [-]: LOADK     R8 K4        ; R8 := ".Bg"
 36 [-]: CONCAT    R7 R7 R8     ; R7 := R7 .. R8
 37 [-]: LOADK     R8 K12       ; R8 := "RectEdgeColor"
 38 [-]: GETTABLE  R9 R3 K13    ; R9 := R3["red"]
 39 [-]: DIV       R9 R9 K14    ; R9 := R9 / 255.000000
 40 [-]: GETTABLE  R10 R3 K15   ; R10 := R3["green"]
 41 [-]: DIV       R10 R10 K14  ; R10 := R10 / 255.000000
 42 [-]: GETTABLE  R11 R3 K16   ; R11 := R3["blue"]
 43 [-]: DIV       R11 R11 K14  ; R11 := R11 / 255.000000
 44 [-]: LOADK     R12 K17      ; R12 := 0.200000
 45 [-]: CALL      R5 8 1       ; R5(R6,R7,R8,R9,R10,R11,R12)
 46 [-]: GETGLOBAL R5 K1        ; R5 := 0xae91e43b
 47 [-]: SELF      R5 R5 K11    ; R6 := R5; R5 := R5[0x91e13703]
 48 [-]: MOVE      R7 R2        ; R7 := R2
 49 [-]: LOADK     R8 K4        ; R8 := ".Bg"
 50 [-]: CONCAT    R7 R7 R8     ; R7 := R7 .. R8
 51 [-]: LOADK     R8 K18       ; R8 := "RectInnerColor"
 52 [-]: GETTABLE  R9 R4 K13    ; R9 := R4["red"]
 53 [-]: DIV       R9 R9 K14    ; R9 := R9 / 255.000000
 54 [-]: GETTABLE  R10 R4 K15   ; R10 := R4["green"]
 55 [-]: DIV       R10 R10 K14  ; R10 := R10 / 255.000000
 56 [-]: GETTABLE  R11 R4 K16   ; R11 := R4["blue"]
 57 [-]: DIV       R11 R11 K14  ; R11 := R11 / 255.000000
 58 [-]: CONST     R12 1        ; R12 := 1.000000
 59 [-]: CALL      R5 8 1       ; R5(R6,R7,R8,R9,R10,R11,R12)
 60 [-]: GETGLOBAL R5 K1        ; R5 := 0xae91e43b
 61 [-]: SELF      R5 R5 K19    ; R6 := R5; R5 := R5[0xe261aa96]
 62 [-]: MOVE      R7 R2        ; R7 := R2
 63 [-]: LOADK     R8 K20       ; R8 := "Message"
 64 [-]: CONST     R9 29        ; R9 := 29.000000
 65 [-]: LOADK     R10 K21      ; R10 := ""
 66 [-]: CALL      R5 6 1       ; R5(R6,R7,R8,R9,R10)
 67 [-]: GETGLOBAL R5 K1        ; R5 := 0xae91e43b
 68 [-]: SELF      R5 R5 K19    ; R6 := R5; R5 := R5[0xe261aa96]
 69 [-]: MOVE      R7 R2        ; R7 := R2
 70 [-]: LOADK     R8 K20       ; R8 := "Message"
 71 [-]: CONST     R9 49        ; R9 := 49.000000
 72 [-]: GETUPVAL  R10 U1       ; R10 := U1
 73 [-]: GETTABLE  R10 R10 K22  ; R10 := R10[0x06d055f9]
 74 [-]: GETGLOBAL R11 K23      ; R11 := 0x34291f5c
 75 [-]: GETTABLE  R11 R11 K24  ; R11 := R11[0x1467d5f4]
 76 [-]: CALL      R11 1 2      ; R11 := R11()
 77 [-]: LOADK     R12 K25      ; R12 := "dynamic"
 78 [-]: LOADK     R13 K26      ; R13 := "input"
 79 [-]: CALL      R10 4 0      ; R10,... := R10(R11,R12,R13)
 80 [-]: CALL      R5 0 1       ; R5(R6,...)
 81 [-]: GETGLOBAL R5 K1        ; R5 := 0xae91e43b
 82 [-]: SELF      R5 R5 K27    ; R6 := R5; R5 := R5[0xf64b7262]
 83 [-]: MOVE      R7 R2        ; R7 := R2
 84 [-]: LOADK     R8 K20       ; R8 := "Message"
 85 [-]: CONST     R9 36        ; R9 := 36.000000
 86 [-]: GETUPVAL  R10 U0       ; R10 := U0
 87 [-]: GETTABLE  R10 R10 K28  ; R10 := R10["Content"]
 88 [-]: CALL      R5 6 1       ; R5(R6,R7,R8,R9,R10)
 89 [-]: GETGLOBAL R5 K1        ; R5 := 0xae91e43b
 90 [-]: SELF      R5 R5 K29    ; R6 := R5; R5 := R5[0x20b98db3]
 91 [-]: MOVE      R7 R2        ; R7 := R2
 92 [-]: LOADK     R8 K30       ; R8 := ".Hint.text"
 93 [-]: CONCAT    R7 R7 R8     ; R7 := R7 .. R8
 94 [-]: MOVE      R8 R1        ; R8 := R1
 95 [-]: CALL      R5 4 1       ; R5(R6,R7,R8)
 96 [-]: GETGLOBAL R5 K1        ; R5 := 0xae91e43b
 97 [-]: SELF      R5 R5 K27    ; R6 := R5; R5 := R5[0xf64b7262]
 98 [-]: MOVE      R7 R2        ; R7 := R2
 99 [-]: LOADK     R8 K31       ; R8 := "Hint"
100 [-]: CONST     R9 10        ; R9 := 10.000000
101 [-]: CONST     R10 75       ; R10 := 75.000000
102 [-]: CALL      R5 6 1       ; R5(R6,R7,R8,R9,R10)
103 [-]: GETGLOBAL R5 K1        ; R5 := 0xae91e43b
104 [-]: SELF      R5 R5 K27    ; R6 := R5; R5 := R5[0xf64b7262]
105 [-]: MOVE      R7 R2        ; R7 := R2
106 [-]: LOADK     R8 K31       ; R8 := "Hint"
107 [-]: CONST     R9 36        ; R9 := 36.000000
108 [-]: GETUPVAL  R10 U0       ; R10 := U0
109 [-]: GETTABLE  R10 R10 K28  ; R10 := R10["Content"]
110 [-]: CALL      R5 6 1       ; R5(R6,R7,R8,R9,R10)
111 [-]: GETGLOBAL R5 K1        ; R5 := 0xae91e43b
112 [-]: SELF      R5 R5 K27    ; R6 := R5; R5 := R5[0xf64b7262]
113 [-]: MOVE      R7 R2        ; R7 := R2
114 [-]: LOADK     R8 K20       ; R8 := "Message"
115 [-]: CONST     R9 79        ; R9 := 79.000000
116 [-]: CONST     R10 470      ; R10 := 470.000000
117 [-]: CALL      R5 6 1       ; R5(R6,R7,R8,R9,R10)
118 [-]: GETGLOBAL R5 K1        ; R5 := 0xae91e43b
119 [-]: SELF      R5 R5 K32    ; R6 := R5; R5 := R5[0xc0a3774b]
120 [-]: MOVE      R7 R2        ; R7 := R2
121 [-]: LOADK     R8 K20       ; R8 := "Message"
122 [-]: CONST     R9 81        ; R9 := 81.000000
123 [-]: LOADKB    R10 1 0      ; R10 := true
124 [-]: CALL      R5 6 1       ; R5(R6,R7,R8,R9,R10)
125 [-]: GETGLOBAL R5 K1        ; R5 := 0xae91e43b
126 [-]: SELF      R5 R5 K27    ; R6 := R5; R5 := R5[0xf64b7262]
127 [-]: MOVE      R7 R2        ; R7 := R2
128 [-]: LOADK     R8 K20       ; R8 := "Message"
129 [-]: CONST     R9 78        ; R9 := 78.000000
130 [-]: CONST     R10 1        ; R10 := 1.000000
131 [-]: CALL      R5 6 1       ; R5(R6,R7,R8,R9,R10)
132 [-]: CONST     R5 23        ; R5 := 23.000000
133 [-]: GETGLOBAL R6 K1        ; R6 := 0xae91e43b
134 [-]: SELF      R6 R6 K27    ; R7 := R6; R6 := R6[0xf64b7262]
135 [-]: MOVE      R8 R2        ; R8 := R2
136 [-]: LOADK     R9 K20       ; R9 := "Message"
137 [-]: CONST     R10 13       ; R10 := 13.000000
138 [-]: MOVE      R11 R5       ; R11 := R5
139 [-]: CALL      R6 6 1       ; R6(R7,R8,R9,R10,R11)
140 [-]: GETGLOBAL R6 K1        ; R6 := 0xae91e43b
141 [-]: SELF      R6 R6 K27    ; R7 := R6; R6 := R6[0xf64b7262]
142 [-]: MOVE      R8 R2        ; R8 := R2
143 [-]: LOADK     R9 K33       ; R9 := "Bg"
144 [-]: CONST     R10 13       ; R10 := 13.000000
145 [-]: ADD       R11 R5 K34   ; R11 := R5 + 25.000000
146 [-]: CALL      R6 6 1       ; R6(R7,R8,R9,R10,R11)
147 [-]: CLOSURE   R6 0         ; R6 := closure(Function #61.1)
148 [-]: MOVE      R0 R2        ; R0 := R2
149 [-]: MOVE      R0 R0        ; R0 := R0
150 [-]: MOVE      R0 R3        ; R0 := R3
151 [-]: MOVE      R0 R4        ; R0 := R4
152 [-]: GETUPVAL  R0 U0        ; R0 := U0
153 [-]: GETUPVAL  R0 U1        ; R0 := U1
154 [-]: MOVE      R7 R6        ; R7 := R6
155 [-]: GETGLOBAL R8 K35       ; R8 := 0xbf2ae52b
156 [-]: CONST     R9 1         ; R9 := 1.000000
157 [-]: CALL      R7 3 1       ; R7(R8,R9)
158 [-]: MOVE      R7 R6        ; R7 := R6
159 [-]: GETGLOBAL R8 K36       ; R8 := 0x2efcea8b
160 [-]: CONST     R9 2         ; R9 := 2.000000
161 [-]: CALL      R7 3 1       ; R7(R8,R9)
162 [-]: RETURN    R0 1         ; return 


; Function #61.1:
;
; Name:            
; Defined at line: 1238
; #Upvalues:       6
; #Parameters:     2
; Is_vararg:       0
; Max Stack Size:  11

  1 [-]: GETUPVAL  R2 U0        ; R2 := U0
  2 [-]: LOADK     R3 K0        ; R3 := ".EditAction"
  3 [-]: GETGLOBAL R4 K1        ; R4 := 0x64fb1586
  4 [-]: MOVE      R5 R1        ; R5 := R1
  5 [-]: CALL      R4 2 2       ; R4 := R4(R5)
  6 [-]: CONCAT    R2 R2 R4     ; R2 := R2 .. R3 .. R4
  7 [-]: GETGLOBAL R3 K2        ; R3 := 0xae91e43b
  8 [-]: SELF      R3 R3 K3     ; R4 := R3; R3 := R3[0xf64b7262]
  9 [-]: MOVE      R5 R2        ; R5 := R2
 10 [-]: LOADK     R6 K4        ; R6 := "Bg"
 11 [-]: CONST     R7 85        ; R7 := 85.000000
 12 [-]: MOVE      R8 R1        ; R8 := R1
 13 [-]: CALL      R3 6 1       ; R3(R4,R5,R6,R7,R8)
 14 [-]: GETGLOBAL R3 K2        ; R3 := 0xae91e43b
 15 [-]: SELF      R3 R3 K5     ; R4 := R3; R3 := R3[0x1e5b5cfe]
 16 [-]: MOVE      R5 R2        ; R5 := R2
 17 [-]: LOADK     R6 K6        ; R6 := ".Bg"
 18 [-]: CONCAT    R5 R5 R6     ; R5 := R5 .. R6
 19 [-]: GETUPVAL  R6 U1        ; R6 := U1
 20 [-]: LOADK     R7 K7        ; R7 := "ActionFocused"
 21 [-]: CONCAT    R6 R6 R7     ; R6 := R6 .. R7
 22 [-]: GETUPVAL  R7 U1        ; R7 := U1
 23 [-]: LOADK     R8 K8        ; R8 := "ActionUnfocused"
 24 [-]: CONCAT    R7 R7 R8     ; R7 := R7 .. R8
 25 [-]: LOADNIL   R8 R8        ; R8 := nil
 26 [-]: GETUPVAL  R9 U1        ; R9 := U1
 27 [-]: LOADK     R10 K9       ; R10 := "ActionPressed"
 28 [-]: CONCAT    R9 R9 R10    ; R9 := R9 .. R10
 29 [-]: CALL      R3 7 1       ; R3(R4,R5,R6,R7,R8,R9)
 30 [-]: GETGLOBAL R3 K2        ; R3 := 0xae91e43b
 31 [-]: SELF      R3 R3 K10    ; R4 := R3; R3 := R3[0xd5181643]
 32 [-]: MOVE      R5 R2        ; R5 := R2
 33 [-]: LOADK     R6 K6        ; R6 := ".Bg"
 34 [-]: CONCAT    R5 R5 R6     ; R5 := R5 .. R6
 35 [-]: GETGLOBAL R6 K11       ; R6 := 0x0032441c
 36 [-]: GETTABLE  R6 R6 K12    ; R6 := R6["UIMaterial_RectangleNoDepth"]
 37 [-]: CALL      R3 4 1       ; R3(R4,R5,R6)
 38 [-]: GETGLOBAL R3 K2        ; R3 := 0xae91e43b
 39 [-]: SELF      R3 R3 K13    ; R4 := R3; R3 := R3[0x91e13703]
 40 [-]: MOVE      R5 R2        ; R5 := R2
 41 [-]: LOADK     R6 K6        ; R6 := ".Bg"
 42 [-]: CONCAT    R5 R5 R6     ; R5 := R5 .. R6
 43 [-]: LOADK     R6 K14       ; R6 := "RectEdgeColor"
 44 [-]: GETUPVAL  R7 U2        ; R7 := U2
 45 [-]: GETTABLE  R7 R7 K15    ; R7 := R7["red"]
 46 [-]: DIV       R7 R7 K16    ; R7 := R7 / 255.000000
 47 [-]: GETUPVAL  R8 U2        ; R8 := U2
 48 [-]: GETTABLE  R8 R8 K17    ; R8 := R8["green"]
 49 [-]: DIV       R8 R8 K16    ; R8 := R8 / 255.000000
 50 [-]: GETUPVAL  R9 U2        ; R9 := U2
 51 [-]: GETTABLE  R9 R9 K18    ; R9 := R9["blue"]
 52 [-]: DIV       R9 R9 K16    ; R9 := R9 / 255.000000
 53 [-]: LOADK     R10 K19      ; R10 := 0.200000
 54 [-]: CALL      R3 8 1       ; R3(R4,R5,R6,R7,R8,R9,R10)
 55 [-]: GETGLOBAL R3 K2        ; R3 := 0xae91e43b
 56 [-]: SELF      R3 R3 K13    ; R4 := R3; R3 := R3[0x91e13703]
 57 [-]: MOVE      R5 R2        ; R5 := R2
 58 [-]: LOADK     R6 K6        ; R6 := ".Bg"
 59 [-]: CONCAT    R5 R5 R6     ; R5 := R5 .. R6
 60 [-]: LOADK     R6 K20       ; R6 := "RectInnerColor"
 61 [-]: GETUPVAL  R7 U3        ; R7 := U3
 62 [-]: GETTABLE  R7 R7 K15    ; R7 := R7["red"]
 63 [-]: DIV       R7 R7 K16    ; R7 := R7 / 255.000000
 64 [-]: GETUPVAL  R8 U3        ; R8 := U3
 65 [-]: GETTABLE  R8 R8 K17    ; R8 := R8["green"]
 66 [-]: DIV       R8 R8 K16    ; R8 := R8 / 255.000000
 67 [-]: GETUPVAL  R9 U3        ; R9 := U3
 68 [-]: GETTABLE  R9 R9 K18    ; R9 := R9["blue"]
 69 [-]: DIV       R9 R9 K16    ; R9 := R9 / 255.000000
 70 [-]: CONST     R10 1        ; R10 := 1.000000
 71 [-]: CALL      R3 8 1       ; R3(R4,R5,R6,R7,R8,R9,R10)
 72 [-]: GETGLOBAL R3 K2        ; R3 := 0xae91e43b
 73 [-]: SELF      R3 R3 K21    ; R4 := R3; R3 := R3[0x1cb415c1]
 74 [-]: MOVE      R5 R2        ; R5 := R2
 75 [-]: LOADK     R6 K22       ; R6 := ".Icon"
 76 [-]: CONCAT    R5 R5 R6     ; R5 := R5 .. R6
 77 [-]: MOVE      R6 R0        ; R6 := R0
 78 [-]: CALL      R3 4 1       ; R3(R4,R5,R6)
 79 [-]: GETGLOBAL R3 K2        ; R3 := 0xae91e43b
 80 [-]: SELF      R3 R3 K3     ; R4 := R3; R3 := R3[0xf64b7262]
 81 [-]: MOVE      R5 R2        ; R5 := R2
 82 [-]: LOADK     R6 K23       ; R6 := "Icon"
 83 [-]: CONST     R7 9         ; R7 := 9.000000
 84 [-]: GETUPVAL  R8 U4        ; R8 := U4
 85 [-]: GETTABLE  R8 R8 K24    ; R8 := R8["FloatingContent"]
 86 [-]: CALL      R3 6 1       ; R3(R4,R5,R6,R7,R8)
 87 [-]: GETUPVAL  R3 U5        ; R3 := U5
 88 [-]: GETTABLE  R3 R3 K25    ; R3 := R3[0x06d055f9]
 89 [-]: EQ        1 R1 K26     ; if R1 == 1.000000 then PC := 92
 90 [-]: JMP       92           ; PC := 92
 91 [-]: LOADKB    R4 0 1       ; R4 := false; PC := 92
 92 [-]: LOADKB    R4 1 0       ; R4 := true
 93 [-]: CONST     R5 20        ; R5 := 20.000000
 94 [-]: CONST     R6 35        ; R6 := 35.000000
 95 [-]: CALL      R3 4 2       ; R3 := R3(R4,R5,R6)
 96 [-]: GETGLOBAL R4 K2        ; R4 := 0xae91e43b
 97 [-]: SELF      R4 R4 K3     ; R5 := R4; R4 := R4[0xf64b7262]
 98 [-]: MOVE      R6 R2        ; R6 := R2
 99 [-]: LOADK     R7 K23       ; R7 := "Icon"
100 [-]: CONST     R8 12        ; R8 := 12.000000
101 [-]: MOVE      R9 R3        ; R9 := R3
102 [-]: CALL      R4 6 1       ; R4(R5,R6,R7,R8,R9)
103 [-]: GETGLOBAL R4 K2        ; R4 := 0xae91e43b
104 [-]: SELF      R4 R4 K3     ; R5 := R4; R4 := R4[0xf64b7262]
105 [-]: MOVE      R6 R2        ; R6 := R2
106 [-]: LOADK     R7 K23       ; R7 := "Icon"
107 [-]: CONST     R8 13        ; R8 := 13.000000
108 [-]: MOVE      R9 R3        ; R9 := R3
109 [-]: CALL      R4 6 1       ; R4(R5,R6,R7,R8,R9)
110 [-]: GETGLOBAL R4 K2        ; R4 := 0xae91e43b
111 [-]: SELF      R4 R4 K3     ; R5 := R4; R4 := R4[0xf64b7262]
112 [-]: MOVE      R6 R2        ; R6 := R2
113 [-]: LOADK     R7 K27       ; R7 := "Gradient"
114 [-]: CONST     R8 9         ; R8 := 9.000000
115 [-]: GETUPVAL  R9 U4        ; R9 := U4
116 [-]: GETTABLE  R9 R9 K24    ; R9 := R9["FloatingContent"]
117 [-]: CALL      R4 6 1       ; R4(R5,R6,R7,R8,R9)
118 [-]: GETGLOBAL R4 K2        ; R4 := 0xae91e43b
119 [-]: SELF      R4 R4 K3     ; R5 := R4; R4 := R4[0xf64b7262]
120 [-]: MOVE      R6 R2        ; R6 := R2
121 [-]: LOADK     R7 K27       ; R7 := "Gradient"
122 [-]: CONST     R8 10        ; R8 := 10.000000
123 [-]: CONST     R9 50        ; R9 := 50.000000
124 [-]: CALL      R4 6 1       ; R4(R5,R6,R7,R8,R9)
125 [-]: RETURN    R0 1         ; return 


; Function #62:
;
; Name:            
; Defined at line: 1262
; #Upvalues:       1
; #Parameters:     0
; Is_vararg:       0
; Max Stack Size:  5

  1 [-]: GETGLOBAL R0 K0        ; R0 := 0x2d0fad09
  2 [-]: LOADK     R1 K1        ; R1 := "EE.Interface.Components.List"
  3 [-]: CALL      R0 2 2       ; R0 := R0(R1)
  4 [-]: GETGLOBAL R1 K0        ; R1 := 0x2d0fad09
  5 [-]: LOADK     R2 K2        ; R2 := "Lotus.Interface.Components.ThemedButton"
  6 [-]: CALL      R1 2 2       ; R1 := R1(R2)
  7 [-]: GETTABLE  R2 R0 K3     ; R2 := R0[0x9383bc56]
  8 [-]: GETGLOBAL R3 K4        ; R3 := 0xae91e43b
  9 [-]: LOADK     R4 K5        ; R4 := "Options.ButtonList.Button"
 10 [-]: CALL      R2 3 2       ; R2 := R2(R3,R4)
 11 [-]: SETUPVAL  R2 U0        ; U82 := R0
 12 [-]: GETUPVAL  R2 U0        ; R2 := U0
 13 [-]: SETTABLE  R2 K6 K7     ; R2["mForcedVerticalSeparation"] := 40.000000
 14 [-]: GETUPVAL  R2 U0        ; R2 := U0
 15 [-]: CLOSURE   R3 0         ; R3 := closure(Function #62.1)
 16 [-]: MOVE      R0 R1        ; R0 := R1
 17 [-]: SETTABLE  R2 K8 R3     ; R2["mElementDrawCallback"] := R3
 18 [-]: RETURN    R0 1         ; return 


; Function #62.1:
;
; Name:            
; Defined at line: 1268
; #Upvalues:       1
; #Parameters:     1
; Is_vararg:       0
; Max Stack Size:  6

  1 [-]: GETUPVAL  R1 U0        ; R1 := U0
  2 [-]: GETTABLE  R1 R1 K1     ; R1 := R1[0xae6791ba]
  3 [-]: GETGLOBAL R2 K2        ; R2 := 0xae91e43b
  4 [-]: GETTABLE  R3 R0 K3     ; R3 := R0["mClipName"]
  5 [-]: GETTABLE  R4 R0 K4     ; R4 := R0["Label"]
  6 [-]: GETTABLE  R5 R0 K5     ; R5 := R0["Callback"]
  7 [-]: CALL      R1 5 2       ; R1 := R1(R2,R3,R4,R5)
  8 [-]: SETTABLE  R0 K0 R1     ; R0["Button"] := R1
  9 [-]: GETTABLE  R1 R0 K0     ; R1 := R0["Button"]
 10 [-]: SELF      R1 R1 K6     ; R2 := R1; R1 := R1[0x1403231b]
 11 [-]: GETTABLE  R3 R0 K7     ; R3 := R0["Id"]
 12 [-]: CALL      R1 3 1       ; R1(R2,R3)
 13 [-]: GETTABLE  R1 R0 K0     ; R1 := R0["Button"]
 14 [-]: SELF      R1 R1 K8     ; R2 := R1; R1 := R1[0x6b2ab44e]
 15 [-]: LOADK     R3 K9        ; R3 := "left"
 16 [-]: CALL      R1 3 1       ; R1(R2,R3)
 17 [-]: GETTABLE  R1 R0 K0     ; R1 := R0["Button"]
 18 [-]: SELF      R1 R1 K10    ; R2 := R1; R1 := R1[0x8d77b2b2]
 19 [-]: CONST     R3 400       ; R3 := 400.000000
 20 [-]: CALL      R1 3 1       ; R1(R2,R3)
 21 [-]: GETTABLE  R1 R0 K0     ; R1 := R0["Button"]
 22 [-]: SELF      R1 R1 K11    ; R2 := R1; R1 := R1[0x71e9ac81]
 23 [-]: CALL      R1 2 1       ; R1(R2)
 24 [-]: RETURN    R0 1         ; return 


; Function #63:
;
; Name:            
; Defined at line: 1277
; #Upvalues:       1
; #Parameters:     1
; Is_vararg:       0
; Max Stack Size:  8

  1 [-]: GETGLOBAL R1 K0        ; R1 := 0xae91e43b
  2 [-]: SELF      R1 R1 K1     ; R2 := R1; R1 := R1[0xaade900e]
  3 [-]: MOVE      R3 R0        ; R3 := R0
  4 [-]: CONST     R4 11        ; R4 := 11.000000
  5 [-]: LOADKB    R5 0 0       ; R5 := false
  6 [-]: CALL      R1 5 1       ; R1(R2,R3,R4,R5)
  7 [-]: GETGLOBAL R1 K0        ; R1 := 0xae91e43b
  8 [-]: SELF      R1 R1 K2     ; R2 := R1; R1 := R1[0x1e5b5cfe]
  9 [-]: MOVE      R3 R0        ; R3 := R0
 10 [-]: LOADK     R4 K3        ; R4 := ".Bg"
 11 [-]: CONCAT    R3 R3 R4     ; R3 := R3 .. R4
 12 [-]: LOADK     R4 K4        ; R4 := "DeleteFocused"
 13 [-]: LOADK     R5 K5        ; R5 := "DeleteUnfocused"
 14 [-]: LOADNIL   R6 R6        ; R6 := nil
 15 [-]: LOADK     R7 K6        ; R7 := "DeletePressed"
 16 [-]: CALL      R1 7 1       ; R1(R2,R3,R4,R5,R6,R7)
 17 [-]: GETGLOBAL R1 K0        ; R1 := 0xae91e43b
 18 [-]: SELF      R1 R1 K7     ; R2 := R1; R1 := R1[0xf64b7262]
 19 [-]: MOVE      R3 R0        ; R3 := R0
 20 [-]: LOADK     R4 K8        ; R4 := "Outline"
 21 [-]: CONST     R5 9         ; R5 := 9.000000
 22 [-]: GETUPVAL  R6 U0        ; R6 := U0
 23 [-]: GETTABLE  R6 R6 K9     ; R6 := R6["FloatingContent"]
 24 [-]: CALL      R1 6 1       ; R1(R2,R3,R4,R5,R6)
 25 [-]: GETGLOBAL R1 K0        ; R1 := 0xae91e43b
 26 [-]: SELF      R1 R1 K7     ; R2 := R1; R1 := R1[0xf64b7262]
 27 [-]: MOVE      R3 R0        ; R3 := R0
 28 [-]: LOADK     R4 K10       ; R4 := "Outline.Backer"
 29 [-]: CONST     R5 10        ; R5 := 10.000000
 30 [-]: CONST     R6 20        ; R6 := 20.000000
 31 [-]: CALL      R1 6 1       ; R1(R2,R3,R4,R5,R6)
 32 [-]: GETGLOBAL R1 K0        ; R1 := 0xae91e43b
 33 [-]: SELF      R1 R1 K7     ; R2 := R1; R1 := R1[0xf64b7262]
 34 [-]: MOVE      R3 R0        ; R3 := R0
 35 [-]: LOADK     R4 K11       ; R4 := "Bg"
 36 [-]: CONST     R5 9         ; R5 := 9.000000
 37 [-]: GETUPVAL  R6 U0        ; R6 := U0
 38 [-]: GETTABLE  R6 R6 K12    ; R6 := R6["Background1"]
 39 [-]: CALL      R1 6 1       ; R1(R2,R3,R4,R5,R6)
 40 [-]: GETGLOBAL R1 K0        ; R1 := 0xae91e43b
 41 [-]: SELF      R1 R1 K7     ; R2 := R1; R1 := R1[0xf64b7262]
 42 [-]: MOVE      R3 R0        ; R3 := R0
 43 [-]: LOADK     R4 K13       ; R4 := "Label"
 44 [-]: CONST     R5 36        ; R5 := 36.000000
 45 [-]: GETUPVAL  R6 U0        ; R6 := U0
 46 [-]: GETTABLE  R6 R6 K9     ; R6 := R6["FloatingContent"]
 47 [-]: CALL      R1 6 1       ; R1(R2,R3,R4,R5,R6)
 48 [-]: GETGLOBAL R1 K0        ; R1 := 0xae91e43b
 49 [-]: SELF      R1 R1 K7     ; R2 := R1; R1 := R1[0xf64b7262]
 50 [-]: MOVE      R3 R0        ; R3 := R0
 51 [-]: LOADK     R4 K14       ; R4 := "Icon"
 52 [-]: CONST     R5 9         ; R5 := 9.000000
 53 [-]: GETUPVAL  R6 U0        ; R6 := U0
 54 [-]: GETTABLE  R6 R6 K9     ; R6 := R6["FloatingContent"]
 55 [-]: CALL      R1 6 1       ; R1(R2,R3,R4,R5,R6)
 56 [-]: GETGLOBAL R1 K0        ; R1 := 0xae91e43b
 57 [-]: SELF      R1 R1 K7     ; R2 := R1; R1 := R1[0xf64b7262]
 58 [-]: MOVE      R3 R0        ; R3 := R0
 59 [-]: LOADK     R4 K15       ; R4 := "Gradient"
 60 [-]: CONST     R5 9         ; R5 := 9.000000
 61 [-]: GETUPVAL  R6 U0        ; R6 := U0
 62 [-]: GETTABLE  R6 R6 K9     ; R6 := R6["FloatingContent"]
 63 [-]: CALL      R1 6 1       ; R1(R2,R3,R4,R5,R6)
 64 [-]: GETGLOBAL R1 K0        ; R1 := 0xae91e43b
 65 [-]: SELF      R1 R1 K7     ; R2 := R1; R1 := R1[0xf64b7262]
 66 [-]: MOVE      R3 R0        ; R3 := R0
 67 [-]: LOADK     R4 K15       ; R4 := "Gradient"
 68 [-]: CONST     R5 10        ; R5 := 10.000000
 69 [-]: CONST     R6 50        ; R6 := 50.000000
 70 [-]: CALL      R1 6 1       ; R1(R2,R3,R4,R5,R6)
 71 [-]: GETGLOBAL R1 K0        ; R1 := 0xae91e43b
 72 [-]: SELF      R1 R1 K7     ; R2 := R1; R1 := R1[0xf64b7262]
 73 [-]: MOVE      R3 R0        ; R3 := R0
 74 [-]: LOADK     R4 K16       ; R4 := "TimeLeft"
 75 [-]: CONST     R5 36        ; R5 := 36.000000
 76 [-]: GETUPVAL  R6 U0        ; R6 := U0
 77 [-]: GETTABLE  R6 R6 K9     ; R6 := R6["FloatingContent"]
 78 [-]: CALL      R1 6 1       ; R1(R2,R3,R4,R5,R6)
 79 [-]: RETURN    R0 1         ; return 


; Function #64:
;
; Name:            
; Defined at line: 1290
; #Upvalues:       13
; #Parameters:     0
; Is_vararg:       0
; Max Stack Size:  9

  1 [-]: GETGLOBAL R0 K0        ; R0 := 0x7b998233
  2 [-]: GETGLOBAL R1 K1        ; R1 := _T
  3 [-]: GETTABLE  R1 R1 K2     ; R1 := R1["ChangeHubVisCounter"]
  4 [-]: CALL      R0 2 2       ; R0 := R0(R1)
  5 [-]: TEST      R0 1         ; if R0 then PC := 11
  6 [-]: JMP       11           ; PC := 11
  7 [-]: GETGLOBAL R0 K1        ; R0 := _T
  8 [-]: GETTABLE  R0 R0 K3     ; R0 := R0[0x33cfa273]
  9 [-]: CONST     R1 1         ; R1 := 1.000000
 10 [-]: CALL      R0 2 1       ; R0(R1)
 11 [-]: GETGLOBAL R0 K0        ; R0 := 0x7b998233
 12 [-]: GETGLOBAL R1 K4        ; R1 := 0xbe190284
 13 [-]: CALL      R0 2 2       ; R0 := R0(R1)
 14 [-]: TEST      R0 1         ; if R0 then PC := 20
 15 [-]: JMP       20           ; PC := 20
 16 [-]: GETGLOBAL R0 K4        ; R0 := 0xbe190284
 17 [-]: SELF      R0 R0 K5     ; R1 := R0; R0 := R0[0xc02f2cb8]
 18 [-]: LOADKB    R2 1 0       ; R2 := true
 19 [-]: CALL      R0 3 1       ; R0(R1,R2)
 20 [-]: GETUPVAL  R0 U0        ; R0 := U0
 21 [-]: GETTABLE  R0 R0 K6     ; R0 := R0[0x9e3d3434]
 22 [-]: LOADKB    R1 1 0       ; R1 := true
 23 [-]: CALL      R0 2 1       ; R0(R1)
 24 [-]: GETGLOBAL R0 K7        ; R0 := 0x76ea806b
 25 [-]: SELF      R0 R0 K8     ; R1 := R0; R0 := R0[0x3f3ae64c]
 26 [-]: CONST     R2 0         ; R2 := 0.000000
 27 [-]: CALL      R0 3 2       ; R0 := R0(R1,R2)
 28 [-]: GETGLOBAL R1 K0        ; R1 := 0x7b998233
 29 [-]: MOVE      R2 R0        ; R2 := R0
 30 [-]: CALL      R1 2 2       ; R1 := R1(R2)
 31 [-]: TEST      R1 1         ; if R1 then PC := 43
 32 [-]: JMP       43           ; PC := 43
 33 [-]: SELF      R1 R0 K9     ; R2 := R0; R1 := R0[0x40e9c32b]
 34 [-]: CALL      R1 2 2       ; R1 := R1(R2)
 35 [-]: GETGLOBAL R2 K0        ; R2 := 0x7b998233
 36 [-]: MOVE      R3 R1        ; R3 := R1
 37 [-]: CALL      R2 2 2       ; R2 := R2(R3)
 38 [-]: TEST      R2 1         ; if R2 then PC := 43
 39 [-]: JMP       43           ; PC := 43
 40 [-]: SELF      R2 R1 K10    ; R3 := R1; R2 := R1[0xb1d9bcb1]
 41 [-]: CALL      R2 2 2       ; R2 := R2(R3)
 42 [-]: SETUPVAL  R2 U1        ; U82 := R1
 43 [-]: NEWTABLE  R2 0 7       ; R2 := {}
 44 [-]: GETUPVAL  R3 U3        ; R3 := U3
 45 [-]: GETTABLE  R3 R3 K12    ; R3 := R3[0x5d10207d]
 46 [-]: CONST     R4 2         ; R4 := 2.000000
 47 [-]: LOADKB    R5 1 0       ; R5 := true
 48 [-]: CALL      R3 3 2       ; R3 := R3(R4,R5)
 49 [-]: SETTABLE  R2 K11 R3    ; R2["Background1"] := R3
 50 [-]: GETUPVAL  R3 U3        ; R3 := U3
 51 [-]: GETTABLE  R3 R3 K12    ; R3 := R3[0x5d10207d]
 52 [-]: CONST     R4 2         ; R4 := 2.000000
 53 [-]: LOADKB    R5 0 0       ; R5 := false
 54 [-]: CALL      R3 3 2       ; R3 := R3(R4,R5)
 55 [-]: SETTABLE  R2 K14 R3    ; R2["Background1Object"] := R3
 56 [-]: GETUPVAL  R3 U3        ; R3 := U3
 57 [-]: GETTABLE  R3 R3 K12    ; R3 := R3[0x5d10207d]
 58 [-]: CONST     R4 9         ; R4 := 9.000000
 59 [-]: LOADKB    R5 1 0       ; R5 := true
 60 [-]: CALL      R3 3 2       ; R3 := R3(R4,R5)
 61 [-]: SETTABLE  R2 K15 R3    ; R2["FloatingContent"] := R3
 62 [-]: GETUPVAL  R3 U3        ; R3 := U3
 63 [-]: GETTABLE  R3 R3 K12    ; R3 := R3[0x5d10207d]
 64 [-]: CONST     R4 9         ; R4 := 9.000000
 65 [-]: LOADKB    R5 0 0       ; R5 := false
 66 [-]: CALL      R3 3 2       ; R3 := R3(R4,R5)
 67 [-]: SETTABLE  R2 K16 R3    ; R2["FloatingContentObject"] := R3
 68 [-]: GETUPVAL  R3 U3        ; R3 := U3
 69 [-]: GETTABLE  R3 R3 K12    ; R3 := R3[0x5d10207d]
 70 [-]: CONST     R4 10        ; R4 := 10.000000
 71 [-]: LOADKB    R5 1 0       ; R5 := true
 72 [-]: CALL      R3 3 2       ; R3 := R3(R4,R5)
 73 [-]: SETTABLE  R2 K17 R3    ; R2["FloatingContentHighlight"] := R3
 74 [-]: GETUPVAL  R3 U3        ; R3 := U3
 75 [-]: GETTABLE  R3 R3 K12    ; R3 := R3[0x5d10207d]
 76 [-]: CONST     R4 10        ; R4 := 10.000000
 77 [-]: LOADKB    R5 0 0       ; R5 := false
 78 [-]: CALL      R3 3 2       ; R3 := R3(R4,R5)
 79 [-]: SETTABLE  R2 K18 R3    ; R2["FloatingContentHighlightObject"] := R3
 80 [-]: GETUPVAL  R3 U3        ; R3 := U3
 81 [-]: GETTABLE  R3 R3 K12    ; R3 := R3[0x5d10207d]
 82 [-]: CONST     R4 6         ; R4 := 6.000000
 83 [-]: LOADKB    R5 1 0       ; R5 := true
 84 [-]: CALL      R3 3 2       ; R3 := R3(R4,R5)
 85 [-]: SETTABLE  R2 K19 R3    ; R2["Content"] := R3
 86 [-]: SETUPVAL  R2 U2        ; U82 := R2
 87 [-]: GETUPVAL  R2 U5        ; R2 := U5
 88 [-]: GETTABLE  R2 R2 K20    ; R2 := R2[0xae6791ba]
 89 [-]: GETGLOBAL R3 K21       ; R3 := 0xae91e43b
 90 [-]: CALL      R2 2 2       ; R2 := R2(R3)
 91 [-]: SETUPVAL  R2 U4        ; U82 := R4
 92 [-]: GETUPVAL  R2 U4        ; R2 := U4
 93 [-]: SELF      R2 R2 K22    ; R3 := R2; R2 := R2[0x20ff29f7]
 94 [-]: GETGLOBAL R4 K21       ; R4 := 0xae91e43b
 95 [-]: LOADK     R5 K23       ; R5 := "CornerBg"
 96 [-]: NEWTABLE  R6 2 0       ; R6 := {}
 97 [-]: GETUPVAL  R7 U4        ; R7 := U4
 98 [-]: GETTABLE  R7 R7 K24    ; R7 := R7["ANCHOR_V_TOP"]
 99 [-]: GETUPVAL  R8 U4        ; R8 := U4
100 [-]: GETTABLE  R8 R8 K25    ; R8 := R8["ANCHOR_H_LEFT"]
101 [-]: SETLIST   R6 2 1       ; R6[(1-1)*FPF+i] := R(6+i), 1 <= i <= 2
102 [-]: CALL      R2 5 1       ; R2(R3,R4,R5,R6)
103 [-]: GETUPVAL  R2 U4        ; R2 := U4
104 [-]: SELF      R2 R2 K22    ; R3 := R2; R2 := R2[0x20ff29f7]
105 [-]: GETGLOBAL R4 K21       ; R4 := 0xae91e43b
106 [-]: LOADK     R5 K26       ; R5 := "Options"
107 [-]: NEWTABLE  R6 2 0       ; R6 := {}
108 [-]: GETUPVAL  R7 U4        ; R7 := U4
109 [-]: GETTABLE  R7 R7 K24    ; R7 := R7["ANCHOR_V_TOP"]
110 [-]: GETUPVAL  R8 U4        ; R8 := U4
111 [-]: GETTABLE  R8 R8 K25    ; R8 := R8["ANCHOR_H_LEFT"]
112 [-]: SETLIST   R6 2 1       ; R6[(1-1)*FPF+i] := R(6+i), 1 <= i <= 2
113 [-]: CALL      R2 5 1       ; R2(R3,R4,R5,R6)
114 [-]: GETUPVAL  R2 U4        ; R2 := U4
115 [-]: SELF      R2 R2 K27    ; R3 := R2; R2 := R2[0xfaa69527]
116 [-]: GETGLOBAL R4 K21       ; R4 := 0xae91e43b
117 [-]: SELF      R4 R4 K28    ; R5 := R4; R4 := R4[0x6b837788]
118 [-]: CALL      R4 2 2       ; R4 := R4(R5)
119 [-]: GETGLOBAL R5 K21       ; R5 := 0xae91e43b
120 [-]: SELF      R5 R5 K29    ; R6 := R5; R5 := R5[0xaf9fda9f]
121 [-]: CALL      R5 2 0       ; R5,... := R5(R6)
122 [-]: CALL      R2 0 1       ; R2(R3,...)
123 [-]: GETUPVAL  R2 U6        ; R2 := U6
124 [-]: LOADK     R3 K30       ; R3 := "EditMessage"
125 [-]: LOADK     R4 K31       ; R4 := "/Lotus/Language/Dojo/DojoRoomMessage"
126 [-]: CALL      R2 3 1       ; R2(R3,R4)
127 [-]: GETUPVAL  R2 U6        ; R2 := U6
128 [-]: LOADK     R3 K32       ; R3 := "RoomName"
129 [-]: LOADK     R4 K33       ; R4 := "/Lotus/Language/Dojo/DojoRoomName"
130 [-]: CALL      R2 3 1       ; R2(R3,R4)
131 [-]: GETUPVAL  R2 U7        ; R2 := U7
132 [-]: CALL      R2 1 1       ; R2()
133 [-]: GETUPVAL  R2 U8        ; R2 := U8
134 [-]: LOADK     R3 K34       ; R3 := "Options.Destroy"
135 [-]: CALL      R2 2 1       ; R2(R3)
136 [-]: GETUPVAL  R2 U8        ; R2 := U8
137 [-]: LOADK     R3 K35       ; R3 := "Options.DestroyTimer"
138 [-]: CALL      R2 2 1       ; R2(R3)
139 [-]: GETGLOBAL R2 K21       ; R2 := 0xae91e43b
140 [-]: SELF      R2 R2 K36    ; R3 := R2; R2 := R2[0xaade900e]
141 [-]: LOADK     R4 K37       ; R4 := "Options.Destroy.TimeLeft"
142 [-]: CONST     R5 11        ; R5 := 11.000000
143 [-]: LOADKB    R6 0 0       ; R6 := false
144 [-]: CALL      R2 5 1       ; R2(R3,R4,R5,R6)
145 [-]: GETGLOBAL R2 K21       ; R2 := 0xae91e43b
146 [-]: SELF      R2 R2 K36    ; R3 := R2; R2 := R2[0xaade900e]
147 [-]: LOADK     R4 K38       ; R4 := "Options.DestroyTimer.Icon"
148 [-]: CONST     R5 11        ; R5 := 11.000000
149 [-]: LOADKB    R6 0 0       ; R6 := false
150 [-]: CALL      R2 5 1       ; R2(R3,R4,R5,R6)
151 [-]: GETGLOBAL R2 K21       ; R2 := 0xae91e43b
152 [-]: SELF      R2 R2 K36    ; R3 := R2; R2 := R2[0xaade900e]
153 [-]: LOADK     R4 K39       ; R4 := "Options.DestroyTimer.Bg"
154 [-]: CONST     R5 59        ; R5 := 59.000000
155 [-]: LOADKB    R6 0 0       ; R6 := false
156 [-]: CALL      R2 5 1       ; R2(R3,R4,R5,R6)
157 [-]: GETUPVAL  R2 U9        ; R2 := U9
158 [-]: CALL      R2 1 1       ; R2()
159 [-]: GETGLOBAL R2 K21       ; R2 := 0xae91e43b
160 [-]: SELF      R2 R2 K40    ; R3 := R2; R2 := R2[0x67bc869f]
161 [-]: LOADK     R4 K23       ; R4 := "CornerBg"
162 [-]: CONST     R5 9         ; R5 := 9.000000
163 [-]: GETUPVAL  R6 U2        ; R6 := U2
164 [-]: GETTABLE  R6 R6 K11    ; R6 := R6["Background1"]
165 [-]: CALL      R2 5 1       ; R2(R3,R4,R5,R6)
166 [-]: GETGLOBAL R2 K21       ; R2 := 0xae91e43b
167 [-]: SELF      R2 R2 K40    ; R3 := R2; R2 := R2[0x67bc869f]
168 [-]: LOADK     R4 K41       ; R4 := "Options.Hint"
169 [-]: CONST     R5 36        ; R5 := 36.000000
170 [-]: GETUPVAL  R6 U2        ; R6 := U2
171 [-]: GETTABLE  R6 R6 K15    ; R6 := R6["FloatingContent"]
172 [-]: CALL      R2 5 1       ; R2(R3,R4,R5,R6)
173 [-]: GETGLOBAL R2 K21       ; R2 := 0xae91e43b
174 [-]: SELF      R2 R2 K42    ; R3 := R2; R2 := R2[0x20b98db3]
175 [-]: LOADK     R4 K43       ; R4 := "Options.Hint.text"
176 [-]: LOADK     R5 K44       ; R5 := "/Lotus/Language/Dojo/RoomOptionsArchitectHint"
177 [-]: CALL      R2 4 1       ; R2(R3,R4,R5)
178 [-]: GETGLOBAL R2 K21       ; R2 := 0xae91e43b
179 [-]: SELF      R2 R2 K40    ; R3 := R2; R2 := R2[0x67bc869f]
180 [-]: LOADK     R4 K45       ; R4 := "_root"
181 [-]: CONST     R5 10        ; R5 := 10.000000
182 [-]: CONST     R6 0         ; R6 := 0.000000
183 [-]: CALL      R2 5 1       ; R2(R3,R4,R5,R6)
184 [-]: GETGLOBAL R2 K21       ; R2 := 0xae91e43b
185 [-]: SELF      R2 R2 K46    ; R3 := R2; R2 := R2[0xc6a10ab1]
186 [-]: CONST     R4 0         ; R4 := 0.000000
187 [-]: CALL      R2 3 1       ; R2(R3,R4)
188 [-]: GETUPVAL  R2 U10       ; R2 := U10
189 [-]: GETTABLE  R2 R2 K47    ; R2 := R2[0x4c232afc]
190 [-]: GETGLOBAL R3 K21       ; R3 := 0xae91e43b
191 [-]: CONST     R4 1         ; R4 := 1.000000
192 [-]: CONST     R5 0         ; R5 := 0.250000
193 [-]: CONST     R6 0         ; R6 := 0.000000
194 [-]: CLOSURE   R7 0         ; R7 := closure(Function #64.1)
195 [-]: GETUPVAL  R0 U11       ; R0 := U11
196 [-]: CALL      R2 6 1       ; R2(R3,R4,R5,R6,R7)
197 [-]: LOADKB    R2 1 0       ; R2 := true
198 [-]: SETUPVAL  R2 U12       ; U82 := R12
199 [-]: RETURN    R0 1         ; return 


; Function #64.1:
;
; Name:            
; Defined at line: 1343
; #Upvalues:       1
; #Parameters:     0
; Is_vararg:       0
; Max Stack Size:  5

  1 [-]: GETGLOBAL R0 K0        ; R0 := 0xae91e43b
  2 [-]: SELF      R0 R0 K1     ; R1 := R0; R0 := R0[0x67bc869f]
  3 [-]: LOADK     R2 K2        ; R2 := "_root"
  4 [-]: CONST     R3 10        ; R3 := 10.000000
  5 [-]: CONST     R4 100       ; R4 := 100.000000
  6 [-]: CALL      R0 5 1       ; R0(R1,R2,R3,R4)
  7 [-]: LOADKB    R0 1 0       ; R0 := true
  8 [-]: SETUPVAL  R0 U0        ; U82 := R0
  9 [-]: RETURN    R0 1         ; return 


; Function #65:
;
; Name:            
; Defined at line: 1351
; #Upvalues:       1
; #Parameters:     0
; Is_vararg:       0
; Max Stack Size:  2

  1 [-]: GETUPVAL  R0 U0        ; R0 := U0
  2 [-]: CALL      R0 1 1       ; R0()
  3 [-]: RETURN    R0 1         ; return 


; Function #66:
;
; Name:            
; Defined at line: 1355
; #Upvalues:       1
; #Parameters:     0
; Is_vararg:       0
; Max Stack Size:  2

  1 [-]: GETUPVAL  R0 U0        ; R0 := U0
  2 [-]: CALL      R0 1 1       ; R0()
  3 [-]: RETURN    R0 1         ; return 


; Function #67:
;
; Name:            
; Defined at line: 1359
; #Upvalues:       6
; #Parameters:     0
; Is_vararg:       0
; Max Stack Size:  5

  1 [-]: GETGLOBAL R0 K0        ; R0 := _T
  2 [-]: GETTABLE  R0 R0 K1     ; R0 := R0["ComponentParams"]
  3 [-]: SETUPVAL  R0 U0        ; U82 := R0
  4 [-]: GETGLOBAL R0 K2        ; R0 := 0x7b998233
  5 [-]: GETUPVAL  R1 U0        ; R1 := U0
  6 [-]: CALL      R0 2 2       ; R0 := R0(R1)
  7 [-]: TEST      R0 0         ; if not R0 then PC := 10
  8 [-]: JMP       10           ; PC := 10
  9 [-]: RETURN    R0 1         ; return 
 10 [-]: GETGLOBAL R0 K0        ; R0 := _T
 11 [-]: GETTABLE  R0 R0 K3     ; R0 := R0["DojoMgr"]
 12 [-]: SELF      R0 R0 K4     ; R1 := R0; R0 := R0[0xa30a366c]
 13 [-]: GETUPVAL  R2 U0        ; R2 := U0
 14 [-]: GETTABLE  R2 R2 K5     ; R2 := R2["id"]
 15 [-]: GETUPVAL  R3 U1        ; R3 := U1
 16 [-]: LOADKB    R4 1 0       ; R4 := true
 17 [-]: CALL      R0 5 1       ; R0(R1,R2,R3,R4)
 18 [-]: GETGLOBAL R0 K0        ; R0 := _T
 19 [-]: GETTABLE  R0 R0 K3     ; R0 := R0["DojoMgr"]
 20 [-]: GETTABLE  R0 R0 K6     ; R0 := R0["mIdToRoomCameraSpots"]
 21 [-]: GETUPVAL  R1 U0        ; R1 := U0
 22 [-]: GETTABLE  R1 R1 K5     ; R1 := R1["id"]
 23 [-]: GETTABLE  R0 R0 R1     ; R0 := R0[R1]
 24 [-]: GETGLOBAL R1 K2        ; R1 := 0x7b998233
 25 [-]: MOVE      R2 R0        ; R2 := R0
 26 [-]: CALL      R1 2 2       ; R1 := R1(R2)
 27 [-]: TEST      R1 1         ; if R1 then PC := 36
 28 [-]: JMP       36           ; PC := 36
 29 [-]: GETUPVAL  R1 U2        ; R1 := U2
 30 [-]: SETTABLE  R1 K7 R0     ; R1["Spot"] := R0
 31 [-]: GETUPVAL  R1 U3        ; R1 := U3
 32 [-]: TEST      R1 0         ; if not R1 then PC := 36
 33 [-]: JMP       36           ; PC := 36
 34 [-]: GETUPVAL  R1 U4        ; R1 := U4
 35 [-]: CALL      R1 1 1       ; R1()
 36 [-]: LOADKB    R1 0 0       ; R1 := false
 37 [-]: SETUPVAL  R1 U5        ; U82 := R5
 38 [-]: RETURN    R0 1         ; return 


; Function #68:
;
; Name:            
; Defined at line: 1377
; #Upvalues:       2
; #Parameters:     0
; Is_vararg:       0
; Max Stack Size:  2

  1 [-]: GETUPVAL  R0 U0        ; R0 := U0
  2 [-]: TEST      R0 1         ; if R0 then PC := 6
  3 [-]: JMP       6            ; PC := 6
  4 [-]: GETUPVAL  R0 U1        ; R0 := U1
  5 [-]: CALL      R0 1 1       ; R0()
  6 [-]: RETURN    R0 1         ; return 


; Function #69:
;
; Name:            
; Defined at line: 1383
; #Upvalues:       2
; #Parameters:     1
; Is_vararg:       0
; Max Stack Size:  10

  1 [-]: GETUPVAL  R1 U0        ; R1 := U0
  2 [-]: GETTABLE  R1 R1 K0     ; R1 := R1[0x659d451f]
  3 [-]: GETGLOBAL R2 K1        ; R2 := 0x0032441c
  4 [-]: GETTABLE  R2 R2 K2     ; R2 := R2["UISound_Focus"]
  5 [-]: CALL      R1 2 1       ; R1(R2)
  6 [-]: GETUPVAL  R1 U1        ; R1 := U1
  7 [-]: GETTABLE  R1 R1 K3     ; R1 := R1["FloatingContentHighlightObject"]
  8 [-]: GETGLOBAL R2 K4        ; R2 := 0xae91e43b
  9 [-]: SELF      R2 R2 K5     ; R3 := R2; R2 := R2[0x91e13703]
 10 [-]: MOVE      R4 R0        ; R4 := R0
 11 [-]: LOADK     R5 K6        ; R5 := ".Bg"
 12 [-]: CONCAT    R4 R4 R5     ; R4 := R4 .. R5
 13 [-]: LOADK     R5 K7        ; R5 := "RectEdgeColor"
 14 [-]: GETTABLE  R6 R1 K8     ; R6 := R1["red"]
 15 [-]: DIV       R6 R6 K9     ; R6 := R6 / 255.000000
 16 [-]: GETTABLE  R7 R1 K10    ; R7 := R1["green"]
 17 [-]: DIV       R7 R7 K9     ; R7 := R7 / 255.000000
 18 [-]: GETTABLE  R8 R1 K11    ; R8 := R1["blue"]
 19 [-]: DIV       R8 R8 K9     ; R8 := R8 / 255.000000
 20 [-]: CONST     R9 1         ; R9 := 1.000000
 21 [-]: CALL      R2 8 1       ; R2(R3,R4,R5,R6,R7,R8,R9)
 22 [-]: GETGLOBAL R2 K4        ; R2 := 0xae91e43b
 23 [-]: SELF      R2 R2 K12    ; R3 := R2; R2 := R2[0xf64b7262]
 24 [-]: MOVE      R4 R0        ; R4 := R0
 25 [-]: LOADK     R5 K13       ; R5 := "Icon"
 26 [-]: CONST     R6 9         ; R6 := 9.000000
 27 [-]: GETUPVAL  R7 U1        ; R7 := U1
 28 [-]: GETTABLE  R7 R7 K14    ; R7 := R7["FloatingContentHighlight"]
 29 [-]: CALL      R2 6 1       ; R2(R3,R4,R5,R6,R7)
 30 [-]: RETURN    R0 1         ; return 


; Function #70:
;
; Name:            
; Defined at line: 1391
; #Upvalues:       1
; #Parameters:     1
; Is_vararg:       0
; Max Stack Size:  4

  1 [-]: GETUPVAL  R1 U0        ; R1 := U0
  2 [-]: LOADK     R2 K0        ; R2 := "Options.EditMessage.EditAction"
  3 [-]: MOVE      R3 R0        ; R3 := R0
  4 [-]: CONCAT    R2 R2 R3     ; R2 := R2 .. R3
  5 [-]: CALL      R1 2 1       ; R1(R2)
  6 [-]: RETURN    R0 1         ; return 


; Function #71:
;
; Name:            
; Defined at line: 1395
; #Upvalues:       1
; #Parameters:     1
; Is_vararg:       0
; Max Stack Size:  4

  1 [-]: GETUPVAL  R1 U0        ; R1 := U0
  2 [-]: LOADK     R2 K0        ; R2 := "Options.RoomName.EditAction"
  3 [-]: MOVE      R3 R0        ; R3 := R0
  4 [-]: CONCAT    R2 R2 R3     ; R2 := R2 .. R3
  5 [-]: CALL      R1 2 1       ; R1(R2)
  6 [-]: RETURN    R0 1         ; return 


; Function #72:
;
; Name:            
; Defined at line: 1399
; #Upvalues:       1
; #Parameters:     1
; Is_vararg:       0
; Max Stack Size:  10

  1 [-]: GETUPVAL  R1 U0        ; R1 := U0
  2 [-]: GETTABLE  R1 R1 K0     ; R1 := R1["FloatingContentObject"]
  3 [-]: GETGLOBAL R2 K1        ; R2 := 0xae91e43b
  4 [-]: SELF      R2 R2 K2     ; R3 := R2; R2 := R2[0x91e13703]
  5 [-]: MOVE      R4 R0        ; R4 := R0
  6 [-]: LOADK     R5 K3        ; R5 := ".Bg"
  7 [-]: CONCAT    R4 R4 R5     ; R4 := R4 .. R5
  8 [-]: LOADK     R5 K4        ; R5 := "RectEdgeColor"
  9 [-]: GETTABLE  R6 R1 K5     ; R6 := R1["red"]
 10 [-]: DIV       R6 R6 K6     ; R6 := R6 / 255.000000
 11 [-]: GETTABLE  R7 R1 K7     ; R7 := R1["green"]
 12 [-]: DIV       R7 R7 K6     ; R7 := R7 / 255.000000
 13 [-]: GETTABLE  R8 R1 K8     ; R8 := R1["blue"]
 14 [-]: DIV       R8 R8 K6     ; R8 := R8 / 255.000000
 15 [-]: LOADK     R9 K9        ; R9 := 0.300000
 16 [-]: CALL      R2 8 1       ; R2(R3,R4,R5,R6,R7,R8,R9)
 17 [-]: GETGLOBAL R2 K1        ; R2 := 0xae91e43b
 18 [-]: SELF      R2 R2 K10    ; R3 := R2; R2 := R2[0xf64b7262]
 19 [-]: MOVE      R4 R0        ; R4 := R0
 20 [-]: LOADK     R5 K11       ; R5 := "Icon"
 21 [-]: CONST     R6 9         ; R6 := 9.000000
 22 [-]: GETUPVAL  R7 U0        ; R7 := U0
 23 [-]: GETTABLE  R7 R7 K12    ; R7 := R7["FloatingContent"]
 24 [-]: CALL      R2 6 1       ; R2(R3,R4,R5,R6,R7)
 25 [-]: RETURN    R0 1         ; return 


; Function #73:
;
; Name:            
; Defined at line: 1406
; #Upvalues:       1
; #Parameters:     1
; Is_vararg:       0
; Max Stack Size:  4

  1 [-]: GETUPVAL  R1 U0        ; R1 := U0
  2 [-]: LOADK     R2 K0        ; R2 := "Options.EditMessage.EditAction"
  3 [-]: MOVE      R3 R0        ; R3 := R0
  4 [-]: CONCAT    R2 R2 R3     ; R2 := R2 .. R3
  5 [-]: CALL      R1 2 1       ; R1(R2)
  6 [-]: RETURN    R0 1         ; return 


; Function #74:
;
; Name:            
; Defined at line: 1410
; #Upvalues:       1
; #Parameters:     1
; Is_vararg:       0
; Max Stack Size:  4

  1 [-]: GETUPVAL  R1 U0        ; R1 := U0
  2 [-]: LOADK     R2 K0        ; R2 := "Options.RoomName.EditAction"
  3 [-]: MOVE      R3 R0        ; R3 := R0
  4 [-]: CONCAT    R2 R2 R3     ; R2 := R2 .. R3
  5 [-]: CALL      R1 2 1       ; R1(R2)
  6 [-]: RETURN    R0 1         ; return 


; Function #75:
;
; Name:            
; Defined at line: 1414
; #Upvalues:       1
; #Parameters:     3
; Is_vararg:       0
; Max Stack Size:  8

  1 [-]: GETGLOBAL R3 K0        ; R3 := 0x03f57322
  2 [-]: MOVE      R4 R0        ; R4 := R0
  3 [-]: CALL      R3 2 2       ; R3 := R3(R4)
  4 [-]: MOVE      R0 R3        ; R0 := R3
  5 [-]: EQ        0 R0 K1      ; if R0 ~= 1.000000 then PC := 19
  6 [-]: JMP       19           ; PC := 19
  7 [-]: GETUPVAL  R3 U0        ; R3 := U0
  8 [-]: GETTABLE  R3 R3 K2     ; R3 := R3[0x659d451f]
  9 [-]: GETGLOBAL R4 K3        ; R4 := 0x0032441c
 10 [-]: GETTABLE  R4 R4 K4     ; R4 := R4["UISound_Select"]
 11 [-]: CALL      R3 2 1       ; R3(R4)
 12 [-]: GETGLOBAL R3 K5        ; R3 := 0xae91e43b
 13 [-]: SELF      R3 R3 K6     ; R4 := R3; R3 := R3[0x5f56eeab]
 14 [-]: MOVE      R5 R1        ; R5 := R1
 15 [-]: CONST     R6 29        ; R6 := 29.000000
 16 [-]: LOADK     R7 K7        ; R7 := ""
 17 [-]: CALL      R3 5 1       ; R3(R4,R5,R6,R7)
 18 [-]: JMP       24           ; PC := 24
 19 [-]: GETGLOBAL R3 K5        ; R3 := 0xae91e43b
 20 [-]: SELF      R3 R3 K8     ; R4 := R3; R3 := R3[0xe4162eed]
 21 [-]: MOVE      R5 R2        ; R5 := R2
 22 [-]: LOADK     R6 K7        ; R6 := ""
 23 [-]: CALL      R3 4 1       ; R3(R4,R5,R6)
 24 [-]: RETURN    R0 1         ; return 


; Function #76:
;
; Name:            
; Defined at line: 1425
; #Upvalues:       1
; #Parameters:     1
; Is_vararg:       0
; Max Stack Size:  5

  1 [-]: GETUPVAL  R1 U0        ; R1 := U0
  2 [-]: MOVE      R2 R0        ; R2 := R0
  3 [-]: LOADK     R3 K0        ; R3 := "Options.EditMessage.Message"
  4 [-]: LOADK     R4 K1        ; R4 := "UpdateMessage"
  5 [-]: CALL      R1 4 1       ; R1(R2,R3,R4)
  6 [-]: RETURN    R0 1         ; return 


; Function #77:
;
; Name:            
; Defined at line: 1429
; #Upvalues:       1
; #Parameters:     1
; Is_vararg:       0
; Max Stack Size:  5

  1 [-]: GETUPVAL  R1 U0        ; R1 := U0
  2 [-]: MOVE      R2 R0        ; R2 := R0
  3 [-]: LOADK     R3 K0        ; R3 := "Options.RoomName.Message"
  4 [-]: LOADK     R4 K1        ; R4 := "UpdateName"
  5 [-]: CALL      R1 4 1       ; R1(R2,R3,R4)
  6 [-]: RETURN    R0 1         ; return 


; Function #78:
;
; Name:            
; Defined at line: 1433
; #Upvalues:       3
; #Parameters:     1
; Is_vararg:       0
; Max Stack Size:  8

  1 [-]: GETUPVAL  R1 U0        ; R1 := U0
  2 [-]: GETTABLE  R1 R1 K0     ; R1 := R1[0x659d451f]
  3 [-]: GETGLOBAL R2 K1        ; R2 := 0x0032441c
  4 [-]: GETTABLE  R2 R2 K2     ; R2 := R2["UISound_Focus"]
  5 [-]: CALL      R1 2 1       ; R1(R2)
  6 [-]: LOADK     R1 K3        ; R1 := "Options.Destroy"
  7 [-]: GETGLOBAL R2 K4        ; R2 := 0xae91e43b
  8 [-]: SELF      R2 R2 K5     ; R3 := R2; R2 := R2[0xf64b7262]
  9 [-]: MOVE      R4 R1        ; R4 := R1
 10 [-]: LOADK     R5 K6        ; R5 := "Outline"
 11 [-]: CONST     R6 9         ; R6 := 9.000000
 12 [-]: GETUPVAL  R7 U1        ; R7 := U1
 13 [-]: GETTABLE  R7 R7 K7     ; R7 := R7["FloatingContentHighlight"]
 14 [-]: CALL      R2 6 1       ; R2(R3,R4,R5,R6,R7)
 15 [-]: GETGLOBAL R2 K4        ; R2 := 0xae91e43b
 16 [-]: SELF      R2 R2 K5     ; R3 := R2; R2 := R2[0xf64b7262]
 17 [-]: MOVE      R4 R1        ; R4 := R1
 18 [-]: LOADK     R5 K8        ; R5 := "Outline.Backer"
 19 [-]: CONST     R6 10        ; R6 := 10.000000
 20 [-]: CONST     R7 100       ; R7 := 100.000000
 21 [-]: CALL      R2 6 1       ; R2(R3,R4,R5,R6,R7)
 22 [-]: GETGLOBAL R2 K4        ; R2 := 0xae91e43b
 23 [-]: SELF      R2 R2 K5     ; R3 := R2; R2 := R2[0xf64b7262]
 24 [-]: MOVE      R4 R1        ; R4 := R1
 25 [-]: LOADK     R5 K9        ; R5 := "Icon"
 26 [-]: CONST     R6 9         ; R6 := 9.000000
 27 [-]: GETUPVAL  R7 U1        ; R7 := U1
 28 [-]: GETTABLE  R7 R7 K7     ; R7 := R7["FloatingContentHighlight"]
 29 [-]: CALL      R2 6 1       ; R2(R3,R4,R5,R6,R7)
 30 [-]: GETGLOBAL R2 K4        ; R2 := 0xae91e43b
 31 [-]: SELF      R2 R2 K5     ; R3 := R2; R2 := R2[0xf64b7262]
 32 [-]: MOVE      R4 R1        ; R4 := R1
 33 [-]: LOADK     R5 K10       ; R5 := "Label"
 34 [-]: CONST     R6 36        ; R6 := 36.000000
 35 [-]: GETUPVAL  R7 U1        ; R7 := U1
 36 [-]: GETTABLE  R7 R7 K7     ; R7 := R7["FloatingContentHighlight"]
 37 [-]: CALL      R2 6 1       ; R2(R3,R4,R5,R6,R7)
 38 [-]: GETUPVAL  R2 U2        ; R2 := U2
 39 [-]: EQ        1 R2 K11     ; if R2 == "" then PC := 48
 40 [-]: JMP       48           ; PC := 48
 41 [-]: GETGLOBAL R2 K12       ; R2 := _T
 42 [-]: GETGLOBAL R3 K4        ; R3 := 0xae91e43b
 43 [-]: SELF      R3 R3 K14    ; R4 := R3; R3 := R3[0x42b04007]
 44 [-]: GETUPVAL  R5 U2        ; R5 := U2
 45 [-]: LOADKB    R6 0 0       ; R6 := false
 46 [-]: CALL      R3 4 2       ; R3 := R3(R4,R5,R6)
 47 [-]: SETTABLE  R2 K13 R3    ; R2["gToolTip"] := R3
 48 [-]: RETURN    R0 1         ; return 


; Function #79:
;
; Name:            
; Defined at line: 1447
; #Upvalues:       1
; #Parameters:     1
; Is_vararg:       0
; Max Stack Size:  8

  1 [-]: LOADK     R1 K0        ; R1 := "Options.Destroy"
  2 [-]: GETGLOBAL R2 K1        ; R2 := 0xae91e43b
  3 [-]: SELF      R2 R2 K2     ; R3 := R2; R2 := R2[0xf64b7262]
  4 [-]: MOVE      R4 R1        ; R4 := R1
  5 [-]: LOADK     R5 K3        ; R5 := "Outline"
  6 [-]: CONST     R6 9         ; R6 := 9.000000
  7 [-]: GETUPVAL  R7 U0        ; R7 := U0
  8 [-]: GETTABLE  R7 R7 K4     ; R7 := R7["FloatingContent"]
  9 [-]: CALL      R2 6 1       ; R2(R3,R4,R5,R6,R7)
 10 [-]: GETGLOBAL R2 K1        ; R2 := 0xae91e43b
 11 [-]: SELF      R2 R2 K2     ; R3 := R2; R2 := R2[0xf64b7262]
 12 [-]: MOVE      R4 R1        ; R4 := R1
 13 [-]: LOADK     R5 K5        ; R5 := "Outline.Backer"
 14 [-]: CONST     R6 10        ; R6 := 10.000000
 15 [-]: CONST     R7 20        ; R7 := 20.000000
 16 [-]: CALL      R2 6 1       ; R2(R3,R4,R5,R6,R7)
 17 [-]: GETGLOBAL R2 K1        ; R2 := 0xae91e43b
 18 [-]: SELF      R2 R2 K2     ; R3 := R2; R2 := R2[0xf64b7262]
 19 [-]: MOVE      R4 R1        ; R4 := R1
 20 [-]: LOADK     R5 K6        ; R5 := "Icon"
 21 [-]: CONST     R6 9         ; R6 := 9.000000
 22 [-]: GETUPVAL  R7 U0        ; R7 := U0
 23 [-]: GETTABLE  R7 R7 K4     ; R7 := R7["FloatingContent"]
 24 [-]: CALL      R2 6 1       ; R2(R3,R4,R5,R6,R7)
 25 [-]: GETGLOBAL R2 K1        ; R2 := 0xae91e43b
 26 [-]: SELF      R2 R2 K2     ; R3 := R2; R2 := R2[0xf64b7262]
 27 [-]: MOVE      R4 R1        ; R4 := R1
 28 [-]: LOADK     R5 K7        ; R5 := "Label"
 29 [-]: CONST     R6 36        ; R6 := 36.000000
 30 [-]: GETUPVAL  R7 U0        ; R7 := U0
 31 [-]: GETTABLE  R7 R7 K4     ; R7 := R7["FloatingContent"]
 32 [-]: CALL      R2 6 1       ; R2(R3,R4,R5,R6,R7)
 33 [-]: GETGLOBAL R2 K8        ; R2 := _T
 34 [-]: SETTABLE  R2 K9 K10    ; R2["gToolTip"] := nil
 35 [-]: RETURN    R0 1         ; return 


; Function #80:
;
; Name:            
; Defined at line: 1458
; #Upvalues:       1
; #Parameters:     1
; Is_vararg:       0
; Max Stack Size:  5

  1 [-]: GETUPVAL  R1 U0        ; R1 := U0
  2 [-]: EQ        1 R1 K0      ; if R1 == nil then PC := 9
  3 [-]: JMP       9            ; PC := 9
  4 [-]: GETGLOBAL R1 K1        ; R1 := 0xae91e43b
  5 [-]: SELF      R1 R1 K2     ; R2 := R1; R1 := R1[0xe4162eed]
  6 [-]: GETUPVAL  R3 U0        ; R3 := U0
  7 [-]: LOADK     R4 K3        ; R4 := ""
  8 [-]: CALL      R1 4 1       ; R1(R2,R3,R4)
  9 [-]: RETURN    R0 1         ; return 


; Function #81:
;
; Name:            
; Defined at line: 1464
; #Upvalues:       1
; #Parameters:     4
; Is_vararg:       0
; Max Stack Size:  8

  1 [-]: GETGLOBAL R4 K0        ; R4 := 0x7b998233
  2 [-]: GETUPVAL  R5 U0        ; R5 := U0
  3 [-]: CALL      R4 2 2       ; R4 := R4(R5)
  4 [-]: TEST      R4 1         ; if R4 then PC := 11
  5 [-]: JMP       11           ; PC := 11
  6 [-]: GETUPVAL  R4 U0        ; R4 := U0
  7 [-]: SELF      R4 R4 K1     ; R5 := R4; R4 := R4[0xfaa69527]
  8 [-]: MOVE      R6 R0        ; R6 := R0
  9 [-]: MOVE      R7 R1        ; R7 := R1
 10 [-]: CALL      R4 4 1       ; R4(R5,R6,R7)
 11 [-]: RETURN    R0 1         ; return 


; Function #82:
;
; Name:            
; Defined at line: 1470
; #Upvalues:       1
; #Parameters:     1
; Is_vararg:       0
; Max Stack Size:  9

  1 [-]: EQ        1 R0 K0      ; if R0 == "true" then PC := 4
  2 [-]: JMP       4            ; PC := 4
  3 [-]: LOADKB    R0 0 1       ; R0 := false; PC := 4
  4 [-]: LOADKB    R0 1 0       ; R0 := true
  5 [-]: GETGLOBAL R1 K1        ; R1 := 0xae91e43b
  6 [-]: SELF      R1 R1 K2     ; R2 := R1; R1 := R1[0x80dc5f76]
  7 [-]: CALL      R1 2 1       ; R1(R2)
  8 [-]: GETGLOBAL R1 K1        ; R1 := 0xae91e43b
  9 [-]: SELF      R1 R1 K3     ; R2 := R1; R1 := R1[0x5f56eeab]
 10 [-]: LOADK     R3 K4        ; R3 := "Options.EditMessage.Message"
 11 [-]: CONST     R4 49        ; R4 := 49.000000
 12 [-]: GETUPVAL  R5 U0        ; R5 := U0
 13 [-]: GETTABLE  R5 R5 K5     ; R5 := R5[0x06d055f9]
 14 [-]: MOVE      R6 R0        ; R6 := R0
 15 [-]: LOADK     R7 K6        ; R7 := "input"
 16 [-]: LOADK     R8 K7        ; R8 := "dynamic"
 17 [-]: CALL      R5 4 0       ; R5,... := R5(R6,R7,R8)
 18 [-]: CALL      R1 0 1       ; R1(R2,...)
 19 [-]: GETGLOBAL R1 K1        ; R1 := 0xae91e43b
 20 [-]: SELF      R1 R1 K3     ; R2 := R1; R1 := R1[0x5f56eeab]
 21 [-]: LOADK     R3 K8        ; R3 := "Options.RoomName.Message"
 22 [-]: CONST     R4 49        ; R4 := 49.000000
 23 [-]: GETUPVAL  R5 U0        ; R5 := U0
 24 [-]: GETTABLE  R5 R5 K5     ; R5 := R5[0x06d055f9]
 25 [-]: MOVE      R6 R0        ; R6 := R0
 26 [-]: LOADK     R7 K6        ; R7 := "input"
 27 [-]: LOADK     R8 K7        ; R8 := "dynamic"
 28 [-]: CALL      R5 4 0       ; R5,... := R5(R6,R7,R8)
 29 [-]: CALL      R1 0 1       ; R1(R2,...)
 30 [-]: RETURN    R0 1         ; return 


; Function #83:
;
; Name:            
; Defined at line: 1478
; #Upvalues:       0
; #Parameters:     0
; Is_vararg:       0
; Max Stack Size:  2

  1 [-]: LOADKB    R0 1 0       ; R0 := true
  2 [-]: RETURN    R0 2         ; return R0
  3 [-]: RETURN    R0 1         ; return 


