; Name:            
; Defined at line: 1
; #Upvalues:       0
; #Parameters:     0
; Is_vararg:       1
; Max Stack Size:  121

            1 [-]: GETIMPORT R0 1 [nil]
       2 [-]: LOADK R1 K2 ["EE.Interface.Utilities"]
       3 [-]: CALL R0 1 1  
       4 [-]: GETIMPORT R1 1 [nil]
       5 [-]: LOADK R2 K3 ["Lotus.Interface.LotusUtilities"]
       6 [-]: CALL R1 1 1  
       7 [-]: GETIMPORT R2 1 [nil]
       8 [-]: LOADK R3 K4 ["Lotus.Scripts.Libs.TransmissionSet"]
       9 [-]: CALL R2 1 1  
      10 [-]: GETIMPORT R3 1 [nil]
      11 [-]: LOADK R4 K5 ["Lotus.Scripts.Libs.CommonGamemodeFunctions"]
      12 [-]: CALL R3 1 1  
      13 [-]: GETIMPORT R4 1 [nil]
      14 [-]: LOADK R5 K6 ["Lotus.Scripts.Libs.ObjectiveText"]
      15 [-]: CALL R4 1 1  
      16 [-]: GETIMPORT R5 1 [nil]
      17 [-]: LOADK R6 K7 ["Lotus.Scripts.Libs.LandscapeLib"]
      18 [-]: CALL R5 1 1  
      19 [-]: LOADN R6 1   
      20 [-]: LOADN R7 3   
      21 [-]: LOADN R8 0   
      22 [-]: LOADN R9 0   
      23 [-]: LOADN R10 0  
      24 [-]: NEWTABLE R11 0 4
      25 [-]: LOADN R12 8  
      26 [-]: LOADN R13 15 
      27 [-]: LOADN R14 25 
      28 [-]: LOADN R15 30 
      29 [-]: SETLIST R11 R12 4 [1]
      30 [-]: NEWTABLE R12 0 4
      31 [-]: LOADN R13 12 
      32 [-]: LOADN R14 25 
      33 [-]: LOADN R15 30 
      34 [-]: LOADN R16 35 
      35 [-]: SETLIST R12 R13 4 [1]
      36 [-]: NEWTABLE R13 0 4
      37 [-]: LOADN R14 7  
      38 [-]: LOADN R15 15 
      39 [-]: LOADN R16 25 
      40 [-]: LOADN R17 30 
      41 [-]: SETLIST R13 R14 4 [1]
      42 [-]: NEWTABLE R14 0 4
      43 [-]: LOADN R15 10 
      44 [-]: LOADN R16 25 
      45 [-]: LOADN R17 30 
      46 [-]: LOADN R18 35 
      47 [-]: SETLIST R14 R15 4 [1]
      48 [-]: NEWTABLE R15 0 4
      49 [-]: LOADN R16 5  
      50 [-]: LOADN R17 5  
      51 [-]: LOADN R18 5  
      52 [-]: LOADN R19 5  
      53 [-]: SETLIST R15 R16 4 [1]
      54 [-]: NEWTABLE R16 0 4
      55 [-]: LOADN R17 5  
      56 [-]: LOADN R18 5  
      57 [-]: LOADN R19 5  
      58 [-]: LOADN R20 5  
      59 [-]: SETLIST R16 R17 4 [1]
      60 [-]: LOADN R17 0  
      61 [-]: LOADN R18 0  
      62 [-]: LOADN R19 900
      63 [-]: LOADN R20 1020
      64 [-]: LOADNIL R21  
      65 [-]: LOADN R22 100
      66 [-]: LOADN R23 100
      67 [-]: LOADB R24 0  
      68 [-]: GETIMPORT R25 9 [nil]
      69 [-]: LOADK R26 K10 ["HiddenMissionTimer"]
      70 [-]: CALL R25 1 1 
      71 [-]: GETIMPORT R26 9 [nil]
      72 [-]: LOADK R27 K11 ["ExcavationScanner"]
      73 [-]: CALL R26 1 1 
      74 [-]: GETIMPORT R27 9 [nil]
      75 [-]: LOADK R28 K12 ["ExcavationExtractor"]
      76 [-]: CALL R27 1 1 
      77 [-]: GETIMPORT R28 9 [nil]
      78 [-]: LOADK R29 K13 ["ExcavationExtractorSand"]
      79 [-]: CALL R28 1 1 
      80 [-]: GETIMPORT R29 9 [nil]
      81 [-]: LOADK R30 K14 ["ExcavatorAvatar"]
      82 [-]: CALL R29 1 1 
      83 [-]: GETIMPORT R30 9 [nil]
      84 [-]: LOADK R31 K15 ["ExcavationState"]
      85 [-]: CALL R30 1 1 
      86 [-]: GETIMPORT R31 9 [nil]
      87 [-]: LOADK R32 K16 ["ExcavatorMover"]
      88 [-]: CALL R31 1 1 
      89 [-]: GETIMPORT R32 9 [nil]
      90 [-]: LOADK R33 K17 ["ExcavationScannerDeco"]
      91 [-]: CALL R32 1 1 
      92 [-]: GETIMPORT R33 9 [nil]
      93 [-]: LOADK R34 K18 ["ExcavationObjectiveMarker"]
      94 [-]: CALL R33 1 1 
      95 [-]: GETIMPORT R34 9 [nil]
      96 [-]: LOADK R35 K19 ["ScannerTrigger"]
      97 [-]: CALL R34 1 1 
      98 [-]: GETIMPORT R35 9 [nil]
      99 [-]: LOADK R36 K15 ["ExcavationState"]
     100 [-]: CALL R35 1 1 
     101 [-]: GETIMPORT R36 9 [nil]
     102 [-]: LOADK R37 K20 ["ScannerPowerVal"]
     103 [-]: CALL R36 1 1 
     104 [-]: GETIMPORT R37 9 [nil]
     105 [-]: LOADK R38 K21 ["ScanTime"]
     106 [-]: CALL R37 1 1 
     107 [-]: GETIMPORT R38 9 [nil]
     108 [-]: LOADK R39 K22 ["TimeElapsed"]
     109 [-]: CALL R38 1 1 
     110 [-]: GETIMPORT R39 9 [nil]
     111 [-]: LOADK R40 K23 ["DigsScore"]
     112 [-]: CALL R39 1 1 
     113 [-]: GETIMPORT R40 9 [nil]
     114 [-]: LOADK R41 K24 ["Score"]
     115 [-]: CALL R40 1 1 
     116 [-]: GETIMPORT R41 9 [nil]
     117 [-]: LOADK R42 K25 ["ExcavatorsSpawned"]
     118 [-]: CALL R41 1 1 
     119 [-]: GETIMPORT R42 9 [nil]
     120 [-]: LOADK R43 K26 ["ExcavatorsStarted"]
     121 [-]: CALL R42 1 1 
     122 [-]: GETIMPORT R43 9 [nil]
     123 [-]: LOADK R44 K27 ["ExcavatorsEnded"]
     124 [-]: CALL R43 1 1 
     125 [-]: GETIMPORT R44 9 [nil]
     126 [-]: LOADK R45 K28 ["LastSuccessfulDig"]
     127 [-]: CALL R44 1 1 
     128 [-]: GETIMPORT R45 9 [nil]
     129 [-]: LOADK R46 K29 ["RewardsGiven"]
     130 [-]: CALL R45 1 1 
     131 [-]: GETIMPORT R46 9 [nil]
     132 [-]: LOADK R47 K30 ["LastBossSpawnTime"]
     133 [-]: CALL R46 1 1 
     134 [-]: GETIMPORT R47 9 [nil]
     135 [-]: LOADK R48 K31 ["VoidProjectionFlow"]
     136 [-]: CALL R47 1 1 
     137 [-]: GETIMPORT R48 9 [nil]
     138 [-]: LOADK R49 K32 ["DigsFullyCompleted"]
     139 [-]: CALL R48 1 1 
     140 [-]: GETIMPORT R49 9 [nil]
     141 [-]: LOADK R50 K33 ["CustomMissionHealth"]
     142 [-]: CALL R49 1 1 
     143 [-]: GETIMPORT R50 9 [nil]
     144 [-]: LOADK R51 K34 ["PossibleAFKFarming"]
     145 [-]: CALL R50 1 1 
     146 [-]: GETIMPORT R51 9 [nil]
     147 [-]: LOADK R52 K35 ["ExcavatorStatesCount"]
     148 [-]: CALL R51 1 1 
     149 [-]: GETIMPORT R52 9 [nil]
     150 [-]: LOADK R53 K36 ["ModeAlreadyStarted"]
     151 [-]: CALL R52 1 1 
     152 [-]: GETIMPORT R53 9 [nil]
     153 [-]: LOADK R54 K37 ["mArenaComplete"]
     154 [-]: CALL R53 1 1 
     155 [-]: GETIMPORT R54 9 [nil]
     156 [-]: LOADK R55 K38 ["Infestation"]
     157 [-]: CALL R54 1 1 
     158 [-]: GETIMPORT R55 9 [nil]
     159 [-]: LOADK R56 K39 ["RandomTeam"]
     160 [-]: CALL R55 1 1 
     161 [-]: GETIMPORT R56 9 [nil]
     162 [-]: LOADK R57 K40 ["DefenseAgentSpawn"]
     163 [-]: CALL R56 1 1 
     164 [-]: GETIMPORT R57 9 [nil]
     165 [-]: LOADK R58 K41 ["BipedSpecialSpawn"]
     166 [-]: CALL R57 1 1 
     167 [-]: GETIMPORT R58 9 [nil]
     168 [-]: LOADK R59 K42 ["DoNotUse"]
     169 [-]: CALL R58 1 1 
     170 [-]: GETIMPORT R59 9 [nil]
     171 [-]: LOADK R60 K43 ["CameraSpawn"]
     172 [-]: CALL R59 1 1 
     173 [-]: GETIMPORT R60 9 [nil]
     174 [-]: LOADK R61 K44 ["TurretSpawn"]
     175 [-]: CALL R60 1 1 
     176 [-]: GETIMPORT R61 9 [nil]
     177 [-]: LOADK R62 K45 ["ExitMarker"]
     178 [-]: CALL R61 1 1 
     179 [-]: GETIMPORT R62 9 [nil]
     180 [-]: LOADK R63 K46 ["MissionExtractionAvailable"]
     181 [-]: CALL R62 1 1 
     182 [-]: GETIMPORT R63 9 [nil]
     183 [-]: LOADK R64 K47 ["MissionExcavatorItemFound"]
     184 [-]: CALL R63 1 1 
     185 [-]: GETIMPORT R64 9 [nil]
     186 [-]: LOADK R65 K48 ["NV_FOUND_PISTOLS"]
     187 [-]: CALL R64 1 1 
     188 [-]: LOADNIL R65  
     189 [-]: GETIMPORT R66 9 [nil]
     190 [-]: LOADK R67 K49 ["BeamAttach"]
     191 [-]: CALL R66 1 1 
     192 [-]: GETIMPORT R67 9 [nil]
     193 [-]: LOADK R68 K50 ["BeamX"]
     194 [-]: CALL R67 1 1 
     195 [-]: GETIMPORT R68 9 [nil]
     196 [-]: LOADK R69 K51 ["BeamY"]
     197 [-]: CALL R68 1 1 
     198 [-]: GETIMPORT R69 9 [nil]
     199 [-]: LOADK R70 K52 ["BeamZ"]
     200 [-]: CALL R69 1 1 
     201 [-]: GETIMPORT R70 54 [nil]
     202 [-]: LOADK R71 K55 ["/Lotus/Fx/Gameplay/MoonShieldBeam"]
     203 [-]: CALL R70 1 1 
     204 [-]: LOADNIL R71  
     205 [-]: LOADNIL R72  
     206 [-]: LOADNIL R73  
     207 [-]: LOADNIL R74  
     208 [-]: GETIMPORT R75 9 [nil]
     209 [-]: LOADK R76 K56 ["SolNode332"]
     210 [-]: CALL R75 1 1 
     211 [-]: LOADB R76 0  
     212 [-]: LOADNIL R77  
     213 [-]: LOADNIL R78  
     214 [-]: LOADNIL R79  
     215 [-]: GETIMPORT R80 58 [nil]
     216 [-]: LOADK R81 K59 ["/Lotus/Interface/SurvivalReward.swf"]
     217 [-]: CALL R80 1 1 
     218 [-]: GETIMPORT R81 9 [nil]
     219 [-]: LOADK R82 K60 ["DuviriQuest"]
     220 [-]: CALL R81 1 1 
     221 [-]: GETIMPORT R82 62 [nil]
     222 [-]: LOADK R83 K63 ["/Lotus/Types/Friendly/PlayerControllable/ControllableDuviriDrifterTennoAvatar"]
     223 [-]: CALL R82 1 1 
     224 [-]: NEWCLOSURE R83 P0
     225 [-]: MOVE R1 R76  
     226 [-]: MOVE R0 R52  
     227 [-]: DUPCLOSURE R84 K64 []
     228 [-]: MOVE R0 R1   
     229 [-]: DUPCLOSURE R85 K65 []
     230 [-]: MOVE R0 R1   
     231 [-]: DUPCLOSURE R86 K66 []
     232 [-]: DUPCLOSURE R87 K67 []
     233 [-]: DUPCLOSURE R88 K68 []
     234 [-]: DUPCLOSURE R89 K69 []
     235 [-]: MOVE R0 R30  
     236 [-]: MOVE R0 R88  
     237 [-]: SETGLOBAL R89 K70 ["ShowExcavationFX"]
     238 [-]: DUPCLOSURE R89 K71 []
     239 [-]: DUPCLOSURE R90 K72 []
     240 [-]: MOVE R0 R37  
     241 [-]: DUPCLOSURE R91 K73 []
     242 [-]: MOVE R0 R37  
     243 [-]: DUPCLOSURE R92 K74 []
     244 [-]: MOVE R0 R80  
     245 [-]: DUPCLOSURE R93 K75 []
     246 [-]: MOVE R0 R45  
     247 [-]: MOVE R0 R80  
     248 [-]: MOVE R0 R66  
     249 [-]: MOVE R0 R70  
     250 [-]: MOVE R0 R67  
     251 [-]: MOVE R0 R68  
     252 [-]: MOVE R0 R69  
     253 [-]: MOVE R0 R89  
     254 [-]: DUPCLOSURE R94 K76 []
     255 [-]: MOVE R0 R45  
     256 [-]: MOVE R0 R80  
     257 [-]: NEWCLOSURE R95 P13
     258 [-]: MOVE R1 R76  
     259 [-]: MOVE R0 R29  
     260 [-]: DUPCLOSURE R96 K77 []
     261 [-]: MOVE R0 R42  
     262 [-]: MOVE R0 R95  
     263 [-]: DUPCLOSURE R97 K78 []
     264 [-]: DUPCLOSURE R98 K79 []
     265 [-]: MOVE R0 R95  
     266 [-]: DUPCLOSURE R99 K80 []
     267 [-]: MOVE R0 R81  
     268 [-]: DUPCLOSURE R100 K81 []
     269 [-]: NEWCLOSURE R101 P19
     270 [-]: MOVE R1 R72  
     271 [-]: MOVE R1 R20  
     272 [-]: MOVE R1 R19  
     273 [-]: MOVE R1 R76  
     274 [-]: MOVE R0 R46  
     275 [-]: MOVE R0 R99  
     276 [-]: MOVE R0 R55  
     277 [-]: MOVE R0 R98  
     278 [-]: MOVE R0 R81  
     279 [-]: MOVE R0 R5   
     280 [-]: MOVE R0 R40  
     281 [-]: MOVE R1 R9   
     282 [-]: NEWCLOSURE R102 P20
     283 [-]: MOVE R0 R81  
     284 [-]: MOVE R0 R15  
     285 [-]: MOVE R0 R16  
     286 [-]: MOVE R0 R54  
     287 [-]: MOVE R0 R11  
     288 [-]: MOVE R0 R12  
     289 [-]: MOVE R0 R13  
     290 [-]: MOVE R0 R14  
     291 [-]: MOVE R0 R0   
     292 [-]: MOVE R1 R10  
     293 [-]: MOVE R1 R71  
     294 [-]: MOVE R1 R8   
     295 [-]: NEWCLOSURE R103 P21
     296 [-]: MOVE R1 R18  
     297 [-]: MOVE R1 R10  
     298 [-]: NEWCLOSURE R104 P22
     299 [-]: MOVE R1 R10  
     300 [-]: NEWCLOSURE R105 P23
     301 [-]: MOVE R0 R39  
     302 [-]: MOVE R0 R102 
     303 [-]: MOVE R0 R104 
     304 [-]: MOVE R0 R100 
     305 [-]: MOVE R1 R17  
     306 [-]: MOVE R0 R42  
     307 [-]: MOVE R0 R101 
     308 [-]: MOVE R1 R18  
     309 [-]: MOVE R1 R10  
     310 [-]: DUPCLOSURE R106 K82 []
     311 [-]: MOVE R0 R0   
     312 [-]: DUPCLOSURE R107 K83 []
     313 [-]: NEWCLOSURE R108 P26
     314 [-]: MOVE R1 R71  
     315 [-]: MOVE R1 R65  
     316 [-]: MOVE R0 R28  
     317 [-]: MOVE R0 R27  
     318 [-]: MOVE R1 R76  
     319 [-]: MOVE R0 R0   
     320 [-]: MOVE R0 R3   
     321 [-]: MOVE R0 R107 
     322 [-]: MOVE R0 R106 
     323 [-]: NEWCLOSURE R109 P27
     324 [-]: MOVE R1 R72  
     325 [-]: MOVE R1 R8   
     326 [-]: MOVE R1 R7   
     327 [-]: MOVE R1 R65  
     328 [-]: MOVE R0 R108 
     329 [-]: MOVE R0 R41  
     330 [-]: MOVE R0 R42  
     331 [-]: MOVE R0 R37  
     332 [-]: MOVE R0 R39  
     333 [-]: MOVE R1 R77  
     334 [-]: MOVE R1 R23  
     335 [-]: MOVE R0 R1   
     336 [-]: MOVE R0 R48  
     337 [-]: MOVE R1 R74  
     338 [-]: MOVE R0 R84  
     339 [-]: MOVE R0 R2   
     340 [-]: MOVE R0 R0   
     341 [-]: NEWCLOSURE R110 P28
     342 [-]: MOVE R1 R73  
     343 [-]: MOVE R0 R47  
     344 [-]: MOVE R0 R0   
     345 [-]: MOVE R0 R1   
     346 [-]: NEWCLOSURE R111 P29
     347 [-]: MOVE R1 R76  
     348 [-]: MOVE R0 R56  
     349 [-]: MOVE R0 R57  
     350 [-]: MOVE R0 R58  
     351 [-]: MOVE R0 R59  
     352 [-]: MOVE R0 R60  
     353 [-]: MOVE R1 R79  
     354 [-]: MOVE R0 R61  
     355 [-]: MOVE R0 R35  
     356 [-]: MOVE R0 R38  
     357 [-]: MOVE R1 R24  
     358 [-]: MOVE R0 R50  
     359 [-]: MOVE R0 R105 
     360 [-]: MOVE R0 R25  
     361 [-]: MOVE R0 R40  
     362 [-]: MOVE R0 R42  
     363 [-]: MOVE R0 R29  
     364 [-]: MOVE R0 R33  
     365 [-]: MOVE R0 R96  
     366 [-]: MOVE R0 R109 
     367 [-]: MOVE R1 R74  
     368 [-]: MOVE R0 R62  
     369 [-]: MOVE R0 R64  
     370 [-]: MOVE R0 R1   
     371 [-]: MOVE R0 R2   
     372 [-]: MOVE R0 R81  
     373 [-]: MOVE R1 R72  
     374 [-]: MOVE R0 R39  
     375 [-]: MOVE R1 R23  
     376 [-]: MOVE R0 R110 
     377 [-]: MOVE R0 R44  
     378 [-]: DUPCLOSURE R112 K84 []
     379 [-]: MOVE R0 R26  
     380 [-]: MOVE R0 R30  
     381 [-]: MOVE R0 R33  
     382 [-]: NEWCLOSURE R113 P31
     383 [-]: MOVE R1 R71  
     384 [-]: MOVE R1 R73  
     385 [-]: MOVE R1 R76  
     386 [-]: MOVE R1 R72  
     387 [-]: MOVE R1 R20  
     388 [-]: MOVE R1 R19  
     389 [-]: MOVE R0 R75  
     390 [-]: MOVE R1 R74  
     391 [-]: MOVE R1 R23  
     392 [-]: MOVE R1 R22  
     393 [-]: MOVE R0 R1   
     394 [-]: MOVE R1 R77  
     395 [-]: DUPCLOSURE R114 K85 []
     396 [-]: MOVE R0 R4   
     397 [-]: MOVE R0 R35  
     398 [-]: MOVE R0 R36  
     399 [-]: MOVE R0 R37  
     400 [-]: MOVE R0 R39  
     401 [-]: MOVE R0 R40  
     402 [-]: MOVE R0 R41  
     403 [-]: MOVE R0 R42  
     404 [-]: MOVE R0 R43  
     405 [-]: MOVE R0 R44  
     406 [-]: MOVE R0 R45  
     407 [-]: MOVE R0 R46  
     408 [-]: MOVE R0 R47  
     409 [-]: MOVE R0 R48  
     410 [-]: MOVE R0 R49  
     411 [-]: MOVE R0 R50  
     412 [-]: MOVE R0 R51  
     413 [-]: MOVE R0 R38  
     414 [-]: NEWCLOSURE R115 P33
     415 [-]: MOVE R0 R2   
     416 [-]: MOVE R1 R74  
     417 [-]: MOVE R0 R35  
     418 [-]: NEWCLOSURE R116 P34
     419 [-]: MOVE R1 R78  
     420 [-]: MOVE R0 R113 
     421 [-]: MOVE R0 R45  
     422 [-]: MOVE R1 R76  
     423 [-]: MOVE R0 R52  
     424 [-]: MOVE R0 R47  
     425 [-]: MOVE R0 R40  
     426 [-]: MOVE R0 R110 
     427 [-]: MOVE R0 R53  
     428 [-]: MOVE R0 R35  
     429 [-]: MOVE R0 R115 
     430 [-]: MOVE R0 R111 
     431 [-]: MOVE R0 R114 
     432 [-]: MOVE R0 R32  
     433 [-]: MOVE R0 R31  
     434 [-]: MOVE R0 R93  
     435 [-]: SETGLOBAL R116 K86 ["Excavation"]
     436 [-]: NEWCLOSURE R116 P35
     437 [-]: MOVE R1 R78  
     438 [-]: MOVE R0 R113 
     439 [-]: MOVE R1 R76  
     440 [-]: MOVE R0 R82  
     441 [-]: MOVE R1 R77  
     442 [-]: MOVE R1 R23  
     443 [-]: MOVE R0 R1   
     444 [-]: MOVE R0 R0   
     445 [-]: MOVE R1 R74  
     446 [-]: MOVE R1 R72  
     447 [-]: MOVE R0 R51  
     448 [-]: MOVE R0 R30  
     449 [-]: MOVE R0 R35  
     450 [-]: MOVE R1 R73  
     451 [-]: MOVE R0 R4   
     452 [-]: MOVE R1 R79  
     453 [-]: MOVE R0 R61  
     454 [-]: MOVE R0 R40  
     455 [-]: MOVE R0 R48  
     456 [-]: MOVE R0 R45  
     457 [-]: MOVE R0 R80  
     458 [-]: MOVE R0 R3   
     459 [-]: SETGLOBAL R116 K87 ["ExcavationHUD"]
     460 [-]: NEWCLOSURE R116 P36
     461 [-]: MOVE R0 R27  
     462 [-]: MOVE R1 R71  
     463 [-]: MOVE R0 R28  
     464 [-]: MOVE R1 R76  
     465 [-]: MOVE R0 R52  
     466 [-]: MOVE R1 R21  
     467 [-]: MOVE R1 R7   
     468 [-]: DUPCLOSURE R117 K88 []
     469 [-]: NEWCLOSURE R118 P38
     470 [-]: MOVE R1 R71  
     471 [-]: MOVE R1 R7   
     472 [-]: MOVE R0 R116 
     473 [-]: MOVE R0 R35  
     474 [-]: MOVE R0 R36  
     475 [-]: MOVE R0 R32  
     476 [-]: MOVE R1 R76  
     477 [-]: MOVE R0 R52  
     478 [-]: MOVE R0 R37  
     479 [-]: MOVE R0 R29  
     480 [-]: MOVE R0 R33  
     481 [-]: MOVE R0 R41  
     482 [-]: MOVE R0 R117 
     483 [-]: MOVE R1 R21  
     484 [-]: MOVE R0 R2   
     485 [-]: MOVE R1 R22  
     486 [-]: MOVE R0 R0   
     487 [-]: DUPCLOSURE R119 K89 []
     488 [-]: MOVE R0 R118 
     489 [-]: SETGLOBAL R119 K90 ["Scanner"]
     490 [-]: NEWCLOSURE R119 P40
     491 [-]: MOVE R1 R22  
     492 [-]: MOVE R0 R66  
     493 [-]: MOVE R0 R67  
     494 [-]: MOVE R0 R68  
     495 [-]: MOVE R0 R69  
     496 [-]: MOVE R0 R89  
     497 [-]: NEWCLOSURE R120 P41
     498 [-]: MOVE R0 R1   
     499 [-]: MOVE R0 R113 
     500 [-]: MOVE R1 R22  
     501 [-]: MOVE R1 R6   
     502 [-]: MOVE R0 R35  
     503 [-]: MOVE R0 R42  
     504 [-]: MOVE R0 R2   
     505 [-]: MOVE R0 R88  
     506 [-]: MOVE R0 R33  
     507 [-]: MOVE R0 R49  
     508 [-]: MOVE R0 R25  
     509 [-]: MOVE R1 R76  
     510 [-]: MOVE R0 R52  
     511 [-]: MOVE R0 R119 
     512 [-]: MOVE R0 R0   
     513 [-]: MOVE R0 R43  
     514 [-]: MOVE R0 R48  
     515 [-]: MOVE R1 R23  
     516 [-]: MOVE R0 R38  
     517 [-]: MOVE R0 R44  
     518 [-]: MOVE R0 R89  
     519 [-]: MOVE R0 R39  
     520 [-]: MOVE R0 R40  
     521 [-]: MOVE R1 R77  
     522 [-]: MOVE R1 R71  
     523 [-]: MOVE R1 R74  
     524 [-]: MOVE R0 R84  
     525 [-]: MOVE R1 R72  
     526 [-]: MOVE R1 R73  
     527 [-]: MOVE R0 R87  
     528 [-]: MOVE R0 R94  
     529 [-]: MOVE R0 R63  
     530 [-]: MOVE R0 R64  
     531 [-]: SETGLOBAL R120 K14 ["ExcavatorAvatar"]
     532 [-]: DUPCLOSURE R120 K91 []
     533 [-]: MOVE R0 R39  
     534 [-]: MOVE R0 R40  
     535 [-]: SETGLOBAL R120 K92 ["EndMission"]
     536 [-]: DUPCLOSURE R120 K93 []
     537 [-]: MOVE R0 R35  
     538 [-]: SETGLOBAL R120 K94 ["HostMigrationInit"]
     539 [-]: DUPCLOSURE R120 K95 []
     540 [-]: MOVE R0 R29  
     541 [-]: SETGLOBAL R120 K96 ["BatteryBeam"]
     542 [-]: DUPCLOSURE R120 K97 []
     543 [-]: SETGLOBAL R120 K98 ["OnExcavatorDeath"]
     544 [-]: CLOSEUPVALS R6
     545 [-]: RETURN R0 0  


; Name:            
; Defined at line: 211
; #Upvalues:       2
; #Parameters:     0
; Is_vararg:       0
; Max Stack Size:  5

       0 [-]: GETUPVAL R0 0
       1 [-]: JUMPIFNOT R0 L2
       2 [-]: GETIMPORT R0 1 [nil]
       3 [-]: NAMECALL R0 R0 K2 [0x18D05D30]
       4 [-]: CALL R0 1 1  
       5 [-]: JUMPIFNOT R0 L1
       6 [-]: GETIMPORT R1 4 [nil]
       7 [-]: GETUPVAL R3 1
       8 [-]: LOADN R4 0   
       9 [-]: NAMECALL R1 R1 K5 [0x0EB34C69]
      10 [-]: CALL R1 3 1  
      11 [-]: JUMPXEQKN R1 K6 L0 [1]
      12 [-]: LOADB R0 0 +1
L 0:  13 [-]: LOADB R0 1   
L 1:  14 [-]: RETURN R0 1  
L 2:  15 [-]: GETIMPORT R0 8 [nil]
      16 [-]: RETURN R0 1  


; Name:            
; Defined at line: 219
; #Upvalues:       1
; #Parameters:     0
; Is_vararg:       0
; Max Stack Size:  6

       0 [-]: GETIMPORT R1 1 [nil]
       1 [-]: FASTCALL1 62 R1 L0
       2 [-]: GETIMPORT R0 3 [nil]
       3 [-]: CALL R0 1 1  
L 0:   4 [-]: JUMPIF R0 L3 
       5 [-]: GETIMPORT R0 1 [nil]
       6 [-]: NAMECALL R0 R0 K4 [0x7D108DDB]
       7 [-]: CALL R0 1 1  
       8 [-]: LOADN R3 1   
       9 [-]: LENGTH R1 R0 
      10 [-]: LOADN R2 1   
      11 [-]: FORNPREP R1 L3
L 1:  12 [-]: GETUPVAL R5 0
      13 [-]: GETTABLEKS R4 R5 K5 [0x56B5886E]
      14 [-]: GETTABLE R5 R0 R3
      15 [-]: CALL R4 1 1  
      16 [-]: JUMPIFNOT R4 L2
      17 [-]: LOADB R4 1   
      18 [-]: RETURN R4 1  
L 2:  19 [-]: FORNLOOP R1 L1
L 3:  20 [-]: LOADB R0 0   
      21 [-]: RETURN R0 1  


; Name:            
; Defined at line: 232
; #Upvalues:       1
; #Parameters:     0
; Is_vararg:       0
; Max Stack Size:  4

       0 [-]: LOADB R0 1   
       1 [-]: GETIMPORT R2 1 [nil]
       2 [-]: NAMECALL R2 R2 K2 [0xEF893AEC]
       3 [-]: CALL R2 1 1  
       4 [-]: GETTABLEKS R1 R2 K3 ["periodicMissionTag"]
       5 [-]: GETUPVAL R3 0
       6 [-]: GETTABLEKS R2 R3 K4 ["ELITE_ALERT_PERIODIC_MISSION_TAG"]
       7 [-]: JUMPIFEQ R1 R2 L1
       8 [-]: GETIMPORT R2 1 [nil]
       9 [-]: NAMECALL R2 R2 K2 [0xEF893AEC]
      10 [-]: CALL R2 1 1  
      11 [-]: GETTABLEKS R1 R2 K3 ["periodicMissionTag"]
      12 [-]: GETUPVAL R3 0
      13 [-]: GETTABLEKS R2 R3 K5 ["ELITE_ALERT_PERIODIC_MISSION_TAG_ALT"]
      14 [-]: JUMPIFEQ R1 R2 L0
      15 [-]: LOADB R0 0 +1
L 0:  16 [-]: LOADB R0 1   
L 1:  17 [-]: RETURN R0 1  


; Name:            
; Defined at line: 260
; #Upvalues:       0
; #Parameters:     1
; Is_vararg:       0
; Max Stack Size:  4

       0 [-]: GETIMPORT R3 1 [nil]
       1 [-]: NAMECALL R1 R0 K2 [0xF2DEAF69]
       2 [-]: CALL R1 2 1  
       3 [-]: JUMPIFNOT R1 L0
       4 [-]: NAMECALL R1 R0 K3 [0xB0E8475C]
       5 [-]: CALL R1 1 1  
       6 [-]: JUMPIFNOT R1 L0
       7 [-]: NAMECALL R1 R0 K4 [0xFF005826]
       8 [-]: CALL R1 1 1  
       9 [-]: JUMPIFNOT R1 L0
      10 [-]: NAMECALL R1 R0 K4 [0xFF005826]
      11 [-]: CALL R1 1 -1 
      12 [-]: RETURN R1 -1 
L 0:  13 [-]: RETURN R0 1  


; Name:            
; Defined at line: 267
; #Upvalues:       0
; #Parameters:     2
; Is_vararg:       0
; Max Stack Size:  13

       0 [-]: FASTCALL1 62 R0 L0
       1 [-]: MOVE R3 R0   
       2 [-]: GETIMPORT R2 1 [nil]
       3 [-]: CALL R2 1 1  
L 0:   4 [-]: JUMPIFNOT R2 L1
       5 [-]: RETURN R0 0  
L 1:   6 [-]: GETIMPORT R2 3 [nil]
       7 [-]: NAMECALL R2 R2 K4 [0x8B5B1F58]
       8 [-]: CALL R2 1 1  
       9 [-]: GETIMPORT R3 6 [nil]
      10 [-]: MOVE R4 R2   
      11 [-]: CALL R3 1 3  
      12 [-]: FORGPREP_INEXT R3 L6
L 2:  13 [-]: NAMECALL R9 R7 K7 [0x5E651723]
      14 [-]: CALL R9 1 1  
      15 [-]: FASTCALL1 62 R9 L3
      16 [-]: GETIMPORT R8 1 [nil]
      17 [-]: CALL R8 1 1  
L 3:  18 [-]: JUMPIF R8 L6 
      19 [-]: NAMECALL R8 R7 K7 [0x5E651723]
      20 [-]: CALL R8 1 1  
      21 [-]: NAMECALL R8 R8 K8 [0xD8140B94]
      22 [-]: CALL R8 1 1  
      23 [-]: JUMPIFNOT R8 L6
      24 [-]: GETIMPORT R11 10 [nil]
      25 [-]: NAMECALL R9 R7 K11 [0xF2DEAF69]
      26 [-]: CALL R9 2 1  
      27 [-]: JUMPIFNOT R9 L4
      28 [-]: NAMECALL R9 R7 K12 [0xB0E8475C]
      29 [-]: CALL R9 1 1  
      30 [-]: JUMPIFNOT R9 L4
      31 [-]: NAMECALL R9 R7 K13 [0xFF005826]
      32 [-]: CALL R9 1 1  
      33 [-]: JUMPIFNOT R9 L4
      34 [-]: NAMECALL R8 R7 K13 [0xFF005826]
      35 [-]: CALL R8 1 1  
      36 [-]: JUMP L5
     
L 4:  37 [-]: MOVE R8 R7   
L 5:  38 [-]: NAMECALL R9 R8 K14 [0xDE321E6F]
      39 [-]: CALL R9 1 1  
      40 [-]: MOVE R11 R0  
      41 [-]: MOVE R12 R1  
      42 [-]: NAMECALL R9 R9 K15 [0xEC017EFA]
      43 [-]: CALL R9 3 0  
L 6:  44 [-]: FORGLOOP R3 L2 2 [inext]
      45 [-]: RETURN R0 0  


; Name:            
; Defined at line: 281
; #Upvalues:       0
; #Parameters:     4
; Is_vararg:       0
; Max Stack Size:  11

       0 [-]: JUMPIFNOT R3 L6
       1 [-]: LOADB R6 1   
       2 [-]: LOADB R7 0   
       3 [-]: NAMECALL R4 R0 K0 [0x768274D6]
       4 [-]: CALL R4 3 0  
       5 [-]: GETIMPORT R4 2 [nil]
       6 [-]: MOVE R5 R1   
       7 [-]: CALL R4 1 3  
       8 [-]: FORGPREP_INEXT R4 L2
L 0:   9 [-]: FASTCALL1 62 R8 L1
      10 [-]: MOVE R10 R8  
      11 [-]: GETIMPORT R9 4 [nil]
      12 [-]: CALL R9 1 1  
L 1:  13 [-]: JUMPIF R9 L2 
      14 [-]: NAMECALL R9 R8 K5 [0x383D2E7D]
      15 [-]: CALL R9 1 0  
L 2:  16 [-]: FORGLOOP R4 L0 2 [inext]
      17 [-]: GETIMPORT R4 2 [nil]
      18 [-]: MOVE R5 R2   
      19 [-]: CALL R4 1 3  
      20 [-]: FORGPREP_INEXT R4 L5
L 3:  21 [-]: FASTCALL1 62 R8 L4
      22 [-]: MOVE R10 R8  
      23 [-]: GETIMPORT R9 4 [nil]
      24 [-]: CALL R9 1 1  
L 4:  25 [-]: JUMPIF R9 L5 
      26 [-]: NAMECALL R9 R8 K5 [0x383D2E7D]
      27 [-]: CALL R9 1 0  
L 5:  28 [-]: FORGLOOP R4 L3 2 [inext]
      29 [-]: RETURN R0 0  
L 6:  30 [-]: LOADB R6 0   
      31 [-]: LOADB R7 0   
      32 [-]: NAMECALL R4 R0 K0 [0x768274D6]
      33 [-]: CALL R4 3 0  
      34 [-]: GETIMPORT R4 2 [nil]
      35 [-]: MOVE R5 R1   
      36 [-]: CALL R4 1 3  
      37 [-]: FORGPREP_INEXT R4 L9
L 7:  38 [-]: FASTCALL1 62 R8 L8
      39 [-]: MOVE R10 R8  
      40 [-]: GETIMPORT R9 4 [nil]
      41 [-]: CALL R9 1 1  
L 8:  42 [-]: JUMPIF R9 L9 
      43 [-]: NAMECALL R9 R8 K6 [0xF4E253B6]
      44 [-]: CALL R9 1 0  
L 9:  45 [-]: FORGLOOP R4 L7 2 [inext]
      46 [-]: GETIMPORT R4 2 [nil]
      47 [-]: MOVE R5 R2   
      48 [-]: CALL R4 1 3  
      49 [-]: FORGPREP_INEXT R4 L12
L10:  50 [-]: FASTCALL1 62 R8 L11
      51 [-]: MOVE R10 R8  
      52 [-]: GETIMPORT R9 4 [nil]
      53 [-]: CALL R9 1 1  
L11:  54 [-]: JUMPIF R9 L12
      55 [-]: NAMECALL R9 R8 K6 [0xF4E253B6]
      56 [-]: CALL R9 1 0  
L12:  57 [-]: FORGLOOP R4 L10 2 [inext]
      58 [-]: RETURN R0 0  


; Name:            
; Defined at line: 309
; #Upvalues:       2
; #Parameters:     2
; Is_vararg:       0
; Max Stack Size:  12

       0 [-]: GETIMPORT R2 1 [nil]
       1 [-]: GETUPVAL R4 0
       2 [-]: NAMECALL R5 R0 K2 [0xD1586535]
       3 [-]: CALL R5 1 -1 
       4 [-]: NAMECALL R2 R2 K3 [0xC7B81E8D]
       5 [-]: CALL R2 -1 1 
       6 [-]: GETIMPORT R5 5 [nil]
       7 [-]: NAMECALL R3 R1 K6 [0xC1595BD5]
       8 [-]: CALL R3 2 1  
       9 [-]: GETIMPORT R6 8 [nil]
      10 [-]: NAMECALL R4 R1 K6 [0xC1595BD5]
      11 [-]: CALL R4 2 1  
      12 [-]: GETIMPORT R7 10 [nil]
      13 [-]: NAMECALL R5 R1 K11 [0xC9F6A7D7]
      14 [-]: CALL R5 2 1  
      15 [-]: NAMECALL R6 R2 K12 [0xF37943FF]
      16 [-]: CALL R6 1 1  
      17 [-]: JUMPIFNOT R6 L1
      18 [-]: NAMECALL R7 R2 K13 [0x08E5889B]
      19 [-]: CALL R7 1 1  
      20 [-]: LOADN R8 0   
      21 [-]: JUMPIFLT R8 R7 L0
      22 [-]: LOADB R6 0 +1
L 0:  23 [-]: LOADB R6 1   
L 1:  24 [-]: GETUPVAL R7 1
      25 [-]: MOVE R8 R5   
      26 [-]: MOVE R9 R3   
      27 [-]: MOVE R10 R4  
      28 [-]: MOVE R11 R6  
      29 [-]: CALL R7 4 0  
      30 [-]: RETURN R0 0  


; Name:            
; Defined at line: 323
; #Upvalues:       0
; #Parameters:     3
; Is_vararg:       0
; Max Stack Size:  12

       0 [-]: FASTCALL1 62 R0 L0
       1 [-]: MOVE R4 R0   
       2 [-]: GETIMPORT R3 1 [nil]
       3 [-]: CALL R3 1 1  
L 0:   4 [-]: JUMPIF R3 L6 
       5 [-]: MOVE R5 R1   
       6 [-]: NAMECALL R3 R0 K2 [0xC1595BD5]
       7 [-]: CALL R3 2 1  
       8 [-]: GETIMPORT R4 4 [nil]
       9 [-]: MOVE R5 R3   
      10 [-]: CALL R4 1 3  
      11 [-]: FORGPREP_INEXT R4 L5
L 1:  12 [-]: NAMECALL R9 R8 K5 [0x22DA1852]
      13 [-]: CALL R9 1 1  
      14 [-]: JUMPIFEQ R9 R2 L4
      15 [-]: FASTCALL1 62 R9 L2
      16 [-]: MOVE R11 R9  
      17 [-]: GETIMPORT R10 1 [nil]
      18 [-]: CALL R10 1 1 
L 2:  19 [-]: JUMPIF R10 L4
      20 [-]: FASTCALL1 62 R2 L3
      21 [-]: MOVE R11 R2  
      22 [-]: GETIMPORT R10 1 [nil]
      23 [-]: CALL R10 1 1 
L 3:  24 [-]: JUMPIFNOT R10 L5
L 4:  25 [-]: NAMECALL R10 R8 K6 [0xA2880940]
      26 [-]: CALL R10 1 0 
L 5:  27 [-]: FORGLOOP R4 L1 2 [inext]
L 6:  28 [-]: RETURN R0 0  


; Name:            
; Defined at line: 336
; #Upvalues:       1
; #Parameters:     1
; Is_vararg:       0
; Max Stack Size:  7

       0 [-]: GETIMPORT R1 1 [nil]
       1 [-]: LOADN R2 0   
       2 [-]: JUMPIFNOTLT R0 R2 L0
       3 [-]: LOADN R0 0   
L 0:   4 [-]: GETUPVAL R4 0
       5 [-]: MULK R6 R0 K2 [16384]
       6 [-]: FASTCALL1 7 R6 L1
       7 [-]: GETIMPORT R5 5 [nil]
       8 [-]: CALL R5 1 1  
L 1:   9 [-]: NAMECALL R2 R1 K6 [0x751F061D]
      10 [-]: CALL R2 3 0  
      11 [-]: RETURN R0 0  


; Name:            
; Defined at line: 346
; #Upvalues:       1
; #Parameters:     0
; Is_vararg:       0
; Max Stack Size:  5

       0 [-]: GETIMPORT R0 1 [nil]
       1 [-]: GETUPVAL R4 0
       2 [-]: NAMECALL R2 R0 K3 [0x0EB34C69]
       3 [-]: CALL R2 2 1  
       4 [-]: DIVK R1 R2 K2 [16384]
       5 [-]: RETURN R1 1  


; Name:            
; Defined at line: 351
; #Upvalues:       1
; #Parameters:     1
; Is_vararg:       0
; Max Stack Size:  7

       0 [-]: GETIMPORT R1 1 [nil]
       1 [-]: GETUPVAL R3 0
       2 [-]: NAMECALL R1 R1 K2 [0x6DD7AA66]
       3 [-]: CALL R1 2 1  
       4 [-]: FASTCALL1 62 R1 L0
       5 [-]: MOVE R3 R1   
       6 [-]: GETIMPORT R2 4 [nil]
       7 [-]: CALL R2 1 1  
L 0:   8 [-]: JUMPIF R2 L1 
       9 [-]: LOADK R4 K5 ["ShowReward"]
      10 [-]: GETIMPORT R5 7 [nil]
      11 [-]: MOVE R6 R0   
      12 [-]: CALL R5 1 -1 
      13 [-]: NAMECALL R2 R1 K8 [0xE4162EED]
      14 [-]: CALL R2 -1 0 
      15 [-]: GETIMPORT R2 10 [nil]
      16 [-]: LOADK R4 K11 ["Survival: Gave reward tier "]
      17 [-]: MOVE R5 R0   
      18 [-]: CONCAT R3 R4 R5
      19 [-]: CALL R2 1 0  
L 1:  20 [-]: RETURN R0 0  


; Name:            
; Defined at line: 361
; #Upvalues:       8
; #Parameters:     0
; Is_vararg:       0
; Max Stack Size:  19

       0 [-]: GETIMPORT R0 1 [nil]
       1 [-]: LOADK R1 K2 ["excavation: starting client loop"]
       2 [-]: CALL R0 1 0  
       3 [-]: GETIMPORT R0 4 [nil]
L 0:   4 [-]: FASTCALL1 62 R0 L1
       5 [-]: MOVE R2 R0   
       6 [-]: GETIMPORT R1 6 [nil]
       7 [-]: CALL R1 1 1  
L 1:   8 [-]: JUMPIFNOT R1 L2
       9 [-]: GETIMPORT R1 8 [nil]
      10 [-]: LOADN R2 0   
      11 [-]: CALL R1 1 0  
      12 [-]: GETIMPORT R0 4 [nil]
      13 [-]: JUMPBACK L0  
L 2:  14 [-]: GETUPVAL R3 0
      15 [-]: LOADK R4 K9 [65535]
      16 [-]: NAMECALL R1 R0 K10 [0x0EB34C69]
      17 [-]: CALL R1 3 1  
L 3:  18 [-]: GETIMPORT R2 12 [nil]
      19 [-]: JUMPIF R2 L5 
      20 [-]: FASTCALL1 62 R0 L4
      21 [-]: MOVE R3 R0   
      22 [-]: GETIMPORT R2 6 [nil]
      23 [-]: CALL R2 1 1  
L 4:  24 [-]: JUMPIFNOT R2 L6
L 5:  25 [-]: GETIMPORT R2 1 [nil]
      26 [-]: LOADK R3 K13 ["Bailing on ExcavationLoopClient because I am now the host!"]
      27 [-]: CALL R2 1 0  
      28 [-]: RETURN R0 0  
L 6:  29 [-]: GETUPVAL R4 0
      30 [-]: NAMECALL R2 R0 K10 [0x0EB34C69]
      31 [-]: CALL R2 2 1  
      32 [-]: JUMPIFEQ R1 R2 L11
      33 [-]: JUMPIFNOTLT R1 R2 L10
      34 [-]: NAMECALL R3 R0 K14 [0x7606ACC3]
      35 [-]: CALL R3 1 0  
      36 [-]: SUBK R5 R2 K15 [1]
      37 [-]: NAMECALL R3 R0 K16 [0x7A91BA3D]
      38 [-]: CALL R3 2 0  
L 7:  39 [-]: JUMPIFEQ R1 R2 L11
      40 [-]: GETIMPORT R3 1 [nil]
      41 [-]: LOADK R5 K17 ["Client: trying to catch up with new reward count= "]
      42 [-]: GETIMPORT R9 19 [nil]
      43 [-]: MOVE R10 R2  
      44 [-]: CALL R9 1 1  
      45 [-]: MOVE R6 R9   
      46 [-]: LOADK R7 K20 [", current="]
      47 [-]: GETIMPORT R8 19 [nil]
      48 [-]: MOVE R9 R1   
      49 [-]: CALL R8 1 1  
      50 [-]: CONCAT R4 R5 R8
      51 [-]: CALL R3 1 0  
      52 [-]: ADDK R1 R1 K15 [1]
      53 [-]: MOVE R3 R1   
      54 [-]: GETIMPORT R4 22 [nil]
      55 [-]: GETUPVAL R6 1
      56 [-]: NAMECALL R4 R4 K23 [0x6DD7AA66]
      57 [-]: CALL R4 2 1  
      58 [-]: FASTCALL1 62 R4 L8
      59 [-]: MOVE R6 R4   
      60 [-]: GETIMPORT R5 6 [nil]
      61 [-]: CALL R5 1 1  
L 8:  62 [-]: JUMPIF R5 L9 
      63 [-]: LOADK R7 K24 ["ShowReward"]
      64 [-]: GETIMPORT R8 19 [nil]
      65 [-]: MOVE R9 R3   
      66 [-]: CALL R8 1 -1 
      67 [-]: NAMECALL R5 R4 K25 [0xE4162EED]
      68 [-]: CALL R5 -1 0 
      69 [-]: GETIMPORT R5 1 [nil]
      70 [-]: LOADK R7 K26 ["Survival: Gave reward tier "]
      71 [-]: MOVE R8 R3   
      72 [-]: CONCAT R6 R7 R8
      73 [-]: CALL R5 1 0  
L 9:  74 [-]: JUMPBACK L7  
      75 [-]: JUMP L11
    
L10:  76 [-]: JUMPXEQKN R1 K9 L11 NOT [65535]
      77 [-]: GETIMPORT R3 1 [nil]
      78 [-]: LOADK R5 K27 ["Reward count not yet initialized, setting to "]
      79 [-]: GETIMPORT R6 19 [nil]
      80 [-]: MOVE R7 R2   
      81 [-]: CALL R6 1 1  
      82 [-]: CONCAT R4 R5 R6
      83 [-]: CALL R3 1 0  
      84 [-]: MOVE R1 R2   
L11:  85 [-]: GETIMPORT R4 29 [nil]
      86 [-]: FASTCALL1 62 R4 L12
      87 [-]: GETIMPORT R3 6 [nil]
      88 [-]: CALL R3 1 1  
L12:  89 [-]: JUMPIF R3 L21
      90 [-]: GETIMPORT R3 29 [nil]
      91 [-]: NAMECALL R3 R3 K30 [0x7D108DDB]
      92 [-]: CALL R3 1 1  
      93 [-]: LOADN R6 1   
      94 [-]: LENGTH R4 R3 
      95 [-]: LOADN R5 1   
      96 [-]: FORNPREP R4 L21
L13:  97 [-]: GETTABLE R7 R3 R6
      98 [-]: NAMECALL R7 R7 K31 [0x01621194]
      99 [-]: CALL R7 1 1  
     100 [-]: GETTABLE R8 R3 R6
     101 [-]: NAMECALL R8 R8 K32 [0xBB610E5B]
     102 [-]: CALL R8 1 1  
     103 [-]: FASTCALL1 62 R7 L14
     104 [-]: MOVE R10 R7  
     105 [-]: GETIMPORT R9 6 [nil]
     106 [-]: CALL R9 1 1  
L14: 107 [-]: JUMPIF R9 L20
     108 [-]: GETUPVAL R11 2
     109 [-]: NAMECALL R9 R7 K33 [0x7AABEDFB]
     110 [-]: CALL R9 2 1  
     111 [-]: JUMPXEQKN R9 K15 L19 NOT [1]
     112 [-]: FASTCALL1 62 R8 L15
     113 [-]: MOVE R10 R8  
     114 [-]: GETIMPORT R9 6 [nil]
     115 [-]: CALL R9 1 1  
L15: 116 [-]: JUMPIF R9 L20
     117 [-]: GETUPVAL R11 3
     118 [-]: NAMECALL R9 R8 K34 [0xC9F6A7D7]
     119 [-]: CALL R9 2 1  
     120 [-]: FASTCALL1 62 R9 L16
     121 [-]: MOVE R11 R9  
     122 [-]: GETIMPORT R10 6 [nil]
     123 [-]: CALL R10 1 1 
L16: 124 [-]: JUMPIFNOT R10 L17
     125 [-]: NAMECALL R10 R8 K35 [0x1AC1655C]
     126 [-]: CALL R10 1 1 
     127 [-]: LOADN R12 0  
     128 [-]: NAMECALL R10 R10 K36 [0x9EB6D632]
     129 [-]: CALL R10 2 1 
     130 [-]: GETUPVAL R13 3
     131 [-]: MOVE R14 R10 
     132 [-]: GETIMPORT R15 38 [nil]
     133 [-]: LOADK R16 K39 [-0.20000000000000001]
     134 [-]: LOADN R17 0  
     135 [-]: LOADN R18 0  
     136 [-]: CALL R15 3 -1
     137 [-]: NAMECALL R11 R8 K40 [0x47901F07]
     138 [-]: CALL R11 -1 1
     139 [-]: MOVE R9 R11  
L17: 140 [-]: FASTCALL1 62 R9 L18
     141 [-]: MOVE R11 R9  
     142 [-]: GETIMPORT R10 6 [nil]
     143 [-]: CALL R10 1 1 
L18: 144 [-]: JUMPIF R10 L20
     145 [-]: GETIMPORT R10 38 [nil]
     146 [-]: GETUPVAL R13 4
     147 [-]: NAMECALL R11 R7 K33 [0x7AABEDFB]
     148 [-]: CALL R11 2 1 
     149 [-]: GETUPVAL R14 5
     150 [-]: NAMECALL R12 R7 K33 [0x7AABEDFB]
     151 [-]: CALL R12 2 1 
     152 [-]: GETUPVAL R15 6
     153 [-]: NAMECALL R13 R7 K33 [0x7AABEDFB]
     154 [-]: CALL R13 2 -1
     155 [-]: CALL R10 -1 1
     156 [-]: MOVE R13 R10 
     157 [-]: NAMECALL R11 R9 K41 [0x9E9C67CB]
     158 [-]: CALL R11 2 0 
     159 [-]: JUMP L20
    
L19: 160 [-]: GETUPVAL R9 7
     161 [-]: MOVE R10 R8  
     162 [-]: GETUPVAL R11 3
     163 [-]: LOADNIL R12  
     164 [-]: CALL R9 3 0  
L20: 165 [-]: FORNLOOP R4 L13
L21: 166 [-]: GETIMPORT R3 8 [nil]
     167 [-]: LOADN R4 0   
     168 [-]: CALL R3 1 0  
     169 [-]: JUMPBACK L3  
     170 [-]: RETURN R0 0  


; Name:            
; Defined at line: 429
; #Upvalues:       2
; #Parameters:     0
; Is_vararg:       0
; Max Stack Size:  8

       0 [-]: GETIMPORT R0 1 [nil]
       1 [-]: GETUPVAL R2 0
       2 [-]: NAMECALL R0 R0 K2 [0x0EB34C69]
       3 [-]: CALL R0 2 1  
       4 [-]: JUMPXEQKN R0 K3 L1 NOT [0]
       5 [-]: GETIMPORT R1 1 [nil]
       6 [-]: GETUPVAL R3 0
       7 [-]: LOADN R4 1   
       8 [-]: NAMECALL R1 R1 K4 [0x751F061D]
       9 [-]: CALL R1 3 0  
      10 [-]: GETIMPORT R1 1 [nil]
      11 [-]: NAMECALL R1 R1 K5 [0x7606ACC3]
      12 [-]: CALL R1 1 0  
      13 [-]: GETIMPORT R1 1 [nil]
      14 [-]: LOADN R3 0   
      15 [-]: NAMECALL R1 R1 K6 [0x7A91BA3D]
      16 [-]: CALL R1 2 0  
      17 [-]: GETIMPORT R1 8 [nil]
      18 [-]: GETUPVAL R3 1
      19 [-]: NAMECALL R1 R1 K9 [0x6DD7AA66]
      20 [-]: CALL R1 2 1  
      21 [-]: FASTCALL1 62 R1 L0
      22 [-]: MOVE R3 R1   
      23 [-]: GETIMPORT R2 11 [nil]
      24 [-]: CALL R2 1 1  
L 0:  25 [-]: JUMPIF R2 L3 
      26 [-]: LOADK R4 K12 ["ShowReward"]
      27 [-]: GETIMPORT R5 14 [nil]
      28 [-]: LOADN R6 1   
      29 [-]: CALL R5 1 -1 
      30 [-]: NAMECALL R2 R1 K15 [0xE4162EED]
      31 [-]: CALL R2 -1 0 
      32 [-]: GETIMPORT R2 17 [nil]
      33 [-]: LOADK R4 K18 ["Survival: Gave reward tier "]
      34 [-]: LOADN R5 1   
      35 [-]: CONCAT R3 R4 R5
      36 [-]: CALL R2 1 0  
      37 [-]: RETURN R0 0  
L 1:  38 [-]: ADDK R1 R0 K19 [1]
      39 [-]: GETIMPORT R2 1 [nil]
      40 [-]: GETUPVAL R4 0
      41 [-]: MOVE R5 R1   
      42 [-]: NAMECALL R2 R2 K4 [0x751F061D]
      43 [-]: CALL R2 3 0  
      44 [-]: GETIMPORT R2 1 [nil]
      45 [-]: SUBK R4 R1 K19 [1]
      46 [-]: NAMECALL R2 R2 K6 [0x7A91BA3D]
      47 [-]: CALL R2 2 0  
      48 [-]: GETIMPORT R2 8 [nil]
      49 [-]: GETUPVAL R4 1
      50 [-]: NAMECALL R2 R2 K9 [0x6DD7AA66]
      51 [-]: CALL R2 2 1  
      52 [-]: FASTCALL1 62 R2 L2
      53 [-]: MOVE R4 R2   
      54 [-]: GETIMPORT R3 11 [nil]
      55 [-]: CALL R3 1 1  
L 2:  56 [-]: JUMPIF R3 L3 
      57 [-]: LOADK R5 K12 ["ShowReward"]
      58 [-]: GETIMPORT R6 14 [nil]
      59 [-]: MOVE R7 R1   
      60 [-]: CALL R6 1 -1 
      61 [-]: NAMECALL R3 R2 K15 [0xE4162EED]
      62 [-]: CALL R3 -1 0 
      63 [-]: GETIMPORT R3 17 [nil]
      64 [-]: LOADK R5 K18 ["Survival: Gave reward tier "]
      65 [-]: MOVE R6 R1   
      66 [-]: CONCAT R4 R5 R6
      67 [-]: CALL R3 1 0  
L 3:  68 [-]: RETURN R0 0  


; Name:            
; Defined at line: 444
; #Upvalues:       2
; #Parameters:     4
; Is_vararg:       0
; Max Stack Size:  14

       0 [-]: NAMECALL R4 R0 K0 [0xBB610E5B]
       1 [-]: CALL R4 1 1  
       2 [-]: FASTCALL1 62 R4 L0
       3 [-]: MOVE R6 R4   
       4 [-]: GETIMPORT R5 2 [nil]
       5 [-]: CALL R5 1 1  
L 0:   6 [-]: JUMPIFNOT R5 L1
       7 [-]: RETURN R0 0  
L 1:   8 [-]: GETIMPORT R5 4 [nil]
       9 [-]: MOVE R7 R4   
      10 [-]: MOVE R8 R1   
      11 [-]: NAMECALL R5 R5 K5 [0xEBBDC5C2]
      12 [-]: CALL R5 3 1  
      13 [-]: LOADNIL R6   
      14 [-]: GETIMPORT R7 4 [nil]
      15 [-]: NAMECALL R7 R7 K6 [0x29EF273D]
      16 [-]: CALL R7 1 1  
      17 [-]: NAMECALL R7 R7 K7 [0x66905CB0]
      18 [-]: CALL R7 1 1  
      19 [-]: FASTCALL1 62 R5 L2
      20 [-]: MOVE R9 R5   
      21 [-]: GETIMPORT R8 2 [nil]
      22 [-]: CALL R8 1 1  
L 2:  23 [-]: JUMPIFNOT R8 L3
      24 [-]: GETUPVAL R8 0
      25 [-]: JUMPIFNOT R8 L3
      26 [-]: GETIMPORT R8 4 [nil]
      27 [-]: GETUPVAL R10 1
      28 [-]: NAMECALL R11 R4 K8 [0xD1586535]
      29 [-]: CALL R11 1 -1
      30 [-]: NAMECALL R8 R8 K9 [0xC7B81E8D]
      31 [-]: CALL R8 -1 1 
      32 [-]: MOVE R5 R8   
L 3:  33 [-]: LOADN R8 0   
      34 [-]: JUMPIFNOTLT R8 R2 L5
      35 [-]: GETIMPORT R8 4 [nil]
      36 [-]: MOVE R10 R4  
      37 [-]: MOVE R11 R3  
      38 [-]: NAMECALL R8 R8 K5 [0xEBBDC5C2]
      39 [-]: CALL R8 3 1  
      40 [-]: MOVE R6 R8   
      41 [-]: FASTCALL1 62 R6 L4
      42 [-]: MOVE R9 R6   
      43 [-]: GETIMPORT R8 2 [nil]
      44 [-]: CALL R8 1 1  
L 4:  45 [-]: JUMPIFNOT R8 L5
      46 [-]: GETUPVAL R8 0
      47 [-]: JUMPIFNOT R8 L5
      48 [-]: MOVE R10 R4  
      49 [-]: NAMECALL R8 R7 K10 [0x58C656C5]
      50 [-]: CALL R8 2 1  
      51 [-]: MOVE R6 R8   
L 5:  52 [-]: FASTCALL1 62 R5 L6
      53 [-]: MOVE R9 R5   
      54 [-]: GETIMPORT R8 2 [nil]
      55 [-]: CALL R8 1 1  
L 6:  56 [-]: JUMPIFNOT R8 L8
      57 [-]: FASTCALL1 62 R6 L7
      58 [-]: MOVE R9 R6   
      59 [-]: GETIMPORT R8 2 [nil]
      60 [-]: CALL R8 1 1  
L 7:  61 [-]: JUMPIFNOT R8 L8
      62 [-]: RETURN R0 0  
L 8:  63 [-]: FASTCALL1 62 R5 L9
      64 [-]: MOVE R9 R5   
      65 [-]: GETIMPORT R8 2 [nil]
      66 [-]: CALL R8 1 1  
L 9:  67 [-]: JUMPIFNOT R8 L10
      68 [-]: MOVE R10 R6  
      69 [-]: NAMECALL R8 R0 K11 [0xA64A1F4A]
      70 [-]: CALL R8 2 0  
      71 [-]: RETURN R0 0  
L10:  72 [-]: FASTCALL1 62 R6 L11
      73 [-]: MOVE R9 R6   
      74 [-]: GETIMPORT R8 2 [nil]
      75 [-]: CALL R8 1 1  
L11:  76 [-]: JUMPIFNOT R8 L12
      77 [-]: MOVE R10 R5  
      78 [-]: NAMECALL R8 R0 K11 [0xA64A1F4A]
      79 [-]: CALL R8 2 0  
      80 [-]: RETURN R0 0  
L12:  81 [-]: NAMECALL R8 R4 K8 [0xD1586535]
      82 [-]: CALL R8 1 1  
      83 [-]: MOVE R11 R8  
      84 [-]: NAMECALL R9 R5 K12 [0x1F420A3A]
      85 [-]: CALL R9 2 1  
      86 [-]: MOVE R12 R8  
      87 [-]: NAMECALL R10 R6 K12 [0x1F420A3A]
      88 [-]: CALL R10 2 1 
      89 [-]: ADDK R11 R10 K13 [25]
      90 [-]: JUMPIFNOTLT R11 R9 L13
      91 [-]: MOVE R13 R6  
      92 [-]: NAMECALL R11 R0 K11 [0xA64A1F4A]
      93 [-]: CALL R11 2 0 
      94 [-]: RETURN R0 0  
L13:  95 [-]: MOVE R13 R5  
      96 [-]: NAMECALL R11 R0 K11 [0xA64A1F4A]
      97 [-]: CALL R11 2 0 
      98 [-]: RETURN R0 0  


; Name:            
; Defined at line: 495
; #Upvalues:       2
; #Parameters:     1
; Is_vararg:       0
; Max Stack Size:  15

       0 [-]: GETIMPORT R1 1 [nil]
       1 [-]: NAMECALL R1 R1 K2 [0x8B5B1F58]
       2 [-]: CALL R1 1 1  
       3 [-]: GETIMPORT R2 4 [nil]
       4 [-]: MOVE R3 R1   
       5 [-]: CALL R2 1 3  
       6 [-]: FORGPREP_INEXT R2 L2
L 0:   7 [-]: FASTCALL1 62 R6 L1
       8 [-]: MOVE R8 R6   
       9 [-]: GETIMPORT R7 6 [nil]
      10 [-]: CALL R7 1 1  
L 1:  11 [-]: JUMPIF R7 L2 
      12 [-]: NAMECALL R7 R6 K7 [0x2047CFE7]
      13 [-]: CALL R7 1 1  
      14 [-]: JUMPIFNOT R7 L2
      15 [-]: LOADNIL R7   
      16 [-]: SETTABLE R7 R1 R5
L 2:  17 [-]: FORGLOOP R2 L0 2 [inext]
      18 [-]: GETIMPORT R2 9 [nil]
      19 [-]: GETUPVAL R4 0
      20 [-]: LOADN R5 0   
      21 [-]: NAMECALL R2 R2 K10 [0x0EB34C69]
      22 [-]: CALL R2 3 1  
      23 [-]: GETIMPORT R3 1 [nil]
      24 [-]: NAMECALL R3 R3 K11 [0x29EF273D]
      25 [-]: CALL R3 1 1  
      26 [-]: NAMECALL R3 R3 K12 [0x66905CB0]
      27 [-]: CALL R3 1 1  
      28 [-]: LOADNIL R6   
      29 [-]: LOADN R7 10000
      30 [-]: LOADB R8 0   
      31 [-]: NAMECALL R4 R3 K13 [0x073A4A95]
      32 [-]: CALL R4 4 1  
      33 [-]: LENGTH R7 R4 
      34 [-]: LOADN R5 1   
      35 [-]: LOADN R6 -1  
      36 [-]: FORNPREP R5 L13
L 3:  37 [-]: GETTABLE R8 R4 R7
      38 [-]: FASTCALL1 62 R8 L4
      39 [-]: MOVE R10 R8  
      40 [-]: GETIMPORT R9 6 [nil]
      41 [-]: CALL R9 1 1  
L 4:  42 [-]: JUMPIF R9 L12
      43 [-]: NAMECALL R9 R8 K14 [0x9ACF9296]
      44 [-]: CALL R9 1 1  
      45 [-]: LENGTH R10 R0
      46 [-]: LOADN R11 0  
      47 [-]: JUMPIFNOTLT R11 R10 L7
      48 [-]: FASTCALL1 62 R9 L5
      49 [-]: MOVE R11 R9  
      50 [-]: GETIMPORT R10 6 [nil]
      51 [-]: CALL R10 1 1 
L 5:  52 [-]: JUMPIF R10 L7
      53 [-]: GETIMPORT R12 16 [nil]
      54 [-]: NAMECALL R10 R9 K17 [0xF2DEAF69]
      55 [-]: CALL R10 2 1 
      56 [-]: JUMPIFNOT R10 L7
      57 [-]: NAMECALL R11 R9 K18 [0x5E651723]
      58 [-]: CALL R11 1 1 
      59 [-]: FASTCALL1 62 R11 L6
      60 [-]: GETIMPORT R10 6 [nil]
      61 [-]: CALL R10 1 1 
L 6:  62 [-]: JUMPIF R10 L7
      63 [-]: LOADNIL R9   
      64 [-]: JUMP L9
     
L 7:  65 [-]: FASTCALL1 62 R9 L8
      66 [-]: MOVE R11 R9  
      67 [-]: GETIMPORT R10 6 [nil]
      68 [-]: CALL R10 1 1 
L 8:  69 [-]: JUMPIF R10 L9
      70 [-]: NAMECALL R10 R9 K7 [0x2047CFE7]
      71 [-]: CALL R10 1 1 
      72 [-]: JUMPIFNOT R10 L9
      73 [-]: MOVE R12 R9  
      74 [-]: NAMECALL R10 R3 K19 [0x996C2CAB]
      75 [-]: CALL R10 2 0 
      76 [-]: LOADNIL R9   
L 9:  77 [-]: FASTCALL1 62 R9 L10
      78 [-]: MOVE R11 R9  
      79 [-]: GETIMPORT R10 6 [nil]
      80 [-]: CALL R10 1 1 
L10:  81 [-]: JUMPIFNOT R10 L11
      82 [-]: GETUPVAL R10 1
      83 [-]: MOVE R11 R8  
      84 [-]: MOVE R12 R0  
      85 [-]: MOVE R13 R2  
      86 [-]: MOVE R14 R1  
      87 [-]: CALL R10 4 0 
      88 [-]: JUMP L12
    
L11:  89 [-]: GETIMPORT R10 21 [nil]
      90 [-]: LOADK R12 K22 ["Keeping existing target of "]
      91 [-]: NAMECALL R13 R9 K23 [0xED4E0128]
      92 [-]: CALL R13 1 1 
      93 [-]: CONCAT R11 R12 R13
      94 [-]: CALL R10 1 0 
L12:  95 [-]: FORNLOOP R5 L3
L13:  96 [-]: LENGTH R5 R0 
      97 [-]: LOADN R6 0   
      98 [-]: JUMPIFNOTLT R6 R5 L14
      99 [-]: GETIMPORT R6 25 [nil]
     100 [-]: LOADN R7 1   
     101 [-]: LENGTH R8 R0 
     102 [-]: CALL R6 2 1  
     103 [-]: GETTABLE R5 R0 R6
     104 [-]: MOVE R8 R5   
     105 [-]: NAMECALL R6 R3 K26 [0xE2871589]
     106 [-]: CALL R6 2 0  
     107 [-]: GETIMPORT R6 21 [nil]
     108 [-]: LOADK R8 K27 ["SetObjective "]
     109 [-]: NAMECALL R9 R5 K23 [0xED4E0128]
     110 [-]: CALL R9 1 1  
     111 [-]: CONCAT R7 R8 R9
     112 [-]: CALL R6 1 0  
     113 [-]: RETURN R0 0  
L14: 114 [-]: RETURN R0 0  


; Name:            
; Defined at line: 545
; #Upvalues:       0
; #Parameters:     0
; Is_vararg:       0
; Max Stack Size:  4

       0 [-]: GETIMPORT R1 2 [nil]
       1 [-]: FASTCALL1 62 R1 L0
       2 [-]: GETIMPORT R0 4 [nil]
       3 [-]: CALL R0 1 1  
L 0:   4 [-]: JUMPIFNOT R0 L1
       5 [-]: GETIMPORT R0 6 [nil]
       6 [-]: NAMECALL R0 R0 K7 [0x29EF273D]
       7 [-]: CALL R0 1 1  
       8 [-]: NAMECALL R0 R0 K8 [0x66905CB0]
       9 [-]: CALL R0 1 1  
      10 [-]: GETIMPORT R1 9 [nil]
      11 [-]: NAMECALL R2 R0 K10 [0xCEA36880]
      12 [-]: CALL R2 1 1  
      13 [-]: SETTABLEKS R2 R1 K1 ["EndlessModeEnemyLevel"]
L 1:  14 [-]: GETIMPORT R2 2 [nil]
      15 [-]: DIVK R1 R2 K11 [30]
      16 [-]: FASTCALL2K 19 R1 K12 L2 [1]
      17 [-]: LOADK R2 K12 [1]
      18 [-]: GETIMPORT R0 15 [nil]
      19 [-]: CALL R0 2 1  
L 2:  20 [-]: RETURN R0 1  


; Name:            
; Defined at line: 554
; #Upvalues:       1
; #Parameters:     4
; Is_vararg:       0
; Max Stack Size:  11

       0 [-]: NAMECALL R4 R0 K0 [0x9E21E394]
       1 [-]: CALL R4 1 0  
       2 [-]: GETIMPORT R4 2 [nil]
       3 [-]: LOADN R5 0   
       4 [-]: CALL R4 1 0  
       5 [-]: FASTCALL1 62 R0 L0
       6 [-]: MOVE R5 R0   
       7 [-]: GETIMPORT R4 4 [nil]
       8 [-]: CALL R4 1 1  
L 0:   9 [-]: JUMPIFNOT R4 L1
      10 [-]: RETURN R0 0  
L 1:  11 [-]: GETIMPORT R4 6 [nil]
      12 [-]: MOVE R5 R3   
      13 [-]: CALL R4 1 3  
      14 [-]: FORGPREP_INEXT R4 L4
L 2:  15 [-]: FASTCALL1 62 R8 L3
      16 [-]: MOVE R10 R8  
      17 [-]: GETIMPORT R9 4 [nil]
      18 [-]: CALL R9 1 1  
L 3:  19 [-]: JUMPIF R9 L4 
      20 [-]: NAMECALL R9 R8 K7 [0x2047CFE7]
      21 [-]: CALL R9 1 1  
      22 [-]: JUMPIFNOT R9 L4
      23 [-]: LOADNIL R9   
      24 [-]: SETTABLE R9 R3 R7
L 4:  25 [-]: FORGLOOP R4 L2 2 [inext]
      26 [-]: GETUPVAL R4 0
      27 [-]: MOVE R5 R0   
      28 [-]: MOVE R6 R1   
      29 [-]: MOVE R7 R2   
      30 [-]: MOVE R8 R3   
      31 [-]: CALL R4 4 0  
      32 [-]: RETURN R0 0  


; Name:            
; Defined at line: 576
; #Upvalues:       1
; #Parameters:     0
; Is_vararg:       0
; Max Stack Size:  13

       0 [-]: GETIMPORT R0 1 [nil]
       1 [-]: NAMECALL R1 R0 K2 [0xEF893AEC]
       2 [-]: CALL R1 1 1  
       3 [-]: GETTABLEKS R2 R1 K3 ["enemySpec"]
       4 [-]: LOADN R3 0   
       5 [-]: FASTCALL1 62 R2 L0
       6 [-]: MOVE R5 R2   
       7 [-]: GETIMPORT R4 5 [nil]
       8 [-]: CALL R4 1 1  
L 0:   9 [-]: JUMPIF R4 L4 
      10 [-]: NAMECALL R4 R2 K6 [0xEC195A1E]
      11 [-]: CALL R4 1 1  
      12 [-]: GETIMPORT R5 8 [nil]
      13 [-]: MOVE R6 R4   
      14 [-]: CALL R5 1 3  
      15 [-]: FORGPREP_INEXT R5 L3
L 1:  16 [-]: GETTABLEKS R10 R9 K9 ["tier"]
      17 [-]: JUMPXEQKN R10 K10 L3 NOT [9]
      18 [-]: GETTABLEKS R12 R9 K11 ["maxSimultaneous"]
      19 [-]: FASTCALL2 18 R3 R12 L2
      20 [-]: MOVE R11 R3  
      21 [-]: GETIMPORT R10 14 [nil]
      22 [-]: CALL R10 2 1 
L 2:  23 [-]: MOVE R3 R10  
L 3:  24 [-]: FORGLOOP R5 L1 2 [inext]
L 4:  25 [-]: GETTABLEKS R4 R1 K15 ["goalTag"]
      26 [-]: GETUPVAL R5 0
      27 [-]: JUMPIFNOTEQ R4 R5 L5
      28 [-]: LOADN R3 0   
L 5:  29 [-]: RETURN R3 1  


; Name:            
; Defined at line: 597
; #Upvalues:       0
; #Parameters:     1
; Is_vararg:       0
; Max Stack Size:  8

       0 [-]: GETIMPORT R1 1 [nil]
       1 [-]: MOVE R2 R0   
       2 [-]: CALL R1 1 3  
       3 [-]: FORGPREP_INEXT R1 L1
L 0:   4 [-]: NAMECALL R6 R5 K2 [0x08E5889B]
       5 [-]: CALL R6 1 1  
       6 [-]: LOADN R7 0   
       7 [-]: JUMPIFNOTLT R7 R6 L1
       8 [-]: LOADB R6 1   
       9 [-]: RETURN R6 1  
L 1:  10 [-]: FORGLOOP R1 L0 2 [inext]
      11 [-]: LOADB R1 0   
      12 [-]: RETURN R1 1  


; Name:            
; Defined at line: 636
; #Upvalues:       12
; #Parameters:     4
; Is_vararg:       0
; Max Stack Size:  25

       0 [-]: GETIMPORT R4 1 [nil]
       1 [-]: NAMECALL R4 R4 K2 [0x29EF273D]
       2 [-]: CALL R4 1 1  
       3 [-]: NAMECALL R4 R4 K3 [0x66905CB0]
       4 [-]: CALL R4 1 1  
       5 [-]: NAMECALL R5 R4 K4 [0xCEA36880]
       6 [-]: CALL R5 1 1  
       7 [-]: NAMECALL R6 R4 K5 [0x6968EA36]
       8 [-]: CALL R6 1 1  
       9 [-]: LOADNIL R7   
      10 [-]: GETUPVAL R8 0
      11 [-]: JUMPIFNOT R8 L0
      12 [-]: ADDK R6 R5 K6 [5]
L 0:  13 [-]: GETUPVAL R8 1
      14 [-]: JUMPIFNOTLT R8 R0 L4
      15 [-]: LOADN R11 40 
      16 [-]: GETUPVAL R15 1
      17 [-]: SUB R14 R0 R15
      18 [-]: DIVK R13 R14 K8 [40]
      19 [-]: MULK R12 R13 K7 [0.13]
      20 [-]: SUB R10 R11 R12
      21 [-]: FASTCALL1 12 R10 L1
      22 [-]: GETIMPORT R9 11 [nil]
      23 [-]: CALL R9 1 1  
L 1:  24 [-]: FASTCALL2K 18 R9 K6 L2 [5]
      25 [-]: LOADK R10 K6 [5]
      26 [-]: GETIMPORT R8 13 [nil]
      27 [-]: CALL R8 2 1  
L 2:  28 [-]: GETUPVAL R12 1
      29 [-]: SUB R11 R0 R12
      30 [-]: DIV R10 R11 R8
      31 [-]: FASTCALL1 12 R10 L3
      32 [-]: GETIMPORT R9 11 [nil]
      33 [-]: CALL R9 1 1  
L 3:  34 [-]: ADD R7 R6 R9 
      35 [-]: JUMP L5
     
L 4:  36 [-]: GETUPVAL R9 2
      37 [-]: DIV R8 R0 R9 
      38 [-]: GETIMPORT R9 15 [nil]
      39 [-]: MOVE R10 R5  
      40 [-]: MOVE R11 R6  
      41 [-]: MOVE R12 R8  
      42 [-]: CALL R9 3 1  
      43 [-]: MOVE R7 R9   
L 5:  44 [-]: GETUPVAL R8 3
      45 [-]: JUMPIFNOT R8 L6
      46 [-]: ADDK R7 R7 K16 [0]
L 6:  47 [-]: GETIMPORT R10 19 [nil]
      48 [-]: FASTCALL2 19 R7 R10 L7
      49 [-]: MOVE R9 R7   
      50 [-]: GETIMPORT R8 21 [nil]
      51 [-]: CALL R8 2 1  
L 7:  52 [-]: MOVE R7 R8   
      53 [-]: GETIMPORT R8 23 [nil]
      54 [-]: SETTABLEKS R7 R8 K24 ["EndlessModeEnemyLevel"]
      55 [-]: MODK R8 R0 K25 [300]
      56 [-]: LOADN R9 300 
      57 [-]: JUMPIFNOTLT R9 R0 L11
      58 [-]: LOADN R9 0   
      59 [-]: JUMPIFNOTLE R9 R8 L11
      60 [-]: LOADN R9 15  
      61 [-]: JUMPIFNOTLT R8 R9 L11
      62 [-]: SUB R9 R0 R8 
      63 [-]: GETIMPORT R10 27 [nil]
      64 [-]: GETUPVAL R12 4
      65 [-]: NAMECALL R10 R10 K28 [0x0EB34C69]
      66 [-]: CALL R10 2 1 
      67 [-]: JUMPIFNOTLT R10 R9 L11
      68 [-]: LOADN R13 9  
      69 [-]: LOADB R14 1  
      70 [-]: NAMECALL R11 R4 K29 [0xD5BF651F]
      71 [-]: CALL R11 3 0 
      72 [-]: GETUPVAL R11 5
      73 [-]: CALL R11 0 1 
      74 [-]: LOADN R14 1  
      75 [-]: MOVE R12 R11 
      76 [-]: LOADN R13 1  
      77 [-]: FORNPREP R12 L11
L 8:  78 [-]: LOADNIL R17  
      79 [-]: GETUPVAL R18 6
      80 [-]: MOVE R19 R7  
      81 [-]: LOADNIL R20  
      82 [-]: LOADN R21 1  
      83 [-]: NAMECALL R15 R4 K30 [0xC3F557D6]
      84 [-]: CALL R15 6 1 
      85 [-]: FASTCALL1 62 R15 L9
      86 [-]: MOVE R17 R15 
      87 [-]: GETIMPORT R16 32 [nil]
      88 [-]: CALL R16 1 1 
L 9:  89 [-]: JUMPIF R16 L10
      90 [-]: GETIMPORT R16 27 [nil]
      91 [-]: GETUPVAL R18 4
      92 [-]: MOVE R19 R0  
      93 [-]: NAMECALL R16 R16 K33 [0x751F061D]
      94 [-]: CALL R16 3 0 
      95 [-]: GETUPVAL R16 7
      96 [-]: MOVE R17 R15 
      97 [-]: MOVE R18 R1  
      98 [-]: MOVE R19 R2  
      99 [-]: MOVE R20 R3  
     100 [-]: CALL R16 4 0 
L10: 101 [-]: FORNLOOP R12 L8
L11: 102 [-]: DIVK R11 R0 K35 [120]
     103 [-]: FASTCALL1 12 R11 L12
     104 [-]: GETIMPORT R10 11 [nil]
     105 [-]: CALL R10 1 1 
L12: 106 [-]: MULK R9 R10 K34 [1]
     107 [-]: FASTCALL2K 19 R9 K6 L13 [5]
     108 [-]: MOVE R11 R9  
     109 [-]: LOADK R12 K6 [5]
     110 [-]: GETIMPORT R10 21 [nil]
     111 [-]: CALL R10 2 1 
L13: 112 [-]: MOVE R9 R10  
     113 [-]: MOVE R12 R9  
     114 [-]: NAMECALL R10 R4 K29 [0xD5BF651F]
     115 [-]: CALL R10 2 0 
     116 [-]: GETIMPORT R10 27 [nil]
     117 [-]: NAMECALL R10 R10 K36 [0xEF893AEC]
     118 [-]: CALL R10 1 1 
     119 [-]: LOADN R11 0  
     120 [-]: LOADN R13 60 
     121 [-]: GETIMPORT R14 15 [nil]
     122 [-]: LOADN R15 120
     123 [-]: LOADN R16 0  
     124 [-]: GETTABLEKS R17 R10 K37 ["difficulty"]
     125 [-]: CALL R14 3 1 
     126 [-]: ADD R12 R13 R14
     127 [-]: LOADN R14 3000
     128 [-]: GETIMPORT R15 15 [nil]
     129 [-]: LOADN R16 120
     130 [-]: LOADN R17 0  
     131 [-]: GETTABLEKS R18 R10 K37 ["difficulty"]
     132 [-]: CALL R15 3 1 
     133 [-]: ADD R13 R14 R15
     134 [-]: LOADK R14 K38 [0.02]
     135 [-]: LOADK R15 K39 [0.14999999999999999]
     136 [-]: GETTABLEKS R16 R10 K40 ["goalTag"]
     137 [-]: GETUPVAL R17 8
     138 [-]: JUMPIFNOTEQ R16 R17 L14
     139 [-]: LOADN R14 0  
     140 [-]: LOADN R15 0  
L14: 141 [-]: LOADB R16 0  
     142 [-]: GETTABLEKS R17 R10 K41 ["leadersAlwaysAllowed"]
     143 [-]: JUMPIFNOT R17 L17
     144 [-]: GETTABLEKS R17 R10 K42 ["sortieId"]
     145 [-]: JUMPXEQKS R17 K43 L15 NOT [""]
     146 [-]: GETTABLEKS R17 R10 K44 ["alertId"]
     147 [-]: JUMPXEQKS R17 K43 L15 NOT [""]
     148 [-]: GETTABLEKS R17 R10 K45 ["goalId"]
     149 [-]: JUMPXEQKS R17 K43 L17 [""]
L15: 150 [-]: GETIMPORT R17 47 [nil]
     151 [-]: MULK R18 R12 K48 [0.10000000000000001]
     152 [-]: LOADN R19 1  
     153 [-]: MOVE R20 R12 
     154 [-]: CALL R17 3 1 
     155 [-]: MOVE R12 R17 
     156 [-]: GETIMPORT R17 47 [nil]
     157 [-]: MULK R18 R13 K48 [0.10000000000000001]
     158 [-]: LOADN R19 1  
     159 [-]: MOVE R20 R13 
     160 [-]: CALL R17 3 1 
     161 [-]: MOVE R13 R17 
     162 [-]: GETIMPORT R17 50 [nil]
     163 [-]: JUMPIFNOT R17 L16
     164 [-]: LOADK R17 K51 [0.050000000000000003]
     165 [-]: GETIMPORT R19 1 [nil]
     166 [-]: NAMECALL R19 R19 K53 [0x5D971903]
     167 [-]: CALL R19 1 1 
     168 [-]: MULK R18 R19 K52 [0.025000000000000001]
     169 [-]: ADD R15 R17 R18
     170 [-]: JUMP L20
    
L16: 171 [-]: MULK R14 R14 K6 [5]
     172 [-]: MULK R15 R15 K6 [5]
     173 [-]: JUMP L20
    
L17: 174 [-]: GETUPVAL R17 3
     175 [-]: JUMPIFNOT R17 L20
     176 [-]: GETIMPORT R17 27 [nil]
     177 [-]: GETIMPORT R19 55 [nil]
     178 [-]: LOADK R20 K56 ["mCurrentPortalId"]
     179 [-]: CALL R19 1 -1
     180 [-]: NAMECALL R17 R17 K28 [0x0EB34C69]
     181 [-]: CALL R17 -1 1
     182 [-]: GETUPVAL R19 9
     183 [-]: GETTABLEKS R18 R19 K57 [0x21EAFB00]
     184 [-]: GETIMPORT R19 59 [nil]
     185 [-]: MOVE R20 R17 
     186 [-]: CALL R19 1 -1
     187 [-]: CALL R18 -1 1
     188 [-]: FASTCALL1 62 R18 L18
     189 [-]: MOVE R21 R18 
     190 [-]: GETIMPORT R20 32 [nil]
     191 [-]: CALL R20 1 1 
L18: 192 [-]: NOT R19 R20  
     193 [-]: JUMPIFNOT R19 L19
     194 [-]: GETTABLEKS R19 R18 K60 ["isStaticPortal"]
L19: 195 [-]: MOVE R16 R19 
L20: 196 [-]: GETIMPORT R17 27 [nil]
     197 [-]: NAMECALL R17 R17 K61 [0x30625642]
     198 [-]: CALL R17 1 1 
     199 [-]: MUL R14 R14 R17
     200 [-]: MUL R15 R15 R17
     201 [-]: JUMPIFNOT R16 L22
     202 [-]: GETIMPORT R18 27 [nil]
     203 [-]: GETUPVAL R20 10
     204 [-]: LOADN R21 0  
     205 [-]: NAMECALL R18 R18 K28 [0x0EB34C69]
     206 [-]: CALL R18 3 1 
     207 [-]: DIVK R20 R18 K62 [500]
     208 [-]: FASTCALL2K 19 R20 K34 L21 [1]
     209 [-]: LOADK R21 K34 [1]
     210 [-]: GETIMPORT R19 21 [nil]
     211 [-]: CALL R19 2 1 
L21: 212 [-]: GETIMPORT R20 15 [nil]
     213 [-]: MOVE R21 R14 
     214 [-]: MOVE R22 R15 
     215 [-]: MOVE R23 R19 
     216 [-]: CALL R20 3 1 
     217 [-]: MULK R20 R20 K6 [5]
     218 [-]: GETIMPORT R21 64 [nil]
     219 [-]: CALL R21 0 1 
     220 [-]: JUMPIFNOTLE R21 R20 L24
     221 [-]: LOADN R11 1  
     222 [-]: JUMP L24
    
L22: 223 [-]: JUMPIFNOTLE R12 R0 L24
     224 [-]: SUB R20 R0 R12
     225 [-]: SUB R21 R13 R12
     226 [-]: DIV R19 R20 R21
     227 [-]: FASTCALL2K 19 R19 K34 L23 [1]
     228 [-]: LOADK R20 K34 [1]
     229 [-]: GETIMPORT R18 21 [nil]
     230 [-]: CALL R18 2 1 
L23: 231 [-]: GETIMPORT R19 15 [nil]
     232 [-]: MOVE R20 R14 
     233 [-]: MOVE R21 R15 
     234 [-]: MOVE R22 R18 
     235 [-]: CALL R19 3 1 
     236 [-]: GETIMPORT R20 64 [nil]
     237 [-]: CALL R20 0 1 
     238 [-]: JUMPIFNOTLE R20 R19 L24
     239 [-]: LOADN R11 1  
L24: 240 [-]: LOADNIL R20  
     241 [-]: GETUPVAL R21 6
     242 [-]: MOVE R22 R7  
     243 [-]: LOADNIL R23  
     244 [-]: MOVE R24 R11 
     245 [-]: NAMECALL R18 R4 K30 [0xC3F557D6]
     246 [-]: CALL R18 6 1 
     247 [-]: FASTCALL1 62 R18 L25
     248 [-]: MOVE R20 R18 
     249 [-]: GETIMPORT R19 32 [nil]
     250 [-]: CALL R19 1 1 
L25: 251 [-]: JUMPIFNOT R19 L26
     252 [-]: GETIMPORT R19 66 [nil]
     253 [-]: CALL R19 0 1 
     254 [-]: GETUPVAL R20 11
     255 [-]: JUMPIFNOTLT R20 R19 L27
     256 [-]: GETIMPORT R20 68 [nil]
     257 [-]: LOADK R21 K69 ["Could not spawn agent"]
     258 [-]: CALL R20 1 0 
     259 [-]: ADDK R20 R19 K6 [5]
     260 [-]: SETUPVAL R20 11
     261 [-]: RETURN R18 1 
L26: 262 [-]: GETUPVAL R19 7
     263 [-]: MOVE R20 R18 
     264 [-]: MOVE R21 R1  
     265 [-]: MOVE R22 R2  
     266 [-]: MOVE R23 R3  
     267 [-]: CALL R19 4 0 
L27: 268 [-]: RETURN R18 1 


; Name:            
; Defined at line: 756
; #Upvalues:       12
; #Parameters:     2
; Is_vararg:       0
; Max Stack Size:  16

       0 [-]: GETIMPORT R2 1 [nil]
       1 [-]: NAMECALL R2 R2 K2 [0x61BE252A]
       2 [-]: CALL R2 1 1  
       3 [-]: GETIMPORT R3 4 [nil]
       4 [-]: NAMECALL R3 R3 K5 [0xEF893AEC]
       5 [-]: CALL R3 1 1  
       6 [-]: NAMECALL R4 R3 K6 [0x243148D6]
       7 [-]: CALL R4 1 1  
       8 [-]: LOADNIL R5   
       9 [-]: LOADNIL R6   
      10 [-]: GETTABLEKS R7 R3 K7 ["goalTag"]
      11 [-]: GETUPVAL R8 0
      12 [-]: JUMPIFNOTEQ R7 R8 L0
      13 [-]: GETUPVAL R5 1
      14 [-]: GETUPVAL R6 2
      15 [-]: JUMP L2
     
L 0:  16 [-]: GETUPVAL R7 3
      17 [-]: JUMPIFNOTEQ R4 R7 L1
      18 [-]: GETUPVAL R5 4
      19 [-]: GETUPVAL R6 5
      20 [-]: JUMP L2
     
L 1:  21 [-]: GETUPVAL R5 6
      22 [-]: GETUPVAL R6 7
L 2:  23 [-]: FASTCALL2 18 R2 R1 L3
      24 [-]: MOVE R8 R2   
      25 [-]: MOVE R9 R1   
      26 [-]: GETIMPORT R7 10 [nil]
      27 [-]: CALL R7 2 1  
L 3:  28 [-]: MOVE R2 R7   
      29 [-]: GETUPVAL R8 8
      30 [-]: GETTABLEKS R7 R8 K11 [0x06D055F9]
      31 [-]: GETIMPORT R8 14 [nil]
      32 [-]: CALL R8 0 1  
      33 [-]: LOADN R9 3   
      34 [-]: LOADN R10 4  
      35 [-]: CALL R7 3 1  
      36 [-]: GETIMPORT R8 16 [nil]
      37 [-]: MOVE R9 R2   
      38 [-]: LOADN R10 1  
      39 [-]: MOVE R11 R7  
      40 [-]: CALL R8 3 1  
      41 [-]: MOVE R2 R8   
      42 [-]: GETIMPORT R8 18 [nil]
      43 [-]: GETTABLE R9 R5 R2
      44 [-]: GETTABLE R10 R6 R2
      45 [-]: GETIMPORT R13 21 [nil]
      46 [-]: FASTCALL1 62 R13 L4
      47 [-]: GETIMPORT R12 23 [nil]
      48 [-]: CALL R12 1 1 
L 4:  49 [-]: JUMPIFNOT R12 L5
      50 [-]: GETIMPORT R12 1 [nil]
      51 [-]: NAMECALL R12 R12 K24 [0x29EF273D]
      52 [-]: CALL R12 1 1 
      53 [-]: NAMECALL R12 R12 K25 [0x66905CB0]
      54 [-]: CALL R12 1 1 
      55 [-]: GETIMPORT R13 26 [nil]
      56 [-]: NAMECALL R14 R12 K27 [0xCEA36880]
      57 [-]: CALL R14 1 1 
      58 [-]: SETTABLEKS R14 R13 K20 ["EndlessModeEnemyLevel"]
L 5:  59 [-]: GETIMPORT R14 21 [nil]
      60 [-]: DIVK R13 R14 K28 [30]
      61 [-]: FASTCALL2K 19 R13 K29 L6 [1]
      62 [-]: LOADK R14 K29 [1]
      63 [-]: GETIMPORT R12 31 [nil]
      64 [-]: CALL R12 2 1 
L 6:  65 [-]: MOVE R11 R12 
      66 [-]: CALL R8 3 1  
      67 [-]: SETUPVAL R8 9
      68 [-]: LOADN R8 15  
      69 [-]: JUMPIFNOTLT R0 R8 L8
      70 [-]: DIVK R8 R0 K32 [15]
      71 [-]: GETIMPORT R10 18 [nil]
      72 [-]: LOADN R11 0  
      73 [-]: GETUPVAL R12 9
      74 [-]: MOVE R13 R8  
      75 [-]: CALL R10 3 1 
      76 [-]: FASTCALL1 12 R10 L7
      77 [-]: GETIMPORT R9 34 [nil]
      78 [-]: CALL R9 1 1  
L 7:  79 [-]: SETUPVAL R9 9
L 8:  80 [-]: GETUPVAL R8 10
      81 [-]: JUMPIFNOT R8 L10
      82 [-]: GETUPVAL R8 11
      83 [-]: LOADN R9 0   
      84 [-]: JUMPIFNOTLT R9 R8 L10
      85 [-]: GETUPVAL R10 9
      86 [-]: MULK R9 R10 K35 [0.65000000000000002]
      87 [-]: FASTCALL1 7 R9 L9
      88 [-]: GETIMPORT R8 37 [nil]
      89 [-]: CALL R8 1 1  
L 9:  90 [-]: SETUPVAL R8 9
L10:  91 [-]: GETUPVAL R9 9
      92 [-]: FASTCALL1 12 R9 L11
      93 [-]: GETIMPORT R8 34 [nil]
      94 [-]: CALL R8 1 1  
L11:  95 [-]: SETUPVAL R8 9
      96 [-]: GETIMPORT R8 1 [nil]
      97 [-]: NAMECALL R8 R8 K24 [0x29EF273D]
      98 [-]: CALL R8 1 1  
      99 [-]: NAMECALL R8 R8 K25 [0x66905CB0]
     100 [-]: CALL R8 1 1  
     101 [-]: NAMECALL R10 R8 K38 [0x9A49D00C]
     102 [-]: CALL R10 1 1 
     103 [-]: GETUPVAL R11 9
     104 [-]: FASTCALL2 19 R10 R11 L12
     105 [-]: GETIMPORT R9 31 [nil]
     106 [-]: CALL R9 2 1  
L12: 107 [-]: SETUPVAL R9 9
     108 [-]: RETURN R0 0  


; Name:            
; Defined at line: 800
; #Upvalues:       2
; #Parameters:     0
; Is_vararg:       0
; Max Stack Size:  6

       0 [-]: LOADK R1 K0 [0.25]
       1 [-]: GETUPVAL R5 0
       2 [-]: FASTCALL1 9 R5 L0
       3 [-]: GETIMPORT R4 5 [nil]
       4 [-]: CALL R4 1 1  
L 0:   5 [-]: ADDK R3 R4 K2 [0.98999999999999999]
       6 [-]: POWK R2 R3 K1 [2]
       7 [-]: MUL R0 R1 R2 
       8 [-]: GETIMPORT R1 7 [nil]
       9 [-]: LOADK R2 K8 [0.10000000000000001]
      10 [-]: LOADK R3 K9 [1.8]
      11 [-]: MOVE R4 R0   
      12 [-]: CALL R1 3 1  
      13 [-]: LOADK R3 K10 [6.2800000000000002]
      14 [-]: GETUPVAL R4 1
      15 [-]: DIV R2 R3 R4 
      16 [-]: GETUPVAL R4 0
      17 [-]: ADD R3 R4 R2 
      18 [-]: SETUPVAL R3 0
      19 [-]: GETUPVAL R3 0
      20 [-]: LOADK R4 K10 [6.2800000000000002]
      21 [-]: JUMPIFNOTLT R4 R3 L1
      22 [-]: GETIMPORT R3 12 [nil]
      23 [-]: GETUPVAL R4 0
      24 [-]: LOADK R5 K10 [6.2800000000000002]
      25 [-]: CALL R3 2 1  
      26 [-]: SETUPVAL R3 0
L 1:  27 [-]: RETURN R1 1  


; Name:            
; Defined at line: 811
; #Upvalues:       1
; #Parameters:     1
; Is_vararg:       0
; Max Stack Size:  5

       0 [-]: GETUPVAL R1 0
       1 [-]: JUMPIFNOT R0 L1
       2 [-]: MULK R3 R1 K0 [0.80000000000000004]
       3 [-]: FASTCALL1 12 R3 L0
       4 [-]: GETIMPORT R2 3 [nil]
       5 [-]: CALL R2 1 1  
L 0:   6 [-]: MOVE R1 R2   
L 1:   7 [-]: GETIMPORT R2 5 [nil]
       8 [-]: NAMECALL R2 R2 K6 [0x29EF273D]
       9 [-]: CALL R2 1 1  
      10 [-]: NAMECALL R2 R2 K7 [0x66905CB0]
      11 [-]: CALL R2 1 1  
      12 [-]: NAMECALL R3 R2 K8 [0xE2E98521]
      13 [-]: CALL R3 1 1  
      14 [-]: JUMPIFNOTLT R3 R1 L2
      15 [-]: NAMECALL R3 R2 K9 [0xE830AC3D]
      16 [-]: CALL R3 1 1  
      17 [-]: ADDK R4 R1 K10 [20]
      18 [-]: JUMPIFNOTLT R3 R4 L2
      19 [-]: LOADB R3 1   
      20 [-]: RETURN R3 1  
L 2:  21 [-]: LOADB R3 0   
      22 [-]: RETURN R3 1  


; Name:            
; Defined at line: 825
; #Upvalues:       9
; #Parameters:     4
; Is_vararg:       0
; Max Stack Size:  18

       0 [-]: LOADK R4 K0 [0.5]
       1 [-]: GETIMPORT R5 2 [nil]
       2 [-]: GETUPVAL R7 0
       3 [-]: LOADN R8 0   
       4 [-]: NAMECALL R5 R5 K3 [0x0EB34C69]
       5 [-]: CALL R5 3 1  
       6 [-]: MULK R7 R0 K0 [0.5]
       7 [-]: MULK R8 R5 K4 [0.75]
       8 [-]: ADD R6 R7 R8 
       9 [-]: LENGTH R8 R2 
      10 [-]: JUMPXEQKN R8 K5 L0 [0]
      11 [-]: LOADB R7 0 +1
L 0:  12 [-]: LOADB R7 1   
L 1:  13 [-]: GETUPVAL R8 1
      14 [-]: MOVE R9 R6   
      15 [-]: LENGTH R10 R2
      16 [-]: CALL R8 2 0  
      17 [-]: GETUPVAL R8 2
      18 [-]: MOVE R9 R7   
      19 [-]: CALL R8 1 1  
      20 [-]: JUMPIF R8 L2 
      21 [-]: RETURN R4 1  
L 2:  22 [-]: GETIMPORT R9 7 [nil]
      23 [-]: FASTCALL1 62 R9 L3
      24 [-]: GETIMPORT R8 9 [nil]
      25 [-]: CALL R8 1 1  
L 3:  26 [-]: JUMPIFNOT R8 L4
      27 [-]: GETIMPORT R8 11 [nil]
      28 [-]: LOADK R9 K12 ["No cellItemPickup"]
      29 [-]: CALL R8 1 0  
      30 [-]: JUMP L5
     
L 4:  31 [-]: GETIMPORT R8 14 [nil]
      32 [-]: GETIMPORT R10 7 [nil]
      33 [-]: NAMECALL R8 R8 K15 [0x2B2227CC]
      34 [-]: CALL R8 2 1  
      35 [-]: JUMPIFNOT R8 L5
      36 [-]: GETUPVAL R8 3
      37 [-]: MOVE R9 R3   
      38 [-]: CALL R8 1 1  
      39 [-]: JUMPIF R8 L5 
      40 [-]: RETURN R4 1  
L 5:  41 [-]: GETUPVAL R10 4
      42 [-]: SUB R9 R10 R1
      43 [-]: FASTCALL2K 18 R9 K16 L6 [-0.5]
      44 [-]: LOADK R10 K16 [-0.5]
      45 [-]: GETIMPORT R8 19 [nil]
      46 [-]: CALL R8 2 1  
L 6:  47 [-]: SETUPVAL R8 4
      48 [-]: GETUPVAL R8 4
      49 [-]: LOADN R9 0   
      50 [-]: JUMPIFNOTLT R9 R8 L8
      51 [-]: GETUPVAL R10 4
      52 [-]: FASTCALL2 19 R4 R10 L7
      53 [-]: MOVE R9 R4   
      54 [-]: GETIMPORT R8 21 [nil]
      55 [-]: CALL R8 2 1  
L 7:  56 [-]: RETURN R8 1  
L 8:  57 [-]: GETIMPORT R8 14 [nil]
      58 [-]: NAMECALL R8 R8 K22 [0x8B5B1F58]
      59 [-]: CALL R8 1 1  
      60 [-]: GETIMPORT R9 2 [nil]
      61 [-]: GETUPVAL R11 5
      62 [-]: LOADN R12 0  
      63 [-]: NAMECALL R9 R9 K3 [0x0EB34C69]
      64 [-]: CALL R9 3 1  
L 9:  65 [-]: GETUPVAL R10 6
      66 [-]: MOVE R11 R6  
      67 [-]: MOVE R12 R2  
      68 [-]: MOVE R13 R9  
      69 [-]: MOVE R14 R8  
      70 [-]: CALL R10 4 1 
      71 [-]: FASTCALL1 62 R10 L10
      72 [-]: MOVE R12 R10 
      73 [-]: GETIMPORT R11 9 [nil]
      74 [-]: CALL R11 1 1 
L10:  75 [-]: JUMPIFNOT R11 L11
      76 [-]: RETURN R4 1  
L11:  77 [-]: LOADK R13 K23 [0.25]
      78 [-]: GETUPVAL R17 7
      79 [-]: FASTCALL1 9 R17 L12
      80 [-]: GETIMPORT R16 27 [nil]
      81 [-]: CALL R16 1 1 
L12:  82 [-]: ADDK R15 R16 K25 [0.98999999999999999]
      83 [-]: POWK R14 R15 K24 [2]
      84 [-]: MUL R12 R13 R14
      85 [-]: GETIMPORT R13 29 [nil]
      86 [-]: LOADK R14 K30 [0.10000000000000001]
      87 [-]: LOADK R15 K31 [1.8]
      88 [-]: MOVE R16 R12 
      89 [-]: CALL R13 3 1 
      90 [-]: LOADK R15 K32 [6.2800000000000002]
      91 [-]: GETUPVAL R16 8
      92 [-]: DIV R14 R15 R16
      93 [-]: GETUPVAL R16 7
      94 [-]: ADD R15 R16 R14
      95 [-]: SETUPVAL R15 7
      96 [-]: GETUPVAL R15 7
      97 [-]: LOADK R16 K32 [6.2800000000000002]
      98 [-]: JUMPIFNOTLT R16 R15 L13
      99 [-]: GETIMPORT R15 34 [nil]
     100 [-]: GETUPVAL R16 7
     101 [-]: LOADK R17 K32 [6.2800000000000002]
     102 [-]: CALL R15 2 1 
     103 [-]: SETUPVAL R15 7
L13: 104 [-]: MOVE R11 R13 
     105 [-]: GETUPVAL R13 4
     106 [-]: ADD R12 R13 R11
     107 [-]: SETUPVAL R12 4
     108 [-]: GETUPVAL R12 4
     109 [-]: LOADN R13 0  
     110 [-]: JUMPIFNOTLT R13 R12 L15
     111 [-]: GETUPVAL R14 4
     112 [-]: FASTCALL2 19 R4 R14 L14
     113 [-]: MOVE R13 R4  
     114 [-]: GETIMPORT R12 21 [nil]
     115 [-]: CALL R12 2 1 
L14: 116 [-]: RETURN R12 1 
L15: 117 [-]: GETUPVAL R12 2
     118 [-]: MOVE R13 R7  
     119 [-]: CALL R12 1 1 
     120 [-]: JUMPIF R12 L16
     121 [-]: RETURN R4 1  
L16: 122 [-]: GETIMPORT R12 36 [nil]
     123 [-]: LOADN R13 0  
     124 [-]: CALL R12 1 0 
     125 [-]: GETIMPORT R12 38 [nil]
     126 [-]: CALL R12 0 1 
     127 [-]: SUB R4 R4 R12
     128 [-]: LOADN R12 0  
     129 [-]: JUMPIFNOTLT R4 R12 L17
     130 [-]: LOADN R12 0  
     131 [-]: RETURN R12 1 
L17: 132 [-]: JUMPBACK L9  
     133 [-]: RETURN R4 1  


; Name:            
; Defined at line: 899
; #Upvalues:       1
; #Parameters:     2
; Is_vararg:       0
; Max Stack Size:  14

       0 [-]: LENGTH R2 R1 
       1 [-]: LOADN R3 2   
       2 [-]: JUMPIFNOTLT R2 R3 L0
       3 [-]: RETURN R0 0  
L 0:   4 [-]: LOADN R2 0   
       5 [-]: LOADN R3 0   
       6 [-]: LENGTH R5 R1 
       7 [-]: GETTABLE R4 R1 R5
       8 [-]: NAMECALL R4 R4 K0 [0xD1586535]
       9 [-]: CALL R4 1 1  
      10 [-]: LOADN R7 1   
      11 [-]: LENGTH R5 R1 
      12 [-]: LOADN R6 1   
      13 [-]: FORNPREP R5 L2
L 1:  14 [-]: GETTABLE R8 R1 R7
      15 [-]: NAMECALL R8 R8 K0 [0xD1586535]
      16 [-]: CALL R8 1 1  
      17 [-]: GETIMPORT R9 2 [nil]
      18 [-]: MOVE R10 R4  
      19 [-]: MOVE R11 R8  
      20 [-]: CALL R9 2 1  
      21 [-]: ADD R2 R2 R9 
      22 [-]: ADDK R3 R3 K3 [1]
      23 [-]: MOVE R4 R8   
      24 [-]: FORNLOOP R5 L1
L 2:  25 [-]: DIV R5 R2 R3 
      26 [-]: GETUPVAL R7 0
      27 [-]: GETTABLEKS R6 R7 K4 [0x74A11EC6]
      28 [-]: MOVE R7 R2   
      29 [-]: CALL R6 1 1  
      30 [-]: MOVE R2 R6   
      31 [-]: GETUPVAL R7 0
      32 [-]: GETTABLEKS R6 R7 K4 [0x74A11EC6]
      33 [-]: MOVE R7 R5   
      34 [-]: CALL R6 1 1  
      35 [-]: MOVE R5 R6   
      36 [-]: GETIMPORT R6 6 [nil]
      37 [-]: MOVE R8 R0   
      38 [-]: LOADK R9 K7 [" tour length: "]
      39 [-]: MOVE R10 R2  
      40 [-]: LOADK R11 K8 [" m ("]
      41 [-]: MOVE R12 R5  
      42 [-]: LOADK R13 K9 ["m avg)"]
      43 [-]: CONCAT R7 R8 R13
      44 [-]: CALL R6 1 0  
      45 [-]: RETURN R0 0  


; Name:            
; Defined at line: 928
; #Upvalues:       0
; #Parameters:     1
; Is_vararg:       0
; Max Stack Size:  14

       0 [-]: GETTABLEN R1 R0 1
       1 [-]: NAMECALL R1 R1 K0 [0xD1586535]
       2 [-]: CALL R1 1 1  
       3 [-]: LENGTH R2 R0 
       4 [-]: LOADN R5 2   
       5 [-]: MOVE R3 R2   
       6 [-]: LOADN R4 1   
       7 [-]: FORNPREP R3 L6
L 0:   8 [-]: LOADNIL R6   
       9 [-]: LOADNIL R7   
      10 [-]: MOVE R10 R5  
      11 [-]: MOVE R8 R2   
      12 [-]: LOADN R9 1   
      13 [-]: FORNPREP R8 L4
L 1:  14 [-]: GETTABLE R11 R0 R10
      15 [-]: MOVE R13 R1  
      16 [-]: NAMECALL R11 R11 K1 [0x1F420A3A]
      17 [-]: CALL R11 2 1 
      18 [-]: JUMPXEQKNIL R6 L2
      19 [-]: JUMPIFNOTLT R11 R7 L3
L 2:  20 [-]: MOVE R6 R10  
      21 [-]: MOVE R7 R11  
L 3:  22 [-]: FORNLOOP R8 L1
L 4:  23 [-]: JUMPIFEQ R6 R5 L5
      24 [-]: GETTABLE R8 R0 R5
      25 [-]: GETTABLE R9 R0 R6
      26 [-]: SETTABLE R9 R0 R5
      27 [-]: SETTABLE R8 R0 R6
L 5:  28 [-]: GETTABLE R8 R0 R5
      29 [-]: NAMECALL R8 R8 K0 [0xD1586535]
      30 [-]: CALL R8 1 1  
      31 [-]: MOVE R1 R8   
      32 [-]: FORNLOOP R3 L0
L 6:  33 [-]: RETURN R0 0  


; Name:            
; Defined at line: 959
; #Upvalues:       9
; #Parameters:     0
; Is_vararg:       0
; Max Stack Size:  30

       0 [-]: GETIMPORT R0 1 [nil]
       1 [-]: GETIMPORT R2 3 [nil]
       2 [-]: LOADK R3 K4 ["Spawn"]
       3 [-]: CALL R2 1 -1 
       4 [-]: NAMECALL R0 R0 K5 [0xC7FCADA9]
       5 [-]: CALL R0 -1 1 
       6 [-]: LENGTH R1 R0 
       7 [-]: JUMPXEQKN R1 K6 L0 NOT [0]
       8 [-]: RETURN R0 0  
L 0:   9 [-]: GETUPVAL R1 0
      10 [-]: JUMPIFNOT R1 L1
      11 [-]: GETIMPORT R1 1 [nil]
      12 [-]: GETUPVAL R3 2
      13 [-]: NAMECALL R1 R1 K5 [0xC7FCADA9]
      14 [-]: CALL R1 2 1  
      15 [-]: SETUPVAL R1 1
      16 [-]: JUMP L7
     
L 1:  17 [-]: NEWTABLE R1 0 0
      18 [-]: SETUPVAL R1 1
      19 [-]: GETIMPORT R1 1 [nil]
      20 [-]: GETUPVAL R3 2
      21 [-]: NAMECALL R1 R1 K5 [0xC7FCADA9]
      22 [-]: CALL R1 2 1  
      23 [-]: LOADN R4 1   
      24 [-]: LENGTH R2 R1 
      25 [-]: LOADN R3 1   
      26 [-]: FORNPREP R2 L4
L 2:  27 [-]: GETUPVAL R6 1
      28 [-]: GETTABLE R7 R1 R4
      29 [-]: FASTCALL2 52 R6 R7 L3
      30 [-]: GETIMPORT R5 9 [nil]
      31 [-]: CALL R5 2 0  
L 3:  32 [-]: FORNLOOP R2 L2
L 4:  33 [-]: GETIMPORT R2 1 [nil]
      34 [-]: GETUPVAL R4 3
      35 [-]: NAMECALL R2 R2 K5 [0xC7FCADA9]
      36 [-]: CALL R2 2 1  
      37 [-]: MOVE R1 R2   
      38 [-]: LOADN R4 1   
      39 [-]: LENGTH R2 R1 
      40 [-]: LOADN R3 1   
      41 [-]: FORNPREP R2 L7
L 5:  42 [-]: GETUPVAL R6 1
      43 [-]: GETTABLE R7 R1 R4
      44 [-]: FASTCALL2 52 R6 R7 L6
      45 [-]: GETIMPORT R5 9 [nil]
      46 [-]: CALL R5 2 0  
L 6:  47 [-]: FORNLOOP R2 L5
L 7:  48 [-]: GETUPVAL R1 4
      49 [-]: JUMPIFNOT R1 L9
      50 [-]: GETIMPORT R1 12 [nil]
      51 [-]: JUMPIFNOT R1 L8
      52 [-]: GETIMPORT R1 12 [nil]
      53 [-]: GETUPVAL R2 1
      54 [-]: CALL R1 1 1  
      55 [-]: SETUPVAL R1 1
L 8:  56 [-]: GETUPVAL R2 5
      57 [-]: GETTABLEKS R1 R2 K13 [0x622A0C19]
      58 [-]: GETUPVAL R2 1
      59 [-]: CALL R1 1 0  
      60 [-]: RETURN R0 0  
L 9:  61 [-]: GETIMPORT R2 15 [nil]
      62 [-]: NAMECALL R2 R2 K16 [0xEF893AEC]
      63 [-]: CALL R2 1 1  
      64 [-]: GETTABLEKS R1 R2 K17 ["goalTag"]
      65 [-]: LOADB R2 1   
      66 [-]: GETIMPORT R3 3 [nil]
      67 [-]: LOADK R4 K18 ["ShieldExcav"]
      68 [-]: CALL R3 1 1  
      69 [-]: JUMPIFEQ R1 R3 L11
      70 [-]: GETIMPORT R3 3 [nil]
      71 [-]: LOADK R4 K19 ["OldWorldSalvage"]
      72 [-]: CALL R3 1 1  
      73 [-]: JUMPIFEQ R1 R3 L10
      74 [-]: LOADB R2 0 +1
L10:  75 [-]: LOADB R2 1   
L11:  76 [-]: JUMPIFNOT R2 L15
      77 [-]: GETUPVAL R4 6
      78 [-]: GETTABLEKS R3 R4 K20 [0x10372A64]
      79 [-]: GETUPVAL R4 1
      80 [-]: CALL R3 1 1  
      81 [-]: SETUPVAL R3 1
      82 [-]: GETUPVAL R4 1
      83 [-]: GETUPVAL R6 1
      84 [-]: LENGTH R5 R6 
      85 [-]: GETTABLE R3 R4 R5
      86 [-]: NAMECALL R3 R3 K21 [0xE79E7EF4]
      87 [-]: CALL R3 1 1  
      88 [-]: NAMECALL R3 R3 K22 [0x9435EB6D]
      89 [-]: CALL R3 1 1  
      90 [-]: GETUPVAL R7 1
      91 [-]: LENGTH R6 R7 
      92 [-]: LOADN R4 1   
      93 [-]: LOADN R5 -1  
      94 [-]: FORNPREP R4 L14
L12:  95 [-]: GETUPVAL R8 1
      96 [-]: GETTABLE R7 R8 R6
      97 [-]: NAMECALL R7 R7 K21 [0xE79E7EF4]
      98 [-]: CALL R7 1 1  
      99 [-]: NAMECALL R7 R7 K22 [0x9435EB6D]
     100 [-]: CALL R7 1 1  
     101 [-]: JUMPIFEQ R7 R3 L13
     102 [-]: GETIMPORT R8 24 [nil]
     103 [-]: GETUPVAL R9 1
     104 [-]: MOVE R10 R6  
     105 [-]: CALL R8 2 0  
L13: 106 [-]: FORNLOOP R4 L12
L14: 107 [-]: RETURN R0 0  
L15: 108 [-]: GETUPVAL R4 1
     109 [-]: LENGTH R3 R4 
     110 [-]: JUMPXEQKN R3 K6 L16 NOT [0]
     111 [-]: RETURN R0 0  
L16: 112 [-]: GETIMPORT R3 26 [nil]
     113 [-]: GETUPVAL R7 1
     114 [-]: LENGTH R5 R7 
     115 [-]: LOADK R6 K27 [" extractors found"]
     116 [-]: CONCAT R4 R5 R6
     117 [-]: CALL R3 1 0  
     118 [-]: GETUPVAL R4 1
     119 [-]: LENGTH R3 R4 
     120 [-]: JUMPXEQKN R3 K28 L17 NOT [1]
     121 [-]: RETURN R0 0  
L17: 122 [-]: NEWTABLE R3 0 0
     123 [-]: NEWTABLE R4 0 0
     124 [-]: LOADN R7 1   
     125 [-]: GETUPVAL R8 1
     126 [-]: LENGTH R5 R8 
     127 [-]: LOADN R6 1   
     128 [-]: FORNPREP R5 L24
L18: 129 [-]: GETUPVAL R9 1
     130 [-]: GETTABLE R8 R9 R7
     131 [-]: NAMECALL R9 R8 K21 [0xE79E7EF4]
     132 [-]: CALL R9 1 1  
     133 [-]: FASTCALL1 62 R9 L19
     134 [-]: MOVE R11 R9  
     135 [-]: GETIMPORT R10 30 [nil]
     136 [-]: CALL R10 1 1 
L19: 137 [-]: JUMPIFNOT R10 L20
     138 [-]: GETIMPORT R10 26 [nil]
     139 [-]: LOADK R12 K31 ["Skipping "]
     140 [-]: NAMECALL R15 R8 K32 [0xED4E0128]
     141 [-]: CALL R15 1 1 
     142 [-]: MOVE R13 R15 
     143 [-]: LOADK R14 K33 [" (in the void)"]
     144 [-]: CONCAT R11 R12 R14
     145 [-]: CALL R10 1 0 
     146 [-]: JUMP L23
    
L20: 147 [-]: GETIMPORT R10 26 [nil]
     148 [-]: LOADK R12 K34 ["Found"]
     149 [-]: NAMECALL R13 R8 K32 [0xED4E0128]
     150 [-]: CALL R13 1 1 
     151 [-]: CONCAT R11 R12 R13
     152 [-]: CALL R10 1 0 
     153 [-]: NAMECALL R10 R9 K22 [0x9435EB6D]
     154 [-]: CALL R10 1 1 
     155 [-]: GETTABLE R11 R3 R10
     156 [-]: JUMPXEQKNIL R11 L22 NOT
     157 [-]: NEWTABLE R11 0 1
     158 [-]: MOVE R12 R8  
     159 [-]: SETLIST R11 R12 1 [1]
     160 [-]: SETTABLE R11 R3 R10
     161 [-]: FASTCALL2 52 R4 R8 L21
     162 [-]: MOVE R12 R4  
     163 [-]: MOVE R13 R8  
     164 [-]: GETIMPORT R11 9 [nil]
     165 [-]: CALL R11 2 0 
L21: 166 [-]: JUMP L23
    
L22: 167 [-]: GETTABLE R12 R3 R10
     168 [-]: FASTCALL2 52 R12 R8 L23
     169 [-]: MOVE R13 R8  
     170 [-]: GETIMPORT R11 9 [nil]
     171 [-]: CALL R11 2 0 
L23: 172 [-]: FORNLOOP R5 L18
L24: 173 [-]: GETUPVAL R5 7
     174 [-]: MOVE R6 R4   
     175 [-]: CALL R5 1 0  
     176 [-]: GETIMPORT R5 26 [nil]
     177 [-]: LENGTH R7 R4 
     178 [-]: LOADK R8 K35 [" tiles in path"]
     179 [-]: CONCAT R6 R7 R8
     180 [-]: CALL R5 1 0  
     181 [-]: LENGTH R5 R4 
     182 [-]: JUMPXEQKN R5 K28 L25 NOT [1]
     183 [-]: RETURN R0 0  
L25: 184 [-]: LENGTH R6 R4 
     185 [-]: GETTABLE R5 R4 R6
     186 [-]: LOADNIL R6   
     187 [-]: NEWTABLE R7 0 0
     188 [-]: LOADN R10 1  
     189 [-]: LENGTH R8 R4 
     190 [-]: LOADN R9 1   
     191 [-]: FORNPREP R8 L32
L26: 192 [-]: GETTABLE R11 R4 R10
     193 [-]: GETIMPORT R12 1 [nil]
     194 [-]: MOVE R14 R5  
     195 [-]: MOVE R15 R11 
     196 [-]: NAMECALL R12 R12 K36 [0xF8F0A754]
     197 [-]: CALL R12 3 1 
     198 [-]: LOADN R15 1  
     199 [-]: LENGTH R13 R12
     200 [-]: LOADN R14 1  
     201 [-]: FORNPREP R13 L31
L27: 202 [-]: GETTABLE R16 R12 R15
     203 [-]: NAMECALL R16 R16 K21 [0xE79E7EF4]
     204 [-]: CALL R16 1 1 
     205 [-]: FASTCALL1 62 R16 L28
     206 [-]: MOVE R18 R16 
     207 [-]: GETIMPORT R17 30 [nil]
     208 [-]: CALL R17 1 1 
L28: 209 [-]: JUMPIF R17 L30
     210 [-]: NAMECALL R17 R16 K22 [0x9435EB6D]
     211 [-]: CALL R17 1 1 
     212 [-]: GETTABLE R18 R3 R17
     213 [-]: JUMPXEQKNIL R18 L30
     214 [-]: JUMPIFEQ R6 R17 L30
     215 [-]: FASTCALL2 52 R7 R17 L29
     216 [-]: MOVE R19 R7  
     217 [-]: MOVE R20 R17 
     218 [-]: GETIMPORT R18 9 [nil]
     219 [-]: CALL R18 2 0 
L29: 220 [-]: MOVE R6 R17  
L30: 221 [-]: FORNLOOP R13 L27
L31: 222 [-]: MOVE R5 R11  
     223 [-]: FORNLOOP R8 L26
L32: 224 [-]: GETTABLEN R8 R7 1
     225 [-]: LENGTH R10 R7
     226 [-]: GETTABLE R9 R7 R10
     227 [-]: JUMPIFNOTEQ R8 R9 L33
     228 [-]: GETIMPORT R8 24 [nil]
     229 [-]: MOVE R9 R7   
     230 [-]: LENGTH R10 R7
     231 [-]: CALL R8 2 0  
L33: 232 [-]: GETIMPORT R8 26 [nil]
     233 [-]: LENGTH R10 R7
     234 [-]: LOADK R11 K37 [" tiles in tour"]
     235 [-]: CONCAT R9 R10 R11
     236 [-]: CALL R8 1 0  
     237 [-]: LOADN R10 1  
     238 [-]: LENGTH R8 R3 
     239 [-]: LOADN R9 1   
     240 [-]: FORNPREP R8 L35
L34: 241 [-]: GETUPVAL R12 5
     242 [-]: GETTABLEKS R11 R12 K13 [0x622A0C19]
     243 [-]: GETTABLE R12 R3 R10
     244 [-]: CALL R11 1 0 
     245 [-]: FORNLOOP R8 L34
L35: 246 [-]: NEWTABLE R8 0 0
     247 [-]: LOADN R11 1  
     248 [-]: LENGTH R9 R7 
     249 [-]: LOADN R10 1  
     250 [-]: FORNPREP R9 L39
L36: 251 [-]: GETTABLE R12 R7 R11
     252 [-]: GETTABLE R13 R8 R12
     253 [-]: JUMPXEQKNIL R13 L37 NOT
     254 [-]: LOADN R13 1  
     255 [-]: SETTABLE R13 R8 R12
     256 [-]: JUMP L38
    
L37: 257 [-]: GETTABLE R14 R8 R12
     258 [-]: ADDK R13 R14 K28 [1]
     259 [-]: SETTABLE R13 R8 R12
L38: 260 [-]: FORNLOOP R9 L36
L39: 261 [-]: LENGTH R9 R7 
     262 [-]: LOADN R12 1  
     263 [-]: MOVE R10 R9  
     264 [-]: LOADN R11 1  
     265 [-]: FORNPREP R10 L42
L40: 266 [-]: GETTABLE R15 R7 R12
     267 [-]: FASTCALL2 52 R7 R15 L41
     268 [-]: MOVE R14 R7  
     269 [-]: GETIMPORT R13 9 [nil]
     270 [-]: CALL R13 2 0 
L41: 271 [-]: FORNLOOP R10 L40
L42: 272 [-]: LOADN R12 1  
     273 [-]: MOVE R10 R9  
     274 [-]: LOADN R11 1  
     275 [-]: FORNPREP R10 L45
L43: 276 [-]: GETTABLE R15 R7 R12
     277 [-]: FASTCALL2 52 R7 R15 L44
     278 [-]: MOVE R14 R7  
     279 [-]: GETIMPORT R13 9 [nil]
     280 [-]: CALL R13 2 0 
L44: 281 [-]: FORNLOOP R10 L43
L45: 282 [-]: NEWTABLE R10 0 0
     283 [-]: SETUPVAL R10 1
     284 [-]: LOADNIL R10  
     285 [-]: LOADN R11 0  
     286 [-]: LOADN R14 1  
     287 [-]: LENGTH R12 R7
     288 [-]: LOADN R13 1  
     289 [-]: FORNPREP R12 L56
L46: 290 [-]: GETTABLE R15 R7 R14
     291 [-]: GETTABLE R16 R3 R15
     292 [-]: LOADN R17 100
     293 [-]: GETTABLE R18 R8 R15
     294 [-]: JUMPXEQKN R18 K28 L47 NOT [1]
     295 [-]: MULK R17 R17 K38 [0.5]
L47: 296 [-]: LOADN R20 1  
     297 [-]: LENGTH R18 R16
     298 [-]: LOADN R19 1  
     299 [-]: FORNPREP R18 L55
L48: 300 [-]: GETTABLE R21 R16 R20
     301 [-]: LOADN R22 0  
     302 [-]: JUMPXEQKNIL R10 L51
     303 [-]: MOVE R25 R10 
     304 [-]: NAMECALL R23 R21 K39 [0xBEBAD19F]
     305 [-]: CALL R23 2 1 
     306 [-]: MOVE R22 R23 
     307 [-]: ADD R24 R11 R22
     308 [-]: GETUPVAL R27 1
     309 [-]: LENGTH R26 R27
     310 [-]: ADDK R25 R26 K28 [1]
     311 [-]: DIV R23 R24 R25
     312 [-]: JUMPIFNOTLT R23 R17 L49
     313 [-]: LOADN R22 0  
L49: 314 [-]: GETUPVAL R25 1
     315 [-]: LENGTH R24 R25
     316 [-]: LOADN R25 1  
     317 [-]: JUMPIFLT R24 R25 L51
     318 [-]: GETUPVAL R25 1
     319 [-]: GETUPVAL R29 1
     320 [-]: LENGTH R28 R29
     321 [-]: SUBK R27 R28 K28 [1]
     322 [-]: ADDK R26 R27 K28 [1]
     323 [-]: GETTABLE R24 R25 R26
     324 [-]: JUMPIFNOTEQ R24 R21 L50
     325 [-]: LOADN R22 0  
     326 [-]: JUMP L51
    
L50: 327 [-]: GETUPVAL R25 1
     328 [-]: LENGTH R24 R25
     329 [-]: LOADN R25 2  
     330 [-]: JUMPIFLT R24 R25 L51
     331 [-]: GETUPVAL R25 1
     332 [-]: GETUPVAL R29 1
     333 [-]: LENGTH R28 R29
     334 [-]: SUBK R27 R28 K40 [2]
     335 [-]: ADDK R26 R27 K28 [1]
     336 [-]: GETTABLE R24 R25 R26
     337 [-]: JUMPIFNOTEQ R24 R21 L51
     338 [-]: LOADN R22 0  
     339 [-]: JUMP L51
    
L51: 340 [-]: JUMPXEQKNIL R10 L52
     341 [-]: LOADN R23 50 
     342 [-]: JUMPIFNOTLT R23 R22 L54
L52: 343 [-]: GETUPVAL R24 1
     344 [-]: FASTCALL2 52 R24 R21 L53
     345 [-]: MOVE R25 R21 
     346 [-]: GETIMPORT R23 9 [nil]
     347 [-]: CALL R23 2 0 
L53: 348 [-]: ADD R11 R11 R22
     349 [-]: MOVE R10 R21 
     350 [-]: GETIMPORT R23 24 [nil]
     351 [-]: MOVE R24 R16 
     352 [-]: LOADN R25 1  
     353 [-]: CALL R23 2 0 
     354 [-]: FASTCALL2 52 R16 R21 L54
     355 [-]: MOVE R24 R16 
     356 [-]: MOVE R25 R21 
     357 [-]: GETIMPORT R23 9 [nil]
     358 [-]: CALL R23 2 0 
L54: 359 [-]: FORNLOOP R18 L48
L55: 360 [-]: FORNLOOP R12 L46
L56: 361 [-]: GETIMPORT R12 1 [nil]
     362 [-]: GETTABLEN R14 R0 1
     363 [-]: GETUPVAL R15 1
     364 [-]: NAMECALL R12 R12 K41 [0xEBBDC5C2]
     365 [-]: CALL R12 3 1 
     366 [-]: FASTCALL1 62 R12 L57
     367 [-]: MOVE R14 R12 
     368 [-]: GETIMPORT R13 30 [nil]
     369 [-]: CALL R13 1 1 
L57: 370 [-]: JUMPIF R13 L60
     371 [-]: LOADN R15 1  
     372 [-]: GETUPVAL R16 1
     373 [-]: LENGTH R13 R16
     374 [-]: LOADN R14 1  
     375 [-]: FORNPREP R13 L60
L58: 376 [-]: GETUPVAL R17 1
     377 [-]: GETTABLEN R16 R17 1
     378 [-]: JUMPIFEQ R16 R12 L60
     379 [-]: GETIMPORT R17 24 [nil]
     380 [-]: GETUPVAL R18 1
     381 [-]: LOADN R19 1  
     382 [-]: CALL R17 2 0 
     383 [-]: GETUPVAL R18 1
     384 [-]: FASTCALL2 52 R18 R16 L59
     385 [-]: MOVE R19 R16 
     386 [-]: GETIMPORT R17 9 [nil]
     387 [-]: CALL R17 2 0 
L59: 388 [-]: FORNLOOP R13 L58
L60: 389 [-]: GETUPVAL R13 8
     390 [-]: LOADK R14 K42 ["Optimized"]
     391 [-]: GETUPVAL R15 1
     392 [-]: CALL R13 2 0 
     393 [-]: RETURN R0 0  


; Name:            
; Defined at line: 1181
; #Upvalues:       17
; #Parameters:     3
; Is_vararg:       0
; Max Stack Size:  23

       0 [-]: GETUPVAL R3 0
       1 [-]: JUMPIFNOT R3 L0
       2 [-]: GETIMPORT R3 2 [nil]
       3 [-]: JUMPIFNOT R3 L0
       4 [-]: RETURN R0 0  
L 0:   5 [-]: LENGTH R3 R1 
       6 [-]: SETUPVAL R3 1
       7 [-]: GETIMPORT R3 4 [nil]
       8 [-]: MOVE R4 R2   
       9 [-]: CALL R3 1 3  
      10 [-]: FORGPREP_INEXT R3 L3
L 1:  11 [-]: FASTCALL1 62 R7 L2
      12 [-]: MOVE R9 R7   
      13 [-]: GETIMPORT R8 6 [nil]
      14 [-]: CALL R8 1 1  
L 2:  15 [-]: JUMPIF R8 L3 
      16 [-]: NAMECALL R8 R7 K7 [0xF37943FF]
      17 [-]: CALL R8 1 1  
      18 [-]: JUMPIFNOT R8 L3
      19 [-]: GETUPVAL R9 1
      20 [-]: ADDK R8 R9 K8 [1]
      21 [-]: SETUPVAL R8 1
L 3:  22 [-]: FORGLOOP R3 L1 2 [inext]
      23 [-]: GETUPVAL R3 1
      24 [-]: GETUPVAL R4 2
      25 [-]: JUMPIFNOTLE R4 R3 L4
      26 [-]: RETURN R0 0  
L 4:  27 [-]: GETUPVAL R3 3
      28 [-]: JUMPXEQKNIL R3 L5 NOT
      29 [-]: GETUPVAL R3 4
      30 [-]: CALL R3 0 0  
L 5:  31 [-]: GETUPVAL R4 3
      32 [-]: LENGTH R3 R4 
      33 [-]: JUMPXEQKN R3 K9 L6 NOT [0]
      34 [-]: RETURN R0 0  
L 6:  35 [-]: GETIMPORT R3 11 [nil]
      36 [-]: GETUPVAL R6 5
      37 [-]: LOADN R7 0   
      38 [-]: NAMECALL R4 R3 K12 [0x0EB34C69]
      39 [-]: CALL R4 3 1  
      40 [-]: GETUPVAL R7 6
      41 [-]: LOADN R8 0   
      42 [-]: NAMECALL R5 R3 K12 [0x0EB34C69]
      43 [-]: CALL R5 3 1  
      44 [-]: JUMPXEQKN R4 K8 L7 NOT [1]
      45 [-]: JUMPXEQKN R5 K9 L7 NOT [0]
      46 [-]: RETURN R0 0  
L 7:  47 [-]: LOADN R7 1   
      48 [-]: GETUPVAL R10 3
      49 [-]: LENGTH R9 R10
      50 [-]: MOD R8 R4 R9 
      51 [-]: ADD R6 R7 R8 
      52 [-]: GETUPVAL R8 3
      53 [-]: GETTABLE R7 R8 R6
      54 [-]: GETIMPORT R8 14 [nil]
      55 [-]: GETIMPORT R10 16 [nil]
      56 [-]: NAMECALL R11 R7 K17 [0xD1586535]
      57 [-]: CALL R11 1 1 
      58 [-]: LOADN R12 5  
      59 [-]: NAMECALL R8 R8 K18 [0x4E5939A5]
      60 [-]: CALL R8 4 1  
      61 [-]: FASTCALL1 62 R8 L8
      62 [-]: MOVE R10 R8  
      63 [-]: GETIMPORT R9 6 [nil]
      64 [-]: CALL R9 1 1  
L 8:  65 [-]: JUMPIFNOT R9 L9
      66 [-]: GETIMPORT R9 20 [nil]
      67 [-]: LOADK R11 K21 ["Could not find excavator state for "]
      68 [-]: NAMECALL R12 R7 K22 [0xED4E0128]
      69 [-]: CALL R12 1 1 
      70 [-]: CONCAT R10 R11 R12
      71 [-]: CALL R9 1 0  
      72 [-]: GETIMPORT R9 25 [nil]
      73 [-]: GETUPVAL R10 3
      74 [-]: MOVE R11 R6  
      75 [-]: CALL R9 2 0  
      76 [-]: RETURN R0 0  
L 9:  77 [-]: NAMECALL R9 R8 K7 [0xF37943FF]
      78 [-]: CALL R9 1 1  
      79 [-]: JUMPIFNOT R9 L10
      80 [-]: RETURN R0 0  
L10:  81 [-]: GETUPVAL R11 7
      82 [-]: LOADN R12 0  
      83 [-]: NAMECALL R9 R3 K12 [0x0EB34C69]
      84 [-]: CALL R9 3 1  
      85 [-]: JUMPXEQKN R9 K9 L26 NOT [0]
      86 [-]: GETIMPORT R10 14 [nil]
      87 [-]: GETIMPORT R12 27 [nil]
      88 [-]: NAMECALL R13 R7 K17 [0xD1586535]
      89 [-]: CALL R13 1 1 
      90 [-]: LOADK R14 K28 [0.20000000000000001]
      91 [-]: NAMECALL R10 R10 K18 [0x4E5939A5]
      92 [-]: CALL R10 4 1 
      93 [-]: FASTCALL1 62 R10 L11
      94 [-]: MOVE R12 R10 
      95 [-]: GETIMPORT R11 6 [nil]
      96 [-]: CALL R11 1 1 
L11:  97 [-]: JUMPIF R11 L12
      98 [-]: NAMECALL R11 R10 K7 [0xF37943FF]
      99 [-]: CALL R11 1 1 
     100 [-]: JUMPIFNOT R11 L12
     101 [-]: RETURN R0 0  
L12: 102 [-]: GETUPVAL R13 8
     103 [-]: LOADN R14 0  
     104 [-]: NAMECALL R11 R3 K12 [0x0EB34C69]
     105 [-]: CALL R11 3 1 
     106 [-]: LOADN R12 500
     107 [-]: GETIMPORT R13 11 [nil]
     108 [-]: NAMECALL R13 R13 K29 [0xEF893AEC]
     109 [-]: CALL R13 1 1 
     110 [-]: GETUPVAL R14 9
     111 [-]: JUMPIF R14 L13
     112 [-]: GETTABLEKS R14 R13 K30 ["maxWaveNum"]
L13: 113 [-]: LOADN R15 0  
     114 [-]: JUMPIFNOTLT R15 R14 L14
     115 [-]: GETUPVAL R15 10
     116 [-]: MUL R12 R14 R15
L14: 117 [-]: LOADB R15 1  
     118 [-]: GETIMPORT R17 11 [nil]
     119 [-]: NAMECALL R17 R17 K29 [0xEF893AEC]
     120 [-]: CALL R17 1 1 
     121 [-]: GETTABLEKS R16 R17 K31 ["periodicMissionTag"]
     122 [-]: GETUPVAL R18 11
     123 [-]: GETTABLEKS R17 R18 K32 ["ELITE_ALERT_PERIODIC_MISSION_TAG"]
     124 [-]: JUMPIFEQ R16 R17 L16
     125 [-]: GETIMPORT R17 11 [nil]
     126 [-]: NAMECALL R17 R17 K29 [0xEF893AEC]
     127 [-]: CALL R17 1 1 
     128 [-]: GETTABLEKS R16 R17 K31 ["periodicMissionTag"]
     129 [-]: GETUPVAL R18 11
     130 [-]: GETTABLEKS R17 R18 K33 ["ELITE_ALERT_PERIODIC_MISSION_TAG_ALT"]
     131 [-]: JUMPIFEQ R16 R17 L15
     132 [-]: LOADB R15 0 +1
L15: 133 [-]: LOADB R15 1  
L16: 134 [-]: JUMPIFNOT R15 L17
     135 [-]: MULK R12 R12 K34 [2]
L17: 136 [-]: LOADB R15 0  
     137 [-]: GETUPVAL R18 12
     138 [-]: NAMECALL R16 R3 K12 [0x0EB34C69]
     139 [-]: CALL R16 2 1 
     140 [-]: GETUPVAL R17 13
     141 [-]: JUMPIFNOT R17 L18
     142 [-]: JUMPXEQKN R16 K9 L18 NOT [0]
     143 [-]: GETUPVAL R17 14
     144 [-]: CALL R17 0 1 
     145 [-]: JUMPIFNOT R17 L18
     146 [-]: LOADB R15 1  
L18: 147 [-]: LOADB R17 1  
     148 [-]: GETTABLEKS R18 R13 K35 ["goalTag"]
     149 [-]: GETIMPORT R19 37 [nil]
     150 [-]: LOADK R20 K38 ["ShieldExcav"]
     151 [-]: CALL R19 1 1 
     152 [-]: JUMPIFEQ R18 R19 L20
     153 [-]: GETTABLEKS R18 R13 K35 ["goalTag"]
     154 [-]: GETIMPORT R19 37 [nil]
     155 [-]: LOADK R20 K39 ["OldWorldSalvage"]
     156 [-]: CALL R19 1 1 
     157 [-]: JUMPIFEQ R18 R19 L19
     158 [-]: LOADB R17 0 +1
L19: 159 [-]: LOADB R17 1  
L20: 160 [-]: JUMPIFNOT R17 L21
     161 [-]: JUMPIFNOTLE R14 R4 L21
     162 [-]: JUMPIF R15 L21
     163 [-]: LOADN R18 0  
     164 [-]: SETUPVAL R18 2
     165 [-]: RETURN R0 0  
L21: 166 [-]: GETUPVAL R18 0
     167 [-]: JUMPIFNOT R18 L22
     168 [-]: JUMPIFNOTLE R12 R11 L22
     169 [-]: JUMPIF R17 L22
     170 [-]: LOADN R18 0  
     171 [-]: SETUPVAL R18 2
     172 [-]: RETURN R0 0  
L22: 173 [-]: LOADNIL R18  
     174 [-]: JUMPXEQKN R4 K9 L23 [0]
     175 [-]: JUMP L24
    
L23: 176 [-]: LOADN R18 2  
     177 [-]: JUMP L25
    
L24: 178 [-]: LOADN R18 60 
L25: 179 [-]: GETUPVAL R21 7
     180 [-]: ADD R22 R0 R18
     181 [-]: NAMECALL R19 R3 K40 [0x751F061D]
     182 [-]: CALL R19 3 0 
     183 [-]: RETURN R0 0  
L26: 184 [-]: JUMPIFNOTLT R0 R9 L27
     185 [-]: RETURN R0 0  
L27: 186 [-]: JUMPIFNOTLT R5 R4 L28
     187 [-]: RETURN R0 0  
L28: 188 [-]: GETUPVAL R10 1
     189 [-]: JUMPXEQKN R10 K9 L29 NOT [0]
     190 [-]: GETIMPORT R10 14 [nil]
     191 [-]: NAMECALL R10 R10 K41 [0x29EF273D]
     192 [-]: CALL R10 1 1 
     193 [-]: NAMECALL R10 R10 K42 [0x66905CB0]
     194 [-]: CALL R10 1 1 
     195 [-]: MOVE R13 R7  
     196 [-]: NAMECALL R11 R10 K43 [0xE2871589]
     197 [-]: CALL R11 2 0 
L29: 198 [-]: GETUPVAL R12 5
     199 [-]: ADDK R13 R4 K8 [1]
     200 [-]: NAMECALL R10 R3 K40 [0x751F061D]
     201 [-]: CALL R10 3 0 
     202 [-]: GETUPVAL R12 7
     203 [-]: LOADN R13 0  
     204 [-]: NAMECALL R10 R3 K40 [0x751F061D]
     205 [-]: CALL R10 3 0 
     206 [-]: LOADK R12 K44 ["TriggerPort"]
     207 [-]: NAMECALL R10 R7 K45 [0x8EB2112D]
     208 [-]: CALL R10 2 0 
     209 [-]: GETUPVAL R11 15
     210 [-]: GETTABLEKS R10 R11 K46 [0x9742B85B]
     211 [-]: GETIMPORT R11 48 [nil]
     212 [-]: GETUPVAL R13 16
     213 [-]: GETTABLEKS R12 R13 K49 [0x06D055F9]
     214 [-]: GETUPVAL R14 1
     215 [-]: JUMPXEQKN R14 K9 L30 [0]
     216 [-]: LOADB R13 0 +1
L30: 217 [-]: LOADB R13 1  
L31: 218 [-]: GETIMPORT R14 37 [nil]
     219 [-]: LOADK R15 K50 ["MissionIntro"]
     220 [-]: CALL R14 1 1 
     221 [-]: GETIMPORT R15 37 [nil]
     222 [-]: LOADK R16 K51 ["MissionScannerComplete"]
     223 [-]: CALL R15 1 -1
     224 [-]: CALL R12 -1 -1
     225 [-]: CALL R10 -1 0
     226 [-]: GETUPVAL R11 15
     227 [-]: GETTABLEKS R10 R11 K46 [0x9742B85B]
     228 [-]: GETIMPORT R11 48 [nil]
     229 [-]: GETUPVAL R13 16
     230 [-]: GETTABLEKS R12 R13 K49 [0x06D055F9]
     231 [-]: GETUPVAL R14 1
     232 [-]: JUMPXEQKN R14 K9 L32 [0]
     233 [-]: LOADB R13 0 +1
L32: 234 [-]: LOADB R13 1  
L33: 235 [-]: GETIMPORT R14 37 [nil]
     236 [-]: LOADK R15 K52 ["MissionIntroExtra"]
     237 [-]: CALL R14 1 1 
     238 [-]: GETIMPORT R15 37 [nil]
     239 [-]: LOADK R16 K53 ["MissionScannerCompleteExtra"]
     240 [-]: CALL R15 1 -1
     241 [-]: CALL R12 -1 -1
     242 [-]: CALL R10 -1 0
     243 [-]: RETURN R0 0  


; Name:            
; Defined at line: 1308
; #Upvalues:       4
; #Parameters:     2
; Is_vararg:       0
; Max Stack Size:  8

       0 [-]: LOADB R2 0   
       1 [-]: GETUPVAL R3 0
       2 [-]: JUMPIFNOT R3 L11
       3 [-]: JUMPXEQKNIL R1 L0
       4 [-]: JUMPXEQKN R1 K0 L11 NOT [1]
L 0:   5 [-]: GETIMPORT R3 2 [nil]
       6 [-]: GETUPVAL R5 1
       7 [-]: LOADN R6 1   
       8 [-]: NAMECALL R3 R3 K3 [0x751F061D]
       9 [-]: CALL R3 3 0  
      10 [-]: GETUPVAL R4 2
      11 [-]: GETTABLEKS R3 R4 K4 [0x06D055F9]
      12 [-]: JUMPXEQKNIL R1 L1
      13 [-]: LOADB R4 0 +1
L 1:  14 [-]: LOADB R4 1   
L 2:  15 [-]: LOADN R5 3   
      16 [-]: LOADN R6 0   
      17 [-]: CALL R3 3 1  
L 3:  18 [-]: GETUPVAL R5 3
      19 [-]: GETTABLEKS R4 R5 K5 [0x0DEACD54]
      20 [-]: CALL R4 0 1  
      21 [-]: JUMPIF R4 L4 
      22 [-]: GETIMPORT R4 7 [nil]
      23 [-]: CALL R4 0 1  
      24 [-]: SUB R3 R3 R4 
      25 [-]: LOADN R4 0   
      26 [-]: JUMPIFLE R3 R4 L4
      27 [-]: GETIMPORT R4 9 [nil]
      28 [-]: LOADN R5 0   
      29 [-]: CALL R4 1 0  
      30 [-]: JUMPBACK L3  
L 4:  31 [-]: LOADN R3 20  
L 5:  32 [-]: GETUPVAL R5 3
      33 [-]: GETTABLEKS R4 R5 K5 [0x0DEACD54]
      34 [-]: CALL R4 0 1  
      35 [-]: JUMPIFNOT R4 L6
      36 [-]: GETIMPORT R4 7 [nil]
      37 [-]: CALL R4 0 1  
      38 [-]: SUB R3 R3 R4 
      39 [-]: LOADN R4 0   
      40 [-]: JUMPIFLE R3 R4 L6
      41 [-]: GETIMPORT R4 9 [nil]
      42 [-]: LOADN R5 0   
      43 [-]: CALL R4 1 0  
      44 [-]: JUMPBACK L5  
L 6:  45 [-]: GETIMPORT R4 2 [nil]
      46 [-]: MOVE R6 R0   
      47 [-]: LOADB R7 0   
      48 [-]: NAMECALL R4 R4 K10 [0xDCED2D0E]
      49 [-]: CALL R4 3 1  
      50 [-]: FASTCALL1 62 R4 L7
      51 [-]: MOVE R6 R4   
      52 [-]: GETIMPORT R5 12 [nil]
      53 [-]: CALL R5 1 1  
L 7:  54 [-]: JUMPIF R5 L11
      55 [-]: LOADB R2 1   
L 8:  56 [-]: FASTCALL1 62 R4 L9
      57 [-]: MOVE R6 R4   
      58 [-]: GETIMPORT R5 12 [nil]
      59 [-]: CALL R5 1 1  
L 9:  60 [-]: JUMPIF R5 L10
      61 [-]: GETIMPORT R5 9 [nil]
      62 [-]: LOADN R6 0   
      63 [-]: CALL R5 1 0  
      64 [-]: JUMPBACK L8  
L10:  65 [-]: GETIMPORT R5 2 [nil]
      66 [-]: NAMECALL R5 R5 K13 [0xF36E974A]
      67 [-]: CALL R5 1 0  
L11:  68 [-]: JUMPIF R2 L12
      69 [-]: JUMPXEQKN R1 K14 L18 NOT [2]
L12:  70 [-]: GETIMPORT R3 2 [nil]
      71 [-]: GETUPVAL R5 1
      72 [-]: LOADN R6 2   
      73 [-]: NAMECALL R3 R3 K3 [0x751F061D]
      74 [-]: CALL R3 3 0  
      75 [-]: GETIMPORT R3 2 [nil]
      76 [-]: JUMPXEQKNIL R1 L13 NOT
      77 [-]: LOADB R5 0 +1
L13:  78 [-]: LOADB R5 1   
L14:  79 [-]: NAMECALL R3 R3 K15 [0x494DB239]
      80 [-]: CALL R3 2 1  
      81 [-]: FASTCALL1 62 R3 L15
      82 [-]: MOVE R5 R3   
      83 [-]: GETIMPORT R4 12 [nil]
      84 [-]: CALL R4 1 1  
L15:  85 [-]: JUMPIF R4 L18
L16:  86 [-]: FASTCALL1 62 R3 L17
      87 [-]: MOVE R5 R3   
      88 [-]: GETIMPORT R4 12 [nil]
      89 [-]: CALL R4 1 1  
L17:  90 [-]: JUMPIF R4 L18
      91 [-]: GETIMPORT R4 9 [nil]
      92 [-]: LOADN R5 0   
      93 [-]: CALL R4 1 0  
      94 [-]: JUMPBACK L16 
L18:  95 [-]: GETIMPORT R3 2 [nil]
      96 [-]: GETUPVAL R5 1
      97 [-]: LOADN R6 0   
      98 [-]: NAMECALL R3 R3 K3 [0x751F061D]
      99 [-]: CALL R3 3 0  
     100 [-]: RETURN R0 0  


; Name:            
; Defined at line: 1362
; #Upvalues:       31
; #Parameters:     0
; Is_vararg:       0
; Max Stack Size:  29

       0 [-]: GETIMPORT R0 1 [nil]
       1 [-]: NAMECALL R0 R0 K2 [0x29EF273D]
       2 [-]: CALL R0 1 1  
       3 [-]: NAMECALL R0 R0 K3 [0x66905CB0]
       4 [-]: CALL R0 1 1  
       5 [-]: LOADB R3 1   
       6 [-]: NAMECALL R1 R0 K4 [0x383D2E7D]
       7 [-]: CALL R1 2 0  
       8 [-]: LOADB R3 0   
       9 [-]: NAMECALL R1 R0 K5 [0x911CE2B4]
      10 [-]: CALL R1 2 0  
      11 [-]: LOADB R3 0   
      12 [-]: NAMECALL R1 R0 K6 [0x2FAEAD12]
      13 [-]: CALL R1 2 0  
      14 [-]: LOADB R3 1   
      15 [-]: NAMECALL R1 R0 K7 [0xE603BAB2]
      16 [-]: CALL R1 2 0  
      17 [-]: LOADN R3 0   
      18 [-]: NAMECALL R1 R0 K8 [0x3EA76F0C]
      19 [-]: CALL R1 2 0  
      20 [-]: LOADN R3 1500
      21 [-]: LOADN R4 1500
      22 [-]: LOADB R5 0   
      23 [-]: LOADB R6 0   
      24 [-]: NAMECALL R1 R0 K9 [0x2B39CBDE]
      25 [-]: CALL R1 5 0  
      26 [-]: LOADB R3 1   
      27 [-]: NAMECALL R1 R0 K10 [0x1A82855B]
      28 [-]: CALL R1 2 0  
      29 [-]: GETUPVAL R1 0
      30 [-]: JUMPIFNOT R1 L0
      31 [-]: LOADB R3 0   
      32 [-]: NAMECALL R1 R0 K11 [0x9AEF5DCB]
      33 [-]: CALL R1 2 0  
      34 [-]: LOADN R3 10  
      35 [-]: LOADN R4 1500
      36 [-]: LOADN R5 0   
      37 [-]: LOADN R6 3   
      38 [-]: LOADB R7 0   
      39 [-]: LOADB R8 0   
      40 [-]: LOADB R9 1   
      41 [-]: NAMECALL R1 R0 K12 [0xA2367658]
      42 [-]: CALL R1 8 0  
      43 [-]: JUMP L1
     
L 0:  44 [-]: LOADN R3 10  
      45 [-]: LOADN R4 1500
      46 [-]: LOADN R5 0   
      47 [-]: LOADN R6 3   
      48 [-]: LOADB R7 1   
      49 [-]: LOADB R8 1   
      50 [-]: LOADB R9 1   
      51 [-]: NAMECALL R1 R0 K12 [0xA2367658]
      52 [-]: CALL R1 8 0  
L 1:  53 [-]: GETUPVAL R3 1
      54 [-]: NAMECALL R1 R0 K13 [0xA7FB023F]
      55 [-]: CALL R1 2 0  
      56 [-]: GETUPVAL R3 2
      57 [-]: NAMECALL R1 R0 K13 [0xA7FB023F]
      58 [-]: CALL R1 2 0  
      59 [-]: GETUPVAL R3 3
      60 [-]: NAMECALL R1 R0 K13 [0xA7FB023F]
      61 [-]: CALL R1 2 0  
      62 [-]: GETUPVAL R3 4
      63 [-]: NAMECALL R1 R0 K13 [0xA7FB023F]
      64 [-]: CALL R1 2 0  
      65 [-]: GETUPVAL R3 5
      66 [-]: NAMECALL R1 R0 K13 [0xA7FB023F]
      67 [-]: CALL R1 2 0  
      68 [-]: LOADN R3 0   
      69 [-]: NAMECALL R1 R0 K14 [0xFDA3B6ED]
      70 [-]: CALL R1 2 0  
      71 [-]: GETUPVAL R1 0
      72 [-]: JUMPIF R1 L2 
      73 [-]: GETIMPORT R1 1 [nil]
      74 [-]: GETUPVAL R3 7
      75 [-]: NAMECALL R1 R1 K15 [0x46A0EBF5]
      76 [-]: CALL R1 2 1  
      77 [-]: SETUPVAL R1 6
L 2:  78 [-]: GETIMPORT R2 18 [nil]
      79 [-]: FASTCALL1 62 R2 L3
      80 [-]: GETIMPORT R1 20 [nil]
      81 [-]: CALL R1 1 1  
L 3:  82 [-]: JUMPIF R1 L4 
      83 [-]: GETIMPORT R3 18 [nil]
      84 [-]: NAMECALL R1 R0 K21 [0xE2871589]
      85 [-]: CALL R1 2 0  
      86 [-]: JUMP L6
     
L 4:  87 [-]: GETUPVAL R1 0
      88 [-]: JUMPIF R1 L6 
      89 [-]: GETUPVAL R2 6
      90 [-]: FASTCALL1 62 R2 L5
      91 [-]: GETIMPORT R1 20 [nil]
      92 [-]: CALL R1 1 1  
L 5:  93 [-]: JUMPIF R1 L6 
      94 [-]: GETUPVAL R3 6
      95 [-]: NAMECALL R1 R0 K21 [0xE2871589]
      96 [-]: CALL R1 2 0  
L 6:  97 [-]: GETIMPORT R1 23 [nil]
      98 [-]: GETUPVAL R3 8
      99 [-]: NAMECALL R1 R1 K24 [0x0EB34C69]
     100 [-]: CALL R1 2 1  
     101 [-]: GETIMPORT R2 23 [nil]
     102 [-]: GETUPVAL R4 9
     103 [-]: LOADN R5 0   
     104 [-]: NAMECALL R2 R2 K24 [0x0EB34C69]
     105 [-]: CALL R2 3 1  
     106 [-]: GETIMPORT R3 23 [nil]
     107 [-]: NAMECALL R3 R3 K25 [0xEF893AEC]
     108 [-]: CALL R3 1 1  
     109 [-]: NEWTABLE R4 0 0
     110 [-]: NEWTABLE R5 0 0
     111 [-]: NEWTABLE R6 0 0
     112 [-]: LOADN R7 0   
     113 [-]: GETIMPORT R9 23 [nil]
     114 [-]: GETUPVAL R11 11
     115 [-]: LOADN R12 0  
     116 [-]: NAMECALL R9 R9 K24 [0x0EB34C69]
     117 [-]: CALL R9 3 1  
     118 [-]: LOADN R10 0  
     119 [-]: JUMPIFLT R10 R9 L7
     120 [-]: LOADB R8 0 +1
L 7: 121 [-]: LOADB R8 1   
L 8: 122 [-]: SETUPVAL R8 10
L 9: 123 [-]: JUMPXEQKN R1 K26 L10 NOT [0]
     124 [-]: GETUPVAL R8 12
     125 [-]: MOVE R9 R2   
     126 [-]: MOVE R10 R7  
     127 [-]: MOVE R11 R4  
     128 [-]: MOVE R12 R5  
     129 [-]: CALL R8 4 1  
     130 [-]: MOVE R7 R8   
     131 [-]: GETIMPORT R8 28 [nil]
     132 [-]: MOVE R9 R7   
     133 [-]: CALL R8 1 0  
     134 [-]: GETIMPORT R8 23 [nil]
     135 [-]: GETUPVAL R10 8
     136 [-]: NAMECALL R8 R8 K24 [0x0EB34C69]
     137 [-]: CALL R8 2 1  
     138 [-]: MOVE R1 R8   
     139 [-]: JUMPBACK L9  
L10: 140 [-]: JUMPXEQKN R1 K29 L11 NOT [1]
     141 [-]: GETUPVAL R8 12
     142 [-]: MOVE R9 R2   
     143 [-]: MOVE R10 R7  
     144 [-]: MOVE R11 R4  
     145 [-]: MOVE R12 R5  
     146 [-]: CALL R8 4 1  
     147 [-]: MOVE R7 R8   
     148 [-]: GETIMPORT R8 28 [nil]
     149 [-]: MOVE R9 R7   
     150 [-]: CALL R8 1 0  
     151 [-]: GETIMPORT R8 23 [nil]
     152 [-]: GETUPVAL R10 8
     153 [-]: NAMECALL R8 R8 K24 [0x0EB34C69]
     154 [-]: CALL R8 2 1  
     155 [-]: MOVE R1 R8   
     156 [-]: JUMPBACK L10 
L11: 157 [-]: GETIMPORT R8 23 [nil]
     158 [-]: GETUPVAL R10 13
     159 [-]: GETIMPORT R11 31 [nil]
     160 [-]: LOADN R12 0  
     161 [-]: LOADB R13 0  
     162 [-]: LOADB R14 0  
     163 [-]: LOADB R15 1  
     164 [-]: NAMECALL R8 R8 K32 [0xFE23FE59]
     165 [-]: CALL R8 7 0  
     166 [-]: GETIMPORT R8 23 [nil]
     167 [-]: GETUPVAL R10 13
     168 [-]: MOVE R11 R2  
     169 [-]: NAMECALL R8 R8 K33 [0x39A80406]
     170 [-]: CALL R8 3 0  
     171 [-]: GETIMPORT R8 34 [nil]
     172 [-]: SETTABLEKS R2 R8 K35 ["LastActivityTime"]
     173 [-]: LOADB R10 1  
     174 [-]: NAMECALL R8 R0 K7 [0xE603BAB2]
     175 [-]: CALL R8 2 0  
     176 [-]: LOADN R10 10 
     177 [-]: NAMECALL R8 R0 K36 [0xB999D6BE]
     178 [-]: CALL R8 2 0  
     179 [-]: LOADB R8 0   
     180 [-]: LOADB R9 0   
     181 [-]: LOADN R10 0  
     182 [-]: LOADN R11 60 
     183 [-]: GETIMPORT R12 23 [nil]
     184 [-]: GETUPVAL R14 14
     185 [-]: LOADN R15 0  
     186 [-]: NAMECALL R12 R12 K24 [0x0EB34C69]
     187 [-]: CALL R12 3 1 
     188 [-]: LOADN R14 200
     189 [-]: LOADN R16 1  
     190 [-]: DIVK R18 R12 K37 [200]
     191 [-]: FASTCALL1 12 R18 L12
     192 [-]: GETIMPORT R17 40 [nil]
     193 [-]: CALL R17 1 1 
L12: 194 [-]: ADD R15 R16 R17
     195 [-]: MUL R13 R14 R15
     196 [-]: LOADN R14 -1 
     197 [-]: LOADN R15 0  
     198 [-]: LOADN R16 0  
L13: 199 [-]: JUMPXEQKN R1 K41 L53 NOT [2]
     200 [-]: GETIMPORT R17 23 [nil]
     201 [-]: GETUPVAL R19 15
     202 [-]: LOADN R20 0  
     203 [-]: NAMECALL R17 R17 K24 [0x0EB34C69]
     204 [-]: CALL R17 3 1 
     205 [-]: LOADB R18 0  
     206 [-]: JUMPIFEQ R14 R17 L18
     207 [-]: MOVE R14 R17 
     208 [-]: GETIMPORT R19 1 [nil]
     209 [-]: GETUPVAL R21 16
     210 [-]: NAMECALL R19 R19 K42 [0xC7FCADA9]
     211 [-]: CALL R19 2 1 
     212 [-]: MOVE R4 R19  
     213 [-]: NEWTABLE R5 0 0
     214 [-]: LOADN R21 1  
     215 [-]: LENGTH R19 R4
     216 [-]: LOADN R20 1  
     217 [-]: FORNPREP R19 L17
L14: 218 [-]: GETTABLE R22 R4 R21
     219 [-]: GETIMPORT R23 1 [nil]
     220 [-]: GETIMPORT R25 44 [nil]
     221 [-]: NAMECALL R26 R22 K45 [0xD1586535]
     222 [-]: CALL R26 1 1 
     223 [-]: LOADN R27 5  
     224 [-]: NAMECALL R23 R23 K46 [0x4E5939A5]
     225 [-]: CALL R23 4 1 
     226 [-]: FASTCALL1 62 R23 L15
     227 [-]: MOVE R25 R23 
     228 [-]: GETIMPORT R24 20 [nil]
     229 [-]: CALL R24 1 1 
L15: 230 [-]: JUMPIFNOT R24 L16
     231 [-]: GETIMPORT R24 48 [nil]
     232 [-]: LOADK R26 K49 ["No state for "]
     233 [-]: NAMECALL R27 R22 K50 [0xED4E0128]
     234 [-]: CALL R27 1 1 
     235 [-]: CONCAT R25 R26 R27
     236 [-]: CALL R24 1 0 
L16: 237 [-]: SETTABLE R23 R5 R21
     238 [-]: FORNLOOP R19 L14
L17: 239 [-]: LOADB R18 1  
     240 [-]: JUMP L22
    
L18: 241 [-]: LENGTH R21 R4
     242 [-]: LOADN R19 1  
     243 [-]: LOADN R20 -1 
     244 [-]: FORNPREP R19 L22
L19: 245 [-]: GETTABLE R23 R4 R21
     246 [-]: FASTCALL1 62 R23 L20
     247 [-]: GETIMPORT R22 20 [nil]
     248 [-]: CALL R22 1 1 
L20: 249 [-]: JUMPIFNOT R22 L21
     250 [-]: GETIMPORT R22 53 [nil]
     251 [-]: MOVE R23 R4  
     252 [-]: MOVE R24 R21 
     253 [-]: CALL R22 2 0 
     254 [-]: GETIMPORT R22 53 [nil]
     255 [-]: MOVE R23 R5  
     256 [-]: MOVE R24 R21 
     257 [-]: CALL R22 2 0 
     258 [-]: LOADB R18 1  
L21: 259 [-]: FORNLOOP R19 L19
L22: 260 [-]: LENGTH R19 R6
     261 [-]: JUMPXEQKN R19 K26 L23 NOT [0]
     262 [-]: GETIMPORT R19 1 [nil]
     263 [-]: GETUPVAL R21 17
     264 [-]: NAMECALL R19 R19 K42 [0xC7FCADA9]
     265 [-]: CALL R19 2 1 
     266 [-]: MOVE R6 R19  
     267 [-]: GETUPVAL R19 0
     268 [-]: JUMPIFNOT R19 L23
     269 [-]: GETIMPORT R19 55 [nil]
     270 [-]: JUMPIFNOT R19 L23
     271 [-]: GETIMPORT R19 55 [nil]
     272 [-]: MOVE R20 R6  
     273 [-]: CALL R19 1 1 
     274 [-]: MOVE R6 R19  
L23: 275 [-]: JUMPIFNOT R18 L26
     276 [-]: MOVE R21 R4  
     277 [-]: NAMECALL R19 R0 K56 [0xFF7A6E32]
     278 [-]: CALL R19 2 0 
     279 [-]: LENGTH R19 R4
     280 [-]: LOADN R20 0  
     281 [-]: JUMPIFNOTLT R20 R19 L25
     282 [-]: GETUPVAL R19 0
     283 [-]: JUMPIFNOT R19 L24
     284 [-]: LOADN R21 10 
     285 [-]: LOADN R22 1500
     286 [-]: LOADN R23 0  
     287 [-]: LOADN R24 3  
     288 [-]: LOADB R25 0  
     289 [-]: LOADB R26 0  
     290 [-]: LOADB R27 1  
     291 [-]: NAMECALL R19 R0 K12 [0xA2367658]
     292 [-]: CALL R19 8 0 
     293 [-]: JUMP L25
    
L24: 294 [-]: LOADN R21 10 
     295 [-]: LOADN R22 1500
     296 [-]: LOADN R23 0  
     297 [-]: LOADN R24 3  
     298 [-]: LOADB R25 1  
     299 [-]: LOADB R26 0  
     300 [-]: LOADB R27 1  
     301 [-]: NAMECALL R19 R0 K12 [0xA2367658]
     302 [-]: CALL R19 8 0 
L25: 303 [-]: GETUPVAL R19 18
     304 [-]: MOVE R20 R4  
     305 [-]: CALL R19 1 0 
     306 [-]: JUMP L31
    
L26: 307 [-]: GETIMPORT R19 1 [nil]
     308 [-]: NAMECALL R19 R19 K57 [0x8B5B1F58]
     309 [-]: CALL R19 1 1 
     310 [-]: LOADN R20 0  
     311 [-]: GETIMPORT R21 59 [nil]
     312 [-]: MOVE R22 R19 
     313 [-]: CALL R21 1 3 
     314 [-]: FORGPREP_INEXT R21 L29
L27: 315 [-]: FASTCALL1 62 R25 L28
     316 [-]: MOVE R27 R25 
     317 [-]: GETIMPORT R26 20 [nil]
     318 [-]: CALL R26 1 1 
L28: 319 [-]: JUMPIF R26 L29
     320 [-]: NAMECALL R26 R25 K60 [0x2047CFE7]
     321 [-]: CALL R26 1 1 
     322 [-]: JUMPIF R26 L29
     323 [-]: ADDK R20 R20 K29 [1]
L29: 324 [-]: FORGLOOP R21 L27 2 [inext]
     325 [-]: LENGTH R21 R19
     326 [-]: JUMPIFNOTEQ R15 R21 L30
     327 [-]: JUMPIFEQ R16 R20 L31
L30: 328 [-]: GETUPVAL R21 18
     329 [-]: MOVE R22 R4  
     330 [-]: CALL R21 1 0 
     331 [-]: LENGTH R15 R19
     332 [-]: MOVE R16 R20 
L31: 333 [-]: GETUPVAL R19 19
     334 [-]: MOVE R20 R2  
     335 [-]: MOVE R21 R4  
     336 [-]: MOVE R22 R6  
     337 [-]: CALL R19 3 0 
     338 [-]: GETIMPORT R19 62 [nil]
     339 [-]: JUMPIFNOT R19 L39
     340 [-]: JUMPIF R8 L39
     341 [-]: GETUPVAL R19 20
     342 [-]: JUMPIFNOT R19 L35
     343 [-]: GETUPVAL R19 21
     344 [-]: GETIMPORT R20 23 [nil]
     345 [-]: GETUPVAL R22 22
     346 [-]: LOADN R23 0  
     347 [-]: NAMECALL R20 R20 K24 [0x0EB34C69]
     348 [-]: CALL R20 3 1 
     349 [-]: JUMPXEQKN R20 K29 L32 NOT [1]
     350 [-]: GETIMPORT R20 64 [nil]
     351 [-]: LOADK R21 K65 ["MissionExtractionAvailablePistol"]
     352 [-]: CALL R20 1 1 
     353 [-]: MOVE R19 R20 
L32: 354 [-]: GETIMPORT R20 1 [nil]
     355 [-]: NAMECALL R20 R20 K66 [0x7D108DDB]
     356 [-]: CALL R20 1 1 
     357 [-]: LOADN R23 1  
     358 [-]: LENGTH R21 R20
     359 [-]: LOADN R22 1  
     360 [-]: FORNPREP R21 L36
L33: 361 [-]: GETUPVAL R25 23
     362 [-]: GETTABLEKS R24 R25 K67 [0x56B5886E]
     363 [-]: GETTABLE R25 R20 R23
     364 [-]: CALL R24 1 1 
     365 [-]: JUMPIFNOT R24 L34
     366 [-]: GETIMPORT R24 64 [nil]
     367 [-]: LOADK R25 K68 ["MissionFirstExtractionAvailable"]
     368 [-]: CALL R24 1 1 
     369 [-]: MOVE R19 R24 
L34: 370 [-]: GETUPVAL R25 24
     371 [-]: GETTABLEKS R24 R25 K69 [0xF22CFC77]
     372 [-]: GETIMPORT R25 71 [nil]
     373 [-]: MOVE R26 R19 
     374 [-]: GETTABLE R27 R20 R23
     375 [-]: NAMECALL R27 R27 K72 [0xBB610E5B]
     376 [-]: CALL R27 1 -1
     377 [-]: CALL R24 -1 0
     378 [-]: FORNLOOP R21 L33
     379 [-]: JUMP L36
    
L35: 380 [-]: GETTABLEKS R19 R3 K73 ["goalTag"]
     381 [-]: GETUPVAL R20 25
     382 [-]: JUMPIFEQ R19 R20 L36
     383 [-]: GETUPVAL R20 24
     384 [-]: GETTABLEKS R19 R20 K74 [0x9742B85B]
     385 [-]: GETIMPORT R20 71 [nil]
     386 [-]: GETUPVAL R21 21
     387 [-]: CALL R19 2 0 
L36: 388 [-]: GETUPVAL R19 0
     389 [-]: JUMPIF R19 L38
     390 [-]: GETIMPORT R19 23 [nil]
     391 [-]: LOADB R21 1  
     392 [-]: LOADB R22 1  
     393 [-]: NAMECALL R19 R19 K75 [0xC7C8DAD6]
     394 [-]: CALL R19 3 0 
     395 [-]: GETUPVAL R20 6
     396 [-]: FASTCALL1 62 R20 L37
     397 [-]: GETIMPORT R19 20 [nil]
     398 [-]: CALL R19 1 1 
L37: 399 [-]: JUMPIF R19 L38
     400 [-]: GETUPVAL R19 6
     401 [-]: LOADK R21 K76 ["Enable"]
     402 [-]: NAMECALL R19 R19 K77 [0x8EB2112D]
     403 [-]: CALL R19 2 0 
L38: 404 [-]: LOADB R8 1   
L39: 405 [-]: JUMPIF R9 L40
     406 [-]: GETUPVAL R19 26
     407 [-]: JUMPIFNOT R19 L40
     408 [-]: GETIMPORT R19 23 [nil]
     409 [-]: GETUPVAL R21 27
     410 [-]: LOADN R22 0  
     411 [-]: NAMECALL R19 R19 K24 [0x0EB34C69]
     412 [-]: CALL R19 3 1 
     413 [-]: GETUPVAL R21 28
     414 [-]: MULK R20 R21 K78 [3]
     415 [-]: JUMPIFNOTLE R20 R19 L40
     416 [-]: GETIMPORT R19 23 [nil]
     417 [-]: LOADB R21 1  
     418 [-]: NAMECALL R19 R19 K79 [0xD1961230]
     419 [-]: CALL R19 2 0 
     420 [-]: LOADB R9 1   
L40: 421 [-]: GETIMPORT R19 23 [nil]
     422 [-]: GETUPVAL R21 14
     423 [-]: LOADN R22 0  
     424 [-]: NAMECALL R19 R19 K24 [0x0EB34C69]
     425 [-]: CALL R19 3 1 
     426 [-]: MOVE R12 R19 
     427 [-]: JUMPIFEQ R12 R10 L43
     428 [-]: JUMPIFNOTLT R10 R13 L42
     429 [-]: JUMPIFNOTLE R13 R12 L42
     430 [-]: ADDK R13 R13 K37 [200]
     431 [-]: GETUPVAL R19 29
     432 [-]: DIVK R21 R12 K37 [200]
     433 [-]: FASTCALL1 12 R21 L41
     434 [-]: GETIMPORT R20 40 [nil]
     435 [-]: CALL R20 1 1 
L41: 436 [-]: CALL R19 1 0 
L42: 437 [-]: MOVE R10 R12 
L43: 438 [-]: GETUPVAL R19 12
     439 [-]: MOVE R20 R2  
     440 [-]: MOVE R21 R7  
     441 [-]: MOVE R22 R4  
     442 [-]: MOVE R23 R5  
     443 [-]: CALL R19 4 1 
     444 [-]: MOVE R7 R19  
     445 [-]: JUMPIFNOT R8 L45
     446 [-]: LOADN R19 0  
     447 [-]: JUMPIFNOTLT R19 R11 L45
     448 [-]: SUB R11 R11 R7
     449 [-]: LOADN R19 0  
     450 [-]: JUMPIFNOTLE R11 R19 L45
     451 [-]: GETUPVAL R20 6
     452 [-]: FASTCALL1 62 R20 L44
     453 [-]: GETIMPORT R19 20 [nil]
     454 [-]: CALL R19 1 1 
L44: 455 [-]: JUMPIF R19 L45
     456 [-]: GETUPVAL R19 6
     457 [-]: LOADN R21 1  
     458 [-]: NAMECALL R19 R19 K80 [0xBF4030D2]
     459 [-]: CALL R19 2 0 
L45: 460 [-]: GETIMPORT R20 82 [nil]
     461 [-]: FASTCALL1 62 R20 L46
     462 [-]: GETIMPORT R19 20 [nil]
     463 [-]: CALL R19 1 1 
L46: 464 [-]: JUMPIF R19 L47
     465 [-]: GETIMPORT R20 23 [nil]
     466 [-]: GETUPVAL R22 30
     467 [-]: LOADN R23 0  
     468 [-]: NAMECALL R20 R20 K24 [0x0EB34C69]
     469 [-]: CALL R20 3 1 
     470 [-]: SUB R19 R2 R20
     471 [-]: LOADN R20 150
     472 [-]: JUMPIFNOTLT R20 R19 L47
     473 [-]: GETIMPORT R20 34 [nil]
     474 [-]: GETIMPORT R22 82 [nil]
     475 [-]: ADD R21 R22 R7
     476 [-]: SETTABLEKS R21 R20 K81 ["DropshipNextEventTime"]
L47: 477 [-]: GETUPVAL R19 0
     478 [-]: JUMPIFNOT R19 L48
     479 [-]: GETIMPORT R19 62 [nil]
     480 [-]: JUMPIFNOT R19 L48
     481 [-]: RETURN R0 0  
L48: 482 [-]: GETIMPORT R19 28 [nil]
     483 [-]: MOVE R20 R7  
     484 [-]: CALL R19 1 0 
     485 [-]: GETIMPORT R19 23 [nil]
     486 [-]: GETUPVAL R21 8
     487 [-]: NAMECALL R19 R19 K24 [0x0EB34C69]
     488 [-]: CALL R19 2 1 
     489 [-]: MOVE R1 R19  
     490 [-]: GETIMPORT R19 23 [nil]
     491 [-]: GETUPVAL R21 13
     492 [-]: NAMECALL R19 R19 K83 [0xFFDDF768]
     493 [-]: CALL R19 2 1 
     494 [-]: MOVE R2 R19  
     495 [-]: LOADN R19 0  
     496 [-]: JUMPIFNOTLE R19 R2 L50
     497 [-]: GETIMPORT R19 23 [nil]
     498 [-]: GETUPVAL R21 9
     499 [-]: FASTCALL1 7 R2 L49
     500 [-]: MOVE R23 R2  
     501 [-]: GETIMPORT R22 85 [nil]
     502 [-]: CALL R22 1 1 
L49: 503 [-]: NAMECALL R19 R19 K86 [0x751F061D]
     504 [-]: CALL R19 3 0 
L50: 505 [-]: GETIMPORT R20 87 [nil]
     506 [-]: SUB R19 R2 R20
     507 [-]: LOADN R20 180
     508 [-]: JUMPIFNOTLT R20 R19 L51
     509 [-]: GETUPVAL R19 10
     510 [-]: JUMPIF R19 L52
     511 [-]: LOADB R19 1  
     512 [-]: SETUPVAL R19 10
     513 [-]: GETIMPORT R19 23 [nil]
     514 [-]: GETUPVAL R21 11
     515 [-]: LOADN R22 1  
     516 [-]: NAMECALL R19 R19 K86 [0x751F061D]
     517 [-]: CALL R19 3 0 
     518 [-]: JUMP L52
    
L51: 519 [-]: GETUPVAL R19 10
     520 [-]: JUMPIFNOT R19 L52
     521 [-]: LOADB R19 0  
     522 [-]: SETUPVAL R19 10
     523 [-]: GETIMPORT R19 23 [nil]
     524 [-]: GETUPVAL R21 11
     525 [-]: LOADN R22 0  
     526 [-]: NAMECALL R19 R19 K86 [0x751F061D]
     527 [-]: CALL R19 3 0 
L52: 528 [-]: JUMPBACK L13 
L53: 529 [-]: RETURN R0 0  


; Name:            
; Defined at line: 1624
; #Upvalues:       3
; #Parameters:     0
; Is_vararg:       0
; Max Stack Size:  17

       0 [-]: LOADNIL R0   
L 0:   1 [-]: FASTCALL1 62 R0 L1
       2 [-]: MOVE R2 R0   
       3 [-]: GETIMPORT R1 1 [nil]
       4 [-]: CALL R1 1 1  
L 1:   5 [-]: JUMPIFNOT R1 L2
       6 [-]: GETIMPORT R1 3 [nil]
       7 [-]: NAMECALL R1 R1 K4 [0x78298275]
       8 [-]: CALL R1 1 1  
       9 [-]: MOVE R0 R1   
      10 [-]: GETIMPORT R1 6 [nil]
      11 [-]: LOADN R2 0   
      12 [-]: CALL R1 1 0  
      13 [-]: JUMPBACK L0  
L 2:  14 [-]: GETIMPORT R1 3 [nil]
      15 [-]: GETUPVAL R3 0
      16 [-]: NAMECALL R1 R1 K7 [0xC7FCADA9]
      17 [-]: CALL R1 2 1  
      18 [-]: LOADNIL R2   
      19 [-]: LENGTH R3 R1 
      20 [-]: JUMPXEQKN R3 K8 L3 NOT [0]
      21 [-]: LOADNIL R2   
      22 [-]: JUMP L13
    
L 3:  23 [-]: LENGTH R3 R1 
      24 [-]: JUMPXEQKN R3 K9 L4 NOT [1]
      25 [-]: GETTABLEN R2 R1 1
      26 [-]: JUMP L13
    
L 4:  27 [-]: GETIMPORT R3 3 [nil]
      28 [-]: GETUPVAL R5 1
      29 [-]: NAMECALL R3 R3 K7 [0xC7FCADA9]
      30 [-]: CALL R3 2 1  
      31 [-]: NEWTABLE R4 0 0
      32 [-]: LOADN R7 1   
      33 [-]: LENGTH R5 R3 
      34 [-]: LOADN R6 1   
      35 [-]: FORNPREP R5 L7
L 5:  36 [-]: MOVE R9 R4   
      37 [-]: GETTABLE R10 R3 R7
      38 [-]: NAMECALL R10 R10 K10 [0xD1586535]
      39 [-]: CALL R10 1 -1
      40 [-]: FASTCALL 52 L6
      41 [-]: GETIMPORT R8 13 [nil]
      42 [-]: CALL R8 -1 0 
L 6:  43 [-]: FORNLOOP R5 L5
L 7:  44 [-]: LOADN R5 0   
      45 [-]: LOADN R8 1   
      46 [-]: LENGTH R6 R1 
      47 [-]: LOADN R7 1   
      48 [-]: FORNPREP R6 L13
L 8:  49 [-]: LOADN R9 0   
      50 [-]: GETTABLE R10 R1 R8
      51 [-]: NAMECALL R10 R10 K10 [0xD1586535]
      52 [-]: CALL R10 1 1 
      53 [-]: LOADN R13 1  
      54 [-]: LENGTH R11 R4
      55 [-]: LOADN R12 1  
      56 [-]: FORNPREP R11 L10
L 9:  57 [-]: GETIMPORT R14 15 [nil]
      58 [-]: MOVE R15 R10 
      59 [-]: GETTABLE R16 R4 R13
      60 [-]: CALL R14 2 1 
      61 [-]: ADD R9 R9 R14
      62 [-]: FORNLOOP R11 L9
L10:  63 [-]: JUMPXEQKNIL R2 L11
      64 [-]: JUMPIFNOTLT R9 R5 L12
L11:  65 [-]: GETTABLE R2 R1 R8
      66 [-]: MOVE R5 R9   
L12:  67 [-]: FORNLOOP R6 L8
L13:  68 [-]: GETIMPORT R3 17 [nil]
      69 [-]: LOADNIL R4   
      70 [-]: SETTABLEKS R4 R3 K18 ["ExcavationScanner"]
      71 [-]: RETURN R0 0  
      72 [-]: FASTCALL1 62 R2 L14
      73 [-]: MOVE R4 R2   
      74 [-]: GETIMPORT R3 1 [nil]
      75 [-]: CALL R3 1 1  
L14:  76 [-]: JUMPIFNOT R3 L15
      77 [-]: GETIMPORT R3 20 [nil]
      78 [-]: LOADK R4 K21 ["No scanner to enable!"]
      79 [-]: CALL R3 1 0  
      80 [-]: RETURN R0 0  
L15:  81 [-]: GETIMPORT R3 20 [nil]
      82 [-]: LOADK R5 K22 ["SelectedScanner "]
      83 [-]: NAMECALL R6 R2 K23 [0xED4E0128]
      84 [-]: CALL R6 1 1  
      85 [-]: CONCAT R4 R5 R6
      86 [-]: CALL R3 1 0  
      87 [-]: LOADK R5 K24 ["TriggerPort"]
      88 [-]: NAMECALL R3 R2 K25 [0x8EB2112D]
      89 [-]: CALL R3 2 0  
L16:  90 [-]: GETIMPORT R3 26 [nil]
      91 [-]: JUMPXEQKNIL R3 L21 NOT
      92 [-]: GETIMPORT R3 3 [nil]
      93 [-]: GETUPVAL R5 2
      94 [-]: NAMECALL R3 R3 K7 [0xC7FCADA9]
      95 [-]: CALL R3 2 1  
      96 [-]: LOADN R6 1   
      97 [-]: LENGTH R4 R3 
      98 [-]: LOADN R5 1   
      99 [-]: FORNPREP R4 L19
L17: 100 [-]: GETTABLE R7 R3 R6
     101 [-]: NAMECALL R7 R7 K27 [0xD4CC05B4]
     102 [-]: CALL R7 1 1  
     103 [-]: JUMPIFNOT R7 L18
     104 [-]: GETIMPORT R7 17 [nil]
     105 [-]: GETTABLE R8 R3 R6
     106 [-]: SETTABLEKS R8 R7 K18 ["ExcavationScanner"]
     107 [-]: JUMP L19
    
L18: 108 [-]: FORNLOOP R4 L17
L19: 109 [-]: GETIMPORT R4 26 [nil]
     110 [-]: JUMPXEQKNIL R4 L20 NOT
     111 [-]: GETIMPORT R4 6 [nil]
     112 [-]: LOADN R5 1   
     113 [-]: CALL R4 1 0  
L20: 114 [-]: JUMPBACK L16 
L21: 115 [-]: GETIMPORT R3 3 [nil]
     116 [-]: NAMECALL R3 R3 K28 [0x29EF273D]
     117 [-]: CALL R3 1 1  
     118 [-]: NAMECALL R3 R3 K29 [0x66905CB0]
     119 [-]: CALL R3 1 1  
     120 [-]: GETIMPORT R6 26 [nil]
     121 [-]: NAMECALL R4 R3 K30 [0xE2871589]
     122 [-]: CALL R4 2 0  
     123 [-]: GETIMPORT R4 20 [nil]
     124 [-]: LOADK R6 K31 ["SetObjective "]
     125 [-]: GETIMPORT R7 26 [nil]
     126 [-]: NAMECALL R7 R7 K23 [0xED4E0128]
     127 [-]: CALL R7 1 1  
     128 [-]: CONCAT R5 R6 R7
     129 [-]: CALL R4 1 0  
     130 [-]: RETURN R0 0  


; Name:            
; Defined at line: 1705
; #Upvalues:       12
; #Parameters:     0
; Is_vararg:       0
; Max Stack Size:  6

L 0:   0 [-]: GETIMPORT R1 1 [nil]
       1 [-]: FASTCALL1 62 R1 L1
       2 [-]: GETIMPORT R0 3 [nil]
       3 [-]: CALL R0 1 1  
L 1:   4 [-]: JUMPIFNOT R0 L2
       5 [-]: GETIMPORT R0 5 [nil]
       6 [-]: LOADN R1 0   
       7 [-]: CALL R0 1 0  
       8 [-]: JUMPBACK L0  
L 2:   9 [-]: GETIMPORT R0 7 [nil]
      10 [-]: LOADB R1 0   
      11 [-]: SETTABLEKS R1 R0 K8 ["extractionAvailable"]
      12 [-]: GETIMPORT R0 1 [nil]
      13 [-]: NAMECALL R0 R0 K9 [0xEF893AEC]
      14 [-]: CALL R0 1 1  
      15 [-]: GETTABLEKS R2 R0 K10 ["levelOverride"]
      16 [-]: FASTCALL1 62 R2 L3
      17 [-]: GETIMPORT R1 3 [nil]
      18 [-]: CALL R1 1 1  
L 3:  19 [-]: JUMPIF R1 L4 
      20 [-]: GETTABLEKS R1 R0 K11 ["goalId"]
      21 [-]: JUMPXEQKS R1 K12 L5 NOT [""]
L 4:  22 [-]: LOADB R1 0   
      23 [-]: SETUPVAL R1 0
      24 [-]: JUMP L5
     
L 5:  25 [-]: GETIMPORT R1 15 [nil]
      26 [-]: GETIMPORT R2 17 [nil]
      27 [-]: GETTABLEKS R3 R0 K18 ["activeMissionTag"]
      28 [-]: CALL R2 1 1  
      29 [-]: LOADK R3 K19 ["Void"]
      30 [-]: CALL R1 2 1  
      31 [-]: SETUPVAL R1 1
      32 [-]: GETIMPORT R2 15 [nil]
      33 [-]: GETIMPORT R3 17 [nil]
      34 [-]: GETTABLEKS R4 R0 K10 ["levelOverride"]
      35 [-]: NAMECALL R4 R4 K20 [0xED4E0128]
      36 [-]: CALL R4 1 -1 
      37 [-]: CALL R3 -1 1 
      38 [-]: LOADK R4 K21 ["Duviri"]
      39 [-]: CALL R2 2 1  
      40 [-]: JUMPXEQKNIL R2 L6 NOT
      41 [-]: LOADB R1 0 +1
L 6:  42 [-]: LOADB R1 1   
L 7:  43 [-]: SETUPVAL R1 2
      44 [-]: GETTABLEKS R1 R0 K22 ["alertId"]
      45 [-]: JUMPXEQKS R1 K12 L8 NOT [""]
      46 [-]: GETTABLEKS R1 R0 K23 ["invasionId"]
      47 [-]: JUMPXEQKS R1 K12 L8 NOT [""]
      48 [-]: GETTABLEKS R1 R0 K24 ["syndicateTag"]
      49 [-]: NAMECALL R1 R1 K25 [0x56C01834]
      50 [-]: CALL R1 1 1  
      51 [-]: JUMPIF R1 L8 
      52 [-]: GETTABLEKS R1 R0 K26 ["sortieId"]
      53 [-]: JUMPXEQKS R1 K12 L8 NOT [""]
      54 [-]: GETTABLEKS R1 R0 K27 ["nightmare"]
      55 [-]: JUMPIF R1 L8 
      56 [-]: GETTABLEKS R1 R0 K28 ["maxWaveNum"]
      57 [-]: LOADN R2 0   
      58 [-]: JUMPIFLT R2 R1 L8
      59 [-]: GETUPVAL R1 2
      60 [-]: JUMPIFNOT R1 L9
L 8:  61 [-]: LOADB R1 1   
      62 [-]: SETUPVAL R1 3
      63 [-]: LOADN R1 600 
      64 [-]: SETUPVAL R1 4
      65 [-]: LOADN R1 600 
      66 [-]: SETUPVAL R1 5
L 9:  67 [-]: GETTABLEKS R1 R0 K29 ["goalTag"]
      68 [-]: GETIMPORT R2 31 [nil]
      69 [-]: LOADK R3 K32 ["OldWorldSalvage"]
      70 [-]: CALL R2 1 1  
      71 [-]: JUMPIFNOTEQ R1 R2 L10
      72 [-]: GETTABLEKS R1 R0 K33 ["location"]
      73 [-]: GETUPVAL R2 6
      74 [-]: JUMPIFNOTEQ R1 R2 L10
      75 [-]: LOADB R1 1   
      76 [-]: SETUPVAL R1 7
      77 [-]: LOADN R1 10  
      78 [-]: SETUPVAL R1 8
      79 [-]: LOADN R1 60  
      80 [-]: SETUPVAL R1 9
      81 [-]: RETURN R0 0  
L10:  82 [-]: LOADB R1 1   
      83 [-]: GETIMPORT R3 1 [nil]
      84 [-]: NAMECALL R3 R3 K9 [0xEF893AEC]
      85 [-]: CALL R3 1 1  
      86 [-]: GETTABLEKS R2 R3 K34 ["periodicMissionTag"]
      87 [-]: GETUPVAL R4 10
      88 [-]: GETTABLEKS R3 R4 K35 ["ELITE_ALERT_PERIODIC_MISSION_TAG"]
      89 [-]: JUMPIFEQ R2 R3 L12
      90 [-]: GETIMPORT R3 1 [nil]
      91 [-]: NAMECALL R3 R3 K9 [0xEF893AEC]
      92 [-]: CALL R3 1 1  
      93 [-]: GETTABLEKS R2 R3 K34 ["periodicMissionTag"]
      94 [-]: GETUPVAL R4 10
      95 [-]: GETTABLEKS R3 R4 K36 ["ELITE_ALERT_PERIODIC_MISSION_TAG_ALT"]
      96 [-]: JUMPIFEQ R2 R3 L11
      97 [-]: LOADB R1 0 +1
L11:  98 [-]: LOADB R1 1   
L12:  99 [-]: JUMPIFNOT R1 L13
     100 [-]: LOADN R1 140 
     101 [-]: SETUPVAL R1 9
     102 [-]: RETURN R0 0  
L13: 103 [-]: GETUPVAL R1 2
     104 [-]: JUMPIFNOT R1 L14
     105 [-]: LOADN R1 3   
     106 [-]: SETUPVAL R1 11
L14: 107 [-]: RETURN R0 0  


; Name:            
; Defined at line: 1746
; #Upvalues:       18
; #Parameters:     0
; Is_vararg:       0
; Max Stack Size:  4

       0 [-]: GETUPVAL R1 0
       1 [-]: GETTABLEKS R0 R1 K0 [0xDC3B2033]
       2 [-]: CALL R0 0 0  
       3 [-]: GETUPVAL R1 0
       4 [-]: GETTABLEKS R0 R1 K1 [0xF94B7537]
       5 [-]: CALL R0 0 0  
       6 [-]: GETUPVAL R1 0
       7 [-]: GETTABLEKS R0 R1 K2 [0xBD3CE95D]
       8 [-]: CALL R0 0 0  
       9 [-]: GETIMPORT R0 4 [nil]
      10 [-]: NAMECALL R0 R0 K5 [0x18D05D30]
      11 [-]: CALL R0 1 1  
      12 [-]: JUMPIFNOT R0 L1
      13 [-]: GETIMPORT R0 7 [nil]
      14 [-]: LOADK R1 K8 ["duviri excav clearing state"]
      15 [-]: CALL R0 1 0  
      16 [-]: GETIMPORT R0 10 [nil]
      17 [-]: GETUPVAL R2 1
      18 [-]: NAMECALL R0 R0 K11 [0xB9BFD47C]
      19 [-]: CALL R0 2 0  
      20 [-]: GETIMPORT R0 10 [nil]
      21 [-]: GETUPVAL R2 2
      22 [-]: NAMECALL R0 R0 K11 [0xB9BFD47C]
      23 [-]: CALL R0 2 0  
      24 [-]: GETIMPORT R0 10 [nil]
      25 [-]: GETUPVAL R2 3
      26 [-]: NAMECALL R0 R0 K11 [0xB9BFD47C]
      27 [-]: CALL R0 2 0  
      28 [-]: GETIMPORT R0 10 [nil]
      29 [-]: GETUPVAL R2 4
      30 [-]: NAMECALL R0 R0 K11 [0xB9BFD47C]
      31 [-]: CALL R0 2 0  
      32 [-]: GETIMPORT R0 10 [nil]
      33 [-]: GETUPVAL R2 5
      34 [-]: NAMECALL R0 R0 K11 [0xB9BFD47C]
      35 [-]: CALL R0 2 0  
      36 [-]: GETIMPORT R0 10 [nil]
      37 [-]: GETUPVAL R2 6
      38 [-]: NAMECALL R0 R0 K11 [0xB9BFD47C]
      39 [-]: CALL R0 2 0  
      40 [-]: GETIMPORT R0 10 [nil]
      41 [-]: GETUPVAL R2 7
      42 [-]: NAMECALL R0 R0 K11 [0xB9BFD47C]
      43 [-]: CALL R0 2 0  
      44 [-]: GETIMPORT R0 10 [nil]
      45 [-]: GETUPVAL R2 8
      46 [-]: NAMECALL R0 R0 K11 [0xB9BFD47C]
      47 [-]: CALL R0 2 0  
      48 [-]: GETIMPORT R0 10 [nil]
      49 [-]: GETUPVAL R2 9
      50 [-]: NAMECALL R0 R0 K11 [0xB9BFD47C]
      51 [-]: CALL R0 2 0  
      52 [-]: GETIMPORT R0 10 [nil]
      53 [-]: GETUPVAL R2 10
      54 [-]: NAMECALL R0 R0 K11 [0xB9BFD47C]
      55 [-]: CALL R0 2 0  
      56 [-]: GETIMPORT R0 10 [nil]
      57 [-]: GETUPVAL R2 11
      58 [-]: NAMECALL R0 R0 K11 [0xB9BFD47C]
      59 [-]: CALL R0 2 0  
      60 [-]: GETIMPORT R0 10 [nil]
      61 [-]: GETUPVAL R2 12
      62 [-]: NAMECALL R0 R0 K11 [0xB9BFD47C]
      63 [-]: CALL R0 2 0  
      64 [-]: GETIMPORT R0 10 [nil]
      65 [-]: GETUPVAL R2 13
      66 [-]: NAMECALL R0 R0 K11 [0xB9BFD47C]
      67 [-]: CALL R0 2 0  
      68 [-]: GETIMPORT R0 10 [nil]
      69 [-]: GETUPVAL R2 14
      70 [-]: NAMECALL R0 R0 K11 [0xB9BFD47C]
      71 [-]: CALL R0 2 0  
      72 [-]: GETIMPORT R0 10 [nil]
      73 [-]: GETUPVAL R2 15
      74 [-]: NAMECALL R0 R0 K11 [0xB9BFD47C]
      75 [-]: CALL R0 2 0  
      76 [-]: GETIMPORT R0 10 [nil]
      77 [-]: GETUPVAL R2 16
      78 [-]: NAMECALL R0 R0 K11 [0xB9BFD47C]
      79 [-]: CALL R0 2 0  
      80 [-]: GETIMPORT R0 10 [nil]
      81 [-]: GETUPVAL R2 17
      82 [-]: NAMECALL R0 R0 K11 [0xB9BFD47C]
      83 [-]: CALL R0 2 0  
      84 [-]: GETIMPORT R0 14 [nil]
      85 [-]: JUMPIFNOT R0 L0
      86 [-]: GETIMPORT R0 14 [nil]
      87 [-]: CALL R0 0 0  
L 0:  88 [-]: GETIMPORT R0 4 [nil]
      89 [-]: NAMECALL R0 R0 K15 [0x29EF273D]
      90 [-]: CALL R0 1 1  
      91 [-]: NAMECALL R0 R0 K16 [0x66905CB0]
      92 [-]: CALL R0 1 1  
      93 [-]: LOADNIL R3   
      94 [-]: NAMECALL R1 R0 K17 [0xB4DE0035]
      95 [-]: CALL R1 2 0  
L 1:  96 [-]: RETURN R0 0  


; Name:            
; Defined at line: 1781
; #Upvalues:       3
; #Parameters:     0
; Is_vararg:       0
; Max Stack Size:  7

       0 [-]: GETIMPORT R0 1 [nil]
       1 [-]: LOADN R1 5   
       2 [-]: SETTABLEKS R1 R0 K2 ["maxTier"]
       3 [-]: GETUPVAL R1 0
       4 [-]: GETTABLEKS R0 R1 K3 [0x59F914CD]
       5 [-]: GETIMPORT R1 5 [nil]
       6 [-]: CALL R0 1 0  
       7 [-]: GETIMPORT R0 7 [nil]
       8 [-]: GETIMPORT R2 9 [nil]
       9 [-]: LOADK R3 K10 ["BreakableOnPath"]
      10 [-]: CALL R2 1 -1 
      11 [-]: NAMECALL R0 R0 K11 [0xC7FCADA9]
      12 [-]: CALL R0 -1 1 
      13 [-]: LOADN R3 1   
      14 [-]: LENGTH R1 R0 
      15 [-]: LOADN R2 1   
      16 [-]: FORNPREP R1 L1
L 0:  17 [-]: GETTABLE R4 R0 R3
      18 [-]: LOADK R6 K12 ["Destroy"]
      19 [-]: NAMECALL R4 R4 K13 [0x8EB2112D]
      20 [-]: CALL R4 2 0  
      21 [-]: FORNLOOP R1 L0
L 1:  22 [-]: GETUPVAL R1 1
      23 [-]: JUMPIFNOT R1 L2
      24 [-]: GETUPVAL R2 0
      25 [-]: GETTABLEKS R1 R2 K14 [0x9742B85B]
      26 [-]: GETIMPORT R2 16 [nil]
      27 [-]: GETIMPORT R3 9 [nil]
      28 [-]: LOADK R4 K17 ["MissionIntro"]
      29 [-]: CALL R3 1 -1 
      30 [-]: CALL R1 -1 0 
L 2:  31 [-]: GETIMPORT R1 19 [nil]
      32 [-]: GETUPVAL R3 2
      33 [-]: LOADN R4 2   
      34 [-]: NAMECALL R1 R1 K20 [0x751F061D]
      35 [-]: CALL R1 3 0  
      36 [-]: RETURN R0 0  


; Name:            
; Defined at line: 1808
; #Upvalues:       16
; #Parameters:     1
; Is_vararg:       0
; Max Stack Size:  12

       0 [-]: SETUPVAL R0 0
       1 [-]: GETUPVAL R1 1
       2 [-]: CALL R1 0 0  
       3 [-]: GETIMPORT R1 1 [nil]
       4 [-]: GETIMPORT R2 3 [nil]
       5 [-]: NAMECALL R2 R2 K4 [0x9DDA54DC]
       6 [-]: CALL R2 1 1  
       7 [-]: SETTABLEKS R2 R1 K5 ["gSurvivalRewardSeed"]
       8 [-]: GETIMPORT R1 3 [nil]
       9 [-]: GETUPVAL R3 2
      10 [-]: LOADN R4 0   
      11 [-]: NAMECALL R1 R1 K6 [0x0EB34C69]
      12 [-]: CALL R1 3 1  
      13 [-]: LOADN R2 0   
      14 [-]: JUMPIFNOTLT R2 R1 L0
      15 [-]: GETIMPORT R2 8 [nil]
      16 [-]: CALL R2 0 1  
      17 [-]: GETIMPORT R3 10 [nil]
      18 [-]: GETIMPORT R4 11 [nil]
      19 [-]: MOVE R5 R1   
      20 [-]: CALL R3 2 0  
      21 [-]: GETIMPORT R3 1 [nil]
      22 [-]: GETIMPORT R4 8 [nil]
      23 [-]: CALL R4 0 1  
      24 [-]: SETTABLEKS R4 R3 K5 ["gSurvivalRewardSeed"]
      25 [-]: GETIMPORT R3 13 [nil]
      26 [-]: MOVE R4 R2   
      27 [-]: CALL R3 1 0  
L 0:  28 [-]: GETUPVAL R3 3
      29 [-]: JUMPIFNOT R3 L3
      30 [-]: GETIMPORT R2 15 [nil]
      31 [-]: NAMECALL R2 R2 K16 [0x18D05D30]
      32 [-]: CALL R2 1 1  
      33 [-]: JUMPIFNOT R2 L4
      34 [-]: GETIMPORT R3 3 [nil]
      35 [-]: GETUPVAL R5 4
      36 [-]: LOADN R6 0   
      37 [-]: NAMECALL R3 R3 K6 [0x0EB34C69]
      38 [-]: CALL R3 3 1  
      39 [-]: JUMPXEQKN R3 K17 L1 [1]
      40 [-]: LOADB R2 0 +1
L 1:  41 [-]: LOADB R2 1   
L 2:  42 [-]: JUMP L4
     
L 3:  43 [-]: GETIMPORT R2 19 [nil]
      44 [-]: JUMP L4
     
L 4:  45 [-]: JUMPIFNOT R2 L16
      46 [-]: GETIMPORT R2 3 [nil]
      47 [-]: GETUPVAL R4 5
      48 [-]: LOADN R5 0   
      49 [-]: NAMECALL R2 R2 K6 [0x0EB34C69]
      50 [-]: CALL R2 3 1  
      51 [-]: JUMPXEQKN R2 K20 L9 [0]
      52 [-]: GETIMPORT R3 22 [nil]
      53 [-]: GETIMPORT R5 24 [nil]
      54 [-]: NAMECALL R3 R3 K25 [0xBCFB64AB]
      55 [-]: CALL R3 2 1  
L 5:  56 [-]: FASTCALL1 62 R3 L6
      57 [-]: MOVE R5 R3   
      58 [-]: GETIMPORT R4 27 [nil]
      59 [-]: CALL R4 1 1  
L 6:  60 [-]: JUMPIF R4 L7 
      61 [-]: GETIMPORT R4 29 [nil]
      62 [-]: LOADN R5 0   
      63 [-]: CALL R4 1 0  
      64 [-]: JUMPBACK L5  
L 7:  65 [-]: GETIMPORT R4 3 [nil]
      66 [-]: GETUPVAL R6 6
      67 [-]: LOADN R7 0   
      68 [-]: NAMECALL R4 R4 K6 [0x0EB34C69]
      69 [-]: CALL R4 3 1  
      70 [-]: GETUPVAL R5 7
      71 [-]: DIVK R7 R4 K30 [200]
      72 [-]: FASTCALL1 12 R7 L8
      73 [-]: GETIMPORT R6 33 [nil]
      74 [-]: CALL R6 1 1  
L 8:  75 [-]: MOVE R7 R2   
      76 [-]: CALL R5 2 0  
L 9:  77 [-]: GETIMPORT R4 3 [nil]
      78 [-]: GETUPVAL R6 8
      79 [-]: LOADN R7 0   
      80 [-]: NAMECALL R4 R4 K6 [0x0EB34C69]
      81 [-]: CALL R4 3 1  
      82 [-]: JUMPXEQKN R4 K17 L10 [1]
      83 [-]: LOADB R3 0 +1
L10:  84 [-]: LOADB R3 1   
L11:  85 [-]: GETIMPORT R5 3 [nil]
      86 [-]: GETUPVAL R7 9
      87 [-]: LOADN R8 0   
      88 [-]: NAMECALL R5 R5 K6 [0x0EB34C69]
      89 [-]: CALL R5 3 1  
      90 [-]: JUMPXEQKN R5 K34 L12 [2]
      91 [-]: LOADB R4 0 +1
L12:  92 [-]: LOADB R4 1   
L13:  93 [-]: GETUPVAL R5 3
      94 [-]: JUMPIFNOT R5 L14
      95 [-]: JUMPIF R3 L14
      96 [-]: JUMPIF R4 L14
      97 [-]: GETUPVAL R5 10
      98 [-]: CALL R5 0 0  
L14:  99 [-]: GETUPVAL R5 11
     100 [-]: CALL R5 0 0  
     101 [-]: GETUPVAL R5 3
     102 [-]: JUMPIFNOT R5 L15
     103 [-]: GETUPVAL R5 12
     104 [-]: CALL R5 0 0  
L15: 105 [-]: RETURN R0 0  
L16: 106 [-]: GETIMPORT R2 15 [nil]
     107 [-]: GETUPVAL R4 13
     108 [-]: NAMECALL R2 R2 K35 [0xC7FCADA9]
     109 [-]: CALL R2 2 1  
     110 [-]: GETIMPORT R3 15 [nil]
     111 [-]: GETUPVAL R5 14
     112 [-]: NAMECALL R3 R3 K35 [0xC7FCADA9]
     113 [-]: CALL R3 2 1  
     114 [-]: LOADN R6 1   
     115 [-]: LENGTH R4 R2 
     116 [-]: LOADN R5 1   
     117 [-]: FORNPREP R4 L18
L17: 118 [-]: GETTABLE R7 R2 R6
     119 [-]: GETIMPORT R9 37 [nil]
     120 [-]: LOADB R10 0  
     121 [-]: LOADB R11 0  
     122 [-]: NAMECALL R7 R7 K38 [0x2970F52F]
     123 [-]: CALL R7 4 0  
     124 [-]: FORNLOOP R4 L17
L18: 125 [-]: LOADN R6 1   
     126 [-]: LENGTH R4 R3 
     127 [-]: LOADN R5 1   
     128 [-]: FORNPREP R4 L20
L19: 129 [-]: GETTABLE R7 R3 R6
     130 [-]: GETIMPORT R9 40 [nil]
     131 [-]: LOADB R10 0  
     132 [-]: LOADB R11 0  
     133 [-]: NAMECALL R7 R7 K38 [0x2970F52F]
     134 [-]: CALL R7 4 0  
     135 [-]: FORNLOOP R4 L19
L20: 136 [-]: GETIMPORT R4 15 [nil]
     137 [-]: NAMECALL R4 R4 K16 [0x18D05D30]
     138 [-]: CALL R4 1 1  
     139 [-]: JUMPIFNOT R4 L21
     140 [-]: GETUPVAL R4 10
     141 [-]: CALL R4 0 0  
     142 [-]: GETUPVAL R4 11
     143 [-]: CALL R4 0 0  
     144 [-]: GETUPVAL R4 3
     145 [-]: JUMPIFNOT R4 L23
     146 [-]: GETUPVAL R4 12
     147 [-]: CALL R4 0 0  
     148 [-]: RETURN R0 0  
L21: 149 [-]: GETUPVAL R4 15
     150 [-]: CALL R4 0 0  
     151 [-]: GETIMPORT R4 19 [nil]
     152 [-]: JUMPIFNOT R4 L22
     153 [-]: GETIMPORT R4 42 [nil]
     154 [-]: LOADK R5 K43 ["Bailing on Excavation because I am now the host!"]
     155 [-]: CALL R4 1 0  
     156 [-]: RETURN R0 0  
L22: 157 [-]: GETUPVAL R4 3
     158 [-]: JUMPIFNOT R4 L23
     159 [-]: GETUPVAL R4 12
     160 [-]: CALL R4 0 0  
L23: 161 [-]: RETURN R0 0  


; Name:            
; Defined at line: 1883
; #Upvalues:       22
; #Parameters:     1
; Is_vararg:       0
; Max Stack Size:  43

       0 [-]: SETUPVAL R0 0
       1 [-]: GETUPVAL R1 1
       2 [-]: CALL R1 0 0  
       3 [-]: GETIMPORT R1 1 [nil]
L 0:   4 [-]: FASTCALL1 62 R1 L1
       5 [-]: MOVE R3 R1   
       6 [-]: GETIMPORT R2 3 [nil]
       7 [-]: CALL R2 1 1  
L 1:   8 [-]: JUMPIFNOT R2 L2
       9 [-]: GETIMPORT R1 1 [nil]
      10 [-]: GETIMPORT R2 5 [nil]
      11 [-]: LOADK R3 K6 [0.10000000000000001]
      12 [-]: CALL R2 1 0  
      13 [-]: JUMPBACK L0  
L 2:  14 [-]: GETUPVAL R2 2
      15 [-]: JUMPIFNOT R2 L6
      16 [-]: GETIMPORT R2 8 [nil]
      17 [-]: NAMECALL R2 R2 K9 [0x78298275]
      18 [-]: CALL R2 1 1  
L 3:  19 [-]: FASTCALL1 62 R2 L4
      20 [-]: MOVE R4 R2   
      21 [-]: GETIMPORT R3 3 [nil]
      22 [-]: CALL R3 1 1  
L 4:  23 [-]: JUMPIF R3 L5 
      24 [-]: GETUPVAL R5 3
      25 [-]: NAMECALL R3 R2 K10 [0xF2DEAF69]
      26 [-]: CALL R3 2 1  
      27 [-]: JUMPIFNOT R3 L6
L 5:  28 [-]: GETIMPORT R3 5 [nil]
      29 [-]: LOADN R4 0   
      30 [-]: CALL R3 1 0  
      31 [-]: GETIMPORT R3 8 [nil]
      32 [-]: NAMECALL R3 R3 K9 [0x78298275]
      33 [-]: CALL R3 1 1  
      34 [-]: MOVE R2 R3   
      35 [-]: JUMPBACK L3  
L 6:  36 [-]: FASTCALL1 62 R1 L7
      37 [-]: MOVE R3 R1   
      38 [-]: GETIMPORT R2 3 [nil]
      39 [-]: CALL R2 1 1  
L 7:  40 [-]: JUMPIFNOT R2 L8
      41 [-]: RETURN R0 0  
L 8:  42 [-]: NAMECALL R2 R1 K11 [0x33307F92]
      43 [-]: CALL R2 1 1  
L 9:  44 [-]: FASTCALL1 62 R2 L10
      45 [-]: MOVE R4 R2   
      46 [-]: GETIMPORT R3 3 [nil]
      47 [-]: CALL R3 1 1  
L10:  48 [-]: JUMPIFNOT R3 L13
      49 [-]: FASTCALL1 62 R1 L11
      50 [-]: MOVE R4 R1   
      51 [-]: GETIMPORT R3 3 [nil]
      52 [-]: CALL R3 1 1  
L11:  53 [-]: JUMPIFNOT R3 L12
      54 [-]: RETURN R0 0  
L12:  55 [-]: NAMECALL R3 R1 K11 [0x33307F92]
      56 [-]: CALL R3 1 1  
      57 [-]: MOVE R2 R3   
      58 [-]: GETIMPORT R3 5 [nil]
      59 [-]: LOADK R4 K6 [0.10000000000000001]
      60 [-]: CALL R3 1 0  
      61 [-]: JUMPBACK L9  
L13:  62 [-]: LOADB R3 0   
      63 [-]: LOADK R6 K12 ["/Lotus/Language/Game/ExcavatorObject"]
      64 [-]: LOADB R7 0   
      65 [-]: NAMECALL R4 R2 K13 [0x42B04007]
      66 [-]: CALL R4 3 1  
      67 [-]: NEWTABLE R5 0 6
      68 [-]: LOADK R6 K14 ["<MISSION_MARKER_A>"]
      69 [-]: LOADK R7 K15 ["<MISSION_MARKER_B>"]
      70 [-]: LOADK R8 K16 ["<MISSION_MARKER_C>"]
      71 [-]: LOADK R9 K17 ["<MISSION_MARKER_D>"]
      72 [-]: LOADK R10 K18 ["<MISSION_MARKER_E>"]
      73 [-]: LOADK R11 K19 ["<MISSION_MARKER_F>"]
      74 [-]: SETLIST R5 R6 6 [1]
      75 [-]: GETIMPORT R6 21 [nil]
      76 [-]: MOVE R7 R5   
      77 [-]: CALL R6 1 3  
      78 [-]: FORGPREP_INEXT R6 L15
L14:  79 [-]: MOVE R17 R10 
      80 [-]: LOADB R18 1  
      81 [-]: NAMECALL R15 R2 K13 [0x42B04007]
      82 [-]: CALL R15 3 1 
      83 [-]: MOVE R12 R15 
      84 [-]: LOADK R13 K22 [" "]
      85 [-]: MOVE R14 R4  
      86 [-]: CONCAT R11 R12 R14
      87 [-]: SETTABLE R11 R5 R9
L15:  88 [-]: FORGLOOP R6 L14 2 [inext]
      89 [-]: LENGTH R6 R5 
      90 [-]: LOADN R7 500 
      91 [-]: GETIMPORT R8 1 [nil]
      92 [-]: NAMECALL R8 R8 K23 [0xEF893AEC]
      93 [-]: CALL R8 1 1  
      94 [-]: GETUPVAL R9 4
      95 [-]: JUMPIF R9 L16
      96 [-]: GETTABLEKS R9 R8 K24 ["maxWaveNum"]
L16:  97 [-]: LOADN R10 0  
      98 [-]: JUMPIFNOTLT R10 R9 L17
      99 [-]: GETUPVAL R10 5
     100 [-]: MUL R7 R9 R10
L17: 101 [-]: LOADB R10 1  
     102 [-]: GETIMPORT R12 1 [nil]
     103 [-]: NAMECALL R12 R12 K23 [0xEF893AEC]
     104 [-]: CALL R12 1 1 
     105 [-]: GETTABLEKS R11 R12 K25 ["periodicMissionTag"]
     106 [-]: GETUPVAL R13 6
     107 [-]: GETTABLEKS R12 R13 K26 ["ELITE_ALERT_PERIODIC_MISSION_TAG"]
     108 [-]: JUMPIFEQ R11 R12 L19
     109 [-]: GETIMPORT R12 1 [nil]
     110 [-]: NAMECALL R12 R12 K23 [0xEF893AEC]
     111 [-]: CALL R12 1 1 
     112 [-]: GETTABLEKS R11 R12 K25 ["periodicMissionTag"]
     113 [-]: GETUPVAL R13 6
     114 [-]: GETTABLEKS R12 R13 K27 ["ELITE_ALERT_PERIODIC_MISSION_TAG_ALT"]
     115 [-]: JUMPIFEQ R11 R12 L18
     116 [-]: LOADB R10 0 +1
L18: 117 [-]: LOADB R10 1  
L19: 118 [-]: JUMPIFNOT R10 L20
     119 [-]: MULK R7 R7 K28 [2]
L20: 120 [-]: GETUPVAL R11 7
     121 [-]: GETTABLEKS R10 R11 K29 [0x06D055F9]
     122 [-]: GETUPVAL R11 8
     123 [-]: LOADK R12 K30 ["/Lotus/Language/Game/OldWorldCompletedExcavations"]
     124 [-]: LOADK R13 K31 ["/Lotus/Language/Game/ExcavationsRemaining"]
     125 [-]: CALL R10 3 1 
     126 [-]: GETUPVAL R14 7
     127 [-]: GETTABLEKS R13 R14 K29 [0x06D055F9]
     128 [-]: GETUPVAL R14 9
     129 [-]: MOVE R15 R10 
     130 [-]: LOADK R16 K32 ["/Lotus/Language/Game/CompletedExcavations"]
     131 [-]: CALL R13 3 1 
     132 [-]: LOADB R14 1  
     133 [-]: NAMECALL R11 R2 K13 [0x42B04007]
     134 [-]: CALL R11 3 1 
     135 [-]: LOADK R14 K33 ["/Lotus/Language/Objectives/ExcavPowerFull"]
     136 [-]: LOADB R15 1  
     137 [-]: NAMECALL R12 R2 K13 [0x42B04007]
     138 [-]: CALL R12 3 1 
     139 [-]: LOADK R14 K34 ["0% "]
     140 [-]: LOADK R17 K35 ["/Lotus/Language/Game/ExcavationHalted"]
     141 [-]: LOADB R18 1  
     142 [-]: NAMECALL R15 R2 K13 [0x42B04007]
     143 [-]: CALL R15 3 1 
     144 [-]: CONCAT R13 R14 R15
     145 [-]: LOADNIL R14  
     146 [-]: GETIMPORT R15 1 [nil]
     147 [-]: GETUPVAL R17 10
     148 [-]: LOADN R18 1  
     149 [-]: NAMECALL R15 R15 K36 [0x0EB34C69]
     150 [-]: CALL R15 3 1 
L21: 151 [-]: GETIMPORT R16 8 [nil]
     152 [-]: NAMECALL R16 R16 K37 [0x18D05D30]
     153 [-]: CALL R16 1 1 
     154 [-]: JUMPIF R16 L22
     155 [-]: JUMPXEQKN R15 K38 L22 NOT [1]
     156 [-]: GETIMPORT R16 5 [nil]
     157 [-]: LOADK R17 K6 [0.10000000000000001]
     158 [-]: CALL R16 1 0 
     159 [-]: GETIMPORT R16 1 [nil]
     160 [-]: GETUPVAL R18 10
     161 [-]: LOADN R19 1  
     162 [-]: NAMECALL R16 R16 K36 [0x0EB34C69]
     163 [-]: CALL R16 3 1 
     164 [-]: MOVE R15 R16 
     165 [-]: JUMPBACK L21 
L22: 166 [-]: LENGTH R16 R14
     167 [-]: JUMPIFNOTLT R16 R15 L24
     168 [-]: GETIMPORT R16 8 [nil]
     169 [-]: GETUPVAL R18 11
     170 [-]: NAMECALL R16 R16 K39 [0xC7FCADA9]
     171 [-]: CALL R16 2 1 
     172 [-]: MOVE R14 R16 
     173 [-]: GETUPVAL R16 2
     174 [-]: JUMPIFNOT R16 L23
     175 [-]: GETIMPORT R16 42 [nil]
     176 [-]: JUMPIFNOT R16 L23
     177 [-]: GETIMPORT R16 42 [nil]
     178 [-]: MOVE R17 R14 
     179 [-]: CALL R16 1 1 
     180 [-]: MOVE R14 R16 
L23: 181 [-]: GETIMPORT R16 5 [nil]
     182 [-]: LOADK R17 K6 [0.10000000000000001]
     183 [-]: CALL R16 1 0 
     184 [-]: JUMPBACK L22 
L24: 185 [-]: GETIMPORT R16 8 [nil]
     186 [-]: NAMECALL R16 R16 K37 [0x18D05D30]
     187 [-]: CALL R16 1 1 
     188 [-]: JUMPIFNOT R16 L25
     189 [-]: GETIMPORT R16 1 [nil]
     190 [-]: GETUPVAL R18 10
     191 [-]: LENGTH R19 R14
     192 [-]: NAMECALL R16 R16 K43 [0x751F061D]
     193 [-]: CALL R16 3 0 
L25: 194 [-]: GETIMPORT R16 45 [nil]
     195 [-]: LOADK R18 K46 ["Num excav states found: "]
     196 [-]: LENGTH R19 R14
     197 [-]: CONCAT R17 R18 R19
     198 [-]: CALL R16 1 0 
     199 [-]: LOADNIL R16  
     200 [-]: GETIMPORT R17 1 [nil]
     201 [-]: GETUPVAL R19 12
     202 [-]: NAMECALL R17 R17 K36 [0x0EB34C69]
     203 [-]: CALL R17 2 1 
     204 [-]: GETIMPORT R18 45 [nil]
     205 [-]: LOADK R20 K47 ["HUD: state="]
     206 [-]: GETIMPORT R21 49 [nil]
     207 [-]: MOVE R22 R17 
     208 [-]: CALL R21 1 1 
     209 [-]: CONCAT R19 R20 R21
     210 [-]: CALL R18 1 0 
L26: 211 [-]: FASTCALL1 62 R2 L27
     212 [-]: MOVE R19 R2  
     213 [-]: GETIMPORT R18 3 [nil]
     214 [-]: CALL R18 1 1 
L27: 215 [-]: JUMPIFNOT R18 L30
     216 [-]: FASTCALL1 62 R1 L28
     217 [-]: MOVE R19 R1  
     218 [-]: GETIMPORT R18 3 [nil]
     219 [-]: CALL R18 1 1 
L28: 220 [-]: JUMPIFNOT R18 L29
     221 [-]: RETURN R0 0  
L29: 222 [-]: NAMECALL R18 R1 K11 [0x33307F92]
     223 [-]: CALL R18 1 1 
     224 [-]: MOVE R2 R18  
     225 [-]: GETIMPORT R18 5 [nil]
     226 [-]: LOADK R19 K6 [0.10000000000000001]
     227 [-]: CALL R18 1 0 
     228 [-]: JUMPBACK L26 
L30: 229 [-]: LOADK R18 K50 ["<p><font face=\"Noto Sans\">"]
     230 [-]: MOVE R19 R11 
     231 [-]: LOADK R20 K51 ["</font></p><p><font face=\"Noto Sans\" size=\"24\"><b> %s</b></font></p> "]
     232 [-]: CONCAT R11 R18 R20
     233 [-]: LOADK R18 K52 ["<p><font face=\"Noto Sans\"><b>%s</b> </font>"]
     234 [-]: GETIMPORT R19 55 [nil]
     235 [-]: LOADK R20 K56 ["<Color%u>"]
     236 [-]: LOADN R21 38 
     237 [-]: CALL R19 2 1 
     238 [-]: MOVE R20 R18 
     239 [-]: LOADK R21 K57 ["<font color=\""]
     240 [-]: GETIMPORT R26 55 [nil]
     241 [-]: LOADK R27 K56 ["<Color%u>"]
     242 [-]: LOADN R28 49 
     243 [-]: CALL R26 2 1 
     244 [-]: MOVE R22 R26 
     245 [-]: LOADK R23 K58 ["\"><b> %s</b></font><font color=\""]
     246 [-]: GETIMPORT R26 55 [nil]
     247 [-]: LOADK R27 K56 ["<Color%u>"]
     248 [-]: LOADN R28 20 
     249 [-]: CALL R26 2 1 
     250 [-]: MOVE R24 R26 
     251 [-]: LOADK R25 K59 ["\"><b> %s</b></font>"]
     252 [-]: CONCAT R18 R20 R25
     253 [-]: MOVE R20 R18 
     254 [-]: LOADK R21 K57 ["<font color=\""]
     255 [-]: MOVE R22 R19 
     256 [-]: LOADK R23 K60 ["\"><br>      "]
     257 [-]: LOADK R30 K61 ["/Lotus/Language/Game/ExcavationTime"]
     258 [-]: LOADB R31 1  
     259 [-]: NAMECALL R28 R2 K13 [0x42B04007]
     260 [-]: CALL R28 3 1 
     261 [-]: MOVE R24 R28 
     262 [-]: LOADK R25 K62 ["</font><font color=\""]
     263 [-]: MOVE R26 R19 
     264 [-]: LOADK R27 K59 ["\"><b> %s</b></font>"]
     265 [-]: CONCAT R18 R20 R27
     266 [-]: MOVE R20 R18 
     267 [-]: LOADK R21 K57 ["<font color=\""]
     268 [-]: MOVE R22 R19 
     269 [-]: LOADK R23 K63 ["\">  "]
     270 [-]: LOADK R28 K64 ["/Lotus/Language/Game/ExcavationPower"]
     271 [-]: LOADB R29 1  
     272 [-]: NAMECALL R26 R2 K13 [0x42B04007]
     273 [-]: CALL R26 3 1 
     274 [-]: MOVE R24 R26 
     275 [-]: LOADK R25 K65 ["</font>%s"]
     276 [-]: CONCAT R18 R20 R25
     277 [-]: MOVE R20 R18 
     278 [-]: LOADK R21 K66 ["</p>"]
     279 [-]: CONCAT R18 R20 R21
     280 [-]: GETUPVAL R20 13
     281 [-]: JUMPIFNOT R20 L31
L31: 282 [-]: GETUPVAL R20 13
     283 [-]: JUMPIFNOT R20 L32
     284 [-]: GETUPVAL R21 14
     285 [-]: GETTABLEKS R20 R21 K67 [0xEA753E99]
     286 [-]: LOADK R21 K68 ["/Lotus/Language/Objectives/ExcavNextRelicTitle"]
     287 [-]: LOADN R22 0  
     288 [-]: LOADN R23 200
     289 [-]: LOADNIL R24  
     290 [-]: LOADB R25 0  
     291 [-]: LOADK R26 K69 ["/Lotus/Language/Objectives/ExcavNextRelicCryotic"]
     292 [-]: CALL R20 6 0 
     293 [-]: JUMP L34
    
L32: 294 [-]: GETUPVAL R20 9
     295 [-]: JUMPIFNOT R20 L33
     296 [-]: GETUPVAL R21 14
     297 [-]: GETTABLEKS R20 R21 K67 [0xEA753E99]
     298 [-]: LOADK R21 K32 ["/Lotus/Language/Game/CompletedExcavations"]
     299 [-]: LOADN R22 0  
     300 [-]: MOVE R23 R7  
     301 [-]: CALL R20 3 0 
     302 [-]: JUMP L34
    
L33: 303 [-]: GETUPVAL R21 14
     304 [-]: GETTABLEKS R20 R21 K70 [0x118E5C26]
     305 [-]: LOADK R21 K71 ["/Lotus/Language/Objectives/ExcavDigsComplete"]
     306 [-]: LOADN R22 0  
     307 [-]: LOADK R23 K72 [": 0"]
     308 [-]: LOADN R24 1  
     309 [-]: CALL R20 4 0 
L34: 310 [-]: GETUPVAL R20 8
     311 [-]: JUMPIFNOT R20 L35
     312 [-]: JUMP L35
    
L35: 313 [-]: NEWTABLE R20 0 0
     314 [-]: GETUPVAL R21 8
     315 [-]: JUMPIF R21 L36
L36: 316 [-]: JUMPXEQKN R17 K73 L39 NOT [0]
     317 [-]: FASTCALL1 62 R1 L37
     318 [-]: MOVE R22 R1  
     319 [-]: GETIMPORT R21 3 [nil]
     320 [-]: CALL R21 1 1 
L37: 321 [-]: JUMPIFNOT R21 L38
     322 [-]: RETURN R0 0  
L38: 323 [-]: GETUPVAL R23 12
     324 [-]: NAMECALL R21 R1 K36 [0x0EB34C69]
     325 [-]: CALL R21 2 1 
     326 [-]: MOVE R17 R21 
     327 [-]: GETIMPORT R21 5 [nil]
     328 [-]: LOADN R22 0  
     329 [-]: CALL R21 1 0 
     330 [-]: JUMPBACK L36 
L39: 331 [-]: GETUPVAL R21 8
     332 [-]: JUMPIF R21 L40
L40: 333 [-]: JUMPXEQKN R17 K38 L43 NOT [1]
     334 [-]: FASTCALL1 62 R1 L41
     335 [-]: MOVE R22 R1  
     336 [-]: GETIMPORT R21 3 [nil]
     337 [-]: CALL R21 1 1 
L41: 338 [-]: JUMPIFNOT R21 L42
     339 [-]: RETURN R0 0  
L42: 340 [-]: GETUPVAL R23 12
     341 [-]: NAMECALL R21 R1 K36 [0x0EB34C69]
     342 [-]: CALL R21 2 1 
     343 [-]: MOVE R17 R21 
     344 [-]: GETIMPORT R21 5 [nil]
     345 [-]: LOADN R22 0  
     346 [-]: CALL R21 1 0 
     347 [-]: JUMPBACK L40 
L43: 348 [-]: GETUPVAL R21 8
     349 [-]: JUMPIF R21 L44
     350 [-]: GETUPVAL R22 14
     351 [-]: GETTABLEKS R21 R22 K74 [0xA1DF01D6]
     352 [-]: LOADK R22 K75 ["/Lotus/Language/Game/ExcavationLocateAndProtect"]
     353 [-]: LOADN R23 1  
     354 [-]: CALL R21 2 0 
L44: 355 [-]: FASTCALL1 62 R2 L45
     356 [-]: MOVE R22 R2  
     357 [-]: GETIMPORT R21 3 [nil]
     358 [-]: CALL R21 1 1 
L45: 359 [-]: JUMPIFNOT R21 L48
     360 [-]: JUMPXEQKN R17 K28 L48 NOT [2]
     361 [-]: FASTCALL1 62 R1 L46
     362 [-]: MOVE R22 R1  
     363 [-]: GETIMPORT R21 3 [nil]
     364 [-]: CALL R21 1 1 
L46: 365 [-]: JUMPIFNOT R21 L47
     366 [-]: RETURN R0 0  
L47: 367 [-]: NAMECALL R21 R1 K11 [0x33307F92]
     368 [-]: CALL R21 1 1 
     369 [-]: MOVE R2 R21  
     370 [-]: GETUPVAL R23 12
     371 [-]: NAMECALL R21 R1 K36 [0x0EB34C69]
     372 [-]: CALL R21 2 1 
     373 [-]: MOVE R17 R21 
     374 [-]: GETIMPORT R21 5 [nil]
     375 [-]: LOADN R22 0  
     376 [-]: CALL R21 1 0 
     377 [-]: JUMPBACK L44 
L48: 378 [-]: GETUPVAL R21 2
     379 [-]: JUMPIF R21 L49
     380 [-]: GETIMPORT R21 8 [nil]
     381 [-]: GETUPVAL R23 16
     382 [-]: NAMECALL R21 R21 K76 [0x46A0EBF5]
     383 [-]: CALL R21 2 1 
     384 [-]: SETUPVAL R21 15
L49: 385 [-]: JUMPXEQKN R17 K28 L88 NOT [2]
     386 [-]: FASTCALL1 62 R1 L50
     387 [-]: MOVE R22 R1  
     388 [-]: GETIMPORT R21 3 [nil]
     389 [-]: CALL R21 1 1 
L50: 390 [-]: JUMPIFNOT R21 L51
     391 [-]: RETURN R0 0  
L51: 392 [-]: GETUPVAL R23 12
     393 [-]: NAMECALL R21 R1 K36 [0x0EB34C69]
     394 [-]: CALL R21 2 1 
     395 [-]: MOVE R17 R21 
     396 [-]: GETUPVAL R23 17
     397 [-]: LOADN R24 0  
     398 [-]: NAMECALL R21 R1 K36 [0x0EB34C69]
     399 [-]: CALL R21 3 1 
     400 [-]: JUMPIFEQ R16 R21 L57
     401 [-]: MOVE R16 R21 
     402 [-]: GETUPVAL R22 9
     403 [-]: JUMPIFNOT R22 L52
     404 [-]: GETUPVAL R22 8
     405 [-]: JUMPIF R22 L52
     406 [-]: GETUPVAL R23 14
     407 [-]: GETTABLEKS R22 R23 K77 [0xF3928F38]
     408 [-]: MOVE R23 R21 
     409 [-]: MOVE R24 R7  
     410 [-]: CALL R22 2 0 
     411 [-]: JUMP L57
    
L52: 412 [-]: GETUPVAL R22 13
     413 [-]: JUMPIFNOT R22 L53
     414 [-]: GETIMPORT R22 80 [nil]
     415 [-]: MOVE R23 R21 
     416 [-]: LOADN R24 200
     417 [-]: CALL R22 2 1 
     418 [-]: GETUPVAL R24 14
     419 [-]: GETTABLEKS R23 R24 K77 [0xF3928F38]
     420 [-]: MOVE R24 R22 
     421 [-]: LOADN R25 200
     422 [-]: LOADK R26 K69 ["/Lotus/Language/Objectives/ExcavNextRelicCryotic"]
     423 [-]: CALL R23 3 0 
     424 [-]: JUMP L57
    
L53: 425 [-]: GETUPVAL R22 8
     426 [-]: JUMPIFNOT R22 L54
     427 [-]: GETUPVAL R22 8
     428 [-]: JUMPIFNOT R22 L57
     429 [-]: LOADN R22 0  
     430 [-]: JUMPIFNOTLT R22 R21 L57
L54: 431 [-]: GETUPVAL R25 7
     432 [-]: GETTABLEKS R24 R25 K29 [0x06D055F9]
     433 [-]: LOADB R25 1  
     434 [-]: GETIMPORT R27 1 [nil]
     435 [-]: NAMECALL R27 R27 K23 [0xEF893AEC]
     436 [-]: CALL R27 1 1 
     437 [-]: GETTABLEKS R26 R27 K25 ["periodicMissionTag"]
     438 [-]: GETUPVAL R28 6
     439 [-]: GETTABLEKS R27 R28 K26 ["ELITE_ALERT_PERIODIC_MISSION_TAG"]
     440 [-]: JUMPIFEQ R26 R27 L56
     441 [-]: GETIMPORT R27 1 [nil]
     442 [-]: NAMECALL R27 R27 K23 [0xEF893AEC]
     443 [-]: CALL R27 1 1 
     444 [-]: GETTABLEKS R26 R27 K25 ["periodicMissionTag"]
     445 [-]: GETUPVAL R28 6
     446 [-]: GETTABLEKS R27 R28 K27 ["ELITE_ALERT_PERIODIC_MISSION_TAG_ALT"]
     447 [-]: JUMPIFEQ R26 R27 L55
     448 [-]: LOADB R25 0 +1
L55: 449 [-]: LOADB R25 1  
L56: 450 [-]: GETUPVAL R26 18
     451 [-]: GETUPVAL R27 19
     452 [-]: CALL R24 3 -1
     453 [-]: NAMECALL R22 R1 K36 [0x0EB34C69]
     454 [-]: CALL R22 -1 1
     455 [-]: GETUPVAL R24 14
     456 [-]: GETTABLEKS R23 R24 K70 [0x118E5C26]
     457 [-]: LOADK R24 K71 ["/Lotus/Language/Objectives/ExcavDigsComplete"]
     458 [-]: LOADN R25 0  
     459 [-]: LOADK R27 K81 [": "]
     460 [-]: MOVE R28 R22 
     461 [-]: CONCAT R26 R27 R28
     462 [-]: LOADN R27 1  
     463 [-]: CALL R23 4 0 
L57: 464 [-]: GETUPVAL R22 2
     465 [-]: JUMPIF R22 L59
     466 [-]: GETUPVAL R23 15
     467 [-]: FASTCALL1 62 R23 L58
     468 [-]: GETIMPORT R22 3 [nil]
     469 [-]: CALL R22 1 1 
L58: 470 [-]: JUMPIFNOT R22 L59
     471 [-]: GETIMPORT R22 8 [nil]
     472 [-]: GETUPVAL R24 16
     473 [-]: NAMECALL R22 R22 K76 [0x46A0EBF5]
     474 [-]: CALL R22 2 1 
     475 [-]: SETUPVAL R22 15
L59: 476 [-]: GETUPVAL R22 9
     477 [-]: JUMPIFNOT R22 L65
     478 [-]: JUMPIF R3 L65
     479 [-]: GETUPVAL R23 20
     480 [-]: FASTCALL1 62 R23 L60
     481 [-]: GETIMPORT R22 3 [nil]
     482 [-]: CALL R22 1 1 
L60: 483 [-]: JUMPIF R22 L65
     484 [-]: GETUPVAL R23 15
     485 [-]: FASTCALL1 62 R23 L61
     486 [-]: GETIMPORT R22 3 [nil]
     487 [-]: CALL R22 1 1 
L61: 488 [-]: JUMPIF R22 L65
     489 [-]: GETUPVAL R22 15
     490 [-]: NAMECALL R22 R22 K82 [0xF37943FF]
     491 [-]: CALL R22 1 1 
     492 [-]: JUMPIFNOT R22 L65
     493 [-]: NAMECALL R22 R1 K83 [0x62623029]
     494 [-]: CALL R22 1 1 
     495 [-]: LOADK R23 K84 [4294967295]
     496 [-]: JUMPIFNOTLT R22 R23 L65
     497 [-]: LOADB R3 1   
     498 [-]: GETIMPORT R23 86 [nil]
     499 [-]: NAMECALL R25 R1 K23 [0xEF893AEC]
     500 [-]: CALL R25 1 1 
     501 [-]: GETTABLEKS R24 R25 K87 ["levelKeyName"]
     502 [-]: CALL R23 1 1 
     503 [-]: FASTCALL1 62 R23 L62
     504 [-]: MOVE R25 R23 
     505 [-]: GETIMPORT R24 3 [nil]
     506 [-]: CALL R24 1 1 
L62: 507 [-]: JUMPIF R24 L65
     508 [-]: MOVE R26 R22 
     509 [-]: NAMECALL R24 R23 K88 [0x8DA7EA75]
     510 [-]: CALL R24 2 1 
     511 [-]: GETTABLEKS R25 R24 K89 ["items"]
     512 [-]: JUMPXEQKNIL R25 L65
     513 [-]: GETTABLEN R27 R25 1
     514 [-]: FASTCALL1 62 R27 L63
     515 [-]: GETIMPORT R26 3 [nil]
     516 [-]: CALL R26 1 1 
L63: 517 [-]: JUMPIF R26 L65
     518 [-]: GETIMPORT R26 91 [nil]
     519 [-]: GETUPVAL R28 20
     520 [-]: NAMECALL R26 R26 K92 [0x6DD7AA66]
     521 [-]: CALL R26 2 1 
     522 [-]: FASTCALL1 62 R26 L64
     523 [-]: MOVE R28 R26 
     524 [-]: GETIMPORT R27 3 [nil]
     525 [-]: CALL R27 1 1 
L64: 526 [-]: JUMPIF R27 L65
     527 [-]: GETIMPORT R27 94 [nil]
     528 [-]: GETTABLEN R28 R25 1
     529 [-]: LOADN R29 1  
     530 [-]: CALL R27 2 0 
L65: 531 [-]: LOADN R22 0  
     532 [-]: LOADN R25 1  
     533 [-]: LENGTH R23 R14
     534 [-]: LOADN R24 1  
     535 [-]: FORNPREP R23 L87
L66: 536 [-]: GETTABLE R26 R14 R25
     537 [-]: FASTCALL1 62 R26 L67
     538 [-]: MOVE R28 R26 
     539 [-]: GETIMPORT R27 3 [nil]
     540 [-]: CALL R27 1 1 
L67: 541 [-]: JUMPIF R27 L85
     542 [-]: NAMECALL R27 R26 K82 [0xF37943FF]
     543 [-]: CALL R27 1 1 
     544 [-]: JUMPIFNOT R27 L85
     545 [-]: NAMECALL R28 R26 K95 [0xF329A790]
     546 [-]: CALL R28 1 1 
     547 [-]: MOD R27 R28 R6
     548 [-]: JUMPXEQKN R27 K73 L68 NOT [0]
     549 [-]: MOVE R27 R6  
L68: 550 [-]: ADDK R22 R22 K38 [1]
     551 [-]: GETTABLE R29 R20 R25
     552 [-]: FASTCALL1 62 R29 L69
     553 [-]: GETIMPORT R28 3 [nil]
     554 [-]: CALL R28 1 1 
L69: 555 [-]: JUMPIFNOT R28 L70
     556 [-]: GETUPVAL R30 14
     557 [-]: GETTABLEKS R29 R30 K97 [0xBD51F1E9]
     558 [-]: CALL R29 0 1 
     559 [-]: ADDK R28 R29 K96 [10]
     560 [-]: GETIMPORT R29 99 [nil]
     561 [-]: LOADK R31 K100 ["ExcavationInfo"]
     562 [-]: MOVE R32 R25 
     563 [-]: CONCAT R30 R31 R32
     564 [-]: GETUPVAL R32 6
     565 [-]: GETTABLEKS R31 R32 K101 ["HT_LABEL"]
     566 [-]: LOADK R32 K102 [0.14999999999999999]
     567 [-]: MOVE R33 R28 
     568 [-]: LOADB R34 0  
     569 [-]: CALL R29 5 1 
     570 [-]: SETTABLE R29 R20 R25
     571 [-]: GETTABLE R30 R20 R25
     572 [-]: GETTABLEKS R29 R30 K103 ["Colorize"]
     573 [-]: LOADN R30 38 
     574 [-]: CALL R29 1 0 
     575 [-]: GETTABLE R30 R20 R25
     576 [-]: GETTABLEKS R29 R30 K103 ["Colorize"]
     577 [-]: LOADN R30 49 
     578 [-]: CALL R29 1 0 
     579 [-]: GETTABLE R30 R20 R25
     580 [-]: GETTABLEKS R29 R30 K103 ["Colorize"]
     581 [-]: LOADN R30 20 
     582 [-]: CALL R29 1 0 
L70: 583 [-]: GETIMPORT R28 105 [nil]
     584 [-]: JUMPIFNOT R28 L86
     585 [-]: LOADNIL R28  
     586 [-]: LOADNIL R29  
     587 [-]: NAMECALL R30 R26 K106 [0xBB610E5B]
     588 [-]: CALL R30 1 1 
     589 [-]: FASTCALL1 62 R30 L71
     590 [-]: MOVE R32 R30 
     591 [-]: GETIMPORT R31 3 [nil]
     592 [-]: CALL R31 1 1 
L71: 593 [-]: JUMPIFNOT R31 L72
     594 [-]: LOADN R28 0  
     595 [-]: LOADN R29 0  
     596 [-]: JUMP L73
    
L72: 597 [-]: NAMECALL R31 R30 K107 [0xD2715720]
     598 [-]: CALL R31 1 1 
     599 [-]: MOVE R28 R31 
     600 [-]: NAMECALL R31 R30 K108 [0x1AC1655C]
     601 [-]: CALL R31 1 1 
     602 [-]: NAMECALL R31 R31 K109 [0xD127117D]
     603 [-]: CALL R31 1 1 
     604 [-]: MOVE R29 R31 
L73: 605 [-]: NAMECALL R31 R26 K110 [0x08E5889B]
     606 [-]: CALL R31 1 1 
     607 [-]: LOADK R32 K111 [""]
     608 [-]: LOADK R33 K112 [0.001]
     609 [-]: JUMPIFNOTLT R31 R33 L74
     610 [-]: LOADN R31 -1 
     611 [-]: JUMP L75
    
L74: 612 [-]: GETUPVAL R34 7
     613 [-]: GETTABLEKS R33 R34 K113 [0x74A11EC6]
     614 [-]: MOVE R34 R31 
     615 [-]: CALL R33 1 1 
     616 [-]: MOVE R31 R33 
L75: 617 [-]: NAMECALL R33 R26 K114 [0x17DD42BB]
     618 [-]: CALL R33 1 1 
     619 [-]: LOADN R34 0  
     620 [-]: JUMPIFNOTLT R31 R34 L76
     621 [-]: GETIMPORT R34 55 [nil]
     622 [-]: LOADK R35 K115 ["<font color=\"%s\"><b>%s</b></font>"]
     623 [-]: GETTABLE R37 R20 R25
     624 [-]: GETTABLEKS R36 R37 K116 ["ColorizeBlink"]
     625 [-]: LOADN R37 38 
     626 [-]: LOADN R38 34 
     627 [-]: CALL R36 2 1 
     628 [-]: MOVE R37 R13 
     629 [-]: CALL R34 3 1 
     630 [-]: MOVE R32 R34 
     631 [-]: JUMP L81
    
L76: 632 [-]: LOADN R34 25 
     633 [-]: JUMPIFNOTLE R31 R34 L78
     634 [-]: FASTCALL1 12 R33 L77
     635 [-]: MOVE R35 R33 
     636 [-]: GETIMPORT R34 118 [nil]
     637 [-]: CALL R34 1 1 
L77: 638 [-]: JUMPIFNOTLT R31 R34 L78
     639 [-]: GETIMPORT R34 55 [nil]
     640 [-]: LOADK R35 K115 ["<font color=\"%s\"><b>%s</b></font>"]
     641 [-]: GETTABLE R37 R20 R25
     642 [-]: GETTABLEKS R36 R37 K116 ["ColorizeBlink"]
     643 [-]: LOADN R37 38 
     644 [-]: LOADN R38 34 
     645 [-]: CALL R36 2 1 
     646 [-]: MOVE R38 R31 
     647 [-]: LOADK R39 K119 ["%"]
     648 [-]: CONCAT R37 R38 R39
     649 [-]: CALL R34 3 1 
     650 [-]: MOVE R32 R34 
     651 [-]: JUMP L81
    
L78: 652 [-]: FASTCALL1 12 R33 L79
     653 [-]: MOVE R35 R33 
     654 [-]: GETIMPORT R34 118 [nil]
     655 [-]: CALL R34 1 1 
L79: 656 [-]: JUMPIFNOTLE R34 R31 L80
     657 [-]: GETIMPORT R34 55 [nil]
     658 [-]: LOADK R35 K115 ["<font color=\"%s\"><b>%s</b></font>"]
     659 [-]: GETTABLE R37 R20 R25
     660 [-]: GETTABLEKS R36 R37 K103 ["Colorize"]
     661 [-]: LOADN R37 10 
     662 [-]: CALL R36 1 1 
     663 [-]: MOVE R37 R12 
     664 [-]: CALL R34 3 1 
     665 [-]: MOVE R32 R34 
     666 [-]: JUMP L81
    
L80: 667 [-]: GETIMPORT R34 55 [nil]
     668 [-]: LOADK R35 K115 ["<font color=\"%s\"><b>%s</b></font>"]
     669 [-]: GETTABLE R37 R20 R25
     670 [-]: GETTABLEKS R36 R37 K103 ["Colorize"]
     671 [-]: LOADN R37 38 
     672 [-]: CALL R36 1 1 
     673 [-]: MOVE R38 R31 
     674 [-]: LOADK R39 K119 ["%"]
     675 [-]: CONCAT R37 R38 R39
     676 [-]: CALL R34 3 1 
     677 [-]: MOVE R32 R34 
L81: 678 [-]: GETUPVAL R35 7
     679 [-]: GETTABLEKS R34 R35 K120 [0x1142C7A8]
     680 [-]: MOVE R35 R33 
     681 [-]: LOADN R36 1  
     682 [-]: LOADNIL R37  
     683 [-]: LOADNIL R38  
     684 [-]: LOADB R39 1  
     685 [-]: CALL R34 5 1 
     686 [-]: GETTABLE R36 R20 R25
     687 [-]: GETTABLEKS R35 R36 K121 ["SetLabel"]
     688 [-]: GETIMPORT R36 55 [nil]
     689 [-]: MOVE R37 R18 
     690 [-]: GETTABLE R38 R5 R27
     691 [-]: MOVE R39 R29 
     692 [-]: MOVE R40 R28 
     693 [-]: GETUPVAL R42 21
     694 [-]: GETTABLEKS R41 R42 K122 [0xC70DAAAC]
     695 [-]: MOVE R42 R34 
     696 [-]: CALL R41 1 1 
     697 [-]: MOVE R42 R32 
     698 [-]: CALL R36 6 -1
     699 [-]: CALL R35 -1 0
     700 [-]: GETTABLE R36 R20 R25
     701 [-]: GETTABLEKS R35 R36 K123 ["NeedsInit"]
     702 [-]: JUMPIF R35 L86
     703 [-]: FASTCALL1 62 R2 L82
     704 [-]: MOVE R36 R2  
     705 [-]: GETIMPORT R35 3 [nil]
     706 [-]: CALL R35 1 1 
L82: 707 [-]: JUMPIFNOT R35 L83
     708 [-]: NAMECALL R35 R1 K11 [0x33307F92]
     709 [-]: CALL R35 1 1 
     710 [-]: MOVE R2 R35  
L83: 711 [-]: FASTCALL1 62 R2 L84
     712 [-]: MOVE R36 R2  
     713 [-]: GETIMPORT R35 3 [nil]
     714 [-]: CALL R35 1 1 
L84: 715 [-]: JUMPIF R35 L86
     716 [-]: GETTABLE R40 R20 R25
     717 [-]: GETTABLEKS R38 R40 K124 ["ClipName"]
     718 [-]: LOADK R39 K125 [".Label"]
     719 [-]: CONCAT R37 R38 R39
     720 [-]: LOADN R38 34 
     721 [-]: NAMECALL R35 R2 K126 [0x91A24E4B]
     722 [-]: CALL R35 3 1 
     723 [-]: JUMPXEQKNIL R35 L86
     724 [-]: GETTABLE R37 R20 R25
     725 [-]: GETTABLEKS R36 R37 K127 ["SetHeight"]
     726 [-]: ADDK R37 R35 K128 [25]
     727 [-]: CALL R36 1 0 
     728 [-]: JUMP L86
    
L85: 729 [-]: GETTABLE R27 R20 R25
     730 [-]: JUMPIFNOT R27 L86
     731 [-]: GETIMPORT R27 130 [nil]
     732 [-]: GETTABLE R28 R20 R25
     733 [-]: CALL R27 1 0 
     734 [-]: LOADNIL R27  
     735 [-]: SETTABLE R27 R20 R25
L86: 736 [-]: FORNLOOP R23 L66
L87: 737 [-]: GETIMPORT R23 5 [nil]
     738 [-]: LOADN R24 0  
     739 [-]: CALL R23 1 0 
     740 [-]: JUMPBACK L49 
L88: 741 [-]: GETUPVAL R21 2
     742 [-]: JUMPIFNOT R21 L91
     743 [-]: GETIMPORT R21 130 [nil]
     744 [-]: JUMPIFNOT R21 L91
     745 [-]: LOADN R23 1  
     746 [-]: LENGTH R21 R14
     747 [-]: LOADN R22 1  
     748 [-]: FORNPREP R21 L91
L89: 749 [-]: GETTABLE R24 R20 R23
     750 [-]: JUMPIFNOT R24 L90
     751 [-]: GETIMPORT R24 130 [nil]
     752 [-]: GETTABLE R25 R20 R23
     753 [-]: CALL R24 1 0 
L90: 754 [-]: FORNLOOP R21 L89
L91: 755 [-]: RETURN R0 0  


; Name:            
; Defined at line: 2217
; #Upvalues:       7
; #Parameters:     0
; Is_vararg:       0
; Max Stack Size:  15

       0 [-]: GETUPVAL R0 0
       1 [-]: GETUPVAL R1 1
       2 [-]: JUMPIFNOT R1 L0
       3 [-]: GETUPVAL R0 2
L 0:   4 [-]: GETIMPORT R1 1 [nil]
       5 [-]: MOVE R3 R0   
       6 [-]: NAMECALL R1 R1 K2 [0xC7FCADA9]
       7 [-]: CALL R1 2 1  
       8 [-]: GETUPVAL R3 3
       9 [-]: JUMPIFNOT R3 L3
      10 [-]: GETIMPORT R2 1 [nil]
      11 [-]: NAMECALL R2 R2 K3 [0x18D05D30]
      12 [-]: CALL R2 1 1  
      13 [-]: JUMPIFNOT R2 L4
      14 [-]: GETIMPORT R3 5 [nil]
      15 [-]: GETUPVAL R5 4
      16 [-]: LOADN R6 0   
      17 [-]: NAMECALL R3 R3 K6 [0x0EB34C69]
      18 [-]: CALL R3 3 1  
      19 [-]: JUMPXEQKN R3 K7 L1 [1]
      20 [-]: LOADB R2 0 +1
L 1:  21 [-]: LOADB R2 1   
L 2:  22 [-]: JUMP L4
     
L 3:  23 [-]: GETIMPORT R2 9 [nil]
      24 [-]: JUMP L4
     
L 4:  25 [-]: JUMPIF R2 L5 
      26 [-]: RETURN R1 1  
L 5:  27 [-]: NEWTABLE R2 0 0
      28 [-]: LOADN R5 1   
      29 [-]: LENGTH R3 R1 
      30 [-]: LOADN R4 1   
      31 [-]: FORNPREP R3 L11
L 6:  32 [-]: GETIMPORT R6 1 [nil]
      33 [-]: GETIMPORT R8 11 [nil]
      34 [-]: GETTABLE R9 R1 R5
      35 [-]: NAMECALL R9 R9 K12 [0xD1586535]
      36 [-]: CALL R9 1 1  
      37 [-]: LOADK R10 K13 [0.20000000000000001]
      38 [-]: NAMECALL R6 R6 K14 [0x4E5939A5]
      39 [-]: CALL R6 4 1  
      40 [-]: FASTCALL1 62 R6 L7
      41 [-]: MOVE R8 R6   
      42 [-]: GETIMPORT R7 16 [nil]
      43 [-]: CALL R7 1 1  
L 7:  44 [-]: JUMPIF R7 L8 
      45 [-]: NAMECALL R7 R6 K17 [0xF37943FF]
      46 [-]: CALL R7 1 1  
      47 [-]: JUMPIFNOT R7 L8
      48 [-]: GETIMPORT R7 19 [nil]
      49 [-]: LOADK R9 K20 ["Extractor "]
      50 [-]: GETIMPORT R12 22 [nil]
      51 [-]: GETTABLE R13 R1 R5
      52 [-]: NAMECALL R13 R13 K23 [0xED4E0128]
      53 [-]: CALL R13 1 -1
      54 [-]: CALL R12 -1 1
      55 [-]: MOVE R10 R12 
      56 [-]: LOADK R11 K24 [" already used, removing"]
      57 [-]: CONCAT R8 R9 R11
      58 [-]: CALL R7 1 0  
      59 [-]: JUMP L10
    
L 8:  60 [-]: GETTABLE R7 R1 R5
      61 [-]: GETUPVAL R8 5
      62 [-]: JUMPIFNOTEQ R7 R8 L9
      63 [-]: LENGTH R7 R1 
      64 [-]: GETUPVAL R8 6
      65 [-]: JUMPIFNOTLE R7 R8 L10
L 9:  66 [-]: GETTABLE R9 R1 R5
      67 [-]: FASTCALL2 52 R2 R9 L10
      68 [-]: MOVE R8 R2   
      69 [-]: GETIMPORT R7 27 [nil]
      70 [-]: CALL R7 2 0  
L10:  71 [-]: FORNLOOP R3 L6
L11:  72 [-]: RETURN R2 1  


; Name:            
; Defined at line: 2245
; #Upvalues:       0
; #Parameters:     3
; Is_vararg:       0
; Max Stack Size:  11

       0 [-]: LOADNIL R3   
       1 [-]: LOADN R6 1   
       2 [-]: LENGTH R4 R0 
       3 [-]: LOADN R5 1   
       4 [-]: FORNPREP R4 L4
L 0:   5 [-]: GETTABLE R8 R0 R6
       6 [-]: MOVE R10 R1  
       7 [-]: NAMECALL R8 R8 K0 [0x1F420A3A]
       8 [-]: CALL R8 2 1  
       9 [-]: JUMPIFLT R8 R2 L1
      10 [-]: LOADB R7 0 +1
L 1:  11 [-]: LOADB R7 1   
L 2:  12 [-]: JUMPIFNOT R7 L3
      13 [-]: MOVE R3 R6   
L 3:  14 [-]: FORNLOOP R4 L0
L 4:  15 [-]: FASTCALL1 62 R3 L5
      16 [-]: MOVE R5 R3   
      17 [-]: GETIMPORT R4 2 [nil]
      18 [-]: CALL R4 1 1  
L 5:  19 [-]: JUMPIFNOT R4 L6
      20 [-]: GETIMPORT R4 4 [nil]
      21 [-]: LOADN R5 1   
      22 [-]: LENGTH R6 R0 
      23 [-]: CALL R4 2 1  
      24 [-]: MOVE R3 R4   
L 6:  25 [-]: RETURN R3 1  


; Name:            
; Defined at line: 2261
; #Upvalues:       17
; #Parameters:     1
; Is_vararg:       0
; Max Stack Size:  34

       0 [-]: GETIMPORT R1 1 [nil]
       1 [-]: NAMECALL R1 R1 K2 [0x18D05D30]
       2 [-]: CALL R1 1 1  
       3 [-]: JUMPIF R1 L0 
       4 [-]: RETURN R0 0  
L 0:   5 [-]: GETUPVAL R1 0
       6 [-]: JUMPIFNOT R1 L1
       7 [-]: LOADN R1 1   
       8 [-]: SETUPVAL R1 1
L 1:   9 [-]: GETUPVAL R1 2
      10 [-]: CALL R1 0 1  
      11 [-]: LOADN R2 50  
      12 [-]: GETIMPORT R3 4 [nil]
      13 [-]: LOADK R5 K5 ["Nr of extractors = "]
      14 [-]: GETIMPORT R6 7 [nil]
      15 [-]: LENGTH R7 R1 
      16 [-]: CALL R6 1 1  
      17 [-]: CONCAT R4 R5 R6
      18 [-]: CALL R3 1 0  
      19 [-]: GETIMPORT R3 9 [nil]
      20 [-]: GETUPVAL R5 3
      21 [-]: NAMECALL R3 R3 K10 [0x0EB34C69]
      22 [-]: CALL R3 2 1  
      23 [-]: JUMPXEQKN R3 K11 L2 NOT [0]
      24 [-]: GETIMPORT R4 9 [nil]
      25 [-]: GETUPVAL R6 4
      26 [-]: MOVE R7 R2   
      27 [-]: NAMECALL R4 R4 K12 [0x751F061D]
      28 [-]: CALL R4 3 0  
L 2:  29 [-]: LOADN R4 0   
      30 [-]: LOADN R5 0   
      31 [-]: LOADN R6 0   
      32 [-]: JUMPXEQKN R3 K11 L3 NOT [0]
      33 [-]: GETIMPORT R7 9 [nil]
      34 [-]: GETUPVAL R9 3
      35 [-]: LOADN R10 1  
      36 [-]: NAMECALL R7 R7 K12 [0x751F061D]
      37 [-]: CALL R7 3 0  
L 3:  38 [-]: LOADNIL R7   
L 4:  39 [-]: FASTCALL1 62 R7 L5
      40 [-]: MOVE R9 R7   
      41 [-]: GETIMPORT R8 14 [nil]
      42 [-]: CALL R8 1 1  
L 5:  43 [-]: JUMPIFNOT R8 L9
      44 [-]: GETIMPORT R8 1 [nil]
      45 [-]: GETUPVAL R10 5
      46 [-]: NAMECALL R8 R8 K15 [0xC7FCADA9]
      47 [-]: CALL R8 2 1  
      48 [-]: LOADN R11 1  
      49 [-]: LENGTH R9 R8 
      50 [-]: LOADN R10 1  
      51 [-]: FORNPREP R9 L8
L 6:  52 [-]: GETTABLE R12 R8 R11
      53 [-]: NAMECALL R12 R12 K16 [0xD4CC05B4]
      54 [-]: CALL R12 1 1 
      55 [-]: JUMPIFNOT R12 L7
      56 [-]: GETTABLE R7 R8 R11
      57 [-]: JUMP L8
     
L 7:  58 [-]: FORNLOOP R9 L6
L 8:  59 [-]: GETIMPORT R9 18 [nil]
      60 [-]: LOADN R10 0  
      61 [-]: CALL R9 1 0  
      62 [-]: JUMPBACK L4  
L 9:  63 [-]: NAMECALL R8 R7 K19 [0xD1586535]
      64 [-]: CALL R8 1 1  
      65 [-]: GETUPVAL R10 6
      66 [-]: JUMPIFNOT R10 L12
      67 [-]: GETIMPORT R9 1 [nil]
      68 [-]: NAMECALL R9 R9 K2 [0x18D05D30]
      69 [-]: CALL R9 1 1  
      70 [-]: JUMPIFNOT R9 L13
      71 [-]: GETIMPORT R10 9 [nil]
      72 [-]: GETUPVAL R12 7
      73 [-]: LOADN R13 0  
      74 [-]: NAMECALL R10 R10 K10 [0x0EB34C69]
      75 [-]: CALL R10 3 1 
      76 [-]: JUMPXEQKN R10 K20 L10 [1]
      77 [-]: LOADB R9 0 +1
L10:  78 [-]: LOADB R9 1   
L11:  79 [-]: JUMP L13
    
L12:  80 [-]: GETIMPORT R9 22 [nil]
      81 [-]: JUMP L13
    
L13:  82 [-]: JUMPIFNOT R9 L14
      83 [-]: JUMPXEQKN R3 K11 L14 [0]
      84 [-]: LOADN R9 25  
      85 [-]: GETIMPORT R11 9 [nil]
      86 [-]: GETUPVAL R14 8
      87 [-]: NAMECALL R12 R11 K10 [0x0EB34C69]
      88 [-]: CALL R12 2 1 
      89 [-]: DIVK R10 R12 K23 [16384]
      90 [-]: SUB R6 R9 R10
L14:  91 [-]: LOADB R9 1   
L15:  92 [-]: GETIMPORT R10 9 [nil]
      93 [-]: GETUPVAL R12 4
      94 [-]: LOADN R13 0  
      95 [-]: NAMECALL R10 R10 K10 [0x0EB34C69]
      96 [-]: CALL R10 3 1 
      97 [-]: MOVE R2 R10  
      98 [-]: GETIMPORT R10 1 [nil]
      99 [-]: GETUPVAL R12 9
     100 [-]: NAMECALL R10 R10 K15 [0xC7FCADA9]
     101 [-]: CALL R10 2 1 
     102 [-]: LENGTH R11 R10
     103 [-]: GETIMPORT R12 1 [nil]
     104 [-]: GETUPVAL R14 10
     105 [-]: NAMECALL R12 R12 K15 [0xC7FCADA9]
     106 [-]: CALL R12 2 1 
     107 [-]: MOVE R10 R12 
     108 [-]: LOADN R14 1  
     109 [-]: LENGTH R12 R10
     110 [-]: LOADN R13 1  
     111 [-]: FORNPREP R12 L18
L16: 112 [-]: GETTABLE R15 R10 R14
     113 [-]: NAMECALL R15 R15 K24 [0xF37943FF]
     114 [-]: CALL R15 1 1 
     115 [-]: JUMPIFNOT R15 L17
     116 [-]: ADDK R11 R11 K20 [1]
L17: 117 [-]: FORNLOOP R12 L16
L18: 118 [-]: GETIMPORT R12 9 [nil]
     119 [-]: GETUPVAL R14 11
     120 [-]: LOADN R15 0  
     121 [-]: NAMECALL R12 R12 K10 [0x0EB34C69]
     122 [-]: CALL R12 3 1 
     123 [-]: LOADN R13 25 
     124 [-]: JUMPIFNOTLT R13 R6 L24
     125 [-]: LOADN R13 0  
     126 [-]: JUMPIFNOTLT R13 R2 L24
     127 [-]: GETUPVAL R13 1
     128 [-]: JUMPIFNOTLT R11 R13 L24
     129 [-]: LENGTH R13 R1
     130 [-]: LOADN R14 0  
     131 [-]: JUMPIFNOTLE R13 R14 L19
     132 [-]: GETUPVAL R13 2
     133 [-]: CALL R13 0 1 
     134 [-]: MOVE R1 R13  
     135 [-]: GETIMPORT R13 4 [nil]
     136 [-]: LOADK R15 K5 ["Nr of extractors = "]
     137 [-]: GETIMPORT R16 7 [nil]
     138 [-]: LENGTH R17 R1
     139 [-]: CALL R16 1 1 
     140 [-]: CONCAT R14 R15 R16
     141 [-]: CALL R13 1 0 
L19: 142 [-]: LOADNIL R13  
     143 [-]: LOADN R14 3  
     144 [-]: JUMPIFNOTLT R14 R12 L20
     145 [-]: GETIMPORT R14 26 [nil]
     146 [-]: LOADN R15 1  
     147 [-]: LENGTH R16 R1
     148 [-]: CALL R14 2 1 
     149 [-]: MOVE R13 R14 
     150 [-]: JUMP L23
    
L20: 151 [-]: LOADN R14 2  
     152 [-]: JUMPIFNOTLT R14 R12 L21
     153 [-]: GETUPVAL R14 12
     154 [-]: MOVE R15 R1  
     155 [-]: MOVE R16 R8  
     156 [-]: LOADN R17 400
     157 [-]: CALL R14 3 1 
     158 [-]: MOVE R13 R14 
     159 [-]: JUMP L23
    
L21: 160 [-]: LOADN R14 1  
     161 [-]: JUMPIFNOTLT R14 R12 L22
     162 [-]: GETUPVAL R14 12
     163 [-]: MOVE R15 R1  
     164 [-]: MOVE R16 R8  
     165 [-]: LOADN R17 300
     166 [-]: CALL R14 3 1 
     167 [-]: MOVE R13 R14 
     168 [-]: JUMP L23
    
L22: 169 [-]: GETUPVAL R14 12
     170 [-]: MOVE R15 R1  
     171 [-]: MOVE R16 R8  
     172 [-]: LOADN R17 200
     173 [-]: CALL R14 3 1 
     174 [-]: MOVE R13 R14 
L23: 175 [-]: GETTABLE R14 R1 R13
     176 [-]: SETUPVAL R14 13
     177 [-]: GETTABLE R14 R1 R13
     178 [-]: LOADK R16 K27 ["TriggerPort"]
     179 [-]: NAMECALL R14 R14 K28 [0x8EB2112D]
     180 [-]: CALL R14 2 0 
     181 [-]: GETIMPORT R14 31 [nil]
     182 [-]: MOVE R15 R1  
     183 [-]: MOVE R16 R13 
     184 [-]: CALL R14 2 0 
     185 [-]: GETUPVAL R15 14
     186 [-]: GETTABLEKS R14 R15 K32 [0x9742B85B]
     187 [-]: GETIMPORT R15 35 [nil]
     188 [-]: GETIMPORT R16 37 [nil]
     189 [-]: LOADK R17 K38 ["MissionScannerComplete"]
     190 [-]: CALL R16 1 -1
     191 [-]: CALL R14 -1 0
     192 [-]: LOADN R6 0   
L24: 193 [-]: GETIMPORT R13 1 [nil]
     194 [-]: NAMECALL R13 R13 K39 [0x8B5B1F58]
     195 [-]: CALL R13 1 1 
     196 [-]: LOADN R16 1  
     197 [-]: LENGTH R14 R13
     198 [-]: LOADN R15 1  
     199 [-]: FORNPREP R14 L32
L25: 200 [-]: GETTABLE R18 R13 R16
     201 [-]: GETIMPORT R21 41 [nil]
     202 [-]: NAMECALL R19 R18 K42 [0xF2DEAF69]
     203 [-]: CALL R19 2 1 
     204 [-]: JUMPIFNOT R19 L26
     205 [-]: NAMECALL R19 R18 K43 [0xB0E8475C]
     206 [-]: CALL R19 1 1 
     207 [-]: JUMPIFNOT R19 L26
     208 [-]: NAMECALL R19 R18 K44 [0xFF005826]
     209 [-]: CALL R19 1 1 
     210 [-]: JUMPIFNOT R19 L26
     211 [-]: NAMECALL R19 R18 K44 [0xFF005826]
     212 [-]: CALL R19 1 1 
     213 [-]: MOVE R17 R19 
     214 [-]: JUMP L27
    
L26: 215 [-]: MOVE R17 R18 
L27: 216 [-]: GETIMPORT R20 46 [nil]
     217 [-]: NAMECALL R18 R17 K47 [0x0866B4BD]
     218 [-]: CALL R18 2 1 
     219 [-]: JUMPIFNOT R18 L31
     220 [-]: GETUPVAL R20 15
     221 [-]: MULK R19 R20 K49 [10]
     222 [-]: DIVK R18 R19 K48 [9]
     223 [-]: JUMPIFNOTLT R2 R18 L31
     224 [-]: GETTABLE R18 R13 R16
     225 [-]: NAMECALL R18 R18 K19 [0xD1586535]
     226 [-]: CALL R18 1 1 
     227 [-]: GETTABLEKS R22 R18 K50 ["x"]
     228 [-]: GETTABLEKS R23 R8 K50 ["x"]
     229 [-]: SUB R21 R22 R23
     230 [-]: GETTABLEKS R23 R18 K50 ["x"]
     231 [-]: GETTABLEKS R24 R8 K50 ["x"]
     232 [-]: SUB R22 R23 R24
     233 [-]: MUL R20 R21 R22
     234 [-]: GETTABLEKS R23 R18 K51 ["z"]
     235 [-]: GETTABLEKS R24 R8 K51 ["z"]
     236 [-]: SUB R22 R23 R24
     237 [-]: GETTABLEKS R24 R18 K51 ["z"]
     238 [-]: GETTABLEKS R25 R8 K51 ["z"]
     239 [-]: SUB R23 R24 R25
     240 [-]: MUL R21 R22 R23
     241 [-]: ADD R19 R20 R21
     242 [-]: LOADN R20 25 
     243 [-]: JUMPIFNOTLT R19 R20 L31
     244 [-]: GETTABLE R20 R13 R16
     245 [-]: NAMECALL R20 R20 K52 [0x5E651723]
     246 [-]: CALL R20 1 1 
     247 [-]: NAMECALL R21 R17 K53 [0xDE321E6F]
     248 [-]: CALL R21 1 1 
     249 [-]: NAMECALL R21 R21 K54 [0xC9CDF64D]
     250 [-]: CALL R21 1 1 
     251 [-]: GETUPVAL R23 16
     252 [-]: GETTABLEKS R22 R23 K55 [0x74A11EC6]
     253 [-]: LOADN R25 20 
     254 [-]: MUL R24 R25 R21
     255 [-]: GETUPVAL R26 15
     256 [-]: SUB R25 R26 R2
     257 [-]: FASTCALL2 19 R24 R25 L28
     258 [-]: GETIMPORT R23 58 [nil]
     259 [-]: CALL R23 2 1 
L28: 260 [-]: CALL R22 1 1 
     261 [-]: GETIMPORT R23 9 [nil]
     262 [-]: MOVE R25 R20 
     263 [-]: LOADK R26 K59 ["/Lotus/Language/Game/GainedPower"]
     264 [-]: LOADK R27 K60 [""]
     265 [-]: LOADN R28 0  
     266 [-]: LOADN R29 2  
     267 [-]: LOADB R30 1  
     268 [-]: LOADK R31 K61 ["AMOUNT"]
     269 [-]: GETIMPORT R32 7 [nil]
     270 [-]: MOVE R33 R22 
     271 [-]: CALL R32 1 -1
     272 [-]: NAMECALL R23 R23 K62 [0x06D4C9EB]
     273 [-]: CALL R23 -1 0
     274 [-]: ADD R2 R2 R22
     275 [-]: GETTABLE R23 R13 R16
     276 [-]: GETIMPORT R25 64 [nil]
     277 [-]: LOADB R26 0  
     278 [-]: NAMECALL R23 R23 K65 [0x659D451F]
     279 [-]: CALL R23 3 0 
     280 [-]: GETIMPORT R25 46 [nil]
     281 [-]: NAMECALL R23 R17 K66 [0x35B09371]
     282 [-]: CALL R23 2 0 
     283 [-]: FASTCALL1 62 R20 L29
     284 [-]: MOVE R24 R20 
     285 [-]: GETIMPORT R23 14 [nil]
     286 [-]: CALL R23 1 1 
L29: 287 [-]: JUMPIF R23 L31
     288 [-]: NAMECALL R23 R20 K67 [0x61C34FA9]
     289 [-]: CALL R23 1 1 
     290 [-]: FASTCALL1 62 R23 L30
     291 [-]: MOVE R25 R23 
     292 [-]: GETIMPORT R24 14 [nil]
     293 [-]: CALL R24 1 1 
L30: 294 [-]: JUMPIF R24 L31
     295 [-]: NAMECALL R24 R23 K68 [0xA44E757A]
     296 [-]: CALL R24 1 0 
L31: 297 [-]: FORNLOOP R14 L25
L32: 298 [-]: LOADN R14 1  
     299 [-]: JUMPIFNOTLE R14 R5 L34
     300 [-]: GETUPVAL R14 1
     301 [-]: JUMPIFNOTLT R11 R14 L34
     302 [-]: SUBK R15 R2 K20 [1]
     303 [-]: FASTCALL2K 18 R15 K11 L33 [0]
     304 [-]: LOADK R16 K11 [0]
     305 [-]: GETIMPORT R14 70 [nil]
     306 [-]: CALL R14 2 1 
L33: 307 [-]: MOVE R2 R14  
     308 [-]: LOADN R5 0   
L34: 309 [-]: LOADN R14 0  
     310 [-]: JUMPIFNOTLE R2 R14 L35
     311 [-]: JUMPXEQKN R11 K11 L35 NOT [0]
     312 [-]: GETUPVAL R15 14
     313 [-]: GETTABLEKS R14 R15 K32 [0x9742B85B]
     314 [-]: GETIMPORT R15 35 [nil]
     315 [-]: GETIMPORT R16 37 [nil]
     316 [-]: LOADK R17 K71 ["MissionScannerUnpowered"]
     317 [-]: CALL R16 1 -1
     318 [-]: CALL R14 -1 0
     319 [-]: LOADN R4 0   
L35: 320 [-]: LOADN R14 0  
     321 [-]: JUMPIFNOTLE R2 R14 L36
     322 [-]: JUMPIFNOT R9 L36
     323 [-]: LOADB R9 0   
     324 [-]: JUMP L37
    
L36: 325 [-]: LOADN R14 0  
     326 [-]: JUMPIFNOTLT R14 R2 L37
     327 [-]: JUMPIF R9 L37
     328 [-]: LOADB R9 1   
L37: 329 [-]: GETIMPORT R14 9 [nil]
     330 [-]: GETUPVAL R16 4
     331 [-]: MOVE R17 R2  
     332 [-]: NAMECALL R14 R14 K12 [0x751F061D]
     333 [-]: CALL R14 3 0 
     334 [-]: GETIMPORT R14 9 [nil]
     335 [-]: GETUPVAL R16 11
     336 [-]: MOVE R17 R12 
     337 [-]: NAMECALL R14 R14 K12 [0x751F061D]
     338 [-]: CALL R14 3 0 
     339 [-]: GETIMPORT R14 73 [nil]
     340 [-]: CALL R14 0 1 
     341 [-]: ADD R4 R4 R14
     342 [-]: GETIMPORT R14 73 [nil]
     343 [-]: CALL R14 0 1 
     344 [-]: ADD R5 R5 R14
     345 [-]: LOADN R14 0  
     346 [-]: JUMPIFNOTLT R14 R2 L38
     347 [-]: GETUPVAL R14 1
     348 [-]: JUMPIFNOTLT R11 R14 L38
     349 [-]: GETIMPORT R14 73 [nil]
     350 [-]: CALL R14 0 1 
     351 [-]: ADD R6 R6 R14
L38: 352 [-]: LOADN R15 25 
     353 [-]: SUB R14 R15 R6
     354 [-]: GETIMPORT R15 9 [nil]
     355 [-]: LOADN R16 0  
     356 [-]: JUMPIFNOTLT R14 R16 L39
     357 [-]: LOADN R14 0  
L39: 358 [-]: GETUPVAL R18 8
     359 [-]: MULK R20 R14 K23 [16384]
     360 [-]: FASTCALL1 7 R20 L40
     361 [-]: GETIMPORT R19 75 [nil]
     362 [-]: CALL R19 1 1 
L40: 363 [-]: NAMECALL R16 R15 K12 [0x751F061D]
     364 [-]: CALL R16 3 0 
     365 [-]: GETIMPORT R14 18 [nil]
     366 [-]: LOADN R15 0  
     367 [-]: CALL R14 1 0 
     368 [-]: JUMPBACK L15 
     369 [-]: RETURN R0 0  


; Name:            
; Defined at line: 2427
; #Upvalues:       1
; #Parameters:     2
; Is_vararg:       0
; Max Stack Size:  4

       0 [-]: GETUPVAL R2 0
       1 [-]: MOVE R3 R0   
       2 [-]: CALL R2 1 0  
       3 [-]: RETURN R0 0  


; Name:            
; Defined at line: 2431
; #Upvalues:       6
; #Parameters:     5
; Is_vararg:       0
; Max Stack Size:  27

       0 [-]: LOADN R5 0   
       1 [-]: LOADB R6 0   
       2 [-]: LOADN R9 1   
       3 [-]: LENGTH R7 R0 
       4 [-]: LOADN R8 1   
       5 [-]: FORNPREP R7 L15
L 0:   6 [-]: GETTABLE R10 R0 R9
       7 [-]: NAMECALL R10 R10 K0 [0x5E651723]
       8 [-]: CALL R10 1 1 
       9 [-]: NAMECALL R11 R10 K1 [0x01621194]
      10 [-]: CALL R11 1 1 
      11 [-]: GETTABLE R13 R0 R9
      12 [-]: MOVE R15 R1  
      13 [-]: NAMECALL R13 R13 K2 [0x1F420A3A]
      14 [-]: CALL R13 2 1 
      15 [-]: LOADN R14 6  
      16 [-]: JUMPIFLT R13 R14 L1
      17 [-]: LOADB R12 0 +1
L 1:  18 [-]: LOADB R12 1  
L 2:  19 [-]: LOADB R13 0  
      20 [-]: JUMPIFNOT R12 L12
      21 [-]: GETUPVAL R14 0
      22 [-]: JUMPIFNOTLT R3 R14 L12
      23 [-]: GETUPVAL R15 0
      24 [-]: SUB R14 R15 R4
      25 [-]: JUMPIFNOTLE R3 R14 L12
      26 [-]: GETTABLE R14 R0 R9
      27 [-]: NAMECALL R14 R14 K3 [0x1AC1655C]
      28 [-]: CALL R14 1 1 
      29 [-]: NAMECALL R15 R14 K4 [0xF456C2D7]
      30 [-]: CALL R15 1 1 
      31 [-]: NAMECALL R16 R14 K5 [0xB87F958D]
      32 [-]: CALL R16 1 1 
      33 [-]: GETTABLE R17 R0 R9
      34 [-]: NAMECALL R17 R17 K6 [0xD2715720]
      35 [-]: CALL R17 1 1 
      36 [-]: LOADN R18 0  
      37 [-]: JUMPIFNOTLT R18 R15 L5
      38 [-]: GETIMPORT R18 8 [nil]
      39 [-]: NAMECALL R18 R18 K9 [0x18D05D30]
      40 [-]: CALL R18 1 1 
      41 [-]: JUMPIFNOT R18 L4
      42 [-]: SUBK R19 R15 K10 [30]
      43 [-]: FASTCALL2K 18 R19 K11 L3 [0]
      44 [-]: LOADK R20 K11 [0]
      45 [-]: GETIMPORT R18 14 [nil]
      46 [-]: CALL R18 2 1 
L 3:  47 [-]: MOVE R21 R18 
      48 [-]: NAMECALL R19 R14 K15 [0x57369B8B]
      49 [-]: CALL R19 2 0 
L 4:  50 [-]: LOADB R13 1  
      51 [-]: JUMP L8
     
L 5:  52 [-]: JUMPXEQKN R16 K11 L8 NOT [0]
      53 [-]: LOADN R18 100
      54 [-]: JUMPIFNOTLT R18 R17 L8
      55 [-]: GETIMPORT R18 8 [nil]
      56 [-]: NAMECALL R18 R18 K9 [0x18D05D30]
      57 [-]: CALL R18 1 1 
      58 [-]: JUMPIFNOT R18 L7
      59 [-]: SUBK R19 R17 K10 [30]
      60 [-]: FASTCALL2K 18 R19 K11 L6 [0]
      61 [-]: LOADK R20 K11 [0]
      62 [-]: GETIMPORT R18 14 [nil]
      63 [-]: CALL R18 2 1 
L 6:  64 [-]: GETTABLE R19 R0 R9
      65 [-]: MOVE R21 R18 
      66 [-]: NAMECALL R19 R19 K16 [0x014DB014]
      67 [-]: CALL R19 2 0 
L 7:  68 [-]: LOADB R13 1  
L 8:  69 [-]: JUMPIFNOT R13 L12
      70 [-]: GETTABLE R19 R0 R9
      71 [-]: GETIMPORT R21 18 [nil]
      72 [-]: NAMECALL R19 R19 K19 [0xC9F6A7D7]
      73 [-]: CALL R19 2 1 
      74 [-]: FASTCALL1 62 R19 L9
      75 [-]: GETIMPORT R18 21 [nil]
      76 [-]: CALL R18 1 1 
L 9:  77 [-]: JUMPIFNOT R18 L11
      78 [-]: LOADN R20 0  
      79 [-]: NAMECALL R18 R14 K22 [0x9EB6D632]
      80 [-]: CALL R18 2 1 
      81 [-]: GETTABLE R19 R0 R9
      82 [-]: GETIMPORT R21 18 [nil]
      83 [-]: MOVE R22 R18 
      84 [-]: GETIMPORT R23 24 [nil]
      85 [-]: LOADK R24 K25 [-0.20000000000000001]
      86 [-]: LOADN R25 0  
      87 [-]: LOADN R26 0  
      88 [-]: CALL R23 3 -1
      89 [-]: NAMECALL R19 R19 K26 [0x47901F07]
      90 [-]: CALL R19 -1 1
      91 [-]: GETIMPORT R23 24 [nil]
      92 [-]: LOADN R24 0  
      93 [-]: LOADN R25 2  
      94 [-]: LOADN R26 0  
      95 [-]: CALL R23 3 1 
      96 [-]: ADD R22 R1 R23
      97 [-]: NAMECALL R20 R19 K27 [0x9E9C67CB]
      98 [-]: CALL R20 2 0 
      99 [-]: MOVE R22 R2  
     100 [-]: NAMECALL R20 R19 K28 [0x3273BA96]
     101 [-]: CALL R20 2 0 
     102 [-]: GETTABLE R20 R0 R9
     103 [-]: GETIMPORT R22 30 [nil]
     104 [-]: GETIMPORT R23 32 [nil]
     105 [-]: NAMECALL R20 R20 K26 [0x47901F07]
     106 [-]: CALL R20 3 0 
     107 [-]: FASTCALL1 62 R11 L10
     108 [-]: MOVE R21 R11 
     109 [-]: GETIMPORT R20 21 [nil]
     110 [-]: CALL R20 1 1 
L10: 111 [-]: JUMPIF R20 L11
     112 [-]: GETUPVAL R22 1
     113 [-]: LOADN R23 1  
     114 [-]: NAMECALL R20 R11 K33 [0xCA1E6AF9]
     115 [-]: CALL R20 3 0 
     116 [-]: GETUPVAL R22 2
     117 [-]: GETTABLEKS R23 R1 K34 ["x"]
     118 [-]: NAMECALL R20 R11 K33 [0xCA1E6AF9]
     119 [-]: CALL R20 3 0 
     120 [-]: GETUPVAL R22 3
     121 [-]: GETTABLEKS R24 R1 K36 ["y"]
     122 [-]: ADDK R23 R24 K35 [2]
     123 [-]: NAMECALL R20 R11 K33 [0xCA1E6AF9]
     124 [-]: CALL R20 3 0 
     125 [-]: GETUPVAL R22 4
     126 [-]: GETTABLEKS R23 R1 K37 ["z"]
     127 [-]: NAMECALL R20 R11 K33 [0xCA1E6AF9]
     128 [-]: CALL R20 3 0 
L11: 129 [-]: ADDK R5 R5 K38 [0.40000000000000002]
L12: 130 [-]: JUMPIF R13 L14
     131 [-]: GETUPVAL R14 5
     132 [-]: GETTABLE R15 R0 R9
     133 [-]: GETIMPORT R16 18 [nil]
     134 [-]: MOVE R17 R2  
     135 [-]: CALL R14 3 0 
     136 [-]: FASTCALL1 62 R11 L13
     137 [-]: MOVE R15 R11 
     138 [-]: GETIMPORT R14 21 [nil]
     139 [-]: CALL R14 1 1 
L13: 140 [-]: JUMPIF R14 L14
     141 [-]: GETUPVAL R16 1
     142 [-]: LOADN R17 0  
     143 [-]: NAMECALL R14 R11 K33 [0xCA1E6AF9]
     144 [-]: CALL R14 3 0 
L14: 145 [-]: FORNLOOP R7 L0
L15: 146 [-]: GETUPVAL R8 0
     147 [-]: SUB R7 R8 R4 
     148 [-]: JUMPIFNOTLT R7 R3 L16
     149 [-]: LOADB R6 1   
L16: 150 [-]: RETURN R5 2  


; Name:            
; Defined at line: 2504
; #Upvalues:       33
; #Parameters:     1
; Is_vararg:       0
; Max Stack Size:  61

L 0:   0 [-]: GETIMPORT R2 1 [nil]
       1 [-]: FASTCALL1 62 R2 L1
       2 [-]: GETIMPORT R1 3 [nil]
       3 [-]: CALL R1 1 1  
L 1:   4 [-]: JUMPIFNOT R1 L2
       5 [-]: GETIMPORT R1 5 [nil]
       6 [-]: LOADN R2 0   
       7 [-]: CALL R1 1 0  
       8 [-]: JUMPBACK L0  
L 2:   9 [-]: GETIMPORT R1 1 [nil]
      10 [-]: GETIMPORT R3 7 [nil]
      11 [-]: NAMECALL R1 R1 K8 [0xF2DEAF69]
      12 [-]: CALL R1 2 1  
      13 [-]: JUMPIF R1 L3 
      14 [-]: RETURN R0 0  
L 3:  15 [-]: GETIMPORT R1 1 [nil]
      16 [-]: NAMECALL R1 R1 K9 [0xEF893AEC]
      17 [-]: CALL R1 1 1  
      18 [-]: GETIMPORT R2 11 [nil]
      19 [-]: NAMECALL R2 R2 K12 [0x29EF273D]
      20 [-]: CALL R2 1 1  
      21 [-]: NAMECALL R2 R2 K13 [0x66905CB0]
      22 [-]: CALL R2 1 1  
      23 [-]: GETTABLEKS R3 R1 K14 ["goalTag"]
      24 [-]: LOADB R4 1   
      25 [-]: GETIMPORT R5 16 [nil]
      26 [-]: LOADK R6 K17 ["ShieldExcav"]
      27 [-]: CALL R5 1 1  
      28 [-]: JUMPIFEQ R3 R5 L5
      29 [-]: GETIMPORT R5 16 [nil]
      30 [-]: LOADK R6 K18 ["OldWorldSalvage"]
      31 [-]: CALL R5 1 1  
      32 [-]: JUMPIFEQ R3 R5 L4
      33 [-]: LOADB R4 0 +1
L 4:  34 [-]: LOADB R4 1   
L 5:  35 [-]: JUMPIFNOT R4 L8
      36 [-]: GETIMPORT R5 20 [nil]
      37 [-]: LOADK R6 K21 ["/Lotus/Fx/Gameplay/Excavation/ExcavationPillar"]
      38 [-]: CALL R5 1 1  
      39 [-]: LOADN R8 0   
      40 [-]: GETIMPORT R9 23 [nil]
      41 [-]: NAMECALL R6 R0 K24 [0xCDDC3ABB]
      42 [-]: CALL R6 3 0  
      43 [-]: MOVE R8 R5   
      44 [-]: NAMECALL R6 R0 K25 [0xC1595BD5]
      45 [-]: CALL R6 2 1  
      46 [-]: GETIMPORT R7 27 [nil]
      47 [-]: MOVE R8 R6   
      48 [-]: CALL R7 1 3  
      49 [-]: FORGPREP_INEXT R7 L7
L 6:  50 [-]: LOADN R14 0  
      51 [-]: GETIMPORT R15 29 [nil]
      52 [-]: NAMECALL R12 R11 K24 [0xCDDC3ABB]
      53 [-]: CALL R12 3 0 
L 7:  54 [-]: FORGLOOP R7 L6 2 [inext]
      55 [-]: GETIMPORT R9 31 [nil]
      56 [-]: GETIMPORT R10 33 [nil]
      57 [-]: NAMECALL R7 R0 K34 [0x47901F07]
      58 [-]: CALL R7 3 1  
      59 [-]: LOADK R10 K35 [0.59999999999999998]
      60 [-]: LOADB R11 1  
      61 [-]: NAMECALL R8 R7 K36 [0x2D9BA74F]
      62 [-]: CALL R8 3 0  
L 8:  63 [-]: GETUPVAL R6 0
      64 [-]: GETTABLEKS R5 R6 K37 [0xD342D13D]
      65 [-]: CALL R5 0 1  
      66 [-]: JUMPIF R5 L9 
      67 [-]: RETURN R0 0  
L 9:  68 [-]: GETUPVAL R5 1
      69 [-]: CALL R5 0 0  
      70 [-]: LOADN R5 20  
      71 [-]: LOADN R6 0   
      72 [-]: GETUPVAL R7 2
      73 [-]: LOADN R8 0   
      74 [-]: LOADB R9 0   
      75 [-]: GETTABLEKS R11 R1 K38 ["goalId"]
      76 [-]: JUMPXEQKS R11 K39 L10 NOT [""]
      77 [-]: LOADB R10 0 +1
L10:  78 [-]: LOADB R10 1  
L11:  79 [-]: GETTABLEKS R11 R1 K40 ["levelOverride"]
      80 [-]: LOADNIL R12  
      81 [-]: FASTCALL1 62 R11 L12
      82 [-]: MOVE R14 R11 
      83 [-]: GETIMPORT R13 3 [nil]
      84 [-]: CALL R13 1 1 
L12:  85 [-]: JUMPIF R13 L15
      86 [-]: JUMPIFNOT R10 L15
      87 [-]: NAMECALL R13 R11 K41 [0xED4E0128]
      88 [-]: CALL R13 1 1 
      89 [-]: MOVE R12 R13 
      90 [-]: GETIMPORT R13 44 [nil]
      91 [-]: MOVE R14 R12 
      92 [-]: LOADK R15 K45 ["Ice"]
      93 [-]: CALL R13 2 1 
      94 [-]: JUMPIFNOT R13 L13
      95 [-]: LOADN R13 3  
      96 [-]: SETUPVAL R13 3
      97 [-]: JUMP L15
    
L13:  98 [-]: GETIMPORT R13 44 [nil]
      99 [-]: MOVE R14 R12 
     100 [-]: LOADK R15 K46 ["Settlement"]
     101 [-]: CALL R13 2 1 
     102 [-]: JUMPIFNOT R13 L14
     103 [-]: GETIMPORT R13 44 [nil]
     104 [-]: GETIMPORT R14 48 [nil]
     105 [-]: GETTABLEKS R15 R1 K14 ["goalTag"]
     106 [-]: CALL R14 1 1 
     107 [-]: LOADK R15 K49 ["Anniversary"]
     108 [-]: CALL R13 2 1 
     109 [-]: JUMPIF R13 L14
     110 [-]: LOADN R13 2  
     111 [-]: SETUPVAL R13 3
     112 [-]: JUMP L15
    
L14: 113 [-]: LOADN R13 1  
     114 [-]: SETUPVAL R13 3
L15: 115 [-]: GETIMPORT R13 11 [nil]
     116 [-]: GETIMPORT R15 51 [nil]
     117 [-]: NAMECALL R13 R13 K52 [0xB0B2C5BF]
     118 [-]: CALL R13 2 1 
     119 [-]: GETIMPORT R14 54 [nil]
     120 [-]: LOADK R16 K55 ["Flushed "]
     121 [-]: MOVE R17 R13 
     122 [-]: LOADK R18 K56 [" inactive power cells."]
     123 [-]: CONCAT R15 R16 R18
     124 [-]: CALL R14 1 0 
     125 [-]: GETIMPORT R14 1 [nil]
     126 [-]: GETUPVAL R16 4
     127 [-]: LOADN R17 2  
     128 [-]: NAMECALL R14 R14 K57 [0x751F061D]
     129 [-]: CALL R14 3 0 
     130 [-]: GETIMPORT R14 1 [nil]
     131 [-]: GETUPVAL R16 5
     132 [-]: LOADN R17 0  
     133 [-]: NAMECALL R14 R14 K58 [0x0EB34C69]
     134 [-]: CALL R14 3 1 
     135 [-]: ADDK R14 R14 K59 [1]
     136 [-]: GETIMPORT R15 1 [nil]
     137 [-]: GETUPVAL R17 5
     138 [-]: MOVE R18 R14 
     139 [-]: NAMECALL R15 R15 K57 [0x751F061D]
     140 [-]: CALL R15 3 0 
     141 [-]: GETIMPORT R15 5 [nil]
     142 [-]: LOADK R16 K60 [0.10000000000000001]
     143 [-]: CALL R15 1 0 
     144 [-]: GETIMPORT R15 11 [nil]
     145 [-]: GETIMPORT R17 62 [nil]
     146 [-]: NAMECALL R18 R0 K63 [0xD1586535]
     147 [-]: CALL R18 1 1 
     148 [-]: LOADN R19 5  
     149 [-]: NAMECALL R15 R15 K64 [0x4E5939A5]
     150 [-]: CALL R15 4 1 
     151 [-]: FASTCALL1 62 R15 L16
     152 [-]: MOVE R17 R15 
     153 [-]: GETIMPORT R16 3 [nil]
     154 [-]: CALL R16 1 1 
L16: 155 [-]: JUMPIFNOT R16 L17
     156 [-]: GETIMPORT R18 66 [nil]
     157 [-]: LOADB R19 0  
     158 [-]: LOADN R20 2  
     159 [-]: LOADN R21 2  
     160 [-]: NAMECALL R16 R0 K67 [0x5D985C7E]
     161 [-]: CALL R16 5 0 
     162 [-]: RETURN R0 0  
L17: 163 [-]: MOVE R18 R0  
     164 [-]: NAMECALL R16 R2 K68 [0xE2871589]
     165 [-]: CALL R16 2 0 
     166 [-]: GETIMPORT R16 54 [nil]
     167 [-]: LOADK R18 K69 ["SetObjective "]
     168 [-]: NAMECALL R19 R0 K41 [0xED4E0128]
     169 [-]: CALL R19 1 1 
     170 [-]: CONCAT R17 R18 R19
     171 [-]: CALL R16 1 0 
     172 [-]: GETUPVAL R17 6
     173 [-]: GETTABLEKS R16 R17 K70 [0x9742B85B]
     174 [-]: GETIMPORT R17 73 [nil]
     175 [-]: GETIMPORT R18 16 [nil]
     176 [-]: LOADK R19 K74 ["MissionExcavatorDeployed"]
     177 [-]: CALL R18 1 -1
     178 [-]: CALL R16 -1 0
     179 [-]: GETIMPORT R18 66 [nil]
     180 [-]: LOADB R19 0  
     181 [-]: LOADN R20 2  
     182 [-]: LOADN R21 2  
     183 [-]: NAMECALL R16 R0 K67 [0x5D985C7E]
     184 [-]: CALL R16 5 0 
     185 [-]: LOADB R18 1  
     186 [-]: NAMECALL R16 R15 K75 [0x383D2E7D]
     187 [-]: CALL R16 2 0 
     188 [-]: MOVE R18 R0  
     189 [-]: NAMECALL R16 R15 K76 [0x00F85B37]
     190 [-]: CALL R16 2 0 
     191 [-]: MOVE R18 R14 
     192 [-]: NAMECALL R16 R15 K77 [0xD95ACD2C]
     193 [-]: CALL R16 2 0 
     194 [-]: GETIMPORT R18 79 [nil]
     195 [-]: NAMECALL R16 R0 K25 [0xC1595BD5]
     196 [-]: CALL R16 2 1 
     197 [-]: GETIMPORT R19 81 [nil]
     198 [-]: NAMECALL R17 R0 K25 [0xC1595BD5]
     199 [-]: CALL R17 2 1 
     200 [-]: GETIMPORT R20 83 [nil]
     201 [-]: NAMECALL R18 R0 K84 [0xC9F6A7D7]
     202 [-]: CALL R18 2 1 
     203 [-]: GETUPVAL R19 7
     204 [-]: MOVE R20 R18 
     205 [-]: MOVE R21 R16 
     206 [-]: MOVE R22 R17 
     207 [-]: LOADB R23 1  
     208 [-]: CALL R19 4 0 
     209 [-]: LOADB R19 1  
     210 [-]: NAMECALL R20 R0 K85 [0x1AC1655C]
     211 [-]: CALL R20 1 1 
     212 [-]: GETIMPORT R23 87 [nil]
     213 [-]: LENGTH R22 R23
     214 [-]: MOD R21 R14 R22
     215 [-]: JUMPXEQKN R21 K88 L18 NOT [0]
     216 [-]: GETIMPORT R22 87 [nil]
     217 [-]: LENGTH R21 R22
L18: 218 [-]: GETIMPORT R22 11 [nil]
     219 [-]: GETUPVAL R24 8
     220 [-]: NAMECALL R25 R0 K63 [0xD1586535]
     221 [-]: CALL R25 1 1 
     222 [-]: LOADN R26 0  
     223 [-]: LOADN R27 5  
     224 [-]: NAMECALL R22 R22 K89 [0x462C251C]
     225 [-]: CALL R22 5 1 
     226 [-]: FASTCALL1 62 R22 L19
     227 [-]: MOVE R24 R22 
     228 [-]: GETIMPORT R23 3 [nil]
     229 [-]: CALL R23 1 1 
L19: 230 [-]: JUMPIF R23 L20
     231 [-]: NAMECALL R23 R22 K90 [0xF4E253B6]
     232 [-]: CALL R23 1 0 
L20: 233 [-]: NAMECALL R23 R2 K91 [0x6968EA36]
     234 [-]: CALL R23 1 1 
     235 [-]: GETIMPORT R25 11 [nil]
     236 [-]: NAMECALL R25 R25 K92 [0x61BE252A]
     237 [-]: CALL R25 1 1 
     238 [-]: GETIMPORT R26 94 [nil]
     239 [-]: LOADK R28 K95 ["Server.NumVirtualTestClients"]
     240 [-]: NAMECALL R26 R26 K96 [0x8151451D]
     241 [-]: CALL R26 2 1 
     242 [-]: ADD R24 R25 R26
     243 [-]: GETIMPORT R25 98 [nil]
     244 [-]: JUMPXEQKN R24 K59 L21 NOT [1]
     245 [-]: GETIMPORT R25 100 [nil]
L21: 246 [-]: GETIMPORT R26 1 [nil]
     247 [-]: GETUPVAL R28 9
     248 [-]: LOADN R29 0  
     249 [-]: NAMECALL R26 R26 K58 [0x0EB34C69]
     250 [-]: CALL R26 3 1 
     251 [-]: GETIMPORT R27 102 [nil]
     252 [-]: LOADN R28 0  
     253 [-]: JUMPIFNOTLT R28 R26 L22
     254 [-]: MOVE R27 R26 
L22: 255 [-]: POW R29 R23 R25
     256 [-]: MUL R28 R27 R29
     257 [-]: GETIMPORT R30 104 [nil]
     258 [-]: POW R31 R23 R25
     259 [-]: MUL R29 R30 R31
     260 [-]: MOVE R32 R23 
     261 [-]: NAMECALL R30 R0 K105 [0x8623CF14]
     262 [-]: CALL R30 2 0 
     263 [-]: MOVE R32 R28 
     264 [-]: LOADB R33 1  
     265 [-]: NAMECALL R30 R0 K106 [0xA31BA7EE]
     266 [-]: CALL R30 3 0 
     267 [-]: NAMECALL R30 R0 K107 [0x2047CFE7]
     268 [-]: CALL R30 1 1 
     269 [-]: JUMPIF R30 L23
     270 [-]: NAMECALL R32 R0 K108 [0xB40C191A]
     271 [-]: CALL R32 1 1 
     272 [-]: LOADB R33 0  
     273 [-]: NAMECALL R30 R0 K109 [0x014DB014]
     274 [-]: CALL R30 3 0 
L23: 275 [-]: NAMECALL R30 R0 K85 [0x1AC1655C]
     276 [-]: CALL R30 1 1 
     277 [-]: MOVE R32 R29 
     278 [-]: NAMECALL R30 R30 K110 [0x7B1C3D01]
     279 [-]: CALL R30 2 0 
     280 [-]: NAMECALL R30 R0 K85 [0x1AC1655C]
     281 [-]: CALL R30 1 1 
     282 [-]: NAMECALL R32 R0 K85 [0x1AC1655C]
     283 [-]: CALL R32 1 1 
     284 [-]: NAMECALL R32 R32 K111 [0xB87F958D]
     285 [-]: CALL R32 1 -1
     286 [-]: NAMECALL R30 R30 K112 [0x57369B8B]
     287 [-]: CALL R30 -1 0
     288 [-]: GETIMPORT R30 114 [nil]
     289 [-]: LOADN R31 0  
     290 [-]: JUMPIFNOTLT R31 R30 L24
     291 [-]: NAMECALL R30 R0 K85 [0x1AC1655C]
     292 [-]: CALL R30 1 1 
     293 [-]: GETIMPORT R32 114 [nil]
     294 [-]: GETIMPORT R33 114 [nil]
     295 [-]: NAMECALL R30 R30 K115 [0x4A9DA24C]
     296 [-]: CALL R30 3 0 
L24: 297 [-]: GETIMPORT R33 87 [nil]
     298 [-]: GETTABLE R32 R33 R21
     299 [-]: GETIMPORT R33 33 [nil]
     300 [-]: GETIMPORT R34 117 [nil]
     301 [-]: LOADN R35 0  
     302 [-]: LOADK R36 K118 [1.5]
     303 [-]: LOADN R37 0  
     304 [-]: CALL R34 3 -1
     305 [-]: NAMECALL R30 R0 K34 [0x47901F07]
     306 [-]: CALL R30 -1 0
     307 [-]: GETIMPORT R30 119 [nil]
     308 [-]: GETIMPORT R31 1 [nil]
     309 [-]: GETUPVAL R33 10
     310 [-]: NAMECALL R31 R31 K120 [0xFFDDF768]
     311 [-]: CALL R31 2 1 
     312 [-]: SETTABLEKS R31 R30 K121 ["LastActivityTime"]
     313 [-]: GETUPVAL R31 11
     314 [-]: JUMPIFNOT R31 L27
     315 [-]: GETIMPORT R30 11 [nil]
     316 [-]: NAMECALL R30 R30 K122 [0x18D05D30]
     317 [-]: CALL R30 1 1 
     318 [-]: JUMPIFNOT R30 L28
     319 [-]: GETIMPORT R31 1 [nil]
     320 [-]: GETUPVAL R33 12
     321 [-]: LOADN R34 0  
     322 [-]: NAMECALL R31 R31 K58 [0x0EB34C69]
     323 [-]: CALL R31 3 1 
     324 [-]: JUMPXEQKN R31 K59 L25 [1]
     325 [-]: LOADB R30 0 +1
L25: 326 [-]: LOADB R30 1  
L26: 327 [-]: JUMP L28
    
L27: 328 [-]: GETIMPORT R30 124 [nil]
     329 [-]: JUMP L28
    
L28: 330 [-]: JUMPIFNOT R30 L29
     331 [-]: NAMECALL R30 R15 K125 [0x08E5889B]
     332 [-]: CALL R30 1 1 
     333 [-]: JUMPXEQKN R30 K88 L29 [0]
     334 [-]: MOVE R5 R30  
     335 [-]: NAMECALL R31 R15 K126 [0x17DD42BB]
     336 [-]: CALL R31 1 1 
     337 [-]: SUB R6 R7 R31
L29: 338 [-]: GETIMPORT R30 16 [nil]
     339 [-]: LOADK R32 K127 ["Excavator"]
     340 [-]: GETIMPORT R33 130 [nil]
     341 [-]: CALL R33 0 1 
     342 [-]: CONCAT R31 R32 R33
     343 [-]: CALL R30 1 1 
     344 [-]: LOADN R31 0  
     345 [-]: LOADB R32 0  
     346 [-]: LOADB R33 0  
     347 [-]: GETIMPORT R35 132 [nil]
     348 [-]: FASTCALL1 62 R35 L30
     349 [-]: GETIMPORT R34 3 [nil]
     350 [-]: CALL R34 1 1 
L30: 351 [-]: JUMPIFNOT R34 L31
     352 [-]: GETIMPORT R34 119 [nil]
     353 [-]: NEWTABLE R35 0 0
     354 [-]: SETTABLEKS R35 R34 K131 ["ExcavatorHealthTransmissionState"]
L31: 355 [-]: GETIMPORT R35 132 [nil]
     356 [-]: NAMECALL R36 R15 K133 [0xF329A790]
     357 [-]: CALL R36 1 1 
     358 [-]: DUPTABLE R37 136
     359 [-]: LOADB R38 0  
     360 [-]: SETTABLEKS R38 R37 K134 ["heavyDamage"]
     361 [-]: LOADB R38 0  
     362 [-]: SETTABLEKS R38 R37 K135 ["damaged"]
     363 [-]: FASTCALL 52 L32
     364 [-]: GETIMPORT R34 139 [nil]
     365 [-]: CALL R34 3 0 
L32: 366 [-]: FASTCALL1 62 R0 L33
     367 [-]: MOVE R35 R0  
     368 [-]: GETIMPORT R34 3 [nil]
     369 [-]: CALL R34 1 1 
L33: 370 [-]: JUMPIF R34 L65
     371 [-]: NAMECALL R34 R0 K107 [0x2047CFE7]
     372 [-]: CALL R34 1 1 
     373 [-]: JUMPIF R34 L65
     374 [-]: FASTCALL1 62 R15 L34
     375 [-]: MOVE R35 R15 
     376 [-]: GETIMPORT R34 3 [nil]
     377 [-]: CALL R34 1 1 
L34: 378 [-]: JUMPIF R34 L65
     379 [-]: GETIMPORT R34 11 [nil]
     380 [-]: NAMECALL R34 R34 K140 [0x8B5B1F58]
     381 [-]: CALL R34 1 1 
     382 [-]: NAMECALL R35 R0 K63 [0xD1586535]
     383 [-]: CALL R35 1 1 
     384 [-]: JUMPIFNOT R4 L39
     385 [-]: JUMPIF R32 L55
     386 [-]: LOADK R36 K141 [0.20000000000000001]
     387 [-]: JUMPIFNOTLT R36 R31 L36
     388 [-]: LOADN R36 0  
     389 [-]: GETUPVAL R37 13
     390 [-]: MOVE R38 R34 
     391 [-]: MOVE R39 R35 
     392 [-]: MOVE R40 R30 
     393 [-]: MOVE R41 R5  
     394 [-]: MOVE R42 R6  
     395 [-]: CALL R37 5 2 
     396 [-]: MOVE R36 R37 
     397 [-]: MOVE R32 R38 
     398 [-]: ADD R38 R5 R36
     399 [-]: GETUPVAL R39 2
     400 [-]: FASTCALL2 19 R38 R39 L35
     401 [-]: GETIMPORT R37 143 [nil]
     402 [-]: CALL R37 2 1 
L35: 403 [-]: MOVE R5 R37  
     404 [-]: LOADN R31 0  
     405 [-]: JUMP L37
    
L36: 406 [-]: GETIMPORT R36 145 [nil]
     407 [-]: CALL R36 0 1 
     408 [-]: ADD R31 R31 R36
L37: 409 [-]: JUMPIFNOT R32 L55
     410 [-]: GETIMPORT R38 31 [nil]
     411 [-]: NAMECALL R36 R0 K84 [0xC9F6A7D7]
     412 [-]: CALL R36 2 1 
     413 [-]: FASTCALL1 62 R36 L38
     414 [-]: MOVE R38 R36 
     415 [-]: GETIMPORT R37 3 [nil]
     416 [-]: CALL R37 1 1 
L38: 417 [-]: JUMPIF R37 L55
     418 [-]: NAMECALL R37 R36 K146 [0xA2880940]
     419 [-]: CALL R37 1 0 
     420 [-]: JUMP L55
    
L39: 421 [-]: GETUPVAL R37 14
     422 [-]: GETTABLEKS R36 R37 K147 [0x74A11EC6]
     423 [-]: NAMECALL R37 R15 K125 [0x08E5889B]
     424 [-]: CALL R37 1 -1
     425 [-]: CALL R36 -1 1
     426 [-]: NAMECALL R38 R15 K126 [0x17DD42BB]
     427 [-]: CALL R38 1 1 
     428 [-]: FASTCALL1 12 R38 L40
     429 [-]: GETIMPORT R37 149 [nil]
     430 [-]: CALL R37 1 1 
L40: 431 [-]: NAMECALL R38 R20 K150 [0xF456C2D7]
     432 [-]: CALL R38 1 1 
     433 [-]: NAMECALL R39 R20 K111 [0xB87F958D]
     434 [-]: CALL R39 1 1 
     435 [-]: JUMPIFLT R36 R37 L41
     436 [-]: JUMPIFNOTLT R38 R39 L53
L41: 437 [-]: GETIMPORT R40 27 [nil]
     438 [-]: MOVE R41 R34 
     439 [-]: CALL R40 1 3 
     440 [-]: FORGPREP_INEXT R40 L52
L42: 441 [-]: GETIMPORT R48 152 [nil]
     442 [-]: NAMECALL R46 R44 K8 [0xF2DEAF69]
     443 [-]: CALL R46 2 1 
     444 [-]: JUMPIFNOT R46 L43
     445 [-]: NAMECALL R46 R44 K153 [0xB0E8475C]
     446 [-]: CALL R46 1 1 
     447 [-]: JUMPIFNOT R46 L43
     448 [-]: NAMECALL R46 R44 K154 [0xFF005826]
     449 [-]: CALL R46 1 1 
     450 [-]: JUMPIFNOT R46 L43
     451 [-]: NAMECALL R45 R44 K154 [0xFF005826]
     452 [-]: CALL R45 1 1 
     453 [-]: JUMP L44
    
L43: 454 [-]: MOVE R45 R44 
L44: 455 [-]: GETIMPORT R48 156 [nil]
     456 [-]: NAMECALL R46 R45 K157 [0x0866B4BD]
     457 [-]: CALL R46 2 1 
     458 [-]: JUMPIFNOT R46 L52
     459 [-]: MOVE R49 R35 
     460 [-]: NAMECALL R47 R44 K158 [0x1F420A3A]
     461 [-]: CALL R47 2 1 
     462 [-]: LOADN R48 5  
     463 [-]: JUMPIFLT R47 R48 L45
     464 [-]: LOADB R46 0 +1
L45: 465 [-]: LOADB R46 1  
L46: 466 [-]: JUMPIFNOT R46 L52
     467 [-]: NAMECALL R47 R44 K159 [0x5E651723]
     468 [-]: CALL R47 1 1 
     469 [-]: NAMECALL R48 R45 K160 [0xDE321E6F]
     470 [-]: CALL R48 1 1 
     471 [-]: NAMECALL R48 R48 K161 [0xC9CDF64D]
     472 [-]: CALL R48 1 1 
     473 [-]: GETUPVAL R50 14
     474 [-]: GETTABLEKS R49 R50 K147 [0x74A11EC6]
     475 [-]: LOADN R52 20 
     476 [-]: MUL R51 R52 R48
     477 [-]: GETUPVAL R53 2
     478 [-]: SUB R52 R53 R5
     479 [-]: FASTCALL2 19 R51 R52 L47
     480 [-]: GETIMPORT R50 143 [nil]
     481 [-]: CALL R50 2 1 
L47: 482 [-]: CALL R49 1 1 
     483 [-]: GETIMPORT R50 1 [nil]
     484 [-]: MOVE R52 R47 
     485 [-]: LOADK R53 K162 ["/Lotus/Language/Game/GainedPower"]
     486 [-]: LOADK R54 K39 [""]
     487 [-]: LOADN R55 0  
     488 [-]: LOADN R56 2  
     489 [-]: LOADB R57 1  
     490 [-]: LOADK R58 K163 ["AMOUNT"]
     491 [-]: GETIMPORT R59 48 [nil]
     492 [-]: MOVE R60 R49 
     493 [-]: CALL R59 1 -1
     494 [-]: NAMECALL R50 R50 K164 [0x06D4C9EB]
     495 [-]: CALL R50 -1 0
     496 [-]: ADD R5 R5 R49
     497 [-]: GETIMPORT R52 156 [nil]
     498 [-]: NAMECALL R50 R45 K165 [0x35B09371]
     499 [-]: CALL R50 2 0 
     500 [-]: GETIMPORT R52 167 [nil]
     501 [-]: LOADB R53 0  
     502 [-]: NAMECALL R50 R44 K168 [0x659D451F]
     503 [-]: CALL R50 3 0 
     504 [-]: GETIMPORT R50 119 [nil]
     505 [-]: GETIMPORT R51 1 [nil]
     506 [-]: GETUPVAL R53 10
     507 [-]: NAMECALL R51 R51 K120 [0xFFDDF768]
     508 [-]: CALL R51 2 1 
     509 [-]: SETTABLEKS R51 R50 K121 ["LastActivityTime"]
     510 [-]: FASTCALL1 62 R47 L48
     511 [-]: MOVE R51 R47 
     512 [-]: GETIMPORT R50 3 [nil]
     513 [-]: CALL R50 1 1 
L48: 514 [-]: JUMPIF R50 L50
     515 [-]: NAMECALL R50 R47 K169 [0x61C34FA9]
     516 [-]: CALL R50 1 1 
     517 [-]: FASTCALL1 62 R50 L49
     518 [-]: MOVE R52 R50 
     519 [-]: GETIMPORT R51 3 [nil]
     520 [-]: CALL R51 1 1 
L49: 521 [-]: JUMPIF R51 L50
     522 [-]: NAMECALL R51 R50 K170 [0xA44E757A]
     523 [-]: CALL R51 1 0 
L50: 524 [-]: JUMPIFNOTLT R38 R39 L51
     525 [-]: GETIMPORT R52 172 [nil]
     526 [-]: NAMECALL R50 R0 K173 [0x0542D42B]
     527 [-]: CALL R50 2 1 
     528 [-]: JUMPIF R50 L51
     529 [-]: GETIMPORT R52 172 [nil]
     530 [-]: GETIMPORT R53 33 [nil]
     531 [-]: NAMECALL R50 R0 K34 [0x47901F07]
     532 [-]: CALL R50 3 0 
L51: 533 [-]: MOVE R52 R39 
     534 [-]: NAMECALL R50 R20 K112 [0x57369B8B]
     535 [-]: CALL R50 2 0 
     536 [-]: GETIMPORT R52 175 [nil]
     537 [-]: NAMECALL R50 R44 K173 [0x0542D42B]
     538 [-]: CALL R50 2 1 
     539 [-]: JUMPIF R50 L52
     540 [-]: NAMECALL R50 R44 K85 [0x1AC1655C]
     541 [-]: CALL R50 1 1 
     542 [-]: LOADN R53 0  
     543 [-]: NAMECALL R51 R50 K176 [0x9EB6D632]
     544 [-]: CALL R51 2 1 
     545 [-]: GETIMPORT R54 175 [nil]
     546 [-]: MOVE R55 R51 
     547 [-]: NAMECALL R52 R44 K34 [0x47901F07]
     548 [-]: CALL R52 3 0 
L52: 549 [-]: FORGLOOP R40 L42 2 [inext]
L53: 550 [-]: NAMECALL R40 R0 K177 [0xC8442850]
     551 [-]: CALL R40 1 1 
     552 [-]: GETIMPORT R42 132 [nil]
     553 [-]: NAMECALL R43 R15 K133 [0xF329A790]
     554 [-]: CALL R43 1 1 
     555 [-]: GETTABLE R41 R42 R43
     556 [-]: LOADK R42 K178 [0.25]
     557 [-]: JUMPIFNOTLE R40 R42 L54
     558 [-]: GETTABLEKS R42 R41 K134 ["heavyDamage"]
     559 [-]: JUMPIF R42 L54
     560 [-]: GETUPVAL R43 6
     561 [-]: GETTABLEKS R42 R43 K70 [0x9742B85B]
     562 [-]: GETIMPORT R43 73 [nil]
     563 [-]: GETIMPORT R44 16 [nil]
     564 [-]: LOADK R45 K179 ["MissionExcavatorHeavyDamaged"]
     565 [-]: CALL R44 1 -1
     566 [-]: CALL R42 -1 0
     567 [-]: LOADB R42 1  
     568 [-]: SETTABLEKS R42 R41 K134 ["heavyDamage"]
     569 [-]: JUMP L55
    
L54: 570 [-]: LOADK R42 K180 [0.75]
     571 [-]: JUMPIFNOTLE R40 R42 L55
     572 [-]: GETTABLEKS R42 R41 K135 ["damaged"]
     573 [-]: JUMPIF R42 L55
     574 [-]: GETUPVAL R43 6
     575 [-]: GETTABLEKS R42 R43 K70 [0x9742B85B]
     576 [-]: GETIMPORT R43 73 [nil]
     577 [-]: GETIMPORT R44 16 [nil]
     578 [-]: LOADK R45 K181 ["MissionExcavatorDamaged"]
     579 [-]: CALL R44 1 -1
     580 [-]: CALL R42 -1 0
     581 [-]: LOADB R42 1  
     582 [-]: SETTABLEKS R42 R41 K135 ["damaged"]
L55: 583 [-]: LOADN R36 0  
     584 [-]: JUMPIFNOTLE R5 R36 L58
     585 [-]: JUMPIFNOT R19 L58
     586 [-]: GETUPVAL R36 7
     587 [-]: MOVE R37 R18 
     588 [-]: MOVE R38 R16 
     589 [-]: MOVE R39 R17 
     590 [-]: LOADB R40 0  
     591 [-]: CALL R36 4 0 
     592 [-]: LOADB R19 0  
     593 [-]: LOADB R33 1  
     594 [-]: LOADNIL R38  
     595 [-]: LOADB R39 0  
     596 [-]: LOADN R40 2  
     597 [-]: LOADN R41 2  
     598 [-]: NAMECALL R36 R0 K67 [0x5D985C7E]
     599 [-]: CALL R36 5 0 
     600 [-]: JUMPIFNOT R4 L56
     601 [-]: GETUPVAL R37 6
     602 [-]: GETTABLEKS R36 R37 K70 [0x9742B85B]
     603 [-]: GETIMPORT R37 73 [nil]
     604 [-]: GETIMPORT R38 16 [nil]
     605 [-]: LOADK R39 K182 ["MissionExcavatorUnpoweredShield"]
     606 [-]: CALL R38 1 -1
     607 [-]: CALL R36 -1 0
     608 [-]: JUMP L57
    
L56: 609 [-]: GETUPVAL R37 6
     610 [-]: GETTABLEKS R36 R37 K70 [0x9742B85B]
     611 [-]: GETIMPORT R37 73 [nil]
     612 [-]: GETIMPORT R38 16 [nil]
     613 [-]: LOADK R39 K183 ["MissionExcavatorUnpowered"]
     614 [-]: CALL R38 1 -1
     615 [-]: CALL R36 -1 0
L57: 616 [-]: MOVE R38 R0  
     617 [-]: NAMECALL R36 R2 K68 [0xE2871589]
     618 [-]: CALL R36 2 0 
     619 [-]: JUMP L59
    
L58: 620 [-]: LOADN R36 0  
     621 [-]: JUMPIFNOTLT R36 R5 L59
     622 [-]: JUMPIF R19 L59
     623 [-]: GETUPVAL R36 7
     624 [-]: MOVE R37 R18 
     625 [-]: MOVE R38 R16 
     626 [-]: MOVE R39 R17 
     627 [-]: LOADB R40 1  
     628 [-]: CALL R36 4 0 
     629 [-]: LOADB R19 1  
     630 [-]: GETIMPORT R38 66 [nil]
     631 [-]: LOADB R39 0  
     632 [-]: LOADN R40 2  
     633 [-]: LOADN R41 2  
     634 [-]: NAMECALL R36 R0 K67 [0x5D985C7E]
     635 [-]: CALL R36 5 0 
L59: 636 [-]: GETIMPORT R36 145 [nil]
     637 [-]: CALL R36 0 1 
     638 [-]: LOADN R37 0  
     639 [-]: JUMPIFNOTLT R37 R5 L60
     640 [-]: ADD R6 R6 R36
L60: 641 [-]: MULK R39 R36 K59 [1]
     642 [-]: SUB R38 R5 R39
     643 [-]: FASTCALL2K 18 R38 K88 L61 [0]
     644 [-]: LOADK R39 K88 [0]
     645 [-]: GETIMPORT R37 185 [nil]
     646 [-]: CALL R37 2 1 
L61: 647 [-]: MOVE R5 R37  
     648 [-]: ADDK R37 R6 K186 [0.050000000000000003]
     649 [-]: JUMPIFNOTLE R7 R37 L62
     650 [-]: LOADB R9 1   
     651 [-]: JUMP L65
    
L62: 652 [-]: FASTCALL1 62 R15 L63
     653 [-]: MOVE R38 R15 
     654 [-]: GETIMPORT R37 3 [nil]
     655 [-]: CALL R37 1 1 
L63: 656 [-]: JUMPIF R37 L64
     657 [-]: MOVE R39 R5  
     658 [-]: NAMECALL R37 R15 K187 [0x8061B6D7]
     659 [-]: CALL R37 2 0 
     660 [-]: SUB R39 R7 R6
     661 [-]: NAMECALL R37 R15 K188 [0x2F5F5657]
     662 [-]: CALL R37 2 0 
L64: 663 [-]: GETIMPORT R37 5 [nil]
     664 [-]: LOADN R38 0  
     665 [-]: CALL R37 1 0 
     666 [-]: JUMPBACK L32 
L65: 667 [-]: GETIMPORT R34 1 [nil]
     668 [-]: GETUPVAL R36 15
     669 [-]: LOADN R37 0  
     670 [-]: NAMECALL R34 R34 K58 [0x0EB34C69]
     671 [-]: CALL R34 3 1 
     672 [-]: ADDK R34 R34 K59 [1]
     673 [-]: GETIMPORT R35 1 [nil]
     674 [-]: GETUPVAL R37 15
     675 [-]: MOVE R38 R34 
     676 [-]: NAMECALL R35 R35 K57 [0x751F061D]
     677 [-]: CALL R35 3 0 
     678 [-]: GETIMPORT R35 1 [nil]
     679 [-]: GETUPVAL R37 16
     680 [-]: LOADN R38 0  
     681 [-]: NAMECALL R35 R35 K58 [0x0EB34C69]
     682 [-]: CALL R35 3 1 
     683 [-]: JUMPIFNOT R9 L66
     684 [-]: GETUPVAL R8 17
     685 [-]: GETIMPORT R36 1 [nil]
     686 [-]: GETUPVAL R38 18
     687 [-]: LOADN R39 0  
     688 [-]: NAMECALL R36 R36 K58 [0x0EB34C69]
     689 [-]: CALL R36 3 1 
     690 [-]: GETIMPORT R37 1 [nil]
     691 [-]: GETUPVAL R39 19
     692 [-]: MOVE R40 R36 
     693 [-]: NAMECALL R37 R37 K57 [0x751F061D]
     694 [-]: CALL R37 3 0 
     695 [-]: ADDK R35 R35 K59 [1]
     696 [-]: GETIMPORT R37 1 [nil]
     697 [-]: GETUPVAL R39 16
     698 [-]: MOVE R40 R35 
     699 [-]: NAMECALL R37 R37 K57 [0x751F061D]
     700 [-]: CALL R37 3 0 
     701 [-]: JUMPIF R33 L67
     702 [-]: GETIMPORT R37 190 [nil]
     703 [-]: GETIMPORT R39 16 [nil]
     704 [-]: LOADK R40 K191 ["EXCAVATION_COMPLETED_WITHOUT_LOSING_POWER"]
     705 [-]: CALL R39 1 -1
     706 [-]: NAMECALL R37 R37 K192 [0x78BD21C8]
     707 [-]: CALL R37 -1 0
     708 [-]: JUMP L67
    
L66: 709 [-]: GETUPVAL R37 14
     710 [-]: GETTABLEKS R36 R37 K147 [0x74A11EC6]
     711 [-]: GETUPVAL R38 17
     712 [-]: DIV R39 R6 R7
     713 [-]: MUL R37 R38 R39
     714 [-]: CALL R36 1 1 
     715 [-]: MOVE R8 R36  
     716 [-]: GETUPVAL R37 6
     717 [-]: GETTABLEKS R36 R37 K70 [0x9742B85B]
     718 [-]: GETIMPORT R37 73 [nil]
     719 [-]: GETIMPORT R38 16 [nil]
     720 [-]: LOADK R39 K193 ["MissionExcavatorDestroyed"]
     721 [-]: CALL R38 1 -1
     722 [-]: CALL R36 -1 0
L67: 723 [-]: JUMPIFNOT R4 L70
     724 [-]: GETIMPORT R36 11 [nil]
     725 [-]: NAMECALL R36 R36 K140 [0x8B5B1F58]
     726 [-]: CALL R36 1 1 
     727 [-]: GETIMPORT R37 27 [nil]
     728 [-]: MOVE R38 R36 
     729 [-]: CALL R37 1 3 
     730 [-]: FORGPREP_INEXT R37 L69
L68: 731 [-]: GETUPVAL R42 20
     732 [-]: MOVE R43 R41 
     733 [-]: GETIMPORT R44 195 [nil]
     734 [-]: MOVE R45 R30 
     735 [-]: CALL R42 3 0 
L69: 736 [-]: FORGLOOP R37 L68 2 [inext]
L70: 737 [-]: FASTCALL2K 18 R8 K59 L71 [1]
     738 [-]: MOVE R37 R8  
     739 [-]: LOADK R38 K59 [1]
     740 [-]: GETIMPORT R36 185 [nil]
     741 [-]: CALL R36 2 1 
L71: 742 [-]: MOVE R8 R36  
     743 [-]: GETIMPORT R36 1 [nil]
     744 [-]: GETUPVAL R38 21
     745 [-]: LOADN R39 0  
     746 [-]: NAMECALL R36 R36 K58 [0x0EB34C69]
     747 [-]: CALL R36 3 1 
     748 [-]: ADD R36 R36 R8
     749 [-]: GETIMPORT R37 1 [nil]
     750 [-]: GETUPVAL R39 21
     751 [-]: MOVE R40 R36 
     752 [-]: NAMECALL R37 R37 K57 [0x751F061D]
     753 [-]: CALL R37 3 0 
     754 [-]: GETIMPORT R37 1 [nil]
     755 [-]: GETUPVAL R39 22
     756 [-]: LOADN R40 0  
     757 [-]: NAMECALL R37 R37 K58 [0x0EB34C69]
     758 [-]: CALL R37 3 1 
     759 [-]: GETUPVAL R39 3
     760 [-]: MUL R38 R8 R39
     761 [-]: ADD R37 R37 R38
     762 [-]: GETIMPORT R38 1 [nil]
     763 [-]: GETUPVAL R40 22
     764 [-]: MOVE R41 R37 
     765 [-]: NAMECALL R38 R38 K57 [0x751F061D]
     766 [-]: CALL R38 3 0 
     767 [-]: LOADN R38 500
     768 [-]: GETUPVAL R39 23
     769 [-]: JUMPIF R39 L72
     770 [-]: GETTABLEKS R39 R1 K196 ["maxWaveNum"]
L72: 771 [-]: LOADN R40 0  
     772 [-]: JUMPIFNOTLT R40 R39 L73
     773 [-]: GETUPVAL R40 17
     774 [-]: MUL R38 R39 R40
L73: 775 [-]: GETIMPORT R41 198 [nil]
     776 [-]: FASTCALL1 62 R41 L74
     777 [-]: GETIMPORT R40 3 [nil]
     778 [-]: CALL R40 1 1 
L74: 779 [-]: JUMPIFNOT R40 L75
     780 [-]: GETIMPORT R40 119 [nil]
     781 [-]: LOADB R41 0  
     782 [-]: SETTABLEKS R41 R40 K197 ["HasPlayedHalfwayTransmission"]
L75: 783 [-]: DIVK R40 R38 K199 [2]
     784 [-]: JUMPIFNOTLT R40 R37 L76
     785 [-]: GETIMPORT R40 198 [nil]
     786 [-]: JUMPIF R40 L76
     787 [-]: GETIMPORT R40 119 [nil]
     788 [-]: LOADB R41 1  
     789 [-]: SETTABLEKS R41 R40 K197 ["HasPlayedHalfwayTransmission"]
     790 [-]: GETUPVAL R41 6
     791 [-]: GETTABLEKS R40 R41 K70 [0x9742B85B]
     792 [-]: GETIMPORT R41 73 [nil]
     793 [-]: GETIMPORT R42 16 [nil]
     794 [-]: LOADK R43 K200 ["MissionHalfway"]
     795 [-]: CALL R42 1 -1
     796 [-]: CALL R40 -1 0
L76: 797 [-]: GETUPVAL R40 24
     798 [-]: JUMPIFNOT R40 L77
     799 [-]: GETIMPORT R40 119 [nil]
     800 [-]: LOADB R41 1  
     801 [-]: SETTABLEKS R41 R40 K201 ["extractionAvailable"]
     802 [-]: JUMP L94
    
L77: 803 [-]: GETUPVAL R40 25
     804 [-]: JUMPIFNOT R40 L83
     805 [-]: LOADB R40 0  
     806 [-]: GETUPVAL R41 26
     807 [-]: CALL R41 0 1 
     808 [-]: JUMPIFNOT R41 L80
     809 [-]: LOADB R42 0  
     810 [-]: JUMPIFNOTLE R39 R34 L79
     811 [-]: LOADN R43 0  
     812 [-]: JUMPIFLT R43 R35 L78
     813 [-]: LOADB R42 0 +1
L78: 814 [-]: LOADB R42 1  
L79: 815 [-]: MOVE R40 R42 
     816 [-]: JUMP L82
    
L80: 817 [-]: JUMPIFLE R39 R34 L81
     818 [-]: LOADB R40 0 +1
L81: 819 [-]: LOADB R40 1  
L82: 820 [-]: GETIMPORT R42 119 [nil]
     821 [-]: SETTABLEKS R40 R42 K201 ["extractionAvailable"]
     822 [-]: JUMP L94
    
L83: 823 [-]: GETUPVAL R40 27
     824 [-]: JUMPIFNOT R40 L86
     825 [-]: GETIMPORT R40 119 [nil]
     826 [-]: JUMPIFLE R38 R36 L84
     827 [-]: LOADB R41 0 +1
L84: 828 [-]: LOADB R41 1  
L85: 829 [-]: SETTABLEKS R41 R40 K201 ["extractionAvailable"]
     830 [-]: JUMP L94
    
L86: 831 [-]: GETUPVAL R40 28
     832 [-]: JUMPIFNOT R40 L89
     833 [-]: GETIMPORT R40 119 [nil]
     834 [-]: LOADB R41 0  
     835 [-]: LOADN R42 200
     836 [-]: JUMPIFNOTLE R42 R37 L88
     837 [-]: LOADN R42 0  
     838 [-]: JUMPIFLT R42 R35 L87
     839 [-]: LOADB R41 0 +1
L87: 840 [-]: LOADB R41 1  
L88: 841 [-]: SETTABLEKS R41 R40 K201 ["extractionAvailable"]
     842 [-]: JUMP L94
    
L89: 843 [-]: JUMPIFNOT R9 L94
     844 [-]: GETIMPORT R40 119 [nil]
     845 [-]: LOADB R42 1  
     846 [-]: GETIMPORT R44 1 [nil]
     847 [-]: NAMECALL R44 R44 K9 [0xEF893AEC]
     848 [-]: CALL R44 1 1 
     849 [-]: GETTABLEKS R43 R44 K202 ["periodicMissionTag"]
     850 [-]: GETUPVAL R45 0
     851 [-]: GETTABLEKS R44 R45 K203 ["ELITE_ALERT_PERIODIC_MISSION_TAG"]
     852 [-]: JUMPIFEQ R43 R44 L91
     853 [-]: GETIMPORT R44 1 [nil]
     854 [-]: NAMECALL R44 R44 K9 [0xEF893AEC]
     855 [-]: CALL R44 1 1 
     856 [-]: GETTABLEKS R43 R44 K202 ["periodicMissionTag"]
     857 [-]: GETUPVAL R45 0
     858 [-]: GETTABLEKS R44 R45 K204 ["ELITE_ALERT_PERIODIC_MISSION_TAG_ALT"]
     859 [-]: JUMPIFEQ R43 R44 L90
     860 [-]: LOADB R42 0 +1
L90: 861 [-]: LOADB R42 1  
L91: 862 [-]: NOT R41 R42  
     863 [-]: JUMPIF R41 L93
     864 [-]: LOADN R42 1  
     865 [-]: JUMPIFLT R42 R35 L92
     866 [-]: LOADB R41 0 +1
L92: 867 [-]: LOADB R41 1  
L93: 868 [-]: SETTABLEKS R41 R40 K201 ["extractionAvailable"]
L94: 869 [-]: LOADN R40 0  
     870 [-]: JUMPIFNOTLT R40 R8 L97
     871 [-]: GETUPVAL R43 3
     872 [-]: MUL R42 R8 R43
     873 [-]: MULK R41 R42 K59 [1]
     874 [-]: FASTCALL2K 18 R41 K59 L95 [1]
     875 [-]: LOADK R42 K59 [1]
     876 [-]: GETIMPORT R40 185 [nil]
     877 [-]: CALL R40 2 1 
L95: 878 [-]: GETUPVAL R41 29
     879 [-]: GETUPVAL R43 14
     880 [-]: GETTABLEKS R42 R43 K205 [0x06D055F9]
     881 [-]: GETUPVAL R43 25
     882 [-]: GETIMPORT R44 207 [nil]
     883 [-]: GETIMPORT R45 209 [nil]
     884 [-]: CALL R42 3 1 
     885 [-]: MOVE R43 R40 
     886 [-]: CALL R41 2 0 
     887 [-]: GETUPVAL R42 14
     888 [-]: GETTABLEKS R41 R42 K205 [0x06D055F9]
     889 [-]: GETUPVAL R42 25
     890 [-]: LOADK R43 K210 ["/Lotus/Language/Game/GainedOldWorldSalvage"]
     891 [-]: LOADK R44 K211 ["/Lotus/Language/Game/GainedCryotic"]
     892 [-]: CALL R41 3 1 
     893 [-]: GETIMPORT R42 11 [nil]
     894 [-]: NAMECALL R42 R42 K140 [0x8B5B1F58]
     895 [-]: CALL R42 1 1 
     896 [-]: LOADN R45 1  
     897 [-]: LENGTH R43 R42
     898 [-]: LOADN R44 1  
     899 [-]: FORNPREP R43 L97
L96: 900 [-]: GETIMPORT R46 1 [nil]
     901 [-]: GETTABLE R48 R42 R45
     902 [-]: NAMECALL R48 R48 K159 [0x5E651723]
     903 [-]: CALL R48 1 1 
     904 [-]: MOVE R49 R41 
     905 [-]: LOADK R50 K39 [""]
     906 [-]: LOADN R51 0  
     907 [-]: LOADN R52 2  
     908 [-]: LOADB R53 1  
     909 [-]: LOADK R54 K163 ["AMOUNT"]
     910 [-]: GETIMPORT R55 48 [nil]
     911 [-]: MOVE R56 R40 
     912 [-]: CALL R55 1 -1
     913 [-]: NAMECALL R46 R46 K164 [0x06D4C9EB]
     914 [-]: CALL R46 -1 0
     915 [-]: FORNLOOP R43 L96
L97: 916 [-]: JUMPIFNOT R9 L107
     917 [-]: GETUPVAL R40 27
     918 [-]: JUMPIFNOT R40 L98
     919 [-]: GETUPVAL R40 25
     920 [-]: JUMPIFNOT R40 L107
L98: 921 [-]: LOADB R40 1  
     922 [-]: GETIMPORT R42 1 [nil]
     923 [-]: NAMECALL R42 R42 K9 [0xEF893AEC]
     924 [-]: CALL R42 1 1 
     925 [-]: GETTABLEKS R41 R42 K202 ["periodicMissionTag"]
     926 [-]: GETUPVAL R43 0
     927 [-]: GETTABLEKS R42 R43 K203 ["ELITE_ALERT_PERIODIC_MISSION_TAG"]
     928 [-]: JUMPIFEQ R41 R42 L100
     929 [-]: GETIMPORT R42 1 [nil]
     930 [-]: NAMECALL R42 R42 K9 [0xEF893AEC]
     931 [-]: CALL R42 1 1 
     932 [-]: GETTABLEKS R41 R42 K202 ["periodicMissionTag"]
     933 [-]: GETUPVAL R43 0
     934 [-]: GETTABLEKS R42 R43 K204 ["ELITE_ALERT_PERIODIC_MISSION_TAG_ALT"]
     935 [-]: JUMPIFEQ R41 R42 L99
     936 [-]: LOADB R40 0 +1
L99: 937 [-]: LOADB R40 1  
L100: 938 [-]: JUMPIFNOT R40 L101
     939 [-]: MODK R40 R35 K199 [2]
     940 [-]: JUMPXEQKN R40 K88 L107 NOT [0]
L101: 941 [-]: GETUPVAL R40 30
     942 [-]: CALL R40 0 0 
     943 [-]: GETUPVAL R40 31
     944 [-]: GETIMPORT R42 213 [nil]
     945 [-]: FASTCALL1 62 R42 L102
     946 [-]: GETIMPORT R41 3 [nil]
     947 [-]: CALL R41 1 1 
L102: 948 [-]: JUMPIF R41 L103
     949 [-]: GETIMPORT R41 44 [nil]
     950 [-]: GETIMPORT R42 213 [nil]
     951 [-]: NAMECALL R42 R42 K214 [0xD3A9D01F]
     952 [-]: CALL R42 1 1 
     953 [-]: NAMECALL R42 R42 K215 [0x6D604BA7]
     954 [-]: CALL R42 1 1 
     955 [-]: LOADK R43 K216 ["Rusty"]
     956 [-]: CALL R41 2 1 
     957 [-]: JUMPXEQKNIL R41 L103
     958 [-]: GETIMPORT R41 16 [nil]
     959 [-]: LOADK R42 K217 ["MissionExcavatorPistolFound"]
     960 [-]: CALL R41 1 1 
     961 [-]: MOVE R40 R41 
     962 [-]: GETIMPORT R41 1 [nil]
     963 [-]: GETUPVAL R43 32
     964 [-]: LOADN R44 1  
     965 [-]: NAMECALL R41 R41 K57 [0x751F061D]
     966 [-]: CALL R41 3 0 
L103: 967 [-]: GETUPVAL R41 25
     968 [-]: JUMPIFNOT R41 L106
     969 [-]: GETIMPORT R41 11 [nil]
     970 [-]: NAMECALL R41 R41 K218 [0x7D108DDB]
     971 [-]: CALL R41 1 1 
     972 [-]: LOADN R44 1  
     973 [-]: LENGTH R42 R41
     974 [-]: LOADN R43 1  
     975 [-]: FORNPREP R42 L107
L104: 976 [-]: GETUPVAL R46 0
     977 [-]: GETTABLEKS R45 R46 K219 [0x56B5886E]
     978 [-]: GETTABLE R46 R41 R44
     979 [-]: CALL R45 1 1 
     980 [-]: JUMPIFNOT R45 L105
     981 [-]: GETUPVAL R40 31
     982 [-]: JUMPXEQKN R35 K59 L105 NOT [1]
     983 [-]: GETIMPORT R45 16 [nil]
     984 [-]: LOADK R46 K220 ["MissionExcavatorFirstPistolFound"]
     985 [-]: CALL R45 1 1 
     986 [-]: MOVE R40 R45 
L105: 987 [-]: GETUPVAL R46 6
     988 [-]: GETTABLEKS R45 R46 K221 [0xF22CFC77]
     989 [-]: GETIMPORT R46 73 [nil]
     990 [-]: MOVE R47 R40 
     991 [-]: GETTABLE R48 R41 R44
     992 [-]: NAMECALL R48 R48 K222 [0xBB610E5B]
     993 [-]: CALL R48 1 -1
     994 [-]: CALL R45 -1 0
     995 [-]: FORNLOOP R42 L104
     996 [-]: JUMP L107
   
L106: 997 [-]: GETUPVAL R42 6
     998 [-]: GETTABLEKS R41 R42 K70 [0x9742B85B]
     999 [-]: GETIMPORT R42 73 [nil]
     1000 [-]: MOVE R43 R40 
     1001 [-]: CALL R41 2 0 
L107: 1002 [-]: FASTCALL1 62 R15 L108
     1003 [-]: MOVE R41 R15 
     1004 [-]: GETIMPORT R40 3 [nil]
     1005 [-]: CALL R40 1 1 
L108: 1006 [-]: JUMPIF R40 L109
     1007 [-]: LOADN R42 0  
     1008 [-]: NAMECALL R40 R15 K187 [0x8061B6D7]
     1009 [-]: CALL R40 2 0 
     1010 [-]: LOADN R42 0  
     1011 [-]: NAMECALL R40 R15 K188 [0x2F5F5657]
     1012 [-]: CALL R40 2 0 
     1013 [-]: LOADB R42 0  
     1014 [-]: NAMECALL R40 R15 K75 [0x383D2E7D]
     1015 [-]: CALL R40 2 0 
L109: 1016 [-]: FASTCALL1 62 R0 L110
     1017 [-]: MOVE R41 R0  
     1018 [-]: GETIMPORT R40 3 [nil]
     1019 [-]: CALL R40 1 1 
L110: 1020 [-]: JUMPIF R40 L111
     1021 [-]: GETIMPORT R40 11 [nil]
     1022 [-]: GETIMPORT R42 224 [nil]
     1023 [-]: NAMECALL R43 R0 K225 [0xF6EBD926]
     1024 [-]: CALL R43 1 1 
     1025 [-]: GETIMPORT R44 227 [nil]
     1026 [-]: NAMECALL R40 R40 K228 [0x05909209]
     1027 [-]: CALL R40 4 0 
     1028 [-]: GETIMPORT R40 231 [nil]
     1029 [-]: CALL R40 0 1 
     1030 [-]: LOADN R43 0  
     1031 [-]: LOADN R44 1  
     1032 [-]: NAMECALL R41 R40 K232 [0x1586E35E]
     1033 [-]: CALL R41 3 0 
     1034 [-]: LOADK R41 K233 [999999]
     1035 [-]: SETTABLEKS R41 R40 K234 ["baseAmount"]
     1036 [-]: MOVE R43 R15 
     1037 [-]: NAMECALL R41 R40 K235 [0x86CD00CB]
     1038 [-]: CALL R41 2 0 
     1039 [-]: MOVE R43 R40 
     1040 [-]: NAMECALL R41 R0 K236 [0x479483BB]
     1041 [-]: CALL R41 2 0 
     1042 [-]: NAMECALL R41 R0 K146 [0xA2880940]
     1043 [-]: CALL R41 1 0 
L111: 1044 [-]: RETURN R0 0  


; Name:            
; Defined at line: 2927
; #Upvalues:       2
; #Parameters:     0
; Is_vararg:       0
; Max Stack Size:  5

       0 [-]: GETIMPORT R0 1 [nil]
       1 [-]: GETUPVAL R2 0
       2 [-]: LOADN R3 0   
       3 [-]: NAMECALL R0 R0 K2 [0x0EB34C69]
       4 [-]: CALL R0 3 1  
       5 [-]: GETIMPORT R1 1 [nil]
       6 [-]: GETUPVAL R3 1
       7 [-]: MOVE R4 R0   
       8 [-]: NAMECALL R1 R1 K3 [0x751F061D]
       9 [-]: CALL R1 3 0  
      10 [-]: RETURN R0 0  


; Name:            
; Defined at line: 2932
; #Upvalues:       1
; #Parameters:     0
; Is_vararg:       0
; Max Stack Size:  7

       0 [-]: GETIMPORT R0 1 [nil]
L 0:   1 [-]: FASTCALL1 62 R0 L1
       2 [-]: MOVE R2 R0   
       3 [-]: GETIMPORT R1 3 [nil]
       4 [-]: CALL R1 1 1  
L 1:   5 [-]: JUMPIFNOT R1 L2
       6 [-]: GETIMPORT R0 1 [nil]
       7 [-]: GETIMPORT R1 5 [nil]
       8 [-]: LOADK R2 K6 [0.10000000000000001]
       9 [-]: CALL R1 1 0  
      10 [-]: JUMPBACK L0  
L 2:  11 [-]: NAMECALL R1 R0 K7 [0x5C390F04]
      12 [-]: CALL R1 1 1  
      13 [-]: LOADN R2 17  
      14 [-]: JUMPIFEQ R1 R2 L3
      15 [-]: RETURN R0 0  
L 3:  16 [-]: GETUPVAL R3 0
      17 [-]: NAMECALL R1 R0 K8 [0x0EB34C69]
      18 [-]: CALL R1 2 1  
      19 [-]: GETIMPORT R2 10 [nil]
      20 [-]: LOADK R4 K11 ["HostMigrationInit - excavation state="]
      21 [-]: GETIMPORT R5 13 [nil]
      22 [-]: MOVE R6 R1   
      23 [-]: CALL R5 1 1  
      24 [-]: CONCAT R3 R4 R5
      25 [-]: CALL R2 1 0  
      26 [-]: RETURN R0 0  


; Name:            
; Defined at line: 2970
; #Upvalues:       1
; #Parameters:     1
; Is_vararg:       0
; Max Stack Size:  7

       0 [-]: GETIMPORT R1 1 [nil]
       1 [-]: GETUPVAL R3 0
       2 [-]: NAMECALL R4 R0 K2 [0xD1586535]
       3 [-]: CALL R4 1 -1 
       4 [-]: NAMECALL R1 R1 K3 [0xC7B81E8D]
       5 [-]: CALL R1 -1 1 
       6 [-]: NAMECALL R2 R1 K2 [0xD1586535]
       7 [-]: CALL R2 1 1  
       8 [-]: LOADN R3 0   
L 0:   9 [-]: GETIMPORT R4 5 [nil]
      10 [-]: JUMPIFNOTLT R3 R4 L2
      11 [-]: FASTCALL1 62 R1 L1
      12 [-]: MOVE R5 R1   
      13 [-]: GETIMPORT R4 7 [nil]
      14 [-]: CALL R4 1 1  
L 1:  15 [-]: JUMPIF R4 L2 
      16 [-]: NAMECALL R4 R1 K2 [0xD1586535]
      17 [-]: CALL R4 1 1  
      18 [-]: MOVE R2 R4   
      19 [-]: MOVE R6 R2   
      20 [-]: NAMECALL R4 R0 K8 [0x9E9C67CB]
      21 [-]: CALL R4 2 0  
      22 [-]: GETIMPORT R4 10 [nil]
      23 [-]: CALL R4 0 1  
      24 [-]: ADD R3 R3 R4 
      25 [-]: GETIMPORT R4 12 [nil]
      26 [-]: LOADN R5 0   
      27 [-]: CALL R4 1 0  
      28 [-]: JUMPBACK L0  
L 2:  29 [-]: FASTCALL1 62 R0 L3
      30 [-]: MOVE R5 R0   
      31 [-]: GETIMPORT R4 7 [nil]
      32 [-]: CALL R4 1 1  
L 3:  33 [-]: JUMPIF R4 L4 
      34 [-]: NAMECALL R4 R0 K13 [0xA2880940]
      35 [-]: CALL R4 1 0  
L 4:  36 [-]: RETURN R0 0  


; Name:            
; Defined at line: 2986
; #Upvalues:       0
; #Parameters:     1
; Is_vararg:       0
; Max Stack Size:  6

       0 [-]: GETIMPORT R1 1 [nil]
       1 [-]: GETIMPORT R3 3 [nil]
       2 [-]: NAMECALL R4 R0 K4 [0xD1586535]
       3 [-]: CALL R4 1 1  
       4 [-]: LOADN R5 5   
       5 [-]: NAMECALL R1 R1 K5 [0x4E5939A5]
       6 [-]: CALL R1 4 1  
       7 [-]: FASTCALL1 62 R1 L0
       8 [-]: MOVE R3 R1   
       9 [-]: GETIMPORT R2 7 [nil]
      10 [-]: CALL R2 1 1  
L 0:  11 [-]: JUMPIF R2 L1 
      12 [-]: LOADN R4 0   
      13 [-]: NAMECALL R2 R1 K8 [0x8061B6D7]
      14 [-]: CALL R2 2 0  
      15 [-]: LOADN R4 0   
      16 [-]: NAMECALL R2 R1 K9 [0x2F5F5657]
      17 [-]: CALL R2 2 0  
      18 [-]: LOADB R4 0   
      19 [-]: NAMECALL R2 R1 K10 [0x383D2E7D]
      20 [-]: CALL R2 2 0  
L 1:  21 [-]: RETURN R0 0  



