; Name:            
; Defined at line: 1
; #Upvalues:       0
; #Parameters:     0
; Is_vararg:       1
; Max Stack Size:  41

       1 [-]: GETIMPORT R0 1; var0 = 0xB009BBC6
       2 [-]: LOADK R1 K2  ; var1 = "/Lotus/Animations/Tenno/Emotes/Generic/Shrug_anim.fbx"
       3 [-]: CALL R0 2 2  ; var0 = var0(var1)
       4 [-]: GETIMPORT R1 1; var1 = 0xB009BBC6
       5 [-]: LOADK R2 K3  ; var2 = "/Lotus/Animations/Tenno/Emotes/Generic/Brag01_anim.fbx"
       6 [-]: CALL R1 2 2  ; var1 = var1(var2)
       7 [-]: LOADNIL R2   ; var2 = nil
       8 [-]: LOADB R3 0   ; var3 = false
       9 [-]: LOADB R4 0   ; var4 = false
      10 [-]: GETIMPORT R5 5; var5 = 0xA421AF95
      11 [-]: CALL R5 1 2  ; var5 = var5()
      12 [-]: LOADNIL R6   ; var6 = nil
      13 [-]: LOADNIL R7   ; var7 = nil
      14 [-]: NEWTABLE R8 0 2; var8 = {}
      15 [-]: LOADB R9 0   ; var9 = false
      16 [-]: SETTABLEN R9 R8 1; SETTABLEN R9 R8 1
      17 [-]: LOADB R9 0   ; var9 = false
      18 [-]: SETTABLEN R9 R8 2; SETTABLEN R9 R8 2
      19 [-]: LOADN R9 1   ; var9 = 1
      20 [-]: LOADN R10 0  ; var10 = 0
      21 [-]: LOADN R11 0  ; var11 = 0
      22 [-]: LOADN R12 0  ; var12 = 0
      23 [-]: LOADN R13 0  ; var13 = 0
      24 [-]: LOADN R14 0  ; var14 = 0
      25 [-]: LOADB R15 0  ; var15 = false
      26 [-]: LOADN R16 0  ; var16 = 0
      27 [-]: LOADN R17 0  ; var17 = 0
      28 [-]: LOADN R18 0  ; var18 = 0
      29 [-]: LOADB R19 0  ; var19 = false
      30 [-]: LOADB R20 0  ; var20 = false
      31 [-]: LOADB R21 0  ; var21 = false
      32 [-]: LOADK R22 K6 ; var22 = 1.2
      33 [-]: GETIMPORT R23 8; var23 = 0x2D0FAD09
      34 [-]: LOADK R24 K9 ; var24 = "EE.Interface.Utilities"
      35 [-]: CALL R23 2 2 ; var23 = var23(var24)
      36 [-]: NEWCLOSURE R24 P0; 
      37 [-]: CAPTURE REF R2; 
      38 [-]: CAPTURE REF R3; 
      39 [-]: NEWCLOSURE R25 P1; 
      40 [-]: CAPTURE REF R2; 
      41 [-]: CAPTURE REF R5; 
      42 [-]: GETIMPORT R26 11; var26 = _T
      43 [-]: DUPCLOSURE R27 K12; 
      44 [-]: SETTABLEKS R27 R26 K13; var27["SetFightingGameCameraOffset"] = var26
      45 [-]: DUPCLOSURE R26 K14; 
      46 [-]: DUPCLOSURE R27 K15; 
      47 [-]: NEWCLOSURE R28 P5; 
      48 [-]: CAPTURE REF R11; 
      49 [-]: CAPTURE REF R10; 
      50 [-]: CAPTURE REF R12; 
      51 [-]: NEWCLOSURE R29 P6; 
      52 [-]: CAPTURE REF R13; 
      53 [-]: DUPCLOSURE R30 K16; 
      54 [-]: NEWCLOSURE R31 P8; 
      55 [-]: CAPTURE REF R6; 
      56 [-]: CAPTURE REF R7; 
      57 [-]: CAPTURE VAL R23; 
      58 [-]: NEWCLOSURE R32 P9; 
      59 [-]: CAPTURE REF R14; 
      60 [-]: CAPTURE REF R2; 
      61 [-]: NEWCLOSURE R33 P10; 
      62 [-]: CAPTURE REF R15; 
      63 [-]: CAPTURE REF R16; 
      64 [-]: DUPCLOSURE R34 K17; 
      65 [-]: DUPCLOSURE R35 K18; 
      66 [-]: CAPTURE VAL R23; 
      67 [-]: CAPTURE VAL R1; 
      68 [-]: CAPTURE VAL R0; 
      69 [-]: DUPCLOSURE R36 K19; 
      70 [-]: DUPCLOSURE R37 K20; 
      71 [-]: CAPTURE VAL R26; 
      72 [-]: DUPCLOSURE R38 K21; 
      73 [-]: NEWCLOSURE R39 P16; 
      74 [-]: CAPTURE REF R9; 
      75 [-]: CAPTURE VAL R27; 
      76 [-]: NEWCLOSURE R40 P17; 
      77 [-]: CAPTURE REF R19; 
      78 [-]: SETGLOBAL R40 K22; "OnMatchStarted" = var40
      79 [-]: DUPCLOSURE R40 K23; 
      80 [-]: SETGLOBAL R40 K24; "OnDBUpdateCompleted" = var40
      81 [-]: NEWCLOSURE R40 P19; 
      82 [-]: CAPTURE VAL R38; 
      83 [-]: CAPTURE REF R15; 
      84 [-]: CAPTURE REF R16; 
      85 [-]: CAPTURE VAL R35; 
      86 [-]: CAPTURE VAL R36; 
      87 [-]: CAPTURE VAL R23; 
      88 [-]: CAPTURE REF R19; 
      89 [-]: CAPTURE REF R12; 
      90 [-]: CAPTURE REF R10; 
      91 [-]: CAPTURE REF R11; 
      92 [-]: SETGLOBAL R40 K25; "OnMatchEnded" = var40
      93 [-]: DUPCLOSURE R40 K26; 
      94 [-]: CAPTURE VAL R23; 
      95 [-]: SETGLOBAL R40 K27; "OnStartNewRound" = var40
      96 [-]: NEWCLOSURE R40 P21; 
      97 [-]: CAPTURE REF R17; 
      98 [-]: CAPTURE REF R18; 
      99 [-]: SETGLOBAL R40 K28; "OnFirstRound" = var40
     100 [-]: NEWCLOSURE R40 P22; 
     101 [-]: CAPTURE REF R9; 
     102 [-]: CAPTURE REF R19; 
     103 [-]: CAPTURE VAL R39; 
     104 [-]: CAPTURE VAL R8; 
     105 [-]: CAPTURE REF R13; 
     106 [-]: CAPTURE VAL R23; 
     107 [-]: SETGLOBAL R40 K29; "OnQueueNewRound" = var40
     108 [-]: NEWCLOSURE R40 P23; 
     109 [-]: CAPTURE REF R20; 
     110 [-]: CAPTURE REF R17; 
     111 [-]: CAPTURE REF R18; 
     112 [-]: CAPTURE REF R19; 
     113 [-]: CAPTURE VAL R8; 
     114 [-]: CAPTURE VAL R39; 
     115 [-]: CAPTURE REF R15; 
     116 [-]: CAPTURE REF R16; 
     117 [-]: CAPTURE REF R3; 
     118 [-]: CAPTURE REF R2; 
     119 [-]: CAPTURE REF R4; 
     120 [-]: CAPTURE REF R5; 
     121 [-]: CAPTURE REF R21; 
     122 [-]: CAPTURE REF R22; 
     123 [-]: CAPTURE VAL R25; 
     124 [-]: CAPTURE VAL R28; 
     125 [-]: CAPTURE REF R13; 
     126 [-]: CAPTURE REF R14; 
     127 [-]: CAPTURE VAL R31; 
     128 [-]: CAPTURE VAL R34; 
     129 [-]: SETGLOBAL R40 K30; "OnUpdate" = var40
     130 [-]: DUPCLOSURE R40 K31; 
     131 [-]: SETGLOBAL R40 K32; "OnPlayerSpawned" = var40
     132 [-]: DUPCLOSURE R40 K33; 
     133 [-]: SETGLOBAL R40 K34; "OnPlayerDisconnected" = var40
     134 [-]: NEWCLOSURE R40 P26; 
     135 [-]: CAPTURE VAL R37; 
     136 [-]: CAPTURE REF R21; 
     137 [-]: CAPTURE VAL R24; 
     138 [-]: SETGLOBAL R40 K35; "OnAvatarChanged" = var40
     139 [-]: NEWCLOSURE R40 P27; 
     140 [-]: CAPTURE VAL R38; 
     141 [-]: CAPTURE REF R15; 
     142 [-]: CAPTURE REF R16; 
     143 [-]: CAPTURE VAL R35; 
     144 [-]: CAPTURE VAL R36; 
     145 [-]: CAPTURE REF R12; 
     146 [-]: CAPTURE REF R10; 
     147 [-]: CAPTURE REF R11; 
     148 [-]: SETGLOBAL R40 K36; "OnRoundEnded" = var40
     149 [-]: NEWCLOSURE R40 P28; 
     150 [-]: CAPTURE REF R19; 
     151 [-]: CAPTURE VAL R37; 
     152 [-]: CAPTURE VAL R24; 
     153 [-]: SETGLOBAL R40 K37; "OnProxyAvatarSpawned" = var40
     154 [-]: NEWCLOSURE R40 P29; 
     155 [-]: CAPTURE REF R2; 
     156 [-]: CAPTURE REF R14; 
     157 [-]: SETGLOBAL R40 K38; "OnDamageHit" = var40
     158 [-]: CLOSEUPVALS R2; 
     159 [-]: RETURN R0 0  ; 


; Name:            
; Defined at line: 67
; #Upvalues:       2
; #Parameters:     0
; Is_vararg:       0
; Max Stack Size:  12

       0 [-]: GETUPVAL R1 0; var1 = upvalues[0]
       1 [-]: FASTCALL1 62 R1 L0; 
       2 [-]: GETIMPORT R0 1; var0 = 0x7B998233
       3 [-]: CALL R0 2 2  ; var0 = var0(var1)
L 0:   4 [-]: JUMPIFNOT R0 L1; goto L1 if not var0
       5 [-]: GETIMPORT R0 3; var0 = 0x89326C93
       6 [-]: GETIMPORT R2 5; var2 = 0x6AFBF541
       7 [-]: NAMECALL R0 R0 K6; var1 = var0; var0 = var0[0x46A0EBF5]
       8 [-]: CALL R0 3 2  ; var0 = var0(var1, var2)
       9 [-]: SETUPVAL R0 0; upvalues[0] = var0
L 1:  10 [-]: GETIMPORT R0 8; var0 = 0xCFC01047
      11 [-]: GETIMPORT R1 3; var1 = 0x89326C93
      12 [-]: NAMECALL R1 R1 K9; var2 = var1; var1 = var1[0x7D108DDB]
      13 [-]: CALL R1 2 0  ; var1, ... = var1(var2)
      14 [-]: CALL R0 0 4  ; var0, var1, var2 = var0(var1, ...)
      15 [-]: FORGPREP_NEXT R0 L6; 
L 2:  16 [-]: NAMECALL R5 R4 K10; var6 = var4; var5 = var4[0x420402A9]
      17 [-]: CALL R5 2 2  ; var5 = var5(var6)
      18 [-]: JUMPIFNOT R5 L6; goto L6 if not var5
      19 [-]: NAMECALL R5 R4 K11; var6 = var4; var5 = var4[0xBB610E5B]
      20 [-]: CALL R5 2 2  ; var5 = var5(var6)
      21 [-]: FASTCALL1 62 R5 L3; 
      22 [-]: MOVE R7 R5   ; var7 = var5
      23 [-]: GETIMPORT R6 1; var6 = 0x7B998233
      24 [-]: CALL R6 2 2  ; var6 = var6(var7)
L 3:  25 [-]: JUMPIF R6 L6 ; goto L6 if var6
      26 [-]: LOADB R8 0   ; var8 = false
      27 [-]: NAMECALL R6 R5 K12; var7 = var5; var6 = var5[0xFC40040F]
      28 [-]: CALL R6 3 1  ; var6(var7, var8)
      29 [-]: GETUPVAL R7 0; var7 = upvalues[0]
      30 [-]: FASTCALL1 62 R7 L4; 
      31 [-]: GETIMPORT R6 1; var6 = 0x7B998233
      32 [-]: CALL R6 2 2  ; var6 = var6(var7)
L 4:  33 [-]: JUMPIF R6 L5 ; goto L5 if var6
      34 [-]: GETUPVAL R6 0; var6 = upvalues[0]
      35 [-]: NAMECALL R6 R6 K13; var7 = var6; var6 = var6[0x5710748F]
      36 [-]: CALL R6 2 1  ; var6(var7)
      37 [-]: GETIMPORT R6 15; var6 = 0x3D106989
      38 [-]: LOADK R8 K16 ; var8 = "TRACKING CAMERA NOW FOR PLAYER "
      39 [-]: GETIMPORT R9 18; var9 = 0x64FB1586
      40 [-]: NAMECALL R10 R4 K19; var11 = var4; var10 = var4[0x5CA33548]
      41 [-]: CALL R10 2 0 ; var10, ... = var10(var11)
      42 [-]: CALL R9 0 2  ; var9 = var9(var10, ...)
      43 [-]: CONCAT R7 R8 R9; var7 = var8 .. var9
      44 [-]: CALL R6 2 1  ; var6(var7)
      45 [-]: LOADB R6 1   ; var6 = true
      46 [-]: SETUPVAL R6 1; upvalues[6] = var1
      47 [-]: JUMP L6      ; goto L6
L 5:  48 [-]: GETIMPORT R6 15; var6 = 0x3D106989
      49 [-]: LOADK R7 K20 ; var7 = "WTH HAPPENED WITH THE CAMERA SPOT!"
      50 [-]: CALL R6 2 1  ; var6(var7)
L 6:  51 [-]: FORGLOOP R0 L2 2; 
      52 [-]: GETIMPORT R0 22; var0 = 0xBE190284
      53 [-]: GETIMPORT R2 24; var2 = 0x7591E528
      54 [-]: NAMECALL R0 R0 K25; var1 = var0; var0 = var0[0x23A0D2D2]
      55 [-]: CALL R0 3 1  ; var0(var1, var2)
      56 [-]: RETURN R0 0  ; 


; Name:            
; Defined at line: 91
; #Upvalues:       2
; #Parameters:     1
; Is_vararg:       0
; Max Stack Size:  16

       0 [-]: LOADN R1 1   ; var1 = 1
       1 [-]: GETIMPORT R3 1; var3 = 0xBE190284
       2 [-]: FASTCALL1 62 R3 L0; 
       3 [-]: GETIMPORT R2 3; var2 = 0x7B998233
       4 [-]: CALL R2 2 2  ; var2 = var2(var3)
L 0:   5 [-]: JUMPIF R2 L1 ; goto L1 if var2
       6 [-]: GETIMPORT R2 1; var2 = 0xBE190284
       7 [-]: NAMECALL R2 R2 K4; var3 = var2; var2 = var2[0x36880F9B]
       8 [-]: CALL R2 2 2  ; var2 = var2(var3)
       9 [-]: JUMPIFNOT R2 L1; goto L1 if not var2
      10 [-]: LOADN R1 -1  ; var1 = -1
L 1:  11 [-]: GETUPVAL R3 0; var3 = upvalues[0]
      12 [-]: FASTCALL1 62 R3 L2; 
      13 [-]: GETIMPORT R2 3; var2 = 0x7B998233
      14 [-]: CALL R2 2 2  ; var2 = var2(var3)
L 2:  15 [-]: JUMPIF R2 L9 ; goto L9 if var2
      16 [-]: GETIMPORT R2 6; var2 = 0x89326C93
      17 [-]: NAMECALL R2 R2 K7; var3 = var2; var2 = var2[0x7D108DDB]
      18 [-]: CALL R2 2 2  ; var2 = var2(var3)
      19 [-]: LOADNIL R3   ; var3 = nil
      20 [-]: LOADNIL R4   ; var4 = nil
      21 [-]: LENGTH R5 R2 ; var5 = #var2
      22 [-]: JUMPXEQKN R5 K8 L6 NOT; 
      23 [-]: GETTABLEN R6 R2 1; var6 = var2[1]
      24 [-]: NAMECALL R6 R6 K9; var7 = var6; var6 = var6[0xBB610E5B]
      25 [-]: CALL R6 2 2  ; var6 = var6(var7)
      26 [-]: FASTCALL1 62 R6 L3; 
      27 [-]: GETIMPORT R5 3; var5 = 0x7B998233
      28 [-]: CALL R5 2 2  ; var5 = var5(var6)
L 3:  29 [-]: JUMPIF R5 L6 ; goto L6 if var5
      30 [-]: GETTABLEN R6 R2 2; var6 = var2[2]
      31 [-]: NAMECALL R6 R6 K9; var7 = var6; var6 = var6[0xBB610E5B]
      32 [-]: CALL R6 2 2  ; var6 = var6(var7)
      33 [-]: FASTCALL1 62 R6 L4; 
      34 [-]: GETIMPORT R5 3; var5 = 0x7B998233
      35 [-]: CALL R5 2 2  ; var5 = var5(var6)
L 4:  36 [-]: JUMPIF R5 L6 ; goto L6 if var5
      37 [-]: GETTABLEN R5 R2 1; var5 = var2[1]
      38 [-]: NAMECALL R5 R5 K9; var6 = var5; var5 = var5[0xBB610E5B]
      39 [-]: CALL R5 2 2  ; var5 = var5(var6)
      40 [-]: NAMECALL R5 R5 K10; var6 = var5; var5 = var5[0xF6EBD926]
      41 [-]: CALL R5 2 2  ; var5 = var5(var6)
      42 [-]: MOVE R3 R5   ; var3 = var5
      43 [-]: GETTABLEN R5 R2 2; var5 = var2[2]
      44 [-]: NAMECALL R5 R5 K9; var6 = var5; var5 = var5[0xBB610E5B]
      45 [-]: CALL R5 2 2  ; var5 = var5(var6)
      46 [-]: NAMECALL R5 R5 K10; var6 = var5; var5 = var5[0xF6EBD926]
      47 [-]: CALL R5 2 2  ; var5 = var5(var6)
      48 [-]: MOVE R4 R5   ; var4 = var5
      49 [-]: GETTABLEN R5 R2 1; var5 = var2[1]
      50 [-]: NAMECALL R5 R5 K9; var6 = var5; var5 = var5[0xBB610E5B]
      51 [-]: CALL R5 2 2  ; var5 = var5(var6)
      52 [-]: NAMECALL R5 R5 K11; var6 = var5; var5 = var5[0x2047CFE7]
      53 [-]: CALL R5 2 2  ; var5 = var5(var6)
      54 [-]: JUMPIFNOT R5 L5; goto L5 if not var5
      55 [-]: GETTABLEKS R5 R4 K12; var5 = var4["z"]
      56 [-]: SETTABLEKS R5 R3 K12; var5["z"] = var3
      57 [-]: JUMP L8      ; goto L8
L 5:  58 [-]: GETTABLEN R5 R2 2; var5 = var2[2]
      59 [-]: NAMECALL R5 R5 K9; var6 = var5; var5 = var5[0xBB610E5B]
      60 [-]: CALL R5 2 2  ; var5 = var5(var6)
      61 [-]: NAMECALL R5 R5 K11; var6 = var5; var5 = var5[0x2047CFE7]
      62 [-]: CALL R5 2 2  ; var5 = var5(var6)
      63 [-]: JUMPIFNOT R5 L8; goto L8 if not var5
      64 [-]: GETTABLEKS R5 R3 K12; var5 = var3["z"]
      65 [-]: SETTABLEKS R5 R4 K12; var5["z"] = var4
      66 [-]: JUMP L8      ; goto L8
L 6:  67 [-]: GETIMPORT R5 6; var5 = 0x89326C93
      68 [-]: GETIMPORT R7 14; var7 = gPlayerSpawnType
      69 [-]: NAMECALL R5 R5 K15; var6 = var5; var5 = var5[0xFB669000]
      70 [-]: CALL R5 3 2  ; var5 = var5(var6, var7)
      71 [-]: LENGTH R6 R5 ; var6 = #var5
      72 [-]: JUMPXEQKN R6 K16 L7 NOT; 
      73 [-]: GETUPVAL R6 0; var6 = upvalues[0]
      74 [-]: GETUPVAL R8 1; var8 = upvalues[1]
      75 [-]: NAMECALL R6 R6 K17; var7 = var6; var6 = var6[0x9307AA51]
      76 [-]: CALL R6 3 1  ; var6(var7, var8)
      77 [-]: RETURN R0 0  ; 
L 7:  78 [-]: GETTABLEN R6 R5 1; var6 = var5[1]
      79 [-]: NAMECALL R6 R6 K18; var7 = var6; var6 = var6[0xD1586535]
      80 [-]: CALL R6 2 2  ; var6 = var6(var7)
      81 [-]: MOVE R3 R6   ; var3 = var6
      82 [-]: GETTABLEN R6 R5 2; var6 = var5[2]
      83 [-]: NAMECALL R6 R6 K18; var7 = var6; var6 = var6[0xD1586535]
      84 [-]: CALL R6 2 2  ; var6 = var6(var7)
      85 [-]: MOVE R4 R6   ; var4 = var6
      86 [-]: GETTABLEKS R7 R3 K20; var7 = var3["y"]
      87 [-]: SUBK R6 R7 K19; var6 = var7 - 0.23999999999999999
      88 [-]: SETTABLEKS R6 R3 K20; var6["y"] = var3
      89 [-]: GETTABLEKS R7 R4 K20; var7 = var4["y"]
      90 [-]: SUBK R6 R7 K19; var6 = var7 - 0.23999999999999999
      91 [-]: SETTABLEKS R6 R4 K20; var6["y"] = var4
L 8:  92 [-]: ADD R6 R3 R4 ; var6 = var3 + var4
      93 [-]: DIVK R5 R6 K8; var5 = var6 / 2
      94 [-]: LOADN R7 1   ; var7 = 1
      95 [-]: GETIMPORT R8 22; var8 = 0x42DCC9F5
      96 [-]: GETIMPORT R10 24; var10 = 0x03EA2485
      97 [-]: MOVE R11 R3  ; var11 = var3
      98 [-]: MOVE R12 R4  ; var12 = var4
      99 [-]: CALL R10 3 2 ; var10 = var10(var11, var12)
     100 [-]: GETIMPORT R11 26; var11 = 0x7591E528
     101 [-]: DIV R9 R10 R11; var9 = var10 / var11
     102 [-]: LOADN R10 0  ; var10 = 0
     103 [-]: LOADN R11 1  ; var11 = 1
     104 [-]: CALL R8 4 2  ; var8 = var8(var9, var10, var11)
     105 [-]: SUB R6 R7 R8 ; var6 = var7 - var8
     106 [-]: GETIMPORT R7 28; var7 = 0xB7CBD06B
     107 [-]: GETGLOBAL R8 K29; var8 = 0x8353E0FC
     108 [-]: GETGLOBAL R9 K30; var9 = 0xC367B736
     109 [-]: CALL R7 3 2  ; var7 = var7(var8, var9)
     110 [-]: MOVE R10 R6  ; var10 = var6
     111 [-]: NAMECALL R8 R7 K31; var9 = var7; var8 = var7[0x70596BFE]
     112 [-]: CALL R8 3 2  ; var8 = var8(var9, var10)
     113 [-]: MOVE R6 R8   ; var6 = var8
     114 [-]: GETIMPORT R8 33; var8 = 0xA421AF95
     115 [-]: GETTABLEKS R9 R5 K34; var9 = var5["x"]
     116 [-]: GETTABLEKS R11 R5 K20; var11 = var5["y"]
     117 [-]: ADDK R10 R11 K35; var10 = var11 + 1
     118 [-]: GETUPVAL R13 1; var13 = upvalues[1]
     119 [-]: GETTABLEKS R12 R13 K12; var12 = var13["z"]
     120 [-]: MUL R13 R6 R1; var13 = var6 * var1
     121 [-]: ADD R11 R12 R13; var11 = var12 + var13
     122 [-]: CALL R8 4 2  ; var8 = var8(var9, var10, var11)
     123 [-]: GETUPVAL R9 0; var9 = upvalues[0]
     124 [-]: GETIMPORT R11 37; var11 = 0x5DB3CE80
     125 [-]: GETUPVAL R12 0; var12 = upvalues[0]
     126 [-]: NAMECALL R12 R12 K18; var13 = var12; var12 = var12[0xD1586535]
     127 [-]: CALL R12 2 2 ; var12 = var12(var13)
     128 [-]: MOVE R13 R8  ; var13 = var8
     129 [-]: GETIMPORT R15 39; var15 = 0xAD0AC8AB
     130 [-]: MUL R14 R0 R15; var14 = var0 * var15
     131 [-]: CALL R11 4 0 ; var11, ... = var11(var12, var13, var14)
     132 [-]: NAMECALL R9 R9 K17; var10 = var9; var9 = var9[0x9307AA51]
     133 [-]: CALL R9 0 1  ; var9(var10, ...)
L 9: 134 [-]: RETURN R0 0  ; 


; Name:            
; Defined at line: 138
; #Upvalues:       0
; #Parameters:     2
; Is_vararg:       0
; Max Stack Size:  2

       0 [-]: SETGLOBAL R0 K0; 0x8353E0FC = var0
       1 [-]: SETGLOBAL R1 K1; 0xC367B736 = var1
       2 [-]: RETURN R0 0  ; 


; Name:            
; Defined at line: 143
; #Upvalues:       0
; #Parameters:     1
; Is_vararg:       0
; Max Stack Size:  6

       0 [-]: NAMECALL R1 R0 K0; var2 = var0; var1 = var0[0xDE321E6F]
       1 [-]: CALL R1 2 2  ; var1 = var1(var2)
       2 [-]: NAMECALL R1 R1 K1; var2 = var1; var1 = var1[0xBB4A3D82]
       3 [-]: CALL R1 2 2  ; var1 = var1(var2)
       4 [-]: FASTCALL1 62 R1 L0; 
       5 [-]: MOVE R3 R1   ; var3 = var1
       6 [-]: GETIMPORT R2 3; var2 = 0x7B998233
       7 [-]: CALL R2 2 2  ; var2 = var2(var3)
L 0:   8 [-]: JUMPIF R2 L2 ; goto L2 if var2
       9 [-]: NAMECALL R2 R1 K4; var3 = var1; var2 = var1[0xE3CA779E]
      10 [-]: CALL R2 2 2  ; var2 = var2(var3)
      11 [-]: FASTCALL1 62 R2 L1; 
      12 [-]: MOVE R4 R2   ; var4 = var2
      13 [-]: GETIMPORT R3 3; var3 = 0x7B998233
      14 [-]: CALL R3 2 2  ; var3 = var3(var4)
L 1:  15 [-]: JUMPIF R3 L2 ; goto L2 if var3
      16 [-]: LOADB R5 1   ; var5 = true
      17 [-]: NAMECALL R3 R2 K5; var4 = var2; var3 = var2[0x74939C55]
      18 [-]: CALL R3 3 1  ; var3(var4, var5)
      19 [-]: NAMECALL R3 R2 K6; var4 = var2; var3 = var2[0xC1F1F809]
      20 [-]: CALL R3 2 1  ; var3(var4)
L 2:  21 [-]: RETURN R0 0  ; 


; Name:            
; Defined at line: 154
; #Upvalues:       0
; #Parameters:     1
; Is_vararg:       0
; Max Stack Size:  6

       0 [-]: FASTCALL1 62 R0 L0; 
       1 [-]: MOVE R2 R0   ; var2 = var0
       2 [-]: GETIMPORT R1 1; var1 = 0x7B998233
       3 [-]: CALL R1 2 2  ; var1 = var1(var2)
L 0:   4 [-]: JUMPIF R1 L2 ; goto L2 if var1
       5 [-]: NAMECALL R2 R0 K2; var3 = var0; var2 = var0[0x5E651723]
       6 [-]: CALL R2 2 2  ; var2 = var2(var3)
       7 [-]: FASTCALL1 62 R2 L1; 
       8 [-]: GETIMPORT R1 1; var1 = 0x7B998233
       9 [-]: CALL R1 2 2  ; var1 = var1(var2)
L 1:  10 [-]: JUMPIFNOT R1 L3; goto L3 if not var1
L 2:  11 [-]: RETURN R0 0  ; 
L 3:  12 [-]: NAMECALL R1 R0 K2; var2 = var0; var1 = var0[0x5E651723]
      13 [-]: CALL R1 2 2  ; var1 = var1(var2)
      14 [-]: NAMECALL R1 R1 K3; var2 = var1; var1 = var1[0x5CA33548]
      15 [-]: CALL R1 2 2  ; var1 = var1(var2)
      16 [-]: GETIMPORT R3 6; var3 = _T["LastKnownEnergy"]
      17 [-]: FASTCALL1 62 R3 L4; 
      18 [-]: GETIMPORT R2 1; var2 = 0x7B998233
      19 [-]: CALL R2 2 2  ; var2 = var2(var3)
L 4:  20 [-]: JUMPIF R2 L6 ; goto L6 if var2
      21 [-]: GETIMPORT R4 6; var4 = _T["LastKnownEnergy"]
      22 [-]: GETTABLE R3 R4 R1; var3 = var4[var1]
      23 [-]: FASTCALL1 62 R3 L5; 
      24 [-]: GETIMPORT R2 1; var2 = 0x7B998233
      25 [-]: CALL R2 2 2  ; var2 = var2(var3)
L 5:  26 [-]: JUMPIF R2 L6 ; goto L6 if var2
      27 [-]: NAMECALL R2 R0 K7; var3 = var0; var2 = var0[0xDE321E6F]
      28 [-]: CALL R2 2 2  ; var2 = var2(var3)
      29 [-]: NAMECALL R2 R2 K8; var3 = var2; var2 = var2[0xF7D48EE0]
      30 [-]: CALL R2 2 2  ; var2 = var2(var3)
      31 [-]: GETIMPORT R5 6; var5 = _T["LastKnownEnergy"]
      32 [-]: GETTABLE R4 R5 R1; var4 = var5[var1]
      33 [-]: NAMECALL R2 R2 K9; var3 = var2; var2 = var2[0x6E19D3FE]
      34 [-]: CALL R2 3 1  ; var2(var3, var4)
L 6:  35 [-]: RETURN R0 0  ; 


; Name:            
; Defined at line: 165
; #Upvalues:       3
; #Parameters:     1
; Is_vararg:       0
; Max Stack Size:  7

       0 [-]: GETUPVAL R1 0; var1 = upvalues[0]
       1 [-]: GETIMPORT R2 1; var2 = 0x137C8F27
       2 [-]: JUMPIFNOTLT R1 R2 L0; goto L0 if var1 >= var519
       3 [-]: GETUPVAL R2 0; var2 = upvalues[0]
       4 [-]: ADD R1 R2 R0 ; var1 = var2 + var0
       5 [-]: SETUPVAL R1 0; upvalues[1] = var0
       6 [-]: RETURN R0 0  ; 
L 0:   7 [-]: GETUPVAL R2 1; var2 = upvalues[1]
       8 [-]: ADD R1 R2 R0 ; var1 = var2 + var0
       9 [-]: SETUPVAL R1 1; upvalues[1] = var1
      10 [-]: GETUPVAL R1 1; var1 = upvalues[1]
      11 [-]: LOADN R2 0   ; var2 = 0
      12 [-]: JUMPIFNOTLT R1 R2 L1; goto L1 if var1 >= var65581
      13 [-]: RETURN R0 0  ; 
L 1:  14 [-]: GETUPVAL R2 1; var2 = upvalues[1]
      15 [-]: GETIMPORT R3 3; var3 = 0x2FAE7303
      16 [-]: MUL R1 R2 R3 ; var1 = var2 * var3
      17 [-]: GETUPVAL R2 2; var2 = upvalues[2]
      18 [-]: JUMPXEQKN R2 K4 L3 NOT; 
      19 [-]: LOADN R2 1   ; var2 = 1
      20 [-]: JUMPIFNOTLT R2 R1 L2; goto L2 if var2 >= var65863
      21 [-]: LOADN R1 1   ; var1 = 1
      22 [-]: LOADN R2 -1  ; var2 = -1
      23 [-]: SETUPVAL R2 2; upvalues[2] = var2
      24 [-]: LOADN R2 0   ; var2 = 0
      25 [-]: SETUPVAL R2 1; upvalues[2] = var1
      26 [-]: GETIMPORT R3 1; var3 = 0x137C8F27
      27 [-]: MULK R2 R3 K5; var2 = var3 * 0.80000000000000004
      28 [-]: SETUPVAL R2 0; upvalues[2] = var0
L 2:  29 [-]: GETIMPORT R2 7; var2 = 0x89326C93
      30 [-]: NAMECALL R2 R2 K8; var3 = var2; var2 = var2[0x7C1A0374]
      31 [-]: CALL R2 2 2  ; var2 = var2(var3)
      32 [-]: MOVE R4 R1   ; var4 = var1
      33 [-]: NAMECALL R2 R2 K9; var3 = var2; var2 = var2[0xB6DF3E50]
      34 [-]: CALL R2 3 1  ; var2(var3, var4)
      35 [-]: JUMP L5      ; goto L5
L 3:  36 [-]: GETUPVAL R2 2; var2 = upvalues[2]
      37 [-]: JUMPXEQKN R2 K10 L5 NOT; 
      38 [-]: LOADN R2 1   ; var2 = 1
      39 [-]: JUMPIFNOTLT R2 R1 L4; goto L4 if var2 >= var65863
      40 [-]: LOADN R1 1   ; var1 = 1
      41 [-]: LOADN R2 0   ; var2 = 0
      42 [-]: SETUPVAL R2 2; upvalues[2] = var2
L 4:  43 [-]: GETIMPORT R2 7; var2 = 0x89326C93
      44 [-]: NAMECALL R2 R2 K8; var3 = var2; var2 = var2[0x7C1A0374]
      45 [-]: CALL R2 2 2  ; var2 = var2(var3)
      46 [-]: LOADN R5 1   ; var5 = 1
      47 [-]: SUB R4 R5 R1 ; var4 = var5 - var1
      48 [-]: NAMECALL R2 R2 K9; var3 = var2; var2 = var2[0xB6DF3E50]
      49 [-]: CALL R2 3 1  ; var2(var3, var4)
L 5:  50 [-]: GETIMPORT R2 12; var2 = _T
      51 [-]: LOADN R4 1   ; var4 = 1
      52 [-]: GETIMPORT R5 7; var5 = 0x89326C93
      53 [-]: NAMECALL R5 R5 K8; var6 = var5; var5 = var5[0x7C1A0374]
      54 [-]: CALL R5 2 2  ; var5 = var5(var6)
      55 [-]: NAMECALL R5 R5 K13; var6 = var5; var5 = var5[0x65C7544C]
      56 [-]: CALL R5 2 2  ; var5 = var5(var6)
      57 [-]: SUB R3 R4 R5 ; var3 = var4 - var5
      58 [-]: SETTABLEKS R3 R2 K14; var3["RoundFade"] = var2
      59 [-]: RETURN R0 0  ; 


; Name:            
; Defined at line: 197
; #Upvalues:       1
; #Parameters:     1
; Is_vararg:       0
; Max Stack Size:  4

       0 [-]: GETUPVAL R1 0; var1 = upvalues[0]
       1 [-]: LOADN R2 0   ; var2 = 0
       2 [-]: JUMPIFNOTLT R2 R1 L2; goto L2 if var2 >= var519
       3 [-]: GETUPVAL R2 0; var2 = upvalues[0]
       4 [-]: FASTCALL1 7 R2 L0; 
       5 [-]: GETIMPORT R1 2; var1 = 0x5BCED4C4[0x99675E23]
       6 [-]: CALL R1 2 2  ; var1 = var1(var2)
L 0:   7 [-]: GETUPVAL R3 0; var3 = upvalues[0]
       8 [-]: SUB R2 R3 R0 ; var2 = var3 - var0
       9 [-]: SETUPVAL R2 0; upvalues[2] = var0
      10 [-]: GETUPVAL R3 0; var3 = upvalues[0]
      11 [-]: FASTCALL1 7 R3 L1; 
      12 [-]: GETIMPORT R2 2; var2 = 0x5BCED4C4[0x99675E23]
      13 [-]: CALL R2 2 2  ; var2 = var2(var3)
L 1:  14 [-]: JUMPIFEQ R2 R1 L2; goto L2 if var2 == var839
      15 [-]: LOADN R3 0   ; var3 = 0
      16 [-]: JUMPIFNOTLT R3 R2 L2; goto L2 if var3 >= var197447
      17 [-]: LOADN R3 3   ; var3 = 3
      18 [-]: JUMPIFNOTLE R2 R3 L2; goto L2 if var2 > var262990
      19 [-]: GETIMPORT R3 4; var3 = _T
      20 [-]: SETTABLEKS R2 R3 K5; var2["RoundTimeLeft"] = var3
L 2:  21 [-]: RETURN R0 0  ; 


; Name:            
; Defined at line: 209
; #Upvalues:       0
; #Parameters:     0
; Is_vararg:       0
; Max Stack Size:  4

       0 [-]: GETIMPORT R0 1; var0 = 0xBE190284
       1 [-]: NAMECALL R0 R0 K2; var1 = var0; var0 = var0[0x82374F71]
       2 [-]: CALL R0 2 2  ; var0 = var0(var1)
       3 [-]: LOADN R1 2   ; var1 = 2
       4 [-]: JUMPIFNOTEQ R0 R1 L1; goto L1 if var0 ~= var262222
       5 [-]: GETIMPORT R0 4; var0 = _T
       6 [-]: GETIMPORT R2 1; var2 = 0xBE190284
       7 [-]: NAMECALL R2 R2 K5; var3 = var2; var2 = var2[0xDBB6F358]
       8 [-]: CALL R2 2 2  ; var2 = var2(var3)
       9 [-]: FASTCALL1 7 R2 L0; 
      10 [-]: GETIMPORT R1 8; var1 = 0x5BCED4C4[0x99675E23]
      11 [-]: CALL R1 2 2  ; var1 = var1(var2)
L 0:  12 [-]: SETTABLEKS R1 R0 K9; var1["RoundTimeLeft"] = var0
L 1:  13 [-]: RETURN R0 0  ; 


; Name:            
; Defined at line: 215
; #Upvalues:       3
; #Parameters:     0
; Is_vararg:       0
; Max Stack Size:  4

       0 [-]: GETIMPORT R0 1; var0 = 0xBE190284
       1 [-]: NAMECALL R0 R0 K2; var1 = var0; var0 = var0[0x82374F71]
       2 [-]: CALL R0 2 2  ; var0 = var0(var1)
       3 [-]: LOADN R1 2   ; var1 = 2
       4 [-]: JUMPIFNOTEQ R0 R1 L4; goto L4 if var0 ~= var519
       5 [-]: GETUPVAL R2 0; var2 = upvalues[0]
       6 [-]: FASTCALL1 62 R2 L0; 
       7 [-]: GETIMPORT R1 4; var1 = 0x7B998233
       8 [-]: CALL R1 2 2  ; var1 = var1(var2)
L 0:   9 [-]: JUMPIF R1 L1 ; goto L1 if var1
      10 [-]: GETUPVAL R1 0; var1 = upvalues[0]
      11 [-]: LOADB R3 0   ; var3 = false
      12 [-]: NAMECALL R1 R1 K5; var2 = var1; var1 = var1[0x6CF1E476]
      13 [-]: CALL R1 3 1  ; var1(var2, var3)
      14 [-]: LOADNIL R1   ; var1 = nil
      15 [-]: SETUPVAL R1 0; upvalues[1] = var0
L 1:  16 [-]: GETUPVAL R2 1; var2 = upvalues[1]
      17 [-]: FASTCALL1 62 R2 L2; 
      18 [-]: GETIMPORT R1 4; var1 = 0x7B998233
      19 [-]: CALL R1 2 2  ; var1 = var1(var2)
L 2:  20 [-]: JUMPIFNOT R1 L8; goto L8 if not var1
      21 [-]: GETIMPORT R2 7; var2 = 0x3747709B
      22 [-]: FASTCALL1 62 R2 L3; 
      23 [-]: GETIMPORT R1 4; var1 = 0x7B998233
      24 [-]: CALL R1 2 2  ; var1 = var1(var2)
L 3:  25 [-]: JUMPIF R1 L8 ; goto L8 if var1
      26 [-]: GETUPVAL R2 2; var2 = upvalues[2]
      27 [-]: GETTABLEKS R1 R2 K8; var1 = var2[0x659D451F]
      28 [-]: GETIMPORT R2 7; var2 = 0x3747709B
      29 [-]: CALL R1 2 2  ; var1 = var1(var2)
      30 [-]: SETUPVAL R1 1; upvalues[1] = var1
      31 [-]: RETURN R0 0  ; 
L 4:  32 [-]: LOADN R1 0   ; var1 = 0
      33 [-]: JUMPIFNOTEQ R0 R1 L8; goto L8 if var0 ~= var519
      34 [-]: GETUPVAL R2 0; var2 = upvalues[0]
      35 [-]: FASTCALL1 62 R2 L5; 
      36 [-]: GETIMPORT R1 4; var1 = 0x7B998233
      37 [-]: CALL R1 2 2  ; var1 = var1(var2)
L 5:  38 [-]: JUMPIFNOT R1 L6; goto L6 if not var1
      39 [-]: GETUPVAL R2 2; var2 = upvalues[2]
      40 [-]: GETTABLEKS R1 R2 K8; var1 = var2[0x659D451F]
      41 [-]: GETIMPORT R2 10; var2 = 0x6DFDF9A1
      42 [-]: CALL R1 2 2  ; var1 = var1(var2)
      43 [-]: SETUPVAL R1 0; upvalues[1] = var0
L 6:  44 [-]: GETUPVAL R2 1; var2 = upvalues[1]
      45 [-]: FASTCALL1 62 R2 L7; 
      46 [-]: GETIMPORT R1 4; var1 = 0x7B998233
      47 [-]: CALL R1 2 2  ; var1 = var1(var2)
L 7:  48 [-]: JUMPIF R1 L8 ; goto L8 if var1
      49 [-]: GETUPVAL R1 1; var1 = upvalues[1]
      50 [-]: LOADB R3 0   ; var3 = false
      51 [-]: NAMECALL R1 R1 K5; var2 = var1; var1 = var1[0x6CF1E476]
      52 [-]: CALL R1 3 1  ; var1(var2, var3)
      53 [-]: LOADNIL R1   ; var1 = nil
      54 [-]: SETUPVAL R1 1; upvalues[1] = var1
L 8:  55 [-]: RETURN R0 0  ; 


; Name:            
; Defined at line: 236
; #Upvalues:       2
; #Parameters:     1
; Is_vararg:       0
; Max Stack Size:  5

       0 [-]: GETUPVAL R1 0; var1 = upvalues[0]
       1 [-]: LOADN R2 0   ; var2 = 0
       2 [-]: JUMPIFNOTLT R2 R1 L1; goto L1 if var2 >= var519
       3 [-]: GETUPVAL R2 0; var2 = upvalues[0]
       4 [-]: SUB R1 R2 R0 ; var1 = var2 - var0
       5 [-]: SETUPVAL R1 0; upvalues[1] = var0
       6 [-]: GETUPVAL R1 0; var1 = upvalues[0]
       7 [-]: LOADN R2 0   ; var2 = 0
       8 [-]: JUMPIFNOTLT R1 R2 L1; goto L1 if var1 >= var66055
       9 [-]: GETUPVAL R2 1; var2 = upvalues[1]
      10 [-]: FASTCALL1 62 R2 L0; 
      11 [-]: GETIMPORT R1 1; var1 = 0x7B998233
      12 [-]: CALL R1 2 2  ; var1 = var1(var2)
L 0:  13 [-]: JUMPIF R1 L1 ; goto L1 if var1
      14 [-]: GETUPVAL R1 1; var1 = upvalues[1]
      15 [-]: LOADN R3 0   ; var3 = 0
      16 [-]: LOADN R4 0   ; var4 = 0
      17 [-]: NAMECALL R1 R1 K2; var2 = var1; var1 = var1[0xF3CEFA26]
      18 [-]: CALL R1 4 1  ; var1(var2, var3, var4)
L 1:  19 [-]: RETURN R0 0  ; 


; Name:            
; Defined at line: 245
; #Upvalues:       2
; #Parameters:     1
; Is_vararg:       0
; Max Stack Size:  4

       0 [-]: GETIMPORT R3 1; var3 = 0x97B85C09
       1 [-]: NAMECALL R1 R0 K2; var2 = var0; var1 = var0[0xD761A7A1]
       2 [-]: CALL R1 3 1  ; var1(var2, var3)
       3 [-]: LOADB R1 1   ; var1 = true
       4 [-]: SETUPVAL R1 0; upvalues[1] = var0
       5 [-]: LOADN R1 0   ; var1 = 0
       6 [-]: SETUPVAL R1 1; upvalues[1] = var1
       7 [-]: RETURN R0 0  ; 


; Name:            
; Defined at line: 251
; #Upvalues:       0
; #Parameters:     0
; Is_vararg:       0
; Max Stack Size:  10

       0 [-]: GETIMPORT R0 1; var0 = 0x89326C93
       1 [-]: NAMECALL R0 R0 K2; var1 = var0; var0 = var0[0x18D05D30]
       2 [-]: CALL R0 2 2  ; var0 = var0(var1)
       3 [-]: JUMPIF R0 L0 ; goto L0 if var0
       4 [-]: RETURN R0 0  ; 
L 0:   5 [-]: GETIMPORT R0 4; var0 = 0xBE190284
       6 [-]: NAMECALL R0 R0 K5; var1 = var0; var0 = var0[0x82374F71]
       7 [-]: CALL R0 2 2  ; var0 = var0(var1)
       8 [-]: LOADN R1 2   ; var1 = 2
       9 [-]: JUMPIFEQ R0 R1 L1; goto L1 if var0 == var65581
      10 [-]: RETURN R0 0  ; 
L 1:  11 [-]: GETIMPORT R1 8; var1 = _T["LastKnownEnergy"]
      12 [-]: FASTCALL1 62 R1 L2; 
      13 [-]: GETIMPORT R0 10; var0 = 0x7B998233
      14 [-]: CALL R0 2 2  ; var0 = var0(var1)
L 2:  15 [-]: JUMPIFNOT R0 L3; goto L3 if not var0
      16 [-]: GETIMPORT R0 11; var0 = _T
      17 [-]: NEWTABLE R1 0 0; var1 = {}
      18 [-]: SETTABLEKS R1 R0 K7; var1["LastKnownEnergy"] = var0
L 3:  19 [-]: GETIMPORT R0 13; var0 = 0xCFC01047
      20 [-]: GETIMPORT R1 1; var1 = 0x89326C93
      21 [-]: NAMECALL R1 R1 K14; var2 = var1; var1 = var1[0x7D108DDB]
      22 [-]: CALL R1 2 0  ; var1, ... = var1(var2)
      23 [-]: CALL R0 0 4  ; var0, var1, var2 = var0(var1, ...)
      24 [-]: FORGPREP_NEXT R0 L8; 
L 4:  25 [-]: NAMECALL R5 R4 K15; var6 = var4; var5 = var4[0x5CA33548]
      26 [-]: CALL R5 2 2  ; var5 = var5(var6)
      27 [-]: NAMECALL R6 R4 K16; var7 = var4; var6 = var4[0xBB610E5B]
      28 [-]: CALL R6 2 2  ; var6 = var6(var7)
      29 [-]: FASTCALL1 62 R6 L5; 
      30 [-]: MOVE R8 R6   ; var8 = var6
      31 [-]: GETIMPORT R7 10; var7 = 0x7B998233
      32 [-]: CALL R7 2 2  ; var7 = var7(var8)
L 5:  33 [-]: JUMPIF R7 L8 ; goto L8 if var7
      34 [-]: NAMECALL R8 R6 K17; var9 = var6; var8 = var6[0xDE321E6F]
      35 [-]: CALL R8 2 2  ; var8 = var8(var9)
      36 [-]: FASTCALL1 62 R8 L6; 
      37 [-]: GETIMPORT R7 10; var7 = 0x7B998233
      38 [-]: CALL R7 2 2  ; var7 = var7(var8)
L 6:  39 [-]: JUMPIF R7 L8 ; goto L8 if var7
      40 [-]: NAMECALL R8 R6 K17; var9 = var6; var8 = var6[0xDE321E6F]
      41 [-]: CALL R8 2 2  ; var8 = var8(var9)
      42 [-]: NAMECALL R8 R8 K18; var9 = var8; var8 = var8[0xF7D48EE0]
      43 [-]: CALL R8 2 2  ; var8 = var8(var9)
      44 [-]: FASTCALL1 62 R8 L7; 
      45 [-]: GETIMPORT R7 10; var7 = 0x7B998233
      46 [-]: CALL R7 2 2  ; var7 = var7(var8)
L 7:  47 [-]: JUMPIF R7 L8 ; goto L8 if var7
      48 [-]: GETIMPORT R7 8; var7 = _T["LastKnownEnergy"]
      49 [-]: NAMECALL R8 R6 K17; var9 = var6; var8 = var6[0xDE321E6F]
      50 [-]: CALL R8 2 2  ; var8 = var8(var9)
      51 [-]: NAMECALL R8 R8 K18; var9 = var8; var8 = var8[0xF7D48EE0]
      52 [-]: CALL R8 2 2  ; var8 = var8(var9)
      53 [-]: NAMECALL R8 R8 K19; var9 = var8; var8 = var8[0x58A4D5AC]
      54 [-]: CALL R8 2 2  ; var8 = var8(var9)
      55 [-]: SETTABLE R8 R7 R5; var8[var7] = var5
L 8:  56 [-]: FORGLOOP R0 L4 2; 
      57 [-]: RETURN R0 0  ; 


; Name:            
; Defined at line: 273
; #Upvalues:       3
; #Parameters:     2
; Is_vararg:       0
; Max Stack Size:  15

       0 [-]: GETIMPORT R2 1; var2 = 0xCFC01047
       1 [-]: GETIMPORT R3 3; var3 = 0x89326C93
       2 [-]: NAMECALL R3 R3 K4; var4 = var3; var3 = var3[0x7D108DDB]
       3 [-]: CALL R3 2 0  ; var3, ... = var3(var4)
       4 [-]: CALL R2 0 4  ; var2, var3, var4 = var2(var3, ...)
       5 [-]: FORGPREP_NEXT R2 L2; 
L 0:   6 [-]: JUMPIFNOTEQ R6 R1 L2; goto L2 if var6 ~= var1527121733
       7 [-]: NAMECALL R7 R6 K5; var8 = var6; var7 = var6[0xBB610E5B]
       8 [-]: CALL R7 2 2  ; var7 = var7(var8)
       9 [-]: FASTCALL1 62 R7 L1; 
      10 [-]: MOVE R9 R7   ; var9 = var7
      11 [-]: GETIMPORT R8 7; var8 = 0x7B998233
      12 [-]: CALL R8 2 2  ; var8 = var8(var9)
L 1:  13 [-]: JUMPIF R8 L2 ; goto L2 if var8
      14 [-]: NAMECALL R8 R7 K8; var9 = var7; var8 = var7[0x2047CFE7]
      15 [-]: CALL R8 2 2  ; var8 = var8(var9)
      16 [-]: JUMPIF R8 L2 ; goto L2 if var8
      17 [-]: NAMECALL R8 R7 K9; var9 = var7; var8 = var7[0x97CE7A31]
      18 [-]: CALL R8 2 2  ; var8 = var8(var9)
      19 [-]: JUMPIF R8 L2 ; goto L2 if var8
      20 [-]: LOADN R10 15 ; var10 = 15
      21 [-]: NAMECALL R8 R7 K10; var9 = var7; var8 = var7[0x0E46E45B]
      22 [-]: CALL R8 3 2  ; var8 = var8(var9, var10)
      23 [-]: JUMPIF R8 L2 ; goto L2 if var8
      24 [-]: NAMECALL R8 R7 K11; var9 = var7; var8 = var7[0xDE321E6F]
      25 [-]: CALL R8 2 2  ; var8 = var8(var9)
      26 [-]: NAMECALL R8 R8 K12; var9 = var8; var8 = var8[0x7F6EBE4E]
      27 [-]: CALL R8 2 1  ; var8(var9)
      28 [-]: GETUPVAL R9 0; var9 = upvalues[0]
      29 [-]: GETTABLEKS R8 R9 K13; var8 = var9[0x06D055F9]
      30 [-]: MOVE R9 R0   ; var9 = var0
      31 [-]: GETUPVAL R10 1; var10 = upvalues[1]
      32 [-]: GETUPVAL R11 2; var11 = upvalues[2]
      33 [-]: CALL R8 4 2  ; var8 = var8(var9, var10, var11)
      34 [-]: MOVE R11 R8  ; var11 = var8
      35 [-]: LOADB R12 0  ; var12 = false
      36 [-]: LOADN R13 3  ; var13 = 3
      37 [-]: LOADN R14 1  ; var14 = 1
      38 [-]: NAMECALL R9 R7 K14; var10 = var7; var9 = var7[0x5D985C7E]
      39 [-]: CALL R9 6 1  ; var9(var10, var11, var12, var13, var14)
      40 [-]: RETURN R0 0  ; 
L 2:  41 [-]: FORGLOOP R2 L0 2; 
      42 [-]: RETURN R0 0  ; 


; Name:            
; Defined at line: 287
; #Upvalues:       0
; #Parameters:     0
; Is_vararg:       0
; Max Stack Size:  9

       0 [-]: LOADB R0 0   ; var0 = false
       1 [-]: GETIMPORT R1 1; var1 = 0xCFC01047
       2 [-]: GETIMPORT R2 3; var2 = 0x89326C93
       3 [-]: NAMECALL R2 R2 K4; var3 = var2; var2 = var2[0x7D108DDB]
       4 [-]: CALL R2 2 0  ; var2, ... = var2(var3)
       5 [-]: CALL R1 0 4  ; var1, var2, var3 = var1(var2, ...)
       6 [-]: FORGPREP_NEXT R1 L2; 
L 0:   7 [-]: NAMECALL R6 R5 K5; var7 = var5; var6 = var5[0xBB610E5B]
       8 [-]: CALL R6 2 2  ; var6 = var6(var7)
       9 [-]: FASTCALL1 62 R6 L1; 
      10 [-]: MOVE R8 R6   ; var8 = var6
      11 [-]: GETIMPORT R7 7; var7 = 0x7B998233
      12 [-]: CALL R7 2 2  ; var7 = var7(var8)
L 1:  13 [-]: JUMPIF R7 L2 ; goto L2 if var7
      14 [-]: NAMECALL R7 R6 K8; var8 = var6; var7 = var6[0x2047CFE7]
      15 [-]: CALL R7 2 2  ; var7 = var7(var8)
      16 [-]: JUMPIFNOT R7 L2; goto L2 if not var7
      17 [-]: LOADB R0 1   ; var0 = true
      18 [-]: JUMP L3      ; goto L3
L 2:  19 [-]: FORGLOOP R1 L0 2; 
L 3:  20 [-]: JUMPIFNOT R0 L4; goto L4 if not var0
      21 [-]: GETIMPORT R1 3; var1 = 0x89326C93
      22 [-]: GETIMPORT R3 10; var3 = 0x48D7EE0B
      23 [-]: GETIMPORT R4 12; var4 = 0x9942EF35
      24 [-]: GETIMPORT R5 12; var5 = 0x9942EF35
      25 [-]: GETIMPORT R6 14; var6 = 0x2EEAD8CF
      26 [-]: LOADB R7 1   ; var7 = true
      27 [-]: NAMECALL R1 R1 K15; var2 = var1; var1 = var1[0xA128259D]
      28 [-]: CALL R1 7 1  ; var1(var2, var3, var4, var5, var6, var7)
L 4:  29 [-]: RETURN R0 0  ; 


; Name:            
; Defined at line: 302
; #Upvalues:       1
; #Parameters:     2
; Is_vararg:       0
; Max Stack Size:  10

       0 [-]: FASTCALL1 62 R0 L0; 
       1 [-]: MOVE R3 R0   ; var3 = var0
       2 [-]: GETIMPORT R2 1; var2 = 0x7B998233
       3 [-]: CALL R2 2 2  ; var2 = var2(var3)
L 0:   4 [-]: JUMPIF R2 L7 ; goto L7 if var2
       5 [-]: NAMECALL R3 R0 K2; var4 = var0; var3 = var0[0x5E651723]
       6 [-]: CALL R3 2 2  ; var3 = var3(var4)
       7 [-]: FASTCALL1 62 R3 L1; 
       8 [-]: GETIMPORT R2 1; var2 = 0x7B998233
       9 [-]: CALL R2 2 2  ; var2 = var2(var3)
L 1:  10 [-]: JUMPIF R2 L7 ; goto L7 if var2
      11 [-]: GETIMPORT R2 4; var2 = 0x3D106989
      12 [-]: LOADK R4 K5  ; var4 = "Setting up avatar with player "
      13 [-]: GETIMPORT R5 7; var5 = 0x64FB1586
      14 [-]: NAMECALL R6 R0 K2; var7 = var0; var6 = var0[0x5E651723]
      15 [-]: CALL R6 2 2  ; var6 = var6(var7)
      16 [-]: NAMECALL R6 R6 K8; var7 = var6; var6 = var6[0x5CA33548]
      17 [-]: CALL R6 2 0  ; var6, ... = var6(var7)
      18 [-]: CALL R5 0 2  ; var5 = var5(var6, ...)
      19 [-]: CONCAT R3 R4 R5; var3 = var4 .. var5
      20 [-]: CALL R2 2 1  ; var2(var3)
      21 [-]: NAMECALL R2 R0 K9; var3 = var0; var2 = var0[0xDE321E6F]
      22 [-]: CALL R2 2 2  ; var2 = var2(var3)
      23 [-]: GETIMPORT R3 11; var3 = 0x89326C93
      24 [-]: NAMECALL R3 R3 K12; var4 = var3; var3 = var3[0x18D05D30]
      25 [-]: CALL R3 2 2  ; var3 = var3(var4)
      26 [-]: JUMPIFNOT R3 L2; goto L2 if not var3
      27 [-]: LOADN R5 75  ; var5 = 75
      28 [-]: LOADN R6 4   ; var6 = 4
      29 [-]: LOADN R7 1   ; var7 = 1
      30 [-]: NAMECALL R3 R2 K13; var4 = var2; var3 = var2[0x5E6704FF]
      31 [-]: CALL R3 5 1  ; var3(var4, var5, var6, var7)
      32 [-]: LOADN R5 144 ; var5 = 144
      33 [-]: LOADN R6 4   ; var6 = 4
      34 [-]: LOADN R7 0   ; var7 = 0
      35 [-]: NAMECALL R3 R2 K13; var4 = var2; var3 = var2[0x5E6704FF]
      36 [-]: CALL R3 5 1  ; var3(var4, var5, var6, var7)
      37 [-]: LOADN R5 64  ; var5 = 64
      38 [-]: LOADN R6 4   ; var6 = 4
      39 [-]: LOADN R7 0   ; var7 = 0
      40 [-]: NAMECALL R3 R2 K13; var4 = var2; var3 = var2[0x5E6704FF]
      41 [-]: CALL R3 5 1  ; var3(var4, var5, var6, var7)
      42 [-]: LOADN R5 66  ; var5 = 66
      43 [-]: LOADN R6 4   ; var6 = 4
      44 [-]: GETIMPORT R7 15; var7 = 0x465ECCF1
      45 [-]: NAMECALL R3 R2 K13; var4 = var2; var3 = var2[0x5E6704FF]
      46 [-]: CALL R3 5 1  ; var3(var4, var5, var6, var7)
      47 [-]: LOADN R5 123 ; var5 = 123
      48 [-]: LOADN R6 4   ; var6 = 4
      49 [-]: LOADN R7 0   ; var7 = 0
      50 [-]: NAMECALL R3 R2 K13; var4 = var2; var3 = var2[0x5E6704FF]
      51 [-]: CALL R3 5 1  ; var3(var4, var5, var6, var7)
L 2:  52 [-]: GETIMPORT R5 15; var5 = 0x465ECCF1
      53 [-]: NAMECALL R3 R0 K16; var4 = var0; var3 = var0[0x014DB014]
      54 [-]: CALL R3 3 1  ; var3(var4, var5)
      55 [-]: NAMECALL R3 R0 K17; var4 = var0; var3 = var0[0x1AC1655C]
      56 [-]: CALL R3 2 2  ; var3 = var3(var4)
      57 [-]: LOADN R5 0   ; var5 = 0
      58 [-]: NAMECALL R3 R3 K18; var4 = var3; var3 = var3[0x57369B8B]
      59 [-]: CALL R3 3 1  ; var3(var4, var5)
      60 [-]: GETUPVAL R3 0; var3 = upvalues[0]
      61 [-]: MOVE R4 R0   ; var4 = var0
      62 [-]: CALL R3 2 1  ; var3(var4)
      63 [-]: NAMECALL R3 R2 K19; var4 = var2; var3 = var2[0xF7D48EE0]
      64 [-]: CALL R3 2 2  ; var3 = var3(var4)
      65 [-]: FASTCALL1 62 R3 L3; 
      66 [-]: MOVE R5 R3   ; var5 = var3
      67 [-]: GETIMPORT R4 1; var4 = 0x7B998233
      68 [-]: CALL R4 2 2  ; var4 = var4(var5)
L 3:  69 [-]: JUMPIF R4 L4 ; goto L4 if var4
      70 [-]: LOADB R6 0   ; var6 = false
      71 [-]: NAMECALL R4 R3 K20; var5 = var3; var4 = var3[0x250C88D6]
      72 [-]: CALL R4 3 1  ; var4(var5, var6)
      73 [-]: JUMP L5      ; goto L5
L 4:  74 [-]: GETIMPORT R4 4; var4 = 0x3D106989
      75 [-]: LOADK R6 K21 ; var6 = "NULL POWERSUIT TRYING TO SETUP AVATAR "
      76 [-]: GETIMPORT R7 7; var7 = 0x64FB1586
      77 [-]: NAMECALL R8 R0 K22; var9 = var0; var8 = var0[0xED4E0128]
      78 [-]: CALL R8 2 0  ; var8, ... = var8(var9)
      79 [-]: CALL R7 0 2  ; var7 = var7(var8, ...)
      80 [-]: CONCAT R5 R6 R7; var5 = var6 .. var7
      81 [-]: CALL R4 2 1  ; var4(var5)
L 5:  82 [-]: GETIMPORT R5 24; var5 = 0x22B09C78
      83 [-]: FASTCALL1 62 R5 L6; 
      84 [-]: GETIMPORT R4 1; var4 = 0x7B998233
      85 [-]: CALL R4 2 2  ; var4 = var4(var5)
L 6:  86 [-]: JUMPIF R4 L7 ; goto L7 if var4
      87 [-]: GETIMPORT R6 24; var6 = 0x22B09C78
      88 [-]: LOADN R7 2   ; var7 = 2
      89 [-]: LOADB R8 1   ; var8 = true
      90 [-]: NAMECALL R4 R0 K25; var5 = var0; var4 = var0[0x1C661E00]
      91 [-]: CALL R4 5 1  ; var4(var5, var6, var7, var8)
L 7:  92 [-]: RETURN R0 0  ; 


; Name:            
; Defined at line: 336
; #Upvalues:       0
; #Parameters:     0
; Is_vararg:       0
; Max Stack Size:  10

       0 [-]: GETIMPORT R0 1; var0 = 0xCFC01047
       1 [-]: GETIMPORT R1 3; var1 = 0x89326C93
       2 [-]: NAMECALL R1 R1 K4; var2 = var1; var1 = var1[0x7D108DDB]
       3 [-]: CALL R1 2 0  ; var1, ... = var1(var2)
       4 [-]: CALL R0 0 4  ; var0, var1, var2 = var0(var1, ...)
       5 [-]: FORGPREP_NEXT R0 L2; 
L 0:   6 [-]: NAMECALL R5 R4 K5; var6 = var4; var5 = var4[0xBB610E5B]
       7 [-]: CALL R5 2 2  ; var5 = var5(var6)
       8 [-]: FASTCALL1 62 R5 L1; 
       9 [-]: MOVE R7 R5   ; var7 = var5
      10 [-]: GETIMPORT R6 7; var6 = 0x7B998233
      11 [-]: CALL R6 2 2  ; var6 = var6(var7)
L 1:  12 [-]: JUMPIF R6 L2 ; goto L2 if var6
      13 [-]: NAMECALL R6 R5 K8; var7 = var5; var6 = var5[0x2047CFE7]
      14 [-]: CALL R6 2 2  ; var6 = var6(var7)
      15 [-]: JUMPIF R6 L2 ; goto L2 if var6
      16 [-]: NAMECALL R6 R5 K9; var7 = var5; var6 = var5[0xDE321E6F]
      17 [-]: CALL R6 2 2  ; var6 = var6(var7)
      18 [-]: NAMECALL R6 R6 K10; var7 = var6; var6 = var6[0xF7D48EE0]
      19 [-]: CALL R6 2 2  ; var6 = var6(var7)
      20 [-]: LOADB R8 0   ; var8 = false
      21 [-]: LOADB R9 1   ; var9 = true
      22 [-]: NAMECALL R6 R6 K11; var7 = var6; var6 = var6[0x1BF26251]
      23 [-]: CALL R6 4 1  ; var6(var7, var8, var9)
L 2:  24 [-]: FORGLOOP R0 L0 2; 
      25 [-]: RETURN R0 0  ; 


; Name:            
; Defined at line: 345
; #Upvalues:       2
; #Parameters:     1
; Is_vararg:       0
; Max Stack Size:  14

       0 [-]: NAMECALL R1 R0 K0; var2 = var0; var1 = var0[0xDE321E6F]
       1 [-]: CALL R1 2 2  ; var1 = var1(var2)
       2 [-]: NAMECALL R2 R1 K1; var3 = var1; var2 = var1[0xF7D48EE0]
       3 [-]: CALL R2 2 2  ; var2 = var2(var3)
       4 [-]: FASTCALL1 62 R2 L0; 
       5 [-]: MOVE R4 R2   ; var4 = var2
       6 [-]: GETIMPORT R3 3; var3 = 0x7B998233
       7 [-]: CALL R3 2 2  ; var3 = var3(var4)
L 0:   8 [-]: JUMPIF R3 L1 ; goto L1 if var3
       9 [-]: GETIMPORT R3 5; var3 = 0xBE190284
      10 [-]: NAMECALL R3 R3 K6; var4 = var3; var3 = var3[0xC911409E]
      11 [-]: CALL R3 2 2  ; var3 = var3(var4)
      12 [-]: LOADN R6 91  ; var6 = 91
      13 [-]: LOADN R7 4   ; var7 = 4
      14 [-]: MOVE R8 R3   ; var8 = var3
      15 [-]: NAMECALL R4 R1 K7; var5 = var1; var4 = var1[0x5E6704FF]
      16 [-]: CALL R4 5 1  ; var4(var5, var6, var7, var8)
      17 [-]: LOADN R6 92  ; var6 = 92
      18 [-]: LOADN R7 4   ; var7 = 4
      19 [-]: LOADN R8 0   ; var8 = 0
      20 [-]: NAMECALL R4 R1 K7; var5 = var1; var4 = var1[0x5E6704FF]
      21 [-]: CALL R4 5 1  ; var4(var5, var6, var7, var8)
      22 [-]: NAMECALL R5 R1 K1; var6 = var1; var5 = var1[0xF7D48EE0]
      23 [-]: CALL R5 2 2  ; var5 = var5(var6)
      24 [-]: NAMECALL R5 R5 K9; var6 = var5; var5 = var5[0xE7384669]
      25 [-]: CALL R5 2 2  ; var5 = var5(var6)
      26 [-]: SUBK R4 R5 K8; var4 = var5 - 1
      27 [-]: LOADN R6 1   ; var6 = 1
      28 [-]: GETIMPORT R8 11; var8 = 0x43930F18
      29 [-]: MUL R7 R4 R8 ; var7 = var4 * var8
      30 [-]: ADD R5 R6 R7 ; var5 = var6 + var7
      31 [-]: LOADN R8 83  ; var8 = 83
      32 [-]: LOADN R9 4   ; var9 = 4
      33 [-]: MOVE R10 R5  ; var10 = var5
      34 [-]: NAMECALL R6 R1 K7; var7 = var1; var6 = var1[0x5E6704FF]
      35 [-]: CALL R6 5 1  ; var6(var7, var8, var9, var10)
      36 [-]: LOADN R8 73  ; var8 = 73
      37 [-]: LOADN R9 4   ; var9 = 4
      38 [-]: MOVE R10 R5  ; var10 = var5
      39 [-]: NAMECALL R6 R1 K7; var7 = var1; var6 = var1[0x5E6704FF]
      40 [-]: CALL R6 5 1  ; var6(var7, var8, var9, var10)
      41 [-]: GETIMPORT R7 13; var7 = 0xAA51A169
      42 [-]: MUL R6 R5 R7 ; var6 = var5 * var7
      43 [-]: LOADN R9 246 ; var9 = 246
      44 [-]: LOADN R10 4  ; var10 = 4
      45 [-]: MOVE R11 R6  ; var11 = var6
      46 [-]: NAMECALL R7 R1 K7; var8 = var1; var7 = var1[0x5E6704FF]
      47 [-]: CALL R7 5 1  ; var7(var8, var9, var10, var11)
      48 [-]: MINUS R7 R4  ; 
      49 [-]: LOADN R10 1  ; var10 = 1
      50 [-]: ADD R9 R10 R7; var9 = var10 + var7
      51 [-]: GETIMPORT R10 15; var10 = 0x1E5117AA
      52 [-]: MUL R8 R9 R10; var8 = var9 * var10
      53 [-]: LOADN R11 292; var11 = 292
      54 [-]: LOADN R12 2  ; var12 = 2
      55 [-]: MOVE R13 R8  ; var13 = var8
      56 [-]: NAMECALL R9 R1 K16; var10 = var1; var9 = var1[0x12DD9DA2]
      57 [-]: CALL R9 5 1  ; var9(var10, var11, var12, var13)
      58 [-]: LOADN R11 292; var11 = 292
      59 [-]: LOADN R12 2  ; var12 = 2
      60 [-]: MOVE R13 R8  ; var13 = var8
      61 [-]: NAMECALL R9 R1 K7; var10 = var1; var9 = var1[0x5E6704FF]
      62 [-]: CALL R9 5 1  ; var9(var10, var11, var12, var13)
      63 [-]: MOVE R11 R3  ; var11 = var3
      64 [-]: NAMECALL R9 R2 K17; var10 = var2; var9 = var2[0xDF93C3EC]
      65 [-]: CALL R9 3 1  ; var9(var10, var11)
      66 [-]: NAMECALL R9 R0 K0; var10 = var0; var9 = var0[0xDE321E6F]
      67 [-]: CALL R9 2 2  ; var9 = var9(var10)
      68 [-]: NAMECALL R9 R9 K1; var10 = var9; var9 = var9[0xF7D48EE0]
      69 [-]: CALL R9 2 2  ; var9 = var9(var10)
      70 [-]: LOADB R11 0  ; var11 = false
      71 [-]: NAMECALL R9 R9 K18; var10 = var9; var9 = var9[0x250C88D6]
      72 [-]: CALL R9 3 1  ; var9(var10, var11)
      73 [-]: JUMP L2      ; goto L2
L 1:  74 [-]: GETIMPORT R3 20; var3 = 0x3D106989
      75 [-]: LOADK R5 K21 ; var5 = "NULL SUIT FOR AVATAR "
      76 [-]: GETIMPORT R8 23; var8 = 0x64FB1586
      77 [-]: NAMECALL R9 R0 K24; var10 = var0; var9 = var0[0xED4E0128]
      78 [-]: CALL R9 2 0  ; var9, ... = var9(var10)
      79 [-]: CALL R8 0 2  ; var8 = var8(var9, ...)
      80 [-]: MOVE R6 R8   ; var6 = var8
      81 [-]: LOADK R7 K25 ; var7 = "!!!!"
      82 [-]: CONCAT R4 R5 R7; var4 = var5 .. var7
      83 [-]: CALL R3 2 1  ; var3(var4)
L 2:  84 [-]: GETUPVAL R3 0; var3 = upvalues[0]
      85 [-]: LOADN R4 1   ; var4 = 1
      86 [-]: JUMPIFNOTLT R4 R3 L3; goto L3 if var4 >= var1770318
      87 [-]: GETIMPORT R3 27; var3 = 0x89326C93
      88 [-]: NAMECALL R3 R3 K28; var4 = var3; var3 = var3[0x18D05D30]
      89 [-]: CALL R3 2 2  ; var3 = var3(var4)
      90 [-]: JUMPIFNOT R3 L3; goto L3 if not var3
      91 [-]: GETUPVAL R3 1; var3 = upvalues[1]
      92 [-]: MOVE R4 R0   ; var4 = var0
      93 [-]: CALL R3 2 1  ; var3(var4)
L 3:  94 [-]: GETIMPORT R5 30; var5 = 0x465ECCF1
      95 [-]: NAMECALL R3 R0 K31; var4 = var0; var3 = var0[0x014DB014]
      96 [-]: CALL R3 3 1  ; var3(var4, var5)
      97 [-]: GETIMPORT R4 33; var4 = 0x22B09C78
      98 [-]: FASTCALL1 62 R4 L4; 
      99 [-]: GETIMPORT R3 3; var3 = 0x7B998233
     100 [-]: CALL R3 2 2  ; var3 = var3(var4)
L 4: 101 [-]: JUMPIF R3 L5 ; goto L5 if var3
     102 [-]: GETIMPORT R5 33; var5 = 0x22B09C78
     103 [-]: LOADN R6 2   ; var6 = 2
     104 [-]: LOADB R7 1   ; var7 = true
     105 [-]: NAMECALL R3 R0 K34; var4 = var0; var3 = var0[0x1C661E00]
     106 [-]: CALL R3 5 1  ; var3(var4, var5, var6, var7)
     107 [-]: GETIMPORT R3 20; var3 = 0x3D106989
     108 [-]: LOADK R4 K35 ; var4 = "Setting idle override"
     109 [-]: CALL R3 2 1  ; var3(var4)
L 5: 110 [-]: RETURN R0 0  ; 


; Name:            
; Defined at line: 387
; #Upvalues:       1
; #Parameters:     1
; Is_vararg:       0
; Max Stack Size:  4

       0 [-]: GETIMPORT R1 1; var1 = 0x3D106989
       1 [-]: LOADK R2 K2  ; var2 = "OnMatchStarted"
       2 [-]: CALL R1 2 1  ; var1(var2)
       3 [-]: LOADB R3 0   ; var3 = false
       4 [-]: NAMECALL R1 R0 K3; var2 = var0; var1 = var0[0xBF45A5BB]
       5 [-]: CALL R1 3 1  ; var1(var2, var3)
       6 [-]: GETIMPORT R3 5; var3 = gLotusLocalFightingGameRulesType
       7 [-]: NAMECALL R1 R0 K6; var2 = var0; var1 = var0[0xF2DEAF69]
       8 [-]: CALL R1 3 2  ; var1 = var1(var2, var3)
       9 [-]: SETUPVAL R1 0; upvalues[1] = var0
      10 [-]: RETURN R0 0  ; 


; Name:            
; Defined at line: 393
; #Upvalues:       0
; #Parameters:     2
; Is_vararg:       0
; Max Stack Size:  7

       0 [-]: GETIMPORT R2 1; var2 = 0x3D106989
       1 [-]: LOADK R4 K2  ; var4 = "DB RESULT: "
       2 [-]: GETIMPORT R5 4; var5 = 0x64FB1586
       3 [-]: MOVE R6 R0   ; var6 = var0
       4 [-]: CALL R5 2 2  ; var5 = var5(var6)
       5 [-]: CONCAT R3 R4 R5; var3 = var4 .. var5
       6 [-]: CALL R2 2 1  ; var2(var3)
       7 [-]: RETURN R0 0  ; 


; Name:            
; Defined at line: 397
; #Upvalues:       10
; #Parameters:     2
; Is_vararg:       0
; Max Stack Size:  12

       0 [-]: GETIMPORT R2 1; var2 = 0x3D106989
       1 [-]: LOADK R3 K2  ; var3 = "OnMatchEnded"
       2 [-]: CALL R2 2 1  ; var2(var3)
       3 [-]: GETIMPORT R2 4; var2 = 0x89326C93
       4 [-]: NAMECALL R2 R2 K5; var3 = var2; var2 = var2[0x18D05D30]
       5 [-]: CALL R2 2 2  ; var2 = var2(var3)
       6 [-]: JUMPIFNOT R2 L0; goto L0 if not var2
       7 [-]: GETUPVAL R2 0; var2 = upvalues[0]
       8 [-]: CALL R2 1 1  ; var2()
L 0:   9 [-]: GETIMPORT R4 7; var4 = 0x97B85C09
      10 [-]: NAMECALL R2 R0 K8; var3 = var0; var2 = var0[0xD761A7A1]
      11 [-]: CALL R2 3 1  ; var2(var3, var4)
      12 [-]: LOADB R2 1   ; var2 = true
      13 [-]: SETUPVAL R2 1; upvalues[2] = var1
      14 [-]: LOADN R2 0   ; var2 = 0
      15 [-]: SETUPVAL R2 2; upvalues[2] = var2
      16 [-]: FASTCALL1 62 R1 L1; 
      17 [-]: MOVE R3 R1   ; var3 = var1
      18 [-]: GETIMPORT R2 10; var2 = 0x7B998233
      19 [-]: CALL R2 2 2  ; var2 = var2(var3)
L 1:  20 [-]: JUMPIF R2 L2 ; goto L2 if var2
      21 [-]: GETUPVAL R2 3; var2 = upvalues[3]
      22 [-]: LOADB R3 1   ; var3 = true
      23 [-]: MOVE R4 R1   ; var4 = var1
      24 [-]: CALL R2 3 1  ; var2(var3, var4)
L 2:  25 [-]: GETUPVAL R2 4; var2 = upvalues[4]
      26 [-]: CALL R2 1 1  ; var2()
      27 [-]: FASTCALL1 62 R1 L3; 
      28 [-]: MOVE R3 R1   ; var3 = var1
      29 [-]: GETIMPORT R2 10; var2 = 0x7B998233
      30 [-]: CALL R2 2 2  ; var2 = var2(var3)
L 3:  31 [-]: JUMPIFNOT R2 L6; goto L6 if not var2
      32 [-]: GETIMPORT R3 13; var3 = _T["ShowImpactMessage"]
      33 [-]: FASTCALL1 62 R3 L4; 
      34 [-]: GETIMPORT R2 10; var2 = 0x7B998233
      35 [-]: CALL R2 2 2  ; var2 = var2(var3)
L 4:  36 [-]: JUMPIF R2 L5 ; goto L5 if var2
      37 [-]: GETIMPORT R2 13; var2 = _T["ShowImpactMessage"]
      38 [-]: GETIMPORT R3 15; var3 = 0x603636AD
      39 [-]: LOADK R4 K16 ; var4 = "/Lotus/Language/Game/Fighter_Draw"
      40 [-]: LOADB R5 0   ; var5 = false
      41 [-]: CALL R3 3 2  ; var3 = var3(var4, var5)
      42 [-]: LOADN R4 3   ; var4 = 3
      43 [-]: CALL R2 3 1  ; var2(var3, var4)
L 5:  44 [-]: GETUPVAL R3 5; var3 = upvalues[5]
      45 [-]: GETTABLEKS R2 R3 K17; var2 = var3[0x659D451F]
      46 [-]: GETIMPORT R3 19; var3 = 0x5C44C965
      47 [-]: CALL R2 2 1  ; var2(var3)
      48 [-]: JUMP L17     ; goto L17
L 6:  49 [-]: GETUPVAL R2 6; var2 = upvalues[6]
      50 [-]: JUMPIFNOT R2 L11; goto L11 if not var2
      51 [-]: NAMECALL R2 R1 K20; var3 = var1; var2 = var1[0xBB610E5B]
      52 [-]: CALL R2 2 2  ; var2 = var2(var3)
      53 [-]: FASTCALL1 62 R2 L7; 
      54 [-]: MOVE R4 R2   ; var4 = var2
      55 [-]: GETIMPORT R3 10; var3 = 0x7B998233
      56 [-]: CALL R3 2 2  ; var3 = var3(var4)
L 7:  57 [-]: JUMPIF R3 L10; goto L10 if var3
      58 [-]: NAMECALL R3 R2 K21; var4 = var2; var3 = var2[0xDE321E6F]
      59 [-]: CALL R3 2 2  ; var3 = var3(var4)
      60 [-]: NAMECALL R3 R3 K22; var4 = var3; var3 = var3[0xF7D48EE0]
      61 [-]: CALL R3 2 2  ; var3 = var3(var4)
      62 [-]: FASTCALL1 62 R3 L8; 
      63 [-]: MOVE R5 R3   ; var5 = var3
      64 [-]: GETIMPORT R4 10; var4 = 0x7B998233
      65 [-]: CALL R4 2 2  ; var4 = var4(var5)
L 8:  66 [-]: JUMPIF R4 L17; goto L17 if var4
      67 [-]: GETIMPORT R5 13; var5 = _T["ShowImpactMessage"]
      68 [-]: FASTCALL1 62 R5 L9; 
      69 [-]: GETIMPORT R4 10; var4 = 0x7B998233
      70 [-]: CALL R4 2 2  ; var4 = var4(var5)
L 9:  71 [-]: JUMPIF R4 L17; goto L17 if var4
      72 [-]: GETIMPORT R4 13; var4 = _T["ShowImpactMessage"]
      73 [-]: GETIMPORT R8 15; var8 = 0x603636AD
      74 [-]: GETIMPORT R9 24; var9 = 0x64FB1586
      75 [-]: NAMECALL R10 R3 K25; var11 = var3; var10 = var3[0xD3A9D01F]
      76 [-]: CALL R10 2 0 ; var10, ... = var10(var11)
      77 [-]: CALL R9 0 2  ; var9 = var9(var10, ...)
      78 [-]: LOADNIL R10  ; var10 = nil
      79 [-]: CALL R8 3 2  ; var8 = var8(var9, var10)
      80 [-]: MOVE R6 R8   ; var6 = var8
      81 [-]: LOADK R7 K26 ; var7 = " WINS!"
      82 [-]: CONCAT R5 R6 R7; var5 = var6 .. var7
      83 [-]: LOADN R6 3   ; var6 = 3
      84 [-]: CALL R4 3 1  ; var4(var5, var6)
      85 [-]: JUMP L17     ; goto L17
L10:  86 [-]: GETIMPORT R3 1; var3 = 0x3D106989
      87 [-]: LOADK R4 K27 ; var4 = "NANI!?"
      88 [-]: CALL R3 2 1  ; var3(var4)
      89 [-]: JUMP L17     ; goto L17
L11:  90 [-]: GETIMPORT R2 4; var2 = 0x89326C93
      91 [-]: NAMECALL R2 R2 K28; var3 = var2; var2 = var2[0xFB64E76C]
      92 [-]: CALL R2 2 2  ; var2 = var2(var3)
      93 [-]: JUMPIFNOTEQ R1 R2 L14; goto L14 if var1 ~= var852814
      94 [-]: GETIMPORT R3 13; var3 = _T["ShowImpactMessage"]
      95 [-]: FASTCALL1 62 R3 L12; 
      96 [-]: GETIMPORT R2 10; var2 = 0x7B998233
      97 [-]: CALL R2 2 2  ; var2 = var2(var3)
L12:  98 [-]: JUMPIF R2 L13; goto L13 if var2
      99 [-]: GETIMPORT R2 13; var2 = _T["ShowImpactMessage"]
     100 [-]: GETIMPORT R3 15; var3 = 0x603636AD
     101 [-]: LOADK R4 K29 ; var4 = "/Lotus/Language/Game/Fighter_Win"
     102 [-]: LOADB R5 0   ; var5 = false
     103 [-]: CALL R3 3 2  ; var3 = var3(var4, var5)
     104 [-]: LOADN R4 3   ; var4 = 3
     105 [-]: CALL R2 3 1  ; var2(var3, var4)
L13: 106 [-]: GETUPVAL R3 5; var3 = upvalues[5]
     107 [-]: GETTABLEKS R2 R3 K17; var2 = var3[0x659D451F]
     108 [-]: GETIMPORT R3 31; var3 = 0xF1929D5B
     109 [-]: CALL R2 2 1  ; var2(var3)
     110 [-]: JUMP L17     ; goto L17
L14: 111 [-]: GETIMPORT R3 13; var3 = _T["ShowImpactMessage"]
     112 [-]: FASTCALL1 62 R3 L15; 
     113 [-]: GETIMPORT R2 10; var2 = 0x7B998233
     114 [-]: CALL R2 2 2  ; var2 = var2(var3)
L15: 115 [-]: JUMPIF R2 L16; goto L16 if var2
     116 [-]: GETIMPORT R2 13; var2 = _T["ShowImpactMessage"]
     117 [-]: GETIMPORT R3 15; var3 = 0x603636AD
     118 [-]: LOADK R4 K32 ; var4 = "/Lotus/Language/Game/Fighter_Lose"
     119 [-]: LOADB R5 0   ; var5 = false
     120 [-]: CALL R3 3 2  ; var3 = var3(var4, var5)
     121 [-]: LOADN R4 3   ; var4 = 3
     122 [-]: CALL R2 3 1  ; var2(var3, var4)
L16: 123 [-]: GETUPVAL R3 5; var3 = upvalues[5]
     124 [-]: GETTABLEKS R2 R3 K17; var2 = var3[0x659D451F]
     125 [-]: GETIMPORT R3 34; var3 = 0xCD1D81A9
     126 [-]: CALL R2 2 1  ; var2(var3)
L17: 127 [-]: LOADN R2 1   ; var2 = 1
     128 [-]: SETUPVAL R2 7; upvalues[2] = var7
     129 [-]: LOADN R2 0   ; var2 = 0
     130 [-]: SETUPVAL R2 8; upvalues[2] = var8
     131 [-]: LOADN R2 -1  ; var2 = -1
     132 [-]: SETUPVAL R2 9; upvalues[2] = var9
     133 [-]: GETIMPORT R2 36; var2 = _T["ShowRoundInfo"]
     134 [-]: JUMPIFNOT R2 L18; goto L18 if not var2
     135 [-]: GETIMPORT R2 36; var2 = _T["ShowRoundInfo"]
     136 [-]: LOADB R3 0   ; var3 = false
     137 [-]: CALL R2 2 1  ; var2(var3)
L18: 138 [-]: GETIMPORT R2 38; var2 = _T["SetFightingGameCameraOffset"]
     139 [-]: LOADN R3 0   ; var3 = 0
     140 [-]: LOADK R4 K39 ; var4 = 3.5
     141 [-]: CALL R2 3 1  ; var2(var3, var4)
     142 [-]: GETIMPORT R2 41; var2 = 0xBE190284
     143 [-]: LOADK R4 K42 ; var4 = "OnDBUpdateCompleted"
     144 [-]: NAMECALL R2 R2 K43; var3 = var2; var2 = var2[0x8AEC9909]
     145 [-]: CALL R2 3 1  ; var2(var3, var4)
     146 [-]: RETURN R0 0  ; 


; Name:            
; Defined at line: 452
; #Upvalues:       1
; #Parameters:     1
; Is_vararg:       0
; Max Stack Size:  13

       0 [-]: GETIMPORT R1 1; var1 = 0x89326C93
       1 [-]: NAMECALL R1 R1 K2; var2 = var1; var1 = var1[0x7D108DDB]
       2 [-]: CALL R1 2 2  ; var1 = var1(var2)
       3 [-]: LOADN R4 1   ; var4 = 1
       4 [-]: LENGTH R2 R1 ; var2 = #var1
       5 [-]: LOADN R3 1   ; var3 = 1
       6 [-]: FORNPREP R2 L1; nforprep start - [escape at L1] -- var2 = iterator
L 0:   7 [-]: GETTABLE R7 R1 R4; var7 = var1[var4]
       8 [-]: GETIMPORT R8 4; var8 = 0x603636AD
       9 [-]: LOADK R9 K5  ; var9 = "/Lotus/Language/Game/Fight"
      10 [-]: LOADB R10 0  ; var10 = false
      11 [-]: CALL R8 3 2  ; var8 = var8(var9, var10)
      12 [-]: LOADK R9 K6  ; var9 = ""
      13 [-]: LOADN R10 0  ; var10 = 0
      14 [-]: LOADN R11 2  ; var11 = 2
      15 [-]: LOADB R12 1  ; var12 = true
      16 [-]: NAMECALL R5 R0 K7; var6 = var0; var5 = var0[0x06D4C9EB]
      17 [-]: CALL R5 8 1  ; var5(var6, var7, var8, var9, var10, var11, var12)
      18 [-]: FORNLOOP R2 L0; nforloop end - iterate + goto L0
L 1:  19 [-]: GETUPVAL R3 0; var3 = upvalues[0]
      20 [-]: GETTABLEKS R2 R3 K8; var2 = var3[0x659D451F]
      21 [-]: GETIMPORT R3 10; var3 = 0xDC929F57
      22 [-]: CALL R2 2 1  ; var2(var3)
      23 [-]: RETURN R0 0  ; 


; Name:            
; Defined at line: 461
; #Upvalues:       2
; #Parameters:     1
; Is_vararg:       0
; Max Stack Size:  4

       0 [-]: GETIMPORT R1 2; var1 = _T["ShowRoundInfo"]
       1 [-]: JUMPIFNOT R1 L0; goto L0 if not var1
       2 [-]: GETIMPORT R1 2; var1 = _T["ShowRoundInfo"]
       3 [-]: LOADB R2 1   ; var2 = true
       4 [-]: CALL R1 2 1  ; var1(var2)
L 0:   5 [-]: GETIMPORT R1 4; var1 = _T["SetFightingGameCameraOffset"]
       6 [-]: GETUPVAL R2 0; var2 = upvalues[0]
       7 [-]: GETUPVAL R3 1; var3 = upvalues[1]
       8 [-]: CALL R1 3 1  ; var1(var2, var3)
       9 [-]: RETURN R0 0  ; 


; Name:            
; Defined at line: 469
; #Upvalues:       6
; #Parameters:     2
; Is_vararg:       0
; Max Stack Size:  16

       0 [-]: GETIMPORT R2 1; var2 = 0x3D106989
       1 [-]: LOADK R3 K2  ; var3 = "OnQueueNewRound"
       2 [-]: CALL R2 2 1  ; var2(var3)
       3 [-]: SETUPVAL R1 0; upvalues[1] = var0
       4 [-]: GETIMPORT R2 4; var2 = 0x89326C93
       5 [-]: NAMECALL R2 R2 K5; var3 = var2; var2 = var2[0x7D108DDB]
       6 [-]: CALL R2 2 2  ; var2 = var2(var3)
       7 [-]: JUMPXEQKNIL R2 L5; 
       8 [-]: LOADN R5 1   ; var5 = 1
       9 [-]: LENGTH R3 R2 ; var3 = #var2
      10 [-]: LOADN R4 1   ; var4 = 1
      11 [-]: FORNPREP R3 L5; nforprep start - [escape at L5] -- var3 = iterator
L 0:  12 [-]: GETTABLE R6 R2 R5; var6 = var2[var5]
      13 [-]: NAMECALL R6 R6 K6; var7 = var6; var6 = var6[0xBB610E5B]
      14 [-]: CALL R6 2 2  ; var6 = var6(var7)
      15 [-]: FASTCALL1 62 R6 L1; 
      16 [-]: MOVE R8 R6   ; var8 = var6
      17 [-]: GETIMPORT R7 8; var7 = 0x7B998233
      18 [-]: CALL R7 2 2  ; var7 = var7(var8)
L 1:  19 [-]: JUMPIF R7 L4 ; goto L4 if var7
      20 [-]: NAMECALL R7 R6 K9; var8 = var6; var7 = var6[0x2047CFE7]
      21 [-]: CALL R7 2 2  ; var7 = var7(var8)
      22 [-]: JUMPIF R7 L4 ; goto L4 if var7
      23 [-]: GETUPVAL R7 1; var7 = upvalues[1]
      24 [-]: JUMPIFNOT R7 L2; goto L2 if not var7
      25 [-]: NAMECALL R8 R6 K10; var9 = var6; var8 = var6[0xDE321E6F]
      26 [-]: CALL R8 2 2  ; var8 = var8(var9)
      27 [-]: NAMECALL R8 R8 K11; var9 = var8; var8 = var8[0xF7D48EE0]
      28 [-]: CALL R8 2 2  ; var8 = var8(var9)
      29 [-]: FASTCALL1 62 R8 L2; 
      30 [-]: GETIMPORT R7 8; var7 = 0x7B998233
      31 [-]: CALL R7 2 2  ; var7 = var7(var8)
L 2:  32 [-]: JUMPIF R7 L3 ; goto L3 if var7
      33 [-]: GETUPVAL R8 2; var8 = upvalues[2]
      34 [-]: MOVE R9 R6   ; var9 = var6
      35 [-]: CALL R8 2 1  ; var8(var9)
      36 [-]: JUMP L4      ; goto L4
L 3:  37 [-]: GETUPVAL R8 3; var8 = upvalues[3]
      38 [-]: LOADB R9 1   ; var9 = true
      39 [-]: SETTABLE R9 R8 R5; var9[var8] = var5
L 4:  40 [-]: GETIMPORT R7 13; var7 = 0x603636AD
      41 [-]: LOADK R8 K14 ; var8 = "/Lotus/Language/Game/Fighter_Round"
      42 [-]: DUPTABLE R9 16; 
      43 [-]: SETTABLEKS R1 R9 K15; var1["NUM"] = var9
      44 [-]: CALL R7 3 2  ; var7 = var7(var8, var9)
      45 [-]: GETTABLE R10 R2 R5; var10 = var2[var5]
      46 [-]: MOVE R11 R7  ; var11 = var7
      47 [-]: LOADK R12 K17; var12 = ""
      48 [-]: LOADN R13 0  ; var13 = 0
      49 [-]: LOADN R14 2  ; var14 = 2
      50 [-]: LOADB R15 1  ; var15 = true
      51 [-]: NAMECALL R8 R0 K18; var9 = var0; var8 = var0[0x06D4C9EB]
      52 [-]: CALL R8 8 1  ; var8(var9, var10, var11, var12, var13, var14, var15)
      53 [-]: FORNLOOP R3 L0; nforloop end - iterate + goto L0
L 5:  54 [-]: LOADN R3 5   ; var3 = 5
      55 [-]: SETUPVAL R3 4; upvalues[3] = var4
      56 [-]: GETUPVAL R4 5; var4 = upvalues[5]
      57 [-]: GETTABLEKS R3 R4 K19; var3 = var4[0x659D451F]
      58 [-]: GETIMPORT R4 21; var4 = 0x1A199142
      59 [-]: CALL R3 2 1  ; var3(var4)
      60 [-]: RETURN R0 0  ; 


; Name:            
; Defined at line: 495
; #Upvalues:       20
; #Parameters:     2
; Is_vararg:       0
; Max Stack Size:  17

       0 [-]: GETUPVAL R2 0; var2 = upvalues[0]
       1 [-]: JUMPIF R2 L0 ; goto L0 if var2
       2 [-]: GETGLOBAL R2 K0; var2 = 0x8353E0FC
       3 [-]: SETUPVAL R2 1; upvalues[2] = var1
       4 [-]: GETGLOBAL R2 K1; var2 = 0xC367B736
       5 [-]: SETUPVAL R2 2; upvalues[2] = var2
       6 [-]: LOADB R2 1   ; var2 = true
       7 [-]: SETUPVAL R2 0; upvalues[2] = var0
       8 [-]: GETIMPORT R2 3; var2 = 0x3D106989
       9 [-]: LOADK R4 K4  ; var4 = "INITIAL CAMERA VALUES: "
      10 [-]: GETUPVAL R5 1; var5 = upvalues[1]
      11 [-]: LOADK R6 K5  ; var6 = " - "
      12 [-]: GETUPVAL R7 2; var7 = upvalues[2]
      13 [-]: CONCAT R3 R4 R7; var3 = var4 .. var7
      14 [-]: CALL R2 2 1  ; var2(var3)
      15 [-]: GETIMPORT R2 7; var2 = 0x0032441C
      16 [-]: LOADB R3 1   ; var3 = true
      17 [-]: SETTABLEKS R3 R2 K8; var3["PlayedFightingGame"] = var2
L 0:  18 [-]: GETUPVAL R2 3; var2 = upvalues[3]
      19 [-]: JUMPIFNOT R2 L10; goto L10 if not var2
      20 [-]: GETIMPORT R2 10; var2 = 0x89326C93
      21 [-]: NAMECALL R2 R2 K11; var3 = var2; var2 = var2[0x7D108DDB]
      22 [-]: CALL R2 2 2  ; var2 = var2(var3)
      23 [-]: LOADN R5 1   ; var5 = 1
      24 [-]: LENGTH R3 R2 ; var3 = #var2
      25 [-]: LOADN R4 1   ; var4 = 1
      26 [-]: FORNPREP R3 L10; nforprep start - [escape at L10] -- var3 = iterator
L 1:  27 [-]: GETTABLE R6 R2 R5; var6 = var2[var5]
      28 [-]: NAMECALL R6 R6 K12; var7 = var6; var6 = var6[0xBB610E5B]
      29 [-]: CALL R6 2 2  ; var6 = var6(var7)
      30 [-]: NAMECALL R7 R0 K13; var8 = var0; var7 = var0[0x82374F71]
      31 [-]: CALL R7 2 2  ; var7 = var7(var8)
      32 [-]: FASTCALL1 62 R6 L2; 
      33 [-]: MOVE R9 R6   ; var9 = var6
      34 [-]: GETIMPORT R8 15; var8 = 0x7B998233
      35 [-]: CALL R8 2 2  ; var8 = var8(var9)
L 2:  36 [-]: JUMPIF R8 L3 ; goto L3 if var8
      37 [-]: LOADN R8 2   ; var8 = 2
      38 [-]: JUMPIFEQ R7 R8 L4; goto L4 if var7 == var67655
L 3:  39 [-]: LOADN R8 1   ; var8 = 1
      40 [-]: JUMPIFNOTEQ R7 R8 L9; goto L9 if var7 ~= var1862666565
L 4:  41 [-]: NAMECALL R9 R6 K16; var10 = var6; var9 = var6[0xDE321E6F]
      42 [-]: CALL R9 2 2  ; var9 = var9(var10)
      43 [-]: NAMECALL R9 R9 K17; var10 = var9; var9 = var9[0xF7D48EE0]
      44 [-]: CALL R9 2 2  ; var9 = var9(var10)
      45 [-]: FASTCALL1 62 R9 L5; 
      46 [-]: GETIMPORT R8 15; var8 = 0x7B998233
      47 [-]: CALL R8 2 2  ; var8 = var8(var9)
L 5:  48 [-]: GETUPVAL R10 4; var10 = upvalues[4]
      49 [-]: GETTABLE R9 R10 R5; var9 = var10[var5]
      50 [-]: JUMPIF R9 L6 ; goto L6 if var9
      51 [-]: JUMPIFNOT R8 L9; goto L9 if not var8
L 6:  52 [-]: GETTABLE R11 R2 R5; var11 = var2[var5]
      53 [-]: NAMECALL R9 R0 K18; var10 = var0; var9 = var0[0x1BF1E18F]
      54 [-]: CALL R9 3 1  ; var9(var10, var11)
      55 [-]: FASTCALL1 62 R6 L7; 
      56 [-]: MOVE R10 R6  ; var10 = var6
      57 [-]: GETIMPORT R9 15; var9 = 0x7B998233
      58 [-]: CALL R9 2 2  ; var9 = var9(var10)
L 7:  59 [-]: JUMPIF R9 L9 ; goto L9 if var9
      60 [-]: NAMECALL R10 R6 K16; var11 = var6; var10 = var6[0xDE321E6F]
      61 [-]: CALL R10 2 2 ; var10 = var10(var11)
      62 [-]: NAMECALL R10 R10 K17; var11 = var10; var10 = var10[0xF7D48EE0]
      63 [-]: CALL R10 2 2 ; var10 = var10(var11)
      64 [-]: FASTCALL1 62 R10 L8; 
      65 [-]: GETIMPORT R9 15; var9 = 0x7B998233
      66 [-]: CALL R9 2 2  ; var9 = var9(var10)
L 8:  67 [-]: JUMPIF R9 L9 ; goto L9 if var9
      68 [-]: GETUPVAL R9 5; var9 = upvalues[5]
      69 [-]: MOVE R10 R6  ; var10 = var6
      70 [-]: CALL R9 2 1  ; var9(var10)
      71 [-]: GETUPVAL R9 4; var9 = upvalues[4]
      72 [-]: LOADB R10 0  ; var10 = false
      73 [-]: SETTABLE R10 R9 R5; var10[var9] = var5
L 9:  74 [-]: FORNLOOP R3 L1; nforloop end - iterate + goto L1
L10:  75 [-]: GETUPVAL R2 6; var2 = upvalues[6]
      76 [-]: JUMPIFNOT R2 L11; goto L11 if not var2
      77 [-]: GETUPVAL R3 7; var3 = upvalues[7]
      78 [-]: GETIMPORT R4 20; var4 = 0xB693B6C1
      79 [-]: CALL R4 1 2  ; var4 = var4()
      80 [-]: ADD R2 R3 R4 ; var2 = var3 + var4
      81 [-]: SETUPVAL R2 7; upvalues[2] = var7
      82 [-]: GETUPVAL R2 7; var2 = upvalues[7]
      83 [-]: GETIMPORT R3 22; var3 = 0xE5C1D55D
      84 [-]: JUMPIFNOTLE R3 R2 L11; goto L11 if var3 > var872415813
      85 [-]: NAMECALL R2 R0 K23; var3 = var0; var2 = var0[0xA0E2A834]
      86 [-]: CALL R2 2 1  ; var2(var3)
      87 [-]: LOADB R2 0   ; var2 = false
      88 [-]: SETUPVAL R2 6; upvalues[2] = var6
L11:  89 [-]: GETUPVAL R2 8; var2 = upvalues[8]
      90 [-]: JUMPIFNOT R2 L15; goto L15 if not var2
      91 [-]: GETIMPORT R2 25; var2 = 0xCFC01047
      92 [-]: GETIMPORT R3 10; var3 = 0x89326C93
      93 [-]: NAMECALL R3 R3 K11; var4 = var3; var3 = var3[0x7D108DDB]
      94 [-]: CALL R3 2 0  ; var3, ... = var3(var4)
      95 [-]: CALL R2 0 4  ; var2, var3, var4 = var2(var3, ...)
      96 [-]: FORGPREP_NEXT R2 L14; 
L12:  97 [-]: NAMECALL R7 R6 K26; var8 = var6; var7 = var6[0x420402A9]
      98 [-]: CALL R7 2 2  ; var7 = var7(var8)
      99 [-]: JUMPIFNOT R7 L14; goto L14 if not var7
     100 [-]: NAMECALL R8 R6 K12; var9 = var6; var8 = var6[0xBB610E5B]
     101 [-]: CALL R8 2 2  ; var8 = var8(var9)
     102 [-]: FASTCALL1 62 R8 L13; 
     103 [-]: GETIMPORT R7 15; var7 = 0x7B998233
     104 [-]: CALL R7 2 2  ; var7 = var7(var8)
L13: 105 [-]: JUMPIF R7 L14; goto L14 if var7
     106 [-]: NAMECALL R7 R6 K12; var8 = var6; var7 = var6[0xBB610E5B]
     107 [-]: CALL R7 2 2  ; var7 = var7(var8)
     108 [-]: NAMECALL R7 R7 K27; var8 = var7; var7 = var7[0x0B4BCFB6]
     109 [-]: CALL R7 2 2  ; var7 = var7(var8)
     110 [-]: GETUPVAL R9 9; var9 = upvalues[9]
     111 [-]: NAMECALL R7 R7 K28; var8 = var7; var7 = var7[0x14C7F7DD]
     112 [-]: CALL R7 3 1  ; var7(var8, var9)
L14: 113 [-]: FORGLOOP R2 L12 2; 
L15: 114 [-]: GETUPVAL R2 10; var2 = upvalues[10]
     115 [-]: JUMPIF R2 L17; goto L17 if var2
     116 [-]: GETUPVAL R3 9; var3 = upvalues[9]
     117 [-]: FASTCALL1 62 R3 L16; 
     118 [-]: GETIMPORT R2 15; var2 = 0x7B998233
     119 [-]: CALL R2 2 2  ; var2 = var2(var3)
L16: 120 [-]: JUMPIF R2 L17; goto L17 if var2
     121 [-]: GETUPVAL R2 9; var2 = upvalues[9]
     122 [-]: NAMECALL R2 R2 K29; var3 = var2; var2 = var2[0xF6EBD926]
     123 [-]: CALL R2 2 2  ; var2 = var2(var3)
     124 [-]: SETUPVAL R2 11; upvalues[2] = var11
     125 [-]: LOADB R2 1   ; var2 = true
     126 [-]: SETUPVAL R2 10; upvalues[2] = var10
L17: 127 [-]: GETIMPORT R2 10; var2 = 0x89326C93
     128 [-]: NAMECALL R2 R2 K30; var3 = var2; var2 = var2[0x18D05D30]
     129 [-]: CALL R2 2 2  ; var2 = var2(var3)
     130 [-]: JUMPIFNOT R2 L18; goto L18 if not var2
     131 [-]: GETUPVAL R2 12; var2 = upvalues[12]
     132 [-]: JUMPIFNOT R2 L18; goto L18 if not var2
     133 [-]: GETIMPORT R2 10; var2 = 0x89326C93
     134 [-]: NAMECALL R2 R2 K11; var3 = var2; var2 = var2[0x7D108DDB]
     135 [-]: CALL R2 2 2  ; var2 = var2(var3)
     136 [-]: LENGTH R3 R2 ; var3 = #var2
     137 [-]: LOADN R4 1   ; var4 = 1
     138 [-]: JUMPIFNOTLT R4 R3 L18; goto L18 if var4 >= var852999
     139 [-]: GETUPVAL R4 13; var4 = upvalues[13]
     140 [-]: GETIMPORT R5 32; var5 = 0x67652851
     141 [-]: CALL R5 1 2  ; var5 = var5()
     142 [-]: SUB R3 R4 R5 ; var3 = var4 - var5
     143 [-]: SETUPVAL R3 13; upvalues[3] = var13
     144 [-]: GETUPVAL R3 13; var3 = upvalues[13]
     145 [-]: LOADN R4 0   ; var4 = 0
     146 [-]: JUMPIFNOTLT R3 R4 L18; goto L18 if var3 >= var795
     147 [-]: LOADB R3 0   ; var3 = false
     148 [-]: SETUPVAL R3 12; upvalues[3] = var12
     149 [-]: GETIMPORT R3 10; var3 = 0x89326C93
     150 [-]: NAMECALL R3 R3 K33; var4 = var3; var3 = var3[0x78298275]
     151 [-]: CALL R3 2 2  ; var3 = var3(var4)
     152 [-]: NAMECALL R7 R3 K34; var8 = var3; var7 = var3[0xD1586535]
     153 [-]: CALL R7 2 2  ; var7 = var7(var8)
     154 [-]: GETIMPORT R8 36; var8 = 0xA421AF95
     155 [-]: LOADN R9 0   ; var9 = 0
     156 [-]: LOADK R10 K37; var10 = 0.10000000000000001
     157 [-]: LOADN R11 0  ; var11 = 0
     158 [-]: CALL R8 4 2  ; var8 = var8(var9, var10, var11)
     159 [-]: ADD R6 R7 R8 ; var6 = var7 + var8
     160 [-]: NAMECALL R4 R3 K38; var5 = var3; var4 = var3[0x589EF1C1]
     161 [-]: CALL R4 3 1  ; var4(var5, var6)
L18: 162 [-]: NAMECALL R2 R0 K39; var3 = var0; var2 = var0[0x57BE7458]
     163 [-]: CALL R2 2 2  ; var2 = var2(var3)
     164 [-]: GETIMPORT R3 25; var3 = 0xCFC01047
     165 [-]: GETIMPORT R4 10; var4 = 0x89326C93
     166 [-]: NAMECALL R4 R4 K11; var5 = var4; var4 = var4[0x7D108DDB]
     167 [-]: CALL R4 2 0  ; var4, ... = var4(var5)
     168 [-]: CALL R3 0 4  ; var3, var4, var5 = var3(var4, ...)
     169 [-]: FORGPREP_NEXT R3 L22; 
L19: 170 [-]: NAMECALL R8 R7 K12; var9 = var7; var8 = var7[0xBB610E5B]
     171 [-]: CALL R8 2 2  ; var8 = var8(var9)
     172 [-]: FASTCALL1 62 R8 L20; 
     173 [-]: MOVE R10 R8  ; var10 = var8
     174 [-]: GETIMPORT R9 15; var9 = 0x7B998233
     175 [-]: CALL R9 2 2  ; var9 = var9(var10)
L20: 176 [-]: JUMPIF R9 L22; goto L22 if var9
     177 [-]: NAMECALL R9 R8 K29; var10 = var8; var9 = var8[0xF6EBD926]
     178 [-]: CALL R9 2 2  ; var9 = var9(var10)
     179 [-]: GETTABLEKS R12 R9 K40; var12 = var9["x"]
     180 [-]: NAMECALL R10 R2 K41; var11 = var2; var10 = var2[0xFE20096B]
     181 [-]: CALL R10 3 2 ; var10 = var10(var11, var12)
     182 [-]: JUMPIF R10 L22; goto L22 if var10
     183 [-]: GETIMPORT R10 43; var10 = 0x7FA0B32A
     184 [-]: GETTABLEKS R12 R9 K40; var12 = var9["x"]
     185 [-]: GETTABLEKS R13 R2 K44; var13 = var2["minValue"]
     186 [-]: SUB R11 R12 R13; var11 = var12 - var13
     187 [-]: CALL R10 2 2 ; var10 = var10(var11)
     188 [-]: GETIMPORT R11 43; var11 = 0x7FA0B32A
     189 [-]: GETTABLEKS R13 R9 K40; var13 = var9["x"]
     190 [-]: GETTABLEKS R14 R2 K45; var14 = var2["maxValue"]
     191 [-]: SUB R12 R13 R14; var12 = var13 - var14
     192 [-]: CALL R11 2 2 ; var11 = var11(var12)
     193 [-]: JUMPIFNOTLT R10 R11 L21; goto L21 if var10 >= var2362446
     194 [-]: GETIMPORT R12 36; var12 = 0xA421AF95
     195 [-]: GETTABLEKS R13 R2 K44; var13 = var2["minValue"]
     196 [-]: GETTABLEKS R14 R9 K46; var14 = var9["y"]
     197 [-]: GETTABLEKS R15 R9 K47; var15 = var9["z"]
     198 [-]: CALL R12 4 0 ; var12, ... = var12(var13, var14, var15)
     199 [-]: NAMECALL R10 R8 K38; var11 = var8; var10 = var8[0x589EF1C1]
     200 [-]: CALL R10 0 1 ; var10(var11, ...)
     201 [-]: JUMP L22     ; goto L22
L21: 202 [-]: GETIMPORT R12 36; var12 = 0xA421AF95
     203 [-]: GETTABLEKS R13 R2 K45; var13 = var2["maxValue"]
     204 [-]: GETTABLEKS R14 R9 K46; var14 = var9["y"]
     205 [-]: GETTABLEKS R15 R9 K47; var15 = var9["z"]
     206 [-]: CALL R12 4 0 ; var12, ... = var12(var13, var14, var15)
     207 [-]: NAMECALL R10 R8 K38; var11 = var8; var10 = var8[0x589EF1C1]
     208 [-]: CALL R10 0 1 ; var10(var11, ...)
L22: 209 [-]: FORGLOOP R3 L19 2; 
     210 [-]: GETIMPORT R4 50; var4 = _T["LastChosenEntry"]
     211 [-]: FASTCALL1 62 R4 L23; 
     212 [-]: GETIMPORT R3 15; var3 = 0x7B998233
     213 [-]: CALL R3 2 2  ; var3 = var3(var4)
L23: 214 [-]: JUMPIFNOT R3 L31; goto L31 if not var3
     215 [-]: NAMECALL R3 R0 K51; var4 = var0; var3 = var0[0xC9BDFB7C]
     216 [-]: CALL R3 2 2  ; var3 = var3(var4)
     217 [-]: GETIMPORT R4 25; var4 = 0xCFC01047
     218 [-]: MOVE R5 R3   ; var5 = var3
     219 [-]: CALL R4 2 4  ; var4, var5, var6 = var4(var5)
     220 [-]: FORGPREP_NEXT R4 L30; 
L24: 221 [-]: FASTCALL1 62 R8 L25; 
     222 [-]: MOVE R10 R8  ; var10 = var8
     223 [-]: GETIMPORT R9 15; var9 = 0x7B998233
     224 [-]: CALL R9 2 2  ; var9 = var9(var10)
L25: 225 [-]: JUMPIF R9 L30; goto L30 if var9
     226 [-]: GETIMPORT R9 53; var9 = 0xB009BBC6
     227 [-]: GETTABLEKS R10 R8 K54; var10 = var8["normalVersion"]
     228 [-]: CALL R9 2 2  ; var9 = var9(var10)
     229 [-]: LOADNIL R10  ; var10 = nil
     230 [-]: FASTCALL1 62 R9 L26; 
     231 [-]: MOVE R12 R9  ; var12 = var9
     232 [-]: GETIMPORT R11 15; var11 = 0x7B998233
     233 [-]: CALL R11 2 2 ; var11 = var11(var12)
L26: 234 [-]: JUMPIF R11 L27; goto L27 if var11
     235 [-]: NAMECALL R11 R9 K55; var12 = var9; var11 = var9[0x056DCF06]
     236 [-]: CALL R11 2 2 ; var11 = var11(var12)
     237 [-]: MOVE R10 R11 ; var10 = var11
L27: 238 [-]: GETIMPORT R11 53; var11 = 0xB009BBC6
     239 [-]: GETTABLEKS R12 R8 K56; var12 = var8["primeVersion"]
     240 [-]: CALL R11 2 2 ; var11 = var11(var12)
     241 [-]: LOADNIL R12  ; var12 = nil
     242 [-]: FASTCALL1 62 R11 L28; 
     243 [-]: MOVE R14 R11 ; var14 = var11
     244 [-]: GETIMPORT R13 15; var13 = 0x7B998233
     245 [-]: CALL R13 2 2 ; var13 = var13(var14)
L28: 246 [-]: JUMPIF R13 L29; goto L29 if var13
     247 [-]: NAMECALL R13 R11 K55; var14 = var11; var13 = var11[0x056DCF06]
     248 [-]: CALL R13 2 2 ; var13 = var13(var14)
     249 [-]: MOVE R12 R13 ; var12 = var13
L29: 250 [-]: DUPTABLE R13 61; 
     251 [-]: GETTABLEKS R14 R8 K54; var14 = var8["normalVersion"]
     252 [-]: SETTABLEKS R14 R13 K57; var14["Type"] = var13
     253 [-]: SETTABLEKS R10 R13 K58; var10["Icon"] = var13
     254 [-]: GETTABLEKS R14 R8 K56; var14 = var8["primeVersion"]
     255 [-]: SETTABLEKS R14 R13 K59; var14["PrimeType"] = var13
     256 [-]: SETTABLEKS R12 R13 K60; var12["PrimeIcon"] = var13
     257 [-]: GETIMPORT R14 62; var14 = _T
     258 [-]: DUPTABLE R15 65; 
     259 [-]: SETTABLEKS R13 R15 K63; var13["entry"] = var15
     260 [-]: LOADB R16 0  ; var16 = false
     261 [-]: SETTABLEKS R16 R15 K64; var16["prime"] = var15
     262 [-]: SETTABLEKS R15 R14 K49; var15["LastChosenEntry"] = var14
     263 [-]: JUMP L31     ; goto L31
L30: 264 [-]: FORGLOOP R4 L24 2; 
L31: 265 [-]: GETUPVAL R3 14; var3 = upvalues[14]
     266 [-]: MOVE R4 R1   ; var4 = var1
     267 [-]: CALL R3 2 1  ; var3(var4)
     268 [-]: GETUPVAL R3 15; var3 = upvalues[15]
     269 [-]: MOVE R4 R1   ; var4 = var1
     270 [-]: CALL R3 2 1  ; var3(var4)
     271 [-]: GETUPVAL R3 16; var3 = upvalues[16]
     272 [-]: LOADN R4 0   ; var4 = 0
     273 [-]: JUMPIFNOTLT R4 R3 L34; goto L34 if var4 >= var1049607
     274 [-]: GETUPVAL R4 16; var4 = upvalues[16]
     275 [-]: FASTCALL1 7 R4 L32; 
     276 [-]: GETIMPORT R3 68; var3 = 0x5BCED4C4[0x99675E23]
     277 [-]: CALL R3 2 2  ; var3 = var3(var4)
L32: 278 [-]: GETUPVAL R5 16; var5 = upvalues[16]
     279 [-]: SUB R4 R5 R1 ; var4 = var5 - var1
     280 [-]: SETUPVAL R4 16; upvalues[4] = var16
     281 [-]: GETUPVAL R5 16; var5 = upvalues[16]
     282 [-]: FASTCALL1 7 R5 L33; 
     283 [-]: GETIMPORT R4 68; var4 = 0x5BCED4C4[0x99675E23]
     284 [-]: CALL R4 2 2  ; var4 = var4(var5)
L33: 285 [-]: JUMPIFEQ R4 R3 L34; goto L34 if var4 == var1351
     286 [-]: LOADN R5 0   ; var5 = 0
     287 [-]: JUMPIFNOTLT R5 R4 L34; goto L34 if var5 >= var197959
     288 [-]: LOADN R5 3   ; var5 = 3
     289 [-]: JUMPIFNOTLE R4 R5 L34; goto L34 if var4 > var4064590
     290 [-]: GETIMPORT R5 62; var5 = _T
     291 [-]: SETTABLEKS R4 R5 K69; var4["RoundTimeLeft"] = var5
L34: 292 [-]: GETUPVAL R3 17; var3 = upvalues[17]
     293 [-]: LOADN R4 0   ; var4 = 0
     294 [-]: JUMPIFNOTLT R4 R3 L36; goto L36 if var4 >= var1115143
     295 [-]: GETUPVAL R4 17; var4 = upvalues[17]
     296 [-]: SUB R3 R4 R1 ; var3 = var4 - var1
     297 [-]: SETUPVAL R3 17; upvalues[3] = var17
     298 [-]: GETUPVAL R3 17; var3 = upvalues[17]
     299 [-]: LOADN R4 0   ; var4 = 0
     300 [-]: JUMPIFNOTLT R3 R4 L36; goto L36 if var3 >= var590855
     301 [-]: GETUPVAL R4 9; var4 = upvalues[9]
     302 [-]: FASTCALL1 62 R4 L35; 
     303 [-]: GETIMPORT R3 15; var3 = 0x7B998233
     304 [-]: CALL R3 2 2  ; var3 = var3(var4)
L35: 305 [-]: JUMPIF R3 L36; goto L36 if var3
     306 [-]: GETUPVAL R3 9; var3 = upvalues[9]
     307 [-]: LOADN R5 0   ; var5 = 0
     308 [-]: LOADN R6 0   ; var6 = 0
     309 [-]: NAMECALL R3 R3 K70; var4 = var3; var3 = var3[0xF3CEFA26]
     310 [-]: CALL R3 4 1  ; var3(var4, var5, var6)
L36: 311 [-]: GETIMPORT R3 72; var3 = 0xBE190284
     312 [-]: NAMECALL R3 R3 K13; var4 = var3; var3 = var3[0x82374F71]
     313 [-]: CALL R3 2 2  ; var3 = var3(var4)
     314 [-]: LOADN R4 2   ; var4 = 2
     315 [-]: JUMPIFNOTEQ R3 R4 L38; goto L38 if var3 ~= var4064078
     316 [-]: GETIMPORT R3 62; var3 = _T
     317 [-]: GETIMPORT R5 72; var5 = 0xBE190284
     318 [-]: NAMECALL R5 R5 K73; var6 = var5; var5 = var5[0xDBB6F358]
     319 [-]: CALL R5 2 2  ; var5 = var5(var6)
     320 [-]: FASTCALL1 7 R5 L37; 
     321 [-]: GETIMPORT R4 68; var4 = 0x5BCED4C4[0x99675E23]
     322 [-]: CALL R4 2 2  ; var4 = var4(var5)
L37: 323 [-]: SETTABLEKS R4 R3 K69; var4["RoundTimeLeft"] = var3
L38: 324 [-]: GETUPVAL R3 18; var3 = upvalues[18]
     325 [-]: CALL R3 1 1  ; var3()
     326 [-]: GETUPVAL R3 19; var3 = upvalues[19]
     327 [-]: CALL R3 1 1  ; var3()
     328 [-]: RETURN R0 0  ; 


; Name:            
; Defined at line: 608
; #Upvalues:       0
; #Parameters:     2
; Is_vararg:       0
; Max Stack Size:  4

       0 [-]: GETIMPORT R2 1; var2 = 0x3747709B
       1 [-]: GETIMPORT R2 3; var2 = 0x48D7EE0B
       2 [-]: GETIMPORT R2 5; var2 = 0x22B09C78
       3 [-]: GETIMPORT R2 7; var2 = 0xDC929F57
       4 [-]: GETIMPORT R2 9; var2 = 0x1A199142
       5 [-]: GETIMPORT R2 11; var2 = 0xF1929D5B
       6 [-]: GETIMPORT R2 13; var2 = 0xCD1D81A9
       7 [-]: GETIMPORT R2 15; var2 = 0x5C44C965
       8 [-]: GETGLOBAL R3 K16; var3 = 0x8353E0FC
       9 [-]: GETGLOBAL R3 K17; var3 = 0xC367B736
      10 [-]: GETIMPORT R3 19; var3 = 0x7591E528
      11 [-]: GETIMPORT R3 21; var3 = 0x2FAE7303
      12 [-]: GETIMPORT R3 23; var3 = 0x3D39B196
      13 [-]: GETIMPORT R3 25; var3 = 0xF92B4175
      14 [-]: GETIMPORT R3 27; var3 = 0xE239815F
      15 [-]: GETIMPORT R3 29; var3 = 0x4FB28C09
      16 [-]: GETIMPORT R3 31; var3 = 0x8FB60DB1
      17 [-]: GETIMPORT R3 33; var3 = 0x73BB0A3B
      18 [-]: GETIMPORT R3 35; var3 = 0x9E8A0171
      19 [-]: GETIMPORT R3 37; var3 = 0xF854D632
      20 [-]: GETIMPORT R3 39; var3 = 0x97B85C09
      21 [-]: GETIMPORT R3 41; var3 = 0xE5C1D55D
      22 [-]: GETIMPORT R3 43; var3 = 0x9942EF35
      23 [-]: GETIMPORT R3 45; var3 = 0x2EEAD8CF
      24 [-]: GETIMPORT R3 47; var3 = 0x1E5117AA
      25 [-]: GETIMPORT R3 49; var3 = 0x43930F18
      26 [-]: GETIMPORT R3 51; var3 = 0xAA51A169
      27 [-]: RETURN R0 0  ; 


; Name:            
; Defined at line: 640
; #Upvalues:       0
; #Parameters:     2
; Is_vararg:       0
; Max Stack Size:  6

       0 [-]: GETIMPORT R2 1; var2 = 0x89326C93
       1 [-]: NAMECALL R2 R2 K2; var3 = var2; var2 = var2[0x18D05D30]
       2 [-]: CALL R2 2 2  ; var2 = var2(var3)
       3 [-]: JUMPIFNOT R2 L1; goto L1 if not var2
       4 [-]: GETIMPORT R2 1; var2 = 0x89326C93
       5 [-]: NAMECALL R2 R2 K3; var3 = var2; var2 = var2[0xFB64E76C]
       6 [-]: CALL R2 2 2  ; var2 = var2(var3)
       7 [-]: JUMPIFNOT R2 L1; goto L1 if not var2
       8 [-]: JUMPIFNOT R1 L1; goto L1 if not var1
       9 [-]: JUMPIFEQ R2 R1 L1; goto L1 if var2 == var394062
      10 [-]: GETIMPORT R3 6; var3 = _T["ShowRoundInfo"]
      11 [-]: JUMPIFNOT R3 L0; goto L0 if not var3
      12 [-]: GETIMPORT R3 6; var3 = _T["ShowRoundInfo"]
      13 [-]: LOADB R4 0   ; var4 = false
      14 [-]: CALL R3 2 1  ; var3(var4)
L 0:  15 [-]: GETIMPORT R3 8; var3 = _T["SetFightingGameCameraOffset"]
      16 [-]: LOADN R4 0   ; var4 = 0
      17 [-]: LOADK R5 K9  ; var5 = 3.5
      18 [-]: CALL R3 3 1  ; var3(var4, var5)
L 1:  19 [-]: RETURN R0 0  ; 


; Name:            
; Defined at line: 653
; #Upvalues:       3
; #Parameters:     2
; Is_vararg:       0
; Max Stack Size:  10

       0 [-]: GETIMPORT R2 1; var2 = 0x3D106989
       1 [-]: LOADK R4 K2  ; var4 = "Avatar with player: "
       2 [-]: GETIMPORT R7 4; var7 = 0x64FB1586
       3 [-]: NAMECALL R8 R1 K5; var9 = var1; var8 = var1[0x5CA33548]
       4 [-]: CALL R8 2 0  ; var8, ... = var8(var9)
       5 [-]: CALL R7 0 2  ; var7 = var7(var8, ...)
       6 [-]: MOVE R5 R7   ; var5 = var7
       7 [-]: LOADK R6 K6  ; var6 = " CHANGED"
       8 [-]: CONCAT R3 R4 R6; var3 = var4 .. var6
       9 [-]: CALL R2 2 1  ; var2(var3)
      10 [-]: NAMECALL R2 R1 K7; var3 = var1; var2 = var1[0xBB610E5B]
      11 [-]: CALL R2 2 2  ; var2 = var2(var3)
      12 [-]: FASTCALL1 62 R2 L0; 
      13 [-]: MOVE R4 R2   ; var4 = var2
      14 [-]: GETIMPORT R3 9; var3 = 0x7B998233
      15 [-]: CALL R3 2 2  ; var3 = var3(var4)
L 0:  16 [-]: JUMPIFNOT R3 L1; goto L1 if not var3
      17 [-]: RETURN R0 0  ; 
L 1:  18 [-]: GETUPVAL R3 0; var3 = upvalues[0]
      19 [-]: MOVE R4 R2   ; var4 = var2
      20 [-]: MOVE R5 R0   ; var5 = var0
      21 [-]: CALL R3 3 1  ; var3(var4, var5)
      22 [-]: NAMECALL R3 R1 K10; var4 = var1; var3 = var1[0x420402A9]
      23 [-]: CALL R3 2 2  ; var3 = var3(var4)
      24 [-]: JUMPIF R3 L4 ; goto L4 if var3
      25 [-]: GETIMPORT R3 12; var3 = 0x89326C93
      26 [-]: NAMECALL R3 R3 K13; var4 = var3; var3 = var3[0x18D05D30]
      27 [-]: CALL R3 2 2  ; var3 = var3(var4)
      28 [-]: JUMPIFNOT R3 L3; goto L3 if not var3
      29 [-]: GETIMPORT R3 12; var3 = 0x89326C93
      30 [-]: NAMECALL R3 R3 K14; var4 = var3; var3 = var3[0x78298275]
      31 [-]: CALL R3 2 2  ; var3 = var3(var4)
      32 [-]: FASTCALL1 62 R3 L2; 
      33 [-]: MOVE R5 R3   ; var5 = var3
      34 [-]: GETIMPORT R4 9; var4 = 0x7B998233
      35 [-]: CALL R4 2 2  ; var4 = var4(var5)
L 2:  36 [-]: JUMPIF R4 L3 ; goto L3 if var4
      37 [-]: JUMPIFEQ R3 R2 L3; goto L3 if var3 == var66587
      38 [-]: LOADB R4 1   ; var4 = true
      39 [-]: SETUPVAL R4 1; upvalues[4] = var1
L 3:  40 [-]: RETURN R0 0  ; 
L 4:  41 [-]: GETUPVAL R3 2; var3 = upvalues[2]
      42 [-]: CALL R3 1 1  ; var3()
      43 [-]: RETURN R0 0  ; 


; Name:            
; Defined at line: 678
; #Upvalues:       8
; #Parameters:     2
; Is_vararg:       0
; Max Stack Size:  5

       0 [-]: GETIMPORT R2 1; var2 = 0x89326C93
       1 [-]: NAMECALL R2 R2 K2; var3 = var2; var2 = var2[0x18D05D30]
       2 [-]: CALL R2 2 2  ; var2 = var2(var3)
       3 [-]: JUMPIFNOT R2 L0; goto L0 if not var2
       4 [-]: GETUPVAL R2 0; var2 = upvalues[0]
       5 [-]: CALL R2 1 1  ; var2()
L 0:   6 [-]: GETIMPORT R4 4; var4 = 0x97B85C09
       7 [-]: NAMECALL R2 R0 K5; var3 = var0; var2 = var0[0xD761A7A1]
       8 [-]: CALL R2 3 1  ; var2(var3, var4)
       9 [-]: LOADB R2 1   ; var2 = true
      10 [-]: SETUPVAL R2 1; upvalues[2] = var1
      11 [-]: LOADN R2 0   ; var2 = 0
      12 [-]: SETUPVAL R2 2; upvalues[2] = var2
      13 [-]: FASTCALL1 62 R1 L1; 
      14 [-]: MOVE R3 R1   ; var3 = var1
      15 [-]: GETIMPORT R2 7; var2 = 0x7B998233
      16 [-]: CALL R2 2 2  ; var2 = var2(var3)
L 1:  17 [-]: JUMPIF R2 L2 ; goto L2 if var2
      18 [-]: GETUPVAL R2 3; var2 = upvalues[3]
      19 [-]: LOADB R3 0   ; var3 = false
      20 [-]: MOVE R4 R1   ; var4 = var1
      21 [-]: CALL R2 3 1  ; var2(var3, var4)
L 2:  22 [-]: GETUPVAL R2 4; var2 = upvalues[4]
      23 [-]: CALL R2 1 1  ; var2()
      24 [-]: LOADN R2 1   ; var2 = 1
      25 [-]: SETUPVAL R2 5; upvalues[2] = var5
      26 [-]: LOADN R2 0   ; var2 = 0
      27 [-]: SETUPVAL R2 6; upvalues[2] = var6
      28 [-]: LOADN R2 0   ; var2 = 0
      29 [-]: SETUPVAL R2 7; upvalues[2] = var7
      30 [-]: RETURN R0 0  ; 


; Name:            
; Defined at line: 694
; #Upvalues:       3
; #Parameters:     1
; Is_vararg:       0
; Max Stack Size:  6

       0 [-]: GETIMPORT R1 1; var1 = 0x89326C93
       1 [-]: NAMECALL R1 R1 K2; var2 = var1; var1 = var1[0xFB64E76C]
       2 [-]: CALL R1 2 2  ; var1 = var1(var2)
       3 [-]: FASTCALL1 62 R1 L0; 
       4 [-]: MOVE R3 R1   ; var3 = var1
       5 [-]: GETIMPORT R2 4; var2 = 0x7B998233
       6 [-]: CALL R2 2 2  ; var2 = var2(var3)
L 0:   7 [-]: JUMPIF R2 L1 ; goto L1 if var2
       8 [-]: NAMECALL R2 R0 K5; var3 = var0; var2 = var0[0xDE321E6F]
       9 [-]: CALL R2 2 2  ; var2 = var2(var3)
      10 [-]: MOVE R4 R1   ; var4 = var1
      11 [-]: LOADB R5 1   ; var5 = true
      12 [-]: NAMECALL R2 R2 K6; var3 = var2; var2 = var2[0x88B323D0]
      13 [-]: CALL R2 4 1  ; var2(var3, var4, var5)
      14 [-]: GETUPVAL R2 0; var2 = upvalues[0]
      15 [-]: JUMPIFNOT R2 L1; goto L1 if not var2
      16 [-]: GETIMPORT R2 8; var2 = 0xBE190284
      17 [-]: NAMECALL R4 R0 K9; var5 = var0; var4 = var0[0x5E651723]
      18 [-]: CALL R4 2 0  ; var4, ... = var4(var5)
      19 [-]: NAMECALL R2 R2 K10; var3 = var2; var2 = var2[0x1BF1E18F]
      20 [-]: CALL R2 0 1  ; var2(var3, ...)
L 1:  21 [-]: GETUPVAL R2 1; var2 = upvalues[1]
      22 [-]: MOVE R3 R0   ; var3 = var0
      23 [-]: GETIMPORT R4 8; var4 = 0xBE190284
      24 [-]: CALL R2 3 1  ; var2(var3, var4)
      25 [-]: GETUPVAL R2 2; var2 = upvalues[2]
      26 [-]: CALL R2 1 1  ; var2()
      27 [-]: RETURN R0 0  ; 


; Name:            
; Defined at line: 707
; #Upvalues:       2
; #Parameters:     3
; Is_vararg:       0
; Max Stack Size:  13

       0 [-]: GETUPVAL R4 0; var4 = upvalues[0]
       1 [-]: FASTCALL1 62 R4 L0; 
       2 [-]: GETIMPORT R3 1; var3 = 0x7B998233
       3 [-]: CALL R3 2 2  ; var3 = var3(var4)
L 0:   4 [-]: JUMPIF R3 L4 ; goto L4 if var3
       5 [-]: FASTCALL1 62 R1 L1; 
       6 [-]: MOVE R4 R1   ; var4 = var1
       7 [-]: GETIMPORT R3 1; var3 = 0x7B998233
       8 [-]: CALL R3 2 2  ; var3 = var3(var4)
L 1:   9 [-]: JUMPIF R3 L4 ; goto L4 if var3
      10 [-]: NAMECALL R4 R1 K2; var5 = var1; var4 = var1[0xBB610E5B]
      11 [-]: CALL R4 2 2  ; var4 = var4(var5)
      12 [-]: FASTCALL1 62 R4 L2; 
      13 [-]: GETIMPORT R3 1; var3 = 0x7B998233
      14 [-]: CALL R3 2 2  ; var3 = var3(var4)
L 2:  15 [-]: JUMPIF R3 L4 ; goto L4 if var3
      16 [-]: NAMECALL R3 R1 K2; var4 = var1; var3 = var1[0xBB610E5B]
      17 [-]: CALL R3 2 2  ; var3 = var3(var4)
      18 [-]: LOADN R5 26  ; var5 = 26
      19 [-]: NAMECALL R3 R3 K3; var4 = var3; var3 = var3[0x0E46E45B]
      20 [-]: CALL R3 3 2  ; var3 = var3(var4, var5)
      21 [-]: JUMPIFNOT R3 L3; goto L3 if not var3
      22 [-]: GETUPVAL R3 0; var3 = upvalues[0]
      23 [-]: GETIMPORT R5 5; var5 = 0x8FB60DB1
      24 [-]: GETIMPORT R6 7; var6 = 0x73BB0A3B
      25 [-]: NAMECALL R3 R3 K8; var4 = var3; var3 = var3[0xF3CEFA26]
      26 [-]: CALL R3 4 1  ; var3(var4, var5, var6)
      27 [-]: GETIMPORT R3 10; var3 = 0xF92B4175
      28 [-]: SETUPVAL R3 1; upvalues[3] = var1
      29 [-]: JUMP L4      ; goto L4
L 3:  30 [-]: GETUPVAL R3 0; var3 = upvalues[0]
      31 [-]: GETIMPORT R5 12; var5 = 0xE239815F
      32 [-]: GETIMPORT R6 14; var6 = 0x4FB28C09
      33 [-]: NAMECALL R3 R3 K8; var4 = var3; var3 = var3[0xF3CEFA26]
      34 [-]: CALL R3 4 1  ; var3(var4, var5, var6)
      35 [-]: GETIMPORT R3 16; var3 = 0x3D39B196
      36 [-]: SETUPVAL R3 1; upvalues[3] = var1
L 4:  37 [-]: NAMECALL R5 R2 K17; var6 = var2; var5 = var2[0x14A55974]
      38 [-]: CALL R5 2 2  ; var5 = var5(var6)
      39 [-]: FASTCALL1 62 R5 L5; 
      40 [-]: GETIMPORT R4 1; var4 = 0x7B998233
      41 [-]: CALL R4 2 2  ; var4 = var4(var5)
L 5:  42 [-]: NOT R3 R4    ; var3 = not var4
      43 [-]: JUMPIFNOT R3 L6; goto L6 if not var3
      44 [-]: NAMECALL R3 R2 K17; var4 = var2; var3 = var2[0x14A55974]
      45 [-]: CALL R3 2 2  ; var3 = var3(var4)
      46 [-]: GETIMPORT R5 19; var5 = gPowerSuitType
      47 [-]: NAMECALL R3 R3 K20; var4 = var3; var3 = var3[0xF2DEAF69]
      48 [-]: CALL R3 3 2  ; var3 = var3(var4, var5)
L 6:  49 [-]: NAMECALL R5 R2 K21; var6 = var2; var5 = var2[0xE8B105B3]
      50 [-]: CALL R5 2 2  ; var5 = var5(var6)
      51 [-]: LOADN R6 7   ; var6 = 7
      52 [-]: JUMPIFEQ R5 R6 L7; goto L7 if var5 == var16778267
      53 [-]: LOADB R4 0 +1; var4 = false
L 7:  54 [-]: LOADB R4 1   ; var4 = true
L 8:  55 [-]: GETIMPORT R6 23; var6 = 0x89326C93
      56 [-]: FASTCALL1 62 R6 L9; 
      57 [-]: GETIMPORT R5 1; var5 = 0x7B998233
      58 [-]: CALL R5 2 2  ; var5 = var5(var6)
L 9:  59 [-]: JUMPIF R5 L17; goto L17 if var5
      60 [-]: GETIMPORT R5 23; var5 = 0x89326C93
      61 [-]: NAMECALL R5 R5 K24; var6 = var5; var5 = var5[0x18D05D30]
      62 [-]: CALL R5 2 2  ; var5 = var5(var6)
      63 [-]: JUMPIFNOT R5 L17; goto L17 if not var5
      64 [-]: FASTCALL1 62 R0 L10; 
      65 [-]: MOVE R6 R0   ; var6 = var0
      66 [-]: GETIMPORT R5 1; var5 = 0x7B998233
      67 [-]: CALL R5 2 2  ; var5 = var5(var6)
L10:  68 [-]: JUMPIF R5 L17; goto L17 if var5
      69 [-]: FASTCALL1 62 R1 L11; 
      70 [-]: MOVE R6 R1   ; var6 = var1
      71 [-]: GETIMPORT R5 1; var5 = 0x7B998233
      72 [-]: CALL R5 2 2  ; var5 = var5(var6)
L11:  73 [-]: JUMPIF R5 L17; goto L17 if var5
      74 [-]: NAMECALL R5 R0 K2; var6 = var0; var5 = var0[0xBB610E5B]
      75 [-]: CALL R5 2 2  ; var5 = var5(var6)
      76 [-]: FASTCALL1 62 R5 L12; 
      77 [-]: MOVE R7 R5   ; var7 = var5
      78 [-]: GETIMPORT R6 1; var6 = 0x7B998233
      79 [-]: CALL R6 2 2  ; var6 = var6(var7)
L12:  80 [-]: JUMPIF R6 L14; goto L14 if var6
      81 [-]: NAMECALL R7 R5 K25; var8 = var5; var7 = var5[0xDE321E6F]
      82 [-]: CALL R7 2 2  ; var7 = var7(var8)
      83 [-]: NAMECALL R7 R7 K26; var8 = var7; var7 = var7[0xF7D48EE0]
      84 [-]: CALL R7 2 2  ; var7 = var7(var8)
      85 [-]: FASTCALL1 62 R7 L13; 
      86 [-]: GETIMPORT R6 1; var6 = 0x7B998233
      87 [-]: CALL R6 2 2  ; var6 = var6(var7)
L13:  88 [-]: JUMPIF R6 L14; goto L14 if var6
      89 [-]: JUMPIF R4 L14; goto L14 if var4
      90 [-]: JUMPIF R3 L14; goto L14 if var3
      91 [-]: NAMECALL R6 R5 K25; var7 = var5; var6 = var5[0xDE321E6F]
      92 [-]: CALL R6 2 2  ; var6 = var6(var7)
      93 [-]: NAMECALL R6 R6 K26; var7 = var6; var6 = var6[0xF7D48EE0]
      94 [-]: CALL R6 2 2  ; var6 = var6(var7)
      95 [-]: NAMECALL R10 R6 K27; var11 = var6; var10 = var6[0x58A4D5AC]
      96 [-]: CALL R10 2 2 ; var10 = var10(var11)
      97 [-]: GETIMPORT R11 29; var11 = 0x9E8A0171
      98 [-]: ADD R9 R10 R11; var9 = var10 + var11
      99 [-]: NAMECALL R7 R6 K30; var8 = var6; var7 = var6[0x6E19D3FE]
     100 [-]: CALL R7 3 1  ; var7(var8, var9)
L14: 101 [-]: NAMECALL R6 R1 K2; var7 = var1; var6 = var1[0xBB610E5B]
     102 [-]: CALL R6 2 2  ; var6 = var6(var7)
     103 [-]: FASTCALL1 62 R6 L15; 
     104 [-]: MOVE R8 R6   ; var8 = var6
     105 [-]: GETIMPORT R7 1; var7 = 0x7B998233
     106 [-]: CALL R7 2 2  ; var7 = var7(var8)
L15: 107 [-]: JUMPIF R7 L17; goto L17 if var7
     108 [-]: NAMECALL R8 R6 K25; var9 = var6; var8 = var6[0xDE321E6F]
     109 [-]: CALL R8 2 2  ; var8 = var8(var9)
     110 [-]: NAMECALL R8 R8 K26; var9 = var8; var8 = var8[0xF7D48EE0]
     111 [-]: CALL R8 2 2  ; var8 = var8(var9)
     112 [-]: FASTCALL1 62 R8 L16; 
     113 [-]: GETIMPORT R7 1; var7 = 0x7B998233
     114 [-]: CALL R7 2 2  ; var7 = var7(var8)
L16: 115 [-]: JUMPIF R7 L17; goto L17 if var7
     116 [-]: NAMECALL R7 R6 K25; var8 = var6; var7 = var6[0xDE321E6F]
     117 [-]: CALL R7 2 2  ; var7 = var7(var8)
     118 [-]: NAMECALL R7 R7 K26; var8 = var7; var7 = var7[0xF7D48EE0]
     119 [-]: CALL R7 2 2  ; var7 = var7(var8)
     120 [-]: NAMECALL R11 R7 K27; var12 = var7; var11 = var7[0x58A4D5AC]
     121 [-]: CALL R11 2 2 ; var11 = var11(var12)
     122 [-]: GETIMPORT R12 32; var12 = 0xF854D632
     123 [-]: ADD R10 R11 R12; var10 = var11 + var12
     124 [-]: NAMECALL R8 R7 K30; var9 = var7; var8 = var7[0x6E19D3FE]
     125 [-]: CALL R8 3 1  ; var8(var9, var10)
L17: 126 [-]: RETURN R0 0  ; 



