; Name:            
; Defined at line: 1
; #Upvalues:       0
; #Parameters:     0
; Is_vararg:       1
; Max Stack Size:  90

            1 [-]: LOADN R0 5   
       2 [-]: LOADN R1 15  
       3 [-]: LOADN R2 16  
       4 [-]: GETIMPORT R3 1 [nil]
       5 [-]: LOADK R4 K2 ["EE.Interface.Utilities"]
       6 [-]: CALL R3 1 1  
       7 [-]: GETIMPORT R4 1 [nil]
       8 [-]: LOADK R5 K3 ["Lotus.Interface.LotusUtilities"]
       9 [-]: CALL R4 1 1  
      10 [-]: GETIMPORT R5 1 [nil]
      11 [-]: LOADK R6 K4 ["Lotus.Scripts.Libs.CommonGamemodeFunctions"]
      12 [-]: CALL R5 1 1  
      13 [-]: GETIMPORT R6 6 [nil]
      14 [-]: LOADK R7 K7 ["PixelateBias"]
      15 [-]: CALL R6 1 1  
      16 [-]: LOADB R7 0   
      17 [-]: LOADB R8 1   
      18 [-]: LOADB R9 0   
      19 [-]: LOADB R10 0  
      20 [-]: LOADNIL R11  
      21 [-]: LOADN R12 1  
      22 [-]: LOADN R13 0  
      23 [-]: LOADNIL R14  
      24 [-]: LOADB R15 1  
      25 [-]: LOADB R16 1  
      26 [-]: LOADN R17 0  
      27 [-]: LOADB R18 0  
      28 [-]: GETIMPORT R19 9 [nil]
      29 [-]: CALL R19 0 1 
      30 [-]: NEWTABLE R20 0 0
      31 [-]: LOADNIL R21  
      32 [-]: LOADB R22 0  
      33 [-]: LOADNIL R23  
      34 [-]: LOADNIL R24  
      35 [-]: LOADNIL R25  
      36 [-]: GETIMPORT R26 11 [nil]
      37 [-]: CALL R26 0 1 
      38 [-]: LOADNIL R27  
      39 [-]: LOADNIL R28  
      40 [-]: LOADB R29 0  
      41 [-]: LOADNIL R30  
      42 [-]: GETIMPORT R31 6 [nil]
      43 [-]: LOADK R32 K12 ["Deck12Code"]
      44 [-]: CALL R31 1 1 
      45 [-]: LOADB R32 0  
      46 [-]: LOADNIL R33  
      47 [-]: LOADN R34 0  
      48 [-]: LOADN R35 0  
      49 [-]: NEWTABLE R36 0 0
      50 [-]: NEWTABLE R37 0 0
      51 [-]: NEWTABLE R38 0 4
      52 [-]: NEWTABLE R39 0 1
      53 [-]: DUPTABLE R40 15
      54 [-]: LOADK R41 K16 [0.050000000000000003]
      55 [-]: SETTABLEKS R41 R40 K13 ["X"]
      56 [-]: LOADK R41 K17 [0.01]
      57 [-]: SETTABLEKS R41 R40 K14 ["Y"]
      58 [-]: SETLIST R39 R40 1 [1]
      59 [-]: NEWTABLE R40 0 2
      60 [-]: DUPTABLE R41 15
      61 [-]: LOADK R42 K18 [-0.14999999999999999]
      62 [-]: SETTABLEKS R42 R41 K13 ["X"]
      63 [-]: LOADK R42 K16 [0.050000000000000003]
      64 [-]: SETTABLEKS R42 R41 K14 ["Y"]
      65 [-]: DUPTABLE R42 15
      66 [-]: LOADK R43 K19 [0.14999999999999999]
      67 [-]: SETTABLEKS R43 R42 K13 ["X"]
      68 [-]: LOADK R43 K20 [-0.02]
      69 [-]: SETTABLEKS R43 R42 K14 ["Y"]
      70 [-]: SETLIST R40 R41 2 [1]
      71 [-]: NEWTABLE R41 0 3
      72 [-]: DUPTABLE R42 15
      73 [-]: LOADK R43 K21 [-0.10000000000000001]
      74 [-]: SETTABLEKS R43 R42 K13 ["X"]
      75 [-]: LOADK R43 K17 [0.01]
      76 [-]: SETTABLEKS R43 R42 K14 ["Y"]
      77 [-]: DUPTABLE R43 15
      78 [-]: LOADN R44 0  
      79 [-]: SETTABLEKS R44 R43 K13 ["X"]
      80 [-]: LOADK R44 K22 [-0.01]
      81 [-]: SETTABLEKS R44 R43 K14 ["Y"]
      82 [-]: DUPTABLE R44 15
      83 [-]: LOADK R45 K23 [0.10000000000000001]
      84 [-]: SETTABLEKS R45 R44 K13 ["X"]
      85 [-]: LOADK R45 K17 [0.01]
      86 [-]: SETTABLEKS R45 R44 K14 ["Y"]
      87 [-]: SETLIST R41 R42 3 [1]
      88 [-]: NEWTABLE R42 0 4
      89 [-]: DUPTABLE R43 15
      90 [-]: LOADK R44 K18 [-0.14999999999999999]
      91 [-]: SETTABLEKS R44 R43 K13 ["X"]
      92 [-]: LOADK R44 K16 [0.050000000000000003]
      93 [-]: SETTABLEKS R44 R43 K14 ["Y"]
      94 [-]: DUPTABLE R44 15
      95 [-]: LOADK R45 K24 [-0.050000000000000003]
      96 [-]: SETTABLEKS R45 R44 K13 ["X"]
      97 [-]: LOADK R45 K20 [-0.02]
      98 [-]: SETTABLEKS R45 R44 K14 ["Y"]
      99 [-]: DUPTABLE R45 15
     100 [-]: LOADK R46 K16 [0.050000000000000003]
     101 [-]: SETTABLEKS R46 R45 K13 ["X"]
     102 [-]: LOADK R46 K25 [0.02]
     103 [-]: SETTABLEKS R46 R45 K14 ["Y"]
     104 [-]: DUPTABLE R46 15
     105 [-]: LOADK R47 K19 [0.14999999999999999]
     106 [-]: SETTABLEKS R47 R46 K13 ["X"]
     107 [-]: LOADK R47 K20 [-0.02]
     108 [-]: SETTABLEKS R47 R46 K14 ["Y"]
     109 [-]: SETLIST R42 R43 4 [1]
     110 [-]: SETLIST R38 R39 4 [1]
     111 [-]: LOADNIL R39  
     112 [-]: LOADNIL R40  
     113 [-]: LOADNIL R41  
     114 [-]: LOADNIL R42  
     115 [-]: LOADNIL R43  
     116 [-]: LOADK R44 K26 [13421772]
     117 [-]: LOADK R45 K27 [11436338]
     118 [-]: LOADK R46 K28 [13369344]
     119 [-]: LOADK R47 K29 [3289650]
     120 [-]: LOADK R48 K30 [2333408]
     121 [-]: LOADNIL R49  
     122 [-]: LOADNIL R50  
     123 [-]: LOADNIL R51  
     124 [-]: NEWCLOSURE R52 P0
     125 [-]: MOVE R1 R40  
     126 [-]: MOVE R1 R21  
     127 [-]: MOVE R1 R43  
     128 [-]: MOVE R1 R42  
     129 [-]: MOVE R1 R39  
     130 [-]: MOVE R1 R51  
     131 [-]: DUPCLOSURE R53 K31 []
     132 [-]: DUPCLOSURE R54 K32 []
     133 [-]: NEWCLOSURE R55 P3
     134 [-]: MOVE R1 R27  
     135 [-]: MOVE R0 R54  
     136 [-]: MOVE R1 R36  
     137 [-]: NEWCLOSURE R56 P4
     138 [-]: MOVE R1 R8   
     139 [-]: MOVE R1 R14  
     140 [-]: MOVE R1 R21  
     141 [-]: MOVE R1 R0   
     142 [-]: MOVE R1 R11  
     143 [-]: MOVE R1 R48  
     144 [-]: MOVE R0 R53  
     145 [-]: MOVE R0 R52  
     146 [-]: MOVE R1 R23  
     147 [-]: MOVE R0 R3   
     148 [-]: MOVE R1 R25  
     149 [-]: MOVE R1 R22  
     150 [-]: DUPCLOSURE R57 K33 []
     151 [-]: MOVE R0 R56  
     152 [-]: SETGLOBAL R57 K34 ["Close"]
     153 [-]: NEWCLOSURE R57 P6
     154 [-]: MOVE R1 R11  
     155 [-]: MOVE R0 R52  
     156 [-]: MOVE R0 R3   
     157 [-]: MOVE R1 R49  
     158 [-]: MOVE R1 R50  
     159 [-]: NEWCLOSURE R58 P7
     160 [-]: MOVE R1 R8   
     161 [-]: MOVE R1 R12  
     162 [-]: MOVE R0 R57  
     163 [-]: MOVE R0 R3   
     164 [-]: NEWCLOSURE R59 P8
     165 [-]: MOVE R1 R8   
     166 [-]: NEWCLOSURE R60 P9
     167 [-]: MOVE R1 R14  
     168 [-]: SETGLOBAL R60 K35 ["EffectFadeOut"]
     169 [-]: NEWCLOSURE R60 P10
     170 [-]: MOVE R1 R14  
     171 [-]: MOVE R1 R36  
     172 [-]: MOVE R1 R21  
     173 [-]: SETGLOBAL R60 K36 ["Shutdown"]
     174 [-]: NEWCLOSURE R60 P11
     175 [-]: MOVE R1 R32  
     176 [-]: MOVE R1 R33  
     177 [-]: MOVE R0 R20  
     178 [-]: MOVE R1 R2   
     179 [-]: NEWCLOSURE R61 P12
     180 [-]: MOVE R1 R32  
     181 [-]: MOVE R1 R34  
     182 [-]: MOVE R0 R31  
     183 [-]: NEWCLOSURE R62 P13
     184 [-]: MOVE R0 R61  
     185 [-]: MOVE R1 R33  
     186 [-]: MOVE R1 R10  
     187 [-]: MOVE R1 R0   
     188 [-]: MOVE R0 R60  
     189 [-]: MOVE R1 R32  
     190 [-]: MOVE R1 R37  
     191 [-]: MOVE R0 R5   
     192 [-]: MOVE R0 R20  
     193 [-]: MOVE R1 R11  
     194 [-]: MOVE R1 R2   
     195 [-]: MOVE R1 R1   
     196 [-]: MOVE R0 R57  
     197 [-]: MOVE R1 R12  
     198 [-]: NEWCLOSURE R63 P14
     199 [-]: MOVE R1 R11  
     200 [-]: MOVE R1 R1   
     201 [-]: DUPCLOSURE R64 K37 []
     202 [-]: MOVE R0 R63  
     203 [-]: SETGLOBAL R64 K38 ["SetPartialSolution"]
     204 [-]: NEWCLOSURE R64 P16
     205 [-]: MOVE R1 R0   
     206 [-]: MOVE R0 R63  
     207 [-]: MOVE R1 R21  
     208 [-]: MOVE R0 R56  
     209 [-]: DUPCLOSURE R65 K39 []
     210 [-]: MOVE R0 R64  
     211 [-]: SETGLOBAL R65 K40 ["ForceComplete"]
     212 [-]: NEWCLOSURE R65 P18
     213 [-]: MOVE R1 R44  
     214 [-]: MOVE R1 R45  
     215 [-]: MOVE R0 R3   
     216 [-]: MOVE R1 R48  
     217 [-]: MOVE R0 R65  
     218 [-]: DUPCLOSURE R66 K41 []
     219 [-]: MOVE R0 R66  
     220 [-]: NEWCLOSURE R67 P20
     221 [-]: MOVE R1 R28  
     222 [-]: MOVE R1 R23  
     223 [-]: MOVE R0 R55  
     224 [-]: MOVE R1 R21  
     225 [-]: MOVE R0 R3   
     226 [-]: NEWCLOSURE R68 P21
     227 [-]: MOVE R1 R11  
     228 [-]: MOVE R0 R67  
     229 [-]: MOVE R1 R28  
     230 [-]: MOVE R1 R0   
     231 [-]: MOVE R1 R23  
     232 [-]: MOVE R0 R66  
     233 [-]: MOVE R0 R65  
     234 [-]: NEWCLOSURE R69 P22
     235 [-]: MOVE R1 R21  
     236 [-]: MOVE R0 R56  
     237 [-]: SETGLOBAL R69 K42 ["OnGoalUnlock"]
     238 [-]: NEWCLOSURE R69 P23
     239 [-]: MOVE R1 R32  
     240 [-]: MOVE R1 R0   
     241 [-]: MOVE R1 R11  
     242 [-]: MOVE R1 R21  
     243 [-]: MOVE R0 R56  
     244 [-]: MOVE R1 R33  
     245 [-]: MOVE R0 R31  
     246 [-]: NEWCLOSURE R70 P24
     247 [-]: MOVE R1 R36  
     248 [-]: NEWCLOSURE R71 P25
     249 [-]: MOVE R1 R0   
     250 [-]: MOVE R1 R32  
     251 [-]: MOVE R1 R24  
     252 [-]: MOVE R0 R70  
     253 [-]: MOVE R1 R11  
     254 [-]: MOVE R0 R53  
     255 [-]: MOVE R0 R52  
     256 [-]: MOVE R1 R26  
     257 [-]: MOVE R1 R25  
     258 [-]: NEWCLOSURE R72 P26
     259 [-]: MOVE R1 R11  
     260 [-]: MOVE R1 R0   
     261 [-]: MOVE R1 R7   
     262 [-]: MOVE R1 R45  
     263 [-]: MOVE R1 R32  
     264 [-]: MOVE R1 R1   
     265 [-]: MOVE R1 R44  
     266 [-]: MOVE R0 R69  
     267 [-]: MOVE R0 R68  
     268 [-]: MOVE R0 R3   
     269 [-]: MOVE R1 R47  
     270 [-]: MOVE R0 R53  
     271 [-]: MOVE R0 R52  
     272 [-]: NEWCLOSURE R73 P27
     273 [-]: MOVE R1 R25  
     274 [-]: MOVE R1 R26  
     275 [-]: MOVE R1 R13  
     276 [-]: NEWCLOSURE R74 P28
     277 [-]: MOVE R1 R1   
     278 [-]: MOVE R1 R0   
     279 [-]: MOVE R1 R11  
     280 [-]: MOVE R1 R15  
     281 [-]: MOVE R0 R3   
     282 [-]: MOVE R1 R13  
     283 [-]: MOVE R0 R73  
     284 [-]: NEWCLOSURE R75 P29
     285 [-]: MOVE R0 R3   
     286 [-]: MOVE R1 R11  
     287 [-]: MOVE R1 R12  
     288 [-]: MOVE R0 R53  
     289 [-]: MOVE R0 R52  
     290 [-]: MOVE R1 R0   
     291 [-]: MOVE R1 R25  
     292 [-]: MOVE R1 R27  
     293 [-]: MOVE R1 R9   
     294 [-]: MOVE R1 R8   
     295 [-]: NEWCLOSURE R76 P30
     296 [-]: MOVE R1 R45  
     297 [-]: MOVE R0 R3   
     298 [-]: MOVE R0 R73  
     299 [-]: DUPCLOSURE R77 K43 []
     300 [-]: DUPCLOSURE R78 K44 []
     301 [-]: DUPCLOSURE R79 K45 []
     302 [-]: DUPCLOSURE R80 K46 []
     303 [-]: NEWCLOSURE R81 P35
     304 [-]: MOVE R1 R30  
     305 [-]: MOVE R1 R23  
     306 [-]: MOVE R0 R79  
     307 [-]: MOVE R0 R78  
     308 [-]: MOVE R1 R28  
     309 [-]: MOVE R0 R80  
     310 [-]: MOVE R0 R67  
     311 [-]: NEWCLOSURE R82 P36
     312 [-]: MOVE R1 R23  
     313 [-]: MOVE R0 R55  
     314 [-]: MOVE R0 R81  
     315 [-]: MOVE R1 R28  
     316 [-]: MOVE R0 R38  
     317 [-]: MOVE R0 R77  
     318 [-]: MOVE R1 R29  
     319 [-]: MOVE R1 R26  
     320 [-]: NEWCLOSURE R83 P37
     321 [-]: MOVE R1 R32  
     322 [-]: MOVE R1 R39  
     323 [-]: MOVE R1 R40  
     324 [-]: MOVE R1 R41  
     325 [-]: MOVE R1 R42  
     326 [-]: MOVE R1 R43  
     327 [-]: MOVE R1 R49  
     328 [-]: MOVE R1 R50  
     329 [-]: MOVE R1 R51  
     330 [-]: MOVE R1 R44  
     331 [-]: MOVE R0 R3   
     332 [-]: MOVE R1 R45  
     333 [-]: MOVE R1 R46  
     334 [-]: MOVE R1 R47  
     335 [-]: MOVE R1 R48  
     336 [-]: NEWCLOSURE R84 P38
     337 [-]: MOVE R1 R32  
     338 [-]: DUPCLOSURE R85 K47 []
     339 [-]: MOVE R0 R3   
     340 [-]: NEWCLOSURE R86 P40
     341 [-]: MOVE R0 R84  
     342 [-]: MOVE R1 R0   
     343 [-]: MOVE R1 R7   
     344 [-]: MOVE R1 R2   
     345 [-]: MOVE R1 R37  
     346 [-]: MOVE R1 R29  
     347 [-]: MOVE R1 R30  
     348 [-]: MOVE R1 R36  
     349 [-]: MOVE R1 R1   
     350 [-]: MOVE R1 R32  
     351 [-]: MOVE R0 R3   
     352 [-]: MOVE R1 R45  
     353 [-]: MOVE R0 R83  
     354 [-]: MOVE R0 R82  
     355 [-]: MOVE R0 R72  
     356 [-]: MOVE R0 R76  
     357 [-]: MOVE R0 R85  
     358 [-]: SETGLOBAL R86 K48 ["Initialize"]
     359 [-]: NEWCLOSURE R86 P41
     360 [-]: MOVE R0 R59  
     361 [-]: MOVE R1 R10  
     362 [-]: MOVE R0 R62  
     363 [-]: MOVE R1 R18  
     364 [-]: MOVE R1 R17  
     365 [-]: MOVE R1 R9   
     366 [-]: MOVE R0 R71  
     367 [-]: MOVE R0 R75  
     368 [-]: MOVE R0 R74  
     369 [-]: MOVE R1 R14  
     370 [-]: MOVE R1 R8   
     371 [-]: MOVE R1 R36  
     372 [-]: MOVE R1 R23  
     373 [-]: MOVE R1 R32  
     374 [-]: MOVE R1 R35  
     375 [-]: MOVE R1 R34  
     376 [-]: MOVE R0 R6   
     377 [-]: MOVE R1 R19  
     378 [-]: MOVE R0 R4   
     379 [-]: SETGLOBAL R86 K49 ["Update"]
     380 [-]: DUPCLOSURE R86 K50 []
     381 [-]: MOVE R0 R56  
     382 [-]: SETGLOBAL R86 K51 ["onKeyUp_MINI_INVENTORY_HOLD"]
     383 [-]: DUPCLOSURE R86 K52 []
     384 [-]: MOVE R0 R56  
     385 [-]: SETGLOBAL R86 K53 ["onKeyUp_MINI_INVENTORY_TOGGLE"]
     386 [-]: NEWCLOSURE R86 P44
     387 [-]: MOVE R1 R8   
     388 [-]: SETGLOBAL R86 K54 ["onKeyDown_MINI_GAME_SELECT"]
     389 [-]: DUPCLOSURE R86 K55 []
     390 [-]: SETGLOBAL R86 K56 ["onKeyDown_MENU_SELECT"]
     391 [-]: NEWCLOSURE R86 P46
     392 [-]: MOVE R1 R8   
     393 [-]: MOVE R0 R56  
     394 [-]: SETGLOBAL R86 K57 ["onKeyDown_MENU_CANCEL"]
     395 [-]: NEWCLOSURE R86 P47
     396 [-]: MOVE R1 R8   
     397 [-]: SETGLOBAL R86 K58 ["IsInputBlocked"]
     398 [-]: NEWCLOSURE R86 P48
     399 [-]: MOVE R1 R11  
     400 [-]: MOVE R1 R12  
     401 [-]: MOVE R1 R8   
     402 [-]: MOVE R0 R3   
     403 [-]: DUPCLOSURE R87 K59 []
     404 [-]: MOVE R0 R86  
     405 [-]: SETGLOBAL R87 K60 ["onKeyDown_MENU_MOUSE_Z"]
     406 [-]: DUPCLOSURE R87 K61 []
     407 [-]: MOVE R0 R86  
     408 [-]: SETGLOBAL R87 K62 ["onKeyDown_MENU_CLICK"]
     409 [-]: DUPCLOSURE R87 K63 []
     410 [-]: MOVE R0 R86  
     411 [-]: SETGLOBAL R87 K64 ["onKeyDown_MENU_RIGHT_CLICK"]
     412 [-]: DUPCLOSURE R87 K65 []
     413 [-]: MOVE R0 R86  
     414 [-]: SETGLOBAL R87 K66 ["onKeyDown_MENU_GENERIC1"]
     415 [-]: DUPCLOSURE R87 K67 []
     416 [-]: MOVE R0 R86  
     417 [-]: SETGLOBAL R87 K68 ["onKeyDown_MENU_UP"]
     418 [-]: DUPCLOSURE R87 K69 []
     419 [-]: MOVE R0 R86  
     420 [-]: SETGLOBAL R87 K70 ["onKeyDown_MENU_DOWN"]
     421 [-]: NEWCLOSURE R87 P55
     422 [-]: MOVE R0 R57  
     423 [-]: MOVE R1 R12  
     424 [-]: MOVE R1 R0   
     425 [-]: NEWCLOSURE R88 P56
     426 [-]: MOVE R0 R87  
     427 [-]: MOVE R1 R12  
     428 [-]: SETGLOBAL R88 K71 ["onKeyDown_MENU_LEFT"]
     429 [-]: NEWCLOSURE R88 P57
     430 [-]: MOVE R0 R87  
     431 [-]: MOVE R1 R12  
     432 [-]: SETGLOBAL R88 K72 ["onKeyDown_MENU_RIGHT"]
     433 [-]: NEWCLOSURE R88 P58
     434 [-]: MOVE R0 R87  
     435 [-]: MOVE R1 R12  
     436 [-]: SETGLOBAL R88 K73 ["onKeyDown_MENU_LTRIGGER2"]
     437 [-]: NEWCLOSURE R88 P59
     438 [-]: MOVE R0 R87  
     439 [-]: MOVE R1 R12  
     440 [-]: SETGLOBAL R88 K74 ["onKeyDown_MENU_RTRIGGER2"]
     441 [-]: NEWCLOSURE R88 P60
     442 [-]: MOVE R1 R16  
     443 [-]: DUPCLOSURE R89 K75 []
     444 [-]: MOVE R0 R88  
     445 [-]: MOVE R0 R86  
     446 [-]: SETGLOBAL R89 K76 ["onKeyDown_MENU_RIGHT_Y"]
     447 [-]: NEWCLOSURE R89 P62
     448 [-]: MOVE R1 R16  
     449 [-]: SETGLOBAL R89 K77 ["onKeyUp_MENU_RIGHT_Y"]
     450 [-]: NEWCLOSURE R89 P63
     451 [-]: MOVE R0 R88  
     452 [-]: MOVE R0 R87  
     453 [-]: MOVE R1 R12  
     454 [-]: SETGLOBAL R89 K78 ["onKeyDown_MENU_RIGHT_X"]
     455 [-]: NEWCLOSURE R89 P64
     456 [-]: MOVE R1 R16  
     457 [-]: SETGLOBAL R89 K79 ["onKeyUp_MENU_RIGHT_X"]
     458 [-]: NEWCLOSURE R89 P65
     459 [-]: MOVE R1 R11  
     460 [-]: MOVE R0 R58  
     461 [-]: SETGLOBAL R89 K80 ["DialFocused"]
     462 [-]: DUPCLOSURE R89 K81 []
     463 [-]: SETGLOBAL R89 K82 ["DialUnfocused"]
     464 [-]: DUPCLOSURE R89 K83 []
     465 [-]: MOVE R0 R86  
     466 [-]: SETGLOBAL R89 K84 ["DialPressed"]
     467 [-]: CLOSEUPVALS R0
     468 [-]: RETURN R0 0  


; Name:            
; Defined at line: 131
; #Upvalues:       6
; #Parameters:     4
; Is_vararg:       0
; Max Stack Size:  7

       0 [-]: GETUPVAL R4 0
       1 [-]: GETUPVAL R5 1
       2 [-]: JUMPIFNOT R5 L0
       3 [-]: GETUPVAL R4 2
       4 [-]: JUMP L2
     
L 0:   5 [-]: JUMPIFNOT R0 L1
       6 [-]: GETUPVAL R4 3
       7 [-]: JUMP L2
     
L 1:   8 [-]: JUMPIFNOT R1 L2
       9 [-]: GETUPVAL R4 4
L 2:  10 [-]: JUMPIF R1 L3 
      11 [-]: JUMPIF R3 L4 
L 3:  12 [-]: MOVE R5 R2   
      13 [-]: JUMPIF R5 L5 
L 4:  14 [-]: GETUPVAL R6 5
      15 [-]: MUL R5 R2 R6 
L 5:  16 [-]: SETTABLEKS R5 R4 K0 ["alpha"]
      17 [-]: RETURN R4 1  


; Name:            
; Defined at line: 144
; #Upvalues:       0
; #Parameters:     4
; Is_vararg:       0
; Max Stack Size:  10

       0 [-]: FASTCALL1 62 R0 L0
       1 [-]: MOVE R5 R0   
       2 [-]: GETIMPORT R4 1 [nil]
       3 [-]: CALL R4 1 1  
L 0:   4 [-]: JUMPIF R4 L1 
       5 [-]: GETIMPORT R4 3 [nil]
       6 [-]: NAMECALL R4 R4 K4 [0xA51F7C05]
       7 [-]: CALL R4 1 1  
       8 [-]: MOVE R7 R1   
       9 [-]: NAMECALL R5 R0 K5 [0xC2B4E597]
      10 [-]: CALL R5 2 0  
      11 [-]: GETTABLEKS R8 R4 K6 ["y"]
      12 [-]: MUL R7 R2 R8 
      13 [-]: GETTABLEKS R9 R4 K7 ["z"]
      14 [-]: MUL R8 R2 R9 
      15 [-]: NAMECALL R5 R0 K8 [0x1B50CF3B]
      16 [-]: CALL R5 3 0  
      17 [-]: GETTABLEKS R8 R4 K9 ["x"]
      18 [-]: MUL R7 R3 R8 
      19 [-]: NAMECALL R5 R0 K10 [0xCE1FC190]
      20 [-]: CALL R5 2 0  
L 1:  21 [-]: RETURN R0 0  


; Name:            
; Defined at line: 153
; #Upvalues:       0
; #Parameters:     1
; Is_vararg:       0
; Max Stack Size:  4

       0 [-]: SUBK R0 R0 K0 [1]
       1 [-]: MODK R2 R0 K1 [4]
       2 [-]: FASTCALL1 12 R2 L0
       3 [-]: GETIMPORT R1 4 [nil]
       4 [-]: CALL R1 1 1  
L 0:   5 [-]: DIVK R3 R0 K1 [4]
       6 [-]: FASTCALL1 12 R3 L1
       7 [-]: GETIMPORT R2 4 [nil]
       8 [-]: CALL R2 1 1  
L 1:   9 [-]: RETURN R1 2  


; Name:            
; Defined at line: 160
; #Upvalues:       3
; #Parameters:     3
; Is_vararg:       0
; Max Stack Size:  13

       0 [-]: GETUPVAL R4 0
       1 [-]: FASTCALL1 62 R4 L0
       2 [-]: GETIMPORT R3 1 [nil]
       3 [-]: CALL R3 1 1  
L 0:   4 [-]: JUMPIF R3 L2 
       5 [-]: GETIMPORT R4 3 [nil]
       6 [-]: FASTCALL1 62 R4 L1
       7 [-]: GETIMPORT R3 1 [nil]
       8 [-]: CALL R3 1 1  
L 1:   9 [-]: JUMPIFNOT R3 L3
L 2:  10 [-]: RETURN R0 0  
L 3:  11 [-]: GETUPVAL R3 1
      12 [-]: MOVE R4 R0   
      13 [-]: CALL R3 1 2  
      14 [-]: GETUPVAL R5 0
      15 [-]: GETIMPORT R7 3 [nil]
      16 [-]: GETIMPORT R8 5 [nil]
      17 [-]: NAMECALL R5 R5 K6 [0x47901F07]
      18 [-]: CALL R5 3 1  
      19 [-]: FASTCALL1 62 R5 L4
      20 [-]: MOVE R7 R5   
      21 [-]: GETIMPORT R6 1 [nil]
      22 [-]: CALL R6 1 1  
L 4:  23 [-]: JUMPIF R6 L6 
      24 [-]: GETIMPORT R8 8 [nil]
      25 [-]: LOADK R9 K9 ["uvOffsets"]
      26 [-]: CALL R8 1 1  
      27 [-]: DIVK R9 R3 K10 [4]
      28 [-]: DIVK R10 R4 K10 [4]
      29 [-]: LOADN R11 0  
      30 [-]: LOADN R12 0  
      31 [-]: NAMECALL R6 R5 K11 [0x986D2AB8]
      32 [-]: CALL R6 6 0  
      33 [-]: LOADK R8 K12 [0.001]
      34 [-]: LOADB R9 1   
      35 [-]: NAMECALL R6 R5 K13 [0x2D9BA74F]
      36 [-]: CALL R6 3 0  
      37 [-]: JUMPIFNOT R2 L5
      38 [-]: GETIMPORT R8 8 [nil]
      39 [-]: LOADK R9 K14 ["TintColor"]
      40 [-]: CALL R8 1 1  
      41 [-]: LOADN R9 1   
      42 [-]: LOADN R10 0  
      43 [-]: LOADN R11 0  
      44 [-]: LOADN R12 1  
      45 [-]: NAMECALL R6 R5 K11 [0x986D2AB8]
      46 [-]: CALL R6 6 0  
      47 [-]: JUMP L6
     
L 5:  48 [-]: GETIMPORT R8 8 [nil]
      49 [-]: LOADK R9 K14 ["TintColor"]
      50 [-]: CALL R8 1 1  
      51 [-]: LOADK R9 K15 [0.68200000000000005]
      52 [-]: LOADK R10 K16 [0.50600000000000001]
      53 [-]: LOADK R11 K17 [0.19600000000000001]
      54 [-]: LOADN R12 1  
      55 [-]: NAMECALL R6 R5 K11 [0x986D2AB8]
      56 [-]: CALL R6 6 0  
L 6:  57 [-]: GETIMPORT R6 19 [nil]
      58 [-]: GETIMPORT R7 21 [nil]
      59 [-]: MOVE R8 R1   
      60 [-]: LOADN R9 2   
      61 [-]: NEWTABLE R10 0 1
      62 [-]: NEWCLOSURE R11 P0
      63 [-]: MOVE R0 R5   
      64 [-]: SETLIST R10 R11 1 [1]
      65 [-]: NEWTABLE R11 0 1
      66 [-]: LOADN R12 1  
      67 [-]: SETLIST R11 R12 1 [1]
      68 [-]: GETIMPORT R12 23 [nil]
      69 [-]: CALL R6 6 0  
      70 [-]: GETUPVAL R7 2
      71 [-]: FASTCALL2 52 R7 R5 L7
      72 [-]: MOVE R8 R5   
      73 [-]: GETIMPORT R6 26 [nil]
      74 [-]: CALL R6 2 0  
L 7:  75 [-]: RETURN R5 1  


; Name:            
; Defined at line: 189
; #Upvalues:       12
; #Parameters:     0
; Is_vararg:       0
; Max Stack Size:  18

       0 [-]: LOADB R0 1   
       1 [-]: SETUPVAL R0 0
       2 [-]: GETUPVAL R1 1
       3 [-]: FASTCALL1 62 R1 L0
       4 [-]: GETIMPORT R0 1 [nil]
       5 [-]: CALL R0 1 1  
L 0:   6 [-]: JUMPIF R0 L1 
       7 [-]: GETUPVAL R0 1
       8 [-]: GETIMPORT R2 3 [nil]
       9 [-]: LOADK R3 K4 ["EffectFadeOut"]
      10 [-]: CALL R2 1 1  
      11 [-]: LOADB R3 0   
      12 [-]: NAMECALL R0 R0 K5 [0xD5F7912B]
      13 [-]: CALL R0 3 0  
L 1:  14 [-]: LOADN R0 0   
      15 [-]: GETUPVAL R1 2
      16 [-]: JUMPIFNOT R1 L12
      17 [-]: LOADN R3 1   
      18 [-]: GETUPVAL R1 3
      19 [-]: LOADN R2 1   
      20 [-]: FORNPREP R1 L5
L 2:  21 [-]: GETUPVAL R5 4
      22 [-]: GETTABLE R4 R5 R3
      23 [-]: JUMPXEQKNIL R4 L4
      24 [-]: GETTABLEKS R5 R4 K6 ["FocusedElement"]
      25 [-]: JUMPXEQKNIL R5 L3
      26 [-]: GETTABLEKS R6 R4 K6 ["FocusedElement"]
      27 [-]: GETTABLEKS R5 R6 K7 ["mClipName"]
      28 [-]: JUMPXEQKNIL R5 L3
      29 [-]: GETIMPORT R5 9 [nil]
      30 [-]: GETTABLEKS R8 R4 K6 ["FocusedElement"]
      31 [-]: GETTABLEKS R7 R8 K7 ["mClipName"]
      32 [-]: LOADK R8 K10 ["Icon"]
      33 [-]: LOADN R9 9   
      34 [-]: GETUPVAL R10 5
      35 [-]: NAMECALL R5 R5 K11 [0xF64B7262]
      36 [-]: CALL R5 5 0  
L 3:  37 [-]: GETUPVAL R5 6
      38 [-]: GETTABLEKS R6 R4 K12 ["RingEntity"]
      39 [-]: GETUPVAL R7 7
      40 [-]: GETTABLEKS R8 R4 K13 ["mLocked"]
      41 [-]: LOADB R9 0   
      42 [-]: LOADN R10 255
      43 [-]: LOADB R11 1  
      44 [-]: CALL R7 4 1  
      45 [-]: LOADK R8 K14 [0.22222222222222221]
      46 [-]: LOADK R9 K15 [0.059999999999999998]
      47 [-]: CALL R5 4 0  
      48 [-]: GETUPVAL R5 6
      49 [-]: GETTABLEKS R6 R4 K16 ["RingFrontEntity"]
      50 [-]: GETUPVAL R7 7
      51 [-]: GETTABLEKS R8 R4 K13 ["mLocked"]
      52 [-]: LOADB R9 0   
      53 [-]: LOADN R10 255
      54 [-]: CALL R7 3 1  
      55 [-]: LOADK R8 K14 [0.22222222222222221]
      56 [-]: LOADK R9 K15 [0.059999999999999998]
      57 [-]: CALL R5 4 0  
L 4:  58 [-]: FORNLOOP R1 L2
L 5:  59 [-]: GETUPVAL R2 8
      60 [-]: GETTABLEKS R1 R2 K17 ["Elements"]
      61 [-]: LOADN R4 1   
      62 [-]: LENGTH R2 R1 
      63 [-]: LOADN R3 1   
      64 [-]: FORNPREP R2 L11
L 6:  65 [-]: GETTABLE R6 R1 R4
      66 [-]: GETTABLEKS R5 R6 K18 ["Symbols"]
      67 [-]: LOADN R8 1   
      68 [-]: LENGTH R6 R5 
      69 [-]: LOADN R7 1   
      70 [-]: FORNPREP R6 L10
L 7:  71 [-]: GETTABLE R10 R5 R8
      72 [-]: FASTCALL1 62 R10 L8
      73 [-]: GETIMPORT R9 1 [nil]
      74 [-]: CALL R9 1 1  
L 8:  75 [-]: JUMPIF R9 L9 
      76 [-]: GETTABLE R9 R5 R8
      77 [-]: GETIMPORT R11 3 [nil]
      78 [-]: LOADK R12 K19 ["TintColor"]
      79 [-]: CALL R11 1 1 
      80 [-]: LOADK R12 K20 [0.012999999999999999]
      81 [-]: LOADK R13 K21 [0.33000000000000002]
      82 [-]: LOADK R14 K22 [0.75]
      83 [-]: LOADN R15 1  
      84 [-]: NAMECALL R9 R9 K23 [0x986D2AB8]
      85 [-]: CALL R9 6 0  
L 9:  86 [-]: FORNLOOP R6 L7
L10:  87 [-]: FORNLOOP R2 L6
L11:  88 [-]: GETUPVAL R3 9
      89 [-]: GETTABLEKS R2 R3 K24 [0x659D451F]
      90 [-]: GETIMPORT R3 26 [nil]
      91 [-]: CALL R2 1 0  
      92 [-]: LOADN R0 1   
      93 [-]: JUMP L17
    
L12:  94 [-]: GETUPVAL R2 8
      95 [-]: GETTABLEKS R1 R2 K17 ["Elements"]
      96 [-]: LENGTH R2 R1 
      97 [-]: LOADN R3 0   
      98 [-]: JUMPIFNOTLT R3 R2 L16
      99 [-]: NEWTABLE R2 0 0
     100 [-]: LOADN R5 1   
     101 [-]: LENGTH R3 R1 
     102 [-]: LOADN R4 1   
     103 [-]: FORNPREP R3 L15
L13: 104 [-]: GETTABLE R9 R1 R5
     105 [-]: GETTABLEKS R8 R9 K27 ["SymbolIds"]
     106 [-]: FASTCALL2 52 R2 R8 L14
     107 [-]: MOVE R7 R2   
     108 [-]: GETIMPORT R6 30 [nil]
     109 [-]: CALL R6 2 0  
L14: 110 [-]: FORNLOOP R3 L13
L15: 111 [-]: GETIMPORT R3 33 [nil]
     112 [-]: SETTABLEKS R2 R3 K34 ["SavedHints"]
L16: 113 [-]: GETUPVAL R3 9
     114 [-]: GETTABLEKS R2 R3 K24 [0x659D451F]
     115 [-]: GETIMPORT R3 36 [nil]
     116 [-]: CALL R2 1 0  
L17: 117 [-]: NEWTABLE R1 0 0
     118 [-]: NEWCLOSURE R2 P0
     119 [-]: MOVE R0 R1   
     120 [-]: MOVE R2 R9   
     121 [-]: NEWCLOSURE R3 P1
     122 [-]: MOVE R0 R2   
     123 [-]: MOVE R2 R4   
     124 [-]: MOVE R2 R6   
     125 [-]: MOVE R2 R7   
     126 [-]: LOADK R5 K37 [0.10000000000000001]
     127 [-]: LOADK R7 K38 [0.5]
     128 [-]: GETUPVAL R8 3
     129 [-]: DIV R6 R7 R8 
     130 [-]: FASTCALL2 19 R5 R6 L18
     131 [-]: GETIMPORT R4 41 [nil]
     132 [-]: CALL R4 2 1  
L18: 133 [-]: LOADN R7 1   
     134 [-]: GETUPVAL R5 3
     135 [-]: LOADN R6 1   
     136 [-]: FORNPREP R5 L20
L19: 137 [-]: LOADK R9 K42 ["Dial"]
     138 [-]: MOVE R10 R7  
     139 [-]: CONCAT R8 R9 R10
     140 [-]: GETIMPORT R9 44 [nil]
     141 [-]: GETIMPORT R10 9 [nil]
     142 [-]: MOVE R11 R8  
     143 [-]: LOADN R12 2  
     144 [-]: NEWTABLE R13 0 2
     145 [-]: LOADN R14 5  
     146 [-]: LOADN R15 10 
     147 [-]: SETLIST R13 R14 2 [1]
     148 [-]: NEWTABLE R14 0 2
     149 [-]: LOADN R15 10 
     150 [-]: LOADN R16 0  
     151 [-]: SETLIST R14 R15 2 [1]
     152 [-]: LOADK R15 K45 [0.25]
     153 [-]: MUL R17 R4 R7
     154 [-]: ADD R16 R17 R0
     155 [-]: NEWCLOSURE R17 P2
     156 [-]: MOVE R0 R8   
     157 [-]: MOVE R0 R3   
     158 [-]: MOVE R0 R7   
     159 [-]: CALL R9 8 0  
     160 [-]: FORNLOOP R5 L19
L20: 161 [-]: NEWCLOSURE R5 P3
     162 [-]: MOVE R2 R6   
     163 [-]: MOVE R2 R10  
     164 [-]: MOVE R2 R7   
     165 [-]: GETIMPORT R6 44 [nil]
     166 [-]: GETIMPORT R7 9 [nil]
     167 [-]: LOADK R8 K46 ["LinesRingShrink"]
     168 [-]: LOADN R9 2   
     169 [-]: NEWTABLE R10 0 1
     170 [-]: MOVE R11 R5  
     171 [-]: SETLIST R10 R11 1 [1]
     172 [-]: NEWTABLE R11 0 1
     173 [-]: LOADN R12 1  
     174 [-]: SETLIST R11 R12 1 [1]
     175 [-]: LOADK R12 K47 [0.40000000000000002]
     176 [-]: LOADN R14 0  
     177 [-]: ADD R13 R14 R0
     178 [-]: CALL R6 7 0  
     179 [-]: GETUPVAL R7 8
     180 [-]: FASTCALL1 62 R7 L21
     181 [-]: GETIMPORT R6 1 [nil]
     182 [-]: CALL R6 1 1  
L21: 183 [-]: JUMPIF R6 L23
     184 [-]: GETUPVAL R7 8
     185 [-]: GETTABLEKS R6 R7 K17 ["Elements"]
     186 [-]: LOADN R9 1   
     187 [-]: LENGTH R7 R6 
     188 [-]: LOADN R8 1   
     189 [-]: FORNPREP R7 L23
L22: 190 [-]: GETTABLE R10 R6 R9
     191 [-]: LOADN R13 0  
     192 [-]: ADD R12 R13 R0
     193 [-]: NAMECALL R10 R10 K48 [0xA2880940]
     194 [-]: CALL R10 2 0 
     195 [-]: FORNLOOP R7 L22
L23: 196 [-]: GETIMPORT R6 44 [nil]
     197 [-]: GETIMPORT R7 9 [nil]
     198 [-]: LOADK R8 K49 ["_root"]
     199 [-]: LOADN R9 2   
     200 [-]: NEWTABLE R10 0 1
     201 [-]: LOADN R11 10 
     202 [-]: SETLIST R10 R11 1 [1]
     203 [-]: NEWTABLE R11 0 1
     204 [-]: LOADN R12 0  
     205 [-]: SETLIST R11 R12 1 [1]
     206 [-]: LOADK R12 K50 [0.34999999999999998]
     207 [-]: LOADK R14 K38 [0.5]
     208 [-]: ADD R13 R14 R0
     209 [-]: NEWCLOSURE R14 P4
     210 [-]: MOVE R2 R2   
     211 [-]: MOVE R2 R9   
     212 [-]: MOVE R2 R11  
     213 [-]: CALL R6 8 0  
     214 [-]: RETURN R0 0  


; Name:            
; Defined at line: 310
; #Upvalues:       1
; #Parameters:     0
; Is_vararg:       0
; Max Stack Size:  1

       0 [-]: GETUPVAL R0 0
       1 [-]: CALL R0 0 0  
       2 [-]: RETURN R0 0  


; Name:            
; Defined at line: 314
; #Upvalues:       5
; #Parameters:     2
; Is_vararg:       0
; Max Stack Size:  16

       0 [-]: GETUPVAL R3 0
       1 [-]: GETTABLE R2 R3 R0
       2 [-]: GETTABLEKS R3 R2 K0 ["FocusedElement"]
       3 [-]: GETTABLEKS R4 R2 K1 ["RingLoaded"]
       4 [-]: JUMPIFNOT R4 L2
       5 [-]: GETTABLEKS R5 R2 K2 ["RingEntity"]
       6 [-]: FASTCALL1 62 R5 L0
       7 [-]: GETIMPORT R4 4 [nil]
       8 [-]: CALL R4 1 1  
L 0:   9 [-]: JUMPIF R4 L2 
      10 [-]: GETTABLEKS R5 R2 K5 ["RingFrontEntity"]
      11 [-]: FASTCALL1 62 R5 L1
      12 [-]: GETIMPORT R4 4 [nil]
      13 [-]: CALL R4 1 1  
L 1:  14 [-]: JUMPIF R4 L2 
      15 [-]: GETTABLEKS R4 R2 K2 ["RingEntity"]
      16 [-]: GETUPVAL R6 1
      17 [-]: GETTABLEKS R7 R2 K6 ["mLocked"]
      18 [-]: MOVE R8 R1   
      19 [-]: LOADN R9 255 
      20 [-]: LOADB R10 1  
      21 [-]: CALL R6 4 -1 
      22 [-]: NAMECALL R4 R4 K7 [0xC2B4E597]
      23 [-]: CALL R4 -1 0 
      24 [-]: GETTABLEKS R4 R2 K5 ["RingFrontEntity"]
      25 [-]: GETUPVAL R6 1
      26 [-]: GETTABLEKS R7 R2 K6 ["mLocked"]
      27 [-]: MOVE R8 R1   
      28 [-]: LOADN R9 255 
      29 [-]: CALL R6 3 -1 
      30 [-]: NAMECALL R4 R4 K7 [0xC2B4E597]
      31 [-]: CALL R4 -1 0 
L 2:  32 [-]: JUMPIFNOT R3 L6
      33 [-]: LOADN R6 1   
      34 [-]: GETTABLEKS R7 R2 K8 ["mElements"]
      35 [-]: LENGTH R4 R7 
      36 [-]: LOADN R5 1   
      37 [-]: FORNPREP R4 L6
L 3:  38 [-]: GETIMPORT R7 10 [nil]
      39 [-]: GETTABLEKS R11 R2 K8 ["mElements"]
      40 [-]: GETTABLE R10 R11 R6
      41 [-]: GETTABLEKS R9 R10 K11 ["mClipName"]
      42 [-]: LOADK R10 K12 ["Icon"]
      43 [-]: LOADN R11 10 
      44 [-]: GETUPVAL R13 2
      45 [-]: GETTABLEKS R12 R13 K13 [0x06D055F9]
      46 [-]: GETTABLEKS R14 R3 K14 ["Id"]
      47 [-]: JUMPIFEQ R14 R6 L4
      48 [-]: LOADB R13 0 +1
L 4:  49 [-]: LOADB R13 1  
L 5:  50 [-]: GETUPVAL R14 3
      51 [-]: GETUPVAL R15 4
      52 [-]: CALL R12 3 -1
      53 [-]: NAMECALL R7 R7 K15 [0xF64B7262]
      54 [-]: CALL R7 -1 0 
      55 [-]: FORNLOOP R4 L3
L 6:  56 [-]: RETURN R0 0  


; Name:            
; Defined at line: 330
; #Upvalues:       4
; #Parameters:     1
; Is_vararg:       0
; Max Stack Size:  4

       0 [-]: GETUPVAL R1 0
       1 [-]: JUMPIF R1 L0 
       2 [-]: GETUPVAL R1 1
       3 [-]: JUMPIFNOTEQ R1 R0 L1
L 0:   4 [-]: RETURN R0 0  
L 1:   5 [-]: GETUPVAL R1 1
       6 [-]: JUMPXEQKNIL R1 L2
       7 [-]: GETUPVAL R1 2
       8 [-]: GETUPVAL R2 1
       9 [-]: LOADB R3 0   
      10 [-]: CALL R1 2 0  
      11 [-]: GETUPVAL R2 3
      12 [-]: GETTABLEKS R1 R2 K0 [0x659D451F]
      13 [-]: GETIMPORT R2 2 [nil]
      14 [-]: CALL R1 1 0  
L 2:  15 [-]: SETUPVAL R0 1
      16 [-]: GETUPVAL R1 2
      17 [-]: GETUPVAL R2 1
      18 [-]: LOADB R3 1   
      19 [-]: CALL R1 2 0  
      20 [-]: RETURN R0 0  


; Name:            
; Defined at line: 344
; #Upvalues:       1
; #Parameters:     1
; Is_vararg:       0
; Max Stack Size:  5

       0 [-]: LOADB R1 1   
       1 [-]: SETUPVAL R1 0
       2 [-]: GETIMPORT R1 1 [nil]
       3 [-]: LOADK R3 K2 ["Wheel"]
       4 [-]: NAMECALL R1 R1 K3 [0xAF5300DC]
       5 [-]: CALL R1 2 0  
       6 [-]: GETIMPORT R1 1 [nil]
       7 [-]: NAMECALL R1 R1 K4 [0xA1653871]
       8 [-]: CALL R1 1 1  
       9 [-]: FASTCALL1 62 R1 L0
      10 [-]: MOVE R3 R1   
      11 [-]: GETIMPORT R2 6 [nil]
      12 [-]: CALL R2 1 1  
L 0:  13 [-]: JUMPIF R2 L1 
      14 [-]: LOADK R4 K7 ["Close"]
      15 [-]: NAMECALL R2 R1 K8 [0x8EB2112D]
      16 [-]: CALL R2 2 0  
L 1:  17 [-]: GETIMPORT R2 1 [nil]
      18 [-]: NAMECALL R2 R2 K9 [0x32302B4A]
      19 [-]: CALL R2 1 0  
      20 [-]: RETURN R0 0  


; Name:            
; Defined at line: 356
; #Upvalues:       1
; #Parameters:     1
; Is_vararg:       0
; Max Stack Size:  13

       0 [-]: LOADN R1 1   
       1 [-]: GETIMPORT R4 1 [nil]
       2 [-]: NAMECALL R2 R0 K2 [0xC1595BD5]
       3 [-]: CALL R2 2 1  
       4 [-]: GETIMPORT R5 4 [nil]
       5 [-]: NAMECALL R3 R0 K5 [0xC9F6A7D7]
       6 [-]: CALL R3 2 1  
L 0:   7 [-]: LOADN R4 0   
       8 [-]: JUMPIFNOTLT R4 R1 L5
       9 [-]: GETIMPORT R4 7 [nil]
      10 [-]: MOVE R5 R2   
      11 [-]: CALL R4 1 3  
      12 [-]: FORGPREP_INEXT R4 L2
L 1:  13 [-]: GETIMPORT R11 10 [nil]
      14 [-]: MOVE R12 R1  
      15 [-]: NAMECALL R9 R8 K11 [0x986D2AB8]
      16 [-]: CALL R9 3 0  
L 2:  17 [-]: FORGLOOP R4 L1 2 [inext]
      18 [-]: FASTCALL1 62 R3 L3
      19 [-]: MOVE R5 R3   
      20 [-]: GETIMPORT R4 13 [nil]
      21 [-]: CALL R4 1 1  
L 3:  22 [-]: JUMPIF R4 L4 
      23 [-]: MOVE R6 R1   
      24 [-]: NAMECALL R4 R3 K14 [0x178D8B0F]
      25 [-]: CALL R4 2 0  
L 4:  26 [-]: GETIMPORT R5 17 [nil]
      27 [-]: CALL R5 0 1  
      28 [-]: MULK R4 R5 K15 [4]
      29 [-]: SUB R1 R1 R4 
      30 [-]: GETIMPORT R4 19 [nil]
      31 [-]: LOADN R5 0   
      32 [-]: CALL R4 1 0  
      33 [-]: JUMPBACK L0  
L 5:  34 [-]: LOADN R4 1   
      35 [-]: JUMPIFNOTLT R1 R4 L6
      36 [-]: MOVE R6 R1   
      37 [-]: NAMECALL R4 R0 K20 [0x66472BF5]
      38 [-]: CALL R4 2 0  
      39 [-]: LOADN R7 1   
      40 [-]: SUB R6 R7 R1 
      41 [-]: NAMECALL R4 R0 K21 [0x2D9BA74F]
      42 [-]: CALL R4 2 0  
      43 [-]: GETIMPORT R5 17 [nil]
      44 [-]: CALL R5 0 1  
      45 [-]: MULK R4 R5 K22 [3]
      46 [-]: ADD R1 R1 R4 
      47 [-]: GETIMPORT R4 19 [nil]
      48 [-]: LOADN R5 0   
      49 [-]: CALL R4 1 0  
      50 [-]: JUMPBACK L5  
L 6:  51 [-]: GETUPVAL R5 0
      52 [-]: FASTCALL1 62 R5 L7
      53 [-]: GETIMPORT R4 13 [nil]
      54 [-]: CALL R4 1 1  
L 7:  55 [-]: JUMPIF R4 L8 
      56 [-]: GETIMPORT R4 24 [nil]
      57 [-]: GETUPVAL R6 0
      58 [-]: NAMECALL R4 R4 K25 [0x59C96E77]
      59 [-]: CALL R4 2 0  
L 8:  60 [-]: RETURN R0 0  


; Name:            
; Defined at line: 381
; #Upvalues:       3
; #Parameters:     0
; Is_vararg:       0
; Max Stack Size:  8

       0 [-]: GETIMPORT R1 1 [nil]
       1 [-]: FASTCALL1 62 R1 L0
       2 [-]: GETIMPORT R0 3 [nil]
       3 [-]: CALL R0 1 1  
L 0:   4 [-]: JUMPIF R0 L3 
       5 [-]: GETIMPORT R0 1 [nil]
       6 [-]: NAMECALL R0 R0 K4 [0x33307F92]
       7 [-]: CALL R0 1 1  
       8 [-]: FASTCALL1 62 R0 L1
       9 [-]: MOVE R2 R0   
      10 [-]: GETIMPORT R1 3 [nil]
      11 [-]: CALL R1 1 1  
L 1:  12 [-]: JUMPIF R1 L2 
      13 [-]: GETIMPORT R1 6 [nil]
      14 [-]: LOADK R2 K7 ["ScopeDebug: Show from OrokinLock"]
      15 [-]: CALL R1 1 0  
      16 [-]: LOADK R3 K8 ["ShowReticle"]
      17 [-]: LOADK R4 K9 [""]
      18 [-]: NAMECALL R1 R0 K10 [0xE4162EED]
      19 [-]: CALL R1 3 0  
      20 [-]: LOADK R3 K11 ["ShowAbilityDots"]
      21 [-]: LOADK R4 K9 [""]
      22 [-]: NAMECALL R1 R0 K10 [0xE4162EED]
      23 [-]: CALL R1 3 0  
L 2:  24 [-]: GETIMPORT R1 1 [nil]
      25 [-]: LOADB R3 0   
      26 [-]: NAMECALL R1 R1 K12 [0xC02F2CB8]
      27 [-]: CALL R1 2 0  
L 3:  28 [-]: GETIMPORT R0 14 [nil]
      29 [-]: NAMECALL R0 R0 K15 [0x78298275]
      30 [-]: CALL R0 1 1  
      31 [-]: GETIMPORT R3 17 [nil]
      32 [-]: LOADK R4 K18 ["/Lotus/Interface/Cipher.lua"]
      33 [-]: CALL R3 1 1  
      34 [-]: GETIMPORT R4 20 [nil]
      35 [-]: LOADK R5 K21 ["WaitForHackingAnimDone"]
      36 [-]: CALL R4 1 1  
      37 [-]: LOADB R5 1   
      38 [-]: NAMECALL R1 R0 K22 [0x2494B830]
      39 [-]: CALL R1 4 0  
      40 [-]: GETIMPORT R2 14 [nil]
      41 [-]: FASTCALL1 62 R2 L4
      42 [-]: GETIMPORT R1 3 [nil]
      43 [-]: CALL R1 1 1  
L 4:  44 [-]: JUMPIF R1 L8 
      45 [-]: GETIMPORT R1 14 [nil]
      46 [-]: NAMECALL R1 R1 K15 [0x78298275]
      47 [-]: CALL R1 1 1  
      48 [-]: FASTCALL1 62 R1 L5
      49 [-]: MOVE R3 R1   
      50 [-]: GETIMPORT R2 3 [nil]
      51 [-]: CALL R2 1 1  
L 5:  52 [-]: JUMPIF R2 L8 
      53 [-]: LOADB R4 0   
      54 [-]: NAMECALL R2 R1 K23 [0x044B7BE8]
      55 [-]: CALL R2 2 0  
      56 [-]: LOADB R4 1   
      57 [-]: NAMECALL R2 R1 K24 [0x768274D6]
      58 [-]: CALL R2 2 0  
      59 [-]: NAMECALL R2 R1 K25 [0xDE321E6F]
      60 [-]: CALL R2 1 1  
      61 [-]: FASTCALL1 62 R2 L6
      62 [-]: MOVE R4 R2   
      63 [-]: GETIMPORT R3 3 [nil]
      64 [-]: CALL R3 1 1  
L 6:  65 [-]: JUMPIF R3 L8 
      66 [-]: NAMECALL R3 R2 K26 [0x2676DEEE]
      67 [-]: CALL R3 1 1  
      68 [-]: FASTCALL1 62 R3 L7
      69 [-]: MOVE R5 R3   
      70 [-]: GETIMPORT R4 3 [nil]
      71 [-]: CALL R4 1 1  
L 7:  72 [-]: JUMPIF R4 L8 
      73 [-]: LOADB R6 0   
      74 [-]: NAMECALL R4 R3 K23 [0x044B7BE8]
      75 [-]: CALL R4 2 0  
      76 [-]: LOADB R6 1   
      77 [-]: NAMECALL R4 R3 K24 [0x768274D6]
      78 [-]: CALL R4 2 0  
L 8:  79 [-]: GETUPVAL R2 0
      80 [-]: FASTCALL1 62 R2 L9
      81 [-]: GETIMPORT R1 3 [nil]
      82 [-]: CALL R1 1 1  
L 9:  83 [-]: JUMPIF R1 L10
      84 [-]: GETUPVAL R1 0
      85 [-]: GETIMPORT R3 20 [nil]
      86 [-]: LOADK R4 K27 ["EffectFadeOut"]
      87 [-]: CALL R3 1 1  
      88 [-]: LOADB R4 0   
      89 [-]: NAMECALL R1 R1 K28 [0xD5F7912B]
      90 [-]: CALL R1 3 0  
L10:  91 [-]: GETIMPORT R1 32 [nil]
      92 [-]: SETUPVAL R1 1
      93 [-]: GETUPVAL R2 1
      94 [-]: FASTCALL1 62 R2 L11
      95 [-]: GETIMPORT R1 3 [nil]
      96 [-]: CALL R1 1 1  
L11:  97 [-]: JUMPIF R1 L15
      98 [-]: LOADN R3 1   
      99 [-]: GETUPVAL R4 1
     100 [-]: LENGTH R1 R4 
     101 [-]: LOADN R2 1   
     102 [-]: FORNPREP R1 L15
L12: 103 [-]: GETUPVAL R5 1
     104 [-]: GETTABLE R4 R5 R3
     105 [-]: FASTCALL1 62 R4 L13
     106 [-]: MOVE R6 R4   
     107 [-]: GETIMPORT R5 3 [nil]
     108 [-]: CALL R5 1 1  
L13: 109 [-]: JUMPIF R5 L14
     110 [-]: GETIMPORT R5 14 [nil]
     111 [-]: MOVE R7 R4   
     112 [-]: NAMECALL R5 R5 K33 [0x59C96E77]
     113 [-]: CALL R5 2 0  
L14: 114 [-]: FORNLOOP R1 L12
L15: 115 [-]: GETIMPORT R1 34 [nil]
     116 [-]: NEWTABLE R2 0 0
     117 [-]: SETTABLEKS R2 R1 K31 ["OldEntities"]
     118 [-]: GETUPVAL R1 2
     119 [-]: JUMPIFNOT R1 L18
     120 [-]: GETIMPORT R1 36 [nil]
     121 [-]: NAMECALL R1 R1 K37 [0xCD73323E]
     122 [-]: CALL R1 1 1  
     123 [-]: FASTCALL1 62 R1 L16
     124 [-]: MOVE R3 R1   
     125 [-]: GETIMPORT R2 3 [nil]
     126 [-]: CALL R2 1 1  
L16: 127 [-]: JUMPIF R2 L17
     128 [-]: NAMECALL R2 R1 K38 [0xF4E253B6]
     129 [-]: CALL R2 1 0  
L17: 130 [-]: GETIMPORT R2 39 [nil]
     131 [-]: LOADNIL R3   
     132 [-]: SETTABLEKS R3 R2 K30 ["OrokinLockPuzzle"]
L18: 133 [-]: GETIMPORT R1 42 [nil]
     134 [-]: CALL R1 0 1  
     135 [-]: JUMPIFNOT R1 L22
     136 [-]: GETIMPORT R2 44 [nil]
     137 [-]: FASTCALL1 62 R2 L19
     138 [-]: GETIMPORT R1 3 [nil]
     139 [-]: CALL R1 1 1  
L19: 140 [-]: JUMPIF R1 L20
     141 [-]: GETIMPORT R1 44 [nil]
     142 [-]: CALL R1 0 0  
L20: 143 [-]: GETIMPORT R2 46 [nil]
     144 [-]: FASTCALL1 62 R2 L21
     145 [-]: GETIMPORT R1 3 [nil]
     146 [-]: CALL R1 1 1  
L21: 147 [-]: JUMPIF R1 L22
     148 [-]: GETIMPORT R1 46 [nil]
     149 [-]: CALL R1 0 0  
L22: 150 [-]: RETURN R0 0  


; Name:            
; Defined at line: 447
; #Upvalues:       4
; #Parameters:     1
; Is_vararg:       0
; Max Stack Size:  7

       0 [-]: GETUPVAL R1 0
       1 [-]: JUMPIFNOT R1 L0
       2 [-]: GETUPVAL R1 1
       3 [-]: JUMPIFNOT R1 L0
       4 [-]: GETUPVAL R1 2
       5 [-]: GETIMPORT R2 1 [nil]
       6 [-]: GETUPVAL R3 1
       7 [-]: MOVE R5 R0   
       8 [-]: MOVE R6 R0   
       9 [-]: NAMECALL R3 R3 K2 [0x1A94C9CC]
      10 [-]: CALL R3 3 -1 
      11 [-]: CALL R2 -1 1 
      12 [-]: SETTABLE R2 R1 R0
      13 [-]: RETURN R0 0  
L 0:  14 [-]: GETUPVAL R1 2
      15 [-]: GETIMPORT R2 4 [nil]
      16 [-]: LOADN R3 1   
      17 [-]: GETUPVAL R4 3
      18 [-]: CALL R2 2 1  
      19 [-]: SETTABLE R2 R1 R0
      20 [-]: GETIMPORT R2 7 [nil]
      21 [-]: FASTCALL1 62 R2 L1
      22 [-]: GETIMPORT R1 9 [nil]
      23 [-]: CALL R1 1 1  
L 1:  24 [-]: JUMPIF R1 L4 
      25 [-]: GETIMPORT R2 11 [nil]
      26 [-]: FASTCALL1 62 R2 L2
      27 [-]: GETIMPORT R1 9 [nil]
      28 [-]: CALL R1 1 1  
L 2:  29 [-]: JUMPIF R1 L4 
      30 [-]: GETIMPORT R2 11 [nil]
      31 [-]: GETTABLE R1 R2 R0
      32 [-]: FASTCALL1 62 R1 L3
      33 [-]: MOVE R3 R1   
      34 [-]: GETIMPORT R2 9 [nil]
      35 [-]: CALL R2 1 1  
L 3:  36 [-]: JUMPIF R2 L4 
      37 [-]: GETUPVAL R2 2
      38 [-]: SETTABLE R1 R2 R0
L 4:  39 [-]: RETURN R0 0  


; Name:            
; Defined at line: 462
; #Upvalues:       3
; #Parameters:     0
; Is_vararg:       0
; Max Stack Size:  17

       0 [-]: LOADNIL R0   
       1 [-]: LOADNIL R1   
       2 [-]: GETUPVAL R2 0
       3 [-]: JUMPIFNOT R2 L7
       4 [-]: GETIMPORT R3 1 [nil]
       5 [-]: FASTCALL1 62 R3 L0
       6 [-]: GETIMPORT R2 3 [nil]
       7 [-]: CALL R2 1 1  
L 0:   8 [-]: JUMPIF R2 L7 
       9 [-]: GETIMPORT R2 6 [nil]
      10 [-]: CALL R2 0 1  
      11 [-]: JUMPIF R2 L1 
      12 [-]: GETIMPORT R2 8 [nil]
      13 [-]: CALL R2 0 1  
      14 [-]: JUMPIF R2 L1 
      15 [-]: LOADB R0 1   
      16 [-]: LOADK R1 K9 ["7543413518434276"]
      17 [-]: LOADN R2 1   
      18 [-]: SETUPVAL R2 1
      19 [-]: JUMP L7
     
L 1:  20 [-]: GETIMPORT R2 1 [nil]
      21 [-]: NAMECALL R2 R2 K10 [0x69727E0B]
      22 [-]: CALL R2 1 1  
      23 [-]: GETIMPORT R3 12 [nil]
      24 [-]: LOADK R4 K13 ["GlyphHunt"]
      25 [-]: CALL R3 1 1  
      26 [-]: GETIMPORT R4 15 [nil]
      27 [-]: GETTABLEKS R5 R2 K16 ["mGoals"]
      28 [-]: CALL R4 1 3  
      29 [-]: FORGPREP_NEXT R4 L6
L 2:  30 [-]: GETTABLEKS R9 R8 K17 ["mTag"]
      31 [-]: JUMPIFNOTEQ R9 R3 L5
      32 [-]: LOADN R10 0  
      33 [-]: GETTABLEKS R12 R8 K18 ["mMultiProgress"]
      34 [-]: LENGTH R11 R12
      35 [-]: LOADN R14 1  
      36 [-]: MOVE R12 R11 
      37 [-]: LOADN R13 1  
      38 [-]: FORNPREP R12 L4
L 3:  39 [-]: GETTABLEKS R16 R8 K18 ["mMultiProgress"]
      40 [-]: GETTABLE R15 R16 R14
      41 [-]: ADD R10 R10 R15
      42 [-]: FORNLOOP R12 L3
L 4:  43 [-]: DIV R12 R10 R11
      44 [-]: SETUPVAL R12 1
      45 [-]: GETTABLEKS R12 R8 K19 ["mSuccess"]
      46 [-]: JUMPXEQKN R12 K20 L6 NOT [1]
      47 [-]: LOADB R0 1   
      48 [-]: JUMP L6
     
L 5:  49 [-]: GETUPVAL R10 2
      50 [-]: JUMPIFNOTEQ R9 R10 L6
      51 [-]: GETTABLEKS R10 R8 K19 ["mSuccess"]
      52 [-]: JUMPXEQKN R10 K20 L6 NOT [1]
      53 [-]: GETTABLEKS R1 R8 K21 ["mRewardRegion"]
L 6:  54 [-]: FORGLOOP R4 L2 2
L 7:  55 [-]: GETUPVAL R2 0
      56 [-]: JUMPIFNOT R2 L8
      57 [-]: MOVE R2 R1   
      58 [-]: JUMPIF R2 L8 
      59 [-]: NOT R2 R0    
L 8:  60 [-]: MOVE R3 R2   
      61 [-]: MOVE R4 R1   
      62 [-]: RETURN R3 2  


; Name:            
; Defined at line: 503
; #Upvalues:       14
; #Parameters:     0
; Is_vararg:       0
; Max Stack Size:  18

       0 [-]: GETUPVAL R0 0
       1 [-]: CALL R0 0 2  
       2 [-]: SETUPVAL R1 1
       3 [-]: LOADB R2 1   
       4 [-]: SETUPVAL R2 2
       5 [-]: LOADN R4 1   
       6 [-]: GETUPVAL R2 3
       7 [-]: LOADN R3 1   
       8 [-]: FORNPREP R2 L18
L 0:   9 [-]: GETUPVAL R5 4
      10 [-]: MOVE R6 R4   
      11 [-]: CALL R5 1 0  
      12 [-]: GETUPVAL R5 5
      13 [-]: JUMPIF R5 L1 
      14 [-]: GETUPVAL R6 7
      15 [-]: GETTABLEKS R5 R6 K0 [0x9B497F3E]
      16 [-]: GETUPVAL R6 6
      17 [-]: CALL R5 1 1  
      18 [-]: SETUPVAL R5 6
L 1:  19 [-]: GETUPVAL R5 6
      20 [-]: GETUPVAL R7 8
      21 [-]: GETTABLE R6 R7 R4
      22 [-]: GETUPVAL R8 9
      23 [-]: GETTABLE R7 R8 R4
      24 [-]: GETUPVAL R8 10
      25 [-]: GETUPVAL R9 11
      26 [-]: JUMPIFNOTLT R9 R8 L11
      27 [-]: NEWTABLE R5 0 0
      28 [-]: LOADB R8 0   
      29 [-]: LOADN R11 1  
      30 [-]: GETUPVAL R9 10
      31 [-]: LOADN R10 1  
      32 [-]: FORNPREP R9 L10
L 2:  33 [-]: GETUPVAL R13 6
      34 [-]: GETTABLE R12 R13 R11
      35 [-]: MOVE R13 R8  
      36 [-]: JUMPIF R13 L4
      37 [-]: GETTABLEKS R14 R12 K1 ["Index"]
      38 [-]: JUMPIFEQ R14 R6 L3
      39 [-]: LOADB R13 0 +1
L 3:  40 [-]: LOADB R13 1  
L 4:  41 [-]: MOVE R8 R13  
      42 [-]: JUMPIFNOT R8 L5
      43 [-]: GETUPVAL R13 11
      44 [-]: JUMPIF R13 L6
L 5:  45 [-]: GETUPVAL R14 11
      46 [-]: SUBK R13 R14 K2 [1]
L 6:  47 [-]: LENGTH R14 R5
      48 [-]: JUMPIFNOTLT R14 R13 L8
      49 [-]: FASTCALL2 52 R5 R12 L7
      50 [-]: MOVE R15 R5  
      51 [-]: MOVE R16 R12 
      52 [-]: GETIMPORT R14 5 [nil]
      53 [-]: CALL R14 2 0 
L 7:  54 [-]: JUMP L9
     
L 8:  55 [-]: JUMPIF R8 L10
L 9:  56 [-]: FORNLOOP R9 L2
L10:  57 [-]: GETUPVAL R10 7
      58 [-]: GETTABLEKS R9 R10 K0 [0x9B497F3E]
      59 [-]: MOVE R10 R5  
      60 [-]: CALL R9 1 1  
      61 [-]: MOVE R5 R9   
L11:  62 [-]: LOADN R10 1  
      63 [-]: GETUPVAL R8 11
      64 [-]: LOADN R9 1   
      65 [-]: FORNPREP R8 L16
L12:  66 [-]: GETTABLE R11 R5 R10
      67 [-]: GETTABLEKS R12 R11 K1 ["Index"]
      68 [-]: MOVE R13 R12 
      69 [-]: GETUPVAL R14 5
      70 [-]: JUMPIFNOT R14 L13
      71 [-]: GETUPVAL R14 1
      72 [-]: JUMPIFNOT R14 L13
      73 [-]: MOVE R13 R10 
L13:  74 [-]: DUPTABLE R16 8
      75 [-]: SETTABLEKS R12 R16 K6 ["mIconIndex"]
      76 [-]: JUMPIFEQ R13 R6 L14
      77 [-]: LOADB R17 0 +1
L14:  78 [-]: LOADB R17 1  
L15:  79 [-]: SETTABLEKS R17 R16 K7 ["mTarget"]
      80 [-]: LOADB R17 1  
      81 [-]: NAMECALL R14 R7 K9 [0xBAD4316F]
      82 [-]: CALL R14 3 0 
      83 [-]: FORNLOOP R8 L12
L16:  84 [-]: JUMPIFNOT R0 L17
      85 [-]: GETUPVAL R8 1
      86 [-]: JUMPIF R8 L17
      87 [-]: NAMECALL R8 R7 K10 [0xB9890388]
      88 [-]: CALL R8 1 0  
L17:  89 [-]: FORNLOOP R2 L0
L18:  90 [-]: GETIMPORT R2 14 [nil]
      91 [-]: JUMPXEQKNIL R2 L19 NOT
      92 [-]: GETIMPORT R2 15 [nil]
      93 [-]: GETUPVAL R3 8
      94 [-]: SETTABLEKS R3 R2 K13 ["Solution"]
      95 [-]: GETUPVAL R3 7
      96 [-]: GETTABLEKS R2 R3 K16 [0x102DF724]
      97 [-]: CALL R2 0 0  
L19:  98 [-]: LOADN R4 1   
      99 [-]: GETUPVAL R2 3
     100 [-]: LOADN R3 1   
     101 [-]: FORNPREP R2 L27
L20: 102 [-]: GETUPVAL R6 9
     103 [-]: GETTABLE R5 R6 R4
     104 [-]: LOADNIL R8   
     105 [-]: LOADB R9 0   
     106 [-]: LOADB R10 1  
     107 [-]: NAMECALL R6 R5 K17 [0x71E9AC81]
     108 [-]: CALL R6 4 0  
     109 [-]: LOADNIL R6   
     110 [-]: GETUPVAL R7 5
     111 [-]: JUMPIFNOT R7 L21
     112 [-]: LOADN R6 1   
     113 [-]: GETUPVAL R7 1
     114 [-]: JUMPIFNOT R7 L23
     115 [-]: GETUPVAL R7 8
     116 [-]: GETTABLE R6 R7 R4
     117 [-]: JUMP L23
    
L21: 118 [-]: GETIMPORT R7 19 [nil]
     119 [-]: LOADN R8 1   
     120 [-]: GETUPVAL R9 11
     121 [-]: CALL R7 2 1  
     122 [-]: MOVE R6 R7   
L22: 123 [-]: GETTABLEKS R9 R5 K20 ["mElements"]
     124 [-]: GETTABLE R8 R9 R6
     125 [-]: GETTABLEKS R7 R8 K7 ["mTarget"]
     126 [-]: JUMPIFNOT R7 L23
     127 [-]: GETIMPORT R7 19 [nil]
     128 [-]: LOADN R8 1   
     129 [-]: GETUPVAL R9 11
     130 [-]: CALL R7 2 1  
     131 [-]: MOVE R6 R7   
     132 [-]: JUMPBACK L22 
L23: 133 [-]: MOVE R9 R6   
     134 [-]: NAMECALL R7 R5 K21 [0x0417AD4A]
     135 [-]: CALL R7 2 0  
     136 [-]: GETUPVAL R7 12
     137 [-]: MOVE R8 R4   
     138 [-]: GETUPVAL R10 13
     139 [-]: JUMPIFEQ R4 R10 L24
     140 [-]: LOADB R9 0 +1
L24: 141 [-]: LOADB R9 1   
L25: 142 [-]: CALL R7 2 0  
     143 [-]: GETUPVAL R7 1
     144 [-]: JUMPIFNOT R7 L26
     145 [-]: NAMECALL R7 R5 K10 [0xB9890388]
     146 [-]: CALL R7 1 0  
L26: 147 [-]: FORNLOOP R2 L20
L27: 148 [-]: RETURN R0 0  


; Name:            
; Defined at line: 577
; #Upvalues:       2
; #Parameters:     0
; Is_vararg:       1
; Max Stack Size:  12

            1 [-]: NEWTABLE R0 0 0
       2 [-]: GETVARARGS R1 -1
       3 [-]: SETLIST R0 R1 -1 [1]
       4 [-]: LOADN R3 1   
       5 [-]: LENGTH R1 R0 
       6 [-]: LOADN R2 1   
       7 [-]: FORNPREP R1 L4
L 0:   8 [-]: GETIMPORT R4 1 [nil]
       9 [-]: GETTABLE R5 R0 R3
      10 [-]: CALL R4 1 1  
      11 [-]: JUMPXEQKNIL R4 L3
      12 [-]: GETUPVAL R6 0
      13 [-]: GETTABLE R5 R6 R4
      14 [-]: JUMPXEQKNIL R5 L3
      15 [-]: LOADN R8 1   
      16 [-]: GETUPVAL R6 1
      17 [-]: LOADN R7 1   
      18 [-]: FORNPREP R6 L3
L 1:  19 [-]: GETTABLEKS R11 R5 K2 ["mElements"]
      20 [-]: GETTABLE R10 R11 R8
      21 [-]: GETTABLEKS R9 R10 K3 ["mTarget"]
      22 [-]: JUMPIFNOT R9 L2
      23 [-]: LOADNIL R9   
      24 [-]: SETTABLEKS R9 R5 K4 ["FocusedElement"]
      25 [-]: MOVE R11 R8  
      26 [-]: NAMECALL R9 R5 K5 [0x0417AD4A]
      27 [-]: CALL R9 2 0  
      28 [-]: NAMECALL R9 R5 K6 [0xB9890388]
      29 [-]: CALL R9 1 0  
L 2:  30 [-]: FORNLOOP R6 L1
L 3:  31 [-]: FORNLOOP R1 L0
L 4:  32 [-]: RETURN R0 0  


; Name:            
; Defined at line: 596
; #Upvalues:       1
; #Parameters:     0
; Is_vararg:       1
; Max Stack Size:  2

            1 [-]: GETUPVAL R0 0
       2 [-]: GETVARARGS R1 -1
       3 [-]: CALL R0 -1 0 
       4 [-]: RETURN R0 0  


; Name:            
; Defined at line: 600
; #Upvalues:       4
; #Parameters:     0
; Is_vararg:       0
; Max Stack Size:  7

       0 [-]: NEWTABLE R0 0 0
       1 [-]: LOADN R3 1   
       2 [-]: GETUPVAL R1 0
       3 [-]: LOADN R2 1   
       4 [-]: FORNPREP R1 L2
L 0:   5 [-]: FASTCALL2 52 R0 R3 L1
       6 [-]: MOVE R5 R0   
       7 [-]: MOVE R6 R3   
       8 [-]: GETIMPORT R4 2 [nil]
       9 [-]: CALL R4 2 0  
L 1:  10 [-]: FORNLOOP R1 L0
L 2:  11 [-]: GETUPVAL R1 1
      12 [-]: FASTCALL1 53 R0 L3
      13 [-]: MOVE R3 R0   
      14 [-]: GETIMPORT R2 4 [nil]
      15 [-]: CALL R2 1 -1 
L 3:  16 [-]: CALL R1 -1 0 
      17 [-]: LOADB R1 1   
      18 [-]: SETUPVAL R1 2
      19 [-]: GETUPVAL R1 3
      20 [-]: CALL R1 0 0  
      21 [-]: RETURN R0 0  


; Name:            
; Defined at line: 610
; #Upvalues:       1
; #Parameters:     0
; Is_vararg:       0
; Max Stack Size:  1

       0 [-]: GETUPVAL R0 0
       1 [-]: CALL R0 0 0  
       2 [-]: RETURN R0 0  


; Name:            
; Defined at line: 614
; #Upvalues:       5
; #Parameters:     2
; Is_vararg:       0
; Max Stack Size:  14

       0 [-]: GETTABLEKS R2 R0 K0 ["mClipName"]
       1 [-]: MODK R4 R1 K1 [2]
       2 [-]: JUMPXEQKN R4 K2 L0 [1]
       3 [-]: LOADB R3 0 +1
L 0:   4 [-]: LOADB R3 1   
L 1:   5 [-]: NEWCLOSURE R4 P0
       6 [-]: MOVE R0 R3   
       7 [-]: MOVE R0 R0   
       8 [-]: MOVE R2 R0   
       9 [-]: MOVE R2 R1   
      10 [-]: MOVE R2 R2   
      11 [-]: MOVE R2 R3   
      12 [-]: MOVE R0 R2   
      13 [-]: GETIMPORT R5 4 [nil]
      14 [-]: GETIMPORT R6 6 [nil]
      15 [-]: MOVE R7 R2   
      16 [-]: LOADN R8 2   
      17 [-]: NEWTABLE R9 0 1
      18 [-]: MOVE R10 R4  
      19 [-]: SETLIST R9 R10 1 [1]
      20 [-]: NEWTABLE R10 0 1
      21 [-]: LOADN R11 1  
      22 [-]: SETLIST R10 R11 1 [1]
      23 [-]: LOADK R11 K7 [0.29999999999999999]
      24 [-]: LOADN R12 0  
      25 [-]: NEWCLOSURE R13 P1
      26 [-]: MOVE R0 R1   
      27 [-]: MOVE R2 R4   
      28 [-]: MOVE R0 R0   
      29 [-]: CALL R5 8 0  
      30 [-]: RETURN R0 0  


; Name:            
; Defined at line: 636
; #Upvalues:       1
; #Parameters:     3
; Is_vararg:       0
; Max Stack Size:  20

       0 [-]: JUMPXEQKNIL R0 L0 NOT
       1 [-]: RETURN R0 0  
L 0:   2 [-]: MODK R4 R2 K0 [2]
       3 [-]: JUMPXEQKN R4 K1 L1 [1]
       4 [-]: LOADB R3 0 +1
L 1:   5 [-]: LOADB R3 1   
L 2:   6 [-]: JUMPIFNOT R3 L3
       7 [-]: LOADK R4 K2 [0.68200000000000005]
       8 [-]: JUMP L4
     
L 3:   9 [-]: LOADK R4 K3 [0.012999999999999999]
L 4:  10 [-]: JUMPIFNOT R3 L5
      11 [-]: LOADK R5 K4 [0.50600000000000001]
      12 [-]: JUMP L6
     
L 5:  13 [-]: LOADK R5 K5 [0.33000000000000002]
L 6:  14 [-]: JUMPIFNOT R3 L7
      15 [-]: LOADK R6 K6 [0.19600000000000001]
      16 [-]: JUMP L8
     
L 7:  17 [-]: LOADK R6 K7 [0.75]
L 8:  18 [-]: JUMPIFNOT R3 L9
      19 [-]: LOADK R7 K3 [0.012999999999999999]
      20 [-]: JUMP L10
    
L 9:  21 [-]: LOADK R7 K2 [0.68200000000000005]
L10:  22 [-]: JUMPIFNOT R3 L11
      23 [-]: LOADK R8 K5 [0.33000000000000002]
      24 [-]: JUMP L12
    
L11:  25 [-]: LOADK R8 K4 [0.50600000000000001]
L12:  26 [-]: JUMPIFNOT R3 L13
      27 [-]: LOADK R9 K7 [0.75]
      28 [-]: JUMP L14
    
L13:  29 [-]: LOADK R9 K6 [0.19600000000000001]
L14:  30 [-]: NEWCLOSURE R10 P0
      31 [-]: MOVE R0 R4   
      32 [-]: MOVE R0 R7   
      33 [-]: MOVE R0 R5   
      34 [-]: MOVE R0 R8   
      35 [-]: MOVE R0 R6   
      36 [-]: MOVE R0 R9   
      37 [-]: MOVE R0 R0   
      38 [-]: GETIMPORT R11 9 [nil]
      39 [-]: GETIMPORT R12 11 [nil]
      40 [-]: LOADK R14 K12 ["SymbolPairPulse"]
      41 [-]: MOVE R15 R1  
      42 [-]: CONCAT R13 R14 R15
      43 [-]: LOADN R14 2  
      44 [-]: NEWTABLE R15 0 1
      45 [-]: MOVE R16 R10 
      46 [-]: SETLIST R15 R16 1 [1]
      47 [-]: NEWTABLE R16 0 1
      48 [-]: LOADN R17 1  
      49 [-]: SETLIST R16 R17 1 [1]
      50 [-]: LOADK R17 K13 [0.29999999999999999]
      51 [-]: LOADN R18 0  
      52 [-]: NEWCLOSURE R19 P1
      53 [-]: MOVE R0 R2   
      54 [-]: MOVE R2 R0   
      55 [-]: MOVE R0 R0   
      56 [-]: MOVE R0 R1   
      57 [-]: CALL R11 8 0 
      58 [-]: RETURN R0 0  


; Name:            
; Defined at line: 672
; #Upvalues:       5
; #Parameters:     3
; Is_vararg:       0
; Max Stack Size:  17

       0 [-]: GETUPVAL R3 0
       1 [-]: JUMPIF R3 L0 
       2 [-]: GETUPVAL R5 1
       3 [-]: GETTABLEKS R4 R5 K0 ["Elements"]
       4 [-]: GETTABLE R3 R4 R2
L 0:   5 [-]: JUMPXEQKNIL R3 L7
       6 [-]: LOADNIL R4   
       7 [-]: GETTABLEKS R6 R3 K1 ["SymbolIds"]
       8 [-]: GETTABLE R5 R6 R0
       9 [-]: JUMPIFNOT R5 L1
      10 [-]: GETTABLEKS R6 R3 K1 ["SymbolIds"]
      11 [-]: GETTABLE R5 R6 R1
      12 [-]: JUMPIF R5 L1 
      13 [-]: LOADB R4 0   
      14 [-]: JUMP L2
     
L 1:  15 [-]: GETTABLEKS R6 R3 K1 ["SymbolIds"]
      16 [-]: GETTABLE R5 R6 R1
      17 [-]: JUMPIFNOT R5 L2
      18 [-]: GETTABLEKS R6 R3 K1 ["SymbolIds"]
      19 [-]: GETTABLE R5 R6 R0
      20 [-]: JUMPIF R5 L2 
      21 [-]: LOADB R4 1   
L 2:  22 [-]: JUMPXEQKNIL R4 L7
      23 [-]: GETUPVAL R5 0
      24 [-]: JUMPXEQKNIL R5 L3 NOT
      25 [-]: SETUPVAL R3 0
      26 [-]: GETIMPORT R5 4 [nil]
      27 [-]: GETUPVAL R7 1
      28 [-]: GETTABLEKS R6 R7 K0 ["Elements"]
      29 [-]: MOVE R7 R2   
      30 [-]: CALL R5 2 0  
      31 [-]: GETUPVAL R7 1
      32 [-]: GETTABLEKS R6 R7 K0 ["Elements"]
      33 [-]: GETUPVAL R7 0
      34 [-]: FASTCALL2 52 R6 R7 L3
      35 [-]: GETIMPORT R5 6 [nil]
      36 [-]: CALL R5 2 0  
L 3:  37 [-]: GETUPVAL R6 0
      38 [-]: GETTABLEKS R5 R6 K1 ["SymbolIds"]
      39 [-]: LOADB R6 1   
      40 [-]: SETTABLE R6 R5 R0
      41 [-]: GETUPVAL R6 0
      42 [-]: GETTABLEKS R5 R6 K1 ["SymbolIds"]
      43 [-]: LOADB R6 1   
      44 [-]: SETTABLE R6 R5 R1
      45 [-]: GETUPVAL R6 0
      46 [-]: GETTABLEKS R5 R6 K7 ["Symbols"]
      47 [-]: JUMPIFNOT R4 L5
      48 [-]: MOVE R7 R5   
      49 [-]: LOADN R8 1   
      50 [-]: GETUPVAL R9 2
      51 [-]: MOVE R10 R0  
      52 [-]: LOADK R12 K8 ["FloatingSymbolInit"]
      53 [-]: MOVE R13 R2  
      54 [-]: LOADK R14 K9 ["Id"]
      55 [-]: LENGTH R16 R5
      56 [-]: ADDK R15 R16 K10 [1]
      57 [-]: CONCAT R11 R12 R15
      58 [-]: LOADB R12 0  
      59 [-]: CALL R9 3 -1 
      60 [-]: FASTCALL 52 L4
      61 [-]: GETIMPORT R6 6 [nil]
      62 [-]: CALL R6 -1 0 
L 4:  63 [-]: JUMP L6
     
L 5:  64 [-]: MOVE R7 R5   
      65 [-]: GETUPVAL R8 2
      66 [-]: MOVE R9 R1   
      67 [-]: LOADK R11 K8 ["FloatingSymbolInit"]
      68 [-]: MOVE R12 R2  
      69 [-]: LOADK R13 K9 ["Id"]
      70 [-]: LENGTH R15 R5
      71 [-]: ADDK R14 R15 K10 [1]
      72 [-]: CONCAT R10 R11 R14
      73 [-]: LOADB R11 0  
      74 [-]: CALL R8 3 -1 
      75 [-]: FASTCALL 52 L6
      76 [-]: GETIMPORT R6 6 [nil]
      77 [-]: CALL R6 -1 0 
L 6:  78 [-]: GETUPVAL R6 3
      79 [-]: JUMPIF R6 L7 
      80 [-]: GETUPVAL R7 4
      81 [-]: GETTABLEKS R6 R7 K11 [0x659D451F]
      82 [-]: GETIMPORT R7 13 [nil]
      83 [-]: CALL R6 1 0  
L 7:  84 [-]: RETURN R0 0  


; Name:            
; Defined at line: 703
; #Upvalues:       7
; #Parameters:     1
; Is_vararg:       0
; Max Stack Size:  21

       0 [-]: GETUPVAL R2 0
       1 [-]: GETTABLE R1 R2 R0
       2 [-]: GETTABLEKS R2 R1 K0 ["FocusedElement"]
       3 [-]: JUMPXEQKNIL R2 L0 NOT
       4 [-]: RETURN R0 0  
L 0:   5 [-]: GETIMPORT R3 4 [nil]
       6 [-]: JUMPIF R3 L1 
       7 [-]: GETIMPORT R3 6 [nil]
L 1:   8 [-]: NEWCLOSURE R4 P0
       9 [-]: MOVE R0 R3   
      10 [-]: MOVE R2 R1   
      11 [-]: LOADN R7 1   
      12 [-]: LENGTH R5 R3 
      13 [-]: LOADN R6 1   
      14 [-]: FORNPREP R5 L18
L 2:  15 [-]: LOADNIL R8   
      16 [-]: GETTABLE R9 R3 R7
      17 [-]: LOADB R10 0  
      18 [-]: GETTABLEKS R11 R9 K7 ["first"]
      19 [-]: GETTABLEKS R12 R2 K8 ["mIconIndex"]
      20 [-]: JUMPIFNOTEQ R11 R12 L5
      21 [-]: GETUPVAL R11 0
      22 [-]: ADDK R12 R0 K9 [1]
      23 [-]: GETTABLE R8 R11 R12
      24 [-]: JUMPXEQKNIL R8 L8
      25 [-]: LOADB R11 0  
      26 [-]: GETTABLEKS R12 R8 K0 ["FocusedElement"]
      27 [-]: JUMPXEQKNIL R12 L4
      28 [-]: GETTABLEKS R13 R8 K0 ["FocusedElement"]
      29 [-]: GETTABLEKS R12 R13 K8 ["mIconIndex"]
      30 [-]: GETTABLEKS R13 R9 K10 ["second"]
      31 [-]: JUMPIFEQ R12 R13 L3
      32 [-]: LOADB R11 0 +1
L 3:  33 [-]: LOADB R11 1  
L 4:  34 [-]: MOVE R10 R11 
      35 [-]: JUMP L8
     
L 5:  36 [-]: GETTABLEKS R11 R9 K10 ["second"]
      37 [-]: GETTABLEKS R12 R2 K8 ["mIconIndex"]
      38 [-]: JUMPIFNOTEQ R11 R12 L8
      39 [-]: GETUPVAL R11 0
      40 [-]: SUBK R12 R0 K9 [1]
      41 [-]: GETTABLE R8 R11 R12
      42 [-]: JUMPXEQKNIL R8 L8
      43 [-]: LOADB R11 0  
      44 [-]: GETTABLEKS R12 R8 K0 ["FocusedElement"]
      45 [-]: JUMPXEQKNIL R12 L7
      46 [-]: GETTABLEKS R13 R8 K0 ["FocusedElement"]
      47 [-]: GETTABLEKS R12 R13 K8 ["mIconIndex"]
      48 [-]: GETTABLEKS R13 R9 K7 ["first"]
      49 [-]: JUMPIFEQ R12 R13 L6
      50 [-]: LOADB R11 0 +1
L 6:  51 [-]: LOADB R11 1  
L 7:  52 [-]: MOVE R10 R11 
L 8:  53 [-]: JUMPIFNOT R10 L17
      54 [-]: GETUPVAL R11 2
      55 [-]: JUMPXEQKNIL R11 L9
      56 [-]: MOVE R11 R4  
      57 [-]: GETTABLEKS R12 R9 K7 ["first"]
      58 [-]: GETTABLEKS R13 R9 K10 ["second"]
      59 [-]: MOVE R14 R7  
      60 [-]: CALL R11 3 0 
L 9:  61 [-]: SUBK R13 R0 K9 [1]
      62 [-]: LOADN R11 1  
      63 [-]: LOADN R12 -1 
      64 [-]: FORNPREP R11 L11
L10:  65 [-]: GETUPVAL R15 0
      66 [-]: GETTABLE R14 R15 R13
      67 [-]: GETUPVAL R16 0
      68 [-]: ADDK R17 R13 K9 [1]
      69 [-]: GETTABLE R15 R16 R17
      70 [-]: JUMPIFNOT R14 L11
      71 [-]: GETTABLEKS R16 R14 K0 ["FocusedElement"]
      72 [-]: JUMPIFNOT R16 L11
      73 [-]: GETTABLEKS R17 R14 K0 ["FocusedElement"]
      74 [-]: GETTABLEKS R16 R17 K8 ["mIconIndex"]
      75 [-]: JUMPIFNOT R16 L11
      76 [-]: JUMPIFNOT R15 L11
      77 [-]: GETTABLEKS R16 R15 K0 ["FocusedElement"]
      78 [-]: JUMPIFNOT R16 L11
      79 [-]: GETTABLEKS R17 R15 K0 ["FocusedElement"]
      80 [-]: GETTABLEKS R16 R17 K8 ["mIconIndex"]
      81 [-]: JUMPIFNOT R16 L11
      82 [-]: MOVE R16 R4  
      83 [-]: GETTABLEKS R18 R14 K0 ["FocusedElement"]
      84 [-]: GETTABLEKS R17 R18 K8 ["mIconIndex"]
      85 [-]: GETTABLEKS R19 R15 K0 ["FocusedElement"]
      86 [-]: GETTABLEKS R18 R19 K8 ["mIconIndex"]
      87 [-]: MOVE R19 R7  
      88 [-]: CALL R16 3 1 
      89 [-]: JUMPIFNOT R16 L11
      90 [-]: FORNLOOP R11 L10
L11:  91 [-]: ADDK R13 R0 K9 [1]
      92 [-]: GETUPVAL R11 3
      93 [-]: LOADN R12 1  
      94 [-]: FORNPREP R11 L13
L12:  95 [-]: GETUPVAL R15 0
      96 [-]: SUBK R16 R13 K9 [1]
      97 [-]: GETTABLE R14 R15 R16
      98 [-]: GETUPVAL R16 0
      99 [-]: GETTABLE R15 R16 R13
     100 [-]: JUMPIFNOT R14 L13
     101 [-]: GETTABLEKS R16 R14 K0 ["FocusedElement"]
     102 [-]: JUMPIFNOT R16 L13
     103 [-]: GETTABLEKS R17 R14 K0 ["FocusedElement"]
     104 [-]: GETTABLEKS R16 R17 K8 ["mIconIndex"]
     105 [-]: JUMPIFNOT R16 L13
     106 [-]: JUMPIFNOT R15 L13
     107 [-]: GETTABLEKS R16 R15 K0 ["FocusedElement"]
     108 [-]: JUMPIFNOT R16 L13
     109 [-]: GETTABLEKS R17 R15 K0 ["FocusedElement"]
     110 [-]: GETTABLEKS R16 R17 K8 ["mIconIndex"]
     111 [-]: JUMPIFNOT R16 L13
     112 [-]: MOVE R16 R4  
     113 [-]: GETTABLEKS R18 R14 K0 ["FocusedElement"]
     114 [-]: GETTABLEKS R17 R18 K8 ["mIconIndex"]
     115 [-]: GETTABLEKS R19 R15 K0 ["FocusedElement"]
     116 [-]: GETTABLEKS R18 R19 K8 ["mIconIndex"]
     117 [-]: MOVE R19 R7  
     118 [-]: CALL R16 3 1 
     119 [-]: JUMPIFNOT R16 L13
     120 [-]: FORNLOOP R11 L12
L13: 121 [-]: LOADNIL R11  
     122 [-]: GETUPVAL R16 4
     123 [-]: GETTABLEKS R15 R16 K11 ["Elements"]
     124 [-]: LENGTH R14 R15
     125 [-]: LOADN R12 1  
     126 [-]: LOADN R13 -1 
     127 [-]: FORNPREP R12 L16
L14: 128 [-]: GETUPVAL R18 4
     129 [-]: GETTABLEKS R17 R18 K11 ["Elements"]
     130 [-]: GETTABLE R16 R17 R14
     131 [-]: GETTABLEKS R15 R16 K12 ["SymbolIds"]
     132 [-]: GETTABLEKS R17 R9 K7 ["first"]
     133 [-]: GETTABLE R16 R15 R17
     134 [-]: JUMPIFNOT R16 L15
     135 [-]: GETTABLEKS R17 R9 K10 ["second"]
     136 [-]: GETTABLE R16 R15 R17
     137 [-]: JUMPIFNOT R16 L15
     138 [-]: GETUPVAL R17 4
     139 [-]: GETTABLEKS R16 R17 K11 ["Elements"]
     140 [-]: GETTABLE R11 R16 R14
     141 [-]: JUMP L16
    
L15: 142 [-]: FORNLOOP R12 L14
L16: 143 [-]: JUMPXEQKNIL R11 L17
     144 [-]: GETUPVAL R12 5
     145 [-]: GETTABLEKS R13 R11 K13 ["Symbols"]
     146 [-]: MOVE R14 R7  
     147 [-]: LOADN R15 1  
     148 [-]: CALL R12 3 0 
     149 [-]: GETUPVAL R12 6
     150 [-]: GETTABLEKS R13 R1 K0 ["FocusedElement"]
     151 [-]: LOADN R14 1  
     152 [-]: CALL R12 2 0 
     153 [-]: GETUPVAL R12 6
     154 [-]: GETTABLEKS R13 R8 K0 ["FocusedElement"]
     155 [-]: LOADN R14 1  
     156 [-]: CALL R12 2 0 
L17: 157 [-]: FORNLOOP R5 L2
L18: 158 [-]: GETUPVAL R9 4
     159 [-]: GETTABLEKS R8 R9 K11 ["Elements"]
     160 [-]: LENGTH R7 R8 
     161 [-]: LOADN R5 1   
     162 [-]: LOADN R6 -1  
     163 [-]: FORNPREP R5 L27
L19: 164 [-]: GETUPVAL R10 4
     165 [-]: GETTABLEKS R9 R10 K11 ["Elements"]
     166 [-]: GETTABLE R8 R9 R7
     167 [-]: JUMPXEQKNIL R8 L26
     168 [-]: GETUPVAL R9 2
     169 [-]: JUMPXEQKNIL R9 L26
     170 [-]: GETUPVAL R9 2
     171 [-]: JUMPIFEQ R8 R9 L26
     172 [-]: LOADB R9 1   
     173 [-]: GETIMPORT R10 15 [nil]
     174 [-]: GETTABLEKS R11 R8 K12 ["SymbolIds"]
     175 [-]: CALL R10 1 3 
     176 [-]: FORGPREP_NEXT R10 L24
L20: 177 [-]: LOADB R15 0  
     178 [-]: GETIMPORT R16 15 [nil]
     179 [-]: GETUPVAL R19 2
     180 [-]: GETTABLEKS R17 R19 K12 ["SymbolIds"]
     181 [-]: CALL R16 1 3 
     182 [-]: FORGPREP_NEXT R16 L22
L21: 183 [-]: JUMPIFNOTEQ R13 R19 L22
     184 [-]: LOADB R15 1  
     185 [-]: JUMP L23
    
L22: 186 [-]: FORGLOOP R16 L21 2
L23: 187 [-]: JUMPIF R15 L24
     188 [-]: LOADB R9 0   
     189 [-]: JUMP L25
    
L24: 190 [-]: FORGLOOP R10 L20 2
L25: 191 [-]: JUMPIFNOT R9 L26
     192 [-]: NAMECALL R10 R8 K16 [0xA2880940]
     193 [-]: CALL R10 1 0 
     194 [-]: GETIMPORT R10 19 [nil]
     195 [-]: GETUPVAL R12 4
     196 [-]: GETTABLEKS R11 R12 K11 ["Elements"]
     197 [-]: MOVE R12 R7  
     198 [-]: CALL R10 2 0 
L26: 199 [-]: FORNLOOP R5 L19
L27: 200 [-]: RETURN R0 0  


; Name:            
; Defined at line: 823
; #Upvalues:       2
; #Parameters:     1
; Is_vararg:       0
; Max Stack Size:  2

       0 [-]: JUMPIFNOT R0 L0
       1 [-]: LOADB R1 1   
       2 [-]: SETUPVAL R1 0
       3 [-]: GETUPVAL R1 1
       4 [-]: CALL R1 0 0  
L 0:   5 [-]: RETURN R0 0  


; Name:            
; Defined at line: 830
; #Upvalues:       7
; #Parameters:     0
; Is_vararg:       0
; Max Stack Size:  13

       0 [-]: GETUPVAL R0 0
       1 [-]: JUMPIF R0 L8 
       2 [-]: GETIMPORT R1 3 [nil]
       3 [-]: JUMPIF R1 L0 
       4 [-]: GETIMPORT R1 5 [nil]
L 0:   5 [-]: LENGTH R0 R1 
       6 [-]: GETIMPORT R2 5 [nil]
       7 [-]: LENGTH R1 R2 
       8 [-]: FASTCALL1 62 R0 L1
       9 [-]: MOVE R3 R0   
      10 [-]: GETIMPORT R2 7 [nil]
      11 [-]: CALL R2 1 1  
L 1:  12 [-]: JUMPIF R2 L3 
      13 [-]: FASTCALL1 62 R1 L2
      14 [-]: MOVE R3 R1   
      15 [-]: GETIMPORT R2 7 [nil]
      16 [-]: CALL R2 1 1  
L 2:  17 [-]: JUMPIF R2 L3 
      18 [-]: JUMPIFNOTLT R0 R1 L4
L 3:  19 [-]: RETURN R0 0  
L 4:  20 [-]: LOADN R4 1   
      21 [-]: GETUPVAL R2 1
      22 [-]: LOADN R3 1   
      23 [-]: FORNPREP R2 L7
L 5:  24 [-]: GETUPVAL R7 2
      25 [-]: GETTABLE R6 R7 R4
      26 [-]: GETTABLEKS R5 R6 K8 ["Correct"]
      27 [-]: JUMPIF R5 L6 
      28 [-]: RETURN R0 0  
L 6:  29 [-]: FORNLOOP R2 L5
L 7:  30 [-]: LOADB R2 1   
      31 [-]: SETUPVAL R2 3
      32 [-]: GETUPVAL R2 4
      33 [-]: CALL R2 0 0  
      34 [-]: RETURN R0 0  
L 8:  35 [-]: GETUPVAL R0 5
      36 [-]: JUMPIFNOT R0 L9
      37 [-]: RETURN R0 0  
L 9:  38 [-]: LOADK R0 K9 [""]
      39 [-]: LOADN R3 1   
      40 [-]: GETUPVAL R1 1
      41 [-]: LOADN R2 1   
      42 [-]: FORNPREP R1 L11
L10:  43 [-]: MOVE R4 R0   
      44 [-]: GETUPVAL R8 2
      45 [-]: GETTABLE R7 R8 R3
      46 [-]: GETTABLEKS R6 R7 K10 ["FocusedElement"]
      47 [-]: GETTABLEKS R5 R6 K11 ["Id"]
      48 [-]: CONCAT R0 R4 R5
      49 [-]: FORNLOOP R1 L10
L11:  50 [-]: GETIMPORT R1 13 [nil]
      51 [-]: MOVE R2 R0   
      52 [-]: CALL R1 1 1  
      53 [-]: JUMPXEQKN R1 K14 L15 NOT [2726351360]
      54 [-]: GETIMPORT R2 16 [nil]
      55 [-]: FASTCALL1 62 R2 L12
      56 [-]: GETIMPORT R1 7 [nil]
      57 [-]: CALL R1 1 1  
L12:  58 [-]: JUMPIF R1 L15
      59 [-]: GETIMPORT R1 16 [nil]
      60 [-]: NAMECALL R1 R1 K17 [0x69727E0B]
      61 [-]: CALL R1 1 1  
      62 [-]: GETTABLEKS R2 R1 K18 ["mGoals"]
      63 [-]: LOADN R5 1   
      64 [-]: LENGTH R3 R2 
      65 [-]: LOADN R4 1   
      66 [-]: FORNPREP R3 L15
L13:  67 [-]: GETTABLE R6 R2 R5
      68 [-]: GETTABLEKS R7 R6 K19 ["mTag"]
      69 [-]: GETUPVAL R8 6
      70 [-]: JUMPIFNOTEQ R7 R8 L14
      71 [-]: GETIMPORT R7 21 [nil]
      72 [-]: CALL R7 0 1  
      73 [-]: GETTABLEKS R10 R6 K22 ["mId"]
      74 [-]: NAMECALL R10 R10 K23 [0xF537CFC7]
      75 [-]: CALL R10 1 -1
      76 [-]: NAMECALL R8 R7 K24 [0x46E9D221]
      77 [-]: CALL R8 -1 0 
      78 [-]: GETIMPORT R8 16 [nil]
      79 [-]: MOVE R10 R7  
      80 [-]: MOVE R11 R0  
      81 [-]: LOADK R12 K25 ["OnGoalUnlock"]
      82 [-]: NAMECALL R8 R8 K26 [0x085BDC70]
      83 [-]: CALL R8 4 0  
L14:  84 [-]: FORNLOOP R3 L13
L15:  85 [-]: RETURN R0 0  


; Name:            
; Defined at line: 875
; #Upvalues:       1
; #Parameters:     4
; Is_vararg:       0
; Max Stack Size:  11

       0 [-]: LOADNIL R4   
       1 [-]: MOVE R7 R0   
       2 [-]: GETIMPORT R8 1 [nil]
       3 [-]: MOVE R9 R2   
       4 [-]: MOVE R10 R3  
       5 [-]: NAMECALL R5 R1 K2 [0x47901F07]
       6 [-]: CALL R5 5 1  
       7 [-]: MOVE R4 R5   
       8 [-]: GETUPVAL R6 0
       9 [-]: FASTCALL2 52 R6 R4 L0
      10 [-]: MOVE R7 R4   
      11 [-]: GETIMPORT R5 5 [nil]
      12 [-]: CALL R5 2 0  
L 0:  13 [-]: RETURN R4 1  


; Name:            
; Defined at line: 882
; #Upvalues:       9
; #Parameters:     0
; Is_vararg:       0
; Max Stack Size:  20

       0 [-]: GETIMPORT R0 1 [nil]
       1 [-]: NAMECALL R0 R0 K2 [0xA1653871]
       2 [-]: CALL R0 1 1  
       3 [-]: GETIMPORT R1 1 [nil]
       4 [-]: NAMECALL R1 R1 K3 [0xA51F7C05]
       5 [-]: CALL R1 1 1  
       6 [-]: GETIMPORT R2 1 [nil]
       7 [-]: NAMECALL R2 R2 K4 [0x87E5BE20]
       8 [-]: CALL R2 1 1  
       9 [-]: GETIMPORT R3 6 [nil]
      10 [-]: GETIMPORT R4 1 [nil]
      11 [-]: NAMECALL R4 R4 K7 [0xE0BCE76E]
      12 [-]: CALL R4 1 1  
      13 [-]: MOVE R5 R2   
      14 [-]: CALL R3 2 1  
      15 [-]: GETTABLEKS R5 R3 K8 ["x"]
      16 [-]: GETTABLEKS R6 R1 K8 ["x"]
      17 [-]: MUL R4 R5 R6 
      18 [-]: SETTABLEKS R4 R3 K8 ["x"]
      19 [-]: GETTABLEKS R5 R3 K9 ["y"]
      20 [-]: GETTABLEKS R6 R1 K9 ["y"]
      21 [-]: MUL R4 R5 R6 
      22 [-]: SETTABLEKS R4 R3 K9 ["y"]
      23 [-]: GETTABLEKS R5 R3 K10 ["z"]
      24 [-]: GETTABLEKS R6 R1 K10 ["z"]
      25 [-]: MUL R4 R5 R6 
      26 [-]: SETTABLEKS R4 R3 K10 ["z"]
      27 [-]: GETIMPORT R4 12 [nil]
      28 [-]: MOVE R5 R2   
      29 [-]: CALL R4 1 1  
      30 [-]: GETTABLEKS R6 R3 K8 ["x"]
      31 [-]: GETTABLEKS R9 R4 K8 ["x"]
      32 [-]: MULK R8 R9 K13 [0.1111111111111111]
      33 [-]: GETTABLEKS R9 R1 K8 ["x"]
      34 [-]: MUL R7 R8 R9 
      35 [-]: ADD R5 R6 R7 
      36 [-]: SETTABLEKS R5 R3 K8 ["x"]
      37 [-]: GETTABLEKS R6 R3 K9 ["y"]
      38 [-]: GETTABLEKS R9 R4 K9 ["y"]
      39 [-]: MULK R8 R9 K13 [0.1111111111111111]
      40 [-]: GETTABLEKS R9 R1 K9 ["y"]
      41 [-]: MUL R7 R8 R9 
      42 [-]: ADD R5 R6 R7 
      43 [-]: SETTABLEKS R5 R3 K9 ["y"]
      44 [-]: GETTABLEKS R6 R3 K10 ["z"]
      45 [-]: GETTABLEKS R9 R4 K10 ["z"]
      46 [-]: MULK R8 R9 K13 [0.1111111111111111]
      47 [-]: GETTABLEKS R9 R1 K10 ["z"]
      48 [-]: MUL R7 R8 R9 
      49 [-]: ADD R5 R6 R7 
      50 [-]: SETTABLEKS R5 R3 K10 ["z"]
      51 [-]: GETIMPORT R5 12 [nil]
      52 [-]: GETIMPORT R6 15 [nil]
      53 [-]: GETTABLEKS R8 R2 K17 ["heading"]
      54 [-]: ADDK R7 R8 K16 [90]
      55 [-]: GETTABLEKS R8 R2 K18 ["pitch"]
      56 [-]: GETTABLEKS R9 R2 K19 ["bank"]
      57 [-]: CALL R6 3 -1 
      58 [-]: CALL R5 -1 1 
      59 [-]: LOADK R8 K21 [0.12]
      60 [-]: GETUPVAL R10 0
      61 [-]: SUBK R9 R10 K22 [1]
      62 [-]: MUL R7 R8 R9 
      63 [-]: DIVK R6 R7 K20 [2]
      64 [-]: GETTABLEKS R8 R3 K8 ["x"]
      65 [-]: GETTABLEKS R11 R5 K8 ["x"]
      66 [-]: MUL R10 R11 R6
      67 [-]: GETTABLEKS R11 R1 K8 ["x"]
      68 [-]: MUL R9 R10 R11
      69 [-]: SUB R7 R8 R9 
      70 [-]: SETTABLEKS R7 R3 K8 ["x"]
      71 [-]: GETTABLEKS R8 R3 K9 ["y"]
      72 [-]: GETTABLEKS R11 R5 K9 ["y"]
      73 [-]: MUL R10 R11 R6
      74 [-]: GETTABLEKS R11 R1 K9 ["y"]
      75 [-]: MUL R9 R10 R11
      76 [-]: SUB R7 R8 R9 
      77 [-]: SETTABLEKS R7 R3 K9 ["y"]
      78 [-]: GETTABLEKS R8 R3 K10 ["z"]
      79 [-]: GETTABLEKS R11 R5 K10 ["z"]
      80 [-]: MUL R10 R11 R6
      81 [-]: GETTABLEKS R11 R1 K10 ["z"]
      82 [-]: MUL R9 R10 R11
      83 [-]: SUB R7 R8 R9 
      84 [-]: SETTABLEKS R7 R3 K10 ["z"]
      85 [-]: GETUPVAL R7 1
      86 [-]: JUMPIFNOT R7 L0
      87 [-]: GETUPVAL R7 3
      88 [-]: GETIMPORT R8 24 [nil]
      89 [-]: MOVE R9 R0   
      90 [-]: GETIMPORT R10 26 [nil]
      91 [-]: LOADN R11 0  
      92 [-]: LOADN R12 1  
      93 [-]: LOADN R13 -2 
      94 [-]: CALL R10 3 1 
      95 [-]: GETIMPORT R11 15 [nil]
      96 [-]: CALL R11 0 -1
      97 [-]: CALL R7 -1 1 
      98 [-]: SETUPVAL R7 2
      99 [-]: JUMP L1
     
L 0: 100 [-]: GETUPVAL R7 3
     101 [-]: GETIMPORT R8 24 [nil]
     102 [-]: MOVE R9 R0   
     103 [-]: GETIMPORT R10 26 [nil]
     104 [-]: LOADN R11 0  
     105 [-]: LOADN R12 1  
     106 [-]: LOADN R13 2  
     107 [-]: CALL R10 3 1 
     108 [-]: GETIMPORT R11 15 [nil]
     109 [-]: CALL R11 0 -1
     110 [-]: CALL R7 -1 1 
     111 [-]: SETUPVAL R7 2
L 1: 112 [-]: GETTABLEKS R8 R2 K19 ["bank"]
     113 [-]: ADDK R7 R8 K16 [90]
     114 [-]: SETTABLEKS R7 R2 K19 ["bank"]
     115 [-]: GETIMPORT R7 26 [nil]
     116 [-]: GETTABLEKS R8 R3 K8 ["x"]
     117 [-]: GETTABLEKS R9 R3 K9 ["y"]
     118 [-]: GETTABLEKS R10 R3 K10 ["z"]
     119 [-]: CALL R7 3 1  
     120 [-]: LOADN R10 1  
     121 [-]: GETUPVAL R8 0
     122 [-]: LOADN R9 1   
     123 [-]: FORNPREP R8 L3
L 2: 124 [-]: SUBK R12 R10 K22 [1]
     125 [-]: MULK R11 R12 K21 [0.12]
     126 [-]: GETTABLEKS R13 R7 K8 ["x"]
     127 [-]: GETTABLEKS R16 R5 K8 ["x"]
     128 [-]: MUL R15 R11 R16
     129 [-]: GETTABLEKS R16 R1 K8 ["x"]
     130 [-]: MUL R14 R15 R16
     131 [-]: ADD R12 R13 R14
     132 [-]: SETTABLEKS R12 R3 K8 ["x"]
     133 [-]: GETTABLEKS R13 R7 K9 ["y"]
     134 [-]: GETTABLEKS R16 R5 K9 ["y"]
     135 [-]: MUL R15 R11 R16
     136 [-]: GETTABLEKS R16 R1 K9 ["y"]
     137 [-]: MUL R14 R15 R16
     138 [-]: ADD R12 R13 R14
     139 [-]: SETTABLEKS R12 R3 K9 ["y"]
     140 [-]: GETTABLEKS R13 R7 K10 ["z"]
     141 [-]: GETTABLEKS R16 R5 K10 ["z"]
     142 [-]: MUL R15 R11 R16
     143 [-]: GETTABLEKS R16 R1 K10 ["z"]
     144 [-]: MUL R14 R15 R16
     145 [-]: ADD R12 R13 R14
     146 [-]: SETTABLEKS R12 R3 K10 ["z"]
     147 [-]: GETUPVAL R13 4
     148 [-]: GETTABLE R12 R13 R10
     149 [-]: GETUPVAL R13 3
     150 [-]: GETGLOBAL R14 K27 [0x90A24D27]
     151 [-]: MOVE R15 R0  
     152 [-]: MOVE R16 R3  
     153 [-]: MOVE R17 R2  
     154 [-]: CALL R13 4 1 
     155 [-]: SETTABLEKS R13 R12 K28 ["RingEntity"]
     156 [-]: GETUPVAL R13 3
     157 [-]: GETGLOBAL R14 K29 [0x6B0C7C2B]
     158 [-]: MOVE R15 R0  
     159 [-]: MOVE R16 R3  
     160 [-]: MOVE R17 R2  
     161 [-]: CALL R13 4 1 
     162 [-]: SETTABLEKS R13 R12 K30 ["RingFrontEntity"]
     163 [-]: GETUPVAL R13 5
     164 [-]: GETTABLEKS R14 R12 K28 ["RingEntity"]
     165 [-]: GETUPVAL R15 6
     166 [-]: LOADB R16 0  
     167 [-]: LOADB R17 0  
     168 [-]: LOADN R18 0  
     169 [-]: LOADB R19 1  
     170 [-]: CALL R15 4 1 
     171 [-]: LOADK R16 K31 [0.22222222222222221]
     172 [-]: LOADK R17 K32 [0.059999999999999998]
     173 [-]: CALL R13 4 0 
     174 [-]: GETUPVAL R13 5
     175 [-]: GETTABLEKS R14 R12 K30 ["RingFrontEntity"]
     176 [-]: GETUPVAL R15 6
     177 [-]: LOADB R16 0  
     178 [-]: LOADB R17 0  
     179 [-]: LOADN R18 0  
     180 [-]: CALL R15 3 1 
     181 [-]: LOADK R16 K31 [0.22222222222222221]
     182 [-]: LOADK R17 K32 [0.059999999999999998]
     183 [-]: CALL R13 4 0 
     184 [-]: GETIMPORT R13 1 [nil]
     185 [-]: LOADK R15 K33 ["_root"]
     186 [-]: LOADN R16 11 
     187 [-]: LOADB R17 1  
     188 [-]: NAMECALL R13 R13 K34 [0xAADE900E]
     189 [-]: CALL R13 4 0 
     190 [-]: FORNLOOP R8 L2
L 3: 191 [-]: SUB R10 R3 R7
     192 [-]: DIVK R9 R10 K20 [2]
     193 [-]: ADD R8 R7 R9 
     194 [-]: SETUPVAL R8 7
     195 [-]: GETUPVAL R8 3
     196 [-]: GETIMPORT R9 36 [nil]
     197 [-]: MOVE R10 R0  
     198 [-]: GETUPVAL R11 7
     199 [-]: MOVE R12 R2  
     200 [-]: CALL R8 4 1  
     201 [-]: SETUPVAL R8 8
     202 [-]: GETUPVAL R8 5
     203 [-]: GETUPVAL R9 8
     204 [-]: GETUPVAL R10 6
     205 [-]: LOADB R11 0  
     206 [-]: LOADB R12 0  
     207 [-]: LOADN R13 0  
     208 [-]: CALL R10 3 1 
     209 [-]: LOADK R11 K37 [0.10000000000000001]
     210 [-]: LOADN R12 1  
     211 [-]: CALL R8 4 0  
     212 [-]: RETURN R0 0  


; Name:            
; Defined at line: 934
; #Upvalues:       13
; #Parameters:     0
; Is_vararg:       0
; Max Stack Size:  14

       0 [-]: GETIMPORT R0 1 [nil]
       1 [-]: LOADK R1 K2 ["EE.Interface.Components.List"]
       2 [-]: CALL R0 1 1  
       3 [-]: NEWTABLE R1 0 0
       4 [-]: SETUPVAL R1 0
       5 [-]: LOADN R2 640 
       6 [-]: LOADK R5 K4 [43.200000000000003]
       7 [-]: GETUPVAL R7 1
       8 [-]: SUBK R6 R7 K5 [1]
       9 [-]: MUL R4 R5 R6 
      10 [-]: DIVK R3 R4 K3 [2]
      11 [-]: SUB R1 R2 R3 
      12 [-]: LOADN R4 1   
      13 [-]: GETUPVAL R2 1
      14 [-]: LOADN R3 1   
      15 [-]: FORNPREP R2 L6
L 0:  16 [-]: LOADK R6 K6 ["Dial"]
      17 [-]: MOVE R7 R4   
      18 [-]: CONCAT R5 R6 R7
      19 [-]: LOADN R7 1000
      20 [-]: ADD R6 R7 R4 
      21 [-]: GETIMPORT R7 8 [nil]
      22 [-]: MOVE R9 R5   
      23 [-]: NAMECALL R7 R7 K9 [0xA7EC3E8A]
      24 [-]: CALL R7 2 1  
      25 [-]: JUMPIF R7 L1 
      26 [-]: GETIMPORT R7 11 [nil]
      27 [-]: GETIMPORT R8 8 [nil]
      28 [-]: LOADK R9 K12 ["Dial1.duplicateMovieClip"]
      29 [-]: MOVE R10 R5  
      30 [-]: MOVE R11 R6  
      31 [-]: CALL R7 4 0  
      32 [-]: JUMP L2
     
L 1:  33 [-]: GETIMPORT R7 11 [nil]
      34 [-]: GETIMPORT R8 8 [nil]
      35 [-]: MOVE R10 R5  
      36 [-]: LOADK R11 K13 [".swapDepths"]
      37 [-]: CONCAT R9 R10 R11
      38 [-]: MOVE R10 R6  
      39 [-]: CALL R7 3 0  
L 2:  40 [-]: GETIMPORT R7 8 [nil]
      41 [-]: MOVE R10 R5  
      42 [-]: LOADK R11 K14 [".Btn"]
      43 [-]: CONCAT R9 R10 R11
      44 [-]: LOADN R10 85 
      45 [-]: MOVE R11 R4  
      46 [-]: NAMECALL R7 R7 K15 [0x67BC869F]
      47 [-]: CALL R7 4 0  
      48 [-]: GETIMPORT R7 18 [nil]
      49 [-]: CALL R7 0 1  
      50 [-]: JUMPIFNOT R7 L3
      51 [-]: GETIMPORT R7 8 [nil]
      52 [-]: MOVE R10 R5  
      53 [-]: LOADK R11 K14 [".Btn"]
      54 [-]: CONCAT R9 R10 R11
      55 [-]: LOADK R10 K19 [""]
      56 [-]: LOADK R11 K20 ["DialUnfocused"]
      57 [-]: LOADK R12 K21 ["DialPressed"]
      58 [-]: LOADK R13 K22 ["DialFocused"]
      59 [-]: NAMECALL R7 R7 K23 [0x1E5B5CFE]
      60 [-]: CALL R7 6 0  
      61 [-]: JUMP L4
     
L 3:  62 [-]: GETIMPORT R7 8 [nil]
      63 [-]: MOVE R10 R5  
      64 [-]: LOADK R11 K14 [".Btn"]
      65 [-]: CONCAT R9 R10 R11
      66 [-]: LOADK R10 K22 ["DialFocused"]
      67 [-]: LOADK R11 K20 ["DialUnfocused"]
      68 [-]: LOADK R12 K21 ["DialPressed"]
      69 [-]: LOADK R13 K19 [""]
      70 [-]: NAMECALL R7 R7 K23 [0x1E5B5CFE]
      71 [-]: CALL R7 6 0  
L 4:  72 [-]: GETIMPORT R7 8 [nil]
      73 [-]: MOVE R9 R5   
      74 [-]: LOADN R10 0  
      75 [-]: SUBK R13 R4 K5 [1]
      76 [-]: MULK R12 R13 K4 [43.200000000000003]
      77 [-]: ADD R11 R1 R12
      78 [-]: NAMECALL R7 R7 K15 [0x67BC869F]
      79 [-]: CALL R7 4 0  
      80 [-]: MULK R8 R4 K25 [5]
      81 [-]: SUBK R7 R8 K24 [7]
      82 [-]: GETUPVAL R8 2
      83 [-]: JUMPIFNOT R8 L5
      84 [-]: SUBK R8 R4 K27 [3]
      85 [-]: MULK R7 R8 K26 [3.5]
L 5:  86 [-]: GETIMPORT R8 8 [nil]
      87 [-]: MOVE R10 R5  
      88 [-]: LOADK R11 K28 ["Btn"]
      89 [-]: LOADN R12 0  
      90 [-]: MOVE R13 R7  
      91 [-]: NAMECALL R8 R8 K29 [0xF64B7262]
      92 [-]: CALL R8 5 0  
      93 [-]: GETIMPORT R8 8 [nil]
      94 [-]: MOVE R10 R5  
      95 [-]: LOADK R11 K30 ["DialIndex"]
      96 [-]: MOVE R12 R4  
      97 [-]: NAMECALL R8 R8 K31 [0x0C33EBB2]
      98 [-]: CALL R8 4 0  
      99 [-]: GETTABLEKS R8 R0 K32 [0x9383BC56]
     100 [-]: GETIMPORT R9 8 [nil]
     101 [-]: MOVE R11 R5  
     102 [-]: LOADK R12 K33 [".Item1"]
     103 [-]: CONCAT R10 R11 R12
     104 [-]: CALL R8 2 1  
     105 [-]: LOADN R9 1   
     106 [-]: SETTABLEKS R9 R8 K34 ["Focus"]
     107 [-]: LOADNIL R9   
     108 [-]: SETTABLEKS R9 R8 K35 ["FocusedElement"]
     109 [-]: GETIMPORT R9 37 [nil]
     110 [-]: LOADN R10 0  
     111 [-]: LOADK R11 K38 [0.25]
     112 [-]: CALL R9 2 1  
     113 [-]: SETTABLEKS R9 R8 K39 ["mRotation"]
     114 [-]: DUPCLOSURE R9 K40 []
     115 [-]: SETTABLEKS R9 R8 K41 ["mOnFocusedCallback"]
     116 [-]: DUPCLOSURE R9 K42 []
     117 [-]: SETTABLEKS R9 R8 K43 ["mOnUnfocusedCallback"]
     118 [-]: DUPCLOSURE R9 K44 []
     119 [-]: SETTABLEKS R9 R8 K45 ["mOnSelectedCallback"]
     120 [-]: NEWCLOSURE R9 P3
     121 [-]: MOVE R2 R3   
     122 [-]: MOVE R2 R4   
     123 [-]: SETTABLEKS R9 R8 K46 ["mElementDrawCallback"]
     124 [-]: NEWCLOSURE R9 P4
     125 [-]: MOVE R2 R5   
     126 [-]: SETTABLEKS R9 R8 K47 ["ConvertFocusToElement"]
     127 [-]: NEWCLOSURE R9 P5
     128 [-]: MOVE R2 R3   
     129 [-]: MOVE R2 R6   
     130 [-]: MOVE R2 R4   
     131 [-]: MOVE R2 R7   
     132 [-]: MOVE R2 R8   
     133 [-]: MOVE R0 R4   
     134 [-]: SETTABLEKS R9 R8 K48 ["SetFocus"]
     135 [-]: NEWCLOSURE R9 P6
     136 [-]: MOVE R2 R5   
     137 [-]: MOVE R2 R9   
     138 [-]: MOVE R2 R6   
     139 [-]: MOVE R2 R10  
     140 [-]: MOVE R2 R11  
     141 [-]: MOVE R2 R12  
     142 [-]: SETTABLEKS R9 R8 K49 ["SetLocked"]
     143 [-]: GETUPVAL R9 0
     144 [-]: SETTABLE R8 R9 R4
     145 [-]: FORNLOOP R2 L0
L 6: 146 [-]: RETURN R0 0  


; Name:            
; Defined at line: 1068
; #Upvalues:       3
; #Parameters:     0
; Is_vararg:       0
; Max Stack Size:  7

       0 [-]: GETUPVAL R1 0
       1 [-]: FASTCALL1 62 R1 L0
       2 [-]: GETIMPORT R0 1 [nil]
       3 [-]: CALL R0 1 1  
L 0:   4 [-]: JUMPIF R0 L1 
       5 [-]: GETUPVAL R0 0
       6 [-]: GETUPVAL R2 1
       7 [-]: GETIMPORT R3 3 [nil]
       8 [-]: LOADN R4 0   
       9 [-]: GETUPVAL R5 2
      10 [-]: LOADN R6 90  
      11 [-]: CALL R3 3 -1 
      12 [-]: NAMECALL R0 R0 K4 [0xE28AA928]
      13 [-]: CALL R0 -1 0 
L 1:  14 [-]: RETURN R0 0  


; Name:            
; Defined at line: 1074
; #Upvalues:       7
; #Parameters:     0
; Is_vararg:       0
; Max Stack Size:  22

       0 [-]: LOADN R1 360 
       1 [-]: GETUPVAL R2 0
       2 [-]: DIV R0 R1 R2 
       3 [-]: LOADNIL R1   
       4 [-]: LOADNIL R2   
       5 [-]: LOADNIL R3   
       6 [-]: LOADNIL R4   
       7 [-]: LOADNIL R5   
       8 [-]: LOADNIL R6   
       9 [-]: LOADNIL R7   
      10 [-]: LOADN R10 1  
      11 [-]: GETUPVAL R8 1
      12 [-]: LOADN R9 1   
      13 [-]: FORNPREP R8 L12
L 0:  14 [-]: GETUPVAL R13 2
      15 [-]: GETTABLE R12 R13 R10
      16 [-]: GETTABLEKS R11 R12 K0 ["Focus"]
      17 [-]: MUL R1 R11 R0
      18 [-]: GETUPVAL R11 3
      19 [-]: JUMPIFNOT R11 L1
      20 [-]: GETUPVAL R13 2
      21 [-]: GETTABLE R12 R13 R10
      22 [-]: GETTABLEKS R11 R12 K1 ["mRotation"]
      23 [-]: MOVE R13 R1  
      24 [-]: NAMECALL R11 R11 K2 [0xD0F998CD]
      25 [-]: CALL R11 2 0 
      26 [-]: JUMP L2
     
L 1:  27 [-]: GETUPVAL R13 2
      28 [-]: GETTABLE R12 R13 R10
      29 [-]: GETTABLEKS R11 R12 K1 ["mRotation"]
      30 [-]: MOVE R13 R1  
      31 [-]: NAMECALL R11 R11 K3 [0x188E2BEE]
      32 [-]: CALL R11 2 0 
L 2:  33 [-]: GETUPVAL R13 2
      34 [-]: GETTABLE R12 R13 R10
      35 [-]: GETTABLEKS R11 R12 K1 ["mRotation"]
      36 [-]: GETIMPORT R13 5 [nil]
      37 [-]: CALL R13 0 -1
      38 [-]: NAMECALL R11 R11 K6 [0xFAA69527]
      39 [-]: CALL R11 -1 0
      40 [-]: GETUPVAL R13 2
      41 [-]: GETTABLE R12 R13 R10
      42 [-]: GETTABLEKS R11 R12 K1 ["mRotation"]
      43 [-]: NAMECALL R11 R11 K7 [0x54AB95F9]
      44 [-]: CALL R11 1 1 
      45 [-]: MOVE R2 R11  
      46 [-]: GETUPVAL R11 3
      47 [-]: JUMPIF R11 L4
      48 [-]: SUB R12 R1 R2
      49 [-]: FASTCALL1 2 R12 L3
      50 [-]: GETIMPORT R11 10 [nil]
      51 [-]: CALL R11 1 1 
L 3:  52 [-]: LOADK R12 K11 [0.001]
      53 [-]: JUMPIFNOTLT R12 R11 L11
L 4:  54 [-]: LOADN R13 1  
      55 [-]: GETUPVAL R16 2
      56 [-]: GETTABLE R15 R16 R10
      57 [-]: GETTABLEKS R14 R15 K12 ["mElements"]
      58 [-]: LENGTH R11 R14
      59 [-]: LOADN R12 1  
      60 [-]: FORNPREP R11 L10
L 5:  61 [-]: GETUPVAL R16 2
      62 [-]: GETTABLE R15 R16 R10
      63 [-]: GETTABLEKS R14 R15 K12 ["mElements"]
      64 [-]: GETTABLE R3 R14 R13
      65 [-]: MUL R15 R13 R0
      66 [-]: SUB R14 R15 R2
      67 [-]: SUBK R4 R14 K13 [90]
      68 [-]: GETUPVAL R16 4
      69 [-]: GETTABLEKS R15 R16 K15 [0x15BA5FE6]
      70 [-]: MOVE R16 R4  
      71 [-]: CALL R15 1 1 
      72 [-]: FASTCALL1 9 R15 L6
      73 [-]: GETIMPORT R14 17 [nil]
      74 [-]: CALL R14 1 1 
L 6:  75 [-]: MULK R6 R14 K14 [80]
      76 [-]: LOADN R14 40 
      77 [-]: GETUPVAL R18 4
      78 [-]: GETTABLEKS R17 R18 K15 [0x15BA5FE6]
      79 [-]: MOVE R18 R4  
      80 [-]: CALL R17 1 1 
      81 [-]: FASTCALL1 24 R17 L7
      82 [-]: GETIMPORT R16 19 [nil]
      83 [-]: CALL R16 1 1 
L 7:  84 [-]: MULK R15 R16 K14 [80]
      85 [-]: ADD R7 R14 R15
      86 [-]: MULK R7 R7 K20 [20]
      87 [-]: GETIMPORT R14 22 [nil]
      88 [-]: GETTABLEKS R16 R3 K23 ["mClipName"]
      89 [-]: LOADN R17 1  
      90 [-]: MOVE R18 R6  
      91 [-]: NAMECALL R14 R14 K24 [0x67BC869F]
      92 [-]: CALL R14 4 0 
      93 [-]: GETIMPORT R14 22 [nil]
      94 [-]: GETTABLEKS R16 R3 K23 ["mClipName"]
      95 [-]: LOADN R17 4  
      96 [-]: MOVE R18 R7  
      97 [-]: NAMECALL R14 R14 K24 [0x67BC869F]
      98 [-]: CALL R14 4 0 
      99 [-]: MODK R4 R4 K25 [360]
     100 [-]: LOADB R14 1  
     101 [-]: LOADN R15 190
     102 [-]: JUMPIFLT R4 R15 L9
     103 [-]: LOADN R15 350
     104 [-]: JUMPIFLT R15 R4 L8
     105 [-]: LOADB R14 0 +1
L 8: 106 [-]: LOADB R14 1  
L 9: 107 [-]: MOVE R5 R14  
     108 [-]: GETIMPORT R14 22 [nil]
     109 [-]: GETTABLEKS R16 R3 K23 ["mClipName"]
     110 [-]: LOADN R17 14 
     111 [-]: GETUPVAL R19 4
     112 [-]: GETTABLEKS R18 R19 K26 [0x06D055F9]
     113 [-]: MOVE R19 R5  
     114 [-]: LOADN R20 180
     115 [-]: LOADN R21 0  
     116 [-]: CALL R18 3 -1
     117 [-]: NAMECALL R14 R14 K24 [0x67BC869F]
     118 [-]: CALL R14 -1 0
     119 [-]: GETIMPORT R14 22 [nil]
     120 [-]: GETTABLEKS R16 R3 K23 ["mClipName"]
     121 [-]: LOADN R17 16 
     122 [-]: GETUPVAL R19 4
     123 [-]: GETTABLEKS R18 R19 K26 [0x06D055F9]
     124 [-]: MOVE R19 R5  
     125 [-]: SUBK R20 R4 K13 [90]
     126 [-]: ADDK R21 R4 K13 [90]
     127 [-]: CALL R18 3 -1
     128 [-]: NAMECALL R14 R14 K24 [0x67BC869F]
     129 [-]: CALL R14 -1 0
     130 [-]: GETIMPORT R14 22 [nil]
     131 [-]: GETTABLEKS R16 R3 K23 ["mClipName"]
     132 [-]: LOADN R17 10 
     133 [-]: GETUPVAL R19 4
     134 [-]: GETTABLEKS R18 R19 K26 [0x06D055F9]
     135 [-]: MOVE R19 R5  
     136 [-]: LOADN R20 15 
     137 [-]: LOADN R21 100
     138 [-]: CALL R18 3 -1
     139 [-]: NAMECALL R14 R14 K24 [0x67BC869F]
     140 [-]: CALL R14 -1 0
     141 [-]: FORNLOOP R11 L5
L10: 142 [-]: GETUPVAL R12 5
     143 [-]: SUB R14 R1 R2
     144 [-]: MULK R13 R14 K27 [0.10000000000000001]
     145 [-]: ADD R11 R12 R13
     146 [-]: SETUPVAL R11 5
     147 [-]: GETUPVAL R11 6
     148 [-]: CALL R11 0 0 
L11: 149 [-]: FORNLOOP R8 L0
L12: 150 [-]: LOADB R8 0   
     151 [-]: SETUPVAL R8 3
     152 [-]: RETURN R0 0  


; Name:            
; Defined at line: 1112
; #Upvalues:       10
; #Parameters:     0
; Is_vararg:       0
; Max Stack Size:  17

       0 [-]: GETIMPORT R0 1 [nil]
       1 [-]: GETIMPORT R1 3 [nil]
       2 [-]: LOADK R2 K4 ["Wheel"]
       3 [-]: LOADN R3 2   
       4 [-]: NEWTABLE R4 0 1
       5 [-]: LOADN R5 10  
       6 [-]: SETLIST R4 R5 1 [1]
       7 [-]: NEWTABLE R5 0 1
       8 [-]: LOADN R6 20  
       9 [-]: SETLIST R5 R6 1 [1]
      10 [-]: LOADK R6 K5 [0.65000000000000002]
      11 [-]: LOADK R7 K6 [0.29999999999999999]
      12 [-]: CALL R0 7 0  
      13 [-]: NEWTABLE R0 0 0
      14 [-]: NEWCLOSURE R1 P0
      15 [-]: MOVE R0 R0   
      16 [-]: MOVE R2 R0   
      17 [-]: NEWCLOSURE R2 P1
      18 [-]: MOVE R2 R1   
      19 [-]: MOVE R2 R2   
      20 [-]: MOVE R2 R3   
      21 [-]: MOVE R2 R4   
      22 [-]: LOADK R4 K7 [0.20000000000000001]
      23 [-]: LOADN R6 1   
      24 [-]: GETUPVAL R7 5
      25 [-]: DIV R5 R6 R7 
      26 [-]: FASTCALL2 19 R4 R5 L0
      27 [-]: GETIMPORT R3 10 [nil]
      28 [-]: CALL R3 2 1  
L 0:  29 [-]: LOADN R6 1   
      30 [-]: GETUPVAL R4 5
      31 [-]: LOADN R5 1   
      32 [-]: FORNPREP R4 L2
L 1:  33 [-]: LOADK R8 K11 ["Dial"]
      34 [-]: MOVE R9 R6   
      35 [-]: CONCAT R7 R8 R9
      36 [-]: GETIMPORT R8 3 [nil]
      37 [-]: MOVE R10 R7  
      38 [-]: LOADN R11 10 
      39 [-]: LOADN R12 0  
      40 [-]: NAMECALL R8 R8 K12 [0x67BC869F]
      41 [-]: CALL R8 4 0  
      42 [-]: GETIMPORT R8 3 [nil]
      43 [-]: MOVE R10 R7  
      44 [-]: LOADN R11 4  
      45 [-]: LOADN R12 10000
      46 [-]: NAMECALL R8 R8 K12 [0x67BC869F]
      47 [-]: CALL R8 4 0  
      48 [-]: GETIMPORT R8 3 [nil]
      49 [-]: MOVE R10 R7  
      50 [-]: LOADN R11 5  
      51 [-]: LOADN R12 10 
      52 [-]: NAMECALL R8 R8 K12 [0x67BC869F]
      53 [-]: CALL R8 4 0  
      54 [-]: GETIMPORT R8 1 [nil]
      55 [-]: GETIMPORT R9 3 [nil]
      56 [-]: MOVE R10 R7  
      57 [-]: LOADN R11 2  
      58 [-]: NEWTABLE R12 0 2
      59 [-]: NEWCLOSURE R13 P2
      60 [-]: MOVE R0 R2   
      61 [-]: MOVE R0 R6   
      62 [-]: LOADK R14 K13 ["_z"]
      63 [-]: SETLIST R12 R13 2 [1]
      64 [-]: NEWTABLE R13 0 2
      65 [-]: LOADN R14 1  
      66 [-]: LOADN R15 0  
      67 [-]: SETLIST R13 R14 2 [1]
      68 [-]: LOADK R14 K14 [0.34999999999999998]
      69 [-]: MUL R15 R3 R6
      70 [-]: NEWCLOSURE R16 P3
      71 [-]: MOVE R2 R1   
      72 [-]: MOVE R0 R6   
      73 [-]: MOVE R0 R7   
      74 [-]: MOVE R0 R1   
      75 [-]: CALL R8 8 0  
      76 [-]: FORNLOOP R4 L1
L 2:  77 [-]: LOADK R5 K7 [0.20000000000000001]
      78 [-]: GETUPVAL R6 5
      79 [-]: MUL R4 R5 R6 
      80 [-]: NEWCLOSURE R5 P4
      81 [-]: MOVE R2 R3   
      82 [-]: MOVE R2 R6   
      83 [-]: MOVE R2 R4   
      84 [-]: MOVE R0 R4   
      85 [-]: GETIMPORT R6 1 [nil]
      86 [-]: GETIMPORT R7 3 [nil]
      87 [-]: LOADK R8 K15 ["LinesRingExpand"]
      88 [-]: LOADN R9 2   
      89 [-]: NEWTABLE R10 0 1
      90 [-]: MOVE R11 R5  
      91 [-]: SETLIST R10 R11 1 [1]
      92 [-]: NEWTABLE R11 0 1
      93 [-]: LOADN R12 1  
      94 [-]: SETLIST R11 R12 1 [1]
      95 [-]: LOADK R12 K16 [0.40000000000000002]
      96 [-]: LOADK R13 K16 [0.40000000000000002]
      97 [-]: CALL R6 7 0  
      98 [-]: GETIMPORT R6 3 [nil]
      99 [-]: NAMECALL R6 R6 K17 [0xA1653871]
     100 [-]: CALL R6 1 1  
     101 [-]: SETUPVAL R6 7
     102 [-]: LOADB R6 1   
     103 [-]: SETUPVAL R6 8
     104 [-]: LOADB R6 0   
     105 [-]: SETUPVAL R6 9
     106 [-]: RETURN R0 0  


; Name:            
; Defined at line: 1165
; #Upvalues:       3
; #Parameters:     0
; Is_vararg:       0
; Max Stack Size:  13

       0 [-]: LOADN R2 1   
       1 [-]: LOADN R0 11  
       2 [-]: LOADN R1 1   
       3 [-]: FORNPREP R0 L5
L 0:   4 [-]: LOADK R4 K0 ["Lines.Line"]
       5 [-]: MOVE R5 R2   
       6 [-]: CONCAT R3 R4 R5
       7 [-]: LOADN R5 -1000
       8 [-]: ADD R4 R5 R2 
       9 [-]: GETIMPORT R5 2 [nil]
      10 [-]: MOVE R7 R3   
      11 [-]: NAMECALL R5 R5 K3 [0xA7EC3E8A]
      12 [-]: CALL R5 2 1  
      13 [-]: JUMPIF R5 L1 
      14 [-]: GETIMPORT R5 5 [nil]
      15 [-]: GETIMPORT R6 2 [nil]
      16 [-]: LOADK R7 K6 ["Lines.Line1.duplicateMovieClip"]
      17 [-]: LOADK R9 K7 ["Line"]
      18 [-]: MOVE R10 R2  
      19 [-]: CONCAT R8 R9 R10
      20 [-]: MOVE R9 R4   
      21 [-]: CALL R5 4 0  
      22 [-]: JUMP L2
     
L 1:  23 [-]: GETIMPORT R5 5 [nil]
      24 [-]: GETIMPORT R6 2 [nil]
      25 [-]: MOVE R8 R3   
      26 [-]: LOADK R9 K8 [".swapDepths"]
      27 [-]: CONCAT R7 R8 R9
      28 [-]: MOVE R8 R4   
      29 [-]: CALL R5 3 0  
L 2:  30 [-]: GETIMPORT R5 2 [nil]
      31 [-]: MOVE R7 R3   
      32 [-]: GETIMPORT R8 10 [nil]
      33 [-]: NAMECALL R5 R5 K11 [0xD5181643]
      34 [-]: CALL R5 3 0  
      35 [-]: GETIMPORT R5 2 [nil]
      36 [-]: MOVE R7 R3   
      37 [-]: LOADN R8 0   
      38 [-]: LOADN R9 690 
      39 [-]: NAMECALL R5 R5 K12 [0x67BC869F]
      40 [-]: CALL R5 4 0  
      41 [-]: GETIMPORT R5 2 [nil]
      42 [-]: MOVE R7 R3   
      43 [-]: LOADN R8 12  
      44 [-]: LOADN R9 600 
      45 [-]: NAMECALL R5 R5 K12 [0x67BC869F]
      46 [-]: CALL R5 4 0  
      47 [-]: GETIMPORT R5 2 [nil]
      48 [-]: MOVE R7 R3   
      49 [-]: LOADN R8 13  
      50 [-]: LOADN R9 2   
      51 [-]: NAMECALL R5 R5 K12 [0x67BC869F]
      52 [-]: CALL R5 4 0  
      53 [-]: GETIMPORT R5 2 [nil]
      54 [-]: MOVE R7 R3   
      55 [-]: LOADN R8 9   
      56 [-]: GETUPVAL R9 0
      57 [-]: NAMECALL R5 R5 K12 [0x67BC869F]
      58 [-]: CALL R5 4 0  
      59 [-]: GETIMPORT R5 2 [nil]
      60 [-]: MOVE R7 R3   
      61 [-]: LOADN R8 10  
      62 [-]: GETUPVAL R10 1
      63 [-]: GETTABLEKS R9 R10 K13 [0x06D055F9]
      64 [-]: MODK R11 R2 K14 [2]
      65 [-]: JUMPXEQKN R11 K15 L3 [0]
      66 [-]: LOADB R10 0 +1
L 3:  67 [-]: LOADB R10 1  
L 4:  68 [-]: LOADN R11 50 
      69 [-]: LOADN R12 10 
      70 [-]: CALL R9 3 -1 
      71 [-]: NAMECALL R5 R5 K12 [0x67BC869F]
      72 [-]: CALL R5 -1 0 
      73 [-]: FORNLOOP R0 L0
L 5:  74 [-]: GETUPVAL R0 2
      75 [-]: CALL R0 0 0  
      76 [-]: GETIMPORT R0 2 [nil]
      77 [-]: LOADK R2 K16 ["Lines"]
      78 [-]: LOADN R3 4   
      79 [-]: LOADN R4 1600
      80 [-]: NAMECALL R0 R0 K12 [0x67BC869F]
      81 [-]: CALL R0 4 0  
      82 [-]: RETURN R0 0  


; Name:            
; Defined at line: 1185
; #Upvalues:       0
; #Parameters:     2
; Is_vararg:       0
; Max Stack Size:  11

       0 [-]: GETTABLEKS R2 R0 K0 ["Offsets"]
       1 [-]: GETTABLEKS R3 R2 K1 ["Current"]
       2 [-]: GETTABLEKS R4 R2 K2 ["Start"]
       3 [-]: GETTABLEKS R5 R2 K3 ["End"]
       4 [-]: GETTABLEKS R6 R0 K4 ["Timer"]
       5 [-]: GETTABLEKS R7 R0 K5 ["Time"]
       6 [-]: JUMPIFNOTLE R7 R6 L0
       7 [-]: GETTABLEKS R6 R3 K6 ["X"]
       8 [-]: SETTABLEKS R6 R4 K6 ["X"]
       9 [-]: GETTABLEKS R6 R3 K7 ["Y"]
      10 [-]: SETTABLEKS R6 R4 K7 ["Y"]
      11 [-]: GETTABLEKS R6 R3 K8 ["R"]
      12 [-]: SETTABLEKS R6 R4 K8 ["R"]
      13 [-]: GETIMPORT R6 10 [nil]
      14 [-]: GETIMPORT R8 12 [nil]
      15 [-]: MINUS R7 R8  
      16 [-]: GETIMPORT R8 12 [nil]
      17 [-]: CALL R6 2 1  
      18 [-]: SETTABLEKS R6 R5 K6 ["X"]
      19 [-]: GETIMPORT R6 10 [nil]
      20 [-]: GETIMPORT R8 14 [nil]
      21 [-]: MINUS R7 R8  
      22 [-]: GETIMPORT R8 14 [nil]
      23 [-]: CALL R6 2 1  
      24 [-]: SETTABLEKS R6 R5 K7 ["Y"]
      25 [-]: GETIMPORT R6 10 [nil]
      26 [-]: GETIMPORT R8 16 [nil]
      27 [-]: MINUS R7 R8  
      28 [-]: GETIMPORT R8 16 [nil]
      29 [-]: CALL R6 2 1  
      30 [-]: SETTABLEKS R6 R5 K8 ["R"]
      31 [-]: LOADN R6 0   
      32 [-]: SETTABLEKS R6 R0 K4 ["Timer"]
      33 [-]: GETIMPORT R6 18 [nil]
      34 [-]: GETIMPORT R7 20 [nil]
      35 [-]: GETIMPORT R8 22 [nil]
      36 [-]: CALL R6 2 1  
      37 [-]: SETTABLEKS R6 R0 K5 ["Time"]
L 0:  38 [-]: GETTABLEKS R7 R0 K4 ["Timer"]
      39 [-]: ADD R6 R7 R1 
      40 [-]: SETTABLEKS R6 R0 K4 ["Timer"]
      41 [-]: GETTABLEKS R7 R0 K4 ["Timer"]
      42 [-]: GETTABLEKS R8 R0 K5 ["Time"]
      43 [-]: DIV R6 R7 R8 
      44 [-]: GETIMPORT R7 24 [nil]
      45 [-]: GETTABLEKS R8 R4 K6 ["X"]
      46 [-]: GETTABLEKS R9 R5 K6 ["X"]
      47 [-]: MOVE R10 R6  
      48 [-]: CALL R7 3 1  
      49 [-]: SETTABLEKS R7 R3 K6 ["X"]
      50 [-]: GETIMPORT R7 24 [nil]
      51 [-]: GETTABLEKS R8 R4 K7 ["Y"]
      52 [-]: GETTABLEKS R9 R5 K7 ["Y"]
      53 [-]: MOVE R10 R6  
      54 [-]: CALL R7 3 1  
      55 [-]: SETTABLEKS R7 R3 K7 ["Y"]
      56 [-]: GETIMPORT R7 24 [nil]
      57 [-]: GETTABLEKS R8 R4 K8 ["R"]
      58 [-]: GETTABLEKS R9 R5 K8 ["R"]
      59 [-]: MOVE R10 R6  
      60 [-]: CALL R7 3 1  
      61 [-]: SETTABLEKS R7 R3 K8 ["R"]
      62 [-]: RETURN R3 1  


; Name:            
; Defined at line: 1208
; #Upvalues:       0
; #Parameters:     1
; Is_vararg:       0
; Max Stack Size:  7

       0 [-]: LOADN R1 0   
       1 [-]: GETIMPORT R2 1 [nil]
       2 [-]: MOVE R3 R0   
       3 [-]: CALL R2 1 3  
       4 [-]: FORGPREP_NEXT R2 L1
L 0:   5 [-]: ADDK R1 R1 K2 [1]
L 1:   6 [-]: FORGLOOP R2 L0 2
       7 [-]: RETURN R1 1  


; Name:            
; Defined at line: 1216
; #Upvalues:       0
; #Parameters:     2
; Is_vararg:       0
; Max Stack Size:  8

       0 [-]: GETIMPORT R2 1 [nil]
       1 [-]: MOVE R3 R0   
       2 [-]: CALL R2 1 3  
       3 [-]: FORGPREP_NEXT R2 L1
L 0:   4 [-]: GETTABLE R7 R1 R5
       5 [-]: JUMPIF R7 L1 
       6 [-]: LOADB R7 0   
       7 [-]: RETURN R7 1  
L 1:   8 [-]: FORGLOOP R2 L0 2
       9 [-]: LOADB R2 1   
      10 [-]: RETURN R2 1  


; Name:            
; Defined at line: 1225
; #Upvalues:       0
; #Parameters:     1
; Is_vararg:       0
; Max Stack Size:  7

       0 [-]: GETIMPORT R1 3 [nil]
       1 [-]: LOADN R4 1   
       2 [-]: LENGTH R2 R1 
       3 [-]: LOADN R3 1   
       4 [-]: FORNPREP R2 L2
L 0:   5 [-]: GETTABLE R5 R1 R4
       6 [-]: GETTABLEKS R6 R5 K4 ["index"]
       7 [-]: JUMPIFNOTEQ R6 R0 L1
       8 [-]: RETURN R5 1  
L 1:   9 [-]: FORNLOOP R2 L0
L 2:  10 [-]: LOADNIL R2   
      11 [-]: RETURN R2 1  


; Name:            
; Defined at line: 1236
; #Upvalues:       7
; #Parameters:     0
; Is_vararg:       0
; Max Stack Size:  20

       0 [-]: GETUPVAL R0 0
       1 [-]: JUMPXEQKNIL R0 L0 NOT
       2 [-]: RETURN R0 0  
L 0:   3 [-]: GETUPVAL R1 1
       4 [-]: GETTABLEKS R0 R1 K0 ["Elements"]
       5 [-]: LENGTH R3 R0 
       6 [-]: LOADN R1 1   
       7 [-]: LOADN R2 -1  
       8 [-]: FORNPREP R1 L12
L 1:   9 [-]: GETTABLE R4 R0 R3
      10 [-]: LOADN R7 1   
      11 [-]: GETUPVAL R8 0
      12 [-]: LENGTH R5 R8 
      13 [-]: LOADN R6 1   
      14 [-]: FORNPREP R5 L11
L 2:  15 [-]: GETUPVAL R9 0
      16 [-]: GETTABLE R8 R9 R7
      17 [-]: GETTABLEKS R9 R4 K1 ["SymbolIds"]
      18 [-]: GETUPVAL R10 2
      19 [-]: MOVE R11 R9  
      20 [-]: MOVE R12 R8  
      21 [-]: CALL R10 2 1 
      22 [-]: JUMPIFNOT R10 L10
      23 [-]: GETUPVAL R10 3
      24 [-]: MOVE R11 R8  
      25 [-]: CALL R10 1 1 
      26 [-]: LOADN R11 2  
      27 [-]: JUMPIFNOTLT R11 R10 L11
      28 [-]: GETUPVAL R11 4
      29 [-]: JUMPXEQKNIL R11 L9 NOT
      30 [-]: SETUPVAL R4 4
      31 [-]: GETIMPORT R11 4 [nil]
      32 [-]: MOVE R12 R0  
      33 [-]: MOVE R13 R3  
      34 [-]: CALL R11 2 0 
      35 [-]: GETUPVAL R13 4
      36 [-]: FASTCALL2 52 R0 R13 L3
      37 [-]: MOVE R12 R0  
      38 [-]: GETIMPORT R11 6 [nil]
      39 [-]: CALL R11 2 0 
L 3:  40 [-]: GETUPVAL R12 4
      41 [-]: GETTABLEKS R11 R12 K7 ["PairIndex"]
      42 [-]: SUBK R14 R11 K8 [1]
      43 [-]: LOADN R12 1  
      44 [-]: LOADN R13 -1 
      45 [-]: FORNPREP R12 L6
L 4:  46 [-]: GETUPVAL R15 5
      47 [-]: MOVE R16 R14 
      48 [-]: CALL R15 1 1 
      49 [-]: JUMPXEQKNIL R15 L5
      50 [-]: GETTABLEKS R17 R15 K9 ["first"]
      51 [-]: GETTABLE R16 R8 R17
      52 [-]: JUMPIFNOT R16 L5
      53 [-]: GETTABLEKS R17 R15 K10 ["second"]
      54 [-]: GETTABLE R16 R8 R17
      55 [-]: JUMPIFNOT R16 L5
      56 [-]: GETUPVAL R16 6
      57 [-]: GETTABLEKS R17 R15 K9 ["first"]
      58 [-]: GETTABLEKS R18 R15 K10 ["second"]
      59 [-]: MOVE R19 R3  
      60 [-]: CALL R16 3 0 
L 5:  61 [-]: FORNLOOP R12 L4
L 6:  62 [-]: ADDK R14 R11 K8 [1]
      63 [-]: GETIMPORT R15 14 [nil]
      64 [-]: LENGTH R12 R15
      65 [-]: LOADN R13 1  
      66 [-]: FORNPREP R12 L11
L 7:  67 [-]: GETUPVAL R15 5
      68 [-]: MOVE R16 R14 
      69 [-]: CALL R15 1 1 
      70 [-]: JUMPXEQKNIL R15 L8
      71 [-]: GETTABLEKS R17 R15 K9 ["first"]
      72 [-]: GETTABLE R16 R8 R17
      73 [-]: JUMPIFNOT R16 L8
      74 [-]: GETTABLEKS R17 R15 K10 ["second"]
      75 [-]: GETTABLE R16 R8 R17
      76 [-]: JUMPIFNOT R16 L8
      77 [-]: GETUPVAL R16 6
      78 [-]: GETTABLEKS R17 R15 K9 ["first"]
      79 [-]: GETTABLEKS R18 R15 K10 ["second"]
      80 [-]: MOVE R19 R3  
      81 [-]: CALL R16 3 0 
L 8:  82 [-]: FORNLOOP R12 L7
      83 [-]: JUMP L11
    
L 9:  84 [-]: NAMECALL R11 R4 K15 [0xA2880940]
      85 [-]: CALL R11 1 0 
      86 [-]: GETIMPORT R11 4 [nil]
      87 [-]: MOVE R12 R0  
      88 [-]: MOVE R13 R3  
      89 [-]: CALL R11 2 0 
      90 [-]: JUMP L11
    
L10:  91 [-]: FORNLOOP R5 L2
L11:  92 [-]: FORNLOOP R1 L1
L12:  93 [-]: LOADNIL R1   
      94 [-]: SETUPVAL R1 0
      95 [-]: RETURN R0 0  


; Name:            
; Defined at line: 1282
; #Upvalues:       8
; #Parameters:     0
; Is_vararg:       0
; Max Stack Size:  2

       0 [-]: DUPTABLE R0 4
       1 [-]: NEWTABLE R1 0 0
       2 [-]: SETTABLEKS R1 R0 K0 ["Elements"]
       3 [-]: LOADN R1 0   
       4 [-]: SETTABLEKS R1 R0 K1 ["Count"]
       5 [-]: DUPCLOSURE R1 K5 []
       6 [-]: MOVE R2 R1   
       7 [-]: SETTABLEKS R1 R0 K2 ["AddElement"]
       8 [-]: NEWCLOSURE R1 P1
       9 [-]: MOVE R2 R2   
      10 [-]: MOVE R2 R3   
      11 [-]: MOVE R2 R4   
      12 [-]: MOVE R2 R5   
      13 [-]: MOVE R2 R6   
      14 [-]: MOVE R2 R7   
      15 [-]: SETTABLEKS R1 R0 K3 ["Update"]
      16 [-]: SETUPVAL R0 0
      17 [-]: RETURN R0 0  


; Name:            
; Defined at line: 1415
; #Upvalues:       15
; #Parameters:     0
; Is_vararg:       0
; Max Stack Size:  7

       0 [-]: GETUPVAL R0 0
       1 [-]: JUMPIFNOT R0 L0
       2 [-]: GETIMPORT R0 1 [nil]
       3 [-]: SETUPVAL R0 1
       4 [-]: GETIMPORT R0 3 [nil]
       5 [-]: SETUPVAL R0 2
       6 [-]: GETIMPORT R0 5 [nil]
       7 [-]: SETUPVAL R0 3
       8 [-]: GETIMPORT R0 7 [nil]
       9 [-]: SETUPVAL R0 4
      10 [-]: GETIMPORT R0 9 [nil]
      11 [-]: SETUPVAL R0 5
      12 [-]: GETIMPORT R0 11 [nil]
      13 [-]: SETUPVAL R0 6
      14 [-]: GETIMPORT R0 13 [nil]
      15 [-]: SETUPVAL R0 7
      16 [-]: GETIMPORT R0 15 [nil]
      17 [-]: SETUPVAL R0 8
      18 [-]: JUMP L1
     
L 0:  19 [-]: GETIMPORT R0 17 [nil]
      20 [-]: SETUPVAL R0 1
      21 [-]: GETIMPORT R0 19 [nil]
      22 [-]: SETUPVAL R0 2
      23 [-]: GETIMPORT R0 21 [nil]
      24 [-]: SETUPVAL R0 3
      25 [-]: GETIMPORT R0 23 [nil]
      26 [-]: SETUPVAL R0 4
      27 [-]: GETIMPORT R0 25 [nil]
      28 [-]: SETUPVAL R0 5
      29 [-]: GETIMPORT R0 27 [nil]
      30 [-]: SETUPVAL R0 6
      31 [-]: GETIMPORT R0 29 [nil]
      32 [-]: SETUPVAL R0 7
      33 [-]: GETIMPORT R0 31 [nil]
      34 [-]: SETUPVAL R0 8
L 1:  35 [-]: LOADK R1 K32 ["0x"]
      36 [-]: GETUPVAL R3 10
      37 [-]: GETTABLEKS R2 R3 K33 [0x2D56AB0B]
      38 [-]: GETUPVAL R4 1
      39 [-]: GETTABLEKS R3 R4 K34 ["red"]
      40 [-]: GETUPVAL R5 1
      41 [-]: GETTABLEKS R4 R5 K35 ["green"]
      42 [-]: GETUPVAL R6 1
      43 [-]: GETTABLEKS R5 R6 K36 ["blue"]
      44 [-]: CALL R2 3 1  
      45 [-]: CONCAT R0 R1 R2
      46 [-]: SETUPVAL R0 9
      47 [-]: LOADK R1 K32 ["0x"]
      48 [-]: GETUPVAL R3 10
      49 [-]: GETTABLEKS R2 R3 K33 [0x2D56AB0B]
      50 [-]: GETUPVAL R4 2
      51 [-]: GETTABLEKS R3 R4 K34 ["red"]
      52 [-]: GETUPVAL R5 2
      53 [-]: GETTABLEKS R4 R5 K35 ["green"]
      54 [-]: GETUPVAL R6 2
      55 [-]: GETTABLEKS R5 R6 K36 ["blue"]
      56 [-]: CALL R2 3 1  
      57 [-]: CONCAT R0 R1 R2
      58 [-]: SETUPVAL R0 11
      59 [-]: LOADK R1 K32 ["0x"]
      60 [-]: GETUPVAL R3 10
      61 [-]: GETTABLEKS R2 R3 K33 [0x2D56AB0B]
      62 [-]: GETUPVAL R4 3
      63 [-]: GETTABLEKS R3 R4 K34 ["red"]
      64 [-]: GETUPVAL R5 3
      65 [-]: GETTABLEKS R4 R5 K35 ["green"]
      66 [-]: GETUPVAL R6 3
      67 [-]: GETTABLEKS R5 R6 K36 ["blue"]
      68 [-]: CALL R2 3 1  
      69 [-]: CONCAT R0 R1 R2
      70 [-]: SETUPVAL R0 12
      71 [-]: LOADK R1 K32 ["0x"]
      72 [-]: GETUPVAL R3 10
      73 [-]: GETTABLEKS R2 R3 K33 [0x2D56AB0B]
      74 [-]: GETUPVAL R4 4
      75 [-]: GETTABLEKS R3 R4 K34 ["red"]
      76 [-]: GETUPVAL R5 4
      77 [-]: GETTABLEKS R4 R5 K35 ["green"]
      78 [-]: GETUPVAL R6 4
      79 [-]: GETTABLEKS R5 R6 K36 ["blue"]
      80 [-]: CALL R2 3 1  
      81 [-]: CONCAT R0 R1 R2
      82 [-]: SETUPVAL R0 13
      83 [-]: LOADK R1 K32 ["0x"]
      84 [-]: GETUPVAL R3 10
      85 [-]: GETTABLEKS R2 R3 K33 [0x2D56AB0B]
      86 [-]: GETUPVAL R4 5
      87 [-]: GETTABLEKS R3 R4 K34 ["red"]
      88 [-]: GETUPVAL R5 5
      89 [-]: GETTABLEKS R4 R5 K35 ["green"]
      90 [-]: GETUPVAL R6 5
      91 [-]: GETTABLEKS R5 R6 K36 ["blue"]
      92 [-]: CALL R2 3 1  
      93 [-]: CONCAT R0 R1 R2
      94 [-]: SETUPVAL R0 14
      95 [-]: RETURN R0 0  


; Name:            
; Defined at line: 1445
; #Upvalues:       1
; #Parameters:     0
; Is_vararg:       0
; Max Stack Size:  19

       0 [-]: GETIMPORT R0 1 [nil]
       1 [-]: NAMECALL R0 R0 K2 [0xCD73323E]
       2 [-]: CALL R0 1 1  
       3 [-]: FASTCALL1 62 R0 L0
       4 [-]: MOVE R2 R0   
       5 [-]: GETIMPORT R1 4 [nil]
       6 [-]: CALL R1 1 1  
L 0:   7 [-]: JUMPIF R1 L3 
       8 [-]: NAMECALL R1 R0 K5 [0x22DA1852]
       9 [-]: CALL R1 1 1  
      10 [-]: GETIMPORT R2 7 [nil]
      11 [-]: LOADK R3 K8 ["OrbCaveHack"]
      12 [-]: CALL R2 1 1  
      13 [-]: JUMPIFNOTEQ R1 R2 L3
      14 [-]: LOADB R1 1   
      15 [-]: SETUPVAL R1 0
      16 [-]: GETIMPORT R1 11 [nil]
      17 [-]: NEWTABLE R2 0 8
      18 [-]: LOADN R3 1   
      19 [-]: LOADN R4 2   
      20 [-]: LOADN R5 4   
      21 [-]: LOADN R6 5   
      22 [-]: LOADN R7 8   
      23 [-]: LOADN R8 18  
      24 [-]: LOADN R9 19  
      25 [-]: LOADN R10 21 
      26 [-]: SETLIST R2 R3 8 [1]
      27 [-]: SETTABLEKS R2 R1 K12 ["Symbols"]
      28 [-]: GETIMPORT R1 11 [nil]
      29 [-]: NEWTABLE R2 0 16
      30 [-]: LOADN R3 4   
      31 [-]: LOADN R4 2   
      32 [-]: LOADN R5 8   
      33 [-]: LOADN R6 1   
      34 [-]: LOADN R7 1   
      35 [-]: LOADN R8 19  
      36 [-]: LOADN R9 7   
      37 [-]: LOADN R10 20 
      38 [-]: LOADN R11 19 
      39 [-]: LOADN R12 5  
      40 [-]: LOADN R13 11 
      41 [-]: LOADN R14 19 
      42 [-]: LOADN R15 0  
      43 [-]: LOADN R16 3  
      44 [-]: LOADN R17 8  
      45 [-]: LOADN R18 13 
      46 [-]: SETLIST R2 R3 16 [1]
      47 [-]: SETTABLEKS R2 R1 K13 ["Solution"]
      48 [-]: GETIMPORT R1 15 [nil]
      49 [-]: JUMPIF R1 L1 
      50 [-]: GETGLOBAL R1 K16 [0x90A24D27]
L 1:  51 [-]: SETGLOBAL R1 K16 [0x90A24D27]
      52 [-]: GETIMPORT R1 18 [nil]
      53 [-]: JUMPIF R1 L2 
      54 [-]: GETGLOBAL R1 K19 [0x6B0C7C2B]
L 2:  55 [-]: SETGLOBAL R1 K19 [0x6B0C7C2B]
L 3:  56 [-]: RETURN R0 0  


; Name:            
; Defined at line: 1456
; #Upvalues:       1
; #Parameters:     0
; Is_vararg:       0
; Max Stack Size:  11

       0 [-]: NEWTABLE R0 0 0
       1 [-]: GETIMPORT R1 2 [nil]
       2 [-]: CALL R1 0 1  
       3 [-]: JUMPIFNOT R1 L3
       4 [-]: GETIMPORT R3 5 [nil]
       5 [-]: LENGTH R2 R3 
       6 [-]: LOADN R3 0   
       7 [-]: JUMPIFLT R3 R2 L0
       8 [-]: LOADB R1 0 +1
L 0:   9 [-]: LOADB R1 1   
L 1:  10 [-]: DUPTABLE R4 9
      11 [-]: LOADK R6 K10 ["/Lotus/Language/Menu/"]
      12 [-]: GETUPVAL R8 0
      13 [-]: GETTABLEKS R7 R8 K11 [0x06D055F9]
      14 [-]: MOVE R8 R1   
      15 [-]: LOADK R9 K12 ["Global_Back"]
      16 [-]: LOADK R10 K13 ["Exit"]
      17 [-]: CALL R7 3 1  
      18 [-]: CONCAT R5 R6 R7
      19 [-]: SETTABLEKS R5 R4 K6 ["Label"]
      20 [-]: GETGLOBAL R5 K14 ["Close"]
      21 [-]: SETTABLEKS R5 R4 K7 ["CallBack"]
      22 [-]: LOADK R5 K15 ["MENU_CANCEL"]
      23 [-]: SETTABLEKS R5 R4 K8 ["CallOut"]
      24 [-]: FASTCALL2 52 R0 R4 L2
      25 [-]: MOVE R3 R0   
      26 [-]: GETIMPORT R2 18 [nil]
      27 [-]: CALL R2 2 0  
L 2:  28 [-]: GETIMPORT R2 20 [nil]
      29 [-]: JUMPIFNOT R2 L3
      30 [-]: GETIMPORT R2 20 [nil]
      31 [-]: GETIMPORT R3 22 [nil]
      32 [-]: MOVE R4 R0   
      33 [-]: GETIMPORT R5 24 [nil]
      34 [-]: LOADN R6 1   
      35 [-]: CALL R5 1 -1 
      36 [-]: CALL R2 -1 0 
L 3:  37 [-]: RETURN R0 0  


; Name:            
; Defined at line: 1469
; #Upvalues:       17
; #Parameters:     0
; Is_vararg:       0
; Max Stack Size:  13

       0 [-]: GETIMPORT R0 1 [nil]
       1 [-]: GETIMPORT R1 3 [nil]
       2 [-]: SETTABLEKS R1 R0 K4 ["OrokinLockPuzzleMovie"]
       3 [-]: GETIMPORT R0 3 [nil]
       4 [-]: LOADB R2 1   
       5 [-]: NAMECALL R0 R0 K5 [0x824D113A]
       6 [-]: CALL R0 2 0  
       7 [-]: GETIMPORT R1 7 [nil]
       8 [-]: FASTCALL1 62 R1 L0
       9 [-]: GETIMPORT R0 9 [nil]
      10 [-]: CALL R0 1 1  
L 0:  11 [-]: JUMPIFNOT R0 L1
      12 [-]: GETIMPORT R0 1 [nil]
      13 [-]: NEWTABLE R1 0 0
      14 [-]: SETTABLEKS R1 R0 K6 ["OrokinLockPuzzle"]
L 1:  15 [-]: GETUPVAL R0 0
      16 [-]: CALL R0 0 0  
      17 [-]: GETIMPORT R1 11 [nil]
      18 [-]: FASTCALL1 62 R1 L2
      19 [-]: GETIMPORT R0 9 [nil]
      20 [-]: CALL R0 1 1  
L 2:  21 [-]: JUMPIF R0 L5 
      22 [-]: GETIMPORT R1 11 [nil]
      23 [-]: LENGTH R0 R1 
      24 [-]: SETUPVAL R0 1
      25 [-]: GETUPVAL R1 1
      26 [-]: LOADN R2 5   
      27 [-]: JUMPIFLT R2 R1 L3
      28 [-]: LOADB R0 0 +1
L 3:  29 [-]: LOADB R0 1   
L 4:  30 [-]: SETUPVAL R0 2
L 5:  31 [-]: GETIMPORT R0 13 [nil]
      32 [-]: FASTCALL1 40 R0 L6
      33 [-]: MOVE R2 R0   
      34 [-]: GETIMPORT R1 15 [nil]
      35 [-]: CALL R1 1 1  
L 6:  36 [-]: JUMPXEQKS R1 K16 L7 NOT ["table"]
      37 [-]: LENGTH R1 R0 
      38 [-]: SETUPVAL R1 3
      39 [-]: JUMP L9
     
L 7:  40 [-]: GETIMPORT R1 18 [nil]
      41 [-]: MOVE R2 R0   
      42 [-]: CALL R1 1 1  
      43 [-]: JUMPXEQKNIL R1 L8
      44 [-]: SETUPVAL R1 3
L 8:  45 [-]: NEWTABLE R0 0 0
L 9:  46 [-]: LOADN R3 1   
      47 [-]: GETUPVAL R1 3
      48 [-]: LOADN R2 1   
      49 [-]: FORNPREP R1 L12
L10:  50 [-]: GETTABLE R5 R0 R3
      51 [-]: OR R4 R5 R3  
      52 [-]: GETUPVAL R6 4
      53 [-]: DUPTABLE R7 20
      54 [-]: SETTABLEKS R4 R7 K19 ["Index"]
      55 [-]: FASTCALL2 52 R6 R7 L11
      56 [-]: GETIMPORT R5 23 [nil]
      57 [-]: CALL R5 2 0  
L11:  58 [-]: FORNLOOP R1 L10
L12:  59 [-]: GETIMPORT R2 25 [nil]
      60 [-]: JUMPXEQKB R2 1 L13
      61 [-]: LOADB R1 0 +1
L13:  62 [-]: LOADB R1 1   
L14:  63 [-]: SETUPVAL R1 5
      64 [-]: GETIMPORT R1 27 [nil]
      65 [-]: SETUPVAL R1 6
      66 [-]: GETIMPORT R1 7 [nil]
      67 [-]: GETUPVAL R2 7
      68 [-]: SETTABLEKS R2 R1 K28 ["OldEntities"]
      69 [-]: GETUPVAL R2 8
      70 [-]: GETUPVAL R3 3
      71 [-]: FASTCALL2 19 R2 R3 L15
      72 [-]: GETIMPORT R1 31 [nil]
      73 [-]: CALL R1 2 1  
L15:  74 [-]: SETUPVAL R1 8
      75 [-]: GETIMPORT R1 33 [nil]
      76 [-]: LOADB R3 1   
      77 [-]: NAMECALL R1 R1 K34 [0xC02F2CB8]
      78 [-]: CALL R1 2 0  
      79 [-]: GETIMPORT R1 36 [nil]
      80 [-]: NAMECALL R1 R1 K37 [0x78298275]
      81 [-]: CALL R1 1 1  
      82 [-]: NAMECALL R2 R1 K38 [0xDE321E6F]
      83 [-]: CALL R2 1 1  
      84 [-]: LOADN R5 0   
      85 [-]: NAMECALL R3 R2 K39 [0x881B6B90]
      86 [-]: CALL R3 2 1  
      87 [-]: FASTCALL1 62 R3 L16
      88 [-]: MOVE R5 R3   
      89 [-]: GETIMPORT R4 9 [nil]
      90 [-]: CALL R4 1 1  
L16:  91 [-]: JUMPIF R4 L17
      92 [-]: GETIMPORT R4 1 [nil]
      93 [-]: NAMECALL R5 R3 K40 [0xB5D09C91]
      94 [-]: CALL R5 1 1  
      95 [-]: SETTABLEKS R5 R4 K41 ["lastSlot"]
L17:  96 [-]: GETIMPORT R5 42 [nil]
      97 [-]: FASTCALL1 62 R5 L18
      98 [-]: GETIMPORT R4 9 [nil]
      99 [-]: CALL R4 1 1  
L18: 100 [-]: JUMPIF R4 L19
     101 [-]: GETIMPORT R6 44 [nil]
     102 [-]: NAMECALL R4 R1 K45 [0xF2DEAF69]
     103 [-]: CALL R4 2 1  
     104 [-]: JUMPIF R4 L19
     105 [-]: LOADN R6 0   
     106 [-]: LOADN R7 2   
     107 [-]: NAMECALL R4 R2 K46 [0x4703255B]
     108 [-]: CALL R4 3 0  
L19: 109 [-]: GETIMPORT R6 44 [nil]
     110 [-]: NAMECALL R4 R1 K45 [0xF2DEAF69]
     111 [-]: CALL R4 2 1  
     112 [-]: JUMPIF R4 L20
     113 [-]: LOADN R6 11  
     114 [-]: LOADN R7 0   
     115 [-]: LOADN R8 2   
     116 [-]: NAMECALL R4 R2 K47 [0xC69087F6]
     117 [-]: CALL R4 4 0  
L20: 118 [-]: FASTCALL1 62 R1 L21
     119 [-]: MOVE R5 R1   
     120 [-]: GETIMPORT R4 9 [nil]
     121 [-]: CALL R4 1 1  
L21: 122 [-]: JUMPIF R4 L26
     123 [-]: LOADB R6 1   
     124 [-]: NAMECALL R4 R1 K48 [0x044B7BE8]
     125 [-]: CALL R4 2 0  
     126 [-]: GETUPVAL R7 2
     127 [-]: NOT R6 R7    
     128 [-]: NAMECALL R4 R1 K49 [0x768274D6]
     129 [-]: CALL R4 2 0  
     130 [-]: FASTCALL1 62 R2 L22
     131 [-]: MOVE R5 R2   
     132 [-]: GETIMPORT R4 9 [nil]
     133 [-]: CALL R4 1 1  
L22: 134 [-]: JUMPIF R4 L24
     135 [-]: NAMECALL R4 R2 K50 [0x2676DEEE]
     136 [-]: CALL R4 1 1  
     137 [-]: FASTCALL1 62 R4 L23
     138 [-]: MOVE R6 R4   
     139 [-]: GETIMPORT R5 9 [nil]
     140 [-]: CALL R5 1 1  
L23: 141 [-]: JUMPIF R5 L24
     142 [-]: LOADB R7 1   
     143 [-]: NAMECALL R5 R4 K48 [0x044B7BE8]
     144 [-]: CALL R5 2 0  
     145 [-]: GETUPVAL R8 2
     146 [-]: NOT R7 R8    
     147 [-]: NAMECALL R5 R4 K49 [0x768274D6]
     148 [-]: CALL R5 2 0  
L24: 149 [-]: GETUPVAL R4 9
     150 [-]: JUMPIFNOT R4 L26
     151 [-]: NAMECALL R4 R1 K51 [0x0B4BCFB6]
     152 [-]: CALL R4 1 1  
     153 [-]: FASTCALL1 62 R4 L25
     154 [-]: MOVE R6 R4   
     155 [-]: GETIMPORT R5 9 [nil]
     156 [-]: CALL R5 1 1  
L25: 157 [-]: JUMPIF R5 L26
     158 [-]: MOVE R7 R1   
     159 [-]: LOADN R8 100 
     160 [-]: NAMECALL R5 R4 K52 [0xA97A9C68]
     161 [-]: CALL R5 3 0  
L26: 162 [-]: GETIMPORT R4 3 [nil]
     163 [-]: NAMECALL R4 R4 K53 [0xCD73323E]
     164 [-]: CALL R4 1 1  
     165 [-]: FASTCALL1 62 R4 L27
     166 [-]: MOVE R6 R4   
     167 [-]: GETIMPORT R5 9 [nil]
     168 [-]: CALL R5 1 1  
L27: 169 [-]: JUMPIF R5 L30
     170 [-]: GETUPVAL R5 2
     171 [-]: JUMPIFNOT R5 L28
     172 [-]: MOVE R7 R4   
     173 [-]: NAMECALL R5 R4 K54 [0xA5AD8E87]
     174 [-]: CALL R5 2 0  
     175 [-]: GETIMPORT R7 56 [nil]
     176 [-]: LOADN R8 0   
     177 [-]: LOADN R9 3   
     178 [-]: LOADK R10 K57 [-0.25]
     179 [-]: CALL R7 3 1  
     180 [-]: GETIMPORT R8 59 [nil]
     181 [-]: CALL R8 0 1  
     182 [-]: GETIMPORT R9 56 [nil]
     183 [-]: LOADN R10 0  
     184 [-]: LOADK R11 K60 [1.5]
     185 [-]: LOADN R12 -1 
     186 [-]: CALL R9 3 1  
     187 [-]: GETIMPORT R10 59 [nil]
     188 [-]: CALL R10 0 -1
     189 [-]: NAMECALL R5 R4 K61 [0xFF269DE7]
     190 [-]: CALL R5 -1 0 
     191 [-]: GETIMPORT R5 3 [nil]
     192 [-]: LOADK R7 K62 ["Wheel"]
     193 [-]: LOADN R8 11  
     194 [-]: LOADB R9 0   
     195 [-]: NAMECALL R5 R5 K63 [0xAADE900E]
     196 [-]: CALL R5 4 0  
     197 [-]: JUMP L30
    
L28: 198 [-]: GETIMPORT R5 65 [nil]
     199 [-]: JUMPXEQKNIL R5 L30
     200 [-]: MOVE R7 R1   
     201 [-]: NAMECALL R5 R4 K54 [0xA5AD8E87]
     202 [-]: CALL R5 2 0  
     203 [-]: GETIMPORT R8 65 [nil]
     204 [-]: FASTCALL1 53 R8 L29
     205 [-]: GETIMPORT R7 67 [nil]
     206 [-]: CALL R7 1 -1 
L29: 207 [-]: NAMECALL R5 R4 K61 [0xFF269DE7]
     208 [-]: CALL R5 -1 0 
L30: 209 [-]: GETUPVAL R6 10
     210 [-]: GETTABLEKS R5 R6 K68 [0x659D451F]
     211 [-]: GETIMPORT R6 70 [nil]
     212 [-]: CALL R5 1 0  
     213 [-]: GETIMPORT R5 73 [nil]
     214 [-]: CALL R5 0 1  
     215 [-]: JUMPIF R5 L31
     216 [-]: GETIMPORT R5 3 [nil]
     217 [-]: LOADB R7 1   
     218 [-]: NAMECALL R5 R5 K74 [0x5477B639]
     219 [-]: CALL R5 2 0  
L31: 220 [-]: GETIMPORT R5 3 [nil]
     221 [-]: LOADK R7 K75 ["FloatingHint1"]
     222 [-]: LOADN R8 10  
     223 [-]: LOADN R9 0   
     224 [-]: NAMECALL R5 R5 K76 [0x67BC869F]
     225 [-]: CALL R5 4 0  
     226 [-]: GETIMPORT R5 3 [nil]
     227 [-]: LOADK R7 K62 ["Wheel"]
     228 [-]: LOADN R8 10  
     229 [-]: LOADN R9 0   
     230 [-]: NAMECALL R5 R5 K76 [0x67BC869F]
     231 [-]: CALL R5 4 0  
     232 [-]: GETIMPORT R5 3 [nil]
     233 [-]: LOADK R7 K62 ["Wheel"]
     234 [-]: LOADN R8 9   
     235 [-]: GETUPVAL R9 11
     236 [-]: NAMECALL R5 R5 K76 [0x67BC869F]
     237 [-]: CALL R5 4 0  
     238 [-]: GETIMPORT R5 3 [nil]
     239 [-]: LOADK R7 K62 ["Wheel"]
     240 [-]: LOADN R8 0   
     241 [-]: LOADN R9 -50 
     242 [-]: NAMECALL R5 R5 K76 [0x67BC869F]
     243 [-]: CALL R5 4 0  
     244 [-]: GETIMPORT R5 3 [nil]
     245 [-]: LOADK R7 K62 ["Wheel"]
     246 [-]: LOADN R8 4   
     247 [-]: LOADN R9 3000
     248 [-]: NAMECALL R5 R5 K76 [0x67BC869F]
     249 [-]: CALL R5 4 0  
     250 [-]: GETIMPORT R5 3 [nil]
     251 [-]: LOADK R7 K62 ["Wheel"]
     252 [-]: LOADN R8 5   
     253 [-]: LOADN R9 75  
     254 [-]: NAMECALL R5 R5 K76 [0x67BC869F]
     255 [-]: CALL R5 4 0  
     256 [-]: GETIMPORT R5 3 [nil]
     257 [-]: LOADK R7 K62 ["Wheel"]
     258 [-]: LOADN R8 6   
     259 [-]: LOADN R9 75  
     260 [-]: NAMECALL R5 R5 K76 [0x67BC869F]
     261 [-]: CALL R5 4 0  
     262 [-]: GETIMPORT R5 3 [nil]
     263 [-]: LOADK R7 K77 ["Bg"]
     264 [-]: LOADN R8 0   
     265 [-]: LOADN R9 -1000
     266 [-]: NAMECALL R5 R5 K76 [0x67BC869F]
     267 [-]: CALL R5 4 0  
     268 [-]: GETIMPORT R5 3 [nil]
     269 [-]: LOADK R7 K77 ["Bg"]
     270 [-]: LOADN R8 12  
     271 [-]: LOADN R9 4000
     272 [-]: NAMECALL R5 R5 K76 [0x67BC869F]
     273 [-]: CALL R5 4 0  
     274 [-]: GETIMPORT R5 3 [nil]
     275 [-]: LOADK R7 K77 ["Bg"]
     276 [-]: LOADN R8 13  
     277 [-]: LOADN R9 2000
     278 [-]: NAMECALL R5 R5 K76 [0x67BC869F]
     279 [-]: CALL R5 4 0  
     280 [-]: GETIMPORT R5 3 [nil]
     281 [-]: LOADK R7 K77 ["Bg"]
     282 [-]: LOADN R8 4   
     283 [-]: LOADN R9 8000
     284 [-]: NAMECALL R5 R5 K76 [0x67BC869F]
     285 [-]: CALL R5 4 0  
     286 [-]: GETIMPORT R5 3 [nil]
     287 [-]: LOADK R7 K77 ["Bg"]
     288 [-]: LOADN R8 10  
     289 [-]: LOADN R9 0   
     290 [-]: NAMECALL R5 R5 K76 [0x67BC869F]
     291 [-]: CALL R5 4 0  
     292 [-]: GETIMPORT R5 3 [nil]
     293 [-]: LOADK R7 K78 ["Wheel.Dots"]
     294 [-]: GETIMPORT R8 80 [nil]
     295 [-]: NAMECALL R5 R5 K81 [0xD5181643]
     296 [-]: CALL R5 3 0  
     297 [-]: GETIMPORT R5 3 [nil]
     298 [-]: LOADK R7 K77 ["Bg"]
     299 [-]: GETIMPORT R8 80 [nil]
     300 [-]: NAMECALL R5 R5 K81 [0xD5181643]
     301 [-]: CALL R5 3 0  
     302 [-]: GETUPVAL R5 12
     303 [-]: CALL R5 0 0  
     304 [-]: GETUPVAL R5 13
     305 [-]: CALL R5 0 0  
     306 [-]: GETUPVAL R5 14
     307 [-]: CALL R5 0 0  
     308 [-]: GETUPVAL R5 15
     309 [-]: CALL R5 0 0  
     310 [-]: GETIMPORT R5 33 [nil]
     311 [-]: NAMECALL R5 R5 K82 [0x33307F92]
     312 [-]: CALL R5 1 1  
     313 [-]: FASTCALL1 62 R5 L32
     314 [-]: MOVE R7 R5   
     315 [-]: GETIMPORT R6 9 [nil]
     316 [-]: CALL R6 1 1  
L32: 317 [-]: JUMPIF R6 L33
     318 [-]: GETIMPORT R6 84 [nil]
     319 [-]: LOADK R7 K85 ["ScopeDebug: Hide from OrokinLock"]
     320 [-]: CALL R6 1 0  
     321 [-]: LOADK R8 K86 ["HideReticle"]
     322 [-]: LOADK R9 K87 [""]
     323 [-]: NAMECALL R6 R5 K88 [0xE4162EED]
     324 [-]: CALL R6 3 0  
     325 [-]: LOADK R8 K89 ["HideAbilityDots"]
     326 [-]: LOADK R9 K87 [""]
     327 [-]: NAMECALL R6 R5 K88 [0xE4162EED]
     328 [-]: CALL R6 3 0  
L33: 329 [-]: GETIMPORT R6 3 [nil]
     330 [-]: LOADK R8 K90 ["_root"]
     331 [-]: LOADN R9 11  
     332 [-]: LOADB R10 0  
     333 [-]: NAMECALL R6 R6 K63 [0xAADE900E]
     334 [-]: CALL R6 4 0  
     335 [-]: GETUPVAL R6 16
     336 [-]: CALL R6 0 0  
     337 [-]: GETIMPORT R6 92 [nil]
     338 [-]: CALL R6 0 1  
     339 [-]: JUMPIFNOT R6 L37
     340 [-]: GETIMPORT R7 94 [nil]
     341 [-]: FASTCALL1 62 R7 L34
     342 [-]: GETIMPORT R6 9 [nil]
     343 [-]: CALL R6 1 1  
L34: 344 [-]: JUMPIF R6 L35
     345 [-]: GETIMPORT R6 94 [nil]
     346 [-]: CALL R6 0 0  
L35: 347 [-]: GETIMPORT R7 96 [nil]
     348 [-]: FASTCALL1 62 R7 L36
     349 [-]: GETIMPORT R6 9 [nil]
     350 [-]: CALL R6 1 1  
L36: 351 [-]: JUMPIF R6 L37
     352 [-]: GETIMPORT R6 96 [nil]
     353 [-]: CALL R6 0 0  
L37: 354 [-]: RETURN R0 0  


; Name:            
; Defined at line: 1605
; #Upvalues:       19
; #Parameters:     0
; Is_vararg:       0
; Max Stack Size:  12

       0 [-]: GETIMPORT R0 1 [nil]
       1 [-]: NAMECALL R0 R0 K2 [0x78298275]
       2 [-]: CALL R0 1 1  
       3 [-]: FASTCALL1 62 R0 L0
       4 [-]: MOVE R2 R0   
       5 [-]: GETIMPORT R1 4 [nil]
       6 [-]: CALL R1 1 1  
L 0:   7 [-]: JUMPIF R1 L1 
       8 [-]: NAMECALL R1 R0 K5 [0xD2715720]
       9 [-]: CALL R1 1 1  
      10 [-]: LOADN R2 0   
      11 [-]: JUMPIFNOTLE R1 R2 L1
      12 [-]: GETUPVAL R1 0
      13 [-]: MOVE R2 R0   
      14 [-]: CALL R1 1 0  
      15 [-]: RETURN R0 0  
L 1:  16 [-]: GETUPVAL R1 1
      17 [-]: JUMPIF R1 L2 
      18 [-]: GETUPVAL R1 2
      19 [-]: CALL R1 0 0  
L 2:  20 [-]: GETIMPORT R1 7 [nil]
      21 [-]: CALL R1 0 1  
      22 [-]: GETUPVAL R2 3
      23 [-]: JUMPIF R2 L4 
      24 [-]: GETUPVAL R3 4
      25 [-]: ADD R2 R3 R1 
      26 [-]: SETUPVAL R2 4
      27 [-]: GETUPVAL R2 4
      28 [-]: GETIMPORT R3 9 [nil]
      29 [-]: JUMPIFNOTLT R2 R3 L3
      30 [-]: RETURN R0 0  
L 3:  31 [-]: LOADB R2 1   
      32 [-]: SETUPVAL R2 3
L 4:  33 [-]: GETUPVAL R2 5
      34 [-]: JUMPIF R2 L5 
      35 [-]: GETUPVAL R2 6
      36 [-]: CALL R2 0 0  
      37 [-]: GETUPVAL R2 7
      38 [-]: CALL R2 0 0  
L 5:  39 [-]: GETIMPORT R3 11 [nil]
      40 [-]: FASTCALL1 62 R3 L6
      41 [-]: GETIMPORT R2 4 [nil]
      42 [-]: CALL R2 1 1  
L 6:  43 [-]: JUMPIF R2 L7 
      44 [-]: GETUPVAL R2 5
      45 [-]: JUMPIF R2 L8 
L 7:  46 [-]: RETURN R0 0  
L 8:  47 [-]: GETIMPORT R2 11 [nil]
      48 [-]: MOVE R4 R1   
      49 [-]: NAMECALL R2 R2 K12 [0x8A8C8D5A]
      50 [-]: CALL R2 2 0  
      51 [-]: GETUPVAL R2 8
      52 [-]: CALL R2 0 0  
      53 [-]: GETUPVAL R3 9
      54 [-]: FASTCALL1 62 R3 L9
      55 [-]: GETIMPORT R2 4 [nil]
      56 [-]: CALL R2 1 1  
L 9:  57 [-]: JUMPIFNOT R2 L13
      58 [-]: GETUPVAL R2 10
      59 [-]: JUMPIF R2 L13
      60 [-]: GETIMPORT R2 11 [nil]
      61 [-]: NAMECALL R2 R2 K13 [0xA1653871]
      62 [-]: CALL R2 1 1  
      63 [-]: FASTCALL1 62 R2 L10
      64 [-]: MOVE R4 R2   
      65 [-]: GETIMPORT R3 4 [nil]
      66 [-]: CALL R3 1 1  
L10:  67 [-]: JUMPIF R3 L13
      68 [-]: GETIMPORT R5 15 [nil]
      69 [-]: GETIMPORT R6 17 [nil]
      70 [-]: GETIMPORT R7 19 [nil]
      71 [-]: LOADN R8 0   
      72 [-]: LOADK R9 K20 [1.25]
      73 [-]: LOADK R10 K21 [0.87]
      74 [-]: CALL R7 3 1  
      75 [-]: GETIMPORT R8 23 [nil]
      76 [-]: LOADN R9 160 
      77 [-]: LOADN R10 -30
      78 [-]: LOADN R11 0  
      79 [-]: CALL R8 3 -1 
      80 [-]: NAMECALL R3 R2 K24 [0x47901F07]
      81 [-]: CALL R3 -1 1 
      82 [-]: SETUPVAL R3 9
      83 [-]: GETUPVAL R4 9
      84 [-]: FASTCALL1 62 R4 L11
      85 [-]: GETIMPORT R3 4 [nil]
      86 [-]: CALL R3 1 1  
L11:  87 [-]: JUMPIF R3 L12
      88 [-]: GETUPVAL R3 9
      89 [-]: LOADB R5 1   
      90 [-]: NAMECALL R3 R3 K25 [0x044B7BE8]
      91 [-]: CALL R3 2 0  
L12:  92 [-]: GETUPVAL R4 11
      93 [-]: GETUPVAL R5 9
      94 [-]: FASTCALL2 52 R4 R5 L13
      95 [-]: GETIMPORT R3 28 [nil]
      96 [-]: CALL R3 2 0  
L13:  97 [-]: GETIMPORT R3 31 [nil]
      98 [-]: FASTCALL1 62 R3 L14
      99 [-]: GETIMPORT R2 4 [nil]
     100 [-]: CALL R2 1 1  
L14: 101 [-]: JUMPIF R2 L17
L15: 102 [-]: GETUPVAL R3 12
     103 [-]: GETTABLEKS R2 R3 K32 ["Count"]
     104 [-]: GETIMPORT R4 34 [nil]
     105 [-]: JUMPIF R4 L16
     106 [-]: GETIMPORT R4 36 [nil]
L16: 107 [-]: LENGTH R3 R4 
     108 [-]: JUMPIFNOTLT R2 R3 L17
     109 [-]: GETUPVAL R2 12
     110 [-]: NAMECALL R2 R2 K37 [0xBAD4316F]
     111 [-]: CALL R2 1 0  
     112 [-]: JUMPBACK L15 
L17: 113 [-]: GETUPVAL R2 12
     114 [-]: MOVE R4 R1   
     115 [-]: NAMECALL R2 R2 K38 [0xFAA69527]
     116 [-]: CALL R2 2 0  
     117 [-]: GETUPVAL R2 13
     118 [-]: JUMPIFNOT R2 L20
     119 [-]: GETIMPORT R3 40 [nil]
     120 [-]: FASTCALL1 62 R3 L18
     121 [-]: GETIMPORT R2 4 [nil]
     122 [-]: CALL R2 1 1  
L18: 123 [-]: JUMPIF R2 L20
     124 [-]: GETUPVAL R3 14
     125 [-]: GETIMPORT R5 7 [nil]
     126 [-]: CALL R5 0 1  
     127 [-]: MULK R4 R5 K41 [0.34999999999999998]
     128 [-]: ADD R2 R3 R4 
     129 [-]: SETUPVAL R2 14
     130 [-]: GETIMPORT R2 43 [nil]
     131 [-]: LOADK R3 K44 [0.5]
     132 [-]: LOADK R4 K45 [1.5]
     133 [-]: GETUPVAL R6 15
     134 [-]: FASTCALL2K 21 R6 K46 L19 [5]
     135 [-]: LOADK R7 K46 [5]
     136 [-]: GETIMPORT R5 49 [nil]
     137 [-]: CALL R5 2 1  
L19: 138 [-]: CALL R2 3 1  
     139 [-]: GETUPVAL R4 14
     140 [-]: LOADN R6 1   
     141 [-]: GETUPVAL R7 15
     142 [-]: SUB R5 R6 R7 
     143 [-]: MUL R3 R4 R5 
     144 [-]: LOADK R5 K44 [0.5]
     145 [-]: LOADN R8 1   
     146 [-]: GETUPVAL R9 15
     147 [-]: SUB R7 R8 R9 
     148 [-]: MULK R6 R7 K44 [0.5]
     149 [-]: ADD R4 R5 R6 
     150 [-]: GETIMPORT R5 40 [nil]
     151 [-]: GETUPVAL R7 16
     152 [-]: LOADK R8 K44 [0.5]
     153 [-]: MOVE R9 R2   
     154 [-]: MOVE R10 R3  
     155 [-]: MOVE R11 R4  
     156 [-]: NAMECALL R5 R5 K50 [0x830EEA67]
     157 [-]: CALL R5 6 0  
L20: 158 [-]: GETIMPORT R4 11 [nil]
     159 [-]: NAMECALL R4 R4 K52 [0x906FAF80]
     160 [-]: CALL R4 1 1  
     161 [-]: GETIMPORT R6 11 [nil]
     162 [-]: NAMECALL R6 R6 K54 [0x091C120E]
     163 [-]: CALL R6 1 1  
     164 [-]: DIVK R5 R6 K53 [2]
     165 [-]: SUB R3 R4 R5 
     166 [-]: DIVK R2 R3 K51 [100]
     167 [-]: GETIMPORT R5 11 [nil]
     168 [-]: NAMECALL R5 R5 K55 [0x916FB113]
     169 [-]: CALL R5 1 1  
     170 [-]: GETIMPORT R7 11 [nil]
     171 [-]: NAMECALL R7 R7 K56 [0x2CC9D281]
     172 [-]: CALL R7 1 1  
     173 [-]: DIVK R6 R7 K53 [2]
     174 [-]: SUB R4 R5 R6 
     175 [-]: DIVK R3 R4 K51 [100]
     176 [-]: GETIMPORT R4 23 [nil]
     177 [-]: GETIMPORT R5 58 [nil]
     178 [-]: MOVE R6 R2   
     179 [-]: LOADN R7 -10 
     180 [-]: LOADN R8 20  
     181 [-]: CALL R5 3 1  
     182 [-]: GETIMPORT R7 58 [nil]
     183 [-]: MOVE R8 R3   
     184 [-]: LOADN R9 -10 
     185 [-]: LOADN R10 10 
     186 [-]: CALL R7 3 1  
     187 [-]: SUBK R6 R7 K59 [20]
     188 [-]: LOADN R7 0   
     189 [-]: CALL R4 3 1  
     190 [-]: GETUPVAL R6 18
     191 [-]: GETTABLEKS R5 R6 K60 [0xFBB210BD]
     192 [-]: MOVE R6 R4   
     193 [-]: GETUPVAL R7 17
     194 [-]: CALL R5 2 1  
     195 [-]: SETUPVAL R5 17
     196 [-]: RETURN R0 0  


; Name:            
; Defined at line: 1673
; #Upvalues:       1
; #Parameters:     0
; Is_vararg:       0
; Max Stack Size:  1

       0 [-]: GETUPVAL R0 0
       1 [-]: CALL R0 0 0  
       2 [-]: LOADB R0 1   
       3 [-]: RETURN R0 1  


; Name:            
; Defined at line: 1678
; #Upvalues:       1
; #Parameters:     0
; Is_vararg:       0
; Max Stack Size:  1

       0 [-]: GETUPVAL R0 0
       1 [-]: CALL R0 0 0  
       2 [-]: LOADB R0 1   
       3 [-]: RETURN R0 1  


; Name:            
; Defined at line: 1683
; #Upvalues:       1
; #Parameters:     0
; Is_vararg:       0
; Max Stack Size:  1

       0 [-]: GETUPVAL R0 0
       1 [-]: JUMPIF R0 L0 
L 0:   2 [-]: RETURN R0 0  


; Name:            
; Defined at line: 1688
; #Upvalues:       0
; #Parameters:     0
; Is_vararg:       0
; Max Stack Size:  1

       0 [-]: LOADB R0 1   
       1 [-]: RETURN R0 1  


; Name:            
; Defined at line: 1695
; #Upvalues:       2
; #Parameters:     0
; Is_vararg:       0
; Max Stack Size:  1

       0 [-]: GETUPVAL R0 0
       1 [-]: JUMPIF R0 L0 
       2 [-]: GETUPVAL R0 1
       3 [-]: CALL R0 0 0  
L 0:   4 [-]: LOADB R0 1   
       5 [-]: RETURN R0 1  


; Name:            
; Defined at line: 1702
; #Upvalues:       1
; #Parameters:     0
; Is_vararg:       0
; Max Stack Size:  1

       0 [-]: GETUPVAL R0 0
       1 [-]: RETURN R0 1  


; Name:            
; Defined at line: 1706
; #Upvalues:       4
; #Parameters:     1
; Is_vararg:       0
; Max Stack Size:  8

       0 [-]: GETUPVAL R2 0
       1 [-]: GETUPVAL R3 1
       2 [-]: GETTABLE R1 R2 R3
       3 [-]: GETUPVAL R2 2
       4 [-]: JUMPIF R2 L1 
       5 [-]: FASTCALL1 62 R1 L0
       6 [-]: MOVE R3 R1   
       7 [-]: GETIMPORT R2 1 [nil]
       8 [-]: CALL R2 1 1  
L 0:   9 [-]: JUMPIF R2 L1 
      10 [-]: GETTABLEKS R2 R1 K2 ["mLocked"]
      11 [-]: JUMPIF R2 L1 
      12 [-]: GETTABLEKS R5 R1 K3 ["Focus"]
      13 [-]: GETIMPORT R6 5 [nil]
      14 [-]: MOVE R7 R0   
      15 [-]: CALL R6 1 1  
      16 [-]: ADD R4 R5 R6 
      17 [-]: NAMECALL R2 R1 K6 [0x0417AD4A]
      18 [-]: CALL R2 2 0  
      19 [-]: GETUPVAL R3 3
      20 [-]: GETTABLEKS R2 R3 K7 [0x659D451F]
      21 [-]: GETIMPORT R3 9 [nil]
      22 [-]: CALL R2 1 0  
L 1:  23 [-]: RETURN R0 0  


; Name:            
; Defined at line: 1714
; #Upvalues:       1
; #Parameters:     2
; Is_vararg:       0
; Max Stack Size:  4

       0 [-]: GETUPVAL R2 0
       1 [-]: MOVE R3 R1   
       2 [-]: CALL R2 1 0  
       3 [-]: RETURN R0 0  


; Name:            
; Defined at line: 1718
; #Upvalues:       1
; #Parameters:     0
; Is_vararg:       0
; Max Stack Size:  2

       0 [-]: GETIMPORT R0 2 [nil]
       1 [-]: CALL R0 0 1  
       2 [-]: JUMPIFNOT R0 L0
       3 [-]: LOADB R0 0   
       4 [-]: RETURN R0 1  
L 0:   5 [-]: GETUPVAL R0 0
       6 [-]: LOADN R1 1   
       7 [-]: CALL R0 1 0  
       8 [-]: LOADB R0 1   
       9 [-]: RETURN R0 1  


; Name:            
; Defined at line: 1726
; #Upvalues:       1
; #Parameters:     0
; Is_vararg:       0
; Max Stack Size:  2

       0 [-]: GETUPVAL R0 0
       1 [-]: LOADN R1 -1  
       2 [-]: CALL R0 1 0  
       3 [-]: LOADB R0 1   
       4 [-]: RETURN R0 1  


; Name:            
; Defined at line: 1731
; #Upvalues:       1
; #Parameters:     0
; Is_vararg:       0
; Max Stack Size:  2

       0 [-]: GETUPVAL R0 0
       1 [-]: LOADN R1 -1  
       2 [-]: CALL R0 1 0  
       3 [-]: LOADB R0 1   
       4 [-]: RETURN R0 1  


; Name:            
; Defined at line: 1736
; #Upvalues:       1
; #Parameters:     0
; Is_vararg:       0
; Max Stack Size:  2

       0 [-]: GETUPVAL R0 0
       1 [-]: LOADN R1 1   
       2 [-]: CALL R0 1 0  
       3 [-]: LOADB R0 1   
       4 [-]: RETURN R0 1  


; Name:            
; Defined at line: 1741
; #Upvalues:       1
; #Parameters:     0
; Is_vararg:       0
; Max Stack Size:  2

       0 [-]: GETUPVAL R0 0
       1 [-]: LOADN R1 -1  
       2 [-]: CALL R0 1 0  
       3 [-]: LOADB R0 1   
       4 [-]: RETURN R0 1  


; Name:            
; Defined at line: 1746
; #Upvalues:       3
; #Parameters:     1
; Is_vararg:       0
; Max Stack Size:  4

       0 [-]: GETUPVAL R1 0
       1 [-]: GETUPVAL R2 1
       2 [-]: LOADB R3 0   
       3 [-]: CALL R1 2 0  
       4 [-]: LOADN R1 1   
       5 [-]: JUMPIFNOTLT R0 R1 L0
       6 [-]: GETUPVAL R1 2
       7 [-]: ADD R0 R0 R1 
       8 [-]: JUMP L1
     
L 0:   9 [-]: GETUPVAL R1 2
      10 [-]: JUMPIFNOTLT R1 R0 L1
      11 [-]: GETUPVAL R1 2
      12 [-]: SUB R0 R0 R1 
L 1:  13 [-]: SETUPVAL R0 1
      14 [-]: GETUPVAL R1 0
      15 [-]: GETUPVAL R2 1
      16 [-]: LOADB R3 1   
      17 [-]: CALL R1 2 0  
      18 [-]: RETURN R0 0  


; Name:            
; Defined at line: 1757
; #Upvalues:       2
; #Parameters:     0
; Is_vararg:       0
; Max Stack Size:  3

       0 [-]: GETUPVAL R0 0
       1 [-]: GETUPVAL R2 1
       2 [-]: SUBK R1 R2 K0 [1]
       3 [-]: CALL R0 1 0  
       4 [-]: LOADB R0 1   
       5 [-]: RETURN R0 1  


; Name:            
; Defined at line: 1762
; #Upvalues:       2
; #Parameters:     0
; Is_vararg:       0
; Max Stack Size:  3

       0 [-]: GETUPVAL R0 0
       1 [-]: GETUPVAL R2 1
       2 [-]: ADDK R1 R2 K0 [1]
       3 [-]: CALL R0 1 0  
       4 [-]: LOADB R0 1   
       5 [-]: RETURN R0 1  


; Name:            
; Defined at line: 1767
; #Upvalues:       2
; #Parameters:     0
; Is_vararg:       0
; Max Stack Size:  3

       0 [-]: GETUPVAL R0 0
       1 [-]: GETUPVAL R2 1
       2 [-]: SUBK R1 R2 K0 [1]
       3 [-]: CALL R0 1 0  
       4 [-]: LOADB R0 1   
       5 [-]: RETURN R0 1  


; Name:            
; Defined at line: 1772
; #Upvalues:       2
; #Parameters:     0
; Is_vararg:       0
; Max Stack Size:  3

       0 [-]: GETUPVAL R0 0
       1 [-]: GETUPVAL R2 1
       2 [-]: ADDK R1 R2 K0 [1]
       3 [-]: CALL R0 1 0  
       4 [-]: LOADB R0 1   
       5 [-]: RETURN R0 1  


; Name:            
; Defined at line: 1777
; #Upvalues:       1
; #Parameters:     1
; Is_vararg:       0
; Max Stack Size:  3

       0 [-]: GETIMPORT R1 1 [nil]
       1 [-]: MOVE R2 R0   
       2 [-]: CALL R1 1 1  
       3 [-]: MOVE R0 R1   
       4 [-]: GETUPVAL R1 0
       5 [-]: JUMPIFNOT R1 L2
       6 [-]: FASTCALL1 2 R0 L0
       7 [-]: MOVE R2 R0   
       8 [-]: GETIMPORT R1 4 [nil]
       9 [-]: CALL R1 1 1  
L 0:  10 [-]: LOADK R2 K5 [0.5]
      11 [-]: JUMPIFNOTLT R2 R1 L2
      12 [-]: LOADB R1 0   
      13 [-]: SETUPVAL R1 0
      14 [-]: LOADN R2 0   
      15 [-]: JUMPIFNOTLT R2 R0 L1
      16 [-]: LOADN R1 1   
      17 [-]: RETURN R1 1  
L 1:  18 [-]: LOADN R1 -1  
      19 [-]: RETURN R1 1  
L 2:  20 [-]: LOADNIL R1   
      21 [-]: RETURN R1 1  


; Name:            
; Defined at line: 1786
; #Upvalues:       2
; #Parameters:     2
; Is_vararg:       0
; Max Stack Size:  4

       0 [-]: GETUPVAL R2 0
       1 [-]: MOVE R3 R1   
       2 [-]: CALL R2 1 1  
       3 [-]: MOVE R1 R2   
       4 [-]: JUMPIFNOT R1 L0
       5 [-]: GETUPVAL R2 1
       6 [-]: MOVE R3 R1   
       7 [-]: CALL R2 1 0  
L 0:   8 [-]: LOADB R2 1   
       9 [-]: RETURN R2 1  


; Name:            
; Defined at line: 1794
; #Upvalues:       1
; #Parameters:     2
; Is_vararg:       0
; Max Stack Size:  3

       0 [-]: LOADB R2 1   
       1 [-]: SETUPVAL R2 0
       2 [-]: LOADB R2 1   
       3 [-]: RETURN R2 1  


; Name:            
; Defined at line: 1799
; #Upvalues:       3
; #Parameters:     2
; Is_vararg:       0
; Max Stack Size:  5

       0 [-]: GETUPVAL R2 0
       1 [-]: MOVE R3 R1   
       2 [-]: CALL R2 1 1  
       3 [-]: MOVE R1 R2   
       4 [-]: JUMPIFNOT R1 L0
       5 [-]: GETUPVAL R2 1
       6 [-]: GETUPVAL R4 2
       7 [-]: ADD R3 R4 R1 
       8 [-]: CALL R2 1 0  
L 0:   9 [-]: LOADB R2 1   
      10 [-]: RETURN R2 1  


; Name:            
; Defined at line: 1807
; #Upvalues:       1
; #Parameters:     2
; Is_vararg:       0
; Max Stack Size:  3

       0 [-]: LOADB R2 1   
       1 [-]: SETUPVAL R2 0
       2 [-]: LOADB R2 1   
       3 [-]: RETURN R2 1  


; Name:            
; Defined at line: 1812
; #Upvalues:       2
; #Parameters:     1
; Is_vararg:       0
; Max Stack Size:  4

       0 [-]: GETIMPORT R1 1 [nil]
       1 [-]: MOVE R2 R0   
       2 [-]: CALL R1 1 1  
       3 [-]: MOVE R0 R1   
       4 [-]: GETUPVAL R3 0
       5 [-]: GETTABLE R2 R3 R0
       6 [-]: FASTCALL1 62 R2 L0
       7 [-]: GETIMPORT R1 3 [nil]
       8 [-]: CALL R1 1 1  
L 0:   9 [-]: JUMPIF R1 L1 
      10 [-]: GETUPVAL R1 1
      11 [-]: MOVE R2 R0   
      12 [-]: CALL R1 1 0  
L 1:  13 [-]: RETURN R0 0  


; Name:            
; Defined at line: 1819
; #Upvalues:       0
; #Parameters:     1
; Is_vararg:       0
; Max Stack Size:  3

       0 [-]: GETIMPORT R1 1 [nil]
       1 [-]: MOVE R2 R0   
       2 [-]: CALL R1 1 1  
       3 [-]: MOVE R0 R1   
       4 [-]: RETURN R0 0  


; Name:            
; Defined at line: 1823
; #Upvalues:       1
; #Parameters:     1
; Is_vararg:       0
; Max Stack Size:  3

       0 [-]: GETIMPORT R1 1 [nil]
       1 [-]: MOVE R2 R0   
       2 [-]: CALL R1 1 1  
       3 [-]: MOVE R0 R1   
       4 [-]: GETIMPORT R1 4 [nil]
       5 [-]: CALL R1 0 1  
       6 [-]: JUMPIFNOT R1 L0
       7 [-]: GETUPVAL R1 0
       8 [-]: LOADN R2 1   
       9 [-]: CALL R1 1 0  
L 0:  10 [-]: RETURN R0 0  



