; This file has been disassembled using luadec 2.0.2 by sztupy (modified by Reversive)

; Name:            
; Defined at line: 0
; #Upvalues:       0
; #Parameters:     0
; Is_vararg:       2
; Max Stack Size:  34

  1 [-]: GETGLOBAL R0 K0        ; R0 := 0x2d0fad09
  2 [-]: LOADK     R1 K1        ; R1 := "EE.Interface.Utilities"
  3 [-]: CALL      R0 2 2       ; R0 := R0(R1)
  4 [-]: GETGLOBAL R1 K0        ; R1 := 0x2d0fad09
  5 [-]: LOADK     R2 K2        ; R2 := "Lotus.Interface.UIStyleUtilities"
  6 [-]: CALL      R1 2 2       ; R1 := R1(R2)
  7 [-]: GETGLOBAL R2 K0        ; R2 := 0x2d0fad09
  8 [-]: LOADK     R3 K3        ; R3 := "Lotus.Interface.LotusUtilities"
  9 [-]: CALL      R2 2 2       ; R2 := R2(R3)
 10 [-]: LOADNIL   R3 R3        ; R3 := nil
 11 [-]: LOADK     R4 0         ; R4 := 0.000000
 12 [-]: LOADNIL   R5 R5        ; R5 := nil
 13 [-]: GETGLOBAL R6 K4        ; R6 := 0x78ca68a2
 14 [-]: LOADK     R7 0         ; R7 := 0.000000
 15 [-]: LOADK     R8 K5        ; R8 := 0.150000
 16 [-]: CALL      R6 3 2       ; R6 := R6(R7,R8)
 17 [-]: GETGLOBAL R7 K4        ; R7 := 0x78ca68a2
 18 [-]: LOADK     R8 0         ; R8 := 0.000000
 19 [-]: LOADK     R9 K5        ; R9 := 0.150000
 20 [-]: CALL      R7 3 2       ; R7 := R7(R8,R9)
 21 [-]: LOADK     R8 1         ; R8 := 1.000000
 22 [-]: NEWTABLE  R9 0 6       ; R9 := {}
 23 [-]: SETTABLE  R9 K6 K7     ; R9["x"] := 0.000000
 24 [-]: SETTABLE  R9 K8 K7     ; R9["y"] := 0.000000
 25 [-]: SETTABLE  R9 K9 K7     ; R9["tx"] := 0.000000
 26 [-]: SETTABLE  R9 K10 K7    ; R9["ty"] := 0.000000
 27 [-]: SETTABLE  R9 K11 K7    ; R9["z"] := 0.000000
 28 [-]: SETTABLE  R9 K12 K13   ; R9["dir"] := 1.000000
 29 [-]: LOADNIL   R10 R12      ; R10 := R11 := R12 := nil
 30 [-]: LOADK     R13 4        ; R13 := 4.000000
 31 [-]: NEWTABLE  R14 0 0      ; R14 := {}
 32 [-]: LOADK     R15 0        ; R15 := 0.000000
 33 [-]: NEWTABLE  R16 0 3      ; R16 := {}
 34 [-]: SETTABLE  R16 K14 K13  ; R16["SLIDE"] := 1.000000
 35 [-]: SETTABLE  R16 K15 K16  ; R16["LOCK"] := 2.000000
 36 [-]: SETTABLE  R16 K17 K18  ; R16["UNLOCKED_LOCK"] := 3.000000
 37 [-]: LOADBOOL  R17 0 0      ; R17 := false
 38 [-]: LOADBOOL  R18 0 0      ; R18 := false
 39 [-]: LOADBOOL  R19 0 0      ; R19 := false
 40 [-]: LOADNIL   R20 R20      ; R20 := nil
 41 [-]: LOADK     R21 K19      ; R21 := 16777138.000000
 42 [-]: LOADK     R22 K20      ; R22 := 8877891.000000
 43 [-]: CLOSURE   R23 0        ; R23 := closure(Function #1)
 44 [-]: CLOSURE   R24 1        ; R24 := closure(Function #2)
 45 [-]: MOVE      R0 R22       ; R0 := R22
 46 [-]: CLOSURE   R25 2        ; R25 := closure(Function #3)
 47 [-]: MOVE      R0 R18       ; R0 := R18
 48 [-]: MOVE      R0 R3        ; R0 := R3
 49 [-]: CLOSURE   R26 3        ; R26 := closure(Function #4)
 50 [-]: MOVE      R0 R18       ; R0 := R18
 51 [-]: CLOSURE   R27 4        ; R27 := closure(Function #5)
 52 [-]: MOVE      R0 R0        ; R0 := R0
 53 [-]: MOVE      R0 R8        ; R0 := R8
 54 [-]: CLOSURE   R28 5        ; R28 := closure(Function #6)
 55 [-]: MOVE      R0 R0        ; R0 := R0
 56 [-]: MOVE      R0 R5        ; R0 := R5
 57 [-]: CLOSURE   R29 6        ; R29 := closure(Function #7)
 58 [-]: MOVE      R0 R4        ; R0 := R4
 59 [-]: CLOSURE   R30 7        ; R30 := closure(Function #8)
 60 [-]: MOVE      R0 R4        ; R0 := R4
 61 [-]: MOVE      R0 R5        ; R0 := R5
 62 [-]: MOVE      R0 R2        ; R0 := R2
 63 [-]: MOVE      R0 R3        ; R0 := R3
 64 [-]: MOVE      R0 R19       ; R0 := R19
 65 [-]: MOVE      R0 R17       ; R0 := R17
 66 [-]: MOVE      R0 R9        ; R0 := R9
 67 [-]: MOVE      R0 R29       ; R0 := R29
 68 [-]: CLOSURE   R31 8        ; R31 := closure(Function #9)
 69 [-]: MOVE      R0 R30       ; R0 := R30
 70 [-]: MOVE      R0 R4        ; R0 := R4
 71 [-]: CLOSURE   R32 9        ; R32 := closure(Function #10)
 72 [-]: MOVE      R0 R14       ; R0 := R14
 73 [-]: MOVE      R0 R15       ; R0 := R15
 74 [-]: MOVE      R0 R26       ; R0 := R26
 75 [-]: MOVE      R0 R16       ; R0 := R16
 76 [-]: MOVE      R0 R30       ; R0 := R30
 77 [-]: MOVE      R0 R20       ; R0 := R20
 78 [-]: MOVE      R0 R23       ; R0 := R23
 79 [-]: CLOSURE   R33 10       ; R33 := closure(Function #11)
 80 [-]: MOVE      R0 R1        ; R0 := R1
 81 [-]: MOVE      R0 R2        ; R0 := R2
 82 [-]: MOVE      R0 R11       ; R0 := R11
 83 [-]: MOVE      R0 R12       ; R0 := R12
 84 [-]: SETGLOBAL R33 K21      ; Shutdown := R33
 85 [-]: CLOSURE   R33 11       ; R33 := closure(Function #12)
 86 [-]: MOVE      R0 R13       ; R0 := R13
 87 [-]: MOVE      R0 R1        ; R0 := R1
 88 [-]: MOVE      R0 R3        ; R0 := R3
 89 [-]: MOVE      R0 R15       ; R0 := R15
 90 [-]: MOVE      R0 R14       ; R0 := R14
 91 [-]: MOVE      R0 R16       ; R0 := R16
 92 [-]: MOVE      R0 R27       ; R0 := R27
 93 [-]: MOVE      R0 R2        ; R0 := R2
 94 [-]: MOVE      R0 R24       ; R0 := R24
 95 [-]: MOVE      R0 R32       ; R0 := R32
 96 [-]: MOVE      R0 R11       ; R0 := R11
 97 [-]: MOVE      R0 R12       ; R0 := R12
 98 [-]: SETGLOBAL R33 K22      ; Initialize := R33
 99 [-]: CLOSURE   R33 12       ; R33 := closure(Function #13)
100 [-]: MOVE      R0 R3        ; R0 := R3
101 [-]: MOVE      R0 R9        ; R0 := R9
102 [-]: MOVE      R0 R8        ; R0 := R8
103 [-]: MOVE      R0 R17       ; R0 := R17
104 [-]: MOVE      R0 R25       ; R0 := R25
105 [-]: MOVE      R0 R19       ; R0 := R19
106 [-]: MOVE      R0 R23       ; R0 := R23
107 [-]: MOVE      R0 R10       ; R0 := R10
108 [-]: SETGLOBAL R33 K23      ; Update := R33
109 [-]: CLOSURE   R33 13       ; R33 := closure(Function #14)
110 [-]: SETGLOBAL R33 K24      ; SupportsThemes := R33
111 [-]: CLOSURE   R33 14       ; R33 := closure(Function #15)
112 [-]: MOVE      R0 R32       ; R0 := R32
113 [-]: SETGLOBAL R33 K25      ; Next := R33
114 [-]: CLOSURE   R33 15       ; R33 := closure(Function #16)
115 [-]: MOVE      R0 R0        ; R0 := R0
116 [-]: MOVE      R0 R21       ; R0 := R21
117 [-]: SETGLOBAL R33 K26      ; ArrowRollOver := R33
118 [-]: CLOSURE   R33 16       ; R33 := closure(Function #17)
119 [-]: MOVE      R0 R22       ; R0 := R22
120 [-]: SETGLOBAL R33 K27      ; ArrowRollOut := R33
121 [-]: CLOSURE   R33 17       ; R33 := closure(Function #18)
122 [-]: MOVE      R0 R0        ; R0 := R0
123 [-]: MOVE      R0 R32       ; R0 := R32
124 [-]: SETGLOBAL R33 K28      ; ArrowSelected := R33
125 [-]: RETURN    R0 1         ; return 


; Function #1:
;
; Name:            
; Defined at line: 56
; #Upvalues:       0
; #Parameters:     0
; Is_vararg:       0
; Max Stack Size:  2

  1 [-]: GETGLOBAL R0 K0        ; R0 := 0xae91e43b
  2 [-]: SELF      R0 R0 K1     ; R1 := R0; R0 := R0[0x32302b4a]
  3 [-]: CALL      R0 2 1       ; R0(R1)
  4 [-]: RETURN    R0 1         ; return 


; Function #2:
;
; Name:            
; Defined at line: 61
; #Upvalues:       1
; #Parameters:     0
; Is_vararg:       0
; Max Stack Size:  8

  1 [-]: GETGLOBAL R0 K0        ; R0 := 0x3d106989
  2 [-]: LOADK     R1 K1        ; R1 := "SetupNextButton()"
  3 [-]: CALL      R0 2 1       ; R0(R1)
  4 [-]: GETGLOBAL R0 K2        ; R0 := 0xae91e43b
  5 [-]: SELF      R0 R0 K3     ; R1 := R0; R0 := R0[0x20b98db3]
  6 [-]: LOADK     R2 K4        ; R2 := "NextButton.NextText.Label.text"
  7 [-]: LOADK     R3 K5        ; R3 := "/Lotus/Language/Menu/Badlands_Continue"
  8 [-]: CALL      R0 4 1       ; R0(R1,R2,R3)
  9 [-]: GETGLOBAL R0 K2        ; R0 := 0xae91e43b
 10 [-]: SELF      R0 R0 K6     ; R1 := R0; R0 := R0[0x1e5b5cfe]
 11 [-]: LOADK     R2 K7        ; R2 := "NextButton.Btn"
 12 [-]: LOADK     R3 K8        ; R3 := "ArrowRollOver"
 13 [-]: LOADK     R4 K9        ; R4 := "ArrowRollOut"
 14 [-]: LOADK     R5 K10       ; R5 := "ArrowSelected"
 15 [-]: LOADK     R6 K11       ; R6 := ""
 16 [-]: CALL      R0 7 1       ; R0(R1,R2,R3,R4,R5,R6)
 17 [-]: GETGLOBAL R0 K2        ; R0 := 0xae91e43b
 18 [-]: SELF      R0 R0 K12    ; R1 := R0; R0 := R0[0x91a24e4b]
 19 [-]: LOADK     R2 K13       ; R2 := "NextButton.NextText.Label"
 20 [-]: LOADK     R3 33        ; R3 := 33.000000
 21 [-]: CALL      R0 4 2       ; R0 := R0(R1,R2,R3)
 22 [-]: SUB       R1 K14 R0    ; R1 := -50.000000 - R0
 23 [-]: GETGLOBAL R2 K2        ; R2 := 0xae91e43b
 24 [-]: SELF      R2 R2 K15    ; R3 := R2; R2 := R2[0x67bc869f]
 25 [-]: LOADK     R4 K16       ; R4 := "NextButton.NextText"
 26 [-]: LOADK     R5 0         ; R5 := 0.000000
 27 [-]: MOVE      R6 R1        ; R6 := R1
 28 [-]: CALL      R2 5 1       ; R2(R3,R4,R5,R6)
 29 [-]: GETGLOBAL R2 K2        ; R2 := 0xae91e43b
 30 [-]: SELF      R2 R2 K15    ; R3 := R2; R2 := R2[0x67bc869f]
 31 [-]: LOADK     R4 K16       ; R4 := "NextButton.NextText"
 32 [-]: LOADK     R5 10        ; R5 := 10.000000
 33 [-]: LOADK     R6 0         ; R6 := 0.000000
 34 [-]: CALL      R2 5 1       ; R2(R3,R4,R5,R6)
 35 [-]: SUB       R1 R1 K17    ; R1 := R1 - 77.000000
 36 [-]: GETGLOBAL R2 K2        ; R2 := 0xae91e43b
 37 [-]: SELF      R2 R2 K15    ; R3 := R2; R2 := R2[0x67bc869f]
 38 [-]: LOADK     R4 K18       ; R4 := "NextButton.Line"
 39 [-]: LOADK     R5 0         ; R5 := 0.000000
 40 [-]: MOVE      R6 R1        ; R6 := R1
 41 [-]: CALL      R2 5 1       ; R2(R3,R4,R5,R6)
 42 [-]: GETGLOBAL R2 K2        ; R2 := 0xae91e43b
 43 [-]: SELF      R2 R2 K15    ; R3 := R2; R2 := R2[0x67bc869f]
 44 [-]: LOADK     R4 K7        ; R4 := "NextButton.Btn"
 45 [-]: LOADK     R5 12        ; R5 := 12.000000
 46 [-]: GETGLOBAL R6 K19       ; R6 := 0x5bced4c4
 47 [-]: GETTABLE  R6 R6 K20    ; R6 := R6[0xe4a5b3ca]
 48 [-]: MOVE      R7 R1        ; R7 := R1
 49 [-]: CALL      R6 2 0       ; R6,... := R6(R7)
 50 [-]: CALL      R2 0 1       ; R2(R3,...)
 51 [-]: GETGLOBAL R2 K0        ; R2 := 0x3d106989
 52 [-]: LOADK     R3 K21       ; R3 := "Button Width = "
 53 [-]: GETGLOBAL R4 K22       ; R4 := 0x64fb1586
 54 [-]: GETGLOBAL R5 K19       ; R5 := 0x5bced4c4
 55 [-]: GETTABLE  R5 R5 K20    ; R5 := R5[0xe4a5b3ca]
 56 [-]: MOVE      R6 R1        ; R6 := R1
 57 [-]: CALL      R5 2 0       ; R5,... := R5(R6)
 58 [-]: CALL      R4 0 2       ; R4 := R4(R5,...)
 59 [-]: CONCAT    R3 R3 R4     ; R3 := R3 .. R4
 60 [-]: CALL      R2 2 1       ; R2(R3)
 61 [-]: GETGLOBAL R2 K2        ; R2 := 0xae91e43b
 62 [-]: SELF      R2 R2 K23    ; R3 := R2; R2 := R2[0xaade900e]
 63 [-]: LOADK     R4 K7        ; R4 := "NextButton.Btn"
 64 [-]: LOADK     R5 59        ; R5 := 59.000000
 65 [-]: LOADBOOL  R6 0 0       ; R6 := false
 66 [-]: CALL      R2 5 1       ; R2(R3,R4,R5,R6)
 67 [-]: GETGLOBAL R2 K2        ; R2 := 0xae91e43b
 68 [-]: SELF      R2 R2 K15    ; R3 := R2; R2 := R2[0x67bc869f]
 69 [-]: LOADK     R4 K24       ; R4 := "NextButton"
 70 [-]: LOADK     R5 9         ; R5 := 9.000000
 71 [-]: GETUPVAL  R6 U0        ; R6 := U0
 72 [-]: CALL      R2 5 1       ; R2(R3,R4,R5,R6)
 73 [-]: RETURN    R0 1         ; return 


; Function #3:
;
; Name:            
; Defined at line: 81
; #Upvalues:       2
; #Parameters:     0
; Is_vararg:       0
; Max Stack Size:  8

  1 [-]: GETGLOBAL R0 K0        ; R0 := 0x3d106989
  2 [-]: LOADK     R1 K1        ; R1 := "ShowNextButton()"
  3 [-]: CALL      R0 2 1       ; R0(R1)
  4 [-]: LOADBOOL  R0 1 0       ; R0 := true
  5 [-]: SETUPVAL  R0 U0        ; U82 := R0
  6 [-]: GETGLOBAL R0 K2        ; R0 := 0x38f10e85
  7 [-]: GETGLOBAL R1 K3        ; R1 := 0xae91e43b
  8 [-]: LOADK     R2 K4        ; R2 := "NextButton.Line.gotoAndPlay"
  9 [-]: LOADK     R3 K5        ; R3 := "Show"
 10 [-]: CALL      R0 4 1       ; R0(R1,R2,R3)
 11 [-]: GETGLOBAL R0 K6        ; R0 := 0x25312c9b
 12 [-]: GETGLOBAL R1 K3        ; R1 := 0xae91e43b
 13 [-]: LOADK     R2 K7        ; R2 := "NextButton.NextText"
 14 [-]: LOADK     R3 0         ; R3 := 0.000000
 15 [-]: NEWTABLE  R4 1 0       ; R4 := {}
 16 [-]: LOADK     R5 10        ; R5 := 10.000000
 17 [-]: SETLIST   R4 1 1       ; R4[(1-1)*FPF+i] := R(4+i), 1 <= i <= 1
 18 [-]: NEWTABLE  R5 1 0       ; R5 := {}
 19 [-]: LOADK     R6 100       ; R6 := 100.000000
 20 [-]: SETLIST   R5 1 1       ; R5[(1-1)*FPF+i] := R(5+i), 1 <= i <= 1
 21 [-]: LOADK     R6 K9        ; R6 := 0.200000
 22 [-]: LOADK     R7 K10       ; R7 := 0.150000
 23 [-]: CALL      R0 8 1       ; R0(R1,R2,R3,R4,R5,R6,R7)
 24 [-]: GETUPVAL  R0 U1        ; R0 := U1
 25 [-]: SELF      R0 R0 K11    ; R1 := R0; R0 := R0[0xbd2e96ea]
 26 [-]: LOADK     R2 K12       ; R2 := 0.350000
 27 [-]: CLOSURE   R3 0         ; R3 := closure(Function #3.1)
 28 [-]: CALL      R0 4 1       ; R0(R1,R2,R3)
 29 [-]: RETURN    R0 1         ; return 


; Function #3.1:
;
; Name:            
; Defined at line: 88
; #Upvalues:       0
; #Parameters:     0
; Is_vararg:       0
; Max Stack Size:  5

  1 [-]: GETGLOBAL R0 K0        ; R0 := 0x3d106989
  2 [-]: LOADK     R1 K1        ; R1 := "Enable button"
  3 [-]: CALL      R0 2 1       ; R0(R1)
  4 [-]: GETGLOBAL R0 K2        ; R0 := 0x38f10e85
  5 [-]: GETGLOBAL R1 K3        ; R1 := 0xae91e43b
  6 [-]: LOADK     R2 K4        ; R2 := "NextButton.Arrow.gotoAndPlay"
  7 [-]: LOADK     R3 K5        ; R3 := "Show"
  8 [-]: CALL      R0 4 1       ; R0(R1,R2,R3)
  9 [-]: GETGLOBAL R0 K3        ; R0 := 0xae91e43b
 10 [-]: SELF      R0 R0 K6     ; R1 := R0; R0 := R0[0xaade900e]
 11 [-]: LOADK     R2 K7        ; R2 := "NextButton.Btn"
 12 [-]: LOADK     R3 59        ; R3 := 59.000000
 13 [-]: LOADBOOL  R4 1 0       ; R4 := true
 14 [-]: CALL      R0 5 1       ; R0(R1,R2,R3,R4)
 15 [-]: RETURN    R0 1         ; return 


; Function #4:
;
; Name:            
; Defined at line: 95
; #Upvalues:       1
; #Parameters:     0
; Is_vararg:       0
; Max Stack Size:  7

  1 [-]: GETUPVAL  R0 U0        ; R0 := U0
  2 [-]: TEST      R0 0         ; if not R0 then PC := 37
  3 [-]: JMP       37           ; PC := 37
  4 [-]: GETGLOBAL R0 K0        ; R0 := 0x3d106989
  5 [-]: LOADK     R1 K1        ; R1 := "HideNextButton()"
  6 [-]: CALL      R0 2 1       ; R0(R1)
  7 [-]: LOADBOOL  R0 0 0       ; R0 := false
  8 [-]: SETUPVAL  R0 U0        ; U82 := R0
  9 [-]: GETGLOBAL R0 K2        ; R0 := 0x38f10e85
 10 [-]: GETGLOBAL R1 K3        ; R1 := 0xae91e43b
 11 [-]: LOADK     R2 K4        ; R2 := "NextButton.Line.gotoAndPlay"
 12 [-]: LOADK     R3 K5        ; R3 := "Hide"
 13 [-]: CALL      R0 4 1       ; R0(R1,R2,R3)
 14 [-]: GETGLOBAL R0 K2        ; R0 := 0x38f10e85
 15 [-]: GETGLOBAL R1 K3        ; R1 := 0xae91e43b
 16 [-]: LOADK     R2 K6        ; R2 := "NextButton.Arrow.gotoAndPlay"
 17 [-]: LOADK     R3 K5        ; R3 := "Hide"
 18 [-]: CALL      R0 4 1       ; R0(R1,R2,R3)
 19 [-]: GETGLOBAL R0 K3        ; R0 := 0xae91e43b
 20 [-]: SELF      R0 R0 K7     ; R1 := R0; R0 := R0[0xaade900e]
 21 [-]: LOADK     R2 K8        ; R2 := "NextButton.Btn"
 22 [-]: LOADK     R3 59        ; R3 := 59.000000
 23 [-]: LOADBOOL  R4 0 0       ; R4 := false
 24 [-]: CALL      R0 5 1       ; R0(R1,R2,R3,R4)
 25 [-]: GETGLOBAL R0 K9        ; R0 := 0x25312c9b
 26 [-]: GETGLOBAL R1 K3        ; R1 := 0xae91e43b
 27 [-]: LOADK     R2 K10       ; R2 := "NextButton.NextText"
 28 [-]: LOADK     R3 0         ; R3 := 0.000000
 29 [-]: NEWTABLE  R4 1 0       ; R4 := {}
 30 [-]: LOADK     R5 10        ; R5 := 10.000000
 31 [-]: SETLIST   R4 1 1       ; R4[(1-1)*FPF+i] := R(4+i), 1 <= i <= 1
 32 [-]: NEWTABLE  R5 1 0       ; R5 := {}
 33 [-]: LOADK     R6 0         ; R6 := 0.000000
 34 [-]: SETLIST   R5 1 1       ; R5[(1-1)*FPF+i] := R(5+i), 1 <= i <= 1
 35 [-]: LOADK     R6 K12       ; R6 := 0.200000
 36 [-]: CALL      R0 7 1       ; R0(R1,R2,R3,R4,R5,R6)
 37 [-]: RETURN    R0 1         ; return 


; Function #5:
;
; Name:            
; Defined at line: 106
; #Upvalues:       2
; #Parameters:     0
; Is_vararg:       0
; Max Stack Size:  11

  1 [-]: GETUPVAL  R0 U0        ; R0 := U0
  2 [-]: GETTABLE  R0 R0 K0     ; R0 := R0[0x44537adf]
  3 [-]: GETGLOBAL R1 K1        ; R1 := 0xae91e43b
  4 [-]: CALL      R0 2 3       ; R0,R1 := R0(R1)
  5 [-]: GETGLOBAL R2 K1        ; R2 := 0xae91e43b
  6 [-]: SELF      R2 R2 K2     ; R3 := R2; R2 := R2[0x091c120e]
  7 [-]: CALL      R2 2 2       ; R2 := R2(R3)
  8 [-]: MOVE      R0 R2        ; R0 := R2
  9 [-]: GETGLOBAL R2 K1        ; R2 := 0xae91e43b
 10 [-]: SELF      R2 R2 K3     ; R3 := R2; R2 := R2[0x2cc9d281]
 11 [-]: CALL      R2 2 2       ; R2 := R2(R3)
 12 [-]: MOVE      R1 R2        ; R1 := R2
 13 [-]: GETGLOBAL R2 K1        ; R2 := 0xae91e43b
 14 [-]: SELF      R2 R2 K4     ; R3 := R2; R2 := R2[0x67bc869f]
 15 [-]: LOADK     R4 K5        ; R4 := "Slide1"
 16 [-]: LOADK     R5 12        ; R5 := 12.000000
 17 [-]: MOVE      R6 R0        ; R6 := R0
 18 [-]: CALL      R2 5 1       ; R2(R3,R4,R5,R6)
 19 [-]: GETGLOBAL R2 K1        ; R2 := 0xae91e43b
 20 [-]: SELF      R2 R2 K4     ; R3 := R2; R2 := R2[0x67bc869f]
 21 [-]: LOADK     R4 K5        ; R4 := "Slide1"
 22 [-]: LOADK     R5 13        ; R5 := 13.000000
 23 [-]: MOVE      R6 R1        ; R6 := R1
 24 [-]: CALL      R2 5 1       ; R2(R3,R4,R5,R6)
 25 [-]: LOADK     R2 K6        ; R2 := 1.300000
 26 [-]: MUL       R3 R0 R2     ; R3 := R0 * R2
 27 [-]: DIV       R3 R3 K7     ; R3 := R3 / 150.000000
 28 [-]: SETUPVAL  R3 U1        ; U82 := R1
 29 [-]: GETGLOBAL R3 K1        ; R3 := 0xae91e43b
 30 [-]: SELF      R3 R3 K4     ; R4 := R3; R3 := R3[0x67bc869f]
 31 [-]: LOADK     R5 K8        ; R5 := "Pattern"
 32 [-]: LOADK     R6 12        ; R6 := 12.000000
 33 [-]: MUL       R7 R0 R2     ; R7 := R0 * R2
 34 [-]: CALL      R3 5 1       ; R3(R4,R5,R6,R7)
 35 [-]: GETGLOBAL R3 K1        ; R3 := 0xae91e43b
 36 [-]: SELF      R3 R3 K4     ; R4 := R3; R3 := R3[0x67bc869f]
 37 [-]: LOADK     R5 K8        ; R5 := "Pattern"
 38 [-]: LOADK     R6 13        ; R6 := 13.000000
 39 [-]: MUL       R7 R1 R2     ; R7 := R1 * R2
 40 [-]: CALL      R3 5 1       ; R3(R4,R5,R6,R7)
 41 [-]: GETGLOBAL R3 K1        ; R3 := 0xae91e43b
 42 [-]: SELF      R3 R3 K9     ; R4 := R3; R3 := R3[0x91e13703]
 43 [-]: LOADK     R5 K8        ; R5 := "Pattern"
 44 [-]: LOADK     R6 K10       ; R6 := "TileRepeats"
 45 [-]: GETUPVAL  R7 U1        ; R7 := U1
 46 [-]: MUL       R8 R1 R2     ; R8 := R1 * R2
 47 [-]: DIV       R8 R8 K11    ; R8 := R8 / 400.000000
 48 [-]: LOADK     R9 1         ; R9 := 1.000000
 49 [-]: LOADK     R10 1        ; R10 := 1.000000
 50 [-]: CALL      R3 8 1       ; R3(R4,R5,R6,R7,R8,R9,R10)
 51 [-]: GETGLOBAL R3 K1        ; R3 := 0xae91e43b
 52 [-]: SELF      R3 R3 K4     ; R4 := R3; R3 := R3[0x67bc869f]
 53 [-]: LOADK     R5 K12       ; R5 := "Pattern2"
 54 [-]: LOADK     R6 12        ; R6 := 12.000000
 55 [-]: MUL       R7 R0 R2     ; R7 := R0 * R2
 56 [-]: CALL      R3 5 1       ; R3(R4,R5,R6,R7)
 57 [-]: GETGLOBAL R3 K1        ; R3 := 0xae91e43b
 58 [-]: SELF      R3 R3 K4     ; R4 := R3; R3 := R3[0x67bc869f]
 59 [-]: LOADK     R5 K12       ; R5 := "Pattern2"
 60 [-]: LOADK     R6 13        ; R6 := 13.000000
 61 [-]: MUL       R7 R1 R2     ; R7 := R1 * R2
 62 [-]: CALL      R3 5 1       ; R3(R4,R5,R6,R7)
 63 [-]: GETGLOBAL R3 K1        ; R3 := 0xae91e43b
 64 [-]: SELF      R3 R3 K9     ; R4 := R3; R3 := R3[0x91e13703]
 65 [-]: LOADK     R5 K12       ; R5 := "Pattern2"
 66 [-]: LOADK     R6 K10       ; R6 := "TileRepeats"
 67 [-]: GETUPVAL  R7 U1        ; R7 := U1
 68 [-]: MUL       R8 R1 R2     ; R8 := R1 * R2
 69 [-]: DIV       R8 R8 K11    ; R8 := R8 / 400.000000
 70 [-]: LOADK     R9 1         ; R9 := 1.000000
 71 [-]: LOADK     R10 1        ; R10 := 1.000000
 72 [-]: CALL      R3 8 1       ; R3(R4,R5,R6,R7,R8,R9,R10)
 73 [-]: RETURN    R0 1         ; return 


; Function #6:
;
; Name:            
; Defined at line: 125
; #Upvalues:       2
; #Parameters:     1
; Is_vararg:       0
; Max Stack Size:  5

  1 [-]: GETUPVAL  R1 U0        ; R1 := U0
  2 [-]: GETTABLE  R1 R1 K0     ; R1 := R1[0x06d055f9]
  3 [-]: GETUPVAL  R2 U1        ; R2 := U1
  4 [-]: EQ        1 R2 K1      ; if R2 == "Slide1" then PC := 7
  5 [-]: JMP       7            ; PC := 7
  6 [-]: LOADBOOL  R2 0 1       ; R2 := false; PC := 7
  7 [-]: LOADBOOL  R2 1 0       ; R2 := true
  8 [-]: LOADK     R3 K2        ; R3 := "Slide2"
  9 [-]: LOADK     R4 K1        ; R4 := "Slide1"
 10 [-]: CALL      R1 4 2       ; R1 := R1(R2,R3,R4)
 11 [-]: RETURN    R1 2         ; return R1
 12 [-]: RETURN    R0 1         ; return 


; Function #7:
;
; Name:            
; Defined at line: 129
; #Upvalues:       1
; #Parameters:     0
; Is_vararg:       0
; Max Stack Size:  8

  1 [-]: GETGLOBAL R0 K0        ; R0 := 0x25312c9b
  2 [-]: GETGLOBAL R1 K1        ; R1 := 0xae91e43b
  3 [-]: LOADK     R2 K2        ; R2 := "LoomAnimations"
  4 [-]: LOADK     R3 0         ; R3 := 0.000000
  5 [-]: NEWTABLE  R4 1 0       ; R4 := {}
  6 [-]: LOADK     R5 10        ; R5 := 10.000000
  7 [-]: SETLIST   R4 1 1       ; R4[(1-1)*FPF+i] := R(4+i), 1 <= i <= 1
  8 [-]: NEWTABLE  R5 1 0       ; R5 := {}
  9 [-]: LOADK     R6 100       ; R6 := 100.000000
 10 [-]: SETLIST   R5 1 1       ; R5[(1-1)*FPF+i] := R(5+i), 1 <= i <= 1
 11 [-]: LOADK     R6 0         ; R6 := 0.500000
 12 [-]: LOADK     R7 1         ; R7 := 1.000000
 13 [-]: CALL      R0 8 1       ; R0(R1,R2,R3,R4,R5,R6,R7)
 14 [-]: GETGLOBAL R0 K4        ; R0 := 0x38f10e85
 15 [-]: GETGLOBAL R1 K1        ; R1 := 0xae91e43b
 16 [-]: LOADK     R2 K5        ; R2 := "LoomAnimations.gotoAndStop"
 17 [-]: LOADK     R3 K6        ; R3 := "StopLoom"
 18 [-]: GETUPVAL  R4 U0        ; R4 := U0
 19 [-]: CONCAT    R3 R3 R4     ; R3 := R3 .. R4
 20 [-]: CALL      R0 4 1       ; R0(R1,R2,R3)
 21 [-]: RETURN    R0 1         ; return 


; Function #8:
;
; Name:            
; Defined at line: 134
; #Upvalues:       8
; #Parameters:     2
; Is_vararg:       0
; Max Stack Size:  9

  1 [-]: SETUPVAL  R0 U0        ; U82 := R0
  2 [-]: LOADK     R2 K0        ; R2 := "Slide1"
  3 [-]: SETUPVAL  R2 U1        ; U82 := R1
  4 [-]: GETGLOBAL R2 K1        ; R2 := 0xae91e43b
  5 [-]: SELF      R2 R2 K2     ; R3 := R2; R2 := R2[0x1cb415c1]
  6 [-]: GETUPVAL  R4 U1        ; R4 := U1
  7 [-]: GETGLOBAL R5 K3        ; R5 := 0x68db7d54
  8 [-]: GETUPVAL  R6 U0        ; R6 := U0
  9 [-]: GETTABLE  R5 R5 R6     ; R5 := R5[R6]
 10 [-]: CALL      R2 4 1       ; R2(R3,R4,R5)
 11 [-]: GETGLOBAL R2 K4        ; R2 := 0x25312c9b
 12 [-]: GETGLOBAL R3 K1        ; R3 := 0xae91e43b
 13 [-]: LOADK     R4 K5        ; R4 := "LoomAnimations"
 14 [-]: LOADK     R5 0         ; R5 := 0.000000
 15 [-]: NEWTABLE  R6 1 0       ; R6 := {}
 16 [-]: LOADK     R7 10        ; R7 := 10.000000
 17 [-]: SETLIST   R6 1 1       ; R6[(1-1)*FPF+i] := R(6+i), 1 <= i <= 1
 18 [-]: NEWTABLE  R7 1 0       ; R7 := {}
 19 [-]: LOADK     R8 0         ; R8 := 0.000000
 20 [-]: SETLIST   R7 1 1       ; R7[(1-1)*FPF+i] := R(7+i), 1 <= i <= 1
 21 [-]: LOADK     R8 K7        ; R8 := 0.350000
 22 [-]: CALL      R2 7 1       ; R2(R3,R4,R5,R6,R7,R8)
 23 [-]: GETGLOBAL R2 K4        ; R2 := 0x25312c9b
 24 [-]: GETGLOBAL R3 K1        ; R3 := 0xae91e43b
 25 [-]: GETUPVAL  R4 U1        ; R4 := U1
 26 [-]: LOADK     R5 0         ; R5 := 0.000000
 27 [-]: NEWTABLE  R6 1 0       ; R6 := {}
 28 [-]: LOADK     R7 10        ; R7 := 10.000000
 29 [-]: SETLIST   R6 1 1       ; R6[(1-1)*FPF+i] := R(6+i), 1 <= i <= 1
 30 [-]: NEWTABLE  R7 1 0       ; R7 := {}
 31 [-]: LOADK     R8 100       ; R8 := 100.000000
 32 [-]: SETLIST   R7 1 1       ; R7[(1-1)*FPF+i] := R(7+i), 1 <= i <= 1
 33 [-]: LOADK     R8 6         ; R8 := 6.000000
 34 [-]: CALL      R2 7 1       ; R2(R3,R4,R5,R6,R7,R8)
 35 [-]: GETGLOBAL R2 K8        ; R2 := 0x7b998233
 36 [-]: GETGLOBAL R3 K9        ; R3 := 0xe91d7466
 37 [-]: CALL      R2 2 2       ; R2 := R2(R3)
 38 [-]: TEST      R2 1         ; if R2 then PC := 61
 39 [-]: JMP       61           ; PC := 61
 40 [-]: GETUPVAL  R2 U2        ; R2 := U2
 41 [-]: GETTABLE  R2 R2 K10    ; R2 := R2[0x1f60d532]
 42 [-]: GETGLOBAL R3 K9        ; R3 := 0xe91d7466
 43 [-]: SELF      R3 R3 K11    ; R4 := R3; R3 := R3[0x10c9eef2]
 44 [-]: GETGLOBAL R5 K12       ; R5 := 0x0469f296
 45 [-]: LOADK     R6 K13       ; R6 := "Vitruvian"
 46 [-]: GETGLOBAL R7 K14       ; R7 := 0x64fb1586
 47 [-]: GETUPVAL  R8 U0        ; R8 := U0
 48 [-]: CALL      R7 2 2       ; R7 := R7(R8)
 49 [-]: CONCAT    R6 R6 R7     ; R6 := R6 .. R7
 50 [-]: CALL      R5 2 0       ; R5,... := R5(R6)
 51 [-]: CALL      R3 0 0       ; R3,... := R3(R4,...)
 52 [-]: CALL      R2 0 1       ; R2(R3,...)
 53 [-]: GETUPVAL  R2 U3        ; R2 := U3
 54 [-]: SELF      R2 R2 K15    ; R3 := R2; R2 := R2[0xbd2e96ea]
 55 [-]: LOADK     R4 2         ; R4 := 2.000000
 56 [-]: CLOSURE   R5 0         ; R5 := closure(Function #8.1)
 57 [-]: MOVE      R0 R1        ; R0 := R1
 58 [-]: GETUPVAL  R0 U4        ; R0 := U4
 59 [-]: GETUPVAL  R0 U5        ; R0 := U5
 60 [-]: CALL      R2 4 1       ; R2(R3,R4,R5)
 61 [-]: GETUPVAL  R2 U0        ; R2 := U0
 62 [-]: LT        0 K16 R2     ; if 1.000000 >= R2 then PC := 71
 63 [-]: JMP       71           ; PC := 71
 64 [-]: GETGLOBAL R2 K17       ; R2 := 0x89326c93
 65 [-]: SELF      R2 R2 K18    ; R3 := R2; R2 := R2[0x659d451f]
 66 [-]: GETGLOBAL R4 K19       ; R4 := 0x7e628e96
 67 [-]: GETGLOBAL R5 K20       ; R5 := ZERO_VECTOR
 68 [-]: LOADBOOL  R6 0 0       ; R6 := false
 69 [-]: CALL      R2 5 1       ; R2(R3,R4,R5,R6)
 70 [-]: JMP       77           ; PC := 77
 71 [-]: GETGLOBAL R2 K17       ; R2 := 0x89326c93
 72 [-]: SELF      R2 R2 K18    ; R3 := R2; R2 := R2[0x659d451f]
 73 [-]: GETGLOBAL R4 K21       ; R4 := 0xdeba9bb9
 74 [-]: GETGLOBAL R5 K20       ; R5 := ZERO_VECTOR
 75 [-]: LOADBOOL  R6 0 0       ; R6 := false
 76 [-]: CALL      R2 5 1       ; R2(R3,R4,R5,R6)
 77 [-]: GETUPVAL  R2 U6        ; R2 := U6
 78 [-]: GETTABLE  R2 R2 K22    ; R2 := R2["dir"]
 79 [-]: LT        0 K23 R2     ; if 0.000000 >= R2 then PC := 106
 80 [-]: JMP       106          ; PC := 106
 81 [-]: GETUPVAL  R2 U6        ; R2 := U6
 82 [-]: SETTABLE  R2 K24 K16   ; R2["z"] := 1.000000
 83 [-]: GETUPVAL  R2 U6        ; R2 := U6
 84 [-]: SETTABLE  R2 K22 K25   ; R2["dir"] := -1.000000
 85 [-]: GETUPVAL  R2 U6        ; R2 := U6
 86 [-]: GETGLOBAL R3 K27       ; R3 := 0x9bafffe3
 87 [-]: LOADK     R4 -100      ; R4 := -100.000000
 88 [-]: LOADK     R5 0         ; R5 := 0.000000
 89 [-]: GETGLOBAL R6 K28       ; R6 := 0xc163f229
 90 [-]: LOADK     R7 0         ; R7 := 0.000000
 91 [-]: LOADK     R8 1         ; R8 := 1.000000
 92 [-]: CALL      R6 3 0       ; R6,... := R6(R7,R8)
 93 [-]: CALL      R3 0 2       ; R3 := R3(R4,...)
 94 [-]: SETTABLE  R2 K26 R3    ; R2["tx"] := R3
 95 [-]: GETUPVAL  R2 U6        ; R2 := U6
 96 [-]: GETGLOBAL R3 K27       ; R3 := 0x9bafffe3
 97 [-]: LOADK     R4 0         ; R4 := 0.000000
 98 [-]: LOADK     R5 -20       ; R5 := -20.000000
 99 [-]: GETGLOBAL R6 K28       ; R6 := 0xc163f229
100 [-]: LOADK     R7 0         ; R7 := 0.000000
101 [-]: LOADK     R8 1         ; R8 := 1.000000
102 [-]: CALL      R6 3 0       ; R6,... := R6(R7,R8)
103 [-]: CALL      R3 0 2       ; R3 := R3(R4,...)
104 [-]: SETTABLE  R2 K29 R3    ; R2["ty"] := R3
105 [-]: JMP       130          ; PC := 130
106 [-]: GETUPVAL  R2 U6        ; R2 := U6
107 [-]: SETTABLE  R2 K24 K23   ; R2["z"] := 0.000000
108 [-]: GETUPVAL  R2 U6        ; R2 := U6
109 [-]: SETTABLE  R2 K22 K16   ; R2["dir"] := 1.000000
110 [-]: GETUPVAL  R2 U6        ; R2 := U6
111 [-]: GETGLOBAL R3 K27       ; R3 := 0x9bafffe3
112 [-]: LOADK     R4 -100      ; R4 := -100.000000
113 [-]: LOADK     R5 0         ; R5 := 0.000000
114 [-]: GETGLOBAL R6 K28       ; R6 := 0xc163f229
115 [-]: LOADK     R7 0         ; R7 := 0.000000
116 [-]: LOADK     R8 1         ; R8 := 1.000000
117 [-]: CALL      R6 3 0       ; R6,... := R6(R7,R8)
118 [-]: CALL      R3 0 2       ; R3 := R3(R4,...)
119 [-]: SETTABLE  R2 K26 R3    ; R2["tx"] := R3
120 [-]: GETUPVAL  R2 U6        ; R2 := U6
121 [-]: GETGLOBAL R3 K27       ; R3 := 0x9bafffe3
122 [-]: LOADK     R4 0         ; R4 := 0.000000
123 [-]: LOADK     R5 -20       ; R5 := -20.000000
124 [-]: GETGLOBAL R6 K28       ; R6 := 0xc163f229
125 [-]: LOADK     R7 0         ; R7 := 0.000000
126 [-]: LOADK     R8 1         ; R8 := 1.000000
127 [-]: CALL      R6 3 0       ; R6,... := R6(R7,R8)
128 [-]: CALL      R3 0 2       ; R3 := R3(R4,...)
129 [-]: SETTABLE  R2 K29 R3    ; R2["ty"] := R3
130 [-]: GETUPVAL  R2 U7        ; R2 := U7
131 [-]: CALL      R2 1 1       ; R2()
132 [-]: RETURN    R0 1         ; return 


; Function #8.1:
;
; Name:            
; Defined at line: 146
; #Upvalues:       3
; #Parameters:     0
; Is_vararg:       0
; Max Stack Size:  2

  1 [-]: GETUPVAL  R0 U0        ; R0 := U0
  2 [-]: TEST      R0 0         ; if not R0 then PC := 7
  3 [-]: JMP       7            ; PC := 7
  4 [-]: LOADBOOL  R0 1 0       ; R0 := true
  5 [-]: SETUPVAL  R0 U1        ; U82 := R1
  6 [-]: JMP       9            ; PC := 9
  7 [-]: LOADBOOL  R0 1 0       ; R0 := true
  8 [-]: SETUPVAL  R0 U2        ; U82 := R2
  9 [-]: RETURN    R0 1         ; return 


; Function #9:
;
; Name:            
; Defined at line: 176
; #Upvalues:       2
; #Parameters:     0
; Is_vararg:       0
; Max Stack Size:  2

  1 [-]: GETUPVAL  R0 U0        ; R0 := U0
  2 [-]: GETUPVAL  R1 U1        ; R1 := U1
  3 [-]: ADD       R1 R1 K0     ; R1 := R1 + 1.000000
  4 [-]: CALL      R0 2 1       ; R0(R1)
  5 [-]: RETURN    R0 1         ; return 


; Function #10:
;
; Name:            
; Defined at line: 180
; #Upvalues:       7
; #Parameters:     0
; Is_vararg:       0
; Max Stack Size:  11

  1 [-]: GETUPVAL  R0 U0        ; R0 := U0
  2 [-]: GETUPVAL  R1 U1        ; R1 := U1
  3 [-]: GETTABLE  R0 R0 R1     ; R0 := R0[R1]
  4 [-]: GETUPVAL  R1 U2        ; R1 := U2
  5 [-]: CALL      R1 1 1       ; R1()
  6 [-]: GETUPVAL  R1 U1        ; R1 := U1
  7 [-]: ADD       R1 R1 K0     ; R1 := R1 + 1.000000
  8 [-]: SETUPVAL  R1 U1        ; U82 := R1
  9 [-]: GETUPVAL  R1 U0        ; R1 := U0
 10 [-]: GETUPVAL  R2 U1        ; R2 := U1
 11 [-]: GETTABLE  R1 R1 R2     ; R1 := R1[R2]
 12 [-]: EQ        1 R1 K1      ; if R1 == nil then PC := 92
 13 [-]: JMP       92           ; PC := 92
 14 [-]: GETTABLE  R2 R1 K2     ; R2 := R1["Type"]
 15 [-]: GETUPVAL  R3 U3        ; R3 := U3
 16 [-]: GETTABLE  R3 R3 K3     ; R3 := R3["SLIDE"]
 17 [-]: EQ        0 R2 R3      ; if R2 ~= R3 then PC := 48
 18 [-]: JMP       48           ; PC := 48
 19 [-]: EQ        1 R0 K1      ; if R0 == nil then PC := 43
 20 [-]: JMP       43           ; PC := 43
 21 [-]: GETTABLE  R2 R0 K2     ; R2 := R0["Type"]
 22 [-]: GETUPVAL  R3 U3        ; R3 := U3
 23 [-]: GETTABLE  R3 R3 K3     ; R3 := R3["SLIDE"]
 24 [-]: EQ        0 R2 R3      ; if R2 ~= R3 then PC := 43
 25 [-]: JMP       43           ; PC := 43
 26 [-]: GETGLOBAL R2 K4        ; R2 := 0x25312c9b
 27 [-]: GETGLOBAL R3 K5        ; R3 := 0xae91e43b
 28 [-]: LOADK     R4 K6        ; R4 := "Slide1"
 29 [-]: LOADK     R5 0         ; R5 := 0.000000
 30 [-]: NEWTABLE  R6 1 0       ; R6 := {}
 31 [-]: LOADK     R7 10        ; R7 := 10.000000
 32 [-]: SETLIST   R6 1 1       ; R6[(1-1)*FPF+i] := R(6+i), 1 <= i <= 1
 33 [-]: NEWTABLE  R7 1 0       ; R7 := {}
 34 [-]: LOADK     R8 0         ; R8 := 0.000000
 35 [-]: SETLIST   R7 1 1       ; R7[(1-1)*FPF+i] := R(7+i), 1 <= i <= 1
 36 [-]: LOADK     R8 K8        ; R8 := 0.350000
 37 [-]: LOADK     R9 0         ; R9 := 0.000000
 38 [-]: CLOSURE   R10 0        ; R10 := closure(Function #10.1)
 39 [-]: GETUPVAL  R0 U4        ; R0 := U4
 40 [-]: MOVE      R0 R1        ; R0 := R1
 41 [-]: CALL      R2 9 1       ; R2(R3,R4,R5,R6,R7,R8,R9,R10)
 42 [-]: JMP       106          ; PC := 106
 43 [-]: GETUPVAL  R2 U4        ; R2 := U4
 44 [-]: GETTABLE  R3 R1 K9     ; R3 := R1["Index"]
 45 [-]: GETTABLE  R4 R1 K10    ; R4 := R1["AutoClose"]
 46 [-]: CALL      R2 3 1       ; R2(R3,R4)
 47 [-]: JMP       106          ; PC := 106
 48 [-]: GETGLOBAL R2 K4        ; R2 := 0x25312c9b
 49 [-]: GETGLOBAL R3 K5        ; R3 := 0xae91e43b
 50 [-]: LOADK     R4 K11       ; R4 := "LoomAnimations"
 51 [-]: LOADK     R5 0         ; R5 := 0.000000
 52 [-]: NEWTABLE  R6 1 0       ; R6 := {}
 53 [-]: LOADK     R7 10        ; R7 := 10.000000
 54 [-]: SETLIST   R6 1 1       ; R6[(1-1)*FPF+i] := R(6+i), 1 <= i <= 1
 55 [-]: NEWTABLE  R7 1 0       ; R7 := {}
 56 [-]: LOADK     R8 0         ; R8 := 0.000000
 57 [-]: SETLIST   R7 1 1       ; R7[(1-1)*FPF+i] := R(7+i), 1 <= i <= 1
 58 [-]: LOADK     R8 K8        ; R8 := 0.350000
 59 [-]: CALL      R2 7 1       ; R2(R3,R4,R5,R6,R7,R8)
 60 [-]: EQ        1 R0 K1      ; if R0 == nil then PC := 74
 61 [-]: JMP       74           ; PC := 74
 62 [-]: GETGLOBAL R2 K4        ; R2 := 0x25312c9b
 63 [-]: GETGLOBAL R3 K5        ; R3 := 0xae91e43b
 64 [-]: LOADK     R4 K6        ; R4 := "Slide1"
 65 [-]: LOADK     R5 0         ; R5 := 0.000000
 66 [-]: NEWTABLE  R6 1 0       ; R6 := {}
 67 [-]: LOADK     R7 10        ; R7 := 10.000000
 68 [-]: SETLIST   R6 1 1       ; R6[(1-1)*FPF+i] := R(6+i), 1 <= i <= 1
 69 [-]: NEWTABLE  R7 1 0       ; R7 := {}
 70 [-]: LOADK     R8 0         ; R8 := 0.000000
 71 [-]: SETLIST   R7 1 1       ; R7[(1-1)*FPF+i] := R(7+i), 1 <= i <= 1
 72 [-]: LOADK     R8 K12       ; R8 := 0.200000
 73 [-]: CALL      R2 7 1       ; R2(R3,R4,R5,R6,R7,R8)
 74 [-]: GETGLOBAL R2 K13       ; R2 := _T
 75 [-]: GETTABLE  R3 R1 K9     ; R3 := R1["Index"]
 76 [-]: SETTABLE  R2 K14 R3    ; R2["VitruvianPasswordStage"] := R3
 77 [-]: GETGLOBAL R2 K13       ; R2 := _T
 78 [-]: GETTABLE  R3 R1 K2     ; R3 := R1["Type"]
 79 [-]: GETUPVAL  R4 U3        ; R4 := U3
 80 [-]: GETTABLE  R4 R4 K16    ; R4 := R4["LOCK"]
 81 [-]: EQ        1 R3 R4      ; if R3 == R4 then PC := 84
 82 [-]: JMP       84           ; PC := 84
 83 [-]: LOADBOOL  R3 0 1       ; R3 := false; PC := 84
 84 [-]: LOADBOOL  R3 1 0       ; R3 := true
 85 [-]: SETTABLE  R2 K15 R3    ; R2["VitruvianPasswordLocked"] := R3
 86 [-]: GETGLOBAL R2 K5        ; R2 := 0xae91e43b
 87 [-]: SELF      R2 R2 K17    ; R3 := R2; R2 := R2[0x1fd6abd0]
 88 [-]: GETGLOBAL R4 K18       ; R4 := 0x0662fad9
 89 [-]: CALL      R2 3 2       ; R2 := R2(R3,R4)
 90 [-]: SETUPVAL  R2 U5        ; U82 := R5
 91 [-]: JMP       106          ; PC := 106
 92 [-]: GETGLOBAL R2 K4        ; R2 := 0x25312c9b
 93 [-]: GETGLOBAL R3 K5        ; R3 := 0xae91e43b
 94 [-]: LOADK     R4 K19       ; R4 := "_root"
 95 [-]: LOADK     R5 0         ; R5 := 0.000000
 96 [-]: NEWTABLE  R6 1 0       ; R6 := {}
 97 [-]: LOADK     R7 10        ; R7 := 10.000000
 98 [-]: SETLIST   R6 1 1       ; R6[(1-1)*FPF+i] := R(6+i), 1 <= i <= 1
 99 [-]: NEWTABLE  R7 1 0       ; R7 := {}
100 [-]: LOADK     R8 0         ; R8 := 0.000000
101 [-]: SETLIST   R7 1 1       ; R7[(1-1)*FPF+i] := R(7+i), 1 <= i <= 1
102 [-]: LOADK     R8 K20       ; R8 := 0.550000
103 [-]: LOADK     R9 0         ; R9 := 0.000000
104 [-]: GETUPVAL  R10 U6       ; R10 := U6
105 [-]: CALL      R2 9 1       ; R2(R3,R4,R5,R6,R7,R8,R9,R10)
106 [-]: RETURN    R0 1         ; return 


; Function #10.1:
;
; Name:            
; Defined at line: 191
; #Upvalues:       2
; #Parameters:     0
; Is_vararg:       0
; Max Stack Size:  3

  1 [-]: GETUPVAL  R0 U0        ; R0 := U0
  2 [-]: GETUPVAL  R1 U1        ; R1 := U1
  3 [-]: GETTABLE  R1 R1 K0     ; R1 := R1["Index"]
  4 [-]: GETUPVAL  R2 U1        ; R2 := U1
  5 [-]: GETTABLE  R2 R2 K1     ; R2 := R2["AutoClose"]
  6 [-]: CALL      R0 3 1       ; R0(R1,R2)
  7 [-]: RETURN    R0 1         ; return 


; Function #11:
;
; Name:            
; Defined at line: 214
; #Upvalues:       4
; #Parameters:     0
; Is_vararg:       0
; Max Stack Size:  7

  1 [-]: GETGLOBAL R0 K0        ; R0 := 0x7b998233
  2 [-]: GETGLOBAL R1 K1        ; R1 := 0x89326c93
  3 [-]: CALL      R0 2 2       ; R0 := R0(R1)
  4 [-]: TEST      R0 1         ; if R0 then PC := 11
  5 [-]: JMP       11           ; PC := 11
  6 [-]: GETGLOBAL R0 K0        ; R0 := 0x7b998233
  7 [-]: GETGLOBAL R1 K2        ; R1 := 0x83f4e77c
  8 [-]: CALL      R0 2 2       ; R0 := R0(R1)
  9 [-]: TEST      R0 0         ; if not R0 then PC := 12
 10 [-]: JMP       12           ; PC := 12
 11 [-]: RETURN    R0 1         ; return 
 12 [-]: GETGLOBAL R0 K0        ; R0 := 0x7b998233
 13 [-]: GETGLOBAL R1 K3        ; R1 := 0xbe190284
 14 [-]: CALL      R0 2 2       ; R0 := R0(R1)
 15 [-]: TEST      R0 1         ; if R0 then PC := 21
 16 [-]: JMP       21           ; PC := 21
 17 [-]: GETGLOBAL R0 K3        ; R0 := 0xbe190284
 18 [-]: SELF      R0 R0 K4     ; R1 := R0; R0 := R0[0xc02f2cb8]
 19 [-]: LOADBOOL  R2 0 0       ; R2 := false
 20 [-]: CALL      R0 3 1       ; R0(R1,R2)
 21 [-]: GETUPVAL  R0 U0        ; R0 := U0
 22 [-]: GETTABLE  R0 R0 K5     ; R0 := R0[0x1146d233]
 23 [-]: CALL      R0 1 1       ; R0()
 24 [-]: GETGLOBAL R0 K6        ; R0 := 0xae91e43b
 25 [-]: SELF      R0 R0 K7     ; R1 := R0; R0 := R0[0xcd73323e]
 26 [-]: CALL      R0 2 2       ; R0 := R0(R1)
 27 [-]: GETGLOBAL R1 K0        ; R1 := 0x7b998233
 28 [-]: MOVE      R2 R0        ; R2 := R0
 29 [-]: CALL      R1 2 2       ; R1 := R1(R2)
 30 [-]: TEST      R1 1         ; if R1 then PC := 35
 31 [-]: JMP       35           ; PC := 35
 32 [-]: SELF      R1 R0 K8     ; R2 := R0; R1 := R0[0x8eb2112d]
 33 [-]: LOADK     R3 K9        ; R3 := "Close"
 34 [-]: CALL      R1 3 1       ; R1(R2,R3)
 35 [-]: GETGLOBAL R1 K0        ; R1 := 0x7b998233
 36 [-]: GETGLOBAL R2 K10       ; R2 := _T
 37 [-]: GETTABLE  R2 R2 K11    ; R2 := R2["HideBackground"]
 38 [-]: CALL      R1 2 2       ; R1 := R1(R2)
 39 [-]: TEST      R1 1         ; if R1 then PC := 44
 40 [-]: JMP       44           ; PC := 44
 41 [-]: GETGLOBAL R1 K10       ; R1 := _T
 42 [-]: GETTABLE  R1 R1 K12    ; R1 := R1[0x6d147816]
 43 [-]: CALL      R1 1 1       ; R1()
 44 [-]: GETUPVAL  R1 U1        ; R1 := U1
 45 [-]: GETTABLE  R1 R1 K13    ; R1 := R1[0x6ef45ebc]
 46 [-]: CALL      R1 1 2       ; R1 := R1()
 47 [-]: GETGLOBAL R2 K0        ; R2 := 0x7b998233
 48 [-]: MOVE      R3 R1        ; R3 := R1
 49 [-]: CALL      R2 2 2       ; R2 := R2(R3)
 50 [-]: TEST      R2 1         ; if R2 then PC := 55
 51 [-]: JMP       55           ; PC := 55
 52 [-]: SELF      R2 R1 K14    ; R3 := R1; R2 := R1[0x768274d6]
 53 [-]: LOADBOOL  R4 1 0       ; R4 := true
 54 [-]: CALL      R2 3 1       ; R2(R3,R4)
 55 [-]: GETGLOBAL R2 K1        ; R2 := 0x89326c93
 56 [-]: SELF      R2 R2 K15    ; R3 := R2; R2 := R2[0x659d451f]
 57 [-]: GETGLOBAL R4 K16       ; R4 := 0x0a007b25
 58 [-]: GETGLOBAL R5 K17       ; R5 := ZERO_VECTOR
 59 [-]: LOADBOOL  R6 0 0       ; R6 := false
 60 [-]: CALL      R2 5 1       ; R2(R3,R4,R5,R6)
 61 [-]: GETGLOBAL R2 K10       ; R2 := _T
 62 [-]: SETTABLE  R2 K18 K19   ; R2["EndOfQuestOpen"] := false
 63 [-]: GETUPVAL  R2 U1        ; R2 := U1
 64 [-]: GETTABLE  R2 R2 K20    ; R2 := R2[0x9e3d3434]
 65 [-]: LOADBOOL  R3 0 0       ; R3 := false
 66 [-]: CALL      R2 2 1       ; R2(R3)
 67 [-]: GETGLOBAL R2 K0        ; R2 := 0x7b998233
 68 [-]: GETUPVAL  R3 U2        ; R3 := U2
 69 [-]: CALL      R2 2 2       ; R2 := R2(R3)
 70 [-]: TEST      R2 1         ; if R2 then PC := 76
 71 [-]: JMP       76           ; PC := 76
 72 [-]: GETUPVAL  R2 U2        ; R2 := U2
 73 [-]: SELF      R2 R2 K21    ; R3 := R2; R2 := R2[0x6cf1e476]
 74 [-]: LOADBOOL  R4 0 0       ; R4 := false
 75 [-]: CALL      R2 3 1       ; R2(R3,R4)
 76 [-]: GETGLOBAL R2 K0        ; R2 := 0x7b998233
 77 [-]: GETUPVAL  R3 U3        ; R3 := U3
 78 [-]: CALL      R2 2 2       ; R2 := R2(R3)
 79 [-]: TEST      R2 1         ; if R2 then PC := 85
 80 [-]: JMP       85           ; PC := 85
 81 [-]: GETUPVAL  R2 U3        ; R2 := U3
 82 [-]: SELF      R2 R2 K21    ; R3 := R2; R2 := R2[0x6cf1e476]
 83 [-]: LOADBOOL  R4 0 0       ; R4 := false
 84 [-]: CALL      R2 3 1       ; R2(R3,R4)
 85 [-]: RETURN    R0 1         ; return 


; Function #12:
;
; Name:            
; Defined at line: 250
; #Upvalues:       12
; #Parameters:     0
; Is_vararg:       0
; Max Stack Size:  8

  1 [-]: GETGLOBAL R0 K0        ; R0 := 0x7b998233
  2 [-]: GETGLOBAL R1 K1        ; R1 := 0xbe190284
  3 [-]: CALL      R0 2 2       ; R0 := R0(R1)
  4 [-]: TEST      R0 1         ; if R0 then PC := 10
  5 [-]: JMP       10           ; PC := 10
  6 [-]: GETGLOBAL R0 K1        ; R0 := 0xbe190284
  7 [-]: SELF      R0 R0 K2     ; R1 := R0; R0 := R0[0xc02f2cb8]
  8 [-]: LOADBOOL  R2 1 0       ; R2 := true
  9 [-]: CALL      R0 3 1       ; R0(R1,R2)
 10 [-]: GETGLOBAL R0 K3        ; R0 := _T
 11 [-]: GETTABLE  R0 R0 K4     ; R0 := R0["VitruvianStage"]
 12 [-]: EQ        1 R0 K5      ; if R0 == nil then PC := 17
 13 [-]: JMP       17           ; PC := 17
 14 [-]: GETGLOBAL R0 K3        ; R0 := _T
 15 [-]: GETTABLE  R0 R0 K4     ; R0 := R0["VitruvianStage"]
 16 [-]: SETUPVAL  R0 U0        ; U82 := R0
 17 [-]: GETUPVAL  R0 U1        ; R0 := U1
 18 [-]: GETTABLE  R0 R0 K6     ; R0 := R0[0x1146d233]
 19 [-]: GETGLOBAL R1 K7        ; R1 := 0x969b72cb
 20 [-]: GETGLOBAL R2 K8        ; R2 := 0x91fb2b2a
 21 [-]: GETGLOBAL R3 K9        ; R3 := 0x026db9c4
 22 [-]: CALL      R0 4 1       ; R0(R1,R2,R3)
 23 [-]: GETGLOBAL R0 K3        ; R0 := _T
 24 [-]: GETTABLE  R0 R0 K10    ; R0 := R0[0x1c5b546f]
 25 [-]: GETGLOBAL R1 K11       ; R1 := 0xae91e43b
 26 [-]: LOADNIL   R2 R2        ; R2 := nil
 27 [-]: GETGLOBAL R3 K12       ; R3 := 0xcd0165a3
 28 [-]: LOADK     R4 1         ; R4 := 1.000000
 29 [-]: CALL      R3 2 0       ; R3,... := R3(R4)
 30 [-]: CALL      R0 0 1       ; R0(R1,...)
 31 [-]: GETGLOBAL R0 K13       ; R0 := 0x2d0fad09
 32 [-]: LOADK     R1 K14       ; R1 := "Lotus.Interface.Libs.TimerMgr"
 33 [-]: CALL      R0 2 2       ; R0 := R0(R1)
 34 [-]: GETTABLE  R1 R0 K15    ; R1 := R0[0xde474187]
 35 [-]: CALL      R1 1 2       ; R1 := R1()
 36 [-]: SETUPVAL  R1 U2        ; U82 := R2
 37 [-]: LOADK     R1 0         ; R1 := 0.000000
 38 [-]: SETUPVAL  R1 U3        ; U82 := R3
 39 [-]: GETUPVAL  R1 U0        ; R1 := U0
 40 [-]: EQ        0 R1 K16     ; if R1 ~= 1.000000 then PC := 57
 41 [-]: JMP       57           ; PC := 57
 42 [-]: GETUPVAL  R1 U4        ; R1 := U4
 43 [-]: NEWTABLE  R2 0 2       ; R2 := {}
 44 [-]: GETUPVAL  R3 U5        ; R3 := U5
 45 [-]: GETTABLE  R3 R3 K18    ; R3 := R3["UNLOCKED_LOCK"]
 46 [-]: SETTABLE  R2 K17 R3    ; R2["Type"] := R3
 47 [-]: SETTABLE  R2 K19 K16   ; R2["Index"] := 1.000000
 48 [-]: SETTABLE  R1 K16 R2    ; R1[1.000000] := R2
 49 [-]: GETUPVAL  R1 U4        ; R1 := U4
 50 [-]: NEWTABLE  R2 0 2       ; R2 := {}
 51 [-]: GETUPVAL  R3 U5        ; R3 := U5
 52 [-]: GETTABLE  R3 R3 K21    ; R3 := R3["SLIDE"]
 53 [-]: SETTABLE  R2 K17 R3    ; R2["Type"] := R3
 54 [-]: SETTABLE  R2 K19 K16   ; R2["Index"] := 1.000000
 55 [-]: SETTABLE  R1 K20 R2    ; R1[2.000000] := R2
 56 [-]: JMP       146          ; PC := 146
 57 [-]: GETUPVAL  R1 U0        ; R1 := U0
 58 [-]: EQ        0 R1 K20     ; if R1 ~= 2.000000 then PC := 75
 59 [-]: JMP       75           ; PC := 75
 60 [-]: GETUPVAL  R1 U4        ; R1 := U4
 61 [-]: NEWTABLE  R2 0 2       ; R2 := {}
 62 [-]: GETUPVAL  R3 U5        ; R3 := U5
 63 [-]: GETTABLE  R3 R3 K18    ; R3 := R3["UNLOCKED_LOCK"]
 64 [-]: SETTABLE  R2 K17 R3    ; R2["Type"] := R3
 65 [-]: SETTABLE  R2 K19 K20   ; R2["Index"] := 2.000000
 66 [-]: SETTABLE  R1 K16 R2    ; R1[1.000000] := R2
 67 [-]: GETUPVAL  R1 U4        ; R1 := U4
 68 [-]: NEWTABLE  R2 0 2       ; R2 := {}
 69 [-]: GETUPVAL  R3 U5        ; R3 := U5
 70 [-]: GETTABLE  R3 R3 K21    ; R3 := R3["SLIDE"]
 71 [-]: SETTABLE  R2 K17 R3    ; R2["Type"] := R3
 72 [-]: SETTABLE  R2 K19 K20   ; R2["Index"] := 2.000000
 73 [-]: SETTABLE  R1 K20 R2    ; R1[2.000000] := R2
 74 [-]: JMP       146          ; PC := 146
 75 [-]: GETUPVAL  R1 U0        ; R1 := U0
 76 [-]: EQ        0 R1 K22     ; if R1 ~= 3.000000 then PC := 121
 77 [-]: JMP       121          ; PC := 121
 78 [-]: GETUPVAL  R1 U4        ; R1 := U4
 79 [-]: NEWTABLE  R2 0 2       ; R2 := {}
 80 [-]: GETUPVAL  R3 U5        ; R3 := U5
 81 [-]: GETTABLE  R3 R3 K18    ; R3 := R3["UNLOCKED_LOCK"]
 82 [-]: SETTABLE  R2 K17 R3    ; R2["Type"] := R3
 83 [-]: SETTABLE  R2 K19 K22   ; R2["Index"] := 3.000000
 84 [-]: SETTABLE  R1 K16 R2    ; R1[1.000000] := R2
 85 [-]: GETUPVAL  R1 U4        ; R1 := U4
 86 [-]: NEWTABLE  R2 0 2       ; R2 := {}
 87 [-]: GETUPVAL  R3 U5        ; R3 := U5
 88 [-]: GETTABLE  R3 R3 K21    ; R3 := R3["SLIDE"]
 89 [-]: SETTABLE  R2 K17 R3    ; R2["Type"] := R3
 90 [-]: SETTABLE  R2 K19 K22   ; R2["Index"] := 3.000000
 91 [-]: SETTABLE  R1 K20 R2    ; R1[2.000000] := R2
 92 [-]: GETUPVAL  R1 U4        ; R1 := U4
 93 [-]: NEWTABLE  R2 0 2       ; R2 := {}
 94 [-]: GETUPVAL  R3 U5        ; R3 := U5
 95 [-]: GETTABLE  R3 R3 K21    ; R3 := R3["SLIDE"]
 96 [-]: SETTABLE  R2 K17 R3    ; R2["Type"] := R3
 97 [-]: SETTABLE  R2 K19 K23   ; R2["Index"] := 4.000000
 98 [-]: SETTABLE  R1 K22 R2    ; R1[3.000000] := R2
 99 [-]: GETUPVAL  R1 U4        ; R1 := U4
100 [-]: NEWTABLE  R2 0 2       ; R2 := {}
101 [-]: GETUPVAL  R3 U5        ; R3 := U5
102 [-]: GETTABLE  R3 R3 K21    ; R3 := R3["SLIDE"]
103 [-]: SETTABLE  R2 K17 R3    ; R2["Type"] := R3
104 [-]: SETTABLE  R2 K19 K24   ; R2["Index"] := 5.000000
105 [-]: SETTABLE  R1 K23 R2    ; R1[4.000000] := R2
106 [-]: GETUPVAL  R1 U4        ; R1 := U4
107 [-]: NEWTABLE  R2 0 2       ; R2 := {}
108 [-]: GETUPVAL  R3 U5        ; R3 := U5
109 [-]: GETTABLE  R3 R3 K21    ; R3 := R3["SLIDE"]
110 [-]: SETTABLE  R2 K17 R3    ; R2["Type"] := R3
111 [-]: SETTABLE  R2 K19 K25   ; R2["Index"] := 6.000000
112 [-]: SETTABLE  R1 K24 R2    ; R1[5.000000] := R2
113 [-]: GETUPVAL  R1 U4        ; R1 := U4
114 [-]: NEWTABLE  R2 0 2       ; R2 := {}
115 [-]: GETUPVAL  R3 U5        ; R3 := U5
116 [-]: GETTABLE  R3 R3 K21    ; R3 := R3["SLIDE"]
117 [-]: SETTABLE  R2 K17 R3    ; R2["Type"] := R3
118 [-]: SETTABLE  R2 K19 K26   ; R2["Index"] := 7.000000
119 [-]: SETTABLE  R1 K25 R2    ; R1[6.000000] := R2
120 [-]: JMP       146          ; PC := 146
121 [-]: GETUPVAL  R1 U0        ; R1 := U0
122 [-]: EQ        0 R1 K23     ; if R1 ~= 4.000000 then PC := 146
123 [-]: JMP       146          ; PC := 146
124 [-]: GETUPVAL  R1 U4        ; R1 := U4
125 [-]: NEWTABLE  R2 0 2       ; R2 := {}
126 [-]: GETUPVAL  R3 U5        ; R3 := U5
127 [-]: GETTABLE  R3 R3 K18    ; R3 := R3["UNLOCKED_LOCK"]
128 [-]: SETTABLE  R2 K17 R3    ; R2["Type"] := R3
129 [-]: SETTABLE  R2 K19 K23   ; R2["Index"] := 4.000000
130 [-]: SETTABLE  R1 K16 R2    ; R1[1.000000] := R2
131 [-]: GETUPVAL  R1 U4        ; R1 := U4
132 [-]: NEWTABLE  R2 0 2       ; R2 := {}
133 [-]: GETUPVAL  R3 U5        ; R3 := U5
134 [-]: GETTABLE  R3 R3 K21    ; R3 := R3["SLIDE"]
135 [-]: SETTABLE  R2 K17 R3    ; R2["Type"] := R3
136 [-]: SETTABLE  R2 K19 K27   ; R2["Index"] := 8.000000
137 [-]: SETTABLE  R1 K20 R2    ; R1[2.000000] := R2
138 [-]: GETUPVAL  R1 U4        ; R1 := U4
139 [-]: NEWTABLE  R2 0 3       ; R2 := {}
140 [-]: GETUPVAL  R3 U5        ; R3 := U5
141 [-]: GETTABLE  R3 R3 K21    ; R3 := R3["SLIDE"]
142 [-]: SETTABLE  R2 K17 R3    ; R2["Type"] := R3
143 [-]: SETTABLE  R2 K19 K28   ; R2["Index"] := 9.000000
144 [-]: SETTABLE  R2 K29 K30   ; R2["AutoClose"] := true
145 [-]: SETTABLE  R1 K22 R2    ; R1[3.000000] := R2
146 [-]: GETGLOBAL R1 K31       ; R1 := 0x9ba7909f
147 [-]: SELF      R1 R1 K32    ; R2 := R1; R1 := R1[0xbcfb64ab]
148 [-]: GETGLOBAL R3 K33       ; R3 := 0x0662fad9
149 [-]: CALL      R1 3 2       ; R1 := R1(R2,R3)
150 [-]: GETGLOBAL R2 K0        ; R2 := 0x7b998233
151 [-]: MOVE      R3 R1        ; R3 := R1
152 [-]: CALL      R2 2 2       ; R2 := R2(R3)
153 [-]: TEST      R2 1         ; if R2 then PC := 157
154 [-]: JMP       157          ; PC := 157
155 [-]: SELF      R2 R1 K34    ; R3 := R1; R2 := R1[0x32302b4a]
156 [-]: CALL      R2 2 1       ; R2(R3)
157 [-]: GETUPVAL  R2 U6        ; R2 := U6
158 [-]: CALL      R2 1 1       ; R2()
159 [-]: GETGLOBAL R2 K0        ; R2 := 0x7b998233
160 [-]: GETGLOBAL R3 K3        ; R3 := _T
161 [-]: GETTABLE  R3 R3 K35    ; R3 := R3["ShowBackground"]
162 [-]: CALL      R2 2 2       ; R2 := R2(R3)
163 [-]: TEST      R2 1         ; if R2 then PC := 171
164 [-]: JMP       171          ; PC := 171
165 [-]: GETGLOBAL R2 K3        ; R2 := _T
166 [-]: GETTABLE  R2 R2 K36    ; R2 := R2[0xa460d8df]
167 [-]: LOADK     R3 0         ; R3 := 0.250000
168 [-]: LOADNIL   R4 R4        ; R4 := nil
169 [-]: LOADBOOL  R5 0 0       ; R5 := false
170 [-]: CALL      R2 4 1       ; R2(R3,R4,R5)
171 [-]: GETUPVAL  R2 U7        ; R2 := U7
172 [-]: GETTABLE  R2 R2 K37    ; R2 := R2[0x6ef45ebc]
173 [-]: CALL      R2 1 2       ; R2 := R2()
174 [-]: GETGLOBAL R3 K0        ; R3 := 0x7b998233
175 [-]: MOVE      R4 R2        ; R4 := R2
176 [-]: CALL      R3 2 2       ; R3 := R3(R4)
177 [-]: TEST      R3 1         ; if R3 then PC := 182
178 [-]: JMP       182          ; PC := 182
179 [-]: SELF      R3 R2 K38    ; R4 := R2; R3 := R2[0x768274d6]
180 [-]: LOADBOOL  R5 0 0       ; R5 := false
181 [-]: CALL      R3 3 1       ; R3(R4,R5)
182 [-]: GETGLOBAL R3 K11       ; R3 := 0xae91e43b
183 [-]: SELF      R3 R3 K39    ; R4 := R3; R3 := R3[0x67bc869f]
184 [-]: LOADK     R5 K40       ; R5 := "Slide1"
185 [-]: LOADK     R6 10        ; R6 := 10.000000
186 [-]: LOADK     R7 0         ; R7 := 0.000000
187 [-]: CALL      R3 5 1       ; R3(R4,R5,R6,R7)
188 [-]: GETGLOBAL R3 K11       ; R3 := 0xae91e43b
189 [-]: SELF      R3 R3 K39    ; R4 := R3; R3 := R3[0x67bc869f]
190 [-]: LOADK     R5 K41       ; R5 := "Slide2"
191 [-]: LOADK     R6 10        ; R6 := 10.000000
192 [-]: LOADK     R7 0         ; R7 := 0.000000
193 [-]: CALL      R3 5 1       ; R3(R4,R5,R6,R7)
194 [-]: GETGLOBAL R3 K11       ; R3 := 0xae91e43b
195 [-]: SELF      R3 R3 K42    ; R4 := R3; R3 := R3[0xd5181643]
196 [-]: LOADK     R5 K40       ; R5 := "Slide1"
197 [-]: GETGLOBAL R6 K43       ; R6 := 0xb8cd3c68
198 [-]: CALL      R3 4 1       ; R3(R4,R5,R6)
199 [-]: GETGLOBAL R3 K11       ; R3 := 0xae91e43b
200 [-]: SELF      R3 R3 K42    ; R4 := R3; R3 := R3[0xd5181643]
201 [-]: LOADK     R5 K44       ; R5 := "Pattern"
202 [-]: GETGLOBAL R6 K45       ; R6 := 0xb7bf3765
203 [-]: CALL      R3 4 1       ; R3(R4,R5,R6)
204 [-]: GETGLOBAL R3 K11       ; R3 := 0xae91e43b
205 [-]: SELF      R3 R3 K42    ; R4 := R3; R3 := R3[0xd5181643]
206 [-]: LOADK     R5 K46       ; R5 := "Pattern2"
207 [-]: GETGLOBAL R6 K45       ; R6 := 0xb7bf3765
208 [-]: CALL      R3 4 1       ; R3(R4,R5,R6)
209 [-]: GETUPVAL  R3 U8        ; R3 := U8
210 [-]: CALL      R3 1 1       ; R3()
211 [-]: GETUPVAL  R3 U9        ; R3 := U9
212 [-]: CALL      R3 1 1       ; R3()
213 [-]: GETGLOBAL R3 K3        ; R3 := _T
214 [-]: SETTABLE  R3 K47 K30   ; R3["EndOfQuestOpen"] := true
215 [-]: GETUPVAL  R3 U7        ; R3 := U7
216 [-]: GETTABLE  R3 R3 K48    ; R3 := R3[0x9e3d3434]
217 [-]: LOADBOOL  R4 1 0       ; R4 := true
218 [-]: CALL      R3 2 1       ; R3(R4)
219 [-]: GETGLOBAL R3 K49       ; R3 := 0x89326c93
220 [-]: SELF      R3 R3 K50    ; R4 := R3; R3 := R3[0x659d451f]
221 [-]: GETGLOBAL R5 K51       ; R5 := 0x0184bde9
222 [-]: GETGLOBAL R6 K52       ; R6 := ZERO_VECTOR
223 [-]: LOADBOOL  R7 0 0       ; R7 := false
224 [-]: CALL      R3 5 2       ; R3 := R3(R4,R5,R6,R7)
225 [-]: SETUPVAL  R3 U10       ; U82 := R10
226 [-]: GETGLOBAL R3 K49       ; R3 := 0x89326c93
227 [-]: SELF      R3 R3 K50    ; R4 := R3; R3 := R3[0x659d451f]
228 [-]: GETGLOBAL R5 K53       ; R5 := 0xa62db2fe
229 [-]: GETGLOBAL R6 K52       ; R6 := ZERO_VECTOR
230 [-]: LOADBOOL  R7 0 0       ; R7 := false
231 [-]: CALL      R3 5 2       ; R3 := R3(R4,R5,R6,R7)
232 [-]: SETUPVAL  R3 U11       ; U82 := R11
233 [-]: RETURN    R0 1         ; return 


; Function #13:
;
; Name:            
; Defined at line: 336
; #Upvalues:       8
; #Parameters:     0
; Is_vararg:       0
; Max Stack Size:  19

  1 [-]: GETGLOBAL R0 K0        ; R0 := 0x7b998233
  2 [-]: GETUPVAL  R1 U0        ; R1 := U0
  3 [-]: CALL      R0 2 2       ; R0 := R0(R1)
  4 [-]: TEST      R0 1         ; if R0 then PC := 11
  5 [-]: JMP       11           ; PC := 11
  6 [-]: GETUPVAL  R0 U0        ; R0 := U0
  7 [-]: SELF      R0 R0 K1     ; R1 := R0; R0 := R0[0xfaa69527]
  8 [-]: GETGLOBAL R2 K2        ; R2 := 0x67652851
  9 [-]: CALL      R2 1 0       ; R2,... := R2()
 10 [-]: CALL      R0 0 1       ; R0(R1,...)
 11 [-]: GETGLOBAL R0 K3        ; R0 := 0xae91e43b
 12 [-]: SELF      R0 R0 K4     ; R1 := R0; R0 := R0[0x8a8c8d5a]
 13 [-]: GETGLOBAL R2 K5        ; R2 := 0xb693b6c1
 14 [-]: CALL      R2 1 0       ; R2,... := R2()
 15 [-]: CALL      R0 0 1       ; R0(R1,...)
 16 [-]: GETGLOBAL R0 K2        ; R0 := 0x67652851
 17 [-]: CALL      R0 1 2       ; R0 := R0()
 18 [-]: GETUPVAL  R1 U1        ; R1 := U1
 19 [-]: GETUPVAL  R2 U1        ; R2 := U1
 20 [-]: GETTABLE  R2 R2 K6     ; R2 := R2["z"]
 21 [-]: GETUPVAL  R3 U1        ; R3 := U1
 22 [-]: GETTABLE  R3 R3 K7     ; R3 := R3["dir"]
 23 [-]: MUL       R3 R0 R3     ; R3 := R0 * R3
 24 [-]: MUL       R3 R3 K8     ; R3 := R3 * 0.045000
 25 [-]: ADD       R2 R2 R3     ; R2 := R2 + R3
 26 [-]: SETTABLE  R1 K6 R2     ; R1["z"] := R2
 27 [-]: GETUPVAL  R1 U1        ; R1 := U1
 28 [-]: GETTABLE  R1 R1 K6     ; R1 := R1["z"]
 29 [-]: LT        0 K9 R1      ; if 1.000000 >= R1 then PC := 41
 30 [-]: JMP       41           ; PC := 41
 31 [-]: GETUPVAL  R1 U1        ; R1 := U1
 32 [-]: GETTABLE  R1 R1 K7     ; R1 := R1["dir"]
 33 [-]: LT        0 K10 R1     ; if 0.000000 >= R1 then PC := 41
 34 [-]: JMP       41           ; PC := 41
 35 [-]: GETUPVAL  R1 U1        ; R1 := U1
 36 [-]: GETUPVAL  R2 U1        ; R2 := U1
 37 [-]: GETTABLE  R2 R2 K7     ; R2 := R2["dir"]
 38 [-]: UNM       R2 R2        ; R2 := ^ R2
 39 [-]: SETTABLE  R1 K7 R2     ; R1["dir"] := R2
 40 [-]: JMP       54           ; PC := 54
 41 [-]: GETUPVAL  R1 U1        ; R1 := U1
 42 [-]: GETTABLE  R1 R1 K6     ; R1 := R1["z"]
 43 [-]: LT        0 R1 K10     ; if R1 >= 0.000000 then PC := 54
 44 [-]: JMP       54           ; PC := 54
 45 [-]: GETUPVAL  R1 U1        ; R1 := U1
 46 [-]: GETTABLE  R1 R1 K7     ; R1 := R1["dir"]
 47 [-]: LT        0 R1 K10     ; if R1 >= 0.000000 then PC := 54
 48 [-]: JMP       54           ; PC := 54
 49 [-]: GETUPVAL  R1 U1        ; R1 := U1
 50 [-]: GETUPVAL  R2 U1        ; R2 := U1
 51 [-]: GETTABLE  R2 R2 K7     ; R2 := R2["dir"]
 52 [-]: UNM       R2 R2        ; R2 := ^ R2
 53 [-]: SETTABLE  R1 K7 R2     ; R1["dir"] := R2
 54 [-]: GETUPVAL  R1 U1        ; R1 := U1
 55 [-]: GETGLOBAL R2 K12       ; R2 := 0x9bafffe3
 56 [-]: GETUPVAL  R3 U1        ; R3 := U1
 57 [-]: GETTABLE  R3 R3 K11    ; R3 := R3["x"]
 58 [-]: GETUPVAL  R4 U1        ; R4 := U1
 59 [-]: GETTABLE  R4 R4 K13    ; R4 := R4["tx"]
 60 [-]: MUL       R5 R0 K14    ; R5 := R0 * 0.300000
 61 [-]: CALL      R2 4 2       ; R2 := R2(R3,R4,R5)
 62 [-]: SETTABLE  R1 K11 R2    ; R1["x"] := R2
 63 [-]: GETUPVAL  R1 U1        ; R1 := U1
 64 [-]: GETGLOBAL R2 K12       ; R2 := 0x9bafffe3
 65 [-]: GETUPVAL  R3 U1        ; R3 := U1
 66 [-]: GETTABLE  R3 R3 K15    ; R3 := R3["y"]
 67 [-]: GETUPVAL  R4 U1        ; R4 := U1
 68 [-]: GETTABLE  R4 R4 K16    ; R4 := R4["ty"]
 69 [-]: MUL       R5 R0 K14    ; R5 := R0 * 0.300000
 70 [-]: CALL      R2 4 2       ; R2 := R2(R3,R4,R5)
 71 [-]: SETTABLE  R1 K15 R2    ; R1["y"] := R2
 72 [-]: GETGLOBAL R1 K12       ; R1 := 0x9bafffe3
 73 [-]: LOADK     R2 105       ; R2 := 105.000000
 74 [-]: LOADK     R3 140       ; R3 := 140.000000
 75 [-]: GETGLOBAL R4 K17       ; R4 := 0xa533083a
 76 [-]: GETUPVAL  R5 U1        ; R5 := U1
 77 [-]: GETTABLE  R5 R5 K6     ; R5 := R5["z"]
 78 [-]: CALL      R4 2 0       ; R4,... := R4(R5)
 79 [-]: CALL      R1 0 2       ; R1 := R1(R2,...)
 80 [-]: GETGLOBAL R2 K12       ; R2 := 0x9bafffe3
 81 [-]: LOADK     R3 5000      ; R3 := 5000.000000
 82 [-]: LOADK     R4 -5000     ; R4 := -5000.000000
 83 [-]: GETGLOBAL R5 K17       ; R5 := 0xa533083a
 84 [-]: GETUPVAL  R6 U1        ; R6 := U1
 85 [-]: GETTABLE  R6 R6 K6     ; R6 := R6["z"]
 86 [-]: CALL      R5 2 0       ; R5,... := R5(R6)
 87 [-]: CALL      R2 0 2       ; R2 := R2(R3,...)
 88 [-]: GETGLOBAL R3 K12       ; R3 := 0x9bafffe3
 89 [-]: GETUPVAL  R4 U2        ; R4 := U2
 90 [-]: DIV       R4 K18 R4    ; R4 := -0.500000 / R4
 91 [-]: GETUPVAL  R5 U2        ; R5 := U2
 92 [-]: DIV       R5 K19 R5    ; R5 := 0.500000 / R5
 93 [-]: GETGLOBAL R6 K17       ; R6 := 0xa533083a
 94 [-]: GETUPVAL  R7 U1        ; R7 := U1
 95 [-]: GETTABLE  R7 R7 K6     ; R7 := R7["z"]
 96 [-]: CALL      R6 2 0       ; R6,... := R6(R7)
 97 [-]: CALL      R3 0 2       ; R3 := R3(R4,...)
 98 [-]: GETGLOBAL R4 K12       ; R4 := 0x9bafffe3
 99 [-]: LOADK     R5 K20       ; R5 := 0.020000
100 [-]: LOADK     R6 K21       ; R6 := 0.001000
101 [-]: GETGLOBAL R7 K22       ; R7 := 0x5bced4c4
102 [-]: GETTABLE  R7 R7 K23    ; R7 := R7[0xa40531d8]
103 [-]: GETGLOBAL R8 K3        ; R8 := 0xae91e43b
104 [-]: SELF      R8 R8 K24    ; R9 := R8; R8 := R8[0x91a24e4b]
105 [-]: LOADK     R10 K25      ; R10 := "Slide1"
106 [-]: LOADK     R11 10       ; R11 := 10.000000
107 [-]: CALL      R8 4 2       ; R8 := R8(R9,R10,R11)
108 [-]: DIV       R8 R8 K26    ; R8 := R8 / 100.000000
109 [-]: LOADK     R9 0         ; R9 := 0.500000
110 [-]: CALL      R7 3 0       ; R7,... := R7(R8,R9)
111 [-]: CALL      R4 0 2       ; R4 := R4(R5,...)
112 [-]: GETGLOBAL R5 K12       ; R5 := 0x9bafffe3
113 [-]: LOADK     R6 0         ; R6 := 0.000000
114 [-]: LOADK     R7 -200      ; R7 := -200.000000
115 [-]: GETGLOBAL R8 K17       ; R8 := 0xa533083a
116 [-]: GETUPVAL  R9 U1        ; R9 := U1
117 [-]: GETTABLE  R9 R9 K6     ; R9 := R9["z"]
118 [-]: CALL      R8 2 0       ; R8,... := R8(R9)
119 [-]: CALL      R5 0 2       ; R5 := R5(R6,...)
120 [-]: GETGLOBAL R6 K12       ; R6 := 0x9bafffe3
121 [-]: LOADK     R7 0         ; R7 := 0.000000
122 [-]: LOADK     R8 -112      ; R8 := -112.500000
123 [-]: GETGLOBAL R9 K17       ; R9 := 0xa533083a
124 [-]: GETUPVAL  R10 U1       ; R10 := U1
125 [-]: GETTABLE  R10 R10 K6   ; R10 := R10["z"]
126 [-]: CALL      R9 2 0       ; R9,... := R9(R10)
127 [-]: CALL      R6 0 2       ; R6 := R6(R7,...)
128 [-]: GETGLOBAL R7 K12       ; R7 := 0x9bafffe3
129 [-]: GETGLOBAL R8 K3        ; R8 := 0xae91e43b
130 [-]: SELF      R8 R8 K24    ; R9 := R8; R8 := R8[0x91a24e4b]
131 [-]: LOADK     R10 K27      ; R10 := "_root"
132 [-]: LOADK     R11 0        ; R11 := 0.000000
133 [-]: CALL      R8 4 2       ; R8 := R8(R9,R10,R11)
134 [-]: MOVE      R9 R5        ; R9 := R5
135 [-]: MUL       R10 R0 K28   ; R10 := R0 * 10.000000
136 [-]: CALL      R7 4 2       ; R7 := R7(R8,R9,R10)
137 [-]: MOVE      R5 R7        ; R5 := R7
138 [-]: GETGLOBAL R7 K12       ; R7 := 0x9bafffe3
139 [-]: GETGLOBAL R8 K3        ; R8 := 0xae91e43b
140 [-]: SELF      R8 R8 K24    ; R9 := R8; R8 := R8[0x91a24e4b]
141 [-]: LOADK     R10 K27      ; R10 := "_root"
142 [-]: LOADK     R11 1        ; R11 := 1.000000
143 [-]: CALL      R8 4 2       ; R8 := R8(R9,R10,R11)
144 [-]: MOVE      R9 R6        ; R9 := R6
145 [-]: MUL       R10 R0 K28   ; R10 := R0 * 10.000000
146 [-]: CALL      R7 4 2       ; R7 := R7(R8,R9,R10)
147 [-]: MOVE      R6 R7        ; R6 := R7
148 [-]: GETGLOBAL R7 K3        ; R7 := 0xae91e43b
149 [-]: SELF      R7 R7 K29    ; R8 := R7; R7 := R7[0x67bc869f]
150 [-]: LOADK     R9 K27       ; R9 := "_root"
151 [-]: LOADK     R10 0        ; R10 := 0.000000
152 [-]: MOVE      R11 R5       ; R11 := R5
153 [-]: CALL      R7 5 1       ; R7(R8,R9,R10,R11)
154 [-]: GETGLOBAL R7 K3        ; R7 := 0xae91e43b
155 [-]: SELF      R7 R7 K29    ; R8 := R7; R7 := R7[0x67bc869f]
156 [-]: LOADK     R9 K27       ; R9 := "_root"
157 [-]: LOADK     R10 1        ; R10 := 1.000000
158 [-]: MOVE      R11 R6       ; R11 := R6
159 [-]: CALL      R7 5 1       ; R7(R8,R9,R10,R11)
160 [-]: GETGLOBAL R7 K3        ; R7 := 0xae91e43b
161 [-]: SELF      R7 R7 K30    ; R8 := R7; R7 := R7[0x091c120e]
162 [-]: CALL      R7 2 2       ; R7 := R7(R8)
163 [-]: ADD       R8 K31 R5    ; R8 := 140.000000 + R5
164 [-]: SUB       R7 R7 R8     ; R7 := R7 - R8
165 [-]: DIV       R8 R1 K26    ; R8 := R1 / 100.000000
166 [-]: DIV       R7 R7 R8     ; R7 := R7 / R8
167 [-]: GETGLOBAL R8 K3        ; R8 := 0xae91e43b
168 [-]: SELF      R8 R8 K32    ; R9 := R8; R8 := R8[0x2cc9d281]
169 [-]: CALL      R8 2 2       ; R8 := R8(R9)
170 [-]: ADD       R9 K26 R6    ; R9 := 100.000000 + R6
171 [-]: SUB       R8 R8 R9     ; R8 := R8 - R9
172 [-]: DIV       R9 R1 K26    ; R9 := R1 / 100.000000
173 [-]: DIV       R8 R8 R9     ; R8 := R8 / R9
174 [-]: GETGLOBAL R9 K3        ; R9 := 0xae91e43b
175 [-]: SELF      R9 R9 K29    ; R10 := R9; R9 := R9[0x67bc869f]
176 [-]: LOADK     R11 K33      ; R11 := "NextButton"
177 [-]: LOADK     R12 0        ; R12 := 0.000000
178 [-]: MOVE      R13 R7       ; R13 := R7
179 [-]: CALL      R9 5 1       ; R9(R10,R11,R12,R13)
180 [-]: GETGLOBAL R9 K3        ; R9 := 0xae91e43b
181 [-]: SELF      R9 R9 K29    ; R10 := R9; R9 := R9[0x67bc869f]
182 [-]: LOADK     R11 K33      ; R11 := "NextButton"
183 [-]: LOADK     R12 1        ; R12 := 1.000000
184 [-]: MOVE      R13 R8       ; R13 := R8
185 [-]: CALL      R9 5 1       ; R9(R10,R11,R12,R13)
186 [-]: GETGLOBAL R9 K3        ; R9 := 0xae91e43b
187 [-]: SELF      R9 R9 K29    ; R10 := R9; R9 := R9[0x67bc869f]
188 [-]: LOADK     R11 K27      ; R11 := "_root"
189 [-]: LOADK     R12 5        ; R12 := 5.000000
190 [-]: MOVE      R13 R1       ; R13 := R1
191 [-]: CALL      R9 5 1       ; R9(R10,R11,R12,R13)
192 [-]: GETGLOBAL R9 K3        ; R9 := 0xae91e43b
193 [-]: SELF      R9 R9 K29    ; R10 := R9; R9 := R9[0x67bc869f]
194 [-]: LOADK     R11 K27      ; R11 := "_root"
195 [-]: LOADK     R12 6        ; R12 := 6.000000
196 [-]: MOVE      R13 R1       ; R13 := R1
197 [-]: CALL      R9 5 1       ; R9(R10,R11,R12,R13)
198 [-]: GETGLOBAL R9 K3        ; R9 := 0xae91e43b
199 [-]: SELF      R9 R9 K29    ; R10 := R9; R9 := R9[0x67bc869f]
200 [-]: LOADK     R11 K33      ; R11 := "NextButton"
201 [-]: LOADK     R12 5        ; R12 := 5.000000
202 [-]: SUB       R13 R1 K26   ; R13 := R1 - 100.000000
203 [-]: SUB       R13 K34 R13  ; R13 := 120.000000 - R13
204 [-]: CALL      R9 5 1       ; R9(R10,R11,R12,R13)
205 [-]: GETGLOBAL R9 K3        ; R9 := 0xae91e43b
206 [-]: SELF      R9 R9 K29    ; R10 := R9; R9 := R9[0x67bc869f]
207 [-]: LOADK     R11 K33      ; R11 := "NextButton"
208 [-]: LOADK     R12 6        ; R12 := 6.000000
209 [-]: SUB       R13 R1 K26   ; R13 := R1 - 100.000000
210 [-]: SUB       R13 K34 R13  ; R13 := 120.000000 - R13
211 [-]: CALL      R9 5 1       ; R9(R10,R11,R12,R13)
212 [-]: GETGLOBAL R9 K3        ; R9 := 0xae91e43b
213 [-]: SELF      R9 R9 K29    ; R10 := R9; R9 := R9[0x67bc869f]
214 [-]: LOADK     R11 K35      ; R11 := "Pattern"
215 [-]: LOADK     R12 4        ; R12 := 4.000000
216 [-]: MOVE      R13 R2       ; R13 := R2
217 [-]: CALL      R9 5 1       ; R9(R10,R11,R12,R13)
218 [-]: GETGLOBAL R9 K3        ; R9 := 0xae91e43b
219 [-]: SELF      R9 R9 K29    ; R10 := R9; R9 := R9[0x67bc869f]
220 [-]: LOADK     R11 K36      ; R11 := "Pattern2"
221 [-]: LOADK     R12 4        ; R12 := 4.000000
222 [-]: MOVE      R13 R2       ; R13 := R2
223 [-]: CALL      R9 5 1       ; R9(R10,R11,R12,R13)
224 [-]: GETGLOBAL R9 K3        ; R9 := 0xae91e43b
225 [-]: SELF      R9 R9 K37    ; R10 := R9; R9 := R9[0x91e13703]
226 [-]: LOADK     R11 K25      ; R11 := "Slide1"
227 [-]: LOADK     R12 K38      ; R12 := "PlasmaStrength_PlasmaTopAtten_PlasmaBottomAtten"
228 [-]: MOVE      R13 R4       ; R13 := R4
229 [-]: LOADK     R14 1        ; R14 := 1.000000
230 [-]: LOADK     R15 1        ; R15 := 1.000000
231 [-]: LOADK     R16 0        ; R16 := 0.000000
232 [-]: CALL      R9 8 1       ; R9(R10,R11,R12,R13,R14,R15,R16)
233 [-]: GETGLOBAL R9 K3        ; R9 := 0xae91e43b
234 [-]: SELF      R9 R9 K37    ; R10 := R9; R9 := R9[0x91e13703]
235 [-]: LOADK     R11 K35      ; R11 := "Pattern"
236 [-]: LOADK     R12 K39      ; R12 := "TileOffset"
237 [-]: MUL       R13 R3 K40   ; R13 := R3 * -0.750000
238 [-]: LOADK     R14 0        ; R14 := 0.000000
239 [-]: LOADK     R15 1        ; R15 := 1.000000
240 [-]: LOADK     R16 1        ; R16 := 1.000000
241 [-]: CALL      R9 8 1       ; R9(R10,R11,R12,R13,R14,R15,R16)
242 [-]: GETGLOBAL R9 K3        ; R9 := 0xae91e43b
243 [-]: SELF      R9 R9 K37    ; R10 := R9; R9 := R9[0x91e13703]
244 [-]: LOADK     R11 K36      ; R11 := "Pattern2"
245 [-]: LOADK     R12 K39      ; R12 := "TileOffset"
246 [-]: MUL       R13 R3 K19   ; R13 := R3 * 0.500000
247 [-]: LOADK     R14 0        ; R14 := 0.000000
248 [-]: LOADK     R15 1        ; R15 := 1.000000
249 [-]: LOADK     R16 1        ; R16 := 1.000000
250 [-]: CALL      R9 8 1       ; R9(R10,R11,R12,R13,R14,R15,R16)
251 [-]: LOADBOOL  R9 0 0       ; R9 := false
252 [-]: GETUPVAL  R10 U3       ; R10 := U3
253 [-]: TEST      R10 0        ; if not R10 then PC := 267
254 [-]: JMP       267          ; PC := 267
255 [-]: GETGLOBAL R10 K0       ; R10 := 0x7b998233
256 [-]: GETGLOBAL R11 K41      ; R11 := _T
257 [-]: GETTABLE  R11 R11 K42  ; R11 := R11["curTransmission"]
258 [-]: CALL      R10 2 2      ; R10 := R10(R11)
259 [-]: TEST      R10 1        ; if R10 then PC := 263
260 [-]: JMP       263          ; PC := 263
261 [-]: TEST      R9 0         ; if not R9 then PC := 267
262 [-]: JMP       267          ; PC := 267
263 [-]: LOADBOOL  R10 0 0      ; R10 := false
264 [-]: SETUPVAL  R10 U3       ; U82 := R3
265 [-]: GETUPVAL  R10 U4       ; R10 := U4
266 [-]: CALL      R10 1 1      ; R10()
267 [-]: GETUPVAL  R10 U5       ; R10 := U5
268 [-]: TEST      R10 0        ; if not R10 then PC := 294
269 [-]: JMP       294          ; PC := 294
270 [-]: GETGLOBAL R10 K0       ; R10 := 0x7b998233
271 [-]: GETGLOBAL R11 K41      ; R11 := _T
272 [-]: GETTABLE  R11 R11 K42  ; R11 := R11["curTransmission"]
273 [-]: CALL      R10 2 2      ; R10 := R10(R11)
274 [-]: TEST      R10 1        ; if R10 then PC := 278
275 [-]: JMP       278          ; PC := 278
276 [-]: TEST      R9 0         ; if not R9 then PC := 294
277 [-]: JMP       294          ; PC := 294
278 [-]: LOADBOOL  R10 0 0      ; R10 := false
279 [-]: SETUPVAL  R10 U5       ; U82 := R5
280 [-]: GETGLOBAL R10 K43      ; R10 := 0x25312c9b
281 [-]: GETGLOBAL R11 K3       ; R11 := 0xae91e43b
282 [-]: LOADK     R12 K27      ; R12 := "_root"
283 [-]: LOADK     R13 0        ; R13 := 0.000000
284 [-]: NEWTABLE  R14 1 0      ; R14 := {}
285 [-]: LOADK     R15 10       ; R15 := 10.000000
286 [-]: SETLIST   R14 1 1      ; R14[(1-1)*FPF+i] := R(14+i), 1 <= i <= 1
287 [-]: NEWTABLE  R15 1 0      ; R15 := {}
288 [-]: LOADK     R16 0        ; R16 := 0.000000
289 [-]: SETLIST   R15 1 1      ; R15[(1-1)*FPF+i] := R(15+i), 1 <= i <= 1
290 [-]: LOADK     R16 0        ; R16 := 0.250000
291 [-]: LOADK     R17 0        ; R17 := 0.000000
292 [-]: GETUPVAL  R18 U6       ; R18 := U6
293 [-]: CALL      R10 9 1      ; R10(R11,R12,R13,R14,R15,R16,R17,R18)
294 [-]: LOADK     R10 0        ; R10 := 0.000000
295 [-]: GETGLOBAL R11 K41      ; R11 := _T
296 [-]: GETTABLE  R11 R11 K45  ; R11 := R11["FullscreenOverlayTransmissionAmplitude"]
297 [-]: EQ        1 R11 K46    ; if R11 == nil then PC := 301
298 [-]: JMP       301          ; PC := 301
299 [-]: GETGLOBAL R11 K41      ; R11 := _T
300 [-]: GETTABLE  R10 R11 K45  ; R10 := R11["FullscreenOverlayTransmissionAmplitude"]
301 [-]: GETGLOBAL R11 K12      ; R11 := 0x9bafffe3
302 [-]: LOADK     R12 K47      ; R12 := 0.065000
303 [-]: LOADK     R13 K48      ; R13 := 0.150000
304 [-]: MOVE      R14 R10      ; R14 := R10
305 [-]: CALL      R11 4 2      ; R11 := R11(R12,R13,R14)
306 [-]: MOVE      R10 R11      ; R10 := R11
307 [-]: GETUPVAL  R11 U7       ; R11 := U7
308 [-]: EQ        1 R11 R10    ; if R11 == R10 then PC := 329
309 [-]: JMP       329          ; PC := 329
310 [-]: SETUPVAL  R10 U7       ; U82 := R7
311 [-]: GETGLOBAL R11 K3       ; R11 := 0xae91e43b
312 [-]: SELF      R11 R11 K37  ; R12 := R11; R11 := R11[0x91e13703]
313 [-]: LOADK     R13 K35      ; R13 := "Pattern"
314 [-]: LOADK     R14 K49      ; R14 := "TileStrength"
315 [-]: MOVE      R15 R10      ; R15 := R10
316 [-]: LOADK     R16 1        ; R16 := 1.000000
317 [-]: LOADK     R17 1        ; R17 := 1.000000
318 [-]: LOADK     R18 1        ; R18 := 1.000000
319 [-]: CALL      R11 8 1      ; R11(R12,R13,R14,R15,R16,R17,R18)
320 [-]: GETGLOBAL R11 K3       ; R11 := 0xae91e43b
321 [-]: SELF      R11 R11 K37  ; R12 := R11; R11 := R11[0x91e13703]
322 [-]: LOADK     R13 K36      ; R13 := "Pattern2"
323 [-]: LOADK     R14 K49      ; R14 := "TileStrength"
324 [-]: MOVE      R15 R10      ; R15 := R10
325 [-]: LOADK     R16 1        ; R16 := 1.000000
326 [-]: LOADK     R17 1        ; R17 := 1.000000
327 [-]: LOADK     R18 1        ; R18 := 1.000000
328 [-]: CALL      R11 8 1      ; R11(R12,R13,R14,R15,R16,R17,R18)
329 [-]: RETURN    R0 1         ; return 


; Function #14:
;
; Name:            
; Defined at line: 408
; #Upvalues:       0
; #Parameters:     0
; Is_vararg:       0
; Max Stack Size:  2

  1 [-]: LOADBOOL  R0 1 0       ; R0 := true
  2 [-]: RETURN    R0 2         ; return R0
  3 [-]: RETURN    R0 1         ; return 


; Function #15:
;
; Name:            
; Defined at line: 412
; #Upvalues:       1
; #Parameters:     0
; Is_vararg:       0
; Max Stack Size:  2

  1 [-]: GETUPVAL  R0 U0        ; R0 := U0
  2 [-]: CALL      R0 1 1       ; R0()
  3 [-]: RETURN    R0 1         ; return 


; Function #16:
;
; Name:            
; Defined at line: 416
; #Upvalues:       2
; #Parameters:     0
; Is_vararg:       0
; Max Stack Size:  5

  1 [-]: GETUPVAL  R0 U0        ; R0 := U0
  2 [-]: GETTABLE  R0 R0 K0     ; R0 := R0[0x659d451f]
  3 [-]: GETGLOBAL R1 K1        ; R1 := 0xbd14708a
  4 [-]: CALL      R0 2 1       ; R0(R1)
  5 [-]: GETGLOBAL R0 K2        ; R0 := 0xae91e43b
  6 [-]: SELF      R0 R0 K3     ; R1 := R0; R0 := R0[0x67bc869f]
  7 [-]: LOADK     R2 K4        ; R2 := "NextButton"
  8 [-]: LOADK     R3 9         ; R3 := 9.000000
  9 [-]: GETUPVAL  R4 U1        ; R4 := U1
 10 [-]: CALL      R0 5 1       ; R0(R1,R2,R3,R4)
 11 [-]: RETURN    R0 1         ; return 


; Function #17:
;
; Name:            
; Defined at line: 421
; #Upvalues:       1
; #Parameters:     0
; Is_vararg:       0
; Max Stack Size:  5

  1 [-]: GETGLOBAL R0 K0        ; R0 := 0xae91e43b
  2 [-]: SELF      R0 R0 K1     ; R1 := R0; R0 := R0[0x67bc869f]
  3 [-]: LOADK     R2 K2        ; R2 := "NextButton"
  4 [-]: LOADK     R3 9         ; R3 := 9.000000
  5 [-]: GETUPVAL  R4 U0        ; R4 := U0
  6 [-]: CALL      R0 5 1       ; R0(R1,R2,R3,R4)
  7 [-]: RETURN    R0 1         ; return 


; Function #18:
;
; Name:            
; Defined at line: 425
; #Upvalues:       2
; #Parameters:     0
; Is_vararg:       0
; Max Stack Size:  2

  1 [-]: GETUPVAL  R0 U0        ; R0 := U0
  2 [-]: GETTABLE  R0 R0 K0     ; R0 := R0[0x659d451f]
  3 [-]: GETGLOBAL R1 K1        ; R1 := 0x5e03aa8a
  4 [-]: CALL      R0 2 1       ; R0(R1)
  5 [-]: GETUPVAL  R0 U1        ; R0 := U1
  6 [-]: CALL      R0 1 1       ; R0()
  7 [-]: RETURN    R0 1         ; return 


