; This file has been disassembled using luadec 2.0.2 by sztupy (modified by Reversive)

; Name:            
; Defined at line: 0
; #Upvalues:       0
; #Parameters:     0
; Is_vararg:       2
; Max Stack Size:  37

  1 [-]: GETGLOBAL R0 K0        ; R0 := 0x2d0fad09
  2 [-]: LOADK     R1 K1        ; R1 := "Lotus.Scripts.Libs.TransmissionSet"
  3 [-]: CALL      R0 2 2       ; R0 := R0(R1)
  4 [-]: GETGLOBAL R1 K0        ; R1 := 0x2d0fad09
  5 [-]: LOADK     R2 K2        ; R2 := "Lotus.Scripts.Libs.ObjectiveText"
  6 [-]: CALL      R1 2 2       ; R1 := R1(R2)
  7 [-]: GETGLOBAL R2 K0        ; R2 := 0x2d0fad09
  8 [-]: LOADK     R3 K3        ; R3 := "Lotus.Scripts.Libs.RailjackUtilities"
  9 [-]: CALL      R2 2 2       ; R2 := R2(R3)
 10 [-]: GETGLOBAL R3 K0        ; R3 := 0x2d0fad09
 11 [-]: LOADK     R4 K4        ; R4 := "Lotus.Scripts.Libs.PanicLib"
 12 [-]: CALL      R3 2 2       ; R3 := R3(R4)
 13 [-]: GETGLOBAL R4 K0        ; R4 := 0x2d0fad09
 14 [-]: LOADK     R5 K5        ; R5 := "Lotus.Interface.LotusUtilities"
 15 [-]: CALL      R4 2 2       ; R4 := R4(R5)
 16 [-]: LOADK     R5 1         ; R5 := 1.000000
 17 [-]: LOADK     R6 2         ; R6 := 2.000000
 18 [-]: LOADK     R7 3         ; R7 := 3.000000
 19 [-]: LOADK     R8 4         ; R8 := 4.000000
 20 [-]: LOADK     R9 5         ; R9 := 5.000000
 21 [-]: LOADK     R10 99       ; R10 := 99.000000
 22 [-]: GETGLOBAL R11 K6       ; R11 := INVALID
 23 [-]: LOADNIL   R12 R12      ; R12 := nil
 24 [-]: LOADK     R13 K7       ; R13 := 0.100000
 25 [-]: LOADNIL   R14 R24      ; R14 := R15 := R16 := R17 := R18 := R19 := R20 := R21 := R22 := R23 := R24 := nil
 26 [-]: LOADK     R25 K8       ; R25 := "[HC] RETRIEVE COORDINATES FROM PILOT: "
 27 [-]: LOADK     R26 K9       ; R26 := "[HC] PICK UP COORDINATES: "
 28 [-]: GETGLOBAL R27 K10      ; R27 := 0x0469f296
 29 [-]: LOADK     R28 K11      ; R28 := "CrewShipPilot"
 30 [-]: CALL      R27 2 2      ; R27 := R27(R28)
 31 [-]: CLOSURE   R28 0        ; R28 := closure(Function #1)
 32 [-]: MOVE      R0 R3        ; R0 := R3
 33 [-]: SETGLOBAL R28 K12      ; NPCAlertStart := R28
 34 [-]: CLOSURE   R28 1        ; R28 := closure(Function #2)
 35 [-]: MOVE      R0 R3        ; R0 := R3
 36 [-]: SETGLOBAL R28 K13      ; NPCAlertEnd := R28
 37 [-]: CLOSURE   R28 2        ; R28 := closure(Function #3)
 38 [-]: MOVE      R0 R21       ; R0 := R21
 39 [-]: CLOSURE   R29 3        ; R29 := closure(Function #4)
 40 [-]: MOVE      R0 R18       ; R0 := R18
 41 [-]: MOVE      R0 R28       ; R0 := R28
 42 [-]: MOVE      R0 R20       ; R0 := R20
 43 [-]: MOVE      R0 R2        ; R0 := R2
 44 [-]: MOVE      R0 R19       ; R0 := R19
 45 [-]: CLOSURE   R30 4        ; R30 := closure(Function #5)
 46 [-]: MOVE      R0 R11       ; R0 := R11
 47 [-]: MOVE      R0 R10       ; R0 := R10
 48 [-]: CLOSURE   R31 5        ; R31 := closure(Function #6)
 49 [-]: MOVE      R0 R22       ; R0 := R22
 50 [-]: MOVE      R0 R17       ; R0 := R17
 51 [-]: CLOSURE   R32 6        ; R32 := closure(Function #7)
 52 [-]: MOVE      R0 R2        ; R0 := R2
 53 [-]: MOVE      R0 R19       ; R0 := R19
 54 [-]: MOVE      R0 R20       ; R0 := R20
 55 [-]: MOVE      R0 R27       ; R0 := R27
 56 [-]: MOVE      R0 R18       ; R0 := R18
 57 [-]: MOVE      R0 R17       ; R0 := R17
 58 [-]: MOVE      R0 R15       ; R0 := R15
 59 [-]: CLOSURE   R33 7        ; R33 := closure(Function #8)
 60 [-]: MOVE      R0 R11       ; R0 := R11
 61 [-]: MOVE      R0 R6        ; R0 := R6
 62 [-]: MOVE      R0 R32       ; R0 := R32
 63 [-]: MOVE      R0 R22       ; R0 := R22
 64 [-]: MOVE      R0 R4        ; R0 := R4
 65 [-]: MOVE      R0 R25       ; R0 := R25
 66 [-]: MOVE      R0 R7        ; R0 := R7
 67 [-]: MOVE      R0 R8        ; R0 := R8
 68 [-]: MOVE      R0 R26       ; R0 := R26
 69 [-]: MOVE      R0 R9        ; R0 := R9
 70 [-]: MOVE      R0 R10       ; R0 := R10
 71 [-]: MOVE      R0 R19       ; R0 := R19
 72 [-]: MOVE      R0 R2        ; R0 := R2
 73 [-]: MOVE      R0 R15       ; R0 := R15
 74 [-]: CLOSURE   R34 8        ; R34 := closure(Function #9)
 75 [-]: MOVE      R0 R15       ; R0 := R15
 76 [-]: MOVE      R0 R23       ; R0 := R23
 77 [-]: MOVE      R0 R24       ; R0 := R24
 78 [-]: MOVE      R0 R17       ; R0 := R17
 79 [-]: MOVE      R0 R14       ; R0 := R14
 80 [-]: MOVE      R0 R16       ; R0 := R16
 81 [-]: MOVE      R0 R12       ; R0 := R12
 82 [-]: MOVE      R0 R6        ; R0 := R6
 83 [-]: CLOSURE   R35 9        ; R35 := closure(Function #10)
 84 [-]: MOVE      R0 R11       ; R0 := R11
 85 [-]: MOVE      R0 R6        ; R0 := R6
 86 [-]: MOVE      R0 R18       ; R0 := R18
 87 [-]: MOVE      R0 R12       ; R0 := R12
 88 [-]: MOVE      R0 R7        ; R0 := R7
 89 [-]: MOVE      R0 R20       ; R0 := R20
 90 [-]: MOVE      R0 R29       ; R0 := R29
 91 [-]: MOVE      R0 R8        ; R0 := R8
 92 [-]: MOVE      R0 R21       ; R0 := R21
 93 [-]: MOVE      R0 R9        ; R0 := R9
 94 [-]: MOVE      R0 R10       ; R0 := R10
 95 [-]: CLOSURE   R12 10       ; R12 := closure(Function #11)
 96 [-]: MOVE      R0 R11       ; R0 := R11
 97 [-]: MOVE      R0 R15       ; R0 := R15
 98 [-]: MOVE      R0 R33       ; R0 := R33
 99 [-]: CLOSURE   R36 11       ; R36 := closure(Function #12)
100 [-]: SETGLOBAL R36 K14      ; CanActivateCrewshipDataObjective := R36
101 [-]: CLOSURE   R36 12       ; R36 := closure(Function #13)
102 [-]: MOVE      R0 R34       ; R0 := R34
103 [-]: MOVE      R0 R13       ; R0 := R13
104 [-]: MOVE      R0 R30       ; R0 := R30
105 [-]: MOVE      R0 R35       ; R0 := R35
106 [-]: MOVE      R0 R31       ; R0 := R31
107 [-]: SETGLOBAL R36 K15      ; CrewShipNavDataEncounter := R36
108 [-]: RETURN    R0 1         ; return 


; Function #1:
;
; Name:            
; Defined at line: 50
; #Upvalues:       1
; #Parameters:     1
; Is_vararg:       0
; Max Stack Size:  3

  1 [-]: GETUPVAL  R1 U0        ; R1 := U0
  2 [-]: GETTABLE  R1 R1 K0     ; R1 := R1[0x67a78dad]
  3 [-]: GETUPVAL  R2 U0        ; R2 := U0
  4 [-]: GETTABLE  R2 R2 K1     ; R2 := R2["ALERT"]
  5 [-]: CALL      R1 2 1       ; R1(R2)
  6 [-]: RETURN    R0 1         ; return 


; Function #2:
;
; Name:            
; Defined at line: 54
; #Upvalues:       1
; #Parameters:     1
; Is_vararg:       0
; Max Stack Size:  3

  1 [-]: GETUPVAL  R1 U0        ; R1 := U0
  2 [-]: GETTABLE  R1 R1 K0     ; R1 := R1[0x67a78dad]
  3 [-]: GETUPVAL  R2 U0        ; R2 := U0
  4 [-]: GETTABLE  R2 R2 K1     ; R2 := R2["UNALERT"]
  5 [-]: CALL      R1 2 1       ; R1(R2)
  6 [-]: RETURN    R0 1         ; return 


; Function #3:
;
; Name:            
; Defined at line: 58
; #Upvalues:       1
; #Parameters:     1
; Is_vararg:       0
; Max Stack Size:  7

  1 [-]: SELF      R1 R0 K0     ; R2 := R0; R1 := R0[0xd1586535]
  2 [-]: CALL      R1 2 2       ; R1 := R1(R2)
  3 [-]: GETGLOBAL R2 K1        ; R2 := 0x89326c93
  4 [-]: SELF      R2 R2 K2     ; R3 := R2; R2 := R2[0x05909209]
  5 [-]: GETGLOBAL R4 K3        ; R4 := 0xc5ad911b
  6 [-]: MOVE      R5 R1        ; R5 := R1
  7 [-]: GETGLOBAL R6 K4        ; R6 := ZERO_ROTATION
  8 [-]: CALL      R2 5 2       ; R2 := R2(R3,R4,R5,R6)
  9 [-]: SETUPVAL  R2 U0        ; U82 := R0
 10 [-]: GETUPVAL  R2 U0        ; R2 := U0
 11 [-]: SELF      R2 R2 K5     ; R3 := R2; R2 := R2[0xc9f6a7d7]
 12 [-]: GETGLOBAL R4 K6        ; R4 := gBaseMarkerInfoType
 13 [-]: CALL      R2 3 2       ; R2 := R2(R3,R4)
 14 [-]: GETGLOBAL R3 K7        ; R3 := 0x7b998233
 15 [-]: MOVE      R4 R2        ; R4 := R2
 16 [-]: CALL      R3 2 2       ; R3 := R3(R4)
 17 [-]: TEST      R3 1         ; if R3 then PC := 21
 18 [-]: JMP       21           ; PC := 21
 19 [-]: SELF      R3 R2 K8     ; R4 := R2; R3 := R2[0x383d2e7d]
 20 [-]: CALL      R3 2 1       ; R3(R4)
 21 [-]: RETURN    R0 1         ; return 


; Function #4:
;
; Name:            
; Defined at line: 68
; #Upvalues:       5
; #Parameters:     1
; Is_vararg:       0
; Max Stack Size:  11

  1 [-]: GETGLOBAL R1 K0        ; R1 := 0x7b998233
  2 [-]: MOVE      R2 R0        ; R2 := R0
  3 [-]: CALL      R1 2 2       ; R1 := R1(R2)
  4 [-]: TEST      R1 1         ; if R1 then PC := 39
  5 [-]: JMP       39           ; PC := 39
  6 [-]: GETUPVAL  R1 U0        ; R1 := U0
  7 [-]: EQ        0 R0 R1      ; if R0 ~= R1 then PC := 13
  8 [-]: JMP       13           ; PC := 13
  9 [-]: GETUPVAL  R1 U1        ; R1 := U1
 10 [-]: MOVE      R2 R0        ; R2 := R0
 11 [-]: CALL      R1 2 1       ; R1(R2)
 12 [-]: JMP       39           ; PC := 39
 13 [-]: GETUPVAL  R1 U2        ; R1 := U2
 14 [-]: EQ        0 R0 R1      ; if R0 ~= R1 then PC := 39
 15 [-]: JMP       39           ; PC := 39
 16 [-]: GETUPVAL  R1 U3        ; R1 := U3
 17 [-]: GETTABLE  R1 R1 K1     ; R1 := R1[0x2f6f2966]
 18 [-]: GETGLOBAL R2 K2        ; R2 := 0xc5ad911b
 19 [-]: GETUPVAL  R3 U4        ; R3 := U4
 20 [-]: CALL      R1 3 2       ; R1 := R1(R2,R3)
 21 [-]: LEN       R2 R1        ; R2 := # R1
 22 [-]: LT        0 K3 R2      ; if 0.000000 >= R2 then PC := 36
 23 [-]: JMP       36           ; PC := 36
 24 [-]: LOADK     R2 1         ; R2 := 1.000000
 25 [-]: LEN       R3 R1        ; R3 := # R1
 26 [-]: LOADK     R4 1         ; R4 := 1.000000
 27 [-]: FORPREP   R2 34        ; R2 -= R4; PC := 34
 28 [-]: GETTABLE  R6 R1 R5     ; R6 := R1[R5]
 29 [-]: SELF      R7 R6 K4     ; R8 := R6; R7 := R6[0x589ef1c1]
 30 [-]: SELF      R9 R0 K5     ; R10 := R0; R9 := R0[0xd1586535]
 31 [-]: CALL      R9 2 2       ; R9 := R9(R10)
 32 [-]: GETGLOBAL R10 K6       ; R10 := ZERO_ROTATION
 33 [-]: CALL      R7 4 1       ; R7(R8,R9,R10)
 34 [-]: FORLOOP   R2 28        ; R2 += R4; if R2 <= R3 then begin PC := 28; R5 := R2 end
 35 [-]: JMP       39           ; PC := 39
 36 [-]: GETUPVAL  R7 U1        ; R7 := U1
 37 [-]: MOVE      R8 R0        ; R8 := R0
 38 [-]: CALL      R7 2 1       ; R7(R8)
 39 [-]: RETURN    R0 1         ; return 


; Function #5:
;
; Name:            
; Defined at line: 87
; #Upvalues:       2
; #Parameters:     0
; Is_vararg:       0
; Max Stack Size:  6

  1 [-]: GETGLOBAL R0 K0        ; R0 := 0xbe190284
  2 [-]: SELF      R0 R0 K1     ; R1 := R0; R0 := R0[0xd7d79b74]
  3 [-]: CALL      R0 2 2       ; R0 := R0(R1)
  4 [-]: SELF      R1 R0 K2     ; R2 := R0; R1 := R0[0xcd57f819]
  5 [-]: CALL      R1 2 2       ; R1 := R1(R2)
  6 [-]: SELF      R2 R1 K3     ; R3 := R1; R2 := R1[0x5163741e]
  7 [-]: CALL      R2 2 2       ; R2 := R2(R3)
  8 [-]: SELF      R3 R2 K4     ; R4 := R2; R3 := R2[0x9e4623d9]
  9 [-]: CALL      R3 2 2       ; R3 := R3(R4)
 10 [-]: GETUPVAL  R4 U0        ; R4 := U0
 11 [-]: GETUPVAL  R5 U1        ; R5 := U1
 12 [-]: EQ        1 R4 R5      ; if R4 == R5 then PC := 18
 13 [-]: JMP       18           ; PC := 18
 14 [-]: EQ        1 R3 K6      ; if R3 == 3.000000 then PC := 18
 15 [-]: JMP       18           ; PC := 18
 16 [-]: EQ        0 R3 K7      ; if R3 ~= 4.000000 then PC := 20
 17 [-]: JMP       20           ; PC := 20
 18 [-]: LOADBOOL  R4 1 0       ; R4 := true
 19 [-]: RETURN    R4 2         ; return R4
 20 [-]: LOADBOOL  R4 0 0       ; R4 := false
 21 [-]: RETURN    R4 2         ; return R4
 22 [-]: RETURN    R0 1         ; return 


; Function #6:
;
; Name:            
; Defined at line: 100
; #Upvalues:       2
; #Parameters:     1
; Is_vararg:       0
; Max Stack Size:  4

  1 [-]: GETGLOBAL R1 K0        ; R1 := _T
  2 [-]: GETTABLE  R1 R1 K1     ; R1 := R1[0x1a41a3c1]
  3 [-]: GETUPVAL  R2 U0        ; R2 := U0
  4 [-]: CALL      R1 2 1       ; R1(R2)
  5 [-]: GETUPVAL  R1 U1        ; R1 := U1
  6 [-]: SELF      R1 R1 K2     ; R2 := R1; R1 := R1[0x2faead12]
  7 [-]: LOADBOOL  R3 0 0       ; R3 := false
  8 [-]: CALL      R1 3 1       ; R1(R2,R3)
  9 [-]: RETURN    R0 1         ; return 


; Function #7:
;
; Name:            
; Defined at line: 107
; #Upvalues:       7
; #Parameters:     0
; Is_vararg:       0
; Max Stack Size:  26

  1 [-]: GETGLOBAL R0 K0        ; R0 := 0xbe190284
  2 [-]: SELF      R0 R0 K1     ; R1 := R0; R0 := R0[0xd7d79b74]
  3 [-]: CALL      R0 2 2       ; R0 := R0(R1)
  4 [-]: LOADNIL   R1 R1        ; R1 := nil
  5 [-]: GETGLOBAL R2 K2        ; R2 := 0x7b998233
  6 [-]: MOVE      R3 R1        ; R3 := R1
  7 [-]: CALL      R2 2 2       ; R2 := R2(R3)
  8 [-]: TEST      R2 0         ; if not R2 then PC := 74
  9 [-]: JMP       74           ; PC := 74
 10 [-]: SELF      R2 R0 K3     ; R3 := R0; R2 := R0[0x1b68b9f9]
 11 [-]: LOADBOOL  R4 0 0       ; R4 := false
 12 [-]: CALL      R2 3 2       ; R2 := R2(R3,R4)
 13 [-]: MOVE      R1 R2        ; R1 := R2
 14 [-]: GETGLOBAL R2 K2        ; R2 := 0x7b998233
 15 [-]: MOVE      R3 R1        ; R3 := R1
 16 [-]: CALL      R2 2 2       ; R2 := R2(R3)
 17 [-]: TEST      R2 1         ; if R2 then PC := 22
 18 [-]: JMP       22           ; PC := 22
 19 [-]: LEN       R2 R1        ; R2 := # R1
 20 [-]: EQ        0 R2 K4      ; if R2 ~= 0.000000 then PC := 64
 21 [-]: JMP       64           ; PC := 64
 22 [-]: GETGLOBAL R2 K5        ; R2 := 0x89326c93
 23 [-]: SELF      R2 R2 K6     ; R3 := R2; R2 := R2[0x29ef273d]
 24 [-]: CALL      R2 2 2       ; R2 := R2(R3)
 25 [-]: SELF      R2 R2 K7     ; R3 := R2; R2 := R2[0x66905cb0]
 26 [-]: CALL      R2 2 2       ; R2 := R2(R3)
 27 [-]: SELF      R2 R2 K8     ; R3 := R2; R2 := R2[0x4f5a2d3b]
 28 [-]: CALL      R2 2 2       ; R2 := R2(R3)
 29 [-]: SELF      R3 R0 K3     ; R4 := R0; R3 := R0[0x1b68b9f9]
 30 [-]: LOADBOOL  R5 1 0       ; R5 := true
 31 [-]: CALL      R3 3 2       ; R3 := R3(R4,R5)
 32 [-]: GETTABLE  R4 R3 K9     ; R4 := R3[1.000000]
 33 [-]: SELF      R4 R4 K10    ; R5 := R4; R4 := R4[0x5163741e]
 34 [-]: CALL      R4 2 2       ; R4 := R4(R5)
 35 [-]: GETUPVAL  R5 U0        ; R5 := U0
 36 [-]: GETTABLE  R5 R5 K11    ; R5 := R5[0x40dfe79a]
 37 [-]: MOVE      R6 R2        ; R6 := R2
 38 [-]: MOVE      R7 R4        ; R7 := R4
 39 [-]: GETGLOBAL R8 K12       ; R8 := 0xb7cbd06b
 40 [-]: LOADK     R9 1500      ; R9 := 1500.000000
 41 [-]: LOADK     R10 6000     ; R10 := 6000.000000
 42 [-]: CALL      R8 3 2       ; R8 := R8(R9,R10)
 43 [-]: LOADK     R9 30        ; R9 := 30.000000
 44 [-]: CALL      R5 5 2       ; R5 := R5(R6,R7,R8,R9)
 45 [-]: MOVE      R2 R5        ; R2 := R5
 46 [-]: SELF      R5 R2 K13    ; R6 := R2; R5 := R2[0xf04f37dd]
 47 [-]: CALL      R5 2 2       ; R5 := R5(R6)
 48 [-]: LEN       R6 R5        ; R6 := # R5
 49 [-]: LT        0 K4 R6      ; if 0.000000 >= R6 then PC := 70
 50 [-]: JMP       70           ; PC := 70
 51 [-]: GETGLOBAL R6 K14       ; R6 := 0x55730e1a
 52 [-]: LOADK     R7 1         ; R7 := 1.000000
 53 [-]: LEN       R8 R5        ; R8 := # R5
 54 [-]: CALL      R6 3 2       ; R6 := R6(R7,R8)
 55 [-]: GETTABLE  R7 R5 R6     ; R7 := R5[R6]
 56 [-]: SELF      R8 R0 K15    ; R9 := R0; R8 := R0[0xe091ca15]
 57 [-]: GETGLOBAL R10 K16      ; R10 := 0x93cd7be9
 58 [-]: LOADNIL   R11 R11      ; R11 := nil
 59 [-]: LOADBOOL  R12 0 0      ; R12 := false
 60 [-]: LOADBOOL  R13 0 0      ; R13 := false
 61 [-]: CALL      R8 6 2       ; R8 := R8(R9,R10,R11,R12,R13)
 62 [-]: SETUPVAL  R8 U1        ; U82 := R1
 63 [-]: JMP       70           ; PC := 70
 64 [-]: GETGLOBAL R8 K17       ; R8 := 0x0c5e62f9
 65 [-]: LOADK     R9 1         ; R9 := 1.000000
 66 [-]: LEN       R10 R1       ; R10 := # R1
 67 [-]: CALL      R8 3 2       ; R8 := R8(R9,R10)
 68 [-]: GETTABLE  R8 R1 R8     ; R8 := R1[R8]
 69 [-]: SETUPVAL  R8 U1        ; U82 := R1
 70 [-]: GETGLOBAL R8 K18       ; R8 := 0xcbd666e1
 71 [-]: LOADK     R9 5         ; R9 := 5.000000
 72 [-]: CALL      R8 2 1       ; R8(R9)
 73 [-]: JMP       5            ; PC := 5
 74 [-]: GETGLOBAL R8 K18       ; R8 := 0xcbd666e1
 75 [-]: LOADK     R9 0         ; R9 := 0.000000
 76 [-]: CALL      R8 2 1       ; R8(R9)
 77 [-]: GETGLOBAL R8 K2        ; R8 := 0x7b998233
 78 [-]: GETUPVAL  R9 U1        ; R9 := U1
 79 [-]: CALL      R8 2 2       ; R8 := R8(R9)
 80 [-]: TEST      R8 1         ; if R8 then PC := 212
 81 [-]: JMP       212          ; PC := 212
 82 [-]: GETUPVAL  R8 U1        ; R8 := U1
 83 [-]: SELF      R8 R8 K10    ; R9 := R8; R8 := R8[0x5163741e]
 84 [-]: CALL      R8 2 2       ; R8 := R8(R9)
 85 [-]: SETUPVAL  R8 U2        ; U82 := R2
 86 [-]: GETGLOBAL R8 K19       ; R8 := 0x11a19c5e
 87 [-]: GETUPVAL  R9 U2        ; R9 := U2
 88 [-]: LOADK     R10 K20      ; R10 := "OnKilled"
 89 [-]: CALL      R8 3 1       ; R8(R9,R10)
 90 [-]: GETUPVAL  R8 U0        ; R8 := U0
 91 [-]: GETTABLE  R8 R8 K21    ; R8 := R8[0x2df8b2ba]
 92 [-]: GETUPVAL  R9 U3        ; R9 := U3
 93 [-]: GETUPVAL  R10 U1       ; R10 := U1
 94 [-]: CALL      R8 3 2       ; R8 := R8(R9,R10)
 95 [-]: GETGLOBAL R9 K2        ; R9 := 0x7b998233
 96 [-]: MOVE      R10 R8       ; R10 := R8
 97 [-]: CALL      R9 2 2       ; R9 := R9(R10)
 98 [-]: TEST      R9 1         ; if R9 then PC := 111
 99 [-]: JMP       111          ; PC := 111
100 [-]: SETUPVAL  R8 U4        ; U82 := R4
101 [-]: GETUPVAL  R9 U4        ; R9 := U4
102 [-]: SELF      R9 R9 K22    ; R10 := R9; R9 := R9[0x47901f07]
103 [-]: GETGLOBAL R11 K23      ; R11 := 0xb3ea4254
104 [-]: GETGLOBAL R12 K24      ; R12 := EMPTY_SYMBOL
105 [-]: CALL      R9 4 1       ; R9(R10,R11,R12)
106 [-]: GETUPVAL  R9 U0        ; R9 := U0
107 [-]: GETTABLE  R9 R9 K25    ; R9 := R9[0x33d25c2b]
108 [-]: LOADBOOL  R10 1 0      ; R10 := true
109 [-]: GETUPVAL  R11 U1       ; R11 := U1
110 [-]: CALL      R9 3 1       ; R9(R10,R11)
111 [-]: GETUPVAL  R9 U0        ; R9 := U0
112 [-]: GETTABLE  R9 R9 K26    ; R9 := R9[0x2f6f2966]
113 [-]: GETGLOBAL R10 K27      ; R10 := gNpcSpawnPointType
114 [-]: GETUPVAL  R11 U1       ; R11 := U1
115 [-]: CALL      R9 3 2       ; R9 := R9(R10,R11)
116 [-]: GETGLOBAL R10 K14      ; R10 := 0x55730e1a
117 [-]: LOADK     R11 1        ; R11 := 1.000000
118 [-]: LEN       R12 R9       ; R12 := # R9
119 [-]: CALL      R10 3 2      ; R10 := R10(R11,R12)
120 [-]: GETTABLE  R11 R9 R10   ; R11 := R9[R10]
121 [-]: GETGLOBAL R12 K2       ; R12 := 0x7b998233
122 [-]: MOVE      R13 R11      ; R13 := R11
123 [-]: CALL      R12 2 2      ; R12 := R12(R13)
124 [-]: TEST      R12 1        ; if R12 then PC := 212
125 [-]: JMP       212          ; PC := 212
126 [-]: GETGLOBAL R12 K2       ; R12 := 0x7b998233
127 [-]: GETUPVAL  R13 U2       ; R13 := U2
128 [-]: CALL      R12 2 2      ; R12 := R12(R13)
129 [-]: TEST      R12 1        ; if R12 then PC := 212
130 [-]: JMP       212          ; PC := 212
131 [-]: GETGLOBAL R12 K0       ; R12 := 0xbe190284
132 [-]: SELF      R12 R12 K28  ; R13 := R12; R12 := R12[0xef893aec]
133 [-]: CALL      R12 2 2      ; R12 := R12(R13)
134 [-]: GETGLOBAL R13 K14      ; R13 := 0x55730e1a
135 [-]: GETTABLE  R14 R12 K29  ; R14 := R12["minEnemyLevel"]
136 [-]: GETTABLE  R15 R12 K30  ; R15 := R12["maxEnemyLevel"]
137 [-]: CALL      R13 3 2      ; R13 := R13(R14,R15)
138 [-]: GETUPVAL  R14 U5       ; R14 := U5
139 [-]: SELF      R14 R14 K31  ; R15 := R14; R14 := R14[0xfeeea290]
140 [-]: GETGLOBAL R16 K32      ; R16 := 0x5aa2084e
141 [-]: MOVE      R17 R13      ; R17 := R13
142 [-]: LOADBOOL  R18 1 0      ; R18 := true
143 [-]: LOADBOOL  R19 0 0      ; R19 := false
144 [-]: GETGLOBAL R20 K33      ; R20 := 0x55d44493
145 [-]: LOADBOOL  R21 1 0      ; R21 := true
146 [-]: CALL      R14 8 2      ; R14 := R14(R15,R16,R17,R18,R19,R20,R21)
147 [-]: GETGLOBAL R15 K2       ; R15 := 0x7b998233
148 [-]: MOVE      R16 R14      ; R16 := R14
149 [-]: CALL      R15 2 2      ; R15 := R15(R16)
150 [-]: TEST      R15 0        ; if not R15 then PC := 158
151 [-]: JMP       158          ; PC := 158
152 [-]: GETGLOBAL R15 K34      ; R15 := 0xd644c2f1
153 [-]: LOADK     R16 K35      ; R16 := "Enemy target type is Nil -- AI Spec Issue? Tier: "
154 [-]: GETGLOBAL R17 K33      ; R17 := 0x55d44493
155 [-]: CONCAT    R16 R16 R17  ; R16 := R16 .. R17
156 [-]: CALL      R15 2 1      ; R15(R16)
157 [-]: GETGLOBAL R14 K36      ; R14 := 0x058def74
158 [-]: GETUPVAL  R15 U5       ; R15 := U5
159 [-]: SELF      R15 R15 K37  ; R16 := R15; R15 := R15[0x33fc842f]
160 [-]: MOVE      R17 R14      ; R17 := R14
161 [-]: MOVE      R18 R11      ; R18 := R11
162 [-]: GETGLOBAL R19 K38      ; R19 := 0x529c5b23
163 [-]: MOVE      R20 R13      ; R20 := R13
164 [-]: CALL      R15 6 2      ; R15 := R15(R16,R17,R18,R19,R20)
165 [-]: SELF      R16 R15 K39  ; R17 := R15; R16 := R15[0xbb610e5b]
166 [-]: CALL      R16 2 2      ; R16 := R16(R17)
167 [-]: GETGLOBAL R17 K2       ; R17 := 0x7b998233
168 [-]: MOVE      R18 R16      ; R18 := R16
169 [-]: CALL      R17 2 2      ; R17 := R17(R18)
170 [-]: TEST      R17 0        ; if not R17 then PC := 179
171 [-]: JMP       179          ; PC := 179
172 [-]: SELF      R17 R15 K39  ; R18 := R15; R17 := R15[0xbb610e5b]
173 [-]: CALL      R17 2 2      ; R17 := R17(R18)
174 [-]: MOVE      R16 R17      ; R16 := R17
175 [-]: GETGLOBAL R17 K18      ; R17 := 0xcbd666e1
176 [-]: LOADK     R18 0        ; R18 := 0.000000
177 [-]: CALL      R17 2 1      ; R17(R18)
178 [-]: JMP       167          ; PC := 167
179 [-]: GETGLOBAL R17 K19      ; R17 := 0x11a19c5e
180 [-]: MOVE      R18 R16      ; R18 := R16
181 [-]: LOADK     R19 K20      ; R19 := "OnKilled"
182 [-]: CALL      R17 3 1      ; R17(R18,R19)
183 [-]: GETUPVAL  R17 U6       ; R17 := U6
184 [-]: SELF      R17 R17 K40  ; R18 := R17; R17 := R17[0x2fb0041c]
185 [-]: MOVE      R19 R15      ; R19 := R15
186 [-]: CALL      R17 3 1      ; R17(R18,R19)
187 [-]: SELF      R17 R16 K41  ; R18 := R16; R17 := R16[0xc1595bd5]
188 [-]: GETGLOBAL R19 K23      ; R19 := 0xb3ea4254
189 [-]: CALL      R17 3 2      ; R17 := R17(R18,R19)
190 [-]: LOADK     R18 1        ; R18 := 1.000000
191 [-]: LEN       R19 R17      ; R19 := # R17
192 [-]: LOADK     R20 1        ; R20 := 1.000000
193 [-]: FORPREP   R18 206      ; R18 -= R20; PC := 206
194 [-]: GETTABLE  R22 R17 R21  ; R22 := R17[R21]
195 [-]: GETGLOBAL R23 K2       ; R23 := 0x7b998233
196 [-]: MOVE      R24 R22      ; R24 := R22
197 [-]: CALL      R23 2 2      ; R23 := R23(R24)
198 [-]: TEST      R23 1        ; if R23 then PC := 206
199 [-]: JMP       206          ; PC := 206
200 [-]: SELF      R23 R22 K42  ; R24 := R22; R23 := R22[0xf37943ff]
201 [-]: CALL      R23 2 2      ; R23 := R23(R24)
202 [-]: TEST      R23 1        ; if R23 then PC := 206
203 [-]: JMP       206          ; PC := 206
204 [-]: SELF      R23 R22 K43  ; R24 := R22; R23 := R22[0x383d2e7d]
205 [-]: CALL      R23 2 1      ; R23(R24)
206 [-]: FORLOOP   R18 194      ; R18 += R20; if R18 <= R19 then begin PC := 194; R21 := R18 end
207 [-]: GETUPVAL  R23 U0       ; R23 := U0
208 [-]: GETTABLE  R23 R23 K44  ; R23 := R23[0x0c97556b]
209 [-]: LOADBOOL  R24 1 0      ; R24 := true
210 [-]: GETUPVAL  R25 U1       ; R25 := U1
211 [-]: CALL      R23 3 1      ; R23(R24,R25)
212 [-]: RETURN    R0 1         ; return 


; Function #8:
;
; Name:            
; Defined at line: 184
; #Upvalues:       14
; #Parameters:     0
; Is_vararg:       0
; Max Stack Size:  5

  1 [-]: GETUPVAL  R0 U0        ; R0 := U0
  2 [-]: GETUPVAL  R1 U1        ; R1 := U1
  3 [-]: EQ        0 R0 R1      ; if R0 ~= R1 then PC := 26
  4 [-]: JMP       26           ; PC := 26
  5 [-]: GETUPVAL  R0 U2        ; R0 := U2
  6 [-]: CALL      R0 1 1       ; R0()
  7 [-]: GETGLOBAL R0 K0        ; R0 := _T
  8 [-]: GETTABLE  R0 R0 K1     ; R0 := R0[0x8ee923fe]
  9 [-]: LOADK     R1 K2        ; R1 := "KillObjective"
 10 [-]: GETUPVAL  R2 U4        ; R2 := U4
 11 [-]: GETTABLE  R2 R2 K3     ; R2 := R2["HT_LABEL"]
 12 [-]: CALL      R0 3 2       ; R0 := R0(R1,R2)
 13 [-]: SETUPVAL  R0 U3        ; U82 := R3
 14 [-]: GETUPVAL  R0 U3        ; R0 := U3
 15 [-]: GETTABLE  R0 R0 K4     ; R0 := R0[0x3f8a850c]
 16 [-]: GETUPVAL  R1 U3        ; R1 := U3
 17 [-]: GETTABLE  R1 R1 K5     ; R1 := R1[0x603636ad]
 18 [-]: GETUPVAL  R2 U5        ; R2 := U5
 19 [-]: CALL      R1 2 2       ; R1 := R1(R2)
 20 [-]: LOADK     R2 0         ; R2 := 0.000000
 21 [-]: LOADK     R3 K6        ; R3 := "/"
 22 [-]: LOADK     R4 1         ; R4 := 1.000000
 23 [-]: CONCAT    R1 R1 R4     ; R1 := R1 .. R2 .. R3 .. R4
 24 [-]: CALL      R0 2 1       ; R0(R1)
 25 [-]: JMP       79           ; PC := 79
 26 [-]: GETUPVAL  R0 U0        ; R0 := U0
 27 [-]: GETUPVAL  R1 U6        ; R1 := U6
 28 [-]: EQ        0 R0 R1      ; if R0 ~= R1 then PC := 31
 29 [-]: JMP       31           ; PC := 31
 30 [-]: JMP       79           ; PC := 79
 31 [-]: GETUPVAL  R0 U0        ; R0 := U0
 32 [-]: GETUPVAL  R1 U7        ; R1 := U7
 33 [-]: EQ        0 R0 R1      ; if R0 ~= R1 then PC := 47
 34 [-]: JMP       47           ; PC := 47
 35 [-]: GETUPVAL  R0 U3        ; R0 := U3
 36 [-]: GETTABLE  R0 R0 K4     ; R0 := R0[0x3f8a850c]
 37 [-]: GETUPVAL  R1 U3        ; R1 := U3
 38 [-]: GETTABLE  R1 R1 K5     ; R1 := R1[0x603636ad]
 39 [-]: GETUPVAL  R2 U8        ; R2 := U8
 40 [-]: CALL      R1 2 2       ; R1 := R1(R2)
 41 [-]: LOADK     R2 0         ; R2 := 0.000000
 42 [-]: LOADK     R3 K6        ; R3 := "/"
 43 [-]: LOADK     R4 1         ; R4 := 1.000000
 44 [-]: CONCAT    R1 R1 R4     ; R1 := R1 .. R2 .. R3 .. R4
 45 [-]: CALL      R0 2 1       ; R0(R1)
 46 [-]: JMP       79           ; PC := 79
 47 [-]: GETUPVAL  R0 U0        ; R0 := U0
 48 [-]: GETUPVAL  R1 U9        ; R1 := U9
 49 [-]: EQ        0 R0 R1      ; if R0 ~= R1 then PC := 56
 50 [-]: JMP       56           ; PC := 56
 51 [-]: GETGLOBAL R0 K0        ; R0 := _T
 52 [-]: GETTABLE  R0 R0 K7     ; R0 := R0[0x1a41a3c1]
 53 [-]: GETUPVAL  R1 U3        ; R1 := U3
 54 [-]: CALL      R0 2 1       ; R0(R1)
 55 [-]: JMP       79           ; PC := 79
 56 [-]: GETUPVAL  R0 U0        ; R0 := U0
 57 [-]: GETUPVAL  R1 U10       ; R1 := U10
 58 [-]: EQ        0 R0 R1      ; if R0 ~= R1 then PC := 79
 59 [-]: JMP       79           ; PC := 79
 60 [-]: GETGLOBAL R0 K8        ; R0 := 0x7b998233
 61 [-]: GETUPVAL  R1 U11       ; R1 := U11
 62 [-]: CALL      R0 2 2       ; R0 := R0(R1)
 63 [-]: TEST      R0 1         ; if R0 then PC := 75
 64 [-]: JMP       75           ; PC := 75
 65 [-]: GETUPVAL  R0 U12       ; R0 := U12
 66 [-]: GETTABLE  R0 R0 K9     ; R0 := R0[0x33d25c2b]
 67 [-]: LOADBOOL  R1 0 0       ; R1 := false
 68 [-]: GETUPVAL  R2 U11       ; R2 := U11
 69 [-]: CALL      R0 3 1       ; R0(R1,R2)
 70 [-]: GETUPVAL  R0 U12       ; R0 := U12
 71 [-]: GETTABLE  R0 R0 K10    ; R0 := R0[0x0c97556b]
 72 [-]: LOADBOOL  R1 0 0       ; R1 := false
 73 [-]: GETUPVAL  R2 U11       ; R2 := U11
 74 [-]: CALL      R0 3 1       ; R0(R1,R2)
 75 [-]: GETUPVAL  R0 U13       ; R0 := U13
 76 [-]: SELF      R0 R0 K11    ; R1 := R0; R0 := R0[0xfe9dc265]
 77 [-]: LOADK     R2 4         ; R2 := 4.000000
 78 [-]: CALL      R0 3 1       ; R0(R1,R2)
 79 [-]: RETURN    R0 1         ; return 


; Function #9:
;
; Name:            
; Defined at line: 203
; #Upvalues:       8
; #Parameters:     1
; Is_vararg:       0
; Max Stack Size:  6

  1 [-]: SETUPVAL  R0 U0        ; U82 := R0
  2 [-]: GETUPVAL  R1 U0        ; R1 := U0
  3 [-]: SELF      R1 R1 K0     ; R2 := R1; R1 := R1[0x4c976eda]
  4 [-]: CALL      R1 2 2       ; R1 := R1(R2)
  5 [-]: SETUPVAL  R1 U1        ; U82 := R1
  6 [-]: GETUPVAL  R1 U1        ; R1 := U1
  7 [-]: SELF      R1 R1 K1     ; R2 := R1; R1 := R1[0xe4c355e2]
  8 [-]: CALL      R1 2 2       ; R1 := R1(R2)
  9 [-]: SETUPVAL  R1 U2        ; U82 := R2
 10 [-]: GETGLOBAL R1 K2        ; R1 := 0x89326c93
 11 [-]: SELF      R1 R1 K3     ; R2 := R1; R1 := R1[0x29ef273d]
 12 [-]: CALL      R1 2 2       ; R1 := R1(R2)
 13 [-]: SELF      R1 R1 K4     ; R2 := R1; R1 := R1[0x66905cb0]
 14 [-]: CALL      R1 2 2       ; R1 := R1(R2)
 15 [-]: SETUPVAL  R1 U3        ; U82 := R3
 16 [-]: GETUPVAL  R1 U3        ; R1 := U3
 17 [-]: SELF      R1 R1 K5     ; R2 := R1; R1 := R1[0xa2d83ed4]
 18 [-]: CALL      R1 2 2       ; R1 := R1(R2)
 19 [-]: TEST      R1 1         ; if R1 then PC := 25
 20 [-]: JMP       25           ; PC := 25
 21 [-]: GETGLOBAL R1 K6        ; R1 := 0xcbd666e1
 22 [-]: LOADK     R2 0         ; R2 := 0.000000
 23 [-]: CALL      R1 2 1       ; R1(R2)
 24 [-]: JMP       16           ; PC := 16
 25 [-]: SELF      R1 R0 K7     ; R2 := R0; R1 := R0[0x86d3529e]
 26 [-]: CALL      R1 2 2       ; R1 := R1(R2)
 27 [-]: SETUPVAL  R1 U4        ; U82 := R4
 28 [-]: GETGLOBAL R1 K8        ; R1 := 0x7b998233
 29 [-]: GETUPVAL  R2 U4        ; R2 := U4
 30 [-]: CALL      R1 2 2       ; R1 := R1(R2)
 31 [-]: TEST      R1 0         ; if not R1 then PC := 35
 32 [-]: JMP       35           ; PC := 35
 33 [-]: LOADK     R1 0         ; R1 := 0.000000
 34 [-]: RETURN    R1 2         ; return R1
 35 [-]: GETUPVAL  R1 U4        ; R1 := U4
 36 [-]: SELF      R1 R1 K9     ; R2 := R1; R1 := R1[0xefe6cad1]
 37 [-]: CALL      R1 2 2       ; R1 := R1(R2)
 38 [-]: NOT       R1 R1        ; R1 := not R1
 39 [-]: EQ        0 R1 K11     ; if R1 ~= 2.000000 then PC := 45
 40 [-]: JMP       45           ; PC := 45
 41 [-]: GETGLOBAL R1 K6        ; R1 := 0xcbd666e1
 42 [-]: LOADK     R2 0         ; R2 := 0.000000
 43 [-]: CALL      R1 2 1       ; R1(R2)
 44 [-]: JMP       35           ; PC := 35
 45 [-]: GETGLOBAL R1 K8        ; R1 := 0x7b998233
 46 [-]: GETGLOBAL R2 K12       ; R2 := 0xbe190284
 47 [-]: CALL      R1 2 2       ; R1 := R1(R2)
 48 [-]: TEST      R1 1         ; if R1 then PC := 72
 49 [-]: JMP       72           ; PC := 72
 50 [-]: GETGLOBAL R1 K12       ; R1 := 0xbe190284
 51 [-]: SELF      R1 R1 K13    ; R2 := R1; R1 := R1[0xef893aec]
 52 [-]: CALL      R1 2 2       ; R1 := R1(R2)
 53 [-]: GETTABLE  R2 R1 K14    ; R2 := R1["enemySpec"]
 54 [-]: SETUPVAL  R2 U5        ; U82 := R5
 55 [-]: GETGLOBAL R2 K8        ; R2 := 0x7b998233
 56 [-]: GETUPVAL  R3 U5        ; R3 := U5
 57 [-]: CALL      R2 2 2       ; R2 := R2(R3)
 58 [-]: TEST      R2 0         ; if not R2 then PC := 72
 59 [-]: JMP       72           ; PC := 72
 60 [-]: GETGLOBAL R2 K15       ; R2 := 0x3a3e5b5d
 61 [-]: SETUPVAL  R2 U5        ; U82 := R5
 62 [-]: GETGLOBAL R2 K15       ; R2 := 0x3a3e5b5d
 63 [-]: SETTABLE  R1 K14 R2    ; R1["enemySpec"] := R2
 64 [-]: GETGLOBAL R2 K12       ; R2 := 0xbe190284
 65 [-]: SELF      R2 R2 K16    ; R3 := R2; R2 := R2[0x0670b198]
 66 [-]: MOVE      R4 R1        ; R4 := R1
 67 [-]: CALL      R2 3 1       ; R2(R3,R4)
 68 [-]: GETUPVAL  R2 U3        ; R2 := U3
 69 [-]: SELF      R2 R2 K17    ; R3 := R2; R2 := R2[0x17db0a42]
 70 [-]: GETUPVAL  R4 U5        ; R4 := U5
 71 [-]: CALL      R2 3 1       ; R2(R3,R4)
 72 [-]: GETGLOBAL R2 K2        ; R2 := 0x89326c93
 73 [-]: SELF      R2 R2 K18    ; R3 := R2; R2 := R2[0x7c1a0374]
 74 [-]: CALL      R2 2 2       ; R2 := R2(R3)
 75 [-]: GETGLOBAL R3 K19       ; R3 := 0x11a19c5e
 76 [-]: MOVE      R4 R2        ; R4 := R2
 77 [-]: LOADK     R5 K20       ; R5 := "NPCAlertStart"
 78 [-]: CALL      R3 3 1       ; R3(R4,R5)
 79 [-]: GETGLOBAL R3 K19       ; R3 := 0x11a19c5e
 80 [-]: MOVE      R4 R2        ; R4 := R2
 81 [-]: LOADK     R5 K21       ; R5 := "NPCAlertEnd"
 82 [-]: CALL      R3 3 1       ; R3(R4,R5)
 83 [-]: GETUPVAL  R3 U6        ; R3 := U6
 84 [-]: GETUPVAL  R4 U7        ; R4 := U7
 85 [-]: CALL      R3 2 1       ; R3(R4)
 86 [-]: RETURN    R0 1         ; return 


; Function #10:
;
; Name:            
; Defined at line: 241
; #Upvalues:       11
; #Parameters:     1
; Is_vararg:       0
; Max Stack Size:  3

  1 [-]: GETUPVAL  R1 U0        ; R1 := U0
  2 [-]: GETUPVAL  R2 U1        ; R2 := U1
  3 [-]: EQ        0 R1 R2      ; if R1 ~= R2 then PC := 14
  4 [-]: JMP       14           ; PC := 14
  5 [-]: GETGLOBAL R1 K0        ; R1 := 0x7b998233
  6 [-]: GETUPVAL  R2 U2        ; R2 := U2
  7 [-]: CALL      R1 2 2       ; R1 := R1(R2)
  8 [-]: TEST      R1 1         ; if R1 then PC := 74
  9 [-]: JMP       74           ; PC := 74
 10 [-]: GETUPVAL  R1 U3        ; R1 := U3
 11 [-]: GETUPVAL  R2 U4        ; R2 := U4
 12 [-]: CALL      R1 2 1       ; R1(R2)
 13 [-]: JMP       74           ; PC := 74
 14 [-]: GETUPVAL  R1 U0        ; R1 := U0
 15 [-]: GETUPVAL  R2 U4        ; R2 := U4
 16 [-]: EQ        0 R1 R2      ; if R1 ~= R2 then PC := 52
 17 [-]: JMP       52           ; PC := 52
 18 [-]: GETGLOBAL R1 K0        ; R1 := 0x7b998233
 19 [-]: GETUPVAL  R2 U5        ; R2 := U5
 20 [-]: CALL      R1 2 2       ; R1 := R1(R2)
 21 [-]: TEST      R1 1         ; if R1 then PC := 28
 22 [-]: JMP       28           ; PC := 28
 23 [-]: GETUPVAL  R1 U5        ; R1 := U5
 24 [-]: SELF      R1 R1 K1     ; R2 := R1; R1 := R1[0x2047cfe7]
 25 [-]: CALL      R1 2 2       ; R1 := R1(R2)
 26 [-]: TEST      R1 0         ; if not R1 then PC := 35
 27 [-]: JMP       35           ; PC := 35
 28 [-]: GETUPVAL  R1 U6        ; R1 := U6
 29 [-]: GETUPVAL  R2 U5        ; R2 := U5
 30 [-]: CALL      R1 2 1       ; R1(R2)
 31 [-]: GETUPVAL  R1 U3        ; R1 := U3
 32 [-]: GETUPVAL  R2 U7        ; R2 := U7
 33 [-]: CALL      R1 2 1       ; R1(R2)
 34 [-]: JMP       74           ; PC := 74
 35 [-]: GETGLOBAL R1 K0        ; R1 := 0x7b998233
 36 [-]: GETUPVAL  R2 U2        ; R2 := U2
 37 [-]: CALL      R1 2 2       ; R1 := R1(R2)
 38 [-]: TEST      R1 1         ; if R1 then PC := 45
 39 [-]: JMP       45           ; PC := 45
 40 [-]: GETUPVAL  R1 U2        ; R1 := U2
 41 [-]: SELF      R1 R1 K1     ; R2 := R1; R1 := R1[0x2047cfe7]
 42 [-]: CALL      R1 2 2       ; R1 := R1(R2)
 43 [-]: TEST      R1 0         ; if not R1 then PC := 74
 44 [-]: JMP       74           ; PC := 74
 45 [-]: GETUPVAL  R1 U6        ; R1 := U6
 46 [-]: GETUPVAL  R2 U2        ; R2 := U2
 47 [-]: CALL      R1 2 1       ; R1(R2)
 48 [-]: GETUPVAL  R1 U3        ; R1 := U3
 49 [-]: GETUPVAL  R2 U7        ; R2 := U7
 50 [-]: CALL      R1 2 1       ; R1(R2)
 51 [-]: JMP       74           ; PC := 74
 52 [-]: GETUPVAL  R1 U0        ; R1 := U0
 53 [-]: GETUPVAL  R2 U7        ; R2 := U7
 54 [-]: EQ        0 R1 R2      ; if R1 ~= R2 then PC := 65
 55 [-]: JMP       65           ; PC := 65
 56 [-]: GETGLOBAL R1 K0        ; R1 := 0x7b998233
 57 [-]: GETUPVAL  R2 U8        ; R2 := U8
 58 [-]: CALL      R1 2 2       ; R1 := R1(R2)
 59 [-]: TEST      R1 0         ; if not R1 then PC := 74
 60 [-]: JMP       74           ; PC := 74
 61 [-]: GETUPVAL  R1 U3        ; R1 := U3
 62 [-]: GETUPVAL  R2 U9        ; R2 := U9
 63 [-]: CALL      R1 2 1       ; R1(R2)
 64 [-]: JMP       74           ; PC := 74
 65 [-]: GETUPVAL  R1 U0        ; R1 := U0
 66 [-]: GETUPVAL  R2 U9        ; R2 := U9
 67 [-]: EQ        0 R1 R2      ; if R1 ~= R2 then PC := 70
 68 [-]: JMP       70           ; PC := 70
 69 [-]: JMP       74           ; PC := 74
 70 [-]: GETUPVAL  R1 U0        ; R1 := U0
 71 [-]: GETUPVAL  R2 U10       ; R2 := U10
 72 [-]: EQ        0 R1 R2      ; if R1 ~= R2 then PC := 74
 73 [-]: JMP       74           ; PC := 74
 74 [-]: RETURN    R0 1         ; return 


; Function #11:
;
; Name:            
; Defined at line: 264
; #Upvalues:       3
; #Parameters:     1
; Is_vararg:       0
; Max Stack Size:  4

  1 [-]: GETUPVAL  R1 U0        ; R1 := U0
  2 [-]: EQ        1 R1 R0      ; if R1 == R0 then PC := 12
  3 [-]: JMP       12           ; PC := 12
  4 [-]: SETUPVAL  R0 U0        ; U82 := R0
  5 [-]: GETUPVAL  R1 U1        ; R1 := U1
  6 [-]: SELF      R1 R1 K0     ; R2 := R1; R1 := R1[0x5b18bb5d]
  7 [-]: MOVE      R3 R0        ; R3 := R0
  8 [-]: CALL      R1 3 1       ; R1(R2,R3)
  9 [-]: GETUPVAL  R1 U2        ; R1 := U2
 10 [-]: CALL      R1 1 1       ; R1()
 11 [-]: JMP       15           ; PC := 15
 12 [-]: GETGLOBAL R1 K1        ; R1 := 0x3d106989
 13 [-]: LOADK     R2 K2        ; R2 := "DeepSpaceNavCrewshipDataObjective.lua::SetModeState - trying to set mode to state we're already in"
 14 [-]: CALL      R1 2 1       ; R1(R2)
 15 [-]: RETURN    R0 1         ; return 


; Function #12:
;
; Name:            
; Defined at line: 274
; #Upvalues:       0
; #Parameters:     1
; Is_vararg:       0
; Max Stack Size:  19

  1 [-]: SELF      R1 R0 K0     ; R2 := R0; R1 := R0[0x86d3529e]
  2 [-]: CALL      R1 2 2       ; R1 := R1(R2)
  3 [-]: GETGLOBAL R2 K1        ; R2 := 0x7b998233
  4 [-]: MOVE      R3 R1        ; R3 := R1
  5 [-]: CALL      R2 2 2       ; R2 := R2(R3)
  6 [-]: TEST      R2 0         ; if not R2 then PC := 10
  7 [-]: JMP       10           ; PC := 10
  8 [-]: LOADK     R2 0         ; R2 := 0.000000
  9 [-]: RETURN    R2 2         ; return R2
 10 [-]: GETGLOBAL R2 K2        ; R2 := 0x89326c93
 11 [-]: SELF      R2 R2 K3     ; R3 := R2; R2 := R2[0x8b5b1f58]
 12 [-]: CALL      R2 2 2       ; R2 := R2(R3)
 13 [-]: GETGLOBAL R3 K4        ; R3 := 0xbe190284
 14 [-]: SELF      R3 R3 K5     ; R4 := R3; R3 := R3[0xd7d79b74]
 15 [-]: CALL      R3 2 2       ; R3 := R3(R4)
 16 [-]: SELF      R4 R3 K6     ; R5 := R3; R4 := R3[0x1b68b9f9]
 17 [-]: LOADBOOL  R6 0 0       ; R6 := false
 18 [-]: CALL      R4 3 2       ; R4 := R4(R5,R6)
 19 [-]: LOADK     R5 1         ; R5 := 1.000000
 20 [-]: LEN       R6 R4        ; R6 := # R4
 21 [-]: LOADK     R7 1         ; R7 := 1.000000
 22 [-]: FORPREP   R5 52        ; R5 -= R7; PC := 52
 23 [-]: GETTABLE  R9 R4 R8     ; R9 := R4[R8]
 24 [-]: LOADBOOL  R10 0 0      ; R10 := false
 25 [-]: GETGLOBAL R11 K1       ; R11 := 0x7b998233
 26 [-]: MOVE      R12 R9       ; R12 := R9
 27 [-]: CALL      R11 2 2      ; R11 := R11(R12)
 28 [-]: TEST      R11 1        ; if R11 then PC := 52
 29 [-]: JMP       52           ; PC := 52
 30 [-]: LOADK     R11 1        ; R11 := 1.000000
 31 [-]: LEN       R12 R2       ; R12 := # R2
 32 [-]: LOADK     R13 1        ; R13 := 1.000000
 33 [-]: FORPREP   R11 47       ; R11 -= R13; PC := 47
 34 [-]: GETTABLE  R15 R2 R14   ; R15 := R2[R14]
 35 [-]: GETGLOBAL R16 K1       ; R16 := 0x7b998233
 36 [-]: MOVE      R17 R15      ; R17 := R15
 37 [-]: CALL      R16 2 2      ; R16 := R16(R17)
 38 [-]: TEST      R16 1        ; if R16 then PC := 47
 39 [-]: JMP       47           ; PC := 47
 40 [-]: SELF      R16 R9 K7    ; R17 := R9; R16 := R9[0x7941d56e]
 41 [-]: MOVE      R18 R15      ; R18 := R15
 42 [-]: CALL      R16 3 2      ; R16 := R16(R17,R18)
 43 [-]: TEST      R16 0        ; if not R16 then PC := 47
 44 [-]: JMP       47           ; PC := 47
 45 [-]: LOADBOOL  R10 1 0      ; R10 := true
 46 [-]: JMP       48           ; PC := 48
 47 [-]: FORLOOP   R11 34       ; R11 += R13; if R11 <= R12 then begin PC := 34; R14 := R11 end
 48 [-]: TEST      R10 1        ; if R10 then PC := 52
 49 [-]: JMP       52           ; PC := 52
 50 [-]: LOADK     R16 1        ; R16 := 1.000000
 51 [-]: RETURN    R16 2        ; return R16
 52 [-]: FORLOOP   R5 23        ; R5 += R7; if R5 <= R6 then begin PC := 23; R8 := R5 end
 53 [-]: LOADK     R16 0        ; R16 := 0.000000
 54 [-]: RETURN    R16 2        ; return R16
 55 [-]: RETURN    R0 1         ; return 


; Function #13:
;
; Name:            
; Defined at line: 306
; #Upvalues:       5
; #Parameters:     1
; Is_vararg:       0
; Max Stack Size:  4

  1 [-]: GETGLOBAL R1 K0        ; R1 := 0xd644c2f1
  2 [-]: LOADK     R2 K1        ; R2 := "DeepSpaceNavCrewshipDataObjective.lua -- Deep Space Crewship Objective Started"
  3 [-]: CALL      R1 2 1       ; R1(R2)
  4 [-]: GETUPVAL  R1 U0        ; R1 := U0
  5 [-]: MOVE      R2 R0        ; R2 := R0
  6 [-]: CALL      R1 2 1       ; R1(R2)
  7 [-]: GETUPVAL  R1 U1        ; R1 := U1
  8 [-]: GETUPVAL  R2 U2        ; R2 := U2
  9 [-]: CALL      R2 1 2       ; R2 := R2()
 10 [-]: TEST      R2 1         ; if R2 then PC := 19
 11 [-]: JMP       19           ; PC := 19
 12 [-]: GETUPVAL  R2 U3        ; R2 := U3
 13 [-]: MOVE      R3 R1        ; R3 := R1
 14 [-]: CALL      R2 2 1       ; R2(R3)
 15 [-]: GETGLOBAL R2 K2        ; R2 := 0xcbd666e1
 16 [-]: MOVE      R3 R1        ; R3 := R1
 17 [-]: CALL      R2 2 1       ; R2(R3)
 18 [-]: JMP       8            ; PC := 8
 19 [-]: GETUPVAL  R2 U4        ; R2 := U4
 20 [-]: MOVE      R3 R0        ; R3 := R0
 21 [-]: CALL      R2 2 1       ; R2(R3)
 22 [-]: RETURN    R0 1         ; return 


