; Name:            
; Defined at line: 1
; #Upvalues:       0
; #Parameters:     0
; Is_vararg:       1
; Max Stack Size:  51

       1 [-]: GETIMPORT R0 1; var0 = 0x0469F296
       2 [-]: LOADK R1 K2  ; var1 = "NemesisInvulnerabilityAdd"
       3 [-]: CALL R0 2 2  ; var0 = var0(var1)
       4 [-]: GETIMPORT R1 1; var1 = 0x0469F296
       5 [-]: LOADK R2 K3  ; var2 = "NemesisAdds"
       6 [-]: CALL R1 2 2  ; var1 = var1(var2)
       7 [-]: GETIMPORT R2 1; var2 = 0x0469F296
       8 [-]: LOADK R3 K4  ; var3 = "NemesisIntroCin"
       9 [-]: CALL R2 2 2  ; var2 = var2(var3)
      10 [-]: GETIMPORT R3 1; var3 = 0x0469F296
      11 [-]: LOADK R4 K5  ; var4 = "RJSubMissionStarted"
      12 [-]: CALL R3 2 2  ; var3 = var3(var4)
      13 [-]: GETIMPORT R4 1; var4 = 0x0469F296
      14 [-]: LOADK R5 K6  ; var5 = "RJLichAssassinateComplete"
      15 [-]: CALL R4 2 2  ; var4 = var4(var5)
      16 [-]: GETIMPORT R5 1; var5 = 0x0469F296
      17 [-]: LOADK R6 K7  ; var6 = "RJInvulnAgentCount"
      18 [-]: CALL R5 2 2  ; var5 = var5(var6)
      19 [-]: GETIMPORT R6 1; var6 = 0x0469F296
      20 [-]: LOADK R7 K8  ; var7 = "NV_ROOM_IDX"
      21 [-]: CALL R6 2 2  ; var6 = var6(var7)
      22 [-]: GETIMPORT R7 1; var7 = 0x0469F296
      23 [-]: LOADK R8 K9  ; var8 = "RailjackDisabled"
      24 [-]: CALL R7 2 2  ; var7 = var7(var8)
      25 [-]: GETIMPORT R8 1; var8 = 0x0469F296
      26 [-]: LOADK R9 K10 ; var9 = "Corpus"
      27 [-]: CALL R8 2 2  ; var8 = var8(var9)
      28 [-]: GETIMPORT R9 1; var9 = 0x0469F296
      29 [-]: LOADK R10 K11; var10 = "Grineer"
      30 [-]: CALL R9 2 2  ; var9 = var9(var10)
      31 [-]: GETIMPORT R10 13; var10 = 0x2D0FAD09
      32 [-]: LOADK R11 K14; var11 = "EE.Interface.Utilities"
      33 [-]: CALL R10 2 2 ; var10 = var10(var11)
      34 [-]: GETIMPORT R11 13; var11 = 0x2D0FAD09
      35 [-]: LOADK R12 K15; var12 = "Lotus.Scripts.Libs.EncounterLib"
      36 [-]: CALL R11 2 2 ; var11 = var11(var12)
      37 [-]: GETIMPORT R12 13; var12 = 0x2D0FAD09
      38 [-]: LOADK R13 K16; var13 = "Lotus.Scripts.Nemesis.NemesisGenerator"
      39 [-]: CALL R12 2 2 ; var12 = var12(var13)
      40 [-]: GETIMPORT R13 13; var13 = 0x2D0FAD09
      41 [-]: LOADK R14 K17; var14 = "Lotus.Scripts.Libs.RailjackUtilities"
      42 [-]: CALL R13 2 2 ; var13 = var13(var14)
      43 [-]: GETIMPORT R14 13; var14 = 0x2D0FAD09
      44 [-]: LOADK R15 K18; var15 = "Lotus.Scripts.Libs.ObjectiveText"
      45 [-]: CALL R14 2 2 ; var14 = var14(var15)
      46 [-]: GETIMPORT R15 13; var15 = 0x2D0FAD09
      47 [-]: LOADK R16 K19; var16 = "Lotus.Scripts.Libs.TransmissionSet"
      48 [-]: CALL R15 2 2 ; var15 = var15(var16)
      49 [-]: GETIMPORT R16 13; var16 = 0x2D0FAD09
      50 [-]: LOADK R17 K20; var17 = "Lotus.Scripts.Libs.LandscapeLib"
      51 [-]: CALL R16 2 2 ; var16 = var16(var17)
      52 [-]: NEWTABLE R17 0 0; var17 = {}
      53 [-]: NEWTABLE R18 0 0; var18 = {}
      54 [-]: LOADNIL R19  ; var19 = nil
      55 [-]: LOADNIL R20  ; var20 = nil
      56 [-]: LOADNIL R21  ; var21 = nil
      57 [-]: NEWTABLE R22 0 0; var22 = {}
      58 [-]: NEWTABLE R23 0 0; var23 = {}
      59 [-]: NEWTABLE R24 0 0; var24 = {}
      60 [-]: LOADNIL R25  ; var25 = nil
      61 [-]: NEWTABLE R26 0 0; var26 = {}
      62 [-]: LOADN R27 1  ; var27 = 1
      63 [-]: LOADN R28 0  ; var28 = 0
      64 [-]: LOADN R29 2  ; var29 = 2
      65 [-]: LOADB R30 0  ; var30 = false
      66 [-]: LOADNIL R31  ; var31 = nil
      67 [-]: LOADNIL R32  ; var32 = nil
      68 [-]: LOADB R33 0  ; var33 = false
      69 [-]: LOADNIL R34  ; var34 = nil
      70 [-]: LOADNIL R35  ; var35 = nil
      71 [-]: LOADNIL R36  ; var36 = nil
      72 [-]: GETIMPORT R37 1; var37 = 0x0469F296
      73 [-]: LOADK R38 K21; var38 = "TENNO"
      74 [-]: CALL R37 2 2 ; var37 = var37(var38)
      75 [-]: NEWCLOSURE R38 P0; 
      76 [-]: CAPTURE REF R35; 
      77 [-]: CAPTURE REF R34; 
      78 [-]: CAPTURE VAL R13; 
      79 [-]: CAPTURE REF R32; 
      80 [-]: DUPCLOSURE R39 K22; 
      81 [-]: DUPCLOSURE R40 K23; 
      82 [-]: CAPTURE VAL R39; 
      83 [-]: CAPTURE VAL R13; 
      84 [-]: CAPTURE VAL R7; 
      85 [-]: NEWCLOSURE R41 P3; 
      86 [-]: CAPTURE VAL R7; 
      87 [-]: CAPTURE REF R36; 
      88 [-]: CAPTURE VAL R39; 
      89 [-]: CAPTURE VAL R40; 
      90 [-]: CAPTURE REF R32; 
      91 [-]: CAPTURE VAL R4; 
      92 [-]: SETGLOBAL R41 K24; "DisableRailjack" = var41
      93 [-]: DUPCLOSURE R41 K25; 
      94 [-]: CAPTURE VAL R38; 
      95 [-]: CAPTURE VAL R12; 
      96 [-]: CAPTURE VAL R15; 
      97 [-]: SETGLOBAL R41 K26; "PlayShowdownTransmissions" = var41
      98 [-]: DUPCLOSURE R41 K27; 
      99 [-]: DUPCLOSURE R42 K28; 
     100 [-]: DUPCLOSURE R43 K29; 
     101 [-]: NEWCLOSURE R44 P8; 
     102 [-]: CAPTURE REF R27; 
     103 [-]: CAPTURE REF R26; 
     104 [-]: CAPTURE VAL R10; 
     105 [-]: NEWCLOSURE R45 P9; 
     106 [-]: CAPTURE REF R20; 
     107 [-]: CAPTURE REF R27; 
     108 [-]: CAPTURE REF R26; 
     109 [-]: CAPTURE VAL R10; 
     110 [-]: CAPTURE VAL R0; 
     111 [-]: CAPTURE VAL R1; 
     112 [-]: CAPTURE REF R18; 
     113 [-]: NEWCLOSURE R46 P10; 
     114 [-]: CAPTURE REF R28; 
     115 [-]: CAPTURE REF R18; 
     116 [-]: CAPTURE REF R30; 
     117 [-]: CAPTURE REF R29; 
     118 [-]: DUPCLOSURE R47 K30; 
     119 [-]: NEWCLOSURE R48 P12; 
     120 [-]: CAPTURE REF R17; 
     121 [-]: CAPTURE VAL R16; 
     122 [-]: CAPTURE VAL R12; 
     123 [-]: CAPTURE VAL R8; 
     124 [-]: CAPTURE VAL R9; 
     125 [-]: CAPTURE VAL R47; 
     126 [-]: NEWCLOSURE R49 P13; 
     127 [-]: CAPTURE REF R17; 
     128 [-]: CAPTURE REF R25; 
     129 [-]: CAPTURE VAL R6; 
     130 [-]: CAPTURE REF R23; 
     131 [-]: CAPTURE REF R19; 
     132 [-]: CAPTURE VAL R11; 
     133 [-]: CAPTURE REF R22; 
     134 [-]: CAPTURE REF R20; 
     135 [-]: CAPTURE REF R21; 
     136 [-]: CAPTURE VAL R1; 
     137 [-]: CAPTURE VAL R2; 
     138 [-]: CAPTURE VAL R12; 
     139 [-]: NEWCLOSURE R50 P14; 
     140 [-]: CAPTURE REF R20; 
     141 [-]: CAPTURE VAL R2; 
     142 [-]: CAPTURE REF R21; 
     143 [-]: CAPTURE VAL R42; 
     144 [-]: SETGLOBAL R50 K31; "ManageIntroCin" = var50
     145 [-]: NEWCLOSURE R50 P15; 
     146 [-]: CAPTURE REF R31; 
     147 [-]: CAPTURE VAL R9; 
     148 [-]: CAPTURE VAL R14; 
     149 [-]: CAPTURE REF R26; 
     150 [-]: CAPTURE REF R27; 
     151 [-]: CAPTURE REF R32; 
     152 [-]: CAPTURE VAL R13; 
     153 [-]: CAPTURE REF R36; 
     154 [-]: CAPTURE REF R22; 
     155 [-]: CAPTURE REF R23; 
     156 [-]: CAPTURE VAL R24; 
     157 [-]: CAPTURE VAL R7; 
     158 [-]: CAPTURE VAL R38; 
     159 [-]: CAPTURE VAL R37; 
     160 [-]: CAPTURE REF R20; 
     161 [-]: CAPTURE REF R19; 
     162 [-]: CAPTURE VAL R5; 
     163 [-]: CAPTURE REF R28; 
     164 [-]: CAPTURE REF R18; 
     165 [-]: CAPTURE REF R21; 
     166 [-]: CAPTURE VAL R1; 
     167 [-]: CAPTURE VAL R2; 
     168 [-]: CAPTURE VAL R48; 
     169 [-]: CAPTURE REF R25; 
     170 [-]: CAPTURE VAL R6; 
     171 [-]: CAPTURE REF R33; 
     172 [-]: CAPTURE REF R17; 
     173 [-]: CAPTURE VAL R47; 
     174 [-]: CAPTURE VAL R41; 
     175 [-]: CAPTURE VAL R49; 
     176 [-]: CAPTURE VAL R45; 
     177 [-]: CAPTURE REF R29; 
     178 [-]: CAPTURE VAL R12; 
     179 [-]: CAPTURE REF R30; 
     180 [-]: CAPTURE VAL R46; 
     181 [-]: CAPTURE VAL R43; 
     182 [-]: CAPTURE VAL R16; 
     183 [-]: CAPTURE VAL R15; 
     184 [-]: CAPTURE VAL R4; 
     185 [-]: SETGLOBAL R50 K32; "NemesisAssassinate" = var50
     186 [-]: CLOSEUPVALS R17; 
     187 [-]: RETURN R0 0  ; 


; Name:            
; Defined at line: 69
; #Upvalues:       4
; #Parameters:     1
; Is_vararg:       0
; Max Stack Size:  17

       0 [-]: NEWTABLE R1 0 2; var1 = {}
       1 [-]: GETIMPORT R2 1; var2 = 0x0469F296
       2 [-]: LOADK R3 K2  ; var3 = "EnterCinematic"
       3 [-]: CALL R2 2 2  ; var2 = var2(var3)
       4 [-]: GETIMPORT R3 1; var3 = 0x0469F296
       5 [-]: LOADK R4 K3  ; var4 = "GalleonEnterCinematic"
       6 [-]: CALL R3 2 0  ; var3, ... = var3(var4)
       7 [-]: SETLIST R1 R2 -1 [1]; 
       8 [-]: LOADNIL R2   ; var2 = nil
       9 [-]: JUMPIFNOT R0 L5; goto L5 if not var0
      10 [-]: GETUPVAL R3 0; var3 = upvalues[0]
      11 [-]: JUMPIF R3 L4 ; goto L4 if var3
      12 [-]: NEWTABLE R3 0 0; var3 = {}
      13 [-]: SETUPVAL R3 0; upvalues[3] = var0
      14 [-]: GETIMPORT R3 5; var3 = 0xC8802016
      15 [-]: MOVE R4 R1   ; var4 = var1
      16 [-]: CALL R3 2 4  ; var3, var4, var5 = var3(var4)
      17 [-]: FORGPREP_INEXT R3 L3; 
L 0:  18 [-]: GETIMPORT R8 7; var8 = 0x89326C93
      19 [-]: MOVE R10 R7  ; var10 = var7
      20 [-]: NAMECALL R8 R8 K8; var9 = var8; var8 = var8[0xC7FCADA9]
      21 [-]: CALL R8 3 2  ; var8 = var8(var9, var10)
      22 [-]: GETIMPORT R9 5; var9 = 0xC8802016
      23 [-]: MOVE R10 R8  ; var10 = var8
      24 [-]: CALL R9 2 4  ; var9, var10, var11 = var9(var10)
      25 [-]: FORGPREP_INEXT R9 L2; 
L 1:  26 [-]: GETUPVAL R15 0; var15 = upvalues[0]
      27 [-]: FASTCALL2 52 R15 R13 L2; 
      28 [-]: MOVE R16 R13 ; var16 = var13
      29 [-]: GETIMPORT R14 11; var14 = 0x33BDD652[0x23D5322F]
      30 [-]: CALL R14 3 1 ; var14(var15, var16)
L 2:  31 [-]: FORGLOOP R9 L1 2 [inext]; 
L 3:  32 [-]: FORGLOOP R3 L0 2 [inext]; 
L 4:  33 [-]: GETUPVAL R2 0; var2 = upvalues[0]
      34 [-]: JUMP L11     ; goto L11
L 5:  35 [-]: GETUPVAL R3 1; var3 = upvalues[1]
      36 [-]: JUMPIF R3 L10; goto L10 if var3
      37 [-]: NEWTABLE R3 0 0; var3 = {}
      38 [-]: SETUPVAL R3 1; upvalues[3] = var1
      39 [-]: GETIMPORT R3 5; var3 = 0xC8802016
      40 [-]: MOVE R4 R1   ; var4 = var1
      41 [-]: CALL R3 2 4  ; var3, var4, var5 = var3(var4)
      42 [-]: FORGPREP_INEXT R3 L9; 
L 6:  43 [-]: GETUPVAL R9 2; var9 = upvalues[2]
      44 [-]: GETTABLEKS R8 R9 K12; var8 = var9[0xDE6C4F3E]
      45 [-]: MOVE R9 R7   ; var9 = var7
      46 [-]: GETUPVAL R10 3; var10 = upvalues[3]
      47 [-]: CALL R8 3 2  ; var8 = var8(var9, var10)
      48 [-]: GETIMPORT R9 5; var9 = 0xC8802016
      49 [-]: MOVE R10 R8  ; var10 = var8
      50 [-]: CALL R9 2 4  ; var9, var10, var11 = var9(var10)
      51 [-]: FORGPREP_INEXT R9 L8; 
L 7:  52 [-]: GETUPVAL R15 1; var15 = upvalues[1]
      53 [-]: FASTCALL2 52 R15 R13 L8; 
      54 [-]: MOVE R16 R13 ; var16 = var13
      55 [-]: GETIMPORT R14 11; var14 = 0x33BDD652[0x23D5322F]
      56 [-]: CALL R14 3 1 ; var14(var15, var16)
L 8:  57 [-]: FORGLOOP R9 L7 2 [inext]; 
L 9:  58 [-]: FORGLOOP R3 L6 2 [inext]; 
L10:  59 [-]: GETUPVAL R2 1; var2 = upvalues[1]
L11:  60 [-]: GETIMPORT R3 5; var3 = 0xC8802016
      61 [-]: MOVE R4 R2   ; var4 = var2
      62 [-]: CALL R3 2 4  ; var3, var4, var5 = var3(var4)
      63 [-]: FORGPREP_INEXT R3 L14; 
L12:  64 [-]: FASTCALL1 64 R7 L13; 
      65 [-]: MOVE R9 R7   ; var9 = var7
      66 [-]: GETIMPORT R8 14; var8 = 0x7B998233
      67 [-]: CALL R8 2 2  ; var8 = var8(var9)
L13:  68 [-]: JUMPIF R8 L14; goto L14 if var8
      69 [-]: NAMECALL R8 R7 K15; var9 = var7; var8 = var7[0x1C84839C]
      70 [-]: CALL R8 2 2  ; var8 = var8(var9)
      71 [-]: JUMPIFNOT R8 L14; goto L14 if not var8
      72 [-]: LOADB R8 1   ; var8 = true
      73 [-]: RETURN R8 1  ; 
L14:  74 [-]: FORGLOOP R3 L12 2 [inext]; 
      75 [-]: LOADB R3 0   ; var3 = false
      76 [-]: RETURN R3 1  ; 


; Name:            
; Defined at line: 103
; #Upvalues:       0
; #Parameters:     0
; Is_vararg:       0
; Max Stack Size:  3

L 0:   0 [-]: GETIMPORT R1 1; var1 = 0xBE190284
       1 [-]: FASTCALL1 64 R1 L1; 
       2 [-]: GETIMPORT R0 3; var0 = 0x7B998233
       3 [-]: CALL R0 2 2  ; var0 = var0(var1)
L 1:   4 [-]: JUMPIFNOT R0 L2; goto L2 if not var0
       5 [-]: GETIMPORT R0 5; var0 = 0xCBD666E1
       6 [-]: LOADN R1 0   ; var1 = 0
       7 [-]: CALL R0 2 1  ; var0(var1)
       8 [-]: JUMPBACK L0  ; goto L0
L 2:   9 [-]: GETIMPORT R0 1; var0 = 0xBE190284
      10 [-]: NAMECALL R0 R0 K6; var1 = var0; var0 = var0[0xD7D79B74]
      11 [-]: CALL R0 2 2  ; var0 = var0(var1)
L 3:  12 [-]: FASTCALL1 64 R0 L4; 
      13 [-]: MOVE R2 R0   ; var2 = var0
      14 [-]: GETIMPORT R1 3; var1 = 0x7B998233
      15 [-]: CALL R1 2 2  ; var1 = var1(var2)
L 4:  16 [-]: JUMPIFNOT R1 L5; goto L5 if not var1
      17 [-]: GETIMPORT R1 5; var1 = 0xCBD666E1
      18 [-]: LOADN R2 0   ; var2 = 0
      19 [-]: CALL R1 2 1  ; var1(var2)
      20 [-]: GETIMPORT R1 1; var1 = 0xBE190284
      21 [-]: NAMECALL R1 R1 K6; var2 = var1; var1 = var1[0xD7D79B74]
      22 [-]: CALL R1 2 2  ; var1 = var1(var2)
      23 [-]: MOVE R0 R1   ; var0 = var1
      24 [-]: JUMPBACK L3  ; goto L3
L 5:  25 [-]: NAMECALL R1 R0 K7; var2 = var0; var1 = var0[0xCD57F819]
      26 [-]: CALL R1 2 0  ; var1, ... = var1(var2)
      27 [-]: RETURN R1 -1 ; 


; Name:            
; Defined at line: 117
; #Upvalues:       3
; #Parameters:     2
; Is_vararg:       0
; Max Stack Size:  17

       0 [-]: GETUPVAL R2 0; var2 = upvalues[0]
       1 [-]: CALL R2 1 2  ; var2 = var2()
       2 [-]: FASTCALL1 64 R2 L0; 
       3 [-]: MOVE R4 R2   ; var4 = var2
       4 [-]: GETIMPORT R3 1; var3 = 0x7B998233
       5 [-]: CALL R3 2 2  ; var3 = var3(var4)
L 0:   6 [-]: JUMPIFNOT R3 L1; goto L1 if not var3
       7 [-]: RETURN R0 0  ; 
L 1:   8 [-]: NAMECALL R3 R2 K2; var4 = var2; var3 = var2[0x5163741E]
       9 [-]: CALL R3 2 2  ; var3 = var3(var4)
      10 [-]: FASTCALL1 64 R3 L2; 
      11 [-]: MOVE R5 R3   ; var5 = var3
      12 [-]: GETIMPORT R4 1; var4 = 0x7B998233
      13 [-]: CALL R4 2 2  ; var4 = var4(var5)
L 2:  14 [-]: JUMPIFNOT R4 L3; goto L3 if not var4
      15 [-]: RETURN R0 0  ; 
L 3:  16 [-]: NEWTABLE R4 0 3; var4 = {}
      17 [-]: LOADN R7 1   ; var7 = 1
      18 [-]: NAMECALL R5 R2 K3; var6 = var2; var5 = var2[0x864B7B71]
      19 [-]: CALL R5 3 2  ; var5 = var5(var6, var7)
      20 [-]: SETTABLEN R5 R4 1; SETTABLEN R5 R4 1
      21 [-]: LOADN R7 2   ; var7 = 2
      22 [-]: NAMECALL R5 R2 K3; var6 = var2; var5 = var2[0x864B7B71]
      23 [-]: CALL R5 3 2  ; var5 = var5(var6, var7)
      24 [-]: SETTABLEN R5 R4 2; SETTABLEN R5 R4 2
      25 [-]: LOADN R7 3   ; var7 = 3
      26 [-]: NAMECALL R5 R2 K3; var6 = var2; var5 = var2[0x864B7B71]
      27 [-]: CALL R5 3 2  ; var5 = var5(var6, var7)
      28 [-]: SETTABLEN R5 R4 3; SETTABLEN R5 R4 3
      29 [-]: LENGTH R6 R4 ; var6 = #var4
      30 [-]: ADDK R5 R6 K4; var5 = var6 + 1
      31 [-]: LOADN R8 0   ; var8 = 0
      32 [-]: NAMECALL R6 R2 K3; var7 = var2; var6 = var2[0x864B7B71]
      33 [-]: CALL R6 3 2  ; var6 = var6(var7, var8)
      34 [-]: SETTABLE R6 R4 R5; var6[var4] = var5
      35 [-]: JUMPIFNOT R1 L6; goto L6 if not var1
      36 [-]: NAMECALL R5 R3 K5; var6 = var3; var5 = var3[0xDE321E6F]
      37 [-]: CALL R5 2 2  ; var5 = var5(var6)
      38 [-]: LOADN R7 86  ; var7 = 86
      39 [-]: LOADN R8 2   ; var8 = 2
      40 [-]: MOVE R9 R0   ; var9 = var0
      41 [-]: NAMECALL R5 R5 K6; var6 = var5; var5 = var5[0x12DD9DA2]
      42 [-]: CALL R5 5 1  ; var5(var6, var7, var8, var9)
      43 [-]: NAMECALL R5 R3 K7; var6 = var3; var5 = var3[0xBD8424D2]
      44 [-]: CALL R5 2 1  ; var5(var6)
      45 [-]: LOADN R7 1   ; var7 = 1
      46 [-]: LENGTH R5 R4 ; var5 = #var4
      47 [-]: LOADN R6 1   ; var6 = 1
      48 [-]: FORNPREP R5 L5; nforprep start - [escape at L5] -- var5 = iterator
L 4:  49 [-]: GETTABLE R8 R4 R7; var8 = var4[var7]
      50 [-]: NAMECALL R9 R8 K8; var10 = var8; var9 = var8[0x383D2E7D]
      51 [-]: CALL R9 2 1  ; var9(var10)
      52 [-]: NAMECALL R12 R8 K9; var13 = var8; var12 = var8[0xD1586535]
      53 [-]: CALL R12 2 2 ; var12 = var12(var13)
      54 [-]: GETIMPORT R13 11; var13 = 0xA421AF95
      55 [-]: LOADN R14 0  ; var14 = 0
      56 [-]: LOADN R15 0  ; var15 = 0
      57 [-]: LOADN R16 1  ; var16 = 1
      58 [-]: CALL R13 4 2 ; var13 = var13(var14, var15, var16)
      59 [-]: ADD R11 R12 R13; var11 = var12 + var13
      60 [-]: NAMECALL R12 R8 K12; var13 = var8; var12 = var8[0xCB3851B8]
      61 [-]: CALL R12 2 0 ; var12, ... = var12(var13)
      62 [-]: NAMECALL R9 R8 K13; var10 = var8; var9 = var8[0x589EF1C1]
      63 [-]: CALL R9 0 1  ; var9(var10, ...)
      64 [-]: NAMECALL R12 R8 K9; var13 = var8; var12 = var8[0xD1586535]
      65 [-]: CALL R12 2 2 ; var12 = var12(var13)
      66 [-]: GETIMPORT R13 11; var13 = 0xA421AF95
      67 [-]: LOADN R14 0  ; var14 = 0
      68 [-]: LOADN R15 0  ; var15 = 0
      69 [-]: LOADN R16 1  ; var16 = 1
      70 [-]: CALL R13 4 2 ; var13 = var13(var14, var15, var16)
      71 [-]: SUB R11 R12 R13; var11 = var12 - var13
      72 [-]: NAMECALL R12 R8 K12; var13 = var8; var12 = var8[0xCB3851B8]
      73 [-]: CALL R12 2 0 ; var12, ... = var12(var13)
      74 [-]: NAMECALL R9 R8 K13; var10 = var8; var9 = var8[0x589EF1C1]
      75 [-]: CALL R9 0 1  ; var9(var10, ...)
      76 [-]: FORNLOOP R5 L4; nforloop end - iterate + goto L4
L 5:  77 [-]: NAMECALL R5 R3 K14; var6 = var3; var5 = var3[0x1AC1655C]
      78 [-]: CALL R5 2 2  ; var5 = var5(var6)
      79 [-]: GETIMPORT R7 16; var7 = 0x0469F296
      80 [-]: LOADK R8 K17 ; var8 = "CapitalShipInvuln"
      81 [-]: CALL R7 2 0  ; var7, ... = var7(var8)
      82 [-]: NAMECALL R5 R5 K18; var6 = var5; var5 = var5[0x8E3E343E]
      83 [-]: CALL R5 0 1  ; var5(var6, ...)
      84 [-]: GETUPVAL R6 1; var6 = upvalues[1]
      85 [-]: GETTABLEKS R5 R6 K19; var5 = var6[0x2DF8B2BA]
      86 [-]: GETIMPORT R6 16; var6 = 0x0469F296
      87 [-]: LOADK R7 K20 ; var7 = "TogglePlayerSpawnsScript"
      88 [-]: CALL R6 2 2  ; var6 = var6(var7)
      89 [-]: MOVE R7 R2   ; var7 = var2
      90 [-]: CALL R5 3 2  ; var5 = var5(var6, var7)
      91 [-]: LOADN R8 1   ; var8 = 1
      92 [-]: NAMECALL R6 R5 K21; var7 = var5; var6 = var5[0x05EEB9DB]
      93 [-]: CALL R6 3 1  ; var6(var7, var8)
      94 [-]: LOADK R8 K22 ; var8 = "Execute"
      95 [-]: NAMECALL R6 R5 K23; var7 = var5; var6 = var5[0x8EB2112D]
      96 [-]: CALL R6 3 1  ; var6(var7, var8)
      97 [-]: GETIMPORT R6 25; var6 = 0xBE190284
      98 [-]: GETUPVAL R8 2; var8 = upvalues[2]
      99 [-]: NAMECALL R6 R6 K26; var7 = var6; var6 = var6[0xB9BFD47C]
     100 [-]: CALL R6 3 1  ; var6(var7, var8)
     101 [-]: JUMP L11     ; goto L11
L 6: 102 [-]: NAMECALL R5 R3 K27; var6 = var3; var5 = var3[0x2645258E]
     103 [-]: CALL R5 2 2  ; var5 = var5(var6)
     104 [-]: JUMPIF R5 L7 ; goto L7 if var5
     105 [-]: NAMECALL R5 R3 K5; var6 = var3; var5 = var3[0xDE321E6F]
     106 [-]: CALL R5 2 2  ; var5 = var5(var6)
     107 [-]: LOADN R7 86  ; var7 = 86
     108 [-]: LOADN R8 2   ; var8 = 2
     109 [-]: MOVE R9 R0   ; var9 = var0
     110 [-]: NAMECALL R5 R5 K28; var6 = var5; var5 = var5[0x5E6704FF]
     111 [-]: CALL R5 5 1  ; var5(var6, var7, var8, var9)
     112 [-]: NAMECALL R5 R3 K29; var6 = var3; var5 = var3[0xE43B7B6B]
     113 [-]: CALL R5 2 1  ; var5(var6)
L 7: 114 [-]: LOADN R7 1   ; var7 = 1
     115 [-]: LENGTH R5 R4 ; var5 = #var4
     116 [-]: LOADN R6 1   ; var6 = 1
     117 [-]: FORNPREP R5 L9; nforprep start - [escape at L9] -- var5 = iterator
L 8: 118 [-]: GETTABLE R8 R4 R7; var8 = var4[var7]
     119 [-]: NAMECALL R8 R8 K30; var9 = var8; var8 = var8[0xF4E253B6]
     120 [-]: CALL R8 2 1  ; var8(var9)
     121 [-]: FORNLOOP R5 L8; nforloop end - iterate + goto L8
L 9: 122 [-]: NAMECALL R5 R3 K14; var6 = var3; var5 = var3[0x1AC1655C]
     123 [-]: CALL R5 2 2  ; var5 = var5(var6)
     124 [-]: GETIMPORT R7 16; var7 = 0x0469F296
     125 [-]: LOADK R8 K17 ; var8 = "CapitalShipInvuln"
     126 [-]: CALL R7 2 2  ; var7 = var7(var8)
     127 [-]: LOADN R8 25  ; var8 = 25
     128 [-]: LOADN R9 6   ; var9 = 6
     129 [-]: LOADN R10 0  ; var10 = 0
     130 [-]: NAMECALL R5 R5 K31; var6 = var5; var5 = var5[0xA383DE31]
     131 [-]: CALL R5 6 1  ; var5(var6, var7, var8, var9, var10)
     132 [-]: GETIMPORT R5 34; var5 = _T["RailjackStopHullBreach"]
     133 [-]: JUMPIFNOT R5 L10; goto L10 if not var5
     134 [-]: GETIMPORT R5 34; var5 = _T["RailjackStopHullBreach"]
     135 [-]: CALL R5 1 1  ; var5()
L10: 136 [-]: GETUPVAL R6 1; var6 = upvalues[1]
     137 [-]: GETTABLEKS R5 R6 K19; var5 = var6[0x2DF8B2BA]
     138 [-]: GETIMPORT R6 16; var6 = 0x0469F296
     139 [-]: LOADK R7 K20 ; var7 = "TogglePlayerSpawnsScript"
     140 [-]: CALL R6 2 2  ; var6 = var6(var7)
     141 [-]: MOVE R7 R2   ; var7 = var2
     142 [-]: CALL R5 3 2  ; var5 = var5(var6, var7)
     143 [-]: LOADN R8 0   ; var8 = 0
     144 [-]: NAMECALL R6 R5 K21; var7 = var5; var6 = var5[0x05EEB9DB]
     145 [-]: CALL R6 3 1  ; var6(var7, var8)
     146 [-]: LOADK R8 K22 ; var8 = "Execute"
     147 [-]: NAMECALL R6 R5 K23; var7 = var5; var6 = var5[0x8EB2112D]
     148 [-]: CALL R6 3 1  ; var6(var7, var8)
     149 [-]: GETIMPORT R6 25; var6 = 0xBE190284
     150 [-]: GETUPVAL R8 2; var8 = upvalues[2]
     151 [-]: LOADN R9 1   ; var9 = 1
     152 [-]: NAMECALL R6 R6 K35; var7 = var6; var6 = var6[0x751F061D]
     153 [-]: CALL R6 4 1  ; var6(var7, var8, var9)
L11: 154 [-]: MOVE R7 R1   ; var7 = var1
     155 [-]: NAMECALL R5 R3 K36; var6 = var3; var5 = var3[0xD9848B59]
     156 [-]: CALL R5 3 1  ; var5(var6, var7)
     157 [-]: RETURN R0 0  ; 


; Name:            
; Defined at line: 175
; #Upvalues:       6
; #Parameters:     1
; Is_vararg:       0
; Max Stack Size:  9

       0 [-]: GETIMPORT R1 1; var1 = 0xBE190284
       1 [-]: GETUPVAL R3 0; var3 = upvalues[0]
       2 [-]: LOADN R4 0   ; var4 = 0
       3 [-]: NAMECALL R1 R1 K2; var2 = var1; var1 = var1[0x0EB34C69]
       4 [-]: CALL R1 4 2  ; var1 = var1(var2, var3, var4)
       5 [-]: JUMPXEQKN R1 K3 L3 NOT; 
       6 [-]: LOADN R3 1   ; var3 = 1
       7 [-]: GETUPVAL R4 1; var4 = upvalues[1]
       8 [-]: LENGTH R1 R4 ; var1 = #var4
       9 [-]: LOADN R2 1   ; var2 = 1
      10 [-]: FORNPREP R1 L4; nforprep start - [escape at L4] -- var1 = iterator
L 0:  11 [-]: GETUPVAL R6 1; var6 = upvalues[1]
      12 [-]: GETTABLE R5 R6 R3; var5 = var6[var3]
      13 [-]: FASTCALL1 64 R5 L1; 
      14 [-]: GETIMPORT R4 5; var4 = 0x7B998233
      15 [-]: CALL R4 2 2  ; var4 = var4(var5)
L 1:  16 [-]: JUMPIF R4 L2 ; goto L2 if var4
      17 [-]: GETUPVAL R5 1; var5 = upvalues[1]
      18 [-]: GETTABLE R4 R5 R3; var4 = var5[var3]
      19 [-]: LOADN R6 0   ; var6 = 0
      20 [-]: NAMECALL R4 R4 K6; var5 = var4; var4 = var4[0xEA53C9C4]
      21 [-]: CALL R4 3 1  ; var4(var5, var6)
L 2:  22 [-]: FORNLOOP R1 L0; nforloop end - iterate + goto L0
      23 [-]: JUMP L4      ; goto L4
L 3:  24 [-]: GETUPVAL R1 2; var1 = upvalues[2]
      25 [-]: CALL R1 1 2  ; var1 = var1()
      26 [-]: NAMECALL R1 R1 K7; var2 = var1; var1 = var1[0x5163741E]
      27 [-]: CALL R1 2 2  ; var1 = var1(var2)
      28 [-]: NAMECALL R1 R1 K8; var2 = var1; var1 = var1[0x1AC1655C]
      29 [-]: CALL R1 2 2  ; var1 = var1(var2)
      30 [-]: GETIMPORT R3 10; var3 = 0x0469F296
      31 [-]: LOADK R4 K11 ; var4 = "CapitalShipInvuln"
      32 [-]: CALL R3 2 0  ; var3, ... = var3(var4)
      33 [-]: NAMECALL R1 R1 K12; var2 = var1; var1 = var1[0x8733746A]
      34 [-]: CALL R1 0 2  ; var1 = var1(var2, ...)
      35 [-]: JUMPIF R1 L4 ; goto L4 if var1
      36 [-]: GETUPVAL R1 3; var1 = upvalues[3]
      37 [-]: LOADN R2 0   ; var2 = 0
      38 [-]: LOADB R3 0   ; var3 = false
      39 [-]: CALL R1 3 1  ; var1(var2, var3)
L 4:  40 [-]: FASTCALL1 64 R0 L5; 
      41 [-]: MOVE R2 R0   ; var2 = var0
      42 [-]: GETIMPORT R1 5; var1 = 0x7B998233
      43 [-]: CALL R1 2 2  ; var1 = var1(var2)
L 5:  44 [-]: JUMPIF R1 L22; goto L22 if var1
      45 [-]: GETUPVAL R2 4; var2 = upvalues[4]
      46 [-]: FASTCALL1 64 R2 L6; 
      47 [-]: GETIMPORT R1 5; var1 = 0x7B998233
      48 [-]: CALL R1 2 2  ; var1 = var1(var2)
L 6:  49 [-]: JUMPIF R1 L22; goto L22 if var1
      50 [-]: GETIMPORT R2 1; var2 = 0xBE190284
      51 [-]: GETUPVAL R4 5; var4 = upvalues[5]
      52 [-]: LOADN R5 0   ; var5 = 0
      53 [-]: NAMECALL R2 R2 K2; var3 = var2; var2 = var2[0x0EB34C69]
      54 [-]: CALL R2 4 2  ; var2 = var2(var3, var4, var5)
      55 [-]: JUMPXEQKN R2 K3 L7; 
      56 [-]: LOADB R1 0 +1; var1 = false
L 7:  57 [-]: LOADB R1 1   ; var1 = true
L 8:  58 [-]: JUMPIFNOT R1 L11; goto L11 if not var1
      59 [-]: GETIMPORT R2 14; var2 = 0x89326C93
      60 [-]: NAMECALL R2 R2 K15; var3 = var2; var2 = var2[0x8B5B1F58]
      61 [-]: CALL R2 2 2  ; var2 = var2(var3)
      62 [-]: LOADN R5 1   ; var5 = 1
      63 [-]: LENGTH R3 R2 ; var3 = #var2
      64 [-]: LOADN R4 1   ; var4 = 1
      65 [-]: FORNPREP R3 L11; nforprep start - [escape at L11] -- var3 = iterator
L 9:  66 [-]: GETUPVAL R6 4; var6 = upvalues[4]
      67 [-]: GETTABLE R8 R2 R5; var8 = var2[var5]
      68 [-]: NAMECALL R6 R6 K16; var7 = var6; var6 = var6[0x7941D56E]
      69 [-]: CALL R6 3 2  ; var6 = var6(var7, var8)
      70 [-]: JUMPIF R6 L10; goto L10 if var6
      71 [-]: LOADB R1 0   ; var1 = false
      72 [-]: JUMP L11     ; goto L11
L10:  73 [-]: FORNLOOP R3 L9; nforloop end - iterate + goto L9
L11:  74 [-]: GETIMPORT R3 1; var3 = 0xBE190284
      75 [-]: GETUPVAL R5 0; var5 = upvalues[0]
      76 [-]: LOADN R6 0   ; var6 = 0
      77 [-]: NAMECALL R3 R3 K2; var4 = var3; var3 = var3[0x0EB34C69]
      78 [-]: CALL R3 4 2  ; var3 = var3(var4, var5, var6)
      79 [-]: JUMPXEQKN R3 K17 L12; 
      80 [-]: LOADB R2 0 +1; var2 = false
L12:  81 [-]: LOADB R2 1   ; var2 = true
L13:  82 [-]: JUMPIFEQ R1 R2 L21; goto L21 if var1 == var1245460
      83 [-]: JUMPIFNOT R1 L17; goto L17 if not var1
      84 [-]: LOADN R4 1   ; var4 = 1
      85 [-]: GETUPVAL R5 1; var5 = upvalues[1]
      86 [-]: LENGTH R2 R5 ; var2 = #var5
      87 [-]: LOADN R3 1   ; var3 = 1
      88 [-]: FORNPREP R2 L17; nforprep start - [escape at L17] -- var2 = iterator
L14:  89 [-]: GETUPVAL R7 1; var7 = upvalues[1]
      90 [-]: GETTABLE R6 R7 R4; var6 = var7[var4]
      91 [-]: FASTCALL1 64 R6 L15; 
      92 [-]: GETIMPORT R5 5; var5 = 0x7B998233
      93 [-]: CALL R5 2 2  ; var5 = var5(var6)
L15:  94 [-]: JUMPIF R5 L16; goto L16 if var5
      95 [-]: GETUPVAL R6 1; var6 = upvalues[1]
      96 [-]: GETTABLE R5 R6 R4; var5 = var6[var4]
      97 [-]: LOADN R7 3   ; var7 = 3
      98 [-]: NAMECALL R5 R5 K6; var6 = var5; var5 = var5[0xEA53C9C4]
      99 [-]: CALL R5 3 1  ; var5(var6, var7)
L16: 100 [-]: FORNLOOP R2 L14; nforloop end - iterate + goto L14
L17: 101 [-]: GETUPVAL R2 3; var2 = upvalues[3]
     102 [-]: LOADN R3 0   ; var3 = 0
     103 [-]: NOT R4 R1    ; var4 = not var1
     104 [-]: CALL R2 3 1  ; var2(var3, var4)
L18: 105 [-]: GETIMPORT R3 1; var3 = 0xBE190284
     106 [-]: GETUPVAL R5 0; var5 = upvalues[0]
     107 [-]: LOADN R6 0   ; var6 = 0
     108 [-]: NAMECALL R3 R3 K2; var4 = var3; var3 = var3[0x0EB34C69]
     109 [-]: CALL R3 4 2  ; var3 = var3(var4, var5, var6)
     110 [-]: JUMPXEQKN R3 K17 L19; 
     111 [-]: LOADB R2 0 +1; var2 = false
L19: 112 [-]: LOADB R2 1   ; var2 = true
L20: 113 [-]: JUMPIFEQ R2 R1 L21; goto L21 if var2 == var1245729
     114 [-]: GETIMPORT R2 19; var2 = 0xCBD666E1
     115 [-]: LOADN R3 0   ; var3 = 0
     116 [-]: CALL R2 2 1  ; var2(var3)
     117 [-]: JUMPBACK L18 ; goto L18
L21: 118 [-]: GETIMPORT R2 19; var2 = 0xCBD666E1
     119 [-]: LOADN R3 0   ; var3 = 0
     120 [-]: CALL R2 2 1  ; var2(var3)
     121 [-]: JUMPBACK L4  ; goto L4
L22: 122 [-]: RETURN R0 0  ; 


; Name:            
; Defined at line: 215
; #Upvalues:       3
; #Parameters:     1
; Is_vararg:       0
; Max Stack Size:  9

       0 [-]: NAMECALL R1 R0 K0; var2 = var0; var1 = var0[0x53C3399F]
       1 [-]: CALL R1 2 2  ; var1 = var1(var2)
L 0:   2 [-]: NAMECALL R2 R0 K0; var3 = var0; var2 = var0[0x53C3399F]
       3 [-]: CALL R2 2 2  ; var2 = var2(var3)
       4 [-]: JUMPXEQKN R2 K1 L5; 
       5 [-]: JUMPIFEQ R2 R1 L5; goto L5 if var2 == var131374
       6 [-]: MOVE R1 R2   ; var1 = var2
       7 [-]: GETIMPORT R3 3; var3 = 0x3D106989
       8 [-]: LOADK R5 K4  ; var5 = "Showdown transmission index is "
       9 [-]: MOVE R6 R1   ; var6 = var1
      10 [-]: CONCAT R4 R5 R6; var4 = var5 .. var6
      11 [-]: CALL R3 2 1  ; var3(var4)
      12 [-]: GETIMPORT R4 6; var4 = 0xEF885CB7
      13 [-]: GETTABLE R3 R4 R1; var3 = var4[var1]
      14 [-]: FASTCALL1 64 R3 L1; 
      15 [-]: MOVE R5 R3   ; var5 = var3
      16 [-]: GETIMPORT R4 8; var4 = 0x7B998233
      17 [-]: CALL R4 2 2  ; var4 = var4(var5)
L 1:  18 [-]: JUMPIF R4 L5 ; goto L5 if var4
L 2:  19 [-]: GETUPVAL R4 0; var4 = upvalues[0]
      20 [-]: LOADB R5 1   ; var5 = true
      21 [-]: CALL R4 2 2  ; var4 = var4(var5)
      22 [-]: JUMPIFNOT R4 L3; goto L3 if not var4
      23 [-]: GETIMPORT R4 10; var4 = 0xCBD666E1
      24 [-]: LOADK R5 K11 ; var5 = 0.20000000298023224
      25 [-]: CALL R4 2 1  ; var4(var5)
      26 [-]: JUMPBACK L2  ; goto L2
L 3:  27 [-]: GETIMPORT R4 3; var4 = 0x3D106989
      28 [-]: LOADK R6 K12 ; var6 = "Playing transmission "
      29 [-]: FASTCALL1 63 R3 L4; 
      30 [-]: MOVE R8 R3   ; var8 = var3
      31 [-]: GETIMPORT R7 14; var7 = 0x64FB1586
      32 [-]: CALL R7 2 2  ; var7 = var7(var8)
L 4:  33 [-]: CONCAT R5 R6 R7; var5 = var6 .. var7
      34 [-]: CALL R4 2 1  ; var4(var5)
      35 [-]: GETUPVAL R5 1; var5 = upvalues[1]
      36 [-]: GETTABLEKS R4 R5 K15; var4 = var5[0x9D3FE9C0]
      37 [-]: MOVE R5 R3   ; var5 = var3
      38 [-]: CALL R4 2 2  ; var4 = var4(var5)
      39 [-]: JUMPIFNOT R4 L5; goto L5 if not var4
      40 [-]: GETUPVAL R6 2; var6 = upvalues[2]
      41 [-]: GETTABLEKS R5 R6 K16; var5 = var6[0xFC87A231]
      42 [-]: CALL R5 1 1  ; var5()
L 5:  43 [-]: GETIMPORT R3 10; var3 = 0xCBD666E1
      44 [-]: LOADN R4 0   ; var4 = 0
      45 [-]: CALL R3 2 1  ; var3(var4)
      46 [-]: JUMPBACK L0  ; goto L0
      47 [-]: RETURN R0 0  ; 


; Name:            
; Defined at line: 238
; #Upvalues:       0
; #Parameters:     0
; Is_vararg:       0
; Max Stack Size:  9

       0 [-]: GETIMPORT R1 1; var1 = 0x75B0301E
       1 [-]: FASTCALL1 64 R1 L0; 
       2 [-]: GETIMPORT R0 3; var0 = 0x7B998233
       3 [-]: CALL R0 2 2  ; var0 = var0(var1)
L 0:   4 [-]: JUMPIFNOT R0 L1; goto L1 if not var0
       5 [-]: RETURN R0 0  ; 
L 1:   6 [-]: GETIMPORT R0 5; var0 = 0x89326C93
       7 [-]: NAMECALL R0 R0 K6; var1 = var0; var0 = var0[0x8B5B1F58]
       8 [-]: CALL R0 2 2  ; var0 = var0(var1)
       9 [-]: GETIMPORT R1 8; var1 = 0xC8802016
      10 [-]: MOVE R2 R0   ; var2 = var0
      11 [-]: CALL R1 2 4  ; var1, var2, var3 = var1(var2)
      12 [-]: FORGPREP_INEXT R1 L4; 
L 2:  13 [-]: FASTCALL1 64 R5 L3; 
      14 [-]: MOVE R7 R5   ; var7 = var5
      15 [-]: GETIMPORT R6 3; var6 = 0x7B998233
      16 [-]: CALL R6 2 2  ; var6 = var6(var7)
L 3:  17 [-]: JUMPIF R6 L4 ; goto L4 if var6
      18 [-]: GETIMPORT R8 1; var8 = 0x75B0301E
      19 [-]: NAMECALL R6 R5 K9; var7 = var5; var6 = var5[0x2A748F85]
      20 [-]: CALL R6 3 1  ; var6(var7, var8)
L 4:  21 [-]: FORGLOOP R1 L2 2 [inext]; 
      22 [-]: RETURN R0 0  ; 


; Name:            
; Defined at line: 251
; #Upvalues:       0
; #Parameters:     0
; Is_vararg:       0
; Max Stack Size:  9

       0 [-]: GETIMPORT R1 1; var1 = 0x04462D8E
       1 [-]: FASTCALL1 64 R1 L0; 
       2 [-]: GETIMPORT R0 3; var0 = 0x7B998233
       3 [-]: CALL R0 2 2  ; var0 = var0(var1)
L 0:   4 [-]: JUMPIFNOT R0 L1; goto L1 if not var0
       5 [-]: RETURN R0 0  ; 
L 1:   6 [-]: GETIMPORT R0 5; var0 = 0x89326C93
       7 [-]: NAMECALL R0 R0 K6; var1 = var0; var0 = var0[0x8B5B1F58]
       8 [-]: CALL R0 2 2  ; var0 = var0(var1)
       9 [-]: GETIMPORT R1 8; var1 = 0xC8802016
      10 [-]: MOVE R2 R0   ; var2 = var0
      11 [-]: CALL R1 2 4  ; var1, var2, var3 = var1(var2)
      12 [-]: FORGPREP_INEXT R1 L4; 
L 2:  13 [-]: FASTCALL1 64 R5 L3; 
      14 [-]: MOVE R7 R5   ; var7 = var5
      15 [-]: GETIMPORT R6 3; var6 = 0x7B998233
      16 [-]: CALL R6 2 2  ; var6 = var6(var7)
L 3:  17 [-]: JUMPIF R6 L4 ; goto L4 if var6
      18 [-]: GETIMPORT R8 1; var8 = 0x04462D8E
      19 [-]: NAMECALL R6 R5 K9; var7 = var5; var6 = var5[0x2A748F85]
      20 [-]: CALL R6 3 1  ; var6(var7, var8)
L 4:  21 [-]: FORGLOOP R1 L2 2 [inext]; 
      22 [-]: RETURN R0 0  ; 


; Name:            
; Defined at line: 264
; #Upvalues:       0
; #Parameters:     0
; Is_vararg:       0
; Max Stack Size:  9

       0 [-]: GETIMPORT R1 1; var1 = 0x4DC185DD
       1 [-]: FASTCALL1 64 R1 L0; 
       2 [-]: GETIMPORT R0 3; var0 = 0x7B998233
       3 [-]: CALL R0 2 2  ; var0 = var0(var1)
L 0:   4 [-]: JUMPIFNOT R0 L1; goto L1 if not var0
       5 [-]: RETURN R0 0  ; 
L 1:   6 [-]: GETIMPORT R0 5; var0 = 0x89326C93
       7 [-]: NAMECALL R0 R0 K6; var1 = var0; var0 = var0[0x8B5B1F58]
       8 [-]: CALL R0 2 2  ; var0 = var0(var1)
       9 [-]: GETIMPORT R1 8; var1 = 0xC8802016
      10 [-]: MOVE R2 R0   ; var2 = var0
      11 [-]: CALL R1 2 4  ; var1, var2, var3 = var1(var2)
      12 [-]: FORGPREP_INEXT R1 L4; 
L 2:  13 [-]: FASTCALL1 64 R5 L3; 
      14 [-]: MOVE R7 R5   ; var7 = var5
      15 [-]: GETIMPORT R6 3; var6 = 0x7B998233
      16 [-]: CALL R6 2 2  ; var6 = var6(var7)
L 3:  17 [-]: JUMPIF R6 L4 ; goto L4 if var6
      18 [-]: GETIMPORT R8 1; var8 = 0x4DC185DD
      19 [-]: NAMECALL R6 R5 K9; var7 = var5; var6 = var5[0x2A748F85]
      20 [-]: CALL R6 3 1  ; var6(var7, var8)
L 4:  21 [-]: FORGLOOP R1 L2 2 [inext]; 
      22 [-]: RETURN R0 0  ; 


; Name:            
; Defined at line: 277
; #Upvalues:       3
; #Parameters:     0
; Is_vararg:       0
; Max Stack Size:  3

       0 [-]: GETUPVAL R0 0; var0 = upvalues[0]
       1 [-]: GETUPVAL R2 1; var2 = upvalues[1]
       2 [-]: LENGTH R1 R2 ; var1 = #var2
       3 [-]: JUMPIFNOTEQ R0 R1 L0; goto L0 if var0 ~= var65584
       4 [-]: LOADN R0 1   ; var0 = 1
       5 [-]: SETUPVAL R0 0; upvalues[0] = var0
       6 [-]: GETUPVAL R1 2; var1 = upvalues[2]
       7 [-]: GETTABLEKS R0 R1 K0; var0 = var1[0x622A0C19]
       8 [-]: GETUPVAL R1 1; var1 = upvalues[1]
       9 [-]: CALL R0 2 1  ; var0(var1)
      10 [-]: JUMP L1      ; goto L1
L 0:  11 [-]: GETUPVAL R1 0; var1 = upvalues[0]
      12 [-]: ADDK R0 R1 K1; var0 = var1 + 1
      13 [-]: SETUPVAL R0 0; upvalues[0] = var0
L 1:  14 [-]: GETUPVAL R1 1; var1 = upvalues[1]
      15 [-]: GETUPVAL R2 0; var2 = upvalues[0]
      16 [-]: GETTABLE R0 R1 R2; var0 = var1[var2]
      17 [-]: RETURN R0 1  ; 


; Name:            
; Defined at line: 288
; #Upvalues:       7
; #Parameters:     1
; Is_vararg:       0
; Max Stack Size:  11

       0 [-]: GETUPVAL R2 0; var2 = upvalues[0]
       1 [-]: FASTCALL1 64 R2 L0; 
       2 [-]: GETIMPORT R1 1; var1 = 0x7B998233
       3 [-]: CALL R1 2 2  ; var1 = var1(var2)
L 0:   4 [-]: JUMPIF R1 L6 ; goto L6 if var1
       5 [-]: LOADN R3 1   ; var3 = 1
       6 [-]: LOADN R1 2   ; var1 = 2
       7 [-]: LOADN R2 1   ; var2 = 1
       8 [-]: FORNPREP R1 L6; nforprep start - [escape at L6] -- var1 = iterator
L 1:   9 [-]: GETUPVAL R7 1; var7 = upvalues[1]
      10 [-]: GETUPVAL R9 2; var9 = upvalues[2]
      11 [-]: LENGTH R8 R9 ; var8 = #var9
      12 [-]: JUMPIFNOTEQ R7 R8 L2; goto L2 if var7 ~= var67376
      13 [-]: LOADN R7 1   ; var7 = 1
      14 [-]: SETUPVAL R7 1; upvalues[7] = var1
      15 [-]: GETUPVAL R8 3; var8 = upvalues[3]
      16 [-]: GETTABLEKS R7 R8 K2; var7 = var8[0x622A0C19]
      17 [-]: GETUPVAL R8 2; var8 = upvalues[2]
      18 [-]: CALL R7 2 1  ; var7(var8)
      19 [-]: JUMP L3      ; goto L3
L 2:  20 [-]: GETUPVAL R8 1; var8 = upvalues[1]
      21 [-]: ADDK R7 R8 K3; var7 = var8 + 1
      22 [-]: SETUPVAL R7 1; upvalues[7] = var1
L 3:  23 [-]: GETUPVAL R7 2; var7 = upvalues[2]
      24 [-]: GETUPVAL R8 1; var8 = upvalues[1]
      25 [-]: GETTABLE R6 R7 R8; var6 = var7[var8]
      26 [-]: GETUPVAL R7 0; var7 = upvalues[0]
      27 [-]: LOADN R8 30  ; var8 = 30
      28 [-]: GETUPVAL R9 4; var9 = upvalues[4]
      29 [-]: NAMECALL R4 R0 K4; var5 = var0; var4 = var0[0x2883E796]
      30 [-]: CALL R4 6 2  ; var4 = var4(var5, var6, var7, var8, var9)
      31 [-]: FASTCALL1 64 R4 L4; 
      32 [-]: MOVE R6 R4   ; var6 = var4
      33 [-]: GETIMPORT R5 1; var5 = 0x7B998233
      34 [-]: CALL R5 2 2  ; var5 = var5(var6)
L 4:  35 [-]: JUMPIF R5 L5 ; goto L5 if var5
      36 [-]: LOADB R7 0   ; var7 = false
      37 [-]: NAMECALL R5 R4 K5; var6 = var4; var5 = var4[0xFCC63B72]
      38 [-]: CALL R5 3 1  ; var5(var6, var7)
      39 [-]: LOADB R7 1   ; var7 = true
      40 [-]: NAMECALL R5 R4 K6; var6 = var4; var5 = var4[0x2D427AB1]
      41 [-]: CALL R5 3 1  ; var5(var6, var7)
      42 [-]: NAMECALL R5 R4 K7; var6 = var4; var5 = var4[0xBB610E5B]
      43 [-]: CALL R5 2 2  ; var5 = var5(var6)
      44 [-]: LOADB R8 1   ; var8 = true
      45 [-]: NAMECALL R6 R5 K8; var7 = var5; var6 = var5[0x555194BB]
      46 [-]: CALL R6 3 1  ; var6(var7, var8)
      47 [-]: GETUPVAL R8 5; var8 = upvalues[5]
      48 [-]: GETUPVAL R9 0; var9 = upvalues[0]
      49 [-]: NAMECALL R9 R9 K9; var10 = var9; var9 = var9[0x808B79E6]
      50 [-]: CALL R9 2 0  ; var9, ... = var9(var10)
      51 [-]: NAMECALL R6 R5 K10; var7 = var5; var6 = var5[0xFAF7BD22]
      52 [-]: CALL R6 0 1  ; var6(var7, ...)
      53 [-]: GETUPVAL R7 6; var7 = upvalues[6]
      54 [-]: FASTCALL2 52 R7 R5 L5; 
      55 [-]: MOVE R8 R5   ; var8 = var5
      56 [-]: GETIMPORT R6 13; var6 = 0x33BDD652[0x23D5322F]
      57 [-]: CALL R6 3 1  ; var6(var7, var8)
L 5:  58 [-]: FORNLOOP R1 L1; nforloop end - iterate + goto L1
L 6:  59 [-]: RETURN R0 0  ; 


; Name:            
; Defined at line: 304
; #Upvalues:       4
; #Parameters:     0
; Is_vararg:       0
; Max Stack Size:  9

       0 [-]: GETIMPORT R0 1; var0 = 0x89326C93
       1 [-]: GETIMPORT R2 3; var2 = 0x0469F296
       2 [-]: LOADK R3 K4  ; var3 = "LawyerPet"
       3 [-]: CALL R2 2 0  ; var2, ... = var2(var3)
       4 [-]: NAMECALL R0 R0 K5; var1 = var0; var0 = var0[0xC7FCADA9]
       5 [-]: CALL R0 0 2  ; var0 = var0(var1, ...)
       6 [-]: LENGTH R1 R0 ; var1 = #var0
       7 [-]: SETUPVAL R1 0; upvalues[1] = var0
       8 [-]: GETIMPORT R1 7; var1 = 0xC8802016
       9 [-]: MOVE R2 R0   ; var2 = var0
      10 [-]: CALL R1 2 4  ; var1, var2, var3 = var1(var2)
      11 [-]: FORGPREP_INEXT R1 L2; 
L 0:  12 [-]: GETUPVAL R7 1; var7 = upvalues[1]
      13 [-]: FASTCALL2 52 R7 R5 L1; 
      14 [-]: MOVE R8 R5   ; var8 = var5
      15 [-]: GETIMPORT R6 10; var6 = 0x33BDD652[0x23D5322F]
      16 [-]: CALL R6 3 1  ; var6(var7, var8)
L 1:  17 [-]: LOADB R6 1   ; var6 = true
      18 [-]: SETUPVAL R6 2; upvalues[6] = var2
      19 [-]: LOADN R7 2   ; var7 = 2
      20 [-]: GETUPVAL R8 0; var8 = upvalues[0]
      21 [-]: ADD R6 R7 R8 ; var6 = var7 + var8
      22 [-]: SETUPVAL R6 3; upvalues[6] = var3
L 2:  23 [-]: FORGLOOP R1 L0 2 [inext]; 
      24 [-]: RETURN R0 0  ; 


; Name:            
; Defined at line: 316
; #Upvalues:       0
; #Parameters:     1
; Is_vararg:       0
; Max Stack Size:  9

       0 [-]: GETIMPORT R1 1; var1 = 0x89326C93
       1 [-]: NAMECALL R1 R1 K2; var2 = var1; var1 = var1[0x7D108DDB]
       2 [-]: CALL R1 2 2  ; var1 = var1(var2)
       3 [-]: GETIMPORT R2 4; var2 = 0xC8802016
       4 [-]: MOVE R3 R1   ; var3 = var1
       5 [-]: CALL R2 2 4  ; var2, var3, var4 = var2(var3)
       6 [-]: FORGPREP_INEXT R2 L1; 
L 0:   7 [-]: NAMECALL R7 R6 K5; var8 = var6; var7 = var6[0x5CA33548]
       8 [-]: CALL R7 2 2  ; var7 = var7(var8)
       9 [-]: JUMPIFNOTEQ R7 R0 L1; goto L1 if var7 ~= var67334
      10 [-]: LOADB R7 1   ; var7 = true
      11 [-]: RETURN R7 1  ; 
L 1:  12 [-]: FORGLOOP R2 L0 2 [inext]; 
      13 [-]: LOADB R2 0   ; var2 = false
      14 [-]: RETURN R2 1  ; 


; Name:            
; Defined at line: 326
; #Upvalues:       6
; #Parameters:     2
; Is_vararg:       0
; Max Stack Size:  15

       0 [-]: GETIMPORT R2 1; var2 = 0x3D106989
       1 [-]: LOADK R3 K2  ; var3 = "Requesting liches"
       2 [-]: CALL R2 2 1  ; var2(var3)
       3 [-]: JUMPIFNOT R0 L4; goto L4 if not var0
       4 [-]: GETUPVAL R3 1; var3 = upvalues[1]
       5 [-]: GETTABLEKS R2 R3 K3; var2 = var3[0x21EAFB00]
       6 [-]: LOADK R3 K4  ; var3 = "NemesisAssassinate"
       7 [-]: CALL R2 2 2  ; var2 = var2(var3)
       8 [-]: SETUPVAL R2 0; upvalues[2] = var0
       9 [-]: GETUPVAL R2 0; var2 = upvalues[0]
      10 [-]: JUMPXEQKNIL R2 L4 NOT; 
      11 [-]: GETIMPORT R2 6; var2 = 0xBE190284
      12 [-]: NAMECALL R2 R2 K7; var3 = var2; var2 = var2[0xEF893AEC]
      13 [-]: CALL R2 2 2  ; var2 = var2(var3)
      14 [-]: NAMECALL R2 R2 K8; var3 = var2; var2 = var2[0x243148D6]
      15 [-]: CALL R2 2 2  ; var2 = var2(var3)
      16 [-]: NEWTABLE R3 0 0; var3 = {}
      17 [-]: SETUPVAL R3 0; upvalues[3] = var0
      18 [-]: GETIMPORT R3 10; var3 = 0xE7F2B02F
      19 [-]: NAMECALL R3 R3 K11; var4 = var3; var3 = var3[0x6D0AA187]
      20 [-]: CALL R3 2 2  ; var3 = var3(var4)
      21 [-]: GETIMPORT R4 13; var4 = 0xCFC01047
      22 [-]: MOVE R5 R3   ; var5 = var3
      23 [-]: CALL R4 2 4  ; var4, var5, var6 = var4(var5)
      24 [-]: FORGPREP_NEXT R4 L3; 
L 0:  25 [-]: GETIMPORT R9 16; var9 = cjson[0x7AB914D8]
      26 [-]: GETTABLEKS R10 R8 K17; var10 = var8["loadout"]
      27 [-]: CALL R9 2 2  ; var9 = var9(var10)
      28 [-]: JUMPIFNOT R9 L3; goto L3 if not var9
      29 [-]: GETTABLEKS R10 R9 K18; var10 = var9["Nemesis"]
      30 [-]: JUMPIFNOT R10 L3; goto L3 if not var10
      31 [-]: GETUPVAL R11 2; var11 = upvalues[2]
      32 [-]: GETTABLEKS R10 R11 K19; var10 = var11[0xEAB95B40]
      33 [-]: GETTABLEKS R11 R9 K18; var11 = var9["Nemesis"]
      34 [-]: CALL R10 2 3 ; var10, var11 = var10(var11)
      35 [-]: JUMPIFNOT R10 L2; goto L2 if not var10
      36 [-]: GETTABLEKS R12 R10 K20; var12 = var10["mFaction"]
      37 [-]: LOADN R13 1  ; var13 = 1
      38 [-]: JUMPIFNOTEQ R12 R13 L2; goto L2 if var12 ~= var199740
      39 [-]: GETUPVAL R12 3; var12 = upvalues[3]
      40 [-]: JUMPIFNOTEQ R2 R12 L2; goto L2 if var2 ~= var-703919041
      41 [-]: GETTABLEKS R12 R11 K21; var12 = var11["mWeakened"]
      42 [-]: JUMPIFNOT R12 L3; goto L3 if not var12
      43 [-]: GETUPVAL R13 0; var13 = upvalues[0]
      44 [-]: GETTABLEKS R14 R8 K22; var14 = var8["name"]
      45 [-]: FASTCALL2 52 R13 R14 L1; 
      46 [-]: GETIMPORT R12 25; var12 = 0x33BDD652[0x23D5322F]
      47 [-]: CALL R12 3 1 ; var12(var13, var14)
L 1:  48 [-]: JUMP L3      ; goto L3
L 2:  49 [-]: JUMPIFNOT R10 L3; goto L3 if not var10
      50 [-]: GETTABLEKS R12 R10 K20; var12 = var10["mFaction"]
      51 [-]: LOADN R13 0  ; var13 = 0
      52 [-]: JUMPIFNOTEQ R12 R13 L3; goto L3 if var12 ~= var265276
      53 [-]: GETUPVAL R12 4; var12 = upvalues[4]
      54 [-]: JUMPIFNOTEQ R2 R12 L3; goto L3 if var2 ~= var-703919041
      55 [-]: GETTABLEKS R12 R11 K21; var12 = var11["mWeakened"]
      56 [-]: JUMPIFNOT R12 L3; goto L3 if not var12
      57 [-]: GETUPVAL R13 0; var13 = upvalues[0]
      58 [-]: GETTABLEKS R14 R8 K22; var14 = var8["name"]
      59 [-]: FASTCALL2 52 R13 R14 L3; 
      60 [-]: GETIMPORT R12 25; var12 = 0x33BDD652[0x23D5322F]
      61 [-]: CALL R12 3 1 ; var12(var13, var14)
L 3:  62 [-]: FORGLOOP R4 L0 2; 
      63 [-]: GETUPVAL R5 1; var5 = upvalues[1]
      64 [-]: GETTABLEKS R4 R5 K26; var4 = var5[0xE80ADB64]
      65 [-]: LOADK R5 K4  ; var5 = "NemesisAssassinate"
      66 [-]: GETUPVAL R6 0; var6 = upvalues[0]
      67 [-]: CALL R4 3 1  ; var4(var5, var6)
L 4:  68 [-]: JUMPIFNOT R1 L10; goto L10 if not var1
      69 [-]: LOADN R4 1   ; var4 = 1
      70 [-]: GETUPVAL R5 0; var5 = upvalues[0]
      71 [-]: LENGTH R2 R5 ; var2 = #var5
      72 [-]: LOADN R3 1   ; var3 = 1
      73 [-]: FORNPREP R2 L9; nforprep start - [escape at L9] -- var2 = iterator
L 5:  74 [-]: GETUPVAL R6 0; var6 = upvalues[0]
      75 [-]: GETTABLEN R5 R6 1; var5 = var6[1]
      76 [-]: GETUPVAL R6 5; var6 = upvalues[5]
      77 [-]: MOVE R7 R5   ; var7 = var5
      78 [-]: CALL R6 2 2  ; var6 = var6(var7)
      79 [-]: JUMPIFNOT R6 L7; goto L7 if not var6
      80 [-]: GETIMPORT R6 1; var6 = 0x3D106989
      81 [-]: LOADK R8 K27 ; var8 = "RequestLiches: requesting for "
      82 [-]: MOVE R9 R5   ; var9 = var5
      83 [-]: CONCAT R7 R8 R9; var7 = var8 .. var9
      84 [-]: CALL R6 2 1  ; var6(var7)
      85 [-]: GETIMPORT R6 6; var6 = 0xBE190284
      86 [-]: GETIMPORT R8 29; var8 = 0x0469F296
      87 [-]: MOVE R10 R5  ; var10 = var5
      88 [-]: LOADK R11 K30; var11 = "NemesisSpawned"
      89 [-]: CONCAT R9 R10 R11; var9 = var10 .. var11
      90 [-]: CALL R8 2 2  ; var8 = var8(var9)
      91 [-]: LOADN R9 0   ; var9 = 0
      92 [-]: NAMECALL R6 R6 K31; var7 = var6; var6 = var6[0x0EB34C69]
      93 [-]: CALL R6 4 2  ; var6 = var6(var7, var8, var9)
      94 [-]: JUMPXEQKN R6 K32 L6 NOT; 
      95 [-]: GETIMPORT R6 6; var6 = 0xBE190284
      96 [-]: GETIMPORT R8 29; var8 = 0x0469F296
      97 [-]: LOADK R10 K33; var10 = "RequestNemesis_"
      98 [-]: MOVE R11 R5  ; var11 = var5
      99 [-]: CONCAT R9 R10 R11; var9 = var10 .. var11
     100 [-]: CALL R8 2 2  ; var8 = var8(var9)
     101 [-]: LOADN R9 1   ; var9 = 1
     102 [-]: NAMECALL R6 R6 K34; var7 = var6; var6 = var6[0x751F061D]
     103 [-]: CALL R6 4 1  ; var6(var7, var8, var9)
L 6: 104 [-]: RETURN R0 0  ; 
L 7: 105 [-]: GETIMPORT R6 1; var6 = 0x3D106989
     106 [-]: LOADK R8 K35 ; var8 = "RequestLiches: "
     107 [-]: MOVE R9 R5   ; var9 = var5
     108 [-]: LOADK R10 K36; var10 = " not currently connected"
     109 [-]: CONCAT R7 R8 R10; var7 = var8 .. var10
     110 [-]: CALL R6 2 1  ; var6(var7)
     111 [-]: GETUPVAL R7 0; var7 = upvalues[0]
     112 [-]: LENGTH R6 R7 ; var6 = #var7
     113 [-]: LOADN R7 1   ; var7 = 1
     114 [-]: JUMPIFNOTLT R7 R6 L8; goto L8 if var7 >= var67105
     115 [-]: GETIMPORT R6 1; var6 = 0x3D106989
     116 [-]: LOADK R8 K37 ; var8 = "RequestLiches: Moving "
     117 [-]: MOVE R9 R5   ; var9 = var5
     118 [-]: LOADK R10 K38; var10 = " to the end of the queue"
     119 [-]: CONCAT R7 R8 R10; var7 = var8 .. var10
     120 [-]: CALL R6 2 1  ; var6(var7)
     121 [-]: GETIMPORT R6 40; var6 = 0x33BDD652[0x9C1F3B5A]
     122 [-]: GETUPVAL R7 0; var7 = upvalues[0]
     123 [-]: LOADN R8 1   ; var8 = 1
     124 [-]: CALL R6 3 1  ; var6(var7, var8)
     125 [-]: GETUPVAL R7 0; var7 = upvalues[0]
     126 [-]: FASTCALL2 52 R7 R5 L8; 
     127 [-]: MOVE R8 R5   ; var8 = var5
     128 [-]: GETIMPORT R6 25; var6 = 0x33BDD652[0x23D5322F]
     129 [-]: CALL R6 3 1  ; var6(var7, var8)
L 8: 130 [-]: FORNLOOP R2 L5; nforloop end - iterate + goto L5
L 9: 131 [-]: GETIMPORT R2 1; var2 = 0x3D106989
     132 [-]: LOADK R3 K41 ; var3 = "RequestLiches: no liches available"
     133 [-]: CALL R2 2 1  ; var2(var3)
     134 [-]: NEWTABLE R2 0 0; var2 = {}
     135 [-]: SETUPVAL R2 0; upvalues[2] = var0
L10: 136 [-]: RETURN R0 0  ; 


; Name:            
; Defined at line: 381
; #Upvalues:       12
; #Parameters:     0
; Is_vararg:       0
; Max Stack Size:  10

       0 [-]: GETIMPORT R0 1; var0 = 0x3D106989
       1 [-]: LOADK R1 K2  ; var1 = "SpawnLich"
       2 [-]: CALL R0 2 1  ; var0(var1)
       3 [-]: LOADNIL R0   ; var0 = nil
       4 [-]: GETUPVAL R2 0; var2 = upvalues[0]
       5 [-]: LENGTH R1 R2 ; var1 = #var2
       6 [-]: LOADN R2 0   ; var2 = 0
       7 [-]: JUMPIFNOTLT R2 R1 L0; goto L0 if var2 >= var316
       8 [-]: GETUPVAL R1 0; var1 = upvalues[0]
       9 [-]: GETTABLEN R0 R1 1; var0 = var1[1]
      10 [-]: JUMP L1      ; goto L1
L 0:  11 [-]: GETIMPORT R1 1; var1 = 0x3D106989
      12 [-]: LOADK R2 K3  ; var2 = "Active Liches table is empty - cannot obtain playerName"
      13 [-]: CALL R1 2 1  ; var1(var2)
L 1:  14 [-]: GETIMPORT R2 6; var2 = 0xBE190284
      15 [-]: GETUPVAL R4 2; var4 = upvalues[2]
      16 [-]: LOADN R5 0   ; var5 = 0
      17 [-]: NAMECALL R2 R2 K7; var3 = var2; var2 = var2[0x0EB34C69]
      18 [-]: CALL R2 4 2  ; var2 = var2(var3, var4, var5)
      19 [-]: ADDK R1 R2 K4; var1 = var2 + 1
      20 [-]: SETUPVAL R1 1; upvalues[1] = var1
      21 [-]: GETIMPORT R1 6; var1 = 0xBE190284
      22 [-]: GETUPVAL R3 2; var3 = upvalues[2]
      23 [-]: GETUPVAL R4 1; var4 = upvalues[1]
      24 [-]: NAMECALL R1 R1 K8; var2 = var1; var1 = var1[0x751F061D]
      25 [-]: CALL R1 4 1  ; var1(var2, var3, var4)
      26 [-]: GETUPVAL R2 1; var2 = upvalues[1]
      27 [-]: FASTCALL1 64 R2 L2; 
      28 [-]: GETIMPORT R1 10; var1 = 0x7B998233
      29 [-]: CALL R1 2 2  ; var1 = var1(var2)
L 2:  30 [-]: JUMPIFNOT R1 L3; goto L3 if not var1
      31 [-]: GETIMPORT R1 1; var1 = 0x3D106989
      32 [-]: LOADK R2 K11 ; var2 = "'roomIdx' for Lich assassinate room was nil!"
      33 [-]: CALL R1 2 1  ; var1(var2)
L 3:  34 [-]: GETUPVAL R3 3; var3 = upvalues[3]
      35 [-]: GETUPVAL R4 1; var4 = upvalues[1]
      36 [-]: GETTABLE R2 R3 R4; var2 = var3[var4]
      37 [-]: FASTCALL1 64 R2 L4; 
      38 [-]: GETIMPORT R1 10; var1 = 0x7B998233
      39 [-]: CALL R1 2 2  ; var1 = var1(var2)
L 4:  40 [-]: JUMPIF R1 L12; goto L12 if var1
      41 [-]: GETUPVAL R2 1; var2 = upvalues[1]
      42 [-]: FASTCALL1 64 R2 L5; 
      43 [-]: GETIMPORT R1 10; var1 = 0x7B998233
      44 [-]: CALL R1 2 2  ; var1 = var1(var2)
L 5:  45 [-]: JUMPIF R1 L12; goto L12 if var1
      46 [-]: GETIMPORT R1 14; var1 = _T["NemesisManifestedEnemy"]
      47 [-]: JUMPIFNOT R1 L11; goto L11 if not var1
      48 [-]: GETUPVAL R2 5; var2 = upvalues[5]
      49 [-]: GETTABLEKS R1 R2 K15; var1 = var2[0x21E6F9C3]
      50 [-]: GETIMPORT R2 17; var2 = 0x88EFC25E
      51 [-]: GETIMPORT R3 19; var3 = _T["NemesisManifestedEnemy"]["mAgent"]
      52 [-]: CALL R2 2 2  ; var2 = var2(var3)
      53 [-]: GETUPVAL R4 6; var4 = upvalues[6]
      54 [-]: GETUPVAL R5 1; var5 = upvalues[1]
      55 [-]: GETTABLE R3 R4 R5; var3 = var4[var5]
      56 [-]: LOADNIL R4   ; var4 = nil
      57 [-]: GETIMPORT R5 21; var5 = _T["NemesisManifestedEnemy"]["mLevel"]
      58 [-]: LOADNIL R6   ; var6 = nil
      59 [-]: LOADNIL R7   ; var7 = nil
      60 [-]: LOADNIL R8   ; var8 = nil
      61 [-]: LOADB R9 1   ; var9 = true
      62 [-]: CALL R1 9 2  ; var1 = var1(var2, var3, var4, var5, var6, var7, var8, var9)
      63 [-]: SETUPVAL R1 4; upvalues[1] = var4
      64 [-]: GETUPVAL R1 4; var1 = upvalues[4]
      65 [-]: NAMECALL R1 R1 K22; var2 = var1; var1 = var1[0xBB610E5B]
      66 [-]: CALL R1 2 2  ; var1 = var1(var2)
      67 [-]: SETUPVAL R1 7; upvalues[1] = var7
      68 [-]: GETUPVAL R1 7; var1 = upvalues[7]
      69 [-]: NAMECALL R1 R1 K23; var2 = var1; var1 = var1[0xDE321E6F]
      70 [-]: CALL R1 2 2  ; var1 = var1(var2)
      71 [-]: LOADN R3 0   ; var3 = 0
      72 [-]: NAMECALL R1 R1 K24; var2 = var1; var1 = var1[0x881B6B90]
      73 [-]: CALL R1 3 2  ; var1 = var1(var2, var3)
      74 [-]: LOADN R2 1   ; var2 = 1
      75 [-]: FASTCALL1 64 R1 L6; 
      76 [-]: MOVE R4 R1   ; var4 = var1
      77 [-]: GETIMPORT R3 10; var3 = 0x7B998233
      78 [-]: CALL R3 2 2  ; var3 = var3(var4)
L 6:  79 [-]: JUMPIF R3 L10; goto L10 if var3
      80 [-]: NAMECALL R3 R1 K25; var4 = var1; var3 = var1[0xD51D5B66]
      81 [-]: CALL R3 2 2  ; var3 = var3(var4)
      82 [-]: LOADN R6 1   ; var6 = 1
      83 [-]: GETIMPORT R7 27; var7 = 0xB54C8B65
      84 [-]: LENGTH R4 R7 ; var4 = #var7
      85 [-]: LOADN R5 1   ; var5 = 1
      86 [-]: FORNPREP R4 L10; nforprep start - [escape at L10] -- var4 = iterator
L 7:  87 [-]: GETIMPORT R8 27; var8 = 0xB54C8B65
      88 [-]: GETTABLE R7 R8 R6; var7 = var8[var6]
      89 [-]: JUMPIFNOTEQ R7 R3 L9; goto L9 if var7 ~= var1902881
      90 [-]: GETIMPORT R9 29; var9 = 0x450A8592
      91 [-]: GETTABLE R8 R9 R6; var8 = var9[var6]
      92 [-]: FASTCALL1 64 R8 L8; 
      93 [-]: GETIMPORT R7 10; var7 = 0x7B998233
      94 [-]: CALL R7 2 2  ; var7 = var7(var8)
L 8:  95 [-]: JUMPIF R7 L10; goto L10 if var7
      96 [-]: MOVE R2 R6   ; var2 = var6
      97 [-]: JUMP L10     ; goto L10
L 9:  98 [-]: FORNLOOP R4 L7; nforloop end - iterate + goto L7
L10:  99 [-]: GETUPVAL R3 7; var3 = upvalues[7]
     100 [-]: GETIMPORT R6 29; var6 = 0x450A8592
     101 [-]: GETTABLE R5 R6 R2; var5 = var6[var2]
     102 [-]: LOADB R6 0   ; var6 = false
     103 [-]: LOADN R7 3   ; var7 = 3
     104 [-]: LOADN R8 2   ; var8 = 2
     105 [-]: LOADB R9 1   ; var9 = true
     106 [-]: NAMECALL R3 R3 K30; var4 = var3; var3 = var3[0x5D985C7E]
     107 [-]: CALL R3 7 1  ; var3(var4, var5, var6, var7, var8, var9)
     108 [-]: GETUPVAL R3 7; var3 = upvalues[7]
     109 [-]: GETIMPORT R6 6; var6 = 0xBE190284
     110 [-]: NAMECALL R6 R6 K31; var7 = var6; var6 = var6[0xB0B3152A]
     111 [-]: CALL R6 2 2  ; var6 = var6(var7)
     112 [-]: GETTABLEKS R5 R6 K32; var5 = var6["mPlayerName"]
     113 [-]: NAMECALL R3 R3 K33; var4 = var3; var3 = var3[0x8943FAB4]
     114 [-]: CALL R3 3 1  ; var3(var4, var5)
     115 [-]: JUMP L13     ; goto L13
L11: 116 [-]: GETIMPORT R1 1; var1 = 0x3D106989
     117 [-]: LOADK R2 K34 ; var2 = "_T.NemesisManifestedEnemy was empty!"
     118 [-]: CALL R1 2 1  ; var1(var2)
     119 [-]: JUMP L13     ; goto L13
L12: 120 [-]: GETIMPORT R1 1; var1 = 0x3D106989
     121 [-]: LOADK R2 K35 ; var2 = "Reference to Lich's arena room doors was nil!"
     122 [-]: CALL R1 2 1  ; var1(var2)
L13: 123 [-]: GETIMPORT R1 36; var1 = _T
     124 [-]: LOADNIL R2   ; var2 = nil
     125 [-]: SETTABLEKS R2 R1 K13; var2["NemesisManifestedEnemy"] = var1
     126 [-]: FASTCALL1 64 R0 L14; 
     127 [-]: MOVE R2 R0   ; var2 = var0
     128 [-]: GETIMPORT R1 10; var1 = 0x7B998233
     129 [-]: CALL R1 2 2  ; var1 = var1(var2)
L14: 130 [-]: JUMPIF R1 L15; goto L15 if var1
     131 [-]: GETIMPORT R1 6; var1 = 0xBE190284
     132 [-]: GETIMPORT R3 38; var3 = 0x0469F296
     133 [-]: LOADK R5 K39 ; var5 = "RequestNemesis_"
     134 [-]: MOVE R6 R0   ; var6 = var0
     135 [-]: CONCAT R4 R5 R6; var4 = var5 .. var6
     136 [-]: CALL R3 2 0  ; var3, ... = var3(var4)
     137 [-]: NAMECALL R1 R1 K40; var2 = var1; var1 = var1[0xB9BFD47C]
     138 [-]: CALL R1 0 1  ; var1(var2, ...)
L15: 139 [-]: GETUPVAL R2 7; var2 = upvalues[7]
     140 [-]: FASTCALL1 64 R2 L16; 
     141 [-]: GETIMPORT R1 10; var1 = 0x7B998233
     142 [-]: CALL R1 2 2  ; var1 = var1(var2)
L16: 143 [-]: JUMPIF R1 L17; goto L17 if var1
     144 [-]: GETUPVAL R1 7; var1 = upvalues[7]
     145 [-]: NAMECALL R1 R1 K41; var2 = var1; var1 = var1[0x1AC1655C]
     146 [-]: CALL R1 2 2  ; var1 = var1(var2)
     147 [-]: SETUPVAL R1 8; upvalues[1] = var8
     148 [-]: GETUPVAL R1 8; var1 = upvalues[8]
     149 [-]: GETUPVAL R3 9; var3 = upvalues[9]
     150 [-]: LOADN R4 25  ; var4 = 25
     151 [-]: LOADN R5 6   ; var5 = 6
     152 [-]: LOADN R6 0   ; var6 = 0
     153 [-]: NAMECALL R1 R1 K42; var2 = var1; var1 = var1[0xA383DE31]
     154 [-]: CALL R1 6 1  ; var1(var2, var3, var4, var5, var6)
     155 [-]: GETUPVAL R1 8; var1 = upvalues[8]
     156 [-]: GETUPVAL R3 9; var3 = upvalues[9]
     157 [-]: LOADN R4 25  ; var4 = 25
     158 [-]: LOADN R5 6   ; var5 = 6
     159 [-]: LOADN R6 0   ; var6 = 0
     160 [-]: NAMECALL R1 R1 K43; var2 = var1; var1 = var1[0x4CB29D1C]
     161 [-]: CALL R1 6 1  ; var1(var2, var3, var4, var5, var6)
     162 [-]: GETUPVAL R1 8; var1 = upvalues[8]
     163 [-]: GETUPVAL R3 10; var3 = upvalues[10]
     164 [-]: LOADN R4 25  ; var4 = 25
     165 [-]: LOADN R5 6   ; var5 = 6
     166 [-]: LOADN R6 0   ; var6 = 0
     167 [-]: NAMECALL R1 R1 K42; var2 = var1; var1 = var1[0xA383DE31]
     168 [-]: CALL R1 6 1  ; var1(var2, var3, var4, var5, var6)
     169 [-]: GETUPVAL R1 8; var1 = upvalues[8]
     170 [-]: GETUPVAL R3 10; var3 = upvalues[10]
     171 [-]: LOADN R4 25  ; var4 = 25
     172 [-]: LOADN R5 6   ; var5 = 6
     173 [-]: LOADN R6 0   ; var6 = 0
     174 [-]: NAMECALL R1 R1 K43; var2 = var1; var1 = var1[0x4CB29D1C]
     175 [-]: CALL R1 6 1  ; var1(var2, var3, var4, var5, var6)
     176 [-]: GETIMPORT R1 6; var1 = 0xBE190284
     177 [-]: GETIMPORT R3 38; var3 = 0x0469F296
     178 [-]: LOADK R4 K44 ; var4 = "NemesisIntroCin"
     179 [-]: CALL R3 2 2  ; var3 = var3(var4)
     180 [-]: LOADN R4 0   ; var4 = 0
     181 [-]: NAMECALL R1 R1 K40; var2 = var1; var1 = var1[0xB9BFD47C]
     182 [-]: CALL R1 4 1  ; var1(var2, var3, var4)
L17: 183 [-]: GETUPVAL R2 4; var2 = upvalues[4]
     184 [-]: FASTCALL1 64 R2 L18; 
     185 [-]: GETIMPORT R1 10; var1 = 0x7B998233
     186 [-]: CALL R1 2 2  ; var1 = var1(var2)
L18: 187 [-]: JUMPIF R1 L19; goto L19 if var1
     188 [-]: GETIMPORT R1 1; var1 = 0x3D106989
     189 [-]: LOADK R2 K45 ; var2 = "Created, waiting for transmission"
     190 [-]: CALL R1 2 1  ; var1(var2)
     191 [-]: GETUPVAL R2 11; var2 = upvalues[11]
     192 [-]: GETTABLEKS R1 R2 K46; var1 = var2[0x48EA9DE9]
     193 [-]: GETIMPORT R2 38; var2 = 0x0469F296
     194 [-]: LOADK R3 K47 ; var3 = "RJAssEnterShip"
     195 [-]: CALL R2 2 0  ; var2, ... = var2(var3)
     196 [-]: CALL R1 0 1  ; var1(var2, ...)
L19: 197 [-]: RETURN R0 0  ; 


; Name:            
; Defined at line: 450
; #Upvalues:       4
; #Parameters:     1
; Is_vararg:       0
; Max Stack Size:  12

       0 [-]: NAMECALL R1 R0 K0; var2 = var0; var1 = var0[0xCB3851B8]
       1 [-]: CALL R1 2 2  ; var1 = var1(var2)
       2 [-]: NAMECALL R3 R0 K1; var4 = var0; var3 = var0[0xD1586535]
       3 [-]: CALL R3 2 2  ; var3 = var3(var4)
       4 [-]: GETIMPORT R4 3; var4 = 0x492C7F2A
       5 [-]: GETIMPORT R5 5; var5 = 0xA421AF95
       6 [-]: LOADN R6 0   ; var6 = 0
       7 [-]: LOADK R7 K6  ; var7 = -0.60000002384185791
       8 [-]: LOADN R8 3   ; var8 = 3
       9 [-]: CALL R5 4 2  ; var5 = var5(var6, var7, var8)
      10 [-]: MOVE R6 R1   ; var6 = var1
      11 [-]: CALL R4 3 2  ; var4 = var4(var5, var6)
      12 [-]: ADD R2 R3 R4 ; var2 = var3 + var4
      13 [-]: GETUPVAL R3 0; var3 = upvalues[0]
      14 [-]: MOVE R5 R2   ; var5 = var2
      15 [-]: MOVE R6 R1   ; var6 = var1
      16 [-]: NAMECALL R3 R3 K7; var4 = var3; var3 = var3[0x589EF1C1]
      17 [-]: CALL R3 4 1  ; var3(var4, var5, var6)
      18 [-]: GETUPVAL R3 0; var3 = upvalues[0]
      19 [-]: NAMECALL R3 R3 K8; var4 = var3; var3 = var3[0x020D4331]
      20 [-]: CALL R3 2 2  ; var3 = var3(var4)
      21 [-]: MOVE R5 R1   ; var5 = var1
      22 [-]: NAMECALL R3 R3 K9; var4 = var3; var3 = var3[0x553549E8]
      23 [-]: CALL R3 3 1  ; var3(var4, var5)
      24 [-]: LOADK R5 K10 ; var5 = "StartPlaying"
      25 [-]: NAMECALL R3 R0 K11; var4 = var0; var3 = var0[0x8EB2112D]
      26 [-]: CALL R3 3 1  ; var3(var4, var5)
      27 [-]: GETIMPORT R3 13; var3 = 0xCBD666E1
      28 [-]: LOADN R4 0   ; var4 = 0
      29 [-]: CALL R3 2 1  ; var3(var4)
      30 [-]: LOADB R3 0   ; var3 = false
L 0:  31 [-]: GETUPVAL R5 0; var5 = upvalues[0]
      32 [-]: FASTCALL1 64 R5 L1; 
      33 [-]: GETIMPORT R4 15; var4 = 0x7B998233
      34 [-]: CALL R4 2 2  ; var4 = var4(var5)
L 1:  35 [-]: JUMPIF R4 L5 ; goto L5 if var4
      36 [-]: GETIMPORT R4 17; var4 = 0x89326C93
      37 [-]: NAMECALL R4 R4 K18; var5 = var4; var4 = var4[0xDD25E9D1]
      38 [-]: CALL R4 2 2  ; var4 = var4(var5)
      39 [-]: JUMPIFNOTEQ R4 R0 L5; goto L5 if var4 ~= var1084
      40 [-]: GETUPVAL R4 0; var4 = upvalues[0]
      41 [-]: MOVE R6 R2   ; var6 = var2
      42 [-]: MOVE R7 R1   ; var7 = var1
      43 [-]: NAMECALL R4 R4 K7; var5 = var4; var4 = var4[0x589EF1C1]
      44 [-]: CALL R4 4 1  ; var4(var5, var6, var7)
      45 [-]: GETUPVAL R4 0; var4 = upvalues[0]
      46 [-]: NAMECALL R4 R4 K8; var5 = var4; var4 = var4[0x020D4331]
      47 [-]: CALL R4 2 2  ; var4 = var4(var5)
      48 [-]: MOVE R6 R1   ; var6 = var1
      49 [-]: NAMECALL R4 R4 K9; var5 = var4; var4 = var4[0x553549E8]
      50 [-]: CALL R4 3 1  ; var4(var5, var6)
      51 [-]: GETIMPORT R4 13; var4 = 0xCBD666E1
      52 [-]: LOADN R5 0   ; var5 = 0
      53 [-]: CALL R4 2 1  ; var4(var5)
      54 [-]: GETIMPORT R5 21; var5 = _T["curTransmission"]
      55 [-]: FASTCALL1 64 R5 L2; 
      56 [-]: GETIMPORT R4 15; var4 = 0x7B998233
      57 [-]: CALL R4 2 2  ; var4 = var4(var5)
L 2:  58 [-]: JUMPIF R4 L3 ; goto L3 if var4
      59 [-]: GETIMPORT R4 21; var4 = _T["curTransmission"]
      60 [-]: NAMECALL R4 R4 K22; var5 = var4; var4 = var4[0x22DA1852]
      61 [-]: CALL R4 2 2  ; var4 = var4(var5)
      62 [-]: GETUPVAL R5 1; var5 = upvalues[1]
      63 [-]: JUMPIFNOTEQ R4 R5 L3; goto L3 if var4 ~= var66310
      64 [-]: LOADB R3 1   ; var3 = true
      65 [-]: JUMP L4      ; goto L4
L 3:  66 [-]: JUMPIF R3 L5 ; goto L5 if var3
L 4:  67 [-]: JUMPBACK L0  ; goto L0
L 5:  68 [-]: FASTCALL1 64 R0 L6; 
      69 [-]: MOVE R5 R0   ; var5 = var0
      70 [-]: GETIMPORT R4 15; var4 = 0x7B998233
      71 [-]: CALL R4 2 2  ; var4 = var4(var5)
L 6:  72 [-]: JUMPIF R4 L13; goto L13 if var4
      73 [-]: NAMECALL R4 R0 K23; var5 = var0; var4 = var0[0x1C84839C]
      74 [-]: CALL R4 2 2  ; var4 = var4(var5)
      75 [-]: JUMPIFNOT R4 L13; goto L13 if not var4
      76 [-]: GETUPVAL R5 0; var5 = upvalues[0]
      77 [-]: FASTCALL1 64 R5 L7; 
      78 [-]: GETIMPORT R4 15; var4 = 0x7B998233
      79 [-]: CALL R4 2 2  ; var4 = var4(var5)
L 7:  80 [-]: JUMPIF R4 L9 ; goto L9 if var4
      81 [-]: GETIMPORT R5 25; var5 = 0x12C26950
      82 [-]: FASTCALL1 64 R5 L8; 
      83 [-]: GETIMPORT R4 15; var4 = 0x7B998233
      84 [-]: CALL R4 2 2  ; var4 = var4(var5)
L 8:  85 [-]: JUMPIF R4 L9 ; goto L9 if var4
      86 [-]: GETUPVAL R4 0; var4 = upvalues[0]
      87 [-]: GETIMPORT R6 25; var6 = 0x12C26950
      88 [-]: LOADB R7 0   ; var7 = false
      89 [-]: LOADN R8 1   ; var8 = 1
      90 [-]: LOADB R9 1   ; var9 = true
      91 [-]: NAMECALL R4 R4 K26; var5 = var4; var4 = var4[0x659D451F]
      92 [-]: CALL R4 6 1  ; var4(var5, var6, var7, var8, var9)
L 9:  93 [-]: GETIMPORT R4 13; var4 = 0xCBD666E1
      94 [-]: LOADN R6 0   ; var6 = 0
      95 [-]: GETIMPORT R8 28; var8 = 0xA4420836
      96 [-]: FASTCALL2K 19 R8 K29 L10; 
      97 [-]: LOADK R9 K29 ; var9 = 5
      98 [-]: GETIMPORT R7 32; var7 = 0x5BCED4C4[0xAC1B386A]
      99 [-]: CALL R7 3 2  ; var7 = var7(var8, var9)
L10: 100 [-]: FASTCALL2 18 R6 R7 L11; 
     101 [-]: GETIMPORT R5 34; var5 = 0x5BCED4C4[0xB62ECFE0]
     102 [-]: CALL R5 3 2  ; var5 = var5(var6, var7)
L11: 103 [-]: CALL R4 2 1  ; var4(var5)
     104 [-]: FASTCALL1 64 R0 L12; 
     105 [-]: MOVE R5 R0   ; var5 = var0
     106 [-]: GETIMPORT R4 15; var4 = 0x7B998233
     107 [-]: CALL R4 2 2  ; var4 = var4(var5)
L12: 108 [-]: JUMPIF R4 L13; goto L13 if var4
     109 [-]: NAMECALL R4 R0 K23; var5 = var0; var4 = var0[0x1C84839C]
     110 [-]: CALL R4 2 2  ; var4 = var4(var5)
     111 [-]: JUMPIFNOT R4 L13; goto L13 if not var4
     112 [-]: NAMECALL R4 R0 K35; var5 = var0; var4 = var0[0x1A348FB5]
     113 [-]: CALL R4 2 1  ; var4(var5)
L13: 114 [-]: GETIMPORT R4 13; var4 = 0xCBD666E1
     115 [-]: LOADK R5 K36 ; var5 = 0.5
     116 [-]: CALL R4 2 1  ; var4(var5)
     117 [-]: GETIMPORT R4 17; var4 = 0x89326C93
     118 [-]: NAMECALL R4 R4 K37; var5 = var4; var4 = var4[0x29EF273D]
     119 [-]: CALL R4 2 2  ; var4 = var4(var5)
     120 [-]: NAMECALL R4 R4 K38; var5 = var4; var4 = var4[0x66905CB0]
     121 [-]: CALL R4 2 2  ; var4 = var4(var5)
     122 [-]: FASTCALL1 64 R4 L14; 
     123 [-]: MOVE R6 R4   ; var6 = var4
     124 [-]: GETIMPORT R5 15; var5 = 0x7B998233
     125 [-]: CALL R5 2 2  ; var5 = var5(var6)
L14: 126 [-]: JUMPIF R5 L15; goto L15 if var5
     127 [-]: LOADB R7 0   ; var7 = false
     128 [-]: NAMECALL R5 R4 K39; var6 = var4; var5 = var4[0xB8B90F91]
     129 [-]: CALL R5 3 1  ; var5(var6, var7)
L15: 130 [-]: GETUPVAL R6 0; var6 = upvalues[0]
     131 [-]: FASTCALL1 64 R6 L16; 
     132 [-]: GETIMPORT R5 15; var5 = 0x7B998233
     133 [-]: CALL R5 2 2  ; var5 = var5(var6)
L16: 134 [-]: JUMPIF R5 L17; goto L17 if var5
     135 [-]: GETUPVAL R5 0; var5 = upvalues[0]
     136 [-]: LOADNIL R7   ; var7 = nil
     137 [-]: LOADB R8 0   ; var8 = false
     138 [-]: LOADN R9 3   ; var9 = 3
     139 [-]: LOADN R10 1  ; var10 = 1
     140 [-]: LOADB R11 0  ; var11 = false
     141 [-]: NAMECALL R5 R5 K40; var6 = var5; var5 = var5[0x5D985C7E]
     142 [-]: CALL R5 7 1  ; var5(var6, var7, var8, var9, var10, var11)
L17: 143 [-]: GETUPVAL R6 2; var6 = upvalues[2]
     144 [-]: FASTCALL1 64 R6 L18; 
     145 [-]: GETIMPORT R5 15; var5 = 0x7B998233
     146 [-]: CALL R5 2 2  ; var5 = var5(var6)
L18: 147 [-]: JUMPIF R5 L19; goto L19 if var5
     148 [-]: GETUPVAL R5 2; var5 = upvalues[2]
     149 [-]: GETUPVAL R7 1; var7 = upvalues[1]
     150 [-]: NAMECALL R5 R5 K41; var6 = var5; var5 = var5[0x8E3E343E]
     151 [-]: CALL R5 3 1  ; var5(var6, var7)
     152 [-]: GETUPVAL R5 2; var5 = upvalues[2]
     153 [-]: GETUPVAL R7 1; var7 = upvalues[1]
     154 [-]: NAMECALL R5 R5 K42; var6 = var5; var5 = var5[0x9326CA4B]
     155 [-]: CALL R5 3 1  ; var5(var6, var7)
L19: 156 [-]: GETIMPORT R5 44; var5 = 0xBE190284
     157 [-]: GETIMPORT R7 46; var7 = 0x0469F296
     158 [-]: LOADK R8 K47 ; var8 = "NemesisIntroCin"
     159 [-]: CALL R7 2 2  ; var7 = var7(var8)
     160 [-]: LOADN R8 1   ; var8 = 1
     161 [-]: NAMECALL R5 R5 K48; var6 = var5; var5 = var5[0x751F061D]
     162 [-]: CALL R5 4 1  ; var5(var6, var7, var8)
     163 [-]: GETUPVAL R5 3; var5 = upvalues[3]
     164 [-]: CALL R5 1 1  ; var5()
     165 [-]: RETURN R0 0  ; 


; Name:            
; Defined at line: 498
; #Upvalues:       39
; #Parameters:     1
; Is_vararg:       0
; Max Stack Size:  27

       0 [-]: GETIMPORT R1 1; var1 = 0x3D106989
       1 [-]: LOADK R2 K2  ; var2 = "Starting"
       2 [-]: CALL R1 2 1  ; var1(var2)
       3 [-]: GETIMPORT R1 4; var1 = _T
       4 [-]: GETIMPORT R2 6; var2 = 0x0469F296
       5 [-]: LOADK R3 K7  ; var3 = "LICH_ASSASSINATE"
       6 [-]: CALL R2 2 2  ; var2 = var2(var3)
       7 [-]: SETTABLEKS R2 R1 K8; var2["CapitalShipMission"] = var1
       8 [-]: NAMECALL R1 R0 K9; var2 = var0; var1 = var0[0xED324116]
       9 [-]: CALL R1 2 2  ; var1 = var1(var2)
      10 [-]: SETUPVAL R1 0; upvalues[1] = var0
      11 [-]: GETUPVAL R1 0; var1 = upvalues[0]
      12 [-]: NAMECALL R1 R1 K10; var2 = var1; var1 = var1[0x50A76235]
      13 [-]: CALL R1 2 2  ; var1 = var1(var2)
      14 [-]: JUMPIF R1 L1 ; goto L1 if var1
      15 [-]: GETIMPORT R1 12; var1 = _T["faction"]
      16 [-]: GETUPVAL R2 1; var2 = upvalues[1]
      17 [-]: JUMPIFNOTEQ R1 R2 L0; goto L0 if var1 ~= var131644
      18 [-]: GETUPVAL R2 2; var2 = upvalues[2]
      19 [-]: GETTABLEKS R1 R2 K13; var1 = var2[0xA1DF01D6]
      20 [-]: LOADK R2 K14 ; var2 = "/Lotus/Language/Objectives/GenericAssassinate"
      21 [-]: CALL R1 2 1  ; var1(var2)
      22 [-]: JUMP L1      ; goto L1
L 0:  23 [-]: GETUPVAL R2 2; var2 = upvalues[2]
      24 [-]: GETTABLEKS R1 R2 K13; var1 = var2[0xA1DF01D6]
      25 [-]: LOADK R2 K15 ; var2 = "/Lotus/Language/CorpusRailjack/AssassinateLoc"
      26 [-]: CALL R1 2 1  ; var1(var2)
L 1:  27 [-]: NEWTABLE R1 0 1; var1 = {}
      28 [-]: GETIMPORT R3 17; var3 = 0x0CB1F7B7
      29 [-]: FASTCALL1 53 R3 L2; 
      30 [-]: GETIMPORT R2 19; var2 = unpack
      31 [-]: CALL R2 2 0  ; var2, ... = var2(var3)
L 2:  32 [-]: SETLIST R1 R2 -1 [1]; 
      33 [-]: SETUPVAL R1 3; upvalues[1] = var3
      34 [-]: GETUPVAL R2 3; var2 = upvalues[3]
      35 [-]: LENGTH R1 R2 ; var1 = #var2
      36 [-]: SETUPVAL R1 4; upvalues[1] = var4
L 3:  37 [-]: GETUPVAL R2 5; var2 = upvalues[5]
      38 [-]: FASTCALL1 64 R2 L4; 
      39 [-]: GETIMPORT R1 21; var1 = 0x7B998233
      40 [-]: CALL R1 2 2  ; var1 = var1(var2)
L 4:  41 [-]: JUMPIFNOT R1 L5; goto L5 if not var1
      42 [-]: GETIMPORT R1 23; var1 = 0xCBD666E1
      43 [-]: LOADN R2 0   ; var2 = 0
      44 [-]: CALL R1 2 1  ; var1(var2)
      45 [-]: GETUPVAL R2 6; var2 = upvalues[6]
      46 [-]: GETTABLEKS R1 R2 K24; var1 = var2[0xE4FA70DB]
      47 [-]: MOVE R2 R0   ; var2 = var0
      48 [-]: CALL R1 2 2  ; var1 = var1(var2)
      49 [-]: SETUPVAL R1 5; upvalues[1] = var5
      50 [-]: JUMPBACK L3  ; goto L3
L 5:  51 [-]: GETUPVAL R4 5; var4 = upvalues[5]
      52 [-]: FASTCALL1 64 R4 L6; 
      53 [-]: GETIMPORT R3 21; var3 = 0x7B998233
      54 [-]: CALL R3 2 2  ; var3 = var3(var4)
L 6:  55 [-]: NOT R2 R3    ; var2 = not var3
      56 [-]: FASTCALL1 1 R2 L7; 
      57 [-]: GETIMPORT R1 26; var1 = 0x60CCE7B4
      58 [-]: CALL R1 2 1  ; var1(var2)
L 7:  59 [-]: GETIMPORT R1 28; var1 = 0x89326C93
      60 [-]: NAMECALL R1 R1 K29; var2 = var1; var1 = var1[0x29EF273D]
      61 [-]: CALL R1 2 2  ; var1 = var1(var2)
      62 [-]: NAMECALL R1 R1 K30; var2 = var1; var1 = var1[0x66905CB0]
      63 [-]: CALL R1 2 2  ; var1 = var1(var2)
      64 [-]: GETUPVAL R3 6; var3 = upvalues[6]
      65 [-]: GETTABLEKS R2 R3 K31; var2 = var3[0x2DF8B2BA]
      66 [-]: GETIMPORT R3 6; var3 = 0x0469F296
      67 [-]: LOADK R4 K32 ; var4 = "BoardShipPosition"
      68 [-]: CALL R3 2 2  ; var3 = var3(var4)
      69 [-]: GETUPVAL R4 5; var4 = upvalues[5]
      70 [-]: CALL R2 3 2  ; var2 = var2(var3, var4)
      71 [-]: NAMECALL R2 R2 K33; var3 = var2; var2 = var2[0xD1586535]
      72 [-]: CALL R2 2 2  ; var2 = var2(var3)
      73 [-]: GETUPVAL R4 6; var4 = upvalues[6]
      74 [-]: GETTABLEKS R3 R4 K34; var3 = var4[0xDE6C4F3E]
      75 [-]: GETIMPORT R4 6; var4 = 0x0469F296
      76 [-]: LOADK R5 K35 ; var5 = "DoorHint"
      77 [-]: CALL R4 2 2  ; var4 = var4(var5)
      78 [-]: GETUPVAL R5 5; var5 = upvalues[5]
      79 [-]: CALL R3 3 2  ; var3 = var3(var4, var5)
      80 [-]: SETUPVAL R3 7; upvalues[3] = var7
      81 [-]: GETUPVAL R4 6; var4 = upvalues[6]
      82 [-]: GETTABLEKS R3 R4 K34; var3 = var4[0xDE6C4F3E]
      83 [-]: GETIMPORT R4 6; var4 = 0x0469F296
      84 [-]: LOADK R5 K36 ; var5 = "NemesisArena"
      85 [-]: CALL R4 2 2  ; var4 = var4(var5)
      86 [-]: GETUPVAL R5 5; var5 = upvalues[5]
      87 [-]: CALL R3 3 2  ; var3 = var3(var4, var5)
      88 [-]: SETUPVAL R3 8; upvalues[3] = var8
      89 [-]: GETUPVAL R4 6; var4 = upvalues[6]
      90 [-]: GETTABLEKS R3 R4 K34; var3 = var4[0xDE6C4F3E]
      91 [-]: GETIMPORT R4 6; var4 = 0x0469F296
      92 [-]: LOADK R5 K37 ; var5 = "NemesisDoorHint"
      93 [-]: CALL R4 2 2  ; var4 = var4(var5)
      94 [-]: GETUPVAL R5 5; var5 = upvalues[5]
      95 [-]: CALL R3 3 2  ; var3 = var3(var4, var5)
      96 [-]: SETUPVAL R3 9; upvalues[3] = var9
      97 [-]: NEWTABLE R3 0 0; var3 = {}
      98 [-]: GETIMPORT R4 39; var4 = 0xC8802016
      99 [-]: GETUPVAL R5 8; var5 = upvalues[8]
     100 [-]: CALL R4 2 4  ; var4, var5, var6 = var4(var5)
     101 [-]: FORGPREP_INEXT R4 L9; 
L 8: 102 [-]: MOVE R11 R2  ; var11 = var2
     103 [-]: NAMECALL R12 R8 K33; var13 = var8; var12 = var8[0xD1586535]
     104 [-]: CALL R12 2 0 ; var12, ... = var12(var13)
     105 [-]: NAMECALL R9 R1 K40; var10 = var1; var9 = var1[0x87358EF0]
     106 [-]: CALL R9 0 2  ; var9 = var9(var10, ...)
     107 [-]: SETTABLE R9 R3 R8; var9[var3] = var8
L 9: 108 [-]: FORGLOOP R4 L8 2 [inext]; 
     109 [-]: GETIMPORT R4 39; var4 = 0xC8802016
     110 [-]: GETUPVAL R5 9; var5 = upvalues[9]
     111 [-]: CALL R4 2 4  ; var4, var5, var6 = var4(var5)
     112 [-]: FORGPREP_INEXT R4 L11; 
L10: 113 [-]: MOVE R11 R2  ; var11 = var2
     114 [-]: NAMECALL R12 R8 K33; var13 = var8; var12 = var8[0xD1586535]
     115 [-]: CALL R12 2 0 ; var12, ... = var12(var13)
     116 [-]: NAMECALL R9 R1 K40; var10 = var1; var9 = var1[0x87358EF0]
     117 [-]: CALL R9 0 2  ; var9 = var9(var10, ...)
     118 [-]: SETTABLE R9 R3 R8; var9[var3] = var8
L11: 119 [-]: FORGLOOP R4 L10 2 [inext]; 
     120 [-]: GETIMPORT R4 43; var4 = 0x33BDD652[0xF21B1D8E]
     121 [-]: GETUPVAL R5 8; var5 = upvalues[8]
     122 [-]: NEWCLOSURE R6 P0; 
     123 [-]: CAPTURE REF R3; 
     124 [-]: CALL R4 3 1  ; var4(var5, var6)
     125 [-]: GETIMPORT R4 43; var4 = 0x33BDD652[0xF21B1D8E]
     126 [-]: GETUPVAL R5 9; var5 = upvalues[9]
     127 [-]: NEWCLOSURE R6 P1; 
     128 [-]: CAPTURE REF R3; 
     129 [-]: CALL R4 3 1  ; var4(var5, var6)
     130 [-]: GETUPVAL R5 6; var5 = upvalues[6]
     131 [-]: GETTABLEKS R4 R5 K44; var4 = var5[0x2F6F2966]
     132 [-]: GETIMPORT R5 46; var5 = 0x7ED0A956
     133 [-]: LOADK R6 K47 ; var6 = "/Lotus/Types/Game/CrewShip/ExitShip"
     134 [-]: CALL R5 2 2  ; var5 = var5(var6)
     135 [-]: GETUPVAL R6 5; var6 = upvalues[5]
     136 [-]: CALL R4 3 2  ; var4 = var4(var5, var6)
     137 [-]: GETIMPORT R5 6; var5 = 0x0469F296
     138 [-]: LOADK R6 K48 ; var6 = "Exit"
     139 [-]: CALL R5 2 2  ; var5 = var5(var6)
     140 [-]: LENGTH R8 R4 ; var8 = #var4
     141 [-]: LOADN R6 1   ; var6 = 1
     142 [-]: LOADN R7 -1  ; var7 = -1
     143 [-]: FORNPREP R6 L15; nforprep start - [escape at L15] -- var6 = iterator
L12: 144 [-]: GETTABLE R9 R4 R8; var9 = var4[var8]
     145 [-]: NAMECALL R9 R9 K49; var10 = var9; var9 = var9[0xE79E7EF4]
     146 [-]: CALL R9 2 2  ; var9 = var9(var10)
     147 [-]: GETTABLE R10 R4 R8; var10 = var4[var8]
     148 [-]: NAMECALL R10 R10 K50; var11 = var10; var10 = var10[0xF4E253B6]
     149 [-]: CALL R10 2 1 ; var10(var11)
     150 [-]: FASTCALL1 64 R9 L13; 
     151 [-]: MOVE R11 R9  ; var11 = var9
     152 [-]: GETIMPORT R10 21; var10 = 0x7B998233
     153 [-]: CALL R10 2 2 ; var10 = var10(var11)
L13: 154 [-]: JUMPIF R10 L14; goto L14 if var10
     155 [-]: NAMECALL R10 R9 K51; var11 = var9; var10 = var9[0x22DA1852]
     156 [-]: CALL R10 2 2 ; var10 = var10(var11)
     157 [-]: JUMPIFEQ R10 R5 L14; goto L14 if var10 == var3476001
     158 [-]: GETIMPORT R10 53; var10 = 0x33BDD652[0x9C1F3B5A]
     159 [-]: MOVE R11 R4  ; var11 = var4
     160 [-]: MOVE R12 R8  ; var12 = var8
     161 [-]: CALL R10 3 1 ; var10(var11, var12)
L14: 162 [-]: FORNLOOP R6 L12; nforloop end - iterate + goto L12
L15: 163 [-]: GETIMPORT R6 39; var6 = 0xC8802016
     164 [-]: GETUPVAL R7 8; var7 = upvalues[8]
     165 [-]: CALL R6 2 4  ; var6, var7, var8 = var6(var7)
     166 [-]: FORGPREP_INEXT R6 L19; 
L16: 167 [-]: NEWTABLE R3 0 0; var3 = {}
     168 [-]: GETIMPORT R11 39; var11 = 0xC8802016
     169 [-]: MOVE R12 R4  ; var12 = var4
     170 [-]: CALL R11 2 4 ; var11, var12, var13 = var11(var12)
     171 [-]: FORGPREP_INEXT R11 L18; 
L17: 172 [-]: NAMECALL R18 R15 K33; var19 = var15; var18 = var15[0xD1586535]
     173 [-]: CALL R18 2 2 ; var18 = var18(var19)
     174 [-]: NAMECALL R19 R10 K33; var20 = var10; var19 = var10[0xD1586535]
     175 [-]: CALL R19 2 0 ; var19, ... = var19(var20)
     176 [-]: NAMECALL R16 R1 K40; var17 = var1; var16 = var1[0x87358EF0]
     177 [-]: CALL R16 0 2 ; var16 = var16(var17, ...)
     178 [-]: SETTABLE R16 R3 R15; var16[var3] = var15
L18: 179 [-]: FORGLOOP R11 L17 2 [inext]; 
     180 [-]: GETIMPORT R11 43; var11 = 0x33BDD652[0xF21B1D8E]
     181 [-]: MOVE R12 R4  ; var12 = var4
     182 [-]: NEWCLOSURE R13 P2; 
     183 [-]: CAPTURE REF R3; 
     184 [-]: CALL R11 3 1 ; var11(var12, var13)
     185 [-]: GETIMPORT R11 1; var11 = 0x3D106989
     186 [-]: LOADK R13 K54; var13 = "RoomIdx = "
     187 [-]: MOVE R14 R9  ; var14 = var9
     188 [-]: LOADK R15 K55; var15 = " distance to exit: "
     189 [-]: GETTABLEN R18 R4 1; var18 = var4[1]
     190 [-]: NAMECALL R18 R18 K33; var19 = var18; var18 = var18[0xD1586535]
     191 [-]: CALL R18 2 2 ; var18 = var18(var19)
     192 [-]: NAMECALL R19 R10 K33; var20 = var10; var19 = var10[0xD1586535]
     193 [-]: CALL R19 2 0 ; var19, ... = var19(var20)
     194 [-]: NAMECALL R16 R1 K40; var17 = var1; var16 = var1[0x87358EF0]
     195 [-]: CALL R16 0 2 ; var16 = var16(var17, ...)
     196 [-]: CONCAT R12 R13 R16; var12 = var13 .. var16
     197 [-]: CALL R11 2 1 ; var11(var12)
     198 [-]: GETUPVAL R11 10; var11 = upvalues[10]
     199 [-]: GETTABLEN R12 R4 1; var12 = var4[1]
     200 [-]: SETTABLE R12 R11 R9; var12[var11] = var9
     201 [-]: GETIMPORT R11 53; var11 = 0x33BDD652[0x9C1F3B5A]
     202 [-]: MOVE R12 R4  ; var12 = var4
     203 [-]: LOADN R13 1  ; var13 = 1
     204 [-]: CALL R11 3 1 ; var11(var12, var13)
L19: 205 [-]: FORGLOOP R6 L16 2 [inext]; 
     206 [-]: LOADNIL R3   ; var3 = nil
     207 [-]: GETIMPORT R7 57; var7 = 0xBE190284
     208 [-]: NAMECALL R7 R7 K58; var8 = var7; var7 = var7[0xEF893AEC]
     209 [-]: CALL R7 2 2  ; var7 = var7(var8)
     210 [-]: GETTABLEKS R6 R7 K11; var6 = var7["faction"]
     211 [-]: LOADN R7 0   ; var7 = 0
     212 [-]: JUMPIFNOTEQ R6 R7 L20; goto L20 if var6 ~= var395297
     213 [-]: GETIMPORT R8 6; var8 = 0x0469F296
     214 [-]: LOADK R9 K59 ; var9 = "DisableRailjack"
     215 [-]: CALL R8 2 2  ; var8 = var8(var9)
     216 [-]: LOADB R9 0   ; var9 = false
     217 [-]: NAMECALL R6 R0 K60; var7 = var0; var6 = var0[0xD5F7912B]
     218 [-]: CALL R6 4 1  ; var6(var7, var8, var9)
L20: 219 [-]: GETIMPORT R6 57; var6 = 0xBE190284
     220 [-]: GETUPVAL R8 11; var8 = upvalues[11]
     221 [-]: LOADN R9 0   ; var9 = 0
     222 [-]: NAMECALL R6 R6 K61; var7 = var6; var6 = var6[0x0EB34C69]
     223 [-]: CALL R6 4 2  ; var6 = var6(var7, var8, var9)
     224 [-]: JUMPXEQKN R6 K62 L22; 
     225 [-]: GETIMPORT R7 28; var7 = 0x89326C93
     226 [-]: NAMECALL R7 R7 K63; var8 = var7; var7 = var7[0xDD25E9D1]
     227 [-]: CALL R7 2 0  ; var7, ... = var7(var8)
     228 [-]: FASTCALL 64 L21; 
     229 [-]: GETIMPORT R6 21; var6 = 0x7B998233
     230 [-]: CALL R6 0 2  ; var6 = var6(var7, ...)
L21: 231 [-]: JUMPIFNOT R6 L22; goto L22 if not var6
     232 [-]: GETUPVAL R6 12; var6 = upvalues[12]
     233 [-]: CALL R6 1 2  ; var6 = var6()
     234 [-]: JUMPIFNOT R6 L23; goto L23 if not var6
L22: 235 [-]: GETIMPORT R6 23; var6 = 0xCBD666E1
     236 [-]: LOADN R7 0   ; var7 = 0
     237 [-]: CALL R6 2 1  ; var6(var7)
     238 [-]: JUMPBACK L20 ; goto L20
L23: 239 [-]: GETIMPORT R6 1; var6 = 0x3D106989
     240 [-]: LOADK R7 K64 ; var7 = "Boarding cinematic done"
     241 [-]: CALL R6 2 1  ; var6(var7)
     242 [-]: LOADB R8 1   ; var8 = true
     243 [-]: NAMECALL R6 R1 K65; var7 = var1; var6 = var1[0xBAB10F46]
     244 [-]: CALL R6 3 1  ; var6(var7, var8)
     245 [-]: LOADN R8 20  ; var8 = 20
     246 [-]: NAMECALL R6 R1 K66; var7 = var1; var6 = var1[0x24857BD6]
     247 [-]: CALL R6 3 1  ; var6(var7, var8)
     248 [-]: LOADB R8 0   ; var8 = false
     249 [-]: NAMECALL R6 R1 K67; var7 = var1; var6 = var1[0xB8B90F91]
     250 [-]: CALL R6 3 1  ; var6(var7, var8)
     251 [-]: NAMECALL R6 R0 K68; var7 = var0; var6 = var0[0x53C3399F]
     252 [-]: CALL R6 2 2  ; var6 = var6(var7)
     253 [-]: JUMPXEQKN R6 K62 L24 NOT; 
     254 [-]: GETIMPORT R6 57; var6 = 0xBE190284
     255 [-]: LOADB R8 1   ; var8 = true
     256 [-]: NAMECALL R6 R6 K69; var7 = var6; var6 = var6[0xD1961230]
     257 [-]: CALL R6 3 1  ; var6(var7, var8)
     258 [-]: GETIMPORT R9 28; var9 = 0x89326C93
     259 [-]: NAMECALL R9 R9 K71; var10 = var9; var9 = var9[0x61BE252A]
     260 [-]: CALL R9 2 2  ; var9 = var9(var10)
     261 [-]: MULK R8 R9 K70; var8 = var9 * 10
     262 [-]: NAMECALL R6 R0 K72; var7 = var0; var6 = var0[0x05EEB9DB]
     263 [-]: CALL R6 3 1  ; var6(var7, var8)
L24: 264 [-]: GETUPVAL R6 0; var6 = upvalues[0]
     265 [-]: NAMECALL R6 R6 K10; var7 = var6; var6 = var6[0x50A76235]
     266 [-]: CALL R6 2 2  ; var6 = var6(var7)
     267 [-]: JUMPIFNOT R6 L43; goto L43 if not var6
     268 [-]: GETIMPORT R6 28; var6 = 0x89326C93
     269 [-]: GETIMPORT R8 6; var8 = 0x0469F296
     270 [-]: LOADK R9 K73 ; var9 = "GrineerKingpinAvatar"
     271 [-]: CALL R8 2 0  ; var8, ... = var8(var9)
     272 [-]: NAMECALL R6 R6 K74; var7 = var6; var6 = var6[0xC7FCADA9]
     273 [-]: CALL R6 0 2  ; var6 = var6(var7, ...)
     274 [-]: GETIMPORT R7 39; var7 = 0xC8802016
     275 [-]: MOVE R8 R6   ; var8 = var6
     276 [-]: CALL R7 2 4  ; var7, var8, var9 = var7(var8)
     277 [-]: FORGPREP_INEXT R7 L32; 
L25: 278 [-]: FASTCALL1 64 R11 L26; 
     279 [-]: MOVE R13 R11 ; var13 = var11
     280 [-]: GETIMPORT R12 21; var12 = 0x7B998233
     281 [-]: CALL R12 2 2 ; var12 = var12(var13)
L26: 282 [-]: JUMPIF R12 L32; goto L32 if var12
     283 [-]: GETUPVAL R14 13; var14 = upvalues[13]
     284 [-]: NAMECALL R12 R11 K75; var13 = var11; var12 = var11[0x9D6904C1]
     285 [-]: CALL R12 3 2 ; var12 = var12(var13, var14)
     286 [-]: JUMPIF R12 L32; goto L32 if var12
     287 [-]: NAMECALL R12 R11 K76; var13 = var11; var12 = var11[0x2047CFE7]
     288 [-]: CALL R12 2 2 ; var12 = var12(var13)
     289 [-]: JUMPIF R12 L32; goto L32 if var12
     290 [-]: SETUPVAL R11 14; upvalues[11] = var14
     291 [-]: GETIMPORT R12 57; var12 = 0xBE190284
     292 [-]: GETIMPORT R14 6; var14 = 0x0469F296
     293 [-]: LOADK R15 K77; var15 = "NemesisIntroCin"
     294 [-]: CALL R14 2 2 ; var14 = var14(var15)
     295 [-]: LOADN R15 0  ; var15 = 0
     296 [-]: NAMECALL R12 R12 K61; var13 = var12; var12 = var12[0x0EB34C69]
     297 [-]: CALL R12 4 2 ; var12 = var12(var13, var14, var15)
     298 [-]: JUMPXEQKN R12 K62 L33 NOT; 
     299 [-]: GETUPVAL R12 14; var12 = upvalues[14]
     300 [-]: NAMECALL R12 R12 K78; var13 = var12; var12 = var12[0xDE321E6F]
     301 [-]: CALL R12 2 2 ; var12 = var12(var13)
     302 [-]: LOADN R14 0  ; var14 = 0
     303 [-]: NAMECALL R12 R12 K79; var13 = var12; var12 = var12[0x881B6B90]
     304 [-]: CALL R12 3 2 ; var12 = var12(var13, var14)
     305 [-]: LOADN R13 1  ; var13 = 1
     306 [-]: FASTCALL1 64 R12 L27; 
     307 [-]: MOVE R15 R12 ; var15 = var12
     308 [-]: GETIMPORT R14 21; var14 = 0x7B998233
     309 [-]: CALL R14 2 2 ; var14 = var14(var15)
L27: 310 [-]: JUMPIF R14 L31; goto L31 if var14
     311 [-]: NAMECALL R14 R12 K80; var15 = var12; var14 = var12[0xD51D5B66]
     312 [-]: CALL R14 2 2 ; var14 = var14(var15)
     313 [-]: LOADN R17 1  ; var17 = 1
     314 [-]: GETIMPORT R18 82; var18 = 0xB54C8B65
     315 [-]: LENGTH R15 R18; var15 = #var18
     316 [-]: LOADN R16 1  ; var16 = 1
     317 [-]: FORNPREP R15 L31; nforprep start - [escape at L31] -- var15 = iterator
L28: 318 [-]: GETIMPORT R19 82; var19 = 0xB54C8B65
     319 [-]: GETTABLE R18 R19 R17; var18 = var19[var17]
     320 [-]: JUMPIFNOTEQ R18 R14 L30; goto L30 if var18 ~= var5510177
     321 [-]: GETIMPORT R20 84; var20 = 0x450A8592
     322 [-]: GETTABLE R19 R20 R17; var19 = var20[var17]
     323 [-]: FASTCALL1 64 R19 L29; 
     324 [-]: GETIMPORT R18 21; var18 = 0x7B998233
     325 [-]: CALL R18 2 2 ; var18 = var18(var19)
L29: 326 [-]: JUMPIF R18 L31; goto L31 if var18
     327 [-]: MOVE R13 R17 ; var13 = var17
     328 [-]: JUMP L31     ; goto L31
L30: 329 [-]: FORNLOOP R15 L28; nforloop end - iterate + goto L28
L31: 330 [-]: GETUPVAL R14 14; var14 = upvalues[14]
     331 [-]: GETIMPORT R17 84; var17 = 0x450A8592
     332 [-]: GETTABLE R16 R17 R13; var16 = var17[var13]
     333 [-]: LOADB R17 0  ; var17 = false
     334 [-]: LOADN R18 3  ; var18 = 3
     335 [-]: LOADN R19 2  ; var19 = 2
     336 [-]: LOADB R20 1  ; var20 = true
     337 [-]: NAMECALL R14 R14 K85; var15 = var14; var14 = var14[0x5D985C7E]
     338 [-]: CALL R14 7 1 ; var14(var15, var16, var17, var18, var19, var20)
     339 [-]: JUMP L33     ; goto L33
L32: 340 [-]: FORGLOOP R7 L25 2 [inext]; 
L33: 341 [-]: GETUPVAL R8 14; var8 = upvalues[14]
     342 [-]: FASTCALL1 64 R8 L34; 
     343 [-]: GETIMPORT R7 21; var7 = 0x7B998233
     344 [-]: CALL R7 2 2  ; var7 = var7(var8)
L34: 345 [-]: JUMPIFNOT R7 L35; goto L35 if not var7
     346 [-]: GETIMPORT R7 1; var7 = 0x3D106989
     347 [-]: LOADK R8 K86 ; var8 = "Host was migrated and reference to Lich Avatar could not be recovered!"
     348 [-]: CALL R7 2 1  ; var7(var8)
     349 [-]: JUMP L36     ; goto L36
L35: 350 [-]: GETUPVAL R7 14; var7 = upvalues[14]
     351 [-]: NAMECALL R7 R7 K87; var8 = var7; var7 = var7[0xFA9E477F]
     352 [-]: CALL R7 2 2  ; var7 = var7(var8)
     353 [-]: SETUPVAL R7 15; upvalues[7] = var15
L36: 354 [-]: GETIMPORT R7 57; var7 = 0xBE190284
     355 [-]: GETUPVAL R9 16; var9 = upvalues[16]
     356 [-]: NAMECALL R7 R7 K61; var8 = var7; var7 = var7[0x0EB34C69]
     357 [-]: CALL R7 3 2  ; var7 = var7(var8, var9)
     358 [-]: GETIMPORT R8 28; var8 = 0x89326C93
     359 [-]: GETIMPORT R10 6; var10 = 0x0469F296
     360 [-]: LOADK R11 K88; var11 = "LawyerPet"
     361 [-]: CALL R10 2 0 ; var10, ... = var10(var11)
     362 [-]: NAMECALL R8 R8 K74; var9 = var8; var8 = var8[0xC7FCADA9]
     363 [-]: CALL R8 0 2  ; var8 = var8(var9, ...)
     364 [-]: LENGTH R9 R8 ; var9 = #var8
     365 [-]: SETUPVAL R9 17; upvalues[9] = var17
     366 [-]: GETIMPORT R9 28; var9 = 0x89326C93
     367 [-]: GETIMPORT R11 46; var11 = 0x7ED0A956
     368 [-]: LOADK R12 K89; var12 = "/Lotus/Types/Enemies/TennoReplicants/TennoReplicantAvatar"
     369 [-]: CALL R11 2 0 ; var11, ... = var11(var12)
     370 [-]: NAMECALL R9 R9 K90; var10 = var9; var9 = var9[0xFB669000]
     371 [-]: CALL R9 0 2  ; var9 = var9(var10, ...)
     372 [-]: GETIMPORT R10 39; var10 = 0xC8802016
     373 [-]: MOVE R11 R9  ; var11 = var9
     374 [-]: CALL R10 2 4 ; var10, var11, var12 = var10(var11)
     375 [-]: FORGPREP_INEXT R10 L38; 
L37: 376 [-]: NAMECALL R15 R14 K91; var16 = var14; var15 = var14[0x2D0A291F]
     377 [-]: CALL R15 2 2 ; var15 = var15(var16)
     378 [-]: GETUPVAL R16 13; var16 = upvalues[13]
     379 [-]: JUMPIFEQ R15 R16 L38; goto L38 if var15 == var1183804
     380 [-]: GETUPVAL R16 18; var16 = upvalues[18]
     381 [-]: FASTCALL2 52 R16 R14 L38; 
     382 [-]: MOVE R17 R14 ; var17 = var14
     383 [-]: GETIMPORT R15 93; var15 = 0x33BDD652[0x23D5322F]
     384 [-]: CALL R15 3 1 ; var15(var16, var17)
L38: 385 [-]: FORGLOOP R10 L37 2 [inext]; 
     386 [-]: GETUPVAL R11 14; var11 = upvalues[14]
     387 [-]: FASTCALL1 64 R11 L39; 
     388 [-]: GETIMPORT R10 21; var10 = 0x7B998233
     389 [-]: CALL R10 2 2 ; var10 = var10(var11)
L39: 390 [-]: JUMPIF R10 L40; goto L40 if var10
     391 [-]: GETUPVAL R11 18; var11 = upvalues[18]
     392 [-]: LENGTH R10 R11; var10 = #var11
     393 [-]: LOADN R11 0  ; var11 = 0
     394 [-]: JUMPIFLT R11 R10 L41; goto L41 if var11 < var1116732
L40: 395 [-]: GETUPVAL R10 17; var10 = upvalues[17]
     396 [-]: LOADN R11 0  ; var11 = 0
     397 [-]: JUMPIFNOTLT R11 R10 L42; goto L42 if var11 >= var920124
L41: 398 [-]: GETUPVAL R10 14; var10 = upvalues[14]
     399 [-]: NAMECALL R10 R10 K94; var11 = var10; var10 = var10[0x1AC1655C]
     400 [-]: CALL R10 2 2 ; var10 = var10(var11)
     401 [-]: SETUPVAL R10 19; upvalues[10] = var19
     402 [-]: GETUPVAL R10 19; var10 = upvalues[19]
     403 [-]: GETUPVAL R12 20; var12 = upvalues[20]
     404 [-]: LOADN R13 25 ; var13 = 25
     405 [-]: LOADN R14 6  ; var14 = 6
     406 [-]: LOADN R15 0  ; var15 = 0
     407 [-]: NAMECALL R10 R10 K95; var11 = var10; var10 = var10[0xA383DE31]
     408 [-]: CALL R10 6 1 ; var10(var11, var12, var13, var14, var15)
     409 [-]: GETUPVAL R10 19; var10 = upvalues[19]
     410 [-]: GETUPVAL R12 20; var12 = upvalues[20]
     411 [-]: LOADN R13 25 ; var13 = 25
     412 [-]: LOADN R14 6  ; var14 = 6
     413 [-]: LOADN R15 0  ; var15 = 0
     414 [-]: NAMECALL R10 R10 K96; var11 = var10; var10 = var10[0x4CB29D1C]
     415 [-]: CALL R10 6 1 ; var10(var11, var12, var13, var14, var15)
     416 [-]: GETIMPORT R10 57; var10 = 0xBE190284
     417 [-]: GETIMPORT R12 6; var12 = 0x0469F296
     418 [-]: LOADK R13 K77; var13 = "NemesisIntroCin"
     419 [-]: CALL R12 2 2 ; var12 = var12(var13)
     420 [-]: LOADN R13 0  ; var13 = 0
     421 [-]: NAMECALL R10 R10 K61; var11 = var10; var10 = var10[0x0EB34C69]
     422 [-]: CALL R10 4 2 ; var10 = var10(var11, var12, var13)
     423 [-]: JUMPXEQKN R10 K62 L42 NOT; 
     424 [-]: GETUPVAL R10 19; var10 = upvalues[19]
     425 [-]: GETUPVAL R12 21; var12 = upvalues[21]
     426 [-]: LOADN R13 25 ; var13 = 25
     427 [-]: LOADN R14 6  ; var14 = 6
     428 [-]: LOADN R15 0  ; var15 = 0
     429 [-]: NAMECALL R10 R10 K95; var11 = var10; var10 = var10[0xA383DE31]
     430 [-]: CALL R10 6 1 ; var10(var11, var12, var13, var14, var15)
     431 [-]: GETUPVAL R10 19; var10 = upvalues[19]
     432 [-]: GETUPVAL R12 21; var12 = upvalues[21]
     433 [-]: LOADN R13 25 ; var13 = 25
     434 [-]: LOADN R14 6  ; var14 = 6
     435 [-]: LOADN R15 0  ; var15 = 0
     436 [-]: NAMECALL R10 R10 K96; var11 = var10; var10 = var10[0x4CB29D1C]
     437 [-]: CALL R10 6 1 ; var10(var11, var12, var13, var14, var15)
L42: 438 [-]: GETGLOBAL R12 K97; var12 = 0xBC9D46DD
     439 [-]: SUB R11 R12 R7; var11 = var12 - var7
     440 [-]: GETUPVAL R12 17; var12 = upvalues[17]
     441 [-]: SUB R10 R11 R12; var10 = var11 - var12
     442 [-]: SETGLOBAL R10 K97; 0xBC9D46DD = var10
     443 [-]: GETUPVAL R10 22; var10 = upvalues[22]
     444 [-]: LOADB R11 1  ; var11 = true
     445 [-]: LOADB R12 0  ; var12 = false
     446 [-]: CALL R10 3 1 ; var10(var11, var12)
     447 [-]: GETIMPORT R10 57; var10 = 0xBE190284
     448 [-]: GETUPVAL R12 24; var12 = upvalues[24]
     449 [-]: LOADN R13 0  ; var13 = 0
     450 [-]: NAMECALL R10 R10 K61; var11 = var10; var10 = var10[0x0EB34C69]
     451 [-]: CALL R10 4 2 ; var10 = var10(var11, var12, var13)
     452 [-]: SETUPVAL R10 23; upvalues[10] = var23
     453 [-]: LOADB R10 1  ; var10 = true
     454 [-]: SETUPVAL R10 25; upvalues[10] = var25
     455 [-]: GETUPVAL R10 0; var10 = upvalues[0]
     456 [-]: NAMECALL R10 R10 K98; var11 = var10; var10 = var10[0x8B28A480]
     457 [-]: CALL R10 2 1 ; var10(var11)
     458 [-]: JUMP L44     ; goto L44
L43: 459 [-]: GETUPVAL R6 22; var6 = upvalues[22]
     460 [-]: LOADB R7 1   ; var7 = true
     461 [-]: LOADB R8 1   ; var8 = true
     462 [-]: CALL R6 3 1  ; var6(var7, var8)
L44: 463 [-]: GETIMPORT R6 1; var6 = 0x3D106989
     464 [-]: LOADK R7 K99 ; var7 = "Main loop start"
     465 [-]: CALL R6 2 1  ; var6(var7)
L45: 466 [-]: NAMECALL R7 R0 K68; var8 = var0; var7 = var0[0x53C3399F]
     467 [-]: CALL R7 2 2  ; var7 = var7(var8)
     468 [-]: MODK R6 R7 K70; var6 = var7 10
     469 [-]: NAMECALL R9 R0 K68; var10 = var0; var9 = var0[0x53C3399F]
     470 [-]: CALL R9 2 2  ; var9 = var9(var10)
          472 [-]: FASTCALL1 12 R8 L46; 
     473 [-]: GETIMPORT R7 102; var7 = 0x5BCED4C4[0x55F27C30]
     474 [-]: CALL R7 2 2  ; var7 = var7(var8)
L46: 475 [-]: JUMPIFNOTLT R6 R7 L111; goto L111 if var6 >= var1705788
     476 [-]: GETUPVAL R7 26; var7 = upvalues[26]
     477 [-]: LENGTH R6 R7 ; var6 = #var7
     478 [-]: LOADN R7 0   ; var7 = 0
     479 [-]: JUMPIFNOTLE R6 R7 L47; goto L47 if var6 > var67105
     480 [-]: GETIMPORT R6 1; var6 = 0x3D106989
     481 [-]: LOADK R7 K103; var7 = "We had no active Liches of the matching mission faction - Ending mission"
     482 [-]: CALL R6 2 1  ; var6(var7)
     483 [-]: JUMP L111    ; goto L111
L47: 484 [-]: GETIMPORT R6 105; var6 = _T["NemesisManifestedEnemy"]
     485 [-]: JUMPIF R6 L49; goto L49 if var6
     486 [-]: GETUPVAL R6 25; var6 = upvalues[25]
     487 [-]: JUMPIF R6 L49; goto L49 if var6
     488 [-]: GETUPVAL R6 27; var6 = upvalues[27]
     489 [-]: GETUPVAL R8 26; var8 = upvalues[26]
     490 [-]: GETTABLEN R7 R8 1; var7 = var8[1]
     491 [-]: CALL R6 2 2  ; var6 = var6(var7)
     492 [-]: JUMPIF R6 L48; goto L48 if var6
     493 [-]: GETIMPORT R6 1; var6 = 0x3D106989
     494 [-]: LOADK R7 K106; var7 = "Waiting on player's lich data, but they've disconnected. Trying to spawn lich for next player"
     495 [-]: CALL R6 2 1  ; var6(var7)
     496 [-]: GETUPVAL R6 22; var6 = upvalues[22]
     497 [-]: LOADB R7 0   ; var7 = false
     498 [-]: LOADB R8 1   ; var8 = true
     499 [-]: CALL R6 3 1  ; var6(var7, var8)
     500 [-]: GETUPVAL R7 26; var7 = upvalues[26]
     501 [-]: LENGTH R6 R7 ; var6 = #var7
     502 [-]: JUMPXEQKN R6 K62 L49; 
L48: 503 [-]: GETIMPORT R6 23; var6 = 0xCBD666E1
     504 [-]: LOADN R7 0   ; var7 = 0
     505 [-]: CALL R6 2 1  ; var6(var7)
     506 [-]: JUMPBACK L47 ; goto L47
L49: 507 [-]: GETUPVAL R7 26; var7 = upvalues[26]
     508 [-]: LENGTH R6 R7 ; var6 = #var7
     509 [-]: JUMPXEQKN R6 K62 L50 NOT; 
     510 [-]: GETIMPORT R6 1; var6 = 0x3D106989
     511 [-]: LOADK R7 K107; var7 = "No liches to spawn, bailing to extraction"
     512 [-]: CALL R6 2 1  ; var6(var7)
     513 [-]: JUMP L111    ; goto L111
L50: 514 [-]: GETIMPORT R7 28; var7 = 0x89326C93
     515 [-]: NAMECALL R7 R7 K63; var8 = var7; var7 = var7[0xDD25E9D1]
     516 [-]: CALL R7 2 0  ; var7, ... = var7(var8)
     517 [-]: FASTCALL 64 L51; 
     518 [-]: GETIMPORT R6 21; var6 = 0x7B998233
     519 [-]: CALL R6 0 2  ; var6 = var6(var7, ...)
L51: 520 [-]: JUMPIFNOT R6 L52; goto L52 if not var6
     521 [-]: GETUPVAL R6 12; var6 = upvalues[12]
     522 [-]: CALL R6 1 2  ; var6 = var6()
     523 [-]: JUMPIFNOT R6 L53; goto L53 if not var6
L52: 524 [-]: GETIMPORT R6 23; var6 = 0xCBD666E1
     525 [-]: LOADN R7 0   ; var7 = 0
     526 [-]: CALL R6 2 1  ; var6(var7)
     527 [-]: JUMPBACK L50 ; goto L50
L53: 528 [-]: GETUPVAL R6 28; var6 = upvalues[28]
     529 [-]: CALL R6 1 1  ; var6()
     530 [-]: GETUPVAL R7 14; var7 = upvalues[14]
     531 [-]: FASTCALL1 64 R7 L54; 
     532 [-]: GETIMPORT R6 21; var6 = 0x7B998233
     533 [-]: CALL R6 2 2  ; var6 = var6(var7)
L54: 534 [-]: JUMPIFNOT R6 L55; goto L55 if not var6
     535 [-]: GETUPVAL R6 29; var6 = upvalues[29]
     536 [-]: CALL R6 1 1  ; var6()
     537 [-]: GETUPVAL R6 30; var6 = upvalues[30]
     538 [-]: MOVE R7 R1   ; var7 = var1
     539 [-]: CALL R6 2 1  ; var6(var7)
L55: 540 [-]: GETIMPORT R6 23; var6 = 0xCBD666E1
     541 [-]: LOADN R7 1   ; var7 = 1
     542 [-]: CALL R6 2 1  ; var6(var7)
     543 [-]: LOADB R6 0   ; var6 = false
     544 [-]: LOADB R7 0   ; var7 = false
     545 [-]: LOADB R8 0   ; var8 = false
     546 [-]: LOADNIL R9   ; var9 = nil
     547 [-]: GETUPVAL R11 14; var11 = upvalues[14]
     548 [-]: FASTCALL1 64 R11 L56; 
     549 [-]: GETIMPORT R10 21; var10 = 0x7B998233
     550 [-]: CALL R10 2 2 ; var10 = var10(var11)
L56: 551 [-]: JUMPIF R10 L57; goto L57 if var10
     552 [-]: GETUPVAL R10 14; var10 = upvalues[14]
     553 [-]: GETIMPORT R12 109; var12 = gBaseMarkerInfoType
     554 [-]: NAMECALL R10 R10 K110; var11 = var10; var10 = var10[0xC9F6A7D7]
     555 [-]: CALL R10 3 2 ; var10 = var10(var11, var12)
     556 [-]: MOVE R9 R10  ; var9 = var10
L57: 557 [-]: GETIMPORT R10 57; var10 = 0xBE190284
     558 [-]: GETUPVAL R12 16; var12 = upvalues[16]
     559 [-]: LOADN R13 0  ; var13 = 0
     560 [-]: NAMECALL R10 R10 K61; var11 = var10; var10 = var10[0x0EB34C69]
     561 [-]: CALL R10 4 2 ; var10 = var10(var11, var12, var13)
L58: 562 [-]: GETUPVAL R12 26; var12 = upvalues[26]
     563 [-]: LENGTH R11 R12; var11 = #var12
     564 [-]: LOADN R12 0  ; var12 = 0
     565 [-]: JUMPIFNOTLT R12 R11 L110; goto L110 if var12 >= var50937917
     566 [-]: FASTCALL1 64 R9 L59; 
     567 [-]: MOVE R12 R9  ; var12 = var9
     568 [-]: GETIMPORT R11 21; var11 = 0x7B998233
     569 [-]: CALL R11 2 2 ; var11 = var11(var12)
L59: 570 [-]: JUMPIFNOT R11 L61; goto L61 if not var11
     571 [-]: GETUPVAL R12 14; var12 = upvalues[14]
     572 [-]: FASTCALL1 64 R12 L60; 
     573 [-]: GETIMPORT R11 21; var11 = 0x7B998233
     574 [-]: CALL R11 2 2 ; var11 = var11(var12)
L60: 575 [-]: JUMPIF R11 L61; goto L61 if var11
     576 [-]: GETUPVAL R11 14; var11 = upvalues[14]
     577 [-]: GETIMPORT R13 109; var13 = gBaseMarkerInfoType
     578 [-]: NAMECALL R11 R11 K110; var12 = var11; var11 = var11[0xC9F6A7D7]
     579 [-]: CALL R11 3 2 ; var11 = var11(var12, var13)
     580 [-]: MOVE R9 R11  ; var9 = var11
L61: 581 [-]: JUMPIF R6 L76; goto L76 if var6
     582 [-]: LOADNIL R11  ; var11 = nil
     583 [-]: GETUPVAL R13 14; var13 = upvalues[14]
     584 [-]: FASTCALL1 64 R13 L62; 
     585 [-]: GETIMPORT R12 21; var12 = 0x7B998233
     586 [-]: CALL R12 2 2 ; var12 = var12(var13)
L62: 587 [-]: JUMPIF R12 L63; goto L63 if var12
     588 [-]: GETIMPORT R12 28; var12 = 0x89326C93
     589 [-]: GETUPVAL R14 14; var14 = upvalues[14]
     590 [-]: NAMECALL R14 R14 K33; var15 = var14; var14 = var14[0xD1586535]
     591 [-]: CALL R14 2 2 ; var14 = var14(var15)
     592 [-]: LOADN R15 500; var15 = 500
     593 [-]: NAMECALL R12 R12 K111; var13 = var12; var12 = var12[0x50A314F9]
     594 [-]: CALL R12 4 2 ; var12 = var12(var13, var14, var15)
     595 [-]: MOVE R11 R12 ; var11 = var12
L63: 596 [-]: FASTCALL1 64 R11 L64; 
     597 [-]: MOVE R13 R11 ; var13 = var11
     598 [-]: GETIMPORT R12 21; var12 = 0x7B998233
     599 [-]: CALL R12 2 2 ; var12 = var12(var13)
L64: 600 [-]: JUMPIF R12 L76; goto L76 if var12
     601 [-]: NAMECALL R12 R11 K49; var13 = var11; var12 = var11[0xE79E7EF4]
     602 [-]: CALL R12 2 2 ; var12 = var12(var13)
     603 [-]: GETUPVAL R13 14; var13 = upvalues[14]
     604 [-]: NAMECALL R13 R13 K49; var14 = var13; var13 = var13[0xE79E7EF4]
     605 [-]: CALL R13 2 2 ; var13 = var13(var14)
     606 [-]: FASTCALL1 64 R12 L65; 
     607 [-]: MOVE R15 R12 ; var15 = var12
     608 [-]: GETIMPORT R14 21; var14 = 0x7B998233
     609 [-]: CALL R14 2 2 ; var14 = var14(var15)
L65: 610 [-]: JUMPIF R14 L76; goto L76 if var14
     611 [-]: FASTCALL1 64 R13 L66; 
     612 [-]: MOVE R15 R13 ; var15 = var13
     613 [-]: GETIMPORT R14 21; var14 = 0x7B998233
     614 [-]: CALL R14 2 2 ; var14 = var14(var15)
L66: 615 [-]: JUMPIFNOT R14 L67; goto L67 if not var14
     616 [-]: JUMP L76     ; goto L76
L67: 617 [-]: NAMECALL R14 R12 K112; var15 = var12; var14 = var12[0x9435EB6D]
     618 [-]: CALL R14 2 2 ; var14 = var14(var15)
     619 [-]: NAMECALL R15 R13 K112; var16 = var13; var15 = var13[0x9435EB6D]
     620 [-]: CALL R15 2 2 ; var15 = var15(var16)
     621 [-]: JUMPIFNOTEQ R14 R15 L75; goto L75 if var14 ~= var790049
     622 [-]: GETIMPORT R14 12; var14 = _T["faction"]
     623 [-]: GETUPVAL R15 1; var15 = upvalues[1]
     624 [-]: JUMPIFNOTEQ R14 R15 L68; goto L68 if var14 ~= var134972
     625 [-]: GETUPVAL R15 2; var15 = upvalues[2]
     626 [-]: GETTABLEKS R14 R15 K13; var14 = var15[0xA1DF01D6]
     627 [-]: LOADK R15 K14; var15 = "/Lotus/Language/Objectives/GenericAssassinate"
     628 [-]: LOADN R16 2  ; var16 = 2
     629 [-]: CALL R14 3 1 ; var14(var15, var16)
     630 [-]: JUMP L69     ; goto L69
L68: 631 [-]: GETUPVAL R15 2; var15 = upvalues[2]
     632 [-]: GETTABLEKS R14 R15 K13; var14 = var15[0xA1DF01D6]
     633 [-]: LOADK R15 K113; var15 = "/Lotus/Language/CorpusRailjack/KillLichLoc"
     634 [-]: LOADN R16 2  ; var16 = 2
     635 [-]: CALL R14 3 1 ; var14(var15, var16)
     636 [-]: GETUPVAL R15 2; var15 = upvalues[2]
     637 [-]: GETTABLEKS R14 R15 K114; var14 = var15[0xEA753E99]
     638 [-]: LOADK R15 K115; var15 = "/Lotus/Language/CorpusRailjack/LichSpecterCounter"
     639 [-]: LOADN R16 0  ; var16 = 0
     640 [-]: GETUPVAL R17 31; var17 = upvalues[31]
     641 [-]: CALL R14 4 1 ; var14(var15, var16, var17)
L69: 642 [-]: GETIMPORT R14 39; var14 = 0xC8802016
     643 [-]: GETUPVAL R15 18; var15 = upvalues[18]
     644 [-]: CALL R14 2 4 ; var14, var15, var16 = var14(var15)
     645 [-]: FORGPREP_INEXT R14 L71; 
L70: 646 [-]: GETIMPORT R21 117; var21 = 0xC76CF990
     647 [-]: GETIMPORT R22 119; var22 = EMPTY_SYMBOL
     648 [-]: GETIMPORT R23 121; var23 = 0xA421AF95
     649 [-]: LOADN R24 0  ; var24 = 0
     650 [-]: LOADN R25 2  ; var25 = 2
     651 [-]: LOADN R26 0  ; var26 = 0
     652 [-]: CALL R23 4 2 ; var23 = var23(var24, var25, var26)
     653 [-]: GETIMPORT R24 123; var24 = ZERO_ROTATION
     654 [-]: NAMECALL R19 R18 K124; var20 = var18; var19 = var18[0x47901F07]
     655 [-]: CALL R19 6 1 ; var19(var20, var21, var22, var23, var24)
L71: 656 [-]: FORGLOOP R14 L70 2 [inext]; 
     657 [-]: FASTCALL1 64 R9 L72; 
     658 [-]: MOVE R15 R9  ; var15 = var9
     659 [-]: GETIMPORT R14 21; var14 = 0x7B998233
     660 [-]: CALL R14 2 2 ; var14 = var14(var15)
L72: 661 [-]: JUMPIF R14 L73; goto L73 if var14
     662 [-]: NAMECALL R14 R9 K50; var15 = var9; var14 = var9[0xF4E253B6]
     663 [-]: CALL R14 2 1 ; var14(var15)
L73: 664 [-]: LOADB R6 1   ; var6 = true
     665 [-]: GETIMPORT R14 57; var14 = 0xBE190284
     666 [-]: GETIMPORT R16 6; var16 = 0x0469F296
     667 [-]: LOADK R17 K77; var17 = "NemesisIntroCin"
     668 [-]: CALL R16 2 2 ; var16 = var16(var17)
     669 [-]: LOADN R17 0  ; var17 = 0
     670 [-]: NAMECALL R14 R14 K61; var15 = var14; var14 = var14[0x0EB34C69]
     671 [-]: CALL R14 4 2 ; var14 = var14(var15, var16, var17)
     672 [-]: JUMPXEQKN R14 K62 L76 NOT; 
     673 [-]: GETIMPORT R14 28; var14 = 0x89326C93
     674 [-]: GETIMPORT R16 6; var16 = 0x0469F296
     675 [-]: LOADK R17 K125; var17 = "NemesisIntroCinematic"
     676 [-]: CALL R16 2 2 ; var16 = var16(var17)
     677 [-]: GETUPVAL R17 14; var17 = upvalues[14]
     678 [-]: NAMECALL R17 R17 K33; var18 = var17; var17 = var17[0xD1586535]
     679 [-]: CALL R17 2 0 ; var17, ... = var17(var18)
     680 [-]: NAMECALL R14 R14 K126; var15 = var14; var14 = var14[0xC7B81E8D]
     681 [-]: CALL R14 0 2 ; var14 = var14(var15, ...)
     682 [-]: FASTCALL1 64 R14 L74; 
     683 [-]: MOVE R16 R14 ; var16 = var14
     684 [-]: GETIMPORT R15 21; var15 = 0x7B998233
     685 [-]: CALL R15 2 2 ; var15 = var15(var16)
L74: 686 [-]: JUMPIF R15 L76; goto L76 if var15
     687 [-]: LOADB R17 1  ; var17 = true
     688 [-]: NAMECALL R15 R1 K67; var16 = var1; var15 = var1[0xB8B90F91]
     689 [-]: CALL R15 3 1 ; var15(var16, var17)
     690 [-]: GETUPVAL R16 32; var16 = upvalues[32]
     691 [-]: GETTABLEKS R15 R16 K127; var15 = var16[0x48EA9DE9]
     692 [-]: GETIMPORT R16 6; var16 = 0x0469F296
     693 [-]: LOADK R17 K128; var17 = "RJAssConfront"
     694 [-]: CALL R16 2 0 ; var16, ... = var16(var17)
     695 [-]: CALL R15 0 1 ; var15(var16, ...)
     696 [-]: GETIMPORT R17 6; var17 = 0x0469F296
     697 [-]: LOADK R18 K129; var18 = "ManageIntroCin"
     698 [-]: CALL R17 2 2 ; var17 = var17(var18)
     699 [-]: LOADB R18 0  ; var18 = false
     700 [-]: NAMECALL R15 R14 K60; var16 = var14; var15 = var14[0xD5F7912B]
     701 [-]: CALL R15 4 1 ; var15(var16, var17, var18)
     702 [-]: GETIMPORT R15 28; var15 = 0x89326C93
     703 [-]: GETIMPORT R17 131; var17 = 0x8545F318
     704 [-]: GETUPVAL R18 14; var18 = upvalues[14]
     705 [-]: NAMECALL R18 R18 K33; var19 = var18; var18 = var18[0xD1586535]
     706 [-]: CALL R18 2 2 ; var18 = var18(var19)
     707 [-]: GETIMPORT R19 123; var19 = ZERO_ROTATION
     708 [-]: GETUPVAL R20 14; var20 = upvalues[14]
     709 [-]: NAMECALL R15 R15 K132; var16 = var15; var15 = var15[0x05909209]
     710 [-]: CALL R15 6 1 ; var15(var16, var17, var18, var19, var20)
     711 [-]: JUMP L76     ; goto L76
L75: 712 [-]: JUMPIF R7 L76; goto L76 if var7
     713 [-]: NAMECALL R14 R12 K112; var15 = var12; var14 = var12[0x9435EB6D]
     714 [-]: CALL R14 2 2 ; var14 = var14(var15)
     715 [-]: NAMECALL R15 R13 K112; var16 = var13; var15 = var13[0x9435EB6D]
     716 [-]: CALL R15 2 2 ; var15 = var15(var16)
          718 [-]: JUMPIFNOTLE R16 R14 L76; goto L76 if var16 > var67334
     719 [-]: LOADB R7 1   ; var7 = true
     720 [-]: GETUPVAL R17 32; var17 = upvalues[32]
     721 [-]: GETTABLEKS R16 R17 K127; var16 = var17[0x48EA9DE9]
     722 [-]: GETIMPORT R17 6; var17 = 0x0469F296
     723 [-]: LOADK R18 K134; var18 = "RJAssHalfway"
     724 [-]: CALL R17 2 0 ; var17, ... = var17(var18)
     725 [-]: CALL R16 0 1 ; var16(var17, ...)
L76: 726 [-]: GETUPVAL R14 18; var14 = upvalues[18]
     727 [-]: LENGTH R13 R14; var13 = #var14
     728 [-]: LOADN R11 1  ; var11 = 1
     729 [-]: LOADN R12 -1 ; var12 = -1
     730 [-]: FORNPREP R11 L83; nforprep start - [escape at L83] -- var11 = iterator
L77: 731 [-]: GETUPVAL R16 18; var16 = upvalues[18]
     732 [-]: GETTABLE R15 R16 R13; var15 = var16[var13]
     733 [-]: FASTCALL1 64 R15 L78; 
     734 [-]: GETIMPORT R14 21; var14 = 0x7B998233
     735 [-]: CALL R14 2 2 ; var14 = var14(var15)
L78: 736 [-]: JUMPIF R14 L79; goto L79 if var14
     737 [-]: GETUPVAL R15 18; var15 = upvalues[18]
     738 [-]: GETTABLE R14 R15 R13; var14 = var15[var13]
     739 [-]: NAMECALL R14 R14 K76; var15 = var14; var14 = var14[0x2047CFE7]
     740 [-]: CALL R14 2 2 ; var14 = var14(var15)
     741 [-]: JUMPIF R14 L79; goto L79 if var14
     742 [-]: GETUPVAL R15 18; var15 = upvalues[18]
     743 [-]: GETTABLE R14 R15 R13; var14 = var15[var13]
     744 [-]: NAMECALL R14 R14 K135; var15 = var14; var14 = var14[0x73901ACF]
     745 [-]: CALL R14 2 2 ; var14 = var14(var15)
     746 [-]: JUMPIFNOT R14 L82; goto L82 if not var14
L79: 747 [-]: GETIMPORT R14 53; var14 = 0x33BDD652[0x9C1F3B5A]
     748 [-]: GETUPVAL R15 18; var15 = upvalues[18]
     749 [-]: MOVE R16 R13 ; var16 = var13
     750 [-]: CALL R14 3 1 ; var14(var15, var16)
     751 [-]: ADDK R10 R10 K136; var10 = var10 + 1
     752 [-]: GETIMPORT R14 57; var14 = 0xBE190284
     753 [-]: GETUPVAL R16 16; var16 = upvalues[16]
     754 [-]: MOVE R17 R10 ; var17 = var10
     755 [-]: NAMECALL R14 R14 K137; var15 = var14; var14 = var14[0x751F061D]
     756 [-]: CALL R14 4 1 ; var14(var15, var16, var17)
     757 [-]: GETUPVAL R15 2; var15 = upvalues[2]
     758 [-]: GETTABLEKS R14 R15 K114; var14 = var15[0xEA753E99]
     759 [-]: LOADK R15 K115; var15 = "/Lotus/Language/CorpusRailjack/LichSpecterCounter"
     760 [-]: MOVE R16 R10 ; var16 = var10
     761 [-]: GETUPVAL R17 31; var17 = upvalues[31]
     762 [-]: CALL R14 4 1 ; var14(var15, var16, var17)
     763 [-]: GETUPVAL R14 31; var14 = upvalues[31]
     764 [-]: JUMPIFNOTLE R14 R10 L82; goto L82 if var14 > var2166332
     765 [-]: GETUPVAL R14 33; var14 = upvalues[33]
     766 [-]: JUMPIF R14 L80; goto L80 if var14
     767 [-]: GETUPVAL R14 34; var14 = upvalues[34]
     768 [-]: CALL R14 1 1 ; var14()
L80: 769 [-]: GETIMPORT R14 139; var14 = 0x4EC73E73
     770 [-]: GETUPVAL R15 18; var15 = upvalues[18]
     771 [-]: CALL R14 2 2 ; var14 = var14(var15)
     772 [-]: JUMPIF R14 L81; goto L81 if var14
     773 [-]: GETUPVAL R14 35; var14 = upvalues[35]
     774 [-]: CALL R14 1 1 ; var14()
L81: 775 [-]: GETUPVAL R14 17; var14 = upvalues[17]
     776 [-]: LOADN R15 0  ; var15 = 0
     777 [-]: JUMPIFNOTLT R15 R14 L82; goto L82 if var15 >= var134972
     778 [-]: GETUPVAL R15 2; var15 = upvalues[2]
     779 [-]: GETTABLEKS R14 R15 K140; var14 = var15[0xF3928F38]
     780 [-]: MOVE R15 R10 ; var15 = var10
     781 [-]: GETUPVAL R16 31; var16 = upvalues[31]
     782 [-]: CALL R14 3 1 ; var14(var15, var16)
     783 [-]: GETUPVAL R15 2; var15 = upvalues[2]
     784 [-]: GETTABLEKS R14 R15 K141; var14 = var15[0xCFA44AB1]
     785 [-]: LOADK R15 K142; var15 = "/Lotus/Language/CorpusRailjack/LichSpecterCounterHoundLoc"
     786 [-]: CALL R14 2 1 ; var14(var15)
L82: 787 [-]: FORNLOOP R11 L77; nforloop end - iterate + goto L77
L83: 788 [-]: GETIMPORT R11 139; var11 = 0x4EC73E73
     789 [-]: GETUPVAL R12 18; var12 = upvalues[18]
     790 [-]: CALL R11 2 2 ; var11 = var11(var12)
     791 [-]: JUMPIF R11 L86; goto L86 if var11
     792 [-]: GETUPVAL R12 14; var12 = upvalues[14]
     793 [-]: FASTCALL1 64 R12 L84; 
     794 [-]: GETIMPORT R11 21; var11 = 0x7B998233
     795 [-]: CALL R11 2 2 ; var11 = var11(var12)
L84: 796 [-]: JUMPIF R11 L86; goto L86 if var11
     797 [-]: GETUPVAL R12 2; var12 = upvalues[2]
     798 [-]: GETTABLEKS R11 R12 K143; var11 = var12[0xBD3CE95D]
     799 [-]: CALL R11 1 1 ; var11()
     800 [-]: LOADN R10 0  ; var10 = 0
     801 [-]: GETIMPORT R11 57; var11 = 0xBE190284
     802 [-]: GETUPVAL R13 16; var13 = upvalues[16]
     803 [-]: MOVE R14 R10 ; var14 = var10
     804 [-]: NAMECALL R11 R11 K137; var12 = var11; var11 = var11[0x751F061D]
     805 [-]: CALL R11 4 1 ; var11(var12, var13, var14)
     806 [-]: GETUPVAL R11 14; var11 = upvalues[14]
     807 [-]: NAMECALL R11 R11 K94; var12 = var11; var11 = var11[0x1AC1655C]
     808 [-]: CALL R11 2 2 ; var11 = var11(var12)
     809 [-]: SETUPVAL R11 19; upvalues[11] = var19
     810 [-]: GETUPVAL R11 19; var11 = upvalues[19]
     811 [-]: GETUPVAL R13 20; var13 = upvalues[20]
     812 [-]: NAMECALL R11 R11 K144; var12 = var11; var11 = var11[0x8E3E343E]
     813 [-]: CALL R11 3 1 ; var11(var12, var13)
     814 [-]: GETUPVAL R11 19; var11 = upvalues[19]
     815 [-]: GETUPVAL R13 20; var13 = upvalues[20]
     816 [-]: NAMECALL R11 R11 K145; var12 = var11; var11 = var11[0x9326CA4B]
     817 [-]: CALL R11 3 1 ; var11(var12, var13)
     818 [-]: FASTCALL1 64 R9 L85; 
     819 [-]: MOVE R12 R9  ; var12 = var9
     820 [-]: GETIMPORT R11 21; var11 = 0x7B998233
     821 [-]: CALL R11 2 2 ; var11 = var11(var12)
L85: 822 [-]: JUMPIF R11 L86; goto L86 if var11
     823 [-]: NAMECALL R11 R9 K146; var12 = var9; var11 = var9[0x383D2E7D]
     824 [-]: CALL R11 2 1 ; var11(var12)
L86: 825 [-]: GETUPVAL R12 26; var12 = upvalues[26]
     826 [-]: GETTABLEN R11 R12 1; var11 = var12[1]
     827 [-]: JUMPXEQKS R11 K147 L87 NOT; 
     828 [-]: GETUPVAL R11 14; var11 = upvalues[14]
     829 [-]: NAMECALL R11 R11 K76; var12 = var11; var11 = var11[0x2047CFE7]
     830 [-]: CALL R11 2 2 ; var11 = var11(var12)
     831 [-]: JUMPIFNOT R11 L94; goto L94 if not var11
     832 [-]: LOADNIL R11  ; var11 = nil
     833 [-]: SETUPVAL R11 15; upvalues[11] = var15
     834 [-]: LOADNIL R11  ; var11 = nil
     835 [-]: SETUPVAL R11 14; upvalues[11] = var14
     836 [-]: LOADNIL R9   ; var9 = nil
     837 [-]: JUMP L94     ; goto L94
L87: 838 [-]: GETIMPORT R11 149; var11 = _T["LichFinisherStabSequence"]
     839 [-]: JUMPIFNOT R11 L94; goto L94 if not var11
     840 [-]: GETIMPORT R11 1; var11 = 0x3D106989
     841 [-]: LOADK R12 K150; var12 = "Lich getting stabbed"
     842 [-]: CALL R11 2 1 ; var11(var12)
L88: 843 [-]: GETIMPORT R12 28; var12 = 0x89326C93
     844 [-]: NAMECALL R12 R12 K63; var13 = var12; var12 = var12[0xDD25E9D1]
     845 [-]: CALL R12 2 0 ; var12, ... = var12(var13)
     846 [-]: FASTCALL 64 L89; 
     847 [-]: GETIMPORT R11 21; var11 = 0x7B998233
     848 [-]: CALL R11 0 2 ; var11 = var11(var12, ...)
L89: 849 [-]: JUMPIF R11 L90; goto L90 if var11
     850 [-]: GETIMPORT R11 23; var11 = 0xCBD666E1
     851 [-]: LOADN R12 0  ; var12 = 0
     852 [-]: CALL R11 2 1 ; var11(var12)
     853 [-]: JUMPBACK L88 ; goto L88
L90: 854 [-]: GETUPVAL R12 14; var12 = upvalues[14]
     855 [-]: FASTCALL1 64 R12 L91; 
     856 [-]: GETIMPORT R11 21; var11 = 0x7B998233
     857 [-]: CALL R11 2 2 ; var11 = var11(var12)
L91: 858 [-]: JUMPIF R11 L92; goto L92 if var11
     859 [-]: GETUPVAL R11 14; var11 = upvalues[14]
     860 [-]: NAMECALL R11 R11 K76; var12 = var11; var11 = var11[0x2047CFE7]
     861 [-]: CALL R11 2 2 ; var11 = var11(var12)
     862 [-]: JUMPIF R11 L92; goto L92 if var11
     863 [-]: GETUPVAL R11 14; var11 = upvalues[14]
     864 [-]: NAMECALL R11 R11 K135; var12 = var11; var11 = var11[0x73901ACF]
     865 [-]: CALL R11 2 2 ; var11 = var11(var12)
     866 [-]: JUMPIFNOT R11 L93; goto L93 if not var11
L92: 867 [-]: LOADNIL R11  ; var11 = nil
     868 [-]: SETUPVAL R11 15; upvalues[11] = var15
     869 [-]: LOADNIL R11  ; var11 = nil
     870 [-]: SETUPVAL R11 14; upvalues[11] = var14
     871 [-]: LOADNIL R9   ; var9 = nil
L93: 872 [-]: GETIMPORT R11 4; var11 = _T
     873 [-]: LOADNIL R12  ; var12 = nil
     874 [-]: SETTABLEKS R12 R11 K148; var12["LichFinisherStabSequence"] = var11
L94: 875 [-]: GETUPVAL R12 14; var12 = upvalues[14]
     876 [-]: FASTCALL1 64 R12 L95; 
     877 [-]: GETIMPORT R11 21; var11 = 0x7B998233
     878 [-]: CALL R11 2 2 ; var11 = var11(var12)
L95: 879 [-]: JUMPIF R11 L96; goto L96 if var11
     880 [-]: GETUPVAL R11 14; var11 = upvalues[14]
     881 [-]: NAMECALL R11 R11 K76; var12 = var11; var11 = var11[0x2047CFE7]
     882 [-]: CALL R11 2 2 ; var11 = var11(var12)
     883 [-]: JUMPIFNOT R11 L100; goto L100 if not var11
L96: 884 [-]: GETIMPORT R11 1; var11 = 0x3D106989
     885 [-]: LOADK R12 K151; var12 = "Lich killed, unlocking door"
     886 [-]: CALL R11 2 1 ; var11(var12)
     887 [-]: GETUPVAL R13 9; var13 = upvalues[9]
     888 [-]: GETUPVAL R14 23; var14 = upvalues[23]
     889 [-]: GETTABLE R12 R13 R14; var12 = var13[var14]
     890 [-]: FASTCALL1 64 R12 L97; 
     891 [-]: GETIMPORT R11 21; var11 = 0x7B998233
     892 [-]: CALL R11 2 2 ; var11 = var11(var12)
L97: 893 [-]: JUMPIF R11 L99; goto L99 if var11
     894 [-]: GETUPVAL R12 23; var12 = upvalues[23]
     895 [-]: FASTCALL1 64 R12 L98; 
     896 [-]: GETIMPORT R11 21; var11 = 0x7B998233
     897 [-]: CALL R11 2 2 ; var11 = var11(var12)
L98: 898 [-]: JUMPIF R11 L99; goto L99 if var11
     899 [-]: GETUPVAL R12 9; var12 = upvalues[9]
     900 [-]: GETUPVAL R13 23; var13 = upvalues[23]
     901 [-]: GETTABLE R11 R12 R13; var11 = var12[var13]
     902 [-]: LOADN R13 3  ; var13 = 3
     903 [-]: NAMECALL R11 R11 K152; var12 = var11; var11 = var11[0xEA53C9C4]
     904 [-]: CALL R11 3 1 ; var11(var12, var13)
L99: 905 [-]: GETIMPORT R11 53; var11 = 0x33BDD652[0x9C1F3B5A]
     906 [-]: GETUPVAL R12 26; var12 = upvalues[26]
     907 [-]: LOADN R13 1  ; var13 = 1
     908 [-]: CALL R11 3 1 ; var11(var12, var13)
     909 [-]: GETUPVAL R12 36; var12 = upvalues[36]
     910 [-]: GETTABLEKS R11 R12 K153; var11 = var12[0xE80ADB64]
     911 [-]: LOADK R12 K154; var12 = "NemesisAssassinate"
     912 [-]: GETUPVAL R13 26; var13 = upvalues[26]
     913 [-]: CALL R11 3 1 ; var11(var12, var13)
     914 [-]: LOADNIL R11  ; var11 = nil
     915 [-]: SETUPVAL R11 15; upvalues[11] = var15
     916 [-]: LOADNIL R11  ; var11 = nil
     917 [-]: SETUPVAL R11 14; upvalues[11] = var14
     918 [-]: LOADNIL R9   ; var9 = nil
     919 [-]: JUMP L101    ; goto L101
L100: 920 [-]: JUMPIF R8 L101; goto L101 if var8
     921 [-]: GETUPVAL R11 14; var11 = upvalues[14]
     922 [-]: NAMECALL R11 R11 K155; var12 = var11; var11 = var11[0xC8442850]
     923 [-]: CALL R11 2 2 ; var11 = var11(var12)
     924 [-]: LOADK R12 K156; var12 = 0.5
     925 [-]: JUMPIFNOTLT R11 R12 L101; goto L101 if var11 >= var67590
     926 [-]: LOADB R8 1   ; var8 = true
     927 [-]: GETUPVAL R12 32; var12 = upvalues[32]
     928 [-]: GETTABLEKS R11 R12 K127; var11 = var12[0x48EA9DE9]
     929 [-]: GETIMPORT R12 6; var12 = 0x0469F296
     930 [-]: LOADK R13 K157; var13 = "RJAssHalfHealth"
     931 [-]: CALL R12 2 0 ; var12, ... = var12(var13)
     932 [-]: CALL R11 0 1 ; var11(var12, ...)
L101: 933 [-]: GETUPVAL R12 14; var12 = upvalues[14]
     934 [-]: FASTCALL1 64 R12 L102; 
     935 [-]: GETIMPORT R11 21; var11 = 0x7B998233
     936 [-]: CALL R11 2 2 ; var11 = var11(var12)
L102: 937 [-]: JUMPIFNOT R11 L109; goto L109 if not var11
     938 [-]: GETUPVAL R12 26; var12 = upvalues[26]
     939 [-]: LENGTH R11 R12; var11 = #var12
     940 [-]: LOADN R12 0  ; var12 = 0
     941 [-]: JUMPIFNOTLT R12 R11 L109; goto L109 if var12 >= var68385
     942 [-]: GETIMPORT R11 1; var11 = 0x3D106989
     943 [-]: LOADK R12 K158; var12 = "Looking for next lich"
     944 [-]: CALL R11 2 1 ; var11(var12)
     945 [-]: LOADB R8 0   ; var8 = false
     946 [-]: GETIMPORT R11 12; var11 = _T["faction"]
     947 [-]: GETUPVAL R12 1; var12 = upvalues[1]
     948 [-]: JUMPIFNOTEQ R11 R12 L103; goto L103 if var11 ~= var134204
     949 [-]: GETUPVAL R12 2; var12 = upvalues[2]
     950 [-]: GETTABLEKS R11 R12 K13; var11 = var12[0xA1DF01D6]
     951 [-]: LOADK R12 K14; var12 = "/Lotus/Language/Objectives/GenericAssassinate"
     952 [-]: CALL R11 2 1 ; var11(var12)
     953 [-]: JUMP L104    ; goto L104
L103: 954 [-]: GETUPVAL R12 2; var12 = upvalues[2]
     955 [-]: GETTABLEKS R11 R12 K13; var11 = var12[0xA1DF01D6]
     956 [-]: LOADK R12 K15; var12 = "/Lotus/Language/CorpusRailjack/AssassinateLoc"
     957 [-]: CALL R11 2 1 ; var11(var12)
L104: 958 [-]: NEWTABLE R11 0 0; var11 = {}
     959 [-]: SETUPVAL R11 18; upvalues[11] = var18
     960 [-]: GETUPVAL R11 22; var11 = upvalues[22]
     961 [-]: LOADB R12 0  ; var12 = false
     962 [-]: LOADB R13 1  ; var13 = true
     963 [-]: CALL R11 3 1 ; var11(var12, var13)
L105: 964 [-]: GETIMPORT R11 105; var11 = _T["NemesisManifestedEnemy"]
     965 [-]: JUMPIF R11 L107; goto L107 if var11
     966 [-]: GETUPVAL R11 27; var11 = upvalues[27]
     967 [-]: GETUPVAL R13 26; var13 = upvalues[26]
     968 [-]: GETTABLEN R12 R13 1; var12 = var13[1]
     969 [-]: CALL R11 2 2 ; var11 = var11(var12)
     970 [-]: JUMPIF R11 L106; goto L106 if var11
     971 [-]: GETIMPORT R11 1; var11 = 0x3D106989
     972 [-]: LOADK R12 K106; var12 = "Waiting on player's lich data, but they've disconnected. Trying to spawn lich for next player"
     973 [-]: CALL R11 2 1 ; var11(var12)
     974 [-]: GETUPVAL R11 22; var11 = upvalues[22]
     975 [-]: LOADB R12 0  ; var12 = false
     976 [-]: LOADB R13 1  ; var13 = true
     977 [-]: CALL R11 3 1 ; var11(var12, var13)
     978 [-]: GETUPVAL R12 26; var12 = upvalues[26]
     979 [-]: LENGTH R11 R12; var11 = #var12
     980 [-]: JUMPXEQKN R11 K62 L107; 
L106: 981 [-]: GETIMPORT R11 23; var11 = 0xCBD666E1
     982 [-]: LOADN R12 0  ; var12 = 0
     983 [-]: CALL R11 2 1 ; var11(var12)
     984 [-]: JUMPBACK L105; goto L105
L107: 985 [-]: GETUPVAL R12 26; var12 = upvalues[26]
     986 [-]: LENGTH R11 R12; var11 = #var12
     987 [-]: JUMPXEQKN R11 K62 L108 NOT; 
     988 [-]: GETIMPORT R11 1; var11 = 0x3D106989
     989 [-]: LOADK R12 K159; var12 = "No liches left to spawn, bailing to extraction"
     990 [-]: CALL R11 2 1 ; var11(var12)
     991 [-]: JUMP L110    ; goto L110
L108: 992 [-]: GETUPVAL R11 29; var11 = upvalues[29]
     993 [-]: CALL R11 1 1 ; var11()
     994 [-]: GETUPVAL R11 30; var11 = upvalues[30]
     995 [-]: MOVE R12 R1  ; var12 = var1
     996 [-]: CALL R11 2 1 ; var11(var12)
     997 [-]: LOADN R11 2  ; var11 = 2
     998 [-]: SETUPVAL R11 31; upvalues[11] = var31
     999 [-]: LOADB R6 0   ; var6 = false
     1000 [-]: LOADB R11 0  ; var11 = false
     1001 [-]: SETUPVAL R11 33; upvalues[11] = var33
     1002 [-]: LOADN R11 0  ; var11 = 0
     1003 [-]: SETUPVAL R11 17; upvalues[11] = var17
L109: 1004 [-]: GETIMPORT R11 23; var11 = 0xCBD666E1
     1005 [-]: LOADN R12 0  ; var12 = 0
     1006 [-]: CALL R11 2 1 ; var11(var12)
     1007 [-]: JUMPBACK L58 ; goto L58
L110: 1008 [-]: GETIMPORT R11 1; var11 = 0x3D106989
     1009 [-]: LOADK R12 K160; var12 = "Active liches loop done"
     1010 [-]: CALL R11 2 1 ; var11(var12)
     1011 [-]: GETUPVAL R12 2; var12 = upvalues[2]
     1012 [-]: GETTABLEKS R11 R12 K143; var11 = var12[0xBD3CE95D]
     1013 [-]: CALL R11 1 1 ; var11()
     1014 [-]: GETUPVAL R12 37; var12 = upvalues[37]
     1015 [-]: GETTABLEKS R11 R12 K161; var11 = var12[0xFC87A231]
     1016 [-]: LOADNIL R12  ; var12 = nil
     1017 [-]: LOADB R13 1  ; var13 = true
     1018 [-]: CALL R11 3 1 ; var11(var12, var13)
     1019 [-]: GETIMPORT R11 23; var11 = 0xCBD666E1
     1020 [-]: LOADN R12 2  ; var12 = 2
     1021 [-]: CALL R11 2 1 ; var11(var12)
     1022 [-]: NAMECALL R14 R0 K68; var15 = var0; var14 = var0[0x53C3399F]
     1023 [-]: CALL R14 2 2 ; var14 = var14(var15)
     1024 [-]: ADDK R13 R14 K136; var13 = var14 + 1
     1025 [-]: NAMECALL R11 R0 K72; var12 = var0; var11 = var0[0x05EEB9DB]
     1026 [-]: CALL R11 3 1 ; var11(var12, var13)
     1027 [-]: JUMPBACK L45 ; goto L45
L111: 1028 [-]: GETUPVAL R7 10; var7 = upvalues[10]
     1029 [-]: GETUPVAL R8 23; var8 = upvalues[23]
     1030 [-]: GETTABLE R6 R7 R8; var6 = var7[var8]
     1031 [-]: FASTCALL1 64 R6 L112; 
     1032 [-]: MOVE R8 R6   ; var8 = var6
     1033 [-]: GETIMPORT R7 21; var7 = 0x7B998233
     1034 [-]: CALL R7 2 2  ; var7 = var7(var8)
L112: 1035 [-]: JUMPIFNOT R7 L113; goto L113 if not var7
     1036 [-]: CLOSEUPVALS R3; 
     1037 [-]: RETURN R0 0  ; 
L113: 1038 [-]: GETIMPORT R9 46; var9 = 0x7ED0A956
     1039 [-]: LOADK R10 K162; var10 = "/Lotus/Types/Game/MarkerInfos/ExitMarkerInfo"
     1040 [-]: CALL R9 2 0  ; var9, ... = var9(var10)
     1041 [-]: NAMECALL R7 R6 K110; var8 = var6; var7 = var6[0xC9F6A7D7]
     1042 [-]: CALL R7 0 2  ; var7 = var7(var8, ...)
     1043 [-]: FASTCALL1 64 R7 L114; 
     1044 [-]: MOVE R9 R7   ; var9 = var7
     1045 [-]: GETIMPORT R8 21; var8 = 0x7B998233
     1046 [-]: CALL R8 2 2  ; var8 = var8(var9)
L114: 1047 [-]: JUMPIF R8 L115; goto L115 if var8
     1048 [-]: LOADB R10 1  ; var10 = true
     1049 [-]: LOADB R11 0  ; var11 = false
     1050 [-]: NAMECALL R8 R7 K163; var9 = var7; var8 = var7[0x2F8A0B83]
     1051 [-]: CALL R8 4 1  ; var8(var9, var10, var11)
     1052 [-]: LOADN R10 7  ; var10 = 7
     1053 [-]: NAMECALL R8 R7 K164; var9 = var7; var8 = var7[0x6BD6E2BE]
     1054 [-]: CALL R8 3 1  ; var8(var9, var10)
     1055 [-]: NAMECALL R8 R7 K146; var9 = var7; var8 = var7[0x383D2E7D]
     1056 [-]: CALL R8 2 1  ; var8(var9)
L115: 1057 [-]: GETIMPORT R8 28; var8 = 0x89326C93
     1058 [-]: GETIMPORT R10 6; var10 = 0x0469F296
     1059 [-]: LOADK R11 K165; var11 = "RJExtractionTrigger"
     1060 [-]: CALL R10 2 2 ; var10 = var10(var11)
     1061 [-]: NAMECALL R11 R6 K33; var12 = var6; var11 = var6[0xD1586535]
     1062 [-]: CALL R11 2 0 ; var11, ... = var11(var12)
     1063 [-]: NAMECALL R8 R8 K126; var9 = var8; var8 = var8[0xC7B81E8D]
     1064 [-]: CALL R8 0 2  ; var8 = var8(var9, ...)
     1065 [-]: FASTCALL1 64 R8 L116; 
     1066 [-]: MOVE R10 R8  ; var10 = var8
     1067 [-]: GETIMPORT R9 21; var9 = 0x7B998233
     1068 [-]: CALL R9 2 2  ; var9 = var9(var10)
L116: 1069 [-]: JUMPIFNOT R9 L124; goto L124 if not var9
     1070 [-]: GETIMPORT R9 1; var9 = 0x3D106989
     1071 [-]: LOADK R11 K166; var11 = "Could not find extraction trigger in room "
     1072 [-]: GETUPVAL R18 23; var18 = upvalues[23]
     1073 [-]: FASTCALL1 63 R18 L117; 
     1074 [-]: GETIMPORT R17 168; var17 = 0x64FB1586
     1075 [-]: CALL R17 2 2 ; var17 = var17(var18)
L117: 1076 [-]: MOVE R12 R17 ; var12 = var17
     1077 [-]: LOADK R13 K169; var13 = " reference action: "
     1078 [-]: NAMECALL R18 R6 K170; var19 = var6; var18 = var6[0xED4E0128]
     1079 [-]: CALL R18 2 0 ; var18, ... = var18(var19)
     1080 [-]: FASTCALL 63 L118; 
     1081 [-]: GETIMPORT R17 168; var17 = 0x64FB1586
     1082 [-]: CALL R17 0 2 ; var17 = var17(var18, ...)
L118: 1083 [-]: MOVE R14 R17 ; var14 = var17
     1084 [-]: LOADK R15 K171; var15 = ", pos: "
     1085 [-]: NAMECALL R17 R6 K33; var18 = var6; var17 = var6[0xD1586535]
     1086 [-]: CALL R17 2 0 ; var17, ... = var17(var18)
     1087 [-]: FASTCALL 63 L119; 
     1088 [-]: GETIMPORT R16 168; var16 = 0x64FB1586
     1089 [-]: CALL R16 0 2 ; var16 = var16(var17, ...)
L119: 1090 [-]: CONCAT R10 R11 R16; var10 = var11 .. var16
     1091 [-]: CALL R9 2 1  ; var9(var10)
     1092 [-]: NAMECALL R9 R6 K49; var10 = var6; var9 = var6[0xE79E7EF4]
     1093 [-]: CALL R9 2 2  ; var9 = var9(var10)
     1094 [-]: FASTCALL1 64 R9 L120; 
     1095 [-]: MOVE R11 R9  ; var11 = var9
     1096 [-]: GETIMPORT R10 21; var10 = 0x7B998233
     1097 [-]: CALL R10 2 2 ; var10 = var10(var11)
L120: 1098 [-]: JUMPIF R10 L122; goto L122 if var10
     1099 [-]: GETIMPORT R10 1; var10 = 0x3D106989
     1100 [-]: LOADK R12 K172; var12 = "Action zone "
     1101 [-]: NAMECALL R14 R9 K170; var15 = var9; var14 = var9[0xED4E0128]
     1102 [-]: CALL R14 2 0 ; var14, ... = var14(var15)
     1103 [-]: FASTCALL 63 L121; 
     1104 [-]: GETIMPORT R13 168; var13 = 0x64FB1586
     1105 [-]: CALL R13 0 2 ; var13 = var13(var14, ...)
L121: 1106 [-]: CONCAT R11 R12 R13; var11 = var12 .. var13
     1107 [-]: CALL R10 2 1 ; var10(var11)
     1108 [-]: JUMP L123    ; goto L123
L122: 1109 [-]: GETIMPORT R10 1; var10 = 0x3D106989
     1110 [-]: LOADK R11 K173; var11 = "NULL zone"
     1111 [-]: CALL R10 2 1 ; var10(var11)
L123: 1112 [-]: NAMECALL R10 R6 K146; var11 = var6; var10 = var6[0x383D2E7D]
     1113 [-]: CALL R10 2 1 ; var10(var11)
     1114 [-]: JUMP L125    ; goto L125
L124: 1115 [-]: NAMECALL R9 R8 K146; var10 = var8; var9 = var8[0x383D2E7D]
     1116 [-]: CALL R9 2 1  ; var9(var10)
L125: 1117 [-]: GETUPVAL R10 2; var10 = upvalues[2]
     1118 [-]: GETTABLEKS R9 R10 K174; var9 = var10[0xCC6A9F67]
     1119 [-]: CALL R9 1 1  ; var9()
     1120 [-]: GETIMPORT R9 57; var9 = 0xBE190284
     1121 [-]: GETUPVAL R11 38; var11 = upvalues[38]
     1122 [-]: LOADN R12 1  ; var12 = 1
     1123 [-]: NAMECALL R9 R9 K137; var10 = var9; var9 = var9[0x751F061D]
     1124 [-]: CALL R9 4 1  ; var9(var10, var11, var12)
     1125 [-]: GETIMPORT R9 57; var9 = 0xBE190284
     1126 [-]: GETUPVAL R11 24; var11 = upvalues[24]
     1127 [-]: NAMECALL R9 R9 K175; var10 = var9; var9 = var9[0xB9BFD47C]
     1128 [-]: CALL R9 3 1  ; var9(var10, var11)
     1129 [-]: GETIMPORT R9 1; var9 = 0x3D106989
     1130 [-]: LOADK R10 K176; var10 = "Ending"
     1131 [-]: CALL R9 2 1  ; var9(var10)
     1132 [-]: CLOSEUPVALS R3; 
     1133 [-]: RETURN R0 0  ; 



