; Name:            
; Defined at line: 1
; #Upvalues:       0
; #Parameters:     0
; Is_vararg:       1
; Max Stack Size:  48

       1 [-]: GETIMPORT R0 1; var0 = 0x0469F296
       2 [-]: LOADK R1 K2  ; var1 = "DragonHorsePhaseBabyCount"
       3 [-]: CALL R0 2 2  ; var0 = var0(var1)
       4 [-]: GETIMPORT R1 1; var1 = 0x0469F296
       5 [-]: LOADK R2 K3  ; var2 = "DragonShieldPhaseBabyCount"
       6 [-]: CALL R1 2 2  ; var1 = var1(var2)
       7 [-]: GETIMPORT R2 1; var2 = 0x0469F296
       8 [-]: LOADK R3 K4  ; var3 = "DragonAddPhaseTotalCount"
       9 [-]: CALL R2 2 2  ; var2 = var2(var3)
      10 [-]: GETIMPORT R3 1; var3 = 0x0469F296
      11 [-]: LOADK R4 K5  ; var4 = "GroundDragonPhase"
      12 [-]: CALL R3 2 2  ; var3 = var3(var4)
      13 [-]: GETIMPORT R4 1; var4 = 0x0469F296
      14 [-]: LOADK R5 K6  ; var5 = "GroundDragonSkipDebug"
      15 [-]: CALL R4 2 2  ; var4 = var4(var5)
      16 [-]: GETIMPORT R5 1; var5 = 0x0469F296
      17 [-]: LOADK R6 K7  ; var6 = "GroundDragonHealthIndex"
      18 [-]: CALL R5 2 2  ; var5 = var5(var6)
      19 [-]: GETIMPORT R6 1; var6 = 0x0469F296
      20 [-]: LOADK R7 K8  ; var7 = "GroundDragonPhaseIntroCinDone"
      21 [-]: CALL R6 2 2  ; var6 = var6(var7)
      22 [-]: GETIMPORT R7 1; var7 = 0x0469F296
      23 [-]: LOADK R8 K9  ; var8 = "KullervoQualifiedBonusDragonReward"
      24 [-]: CALL R7 2 2  ; var7 = var7(var8)
      25 [-]: GETIMPORT R8 1; var8 = 0x0469F296
      26 [-]: LOADK R9 K10 ; var9 = "ArchivistMarker"
      27 [-]: CALL R8 2 2  ; var8 = var8(var9)
      28 [-]: GETIMPORT R9 1; var9 = 0x0469F296
      29 [-]: LOADK R10 K11; var10 = "EnemyRadarDragonArena"
      30 [-]: CALL R9 2 2  ; var9 = var9(var10)
      31 [-]: GETIMPORT R10 1; var10 = 0x0469F296
      32 [-]: LOADK R11 K12; var11 = "SpawnArchivist"
      33 [-]: CALL R10 2 2 ; var10 = var10(var11)
      34 [-]: NEWTABLE R11 0 3; var11 = {}
      35 [-]: LOADN R12 4  ; var12 = 4
      36 [-]: LOADN R13 2  ; var13 = 2
      37 [-]: LOADN R14 1  ; var14 = 1
      38 [-]: SETLIST R11 R12 3 [1]; var11[1] = var12; var11[2] = var13; var11[3] = var14; var11[4] = var15; 
      39 [-]: NEWTABLE R12 0 3; var12 = {}
      40 [-]: LOADN R13 3  ; var13 = 3
      41 [-]: LOADN R14 2  ; var14 = 2
      42 [-]: LOADN R15 1  ; var15 = 1
      43 [-]: SETLIST R12 R13 3 [1]; var12[1] = var13; var12[2] = var14; var12[3] = var15; var12[4] = var16; 
      44 [-]: GETIMPORT R13 14; var13 = 0x2D0FAD09
      45 [-]: LOADK R14 K15; var14 = "Lotus.Scripts.Libs.ObjectiveText"
      46 [-]: CALL R13 2 2 ; var13 = var13(var14)
      47 [-]: GETIMPORT R14 14; var14 = 0x2D0FAD09
      48 [-]: LOADK R15 K16; var15 = "Lotus.Scripts.Libs.DuviriActivityLib"
      49 [-]: CALL R14 2 2 ; var14 = var14(var15)
      50 [-]: GETIMPORT R15 14; var15 = 0x2D0FAD09
      51 [-]: LOADK R16 K17; var16 = "Lotus.Scripts.Libs.DuviriStoryQuestLib"
      52 [-]: CALL R15 2 2 ; var15 = var15(var16)
      53 [-]: GETIMPORT R16 14; var16 = 0x2D0FAD09
      54 [-]: LOADK R17 K18; var17 = "Lotus.Scripts.Duviri.Encounters.DuviriRewardsLib"
      55 [-]: CALL R16 2 2 ; var16 = var16(var17)
      56 [-]: GETIMPORT R17 14; var17 = 0x2D0FAD09
      57 [-]: LOADK R18 K19; var18 = "Lotus.Interface.Libs.DuviriUtil"
      58 [-]: CALL R17 2 2 ; var17 = var17(var18)
      59 [-]: GETIMPORT R18 14; var18 = 0x2D0FAD09
      60 [-]: LOADK R19 K20; var19 = "Lotus.Interface.LotusUtilities"
      61 [-]: CALL R18 2 2 ; var18 = var18(var19)
      62 [-]: GETIMPORT R19 14; var19 = 0x2D0FAD09
      63 [-]: LOADK R20 K21; var20 = "Lotus.Scripts.Libs.TransmissionSet"
      64 [-]: CALL R19 2 2 ; var19 = var19(var20)
      65 [-]: DUPTABLE R20 24; 
      66 [-]: NEWTABLE R21 0 5; var21 = {}
      67 [-]: LOADN R22 0  ; var22 = 0
      68 [-]: LOADN R23 1  ; var23 = 1
      69 [-]: LOADN R24 2  ; var24 = 2
      70 [-]: LOADN R25 3  ; var25 = 3
      71 [-]: LOADN R26 4  ; var26 = 4
      72 [-]: SETLIST R21 R22 5 [1]; var21[1] = var22; var21[2] = var23; var21[3] = var24; var21[4] = var25; var21[5] = var26; var21[6] = var27; 
      73 [-]: SETTABLEKS R21 R20 K22; var21["phaseResult"] = var20
      74 [-]: NEWTABLE R21 0 5; var21 = {}
      75 [-]: LOADK R22 K25; var22 = "Normal"
      76 [-]: LOADK R23 K26; var23 = "Shield"
      77 [-]: LOADK R24 K27; var24 = "Horse"
      78 [-]: LOADK R25 K28; var25 = "Intro Cin"
      79 [-]: LOADK R26 K29; var26 = "Ending"
      80 [-]: SETLIST R21 R22 5 [1]; var21[1] = var22; var21[2] = var23; var21[3] = var24; var21[4] = var25; var21[5] = var26; var21[6] = var27; 
      81 [-]: SETTABLEKS R21 R20 K23; var21["text"] = var20
      82 [-]: NEWTABLE R21 4 0; var21 = {}
      83 [-]: GETIMPORT R22 1; var22 = 0x0469F296
      84 [-]: LOADK R23 K30; var23 = "DEFAULT_PHASE_RESPAWN"
      85 [-]: CALL R22 2 2 ; var22 = var22(var23)
      86 [-]: SETTABLEKS R22 R21 K31; var22["DEFAULT"] = var21
      87 [-]: GETIMPORT R22 1; var22 = 0x0469F296
      88 [-]: LOADK R23 K32; var23 = "HORSE_PHASE_RESPAWN"
      89 [-]: CALL R22 2 2 ; var22 = var22(var23)
      90 [-]: SETTABLEKS R22 R21 K33; var22["HORSE"] = var21
      91 [-]: GETIMPORT R22 1; var22 = 0x0469F296
      92 [-]: LOADK R23 K30; var23 = "DEFAULT_PHASE_RESPAWN"
      93 [-]: CALL R22 2 2 ; var22 = var22(var23)
      94 [-]: SETTABLEKS R22 R21 K34; var22["SHIELD"] = var21
      95 [-]: GETIMPORT R22 1; var22 = 0x0469F296
      96 [-]: LOADK R23 K30; var23 = "DEFAULT_PHASE_RESPAWN"
      97 [-]: CALL R22 2 2 ; var22 = var22(var23)
      98 [-]: SETTABLEKS R22 R21 K35; var22["HARPOON"] = var21
      99 [-]: NEWTABLE R22 0 0; var22 = {}
     100 [-]: GETIMPORT R23 37; var23 = 0xA421AF95
     101 [-]: LOADN R24 0  ; var24 = 0
     102 [-]: LOADN R25 0  ; var25 = 0
     103 [-]: LOADN R26 0  ; var26 = 0
     104 [-]: CALL R23 4 2 ; var23 = var23(var24, var25, var26)
     105 [-]: LOADB R24 0  ; var24 = false
     106 [-]: DUPCLOSURE R25 K38; 
     107 [-]: CAPTURE VAL R18; 
     108 [-]: DUPCLOSURE R26 K39; 
     109 [-]: CAPTURE VAL R22; 
     110 [-]: DUPCLOSURE R27 K40; 
     111 [-]: CAPTURE VAL R2; 
     112 [-]: CAPTURE VAL R13; 
     113 [-]: DUPCLOSURE R28 K41; 
     114 [-]: SETGLOBAL R28 K42; "HarpoonProjectileHit" = var28
     115 [-]: DUPCLOSURE R28 K43; 
     116 [-]: DUPCLOSURE R29 K44; 
     117 [-]: CAPTURE VAL R28; 
     118 [-]: DUPCLOSURE R30 K45; 
     119 [-]: CAPTURE VAL R29; 
     120 [-]: CAPTURE VAL R19; 
     121 [-]: CAPTURE VAL R0; 
     122 [-]: CAPTURE VAL R13; 
     123 [-]: CAPTURE VAL R3; 
     124 [-]: DUPCLOSURE R31 K46; 
     125 [-]: CAPTURE VAL R1; 
     126 [-]: CAPTURE VAL R13; 
     127 [-]: CAPTURE VAL R19; 
     128 [-]: DUPCLOSURE R32 K47; 
     129 [-]: CAPTURE VAL R3; 
     130 [-]: DUPCLOSURE R33 K48; 
     131 [-]: CAPTURE VAL R3; 
     132 [-]: CAPTURE VAL R28; 
     133 [-]: SETGLOBAL R33 K49; "HorseSpawnMonitor" = var33
     134 [-]: DUPCLOSURE R33 K50; 
     135 [-]: CAPTURE VAL R21; 
     136 [-]: NEWCLOSURE R34 P11; 
     137 [-]: CAPTURE VAL R33; 
     138 [-]: CAPTURE REF R23; 
     139 [-]: CAPTURE VAL R21; 
     140 [-]: CAPTURE VAL R3; 
     141 [-]: SETGLOBAL R34 K51; "NewRespawnMonitor" = var34
     142 [-]: DUPCLOSURE R34 K52; 
     143 [-]: DUPCLOSURE R35 K53; 
     144 [-]: DUPCLOSURE R36 K54; 
     145 [-]: CAPTURE VAL R18; 
     146 [-]: CAPTURE VAL R19; 
     147 [-]: DUPCLOSURE R37 K55; 
     148 [-]: CAPTURE VAL R10; 
     149 [-]: CAPTURE VAL R8; 
     150 [-]: DUPCLOSURE R38 K56; 
     151 [-]: DUPCLOSURE R39 K57; 
     152 [-]: CAPTURE VAL R7; 
     153 [-]: CAPTURE VAL R16; 
     154 [-]: CAPTURE VAL R37; 
     155 [-]: CAPTURE VAL R38; 
     156 [-]: SETGLOBAL R39 K58; "DragonChestOpened" = var39
     157 [-]: DUPCLOSURE R39 K59; 
     158 [-]: NEWCLOSURE R40 P19; 
     159 [-]: CAPTURE VAL R39; 
     160 [-]: CAPTURE VAL R3; 
     161 [-]: CAPTURE VAL R17; 
     162 [-]: CAPTURE VAL R19; 
     163 [-]: CAPTURE REF R24; 
     164 [-]: CAPTURE VAL R14; 
     165 [-]: CAPTURE VAL R16; 
     166 [-]: DUPCLOSURE R41 K60; 
     167 [-]: CAPTURE VAL R17; 
     168 [-]: DUPCLOSURE R42 K61; 
     169 [-]: CAPTURE VAL R28; 
     170 [-]: DUPCLOSURE R43 K62; 
     171 [-]: CAPTURE VAL R17; 
     172 [-]: CAPTURE VAL R5; 
     173 [-]: CAPTURE VAL R4; 
     174 [-]: CAPTURE VAL R3; 
     175 [-]: CAPTURE VAL R19; 
     176 [-]: CAPTURE VAL R35; 
     177 [-]: CAPTURE VAL R34; 
     178 [-]: CAPTURE VAL R31; 
     179 [-]: CAPTURE VAL R30; 
     180 [-]: CAPTURE VAL R42; 
     181 [-]: CAPTURE VAL R12; 
     182 [-]: CAPTURE VAL R11; 
     183 [-]: CAPTURE VAL R22; 
     184 [-]: CAPTURE VAL R39; 
     185 [-]: CAPTURE VAL R27; 
     186 [-]: CAPTURE VAL R36; 
     187 [-]: CAPTURE VAL R40; 
     188 [-]: DUPCLOSURE R44 K63; 
     189 [-]: DUPCLOSURE R45 K64; 
     190 [-]: DUPCLOSURE R46 K65; 
     191 [-]: CAPTURE VAL R41; 
     192 [-]: NEWCLOSURE R47 P26; 
     193 [-]: CAPTURE VAL R45; 
     194 [-]: CAPTURE VAL R46; 
     195 [-]: CAPTURE VAL R3; 
     196 [-]: CAPTURE VAL R6; 
     197 [-]: CAPTURE VAL R33; 
     198 [-]: CAPTURE VAL R5; 
     199 [-]: CAPTURE VAL R40; 
     200 [-]: CAPTURE VAL R37; 
     201 [-]: CAPTURE REF R24; 
     202 [-]: CAPTURE VAL R38; 
     203 [-]: CAPTURE VAL R4; 
     204 [-]: CAPTURE REF R23; 
     205 [-]: CAPTURE VAL R44; 
     206 [-]: CAPTURE VAL R9; 
     207 [-]: CAPTURE VAL R41; 
     208 [-]: CAPTURE VAL R43; 
     209 [-]: SETGLOBAL R47 K66; "SpawnDragon" = var47
     210 [-]: DUPCLOSURE R47 K67; 
     211 [-]: SETGLOBAL R47 K68; "SetLookAtTarget" = var47
     212 [-]: DUPCLOSURE R47 K69; 
     213 [-]: CAPTURE VAL R3; 
     214 [-]: SETGLOBAL R47 K70; "DoingSpecialPhase" = var47
     215 [-]: DUPCLOSURE R47 K71; 
     216 [-]: SETGLOBAL R47 K72; "ForceEquipReflectShield" = var47
     217 [-]: DUPCLOSURE R47 K73; 
     218 [-]: SETGLOBAL R47 K74; "OnWeakpointDamaged" = var47
     219 [-]: DUPCLOSURE R47 K75; 
     220 [-]: SETGLOBAL R47 K76; "GetOnHorseListener" = var47
     221 [-]: DUPCLOSURE R47 K77; 
     222 [-]: SETGLOBAL R47 K78; "MiniDragonSpeedCheck" = var47
     223 [-]: DUPCLOSURE R47 K79; 
     224 [-]: SETGLOBAL R47 K80; "WeakpointSpawned" = var47
     225 [-]: DUPCLOSURE R47 K81; 
     226 [-]: SETGLOBAL R47 K82; "GiveArchGun" = var47
     227 [-]: CLOSEUPVALS R23; 
     228 [-]: RETURN R0 0  ; 


; Name:            
; Defined at line: 161
; #Upvalues:       1
; #Parameters:     0
; Is_vararg:       0
; Max Stack Size:  2

       0 [-]: GETUPVAL R1 0; var1 = upvalues[0]
       1 [-]: GETTABLEKS R0 R1 K0; var0 = var1[0xA559EB32]
       2 [-]: CALL R0 1 1  ; var0()
       3 [-]: GETUPVAL R1 0; var1 = upvalues[0]
       4 [-]: GETTABLEKS R0 R1 K1; var0 = var1[0xFE0D9469]
       5 [-]: CALL R0 1 1  ; var0()
       6 [-]: RETURN R0 0  ; 


; Name:            
; Defined at line: 166
; #Upvalues:       1
; #Parameters:     1
; Is_vararg:       0
; Max Stack Size:  6

       0 [-]: LOADN R3 1   ; var3 = 1
       1 [-]: GETUPVAL R4 0; var4 = upvalues[0]
       2 [-]: LENGTH R1 R4 ; var1 = #var4
       3 [-]: LOADN R2 1   ; var2 = 1
       4 [-]: FORNPREP R1 L2; nforprep start - [escape at L2] -- var1 = iterator
L 0:   5 [-]: GETUPVAL R5 0; var5 = upvalues[0]
       6 [-]: GETTABLE R4 R5 R3; var4 = var5[var3]
       7 [-]: JUMPIFNOTEQ R4 R0 L1; goto L1 if var4 ~= var66587
       8 [-]: LOADB R4 1   ; var4 = true
       9 [-]: RETURN R4 1  ; 
L 1:  10 [-]: FORNLOOP R1 L0; nforloop end - iterate + goto L0
L 2:  11 [-]: LOADB R1 0   ; var1 = false
      12 [-]: RETURN R1 1  ; 


; Name:            
; Defined at line: 176
; #Upvalues:       2
; #Parameters:     3
; Is_vararg:       0
; Max Stack Size:  25

       0 [-]: GETIMPORT R3 1; var3 = 0x89326C93
       1 [-]: NAMECALL R3 R3 K2; var4 = var3; var3 = var3[0x29EF273D]
       2 [-]: CALL R3 2 2  ; var3 = var3(var4)
       3 [-]: NAMECALL R3 R3 K3; var4 = var3; var3 = var3[0x66905CB0]
       4 [-]: CALL R3 2 2  ; var3 = var3(var4)
       5 [-]: GETIMPORT R4 1; var4 = 0x89326C93
       6 [-]: GETIMPORT R6 5; var6 = 0x1E155F36
       7 [-]: NAMECALL R4 R4 K6; var5 = var4; var4 = var4[0xC7FCADA9]
       8 [-]: CALL R4 3 2  ; var4 = var4(var5, var6)
       9 [-]: GETIMPORT R5 1; var5 = 0x89326C93
      10 [-]: NAMECALL R5 R5 K7; var6 = var5; var5 = var5[0x8B5B1F58]
      11 [-]: CALL R5 2 2  ; var5 = var5(var6)
      12 [-]: LOADN R8 3   ; var8 = 3
      13 [-]: LENGTH R10 R5; var10 = #var5
      14 [-]: SUBK R9 R10 K8; var9 = var10 - 1
      15 [-]: MUL R7 R8 R9 ; var7 = var8 * var9
      16 [-]: ADD R6 R1 R7 ; var6 = var1 + var7
      17 [-]: GETIMPORT R8 10; var8 = 0xBE190284
      18 [-]: GETUPVAL R10 0; var10 = upvalues[0]
      19 [-]: NAMECALL R8 R8 K11; var9 = var8; var8 = var8[0x0EB34C69]
      20 [-]: CALL R8 3 2  ; var8 = var8(var9, var10)
      21 [-]: FASTCALL1 62 R8 L0; 
      22 [-]: GETIMPORT R7 13; var7 = 0x7B998233
      23 [-]: CALL R7 2 2  ; var7 = var7(var8)
L 0:  24 [-]: JUMPIFNOT R7 L1; goto L1 if not var7
      25 [-]: GETIMPORT R7 10; var7 = 0xBE190284
      26 [-]: GETUPVAL R9 0; var9 = upvalues[0]
      27 [-]: LOADN R10 0  ; var10 = 0
      28 [-]: NAMECALL R7 R7 K14; var8 = var7; var7 = var7[0x751F061D]
      29 [-]: CALL R7 4 1  ; var7(var8, var9, var10)
L 1:  30 [-]: GETIMPORT R7 10; var7 = 0xBE190284
      31 [-]: GETUPVAL R9 0; var9 = upvalues[0]
      32 [-]: NAMECALL R7 R7 K11; var8 = var7; var7 = var7[0x0EB34C69]
      33 [-]: CALL R7 3 2  ; var7 = var7(var8, var9)
      34 [-]: GETUPVAL R9 1; var9 = upvalues[1]
      35 [-]: GETTABLEKS R8 R9 K15; var8 = var9[0xEA753E99]
      36 [-]: LOADK R9 K16 ; var9 = "/Lotus/Language/Duviri/DuviriDragonObjectiveDax"
      37 [-]: MOVE R10 R7  ; var10 = var7
      38 [-]: MOVE R11 R6  ; var11 = var6
      39 [-]: CALL R8 4 1  ; var8(var9, var10, var11)
      40 [-]: GETIMPORT R8 18; var8 = 0xFFB56934
      41 [-]: GETIMPORT R10 10; var10 = 0xBE190284
      42 [-]: NAMECALL R10 R10 K19; var11 = var10; var10 = var10[0xEF893AEC]
      43 [-]: CALL R10 2 2 ; var10 = var10(var11)
      44 [-]: GETTABLEKS R9 R10 K20; var9 = var10["tier"]
      45 [-]: LOADN R10 0  ; var10 = 0
      46 [-]: JUMPIFNOTLT R10 R9 L2; goto L2 if var10 >= var1443918
      47 [-]: GETIMPORT R8 22; var8 = 0x742D2745
L 2:  48 [-]: DIVK R9 R6 K23; var9 = var6 / 2
      49 [-]: NEWTABLE R10 0 0; var10 = {}
      50 [-]: LOADN R11 0  ; var11 = 0
      51 [-]: LOADN R12 0  ; var12 = 0
      52 [-]: LOADN R13 0  ; var13 = 0
      53 [-]: LOADN R14 0  ; var14 = 0
L 3:  54 [-]: JUMPIFNOTLT R7 R6 L15; goto L15 if var7 >= var659278
      55 [-]: GETIMPORT R15 10; var15 = 0xBE190284
      56 [-]: GETUPVAL R17 0; var17 = upvalues[0]
      57 [-]: NAMECALL R15 R15 K11; var16 = var15; var15 = var15[0x0EB34C69]
      58 [-]: CALL R15 3 2 ; var15 = var15(var16, var17)
      59 [-]: MOVE R7 R15  ; var7 = var15
      60 [-]: GETUPVAL R16 1; var16 = upvalues[1]
      61 [-]: GETTABLEKS R15 R16 K24; var15 = var16[0xF3928F38]
      62 [-]: MOVE R16 R7  ; var16 = var7
      63 [-]: MOVE R17 R6  ; var17 = var6
      64 [-]: CALL R15 3 1 ; var15(var16, var17)
      65 [-]: LENGTH R15 R10; var15 = #var10
      66 [-]: JUMPIFNOTLT R15 R9 L9; goto L9 if var15 >= var6687500
      67 [-]: JUMPIFNOTLT R11 R6 L9; goto L9 if var11 >= var6557196
      68 [-]: JUMPIFNOTLT R14 R13 L9; goto L9 if var14 >= var3854
      69 [-]: LOADNIL R15  ; var15 = nil
      70 [-]: LOADN R16 3  ; var16 = 3
      71 [-]: JUMPIFNOTLT R16 R12 L4; goto L4 if var16 >= var1708110
      72 [-]: GETIMPORT R16 26; var16 = 0x45C8CA19
      73 [-]: GETIMPORT R17 28; var17 = 0x0C5E62F9
      74 [-]: LOADN R18 1  ; var18 = 1
      75 [-]: GETIMPORT R20 26; var20 = 0x45C8CA19
      76 [-]: LENGTH R19 R20; var19 = #var20
      77 [-]: CALL R17 3 2 ; var17 = var17(var18, var19)
      78 [-]: GETTABLE R15 R16 R17; var15 = var16[var17]
      79 [-]: LOADN R12 0  ; var12 = 0
      80 [-]: JUMP L5      ; goto L5
L 4:  81 [-]: GETIMPORT R16 30; var16 = 0x98CCE1BB
      82 [-]: GETIMPORT R17 28; var17 = 0x0C5E62F9
      83 [-]: LOADN R18 1  ; var18 = 1
      84 [-]: GETIMPORT R20 30; var20 = 0x98CCE1BB
      85 [-]: LENGTH R19 R20; var19 = #var20
      86 [-]: CALL R17 3 2 ; var17 = var17(var18, var19)
      87 [-]: GETTABLE R15 R16 R17; var15 = var16[var17]
L 5:  88 [-]: FASTCALL1 62 R15 L6; 
      89 [-]: MOVE R17 R15 ; var17 = var15
      90 [-]: GETIMPORT R16 13; var16 = 0x7B998233
      91 [-]: CALL R16 2 2 ; var16 = var16(var17)
L 6:  92 [-]: JUMPIF R16 L9; goto L9 if var16
      93 [-]: MOVE R18 R15 ; var18 = var15
      94 [-]: GETIMPORT R20 28; var20 = 0x0C5E62F9
      95 [-]: LOADN R21 1  ; var21 = 1
      96 [-]: LENGTH R22 R4; var22 = #var4
      97 [-]: CALL R20 3 2 ; var20 = var20(var21, var22)
      98 [-]: GETTABLE R19 R4 R20; var19 = var4[var20]
      99 [-]: LOADN R20 3  ; var20 = 3
     100 [-]: GETIMPORT R21 32; var21 = 0x0469F296
     101 [-]: LOADK R22 K33; var22 = "RandomTeam"
     102 [-]: CALL R21 2 2 ; var21 = var21(var22)
     103 [-]: MOVE R22 R8  ; var22 = var8
     104 [-]: NAMECALL R16 R3 K34; var17 = var3; var16 = var3[0x2883E796]
     105 [-]: CALL R16 7 2 ; var16 = var16(var17, var18, var19, var20, var21, var22)
     106 [-]: NAMECALL R17 R16 K35; var18 = var16; var17 = var16[0x9E21E394]
     107 [-]: CALL R17 2 1 ; var17(var18)
     108 [-]: NAMECALL R17 R16 K36; var18 = var16; var17 = var16[0xBB610E5B]
     109 [-]: CALL R17 2 2 ; var17 = var17(var18)
     110 [-]: FASTCALL1 62 R17 L7; 
     111 [-]: MOVE R19 R17 ; var19 = var17
     112 [-]: GETIMPORT R18 13; var18 = 0x7B998233
     113 [-]: CALL R18 2 2 ; var18 = var18(var19)
L 7: 114 [-]: JUMPIF R18 L9; goto L9 if var18
     115 [-]: GETIMPORT R18 1; var18 = 0x89326C93
     116 [-]: GETIMPORT R20 38; var20 = 0xF69297EE
     117 [-]: NAMECALL R21 R17 K39; var22 = var17; var21 = var17[0xD1586535]
     118 [-]: CALL R21 2 2 ; var21 = var21(var22)
     119 [-]: GETIMPORT R22 41; var22 = ZERO_ROTATION
     120 [-]: NAMECALL R18 R18 K42; var19 = var18; var18 = var18[0x05909209]
     121 [-]: CALL R18 5 1 ; var18(var19, var20, var21, var22)
     122 [-]: NAMECALL R18 R17 K43; var19 = var17; var18 = var17[0x1AC1655C]
     123 [-]: CALL R18 2 2 ; var18 = var18(var19)
     124 [-]: LOADB R20 0  ; var20 = false
     125 [-]: NAMECALL R18 R18 K44; var19 = var18; var18 = var18[0x35577788]
     126 [-]: CALL R18 3 1 ; var18(var19, var20)
     127 [-]: GETIMPORT R20 46; var20 = 0x29988258
     128 [-]: NAMECALL R18 R17 K47; var19 = var17; var18 = var17[0x22C4E9DD]
     129 [-]: CALL R18 3 1 ; var18(var19, var20)
     130 [-]: FASTCALL2 52 R10 R17 L8; 
     131 [-]: MOVE R19 R10 ; var19 = var10
     132 [-]: MOVE R20 R17 ; var20 = var17
     133 [-]: GETIMPORT R18 50; var18 = 0x33BDD652[0x23D5322F]
     134 [-]: CALL R18 3 1 ; var18(var19, var20)
L 8: 135 [-]: ADDK R12 R12 K8; var12 = var12 + 1
     136 [-]: ADDK R11 R11 K8; var11 = var11 + 1
     137 [-]: GETIMPORT R18 52; var18 = 0xDD6E4CF8
     138 [-]: LOADN R19 1  ; var19 = 1
     139 [-]: LOADN R20 3  ; var20 = 3
     140 [-]: CALL R18 3 2 ; var18 = var18(var19, var20)
     141 [-]: ADD R14 R13 R18; var14 = var13 + var18
L 9: 142 [-]: LENGTH R17 R10; var17 = #var10
     143 [-]: LOADN R15 1  ; var15 = 1
     144 [-]: LOADN R16 -1 ; var16 = -1
     145 [-]: FORNPREP R15 L14; nforprep start - [escape at L14] -- var15 = iterator
L10: 146 [-]: GETTABLE R19 R10 R17; var19 = var10[var17]
     147 [-]: FASTCALL1 62 R19 L11; 
     148 [-]: GETIMPORT R18 13; var18 = 0x7B998233
     149 [-]: CALL R18 2 2 ; var18 = var18(var19)
L11: 150 [-]: JUMPIF R18 L12; goto L12 if var18
     151 [-]: GETTABLE R18 R10 R17; var18 = var10[var17]
     152 [-]: NAMECALL R18 R18 K53; var19 = var18; var18 = var18[0x2047CFE7]
     153 [-]: CALL R18 2 2 ; var18 = var18(var19)
     154 [-]: JUMPIFNOT R18 L13; goto L13 if not var18
L12: 155 [-]: GETIMPORT R18 55; var18 = 0x33BDD652[0x9C1F3B5A]
     156 [-]: MOVE R19 R10 ; var19 = var10
     157 [-]: MOVE R20 R17 ; var20 = var17
     158 [-]: CALL R18 3 1 ; var18(var19, var20)
     159 [-]: GETIMPORT R18 10; var18 = 0xBE190284
     160 [-]: GETUPVAL R20 0; var20 = upvalues[0]
     161 [-]: GETIMPORT R22 10; var22 = 0xBE190284
     162 [-]: GETUPVAL R24 0; var24 = upvalues[0]
     163 [-]: NAMECALL R22 R22 K11; var23 = var22; var22 = var22[0x0EB34C69]
     164 [-]: CALL R22 3 2 ; var22 = var22(var23, var24)
     165 [-]: ADDK R21 R22 K8; var21 = var22 + 1
     166 [-]: NAMECALL R18 R18 K14; var19 = var18; var18 = var18[0x751F061D]
     167 [-]: CALL R18 4 1 ; var18(var19, var20, var21)
L13: 168 [-]: FORNLOOP R15 L10; nforloop end - iterate + goto L10
L14: 169 [-]: GETIMPORT R15 57; var15 = 0xCBD666E1
     170 [-]: LOADN R16 0  ; var16 = 0
     171 [-]: CALL R15 2 1 ; var15(var16)
     172 [-]: GETIMPORT R15 59; var15 = 0x67652851
     173 [-]: CALL R15 1 2 ; var15 = var15()
     174 [-]: ADD R13 R13 R15; var13 = var13 + var15
     175 [-]: JUMPBACK L3  ; goto L3
L15: 176 [-]: GETUPVAL R16 1; var16 = upvalues[1]
     177 [-]: GETTABLEKS R15 R16 K60; var15 = var16[0xBD3CE95D]
     178 [-]: CALL R15 1 1 ; var15()
     179 [-]: GETIMPORT R15 10; var15 = 0xBE190284
     180 [-]: GETUPVAL R17 0; var17 = upvalues[0]
     181 [-]: LOADN R18 0  ; var18 = 0
     182 [-]: NAMECALL R15 R15 K14; var16 = var15; var15 = var15[0x751F061D]
     183 [-]: CALL R15 4 1 ; var15(var16, var17, var18)
     184 [-]: RETURN R0 0  ; 


; Name:            
; Defined at line: 251
; #Upvalues:       0
; #Parameters:     1
; Is_vararg:       0
; Max Stack Size:  6

       0 [-]: NAMECALL R1 R0 K0; var2 = var0; var1 = var0[0x2B54251B]
       1 [-]: CALL R1 2 2  ; var1 = var1(var2)
       2 [-]: FASTCALL1 62 R1 L0; 
       3 [-]: MOVE R3 R1   ; var3 = var1
       4 [-]: GETIMPORT R2 2; var2 = 0x7B998233
       5 [-]: CALL R2 2 2  ; var2 = var2(var3)
L 0:   6 [-]: JUMPIF R2 L2 ; goto L2 if var2
       7 [-]: NAMECALL R2 R1 K3; var3 = var1; var2 = var1[0x28E744CF]
       8 [-]: CALL R2 2 2  ; var2 = var2(var3)
       9 [-]: FASTCALL1 62 R2 L1; 
      10 [-]: MOVE R4 R2   ; var4 = var2
      11 [-]: GETIMPORT R3 2; var3 = 0x7B998233
      12 [-]: CALL R3 2 2  ; var3 = var3(var4)
L 1:  13 [-]: JUMPIF R3 L2 ; goto L2 if var3
      14 [-]: GETIMPORT R5 5; var5 = 0x70C8BB8C
      15 [-]: NAMECALL R3 R2 K6; var4 = var2; var3 = var2[0xF2DEAF69]
      16 [-]: CALL R3 3 2  ; var3 = var3(var4, var5)
      17 [-]: JUMPIFNOT R3 L2; goto L2 if not var3
      18 [-]: NAMECALL R3 R2 K7; var4 = var2; var3 = var2[0xA2880940]
      19 [-]: CALL R3 2 1  ; var3(var4)
L 2:  20 [-]: RETURN R0 0  ; 


; Name:            
; Defined at line: 310
; #Upvalues:       0
; #Parameters:     3
; Is_vararg:       0
; Max Stack Size:  14

       0 [-]: GETIMPORT R3 1; var3 = 0x89326C93
       1 [-]: NAMECALL R3 R3 K2; var4 = var3; var3 = var3[0x29EF273D]
       2 [-]: CALL R3 2 2  ; var3 = var3(var4)
       3 [-]: NAMECALL R4 R0 K3; var5 = var0; var4 = var0[0x62C81B76]
       4 [-]: CALL R4 2 2  ; var4 = var4(var5)
       5 [-]: LOADN R7 6   ; var7 = 6
       6 [-]: LOADN R8 3   ; var8 = 3
       7 [-]: NAMECALL R5 R4 K4; var6 = var4; var5 = var4[0xB61ABFD2]
       8 [-]: CALL R5 4 2  ; var5 = var5(var6, var7, var8)
       9 [-]: FASTCALL1 62 R5 L0; 
      10 [-]: MOVE R7 R5   ; var7 = var5
      11 [-]: GETIMPORT R6 6; var6 = 0x7B998233
      12 [-]: CALL R6 2 2  ; var6 = var6(var7)
L 0:  13 [-]: JUMPIF R6 L7 ; goto L7 if var6
      14 [-]: NAMECALL R6 R5 K7; var7 = var5; var6 = var5[0x68D708A7]
      15 [-]: CALL R6 2 2  ; var6 = var6(var7)
      16 [-]: GETIMPORT R9 9; var9 = 0x7837AA40
      17 [-]: MOVE R10 R1  ; var10 = var1
      18 [-]: MOVE R11 R2  ; var11 = var2
      19 [-]: NAMECALL R7 R3 K10; var8 = var3; var7 = var3[0x6CD833C5]
      20 [-]: CALL R7 5 2  ; var7 = var7(var8, var9, var10, var11)
      21 [-]: GETIMPORT R8 12; var8 = 0xCBD666E1
      22 [-]: LOADN R9 0   ; var9 = 0
      23 [-]: CALL R8 2 1  ; var8(var9)
      24 [-]: NAMECALL R8 R7 K13; var9 = var7; var8 = var7[0xBB610E5B]
      25 [-]: CALL R8 2 2  ; var8 = var8(var9)
      26 [-]: FASTCALL1 62 R8 L1; 
      27 [-]: MOVE R10 R8  ; var10 = var8
      28 [-]: GETIMPORT R9 6; var9 = 0x7B998233
      29 [-]: CALL R9 2 2  ; var9 = var9(var10)
L 1:  30 [-]: JUMPIF R9 L4 ; goto L4 if var9
      31 [-]: NAMECALL R9 R8 K14; var10 = var8; var9 = var8[0x1AC1655C]
      32 [-]: CALL R9 2 2  ; var9 = var9(var10)
      33 [-]: LOADN R11 1  ; var11 = 1
      34 [-]: LOADN R12 1  ; var12 = 1
      35 [-]: NAMECALL R9 R9 K15; var10 = var9; var9 = var9[0x4A9DA24C]
      36 [-]: CALL R9 4 1  ; var9(var10, var11, var12)
      37 [-]: LOADB R11 0  ; var11 = false
      38 [-]: NAMECALL R9 R8 K16; var10 = var8; var9 = var8[0x2ABC8ECD]
      39 [-]: CALL R9 3 1  ; var9(var10, var11)
      40 [-]: NAMECALL R9 R8 K17; var10 = var8; var9 = var8[0xDE321E6F]
      41 [-]: CALL R9 2 2  ; var9 = var9(var10)
      42 [-]: LOADN R12 3  ; var12 = 3
      43 [-]: NAMECALL R10 R9 K18; var11 = var9; var10 = var9[0xE85A2361]
      44 [-]: CALL R10 3 2 ; var10 = var10(var11, var12)
      45 [-]: FASTCALL1 62 R10 L2; 
      46 [-]: MOVE R12 R10 ; var12 = var10
      47 [-]: GETIMPORT R11 6; var11 = 0x7B998233
      48 [-]: CALL R11 2 2 ; var11 = var11(var12)
L 2:  49 [-]: JUMPIF R11 L3; goto L3 if var11
      50 [-]: MOVE R13 R8  ; var13 = var8
      51 [-]: NAMECALL R11 R10 K19; var12 = var10; var11 = var10[0xD70B80BC]
      52 [-]: CALL R11 3 1 ; var11(var12, var13)
      53 [-]: MOVE R13 R6  ; var13 = var6
      54 [-]: NAMECALL R11 R10 K20; var12 = var10; var11 = var10[0xAA041663]
      55 [-]: CALL R11 3 1 ; var11(var12, var13)
      56 [-]: MOVE R13 R6  ; var13 = var6
      57 [-]: NAMECALL R11 R10 K21; var12 = var10; var11 = var10[0xDEFFCEC7]
      58 [-]: CALL R11 3 1 ; var11(var12, var13)
      59 [-]: NAMECALL R11 R10 K22; var12 = var10; var11 = var10[0x8F8353C4]
      60 [-]: CALL R11 2 1 ; var11(var12)
L 3:  61 [-]: MOVE R13 R8  ; var13 = var8
      62 [-]: NAMECALL R11 R6 K23; var12 = var6; var11 = var6[0x61B59A83]
      63 [-]: CALL R11 3 1 ; var11(var12, var13)
L 4:  64 [-]: GETIMPORT R9 12; var9 = 0xCBD666E1
      65 [-]: LOADN R10 0  ; var10 = 0
      66 [-]: CALL R9 2 1  ; var9(var10)
      67 [-]: FASTCALL1 62 R8 L5; 
      68 [-]: MOVE R10 R8  ; var10 = var8
      69 [-]: GETIMPORT R9 6; var9 = 0x7B998233
      70 [-]: CALL R9 2 2  ; var9 = var9(var10)
L 5:  71 [-]: JUMPIF R9 L6 ; goto L6 if var9
      72 [-]: GETIMPORT R11 25; var11 = 0x0469F296
      73 [-]: LOADK R12 K26; var12 = "MOUNT_ACTION"
      74 [-]: CALL R11 2 0 ; var11, ... = var11(var12)
      75 [-]: NAMECALL R9 R8 K27; var10 = var8; var9 = var8[0xB2532845]
      76 [-]: CALL R9 0 1  ; var9(var10, ...)
      77 [-]: LOADB R11 1  ; var11 = true
      78 [-]: NAMECALL R9 R8 K16; var10 = var8; var9 = var8[0x2ABC8ECD]
      79 [-]: CALL R9 3 1  ; var9(var10, var11)
      80 [-]: LOADN R11 0  ; var11 = 0
      81 [-]: NAMECALL R9 R8 K28; var10 = var8; var9 = var8[0x66472BF5]
      82 [-]: CALL R9 3 1  ; var9(var10, var11)
      83 [-]: GETIMPORT R11 30; var11 = 0xA0A04438
      84 [-]: GETIMPORT R12 32; var12 = EMPTY_SYMBOL
      85 [-]: NAMECALL R9 R8 K33; var10 = var8; var9 = var8[0x47901F07]
      86 [-]: CALL R9 4 1  ; var9(var10, var11, var12)
L 6:  87 [-]: RETURN R8 1  ; 
L 7:  88 [-]: LOADNIL R6   ; var6 = nil
      89 [-]: RETURN R6 1  ; 


; Name:            
; Defined at line: 352
; #Upvalues:       1
; #Parameters:     1
; Is_vararg:       0
; Max Stack Size:  11

       0 [-]: GETIMPORT R1 1; var1 = 0x89326C93
       1 [-]: NAMECALL R1 R1 K2; var2 = var1; var1 = var1[0x7D108DDB]
       2 [-]: CALL R1 2 2  ; var1 = var1(var2)
       3 [-]: LOADN R4 1   ; var4 = 1
       4 [-]: LENGTH R2 R1 ; var2 = #var1
       5 [-]: LOADN R3 1   ; var3 = 1
       6 [-]: FORNPREP R2 L5; nforprep start - [escape at L5] -- var2 = iterator
L 0:   7 [-]: GETTABLE R5 R1 R4; var5 = var1[var4]
       8 [-]: FASTCALL1 62 R5 L1; 
       9 [-]: MOVE R7 R5   ; var7 = var5
      10 [-]: GETIMPORT R6 4; var6 = 0x7B998233
      11 [-]: CALL R6 2 2  ; var6 = var6(var7)
L 1:  12 [-]: JUMPIF R6 L4 ; goto L4 if var6
      13 [-]: NAMECALL R6 R5 K5; var7 = var5; var6 = var5[0xBB610E5B]
      14 [-]: CALL R6 2 2  ; var6 = var6(var7)
      15 [-]: GETIMPORT R8 7; var8 = gLotusVehicleAvatarType
      16 [-]: NAMECALL R6 R6 K8; var7 = var6; var6 = var6[0xF2DEAF69]
      17 [-]: CALL R6 3 2  ; var6 = var6(var7, var8)
      18 [-]: JUMPIF R6 L4 ; goto L4 if var6
      19 [-]: FASTCALL1 62 R0 L2; 
      20 [-]: MOVE R7 R0   ; var7 = var0
      21 [-]: GETIMPORT R6 4; var6 = 0x7B998233
      22 [-]: CALL R6 2 2  ; var6 = var6(var7)
L 2:  23 [-]: JUMPIF R6 L4 ; goto L4 if var6
      24 [-]: LENGTH R6 R0 ; var6 = #var0
      25 [-]: JUMPIFNOTLE R4 R6 L4; goto L4 if var4 > var67110711
      26 [-]: GETTABLE R7 R0 R4; var7 = var0[var4]
      27 [-]: FASTCALL1 62 R7 L3; 
      28 [-]: GETIMPORT R6 4; var6 = 0x7B998233
      29 [-]: CALL R6 2 2  ; var6 = var6(var7)
L 3:  30 [-]: JUMPIF R6 L4 ; goto L4 if var6
      31 [-]: GETUPVAL R6 0; var6 = upvalues[0]
      32 [-]: MOVE R7 R5   ; var7 = var5
      33 [-]: GETTABLE R8 R0 R4; var8 = var0[var4]
      34 [-]: NAMECALL R8 R8 K9; var9 = var8; var8 = var8[0xD1586535]
      35 [-]: CALL R8 2 2  ; var8 = var8(var9)
      36 [-]: GETTABLE R9 R0 R4; var9 = var0[var4]
      37 [-]: NAMECALL R9 R9 K10; var10 = var9; var9 = var9[0xCB3851B8]
      38 [-]: CALL R9 2 0  ; var9, ... = var9(var10)
      39 [-]: CALL R6 0 1  ; var6(var7, ...)
L 4:  40 [-]: FORNLOOP R2 L0; nforloop end - iterate + goto L0
L 5:  41 [-]: RETURN R0 0  ; 


; Name:            
; Defined at line: 364
; #Upvalues:       5
; #Parameters:     2
; Is_vararg:       0
; Max Stack Size:  38

       0 [-]: GETIMPORT R2 1; var2 = 0x89326C93
       1 [-]: GETIMPORT R4 3; var4 = 0xC776E621
       2 [-]: NAMECALL R2 R2 K4; var3 = var2; var2 = var2[0x46A0EBF5]
       3 [-]: CALL R2 3 2  ; var2 = var2(var3, var4)
       4 [-]: LOADB R5 0   ; var5 = false
       5 [-]: LOADB R6 0   ; var6 = false
       6 [-]: NAMECALL R3 R2 K5; var4 = var2; var3 = var2[0x768274D6]
       7 [-]: CALL R3 4 1  ; var3(var4, var5, var6)
       8 [-]: GETIMPORT R3 1; var3 = 0x89326C93
       9 [-]: GETIMPORT R5 7; var5 = 0x49ACADEB
      10 [-]: NAMECALL R3 R3 K8; var4 = var3; var3 = var3[0xC7FCADA9]
      11 [-]: CALL R3 3 2  ; var3 = var3(var4, var5)
      12 [-]: GETIMPORT R4 1; var4 = 0x89326C93
      13 [-]: NAMECALL R4 R4 K9; var5 = var4; var4 = var4[0x8B5B1F58]
      14 [-]: CALL R4 2 2  ; var4 = var4(var5)
      15 [-]: GETTABLEN R6 R4 1; var6 = var4[1]
      16 [-]: FASTCALL1 62 R6 L0; 
      17 [-]: GETIMPORT R5 11; var5 = 0x7B998233
      18 [-]: CALL R5 2 2  ; var5 = var5(var6)
L 0:  19 [-]: JUMPIF R5 L1 ; goto L1 if var5
      20 [-]: GETTABLEN R5 R4 1; var5 = var4[1]
      21 [-]: GETIMPORT R7 13; var7 = 0x0469F296
      22 [-]: LOADK R8 K14 ; var8 = "GetOnHorseListener"
      23 [-]: CALL R7 2 2  ; var7 = var7(var8)
      24 [-]: LOADB R8 0   ; var8 = false
      25 [-]: NAMECALL R5 R5 K15; var6 = var5; var5 = var5[0xD5F7912B]
      26 [-]: CALL R5 4 1  ; var5(var6, var7, var8)
L 1:  27 [-]: GETUPVAL R5 0; var5 = upvalues[0]
      28 [-]: MOVE R6 R3   ; var6 = var3
      29 [-]: CALL R5 2 1  ; var5(var6)
      30 [-]: GETIMPORT R5 1; var5 = 0x89326C93
      31 [-]: GETIMPORT R7 17; var7 = 0x996CC482
      32 [-]: NAMECALL R5 R5 K4; var6 = var5; var5 = var5[0x46A0EBF5]
      33 [-]: CALL R5 3 2  ; var5 = var5(var6, var7)
      34 [-]: FASTCALL1 62 R5 L2; 
      35 [-]: MOVE R7 R5   ; var7 = var5
      36 [-]: GETIMPORT R6 11; var6 = 0x7B998233
      37 [-]: CALL R6 2 2  ; var6 = var6(var7)
L 2:  38 [-]: JUMPIF R6 L3 ; goto L3 if var6
      39 [-]: LOADK R8 K18 ; var8 = "TriggerPort"
      40 [-]: NAMECALL R6 R5 K19; var7 = var5; var6 = var5[0x8EB2112D]
      41 [-]: CALL R6 3 1  ; var6(var7, var8)
L 3:  42 [-]: GETIMPORT R6 1; var6 = 0x89326C93
      43 [-]: GETIMPORT R8 21; var8 = 0xD2BF1FF8
      44 [-]: NAMECALL R6 R6 K4; var7 = var6; var6 = var6[0x46A0EBF5]
      45 [-]: CALL R6 3 2  ; var6 = var6(var7, var8)
      46 [-]: NAMECALL R7 R6 K22; var8 = var6; var7 = var6[0xD1586535]
      47 [-]: CALL R7 2 2  ; var7 = var7(var8)
      48 [-]: GETIMPORT R8 1; var8 = 0x89326C93
      49 [-]: GETIMPORT R10 24; var10 = 0x27275716
      50 [-]: MOVE R11 R7  ; var11 = var7
      51 [-]: GETIMPORT R12 26; var12 = ZERO_ROTATION
      52 [-]: MOVE R13 R0  ; var13 = var0
      53 [-]: NAMECALL R8 R8 K27; var9 = var8; var8 = var8[0x05909209]
      54 [-]: CALL R8 6 1  ; var8(var9, var10, var11, var12, var13)
      55 [-]: GETIMPORT R8 1; var8 = 0x89326C93
      56 [-]: GETIMPORT R10 29; var10 = 0xC40C70E7
      57 [-]: NAMECALL R11 R6 K22; var12 = var6; var11 = var6[0xD1586535]
      58 [-]: CALL R11 2 2 ; var11 = var11(var12)
      59 [-]: GETIMPORT R12 26; var12 = ZERO_ROTATION
      60 [-]: MOVE R13 R0  ; var13 = var0
      61 [-]: NAMECALL R8 R8 K27; var9 = var8; var8 = var8[0x05909209]
      62 [-]: CALL R8 6 2  ; var8 = var8(var9, var10, var11, var12, var13)
      63 [-]: GETUPVAL R10 1; var10 = upvalues[1]
      64 [-]: GETTABLEKS R9 R10 K30; var9 = var10[0x9742B85B]
      65 [-]: MOVE R10 R1  ; var10 = var1
      66 [-]: GETIMPORT R11 13; var11 = 0x0469F296
      67 [-]: LOADK R12 K31; var12 = "Orowyrm_HorseStatue"
      68 [-]: CALL R11 2 0 ; var11, ... = var11(var12)
      69 [-]: CALL R9 0 1  ; var9(var10, ...)
      70 [-]: GETIMPORT R9 33; var9 = 0xCBD666E1
      71 [-]: GETIMPORT R10 35; var10 = 0xD6622A22
      72 [-]: CALL R9 2 1  ; var9(var10)
      73 [-]: GETIMPORT R10 37; var10 = 0x34D86A63
      74 [-]: LOADN R12 2  ; var12 = 2
      75 [-]: LENGTH R14 R4; var14 = #var4
      76 [-]: SUBK R13 R14 K38; var13 = var14 - 1
      77 [-]: MUL R11 R12 R13; var11 = var12 * var13
      78 [-]: ADD R9 R10 R11; var9 = var10 + var11
      79 [-]: GETIMPORT R11 40; var11 = 0xBE190284
      80 [-]: GETUPVAL R13 2; var13 = upvalues[2]
      81 [-]: NAMECALL R11 R11 K41; var12 = var11; var11 = var11[0x0EB34C69]
      82 [-]: CALL R11 3 2 ; var11 = var11(var12, var13)
      83 [-]: FASTCALL1 62 R11 L4; 
      84 [-]: GETIMPORT R10 11; var10 = 0x7B998233
      85 [-]: CALL R10 2 2 ; var10 = var10(var11)
L 4:  86 [-]: JUMPIFNOT R10 L5; goto L5 if not var10
      87 [-]: GETIMPORT R10 40; var10 = 0xBE190284
      88 [-]: GETUPVAL R12 2; var12 = upvalues[2]
      89 [-]: LOADN R13 0  ; var13 = 0
      90 [-]: NAMECALL R10 R10 K42; var11 = var10; var10 = var10[0x751F061D]
      91 [-]: CALL R10 4 1 ; var10(var11, var12, var13)
L 5:  92 [-]: LOADN R10 0  ; var10 = 0
      93 [-]: LOADN R12 1  ; var12 = 1
      94 [-]: DIV R11 R12 R9; var11 = var12 / var9
      95 [-]: GETIMPORT R12 1; var12 = 0x89326C93
      96 [-]: GETIMPORT R14 44; var14 = 0x53E9562A
      97 [-]: NAMECALL R12 R12 K8; var13 = var12; var12 = var12[0xC7FCADA9]
      98 [-]: CALL R12 3 2 ; var12 = var12(var13, var14)
      99 [-]: LOADN R13 1  ; var13 = 1
     100 [-]: NEWTABLE R14 0 0; var14 = {}
     101 [-]: GETIMPORT R15 40; var15 = 0xBE190284
     102 [-]: GETUPVAL R17 2; var17 = upvalues[2]
     103 [-]: NAMECALL R15 R15 K41; var16 = var15; var15 = var15[0x0EB34C69]
     104 [-]: CALL R15 3 2 ; var15 = var15(var16, var17)
     105 [-]: LENGTH R17 R14; var17 = #var14
     106 [-]: ADD R16 R17 R15; var16 = var17 + var15
     107 [-]: LOADN R19 1  ; var19 = 1
     108 [-]: LENGTH R17 R12; var17 = #var12
     109 [-]: LOADN R18 1  ; var18 = 1
     110 [-]: FORNPREP R17 L11; nforprep start - [escape at L11] -- var17 = iterator
L 6: 111 [-]: ADD R20 R15 R19; var20 = var15 + var19
     112 [-]: JUMPIFNOTLE R20 R9 L10; goto L10 if var20 > var218895415
     113 [-]: GETTABLE R20 R12 R13; var20 = var12[var13]
     114 [-]: NAMECALL R20 R20 K22; var21 = var20; var20 = var20[0xD1586535]
     115 [-]: CALL R20 2 2 ; var20 = var20(var21)
     116 [-]: GETIMPORT R21 1; var21 = 0x89326C93
     117 [-]: NAMECALL R21 R21 K45; var22 = var21; var21 = var21[0x29EF273D]
     118 [-]: CALL R21 2 2 ; var21 = var21(var22)
     119 [-]: GETIMPORT R23 47; var23 = 0x881387AD
     120 [-]: MOVE R24 R20 ; var24 = var20
     121 [-]: GETIMPORT R25 26; var25 = ZERO_ROTATION
     122 [-]: NAMECALL R21 R21 K48; var22 = var21; var21 = var21[0x6CD833C5]
     123 [-]: CALL R21 5 2 ; var21 = var21(var22, var23, var24, var25)
     124 [-]: GETIMPORT R24 13; var24 = 0x0469F296
     125 [-]: LOADK R25 K49; var25 = "TargetFlightAction"
     126 [-]: CALL R24 2 2 ; var24 = var24(var25)
     127 [-]: GETTABLE R25 R12 R13; var25 = var12[var13]
     128 [-]: NAMECALL R22 R21 K50; var23 = var21; var22 = var21[0xFBA09E89]
     129 [-]: CALL R22 4 1 ; var22(var23, var24, var25)
     130 [-]: GETIMPORT R24 13; var24 = 0x0469F296
     131 [-]: LOADK R25 K51; var25 = "BV_BABYDRAGON_SPLINE"
     132 [-]: CALL R24 2 2 ; var24 = var24(var25)
     133 [-]: LOADN R25 1  ; var25 = 1
     134 [-]: NAMECALL R22 R21 K52; var23 = var21; var22 = var21[0x6E0C2EE3]
     135 [-]: CALL R22 4 1 ; var22(var23, var24, var25)
     136 [-]: GETIMPORT R22 33; var22 = 0xCBD666E1
     137 [-]: LOADK R23 K53; var23 = 0.10000000000000001
     138 [-]: CALL R22 2 1 ; var22(var23)
     139 [-]: NAMECALL R22 R21 K54; var23 = var21; var22 = var21[0xBB610E5B]
     140 [-]: CALL R22 2 2 ; var22 = var22(var23)
     141 [-]: FASTCALL1 62 R22 L7; 
     142 [-]: MOVE R24 R22 ; var24 = var22
     143 [-]: GETIMPORT R23 11; var23 = 0x7B998233
     144 [-]: CALL R23 2 2 ; var23 = var23(var24)
L 7: 145 [-]: JUMPIF R23 L10; goto L10 if var23
     146 [-]: GETIMPORT R23 1; var23 = 0x89326C93
     147 [-]: GETIMPORT R25 56; var25 = 0xF69297EE
     148 [-]: NAMECALL R26 R22 K22; var27 = var22; var26 = var22[0xD1586535]
     149 [-]: CALL R26 2 2 ; var26 = var26(var27)
     150 [-]: GETIMPORT R27 26; var27 = ZERO_ROTATION
     151 [-]: NAMECALL R23 R23 K27; var24 = var23; var23 = var23[0x05909209]
     152 [-]: CALL R23 5 1 ; var23(var24, var25, var26, var27)
     153 [-]: GETTABLE R23 R12 R13; var23 = var12[var13]
     154 [-]: MOVE R25 R22 ; var25 = var22
     155 [-]: MOVE R26 R10 ; var26 = var10
     156 [-]: NAMECALL R23 R23 K57; var24 = var23; var23 = var23[0x52A4A40C]
     157 [-]: CALL R23 4 1 ; var23(var24, var25, var26)
     158 [-]: ADD R10 R10 R11; var10 = var10 + var11
     159 [-]: GETTABLE R23 R12 R13; var23 = var12[var13]
     160 [-]: LOADN R25 0  ; var25 = 0
     161 [-]: MOVE R26 R10 ; var26 = var10
     162 [-]: MOVE R27 R20 ; var27 = var20
     163 [-]: GETIMPORT R28 59; var28 = 0x00046924
     164 [-]: CALL R28 1 0 ; var28, ... = var28()
     165 [-]: NAMECALL R23 R23 K60; var24 = var23; var23 = var23[0x42FEA71B]
     166 [-]: CALL R23 0 1 ; var23(var24, ...)
     167 [-]: FASTCALL2 52 R14 R22 L8; 
     168 [-]: MOVE R24 R14 ; var24 = var14
     169 [-]: MOVE R25 R22 ; var25 = var22
     170 [-]: GETIMPORT R23 63; var23 = 0x33BDD652[0x23D5322F]
     171 [-]: CALL R23 3 1 ; var23(var24, var25)
L 8: 172 [-]: ADDK R16 R16 K38; var16 = var16 + 1
     173 [-]: ADDK R13 R13 K38; var13 = var13 + 1
     174 [-]: LENGTH R23 R12; var23 = #var12
     175 [-]: JUMPIFNOTLT R23 R13 L9; goto L9 if var23 >= var68935
     176 [-]: LOADN R13 1  ; var13 = 1
L 9: 177 [-]: GETIMPORT R25 65; var25 = 0x5305E7E7
     178 [-]: GETIMPORT R26 13; var26 = 0x0469F296
     179 [-]: LOADK R27 K66; var27 = "GAME_C1_HEAD"
     180 [-]: CALL R26 2 2 ; var26 = var26(var27)
     181 [-]: GETIMPORT R27 68; var27 = 0xA421AF95
     182 [-]: LOADN R28 0  ; var28 = 0
     183 [-]: LOADN R29 1  ; var29 = 1
     184 [-]: LOADN R30 0  ; var30 = 0
     185 [-]: CALL R27 4 0 ; var27, ... = var27(var28, var29, var30)
     186 [-]: NAMECALL R23 R22 K69; var24 = var22; var23 = var22[0x47901F07]
     187 [-]: CALL R23 0 1 ; var23(var24, ...)
     188 [-]: GETIMPORT R25 13; var25 = 0x0469F296
     189 [-]: LOADK R26 K70; var26 = "MiniDragonSpeedCheck"
     190 [-]: CALL R25 2 2 ; var25 = var25(var26)
     191 [-]: LOADB R26 0  ; var26 = false
     192 [-]: NAMECALL R23 R22 K15; var24 = var22; var23 = var22[0xD5F7912B]
     193 [-]: CALL R23 4 1 ; var23(var24, var25, var26)
L10: 194 [-]: GETIMPORT R20 33; var20 = 0xCBD666E1
     195 [-]: LOADN R21 0  ; var21 = 0
     196 [-]: CALL R20 2 1 ; var20(var21)
     197 [-]: FORNLOOP R17 L6; nforloop end - iterate + goto L6
L11: 198 [-]: GETUPVAL R18 3; var18 = upvalues[3]
     199 [-]: GETTABLEKS R17 R18 K71; var17 = var18[0xEA753E99]
     200 [-]: LOADK R18 K72; var18 = "/Lotus/Language/Duviri/DuviriDragonObjectiveSmallDragons"
     201 [-]: MOVE R19 R15 ; var19 = var15
     202 [-]: MOVE R20 R9  ; var20 = var9
     203 [-]: CALL R17 4 1 ; var17(var18, var19, var20)
     204 [-]: LOADN R17 2  ; var17 = 2
     205 [-]: LOADN R18 4  ; var18 = 4
     206 [-]: GETIMPORT R19 68; var19 = 0xA421AF95
     207 [-]: CALL R19 1 2 ; var19 = var19()
     208 [-]: MOVE R20 R18 ; var20 = var18
L12: 209 [-]: JUMPIFNOTLT R15 R9 L32; goto L32 if var15 >= var2626894
     210 [-]: GETIMPORT R21 40; var21 = 0xBE190284
     211 [-]: GETUPVAL R23 2; var23 = upvalues[2]
     212 [-]: NAMECALL R21 R21 K41; var22 = var21; var21 = var21[0x0EB34C69]
     213 [-]: CALL R21 3 2 ; var21 = var21(var22, var23)
     214 [-]: MOVE R15 R21 ; var15 = var21
     215 [-]: GETUPVAL R22 3; var22 = upvalues[3]
     216 [-]: GETTABLEKS R21 R22 K73; var21 = var22[0xF3928F38]
     217 [-]: MOVE R22 R15 ; var22 = var15
     218 [-]: MOVE R23 R9  ; var23 = var9
     219 [-]: CALL R21 3 1 ; var21(var22, var23)
     220 [-]: DIV R21 R15 R9; var21 = var15 / var9
     221 [-]: LOADK R22 K74; var22 = 0.75
     222 [-]: JUMPIFNOTLT R22 R21 L13; goto L13 if var22 >= var266567
     223 [-]: LOADN R17 4  ; var17 = 4
     224 [-]: LOADN R18 1  ; var18 = 1
     225 [-]: JUMP L15     ; goto L15
L13: 226 [-]: LOADK R22 K75; var22 = 0.5
     227 [-]: JUMPIFNOTLT R22 R21 L14; goto L14 if var22 >= var201031
     228 [-]: LOADN R17 3  ; var17 = 3
     229 [-]: LOADN R18 2  ; var18 = 2
     230 [-]: JUMP L15     ; goto L15
L14: 231 [-]: LOADK R22 K76; var22 = 0.25
     232 [-]: JUMPIFNOTLT R22 R21 L15; goto L15 if var22 >= var135495
     233 [-]: LOADN R17 2  ; var17 = 2
     234 [-]: LOADN R18 3  ; var18 = 3
L15: 235 [-]: LOADN R22 0  ; var22 = 0
     236 [-]: JUMPIFNOTLE R20 R22 L22; goto L22 if var20 > var5658
     237 [-]: NEWTABLE R22 0 0; var22 = {}
     238 [-]: GETIMPORT R23 1; var23 = 0x89326C93
     239 [-]: NAMECALL R23 R23 K9; var24 = var23; var23 = var23[0x8B5B1F58]
     240 [-]: CALL R23 2 2 ; var23 = var23(var24)
     241 [-]: MOVE R4 R23  ; var4 = var23
     242 [-]: LOADN R25 1  ; var25 = 1
     243 [-]: LENGTH R23 R4; var23 = #var4
     244 [-]: LOADN R24 1  ; var24 = 1
     245 [-]: FORNPREP R23 L18; nforprep start - [escape at L18] -- var23 = iterator
L16: 246 [-]: GETTABLE R26 R4 R25; var26 = var4[var25]
     247 [-]: NAMECALL R27 R26 K77; var28 = var26; var27 = var26[0xF6EBD926]
     248 [-]: CALL R27 2 2 ; var27 = var27(var28)
     249 [-]: NAMECALL R29 R26 K79; var30 = var26; var29 = var26[0xF376ADF1]
     250 [-]: CALL R29 2 2 ; var29 = var29(var30)
     251 [-]: MULK R28 R29 K78; var28 = var29 * 3
     252 [-]: ADD R27 R27 R28; var27 = var27 + var28
     253 [-]: MOVE R30 R7  ; var30 = var7
     254 [-]: NAMECALL R28 R26 K80; var29 = var26; var28 = var26[0x890697E0]
     255 [-]: CALL R28 3 2 ; var28 = var28(var29, var30)
     256 [-]: LOADN R29 100; var29 = 100
     257 [-]: JUMPIFNOTLT R29 R28 L17; goto L17 if var29 >= var72782
     258 [-]: GETIMPORT R28 1; var28 = 0x89326C93
     259 [-]: GETIMPORT R30 68; var30 = 0xA421AF95
     260 [-]: GETTABLEKS R31 R7 K81; var31 = var7["x"]
     261 [-]: GETTABLEKS R32 R27 K82; var32 = var27["y"]
     262 [-]: GETTABLEKS R33 R7 K83; var33 = var7["z"]
     263 [-]: CALL R30 4 2 ; var30 = var30(var31, var32, var33)
     264 [-]: MOVE R31 R27 ; var31 = var27
     265 [-]: MOVE R32 R0  ; var32 = var0
     266 [-]: LOADNIL R33  ; var33 = nil
     267 [-]: MOVE R34 R19 ; var34 = var19
     268 [-]: LOADB R35 0  ; var35 = false
     269 [-]: NAMECALL R28 R28 K84; var29 = var28; var28 = var28[0xBD5D0EC1]
     270 [-]: CALL R28 8 2 ; var28 = var28(var29, var30, var31, var32, var33, var34, var35)
     271 [-]: JUMPIF R28 L17; goto L17 if var28
     272 [-]: FASTCALL2 52 R22 R27 L17; 
     273 [-]: MOVE R30 R22 ; var30 = var22
     274 [-]: MOVE R31 R27 ; var31 = var27
     275 [-]: GETIMPORT R29 63; var29 = 0x33BDD652[0x23D5322F]
     276 [-]: CALL R29 3 1 ; var29(var30, var31)
L17: 277 [-]: FORNLOOP R23 L16; nforloop end - iterate + goto L16
L18: 278 [-]: LENGTH R24 R22; var24 = #var22
     279 [-]: FASTCALL2 19 R24 R17 L19; 
     280 [-]: MOVE R25 R17 ; var25 = var17
     281 [-]: GETIMPORT R23 87; var23 = 0x5BCED4C4[0xAC1B386A]
     282 [-]: CALL R23 3 2 ; var23 = var23(var24, var25)
L19: 283 [-]: LOADN R26 1  ; var26 = 1
     284 [-]: MOVE R24 R23 ; var24 = var23
     285 [-]: LOADN R25 1  ; var25 = 1
     286 [-]: FORNPREP R24 L21; nforprep start - [escape at L21] -- var24 = iterator
L20: 287 [-]: LENGTH R27 R22; var27 = #var22
     288 [-]: LOADN R28 0  ; var28 = 0
     289 [-]: JUMPIFLE R27 R28 L21; goto L21 if var27 <= var5839950
     290 [-]: GETIMPORT R28 89; var28 = 0x0C5E62F9
     291 [-]: LOADN R29 1  ; var29 = 1
     292 [-]: LENGTH R30 R22; var30 = #var22
     293 [-]: CALL R28 3 2 ; var28 = var28(var29, var30)
     294 [-]: GETTABLE R27 R22 R28; var27 = var22[var28]
     295 [-]: GETIMPORT R28 91; var28 = 0xDD6E4CF8
     296 [-]: LOADN R29 -5 ; var29 = -5
     297 [-]: LOADN R30 5  ; var30 = 5
     298 [-]: CALL R28 3 2 ; var28 = var28(var29, var30)
     299 [-]: GETTABLEKS R30 R27 K82; var30 = var27["y"]
     300 [-]: ADD R29 R30 R28; var29 = var30 + var28
     301 [-]: SETTABLEKS R29 R27 K82; var29["y"] = var27
     302 [-]: GETIMPORT R29 68; var29 = 0xA421AF95
     303 [-]: GETTABLEKS R30 R7 K81; var30 = var7["x"]
     304 [-]: GETTABLEKS R31 R27 K82; var31 = var27["y"]
     305 [-]: GETTABLEKS R32 R7 K83; var32 = var7["z"]
     306 [-]: CALL R29 4 2 ; var29 = var29(var30, var31, var32)
     307 [-]: GETIMPORT R30 93; var30 = 0x20B7F774
     308 [-]: MOVE R31 R29 ; var31 = var29
     309 [-]: MOVE R32 R27 ; var32 = var27
     310 [-]: CALL R30 3 2 ; var30 = var30(var31, var32)
     311 [-]: GETIMPORT R31 95; var31 = 0x492C7F2A
     312 [-]: GETIMPORT R32 68; var32 = 0xA421AF95
     313 [-]: LOADN R33 0  ; var33 = 0
     314 [-]: LOADN R34 0  ; var34 = 0
     315 [-]: LOADN R35 100; var35 = 100
     316 [-]: CALL R32 4 2 ; var32 = var32(var33, var34, var35)
     317 [-]: MOVE R33 R30 ; var33 = var30
     318 [-]: CALL R31 3 2 ; var31 = var31(var32, var33)
     319 [-]: ADD R29 R29 R31; var29 = var29 + var31
     320 [-]: GETIMPORT R31 1; var31 = 0x89326C93
     321 [-]: GETIMPORT R33 97; var33 = 0x1F8C2641
     322 [-]: MOVE R34 R29 ; var34 = var29
     323 [-]: MOVE R35 R30 ; var35 = var30
     324 [-]: MOVE R36 R0  ; var36 = var0
     325 [-]: MOVE R37 R0  ; var37 = var0
     326 [-]: NAMECALL R31 R31 K27; var32 = var31; var31 = var31[0x05909209]
     327 [-]: CALL R31 7 1 ; var31(var32, var33, var34, var35, var36, var37)
     328 [-]: FORNLOOP R24 L20; nforloop end - iterate + goto L20
L21: 329 [-]: MOVE R20 R18 ; var20 = var18
L22: 330 [-]: LENGTH R24 R14; var24 = #var14
     331 [-]: LOADN R22 1  ; var22 = 1
     332 [-]: LOADN R23 -1 ; var23 = -1
     333 [-]: FORNPREP R22 L27; nforprep start - [escape at L27] -- var22 = iterator
L23: 334 [-]: GETTABLE R26 R14 R24; var26 = var14[var24]
     335 [-]: FASTCALL1 62 R26 L24; 
     336 [-]: GETIMPORT R25 11; var25 = 0x7B998233
     337 [-]: CALL R25 2 2 ; var25 = var25(var26)
L24: 338 [-]: JUMPIF R25 L25; goto L25 if var25
     339 [-]: GETTABLE R25 R14 R24; var25 = var14[var24]
     340 [-]: NAMECALL R25 R25 K98; var26 = var25; var25 = var25[0x2047CFE7]
     341 [-]: CALL R25 2 2 ; var25 = var25(var26)
     342 [-]: JUMPIF R25 L25; goto L25 if var25
     343 [-]: GETTABLE R25 R14 R24; var25 = var14[var24]
     344 [-]: NAMECALL R25 R25 K99; var26 = var25; var25 = var25[0x73901ACF]
     345 [-]: CALL R25 2 2 ; var25 = var25(var26)
     346 [-]: JUMPIFNOT R25 L26; goto L26 if not var25
L25: 347 [-]: GETIMPORT R25 40; var25 = 0xBE190284
     348 [-]: GETUPVAL R27 2; var27 = upvalues[2]
     349 [-]: GETIMPORT R29 40; var29 = 0xBE190284
     350 [-]: GETUPVAL R31 2; var31 = upvalues[2]
     351 [-]: NAMECALL R29 R29 K41; var30 = var29; var29 = var29[0x0EB34C69]
     352 [-]: CALL R29 3 2 ; var29 = var29(var30, var31)
     353 [-]: ADDK R28 R29 K38; var28 = var29 + 1
     354 [-]: NAMECALL R25 R25 K42; var26 = var25; var25 = var25[0x751F061D]
     355 [-]: CALL R25 4 1 ; var25(var26, var27, var28)
     356 [-]: GETIMPORT R25 101; var25 = 0x33BDD652[0x9C1F3B5A]
     357 [-]: MOVE R26 R14 ; var26 = var14
     358 [-]: MOVE R27 R24 ; var27 = var24
     359 [-]: CALL R25 3 1 ; var25(var26, var27)
L26: 360 [-]: FORNLOOP R22 L23; nforloop end - iterate + goto L23
L27: 361 [-]: LENGTH R22 R14; var22 = #var14
     362 [-]: GETIMPORT R23 103; var23 = 0x150F616E
     363 [-]: JUMPIFNOTLT R22 R23 L31; goto L31 if var22 >= var7802892
     364 [-]: JUMPIFNOTLT R16 R9 L31; goto L31 if var16 >= var5838414
     365 [-]: GETIMPORT R22 89; var22 = 0x0C5E62F9
     366 [-]: LOADN R23 1  ; var23 = 1
     367 [-]: LENGTH R25 R12; var25 = #var12
     368 [-]: SUBK R24 R25 K38; var24 = var25 - 1
     369 [-]: CALL R22 3 2 ; var22 = var22(var23, var24)
     370 [-]: ADD R13 R13 R22; var13 = var13 + var22
     371 [-]: LENGTH R22 R12; var22 = #var12
     372 [-]: JUMPIFNOTLT R22 R13 L28; goto L28 if var22 >= var792080
     373 [-]: LENGTH R22 R12; var22 = #var12
     374 [-]: SUB R13 R13 R22; var13 = var13 - var22
L28: 375 [-]: GETTABLE R22 R12 R13; var22 = var12[var13]
     376 [-]: NAMECALL R22 R22 K22; var23 = var22; var22 = var22[0xD1586535]
     377 [-]: CALL R22 2 2 ; var22 = var22(var23)
     378 [-]: GETIMPORT R23 1; var23 = 0x89326C93
     379 [-]: NAMECALL R23 R23 K45; var24 = var23; var23 = var23[0x29EF273D]
     380 [-]: CALL R23 2 2 ; var23 = var23(var24)
     381 [-]: GETIMPORT R25 47; var25 = 0x881387AD
     382 [-]: MOVE R26 R22 ; var26 = var22
     383 [-]: GETIMPORT R27 26; var27 = ZERO_ROTATION
     384 [-]: NAMECALL R23 R23 K48; var24 = var23; var23 = var23[0x6CD833C5]
     385 [-]: CALL R23 5 2 ; var23 = var23(var24, var25, var26, var27)
     386 [-]: GETIMPORT R26 13; var26 = 0x0469F296
     387 [-]: LOADK R27 K49; var27 = "TargetFlightAction"
     388 [-]: CALL R26 2 2 ; var26 = var26(var27)
     389 [-]: GETTABLE R27 R12 R13; var27 = var12[var13]
     390 [-]: NAMECALL R24 R23 K50; var25 = var23; var24 = var23[0xFBA09E89]
     391 [-]: CALL R24 4 1 ; var24(var25, var26, var27)
     392 [-]: GETIMPORT R26 13; var26 = 0x0469F296
     393 [-]: LOADK R27 K51; var27 = "BV_BABYDRAGON_SPLINE"
     394 [-]: CALL R26 2 2 ; var26 = var26(var27)
     395 [-]: LOADN R27 1  ; var27 = 1
     396 [-]: NAMECALL R24 R23 K52; var25 = var23; var24 = var23[0x6E0C2EE3]
     397 [-]: CALL R24 4 1 ; var24(var25, var26, var27)
     398 [-]: GETIMPORT R24 33; var24 = 0xCBD666E1
     399 [-]: LOADK R25 K53; var25 = 0.10000000000000001
     400 [-]: CALL R24 2 1 ; var24(var25)
     401 [-]: NAMECALL R24 R23 K54; var25 = var23; var24 = var23[0xBB610E5B]
     402 [-]: CALL R24 2 2 ; var24 = var24(var25)
     403 [-]: FASTCALL1 62 R24 L29; 
     404 [-]: MOVE R26 R24 ; var26 = var24
     405 [-]: GETIMPORT R25 11; var25 = 0x7B998233
     406 [-]: CALL R25 2 2 ; var25 = var25(var26)
L29: 407 [-]: JUMPIF R25 L31; goto L31 if var25
     408 [-]: GETIMPORT R25 1; var25 = 0x89326C93
     409 [-]: GETIMPORT R27 56; var27 = 0xF69297EE
     410 [-]: NAMECALL R28 R24 K22; var29 = var24; var28 = var24[0xD1586535]
     411 [-]: CALL R28 2 2 ; var28 = var28(var29)
     412 [-]: GETIMPORT R29 26; var29 = ZERO_ROTATION
     413 [-]: NAMECALL R25 R25 K27; var26 = var25; var25 = var25[0x05909209]
     414 [-]: CALL R25 5 1 ; var25(var26, var27, var28, var29)
     415 [-]: GETTABLE R25 R12 R13; var25 = var12[var13]
     416 [-]: MOVE R27 R24 ; var27 = var24
     417 [-]: MOVE R28 R10 ; var28 = var10
     418 [-]: NAMECALL R25 R25 K57; var26 = var25; var25 = var25[0x52A4A40C]
     419 [-]: CALL R25 4 1 ; var25(var26, var27, var28)
     420 [-]: ADD R10 R10 R11; var10 = var10 + var11
     421 [-]: GETTABLE R25 R12 R13; var25 = var12[var13]
     422 [-]: LOADN R27 0  ; var27 = 0
     423 [-]: MOVE R28 R10 ; var28 = var10
     424 [-]: MOVE R29 R22 ; var29 = var22
     425 [-]: GETIMPORT R30 59; var30 = 0x00046924
     426 [-]: CALL R30 1 0 ; var30, ... = var30()
     427 [-]: NAMECALL R25 R25 K60; var26 = var25; var25 = var25[0x42FEA71B]
     428 [-]: CALL R25 0 1 ; var25(var26, ...)
     429 [-]: FASTCALL2 52 R14 R24 L30; 
     430 [-]: MOVE R26 R14 ; var26 = var14
     431 [-]: MOVE R27 R24 ; var27 = var24
     432 [-]: GETIMPORT R25 63; var25 = 0x33BDD652[0x23D5322F]
     433 [-]: CALL R25 3 1 ; var25(var26, var27)
L30: 434 [-]: ADDK R16 R16 K38; var16 = var16 + 1
     435 [-]: GETIMPORT R27 65; var27 = 0x5305E7E7
     436 [-]: GETIMPORT R28 13; var28 = 0x0469F296
     437 [-]: LOADK R29 K66; var29 = "GAME_C1_HEAD"
     438 [-]: CALL R28 2 2 ; var28 = var28(var29)
     439 [-]: GETIMPORT R29 68; var29 = 0xA421AF95
     440 [-]: LOADN R30 0  ; var30 = 0
     441 [-]: LOADN R31 1  ; var31 = 1
     442 [-]: LOADN R32 0  ; var32 = 0
     443 [-]: CALL R29 4 0 ; var29, ... = var29(var30, var31, var32)
     444 [-]: NAMECALL R25 R24 K69; var26 = var24; var25 = var24[0x47901F07]
     445 [-]: CALL R25 0 1 ; var25(var26, ...)
     446 [-]: GETIMPORT R27 13; var27 = 0x0469F296
     447 [-]: LOADK R28 K70; var28 = "MiniDragonSpeedCheck"
     448 [-]: CALL R27 2 2 ; var27 = var27(var28)
     449 [-]: LOADB R28 0  ; var28 = false
     450 [-]: NAMECALL R25 R24 K15; var26 = var24; var25 = var24[0xD5F7912B]
     451 [-]: CALL R25 4 1 ; var25(var26, var27, var28)
L31: 452 [-]: GETIMPORT R22 105; var22 = 0x67652851
     453 [-]: CALL R22 1 2 ; var22 = var22()
     454 [-]: SUB R20 R20 R22; var20 = var20 - var22
     455 [-]: GETIMPORT R22 33; var22 = 0xCBD666E1
     456 [-]: LOADN R23 0  ; var23 = 0
     457 [-]: CALL R22 2 1 ; var22(var23)
     458 [-]: JUMPBACK L12 ; goto L12
L32: 459 [-]: GETUPVAL R22 3; var22 = upvalues[3]
     460 [-]: GETTABLEKS R21 R22 K106; var21 = var22[0xBD3CE95D]
     461 [-]: CALL R21 1 1 ; var21()
     462 [-]: GETUPVAL R22 1; var22 = upvalues[1]
     463 [-]: GETTABLEKS R21 R22 K30; var21 = var22[0x9742B85B]
     464 [-]: MOVE R22 R1  ; var22 = var1
     465 [-]: GETIMPORT R23 13; var23 = 0x0469F296
     466 [-]: LOADK R24 K107; var24 = "Orowyrm_DominusTaunts"
     467 [-]: CALL R23 2 0 ; var23, ... = var23(var24)
     468 [-]: CALL R21 0 1 ; var21(var22, ...)
     469 [-]: GETIMPORT R21 40; var21 = 0xBE190284
     470 [-]: GETUPVAL R23 4; var23 = upvalues[4]
     471 [-]: LOADN R24 1  ; var24 = 1
     472 [-]: NAMECALL R21 R21 K42; var22 = var21; var21 = var21[0x751F061D]
     473 [-]: CALL R21 4 1 ; var21(var22, var23, var24)
     474 [-]: GETIMPORT R21 1; var21 = 0x89326C93
     475 [-]: GETIMPORT R23 109; var23 = 0x9E8194E7
     476 [-]: MOVE R24 R7  ; var24 = var7
     477 [-]: GETIMPORT R25 26; var25 = ZERO_ROTATION
     478 [-]: MOVE R26 R0  ; var26 = var0
     479 [-]: NAMECALL R21 R21 K27; var22 = var21; var21 = var21[0x05909209]
     480 [-]: CALL R21 6 1 ; var21(var22, var23, var24, var25, var26)
     481 [-]: GETIMPORT R21 33; var21 = 0xCBD666E1
     482 [-]: GETIMPORT R22 111; var22 = 0x5F7F595F
     483 [-]: CALL R21 2 1 ; var21(var22)
     484 [-]: FASTCALL1 62 R8 L33; 
     485 [-]: MOVE R22 R8  ; var22 = var8
     486 [-]: GETIMPORT R21 11; var21 = 0x7B998233
     487 [-]: CALL R21 2 2 ; var21 = var21(var22)
L33: 488 [-]: JUMPIF R21 L34; goto L34 if var21
     489 [-]: NAMECALL R21 R8 K112; var22 = var8; var21 = var8[0xA2880940]
     490 [-]: CALL R21 2 1 ; var21(var22)
L34: 491 [-]: GETIMPORT R23 114; var23 = 0xC9312B82
     492 [-]: LOADB R24 1  ; var24 = true
     493 [-]: LOADN R25 2  ; var25 = 2
     494 [-]: LOADN R26 1  ; var26 = 1
     495 [-]: LOADB R27 1  ; var27 = true
     496 [-]: NAMECALL R21 R0 K115; var22 = var0; var21 = var0[0x7027C544]
     497 [-]: CALL R21 7 1 ; var21(var22, var23, var24, var25, var26, var27)
     498 [-]: GETIMPORT R23 117; var23 = 0x45DD84BD
     499 [-]: GETIMPORT R26 119; var26 = 0xF5462A7F
     500 [-]: LOADB R27 0  ; var27 = false
     501 [-]: LOADN R28 2  ; var28 = 2
     502 [-]: LOADN R29 1  ; var29 = 1
     503 [-]: LOADB R30 1  ; var30 = true
     504 [-]: NAMECALL R24 R0 K115; var25 = var0; var24 = var0[0x7027C544]
     505 [-]: CALL R24 7 0 ; var24, ... = var24(var25, var26, var27, var28, var29, var30)
     506 [-]: NAMECALL R21 R0 K120; var22 = var0; var21 = var0[0x21B4C60E]
     507 [-]: CALL R21 0 1 ; var21(var22, ...)
     508 [-]: GETIMPORT R21 1; var21 = 0x89326C93
     509 [-]: NAMECALL R21 R21 K9; var22 = var21; var21 = var21[0x8B5B1F58]
     510 [-]: CALL R21 2 2 ; var21 = var21(var22)
     511 [-]: MOVE R4 R21  ; var4 = var21
     512 [-]: LOADN R23 1  ; var23 = 1
     513 [-]: LENGTH R21 R4; var21 = #var4
     514 [-]: LOADN R22 1  ; var22 = 1
     515 [-]: FORNPREP R21 L40; nforprep start - [escape at L40] -- var21 = iterator
L35: 516 [-]: GETTABLE R24 R4 R23; var24 = var4[var23]
     517 [-]: FASTCALL1 62 R24 L36; 
     518 [-]: MOVE R26 R24 ; var26 = var24
     519 [-]: GETIMPORT R25 11; var25 = 0x7B998233
     520 [-]: CALL R25 2 2 ; var25 = var25(var26)
L36: 521 [-]: JUMPIF R25 L39; goto L39 if var25
     522 [-]: GETIMPORT R27 122; var27 = gLotusVehicleAvatarType
     523 [-]: NAMECALL R25 R24 K123; var26 = var24; var25 = var24[0xF2DEAF69]
     524 [-]: CALL R25 3 2 ; var25 = var25(var26, var27)
     525 [-]: JUMPIFNOT R25 L39; goto L39 if not var25
     526 [-]: GETIMPORT R27 125; var27 = 0xA0A04438
     527 [-]: GETIMPORT R28 127; var28 = EMPTY_SYMBOL
     528 [-]: NAMECALL R25 R24 K69; var26 = var24; var25 = var24[0x47901F07]
     529 [-]: CALL R25 4 1 ; var25(var26, var27, var28)
     530 [-]: NAMECALL R25 R24 K128; var26 = var24; var25 = var24[0xFF005826]
     531 [-]: CALL R25 2 2 ; var25 = var25(var26)
     532 [-]: MOVE R28 R25 ; var28 = var25
     533 [-]: GETIMPORT R29 130; var29 = ZERO_VECTOR
     534 [-]: LOADB R30 1  ; var30 = true
     535 [-]: LOADB R31 0  ; var31 = false
     536 [-]: LOADB R32 1  ; var32 = true
     537 [-]: NAMECALL R26 R24 K131; var27 = var24; var26 = var24[0xCAA5DE6D]
     538 [-]: CALL R26 7 1 ; var26(var27, var28, var29, var30, var31, var32)
     539 [-]: MOVE R24 R25 ; var24 = var25
     540 [-]: GETIMPORT R26 33; var26 = 0xCBD666E1
     541 [-]: LOADN R27 0  ; var27 = 0
     542 [-]: CALL R26 2 1 ; var26(var27)
     543 [-]: GETIMPORT R27 133; var27 = 0x851A139F
     544 [-]: FASTCALL1 62 R27 L37; 
     545 [-]: GETIMPORT R26 11; var26 = 0x7B998233
     546 [-]: CALL R26 2 2 ; var26 = var26(var27)
L37: 547 [-]: JUMPIF R26 L39; goto L39 if var26
     548 [-]: FASTCALL1 62 R24 L38; 
     549 [-]: MOVE R27 R24 ; var27 = var24
     550 [-]: GETIMPORT R26 11; var26 = 0x7B998233
     551 [-]: CALL R26 2 2 ; var26 = var26(var27)
L38: 552 [-]: JUMPIF R26 L39; goto L39 if var26
     553 [-]: NAMECALL R26 R24 K134; var27 = var24; var26 = var24[0xDE321E6F]
     554 [-]: CALL R26 2 2 ; var26 = var26(var27)
     555 [-]: LOADB R28 1  ; var28 = true
     556 [-]: NAMECALL R26 R26 K135; var27 = var26; var26 = var26[0x0B5EC5B5]
     557 [-]: CALL R26 3 1 ; var26(var27, var28)
     558 [-]: GETIMPORT R28 133; var28 = 0x851A139F
     559 [-]: NAMECALL R26 R24 K136; var27 = var24; var26 = var24[0x35B09371]
     560 [-]: CALL R26 3 1 ; var26(var27, var28)
     561 [-]: NAMECALL R26 R24 K134; var27 = var24; var26 = var24[0xDE321E6F]
     562 [-]: CALL R26 2 2 ; var26 = var26(var27)
     563 [-]: LOADN R28 7  ; var28 = 7
     564 [-]: LOADN R29 0  ; var29 = 0
     565 [-]: NAMECALL R26 R26 K137; var27 = var26; var26 = var26[0x447665BF]
     566 [-]: CALL R26 4 1 ; var26(var27, var28, var29)
L39: 567 [-]: FORNLOOP R21 L35; nforloop end - iterate + goto L35
L40: 568 [-]: GETIMPORT R21 1; var21 = 0x89326C93
     569 [-]: GETIMPORT R23 139; var23 = 0x88008CBA
     570 [-]: NAMECALL R21 R21 K140; var22 = var21; var21 = var21[0xFB669000]
     571 [-]: CALL R21 3 2 ; var21 = var21(var22, var23)
     572 [-]: FASTCALL1 62 R21 L41; 
     573 [-]: MOVE R23 R21 ; var23 = var21
     574 [-]: GETIMPORT R22 11; var22 = 0x7B998233
     575 [-]: CALL R22 2 2 ; var22 = var22(var23)
L41: 576 [-]: JUMPIF R22 L43; goto L43 if var22
     577 [-]: LOADN R24 1  ; var24 = 1
     578 [-]: LENGTH R22 R21; var22 = #var21
     579 [-]: LOADN R23 1  ; var23 = 1
     580 [-]: FORNPREP R22 L43; nforprep start - [escape at L43] -- var22 = iterator
L42: 581 [-]: GETTABLE R25 R21 R24; var25 = var21[var24]
     582 [-]: NAMECALL R25 R25 K112; var26 = var25; var25 = var25[0xA2880940]
     583 [-]: CALL R25 2 1 ; var25(var26)
     584 [-]: FORNLOOP R22 L42; nforloop end - iterate + goto L42
L43: 585 [-]: LOADB R24 1  ; var24 = true
     586 [-]: LOADB R25 1  ; var25 = true
     587 [-]: NAMECALL R22 R2 K5; var23 = var2; var22 = var2[0x768274D6]
     588 [-]: CALL R22 4 1 ; var22(var23, var24, var25)
     589 [-]: RETURN R0 0  ; 


; Name:            
; Defined at line: 590
; #Upvalues:       3
; #Parameters:     2
; Is_vararg:       0
; Max Stack Size:  26

       0 [-]: GETIMPORT R2 1; var2 = 0x89326C93
       1 [-]: NAMECALL R2 R2 K2; var3 = var2; var2 = var2[0x29EF273D]
       2 [-]: CALL R2 2 2  ; var2 = var2(var3)
       3 [-]: NAMECALL R2 R2 K3; var3 = var2; var2 = var2[0x66905CB0]
       4 [-]: CALL R2 2 2  ; var2 = var2(var3)
       5 [-]: GETIMPORT R3 1; var3 = 0x89326C93
       6 [-]: NAMECALL R3 R3 K4; var4 = var3; var3 = var3[0x8B5B1F58]
       7 [-]: CALL R3 2 2  ; var3 = var3(var4)
       8 [-]: GETIMPORT R5 6; var5 = 0xBE190284
       9 [-]: GETUPVAL R7 0; var7 = upvalues[0]
      10 [-]: NAMECALL R5 R5 K7; var6 = var5; var5 = var5[0x0EB34C69]
      11 [-]: CALL R5 3 2  ; var5 = var5(var6, var7)
      12 [-]: FASTCALL1 62 R5 L0; 
      13 [-]: GETIMPORT R4 9; var4 = 0x7B998233
      14 [-]: CALL R4 2 2  ; var4 = var4(var5)
L 0:  15 [-]: JUMPIFNOT R4 L1; goto L1 if not var4
      16 [-]: GETIMPORT R4 6; var4 = 0xBE190284
      17 [-]: GETUPVAL R6 0; var6 = upvalues[0]
      18 [-]: LOADN R7 0   ; var7 = 0
      19 [-]: NAMECALL R4 R4 K10; var5 = var4; var4 = var4[0x751F061D]
      20 [-]: CALL R4 4 1  ; var4(var5, var6, var7)
L 1:  21 [-]: GETIMPORT R4 12; var4 = 0xFFB56934
      22 [-]: GETIMPORT R6 6; var6 = 0xBE190284
      23 [-]: NAMECALL R6 R6 K13; var7 = var6; var6 = var6[0xEF893AEC]
      24 [-]: CALL R6 2 2  ; var6 = var6(var7)
      25 [-]: GETTABLEKS R5 R6 K14; var5 = var6["tier"]
      26 [-]: LOADN R6 0   ; var6 = 0
      27 [-]: JUMPIFNOTLT R6 R5 L2; goto L2 if var6 >= var1049678
      28 [-]: GETIMPORT R4 16; var4 = 0x742D2745
L 2:  29 [-]: GETIMPORT R5 1; var5 = 0x89326C93
      30 [-]: GETIMPORT R7 18; var7 = 0x8F04B1CB
      31 [-]: NAMECALL R5 R5 K19; var6 = var5; var5 = var5[0xC7FCADA9]
      32 [-]: CALL R5 3 2  ; var5 = var5(var6, var7)
      33 [-]: GETIMPORT R6 6; var6 = 0xBE190284
      34 [-]: GETUPVAL R8 0; var8 = upvalues[0]
      35 [-]: NAMECALL R6 R6 K7; var7 = var6; var6 = var6[0x0EB34C69]
      36 [-]: CALL R6 3 2  ; var6 = var6(var7, var8)
      37 [-]: LENGTH R7 R5 ; var7 = #var5
      38 [-]: GETUPVAL R9 1; var9 = upvalues[1]
      39 [-]: GETTABLEKS R8 R9 K20; var8 = var9[0xEA753E99]
      40 [-]: LOADK R9 K21 ; var9 = "/Lotus/Language/Duviri/DuviriDragonObjectiveSmallDragons"
      41 [-]: MOVE R10 R6  ; var10 = var6
      42 [-]: MOVE R11 R7  ; var11 = var7
      43 [-]: CALL R8 4 1  ; var8(var9, var10, var11)
      44 [-]: NEWTABLE R8 0 0; var8 = {}
      45 [-]: LOADN R11 1  ; var11 = 1
      46 [-]: LENGTH R9 R5 ; var9 = #var5
      47 [-]: LOADN R10 1  ; var10 = 1
      48 [-]: FORNPREP R9 L8; nforprep start - [escape at L8] -- var9 = iterator
L 3:  49 [-]: GETTABLE R12 R5 R11; var12 = var5[var11]
      50 [-]: NAMECALL R12 R12 K22; var13 = var12; var12 = var12[0xD1586535]
      51 [-]: CALL R12 2 2 ; var12 = var12(var13)
      52 [-]: GETIMPORT R13 1; var13 = 0x89326C93
      53 [-]: NAMECALL R13 R13 K2; var14 = var13; var13 = var13[0x29EF273D]
      54 [-]: CALL R13 2 2 ; var13 = var13(var14)
      55 [-]: GETIMPORT R15 24; var15 = 0xD95FCE33
      56 [-]: MOVE R16 R12 ; var16 = var12
      57 [-]: GETIMPORT R17 26; var17 = ZERO_ROTATION
      58 [-]: GETIMPORT R18 28; var18 = 0x0469F296
      59 [-]: LOADK R19 K29; var19 = "RandomTeam"
      60 [-]: CALL R18 2 2 ; var18 = var18(var19)
      61 [-]: MOVE R19 R4  ; var19 = var4
      62 [-]: NAMECALL R13 R13 K30; var14 = var13; var13 = var13[0x6CD833C5]
      63 [-]: CALL R13 7 2 ; var13 = var13(var14, var15, var16, var17, var18, var19)
      64 [-]: NAMECALL R14 R13 K31; var15 = var13; var14 = var13[0xBB610E5B]
      65 [-]: CALL R14 2 2 ; var14 = var14(var15)
      66 [-]: FASTCALL2 52 R8 R14 L4; 
      67 [-]: MOVE R16 R8  ; var16 = var8
      68 [-]: MOVE R17 R14 ; var17 = var14
      69 [-]: GETIMPORT R15 34; var15 = 0x33BDD652[0x23D5322F]
      70 [-]: CALL R15 3 1 ; var15(var16, var17)
L 4:  71 [-]: GETIMPORT R17 28; var17 = 0x0469F296
      72 [-]: LOADK R18 K35; var18 = "TargetFlightAction"
      73 [-]: CALL R17 2 2 ; var17 = var17(var18)
      74 [-]: GETTABLE R18 R5 R11; var18 = var5[var11]
      75 [-]: NAMECALL R15 R13 K36; var16 = var13; var15 = var13[0xFBA09E89]
      76 [-]: CALL R15 4 1 ; var15(var16, var17, var18)
      77 [-]: GETIMPORT R17 28; var17 = 0x0469F296
      78 [-]: LOADK R18 K37; var18 = "BV_BABYDRAGON_SPLINE"
      79 [-]: CALL R17 2 2 ; var17 = var17(var18)
      80 [-]: LOADN R18 1  ; var18 = 1
      81 [-]: NAMECALL R15 R13 K38; var16 = var13; var15 = var13[0x6E0C2EE3]
      82 [-]: CALL R15 4 1 ; var15(var16, var17, var18)
      83 [-]: GETIMPORT R15 40; var15 = 0xCBD666E1
      84 [-]: LOADK R16 K41; var16 = 0.10000000000000001
      85 [-]: CALL R15 2 1 ; var15(var16)
      86 [-]: FASTCALL1 62 R13 L5; 
      87 [-]: MOVE R16 R13 ; var16 = var13
      88 [-]: GETIMPORT R15 9; var15 = 0x7B998233
      89 [-]: CALL R15 2 2 ; var15 = var15(var16)
L 5:  90 [-]: JUMPIF R15 L7; goto L7 if var15
      91 [-]: FASTCALL1 62 R14 L6; 
      92 [-]: MOVE R16 R14 ; var16 = var14
      93 [-]: GETIMPORT R15 9; var15 = 0x7B998233
      94 [-]: CALL R15 2 2 ; var15 = var15(var16)
L 6:  95 [-]: JUMPIF R15 L7; goto L7 if var15
      96 [-]: LOADN R17 2  ; var17 = 2
      97 [-]: NAMECALL R15 R14 K42; var16 = var14; var15 = var14[0xEA2890BE]
      98 [-]: CALL R15 3 1 ; var15(var16, var17)
      99 [-]: GETIMPORT R15 1; var15 = 0x89326C93
     100 [-]: GETIMPORT R17 44; var17 = 0xF69297EE
     101 [-]: NAMECALL R18 R14 K22; var19 = var14; var18 = var14[0xD1586535]
     102 [-]: CALL R18 2 2 ; var18 = var18(var19)
     103 [-]: GETIMPORT R19 26; var19 = ZERO_ROTATION
     104 [-]: NAMECALL R15 R15 K45; var16 = var15; var15 = var15[0x05909209]
     105 [-]: CALL R15 5 1 ; var15(var16, var17, var18, var19)
     106 [-]: GETIMPORT R17 47; var17 = 0x5305E7E7
     107 [-]: GETIMPORT R18 28; var18 = 0x0469F296
     108 [-]: LOADK R19 K48; var19 = "GAME_C1_HEAD"
     109 [-]: CALL R18 2 2 ; var18 = var18(var19)
     110 [-]: GETIMPORT R19 50; var19 = 0xA421AF95
     111 [-]: LOADN R20 0  ; var20 = 0
     112 [-]: LOADN R21 1  ; var21 = 1
     113 [-]: LOADN R22 0  ; var22 = 0
     114 [-]: CALL R19 4 0 ; var19, ... = var19(var20, var21, var22)
     115 [-]: NAMECALL R15 R14 K51; var16 = var14; var15 = var14[0x47901F07]
     116 [-]: CALL R15 0 1 ; var15(var16, ...)
L 7: 117 [-]: GETIMPORT R15 40; var15 = 0xCBD666E1
     118 [-]: LOADN R16 1  ; var16 = 1
     119 [-]: CALL R15 2 1 ; var15(var16)
     120 [-]: FORNLOOP R9 L3; nforloop end - iterate + goto L3
L 8: 121 [-]: GETUPVAL R10 2; var10 = upvalues[2]
     122 [-]: GETTABLEKS R9 R10 K52; var9 = var10[0x9742B85B]
     123 [-]: MOVE R10 R1  ; var10 = var1
     124 [-]: GETIMPORT R11 28; var11 = 0x0469F296
     125 [-]: LOADK R12 K53; var12 = "Orowyrm_StatuePhase"
     126 [-]: CALL R11 2 0 ; var11, ... = var11(var12)
     127 [-]: CALL R9 0 1  ; var9(var10, ...)
     128 [-]: GETIMPORT R9 1; var9 = 0x89326C93
     129 [-]: GETIMPORT R11 55; var11 = 0x1E155F36
     130 [-]: NAMECALL R9 R9 K19; var10 = var9; var9 = var9[0xC7FCADA9]
     131 [-]: CALL R9 3 2  ; var9 = var9(var10, var11)
     132 [-]: NEWTABLE R10 0 0; var10 = {}
     133 [-]: LOADN R12 4  ; var12 = 4
     134 [-]: LOADN R14 2  ; var14 = 2
     135 [-]: LENGTH R16 R3; var16 = #var3
     136 [-]: SUBK R15 R16 K56; var15 = var16 - 1
     137 [-]: MUL R13 R14 R15; var13 = var14 * var15
     138 [-]: ADD R11 R12 R13; var11 = var12 + var13
     139 [-]: LOADN R12 0  ; var12 = 0
     140 [-]: LOADN R13 0  ; var13 = 0
L 9: 141 [-]: JUMPIFNOTLT R6 R7 L25; goto L25 if var6 >= var396878
     142 [-]: GETIMPORT R14 6; var14 = 0xBE190284
     143 [-]: GETUPVAL R16 0; var16 = upvalues[0]
     144 [-]: NAMECALL R14 R14 K7; var15 = var14; var14 = var14[0x0EB34C69]
     145 [-]: CALL R14 3 2 ; var14 = var14(var15, var16)
     146 [-]: MOVE R6 R14  ; var6 = var14
     147 [-]: GETUPVAL R15 1; var15 = upvalues[1]
     148 [-]: GETTABLEKS R14 R15 K57; var14 = var15[0xF3928F38]
     149 [-]: MOVE R15 R6  ; var15 = var6
     150 [-]: MOVE R16 R7  ; var16 = var7
     151 [-]: CALL R14 3 1 ; var14(var15, var16)
     152 [-]: LENGTH R14 R10; var14 = #var10
     153 [-]: JUMPIFNOTLT R14 R11 L14; goto L14 if var14 >= var5836044
     154 [-]: JUMPIFNOTLT R13 R12 L14; goto L14 if var13 >= var3870542
     155 [-]: GETIMPORT R15 59; var15 = 0x98CCE1BB
     156 [-]: GETIMPORT R16 61; var16 = 0x0C5E62F9
     157 [-]: LOADN R17 1  ; var17 = 1
     158 [-]: GETIMPORT R19 59; var19 = 0x98CCE1BB
     159 [-]: LENGTH R18 R19; var18 = #var19
     160 [-]: CALL R16 3 2 ; var16 = var16(var17, var18)
     161 [-]: GETTABLE R14 R15 R16; var14 = var15[var16]
     162 [-]: LOADN R16 1  ; var16 = 1
     163 [-]: LENGTH R18 R10; var18 = #var10
     164 [-]: SUB R17 R11 R18; var17 = var11 - var18
     165 [-]: FASTCALL2 18 R16 R17 L10; 
     166 [-]: GETIMPORT R15 64; var15 = 0x5BCED4C4[0xB62ECFE0]
     167 [-]: CALL R15 3 2 ; var15 = var15(var16, var17)
L10: 168 [-]: LOADN R18 1  ; var18 = 1
     169 [-]: MOVE R16 R15 ; var16 = var15
     170 [-]: LOADN R17 1  ; var17 = 1
     171 [-]: FORNPREP R16 L14; nforprep start - [escape at L14] -- var16 = iterator
L11: 172 [-]: MOVE R21 R14 ; var21 = var14
     173 [-]: GETIMPORT R23 61; var23 = 0x0C5E62F9
     174 [-]: LOADN R24 1  ; var24 = 1
     175 [-]: LENGTH R25 R9; var25 = #var9
     176 [-]: CALL R23 3 2 ; var23 = var23(var24, var25)
     177 [-]: GETTABLE R22 R9 R23; var22 = var9[var23]
     178 [-]: LOADN R23 3  ; var23 = 3
     179 [-]: GETIMPORT R24 28; var24 = 0x0469F296
     180 [-]: LOADK R25 K29; var25 = "RandomTeam"
     181 [-]: CALL R24 2 2 ; var24 = var24(var25)
     182 [-]: MOVE R25 R4  ; var25 = var4
     183 [-]: NAMECALL R19 R2 K65; var20 = var2; var19 = var2[0x2883E796]
     184 [-]: CALL R19 7 2 ; var19 = var19(var20, var21, var22, var23, var24, var25)
     185 [-]: NAMECALL R20 R19 K66; var21 = var19; var20 = var19[0x9E21E394]
     186 [-]: CALL R20 2 1 ; var20(var21)
     187 [-]: NAMECALL R20 R19 K31; var21 = var19; var20 = var19[0xBB610E5B]
     188 [-]: CALL R20 2 2 ; var20 = var20(var21)
     189 [-]: FASTCALL1 62 R20 L12; 
     190 [-]: MOVE R22 R20 ; var22 = var20
     191 [-]: GETIMPORT R21 9; var21 = 0x7B998233
     192 [-]: CALL R21 2 2 ; var21 = var21(var22)
L12: 193 [-]: JUMPIF R21 L13; goto L13 if var21
     194 [-]: GETIMPORT R21 1; var21 = 0x89326C93
     195 [-]: GETIMPORT R23 44; var23 = 0xF69297EE
     196 [-]: NAMECALL R24 R20 K22; var25 = var20; var24 = var20[0xD1586535]
     197 [-]: CALL R24 2 2 ; var24 = var24(var25)
     198 [-]: GETIMPORT R25 26; var25 = ZERO_ROTATION
     199 [-]: NAMECALL R21 R21 K45; var22 = var21; var21 = var21[0x05909209]
     200 [-]: CALL R21 5 1 ; var21(var22, var23, var24, var25)
     201 [-]: NAMECALL R21 R20 K67; var22 = var20; var21 = var20[0x1AC1655C]
     202 [-]: CALL R21 2 2 ; var21 = var21(var22)
     203 [-]: LOADB R23 0  ; var23 = false
     204 [-]: NAMECALL R21 R21 K68; var22 = var21; var21 = var21[0x35577788]
     205 [-]: CALL R21 3 1 ; var21(var22, var23)
     206 [-]: GETIMPORT R23 70; var23 = 0x29988258
     207 [-]: NAMECALL R21 R20 K71; var22 = var20; var21 = var20[0x22C4E9DD]
     208 [-]: CALL R21 3 1 ; var21(var22, var23)
     209 [-]: FASTCALL2 52 R10 R20 L13; 
     210 [-]: MOVE R22 R10 ; var22 = var10
     211 [-]: MOVE R23 R20 ; var23 = var20
     212 [-]: GETIMPORT R21 34; var21 = 0x33BDD652[0x23D5322F]
     213 [-]: CALL R21 3 1 ; var21(var22, var23)
L13: 214 [-]: GETIMPORT R21 73; var21 = 0xDD6E4CF8
     215 [-]: LOADN R22 3  ; var22 = 3
     216 [-]: LOADN R23 5  ; var23 = 5
     217 [-]: CALL R21 3 2 ; var21 = var21(var22, var23)
     218 [-]: ADD R13 R12 R21; var13 = var12 + var21
     219 [-]: FORNLOOP R16 L11; nforloop end - iterate + goto L11
L14: 220 [-]: LENGTH R16 R10; var16 = #var10
     221 [-]: LOADN R14 1  ; var14 = 1
     222 [-]: LOADN R15 -1 ; var15 = -1
     223 [-]: FORNPREP R14 L19; nforprep start - [escape at L19] -- var14 = iterator
L15: 224 [-]: GETTABLE R18 R10 R16; var18 = var10[var16]
     225 [-]: FASTCALL1 62 R18 L16; 
     226 [-]: GETIMPORT R17 9; var17 = 0x7B998233
     227 [-]: CALL R17 2 2 ; var17 = var17(var18)
L16: 228 [-]: JUMPIF R17 L17; goto L17 if var17
     229 [-]: GETTABLE R17 R10 R16; var17 = var10[var16]
     230 [-]: NAMECALL R17 R17 K74; var18 = var17; var17 = var17[0x2047CFE7]
     231 [-]: CALL R17 2 2 ; var17 = var17(var18)
     232 [-]: JUMPIFNOT R17 L18; goto L18 if not var17
L17: 233 [-]: GETIMPORT R17 76; var17 = 0x33BDD652[0x9C1F3B5A]
     234 [-]: MOVE R18 R10 ; var18 = var10
     235 [-]: MOVE R19 R16 ; var19 = var16
     236 [-]: CALL R17 3 1 ; var17(var18, var19)
L18: 237 [-]: FORNLOOP R14 L15; nforloop end - iterate + goto L15
L19: 238 [-]: LENGTH R16 R8; var16 = #var8
     239 [-]: LOADN R14 1  ; var14 = 1
     240 [-]: LOADN R15 -1 ; var15 = -1
     241 [-]: FORNPREP R14 L24; nforprep start - [escape at L24] -- var14 = iterator
L20: 242 [-]: GETTABLE R18 R8 R16; var18 = var8[var16]
     243 [-]: FASTCALL1 62 R18 L21; 
     244 [-]: GETIMPORT R17 9; var17 = 0x7B998233
     245 [-]: CALL R17 2 2 ; var17 = var17(var18)
L21: 246 [-]: JUMPIF R17 L22; goto L22 if var17
     247 [-]: GETTABLE R17 R8 R16; var17 = var8[var16]
     248 [-]: NAMECALL R17 R17 K74; var18 = var17; var17 = var17[0x2047CFE7]
     249 [-]: CALL R17 2 2 ; var17 = var17(var18)
     250 [-]: JUMPIF R17 L22; goto L22 if var17
     251 [-]: GETTABLE R17 R8 R16; var17 = var8[var16]
     252 [-]: NAMECALL R17 R17 K77; var18 = var17; var17 = var17[0x73901ACF]
     253 [-]: CALL R17 2 2 ; var17 = var17(var18)
     254 [-]: JUMPIFNOT R17 L23; goto L23 if not var17
L22: 255 [-]: GETIMPORT R17 6; var17 = 0xBE190284
     256 [-]: GETUPVAL R19 0; var19 = upvalues[0]
     257 [-]: GETIMPORT R21 6; var21 = 0xBE190284
     258 [-]: GETUPVAL R23 0; var23 = upvalues[0]
     259 [-]: NAMECALL R21 R21 K7; var22 = var21; var21 = var21[0x0EB34C69]
     260 [-]: CALL R21 3 2 ; var21 = var21(var22, var23)
     261 [-]: ADDK R20 R21 K56; var20 = var21 + 1
     262 [-]: NAMECALL R17 R17 K10; var18 = var17; var17 = var17[0x751F061D]
     263 [-]: CALL R17 4 1 ; var17(var18, var19, var20)
     264 [-]: GETIMPORT R17 76; var17 = 0x33BDD652[0x9C1F3B5A]
     265 [-]: MOVE R18 R8  ; var18 = var8
     266 [-]: MOVE R19 R16 ; var19 = var16
     267 [-]: CALL R17 3 1 ; var17(var18, var19)
L23: 268 [-]: FORNLOOP R14 L20; nforloop end - iterate + goto L20
L24: 269 [-]: GETIMPORT R14 40; var14 = 0xCBD666E1
     270 [-]: LOADN R15 0  ; var15 = 0
     271 [-]: CALL R14 2 1 ; var14(var15)
     272 [-]: GETIMPORT R14 79; var14 = 0x67652851
     273 [-]: CALL R14 1 2 ; var14 = var14()
     274 [-]: ADD R12 R12 R14; var12 = var12 + var14
     275 [-]: JUMPBACK L9  ; goto L9
L25: 276 [-]: GETUPVAL R15 1; var15 = upvalues[1]
     277 [-]: GETTABLEKS R14 R15 K80; var14 = var15[0xBD3CE95D]
     278 [-]: CALL R14 1 1 ; var14()
     279 [-]: GETIMPORT R14 6; var14 = 0xBE190284
     280 [-]: GETUPVAL R16 0; var16 = upvalues[0]
     281 [-]: LOADN R17 0  ; var17 = 0
     282 [-]: NAMECALL R14 R14 K10; var15 = var14; var14 = var14[0x751F061D]
     283 [-]: CALL R14 4 1 ; var14(var15, var16, var17)
     284 [-]: RETURN R0 0  ; 


; Name:            
; Defined at line: 691
; #Upvalues:       1
; #Parameters:     0
; Is_vararg:       0
; Max Stack Size:  3

       0 [-]: GETIMPORT R0 1; var0 = 0xBE190284
       1 [-]: GETUPVAL R2 0; var2 = upvalues[0]
       2 [-]: NAMECALL R0 R0 K2; var1 = var0; var0 = var0[0x0EB34C69]
       3 [-]: CALL R0 3 2  ; var0 = var0(var1, var2)
       4 [-]: JUMPXEQKN R0 K3 L0 NOT; 
       5 [-]: LOADK R1 K4  ; var1 = "SHIELD"
       6 [-]: RETURN R1 1  ; 
L 0:   7 [-]: JUMPXEQKN R0 K5 L1 NOT; 
       8 [-]: LOADK R1 K6  ; var1 = "HORSE"
       9 [-]: RETURN R1 1  ; 
L 1:  10 [-]: LOADK R1 K7  ; var1 = "DEFAULT"
      11 [-]: RETURN R1 1  ; 


; Name:            
; Defined at line: 704
; #Upvalues:       2
; #Parameters:     0
; Is_vararg:       0
; Max Stack Size:  15

       0 [-]: GETIMPORT R0 1; var0 = 0x89326C93
       1 [-]: GETIMPORT R2 3; var2 = 0xFC65B1D8
       2 [-]: NAMECALL R0 R0 K4; var1 = var0; var0 = var0[0xFB669000]
       3 [-]: CALL R0 3 2  ; var0 = var0(var1, var2)
L 0:   4 [-]: FASTCALL1 62 R0 L1; 
       5 [-]: MOVE R2 R0   ; var2 = var0
       6 [-]: GETIMPORT R1 6; var1 = 0x7B998233
       7 [-]: CALL R1 2 2  ; var1 = var1(var2)
L 1:   8 [-]: JUMPIF R1 L3 ; goto L3 if var1
       9 [-]: LENGTH R1 R0 ; var1 = #var0
      10 [-]: JUMPXEQKN R1 K7 L3; 
      11 [-]: GETTABLEN R2 R0 1; var2 = var0[1]
      12 [-]: FASTCALL1 62 R2 L2; 
      13 [-]: GETIMPORT R1 6; var1 = 0x7B998233
      14 [-]: CALL R1 2 2  ; var1 = var1(var2)
L 2:  15 [-]: JUMPIFNOT R1 L4; goto L4 if not var1
L 3:  16 [-]: GETIMPORT R1 9; var1 = 0xCBD666E1
      17 [-]: LOADN R2 0   ; var2 = 0
      18 [-]: CALL R1 2 1  ; var1(var2)
      19 [-]: GETIMPORT R1 1; var1 = 0x89326C93
      20 [-]: GETIMPORT R3 3; var3 = 0xFC65B1D8
      21 [-]: NAMECALL R1 R1 K4; var2 = var1; var1 = var1[0xFB669000]
      22 [-]: CALL R1 3 2  ; var1 = var1(var2, var3)
      23 [-]: MOVE R0 R1   ; var0 = var1
      24 [-]: JUMPBACK L0  ; goto L0
L 4:  25 [-]: NEWTABLE R1 0 0; var1 = {}
L 5:  26 [-]: FASTCALL1 62 R0 L6; 
      27 [-]: MOVE R3 R0   ; var3 = var0
      28 [-]: GETIMPORT R2 6; var2 = 0x7B998233
      29 [-]: CALL R2 2 2  ; var2 = var2(var3)
L 6:  30 [-]: JUMPIF R2 L23; goto L23 if var2
      31 [-]: LENGTH R2 R0 ; var2 = #var0
      32 [-]: LOADN R3 0   ; var3 = 0
      33 [-]: JUMPIFNOTLT R3 R2 L23; goto L23 if var3 >= var805
      34 [-]: GETTABLEN R3 R0 1; var3 = var0[1]
      35 [-]: FASTCALL1 62 R3 L7; 
      36 [-]: GETIMPORT R2 6; var2 = 0x7B998233
      37 [-]: CALL R2 2 2  ; var2 = var2(var3)
L 7:  38 [-]: JUMPIF R2 L23; goto L23 if var2
      39 [-]: GETIMPORT R2 11; var2 = 0xBE190284
      40 [-]: GETUPVAL R4 0; var4 = upvalues[0]
      41 [-]: NAMECALL R2 R2 K12; var3 = var2; var2 = var2[0x0EB34C69]
      42 [-]: CALL R2 3 2  ; var2 = var2(var3, var4)
      43 [-]: JUMPXEQKN R2 K13 L22 NOT; 
      44 [-]: GETIMPORT R2 1; var2 = 0x89326C93
      45 [-]: NAMECALL R2 R2 K14; var3 = var2; var2 = var2[0x7D108DDB]
      46 [-]: CALL R2 2 2  ; var2 = var2(var3)
      47 [-]: LOADN R5 1   ; var5 = 1
      48 [-]: LENGTH R3 R2 ; var3 = #var2
      49 [-]: LOADN R4 1   ; var4 = 1
      50 [-]: FORNPREP R3 L22; nforprep start - [escape at L22] -- var3 = iterator
L 8:  51 [-]: GETTABLE R7 R2 R5; var7 = var2[var5]
      52 [-]: FASTCALL1 62 R7 L9; 
      53 [-]: GETIMPORT R6 6; var6 = 0x7B998233
      54 [-]: CALL R6 2 2  ; var6 = var6(var7)
L 9:  55 [-]: JUMPIF R6 L21; goto L21 if var6
      56 [-]: GETTABLE R6 R2 R5; var6 = var2[var5]
      57 [-]: NAMECALL R6 R6 K15; var7 = var6; var6 = var6[0xBB610E5B]
      58 [-]: CALL R6 2 2  ; var6 = var6(var7)
      59 [-]: FASTCALL1 62 R6 L10; 
      60 [-]: MOVE R8 R6   ; var8 = var6
      61 [-]: GETIMPORT R7 6; var7 = 0x7B998233
      62 [-]: CALL R7 2 2  ; var7 = var7(var8)
L10:  63 [-]: JUMPIF R7 L18; goto L18 if var7
      64 [-]: GETTABLE R9 R2 R5; var9 = var2[var5]
      65 [-]: GETTABLE R8 R1 R9; var8 = var1[var9]
      66 [-]: FASTCALL1 62 R8 L11; 
      67 [-]: GETIMPORT R7 6; var7 = 0x7B998233
      68 [-]: CALL R7 2 2  ; var7 = var7(var8)
L11:  69 [-]: JUMPIF R7 L18; goto L18 if var7
      70 [-]: GETTABLE R8 R2 R5; var8 = var2[var5]
      71 [-]: GETTABLE R7 R1 R8; var7 = var1[var8]
      72 [-]: JUMPIFNOT R7 L18; goto L18 if not var7
      73 [-]: NAMECALL R7 R6 K16; var8 = var6; var7 = var6[0x2047CFE7]
      74 [-]: CALL R7 2 2  ; var7 = var7(var8)
      75 [-]: JUMPIF R7 L18; goto L18 if var7
      76 [-]: NAMECALL R7 R6 K17; var8 = var6; var7 = var6[0x73901ACF]
      77 [-]: CALL R7 2 2  ; var7 = var7(var8)
      78 [-]: JUMPIF R7 L18; goto L18 if var7
      79 [-]: GETIMPORT R7 9; var7 = 0xCBD666E1
      80 [-]: LOADN R8 1   ; var8 = 1
      81 [-]: CALL R7 2 1  ; var7(var8)
      82 [-]: FASTCALL1 62 R6 L12; 
      83 [-]: MOVE R8 R6   ; var8 = var6
      84 [-]: GETIMPORT R7 6; var7 = 0x7B998233
      85 [-]: CALL R7 2 2  ; var7 = var7(var8)
L12:  86 [-]: JUMPIF R7 L18; goto L18 if var7
      87 [-]: GETIMPORT R9 19; var9 = gLotusVehicleAvatarType
      88 [-]: NAMECALL R7 R6 K20; var8 = var6; var7 = var6[0xF2DEAF69]
      89 [-]: CALL R7 3 2  ; var7 = var7(var8, var9)
      90 [-]: JUMPIF R7 L18; goto L18 if var7
      91 [-]: GETIMPORT R8 22; var8 = 0x851A139F
      92 [-]: FASTCALL1 62 R8 L13; 
      93 [-]: GETIMPORT R7 6; var7 = 0x7B998233
      94 [-]: CALL R7 2 2  ; var7 = var7(var8)
L13:  95 [-]: JUMPIF R7 L16; goto L16 if var7
      96 [-]: NAMECALL R7 R6 K23; var8 = var6; var7 = var6[0xDE321E6F]
      97 [-]: CALL R7 2 2  ; var7 = var7(var8)
      98 [-]: LOADN R9 0   ; var9 = 0
      99 [-]: NAMECALL R7 R7 K24; var8 = var7; var7 = var7[0xFD389C66]
     100 [-]: CALL R7 3 2  ; var7 = var7(var8, var9)
     101 [-]: FASTCALL1 62 R7 L14; 
     102 [-]: MOVE R9 R7   ; var9 = var7
     103 [-]: GETIMPORT R8 6; var8 = 0x7B998233
     104 [-]: CALL R8 2 2  ; var8 = var8(var9)
L14: 105 [-]: JUMPIF R8 L15; goto L15 if var8
     106 [-]: GETIMPORT R10 22; var10 = 0x851A139F
     107 [-]: NAMECALL R8 R7 K20; var9 = var7; var8 = var7[0xF2DEAF69]
     108 [-]: CALL R8 3 2  ; var8 = var8(var9, var10)
     109 [-]: JUMPIF R8 L15; goto L15 if var8
     110 [-]: NAMECALL R8 R6 K23; var9 = var6; var8 = var6[0xDE321E6F]
     111 [-]: CALL R8 2 2  ; var8 = var8(var9)
     112 [-]: LOADN R10 0  ; var10 = 0
     113 [-]: LOADN R11 7  ; var11 = 7
     114 [-]: NAMECALL R8 R8 K25; var9 = var8; var8 = var8[0x447665BF]
     115 [-]: CALL R8 4 1  ; var8(var9, var10, var11)
     116 [-]: GETIMPORT R10 22; var10 = 0x851A139F
     117 [-]: LOADB R11 1  ; var11 = true
     118 [-]: NAMECALL R8 R6 K26; var9 = var6; var8 = var6[0x511D26B8]
     119 [-]: CALL R8 4 1  ; var8(var9, var10, var11)
L15: 120 [-]: NAMECALL R8 R6 K23; var9 = var6; var8 = var6[0xDE321E6F]
     121 [-]: CALL R8 2 2  ; var8 = var8(var9)
     122 [-]: LOADB R10 0  ; var10 = false
     123 [-]: NAMECALL R8 R8 K27; var9 = var8; var8 = var8[0x0B5EC5B5]
     124 [-]: CALL R8 3 1  ; var8(var9, var10)
L16: 125 [-]: GETUPVAL R7 1; var7 = upvalues[1]
     126 [-]: NAMECALL R8 R6 K28; var9 = var6; var8 = var6[0x5E651723]
     127 [-]: CALL R8 2 2  ; var8 = var8(var9)
     128 [-]: NAMECALL R9 R6 K29; var10 = var6; var9 = var6[0xD1586535]
     129 [-]: CALL R9 2 2  ; var9 = var9(var10)
     130 [-]: GETIMPORT R10 31; var10 = ZERO_ROTATION
     131 [-]: CALL R7 4 2  ; var7 = var7(var8, var9, var10)
     132 [-]: FASTCALL1 62 R7 L17; 
     133 [-]: MOVE R9 R7   ; var9 = var7
     134 [-]: GETIMPORT R8 6; var8 = 0x7B998233
     135 [-]: CALL R8 2 2  ; var8 = var8(var9)
L17: 136 [-]: JUMPIF R8 L18; goto L18 if var8
     137 [-]: MOVE R10 R6  ; var10 = var6
     138 [-]: LOADB R11 1  ; var11 = true
     139 [-]: LOADB R12 0  ; var12 = false
     140 [-]: LOADB R13 0  ; var13 = false
     141 [-]: LOADB R14 1  ; var14 = true
     142 [-]: NAMECALL R8 R7 K32; var9 = var7; var8 = var7[0xDFBB9951]
     143 [-]: CALL R8 7 1  ; var8(var9, var10, var11, var12, var13, var14)
L18: 144 [-]: FASTCALL1 62 R6 L19; 
     145 [-]: MOVE R8 R6   ; var8 = var6
     146 [-]: GETIMPORT R7 6; var7 = 0x7B998233
     147 [-]: CALL R7 2 2  ; var7 = var7(var8)
L19: 148 [-]: JUMPIF R7 L21; goto L21 if var7
     149 [-]: GETTABLE R7 R2 R5; var7 = var2[var5]
     150 [-]: NAMECALL R8 R6 K16; var9 = var6; var8 = var6[0x2047CFE7]
     151 [-]: CALL R8 2 2  ; var8 = var8(var9)
     152 [-]: JUMPIF R8 L20; goto L20 if var8
     153 [-]: NAMECALL R8 R6 K17; var9 = var6; var8 = var6[0x73901ACF]
     154 [-]: CALL R8 2 2  ; var8 = var8(var9)
L20: 155 [-]: SETTABLE R8 R1 R7; var8[var1] = var7
L21: 156 [-]: FORNLOOP R3 L8; nforloop end - iterate + goto L8
L22: 157 [-]: GETIMPORT R2 9; var2 = 0xCBD666E1
     158 [-]: LOADN R3 0   ; var3 = 0
     159 [-]: CALL R2 2 1  ; var2(var3)
     160 [-]: JUMPBACK L5  ; goto L5
L23: 161 [-]: RETURN R0 0  ; 


; Name:            
; Defined at line: 763
; #Upvalues:       1
; #Parameters:     0
; Is_vararg:       0
; Max Stack Size:  13

       0 [-]: GETIMPORT R0 1; var0 = 0x89326C93
       1 [-]: NAMECALL R0 R0 K2; var1 = var0; var0 = var0[0x7D108DDB]
       2 [-]: CALL R0 2 2  ; var0 = var0(var1)
       3 [-]: LOADN R3 1   ; var3 = 1
       4 [-]: LENGTH R1 R0 ; var1 = #var0
       5 [-]: LOADN R2 1   ; var2 = 1
       6 [-]: FORNPREP R1 L11; nforprep start - [escape at L11] -- var1 = iterator
L 0:   7 [-]: GETTABLE R5 R0 R3; var5 = var0[var3]
       8 [-]: FASTCALL1 62 R5 L1; 
       9 [-]: GETIMPORT R4 4; var4 = 0x7B998233
      10 [-]: CALL R4 2 2  ; var4 = var4(var5)
L 1:  11 [-]: JUMPIF R4 L10; goto L10 if var4
      12 [-]: GETIMPORT R4 6; var4 = ZERO_VECTOR
      13 [-]: GETIMPORT R5 1; var5 = 0x89326C93
      14 [-]: GETUPVAL R8 0; var8 = upvalues[0]
      15 [-]: GETTABLEKS R7 R8 K7; var7 = var8["DEFAULT"]
      16 [-]: NAMECALL R5 R5 K8; var6 = var5; var5 = var5[0x46A0EBF5]
      17 [-]: CALL R5 3 2  ; var5 = var5(var6, var7)
      18 [-]: FASTCALL1 62 R5 L2; 
      19 [-]: MOVE R7 R5   ; var7 = var5
      20 [-]: GETIMPORT R6 4; var6 = 0x7B998233
      21 [-]: CALL R6 2 2  ; var6 = var6(var7)
L 2:  22 [-]: JUMPIF R6 L3 ; goto L3 if var6
      23 [-]: NAMECALL R6 R5 K9; var7 = var5; var6 = var5[0xD1586535]
      24 [-]: CALL R6 2 2  ; var6 = var6(var7)
      25 [-]: MOVE R4 R6   ; var4 = var6
L 3:  26 [-]: GETTABLE R6 R0 R3; var6 = var0[var3]
      27 [-]: LOADN R8 0   ; var8 = 0
      28 [-]: NAMECALL R6 R6 K10; var7 = var6; var6 = var6[0xE3A0BBCA]
      29 [-]: CALL R6 3 2  ; var6 = var6(var7, var8)
      30 [-]: GETTABLE R7 R0 R3; var7 = var0[var3]
      31 [-]: LOADN R9 8   ; var9 = 8
      32 [-]: NAMECALL R7 R7 K10; var8 = var7; var7 = var7[0xE3A0BBCA]
      33 [-]: CALL R7 3 2  ; var7 = var7(var8, var9)
      34 [-]: FASTCALL1 62 R6 L4; 
      35 [-]: MOVE R9 R6   ; var9 = var6
      36 [-]: GETIMPORT R8 4; var8 = 0x7B998233
      37 [-]: CALL R8 2 2  ; var8 = var8(var9)
L 4:  38 [-]: JUMPIF R8 L5 ; goto L5 if var8
      39 [-]: MOVE R10 R4  ; var10 = var4
      40 [-]: NAMECALL R8 R6 K11; var9 = var6; var8 = var6[0x1F420A3A]
      41 [-]: CALL R8 3 2  ; var8 = var8(var9, var10)
      42 [-]: LOADN R9 200 ; var9 = 200
      43 [-]: JUMPIFNOTLT R9 R8 L5; goto L5 if var9 >= var264726
      44 [-]: MOVE R10 R4  ; var10 = var4
      45 [-]: NAMECALL R11 R6 K12; var12 = var6; var11 = var6[0xCB3851B8]
      46 [-]: CALL R11 2 0 ; var11, ... = var11(var12)
      47 [-]: NAMECALL R8 R6 K13; var9 = var6; var8 = var6[0x589EF1C1]
      48 [-]: CALL R8 0 1  ; var8(var9, ...)
L 5:  49 [-]: FASTCALL1 62 R7 L6; 
      50 [-]: MOVE R9 R7   ; var9 = var7
      51 [-]: GETIMPORT R8 4; var8 = 0x7B998233
      52 [-]: CALL R8 2 2  ; var8 = var8(var9)
L 6:  53 [-]: JUMPIF R8 L10; goto L10 if var8
      54 [-]: MOVE R10 R4  ; var10 = var4
      55 [-]: NAMECALL R8 R7 K11; var9 = var7; var8 = var7[0x1F420A3A]
      56 [-]: CALL R8 3 2  ; var8 = var8(var9, var10)
      57 [-]: LOADN R9 200 ; var9 = 200
      58 [-]: JUMPIFNOTLT R9 R8 L7; goto L7 if var9 >= var264726
      59 [-]: MOVE R10 R4  ; var10 = var4
      60 [-]: NAMECALL R11 R7 K12; var12 = var7; var11 = var7[0xCB3851B8]
      61 [-]: CALL R11 2 0 ; var11, ... = var11(var12)
      62 [-]: NAMECALL R8 R7 K13; var9 = var7; var8 = var7[0x589EF1C1]
      63 [-]: CALL R8 0 1  ; var8(var9, ...)
L 7:  64 [-]: NAMECALL R8 R7 K14; var9 = var7; var8 = var7[0x2047CFE7]
      65 [-]: CALL R8 2 2  ; var8 = var8(var9)
      66 [-]: JUMPIF R8 L8 ; goto L8 if var8
      67 [-]: NAMECALL R8 R7 K15; var9 = var7; var8 = var7[0x73901ACF]
      68 [-]: CALL R8 2 2  ; var8 = var8(var9)
      69 [-]: JUMPIFNOT R8 L9; goto L9 if not var8
L 8:  70 [-]: NAMECALL R8 R7 K16; var9 = var7; var8 = var7[0xAA09C686]
      71 [-]: CALL R8 2 1  ; var8(var9)
L 9:  72 [-]: NAMECALL R8 R7 K17; var9 = var7; var8 = var7[0xD4CC05B4]
      73 [-]: CALL R8 2 2  ; var8 = var8(var9)
      74 [-]: JUMPIFNOT R8 L10; goto L10 if not var8
      75 [-]: LOADB R10 0  ; var10 = false
      76 [-]: NAMECALL R8 R7 K18; var9 = var7; var8 = var7[0xE39D0733]
      77 [-]: CALL R8 3 1  ; var8(var9, var10)
      78 [-]: LOADB R10 0  ; var10 = false
      79 [-]: NAMECALL R8 R7 K19; var9 = var7; var8 = var7[0x8FF7507F]
      80 [-]: CALL R8 3 1  ; var8(var9, var10)
      81 [-]: LOADB R10 1  ; var10 = true
      82 [-]: NAMECALL R8 R7 K20; var9 = var7; var8 = var7[0x6667E5D4]
      83 [-]: CALL R8 3 1  ; var8(var9, var10)
      84 [-]: LOADB R10 1  ; var10 = true
      85 [-]: NAMECALL R8 R7 K21; var9 = var7; var8 = var7[0x069D881F]
      86 [-]: CALL R8 3 1  ; var8(var9, var10)
      87 [-]: LOADB R10 0  ; var10 = false
      88 [-]: LOADB R11 1  ; var11 = true
      89 [-]: NAMECALL R8 R7 K22; var9 = var7; var8 = var7[0x768274D6]
      90 [-]: CALL R8 4 1  ; var8(var9, var10, var11)
      91 [-]: NAMECALL R8 R7 K23; var9 = var7; var8 = var7[0x283A8730]
      92 [-]: CALL R8 2 1  ; var8(var9)
L10:  93 [-]: FORNLOOP R1 L0; nforloop end - iterate + goto L0
L11:  94 [-]: RETURN R0 0  ; 


; Name:            
; Defined at line: 803
; #Upvalues:       4
; #Parameters:     0
; Is_vararg:       0
; Max Stack Size:  12

       0 [-]: GETIMPORT R0 1; var0 = 0x89326C93
       1 [-]: GETIMPORT R2 3; var2 = 0xFC65B1D8
       2 [-]: NAMECALL R0 R0 K4; var1 = var0; var0 = var0[0xFB669000]
       3 [-]: CALL R0 3 2  ; var0 = var0(var1, var2)
L 0:   4 [-]: FASTCALL1 62 R0 L1; 
       5 [-]: MOVE R2 R0   ; var2 = var0
       6 [-]: GETIMPORT R1 6; var1 = 0x7B998233
       7 [-]: CALL R1 2 2  ; var1 = var1(var2)
L 1:   8 [-]: JUMPIF R1 L3 ; goto L3 if var1
       9 [-]: LENGTH R1 R0 ; var1 = #var0
      10 [-]: JUMPXEQKN R1 K7 L3; 
      11 [-]: GETTABLEN R2 R0 1; var2 = var0[1]
      12 [-]: FASTCALL1 62 R2 L2; 
      13 [-]: GETIMPORT R1 6; var1 = 0x7B998233
      14 [-]: CALL R1 2 2  ; var1 = var1(var2)
L 2:  15 [-]: JUMPIFNOT R1 L4; goto L4 if not var1
L 3:  16 [-]: GETIMPORT R1 9; var1 = 0xCBD666E1
      17 [-]: LOADN R2 0   ; var2 = 0
      18 [-]: CALL R1 2 1  ; var1(var2)
      19 [-]: GETIMPORT R1 1; var1 = 0x89326C93
      20 [-]: GETIMPORT R3 3; var3 = 0xFC65B1D8
      21 [-]: NAMECALL R1 R1 K4; var2 = var1; var1 = var1[0xFB669000]
      22 [-]: CALL R1 3 2  ; var1 = var1(var2, var3)
      23 [-]: MOVE R0 R1   ; var0 = var1
      24 [-]: JUMPBACK L0  ; goto L0
L 4:  25 [-]: GETIMPORT R1 1; var1 = 0x89326C93
      26 [-]: NAMECALL R1 R1 K10; var2 = var1; var1 = var1[0xFB64E76C]
      27 [-]: CALL R1 2 2  ; var1 = var1(var2)
L 5:  28 [-]: FASTCALL1 62 R0 L6; 
      29 [-]: MOVE R3 R0   ; var3 = var0
      30 [-]: GETIMPORT R2 6; var2 = 0x7B998233
      31 [-]: CALL R2 2 2  ; var2 = var2(var3)
L 6:  32 [-]: JUMPIF R2 L25; goto L25 if var2
      33 [-]: LENGTH R2 R0 ; var2 = #var0
      34 [-]: LOADN R3 0   ; var3 = 0
      35 [-]: JUMPIFNOTLT R3 R2 L25; goto L25 if var3 >= var805
      36 [-]: GETTABLEN R3 R0 1; var3 = var0[1]
      37 [-]: FASTCALL1 62 R3 L7; 
      38 [-]: GETIMPORT R2 6; var2 = 0x7B998233
      39 [-]: CALL R2 2 2  ; var2 = var2(var3)
L 7:  40 [-]: JUMPIF R2 L25; goto L25 if var2
      41 [-]: GETIMPORT R2 12; var2 = _T
      42 [-]: GETIMPORT R3 14; var3 = 0x55156FF7
      43 [-]: CALL R3 1 2  ; var3 = var3()
      44 [-]: SETTABLEKS R3 R2 K15; var3["DragonRespawnMonitorTime"] = var2
      45 [-]: GETIMPORT R2 1; var2 = 0x89326C93
      46 [-]: NAMECALL R2 R2 K10; var3 = var2; var2 = var2[0xFB64E76C]
      47 [-]: CALL R2 2 2  ; var2 = var2(var3)
      48 [-]: MOVE R1 R2   ; var1 = var2
      49 [-]: GETIMPORT R2 1; var2 = 0x89326C93
      50 [-]: NAMECALL R2 R2 K16; var3 = var2; var2 = var2[0x18D05D30]
      51 [-]: CALL R2 2 2  ; var2 = var2(var3)
      52 [-]: JUMPIFNOT R2 L8; goto L8 if not var2
      53 [-]: GETUPVAL R2 0; var2 = upvalues[0]
      54 [-]: CALL R2 1 1  ; var2()
L 8:  55 [-]: NAMECALL R2 R1 K17; var3 = var1; var2 = var1[0xBB610E5B]
      56 [-]: CALL R2 2 2  ; var2 = var2(var3)
      57 [-]: FASTCALL1 62 R2 L9; 
      58 [-]: MOVE R4 R2   ; var4 = var2
      59 [-]: GETIMPORT R3 6; var3 = 0x7B998233
      60 [-]: CALL R3 2 2  ; var3 = var3(var4)
L 9:  61 [-]: JUMPIF R3 L21; goto L21 if var3
      62 [-]: NAMECALL R3 R2 K18; var4 = var2; var3 = var2[0x2047CFE7]
      63 [-]: CALL R3 2 2  ; var3 = var3(var4)
      64 [-]: JUMPIF R3 L10; goto L10 if var3
      65 [-]: NAMECALL R3 R2 K19; var4 = var2; var3 = var2[0x73901ACF]
      66 [-]: CALL R3 2 2  ; var3 = var3(var4)
      67 [-]: JUMPIFNOT R3 L21; goto L21 if not var3
L10:  68 [-]: FASTCALL1 62 R2 L11; 
      69 [-]: MOVE R4 R2   ; var4 = var2
      70 [-]: GETIMPORT R3 6; var3 = 0x7B998233
      71 [-]: CALL R3 2 2  ; var3 = var3(var4)
L11:  72 [-]: JUMPIF R3 L13; goto L13 if var3
      73 [-]: NAMECALL R3 R2 K18; var4 = var2; var3 = var2[0x2047CFE7]
      74 [-]: CALL R3 2 2  ; var3 = var3(var4)
      75 [-]: JUMPIF R3 L12; goto L12 if var3
      76 [-]: NAMECALL R3 R2 K19; var4 = var2; var3 = var2[0x73901ACF]
      77 [-]: CALL R3 2 2  ; var3 = var3(var4)
      78 [-]: JUMPIFNOT R3 L13; goto L13 if not var3
L12:  79 [-]: GETIMPORT R3 12; var3 = _T
      80 [-]: GETIMPORT R4 14; var4 = 0x55156FF7
      81 [-]: CALL R4 1 2  ; var4 = var4()
      82 [-]: SETTABLEKS R4 R3 K15; var4["DragonRespawnMonitorTime"] = var3
      83 [-]: GETIMPORT R3 9; var3 = 0xCBD666E1
      84 [-]: LOADN R4 0   ; var4 = 0
      85 [-]: CALL R3 2 1  ; var3(var4)
      86 [-]: JUMPBACK L10 ; goto L10
L13:  87 [-]: FASTCALL1 62 R2 L14; 
      88 [-]: MOVE R4 R2   ; var4 = var2
      89 [-]: GETIMPORT R3 6; var3 = 0x7B998233
      90 [-]: CALL R3 2 2  ; var3 = var3(var4)
L14:  91 [-]: JUMPIFNOT R3 L15; goto L15 if not var3
      92 [-]: GETIMPORT R3 12; var3 = _T
      93 [-]: GETIMPORT R4 14; var4 = 0x55156FF7
      94 [-]: CALL R4 1 2  ; var4 = var4()
      95 [-]: SETTABLEKS R4 R3 K15; var4["DragonRespawnMonitorTime"] = var3
      96 [-]: NAMECALL R3 R1 K17; var4 = var1; var3 = var1[0xBB610E5B]
      97 [-]: CALL R3 2 2  ; var3 = var3(var4)
      98 [-]: MOVE R2 R3   ; var2 = var3
      99 [-]: GETIMPORT R3 9; var3 = 0xCBD666E1
     100 [-]: LOADN R4 0   ; var4 = 0
     101 [-]: CALL R3 2 1  ; var3(var4)
     102 [-]: JUMPBACK L13 ; goto L13
L15: 103 [-]: GETUPVAL R3 1; var3 = upvalues[1]
     104 [-]: GETIMPORT R4 1; var4 = 0x89326C93
     105 [-]: GETUPVAL R7 2; var7 = upvalues[2]
     106 [-]: GETIMPORT R9 21; var9 = 0xBE190284
     107 [-]: GETUPVAL R11 3; var11 = upvalues[3]
     108 [-]: NAMECALL R9 R9 K22; var10 = var9; var9 = var9[0x0EB34C69]
     109 [-]: CALL R9 3 2  ; var9 = var9(var10, var11)
     110 [-]: JUMPXEQKN R9 K23 L16 NOT; 
     111 [-]: LOADK R8 K24 ; var8 = "SHIELD"
     112 [-]: JUMP L18     ; goto L18
L16: 113 [-]: JUMPXEQKN R9 K25 L17 NOT; 
     114 [-]: LOADK R8 K26 ; var8 = "HORSE"
     115 [-]: JUMP L18     ; goto L18
L17: 116 [-]: LOADK R8 K27 ; var8 = "DEFAULT"
L18: 117 [-]: GETTABLE R6 R7 R8; var6 = var7[var8]
     118 [-]: NAMECALL R4 R4 K28; var5 = var4; var4 = var4[0x46A0EBF5]
     119 [-]: CALL R4 3 2  ; var4 = var4(var5, var6)
     120 [-]: FASTCALL1 62 R4 L19; 
     121 [-]: MOVE R6 R4   ; var6 = var4
     122 [-]: GETIMPORT R5 6; var5 = 0x7B998233
     123 [-]: CALL R5 2 2  ; var5 = var5(var6)
L19: 124 [-]: JUMPIF R5 L20; goto L20 if var5
     125 [-]: NAMECALL R5 R4 K29; var6 = var4; var5 = var4[0xD1586535]
     126 [-]: CALL R5 2 2  ; var5 = var5(var6)
     127 [-]: MOVE R3 R5   ; var3 = var5
L20: 128 [-]: MOVE R7 R3   ; var7 = var3
     129 [-]: NAMECALL R8 R2 K30; var9 = var2; var8 = var2[0xCB3851B8]
     130 [-]: CALL R8 2 0  ; var8, ... = var8(var9)
     131 [-]: NAMECALL R5 R2 K31; var6 = var2; var5 = var2[0x589EF1C1]
     132 [-]: CALL R5 0 1  ; var5(var6, ...)
L21: 133 [-]: FASTCALL1 62 R2 L22; 
     134 [-]: MOVE R4 R2   ; var4 = var2
     135 [-]: GETIMPORT R3 6; var3 = 0x7B998233
     136 [-]: CALL R3 2 2  ; var3 = var3(var4)
L22: 137 [-]: JUMPIF R3 L24; goto L24 if var3
     138 [-]: NAMECALL R3 R2 K32; var4 = var2; var3 = var2[0xDE321E6F]
     139 [-]: CALL R3 2 2  ; var3 = var3(var4)
     140 [-]: NAMECALL R3 R3 K33; var4 = var3; var3 = var3[0xF7D48EE0]
     141 [-]: CALL R3 2 2  ; var3 = var3(var4)
     142 [-]: FASTCALL1 62 R3 L23; 
     143 [-]: MOVE R5 R3   ; var5 = var3
     144 [-]: GETIMPORT R4 6; var4 = 0x7B998233
     145 [-]: CALL R4 2 2  ; var4 = var4(var5)
L23: 146 [-]: JUMPIF R4 L24; goto L24 if var4
     147 [-]: LOADB R6 1   ; var6 = true
     148 [-]: GETIMPORT R7 35; var7 = 0x0469F296
     149 [-]: LOADK R8 K36 ; var8 = "OPERATOR_TRANSFERENCE"
     150 [-]: CALL R7 2 0  ; var7, ... = var7(var8)
     151 [-]: NAMECALL R4 R3 K37; var5 = var3; var4 = var3[0x83DF59E9]
     152 [-]: CALL R4 0 1  ; var4(var5, ...)
L24: 153 [-]: GETIMPORT R3 12; var3 = _T
     154 [-]: LOADB R4 1   ; var4 = true
     155 [-]: SETTABLEKS R4 R3 K38; var4["DisableSecondChance"] = var3
     156 [-]: GETIMPORT R3 9; var3 = 0xCBD666E1
     157 [-]: LOADN R4 0   ; var4 = 0
     158 [-]: CALL R3 2 1  ; var3(var4)
     159 [-]: JUMPBACK L5  ; goto L5
L25: 160 [-]: RETURN R0 0  ; 


; Name:            
; Defined at line: 860
; #Upvalues:       0
; #Parameters:     2
; Is_vararg:       0
; Max Stack Size:  9

       0 [-]: NAMECALL R6 R0 K1; var7 = var0; var6 = var0[0xB40C191A]
       1 [-]: CALL R6 2 2  ; var6 = var6(var7)
       2 [-]: GETIMPORT R8 3; var8 = 0xC72EF5D9
       3 [-]: GETTABLE R7 R8 R1; var7 = var8[var1]
       4 [-]: MUL R5 R6 R7 ; var5 = var6 * var7
       5 [-]: SUBK R4 R5 K0; var4 = var5 - 1
       6 [-]: NAMECALL R2 R0 K4; var3 = var0; var2 = var0[0x014DB014]
       7 [-]: CALL R2 3 1  ; var2(var3, var4)
       8 [-]: GETIMPORT R4 6; var4 = 0x68F0F00C
       9 [-]: LOADB R5 1   ; var5 = true
      10 [-]: LOADN R6 2   ; var6 = 2
      11 [-]: LOADN R7 1   ; var7 = 1
      12 [-]: LOADB R8 1   ; var8 = true
      13 [-]: NAMECALL R2 R0 K7; var3 = var0; var2 = var0[0x5D985C7E]
      14 [-]: CALL R2 7 1  ; var2(var3, var4, var5, var6, var7, var8)
      15 [-]: GETIMPORT R4 9; var4 = 0x89AF9D7E
      16 [-]: LOADB R5 0   ; var5 = false
      17 [-]: LOADN R6 2   ; var6 = 2
      18 [-]: LOADN R7 2   ; var7 = 2
      19 [-]: LOADB R8 1   ; var8 = true
      20 [-]: NAMECALL R2 R0 K7; var3 = var0; var2 = var0[0x5D985C7E]
      21 [-]: CALL R2 7 1  ; var2(var3, var4, var5, var6, var7, var8)
      22 [-]: RETURN R0 0  ; 


; Name:            
; Defined at line: 866
; #Upvalues:       0
; #Parameters:     0
; Is_vararg:       0
; Max Stack Size:  10

       0 [-]: LOADN R2 1   ; var2 = 1
       1 [-]: GETIMPORT R3 1; var3 = 0xBE25FDE8
       2 [-]: LENGTH R0 R3 ; var0 = #var3
       3 [-]: LOADN R1 1   ; var1 = 1
       4 [-]: FORNPREP R0 L7; nforprep start - [escape at L7] -- var0 = iterator
L 0:   5 [-]: GETIMPORT R5 1; var5 = 0xBE25FDE8
       6 [-]: GETTABLE R4 R5 R2; var4 = var5[var2]
       7 [-]: FASTCALL1 62 R4 L1; 
       8 [-]: GETIMPORT R3 3; var3 = 0x7B998233
       9 [-]: CALL R3 2 2  ; var3 = var3(var4)
L 1:  10 [-]: JUMPIF R3 L6 ; goto L6 if var3
      11 [-]: GETIMPORT R3 5; var3 = 0x89326C93
      12 [-]: GETIMPORT R6 1; var6 = 0xBE25FDE8
      13 [-]: GETTABLE R5 R6 R2; var5 = var6[var2]
      14 [-]: NAMECALL R3 R3 K6; var4 = var3; var3 = var3[0xC7FCADA9]
      15 [-]: CALL R3 3 2  ; var3 = var3(var4, var5)
      16 [-]: FASTCALL1 62 R3 L2; 
      17 [-]: MOVE R5 R3   ; var5 = var3
      18 [-]: GETIMPORT R4 3; var4 = 0x7B998233
      19 [-]: CALL R4 2 2  ; var4 = var4(var5)
L 2:  20 [-]: JUMPIF R4 L6 ; goto L6 if var4
      21 [-]: LOADN R6 1   ; var6 = 1
      22 [-]: LENGTH R4 R3 ; var4 = #var3
      23 [-]: LOADN R5 1   ; var5 = 1
      24 [-]: FORNPREP R4 L6; nforprep start - [escape at L6] -- var4 = iterator
L 3:  25 [-]: GETTABLE R8 R3 R6; var8 = var3[var6]
      26 [-]: FASTCALL1 62 R8 L4; 
      27 [-]: GETIMPORT R7 3; var7 = 0x7B998233
      28 [-]: CALL R7 2 2  ; var7 = var7(var8)
L 4:  29 [-]: JUMPIF R7 L5 ; goto L5 if var7
      30 [-]: GETTABLE R7 R3 R6; var7 = var3[var6]
      31 [-]: LOADK R9 K7  ; var9 = "TriggerPort"
      32 [-]: NAMECALL R7 R7 K8; var8 = var7; var7 = var7[0x8EB2112D]
      33 [-]: CALL R7 3 1  ; var7(var8, var9)
L 5:  34 [-]: FORNLOOP R4 L3; nforloop end - iterate + goto L3
L 6:  35 [-]: FORNLOOP R0 L0; nforloop end - iterate + goto L0
L 7:  36 [-]: LOADN R2 1   ; var2 = 1
      37 [-]: GETIMPORT R3 10; var3 = 0x08C55D4F
      38 [-]: LENGTH R0 R3 ; var0 = #var3
      39 [-]: LOADN R1 1   ; var1 = 1
      40 [-]: FORNPREP R0 L15; nforprep start - [escape at L15] -- var0 = iterator
L 8:  41 [-]: GETIMPORT R5 10; var5 = 0x08C55D4F
      42 [-]: GETTABLE R4 R5 R2; var4 = var5[var2]
      43 [-]: FASTCALL1 62 R4 L9; 
      44 [-]: GETIMPORT R3 3; var3 = 0x7B998233
      45 [-]: CALL R3 2 2  ; var3 = var3(var4)
L 9:  46 [-]: JUMPIF R3 L14; goto L14 if var3
      47 [-]: GETIMPORT R3 5; var3 = 0x89326C93
      48 [-]: GETIMPORT R6 10; var6 = 0x08C55D4F
      49 [-]: GETTABLE R5 R6 R2; var5 = var6[var2]
      50 [-]: NAMECALL R3 R3 K6; var4 = var3; var3 = var3[0xC7FCADA9]
      51 [-]: CALL R3 3 2  ; var3 = var3(var4, var5)
      52 [-]: FASTCALL1 62 R3 L10; 
      53 [-]: MOVE R5 R3   ; var5 = var3
      54 [-]: GETIMPORT R4 3; var4 = 0x7B998233
      55 [-]: CALL R4 2 2  ; var4 = var4(var5)
L10:  56 [-]: JUMPIF R4 L14; goto L14 if var4
      57 [-]: LOADN R6 1   ; var6 = 1
      58 [-]: LENGTH R4 R3 ; var4 = #var3
      59 [-]: LOADN R5 1   ; var5 = 1
      60 [-]: FORNPREP R4 L14; nforprep start - [escape at L14] -- var4 = iterator
L11:  61 [-]: GETTABLE R8 R3 R6; var8 = var3[var6]
      62 [-]: FASTCALL1 62 R8 L12; 
      63 [-]: GETIMPORT R7 3; var7 = 0x7B998233
      64 [-]: CALL R7 2 2  ; var7 = var7(var8)
L12:  65 [-]: JUMPIF R7 L13; goto L13 if var7
      66 [-]: GETTABLE R7 R3 R6; var7 = var3[var6]
      67 [-]: LOADK R9 K11 ; var9 = "Show"
      68 [-]: NAMECALL R7 R7 K8; var8 = var7; var7 = var7[0x8EB2112D]
      69 [-]: CALL R7 3 1  ; var7(var8, var9)
L13:  70 [-]: FORNLOOP R4 L11; nforloop end - iterate + goto L11
L14:  71 [-]: FORNLOOP R0 L8; nforloop end - iterate + goto L8
L15:  72 [-]: LOADN R2 1   ; var2 = 1
      73 [-]: GETIMPORT R3 13; var3 = 0x114D2914
      74 [-]: LENGTH R0 R3 ; var0 = #var3
      75 [-]: LOADN R1 1   ; var1 = 1
      76 [-]: FORNPREP R0 L23; nforprep start - [escape at L23] -- var0 = iterator
L16:  77 [-]: GETIMPORT R5 13; var5 = 0x114D2914
      78 [-]: GETTABLE R4 R5 R2; var4 = var5[var2]
      79 [-]: FASTCALL1 62 R4 L17; 
      80 [-]: GETIMPORT R3 3; var3 = 0x7B998233
      81 [-]: CALL R3 2 2  ; var3 = var3(var4)
L17:  82 [-]: JUMPIF R3 L22; goto L22 if var3
      83 [-]: GETIMPORT R3 5; var3 = 0x89326C93
      84 [-]: GETIMPORT R6 13; var6 = 0x114D2914
      85 [-]: GETTABLE R5 R6 R2; var5 = var6[var2]
      86 [-]: NAMECALL R3 R3 K6; var4 = var3; var3 = var3[0xC7FCADA9]
      87 [-]: CALL R3 3 2  ; var3 = var3(var4, var5)
      88 [-]: FASTCALL1 62 R3 L18; 
      89 [-]: MOVE R5 R3   ; var5 = var3
      90 [-]: GETIMPORT R4 3; var4 = 0x7B998233
      91 [-]: CALL R4 2 2  ; var4 = var4(var5)
L18:  92 [-]: JUMPIF R4 L22; goto L22 if var4
      93 [-]: LOADN R6 1   ; var6 = 1
      94 [-]: LENGTH R4 R3 ; var4 = #var3
      95 [-]: LOADN R5 1   ; var5 = 1
      96 [-]: FORNPREP R4 L22; nforprep start - [escape at L22] -- var4 = iterator
L19:  97 [-]: GETTABLE R8 R3 R6; var8 = var3[var6]
      98 [-]: FASTCALL1 62 R8 L20; 
      99 [-]: GETIMPORT R7 3; var7 = 0x7B998233
     100 [-]: CALL R7 2 2  ; var7 = var7(var8)
L20: 101 [-]: JUMPIF R7 L21; goto L21 if var7
     102 [-]: GETTABLE R7 R3 R6; var7 = var3[var6]
     103 [-]: LOADK R9 K14 ; var9 = "Destroy"
     104 [-]: NAMECALL R7 R7 K8; var8 = var7; var7 = var7[0x8EB2112D]
     105 [-]: CALL R7 3 1  ; var7(var8, var9)
L21: 106 [-]: FORNLOOP R4 L19; nforloop end - iterate + goto L19
L22: 107 [-]: FORNLOOP R0 L16; nforloop end - iterate + goto L16
L23: 108 [-]: RETURN R0 0  ; 


; Name:            
; Defined at line: 907
; #Upvalues:       2
; #Parameters:     1
; Is_vararg:       0
; Max Stack Size:  14

       0 [-]: GETIMPORT R1 1; var1 = 0x89326C93
       1 [-]: GETIMPORT R3 3; var3 = 0x49ACADEB
       2 [-]: NAMECALL R1 R1 K4; var2 = var1; var1 = var1[0xC7FCADA9]
       3 [-]: CALL R1 3 2  ; var1 = var1(var2, var3)
       4 [-]: GETIMPORT R2 1; var2 = 0x89326C93
       5 [-]: NAMECALL R2 R2 K5; var3 = var2; var2 = var2[0x5D971903]
       6 [-]: CALL R2 2 2  ; var2 = var2(var3)
       7 [-]: GETUPVAL R4 0; var4 = upvalues[0]
       8 [-]: GETTABLEKS R3 R4 K6; var3 = var4[0xA559EB32]
       9 [-]: CALL R3 1 1  ; var3()
      10 [-]: GETUPVAL R4 0; var4 = upvalues[0]
      11 [-]: GETTABLEKS R3 R4 K7; var3 = var4[0xFE0D9469]
      12 [-]: CALL R3 1 1  ; var3()
      13 [-]: GETUPVAL R4 1; var4 = upvalues[1]
      14 [-]: GETTABLEKS R3 R4 K8; var3 = var4[0x9742B85B]
      15 [-]: MOVE R4 R0   ; var4 = var0
      16 [-]: GETIMPORT R5 10; var5 = 0x0469F296
      17 [-]: LOADK R6 K11 ; var6 = "Orowyrm_ArchgunDrop"
      18 [-]: CALL R5 2 0  ; var5, ... = var5(var6)
      19 [-]: CALL R3 0 1  ; var3(var4, ...)
      20 [-]: LENGTH R4 R1 ; var4 = #var1
      21 [-]: FASTCALL2 19 R4 R2 L0; 
      22 [-]: MOVE R5 R2   ; var5 = var2
      23 [-]: GETIMPORT R3 14; var3 = 0x5BCED4C4[0xAC1B386A]
      24 [-]: CALL R3 3 2  ; var3 = var3(var4, var5)
L 0:  25 [-]: NEWTABLE R4 0 0; var4 = {}
      26 [-]: LOADN R7 1   ; var7 = 1
      27 [-]: MOVE R5 R3   ; var5 = var3
      28 [-]: LOADN R6 1   ; var6 = 1
      29 [-]: FORNPREP R5 L3; nforprep start - [escape at L3] -- var5 = iterator
L 1:  30 [-]: GETTABLE R8 R1 R7; var8 = var1[var7]
      31 [-]: NAMECALL R8 R8 K15; var9 = var8; var8 = var8[0xD1586535]
      32 [-]: CALL R8 2 2  ; var8 = var8(var9)
      33 [-]: GETTABLEKS R10 R8 K17; var10 = var8["y"]
      34 [-]: ADDK R9 R10 K16; var9 = var10 + 1
      35 [-]: SETTABLEKS R9 R8 K17; var9["y"] = var8
      36 [-]: GETIMPORT R9 1; var9 = 0x89326C93
      37 [-]: GETIMPORT R11 19; var11 = 0xF69297EE
      38 [-]: MOVE R12 R8  ; var12 = var8
      39 [-]: GETIMPORT R13 21; var13 = ZERO_ROTATION
      40 [-]: NAMECALL R9 R9 K22; var10 = var9; var9 = var9[0x05909209]
      41 [-]: CALL R9 5 1  ; var9(var10, var11, var12, var13)
      42 [-]: GETIMPORT R9 1; var9 = 0x89326C93
      43 [-]: GETIMPORT R11 24; var11 = 0x45EBA2FA
      44 [-]: MOVE R12 R8  ; var12 = var8
      45 [-]: LOADB R13 0  ; var13 = false
      46 [-]: NAMECALL R9 R9 K25; var10 = var9; var9 = var9[0x659D451F]
      47 [-]: CALL R9 5 1  ; var9(var10, var11, var12, var13)
      48 [-]: GETIMPORT R9 1; var9 = 0x89326C93
      49 [-]: GETIMPORT R11 27; var11 = 0x3C8ED880
      50 [-]: MOVE R12 R8  ; var12 = var8
      51 [-]: GETIMPORT R13 21; var13 = ZERO_ROTATION
      52 [-]: NAMECALL R9 R9 K22; var10 = var9; var9 = var9[0x05909209]
      53 [-]: CALL R9 5 2  ; var9 = var9(var10, var11, var12, var13)
      54 [-]: FASTCALL2 52 R4 R9 L2; 
      55 [-]: MOVE R11 R4  ; var11 = var4
      56 [-]: MOVE R12 R9  ; var12 = var9
      57 [-]: GETIMPORT R10 30; var10 = 0x33BDD652[0x23D5322F]
      58 [-]: CALL R10 3 1 ; var10(var11, var12)
L 2:  59 [-]: FORNLOOP R5 L1; nforloop end - iterate + goto L1
L 3:  60 [-]: RETURN R4 1  ; 


; Name:            
; Defined at line: 928
; #Upvalues:       2
; #Parameters:     0
; Is_vararg:       0
; Max Stack Size:  5

       0 [-]: GETIMPORT R0 1; var0 = 0x3D106989
       1 [-]: LOADK R1 K2  ; var1 = "Preparing courtyard"
       2 [-]: CALL R0 2 1  ; var0(var1)
       3 [-]: GETIMPORT R0 4; var0 = 0x89326C93
       4 [-]: GETUPVAL R2 0; var2 = upvalues[0]
       5 [-]: NAMECALL R0 R0 K5; var1 = var0; var0 = var0[0x46A0EBF5]
       6 [-]: CALL R0 3 2  ; var0 = var0(var1, var2)
       7 [-]: FASTCALL1 62 R0 L0; 
       8 [-]: MOVE R2 R0   ; var2 = var0
       9 [-]: GETIMPORT R1 7; var1 = 0x7B998233
      10 [-]: CALL R1 2 2  ; var1 = var1(var2)
L 0:  11 [-]: JUMPIF R1 L1 ; goto L1 if var1
      12 [-]: GETIMPORT R1 1; var1 = 0x3D106989
      13 [-]: LOADK R2 K8  ; var2 = "Spawning archivist"
      14 [-]: CALL R1 2 1  ; var1(var2)
      15 [-]: LOADK R3 K9  ; var3 = "Execute"
      16 [-]: NAMECALL R1 R0 K10; var2 = var0; var1 = var0[0x8EB2112D]
      17 [-]: CALL R1 3 1  ; var1(var2, var3)
L 1:  18 [-]: GETIMPORT R1 12; var1 = 0xCBD666E1
      19 [-]: LOADN R2 0   ; var2 = 0
      20 [-]: CALL R1 2 1  ; var1(var2)
      21 [-]: GETIMPORT R1 1; var1 = 0x3D106989
      22 [-]: LOADK R2 K13 ; var2 = "Setting archivist marker"
      23 [-]: CALL R1 2 1  ; var1(var2)
      24 [-]: GETIMPORT R1 4; var1 = 0x89326C93
      25 [-]: GETUPVAL R3 1; var3 = upvalues[1]
      26 [-]: NAMECALL R1 R1 K5; var2 = var1; var1 = var1[0x46A0EBF5]
      27 [-]: CALL R1 3 2  ; var1 = var1(var2, var3)
      28 [-]: FASTCALL1 62 R1 L2; 
      29 [-]: MOVE R3 R1   ; var3 = var1
      30 [-]: GETIMPORT R2 7; var2 = 0x7B998233
      31 [-]: CALL R2 2 2  ; var2 = var2(var3)
L 2:  32 [-]: JUMPIF R2 L3 ; goto L3 if var2
      33 [-]: LOADB R4 1   ; var4 = true
      34 [-]: NAMECALL R2 R1 K14; var3 = var1; var2 = var1[0x2F8A0B83]
      35 [-]: CALL R2 3 1  ; var2(var3, var4)
L 3:  36 [-]: RETURN R0 0  ; 


; Name:            
; Defined at line: 946
; #Upvalues:       0
; #Parameters:     0
; Is_vararg:       0
; Max Stack Size:  9

       0 [-]: GETIMPORT R0 1; var0 = 0x3D106989
       1 [-]: LOADK R1 K2  ; var1 = "Extracting all players"
       2 [-]: CALL R0 2 1  ; var0(var1)
       3 [-]: GETIMPORT R0 4; var0 = 0x89326C93
       4 [-]: GETIMPORT R2 6; var2 = 0x0469F296
       5 [-]: LOADK R3 K7  ; var3 = "DragonChestOpened"
       6 [-]: CALL R2 2 0  ; var2, ... = var2(var3)
       7 [-]: NAMECALL R0 R0 K8; var1 = var0; var0 = var0[0x46A0EBF5]
       8 [-]: CALL R0 0 2  ; var0 = var0(var1, ...)
       9 [-]: FASTCALL1 62 R0 L0; 
      10 [-]: MOVE R2 R0   ; var2 = var0
      11 [-]: GETIMPORT R1 10; var1 = 0x7B998233
      12 [-]: CALL R1 2 2  ; var1 = var1(var2)
L 0:  13 [-]: JUMPIFNOT R1 L1; goto L1 if not var1
      14 [-]: GETIMPORT R1 4; var1 = 0x89326C93
      15 [-]: GETIMPORT R3 12; var3 = 0x5988157D
      16 [-]: GETIMPORT R4 14; var4 = ZERO_VECTOR
      17 [-]: GETIMPORT R5 16; var5 = ZERO_ROTATION
      18 [-]: LOADNIL R6   ; var6 = nil
      19 [-]: LOADNIL R7   ; var7 = nil
      20 [-]: LOADN R8 1   ; var8 = 1
      21 [-]: NAMECALL R1 R1 K17; var2 = var1; var1 = var1[0x05909209]
      22 [-]: CALL R1 8 2  ; var1 = var1(var2, var3, var4, var5, var6, var7, var8)
      23 [-]: MOVE R0 R1   ; var0 = var1
L 1:  24 [-]: LOADK R3 K18 ; var3 = "Execute"
      25 [-]: NAMECALL R1 R0 K19; var2 = var0; var1 = var0[0x8EB2112D]
      26 [-]: CALL R1 3 1  ; var1(var2, var3)
      27 [-]: RETURN R0 0  ; 


; Name:            
; Defined at line: 957
; #Upvalues:       4
; #Parameters:     0
; Is_vararg:       0
; Max Stack Size:  10

       0 [-]: GETIMPORT R0 1; var0 = 0x3D106989
       1 [-]: LOADK R1 K2  ; var1 = "Dragon Chest Opened - Giving rewards"
       2 [-]: CALL R0 2 1  ; var0(var1)
       3 [-]: GETIMPORT R0 4; var0 = 0xBE190284
       4 [-]: NAMECALL R0 R0 K5; var1 = var0; var0 = var0[0xEF893AEC]
       5 [-]: CALL R0 2 2  ; var0 = var0(var1)
       6 [-]: GETTABLEKS R2 R0 K6; var2 = var0["tier"]
       7 [-]: LOADN R3 0   ; var3 = 0
       8 [-]: JUMPIFLT R3 R2 L0; goto L0 if var3 < var16777499
       9 [-]: LOADB R1 0 +1; var1 = false
L 0:  10 [-]: LOADB R1 1   ; var1 = true
L 1:  11 [-]: GETTABLEKS R3 R0 K7; var3 = var0["goalTag"]
      12 [-]: GETIMPORT R4 9; var4 = 0x0469F296
      13 [-]: LOADK R5 K10 ; var5 = "KullervoQuest"
      14 [-]: CALL R4 2 2  ; var4 = var4(var5)
      15 [-]: JUMPIFEQ R3 R4 L2; goto L2 if var3 == var16777755
      16 [-]: LOADB R2 0 +1; var2 = false
L 2:  17 [-]: LOADB R2 1   ; var2 = true
L 3:  18 [-]: LOADB R3 0   ; var3 = false
      19 [-]: GETIMPORT R4 4; var4 = 0xBE190284
      20 [-]: GETUPVAL R6 0; var6 = upvalues[0]
      21 [-]: LOADN R7 0   ; var7 = 0
      22 [-]: NAMECALL R4 R4 K11; var5 = var4; var4 = var4[0x0EB34C69]
      23 [-]: CALL R4 4 2  ; var4 = var4(var5, var6, var7)
      24 [-]: JUMPXEQKN R4 K12 L4 NOT; 
      25 [-]: NOT R3 R2    ; var3 = not var2
L 4:  26 [-]: LOADNIL R4   ; var4 = nil
      27 [-]: LOADNIL R5   ; var5 = nil
      28 [-]: JUMPIFNOT R3 L5; goto L5 if not var3
      29 [-]: GETIMPORT R6 1; var6 = 0x3D106989
      30 [-]: LOADK R7 K13 ; var7 = "Kullervo bonus was earned earlier"
      31 [-]: CALL R6 2 1  ; var6(var7)
      32 [-]: GETUPVAL R7 1; var7 = upvalues[1]
      33 [-]: GETTABLEKS R6 R7 K14; var6 = var7["BONUS_TIER"]
      34 [-]: GETTABLEKS R4 R6 K15; var4 = var6["KULLERVO"]
      35 [-]: GETUPVAL R7 1; var7 = upvalues[1]
      36 [-]: GETTABLEKS R6 R7 K14; var6 = var7["BONUS_TIER"]
      37 [-]: GETTABLEKS R5 R6 K16; var5 = var6["STEELPATHKULLERVO"]
L 5:  38 [-]: JUMPIF R1 L6 ; goto L6 if var1
      39 [-]: GETUPVAL R7 1; var7 = upvalues[1]
      40 [-]: GETTABLEKS R6 R7 K17; var6 = var7[0xE6574978]
      41 [-]: GETUPVAL R9 1; var9 = upvalues[1]
      42 [-]: GETTABLEKS R8 R9 K18; var8 = var9["TIER"]
      43 [-]: GETTABLEKS R7 R8 K19; var7 = var8["DRAGON"]
      44 [-]: MOVE R8 R4   ; var8 = var4
      45 [-]: CALL R6 3 1  ; var6(var7, var8)
      46 [-]: JUMP L7      ; goto L7
L 6:  47 [-]: GETUPVAL R7 1; var7 = upvalues[1]
      48 [-]: GETTABLEKS R6 R7 K17; var6 = var7[0xE6574978]
      49 [-]: GETUPVAL R9 1; var9 = upvalues[1]
      50 [-]: GETTABLEKS R8 R9 K18; var8 = var9["TIER"]
      51 [-]: GETTABLEKS R7 R8 K20; var7 = var8["STEELDRAGON"]
      52 [-]: MOVE R8 R5   ; var8 = var5
      53 [-]: CALL R6 3 1  ; var6(var7, var8)
L 7:  54 [-]: GETIMPORT R6 22; var6 = 0xCBD666E1
      55 [-]: LOADN R7 5   ; var7 = 5
      56 [-]: CALL R6 2 1  ; var6(var7)
      57 [-]: GETUPVAL R6 2; var6 = upvalues[2]
      58 [-]: CALL R6 1 1  ; var6()
      59 [-]: GETUPVAL R6 3; var6 = upvalues[3]
      60 [-]: CALL R6 1 1  ; var6()
      61 [-]: RETURN R0 0  ; 


; Name:            
; Defined at line: 986
; #Upvalues:       0
; #Parameters:     1
; Is_vararg:       0
; Max Stack Size:  11

       0 [-]: GETIMPORT R1 1; var1 = 0x89326C93
       1 [-]: GETIMPORT R3 3; var3 = gLotusNpcAvatarType
       2 [-]: NAMECALL R4 R0 K4; var5 = var0; var4 = var0[0xD1586535]
       3 [-]: CALL R4 2 2  ; var4 = var4(var5)
       4 [-]: LOADN R5 0   ; var5 = 0
       5 [-]: LOADN R6 300 ; var6 = 300
       6 [-]: NAMECALL R1 R1 K5; var2 = var1; var1 = var1[0xFB669000]
       7 [-]: CALL R1 6 2  ; var1 = var1(var2, var3, var4, var5, var6)
       8 [-]: LOADN R4 1   ; var4 = 1
       9 [-]: LENGTH R2 R1 ; var2 = #var1
      10 [-]: LOADN R3 1   ; var3 = 1
      11 [-]: FORNPREP R2 L3; nforprep start - [escape at L3] -- var2 = iterator
L 0:  12 [-]: GETTABLE R5 R1 R4; var5 = var1[var4]
      13 [-]: FASTCALL1 62 R5 L1; 
      14 [-]: MOVE R7 R5   ; var7 = var5
      15 [-]: GETIMPORT R6 7; var6 = 0x7B998233
      16 [-]: CALL R6 2 2  ; var6 = var6(var7)
L 1:  17 [-]: JUMPIF R6 L2 ; goto L2 if var6
      18 [-]: NAMECALL R6 R5 K8; var7 = var5; var6 = var5[0x2047CFE7]
      19 [-]: CALL R6 2 2  ; var6 = var6(var7)
      20 [-]: JUMPIF R6 L2 ; goto L2 if var6
      21 [-]: JUMPIFEQ R5 R0 L2; goto L2 if var5 == var-435878331
      22 [-]: NAMECALL R6 R5 K9; var7 = var5; var6 = var5[0x808B79E6]
      23 [-]: CALL R6 2 2  ; var6 = var6(var7)
      24 [-]: NAMECALL R7 R0 K9; var8 = var0; var7 = var0[0x808B79E6]
      25 [-]: CALL R7 2 2  ; var7 = var7(var8)
      26 [-]: JUMPIFNOTEQ R6 R7 L2; goto L2 if var6 ~= var723022
      27 [-]: GETIMPORT R8 11; var8 = gLotusVehicleAvatarType
      28 [-]: NAMECALL R6 R5 K12; var7 = var5; var6 = var5[0xF2DEAF69]
      29 [-]: CALL R6 3 2  ; var6 = var6(var7, var8)
      30 [-]: JUMPIF R6 L2 ; goto L2 if var6
      31 [-]: GETIMPORT R6 1; var6 = 0x89326C93
      32 [-]: GETIMPORT R8 14; var8 = 0xF69297EE
      33 [-]: NAMECALL R9 R5 K4; var10 = var5; var9 = var5[0xD1586535]
      34 [-]: CALL R9 2 2  ; var9 = var9(var10)
      35 [-]: GETIMPORT R10 16; var10 = ZERO_ROTATION
      36 [-]: NAMECALL R6 R6 K17; var7 = var6; var6 = var6[0x05909209]
      37 [-]: CALL R6 5 1  ; var6(var7, var8, var9, var10)
      38 [-]: NAMECALL R6 R5 K18; var7 = var5; var6 = var5[0xA2880940]
      39 [-]: CALL R6 2 1  ; var6(var7)
L 2:  40 [-]: FORNLOOP R2 L0; nforloop end - iterate + goto L0
L 3:  41 [-]: RETURN R0 0  ; 


; Name:            
; Defined at line: 997
; #Upvalues:       7
; #Parameters:     0
; Is_vararg:       0
; Max Stack Size:  17

       0 [-]: GETIMPORT R0 1; var0 = 0x89326C93
       1 [-]: GETIMPORT R2 3; var2 = 0xFC65B1D8
       2 [-]: NAMECALL R0 R0 K4; var1 = var0; var0 = var0[0xFB669000]
       3 [-]: CALL R0 3 2  ; var0 = var0(var1, var2)
       4 [-]: FASTCALL1 62 R0 L0; 
       5 [-]: MOVE R2 R0   ; var2 = var0
       6 [-]: GETIMPORT R1 6; var1 = 0x7B998233
       7 [-]: CALL R1 2 2  ; var1 = var1(var2)
L 0:   8 [-]: JUMPIF R1 L2 ; goto L2 if var1
       9 [-]: GETTABLEN R2 R0 1; var2 = var0[1]
      10 [-]: FASTCALL1 62 R2 L1; 
      11 [-]: GETIMPORT R1 6; var1 = 0x7B998233
      12 [-]: CALL R1 2 2  ; var1 = var1(var2)
L 1:  13 [-]: JUMPIF R1 L2 ; goto L2 if var1
      14 [-]: GETUPVAL R1 0; var1 = upvalues[0]
      15 [-]: GETTABLEN R2 R0 1; var2 = var0[1]
      16 [-]: CALL R1 2 1  ; var1(var2)
L 2:  17 [-]: GETIMPORT R1 8; var1 = 0xBE190284
      18 [-]: GETUPVAL R3 1; var3 = upvalues[1]
      19 [-]: LOADN R4 10  ; var4 = 10
      20 [-]: NAMECALL R1 R1 K9; var2 = var1; var1 = var1[0x751F061D]
      21 [-]: CALL R1 4 1  ; var1(var2, var3, var4)
      22 [-]: GETIMPORT R1 8; var1 = 0xBE190284
      23 [-]: GETUPVAL R4 2; var4 = upvalues[2]
      24 [-]: GETTABLEKS R3 R4 K10; var3 = var4["NV_CURRENT_MOOD"]
      25 [-]: LOADN R4 0   ; var4 = 0
      26 [-]: NAMECALL R1 R1 K11; var2 = var1; var1 = var1[0x0EB34C69]
      27 [-]: CALL R1 4 2  ; var1 = var1(var2, var3, var4)
      28 [-]: GETIMPORT R3 13; var3 = 0x8982A352
      29 [-]: LOADN R5 1   ; var5 = 1
      30 [-]: FASTCALL2 18 R5 R1 L3; 
      31 [-]: MOVE R6 R1   ; var6 = var1
      32 [-]: GETIMPORT R4 16; var4 = 0x5BCED4C4[0xB62ECFE0]
      33 [-]: CALL R4 3 2  ; var4 = var4(var5, var6)
L 3:  34 [-]: GETTABLE R2 R3 R4; var2 = var3[var4]
      35 [-]: GETUPVAL R4 3; var4 = upvalues[3]
      36 [-]: GETTABLEKS R3 R4 K17; var3 = var4[0x9742B85B]
      37 [-]: MOVE R4 R2   ; var4 = var2
      38 [-]: GETIMPORT R5 19; var5 = 0x0469F296
      39 [-]: LOADK R6 K20 ; var6 = "OrowyrmCharacter_OnDefeat"
      40 [-]: CALL R5 2 0  ; var5, ... = var5(var6)
      41 [-]: CALL R3 0 1  ; var3(var4, ...)
      42 [-]: GETIMPORT R3 1; var3 = 0x89326C93
      43 [-]: GETIMPORT R5 19; var5 = 0x0469F296
      44 [-]: LOADK R6 K21 ; var6 = "DragonDownedCin"
      45 [-]: CALL R5 2 0  ; var5, ... = var5(var6)
      46 [-]: NAMECALL R3 R3 K22; var4 = var3; var3 = var3[0x46A0EBF5]
      47 [-]: CALL R3 0 2  ; var3 = var3(var4, ...)
      48 [-]: FASTCALL1 62 R3 L4; 
      49 [-]: MOVE R5 R3   ; var5 = var3
      50 [-]: GETIMPORT R4 6; var4 = 0x7B998233
      51 [-]: CALL R4 2 2  ; var4 = var4(var5)
L 4:  52 [-]: JUMPIF R4 L5 ; goto L5 if var4
      53 [-]: LOADK R6 K23 ; var6 = "StartPlaying"
      54 [-]: NAMECALL R4 R3 K24; var5 = var3; var4 = var3[0x8EB2112D]
      55 [-]: CALL R4 3 1  ; var4(var5, var6)
L 5:  56 [-]: NAMECALL R4 R3 K25; var5 = var3; var4 = var3[0x1C84839C]
      57 [-]: CALL R4 2 2  ; var4 = var4(var5)
      58 [-]: JUMPIFNOT R4 L6; goto L6 if not var4
      59 [-]: GETIMPORT R4 27; var4 = 0xCBD666E1
      60 [-]: LOADN R5 0   ; var5 = 0
      61 [-]: CALL R4 2 1  ; var4(var5)
      62 [-]: JUMPBACK L5  ; goto L5
L 6:  63 [-]: GETIMPORT R4 1; var4 = 0x89326C93
      64 [-]: NAMECALL R4 R4 K28; var5 = var4; var4 = var4[0x18D05D30]
      65 [-]: CALL R4 2 2  ; var4 = var4(var5)
      66 [-]: JUMPIFNOT R4 L31; goto L31 if not var4
      67 [-]: FASTCALL1 62 R0 L7; 
      68 [-]: MOVE R5 R0   ; var5 = var0
      69 [-]: GETIMPORT R4 6; var4 = 0x7B998233
      70 [-]: CALL R4 2 2  ; var4 = var4(var5)
L 7:  71 [-]: JUMPIF R4 L11; goto L11 if var4
      72 [-]: LOADN R6 1   ; var6 = 1
      73 [-]: LENGTH R4 R0 ; var4 = #var0
      74 [-]: LOADN R5 1   ; var5 = 1
      75 [-]: FORNPREP R4 L11; nforprep start - [escape at L11] -- var4 = iterator
L 8:  76 [-]: GETTABLE R8 R0 R6; var8 = var0[var6]
      77 [-]: FASTCALL1 62 R8 L9; 
      78 [-]: GETIMPORT R7 6; var7 = 0x7B998233
      79 [-]: CALL R7 2 2  ; var7 = var7(var8)
L 9:  80 [-]: JUMPIF R7 L10; goto L10 if var7
      81 [-]: GETTABLE R7 R0 R6; var7 = var0[var6]
      82 [-]: NAMECALL R7 R7 K29; var8 = var7; var7 = var7[0xA2880940]
      83 [-]: CALL R7 2 1  ; var7(var8)
L10:  84 [-]: FORNLOOP R4 L8; nforloop end - iterate + goto L8
L11:  85 [-]: GETIMPORT R4 1; var4 = 0x89326C93
      86 [-]: NAMECALL R4 R4 K30; var5 = var4; var4 = var4[0x7D108DDB]
      87 [-]: CALL R4 2 2  ; var4 = var4(var5)
      88 [-]: LOADN R7 1   ; var7 = 1
      89 [-]: LENGTH R5 R4 ; var5 = #var4
      90 [-]: LOADN R6 1   ; var6 = 1
      91 [-]: FORNPREP R5 L18; nforprep start - [escape at L18] -- var5 = iterator
L12:  92 [-]: GETTABLE R8 R4 R7; var8 = var4[var7]
      93 [-]: FASTCALL1 62 R8 L13; 
      94 [-]: MOVE R10 R8  ; var10 = var8
      95 [-]: GETIMPORT R9 6; var9 = 0x7B998233
      96 [-]: CALL R9 2 2  ; var9 = var9(var10)
L13:  97 [-]: JUMPIF R9 L17; goto L17 if var9
      98 [-]: NAMECALL R9 R8 K31; var10 = var8; var9 = var8[0xBB610E5B]
      99 [-]: CALL R9 2 2  ; var9 = var9(var10)
     100 [-]: FASTCALL1 62 R9 L14; 
     101 [-]: MOVE R11 R9  ; var11 = var9
     102 [-]: GETIMPORT R10 6; var10 = 0x7B998233
     103 [-]: CALL R10 2 2 ; var10 = var10(var11)
L14: 104 [-]: JUMPIF R10 L15; goto L15 if var10
     105 [-]: NAMECALL R10 R9 K32; var11 = var9; var10 = var9[0xDE321E6F]
     106 [-]: CALL R10 2 2 ; var10 = var10(var11)
     107 [-]: LOADK R12 K33; var12 = 100000
     108 [-]: MOVE R13 R9  ; var13 = var9
     109 [-]: GETIMPORT R14 19; var14 = 0x0469F296
     110 [-]: LOADK R15 K34; var15 = "/Lotus/Language/Actions/CompleteXP"
     111 [-]: CALL R14 2 0 ; var14, ... = var14(var15)
     112 [-]: NAMECALL R10 R10 K35; var11 = var10; var10 = var10[0x8DB2624F]
     113 [-]: CALL R10 0 1 ; var10(var11, ...)
L15: 114 [-]: LOADN R12 8  ; var12 = 8
     115 [-]: NAMECALL R10 R8 K36; var11 = var8; var10 = var8[0xE3A0BBCA]
     116 [-]: CALL R10 3 2 ; var10 = var10(var11, var12)
     117 [-]: FASTCALL1 62 R10 L16; 
     118 [-]: MOVE R12 R10 ; var12 = var10
     119 [-]: GETIMPORT R11 6; var11 = 0x7B998233
     120 [-]: CALL R11 2 2 ; var11 = var11(var12)
L16: 121 [-]: JUMPIF R11 L17; goto L17 if var11
     122 [-]: NAMECALL R11 R10 K32; var12 = var10; var11 = var10[0xDE321E6F]
     123 [-]: CALL R11 2 2 ; var11 = var11(var12)
     124 [-]: LOADB R14 1  ; var14 = true
     125 [-]: NAMECALL R12 R11 K37; var13 = var11; var12 = var11[0x0B5EC5B5]
     126 [-]: CALL R12 3 1 ; var12(var13, var14)
     127 [-]: LOADN R14 0  ; var14 = 0
     128 [-]: LOADB R15 1  ; var15 = true
     129 [-]: NAMECALL R12 R11 K38; var13 = var11; var12 = var11[0x35B09371]
     130 [-]: CALL R12 4 1 ; var12(var13, var14, var15)
     131 [-]: LOADN R14 5  ; var14 = 5
     132 [-]: NAMECALL R12 R11 K39; var13 = var11; var12 = var11[0xD80991C3]
     133 [-]: CALL R12 3 1 ; var12(var13, var14)
     134 [-]: GETIMPORT R14 41; var14 = 0x51395EAF
     135 [-]: LOADB R15 1  ; var15 = true
     136 [-]: NAMECALL R12 R10 K42; var13 = var10; var12 = var10[0x511D26B8]
     137 [-]: CALL R12 4 1 ; var12(var13, var14, var15)
     138 [-]: LOADN R14 5  ; var14 = 5
     139 [-]: LOADN R15 0  ; var15 = 0
     140 [-]: LOADN R16 2  ; var16 = 2
     141 [-]: NAMECALL R12 R11 K43; var13 = var11; var12 = var11[0xC69087F6]
     142 [-]: CALL R12 5 1 ; var12(var13, var14, var15, var16)
L17: 143 [-]: FORNLOOP R5 L12; nforloop end - iterate + goto L12
L18: 144 [-]: GETIMPORT R5 1; var5 = 0x89326C93
     145 [-]: GETIMPORT R7 45; var7 = 0x575745BF
     146 [-]: NAMECALL R5 R5 K22; var6 = var5; var5 = var5[0x46A0EBF5]
     147 [-]: CALL R5 3 2  ; var5 = var5(var6, var7)
     148 [-]: FASTCALL1 62 R5 L19; 
     149 [-]: MOVE R7 R5   ; var7 = var5
     150 [-]: GETIMPORT R6 6; var6 = 0x7B998233
     151 [-]: CALL R6 2 2  ; var6 = var6(var7)
L19: 152 [-]: JUMPIF R6 L31; goto L31 if var6
     153 [-]: LOADB R6 0   ; var6 = false
     154 [-]: SETUPVAL R6 4; upvalues[6] = var4
     155 [-]: GETIMPORT R6 1; var6 = 0x89326C93
     156 [-]: GETIMPORT R8 47; var8 = 0x94699BD5
     157 [-]: NAMECALL R9 R5 K48; var10 = var5; var9 = var5[0xD1586535]
     158 [-]: CALL R9 2 2  ; var9 = var9(var10)
     159 [-]: LOADN R10 5  ; var10 = 5
     160 [-]: NAMECALL R6 R6 K49; var7 = var6; var6 = var6[0x4E5939A5]
     161 [-]: CALL R6 5 2  ; var6 = var6(var7, var8, var9, var10)
     162 [-]: FASTCALL1 62 R6 L20; 
     163 [-]: MOVE R8 R6   ; var8 = var6
     164 [-]: GETIMPORT R7 6; var7 = 0x7B998233
     165 [-]: CALL R7 2 2  ; var7 = var7(var8)
L20: 166 [-]: JUMPIF R7 L24; goto L24 if var7
     167 [-]: GETIMPORT R9 51; var9 = gContextActionType
     168 [-]: NAMECALL R7 R6 K52; var8 = var6; var7 = var6[0xC9F6A7D7]
     169 [-]: CALL R7 3 2  ; var7 = var7(var8, var9)
     170 [-]: FASTCALL1 62 R7 L21; 
     171 [-]: MOVE R9 R7   ; var9 = var7
     172 [-]: GETIMPORT R8 6; var8 = 0x7B998233
     173 [-]: CALL R8 2 2  ; var8 = var8(var9)
L21: 174 [-]: JUMPIF R8 L22; goto L22 if var8
     175 [-]: NAMECALL R8 R7 K53; var9 = var7; var8 = var7[0xF37943FF]
     176 [-]: CALL R8 2 2  ; var8 = var8(var9)
     177 [-]: JUMPIF R8 L23; goto L23 if var8
L22: 178 [-]: LOADB R8 1   ; var8 = true
     179 [-]: SETUPVAL R8 4; upvalues[8] = var4
L23: 180 [-]: GETIMPORT R8 1; var8 = 0x89326C93
     181 [-]: MOVE R10 R6  ; var10 = var6
     182 [-]: NAMECALL R8 R8 K54; var9 = var8; var8 = var8[0x59C96E77]
     183 [-]: CALL R8 3 1  ; var8(var9, var10)
L24: 184 [-]: GETIMPORT R7 1; var7 = 0x89326C93
     185 [-]: GETIMPORT R9 56; var9 = 0x6C3E09EF
     186 [-]: NAMECALL R10 R5 K48; var11 = var5; var10 = var5[0xD1586535]
     187 [-]: CALL R10 2 2 ; var10 = var10(var11)
     188 [-]: LOADN R11 5  ; var11 = 5
     189 [-]: NAMECALL R7 R7 K49; var8 = var7; var7 = var7[0x4E5939A5]
     190 [-]: CALL R7 5 2  ; var7 = var7(var8, var9, var10, var11)
     191 [-]: JUMPIFNOT R7 L25; goto L25 if not var7
     192 [-]: LOADB R8 1   ; var8 = true
     193 [-]: SETUPVAL R8 4; upvalues[8] = var4
L25: 194 [-]: GETUPVAL R8 4; var8 = upvalues[4]
     195 [-]: JUMPIFNOT R8 L26; goto L26 if not var8
     196 [-]: GETIMPORT R8 58; var8 = 0x3D106989
     197 [-]: LOADK R9 K59 ; var9 = "Dragon chest opened already"
     198 [-]: CALL R8 2 1  ; var8(var9)
     199 [-]: JUMP L31     ; goto L31
L26: 200 [-]: GETIMPORT R8 58; var8 = 0x3D106989
     201 [-]: LOADK R9 K60 ; var9 = "Create dragon chest block"
     202 [-]: CALL R8 2 1  ; var8(var9)
     203 [-]: GETUPVAL R9 5; var9 = upvalues[5]
     204 [-]: GETTABLEKS R8 R9 K61; var8 = var9[0x0598B961]
     205 [-]: GETIMPORT R9 47; var9 = 0x94699BD5
     206 [-]: MOVE R10 R5  ; var10 = var5
     207 [-]: MOVE R11 R5  ; var11 = var5
     208 [-]: LOADB R12 1  ; var12 = true
     209 [-]: LOADB R13 0  ; var13 = false
     210 [-]: CALL R8 6 2  ; var8 = var8(var9, var10, var11, var12, var13)
     211 [-]: GETIMPORT R11 8; var11 = 0xBE190284
     212 [-]: NAMECALL R11 R11 K62; var12 = var11; var11 = var11[0xEF893AEC]
     213 [-]: CALL R11 2 2 ; var11 = var11(var12)
     214 [-]: GETTABLEKS R10 R11 K63; var10 = var11["tier"]
     215 [-]: LOADN R11 0  ; var11 = 0
     216 [-]: JUMPIFLT R11 R10 L27; goto L27 if var11 < var16779547
     217 [-]: LOADB R9 0 +1; var9 = false
L27: 218 [-]: LOADB R9 1   ; var9 = true
L28: 219 [-]: JUMPIF R9 L29; goto L29 if var9
     220 [-]: GETUPVAL R12 6; var12 = upvalues[6]
     221 [-]: GETTABLEKS R11 R12 K64; var11 = var12["TIER"]
     222 [-]: GETTABLEKS R10 R11 K65; var10 = var11["DRAGON"]
     223 [-]: SETTABLEKS R10 R8 K66; var10["rewardTier"] = var8
     224 [-]: JUMP L30     ; goto L30
L29: 225 [-]: GETUPVAL R12 6; var12 = upvalues[6]
     226 [-]: GETTABLEKS R11 R12 K64; var11 = var12["TIER"]
     227 [-]: GETTABLEKS R10 R11 K67; var10 = var11["STEELDRAGON"]
     228 [-]: SETTABLEKS R10 R8 K66; var10["rewardTier"] = var8
L30: 229 [-]: GETGLOBAL R12 K68; var12 = "DragonChestOpened"
     230 [-]: NAMECALL R10 R8 K69; var11 = var8; var10 = var8[0x0E69F035]
     231 [-]: CALL R10 3 1 ; var10(var11, var12)
L31: 232 [-]: GETIMPORT R4 71; var4 = _T
     233 [-]: LOADB R5 0   ; var5 = false
     234 [-]: SETTABLEKS R5 R4 K72; var5["DisableSecondChance"] = var4
     235 [-]: GETUPVAL R5 3; var5 = upvalues[3]
     236 [-]: GETTABLEKS R4 R5 K17; var4 = var5[0x9742B85B]
     237 [-]: MOVE R5 R2   ; var5 = var2
     238 [-]: GETIMPORT R6 19; var6 = 0x0469F296
     239 [-]: LOADK R7 K73 ; var7 = "Orowyrm_OrowyrmDefeated"
     240 [-]: CALL R6 2 0  ; var6, ... = var6(var7)
     241 [-]: CALL R4 0 1  ; var4(var5, ...)
     242 [-]: RETURN R0 0  ; 


; Name:            
; Defined at line: 1097
; #Upvalues:       1
; #Parameters:     1
; Is_vararg:       0
; Max Stack Size:  7

       0 [-]: FASTCALL1 62 R0 L0; 
       1 [-]: MOVE R2 R0   ; var2 = var0
       2 [-]: GETIMPORT R1 1; var1 = 0x7B998233
       3 [-]: CALL R1 2 2  ; var1 = var1(var2)
L 0:   4 [-]: JUMPIFNOT R1 L1; goto L1 if not var1
       5 [-]: RETURN R0 0  ; 
L 1:   6 [-]: GETIMPORT R1 3; var1 = 0xBE190284
       7 [-]: GETUPVAL R4 0; var4 = upvalues[0]
       8 [-]: GETTABLEKS R3 R4 K4; var3 = var4["NV_CURRENT_MOOD"]
       9 [-]: LOADN R4 0   ; var4 = 0
      10 [-]: NAMECALL R1 R1 K5; var2 = var1; var1 = var1[0x0EB34C69]
      11 [-]: CALL R1 4 2  ; var1 = var1(var2, var3, var4)
      12 [-]: LOADN R2 1   ; var2 = 1
      13 [-]: JUMPIFNOTLE R2 R1 L2; goto L2 if var2 > var328263
      14 [-]: LOADN R2 5   ; var2 = 5
      15 [-]: JUMPIFNOTLE R1 R2 L2; goto L2 if var1 > var459342
      16 [-]: GETIMPORT R2 7; var2 = _T
      17 [-]: GETIMPORT R4 9; var4 = 0xDA66076B
      18 [-]: GETTABLE R3 R4 R1; var3 = var4[var1]
      19 [-]: SETTABLEKS R3 R2 K10; var3["OverrideBossNameTag"] = var2
      20 [-]: GETIMPORT R4 12; var4 = 0x0469F296
      21 [-]: GETIMPORT R6 9; var6 = 0xDA66076B
      22 [-]: GETTABLE R5 R6 R1; var5 = var6[var1]
      23 [-]: CALL R4 2 0  ; var4, ... = var4(var5)
      24 [-]: NAMECALL R2 R0 K13; var3 = var0; var2 = var0[0xC28CB9C0]
      25 [-]: CALL R2 0 1  ; var2(var3, ...)
      26 [-]: RETURN R0 0  ; 
L 2:  27 [-]: GETIMPORT R2 7; var2 = _T
      28 [-]: LOADK R3 K14 ; var3 = "/Lotus/Language/Duviri/DragonName"
      29 [-]: SETTABLEKS R3 R2 K10; var3["OverrideBossNameTag"] = var2
      30 [-]: RETURN R0 0  ; 


; Name:            
; Defined at line: 1111
; #Upvalues:       1
; #Parameters:     1
; Is_vararg:       0
; Max Stack Size:  14

       0 [-]: GETIMPORT R1 1; var1 = 0x89326C93
       1 [-]: NAMECALL R1 R1 K2; var2 = var1; var1 = var1[0x7D108DDB]
       2 [-]: CALL R1 2 2  ; var1 = var1(var2)
       3 [-]: LOADN R4 1   ; var4 = 1
       4 [-]: LENGTH R2 R1 ; var2 = #var1
       5 [-]: LOADN R3 1   ; var3 = 1
       6 [-]: FORNPREP R2 L8; nforprep start - [escape at L8] -- var2 = iterator
L 0:   7 [-]: GETTABLE R5 R1 R4; var5 = var1[var4]
       8 [-]: NAMECALL R5 R5 K3; var6 = var5; var5 = var5[0xBB610E5B]
       9 [-]: CALL R5 2 2  ; var5 = var5(var6)
      10 [-]: JUMPIFNOT R0 L2; goto L2 if not var0
      11 [-]: FASTCALL1 62 R5 L1; 
      12 [-]: MOVE R7 R5   ; var7 = var5
      13 [-]: GETIMPORT R6 5; var6 = 0x7B998233
      14 [-]: CALL R6 2 2  ; var6 = var6(var7)
L 1:  15 [-]: JUMPIF R6 L7 ; goto L7 if var6
      16 [-]: NAMECALL R6 R5 K6; var7 = var5; var6 = var5[0xA955D2C3]
      17 [-]: CALL R6 2 2  ; var6 = var6(var7)
      18 [-]: JUMPIFNOT R6 L7; goto L7 if not var6
L 2:  19 [-]: JUMPIF R0 L5 ; goto L5 if var0
      20 [-]: FASTCALL1 62 R5 L3; 
      21 [-]: MOVE R7 R5   ; var7 = var5
      22 [-]: GETIMPORT R6 5; var6 = 0x7B998233
      23 [-]: CALL R6 2 2  ; var6 = var6(var7)
L 3:  24 [-]: JUMPIF R6 L4 ; goto L4 if var6
      25 [-]: NAMECALL R6 R5 K6; var7 = var5; var6 = var5[0xA955D2C3]
      26 [-]: CALL R6 2 2  ; var6 = var6(var7)
      27 [-]: JUMPIF R6 L5 ; goto L5 if var6
L 4:  28 [-]: GETIMPORT R6 8; var6 = 0xCBD666E1
      29 [-]: LOADN R7 0   ; var7 = 0
      30 [-]: CALL R6 2 1  ; var6(var7)
      31 [-]: GETTABLE R6 R1 R4; var6 = var1[var4]
      32 [-]: NAMECALL R6 R6 K3; var7 = var6; var6 = var6[0xBB610E5B]
      33 [-]: CALL R6 2 2  ; var6 = var6(var7)
      34 [-]: MOVE R5 R6   ; var5 = var6
      35 [-]: JUMPBACK L2  ; goto L2
L 5:  36 [-]: GETIMPORT R8 10; var8 = gLotusVehicleAvatarType
      37 [-]: NAMECALL R6 R5 K11; var7 = var5; var6 = var5[0xF2DEAF69]
      38 [-]: CALL R6 3 2  ; var6 = var6(var7, var8)
      39 [-]: JUMPIF R6 L7 ; goto L7 if var6
      40 [-]: NAMECALL R6 R5 K12; var7 = var5; var6 = var5[0x73901ACF]
      41 [-]: CALL R6 2 2  ; var6 = var6(var7)
      42 [-]: JUMPIF R6 L7 ; goto L7 if var6
      43 [-]: NAMECALL R6 R5 K13; var7 = var5; var6 = var5[0x2047CFE7]
      44 [-]: CALL R6 2 2  ; var6 = var6(var7)
      45 [-]: JUMPIF R6 L7 ; goto L7 if var6
      46 [-]: GETUPVAL R6 0; var6 = upvalues[0]
      47 [-]: NAMECALL R7 R5 K14; var8 = var5; var7 = var5[0x5E651723]
      48 [-]: CALL R7 2 2  ; var7 = var7(var8)
      49 [-]: NAMECALL R8 R5 K15; var9 = var5; var8 = var5[0xD1586535]
      50 [-]: CALL R8 2 2  ; var8 = var8(var9)
      51 [-]: GETIMPORT R9 17; var9 = ZERO_ROTATION
      52 [-]: CALL R6 4 2  ; var6 = var6(var7, var8, var9)
      53 [-]: GETIMPORT R7 8; var7 = 0xCBD666E1
      54 [-]: LOADN R8 0   ; var8 = 0
      55 [-]: CALL R7 2 1  ; var7(var8)
      56 [-]: FASTCALL1 62 R6 L6; 
      57 [-]: MOVE R8 R6   ; var8 = var6
      58 [-]: GETIMPORT R7 5; var7 = 0x7B998233
      59 [-]: CALL R7 2 2  ; var7 = var7(var8)
L 6:  60 [-]: JUMPIF R7 L7 ; goto L7 if var7
      61 [-]: MOVE R9 R5   ; var9 = var5
      62 [-]: LOADB R10 1  ; var10 = true
      63 [-]: LOADB R11 0  ; var11 = false
      64 [-]: LOADB R12 0  ; var12 = false
      65 [-]: LOADB R13 1  ; var13 = true
      66 [-]: NAMECALL R7 R6 K18; var8 = var6; var7 = var6[0xDFBB9951]
      67 [-]: CALL R7 7 1  ; var7(var8, var9, var10, var11, var12, var13)
L 7:  68 [-]: FORNLOOP R2 L0; nforloop end - iterate + goto L0
L 8:  69 [-]: RETURN R0 0  ; 


; Name:            
; Defined at line: 1134
; #Upvalues:       17
; #Parameters:     1
; Is_vararg:       0
; Max Stack Size:  23

       0 [-]: FASTCALL1 62 R0 L0; 
       1 [-]: MOVE R2 R0   ; var2 = var0
       2 [-]: GETIMPORT R1 1; var1 = 0x7B998233
       3 [-]: CALL R1 2 2  ; var1 = var1(var2)
L 0:   4 [-]: JUMPIFNOT R1 L1; goto L1 if not var1
       5 [-]: RETURN R0 0  ; 
L 1:   6 [-]: GETIMPORT R1 3; var1 = _T
       7 [-]: SETTABLEKS R0 R1 K4; var0["DuviriDragonAvatar"] = var1
       8 [-]: GETIMPORT R1 6; var1 = 0xBE190284
       9 [-]: GETUPVAL R4 0; var4 = upvalues[0]
      10 [-]: GETTABLEKS R3 R4 K7; var3 = var4["NV_CURRENT_MOOD"]
      11 [-]: LOADN R4 0   ; var4 = 0
      12 [-]: NAMECALL R1 R1 K8; var2 = var1; var1 = var1[0x0EB34C69]
      13 [-]: CALL R1 4 2  ; var1 = var1(var2, var3, var4)
      14 [-]: GETIMPORT R3 10; var3 = 0x8982A352
      15 [-]: LOADN R5 1   ; var5 = 1
      16 [-]: FASTCALL2 18 R5 R1 L2; 
      17 [-]: MOVE R6 R1   ; var6 = var1
      18 [-]: GETIMPORT R4 13; var4 = 0x5BCED4C4[0xB62ECFE0]
      19 [-]: CALL R4 3 2  ; var4 = var4(var5, var6)
L 2:  20 [-]: GETTABLE R2 R3 R4; var2 = var3[var4]
      21 [-]: GETIMPORT R3 6; var3 = 0xBE190284
      22 [-]: GETUPVAL R5 1; var5 = upvalues[1]
      23 [-]: NAMECALL R3 R3 K8; var4 = var3; var3 = var3[0x0EB34C69]
      24 [-]: CALL R3 3 2  ; var3 = var3(var4, var5)
      25 [-]: JUMPXEQKNIL R3 L3; 
      26 [-]: JUMPXEQKN R3 K14 L3; 
      27 [-]: GETIMPORT R5 16; var5 = 0xC72EF5D9
      28 [-]: LENGTH R4 R5 ; var4 = #var5
      29 [-]: JUMPIFNOTLT R4 R3 L4; goto L4 if var4 >= var66375
L 3:  30 [-]: LOADN R3 1   ; var3 = 1
      31 [-]: GETIMPORT R4 6; var4 = 0xBE190284
      32 [-]: GETUPVAL R6 1; var6 = upvalues[1]
      33 [-]: MOVE R7 R3   ; var7 = var3
      34 [-]: NAMECALL R4 R4 K17; var5 = var4; var4 = var4[0x751F061D]
      35 [-]: CALL R4 4 1  ; var4(var5, var6, var7)
L 4:  36 [-]: NAMECALL R4 R0 K18; var5 = var0; var4 = var0[0x1AC1655C]
      37 [-]: CALL R4 2 2  ; var4 = var4(var5)
      38 [-]: GETIMPORT R5 20; var5 = 0x89326C93
      39 [-]: GETIMPORT R7 22; var7 = 0x2B9F4010
      40 [-]: NAMECALL R8 R0 K23; var9 = var0; var8 = var0[0xD1586535]
      41 [-]: CALL R8 2 2  ; var8 = var8(var9)
      42 [-]: GETIMPORT R9 25; var9 = ZERO_ROTATION
      43 [-]: NAMECALL R5 R5 K26; var6 = var5; var5 = var5[0x05909209]
      44 [-]: CALL R5 5 2  ; var5 = var5(var6, var7, var8, var9)
      45 [-]: GETIMPORT R6 6; var6 = 0xBE190284
      46 [-]: GETUPVAL R8 2; var8 = upvalues[2]
      47 [-]: NAMECALL R6 R6 K8; var7 = var6; var6 = var6[0x0EB34C69]
      48 [-]: CALL R6 3 2  ; var6 = var6(var7, var8)
      49 [-]: GETIMPORT R7 6; var7 = 0xBE190284
      50 [-]: GETUPVAL R9 3; var9 = upvalues[3]
      51 [-]: NAMECALL R7 R7 K8; var8 = var7; var7 = var7[0x0EB34C69]
      52 [-]: CALL R7 3 2  ; var7 = var7(var8, var9)
      53 [-]: JUMPXEQKN R6 K27 L8; 
      54 [-]: JUMPXEQKN R7 K27 L5 NOT; 
      55 [-]: GETIMPORT R11 16; var11 = 0xC72EF5D9
      56 [-]: GETTABLE R10 R11 R3; var10 = var11[var3]
      57 [-]: NAMECALL R8 R4 K28; var9 = var4; var8 = var4[0x4EC6D8A8]
      58 [-]: CALL R8 3 1  ; var8(var9, var10)
      59 [-]: GETUPVAL R9 4; var9 = upvalues[4]
      60 [-]: GETTABLEKS R8 R9 K29; var8 = var9[0x9742B85B]
      61 [-]: MOVE R9 R2   ; var9 = var2
      62 [-]: GETIMPORT R10 31; var10 = 0x0469F296
      63 [-]: LOADK R11 K32; var11 = "Orowyrm_ArenaPhase"
      64 [-]: CALL R10 2 0 ; var10, ... = var10(var11)
      65 [-]: CALL R8 0 1  ; var8(var9, ...)
      66 [-]: JUMP L7      ; goto L7
L 5:  67 [-]: JUMPXEQKN R7 K33 L6 NOT; 
      68 [-]: GETUPVAL R8 5; var8 = upvalues[5]
      69 [-]: CALL R8 1 1  ; var8()
      70 [-]: GETUPVAL R8 6; var8 = upvalues[6]
      71 [-]: MOVE R9 R0   ; var9 = var0
      72 [-]: MOVE R10 R3  ; var10 = var3
      73 [-]: CALL R8 3 1  ; var8(var9, var10)
      74 [-]: GETIMPORT R10 35; var10 = 0xC9312B82
      75 [-]: LOADB R11 0  ; var11 = false
      76 [-]: LOADN R12 2  ; var12 = 2
      77 [-]: LOADN R13 1  ; var13 = 1
      78 [-]: LOADB R14 1  ; var14 = true
      79 [-]: NAMECALL R8 R0 K36; var9 = var0; var8 = var0[0x5D985C7E]
      80 [-]: CALL R8 7 1  ; var8(var9, var10, var11, var12, var13, var14)
      81 [-]: GETIMPORT R11 16; var11 = 0xC72EF5D9
      82 [-]: GETTABLE R10 R11 R3; var10 = var11[var3]
      83 [-]: NAMECALL R8 R4 K28; var9 = var4; var8 = var4[0x4EC6D8A8]
      84 [-]: CALL R8 3 1  ; var8(var9, var10)
      85 [-]: GETUPVAL R8 7; var8 = upvalues[7]
      86 [-]: MOVE R9 R0   ; var9 = var0
      87 [-]: MOVE R10 R2  ; var10 = var2
      88 [-]: CALL R8 3 1  ; var8(var9, var10)
      89 [-]: JUMP L7      ; goto L7
L 6:  90 [-]: JUMPXEQKN R7 K37 L7 NOT; 
      91 [-]: GETUPVAL R8 5; var8 = upvalues[5]
      92 [-]: CALL R8 1 1  ; var8()
      93 [-]: GETUPVAL R8 6; var8 = upvalues[6]
      94 [-]: MOVE R9 R0   ; var9 = var0
      95 [-]: MOVE R10 R3  ; var10 = var3
      96 [-]: CALL R8 3 1  ; var8(var9, var10)
      97 [-]: GETUPVAL R8 8; var8 = upvalues[8]
      98 [-]: MOVE R9 R0   ; var9 = var0
      99 [-]: MOVE R10 R2  ; var10 = var2
     100 [-]: CALL R8 3 1  ; var8(var9, var10)
     101 [-]: GETIMPORT R11 16; var11 = 0xC72EF5D9
     102 [-]: GETTABLE R10 R11 R3; var10 = var11[var3]
     103 [-]: NAMECALL R8 R4 K28; var9 = var4; var8 = var4[0x4EC6D8A8]
     104 [-]: CALL R8 3 1  ; var8(var9, var10)
L 7: 105 [-]: GETIMPORT R8 39; var8 = 0xCBD666E1
     106 [-]: LOADN R9 0   ; var9 = 0
     107 [-]: CALL R8 2 1  ; var8(var9)
     108 [-]: GETIMPORT R8 6; var8 = 0xBE190284
     109 [-]: GETUPVAL R10 3; var10 = upvalues[3]
     110 [-]: LOADN R11 1  ; var11 = 1
     111 [-]: NAMECALL R8 R8 K17; var9 = var8; var8 = var8[0x751F061D]
     112 [-]: CALL R8 4 1  ; var8(var9, var10, var11)
     113 [-]: NAMECALL R8 R0 K40; var9 = var0; var8 = var0[0x9D71D14A]
     114 [-]: CALL R8 2 1  ; var8(var9)
     115 [-]: JUMP L12     ; goto L12
L 8: 116 [-]: GETIMPORT R11 16; var11 = 0xC72EF5D9
     117 [-]: GETTABLE R10 R11 R3; var10 = var11[var3]
     118 [-]: NAMECALL R8 R4 K28; var9 = var4; var8 = var4[0x4EC6D8A8]
     119 [-]: CALL R8 3 1  ; var8(var9, var10)
     120 [-]: GETIMPORT R8 39; var8 = 0xCBD666E1
     121 [-]: LOADN R9 0   ; var9 = 0
     122 [-]: CALL R8 2 1  ; var8(var9)
     123 [-]: NAMECALL R8 R0 K41; var9 = var0; var8 = var0[0x73901ACF]
     124 [-]: CALL R8 2 2  ; var8 = var8(var9)
     125 [-]: JUMPIF R8 L9 ; goto L9 if var8
     126 [-]: NAMECALL R8 R0 K40; var9 = var0; var8 = var0[0x9D71D14A]
     127 [-]: CALL R8 2 1  ; var8(var9)
L 9: 128 [-]: JUMPXEQKN R7 K37 L12 NOT; 
L10: 129 [-]: GETIMPORT R8 20; var8 = 0x89326C93
     130 [-]: NAMECALL R8 R8 K42; var9 = var8; var8 = var8[0x5D971903]
     131 [-]: CALL R8 2 2  ; var8 = var8(var9)
     132 [-]: GETIMPORT R9 44; var9 = 0xE7F2B02F
     133 [-]: NAMECALL R9 R9 K45; var10 = var9; var9 = var9[0xEBE2F513]
     134 [-]: CALL R9 2 2  ; var9 = var9(var10)
     135 [-]: JUMPIFNOTLT R8 R9 L11; goto L11 if var8 >= var591879
     136 [-]: GETUPVAL R8 9; var8 = upvalues[9]
     137 [-]: LOADB R9 1   ; var9 = true
     138 [-]: CALL R8 2 1  ; var8(var9)
     139 [-]: GETIMPORT R8 39; var8 = 0xCBD666E1
     140 [-]: LOADN R9 0   ; var9 = 0
     141 [-]: CALL R8 2 1  ; var8(var9)
     142 [-]: JUMPBACK L10 ; goto L10
L11: 143 [-]: GETUPVAL R8 9; var8 = upvalues[9]
     144 [-]: LOADB R9 0   ; var9 = false
     145 [-]: CALL R8 2 1  ; var8(var9)
L12: 146 [-]: NEWTABLE R8 0 0; var8 = {}
     147 [-]: LOADB R9 0   ; var9 = false
     148 [-]: GETIMPORT R10 47; var10 = 0xE82A68E3
L13: 149 [-]: FASTCALL1 62 R0 L14; 
     150 [-]: MOVE R12 R0  ; var12 = var0
     151 [-]: GETIMPORT R11 1; var11 = 0x7B998233
     152 [-]: CALL R11 2 2 ; var11 = var11(var12)
L14: 153 [-]: JUMPIF R11 L42; goto L42 if var11
     154 [-]: NAMECALL R11 R0 K41; var12 = var0; var11 = var0[0x73901ACF]
     155 [-]: CALL R11 2 2 ; var11 = var11(var12)
     156 [-]: JUMPIFNOT R11 L40; goto L40 if not var11
     157 [-]: NAMECALL R11 R0 K48; var12 = var0; var11 = var0[0x9E8D5622]
     158 [-]: CALL R11 2 1 ; var11(var12)
     159 [-]: LENGTH R13 R8; var13 = #var8
     160 [-]: LOADN R11 1  ; var11 = 1
     161 [-]: LOADN R12 -1 ; var12 = -1
     162 [-]: FORNPREP R11 L18; nforprep start - [escape at L18] -- var11 = iterator
L15: 163 [-]: GETTABLE R15 R8 R13; var15 = var8[var13]
     164 [-]: FASTCALL1 62 R15 L16; 
     165 [-]: GETIMPORT R14 1; var14 = 0x7B998233
     166 [-]: CALL R14 2 2 ; var14 = var14(var15)
L16: 167 [-]: JUMPIF R14 L17; goto L17 if var14
     168 [-]: GETTABLE R14 R8 R13; var14 = var8[var13]
     169 [-]: NAMECALL R14 R14 K49; var15 = var14; var14 = var14[0xA2880940]
     170 [-]: CALL R14 2 1 ; var14(var15)
L17: 171 [-]: FORNLOOP R11 L15; nforloop end - iterate + goto L15
L18: 172 [-]: LOADB R9 0   ; var9 = false
     173 [-]: GETIMPORT R10 47; var10 = 0xE82A68E3
     174 [-]: GETIMPORT R12 51; var12 = 0x644F083A
     175 [-]: LENGTH R11 R12; var11 = #var12
     176 [-]: JUMPIFNOTLE R3 R11 L21; goto L21 if var3 > var3345742
     177 [-]: GETIMPORT R13 51; var13 = 0x644F083A
     178 [-]: GETTABLE R12 R13 R3; var12 = var13[var3]
     179 [-]: FASTCALL1 62 R12 L19; 
     180 [-]: GETIMPORT R11 1; var11 = 0x7B998233
     181 [-]: CALL R11 2 2 ; var11 = var11(var12)
L19: 182 [-]: JUMPIF R11 L21; goto L21 if var11
     183 [-]: GETIMPORT R11 20; var11 = 0x89326C93
     184 [-]: GETIMPORT R14 51; var14 = 0x644F083A
     185 [-]: GETTABLE R13 R14 R3; var13 = var14[var3]
     186 [-]: NAMECALL R11 R11 K52; var12 = var11; var11 = var11[0x46A0EBF5]
     187 [-]: CALL R11 3 2 ; var11 = var11(var12, var13)
     188 [-]: FASTCALL1 62 R11 L20; 
     189 [-]: MOVE R13 R11 ; var13 = var11
     190 [-]: GETIMPORT R12 1; var12 = 0x7B998233
     191 [-]: CALL R12 2 2 ; var12 = var12(var13)
L20: 192 [-]: JUMPIF R12 L21; goto L21 if var12
     193 [-]: LOADK R14 K53; var14 = "TriggerPort"
     194 [-]: NAMECALL R12 R11 K54; var13 = var11; var12 = var11[0x8EB2112D]
     195 [-]: CALL R12 3 1 ; var12(var13, var14)
L21: 196 [-]: GETIMPORT R12 6; var12 = 0xBE190284
     197 [-]: NAMECALL R12 R12 K55; var13 = var12; var12 = var12[0xEF893AEC]
     198 [-]: CALL R12 2 2 ; var12 = var12(var13)
     199 [-]: GETTABLEKS R11 R12 K56; var11 = var12["tier"]
     200 [-]: LOADN R12 0  ; var12 = 0
     201 [-]: JUMPIFNOTLT R12 R11 L22; goto L22 if var12 >= var396110
     202 [-]: GETIMPORT R11 6; var11 = 0xBE190284
     203 [-]: GETUPVAL R13 3; var13 = upvalues[3]
     204 [-]: GETUPVAL R15 10; var15 = upvalues[10]
     205 [-]: GETTABLE R14 R15 R3; var14 = var15[var3]
     206 [-]: NAMECALL R11 R11 K17; var12 = var11; var11 = var11[0x751F061D]
     207 [-]: CALL R11 4 1 ; var11(var12, var13, var14)
     208 [-]: JUMP L23     ; goto L23
L22: 209 [-]: GETIMPORT R11 6; var11 = 0xBE190284
     210 [-]: GETUPVAL R13 3; var13 = upvalues[3]
     211 [-]: GETUPVAL R15 11; var15 = upvalues[11]
     212 [-]: GETTABLE R14 R15 R3; var14 = var15[var3]
     213 [-]: NAMECALL R11 R11 K17; var12 = var11; var11 = var11[0x751F061D]
     214 [-]: CALL R11 4 1 ; var11(var12, var13, var14)
L23: 215 [-]: ADDK R3 R3 K27; var3 = var3 + 1
     216 [-]: GETIMPORT R13 16; var13 = 0xC72EF5D9
     217 [-]: LENGTH R12 R13; var12 = #var13
     218 [-]: ADDK R11 R12 K27; var11 = var12 + 1
     219 [-]: JUMPIFEQ R3 R11 L42; goto L42 if var3 == var3804494
     220 [-]: GETIMPORT R13 58; var13 = 0x68F0F00C
     221 [-]: LOADB R14 0  ; var14 = false
     222 [-]: LOADN R15 2  ; var15 = 2
     223 [-]: LOADN R16 1  ; var16 = 1
     224 [-]: LOADB R17 1  ; var17 = true
     225 [-]: NAMECALL R11 R0 K36; var12 = var0; var11 = var0[0x5D985C7E]
     226 [-]: CALL R11 7 1 ; var11(var12, var13, var14, var15, var16, var17)
     227 [-]: LOADK R13 K59; var13 = "CollapseStatue"
     228 [-]: LOADN R14 5  ; var14 = 5
     229 [-]: NAMECALL R11 R0 K60; var12 = var0; var11 = var0[0x21B4C60E]
     230 [-]: CALL R11 4 1 ; var11(var12, var13, var14)
     231 [-]: GETIMPORT R13 62; var13 = 0x89AF9D7E
     232 [-]: LOADB R14 0  ; var14 = false
     233 [-]: LOADN R15 2  ; var15 = 2
     234 [-]: LOADN R16 2  ; var16 = 2
     235 [-]: LOADB R17 1  ; var17 = true
     236 [-]: NAMECALL R11 R0 K36; var12 = var0; var11 = var0[0x5D985C7E]
     237 [-]: CALL R11 7 1 ; var11(var12, var13, var14, var15, var16, var17)
     238 [-]: NAMECALL R12 R0 K63; var13 = var0; var12 = var0[0x2CF51F14]
     239 [-]: CALL R12 2 2 ; var12 = var12(var13)
     240 [-]: ADDK R11 R12 K27; var11 = var12 + 1
     241 [-]: LOADN R15 1  ; var15 = 1
     242 [-]: GETUPVAL R16 12; var16 = upvalues[12]
     243 [-]: LENGTH R13 R16; var13 = #var16
     244 [-]: LOADN R14 1  ; var14 = 1
     245 [-]: FORNPREP R13 L26; nforprep start - [escape at L26] -- var13 = iterator
L24: 246 [-]: GETUPVAL R17 12; var17 = upvalues[12]
     247 [-]: GETTABLE R16 R17 R15; var16 = var17[var15]
     248 [-]: JUMPIFNOTEQ R16 R11 L25; goto L25 if var16 ~= var68635
     249 [-]: LOADB R12 1  ; var12 = true
     250 [-]: JUMP L27     ; goto L27
L25: 251 [-]: FORNLOOP R13 L24; nforloop end - iterate + goto L24
L26: 252 [-]: LOADB R12 0  ; var12 = false
L27: 253 [-]: JUMPIF R12 L34; goto L34 if var12
     254 [-]: GETUPVAL R13 12; var13 = upvalues[12]
     255 [-]: FASTCALL2 52 R13 R11 L28; 
     256 [-]: MOVE R14 R11 ; var14 = var11
     257 [-]: GETIMPORT R12 66; var12 = 0x33BDD652[0x23D5322F]
     258 [-]: CALL R12 3 1 ; var12(var13, var14)
L28: 259 [-]: GETIMPORT R12 20; var12 = 0x89326C93
     260 [-]: GETIMPORT R15 68; var15 = 0xDC2024EB
     261 [-]: GETTABLE R14 R15 R11; var14 = var15[var11]
     262 [-]: NAMECALL R12 R12 K69; var13 = var12; var12 = var12[0xC7FCADA9]
     263 [-]: CALL R12 3 2 ; var12 = var12(var13, var14)
     264 [-]: FASTCALL1 62 R12 L29; 
     265 [-]: MOVE R14 R12 ; var14 = var12
     266 [-]: GETIMPORT R13 1; var13 = 0x7B998233
     267 [-]: CALL R13 2 2 ; var13 = var13(var14)
L29: 268 [-]: JUMPIF R13 L31; goto L31 if var13
     269 [-]: LENGTH R13 R12; var13 = #var12
     270 [-]: LOADN R14 0  ; var14 = 0
     271 [-]: JUMPIFNOTLT R14 R13 L31; goto L31 if var14 >= var790053
     272 [-]: GETTABLEN R14 R12 1; var14 = var12[1]
     273 [-]: FASTCALL1 62 R14 L30; 
     274 [-]: GETIMPORT R13 1; var13 = 0x7B998233
     275 [-]: CALL R13 2 2 ; var13 = var13(var14)
L30: 276 [-]: JUMPIF R13 L31; goto L31 if var13
     277 [-]: GETTABLEN R13 R12 1; var13 = var12[1]
     278 [-]: LOADB R15 0  ; var15 = false
     279 [-]: NAMECALL R13 R13 K70; var14 = var13; var13 = var13[0x768274D6]
     280 [-]: CALL R13 3 1 ; var13(var14, var15)
L31: 281 [-]: GETIMPORT R14 72; var14 = 0x3AD35A21
     282 [-]: LENGTH R13 R14; var13 = #var14
     283 [-]: JUMPIFNOTLE R11 R13 L34; goto L34 if var11 > var4722510
     284 [-]: GETIMPORT R15 72; var15 = 0x3AD35A21
     285 [-]: GETTABLE R14 R15 R11; var14 = var15[var11]
     286 [-]: FASTCALL1 62 R14 L32; 
     287 [-]: GETIMPORT R13 1; var13 = 0x7B998233
     288 [-]: CALL R13 2 2 ; var13 = var13(var14)
L32: 289 [-]: JUMPIF R13 L34; goto L34 if var13
     290 [-]: GETIMPORT R13 20; var13 = 0x89326C93
     291 [-]: GETIMPORT R16 72; var16 = 0x3AD35A21
     292 [-]: GETTABLE R15 R16 R11; var15 = var16[var11]
     293 [-]: NAMECALL R13 R13 K52; var14 = var13; var13 = var13[0x46A0EBF5]
     294 [-]: CALL R13 3 2 ; var13 = var13(var14, var15)
     295 [-]: FASTCALL1 62 R13 L33; 
     296 [-]: MOVE R15 R13 ; var15 = var13
     297 [-]: GETIMPORT R14 1; var14 = 0x7B998233
     298 [-]: CALL R14 2 2 ; var14 = var14(var15)
L33: 299 [-]: JUMPIF R14 L34; goto L34 if var14
     300 [-]: LOADK R16 K53; var16 = "TriggerPort"
     301 [-]: NAMECALL R14 R13 K54; var15 = var13; var14 = var13[0x8EB2112D]
     302 [-]: CALL R14 3 1 ; var14(var15, var16)
L34: 303 [-]: GETIMPORT R12 6; var12 = 0xBE190284
     304 [-]: GETUPVAL R14 3; var14 = upvalues[3]
     305 [-]: NAMECALL R12 R12 K8; var13 = var12; var12 = var12[0x0EB34C69]
     306 [-]: CALL R12 3 2 ; var12 = var12(var13, var14)
     307 [-]: MOVE R7 R12  ; var7 = var12
     308 [-]: LOADB R12 1  ; var12 = true
     309 [-]: JUMPXEQKN R7 K27 L35 NOT; 
     310 [-]: GETIMPORT R16 16; var16 = 0xC72EF5D9
     311 [-]: GETTABLE R15 R16 R3; var15 = var16[var3]
     312 [-]: NAMECALL R13 R4 K28; var14 = var4; var13 = var4[0x4EC6D8A8]
     313 [-]: CALL R13 3 1 ; var13(var14, var15)
     314 [-]: GETIMPORT R15 35; var15 = 0xC9312B82
     315 [-]: LOADB R16 1  ; var16 = true
     316 [-]: LOADN R17 2  ; var17 = 2
     317 [-]: LOADN R18 1  ; var18 = 1
     318 [-]: LOADB R19 1  ; var19 = true
     319 [-]: NAMECALL R13 R0 K36; var14 = var0; var13 = var0[0x5D985C7E]
     320 [-]: CALL R13 7 1 ; var13(var14, var15, var16, var17, var18, var19)
     321 [-]: GETUPVAL R14 4; var14 = upvalues[4]
     322 [-]: GETTABLEKS R13 R14 K29; var13 = var14[0x9742B85B]
     323 [-]: MOVE R14 R2  ; var14 = var2
     324 [-]: GETIMPORT R15 31; var15 = 0x0469F296
     325 [-]: LOADK R16 K73; var16 = "OrowyrmCharacter_ThirdHealth"
     326 [-]: CALL R15 2 0 ; var15, ... = var15(var16)
     327 [-]: CALL R13 0 1 ; var13(var14, ...)
     328 [-]: JUMP L38     ; goto L38
L35: 329 [-]: JUMPXEQKN R7 K33 L36 NOT; 
     330 [-]: GETIMPORT R15 35; var15 = 0xC9312B82
     331 [-]: LOADB R16 1  ; var16 = true
     332 [-]: LOADN R17 2  ; var17 = 2
     333 [-]: LOADN R18 1  ; var18 = 1
     334 [-]: LOADB R19 1  ; var19 = true
     335 [-]: NAMECALL R13 R0 K36; var14 = var0; var13 = var0[0x5D985C7E]
     336 [-]: CALL R13 7 1 ; var13(var14, var15, var16, var17, var18, var19)
     337 [-]: GETIMPORT R16 16; var16 = 0xC72EF5D9
     338 [-]: GETTABLE R15 R16 R3; var15 = var16[var3]
     339 [-]: NAMECALL R13 R4 K28; var14 = var4; var13 = var4[0x4EC6D8A8]
     340 [-]: CALL R13 3 1 ; var13(var14, var15)
     341 [-]: GETIMPORT R13 6; var13 = 0xBE190284
     342 [-]: GETUPVAL R15 3; var15 = upvalues[3]
     343 [-]: LOADN R16 1  ; var16 = 1
     344 [-]: NAMECALL R13 R13 K17; var14 = var13; var13 = var13[0x751F061D]
     345 [-]: CALL R13 4 1 ; var13(var14, var15, var16)
     346 [-]: GETUPVAL R14 4; var14 = upvalues[4]
     347 [-]: GETTABLEKS R13 R14 K29; var13 = var14[0x9742B85B]
     348 [-]: MOVE R14 R2  ; var14 = var2
     349 [-]: GETIMPORT R15 31; var15 = 0x0469F296
     350 [-]: LOADK R16 K74; var16 = "OrowyrmCharacter_FirstHealth"
     351 [-]: CALL R15 2 0 ; var15, ... = var15(var16)
     352 [-]: CALL R13 0 1 ; var13(var14, ...)
     353 [-]: GETUPVAL R13 7; var13 = upvalues[7]
     354 [-]: MOVE R14 R0  ; var14 = var0
     355 [-]: MOVE R15 R2  ; var15 = var2
     356 [-]: CALL R13 3 1 ; var13(var14, var15)
     357 [-]: JUMP L38     ; goto L38
L36: 358 [-]: JUMPXEQKN R7 K37 L37 NOT; 
     359 [-]: GETUPVAL R13 13; var13 = upvalues[13]
     360 [-]: MOVE R14 R0  ; var14 = var0
     361 [-]: CALL R13 2 1 ; var13(var14)
     362 [-]: GETUPVAL R13 8; var13 = upvalues[8]
     363 [-]: MOVE R14 R0  ; var14 = var0
     364 [-]: MOVE R15 R2  ; var15 = var2
     365 [-]: CALL R13 3 1 ; var13(var14, var15)
     366 [-]: GETUPVAL R14 4; var14 = upvalues[4]
     367 [-]: GETTABLEKS R13 R14 K29; var13 = var14[0x9742B85B]
     368 [-]: MOVE R14 R2  ; var14 = var2
     369 [-]: GETIMPORT R15 31; var15 = 0x0469F296
     370 [-]: LOADK R16 K75; var16 = "OrowyrmCharacter_SecondHealth"
     371 [-]: CALL R15 2 0 ; var15, ... = var15(var16)
     372 [-]: CALL R13 0 1 ; var13(var14, ...)
     373 [-]: GETIMPORT R16 16; var16 = 0xC72EF5D9
     374 [-]: GETTABLE R15 R16 R3; var15 = var16[var3]
     375 [-]: NAMECALL R13 R4 K28; var14 = var4; var13 = var4[0x4EC6D8A8]
     376 [-]: CALL R13 3 1 ; var13(var14, var15)
     377 [-]: LOADB R12 0  ; var12 = false
     378 [-]: JUMP L38     ; goto L38
L37: 379 [-]: JUMPXEQKN R7 K76 L38 NOT; 
     380 [-]: GETUPVAL R14 4; var14 = upvalues[4]
     381 [-]: GETTABLEKS R13 R14 K29; var13 = var14[0x9742B85B]
     382 [-]: MOVE R14 R2  ; var14 = var2
     383 [-]: GETIMPORT R15 31; var15 = 0x0469F296
     384 [-]: LOADK R16 K75; var16 = "OrowyrmCharacter_SecondHealth"
     385 [-]: CALL R15 2 0 ; var15, ... = var15(var16)
     386 [-]: CALL R13 0 1 ; var13(var14, ...)
     387 [-]: GETIMPORT R15 35; var15 = 0xC9312B82
     388 [-]: LOADB R16 1  ; var16 = true
     389 [-]: LOADN R17 2  ; var17 = 2
     390 [-]: LOADN R18 1  ; var18 = 1
     391 [-]: LOADB R19 1  ; var19 = true
     392 [-]: NAMECALL R13 R0 K36; var14 = var0; var13 = var0[0x5D985C7E]
     393 [-]: CALL R13 7 1 ; var13(var14, var15, var16, var17, var18, var19)
     394 [-]: GETUPVAL R13 14; var13 = upvalues[14]
     395 [-]: MOVE R14 R0  ; var14 = var0
     396 [-]: LOADN R15 15 ; var15 = 15
     397 [-]: MOVE R16 R2  ; var16 = var2
     398 [-]: CALL R13 4 1 ; var13(var14, var15, var16)
     399 [-]: GETIMPORT R16 16; var16 = 0xC72EF5D9
     400 [-]: GETTABLE R15 R16 R3; var15 = var16[var3]
     401 [-]: NAMECALL R13 R4 K28; var14 = var4; var13 = var4[0x4EC6D8A8]
     402 [-]: CALL R13 3 1 ; var13(var14, var15)
L38: 403 [-]: GETIMPORT R13 39; var13 = 0xCBD666E1
     404 [-]: LOADN R14 0  ; var14 = 0
     405 [-]: CALL R13 2 1 ; var13(var14)
     406 [-]: GETIMPORT R13 6; var13 = 0xBE190284
     407 [-]: GETUPVAL R15 1; var15 = upvalues[1]
     408 [-]: MOVE R16 R3  ; var16 = var3
     409 [-]: NAMECALL R13 R13 K17; var14 = var13; var13 = var13[0x751F061D]
     410 [-]: CALL R13 4 1 ; var13(var14, var15, var16)
     411 [-]: GETIMPORT R13 6; var13 = 0xBE190284
     412 [-]: GETUPVAL R15 3; var15 = upvalues[3]
     413 [-]: LOADN R16 1  ; var16 = 1
     414 [-]: NAMECALL R13 R13 K17; var14 = var13; var13 = var13[0x751F061D]
     415 [-]: CALL R13 4 2 ; var13 = var13(var14, var15, var16)
     416 [-]: MOVE R7 R13  ; var7 = var13
     417 [-]: JUMPIFNOT R12 L39; goto L39 if not var12
     418 [-]: GETIMPORT R15 78; var15 = 0x45DD84BD
     419 [-]: GETIMPORT R18 80; var18 = 0xF5462A7F
     420 [-]: LOADB R19 0  ; var19 = false
     421 [-]: LOADN R20 2  ; var20 = 2
     422 [-]: LOADN R21 1  ; var21 = 1
     423 [-]: LOADB R22 1  ; var22 = true
     424 [-]: NAMECALL R16 R0 K81; var17 = var0; var16 = var0[0x7027C544]
     425 [-]: CALL R16 7 0 ; var16, ... = var16(var17, var18, var19, var20, var21, var22)
     426 [-]: NAMECALL R13 R0 K60; var14 = var0; var13 = var0[0x21B4C60E]
     427 [-]: CALL R13 0 1 ; var13(var14, ...)
L39: 428 [-]: NAMECALL R13 R0 K40; var14 = var0; var13 = var0[0x9D71D14A]
     429 [-]: CALL R13 2 1 ; var13(var14)
L40: 430 [-]: JUMPIF R9 L41; goto L41 if var9
     431 [-]: LOADN R11 0  ; var11 = 0
     432 [-]: JUMPIFNOTLE R10 R11 L41; goto L41 if var10 > var985863
     433 [-]: GETUPVAL R11 15; var11 = upvalues[15]
     434 [-]: MOVE R12 R2  ; var12 = var2
     435 [-]: CALL R11 2 2 ; var11 = var11(var12)
     436 [-]: MOVE R8 R11  ; var8 = var11
     437 [-]: LOADB R9 1   ; var9 = true
L41: 438 [-]: GETIMPORT R11 83; var11 = 0x67652851
     439 [-]: CALL R11 1 2 ; var11 = var11()
     440 [-]: SUB R10 R10 R11; var10 = var10 - var11
     441 [-]: GETIMPORT R11 39; var11 = 0xCBD666E1
     442 [-]: LOADN R12 0  ; var12 = 0
     443 [-]: CALL R11 2 1 ; var11(var12)
     444 [-]: JUMPBACK L13 ; goto L13
L42: 445 [-]: GETIMPORT R11 6; var11 = 0xBE190284
     446 [-]: GETUPVAL R13 1; var13 = upvalues[1]
     447 [-]: MOVE R14 R3  ; var14 = var3
     448 [-]: NAMECALL R11 R11 K17; var12 = var11; var11 = var11[0x751F061D]
     449 [-]: CALL R11 4 1 ; var11(var12, var13, var14)
     450 [-]: FASTCALL1 62 R5 L43; 
     451 [-]: MOVE R12 R5  ; var12 = var5
     452 [-]: GETIMPORT R11 1; var11 = 0x7B998233
     453 [-]: CALL R11 2 2 ; var11 = var11(var12)
L43: 454 [-]: JUMPIF R11 L44; goto L44 if var11
     455 [-]: NAMECALL R11 R5 K49; var12 = var5; var11 = var5[0xA2880940]
     456 [-]: CALL R11 2 1 ; var11(var12)
L44: 457 [-]: GETUPVAL R11 16; var11 = upvalues[16]
     458 [-]: CALL R11 1 1 ; var11()
     459 [-]: RETURN R0 0  ; 


; Name:            
; Defined at line: 1336
; #Upvalues:       0
; #Parameters:     0
; Is_vararg:       0
; Max Stack Size:  0

       0 [-]: RETURN R0 0  ; 


; Name:            
; Defined at line: 1370
; #Upvalues:       0
; #Parameters:     1
; Is_vararg:       0
; Max Stack Size:  12

       0 [-]: GETIMPORT R1 1; var1 = 0x89326C93
       1 [-]: GETIMPORT R3 3; var3 = 0x0469F296
       2 [-]: LOADK R4 K4  ; var4 = "ProcSunLight"
       3 [-]: CALL R3 2 0  ; var3, ... = var3(var4)
       4 [-]: NAMECALL R1 R1 K5; var2 = var1; var1 = var1[0xC7FCADA9]
       5 [-]: CALL R1 0 2  ; var1 = var1(var2, ...)
       6 [-]: LENGTH R2 R1 ; var2 = #var1
       7 [-]: LOADN R3 0   ; var3 = 0
       8 [-]: JUMPIFNOTLT R3 R2 L8; goto L8 if var3 >= var526
       9 [-]: LOADNIL R2   ; var2 = nil
      10 [-]: LOADNIL R3   ; var3 = nil
      11 [-]: NAMECALL R4 R0 K6; var5 = var0; var4 = var0[0xE79E7EF4]
      12 [-]: CALL R4 2 2  ; var4 = var4(var5)
      13 [-]: NAMECALL R4 R4 K7; var5 = var4; var4 = var4[0xB06572DA]
      14 [-]: CALL R4 2 2  ; var4 = var4(var5)
      15 [-]: LOADN R7 1   ; var7 = 1
      16 [-]: LENGTH R5 R1 ; var5 = #var1
      17 [-]: LOADN R6 1   ; var6 = 1
      18 [-]: FORNPREP R5 L5; nforprep start - [escape at L5] -- var5 = iterator
L 0:  19 [-]: GETTABLE R8 R1 R7; var8 = var1[var7]
      20 [-]: NAMECALL R8 R8 K6; var9 = var8; var8 = var8[0xE79E7EF4]
      21 [-]: CALL R8 2 2  ; var8 = var8(var9)
      22 [-]: FASTCALL1 62 R8 L1; 
      23 [-]: MOVE R10 R8  ; var10 = var8
      24 [-]: GETIMPORT R9 9; var9 = 0x7B998233
      25 [-]: CALL R9 2 2  ; var9 = var9(var10)
L 1:  26 [-]: JUMPIF R9 L4 ; goto L4 if var9
      27 [-]: NAMECALL R9 R8 K7; var10 = var8; var9 = var8[0xB06572DA]
      28 [-]: CALL R9 2 2  ; var9 = var9(var10)
      29 [-]: JUMPIFNOTEQ R9 R4 L2; goto L2 if var9 ~= var117506615
      30 [-]: GETTABLE R2 R1 R7; var2 = var1[var7]
      31 [-]: JUMP L5      ; goto L5
L 2:  32 [-]: FASTCALL1 62 R3 L3; 
      33 [-]: MOVE R11 R3  ; var11 = var3
      34 [-]: GETIMPORT R10 9; var10 = 0x7B998233
      35 [-]: CALL R10 2 2 ; var10 = var10(var11)
L 3:  36 [-]: JUMPIFNOT R10 L4; goto L4 if not var10
      37 [-]: GETTABLE R3 R1 R7; var3 = var1[var7]
L 4:  38 [-]: FORNLOOP R5 L0; nforloop end - iterate + goto L0
L 5:  39 [-]: FASTCALL1 62 R3 L6; 
      40 [-]: MOVE R6 R3   ; var6 = var3
      41 [-]: GETIMPORT R5 9; var5 = 0x7B998233
      42 [-]: CALL R5 2 2  ; var5 = var5(var6)
L 6:  43 [-]: JUMPIF R5 L8 ; goto L8 if var5
      44 [-]: FASTCALL1 62 R2 L7; 
      45 [-]: MOVE R6 R2   ; var6 = var2
      46 [-]: GETIMPORT R5 9; var5 = 0x7B998233
      47 [-]: CALL R5 2 2  ; var5 = var5(var6)
L 7:  48 [-]: JUMPIF R5 L8 ; goto L8 if var5
      49 [-]: NAMECALL R7 R3 K10; var8 = var3; var7 = var3[0x5D10207D]
      50 [-]: CALL R7 2 0  ; var7, ... = var7(var8)
      51 [-]: NAMECALL R5 R2 K11; var6 = var2; var5 = var2[0xA3927FE9]
      52 [-]: CALL R5 0 1  ; var5(var6, ...)
      53 [-]: NAMECALL R7 R3 K12; var8 = var3; var7 = var3[0x128EAD8D]
      54 [-]: CALL R7 2 0  ; var7, ... = var7(var8)
      55 [-]: NAMECALL R5 R2 K13; var6 = var2; var5 = var2[0x96F77E11]
      56 [-]: CALL R5 0 1  ; var5(var6, ...)
      57 [-]: NAMECALL R7 R3 K14; var8 = var3; var7 = var3[0x4EC9BCE1]
      58 [-]: CALL R7 2 0  ; var7, ... = var7(var8)
      59 [-]: NAMECALL R5 R2 K15; var6 = var2; var5 = var2[0xE29E950D]
      60 [-]: CALL R5 0 1  ; var5(var6, ...)
L 8:  61 [-]: RETURN R0 0  ; 


; Name:            
; Defined at line: 1401
; #Upvalues:       1
; #Parameters:     0
; Is_vararg:       0
; Max Stack Size:  9

       0 [-]: GETIMPORT R0 1; var0 = 0x89326C93
       1 [-]: NAMECALL R0 R0 K2; var1 = var0; var0 = var0[0xE3A0BBCA]
       2 [-]: CALL R0 2 2  ; var0 = var0(var1)
       3 [-]: LOADNIL R1   ; var1 = nil
L 0:   4 [-]: FASTCALL1 62 R0 L1; 
       5 [-]: MOVE R3 R0   ; var3 = var0
       6 [-]: GETIMPORT R2 4; var2 = 0x7B998233
       7 [-]: CALL R2 2 2  ; var2 = var2(var3)
L 1:   8 [-]: JUMPIF R2 L2 ; goto L2 if var2
       9 [-]: JUMPIFEQ R0 R1 L5; goto L5 if var0 == var393806
L 2:  10 [-]: GETIMPORT R2 6; var2 = 0xCBD666E1
      11 [-]: LOADN R3 0   ; var3 = 0
      12 [-]: CALL R2 2 1  ; var2(var3)
      13 [-]: GETIMPORT R2 1; var2 = 0x89326C93
      14 [-]: NAMECALL R2 R2 K2; var3 = var2; var2 = var2[0xE3A0BBCA]
      15 [-]: CALL R2 2 2  ; var2 = var2(var3)
      16 [-]: MOVE R0 R2   ; var0 = var2
      17 [-]: FASTCALL1 62 R0 L3; 
      18 [-]: MOVE R3 R0   ; var3 = var0
      19 [-]: GETIMPORT R2 4; var2 = 0x7B998233
      20 [-]: CALL R2 2 2  ; var2 = var2(var3)
L 3:  21 [-]: JUMPIF R2 L4 ; goto L4 if var2
      22 [-]: NAMECALL R2 R0 K7; var3 = var0; var2 = var0[0x5E651723]
      23 [-]: CALL R2 2 2  ; var2 = var2(var3)
      24 [-]: LOADN R4 0   ; var4 = 0
      25 [-]: NAMECALL R2 R2 K2; var3 = var2; var2 = var2[0xE3A0BBCA]
      26 [-]: CALL R2 3 2  ; var2 = var2(var3, var4)
      27 [-]: MOVE R1 R2   ; var1 = var2
L 4:  28 [-]: JUMPBACK L0  ; goto L0
L 5:  29 [-]: NAMECALL R2 R0 K8; var3 = var0; var2 = var0[0xDE321E6F]
      30 [-]: CALL R2 2 2  ; var2 = var2(var3)
      31 [-]: NAMECALL R2 R2 K9; var3 = var2; var2 = var2[0xF7D48EE0]
      32 [-]: CALL R2 2 2  ; var2 = var2(var3)
      33 [-]: FASTCALL1 62 R2 L6; 
      34 [-]: MOVE R4 R2   ; var4 = var2
      35 [-]: GETIMPORT R3 4; var3 = 0x7B998233
      36 [-]: CALL R3 2 2  ; var3 = var3(var4)
L 6:  37 [-]: JUMPIF R3 L7 ; goto L7 if var3
      38 [-]: LOADB R5 1   ; var5 = true
      39 [-]: GETIMPORT R6 11; var6 = 0x0469F296
      40 [-]: LOADK R7 K12 ; var7 = "OPERATOR_TRANSFERENCE"
      41 [-]: CALL R6 2 0  ; var6, ... = var6(var7)
      42 [-]: NAMECALL R3 R2 K13; var4 = var2; var3 = var2[0x83DF59E9]
      43 [-]: CALL R3 0 1  ; var3(var4, ...)
L 7:  44 [-]: GETIMPORT R3 6; var3 = 0xCBD666E1
      45 [-]: LOADN R4 0   ; var4 = 0
      46 [-]: CALL R3 2 1  ; var3(var4)
      47 [-]: GETIMPORT R3 1; var3 = 0x89326C93
      48 [-]: GETIMPORT R5 15; var5 = 0xFC65B1D8
      49 [-]: NAMECALL R3 R3 K16; var4 = var3; var3 = var3[0xFB669000]
      50 [-]: CALL R3 3 2  ; var3 = var3(var4, var5)
L 8:  51 [-]: FASTCALL1 62 R3 L9; 
      52 [-]: MOVE R5 R3   ; var5 = var3
      53 [-]: GETIMPORT R4 4; var4 = 0x7B998233
      54 [-]: CALL R4 2 2  ; var4 = var4(var5)
L 9:  55 [-]: JUMPIF R4 L11; goto L11 if var4
      56 [-]: LENGTH R4 R3 ; var4 = #var3
      57 [-]: JUMPXEQKN R4 K17 L11; 
      58 [-]: GETIMPORT R5 20; var5 = _T["SetupBossAvatar"]
      59 [-]: FASTCALL1 62 R5 L10; 
      60 [-]: GETIMPORT R4 4; var4 = 0x7B998233
      61 [-]: CALL R4 2 2  ; var4 = var4(var5)
L10:  62 [-]: JUMPIFNOT R4 L12; goto L12 if not var4
L11:  63 [-]: GETIMPORT R4 1; var4 = 0x89326C93
      64 [-]: GETIMPORT R6 15; var6 = 0xFC65B1D8
      65 [-]: NAMECALL R4 R4 K16; var5 = var4; var4 = var4[0xFB669000]
      66 [-]: CALL R4 3 2  ; var4 = var4(var5, var6)
      67 [-]: MOVE R3 R4   ; var3 = var4
      68 [-]: GETIMPORT R4 6; var4 = 0xCBD666E1
      69 [-]: LOADN R5 0   ; var5 = 0
      70 [-]: CALL R4 2 1  ; var4(var5)
      71 [-]: JUMPBACK L8  ; goto L8
L12:  72 [-]: FASTCALL1 62 R3 L13; 
      73 [-]: MOVE R5 R3   ; var5 = var3
      74 [-]: GETIMPORT R4 4; var4 = 0x7B998233
      75 [-]: CALL R4 2 2  ; var4 = var4(var5)
L13:  76 [-]: JUMPIF R4 L16; goto L16 if var4
      77 [-]: LENGTH R4 R3 ; var4 = #var3
      78 [-]: LOADN R5 0   ; var5 = 0
      79 [-]: JUMPIFNOTLT R5 R4 L16; goto L16 if var5 >= var197925
      80 [-]: GETTABLEN R5 R3 1; var5 = var3[1]
      81 [-]: FASTCALL1 62 R5 L14; 
      82 [-]: GETIMPORT R4 4; var4 = 0x7B998233
      83 [-]: CALL R4 2 2  ; var4 = var4(var5)
L14:  84 [-]: JUMPIF R4 L16; goto L16 if var4
      85 [-]: GETIMPORT R5 20; var5 = _T["SetupBossAvatar"]
      86 [-]: FASTCALL1 62 R5 L15; 
      87 [-]: GETIMPORT R4 4; var4 = 0x7B998233
      88 [-]: CALL R4 2 2  ; var4 = var4(var5)
L15:  89 [-]: JUMPIF R4 L16; goto L16 if var4
      90 [-]: GETUPVAL R4 0; var4 = upvalues[0]
      91 [-]: GETTABLEN R5 R3 1; var5 = var3[1]
      92 [-]: CALL R4 2 1  ; var4(var5)
      93 [-]: GETIMPORT R4 20; var4 = _T["SetupBossAvatar"]
      94 [-]: GETTABLEN R5 R3 1; var5 = var3[1]
      95 [-]: GETIMPORT R7 22; var7 = 0xC72EF5D9
      96 [-]: LENGTH R6 R7 ; var6 = #var7
      97 [-]: LOADNIL R7   ; var7 = nil
      98 [-]: LOADB R8 1   ; var8 = true
      99 [-]: CALL R4 5 1  ; var4(var5, var6, var7, var8)
L16: 100 [-]: RETURN R0 0  ; 


; Name:            
; Defined at line: 1438
; #Upvalues:       16
; #Parameters:     1
; Is_vararg:       0
; Max Stack Size:  23

       0 [-]: GETIMPORT R1 1; var1 = _T
       1 [-]: LOADB R2 1   ; var2 = true
       2 [-]: SETTABLEKS R2 R1 K2; var2["DisableSecondChance"] = var1
       3 [-]: GETIMPORT R1 4; var1 = 0x89326C93
       4 [-]: GETIMPORT R3 6; var3 = 0x0469F296
       5 [-]: LOADK R4 K7  ; var4 = "SpawnDragonScript"
       6 [-]: CALL R3 2 0  ; var3, ... = var3(var4)
       7 [-]: NAMECALL R1 R1 K8; var2 = var1; var1 = var1[0x46A0EBF5]
       8 [-]: CALL R1 0 2  ; var1 = var1(var2, ...)
L 0:   9 [-]: FASTCALL1 62 R1 L1; 
      10 [-]: MOVE R3 R1   ; var3 = var1
      11 [-]: GETIMPORT R2 10; var2 = 0x7B998233
      12 [-]: CALL R2 2 2  ; var2 = var2(var3)
L 1:  13 [-]: JUMPIF R2 L3 ; goto L3 if var2
      14 [-]: NAMECALL R3 R1 K11; var4 = var1; var3 = var1[0xE79E7EF4]
      15 [-]: CALL R3 2 2  ; var3 = var3(var4)
      16 [-]: FASTCALL1 62 R3 L2; 
      17 [-]: GETIMPORT R2 10; var2 = 0x7B998233
      18 [-]: CALL R2 2 2  ; var2 = var2(var3)
L 2:  19 [-]: JUMPIFNOT R2 L4; goto L4 if not var2
L 3:  20 [-]: GETIMPORT R2 13; var2 = 0xCBD666E1
      21 [-]: LOADN R3 0   ; var3 = 0
      22 [-]: CALL R2 2 1  ; var2(var3)
      23 [-]: GETIMPORT R2 4; var2 = 0x89326C93
      24 [-]: GETIMPORT R4 6; var4 = 0x0469F296
      25 [-]: LOADK R5 K7  ; var5 = "SpawnDragonScript"
      26 [-]: CALL R4 2 0  ; var4, ... = var4(var5)
      27 [-]: NAMECALL R2 R2 K8; var3 = var2; var2 = var2[0x46A0EBF5]
      28 [-]: CALL R2 0 2  ; var2 = var2(var3, ...)
      29 [-]: MOVE R1 R2   ; var1 = var2
      30 [-]: JUMPBACK L0  ; goto L0
L 4:  31 [-]: GETUPVAL R2 0; var2 = upvalues[0]
      32 [-]: MOVE R3 R1   ; var3 = var1
      33 [-]: CALL R2 2 1  ; var2(var3)
      34 [-]: LOADB R2 0   ; var2 = false
      35 [-]: GETIMPORT R3 4; var3 = 0x89326C93
      36 [-]: NAMECALL R3 R3 K14; var4 = var3; var3 = var3[0x18D05D30]
      37 [-]: CALL R3 2 2  ; var3 = var3(var4)
      38 [-]: JUMPIF R3 L24; goto L24 if var3
      39 [-]: GETUPVAL R3 1; var3 = upvalues[1]
      40 [-]: CALL R3 1 1  ; var3()
L 5:  41 [-]: GETIMPORT R3 16; var3 = 0x14459A1C
      42 [-]: JUMPIF R3 L11; goto L11 if var3
      43 [-]: GETIMPORT R3 4; var3 = 0x89326C93
      44 [-]: NAMECALL R3 R3 K17; var4 = var3; var3 = var3[0xE3A0BBCA]
      45 [-]: CALL R3 2 2  ; var3 = var3(var4)
      46 [-]: GETIMPORT R4 19; var4 = 0xBE190284
      47 [-]: GETUPVAL R6 2; var6 = upvalues[2]
      48 [-]: NAMECALL R4 R4 K20; var5 = var4; var4 = var4[0x0EB34C69]
      49 [-]: CALL R4 3 2  ; var4 = var4(var5, var6)
      50 [-]: JUMPXEQKN R4 K21 L6 NOT; 
      51 [-]: RETURN R0 0  ; 
L 6:  52 [-]: GETIMPORT R5 23; var5 = _T["DragonRespawnMonitorTime"]
      53 [-]: FASTCALL1 62 R5 L7; 
      54 [-]: GETIMPORT R4 10; var4 = 0x7B998233
      55 [-]: CALL R4 2 2  ; var4 = var4(var5)
L 7:  56 [-]: JUMPIF R4 L8 ; goto L8 if var4
      57 [-]: GETIMPORT R5 23; var5 = _T["DragonRespawnMonitorTime"]
      58 [-]: GETIMPORT R6 25; var6 = 0x55156FF7
      59 [-]: CALL R6 1 2  ; var6 = var6()
      60 [-]: SUB R4 R5 R6 ; var4 = var5 - var6
      61 [-]: LOADN R5 1   ; var5 = 1
      62 [-]: JUMPIFNOTLT R5 R4 L10; goto L10 if var5 >= var263246
L 8:  63 [-]: GETIMPORT R4 4; var4 = 0x89326C93
      64 [-]: GETIMPORT R6 27; var6 = 0xFC65B1D8
      65 [-]: NAMECALL R4 R4 K28; var5 = var4; var4 = var4[0xFB669000]
      66 [-]: CALL R4 3 2  ; var4 = var4(var5, var6)
      67 [-]: LENGTH R5 R4 ; var5 = #var4
      68 [-]: LOADN R6 0   ; var6 = 0
      69 [-]: JUMPIFNOTLT R6 R5 L10; goto L10 if var6 >= var263717
      70 [-]: GETTABLEN R6 R4 1; var6 = var4[1]
      71 [-]: FASTCALL1 62 R6 L9; 
      72 [-]: GETIMPORT R5 10; var5 = 0x7B998233
      73 [-]: CALL R5 2 2  ; var5 = var5(var6)
L 9:  74 [-]: JUMPIF R5 L10; goto L10 if var5
      75 [-]: GETTABLEN R5 R4 1; var5 = var4[1]
      76 [-]: GETIMPORT R7 6; var7 = 0x0469F296
      77 [-]: LOADK R8 K29 ; var8 = "NewRespawnMonitor"
      78 [-]: CALL R7 2 2  ; var7 = var7(var8)
      79 [-]: LOADB R8 0   ; var8 = false
      80 [-]: NAMECALL R5 R5 K30; var6 = var5; var5 = var5[0xD5F7912B]
      81 [-]: CALL R5 4 1  ; var5(var6, var7, var8)
L10:  82 [-]: GETIMPORT R4 13; var4 = 0xCBD666E1
      83 [-]: LOADN R5 0   ; var5 = 0
      84 [-]: CALL R4 2 1  ; var4(var5)
      85 [-]: JUMPBACK L5  ; goto L5
L11:  86 [-]: GETIMPORT R3 4; var3 = 0x89326C93
      87 [-]: NAMECALL R3 R3 K31; var4 = var3; var3 = var3[0x29EF273D]
      88 [-]: CALL R3 2 2  ; var3 = var3(var4)
      89 [-]: NAMECALL R3 R3 K32; var4 = var3; var3 = var3[0x66905CB0]
      90 [-]: CALL R3 2 2  ; var3 = var3(var4)
L12:  91 [-]: NAMECALL R4 R3 K33; var5 = var3; var4 = var3[0xA2D83ED4]
      92 [-]: CALL R4 2 2  ; var4 = var4(var5)
      93 [-]: JUMPIF R4 L13; goto L13 if var4
      94 [-]: GETIMPORT R4 13; var4 = 0xCBD666E1
      95 [-]: LOADN R5 0   ; var5 = 0
      96 [-]: CALL R4 2 1  ; var4(var5)
      97 [-]: JUMPBACK L12 ; goto L12
L13:  98 [-]: GETIMPORT R5 19; var5 = 0xBE190284
      99 [-]: GETUPVAL R7 3; var7 = upvalues[3]
     100 [-]: NAMECALL R5 R5 K20; var6 = var5; var5 = var5[0x0EB34C69]
     101 [-]: CALL R5 3 2  ; var5 = var5(var6, var7)
     102 [-]: JUMPXEQKN R5 K34 L14; 
     103 [-]: LOADB R4 0 +1; var4 = false
L14: 104 [-]: LOADB R4 1   ; var4 = true
L15: 105 [-]: JUMPIF R4 L20; goto L20 if var4
     106 [-]: GETIMPORT R5 19; var5 = 0xBE190284
     107 [-]: GETUPVAL R7 3; var7 = upvalues[3]
     108 [-]: LOADN R8 1   ; var8 = 1
     109 [-]: NAMECALL R5 R5 K35; var6 = var5; var5 = var5[0x751F061D]
     110 [-]: CALL R5 4 1  ; var5(var6, var7, var8)
     111 [-]: GETIMPORT R5 4; var5 = 0x89326C93
     112 [-]: GETIMPORT R7 6; var7 = 0x0469F296
     113 [-]: LOADK R8 K36 ; var8 = "DragonIntroCin"
     114 [-]: CALL R7 2 0  ; var7, ... = var7(var8)
     115 [-]: NAMECALL R5 R5 K8; var6 = var5; var5 = var5[0x46A0EBF5]
     116 [-]: CALL R5 0 2  ; var5 = var5(var6, ...)
     117 [-]: FASTCALL1 62 R5 L16; 
     118 [-]: MOVE R7 R5   ; var7 = var5
     119 [-]: GETIMPORT R6 10; var6 = 0x7B998233
     120 [-]: CALL R6 2 2  ; var6 = var6(var7)
L16: 121 [-]: JUMPIF R6 L17; goto L17 if var6
     122 [-]: NAMECALL R6 R5 K37; var7 = var5; var6 = var5[0x6CF1E476]
     123 [-]: CALL R6 2 1  ; var6(var7)
L17: 124 [-]: GETIMPORT R6 4; var6 = 0x89326C93
     125 [-]: GETIMPORT R8 27; var8 = 0xFC65B1D8
     126 [-]: NAMECALL R9 R1 K38; var10 = var1; var9 = var1[0xD1586535]
     127 [-]: CALL R9 2 2  ; var9 = var9(var10)
     128 [-]: LOADK R10 K39; var10 = 3.4028234663852886e+38
     129 [-]: NAMECALL R6 R6 K40; var7 = var6; var6 = var6[0x4E5939A5]
     130 [-]: CALL R6 5 2  ; var6 = var6(var7, var8, var9, var10)
     131 [-]: FASTCALL1 62 R6 L18; 
     132 [-]: MOVE R8 R6   ; var8 = var6
     133 [-]: GETIMPORT R7 10; var7 = 0x7B998233
     134 [-]: CALL R7 2 2  ; var7 = var7(var8)
L18: 135 [-]: JUMPIF R7 L19; goto L19 if var7
     136 [-]: NAMECALL R7 R6 K41; var8 = var6; var7 = var6[0xA2880940]
     137 [-]: CALL R7 2 1  ; var7(var8)
L19: 138 [-]: GETUPVAL R7 4; var7 = upvalues[4]
     139 [-]: CALL R7 1 1  ; var7()
L20: 140 [-]: GETIMPORT R5 19; var5 = 0xBE190284
     141 [-]: GETUPVAL R7 5; var7 = upvalues[5]
     142 [-]: NAMECALL R5 R5 K20; var6 = var5; var5 = var5[0x0EB34C69]
     143 [-]: CALL R5 3 2  ; var5 = var5(var6, var7)
     144 [-]: GETIMPORT R7 43; var7 = 0xC72EF5D9
     145 [-]: LENGTH R6 R7 ; var6 = #var7
     146 [-]: JUMPIFLT R6 R5 L21; goto L21 if var6 < var852032
     147 [-]: JUMP L23     ; goto L23
L21: 148 [-]: GETIMPORT R6 45; var6 = 0x3D106989
     149 [-]: LOADK R7 K46 ; var7 = "Host migration after dragon death"
     150 [-]: CALL R6 2 1  ; var6(var7)
     151 [-]: GETUPVAL R6 6; var6 = upvalues[6]
     152 [-]: CALL R6 1 1  ; var6()
     153 [-]: GETUPVAL R6 7; var6 = upvalues[7]
     154 [-]: CALL R6 1 1  ; var6()
     155 [-]: GETUPVAL R6 8; var6 = upvalues[8]
     156 [-]: JUMPIFNOT R6 L22; goto L22 if not var6
     157 [-]: GETUPVAL R6 9; var6 = upvalues[9]
     158 [-]: CALL R6 1 1  ; var6()
L22: 159 [-]: RETURN R0 0  ; 
L23: 160 [-]: GETIMPORT R6 19; var6 = 0xBE190284
     161 [-]: GETUPVAL R8 10; var8 = upvalues[10]
     162 [-]: LOADN R9 1   ; var9 = 1
     163 [-]: NAMECALL R6 R6 K35; var7 = var6; var6 = var6[0x751F061D]
     164 [-]: CALL R6 4 1  ; var6(var7, var8, var9)
     165 [-]: LOADB R2 1   ; var2 = true
     166 [-]: GETIMPORT R6 13; var6 = 0xCBD666E1
     167 [-]: LOADN R7 0   ; var7 = 0
     168 [-]: CALL R6 2 1  ; var6(var7)
L24: 169 [-]: GETIMPORT R3 4; var3 = 0x89326C93
     170 [-]: NAMECALL R3 R3 K17; var4 = var3; var3 = var3[0xE3A0BBCA]
     171 [-]: CALL R3 2 2  ; var3 = var3(var4)
L25: 172 [-]: FASTCALL1 62 R3 L26; 
     173 [-]: MOVE R5 R3   ; var5 = var3
     174 [-]: GETIMPORT R4 10; var4 = 0x7B998233
     175 [-]: CALL R4 2 2  ; var4 = var4(var5)
L26: 176 [-]: JUMPIFNOT R4 L27; goto L27 if not var4
     177 [-]: GETIMPORT R4 4; var4 = 0x89326C93
     178 [-]: NAMECALL R4 R4 K17; var5 = var4; var4 = var4[0xE3A0BBCA]
     179 [-]: CALL R4 2 2  ; var4 = var4(var5)
     180 [-]: MOVE R3 R4   ; var3 = var4
     181 [-]: GETIMPORT R4 13; var4 = 0xCBD666E1
     182 [-]: LOADN R5 0   ; var5 = 0
     183 [-]: CALL R4 2 1  ; var4(var5)
     184 [-]: JUMPBACK L25 ; goto L25
L27: 185 [-]: LOADB R4 0   ; var4 = false
L28: 186 [-]: JUMPIF R4 L38; goto L38 if var4
     187 [-]: LOADB R4 1   ; var4 = true
     188 [-]: GETIMPORT R5 4; var5 = 0x89326C93
     189 [-]: NAMECALL R5 R5 K47; var6 = var5; var5 = var5[0x7D108DDB]
     190 [-]: CALL R5 2 2  ; var5 = var5(var6)
     191 [-]: LOADN R8 1   ; var8 = 1
     192 [-]: LENGTH R6 R5 ; var6 = #var5
     193 [-]: LOADN R7 1   ; var7 = 1
     194 [-]: FORNPREP R6 L37; nforprep start - [escape at L37] -- var6 = iterator
L29: 195 [-]: GETTABLE R10 R5 R8; var10 = var5[var8]
     196 [-]: FASTCALL1 62 R10 L30; 
     197 [-]: GETIMPORT R9 10; var9 = 0x7B998233
     198 [-]: CALL R9 2 2  ; var9 = var9(var10)
L30: 199 [-]: JUMPIF R9 L36; goto L36 if var9
     200 [-]: GETTABLE R9 R5 R8; var9 = var5[var8]
     201 [-]: LOADN R11 0  ; var11 = 0
     202 [-]: NAMECALL R9 R9 K17; var10 = var9; var9 = var9[0xE3A0BBCA]
     203 [-]: CALL R9 3 2  ; var9 = var9(var10, var11)
     204 [-]: GETTABLE R10 R5 R8; var10 = var5[var8]
     205 [-]: LOADN R12 8  ; var12 = 8
     206 [-]: NAMECALL R10 R10 K17; var11 = var10; var10 = var10[0xE3A0BBCA]
     207 [-]: CALL R10 3 2 ; var10 = var10(var11, var12)
     208 [-]: GETTABLE R11 R5 R8; var11 = var5[var8]
     209 [-]: NAMECALL R11 R11 K48; var12 = var11; var11 = var11[0xBB610E5B]
     210 [-]: CALL R11 2 2 ; var11 = var11(var12)
     211 [-]: FASTCALL1 62 R9 L31; 
     212 [-]: MOVE R13 R9  ; var13 = var9
     213 [-]: GETIMPORT R12 10; var12 = 0x7B998233
     214 [-]: CALL R12 2 2 ; var12 = var12(var13)
L31: 215 [-]: JUMPIF R12 L35; goto L35 if var12
     216 [-]: FASTCALL1 62 R11 L32; 
     217 [-]: MOVE R13 R11 ; var13 = var11
     218 [-]: GETIMPORT R12 10; var12 = 0x7B998233
     219 [-]: CALL R12 2 2 ; var12 = var12(var13)
L32: 220 [-]: JUMPIF R12 L35; goto L35 if var12
     221 [-]: NAMECALL R12 R9 K49; var13 = var9; var12 = var9[0x73901ACF]
     222 [-]: CALL R12 2 2 ; var12 = var12(var13)
     223 [-]: JUMPIF R12 L36; goto L36 if var12
     224 [-]: NAMECALL R12 R9 K50; var13 = var9; var12 = var9[0x2047CFE7]
     225 [-]: CALL R12 2 2 ; var12 = var12(var13)
     226 [-]: JUMPIF R12 L36; goto L36 if var12
     227 [-]: FASTCALL1 62 R10 L33; 
     228 [-]: MOVE R13 R10 ; var13 = var10
     229 [-]: GETIMPORT R12 10; var12 = 0x7B998233
     230 [-]: CALL R12 2 2 ; var12 = var12(var13)
L33: 231 [-]: JUMPIF R12 L36; goto L36 if var12
     232 [-]: NAMECALL R12 R10 K49; var13 = var10; var12 = var10[0x73901ACF]
     233 [-]: CALL R12 2 2 ; var12 = var12(var13)
     234 [-]: JUMPIF R12 L36; goto L36 if var12
     235 [-]: NAMECALL R12 R10 K50; var13 = var10; var12 = var10[0x2047CFE7]
     236 [-]: CALL R12 2 2 ; var12 = var12(var13)
     237 [-]: JUMPIF R12 L36; goto L36 if var12
     238 [-]: JUMPIFEQ R9 R11 L34; goto L34 if var9 == var1051
     239 [-]: LOADB R4 0   ; var4 = false
L34: 240 [-]: JUMPIFNOTEQ R10 R11 L36; goto L36 if var10 ~= var134548535
     241 [-]: GETTABLE R12 R5 R8; var12 = var5[var8]
     242 [-]: MOVE R14 R9  ; var14 = var9
     243 [-]: LOADB R15 1  ; var15 = true
     244 [-]: NAMECALL R12 R12 K51; var13 = var12; var12 = var12[0x480B3AAE]
     245 [-]: CALL R12 4 1 ; var12(var13, var14, var15)
     246 [-]: JUMP L36     ; goto L36
L35: 247 [-]: LOADB R4 0   ; var4 = false
L36: 248 [-]: FORNLOOP R6 L29; nforloop end - iterate + goto L29
L37: 249 [-]: GETIMPORT R6 13; var6 = 0xCBD666E1
     250 [-]: LOADN R7 0   ; var7 = 0
     251 [-]: CALL R6 2 1  ; var6(var7)
     252 [-]: JUMPBACK L28 ; goto L28
L38: 253 [-]: GETIMPORT R5 4; var5 = 0x89326C93
     254 [-]: NAMECALL R5 R5 K17; var6 = var5; var5 = var5[0xE3A0BBCA]
     255 [-]: CALL R5 2 2  ; var5 = var5(var6)
     256 [-]: MOVE R3 R5   ; var3 = var5
     257 [-]: NAMECALL R5 R3 K52; var6 = var3; var5 = var3[0xDE321E6F]
     258 [-]: CALL R5 2 2  ; var5 = var5(var6)
     259 [-]: NAMECALL R5 R5 K53; var6 = var5; var5 = var5[0xF7D48EE0]
     260 [-]: CALL R5 2 2  ; var5 = var5(var6)
     261 [-]: FASTCALL1 62 R5 L39; 
     262 [-]: MOVE R7 R5   ; var7 = var5
     263 [-]: GETIMPORT R6 10; var6 = 0x7B998233
     264 [-]: CALL R6 2 2  ; var6 = var6(var7)
L39: 265 [-]: JUMPIF R6 L40; goto L40 if var6
     266 [-]: LOADB R8 1   ; var8 = true
     267 [-]: GETIMPORT R9 6; var9 = 0x0469F296
     268 [-]: LOADK R10 K54; var10 = "OPERATOR_TRANSFERENCE"
     269 [-]: CALL R9 2 0  ; var9, ... = var9(var10)
     270 [-]: NAMECALL R6 R5 K55; var7 = var5; var6 = var5[0x83DF59E9]
     271 [-]: CALL R6 0 1  ; var6(var7, ...)
L40: 272 [-]: NAMECALL R6 R1 K38; var7 = var1; var6 = var1[0xD1586535]
     273 [-]: CALL R6 2 2  ; var6 = var6(var7)
     274 [-]: SETUPVAL R6 11; upvalues[6] = var11
     275 [-]: JUMPIF R2 L41; goto L41 if var2
     276 [-]: GETIMPORT R6 19; var6 = 0xBE190284
     277 [-]: GETUPVAL R8 2; var8 = upvalues[2]
     278 [-]: LOADN R9 1   ; var9 = 1
     279 [-]: NAMECALL R6 R6 K35; var7 = var6; var6 = var6[0x751F061D]
     280 [-]: CALL R6 4 1  ; var6(var7, var8, var9)
     281 [-]: GETIMPORT R6 19; var6 = 0xBE190284
     282 [-]: GETUPVAL R8 5; var8 = upvalues[5]
     283 [-]: LOADN R9 1   ; var9 = 1
     284 [-]: NAMECALL R6 R6 K35; var7 = var6; var6 = var6[0x751F061D]
     285 [-]: CALL R6 4 1  ; var6(var7, var8, var9)
     286 [-]: GETIMPORT R6 19; var6 = 0xBE190284
     287 [-]: GETUPVAL R8 10; var8 = upvalues[10]
     288 [-]: LOADN R9 0   ; var9 = 0
     289 [-]: NAMECALL R6 R6 K35; var7 = var6; var6 = var6[0x751F061D]
     290 [-]: CALL R6 4 1  ; var6(var7, var8, var9)
     291 [-]: GETIMPORT R6 19; var6 = 0xBE190284
     292 [-]: GETUPVAL R8 3; var8 = upvalues[3]
     293 [-]: LOADN R9 0   ; var9 = 0
     294 [-]: NAMECALL R6 R6 K35; var7 = var6; var6 = var6[0x751F061D]
     295 [-]: CALL R6 4 1  ; var6(var7, var8, var9)
     296 [-]: GETUPVAL R6 12; var6 = upvalues[12]
     297 [-]: CALL R6 1 1  ; var6()
L41: 298 [-]: GETIMPORT R7 57; var7 = 0xCB072EC0
     299 [-]: FASTCALL1 62 R7 L42; 
     300 [-]: GETIMPORT R6 10; var6 = 0x7B998233
     301 [-]: CALL R6 2 2  ; var6 = var6(var7)
L42: 302 [-]: JUMPIF R6 L45; goto L45 if var6
     303 [-]: GETIMPORT R6 4; var6 = 0x89326C93
     304 [-]: GETIMPORT R8 57; var8 = 0xCB072EC0
     305 [-]: NAMECALL R6 R6 K58; var7 = var6; var6 = var6[0xC7FCADA9]
     306 [-]: CALL R6 3 2  ; var6 = var6(var7, var8)
     307 [-]: FASTCALL1 62 R6 L43; 
     308 [-]: MOVE R8 R6   ; var8 = var6
     309 [-]: GETIMPORT R7 10; var7 = 0x7B998233
     310 [-]: CALL R7 2 2  ; var7 = var7(var8)
L43: 311 [-]: JUMPIF R7 L45; goto L45 if var7
     312 [-]: LENGTH R7 R6 ; var7 = #var6
     313 [-]: LOADN R8 0   ; var8 = 0
     314 [-]: JUMPIFNOTLT R8 R7 L45; goto L45 if var8 >= var395301
     315 [-]: GETTABLEN R8 R6 1; var8 = var6[1]
     316 [-]: FASTCALL1 62 R8 L44; 
     317 [-]: GETIMPORT R7 10; var7 = 0x7B998233
     318 [-]: CALL R7 2 2  ; var7 = var7(var8)
L44: 319 [-]: JUMPIF R7 L45; goto L45 if var7
     320 [-]: GETTABLEN R7 R6 1; var7 = var6[1]
     321 [-]: NAMECALL R7 R7 K38; var8 = var7; var7 = var7[0xD1586535]
     322 [-]: CALL R7 2 2  ; var7 = var7(var8)
     323 [-]: SETUPVAL R7 11; upvalues[7] = var11
L45: 324 [-]: GETIMPORT R6 19; var6 = 0xBE190284
     325 [-]: GETUPVAL R8 2; var8 = upvalues[2]
     326 [-]: NAMECALL R6 R6 K20; var7 = var6; var6 = var6[0x0EB34C69]
     327 [-]: CALL R6 3 2  ; var6 = var6(var7, var8)
     328 [-]: JUMPXEQKN R6 K59 L50 NOT; 
     329 [-]: JUMPIF R2 L50; goto L50 if var2
     330 [-]: GETIMPORT R7 4; var7 = 0x89326C93
     331 [-]: GETIMPORT R9 6; var9 = 0x0469F296
     332 [-]: LOADK R10 K60; var10 = "DragonStandin"
     333 [-]: CALL R9 2 0  ; var9, ... = var9(var10)
     334 [-]: NAMECALL R7 R7 K8; var8 = var7; var7 = var7[0x46A0EBF5]
     335 [-]: CALL R7 0 2  ; var7 = var7(var8, ...)
     336 [-]: FASTCALL1 62 R7 L46; 
     337 [-]: MOVE R9 R7   ; var9 = var7
     338 [-]: GETIMPORT R8 10; var8 = 0x7B998233
     339 [-]: CALL R8 2 2  ; var8 = var8(var9)
L46: 340 [-]: JUMPIF R8 L47; goto L47 if var8
     341 [-]: GETIMPORT R10 6; var10 = 0x0469F296
     342 [-]: LOADK R11 K61; var11 = "TubificidRig"
     343 [-]: CALL R10 2 0 ; var10, ... = var10(var11)
     344 [-]: NAMECALL R8 R7 K62; var9 = var7; var8 = var7[0x26D544FC]
     345 [-]: CALL R8 0 1  ; var8(var9, ...)
L47: 346 [-]: GETIMPORT R8 4; var8 = 0x89326C93
     347 [-]: GETIMPORT R10 6; var10 = 0x0469F296
     348 [-]: LOADK R11 K36; var11 = "DragonIntroCin"
     349 [-]: CALL R10 2 0 ; var10, ... = var10(var11)
     350 [-]: NAMECALL R8 R8 K8; var9 = var8; var8 = var8[0x46A0EBF5]
     351 [-]: CALL R8 0 2  ; var8 = var8(var9, ...)
     352 [-]: FASTCALL1 62 R8 L48; 
     353 [-]: MOVE R10 R8  ; var10 = var8
     354 [-]: GETIMPORT R9 10; var9 = 0x7B998233
     355 [-]: CALL R9 2 2  ; var9 = var9(var10)
L48: 356 [-]: JUMPIF R9 L49; goto L49 if var9
     357 [-]: LOADK R11 K63; var11 = "StartPlaying"
     358 [-]: NAMECALL R9 R8 K64; var10 = var8; var9 = var8[0x8EB2112D]
     359 [-]: CALL R9 3 1  ; var9(var10, var11)
L49: 360 [-]: RETURN R0 0  ; 
L50: 361 [-]: GETIMPORT R7 4; var7 = 0x89326C93
     362 [-]: NAMECALL R7 R7 K14; var8 = var7; var7 = var7[0x18D05D30]
     363 [-]: CALL R7 2 2  ; var7 = var7(var8)
     364 [-]: JUMPIFNOT R7 L53; goto L53 if not var7
     365 [-]: GETIMPORT R7 4; var7 = 0x89326C93
     366 [-]: GETIMPORT R9 66; var9 = gDragonBossFlyingAvatarType
     367 [-]: NAMECALL R10 R1 K38; var11 = var1; var10 = var1[0xD1586535]
     368 [-]: CALL R10 2 2 ; var10 = var10(var11)
     369 [-]: LOADK R11 K39; var11 = 3.4028234663852886e+38
     370 [-]: NAMECALL R7 R7 K40; var8 = var7; var7 = var7[0x4E5939A5]
     371 [-]: CALL R7 5 2  ; var7 = var7(var8, var9, var10, var11)
L51: 372 [-]: FASTCALL1 62 R7 L52; 
     373 [-]: MOVE R9 R7   ; var9 = var7
     374 [-]: GETIMPORT R8 10; var8 = 0x7B998233
     375 [-]: CALL R8 2 2  ; var8 = var8(var9)
L52: 376 [-]: JUMPIF R8 L53; goto L53 if var8
     377 [-]: GETIMPORT R8 13; var8 = 0xCBD666E1
     378 [-]: LOADN R9 0   ; var9 = 0
     379 [-]: CALL R8 2 1  ; var8(var9)
     380 [-]: JUMPBACK L51 ; goto L51
L53: 381 [-]: GETIMPORT R7 68; var7 = 0x69CF4AD2
     382 [-]: GETIMPORT R9 19; var9 = 0xBE190284
     383 [-]: NAMECALL R9 R9 K69; var10 = var9; var9 = var9[0xEF893AEC]
     384 [-]: CALL R9 2 2  ; var9 = var9(var10)
     385 [-]: GETTABLEKS R8 R9 K70; var8 = var9["tier"]
     386 [-]: LOADN R9 0   ; var9 = 0
     387 [-]: JUMPIFNOTLT R9 R8 L54; goto L54 if var9 >= var4720462
     388 [-]: GETIMPORT R7 72; var7 = 0xD7D7D289
L54: 389 [-]: GETIMPORT R8 4; var8 = 0x89326C93
     390 [-]: GETIMPORT R10 27; var10 = 0xFC65B1D8
     391 [-]: NAMECALL R11 R1 K38; var12 = var1; var11 = var1[0xD1586535]
     392 [-]: CALL R11 2 2 ; var11 = var11(var12)
     393 [-]: LOADK R12 K39; var12 = 3.4028234663852886e+38
     394 [-]: NAMECALL R8 R8 K40; var9 = var8; var8 = var8[0x4E5939A5]
     395 [-]: CALL R8 5 2  ; var8 = var8(var9, var10, var11, var12)
     396 [-]: LOADNIL R9   ; var9 = nil
     397 [-]: FASTCALL1 62 R8 L55; 
     398 [-]: MOVE R11 R8  ; var11 = var8
     399 [-]: GETIMPORT R10 10; var10 = 0x7B998233
     400 [-]: CALL R10 2 2 ; var10 = var10(var11)
L55: 401 [-]: JUMPIF R10 L56; goto L56 if var10
     402 [-]: NAMECALL R10 R8 K73; var11 = var8; var10 = var8[0xFA9E477F]
     403 [-]: CALL R10 2 2 ; var10 = var10(var11)
     404 [-]: MOVE R9 R10  ; var9 = var10
     405 [-]: JUMP L57     ; goto L57
L56: 406 [-]: GETIMPORT R10 4; var10 = 0x89326C93
     407 [-]: NAMECALL R10 R10 K31; var11 = var10; var10 = var10[0x29EF273D]
     408 [-]: CALL R10 2 2 ; var10 = var10(var11)
     409 [-]: GETIMPORT R12 75; var12 = 0x88EFC25E
     410 [-]: GETIMPORT R13 77; var13 = 0x339432FA
     411 [-]: CALL R12 2 2 ; var12 = var12(var13)
     412 [-]: GETUPVAL R13 11; var13 = upvalues[11]
     413 [-]: GETIMPORT R14 79; var14 = ZERO_ROTATION
     414 [-]: GETIMPORT R15 6; var15 = 0x0469F296
     415 [-]: LOADK R16 K80; var16 = "RandomTeam"
     416 [-]: CALL R15 2 2 ; var15 = var15(var16)
     417 [-]: MOVE R16 R7  ; var16 = var7
     418 [-]: NAMECALL R10 R10 K81; var11 = var10; var10 = var10[0x6CD833C5]
     419 [-]: CALL R10 7 2 ; var10 = var10(var11, var12, var13, var14, var15, var16)
     420 [-]: MOVE R9 R10  ; var9 = var10
L57: 421 [-]: FASTCALL1 62 R9 L58; 
     422 [-]: MOVE R11 R9  ; var11 = var9
     423 [-]: GETIMPORT R10 10; var10 = 0x7B998233
     424 [-]: CALL R10 2 2 ; var10 = var10(var11)
L58: 425 [-]: JUMPIFNOT R10 L59; goto L59 if not var10
     426 [-]: RETURN R0 0  ; 
L59: 427 [-]: JUMPXEQKN R6 K34 L63 NOT; 
     428 [-]: JUMPIF R2 L63; goto L63 if var2
     429 [-]: GETIMPORT R10 4; var10 = 0x89326C93
     430 [-]: GETIMPORT R12 6; var12 = 0x0469F296
     431 [-]: LOADK R13 K36; var13 = "DragonIntroCin"
     432 [-]: CALL R12 2 0 ; var12, ... = var12(var13)
     433 [-]: NAMECALL R10 R10 K8; var11 = var10; var10 = var10[0x46A0EBF5]
     434 [-]: CALL R10 0 2 ; var10 = var10(var11, ...)
     435 [-]: FASTCALL1 62 R10 L60; 
     436 [-]: MOVE R12 R10 ; var12 = var10
     437 [-]: GETIMPORT R11 10; var11 = 0x7B998233
     438 [-]: CALL R11 2 2 ; var11 = var11(var12)
L60: 439 [-]: JUMPIF R11 L64; goto L64 if var11
     440 [-]: GETIMPORT R11 13; var11 = 0xCBD666E1
     441 [-]: LOADN R12 0  ; var12 = 0
     442 [-]: CALL R11 2 1 ; var11(var12)
     443 [-]: LOADK R13 K63; var13 = "StartPlaying"
     444 [-]: NAMECALL R11 R10 K64; var12 = var10; var11 = var10[0x8EB2112D]
     445 [-]: CALL R11 3 1 ; var11(var12, var13)
L61: 446 [-]: NAMECALL R11 R10 K82; var12 = var10; var11 = var10[0x1C84839C]
     447 [-]: CALL R11 2 2 ; var11 = var11(var12)
     448 [-]: JUMPIFNOT R11 L62; goto L62 if not var11
     449 [-]: GETIMPORT R11 13; var11 = 0xCBD666E1
     450 [-]: LOADN R12 0  ; var12 = 0
     451 [-]: CALL R11 2 1 ; var11(var12)
     452 [-]: JUMPBACK L61 ; goto L61
L62: 453 [-]: GETIMPORT R11 19; var11 = 0xBE190284
     454 [-]: GETUPVAL R13 3; var13 = upvalues[3]
     455 [-]: LOADN R14 1  ; var14 = 1
     456 [-]: NAMECALL R11 R11 K35; var12 = var11; var11 = var11[0x751F061D]
     457 [-]: CALL R11 4 1 ; var11(var12, var13, var14)
     458 [-]: JUMP L64     ; goto L64
L63: 459 [-]: JUMPXEQKN R6 K83 L64 NOT; 
     460 [-]: GETIMPORT R10 13; var10 = 0xCBD666E1
     461 [-]: LOADN R11 0  ; var11 = 0
     462 [-]: CALL R10 2 1 ; var10(var11)
     463 [-]: GETUPVAL R10 6; var10 = upvalues[6]
     464 [-]: CALL R10 1 1 ; var10()
     465 [-]: RETURN R0 0  ; 
L64: 466 [-]: GETIMPORT R10 4; var10 = 0x89326C93
     467 [-]: NAMECALL R10 R10 K47; var11 = var10; var10 = var10[0x7D108DDB]
     468 [-]: CALL R10 2 2 ; var10 = var10(var11)
     469 [-]: LOADN R13 1  ; var13 = 1
     470 [-]: LENGTH R11 R10; var11 = #var10
     471 [-]: LOADN R12 1  ; var12 = 1
     472 [-]: FORNPREP R11 L71; nforprep start - [escape at L71] -- var11 = iterator
L65: 473 [-]: GETTABLE R14 R10 R13; var14 = var10[var13]
     474 [-]: FASTCALL1 62 R14 L66; 
     475 [-]: MOVE R16 R14 ; var16 = var14
     476 [-]: GETIMPORT R15 10; var15 = 0x7B998233
     477 [-]: CALL R15 2 2 ; var15 = var15(var16)
L66: 478 [-]: JUMPIF R15 L70; goto L70 if var15
     479 [-]: LOADN R17 8  ; var17 = 8
     480 [-]: NAMECALL R15 R14 K17; var16 = var14; var15 = var14[0xE3A0BBCA]
     481 [-]: CALL R15 3 2 ; var15 = var15(var16, var17)
     482 [-]: FASTCALL1 62 R15 L67; 
     483 [-]: MOVE R17 R15 ; var17 = var15
     484 [-]: GETIMPORT R16 10; var16 = 0x7B998233
     485 [-]: CALL R16 2 2 ; var16 = var16(var17)
L67: 486 [-]: JUMPIF R16 L68; goto L68 if var16
     487 [-]: LOADB R18 0  ; var18 = false
     488 [-]: NAMECALL R16 R15 K84; var17 = var15; var16 = var15[0xE39D0733]
     489 [-]: CALL R16 3 1 ; var16(var17, var18)
     490 [-]: LOADB R18 0  ; var18 = false
     491 [-]: NAMECALL R16 R15 K85; var17 = var15; var16 = var15[0x8FF7507F]
     492 [-]: CALL R16 3 1 ; var16(var17, var18)
     493 [-]: LOADB R18 1  ; var18 = true
     494 [-]: NAMECALL R16 R15 K86; var17 = var15; var16 = var15[0x6667E5D4]
     495 [-]: CALL R16 3 1 ; var16(var17, var18)
     496 [-]: LOADB R18 1  ; var18 = true
     497 [-]: NAMECALL R16 R15 K87; var17 = var15; var16 = var15[0x069D881F]
     498 [-]: CALL R16 3 1 ; var16(var17, var18)
     499 [-]: LOADB R18 0  ; var18 = false
     500 [-]: LOADB R19 1  ; var19 = true
     501 [-]: NAMECALL R16 R15 K88; var17 = var15; var16 = var15[0x768274D6]
     502 [-]: CALL R16 4 1 ; var16(var17, var18, var19)
L68: 503 [-]: LOADN R18 0  ; var18 = 0
     504 [-]: NAMECALL R16 R14 K17; var17 = var14; var16 = var14[0xE3A0BBCA]
     505 [-]: CALL R16 3 2 ; var16 = var16(var17, var18)
     506 [-]: FASTCALL1 62 R16 L69; 
     507 [-]: MOVE R18 R16 ; var18 = var16
     508 [-]: GETIMPORT R17 10; var17 = 0x7B998233
     509 [-]: CALL R17 2 2 ; var17 = var17(var18)
L69: 510 [-]: JUMPIF R17 L70; goto L70 if var17
     511 [-]: NAMECALL R17 R16 K52; var18 = var16; var17 = var16[0xDE321E6F]
     512 [-]: CALL R17 2 2 ; var17 = var17(var18)
     513 [-]: GETUPVAL R19 13; var19 = upvalues[13]
     514 [-]: LOADN R20 47 ; var20 = 47
     515 [-]: LOADN R21 4  ; var21 = 4
     516 [-]: LOADN R22 50 ; var22 = 50
     517 [-]: NAMECALL R17 R17 K89; var18 = var17; var17 = var17[0xEADE8050]
     518 [-]: CALL R17 6 1 ; var17(var18, var19, var20, var21, var22)
L70: 519 [-]: FORNLOOP R11 L65; nforloop end - iterate + goto L65
L71: 520 [-]: FASTCALL1 62 R9 L72; 
     521 [-]: MOVE R12 R9  ; var12 = var9
     522 [-]: GETIMPORT R11 10; var11 = 0x7B998233
     523 [-]: CALL R11 2 2 ; var11 = var11(var12)
L72: 524 [-]: JUMPIF R11 L73; goto L73 if var11
     525 [-]: NAMECALL R11 R9 K90; var12 = var9; var11 = var9[0x9E21E394]
     526 [-]: CALL R11 2 1 ; var11(var12)
     527 [-]: GETIMPORT R13 4; var13 = 0x89326C93
     528 [-]: NAMECALL R13 R13 K17; var14 = var13; var13 = var13[0xE3A0BBCA]
     529 [-]: CALL R13 2 0 ; var13, ... = var13(var14)
     530 [-]: NAMECALL R11 R9 K91; var12 = var9; var11 = var9[0x6AD018DE]
     531 [-]: CALL R11 0 1 ; var11(var12, ...)
     532 [-]: NAMECALL R11 R9 K92; var12 = var9; var11 = var9[0xAC41835F]
     533 [-]: CALL R11 2 1 ; var11(var12)
L73: 534 [-]: NAMECALL R11 R9 K48; var12 = var9; var11 = var9[0xBB610E5B]
     535 [-]: CALL R11 2 2 ; var11 = var11(var12)
     536 [-]: MOVE R8 R11  ; var8 = var11
     537 [-]: GETUPVAL R11 14; var11 = upvalues[14]
     538 [-]: MOVE R12 R8  ; var12 = var8
     539 [-]: CALL R11 2 1 ; var11(var12)
L74: 540 [-]: GETIMPORT R12 94; var12 = _T["SetupBossAvatar"]
     541 [-]: FASTCALL1 62 R12 L75; 
     542 [-]: GETIMPORT R11 10; var11 = 0x7B998233
     543 [-]: CALL R11 2 2 ; var11 = var11(var12)
L75: 544 [-]: JUMPIFNOT R11 L76; goto L76 if not var11
     545 [-]: GETIMPORT R11 13; var11 = 0xCBD666E1
     546 [-]: LOADN R12 0  ; var12 = 0
     547 [-]: CALL R11 2 1 ; var11(var12)
     548 [-]: JUMPBACK L74 ; goto L74
L76: 549 [-]: GETIMPORT R11 94; var11 = _T["SetupBossAvatar"]
     550 [-]: MOVE R12 R8  ; var12 = var8
     551 [-]: GETIMPORT R14 43; var14 = 0xC72EF5D9
     552 [-]: LENGTH R13 R14; var13 = #var14
     553 [-]: LOADNIL R14  ; var14 = nil
     554 [-]: LOADB R15 1  ; var15 = true
     555 [-]: CALL R11 5 1 ; var11(var12, var13, var14, var15)
     556 [-]: GETIMPORT R13 6; var13 = 0x0469F296
     557 [-]: LOADK R14 K29; var14 = "NewRespawnMonitor"
     558 [-]: CALL R13 2 2 ; var13 = var13(var14)
     559 [-]: LOADB R14 0  ; var14 = false
     560 [-]: NAMECALL R11 R8 K30; var12 = var8; var11 = var8[0xD5F7912B]
     561 [-]: CALL R11 4 1 ; var11(var12, var13, var14)
     562 [-]: GETIMPORT R13 6; var13 = 0x0469F296
     563 [-]: LOADK R14 K95; var14 = "HorseSpawnMonitor"
     564 [-]: CALL R13 2 2 ; var13 = var13(var14)
     565 [-]: LOADB R14 0  ; var14 = false
     566 [-]: NAMECALL R11 R8 K30; var12 = var8; var11 = var8[0xD5F7912B]
     567 [-]: CALL R11 4 1 ; var11(var12, var13, var14)
     568 [-]: GETUPVAL R11 15; var11 = upvalues[15]
     569 [-]: NAMECALL R12 R9 K48; var13 = var9; var12 = var9[0xBB610E5B]
     570 [-]: CALL R12 2 0 ; var12, ... = var12(var13)
     571 [-]: CALL R11 0 1 ; var11(var12, ...)
     572 [-]: GETIMPORT R11 4; var11 = 0x89326C93
     573 [-]: NAMECALL R11 R11 K47; var12 = var11; var11 = var11[0x7D108DDB]
     574 [-]: CALL R11 2 2 ; var11 = var11(var12)
     575 [-]: MOVE R10 R11 ; var10 = var11
     576 [-]: LOADN R13 1  ; var13 = 1
     577 [-]: LENGTH R11 R10; var11 = #var10
     578 [-]: LOADN R12 1  ; var12 = 1
     579 [-]: FORNPREP R11 L81; nforprep start - [escape at L81] -- var11 = iterator
L77: 580 [-]: GETTABLE R14 R10 R13; var14 = var10[var13]
     581 [-]: FASTCALL1 62 R14 L78; 
     582 [-]: MOVE R16 R14 ; var16 = var14
     583 [-]: GETIMPORT R15 10; var15 = 0x7B998233
     584 [-]: CALL R15 2 2 ; var15 = var15(var16)
L78: 585 [-]: JUMPIF R15 L80; goto L80 if var15
     586 [-]: LOADN R17 0  ; var17 = 0
     587 [-]: NAMECALL R15 R14 K17; var16 = var14; var15 = var14[0xE3A0BBCA]
     588 [-]: CALL R15 3 2 ; var15 = var15(var16, var17)
     589 [-]: FASTCALL1 62 R15 L79; 
     590 [-]: MOVE R17 R15 ; var17 = var15
     591 [-]: GETIMPORT R16 10; var16 = 0x7B998233
     592 [-]: CALL R16 2 2 ; var16 = var16(var17)
L79: 593 [-]: JUMPIF R16 L80; goto L80 if var16
     594 [-]: NAMECALL R16 R15 K52; var17 = var15; var16 = var15[0xDE321E6F]
     595 [-]: CALL R16 2 2 ; var16 = var16(var17)
     596 [-]: GETUPVAL R18 13; var18 = upvalues[13]
     597 [-]: LOADN R19 47 ; var19 = 47
     598 [-]: LOADN R20 4  ; var20 = 4
     599 [-]: LOADN R21 50 ; var21 = 50
     600 [-]: NAMECALL R16 R16 K96; var17 = var16; var16 = var16[0x2722B5C3]
     601 [-]: CALL R16 6 1 ; var16(var17, var18, var19, var20, var21)
     602 [-]: GETIMPORT R18 98; var18 = 0x8C55FAB0
     603 [-]: NAMECALL R16 R15 K99; var17 = var15; var16 = var15[0x0866B4BD]
     604 [-]: CALL R16 3 2 ; var16 = var16(var17, var18)
     605 [-]: JUMPIFNOT R16 L80; goto L80 if not var16
     606 [-]: GETIMPORT R18 98; var18 = 0x8C55FAB0
     607 [-]: NAMECALL R16 R15 K100; var17 = var15; var16 = var15[0x35B09371]
     608 [-]: CALL R16 3 1 ; var16(var17, var18)
L80: 609 [-]: FORNLOOP R11 L77; nforloop end - iterate + goto L77
L81: 610 [-]: RETURN R0 0  ; 


; Name:            
; Defined at line: 1686
; #Upvalues:       0
; #Parameters:     0
; Is_vararg:       0
; Max Stack Size:  6

       0 [-]: GETIMPORT R0 1; var0 = 0x89326C93
       1 [-]: GETIMPORT R2 3; var2 = 0xFC65B1D8
       2 [-]: NAMECALL R0 R0 K4; var1 = var0; var0 = var0[0xFB669000]
       3 [-]: CALL R0 3 2  ; var0 = var0(var1, var2)
       4 [-]: FASTCALL1 62 R0 L0; 
       5 [-]: MOVE R2 R0   ; var2 = var0
       6 [-]: GETIMPORT R1 6; var1 = 0x7B998233
       7 [-]: CALL R1 2 2  ; var1 = var1(var2)
L 0:   8 [-]: JUMPIF R1 L4 ; goto L4 if var1
       9 [-]: LENGTH R1 R0 ; var1 = #var0
      10 [-]: LOADN R2 0   ; var2 = 0
      11 [-]: JUMPIFNOTLT R2 R1 L4; goto L4 if var2 >= var549
      12 [-]: GETTABLEN R2 R0 1; var2 = var0[1]
      13 [-]: FASTCALL1 62 R2 L1; 
      14 [-]: GETIMPORT R1 6; var1 = 0x7B998233
      15 [-]: CALL R1 2 2  ; var1 = var1(var2)
L 1:  16 [-]: JUMPIF R1 L4 ; goto L4 if var1
      17 [-]: GETTABLEN R1 R0 1; var1 = var0[1]
      18 [-]: NAMECALL R1 R1 K7; var2 = var1; var1 = var1[0xFA9E477F]
      19 [-]: CALL R1 2 2  ; var1 = var1(var2)
      20 [-]: FASTCALL1 62 R1 L2; 
      21 [-]: MOVE R3 R1   ; var3 = var1
      22 [-]: GETIMPORT R2 6; var2 = 0x7B998233
      23 [-]: CALL R2 2 2  ; var2 = var2(var3)
L 2:  24 [-]: JUMPIF R2 L4 ; goto L4 if var2
      25 [-]: NAMECALL R2 R1 K8; var3 = var1; var2 = var1[0xA4E3EC34]
      26 [-]: CALL R2 2 2  ; var2 = var2(var3)
      27 [-]: FASTCALL1 62 R2 L3; 
      28 [-]: MOVE R4 R2   ; var4 = var2
      29 [-]: GETIMPORT R3 6; var3 = 0x7B998233
      30 [-]: CALL R3 2 2  ; var3 = var3(var4)
L 3:  31 [-]: JUMPIF R3 L4 ; goto L4 if var3
      32 [-]: MOVE R5 R2   ; var5 = var2
      33 [-]: NAMECALL R3 R1 K9; var4 = var1; var3 = var1[0x0DFD40C9]
      34 [-]: CALL R3 3 1  ; var3(var4, var5)
L 4:  35 [-]: RETURN R0 0  ; 


; Name:            
; Defined at line: 1701
; #Upvalues:       1
; #Parameters:     0
; Is_vararg:       0
; Max Stack Size:  3

       0 [-]: GETIMPORT R0 1; var0 = 0xBE190284
       1 [-]: GETUPVAL R2 0; var2 = upvalues[0]
       2 [-]: NAMECALL R0 R0 K2; var1 = var0; var0 = var0[0x0EB34C69]
       3 [-]: CALL R0 3 2  ; var0 = var0(var1, var2)
       4 [-]: LOADB R1 0   ; var1 = false
       5 [-]: LOADN R2 1   ; var2 = 1
       6 [-]: JUMPIFNOTLT R2 R0 L1; goto L1 if var2 >= var197191
       7 [-]: LOADN R2 3   ; var2 = 3
       8 [-]: JUMPIFLE R0 R2 L0; goto L0 if var0 <= var16777499
       9 [-]: LOADB R1 0 +1; var1 = false
L 0:  10 [-]: LOADB R1 1   ; var1 = true
L 1:  11 [-]: RETURN R1 1  ; 


; Name:            
; Defined at line: 1706
; #Upvalues:       0
; #Parameters:     1
; Is_vararg:       0
; Max Stack Size:  5

       0 [-]: GETIMPORT R1 1; var1 = 0xCBD666E1
       1 [-]: LOADN R2 0   ; var2 = 0
       2 [-]: CALL R1 2 1  ; var1(var2)
       3 [-]: FASTCALL1 62 R0 L0; 
       4 [-]: MOVE R2 R0   ; var2 = var0
       5 [-]: GETIMPORT R1 3; var1 = 0x7B998233
       6 [-]: CALL R1 2 2  ; var1 = var1(var2)
L 0:   7 [-]: JUMPIF R1 L2 ; goto L2 if var1
       8 [-]: NAMECALL R1 R0 K4; var2 = var0; var1 = var0[0x5163741E]
       9 [-]: CALL R1 2 2  ; var1 = var1(var2)
      10 [-]: FASTCALL1 62 R1 L1; 
      11 [-]: MOVE R3 R1   ; var3 = var1
      12 [-]: GETIMPORT R2 3; var2 = 0x7B998233
      13 [-]: CALL R2 2 2  ; var2 = var2(var3)
L 1:  14 [-]: JUMPIF R2 L2 ; goto L2 if var2
      15 [-]: NAMECALL R2 R1 K5; var3 = var1; var2 = var1[0xDE321E6F]
      16 [-]: CALL R2 2 2  ; var2 = var2(var3)
      17 [-]: LOADB R4 1   ; var4 = true
      18 [-]: NAMECALL R2 R2 K6; var3 = var2; var2 = var2[0x59FE5ABE]
      19 [-]: CALL R2 3 1  ; var2(var3, var4)
      20 [-]: NAMECALL R2 R1 K5; var3 = var1; var2 = var1[0xDE321E6F]
      21 [-]: CALL R2 2 2  ; var2 = var2(var3)
      22 [-]: LOADB R4 0   ; var4 = false
      23 [-]: NAMECALL R2 R2 K7; var3 = var2; var2 = var2[0x0B5EC5B5]
      24 [-]: CALL R2 3 1  ; var2(var3, var4)
L 2:  25 [-]: RETURN R0 0  ; 


; Name:            
; Defined at line: 1717
; #Upvalues:       0
; #Parameters:     1
; Is_vararg:       0
; Max Stack Size:  7

       0 [-]: GETIMPORT R1 1; var1 = 0x89326C93
       1 [-]: NAMECALL R1 R1 K2; var2 = var1; var1 = var1[0x18D05D30]
       2 [-]: CALL R1 2 2  ; var1 = var1(var2)
       3 [-]: JUMPIF R1 L0 ; goto L0 if var1
       4 [-]: RETURN R0 0  ; 
L 0:   5 [-]: NAMECALL R1 R0 K3; var2 = var0; var1 = var0[0x2B54251B]
       6 [-]: CALL R1 2 2  ; var1 = var1(var2)
       7 [-]: FASTCALL1 62 R1 L1; 
       8 [-]: MOVE R3 R1   ; var3 = var1
       9 [-]: GETIMPORT R2 5; var2 = 0x7B998233
      10 [-]: CALL R2 2 2  ; var2 = var2(var3)
L 1:  11 [-]: JUMPIFNOT R2 L2; goto L2 if not var2
      12 [-]: RETURN R0 0  ; 
L 2:  13 [-]: NAMECALL R2 R0 K6; var3 = var0; var2 = var0[0xD2715720]
      14 [-]: CALL R2 2 2  ; var2 = var2(var3)
      15 [-]: LOADN R3 0   ; var3 = 0
      16 [-]: JUMPIFNOTLE R2 R3 L3; goto L3 if var2 > var-1644100795
      17 [-]: NAMECALL R3 R1 K7; var4 = var1; var3 = var1[0xF37C129E]
      18 [-]: CALL R3 2 1  ; var3(var4)
      19 [-]: RETURN R0 0  ; 
L 3:  20 [-]: GETIMPORT R5 9; var5 = 0x096F0DE4
      21 [-]: GETIMPORT R6 11; var6 = EMPTY_SYMBOL
      22 [-]: NAMECALL R3 R0 K12; var4 = var0; var3 = var0[0x47901F07]
      23 [-]: CALL R3 4 1  ; var3(var4, var5, var6)
      24 [-]: RETURN R0 0  ; 


; Name:            
; Defined at line: 1735
; #Upvalues:       0
; #Parameters:     0
; Is_vararg:       0
; Max Stack Size:  13

       0 [-]: GETIMPORT R0 1; var0 = 0x89326C93
       1 [-]: NAMECALL R0 R0 K2; var1 = var0; var0 = var0[0x8B5B1F58]
       2 [-]: CALL R0 2 2  ; var0 = var0(var1)
       3 [-]: LOADN R1 0   ; var1 = 0
       4 [-]: NEWTABLE R2 0 0; var2 = {}
       5 [-]: LOADN R5 1   ; var5 = 1
       6 [-]: LENGTH R3 R0 ; var3 = #var0
       7 [-]: LOADN R4 1   ; var4 = 1
       8 [-]: FORNPREP R3 L1; nforprep start - [escape at L1] -- var3 = iterator
L 0:   9 [-]: LOADB R6 0   ; var6 = false
      10 [-]: SETTABLE R6 R2 R5; var6[var2] = var5
      11 [-]: FORNLOOP R3 L0; nforloop end - iterate + goto L0
L 1:  12 [-]: LENGTH R3 R0 ; var3 = #var0
      13 [-]: JUMPIFNOTLT R1 R3 L8; goto L8 if var1 >= var66382
      14 [-]: GETIMPORT R3 1; var3 = 0x89326C93
      15 [-]: NAMECALL R3 R3 K2; var4 = var3; var3 = var3[0x8B5B1F58]
      16 [-]: CALL R3 2 2  ; var3 = var3(var4)
      17 [-]: LOADN R6 1   ; var6 = 1
      18 [-]: LENGTH R4 R3 ; var4 = #var3
      19 [-]: LOADN R5 1   ; var5 = 1
      20 [-]: FORNPREP R4 L7; nforprep start - [escape at L7] -- var4 = iterator
L 2:  21 [-]: GETTABLE R7 R3 R6; var7 = var3[var6]
      22 [-]: FASTCALL1 62 R7 L3; 
      23 [-]: MOVE R9 R7   ; var9 = var7
      24 [-]: GETIMPORT R8 4; var8 = 0x7B998233
      25 [-]: CALL R8 2 2  ; var8 = var8(var9)
L 3:  26 [-]: JUMPIF R8 L6 ; goto L6 if var8
      27 [-]: GETTABLE R8 R2 R6; var8 = var2[var6]
      28 [-]: JUMPIF R8 L6 ; goto L6 if var8
      29 [-]: GETIMPORT R10 6; var10 = gLotusVehicleAvatarType
      30 [-]: NAMECALL R8 R7 K7; var9 = var7; var8 = var7[0xF2DEAF69]
      31 [-]: CALL R8 3 2  ; var8 = var8(var9, var10)
      32 [-]: JUMPIFNOT R8 L6; goto L6 if not var8
      33 [-]: NAMECALL R8 R7 K8; var9 = var7; var8 = var7[0xFF005826]
      34 [-]: CALL R8 2 2  ; var8 = var8(var9)
      35 [-]: GETIMPORT R10 10; var10 = 0x851A139F
      36 [-]: FASTCALL1 62 R10 L4; 
      37 [-]: GETIMPORT R9 4; var9 = 0x7B998233
      38 [-]: CALL R9 2 2  ; var9 = var9(var10)
L 4:  39 [-]: JUMPIF R9 L6 ; goto L6 if var9
      40 [-]: FASTCALL1 62 R8 L5; 
      41 [-]: MOVE R10 R8  ; var10 = var8
      42 [-]: GETIMPORT R9 4; var9 = 0x7B998233
      43 [-]: CALL R9 2 2  ; var9 = var9(var10)
L 5:  44 [-]: JUMPIF R9 L6 ; goto L6 if var9
      45 [-]: NAMECALL R9 R8 K11; var10 = var8; var9 = var8[0xDE321E6F]
      46 [-]: CALL R9 2 2  ; var9 = var9(var10)
      47 [-]: LOADN R11 0  ; var11 = 0
      48 [-]: LOADN R12 7  ; var12 = 7
      49 [-]: NAMECALL R9 R9 K12; var10 = var9; var9 = var9[0x447665BF]
      50 [-]: CALL R9 4 1  ; var9(var10, var11, var12)
      51 [-]: GETIMPORT R11 10; var11 = 0x851A139F
      52 [-]: LOADB R12 1  ; var12 = true
      53 [-]: NAMECALL R9 R8 K13; var10 = var8; var9 = var8[0x511D26B8]
      54 [-]: CALL R9 4 1  ; var9(var10, var11, var12)
      55 [-]: NAMECALL R9 R8 K11; var10 = var8; var9 = var8[0xDE321E6F]
      56 [-]: CALL R9 2 2  ; var9 = var9(var10)
      57 [-]: LOADB R11 0  ; var11 = false
      58 [-]: NAMECALL R9 R9 K14; var10 = var9; var9 = var9[0x0B5EC5B5]
      59 [-]: CALL R9 3 1  ; var9(var10, var11)
      60 [-]: LOADB R9 1   ; var9 = true
      61 [-]: SETTABLE R9 R2 R6; var9[var2] = var6
      62 [-]: ADDK R1 R1 K15; var1 = var1 + 1
L 6:  63 [-]: FORNLOOP R4 L2; nforloop end - iterate + goto L2
L 7:  64 [-]: GETIMPORT R4 17; var4 = 0xCBD666E1
      65 [-]: LOADN R5 0   ; var5 = 0
      66 [-]: CALL R4 2 1  ; var4(var5)
      67 [-]: JUMPBACK L1  ; goto L1
L 8:  68 [-]: RETURN R0 0  ; 


; Name:            
; Defined at line: 1767
; #Upvalues:       0
; #Parameters:     1
; Is_vararg:       0
; Max Stack Size:  25

       0 [-]: LOADN R1 -1  ; var1 = -1
       1 [-]: MOVE R2 R1   ; var2 = var1
       2 [-]: LOADB R3 1   ; var3 = true
       3 [-]: NEWTABLE R4 0 3; var4 = {}
       4 [-]: LOADN R5 10  ; var5 = 10
       5 [-]: LOADN R6 5   ; var6 = 5
       6 [-]: LOADK R7 K0  ; var7 = 0.14999999999999999
       7 [-]: SETLIST R4 R5 3 [1]; var4[1] = var5; var4[2] = var6; var4[3] = var7; var4[4] = var8; 
       8 [-]: NEWTABLE R5 0 3; var5 = {}
       9 [-]: LOADN R6 1   ; var6 = 1
      10 [-]: LOADK R7 K1  ; var7 = 1.8
      11 [-]: LOADN R8 2   ; var8 = 2
      12 [-]: SETLIST R5 R6 3 [1]; var5[1] = var6; var5[2] = var7; var5[3] = var8; var5[4] = var9; 
      13 [-]: LOADN R6 0   ; var6 = 0
      14 [-]: GETIMPORT R7 3; var7 = 0xC163F229
      15 [-]: LOADK R8 K4  ; var8 = 12.5
      16 [-]: LOADN R9 10  ; var9 = 10
      17 [-]: CALL R7 3 2  ; var7 = var7(var8, var9)
      18 [-]: LOADN R8 1   ; var8 = 1
      19 [-]: LOADN R9 1   ; var9 = 1
      20 [-]: NEWTABLE R10 0 0; var10 = {}
      21 [-]: GETIMPORT R11 6; var11 = 0x89326C93
      22 [-]: NAMECALL R11 R11 K7; var12 = var11; var11 = var11[0x8B5B1F58]
      23 [-]: CALL R11 2 2 ; var11 = var11(var12)
      24 [-]: LENGTH R12 R11; var12 = #var11
      25 [-]: LOADN R15 1  ; var15 = 1
      26 [-]: LENGTH R13 R11; var13 = #var11
      27 [-]: LOADN R14 1  ; var14 = 1
      28 [-]: FORNPREP R13 L1; nforprep start - [escape at L1] -- var13 = iterator
L 0:  29 [-]: LOADN R16 0  ; var16 = 0
      30 [-]: SETTABLE R16 R10 R15; var16[var10] = var15
      31 [-]: FORNLOOP R13 L0; nforloop end - iterate + goto L0
L 1:  32 [-]: FASTCALL1 62 R0 L2; 
      33 [-]: MOVE R14 R0  ; var14 = var0
      34 [-]: GETIMPORT R13 9; var13 = 0x7B998233
      35 [-]: CALL R13 2 2 ; var13 = var13(var14)
L 2:  36 [-]: JUMPIF R13 L26; goto L26 if var13
      37 [-]: NAMECALL R13 R0 K10; var14 = var0; var13 = var0[0x2047CFE7]
      38 [-]: CALL R13 2 2 ; var13 = var13(var14)
      39 [-]: JUMPIF R13 L26; goto L26 if var13
      40 [-]: NAMECALL R13 R0 K11; var14 = var0; var13 = var0[0x73901ACF]
      41 [-]: CALL R13 2 2 ; var13 = var13(var14)
      42 [-]: JUMPIF R13 L26; goto L26 if var13
      43 [-]: GETIMPORT R13 6; var13 = 0x89326C93
      44 [-]: NAMECALL R13 R13 K7; var14 = var13; var13 = var13[0x8B5B1F58]
      45 [-]: CALL R13 2 2 ; var13 = var13(var14)
      46 [-]: MOVE R11 R13 ; var11 = var13
      47 [-]: LENGTH R13 R11; var13 = #var11
      48 [-]: JUMPIFEQ R13 R12 L4; goto L4 if var13 == var723984
      49 [-]: LENGTH R12 R11; var12 = #var11
      50 [-]: NEWTABLE R10 0 0; var10 = {}
      51 [-]: LOADN R15 1  ; var15 = 1
      52 [-]: LENGTH R13 R11; var13 = #var11
      53 [-]: LOADN R14 1  ; var14 = 1
      54 [-]: FORNPREP R13 L4; nforprep start - [escape at L4] -- var13 = iterator
L 3:  55 [-]: LOADN R16 0  ; var16 = 0
      56 [-]: SETTABLE R16 R10 R15; var16[var10] = var15
      57 [-]: FORNLOOP R13 L3; nforloop end - iterate + goto L3
L 4:  58 [-]: LOADN R1 3   ; var1 = 3
      59 [-]: LOADN R15 1  ; var15 = 1
      60 [-]: LENGTH R13 R11; var13 = #var11
      61 [-]: LOADN R14 1  ; var14 = 1
      62 [-]: FORNPREP R13 L19; nforprep start - [escape at L19] -- var13 = iterator
L 5:  63 [-]: GETTABLE R17 R11 R15; var17 = var11[var15]
      64 [-]: FASTCALL1 62 R17 L6; 
      65 [-]: GETIMPORT R16 9; var16 = 0x7B998233
      66 [-]: CALL R16 2 2 ; var16 = var16(var17)
L 6:  67 [-]: JUMPIF R16 L18; goto L18 if var16
      68 [-]: GETTABLE R17 R10 R15; var17 = var10[var15]
      69 [-]: FASTCALL1 62 R17 L7; 
      70 [-]: GETIMPORT R16 9; var16 = 0x7B998233
      71 [-]: CALL R16 2 2 ; var16 = var16(var17)
L 7:  72 [-]: JUMPIF R16 L18; goto L18 if var16
      73 [-]: NAMECALL R16 R0 K12; var17 = var0; var16 = var0[0x9BA17154]
      74 [-]: CALL R16 2 2 ; var16 = var16(var17)
      75 [-]: GETTABLE R18 R11 R15; var18 = var11[var15]
      76 [-]: NAMECALL R18 R18 K13; var19 = var18; var18 = var18[0xD1586535]
      77 [-]: CALL R18 2 2 ; var18 = var18(var19)
      78 [-]: NAMECALL R19 R0 K13; var20 = var0; var19 = var0[0xD1586535]
      79 [-]: CALL R19 2 2 ; var19 = var19(var20)
      80 [-]: SUB R17 R18 R19; var17 = var18 - var19
      81 [-]: GETTABLE R18 R11 R15; var18 = var11[var15]
      82 [-]: NAMECALL R18 R18 K12; var19 = var18; var18 = var18[0x9BA17154]
      83 [-]: CALL R18 2 2 ; var18 = var18(var19)
      84 [-]: GETIMPORT R19 15; var19 = 0xC2892F65
      85 [-]: MOVE R20 R17 ; var20 = var17
      86 [-]: CALL R19 2 1 ; var19(var20)
      87 [-]: GETTABLE R21 R11 R15; var21 = var11[var15]
      88 [-]: NAMECALL R19 R0 K16; var20 = var0; var19 = var0[0x68D0CBED]
      89 [-]: CALL R19 3 2 ; var19 = var19(var20, var21)
      90 [-]: LOADN R20 175; var20 = 175
      91 [-]: JUMPIFNOTLT R20 R19 L8; goto L8 if var20 >= var5191
      92 [-]: LOADN R20 0  ; var20 = 0
      93 [-]: SETTABLE R20 R10 R15; var20[var10] = var15
L 8:  94 [-]: GETIMPORT R20 18; var20 = 0x4FD57545
      95 [-]: MOVE R21 R17 ; var21 = var17
      96 [-]: MOVE R22 R16 ; var22 = var16
      97 [-]: CALL R20 3 2 ; var20 = var20(var21, var22)
      98 [-]: LOADN R21 0  ; var21 = 0
      99 [-]: JUMPIFNOTLT R21 R20 L10; goto L10 if var21 >= var1184846
     100 [-]: GETIMPORT R20 18; var20 = 0x4FD57545
     101 [-]: MOVE R21 R16 ; var21 = var16
     102 [-]: MOVE R22 R18 ; var22 = var18
     103 [-]: CALL R20 3 2 ; var20 = var20(var21, var22)
     104 [-]: LOADN R21 0  ; var21 = 0
     105 [-]: JUMPIFNOTLT R20 R21 L10; goto L10 if var20 >= var9835591
     106 [-]: LOADN R20 150; var20 = 150
     107 [-]: JUMPIFNOTLT R19 R20 L18; goto L18 if var19 >= var252319031
     108 [-]: GETTABLE R21 R10 R15; var21 = var10[var15]
     109 [-]: LOADN R23 1  ; var23 = 1
     110 [-]: GETIMPORT R24 20; var24 = 0x67652851
     111 [-]: CALL R24 1 2 ; var24 = var24()
     112 [-]: MUL R22 R23 R24; var22 = var23 * var24
     113 [-]: ADD R20 R21 R22; var20 = var21 + var22
     114 [-]: SETTABLE R20 R10 R15; var20[var10] = var15
     115 [-]: GETTABLE R20 R10 R15; var20 = var10[var15]
     116 [-]: JUMPIFNOTLT R20 R7 L18; goto L18 if var20 >= var83956559
     117 [-]: FASTCALL2K 19 R1 K21 L9; 
     118 [-]: MOVE R21 R1  ; var21 = var1
     119 [-]: LOADK R22 K21; var22 = 1
     120 [-]: GETIMPORT R20 24; var20 = 0x5BCED4C4[0xAC1B386A]
     121 [-]: CALL R20 3 2 ; var20 = var20(var21, var22)
L 9: 122 [-]: MOVE R1 R20  ; var1 = var20
     123 [-]: JUMP L18     ; goto L18
L10: 124 [-]: GETIMPORT R20 18; var20 = 0x4FD57545
     125 [-]: MOVE R21 R17 ; var21 = var17
     126 [-]: MOVE R22 R16 ; var22 = var16
     127 [-]: CALL R20 3 2 ; var20 = var20(var21, var22)
     128 [-]: LOADN R21 0  ; var21 = 0
     129 [-]: JUMPIFNOTLT R21 R20 L12; goto L12 if var21 >= var1184846
     130 [-]: GETIMPORT R20 18; var20 = 0x4FD57545
     131 [-]: MOVE R21 R16 ; var21 = var16
     132 [-]: MOVE R22 R18 ; var22 = var18
     133 [-]: CALL R20 3 2 ; var20 = var20(var21, var22)
     134 [-]: LOADN R21 0  ; var21 = 0
     135 [-]: JUMPIFNOTLT R21 R20 L12; goto L12 if var21 >= var6558791
     136 [-]: LOADN R20 100; var20 = 100
     137 [-]: JUMPIFNOTLT R19 R20 L18; goto L18 if var19 >= var252319031
     138 [-]: GETTABLE R21 R10 R15; var21 = var10[var15]
     139 [-]: LOADN R23 0  ; var23 = 0
     140 [-]: GETIMPORT R24 20; var24 = 0x67652851
     141 [-]: CALL R24 1 2 ; var24 = var24()
     142 [-]: MUL R22 R23 R24; var22 = var23 * var24
     143 [-]: ADD R20 R21 R22; var20 = var21 + var22
     144 [-]: SETTABLE R20 R10 R15; var20[var10] = var15
     145 [-]: GETTABLE R20 R10 R15; var20 = var10[var15]
     146 [-]: JUMPIFNOTLT R20 R7 L18; goto L18 if var20 >= var83956559
     147 [-]: FASTCALL2K 19 R1 K25 L11; 
     148 [-]: MOVE R21 R1  ; var21 = var1
     149 [-]: LOADK R22 K25; var22 = 2
     150 [-]: GETIMPORT R20 24; var20 = 0x5BCED4C4[0xAC1B386A]
     151 [-]: CALL R20 3 2 ; var20 = var20(var21, var22)
L11: 152 [-]: MOVE R1 R20  ; var1 = var20
     153 [-]: JUMP L18     ; goto L18
L12: 154 [-]: GETIMPORT R20 18; var20 = 0x4FD57545
     155 [-]: MOVE R21 R17 ; var21 = var17
     156 [-]: MOVE R22 R16 ; var22 = var16
     157 [-]: CALL R20 3 2 ; var20 = var20(var21, var22)
     158 [-]: LOADN R21 0  ; var21 = 0
     159 [-]: JUMPIFNOTLT R20 R21 L16; goto L16 if var20 >= var1184846
     160 [-]: GETIMPORT R20 18; var20 = 0x4FD57545
     161 [-]: MOVE R21 R16 ; var21 = var16
     162 [-]: MOVE R22 R18 ; var22 = var18
     163 [-]: CALL R20 3 2 ; var20 = var20(var21, var22)
     164 [-]: LOADN R21 0  ; var21 = 0
     165 [-]: JUMPIFNOTLT R21 R20 L16; goto L16 if var21 >= var9835591
     166 [-]: LOADN R20 150; var20 = 150
     167 [-]: JUMPIFNOTLT R19 R20 L14; goto L14 if var19 >= var1315911
     168 [-]: LOADN R20 20 ; var20 = 20
     169 [-]: JUMPIFNOTLT R20 R19 L14; goto L14 if var20 >= var252319031
     170 [-]: GETTABLE R21 R10 R15; var21 = var10[var15]
     171 [-]: LOADN R23 1  ; var23 = 1
     172 [-]: GETIMPORT R24 20; var24 = 0x67652851
     173 [-]: CALL R24 1 2 ; var24 = var24()
     174 [-]: MUL R22 R23 R24; var22 = var23 * var24
     175 [-]: ADD R20 R21 R22; var20 = var21 + var22
     176 [-]: SETTABLE R20 R10 R15; var20[var10] = var15
     177 [-]: GETTABLE R20 R10 R15; var20 = var10[var15]
     178 [-]: JUMPIFNOTLT R20 R7 L18; goto L18 if var20 >= var83956559
     179 [-]: FASTCALL2K 19 R1 K21 L13; 
     180 [-]: MOVE R21 R1  ; var21 = var1
     181 [-]: LOADK R22 K21; var22 = 1
     182 [-]: GETIMPORT R20 24; var20 = 0x5BCED4C4[0xAC1B386A]
     183 [-]: CALL R20 3 2 ; var20 = var20(var21, var22)
L13: 184 [-]: MOVE R1 R20  ; var1 = var20
     185 [-]: JUMP L18     ; goto L18
L14: 186 [-]: LOADN R20 20 ; var20 = 20
     187 [-]: JUMPIFNOTLT R19 R20 L18; goto L18 if var19 >= var252319031
     188 [-]: GETTABLE R21 R10 R15; var21 = var10[var15]
     189 [-]: LOADN R23 0  ; var23 = 0
     190 [-]: GETIMPORT R24 20; var24 = 0x67652851
     191 [-]: CALL R24 1 2 ; var24 = var24()
     192 [-]: MUL R22 R23 R24; var22 = var23 * var24
     193 [-]: ADD R20 R21 R22; var20 = var21 + var22
     194 [-]: SETTABLE R20 R10 R15; var20[var10] = var15
     195 [-]: GETTABLE R20 R10 R15; var20 = var10[var15]
     196 [-]: JUMPIFNOTLT R20 R7 L18; goto L18 if var20 >= var83956559
     197 [-]: FASTCALL2K 19 R1 K25 L15; 
     198 [-]: MOVE R21 R1  ; var21 = var1
     199 [-]: LOADK R22 K25; var22 = 2
     200 [-]: GETIMPORT R20 24; var20 = 0x5BCED4C4[0xAC1B386A]
     201 [-]: CALL R20 3 2 ; var20 = var20(var21, var22)
L15: 202 [-]: MOVE R1 R20  ; var1 = var20
     203 [-]: JUMP L18     ; goto L18
L16: 204 [-]: GETIMPORT R20 18; var20 = 0x4FD57545
     205 [-]: MOVE R21 R17 ; var21 = var17
     206 [-]: MOVE R22 R16 ; var22 = var16
     207 [-]: CALL R20 3 2 ; var20 = var20(var21, var22)
     208 [-]: LOADN R21 0  ; var21 = 0
     209 [-]: JUMPIFNOTLT R20 R21 L18; goto L18 if var20 >= var1184846
     210 [-]: GETIMPORT R20 18; var20 = 0x4FD57545
     211 [-]: MOVE R21 R16 ; var21 = var16
     212 [-]: MOVE R22 R18 ; var22 = var18
     213 [-]: CALL R20 3 2 ; var20 = var20(var21, var22)
     214 [-]: LOADN R21 0  ; var21 = 0
     215 [-]: JUMPIFNOTLT R20 R21 L18; goto L18 if var20 >= var6558791
     216 [-]: LOADN R20 100; var20 = 100
     217 [-]: JUMPIFNOTLT R19 R20 L18; goto L18 if var19 >= var252319031
     218 [-]: GETTABLE R21 R10 R15; var21 = var10[var15]
     219 [-]: LOADN R23 0  ; var23 = 0
     220 [-]: GETIMPORT R24 20; var24 = 0x67652851
     221 [-]: CALL R24 1 2 ; var24 = var24()
     222 [-]: MUL R22 R23 R24; var22 = var23 * var24
     223 [-]: ADD R20 R21 R22; var20 = var21 + var22
     224 [-]: SETTABLE R20 R10 R15; var20[var10] = var15
     225 [-]: GETTABLE R20 R10 R15; var20 = var10[var15]
     226 [-]: JUMPIFNOTLT R20 R7 L18; goto L18 if var20 >= var83956559
     227 [-]: FASTCALL2K 19 R1 K25 L17; 
     228 [-]: MOVE R21 R1  ; var21 = var1
     229 [-]: LOADK R22 K25; var22 = 2
     230 [-]: GETIMPORT R20 24; var20 = 0x5BCED4C4[0xAC1B386A]
     231 [-]: CALL R20 3 2 ; var20 = var20(var21, var22)
L17: 232 [-]: MOVE R1 R20  ; var1 = var20
L18: 233 [-]: FORNLOOP R13 L5; nforloop end - iterate + goto L5
L19: 234 [-]: JUMPIFEQ R1 R2 L22; goto L22 if var1 == var822086981
     235 [-]: NAMECALL R13 R0 K26; var14 = var0; var13 = var0[0x020D4331]
     236 [-]: CALL R13 2 2 ; var13 = var13(var14)
     237 [-]: NAMECALL R13 R13 K27; var14 = var13; var13 = var13[0x4AEA607E]
     238 [-]: CALL R13 2 2 ; var13 = var13(var14)
     239 [-]: LOADN R6 0   ; var6 = 0
     240 [-]: GETTABLE R14 R5 R1; var14 = var5[var1]
     241 [-]: JUMPIFNOTLT R14 R13 L20; goto L20 if var14 >= var795
     242 [-]: LOADB R3 0   ; var3 = false
     243 [-]: JUMP L21     ; goto L21
L20: 244 [-]: GETTABLE R14 R5 R1; var14 = var5[var1]
     245 [-]: JUMPIFNOTLT R13 R14 L21; goto L21 if var13 >= var66331
     246 [-]: LOADB R3 1   ; var3 = true
L21: 247 [-]: MOVE R8 R13  ; var8 = var13
     248 [-]: GETTABLE R9 R5 R1; var9 = var5[var1]
L22: 249 [-]: LOADN R13 1  ; var13 = 1
     250 [-]: JUMPIFNOT R3 L23; goto L23 if not var3
     251 [-]: GETIMPORT R14 29; var14 = 0x9BAFFFE3
     252 [-]: MOVE R15 R8  ; var15 = var8
     253 [-]: MOVE R16 R9  ; var16 = var9
     254 [-]: MOVE R17 R6  ; var17 = var6
     255 [-]: CALL R14 4 2 ; var14 = var14(var15, var16, var17)
     256 [-]: MOVE R13 R14 ; var13 = var14
     257 [-]: JUMPIFNOTLT R9 R13 L24; goto L24 if var9 >= var593174
     258 [-]: MOVE R13 R9  ; var13 = var9
     259 [-]: JUMP L24     ; goto L24
L23: 260 [-]: JUMPIF R3 L24; goto L24 if var3
     261 [-]: GETIMPORT R14 29; var14 = 0x9BAFFFE3
     262 [-]: MOVE R15 R8  ; var15 = var8
     263 [-]: MOVE R16 R9  ; var16 = var9
     264 [-]: MOVE R17 R6  ; var17 = var6
     265 [-]: CALL R14 4 2 ; var14 = var14(var15, var16, var17)
     266 [-]: MOVE R13 R14 ; var13 = var14
     267 [-]: JUMPIFNOTLT R13 R9 L24; goto L24 if var13 >= var593174
     268 [-]: MOVE R13 R9  ; var13 = var9
L24: 269 [-]: GETIMPORT R15 20; var15 = 0x67652851
     270 [-]: CALL R15 1 2 ; var15 = var15()
     271 [-]: GETTABLE R16 R4 R1; var16 = var4[var1]
     272 [-]: MUL R14 R15 R16; var14 = var15 * var16
     273 [-]: ADD R6 R6 R14; var6 = var6 + var14
     274 [-]: LOADN R14 1  ; var14 = 1
     275 [-]: JUMPIFNOTLT R14 R6 L25; goto L25 if var14 >= var67143
     276 [-]: LOADN R6 1   ; var6 = 1
L25: 277 [-]: NAMECALL R14 R0 K26; var15 = var0; var14 = var0[0x020D4331]
     278 [-]: CALL R14 2 2 ; var14 = var14(var15)
     279 [-]: MOVE R16 R13 ; var16 = var13
     280 [-]: NAMECALL R14 R14 K30; var15 = var14; var14 = var14[0x771F7C7A]
     281 [-]: CALL R14 3 1 ; var14(var15, var16)
     282 [-]: MOVE R2 R1   ; var2 = var1
     283 [-]: GETIMPORT R14 32; var14 = 0xCBD666E1
     284 [-]: LOADN R15 0  ; var15 = 0
     285 [-]: CALL R14 2 1 ; var14(var15)
     286 [-]: JUMPBACK L1  ; goto L1
L26: 287 [-]: RETURN R0 0  ; 


; Name:            
; Defined at line: 1917
; #Upvalues:       0
; #Parameters:     1
; Is_vararg:       0
; Max Stack Size:  10

       0 [-]: NAMECALL R1 R0 K0; var2 = var0; var1 = var0[0x2B54251B]
       1 [-]: CALL R1 2 2  ; var1 = var1(var2)
       2 [-]: LOADN R2 1   ; var2 = 1
L 0:   3 [-]: FASTCALL1 62 R1 L1; 
       4 [-]: MOVE R4 R1   ; var4 = var1
       5 [-]: GETIMPORT R3 2; var3 = 0x7B998233
       6 [-]: CALL R3 2 2  ; var3 = var3(var4)
L 1:   7 [-]: JUMPIFNOT R3 L2; goto L2 if not var3
       8 [-]: LOADN R3 0   ; var3 = 0
       9 [-]: JUMPIFNOTLT R3 R2 L2; goto L2 if var3 >= var262990
      10 [-]: GETIMPORT R3 4; var3 = 0x67652851
      11 [-]: CALL R3 1 2  ; var3 = var3()
      12 [-]: SUB R2 R2 R3 ; var2 = var2 - var3
      13 [-]: NAMECALL R3 R0 K0; var4 = var0; var3 = var0[0x2B54251B]
      14 [-]: CALL R3 2 2  ; var3 = var3(var4)
      15 [-]: MOVE R1 R3   ; var1 = var3
      16 [-]: GETIMPORT R3 6; var3 = 0xCBD666E1
      17 [-]: LOADN R4 0   ; var4 = 0
      18 [-]: CALL R3 2 1  ; var3(var4)
      19 [-]: JUMPBACK L0  ; goto L0
L 2:  20 [-]: FASTCALL1 62 R1 L3; 
      21 [-]: MOVE R4 R1   ; var4 = var1
      22 [-]: GETIMPORT R3 2; var3 = 0x7B998233
      23 [-]: CALL R3 2 2  ; var3 = var3(var4)
L 3:  24 [-]: JUMPIFNOT R3 L4; goto L4 if not var3
      25 [-]: RETURN R0 0  ; 
L 4:  26 [-]: NAMECALL R3 R1 K7; var4 = var1; var3 = var1[0xB40C191A]
      27 [-]: CALL R3 2 2  ; var3 = var3(var4)
      28 [-]: GETIMPORT R5 10; var5 = 0x89326C93
      29 [-]: NAMECALL R5 R5 K11; var6 = var5; var5 = var5[0x5D971903]
      30 [-]: CALL R5 2 2  ; var5 = var5(var6)
      31 [-]: SUBK R4 R5 K8; var4 = var5 - 1
      32 [-]: GETIMPORT R6 13; var6 = 0xEA602A5C
      33 [-]: MUL R5 R3 R6 ; var5 = var3 * var6
      34 [-]: MUL R6 R5 R4 ; var6 = var5 * var4
      35 [-]: ADD R3 R3 R6 ; var3 = var3 + var6
      36 [-]: NAMECALL R6 R1 K14; var7 = var1; var6 = var1[0x18D05D30]
      37 [-]: CALL R6 2 2  ; var6 = var6(var7)
      38 [-]: JUMPIFNOT R6 L5; goto L5 if not var6
      39 [-]: MOVE R8 R3   ; var8 = var3
      40 [-]: LOADB R9 1   ; var9 = true
      41 [-]: NAMECALL R6 R0 K15; var7 = var0; var6 = var0[0x014DB014]
      42 [-]: CALL R6 4 1  ; var6(var7, var8, var9)
L 5:  43 [-]: MOVE R8 R3   ; var8 = var3
      44 [-]: NAMECALL R6 R0 K16; var7 = var0; var6 = var0[0xE1FF9B2D]
      45 [-]: CALL R6 3 1  ; var6(var7, var8)
      46 [-]: RETURN R0 0  ; 


; Name:            
; Defined at line: 1943
; #Upvalues:       0
; #Parameters:     2
; Is_vararg:       0
; Max Stack Size:  16

       0 [-]: FASTCALL1 62 R1 L0; 
       1 [-]: MOVE R3 R1   ; var3 = var1
       2 [-]: GETIMPORT R2 1; var2 = 0x7B998233
       3 [-]: CALL R2 2 2  ; var2 = var2(var3)
L 0:   4 [-]: JUMPIF R2 L2 ; goto L2 if var2
       5 [-]: GETIMPORT R3 3; var3 = 0x8C55FAB0
       6 [-]: FASTCALL1 62 R3 L1; 
       7 [-]: GETIMPORT R2 1; var2 = 0x7B998233
       8 [-]: CALL R2 2 2  ; var2 = var2(var3)
L 1:   9 [-]: JUMPIFNOT R2 L3; goto L3 if not var2
L 2:  10 [-]: RETURN R0 0  ; 
L 3:  11 [-]: NAMECALL R2 R1 K4; var3 = var1; var2 = var1[0x18D05D30]
      12 [-]: CALL R2 2 2  ; var2 = var2(var3)
      13 [-]: JUMPIFNOT R2 L9; goto L9 if not var2
      14 [-]: GETIMPORT R3 6; var3 = 0x25D99D89
      15 [-]: FASTCALL1 62 R3 L4; 
      16 [-]: GETIMPORT R2 1; var2 = 0x7B998233
      17 [-]: CALL R2 2 2  ; var2 = var2(var3)
L 4:  18 [-]: JUMPIF R2 L8 ; goto L8 if var2
      19 [-]: GETIMPORT R2 9; var2 = 0x6C97A788[0xE1F94DEE]
      20 [-]: CALL R2 1 2  ; var2 = var2()
      21 [-]: GETIMPORT R3 3; var3 = 0x8C55FAB0
      22 [-]: SETTABLEKS R3 R2 K10; var3["mItemType"] = var2
      23 [-]: GETIMPORT R3 12; var3 = 0x6C97A788[0x2A2F3D6A]
      24 [-]: CALL R3 1 2  ; var3 = var3()
      25 [-]: SETTABLEKS R2 R3 K13; var2["mItem"] = var3
      26 [-]: LOADN R4 255 ; var4 = 255
      27 [-]: SETTABLEKS R4 R3 K14; var4["mModSlot"] = var3
      28 [-]: GETIMPORT R4 16; var4 = 0x6C97A788[0x17574A02]
      29 [-]: CALL R4 1 2  ; var4 = var4()
      30 [-]: LOADN R7 2   ; var7 = 2
      31 [-]: LOADN R8 2   ; var8 = 2
      32 [-]: MOVE R9 R3   ; var9 = var3
      33 [-]: NAMECALL R5 R4 K17; var6 = var4; var5 = var4[0x796650C7]
      34 [-]: CALL R5 5 1  ; var5(var6, var7, var8, var9)
      35 [-]: GETIMPORT R5 6; var5 = 0x25D99D89
      36 [-]: MOVE R7 R4   ; var7 = var4
      37 [-]: LOADN R8 2   ; var8 = 2
      38 [-]: LOADN R9 2   ; var9 = 2
      39 [-]: LOADN R10 28 ; var10 = 28
      40 [-]: NAMECALL R5 R5 K18; var6 = var5; var5 = var5[0x0F236D8B]
      41 [-]: CALL R5 6 1  ; var5(var6, var7, var8, var9, var10)
      42 [-]: LOADN R7 2   ; var7 = 2
      43 [-]: LOADN R8 2   ; var8 = 2
      44 [-]: NAMECALL R5 R4 K19; var6 = var4; var5 = var4[0xC1A84A4B]
      45 [-]: CALL R5 4 2  ; var5 = var5(var6, var7, var8)
      46 [-]: GETIMPORT R6 21; var6 = 0x89326C93
      47 [-]: GETIMPORT R8 23; var8 = 0x88EFC25E
      48 [-]: GETTABLEKS R10 R5 K13; var10 = var5["mItem"]
      49 [-]: GETTABLEKS R9 R10 K10; var9 = var10["mItemType"]
      50 [-]: CALL R8 2 2  ; var8 = var8(var9)
      51 [-]: MOVE R9 R1   ; var9 = var1
      52 [-]: NAMECALL R6 R6 K24; var7 = var6; var6 = var6[0x765DAD71]
      53 [-]: CALL R6 4 2  ; var6 = var6(var7, var8, var9)
      54 [-]: GETIMPORT R7 26; var7 = 0xC8802016
      55 [-]: GETTABLEKS R8 R5 K27; var8 = var5["mAttachedUpgrades"]
      56 [-]: CALL R7 2 4  ; var7, var8, var9 = var7(var8)
      57 [-]: FORGPREP_INEXT R7 L7; 
L 5:  58 [-]: GETTABLEKS R13 R11 K10; var13 = var11["mItemType"]
      59 [-]: FASTCALL1 62 R13 L6; 
      60 [-]: GETIMPORT R12 1; var12 = 0x7B998233
      61 [-]: CALL R12 2 2 ; var12 = var12(var13)
L 6:  62 [-]: JUMPIF R12 L7; goto L7 if var12
      63 [-]: GETIMPORT R12 21; var12 = 0x89326C93
      64 [-]: GETIMPORT R14 23; var14 = 0x88EFC25E
      65 [-]: GETTABLEKS R15 R11 K10; var15 = var11["mItemType"]
      66 [-]: CALL R14 2 2 ; var14 = var14(var15)
      67 [-]: MOVE R15 R6  ; var15 = var6
      68 [-]: NAMECALL R12 R12 K24; var13 = var12; var12 = var12[0x765DAD71]
      69 [-]: CALL R12 4 2 ; var12 = var12(var13, var14, var15)
      70 [-]: GETTABLEKS R15 R11 K28; var15 = var11["mUpgradeFingerprint"]
      71 [-]: NAMECALL R13 R12 K29; var14 = var12; var13 = var12[0x6868F7F8]
      72 [-]: CALL R13 3 1 ; var13(var14, var15)
      73 [-]: MOVE R15 R12 ; var15 = var12
      74 [-]: NAMECALL R13 R6 K30; var14 = var6; var13 = var6[0x5E6704FF]
      75 [-]: CALL R13 3 1 ; var13(var14, var15)
L 7:  76 [-]: FORGLOOP R7 L5 2 [inext]; 
      77 [-]: NAMECALL R7 R1 K31; var8 = var1; var7 = var1[0xDE321E6F]
      78 [-]: CALL R7 2 2  ; var7 = var7(var8)
      79 [-]: MOVE R9 R6   ; var9 = var6
      80 [-]: LOADB R10 1  ; var10 = true
      81 [-]: NAMECALL R7 R7 K32; var8 = var7; var7 = var7[0x511D26B8]
      82 [-]: CALL R7 4 1  ; var7(var8, var9, var10)
      83 [-]: NAMECALL R7 R1 K31; var8 = var1; var7 = var1[0xDE321E6F]
      84 [-]: CALL R7 2 2  ; var7 = var7(var8)
      85 [-]: LOADN R9 10  ; var9 = 10
      86 [-]: LOADN R10 0  ; var10 = 0
      87 [-]: LOADN R11 0  ; var11 = 0
      88 [-]: NAMECALL R7 R7 K33; var8 = var7; var7 = var7[0xC69087F6]
      89 [-]: CALL R7 5 1  ; var7(var8, var9, var10, var11)
      90 [-]: JUMP L9      ; goto L9
L 8:  91 [-]: GETIMPORT R4 3; var4 = 0x8C55FAB0
      92 [-]: LOADB R5 1   ; var5 = true
      93 [-]: NAMECALL R2 R1 K32; var3 = var1; var2 = var1[0x511D26B8]
      94 [-]: CALL R2 4 1  ; var2(var3, var4, var5)
      95 [-]: NAMECALL R2 R1 K31; var3 = var1; var2 = var1[0xDE321E6F]
      96 [-]: CALL R2 2 2  ; var2 = var2(var3)
      97 [-]: LOADN R4 10  ; var4 = 10
      98 [-]: LOADN R5 0   ; var5 = 0
      99 [-]: LOADN R6 0   ; var6 = 0
     100 [-]: NAMECALL R2 R2 K33; var3 = var2; var2 = var2[0xC69087F6]
     101 [-]: CALL R2 5 1  ; var2(var3, var4, var5, var6)
L 9: 102 [-]: NAMECALL R2 R0 K34; var3 = var0; var2 = var0[0x2B54251B]
     103 [-]: CALL R2 2 2  ; var2 = var2(var3)
     104 [-]: FASTCALL1 62 R2 L10; 
     105 [-]: MOVE R4 R2   ; var4 = var2
     106 [-]: GETIMPORT R3 1; var3 = 0x7B998233
     107 [-]: CALL R3 2 2  ; var3 = var3(var4)
L10: 108 [-]: JUMPIF R3 L11; goto L11 if var3
     109 [-]: NAMECALL R3 R2 K35; var4 = var2; var3 = var2[0xA2880940]
     110 [-]: CALL R3 2 1  ; var3(var4)
L11: 111 [-]: RETURN R0 0  ; 



