; Name:            
; Defined at line: 1
; #Upvalues:       0
; #Parameters:     0
; Is_vararg:       1
; Max Stack Size:  45

            1 [-]: NEWTABLE R0 0 3
       2 [-]: GETIMPORT R1 1 [nil]
       3 [-]: LOADK R2 K2 ["TENNO"]
       4 [-]: CALL R1 1 1  
       5 [-]: GETIMPORT R2 1 [nil]
       6 [-]: LOADK R3 K3 ["NEUTRAL"]
       7 [-]: CALL R2 1 1  
       8 [-]: GETIMPORT R3 1 [nil]
       9 [-]: LOADK R4 K4 ["Neutral"]
      10 [-]: CALL R3 1 -1 
      11 [-]: SETLIST R0 R1 -1 [1]
      12 [-]: LOADN R1 150 
      13 [-]: GETIMPORT R2 6 [nil]
      14 [-]: LOADK R3 K7 ["/Lotus/Types/Gameplay/Duviri/SideActivities/Encounters/Komi/KomiBoardGrid"]
      15 [-]: CALL R2 1 1  
      16 [-]: GETIMPORT R3 6 [nil]
      17 [-]: LOADK R4 K8 ["/Lotus/Types/Gameplay/Duviri/SideActivities/Encounters/Komi/CompleteActionWin"]
      18 [-]: CALL R3 1 1  
      19 [-]: GETIMPORT R4 6 [nil]
      20 [-]: LOADK R5 K9 ["/Lotus/Types/Gameplay/Duviri/SideActivities/Encounters/Komi/CompleteActionLoss"]
      21 [-]: CALL R4 1 1  
      22 [-]: GETIMPORT R5 6 [nil]
      23 [-]: LOADK R6 K10 ["/Lotus/Types/Friendly/PlayerControllable/ControllableDuviriDrifterTennoAvatar"]
      24 [-]: CALL R5 1 1  
      25 [-]: LOADNIL R6   
      26 [-]: LOADNIL R7   
      27 [-]: LOADNIL R8   
      28 [-]: LOADB R9 0   
      29 [-]: LOADB R10 0  
      30 [-]: LOADNIL R11  
      31 [-]: LOADNIL R12  
      32 [-]: LOADNIL R13  
      33 [-]: GETIMPORT R14 12 [nil]
      34 [-]: CALL R14 0 1 
      35 [-]: GETIMPORT R15 14 [nil]
      36 [-]: CALL R15 0 1 
      37 [-]: LOADB R16 0  
      38 [-]: LOADB R17 0  
      39 [-]: LOADB R18 0  
      40 [-]: LOADN R19 1  
      41 [-]: LOADN R20 0  
      42 [-]: LOADN R21 0  
      43 [-]: LOADNIL R22  
      44 [-]: LOADNIL R23  
      45 [-]: LOADNIL R24  
      46 [-]: GETIMPORT R25 16 [nil]
      47 [-]: LOADK R26 K17 ["Lotus.Scripts.Libs.TransmissionSet"]
      48 [-]: CALL R25 1 1 
      49 [-]: GETIMPORT R26 16 [nil]
      50 [-]: LOADK R27 K18 ["Lotus.Interface.LotusUtilities"]
      51 [-]: CALL R26 1 1 
      52 [-]: GETIMPORT R27 16 [nil]
      53 [-]: LOADK R28 K19 ["Lotus.Scripts.Minigames.GoLib"]
      54 [-]: CALL R27 1 1 
      55 [-]: NEWCLOSURE R28 P0
      56 [-]: MOVE R1 R10  
      57 [-]: DUPCLOSURE R29 K20 []
      58 [-]: NEWCLOSURE R30 P2
      59 [-]: MOVE R1 R17  
      60 [-]: DUPCLOSURE R31 K21 []
      61 [-]: NEWCLOSURE R32 P4
      62 [-]: MOVE R1 R17  
      63 [-]: DUPCLOSURE R33 K22 []
      64 [-]: NEWCLOSURE R34 P6
      65 [-]: MOVE R1 R17  
      66 [-]: NEWCLOSURE R35 P7
      67 [-]: MOVE R1 R9   
      68 [-]: MOVE R1 R8   
      69 [-]: DUPCLOSURE R36 K23 []
      70 [-]: MOVE R0 R35  
      71 [-]: MOVE R0 R28  
      72 [-]: MOVE R0 R29  
      73 [-]: MOVE R0 R30  
      74 [-]: MOVE R0 R31  
      75 [-]: MOVE R0 R33  
      76 [-]: MOVE R0 R32  
      77 [-]: NEWCLOSURE R37 P9
      78 [-]: MOVE R1 R21  
      79 [-]: MOVE R1 R20  
      80 [-]: DUPCLOSURE R38 K24 []
      81 [-]: MOVE R0 R35  
      82 [-]: MOVE R0 R29  
      83 [-]: MOVE R0 R30  
      84 [-]: MOVE R0 R31  
      85 [-]: MOVE R0 R33  
      86 [-]: MOVE R0 R32  
      87 [-]: MOVE R0 R37  
      88 [-]: NEWCLOSURE R39 P11
      89 [-]: MOVE R1 R6   
      90 [-]: MOVE R1 R12  
      91 [-]: MOVE R1 R9   
      92 [-]: MOVE R1 R16  
      93 [-]: MOVE R0 R35  
      94 [-]: MOVE R0 R2   
      95 [-]: MOVE R0 R14  
      96 [-]: MOVE R1 R13  
      97 [-]: MOVE R0 R15  
      98 [-]: MOVE R1 R8   
      99 [-]: MOVE R1 R10  
     100 [-]: MOVE R0 R29  
     101 [-]: MOVE R0 R30  
     102 [-]: MOVE R0 R31  
     103 [-]: MOVE R0 R33  
     104 [-]: MOVE R0 R32  
     105 [-]: MOVE R0 R37  
     106 [-]: NEWCLOSURE R40 P12
     107 [-]: MOVE R1 R17  
     108 [-]: NEWCLOSURE R41 P13
     109 [-]: MOVE R1 R19  
     110 [-]: MOVE R1 R22  
     111 [-]: MOVE R1 R23  
     112 [-]: MOVE R1 R24  
     113 [-]: MOVE R0 R2   
     114 [-]: MOVE R1 R8   
     115 [-]: MOVE R0 R27  
     116 [-]: MOVE R1 R9   
     117 [-]: MOVE R1 R7   
     118 [-]: MOVE R1 R11  
     119 [-]: MOVE R0 R37  
     120 [-]: MOVE R0 R35  
     121 [-]: MOVE R0 R28  
     122 [-]: MOVE R0 R30  
     123 [-]: MOVE R0 R31  
     124 [-]: MOVE R0 R33  
     125 [-]: MOVE R0 R32  
     126 [-]: MOVE R0 R25  
     127 [-]: MOVE R1 R17  
     128 [-]: MOVE R0 R39  
     129 [-]: MOVE R1 R18  
     130 [-]: MOVE R1 R12  
     131 [-]: NEWCLOSURE R42 P14
     132 [-]: MOVE R1 R6   
     133 [-]: MOVE R0 R26  
     134 [-]: MOVE R1 R7   
     135 [-]: DUPCLOSURE R43 K25 []
     136 [-]: MOVE R0 R26  
     137 [-]: SETGLOBAL R43 K26 ["CanPlayKomi"]
     138 [-]: DUPCLOSURE R43 K27 []
     139 [-]: SETGLOBAL R43 K28 ["KomiKeepActive"]
     140 [-]: DUPCLOSURE R43 K29 []
     141 [-]: MOVE R0 R0   
     142 [-]: NEWCLOSURE R44 P18
     143 [-]: MOVE R1 R1   
     144 [-]: MOVE R0 R43  
     145 [-]: MOVE R1 R6   
     146 [-]: MOVE R1 R7   
     147 [-]: MOVE R0 R42  
     148 [-]: MOVE R1 R13  
     149 [-]: MOVE R1 R12  
     150 [-]: MOVE R1 R17  
     151 [-]: MOVE R1 R18  
     152 [-]: MOVE R0 R41  
     153 [-]: MOVE R0 R34  
     154 [-]: MOVE R1 R19  
     155 [-]: MOVE R0 R3   
     156 [-]: MOVE R0 R4   
     157 [-]: MOVE R0 R35  
     158 [-]: MOVE R0 R29  
     159 [-]: MOVE R0 R30  
     160 [-]: MOVE R0 R31  
     161 [-]: MOVE R0 R33  
     162 [-]: MOVE R0 R32  
     163 [-]: SETGLOBAL R44 K30 ["PlayKomiMonitor"]
     164 [-]: DUPCLOSURE R44 K31 []
     165 [-]: MOVE R0 R5   
     166 [-]: SETGLOBAL R44 K32 ["StartNPCGame"]
     167 [-]: CLOSEUPVALS R1
     168 [-]: RETURN R0 0  


; Name:            
; Defined at line: 79
; #Upvalues:       1
; #Parameters:     0
; Is_vararg:       0
; Max Stack Size:  1

       0 [-]: LOADB R0 1   
       1 [-]: SETUPVAL R0 0
       2 [-]: RETURN R0 0  


; Name:            
; Defined at line: 83
; #Upvalues:       0
; #Parameters:     0
; Is_vararg:       0
; Max Stack Size:  0

       0 [-]: RETURN R0 0  


; Name:            
; Defined at line: 86
; #Upvalues:       1
; #Parameters:     0
; Is_vararg:       0
; Max Stack Size:  1

       0 [-]: LOADB R0 1   
       1 [-]: SETUPVAL R0 0
       2 [-]: RETURN R0 0  


; Name:            
; Defined at line: 91
; #Upvalues:       0
; #Parameters:     0
; Is_vararg:       0
; Max Stack Size:  0

       0 [-]: RETURN R0 0  


; Name:            
; Defined at line: 98
; #Upvalues:       1
; #Parameters:     0
; Is_vararg:       0
; Max Stack Size:  1

       0 [-]: LOADB R0 1   
       1 [-]: SETUPVAL R0 0
       2 [-]: RETURN R0 0  


; Name:            
; Defined at line: 103
; #Upvalues:       0
; #Parameters:     1
; Is_vararg:       0
; Max Stack Size:  1

       0 [-]: RETURN R0 0  


; Name:            
; Defined at line: 126
; #Upvalues:       1
; #Parameters:     1
; Is_vararg:       0
; Max Stack Size:  4

       0 [-]: GETIMPORT R1 1 [nil]
       1 [-]: NAMECALL R1 R1 K2 [0x78298275]
       2 [-]: CALL R1 1 1  
       3 [-]: FASTCALL1 62 R1 L0
       4 [-]: MOVE R3 R1   
       5 [-]: GETIMPORT R2 4 [nil]
       6 [-]: CALL R2 1 1  
L 0:   7 [-]: JUMPIF R2 L1 
       8 [-]: NAMECALL R2 R1 K5 [0x2047CFE7]
       9 [-]: CALL R2 1 1  
      10 [-]: JUMPIF R2 L1 
      11 [-]: NAMECALL R2 R1 K6 [0x73901ACF]
      12 [-]: CALL R2 1 1  
      13 [-]: JUMPIFNOT R2 L2
L 1:  14 [-]: LOADB R2 0   
      15 [-]: RETURN R2 1  
L 2:  16 [-]: GETUPVAL R3 0
      17 [-]: NOT R2 R3    
      18 [-]: RETURN R2 1  


; Name:            
; Defined at line: 136
; #Upvalues:       2
; #Parameters:     0
; Is_vararg:       0
; Max Stack Size:  13

       0 [-]: LOADNIL R0   
       1 [-]: GETIMPORT R1 1 [nil]
       2 [-]: GETIMPORT R3 3 [nil]
       3 [-]: NAMECALL R1 R1 K4 [0xF2DEAF69]
       4 [-]: CALL R1 2 1  
       5 [-]: JUMPIFNOT R1 L0
       6 [-]: GETIMPORT R2 6 [nil]
       7 [-]: GETIMPORT R4 8 [nil]
       8 [-]: NAMECALL R2 R2 K9 [0xBCFB64AB]
       9 [-]: CALL R2 2 1  
      10 [-]: MOVE R0 R2   
      11 [-]: JUMP L1
     
L 0:  12 [-]: GETIMPORT R2 1 [nil]
      13 [-]: NAMECALL R2 R2 K10 [0x33307F92]
      14 [-]: CALL R2 1 1  
      15 [-]: MOVE R0 R2   
L 1:  16 [-]: FASTCALL1 62 R0 L2
      17 [-]: MOVE R3 R0   
      18 [-]: GETIMPORT R2 12 [nil]
      19 [-]: CALL R2 1 1  
L 2:  20 [-]: JUMPIF R2 L7 
      21 [-]: GETIMPORT R2 15 [nil]
      22 [-]: JUMPIFNOT R2 L5
      23 [-]: GETUPVAL R2 0
      24 [-]: JUMPIFNOT R2 L5
      25 [-]: GETUPVAL R2 1
      26 [-]: JUMPIFNOT R2 L5
      27 [-]: GETUPVAL R2 1
      28 [-]: GETUPVAL R4 1
      29 [-]: NAMECALL R4 R4 K16 [0x5E651723]
      30 [-]: CALL R4 1 -1 
      31 [-]: NAMECALL R2 R2 K17 [0x6479E675]
      32 [-]: CALL R2 -1 1 
      33 [-]: JUMPIF R2 L5 
      34 [-]: JUMPIF R1 L7 
      35 [-]: LOADK R4 K18 ["PvPHeldFlagTimer"]
      36 [-]: LOADN R5 29  
      37 [-]: LOADK R8 K19 ["/Lotus/Language/Sacrifice/GoGameHint"]
      38 [-]: LOADB R9 1   
      39 [-]: DUPTABLE R10 21
      40 [-]: GETIMPORT R12 24 [nil]
      41 [-]: CALL R12 0 1 
      42 [-]: JUMPIFNOT R12 L3
      43 [-]: LOADK R11 K25 ["<MENU_SELECT>"]
      44 [-]: JUMP L4
     
L 3:  45 [-]: LOADK R11 K26 ["<MENU_CLICK>"]
L 4:  46 [-]: SETTABLEKS R11 R10 K20 ["CALLOUT"]
      47 [-]: NAMECALL R6 R0 K27 [0x42B04007]
      48 [-]: CALL R6 4 -1 
      49 [-]: NAMECALL R2 R0 K28 [0x5F56EEAB]
      50 [-]: CALL R2 -1 0 
      51 [-]: LOADK R4 K18 ["PvPHeldFlagTimer"]
      52 [-]: LOADN R5 10  
      53 [-]: LOADN R6 100 
      54 [-]: NAMECALL R2 R0 K29 [0x67BC869F]
      55 [-]: CALL R2 4 0  
      56 [-]: RETURN R0 0  
L 5:  57 [-]: JUMPIFNOT R1 L6
      58 [-]: LOADK R4 K30 ["SetHintText"]
      59 [-]: LOADK R5 K31 [""]
      60 [-]: NAMECALL R2 R0 K32 [0xE4162EED]
      61 [-]: CALL R2 3 0  
      62 [-]: RETURN R0 0  
L 6:  63 [-]: LOADK R4 K18 ["PvPHeldFlagTimer"]
      64 [-]: LOADN R5 29  
      65 [-]: LOADK R6 K31 [""]
      66 [-]: NAMECALL R2 R0 K28 [0x5F56EEAB]
      67 [-]: CALL R2 4 0  
      68 [-]: LOADK R4 K18 ["PvPHeldFlagTimer"]
      69 [-]: LOADN R5 10  
      70 [-]: LOADN R6 0   
      71 [-]: NAMECALL R2 R0 K29 [0x67BC869F]
      72 [-]: CALL R2 4 0  
L 7:  73 [-]: RETURN R0 0  


; Name:            
; Defined at line: 170
; #Upvalues:       7
; #Parameters:     1
; Is_vararg:       0
; Max Stack Size:  3

       0 [-]: GETIMPORT R1 1 [nil]
       1 [-]: SETTABLEKS R0 R1 K2 ["HudReplacement_ForceVisibility"]
       2 [-]: GETUPVAL R1 0
       3 [-]: CALL R1 0 0  
       4 [-]: JUMPIFNOT R0 L0
       5 [-]: GETIMPORT R1 1 [nil]
       6 [-]: GETUPVAL R2 1
       7 [-]: SETTABLEKS R2 R1 K3 ["BoardgameClickCallback"]
       8 [-]: JUMP L1
     
L 0:   9 [-]: GETIMPORT R1 1 [nil]
      10 [-]: GETUPVAL R2 2
      11 [-]: SETTABLEKS R2 R1 K3 ["BoardgameClickCallback"]
L 1:  12 [-]: GETIMPORT R1 1 [nil]
      13 [-]: GETUPVAL R2 3
      14 [-]: SETTABLEKS R2 R1 K4 ["BoardGamePauseCallback"]
      15 [-]: GETIMPORT R1 1 [nil]
      16 [-]: GETUPVAL R2 4
      17 [-]: SETTABLEKS R2 R1 K5 ["BoardGameRightClickCallback"]
      18 [-]: GETIMPORT R1 1 [nil]
      19 [-]: GETUPVAL R2 5
      20 [-]: SETTABLEKS R2 R1 K6 ["BoardGameActivateAbilityCallback"]
      21 [-]: GETIMPORT R1 1 [nil]
      22 [-]: GETUPVAL R2 6
      23 [-]: SETTABLEKS R2 R1 K7 ["BoardGameConcede"]
      24 [-]: RETURN R0 0  


; Name:            
; Defined at line: 188
; #Upvalues:       2
; #Parameters:     0
; Is_vararg:       0
; Max Stack Size:  6

       0 [-]: GETUPVAL R0 0
       1 [-]: LOADN R1 0   
       2 [-]: JUMPIFNOTLT R1 R0 L2
       3 [-]: GETUPVAL R0 1
       4 [-]: LOADN R1 0   
       5 [-]: JUMPIFNOTLT R1 R0 L1
       6 [-]: GETIMPORT R0 1 [nil]
       7 [-]: GETUPVAL R1 1
       8 [-]: LOADN R2 1   
       9 [-]: LOADN R3 7   
      10 [-]: CALL R0 3 1  
      11 [-]: SETUPVAL R0 1
      12 [-]: GETIMPORT R1 4 [nil]
      13 [-]: FASTCALL1 62 R1 L0
      14 [-]: GETIMPORT R0 6 [nil]
      15 [-]: CALL R0 1 1  
L 0:  16 [-]: JUMPIF R0 L1 
      17 [-]: GETIMPORT R0 8 [nil]
      18 [-]: LOADK R1 K9 ["/Lotus/Language/Sacrifice/GoGameHintTitle"]
      19 [-]: LOADK R3 K10 ["/Lotus/Language/Duviri/DuviriKomiTip"]
      20 [-]: GETUPVAL R4 1
      21 [-]: CONCAT R2 R3 R4
      22 [-]: NEWTABLE R3 0 0
      23 [-]: CALL R0 3 0  
L 1:  24 [-]: GETUPVAL R1 0
      25 [-]: SUBK R0 R1 K11 [1]
      26 [-]: SETUPVAL R0 0
      27 [-]: RETURN R0 0  
L 2:  28 [-]: LOADN R0 10  
      29 [-]: SETUPVAL R0 0
      30 [-]: GETUPVAL R0 1
L 3:  31 [-]: GETUPVAL R1 1
      32 [-]: JUMPIFNOTEQ R0 R1 L4
      33 [-]: GETIMPORT R1 13 [nil]
      34 [-]: LOADN R2 1   
      35 [-]: LOADN R3 7   
      36 [-]: CALL R1 2 1  
      37 [-]: SETUPVAL R1 1
      38 [-]: JUMPBACK L3  
L 4:  39 [-]: GETIMPORT R2 4 [nil]
      40 [-]: FASTCALL1 62 R2 L5
      41 [-]: GETIMPORT R1 6 [nil]
      42 [-]: CALL R1 1 1  
L 5:  43 [-]: JUMPIF R1 L6 
      44 [-]: GETIMPORT R1 8 [nil]
      45 [-]: LOADK R2 K9 ["/Lotus/Language/Sacrifice/GoGameHintTitle"]
      46 [-]: LOADK R4 K10 ["/Lotus/Language/Duviri/DuviriKomiTip"]
      47 [-]: GETUPVAL R5 1
      48 [-]: CONCAT R3 R4 R5
      49 [-]: NEWTABLE R4 0 0
      50 [-]: CALL R1 3 0  
L 6:  51 [-]: RETURN R0 0  


; Name:            
; Defined at line: 209
; #Upvalues:       7
; #Parameters:     1
; Is_vararg:       0
; Max Stack Size:  4

       0 [-]: GETIMPORT R3 1 [nil]
       1 [-]: NAMECALL R1 R0 K2 [0xF2DEAF69]
       2 [-]: CALL R1 2 1  
       3 [-]: JUMPIFNOT R1 L0
       4 [-]: NAMECALL R1 R0 K3 [0x35844CF2]
       5 [-]: CALL R1 1 1  
       6 [-]: JUMPIFNOT R1 L0
       7 [-]: NAMECALL R1 R0 K4 [0x5E651723]
       8 [-]: CALL R1 1 1  
       9 [-]: NAMECALL R1 R1 K5 [0xB5983272]
      10 [-]: CALL R1 1 0  
L 0:  11 [-]: GETIMPORT R1 7 [nil]
      12 [-]: LOADB R2 0   
      13 [-]: SETTABLEKS R2 R1 K8 ["HudReplacement_ForceVisibility"]
      14 [-]: GETUPVAL R1 0
      15 [-]: CALL R1 0 0  
      16 [-]: GETIMPORT R1 7 [nil]
      17 [-]: GETUPVAL R2 1
      18 [-]: SETTABLEKS R2 R1 K9 ["BoardgameClickCallback"]
      19 [-]: GETIMPORT R1 7 [nil]
      20 [-]: GETUPVAL R2 2
      21 [-]: SETTABLEKS R2 R1 K10 ["BoardGamePauseCallback"]
      22 [-]: GETIMPORT R1 7 [nil]
      23 [-]: GETUPVAL R2 3
      24 [-]: SETTABLEKS R2 R1 K11 ["BoardGameRightClickCallback"]
      25 [-]: GETIMPORT R1 7 [nil]
      26 [-]: GETUPVAL R2 4
      27 [-]: SETTABLEKS R2 R1 K12 ["BoardGameActivateAbilityCallback"]
      28 [-]: GETIMPORT R1 7 [nil]
      29 [-]: GETUPVAL R2 5
      30 [-]: SETTABLEKS R2 R1 K13 ["BoardGameConcede"]
      31 [-]: GETUPVAL R1 6
      32 [-]: CALL R1 0 0  
      33 [-]: RETURN R0 0  


; Name:            
; Defined at line: 217
; #Upvalues:       17
; #Parameters:     2
; Is_vararg:       0
; Max Stack Size:  13

       0 [-]: GETUPVAL R3 0
       1 [-]: FASTCALL1 62 R3 L0
       2 [-]: GETIMPORT R2 1 [nil]
       3 [-]: CALL R2 1 1  
L 0:   4 [-]: JUMPIF R2 L2 
       5 [-]: GETUPVAL R3 1
       6 [-]: FASTCALL1 62 R3 L1
       7 [-]: GETIMPORT R2 1 [nil]
       8 [-]: CALL R2 1 1  
L 1:   9 [-]: JUMPIFNOT R2 L3
L 2:  10 [-]: RETURN R0 0  
L 3:  11 [-]: GETIMPORT R2 4 [nil]
      12 [-]: CALL R2 0 1  
      13 [-]: GETUPVAL R3 2
      14 [-]: JUMPIFNOT R3 L4
      15 [-]: GETUPVAL R3 3
      16 [-]: JUMPIFEQ R3 R2 L4
      17 [-]: SETUPVAL R2 3
      18 [-]: GETUPVAL R3 4
      19 [-]: CALL R3 0 0  
L 4:  20 [-]: NEWTABLE R3 0 2
      21 [-]: GETIMPORT R4 6 [nil]
      22 [-]: GETIMPORT R5 8 [nil]
      23 [-]: GETUPVAL R6 5
      24 [-]: CALL R5 1 -1 
      25 [-]: SETLIST R3 R4 -1 [1]
      26 [-]: GETUPVAL R4 6
      27 [-]: LOADNIL R6   
      28 [-]: NAMECALL R4 R4 K9 [0xC63157A6]
      29 [-]: CALL R4 2 0  
      30 [-]: GETIMPORT R4 11 [nil]
      31 [-]: GETUPVAL R6 7
      32 [-]: GETUPVAL R7 1
      33 [-]: NAMECALL R7 R7 K12 [0x33BFB108]
      34 [-]: CALL R7 1 1  
      35 [-]: MOVE R8 R3   
      36 [-]: GETUPVAL R9 6
      37 [-]: GETUPVAL R10 8
      38 [-]: NAMECALL R4 R4 K13 [0x722CD32C]
      39 [-]: CALL R4 6 1  
      40 [-]: JUMPIFNOT R4 L8
      41 [-]: GETUPVAL R4 6
      42 [-]: NAMECALL R4 R4 K14 [0xEF3A99CA]
      43 [-]: CALL R4 1 1  
      44 [-]: GETUPVAL R5 9
      45 [-]: JUMPIFNOT R5 L8
      46 [-]: GETUPVAL R6 9
      47 [-]: GETUPVAL R8 9
      48 [-]: NAMECALL R8 R8 K15 [0x5E651723]
      49 [-]: CALL R8 1 -1 
      50 [-]: NAMECALL R6 R6 K16 [0x6479E675]
      51 [-]: CALL R6 -1 1 
      52 [-]: NOT R5 R6    
      53 [-]: JUMPIFNOT R5 L6
      54 [-]: GETUPVAL R6 2
      55 [-]: JUMPIFNOT R6 L5
      56 [-]: GETUPVAL R6 9
      57 [-]: MOVE R8 R4   
      58 [-]: NAMECALL R6 R6 K17 [0x1A4D17C8]
      59 [-]: CALL R6 2 0  
      60 [-]: JUMP L6
     
L 5:  61 [-]: GETUPVAL R6 9
      62 [-]: LOADNIL R8   
      63 [-]: NAMECALL R6 R6 K17 [0x1A4D17C8]
      64 [-]: CALL R6 2 0  
L 6:  65 [-]: GETUPVAL R6 10
      66 [-]: JUMPIFNOT R6 L8
      67 [-]: LOADB R6 0   
      68 [-]: SETUPVAL R6 10
      69 [-]: GETUPVAL R6 9
      70 [-]: NAMECALL R6 R6 K18 [0xB763AD66]
      71 [-]: CALL R6 1 2  
      72 [-]: JUMPIFNOT R5 L8
      73 [-]: JUMPIFNOT R6 L8
      74 [-]: JUMPIFNOT R7 L8
      75 [-]: GETUPVAL R8 9
      76 [-]: MOVE R10 R6  
      77 [-]: MOVE R11 R7  
      78 [-]: LOADB R12 1  
      79 [-]: NAMECALL R8 R8 K19 [0x8AD9D7EE]
      80 [-]: CALL R8 4 1  
      81 [-]: JUMPIFNOT R8 L8
      82 [-]: GETIMPORT R10 6 [nil]
      83 [-]: NAMECALL R8 R1 K20 [0xF2DEAF69]
      84 [-]: CALL R8 2 1  
      85 [-]: JUMPIFNOT R8 L7
      86 [-]: NAMECALL R8 R1 K21 [0x35844CF2]
      87 [-]: CALL R8 1 1  
      88 [-]: JUMPIFNOT R8 L7
      89 [-]: NAMECALL R8 R1 K15 [0x5E651723]
      90 [-]: CALL R8 1 1  
      91 [-]: NAMECALL R8 R8 K22 [0xB5983272]
      92 [-]: CALL R8 1 0  
L 7:  93 [-]: GETIMPORT R8 24 [nil]
      94 [-]: LOADB R9 0   
      95 [-]: SETTABLEKS R9 R8 K25 ["HudReplacement_ForceVisibility"]
      96 [-]: GETUPVAL R8 4
      97 [-]: CALL R8 0 0  
      98 [-]: GETIMPORT R8 24 [nil]
      99 [-]: GETUPVAL R9 11
     100 [-]: SETTABLEKS R9 R8 K26 ["BoardgameClickCallback"]
     101 [-]: GETIMPORT R8 24 [nil]
     102 [-]: GETUPVAL R9 12
     103 [-]: SETTABLEKS R9 R8 K27 ["BoardGamePauseCallback"]
     104 [-]: GETIMPORT R8 24 [nil]
     105 [-]: GETUPVAL R9 13
     106 [-]: SETTABLEKS R9 R8 K28 ["BoardGameRightClickCallback"]
     107 [-]: GETIMPORT R8 24 [nil]
     108 [-]: GETUPVAL R9 14
     109 [-]: SETTABLEKS R9 R8 K29 ["BoardGameActivateAbilityCallback"]
     110 [-]: GETIMPORT R8 24 [nil]
     111 [-]: GETUPVAL R9 15
     112 [-]: SETTABLEKS R9 R8 K30 ["BoardGameConcede"]
     113 [-]: GETUPVAL R8 16
     114 [-]: CALL R8 0 0  
L 8: 115 [-]: RETURN R0 0  


; Name:            
; Defined at line: 255
; #Upvalues:       1
; #Parameters:     1
; Is_vararg:       0
; Max Stack Size:  4

       0 [-]: MOVE R1 R0   
L 0:   1 [-]: LOADN R2 0   
       2 [-]: JUMPIFNOTLT R2 R1 L1
       3 [-]: GETUPVAL R2 0
       4 [-]: JUMPIF R2 L1 
       5 [-]: GETIMPORT R2 1 [nil]
       6 [-]: LOADK R3 K2 [0.10000000000000001]
       7 [-]: CALL R2 1 0  
       8 [-]: SUBK R1 R1 K2 [0.10000000000000001]
       9 [-]: JUMPBACK L0  
L 1:  10 [-]: RETURN R0 0  


; Name:            
; Defined at line: 263
; #Upvalues:       22
; #Parameters:     5
; Is_vararg:       0
; Max Stack Size:  28

       0 [-]: LOADN R5 1   
       1 [-]: LOADN R6 0   
       2 [-]: LOADN R7 0   
       3 [-]: LOADNIL R8   
       4 [-]: GETIMPORT R10 2 [nil]
       5 [-]: FASTCALL1 62 R10 L0
       6 [-]: GETIMPORT R9 4 [nil]
       7 [-]: CALL R9 1 1  
L 0:   8 [-]: JUMPIF R9 L1 
       9 [-]: GETIMPORT R9 2 [nil]
      10 [-]: SETUPVAL R9 0
L 1:  11 [-]: GETGLOBAL R10 K5 [0xAA6C2B3F]
      12 [-]: GETUPVAL R11 0
      13 [-]: GETTABLE R9 R10 R11
      14 [-]: GETTABLEKS R10 R9 K6 ["x"]
      15 [-]: GETTABLEKS R11 R9 K7 ["y"]
      16 [-]: GETTABLEKS R12 R9 K8 ["z"]
      17 [-]: GETUPVAL R14 1
      18 [-]: FASTCALL1 62 R14 L2
      19 [-]: GETIMPORT R13 4 [nil]
      20 [-]: CALL R13 1 1 
L 2:  21 [-]: JUMPIFNOT R13 L3
      22 [-]: SETUPVAL R11 1
      23 [-]: JUMP L4
     
L 3:  24 [-]: GETUPVAL R11 1
L 4:  25 [-]: GETUPVAL R14 2
      26 [-]: FASTCALL1 62 R14 L5
      27 [-]: GETIMPORT R13 4 [nil]
      28 [-]: CALL R13 1 1 
L 5:  29 [-]: JUMPIFNOT R13 L6
      30 [-]: SETUPVAL R10 2
      31 [-]: JUMP L7
     
L 6:  32 [-]: GETUPVAL R10 2
L 7:  33 [-]: GETUPVAL R14 3
      34 [-]: FASTCALL1 62 R14 L8
      35 [-]: GETIMPORT R13 4 [nil]
      36 [-]: CALL R13 1 1 
L 8:  37 [-]: JUMPIFNOT R13 L9
      38 [-]: SETUPVAL R12 3
      39 [-]: JUMP L10
    
L 9:  40 [-]: GETUPVAL R12 3
L10:  41 [-]: LOADB R14 1  
      42 [-]: JUMPXEQKN R10 K9 L12 [5]
      43 [-]: LOADB R14 1  
      44 [-]: JUMPXEQKN R10 K10 L12 [7]
      45 [-]: JUMPXEQKN R10 K11 L11 [9]
      46 [-]: LOADB R14 0 +1
L11:  47 [-]: LOADB R14 1  
L12:  48 [-]: FASTCALL1 1 R14 L13
      49 [-]: GETIMPORT R13 13 [nil]
      50 [-]: CALL R13 1 0 
L13:  51 [-]: SUBK R15 R10 K9 [5]
      52 [-]: DIVK R14 R15 K15 [2]
      53 [-]: ADDK R13 R14 K14 [1]
      54 [-]: NAMECALL R14 R2 K16 [0x2B54251B]
      55 [-]: CALL R14 1 1 
      56 [-]: GETUPVAL R16 4
      57 [-]: NAMECALL R14 R14 K17 [0xC9F6A7D7]
      58 [-]: CALL R14 2 1 
      59 [-]: GETIMPORT R16 19 [nil]
      60 [-]: GETTABLE R15 R16 R13
      61 [-]: LOADN R18 0  
      62 [-]: MOVE R19 R15 
      63 [-]: LOADB R20 0  
      64 [-]: NAMECALL R16 R14 K20 [0xCDDC3ABB]
      65 [-]: CALL R16 4 0 
      66 [-]: DUPTABLE R16 25
      67 [-]: GETIMPORT R17 27 [nil]
      68 [-]: SETTABLEKS R17 R16 K21 ["stoneDecoType"]
      69 [-]: GETIMPORT R17 29 [nil]
      70 [-]: SETTABLEKS R17 R16 K22 ["hoverStoneDecoType"]
      71 [-]: GETIMPORT R17 31 [nil]
      72 [-]: SETTABLEKS R17 R16 K23 ["stoneMeshBlack"]
      73 [-]: GETIMPORT R17 33 [nil]
      74 [-]: SETTABLEKS R17 R16 K24 ["stoneMeshWhite"]
      75 [-]: GETUPVAL R18 6
      76 [-]: GETTABLEKS R17 R18 K34 [0x24EC2828]
      77 [-]: NAMECALL R18 R2 K35 [0xF6EBD926]
      78 [-]: CALL R18 1 1 
      79 [-]: NAMECALL R19 R2 K36 [0x5280B883]
      80 [-]: CALL R19 1 1 
      81 [-]: GETIMPORT R20 38 [nil]
      82 [-]: MOVE R21 R10 
      83 [-]: LOADN R22 5  
      84 [-]: LOADN R23 9  
      85 [-]: CALL R20 3 1 
      86 [-]: LOADK R21 K39 [0.42999999999999999]
      87 [-]: MOVE R22 R2  
      88 [-]: MOVE R23 R16 
      89 [-]: CALL R17 6 1 
      90 [-]: SETUPVAL R17 5
      91 [-]: GETUPVAL R17 5
      92 [-]: LOADK R19 K40 ["local"]
      93 [-]: DUPTABLE R20 43
      94 [-]: LOADB R21 1  
      95 [-]: SETTABLEKS R21 R20 K41 ["ai"]
      96 [-]: LOADN R22 2  
      97 [-]: GETIMPORT R23 38 [nil]
      98 [-]: MOVE R24 R11 
      99 [-]: LOADN R25 1  
     100 [-]: LOADN R26 3  
     101 [-]: CALL R23 3 1 
     102 [-]: MUL R21 R22 R23
     103 [-]: SETTABLEKS R21 R20 K42 ["difficulty"]
     104 [-]: NAMECALL R17 R17 K44 [0xDA3AB0F4]
     105 [-]: CALL R17 3 0 
     106 [-]: JUMPIFNOT R3 L14
     107 [-]: GETUPVAL R17 5
     108 [-]: MOVE R19 R3  
     109 [-]: NAMECALL R17 R17 K45 [0x5EF73E0B]
     110 [-]: CALL R17 2 0 
L14: 111 [-]: JUMPIFNOT R4 L18
     112 [-]: LOADN R19 1  
     113 [-]: LENGTH R17 R4
     114 [-]: LOADN R18 1  
     115 [-]: FORNPREP R17 L17
L15: 116 [-]: GETUPVAL R20 5
     117 [-]: LOADB R22 1  
     118 [-]: GETTABLE R24 R4 R19
     119 [-]: FASTCALL1 53 R24 L16
     120 [-]: GETIMPORT R23 47 [nil]
     121 [-]: CALL R23 1 -1
L16: 122 [-]: NAMECALL R20 R20 K48 [0x7FF3A572]
     123 [-]: CALL R20 -1 0
     124 [-]: FORNLOOP R17 L15
L17: 125 [-]: GETUPVAL R17 5
     126 [-]: MOVE R19 R4  
     127 [-]: NAMECALL R17 R17 K49 [0x98B7EA40]
     128 [-]: CALL R17 2 0 
L18: 129 [-]: LOADB R17 1  
     130 [-]: SETUPVAL R17 7
     131 [-]: GETUPVAL R17 8
     132 [-]: GETIMPORT R19 51 [nil]
     133 [-]: NAMECALL R17 R17 K52 [0xD5F884A6]
     134 [-]: CALL R17 2 0 
     135 [-]: GETUPVAL R17 8
     136 [-]: LOADB R19 0  
     137 [-]: NAMECALL R17 R17 K53 [0xE7C54CFD]
     138 [-]: CALL R17 2 0 
     139 [-]: GETIMPORT R18 55 [nil]
     140 [-]: FASTCALL1 62 R18 L19
     141 [-]: GETIMPORT R17 4 [nil]
     142 [-]: CALL R17 1 1 
L19: 143 [-]: JUMPIF R17 L20
     144 [-]: GETIMPORT R17 57 [nil]
     145 [-]: GETIMPORT R19 55 [nil]
     146 [-]: GETIMPORT R20 59 [nil]
     147 [-]: LOADB R21 0  
     148 [-]: NAMECALL R17 R17 K60 [0x659D451F]
     149 [-]: CALL R17 4 1 
     150 [-]: SETUPVAL R17 9
L20: 151 [-]: GETUPVAL R17 5
     152 [-]: MOVE R19 R12 
     153 [-]: NAMECALL R17 R17 K61 [0x3D9ED9C7]
     154 [-]: CALL R17 2 0 
     155 [-]: GETUPVAL R17 10
     156 [-]: CALL R17 0 0 
     157 [-]: GETIMPORT R17 62 [nil]
     158 [-]: LOADB R18 1  
     159 [-]: SETTABLEKS R18 R17 K63 ["HudReplacement_ForceVisibility"]
     160 [-]: GETUPVAL R17 11
     161 [-]: CALL R17 0 0 
     162 [-]: GETIMPORT R17 62 [nil]
     163 [-]: GETUPVAL R18 12
     164 [-]: SETTABLEKS R18 R17 K64 ["BoardgameClickCallback"]
     165 [-]: GETIMPORT R17 62 [nil]
     166 [-]: GETUPVAL R18 13
     167 [-]: SETTABLEKS R18 R17 K65 ["BoardGamePauseCallback"]
     168 [-]: GETIMPORT R17 62 [nil]
     169 [-]: GETUPVAL R18 14
     170 [-]: SETTABLEKS R18 R17 K66 ["BoardGameRightClickCallback"]
     171 [-]: GETIMPORT R17 62 [nil]
     172 [-]: GETUPVAL R18 15
     173 [-]: SETTABLEKS R18 R17 K67 ["BoardGameActivateAbilityCallback"]
     174 [-]: GETIMPORT R17 62 [nil]
     175 [-]: GETUPVAL R18 16
     176 [-]: SETTABLEKS R18 R17 K68 ["BoardGameConcede"]
     177 [-]: LOADB R17 1  
     178 [-]: LOADN R18 0  
L21: 179 [-]: LOADN R19 0  
     180 [-]: JUMPIFNOTLE R18 R19 L44
     181 [-]: JUMPIFNOT R17 L44
     182 [-]: GETUPVAL R19 5
     183 [-]: GETUPVAL R21 5
     184 [-]: NAMECALL R21 R21 K69 [0x5E651723]
     185 [-]: CALL R21 1 -1
     186 [-]: NAMECALL R19 R19 K70 [0x6479E675]
     187 [-]: CALL R19 -1 1
     188 [-]: JUMPIFNOT R19 L36
     189 [-]: LOADN R6 0   
     190 [-]: LOADN R19 0  
     191 [-]: JUMPIFNOTLT R19 R7 L22
     192 [-]: JUMPIF R8 L22
     193 [-]: LOADB R8 0   
L22: 194 [-]: GETIMPORT R19 72 [nil]
     195 [-]: LOADN R20 0  
     196 [-]: LOADN R21 1  
     197 [-]: CALL R19 2 1 
     198 [-]: JUMPIFNOTLT R19 R5 L24
     199 [-]: LOADK R5 K73 [0.10000000000000001]
     200 [-]: JUMPXEQKB R8 0 L23 NOT
     201 [-]: GETUPVAL R20 17
     202 [-]: GETTABLEKS R19 R20 K74 [0x9742B85B]
     203 [-]: LOADNIL R20  
     204 [-]: GETIMPORT R21 76 [nil]
     205 [-]: LOADK R22 K77 ["Go_PlayAfterHurry"]
     206 [-]: CALL R21 1 -1
     207 [-]: CALL R19 -1 0
     208 [-]: LOADB R8 1   
     209 [-]: JUMP L25
    
L23: 210 [-]: GETUPVAL R20 17
     211 [-]: GETTABLEKS R19 R20 K74 [0x9742B85B]
     212 [-]: LOADNIL R20  
     213 [-]: GETIMPORT R21 76 [nil]
     214 [-]: LOADK R22 K78 ["Go_Play"]
     215 [-]: CALL R21 1 -1
     216 [-]: CALL R19 -1 0
     217 [-]: JUMP L25
    
L24: 218 [-]: ADDK R5 R5 K73 [0.10000000000000001]
     219 [-]: JUMPXEQKB R8 0 L25 NOT
     220 [-]: LOADB R8 1   
L25: 221 [-]: GETIMPORT R19 72 [nil]
     222 [-]: LOADN R20 1  
     223 [-]: LOADN R21 2  
     224 [-]: CALL R19 2 1 
     225 [-]: MOVE R20 R19 
L26: 226 [-]: LOADN R21 0  
     227 [-]: JUMPIFNOTLT R21 R20 L27
     228 [-]: GETUPVAL R21 18
     229 [-]: JUMPIF R21 L27
     230 [-]: GETIMPORT R21 80 [nil]
     231 [-]: LOADK R22 K73 [0.10000000000000001]
     232 [-]: CALL R21 1 0 
     233 [-]: SUBK R20 R20 K73 [0.10000000000000001]
     234 [-]: JUMPBACK L26 
L27: 235 [-]: GETUPVAL R19 18
     236 [-]: JUMPIFNOT R19 L28
     237 [-]: LOADB R17 0  
     238 [-]: JUMP L44
    
L28: 239 [-]: LOADNIL R19  
     240 [-]: LOADNIL R20  
     241 [-]: LOADNIL R21  
     242 [-]: GETUPVAL R22 5
     243 [-]: NAMECALL R22 R22 K81 [0x6B1FA511]
     244 [-]: CALL R22 1 1 
     245 [-]: JUMPXEQKN R22 K82 L29 NOT [0]
     246 [-]: GETUPVAL R22 5
     247 [-]: NAMECALL R22 R22 K83 [0x6AA15CCA]
     248 [-]: CALL R22 1 3 
     249 [-]: MOVE R19 R22 
     250 [-]: MOVE R20 R23 
     251 [-]: MOVE R21 R24 
L29: 252 [-]: JUMPIFNOT R19 L35
     253 [-]: JUMPIFNOT R20 L35
     254 [-]: GETUPVAL R22 5
     255 [-]: MOVE R24 R19 
     256 [-]: MOVE R25 R20 
     257 [-]: NAMECALL R22 R22 K84 [0x1A4D17C8]
     258 [-]: CALL R22 3 0 
     259 [-]: GETIMPORT R24 72 [nil]
     260 [-]: LOADK R25 K85 [0.29999999999999999]
     261 [-]: LOADK R26 K86 [1.2]
     262 [-]: CALL R24 2 1 
     263 [-]: SUB R23 R24 R21
     264 [-]: FASTCALL2K 18 R23 K82 L30 [0]
     265 [-]: LOADK R24 K82 [0]
     266 [-]: GETIMPORT R22 89 [nil]
     267 [-]: CALL R22 2 1 
L30: 268 [-]: MOVE R23 R22 
L31: 269 [-]: LOADN R24 0  
     270 [-]: JUMPIFNOTLT R24 R23 L32
     271 [-]: GETUPVAL R24 18
     272 [-]: JUMPIF R24 L32
     273 [-]: GETIMPORT R24 80 [nil]
     274 [-]: LOADK R25 K73 [0.10000000000000001]
     275 [-]: CALL R24 1 0 
     276 [-]: SUBK R23 R23 K73 [0.10000000000000001]
     277 [-]: JUMPBACK L31 
L32: 278 [-]: GETUPVAL R22 18
     279 [-]: JUMPIFNOT R22 L33
     280 [-]: LOADB R17 0  
     281 [-]: JUMP L44
    
L33: 282 [-]: GETUPVAL R22 5
     283 [-]: MOVE R24 R19 
     284 [-]: MOVE R25 R20 
     285 [-]: LOADB R26 1  
     286 [-]: NAMECALL R22 R22 K90 [0x8AD9D7EE]
     287 [-]: CALL R22 4 1 
     288 [-]: JUMPIF R22 L34
     289 [-]: GETIMPORT R23 92 [nil]
     290 [-]: LOADK R24 K93 ["GoLib.lua -- AI picked an invalid move, but thinks it's valid. Likely cpp/lua mismatch. Random move chosen instead."]
     291 [-]: CALL R23 1 0 
     292 [-]: GETUPVAL R23 5
     293 [-]: NAMECALL R23 R23 K94 [0x6E39F503]
     294 [-]: CALL R23 1 2 
     295 [-]: MOVE R19 R23 
     296 [-]: MOVE R20 R24 
     297 [-]: JUMPIFNOT R19 L34
     298 [-]: JUMPIFNOT R20 L34
     299 [-]: GETUPVAL R23 5
     300 [-]: MOVE R25 R19 
     301 [-]: MOVE R26 R20 
     302 [-]: NAMECALL R23 R23 K84 [0x1A4D17C8]
     303 [-]: CALL R23 3 0 
     304 [-]: GETUPVAL R23 5
     305 [-]: MOVE R25 R19 
     306 [-]: MOVE R26 R20 
     307 [-]: LOADB R27 1  
     308 [-]: NAMECALL R23 R23 K90 [0x8AD9D7EE]
     309 [-]: CALL R23 4 1 
     310 [-]: MOVE R22 R23 
     311 [-]: JUMPIF R22 L34
     312 [-]: GETIMPORT R23 92 [nil]
     313 [-]: LOADK R24 K95 ["Error: could not place stone randomly after AI picked an invalid move! Something went very wrong, and we're going to bail out of komi now"]
     314 [-]: CALL R23 1 0 
     315 [-]: LOADB R23 1  
     316 [-]: SETUPVAL R23 18
     317 [-]: LOADB R17 0  
L34: 318 [-]: GETUPVAL R23 5
     319 [-]: NAMECALL R23 R23 K81 [0x6B1FA511]
     320 [-]: CALL R23 1 1 
     321 [-]: MOVE R18 R23 
     322 [-]: JUMPXEQKN R18 K82 L44 NOT [0]
     323 [-]: GETIMPORT R23 62 [nil]
     324 [-]: LOADB R24 1  
     325 [-]: SETTABLEKS R24 R23 K63 ["HudReplacement_ForceVisibility"]
     326 [-]: GETUPVAL R23 11
     327 [-]: CALL R23 0 0 
     328 [-]: GETIMPORT R23 62 [nil]
     329 [-]: GETUPVAL R24 12
     330 [-]: SETTABLEKS R24 R23 K64 ["BoardgameClickCallback"]
     331 [-]: GETIMPORT R23 62 [nil]
     332 [-]: GETUPVAL R24 13
     333 [-]: SETTABLEKS R24 R23 K65 ["BoardGamePauseCallback"]
     334 [-]: GETIMPORT R23 62 [nil]
     335 [-]: GETUPVAL R24 14
     336 [-]: SETTABLEKS R24 R23 K66 ["BoardGameRightClickCallback"]
     337 [-]: GETIMPORT R23 62 [nil]
     338 [-]: GETUPVAL R24 15
     339 [-]: SETTABLEKS R24 R23 K67 ["BoardGameActivateAbilityCallback"]
     340 [-]: GETIMPORT R23 62 [nil]
     341 [-]: GETUPVAL R24 16
     342 [-]: SETTABLEKS R24 R23 K68 ["BoardGameConcede"]
     343 [-]: JUMP L39
    
     344 [-]: JUMP L44
    
     345 [-]: JUMP L39
    
L35: 346 [-]: GETUPVAL R22 5
     347 [-]: NAMECALL R22 R22 K96 [0xE47CB26F]
     348 [-]: CALL R22 1 0 
     349 [-]: LOADN R18 1  
     350 [-]: JUMP L39
    
L36: 351 [-]: GETIMPORT R20 98 [nil]
     352 [-]: FASTCALL1 62 R20 L37
     353 [-]: GETIMPORT R19 4 [nil]
     354 [-]: CALL R19 1 1 
L37: 355 [-]: JUMPIFNOT R19 L39
     356 [-]: GETIMPORT R19 100 [nil]
     357 [-]: CALL R19 0 1 
     358 [-]: ADD R6 R6 R19
     359 [-]: LOADN R20 25 
     360 [-]: ADDK R22 R7 K14 [1]
     361 [-]: MULK R21 R22 K101 [10]
     362 [-]: FASTCALL2 19 R20 R21 L38
     363 [-]: GETIMPORT R19 103 [nil]
     364 [-]: CALL R19 2 1 
L38: 365 [-]: JUMPIFNOTLT R19 R6 L39
     366 [-]: ADDK R7 R7 K14 [1]
     367 [-]: LOADN R6 0   
     368 [-]: GETUPVAL R20 17
     369 [-]: GETTABLEKS R19 R20 K74 [0x9742B85B]
     370 [-]: LOADNIL R20  
     371 [-]: GETIMPORT R21 76 [nil]
     372 [-]: LOADK R22 K104 ["Go_Hurry"]
     373 [-]: CALL R21 1 -1
     374 [-]: CALL R19 -1 0
L39: 375 [-]: GETIMPORT R19 80 [nil]
     376 [-]: LOADN R20 0  
     377 [-]: CALL R19 1 0 
     378 [-]: GETUPVAL R19 19
     379 [-]: GETIMPORT R20 100 [nil]
     380 [-]: CALL R20 0 1 
     381 [-]: MOVE R21 R0  
     382 [-]: CALL R19 2 0 
     383 [-]: JUMPXEQKN R18 K82 L40 [0]
     384 [-]: GETUPVAL R19 20
     385 [-]: JUMPIFNOT R19 L41
L40: 386 [-]: GETUPVAL R19 5
     387 [-]: NAMECALL R19 R19 K81 [0x6B1FA511]
     388 [-]: CALL R19 1 1 
     389 [-]: MOVE R18 R19 
L41: 390 [-]: JUMPIFNOT R1 L42
     391 [-]: MOVE R19 R1  
     392 [-]: GETUPVAL R20 5
     393 [-]: NAMECALL R20 R20 K105 [0x005424E9]
     394 [-]: CALL R20 1 -1
     395 [-]: CALL R19 -1 1
     396 [-]: AND R17 R19 R17
L42: 397 [-]: GETIMPORT R19 107 [nil]
     398 [-]: JUMPIFNOT R19 L43
     399 [-]: LOADB R19 1  
     400 [-]: SETUPVAL R19 18
     401 [-]: LOADB R17 0  
L43: 402 [-]: JUMPBACK L21 
L44: 403 [-]: JUMPIFNOT R17 L45
     404 [-]: LOADN R19 0  
     405 [-]: JUMPIFNOTLT R19 R18 L52
L45: 406 [-]: GETIMPORT R20 109 [nil]
     407 [-]: FASTCALL1 62 R20 L46
     408 [-]: GETIMPORT R19 4 [nil]
     409 [-]: CALL R19 1 1 
L46: 410 [-]: JUMPIF R19 L47
     411 [-]: GETIMPORT R19 57 [nil]
     412 [-]: GETIMPORT R21 109 [nil]
     413 [-]: GETIMPORT R22 59 [nil]
     414 [-]: LOADB R23 0  
     415 [-]: NAMECALL R19 R19 K60 [0x659D451F]
     416 [-]: CALL R19 4 0 
L47: 417 [-]: GETUPVAL R20 9
     418 [-]: FASTCALL1 62 R20 L48
     419 [-]: GETIMPORT R19 4 [nil]
     420 [-]: CALL R19 1 1 
L48: 421 [-]: JUMPIF R19 L49
     422 [-]: GETUPVAL R19 9
     423 [-]: LOADB R21 0  
     424 [-]: NAMECALL R19 R19 K110 [0x6CF1E476]
     425 [-]: CALL R19 2 0 
L49: 426 [-]: GETUPVAL R19 18
     427 [-]: JUMPIF R19 L50
     428 [-]: GETUPVAL R19 21
     429 [-]: LOADK R21 K111 ["HideHint"]
     430 [-]: LOADK R22 K112 [""]
     431 [-]: NAMECALL R19 R19 K113 [0xE4162EED]
     432 [-]: CALL R19 3 0 
     433 [-]: GETUPVAL R19 8
     434 [-]: GETIMPORT R21 51 [nil]
     435 [-]: NAMECALL R19 R19 K52 [0xD5F884A6]
     436 [-]: CALL R19 2 0 
     437 [-]: GETIMPORT R19 80 [nil]
     438 [-]: LOADN R20 3  
     439 [-]: CALL R19 1 0 
L50: 440 [-]: GETUPVAL R20 6
     441 [-]: GETTABLEKS R19 R20 K114 [0x4531F840]
     442 [-]: GETUPVAL R20 5
     443 [-]: CALL R19 1 0 
     444 [-]: LOADNIL R19  
     445 [-]: SETUPVAL R19 5
     446 [-]: LOADB R19 0  
     447 [-]: SETUPVAL R19 7
     448 [-]: GETIMPORT R20 116 [nil]
     449 [-]: FASTCALL1 62 R20 L51
     450 [-]: GETIMPORT R19 4 [nil]
     451 [-]: CALL R19 1 1 
L51: 452 [-]: JUMPIF R19 L52
     453 [-]: GETIMPORT R19 116 [nil]
     454 [-]: GETIMPORT R21 76 [nil]
     455 [-]: LOADK R22 K117 ["DUVIRI_MINIGAME_PLAYED"]
     456 [-]: CALL R21 1 1 
     457 [-]: LOADK R22 K118 ["DuviriKomiEncounter"]
     458 [-]: NAMECALL R19 R19 K119 [0x8B8FB8B7]
     459 [-]: CALL R19 3 0 
L52: 460 [-]: RETURN R18 1 


; Name:            
; Defined at line: 464
; #Upvalues:       3
; #Parameters:     1
; Is_vararg:       0
; Max Stack Size:  5

       0 [-]: GETUPVAL R2 0
       1 [-]: FASTCALL1 62 R2 L0
       2 [-]: GETIMPORT R1 1 [nil]
       3 [-]: CALL R1 1 1  
L 0:   4 [-]: JUMPIFNOT R1 L1
       5 [-]: RETURN R0 0  
L 1:   6 [-]: JUMPIFNOT R0 L3
       7 [-]: GETIMPORT R1 4 [nil]
       8 [-]: LOADB R2 1   
       9 [-]: CALL R1 1 0  
      10 [-]: GETUPVAL R2 1
      11 [-]: GETTABLEKS R1 R2 K5 [0x9E3D3434]
      12 [-]: LOADB R2 1   
      13 [-]: CALL R1 1 0  
      14 [-]: GETUPVAL R2 2
      15 [-]: FASTCALL1 62 R2 L2
      16 [-]: GETIMPORT R1 1 [nil]
      17 [-]: CALL R1 1 1  
L 2:  18 [-]: JUMPIF R1 L4 
      19 [-]: GETUPVAL R1 0
      20 [-]: GETUPVAL R3 2
      21 [-]: LOADN R4 0   
      22 [-]: NAMECALL R1 R1 K6 [0x14C7F7DD]
      23 [-]: CALL R1 3 0  
      24 [-]: RETURN R0 0  
L 3:  25 [-]: GETIMPORT R1 8 [nil]
      26 [-]: CALL R1 0 0  
      27 [-]: GETUPVAL R2 1
      28 [-]: GETTABLEKS R1 R2 K5 [0x9E3D3434]
      29 [-]: LOADB R2 0   
      30 [-]: CALL R1 1 0  
      31 [-]: GETUPVAL R1 0
      32 [-]: LOADNIL R3   
      33 [-]: LOADN R4 0   
      34 [-]: NAMECALL R1 R1 K6 [0x14C7F7DD]
      35 [-]: CALL R1 3 0  
L 4:  36 [-]: RETURN R0 0  


; Name:            
; Defined at line: 485
; #Upvalues:       1
; #Parameters:     2
; Is_vararg:       0
; Max Stack Size:  6

       0 [-]: GETIMPORT R2 1 [nil]
       1 [-]: LOADK R3 K2 ["/Lotus/Types/Keys/DuviriQuest/DuviriQuestKeyChain"]
       2 [-]: CALL R2 1 1  
       3 [-]: GETUPVAL R4 0
       4 [-]: GETTABLEKS R3 R4 K3 [0x8E7C3B5E]
       5 [-]: GETIMPORT R4 5 [nil]
       6 [-]: CALL R3 1 1  
       7 [-]: JUMPIFNOTEQ R3 R2 L0
       8 [-]: LOADB R3 0   
       9 [-]: RETURN R3 1  
L 0:  10 [-]: GETIMPORT R4 7 [nil]
      11 [-]: NAMECALL R4 R4 K8 [0xEF893AEC]
      12 [-]: CALL R4 1 1  
      13 [-]: GETTABLEKS R3 R4 K9 ["goalTag"]
      14 [-]: NAMECALL R4 R3 K10 [0x56C01834]
      15 [-]: CALL R4 1 1  
      16 [-]: JUMPIFNOT R4 L1
      17 [-]: GETIMPORT R4 12 [nil]
      18 [-]: LOADK R5 K13 ["DuviriStoryOnly"]
      19 [-]: CALL R4 1 1  
      20 [-]: JUMPIFNOTEQ R3 R4 L1
      21 [-]: LOADB R4 0   
      22 [-]: RETURN R4 1  
L 1:  23 [-]: GETIMPORT R5 16 [nil]
      24 [-]: NOT R4 R5    
      25 [-]: RETURN R4 1  


; Name:            
; Defined at line: 499
; #Upvalues:       0
; #Parameters:     1
; Is_vararg:       0
; Max Stack Size:  5

L 0:   0 [-]: FASTCALL1 62 R0 L1
       1 [-]: MOVE R2 R0   
       2 [-]: GETIMPORT R1 1 [nil]
       3 [-]: CALL R1 1 1  
L 1:   4 [-]: JUMPIF R1 L2 
       5 [-]: GETIMPORT R3 3 [nil]
       6 [-]: NAMECALL R1 R0 K4 [0xF2DEAF69]
       7 [-]: CALL R1 2 1  
       8 [-]: JUMPIFNOT R1 L2
       9 [-]: NAMECALL R1 R0 K5 [0x35844CF2]
      10 [-]: CALL R1 1 1  
      11 [-]: JUMPIFNOT R1 L2
      12 [-]: GETIMPORT R2 8 [nil]
      13 [-]: NAMECALL R3 R0 K9 [0x388577D5]
      14 [-]: CALL R3 1 1  
      15 [-]: GETTABLE R1 R2 R3
      16 [-]: JUMPIFNOT R1 L2
      17 [-]: NAMECALL R1 R0 K10 [0x5E651723]
      18 [-]: CALL R1 1 1  
      19 [-]: NAMECALL R1 R1 K11 [0xB5983272]
      20 [-]: CALL R1 1 0  
      21 [-]: GETIMPORT R1 13 [nil]
      22 [-]: LOADN R2 1   
      23 [-]: CALL R1 1 0  
      24 [-]: JUMPBACK L0  
L 2:  25 [-]: RETURN R0 0  


; Name:            
; Defined at line: 506
; #Upvalues:       1
; #Parameters:     2
; Is_vararg:       0
; Max Stack Size:  8

       0 [-]: NAMECALL R2 R0 K0 [0xE287C223]
       1 [-]: CALL R2 1 1  
       2 [-]: JUMPIF R2 L0 
       3 [-]: NAMECALL R2 R0 K1 [0x278B099D]
       4 [-]: CALL R2 1 1  
       5 [-]: JUMPIF R2 L0 
       6 [-]: NAMECALL R2 R0 K2 [0x35844CF2]
       7 [-]: CALL R2 1 1  
       8 [-]: JUMPIF R2 L0 
       9 [-]: NAMECALL R2 R0 K3 [0x7EF3366A]
      10 [-]: CALL R2 1 1  
      11 [-]: JUMPIF R2 L0 
      12 [-]: NAMECALL R2 R0 K4 [0x73901ACF]
      13 [-]: CALL R2 1 1  
      14 [-]: JUMPIF R2 L0 
      15 [-]: MOVE R4 R1   
      16 [-]: NAMECALL R2 R0 K5 [0xEE0BC178]
      17 [-]: CALL R2 2 1  
      18 [-]: JUMPIFNOT R2 L1
L 0:  19 [-]: LOADB R2 0   
      20 [-]: RETURN R2 1  
L 1:  21 [-]: NAMECALL R2 R0 K6 [0x2D0A291F]
      22 [-]: CALL R2 1 1  
      23 [-]: LOADN R5 1   
      24 [-]: GETUPVAL R6 0
      25 [-]: LENGTH R3 R6 
      26 [-]: LOADN R4 1   
      27 [-]: FORNPREP R3 L4
L 2:  28 [-]: GETUPVAL R7 0
      29 [-]: GETTABLE R6 R7 R5
      30 [-]: JUMPIFNOTEQ R2 R6 L3
      31 [-]: LOADB R6 0   
      32 [-]: RETURN R6 1  
L 3:  33 [-]: FORNLOOP R3 L2
L 4:  34 [-]: LOADB R3 1   
      35 [-]: RETURN R3 1  


; Name:            
; Defined at line: 528
; #Upvalues:       20
; #Parameters:     1
; Is_vararg:       0
; Max Stack Size:  17

       0 [-]: GETIMPORT R1 1 [nil]
       1 [-]: GETIMPORT R3 3 [nil]
       2 [-]: LOADK R4 K4 ["KomiBoard"]
       3 [-]: CALL R3 1 1  
       4 [-]: NAMECALL R4 R0 K5 [0xF6EBD926]
       5 [-]: CALL R4 1 1  
       6 [-]: LOADN R5 0   
       7 [-]: LOADN R6 20  
       8 [-]: NAMECALL R1 R1 K6 [0x462C251C]
       9 [-]: CALL R1 5 1  
      10 [-]: FASTCALL1 62 R1 L0
      11 [-]: MOVE R3 R1   
      12 [-]: GETIMPORT R2 8 [nil]
      13 [-]: CALL R2 1 1  
L 0:  14 [-]: JUMPIFNOT R2 L1
      15 [-]: GETIMPORT R2 10 [nil]
      16 [-]: LOADK R3 K11 ["ERROR: somehow playing komi without a table?"]
      17 [-]: CALL R2 1 0  
      18 [-]: RETURN R0 0  
L 1:  19 [-]: LOADN R2 50  
      20 [-]: SETUPVAL R2 0
      21 [-]: LOADN R2 0   
      22 [-]: GETIMPORT R3 1 [nil]
      23 [-]: NAMECALL R5 R0 K12 [0xD1586535]
      24 [-]: CALL R5 1 1  
      25 [-]: GETUPVAL R6 0
      26 [-]: GETIMPORT R7 14 [nil]
      27 [-]: NAMECALL R3 R3 K15 [0x5569E534]
      28 [-]: CALL R3 4 1  
      29 [-]: LOADN R6 1   
      30 [-]: LENGTH R4 R3 
      31 [-]: LOADN R5 1   
      32 [-]: FORNPREP R4 L5
L 2:  33 [-]: GETTABLE R7 R3 R6
      34 [-]: FASTCALL1 62 R7 L3
      35 [-]: MOVE R9 R7   
      36 [-]: GETIMPORT R8 8 [nil]
      37 [-]: CALL R8 1 1  
L 3:  38 [-]: JUMPIF R8 L4 
      39 [-]: GETUPVAL R8 1
      40 [-]: MOVE R9 R7   
      41 [-]: MOVE R10 R0  
      42 [-]: CALL R8 2 1  
      43 [-]: JUMPIFNOT R8 L4
      44 [-]: ADDK R2 R2 K16 [1]
L 4:  45 [-]: FORNLOOP R4 L2
L 5:  46 [-]: LOADN R4 0   
      47 [-]: JUMPIFNOTLT R4 R2 L7
      48 [-]: NAMECALL R4 R0 K17 [0xA5E492D4]
      49 [-]: CALL R4 1 1  
      50 [-]: JUMPIFNOT R4 L6
      51 [-]: GETIMPORT R4 10 [nil]
      52 [-]: LOADK R5 K18 ["KOMI: not starting game because enemies too close"]
      53 [-]: CALL R4 1 0  
      54 [-]: GETIMPORT R4 21 [nil]
      55 [-]: LOADK R5 K22 ["/Lotus/Language/Duviri/KomiEnemiesNearby"]
      56 [-]: LOADN R6 3   
      57 [-]: CALL R4 2 0  
L 6:  58 [-]: RETURN R0 0  
L 7:  59 [-]: GETIMPORT R5 24 [nil]
      60 [-]: FASTCALL1 62 R5 L8
      61 [-]: GETIMPORT R4 8 [nil]
      62 [-]: CALL R4 1 1  
L 8:  63 [-]: JUMPIFNOT R4 L9
      64 [-]: GETIMPORT R4 25 [nil]
      65 [-]: NEWTABLE R5 0 0
      66 [-]: SETTABLEKS R5 R4 K23 ["KomiKeepAlive"]
L 9:  67 [-]: GETIMPORT R4 24 [nil]
      68 [-]: NAMECALL R5 R0 K26 [0x388577D5]
      69 [-]: CALL R5 1 1  
      70 [-]: LOADB R6 1   
      71 [-]: SETTABLE R6 R4 R5
      72 [-]: GETIMPORT R6 3 [nil]
      73 [-]: LOADK R7 K27 ["KomiKeepActive"]
      74 [-]: CALL R6 1 1  
      75 [-]: LOADB R7 0   
      76 [-]: NAMECALL R4 R0 K28 [0xD5F7912B]
      77 [-]: CALL R4 3 0  
      78 [-]: NAMECALL R4 R0 K17 [0xA5E492D4]
      79 [-]: CALL R4 1 1  
      80 [-]: JUMPIF R4 L10
      81 [-]: RETURN R0 0  
L10:  82 [-]: LOADB R6 1   
      83 [-]: NAMECALL R4 R0 K29 [0x069D881F]
      84 [-]: CALL R4 2 0  
      85 [-]: GETIMPORT R4 1 [nil]
      86 [-]: NAMECALL R4 R4 K30 [0x8B5B1F58]
      87 [-]: CALL R4 1 1  
      88 [-]: GETIMPORT R5 32 [nil]
      89 [-]: MOVE R6 R4   
      90 [-]: CALL R5 1 3  
      91 [-]: FORGPREP_NEXT R5 L12
L11:  92 [-]: LOADB R12 0  
      93 [-]: NAMECALL R10 R9 K33 [0x2ABC8ECD]
      94 [-]: CALL R10 2 0 
L12:  95 [-]: FORGLOOP R5 L11 2
      96 [-]: GETIMPORT R5 25 [nil]
      97 [-]: LOADB R6 1   
      98 [-]: SETTABLEKS R6 R5 K34 ["KomiGameInProgress"]
      99 [-]: NAMECALL R5 R0 K35 [0x0B4BCFB6]
     100 [-]: CALL R5 1 1  
     101 [-]: SETUPVAL R5 2
L13: 102 [-]: GETUPVAL R6 2
     103 [-]: FASTCALL1 62 R6 L14
     104 [-]: GETIMPORT R5 8 [nil]
     105 [-]: CALL R5 1 1  
L14: 106 [-]: JUMPIFNOT R5 L16
     107 [-]: FASTCALL1 62 R0 L15
     108 [-]: MOVE R6 R0   
     109 [-]: GETIMPORT R5 8 [nil]
     110 [-]: CALL R5 1 1  
L15: 111 [-]: JUMPIF R5 L16
     112 [-]: GETIMPORT R5 37 [nil]
     113 [-]: LOADN R6 0   
     114 [-]: CALL R5 1 0  
     115 [-]: NAMECALL R5 R0 K35 [0x0B4BCFB6]
     116 [-]: CALL R5 1 1  
     117 [-]: SETUPVAL R5 2
     118 [-]: JUMPBACK L13 
L16: 119 [-]: NAMECALL R5 R1 K5 [0xF6EBD926]
     120 [-]: CALL R5 1 1  
     121 [-]: GETIMPORT R6 1 [nil]
     122 [-]: GETIMPORT R8 3 [nil]
     123 [-]: LOADK R9 K38 ["MemoryGoBoard"]
     124 [-]: CALL R8 1 1  
     125 [-]: MOVE R9 R5   
     126 [-]: LOADN R10 0  
     127 [-]: LOADN R11 20 
     128 [-]: NAMECALL R6 R6 K6 [0x462C251C]
     129 [-]: CALL R6 5 1  
     130 [-]: GETIMPORT R9 40 [nil]
     131 [-]: NAMECALL R7 R1 K41 [0xC9F6A7D7]
     132 [-]: CALL R7 2 1  
     133 [-]: SETUPVAL R7 3
     134 [-]: GETUPVAL R10 3
     135 [-]: FASTCALL1 62 R10 L17
     136 [-]: GETIMPORT R9 8 [nil]
     137 [-]: CALL R9 1 1  
L17: 138 [-]: NOT R8 R9    
     139 [-]: FASTCALL1 1 R8 L18
     140 [-]: GETIMPORT R7 43 [nil]
     141 [-]: CALL R7 1 0  
L18: 142 [-]: FASTCALL1 62 R6 L19
     143 [-]: MOVE R10 R6  
     144 [-]: GETIMPORT R9 8 [nil]
     145 [-]: CALL R9 1 1  
L19: 146 [-]: NOT R8 R9    
     147 [-]: FASTCALL1 1 R8 L20
     148 [-]: GETIMPORT R7 43 [nil]
     149 [-]: CALL R7 1 0  
L20: 150 [-]: GETIMPORT R7 1 [nil]
     151 [-]: GETUPVAL R9 3
     152 [-]: NAMECALL R7 R7 K44 [0x55684E45]
     153 [-]: CALL R7 2 0  
     154 [-]: GETUPVAL R7 4
     155 [-]: LOADB R8 1   
     156 [-]: CALL R7 1 0  
     157 [-]: GETIMPORT R7 37 [nil]
     158 [-]: LOADN R8 0   
     159 [-]: CALL R7 1 0  
     160 [-]: GETUPVAL R7 3
     161 [-]: NAMECALL R7 R7 K5 [0xF6EBD926]
     162 [-]: CALL R7 1 1  
     163 [-]: SETUPVAL R7 5
     164 [-]: GETUPVAL R7 3
     165 [-]: NAMECALL R7 R7 K45 [0x39307AF2]
     166 [-]: CALL R7 1 1  
     167 [-]: GETIMPORT R8 48 [nil]
     168 [-]: CALL R8 0 1  
     169 [-]: JUMPIFNOT R8 L21
     170 [-]: MULK R7 R7 K49 [3]
     171 [-]: GETUPVAL R8 3
     172 [-]: MOVE R10 R7  
     173 [-]: NAMECALL R8 R8 K50 [0xDC3E7596]
     174 [-]: CALL R8 2 0  
L21: 175 [-]: GETIMPORT R8 52 [nil]
     176 [-]: GETIMPORT R10 54 [nil]
     177 [-]: NAMECALL R8 R8 K55 [0xCFBA257F]
     178 [-]: CALL R8 2 1  
     179 [-]: SETUPVAL R8 6
     180 [-]: GETUPVAL R9 6
     181 [-]: FASTCALL1 62 R9 L22
     182 [-]: GETIMPORT R8 8 [nil]
     183 [-]: CALL R8 1 1  
L22: 184 [-]: JUMPIF R8 L23
     185 [-]: GETUPVAL R8 6
     186 [-]: GETIMPORT R10 57 [nil]
     187 [-]: NAMECALL R8 R8 K58 [0x3F8A7894]
     188 [-]: CALL R8 2 0  
     189 [-]: GETUPVAL R8 6
     190 [-]: GETIMPORT R10 60 [nil]
     191 [-]: NAMECALL R8 R8 K61 [0x8A548387]
     192 [-]: CALL R8 2 0  
     193 [-]: GETUPVAL R8 6
     194 [-]: LOADB R10 0  
     195 [-]: NAMECALL R8 R8 K62 [0xBDF92E18]
     196 [-]: CALL R8 2 0  
     197 [-]: GETUPVAL R8 6
     198 [-]: LOADK R10 K63 ["Show"]
     199 [-]: LOADK R11 K64 [""]
     200 [-]: NAMECALL R8 R8 K65 [0xE4162EED]
     201 [-]: CALL R8 3 0  
L23: 202 [-]: LOADB R8 0   
     203 [-]: SETUPVAL R8 7
     204 [-]: LOADB R8 0   
     205 [-]: SETUPVAL R8 8
     206 [-]: GETUPVAL R8 9
     207 [-]: MOVE R9 R0   
     208 [-]: GETUPVAL R10 10
     209 [-]: MOVE R11 R6  
     210 [-]: CALL R8 3 1  
     211 [-]: JUMPXEQKN R8 K16 L24 [1]
     212 [-]: GETUPVAL R9 8
     213 [-]: JUMPIFNOT R9 L31
L24: 214 [-]: GETIMPORT R10 67 [nil]
     215 [-]: FASTCALL1 62 R10 L25
     216 [-]: GETIMPORT R9 8 [nil]
     217 [-]: CALL R9 1 1  
L25: 218 [-]: JUMPIF R9 L26
     219 [-]: GETIMPORT R9 67 [nil]
     220 [-]: GETIMPORT R11 3 [nil]
     221 [-]: LOADK R12 K68 ["DUVIRI_MINIGAME_COMPLETE"]
     222 [-]: CALL R11 1 1 
     223 [-]: LOADK R12 K69 ["DuviriKomiEncounter"]
     224 [-]: NAMECALL R9 R9 K70 [0x8B8FB8B7]
     225 [-]: CALL R9 3 0  
L26: 226 [-]: GETUPVAL R10 11
     227 [-]: ADDK R9 R10 K16 [1]
     228 [-]: SETUPVAL R9 11
     229 [-]: GETUPVAL R9 11
     230 [-]: GETGLOBAL R11 K71 [0xAA6C2B3F]
     231 [-]: LENGTH R10 R11
     232 [-]: JUMPIFNOTLT R10 R9 L35
     233 [-]: LOADN R9 1   
     234 [-]: SETUPVAL R9 11
     235 [-]: NAMECALL R9 R0 K72 [0x35844CF2]
     236 [-]: CALL R9 1 1  
     237 [-]: JUMPIFNOT R9 L35
     238 [-]: GETUPVAL R11 12
     239 [-]: NAMECALL R9 R1 K41 [0xC9F6A7D7]
     240 [-]: CALL R9 2 1  
     241 [-]: FASTCALL1 62 R9 L27
     242 [-]: MOVE R11 R9  
     243 [-]: GETIMPORT R10 8 [nil]
     244 [-]: CALL R10 1 1 
L27: 245 [-]: JUMPIF R10 L28
     246 [-]: NAMECALL R10 R9 K73 [0xF37943FF]
     247 [-]: CALL R10 1 1 
     248 [-]: JUMPIF R10 L30
L28: 249 [-]: GETUPVAL R12 13
     250 [-]: NAMECALL R10 R1 K41 [0xC9F6A7D7]
     251 [-]: CALL R10 2 1 
     252 [-]: MOVE R9 R10  
     253 [-]: FASTCALL1 62 R9 L29
     254 [-]: MOVE R11 R9  
     255 [-]: GETIMPORT R10 8 [nil]
     256 [-]: CALL R10 1 1 
L29: 257 [-]: JUMPIF R10 L35
     258 [-]: MOVE R12 R9  
     259 [-]: LOADB R13 1  
     260 [-]: NAMECALL R10 R0 K74 [0x96603F61]
     261 [-]: CALL R10 3 0 
     262 [-]: JUMP L35
    
L30: 263 [-]: MOVE R12 R9  
     264 [-]: LOADB R13 1  
     265 [-]: NAMECALL R10 R0 K74 [0x96603F61]
     266 [-]: CALL R10 3 0 
     267 [-]: JUMP L35
    
     268 [-]: JUMP L35
    
L31: 269 [-]: JUMPXEQKN R8 K75 L33 NOT [2]
     270 [-]: LOADN R10 1  
     271 [-]: GETUPVAL R12 11
     272 [-]: SUBK R11 R12 K16 [1]
     273 [-]: FASTCALL2 18 R10 R11 L32
     274 [-]: GETIMPORT R9 78 [nil]
     275 [-]: CALL R9 2 1  
L32: 276 [-]: SETUPVAL R9 11
     277 [-]: JUMP L33
    
L33: 278 [-]: NAMECALL R9 R0 K72 [0x35844CF2]
     279 [-]: CALL R9 1 1  
     280 [-]: JUMPIFNOT R9 L35
     281 [-]: GETUPVAL R11 13
     282 [-]: NAMECALL R9 R1 K41 [0xC9F6A7D7]
     283 [-]: CALL R9 2 1  
     284 [-]: FASTCALL1 62 R9 L34
     285 [-]: MOVE R11 R9  
     286 [-]: GETIMPORT R10 8 [nil]
     287 [-]: CALL R10 1 1 
L34: 288 [-]: JUMPIF R10 L35
     289 [-]: MOVE R12 R9  
     290 [-]: LOADB R13 1  
     291 [-]: NAMECALL R10 R0 K74 [0x96603F61]
     292 [-]: CALL R10 3 0 
L35: 293 [-]: GETIMPORT R9 25 [nil]
     294 [-]: GETUPVAL R10 11
     295 [-]: SETTABLEKS R10 R9 K79 ["KomiGameIdx"]
     296 [-]: GETUPVAL R10 6
     297 [-]: FASTCALL1 62 R10 L36
     298 [-]: GETIMPORT R9 8 [nil]
     299 [-]: CALL R9 1 1  
L36: 300 [-]: JUMPIF R9 L37
     301 [-]: GETUPVAL R9 6
     302 [-]: NAMECALL R9 R9 K80 [0x32302B4A]
     303 [-]: CALL R9 1 0  
     304 [-]: LOADNIL R9   
     305 [-]: SETUPVAL R9 6
L37: 306 [-]: GETIMPORT R9 25 [nil]
     307 [-]: LOADB R10 0  
     308 [-]: SETTABLEKS R10 R9 K81 ["HudReplacement_ForceVisibility"]
     309 [-]: GETUPVAL R9 14
     310 [-]: CALL R9 0 0  
     311 [-]: GETIMPORT R9 25 [nil]
     312 [-]: GETUPVAL R10 15
     313 [-]: SETTABLEKS R10 R9 K82 ["BoardgameClickCallback"]
     314 [-]: GETIMPORT R9 25 [nil]
     315 [-]: GETUPVAL R10 16
     316 [-]: SETTABLEKS R10 R9 K83 ["BoardGamePauseCallback"]
     317 [-]: GETIMPORT R9 25 [nil]
     318 [-]: GETUPVAL R10 17
     319 [-]: SETTABLEKS R10 R9 K84 ["BoardGameRightClickCallback"]
     320 [-]: GETIMPORT R9 25 [nil]
     321 [-]: GETUPVAL R10 18
     322 [-]: SETTABLEKS R10 R9 K85 ["BoardGameActivateAbilityCallback"]
     323 [-]: GETIMPORT R9 25 [nil]
     324 [-]: GETUPVAL R10 19
     325 [-]: SETTABLEKS R10 R9 K86 ["BoardGameConcede"]
     326 [-]: GETUPVAL R9 4
     327 [-]: LOADB R10 0  
     328 [-]: CALL R9 1 0  
     329 [-]: GETIMPORT R9 1 [nil]
     330 [-]: NAMECALL R9 R9 K30 [0x8B5B1F58]
     331 [-]: CALL R9 1 1  
     332 [-]: MOVE R4 R9   
     333 [-]: GETIMPORT R9 32 [nil]
     334 [-]: MOVE R10 R4  
     335 [-]: CALL R9 1 3  
     336 [-]: FORGPREP_NEXT R9 L39
L38: 337 [-]: LOADB R16 1  
     338 [-]: NAMECALL R14 R13 K33 [0x2ABC8ECD]
     339 [-]: CALL R14 2 0 
L39: 340 [-]: FORGLOOP R9 L38 2
     341 [-]: FASTCALL1 62 R0 L40
     342 [-]: MOVE R10 R0  
     343 [-]: GETIMPORT R9 8 [nil]
     344 [-]: CALL R9 1 1  
L40: 345 [-]: JUMPIF R9 L41
     346 [-]: LOADB R11 0  
     347 [-]: NAMECALL R9 R0 K29 [0x069D881F]
     348 [-]: CALL R9 2 0  
L41: 349 [-]: GETIMPORT R9 25 [nil]
     350 [-]: LOADB R10 0  
     351 [-]: SETTABLEKS R10 R9 K34 ["KomiGameInProgress"]
     352 [-]: RETURN R0 0  


; Name:            
; Defined at line: 724
; #Upvalues:       1
; #Parameters:     2
; Is_vararg:       0
; Max Stack Size:  6

       0 [-]: FASTCALL1 62 R1 L0
       1 [-]: MOVE R3 R1   
       2 [-]: GETIMPORT R2 1 [nil]
       3 [-]: CALL R2 1 1  
L 0:   4 [-]: JUMPIF R2 L1 
       5 [-]: NAMECALL R2 R1 K2 [0xA5E492D4]
       6 [-]: CALL R2 1 1  
       7 [-]: JUMPIF R2 L2 
       8 [-]: GETIMPORT R2 4 [nil]
       9 [-]: NAMECALL R2 R2 K5 [0x18D05D30]
      10 [-]: CALL R2 1 1  
      11 [-]: JUMPIF R2 L2 
L 1:  12 [-]: RETURN R0 0  
L 2:  13 [-]: FASTCALL1 62 R0 L3
      14 [-]: MOVE R3 R0   
      15 [-]: GETIMPORT R2 1 [nil]
      16 [-]: CALL R2 1 1  
L 3:  17 [-]: JUMPIFNOT R2 L4
      18 [-]: GETIMPORT R2 7 [nil]
      19 [-]: LOADN R3 0   
      20 [-]: CALL R2 1 0  
L 4:  21 [-]: GETUPVAL R4 0
      22 [-]: NAMECALL R2 R1 K8 [0xF2DEAF69]
      23 [-]: CALL R2 2 1  
      24 [-]: JUMPIF R2 L5 
      25 [-]: GETIMPORT R2 11 [nil]
      26 [-]: LOADK R3 K12 ["/Lotus/Language/Duviri/KomiBeastMode"]
      27 [-]: LOADN R4 3   
      28 [-]: CALL R2 2 0  
      29 [-]: RETURN R0 0  
L 5:  30 [-]: GETGLOBAL R3 K13 [0xAA6C2B3F]
      31 [-]: FASTCALL1 62 R3 L6
      32 [-]: GETIMPORT R2 1 [nil]
      33 [-]: CALL R2 1 1  
L 6:  34 [-]: JUMPIF R2 L7 
      35 [-]: GETGLOBAL R3 K13 [0xAA6C2B3F]
      36 [-]: LENGTH R2 R3 
      37 [-]: LOADN R3 1   
      38 [-]: JUMPIFNOTLT R2 R3 L8
L 7:  39 [-]: GETIMPORT R2 15 [nil]
      40 [-]: LOADK R3 K16 ["Error: No Komi boards defined; bailing"]
      41 [-]: CALL R2 1 0  
      42 [-]: RETURN R0 0  
L 8:  43 [-]: GETIMPORT R4 18 [nil]
      44 [-]: LOADK R5 K19 ["PlayKomiMonitor"]
      45 [-]: CALL R4 1 1  
      46 [-]: LOADB R5 0   
      47 [-]: NAMECALL R2 R1 K20 [0xD5F7912B]
      48 [-]: CALL R2 3 0  
      49 [-]: RETURN R0 0  



