; Name:            
; Defined at line: 1
; #Upvalues:       0
; #Parameters:     0
; Is_vararg:       1
; Max Stack Size:  49

       1 [-]: GETIMPORT R0 1; var0 = 0x2D0FAD09
       2 [-]: LOADK R1 K2  ; var1 = "EE.Interface.Utilities"
       3 [-]: CALL R0 2 2  ; var0 = var0(var1)
       4 [-]: GETIMPORT R1 1; var1 = 0x2D0FAD09
       5 [-]: LOADK R2 K3  ; var2 = "Lotus.Scripts.Libs.LandscapeLib"
       6 [-]: CALL R1 2 2  ; var1 = var1(var2)
       7 [-]: GETIMPORT R2 1; var2 = 0x2D0FAD09
       8 [-]: LOADK R3 K4  ; var3 = "Lotus.Interface.Libs.TimerMgr"
       9 [-]: CALL R2 2 2  ; var2 = var2(var3)
      10 [-]: GETIMPORT R3 1; var3 = 0x2D0FAD09
      11 [-]: LOADK R4 K5  ; var4 = "Lotus.Scripts.Duviri.Encounters.DuviriRewardsLib"
      12 [-]: CALL R3 2 2  ; var3 = var3(var4)
      13 [-]: GETIMPORT R4 1; var4 = 0x2D0FAD09
      14 [-]: LOADK R5 K6  ; var5 = "Lotus.Scripts.Libs.DuviriActivityLib"
      15 [-]: CALL R4 2 2  ; var4 = var4(var5)
      16 [-]: GETIMPORT R5 1; var5 = 0x2D0FAD09
      17 [-]: LOADK R6 K7  ; var6 = "Lotus.Scripts.Libs.ObjectiveText"
      18 [-]: CALL R5 2 2  ; var5 = var5(var6)
      19 [-]: GETIMPORT R6 1; var6 = 0x2D0FAD09
      20 [-]: LOADK R7 K8  ; var7 = "Lotus.Scripts.Libs.DuviriStoryQuestLib"
      21 [-]: CALL R6 2 2  ; var6 = var6(var7)
      22 [-]: GETIMPORT R7 10; var7 = 0x0469F296
      23 [-]: LOADK R8 K11 ; var8 = "NETVAR"
      24 [-]: CALL R7 2 2  ; var7 = var7(var8)
      25 [-]: GETIMPORT R8 10; var8 = 0x0469F296
      26 [-]: LOADK R9 K12 ; var9 = "NETVAR2"
      27 [-]: CALL R8 2 2  ; var8 = var8(var9)
      28 [-]: LOADNIL R9   ; var9 = nil
      29 [-]: LOADNIL R10  ; var10 = nil
      30 [-]: LOADNIL R11  ; var11 = nil
      31 [-]: LOADNIL R12  ; var12 = nil
      32 [-]: LOADN R13 0  ; var13 = 0
      33 [-]: LOADN R14 0  ; var14 = 0
      34 [-]: LOADNIL R15  ; var15 = nil
      35 [-]: LOADNIL R16  ; var16 = nil
      36 [-]: LOADNIL R17  ; var17 = nil
      37 [-]: LOADNIL R18  ; var18 = nil
      38 [-]: LOADNIL R19  ; var19 = nil
      39 [-]: LOADNIL R20  ; var20 = nil
      40 [-]: LOADNIL R21  ; var21 = nil
      41 [-]: LOADNIL R22  ; var22 = nil
      42 [-]: LOADNIL R23  ; var23 = nil
      43 [-]: NEWTABLE R24 0 0; var24 = {}
      44 [-]: LOADNIL R25  ; var25 = nil
      45 [-]: LOADN R26 0  ; var26 = 0
      46 [-]: LOADNIL R27  ; var27 = nil
      47 [-]: LOADNIL R28  ; var28 = nil
      48 [-]: LOADNIL R29  ; var29 = nil
      49 [-]: LOADN R30 1  ; var30 = 1
      50 [-]: LOADN R31 0  ; var31 = 0
      51 [-]: DUPTABLE R32 20; 
      52 [-]: LOADN R33 0  ; var33 = 0
      53 [-]: SETTABLEKS R33 R32 K13; var33["INVALID"] = var32
      54 [-]: LOADN R33 1  ; var33 = 1
      55 [-]: SETTABLEKS R33 R32 K14; var33["WAITING_NPC"] = var32
      56 [-]: LOADN R33 2  ; var33 = 2
      57 [-]: SETTABLEKS R33 R32 K15; var33["STARTED"] = var32
      58 [-]: LOADN R33 3  ; var33 = 3
      59 [-]: SETTABLEKS R33 R32 K16; var33["PORTAL_ACTIVE"] = var32
      60 [-]: LOADN R33 4  ; var33 = 4
      61 [-]: SETTABLEKS R33 R32 K17; var33["BOSS_STATE"] = var32
      62 [-]: LOADN R33 5  ; var33 = 5
      63 [-]: SETTABLEKS R33 R32 K18; var33["COMPLETE"] = var32
      64 [-]: LOADN R33 6  ; var33 = 6
      65 [-]: SETTABLEKS R33 R32 K19; var33["FAIL"] = var32
      66 [-]: LOADNIL R33  ; var33 = nil
      67 [-]: LOADNIL R34  ; var34 = nil
      68 [-]: LOADN R35 3  ; var35 = 3
      69 [-]: NEWCLOSURE R36 P0; 
      70 [-]: CAPTURE REF R12; 
      71 [-]: DUPCLOSURE R37 K21; 
      72 [-]: NEWCLOSURE R38 P2; 
      73 [-]: CAPTURE REF R11; 
      74 [-]: NEWCLOSURE R39 P3; 
      75 [-]: CAPTURE VAL R36; 
      76 [-]: CAPTURE REF R12; 
      77 [-]: CAPTURE REF R35; 
      78 [-]: CAPTURE REF R30; 
      79 [-]: CAPTURE REF R20; 
      80 [-]: CAPTURE VAL R4; 
      81 [-]: CAPTURE REF R15; 
      82 [-]: CAPTURE REF R29; 
      83 [-]: CAPTURE REF R18; 
      84 [-]: CAPTURE VAL R32; 
      85 [-]: CAPTURE REF R23; 
      86 [-]: NEWCLOSURE R40 P4; 
      87 [-]: CAPTURE REF R20; 
      88 [-]: CAPTURE VAL R6; 
      89 [-]: NEWCLOSURE R41 P5; 
      90 [-]: CAPTURE REF R20; 
      91 [-]: CAPTURE REF R27; 
      92 [-]: CAPTURE REF R11; 
      93 [-]: CAPTURE REF R29; 
      94 [-]: CAPTURE REF R28; 
      95 [-]: CAPTURE REF R10; 
      96 [-]: NEWCLOSURE R42 P6; 
      97 [-]: CAPTURE VAL R37; 
      98 [-]: CAPTURE REF R27; 
      99 [-]: CAPTURE REF R22; 
     100 [-]: CAPTURE REF R29; 
     101 [-]: CAPTURE VAL R4; 
     102 [-]: CAPTURE REF R23; 
     103 [-]: CAPTURE REF R20; 
     104 [-]: CAPTURE VAL R40; 
     105 [-]: CAPTURE REF R15; 
     106 [-]: NEWCLOSURE R43 P7; 
     107 [-]: CAPTURE REF R18; 
     108 [-]: CAPTURE VAL R32; 
     109 [-]: CAPTURE VAL R39; 
     110 [-]: CAPTURE REF R11; 
     111 [-]: CAPTURE REF R29; 
     112 [-]: CAPTURE REF R34; 
     113 [-]: CAPTURE REF R35; 
     114 [-]: CAPTURE VAL R37; 
     115 [-]: CAPTURE REF R20; 
     116 [-]: CAPTURE VAL R41; 
     117 [-]: CAPTURE VAL R3; 
     118 [-]: NEWCLOSURE R44 P8; 
     119 [-]: CAPTURE REF R20; 
     120 [-]: CAPTURE REF R34; 
     121 [-]: CAPTURE REF R27; 
     122 [-]: CAPTURE REF R11; 
     123 [-]: CAPTURE REF R29; 
     124 [-]: CAPTURE REF R35; 
     125 [-]: CAPTURE REF R18; 
     126 [-]: CAPTURE VAL R32; 
     127 [-]: NEWCLOSURE R45 P9; 
     128 [-]: CAPTURE REF R10; 
     129 [-]: CAPTURE REF R12; 
     130 [-]: CAPTURE REF R34; 
     131 [-]: CAPTURE REF R20; 
     132 [-]: CAPTURE VAL R44; 
     133 [-]: NEWCLOSURE R46 P10; 
     134 [-]: CAPTURE REF R34; 
     135 [-]: CAPTURE REF R10; 
     136 [-]: CAPTURE REF R9; 
     137 [-]: CAPTURE REF R11; 
     138 [-]: CAPTURE REF R15; 
     139 [-]: CAPTURE REF R12; 
     140 [-]: CAPTURE REF R13; 
     141 [-]: CAPTURE REF R14; 
     142 [-]: CAPTURE REF R16; 
     143 [-]: CAPTURE REF R19; 
     144 [-]: CAPTURE REF R30; 
     145 [-]: CAPTURE REF R25; 
     146 [-]: CAPTURE REF R18; 
     147 [-]: CAPTURE VAL R1; 
     148 [-]: CAPTURE VAL R43; 
     149 [-]: CAPTURE VAL R7; 
     150 [-]: CAPTURE VAL R8; 
     151 [-]: CAPTURE REF R17; 
     152 [-]: CAPTURE VAL R2; 
     153 [-]: CAPTURE VAL R4; 
     154 [-]: CAPTURE REF R22; 
     155 [-]: CAPTURE VAL R6; 
     156 [-]: CAPTURE REF R29; 
     157 [-]: CAPTURE REF R33; 
     158 [-]: CAPTURE REF R21; 
     159 [-]: NEWCLOSURE R47 P11; 
     160 [-]: CAPTURE VAL R42; 
     161 [-]: CAPTURE REF R15; 
     162 [-]: CAPTURE REF R21; 
     163 [-]: CAPTURE VAL R1; 
     164 [-]: NEWCLOSURE R48 P12; 
     165 [-]: CAPTURE VAL R46; 
     166 [-]: CAPTURE VAL R32; 
     167 [-]: CAPTURE REF R18; 
     168 [-]: CAPTURE REF R20; 
     169 [-]: CAPTURE REF R11; 
     170 [-]: CAPTURE REF R30; 
     171 [-]: CAPTURE REF R17; 
     172 [-]: CAPTURE VAL R47; 
     173 [-]: SETGLOBAL R48 K22; "Start" = var48
     174 [-]: DUPCLOSURE R48 K23; 
     175 [-]: SETGLOBAL R48 K24; "OnPlayersChanged" = var48
     176 [-]: DUPCLOSURE R48 K25; 
     177 [-]: SETGLOBAL R48 K26; "OnAgentRegistered" = var48
     178 [-]: NEWCLOSURE R48 P15; 
     179 [-]: CAPTURE REF R18; 
     180 [-]: CAPTURE VAL R32; 
     181 [-]: CAPTURE REF R26; 
     182 [-]: CAPTURE REF R30; 
     183 [-]: CAPTURE REF R31; 
     184 [-]: CAPTURE REF R35; 
     185 [-]: CAPTURE REF R11; 
     186 [-]: SETGLOBAL R48 K27; "OnKilled" = var48
     187 [-]: NEWCLOSURE R48 P16; 
     188 [-]: CAPTURE REF R11; 
     189 [-]: CAPTURE REF R20; 
     190 [-]: CAPTURE VAL R44; 
     191 [-]: SETGLOBAL R48 K28; "OnPickedUp" = var48
     192 [-]: CLOSEUPVALS R9; 
     193 [-]: RETURN R0 0  ; 


; Name:            
; Defined at line: 104
; #Upvalues:       1
; #Parameters:     0
; Is_vararg:       0
; Max Stack Size:  9

       0 [-]: GETIMPORT R0 1; var0 = 0x89326C93
       1 [-]: GETIMPORT R2 3; var2 = 0x0469F296
       2 [-]: LOADK R3 K4  ; var3 = "ShrinePickUP"
       3 [-]: CALL R2 2 2  ; var2 = var2(var3)
       4 [-]: GETUPVAL R3 0; var3 = upvalues[0]
       5 [-]: LOADN R4 0   ; var4 = 0
       6 [-]: LOADN R5 100 ; var5 = 100
       7 [-]: NAMECALL R0 R0 K5; var1 = var0; var0 = var0[0xF16592C8]
       8 [-]: CALL R0 6 2  ; var0 = var0(var1, var2, var3, var4, var5)
       9 [-]: LENGTH R1 R0 ; var1 = #var0
      10 [-]: MOVE R4 R1   ; var4 = var1
      11 [-]: LOADN R2 1   ; var2 = 1
      12 [-]: LOADN R3 -1  ; var3 = -1
      13 [-]: FORNPREP R2 L3; nforprep start - [escape at L3] -- var2 = iterator
L 0:  14 [-]: GETTABLE R5 R0 R4; var5 = var0[var4]
      15 [-]: FASTCALL1 64 R5 L1; 
      16 [-]: MOVE R7 R5   ; var7 = var5
      17 [-]: GETIMPORT R6 7; var6 = 0x7B998233
      18 [-]: CALL R6 2 2  ; var6 = var6(var7)
L 1:  19 [-]: JUMPIF R6 L2 ; goto L2 if var6
      20 [-]: GETIMPORT R8 9; var8 = 0x3F3E58E9
      21 [-]: NAMECALL R6 R5 K10; var7 = var5; var6 = var5[0xF2DEAF69]
      22 [-]: CALL R6 3 2  ; var6 = var6(var7, var8)
      23 [-]: JUMPIFNOT R6 L2; goto L2 if not var6
      24 [-]: GETIMPORT R6 13; var6 = 0x33BDD652[0x9C1F3B5A]
      25 [-]: MOVE R7 R0   ; var7 = var0
      26 [-]: MOVE R8 R4   ; var8 = var4
      27 [-]: CALL R6 3 1  ; var6(var7, var8)
      28 [-]: NAMECALL R6 R5 K14; var7 = var5; var6 = var5[0xA2880940]
      29 [-]: CALL R6 2 1  ; var6(var7)
L 2:  30 [-]: FORNLOOP R2 L0; nforloop end - iterate + goto L0
L 3:  31 [-]: RETURN R0 0  ; 


; Name:            
; Defined at line: 115
; #Upvalues:       0
; #Parameters:     1
; Is_vararg:       0
; Max Stack Size:  7

       0 [-]: FASTCALL1 64 R0 L0; 
       1 [-]: MOVE R2 R0   ; var2 = var0
       2 [-]: GETIMPORT R1 1; var1 = 0x7B998233
       3 [-]: CALL R1 2 2  ; var1 = var1(var2)
L 0:   4 [-]: JUMPIF R1 L5 ; goto L5 if var1
       5 [-]: NAMECALL R1 R0 K2; var2 = var0; var1 = var0[0x5CE127EE]
       6 [-]: CALL R1 2 2  ; var1 = var1(var2)
       7 [-]: FASTCALL1 64 R1 L1; 
       8 [-]: MOVE R3 R1   ; var3 = var1
       9 [-]: GETIMPORT R2 1; var2 = 0x7B998233
      10 [-]: CALL R2 2 2  ; var2 = var2(var3)
L 1:  11 [-]: JUMPIF R2 L5 ; goto L5 if var2
      12 [-]: LOADN R4 1   ; var4 = 1
      13 [-]: LENGTH R2 R1 ; var2 = #var1
      14 [-]: LOADN R3 1   ; var3 = 1
      15 [-]: FORNPREP R2 L5; nforprep start - [escape at L5] -- var2 = iterator
L 2:  16 [-]: GETTABLE R6 R1 R4; var6 = var1[var4]
      17 [-]: FASTCALL1 64 R6 L3; 
      18 [-]: GETIMPORT R5 1; var5 = 0x7B998233
      19 [-]: CALL R5 2 2  ; var5 = var5(var6)
L 3:  20 [-]: JUMPIF R5 L4 ; goto L4 if var5
      21 [-]: GETTABLE R5 R1 R4; var5 = var1[var4]
      22 [-]: NAMECALL R5 R5 K3; var6 = var5; var5 = var5[0xA2880940]
      23 [-]: CALL R5 2 1  ; var5(var6)
L 4:  24 [-]: FORNLOOP R2 L2; nforloop end - iterate + goto L2
L 5:  25 [-]: RETURN R0 0  ; 


; Name:            
; Defined at line: 129
; #Upvalues:       1
; #Parameters:     1
; Is_vararg:       0
; Max Stack Size:  6

       0 [-]: GETUPVAL R2 0; var2 = upvalues[0]
       1 [-]: FASTCALL1 64 R2 L0; 
       2 [-]: GETIMPORT R1 1; var1 = 0x7B998233
       3 [-]: CALL R1 2 2  ; var1 = var1(var2)
L 0:   4 [-]: JUMPIF R1 L3 ; goto L3 if var1
       5 [-]: GETIMPORT R1 3; var1 = 0x89326C93
       6 [-]: GETIMPORT R3 5; var3 = 0x3F3E58E9
       7 [-]: MOVE R4 R0   ; var4 = var0
       8 [-]: GETIMPORT R5 7; var5 = ZERO_ROTATION
       9 [-]: NAMECALL R1 R1 K8; var2 = var1; var1 = var1[0x05909209]
      10 [-]: CALL R1 5 2  ; var1 = var1(var2, var3, var4, var5)
      11 [-]: FASTCALL1 64 R1 L1; 
      12 [-]: MOVE R3 R1   ; var3 = var1
      13 [-]: GETIMPORT R2 1; var2 = 0x7B998233
      14 [-]: CALL R2 2 2  ; var2 = var2(var3)
L 1:  15 [-]: JUMPIF R2 L2 ; goto L2 if var2
      16 [-]: GETIMPORT R2 10; var2 = 0x11A19C5E
      17 [-]: MOVE R3 R1   ; var3 = var1
      18 [-]: LOADK R4 K11 ; var4 = "OnPickedUp"
      19 [-]: CALL R2 3 1  ; var2(var3, var4)
L 2:  20 [-]: GETUPVAL R2 0; var2 = upvalues[0]
      21 [-]: MOVE R4 R1   ; var4 = var1
      22 [-]: NAMECALL R2 R2 K12; var3 = var2; var2 = var2[0x21DFC654]
      23 [-]: CALL R2 3 1  ; var2(var3, var4)
L 3:  24 [-]: RETURN R0 0  ; 


; Name:            
; Defined at line: 140
; #Upvalues:       11
; #Parameters:     1
; Is_vararg:       0
; Max Stack Size:  11

       0 [-]: NAMECALL R1 R0 K0; var2 = var0; var1 = var0[0x50A76235]
       1 [-]: CALL R1 2 2  ; var1 = var1(var2)
       2 [-]: JUMPIFNOT R1 L0; goto L0 if not var1
       3 [-]: GETUPVAL R1 0; var1 = upvalues[0]
       4 [-]: CALL R1 1 1  ; var1()
L 0:   5 [-]: GETIMPORT R1 2; var1 = 0x89326C93
       6 [-]: GETIMPORT R3 4; var3 = 0x0469F296
       7 [-]: LOADK R4 K5  ; var4 = "AssembleShrineSimpleDeco"
       8 [-]: CALL R3 2 2  ; var3 = var3(var4)
       9 [-]: GETUPVAL R4 1; var4 = upvalues[1]
      10 [-]: LOADN R5 0   ; var5 = 0
      11 [-]: LOADN R6 20  ; var6 = 20
      12 [-]: NAMECALL R1 R1 K6; var2 = var1; var1 = var1[0x462C251C]
      13 [-]: CALL R1 6 2  ; var1 = var1(var2, var3, var4, var5, var6)
      14 [-]: FASTCALL1 64 R1 L1; 
      15 [-]: MOVE R3 R1   ; var3 = var1
      16 [-]: GETIMPORT R2 8; var2 = 0x7B998233
      17 [-]: CALL R2 2 2  ; var2 = var2(var3)
L 1:  18 [-]: JUMPIF R2 L4 ; goto L4 if var2
      19 [-]: GETIMPORT R2 10; var2 = 0x3D106989
      20 [-]: LOADK R3 K11 ; var3 = "There's already a shrine in this spot!"
      21 [-]: CALL R2 2 1  ; var2(var3)
      22 [-]: GETIMPORT R5 13; var5 = gContextActionType
      23 [-]: NAMECALL R3 R1 K14; var4 = var1; var3 = var1[0xC9F6A7D7]
      24 [-]: CALL R3 3 0  ; var3, ... = var3(var4, var5)
      25 [-]: FASTCALL 64 L2; 
      26 [-]: GETIMPORT R2 8; var2 = 0x7B998233
      27 [-]: CALL R2 0 2  ; var2 = var2(var3, ...)
L 2:  28 [-]: JUMPIFNOT R2 L3; goto L3 if not var2
      29 [-]: GETIMPORT R2 10; var2 = 0x3D106989
      30 [-]: LOADK R3 K15 ; var3 = "But it's already finished, destroying persistent deco"
      31 [-]: CALL R2 2 1  ; var2(var3)
      32 [-]: NAMECALL R2 R1 K16; var3 = var1; var2 = var1[0xA2880940]
      33 [-]: CALL R2 2 1  ; var2(var3)
      34 [-]: JUMP L4      ; goto L4
L 3:  35 [-]: GETIMPORT R2 10; var2 = 0x3D106989
      36 [-]: LOADK R3 K17 ; var3 = "And it's active!"
      37 [-]: CALL R2 2 1  ; var2(var3)
      38 [-]: LOADN R4 5   ; var4 = 5
      39 [-]: NAMECALL R2 R0 K18; var3 = var0; var2 = var0[0xFE9DC265]
      40 [-]: CALL R2 3 1  ; var2(var3, var4)
      41 [-]: RETURN R0 0  ; 
L 4:  42 [-]: GETIMPORT R3 20; var3 = 0xAA17B702
      43 [-]: GETUPVAL R4 3; var4 = upvalues[3]
      44 [-]: GETTABLE R2 R3 R4; var2 = var3[var4]
      45 [-]: SETUPVAL R2 2; upvalues[2] = var2
      46 [-]: GETIMPORT R2 22; var2 = 0x7ED0A956
      47 [-]: LOADK R3 K23 ; var3 = "/Lotus/Types/Gameplay/Duviri/Encounters/CombatEncounters/ShrineAssembleCombatEncounter"
      48 [-]: CALL R2 2 2  ; var2 = var2(var3)
      49 [-]: GETUPVAL R4 5; var4 = upvalues[5]
      50 [-]: GETTABLEKS R3 R4 K24; var3 = var4[0x7CD635B1]
      51 [-]: GETUPVAL R4 1; var4 = upvalues[1]
      52 [-]: GETIMPORT R5 26; var5 = ZERO_ROTATION
      53 [-]: GETIMPORT R7 28; var7 = 0x7846E12C
      54 [-]: JUMPIFNOT R7 L5; goto L5 if not var7
      55 [-]: GETUPVAL R6 6; var6 = upvalues[6]
      56 [-]: JUMPIF R6 L6 ; goto L6 if var6
L 5:  57 [-]: MOVE R6 R0   ; var6 = var0
L 6:  58 [-]: GETIMPORT R7 30; var7 = 0x44FEEB71
      59 [-]: LOADB R8 1   ; var8 = true
      60 [-]: MOVE R9 R2   ; var9 = var2
      61 [-]: CALL R3 7 2  ; var3 = var3(var4, var5, var6, var7, var8, var9)
      62 [-]: SETUPVAL R3 4; upvalues[3] = var4
      63 [-]: GETUPVAL R4 4; var4 = upvalues[4]
      64 [-]: FASTCALL1 64 R4 L7; 
      65 [-]: GETIMPORT R3 8; var3 = 0x7B998233
      66 [-]: CALL R3 2 2  ; var3 = var3(var4)
L 7:  67 [-]: JUMPIF R3 L8 ; goto L8 if var3
      68 [-]: GETUPVAL R3 4; var3 = upvalues[4]
      69 [-]: LOADB R5 0   ; var5 = false
      70 [-]: NAMECALL R3 R3 K31; var4 = var3; var3 = var3[0xC942CCB5]
      71 [-]: CALL R3 3 1  ; var3(var4, var5)
      72 [-]: GETUPVAL R4 4; var4 = upvalues[4]
      73 [-]: GETTABLEKS R3 R4 K32; var3 = var4["OnStart"]
      74 [-]: GETUPVAL R4 4; var4 = upvalues[4]
      75 [-]: NEWCLOSURE R5 P0; 
      76 [-]: CAPTURE UPVAL U5; 
      77 [-]: CAPTURE UPVAL U7; 
      78 [-]: CAPTURE UPVAL U8; 
      79 [-]: CAPTURE UPVAL U9; 
      80 [-]: CAPTURE VAL R3; 
      81 [-]: CAPTURE UPVAL U4; 
      82 [-]: SETTABLEKS R5 R4 K32; var5["OnStart"] = var4
      83 [-]: GETUPVAL R5 5; var5 = upvalues[5]
      84 [-]: GETTABLEKS R4 R5 K33; var4 = var5[0x2FEE6764]
      85 [-]: GETUPVAL R6 4; var6 = upvalues[4]
      86 [-]: GETTABLEKS R5 R6 K34; var5 = var6["mShrine"]
      87 [-]: CALL R4 2 1  ; var4(var5)
      88 [-]: GETUPVAL R5 5; var5 = upvalues[5]
      89 [-]: GETTABLEKS R4 R5 K35; var4 = var5[0x1D009439]
      90 [-]: GETUPVAL R7 4; var7 = upvalues[4]
      91 [-]: GETTABLEKS R6 R7 K34; var6 = var7["mShrine"]
      92 [-]: NAMECALL R6 R6 K36; var7 = var6; var6 = var6[0xD1586535]
      93 [-]: CALL R6 2 2  ; var6 = var6(var7)
      94 [-]: GETIMPORT R7 38; var7 = 0xA421AF95
      95 [-]: LOADN R8 0   ; var8 = 0
      96 [-]: LOADN R9 2   ; var9 = 2
      97 [-]: LOADN R10 0  ; var10 = 0
      98 [-]: CALL R7 4 2  ; var7 = var7(var8, var9, var10)
      99 [-]: ADD R5 R6 R7 ; var5 = var6 + var7
     100 [-]: GETIMPORT R6 26; var6 = ZERO_ROTATION
     101 [-]: CALL R4 3 2  ; var4 = var4(var5, var6)
     102 [-]: SETUPVAL R4 10; upvalues[4] = var10
L 8: 103 [-]: RETURN R0 0  ; 


; Name:            
; Defined at line: 195
; #Upvalues:       2
; #Parameters:     0
; Is_vararg:       0
; Max Stack Size:  8

       0 [-]: GETUPVAL R1 0; var1 = upvalues[0]
       1 [-]: FASTCALL1 64 R1 L0; 
       2 [-]: GETIMPORT R0 1; var0 = 0x7B998233
       3 [-]: CALL R0 2 2  ; var0 = var0(var1)
L 0:   4 [-]: JUMPIF R0 L2 ; goto L2 if var0
       5 [-]: GETUPVAL R1 1; var1 = upvalues[1]
       6 [-]: GETTABLEKS R0 R1 K2; var0 = var1[0x732ECA87]
       7 [-]: GETIMPORT R1 4; var1 = 0xEF41F7FE
       8 [-]: LOADNIL R2   ; var2 = nil
       9 [-]: GETIMPORT R3 6; var3 = ZERO_VECTOR
      10 [-]: LOADN R4 2   ; var4 = 2
      11 [-]: LOADN R5 1   ; var5 = 1
      12 [-]: CALL R0 6 2  ; var0 = var0(var1, var2, var3, var4, var5)
      13 [-]: GETUPVAL R2 0; var2 = upvalues[0]
      14 [-]: GETTABLEKS R1 R2 K7; var1 = var2["mShrine"]
      15 [-]: NAMECALL R1 R1 K8; var2 = var1; var1 = var1[0xD1586535]
      16 [-]: CALL R1 2 2  ; var1 = var1(var2)
      17 [-]: GETUPVAL R3 0; var3 = upvalues[0]
      18 [-]: GETTABLEKS R2 R3 K7; var2 = var3["mShrine"]
      19 [-]: NAMECALL R2 R2 K9; var3 = var2; var2 = var2[0xCB3851B8]
      20 [-]: CALL R2 2 2  ; var2 = var2(var3)
      21 [-]: GETUPVAL R3 0; var3 = upvalues[0]
      22 [-]: NAMECALL R3 R3 K10; var4 = var3; var3 = var3[0xF596420F]
      23 [-]: CALL R3 2 1  ; var3(var4)
      24 [-]: GETIMPORT R3 12; var3 = 0x89326C93
      25 [-]: GETIMPORT R5 14; var5 = 0xE7545DFA
      26 [-]: MOVE R6 R1   ; var6 = var1
      27 [-]: MOVE R7 R2   ; var7 = var2
      28 [-]: NAMECALL R3 R3 K15; var4 = var3; var3 = var3[0x05909209]
      29 [-]: CALL R3 5 2  ; var3 = var3(var4, var5, var6, var7)
      30 [-]: FASTCALL1 64 R3 L1; 
      31 [-]: MOVE R5 R3   ; var5 = var3
      32 [-]: GETIMPORT R4 1; var4 = 0x7B998233
      33 [-]: CALL R4 2 2  ; var4 = var4(var5)
L 1:  34 [-]: JUMPIF R4 L2 ; goto L2 if var4
      35 [-]: MOVE R6 R3   ; var6 = var3
      36 [-]: GETIMPORT R7 17; var7 = EMPTY_SYMBOL
      37 [-]: NAMECALL R4 R0 K18; var5 = var0; var4 = var0[0xB6B094B2]
      38 [-]: CALL R4 4 1  ; var4(var5, var6, var7)
L 2:  39 [-]: RETURN R0 0  ; 


; Name:            
; Defined at line: 211
; #Upvalues:       6
; #Parameters:     0
; Is_vararg:       0
; Max Stack Size:  11

       0 [-]: LOADNIL R0   ; var0 = nil
       1 [-]: GETUPVAL R2 0; var2 = upvalues[0]
       2 [-]: FASTCALL1 64 R2 L0; 
       3 [-]: GETIMPORT R1 1; var1 = 0x7B998233
       4 [-]: CALL R1 2 2  ; var1 = var1(var2)
L 0:   5 [-]: JUMPIF R1 L2 ; goto L2 if var1
       6 [-]: GETUPVAL R3 0; var3 = upvalues[0]
       7 [-]: GETTABLEKS R2 R3 K2; var2 = var3["mShrine"]
       8 [-]: FASTCALL1 64 R2 L1; 
       9 [-]: GETIMPORT R1 1; var1 = 0x7B998233
      10 [-]: CALL R1 2 2  ; var1 = var1(var2)
L 1:  11 [-]: JUMPIF R1 L2 ; goto L2 if var1
      12 [-]: GETUPVAL R2 0; var2 = upvalues[0]
      13 [-]: GETTABLEKS R1 R2 K2; var1 = var2["mShrine"]
      14 [-]: NAMECALL R1 R1 K3; var2 = var1; var1 = var1[0xD1586535]
      15 [-]: CALL R1 2 2  ; var1 = var1(var2)
      16 [-]: MOVE R0 R1   ; var0 = var1
L 2:  17 [-]: GETUPVAL R1 1; var1 = upvalues[1]
      18 [-]: NAMECALL R1 R1 K4; var2 = var1; var1 = var1[0xA2880940]
      19 [-]: CALL R1 2 1  ; var1(var2)
      20 [-]: GETIMPORT R1 6; var1 = 0x89326C93
      21 [-]: GETIMPORT R3 8; var3 = 0x1F87C158
      22 [-]: GETIMPORT R5 10; var5 = 0xA421AF95
      23 [-]: LOADN R6 0   ; var6 = 0
      24 [-]: LOADK R7 K11 ; var7 = 1.75
      25 [-]: LOADN R8 0   ; var8 = 0
      26 [-]: CALL R5 4 2  ; var5 = var5(var6, var7, var8)
      27 [-]: ADD R4 R0 R5 ; var4 = var0 + var5
      28 [-]: GETIMPORT R5 13; var5 = ZERO_ROTATION
      29 [-]: GETUPVAL R6 2; var6 = upvalues[2]
      30 [-]: NAMECALL R1 R1 K14; var2 = var1; var1 = var1[0x05909209]
      31 [-]: CALL R1 6 2  ; var1 = var1(var2, var3, var4, var5, var6)
      32 [-]: GETIMPORT R4 16; var4 = 0x6363338F
      33 [-]: LOADB R5 0   ; var5 = false
      34 [-]: LOADB R6 0   ; var6 = false
      35 [-]: LOADN R7 0   ; var7 = 0
      36 [-]: GETIMPORT R8 18; var8 = EMPTY_SYMBOL
      37 [-]: NAMECALL R2 R1 K19; var3 = var1; var2 = var1[0x5D985C7E]
      38 [-]: CALL R2 7 2  ; var2 = var2(var3, var4, var5, var6, var7, var8)
      39 [-]: GETIMPORT R3 21; var3 = 0xCBD666E1
      40 [-]: ADDK R4 R2 K22; var4 = var2 + 1
      41 [-]: CALL R3 2 1  ; var3(var4)
      42 [-]: LOADN R5 1   ; var5 = 1
      43 [-]: NAMECALL R3 R1 K23; var4 = var1; var3 = var1[0x66472BF5]
      44 [-]: CALL R3 3 1  ; var3(var4, var5)
      45 [-]: GETUPVAL R4 3; var4 = upvalues[3]
      46 [-]: GETTABLEKS R3 R4 K24; var3 = var4["RemoveObjProgressBar"]
      47 [-]: CALL R3 1 1  ; var3()
      48 [-]: GETUPVAL R3 5; var3 = upvalues[5]
      49 [-]: GETIMPORT R5 26; var5 = 0x8837054C
      50 [-]: NAMECALL R6 R1 K3; var7 = var1; var6 = var1[0xD1586535]
      51 [-]: CALL R6 2 2  ; var6 = var6(var7)
      52 [-]: GETIMPORT R7 13; var7 = ZERO_ROTATION
      53 [-]: GETIMPORT R8 28; var8 = 0x0469F296
      54 [-]: LOADK R9 K29 ; var9 = "Duviri"
      55 [-]: CALL R8 2 0  ; var8, ... = var8(var9)
      56 [-]: NAMECALL R3 R3 K30; var4 = var3; var3 = var3[0x6CD833C5]
      57 [-]: CALL R3 0 2  ; var3 = var3(var4, ...)
      58 [-]: SETUPVAL R3 4; upvalues[3] = var4
      59 [-]: NAMECALL R3 R1 K4; var4 = var1; var3 = var1[0xA2880940]
      60 [-]: CALL R3 2 1  ; var3(var4)
      61 [-]: FASTCALL1 64 R0 L3; 
      62 [-]: MOVE R4 R0   ; var4 = var0
      63 [-]: GETIMPORT R3 1; var3 = 0x7B998233
      64 [-]: CALL R3 2 2  ; var3 = var3(var4)
L 3:  65 [-]: JUMPIF R3 L4 ; goto L4 if var3
      66 [-]: GETIMPORT R3 6; var3 = 0x89326C93
      67 [-]: GETIMPORT R5 32; var5 = 0xCF7CAC4D
      68 [-]: GETIMPORT R7 10; var7 = 0xA421AF95
      69 [-]: LOADN R8 0   ; var8 = 0
      70 [-]: LOADK R9 K11 ; var9 = 1.75
      71 [-]: LOADN R10 0  ; var10 = 0
      72 [-]: CALL R7 4 2  ; var7 = var7(var8, var9, var10)
      73 [-]: ADD R6 R0 R7 ; var6 = var0 + var7
      74 [-]: GETIMPORT R7 13; var7 = ZERO_ROTATION
      75 [-]: NAMECALL R3 R3 K14; var4 = var3; var3 = var3[0x05909209]
      76 [-]: CALL R3 5 1  ; var3(var4, var5, var6, var7)
L 4:  77 [-]: GETUPVAL R3 4; var3 = upvalues[4]
      78 [-]: JUMPIFNOT R3 L5; goto L5 if not var3
      79 [-]: GETUPVAL R3 2; var3 = upvalues[2]
      80 [-]: GETUPVAL R5 4; var5 = upvalues[4]
      81 [-]: NAMECALL R3 R3 K33; var4 = var3; var3 = var3[0x2FB0041C]
      82 [-]: CALL R3 3 1  ; var3(var4, var5)
      83 [-]: GETUPVAL R3 4; var3 = upvalues[4]
      84 [-]: NAMECALL R3 R3 K34; var4 = var3; var3 = var3[0x9E21E394]
      85 [-]: CALL R3 2 1  ; var3(var4)
L 5:  86 [-]: RETURN R0 0  ; 


; Name:            
; Defined at line: 248
; #Upvalues:       9
; #Parameters:     1
; Is_vararg:       0
; Max Stack Size:  10

       0 [-]: GETUPVAL R1 0; var1 = upvalues[0]
       1 [-]: MOVE R2 R0   ; var2 = var0
       2 [-]: CALL R1 2 1  ; var1(var2)
       3 [-]: LOADNIL R2   ; var2 = nil
       4 [-]: FASTCALL1 64 R2 L0; 
       5 [-]: GETIMPORT R1 1; var1 = 0x7B998233
       6 [-]: CALL R1 2 2  ; var1 = var1(var2)
L 0:   7 [-]: JUMPIF R1 L1 ; goto L1 if var1
       8 [-]: LOADNIL R1   ; var1 = nil
       9 [-]: NAMECALL R1 R1 K2; var2 = var1; var1 = var1[0xA2880940]
      10 [-]: CALL R1 2 1  ; var1(var2)
L 1:  11 [-]: GETUPVAL R2 1; var2 = upvalues[1]
      12 [-]: FASTCALL1 64 R2 L2; 
      13 [-]: GETIMPORT R1 1; var1 = 0x7B998233
      14 [-]: CALL R1 2 2  ; var1 = var1(var2)
L 2:  15 [-]: JUMPIF R1 L3 ; goto L3 if var1
      16 [-]: GETUPVAL R1 1; var1 = upvalues[1]
      17 [-]: NAMECALL R1 R1 K2; var2 = var1; var1 = var1[0xA2880940]
      18 [-]: CALL R1 2 1  ; var1(var2)
L 3:  19 [-]: NAMECALL R1 R0 K3; var2 = var0; var1 = var0[0x22DF603C]
      20 [-]: CALL R1 2 2  ; var1 = var1(var2)
      21 [-]: GETIMPORT R2 5; var2 = 0xC8802016
      22 [-]: MOVE R3 R1   ; var3 = var1
      23 [-]: CALL R2 2 4  ; var2, var3, var4 = var2(var3)
      24 [-]: FORGPREP_INEXT R2 L6; 
L 4:  25 [-]: FASTCALL1 64 R6 L5; 
      26 [-]: MOVE R8 R6   ; var8 = var6
      27 [-]: GETIMPORT R7 1; var7 = 0x7B998233
      28 [-]: CALL R7 2 2  ; var7 = var7(var8)
L 5:  29 [-]: JUMPIF R7 L6 ; goto L6 if var7
      30 [-]: NAMECALL R7 R6 K6; var8 = var6; var7 = var6[0xBB610E5B]
      31 [-]: CALL R7 2 2  ; var7 = var7(var8)
      32 [-]: NAMECALL R8 R7 K2; var9 = var7; var8 = var7[0xA2880940]
      33 [-]: CALL R8 2 1  ; var8(var9)
L 6:  34 [-]: FORGLOOP R2 L4 2 [inext]; 
      35 [-]: GETIMPORT R2 8; var2 = 0x7846E12C
      36 [-]: JUMPIFNOT R2 L8; goto L8 if not var2
      37 [-]: GETUPVAL R3 2; var3 = upvalues[2]
      38 [-]: FASTCALL1 64 R3 L7; 
      39 [-]: GETIMPORT R2 1; var2 = 0x7B998233
      40 [-]: CALL R2 2 2  ; var2 = var2(var3)
L 7:  41 [-]: JUMPIF R2 L8 ; goto L8 if var2
      42 [-]: GETUPVAL R2 2; var2 = upvalues[2]
      43 [-]: NAMECALL R2 R2 K2; var3 = var2; var2 = var2[0xA2880940]
      44 [-]: CALL R2 2 1  ; var2(var3)
L 8:  45 [-]: GETUPVAL R3 3; var3 = upvalues[3]
      46 [-]: GETTABLEKS R2 R3 K9; var2 = var3["ClearPrimaryObjText"]
      47 [-]: CALL R2 1 1  ; var2()
      48 [-]: GETUPVAL R3 3; var3 = upvalues[3]
      49 [-]: GETTABLEKS R2 R3 K10; var2 = var3["RemoveObjProgressBar"]
      50 [-]: CALL R2 1 1  ; var2()
      51 [-]: GETUPVAL R3 4; var3 = upvalues[4]
      52 [-]: GETTABLEKS R2 R3 K11; var2 = var3[0x3C2E4B8B]
      53 [-]: GETUPVAL R3 3; var3 = upvalues[3]
      54 [-]: CALL R2 2 1  ; var2(var3)
      55 [-]: GETUPVAL R3 4; var3 = upvalues[4]
      56 [-]: GETTABLEKS R2 R3 K12; var2 = var3[0x488B7465]
      57 [-]: GETUPVAL R3 5; var3 = upvalues[5]
      58 [-]: CALL R2 2 1  ; var2(var3)
      59 [-]: GETUPVAL R3 6; var3 = upvalues[6]
      60 [-]: FASTCALL1 64 R3 L9; 
      61 [-]: GETIMPORT R2 1; var2 = 0x7B998233
      62 [-]: CALL R2 2 2  ; var2 = var2(var3)
L 9:  63 [-]: JUMPIF R2 L10; goto L10 if var2
      64 [-]: GETUPVAL R3 4; var3 = upvalues[4]
      65 [-]: GETTABLEKS R2 R3 K13; var2 = var3[0x17F75CFC]
      66 [-]: GETUPVAL R4 6; var4 = upvalues[6]
      67 [-]: GETTABLEKS R3 R4 K14; var3 = var4["mShrine"]
      68 [-]: CALL R2 2 1  ; var2(var3)
L10:  69 [-]: GETIMPORT R2 17; var2 = _T["DebugPersistentSideActivities"]
      70 [-]: JUMPXEQKNIL R2 L11; 
      71 [-]: GETIMPORT R2 17; var2 = _T["DebugPersistentSideActivities"]
      72 [-]: JUMPIFNOT R2 L13; goto L13 if not var2
L11:  73 [-]: NAMECALL R2 R0 K18; var3 = var0; var2 = var0[0xEFE6CAD1]
      74 [-]: CALL R2 2 2  ; var2 = var2(var3)
      75 [-]: LOADN R3 4   ; var3 = 4
      76 [-]: JUMPIFNOTEQ R2 R3 L13; goto L13 if var2 ~= var459324
      77 [-]: GETUPVAL R2 7; var2 = upvalues[7]
      78 [-]: CALL R2 1 1  ; var2()
      79 [-]: MOVE R2 R0   ; var2 = var0
      80 [-]: GETIMPORT R3 8; var3 = 0x7846E12C
      81 [-]: JUMPIFNOT R3 L12; goto L12 if not var3
      82 [-]: GETUPVAL R2 8; var2 = upvalues[8]
L12:  83 [-]: NAMECALL R3 R2 K19; var4 = var2; var3 = var2[0xF4E253B6]
      84 [-]: CALL R3 2 1  ; var3(var4)
      85 [-]: RETURN R0 0  ; 
L13:  86 [-]: GETUPVAL R3 6; var3 = upvalues[6]
      87 [-]: FASTCALL1 64 R3 L14; 
      88 [-]: GETIMPORT R2 1; var2 = 0x7B998233
      89 [-]: CALL R2 2 2  ; var2 = var2(var3)
L14:  90 [-]: JUMPIF R2 L15; goto L15 if var2
      91 [-]: GETUPVAL R2 6; var2 = upvalues[6]
      92 [-]: NAMECALL R2 R2 K20; var3 = var2; var2 = var2[0xF596420F]
      93 [-]: CALL R2 2 1  ; var2(var3)
L15:  94 [-]: RETURN R0 0  ; 


; Name:            
; Defined at line: 300
; #Upvalues:       11
; #Parameters:     0
; Is_vararg:       0
; Max Stack Size:  6

       0 [-]: GETUPVAL R0 0; var0 = upvalues[0]
       1 [-]: NAMECALL R0 R0 K0; var1 = var0; var0 = var0[0x209398C2]
       2 [-]: CALL R0 2 2  ; var0 = var0(var1)
       3 [-]: GETUPVAL R2 1; var2 = upvalues[1]
       4 [-]: GETTABLEKS R1 R2 K1; var1 = var2["WAITING_NPC"]
       5 [-]: JUMPIFNOTEQ R0 R1 L0; goto L0 if var0 ~= var65571
       6 [-]: RETURN R0 0  ; 
L 0:   7 [-]: GETUPVAL R2 1; var2 = upvalues[1]
       8 [-]: GETTABLEKS R1 R2 K2; var1 = var2["STARTED"]
       9 [-]: JUMPIFNOTEQ R0 R1 L1; goto L1 if var0 ~= var131388
      10 [-]: GETUPVAL R1 2; var1 = upvalues[2]
      11 [-]: GETUPVAL R2 3; var2 = upvalues[3]
      12 [-]: CALL R1 2 1  ; var1(var2)
      13 [-]: RETURN R0 0  ; 
L 1:  14 [-]: GETUPVAL R2 1; var2 = upvalues[1]
      15 [-]: GETTABLEKS R1 R2 K3; var1 = var2["PORTAL_ACTIVE"]
      16 [-]: JUMPIFNOTEQ R0 R1 L5; goto L5 if var0 ~= var328225
      17 [-]: GETIMPORT R2 5; var2 = 0x89326C93
      18 [-]: FASTCALL1 64 R2 L2; 
      19 [-]: GETIMPORT R1 7; var1 = 0x7B998233
      20 [-]: CALL R1 2 2  ; var1 = var1(var2)
L 2:  21 [-]: JUMPIF R1 L4 ; goto L4 if var1
      22 [-]: GETIMPORT R1 5; var1 = 0x89326C93
      23 [-]: NAMECALL R1 R1 K8; var2 = var1; var1 = var1[0xFB64E76C]
      24 [-]: CALL R1 2 2  ; var1 = var1(var2)
      25 [-]: FASTCALL1 64 R1 L3; 
      26 [-]: MOVE R3 R1   ; var3 = var1
      27 [-]: GETIMPORT R2 7; var2 = 0x7B998233
      28 [-]: CALL R2 2 2  ; var2 = var2(var3)
L 3:  29 [-]: JUMPIF R2 L4 ; goto L4 if var2
      30 [-]: GETIMPORT R2 5; var2 = 0x89326C93
      31 [-]: NAMECALL R2 R2 K9; var3 = var2; var2 = var2[0x18D05D30]
      32 [-]: CALL R2 2 2  ; var2 = var2(var3)
      33 [-]: JUMPIFNOT R2 L4; goto L4 if not var2
      34 [-]: GETIMPORT R4 11; var4 = 0x0469F296
      35 [-]: LOADK R5 K12 ; var5 = "DUVIRI_MINIGAME_PLAYED"
      36 [-]: CALL R4 2 2  ; var4 = var4(var5)
      37 [-]: LOADK R5 K13 ; var5 = "ShrineAssembleEncounter"
      38 [-]: NAMECALL R2 R1 K14; var3 = var1; var2 = var1[0x7802279D]
      39 [-]: CALL R2 4 1  ; var2(var3, var4, var5)
L 4:  40 [-]: GETUPVAL R2 4; var2 = upvalues[4]
      41 [-]: GETTABLEKS R1 R2 K15; var1 = var2["SetPrimaryObjText"]
      42 [-]: LOADK R2 K16 ; var2 = "/Lotus/Language/Duviri/ShrineAssembleGoal"
      43 [-]: CALL R1 2 1  ; var1(var2)
      44 [-]: GETUPVAL R2 4; var2 = upvalues[4]
      45 [-]: GETTABLEKS R1 R2 K17; var1 = var2["SetObjProgressBar"]
      46 [-]: LOADK R2 K18 ; var2 = "/Lotus/Language/Duviri/ShrineAssembleCounter"
      47 [-]: GETUPVAL R3 5; var3 = upvalues[5]
      48 [-]: GETUPVAL R4 6; var4 = upvalues[6]
      49 [-]: CALL R1 4 1  ; var1(var2, var3, var4)
      50 [-]: RETURN R0 0  ; 
L 5:  51 [-]: GETUPVAL R2 1; var2 = upvalues[1]
      52 [-]: GETTABLEKS R1 R2 K19; var1 = var2["BOSS_STATE"]
      53 [-]: JUMPIFNOTEQ R0 R1 L9; goto L9 if var0 ~= var262716
      54 [-]: GETUPVAL R2 4; var2 = upvalues[4]
      55 [-]: GETTABLEKS R1 R2 K15; var1 = var2["SetPrimaryObjText"]
      56 [-]: LOADK R2 K20 ; var2 = "/Lotus/Language/Duviri/ShrineAssembleBoss"
      57 [-]: CALL R1 2 1  ; var1(var2)
      58 [-]: GETUPVAL R1 7; var1 = upvalues[7]
      59 [-]: GETUPVAL R2 3; var2 = upvalues[3]
      60 [-]: CALL R1 2 1  ; var1(var2)
      61 [-]: GETIMPORT R2 22; var2 = 0xD5779F64
      62 [-]: FASTCALL1 64 R2 L6; 
      63 [-]: GETIMPORT R1 7; var1 = 0x7B998233
      64 [-]: CALL R1 2 2  ; var1 = var1(var2)
L 6:  65 [-]: JUMPIF R1 L8 ; goto L8 if var1
      66 [-]: GETUPVAL R2 8; var2 = upvalues[8]
      67 [-]: FASTCALL1 64 R2 L7; 
      68 [-]: GETIMPORT R1 7; var1 = 0x7B998233
      69 [-]: CALL R1 2 2  ; var1 = var1(var2)
L 7:  70 [-]: JUMPIF R1 L8 ; goto L8 if var1
      71 [-]: GETUPVAL R2 8; var2 = upvalues[8]
      72 [-]: GETTABLEKS R1 R2 K23; var1 = var2["mShrine"]
      73 [-]: GETIMPORT R3 22; var3 = 0xD5779F64
      74 [-]: LOADB R4 0   ; var4 = false
      75 [-]: NAMECALL R1 R1 K24; var2 = var1; var1 = var1[0x659D451F]
      76 [-]: CALL R1 4 1  ; var1(var2, var3, var4)
L 8:  77 [-]: GETUPVAL R1 9; var1 = upvalues[9]
      78 [-]: CALL R1 1 1  ; var1()
      79 [-]: RETURN R0 0  ; 
L 9:  80 [-]: GETUPVAL R2 1; var2 = upvalues[1]
      81 [-]: GETTABLEKS R1 R2 K25; var1 = var2["COMPLETE"]
      82 [-]: JUMPIFNOTEQ R0 R1 L26; goto L26 if var0 ~= var328225
      83 [-]: GETIMPORT R2 5; var2 = 0x89326C93
      84 [-]: FASTCALL1 64 R2 L10; 
      85 [-]: GETIMPORT R1 7; var1 = 0x7B998233
      86 [-]: CALL R1 2 2  ; var1 = var1(var2)
L10:  87 [-]: JUMPIF R1 L12; goto L12 if var1
      88 [-]: GETIMPORT R1 5; var1 = 0x89326C93
      89 [-]: NAMECALL R1 R1 K8; var2 = var1; var1 = var1[0xFB64E76C]
      90 [-]: CALL R1 2 2  ; var1 = var1(var2)
      91 [-]: FASTCALL1 64 R1 L11; 
      92 [-]: MOVE R3 R1   ; var3 = var1
      93 [-]: GETIMPORT R2 7; var2 = 0x7B998233
      94 [-]: CALL R2 2 2  ; var2 = var2(var3)
L11:  95 [-]: JUMPIF R2 L12; goto L12 if var2
      96 [-]: GETIMPORT R2 5; var2 = 0x89326C93
      97 [-]: NAMECALL R2 R2 K9; var3 = var2; var2 = var2[0x18D05D30]
      98 [-]: CALL R2 2 2  ; var2 = var2(var3)
      99 [-]: JUMPIFNOT R2 L12; goto L12 if not var2
     100 [-]: GETIMPORT R4 11; var4 = 0x0469F296
     101 [-]: LOADK R5 K26 ; var5 = "DUVIRI_MINIGAME_COMPLETE"
     102 [-]: CALL R4 2 2  ; var4 = var4(var5)
     103 [-]: LOADK R5 K13 ; var5 = "ShrineAssembleEncounter"
     104 [-]: NAMECALL R2 R1 K14; var3 = var1; var2 = var1[0x7802279D]
     105 [-]: CALL R2 4 1  ; var2(var3, var4, var5)
L12: 106 [-]: GETUPVAL R2 8; var2 = upvalues[8]
     107 [-]: FASTCALL1 64 R2 L13; 
     108 [-]: GETIMPORT R1 7; var1 = 0x7B998233
     109 [-]: CALL R1 2 2  ; var1 = var1(var2)
L13: 110 [-]: JUMPIF R1 L21; goto L21 if var1
     111 [-]: GETUPVAL R3 8; var3 = upvalues[8]
     112 [-]: GETTABLEKS R2 R3 K23; var2 = var3["mShrine"]
     113 [-]: FASTCALL1 64 R2 L14; 
     114 [-]: GETIMPORT R1 7; var1 = 0x7B998233
     115 [-]: CALL R1 2 2  ; var1 = var1(var2)
L14: 116 [-]: JUMPIF R1 L21; goto L21 if var1
     117 [-]: GETIMPORT R2 28; var2 = 0xB3136ED2
     118 [-]: FASTCALL1 64 R2 L15; 
     119 [-]: GETIMPORT R1 7; var1 = 0x7B998233
     120 [-]: CALL R1 2 2  ; var1 = var1(var2)
L15: 121 [-]: JUMPIF R1 L16; goto L16 if var1
     122 [-]: GETUPVAL R2 8; var2 = upvalues[8]
     123 [-]: GETTABLEKS R1 R2 K23; var1 = var2["mShrine"]
     124 [-]: GETIMPORT R3 28; var3 = 0xB3136ED2
     125 [-]: LOADB R4 0   ; var4 = false
     126 [-]: NAMECALL R1 R1 K24; var2 = var1; var1 = var1[0x659D451F]
     127 [-]: CALL R1 4 1  ; var1(var2, var3, var4)
L16: 128 [-]: GETIMPORT R2 30; var2 = 0x0ED2C1F0
     129 [-]: FASTCALL1 64 R2 L17; 
     130 [-]: GETIMPORT R1 7; var1 = 0x7B998233
     131 [-]: CALL R1 2 2  ; var1 = var1(var2)
L17: 132 [-]: JUMPIF R1 L18; goto L18 if var1
     133 [-]: GETUPVAL R2 8; var2 = upvalues[8]
     134 [-]: GETTABLEKS R1 R2 K23; var1 = var2["mShrine"]
     135 [-]: GETIMPORT R3 30; var3 = 0x0ED2C1F0
     136 [-]: LOADB R4 1   ; var4 = true
     137 [-]: LOADB R5 0   ; var5 = false
     138 [-]: NAMECALL R1 R1 K31; var2 = var1; var1 = var1[0x5D985C7E]
     139 [-]: CALL R1 5 1  ; var1(var2, var3, var4, var5)
L18: 140 [-]: GETUPVAL R3 8; var3 = upvalues[8]
     141 [-]: GETTABLEKS R2 R3 K23; var2 = var3["mShrine"]
     142 [-]: FASTCALL1 64 R2 L19; 
     143 [-]: GETIMPORT R1 7; var1 = 0x7B998233
     144 [-]: CALL R1 2 2  ; var1 = var1(var2)
L19: 145 [-]: JUMPIF R1 L21; goto L21 if var1
     146 [-]: GETIMPORT R2 33; var2 = 0x8D1E3BF2
     147 [-]: FASTCALL1 64 R2 L20; 
     148 [-]: GETIMPORT R1 7; var1 = 0x7B998233
     149 [-]: CALL R1 2 2  ; var1 = var1(var2)
L20: 150 [-]: JUMPIF R1 L21; goto L21 if var1
     151 [-]: GETUPVAL R2 8; var2 = upvalues[8]
     152 [-]: GETTABLEKS R1 R2 K23; var1 = var2["mShrine"]
     153 [-]: GETIMPORT R3 33; var3 = 0x8D1E3BF2
     154 [-]: LOADB R4 0   ; var4 = false
     155 [-]: LOADB R5 1   ; var5 = true
     156 [-]: NAMECALL R1 R1 K31; var2 = var1; var1 = var1[0x5D985C7E]
     157 [-]: CALL R1 5 1  ; var1(var2, var3, var4, var5)
L21: 158 [-]: GETUPVAL R2 3; var2 = upvalues[3]
     159 [-]: FASTCALL1 64 R2 L22; 
     160 [-]: GETIMPORT R1 7; var1 = 0x7B998233
     161 [-]: CALL R1 2 2  ; var1 = var1(var2)
L22: 162 [-]: JUMPIF R1 L23; goto L23 if var1
     163 [-]: GETUPVAL R1 3; var1 = upvalues[3]
     164 [-]: LOADNIL R3   ; var3 = nil
     165 [-]: NAMECALL R1 R1 K34; var2 = var1; var1 = var1[0x97680C06]
     166 [-]: CALL R1 3 1  ; var1(var2, var3)
     167 [-]: GETUPVAL R1 3; var1 = upvalues[3]
     168 [-]: LOADN R3 4   ; var3 = 4
     169 [-]: NAMECALL R1 R1 K35; var2 = var1; var1 = var1[0xFE9DC265]
     170 [-]: CALL R1 3 1  ; var1(var2, var3)
L23: 171 [-]: GETIMPORT R1 37; var1 = 0x7846E12C
     172 [-]: JUMPIF R1 L24; goto L24 if var1
     173 [-]: GETUPVAL R2 10; var2 = upvalues[10]
     174 [-]: GETTABLEKS R1 R2 K38; var1 = var2[0xE6574978]
     175 [-]: CALL R1 1 1  ; var1()
L24: 176 [-]: GETUPVAL R3 8; var3 = upvalues[8]
     177 [-]: GETTABLEKS R2 R3 K23; var2 = var3["mShrine"]
     178 [-]: FASTCALL1 64 R2 L25; 
     179 [-]: GETIMPORT R1 7; var1 = 0x7B998233
     180 [-]: CALL R1 2 2  ; var1 = var1(var2)
L25: 181 [-]: JUMPIF R1 L27; goto L27 if var1
     182 [-]: GETUPVAL R2 10; var2 = upvalues[10]
     183 [-]: GETTABLEKS R1 R2 K39; var1 = var2[0xDCB808FC]
     184 [-]: GETUPVAL R3 8; var3 = upvalues[8]
     185 [-]: GETTABLEKS R2 R3 K23; var2 = var3["mShrine"]
     186 [-]: NAMECALL R2 R2 K40; var3 = var2; var2 = var2[0xF6EBD926]
     187 [-]: CALL R2 2 0  ; var2, ... = var2(var3)
     188 [-]: CALL R1 0 1  ; var1(var2, ...)
     189 [-]: RETURN R0 0  ; 
L26: 190 [-]: GETUPVAL R2 1; var2 = upvalues[1]
     191 [-]: GETTABLEKS R1 R2 K41; var1 = var2["FAIL"]
     192 [-]: JUMPIFNOTEQ R0 R1 L27; goto L27 if var0 ~= var196924
     193 [-]: GETUPVAL R1 3; var1 = upvalues[3]
     194 [-]: LOADN R3 5   ; var3 = 5
     195 [-]: NAMECALL R1 R1 K35; var2 = var1; var1 = var1[0xFE9DC265]
     196 [-]: CALL R1 3 1  ; var1(var2, var3)
L27: 197 [-]: RETURN R0 0  ; 


; Name:            
; Defined at line: 368
; #Upvalues:       8
; #Parameters:     0
; Is_vararg:       0
; Max Stack Size:  9

       0 [-]: GETUPVAL R1 0; var1 = upvalues[0]
       1 [-]: FASTCALL1 64 R1 L0; 
       2 [-]: GETIMPORT R0 1; var0 = 0x7B998233
       3 [-]: CALL R0 2 2  ; var0 = var0(var1)
L 0:   4 [-]: JUMPIF R0 L2 ; goto L2 if var0
       5 [-]: GETUPVAL R2 0; var2 = upvalues[0]
       6 [-]: GETTABLEKS R1 R2 K2; var1 = var2["mShrine"]
       7 [-]: FASTCALL1 64 R1 L1; 
       8 [-]: GETIMPORT R0 1; var0 = 0x7B998233
       9 [-]: CALL R0 2 2  ; var0 = var0(var1)
L 1:  10 [-]: JUMPIFNOT R0 L3; goto L3 if not var0
L 2:  11 [-]: RETURN R0 0  ; 
L 3:  12 [-]: GETUPVAL R1 1; var1 = upvalues[1]
      13 [-]: ADDK R0 R1 K3; var0 = var1 + 1
      14 [-]: SETUPVAL R0 1; upvalues[0] = var1
      15 [-]: GETIMPORT R0 5; var0 = 0xCBD666E1
      16 [-]: LOADN R1 2   ; var1 = 2
      17 [-]: CALL R0 2 1  ; var0(var1)
      18 [-]: GETUPVAL R1 2; var1 = upvalues[2]
      19 [-]: FASTCALL1 64 R1 L4; 
      20 [-]: GETIMPORT R0 1; var0 = 0x7B998233
      21 [-]: CALL R0 2 2  ; var0 = var0(var1)
L 4:  22 [-]: JUMPIFNOT R0 L5; goto L5 if not var0
      23 [-]: GETIMPORT R0 7; var0 = 0x89326C93
      24 [-]: GETIMPORT R2 9; var2 = 0x27AFD835
      25 [-]: GETUPVAL R5 0; var5 = upvalues[0]
      26 [-]: GETTABLEKS R4 R5 K2; var4 = var5["mShrine"]
      27 [-]: NAMECALL R4 R4 K10; var5 = var4; var4 = var4[0xD1586535]
      28 [-]: CALL R4 2 2  ; var4 = var4(var5)
      29 [-]: GETIMPORT R5 12; var5 = 0xA421AF95
      30 [-]: LOADN R6 0   ; var6 = 0
      31 [-]: LOADN R7 2   ; var7 = 2
      32 [-]: LOADN R8 0   ; var8 = 0
      33 [-]: CALL R5 4 2  ; var5 = var5(var6, var7, var8)
      34 [-]: ADD R3 R4 R5 ; var3 = var4 + var5
      35 [-]: GETIMPORT R4 14; var4 = ZERO_ROTATION
      36 [-]: GETUPVAL R5 3; var5 = upvalues[3]
      37 [-]: NAMECALL R0 R0 K15; var1 = var0; var0 = var0[0x05909209]
      38 [-]: CALL R0 6 2  ; var0 = var0(var1, var2, var3, var4, var5)
      39 [-]: SETUPVAL R0 2; upvalues[0] = var2
L 5:  40 [-]: GETUPVAL R1 0; var1 = upvalues[0]
      41 [-]: GETTABLEKS R0 R1 K2; var0 = var1["mShrine"]
      42 [-]: GETIMPORT R2 17; var2 = 0x7692800D
      43 [-]: LOADB R3 0   ; var3 = false
      44 [-]: NAMECALL R0 R0 K18; var1 = var0; var0 = var0[0x659D451F]
      45 [-]: CALL R0 4 1  ; var0(var1, var2, var3)
      46 [-]: GETUPVAL R0 2; var0 = upvalues[2]
      47 [-]: LOADK R3 K19 ; var3 = 0.25
      48 [-]: GETUPVAL R4 1; var4 = upvalues[1]
      49 [-]: MUL R2 R3 R4 ; var2 = var3 * var4
      50 [-]: NAMECALL R0 R0 K20; var1 = var0; var0 = var0[0x2D9BA74F]
      51 [-]: CALL R0 3 1  ; var0(var1, var2)
      52 [-]: GETUPVAL R1 4; var1 = upvalues[4]
      53 [-]: GETTABLEKS R0 R1 K21; var0 = var1["SetObjProgressBar"]
      54 [-]: LOADK R1 K22 ; var1 = "/Lotus/Language/Duviri/ShrineAssembleCounter"
      55 [-]: GETUPVAL R2 1; var2 = upvalues[1]
      56 [-]: GETUPVAL R3 5; var3 = upvalues[5]
      57 [-]: CALL R0 4 1  ; var0(var1, var2, var3)
      58 [-]: GETUPVAL R0 1; var0 = upvalues[1]
      59 [-]: GETUPVAL R1 5; var1 = upvalues[5]
      60 [-]: JUMPIFNOTLE R1 R0 L6; goto L6 if var1 > var393276
      61 [-]: GETUPVAL R0 6; var0 = upvalues[6]
      62 [-]: GETUPVAL R3 7; var3 = upvalues[7]
      63 [-]: GETTABLEKS R2 R3 K23; var2 = var3["BOSS_STATE"]
      64 [-]: NAMECALL R0 R0 K24; var1 = var0; var0 = var0[0x8ABFF40E]
      65 [-]: CALL R0 3 1  ; var0(var1, var2)
L 6:  66 [-]: RETURN R0 0  ; 


; Name:            
; Defined at line: 401
; #Upvalues:       5
; #Parameters:     2
; Is_vararg:       0
; Max Stack Size:  9

       0 [-]: LOADNIL R2   ; var2 = nil
       1 [-]: FASTCALL1 64 R0 L0; 
       2 [-]: MOVE R4 R0   ; var4 = var0
       3 [-]: GETIMPORT R3 1; var3 = 0x7B998233
       4 [-]: CALL R3 2 2  ; var3 = var3(var4)
L 0:   5 [-]: JUMPIF R3 L7 ; goto L7 if var3
       6 [-]: NAMECALL R3 R0 K2; var4 = var0; var3 = var0[0xDE321E6F]
       7 [-]: CALL R3 2 2  ; var3 = var3(var4)
       8 [-]: GETUPVAL R4 0; var4 = upvalues[0]
       9 [-]: NAMECALL R6 R0 K3; var7 = var0; var6 = var0[0xD1586535]
      10 [-]: CALL R6 2 2  ; var6 = var6(var7)
      11 [-]: GETUPVAL R7 1; var7 = upvalues[1]
      12 [-]: NAMECALL R4 R4 K4; var5 = var4; var4 = var4[0xAC64DA9C]
      13 [-]: CALL R4 4 2  ; var4 = var4(var5, var6, var7)
      14 [-]: FASTCALL1 64 R3 L1; 
      15 [-]: MOVE R6 R3   ; var6 = var3
      16 [-]: GETIMPORT R5 1; var5 = 0x7B998233
      17 [-]: CALL R5 2 2  ; var5 = var5(var6)
L 1:  18 [-]: JUMPIF R5 L2 ; goto L2 if var5
      19 [-]: NAMECALL R5 R3 K5; var6 = var3; var5 = var3[0x487B4AAE]
      20 [-]: CALL R5 2 2  ; var5 = var5(var6)
      21 [-]: MOVE R2 R5   ; var2 = var5
L 2:  22 [-]: FASTCALL1 64 R2 L3; 
      23 [-]: MOVE R6 R2   ; var6 = var2
      24 [-]: GETIMPORT R5 1; var5 = 0x7B998233
      25 [-]: CALL R5 2 2  ; var5 = var5(var6)
L 3:  26 [-]: JUMPIF R5 L7 ; goto L7 if var5
      27 [-]: GETIMPORT R7 7; var7 = 0xD9F921DA
      28 [-]: NAMECALL R5 R2 K8; var6 = var2; var5 = var2[0xF2DEAF69]
      29 [-]: CALL R5 3 2  ; var5 = var5(var6, var7)
      30 [-]: JUMPIFNOT R5 L7; goto L7 if not var5
      31 [-]: LOADN R5 2   ; var5 = 2
      32 [-]: JUMPIFNOTLT R4 R5 L7; goto L7 if var4 >= var132668
      33 [-]: GETUPVAL R6 2; var6 = upvalues[2]
      34 [-]: ADDK R5 R6 K9; var5 = var6 + 1
      35 [-]: SETUPVAL R5 2; upvalues[5] = var2
      36 [-]: GETIMPORT R7 7; var7 = 0xD9F921DA
      37 [-]: NAMECALL R5 R3 K10; var6 = var3; var5 = var3[0x40A5B7AF]
      38 [-]: CALL R5 3 1  ; var5(var6, var7)
      39 [-]: GETUPVAL R6 3; var6 = upvalues[3]
      40 [-]: FASTCALL1 64 R6 L4; 
      41 [-]: GETIMPORT R5 1; var5 = 0x7B998233
      42 [-]: CALL R5 2 2  ; var5 = var5(var6)
L 4:  43 [-]: JUMPIF R5 L6 ; goto L6 if var5
      44 [-]: GETIMPORT R6 12; var6 = 0x7692800D
      45 [-]: FASTCALL1 64 R6 L5; 
      46 [-]: GETIMPORT R5 1; var5 = 0x7B998233
      47 [-]: CALL R5 2 2  ; var5 = var5(var6)
L 5:  48 [-]: JUMPIF R5 L6 ; goto L6 if var5
      49 [-]: GETUPVAL R6 3; var6 = upvalues[3]
      50 [-]: GETTABLEKS R5 R6 K13; var5 = var6["mShrine"]
      51 [-]: GETIMPORT R7 12; var7 = 0x7692800D
      52 [-]: LOADB R8 0   ; var8 = false
      53 [-]: NAMECALL R5 R5 K14; var6 = var5; var5 = var5[0x659D451F]
      54 [-]: CALL R5 4 1  ; var5(var6, var7, var8)
L 6:  55 [-]: GETUPVAL R5 4; var5 = upvalues[4]
      56 [-]: CALL R5 1 1  ; var5()
L 7:  57 [-]: RETURN R0 0  ; 


; Name:            
; Defined at line: 431
; #Upvalues:       25
; #Parameters:     1
; Is_vararg:       0
; Max Stack Size:  12

       0 [-]: LOADN R1 0   ; var1 = 0
       1 [-]: SETUPVAL R1 0; upvalues[1] = var0
       2 [-]: NAMECALL R1 R0 K0; var2 = var0; var1 = var0[0xED4E0128]
       3 [-]: CALL R1 2 2  ; var1 = var1(var2)
       4 [-]: GETIMPORT R2 2; var2 = 0x3D106989
       5 [-]: LOADK R4 K3  ; var4 = "Starting encounter script on object "
       6 [-]: MOVE R5 R1   ; var5 = var1
       7 [-]: CONCAT R3 R4 R5; var3 = var4 .. var5
       8 [-]: CALL R2 2 1  ; var2(var3)
       9 [-]: GETIMPORT R2 5; var2 = 0x89326C93
      10 [-]: NAMECALL R2 R2 K6; var3 = var2; var2 = var2[0x29EF273D]
      11 [-]: CALL R2 2 2  ; var2 = var2(var3)
      12 [-]: NAMECALL R2 R2 K7; var3 = var2; var2 = var2[0x66905CB0]
      13 [-]: CALL R2 2 2  ; var2 = var2(var3)
      14 [-]: SETUPVAL R2 1; upvalues[2] = var1
L 0:  15 [-]: GETUPVAL R2 1; var2 = upvalues[1]
      16 [-]: NAMECALL R2 R2 K8; var3 = var2; var2 = var2[0xA2D83ED4]
      17 [-]: CALL R2 2 2  ; var2 = var2(var3)
      18 [-]: JUMPIF R2 L1 ; goto L1 if var2
      19 [-]: GETIMPORT R2 10; var2 = 0xCBD666E1
      20 [-]: LOADN R3 0   ; var3 = 0
      21 [-]: CALL R2 2 1  ; var2(var3)
      22 [-]: JUMPBACK L0  ; goto L0
L 1:  23 [-]: GETIMPORT R2 12; var2 = 0xBE190284
      24 [-]: SETUPVAL R2 2; upvalues[2] = var2
      25 [-]: SETUPVAL R0 3; upvalues[0] = var3
      26 [-]: NAMECALL R2 R0 K13; var3 = var0; var2 = var0[0x891629FA]
      27 [-]: CALL R2 2 2  ; var2 = var2(var3)
      28 [-]: SETUPVAL R2 4; upvalues[2] = var4
      29 [-]: NAMECALL R2 R0 K14; var3 = var0; var2 = var0[0xD1586535]
      30 [-]: CALL R2 2 2  ; var2 = var2(var3)
      31 [-]: SETUPVAL R2 5; upvalues[2] = var5
      32 [-]: NAMECALL R2 R0 K15; var3 = var0; var2 = var0[0xC5B92518]
      33 [-]: CALL R2 2 2  ; var2 = var2(var3)
      34 [-]: SETUPVAL R2 6; upvalues[2] = var6
      35 [-]: NAMECALL R2 R0 K16; var3 = var0; var2 = var0[0x7C97B143]
      36 [-]: CALL R2 2 2  ; var2 = var2(var3)
      37 [-]: SETUPVAL R2 7; upvalues[2] = var7
      38 [-]: NAMECALL R2 R0 K17; var3 = var0; var2 = var0[0x4C976EDA]
      39 [-]: CALL R2 2 2  ; var2 = var2(var3)
      40 [-]: NAMECALL R2 R2 K18; var3 = var2; var2 = var2[0xE4C355E2]
      41 [-]: CALL R2 2 2  ; var2 = var2(var3)
      42 [-]: SETUPVAL R2 8; upvalues[2] = var8
      43 [-]: GETIMPORT R2 5; var2 = 0x89326C93
      44 [-]: LOADK R4 K19 ; var4 = "OnPlayersChanged"
      45 [-]: NAMECALL R2 R2 K20; var3 = var2; var2 = var2[0xB7D33840]
      46 [-]: CALL R2 3 1  ; var2(var3, var4)
      47 [-]: GETIMPORT R2 5; var2 = 0x89326C93
      48 [-]: NAMECALL R2 R2 K21; var3 = var2; var2 = var2[0x7D108DDB]
      49 [-]: CALL R2 2 2  ; var2 = var2(var3)
      50 [-]: SETUPVAL R2 9; upvalues[2] = var9
      51 [-]: GETIMPORT R2 23; var2 = 0x42DCC9F5
      52 [-]: GETIMPORT R3 5; var3 = 0x89326C93
      53 [-]: NAMECALL R3 R3 K24; var4 = var3; var3 = var3[0x61BE252A]
      54 [-]: CALL R3 2 2  ; var3 = var3(var4)
      55 [-]: LOADN R4 1   ; var4 = 1
      56 [-]: LOADN R5 4   ; var5 = 4
      57 [-]: CALL R2 4 2  ; var2 = var2(var3, var4, var5)
      58 [-]: SETUPVAL R2 10; upvalues[2] = var10
      59 [-]: GETIMPORT R3 26; var3 = 0xF8ADCD3D
      60 [-]: GETUPVAL R4 10; var4 = upvalues[10]
      61 [-]: GETTABLE R2 R3 R4; var2 = var3[var4]
      62 [-]: SETUPVAL R2 11; upvalues[2] = var11
      63 [-]: GETUPVAL R3 13; var3 = upvalues[13]
      64 [-]: GETTABLEKS R2 R3 K27; var2 = var3[0xC9013731]
      65 [-]: GETUPVAL R3 14; var3 = upvalues[14]
      66 [-]: GETUPVAL R4 3; var4 = upvalues[3]
      67 [-]: NEWTABLE R5 0 2; var5 = {}
      68 [-]: GETUPVAL R6 15; var6 = upvalues[15]
      69 [-]: GETUPVAL R7 16; var7 = upvalues[16]
      70 [-]: SETLIST R5 R6 2 [1]; var5[1] = var6; var5[2] = var7; var5[3] = var8; 
      71 [-]: CALL R2 4 2  ; var2 = var2(var3, var4, var5)
      72 [-]: SETUPVAL R2 12; upvalues[2] = var12
      73 [-]: GETUPVAL R3 18; var3 = upvalues[18]
      74 [-]: GETTABLEKS R2 R3 K28; var2 = var3[0xDE474187]
      75 [-]: CALL R2 1 2  ; var2 = var2()
      76 [-]: SETUPVAL R2 17; upvalues[2] = var17
      77 [-]: GETIMPORT R2 5; var2 = 0x89326C93
      78 [-]: GETIMPORT R4 30; var4 = 0x0469F296
      79 [-]: LOADK R5 K31 ; var5 = "ShrineAssembleHintWP"
      80 [-]: CALL R4 2 2  ; var4 = var4(var5)
      81 [-]: GETUPVAL R5 5; var5 = upvalues[5]
      82 [-]: LOADN R6 0   ; var6 = 0
      83 [-]: GETUPVAL R7 6; var7 = upvalues[6]
      84 [-]: NAMECALL R2 R2 K32; var3 = var2; var2 = var2[0x462C251C]
      85 [-]: CALL R2 6 2  ; var2 = var2(var3, var4, var5, var6, var7)
      86 [-]: FASTCALL1 64 R2 L2; 
      87 [-]: MOVE R4 R2   ; var4 = var2
      88 [-]: GETIMPORT R3 34; var3 = 0x7B998233
      89 [-]: CALL R3 2 2  ; var3 = var3(var4)
L 2:  90 [-]: JUMPIF R3 L3 ; goto L3 if var3
      91 [-]: NAMECALL R3 R2 K14; var4 = var2; var3 = var2[0xD1586535]
      92 [-]: CALL R3 2 2  ; var3 = var3(var4)
      93 [-]: SETUPVAL R3 5; upvalues[3] = var5
L 3:  94 [-]: GETIMPORT R3 36; var3 = 0x7846E12C
      95 [-]: JUMPIF R3 L4 ; goto L4 if var3
      96 [-]: GETUPVAL R4 19; var4 = upvalues[19]
      97 [-]: GETTABLEKS R3 R4 K37; var3 = var4[0xCAF8A8D0]
      98 [-]: MOVE R4 R0   ; var4 = var0
      99 [-]: GETIMPORT R5 39; var5 = 0x4A092DC6
     100 [-]: CALL R3 3 1  ; var3(var4, var5)
     101 [-]: GETUPVAL R3 3; var3 = upvalues[3]
     102 [-]: GETUPVAL R5 3; var5 = upvalues[3]
     103 [-]: NAMECALL R5 R5 K17; var6 = var5; var5 = var5[0x4C976EDA]
     104 [-]: CALL R5 2 0  ; var5, ... = var5(var6)
     105 [-]: NAMECALL R3 R3 K40; var4 = var3; var3 = var3[0x97680C06]
     106 [-]: CALL R3 0 1  ; var3(var4, ...)
     107 [-]: JUMP L7      ; goto L7
L 4: 108 [-]: GETUPVAL R4 21; var4 = upvalues[21]
     109 [-]: GETTABLEKS R3 R4 K41; var3 = var4[0xD97DB38D]
     110 [-]: GETUPVAL R4 5; var4 = upvalues[5]
     111 [-]: CALL R3 2 2  ; var3 = var3(var4)
     112 [-]: SETUPVAL R3 20; upvalues[3] = var20
     113 [-]: GETUPVAL R4 20; var4 = upvalues[20]
     114 [-]: FASTCALL1 64 R4 L5; 
     115 [-]: GETIMPORT R3 34; var3 = 0x7B998233
     116 [-]: CALL R3 2 2  ; var3 = var3(var4)
L 5: 117 [-]: JUMPIF R3 L6 ; goto L6 if var3
     118 [-]: GETUPVAL R3 20; var3 = upvalues[20]
     119 [-]: NAMECALL R3 R3 K42; var4 = var3; var3 = var3[0xA2880940]
     120 [-]: CALL R3 2 1  ; var3(var4)
L 6: 121 [-]: GETUPVAL R3 3; var3 = upvalues[3]
     122 [-]: NAMECALL R3 R3 K17; var4 = var3; var3 = var3[0x4C976EDA]
     123 [-]: CALL R3 2 2  ; var3 = var3(var4)
     124 [-]: GETUPVAL R5 21; var5 = upvalues[21]
     125 [-]: GETTABLEKS R4 R5 K43; var4 = var5[0x78686162]
     126 [-]: NAMECALL R5 R3 K44; var6 = var3; var5 = var3[0xAA1950D4]
     127 [-]: CALL R5 2 2  ; var5 = var5(var6)
     128 [-]: GETUPVAL R7 5; var7 = upvalues[5]
     129 [-]: GETIMPORT R8 46; var8 = 0xA421AF95
     130 [-]: LOADN R9 0   ; var9 = 0
     131 [-]: LOADN R10 3  ; var10 = 3
     132 [-]: LOADN R11 0  ; var11 = 0
     133 [-]: CALL R8 4 2  ; var8 = var8(var9, var10, var11)
     134 [-]: ADD R6 R7 R8 ; var6 = var7 + var8
     135 [-]: LOADB R7 0   ; var7 = false
     136 [-]: LOADB R8 0   ; var8 = false
     137 [-]: CALL R4 5 2  ; var4 = var4(var5, var6, var7, var8)
     138 [-]: SETUPVAL R4 20; upvalues[4] = var20
L 7: 139 [-]: GETUPVAL R4 19; var4 = upvalues[19]
     140 [-]: GETTABLEKS R3 R4 K47; var3 = var4[0x1944F6A6]
     141 [-]: MOVE R4 R0   ; var4 = var0
     142 [-]: CALL R3 2 2  ; var3 = var3(var4)
     143 [-]: SETUPVAL R3 22; upvalues[3] = var22
     144 [-]: GETUPVAL R3 4; var3 = upvalues[4]
     145 [-]: LOADK R5 K48 ; var5 = "OnAgentRegistered"
     146 [-]: GETIMPORT R6 30; var6 = 0x0469F296
     147 [-]: LOADK R7 K49 ; var7 = "ShrineAssembleRegistration"
     148 [-]: CALL R6 2 2  ; var6 = var6(var7)
     149 [-]: LOADB R7 1   ; var7 = true
     150 [-]: NAMECALL R3 R3 K50; var4 = var3; var3 = var3[0x5B344F44]
     151 [-]: CALL R3 5 1  ; var3(var4, var5, var6, var7)
     152 [-]: GETIMPORT R3 5; var3 = 0x89326C93
     153 [-]: GETIMPORT R5 30; var5 = 0x0469F296
     154 [-]: LOADK R6 K51 ; var6 = "MissionObject"
     155 [-]: CALL R5 2 0  ; var5, ... = var5(var6)
     156 [-]: NAMECALL R3 R3 K52; var4 = var3; var3 = var3[0x46A0EBF5]
     157 [-]: CALL R3 0 2  ; var3 = var3(var4, ...)
     158 [-]: SETUPVAL R3 23; upvalues[3] = var23
     159 [-]: GETUPVAL R4 23; var4 = upvalues[23]
     160 [-]: FASTCALL1 64 R4 L8; 
     161 [-]: GETIMPORT R3 34; var3 = 0x7B998233
     162 [-]: CALL R3 2 2  ; var3 = var3(var4)
L 8: 163 [-]: JUMPIFNOT R3 L9; goto L9 if not var3
     164 [-]: GETIMPORT R3 5; var3 = 0x89326C93
     165 [-]: GETIMPORT R5 54; var5 = 0x3F3E58E9
     166 [-]: GETIMPORT R6 56; var6 = ZERO_VECTOR
     167 [-]: GETIMPORT R7 58; var7 = ZERO_ROTATION
     168 [-]: NAMECALL R3 R3 K59; var4 = var3; var3 = var3[0x05909209]
     169 [-]: CALL R3 5 2  ; var3 = var3(var4, var5, var6, var7)
     170 [-]: SETUPVAL R3 23; upvalues[3] = var23
L 9: 171 [-]: GETUPVAL R4 13; var4 = upvalues[13]
     172 [-]: GETTABLEKS R3 R4 K60; var3 = var4[0x29A7C917]
     173 [-]: MOVE R4 R0   ; var4 = var0
     174 [-]: CALL R3 2 2  ; var3 = var3(var4)
     175 [-]: SETUPVAL R3 24; upvalues[3] = var24
     176 [-]: LOADN R5 2   ; var5 = 2
     177 [-]: NAMECALL R3 R0 K61; var4 = var0; var3 = var0[0xFE9DC265]
     178 [-]: CALL R3 3 1  ; var3(var4, var5)
     179 [-]: RETURN R0 0  ; 


; Name:            
; Defined at line: 497
; #Upvalues:       4
; #Parameters:     1
; Is_vararg:       0
; Max Stack Size:  5

       0 [-]: GETIMPORT R1 1; var1 = 0x3D106989
       1 [-]: LOADK R2 K2  ; var2 = "Shutting down"
       2 [-]: CALL R1 2 1  ; var1(var2)
       3 [-]: GETUPVAL R1 0; var1 = upvalues[0]
       4 [-]: MOVE R2 R0   ; var2 = var0
       5 [-]: CALL R1 2 1  ; var1(var2)
       6 [-]: GETUPVAL R1 1; var1 = upvalues[1]
       7 [-]: GETIMPORT R3 4; var3 = 0x0469F296
       8 [-]: LOADK R4 K5  ; var4 = "ShrineAssembleRegistration"
       9 [-]: CALL R3 2 0  ; var3, ... = var3(var4)
      10 [-]: NAMECALL R1 R1 K6; var2 = var1; var1 = var1[0x11D6DE31]
      11 [-]: CALL R1 0 1  ; var1(var2, ...)
      12 [-]: GETUPVAL R2 2; var2 = upvalues[2]
      13 [-]: FASTCALL1 64 R2 L0; 
      14 [-]: GETIMPORT R1 8; var1 = 0x7B998233
      15 [-]: CALL R1 2 2  ; var1 = var1(var2)
L 0:  16 [-]: JUMPIF R1 L1 ; goto L1 if var1
      17 [-]: GETUPVAL R2 3; var2 = upvalues[3]
      18 [-]: GETTABLEKS R1 R2 K9; var1 = var2[0x5655B468]
      19 [-]: MOVE R2 R0   ; var2 = var0
      20 [-]: GETUPVAL R3 2; var3 = upvalues[2]
      21 [-]: CALL R1 3 1  ; var1(var2, var3)
L 1:  22 [-]: RETURN R0 0  ; 


; Name:            
; Defined at line: 511
; #Upvalues:       8
; #Parameters:     1
; Is_vararg:       0
; Max Stack Size:  8

       0 [-]: GETUPVAL R1 0; var1 = upvalues[0]
       1 [-]: MOVE R2 R0   ; var2 = var0
       2 [-]: CALL R1 2 1  ; var1(var2)
       3 [-]: LOADN R1 0   ; var1 = 0
       4 [-]: GETUPVAL R3 1; var3 = upvalues[1]
       5 [-]: GETTABLEKS R2 R3 K0; var2 = var3["INVALID"]
       6 [-]: GETIMPORT R4 2; var4 = 0x89326C93
       7 [-]: FASTCALL1 64 R4 L0; 
       8 [-]: GETIMPORT R3 4; var3 = 0x7B998233
       9 [-]: CALL R3 2 2  ; var3 = var3(var4)
L 0:  10 [-]: JUMPIF R3 L3 ; goto L3 if var3
      11 [-]: GETUPVAL R4 2; var4 = upvalues[2]
      12 [-]: FASTCALL1 64 R4 L1; 
      13 [-]: GETIMPORT R3 4; var3 = 0x7B998233
      14 [-]: CALL R3 2 2  ; var3 = var3(var4)
L 1:  15 [-]: JUMPIF R3 L3 ; goto L3 if var3
      16 [-]: FASTCALL1 64 R0 L2; 
      17 [-]: MOVE R4 R0   ; var4 = var0
      18 [-]: GETIMPORT R3 4; var3 = 0x7B998233
      19 [-]: CALL R3 2 2  ; var3 = var3(var4)
L 2:  20 [-]: JUMPIFNOT R3 L4; goto L4 if not var3
L 3:  21 [-]: RETURN R0 0  ; 
L 4:  22 [-]: GETUPVAL R3 2; var3 = upvalues[2]
      23 [-]: GETUPVAL R6 1; var6 = upvalues[1]
      24 [-]: GETTABLEKS R5 R6 K5; var5 = var6["STARTED"]
      25 [-]: NAMECALL R3 R3 K6; var4 = var3; var3 = var3[0x8ABFF40E]
      26 [-]: CALL R3 3 1  ; var3(var4, var5)
L 5:  27 [-]: NAMECALL R3 R0 K7; var4 = var0; var3 = var0[0xEFE6CAD1]
      28 [-]: CALL R3 2 2  ; var3 = var3(var4)
      29 [-]: LOADN R4 4   ; var4 = 4
      30 [-]: JUMPIFNOTLT R3 R4 L19; goto L19 if var3 >= var590625
      31 [-]: GETIMPORT R3 9; var3 = 0xFFF641AF
      32 [-]: CALL R3 1 2  ; var3 = var3()
      33 [-]: MOVE R1 R3   ; var1 = var3
      34 [-]: GETUPVAL R3 2; var3 = upvalues[2]
      35 [-]: NAMECALL R3 R3 K10; var4 = var3; var3 = var3[0x209398C2]
      36 [-]: CALL R3 2 2  ; var3 = var3(var4)
      37 [-]: MOVE R2 R3   ; var2 = var3
      38 [-]: GETUPVAL R4 1; var4 = upvalues[1]
      39 [-]: GETTABLEKS R3 R4 K5; var3 = var4["STARTED"]
      40 [-]: JUMPIFNOTEQ R2 R3 L8; goto L8 if var2 ~= var197692
      41 [-]: GETUPVAL R4 3; var4 = upvalues[3]
      42 [-]: FASTCALL1 64 R4 L6; 
      43 [-]: GETIMPORT R3 4; var3 = 0x7B998233
      44 [-]: CALL R3 2 2  ; var3 = var3(var4)
L 6:  45 [-]: JUMPIF R3 L16; goto L16 if var3
      46 [-]: GETUPVAL R5 3; var5 = upvalues[3]
      47 [-]: GETTABLEKS R4 R5 K11; var4 = var5["mShrine"]
      48 [-]: FASTCALL1 64 R4 L7; 
      49 [-]: GETIMPORT R3 4; var3 = 0x7B998233
      50 [-]: CALL R3 2 2  ; var3 = var3(var4)
L 7:  51 [-]: JUMPIF R3 L16; goto L16 if var3
      52 [-]: GETUPVAL R3 3; var3 = upvalues[3]
      53 [-]: MOVE R5 R1   ; var5 = var1
      54 [-]: NAMECALL R3 R3 K12; var4 = var3; var3 = var3[0xFAA69527]
      55 [-]: CALL R3 3 1  ; var3(var4, var5)
      56 [-]: JUMP L16     ; goto L16
L 8:  57 [-]: GETUPVAL R4 1; var4 = upvalues[1]
      58 [-]: GETTABLEKS R3 R4 K13; var3 = var4["PORTAL_ACTIVE"]
      59 [-]: JUMPIFNOTEQ R2 R3 L15; goto L15 if var2 ~= var197692
      60 [-]: GETUPVAL R4 3; var4 = upvalues[3]
      61 [-]: FASTCALL1 64 R4 L9; 
      62 [-]: GETIMPORT R3 4; var3 = 0x7B998233
      63 [-]: CALL R3 2 2  ; var3 = var3(var4)
L 9:  64 [-]: JUMPIF R3 L16; goto L16 if var3
      65 [-]: GETUPVAL R5 3; var5 = upvalues[3]
      66 [-]: GETTABLEKS R4 R5 K11; var4 = var5["mShrine"]
      67 [-]: FASTCALL1 64 R4 L10; 
      68 [-]: GETIMPORT R3 4; var3 = 0x7B998233
      69 [-]: CALL R3 2 2  ; var3 = var3(var4)
L10:  70 [-]: JUMPIF R3 L16; goto L16 if var3
      71 [-]: GETUPVAL R4 4; var4 = upvalues[4]
      72 [-]: FASTCALL1 64 R4 L11; 
      73 [-]: GETIMPORT R3 4; var3 = 0x7B998233
      74 [-]: CALL R3 2 2  ; var3 = var3(var4)
L11:  75 [-]: JUMPIF R3 L14; goto L14 if var3
      76 [-]: GETIMPORT R4 2; var4 = 0x89326C93
      77 [-]: NAMECALL R4 R4 K14; var5 = var4; var4 = var4[0x29EF273D]
      78 [-]: CALL R4 2 0  ; var4, ... = var4(var5)
      79 [-]: FASTCALL 64 L12; 
      80 [-]: GETIMPORT R3 4; var3 = 0x7B998233
      81 [-]: CALL R3 0 2  ; var3 = var3(var4, ...)
L12:  82 [-]: JUMPIF R3 L14; goto L14 if var3
      83 [-]: GETUPVAL R4 4; var4 = upvalues[4]
      84 [-]: NAMECALL R4 R4 K15; var5 = var4; var4 = var4[0xC8450AEF]
      85 [-]: CALL R4 2 2  ; var4 = var4(var5)
      86 [-]: GETIMPORT R5 17; var5 = 0x9BA7909F
      87 [-]: LOADK R7 K18 ; var7 = "Server.NumVirtualTestClients"
      88 [-]: NAMECALL R5 R5 K19; var6 = var5; var5 = var5[0x8151451D]
      89 [-]: CALL R5 3 2  ; var5 = var5(var6, var7)
      90 [-]: ADD R3 R4 R5 ; var3 = var4 + var5
      91 [-]: SETUPVAL R3 5; upvalues[3] = var5
      92 [-]: GETUPVAL R3 5; var3 = upvalues[5]
      93 [-]: LOADN R4 1   ; var4 = 1
      94 [-]: JUMPIFNOTLE R4 R3 L13; goto L13 if var4 > var328508
      95 [-]: GETUPVAL R3 5; var3 = upvalues[5]
      96 [-]: LOADN R4 4   ; var4 = 4
      97 [-]: JUMPIFLE R3 R4 L14; goto L14 if var3 <= var1377057
L13:  98 [-]: GETIMPORT R3 21; var3 = 0x3D106989
      99 [-]: LOADK R5 K22 ; var5 = "Warning: mNumPlayersInHint is invalid ("
     100 [-]: GETUPVAL R6 5; var6 = upvalues[5]
     101 [-]: LOADK R7 K23 ; var7 = "), assuming 1 so we won't crash"
     102 [-]: CONCAT R4 R5 R7; var4 = var5 .. var7
     103 [-]: CALL R3 2 1  ; var3(var4)
     104 [-]: LOADN R3 1   ; var3 = 1
     105 [-]: SETUPVAL R3 5; upvalues[3] = var5
L14: 106 [-]: GETUPVAL R3 3; var3 = upvalues[3]
     107 [-]: MOVE R5 R1   ; var5 = var1
     108 [-]: NAMECALL R3 R3 K12; var4 = var3; var3 = var3[0xFAA69527]
     109 [-]: CALL R3 3 1  ; var3(var4, var5)
     110 [-]: JUMP L16     ; goto L16
L15: 111 [-]: GETUPVAL R4 1; var4 = upvalues[1]
     112 [-]: GETTABLEKS R3 R4 K24; var3 = var4["COMPLETE"]
     113 [-]: JUMPIFNOTEQ R2 R3 L16; goto L16 if var2 ~= var394044
L16: 114 [-]: GETUPVAL R3 6; var3 = upvalues[6]
     115 [-]: MOVE R5 R1   ; var5 = var1
     116 [-]: NAMECALL R3 R3 K12; var4 = var3; var3 = var3[0xFAA69527]
     117 [-]: CALL R3 3 1  ; var3(var4, var5)
     118 [-]: GETIMPORT R3 26; var3 = 0x7846E12C
     119 [-]: JUMPIF R3 L17; goto L17 if var3
     120 [-]: NAMECALL R3 R0 K27; var4 = var0; var3 = var0[0xD9531187]
     121 [-]: CALL R3 2 2  ; var3 = var3(var4)
     122 [-]: JUMPIFNOT R3 L17; goto L17 if not var3
     123 [-]: GETIMPORT R3 21; var3 = 0x3D106989
     124 [-]: LOADK R4 K28 ; var4 = "Hint ShouldShutDown received"
     125 [-]: CALL R3 2 1  ; var3(var4)
     126 [-]: LOADN R5 5   ; var5 = 5
     127 [-]: NAMECALL R3 R0 K29; var4 = var0; var3 = var0[0xFE9DC265]
     128 [-]: CALL R3 3 1  ; var3(var4, var5)
L17: 129 [-]: GETIMPORT R3 26; var3 = 0x7846E12C
     130 [-]: JUMPIFNOT R3 L18; goto L18 if not var3
     131 [-]: GETIMPORT R3 32; var3 = _T["RespawnInProgress"]
     132 [-]: JUMPIFNOT R3 L18; goto L18 if not var3
     133 [-]: GETUPVAL R3 2; var3 = upvalues[2]
     134 [-]: GETUPVAL R6 1; var6 = upvalues[1]
     135 [-]: GETTABLEKS R5 R6 K33; var5 = var6["FAIL"]
     136 [-]: NAMECALL R3 R3 K6; var4 = var3; var3 = var3[0x8ABFF40E]
     137 [-]: CALL R3 3 1  ; var3(var4, var5)
L18: 138 [-]: GETIMPORT R3 35; var3 = 0xCBD666E1
     139 [-]: LOADN R4 0   ; var4 = 0
     140 [-]: CALL R3 2 1  ; var3(var4)
     141 [-]: JUMPBACK L5  ; goto L5
L19: 142 [-]: GETUPVAL R4 4; var4 = upvalues[4]
     143 [-]: FASTCALL1 64 R4 L20; 
     144 [-]: GETIMPORT R3 4; var3 = 0x7B998233
     145 [-]: CALL R3 2 2  ; var3 = var3(var4)
L20: 146 [-]: JUMPIFNOT R3 L21; goto L21 if not var3
     147 [-]: RETURN R0 0  ; 
L21: 148 [-]: GETUPVAL R3 7; var3 = upvalues[7]
     149 [-]: MOVE R4 R0   ; var4 = var0
     150 [-]: CALL R3 2 1  ; var3(var4)
     151 [-]: GETUPVAL R3 2; var3 = upvalues[2]
     152 [-]: NAMECALL R3 R3 K36; var4 = var3; var3 = var3[0x588ED000]
     153 [-]: CALL R3 2 1  ; var3(var4)
     154 [-]: RETURN R0 0  ; 


; Name:            
; Defined at line: 577
; #Upvalues:       0
; #Parameters:     0
; Is_vararg:       0
; Max Stack Size:  0

       0 [-]: RETURN R0 0  ; 


; Name:            
; Defined at line: 581
; #Upvalues:       0
; #Parameters:     1
; Is_vararg:       0
; Max Stack Size:  5

       0 [-]: NAMECALL R1 R0 K0; var2 = var0; var1 = var0[0xBB610E5B]
       1 [-]: CALL R1 2 2  ; var1 = var1(var2)
       2 [-]: GETIMPORT R2 2; var2 = 0x11A19C5E
       3 [-]: MOVE R3 R1   ; var3 = var1
       4 [-]: LOADK R4 K3  ; var4 = "OnKilled"
       5 [-]: CALL R2 3 1  ; var2(var3, var4)
       6 [-]: RETURN R0 0  ; 


; Name:            
; Defined at line: 589
; #Upvalues:       7
; #Parameters:     1
; Is_vararg:       0
; Max Stack Size:  10

       0 [-]: GETUPVAL R2 0; var2 = upvalues[0]
       1 [-]: FASTCALL1 64 R2 L0; 
       2 [-]: GETIMPORT R1 1; var1 = 0x7B998233
       3 [-]: CALL R1 2 2  ; var1 = var1(var2)
L 0:   4 [-]: JUMPIF R1 L8 ; goto L8 if var1
       5 [-]: GETUPVAL R1 0; var1 = upvalues[0]
       6 [-]: NAMECALL R1 R1 K2; var2 = var1; var1 = var1[0x209398C2]
       7 [-]: CALL R1 2 2  ; var1 = var1(var2)
       8 [-]: FASTCALL1 64 R0 L1; 
       9 [-]: MOVE R3 R0   ; var3 = var0
      10 [-]: GETIMPORT R2 1; var2 = 0x7B998233
      11 [-]: CALL R2 2 2  ; var2 = var2(var3)
L 1:  12 [-]: JUMPIF R2 L8 ; goto L8 if var2
      13 [-]: GETUPVAL R3 1; var3 = upvalues[1]
      14 [-]: GETTABLEKS R2 R3 K3; var2 = var3["PORTAL_ACTIVE"]
      15 [-]: JUMPIFNOTEQ R1 R2 L7; goto L7 if var1 ~= var131900
      16 [-]: GETUPVAL R3 2; var3 = upvalues[2]
      17 [-]: ADDK R2 R3 K4; var2 = var3 + 1
      18 [-]: SETUPVAL R2 2; upvalues[2] = var2
      19 [-]: GETUPVAL R2 3; var2 = upvalues[3]
      20 [-]: LOADN R3 3   ; var3 = 3
      21 [-]: GETUPVAL R4 3; var4 = upvalues[3]
      22 [-]: LOADN R5 1   ; var5 = 1
      23 [-]: JUMPIFNOTLE R5 R4 L2; goto L2 if var5 > var197692
      24 [-]: GETUPVAL R4 3; var4 = upvalues[3]
      25 [-]: LOADN R5 4   ; var5 = 4
      26 [-]: JUMPIFNOTLE R4 R5 L2; goto L2 if var4 > var394273
      27 [-]: GETIMPORT R4 6; var4 = 0xF8ADCD3D
      28 [-]: GETUPVAL R5 3; var5 = upvalues[3]
      29 [-]: GETTABLE R3 R4 R5; var3 = var4[var5]
L 2:  30 [-]: GETUPVAL R6 2; var6 = upvalues[2]
      31 [-]: SUBK R5 R6 K4; var5 = var6 - 1
      32 [-]: MOD R4 R5 R3 ; var4 = var5 var3
      33 [-]: JUMPXEQKN R4 K7 L8 NOT; 
      34 [-]: GETUPVAL R4 4; var4 = upvalues[4]
      35 [-]: GETUPVAL R5 5; var5 = upvalues[5]
      36 [-]: JUMPIFNOTLT R4 R5 L8; goto L8 if var4 >= var889193548
      37 [-]: NAMECALL R4 R0 K8; var5 = var0; var4 = var0[0xD1586535]
      38 [-]: CALL R4 2 2  ; var4 = var4(var5)
      39 [-]: GETUPVAL R6 6; var6 = upvalues[6]
      40 [-]: FASTCALL1 64 R6 L3; 
      41 [-]: GETIMPORT R5 1; var5 = 0x7B998233
      42 [-]: CALL R5 2 2  ; var5 = var5(var6)
L 3:  43 [-]: JUMPIF R5 L6 ; goto L6 if var5
      44 [-]: GETIMPORT R5 10; var5 = 0x89326C93
      45 [-]: GETIMPORT R7 12; var7 = 0x3F3E58E9
      46 [-]: MOVE R8 R4   ; var8 = var4
      47 [-]: GETIMPORT R9 14; var9 = ZERO_ROTATION
      48 [-]: NAMECALL R5 R5 K15; var6 = var5; var5 = var5[0x05909209]
      49 [-]: CALL R5 5 2  ; var5 = var5(var6, var7, var8, var9)
      50 [-]: FASTCALL1 64 R5 L4; 
      51 [-]: MOVE R7 R5   ; var7 = var5
      52 [-]: GETIMPORT R6 1; var6 = 0x7B998233
      53 [-]: CALL R6 2 2  ; var6 = var6(var7)
L 4:  54 [-]: JUMPIF R6 L5 ; goto L5 if var6
      55 [-]: GETIMPORT R6 17; var6 = 0x11A19C5E
      56 [-]: MOVE R7 R5   ; var7 = var5
      57 [-]: LOADK R8 K18 ; var8 = "OnPickedUp"
      58 [-]: CALL R6 3 1  ; var6(var7, var8)
L 5:  59 [-]: GETUPVAL R6 6; var6 = upvalues[6]
      60 [-]: MOVE R8 R5   ; var8 = var5
      61 [-]: NAMECALL R6 R6 K19; var7 = var6; var6 = var6[0x21DFC654]
      62 [-]: CALL R6 3 1  ; var6(var7, var8)
L 6:  63 [-]: GETUPVAL R5 4; var5 = upvalues[4]
      64 [-]: ADDK R4 R5 K4; var4 = var5 + 1
      65 [-]: SETUPVAL R4 4; upvalues[4] = var4
      66 [-]: RETURN R0 0  ; 
L 7:  67 [-]: GETUPVAL R3 1; var3 = upvalues[1]
      68 [-]: GETTABLEKS R2 R3 K20; var2 = var3["BOSS_STATE"]
      69 [-]: JUMPIFNOTEQ R1 R2 L8; goto L8 if var1 ~= var2130707020
      70 [-]: NAMECALL R2 R0 K21; var3 = var0; var2 = var0[0xFA9E477F]
      71 [-]: CALL R2 2 2  ; var2 = var2(var3)
      72 [-]: GETIMPORT R4 23; var4 = 0x8837054C
      73 [-]: NAMECALL R2 R2 K24; var3 = var2; var2 = var2[0xF2DEAF69]
      74 [-]: CALL R2 3 2  ; var2 = var2(var3, var4)
      75 [-]: JUMPIFNOT R2 L8; goto L8 if not var2
      76 [-]: GETIMPORT R2 26; var2 = 0xCBD666E1
      77 [-]: LOADN R3 2   ; var3 = 2
      78 [-]: CALL R2 2 1  ; var2(var3)
      79 [-]: GETUPVAL R2 0; var2 = upvalues[0]
      80 [-]: GETUPVAL R5 1; var5 = upvalues[1]
      81 [-]: GETTABLEKS R4 R5 K27; var4 = var5["COMPLETE"]
      82 [-]: NAMECALL R2 R2 K28; var3 = var2; var2 = var2[0x8ABFF40E]
      83 [-]: CALL R2 3 1  ; var2(var3, var4)
L 8:  84 [-]: RETURN R0 0  ; 


; Name:            
; Defined at line: 618
; #Upvalues:       3
; #Parameters:     1
; Is_vararg:       0
; Max Stack Size:  14

       0 [-]: GETIMPORT R1 1; var1 = 0x89326C93
       1 [-]: GETIMPORT R3 3; var3 = 0x27AFD835
       2 [-]: NAMECALL R5 R0 K4; var6 = var0; var5 = var0[0xD1586535]
       3 [-]: CALL R5 2 2  ; var5 = var5(var6)
       4 [-]: GETIMPORT R6 6; var6 = 0xA421AF95
       5 [-]: LOADN R7 0   ; var7 = 0
       6 [-]: LOADK R8 K7  ; var8 = 1.75
       7 [-]: LOADN R9 0   ; var9 = 0
       8 [-]: CALL R6 4 2  ; var6 = var6(var7, var8, var9)
       9 [-]: ADD R4 R5 R6 ; var4 = var5 + var6
      10 [-]: GETIMPORT R5 9; var5 = ZERO_ROTATION
      11 [-]: GETUPVAL R6 0; var6 = upvalues[0]
      12 [-]: NAMECALL R1 R1 K10; var2 = var1; var1 = var1[0x05909209]
      13 [-]: CALL R1 6 2  ; var1 = var1(var2, var3, var4, var5, var6)
      14 [-]: FASTCALL1 64 R1 L0; 
      15 [-]: MOVE R3 R1   ; var3 = var1
      16 [-]: GETIMPORT R2 12; var2 = 0x7B998233
      17 [-]: CALL R2 2 2  ; var2 = var2(var3)
L 0:  18 [-]: JUMPIF R2 L1 ; goto L1 if var2
      19 [-]: GETIMPORT R4 14; var4 = 0xDFB90504
      20 [-]: LOADB R5 1   ; var5 = true
      21 [-]: LOADB R6 0   ; var6 = false
      22 [-]: NAMECALL R2 R1 K15; var3 = var1; var2 = var1[0x5D985C7E]
      23 [-]: CALL R2 5 1  ; var2(var3, var4, var5, var6)
L 1:  24 [-]: LOADNIL R2   ; var2 = nil
      25 [-]: GETIMPORT R3 1; var3 = 0x89326C93
      26 [-]: NAMECALL R3 R3 K16; var4 = var3; var3 = var3[0x7D108DDB]
      27 [-]: CALL R3 2 2  ; var3 = var3(var4)
      28 [-]: GETIMPORT R4 18; var4 = 0xCFC01047
      29 [-]: MOVE R5 R3   ; var5 = var3
      30 [-]: CALL R4 2 4  ; var4, var5, var6 = var4(var5)
      31 [-]: FORGPREP_NEXT R4 L7; 
L 2:  32 [-]: FASTCALL1 64 R8 L3; 
      33 [-]: MOVE R10 R8  ; var10 = var8
      34 [-]: GETIMPORT R9 12; var9 = 0x7B998233
      35 [-]: CALL R9 2 2  ; var9 = var9(var10)
L 3:  36 [-]: JUMPIF R9 L7 ; goto L7 if var9
      37 [-]: NAMECALL R9 R8 K19; var10 = var8; var9 = var8[0xBB610E5B]
      38 [-]: CALL R9 2 2  ; var9 = var9(var10)
      39 [-]: FASTCALL1 64 R9 L4; 
      40 [-]: MOVE R11 R9  ; var11 = var9
      41 [-]: GETIMPORT R10 12; var10 = 0x7B998233
      42 [-]: CALL R10 2 2 ; var10 = var10(var11)
L 4:  43 [-]: JUMPIF R10 L7; goto L7 if var10
      44 [-]: NAMECALL R10 R9 K20; var11 = var9; var10 = var9[0xDE321E6F]
      45 [-]: CALL R10 2 2 ; var10 = var10(var11)
      46 [-]: FASTCALL1 64 R10 L5; 
      47 [-]: MOVE R12 R10 ; var12 = var10
      48 [-]: GETIMPORT R11 12; var11 = 0x7B998233
      49 [-]: CALL R11 2 2 ; var11 = var11(var12)
L 5:  50 [-]: JUMPIF R11 L7; goto L7 if var11
      51 [-]: NAMECALL R11 R10 K21; var12 = var10; var11 = var10[0x487B4AAE]
      52 [-]: CALL R11 2 2 ; var11 = var11(var12)
      53 [-]: MOVE R2 R11  ; var2 = var11
      54 [-]: FASTCALL1 64 R2 L6; 
      55 [-]: MOVE R12 R2  ; var12 = var2
      56 [-]: GETIMPORT R11 12; var11 = 0x7B998233
      57 [-]: CALL R11 2 2 ; var11 = var11(var12)
L 6:  58 [-]: JUMPIF R11 L7; goto L7 if var11
      59 [-]: GETIMPORT R13 23; var13 = 0xD9F921DA
      60 [-]: NAMECALL R11 R2 K24; var12 = var2; var11 = var2[0xF2DEAF69]
      61 [-]: CALL R11 3 2 ; var11 = var11(var12, var13)
      62 [-]: JUMPIFNOT R11 L7; goto L7 if not var11
      63 [-]: GETIMPORT R13 23; var13 = 0xD9F921DA
      64 [-]: NAMECALL R11 R10 K25; var12 = var10; var11 = var10[0x40A5B7AF]
      65 [-]: CALL R11 3 1 ; var11(var12, var13)
      66 [-]: JUMP L8      ; goto L8
L 7:  67 [-]: FORGLOOP R4 L2 2; 
L 8:  68 [-]: FASTCALL1 64 R1 L9; 
      69 [-]: MOVE R5 R1   ; var5 = var1
      70 [-]: GETIMPORT R4 12; var4 = 0x7B998233
      71 [-]: CALL R4 2 2  ; var4 = var4(var5)
L 9:  72 [-]: JUMPIF R4 L10; goto L10 if var4
      73 [-]: GETIMPORT R6 27; var6 = 0x019A3924
      74 [-]: LOADB R7 0   ; var7 = false
      75 [-]: LOADB R8 1   ; var8 = true
      76 [-]: NAMECALL R4 R1 K15; var5 = var1; var4 = var1[0x5D985C7E]
      77 [-]: CALL R4 5 1  ; var4(var5, var6, var7, var8)
L10:  78 [-]: GETUPVAL R5 1; var5 = upvalues[1]
      79 [-]: FASTCALL1 64 R5 L11; 
      80 [-]: GETIMPORT R4 12; var4 = 0x7B998233
      81 [-]: CALL R4 2 2  ; var4 = var4(var5)
L11:  82 [-]: JUMPIF R4 L13; goto L13 if var4
      83 [-]: GETUPVAL R6 1; var6 = upvalues[1]
      84 [-]: GETTABLEKS R5 R6 K28; var5 = var6["mShrine"]
      85 [-]: FASTCALL1 64 R5 L12; 
      86 [-]: GETIMPORT R4 12; var4 = 0x7B998233
      87 [-]: CALL R4 2 2  ; var4 = var4(var5)
L12:  88 [-]: JUMPIF R4 L13; goto L13 if var4
      89 [-]: LOADB R6 1   ; var6 = true
      90 [-]: GETUPVAL R9 1; var9 = upvalues[1]
      91 [-]: GETTABLEKS R8 R9 K28; var8 = var9["mShrine"]
      92 [-]: NAMECALL R8 R8 K4; var9 = var8; var8 = var8[0xD1586535]
      93 [-]: CALL R8 2 2  ; var8 = var8(var9)
      94 [-]: GETIMPORT R9 6; var9 = 0xA421AF95
      95 [-]: LOADN R10 0  ; var10 = 0
      96 [-]: LOADN R11 2  ; var11 = 2
      97 [-]: LOADN R12 0  ; var12 = 0
      98 [-]: CALL R9 4 2  ; var9 = var9(var10, var11, var12)
      99 [-]: ADD R7 R8 R9 ; var7 = var8 + var9
     100 [-]: GETIMPORT R8 9; var8 = ZERO_ROTATION
     101 [-]: LOADN R9 2   ; var9 = 2
     102 [-]: LOADB R10 0  ; var10 = false
     103 [-]: NAMECALL R4 R1 K29; var5 = var1; var4 = var1[0x98B9FDA7]
     104 [-]: CALL R4 7 1  ; var4(var5, var6, var7, var8, var9, var10)
     105 [-]: GETUPVAL R4 2; var4 = upvalues[2]
     106 [-]: CALL R4 1 1  ; var4()
L13: 107 [-]: GETIMPORT R4 31; var4 = 0xCBD666E1
     108 [-]: LOADN R5 2   ; var5 = 2
     109 [-]: CALL R4 2 1  ; var4(var5)
     110 [-]: FASTCALL1 64 R1 L14; 
     111 [-]: MOVE R5 R1   ; var5 = var1
     112 [-]: GETIMPORT R4 12; var4 = 0x7B998233
     113 [-]: CALL R4 2 2  ; var4 = var4(var5)
L14: 114 [-]: JUMPIF R4 L15; goto L15 if var4
     115 [-]: NAMECALL R4 R1 K32; var5 = var1; var4 = var1[0xA2880940]
     116 [-]: CALL R4 2 1  ; var4(var5)
L15: 117 [-]: RETURN R0 0  ; 



