; Name:            
; Defined at line: 1
; #Upvalues:       0
; #Parameters:     0
; Is_vararg:       1
; Max Stack Size:  86

       1 [-]: GETIMPORT R0 1; var0 = 0x2D0FAD09
       2 [-]: LOADK R1 K2  ; var1 = "Lotus.Scripts.Libs.TransmissionSet"
       3 [-]: CALL R0 2 2  ; var0 = var0(var1)
       4 [-]: GETIMPORT R1 1; var1 = 0x2D0FAD09
       5 [-]: LOADK R2 K3  ; var2 = "Lotus.Scripts.Libs.CommonGamemodeFunctions"
       6 [-]: CALL R1 2 2  ; var1 = var1(var2)
       7 [-]: GETIMPORT R2 1; var2 = 0x2D0FAD09
       8 [-]: LOADK R3 K4  ; var3 = "Lotus.Scripts.Libs.ObjectiveText"
       9 [-]: CALL R2 2 2  ; var2 = var2(var3)
      10 [-]: GETIMPORT R3 1; var3 = 0x2D0FAD09
      11 [-]: LOADK R4 K5  ; var4 = "Lotus.Scripts.Libs.QuestLib"
      12 [-]: CALL R3 2 2  ; var3 = var3(var4)
      13 [-]: GETIMPORT R4 1; var4 = 0x2D0FAD09
      14 [-]: LOADK R5 K6  ; var5 = "Lotus.Scripts.Libs.QuestMissionLib"
      15 [-]: CALL R4 2 2  ; var4 = var4(var5)
      16 [-]: GETIMPORT R5 1; var5 = 0x2D0FAD09
      17 [-]: LOADK R6 K7  ; var6 = "Lotus.Scripts.Quests.EntratiLab.EntratiQuestUtil"
      18 [-]: CALL R5 2 2  ; var5 = var5(var6)
      19 [-]: GETIMPORT R6 1; var6 = 0x2D0FAD09
      20 [-]: LOADK R7 K8  ; var7 = "EE.Interface.Utilities"
      21 [-]: CALL R6 2 2  ; var6 = var6(var7)
      22 [-]: GETIMPORT R7 1; var7 = 0x2D0FAD09
      23 [-]: LOADK R8 K9  ; var8 = "Lotus.Interface.Libs.ImGuiLib"
      24 [-]: CALL R7 2 2  ; var7 = var7(var8)
      25 [-]: GETIMPORT R8 1; var8 = 0x2D0FAD09
      26 [-]: LOADK R9 K10 ; var9 = "Lotus.Scripts.Libs.AudioLib"
      27 [-]: CALL R8 2 2  ; var8 = var8(var9)
      28 [-]: GETIMPORT R9 1; var9 = 0x2D0FAD09
      29 [-]: LOADK R10 K11; var10 = "Lotus.Types.Enemies.ManInTheWall.Octopede.MITWOctopedeBossUtility"
      30 [-]: CALL R9 2 2  ; var9 = var9(var10)
      31 [-]: GETIMPORT R10 13; var10 = 0xB009BBC6
      32 [-]: LOADK R11 K14; var11 = "/Lotus/Types/Input/SimarisInputFilter"
      33 [-]: CALL R10 2 2 ; var10 = var10(var11)
      34 [-]: GETIMPORT R11 13; var11 = 0xB009BBC6
      35 [-]: LOADK R12 K15; var12 = "/Lotus/Commands/CmdTeleportToObjective"
      36 [-]: CALL R11 2 2 ; var11 = var11(var12)
      37 [-]: GETIMPORT R12 13; var12 = 0xB009BBC6
      38 [-]: LOADK R13 K16; var13 = "/Lotus/Types/DropTables/EmptyDropTable"
      39 [-]: CALL R12 2 2 ; var12 = var12(var13)
      40 [-]: GETIMPORT R13 18; var13 = 0x88EFC25E
      41 [-]: LOADK R14 K19; var14 = "/Lotus/Types/Gameplay/EntratiLab/Quest/GrimoireTestWeaponUpgrade"
      42 [-]: CALL R13 2 2 ; var13 = var13(var14)
      43 [-]: GETIMPORT R14 18; var14 = 0x88EFC25E
      44 [-]: LOADK R15 K20; var15 = "/Lotus/Types/Game/MarkerInfos/KillMarkerAlwaysInRange"
      45 [-]: CALL R14 2 2 ; var14 = var14(var15)
      46 [-]: GETIMPORT R15 13; var15 = 0xB009BBC6
      47 [-]: LOADK R16 K21; var16 = "/Lotus/Interface/SurvivalReward.swf"
      48 [-]: CALL R15 2 2 ; var15 = var15(var16)
      49 [-]: GETIMPORT R16 13; var16 = 0xB009BBC6
      50 [-]: LOADK R17 K22; var17 = "/Lotus/StoreItems/Weapons/Tenno/Grimoire/TnGrimoire"
      51 [-]: CALL R16 2 2 ; var16 = var16(var17)
      52 [-]: GETIMPORT R17 24; var17 = 0x7ED0A956
      53 [-]: LOADK R18 K25; var18 = "/Lotus/Characters/Orokin/Loid/LoidHeadAccessoriesDeco"
      54 [-]: CALL R17 2 2 ; var17 = var17(var18)
      55 [-]: GETIMPORT R18 24; var18 = 0x7ED0A956
      56 [-]: LOADK R19 K26; var19 = "/Lotus/Types/Enemies/ManInTheWall/RepairDrone/RepairDroneAvatar"
      57 [-]: CALL R18 2 2 ; var18 = var18(var19)
      58 [-]: GETIMPORT R19 24; var19 = 0x7ED0A956
      59 [-]: LOADK R20 K27; var20 = "/Lotus/Types/Enemies/ManInTheWall/VialCarryDrone/VialDroneAvatar"
      60 [-]: CALL R19 2 2 ; var19 = var19(var20)
      61 [-]: GETIMPORT R20 24; var20 = 0x7ED0A956
      62 [-]: LOADK R21 K28; var21 = "/Lotus/Types/Restoratives/HeavyWeaponSummon"
      63 [-]: CALL R20 2 2 ; var20 = var20(var21)
      64 [-]: GETIMPORT R21 30; var21 = 0x0469F296
      65 [-]: LOADK R22 K31; var22 = "KalymosMechRoomTrigger"
      66 [-]: CALL R21 2 2 ; var21 = var21(var22)
      67 [-]: GETIMPORT R22 30; var22 = 0x0469F296
      68 [-]: LOADK R23 K32; var23 = "SFXEntratiQuestMITWRumble"
      69 [-]: CALL R22 2 2 ; var22 = var22(var23)
      70 [-]: GETIMPORT R23 30; var23 = 0x0469F296
      71 [-]: LOADK R24 K33; var24 = "QuestNecramechEncounter1"
      72 [-]: CALL R23 2 2 ; var23 = var23(var24)
      73 [-]: GETIMPORT R24 30; var24 = 0x0469F296
      74 [-]: LOADK R25 K34; var25 = "KalymosGrimoireSpawnPoint"
      75 [-]: CALL R24 2 2 ; var24 = var24(var25)
      76 [-]: GETIMPORT R25 30; var25 = 0x0469F296
      77 [-]: LOADK R26 K35; var26 = "KalymosGrimoireAction"
      78 [-]: CALL R25 2 2 ; var25 = var25(var26)
      79 [-]: GETIMPORT R26 30; var26 = 0x0469F296
      80 [-]: LOADK R27 K36; var27 = "QuestNecramechEncounter2"
      81 [-]: CALL R26 2 2 ; var26 = var26(var27)
      82 [-]: GETIMPORT R27 30; var27 = 0x0469F296
      83 [-]: LOADK R28 K37; var28 = "QuestEvilTwinRoom"
      84 [-]: CALL R27 2 2 ; var27 = var27(var28)
      85 [-]: GETIMPORT R28 30; var28 = 0x0469F296
      86 [-]: LOADK R29 K38; var29 = "MITWRevealTrigger"
      87 [-]: CALL R28 2 2 ; var28 = var28(var29)
      88 [-]: GETIMPORT R29 30; var29 = 0x0469F296
      89 [-]: LOADK R30 K39; var30 = "QuestStartMurmurFight"
      90 [-]: CALL R29 2 2 ; var29 = var29(var30)
      91 [-]: GETIMPORT R30 30; var30 = 0x0469F296
      92 [-]: LOADK R31 K40; var31 = "KalymosMITWEnemyFightWp"
      93 [-]: CALL R30 2 2 ; var30 = var30(var31)
      94 [-]: GETIMPORT R31 30; var31 = 0x0469F296
      95 [-]: LOADK R32 K41; var32 = "OctopedeSpawn"
      96 [-]: CALL R31 2 2 ; var31 = var31(var32)
      97 [-]: GETIMPORT R32 30; var32 = 0x0469F296
      98 [-]: LOADK R33 K42; var33 = "TrainMover"
      99 [-]: CALL R32 2 2 ; var32 = var32(var33)
     100 [-]: GETIMPORT R33 30; var33 = 0x0469F296
     101 [-]: LOADK R34 K43; var34 = "KalymosHumanLoidWP"
     102 [-]: CALL R33 2 2 ; var33 = var33(var34)
     103 [-]: GETIMPORT R34 30; var34 = 0x0469F296
     104 [-]: LOADK R35 K44; var35 = "EntratiQuestOpenCryopodAction"
     105 [-]: CALL R34 2 2 ; var34 = var34(var35)
     106 [-]: GETIMPORT R35 30; var35 = 0x0469F296
     107 [-]: LOADK R36 K45; var36 = "HumanLoidAvatar"
     108 [-]: CALL R35 2 2 ; var35 = var35(var36)
     109 [-]: GETIMPORT R36 30; var36 = 0x0469F296
     110 [-]: LOADK R37 K46; var37 = "OctopedeBossState"
     111 [-]: CALL R36 2 2 ; var36 = var36(var37)
     112 [-]: LOADB R37 0  ; var37 = false
     113 [-]: LOADB R38 0  ; var38 = false
     114 [-]: LOADB R39 0  ; var39 = false
     115 [-]: LOADB R40 0  ; var40 = false
     116 [-]: LOADB R41 0  ; var41 = false
     117 [-]: LOADB R42 0  ; var42 = false
     118 [-]: LOADB R43 0  ; var43 = false
     119 [-]: LOADB R44 0  ; var44 = false
     120 [-]: LOADNIL R45  ; var45 = nil
     121 [-]: LOADN R46 1  ; var46 = 1
     122 [-]: LOADNIL R47  ; var47 = nil
     123 [-]: LOADNIL R48  ; var48 = nil
     124 [-]: LOADNIL R49  ; var49 = nil
     125 [-]: LOADNIL R50  ; var50 = nil
     126 [-]: LOADNIL R51  ; var51 = nil
     127 [-]: LOADNIL R52  ; var52 = nil
     128 [-]: LOADN R53 0  ; var53 = 0
     129 [-]: LOADNIL R54  ; var54 = nil
     130 [-]: LOADNIL R55  ; var55 = nil
     131 [-]: NEWTABLE R56 0 0; var56 = {}
     132 [-]: NEWTABLE R57 0 0; var57 = {}
     133 [-]: LOADNIL R58  ; var58 = nil
     134 [-]: LOADNIL R59  ; var59 = nil
     135 [-]: LOADNIL R60  ; var60 = nil
     136 [-]: LOADNIL R61  ; var61 = nil
     137 [-]: DUPTABLE R62 54; 
     138 [-]: LOADK R63 K55; var63 = "/Lotus/Language/EntratiLab/EntratiQuest/StageOneFindSleeper"
     139 [-]: SETTABLEKS R63 R62 K47; var63["FIND_SLEEPER"] = var62
     140 [-]: LOADK R63 K56; var63 = "/Lotus/Language/EntratiLab/EntratiQuest/DefeatNecramechs"
     141 [-]: SETTABLEKS R63 R62 K48; var63["DEFEAT_MECH"] = var62
     142 [-]: LOADK R63 K57; var63 = "/Lotus/Language/EntratiLab/EntratiQuest/StageOneTakeGrimoire"
     143 [-]: SETTABLEKS R63 R62 K49; var63["COLLECT_GRIMOIRE"] = var62
     144 [-]: LOADK R63 K58; var63 = "/Lotus/Language/EntratiLab/EntratiQuest/StageOneDefeatMurmur"
     145 [-]: SETTABLEKS R63 R62 K50; var63["DEFEAT_MITW_ENEMIES"] = var62
     146 [-]: LOADK R63 K59; var63 = "/Lotus/Language/EntratiLab/EntratiQuest/StageOneOpenCryopod"
     147 [-]: SETTABLEKS R63 R62 K51; var63["OPEN_CRYOPOD"] = var62
     148 [-]: LOADK R63 K60; var63 = "/Lotus/Language/EntratiLab/EntratiQuest/EnterPortal"
     149 [-]: SETTABLEKS R63 R62 K52; var63["ENTER_VESSEL"] = var62
     150 [-]: LOADK R63 K61; var63 = "/Lotus/Language/EntratiLab/EntratiQuest/FollowLoid"
     151 [-]: SETTABLEKS R63 R62 K53; var63["FOLLOW_LOID"] = var62
     152 [-]: DUPTABLE R63 76; 
     153 [-]: LOADN R64 1  ; var64 = 1
     154 [-]: SETTABLEKS R64 R63 K62; var64["SETUP"] = var63
     155 [-]: LOADN R64 2  ; var64 = 2
     156 [-]: SETTABLEKS R64 R63 K63; var64["FOLLOW_VOICE"] = var63
     157 [-]: LOADN R64 3  ; var64 = 3
     158 [-]: SETTABLEKS R64 R63 K64; var64["MECH"] = var63
     159 [-]: LOADN R64 4  ; var64 = 4
     160 [-]: SETTABLEKS R64 R63 K48; var64["DEFEAT_MECH"] = var63
     161 [-]: LOADN R64 5  ; var64 = 5
     162 [-]: SETTABLEKS R64 R63 K65; var64["FOLLOW_VOICE_AGAIN"] = var63
     163 [-]: LOADN R64 6  ; var64 = 6
     164 [-]: SETTABLEKS R64 R63 K66; var64["GRIMOIRE"] = var63
     165 [-]: LOADN R64 7  ; var64 = 7
     166 [-]: SETTABLEKS R64 R63 K67; var64["DEFEAT_MECH_GRIMOIRE"] = var63
     167 [-]: LOADN R64 8  ; var64 = 8
     168 [-]: SETTABLEKS R64 R63 K68; var64["GOTO_MITW"] = var63
     169 [-]: LOADN R64 9  ; var64 = 9
     170 [-]: SETTABLEKS R64 R63 K69; var64["DEFEAT_MITW"] = var63
     171 [-]: LOADN R64 10 ; var64 = 10
     172 [-]: SETTABLEKS R64 R63 K70; var64["CONTINUE_SEARCH"] = var63
     173 [-]: LOADN R64 11 ; var64 = 11
     174 [-]: SETTABLEKS R64 R63 K71; var64["MEET_HUMAN_LOID"] = var63
     175 [-]: LOADN R64 12 ; var64 = 12
     176 [-]: SETTABLEKS R64 R63 K72; var64["RESCUE_LOID_CIN"] = var63
     177 [-]: LOADN R64 13 ; var64 = 13
     178 [-]: SETTABLEKS R64 R63 K52; var64["ENTER_VESSEL"] = var63
     179 [-]: LOADN R64 14 ; var64 = 14
     180 [-]: SETTABLEKS R64 R63 K73; var64["OUTRO_CIN"] = var63
     181 [-]: LOADN R64 15 ; var64 = 15
     182 [-]: SETTABLEKS R64 R63 K74; var64["COMPLETE"] = var63
     183 [-]: LOADN R64 99 ; var64 = 99
     184 [-]: SETTABLEKS R64 R63 K75; var64["RESPAWN"] = var63
     185 [-]: NEWTABLE R64 16 0; var64 = {}
     186 [-]: GETTABLEKS R65 R63 K62; var65 = var63["SETUP"]
     187 [-]: DUPTABLE R66 78; 
     188 [-]: LOADK R67 K79; var67 = "Setup"
     189 [-]: SETTABLEKS R67 R66 K77; var67["name"] = var66
     190 [-]: SETTABLE R66 R64 R65; var66[var64] = var65
     191 [-]: GETTABLEKS R65 R63 K63; var65 = var63["FOLLOW_VOICE"]
     192 [-]: DUPTABLE R66 78; 
     193 [-]: LOADK R67 K80; var67 = "Follow The Voice"
     194 [-]: SETTABLEKS R67 R66 K77; var67["name"] = var66
     195 [-]: SETTABLE R66 R64 R65; var66[var64] = var65
     196 [-]: GETTABLEKS R65 R63 K64; var65 = var63["MECH"]
     197 [-]: DUPTABLE R66 78; 
     198 [-]: LOADK R67 K81; var67 = "Intro NecraMech"
     199 [-]: SETTABLEKS R67 R66 K77; var67["name"] = var66
     200 [-]: SETTABLE R66 R64 R65; var66[var64] = var65
     201 [-]: GETTABLEKS R65 R63 K48; var65 = var63["DEFEAT_MECH"]
     202 [-]: DUPTABLE R66 78; 
     203 [-]: LOADK R67 K82; var67 = "Defeat the Necramechs"
     204 [-]: SETTABLEKS R67 R66 K77; var67["name"] = var66
     205 [-]: SETTABLE R66 R64 R65; var66[var64] = var65
     206 [-]: GETTABLEKS R65 R63 K65; var65 = var63["FOLLOW_VOICE_AGAIN"]
     207 [-]: DUPTABLE R66 78; 
     208 [-]: LOADK R67 K83; var67 = "Follow The Voice Again"
     209 [-]: SETTABLEKS R67 R66 K77; var67["name"] = var66
     210 [-]: SETTABLE R66 R64 R65; var66[var64] = var65
     211 [-]: GETTABLEKS R65 R63 K66; var65 = var63["GRIMOIRE"]
     212 [-]: DUPTABLE R66 85; 
     213 [-]: LOADK R67 K86; var67 = "Get Grimoire"
     214 [-]: SETTABLEKS R67 R66 K77; var67["name"] = var66
     215 [-]: SETTABLEKS R25 R66 K84; var25["debugPt"] = var66
     216 [-]: SETTABLE R66 R64 R65; var66[var64] = var65
     217 [-]: GETTABLEKS R65 R63 K67; var65 = var63["DEFEAT_MECH_GRIMOIRE"]
     218 [-]: DUPTABLE R66 78; 
     219 [-]: LOADK R67 K87; var67 = "Defeat Necramechs With Grimoire"
     220 [-]: SETTABLEKS R67 R66 K77; var67["name"] = var66
     221 [-]: SETTABLE R66 R64 R65; var66[var64] = var65
     222 [-]: GETTABLEKS R65 R63 K68; var65 = var63["GOTO_MITW"]
     223 [-]: DUPTABLE R66 85; 
     224 [-]: LOADK R67 K88; var67 = "Go to MITW Area"
     225 [-]: SETTABLEKS R67 R66 K77; var67["name"] = var66
     226 [-]: SETTABLEKS R27 R66 K84; var27["debugPt"] = var66
     227 [-]: SETTABLE R66 R64 R65; var66[var64] = var65
     228 [-]: GETTABLEKS R65 R63 K69; var65 = var63["DEFEAT_MITW"]
     229 [-]: DUPTABLE R66 78; 
     230 [-]: LOADK R67 K89; var67 = "Defeat MITW Enemies"
     231 [-]: SETTABLEKS R67 R66 K77; var67["name"] = var66
     232 [-]: SETTABLE R66 R64 R65; var66[var64] = var65
     233 [-]: GETTABLEKS R65 R63 K70; var65 = var63["CONTINUE_SEARCH"]
     234 [-]: DUPTABLE R66 78; 
     235 [-]: LOADK R67 K90; var67 = "Continue Searching"
     236 [-]: SETTABLEKS R67 R66 K77; var67["name"] = var66
     237 [-]: SETTABLE R66 R64 R65; var66[var64] = var65
     238 [-]: GETTABLEKS R65 R63 K71; var65 = var63["MEET_HUMAN_LOID"]
     239 [-]: DUPTABLE R66 78; 
     240 [-]: LOADK R67 K91; var67 = "Meet Meat Loid"
     241 [-]: SETTABLEKS R67 R66 K77; var67["name"] = var66
     242 [-]: SETTABLE R66 R64 R65; var66[var64] = var65
     243 [-]: GETTABLEKS R65 R63 K72; var65 = var63["RESCUE_LOID_CIN"]
     244 [-]: DUPTABLE R66 78; 
     245 [-]: LOADK R67 K92; var67 = "Rescue Loid (Cin)"
     246 [-]: SETTABLEKS R67 R66 K77; var67["name"] = var66
     247 [-]: SETTABLE R66 R64 R65; var66[var64] = var65
     248 [-]: GETTABLEKS R65 R63 K52; var65 = var63["ENTER_VESSEL"]
     249 [-]: DUPTABLE R66 78; 
     250 [-]: LOADK R67 K93; var67 = "Enter Vessel"
     251 [-]: SETTABLEKS R67 R66 K77; var67["name"] = var66
     252 [-]: SETTABLE R66 R64 R65; var66[var64] = var65
     253 [-]: GETTABLEKS R65 R63 K73; var65 = var63["OUTRO_CIN"]
     254 [-]: DUPTABLE R66 78; 
     255 [-]: LOADK R67 K94; var67 = "Outro Cin"
     256 [-]: SETTABLEKS R67 R66 K77; var67["name"] = var66
     257 [-]: SETTABLE R66 R64 R65; var66[var64] = var65
     258 [-]: GETTABLEKS R65 R63 K74; var65 = var63["COMPLETE"]
     259 [-]: DUPTABLE R66 78; 
     260 [-]: LOADK R67 K95; var67 = "Complete"
     261 [-]: SETTABLEKS R67 R66 K77; var67["name"] = var66
     262 [-]: SETTABLE R66 R64 R65; var66[var64] = var65
     263 [-]: GETTABLEKS R65 R63 K75; var65 = var63["RESPAWN"]
     264 [-]: DUPTABLE R66 78; 
     265 [-]: LOADK R67 K96; var67 = "Respawn"
     266 [-]: SETTABLEKS R67 R66 K77; var67["name"] = var66
     267 [-]: SETTABLE R66 R64 R65; var66[var64] = var65
     268 [-]: NEWTABLE R65 4 0; var65 = {}
     269 [-]: GETTABLEKS R66 R63 K63; var66 = var63["FOLLOW_VOICE"]
     270 [-]: SETTABLEKS R66 R65 K97; var66["EntratiQuestSpawnCheckpoint"] = var65
     271 [-]: GETTABLEKS R66 R63 K65; var66 = var63["FOLLOW_VOICE_AGAIN"]
     272 [-]: SETTABLEKS R66 R65 K98; var66["EntratiQuestPostMechCheckpoint"] = var65
     273 [-]: GETTABLEKS R66 R63 K68; var66 = var63["GOTO_MITW"]
     274 [-]: SETTABLEKS R66 R65 K99; var66["QuestPostGrimoireCheckpoint"] = var65
     275 [-]: GETTABLEKS R66 R63 K70; var66 = var63["CONTINUE_SEARCH"]
     276 [-]: SETTABLEKS R66 R65 K100; var66["QuestPostMitwCheckpoint"] = var65
     277 [-]: DUPCLOSURE R66 K101; 
     278 [-]: CAPTURE VAL R64; 
     279 [-]: DUPCLOSURE R67 K102; 
     280 [-]: CAPTURE VAL R63; 
     281 [-]: DUPCLOSURE R68 K103; 
     282 [-]: CAPTURE VAL R64; 
     283 [-]: LOADN R69 0  ; var69 = 0
     284 [-]: NEWCLOSURE R70 P3; 
     285 [-]: CAPTURE REF R46; 
     286 [-]: CAPTURE VAL R64; 
     287 [-]: CAPTURE REF R69; 
     288 [-]: CAPTURE VAL R68; 
     289 [-]: CAPTURE VAL R63; 
     290 [-]: CAPTURE REF R47; 
     291 [-]: CAPTURE REF R48; 
     292 [-]: CAPTURE VAL R7; 
     293 [-]: CAPTURE REF R55; 
     294 [-]: CAPTURE REF R49; 
     295 [-]: CAPTURE REF R51; 
     296 [-]: CAPTURE REF R56; 
     297 [-]: CAPTURE REF R57; 
     298 [-]: NEWCLOSURE R71 P4; 
     299 [-]: CAPTURE VAL R5; 
     300 [-]: CAPTURE VAL R21; 
     301 [-]: CAPTURE VAL R29; 
     302 [-]: CAPTURE VAL R32; 
     303 [-]: CAPTURE VAL R25; 
     304 [-]: CAPTURE VAL R34; 
     305 [-]: CAPTURE VAL R28; 
     306 [-]: CAPTURE REF R56; 
     307 [-]: CAPTURE VAL R23; 
     308 [-]: CAPTURE REF R57; 
     309 [-]: CAPTURE VAL R26; 
     310 [-]: NEWCLOSURE R72 P5; 
     311 [-]: CAPTURE REF R48; 
     312 [-]: NEWCLOSURE R73 P6; 
     313 [-]: CAPTURE REF R48; 
     314 [-]: CAPTURE VAL R13; 
     315 [-]: NEWCLOSURE R74 P7; 
     316 [-]: CAPTURE VAL R28; 
     317 [-]: CAPTURE REF R58; 
     318 [-]: NEWCLOSURE R75 P8; 
     319 [-]: CAPTURE REF R54; 
     320 [-]: CAPTURE VAL R65; 
     321 [-]: NEWCLOSURE R76 P9; 
     322 [-]: CAPTURE REF R51; 
     323 [-]: CAPTURE REF R45; 
     324 [-]: NEWCLOSURE R77 P10; 
     325 [-]: CAPTURE REF R61; 
     326 [-]: NEWCLOSURE R78 P11; 
     327 [-]: CAPTURE VAL R64; 
     328 [-]: CAPTURE VAL R75; 
     329 [-]: CAPTURE VAL R63; 
     330 [-]: CAPTURE REF R51; 
     331 [-]: CAPTURE REF R45; 
     332 [-]: CAPTURE VAL R71; 
     333 [-]: CAPTURE VAL R1; 
     334 [-]: CAPTURE REF R47; 
     335 [-]: CAPTURE VAL R2; 
     336 [-]: CAPTURE VAL R62; 
     337 [-]: CAPTURE VAL R21; 
     338 [-]: CAPTURE VAL R5; 
     339 [-]: CAPTURE REF R49; 
     340 [-]: CAPTURE VAL R23; 
     341 [-]: CAPTURE REF R48; 
     342 [-]: CAPTURE VAL R18; 
     343 [-]: CAPTURE VAL R19; 
     344 [-]: CAPTURE VAL R14; 
     345 [-]: CAPTURE REF R41; 
     346 [-]: CAPTURE VAL R6; 
     347 [-]: CAPTURE VAL R0; 
     348 [-]: CAPTURE REF R50; 
     349 [-]: CAPTURE VAL R24; 
     350 [-]: CAPTURE VAL R25; 
     351 [-]: CAPTURE VAL R26; 
     352 [-]: CAPTURE VAL R22; 
     353 [-]: CAPTURE VAL R29; 
     354 [-]: CAPTURE REF R42; 
     355 [-]: CAPTURE VAL R74; 
     356 [-]: CAPTURE VAL R30; 
     357 [-]: CAPTURE VAL R8; 
     358 [-]: CAPTURE VAL R31; 
     359 [-]: CAPTURE VAL R33; 
     360 [-]: CAPTURE VAL R32; 
     361 [-]: CAPTURE VAL R34; 
     362 [-]: CAPTURE REF R59; 
     363 [-]: CAPTURE REF R60; 
     364 [-]: CAPTURE VAL R17; 
     365 [-]: CAPTURE VAL R4; 
     366 [-]: CAPTURE REF R61; 
     367 [-]: CAPTURE VAL R10; 
     368 [-]: CAPTURE VAL R3; 
     369 [-]: CAPTURE REF R40; 
     370 [-]: CAPTURE VAL R11; 
     371 [-]: NEWCLOSURE R79 P12; 
     372 [-]: CAPTURE REF R52; 
     373 [-]: CAPTURE VAL R4; 
     374 [-]: CAPTURE REF R48; 
     375 [-]: NEWCLOSURE R80 P13; 
     376 [-]: CAPTURE REF R52; 
     377 [-]: CAPTURE VAL R4; 
     378 [-]: CAPTURE REF R48; 
     379 [-]: CAPTURE REF R55; 
     380 [-]: CAPTURE VAL R5; 
     381 [-]: CAPTURE REF R46; 
     382 [-]: CAPTURE VAL R63; 
     383 [-]: CAPTURE REF R37; 
     384 [-]: CAPTURE REF R47; 
     385 [-]: CAPTURE REF R53; 
     386 [-]: CAPTURE REF R56; 
     387 [-]: CAPTURE REF R49; 
     388 [-]: CAPTURE REF R57; 
     389 [-]: CAPTURE VAL R27; 
     390 [-]: CAPTURE REF R41; 
     391 [-]: CAPTURE VAL R1; 
     392 [-]: CAPTURE REF R51; 
     393 [-]: CAPTURE REF R45; 
     394 [-]: CAPTURE VAL R36; 
     395 [-]: CAPTURE VAL R9; 
     396 [-]: CAPTURE REF R38; 
     397 [-]: CAPTURE REF R39; 
     398 [-]: CAPTURE REF R60; 
     399 [-]: CAPTURE REF R43; 
     400 [-]: CAPTURE REF R61; 
     401 [-]: NEWCLOSURE R81 P14; 
     402 [-]: CAPTURE REF R48; 
     403 [-]: CAPTURE REF R50; 
     404 [-]: CAPTURE REF R49; 
     405 [-]: CAPTURE VAL R5; 
     406 [-]: CAPTURE REF R54; 
     407 [-]: CAPTURE VAL R1; 
     408 [-]: CAPTURE VAL R12; 
     409 [-]: CAPTURE REF R47; 
     410 [-]: CAPTURE VAL R63; 
     411 [-]: CAPTURE REF R44; 
     412 [-]: DUPCLOSURE R82 K104; 
     413 [-]: NEWCLOSURE R83 P16; 
     414 [-]: CAPTURE REF R47; 
     415 [-]: CAPTURE VAL R1; 
     416 [-]: CAPTURE VAL R78; 
     417 [-]: CAPTURE REF R44; 
     418 [-]: CAPTURE VAL R81; 
     419 [-]: CAPTURE REF R46; 
     420 [-]: CAPTURE VAL R80; 
     421 [-]: SETGLOBAL R83 K105; "RunStage" = var83
     422 [-]: NEWCLOSURE R83 P17; 
     423 [-]: CAPTURE REF R37; 
     424 [-]: SETGLOBAL R83 K106; "OnCleanup" = var83
     425 [-]: NEWCLOSURE R83 P18; 
     426 [-]: CAPTURE REF R47; 
     427 [-]: CAPTURE VAL R63; 
     428 [-]: CAPTURE VAL R1; 
     429 [-]: SETGLOBAL R83 K107; "OnReset" = var83
     430 [-]: NEWCLOSURE R83 P19; 
     431 [-]: CAPTURE REF R55; 
     432 [-]: SETGLOBAL R83 K108; "OnSaved" = var83
     433 [-]: NEWCLOSURE R83 P20; 
     434 [-]: CAPTURE VAL R65; 
     435 [-]: CAPTURE VAL R63; 
     436 [-]: CAPTURE REF R48; 
     437 [-]: CAPTURE VAL R13; 
     438 [-]: CAPTURE VAL R1; 
     439 [-]: CAPTURE REF R53; 
     440 [-]: CAPTURE REF R47; 
     441 [-]: SETGLOBAL R83 K109; "OnFadeInComplete" = var83
     442 [-]: NEWCLOSURE R83 P21; 
     443 [-]: CAPTURE VAL R21; 
     444 [-]: CAPTURE REF R37; 
     445 [-]: CAPTURE VAL R0; 
     446 [-]: CAPTURE REF R50; 
     447 [-]: CAPTURE VAL R1; 
     448 [-]: CAPTURE REF R47; 
     449 [-]: CAPTURE VAL R63; 
     450 [-]: CAPTURE VAL R32; 
     451 [-]: CAPTURE VAL R28; 
     452 [-]: CAPTURE REF R42; 
     453 [-]: CAPTURE REF R48; 
     454 [-]: CAPTURE VAL R29; 
     455 [-]: CAPTURE VAL R5; 
     456 [-]: CAPTURE REF R43; 
     457 [-]: SETGLOBAL R83 K110; "OnTouched" = var83
     458 [-]: DUPCLOSURE R83 K111; 
     459 [-]: NEWCLOSURE R84 P23; 
     460 [-]: CAPTURE REF R48; 
     461 [-]: CAPTURE VAL R20; 
     462 [-]: CAPTURE VAL R83; 
     463 [-]: CAPTURE VAL R15; 
     464 [-]: CAPTURE VAL R16; 
     465 [-]: CAPTURE VAL R13; 
     466 [-]: NEWCLOSURE R85 P24; 
     467 [-]: CAPTURE REF R48; 
     468 [-]: CAPTURE VAL R84; 
     469 [-]: SETGLOBAL R85 K112; "TestGrimoirePickup" = var85
     470 [-]: NEWCLOSURE R85 P25; 
     471 [-]: CAPTURE VAL R25; 
     472 [-]: CAPTURE VAL R84; 
     473 [-]: CAPTURE REF R47; 
     474 [-]: CAPTURE VAL R63; 
     475 [-]: CAPTURE VAL R34; 
     476 [-]: SETGLOBAL R85 K113; "OnActivated" = var85
     477 [-]: NEWCLOSURE R85 P26; 
     478 [-]: CAPTURE REF R53; 
     479 [-]: SETGLOBAL R85 K114; "OnWavesComplete" = var85
     480 [-]: NEWCLOSURE R85 P27; 
     481 [-]: CAPTURE REF R44; 
     482 [-]: CAPTURE VAL R5; 
     483 [-]: CAPTURE VAL R70; 
     484 [-]: SETGLOBAL R85 K115; "DebugLoop" = var85
     485 [-]: DUPCLOSURE R85 K116; 
     486 [-]: SETGLOBAL R85 K117; "VanishWhenNotVisible" = var85
     487 [-]: NEWCLOSURE R85 P29; 
     488 [-]: CAPTURE VAL R0; 
     489 [-]: CAPTURE REF R50; 
     490 [-]: CAPTURE REF R58; 
     491 [-]: SETGLOBAL R85 K118; "MITWReveal" = var85
     492 [-]: DUPCLOSURE R85 K119; 
     493 [-]: CAPTURE VAL R5; 
     494 [-]: SETGLOBAL R85 K120; "SetupRescueLoidCin" = var85
     495 [-]: NEWCLOSURE R85 P31; 
     496 [-]: CAPTURE REF R60; 
     497 [-]: CAPTURE VAL R35; 
     498 [-]: SETGLOBAL R85 K121; "ReEnableLoidCloth" = var85
     499 [-]: DUPCLOSURE R85 K122; 
     500 [-]: CAPTURE VAL R5; 
     501 [-]: CAPTURE VAL R4; 
     502 [-]: SETGLOBAL R85 K123; "HandleSlowWalk" = var85
     503 [-]: CLOSEUPVALS R37; 
     504 [-]: RETURN R0 0  ; 


; Name:            
; Defined at line: 165
; #Upvalues:       1
; #Parameters:     1
; Is_vararg:       0
; Max Stack Size:  5

       0 [-]: GETUPVAL R4 0; var4 = upvalues[0]
       1 [-]: GETTABLE R3 R4 R0; var3 = var4[var0]
       2 [-]: GETTABLEKS R2 R3 K1; var2 = var3["name"]
       3 [-]: ORK R1 R2 K0 ; var1 = var2 or "State Name Not Found"
       4 [-]: RETURN R1 1  ; 


; Name:            
; Defined at line: 170
; #Upvalues:       1
; #Parameters:     1
; Is_vararg:       0
; Max Stack Size:  4

       0 [-]: GETUPVAL R3 0; var3 = upvalues[0]
       1 [-]: GETTABLEKS R2 R3 K0; var2 = var3["COMPLETE"]
       2 [-]: JUMPIFLT R0 R2 L0; goto L0 if var0 < var16777478
       3 [-]: LOADB R1 0 +1; var1 = false
L 0:   4 [-]: LOADB R1 1   ; var1 = true
L 1:   5 [-]: RETURN R1 1  ; 


; Name:            
; Defined at line: 174
; #Upvalues:       1
; #Parameters:     0
; Is_vararg:       0
; Max Stack Size:  11

       0 [-]: NEWTABLE R0 0 0; var0 = {}
       1 [-]: LOADN R3 1   ; var3 = 1
       2 [-]: GETUPVAL R4 0; var4 = upvalues[0]
       3 [-]: LENGTH R1 R4 ; var1 = #var4
       4 [-]: LOADN R2 1   ; var2 = 1
       5 [-]: FORNPREP R1 L2; nforprep start - [escape at L2] -- var1 = iterator
L 0:   6 [-]: GETUPVAL R10 0; var10 = upvalues[0]
       7 [-]: GETTABLE R9 R10 R3; var9 = var10[var3]
       8 [-]: GETTABLEKS R8 R9 K1; var8 = var9["name"]
       9 [-]: ORK R7 R8 K0 ; var7 = var8 or "State Name Not Found"
      10 [-]: MOVE R6 R7   ; var6 = var7
      11 [-]: FASTCALL2 52 R0 R6 L1; 
      12 [-]: MOVE R5 R0   ; var5 = var0
      13 [-]: GETIMPORT R4 4; var4 = 0x33BDD652[0x23D5322F]
      14 [-]: CALL R4 3 1  ; var4(var5, var6)
L 1:  15 [-]: FORNLOOP R1 L0; nforloop end - iterate + goto L0
L 2:  16 [-]: RETURN R0 1  ; 


; Name:            
; Defined at line: 183
; #Upvalues:       13
; #Parameters:     0
; Is_vararg:       0
; Max Stack Size:  18

       0 [-]: GETIMPORT R0 1; var0 = 0x4C403684
       1 [-]: LOADK R1 K2  ; var1 = "Entrati Lab Quest Stage 1:The Search For Loid"
       2 [-]: CALL R0 2 2  ; var0 = var0(var1)
       3 [-]: JUMPIFNOT R0 L25; goto L25 if not var0
       4 [-]: GETIMPORT R0 4; var0 = 0x2F44540D
       5 [-]: LOADK R1 K5  ; var1 = "Quest State Info"
       6 [-]: CALL R0 2 1  ; var0(var1)
       7 [-]: GETIMPORT R0 7; var0 = 0x1577FC24
       8 [-]: LOADK R2 K8  ; var2 = "State: "
       9 [-]: GETUPVAL R7 0; var7 = upvalues[0]
      10 [-]: GETUPVAL R11 1; var11 = upvalues[1]
      11 [-]: GETTABLE R10 R11 R7; var10 = var11[var7]
      12 [-]: GETTABLEKS R9 R10 K10; var9 = var10["name"]
      13 [-]: ORK R8 R9 K9 ; var8 = var9 or "State Name Not Found"
      14 [-]: MOVE R3 R8   ; var3 = var8
      15 [-]: LOADK R4 K11 ; var4 = " ("
      16 [-]: GETUPVAL R5 0; var5 = upvalues[0]
      17 [-]: LOADK R6 K12 ; var6 = ")"
      18 [-]: CONCAT R1 R2 R6; var1 = var2 .. var6
      19 [-]: CALL R0 2 1  ; var0(var1)
      20 [-]: GETIMPORT R0 14; var0 = 0x6F44BF5B
      21 [-]: LOADK R1 K15 ; var1 = "State"
      22 [-]: GETUPVAL R2 2; var2 = upvalues[2]
      23 [-]: GETUPVAL R3 3; var3 = upvalues[3]
      24 [-]: CALL R3 1 2  ; var3 = var3()
      25 [-]: CALL R0 4 2  ; var0 = var0(var1, var2, var3)
      26 [-]: SETUPVAL R0 2; upvalues[0] = var2
      27 [-]: GETIMPORT R0 17; var0 = 0xCA85312B
      28 [-]: LOADK R1 K18 ; var1 = "Set Stage"
      29 [-]: CALL R0 2 2  ; var0 = var0(var1)
      30 [-]: JUMPIFNOT R0 L3; goto L3 if not var0
      31 [-]: GETUPVAL R1 2; var1 = upvalues[2]
      32 [-]: GETUPVAL R3 4; var3 = upvalues[4]
      33 [-]: GETTABLEKS R2 R3 K19; var2 = var3["COMPLETE"]
      34 [-]: JUMPIFLT R1 R2 L0; goto L0 if var1 < var16777222
      35 [-]: LOADB R0 0 +1; var0 = false
L 0:  36 [-]: LOADB R0 1   ; var0 = true
L 1:  37 [-]: JUMPIFNOT R0 L3; goto L3 if not var0
      38 [-]: GETUPVAL R0 5; var0 = upvalues[5]
      39 [-]: GETUPVAL R2 2; var2 = upvalues[2]
      40 [-]: NAMECALL R0 R0 K20; var1 = var0; var0 = var0[0x8ABFF40E]
      41 [-]: CALL R0 3 1  ; var0(var1, var2)
      42 [-]: GETUPVAL R2 1; var2 = upvalues[1]
      43 [-]: GETUPVAL R3 2; var3 = upvalues[2]
      44 [-]: GETTABLE R1 R2 R3; var1 = var2[var3]
      45 [-]: GETTABLEKS R0 R1 K21; var0 = var1["debugPt"]
      46 [-]: JUMPIFNOT R0 L3; goto L3 if not var0
      47 [-]: GETIMPORT R0 23; var0 = 0x89326C93
      48 [-]: GETUPVAL R4 1; var4 = upvalues[1]
      49 [-]: GETUPVAL R5 2; var5 = upvalues[2]
      50 [-]: GETTABLE R3 R4 R5; var3 = var4[var5]
      51 [-]: GETTABLEKS R2 R3 K21; var2 = var3["debugPt"]
      52 [-]: NAMECALL R0 R0 K24; var1 = var0; var0 = var0[0x46A0EBF5]
      53 [-]: CALL R0 3 2  ; var0 = var0(var1, var2)
      54 [-]: FASTCALL1 64 R0 L2; 
      55 [-]: MOVE R2 R0   ; var2 = var0
      56 [-]: GETIMPORT R1 26; var1 = 0x7B998233
      57 [-]: CALL R1 2 2  ; var1 = var1(var2)
L 2:  58 [-]: JUMPIF R1 L3 ; goto L3 if var1
      59 [-]: GETUPVAL R1 6; var1 = upvalues[6]
      60 [-]: NAMECALL R3 R0 K27; var4 = var0; var3 = var0[0xD1586535]
      61 [-]: CALL R3 2 2  ; var3 = var3(var4)
      62 [-]: NAMECALL R4 R0 K28; var5 = var0; var4 = var0[0xCB3851B8]
      63 [-]: CALL R4 2 0  ; var4, ... = var4(var5)
      64 [-]: NAMECALL R1 R1 K29; var2 = var1; var1 = var1[0x589EF1C1]
      65 [-]: CALL R1 0 1  ; var1(var2, ...)
L 3:  66 [-]: GETUPVAL R1 7; var1 = upvalues[7]
      67 [-]: GETTABLEKS R0 R1 K30; var0 = var1[0xAD3B848A]
      68 [-]: CALL R0 1 1  ; var0()
      69 [-]: GETIMPORT R0 4; var0 = 0x2F44540D
      70 [-]: LOADK R1 K31 ; var1 = "General"
      71 [-]: CALL R0 2 1  ; var0(var1)
      72 [-]: GETUPVAL R1 7; var1 = upvalues[7]
      73 [-]: GETTABLEKS R0 R1 K32; var0 = var1[0xE514A724]
      74 [-]: CALL R0 1 1  ; var0()
      75 [-]: GETUPVAL R1 7; var1 = upvalues[7]
      76 [-]: GETTABLEKS R0 R1 K33; var0 = var1[0x1A80B641]
      77 [-]: CALL R0 1 1  ; var0()
      78 [-]: GETUPVAL R1 7; var1 = upvalues[7]
      79 [-]: GETTABLEKS R0 R1 K34; var0 = var1[0xAFB5885E]
      80 [-]: LOADB R1 1   ; var1 = true
      81 [-]: CALL R0 2 1  ; var0(var1)
      82 [-]: GETUPVAL R1 8; var1 = upvalues[8]
      83 [-]: FASTCALL1 64 R1 L4; 
      84 [-]: GETIMPORT R0 26; var0 = 0x7B998233
      85 [-]: CALL R0 2 2  ; var0 = var0(var1)
L 4:  86 [-]: JUMPIF R0 L7 ; goto L7 if var0
      87 [-]: GETIMPORT R0 7; var0 = 0x1577FC24
      88 [-]: LOADK R2 K35 ; var2 = "Current Checkpoint: "
      89 [-]: GETUPVAL R8 8; var8 = upvalues[8]
      90 [-]: NAMECALL R8 R8 K36; var9 = var8; var8 = var8[0xE223E2B1]
      91 [-]: CALL R8 2 0  ; var8, ... = var8(var9)
      92 [-]: FASTCALL 63 L5; 
      93 [-]: GETIMPORT R7 38; var7 = 0x64FB1586
      94 [-]: CALL R7 0 2  ; var7 = var7(var8, ...)
L 5:  95 [-]: MOVE R3 R7   ; var3 = var7
      96 [-]: LOADK R4 K39 ; var4 = "(tag="
      97 [-]: GETUPVAL R8 8; var8 = upvalues[8]
      98 [-]: NAMECALL R8 R8 K40; var9 = var8; var8 = var8[0x22DA1852]
      99 [-]: CALL R8 2 0  ; var8, ... = var8(var9)
     100 [-]: FASTCALL 63 L6; 
     101 [-]: GETIMPORT R7 38; var7 = 0x64FB1586
     102 [-]: CALL R7 0 2  ; var7 = var7(var8, ...)
L 6: 103 [-]: MOVE R5 R7   ; var5 = var7
     104 [-]: LOADK R6 K12 ; var6 = ")"
     105 [-]: CONCAT R1 R2 R6; var1 = var2 .. var6
     106 [-]: CALL R0 2 1  ; var0(var1)
L 7: 107 [-]: GETUPVAL R1 9; var1 = upvalues[9]
     108 [-]: FASTCALL1 64 R1 L8; 
     109 [-]: GETIMPORT R0 26; var0 = 0x7B998233
     110 [-]: CALL R0 2 2  ; var0 = var0(var1)
L 8: 111 [-]: JUMPIF R0 L10; goto L10 if var0
     112 [-]: GETIMPORT R0 7; var0 = 0x1577FC24
     113 [-]: LOADK R2 K41 ; var2 = "Objective Marker: "
     114 [-]: GETUPVAL R4 9; var4 = upvalues[9]
     115 [-]: NAMECALL R4 R4 K27; var5 = var4; var4 = var4[0xD1586535]
     116 [-]: CALL R4 2 0  ; var4, ... = var4(var5)
     117 [-]: FASTCALL 63 L9; 
     118 [-]: GETIMPORT R3 38; var3 = 0x64FB1586
     119 [-]: CALL R3 0 2  ; var3 = var3(var4, ...)
L 9: 120 [-]: CONCAT R1 R2 R3; var1 = var2 .. var3
     121 [-]: CALL R0 2 1  ; var0(var1)
L10: 122 [-]: GETIMPORT R0 43; var0 = 0xC2975602
     123 [-]: LOADK R1 K44 ; var1 = "Combat"
     124 [-]: CALL R0 2 2  ; var0 = var0(var1)
     125 [-]: JUMPIFNOT R0 L25; goto L25 if not var0
     126 [-]: GETUPVAL R1 10; var1 = upvalues[10]
     127 [-]: FASTCALL1 64 R1 L11; 
     128 [-]: GETIMPORT R0 26; var0 = 0x7B998233
     129 [-]: CALL R0 2 2  ; var0 = var0(var1)
L11: 130 [-]: JUMPIF R0 L13; goto L13 if var0
     131 [-]: GETIMPORT R0 7; var0 = 0x1577FC24
     132 [-]: LOADK R2 K45 ; var2 = "AI Spec: "
     133 [-]: GETUPVAL R4 10; var4 = upvalues[10]
     134 [-]: NAMECALL R4 R4 K36; var5 = var4; var4 = var4[0xE223E2B1]
     135 [-]: CALL R4 2 0  ; var4, ... = var4(var5)
     136 [-]: FASTCALL 63 L12; 
     137 [-]: GETIMPORT R3 38; var3 = 0x64FB1586
     138 [-]: CALL R3 0 2  ; var3 = var3(var4, ...)
L12: 139 [-]: CONCAT R1 R2 R3; var1 = var2 .. var3
     140 [-]: CALL R0 2 1  ; var0(var1)
L13: 141 [-]: GETIMPORT R0 43; var0 = 0xC2975602
     142 [-]: LOADK R1 K46 ; var1 = "Encounter 1 Spawns"
     143 [-]: CALL R0 2 2  ; var0 = var0(var1)
     144 [-]: JUMPIFNOT R0 L19; goto L19 if not var0
     145 [-]: GETIMPORT R0 48; var0 = 0xC8802016
     146 [-]: GETUPVAL R1 11; var1 = upvalues[11]
     147 [-]: CALL R0 2 4  ; var0, var1, var2 = var0(var1)
     148 [-]: FORGPREP_INEXT R0 L18; 
L14: 149 [-]: GETIMPORT R5 43; var5 = 0xC2975602
     150 [-]: LOADK R7 K49 ; var7 = "Spawner "
     151 [-]: MOVE R8 R3   ; var8 = var3
     152 [-]: LOADK R9 K50 ; var9 = ": "
     153 [-]: NAMECALL R10 R4 K36; var11 = var4; var10 = var4[0xE223E2B1]
     154 [-]: CALL R10 2 2 ; var10 = var10(var11)
     155 [-]: CONCAT R6 R7 R10; var6 = var7 .. var10
     156 [-]: CALL R5 2 2  ; var5 = var5(var6)
     157 [-]: JUMPIFNOT R5 L18; goto L18 if not var5
     158 [-]: GETIMPORT R5 48; var5 = 0xC8802016
     159 [-]: NAMECALL R6 R4 K51; var7 = var4; var6 = var4[0x23C35B22]
     160 [-]: CALL R6 2 0  ; var6, ... = var6(var7)
     161 [-]: CALL R5 0 4  ; var5, var6, var7 = var5(var6, ...)
     162 [-]: FORGPREP_INEXT R5 L17; 
L15: 163 [-]: GETIMPORT R10 7; var10 = 0x1577FC24
     164 [-]: LOADK R12 K52; var12 = "Enemy "
     165 [-]: MOVE R13 R8  ; var13 = var8
     166 [-]: LOADK R14 K50; var14 = ": "
     167 [-]: NAMECALL R16 R9 K36; var17 = var9; var16 = var9[0xE223E2B1]
     168 [-]: CALL R16 2 0 ; var16, ... = var16(var17)
     169 [-]: FASTCALL 63 L16; 
     170 [-]: GETIMPORT R15 38; var15 = 0x64FB1586
     171 [-]: CALL R15 0 2 ; var15 = var15(var16, ...)
L16: 172 [-]: CONCAT R11 R12 R15; var11 = var12 .. var15
     173 [-]: CALL R10 2 1 ; var10(var11)
L17: 174 [-]: FORGLOOP R5 L15 2 [inext]; 
L18: 175 [-]: FORGLOOP R0 L14 2 [inext]; 
L19: 176 [-]: GETIMPORT R0 43; var0 = 0xC2975602
     177 [-]: LOADK R1 K53 ; var1 = "Encounter 2 Spawns"
     178 [-]: CALL R0 2 2  ; var0 = var0(var1)
     179 [-]: JUMPIFNOT R0 L25; goto L25 if not var0
     180 [-]: GETIMPORT R0 48; var0 = 0xC8802016
     181 [-]: GETUPVAL R1 12; var1 = upvalues[12]
     182 [-]: CALL R0 2 4  ; var0, var1, var2 = var0(var1)
     183 [-]: FORGPREP_INEXT R0 L24; 
L20: 184 [-]: GETIMPORT R5 43; var5 = 0xC2975602
     185 [-]: LOADK R7 K49 ; var7 = "Spawner "
     186 [-]: MOVE R8 R3   ; var8 = var3
     187 [-]: LOADK R9 K50 ; var9 = ": "
     188 [-]: NAMECALL R10 R4 K36; var11 = var4; var10 = var4[0xE223E2B1]
     189 [-]: CALL R10 2 2 ; var10 = var10(var11)
     190 [-]: CONCAT R6 R7 R10; var6 = var7 .. var10
     191 [-]: CALL R5 2 2  ; var5 = var5(var6)
     192 [-]: JUMPIFNOT R5 L24; goto L24 if not var5
     193 [-]: GETIMPORT R5 48; var5 = 0xC8802016
     194 [-]: NAMECALL R6 R4 K51; var7 = var4; var6 = var4[0x23C35B22]
     195 [-]: CALL R6 2 0  ; var6, ... = var6(var7)
     196 [-]: CALL R5 0 4  ; var5, var6, var7 = var5(var6, ...)
     197 [-]: FORGPREP_INEXT R5 L23; 
L21: 198 [-]: GETIMPORT R10 7; var10 = 0x1577FC24
     199 [-]: LOADK R12 K52; var12 = "Enemy "
     200 [-]: MOVE R13 R8  ; var13 = var8
     201 [-]: LOADK R14 K50; var14 = ": "
     202 [-]: NAMECALL R16 R9 K36; var17 = var9; var16 = var9[0xE223E2B1]
     203 [-]: CALL R16 2 0 ; var16, ... = var16(var17)
     204 [-]: FASTCALL 63 L22; 
     205 [-]: GETIMPORT R15 38; var15 = 0x64FB1586
     206 [-]: CALL R15 0 2 ; var15 = var15(var16, ...)
L22: 207 [-]: CONCAT R11 R12 R15; var11 = var12 .. var15
     208 [-]: CALL R10 2 1 ; var10(var11)
L23: 209 [-]: FORGLOOP R5 L21 2 [inext]; 
L24: 210 [-]: FORGLOOP R0 L20 2 [inext]; 
L25: 211 [-]: GETIMPORT R0 55; var0 = 0xCA9F53F0
     212 [-]: CALL R0 1 1  ; var0()
     213 [-]: RETURN R0 0  ; 


; Name:            
; Defined at line: 246
; #Upvalues:       11
; #Parameters:     0
; Is_vararg:       0
; Max Stack Size:  4

       0 [-]: GETUPVAL R1 0; var1 = upvalues[0]
       1 [-]: GETTABLEKS R0 R1 K0; var0 = var1[0xD1B22BBF]
       2 [-]: GETUPVAL R1 1; var1 = upvalues[1]
       3 [-]: LOADK R2 K1  ; var2 = "OnTouched"
       4 [-]: LOADB R3 0   ; var3 = false
       5 [-]: CALL R0 4 1  ; var0(var1, var2, var3)
       6 [-]: GETUPVAL R1 0; var1 = upvalues[0]
       7 [-]: GETTABLEKS R0 R1 K0; var0 = var1[0xD1B22BBF]
       8 [-]: GETIMPORT R1 3; var1 = 0x0469F296
       9 [-]: LOADK R2 K4  ; var2 = "QuestSpottedMechsTrigger"
      10 [-]: CALL R1 2 2  ; var1 = var1(var2)
      11 [-]: LOADK R2 K1  ; var2 = "OnTouched"
      12 [-]: LOADB R3 0   ; var3 = false
      13 [-]: CALL R0 4 1  ; var0(var1, var2, var3)
      14 [-]: GETUPVAL R1 0; var1 = upvalues[0]
      15 [-]: GETTABLEKS R0 R1 K5; var0 = var1[0x75DC47BD]
      16 [-]: GETUPVAL R1 2; var1 = upvalues[2]
      17 [-]: LOADK R2 K1  ; var2 = "OnTouched"
      18 [-]: LOADB R3 0   ; var3 = false
      19 [-]: CALL R0 4 1  ; var0(var1, var2, var3)
      20 [-]: GETUPVAL R1 0; var1 = upvalues[0]
      21 [-]: GETTABLEKS R0 R1 K0; var0 = var1[0xD1B22BBF]
      22 [-]: GETUPVAL R1 3; var1 = upvalues[3]
      23 [-]: LOADK R2 K1  ; var2 = "OnTouched"
      24 [-]: LOADB R3 0   ; var3 = false
      25 [-]: CALL R0 4 1  ; var0(var1, var2, var3)
      26 [-]: GETUPVAL R1 0; var1 = upvalues[0]
      27 [-]: GETTABLEKS R0 R1 K0; var0 = var1[0xD1B22BBF]
      28 [-]: GETUPVAL R1 4; var1 = upvalues[4]
      29 [-]: LOADK R2 K6  ; var2 = "OnActivated"
      30 [-]: LOADB R3 0   ; var3 = false
      31 [-]: CALL R0 4 1  ; var0(var1, var2, var3)
      32 [-]: GETUPVAL R1 0; var1 = upvalues[0]
      33 [-]: GETTABLEKS R0 R1 K0; var0 = var1[0xD1B22BBF]
      34 [-]: GETUPVAL R1 5; var1 = upvalues[5]
      35 [-]: LOADK R2 K6  ; var2 = "OnActivated"
      36 [-]: LOADB R3 0   ; var3 = false
      37 [-]: CALL R0 4 1  ; var0(var1, var2, var3)
      38 [-]: GETUPVAL R1 0; var1 = upvalues[0]
      39 [-]: GETTABLEKS R0 R1 K0; var0 = var1[0xD1B22BBF]
      40 [-]: GETUPVAL R1 6; var1 = upvalues[6]
      41 [-]: LOADK R2 K1  ; var2 = "OnTouched"
      42 [-]: LOADB R3 0   ; var3 = false
      43 [-]: CALL R0 4 1  ; var0(var1, var2, var3)
      44 [-]: GETUPVAL R1 0; var1 = upvalues[0]
      45 [-]: GETTABLEKS R0 R1 K5; var0 = var1[0x75DC47BD]
      46 [-]: GETUPVAL R1 8; var1 = upvalues[8]
      47 [-]: LOADK R2 K7  ; var2 = "OnWavesComplete"
      48 [-]: LOADB R3 0   ; var3 = false
      49 [-]: CALL R0 4 2  ; var0 = var0(var1, var2, var3)
      50 [-]: SETUPVAL R0 7; upvalues[0] = var7
      51 [-]: GETUPVAL R1 0; var1 = upvalues[0]
      52 [-]: GETTABLEKS R0 R1 K5; var0 = var1[0x75DC47BD]
      53 [-]: GETUPVAL R1 10; var1 = upvalues[10]
      54 [-]: LOADK R2 K7  ; var2 = "OnWavesComplete"
      55 [-]: LOADB R3 0   ; var3 = false
      56 [-]: CALL R0 4 2  ; var0 = var0(var1, var2, var3)
      57 [-]: SETUPVAL R0 9; upvalues[0] = var9
      58 [-]: RETURN R0 0  ; 


; Name:            
; Defined at line: 259
; #Upvalues:       1
; #Parameters:     0
; Is_vararg:       0
; Max Stack Size:  5

       0 [-]: GETUPVAL R0 0; var0 = upvalues[0]
       1 [-]: NAMECALL R0 R0 K0; var1 = var0; var0 = var0[0xDE321E6F]
       2 [-]: CALL R0 2 2  ; var0 = var0(var1)
       3 [-]: LOADN R2 0   ; var2 = 0
       4 [-]: LOADN R3 0   ; var3 = 0
       5 [-]: LOADN R4 2   ; var4 = 2
       6 [-]: NAMECALL R0 R0 K1; var1 = var0; var0 = var0[0xC69087F6]
       7 [-]: CALL R0 5 1  ; var0(var1, var2, var3, var4)
       8 [-]: RETURN R0 0  ; 


; Name:            
; Defined at line: 263
; #Upvalues:       2
; #Parameters:     1
; Is_vararg:       0
; Max Stack Size:  7

       0 [-]: GETUPVAL R1 0; var1 = upvalues[0]
       1 [-]: GETIMPORT R3 1; var3 = 0x018C17B0
       2 [-]: LOADB R4 0   ; var4 = false
       3 [-]: NAMECALL R1 R1 K2; var2 = var1; var1 = var1[0x511D26B8]
       4 [-]: CALL R1 4 2  ; var1 = var1(var2, var3, var4)
       5 [-]: JUMPIFNOT R0 L0; goto L0 if not var0
       6 [-]: GETUPVAL R2 0; var2 = upvalues[0]
       7 [-]: NAMECALL R2 R2 K3; var3 = var2; var2 = var2[0xDE321E6F]
       8 [-]: CALL R2 2 2  ; var2 = var2(var3)
       9 [-]: LOADN R4 0   ; var4 = 0
      10 [-]: LOADN R5 0   ; var5 = 0
      11 [-]: LOADN R6 2   ; var6 = 2
      12 [-]: NAMECALL R2 R2 K4; var3 = var2; var2 = var2[0xC69087F6]
      13 [-]: CALL R2 5 1  ; var2(var3, var4, var5, var6)
L 0:  14 [-]: GETIMPORT R2 6; var2 = 0x89326C93
      15 [-]: GETUPVAL R4 1; var4 = upvalues[1]
      16 [-]: MOVE R5 R1   ; var5 = var1
      17 [-]: NAMECALL R2 R2 K7; var3 = var2; var2 = var2[0x765DAD71]
      18 [-]: CALL R2 4 2  ; var2 = var2(var3, var4, var5)
      19 [-]: FASTCALL1 64 R2 L1; 
      20 [-]: MOVE R4 R2   ; var4 = var2
      21 [-]: GETIMPORT R3 9; var3 = 0x7B998233
      22 [-]: CALL R3 2 2  ; var3 = var3(var4)
L 1:  23 [-]: JUMPIF R3 L2 ; goto L2 if var3
      24 [-]: MOVE R5 R2   ; var5 = var2
      25 [-]: NAMECALL R3 R1 K10; var4 = var1; var3 = var1[0x5E6704FF]
      26 [-]: CALL R3 3 1  ; var3(var4, var5)
L 2:  27 [-]: RETURN R1 1  ; 


; Name:            
; Defined at line: 277
; #Upvalues:       2
; #Parameters:     0
; Is_vararg:       0
; Max Stack Size:  5

       0 [-]: GETIMPORT R0 1; var0 = 0x89326C93
       1 [-]: GETUPVAL R2 0; var2 = upvalues[0]
       2 [-]: NAMECALL R0 R0 K2; var1 = var0; var0 = var0[0x46A0EBF5]
       3 [-]: CALL R0 3 2  ; var0 = var0(var1, var2)
       4 [-]: NAMECALL R1 R0 K3; var2 = var0; var1 = var0[0x383D2E7D]
       5 [-]: CALL R1 2 1  ; var1(var2)
       6 [-]: GETIMPORT R1 1; var1 = 0x89326C93
       7 [-]: GETIMPORT R3 5; var3 = 0x0469F296
       8 [-]: LOADK R4 K6  ; var4 = "QuestStartSlowWalk"
       9 [-]: CALL R3 2 0  ; var3, ... = var3(var4)
      10 [-]: NAMECALL R1 R1 K2; var2 = var1; var1 = var1[0x46A0EBF5]
      11 [-]: CALL R1 0 2  ; var1 = var1(var2, ...)
      12 [-]: MOVE R0 R1   ; var0 = var1
      13 [-]: GETIMPORT R3 5; var3 = 0x0469F296
      14 [-]: LOADK R4 K7  ; var4 = "HandleSlowWalk"
      15 [-]: CALL R3 2 2  ; var3 = var3(var4)
      16 [-]: LOADB R4 0   ; var4 = false
      17 [-]: NAMECALL R1 R0 K8; var2 = var0; var1 = var0[0xD5F7912B]
      18 [-]: CALL R1 4 1  ; var1(var2, var3, var4)
      19 [-]: NAMECALL R1 R0 K3; var2 = var0; var1 = var0[0x383D2E7D]
      20 [-]: CALL R1 2 1  ; var1(var2)
      21 [-]: GETIMPORT R1 1; var1 = 0x89326C93
      22 [-]: GETIMPORT R3 5; var3 = 0x0469F296
      23 [-]: LOADK R4 K9  ; var4 = "EvilTwin"
      24 [-]: CALL R3 2 0  ; var3, ... = var3(var4)
      25 [-]: NAMECALL R1 R1 K2; var2 = var1; var1 = var1[0x46A0EBF5]
      26 [-]: CALL R1 0 2  ; var1 = var1(var2, ...)
      27 [-]: SETUPVAL R1 1; upvalues[1] = var1
      28 [-]: GETUPVAL R2 1; var2 = upvalues[1]
      29 [-]: FASTCALL1 64 R2 L0; 
      30 [-]: GETIMPORT R1 11; var1 = 0x7B998233
      31 [-]: CALL R1 2 2  ; var1 = var1(var2)
L 0:  32 [-]: JUMPIF R1 L1 ; goto L1 if var1
      33 [-]: GETUPVAL R1 1; var1 = upvalues[1]
      34 [-]: LOADK R3 K12 ; var3 = "Show"
      35 [-]: NAMECALL R1 R1 K13; var2 = var1; var1 = var1[0x8EB2112D]
      36 [-]: CALL R1 3 1  ; var1(var2, var3)
L 1:  37 [-]: RETURN R0 0  ; 


; Name:            
; Defined at line: 291
; #Upvalues:       2
; #Parameters:     1
; Is_vararg:       0
; Max Stack Size:  11

       0 [-]: GETIMPORT R1 1; var1 = 0xC8802016
       1 [-]: GETUPVAL R2 0; var2 = upvalues[0]
       2 [-]: CALL R1 2 4  ; var1, var2, var3 = var1(var2)
       3 [-]: FORGPREP_INEXT R1 L2; 
L 0:   4 [-]: FASTCALL1 64 R5 L1; 
       5 [-]: MOVE R7 R5   ; var7 = var5
       6 [-]: GETIMPORT R6 3; var6 = 0x7B998233
       7 [-]: CALL R6 2 2  ; var6 = var6(var7)
L 1:   8 [-]: JUMPIF R6 L2 ; goto L2 if var6
       9 [-]: NAMECALL R6 R5 K4; var7 = var5; var6 = var5[0x22DA1852]
      10 [-]: CALL R6 2 2  ; var6 = var6(var7)
      11 [-]: GETUPVAL R8 1; var8 = upvalues[1]
      12 [-]: NAMECALL R9 R6 K5; var10 = var6; var9 = var6[0x6D604BA7]
      13 [-]: CALL R9 2 2  ; var9 = var9(var10)
      14 [-]: GETTABLE R7 R8 R9; var7 = var8[var9]
      15 [-]: JUMPIFNOTEQ R7 R0 L2; goto L2 if var7 ~= var-1811609780
      16 [-]: NAMECALL R7 R5 K6; var8 = var5; var7 = var5[0xD8140B94]
      17 [-]: CALL R7 2 2  ; var7 = var7(var8)
      18 [-]: JUMPIF R7 L2 ; goto L2 if var7
      19 [-]: NAMECALL R7 R5 K7; var8 = var5; var7 = var5[0x860FB98B]
      20 [-]: CALL R7 2 2  ; var7 = var7(var8)
      21 [-]: JUMPIF R7 L2 ; goto L2 if var7
      22 [-]: NAMECALL R7 R5 K8; var8 = var5; var7 = var5[0xA344563B]
      23 [-]: CALL R7 2 1  ; var7(var8)
      24 [-]: RETURN R0 0  ; 
L 2:  25 [-]: FORGLOOP R1 L0 2 [inext]; 
      26 [-]: RETURN R0 0  ; 


; Name:            
; Defined at line: 305
; #Upvalues:       2
; #Parameters:     0
; Is_vararg:       0
; Max Stack Size:  4

       0 [-]: GETIMPORT R1 1; var1 = 0xBE190284
       1 [-]: NAMECALL R1 R1 K2; var2 = var1; var1 = var1[0xEF893AEC]
       2 [-]: CALL R1 2 2  ; var1 = var1(var2)
       3 [-]: GETTABLEKS R0 R1 K3; var0 = var1["enemySpec"]
       4 [-]: SETUPVAL R0 0; upvalues[0] = var0
       5 [-]: GETIMPORT R0 5; var0 = 0x89326C93
       6 [-]: NAMECALL R0 R0 K6; var1 = var0; var0 = var0[0x29EF273D]
       7 [-]: CALL R0 2 2  ; var0 = var0(var1)
       8 [-]: NAMECALL R1 R0 K7; var2 = var0; var1 = var0[0x66905CB0]
       9 [-]: CALL R1 2 2  ; var1 = var1(var2)
      10 [-]: SETUPVAL R1 1; upvalues[1] = var1
      11 [-]: GETUPVAL R1 1; var1 = upvalues[1]
      12 [-]: LOADB R3 0   ; var3 = false
      13 [-]: NAMECALL R1 R1 K8; var2 = var1; var1 = var1[0x2FAEAD12]
      14 [-]: CALL R1 3 1  ; var1(var2, var3)
      15 [-]: RETURN R0 0  ; 


; Name:            
; Defined at line: 314
; #Upvalues:       1
; #Parameters:     0
; Is_vararg:       0
; Max Stack Size:  2

       0 [-]: GETUPVAL R1 0; var1 = upvalues[0]
       1 [-]: FASTCALL1 64 R1 L0; 
       2 [-]: GETIMPORT R0 1; var0 = 0x7B998233
       3 [-]: CALL R0 2 2  ; var0 = var0(var1)
L 0:   4 [-]: JUMPIF R0 L1 ; goto L1 if var0
       5 [-]: GETUPVAL R0 0; var0 = upvalues[0]
       6 [-]: NAMECALL R0 R0 K2; var1 = var0; var0 = var0[0x1C84839C]
       7 [-]: CALL R0 2 2  ; var0 = var0(var1)
       8 [-]: JUMPIFNOT R0 L1; goto L1 if not var0
       9 [-]: LOADB R0 1   ; var0 = true
      10 [-]: RETURN R0 1  ; 
L 1:  11 [-]: LOADB R0 0   ; var0 = false
      12 [-]: RETURN R0 1  ; 


; Name:            
; Defined at line: 321
; #Upvalues:       44
; #Parameters:     1
; Is_vararg:       0
; Max Stack Size:  13

       0 [-]: GETIMPORT R1 1; var1 = 0x3D106989
       1 [-]: LOADK R3 K2  ; var3 = "On State Changed to "
       2 [-]: GETUPVAL R8 0; var8 = upvalues[0]
       3 [-]: GETTABLE R7 R8 R0; var7 = var8[var0]
       4 [-]: GETTABLEKS R6 R7 K4; var6 = var7["name"]
       5 [-]: ORK R5 R6 K3 ; var5 = var6 or "State Name Not Found"
       6 [-]: MOVE R4 R5   ; var4 = var5
       7 [-]: CONCAT R2 R3 R4; var2 = var3 .. var4
       8 [-]: CALL R1 2 1  ; var1(var2)
       9 [-]: GETUPVAL R1 1; var1 = upvalues[1]
      10 [-]: MOVE R2 R0   ; var2 = var0
      11 [-]: CALL R1 2 1  ; var1(var2)
      12 [-]: GETUPVAL R2 2; var2 = upvalues[2]
      13 [-]: GETTABLEKS R1 R2 K5; var1 = var2["SETUP"]
      14 [-]: JUMPIFNOTEQ R0 R1 L0; goto L0 if var0 ~= var459297
      15 [-]: GETIMPORT R2 7; var2 = 0xBE190284
      16 [-]: NAMECALL R2 R2 K8; var3 = var2; var2 = var2[0xEF893AEC]
      17 [-]: CALL R2 2 2  ; var2 = var2(var3)
      18 [-]: GETTABLEKS R1 R2 K9; var1 = var2["enemySpec"]
      19 [-]: SETUPVAL R1 3; upvalues[1] = var3
      20 [-]: GETIMPORT R1 11; var1 = 0x89326C93
      21 [-]: NAMECALL R1 R1 K12; var2 = var1; var1 = var1[0x29EF273D]
      22 [-]: CALL R1 2 2  ; var1 = var1(var2)
      23 [-]: NAMECALL R2 R1 K13; var3 = var1; var2 = var1[0x66905CB0]
      24 [-]: CALL R2 2 2  ; var2 = var2(var3)
      25 [-]: SETUPVAL R2 4; upvalues[2] = var4
      26 [-]: GETUPVAL R2 4; var2 = upvalues[4]
      27 [-]: LOADB R4 0   ; var4 = false
      28 [-]: NAMECALL R2 R2 K14; var3 = var2; var2 = var2[0x2FAEAD12]
      29 [-]: CALL R2 3 1  ; var2(var3, var4)
      30 [-]: GETUPVAL R1 5; var1 = upvalues[5]
      31 [-]: CALL R1 1 1  ; var1()
      32 [-]: GETUPVAL R2 6; var2 = upvalues[6]
      33 [-]: GETTABLEKS R1 R2 K15; var1 = var2[0xB112401F]
      34 [-]: LOADB R2 0   ; var2 = false
      35 [-]: LOADB R3 0   ; var3 = false
      36 [-]: CALL R1 3 1  ; var1(var2, var3)
      37 [-]: GETUPVAL R1 7; var1 = upvalues[7]
      38 [-]: GETUPVAL R4 2; var4 = upvalues[2]
      39 [-]: GETTABLEKS R3 R4 K16; var3 = var4["FOLLOW_VOICE"]
      40 [-]: NAMECALL R1 R1 K17; var2 = var1; var1 = var1[0x8ABFF40E]
      41 [-]: CALL R1 3 1  ; var1(var2, var3)
      42 [-]: JUMP L61     ; goto L61
L 0:  43 [-]: GETUPVAL R2 2; var2 = upvalues[2]
      44 [-]: GETTABLEKS R1 R2 K16; var1 = var2["FOLLOW_VOICE"]
      45 [-]: JUMPIFNOTEQ R0 R1 L3; goto L3 if var0 ~= var524860
      46 [-]: GETUPVAL R2 8; var2 = upvalues[8]
      47 [-]: GETTABLEKS R1 R2 K18; var1 = var2[0xA1DF01D6]
      48 [-]: GETUPVAL R3 9; var3 = upvalues[9]
      49 [-]: GETTABLEKS R2 R3 K19; var2 = var3["FIND_SLEEPER"]
      50 [-]: CALL R1 2 1  ; var1(var2)
      51 [-]: GETUPVAL R2 6; var2 = upvalues[6]
      52 [-]: GETTABLEKS R1 R2 K20; var1 = var2[0xC474A99E]
      53 [-]: GETIMPORT R2 22; var2 = 0x0469F296
      54 [-]: LOADK R3 K23 ; var3 = "EntratiQuestVialLabDoorsLock"
      55 [-]: CALL R2 2 2  ; var2 = var2(var3)
      56 [-]: LOADK R3 K24 ; var3 = "Execute"
      57 [-]: CALL R1 3 1  ; var1(var2, var3)
      58 [-]: GETIMPORT R1 11; var1 = 0x89326C93
      59 [-]: GETUPVAL R3 10; var3 = upvalues[10]
      60 [-]: NAMECALL R1 R1 K25; var2 = var1; var1 = var1[0x46A0EBF5]
      61 [-]: CALL R1 3 2  ; var1 = var1(var2, var3)
      62 [-]: FASTCALL1 64 R1 L1; 
      63 [-]: MOVE R3 R1   ; var3 = var1
      64 [-]: GETIMPORT R2 27; var2 = 0x7B998233
      65 [-]: CALL R2 2 2  ; var2 = var2(var3)
L 1:  66 [-]: JUMPIF R2 L2 ; goto L2 if var2
      67 [-]: NAMECALL R2 R1 K28; var3 = var1; var2 = var1[0x383D2E7D]
      68 [-]: CALL R2 2 1  ; var2(var3)
L 2:  69 [-]: GETIMPORT R2 11; var2 = 0x89326C93
      70 [-]: GETIMPORT R4 22; var4 = 0x0469F296
      71 [-]: LOADK R5 K29 ; var5 = "QuestStage1MechRoomWp"
      72 [-]: CALL R4 2 0  ; var4, ... = var4(var5)
      73 [-]: NAMECALL R2 R2 K25; var3 = var2; var2 = var2[0x46A0EBF5]
      74 [-]: CALL R2 0 2  ; var2 = var2(var3, ...)
      75 [-]: GETUPVAL R4 11; var4 = upvalues[11]
      76 [-]: GETTABLEKS R3 R4 K30; var3 = var4[0x237A6578]
      77 [-]: GETUPVAL R4 12; var4 = upvalues[12]
      78 [-]: LOADB R5 1   ; var5 = true
      79 [-]: NAMECALL R6 R2 K31; var7 = var2; var6 = var2[0xD1586535]
      80 [-]: CALL R6 2 2  ; var6 = var6(var7)
      81 [-]: GETIMPORT R7 33; var7 = 0xB7CBD06B
      82 [-]: LOADN R8 0   ; var8 = 0
      83 [-]: LOADN R9 1000; var9 = 1000
      84 [-]: CALL R7 3 2  ; var7 = var7(var8, var9)
      85 [-]: LOADB R8 1   ; var8 = true
      86 [-]: CALL R3 6 1  ; var3(var4, var5, var6, var7, var8)
      87 [-]: JUMP L61     ; goto L61
L 3:  88 [-]: GETUPVAL R2 2; var2 = upvalues[2]
      89 [-]: GETTABLEKS R1 R2 K34; var1 = var2["MECH"]
      90 [-]: JUMPIFNOTEQ R0 R1 L7; goto L7 if var0 ~= var721185
      91 [-]: GETIMPORT R1 11; var1 = 0x89326C93
      92 [-]: GETUPVAL R3 13; var3 = upvalues[13]
      93 [-]: NAMECALL R1 R1 K35; var2 = var1; var1 = var1[0xC7FCADA9]
      94 [-]: CALL R1 3 2  ; var1 = var1(var2, var3)
      95 [-]: GETIMPORT R2 37; var2 = 0xC8802016
      96 [-]: MOVE R3 R1   ; var3 = var1
      97 [-]: CALL R2 2 4  ; var2, var3, var4 = var2(var3)
      98 [-]: FORGPREP_INEXT R2 L6; 
L 4:  99 [-]: FASTCALL1 64 R6 L5; 
     100 [-]: MOVE R8 R6   ; var8 = var6
     101 [-]: GETIMPORT R7 27; var7 = 0x7B998233
     102 [-]: CALL R7 2 2  ; var7 = var7(var8)
L 5: 103 [-]: JUMPIF R7 L6 ; goto L6 if var7
     104 [-]: NAMECALL R7 R6 K28; var8 = var6; var7 = var6[0x383D2E7D]
     105 [-]: CALL R7 2 1  ; var7(var8)
     106 [-]: NAMECALL R7 R6 K38; var8 = var6; var7 = var6[0x36FCC811]
     107 [-]: CALL R7 2 1  ; var7(var8)
L 6: 108 [-]: FORGLOOP R2 L4 2 [inext]; 
     109 [-]: GETUPVAL R3 8; var3 = upvalues[8]
     110 [-]: GETTABLEKS R2 R3 K39; var2 = var3[0xDC3B2033]
     111 [-]: CALL R2 1 1  ; var2()
     112 [-]: GETUPVAL R3 11; var3 = upvalues[11]
     113 [-]: GETTABLEKS R2 R3 K30; var2 = var3[0x237A6578]
     114 [-]: GETUPVAL R3 12; var3 = upvalues[12]
     115 [-]: LOADB R4 0   ; var4 = false
     116 [-]: CALL R2 3 1  ; var2(var3, var4)
     117 [-]: GETUPVAL R3 6; var3 = upvalues[6]
     118 [-]: GETTABLEKS R2 R3 K20; var2 = var3[0xC474A99E]
     119 [-]: GETIMPORT R3 22; var3 = 0x0469F296
     120 [-]: LOADK R4 K40 ; var4 = "QuestSpottedMechsTrigger"
     121 [-]: CALL R3 2 2  ; var3 = var3(var4)
     122 [-]: LOADK R4 K41 ; var4 = "Enable"
     123 [-]: CALL R2 3 1  ; var2(var3, var4)
     124 [-]: JUMP L61     ; goto L61
L 7: 125 [-]: GETUPVAL R2 2; var2 = upvalues[2]
     126 [-]: GETTABLEKS R1 R2 K42; var1 = var2["DEFEAT_MECH"]
     127 [-]: JUMPIFNOTEQ R0 R1 L10; goto L10 if var0 ~= var524860
     128 [-]: GETUPVAL R2 8; var2 = upvalues[8]
     129 [-]: GETTABLEKS R1 R2 K18; var1 = var2[0xA1DF01D6]
     130 [-]: GETUPVAL R3 9; var3 = upvalues[9]
     131 [-]: GETTABLEKS R2 R3 K42; var2 = var3["DEFEAT_MECH"]
     132 [-]: CALL R1 2 1  ; var1(var2)
     133 [-]: GETUPVAL R1 4; var1 = upvalues[4]
     134 [-]: LOADB R3 1   ; var3 = true
     135 [-]: NAMECALL R1 R1 K43; var2 = var1; var1 = var1[0xE603BAB2]
     136 [-]: CALL R1 3 1  ; var1(var2, var3)
     137 [-]: GETUPVAL R2 6; var2 = upvalues[6]
     138 [-]: GETTABLEKS R1 R2 K44; var1 = var2[0xFBF314DF]
     139 [-]: GETUPVAL R2 14; var2 = upvalues[14]
     140 [-]: NAMECALL R2 R2 K31; var3 = var2; var2 = var2[0xD1586535]
     141 [-]: CALL R2 2 2  ; var2 = var2(var3)
     142 [-]: LOADN R3 200 ; var3 = 200
     143 [-]: NEWTABLE R4 0 2; var4 = {}
     144 [-]: GETUPVAL R5 15; var5 = upvalues[15]
     145 [-]: GETUPVAL R6 16; var6 = upvalues[16]
     146 [-]: SETLIST R4 R5 2 [1]; var4[1] = var5; var4[2] = var6; var4[3] = var7; 
     147 [-]: CALL R1 4 2  ; var1 = var1(var2, var3, var4)
     148 [-]: GETIMPORT R2 37; var2 = 0xC8802016
     149 [-]: MOVE R3 R1   ; var3 = var1
     150 [-]: CALL R2 2 4  ; var2, var3, var4 = var2(var3)
     151 [-]: FORGPREP_INEXT R2 L9; 
L 8: 152 [-]: GETUPVAL R9 17; var9 = upvalues[17]
     153 [-]: GETIMPORT R10 22; var10 = 0x0469F296
     154 [-]: LOADK R11 K45; var11 = "GAME_C1_SPINE3"
     155 [-]: CALL R10 2 0 ; var10, ... = var10(var11)
     156 [-]: NAMECALL R7 R6 K46; var8 = var6; var7 = var6[0x47901F07]
     157 [-]: CALL R7 0 1  ; var7(var8, ...)
L 9: 158 [-]: FORGLOOP R2 L8 2 [inext]; 
     159 [-]: JUMP L61     ; goto L61
L10: 160 [-]: GETUPVAL R2 2; var2 = upvalues[2]
     161 [-]: GETTABLEKS R1 R2 K47; var1 = var2["FOLLOW_VOICE_AGAIN"]
     162 [-]: JUMPIFNOTEQ R0 R1 L15; goto L15 if var0 ~= var262460
     163 [-]: GETUPVAL R1 4; var1 = upvalues[4]
     164 [-]: LOADB R3 0   ; var3 = false
     165 [-]: NAMECALL R1 R1 K43; var2 = var1; var1 = var1[0xE603BAB2]
     166 [-]: CALL R1 3 1  ; var1(var2, var3)
     167 [-]: LOADB R1 1   ; var1 = true
     168 [-]: SETUPVAL R1 18; upvalues[1] = var18
     169 [-]: GETIMPORT R1 11; var1 = 0x89326C93
     170 [-]: GETIMPORT R3 22; var3 = 0x0469F296
     171 [-]: LOADK R4 K48 ; var4 = "MITWFailureFlicker"
     172 [-]: CALL R3 2 0  ; var3, ... = var3(var4)
     173 [-]: NAMECALL R1 R1 K25; var2 = var1; var1 = var1[0x46A0EBF5]
     174 [-]: CALL R1 0 2  ; var1 = var1(var2, ...)
     175 [-]: FASTCALL1 64 R1 L11; 
     176 [-]: MOVE R3 R1   ; var3 = var1
     177 [-]: GETIMPORT R2 27; var2 = 0x7B998233
     178 [-]: CALL R2 2 2  ; var2 = var2(var3)
L11: 179 [-]: JUMPIF R2 L12; goto L12 if var2
     180 [-]: LOADK R4 K24 ; var4 = "Execute"
     181 [-]: NAMECALL R2 R1 K49; var3 = var1; var2 = var1[0x8EB2112D]
     182 [-]: CALL R2 3 1  ; var2(var3, var4)
L12: 183 [-]: GETUPVAL R3 8; var3 = upvalues[8]
     184 [-]: GETTABLEKS R2 R3 K39; var2 = var3[0xDC3B2033]
     185 [-]: CALL R2 1 1  ; var2()
     186 [-]: GETUPVAL R3 6; var3 = upvalues[6]
     187 [-]: GETTABLEKS R2 R3 K20; var2 = var3[0xC474A99E]
     188 [-]: GETIMPORT R3 22; var3 = 0x0469F296
     189 [-]: LOADK R4 K50 ; var4 = "QuestMechCornerRoom"
     190 [-]: CALL R3 2 2  ; var3 = var3(var4)
     191 [-]: LOADK R4 K51 ; var4 = "Reset"
     192 [-]: CALL R2 3 1  ; var2(var3, var4)
     193 [-]: GETIMPORT R2 11; var2 = 0x89326C93
     194 [-]: GETIMPORT R4 53; var4 = 0x738D40A2
     195 [-]: GETUPVAL R5 14; var5 = upvalues[14]
     196 [-]: NAMECALL R5 R5 K31; var6 = var5; var5 = var5[0xD1586535]
     197 [-]: CALL R5 2 2  ; var5 = var5(var6)
     198 [-]: GETUPVAL R6 14; var6 = upvalues[14]
     199 [-]: NAMECALL R6 R6 K54; var7 = var6; var6 = var6[0xCB3851B8]
     200 [-]: CALL R6 2 0  ; var6, ... = var6(var7)
     201 [-]: NAMECALL R2 R2 K55; var3 = var2; var2 = var2[0x05909209]
     202 [-]: CALL R2 0 1  ; var2(var3, ...)
     203 [-]: GETUPVAL R3 19; var3 = upvalues[19]
     204 [-]: GETTABLEKS R2 R3 K56; var2 = var3[0x659D451F]
     205 [-]: GETIMPORT R3 58; var3 = 0xB68A3BD5
     206 [-]: CALL R2 2 1  ; var2(var3)
     207 [-]: GETUPVAL R3 20; var3 = upvalues[20]
     208 [-]: GETTABLEKS R2 R3 K59; var2 = var3[0x9742B85B]
     209 [-]: GETUPVAL R3 21; var3 = upvalues[21]
     210 [-]: GETIMPORT R4 22; var4 = 0x0469F296
     211 [-]: LOADK R5 K60 ; var5 = "DEnterTheLabs0141Loid"
     212 [-]: CALL R4 2 2  ; var4 = var4(var5)
     213 [-]: LOADB R5 0   ; var5 = false
     214 [-]: LOADB R6 1   ; var6 = true
     215 [-]: CALL R2 5 1  ; var2(var3, var4, var5, var6)
     216 [-]: GETUPVAL R3 8; var3 = upvalues[8]
     217 [-]: GETTABLEKS R2 R3 K18; var2 = var3[0xA1DF01D6]
     218 [-]: GETUPVAL R4 9; var4 = upvalues[9]
     219 [-]: GETTABLEKS R3 R4 K19; var3 = var4["FIND_SLEEPER"]
     220 [-]: CALL R2 2 1  ; var2(var3)
     221 [-]: GETIMPORT R2 11; var2 = 0x89326C93
     222 [-]: GETUPVAL R4 22; var4 = upvalues[22]
     223 [-]: NAMECALL R2 R2 K25; var3 = var2; var2 = var2[0x46A0EBF5]
     224 [-]: CALL R2 3 2  ; var2 = var2(var3, var4)
     225 [-]: FASTCALL1 64 R2 L13; 
     226 [-]: MOVE R4 R2   ; var4 = var2
     227 [-]: GETIMPORT R3 27; var3 = 0x7B998233
     228 [-]: CALL R3 2 2  ; var3 = var3(var4)
L13: 229 [-]: JUMPIF R3 L14; goto L14 if var3
     230 [-]: GETUPVAL R4 11; var4 = upvalues[11]
     231 [-]: GETTABLEKS R3 R4 K30; var3 = var4[0x237A6578]
     232 [-]: GETUPVAL R4 12; var4 = upvalues[12]
     233 [-]: LOADB R5 1   ; var5 = true
     234 [-]: NAMECALL R6 R2 K31; var7 = var2; var6 = var2[0xD1586535]
     235 [-]: CALL R6 2 0  ; var6, ... = var6(var7)
     236 [-]: CALL R3 0 1  ; var3(var4, ...)
L14: 237 [-]: GETUPVAL R3 4; var3 = upvalues[4]
     238 [-]: GETUPVAL R5 12; var5 = upvalues[12]
     239 [-]: NAMECALL R3 R3 K61; var4 = var3; var3 = var3[0xE2871589]
     240 [-]: CALL R3 3 1  ; var3(var4, var5)
     241 [-]: JUMP L61     ; goto L61
L15: 242 [-]: GETUPVAL R2 2; var2 = upvalues[2]
     243 [-]: GETTABLEKS R1 R2 K62; var1 = var2["GRIMOIRE"]
     244 [-]: JUMPIFNOTEQ R0 R1 L17; goto L17 if var0 ~= var393788
     245 [-]: GETUPVAL R2 6; var2 = upvalues[6]
     246 [-]: GETTABLEKS R1 R2 K15; var1 = var2[0xB112401F]
     247 [-]: LOADB R2 0   ; var2 = false
     248 [-]: LOADB R3 0   ; var3 = false
     249 [-]: CALL R1 3 1  ; var1(var2, var3)
     250 [-]: LOADB R1 0   ; var1 = false
     251 [-]: SETUPVAL R1 18; upvalues[1] = var18
     252 [-]: GETIMPORT R2 7; var2 = 0xBE190284
     253 [-]: NAMECALL R2 R2 K8; var3 = var2; var2 = var2[0xEF893AEC]
     254 [-]: CALL R2 2 2  ; var2 = var2(var3)
     255 [-]: GETTABLEKS R1 R2 K9; var1 = var2["enemySpec"]
     256 [-]: SETUPVAL R1 3; upvalues[1] = var3
     257 [-]: GETIMPORT R1 11; var1 = 0x89326C93
     258 [-]: NAMECALL R1 R1 K12; var2 = var1; var1 = var1[0x29EF273D]
     259 [-]: CALL R1 2 2  ; var1 = var1(var2)
     260 [-]: NAMECALL R2 R1 K13; var3 = var1; var2 = var1[0x66905CB0]
     261 [-]: CALL R2 2 2  ; var2 = var2(var3)
     262 [-]: SETUPVAL R2 4; upvalues[2] = var4
     263 [-]: GETUPVAL R2 4; var2 = upvalues[4]
     264 [-]: LOADB R4 0   ; var4 = false
     265 [-]: NAMECALL R2 R2 K14; var3 = var2; var2 = var2[0x2FAEAD12]
     266 [-]: CALL R2 3 1  ; var2(var3, var4)
     267 [-]: GETUPVAL R2 8; var2 = upvalues[8]
     268 [-]: GETTABLEKS R1 R2 K18; var1 = var2[0xA1DF01D6]
     269 [-]: GETUPVAL R3 9; var3 = upvalues[9]
     270 [-]: GETTABLEKS R2 R3 K63; var2 = var3["COLLECT_GRIMOIRE"]
     271 [-]: CALL R1 2 1  ; var1(var2)
     272 [-]: GETUPVAL R2 20; var2 = upvalues[20]
     273 [-]: GETTABLEKS R1 R2 K59; var1 = var2[0x9742B85B]
     274 [-]: GETUPVAL R2 21; var2 = upvalues[21]
     275 [-]: GETIMPORT R3 22; var3 = 0x0469F296
     276 [-]: LOADK R4 K64 ; var4 = "DEnterTheLabs0130"
     277 [-]: CALL R3 2 2  ; var3 = var3(var4)
     278 [-]: LOADB R4 0   ; var4 = false
     279 [-]: LOADB R5 1   ; var5 = true
     280 [-]: CALL R1 5 1  ; var1(var2, var3, var4, var5)
     281 [-]: GETIMPORT R1 11; var1 = 0x89326C93
     282 [-]: GETUPVAL R3 23; var3 = upvalues[23]
     283 [-]: NAMECALL R1 R1 K25; var2 = var1; var1 = var1[0x46A0EBF5]
     284 [-]: CALL R1 3 2  ; var1 = var1(var2, var3)
     285 [-]: FASTCALL1 64 R1 L16; 
     286 [-]: MOVE R3 R1   ; var3 = var1
     287 [-]: GETIMPORT R2 27; var2 = 0x7B998233
     288 [-]: CALL R2 2 2  ; var2 = var2(var3)
L16: 289 [-]: JUMPIF R2 L61; goto L61 if var2
     290 [-]: NAMECALL R2 R1 K28; var3 = var1; var2 = var1[0x383D2E7D]
     291 [-]: CALL R2 2 1  ; var2(var3)
     292 [-]: JUMP L61     ; goto L61
L17: 293 [-]: GETUPVAL R2 2; var2 = upvalues[2]
     294 [-]: GETTABLEKS R1 R2 K65; var1 = var2["DEFEAT_MECH_GRIMOIRE"]
     295 [-]: JUMPIFNOTEQ R0 R1 L23; goto L23 if var0 ~= var721468
     296 [-]: GETUPVAL R2 11; var2 = upvalues[11]
     297 [-]: GETTABLEKS R1 R2 K30; var1 = var2[0x237A6578]
     298 [-]: GETUPVAL R2 12; var2 = upvalues[12]
     299 [-]: LOADB R3 0   ; var3 = false
     300 [-]: CALL R1 3 1  ; var1(var2, var3)
     301 [-]: GETUPVAL R2 8; var2 = upvalues[8]
     302 [-]: GETTABLEKS R1 R2 K18; var1 = var2[0xA1DF01D6]
     303 [-]: GETUPVAL R3 9; var3 = upvalues[9]
     304 [-]: GETTABLEKS R2 R3 K42; var2 = var3["DEFEAT_MECH"]
     305 [-]: CALL R1 2 1  ; var1(var2)
     306 [-]: GETIMPORT R1 11; var1 = 0x89326C93
     307 [-]: GETUPVAL R3 24; var3 = upvalues[24]
     308 [-]: NAMECALL R1 R1 K35; var2 = var1; var1 = var1[0xC7FCADA9]
     309 [-]: CALL R1 3 2  ; var1 = var1(var2, var3)
     310 [-]: GETIMPORT R2 37; var2 = 0xC8802016
     311 [-]: MOVE R3 R1   ; var3 = var1
     312 [-]: CALL R2 2 4  ; var2, var3, var4 = var2(var3)
     313 [-]: FORGPREP_INEXT R2 L20; 
L18: 314 [-]: FASTCALL1 64 R6 L19; 
     315 [-]: MOVE R8 R6   ; var8 = var6
     316 [-]: GETIMPORT R7 27; var7 = 0x7B998233
     317 [-]: CALL R7 2 2  ; var7 = var7(var8)
L19: 318 [-]: JUMPIF R7 L20; goto L20 if var7
     319 [-]: NAMECALL R7 R6 K28; var8 = var6; var7 = var6[0x383D2E7D]
     320 [-]: CALL R7 2 1  ; var7(var8)
     321 [-]: LOADK R9 K51 ; var9 = "Reset"
     322 [-]: NAMECALL R7 R6 K49; var8 = var6; var7 = var6[0x8EB2112D]
     323 [-]: CALL R7 3 1  ; var7(var8, var9)
L20: 324 [-]: FORGLOOP R2 L18 2 [inext]; 
     325 [-]: GETIMPORT R2 11; var2 = 0x89326C93
     326 [-]: GETUPVAL R4 25; var4 = upvalues[25]
     327 [-]: NAMECALL R2 R2 K25; var3 = var2; var2 = var2[0x46A0EBF5]
     328 [-]: CALL R2 3 2  ; var2 = var2(var3, var4)
     329 [-]: FASTCALL1 64 R2 L21; 
     330 [-]: MOVE R4 R2   ; var4 = var2
     331 [-]: GETIMPORT R3 27; var3 = 0x7B998233
     332 [-]: CALL R3 2 2  ; var3 = var3(var4)
L21: 333 [-]: JUMPIF R3 L22; goto L22 if var3
     334 [-]: LOADK R5 K41 ; var5 = "Enable"
     335 [-]: NAMECALL R3 R2 K49; var4 = var2; var3 = var2[0x8EB2112D]
     336 [-]: CALL R3 3 1  ; var3(var4, var5)
L22: 337 [-]: GETUPVAL R4 20; var4 = upvalues[20]
     338 [-]: GETTABLEKS R3 R4 K59; var3 = var4[0x9742B85B]
     339 [-]: GETUPVAL R4 21; var4 = upvalues[21]
     340 [-]: GETIMPORT R5 22; var5 = 0x0469F296
     341 [-]: LOADK R6 K66 ; var6 = "DEnterTheLabs0131Loid"
     342 [-]: CALL R5 2 2  ; var5 = var5(var6)
     343 [-]: LOADB R6 0   ; var6 = false
     344 [-]: LOADB R7 1   ; var7 = true
     345 [-]: CALL R3 5 1  ; var3(var4, var5, var6, var7)
     346 [-]: GETUPVAL R4 8; var4 = upvalues[8]
     347 [-]: GETTABLEKS R3 R4 K67; var3 = var4[0xD10F3DE8]
     348 [-]: LOADK R4 K68 ; var4 = "/Lotus/Language/EntratiLab/EntratiQuest/GrimoireAltFireHint"
     349 [-]: LOADN R5 5   ; var5 = 5
     350 [-]: CALL R3 3 1  ; var3(var4, var5)
     351 [-]: JUMP L61     ; goto L61
L23: 352 [-]: GETUPVAL R2 2; var2 = upvalues[2]
     353 [-]: GETTABLEKS R1 R2 K69; var1 = var2["GOTO_MITW"]
     354 [-]: JUMPIFNOTEQ R0 R1 L31; goto L31 if var0 ~= var721185
     355 [-]: GETIMPORT R1 11; var1 = 0x89326C93
     356 [-]: GETIMPORT R3 22; var3 = 0x0469F296
     357 [-]: LOADK R4 K70 ; var4 = "QuestNecramechVialForwarder"
     358 [-]: CALL R3 2 0  ; var3, ... = var3(var4)
     359 [-]: NAMECALL R1 R1 K35; var2 = var1; var1 = var1[0xC7FCADA9]
     360 [-]: CALL R1 0 2  ; var1 = var1(var2, ...)
     361 [-]: GETIMPORT R2 37; var2 = 0xC8802016
     362 [-]: MOVE R3 R1   ; var3 = var1
     363 [-]: CALL R2 2 4  ; var2, var3, var4 = var2(var3)
     364 [-]: FORGPREP_INEXT R2 L25; 
L24: 365 [-]: LOADK R9 K71 ; var9 = "TriggerPort"
     366 [-]: NAMECALL R7 R6 K49; var8 = var6; var7 = var6[0x8EB2112D]
     367 [-]: CALL R7 3 1  ; var7(var8, var9)
L25: 368 [-]: FORGLOOP R2 L24 2 [inext]; 
     369 [-]: GETIMPORT R2 11; var2 = 0x89326C93
     370 [-]: GETUPVAL R4 26; var4 = upvalues[26]
     371 [-]: NAMECALL R2 R2 K35; var3 = var2; var2 = var2[0xC7FCADA9]
     372 [-]: CALL R2 3 2  ; var2 = var2(var3, var4)
     373 [-]: GETIMPORT R3 37; var3 = 0xC8802016
     374 [-]: MOVE R4 R2   ; var4 = var2
     375 [-]: CALL R3 2 4  ; var3, var4, var5 = var3(var4)
     376 [-]: FORGPREP_INEXT R3 L27; 
L26: 377 [-]: LOADK R10 K41; var10 = "Enable"
     378 [-]: NAMECALL R8 R7 K49; var9 = var7; var8 = var7[0x8EB2112D]
     379 [-]: CALL R8 3 1  ; var8(var9, var10)
L27: 380 [-]: FORGLOOP R3 L26 2 [inext]; 
     381 [-]: GETUPVAL R4 6; var4 = upvalues[6]
     382 [-]: GETTABLEKS R3 R4 K20; var3 = var4[0xC474A99E]
     383 [-]: GETIMPORT R4 22; var4 = 0x0469F296
     384 [-]: LOADK R5 K72 ; var5 = "EntratiQuestVialLabDoorsUnlock"
     385 [-]: CALL R4 2 2  ; var4 = var4(var5)
     386 [-]: LOADK R5 K24 ; var5 = "Execute"
     387 [-]: CALL R3 3 1  ; var3(var4, var5)
     388 [-]: GETUPVAL R3 27; var3 = upvalues[27]
     389 [-]: JUMPIF R3 L28; goto L28 if var3
     390 [-]: GETUPVAL R3 28; var3 = upvalues[28]
     391 [-]: CALL R3 1 1  ; var3()
L28: 392 [-]: GETUPVAL R4 8; var4 = upvalues[8]
     393 [-]: GETTABLEKS R3 R4 K18; var3 = var4[0xA1DF01D6]
     394 [-]: GETUPVAL R5 9; var5 = upvalues[9]
     395 [-]: GETTABLEKS R4 R5 K19; var4 = var5["FIND_SLEEPER"]
     396 [-]: CALL R3 2 1  ; var3(var4)
     397 [-]: GETUPVAL R4 20; var4 = upvalues[20]
     398 [-]: GETTABLEKS R3 R4 K59; var3 = var4[0x9742B85B]
     399 [-]: GETUPVAL R4 21; var4 = upvalues[21]
     400 [-]: GETIMPORT R5 22; var5 = 0x0469F296
     401 [-]: LOADK R6 K73 ; var6 = "DEnterTheLabs0140"
     402 [-]: CALL R5 2 2  ; var5 = var5(var6)
     403 [-]: LOADB R6 0   ; var6 = false
     404 [-]: LOADB R7 0   ; var7 = false
     405 [-]: CALL R3 5 1  ; var3(var4, var5, var6, var7)
     406 [-]: GETIMPORT R3 11; var3 = 0x89326C93
     407 [-]: GETUPVAL R5 29; var5 = upvalues[29]
     408 [-]: NAMECALL R3 R3 K25; var4 = var3; var3 = var3[0x46A0EBF5]
     409 [-]: CALL R3 3 2  ; var3 = var3(var4, var5)
     410 [-]: FASTCALL1 64 R3 L29; 
     411 [-]: MOVE R5 R3   ; var5 = var3
     412 [-]: GETIMPORT R4 27; var4 = 0x7B998233
     413 [-]: CALL R4 2 2  ; var4 = var4(var5)
L29: 414 [-]: JUMPIF R4 L30; goto L30 if var4
     415 [-]: GETUPVAL R5 11; var5 = upvalues[11]
     416 [-]: GETTABLEKS R4 R5 K30; var4 = var5[0x237A6578]
     417 [-]: GETUPVAL R5 12; var5 = upvalues[12]
     418 [-]: LOADB R6 1   ; var6 = true
     419 [-]: NAMECALL R7 R3 K31; var8 = var3; var7 = var3[0xD1586535]
     420 [-]: CALL R7 2 0  ; var7, ... = var7(var8)
     421 [-]: CALL R4 0 1  ; var4(var5, ...)
L30: 422 [-]: GETIMPORT R4 11; var4 = 0x89326C93
     423 [-]: GETIMPORT R6 22; var6 = 0x0469F296
     424 [-]: LOADK R7 K74 ; var7 = "MITWOctopedeEmergeStinger"
     425 [-]: CALL R6 2 0  ; var6, ... = var6(var7)
     426 [-]: NAMECALL R4 R4 K25; var5 = var4; var4 = var4[0x46A0EBF5]
     427 [-]: CALL R4 0 2  ; var4 = var4(var5, ...)
     428 [-]: NAMECALL R5 R4 K28; var6 = var4; var5 = var4[0x383D2E7D]
     429 [-]: CALL R5 2 1  ; var5(var6)
     430 [-]: GETUPVAL R5 4; var5 = upvalues[4]
     431 [-]: GETUPVAL R7 12; var7 = upvalues[12]
     432 [-]: NAMECALL R5 R5 K61; var6 = var5; var5 = var5[0xE2871589]
     433 [-]: CALL R5 3 1  ; var5(var6, var7)
     434 [-]: JUMP L61     ; goto L61
L31: 435 [-]: GETUPVAL R2 2; var2 = upvalues[2]
     436 [-]: GETTABLEKS R1 R2 K75; var1 = var2["DEFEAT_MITW"]
     437 [-]: JUMPIFNOTEQ R0 R1 L34; goto L34 if var0 ~= var721468
     438 [-]: GETUPVAL R2 11; var2 = upvalues[11]
     439 [-]: GETTABLEKS R1 R2 K30; var1 = var2[0x237A6578]
     440 [-]: GETUPVAL R2 12; var2 = upvalues[12]
     441 [-]: LOADB R3 0   ; var3 = false
     442 [-]: CALL R1 3 1  ; var1(var2, var3)
     443 [-]: GETUPVAL R2 8; var2 = upvalues[8]
     444 [-]: GETTABLEKS R1 R2 K18; var1 = var2[0xA1DF01D6]
     445 [-]: GETUPVAL R3 9; var3 = upvalues[9]
     446 [-]: GETTABLEKS R2 R3 K76; var2 = var3["DEFEAT_MITW_ENEMIES"]
     447 [-]: CALL R1 2 1  ; var1(var2)
     448 [-]: GETUPVAL R2 20; var2 = upvalues[20]
     449 [-]: GETTABLEKS R1 R2 K59; var1 = var2[0x9742B85B]
     450 [-]: GETUPVAL R2 21; var2 = upvalues[21]
     451 [-]: GETIMPORT R3 22; var3 = 0x0469F296
     452 [-]: LOADK R4 K77 ; var4 = "DEnterTheLabs0160"
     453 [-]: CALL R3 2 2  ; var3 = var3(var4)
     454 [-]: LOADB R4 0   ; var4 = false
     455 [-]: LOADB R5 0   ; var5 = false
     456 [-]: CALL R1 5 1  ; var1(var2, var3, var4, var5)
     457 [-]: GETUPVAL R2 20; var2 = upvalues[20]
     458 [-]: GETTABLEKS R1 R2 K59; var1 = var2[0x9742B85B]
     459 [-]: GETUPVAL R2 21; var2 = upvalues[21]
     460 [-]: GETIMPORT R3 22; var3 = 0x0469F296
     461 [-]: LOADK R4 K78 ; var4 = "DEnterTheLabs0161Loid"
     462 [-]: CALL R3 2 2  ; var3 = var3(var4)
     463 [-]: LOADB R4 0   ; var4 = false
     464 [-]: CALL R1 4 1  ; var1(var2, var3, var4)
     465 [-]: GETIMPORT R1 11; var1 = 0x89326C93
     466 [-]: GETIMPORT R3 22; var3 = 0x0469F296
     467 [-]: LOADK R4 K79 ; var4 = "MITWCombatCue"
     468 [-]: CALL R3 2 0  ; var3, ... = var3(var4)
     469 [-]: NAMECALL R1 R1 K25; var2 = var1; var1 = var1[0x46A0EBF5]
     470 [-]: CALL R1 0 2  ; var1 = var1(var2, ...)
     471 [-]: FASTCALL1 64 R1 L32; 
     472 [-]: MOVE R3 R1   ; var3 = var1
     473 [-]: GETIMPORT R2 27; var2 = 0x7B998233
     474 [-]: CALL R2 2 2  ; var2 = var2(var3)
L32: 475 [-]: JUMPIF R2 L33; goto L33 if var2
     476 [-]: NAMECALL R2 R1 K28; var3 = var1; var2 = var1[0x383D2E7D]
     477 [-]: CALL R2 2 1  ; var2(var3)
L33: 478 [-]: GETUPVAL R3 30; var3 = upvalues[30]
     479 [-]: GETTABLEKS R2 R3 K80; var2 = var3[0xBF6DF647]
     480 [-]: GETIMPORT R3 22; var3 = 0x0469F296
     481 [-]: LOADK R4 K81 ; var4 = "MITWStingerRumbleLoop"
     482 [-]: CALL R3 2 2  ; var3 = var3(var4)
     483 [-]: LOADB R4 0   ; var4 = false
     484 [-]: CALL R2 3 1  ; var2(var3, var4)
     485 [-]: GETUPVAL R3 19; var3 = upvalues[19]
     486 [-]: GETTABLEKS R2 R3 K56; var2 = var3[0x659D451F]
     487 [-]: GETIMPORT R3 83; var3 = 0x60A0C6E3
     488 [-]: CALL R2 2 1  ; var2(var3)
     489 [-]: GETIMPORT R2 85; var2 = 0xD644C2F1
     490 [-]: LOADK R3 K86 ; var3 = "Beginning Octopede Encounter"
     491 [-]: CALL R2 2 1  ; var2(var3)
     492 [-]: GETIMPORT R2 11; var2 = 0x89326C93
     493 [-]: GETUPVAL R4 31; var4 = upvalues[31]
     494 [-]: NAMECALL R2 R2 K25; var3 = var2; var2 = var2[0x46A0EBF5]
     495 [-]: CALL R2 3 2  ; var2 = var2(var3, var4)
     496 [-]: GETUPVAL R3 4; var3 = upvalues[4]
     497 [-]: GETIMPORT R5 88; var5 = 0x1F9F2D59
     498 [-]: NAMECALL R6 R2 K31; var7 = var2; var6 = var2[0xD1586535]
     499 [-]: CALL R6 2 2  ; var6 = var6(var7)
     500 [-]: NAMECALL R7 R2 K54; var8 = var2; var7 = var2[0xCB3851B8]
     501 [-]: CALL R7 2 2  ; var7 = var7(var8)
     502 [-]: GETIMPORT R8 22; var8 = 0x0469F296
     503 [-]: LOADK R9 K89 ; var9 = "OctopedeFight"
     504 [-]: CALL R8 2 0  ; var8, ... = var8(var9)
     505 [-]: NAMECALL R3 R3 K90; var4 = var3; var3 = var3[0x6CD833C5]
     506 [-]: CALL R3 0 1  ; var3(var4, ...)
     507 [-]: JUMP L61     ; goto L61
L34: 508 [-]: GETUPVAL R2 2; var2 = upvalues[2]
     509 [-]: GETTABLEKS R1 R2 K91; var1 = var2["CONTINUE_SEARCH"]
     510 [-]: JUMPIFNOTEQ R0 R1 L43; goto L43 if var0 ~= var524860
     511 [-]: GETUPVAL R2 8; var2 = upvalues[8]
     512 [-]: GETTABLEKS R1 R2 K18; var1 = var2[0xA1DF01D6]
     513 [-]: GETUPVAL R3 9; var3 = upvalues[9]
     514 [-]: GETTABLEKS R2 R3 K19; var2 = var3["FIND_SLEEPER"]
     515 [-]: CALL R1 2 1  ; var1(var2)
     516 [-]: GETIMPORT R1 11; var1 = 0x89326C93
     517 [-]: GETUPVAL R3 32; var3 = upvalues[32]
     518 [-]: NAMECALL R1 R1 K25; var2 = var1; var1 = var1[0x46A0EBF5]
     519 [-]: CALL R1 3 2  ; var1 = var1(var2, var3)
     520 [-]: FASTCALL1 64 R1 L35; 
     521 [-]: MOVE R3 R1   ; var3 = var1
     522 [-]: GETIMPORT R2 27; var2 = 0x7B998233
     523 [-]: CALL R2 2 2  ; var2 = var2(var3)
L35: 524 [-]: JUMPIF R2 L36; goto L36 if var2
     525 [-]: GETUPVAL R3 11; var3 = upvalues[11]
     526 [-]: GETTABLEKS R2 R3 K30; var2 = var3[0x237A6578]
     527 [-]: GETUPVAL R3 12; var3 = upvalues[12]
     528 [-]: LOADB R4 1   ; var4 = true
     529 [-]: NAMECALL R5 R1 K31; var6 = var1; var5 = var1[0xD1586535]
     530 [-]: CALL R5 2 0  ; var5, ... = var5(var6)
     531 [-]: CALL R2 0 1  ; var2(var3, ...)
L36: 532 [-]: GETIMPORT R2 11; var2 = 0x89326C93
     533 [-]: GETUPVAL R4 33; var4 = upvalues[33]
     534 [-]: NAMECALL R2 R2 K25; var3 = var2; var2 = var2[0x46A0EBF5]
     535 [-]: CALL R2 3 2  ; var2 = var2(var3, var4)
     536 [-]: FASTCALL1 64 R2 L37; 
     537 [-]: MOVE R4 R2   ; var4 = var2
     538 [-]: GETIMPORT R3 27; var3 = 0x7B998233
     539 [-]: CALL R3 2 2  ; var3 = var3(var4)
L37: 540 [-]: JUMPIF R3 L38; goto L38 if var3
     541 [-]: NAMECALL R3 R2 K28; var4 = var2; var3 = var2[0x383D2E7D]
     542 [-]: CALL R3 2 1  ; var3(var4)
L38: 543 [-]: GETIMPORT R3 11; var3 = 0x89326C93
     544 [-]: GETIMPORT R5 22; var5 = 0x0469F296
     545 [-]: LOADK R6 K92 ; var6 = "QuestSubwayAnnouncer"
     546 [-]: CALL R5 2 0  ; var5, ... = var5(var6)
     547 [-]: NAMECALL R3 R3 K25; var4 = var3; var3 = var3[0x46A0EBF5]
     548 [-]: CALL R3 0 2  ; var3 = var3(var4, ...)
     549 [-]: FASTCALL1 64 R3 L39; 
     550 [-]: MOVE R5 R3   ; var5 = var3
     551 [-]: GETIMPORT R4 27; var4 = 0x7B998233
     552 [-]: CALL R4 2 2  ; var4 = var4(var5)
L39: 553 [-]: JUMPIF R4 L40; goto L40 if var4
     554 [-]: NAMECALL R4 R3 K28; var5 = var3; var4 = var3[0x383D2E7D]
     555 [-]: CALL R4 2 1  ; var4(var5)
L40: 556 [-]: GETIMPORT R4 11; var4 = 0x89326C93
     557 [-]: GETIMPORT R6 22; var6 = 0x0469F296
     558 [-]: LOADK R7 K79 ; var7 = "MITWCombatCue"
     559 [-]: CALL R6 2 0  ; var6, ... = var6(var7)
     560 [-]: NAMECALL R4 R4 K25; var5 = var4; var4 = var4[0x46A0EBF5]
     561 [-]: CALL R4 0 2  ; var4 = var4(var5, ...)
     562 [-]: FASTCALL1 64 R4 L41; 
     563 [-]: MOVE R6 R4   ; var6 = var4
     564 [-]: GETIMPORT R5 27; var5 = 0x7B998233
     565 [-]: CALL R5 2 2  ; var5 = var5(var6)
L41: 566 [-]: JUMPIF R5 L42; goto L42 if var5
     567 [-]: NAMECALL R5 R4 K93; var6 = var4; var5 = var4[0xF4E253B6]
     568 [-]: CALL R5 2 1  ; var5(var6)
L42: 569 [-]: GETUPVAL R6 20; var6 = upvalues[20]
     570 [-]: GETTABLEKS R5 R6 K59; var5 = var6[0x9742B85B]
     571 [-]: GETUPVAL R6 21; var6 = upvalues[21]
     572 [-]: GETIMPORT R7 22; var7 = 0x0469F296
     573 [-]: LOADK R8 K94 ; var8 = "DEnterTheLabs0170"
     574 [-]: CALL R7 2 2  ; var7 = var7(var8)
     575 [-]: LOADB R8 0   ; var8 = false
     576 [-]: LOADB R9 0   ; var9 = false
     577 [-]: CALL R5 5 1  ; var5(var6, var7, var8, var9)
     578 [-]: JUMP L61     ; goto L61
L43: 579 [-]: GETUPVAL R2 2; var2 = upvalues[2]
     580 [-]: GETTABLEKS R1 R2 K95; var1 = var2["MEET_HUMAN_LOID"]
     581 [-]: JUMPIFNOTEQ R0 R1 L45; goto L45 if var0 ~= var721468
     582 [-]: GETUPVAL R2 11; var2 = upvalues[11]
     583 [-]: GETTABLEKS R1 R2 K30; var1 = var2[0x237A6578]
     584 [-]: GETUPVAL R2 12; var2 = upvalues[12]
     585 [-]: LOADB R3 0   ; var3 = false
     586 [-]: CALL R1 3 1  ; var1(var2, var3)
     587 [-]: GETUPVAL R2 8; var2 = upvalues[8]
     588 [-]: GETTABLEKS R1 R2 K18; var1 = var2[0xA1DF01D6]
     589 [-]: GETUPVAL R3 9; var3 = upvalues[9]
     590 [-]: GETTABLEKS R2 R3 K96; var2 = var3["OPEN_CRYOPOD"]
     591 [-]: CALL R1 2 1  ; var1(var2)
     592 [-]: GETIMPORT R1 11; var1 = 0x89326C93
     593 [-]: GETUPVAL R3 34; var3 = upvalues[34]
     594 [-]: NAMECALL R1 R1 K25; var2 = var1; var1 = var1[0x46A0EBF5]
     595 [-]: CALL R1 3 2  ; var1 = var1(var2, var3)
     596 [-]: FASTCALL1 64 R1 L44; 
     597 [-]: MOVE R3 R1   ; var3 = var1
     598 [-]: GETIMPORT R2 27; var2 = 0x7B998233
     599 [-]: CALL R2 2 2  ; var2 = var2(var3)
L44: 600 [-]: JUMPIF R2 L61; goto L61 if var2
     601 [-]: GETUPVAL R3 11; var3 = upvalues[11]
     602 [-]: GETTABLEKS R2 R3 K30; var2 = var3[0x237A6578]
     603 [-]: GETUPVAL R3 12; var3 = upvalues[12]
     604 [-]: LOADB R4 1   ; var4 = true
     605 [-]: NAMECALL R5 R1 K31; var6 = var1; var5 = var1[0xD1586535]
     606 [-]: CALL R5 2 0  ; var5, ... = var5(var6)
     607 [-]: CALL R2 0 1  ; var2(var3, ...)
     608 [-]: JUMP L61     ; goto L61
L45: 609 [-]: GETUPVAL R2 2; var2 = upvalues[2]
     610 [-]: GETTABLEKS R1 R2 K97; var1 = var2["RESCUE_LOID_CIN"]
     611 [-]: JUMPIFNOTEQ R0 R1 L50; goto L50 if var0 ~= var721468
     612 [-]: GETUPVAL R2 11; var2 = upvalues[11]
     613 [-]: GETTABLEKS R1 R2 K30; var1 = var2[0x237A6578]
     614 [-]: GETUPVAL R2 12; var2 = upvalues[12]
     615 [-]: LOADB R3 0   ; var3 = false
     616 [-]: CALL R1 3 1  ; var1(var2, var3)
     617 [-]: GETIMPORT R1 11; var1 = 0x89326C93
     618 [-]: GETIMPORT R3 22; var3 = 0x0469F296
     619 [-]: LOADK R4 K98 ; var4 = "HumanLoidAgentSpawn"
     620 [-]: CALL R3 2 0  ; var3, ... = var3(var4)
     621 [-]: NAMECALL R1 R1 K25; var2 = var1; var1 = var1[0x46A0EBF5]
     622 [-]: CALL R1 0 2  ; var1 = var1(var2, ...)
     623 [-]: GETUPVAL R2 4; var2 = upvalues[4]
     624 [-]: GETIMPORT R4 100; var4 = 0x065DEC04
     625 [-]: MOVE R5 R1   ; var5 = var1
     626 [-]: NAMECALL R2 R2 K101; var3 = var2; var2 = var2[0x33FC842F]
     627 [-]: CALL R2 4 2  ; var2 = var2(var3, var4, var5)
     628 [-]: SETUPVAL R2 35; upvalues[2] = var35
     629 [-]: GETUPVAL R2 35; var2 = upvalues[35]
     630 [-]: NAMECALL R2 R2 K102; var3 = var2; var2 = var2[0xBB610E5B]
     631 [-]: CALL R2 2 2  ; var2 = var2(var3)
     632 [-]: SETUPVAL R2 36; upvalues[2] = var36
     633 [-]: GETUPVAL R2 36; var2 = upvalues[36]
     634 [-]: GETIMPORT R4 22; var4 = 0x0469F296
     635 [-]: LOADK R5 K103; var5 = "DisableIdleVariation"
     636 [-]: CALL R4 2 0  ; var4, ... = var4(var5)
     637 [-]: NAMECALL R2 R2 K104; var3 = var2; var2 = var2[0xB2532845]
     638 [-]: CALL R2 0 1  ; var2(var3, ...)
     639 [-]: GETUPVAL R2 36; var2 = upvalues[36]
     640 [-]: GETUPVAL R4 37; var4 = upvalues[37]
     641 [-]: NAMECALL R2 R2 K105; var3 = var2; var2 = var2[0xC9F6A7D7]
     642 [-]: CALL R2 3 2  ; var2 = var2(var3, var4)
     643 [-]: FASTCALL1 64 R2 L46; 
     644 [-]: MOVE R4 R2   ; var4 = var2
     645 [-]: GETIMPORT R3 27; var3 = 0x7B998233
     646 [-]: CALL R3 2 2  ; var3 = var3(var4)
L46: 647 [-]: JUMPIF R3 L47; goto L47 if var3
     648 [-]: LOADB R5 0   ; var5 = false
     649 [-]: LOADB R6 0   ; var6 = false
     650 [-]: NAMECALL R3 R2 K106; var4 = var2; var3 = var2[0x768274D6]
     651 [-]: CALL R3 4 1  ; var3(var4, var5, var6)
L47: 652 [-]: GETUPVAL R3 36; var3 = upvalues[36]
     653 [-]: GETIMPORT R5 108; var5 = gSkeletalClothExType
     654 [-]: NAMECALL R3 R3 K109; var4 = var3; var3 = var3[0xC1595BD5]
     655 [-]: CALL R3 3 2  ; var3 = var3(var4, var5)
     656 [-]: GETIMPORT R4 37; var4 = 0xC8802016
     657 [-]: MOVE R5 R3   ; var5 = var3
     658 [-]: CALL R4 2 4  ; var4, var5, var6 = var4(var5)
     659 [-]: FORGPREP_INEXT R4 L49; 
L48: 660 [-]: LOADB R11 0  ; var11 = false
     661 [-]: LOADB R12 0  ; var12 = false
     662 [-]: NAMECALL R9 R8 K106; var10 = var8; var9 = var8[0x768274D6]
     663 [-]: CALL R9 4 1  ; var9(var10, var11, var12)
L49: 664 [-]: FORGLOOP R4 L48 2 [inext]; 
     665 [-]: GETUPVAL R5 11; var5 = upvalues[11]
     666 [-]: GETTABLEKS R4 R5 K110; var4 = var5[0xDA64D40E]
     667 [-]: LOADB R5 1   ; var5 = true
     668 [-]: LOADB R6 1   ; var6 = true
     669 [-]: CALL R4 3 1  ; var4(var5, var6)
     670 [-]: GETUPVAL R5 38; var5 = upvalues[38]
     671 [-]: GETTABLEKS R4 R5 K111; var4 = var5[0xC2019EF5]
     672 [-]: GETIMPORT R5 22; var5 = 0x0469F296
     673 [-]: LOADK R6 K112; var6 = "RescueLoidCin"
     674 [-]: CALL R5 2 2  ; var5 = var5(var6)
     675 [-]: LOADB R6 1   ; var6 = true
     676 [-]: CALL R4 3 1  ; var4(var5, var6)
     677 [-]: GETUPVAL R4 7; var4 = upvalues[7]
     678 [-]: GETUPVAL R7 2; var7 = upvalues[2]
     679 [-]: GETTABLEKS R6 R7 K113; var6 = var7["ENTER_VESSEL"]
     680 [-]: NAMECALL R4 R4 K17; var5 = var4; var4 = var4[0x8ABFF40E]
     681 [-]: CALL R4 3 1  ; var4(var5, var6)
     682 [-]: JUMP L61     ; goto L61
L50: 683 [-]: GETUPVAL R2 2; var2 = upvalues[2]
     684 [-]: GETTABLEKS R1 R2 K113; var1 = var2["ENTER_VESSEL"]
     685 [-]: JUMPIFNOTEQ R0 R1 L58; goto L58 if var0 ~= var524860
     686 [-]: GETUPVAL R2 8; var2 = upvalues[8]
     687 [-]: GETTABLEKS R1 R2 K18; var1 = var2[0xA1DF01D6]
     688 [-]: GETUPVAL R3 9; var3 = upvalues[9]
     689 [-]: GETTABLEKS R2 R3 K114; var2 = var3["FOLLOW_LOID"]
     690 [-]: CALL R1 2 1  ; var1(var2)
     691 [-]: GETIMPORT R1 11; var1 = 0x89326C93
     692 [-]: GETIMPORT R3 22; var3 = 0x0469F296
     693 [-]: LOADK R4 K115; var4 = "LoidExitTrigger"
     694 [-]: CALL R3 2 0  ; var3, ... = var3(var4)
     695 [-]: NAMECALL R1 R1 K25; var2 = var1; var1 = var1[0x46A0EBF5]
     696 [-]: CALL R1 0 2  ; var1 = var1(var2, ...)
     697 [-]: FASTCALL1 64 R1 L51; 
     698 [-]: MOVE R3 R1   ; var3 = var1
     699 [-]: GETIMPORT R2 27; var2 = 0x7B998233
     700 [-]: CALL R2 2 2  ; var2 = var2(var3)
L51: 701 [-]: JUMPIF R2 L61; goto L61 if var2
     702 [-]: GETUPVAL R3 35; var3 = upvalues[35]
     703 [-]: FASTCALL1 64 R3 L52; 
     704 [-]: GETIMPORT R2 27; var2 = 0x7B998233
     705 [-]: CALL R2 2 2  ; var2 = var2(var3)
L52: 706 [-]: JUMPIFNOT R2 L53; goto L53 if not var2
     707 [-]: GETIMPORT R2 11; var2 = 0x89326C93
     708 [-]: GETIMPORT R4 22; var4 = 0x0469F296
     709 [-]: LOADK R5 K98 ; var5 = "HumanLoidAgentSpawn"
     710 [-]: CALL R4 2 0  ; var4, ... = var4(var5)
     711 [-]: NAMECALL R2 R2 K25; var3 = var2; var2 = var2[0x46A0EBF5]
     712 [-]: CALL R2 0 2  ; var2 = var2(var3, ...)
     713 [-]: GETUPVAL R3 4; var3 = upvalues[4]
     714 [-]: GETIMPORT R5 100; var5 = 0x065DEC04
     715 [-]: MOVE R6 R2   ; var6 = var2
     716 [-]: NAMECALL R3 R3 K101; var4 = var3; var3 = var3[0x33FC842F]
     717 [-]: CALL R3 4 2  ; var3 = var3(var4, var5, var6)
     718 [-]: SETUPVAL R3 35; upvalues[3] = var35
L53: 719 [-]: GETUPVAL R2 35; var2 = upvalues[35]
     720 [-]: NAMECALL R2 R2 K102; var3 = var2; var2 = var2[0xBB610E5B]
     721 [-]: CALL R2 2 2  ; var2 = var2(var3)
     722 [-]: SETUPVAL R2 36; upvalues[2] = var36
     723 [-]: GETUPVAL R2 36; var2 = upvalues[36]
     724 [-]: GETUPVAL R4 37; var4 = upvalues[37]
     725 [-]: NAMECALL R2 R2 K105; var3 = var2; var2 = var2[0xC9F6A7D7]
     726 [-]: CALL R2 3 2  ; var2 = var2(var3, var4)
     727 [-]: FASTCALL1 64 R2 L54; 
     728 [-]: MOVE R4 R2   ; var4 = var2
     729 [-]: GETIMPORT R3 27; var3 = 0x7B998233
     730 [-]: CALL R3 2 2  ; var3 = var3(var4)
L54: 731 [-]: JUMPIF R3 L55; goto L55 if var3
     732 [-]: LOADB R5 1   ; var5 = true
     733 [-]: LOADB R6 1   ; var6 = true
     734 [-]: NAMECALL R3 R2 K106; var4 = var2; var3 = var2[0x768274D6]
     735 [-]: CALL R3 4 1  ; var3(var4, var5, var6)
L55: 736 [-]: GETUPVAL R3 36; var3 = upvalues[36]
     737 [-]: GETIMPORT R5 108; var5 = gSkeletalClothExType
     738 [-]: NAMECALL R3 R3 K109; var4 = var3; var3 = var3[0xC1595BD5]
     739 [-]: CALL R3 3 2  ; var3 = var3(var4, var5)
     740 [-]: GETIMPORT R4 37; var4 = 0xC8802016
     741 [-]: MOVE R5 R3   ; var5 = var3
     742 [-]: CALL R4 2 4  ; var4, var5, var6 = var4(var5)
     743 [-]: FORGPREP_INEXT R4 L57; 
L56: 744 [-]: LOADB R11 1  ; var11 = true
     745 [-]: LOADB R12 1  ; var12 = true
     746 [-]: NAMECALL R9 R8 K106; var10 = var8; var9 = var8[0x768274D6]
     747 [-]: CALL R9 4 1  ; var9(var10, var11, var12)
L57: 748 [-]: FORGLOOP R4 L56 2 [inext]; 
     749 [-]: GETUPVAL R4 35; var4 = upvalues[35]
     750 [-]: NAMECALL R6 R1 K31; var7 = var1; var6 = var1[0xD1586535]
     751 [-]: CALL R6 2 2  ; var6 = var6(var7)
     752 [-]: LOADB R7 0   ; var7 = false
     753 [-]: LOADB R8 0   ; var8 = false
     754 [-]: LOADB R9 0   ; var9 = false
     755 [-]: LOADN R10 15 ; var10 = 15
     756 [-]: LOADN R11 15 ; var11 = 15
     757 [-]: LOADN R12 15 ; var12 = 15
     758 [-]: NAMECALL R4 R4 K116; var5 = var4; var4 = var4[0xE5EB5E37]
     759 [-]: CALL R4 9 1  ; var4(var5, var6, var7, var8, var9, var10, var11, var12)
     760 [-]: GETUPVAL R5 11; var5 = upvalues[11]
     761 [-]: GETTABLEKS R4 R5 K117; var4 = var5[0xA1D0E6E1]
     762 [-]: GETUPVAL R5 14; var5 = upvalues[14]
     763 [-]: LOADB R6 1   ; var6 = true
     764 [-]: CALL R4 3 1  ; var4(var5, var6)
     765 [-]: GETUPVAL R5 38; var5 = upvalues[38]
     766 [-]: GETTABLEKS R4 R5 K118; var4 = var5[0x1BF26251]
     767 [-]: LOADB R5 0   ; var5 = false
     768 [-]: CALL R4 2 1  ; var4(var5)
     769 [-]: GETUPVAL R5 38; var5 = upvalues[38]
     770 [-]: GETTABLEKS R4 R5 K119; var4 = var5[0xBDD9801D]
     771 [-]: LOADB R5 0   ; var5 = false
     772 [-]: CALL R4 2 1  ; var4(var5)
     773 [-]: GETIMPORT R4 121; var4 = 0x11A19C5E
     774 [-]: MOVE R5 R1   ; var5 = var1
     775 [-]: LOADK R6 K122; var6 = "OnTouched"
     776 [-]: CALL R4 3 1  ; var4(var5, var6)
     777 [-]: GETUPVAL R5 20; var5 = upvalues[20]
     778 [-]: GETTABLEKS R4 R5 K59; var4 = var5[0x9742B85B]
     779 [-]: GETUPVAL R5 21; var5 = upvalues[21]
     780 [-]: GETIMPORT R6 22; var6 = 0x0469F296
     781 [-]: LOADK R7 K123; var7 = "DCinWakeLoid0261HumanLoid"
     782 [-]: CALL R6 2 0  ; var6, ... = var6(var7)
     783 [-]: CALL R4 0 1  ; var4(var5, ...)
     784 [-]: JUMP L61     ; goto L61
L58: 785 [-]: GETUPVAL R2 2; var2 = upvalues[2]
     786 [-]: GETTABLEKS R1 R2 K124; var1 = var2["OUTRO_CIN"]
     787 [-]: JUMPIFNOTEQ R0 R1 L59; goto L59 if var0 ~= var2359612
     788 [-]: GETUPVAL R1 36; var1 = upvalues[36]
     789 [-]: LOADB R3 0   ; var3 = false
     790 [-]: LOADB R4 0   ; var4 = false
     791 [-]: NAMECALL R1 R1 K106; var2 = var1; var1 = var1[0x768274D6]
     792 [-]: CALL R1 4 1  ; var1(var2, var3, var4)
     793 [-]: GETUPVAL R2 38; var2 = upvalues[38]
     794 [-]: GETTABLEKS R1 R2 K111; var1 = var2[0xC2019EF5]
     795 [-]: GETIMPORT R2 22; var2 = 0x0469F296
     796 [-]: LOADK R3 K125; var3 = "QuestIntoVesselCin"
     797 [-]: CALL R2 2 0  ; var2, ... = var2(var3)
     798 [-]: CALL R1 0 2  ; var1 = var1(var2, ...)
     799 [-]: SETUPVAL R1 39; upvalues[1] = var39
     800 [-]: JUMP L61     ; goto L61
L59: 801 [-]: GETUPVAL R2 2; var2 = upvalues[2]
     802 [-]: GETTABLEKS R1 R2 K126; var1 = var2["COMPLETE"]
     803 [-]: JUMPIFNOTEQ R0 R1 L60; goto L60 if var0 ~= var524860
     804 [-]: GETUPVAL R2 8; var2 = upvalues[8]
     805 [-]: GETTABLEKS R1 R2 K39; var1 = var2[0xDC3B2033]
     806 [-]: CALL R1 1 1  ; var1()
     807 [-]: GETUPVAL R2 38; var2 = upvalues[38]
     808 [-]: GETTABLEKS R1 R2 K127; var1 = var2[0x12A41A40]
     809 [-]: LOADB R2 1   ; var2 = true
     810 [-]: LOADN R3 0   ; var3 = 0
     811 [-]: CALL R1 3 1  ; var1(var2, var3)
     812 [-]: GETUPVAL R1 14; var1 = upvalues[14]
     813 [-]: LOADB R3 1   ; var3 = true
     814 [-]: NAMECALL R1 R1 K128; var2 = var1; var1 = var1[0x6667E5D4]
     815 [-]: CALL R1 3 1  ; var1(var2, var3)
     816 [-]: GETUPVAL R1 14; var1 = upvalues[14]
     817 [-]: GETUPVAL R3 40; var3 = upvalues[40]
     818 [-]: NAMECALL R1 R1 K129; var2 = var1; var1 = var1[0x89F5ABE4]
     819 [-]: CALL R1 3 1  ; var1(var2, var3)
     820 [-]: GETUPVAL R2 41; var2 = upvalues[41]
     821 [-]: GETTABLEKS R1 R2 K130; var1 = var2[0x436863DC]
     822 [-]: GETUPVAL R3 11; var3 = upvalues[11]
     823 [-]: GETTABLEKS R2 R3 K131; var2 = var3["QUEST_KEY_WRES"]
     824 [-]: LOADN R3 2   ; var3 = 2
     825 [-]: LOADB R4 1   ; var4 = true
     826 [-]: CALL R1 4 1  ; var1(var2, var3, var4)
     827 [-]: GETIMPORT R1 7; var1 = 0xBE190284
     828 [-]: NAMECALL R1 R1 K132; var2 = var1; var1 = var1[0x092CB9A1]
     829 [-]: CALL R1 2 1  ; var1(var2)
     830 [-]: GETUPVAL R2 11; var2 = upvalues[11]
     831 [-]: GETTABLEKS R1 R2 K133; var1 = var2[0x713D423A]
     832 [-]: LOADB R2 1   ; var2 = true
     833 [-]: CALL R1 2 1  ; var1(var2)
     834 [-]: JUMP L61     ; goto L61
L60: 835 [-]: GETUPVAL R2 2; var2 = upvalues[2]
     836 [-]: GETTABLEKS R1 R2 K134; var1 = var2["RESPAWN"]
     837 [-]: JUMPIFNOTEQ R0 R1 L61; goto L61 if var0 ~= var2752828
L61: 838 [-]: GETUPVAL R1 42; var1 = upvalues[42]
     839 [-]: JUMPIFNOT R1 L62; goto L62 if not var1
     840 [-]: LOADB R1 0   ; var1 = false
     841 [-]: SETUPVAL R1 42; upvalues[1] = var42
     842 [-]: GETIMPORT R1 136; var1 = 0xCBD666E1
     843 [-]: LOADK R2 K137; var2 = 0.10000000149011612
     844 [-]: CALL R1 2 1  ; var1(var2)
     845 [-]: GETIMPORT R1 139; var1 = 0x9BA7909F
     846 [-]: GETUPVAL R3 43; var3 = upvalues[43]
     847 [-]: NAMECALL R1 R1 K140; var2 = var1; var1 = var1[0xF37BDBF9]
     848 [-]: CALL R1 3 1  ; var1(var2, var3)
L62: 849 [-]: RETURN R0 0  ; 


; Name:            
; Defined at line: 561
; #Upvalues:       3
; #Parameters:     2
; Is_vararg:       0
; Max Stack Size:  7

       0 [-]: GETUPVAL R3 1; var3 = upvalues[1]
       1 [-]: GETTABLEKS R2 R3 K0; var2 = var3[0xD2CED2F7]
       2 [-]: GETUPVAL R3 2; var3 = upvalues[2]
       3 [-]: MOVE R4 R0   ; var4 = var0
       4 [-]: MOVE R5 R1   ; var5 = var1
       5 [-]: LOADB R6 1   ; var6 = true
       6 [-]: CALL R2 5 2  ; var2 = var2(var3, var4, var5, var6)
       7 [-]: SETUPVAL R2 0; upvalues[2] = var0
       8 [-]: GETUPVAL R3 0; var3 = upvalues[0]
       9 [-]: GETTABLEKS R2 R3 K1; var2 = var3["avatar"]
      10 [-]: SETUPVAL R2 2; upvalues[2] = var2
      11 [-]: RETURN R0 0  ; 


; Name:            
; Defined at line: 566
; #Upvalues:       25
; #Parameters:     1
; Is_vararg:       0
; Max Stack Size:  10

       0 [-]: GETUPVAL R2 1; var2 = upvalues[1]
       1 [-]: GETTABLEKS R1 R2 K0; var1 = var2[0xD2CED2F7]
       2 [-]: GETUPVAL R2 2; var2 = upvalues[2]
       3 [-]: LOADNIL R3   ; var3 = nil
       4 [-]: LOADNIL R4   ; var4 = nil
       5 [-]: LOADB R5 1   ; var5 = true
       6 [-]: CALL R1 5 2  ; var1 = var1(var2, var3, var4, var5)
       7 [-]: SETUPVAL R1 0; upvalues[1] = var0
       8 [-]: GETUPVAL R2 0; var2 = upvalues[0]
       9 [-]: GETTABLEKS R1 R2 K1; var1 = var2["avatar"]
      10 [-]: SETUPVAL R1 2; upvalues[1] = var2
      11 [-]: GETUPVAL R2 3; var2 = upvalues[3]
      12 [-]: FASTCALL1 64 R2 L0; 
      13 [-]: GETIMPORT R1 3; var1 = 0x7B998233
      14 [-]: CALL R1 2 2  ; var1 = var1(var2)
L 0:  15 [-]: JUMPIF R1 L1 ; goto L1 if var1
      16 [-]: GETUPVAL R1 3; var1 = upvalues[3]
      17 [-]: NAMECALL R1 R1 K4; var2 = var1; var1 = var1[0x860FB98B]
      18 [-]: CALL R1 2 2  ; var1 = var1(var2)
      19 [-]: JUMPIFNOT R1 L1; goto L1 if not var1
      20 [-]: RETURN R0 0  ; 
L 1:  21 [-]: GETUPVAL R2 4; var2 = upvalues[4]
      22 [-]: GETTABLEKS R1 R2 K5; var1 = var2[0x4FF20CC9]
      23 [-]: MOVE R2 R0   ; var2 = var0
      24 [-]: CALL R1 2 1  ; var1(var2)
      25 [-]: GETUPVAL R1 5; var1 = upvalues[5]
      26 [-]: GETUPVAL R3 6; var3 = upvalues[6]
      27 [-]: GETTABLEKS R2 R3 K6; var2 = var3["SETUP"]
      28 [-]: JUMPIFNOTEQ R1 R2 L2; goto L2 if var1 ~= var65571
      29 [-]: RETURN R0 0  ; 
L 2:  30 [-]: GETUPVAL R1 5; var1 = upvalues[5]
      31 [-]: GETUPVAL R3 6; var3 = upvalues[6]
      32 [-]: GETTABLEKS R2 R3 K7; var2 = var3["INTRO_TRANS"]
      33 [-]: JUMPIFNOTEQ R1 R2 L3; goto L3 if var1 ~= var65571
      34 [-]: RETURN R0 0  ; 
L 3:  35 [-]: GETUPVAL R1 5; var1 = upvalues[5]
      36 [-]: GETUPVAL R3 6; var3 = upvalues[6]
      37 [-]: GETTABLEKS R2 R3 K8; var2 = var3["FOLLOW_VOICE"]
      38 [-]: JUMPIFNOTEQ R1 R2 L4; goto L4 if var1 ~= var459068
      39 [-]: GETUPVAL R1 7; var1 = upvalues[7]
      40 [-]: JUMPIFNOT R1 L22; goto L22 if not var1
      41 [-]: GETUPVAL R1 8; var1 = upvalues[8]
      42 [-]: GETUPVAL R4 6; var4 = upvalues[6]
      43 [-]: GETTABLEKS R3 R4 K9; var3 = var4["MECH"]
      44 [-]: NAMECALL R1 R1 K10; var2 = var1; var1 = var1[0x8ABFF40E]
      45 [-]: CALL R1 3 1  ; var1(var2, var3)
      46 [-]: RETURN R0 0  ; 
L 4:  47 [-]: GETUPVAL R1 5; var1 = upvalues[5]
      48 [-]: GETUPVAL R3 6; var3 = upvalues[6]
      49 [-]: GETTABLEKS R2 R3 K11; var2 = var3["DEFEAT_MECH"]
      50 [-]: JUMPIFNOTEQ R1 R2 L5; goto L5 if var1 ~= var590140
      51 [-]: GETUPVAL R1 9; var1 = upvalues[9]
      52 [-]: GETUPVAL R3 10; var3 = upvalues[10]
      53 [-]: LENGTH R2 R3 ; var2 = #var3
      54 [-]: JUMPIFNOTLE R2 R1 L22; goto L22 if var2 > var304
      55 [-]: LOADN R1 0   ; var1 = 0
      56 [-]: SETUPVAL R1 9; upvalues[1] = var9
      57 [-]: GETUPVAL R1 8; var1 = upvalues[8]
      58 [-]: GETUPVAL R4 6; var4 = upvalues[6]
      59 [-]: GETTABLEKS R3 R4 K12; var3 = var4["FOLLOW_VOICE_AGAIN"]
      60 [-]: NAMECALL R1 R1 K10; var2 = var1; var1 = var1[0x8ABFF40E]
      61 [-]: CALL R1 3 1  ; var1(var2, var3)
      62 [-]: RETURN R0 0  ; 
L 5:  63 [-]: GETUPVAL R1 5; var1 = upvalues[5]
      64 [-]: GETUPVAL R3 6; var3 = upvalues[6]
      65 [-]: GETTABLEKS R2 R3 K12; var2 = var3["FOLLOW_VOICE_AGAIN"]
      66 [-]: JUMPIFNOTEQ R1 R2 L6; goto L6 if var1 ~= var262716
      67 [-]: GETUPVAL R2 4; var2 = upvalues[4]
      68 [-]: GETTABLEKS R1 R2 K13; var1 = var2[0xDEADD594]
      69 [-]: GETUPVAL R2 2; var2 = upvalues[2]
      70 [-]: GETUPVAL R3 11; var3 = upvalues[11]
      71 [-]: LOADN R4 20  ; var4 = 20
      72 [-]: CALL R1 4 2  ; var1 = var1(var2, var3, var4)
      73 [-]: JUMPIFNOT R1 L22; goto L22 if not var1
      74 [-]: GETUPVAL R1 8; var1 = upvalues[8]
      75 [-]: GETUPVAL R4 6; var4 = upvalues[6]
      76 [-]: GETTABLEKS R3 R4 K14; var3 = var4["GRIMOIRE"]
      77 [-]: NAMECALL R1 R1 K10; var2 = var1; var1 = var1[0x8ABFF40E]
      78 [-]: CALL R1 3 1  ; var1(var2, var3)
      79 [-]: RETURN R0 0  ; 
L 6:  80 [-]: GETUPVAL R1 5; var1 = upvalues[5]
      81 [-]: GETUPVAL R3 6; var3 = upvalues[6]
      82 [-]: GETTABLEKS R2 R3 K14; var2 = var3["GRIMOIRE"]
      83 [-]: JUMPIFNOTEQ R1 R2 L7; goto L7 if var1 ~= var65571
      84 [-]: RETURN R0 0  ; 
L 7:  85 [-]: GETUPVAL R1 5; var1 = upvalues[5]
      86 [-]: GETUPVAL R3 6; var3 = upvalues[6]
      87 [-]: GETTABLEKS R2 R3 K15; var2 = var3["DEFEAT_MECH_GRIMOIRE"]
      88 [-]: JUMPIFNOTEQ R1 R2 L8; goto L8 if var1 ~= var590140
      89 [-]: GETUPVAL R1 9; var1 = upvalues[9]
      90 [-]: GETUPVAL R3 12; var3 = upvalues[12]
      91 [-]: LENGTH R2 R3 ; var2 = #var3
      92 [-]: JUMPIFNOTLE R2 R1 L22; goto L22 if var2 > var304
      93 [-]: LOADN R1 0   ; var1 = 0
      94 [-]: SETUPVAL R1 9; upvalues[1] = var9
      95 [-]: GETUPVAL R1 8; var1 = upvalues[8]
      96 [-]: GETUPVAL R4 6; var4 = upvalues[6]
      97 [-]: GETTABLEKS R3 R4 K16; var3 = var4["GOTO_MITW"]
      98 [-]: NAMECALL R1 R1 K10; var2 = var1; var1 = var1[0x8ABFF40E]
      99 [-]: CALL R1 3 1  ; var1(var2, var3)
     100 [-]: RETURN R0 0  ; 
L 8: 101 [-]: GETUPVAL R1 5; var1 = upvalues[5]
     102 [-]: GETUPVAL R3 6; var3 = upvalues[6]
     103 [-]: GETTABLEKS R2 R3 K16; var2 = var3["GOTO_MITW"]
     104 [-]: JUMPIFNOTEQ R1 R2 L9; goto L9 if var1 ~= var1179937
     105 [-]: GETIMPORT R1 18; var1 = 0x89326C93
     106 [-]: GETUPVAL R3 13; var3 = upvalues[13]
     107 [-]: NAMECALL R1 R1 K19; var2 = var1; var1 = var1[0x46A0EBF5]
     108 [-]: CALL R1 3 2  ; var1 = var1(var2, var3)
     109 [-]: GETUPVAL R2 14; var2 = upvalues[14]
     110 [-]: JUMPIFNOT R2 L22; goto L22 if not var2
     111 [-]: GETUPVAL R3 4; var3 = upvalues[4]
     112 [-]: GETTABLEKS R2 R3 K20; var2 = var3[0xB12182A5]
     113 [-]: GETUPVAL R3 2; var3 = upvalues[2]
     114 [-]: LOADN R4 5   ; var4 = 5
     115 [-]: NAMECALL R5 R1 K21; var6 = var1; var5 = var1[0xD1586535]
     116 [-]: CALL R5 2 0  ; var5, ... = var5(var6)
     117 [-]: CALL R2 0 2  ; var2 = var2(var3, ...)
     118 [-]: JUMPIFNOT R2 L22; goto L22 if not var2
     119 [-]: LOADB R2 0   ; var2 = false
     120 [-]: SETUPVAL R2 14; upvalues[2] = var14
     121 [-]: GETUPVAL R3 15; var3 = upvalues[15]
     122 [-]: GETTABLEKS R2 R3 K22; var2 = var3[0xB112401F]
     123 [-]: CALL R2 1 1  ; var2()
     124 [-]: GETIMPORT R3 24; var3 = 0xBE190284
     125 [-]: NAMECALL R3 R3 K25; var4 = var3; var3 = var3[0xEF893AEC]
     126 [-]: CALL R3 2 2  ; var3 = var3(var4)
     127 [-]: GETTABLEKS R2 R3 K26; var2 = var3["enemySpec"]
     128 [-]: SETUPVAL R2 16; upvalues[2] = var16
     129 [-]: GETIMPORT R2 18; var2 = 0x89326C93
     130 [-]: NAMECALL R2 R2 K27; var3 = var2; var2 = var2[0x29EF273D]
     131 [-]: CALL R2 2 2  ; var2 = var2(var3)
     132 [-]: NAMECALL R3 R2 K28; var4 = var2; var3 = var2[0x66905CB0]
     133 [-]: CALL R3 2 2  ; var3 = var3(var4)
     134 [-]: SETUPVAL R3 17; upvalues[3] = var17
     135 [-]: GETUPVAL R3 17; var3 = upvalues[17]
     136 [-]: LOADB R5 0   ; var5 = false
     137 [-]: NAMECALL R3 R3 K29; var4 = var3; var3 = var3[0x2FAEAD12]
     138 [-]: CALL R3 3 1  ; var3(var4, var5)
     139 [-]: RETURN R0 0  ; 
L 9: 140 [-]: GETUPVAL R1 5; var1 = upvalues[5]
     141 [-]: GETUPVAL R3 6; var3 = upvalues[6]
     142 [-]: GETTABLEKS R2 R3 K30; var2 = var3["DEFEAT_MITW"]
     143 [-]: JUMPIFNOTEQ R1 R2 L12; goto L12 if var1 ~= var1573153
     144 [-]: GETIMPORT R1 24; var1 = 0xBE190284
     145 [-]: GETUPVAL R3 18; var3 = upvalues[18]
     146 [-]: LOADN R4 0   ; var4 = 0
     147 [-]: NAMECALL R1 R1 K31; var2 = var1; var1 = var1[0x0EB34C69]
     148 [-]: CALL R1 4 2  ; var1 = var1(var2, var3, var4)
     149 [-]: GETUPVAL R4 19; var4 = upvalues[19]
     150 [-]: GETTABLEKS R3 R4 K32; var3 = var4["BOSS_STATE"]
     151 [-]: GETTABLEKS R2 R3 K33; var2 = var3["OctopedePhase1"]
     152 [-]: JUMPIFNOTEQ R1 R2 L10; goto L10 if var1 ~= var1311292
     153 [-]: GETUPVAL R2 20; var2 = upvalues[20]
     154 [-]: JUMPIF R2 L10; goto L10 if var2
     155 [-]: LOADB R2 1   ; var2 = true
     156 [-]: SETUPVAL R2 20; upvalues[2] = var20
     157 [-]: JUMP L11     ; goto L11
L10: 158 [-]: GETUPVAL R4 19; var4 = upvalues[19]
     159 [-]: GETTABLEKS R3 R4 K32; var3 = var4["BOSS_STATE"]
     160 [-]: GETTABLEKS R2 R3 K34; var2 = var3["Complete"]
     161 [-]: JUMPIFNOTEQ R1 R2 L11; goto L11 if var1 ~= var66054
     162 [-]: LOADB R2 1   ; var2 = true
     163 [-]: SETUPVAL R2 21; upvalues[2] = var21
L11: 164 [-]: GETUPVAL R2 21; var2 = upvalues[21]
     165 [-]: JUMPIFNOT R2 L22; goto L22 if not var2
     166 [-]: GETUPVAL R2 8; var2 = upvalues[8]
     167 [-]: GETUPVAL R5 6; var5 = upvalues[6]
     168 [-]: GETTABLEKS R4 R5 K35; var4 = var5["CONTINUE_SEARCH"]
     169 [-]: NAMECALL R2 R2 K10; var3 = var2; var2 = var2[0x8ABFF40E]
     170 [-]: CALL R2 3 1  ; var2(var3, var4)
     171 [-]: RETURN R0 0  ; 
L12: 172 [-]: GETUPVAL R1 5; var1 = upvalues[5]
     173 [-]: GETUPVAL R3 6; var3 = upvalues[6]
     174 [-]: GETTABLEKS R2 R3 K35; var2 = var3["CONTINUE_SEARCH"]
     175 [-]: JUMPIFNOTEQ R1 R2 L13; goto L13 if var1 ~= var262716
     176 [-]: GETUPVAL R2 4; var2 = upvalues[4]
     177 [-]: GETTABLEKS R1 R2 K13; var1 = var2[0xDEADD594]
     178 [-]: GETUPVAL R2 2; var2 = upvalues[2]
     179 [-]: GETUPVAL R3 11; var3 = upvalues[11]
     180 [-]: LOADN R4 5   ; var4 = 5
     181 [-]: CALL R1 4 2  ; var1 = var1(var2, var3, var4)
     182 [-]: JUMPIFNOT R1 L22; goto L22 if not var1
     183 [-]: GETUPVAL R1 8; var1 = upvalues[8]
     184 [-]: GETUPVAL R4 6; var4 = upvalues[6]
     185 [-]: GETTABLEKS R3 R4 K36; var3 = var4["MEET_HUMAN_LOID"]
     186 [-]: NAMECALL R1 R1 K10; var2 = var1; var1 = var1[0x8ABFF40E]
     187 [-]: CALL R1 3 1  ; var1(var2, var3)
     188 [-]: RETURN R0 0  ; 
L13: 189 [-]: GETUPVAL R1 5; var1 = upvalues[5]
     190 [-]: GETUPVAL R3 6; var3 = upvalues[6]
     191 [-]: GETTABLEKS R2 R3 K36; var2 = var3["MEET_HUMAN_LOID"]
     192 [-]: JUMPIFNOTEQ R1 R2 L14; goto L14 if var1 ~= var65571
     193 [-]: RETURN R0 0  ; 
L14: 194 [-]: GETUPVAL R1 5; var1 = upvalues[5]
     195 [-]: GETUPVAL R3 6; var3 = upvalues[6]
     196 [-]: GETTABLEKS R2 R3 K37; var2 = var3["RESCUE_LOID_CIN"]
     197 [-]: JUMPIFNOTEQ R1 R2 L15; goto L15 if var1 ~= var65571
     198 [-]: RETURN R0 0  ; 
L15: 199 [-]: GETUPVAL R1 5; var1 = upvalues[5]
     200 [-]: GETUPVAL R3 6; var3 = upvalues[6]
     201 [-]: GETTABLEKS R2 R3 K38; var2 = var3["ENTER_VESSEL"]
     202 [-]: JUMPIFNOTEQ R1 R2 L16; goto L16 if var1 ~= var262716
     203 [-]: GETUPVAL R2 4; var2 = upvalues[4]
     204 [-]: GETTABLEKS R1 R2 K39; var1 = var2[0x237A6578]
     205 [-]: GETUPVAL R2 11; var2 = upvalues[11]
     206 [-]: LOADB R3 1   ; var3 = true
     207 [-]: GETUPVAL R5 22; var5 = upvalues[22]
     208 [-]: NAMECALL R5 R5 K21; var6 = var5; var5 = var5[0xD1586535]
     209 [-]: CALL R5 2 2  ; var5 = var5(var6)
     210 [-]: GETIMPORT R6 41; var6 = 0xA421AF95
     211 [-]: LOADN R7 0   ; var7 = 0
     212 [-]: LOADN R8 2   ; var8 = 2
     213 [-]: LOADN R9 0   ; var9 = 0
     214 [-]: CALL R6 4 2  ; var6 = var6(var7, var8, var9)
     215 [-]: ADD R4 R5 R6 ; var4 = var5 + var6
     216 [-]: CALL R1 4 2  ; var1 = var1(var2, var3, var4)
     217 [-]: SETUPVAL R1 11; upvalues[1] = var11
     218 [-]: GETIMPORT R1 18; var1 = 0x89326C93
     219 [-]: GETIMPORT R3 43; var3 = 0x0469F296
     220 [-]: LOADK R4 K44 ; var4 = "LoidExitTrigger"
     221 [-]: CALL R3 2 0  ; var3, ... = var3(var4)
     222 [-]: NAMECALL R1 R1 K19; var2 = var1; var1 = var1[0x46A0EBF5]
     223 [-]: CALL R1 0 2  ; var1 = var1(var2, ...)
     224 [-]: GETUPVAL R3 4; var3 = upvalues[4]
     225 [-]: GETTABLEKS R2 R3 K20; var2 = var3[0xB12182A5]
     226 [-]: GETUPVAL R3 2; var3 = upvalues[2]
     227 [-]: LOADN R4 5   ; var4 = 5
     228 [-]: NAMECALL R5 R1 K21; var6 = var1; var5 = var1[0xD1586535]
     229 [-]: CALL R5 2 0  ; var5, ... = var5(var6)
     230 [-]: CALL R2 0 2  ; var2 = var2(var3, ...)
     231 [-]: JUMPIFNOT R2 L22; goto L22 if not var2
     232 [-]: GETUPVAL R2 23; var2 = upvalues[23]
     233 [-]: JUMPXEQKB R2 1 L22 NOT; 
     234 [-]: GETUPVAL R2 8; var2 = upvalues[8]
     235 [-]: GETUPVAL R5 6; var5 = upvalues[6]
     236 [-]: GETTABLEKS R4 R5 K45; var4 = var5["OUTRO_CIN"]
     237 [-]: NAMECALL R2 R2 K10; var3 = var2; var2 = var2[0x8ABFF40E]
     238 [-]: CALL R2 3 1  ; var2(var3, var4)
     239 [-]: RETURN R0 0  ; 
L16: 240 [-]: GETUPVAL R1 5; var1 = upvalues[5]
     241 [-]: GETUPVAL R3 6; var3 = upvalues[6]
     242 [-]: GETTABLEKS R2 R3 K45; var2 = var3["OUTRO_CIN"]
     243 [-]: JUMPIFNOTEQ R1 R2 L20; goto L20 if var1 ~= var1573692
     244 [-]: GETUPVAL R3 24; var3 = upvalues[24]
     245 [-]: FASTCALL1 64 R3 L17; 
     246 [-]: GETIMPORT R2 3; var2 = 0x7B998233
     247 [-]: CALL R2 2 2  ; var2 = var2(var3)
L17: 248 [-]: JUMPIF R2 L18; goto L18 if var2
     249 [-]: GETUPVAL R2 24; var2 = upvalues[24]
     250 [-]: NAMECALL R2 R2 K46; var3 = var2; var2 = var2[0x1C84839C]
     251 [-]: CALL R2 2 2  ; var2 = var2(var3)
     252 [-]: JUMPIFNOT R2 L18; goto L18 if not var2
     253 [-]: LOADB R1 1   ; var1 = true
     254 [-]: JUMP L19     ; goto L19
L18: 255 [-]: LOADB R1 0   ; var1 = false
L19: 256 [-]: JUMPIF R1 L22; goto L22 if var1
     257 [-]: LOADB R1 0   ; var1 = false
     258 [-]: SETUPVAL R1 24; upvalues[1] = var24
     259 [-]: GETUPVAL R1 8; var1 = upvalues[8]
     260 [-]: GETUPVAL R4 6; var4 = upvalues[6]
     261 [-]: GETTABLEKS R3 R4 K47; var3 = var4["COMPLETE"]
     262 [-]: NAMECALL R1 R1 K10; var2 = var1; var1 = var1[0x8ABFF40E]
     263 [-]: CALL R1 3 1  ; var1(var2, var3)
     264 [-]: RETURN R0 0  ; 
L20: 265 [-]: GETUPVAL R1 5; var1 = upvalues[5]
     266 [-]: GETUPVAL R3 6; var3 = upvalues[6]
     267 [-]: GETTABLEKS R2 R3 K47; var2 = var3["COMPLETE"]
     268 [-]: JUMPIFNOTEQ R1 R2 L21; goto L21 if var1 ~= var65571
     269 [-]: RETURN R0 0  ; 
L21: 270 [-]: GETUPVAL R1 5; var1 = upvalues[5]
     271 [-]: GETUPVAL R3 6; var3 = upvalues[6]
     272 [-]: GETTABLEKS R2 R3 K48; var2 = var3["RESPAWN"]
     273 [-]: JUMPIFNOTEQ R1 R2 L22; goto L22 if var1 ~= var524604
     274 [-]: GETUPVAL R1 8; var1 = upvalues[8]
     275 [-]: LOADN R3 -1  ; var3 = -1
     276 [-]: NAMECALL R1 R1 K10; var2 = var1; var1 = var1[0x8ABFF40E]
     277 [-]: CALL R1 3 1  ; var1(var2, var3)
L22: 278 [-]: RETURN R0 0  ; 


; Name:            
; Defined at line: 640
; #Upvalues:       10
; #Parameters:     0
; Is_vararg:       0
; Max Stack Size:  8

       0 [-]: GETIMPORT R0 1; var0 = 0x89326C93
       1 [-]: NAMECALL R0 R0 K2; var1 = var0; var0 = var0[0x78298275]
       2 [-]: CALL R0 2 2  ; var0 = var0(var1)
       3 [-]: SETUPVAL R0 0; upvalues[0] = var0
       4 [-]: GETIMPORT R0 4; var0 = 0xE91D7466
       5 [-]: SETUPVAL R0 1; upvalues[0] = var1
       6 [-]: GETUPVAL R1 3; var1 = upvalues[3]
       7 [-]: GETTABLEKS R0 R1 K5; var0 = var1[0xCD96CF2E]
       8 [-]: CALL R0 1 2  ; var0 = var0()
       9 [-]: SETUPVAL R0 2; upvalues[0] = var2
      10 [-]: GETUPVAL R1 3; var1 = upvalues[3]
      11 [-]: GETTABLEKS R0 R1 K6; var0 = var1[0xB01DEB6A]
      12 [-]: GETUPVAL R1 2; var1 = upvalues[2]
      13 [-]: LOADB R2 0   ; var2 = false
      14 [-]: CALL R0 3 1  ; var0(var1, var2)
      15 [-]: GETIMPORT R0 1; var0 = 0x89326C93
      16 [-]: GETIMPORT R2 8; var2 = gMissionCheckpointType
      17 [-]: NAMECALL R0 R0 K9; var1 = var0; var0 = var0[0xFB669000]
      18 [-]: CALL R0 3 2  ; var0 = var0(var1, var2)
      19 [-]: SETUPVAL R0 4; upvalues[0] = var4
      20 [-]: GETIMPORT R0 11; var0 = 0xC8802016
      21 [-]: GETUPVAL R1 4; var1 = upvalues[4]
      22 [-]: CALL R0 2 4  ; var0, var1, var2 = var0(var1)
      23 [-]: FORGPREP_INEXT R0 L1; 
L 0:  24 [-]: GETIMPORT R5 13; var5 = 0x11A19C5E
      25 [-]: MOVE R6 R4   ; var6 = var4
      26 [-]: LOADK R7 K14 ; var7 = "OnSaved"
      27 [-]: CALL R5 3 1  ; var5(var6, var7)
      28 [-]: GETIMPORT R5 13; var5 = 0x11A19C5E
      29 [-]: MOVE R6 R4   ; var6 = var4
      30 [-]: LOADK R7 K15 ; var7 = "OnCleanUp"
      31 [-]: CALL R5 3 1  ; var5(var6, var7)
      32 [-]: GETIMPORT R5 13; var5 = 0x11A19C5E
      33 [-]: MOVE R6 R4   ; var6 = var4
      34 [-]: LOADK R7 K16 ; var7 = "OnReset"
      35 [-]: CALL R5 3 1  ; var5(var6, var7)
      36 [-]: GETIMPORT R5 13; var5 = 0x11A19C5E
      37 [-]: MOVE R6 R4   ; var6 = var4
      38 [-]: LOADK R7 K17 ; var7 = "OnFadeInComplete"
      39 [-]: CALL R5 3 1  ; var5(var6, var7)
L 1:  40 [-]: FORGLOOP R0 L0 2 [inext]; 
      41 [-]: GETUPVAL R1 5; var1 = upvalues[5]
      42 [-]: GETTABLEKS R0 R1 K18; var0 = var1[0xC474A99E]
      43 [-]: GETIMPORT R1 20; var1 = 0x0469F296
      44 [-]: LOADK R2 K21 ; var2 = "LoidQuestSeriglass"
      45 [-]: CALL R1 2 2  ; var1 = var1(var2)
      46 [-]: LOADK R2 K22 ; var2 = "TriggerPort"
      47 [-]: CALL R0 3 1  ; var0(var1, var2)
      48 [-]: GETUPVAL R1 5; var1 = upvalues[5]
      49 [-]: GETTABLEKS R0 R1 K18; var0 = var1[0xC474A99E]
      50 [-]: GETIMPORT R1 20; var1 = 0x0469F296
      51 [-]: LOADK R2 K23 ; var2 = "EntratiQuestShow"
      52 [-]: CALL R1 2 2  ; var1 = var1(var2)
      53 [-]: LOADK R2 K24 ; var2 = "Show"
      54 [-]: CALL R0 3 1  ; var0(var1, var2)
      55 [-]: GETUPVAL R1 5; var1 = upvalues[5]
      56 [-]: GETTABLEKS R0 R1 K18; var0 = var1[0xC474A99E]
      57 [-]: GETIMPORT R1 20; var1 = 0x0469F296
      58 [-]: LOADK R2 K25 ; var2 = "EntratiQuestLight"
      59 [-]: CALL R1 2 2  ; var1 = var1(var2)
      60 [-]: LOADK R2 K26 ; var2 = "TurnOn"
      61 [-]: CALL R0 3 1  ; var0(var1, var2)
      62 [-]: GETIMPORT R0 28; var0 = 0xCFC01047
      63 [-]: GETIMPORT R1 30; var1 = 0x2C82830C
      64 [-]: CALL R0 2 4  ; var0, var1, var2 = var0(var1)
      65 [-]: FORGPREP_NEXT R0 L3; 
L 2:  66 [-]: GETIMPORT R5 32; var5 = 0xBE190284
      67 [-]: MOVE R7 R4   ; var7 = var4
      68 [-]: NAMECALL R5 R5 K33; var6 = var5; var5 = var5[0xA5A5AD50]
      69 [-]: CALL R5 3 1  ; var5(var6, var7)
L 3:  70 [-]: FORGLOOP R0 L2 2; 
      71 [-]: GETIMPORT R0 1; var0 = 0x89326C93
      72 [-]: NAMECALL R0 R0 K34; var1 = var0; var0 = var0[0x29EF273D]
      73 [-]: CALL R0 2 2  ; var0 = var0(var1)
      74 [-]: GETUPVAL R3 6; var3 = upvalues[6]
      75 [-]: NAMECALL R1 R0 K35; var2 = var0; var1 = var0[0x8955C0B5]
      76 [-]: CALL R1 3 1  ; var1(var2, var3)
      77 [-]: GETUPVAL R1 7; var1 = upvalues[7]
      78 [-]: GETUPVAL R4 8; var4 = upvalues[8]
      79 [-]: GETTABLEKS R3 R4 K36; var3 = var4["SETUP"]
      80 [-]: NAMECALL R1 R1 K37; var2 = var1; var1 = var1[0x8ABFF40E]
      81 [-]: CALL R1 3 1  ; var1(var2, var3)
      82 [-]: LOADB R1 1   ; var1 = true
      83 [-]: SETUPVAL R1 9; upvalues[1] = var9
      84 [-]: RETURN R0 0  ; 


; Name:            
; Defined at line: 671
; #Upvalues:       0
; #Parameters:     0
; Is_vararg:       0
; Max Stack Size:  8

       0 [-]: GETIMPORT R0 1; var0 = 0xC8802016
       1 [-]: GETIMPORT R1 3; var1 = 0x2C82830C
       2 [-]: CALL R0 2 4  ; var0, var1, var2 = var0(var1)
       3 [-]: FORGPREP_INEXT R0 L1; 
L 0:   4 [-]: GETIMPORT R5 5; var5 = 0xBE190284
       5 [-]: MOVE R7 R4   ; var7 = var4
       6 [-]: NAMECALL R5 R5 K6; var6 = var5; var5 = var5[0x4924C573]
       7 [-]: CALL R5 3 1  ; var5(var6, var7)
L 1:   8 [-]: FORGLOOP R0 L0 2 [inext]; 
       9 [-]: RETURN R0 0  ; 


; Name:            
; Defined at line: 677
; #Upvalues:       7
; #Parameters:     1
; Is_vararg:       0
; Max Stack Size:  9

       0 [-]: GETIMPORT R1 1; var1 = 0x3D106989
       1 [-]: LOADK R2 K2  ; var2 = "Running Stage ONE for Entrati Quest"
       2 [-]: CALL R1 2 1  ; var1(var2)
       3 [-]: GETUPVAL R2 1; var2 = upvalues[1]
       4 [-]: GETTABLEKS R1 R2 K3; var1 = var2[0xC9013731]
       5 [-]: GETUPVAL R2 2; var2 = upvalues[2]
       6 [-]: CALL R1 2 2  ; var1 = var1(var2)
       7 [-]: SETUPVAL R1 0; upvalues[1] = var0
       8 [-]: LOADB R1 0   ; var1 = false
       9 [-]: SETUPVAL R1 3; upvalues[1] = var3
      10 [-]: GETUPVAL R1 4; var1 = upvalues[4]
      11 [-]: CALL R1 1 1  ; var1()
      12 [-]: GETIMPORT R3 5; var3 = 0x0469F296
      13 [-]: LOADK R4 K6  ; var4 = "DebugLoop"
      14 [-]: CALL R3 2 2  ; var3 = var3(var4)
      15 [-]: LOADB R4 0   ; var4 = false
      16 [-]: NAMECALL R1 R0 K7; var2 = var0; var1 = var0[0xD5F7912B]
      17 [-]: CALL R1 4 1  ; var1(var2, var3, var4)
L 0:  18 [-]: GETUPVAL R1 0; var1 = upvalues[0]
      19 [-]: NAMECALL R1 R1 K8; var2 = var1; var1 = var1[0xFAA69527]
      20 [-]: CALL R1 2 1  ; var1(var2)
      21 [-]: GETUPVAL R1 0; var1 = upvalues[0]
      22 [-]: NAMECALL R1 R1 K9; var2 = var1; var1 = var1[0x209398C2]
      23 [-]: CALL R1 2 2  ; var1 = var1(var2)
      24 [-]: SETUPVAL R1 5; upvalues[1] = var5
      25 [-]: GETUPVAL R1 6; var1 = upvalues[6]
      26 [-]: GETIMPORT R2 11; var2 = 0x67652851
      27 [-]: CALL R2 1 0  ; var2, ... = var2()
      28 [-]: CALL R1 0 1  ; var1(var2, ...)
      29 [-]: GETIMPORT R1 13; var1 = 0xCBD666E1
      30 [-]: LOADN R2 0   ; var2 = 0
      31 [-]: CALL R1 2 1  ; var1(var2)
      32 [-]: JUMPBACK L0  ; goto L0
      33 [-]: GETIMPORT R1 15; var1 = 0xC8802016
      34 [-]: GETIMPORT R2 17; var2 = 0x2C82830C
      35 [-]: CALL R1 2 4  ; var1, var2, var3 = var1(var2)
      36 [-]: FORGPREP_INEXT R1 L2; 
L 1:  37 [-]: GETIMPORT R6 19; var6 = 0xBE190284
      38 [-]: MOVE R8 R5   ; var8 = var5
      39 [-]: NAMECALL R6 R6 K20; var7 = var6; var6 = var6[0x4924C573]
      40 [-]: CALL R6 3 1  ; var6(var7, var8)
L 2:  41 [-]: FORGLOOP R1 L1 2 [inext]; 
      42 [-]: RETURN R0 0  ; 


; Name:            
; Defined at line: 696
; #Upvalues:       1
; #Parameters:     1
; Is_vararg:       0
; Max Stack Size:  2

       0 [-]: GETUPVAL R1 0; var1 = upvalues[0]
       1 [-]: JUMPIFNOT R1 L0; goto L0 if not var1
       2 [-]: LOADB R1 0   ; var1 = false
       3 [-]: SETUPVAL R1 0; upvalues[1] = var0
L 0:   4 [-]: RETURN R0 0  ; 


; Name:            
; Defined at line: 702
; #Upvalues:       3
; #Parameters:     1
; Is_vararg:       0
; Max Stack Size:  5

       0 [-]: GETUPVAL R1 0; var1 = upvalues[0]
       1 [-]: GETUPVAL R4 1; var4 = upvalues[1]
       2 [-]: GETTABLEKS R3 R4 K0; var3 = var4["RESPAWN"]
       3 [-]: NAMECALL R1 R1 K1; var2 = var1; var1 = var1[0x8ABFF40E]
       4 [-]: CALL R1 3 1  ; var1(var2, var3)
       5 [-]: GETUPVAL R2 2; var2 = upvalues[2]
       6 [-]: GETTABLEKS R1 R2 K2; var1 = var2[0xB112401F]
       7 [-]: LOADB R2 0   ; var2 = false
       8 [-]: LOADB R3 0   ; var3 = false
       9 [-]: CALL R1 3 1  ; var1(var2, var3)
      10 [-]: RETURN R0 0  ; 


; Name:            
; Defined at line: 708
; #Upvalues:       1
; #Parameters:     1
; Is_vararg:       0
; Max Stack Size:  11

       0 [-]: GETIMPORT R1 1; var1 = 0x3D106989
       1 [-]: LOADK R3 K2  ; var3 = "Saved checkpoint "
       2 [-]: NAMECALL R9 R0 K3; var10 = var0; var9 = var0[0xE223E2B1]
       3 [-]: CALL R9 2 0  ; var9, ... = var9(var10)
       4 [-]: FASTCALL 63 L0; 
       5 [-]: GETIMPORT R8 5; var8 = 0x64FB1586
       6 [-]: CALL R8 0 2  ; var8 = var8(var9, ...)
L 0:   7 [-]: MOVE R4 R8   ; var4 = var8
       8 [-]: LOADK R5 K6  ; var5 = "(tag="
       9 [-]: NAMECALL R9 R0 K7; var10 = var0; var9 = var0[0x22DA1852]
      10 [-]: CALL R9 2 0  ; var9, ... = var9(var10)
      11 [-]: FASTCALL 63 L1; 
      12 [-]: GETIMPORT R8 5; var8 = 0x64FB1586
      13 [-]: CALL R8 0 2  ; var8 = var8(var9, ...)
L 1:  14 [-]: MOVE R6 R8   ; var6 = var8
      15 [-]: LOADK R7 K8  ; var7 = ")"
      16 [-]: CONCAT R2 R3 R7; var2 = var3 .. var7
      17 [-]: CALL R1 2 1  ; var1(var2)
      18 [-]: SETUPVAL R0 0; upvalues[0] = var0
      19 [-]: RETURN R0 0  ; 


; Name:            
; Defined at line: 713
; #Upvalues:       7
; #Parameters:     1
; Is_vararg:       0
; Max Stack Size:  8

       0 [-]: GETUPVAL R2 0; var2 = upvalues[0]
       1 [-]: NAMECALL R3 R0 K0; var4 = var0; var3 = var0[0x22DA1852]
       2 [-]: CALL R3 2 2  ; var3 = var3(var4)
       3 [-]: NAMECALL R3 R3 K1; var4 = var3; var3 = var3[0x6D604BA7]
       4 [-]: CALL R3 2 2  ; var3 = var3(var4)
       5 [-]: GETTABLE R1 R2 R3; var1 = var2[var3]
       6 [-]: GETUPVAL R3 1; var3 = upvalues[1]
       7 [-]: GETTABLEKS R2 R3 K2; var2 = var3["DEFEAT_MECH_GRIMOIRE"]
       8 [-]: JUMPIFNOTLT R2 R1 L1; goto L1 if var2 >= var131644
       9 [-]: GETUPVAL R2 2; var2 = upvalues[2]
      10 [-]: GETIMPORT R4 4; var4 = 0x018C17B0
      11 [-]: LOADB R5 0   ; var5 = false
      12 [-]: NAMECALL R2 R2 K5; var3 = var2; var2 = var2[0x511D26B8]
      13 [-]: CALL R2 4 2  ; var2 = var2(var3, var4, var5)
      14 [-]: GETUPVAL R3 2; var3 = upvalues[2]
      15 [-]: NAMECALL R3 R3 K6; var4 = var3; var3 = var3[0xDE321E6F]
      16 [-]: CALL R3 2 2  ; var3 = var3(var4)
      17 [-]: LOADN R5 0   ; var5 = 0
      18 [-]: LOADN R6 0   ; var6 = 0
      19 [-]: LOADN R7 2   ; var7 = 2
      20 [-]: NAMECALL R3 R3 K7; var4 = var3; var3 = var3[0xC69087F6]
      21 [-]: CALL R3 5 1  ; var3(var4, var5, var6, var7)
      22 [-]: GETIMPORT R3 9; var3 = 0x89326C93
      23 [-]: GETUPVAL R5 3; var5 = upvalues[3]
      24 [-]: MOVE R6 R2   ; var6 = var2
      25 [-]: NAMECALL R3 R3 K10; var4 = var3; var3 = var3[0x765DAD71]
      26 [-]: CALL R3 4 2  ; var3 = var3(var4, var5, var6)
      27 [-]: FASTCALL1 64 R3 L0; 
      28 [-]: MOVE R5 R3   ; var5 = var3
      29 [-]: GETIMPORT R4 12; var4 = 0x7B998233
      30 [-]: CALL R4 2 2  ; var4 = var4(var5)
L 0:  31 [-]: JUMPIF R4 L2 ; goto L2 if var4
      32 [-]: MOVE R6 R3   ; var6 = var3
      33 [-]: NAMECALL R4 R2 K13; var5 = var2; var4 = var2[0x5E6704FF]
      34 [-]: CALL R4 3 1  ; var4(var5, var6)
      35 [-]: JUMP L2      ; goto L2
L 1:  36 [-]: GETIMPORT R2 9; var2 = 0x89326C93
      37 [-]: GETIMPORT R4 15; var4 = 0x0469F296
      38 [-]: LOADK R5 K16 ; var5 = "GrimoireDeco"
      39 [-]: CALL R4 2 0  ; var4, ... = var4(var5)
      40 [-]: NAMECALL R2 R2 K17; var3 = var2; var2 = var2[0x46A0EBF5]
      41 [-]: CALL R2 0 2  ; var2 = var2(var3, ...)
      42 [-]: LOADB R5 1   ; var5 = true
      43 [-]: LOADB R6 1   ; var6 = true
      44 [-]: NAMECALL R3 R2 K18; var4 = var2; var3 = var2[0x768274D6]
      45 [-]: CALL R3 4 1  ; var3(var4, var5, var6)
      46 [-]: GETUPVAL R4 4; var4 = upvalues[4]
      47 [-]: GETTABLEKS R3 R4 K19; var3 = var4[0xC474A99E]
      48 [-]: GETIMPORT R4 15; var4 = 0x0469F296
      49 [-]: LOADK R5 K20 ; var5 = "ResetGrimoirePickup"
      50 [-]: CALL R4 2 2  ; var4 = var4(var5)
      51 [-]: LOADK R5 K21 ; var5 = "TriggerPort"
      52 [-]: CALL R3 3 1  ; var3(var4, var5)
L 2:  53 [-]: LOADN R2 0   ; var2 = 0
      54 [-]: SETUPVAL R2 5; upvalues[2] = var5
      55 [-]: GETUPVAL R3 4; var3 = upvalues[4]
      56 [-]: GETTABLEKS R2 R3 K19; var2 = var3[0xC474A99E]
      57 [-]: GETIMPORT R3 15; var3 = 0x0469F296
      58 [-]: LOADK R4 K22 ; var4 = "SandWallOff"
      59 [-]: CALL R3 2 2  ; var3 = var3(var4)
      60 [-]: LOADK R4 K21 ; var4 = "TriggerPort"
      61 [-]: CALL R2 3 1  ; var2(var3, var4)
      62 [-]: GETUPVAL R2 6; var2 = upvalues[6]
      63 [-]: MOVE R4 R1   ; var4 = var1
      64 [-]: NAMECALL R2 R2 K23; var3 = var2; var2 = var2[0x8ABFF40E]
      65 [-]: CALL R2 3 1  ; var2(var3, var4)
      66 [-]: RETURN R0 0  ; 


; Name:            
; Defined at line: 728
; #Upvalues:       14
; #Parameters:     2
; Is_vararg:       0
; Max Stack Size:  11

       0 [-]: NAMECALL R2 R0 K0; var3 = var0; var2 = var0[0x22DA1852]
       1 [-]: CALL R2 2 2  ; var2 = var2(var3)
       2 [-]: GETUPVAL R3 0; var3 = upvalues[0]
       3 [-]: JUMPIFNOTEQ R2 R3 L0; goto L0 if var2 ~= var66310
       4 [-]: LOADB R3 1   ; var3 = true
       5 [-]: SETUPVAL R3 1; upvalues[3] = var1
       6 [-]: JUMP L8      ; goto L8
L 0:   7 [-]: GETIMPORT R3 2; var3 = 0x0469F296
       8 [-]: LOADK R4 K3  ; var4 = "QuestSpottedMechsTrigger"
       9 [-]: CALL R3 2 2  ; var3 = var3(var4)
      10 [-]: JUMPIFNOTEQ R2 R3 L1; goto L1 if var2 ~= var-1241513140
      11 [-]: NAMECALL R3 R0 K4; var4 = var0; var3 = var0[0xF4E253B6]
      12 [-]: CALL R3 2 1  ; var3(var4)
      13 [-]: GETUPVAL R4 2; var4 = upvalues[2]
      14 [-]: GETTABLEKS R3 R4 K5; var3 = var4[0x9742B85B]
      15 [-]: GETUPVAL R4 3; var4 = upvalues[3]
      16 [-]: GETIMPORT R5 2; var5 = 0x0469F296
      17 [-]: LOADK R6 K6  ; var6 = "DEnterTheLabs0120"
      18 [-]: CALL R5 2 2  ; var5 = var5(var6)
      19 [-]: LOADB R6 0   ; var6 = false
      20 [-]: LOADB R7 1   ; var7 = true
      21 [-]: CALL R3 5 1  ; var3(var4, var5, var6, var7)
      22 [-]: GETUPVAL R4 4; var4 = upvalues[4]
      23 [-]: GETTABLEKS R3 R4 K7; var3 = var4[0xC474A99E]
      24 [-]: GETIMPORT R4 2; var4 = 0x0469F296
      25 [-]: LOADK R5 K8  ; var5 = "QuestEnableMechAi"
      26 [-]: CALL R4 2 2  ; var4 = var4(var5)
      27 [-]: LOADK R5 K9  ; var5 = "TriggerPort"
      28 [-]: CALL R3 3 1  ; var3(var4, var5)
      29 [-]: GETUPVAL R3 5; var3 = upvalues[5]
      30 [-]: GETUPVAL R6 6; var6 = upvalues[6]
      31 [-]: GETTABLEKS R5 R6 K10; var5 = var6["DEFEAT_MECH"]
      32 [-]: NAMECALL R3 R3 K11; var4 = var3; var3 = var3[0x8ABFF40E]
      33 [-]: CALL R3 3 1  ; var3(var4, var5)
      34 [-]: JUMP L8      ; goto L8
L 1:  35 [-]: GETUPVAL R3 7; var3 = upvalues[7]
      36 [-]: JUMPIFNOTEQ R2 R3 L2; goto L2 if var2 ~= var132156
      37 [-]: GETUPVAL R4 2; var4 = upvalues[2]
      38 [-]: GETTABLEKS R3 R4 K5; var3 = var4[0x9742B85B]
      39 [-]: GETUPVAL R4 3; var4 = upvalues[3]
      40 [-]: GETIMPORT R5 2; var5 = 0x0469F296
      41 [-]: LOADK R6 K12 ; var6 = "DEnterTheLabs0180"
      42 [-]: CALL R5 2 2  ; var5 = var5(var6)
      43 [-]: LOADB R6 0   ; var6 = false
      44 [-]: LOADB R7 1   ; var7 = true
      45 [-]: CALL R3 5 1  ; var3(var4, var5, var6, var7)
      46 [-]: JUMP L8      ; goto L8
L 2:  47 [-]: GETUPVAL R3 8; var3 = upvalues[8]
      48 [-]: JUMPIFNOTEQ R2 R3 L3; goto L3 if var2 ~= var590652
      49 [-]: GETUPVAL R3 9; var3 = upvalues[9]
      50 [-]: JUMPIF R3 L8 ; goto L8 if var3
      51 [-]: LOADB R3 1   ; var3 = true
      52 [-]: SETUPVAL R3 9; upvalues[3] = var9
      53 [-]: GETUPVAL R3 10; var3 = upvalues[10]
      54 [-]: GETIMPORT R5 2; var5 = 0x0469F296
      55 [-]: LOADK R6 K13 ; var6 = "MITWReveal"
      56 [-]: CALL R5 2 2  ; var5 = var5(var6)
      57 [-]: LOADB R6 0   ; var6 = false
      58 [-]: NAMECALL R3 R3 K14; var4 = var3; var3 = var3[0xD5F7912B]
      59 [-]: CALL R3 4 1  ; var3(var4, var5, var6)
      60 [-]: JUMP L8      ; goto L8
L 3:  61 [-]: GETUPVAL R3 11; var3 = upvalues[11]
      62 [-]: JUMPIFNOTEQ R2 R3 L7; goto L7 if var2 ~= var328508
      63 [-]: GETUPVAL R3 5; var3 = upvalues[5]
      64 [-]: GETUPVAL R6 6; var6 = upvalues[6]
      65 [-]: GETTABLEKS R5 R6 K15; var5 = var6["DEFEAT_MITW"]
      66 [-]: NAMECALL R3 R3 K11; var4 = var3; var3 = var3[0x8ABFF40E]
      67 [-]: CALL R3 3 1  ; var3(var4, var5)
      68 [-]: GETIMPORT R3 17; var3 = 0x89326C93
      69 [-]: GETUPVAL R5 11; var5 = upvalues[11]
      70 [-]: NAMECALL R3 R3 K18; var4 = var3; var3 = var3[0xC7FCADA9]
      71 [-]: CALL R3 3 2  ; var3 = var3(var4, var5)
      72 [-]: GETIMPORT R4 20; var4 = 0xC8802016
      73 [-]: MOVE R5 R3   ; var5 = var3
      74 [-]: CALL R4 2 4  ; var4, var5, var6 = var4(var5)
      75 [-]: FORGPREP_INEXT R4 L5; 
L 4:  76 [-]: NAMECALL R9 R8 K4; var10 = var8; var9 = var8[0xF4E253B6]
      77 [-]: CALL R9 2 1  ; var9(var10)
L 5:  78 [-]: FORGLOOP R4 L4 2 [inext]; 
      79 [-]: GETIMPORT R4 17; var4 = 0x89326C93
      80 [-]: GETIMPORT R6 2; var6 = 0x0469F296
      81 [-]: LOADK R7 K21 ; var7 = "InvertedTeleport"
      82 [-]: CALL R6 2 0  ; var6, ... = var6(var7)
      83 [-]: NAMECALL R4 R4 K22; var5 = var4; var4 = var4[0x46A0EBF5]
      84 [-]: CALL R4 0 2  ; var4 = var4(var5, ...)
      85 [-]: FASTCALL1 64 R4 L6; 
      86 [-]: MOVE R6 R4   ; var6 = var4
      87 [-]: GETIMPORT R5 24; var5 = 0x7B998233
      88 [-]: CALL R5 2 2  ; var5 = var5(var6)
L 6:  89 [-]: JUMPIF R5 L8 ; goto L8 if var5
      90 [-]: NAMECALL R5 R4 K25; var6 = var4; var5 = var4[0xD91E1179]
      91 [-]: CALL R5 2 1  ; var5(var6)
      92 [-]: JUMP L8      ; goto L8
L 7:  93 [-]: GETIMPORT R3 2; var3 = 0x0469F296
      94 [-]: LOADK R4 K26 ; var4 = "LoidExitTrigger"
      95 [-]: CALL R3 2 2  ; var3 = var3(var4)
      96 [-]: JUMPIFNOTEQ R2 R3 L8; goto L8 if var2 ~= var787516
      97 [-]: GETUPVAL R4 12; var4 = upvalues[12]
      98 [-]: GETTABLEKS R3 R4 K27; var3 = var4[0xA1D0E6E1]
      99 [-]: GETUPVAL R4 10; var4 = upvalues[10]
     100 [-]: LOADB R5 0   ; var5 = false
     101 [-]: CALL R3 3 1  ; var3(var4, var5)
     102 [-]: LOADB R3 1   ; var3 = true
     103 [-]: SETUPVAL R3 13; upvalues[3] = var13
L 8: 104 [-]: FASTCALL1 64 R0 L9; 
     105 [-]: MOVE R4 R0   ; var4 = var0
     106 [-]: GETIMPORT R3 24; var3 = 0x7B998233
     107 [-]: CALL R3 2 2  ; var3 = var3(var4)
L 9: 108 [-]: JUMPIF R3 L10; goto L10 if var3
     109 [-]: NAMECALL R3 R0 K4; var4 = var0; var3 = var0[0xF4E253B6]
     110 [-]: CALL R3 2 1  ; var3(var4)
L10: 111 [-]: RETURN R0 0  ; 


; Name:            
; Defined at line: 767
; #Upvalues:       0
; #Parameters:     4
; Is_vararg:       0
; Max Stack Size:  13

       0 [-]: LOADN R4 0   ; var4 = 0
       1 [-]: LOADNIL R5   ; var5 = nil
       2 [-]: LOADNIL R6   ; var6 = nil
       3 [-]: NAMECALL R7 R0 K0; var8 = var0; var7 = var0[0xD1586535]
       4 [-]: CALL R7 2 2  ; var7 = var7(var8)
       5 [-]: NAMECALL R8 R0 K1; var9 = var0; var8 = var0[0x5280B883]
       6 [-]: CALL R8 2 2  ; var8 = var8(var9)
L 0:   7 [-]: JUMPIFNOTLT R4 R1 L2; goto L2 if var4 >= var199713
       8 [-]: GETIMPORT R12 3; var12 = 0x67652851
       9 [-]: CALL R12 1 2 ; var12 = var12()
      10 [-]: ADD R11 R4 R12; var11 = var4 + var12
      11 [-]: FASTCALL2 19 R1 R11 L1; 
      12 [-]: MOVE R10 R1  ; var10 = var1
      13 [-]: GETIMPORT R9 6; var9 = 0x5BCED4C4[0xAC1B386A]
      14 [-]: CALL R9 3 2  ; var9 = var9(var10, var11)
L 1:  15 [-]: MOVE R4 R9   ; var4 = var9
      16 [-]: GETIMPORT R9 8; var9 = 0x5DB3CE80
      17 [-]: MOVE R10 R7  ; var10 = var7
      18 [-]: MOVE R11 R2  ; var11 = var2
      19 [-]: DIV R12 R4 R1; var12 = var4 / var1
      20 [-]: CALL R9 4 2  ; var9 = var9(var10, var11, var12)
      21 [-]: MOVE R5 R9   ; var5 = var9
      22 [-]: GETIMPORT R9 10; var9 = 0x5E223E7D
      23 [-]: MOVE R10 R8  ; var10 = var8
      24 [-]: MOVE R11 R3  ; var11 = var3
      25 [-]: DIV R12 R4 R1; var12 = var4 / var1
      26 [-]: CALL R9 4 2  ; var9 = var9(var10, var11, var12)
      27 [-]: MOVE R6 R9   ; var6 = var9
      28 [-]: MOVE R11 R5  ; var11 = var5
      29 [-]: MOVE R12 R6  ; var12 = var6
      30 [-]: NAMECALL R9 R0 K11; var10 = var0; var9 = var0[0x589EF1C1]
      31 [-]: CALL R9 4 1  ; var9(var10, var11, var12)
      32 [-]: GETIMPORT R9 13; var9 = 0xCBD666E1
      33 [-]: LOADN R10 0  ; var10 = 0
      34 [-]: CALL R9 2 1  ; var9(var10)
      35 [-]: JUMPBACK L0  ; goto L0
L 2:  36 [-]: RETURN R0 0  ; 


; Name:            
; Defined at line: 782
; #Upvalues:       6
; #Parameters:     1
; Is_vararg:       0
; Max Stack Size:  15

       0 [-]: GETUPVAL R1 0; var1 = upvalues[0]
       1 [-]: NAMECALL R1 R1 K0; var2 = var1; var1 = var1[0xDE321E6F]
       2 [-]: CALL R1 2 2  ; var1 = var1(var2)
       3 [-]: LOADN R4 0   ; var4 = 0
       4 [-]: LOADN R5 2   ; var5 = 2
       5 [-]: NAMECALL R2 R1 K1; var3 = var1; var2 = var1[0x4703255B]
       6 [-]: CALL R2 4 1  ; var2(var3, var4, var5)
       7 [-]: LOADN R4 0   ; var4 = 0
       8 [-]: NAMECALL R2 R1 K2; var3 = var1; var2 = var1[0x881B6B90]
       9 [-]: CALL R2 3 2  ; var2 = var2(var3, var4)
      10 [-]: LOADN R5 10  ; var5 = 10
      11 [-]: NAMECALL R3 R1 K3; var4 = var1; var3 = var1[0xE85A2361]
      12 [-]: CALL R3 3 2  ; var3 = var3(var4, var5)
      13 [-]: FASTCALL1 64 R2 L0; 
      14 [-]: MOVE R5 R2   ; var5 = var2
      15 [-]: GETIMPORT R4 5; var4 = 0x7B998233
      16 [-]: CALL R4 2 2  ; var4 = var4(var5)
L 0:  17 [-]: JUMPIF R4 L6 ; goto L6 if var4
      18 [-]: JUMPIFNOTEQ R2 R3 L6; goto L6 if var2 ~= var459809
      19 [-]: GETIMPORT R4 7; var4 = 0x25D99D89
      20 [-]: NAMECALL R4 R4 K8; var5 = var4; var4 = var4[0x62C81B76]
      21 [-]: CALL R4 2 2  ; var4 = var4(var5)
      22 [-]: FASTCALL1 64 R4 L1; 
      23 [-]: MOVE R6 R4   ; var6 = var4
      24 [-]: GETIMPORT R5 5; var5 = 0x7B998233
      25 [-]: CALL R5 2 2  ; var5 = var5(var6)
L 1:  26 [-]: JUMPIF R5 L6 ; goto L6 if var5
      27 [-]: NAMECALL R5 R4 K9; var6 = var4; var5 = var4[0x51A64E2E]
      28 [-]: CALL R5 2 2  ; var5 = var5(var6)
      29 [-]: GETIMPORT R6 11; var6 = 0xC8802016
      30 [-]: MOVE R7 R5   ; var7 = var5
      31 [-]: CALL R6 2 4  ; var6, var7, var8 = var6(var7)
      32 [-]: FORGPREP_INEXT R6 L5; 
L 2:  33 [-]: FASTCALL1 64 R10 L3; 
      34 [-]: MOVE R12 R10 ; var12 = var10
      35 [-]: GETIMPORT R11 5; var11 = 0x7B998233
      36 [-]: CALL R11 2 2 ; var11 = var11(var12)
L 3:  37 [-]: JUMPIF R11 L5; goto L5 if var11
      38 [-]: GETTABLEKS R12 R10 K12; var12 = var10["mItemType"]
      39 [-]: FASTCALL1 64 R12 L4; 
      40 [-]: GETIMPORT R11 5; var11 = 0x7B998233
      41 [-]: CALL R11 2 2 ; var11 = var11(var12)
L 4:  42 [-]: JUMPIF R11 L5; goto L5 if var11
      43 [-]: GETTABLEKS R11 R10 K12; var11 = var10["mItemType"]
      44 [-]: GETUPVAL R13 1; var13 = upvalues[1]
      45 [-]: NAMECALL R11 R11 K13; var12 = var11; var11 = var11[0xF2DEAF69]
      46 [-]: CALL R11 3 2 ; var11 = var11(var12, var13)
      47 [-]: JUMPIFNOT R11 L5; goto L5 if not var11
      48 [-]: SUBK R13 R9 K14; var13 = var9 - 1
      49 [-]: NAMECALL R11 R1 K15; var12 = var1; var11 = var1[0xFD52FD85]
      50 [-]: CALL R11 3 1 ; var11(var12, var13)
      51 [-]: JUMP L6      ; goto L6
L 5:  52 [-]: FORGLOOP R6 L2 2 [inext]; 
L 6:  53 [-]: GETUPVAL R4 0; var4 = upvalues[0]
      54 [-]: NAMECALL R4 R4 K16; var5 = var4; var4 = var4[0x03537BE0]
      55 [-]: CALL R4 2 1  ; var4(var5)
      56 [-]: GETUPVAL R4 0; var4 = upvalues[0]
      57 [-]: NAMECALL R4 R4 K17; var5 = var4; var4 = var4[0xD3A01177]
      58 [-]: CALL R4 2 2  ; var4 = var4(var5)
      59 [-]: LOADB R6 0   ; var6 = false
      60 [-]: NAMECALL R4 R4 K18; var5 = var4; var4 = var4[0x17E9BF45]
      61 [-]: CALL R4 3 1  ; var4(var5, var6)
      62 [-]: GETUPVAL R4 0; var4 = upvalues[0]
      63 [-]: NAMECALL R4 R4 K0; var5 = var4; var4 = var4[0xDE321E6F]
      64 [-]: CALL R4 2 2  ; var4 = var4(var5)
      65 [-]: NAMECALL R4 R4 K19; var5 = var4; var4 = var4[0xF7D48EE0]
      66 [-]: CALL R4 2 2  ; var4 = var4(var5)
      67 [-]: FASTCALL1 64 R4 L7; 
      68 [-]: MOVE R6 R4   ; var6 = var4
      69 [-]: GETIMPORT R5 5; var5 = 0x7B998233
      70 [-]: CALL R5 2 2  ; var5 = var5(var6)
L 7:  71 [-]: JUMPIF R5 L8 ; goto L8 if var5
      72 [-]: NAMECALL R5 R4 K20; var6 = var4; var5 = var4[0x707CD1F0]
      73 [-]: CALL R5 2 1  ; var5(var6)
      74 [-]: LOADB R7 0   ; var7 = false
      75 [-]: NAMECALL R5 R4 K21; var6 = var4; var5 = var4[0x1BF26251]
      76 [-]: CALL R5 3 1  ; var5(var6, var7)
L 8:  77 [-]: GETUPVAL R5 2; var5 = upvalues[2]
      78 [-]: GETUPVAL R6 0; var6 = upvalues[0]
      79 [-]: LOADK R7 K22 ; var7 = 0.25
      80 [-]: NAMECALL R8 R0 K23; var9 = var0; var8 = var0[0xD1586535]
      81 [-]: CALL R8 2 2  ; var8 = var8(var9)
      82 [-]: NAMECALL R9 R0 K24; var10 = var0; var9 = var0[0xCB3851B8]
      83 [-]: CALL R9 2 0  ; var9, ... = var9(var10)
      84 [-]: CALL R5 0 1  ; var5(var6, ...)
      85 [-]: GETIMPORT R5 26; var5 = 0x89326C93
      86 [-]: GETIMPORT R7 28; var7 = 0x0469F296
      87 [-]: LOADK R8 K29 ; var8 = "GrimoireDeco"
      88 [-]: CALL R7 2 0  ; var7, ... = var7(var8)
      89 [-]: NAMECALL R5 R5 K30; var6 = var5; var5 = var5[0x46A0EBF5]
      90 [-]: CALL R5 0 2  ; var5 = var5(var6, ...)
      91 [-]: NAMECALL R6 R5 K31; var7 = var5; var6 = var5[0xF6EBD926]
      92 [-]: CALL R6 2 2  ; var6 = var6(var7)
      93 [-]: NAMECALL R7 R5 K32; var8 = var5; var7 = var5[0x5280B883]
      94 [-]: CALL R7 2 2  ; var7 = var7(var8)
      95 [-]: FASTCALL1 64 R5 L9; 
      96 [-]: MOVE R9 R5   ; var9 = var5
      97 [-]: GETIMPORT R8 5; var8 = 0x7B998233
      98 [-]: CALL R8 2 2  ; var8 = var8(var9)
L 9:  99 [-]: JUMPIF R8 L10; goto L10 if var8
     100 [-]: GETIMPORT R10 34; var10 = 0xCB57AD1F
     101 [-]: GETIMPORT R11 36; var11 = EMPTY_SYMBOL
     102 [-]: GETIMPORT R12 38; var12 = ZERO_VECTOR
     103 [-]: GETIMPORT R13 40; var13 = ZERO_ROTATION
     104 [-]: MOVE R14 R5  ; var14 = var5
     105 [-]: NAMECALL R8 R5 K41; var9 = var5; var8 = var5[0x47901F07]
     106 [-]: CALL R8 7 1  ; var8(var9, var10, var11, var12, var13, var14)
     107 [-]: GETIMPORT R10 43; var10 = 0xDDEA6BE1
     108 [-]: LOADB R11 0  ; var11 = false
     109 [-]: NAMECALL R8 R5 K44; var9 = var5; var8 = var5[0x5D985C7E]
     110 [-]: CALL R8 4 1  ; var8(var9, var10, var11)
L10: 111 [-]: GETUPVAL R8 0; var8 = upvalues[0]
     112 [-]: GETIMPORT R10 46; var10 = 0x19CF2005
     113 [-]: LOADB R11 0  ; var11 = false
     114 [-]: LOADN R12 4  ; var12 = 4
     115 [-]: LOADN R13 1  ; var13 = 1
     116 [-]: LOADB R14 0  ; var14 = false
     117 [-]: NAMECALL R8 R8 K44; var9 = var8; var8 = var8[0x5D985C7E]
     118 [-]: CALL R8 7 1  ; var8(var9, var10, var11, var12, var13, var14)
     119 [-]: GETUPVAL R8 0; var8 = upvalues[0]
     120 [-]: LOADK R10 K47; var10 = "Pickup"
     121 [-]: LOADN R11 8  ; var11 = 8
     122 [-]: NAMECALL R8 R8 K48; var9 = var8; var8 = var8[0x21B4C60E]
     123 [-]: CALL R8 4 1  ; var8(var9, var10, var11)
     124 [-]: GETUPVAL R9 3; var9 = upvalues[3]
     125 [-]: FASTCALL1 64 R9 L11; 
     126 [-]: GETIMPORT R8 5; var8 = 0x7B998233
     127 [-]: CALL R8 2 2  ; var8 = var8(var9)
L11: 128 [-]: JUMPIF R8 L14; goto L14 if var8
     129 [-]: GETUPVAL R9 4; var9 = upvalues[4]
     130 [-]: FASTCALL1 64 R9 L12; 
     131 [-]: GETIMPORT R8 5; var8 = 0x7B998233
     132 [-]: CALL R8 2 2  ; var8 = var8(var9)
L12: 133 [-]: JUMPIF R8 L14; goto L14 if var8
     134 [-]: GETIMPORT R8 50; var8 = 0x9BA7909F
     135 [-]: GETUPVAL R10 3; var10 = upvalues[3]
     136 [-]: NAMECALL R8 R8 K51; var9 = var8; var8 = var8[0x6DD7AA66]
     137 [-]: CALL R8 3 2  ; var8 = var8(var9, var10)
     138 [-]: FASTCALL1 64 R8 L13; 
     139 [-]: MOVE R10 R8  ; var10 = var8
     140 [-]: GETIMPORT R9 5; var9 = 0x7B998233
     141 [-]: CALL R9 2 2  ; var9 = var9(var10)
L13: 142 [-]: JUMPIF R9 L14; goto L14 if var9
     143 [-]: GETIMPORT R9 54; var9 = _T["DisplayReward"]
     144 [-]: GETUPVAL R10 4; var10 = upvalues[4]
     145 [-]: LOADN R11 1  ; var11 = 1
     146 [-]: CALL R9 3 1  ; var9(var10, var11)
L14: 147 [-]: GETUPVAL R10 0; var10 = upvalues[0]
     148 [-]: GETIMPORT R11 28; var11 = 0x0469F296
     149 [-]: LOADK R12 K55; var12 = "GAME_R1_WEAPON1"
     150 [-]: CALL R11 2 0 ; var11, ... = var11(var12)
     151 [-]: NAMECALL R8 R5 K56; var9 = var5; var8 = var5[0xB6B094B2]
     152 [-]: CALL R8 0 1  ; var8(var9, ...)
     153 [-]: GETIMPORT R8 26; var8 = 0x89326C93
     154 [-]: GETIMPORT R10 58; var10 = 0x8C214EBE
     155 [-]: NAMECALL R11 R5 K31; var12 = var5; var11 = var5[0xF6EBD926]
     156 [-]: CALL R11 2 2 ; var11 = var11(var12)
     157 [-]: NAMECALL R12 R5 K32; var13 = var5; var12 = var5[0x5280B883]
     158 [-]: CALL R12 2 0 ; var12, ... = var12(var13)
     159 [-]: NAMECALL R8 R8 K59; var9 = var8; var8 = var8[0x05909209]
     160 [-]: CALL R8 0 1  ; var8(var9, ...)
     161 [-]: GETUPVAL R8 0; var8 = upvalues[0]
     162 [-]: GETIMPORT R10 61; var10 = 0x018C17B0
     163 [-]: LOADB R11 0  ; var11 = false
     164 [-]: NAMECALL R8 R8 K62; var9 = var8; var8 = var8[0x511D26B8]
     165 [-]: CALL R8 4 2  ; var8 = var8(var9, var10, var11)
     166 [-]: GETUPVAL R9 0; var9 = upvalues[0]
     167 [-]: NAMECALL R9 R9 K0; var10 = var9; var9 = var9[0xDE321E6F]
     168 [-]: CALL R9 2 2  ; var9 = var9(var10)
     169 [-]: LOADN R11 0  ; var11 = 0
     170 [-]: LOADN R12 0  ; var12 = 0
     171 [-]: LOADN R13 2  ; var13 = 2
     172 [-]: NAMECALL R9 R9 K63; var10 = var9; var9 = var9[0xC69087F6]
     173 [-]: CALL R9 5 1  ; var9(var10, var11, var12, var13)
     174 [-]: GETIMPORT R9 26; var9 = 0x89326C93
     175 [-]: GETUPVAL R11 5; var11 = upvalues[5]
     176 [-]: MOVE R12 R8  ; var12 = var8
     177 [-]: NAMECALL R9 R9 K64; var10 = var9; var9 = var9[0x765DAD71]
     178 [-]: CALL R9 4 2  ; var9 = var9(var10, var11, var12)
     179 [-]: FASTCALL1 64 R9 L15; 
     180 [-]: MOVE R11 R9  ; var11 = var9
     181 [-]: GETIMPORT R10 5; var10 = 0x7B998233
     182 [-]: CALL R10 2 2 ; var10 = var10(var11)
L15: 183 [-]: JUMPIF R10 L16; goto L16 if var10
     184 [-]: MOVE R12 R9  ; var12 = var9
     185 [-]: NAMECALL R10 R8 K65; var11 = var8; var10 = var8[0x5E6704FF]
     186 [-]: CALL R10 3 1 ; var10(var11, var12)
L16: 187 [-]: FASTCALL1 64 R5 L17; 
     188 [-]: MOVE R9 R5   ; var9 = var5
     189 [-]: GETIMPORT R8 5; var8 = 0x7B998233
     190 [-]: CALL R8 2 2  ; var8 = var8(var9)
L17: 191 [-]: JUMPIF R8 L18; goto L18 if var8
     192 [-]: LOADB R10 0  ; var10 = false
     193 [-]: LOADB R11 0  ; var11 = false
     194 [-]: NAMECALL R8 R5 K66; var9 = var5; var8 = var5[0x768274D6]
     195 [-]: CALL R8 4 1  ; var8(var9, var10, var11)
     196 [-]: NAMECALL R8 R5 K67; var9 = var5; var8 = var5[0x467C327C]
     197 [-]: CALL R8 2 1  ; var8(var9)
     198 [-]: MOVE R10 R6  ; var10 = var6
     199 [-]: MOVE R11 R7  ; var11 = var7
     200 [-]: NAMECALL R8 R5 K68; var9 = var5; var8 = var5[0x589EF1C1]
     201 [-]: CALL R8 4 1  ; var8(var9, var10, var11)
L18: 202 [-]: GETUPVAL R8 0; var8 = upvalues[0]
     203 [-]: NAMECALL R8 R8 K17; var9 = var8; var8 = var8[0xD3A01177]
     204 [-]: CALL R8 2 2  ; var8 = var8(var9)
     205 [-]: LOADB R10 1  ; var10 = true
     206 [-]: NAMECALL R8 R8 K18; var9 = var8; var8 = var8[0x17E9BF45]
     207 [-]: CALL R8 3 1  ; var8(var9, var10)
     208 [-]: GETUPVAL R8 0; var8 = upvalues[0]
     209 [-]: NAMECALL R8 R8 K0; var9 = var8; var8 = var8[0xDE321E6F]
     210 [-]: CALL R8 2 2  ; var8 = var8(var9)
     211 [-]: NAMECALL R8 R8 K19; var9 = var8; var8 = var8[0xF7D48EE0]
     212 [-]: CALL R8 2 2  ; var8 = var8(var9)
     213 [-]: MOVE R4 R8   ; var4 = var8
     214 [-]: FASTCALL1 64 R4 L19; 
     215 [-]: MOVE R9 R4   ; var9 = var4
     216 [-]: GETIMPORT R8 5; var8 = 0x7B998233
     217 [-]: CALL R8 2 2  ; var8 = var8(var9)
L19: 218 [-]: JUMPIF R8 L20; goto L20 if var8
     219 [-]: LOADB R10 1  ; var10 = true
     220 [-]: NAMECALL R8 R4 K21; var9 = var4; var8 = var4[0x1BF26251]
     221 [-]: CALL R8 3 1  ; var8(var9, var10)
L20: 222 [-]: RETURN R0 0  ; 


; Name:            
; Defined at line: 847
; #Upvalues:       2
; #Parameters:     1
; Is_vararg:       0
; Max Stack Size:  3

       0 [-]: NAMECALL R1 R0 K0; var2 = var0; var1 = var0[0xF4E253B6]
       1 [-]: CALL R1 2 1  ; var1(var2)
       2 [-]: GETIMPORT R1 2; var1 = 0x89326C93
       3 [-]: NAMECALL R1 R1 K3; var2 = var1; var1 = var1[0x78298275]
       4 [-]: CALL R1 2 2  ; var1 = var1(var2)
       5 [-]: SETUPVAL R1 0; upvalues[1] = var0
       6 [-]: GETUPVAL R1 1; var1 = upvalues[1]
       7 [-]: MOVE R2 R0   ; var2 = var0
       8 [-]: CALL R1 2 1  ; var1(var2)
       9 [-]: RETURN R0 0  ; 


; Name:            
; Defined at line: 853
; #Upvalues:       5
; #Parameters:     1
; Is_vararg:       0
; Max Stack Size:  6

       0 [-]: NAMECALL R1 R0 K0; var2 = var0; var1 = var0[0x22DA1852]
       1 [-]: CALL R1 2 2  ; var1 = var1(var2)
       2 [-]: GETUPVAL R2 0; var2 = upvalues[0]
       3 [-]: JUMPIFNOTEQ R1 R2 L0; goto L0 if var1 ~= var-1241513396
       4 [-]: NAMECALL R2 R0 K1; var3 = var0; var2 = var0[0xF4E253B6]
       5 [-]: CALL R2 2 1  ; var2(var3)
       6 [-]: GETUPVAL R2 1; var2 = upvalues[1]
       7 [-]: MOVE R3 R0   ; var3 = var0
       8 [-]: CALL R2 2 1  ; var2(var3)
       9 [-]: GETIMPORT R2 3; var2 = 0xCBD666E1
      10 [-]: LOADN R3 1   ; var3 = 1
      11 [-]: CALL R2 2 1  ; var2(var3)
      12 [-]: GETUPVAL R2 2; var2 = upvalues[2]
      13 [-]: GETUPVAL R5 3; var5 = upvalues[3]
      14 [-]: GETTABLEKS R4 R5 K4; var4 = var5["DEFEAT_MECH_GRIMOIRE"]
      15 [-]: NAMECALL R2 R2 K5; var3 = var2; var2 = var2[0x8ABFF40E]
      16 [-]: CALL R2 3 1  ; var2(var3, var4)
      17 [-]: JUMP L1      ; goto L1
L 0:  18 [-]: GETUPVAL R2 4; var2 = upvalues[4]
      19 [-]: JUMPIFNOTEQ R1 R2 L1; goto L1 if var1 ~= var131644
      20 [-]: GETUPVAL R2 2; var2 = upvalues[2]
      21 [-]: GETUPVAL R5 3; var5 = upvalues[3]
      22 [-]: GETTABLEKS R4 R5 K6; var4 = var5["RESCUE_LOID_CIN"]
      23 [-]: NAMECALL R2 R2 K5; var3 = var2; var2 = var2[0x8ABFF40E]
      24 [-]: CALL R2 3 1  ; var2(var3, var4)
L 1:  25 [-]: NAMECALL R2 R0 K1; var3 = var0; var2 = var0[0xF4E253B6]
      26 [-]: CALL R2 2 1  ; var2(var3)
      27 [-]: RETURN R0 0  ; 


; Name:            
; Defined at line: 866
; #Upvalues:       1
; #Parameters:     1
; Is_vararg:       0
; Max Stack Size:  2

       0 [-]: GETUPVAL R1 0; var1 = upvalues[0]
       1 [-]: ADDK R1 R1 K0; var1 = var1 + 1
       2 [-]: SETUPVAL R1 0; upvalues[1] = var0
       3 [-]: RETURN R0 0  ; 


; Name:            
; Defined at line: 872
; #Upvalues:       3
; #Parameters:     1
; Is_vararg:       0
; Max Stack Size:  3

L 0:   0 [-]: FASTCALL1 64 R0 L1; 
       1 [-]: MOVE R2 R0   ; var2 = var0
       2 [-]: GETIMPORT R1 1; var1 = 0x7B998233
       3 [-]: CALL R1 2 2  ; var1 = var1(var2)
L 1:   4 [-]: JUMPIF R1 L3 ; goto L3 if var1
       5 [-]: GETUPVAL R1 0; var1 = upvalues[0]
       6 [-]: JUMPIFNOT R1 L3; goto L3 if not var1
       7 [-]: GETUPVAL R2 1; var2 = upvalues[1]
       8 [-]: GETTABLEKS R1 R2 K2; var1 = var2[0x958E23C4]
       9 [-]: CALL R1 1 2  ; var1 = var1()
      10 [-]: JUMPIFNOT R1 L2; goto L2 if not var1
      11 [-]: GETUPVAL R1 2; var1 = upvalues[2]
      12 [-]: CALL R1 1 1  ; var1()
L 2:  13 [-]: GETIMPORT R1 4; var1 = 0xCBD666E1
      14 [-]: LOADN R2 0   ; var2 = 0
      15 [-]: CALL R1 2 1  ; var1(var2)
      16 [-]: JUMPBACK L0  ; goto L0
L 3:  17 [-]: RETURN R0 0  ; 


; Name:            
; Defined at line: 881
; #Upvalues:       0
; #Parameters:     1
; Is_vararg:       0
; Max Stack Size:  9

L 0:   0 [-]: FASTCALL1 64 R0 L1; 
       1 [-]: MOVE R2 R0   ; var2 = var0
       2 [-]: GETIMPORT R1 1; var1 = 0x7B998233
       3 [-]: CALL R1 2 2  ; var1 = var1(var2)
L 1:   4 [-]: JUMPIF R1 L5 ; goto L5 if var1
       5 [-]: LOADK R3 K2  ; var3 = 0.10000000149011612
       6 [-]: NAMECALL R1 R0 K3; var2 = var0; var1 = var0[0x08376326]
       7 [-]: CALL R1 3 2  ; var1 = var1(var2, var3)
       8 [-]: JUMPIF R1 L4 ; goto L4 if var1
       9 [-]: GETIMPORT R1 5; var1 = 0x89326C93
      10 [-]: GETIMPORT R3 7; var3 = 0x0469F296
      11 [-]: LOADK R4 K8  ; var4 = "TwinSwirlDeco"
      12 [-]: CALL R3 2 2  ; var3 = var3(var4)
      13 [-]: NAMECALL R4 R0 K9; var5 = var0; var4 = var0[0xD1586535]
      14 [-]: CALL R4 2 2  ; var4 = var4(var5)
      15 [-]: LOADN R5 0   ; var5 = 0
      16 [-]: LOADN R6 5   ; var6 = 5
      17 [-]: NAMECALL R1 R1 K10; var2 = var1; var1 = var1[0xF16592C8]
      18 [-]: CALL R1 6 2  ; var1 = var1(var2, var3, var4, var5, var6)
      19 [-]: GETIMPORT R2 12; var2 = 0xC8802016
      20 [-]: MOVE R3 R1   ; var3 = var1
      21 [-]: CALL R2 2 4  ; var2, var3, var4 = var2(var3)
      22 [-]: FORGPREP_INEXT R2 L3; 
L 2:  23 [-]: NAMECALL R7 R6 K13; var8 = var6; var7 = var6[0x1DB57C6B]
      24 [-]: CALL R7 2 1  ; var7(var8)
L 3:  25 [-]: FORGLOOP R2 L2 2 [inext]; 
      26 [-]: NAMECALL R2 R0 K14; var3 = var0; var2 = var0[0xA2880940]
      27 [-]: CALL R2 2 1  ; var2(var3)
L 4:  28 [-]: GETIMPORT R1 16; var1 = 0xCBD666E1
      29 [-]: LOADN R2 0   ; var2 = 0
      30 [-]: CALL R1 2 1  ; var1(var2)
      31 [-]: JUMPBACK L0  ; goto L0
L 5:  32 [-]: RETURN R0 0  ; 


; Name:            
; Defined at line: 894
; #Upvalues:       3
; #Parameters:     1
; Is_vararg:       0
; Max Stack Size:  9

       0 [-]: GETUPVAL R2 0; var2 = upvalues[0]
       1 [-]: GETTABLEKS R1 R2 K0; var1 = var2[0x9742B85B]
       2 [-]: GETUPVAL R2 1; var2 = upvalues[1]
       3 [-]: GETIMPORT R3 2; var3 = 0x0469F296
       4 [-]: LOADK R4 K3  ; var4 = "MITWIncantation"
       5 [-]: CALL R3 2 2  ; var3 = var3(var4)
       6 [-]: LOADB R4 0   ; var4 = false
       7 [-]: LOADB R5 1   ; var5 = true
       8 [-]: CALL R1 5 1  ; var1(var2, var3, var4, var5)
       9 [-]: GETIMPORT R1 5; var1 = 0x89326C93
      10 [-]: GETIMPORT R3 2; var3 = 0x0469F296
      11 [-]: LOADK R4 K6  ; var4 = "MITWRevealForwarder"
      12 [-]: CALL R3 2 0  ; var3, ... = var3(var4)
      13 [-]: NAMECALL R1 R1 K7; var2 = var1; var1 = var1[0x46A0EBF5]
      14 [-]: CALL R1 0 2  ; var1 = var1(var2, ...)
      15 [-]: LOADK R4 K8  ; var4 = "TriggerPort"
      16 [-]: NAMECALL R2 R1 K9; var3 = var1; var2 = var1[0x8EB2112D]
      17 [-]: CALL R2 3 1  ; var2(var3, var4)
      18 [-]: GETUPVAL R2 2; var2 = upvalues[2]
      19 [-]: GETIMPORT R4 2; var4 = 0x0469F296
      20 [-]: LOADK R5 K10 ; var5 = "VanishWhenNotVisible"
      21 [-]: CALL R4 2 2  ; var4 = var4(var5)
      22 [-]: LOADB R5 0   ; var5 = false
      23 [-]: NAMECALL R2 R2 K11; var3 = var2; var2 = var2[0xD5F7912B]
      24 [-]: CALL R2 4 1  ; var2(var3, var4, var5)
      25 [-]: GETIMPORT R2 5; var2 = 0x89326C93
      26 [-]: GETIMPORT R4 2; var4 = 0x0469F296
      27 [-]: LOADK R5 K12 ; var5 = "QuestSpawnRats"
      28 [-]: CALL R4 2 0  ; var4, ... = var4(var5)
      29 [-]: NAMECALL R2 R2 K7; var3 = var2; var2 = var2[0x46A0EBF5]
      30 [-]: CALL R2 0 2  ; var2 = var2(var3, ...)
      31 [-]: LOADK R5 K8  ; var5 = "TriggerPort"
      32 [-]: NAMECALL R3 R2 K9; var4 = var2; var3 = var2[0x8EB2112D]
      33 [-]: CALL R3 3 1  ; var3(var4, var5)
      34 [-]: GETIMPORT R3 5; var3 = 0x89326C93
      35 [-]: GETIMPORT R5 2; var5 = 0x0469F296
      36 [-]: LOADK R6 K13 ; var6 = "EntratiMusicSequencer"
      37 [-]: CALL R5 2 0  ; var5, ... = var5(var6)
      38 [-]: NAMECALL R3 R3 K7; var4 = var3; var3 = var3[0x46A0EBF5]
      39 [-]: CALL R3 0 2  ; var3 = var3(var4, ...)
      40 [-]: FASTCALL1 64 R3 L0; 
      41 [-]: MOVE R5 R3   ; var5 = var3
      42 [-]: GETIMPORT R4 15; var4 = 0x7B998233
      43 [-]: CALL R4 2 2  ; var4 = var4(var5)
L 0:  44 [-]: JUMPIF R4 L1 ; goto L1 if var4
      45 [-]: NAMECALL R4 R3 K16; var5 = var3; var4 = var3[0xF4E253B6]
      46 [-]: CALL R4 2 1  ; var4(var5)
L 1:  47 [-]: GETIMPORT R4 18; var4 = 0xCBD666E1
      48 [-]: GETIMPORT R5 20; var5 = 0x543804CB
      49 [-]: CALL R4 2 1  ; var4(var5)
      50 [-]: GETUPVAL R5 0; var5 = upvalues[0]
      51 [-]: GETTABLEKS R4 R5 K0; var4 = var5[0x9742B85B]
      52 [-]: GETUPVAL R5 1; var5 = upvalues[1]
      53 [-]: GETIMPORT R6 2; var6 = 0x0469F296
      54 [-]: LOADK R7 K21 ; var7 = "DEnterTheLabs0150"
      55 [-]: CALL R6 2 2  ; var6 = var6(var7)
      56 [-]: LOADB R7 0   ; var7 = false
      57 [-]: LOADB R8 0   ; var8 = false
      58 [-]: CALL R4 5 1  ; var4(var5, var6, var7, var8)
      59 [-]: RETURN R0 0  ; 


; Name:            
; Defined at line: 913
; #Upvalues:       1
; #Parameters:     1
; Is_vararg:       0
; Max Stack Size:  7

       0 [-]: GETIMPORT R1 1; var1 = 0x89326C93
       1 [-]: GETIMPORT R3 3; var3 = 0x58FC6003
       2 [-]: NAMECALL R4 R0 K4; var5 = var0; var4 = var0[0xD1586535]
       3 [-]: CALL R4 2 2  ; var4 = var4(var5)
       4 [-]: NAMECALL R5 R0 K5; var6 = var0; var5 = var0[0xCB3851B8]
       5 [-]: CALL R5 2 0  ; var5, ... = var5(var6)
       6 [-]: NAMECALL R1 R1 K6; var2 = var1; var1 = var1[0x05909209]
       7 [-]: CALL R1 0 2  ; var1 = var1(var2, ...)
       8 [-]: LOADB R4 0   ; var4 = false
       9 [-]: NAMECALL R2 R1 K7; var3 = var1; var2 = var1[0x8BAD1FDF]
      10 [-]: CALL R2 3 1  ; var2(var3, var4)
      11 [-]: GETUPVAL R3 0; var3 = upvalues[0]
      12 [-]: GETTABLEKS R2 R3 K8; var2 = var3[0xDA64D40E]
      13 [-]: LOADB R3 1   ; var3 = true
      14 [-]: LOADB R4 1   ; var4 = true
      15 [-]: LOADB R5 1   ; var5 = true
      16 [-]: CALL R2 4 1  ; var2(var3, var4, var5)
      17 [-]: RETURN R0 0  ; 


; Name:            
; Defined at line: 920
; #Upvalues:       2
; #Parameters:     1
; Is_vararg:       0
; Max Stack Size:  11

       0 [-]: GETIMPORT R1 1; var1 = 0x89326C93
       1 [-]: GETUPVAL R3 1; var3 = upvalues[1]
       2 [-]: NAMECALL R1 R1 K2; var2 = var1; var1 = var1[0x46A0EBF5]
       3 [-]: CALL R1 3 2  ; var1 = var1(var2, var3)
       4 [-]: SETUPVAL R1 0; upvalues[1] = var0
       5 [-]: GETUPVAL R2 0; var2 = upvalues[0]
       6 [-]: FASTCALL1 64 R2 L0; 
       7 [-]: GETIMPORT R1 4; var1 = 0x7B998233
       8 [-]: CALL R1 2 2  ; var1 = var1(var2)
L 0:   9 [-]: JUMPIFNOT R1 L1; goto L1 if not var1
      10 [-]: RETURN R0 0  ; 
L 1:  11 [-]: GETUPVAL R1 0; var1 = upvalues[0]
      12 [-]: GETIMPORT R3 6; var3 = gSkeletalClothExType
      13 [-]: NAMECALL R1 R1 K7; var2 = var1; var1 = var1[0xC1595BD5]
      14 [-]: CALL R1 3 2  ; var1 = var1(var2, var3)
      15 [-]: GETIMPORT R2 9; var2 = 0xC8802016
      16 [-]: MOVE R3 R1   ; var3 = var1
      17 [-]: CALL R2 2 4  ; var2, var3, var4 = var2(var3)
      18 [-]: FORGPREP_INEXT R2 L3; 
L 2:  19 [-]: LOADB R9 1   ; var9 = true
      20 [-]: LOADB R10 1  ; var10 = true
      21 [-]: NAMECALL R7 R6 K10; var8 = var6; var7 = var6[0x768274D6]
      22 [-]: CALL R7 4 1  ; var7(var8, var9, var10)
L 3:  23 [-]: FORGLOOP R2 L2 2 [inext]; 
      24 [-]: RETURN R0 0  ; 


; Name:            
; Defined at line: 931
; #Upvalues:       2
; #Parameters:     1
; Is_vararg:       0
; Max Stack Size:  12

       0 [-]: GETIMPORT R1 1; var1 = 0xCBD666E1
       1 [-]: LOADN R2 0   ; var2 = 0
       2 [-]: CALL R1 2 1  ; var1(var2)
       3 [-]: NEWTABLE R1 0 0; var1 = {}
L 0:   4 [-]: NAMECALL R2 R0 K2; var3 = var0; var2 = var0[0xF37943FF]
       5 [-]: CALL R2 2 2  ; var2 = var2(var3)
       6 [-]: JUMPIFNOT R2 L5; goto L5 if not var2
       7 [-]: GETIMPORT R2 4; var2 = 0x89326C93
       8 [-]: GETIMPORT R4 6; var4 = gTennoAvatarType
       9 [-]: NAMECALL R2 R2 K7; var3 = var2; var2 = var2[0xFB669000]
      10 [-]: CALL R2 3 2  ; var2 = var2(var3, var4)
      11 [-]: GETIMPORT R3 9; var3 = 0xCFC01047
      12 [-]: MOVE R4 R2   ; var4 = var2
      13 [-]: CALL R3 2 4  ; var3, var4, var5 = var3(var4)
      14 [-]: FORGPREP_NEXT R3 L4; 
L 1:  15 [-]: MOVE R10 R7  ; var10 = var7
      16 [-]: NAMECALL R8 R0 K10; var9 = var0; var8 = var0[0x13D5D3FB]
      17 [-]: CALL R8 3 2  ; var8 = var8(var9, var10)
      18 [-]: JUMPIFNOT R8 L2; goto L2 if not var8
      19 [-]: NAMECALL R9 R7 K11; var10 = var7; var9 = var7[0xE223E2B1]
      20 [-]: CALL R9 2 2  ; var9 = var9(var10)
      21 [-]: GETTABLE R8 R1 R9; var8 = var1[var9]
      22 [-]: JUMPIF R8 L2 ; goto L2 if var8
      23 [-]: GETUPVAL R9 0; var9 = upvalues[0]
      24 [-]: GETTABLEKS R8 R9 K12; var8 = var9[0xA1D0E6E1]
      25 [-]: MOVE R9 R7   ; var9 = var7
      26 [-]: LOADB R10 1  ; var10 = true
      27 [-]: CALL R8 3 1  ; var8(var9, var10)
      28 [-]: GETUPVAL R9 1; var9 = upvalues[1]
      29 [-]: GETTABLEKS R8 R9 K13; var8 = var9[0x1BF26251]
      30 [-]: LOADB R9 0   ; var9 = false
      31 [-]: MOVE R10 R7  ; var10 = var7
      32 [-]: CALL R8 3 1  ; var8(var9, var10)
      33 [-]: GETUPVAL R9 1; var9 = upvalues[1]
      34 [-]: GETTABLEKS R8 R9 K14; var8 = var9[0xBDD9801D]
      35 [-]: LOADB R9 0   ; var9 = false
      36 [-]: MOVE R10 R7  ; var10 = var7
      37 [-]: CALL R8 3 1  ; var8(var9, var10)
      38 [-]: NAMECALL R8 R7 K15; var9 = var7; var8 = var7[0x020D4331]
      39 [-]: CALL R8 2 2  ; var8 = var8(var9)
      40 [-]: LOADK R10 K16; var10 = 0.5
      41 [-]: NAMECALL R8 R8 K17; var9 = var8; var8 = var8[0x771F7C7A]
      42 [-]: CALL R8 3 1  ; var8(var9, var10)
      43 [-]: NAMECALL R8 R7 K11; var9 = var7; var8 = var7[0xE223E2B1]
      44 [-]: CALL R8 2 2  ; var8 = var8(var9)
      45 [-]: LOADB R9 1   ; var9 = true
      46 [-]: SETTABLE R9 R1 R8; var9[var1] = var8
      47 [-]: JUMP L4      ; goto L4
L 2:  48 [-]: MOVE R10 R7  ; var10 = var7
      49 [-]: NAMECALL R8 R0 K10; var9 = var0; var8 = var0[0x13D5D3FB]
      50 [-]: CALL R8 3 2  ; var8 = var8(var9, var10)
      51 [-]: JUMPIF R8 L4 ; goto L4 if var8
      52 [-]: NAMECALL R10 R7 K11; var11 = var7; var10 = var7[0xE223E2B1]
      53 [-]: CALL R10 2 2 ; var10 = var10(var11)
      54 [-]: GETTABLE R9 R1 R10; var9 = var1[var10]
      55 [-]: FASTCALL1 64 R9 L3; 
      56 [-]: GETIMPORT R8 19; var8 = 0x7B998233
      57 [-]: CALL R8 2 2  ; var8 = var8(var9)
L 3:  58 [-]: JUMPIF R8 L4 ; goto L4 if var8
      59 [-]: NAMECALL R9 R7 K11; var10 = var7; var9 = var7[0xE223E2B1]
      60 [-]: CALL R9 2 2  ; var9 = var9(var10)
      61 [-]: GETTABLE R8 R1 R9; var8 = var1[var9]
      62 [-]: JUMPXEQKB R8 1 L4 NOT; 
      63 [-]: GETUPVAL R9 0; var9 = upvalues[0]
      64 [-]: GETTABLEKS R8 R9 K12; var8 = var9[0xA1D0E6E1]
      65 [-]: MOVE R9 R7   ; var9 = var7
      66 [-]: LOADB R10 0  ; var10 = false
      67 [-]: CALL R8 3 1  ; var8(var9, var10)
      68 [-]: GETUPVAL R9 1; var9 = upvalues[1]
      69 [-]: GETTABLEKS R8 R9 K13; var8 = var9[0x1BF26251]
      70 [-]: LOADB R9 1   ; var9 = true
      71 [-]: MOVE R10 R7  ; var10 = var7
      72 [-]: CALL R8 3 1  ; var8(var9, var10)
      73 [-]: GETUPVAL R9 1; var9 = upvalues[1]
      74 [-]: GETTABLEKS R8 R9 K14; var8 = var9[0xBDD9801D]
      75 [-]: LOADB R9 1   ; var9 = true
      76 [-]: MOVE R10 R7  ; var10 = var7
      77 [-]: CALL R8 3 1  ; var8(var9, var10)
      78 [-]: NAMECALL R8 R7 K15; var9 = var7; var8 = var7[0x020D4331]
      79 [-]: CALL R8 2 2  ; var8 = var8(var9)
      80 [-]: LOADN R10 1  ; var10 = 1
      81 [-]: NAMECALL R8 R8 K17; var9 = var8; var8 = var8[0x771F7C7A]
      82 [-]: CALL R8 3 1  ; var8(var9, var10)
      83 [-]: NAMECALL R8 R7 K11; var9 = var7; var8 = var7[0xE223E2B1]
      84 [-]: CALL R8 2 2  ; var8 = var8(var9)
      85 [-]: LOADB R9 0   ; var9 = false
      86 [-]: SETTABLE R9 R1 R8; var9[var1] = var8
L 4:  87 [-]: FORGLOOP R3 L1 2; 
      88 [-]: GETIMPORT R3 1; var3 = 0xCBD666E1
      89 [-]: LOADN R4 0   ; var4 = 0
      90 [-]: CALL R3 2 1  ; var3(var4)
      91 [-]: JUMPBACK L0  ; goto L0
L 5:  92 [-]: GETIMPORT R2 4; var2 = 0x89326C93
      93 [-]: GETIMPORT R4 6; var4 = gTennoAvatarType
      94 [-]: NAMECALL R2 R2 K7; var3 = var2; var2 = var2[0xFB669000]
      95 [-]: CALL R2 3 2  ; var2 = var2(var3, var4)
      96 [-]: GETIMPORT R3 9; var3 = 0xCFC01047
      97 [-]: MOVE R4 R2   ; var4 = var2
      98 [-]: CALL R3 2 4  ; var3, var4, var5 = var3(var4)
      99 [-]: FORGPREP_NEXT R3 L7; 
L 6: 100 [-]: GETUPVAL R9 0; var9 = upvalues[0]
     101 [-]: GETTABLEKS R8 R9 K12; var8 = var9[0xA1D0E6E1]
     102 [-]: MOVE R9 R7   ; var9 = var7
     103 [-]: LOADB R10 0  ; var10 = false
     104 [-]: CALL R8 3 1  ; var8(var9, var10)
     105 [-]: GETUPVAL R9 1; var9 = upvalues[1]
     106 [-]: GETTABLEKS R8 R9 K13; var8 = var9[0x1BF26251]
     107 [-]: LOADB R9 1   ; var9 = true
     108 [-]: MOVE R10 R7  ; var10 = var7
     109 [-]: CALL R8 3 1  ; var8(var9, var10)
     110 [-]: GETUPVAL R9 1; var9 = upvalues[1]
     111 [-]: GETTABLEKS R8 R9 K14; var8 = var9[0xBDD9801D]
     112 [-]: LOADB R9 1   ; var9 = true
     113 [-]: CALL R8 2 1  ; var8(var9)
     114 [-]: NAMECALL R8 R7 K15; var9 = var7; var8 = var7[0x020D4331]
     115 [-]: CALL R8 2 2  ; var8 = var8(var9)
     116 [-]: LOADN R10 1  ; var10 = 1
     117 [-]: NAMECALL R8 R8 K17; var9 = var8; var8 = var8[0x771F7C7A]
     118 [-]: CALL R8 3 1  ; var8(var9, var10)
L 7: 119 [-]: FORGLOOP R3 L6 2; 
     120 [-]: RETURN R0 0  ; 



