; Name:            
; Defined at line: 1
; #Upvalues:       0
; #Parameters:     0
; Is_vararg:       1
; Max Stack Size:  114

       1 [-]: NEWTABLE R0 0 4; var0 = {}
       2 [-]: LOADN R1 1   ; var1 = 1
       3 [-]: LOADK R2 K0  ; var2 = 1.1499999761581421
       4 [-]: LOADK R3 K1  ; var3 = 1.2999999523162842
       5 [-]: LOADK R4 K2  ; var4 = 1.3999999761581421
       6 [-]: SETLIST R0 R1 4 [1]; var0[1] = var1; var0[2] = var2; var0[3] = var3; var0[4] = var4; var0[5] = var5; 
       7 [-]: NEWTABLE R1 0 4; var1 = {}
       8 [-]: LOADN R2 3   ; var2 = 3
       9 [-]: LOADN R3 4   ; var3 = 4
      10 [-]: LOADN R4 7   ; var4 = 7
      11 [-]: LOADN R5 8   ; var5 = 8
      12 [-]: SETLIST R1 R2 4 [1]; var1[1] = var2; var1[2] = var3; var1[3] = var4; var1[4] = var5; var1[5] = var6; 
      13 [-]: NEWTABLE R2 0 4; var2 = {}
      14 [-]: LOADN R3 9   ; var3 = 9
      15 [-]: LOADN R4 12  ; var4 = 12
      16 [-]: LOADN R5 14  ; var5 = 14
      17 [-]: LOADN R6 14  ; var6 = 14
      18 [-]: SETLIST R2 R3 4 [1]; var2[1] = var3; var2[2] = var4; var2[3] = var5; var2[4] = var6; var2[5] = var7; 
      19 [-]: NEWTABLE R3 0 4; var3 = {}
      20 [-]: LOADN R4 3   ; var4 = 3
      21 [-]: LOADN R5 4   ; var5 = 4
      22 [-]: LOADN R6 5   ; var6 = 5
      23 [-]: LOADN R7 6   ; var7 = 6
      24 [-]: SETLIST R3 R4 4 [1]; var3[1] = var4; var3[2] = var5; var3[3] = var6; var3[4] = var7; var3[5] = var8; 
      25 [-]: NEWTABLE R4 0 4; var4 = {}
      26 [-]: LOADN R5 1   ; var5 = 1
      27 [-]: LOADN R6 2   ; var6 = 2
      28 [-]: LOADN R7 2   ; var7 = 2
      29 [-]: LOADN R8 3   ; var8 = 3
      30 [-]: SETLIST R4 R5 4 [1]; var4[1] = var5; var4[2] = var6; var4[3] = var7; var4[4] = var8; var4[5] = var9; 
      31 [-]: NEWTABLE R5 0 4; var5 = {}
      32 [-]: LOADN R6 40  ; var6 = 40
      33 [-]: LOADN R7 40  ; var7 = 40
      34 [-]: LOADN R8 60  ; var8 = 60
      35 [-]: LOADN R9 60  ; var9 = 60
      36 [-]: SETLIST R5 R6 4 [1]; var5[1] = var6; var5[2] = var7; var5[3] = var8; var5[4] = var9; var5[5] = var10; 
      37 [-]: GETIMPORT R6 4; var6 = 0x2D0FAD09
      38 [-]: LOADK R7 K5  ; var7 = "EE.Interface.Utilities"
      39 [-]: CALL R6 2 2  ; var6 = var6(var7)
      40 [-]: GETIMPORT R7 4; var7 = 0x2D0FAD09
      41 [-]: LOADK R8 K6  ; var8 = "Lotus.Interface.LotusUtilities"
      42 [-]: CALL R7 2 2  ; var7 = var7(var8)
      43 [-]: GETIMPORT R8 4; var8 = 0x2D0FAD09
      44 [-]: LOADK R9 K7  ; var9 = "Lotus.Scripts.Libs.LandscapeLib"
      45 [-]: CALL R8 2 2  ; var8 = var8(var9)
      46 [-]: GETIMPORT R9 4; var9 = 0x2D0FAD09
      47 [-]: LOADK R10 K8 ; var10 = "Lotus.Scripts.Libs.TransmissionSet"
      48 [-]: CALL R9 2 2  ; var9 = var9(var10)
      49 [-]: GETIMPORT R10 4; var10 = 0x2D0FAD09
      50 [-]: LOADK R11 K9 ; var11 = "Lotus.Interface.Libs.TimerMgr"
      51 [-]: CALL R10 2 2 ; var10 = var10(var11)
      52 [-]: GETIMPORT R11 4; var11 = 0x2D0FAD09
      53 [-]: LOADK R12 K10; var12 = "Lotus.Scripts.Libs.ObjectiveText"
      54 [-]: CALL R11 2 2 ; var11 = var11(var12)
      55 [-]: GETIMPORT R12 4; var12 = 0x2D0FAD09
      56 [-]: LOADK R13 K11; var13 = "Lotus.Scripts.Libs.CommonGamemodeFunctions"
      57 [-]: CALL R12 2 2 ; var12 = var12(var13)
      58 [-]: GETIMPORT R13 13; var13 = 0x7ED0A956
      59 [-]: LOADK R14 K14; var14 = "/Lotus/Types/PickUps/ExcavatorCellItem"
      60 [-]: CALL R13 2 2 ; var13 = var13(var14)
      61 [-]: GETIMPORT R14 16; var14 = 0x88EFC25E
      62 [-]: LOADK R15 K17; var15 = "/Lotus/Types/PickUps/ExcavatorCellPickup"
      63 [-]: CALL R14 2 2 ; var14 = var14(var15)
      64 [-]: NEWTABLE R15 0 5; var15 = {}
      65 [-]: GETIMPORT R16 16; var16 = 0x88EFC25E
      66 [-]: LOADK R17 K18; var17 = "/Lotus/Types/Game/MarkerInfos/VenusObjectiveAMarkerInfo"
      67 [-]: CALL R16 2 2 ; var16 = var16(var17)
      68 [-]: GETIMPORT R17 16; var17 = 0x88EFC25E
      69 [-]: LOADK R18 K19; var18 = "/Lotus/Types/Game/MarkerInfos/VenusObjectiveBMarkerInfo"
      70 [-]: CALL R17 2 2 ; var17 = var17(var18)
      71 [-]: GETIMPORT R18 16; var18 = 0x88EFC25E
      72 [-]: LOADK R19 K20; var19 = "/Lotus/Types/Game/MarkerInfos/VenusObjectiveCMarkerInfo"
      73 [-]: CALL R18 2 2 ; var18 = var18(var19)
      74 [-]: GETIMPORT R19 16; var19 = 0x88EFC25E
      75 [-]: LOADK R20 K21; var20 = "/Lotus/Types/Game/MarkerInfos/VenusObjectiveDMarkerInfo"
      76 [-]: CALL R19 2 2 ; var19 = var19(var20)
      77 [-]: GETIMPORT R20 16; var20 = 0x88EFC25E
      78 [-]: LOADK R21 K22; var21 = "/Lotus/Types/Game/MarkerInfos/VenusObjectiveEMarkerInfo"
      79 [-]: CALL R20 2 0 ; var20, ... = var20(var21)
      80 [-]: SETLIST R15 R16 -1 [1]; 
      81 [-]: GETIMPORT R16 13; var16 = 0x7ED0A956
      82 [-]: LOADK R17 K23; var17 = "/Lotus/Types/Enemies/Infested/InfestedMicroplanet/CellCarrierDroneMicroPlanet"
      83 [-]: CALL R16 2 2 ; var16 = var16(var17)
      84 [-]: GETIMPORT R17 25; var17 = 0x0469F296
      85 [-]: LOADK R18 K26; var18 = "ExcavatorSpawnPoint"
      86 [-]: CALL R17 2 2 ; var17 = var17(var18)
      87 [-]: GETIMPORT R18 25; var18 = 0x0469F296
      88 [-]: LOADK R19 K27; var19 = "DynamicExcavatorAvatar"
      89 [-]: CALL R18 2 2 ; var18 = var18(var19)
      90 [-]: GETIMPORT R19 25; var19 = 0x0469F296
      91 [-]: LOADK R20 K28; var20 = "LeavingCB"
      92 [-]: CALL R19 2 2 ; var19 = var19(var20)
      93 [-]: GETIMPORT R20 25; var20 = 0x0469F296
      94 [-]: LOADK R21 K29; var21 = "ReturningCB"
      95 [-]: CALL R20 2 2 ; var20 = var20(var21)
      96 [-]: DUPTABLE R21 36; 
      97 [-]: LOADK R22 K37; var22 = "/Lotus/Language/Game/ExcavatorObject"
      98 [-]: SETTABLEKS R22 R21 K30; var22["EXCAVATOR_OBJECT"] = var21
      99 [-]: LOADK R22 K38; var22 = "/Lotus/Language/Objectives/ExcavDigsComplete"
     100 [-]: SETTABLEKS R22 R21 K31; var22["EXCAVATION_PROGRESS"] = var21
     101 [-]: LOADK R22 K39; var22 = "/Lotus/Language/Game/ExcavationLocateAndProtect"
     102 [-]: SETTABLEKS R22 R21 K32; var22["EXCAVATION_OBJECTIVE"] = var21
     103 [-]: LOADK R22 K40; var22 = "/Lotus/Language/SolarisJobs/DynamicExcavationBonusObj"
     104 [-]: SETTABLEKS R22 R21 K33; var22["BONUS_OBJECTIVE"] = var21
     105 [-]: LOADK R22 K41; var22 = "/Lotus/Language/Objectives/ExcavPowerFull"
     106 [-]: SETTABLEKS R22 R21 K34; var22["FULL"] = var21
     107 [-]: LOADK R22 K42; var22 = "<PROBLEM>"
     108 [-]: SETTABLEKS R22 R21 K35; var22["HALTED"] = var21
     109 [-]: GETIMPORT R22 25; var22 = 0x0469F296
     110 [-]: LOADK R24 K43; var24 = "DynExcav"
     111 [-]: LOADK R25 K44; var25 = "_NumDrop"
     112 [-]: CONCAT R23 R24 R25; var23 = var24 .. var25
     113 [-]: CALL R22 2 2 ; var22 = var22(var23)
     114 [-]: GETIMPORT R23 25; var23 = 0x0469F296
     115 [-]: LOADK R25 K43; var25 = "DynExcav"
     116 [-]: LOADK R26 K45; var26 = "_NumComp"
     117 [-]: CONCAT R24 R25 R26; var24 = var25 .. var26
     118 [-]: CALL R23 2 2 ; var23 = var23(var24)
     119 [-]: GETIMPORT R24 25; var24 = 0x0469F296
     120 [-]: LOADK R26 K43; var26 = "DynExcav"
     121 [-]: LOADK R27 K46; var27 = "_NumFail"
     122 [-]: CONCAT R25 R26 R27; var25 = var26 .. var27
     123 [-]: CALL R24 2 2 ; var24 = var24(var25)
     124 [-]: GETIMPORT R25 25; var25 = 0x0469F296
     125 [-]: LOADK R27 K43; var27 = "DynExcav"
     126 [-]: LOADK R28 K47; var28 = "_PlayedUnpow"
     127 [-]: CONCAT R26 R27 R28; var26 = var27 .. var28
     128 [-]: CALL R25 2 2 ; var25 = var25(var26)
     129 [-]: GETIMPORT R26 25; var26 = 0x0469F296
     130 [-]: LOADK R28 K43; var28 = "DynExcav"
     131 [-]: LOADK R29 K48; var29 = "_PlayedPow"
     132 [-]: CONCAT R27 R28 R29; var27 = var28 .. var29
     133 [-]: CALL R26 2 2 ; var26 = var26(var27)
     134 [-]: GETIMPORT R27 25; var27 = 0x0469F296
     135 [-]: LOADK R29 K43; var29 = "DynExcav"
     136 [-]: LOADK R30 K49; var30 = "_PlayedLowHP"
     137 [-]: CONCAT R28 R29 R30; var28 = var29 .. var30
     138 [-]: CALL R27 2 2 ; var27 = var27(var28)
     139 [-]: LOADK R29 K43; var29 = "DynExcav"
     140 [-]: LOADK R30 K50; var30 = "_POWER"
     141 [-]: CONCAT R28 R29 R30; var28 = var29 .. var30
     142 [-]: LOADK R30 K43; var30 = "DynExcav"
     143 [-]: LOADK R31 K51; var31 = "_TIMER"
     144 [-]: CONCAT R29 R30 R31; var29 = var30 .. var31
     145 [-]: LOADK R31 K43; var31 = "DynExcav"
     146 [-]: LOADK R32 K52; var32 = "_STATUS"
     147 [-]: CONCAT R30 R31 R32; var30 = var31 .. var32
     148 [-]: LOADNIL R31  ; var31 = nil
     149 [-]: LOADNIL R32  ; var32 = nil
     150 [-]: LOADNIL R33  ; var33 = nil
     151 [-]: LOADNIL R34  ; var34 = nil
     152 [-]: LOADNIL R35  ; var35 = nil
     153 [-]: LOADNIL R36  ; var36 = nil
     154 [-]: LOADNIL R37  ; var37 = nil
     155 [-]: LOADNIL R38  ; var38 = nil
     156 [-]: LOADNIL R39  ; var39 = nil
     157 [-]: NEWTABLE R40 0 0; var40 = {}
     158 [-]: NEWTABLE R41 0 0; var41 = {}
     159 [-]: NEWTABLE R42 0 0; var42 = {}
     160 [-]: NEWTABLE R43 0 0; var43 = {}
     161 [-]: NEWTABLE R44 0 0; var44 = {}
     162 [-]: NEWTABLE R45 0 0; var45 = {}
     163 [-]: NEWTABLE R46 0 0; var46 = {}
     164 [-]: LOADB R47 1  ; var47 = true
     165 [-]: LOADN R48 0  ; var48 = 0
     166 [-]: LOADNIL R49  ; var49 = nil
     167 [-]: LOADN R50 60 ; var50 = 60
     168 [-]: NEWTABLE R51 0 0; var51 = {}
     169 [-]: DUPTABLE R52 61; 
     170 [-]: LOADN R53 0  ; var53 = 0
     171 [-]: SETTABLEKS R53 R52 K53; var53["NONE"] = var52
     172 [-]: LOADN R53 1  ; var53 = 1
     173 [-]: SETTABLEKS R53 R52 K54; var53["COMPLETED"] = var52
     174 [-]: LOADN R53 2  ; var53 = 2
     175 [-]: SETTABLEKS R53 R52 K55; var53["DESTROYED"] = var52
     176 [-]: LOADN R53 3  ; var53 = 3
     177 [-]: SETTABLEKS R53 R52 K56; var53["A"] = var52
     178 [-]: LOADN R53 4  ; var53 = 4
     179 [-]: SETTABLEKS R53 R52 K57; var53["B"] = var52
     180 [-]: LOADN R53 5  ; var53 = 5
     181 [-]: SETTABLEKS R53 R52 K58; var53["C"] = var52
     182 [-]: LOADN R53 6  ; var53 = 6
     183 [-]: SETTABLEKS R53 R52 K59; var53["D"] = var52
     184 [-]: LOADN R53 7  ; var53 = 7
     185 [-]: SETTABLEKS R53 R52 K60; var53["E"] = var52
     186 [-]: DUPTABLE R53 65; 
     187 [-]: LOADN R54 1  ; var54 = 1
     188 [-]: SETTABLEKS R54 R53 K62; var54["START"] = var53
     189 [-]: LOADN R54 101; var54 = 101
     190 [-]: SETTABLEKS R54 R53 K63; var54["EXCAVATION"] = var53
     191 [-]: LOADN R54 201; var54 = 201
     192 [-]: SETTABLEKS R54 R53 K64; var54["FINISH"] = var53
     193 [-]: LOADN R54 0  ; var54 = 0
     194 [-]: NEWTABLE R55 0 5; var55 = {}
     195 [-]: LOADK R56 K66; var56 = "<MISSION_MARKER_A>"
     196 [-]: LOADK R57 K67; var57 = "<MISSION_MARKER_B>"
     197 [-]: LOADK R58 K68; var58 = "<MISSION_MARKER_C>"
     198 [-]: LOADK R59 K69; var59 = "<MISSION_MARKER_D>"
     199 [-]: LOADK R60 K70; var60 = "<MISSION_MARKER_E>"
     200 [-]: SETLIST R55 R56 5 [1]; var55[1] = var56; var55[2] = var57; var55[3] = var58; var55[4] = var59; var55[5] = var60; var55[6] = var61; 
     201 [-]: LOADK R57 K71; var57 = "<p><font color=\"#"
     202 [-]: GETIMPORT R70 74; var70 = 0x7F5022CF[0xE8072DED]
     203 [-]: LOADK R71 K75; var71 = "%X"
     204 [-]: GETIMPORT R73 77; var73 = 0x0032441C
     205 [-]: GETTABLEKS R72 R73 K78; var72 = var73["UIColor_White"]
     206 [-]: CALL R70 3 2 ; var70 = var70(var71, var72)
     207 [-]: MOVE R58 R70 ; var58 = var70
     208 [-]: LOADK R59 K79; var59 = "\"><br>      "
     209 [-]: LOADK R60 K80; var60 = "/Lotus/Language/Game/ExcavationTime"
     210 [-]: LOADK R61 K81; var61 = "</font><font color=\"#"
     211 [-]: GETIMPORT R70 74; var70 = 0x7F5022CF[0xE8072DED]
     212 [-]: LOADK R71 K75; var71 = "%X"
     213 [-]: GETIMPORT R73 77; var73 = 0x0032441C
     214 [-]: GETTABLEKS R72 R73 K78; var72 = var73["UIColor_White"]
     215 [-]: CALL R70 3 2 ; var70 = var70(var71, var72)
     216 [-]: MOVE R62 R70 ; var62 = var70
     217 [-]: LOADK R63 K82; var63 = "\"><b> %s</b></font>"
     218 [-]: LOADK R64 K83; var64 = "<font color=\"#"
     219 [-]: GETIMPORT R70 74; var70 = 0x7F5022CF[0xE8072DED]
     220 [-]: LOADK R71 K75; var71 = "%X"
     221 [-]: GETIMPORT R73 77; var73 = 0x0032441C
     222 [-]: GETTABLEKS R72 R73 K78; var72 = var73["UIColor_White"]
     223 [-]: CALL R70 3 2 ; var70 = var70(var71, var72)
     224 [-]: MOVE R65 R70 ; var65 = var70
     225 [-]: LOADK R66 K84; var66 = "\">  "
     226 [-]: LOADK R67 K85; var67 = "/Lotus/Language/Game/ExcavationPower"
     227 [-]: LOADK R68 K86; var68 = "</font>%s"
     228 [-]: LOADK R69 K87; var69 = "</p>"
     229 [-]: CONCAT R56 R57 R69; var56 = var57 .. var69
     230 [-]: LOADNIL R57  ; var57 = nil
     231 [-]: DUPCLOSURE R58 K88; 
     232 [-]: DUPCLOSURE R59 K89; 
     233 [-]: DUPCLOSURE R60 K90; 
     234 [-]: DUPCLOSURE R61 K91; 
     235 [-]: DUPCLOSURE R62 K92; 
     236 [-]: DUPCLOSURE R63 K93; 
     237 [-]: NEWCLOSURE R64 P6; 
     238 [-]: CAPTURE REF R42; 
     239 [-]: CAPTURE REF R43; 
     240 [-]: CAPTURE REF R44; 
     241 [-]: CAPTURE VAL R41; 
     242 [-]: CAPTURE VAL R22; 
     243 [-]: CAPTURE VAL R24; 
     244 [-]: CAPTURE VAL R23; 
     245 [-]: DUPCLOSURE R65 K94; 
     246 [-]: NEWCLOSURE R66 P8; 
     247 [-]: CAPTURE VAL R9; 
     248 [-]: CAPTURE REF R35; 
     249 [-]: DUPCLOSURE R67 K95; 
     250 [-]: CAPTURE VAL R11; 
     251 [-]: CAPTURE VAL R21; 
     252 [-]: NEWCLOSURE R68 P10; 
     253 [-]: CAPTURE VAL R24; 
     254 [-]: CAPTURE VAL R11; 
     255 [-]: CAPTURE VAL R21; 
     256 [-]: CAPTURE REF R32; 
     257 [-]: CAPTURE VAL R9; 
     258 [-]: CAPTURE REF R35; 
     259 [-]: NEWCLOSURE R69 P11; 
     260 [-]: CAPTURE REF R37; 
     261 [-]: CAPTURE REF R32; 
     262 [-]: NEWCLOSURE R70 P12; 
     263 [-]: CAPTURE REF R39; 
     264 [-]: CAPTURE REF R37; 
     265 [-]: CAPTURE REF R54; 
     266 [-]: CAPTURE VAL R70; 
     267 [-]: CAPTURE REF R38; 
     268 [-]: CAPTURE REF R40; 
     269 [-]: CAPTURE VAL R53; 
     270 [-]: CAPTURE REF R36; 
     271 [-]: DUPCLOSURE R71 K96; 
     272 [-]: CAPTURE VAL R6; 
     273 [-]: NEWCLOSURE R72 P14; 
     274 [-]: CAPTURE REF R57; 
     275 [-]: CAPTURE VAL R6; 
     276 [-]: CAPTURE VAL R21; 
     277 [-]: DUPCLOSURE R73 K97; 
     278 [-]: NEWCLOSURE R74 P16; 
     279 [-]: CAPTURE REF R42; 
     280 [-]: CAPTURE VAL R52; 
     281 [-]: NEWCLOSURE R75 P17; 
     282 [-]: CAPTURE REF R42; 
     283 [-]: CAPTURE VAL R52; 
     284 [-]: NEWCLOSURE R76 P18; 
     285 [-]: CAPTURE REF R45; 
     286 [-]: CAPTURE REF R42; 
     287 [-]: CAPTURE VAL R75; 
     288 [-]: CAPTURE VAL R41; 
     289 [-]: NEWCLOSURE R77 P19; 
     290 [-]: CAPTURE REF R42; 
     291 [-]: CAPTURE VAL R52; 
     292 [-]: CAPTURE VAL R41; 
     293 [-]: CAPTURE REF R43; 
     294 [-]: CAPTURE REF R44; 
     295 [-]: NEWCLOSURE R78 P20; 
     296 [-]: CAPTURE REF R42; 
     297 [-]: CAPTURE VAL R41; 
     298 [-]: NEWCLOSURE R79 P21; 
     299 [-]: CAPTURE REF R42; 
     300 [-]: CAPTURE VAL R52; 
     301 [-]: CAPTURE VAL R41; 
     302 [-]: NEWCLOSURE R80 P22; 
     303 [-]: CAPTURE REF R42; 
     304 [-]: CAPTURE VAL R52; 
     305 [-]: NEWCLOSURE R81 P23; 
     306 [-]: CAPTURE REF R42; 
     307 [-]: CAPTURE VAL R52; 
     308 [-]: CAPTURE VAL R41; 
     309 [-]: NEWCLOSURE R82 P24; 
     310 [-]: CAPTURE REF R42; 
     311 [-]: CAPTURE VAL R52; 
     312 [-]: NEWCLOSURE R83 P25; 
     313 [-]: CAPTURE REF R45; 
     314 [-]: NEWCLOSURE R84 P26; 
     315 [-]: CAPTURE REF R42; 
     316 [-]: CAPTURE VAL R52; 
     317 [-]: CAPTURE REF R51; 
     318 [-]: CAPTURE VAL R64; 
     319 [-]: NEWCLOSURE R85 P27; 
     320 [-]: CAPTURE REF R42; 
     321 [-]: CAPTURE VAL R52; 
     322 [-]: CAPTURE VAL R41; 
     323 [-]: CAPTURE REF R43; 
     324 [-]: CAPTURE REF R44; 
     325 [-]: CAPTURE VAL R7; 
     326 [-]: CAPTURE VAL R21; 
     327 [-]: CAPTURE VAL R55; 
     328 [-]: CAPTURE REF R51; 
     329 [-]: NEWCLOSURE R86 P28; 
     330 [-]: CAPTURE REF R37; 
     331 [-]: CAPTURE VAL R86; 
     332 [-]: NEWCLOSURE R87 P29; 
     333 [-]: CAPTURE VAL R15; 
     334 [-]: CAPTURE REF R42; 
     335 [-]: CAPTURE VAL R52; 
     336 [-]: NEWCLOSURE R88 P30; 
     337 [-]: CAPTURE REF R42; 
     338 [-]: CAPTURE VAL R52; 
     339 [-]: CAPTURE VAL R41; 
     340 [-]: CAPTURE REF R43; 
     341 [-]: CAPTURE REF R44; 
     342 [-]: CAPTURE VAL R73; 
     343 [-]: NEWCLOSURE R89 P31; 
     344 [-]: CAPTURE VAL R52; 
     345 [-]: CAPTURE VAL R22; 
     346 [-]: CAPTURE REF R42; 
     347 [-]: NEWCLOSURE R90 P32; 
     348 [-]: CAPTURE VAL R76; 
     349 [-]: CAPTURE VAL R5; 
     350 [-]: CAPTURE REF R45; 
     351 [-]: CAPTURE REF R31; 
     352 [-]: CAPTURE VAL R0; 
     353 [-]: CAPTURE VAL R41; 
     354 [-]: CAPTURE REF R42; 
     355 [-]: CAPTURE VAL R89; 
     356 [-]: CAPTURE REF R43; 
     357 [-]: CAPTURE REF R44; 
     358 [-]: CAPTURE VAL R88; 
     359 [-]: CAPTURE VAL R85; 
     360 [-]: CAPTURE VAL R86; 
     361 [-]: CAPTURE VAL R15; 
     362 [-]: CAPTURE VAL R52; 
     363 [-]: NEWCLOSURE R91 P33; 
     364 [-]: CAPTURE REF R48; 
     365 [-]: CAPTURE REF R37; 
     366 [-]: CAPTURE REF R49; 
     367 [-]: CAPTURE VAL R90; 
     368 [-]: NEWCLOSURE R92 P34; 
     369 [-]: CAPTURE REF R42; 
     370 [-]: CAPTURE VAL R52; 
     371 [-]: CAPTURE VAL R22; 
     372 [-]: CAPTURE REF R48; 
     373 [-]: CAPTURE REF R37; 
     374 [-]: CAPTURE REF R49; 
     375 [-]: CAPTURE VAL R91; 
     376 [-]: NEWCLOSURE R93 P35; 
     377 [-]: CAPTURE VAL R61; 
     378 [-]: CAPTURE VAL R30; 
     379 [-]: CAPTURE REF R42; 
     380 [-]: CAPTURE VAL R28; 
     381 [-]: CAPTURE REF R43; 
     382 [-]: CAPTURE VAL R29; 
     383 [-]: CAPTURE REF R44; 
     384 [-]: NEWCLOSURE R94 P36; 
     385 [-]: CAPTURE REF R34; 
     386 [-]: CAPTURE VAL R18; 
     387 [-]: NEWCLOSURE R95 P37; 
     388 [-]: CAPTURE VAL R41; 
     389 [-]: CAPTURE REF R43; 
     390 [-]: CAPTURE REF R44; 
     391 [-]: CAPTURE VAL R84; 
     392 [-]: CAPTURE VAL R94; 
     393 [-]: CAPTURE REF R42; 
     394 [-]: CAPTURE VAL R52; 
     395 [-]: CAPTURE VAL R23; 
     396 [-]: CAPTURE VAL R24; 
     397 [-]: CAPTURE VAL R11; 
     398 [-]: CAPTURE REF R54; 
     399 [-]: CAPTURE VAL R53; 
     400 [-]: CAPTURE VAL R70; 
     401 [-]: NEWCLOSURE R96 P38; 
     402 [-]: CAPTURE VAL R24; 
     403 [-]: CAPTURE VAL R11; 
     404 [-]: CAPTURE VAL R21; 
     405 [-]: CAPTURE VAL R95; 
     406 [-]: CAPTURE REF R42; 
     407 [-]: CAPTURE VAL R52; 
     408 [-]: CAPTURE REF R54; 
     409 [-]: CAPTURE VAL R53; 
     410 [-]: CAPTURE VAL R92; 
     411 [-]: CAPTURE VAL R9; 
     412 [-]: CAPTURE REF R35; 
     413 [-]: NEWCLOSURE R97 P39; 
     414 [-]: CAPTURE VAL R23; 
     415 [-]: CAPTURE VAL R95; 
     416 [-]: CAPTURE REF R42; 
     417 [-]: CAPTURE VAL R52; 
     418 [-]: CAPTURE REF R54; 
     419 [-]: CAPTURE VAL R53; 
     420 [-]: CAPTURE VAL R92; 
     421 [-]: CAPTURE VAL R9; 
     422 [-]: CAPTURE REF R35; 
     423 [-]: NEWCLOSURE R98 P40; 
     424 [-]: CAPTURE VAL R88; 
     425 [-]: CAPTURE VAL R26; 
     426 [-]: CAPTURE VAL R9; 
     427 [-]: CAPTURE REF R35; 
     428 [-]: CAPTURE VAL R25; 
     429 [-]: NEWCLOSURE R99 P41; 
     430 [-]: CAPTURE REF R42; 
     431 [-]: CAPTURE VAL R52; 
     432 [-]: CAPTURE VAL R41; 
     433 [-]: CAPTURE REF R43; 
     434 [-]: CAPTURE REF R44; 
     435 [-]: NEWCLOSURE R100 P42; 
     436 [-]: CAPTURE REF R42; 
     437 [-]: CAPTURE VAL R52; 
     438 [-]: CAPTURE REF R43; 
     439 [-]: CAPTURE VAL R41; 
     440 [-]: CAPTURE REF R44; 
     441 [-]: CAPTURE VAL R98; 
     442 [-]: NEWCLOSURE R101 P43; 
     443 [-]: CAPTURE REF R42; 
     444 [-]: CAPTURE VAL R52; 
     445 [-]: CAPTURE VAL R41; 
     446 [-]: CAPTURE REF R43; 
     447 [-]: CAPTURE REF R44; 
     448 [-]: CAPTURE REF R51; 
     449 [-]: CAPTURE VAL R64; 
     450 [-]: CAPTURE VAL R6; 
     451 [-]: CAPTURE VAL R72; 
     452 [-]: CAPTURE VAL R56; 
     453 [-]: CAPTURE VAL R12; 
     454 [-]: NEWCLOSURE R102 P44; 
     455 [-]: CAPTURE REF R47; 
     456 [-]: NEWCLOSURE R103 P45; 
     457 [-]: CAPTURE VAL R41; 
     458 [-]: CAPTURE REF R47; 
     459 [-]: CAPTURE VAL R46; 
     460 [-]: CAPTURE REF R37; 
     461 [-]: CAPTURE VAL R102; 
     462 [-]: CAPTURE VAL R9; 
     463 [-]: CAPTURE REF R35; 
     464 [-]: CAPTURE REF R43; 
     465 [-]: CAPTURE REF R44; 
     466 [-]: CAPTURE VAL R23; 
     467 [-]: CAPTURE VAL R95; 
     468 [-]: CAPTURE REF R42; 
     469 [-]: CAPTURE VAL R52; 
     470 [-]: CAPTURE REF R54; 
     471 [-]: CAPTURE VAL R53; 
     472 [-]: CAPTURE VAL R92; 
     473 [-]: CAPTURE VAL R98; 
     474 [-]: NEWCLOSURE R104 P46; 
     475 [-]: CAPTURE REF R42; 
     476 [-]: CAPTURE VAL R52; 
     477 [-]: CAPTURE VAL R103; 
     478 [-]: CAPTURE VAL R101; 
     479 [-]: NEWCLOSURE R105 P47; 
     480 [-]: CAPTURE REF R34; 
     481 [-]: CAPTURE VAL R16; 
     482 [-]: CAPTURE VAL R4; 
     483 [-]: NEWCLOSURE R106 P48; 
     484 [-]: CAPTURE REF R31; 
     485 [-]: CAPTURE VAL R79; 
     486 [-]: CAPTURE REF R34; 
     487 [-]: CAPTURE VAL R1; 
     488 [-]: CAPTURE VAL R3; 
     489 [-]: CAPTURE VAL R2; 
     490 [-]: CAPTURE VAL R105; 
     491 [-]: NEWCLOSURE R107 P49; 
     492 [-]: CAPTURE REF R45; 
     493 [-]: CAPTURE VAL R17; 
     494 [-]: CAPTURE REF R33; 
     495 [-]: CAPTURE REF R32; 
     496 [-]: CAPTURE REF R42; 
     497 [-]: CAPTURE VAL R60; 
     498 [-]: CAPTURE VAL R30; 
     499 [-]: CAPTURE REF R43; 
     500 [-]: CAPTURE VAL R28; 
     501 [-]: CAPTURE REF R44; 
     502 [-]: CAPTURE VAL R29; 
     503 [-]: CAPTURE VAL R18; 
     504 [-]: CAPTURE VAL R41; 
     505 [-]: CAPTURE VAL R15; 
     506 [-]: CAPTURE VAL R52; 
     507 [-]: CAPTURE VAL R75; 
     508 [-]: CAPTURE VAL R22; 
     509 [-]: CAPTURE VAL R24; 
     510 [-]: CAPTURE VAL R23; 
     511 [-]: CAPTURE VAL R64; 
     512 [-]: CAPTURE VAL R90; 
     513 [-]: CAPTURE VAL R62; 
     514 [-]: CAPTURE VAL R25; 
     515 [-]: CAPTURE VAL R26; 
     516 [-]: CAPTURE VAL R27; 
     517 [-]: NEWCLOSURE R108 P50; 
     518 [-]: CAPTURE VAL R107; 
     519 [-]: CAPTURE VAL R22; 
     520 [-]: CAPTURE VAL R24; 
     521 [-]: CAPTURE VAL R23; 
     522 [-]: CAPTURE REF R42; 
     523 [-]: CAPTURE VAL R52; 
     524 [-]: CAPTURE VAL R64; 
     525 [-]: CAPTURE VAL R75; 
     526 [-]: CAPTURE VAL R95; 
     527 [-]: CAPTURE VAL R41; 
     528 [-]: CAPTURE VAL R85; 
     529 [-]: CAPTURE VAL R92; 
     530 [-]: NEWCLOSURE R109 P51; 
     531 [-]: CAPTURE REF R54; 
     532 [-]: CAPTURE REF R36; 
     533 [-]: CAPTURE VAL R53; 
     534 [-]: CAPTURE VAL R9; 
     535 [-]: CAPTURE REF R35; 
     536 [-]: CAPTURE VAL R70; 
     537 [-]: CAPTURE VAL R108; 
     538 [-]: CAPTURE REF R38; 
     539 [-]: CAPTURE REF R37; 
     540 [-]: CAPTURE VAL R106; 
     541 [-]: CAPTURE VAL R11; 
     542 [-]: CAPTURE VAL R21; 
     543 [-]: CAPTURE VAL R23; 
     544 [-]: CAPTURE REF R32; 
     545 [-]: CAPTURE VAL R68; 
     546 [-]: NEWCLOSURE R110 P52; 
     547 [-]: CAPTURE REF R31; 
     548 [-]: CAPTURE REF R34; 
     549 [-]: CAPTURE REF R32; 
     550 [-]: CAPTURE REF R33; 
     551 [-]: CAPTURE REF R35; 
     552 [-]: CAPTURE REF R37; 
     553 [-]: CAPTURE VAL R10; 
     554 [-]: CAPTURE VAL R19; 
     555 [-]: CAPTURE VAL R20; 
     556 [-]: CAPTURE VAL R22; 
     557 [-]: CAPTURE VAL R23; 
     558 [-]: CAPTURE VAL R24; 
     559 [-]: CAPTURE VAL R25; 
     560 [-]: CAPTURE VAL R26; 
     561 [-]: CAPTURE VAL R27; 
     562 [-]: CAPTURE REF R36; 
     563 [-]: CAPTURE VAL R8; 
     564 [-]: CAPTURE VAL R109; 
     565 [-]: CAPTURE VAL R53; 
     566 [-]: NEWCLOSURE R111 P53; 
     567 [-]: CAPTURE VAL R13; 
     568 [-]: CAPTURE VAL R75; 
     569 [-]: CAPTURE VAL R95; 
     570 [-]: CAPTURE VAL R14; 
     571 [-]: CAPTURE REF R33; 
     572 [-]: CAPTURE REF R32; 
     573 [-]: CAPTURE REF R34; 
     574 [-]: CAPTURE VAL R16; 
     575 [-]: CAPTURE REF R51; 
     576 [-]: CAPTURE VAL R8; 
     577 [-]: CAPTURE VAL R19; 
     578 [-]: CAPTURE VAL R20; 
     579 [-]: CAPTURE VAL R11; 
     580 [-]: CAPTURE REF R36; 
     581 [-]: CAPTURE VAL R62; 
     582 [-]: CAPTURE VAL R30; 
     583 [-]: CAPTURE REF R42; 
     584 [-]: CAPTURE VAL R28; 
     585 [-]: CAPTURE VAL R29; 
     586 [-]: DUPCLOSURE R112 K98; 
     587 [-]: CAPTURE VAL R17; 
     588 [-]: SETGLOBAL R112 K99; "Evaluate" = var112
     589 [-]: NEWCLOSURE R112 P55; 
     590 [-]: CAPTURE REF R54; 
     591 [-]: CAPTURE VAL R53; 
     592 [-]: CAPTURE VAL R104; 
     593 [-]: CAPTURE VAL R61; 
     594 [-]: CAPTURE VAL R30; 
     595 [-]: CAPTURE REF R42; 
     596 [-]: CAPTURE VAL R28; 
     597 [-]: CAPTURE REF R43; 
     598 [-]: CAPTURE VAL R29; 
     599 [-]: CAPTURE REF R44; 
     600 [-]: CAPTURE REF R50; 
     601 [-]: NEWCLOSURE R113 P56; 
     602 [-]: CAPTURE VAL R110; 
     603 [-]: CAPTURE REF R31; 
     604 [-]: CAPTURE REF R54; 
     605 [-]: CAPTURE VAL R53; 
     606 [-]: CAPTURE VAL R104; 
     607 [-]: CAPTURE VAL R61; 
     608 [-]: CAPTURE VAL R30; 
     609 [-]: CAPTURE REF R42; 
     610 [-]: CAPTURE VAL R28; 
     611 [-]: CAPTURE REF R43; 
     612 [-]: CAPTURE VAL R29; 
     613 [-]: CAPTURE REF R44; 
     614 [-]: CAPTURE REF R50; 
     615 [-]: CAPTURE REF R37; 
     616 [-]: CAPTURE VAL R8; 
     617 [-]: CAPTURE REF R32; 
     618 [-]: CAPTURE VAL R111; 
     619 [-]: SETGLOBAL R113 K100; "ExcavationStart" = var113
     620 [-]: DUPCLOSURE R113 K101; 
     621 [-]: CAPTURE VAL R16; 
     622 [-]: CAPTURE VAL R18; 
     623 [-]: SETGLOBAL R113 K102; "OnAgentRegistered" = var113
     624 [-]: NEWCLOSURE R113 P58; 
     625 [-]: CAPTURE REF R32; 
     626 [-]: CAPTURE REF R31; 
     627 [-]: CAPTURE VAL R23; 
     628 [-]: CAPTURE VAL R11; 
     629 [-]: CAPTURE VAL R92; 
     630 [-]: SETGLOBAL R113 K103; "OnPlayersChanged" = var113
     631 [-]: DUPCLOSURE R113 K104; 
     632 [-]: CAPTURE VAL R81; 
     633 [-]: CAPTURE VAL R96; 
     634 [-]: SETGLOBAL R113 K105; "OnKilled" = var113
     635 [-]: NEWCLOSURE R113 P60; 
     636 [-]: CAPTURE REF R42; 
     637 [-]: CAPTURE VAL R41; 
     638 [-]: CAPTURE VAL R100; 
     639 [-]: SETGLOBAL R113 K106; "OnActivated" = var113
     640 [-]: NEWCLOSURE R113 P61; 
     641 [-]: CAPTURE VAL R8; 
     642 [-]: CAPTURE REF R32; 
     643 [-]: SETGLOBAL R113 K107; "PlayersLeaving" = var113
     644 [-]: NEWCLOSURE R113 P62; 
     645 [-]: CAPTURE VAL R8; 
     646 [-]: CAPTURE REF R32; 
     647 [-]: SETGLOBAL R113 K108; "PlayersReturning" = var113
     648 [-]: NEWCLOSURE R113 P63; 
     649 [-]: CAPTURE REF R54; 
     650 [-]: CAPTURE VAL R53; 
     651 [-]: CAPTURE REF R42; 
     652 [-]: CAPTURE VAL R52; 
     653 [-]: CAPTURE VAL R75; 
     654 [-]: CAPTURE VAL R23; 
     655 [-]: CAPTURE VAL R95; 
     656 [-]: CAPTURE VAL R92; 
     657 [-]: CAPTURE VAL R9; 
     658 [-]: CAPTURE REF R35; 
     659 [-]: SETGLOBAL R113 K109; "SkipPhase" = var113
     660 [-]: CLOSEUPVALS R31; 
     661 [-]: RETURN R0 0  ; 


; Name:            
; Defined at line: 134
; #Upvalues:       0
; #Parameters:     0
; Is_vararg:       0
; Max Stack Size:  1

       0 [-]: LOADB R0 0   ; var0 = false
       1 [-]: RETURN R0 1  ; 


; Name:            
; Defined at line: 138
; #Upvalues:       0
; #Parameters:     2
; Is_vararg:       0
; Max Stack Size:  6

       0 [-]: LOADK R3 K0  ; var3 = "DynExcav"
       1 [-]: LOADK R4 K1  ; var4 = ": "
       2 [-]: MOVE R5 R0   ; var5 = var0
       3 [-]: CONCAT R2 R3 R5; var2 = var3 .. var5
       4 [-]: GETIMPORT R3 3; var3 = 0xD644C2F1
       5 [-]: MOVE R4 R2   ; var4 = var2
       6 [-]: CALL R3 2 1  ; var3(var4)
       7 [-]: JUMPIFNOT R1 L0; goto L0 if not var1
       8 [-]: GETIMPORT R3 5; var3 = 0x3D106989
       9 [-]: MOVE R4 R0   ; var4 = var0
      10 [-]: CALL R3 2 1  ; var3(var4)
L 0:  11 [-]: RETURN R0 0  ; 


; Name:            
; Defined at line: 144
; #Upvalues:       0
; #Parameters:     3
; Is_vararg:       0
; Max Stack Size:  13

       0 [-]: ORK R2 R2 K0 ; var2 = var2 or 1
       1 [-]: NEWTABLE R3 0 0; var3 = {}
       2 [-]: LOADN R6 1   ; var6 = 1
       3 [-]: MOVE R4 R1   ; var4 = var1
       4 [-]: LOADN R5 1   ; var5 = 1
       5 [-]: FORNPREP R4 L1; nforprep start - [escape at L1] -- var4 = iterator
L 0:   6 [-]: GETIMPORT R7 2; var7 = 0xBE190284
       7 [-]: GETIMPORT R9 4; var9 = 0x0469F296
       8 [-]: MOVE R11 R0  ; var11 = var0
       9 [-]: MOVE R12 R6  ; var12 = var6
      10 [-]: CONCAT R10 R11 R12; var10 = var11 .. var12
      11 [-]: CALL R9 2 2  ; var9 = var9(var10)
      12 [-]: LOADN R10 0  ; var10 = 0
      13 [-]: NAMECALL R7 R7 K5; var8 = var7; var7 = var7[0x0EB34C69]
      14 [-]: CALL R7 4 2  ; var7 = var7(var8, var9, var10)
      15 [-]: MUL R8 R7 R2 ; var8 = var7 * var2
      16 [-]: SETTABLE R8 R3 R6; var8[var3] = var6
      17 [-]: FORNLOOP R4 L0; nforloop end - iterate + goto L0
L 1:  18 [-]: RETURN R3 1  ; 


; Name:            
; Defined at line: 154
; #Upvalues:       0
; #Parameters:     3
; Is_vararg:       0
; Max Stack Size:  13

       0 [-]: ORK R2 R2 K0 ; var2 = var2 or 1
       1 [-]: LOADN R5 1   ; var5 = 1
       2 [-]: LENGTH R3 R1 ; var3 = #var1
       3 [-]: LOADN R4 1   ; var4 = 1
       4 [-]: FORNPREP R3 L2; nforprep start - [escape at L2] -- var3 = iterator
L 0:   5 [-]: GETTABLE R6 R1 R5; var6 = var1[var5]
       6 [-]: LOADN R7 0   ; var7 = 0
       7 [-]: JUMPIFNOTLT R7 R6 L1; goto L1 if var7 >= var132897
       8 [-]: GETIMPORT R7 2; var7 = 0xBE190284
       9 [-]: GETIMPORT R9 4; var9 = 0x0469F296
      10 [-]: MOVE R11 R0  ; var11 = var0
      11 [-]: MOVE R12 R5  ; var12 = var5
      12 [-]: CONCAT R10 R11 R12; var10 = var11 .. var12
      13 [-]: CALL R9 2 2  ; var9 = var9(var10)
      14 [-]: GETTABLE R11 R1 R5; var11 = var1[var5]
      15 [-]: DIV R10 R11 R2; var10 = var11 / var2
      16 [-]: NAMECALL R7 R7 K5; var8 = var7; var7 = var7[0x751F061D]
      17 [-]: CALL R7 4 1  ; var7(var8, var9, var10)
L 1:  18 [-]: FORNLOOP R3 L0; nforloop end - iterate + goto L0
L 2:  19 [-]: RETURN R0 0  ; 


; Name:            
; Defined at line: 164
; #Upvalues:       0
; #Parameters:     2
; Is_vararg:       0
; Max Stack Size:  11

       0 [-]: LOADN R4 1   ; var4 = 1
       1 [-]: MOVE R2 R1   ; var2 = var1
       2 [-]: LOADN R3 1   ; var3 = 1
       3 [-]: FORNPREP R2 L1; nforprep start - [escape at L1] -- var2 = iterator
L 0:   4 [-]: GETIMPORT R5 1; var5 = 0xBE190284
       5 [-]: GETIMPORT R7 3; var7 = 0x0469F296
       6 [-]: MOVE R9 R0   ; var9 = var0
       7 [-]: MOVE R10 R4  ; var10 = var4
       8 [-]: CONCAT R8 R9 R10; var8 = var9 .. var10
       9 [-]: CALL R7 2 0  ; var7, ... = var7(var8)
      10 [-]: NAMECALL R5 R5 K4; var6 = var5; var5 = var5[0xB9BFD47C]
      11 [-]: CALL R5 0 1  ; var5(var6, ...)
      12 [-]: FORNLOOP R2 L0; nforloop end - iterate + goto L0
L 1:  13 [-]: RETURN R0 0  ; 


; Name:            
; Defined at line: 170
; #Upvalues:       0
; #Parameters:     2
; Is_vararg:       0
; Max Stack Size:  7

       0 [-]: ORK R1 R1 K0 ; var1 = var1 or 1
       1 [-]: GETIMPORT R2 2; var2 = 0xBE190284
       2 [-]: MOVE R4 R0   ; var4 = var0
       3 [-]: LOADN R5 0   ; var5 = 0
       4 [-]: NAMECALL R2 R2 K3; var3 = var2; var2 = var2[0x0EB34C69]
       5 [-]: CALL R2 4 2  ; var2 = var2(var3, var4, var5)
       6 [-]: ADD R2 R2 R1 ; var2 = var2 + var1
       7 [-]: GETIMPORT R3 2; var3 = 0xBE190284
       8 [-]: MOVE R5 R0   ; var5 = var0
       9 [-]: MOVE R6 R2   ; var6 = var2
      10 [-]: NAMECALL R3 R3 K4; var4 = var3; var3 = var3[0x751F061D]
      11 [-]: CALL R3 4 1  ; var3(var4, var5, var6)
      12 [-]: RETURN R2 1  ; 


; Name:            
; Defined at line: 178
; #Upvalues:       7
; #Parameters:     0
; Is_vararg:       0
; Max Stack Size:  20

       0 [-]: GETIMPORT R0 1; var0 = 0xCFC01047
       1 [-]: GETUPVAL R1 0; var1 = upvalues[0]
       2 [-]: CALL R0 2 4  ; var0, var1, var2 = var0(var1)
       3 [-]: FORGPREP_NEXT R0 L4; 
L 0:   4 [-]: GETIMPORT R5 3; var5 = 0x3D106989
       5 [-]: LOADK R7 K4  ; var7 = "ID: "
       6 [-]: MOVE R8 R3   ; var8 = var3
       7 [-]: LOADK R9 K5  ; var9 = " - Status: "
       8 [-]: MOVE R10 R4  ; var10 = var4
       9 [-]: LOADK R11 K6 ; var11 = " Power: "
      10 [-]: GETUPVAL R18 1; var18 = upvalues[1]
      11 [-]: GETTABLE R17 R18 R3; var17 = var18[var3]
      12 [-]: ORK R12 R17 K7; var12 = var17 or "nil"
      13 [-]: LOADK R13 K8 ; var13 = " Timer: "
      14 [-]: GETUPVAL R18 2; var18 = upvalues[2]
      15 [-]: GETTABLE R17 R18 R3; var17 = var18[var3]
      16 [-]: ORK R14 R17 K7; var14 = var17 or "nil"
      17 [-]: LOADK R15 K9 ; var15 = " Avatar: "
      18 [-]: GETUPVAL R19 3; var19 = upvalues[3]
      19 [-]: GETTABLE R18 R19 R3; var18 = var19[var3]
      20 [-]: FASTCALL1 64 R18 L1; 
      21 [-]: GETIMPORT R17 11; var17 = 0x7B998233
      22 [-]: CALL R17 2 2 ; var17 = var17(var18)
L 1:  23 [-]: JUMPIFNOT R17 L2; goto L2 if not var17
      24 [-]: LOADK R16 K7 ; var16 = "nil"
      25 [-]: JUMP L3      ; goto L3
L 2:  26 [-]: GETUPVAL R17 3; var17 = upvalues[3]
      27 [-]: GETTABLE R16 R17 R3; var16 = var17[var3]
      28 [-]: NAMECALL R16 R16 K12; var17 = var16; var16 = var16[0xE223E2B1]
      29 [-]: CALL R16 2 2 ; var16 = var16(var17)
L 3:  30 [-]: CONCAT R6 R7 R16; var6 = var7 .. var16
      31 [-]: CALL R5 2 1  ; var5(var6)
L 4:  32 [-]: FORGLOOP R0 L0 2; 
      33 [-]: GETIMPORT R0 3; var0 = 0x3D106989
      34 [-]: LOADK R1 K13 ; var1 = "Net vars:"
      35 [-]: CALL R0 2 1  ; var0(var1)
      36 [-]: GETIMPORT R0 15; var0 = 0xBE190284
      37 [-]: GETUPVAL R2 4; var2 = upvalues[4]
      38 [-]: LOADN R3 0   ; var3 = 0
      39 [-]: NAMECALL R0 R0 K16; var1 = var0; var0 = var0[0x0EB34C69]
      40 [-]: CALL R0 4 2  ; var0 = var0(var1, var2, var3)
      41 [-]: GETIMPORT R1 15; var1 = 0xBE190284
      42 [-]: GETUPVAL R3 5; var3 = upvalues[5]
      43 [-]: LOADN R4 0   ; var4 = 0
      44 [-]: NAMECALL R1 R1 K16; var2 = var1; var1 = var1[0x0EB34C69]
      45 [-]: CALL R1 4 2  ; var1 = var1(var2, var3, var4)
      46 [-]: GETIMPORT R2 15; var2 = 0xBE190284
      47 [-]: GETUPVAL R4 6; var4 = upvalues[6]
      48 [-]: LOADN R5 0   ; var5 = 0
      49 [-]: NAMECALL R2 R2 K16; var3 = var2; var2 = var2[0x0EB34C69]
      50 [-]: CALL R2 4 2  ; var2 = var2(var3, var4, var5)
      51 [-]: GETIMPORT R3 3; var3 = 0x3D106989
      52 [-]: LOADK R5 K17 ; var5 = "Dropped: "
      53 [-]: MOVE R6 R0   ; var6 = var0
      54 [-]: LOADK R7 K18 ; var7 = " Failed: "
      55 [-]: MOVE R8 R1   ; var8 = var1
      56 [-]: LOADK R9 K19 ; var9 = " Completed: "
      57 [-]: MOVE R10 R2  ; var10 = var2
      58 [-]: CONCAT R4 R5 R10; var4 = var5 .. var10
      59 [-]: CALL R3 2 1  ; var3(var4)
      60 [-]: RETURN R0 0  ; 


; Name:            
; Defined at line: 189
; #Upvalues:       0
; #Parameters:     0
; Is_vararg:       0
; Max Stack Size:  7

       0 [-]: GETIMPORT R3 1; var3 = 0xE7F2B02F
       1 [-]: NAMECALL R3 R3 K2; var4 = var3; var3 = var3[0xEBE2F513]
       2 [-]: CALL R3 2 2  ; var3 = var3(var4)
       3 [-]: GETIMPORT R4 4; var4 = 0x9BA7909F
       4 [-]: LOADK R6 K5  ; var6 = "Server.NumVirtualTestClients"
       5 [-]: NAMECALL R4 R4 K6; var5 = var4; var4 = var4[0x8151451D]
       6 [-]: CALL R4 3 2  ; var4 = var4(var5, var6)
       7 [-]: ADD R2 R3 R4 ; var2 = var3 + var4
       8 [-]: FASTCALL2K 18 R2 K7 L0; 
       9 [-]: LOADK R3 K7  ; var3 = 1
      10 [-]: GETIMPORT R1 10; var1 = 0x5BCED4C4[0xB62ECFE0]
      11 [-]: CALL R1 3 2  ; var1 = var1(var2, var3)
L 0:  12 [-]: FASTCALL2K 19 R1 K11 L1; 
      13 [-]: LOADK R2 K11 ; var2 = 4
      14 [-]: GETIMPORT R0 13; var0 = 0x5BCED4C4[0xAC1B386A]
      15 [-]: CALL R0 3 2  ; var0 = var0(var1, var2)
L 1:  16 [-]: RETURN R0 1  ; 


; Name:            
; Defined at line: 193
; #Upvalues:       2
; #Parameters:     2
; Is_vararg:       0
; Max Stack Size:  6

       0 [-]: GETUPVAL R3 0; var3 = upvalues[0]
       1 [-]: GETTABLEKS R2 R3 K0; var2 = var3[0x9742B85B]
       2 [-]: GETUPVAL R3 1; var3 = upvalues[1]
       3 [-]: GETIMPORT R4 2; var4 = 0x0469F296
       4 [-]: MOVE R5 R0   ; var5 = var0
       5 [-]: CALL R4 2 2  ; var4 = var4(var5)
       6 [-]: MOVE R5 R1   ; var5 = var1
       7 [-]: CALL R2 4 1  ; var2(var3, var4, var5)
       8 [-]: RETURN R0 0  ; 


; Name:            
; Defined at line: 198
; #Upvalues:       2
; #Parameters:     1
; Is_vararg:       0
; Max Stack Size:  4

       0 [-]: JUMPIFNOT R0 L0; goto L0 if not var0
       1 [-]: GETIMPORT R1 1; var1 = _T
       2 [-]: LOADB R2 1   ; var2 = true
       3 [-]: SETTABLEKS R2 R1 K2; var2["QualifiedForBountyBonus"] = var1
       4 [-]: GETUPVAL R2 0; var2 = upvalues[0]
       5 [-]: GETTABLEKS R1 R2 K3; var1 = var2[0x0A8ECC31]
       6 [-]: GETUPVAL R3 1; var3 = upvalues[1]
       7 [-]: GETTABLEKS R2 R3 K4; var2 = var3["BONUS_OBJECTIVE"]
       8 [-]: CALL R1 2 1  ; var1(var2)
       9 [-]: RETURN R0 0  ; 
L 0:  10 [-]: GETIMPORT R1 1; var1 = _T
      11 [-]: LOADB R2 0   ; var2 = false
      12 [-]: SETTABLEKS R2 R1 K2; var2["QualifiedForBountyBonus"] = var1
      13 [-]: GETUPVAL R2 0; var2 = upvalues[0]
      14 [-]: GETTABLEKS R1 R2 K5; var1 = var2[0x37317859]
      15 [-]: GETUPVAL R3 1; var3 = upvalues[1]
      16 [-]: GETTABLEKS R2 R3 K4; var2 = var3["BONUS_OBJECTIVE"]
      17 [-]: CALL R1 2 1  ; var1(var2)
      18 [-]: RETURN R0 0  ; 


; Name:            
; Defined at line: 208
; #Upvalues:       6
; #Parameters:     0
; Is_vararg:       0
; Max Stack Size:  5

       0 [-]: LOADK R1 K0  ; var1 = "DynExcav"
       1 [-]: LOADK R2 K1  ; var2 = ": "
       2 [-]: LOADK R3 K2  ; var3 = "Encounter set to succeeded"
       3 [-]: CONCAT R0 R1 R3; var0 = var1 .. var3
       4 [-]: GETIMPORT R1 4; var1 = 0xD644C2F1
       5 [-]: MOVE R2 R0   ; var2 = var0
       6 [-]: CALL R1 2 1  ; var1(var2)
       7 [-]: GETIMPORT R1 6; var1 = 0xBE190284
       8 [-]: GETUPVAL R3 0; var3 = upvalues[0]
       9 [-]: LOADN R4 0   ; var4 = 0
      10 [-]: NAMECALL R1 R1 K7; var2 = var1; var1 = var1[0x0EB34C69]
      11 [-]: CALL R1 4 2  ; var1 = var1(var2, var3, var4)
      12 [-]: JUMPXEQKN R1 K8 L0; 
      13 [-]: LOADB R0 0 +1; var0 = false
L 0:  14 [-]: LOADB R0 1   ; var0 = true
L 1:  15 [-]: JUMPIFNOT R0 L2; goto L2 if not var0
      16 [-]: GETIMPORT R1 10; var1 = _T
      17 [-]: LOADB R2 1   ; var2 = true
      18 [-]: SETTABLEKS R2 R1 K11; var2["QualifiedForBountyBonus"] = var1
      19 [-]: GETUPVAL R2 1; var2 = upvalues[1]
      20 [-]: GETTABLEKS R1 R2 K12; var1 = var2[0x0A8ECC31]
      21 [-]: GETUPVAL R3 2; var3 = upvalues[2]
      22 [-]: GETTABLEKS R2 R3 K13; var2 = var3["BONUS_OBJECTIVE"]
      23 [-]: CALL R1 2 1  ; var1(var2)
      24 [-]: JUMP L3      ; goto L3
L 2:  25 [-]: GETIMPORT R1 10; var1 = _T
      26 [-]: LOADB R2 0   ; var2 = false
      27 [-]: SETTABLEKS R2 R1 K11; var2["QualifiedForBountyBonus"] = var1
      28 [-]: GETUPVAL R2 1; var2 = upvalues[1]
      29 [-]: GETTABLEKS R1 R2 K14; var1 = var2[0x37317859]
      30 [-]: GETUPVAL R3 2; var3 = upvalues[2]
      31 [-]: GETTABLEKS R2 R3 K13; var2 = var3["BONUS_OBJECTIVE"]
      32 [-]: CALL R1 2 1  ; var1(var2)
L 3:  33 [-]: GETUPVAL R1 3; var1 = upvalues[3]
      34 [-]: LOADN R3 4   ; var3 = 4
      35 [-]: NAMECALL R1 R1 K15; var2 = var1; var1 = var1[0xFE9DC265]
      36 [-]: CALL R1 3 1  ; var1(var2, var3)
      37 [-]: JUMPIFNOT R0 L4; goto L4 if not var0
      38 [-]: GETUPVAL R2 4; var2 = upvalues[4]
      39 [-]: GETTABLEKS R1 R2 K16; var1 = var2[0x9742B85B]
      40 [-]: GETUPVAL R2 5; var2 = upvalues[5]
      41 [-]: GETIMPORT R3 18; var3 = 0x0469F296
      42 [-]: LOADK R4 K19 ; var4 = "CompleteBonus"
      43 [-]: CALL R3 2 2  ; var3 = var3(var4)
      44 [-]: LOADB R4 0   ; var4 = false
      45 [-]: CALL R1 4 1  ; var1(var2, var3, var4)
      46 [-]: RETURN R0 0  ; 
L 4:  47 [-]: GETUPVAL R2 4; var2 = upvalues[4]
      48 [-]: GETTABLEKS R1 R2 K16; var1 = var2[0x9742B85B]
      49 [-]: GETUPVAL R2 5; var2 = upvalues[5]
      50 [-]: GETIMPORT R3 18; var3 = 0x0469F296
      51 [-]: LOADK R4 K20 ; var4 = "Complete"
      52 [-]: CALL R3 2 2  ; var3 = var3(var4)
      53 [-]: LOADB R4 0   ; var4 = false
      54 [-]: CALL R1 4 1  ; var1(var2, var3, var4)
      55 [-]: RETURN R0 0  ; 


; Name:            
; Defined at line: 220
; #Upvalues:       2
; #Parameters:     0
; Is_vararg:       0
; Max Stack Size:  3

       0 [-]: GETUPVAL R0 0; var0 = upvalues[0]
       1 [-]: NAMECALL R0 R0 K0; var1 = var0; var0 = var0[0x7076B095]
       2 [-]: CALL R0 2 1  ; var0(var1)
       3 [-]: GETUPVAL R0 1; var0 = upvalues[1]
       4 [-]: LOADN R2 5   ; var2 = 5
       5 [-]: NAMECALL R0 R0 K1; var1 = var0; var0 = var0[0xFE9DC265]
       6 [-]: CALL R0 3 1  ; var0(var1, var2)
       7 [-]: GETIMPORT R0 3; var0 = 0x3D106989
       8 [-]: LOADK R1 K4  ; var1 = "Encounter failed"
       9 [-]: CALL R0 2 1  ; var0(var1)
      10 [-]: RETURN R0 0  ; 


; Name:            
; Defined at line: 226
; #Upvalues:       8
; #Parameters:     1
; Is_vararg:       0
; Max Stack Size:  7

       0 [-]: GETUPVAL R1 0; var1 = upvalues[0]
       1 [-]: JUMPIFNOT R1 L0; goto L0 if not var1
       2 [-]: GETUPVAL R1 1; var1 = upvalues[1]
       3 [-]: GETUPVAL R3 0; var3 = upvalues[0]
       4 [-]: NAMECALL R1 R1 K0; var2 = var1; var1 = var1[0x5570EB3F]
       5 [-]: CALL R1 3 2  ; var1 = var1(var2, var3)
       6 [-]: JUMPIFNOT R1 L0; goto L0 if not var1
       7 [-]: GETIMPORT R1 2; var1 = 0x3D106989
       8 [-]: LOADK R3 K3  ; var3 = "Error: can't finish state, already queued one, time remaining: "
       9 [-]: GETUPVAL R4 1; var4 = upvalues[1]
      10 [-]: GETUPVAL R6 0; var6 = upvalues[0]
      11 [-]: NAMECALL R4 R4 K4; var5 = var4; var4 = var4[0x5D390332]
      12 [-]: CALL R4 3 2  ; var4 = var4(var5, var6)
      13 [-]: CONCAT R2 R3 R4; var2 = var3 .. var4
      14 [-]: CALL R1 2 1  ; var1(var2)
      15 [-]: RETURN R0 0  ; 
L 0:  16 [-]: LOADNIL R1   ; var1 = nil
      17 [-]: SETUPVAL R1 0; upvalues[1] = var0
      18 [-]: FASTCALL1 64 R0 L1; 
      19 [-]: MOVE R2 R0   ; var2 = var0
      20 [-]: GETIMPORT R1 6; var1 = 0x7B998233
      21 [-]: CALL R1 2 2  ; var1 = var1(var2)
L 1:  22 [-]: JUMPIF R1 L2 ; goto L2 if var1
      23 [-]: LOADN R1 0   ; var1 = 0
      24 [-]: JUMPIFNOTLT R1 R0 L2; goto L2 if var1 >= var131361
      25 [-]: GETIMPORT R1 2; var1 = 0x3D106989
      26 [-]: LOADK R3 K7  ; var3 = "queuing FinishState "
      27 [-]: GETUPVAL R4 2; var4 = upvalues[2]
      28 [-]: CONCAT R2 R3 R4; var2 = var3 .. var4
      29 [-]: CALL R1 2 1  ; var1(var2)
      30 [-]: GETUPVAL R1 1; var1 = upvalues[1]
      31 [-]: MOVE R3 R0   ; var3 = var0
      32 [-]: GETUPVAL R4 3; var4 = upvalues[3]
      33 [-]: LOADNIL R5   ; var5 = nil
      34 [-]: NAMECALL R1 R1 K8; var2 = var1; var1 = var1[0xBD2E96EA]
      35 [-]: CALL R1 5 2  ; var1 = var1(var2, var3, var4, var5)
      36 [-]: SETUPVAL R1 0; upvalues[1] = var0
      37 [-]: RETURN R0 0  ; 
L 2:  38 [-]: GETIMPORT R1 2; var1 = 0x3D106989
      39 [-]: LOADK R3 K9  ; var3 = "Finishing state "
      40 [-]: GETUPVAL R4 2; var4 = upvalues[2]
      41 [-]: CONCAT R2 R3 R4; var2 = var3 .. var4
      42 [-]: CALL R1 2 1  ; var1(var2)
      43 [-]: LOADNIL R2   ; var2 = nil
      44 [-]: FASTCALL1 64 R2 L3; 
      45 [-]: GETIMPORT R1 6; var1 = 0x7B998233
      46 [-]: CALL R1 2 2  ; var1 = var1(var2)
L 3:  47 [-]: JUMPIF R1 L4 ; goto L4 if var1
      48 [-]: LOADNIL R1   ; var1 = nil
      49 [-]: NAMECALL R1 R1 K10; var2 = var1; var1 = var1[0xA2880940]
      50 [-]: CALL R1 2 1  ; var1(var2)
L 4:  51 [-]: GETUPVAL R2 4; var2 = upvalues[4]
      52 [-]: FASTCALL1 64 R2 L5; 
      53 [-]: GETIMPORT R1 6; var1 = 0x7B998233
      54 [-]: CALL R1 2 2  ; var1 = var1(var2)
L 5:  55 [-]: JUMPIF R1 L6 ; goto L6 if var1
      56 [-]: GETUPVAL R1 1; var1 = upvalues[1]
      57 [-]: GETUPVAL R3 4; var3 = upvalues[4]
      58 [-]: NAMECALL R1 R1 K11; var2 = var1; var1 = var1[0x775C858B]
      59 [-]: CALL R1 3 1  ; var1(var2, var3)
      60 [-]: LOADNIL R1   ; var1 = nil
      61 [-]: SETUPVAL R1 4; upvalues[1] = var4
L 6:  62 [-]: LOADN R3 1   ; var3 = 1
      63 [-]: GETUPVAL R4 5; var4 = upvalues[5]
      64 [-]: LENGTH R1 R4 ; var1 = #var4
      65 [-]: LOADN R2 1   ; var2 = 1
      66 [-]: FORNPREP R1 L10; nforprep start - [escape at L10] -- var1 = iterator
L 7:  67 [-]: GETUPVAL R6 5; var6 = upvalues[5]
      68 [-]: GETTABLE R5 R6 R3; var5 = var6[var3]
      69 [-]: FASTCALL1 64 R5 L8; 
      70 [-]: GETIMPORT R4 6; var4 = 0x7B998233
      71 [-]: CALL R4 2 2  ; var4 = var4(var5)
L 8:  72 [-]: JUMPIF R4 L9 ; goto L9 if var4
      73 [-]: GETUPVAL R5 5; var5 = upvalues[5]
      74 [-]: GETTABLE R4 R5 R3; var4 = var5[var3]
      75 [-]: NAMECALL R4 R4 K10; var5 = var4; var4 = var4[0xA2880940]
      76 [-]: CALL R4 2 1  ; var4(var5)
L 9:  77 [-]: FORNLOOP R1 L7; nforloop end - iterate + goto L7
L10:  78 [-]: NEWTABLE R1 0 0; var1 = {}
      79 [-]: SETUPVAL R1 5; upvalues[1] = var5
      80 [-]: LOADNIL R1   ; var1 = nil
      81 [-]: GETUPVAL R2 2; var2 = upvalues[2]
      82 [-]: GETUPVAL R4 6; var4 = upvalues[6]
      83 [-]: GETTABLEKS R3 R4 K12; var3 = var4["START"]
      84 [-]: JUMPIFNOTEQ R2 R3 L11; goto L11 if var2 ~= var393788
      85 [-]: GETUPVAL R2 6; var2 = upvalues[6]
      86 [-]: GETTABLEKS R1 R2 K13; var1 = var2["EXCAVATION"]
      87 [-]: JUMP L15     ; goto L15
L11:  88 [-]: GETUPVAL R2 2; var2 = upvalues[2]
      89 [-]: GETUPVAL R4 6; var4 = upvalues[6]
      90 [-]: GETTABLEKS R3 R4 K13; var3 = var4["EXCAVATION"]
      91 [-]: JUMPIFNOTEQ R2 R3 L12; goto L12 if var2 ~= var393788
      92 [-]: GETUPVAL R2 6; var2 = upvalues[6]
      93 [-]: GETTABLEKS R1 R2 K14; var1 = var2["FINISH"]
      94 [-]: JUMP L15     ; goto L15
L12:  95 [-]: GETUPVAL R2 2; var2 = upvalues[2]
      96 [-]: GETUPVAL R4 6; var4 = upvalues[6]
      97 [-]: GETTABLEKS R3 R4 K14; var3 = var4["FINISH"]
      98 [-]: JUMPIFNOTEQ R2 R3 L13; goto L13 if var2 ~= var720928
      99 [-]: JUMP L15     ; goto L15
L13: 100 [-]: GETIMPORT R2 2; var2 = 0x3D106989
     101 [-]: LOADK R4 K15 ; var4 = "Invalid finish state: "
     102 [-]: GETUPVAL R6 2; var6 = upvalues[2]
     103 [-]: FASTCALL1 63 R6 L14; 
     104 [-]: GETIMPORT R5 17; var5 = 0x64FB1586
     105 [-]: CALL R5 2 2  ; var5 = var5(var6)
L14: 106 [-]: CONCAT R3 R4 R5; var3 = var4 .. var5
     107 [-]: CALL R2 2 1  ; var2(var3)
     108 [-]: RETURN R0 0  ; 
L15: 109 [-]: GETUPVAL R2 7; var2 = upvalues[7]
     110 [-]: MOVE R4 R1   ; var4 = var1
     111 [-]: NAMECALL R2 R2 K18; var3 = var2; var2 = var2[0x8ABFF40E]
     112 [-]: CALL R2 3 1  ; var2(var3, var4)
     113 [-]: RETURN R0 0  ; 


; Name:            
; Defined at line: 268
; #Upvalues:       1
; #Parameters:     0
; Is_vararg:       0
; Max Stack Size:  8

       0 [-]: GETIMPORT R4 3; var4 = 0x107BF6DA
       1 [-]: GETIMPORT R5 5; var5 = 0x55156FF7
       2 [-]: CALL R5 1 0  ; var5, ... = var5()
       3 [-]: CALL R4 0 2  ; var4 = var4(var5, ...)
       4 [-]: SUBK R3 R4 K1; var3 = var4 - 0.5
            6 [-]: FASTCALL1 2 R2 L0; 
       7 [-]: GETIMPORT R1 8; var1 = 0x5BCED4C4[0xE4A5B3CA]
       8 [-]: CALL R1 2 2  ; var1 = var1(var2)
L 0:   9 [-]: MULK R0 R1 K0; var0 = var1 * 255
      10 [-]: LOADK R3 K9  ; var3 = "0x"
      11 [-]: GETUPVAL R5 0; var5 = upvalues[0]
      12 [-]: GETTABLEKS R4 R5 K10; var4 = var5[0x2D56AB0B]
      13 [-]: LOADN R5 255 ; var5 = 255
      14 [-]: MOVE R6 R0   ; var6 = var0
      15 [-]: MOVE R7 R0   ; var7 = var0
      16 [-]: CALL R4 4 2  ; var4 = var4(var5, var6, var7)
      17 [-]: CONCAT R2 R3 R4; var2 = var3 .. var4
      18 [-]: FASTCALL1 62 R2 L1; 
      19 [-]: GETIMPORT R1 12; var1 = 0x03F57322
      20 [-]: CALL R1 2 2  ; var1 = var1(var2)
L 1:  21 [-]: RETURN R1 1  ; 


; Name:            
; Defined at line: 273
; #Upvalues:       3
; #Parameters:     3
; Is_vararg:       0
; Max Stack Size:  13

       0 [-]: LOADK R3 K0  ; var3 = ""
       1 [-]: FASTCALL1 64 R2 L0; 
       2 [-]: MOVE R5 R2   ; var5 = var2
       3 [-]: GETIMPORT R4 2; var4 = 0x7B998233
       4 [-]: CALL R4 2 2  ; var4 = var4(var5)
L 0:   5 [-]: JUMPIF R4 L10; goto L10 if var4
       6 [-]: LOADN R4 0   ; var4 = 0
       7 [-]: JUMPIFNOTLE R0 R4 L3; goto L3 if var0 > var395553
       8 [-]: GETIMPORT R9 6; var9 = 0x107BF6DA
       9 [-]: GETIMPORT R10 8; var10 = 0x55156FF7
      10 [-]: CALL R10 1 0 ; var10, ... = var10()
      11 [-]: CALL R9 0 2  ; var9 = var9(var10, ...)
      12 [-]: SUBK R8 R9 K4; var8 = var9 - 0.5
           14 [-]: FASTCALL1 2 R7 L1; 
      15 [-]: GETIMPORT R6 11; var6 = 0x5BCED4C4[0xE4A5B3CA]
      16 [-]: CALL R6 2 2  ; var6 = var6(var7)
L 1:  17 [-]: MULK R5 R6 K3; var5 = var6 * 255
      18 [-]: LOADK R8 K12 ; var8 = "0x"
      19 [-]: GETUPVAL R10 1; var10 = upvalues[1]
      20 [-]: GETTABLEKS R9 R10 K13; var9 = var10[0x2D56AB0B]
      21 [-]: LOADN R10 255; var10 = 255
      22 [-]: MOVE R11 R5  ; var11 = var5
      23 [-]: MOVE R12 R5  ; var12 = var5
      24 [-]: CALL R9 4 2  ; var9 = var9(var10, var11, var12)
      25 [-]: CONCAT R7 R8 R9; var7 = var8 .. var9
      26 [-]: FASTCALL1 62 R7 L2; 
      27 [-]: GETIMPORT R6 15; var6 = 0x03F57322
      28 [-]: CALL R6 2 2  ; var6 = var6(var7)
L 2:  29 [-]: MOVE R4 R6   ; var4 = var6
      30 [-]: SETUPVAL R4 0; upvalues[4] = var0
      31 [-]: GETIMPORT R4 18; var4 = 0x7F5022CF[0xE8072DED]
      32 [-]: LOADK R5 K19 ; var5 = "<font color=\"#%X\"><b>%s</b></font>"
      33 [-]: GETUPVAL R6 0; var6 = upvalues[0]
      34 [-]: LOADK R8 K20 ; var8 = "0% "
      35 [-]: GETTABLEKS R9 R2 K21; var9 = var2["Localize"]
      36 [-]: GETUPVAL R11 2; var11 = upvalues[2]
      37 [-]: GETTABLEKS R10 R11 K22; var10 = var11["HALTED"]
      38 [-]: CALL R9 2 2  ; var9 = var9(var10)
      39 [-]: CONCAT R7 R8 R9; var7 = var8 .. var9
      40 [-]: CALL R4 4 2  ; var4 = var4(var5, var6, var7)
      41 [-]: MOVE R3 R4   ; var3 = var4
      42 [-]: RETURN R3 1  ; 
L 3:  43 [-]: LOADN R4 25  ; var4 = 25
      44 [-]: JUMPIFNOTLE R0 R4 L7; goto L7 if var0 > var50400317
      45 [-]: FASTCALL1 12 R1 L4; 
      46 [-]: MOVE R5 R1   ; var5 = var1
      47 [-]: GETIMPORT R4 24; var4 = 0x5BCED4C4[0x55F27C30]
      48 [-]: CALL R4 2 2  ; var4 = var4(var5)
L 4:  49 [-]: JUMPIFNOTLT R0 R4 L7; goto L7 if var0 >= var395553
      50 [-]: GETIMPORT R9 6; var9 = 0x107BF6DA
      51 [-]: GETIMPORT R10 8; var10 = 0x55156FF7
      52 [-]: CALL R10 1 0 ; var10, ... = var10()
      53 [-]: CALL R9 0 2  ; var9 = var9(var10, ...)
      54 [-]: SUBK R8 R9 K4; var8 = var9 - 0.5
           56 [-]: FASTCALL1 2 R7 L5; 
      57 [-]: GETIMPORT R6 11; var6 = 0x5BCED4C4[0xE4A5B3CA]
      58 [-]: CALL R6 2 2  ; var6 = var6(var7)
L 5:  59 [-]: MULK R5 R6 K3; var5 = var6 * 255
      60 [-]: LOADK R8 K12 ; var8 = "0x"
      61 [-]: GETUPVAL R10 1; var10 = upvalues[1]
      62 [-]: GETTABLEKS R9 R10 K13; var9 = var10[0x2D56AB0B]
      63 [-]: LOADN R10 255; var10 = 255
      64 [-]: MOVE R11 R5  ; var11 = var5
      65 [-]: MOVE R12 R5  ; var12 = var5
      66 [-]: CALL R9 4 2  ; var9 = var9(var10, var11, var12)
      67 [-]: CONCAT R7 R8 R9; var7 = var8 .. var9
      68 [-]: FASTCALL1 62 R7 L6; 
      69 [-]: GETIMPORT R6 15; var6 = 0x03F57322
      70 [-]: CALL R6 2 2  ; var6 = var6(var7)
L 6:  71 [-]: MOVE R4 R6   ; var4 = var6
      72 [-]: SETUPVAL R4 0; upvalues[4] = var0
      73 [-]: GETIMPORT R4 18; var4 = 0x7F5022CF[0xE8072DED]
      74 [-]: LOADK R5 K19 ; var5 = "<font color=\"#%X\"><b>%s</b></font>"
      75 [-]: GETUPVAL R6 0; var6 = upvalues[0]
      76 [-]: MOVE R8 R0   ; var8 = var0
      77 [-]: LOADK R9 K25 ; var9 = "%"
      78 [-]: CONCAT R7 R8 R9; var7 = var8 .. var9
      79 [-]: CALL R4 4 2  ; var4 = var4(var5, var6, var7)
      80 [-]: MOVE R3 R4   ; var3 = var4
      81 [-]: RETURN R3 1  ; 
L 7:  82 [-]: MULK R4 R0 K26; var4 = var0 * 1
      83 [-]: FASTCALL1 12 R1 L8; 
      84 [-]: MOVE R6 R1   ; var6 = var1
      85 [-]: GETIMPORT R5 24; var5 = 0x5BCED4C4[0x55F27C30]
      86 [-]: CALL R5 2 2  ; var5 = var5(var6)
L 8:  87 [-]: JUMPIFNOTLE R5 R4 L9; goto L9 if var5 > var1180705
      88 [-]: GETIMPORT R4 18; var4 = 0x7F5022CF[0xE8072DED]
      89 [-]: LOADK R5 K19 ; var5 = "<font color=\"#%X\"><b>%s</b></font>"
      90 [-]: GETIMPORT R7 28; var7 = 0x0032441C
      91 [-]: GETTABLEKS R6 R7 K29; var6 = var7["UIColor_MediumGrey"]
      92 [-]: GETTABLEKS R7 R2 K21; var7 = var2["Localize"]
      93 [-]: GETUPVAL R9 2; var9 = upvalues[2]
      94 [-]: GETTABLEKS R8 R9 K30; var8 = var9["FULL"]
      95 [-]: CALL R7 2 0  ; var7, ... = var7(var8)
      96 [-]: CALL R4 0 2  ; var4 = var4(var5, ...)
      97 [-]: MOVE R3 R4   ; var3 = var4
      98 [-]: RETURN R3 1  ; 
L 9:  99 [-]: GETIMPORT R4 18; var4 = 0x7F5022CF[0xE8072DED]
     100 [-]: LOADK R5 K19 ; var5 = "<font color=\"#%X\"><b>%s</b></font>"
     101 [-]: GETIMPORT R7 28; var7 = 0x0032441C
     102 [-]: GETTABLEKS R6 R7 K31; var6 = var7["UIColor_White"]
     103 [-]: MOVE R8 R0   ; var8 = var0
     104 [-]: LOADK R9 K25 ; var9 = "%"
     105 [-]: CONCAT R7 R8 R9; var7 = var8 .. var9
     106 [-]: CALL R4 4 2  ; var4 = var4(var5, var6, var7)
     107 [-]: MOVE R3 R4   ; var3 = var4
L10: 108 [-]: RETURN R3 1  ; 


; Name:            
; Defined at line: 292
; #Upvalues:       0
; #Parameters:     4
; Is_vararg:       0
; Max Stack Size:  11

       0 [-]: JUMPIFNOT R3 L8; goto L8 if not var3
       1 [-]: FASTCALL1 64 R0 L0; 
       2 [-]: MOVE R5 R0   ; var5 = var0
       3 [-]: GETIMPORT R4 1; var4 = 0x7B998233
       4 [-]: CALL R4 2 2  ; var4 = var4(var5)
L 0:   5 [-]: JUMPIF R4 L1 ; goto L1 if var4
       6 [-]: LOADB R6 1   ; var6 = true
       7 [-]: LOADB R7 0   ; var7 = false
       8 [-]: NAMECALL R4 R0 K2; var5 = var0; var4 = var0[0x768274D6]
       9 [-]: CALL R4 4 1  ; var4(var5, var6, var7)
L 1:  10 [-]: GETIMPORT R4 4; var4 = 0xC8802016
      11 [-]: MOVE R5 R1   ; var5 = var1
      12 [-]: CALL R4 2 4  ; var4, var5, var6 = var4(var5)
      13 [-]: FORGPREP_INEXT R4 L4; 
L 2:  14 [-]: FASTCALL1 64 R8 L3; 
      15 [-]: MOVE R10 R8  ; var10 = var8
      16 [-]: GETIMPORT R9 1; var9 = 0x7B998233
      17 [-]: CALL R9 2 2  ; var9 = var9(var10)
L 3:  18 [-]: JUMPIF R9 L4 ; goto L4 if var9
      19 [-]: NAMECALL R9 R8 K5; var10 = var8; var9 = var8[0x383D2E7D]
      20 [-]: CALL R9 2 1  ; var9(var10)
L 4:  21 [-]: FORGLOOP R4 L2 2 [inext]; 
      22 [-]: GETIMPORT R4 4; var4 = 0xC8802016
      23 [-]: MOVE R5 R2   ; var5 = var2
      24 [-]: CALL R4 2 4  ; var4, var5, var6 = var4(var5)
      25 [-]: FORGPREP_INEXT R4 L7; 
L 5:  26 [-]: FASTCALL1 64 R8 L6; 
      27 [-]: MOVE R10 R8  ; var10 = var8
      28 [-]: GETIMPORT R9 1; var9 = 0x7B998233
      29 [-]: CALL R9 2 2  ; var9 = var9(var10)
L 6:  30 [-]: JUMPIF R9 L7 ; goto L7 if var9
      31 [-]: NAMECALL R9 R8 K5; var10 = var8; var9 = var8[0x383D2E7D]
      32 [-]: CALL R9 2 1  ; var9(var10)
L 7:  33 [-]: FORGLOOP R4 L5 2 [inext]; 
      34 [-]: RETURN R0 0  ; 
L 8:  35 [-]: FASTCALL1 64 R0 L9; 
      36 [-]: MOVE R5 R0   ; var5 = var0
      37 [-]: GETIMPORT R4 1; var4 = 0x7B998233
      38 [-]: CALL R4 2 2  ; var4 = var4(var5)
L 9:  39 [-]: JUMPIF R4 L10; goto L10 if var4
      40 [-]: LOADB R6 0   ; var6 = false
      41 [-]: LOADB R7 0   ; var7 = false
      42 [-]: NAMECALL R4 R0 K2; var5 = var0; var4 = var0[0x768274D6]
      43 [-]: CALL R4 4 1  ; var4(var5, var6, var7)
L10:  44 [-]: GETIMPORT R4 4; var4 = 0xC8802016
      45 [-]: MOVE R5 R1   ; var5 = var1
      46 [-]: CALL R4 2 4  ; var4, var5, var6 = var4(var5)
      47 [-]: FORGPREP_INEXT R4 L13; 
L11:  48 [-]: FASTCALL1 64 R8 L12; 
      49 [-]: MOVE R10 R8  ; var10 = var8
      50 [-]: GETIMPORT R9 1; var9 = 0x7B998233
      51 [-]: CALL R9 2 2  ; var9 = var9(var10)
L12:  52 [-]: JUMPIF R9 L13; goto L13 if var9
      53 [-]: NAMECALL R9 R8 K6; var10 = var8; var9 = var8[0xF4E253B6]
      54 [-]: CALL R9 2 1  ; var9(var10)
L13:  55 [-]: FORGLOOP R4 L11 2 [inext]; 
      56 [-]: GETIMPORT R4 4; var4 = 0xC8802016
      57 [-]: MOVE R5 R2   ; var5 = var2
      58 [-]: CALL R4 2 4  ; var4, var5, var6 = var4(var5)
      59 [-]: FORGPREP_INEXT R4 L16; 
L14:  60 [-]: FASTCALL1 64 R8 L15; 
      61 [-]: MOVE R10 R8  ; var10 = var8
      62 [-]: GETIMPORT R9 1; var9 = 0x7B998233
      63 [-]: CALL R9 2 2  ; var9 = var9(var10)
L15:  64 [-]: JUMPIF R9 L16; goto L16 if var9
      65 [-]: NAMECALL R9 R8 K6; var10 = var8; var9 = var8[0xF4E253B6]
      66 [-]: CALL R9 2 1  ; var9(var10)
L16:  67 [-]: FORGLOOP R4 L14 2 [inext]; 
      68 [-]: RETURN R0 0  ; 


; Name:            
; Defined at line: 324
; #Upvalues:       2
; #Parameters:     1
; Is_vararg:       0
; Max Stack Size:  5

       0 [-]: GETUPVAL R2 0; var2 = upvalues[0]
       1 [-]: GETTABLE R1 R2 R0; var1 = var2[var0]
       2 [-]: JUMPIFNOT R1 L1; goto L1 if not var1
       3 [-]: GETUPVAL R3 0; var3 = upvalues[0]
       4 [-]: GETTABLE R2 R3 R0; var2 = var3[var0]
       5 [-]: GETUPVAL R4 1; var4 = upvalues[1]
       6 [-]: GETTABLEKS R3 R4 K0; var3 = var4["A"]
       7 [-]: JUMPIFLE R3 R2 L0; goto L0 if var3 <= var16777478
       8 [-]: LOADB R1 0 +1; var1 = false
L 0:   9 [-]: LOADB R1 1   ; var1 = true
L 1:  10 [-]: RETURN R1 1  ; 


; Name:            
; Defined at line: 328
; #Upvalues:       2
; #Parameters:     0
; Is_vararg:       0
; Max Stack Size:  10

       0 [-]: NEWTABLE R0 0 0; var0 = {}
       1 [-]: GETIMPORT R1 1; var1 = 0xCFC01047
       2 [-]: GETUPVAL R2 0; var2 = upvalues[0]
       3 [-]: CALL R1 2 4  ; var1, var2, var3 = var1(var2)
       4 [-]: FORGPREP_NEXT R1 L3; 
L 0:   5 [-]: GETUPVAL R7 0; var7 = upvalues[0]
       6 [-]: GETTABLE R6 R7 R4; var6 = var7[var4]
       7 [-]: JUMPIFNOT R6 L2; goto L2 if not var6
       8 [-]: GETUPVAL R8 0; var8 = upvalues[0]
       9 [-]: GETTABLE R7 R8 R4; var7 = var8[var4]
      10 [-]: GETUPVAL R9 1; var9 = upvalues[1]
      11 [-]: GETTABLEKS R8 R9 K2; var8 = var9["A"]
      12 [-]: JUMPIFLE R8 R7 L1; goto L1 if var8 <= var16778758
      13 [-]: LOADB R6 0 +1; var6 = false
L 1:  14 [-]: LOADB R6 1   ; var6 = true
L 2:  15 [-]: JUMPIFNOT R6 L3; goto L3 if not var6
      16 [-]: FASTCALL2 52 R0 R4 L3; 
      17 [-]: MOVE R7 R0   ; var7 = var0
      18 [-]: MOVE R8 R4   ; var8 = var4
      19 [-]: GETIMPORT R6 5; var6 = 0x33BDD652[0x23D5322F]
      20 [-]: CALL R6 3 1  ; var6(var7, var8)
L 3:  21 [-]: FORGLOOP R1 L0 2; 
      22 [-]: RETURN R0 1  ; 


; Name:            
; Defined at line: 338
; #Upvalues:       4
; #Parameters:     1
; Is_vararg:       0
; Max Stack Size:  18

       0 [-]: NEWTABLE R1 0 0; var1 = {}
       1 [-]: LOADN R4 1   ; var4 = 1
       2 [-]: GETUPVAL R5 0; var5 = upvalues[0]
       3 [-]: LENGTH R2 R5 ; var2 = #var5
       4 [-]: LOADN R3 1   ; var3 = 1
       5 [-]: FORNPREP R2 L2; nforprep start - [escape at L2] -- var2 = iterator
L 0:   6 [-]: GETUPVAL R6 1; var6 = upvalues[1]
       7 [-]: GETTABLE R5 R6 R4; var5 = var6[var4]
       8 [-]: JUMPXEQKN R5 K0 L1 NOT; 
       9 [-]: MOVE R6 R1   ; var6 = var1
      10 [-]: GETIMPORT R8 3; var8 = 0x55730E1A
      11 [-]: LOADN R9 0   ; var9 = 0
      12 [-]: LENGTH R10 R1; var10 = #var1
      13 [-]: CALL R8 3 2  ; var8 = var8(var9, var10)
      14 [-]: ADDK R7 R8 K1; var7 = var8 + 1
      15 [-]: MOVE R8 R4   ; var8 = var4
      16 [-]: FASTCALL 52 L1; 
      17 [-]: GETIMPORT R5 6; var5 = 0x33BDD652[0x23D5322F]
      18 [-]: CALL R5 4 1  ; var5(var6, var7, var8)
L 1:  19 [-]: FORNLOOP R2 L0; nforloop end - iterate + goto L0
L 2:  20 [-]: JUMPIFNOT R0 L8; goto L8 if not var0
      21 [-]: GETIMPORT R2 8; var2 = 0xCFC01047
      22 [-]: MOVE R3 R1   ; var3 = var1
      23 [-]: CALL R2 2 4  ; var2, var3, var4 = var2(var3)
      24 [-]: FORGPREP_NEXT R2 L7; 
L 3:  25 [-]: LOADB R7 1   ; var7 = true
      26 [-]: GETUPVAL R8 2; var8 = upvalues[2]
      27 [-]: CALL R8 1 2  ; var8 = var8()
      28 [-]: GETIMPORT R9 8; var9 = 0xCFC01047
      29 [-]: MOVE R10 R8  ; var10 = var8
      30 [-]: CALL R9 2 4  ; var9, var10, var11 = var9(var10)
      31 [-]: FORGPREP_NEXT R9 L5; 
L 4:  32 [-]: GETUPVAL R15 0; var15 = upvalues[0]
      33 [-]: GETTABLE R14 R15 R6; var14 = var15[var6]
      34 [-]: GETUPVAL R17 3; var17 = upvalues[3]
      35 [-]: GETTABLE R16 R17 R13; var16 = var17[var13]
      36 [-]: NAMECALL R14 R14 K9; var15 = var14; var14 = var14[0xBEBAD19F]
      37 [-]: CALL R14 3 2 ; var14 = var14(var15, var16)
      38 [-]: JUMPIFNOTLT R14 R0 L5; goto L5 if var14 >= var1798
      39 [-]: LOADB R7 0   ; var7 = false
      40 [-]: JUMP L6      ; goto L6
L 5:  41 [-]: FORGLOOP R9 L4 2; 
L 6:  42 [-]: JUMPIFNOT R7 L7; goto L7 if not var7
      43 [-]: RETURN R6 1  ; 
L 7:  44 [-]: FORGLOOP R2 L3 2; 
L 8:  45 [-]: GETTABLEN R2 R1 1; var2 = var1[1]
      46 [-]: RETURN R2 1  ; 


; Name:            
; Defined at line: 363
; #Upvalues:       5
; #Parameters:     1
; Is_vararg:       0
; Max Stack Size:  6

       0 [-]: GETUPVAL R3 0; var3 = upvalues[0]
       1 [-]: GETTABLE R2 R3 R0; var2 = var3[var0]
       2 [-]: JUMPIFNOT R2 L1; goto L1 if not var2
       3 [-]: GETUPVAL R4 0; var4 = upvalues[0]
       4 [-]: GETTABLE R3 R4 R0; var3 = var4[var0]
       5 [-]: GETUPVAL R5 1; var5 = upvalues[1]
       6 [-]: GETTABLEKS R4 R5 K0; var4 = var5["A"]
       7 [-]: JUMPIFLE R4 R3 L0; goto L0 if var4 <= var16777734
       8 [-]: LOADB R2 0 +1; var2 = false
L 0:   9 [-]: LOADB R2 1   ; var2 = true
L 1:  10 [-]: FASTCALL2K 1 R2 K1 L2; 
      11 [-]: LOADK R3 K1  ; var3 = "ERROR: invalid excavator id"
      12 [-]: GETIMPORT R1 3; var1 = 0x60CCE7B4
      13 [-]: CALL R1 3 1  ; var1(var2, var3)
L 2:  14 [-]: GETUPVAL R2 2; var2 = upvalues[2]
      15 [-]: GETTABLE R1 R2 R0; var1 = var2[var0]
      16 [-]: GETUPVAL R3 3; var3 = upvalues[3]
      17 [-]: GETTABLE R2 R3 R0; var2 = var3[var0]
      18 [-]: GETUPVAL R4 4; var4 = upvalues[4]
      19 [-]: GETTABLE R3 R4 R0; var3 = var4[var0]
      20 [-]: RETURN R1 3  ; 


; Name:            
; Defined at line: 368
; #Upvalues:       2
; #Parameters:     1
; Is_vararg:       0
; Max Stack Size:  8

       0 [-]: GETIMPORT R1 1; var1 = 0xCFC01047
       1 [-]: GETUPVAL R2 0; var2 = upvalues[0]
       2 [-]: CALL R1 2 4  ; var1, var2, var3 = var1(var2)
       3 [-]: FORGPREP_NEXT R1 L1; 
L 0:   4 [-]: GETUPVAL R7 1; var7 = upvalues[1]
       5 [-]: GETTABLE R6 R7 R4; var6 = var7[var4]
       6 [-]: JUMPIFNOTEQ R6 R0 L1; goto L1 if var6 ~= var132131
       7 [-]: RETURN R4 1  ; 
L 1:   8 [-]: FORGLOOP R1 L0 2; 
       9 [-]: RETURN R0 0  ; 


; Name:            
; Defined at line: 376
; #Upvalues:       3
; #Parameters:     0
; Is_vararg:       0
; Max Stack Size:  10

       0 [-]: NEWTABLE R0 0 0; var0 = {}
       1 [-]: GETIMPORT R1 1; var1 = 0xCFC01047
       2 [-]: GETUPVAL R2 0; var2 = upvalues[0]
       3 [-]: CALL R1 2 4  ; var1, var2, var3 = var1(var2)
       4 [-]: FORGPREP_NEXT R1 L1; 
L 0:   5 [-]: GETUPVAL R7 1; var7 = upvalues[1]
       6 [-]: GETTABLEKS R6 R7 K2; var6 = var7["A"]
       7 [-]: JUMPIFNOTLE R6 R5 L1; goto L1 if var6 > var133436
       8 [-]: GETUPVAL R9 2; var9 = upvalues[2]
       9 [-]: GETTABLE R8 R9 R4; var8 = var9[var4]
      10 [-]: FASTCALL2 52 R0 R8 L1; 
      11 [-]: MOVE R7 R0   ; var7 = var0
      12 [-]: GETIMPORT R6 5; var6 = 0x33BDD652[0x23D5322F]
      13 [-]: CALL R6 3 1  ; var6(var7, var8)
L 1:  14 [-]: FORGLOOP R1 L0 2; 
      15 [-]: RETURN R0 1  ; 


; Name:            
; Defined at line: 386
; #Upvalues:       2
; #Parameters:     0
; Is_vararg:       0
; Max Stack Size:  8

       0 [-]: LOADN R0 0   ; var0 = 0
       1 [-]: GETIMPORT R1 1; var1 = 0xCFC01047
       2 [-]: GETUPVAL R2 0; var2 = upvalues[0]
       3 [-]: CALL R1 2 4  ; var1, var2, var3 = var1(var2)
       4 [-]: FORGPREP_NEXT R1 L1; 
L 0:   5 [-]: GETUPVAL R7 1; var7 = upvalues[1]
       6 [-]: GETTABLEKS R6 R7 K2; var6 = var7["A"]
       7 [-]: JUMPIFNOTLE R6 R5 L1; goto L1 if var6 > var50331656
       8 [-]: ADDK R0 R0 K3; var0 = var0 + 1
L 1:   9 [-]: FORGLOOP R1 L0 2; 
      10 [-]: RETURN R0 1  ; 


; Name:            
; Defined at line: 396
; #Upvalues:       3
; #Parameters:     1
; Is_vararg:       0
; Max Stack Size:  8

       0 [-]: LOADN R3 1   ; var3 = 1
       1 [-]: GETUPVAL R4 0; var4 = upvalues[0]
       2 [-]: LENGTH R1 R4 ; var1 = #var4
       3 [-]: LOADN R2 1   ; var2 = 1
       4 [-]: FORNPREP R1 L4; nforprep start - [escape at L4] -- var1 = iterator
L 0:   5 [-]: GETUPVAL R5 0; var5 = upvalues[0]
       6 [-]: GETTABLE R4 R5 R3; var4 = var5[var3]
       7 [-]: JUMPIFNOT R4 L2; goto L2 if not var4
       8 [-]: GETUPVAL R6 0; var6 = upvalues[0]
       9 [-]: GETTABLE R5 R6 R3; var5 = var6[var3]
      10 [-]: GETUPVAL R7 1; var7 = upvalues[1]
      11 [-]: GETTABLEKS R6 R7 K0; var6 = var7["A"]
      12 [-]: JUMPIFLE R6 R5 L1; goto L1 if var6 <= var16778246
      13 [-]: LOADB R4 0 +1; var4 = false
L 1:  14 [-]: LOADB R4 1   ; var4 = true
L 2:  15 [-]: JUMPIFNOT R4 L3; goto L3 if not var4
      16 [-]: GETUPVAL R5 2; var5 = upvalues[2]
      17 [-]: GETTABLE R4 R5 R3; var4 = var5[var3]
      18 [-]: JUMPIFNOTEQ R4 R0 L3; goto L3 if var4 ~= var131875
      19 [-]: RETURN R3 1  ; 
L 3:  20 [-]: FORNLOOP R1 L0; nforloop end - iterate + goto L0
L 4:  21 [-]: RETURN R0 0  ; 


; Name:            
; Defined at line: 406
; #Upvalues:       2
; #Parameters:     1
; Is_vararg:       0
; Max Stack Size:  6

       0 [-]: GETUPVAL R4 0; var4 = upvalues[0]
       1 [-]: GETTABLE R3 R4 R0; var3 = var4[var0]
       2 [-]: GETUPVAL R5 1; var5 = upvalues[1]
       3 [-]: GETTABLEKS R4 R5 K1; var4 = var5["A"]
       4 [-]: SUB R2 R3 R4 ; var2 = var3 - var4
       5 [-]: ADDK R1 R2 K0; var1 = var2 + 1
       6 [-]: RETURN R1 1  ; 


; Name:            
; Defined at line: 411
; #Upvalues:       1
; #Parameters:     1
; Is_vararg:       0
; Max Stack Size:  6

       0 [-]: GETUPVAL R4 0; var4 = upvalues[0]
       1 [-]: LENGTH R3 R4 ; var3 = #var4
       2 [-]: JUMPIFLE R0 R3 L0; goto L0 if var0 <= var16777734
       3 [-]: LOADB R2 0 +1; var2 = false
L 0:   4 [-]: LOADB R2 1   ; var2 = true
L 1:   5 [-]: FASTCALL2K 1 R2 K0 L2; 
       6 [-]: LOADK R3 K0  ; var3 = "ERROR: id is bigger that amount of waypoints"
       7 [-]: GETIMPORT R1 2; var1 = 0x60CCE7B4
       8 [-]: CALL R1 3 1  ; var1(var2, var3)
L 2:   9 [-]: GETUPVAL R2 0; var2 = upvalues[0]
      10 [-]: GETTABLE R1 R2 R0; var1 = var2[var0]
      11 [-]: LOADNIL R2   ; var2 = nil
      12 [-]: LOADNIL R3   ; var3 = nil
      13 [-]: FASTCALL1 64 R2 L3; 
      14 [-]: MOVE R5 R2   ; var5 = var2
      15 [-]: GETIMPORT R4 4; var4 = 0x7B998233
      16 [-]: CALL R4 2 2  ; var4 = var4(var5)
L 3:  17 [-]: JUMPIFNOT R4 L4; goto L4 if not var4
      18 [-]: NAMECALL R4 R1 K5; var5 = var1; var4 = var1[0xD1586535]
      19 [-]: CALL R4 2 2  ; var4 = var4(var5)
      20 [-]: MOVE R2 R4   ; var2 = var4
      21 [-]: NAMECALL R4 R1 K6; var5 = var1; var4 = var1[0xCB3851B8]
      22 [-]: CALL R4 2 2  ; var4 = var4(var5)
      23 [-]: MOVE R3 R4   ; var3 = var4
L 4:  24 [-]: RETURN R2 2  ; 


; Name:            
; Defined at line: 422
; #Upvalues:       4
; #Parameters:     2
; Is_vararg:       0
; Max Stack Size:  10

       0 [-]: GETUPVAL R5 0; var5 = upvalues[0]
       1 [-]: GETTABLE R4 R5 R0; var4 = var5[var0]
       2 [-]: GETUPVAL R6 1; var6 = upvalues[1]
       3 [-]: GETTABLEKS R5 R6 K1; var5 = var6["A"]
       4 [-]: SUB R3 R4 R5 ; var3 = var4 - var5
       5 [-]: ADDK R2 R3 K0; var2 = var3 + 1
       6 [-]: GETUPVAL R4 2; var4 = upvalues[2]
       7 [-]: GETTABLE R3 R4 R2; var3 = var4[var2]
       8 [-]: FASTCALL1 64 R3 L0; 
       9 [-]: MOVE R5 R3   ; var5 = var3
      10 [-]: GETIMPORT R4 3; var4 = 0x7B998233
      11 [-]: CALL R4 2 2  ; var4 = var4(var5)
L 0:  12 [-]: JUMPIFNOT R4 L2; goto L2 if not var4
      13 [-]: JUMPIFNOT R1 L1; goto L1 if not var1
      14 [-]: RETURN R0 0  ; 
L 1:  15 [-]: GETUPVAL R4 3; var4 = upvalues[3]
      16 [-]: CALL R4 1 1  ; var4()
      17 [-]: GETIMPORT R4 5; var4 = 0x3D106989
      18 [-]: LOADK R6 K6  ; var6 = "ID: "
      19 [-]: MOVE R7 R0   ; var7 = var0
      20 [-]: CONCAT R5 R6 R7; var5 = var6 .. var7
      21 [-]: CALL R4 2 1  ; var4(var5)
      22 [-]: LOADB R5 0   ; var5 = false
      23 [-]: FASTCALL2K 1 R5 K7 L2; 
      24 [-]: LOADK R6 K7  ; var6 = "ERROR: null hud info"
      25 [-]: GETIMPORT R4 9; var4 = 0x60CCE7B4
      26 [-]: CALL R4 3 1  ; var4(var5, var6)
L 2:  27 [-]: GETIMPORT R4 5; var4 = 0x3D106989
      28 [-]: LOADK R6 K10 ; var6 = "Removing hud for id "
      29 [-]: MOVE R7 R0   ; var7 = var0
      30 [-]: LOADK R8 K11 ; var8 = " with index "
      31 [-]: MOVE R9 R2   ; var9 = var2
      32 [-]: CONCAT R5 R6 R9; var5 = var6 .. var9
      33 [-]: CALL R4 2 1  ; var4(var5)
      34 [-]: GETIMPORT R4 14; var4 = _T["RemoveHudTracker"]
      35 [-]: GETTABLEN R5 R3 1; var5 = var3[1]
      36 [-]: CALL R4 2 1  ; var4(var5)
      37 [-]: GETIMPORT R4 14; var4 = _T["RemoveHudTracker"]
      38 [-]: GETTABLEN R5 R3 2; var5 = var3[2]
      39 [-]: CALL R4 2 1  ; var4(var5)
      40 [-]: GETUPVAL R4 2; var4 = upvalues[2]
      41 [-]: LOADNIL R5   ; var5 = nil
      42 [-]: SETTABLE R5 R4 R2; var5[var4] = var2
      43 [-]: RETURN R0 0  ; 


; Name:            
; Defined at line: 439
; #Upvalues:       9
; #Parameters:     1
; Is_vararg:       0
; Max Stack Size:  11

       0 [-]: GETIMPORT R1 1; var1 = 0x3D106989
       1 [-]: LOADK R3 K2  ; var3 = "AddExcavatorLabel "
       2 [-]: MOVE R4 R0   ; var4 = var0
       3 [-]: CONCAT R2 R3 R4; var2 = var3 .. var4
       4 [-]: CALL R1 2 1  ; var1(var2)
       5 [-]: GETUPVAL R4 0; var4 = upvalues[0]
       6 [-]: GETTABLE R3 R4 R0; var3 = var4[var0]
       7 [-]: GETUPVAL R5 1; var5 = upvalues[1]
       8 [-]: GETTABLEKS R4 R5 K4; var4 = var5["A"]
       9 [-]: SUB R2 R3 R4 ; var2 = var3 - var4
      10 [-]: ADDK R1 R2 K3; var1 = var2 + 1
      11 [-]: GETIMPORT R2 1; var2 = 0x3D106989
      12 [-]: LOADK R4 K5  ; var4 = "Given index: "
      13 [-]: MOVE R5 R1   ; var5 = var1
      14 [-]: CONCAT R3 R4 R5; var3 = var4 .. var5
      15 [-]: CALL R2 2 1  ; var2(var3)
      16 [-]: GETUPVAL R5 0; var5 = upvalues[0]
      17 [-]: GETTABLE R4 R5 R0; var4 = var5[var0]
      18 [-]: JUMPIFNOT R4 L1; goto L1 if not var4
      19 [-]: GETUPVAL R6 0; var6 = upvalues[0]
      20 [-]: GETTABLE R5 R6 R0; var5 = var6[var0]
      21 [-]: GETUPVAL R7 1; var7 = upvalues[1]
      22 [-]: GETTABLEKS R6 R7 K4; var6 = var7["A"]
      23 [-]: JUMPIFLE R6 R5 L0; goto L0 if var6 <= var16778246
      24 [-]: LOADB R4 0 +1; var4 = false
L 0:  25 [-]: LOADB R4 1   ; var4 = true
L 1:  26 [-]: FASTCALL2K 1 R4 K6 L2; 
      27 [-]: LOADK R5 K6  ; var5 = "ERROR: invalid excavator id"
      28 [-]: GETIMPORT R3 8; var3 = 0x60CCE7B4
      29 [-]: CALL R3 3 1  ; var3(var4, var5)
L 2:  30 [-]: GETUPVAL R3 2; var3 = upvalues[2]
      31 [-]: GETTABLE R2 R3 R0; var2 = var3[var0]
      32 [-]: GETUPVAL R4 3; var4 = upvalues[3]
      33 [-]: GETTABLE R3 R4 R0; var3 = var4[var0]
      34 [-]: GETUPVAL R4 4; var4 = upvalues[4]
      35 [-]: GETTABLE R3 R4 R0; var3 = var4[var0]
      36 [-]: LOADK R4 K9  ; var4 = "DynamicExcavationInfo"
      37 [-]: MOVE R5 R1   ; var5 = var1
      38 [-]: CONCAT R3 R4 R5; var3 = var4 .. var5
      39 [-]: NEWTABLE R4 0 0; var4 = {}
      40 [-]: GETIMPORT R5 12; var5 = _T["AddHudTracker"]
      41 [-]: MOVE R7 R3   ; var7 = var3
      42 [-]: LOADK R8 K13 ; var8 = "health"
      43 [-]: CONCAT R6 R7 R8; var6 = var7 .. var8
      44 [-]: GETUPVAL R8 5; var8 = upvalues[5]
      45 [-]: GETTABLEKS R7 R8 K14; var7 = var8["HT_HEALTH_TRACKER"]
      46 [-]: LOADK R8 K15 ; var8 = 0.15000000596046448
      47 [-]: LOADN R9 10  ; var9 = 10
      48 [-]: LOADB R10 1  ; var10 = true
      49 [-]: CALL R5 6 2  ; var5 = var5(var6, var7, var8, var9, var10)
      50 [-]: SETTABLEN R5 R4 1; SETTABLEN R5 R4 1
      51 [-]: GETTABLEN R6 R4 1; var6 = var4[1]
      52 [-]: GETTABLEKS R5 R6 K16; var5 = var6["SetOffset"]
      53 [-]: LOADN R6 5   ; var6 = 5
      54 [-]: LOADN R7 0   ; var7 = 0
      55 [-]: CALL R5 3 1  ; var5(var6, var7)
      56 [-]: GETTABLEN R6 R4 1; var6 = var4[1]
      57 [-]: GETTABLEKS R5 R6 K17; var5 = var6["SetTarget"]
      58 [-]: MOVE R6 R2   ; var6 = var2
      59 [-]: CALL R5 2 1  ; var5(var6)
      60 [-]: GETTABLEN R6 R4 1; var6 = var4[1]
      61 [-]: GETTABLEKS R5 R6 K18; var5 = var6["SetHealthWarningThreshold"]
      62 [-]: LOADN R6 20  ; var6 = 20
      63 [-]: LOADB R7 0   ; var7 = false
      64 [-]: CALL R5 3 1  ; var5(var6, var7)
      65 [-]: GETTABLEN R6 R4 1; var6 = var4[1]
      66 [-]: GETTABLEKS R5 R6 K19; var5 = var6["SetNameOverride"]
      67 [-]: GETUPVAL R7 6; var7 = upvalues[6]
      68 [-]: GETTABLEKS R6 R7 K20; var6 = var7["EXCAVATOR_OBJECT"]
      69 [-]: CALL R5 2 1  ; var5(var6)
      70 [-]: GETTABLEN R6 R4 1; var6 = var4[1]
      71 [-]: GETTABLEKS R5 R6 K21; var5 = var6["SetNameFormat"]
      72 [-]: GETUPVAL R9 7; var9 = upvalues[7]
      73 [-]: GETTABLE R7 R9 R1; var7 = var9[var1]
      74 [-]: LOADK R8 K22 ; var8 = " |NAME|"
      75 [-]: CONCAT R6 R7 R8; var6 = var7 .. var8
      76 [-]: CALL R5 2 1  ; var5(var6)
      77 [-]: GETIMPORT R5 12; var5 = _T["AddHudTracker"]
      78 [-]: MOVE R7 R3   ; var7 = var3
      79 [-]: LOADK R8 K23 ; var8 = "label"
      80 [-]: CONCAT R6 R7 R8; var6 = var7 .. var8
      81 [-]: GETUPVAL R8 5; var8 = upvalues[5]
      82 [-]: GETTABLEKS R7 R8 K24; var7 = var8["HT_LABEL"]
      83 [-]: LOADK R8 K15 ; var8 = 0.15000000596046448
      84 [-]: LOADN R9 10  ; var9 = 10
      85 [-]: LOADB R10 1  ; var10 = true
      86 [-]: CALL R5 6 2  ; var5 = var5(var6, var7, var8, var9, var10)
      87 [-]: SETTABLEN R5 R4 2; SETTABLEN R5 R4 2
      88 [-]: GETTABLEN R6 R4 2; var6 = var4[2]
      89 [-]: GETTABLEKS R5 R6 K16; var5 = var6["SetOffset"]
      90 [-]: LOADN R6 -20 ; var6 = -20
      91 [-]: LOADN R7 -34 ; var7 = -34
      92 [-]: CALL R5 3 1  ; var5(var6, var7)
      93 [-]: GETUPVAL R5 8; var5 = upvalues[8]
      94 [-]: SETTABLE R4 R5 R1; var4[var5] = var1
      95 [-]: RETURN R0 0  ; 


; Name:            
; Defined at line: 460
; #Upvalues:       2
; #Parameters:     3
; Is_vararg:       0
; Max Stack Size:  10

       0 [-]: FASTCALL1 64 R0 L0; 
       1 [-]: MOVE R4 R0   ; var4 = var0
       2 [-]: GETIMPORT R3 1; var3 = 0x7B998233
       3 [-]: CALL R3 2 2  ; var3 = var3(var4)
L 0:   4 [-]: JUMPIFNOT R3 L2; goto L2 if not var3
       5 [-]: LOADB R3 0   ; var3 = false
       6 [-]: JUMPIF R3 L1 ; goto L1 if var3
       7 [-]: GETIMPORT R3 3; var3 = 0x484742B6
       8 [-]: LOADK R4 K4  ; var4 = "ERROR: avatar is null"
       9 [-]: CALL R3 2 1  ; var3(var4)
L 1:  10 [-]: RETURN R0 0  ; 
L 2:  11 [-]: NAMECALL R3 R0 K5; var4 = var0; var3 = var0[0x1AC1655C]
      12 [-]: CALL R3 2 2  ; var3 = var3(var4)
      13 [-]: FASTCALL1 64 R3 L3; 
      14 [-]: MOVE R5 R3   ; var5 = var3
      15 [-]: GETIMPORT R4 1; var4 = 0x7B998233
      16 [-]: CALL R4 2 2  ; var4 = var4(var5)
L 3:  17 [-]: JUMPIFNOT R4 L4; goto L4 if not var4
      18 [-]: GETIMPORT R4 7; var4 = 0x3D106989
      19 [-]: LOADK R6 K8  ; var6 = "Avatar name is: "
      20 [-]: NAMECALL R7 R0 K9; var8 = var0; var7 = var0[0xE223E2B1]
      21 [-]: CALL R7 2 2  ; var7 = var7(var8)
      22 [-]: CONCAT R5 R6 R7; var5 = var6 .. var7
      23 [-]: CALL R4 2 1  ; var4(var5)
      24 [-]: GETIMPORT R4 3; var4 = 0x484742B6
      25 [-]: LOADK R5 K10 ; var5 = "ERROR: Excavator has null damage control"
      26 [-]: CALL R4 2 1  ; var4(var5)
      27 [-]: RETURN R0 0  ; 
L 4:  28 [-]: JUMPIFNOT R1 L5; goto L5 if not var1
      29 [-]: GETIMPORT R6 12; var6 = 0x0469F296
      30 [-]: LOADK R7 K13 ; var7 = "DynamicSurvivorsRetreatInvul"
      31 [-]: CALL R6 2 2  ; var6 = var6(var7)
      32 [-]: LOADN R7 25  ; var7 = 25
      33 [-]: LOADN R8 6   ; var8 = 6
      34 [-]: LOADN R9 0   ; var9 = 0
      35 [-]: NAMECALL R4 R3 K14; var5 = var3; var4 = var3[0xA383DE31]
      36 [-]: CALL R4 6 1  ; var4(var5, var6, var7, var8, var9)
      37 [-]: JUMPIFNOT R2 L6; goto L6 if not var2
      38 [-]: LOADN R4 0   ; var4 = 0
      39 [-]: JUMPIFNOTLT R4 R2 L6; goto L6 if var4 >= var1084
      40 [-]: GETUPVAL R4 0; var4 = upvalues[0]
      41 [-]: MOVE R6 R2   ; var6 = var2
      42 [-]: NEWCLOSURE R7 P0; 
      43 [-]: CAPTURE UPVAL U1; 
      44 [-]: CAPTURE VAL R0; 
      45 [-]: NAMECALL R4 R4 K15; var5 = var4; var4 = var4[0xBD2E96EA]
      46 [-]: CALL R4 4 1  ; var4(var5, var6, var7)
      47 [-]: RETURN R0 0  ; 
L 5:  48 [-]: GETIMPORT R6 12; var6 = 0x0469F296
      49 [-]: LOADK R7 K13 ; var7 = "DynamicSurvivorsRetreatInvul"
      50 [-]: CALL R6 2 0  ; var6, ... = var6(var7)
      51 [-]: NAMECALL R4 R3 K16; var5 = var3; var4 = var3[0x8E3E343E]
      52 [-]: CALL R4 0 1  ; var4(var5, ...)
L 6:  53 [-]: RETURN R0 0  ; 


; Name:            
; Defined at line: 483
; #Upvalues:       3
; #Parameters:     2
; Is_vararg:       0
; Max Stack Size:  11

       0 [-]: GETUPVAL R5 0; var5 = upvalues[0]
       1 [-]: GETUPVAL R9 1; var9 = upvalues[1]
       2 [-]: GETTABLE R8 R9 R1; var8 = var9[var1]
       3 [-]: GETUPVAL R10 2; var10 = upvalues[2]
       4 [-]: GETTABLEKS R9 R10 K1; var9 = var10["A"]
       5 [-]: SUB R7 R8 R9 ; var7 = var8 - var9
       6 [-]: ADDK R6 R7 K0; var6 = var7 + 1
       7 [-]: GETTABLE R4 R5 R6; var4 = var5[var6]
       8 [-]: GETIMPORT R5 3; var5 = EMPTY_SYMBOL
       9 [-]: NAMECALL R2 R0 K4; var3 = var0; var2 = var0[0x47901F07]
      10 [-]: CALL R2 4 1  ; var2(var3, var4, var5)
      11 [-]: GETIMPORT R2 6; var2 = 0x11A19C5E
      12 [-]: MOVE R3 R0   ; var3 = var0
      13 [-]: LOADK R4 K7  ; var4 = "OnKilled"
      14 [-]: CALL R2 3 1  ; var2(var3, var4)
      15 [-]: GETIMPORT R4 9; var4 = gContextActionType
      16 [-]: NAMECALL R2 R0 K10; var3 = var0; var2 = var0[0xC9F6A7D7]
      17 [-]: CALL R2 3 2  ; var2 = var2(var3, var4)
      18 [-]: GETIMPORT R3 6; var3 = 0x11A19C5E
      19 [-]: MOVE R4 R2   ; var4 = var2
      20 [-]: LOADK R5 K11 ; var5 = "OnActivated"
      21 [-]: CALL R3 3 1  ; var3(var4, var5)
      22 [-]: RETURN R0 0  ; 


; Name:            
; Defined at line: 490
; #Upvalues:       6
; #Parameters:     2
; Is_vararg:       0
; Max Stack Size:  12

       0 [-]: GETUPVAL R5 0; var5 = upvalues[0]
       1 [-]: GETTABLE R4 R5 R0; var4 = var5[var0]
       2 [-]: JUMPIFNOT R4 L1; goto L1 if not var4
       3 [-]: GETUPVAL R6 0; var6 = upvalues[0]
       4 [-]: GETTABLE R5 R6 R0; var5 = var6[var0]
       5 [-]: GETUPVAL R7 1; var7 = upvalues[1]
       6 [-]: GETTABLEKS R6 R7 K0; var6 = var7["A"]
       7 [-]: JUMPIFLE R6 R5 L0; goto L0 if var6 <= var16778246
       8 [-]: LOADB R4 0 +1; var4 = false
L 0:   9 [-]: LOADB R4 1   ; var4 = true
L 1:  10 [-]: FASTCALL2K 1 R4 K1 L2; 
      11 [-]: LOADK R5 K1  ; var5 = "ERROR: invalid excavator id"
      12 [-]: GETIMPORT R3 3; var3 = 0x60CCE7B4
      13 [-]: CALL R3 3 1  ; var3(var4, var5)
L 2:  14 [-]: GETUPVAL R3 2; var3 = upvalues[2]
      15 [-]: GETTABLE R2 R3 R0; var2 = var3[var0]
      16 [-]: GETUPVAL R4 3; var4 = upvalues[3]
      17 [-]: GETTABLE R3 R4 R0; var3 = var4[var0]
      18 [-]: GETUPVAL R4 4; var4 = upvalues[4]
      19 [-]: GETTABLE R3 R4 R0; var3 = var4[var0]
      20 [-]: GETIMPORT R5 5; var5 = gParticleSysType
      21 [-]: NAMECALL R3 R2 K6; var4 = var2; var3 = var2[0xC1595BD5]
      22 [-]: CALL R3 3 2  ; var3 = var3(var4, var5)
      23 [-]: GETIMPORT R6 8; var6 = gSequencerType
      24 [-]: NAMECALL R4 R2 K6; var5 = var2; var4 = var2[0xC1595BD5]
      25 [-]: CALL R4 3 2  ; var4 = var4(var5, var6)
      26 [-]: GETIMPORT R7 10; var7 = gDecorationType
      27 [-]: NAMECALL R5 R2 K11; var6 = var2; var5 = var2[0xC9F6A7D7]
      28 [-]: CALL R5 3 2  ; var5 = var5(var6, var7)
      29 [-]: GETUPVAL R6 5; var6 = upvalues[5]
      30 [-]: MOVE R7 R5   ; var7 = var5
      31 [-]: MOVE R8 R3   ; var8 = var3
      32 [-]: MOVE R9 R4   ; var9 = var4
      33 [-]: MOVE R10 R1  ; var10 = var1
      34 [-]: CALL R6 5 1  ; var6(var7, var8, var9, var10)
      35 [-]: JUMPIFNOT R1 L3; goto L3 if not var1
      36 [-]: GETIMPORT R8 13; var8 = 0xDDB2A096
      37 [-]: JUMPIF R8 L4 ; goto L4 if var8
L 3:  38 [-]: LOADNIL R8   ; var8 = nil
L 4:  39 [-]: LOADB R9 0   ; var9 = false
      40 [-]: LOADN R10 2  ; var10 = 2
      41 [-]: LOADN R11 2  ; var11 = 2
      42 [-]: NAMECALL R6 R2 K14; var7 = var2; var6 = var2[0x5D985C7E]
      43 [-]: CALL R6 6 1  ; var6(var7, var8, var9, var10, var11)
      44 [-]: RETURN R0 0  ; 


; Name:            
; Defined at line: 499
; #Upvalues:       3
; #Parameters:     0
; Is_vararg:       0
; Max Stack Size:  18

       0 [-]: GETUPVAL R3 0; var3 = upvalues[0]
       1 [-]: GETTABLEKS R2 R3 K1; var2 = var3["A"]
       2 [-]: GETUPVAL R4 1; var4 = upvalues[1]
       3 [-]: LOADNIL R5   ; var5 = nil
       4 [-]: ORK R5 R5 K0 ; var5 = var5 or 1
       5 [-]: GETIMPORT R6 3; var6 = 0xBE190284
       6 [-]: MOVE R8 R4   ; var8 = var4
       7 [-]: LOADN R9 0   ; var9 = 0
       8 [-]: NAMECALL R6 R6 K4; var7 = var6; var6 = var6[0x0EB34C69]
       9 [-]: CALL R6 4 2  ; var6 = var6(var7, var8, var9)
      10 [-]: ADD R6 R6 R5 ; var6 = var6 + var5
      11 [-]: GETIMPORT R7 3; var7 = 0xBE190284
      12 [-]: MOVE R9 R4   ; var9 = var4
      13 [-]: MOVE R10 R6  ; var10 = var6
      14 [-]: NAMECALL R7 R7 K5; var8 = var7; var7 = var7[0x751F061D]
      15 [-]: CALL R7 4 1  ; var7(var8, var9, var10)
      16 [-]: MOVE R3 R6   ; var3 = var6
      17 [-]: ADD R1 R2 R3 ; var1 = var2 + var3
      18 [-]: SUBK R0 R1 K0; var0 = var1 - 1
      19 [-]: GETIMPORT R1 7; var1 = 0xCFC01047
      20 [-]: GETUPVAL R2 2; var2 = upvalues[2]
      21 [-]: CALL R1 2 4  ; var1, var2, var3 = var1(var2)
      22 [-]: FORGPREP_NEXT R1 L5; 
L 0:  23 [-]: JUMPIFNOTEQ R5 R0 L5; goto L5 if var5 ~= var591393
      24 [-]: GETIMPORT R6 9; var6 = 0x3D106989
      25 [-]: LOADK R7 K10 ; var7 = "Default next status was used"
      26 [-]: CALL R6 2 1  ; var6(var7)
      27 [-]: NEWTABLE R6 0 5; var6 = {}
      28 [-]: GETUPVAL R8 0; var8 = upvalues[0]
      29 [-]: GETTABLEKS R7 R8 K1; var7 = var8["A"]
      30 [-]: GETUPVAL R9 0; var9 = upvalues[0]
      31 [-]: GETTABLEKS R8 R9 K11; var8 = var9["B"]
      32 [-]: GETUPVAL R10 0; var10 = upvalues[0]
      33 [-]: GETTABLEKS R9 R10 K12; var9 = var10["C"]
      34 [-]: GETUPVAL R11 0; var11 = upvalues[0]
      35 [-]: GETTABLEKS R10 R11 K13; var10 = var11["D"]
      36 [-]: GETUPVAL R12 0; var12 = upvalues[0]
      37 [-]: GETTABLEKS R11 R12 K14; var11 = var12["E"]
      38 [-]: SETLIST R6 R7 5 [1]; var6[1] = var7; var6[2] = var8; var6[3] = var9; var6[4] = var10; var6[5] = var11; var6[6] = var12; 
      39 [-]: GETIMPORT R7 7; var7 = 0xCFC01047
      40 [-]: GETUPVAL R8 2; var8 = upvalues[2]
      41 [-]: CALL R7 2 4  ; var7, var8, var9 = var7(var8)
      42 [-]: FORGPREP_NEXT R7 L4; 
L 1:  43 [-]: LENGTH R14 R6; var14 = #var6
      44 [-]: LOADN R12 1  ; var12 = 1
      45 [-]: LOADN R13 -1 ; var13 = -1
      46 [-]: FORNPREP R12 L4; nforprep start - [escape at L4] -- var12 = iterator
L 2:  47 [-]: GETTABLE R15 R6 R14; var15 = var6[var14]
      48 [-]: JUMPIFNOTEQ R11 R15 L3; goto L3 if var11 ~= var1117985
      49 [-]: GETIMPORT R15 17; var15 = 0x33BDD652[0x9C1F3B5A]
      50 [-]: MOVE R16 R6  ; var16 = var6
      51 [-]: MOVE R17 R14 ; var17 = var14
      52 [-]: CALL R15 3 1 ; var15(var16, var17)
      53 [-]: JUMP L4      ; goto L4
L 3:  54 [-]: FORNLOOP R12 L2; nforloop end - iterate + goto L2
L 4:  55 [-]: FORGLOOP R7 L1 2; 
      56 [-]: GETTABLEN R0 R6 1; var0 = var6[1]
      57 [-]: RETURN R0 1  ; 
L 5:  58 [-]: FORGLOOP R1 L0 2; 
      59 [-]: RETURN R0 1  ; 


; Name:            
; Defined at line: 523
; #Upvalues:       15
; #Parameters:     2
; Is_vararg:       0
; Max Stack Size:  18

       0 [-]: MOVE R2 R0   ; var2 = var0
       1 [-]: JUMPIF R2 L2 ; goto L2 if var2
       2 [-]: GETUPVAL R2 0; var2 = upvalues[0]
       3 [-]: GETUPVAL R4 1; var4 = upvalues[1]
       4 [-]: GETIMPORT R8 1; var8 = 0xE7F2B02F
       5 [-]: NAMECALL R8 R8 K2; var9 = var8; var8 = var8[0xEBE2F513]
       6 [-]: CALL R8 2 2  ; var8 = var8(var9)
       7 [-]: GETIMPORT R9 4; var9 = 0x9BA7909F
       8 [-]: LOADK R11 K5 ; var11 = "Server.NumVirtualTestClients"
       9 [-]: NAMECALL R9 R9 K6; var10 = var9; var9 = var9[0x8151451D]
      10 [-]: CALL R9 3 2  ; var9 = var9(var10, var11)
      11 [-]: ADD R7 R8 R9 ; var7 = var8 + var9
      12 [-]: FASTCALL2K 18 R7 K7 L0; 
      13 [-]: LOADK R8 K7  ; var8 = 1
      14 [-]: GETIMPORT R6 10; var6 = 0x5BCED4C4[0xB62ECFE0]
      15 [-]: CALL R6 3 2  ; var6 = var6(var7, var8)
L 0:  16 [-]: FASTCALL2K 19 R6 K11 L1; 
      17 [-]: LOADK R7 K11 ; var7 = 4
      18 [-]: GETIMPORT R5 13; var5 = 0x5BCED4C4[0xAC1B386A]
      19 [-]: CALL R5 3 2  ; var5 = var5(var6, var7)
L 1:  20 [-]: GETTABLE R3 R4 R5; var3 = var4[var5]
      21 [-]: CALL R2 2 2  ; var2 = var2(var3)
L 2:  22 [-]: MOVE R0 R2   ; var0 = var2
      23 [-]: GETIMPORT R2 15; var2 = 0x3D106989
      24 [-]: LOADK R4 K16 ; var4 = "Creating excavator with id "
      25 [-]: MOVE R5 R0   ; var5 = var0
      26 [-]: CONCAT R3 R4 R5; var3 = var4 .. var5
      27 [-]: CALL R2 2 1  ; var2(var3)
      28 [-]: MOVE R4 R0   ; var4 = var0
      29 [-]: GETUPVAL R8 2; var8 = upvalues[2]
      30 [-]: LENGTH R7 R8 ; var7 = #var8
      31 [-]: JUMPIFLE R4 R7 L3; goto L3 if var4 <= var16778758
      32 [-]: LOADB R6 0 +1; var6 = false
L 3:  33 [-]: LOADB R6 1   ; var6 = true
L 4:  34 [-]: FASTCALL2K 1 R6 K17 L5; 
      35 [-]: LOADK R7 K17 ; var7 = "ERROR: id is bigger that amount of waypoints"
      36 [-]: GETIMPORT R5 19; var5 = 0x60CCE7B4
      37 [-]: CALL R5 3 1  ; var5(var6, var7)
L 5:  38 [-]: GETUPVAL R6 2; var6 = upvalues[2]
      39 [-]: GETTABLE R5 R6 R4; var5 = var6[var4]
      40 [-]: LOADNIL R6   ; var6 = nil
      41 [-]: LOADNIL R7   ; var7 = nil
      42 [-]: FASTCALL1 64 R6 L6; 
      43 [-]: MOVE R9 R6   ; var9 = var6
      44 [-]: GETIMPORT R8 21; var8 = 0x7B998233
      45 [-]: CALL R8 2 2  ; var8 = var8(var9)
L 6:  46 [-]: JUMPIFNOT R8 L7; goto L7 if not var8
      47 [-]: NAMECALL R8 R5 K22; var9 = var5; var8 = var5[0xD1586535]
      48 [-]: CALL R8 2 2  ; var8 = var8(var9)
      49 [-]: MOVE R6 R8   ; var6 = var8
      50 [-]: NAMECALL R8 R5 K23; var9 = var5; var8 = var5[0xCB3851B8]
      51 [-]: CALL R8 2 2  ; var8 = var8(var9)
      52 [-]: MOVE R7 R8   ; var7 = var8
L 7:  53 [-]: MOVE R2 R6   ; var2 = var6
      54 [-]: MOVE R3 R7   ; var3 = var7
      55 [-]: FASTCALL1 64 R2 L8; 
      56 [-]: MOVE R5 R2   ; var5 = var2
      57 [-]: GETIMPORT R4 21; var4 = 0x7B998233
      58 [-]: CALL R4 2 2  ; var4 = var4(var5)
L 8:  59 [-]: JUMPIFNOT R4 L9; goto L9 if not var4
      60 [-]: GETIMPORT R4 15; var4 = 0x3D106989
      61 [-]: LOADK R5 K24 ; var5 = "Null pos"
      62 [-]: CALL R4 2 1  ; var4(var5)
L 9:  63 [-]: GETUPVAL R4 3; var4 = upvalues[3]
      64 [-]: MOVE R6 R2   ; var6 = var2
      65 [-]: NAMECALL R4 R4 K25; var5 = var4; var4 = var4[0xC1088746]
      66 [-]: CALL R4 3 2  ; var4 = var4(var5, var6)
      67 [-]: GETUPVAL R5 3; var5 = upvalues[3]
      68 [-]: GETIMPORT R7 27; var7 = 0x872A2DDC
      69 [-]: MOVE R8 R2   ; var8 = var2
      70 [-]: MOVE R9 R3   ; var9 = var3
      71 [-]: GETIMPORT R10 29; var10 = EMPTY_SYMBOL
      72 [-]: MOVE R11 R4  ; var11 = var4
      73 [-]: NAMECALL R5 R5 K30; var6 = var5; var5 = var5[0x3ACD2A13]
      74 [-]: CALL R5 7 2  ; var5 = var5(var6, var7, var8, var9, var10, var11)
      75 [-]: NAMECALL R6 R5 K31; var7 = var5; var6 = var5[0xBB610E5B]
      76 [-]: CALL R6 2 2  ; var6 = var6(var7)
      77 [-]: NAMECALL R8 R6 K32; var9 = var6; var8 = var6[0xB40C191A]
      78 [-]: CALL R8 2 2  ; var8 = var8(var9)
      79 [-]: GETUPVAL R10 4; var10 = upvalues[4]
      80 [-]: GETIMPORT R14 1; var14 = 0xE7F2B02F
      81 [-]: NAMECALL R14 R14 K2; var15 = var14; var14 = var14[0xEBE2F513]
      82 [-]: CALL R14 2 2 ; var14 = var14(var15)
      83 [-]: GETIMPORT R15 4; var15 = 0x9BA7909F
      84 [-]: LOADK R17 K5 ; var17 = "Server.NumVirtualTestClients"
      85 [-]: NAMECALL R15 R15 K6; var16 = var15; var15 = var15[0x8151451D]
      86 [-]: CALL R15 3 2 ; var15 = var15(var16, var17)
      87 [-]: ADD R13 R14 R15; var13 = var14 + var15
      88 [-]: FASTCALL2K 18 R13 K7 L10; 
      89 [-]: LOADK R14 K7 ; var14 = 1
      90 [-]: GETIMPORT R12 10; var12 = 0x5BCED4C4[0xB62ECFE0]
      91 [-]: CALL R12 3 2 ; var12 = var12(var13, var14)
L10:  92 [-]: FASTCALL2K 19 R12 K11 L11; 
      93 [-]: LOADK R13 K11; var13 = 4
      94 [-]: GETIMPORT R11 13; var11 = 0x5BCED4C4[0xAC1B386A]
      95 [-]: CALL R11 3 2 ; var11 = var11(var12, var13)
L11:  96 [-]: GETTABLE R9 R10 R11; var9 = var10[var11]
      97 [-]: MUL R7 R8 R9 ; var7 = var8 * var9
      98 [-]: MOVE R10 R7  ; var10 = var7
      99 [-]: LOADB R11 1  ; var11 = true
     100 [-]: NAMECALL R8 R6 K33; var9 = var6; var8 = var6[0xA31BA7EE]
     101 [-]: CALL R8 4 1  ; var8(var9, var10, var11)
     102 [-]: MOVE R10 R7  ; var10 = var7
     103 [-]: LOADB R11 1  ; var11 = true
     104 [-]: NAMECALL R8 R6 K34; var9 = var6; var8 = var6[0x014DB014]
     105 [-]: CALL R8 4 1  ; var8(var9, var10, var11)
     106 [-]: GETUPVAL R8 5; var8 = upvalues[5]
     107 [-]: SETTABLE R6 R8 R0; var6[var8] = var0
     108 [-]: JUMPIFNOT R1 L12; goto L12 if not var1
     109 [-]: JUMP L13     ; goto L13
L12: 110 [-]: GETUPVAL R8 6; var8 = upvalues[6]
     111 [-]: GETUPVAL R9 7; var9 = upvalues[7]
     112 [-]: CALL R9 1 2  ; var9 = var9()
     113 [-]: SETTABLE R9 R8 R0; var9[var8] = var0
     114 [-]: GETUPVAL R8 8; var8 = upvalues[8]
     115 [-]: LOADN R9 20  ; var9 = 20
     116 [-]: SETTABLE R9 R8 R0; var9[var8] = var0
     117 [-]: GETUPVAL R8 9; var8 = upvalues[9]
     118 [-]: LOADN R9 100 ; var9 = 100
     119 [-]: SETTABLE R9 R8 R0; var9[var8] = var0
L13: 120 [-]: GETUPVAL R8 10; var8 = upvalues[10]
     121 [-]: MOVE R9 R0   ; var9 = var0
     122 [-]: LOADB R10 1  ; var10 = true
     123 [-]: CALL R8 3 1  ; var8(var9, var10)
     124 [-]: GETUPVAL R8 11; var8 = upvalues[11]
     125 [-]: MOVE R9 R0   ; var9 = var0
     126 [-]: CALL R8 2 1  ; var8(var9)
     127 [-]: GETUPVAL R8 12; var8 = upvalues[12]
     128 [-]: MOVE R9 R6   ; var9 = var6
     129 [-]: LOADB R10 1  ; var10 = true
     130 [-]: LOADN R11 5  ; var11 = 5
     131 [-]: CALL R8 4 1  ; var8(var9, var10, var11)
     132 [-]: MOVE R8 R0   ; var8 = var0
     133 [-]: GETUPVAL R12 13; var12 = upvalues[13]
     134 [-]: GETUPVAL R16 6; var16 = upvalues[6]
     135 [-]: GETTABLE R15 R16 R8; var15 = var16[var8]
     136 [-]: GETUPVAL R17 14; var17 = upvalues[14]
     137 [-]: GETTABLEKS R16 R17 K35; var16 = var17["A"]
     138 [-]: SUB R14 R15 R16; var14 = var15 - var16
     139 [-]: ADDK R13 R14 K7; var13 = var14 + 1
     140 [-]: GETTABLE R11 R12 R13; var11 = var12[var13]
     141 [-]: GETIMPORT R12 29; var12 = EMPTY_SYMBOL
     142 [-]: NAMECALL R9 R6 K36; var10 = var6; var9 = var6[0x47901F07]
     143 [-]: CALL R9 4 1  ; var9(var10, var11, var12)
     144 [-]: GETIMPORT R9 38; var9 = 0x11A19C5E
     145 [-]: MOVE R10 R6  ; var10 = var6
     146 [-]: LOADK R11 K39; var11 = "OnKilled"
     147 [-]: CALL R9 3 1  ; var9(var10, var11)
     148 [-]: GETIMPORT R11 41; var11 = gContextActionType
     149 [-]: NAMECALL R9 R6 K42; var10 = var6; var9 = var6[0xC9F6A7D7]
     150 [-]: CALL R9 3 2  ; var9 = var9(var10, var11)
     151 [-]: GETIMPORT R10 38; var10 = 0x11A19C5E
     152 [-]: MOVE R11 R9  ; var11 = var9
     153 [-]: LOADK R12 K43; var12 = "OnActivated"
     154 [-]: CALL R10 3 1 ; var10(var11, var12)
     155 [-]: GETIMPORT R8 15; var8 = 0x3D106989
     156 [-]: LOADK R10 K44; var10 = "Excavator created with id "
     157 [-]: MOVE R11 R0  ; var11 = var0
     158 [-]: CONCAT R9 R10 R11; var9 = var10 .. var11
     159 [-]: CALL R8 2 1  ; var8(var9)
     160 [-]: RETURN R6 1  ; 


; Name:            
; Defined at line: 554
; #Upvalues:       4
; #Parameters:     0
; Is_vararg:       0
; Max Stack Size:  3

       0 [-]: GETIMPORT R0 1; var0 = 0x3D106989
       1 [-]: LOADK R1 K2  ; var1 = "Deploying excavator"
       2 [-]: CALL R0 2 1  ; var0(var1)
       3 [-]: GETUPVAL R1 0; var1 = upvalues[0]
       4 [-]: SUBK R0 R1 K3; var0 = var1 - 1
       5 [-]: SETUPVAL R0 0; upvalues[0] = var0
       6 [-]: GETUPVAL R0 0; var0 = upvalues[0]
       7 [-]: LOADN R1 0   ; var1 = 0
       8 [-]: JUMPIFNOTLE R0 R1 L0; goto L0 if var0 > var65569
       9 [-]: GETIMPORT R0 1; var0 = 0x3D106989
      10 [-]: LOADK R1 K4  ; var1 = "No more scheduled excavators, removing timer"
      11 [-]: CALL R0 2 1  ; var0(var1)
      12 [-]: GETUPVAL R0 1; var0 = upvalues[1]
      13 [-]: GETUPVAL R2 2; var2 = upvalues[2]
      14 [-]: NAMECALL R0 R0 K5; var1 = var0; var0 = var0[0x775C858B]
      15 [-]: CALL R0 3 1  ; var0(var1, var2)
      16 [-]: LOADNIL R0   ; var0 = nil
      17 [-]: SETUPVAL R0 2; upvalues[0] = var2
L 0:  18 [-]: GETUPVAL R0 3; var0 = upvalues[3]
      19 [-]: CALL R0 1 1  ; var0()
      20 [-]: RETURN R0 0  ; 


; Name:            
; Defined at line: 565
; #Upvalues:       7
; #Parameters:     2
; Is_vararg:       0
; Max Stack Size:  11

       0 [-]: JUMPIF R0 L5 ; goto L5 if var0
       1 [-]: LOADN R3 0   ; var3 = 0
       2 [-]: GETIMPORT R4 1; var4 = 0xCFC01047
       3 [-]: GETUPVAL R5 0; var5 = upvalues[0]
       4 [-]: CALL R4 2 4  ; var4, var5, var6 = var4(var5)
       5 [-]: FORGPREP_NEXT R4 L1; 
L 0:   6 [-]: GETUPVAL R10 1; var10 = upvalues[1]
       7 [-]: GETTABLEKS R9 R10 K2; var9 = var10["A"]
       8 [-]: JUMPIFNOTLE R9 R8 L1; goto L1 if var9 > var50529032
       9 [-]: ADDK R3 R3 K3; var3 = var3 + 1
L 1:  10 [-]: FORGLOOP R4 L0 2; 
      11 [-]: MOVE R2 R3   ; var2 = var3
      12 [-]: GETIMPORT R6 5; var6 = 0xE7F2B02F
      13 [-]: NAMECALL R6 R6 K6; var7 = var6; var6 = var6[0xEBE2F513]
      14 [-]: CALL R6 2 2  ; var6 = var6(var7)
      15 [-]: GETIMPORT R7 8; var7 = 0x9BA7909F
      16 [-]: LOADK R9 K9  ; var9 = "Server.NumVirtualTestClients"
      17 [-]: NAMECALL R7 R7 K10; var8 = var7; var7 = var7[0x8151451D]
      18 [-]: CALL R7 3 2  ; var7 = var7(var8, var9)
      19 [-]: ADD R5 R6 R7 ; var5 = var6 + var7
      20 [-]: FASTCALL2K 18 R5 K3 L2; 
      21 [-]: LOADK R6 K3  ; var6 = 1
      22 [-]: GETIMPORT R4 13; var4 = 0x5BCED4C4[0xB62ECFE0]
      23 [-]: CALL R4 3 2  ; var4 = var4(var5, var6)
L 2:  24 [-]: FASTCALL2K 19 R4 K14 L3; 
      25 [-]: LOADK R5 K14 ; var5 = 4
      26 [-]: GETIMPORT R3 16; var3 = 0x5BCED4C4[0xAC1B386A]
      27 [-]: CALL R3 3 2  ; var3 = var3(var4, var5)
L 3:  28 [-]: GETIMPORT R6 18; var6 = 0xA8CCD011
      29 [-]: GETTABLE R5 R6 R3; var5 = var6[var3]
      30 [-]: GETIMPORT R7 20; var7 = 0xBE190284
      31 [-]: GETUPVAL R9 2; var9 = upvalues[2]
      32 [-]: LOADN R10 0  ; var10 = 0
      33 [-]: NAMECALL R7 R7 K21; var8 = var7; var7 = var7[0x0EB34C69]
      34 [-]: CALL R7 4 2  ; var7 = var7(var8, var9, var10)
      35 [-]: GETUPVAL R8 3; var8 = upvalues[3]
      36 [-]: ADD R6 R7 R8 ; var6 = var7 + var8
      37 [-]: SUB R4 R5 R6 ; var4 = var5 - var6
      38 [-]: GETIMPORT R8 23; var8 = 0x8689848D
      39 [-]: GETTABLE R7 R8 R3; var7 = var8[var3]
      40 [-]: SUB R6 R7 R2 ; var6 = var7 - var2
      41 [-]: FASTCALL2 19 R6 R4 L4; 
      42 [-]: MOVE R7 R4   ; var7 = var4
      43 [-]: GETIMPORT R5 16; var5 = 0x5BCED4C4[0xAC1B386A]
      44 [-]: CALL R5 3 2  ; var5 = var5(var6, var7)
L 4:  45 [-]: MOVE R0 R5   ; var0 = var5
L 5:  46 [-]: LOADN R2 0   ; var2 = 0
      47 [-]: JUMPIFNOTLE R0 R2 L6; goto L6 if var0 > var1638945
      48 [-]: GETIMPORT R2 25; var2 = 0x3D106989
      49 [-]: LOADK R3 K26 ; var3 = "Not scheduling excavators"
      50 [-]: CALL R2 2 1  ; var2(var3)
      51 [-]: RETURN R0 0  ; 
L 6:  52 [-]: GETIMPORT R2 25; var2 = 0x3D106989
      53 [-]: LOADK R4 K27 ; var4 = "Scheduling "
      54 [-]: MOVE R5 R0   ; var5 = var0
      55 [-]: LOADK R6 K28 ; var6 = " excavations"
      56 [-]: CONCAT R3 R4 R6; var3 = var4 .. var6
      57 [-]: CALL R2 2 1  ; var2(var3)
      58 [-]: GETUPVAL R3 3; var3 = upvalues[3]
      59 [-]: ADD R2 R3 R0 ; var2 = var3 + var0
      60 [-]: SETUPVAL R2 3; upvalues[2] = var3
      61 [-]: GETUPVAL R2 4; var2 = upvalues[4]
      62 [-]: GETUPVAL R4 5; var4 = upvalues[5]
      63 [-]: NAMECALL R2 R2 K29; var3 = var2; var2 = var2[0x5D390332]
      64 [-]: CALL R2 3 2  ; var2 = var2(var3, var4)
      65 [-]: JUMPIFNOT R2 L7; goto L7 if not var2
      66 [-]: GETIMPORT R3 25; var3 = 0x3D106989
      67 [-]: MOVE R5 R2   ; var5 = var2
      68 [-]: LOADK R6 K30 ; var6 = " until next excavator"
      69 [-]: CONCAT R4 R5 R6; var4 = var5 .. var6
      70 [-]: CALL R3 2 1  ; var3(var4)
      71 [-]: RETURN R0 0  ; 
L 7:  72 [-]: ORK R1 R1 K31; var1 = var1 or 0
      73 [-]: LOADN R4 5   ; var4 = 5
      74 [-]: ADD R3 R4 R1 ; var3 = var4 + var1
      75 [-]: GETUPVAL R4 4; var4 = upvalues[4]
      76 [-]: MOVE R6 R3   ; var6 = var3
      77 [-]: GETUPVAL R7 6; var7 = upvalues[6]
      78 [-]: LOADB R8 1   ; var8 = true
      79 [-]: NAMECALL R4 R4 K32; var5 = var4; var4 = var4[0xBD2E96EA]
      80 [-]: CALL R4 5 2  ; var4 = var4(var5, var6, var7, var8)
      81 [-]: SETUPVAL R4 5; upvalues[4] = var5
      82 [-]: GETIMPORT R4 25; var4 = 0x3D106989
      83 [-]: LOADK R6 K33 ; var6 = "Added timer for "
      84 [-]: MOVE R7 R3   ; var7 = var3
      85 [-]: LOADK R8 K34 ; var8 = " seconds"
      86 [-]: CONCAT R5 R6 R8; var5 = var6 .. var8
      87 [-]: CALL R4 2 1  ; var4(var5)
      88 [-]: RETURN R0 0  ; 


; Name:            
; Defined at line: 589
; #Upvalues:       7
; #Parameters:     0
; Is_vararg:       0
; Max Stack Size:  4

       0 [-]: GETUPVAL R0 0; var0 = upvalues[0]
       1 [-]: GETUPVAL R1 1; var1 = upvalues[1]
       2 [-]: GETUPVAL R2 2; var2 = upvalues[2]
       3 [-]: CALL R0 3 1  ; var0(var1, var2)
       4 [-]: GETUPVAL R0 0; var0 = upvalues[0]
       5 [-]: GETUPVAL R1 3; var1 = upvalues[3]
       6 [-]: GETUPVAL R2 4; var2 = upvalues[4]
       7 [-]: LOADK R3 K0  ; var3 = 0.0099999997764825821
       8 [-]: CALL R0 4 1  ; var0(var1, var2, var3)
       9 [-]: GETUPVAL R0 0; var0 = upvalues[0]
      10 [-]: GETUPVAL R1 5; var1 = upvalues[5]
      11 [-]: GETUPVAL R2 6; var2 = upvalues[6]
      12 [-]: LOADK R3 K0  ; var3 = 0.0099999997764825821
      13 [-]: CALL R0 4 1  ; var0(var1, var2, var3)
      14 [-]: RETURN R0 0  ; 


; Name:            
; Defined at line: 595
; #Upvalues:       2
; #Parameters:     0
; Is_vararg:       0
; Max Stack Size:  12

       0 [-]: GETUPVAL R0 0; var0 = upvalues[0]
       1 [-]: NAMECALL R0 R0 K0; var1 = var0; var0 = var0[0x4F88BE0F]
       2 [-]: CALL R0 2 2  ; var0 = var0(var1)
       3 [-]: LOADK R2 K1  ; var2 = "DynExcav"
       4 [-]: LOADK R3 K2  ; var3 = ": "
       5 [-]: LOADK R4 K3  ; var4 = "Reassigning all agents to storm other excavators"
       6 [-]: CONCAT R1 R2 R4; var1 = var2 .. var4
       7 [-]: GETIMPORT R2 5; var2 = 0xD644C2F1
       8 [-]: MOVE R3 R1   ; var3 = var1
       9 [-]: CALL R2 2 1  ; var2(var3)
      10 [-]: GETIMPORT R1 7; var1 = 0xC8802016
      11 [-]: MOVE R2 R0   ; var2 = var0
      12 [-]: CALL R1 2 4  ; var1, var2, var3 = var1(var2)
      13 [-]: FORGPREP_INEXT R1 L2; 
L 0:  14 [-]: NAMECALL R6 R5 K8; var7 = var5; var6 = var5[0xBB610E5B]
      15 [-]: CALL R6 2 2  ; var6 = var6(var7)
      16 [-]: GETIMPORT R7 10; var7 = 0x89326C93
      17 [-]: GETUPVAL R9 1; var9 = upvalues[1]
      18 [-]: NAMECALL R10 R6 K11; var11 = var6; var10 = var6[0xD1586535]
      19 [-]: CALL R10 2 0 ; var10, ... = var10(var11)
      20 [-]: NAMECALL R7 R7 K12; var8 = var7; var7 = var7[0xC7B81E8D]
      21 [-]: CALL R7 0 2  ; var7 = var7(var8, ...)
      22 [-]: FASTCALL1 64 R7 L1; 
      23 [-]: MOVE R9 R7   ; var9 = var7
      24 [-]: GETIMPORT R8 14; var8 = 0x7B998233
      25 [-]: CALL R8 2 2  ; var8 = var8(var9)
L 1:  26 [-]: JUMPIF R8 L2 ; goto L2 if var8
      27 [-]: MOVE R10 R7  ; var10 = var7
      28 [-]: NAMECALL R8 R5 K15; var9 = var5; var8 = var5[0xA64A1F4A]
      29 [-]: CALL R8 3 1  ; var8(var9, var10)
L 2:  30 [-]: FORGLOOP R1 L0 2 [inext]; 
      31 [-]: RETURN R0 0  ; 


; Name:            
; Defined at line: 607
; #Upvalues:       13
; #Parameters:     2
; Is_vararg:       0
; Max Stack Size:  16

       0 [-]: GETUPVAL R3 0; var3 = upvalues[0]
       1 [-]: GETTABLE R2 R3 R0; var2 = var3[var0]
       2 [-]: FASTCALL1 64 R2 L0; 
       3 [-]: MOVE R6 R2   ; var6 = var2
       4 [-]: GETIMPORT R5 1; var5 = 0x7B998233
       5 [-]: CALL R5 2 2  ; var5 = var5(var6)
L 0:   6 [-]: NOT R4 R5    ; var4 = not var5
       7 [-]: FASTCALL2K 1 R4 K2 L1; 
       8 [-]: LOADK R5 K2  ; var5 = "ERROR: null avatar when destroying excavator"
       9 [-]: GETIMPORT R3 4; var3 = 0x60CCE7B4
      10 [-]: CALL R3 3 1  ; var3(var4, var5)
L 1:  11 [-]: NAMECALL R3 R2 K5; var4 = var2; var3 = var2[0xD1586535]
      12 [-]: CALL R3 2 2  ; var3 = var3(var4)
      13 [-]: NAMECALL R4 R2 K6; var5 = var2; var4 = var2[0xA2880940]
      14 [-]: CALL R4 2 1  ; var4(var5)
      15 [-]: GETUPVAL R4 1; var4 = upvalues[1]
      16 [-]: LOADN R5 0   ; var5 = 0
      17 [-]: SETTABLE R5 R4 R0; var5[var4] = var0
      18 [-]: GETUPVAL R4 2; var4 = upvalues[2]
      19 [-]: LOADN R5 0   ; var5 = 0
      20 [-]: SETTABLE R5 R4 R0; var5[var4] = var0
      21 [-]: GETUPVAL R4 3; var4 = upvalues[3]
      22 [-]: MOVE R5 R0   ; var5 = var0
      23 [-]: MOVE R6 R1   ; var6 = var1
      24 [-]: CALL R4 3 1  ; var4(var5, var6)
      25 [-]: GETUPVAL R4 4; var4 = upvalues[4]
      26 [-]: CALL R4 1 1  ; var4()
      27 [-]: JUMPIFNOT R1 L2; goto L2 if not var1
      28 [-]: GETIMPORT R4 8; var4 = 0x3D106989
      29 [-]: LOADK R6 K9  ; var6 = "Forced destroy on excavator ID:"
      30 [-]: MOVE R7 R0   ; var7 = var0
      31 [-]: LOADK R8 K10 ; var8 = ", skipping evaluations"
      32 [-]: CONCAT R5 R6 R8; var5 = var6 .. var8
      33 [-]: CALL R4 2 1  ; var4(var5)
      34 [-]: GETUPVAL R4 5; var4 = upvalues[5]
      35 [-]: GETUPVAL R6 6; var6 = upvalues[6]
      36 [-]: GETTABLEKS R5 R6 K11; var5 = var6["NONE"]
      37 [-]: SETTABLE R5 R4 R0; var5[var4] = var0
      38 [-]: RETURN R0 0  ; 
L 2:  39 [-]: GETIMPORT R4 13; var4 = 0x89326C93
      40 [-]: GETIMPORT R6 15; var6 = 0xD02846B9
      41 [-]: MOVE R7 R3   ; var7 = var3
      42 [-]: GETIMPORT R8 17; var8 = ZERO_ROTATION
      43 [-]: LOADNIL R9   ; var9 = nil
      44 [-]: LOADNIL R10  ; var10 = nil
      45 [-]: NAMECALL R4 R4 K18; var5 = var4; var4 = var4[0x05909209]
      46 [-]: CALL R4 7 1  ; var4(var5, var6, var7, var8, var9, var10)
      47 [-]: GETIMPORT R4 20; var4 = 0xBE190284
      48 [-]: GETUPVAL R6 7; var6 = upvalues[7]
      49 [-]: LOADN R7 0   ; var7 = 0
      50 [-]: NAMECALL R4 R4 K21; var5 = var4; var4 = var4[0x0EB34C69]
      51 [-]: CALL R4 4 2  ; var4 = var4(var5, var6, var7)
      52 [-]: GETIMPORT R5 20; var5 = 0xBE190284
      53 [-]: GETUPVAL R7 8; var7 = upvalues[8]
      54 [-]: LOADN R8 0   ; var8 = 0
      55 [-]: NAMECALL R5 R5 K21; var6 = var5; var5 = var5[0x0EB34C69]
      56 [-]: CALL R5 4 2  ; var5 = var5(var6, var7, var8)
      57 [-]: ADD R6 R4 R5 ; var6 = var4 + var5
      58 [-]: GETIMPORT R8 23; var8 = 0xA8CCD011
      59 [-]: GETIMPORT R12 25; var12 = 0xE7F2B02F
      60 [-]: NAMECALL R12 R12 K26; var13 = var12; var12 = var12[0xEBE2F513]
      61 [-]: CALL R12 2 2 ; var12 = var12(var13)
      62 [-]: GETIMPORT R13 28; var13 = 0x9BA7909F
      63 [-]: LOADK R15 K29; var15 = "Server.NumVirtualTestClients"
      64 [-]: NAMECALL R13 R13 K30; var14 = var13; var13 = var13[0x8151451D]
      65 [-]: CALL R13 3 2 ; var13 = var13(var14, var15)
      66 [-]: ADD R11 R12 R13; var11 = var12 + var13
      67 [-]: FASTCALL2K 18 R11 K31 L3; 
      68 [-]: LOADK R12 K31; var12 = 1
      69 [-]: GETIMPORT R10 34; var10 = 0x5BCED4C4[0xB62ECFE0]
      70 [-]: CALL R10 3 2 ; var10 = var10(var11, var12)
L 3:  71 [-]: FASTCALL2K 19 R10 K35 L4; 
      72 [-]: LOADK R11 K35; var11 = 4
      73 [-]: GETIMPORT R9 37; var9 = 0x5BCED4C4[0xAC1B386A]
      74 [-]: CALL R9 3 2  ; var9 = var9(var10, var11)
L 4:  75 [-]: GETTABLE R7 R8 R9; var7 = var8[var9]
      76 [-]: GETUPVAL R9 9; var9 = upvalues[9]
      77 [-]: GETTABLEKS R8 R9 K38; var8 = var9[0xF3928F38]
      78 [-]: MOVE R9 R4   ; var9 = var4
      79 [-]: MOVE R10 R7  ; var10 = var7
      80 [-]: CALL R8 3 1  ; var8(var9, var10)
      81 [-]: GETUPVAL R8 10; var8 = upvalues[10]
      82 [-]: GETUPVAL R10 11; var10 = upvalues[11]
      83 [-]: GETTABLEKS R9 R10 K39; var9 = var10["EXCAVATION"]
      84 [-]: JUMPIFNOTEQ R8 R9 L5; goto L5 if var8 ~= var198404
      85 [-]: JUMPIFNOTLE R7 R6 L5; goto L5 if var7 > var788540
      86 [-]: GETUPVAL R8 12; var8 = upvalues[12]
      87 [-]: CALL R8 1 1  ; var8()
L 5:  88 [-]: RETURN R0 0  ; 


; Name:            
; Defined at line: 632
; #Upvalues:       11
; #Parameters:     1
; Is_vararg:       0
; Max Stack Size:  8

       0 [-]: GETIMPORT R1 1; var1 = 0x3D106989
       1 [-]: LOADK R3 K2  ; var3 = "Excavation failed "
       2 [-]: MOVE R4 R0   ; var4 = var0
       3 [-]: CONCAT R2 R3 R4; var2 = var3 .. var4
       4 [-]: CALL R1 2 1  ; var1(var2)
       5 [-]: GETUPVAL R1 0; var1 = upvalues[0]
       6 [-]: LOADNIL R2   ; var2 = nil
       7 [-]: ORK R2 R2 K3 ; var2 = var2 or 1
       8 [-]: GETIMPORT R3 5; var3 = 0xBE190284
       9 [-]: MOVE R5 R1   ; var5 = var1
      10 [-]: LOADN R6 0   ; var6 = 0
      11 [-]: NAMECALL R3 R3 K6; var4 = var3; var3 = var3[0x0EB34C69]
      12 [-]: CALL R3 4 2  ; var3 = var3(var4, var5, var6)
      13 [-]: ADD R3 R3 R2 ; var3 = var3 + var2
      14 [-]: GETIMPORT R4 5; var4 = 0xBE190284
      15 [-]: MOVE R6 R1   ; var6 = var1
      16 [-]: MOVE R7 R3   ; var7 = var3
      17 [-]: NAMECALL R4 R4 K7; var5 = var4; var4 = var4[0x751F061D]
      18 [-]: CALL R4 4 1  ; var4(var5, var6, var7)
      19 [-]: GETIMPORT R1 9; var1 = _T
      20 [-]: LOADB R2 0   ; var2 = false
      21 [-]: SETTABLEKS R2 R1 K10; var2["QualifiedForBountyBonus"] = var1
      22 [-]: GETUPVAL R2 1; var2 = upvalues[1]
      23 [-]: GETTABLEKS R1 R2 K11; var1 = var2[0x37317859]
      24 [-]: GETUPVAL R3 2; var3 = upvalues[2]
      25 [-]: GETTABLEKS R2 R3 K12; var2 = var3["BONUS_OBJECTIVE"]
      26 [-]: CALL R1 2 1  ; var1(var2)
      27 [-]: GETUPVAL R1 3; var1 = upvalues[3]
      28 [-]: MOVE R2 R0   ; var2 = var0
      29 [-]: CALL R1 2 1  ; var1(var2)
      30 [-]: GETUPVAL R1 4; var1 = upvalues[4]
      31 [-]: GETUPVAL R3 5; var3 = upvalues[5]
      32 [-]: GETTABLEKS R2 R3 K13; var2 = var3["DESTROYED"]
      33 [-]: SETTABLE R2 R1 R0; var2[var1] = var0
      34 [-]: GETUPVAL R1 6; var1 = upvalues[6]
      35 [-]: GETUPVAL R3 7; var3 = upvalues[7]
      36 [-]: GETTABLEKS R2 R3 K14; var2 = var3["EXCAVATION"]
      37 [-]: JUMPIFNOTEQ R1 R2 L0; goto L0 if var1 ~= var524604
      38 [-]: GETUPVAL R1 8; var1 = upvalues[8]
      39 [-]: CALL R1 1 1  ; var1()
      40 [-]: GETUPVAL R2 9; var2 = upvalues[9]
      41 [-]: GETTABLEKS R1 R2 K15; var1 = var2[0x9742B85B]
      42 [-]: GETUPVAL R2 10; var2 = upvalues[10]
      43 [-]: GETIMPORT R3 17; var3 = 0x0469F296
      44 [-]: LOADK R4 K18 ; var4 = "ExcavatorDestroyed"
      45 [-]: CALL R3 2 2  ; var3 = var3(var4)
      46 [-]: LOADB R4 0   ; var4 = false
      47 [-]: CALL R1 4 1  ; var1(var2, var3, var4)
L 0:  48 [-]: RETURN R0 0  ; 


; Name:            
; Defined at line: 644
; #Upvalues:       9
; #Parameters:     1
; Is_vararg:       0
; Max Stack Size:  8

       0 [-]: GETIMPORT R1 1; var1 = 0x3D106989
       1 [-]: LOADK R3 K2  ; var3 = "Excavation completed "
       2 [-]: MOVE R4 R0   ; var4 = var0
       3 [-]: CONCAT R2 R3 R4; var2 = var3 .. var4
       4 [-]: CALL R1 2 1  ; var1(var2)
       5 [-]: GETUPVAL R1 0; var1 = upvalues[0]
       6 [-]: LOADNIL R2   ; var2 = nil
       7 [-]: ORK R2 R2 K3 ; var2 = var2 or 1
       8 [-]: GETIMPORT R3 5; var3 = 0xBE190284
       9 [-]: MOVE R5 R1   ; var5 = var1
      10 [-]: LOADN R6 0   ; var6 = 0
      11 [-]: NAMECALL R3 R3 K6; var4 = var3; var3 = var3[0x0EB34C69]
      12 [-]: CALL R3 4 2  ; var3 = var3(var4, var5, var6)
      13 [-]: ADD R3 R3 R2 ; var3 = var3 + var2
      14 [-]: GETIMPORT R4 5; var4 = 0xBE190284
      15 [-]: MOVE R6 R1   ; var6 = var1
      16 [-]: MOVE R7 R3   ; var7 = var3
      17 [-]: NAMECALL R4 R4 K7; var5 = var4; var4 = var4[0x751F061D]
      18 [-]: CALL R4 4 1  ; var4(var5, var6, var7)
      19 [-]: GETUPVAL R1 1; var1 = upvalues[1]
      20 [-]: MOVE R2 R0   ; var2 = var0
      21 [-]: CALL R1 2 1  ; var1(var2)
      22 [-]: GETUPVAL R1 2; var1 = upvalues[2]
      23 [-]: GETUPVAL R3 3; var3 = upvalues[3]
      24 [-]: GETTABLEKS R2 R3 K8; var2 = var3["COMPLETED"]
      25 [-]: SETTABLE R2 R1 R0; var2[var1] = var0
      26 [-]: GETUPVAL R1 4; var1 = upvalues[4]
      27 [-]: GETUPVAL R3 5; var3 = upvalues[5]
      28 [-]: GETTABLEKS R2 R3 K9; var2 = var3["EXCAVATION"]
      29 [-]: JUMPIFNOTEQ R1 R2 L0; goto L0 if var1 ~= var393532
      30 [-]: GETUPVAL R1 6; var1 = upvalues[6]
      31 [-]: CALL R1 1 1  ; var1()
      32 [-]: GETUPVAL R2 7; var2 = upvalues[7]
      33 [-]: GETTABLEKS R1 R2 K10; var1 = var2[0x9742B85B]
      34 [-]: GETUPVAL R2 8; var2 = upvalues[8]
      35 [-]: GETIMPORT R3 12; var3 = 0x0469F296
      36 [-]: LOADK R4 K13 ; var4 = "DigComplete"
      37 [-]: CALL R3 2 2  ; var3 = var3(var4)
      38 [-]: LOADB R4 0   ; var4 = false
      39 [-]: CALL R1 4 1  ; var1(var2, var3, var4)
L 0:  40 [-]: RETURN R0 0  ; 


; Name:            
; Defined at line: 655
; #Upvalues:       5
; #Parameters:     2
; Is_vararg:       0
; Max Stack Size:  9

       0 [-]: GETUPVAL R2 0; var2 = upvalues[0]
       1 [-]: MOVE R3 R0   ; var3 = var0
       2 [-]: MOVE R4 R1   ; var4 = var1
       3 [-]: CALL R2 3 1  ; var2(var3, var4)
       4 [-]: JUMPIFNOT R1 L0; goto L0 if not var1
       5 [-]: GETIMPORT R2 1; var2 = 0xBE190284
       6 [-]: GETUPVAL R4 1; var4 = upvalues[1]
       7 [-]: LOADN R5 0   ; var5 = 0
       8 [-]: NAMECALL R2 R2 K2; var3 = var2; var2 = var2[0x0EB34C69]
       9 [-]: CALL R2 4 2  ; var2 = var2(var3, var4, var5)
      10 [-]: JUMPXEQKN R2 K3 L1 NOT; 
      11 [-]: GETUPVAL R3 2; var3 = upvalues[2]
      12 [-]: GETTABLEKS R2 R3 K4; var2 = var3[0x9742B85B]
      13 [-]: GETUPVAL R3 3; var3 = upvalues[3]
      14 [-]: GETIMPORT R4 6; var4 = 0x0469F296
      15 [-]: LOADK R5 K7  ; var5 = "ExcavatorPowerAdded"
      16 [-]: CALL R4 2 2  ; var4 = var4(var5)
      17 [-]: LOADB R5 0   ; var5 = false
      18 [-]: CALL R2 4 1  ; var2(var3, var4, var5)
      19 [-]: GETUPVAL R2 1; var2 = upvalues[1]
      20 [-]: LOADNIL R3   ; var3 = nil
      21 [-]: ORK R3 R3 K8 ; var3 = var3 or 1
      22 [-]: GETIMPORT R4 1; var4 = 0xBE190284
      23 [-]: MOVE R6 R2   ; var6 = var2
      24 [-]: LOADN R7 0   ; var7 = 0
      25 [-]: NAMECALL R4 R4 K2; var5 = var4; var4 = var4[0x0EB34C69]
      26 [-]: CALL R4 4 2  ; var4 = var4(var5, var6, var7)
      27 [-]: ADD R4 R4 R3 ; var4 = var4 + var3
      28 [-]: GETIMPORT R5 1; var5 = 0xBE190284
      29 [-]: MOVE R7 R2   ; var7 = var2
      30 [-]: MOVE R8 R4   ; var8 = var4
      31 [-]: NAMECALL R5 R5 K9; var6 = var5; var5 = var5[0x751F061D]
      32 [-]: CALL R5 4 1  ; var5(var6, var7, var8)
      33 [-]: RETURN R0 0  ; 
L 0:  34 [-]: GETIMPORT R2 1; var2 = 0xBE190284
      35 [-]: GETUPVAL R4 4; var4 = upvalues[4]
      36 [-]: LOADN R5 0   ; var5 = 0
      37 [-]: NAMECALL R2 R2 K2; var3 = var2; var2 = var2[0x0EB34C69]
      38 [-]: CALL R2 4 2  ; var2 = var2(var3, var4, var5)
      39 [-]: JUMPXEQKN R2 K3 L1 NOT; 
      40 [-]: GETUPVAL R3 2; var3 = upvalues[2]
      41 [-]: GETTABLEKS R2 R3 K4; var2 = var3[0x9742B85B]
      42 [-]: GETUPVAL R3 3; var3 = upvalues[3]
      43 [-]: GETIMPORT R4 6; var4 = 0x0469F296
      44 [-]: LOADK R5 K10 ; var5 = "ExcavatorNoPower"
      45 [-]: CALL R4 2 2  ; var4 = var4(var5)
      46 [-]: LOADB R5 0   ; var5 = false
      47 [-]: CALL R2 4 1  ; var2(var3, var4, var5)
      48 [-]: GETUPVAL R2 4; var2 = upvalues[4]
      49 [-]: LOADNIL R3   ; var3 = nil
      50 [-]: ORK R3 R3 K8 ; var3 = var3 or 1
      51 [-]: GETIMPORT R4 1; var4 = 0xBE190284
      52 [-]: MOVE R6 R2   ; var6 = var2
      53 [-]: LOADN R7 0   ; var7 = 0
      54 [-]: NAMECALL R4 R4 K2; var5 = var4; var4 = var4[0x0EB34C69]
      55 [-]: CALL R4 4 2  ; var4 = var4(var5, var6, var7)
      56 [-]: ADD R4 R4 R3 ; var4 = var4 + var3
      57 [-]: GETIMPORT R5 1; var5 = 0xBE190284
      58 [-]: MOVE R7 R2   ; var7 = var2
      59 [-]: MOVE R8 R4   ; var8 = var4
      60 [-]: NAMECALL R5 R5 K9; var6 = var5; var5 = var5[0x751F061D]
      61 [-]: CALL R5 4 1  ; var5(var6, var7, var8)
L 1:  62 [-]: RETURN R0 0  ; 


; Name:            
; Defined at line: 673
; #Upvalues:       5
; #Parameters:     1
; Is_vararg:       0
; Max Stack Size:  12

       0 [-]: GETUPVAL R4 0; var4 = upvalues[0]
       1 [-]: GETTABLE R3 R4 R0; var3 = var4[var0]
       2 [-]: JUMPIFNOT R3 L1; goto L1 if not var3
       3 [-]: GETUPVAL R5 0; var5 = upvalues[0]
       4 [-]: GETTABLE R4 R5 R0; var4 = var5[var0]
       5 [-]: GETUPVAL R6 1; var6 = upvalues[1]
       6 [-]: GETTABLEKS R5 R6 K0; var5 = var6["A"]
       7 [-]: JUMPIFLE R5 R4 L0; goto L0 if var5 <= var16777990
       8 [-]: LOADB R3 0 +1; var3 = false
L 0:   9 [-]: LOADB R3 1   ; var3 = true
L 1:  10 [-]: FASTCALL2K 1 R3 K1 L2; 
      11 [-]: LOADK R4 K1  ; var4 = "ERROR: invalid excavator id"
      12 [-]: GETIMPORT R2 3; var2 = 0x60CCE7B4
      13 [-]: CALL R2 3 1  ; var2(var3, var4)
L 2:  14 [-]: GETUPVAL R2 2; var2 = upvalues[2]
      15 [-]: GETTABLE R1 R2 R0; var1 = var2[var0]
      16 [-]: GETUPVAL R3 3; var3 = upvalues[3]
      17 [-]: GETTABLE R2 R3 R0; var2 = var3[var0]
      18 [-]: GETUPVAL R3 4; var3 = upvalues[4]
      19 [-]: GETTABLE R2 R3 R0; var2 = var3[var0]
      20 [-]: GETIMPORT R2 5; var2 = 0x89326C93
      21 [-]: GETIMPORT R4 7; var4 = 0x89E55121
      22 [-]: NAMECALL R5 R1 K8; var6 = var1; var5 = var1[0xD1586535]
      23 [-]: CALL R5 2 2  ; var5 = var5(var6)
      24 [-]: LOADB R6 0   ; var6 = false
      25 [-]: LOADN R7 0   ; var7 = 0
      26 [-]: LOADNIL R8   ; var8 = nil
      27 [-]: LOADNIL R9   ; var9 = nil
      28 [-]: LOADNIL R10  ; var10 = nil
      29 [-]: LOADB R11 1  ; var11 = true
      30 [-]: NAMECALL R2 R2 K9; var3 = var2; var2 = var2[0x659D451F]
      31 [-]: CALL R2 10 1 ; var2(var3, var4, var5, var6, var7, var8, var9, var10, var11)
      32 [-]: RETURN R0 0  ; 


; Name:            
; Defined at line: 678
; #Upvalues:       6
; #Parameters:     1
; Is_vararg:       0
; Max Stack Size:  14

       0 [-]: GETUPVAL R3 0; var3 = upvalues[0]
       1 [-]: GETTABLE R2 R3 R0; var2 = var3[var0]
       2 [-]: JUMPIFNOT R2 L1; goto L1 if not var2
       3 [-]: GETUPVAL R4 0; var4 = upvalues[0]
       4 [-]: GETTABLE R3 R4 R0; var3 = var4[var0]
       5 [-]: GETUPVAL R5 1; var5 = upvalues[1]
       6 [-]: GETTABLEKS R4 R5 K0; var4 = var5["A"]
       7 [-]: JUMPIFLE R4 R3 L0; goto L0 if var4 <= var16777734
       8 [-]: LOADB R2 0 +1; var2 = false
L 0:   9 [-]: LOADB R2 1   ; var2 = true
L 1:  10 [-]: LOADK R4 K1  ; var4 = "ERROR: Activating invalid activator "
      11 [-]: MOVE R5 R0   ; var5 = var0
      12 [-]: CONCAT R3 R4 R5; var3 = var4 .. var5
      13 [-]: FASTCALL2 1 R2 R3 L2; 
      14 [-]: GETIMPORT R1 3; var1 = 0x60CCE7B4
      15 [-]: CALL R1 3 1  ; var1(var2, var3)
L 2:  16 [-]: GETUPVAL R2 2; var2 = upvalues[2]
      17 [-]: GETTABLE R1 R2 R0; var1 = var2[var0]
      18 [-]: GETUPVAL R2 2; var2 = upvalues[2]
      19 [-]: GETUPVAL R6 2; var6 = upvalues[2]
      20 [-]: GETTABLE R5 R6 R0; var5 = var6[var0]
      21 [-]: ADDK R4 R5 K5; var4 = var5 + 20
      22 [-]: ADDK R3 R4 K4; var3 = var4 + 0.05000000074505806
      23 [-]: SETTABLE R3 R2 R0; var3[var2] = var0
      24 [-]: GETUPVAL R3 3; var3 = upvalues[3]
      25 [-]: GETTABLE R2 R3 R0; var2 = var3[var0]
      26 [-]: NAMECALL R2 R2 K6; var3 = var2; var2 = var2[0x1AC1655C]
      27 [-]: CALL R2 2 2  ; var2 = var2(var3)
      28 [-]: NAMECALL R2 R2 K7; var3 = var2; var2 = var2[0xB87F958D]
      29 [-]: CALL R2 2 2  ; var2 = var2(var3)
      30 [-]: GETUPVAL R4 3; var4 = upvalues[3]
      31 [-]: GETTABLE R3 R4 R0; var3 = var4[var0]
      32 [-]: NAMECALL R3 R3 K6; var4 = var3; var3 = var3[0x1AC1655C]
      33 [-]: CALL R3 2 2  ; var3 = var3(var4)
      34 [-]: MOVE R5 R2   ; var5 = var2
      35 [-]: NAMECALL R3 R3 K8; var4 = var3; var3 = var3[0x57369B8B]
      36 [-]: CALL R3 3 1  ; var3(var4, var5)
      37 [-]: MULK R3 R1 K9; var3 = var1 * 1
      38 [-]: GETUPVAL R5 4; var5 = upvalues[4]
      39 [-]: GETTABLE R4 R5 R0; var4 = var5[var0]
      40 [-]: JUMPIFNOTLT R3 R4 L6; goto L6 if var3 >= var132412
      41 [-]: GETUPVAL R5 2; var5 = upvalues[2]
      42 [-]: GETTABLE R4 R5 R0; var4 = var5[var0]
      43 [-]: MULK R3 R4 K9; var3 = var4 * 1
      44 [-]: GETUPVAL R5 4; var5 = upvalues[4]
      45 [-]: GETTABLE R4 R5 R0; var4 = var5[var0]
      46 [-]: JUMPIFNOTLE R4 R3 L6; goto L6 if var4 > var1596
      47 [-]: GETUPVAL R6 0; var6 = upvalues[0]
      48 [-]: GETTABLE R5 R6 R0; var5 = var6[var0]
      49 [-]: JUMPIFNOT R5 L4; goto L4 if not var5
      50 [-]: GETUPVAL R7 0; var7 = upvalues[0]
      51 [-]: GETTABLE R6 R7 R0; var6 = var7[var0]
      52 [-]: GETUPVAL R8 1; var8 = upvalues[1]
      53 [-]: GETTABLEKS R7 R8 K0; var7 = var8["A"]
      54 [-]: JUMPIFLE R7 R6 L3; goto L3 if var7 <= var16778502
      55 [-]: LOADB R5 0 +1; var5 = false
L 3:  56 [-]: LOADB R5 1   ; var5 = true
L 4:  57 [-]: FASTCALL2K 1 R5 K10 L5; 
      58 [-]: LOADK R6 K10 ; var6 = "ERROR: invalid excavator id"
      59 [-]: GETIMPORT R4 3; var4 = 0x60CCE7B4
      60 [-]: CALL R4 3 1  ; var4(var5, var6)
L 5:  61 [-]: GETUPVAL R4 3; var4 = upvalues[3]
      62 [-]: GETTABLE R3 R4 R0; var3 = var4[var0]
      63 [-]: GETUPVAL R5 2; var5 = upvalues[2]
      64 [-]: GETTABLE R4 R5 R0; var4 = var5[var0]
      65 [-]: GETUPVAL R5 4; var5 = upvalues[4]
      66 [-]: GETTABLE R4 R5 R0; var4 = var5[var0]
      67 [-]: GETIMPORT R4 12; var4 = 0x89326C93
      68 [-]: GETIMPORT R6 14; var6 = 0x89E55121
      69 [-]: NAMECALL R7 R3 K15; var8 = var3; var7 = var3[0xD1586535]
      70 [-]: CALL R7 2 2  ; var7 = var7(var8)
      71 [-]: LOADB R8 0   ; var8 = false
      72 [-]: LOADN R9 0   ; var9 = 0
      73 [-]: LOADNIL R10  ; var10 = nil
      74 [-]: LOADNIL R11  ; var11 = nil
      75 [-]: LOADNIL R12  ; var12 = nil
      76 [-]: LOADB R13 1  ; var13 = true
      77 [-]: NAMECALL R4 R4 K16; var5 = var4; var4 = var4[0x659D451F]
      78 [-]: CALL R4 10 1 ; var4(var5, var6, var7, var8, var9, var10, var11, var12, var13)
L 6:  79 [-]: JUMPXEQKN R1 K17 L7 NOT; 
      80 [-]: GETUPVAL R3 5; var3 = upvalues[5]
      81 [-]: MOVE R4 R0   ; var4 = var0
      82 [-]: LOADB R5 1   ; var5 = true
      83 [-]: CALL R3 3 1  ; var3(var4, var5)
L 7:  84 [-]: RETURN R0 0  ; 


; Name:            
; Defined at line: 695
; #Upvalues:       11
; #Parameters:     1
; Is_vararg:       0
; Max Stack Size:  15

       0 [-]: LOADN R3 0   ; var3 = 0
       1 [-]: JUMPIFLT R3 R0 L0; goto L0 if var3 < var16777734
       2 [-]: LOADB R2 0 +1; var2 = false
L 0:   3 [-]: LOADB R2 1   ; var2 = true
L 1:   4 [-]: FASTCALL2K 1 R2 K0 L2; 
       5 [-]: LOADK R3 K0  ; var3 = "ERROR: invalid excavator id"
       6 [-]: GETIMPORT R1 2; var1 = 0x60CCE7B4
       7 [-]: CALL R1 3 1  ; var1(var2, var3)
L 2:   8 [-]: GETUPVAL R4 0; var4 = upvalues[0]
       9 [-]: GETTABLE R3 R4 R0; var3 = var4[var0]
      10 [-]: GETUPVAL R5 1; var5 = upvalues[1]
      11 [-]: GETTABLEKS R4 R5 K4; var4 = var5["A"]
      12 [-]: SUB R2 R3 R4 ; var2 = var3 - var4
      13 [-]: ADDK R1 R2 K3; var1 = var2 + 1
      14 [-]: GETIMPORT R2 6; var2 = 0xBE190284
      15 [-]: NAMECALL R2 R2 K7; var3 = var2; var2 = var2[0x33307F92]
      16 [-]: CALL R2 2 2  ; var2 = var2(var3)
      17 [-]: GETUPVAL R8 0; var8 = upvalues[0]
      18 [-]: GETTABLE R7 R8 R0; var7 = var8[var0]
      19 [-]: JUMPIFNOT R7 L4; goto L4 if not var7
      20 [-]: GETUPVAL R9 0; var9 = upvalues[0]
      21 [-]: GETTABLE R8 R9 R0; var8 = var9[var0]
      22 [-]: GETUPVAL R10 1; var10 = upvalues[1]
      23 [-]: GETTABLEKS R9 R10 K4; var9 = var10["A"]
      24 [-]: JUMPIFLE R9 R8 L3; goto L3 if var9 <= var16779014
      25 [-]: LOADB R7 0 +1; var7 = false
L 3:  26 [-]: LOADB R7 1   ; var7 = true
L 4:  27 [-]: FASTCALL2K 1 R7 K0 L5; 
      28 [-]: LOADK R8 K0  ; var8 = "ERROR: invalid excavator id"
      29 [-]: GETIMPORT R6 2; var6 = 0x60CCE7B4
      30 [-]: CALL R6 3 1  ; var6(var7, var8)
L 5:  31 [-]: GETUPVAL R6 2; var6 = upvalues[2]
      32 [-]: GETTABLE R3 R6 R0; var3 = var6[var0]
      33 [-]: GETUPVAL R6 3; var6 = upvalues[3]
      34 [-]: GETTABLE R4 R6 R0; var4 = var6[var0]
      35 [-]: GETUPVAL R6 4; var6 = upvalues[4]
      36 [-]: GETTABLE R5 R6 R0; var5 = var6[var0]
      37 [-]: FASTCALL1 12 R4 L6; 
      38 [-]: MOVE R7 R4   ; var7 = var4
      39 [-]: GETIMPORT R6 10; var6 = 0x5BCED4C4[0x55F27C30]
      40 [-]: CALL R6 2 2  ; var6 = var6(var7)
L 6:  41 [-]: MOVE R4 R6   ; var4 = var6
      42 [-]: GETUPVAL R8 5; var8 = upvalues[5]
      43 [-]: GETTABLE R7 R8 R1; var7 = var8[var1]
      44 [-]: FASTCALL1 64 R7 L7; 
      45 [-]: GETIMPORT R6 12; var6 = 0x7B998233
      46 [-]: CALL R6 2 2  ; var6 = var6(var7)
L 7:  47 [-]: JUMPIFNOT R6 L8; goto L8 if not var6
      48 [-]: GETUPVAL R6 6; var6 = upvalues[6]
      49 [-]: CALL R6 1 1  ; var6()
      50 [-]: GETIMPORT R6 14; var6 = 0x3D106989
      51 [-]: LOADK R8 K15 ; var8 = "ID: "
      52 [-]: MOVE R9 R0   ; var9 = var0
      53 [-]: LOADK R10 K16; var10 = " index: "
      54 [-]: MOVE R11 R1  ; var11 = var1
      55 [-]: CONCAT R7 R8 R11; var7 = var8 .. var11
      56 [-]: CALL R6 2 1  ; var6(var7)
      57 [-]: LOADB R7 0   ; var7 = false
      58 [-]: FASTCALL2K 1 R7 K17 L8; 
      59 [-]: LOADK R8 K17 ; var8 = "ERROR: null HudInfo"
      60 [-]: GETIMPORT R6 2; var6 = 0x60CCE7B4
      61 [-]: CALL R6 3 1  ; var6(var7, var8)
L 8:  62 [-]: GETUPVAL R7 5; var7 = upvalues[5]
      63 [-]: GETTABLE R6 R7 R1; var6 = var7[var1]
      64 [-]: FASTCALL1 64 R6 L9; 
      65 [-]: MOVE R8 R6   ; var8 = var6
      66 [-]: GETIMPORT R7 12; var7 = 0x7B998233
      67 [-]: CALL R7 2 2  ; var7 = var7(var8)
L 9:  68 [-]: JUMPIF R7 L15; goto L15 if var7
      69 [-]: GETUPVAL R8 7; var8 = upvalues[7]
      70 [-]: GETTABLEKS R7 R8 K18; var7 = var8[0x1142C7A8]
           72 [-]: LOADN R9 1   ; var9 = 1
      73 [-]: LOADNIL R10  ; var10 = nil
      74 [-]: LOADNIL R11  ; var11 = nil
      75 [-]: LOADB R12 1  ; var12 = true
      76 [-]: CALL R7 6 2  ; var7 = var7(var8, var9, var10, var11, var12)
      77 [-]: GETUPVAL R8 8; var8 = upvalues[8]
      78 [-]: MOVE R9 R4   ; var9 = var4
      79 [-]: MOVE R10 R5  ; var10 = var5
      80 [-]: GETTABLEN R11 R6 2; var11 = var6[2]
      81 [-]: CALL R8 4 2  ; var8 = var8(var9, var10, var11)
      82 [-]: GETTABLEN R10 R6 2; var10 = var6[2]
      83 [-]: GETTABLEKS R9 R10 K19; var9 = var10["Localize"]
      84 [-]: LOADK R10 K20; var10 = "/Lotus/Language/Game/ExcavationTime"
      85 [-]: CALL R9 2 1  ; var9(var10)
      86 [-]: GETTABLEN R10 R6 2; var10 = var6[2]
      87 [-]: GETTABLEKS R9 R10 K19; var9 = var10["Localize"]
      88 [-]: LOADK R10 K21; var10 = "/Lotus/Language/Game/ExcavationPower"
      89 [-]: CALL R9 2 1  ; var9(var10)
      90 [-]: GETTABLEN R10 R6 2; var10 = var6[2]
      91 [-]: GETTABLEKS R9 R10 K22; var9 = var10["SetLabel"]
      92 [-]: GETIMPORT R10 25; var10 = 0x7F5022CF[0xE8072DED]
      93 [-]: GETUPVAL R11 9; var11 = upvalues[9]
      94 [-]: GETUPVAL R13 10; var13 = upvalues[10]
      95 [-]: GETTABLEKS R12 R13 K26; var12 = var13[0xC70DAAAC]
      96 [-]: MOVE R13 R7  ; var13 = var7
      97 [-]: CALL R12 2 2 ; var12 = var12(var13)
      98 [-]: MOVE R13 R8  ; var13 = var8
      99 [-]: CALL R10 4 0 ; var10, ... = var10(var11, var12, var13)
     100 [-]: CALL R9 0 1  ; var9(var10, ...)
     101 [-]: GETTABLEN R10 R6 2; var10 = var6[2]
     102 [-]: GETTABLEKS R9 R10 K27; var9 = var10["NeedsInit"]
     103 [-]: JUMPIF R9 L16; goto L16 if var9
     104 [-]: FASTCALL1 64 R2 L10; 
     105 [-]: MOVE R10 R2  ; var10 = var2
     106 [-]: GETIMPORT R9 12; var9 = 0x7B998233
     107 [-]: CALL R9 2 2  ; var9 = var9(var10)
L10: 108 [-]: JUMPIF R9 L16; goto L16 if var9
     109 [-]: GETTABLEN R14 R6 2; var14 = var6[2]
     110 [-]: GETTABLEKS R12 R14 K28; var12 = var14["ClipName"]
     111 [-]: LOADK R13 K29; var13 = ".Label"
     112 [-]: CONCAT R11 R12 R13; var11 = var12 .. var13
     113 [-]: LOADN R12 36 ; var12 = 36
     114 [-]: NAMECALL R9 R2 K30; var10 = var2; var9 = var2[0x91A24E4B]
     115 [-]: CALL R9 4 2  ; var9 = var9(var10, var11, var12)
     116 [-]: FASTCALL1 64 R9 L11; 
     117 [-]: MOVE R11 R9  ; var11 = var9
     118 [-]: GETIMPORT R10 12; var10 = 0x7B998233
     119 [-]: CALL R10 2 2 ; var10 = var10(var11)
L11: 120 [-]: JUMPIF R10 L16; goto L16 if var10
     121 [-]: FASTCALL1 62 R9 L12; 
     122 [-]: MOVE R12 R9  ; var12 = var9
     123 [-]: GETIMPORT R11 32; var11 = 0x03F57322
     124 [-]: CALL R11 2 2 ; var11 = var11(var12)
L12: 125 [-]: FASTCALL1 64 R11 L13; 
     126 [-]: GETIMPORT R10 12; var10 = 0x7B998233
     127 [-]: CALL R10 2 2 ; var10 = var10(var11)
L13: 128 [-]: JUMPIF R10 L16; goto L16 if var10
     129 [-]: GETTABLEN R11 R6 2; var11 = var6[2]
     130 [-]: GETTABLEKS R10 R11 K33; var10 = var11["SetHeight"]
     131 [-]: FASTCALL1 62 R9 L14; 
     132 [-]: MOVE R13 R9  ; var13 = var9
     133 [-]: GETIMPORT R12 32; var12 = 0x03F57322
     134 [-]: CALL R12 2 2 ; var12 = var12(var13)
L14: 135 [-]: ADDK R11 R12 K34; var11 = var12 + 25
     136 [-]: CALL R10 2 1 ; var10(var11)
     137 [-]: RETURN R0 0  ; 
L15: 138 [-]: GETIMPORT R7 14; var7 = 0x3D106989
     139 [-]: LOADK R8 K35 ; var8 = "NULL HUD IN UPDATE"
     140 [-]: CALL R7 2 1  ; var7(var8)
L16: 141 [-]: RETURN R0 0  ; 


; Name:            
; Defined at line: 728
; #Upvalues:       1
; #Parameters:     0
; Is_vararg:       0
; Max Stack Size:  1

       0 [-]: LOADB R0 1   ; var0 = true
       1 [-]: SETUPVAL R0 0; upvalues[0] = var0
       2 [-]: RETURN R0 0  ; 


; Name:            
; Defined at line: 732
; #Upvalues:       17
; #Parameters:     2
; Is_vararg:       0
; Max Stack Size:  12

       0 [-]: GETUPVAL R3 0; var3 = upvalues[0]
       1 [-]: GETTABLE R2 R3 R0; var2 = var3[var0]
       2 [-]: NAMECALL R2 R2 K0; var3 = var2; var2 = var2[0xC8442850]
       3 [-]: CALL R2 2 2  ; var2 = var2(var3)
       4 [-]: GETUPVAL R3 1; var3 = upvalues[1]
       5 [-]: JUMPIFNOT R3 L0; goto L0 if not var3
       6 [-]: GETUPVAL R4 2; var4 = upvalues[2]
       7 [-]: GETTABLE R3 R4 R0; var3 = var4[var0]
       8 [-]: JUMPIF R3 L0 ; goto L0 if var3
       9 [-]: LOADK R3 K1  ; var3 = 0.25
      10 [-]: JUMPIFNOTLT R2 R3 L0; goto L0 if var2 >= var131900
      11 [-]: GETUPVAL R3 2; var3 = upvalues[2]
      12 [-]: LOADB R4 1   ; var4 = true
      13 [-]: SETTABLE R4 R3 R0; var4[var3] = var0
      14 [-]: LOADB R3 0   ; var3 = false
      15 [-]: SETUPVAL R3 1; upvalues[3] = var1
      16 [-]: GETUPVAL R3 3; var3 = upvalues[3]
      17 [-]: LOADN R5 10  ; var5 = 10
      18 [-]: GETUPVAL R6 4; var6 = upvalues[4]
      19 [-]: NAMECALL R3 R3 K2; var4 = var3; var3 = var3[0xBD2E96EA]
      20 [-]: CALL R3 4 1  ; var3(var4, var5, var6)
      21 [-]: GETUPVAL R4 5; var4 = upvalues[5]
      22 [-]: GETTABLEKS R3 R4 K3; var3 = var4[0x9742B85B]
      23 [-]: GETUPVAL R4 6; var4 = upvalues[6]
      24 [-]: GETIMPORT R5 5; var5 = 0x0469F296
      25 [-]: LOADK R6 K6  ; var6 = "ExcavatorLowHealth"
      26 [-]: CALL R5 2 2  ; var5 = var5(var6)
      27 [-]: LOADB R6 0   ; var6 = false
      28 [-]: CALL R3 4 1  ; var3(var4, var5, var6)
L 0:  29 [-]: GETUPVAL R4 7; var4 = upvalues[7]
      30 [-]: GETTABLE R3 R4 R0; var3 = var4[var0]
      31 [-]: LOADN R4 0   ; var4 = 0
      32 [-]: JUMPIFNOTLE R3 R4 L1; goto L1 if var3 > var65571
      33 [-]: RETURN R0 0  ; 
L 1:  34 [-]: LOADN R4 1   ; var4 = 1
      35 [-]: MUL R3 R4 R1 ; var3 = var4 * var1
      36 [-]: GETUPVAL R5 7; var5 = upvalues[7]
      37 [-]: GETTABLE R4 R5 R0; var4 = var5[var0]
      38 [-]: GETUPVAL R5 7; var5 = upvalues[7]
      39 [-]: GETUPVAL R9 7; var9 = upvalues[7]
      40 [-]: GETTABLE R8 R9 R0; var8 = var9[var0]
      41 [-]: SUB R7 R8 R3 ; var7 = var8 - var3
      42 [-]: FASTCALL2K 18 R7 K7 L2; 
      43 [-]: LOADK R8 K7  ; var8 = 0
      44 [-]: GETIMPORT R6 10; var6 = 0x5BCED4C4[0xB62ECFE0]
      45 [-]: CALL R6 3 2  ; var6 = var6(var7, var8)
L 2:  46 [-]: SETTABLE R6 R5 R0; var6[var5] = var0
      47 [-]: GETUPVAL R5 8; var5 = upvalues[8]
      48 [-]: GETUPVAL R9 8; var9 = upvalues[8]
      49 [-]: GETTABLE R8 R9 R0; var8 = var9[var0]
      50 [-]: SUB R7 R8 R1 ; var7 = var8 - var1
      51 [-]: FASTCALL2K 18 R7 K7 L3; 
      52 [-]: LOADK R8 K7  ; var8 = 0
      53 [-]: GETIMPORT R6 10; var6 = 0x5BCED4C4[0xB62ECFE0]
      54 [-]: CALL R6 3 2  ; var6 = var6(var7, var8)
L 3:  55 [-]: SETTABLE R6 R5 R0; var6[var5] = var0
      56 [-]: GETUPVAL R6 8; var6 = upvalues[8]
      57 [-]: GETTABLE R5 R6 R0; var5 = var6[var0]
      58 [-]: LOADN R6 0   ; var6 = 0
      59 [-]: JUMPIFNOTLE R5 R6 L5; goto L5 if var5 > var787745
      60 [-]: GETIMPORT R5 12; var5 = 0x3D106989
      61 [-]: LOADK R7 K13 ; var7 = "Excavation completed "
      62 [-]: MOVE R8 R0   ; var8 = var0
      63 [-]: CONCAT R6 R7 R8; var6 = var7 .. var8
      64 [-]: CALL R5 2 1  ; var5(var6)
      65 [-]: GETUPVAL R5 9; var5 = upvalues[9]
      66 [-]: LOADNIL R6   ; var6 = nil
      67 [-]: ORK R6 R6 K14; var6 = var6 or 1
      68 [-]: GETIMPORT R7 16; var7 = 0xBE190284
      69 [-]: MOVE R9 R5   ; var9 = var5
      70 [-]: LOADN R10 0  ; var10 = 0
      71 [-]: NAMECALL R7 R7 K17; var8 = var7; var7 = var7[0x0EB34C69]
      72 [-]: CALL R7 4 2  ; var7 = var7(var8, var9, var10)
      73 [-]: ADD R7 R7 R6 ; var7 = var7 + var6
      74 [-]: GETIMPORT R8 16; var8 = 0xBE190284
      75 [-]: MOVE R10 R5  ; var10 = var5
      76 [-]: MOVE R11 R7  ; var11 = var7
      77 [-]: NAMECALL R8 R8 K18; var9 = var8; var8 = var8[0x751F061D]
      78 [-]: CALL R8 4 1  ; var8(var9, var10, var11)
      79 [-]: GETUPVAL R5 10; var5 = upvalues[10]
      80 [-]: MOVE R6 R0   ; var6 = var0
      81 [-]: CALL R5 2 1  ; var5(var6)
      82 [-]: GETUPVAL R5 11; var5 = upvalues[11]
      83 [-]: GETUPVAL R7 12; var7 = upvalues[12]
      84 [-]: GETTABLEKS R6 R7 K19; var6 = var7["COMPLETED"]
      85 [-]: SETTABLE R6 R5 R0; var6[var5] = var0
      86 [-]: GETUPVAL R5 13; var5 = upvalues[13]
      87 [-]: GETUPVAL R7 14; var7 = upvalues[14]
      88 [-]: GETTABLEKS R6 R7 K20; var6 = var7["EXCAVATION"]
      89 [-]: JUMPIFNOTEQ R5 R6 L4; goto L4 if var5 ~= var984380
      90 [-]: GETUPVAL R5 15; var5 = upvalues[15]
      91 [-]: CALL R5 1 1  ; var5()
      92 [-]: GETUPVAL R6 5; var6 = upvalues[5]
      93 [-]: GETTABLEKS R5 R6 K3; var5 = var6[0x9742B85B]
      94 [-]: GETUPVAL R6 6; var6 = upvalues[6]
      95 [-]: GETIMPORT R7 5; var7 = 0x0469F296
      96 [-]: LOADK R8 K21 ; var8 = "DigComplete"
      97 [-]: CALL R7 2 2  ; var7 = var7(var8)
      98 [-]: LOADB R8 0   ; var8 = false
      99 [-]: CALL R5 4 1  ; var5(var6, var7, var8)
L 4: 100 [-]: RETURN R0 0  ; 
L 5: 101 [-]: LOADN R5 0   ; var5 = 0
     102 [-]: JUMPIFNOTLT R5 R4 L6; goto L6 if var5 >= var460348
     103 [-]: GETUPVAL R6 7; var6 = upvalues[7]
     104 [-]: GETTABLE R5 R6 R0; var5 = var6[var0]
     105 [-]: LOADN R6 0   ; var6 = 0
     106 [-]: JUMPIFNOTLE R5 R6 L6; goto L6 if var5 > var1049916
     107 [-]: GETUPVAL R5 16; var5 = upvalues[16]
     108 [-]: MOVE R6 R0   ; var6 = var0
     109 [-]: LOADB R7 0   ; var7 = false
     110 [-]: CALL R5 3 1  ; var5(var6, var7)
L 6: 111 [-]: RETURN R0 0  ; 


; Name:            
; Defined at line: 762
; #Upvalues:       4
; #Parameters:     1
; Is_vararg:       0
; Max Stack Size:  10

       0 [-]: GETIMPORT R1 1; var1 = 0xCFC01047
       1 [-]: GETUPVAL R2 0; var2 = upvalues[0]
       2 [-]: CALL R1 2 4  ; var1, var2, var3 = var1(var2)
       3 [-]: FORGPREP_NEXT R1 L3; 
L 0:   4 [-]: GETUPVAL R7 0; var7 = upvalues[0]
       5 [-]: GETTABLE R6 R7 R4; var6 = var7[var4]
       6 [-]: JUMPIFNOT R6 L2; goto L2 if not var6
       7 [-]: GETUPVAL R8 0; var8 = upvalues[0]
       8 [-]: GETTABLE R7 R8 R4; var7 = var8[var4]
       9 [-]: GETUPVAL R9 1; var9 = upvalues[1]
      10 [-]: GETTABLEKS R8 R9 K2; var8 = var9["A"]
      11 [-]: JUMPIFLE R8 R7 L1; goto L1 if var8 <= var16778758
      12 [-]: LOADB R6 0 +1; var6 = false
L 1:  13 [-]: LOADB R6 1   ; var6 = true
L 2:  14 [-]: JUMPIFNOT R6 L3; goto L3 if not var6
      15 [-]: GETUPVAL R6 2; var6 = upvalues[2]
      16 [-]: MOVE R7 R4   ; var7 = var4
      17 [-]: MOVE R8 R0   ; var8 = var0
      18 [-]: CALL R6 3 1  ; var6(var7, var8)
L 3:  19 [-]: FORGLOOP R1 L0 2; 
      20 [-]: GETIMPORT R1 1; var1 = 0xCFC01047
      21 [-]: GETUPVAL R2 0; var2 = upvalues[0]
      22 [-]: CALL R1 2 4  ; var1, var2, var3 = var1(var2)
      23 [-]: FORGPREP_NEXT R1 L7; 
L 4:  24 [-]: GETUPVAL R7 0; var7 = upvalues[0]
      25 [-]: GETTABLE R6 R7 R4; var6 = var7[var4]
      26 [-]: JUMPIFNOT R6 L6; goto L6 if not var6
      27 [-]: GETUPVAL R8 0; var8 = upvalues[0]
      28 [-]: GETTABLE R7 R8 R4; var7 = var8[var4]
      29 [-]: GETUPVAL R9 1; var9 = upvalues[1]
      30 [-]: GETTABLEKS R8 R9 K2; var8 = var9["A"]
      31 [-]: JUMPIFLE R8 R7 L5; goto L5 if var8 <= var16778758
      32 [-]: LOADB R6 0 +1; var6 = false
L 5:  33 [-]: LOADB R6 1   ; var6 = true
L 6:  34 [-]: JUMPIFNOT R6 L7; goto L7 if not var6
      35 [-]: GETUPVAL R6 3; var6 = upvalues[3]
      36 [-]: MOVE R7 R4   ; var7 = var4
      37 [-]: CALL R6 2 1  ; var6(var7)
L 7:  38 [-]: FORGLOOP R1 L4 2; 
      39 [-]: RETURN R0 0  ; 


; Name:            
; Defined at line: 775
; #Upvalues:       3
; #Parameters:     0
; Is_vararg:       0
; Max Stack Size:  12

       0 [-]: GETUPVAL R0 0; var0 = upvalues[0]
       1 [-]: GETUPVAL R2 1; var2 = upvalues[1]
       2 [-]: LOADB R3 1   ; var3 = true
       3 [-]: NAMECALL R0 R0 K0; var1 = var0; var0 = var0[0x7F79474D]
       4 [-]: CALL R0 4 2  ; var0 = var0(var1, var2, var3)
       5 [-]: GETUPVAL R1 0; var1 = upvalues[0]
       6 [-]: NAMECALL R1 R1 K1; var2 = var1; var1 = var1[0x202F3902]
       7 [-]: CALL R1 2 2  ; var1 = var1(var2)
       8 [-]: GETIMPORT R2 3; var2 = 0xC8802016
       9 [-]: MOVE R3 R1   ; var3 = var1
      10 [-]: CALL R2 2 4  ; var2, var3, var4 = var2(var3)
      11 [-]: FORGPREP_INEXT R2 L2; 
L 0:  12 [-]: NAMECALL R7 R6 K4; var8 = var6; var7 = var6[0x4C976EDA]
      13 [-]: CALL R7 2 2  ; var7 = var7(var8)
      14 [-]: GETUPVAL R10 1; var10 = upvalues[1]
      15 [-]: NAMECALL R8 R6 K0; var9 = var6; var8 = var6[0x7F79474D]
      16 [-]: CALL R8 3 2  ; var8 = var8(var9, var10)
      17 [-]: FASTCALL1 64 R7 L1; 
      18 [-]: MOVE R10 R7  ; var10 = var7
      19 [-]: GETIMPORT R9 6; var9 = 0x7B998233
      20 [-]: CALL R9 2 2  ; var9 = var9(var10)
L 1:  21 [-]: JUMPIF R9 L2 ; goto L2 if var9
      22 [-]: GETIMPORT R11 8; var11 = 0x3FA1B9D9
      23 [-]: NAMECALL R9 R7 K9; var10 = var7; var9 = var7[0xF2DEAF69]
      24 [-]: CALL R9 3 2  ; var9 = var9(var10, var11)
      25 [-]: JUMPIFNOT R9 L2; goto L2 if not var9
      26 [-]: JUMPXEQKN R8 K10 L2 NOT; 
      27 [-]: NAMECALL R9 R6 K11; var10 = var6; var9 = var6[0xEFE6CAD1]
      28 [-]: CALL R9 2 2  ; var9 = var9(var10)
      29 [-]: LOADN R10 2  ; var10 = 2
      30 [-]: JUMPIFNOTLT R9 R10 L2; goto L2 if var9 >= var201326600
      31 [-]: ADDK R0 R0 K12; var0 = var0 + 1
L 2:  32 [-]: FORGLOOP R2 L0 2 [inext]; 
      33 [-]: GETUPVAL R3 2; var3 = upvalues[2]
      34 [-]: GETIMPORT R7 14; var7 = 0xE7F2B02F
      35 [-]: NAMECALL R7 R7 K15; var8 = var7; var7 = var7[0xEBE2F513]
      36 [-]: CALL R7 2 2  ; var7 = var7(var8)
      37 [-]: GETIMPORT R8 17; var8 = 0x9BA7909F
      38 [-]: LOADK R10 K18; var10 = "Server.NumVirtualTestClients"
      39 [-]: NAMECALL R8 R8 K19; var9 = var8; var8 = var8[0x8151451D]
      40 [-]: CALL R8 3 2  ; var8 = var8(var9, var10)
      41 [-]: ADD R6 R7 R8 ; var6 = var7 + var8
      42 [-]: FASTCALL2K 18 R6 K12 L3; 
      43 [-]: LOADK R7 K12 ; var7 = 1
      44 [-]: GETIMPORT R5 22; var5 = 0x5BCED4C4[0xB62ECFE0]
      45 [-]: CALL R5 3 2  ; var5 = var5(var6, var7)
L 3:  46 [-]: FASTCALL2K 19 R5 K23 L4; 
      47 [-]: LOADK R6 K23 ; var6 = 4
      48 [-]: GETIMPORT R4 25; var4 = 0x5BCED4C4[0xAC1B386A]
      49 [-]: CALL R4 3 2  ; var4 = var4(var5, var6)
L 4:  50 [-]: GETTABLE R2 R3 R4; var2 = var3[var4]
      51 [-]: JUMPIFNOTLT R0 R2 L5; goto L5 if var0 >= var66054
      52 [-]: LOADB R2 1   ; var2 = true
      53 [-]: RETURN R2 1  ; 
L 5:  54 [-]: LOADB R2 0   ; var2 = false
      55 [-]: RETURN R2 1  ; 


; Name:            
; Defined at line: 793
; #Upvalues:       7
; #Parameters:     0
; Is_vararg:       0
; Max Stack Size:  17

       0 [-]: GETUPVAL R1 0; var1 = upvalues[0]
       1 [-]: FASTCALL1 64 R1 L0; 
       2 [-]: GETIMPORT R0 1; var0 = 0x7B998233
       3 [-]: CALL R0 2 2  ; var0 = var0(var1)
L 0:   4 [-]: JUMPIF R0 L1 ; goto L1 if var0
       5 [-]: GETUPVAL R0 0; var0 = upvalues[0]
       6 [-]: NAMECALL R0 R0 K2; var1 = var0; var0 = var0[0xF37943FF]
       7 [-]: CALL R0 2 2  ; var0 = var0(var1)
       8 [-]: JUMPIF R0 L2 ; goto L2 if var0
L 1:   9 [-]: RETURN R0 0  ; 
L 2:  10 [-]: GETUPVAL R0 1; var0 = upvalues[1]
      11 [-]: CALL R0 1 2  ; var0 = var0()
      12 [-]: LENGTH R1 R0 ; var1 = #var0
      13 [-]: JUMPXEQKN R1 K3 L3 NOT; 
      14 [-]: RETURN R0 0  ; 
L 3:  15 [-]: GETUPVAL R1 2; var1 = upvalues[2]
      16 [-]: LOADB R3 1   ; var3 = true
      17 [-]: NAMECALL R1 R1 K4; var2 = var1; var1 = var1[0x39E33D94]
      18 [-]: CALL R1 3 2  ; var1 = var1(var2, var3)
      19 [-]: GETUPVAL R2 2; var2 = upvalues[2]
      20 [-]: NAMECALL R2 R2 K5; var3 = var2; var2 = var2[0x202F3902]
      21 [-]: CALL R2 2 2  ; var2 = var2(var3)
      22 [-]: LOADN R3 0   ; var3 = 0
      23 [-]: GETIMPORT R4 7; var4 = 0xC8802016
      24 [-]: MOVE R5 R2   ; var5 = var2
      25 [-]: CALL R4 2 4  ; var4, var5, var6 = var4(var5)
      26 [-]: FORGPREP_INEXT R4 L6; 
L 4:  27 [-]: NAMECALL R9 R8 K8; var10 = var8; var9 = var8[0x4C976EDA]
      28 [-]: CALL R9 2 2  ; var9 = var9(var10)
      29 [-]: FASTCALL1 64 R9 L5; 
      30 [-]: MOVE R11 R9  ; var11 = var9
      31 [-]: GETIMPORT R10 1; var10 = 0x7B998233
      32 [-]: CALL R10 2 2 ; var10 = var10(var11)
L 5:  33 [-]: JUMPIF R10 L6; goto L6 if var10
      34 [-]: NAMECALL R10 R8 K9; var11 = var8; var10 = var8[0xEFE6CAD1]
      35 [-]: CALL R10 2 2 ; var10 = var10(var11)
      36 [-]: LOADN R11 2  ; var11 = 2
      37 [-]: JUMPIFNOTLT R10 R11 L6; goto L6 if var10 >= var167969544
      38 [-]: ADDK R3 R3 K10; var3 = var3 + 1
L 6:  39 [-]: FORGLOOP R4 L4 2 [inext]; 
      40 [-]: GETIMPORT R7 12; var7 = 0xE7F2B02F
      41 [-]: NAMECALL R7 R7 K13; var8 = var7; var7 = var7[0xEBE2F513]
      42 [-]: CALL R7 2 2  ; var7 = var7(var8)
      43 [-]: GETIMPORT R8 15; var8 = 0x9BA7909F
      44 [-]: LOADK R10 K16; var10 = "Server.NumVirtualTestClients"
      45 [-]: NAMECALL R8 R8 K17; var9 = var8; var8 = var8[0x8151451D]
      46 [-]: CALL R8 3 2  ; var8 = var8(var9, var10)
      47 [-]: ADD R6 R7 R8 ; var6 = var7 + var8
      48 [-]: FASTCALL2K 18 R6 K10 L7; 
      49 [-]: LOADK R7 K10 ; var7 = 1
      50 [-]: GETIMPORT R5 20; var5 = 0x5BCED4C4[0xB62ECFE0]
      51 [-]: CALL R5 3 2  ; var5 = var5(var6, var7)
L 7:  52 [-]: FASTCALL2K 19 R5 K21 L8; 
      53 [-]: LOADK R6 K21 ; var6 = 4
      54 [-]: GETIMPORT R4 23; var4 = 0x5BCED4C4[0xAC1B386A]
      55 [-]: CALL R4 3 2  ; var4 = var4(var5, var6)
L 8:  56 [-]: GETUPVAL R6 3; var6 = upvalues[3]
      57 [-]: GETTABLE R5 R6 R4; var5 = var6[var4]
      58 [-]: JUMPIFNOTLT R1 R5 L12; goto L12 if var1 >= var263996
      59 [-]: GETUPVAL R7 4; var7 = upvalues[4]
      60 [-]: GETTABLE R6 R7 R4; var6 = var7[var4]
      61 [-]: ADD R5 R1 R6 ; var5 = var1 + var6
      62 [-]: GETUPVAL R7 5; var7 = upvalues[5]
      63 [-]: GETTABLE R6 R7 R4; var6 = var7[var4]
      64 [-]: JUMPIFNOTLT R5 R6 L12; goto L12 if var5 >= var132400
      65 [-]: LOADN R5 2   ; var5 = 2
      66 [-]: JUMPIFNOTLE R3 R5 L12; goto L12 if var3 > var394556
      67 [-]: GETUPVAL R5 6; var5 = upvalues[6]
      68 [-]: CALL R5 1 2  ; var5 = var5()
      69 [-]: GETIMPORT R7 25; var7 = 0x55730E1A
      70 [-]: LOADN R8 1   ; var8 = 1
      71 [-]: LENGTH R9 R0 ; var9 = #var0
      72 [-]: CALL R7 3 2  ; var7 = var7(var8, var9)
      73 [-]: GETTABLE R6 R0 R7; var6 = var0[var7]
      74 [-]: LOADNIL R7   ; var7 = nil
      75 [-]: JUMPIFNOT R5 L10; goto L10 if not var5
      76 [-]: GETUPVAL R8 0; var8 = upvalues[0]
      77 [-]: NAMECALL R10 R6 K26; var11 = var6; var10 = var6[0xD1586535]
      78 [-]: CALL R10 2 2 ; var10 = var10(var11)
      79 [-]: LOADN R11 0  ; var11 = 0
      80 [-]: LOADN R12 20 ; var12 = 20
      81 [-]: GETIMPORT R13 28; var13 = 0x3FA1B9D9
      82 [-]: LOADN R14 2  ; var14 = 2
      83 [-]: LOADN R15 2  ; var15 = 2
      84 [-]: GETUPVAL R16 2; var16 = upvalues[2]
      85 [-]: NAMECALL R8 R8 K29; var9 = var8; var8 = var8[0xA3871690]
      86 [-]: CALL R8 9 2  ; var8 = var8(var9, var10, var11, var12, var13, var14, var15, var16)
      87 [-]: MOVE R7 R8   ; var7 = var8
      88 [-]: FASTCALL1 64 R7 L9; 
      89 [-]: MOVE R9 R7   ; var9 = var7
      90 [-]: GETIMPORT R8 1; var8 = 0x7B998233
      91 [-]: CALL R8 2 2  ; var8 = var8(var9)
L 9:  92 [-]: JUMPIF R8 L12; goto L12 if var8
      93 [-]: GETIMPORT R8 31; var8 = 0x3D106989
      94 [-]: LOADK R9 K32 ; var9 = "Spawning a reinforcement encounter with a carrier"
      95 [-]: CALL R8 2 1  ; var8(var9)
      96 [-]: RETURN R0 0  ; 
L10:  97 [-]: GETUPVAL R8 0; var8 = upvalues[0]
      98 [-]: NAMECALL R10 R6 K26; var11 = var6; var10 = var6[0xD1586535]
      99 [-]: CALL R10 2 2 ; var10 = var10(var11)
     100 [-]: LOADN R11 0  ; var11 = 0
     101 [-]: LOADN R12 20 ; var12 = 20
     102 [-]: LOADN R13 2  ; var13 = 2
     103 [-]: LOADN R14 2  ; var14 = 2
     104 [-]: GETUPVAL R15 2; var15 = upvalues[2]
     105 [-]: NAMECALL R8 R8 K33; var9 = var8; var8 = var8[0xFA25307F]
     106 [-]: CALL R8 8 2  ; var8 = var8(var9, var10, var11, var12, var13, var14, var15)
     107 [-]: MOVE R7 R8   ; var7 = var8
     108 [-]: FASTCALL1 64 R7 L11; 
     109 [-]: MOVE R9 R7   ; var9 = var7
     110 [-]: GETIMPORT R8 1; var8 = 0x7B998233
     111 [-]: CALL R8 2 2  ; var8 = var8(var9)
L11: 112 [-]: JUMPIF R8 L12; goto L12 if var8
     113 [-]: GETIMPORT R8 31; var8 = 0x3D106989
     114 [-]: LOADK R9 K34 ; var9 = "Spawning a reinforcement encounter"
     115 [-]: CALL R8 2 1  ; var8(var9)
L12: 116 [-]: RETURN R0 0  ; 


; Name:            
; Defined at line: 834
; #Upvalues:       25
; #Parameters:     0
; Is_vararg:       0
; Max Stack Size:  23

       0 [-]: GETIMPORT R0 1; var0 = 0x89326C93
       1 [-]: GETUPVAL R2 1; var2 = upvalues[1]
       2 [-]: GETUPVAL R3 2; var3 = upvalues[2]
       3 [-]: LOADN R4 0   ; var4 = 0
       4 [-]: GETUPVAL R5 3; var5 = upvalues[3]
       5 [-]: NAMECALL R5 R5 K2; var6 = var5; var5 = var5[0xC5B92518]
       6 [-]: CALL R5 2 0  ; var5, ... = var5(var6)
       7 [-]: NAMECALL R0 R0 K3; var1 = var0; var0 = var0[0xF16592C8]
       8 [-]: CALL R0 0 2  ; var0 = var0(var1, ...)
       9 [-]: SETUPVAL R0 0; upvalues[0] = var0
      10 [-]: GETIMPORT R0 6; var0 = 0x33BDD652[0xF21B1D8E]
      11 [-]: GETUPVAL R1 0; var1 = upvalues[0]
      12 [-]: NEWCLOSURE R2 P0; 
      13 [-]: CAPTURE UPVAL U3; 
      14 [-]: CALL R0 3 1  ; var0(var1, var2)
      15 [-]: GETUPVAL R0 5; var0 = upvalues[5]
      16 [-]: GETUPVAL R1 6; var1 = upvalues[6]
      17 [-]: GETUPVAL R3 0; var3 = upvalues[0]
      18 [-]: LENGTH R2 R3 ; var2 = #var3
      19 [-]: CALL R0 3 2  ; var0 = var0(var1, var2)
      20 [-]: SETUPVAL R0 4; upvalues[0] = var4
      21 [-]: GETUPVAL R0 5; var0 = upvalues[5]
      22 [-]: GETUPVAL R1 8; var1 = upvalues[8]
      23 [-]: GETUPVAL R3 0; var3 = upvalues[0]
      24 [-]: LENGTH R2 R3 ; var2 = #var3
      25 [-]: LOADK R3 K7  ; var3 = 0.0099999997764825821
      26 [-]: CALL R0 4 2  ; var0 = var0(var1, var2, var3)
      27 [-]: SETUPVAL R0 7; upvalues[0] = var7
      28 [-]: GETUPVAL R0 5; var0 = upvalues[5]
      29 [-]: GETUPVAL R1 10; var1 = upvalues[10]
      30 [-]: GETUPVAL R3 0; var3 = upvalues[0]
      31 [-]: LENGTH R2 R3 ; var2 = #var3
      32 [-]: LOADK R3 K7  ; var3 = 0.0099999997764825821
      33 [-]: CALL R0 4 2  ; var0 = var0(var1, var2, var3)
      34 [-]: SETUPVAL R0 9; upvalues[0] = var9
      35 [-]: LOADN R0 0   ; var0 = 0
      36 [-]: GETIMPORT R1 9; var1 = 0xCFC01047
      37 [-]: GETUPVAL R2 0; var2 = upvalues[0]
      38 [-]: CALL R1 2 4  ; var1, var2, var3 = var1(var2)
      39 [-]: FORGPREP_NEXT R1 L2; 
L 0:  40 [-]: GETIMPORT R6 1; var6 = 0x89326C93
      41 [-]: GETUPVAL R8 11; var8 = upvalues[11]
      42 [-]: NAMECALL R9 R5 K10; var10 = var5; var9 = var5[0xD1586535]
      43 [-]: CALL R9 2 2  ; var9 = var9(var10)
      44 [-]: LOADN R10 0  ; var10 = 0
      45 [-]: LOADN R11 4  ; var11 = 4
      46 [-]: NAMECALL R6 R6 K11; var7 = var6; var6 = var6[0x462C251C]
      47 [-]: CALL R6 6 2  ; var6 = var6(var7, var8, var9, var10, var11)
      48 [-]: GETUPVAL R7 12; var7 = upvalues[12]
      49 [-]: SETTABLE R6 R7 R4; var6[var7] = var4
      50 [-]: FASTCALL1 64 R6 L1; 
      51 [-]: MOVE R8 R6   ; var8 = var6
      52 [-]: GETIMPORT R7 13; var7 = 0x7B998233
      53 [-]: CALL R7 2 2  ; var7 = var7(var8)
L 1:  54 [-]: JUMPIF R7 L2 ; goto L2 if var7
      55 [-]: ADDK R0 R0 K14; var0 = var0 + 1
      56 [-]: GETUPVAL R10 13; var10 = upvalues[13]
      57 [-]: GETUPVAL R14 4; var14 = upvalues[4]
      58 [-]: GETTABLE R13 R14 R4; var13 = var14[var4]
      59 [-]: GETUPVAL R15 14; var15 = upvalues[14]
      60 [-]: GETTABLEKS R14 R15 K15; var14 = var15["A"]
      61 [-]: SUB R12 R13 R14; var12 = var13 - var14
      62 [-]: ADDK R11 R12 K14; var11 = var12 + 1
      63 [-]: GETTABLE R9 R10 R11; var9 = var10[var11]
      64 [-]: GETIMPORT R10 17; var10 = EMPTY_SYMBOL
      65 [-]: NAMECALL R7 R6 K18; var8 = var6; var7 = var6[0x47901F07]
      66 [-]: CALL R7 4 1  ; var7(var8, var9, var10)
      67 [-]: GETIMPORT R7 20; var7 = 0x11A19C5E
      68 [-]: MOVE R8 R6   ; var8 = var6
      69 [-]: LOADK R9 K21 ; var9 = "OnKilled"
      70 [-]: CALL R7 3 1  ; var7(var8, var9)
      71 [-]: GETIMPORT R9 23; var9 = gContextActionType
      72 [-]: NAMECALL R7 R6 K24; var8 = var6; var7 = var6[0xC9F6A7D7]
      73 [-]: CALL R7 3 2  ; var7 = var7(var8, var9)
      74 [-]: GETIMPORT R8 20; var8 = 0x11A19C5E
      75 [-]: MOVE R9 R7   ; var9 = var7
      76 [-]: LOADK R10 K25; var10 = "OnActivated"
      77 [-]: CALL R8 3 1  ; var8(var9, var10)
L 2:  78 [-]: FORGLOOP R1 L0 2; 
      79 [-]: LOADN R1 0   ; var1 = 0
      80 [-]: GETIMPORT R2 9; var2 = 0xCFC01047
      81 [-]: GETUPVAL R3 4; var3 = upvalues[4]
      82 [-]: CALL R2 2 4  ; var2, var3, var4 = var2(var3)
      83 [-]: FORGPREP_NEXT R2 L4; 
L 3:  84 [-]: GETUPVAL R8 14; var8 = upvalues[14]
      85 [-]: GETTABLEKS R7 R8 K26; var7 = var8["DESTROYED"]
      86 [-]: JUMPIFNOTLT R7 R6 L4; goto L4 if var7 >= var234946824
      87 [-]: ADDK R1 R1 K14; var1 = var1 + 1
L 4:  88 [-]: FORGLOOP R2 L3 2; 
      89 [-]: GETIMPORT R2 28; var2 = 0x3D106989
      90 [-]: LOADK R4 K29 ; var4 = "Net excavator count: "
      91 [-]: MOVE R5 R1   ; var5 = var1
      92 [-]: LOADK R6 K30 ; var6 = " vs Avatar excavator count: "
      93 [-]: MOVE R7 R0   ; var7 = var0
      94 [-]: CONCAT R3 R4 R7; var3 = var4 .. var7
      95 [-]: CALL R2 2 1  ; var2(var3)
      96 [-]: LOADB R2 1   ; var2 = true
      97 [-]: GETUPVAL R3 15; var3 = upvalues[15]
      98 [-]: CALL R3 1 2  ; var3 = var3()
      99 [-]: GETIMPORT R4 9; var4 = 0xCFC01047
     100 [-]: MOVE R5 R3   ; var5 = var3
     101 [-]: CALL R4 2 4  ; var4, var5, var6 = var4(var5)
     102 [-]: FORGPREP_NEXT R4 L7; 
L 5: 103 [-]: GETUPVAL R11 12; var11 = upvalues[12]
     104 [-]: GETTABLE R10 R11 R8; var10 = var11[var8]
     105 [-]: FASTCALL1 64 R10 L6; 
     106 [-]: GETIMPORT R9 13; var9 = 0x7B998233
     107 [-]: CALL R9 2 2  ; var9 = var9(var10)
L 6: 108 [-]: JUMPIFNOT R9 L7; goto L7 if not var9
     109 [-]: LOADB R2 0   ; var2 = false
     110 [-]: JUMP L8      ; goto L8
L 7: 111 [-]: FORGLOOP R4 L5 2; 
L 8: 112 [-]: JUMPIFNOTEQ R1 R0 L9; goto L9 if var1 ~= var17629773
     113 [-]: JUMPIF R2 L28; goto L28 if var2
L 9: 114 [-]: JUMPIF R2 L10; goto L10 if var2
     115 [-]: GETIMPORT R4 28; var4 = 0x3D106989
     116 [-]: LOADK R5 K31 ; var5 = "Net and avatars didn't match"
     117 [-]: CALL R4 2 1  ; var4(var5)
L10: 118 [-]: GETIMPORT R4 33; var4 = 0xBE190284
     119 [-]: GETUPVAL R6 16; var6 = upvalues[16]
     120 [-]: LOADN R7 0   ; var7 = 0
     121 [-]: NAMECALL R4 R4 K34; var5 = var4; var4 = var4[0x0EB34C69]
     122 [-]: CALL R4 4 2  ; var4 = var4(var5, var6, var7)
     123 [-]: GETIMPORT R5 33; var5 = 0xBE190284
     124 [-]: GETUPVAL R7 17; var7 = upvalues[17]
     125 [-]: LOADN R8 0   ; var8 = 0
     126 [-]: NAMECALL R5 R5 K34; var6 = var5; var5 = var5[0x0EB34C69]
     127 [-]: CALL R5 4 2  ; var5 = var5(var6, var7, var8)
     128 [-]: GETIMPORT R6 33; var6 = 0xBE190284
     129 [-]: GETUPVAL R8 18; var8 = upvalues[18]
     130 [-]: LOADN R9 0   ; var9 = 0
     131 [-]: NAMECALL R6 R6 K34; var7 = var6; var6 = var6[0x0EB34C69]
     132 [-]: CALL R6 4 2  ; var6 = var6(var7, var8, var9)
     133 [-]: GETIMPORT R7 28; var7 = 0x3D106989
     134 [-]: LOADK R8 K35 ; var8 = "Printing data in netvars:"
     135 [-]: CALL R7 2 1  ; var7(var8)
     136 [-]: GETUPVAL R7 19; var7 = upvalues[19]
     137 [-]: CALL R7 1 1  ; var7()
     138 [-]: ADD R8 R5 R6 ; var8 = var5 + var6
     139 [-]: ADD R7 R8 R1 ; var7 = var8 + var1
     140 [-]: JUMPIFNOTEQ R4 R7 L23; goto L23 if var4 ~= var2426913
     141 [-]: GETIMPORT R8 37; var8 = 0xA8CCD011
     142 [-]: GETIMPORT R12 39; var12 = 0xE7F2B02F
     143 [-]: NAMECALL R12 R12 K40; var13 = var12; var12 = var12[0xEBE2F513]
     144 [-]: CALL R12 2 2 ; var12 = var12(var13)
     145 [-]: GETIMPORT R13 42; var13 = 0x9BA7909F
     146 [-]: LOADK R15 K43; var15 = "Server.NumVirtualTestClients"
     147 [-]: NAMECALL R13 R13 K44; var14 = var13; var13 = var13[0x8151451D]
     148 [-]: CALL R13 3 2 ; var13 = var13(var14, var15)
     149 [-]: ADD R11 R12 R13; var11 = var12 + var13
     150 [-]: FASTCALL2K 18 R11 K14 L11; 
     151 [-]: LOADK R12 K14; var12 = 1
     152 [-]: GETIMPORT R10 47; var10 = 0x5BCED4C4[0xB62ECFE0]
     153 [-]: CALL R10 3 2 ; var10 = var10(var11, var12)
L11: 154 [-]: FASTCALL2K 19 R10 K48 L12; 
     155 [-]: LOADK R11 K48; var11 = 4
     156 [-]: GETIMPORT R9 50; var9 = 0x5BCED4C4[0xAC1B386A]
     157 [-]: CALL R9 3 2  ; var9 = var9(var10, var11)
L12: 158 [-]: GETTABLE R7 R8 R9; var7 = var8[var9]
     159 [-]: SUB R8 R4 R7 ; var8 = var4 - var7
     160 [-]: GETIMPORT R9 28; var9 = 0x3D106989
     161 [-]: LOADK R10 K51; var10 = "Net count seems fine, can recover creating new excavators where missing"
     162 [-]: CALL R9 2 1  ; var9(var10)
     163 [-]: GETIMPORT R9 9; var9 = 0xCFC01047
     164 [-]: GETUPVAL R10 4; var10 = upvalues[4]
     165 [-]: CALL R9 2 4  ; var9, var10, var11 = var9(var10)
     166 [-]: FORGPREP_NEXT R9 L20; 
L13: 167 [-]: GETUPVAL R15 4; var15 = upvalues[4]
     168 [-]: GETTABLE R14 R15 R12; var14 = var15[var12]
     169 [-]: JUMPIFNOT R14 L15; goto L15 if not var14
     170 [-]: GETUPVAL R16 4; var16 = upvalues[4]
     171 [-]: GETTABLE R15 R16 R12; var15 = var16[var12]
     172 [-]: GETUPVAL R17 14; var17 = upvalues[14]
     173 [-]: GETTABLEKS R16 R17 K15; var16 = var17["A"]
     174 [-]: JUMPIFLE R16 R15 L14; goto L14 if var16 <= var16780806
     175 [-]: LOADB R14 0 +1; var14 = false
L14: 176 [-]: LOADB R14 1  ; var14 = true
L15: 177 [-]: JUMPIFNOT R14 L18; goto L18 if not var14
     178 [-]: GETUPVAL R16 12; var16 = upvalues[12]
     179 [-]: GETTABLE R15 R16 R12; var15 = var16[var12]
     180 [-]: FASTCALL1 64 R15 L16; 
     181 [-]: GETIMPORT R14 13; var14 = 0x7B998233
     182 [-]: CALL R14 2 2 ; var14 = var14(var15)
L16: 183 [-]: JUMPIFNOT R14 L20; goto L20 if not var14
     184 [-]: LOADN R14 0  ; var14 = 0
     185 [-]: JUMPIFNOTLT R14 R8 L17; goto L17 if var14 >= var235407362
     186 [-]: SUBK R8 R8 K14; var8 = var8 - 1
     187 [-]: GETUPVAL R14 4; var14 = upvalues[4]
     188 [-]: LOADN R15 0  ; var15 = 0
     189 [-]: SETTABLE R15 R14 R12; var15[var14] = var12
     190 [-]: GETUPVAL R14 7; var14 = upvalues[7]
     191 [-]: LOADN R15 0  ; var15 = 0
     192 [-]: SETTABLE R15 R14 R12; var15[var14] = var12
     193 [-]: GETUPVAL R14 9; var14 = upvalues[9]
     194 [-]: LOADN R15 0  ; var15 = 0
     195 [-]: SETTABLE R15 R14 R12; var15[var14] = var12
     196 [-]: JUMP L20     ; goto L20
L17: 197 [-]: GETUPVAL R14 20; var14 = upvalues[20]
     198 [-]: MOVE R15 R12 ; var15 = var12
     199 [-]: LOADB R16 1  ; var16 = true
     200 [-]: CALL R14 3 1 ; var14(var15, var16)
     201 [-]: JUMP L20     ; goto L20
L18: 202 [-]: GETUPVAL R16 12; var16 = upvalues[12]
     203 [-]: GETTABLE R15 R16 R12; var15 = var16[var12]
     204 [-]: FASTCALL1 64 R15 L19; 
     205 [-]: GETIMPORT R14 13; var14 = 0x7B998233
     206 [-]: CALL R14 2 2 ; var14 = var14(var15)
L19: 207 [-]: JUMPIF R14 L20; goto L20 if var14
     208 [-]: GETUPVAL R15 12; var15 = upvalues[12]
     209 [-]: GETTABLE R14 R15 R12; var14 = var15[var12]
     210 [-]: NAMECALL R14 R14 K52; var15 = var14; var14 = var14[0xA2880940]
     211 [-]: CALL R14 2 1 ; var14(var15)
L20: 212 [-]: FORGLOOP R9 L13 2; 
     213 [-]: GETIMPORT R9 33; var9 = 0xBE190284
     214 [-]: GETUPVAL R11 16; var11 = upvalues[16]
     215 [-]: ADD R13 R5 R6; var13 = var5 + var6
     216 [-]: LOADN R15 0  ; var15 = 0
     217 [-]: GETIMPORT R16 9; var16 = 0xCFC01047
     218 [-]: GETUPVAL R17 4; var17 = upvalues[4]
     219 [-]: CALL R16 2 4 ; var16, var17, var18 = var16(var17)
     220 [-]: FORGPREP_NEXT R16 L22; 
L21: 221 [-]: GETUPVAL R22 14; var22 = upvalues[14]
     222 [-]: GETTABLEKS R21 R22 K15; var21 = var22["A"]
     223 [-]: JUMPIFNOTLE R21 R20 L22; goto L22 if var21 > var235867912
     224 [-]: ADDK R15 R15 K14; var15 = var15 + 1
L22: 225 [-]: FORGLOOP R16 L21 2; 
     226 [-]: MOVE R14 R15 ; var14 = var15
     227 [-]: ADD R12 R13 R14; var12 = var13 + var14
     228 [-]: NAMECALL R9 R9 K53; var10 = var9; var9 = var9[0x751F061D]
     229 [-]: CALL R9 4 1  ; var9(var10, var11, var12)
     230 [-]: GETIMPORT R9 28; var9 = 0x3D106989
     231 [-]: LOADK R10 K54; var10 = "Results after recovering using netvar data:"
     232 [-]: CALL R9 2 1  ; var9(var10)
     233 [-]: GETUPVAL R9 19; var9 = upvalues[19]
     234 [-]: CALL R9 1 1  ; var9()
     235 [-]: JUMP L27     ; goto L27
L23: 236 [-]: GETIMPORT R7 28; var7 = 0x3D106989
     237 [-]: LOADK R8 K55 ; var8 = "Net count doesn't add up, restarting from scratch"
     238 [-]: CALL R7 2 1  ; var7(var8)
     239 [-]: GETUPVAL R7 21; var7 = upvalues[21]
     240 [-]: GETUPVAL R8 6; var8 = upvalues[6]
     241 [-]: GETUPVAL R10 4; var10 = upvalues[4]
     242 [-]: LENGTH R9 R10; var9 = #var10
     243 [-]: CALL R7 3 1  ; var7(var8, var9)
     244 [-]: GETUPVAL R7 21; var7 = upvalues[21]
     245 [-]: GETUPVAL R8 8; var8 = upvalues[8]
     246 [-]: GETUPVAL R10 4; var10 = upvalues[4]
     247 [-]: LENGTH R9 R10; var9 = #var10
     248 [-]: CALL R7 3 1  ; var7(var8, var9)
     249 [-]: GETUPVAL R7 21; var7 = upvalues[21]
     250 [-]: GETUPVAL R8 10; var8 = upvalues[10]
     251 [-]: GETUPVAL R10 4; var10 = upvalues[4]
     252 [-]: LENGTH R9 R10; var9 = #var10
     253 [-]: CALL R7 3 1  ; var7(var8, var9)
     254 [-]: GETUPVAL R7 5; var7 = upvalues[5]
     255 [-]: GETUPVAL R8 6; var8 = upvalues[6]
     256 [-]: GETUPVAL R10 0; var10 = upvalues[0]
     257 [-]: LENGTH R9 R10; var9 = #var10
     258 [-]: CALL R7 3 2  ; var7 = var7(var8, var9)
     259 [-]: SETUPVAL R7 4; upvalues[7] = var4
     260 [-]: GETUPVAL R7 5; var7 = upvalues[5]
     261 [-]: GETUPVAL R8 8; var8 = upvalues[8]
     262 [-]: GETUPVAL R10 0; var10 = upvalues[0]
     263 [-]: LENGTH R9 R10; var9 = #var10
     264 [-]: LOADK R10 K7 ; var10 = 0.0099999997764825821
     265 [-]: CALL R7 4 2  ; var7 = var7(var8, var9, var10)
     266 [-]: SETUPVAL R7 7; upvalues[7] = var7
     267 [-]: GETUPVAL R7 5; var7 = upvalues[5]
     268 [-]: GETUPVAL R8 10; var8 = upvalues[10]
     269 [-]: GETUPVAL R10 0; var10 = upvalues[0]
     270 [-]: LENGTH R9 R10; var9 = #var10
     271 [-]: LOADK R10 K7 ; var10 = 0.0099999997764825821
     272 [-]: CALL R7 4 2  ; var7 = var7(var8, var9, var10)
     273 [-]: SETUPVAL R7 9; upvalues[7] = var9
     274 [-]: GETIMPORT R7 33; var7 = 0xBE190284
     275 [-]: GETUPVAL R9 17; var9 = upvalues[17]
     276 [-]: NAMECALL R7 R7 K56; var8 = var7; var7 = var7[0xB9BFD47C]
     277 [-]: CALL R7 3 1  ; var7(var8, var9)
     278 [-]: GETIMPORT R7 33; var7 = 0xBE190284
     279 [-]: GETUPVAL R9 18; var9 = upvalues[18]
     280 [-]: NAMECALL R7 R7 K56; var8 = var7; var7 = var7[0xB9BFD47C]
     281 [-]: CALL R7 3 1  ; var7(var8, var9)
     282 [-]: GETIMPORT R7 33; var7 = 0xBE190284
     283 [-]: GETUPVAL R9 16; var9 = upvalues[16]
     284 [-]: NAMECALL R7 R7 K56; var8 = var7; var7 = var7[0xB9BFD47C]
     285 [-]: CALL R7 3 1  ; var7(var8, var9)
     286 [-]: GETIMPORT R7 33; var7 = 0xBE190284
     287 [-]: GETUPVAL R9 22; var9 = upvalues[22]
     288 [-]: NAMECALL R7 R7 K56; var8 = var7; var7 = var7[0xB9BFD47C]
     289 [-]: CALL R7 3 1  ; var7(var8, var9)
     290 [-]: GETIMPORT R7 33; var7 = 0xBE190284
     291 [-]: GETUPVAL R9 23; var9 = upvalues[23]
     292 [-]: NAMECALL R7 R7 K56; var8 = var7; var7 = var7[0xB9BFD47C]
     293 [-]: CALL R7 3 1  ; var7(var8, var9)
     294 [-]: GETIMPORT R7 33; var7 = 0xBE190284
     295 [-]: GETUPVAL R9 24; var9 = upvalues[24]
     296 [-]: NAMECALL R7 R7 K56; var8 = var7; var7 = var7[0xB9BFD47C]
     297 [-]: CALL R7 3 1  ; var7(var8, var9)
     298 [-]: GETIMPORT R7 9; var7 = 0xCFC01047
     299 [-]: GETUPVAL R8 0; var8 = upvalues[0]
     300 [-]: CALL R7 2 4  ; var7, var8, var9 = var7(var8)
     301 [-]: FORGPREP_NEXT R7 L26; 
L24: 302 [-]: GETUPVAL R14 12; var14 = upvalues[12]
     303 [-]: GETTABLE R13 R14 R10; var13 = var14[var10]
     304 [-]: FASTCALL1 64 R13 L25; 
     305 [-]: GETIMPORT R12 13; var12 = 0x7B998233
     306 [-]: CALL R12 2 2 ; var12 = var12(var13)
L25: 307 [-]: JUMPIF R12 L26; goto L26 if var12
     308 [-]: GETIMPORT R12 28; var12 = 0x3D106989
     309 [-]: LOADK R14 K57; var14 = "Destroying excavator avatar "
     310 [-]: GETUPVAL R16 12; var16 = upvalues[12]
     311 [-]: GETTABLE R15 R16 R10; var15 = var16[var10]
     312 [-]: NAMECALL R15 R15 K58; var16 = var15; var15 = var15[0xE223E2B1]
     313 [-]: CALL R15 2 2 ; var15 = var15(var16)
     314 [-]: CONCAT R13 R14 R15; var13 = var14 .. var15
     315 [-]: CALL R12 2 1 ; var12(var13)
     316 [-]: GETUPVAL R13 12; var13 = upvalues[12]
     317 [-]: GETTABLE R12 R13 R10; var12 = var13[var10]
     318 [-]: NAMECALL R12 R12 K52; var13 = var12; var12 = var12[0xA2880940]
     319 [-]: CALL R12 2 1 ; var12(var13)
L26: 320 [-]: FORGLOOP R7 L24 2; 
     321 [-]: LOADN R1 0   ; var1 = 0
     322 [-]: GETIMPORT R7 28; var7 = 0x3D106989
     323 [-]: LOADK R8 K59 ; var8 = "Results after restarting (should be all nil/0):"
     324 [-]: CALL R7 2 1  ; var7(var8)
     325 [-]: GETUPVAL R7 19; var7 = upvalues[19]
     326 [-]: CALL R7 1 1  ; var7()
L27: 327 [-]: LOADB R7 1   ; var7 = true
     328 [-]: RETURN R7 1  ; 
L28: 329 [-]: RETURN R0 0  ; 


; Name:            
; Defined at line: 932
; #Upvalues:       12
; #Parameters:     0
; Is_vararg:       0
; Max Stack Size:  20

       0 [-]: GETUPVAL R0 0; var0 = upvalues[0]
       1 [-]: CALL R0 1 2  ; var0 = var0()
       2 [-]: GETIMPORT R2 1; var2 = 0xA8CCD011
       3 [-]: GETIMPORT R6 3; var6 = 0xE7F2B02F
       4 [-]: NAMECALL R6 R6 K4; var7 = var6; var6 = var6[0xEBE2F513]
       5 [-]: CALL R6 2 2  ; var6 = var6(var7)
       6 [-]: GETIMPORT R7 6; var7 = 0x9BA7909F
       7 [-]: LOADK R9 K7  ; var9 = "Server.NumVirtualTestClients"
       8 [-]: NAMECALL R7 R7 K8; var8 = var7; var7 = var7[0x8151451D]
       9 [-]: CALL R7 3 2  ; var7 = var7(var8, var9)
      10 [-]: ADD R5 R6 R7 ; var5 = var6 + var7
      11 [-]: FASTCALL2K 18 R5 K9 L0; 
      12 [-]: LOADK R6 K9  ; var6 = 1
      13 [-]: GETIMPORT R4 12; var4 = 0x5BCED4C4[0xB62ECFE0]
      14 [-]: CALL R4 3 2  ; var4 = var4(var5, var6)
L 0:  15 [-]: FASTCALL2K 19 R4 K13 L1; 
      16 [-]: LOADK R5 K13 ; var5 = 4
      17 [-]: GETIMPORT R3 15; var3 = 0x5BCED4C4[0xAC1B386A]
      18 [-]: CALL R3 3 2  ; var3 = var3(var4, var5)
L 1:  19 [-]: GETTABLE R1 R2 R3; var1 = var2[var3]
      20 [-]: GETIMPORT R2 17; var2 = 0xBE190284
      21 [-]: GETUPVAL R4 1; var4 = upvalues[1]
      22 [-]: LOADN R5 0   ; var5 = 0
      23 [-]: NAMECALL R2 R2 K18; var3 = var2; var2 = var2[0x0EB34C69]
      24 [-]: CALL R2 4 2  ; var2 = var2(var3, var4, var5)
      25 [-]: GETIMPORT R3 17; var3 = 0xBE190284
      26 [-]: GETUPVAL R5 2; var5 = upvalues[2]
      27 [-]: LOADN R6 0   ; var6 = 0
      28 [-]: NAMECALL R3 R3 K18; var4 = var3; var3 = var3[0x0EB34C69]
      29 [-]: CALL R3 4 2  ; var3 = var3(var4, var5, var6)
      30 [-]: GETIMPORT R4 17; var4 = 0xBE190284
      31 [-]: GETUPVAL R6 3; var6 = upvalues[3]
      32 [-]: LOADN R7 0   ; var7 = 0
      33 [-]: NAMECALL R4 R4 K18; var5 = var4; var4 = var4[0x0EB34C69]
      34 [-]: CALL R4 4 2  ; var4 = var4(var5, var6, var7)
      35 [-]: LOADN R6 0   ; var6 = 0
      36 [-]: GETIMPORT R7 20; var7 = 0xCFC01047
      37 [-]: GETUPVAL R8 4; var8 = upvalues[4]
      38 [-]: CALL R7 2 4  ; var7, var8, var9 = var7(var8)
      39 [-]: FORGPREP_NEXT R7 L3; 
L 2:  40 [-]: GETUPVAL R13 5; var13 = upvalues[5]
      41 [-]: GETTABLEKS R12 R13 K21; var12 = var13["A"]
      42 [-]: JUMPIFNOTLE R12 R11 L3; goto L3 if var12 > var151389704
      43 [-]: ADDK R6 R6 K9; var6 = var6 + 1
L 3:  44 [-]: FORGLOOP R7 L2 2; 
      45 [-]: MOVE R5 R6   ; var5 = var6
      46 [-]: SUB R6 R2 R1 ; var6 = var2 - var1
      47 [-]: GETIMPORT R7 23; var7 = 0x3D106989
      48 [-]: LOADK R8 K24 ; var8 = "Before net data"
      49 [-]: CALL R7 2 1  ; var7(var8)
      50 [-]: GETUPVAL R7 6; var7 = upvalues[6]
      51 [-]: CALL R7 1 1  ; var7()
      52 [-]: LOADN R7 1   ; var7 = 1
      53 [-]: JUMPIFNOTLT R7 R5 L6; goto L6 if var7 >= var67632
      54 [-]: LOADN R8 1   ; var8 = 1
      55 [-]: ADD R12 R3 R4; var12 = var3 + var4
      56 [-]: SUB R11 R1 R12; var11 = var1 - var12
      57 [-]: FASTCALL2 19 R5 R11 L4; 
      58 [-]: MOVE R10 R5  ; var10 = var5
      59 [-]: GETIMPORT R9 15; var9 = 0x5BCED4C4[0xAC1B386A]
      60 [-]: CALL R9 3 2  ; var9 = var9(var10, var11)
L 4:  61 [-]: FASTCALL2 18 R8 R9 L5; 
      62 [-]: GETIMPORT R7 12; var7 = 0x5BCED4C4[0xB62ECFE0]
      63 [-]: CALL R7 3 2  ; var7 = var7(var8, var9)
L 5:  64 [-]: MOVE R5 R7   ; var5 = var7
L 6:  65 [-]: LOADN R7 1   ; var7 = 1
      66 [-]: JUMPIFNOTLE R7 R3 L9; goto L9 if var7 > var67632
      67 [-]: LOADN R8 1   ; var8 = 1
      68 [-]: SUB R11 R2 R4; var11 = var2 - var4
      69 [-]: FASTCALL2 19 R3 R11 L7; 
      70 [-]: MOVE R10 R3  ; var10 = var3
      71 [-]: GETIMPORT R9 15; var9 = 0x5BCED4C4[0xAC1B386A]
      72 [-]: CALL R9 3 2  ; var9 = var9(var10, var11)
L 7:  73 [-]: FASTCALL2 18 R8 R9 L8; 
      74 [-]: GETIMPORT R7 12; var7 = 0x5BCED4C4[0xB62ECFE0]
      75 [-]: CALL R7 3 2  ; var7 = var7(var8, var9)
L 8:  76 [-]: MOVE R3 R7   ; var3 = var7
      77 [-]: GETIMPORT R7 17; var7 = 0xBE190284
      78 [-]: GETUPVAL R9 2; var9 = upvalues[2]
      79 [-]: MOVE R10 R3  ; var10 = var3
      80 [-]: NAMECALL R7 R7 K25; var8 = var7; var7 = var7[0x751F061D]
      81 [-]: CALL R7 4 1  ; var7(var8, var9, var10)
L 9:  82 [-]: LOADN R8 0   ; var8 = 0
      83 [-]: FASTCALL2K 18 R5 K9 L10; 
      84 [-]: MOVE R14 R5  ; var14 = var5
      85 [-]: LOADK R15 K9 ; var15 = 1
      86 [-]: GETIMPORT R13 12; var13 = 0x5BCED4C4[0xB62ECFE0]
      87 [-]: CALL R13 3 2 ; var13 = var13(var14, var15)
L10:  88 [-]: SUB R12 R1 R13; var12 = var1 - var13
      89 [-]: SUB R11 R12 R3; var11 = var12 - var3
      90 [-]: FASTCALL2 19 R4 R11 L11; 
      91 [-]: MOVE R10 R4  ; var10 = var4
      92 [-]: GETIMPORT R9 15; var9 = 0x5BCED4C4[0xAC1B386A]
      93 [-]: CALL R9 3 2  ; var9 = var9(var10, var11)
L11:  94 [-]: FASTCALL2 18 R8 R9 L12; 
      95 [-]: GETIMPORT R7 12; var7 = 0x5BCED4C4[0xB62ECFE0]
      96 [-]: CALL R7 3 2  ; var7 = var7(var8, var9)
L12:  97 [-]: MOVE R4 R7   ; var4 = var7
      98 [-]: GETIMPORT R7 17; var7 = 0xBE190284
      99 [-]: GETUPVAL R9 3; var9 = upvalues[3]
     100 [-]: MOVE R10 R4  ; var10 = var4
     101 [-]: NAMECALL R7 R7 K25; var8 = var7; var7 = var7[0x751F061D]
     102 [-]: CALL R7 4 1  ; var7(var8, var9, var10)
     103 [-]: ADD R7 R3 R4 ; var7 = var3 + var4
     104 [-]: ADD R2 R7 R5 ; var2 = var7 + var5
     105 [-]: GETIMPORT R7 17; var7 = 0xBE190284
     106 [-]: GETUPVAL R9 1; var9 = upvalues[1]
     107 [-]: MOVE R10 R2  ; var10 = var2
     108 [-]: NAMECALL R7 R7 K25; var8 = var7; var7 = var7[0x751F061D]
     109 [-]: CALL R7 4 1  ; var7(var8, var9, var10)
     110 [-]: GETIMPORT R7 23; var7 = 0x3D106989
     111 [-]: LOADK R8 K26 ; var8 = "After net data"
     112 [-]: CALL R7 2 1  ; var7(var8)
     113 [-]: GETUPVAL R7 6; var7 = upvalues[6]
     114 [-]: CALL R7 1 1  ; var7()
     115 [-]: LOADN R7 0   ; var7 = 0
     116 [-]: GETIMPORT R8 20; var8 = 0xCFC01047
     117 [-]: GETUPVAL R9 4; var9 = upvalues[4]
     118 [-]: CALL R8 2 4  ; var8, var9, var10 = var8(var9)
     119 [-]: FORGPREP_NEXT R8 L14; 
L13: 120 [-]: GETUPVAL R14 5; var14 = upvalues[5]
     121 [-]: GETTABLEKS R13 R14 K21; var13 = var14["A"]
     122 [-]: JUMPIFNOTLE R13 R12 L14; goto L14 if var13 > var151455496
     123 [-]: ADDK R7 R7 K9; var7 = var7 + 1
L14: 124 [-]: FORGLOOP R8 L13 2; 
     125 [-]: MOVE R5 R7   ; var5 = var7
     126 [-]: JUMPIF R0 L18; goto L18 if var0
     127 [-]: GETIMPORT R7 23; var7 = 0x3D106989
     128 [-]: LOADK R9 K27 ; var9 = "Before extra: "
     129 [-]: MOVE R10 R6  ; var10 = var6
     130 [-]: CONCAT R8 R9 R10; var8 = var9 .. var10
     131 [-]: CALL R7 2 1  ; var7(var8)
     132 [-]: SUB R7 R5 R1 ; var7 = var5 - var1
     133 [-]: ADD R6 R7 R4 ; var6 = var7 + var4
     134 [-]: GETIMPORT R7 23; var7 = 0x3D106989
     135 [-]: LOADK R9 K28 ; var9 = "Extra excavator for current SquadSize("
     136 [-]: GETIMPORT R16 3; var16 = 0xE7F2B02F
     137 [-]: NAMECALL R16 R16 K4; var17 = var16; var16 = var16[0xEBE2F513]
     138 [-]: CALL R16 2 2 ; var16 = var16(var17)
     139 [-]: GETIMPORT R17 6; var17 = 0x9BA7909F
     140 [-]: LOADK R19 K7 ; var19 = "Server.NumVirtualTestClients"
     141 [-]: NAMECALL R17 R17 K8; var18 = var17; var17 = var17[0x8151451D]
     142 [-]: CALL R17 3 2 ; var17 = var17(var18, var19)
     143 [-]: ADD R15 R16 R17; var15 = var16 + var17
     144 [-]: FASTCALL2K 18 R15 K9 L15; 
     145 [-]: LOADK R16 K9 ; var16 = 1
     146 [-]: GETIMPORT R14 12; var14 = 0x5BCED4C4[0xB62ECFE0]
     147 [-]: CALL R14 3 2 ; var14 = var14(var15, var16)
L15: 148 [-]: FASTCALL2K 19 R14 K13 L16; 
     149 [-]: LOADK R15 K13; var15 = 4
     150 [-]: GETIMPORT R13 15; var13 = 0x5BCED4C4[0xAC1B386A]
     151 [-]: CALL R13 3 2 ; var13 = var13(var14, var15)
L16: 152 [-]: MOVE R10 R13 ; var10 = var13
     153 [-]: LOADK R11 K29; var11 = "): "
     154 [-]: MOVE R12 R6  ; var12 = var6
     155 [-]: CONCAT R8 R9 R12; var8 = var9 .. var12
     156 [-]: CALL R7 2 1  ; var7(var8)
     157 [-]: LOADN R7 0   ; var7 = 0
     158 [-]: JUMPIFNOTLT R7 R6 L18; goto L18 if var7 >= var1509153
     159 [-]: GETIMPORT R7 23; var7 = 0x3D106989
     160 [-]: LOADK R8 K30 ; var8 = "Will destroy extra excavators"
     161 [-]: CALL R7 2 1  ; var7(var8)
     162 [-]: GETUPVAL R7 7; var7 = upvalues[7]
     163 [-]: CALL R7 1 2  ; var7 = var7()
     164 [-]: GETIMPORT R8 33; var8 = 0x33BDD652[0xF21B1D8E]
     165 [-]: MOVE R9 R7   ; var9 = var7
     166 [-]: NEWCLOSURE R10 P0; 
     167 [-]: CAPTURE UPVAL U4; 
     168 [-]: CALL R8 3 1  ; var8(var9, var10)
     169 [-]: LOADN R10 1  ; var10 = 1
     170 [-]: MOVE R8 R6   ; var8 = var6
     171 [-]: LOADN R9 1   ; var9 = 1
     172 [-]: FORNPREP R8 L18; nforprep start - [escape at L18] -- var8 = iterator
L17: 173 [-]: GETIMPORT R11 23; var11 = 0x3D106989
     174 [-]: LOADK R13 K34; var13 = "Will destroy excavator ID:"
     175 [-]: GETTABLE R14 R7 R10; var14 = var7[var10]
     176 [-]: CONCAT R12 R13 R14; var12 = var13 .. var14
     177 [-]: CALL R11 2 1 ; var11(var12)
     178 [-]: GETUPVAL R11 8; var11 = upvalues[8]
     179 [-]: GETTABLE R12 R7 R10; var12 = var7[var10]
     180 [-]: LOADB R13 1  ; var13 = true
     181 [-]: CALL R11 3 1 ; var11(var12, var13)
     182 [-]: FORNLOOP R8 L17; nforloop end - iterate + goto L17
L18: 183 [-]: GETUPVAL R7 7; var7 = upvalues[7]
     184 [-]: CALL R7 1 2  ; var7 = var7()
     185 [-]: GETIMPORT R8 20; var8 = 0xCFC01047
     186 [-]: MOVE R9 R7   ; var9 = var7
     187 [-]: CALL R8 2 4  ; var8, var9, var10 = var8(var9)
     188 [-]: FORGPREP_NEXT R8 L21; 
L19: 189 [-]: GETUPVAL R14 9; var14 = upvalues[9]
     190 [-]: GETTABLE R13 R14 R12; var13 = var14[var12]
     191 [-]: NAMECALL R13 R13 K35; var14 = var13; var13 = var13[0xC8442850]
     192 [-]: CALL R13 2 2 ; var13 = var13(var14)
     193 [-]: LOADK R14 K36; var14 = 0.25
     194 [-]: JUMPIFNOTLT R13 R14 L20; goto L20 if var13 >= var593468
     195 [-]: GETUPVAL R14 9; var14 = upvalues[9]
     196 [-]: GETTABLE R13 R14 R12; var13 = var14[var12]
     197 [-]: GETUPVAL R17 9; var17 = upvalues[9]
     198 [-]: GETTABLE R16 R17 R12; var16 = var17[var12]
     199 [-]: NAMECALL R16 R16 K37; var17 = var16; var16 = var16[0xB40C191A]
     200 [-]: CALL R16 2 2 ; var16 = var16(var17)
     201 [-]: MULK R15 R16 K36; var15 = var16 * 0.25
     202 [-]: NAMECALL R13 R13 K38; var14 = var13; var13 = var13[0x014DB014]
     203 [-]: CALL R13 3 1 ; var13(var14, var15)
L20: 204 [-]: GETUPVAL R13 10; var13 = upvalues[10]
     205 [-]: MOVE R14 R12 ; var14 = var12
     206 [-]: CALL R13 2 1 ; var13(var14)
L21: 207 [-]: FORGLOOP R8 L19 2; 
     208 [-]: GETUPVAL R8 11; var8 = upvalues[11]
     209 [-]: LOADNIL R9   ; var9 = nil
     210 [-]: LOADN R10 3  ; var10 = 3
     211 [-]: CALL R8 3 1  ; var8(var9, var10)
     212 [-]: RETURN R0 0  ; 


; Name:            
; Defined at line: 988
; #Upvalues:       15
; #Parameters:     0
; Is_vararg:       0
; Max Stack Size:  10

       0 [-]: GETUPVAL R0 1; var0 = upvalues[1]
       1 [-]: NAMECALL R0 R0 K0; var1 = var0; var0 = var0[0x209398C2]
       2 [-]: CALL R0 2 2  ; var0 = var0(var1)
       3 [-]: SETUPVAL R0 0; upvalues[0] = var0
       4 [-]: GETUPVAL R0 0; var0 = upvalues[0]
       5 [-]: GETUPVAL R2 2; var2 = upvalues[2]
       6 [-]: GETTABLEKS R1 R2 K1; var1 = var2["START"]
       7 [-]: JUMPIFNOTEQ R0 R1 L0; goto L0 if var0 ~= var196641
       8 [-]: GETIMPORT R0 3; var0 = 0x3D106989
       9 [-]: LOADK R1 K4  ; var1 = "Start state"
      10 [-]: CALL R0 2 1  ; var0(var1)
      11 [-]: GETUPVAL R1 3; var1 = upvalues[3]
      12 [-]: GETTABLEKS R0 R1 K5; var0 = var1[0x9742B85B]
      13 [-]: GETUPVAL R1 4; var1 = upvalues[4]
      14 [-]: GETIMPORT R2 7; var2 = 0x0469F296
      15 [-]: LOADK R3 K8  ; var3 = "Arrival"
      16 [-]: CALL R2 2 2  ; var2 = var2(var3)
      17 [-]: LOADB R3 1   ; var3 = true
      18 [-]: CALL R0 4 1  ; var0(var1, var2, var3)
      19 [-]: GETUPVAL R0 5; var0 = upvalues[5]
      20 [-]: CALL R0 1 1  ; var0()
      21 [-]: RETURN R0 0  ; 
L 0:  22 [-]: GETUPVAL R0 0; var0 = upvalues[0]
      23 [-]: GETUPVAL R2 2; var2 = upvalues[2]
      24 [-]: GETTABLEKS R1 R2 K9; var1 = var2["EXCAVATION"]
      25 [-]: JUMPIFNOTEQ R0 R1 L5; goto L5 if var0 ~= var196641
      26 [-]: GETIMPORT R0 3; var0 = 0x3D106989
      27 [-]: LOADK R1 K10 ; var1 = "Excavation state"
      28 [-]: CALL R0 2 1  ; var0(var1)
      29 [-]: GETUPVAL R0 6; var0 = upvalues[6]
      30 [-]: CALL R0 1 1  ; var0()
      31 [-]: GETUPVAL R0 8; var0 = upvalues[8]
      32 [-]: LOADN R2 3   ; var2 = 3
      33 [-]: GETUPVAL R3 9; var3 = upvalues[9]
      34 [-]: LOADB R4 1   ; var4 = true
      35 [-]: NAMECALL R0 R0 K11; var1 = var0; var0 = var0[0xBD2E96EA]
      36 [-]: CALL R0 5 2  ; var0 = var0(var1, var2, var3, var4)
      37 [-]: SETUPVAL R0 7; upvalues[0] = var7
      38 [-]: GETUPVAL R1 10; var1 = upvalues[10]
      39 [-]: GETTABLEKS R0 R1 K12; var0 = var1[0xA1DF01D6]
      40 [-]: GETUPVAL R2 11; var2 = upvalues[11]
      41 [-]: GETTABLEKS R1 R2 K13; var1 = var2["EXCAVATION_OBJECTIVE"]
      42 [-]: GETUPVAL R3 10; var3 = upvalues[10]
      43 [-]: GETTABLEKS R2 R3 K14; var2 = var3["GENERIC_ICON"]
      44 [-]: CALL R0 3 1  ; var0(var1, var2)
      45 [-]: GETUPVAL R1 10; var1 = upvalues[10]
      46 [-]: GETTABLEKS R0 R1 K15; var0 = var1[0xA8FBEA61]
      47 [-]: GETUPVAL R2 11; var2 = upvalues[11]
      48 [-]: GETTABLEKS R1 R2 K16; var1 = var2["BONUS_OBJECTIVE"]
      49 [-]: CALL R0 2 1  ; var0(var1)
      50 [-]: GETIMPORT R0 18; var0 = 0xBE190284
      51 [-]: GETUPVAL R2 12; var2 = upvalues[12]
      52 [-]: LOADN R3 0   ; var3 = 0
      53 [-]: NAMECALL R0 R0 K19; var1 = var0; var0 = var0[0x0EB34C69]
      54 [-]: CALL R0 4 2  ; var0 = var0(var1, var2, var3)
      55 [-]: GETIMPORT R2 21; var2 = 0xA8CCD011
      56 [-]: GETIMPORT R6 23; var6 = 0xE7F2B02F
      57 [-]: NAMECALL R6 R6 K24; var7 = var6; var6 = var6[0xEBE2F513]
      58 [-]: CALL R6 2 2  ; var6 = var6(var7)
      59 [-]: GETIMPORT R7 26; var7 = 0x9BA7909F
      60 [-]: LOADK R9 K27 ; var9 = "Server.NumVirtualTestClients"
      61 [-]: NAMECALL R7 R7 K28; var8 = var7; var7 = var7[0x8151451D]
      62 [-]: CALL R7 3 2  ; var7 = var7(var8, var9)
      63 [-]: ADD R5 R6 R7 ; var5 = var6 + var7
      64 [-]: FASTCALL2K 18 R5 K29 L1; 
      65 [-]: LOADK R6 K29 ; var6 = 1
      66 [-]: GETIMPORT R4 32; var4 = 0x5BCED4C4[0xB62ECFE0]
      67 [-]: CALL R4 3 2  ; var4 = var4(var5, var6)
L 1:  68 [-]: FASTCALL2K 19 R4 K33 L2; 
      69 [-]: LOADK R5 K33 ; var5 = 4
      70 [-]: GETIMPORT R3 35; var3 = 0x5BCED4C4[0xAC1B386A]
      71 [-]: CALL R3 3 2  ; var3 = var3(var4, var5)
L 2:  72 [-]: GETTABLE R1 R2 R3; var1 = var2[var3]
      73 [-]: GETUPVAL R3 10; var3 = upvalues[10]
      74 [-]: GETTABLEKS R2 R3 K36; var2 = var3[0xEA753E99]
      75 [-]: GETUPVAL R4 11; var4 = upvalues[11]
      76 [-]: GETTABLEKS R3 R4 K37; var3 = var4["EXCAVATION_PROGRESS"]
      77 [-]: SUBK R6 R1 K29; var6 = var1 - 1
      78 [-]: FASTCALL2 19 R0 R6 L3; 
      79 [-]: MOVE R5 R0   ; var5 = var0
      80 [-]: GETIMPORT R4 35; var4 = 0x5BCED4C4[0xAC1B386A]
      81 [-]: CALL R4 3 2  ; var4 = var4(var5, var6)
L 3:  82 [-]: MOVE R5 R1   ; var5 = var1
      83 [-]: CALL R2 4 1  ; var2(var3, var4, var5)
      84 [-]: GETIMPORT R2 18; var2 = 0xBE190284
      85 [-]: NAMECALL R2 R2 K38; var3 = var2; var2 = var2[0xABF50B1C]
      86 [-]: CALL R2 2 2  ; var2 = var2(var3)
      87 [-]: FASTCALL1 64 R2 L4; 
      88 [-]: MOVE R4 R2   ; var4 = var2
      89 [-]: GETIMPORT R3 40; var3 = 0x7B998233
      90 [-]: CALL R3 2 2  ; var3 = var3(var4)
L 4:  91 [-]: JUMPIF R3 L7 ; goto L7 if var3
      92 [-]: LOADN R5 0   ; var5 = 0
      93 [-]: NAMECALL R3 R2 K41; var4 = var2; var3 = var2[0x8CFF1D7A]
      94 [-]: CALL R3 3 1  ; var3(var4, var5)
      95 [-]: LOADB R5 0   ; var5 = false
      96 [-]: NAMECALL R3 R2 K42; var4 = var2; var3 = var2[0x543A0B5E]
      97 [-]: CALL R3 3 1  ; var3(var4, var5)
      98 [-]: RETURN R0 0  ; 
L 5:  99 [-]: GETUPVAL R0 0; var0 = upvalues[0]
     100 [-]: GETUPVAL R2 2; var2 = upvalues[2]
     101 [-]: GETTABLEKS R1 R2 K43; var1 = var2["FINISH"]
     102 [-]: JUMPIFNOTEQ R0 R1 L7; goto L7 if var0 ~= var1179681
     103 [-]: GETIMPORT R0 18; var0 = 0xBE190284
     104 [-]: GETUPVAL R2 12; var2 = upvalues[12]
     105 [-]: NAMECALL R0 R0 K19; var1 = var0; var0 = var0[0x0EB34C69]
     106 [-]: CALL R0 3 2  ; var0 = var0(var1, var2)
     107 [-]: LOADN R1 0   ; var1 = 0
     108 [-]: JUMPIFNOTLE R0 R1 L6; goto L6 if var0 > var524604
     109 [-]: GETUPVAL R1 8; var1 = upvalues[8]
     110 [-]: NAMECALL R1 R1 K44; var2 = var1; var1 = var1[0x7076B095]
     111 [-]: CALL R1 2 1  ; var1(var2)
     112 [-]: GETUPVAL R1 13; var1 = upvalues[13]
     113 [-]: LOADN R3 5   ; var3 = 5
     114 [-]: NAMECALL R1 R1 K45; var2 = var1; var1 = var1[0xFE9DC265]
     115 [-]: CALL R1 3 1  ; var1(var2, var3)
     116 [-]: GETIMPORT R1 3; var1 = 0x3D106989
     117 [-]: LOADK R2 K46 ; var2 = "Encounter failed"
     118 [-]: CALL R1 2 1  ; var1(var2)
     119 [-]: RETURN R0 0  ; 
L 6: 120 [-]: GETUPVAL R1 14; var1 = upvalues[14]
     121 [-]: CALL R1 1 1  ; var1()
     122 [-]: RETURN R0 0  ; 
L 7: 123 [-]: RETURN R0 0  ; 


; Name:            
; Defined at line: 1021
; #Upvalues:       19
; #Parameters:     1
; Is_vararg:       0
; Max Stack Size:  9

       0 [-]: LOADB R1 0   ; var1 = false
       1 [-]: JUMPIFNOT R1 L0; goto L0 if not var1
       2 [-]: GETIMPORT R1 1; var1 = 0x89326C93
       3 [-]: NAMECALL R1 R1 K2; var2 = var1; var1 = var1[0xFB64E76C]
       4 [-]: CALL R1 2 2  ; var1 = var1(var2)
       5 [-]: GETIMPORT R3 4; var3 = 0x0469F296
       6 [-]: LOADK R4 K5  ; var4 = "DEBUG_SkipPhase"
       7 [-]: CALL R3 2 2  ; var3 = var3(var4)
       8 [-]: GETIMPORT R4 7; var4 = 0x9BA7909F
       9 [-]: LOADK R6 K8  ; var6 = "SHOW_LEVEL_MAP"
      10 [-]: NAMECALL R4 R4 K9; var5 = var4; var4 = var4[0xFBDF1860]
      11 [-]: CALL R4 3 2  ; var4 = var4(var5, var6)
      12 [-]: LOADK R5 K10 ; var5 = "SkipPhase"
      13 [-]: NAMECALL R1 R1 K11; var2 = var1; var1 = var1[0x1064A8AC]
      14 [-]: CALL R1 5 1  ; var1(var2, var3, var4, var5)
L 0:  15 [-]: GETIMPORT R1 1; var1 = 0x89326C93
      16 [-]: NAMECALL R1 R1 K12; var2 = var1; var1 = var1[0x29EF273D]
      17 [-]: CALL R1 2 2  ; var1 = var1(var2)
      18 [-]: NAMECALL R1 R1 K13; var2 = var1; var1 = var1[0x66905CB0]
      19 [-]: CALL R1 2 2  ; var1 = var1(var2)
      20 [-]: SETUPVAL R1 0; upvalues[1] = var0
L 1:  21 [-]: GETUPVAL R1 0; var1 = upvalues[0]
      22 [-]: NAMECALL R1 R1 K14; var2 = var1; var1 = var1[0xA2D83ED4]
      23 [-]: CALL R1 2 2  ; var1 = var1(var2)
      24 [-]: JUMPIF R1 L2 ; goto L2 if var1
      25 [-]: GETIMPORT R1 16; var1 = 0xCBD666E1
      26 [-]: LOADN R2 0   ; var2 = 0
      27 [-]: CALL R1 2 1  ; var1(var2)
      28 [-]: JUMPBACK L1  ; goto L1
L 2:  29 [-]: NAMECALL R1 R0 K17; var2 = var0; var1 = var0[0x891629FA]
      30 [-]: CALL R1 2 2  ; var1 = var1(var2)
      31 [-]: SETUPVAL R1 1; upvalues[1] = var1
      32 [-]: SETUPVAL R0 2; upvalues[0] = var2
      33 [-]: NAMECALL R1 R0 K18; var2 = var0; var1 = var0[0xD1586535]
      34 [-]: CALL R1 2 2  ; var1 = var1(var2)
      35 [-]: SETUPVAL R1 3; upvalues[1] = var3
      36 [-]: NAMECALL R1 R0 K19; var2 = var0; var1 = var0[0x4C976EDA]
      37 [-]: CALL R1 2 2  ; var1 = var1(var2)
      38 [-]: NAMECALL R2 R1 K20; var3 = var1; var2 = var1[0xE4C355E2]
      39 [-]: CALL R2 2 2  ; var2 = var2(var3)
      40 [-]: SETUPVAL R2 4; upvalues[2] = var4
      41 [-]: GETUPVAL R3 6; var3 = upvalues[6]
      42 [-]: GETTABLEKS R2 R3 K21; var2 = var3[0xDE474187]
      43 [-]: CALL R2 1 2  ; var2 = var2()
      44 [-]: SETUPVAL R2 5; upvalues[2] = var5
      45 [-]: GETUPVAL R2 2; var2 = upvalues[2]
      46 [-]: LOADK R4 K22 ; var4 = "PlayersLeaving"
      47 [-]: GETUPVAL R5 7; var5 = upvalues[7]
      48 [-]: NAMECALL R2 R2 K23; var3 = var2; var2 = var2[0xE19C3F44]
      49 [-]: CALL R2 4 1  ; var2(var3, var4, var5)
      50 [-]: GETUPVAL R2 2; var2 = upvalues[2]
      51 [-]: LOADK R4 K24 ; var4 = "PlayersReturning"
      52 [-]: GETUPVAL R5 8; var5 = upvalues[8]
      53 [-]: NAMECALL R2 R2 K25; var3 = var2; var2 = var2[0x3F86F5A0]
      54 [-]: CALL R2 4 1  ; var2(var3, var4, var5)
      55 [-]: GETUPVAL R2 1; var2 = upvalues[1]
      56 [-]: LOADK R4 K26 ; var4 = "OnAgentRegistered"
      57 [-]: GETIMPORT R5 4; var5 = 0x0469F296
      58 [-]: LOADK R6 K27 ; var6 = "DynamicExcavationRegistration"
      59 [-]: CALL R5 2 2  ; var5 = var5(var6)
      60 [-]: LOADB R6 1   ; var6 = true
      61 [-]: NAMECALL R2 R2 K28; var3 = var2; var2 = var2[0x5B344F44]
      62 [-]: CALL R2 5 1  ; var2(var3, var4, var5, var6)
      63 [-]: GETIMPORT R2 1; var2 = 0x89326C93
      64 [-]: LOADK R4 K29 ; var4 = "OnPlayersChanged"
      65 [-]: NAMECALL R2 R2 K30; var3 = var2; var2 = var2[0xB7D33840]
      66 [-]: CALL R2 3 1  ; var2(var3, var4)
      67 [-]: NAMECALL R2 R0 K31; var3 = var0; var2 = var0[0xEFE6CAD1]
      68 [-]: CALL R2 2 2  ; var2 = var2(var3)
      69 [-]: LOADN R3 1   ; var3 = 1
      70 [-]: JUMPIFNOTEQ R2 R3 L3; goto L3 if var2 ~= var132144
      71 [-]: LOADN R4 2   ; var4 = 2
      72 [-]: NAMECALL R2 R0 K32; var3 = var0; var2 = var0[0xFE9DC265]
      73 [-]: CALL R2 3 1  ; var2(var3, var4)
L 3:  74 [-]: NEWTABLE R2 0 6; var2 = {}
      75 [-]: GETUPVAL R3 9; var3 = upvalues[9]
      76 [-]: GETUPVAL R4 10; var4 = upvalues[10]
      77 [-]: GETUPVAL R5 11; var5 = upvalues[11]
      78 [-]: GETUPVAL R6 12; var6 = upvalues[12]
      79 [-]: GETUPVAL R7 13; var7 = upvalues[13]
      80 [-]: GETUPVAL R8 14; var8 = upvalues[14]
      81 [-]: SETLIST R2 R3 6 [1]; var2[1] = var3; var2[2] = var4; var2[3] = var5; var2[4] = var6; var2[5] = var7; var2[6] = var8; var2[7] = var9; 
      82 [-]: GETUPVAL R4 16; var4 = upvalues[16]
      83 [-]: GETTABLEKS R3 R4 K33; var3 = var4[0xC9013731]
      84 [-]: GETUPVAL R4 17; var4 = upvalues[17]
      85 [-]: GETUPVAL R5 2; var5 = upvalues[2]
      86 [-]: MOVE R6 R2   ; var6 = var2
      87 [-]: CALL R3 4 2  ; var3 = var3(var4, var5, var6)
      88 [-]: SETUPVAL R3 15; upvalues[3] = var15
      89 [-]: GETUPVAL R3 2; var3 = upvalues[2]
      90 [-]: NAMECALL R3 R3 K34; var4 = var3; var3 = var3[0xABE61691]
      91 [-]: CALL R3 2 2  ; var3 = var3(var4)
      92 [-]: GETUPVAL R4 15; var4 = upvalues[15]
      93 [-]: JUMPXEQKN R3 K35 L4; 
      94 [-]: MOVE R6 R3   ; var6 = var3
      95 [-]: JUMPIF R6 L5 ; goto L5 if var6
L 4:  96 [-]: GETUPVAL R7 18; var7 = upvalues[18]
      97 [-]: GETTABLEKS R6 R7 K36; var6 = var7["START"]
L 5:  98 [-]: NAMECALL R4 R4 K37; var5 = var4; var4 = var4[0x8ABFF40E]
      99 [-]: CALL R4 3 1  ; var4(var5, var6)
     100 [-]: RETURN R0 0  ; 


; Name:            
; Defined at line: 1055
; #Upvalues:       19
; #Parameters:     0
; Is_vararg:       0
; Max Stack Size:  11

       0 [-]: GETIMPORT R0 1; var0 = 0x89326C93
       1 [-]: NAMECALL R0 R0 K2; var1 = var0; var0 = var0[0x8B5B1F58]
       2 [-]: CALL R0 2 2  ; var0 = var0(var1)
       3 [-]: GETIMPORT R1 4; var1 = 0xC8802016
       4 [-]: MOVE R2 R0   ; var2 = var0
       5 [-]: CALL R1 2 4  ; var1, var2, var3 = var1(var2)
       6 [-]: FORGPREP_INEXT R1 L1; 
L 0:   7 [-]: GETUPVAL R8 0; var8 = upvalues[0]
       8 [-]: NAMECALL R6 R5 K5; var7 = var5; var6 = var5[0x0866B4BD]
       9 [-]: CALL R6 3 2  ; var6 = var6(var7, var8)
      10 [-]: JUMPIFNOT R6 L1; goto L1 if not var6
      11 [-]: GETUPVAL R8 0; var8 = upvalues[0]
      12 [-]: NAMECALL R6 R5 K6; var7 = var5; var6 = var5[0x35B09371]
      13 [-]: CALL R6 3 1  ; var6(var7, var8)
L 1:  14 [-]: FORGLOOP R1 L0 2 [inext]; 
      15 [-]: GETUPVAL R1 1; var1 = upvalues[1]
      16 [-]: CALL R1 1 2  ; var1 = var1()
      17 [-]: LOADN R4 1   ; var4 = 1
      18 [-]: LENGTH R2 R1 ; var2 = #var1
      19 [-]: LOADN R3 1   ; var3 = 1
      20 [-]: FORNPREP R2 L3; nforprep start - [escape at L3] -- var2 = iterator
L 2:  21 [-]: GETUPVAL R5 2; var5 = upvalues[2]
      22 [-]: GETTABLE R6 R1 R4; var6 = var1[var4]
      23 [-]: LOADB R7 1   ; var7 = true
      24 [-]: CALL R5 3 1  ; var5(var6, var7)
      25 [-]: FORNLOOP R2 L2; nforloop end - iterate + goto L2
L 3:  26 [-]: GETIMPORT R2 1; var2 = 0x89326C93
      27 [-]: GETUPVAL R4 3; var4 = upvalues[3]
      28 [-]: GETUPVAL R5 4; var5 = upvalues[4]
      29 [-]: LOADN R6 0   ; var6 = 0
      30 [-]: GETUPVAL R7 5; var7 = upvalues[5]
      31 [-]: NAMECALL R7 R7 K7; var8 = var7; var7 = var7[0x7C97B143]
      32 [-]: CALL R7 2 0  ; var7, ... = var7(var8)
      33 [-]: NAMECALL R2 R2 K8; var3 = var2; var2 = var2[0xFB669000]
      34 [-]: CALL R2 0 2  ; var2 = var2(var3, ...)
      35 [-]: GETIMPORT R3 4; var3 = 0xC8802016
      36 [-]: MOVE R4 R2   ; var4 = var2
      37 [-]: CALL R3 2 4  ; var3, var4, var5 = var3(var4)
      38 [-]: FORGPREP_INEXT R3 L5; 
L 4:  39 [-]: NAMECALL R8 R7 K9; var9 = var7; var8 = var7[0xA2880940]
      40 [-]: CALL R8 2 1  ; var8(var9)
L 5:  41 [-]: FORGLOOP R3 L4 2 [inext]; 
      42 [-]: GETUPVAL R3 6; var3 = upvalues[6]
      43 [-]: GETUPVAL R5 7; var5 = upvalues[7]
      44 [-]: LOADB R6 1   ; var6 = true
      45 [-]: NAMECALL R3 R3 K10; var4 = var3; var3 = var3[0xFA6491F5]
      46 [-]: CALL R3 4 2  ; var3 = var3(var4, var5, var6)
      47 [-]: GETIMPORT R4 4; var4 = 0xC8802016
      48 [-]: MOVE R5 R3   ; var5 = var3
      49 [-]: CALL R4 2 4  ; var4, var5, var6 = var4(var5)
      50 [-]: FORGPREP_INEXT R4 L7; 
L 6:  51 [-]: NAMECALL R9 R8 K11; var10 = var8; var9 = var8[0xBB610E5B]
      52 [-]: CALL R9 2 2  ; var9 = var9(var10)
      53 [-]: NAMECALL R9 R9 K9; var10 = var9; var9 = var9[0xA2880940]
      54 [-]: CALL R9 2 1  ; var9(var10)
L 7:  55 [-]: FORGLOOP R4 L6 2 [inext]; 
      56 [-]: GETIMPORT R4 13; var4 = 0xBE190284
      57 [-]: NAMECALL R4 R4 K14; var5 = var4; var4 = var4[0xABF50B1C]
      58 [-]: CALL R4 2 2  ; var4 = var4(var5)
      59 [-]: FASTCALL1 64 R4 L8; 
      60 [-]: MOVE R6 R4   ; var6 = var4
      61 [-]: GETIMPORT R5 16; var5 = 0x7B998233
      62 [-]: CALL R5 2 2  ; var5 = var5(var6)
L 8:  63 [-]: JUMPIF R5 L9 ; goto L9 if var5
      64 [-]: LOADN R7 0   ; var7 = 0
      65 [-]: NAMECALL R5 R4 K17; var6 = var4; var5 = var4[0x8CFF1D7A]
      66 [-]: CALL R5 3 1  ; var5(var6, var7)
      67 [-]: LOADB R7 1   ; var7 = true
      68 [-]: NAMECALL R5 R4 K18; var6 = var4; var5 = var4[0x543A0B5E]
      69 [-]: CALL R5 3 1  ; var5(var6, var7)
L 9:  70 [-]: LOADNIL R5   ; var5 = nil
      71 [-]: SETUPVAL R5 8; upvalues[5] = var8
      72 [-]: GETUPVAL R6 9; var6 = upvalues[9]
      73 [-]: GETTABLEKS R5 R6 K19; var5 = var6[0xE69049EB]
      74 [-]: GETUPVAL R6 6; var6 = upvalues[6]
      75 [-]: CALL R5 2 1  ; var5(var6)
      76 [-]: GETUPVAL R5 6; var5 = upvalues[6]
      77 [-]: GETIMPORT R7 21; var7 = 0x0469F296
      78 [-]: LOADK R8 K22 ; var8 = "OnAgentRegistered"
      79 [-]: CALL R7 2 0  ; var7, ... = var7(var8)
      80 [-]: NAMECALL R5 R5 K23; var6 = var5; var5 = var5[0x11D6DE31]
      81 [-]: CALL R5 0 1  ; var5(var6, ...)
      82 [-]: GETIMPORT R5 1; var5 = 0x89326C93
      83 [-]: LOADK R7 K24 ; var7 = "OnPlayersChanged"
      84 [-]: NAMECALL R5 R5 K25; var6 = var5; var5 = var5[0xBBC228B5]
      85 [-]: CALL R5 3 1  ; var5(var6, var7)
      86 [-]: GETUPVAL R5 5; var5 = upvalues[5]
      87 [-]: GETUPVAL R7 10; var7 = upvalues[10]
      88 [-]: NAMECALL R5 R5 K26; var6 = var5; var5 = var5[0x3D412E0D]
      89 [-]: CALL R5 3 1  ; var5(var6, var7)
      90 [-]: GETUPVAL R5 5; var5 = upvalues[5]
      91 [-]: GETUPVAL R7 11; var7 = upvalues[11]
      92 [-]: NAMECALL R5 R5 K27; var6 = var5; var5 = var5[0x136A027D]
      93 [-]: CALL R5 3 1  ; var5(var6, var7)
      94 [-]: GETUPVAL R6 12; var6 = upvalues[12]
      95 [-]: GETTABLEKS R5 R6 K28; var5 = var6[0xDC3B2033]
      96 [-]: CALL R5 1 1  ; var5()
      97 [-]: GETUPVAL R6 12; var6 = upvalues[12]
      98 [-]: GETTABLEKS R5 R6 K29; var5 = var6[0xBD3CE95D]
      99 [-]: CALL R5 1 1  ; var5()
     100 [-]: GETUPVAL R6 12; var6 = upvalues[12]
     101 [-]: GETTABLEKS R5 R6 K30; var5 = var6[0xF7EBDDC8]
     102 [-]: CALL R5 1 1  ; var5()
     103 [-]: GETUPVAL R5 13; var5 = upvalues[13]
     104 [-]: NAMECALL R5 R5 K31; var6 = var5; var5 = var5[0x588ED000]
     105 [-]: CALL R5 2 1  ; var5(var6)
     106 [-]: GETUPVAL R5 14; var5 = upvalues[14]
     107 [-]: GETUPVAL R6 15; var6 = upvalues[15]
     108 [-]: GETUPVAL R8 16; var8 = upvalues[16]
     109 [-]: LENGTH R7 R8 ; var7 = #var8
     110 [-]: CALL R5 3 1  ; var5(var6, var7)
     111 [-]: GETUPVAL R5 14; var5 = upvalues[14]
     112 [-]: GETUPVAL R6 17; var6 = upvalues[17]
     113 [-]: GETUPVAL R8 16; var8 = upvalues[16]
     114 [-]: LENGTH R7 R8 ; var7 = #var8
     115 [-]: CALL R5 3 1  ; var5(var6, var7)
     116 [-]: GETUPVAL R5 14; var5 = upvalues[14]
     117 [-]: GETUPVAL R6 18; var6 = upvalues[18]
     118 [-]: GETUPVAL R8 16; var8 = upvalues[16]
     119 [-]: LENGTH R7 R8 ; var7 = #var8
     120 [-]: CALL R5 3 1  ; var5(var6, var7)
     121 [-]: LOADB R5 0   ; var5 = false
     122 [-]: JUMPIFNOT R5 L10; goto L10 if not var5
     123 [-]: GETIMPORT R5 1; var5 = 0x89326C93
     124 [-]: NAMECALL R5 R5 K32; var6 = var5; var5 = var5[0xFB64E76C]
     125 [-]: CALL R5 2 2  ; var5 = var5(var6)
     126 [-]: GETIMPORT R7 21; var7 = 0x0469F296
     127 [-]: LOADK R8 K33 ; var8 = "DEBUG_SkipPhase"
     128 [-]: CALL R7 2 2  ; var7 = var7(var8)
     129 [-]: GETIMPORT R8 35; var8 = 0x9BA7909F
     130 [-]: LOADK R10 K36; var10 = "SHOW_LEVEL_MAP"
     131 [-]: NAMECALL R8 R8 K37; var9 = var8; var8 = var8[0xFBDF1860]
     132 [-]: CALL R8 3 0  ; var8, ... = var8(var9, var10)
     133 [-]: NAMECALL R5 R5 K38; var6 = var5; var5 = var5[0x1A415347]
     134 [-]: CALL R5 0 1  ; var5(var6, ...)
L10: 135 [-]: RETURN R0 0  ; 


; Name:            
; Defined at line: 1105
; #Upvalues:       1
; #Parameters:     1
; Is_vararg:       0
; Max Stack Size:  21

       0 [-]: GETIMPORT R1 1; var1 = 0x89326C93
       1 [-]: GETUPVAL R3 0; var3 = upvalues[0]
       2 [-]: NAMECALL R4 R0 K2; var5 = var0; var4 = var0[0xD1586535]
       3 [-]: CALL R4 2 2  ; var4 = var4(var5)
       4 [-]: LOADN R5 0   ; var5 = 0
       5 [-]: NAMECALL R6 R0 K3; var7 = var0; var6 = var0[0xC5B92518]
       6 [-]: CALL R6 2 0  ; var6, ... = var6(var7)
       7 [-]: NAMECALL R1 R1 K4; var2 = var1; var1 = var1[0xF16592C8]
       8 [-]: CALL R1 0 2  ; var1 = var1(var2, ...)
       9 [-]: LOADB R2 0   ; var2 = false
      10 [-]: LOADN R5 1   ; var5 = 1
      11 [-]: LENGTH R3 R1 ; var3 = #var1
      12 [-]: LOADN R4 1   ; var4 = 1
      13 [-]: FORNPREP R3 L4; nforprep start - [escape at L4] -- var3 = iterator
L 0:  14 [-]: ADDK R8 R5 K5; var8 = var5 + 1
      15 [-]: LENGTH R6 R1 ; var6 = #var1
      16 [-]: LOADN R7 1   ; var7 = 1
      17 [-]: FORNPREP R6 L3; nforprep start - [escape at L3] -- var6 = iterator
L 1:  18 [-]: GETTABLE R9 R1 R5; var9 = var1[var5]
      19 [-]: GETTABLE R11 R1 R8; var11 = var1[var8]
      20 [-]: NAMECALL R9 R9 K6; var10 = var9; var9 = var9[0x68D0CBED]
      21 [-]: CALL R9 3 2  ; var9 = var9(var10, var11)
      22 [-]: LOADN R10 8  ; var10 = 8
      23 [-]: JUMPIFNOTLT R9 R10 L2; goto L2 if var9 >= var526625
      24 [-]: GETIMPORT R9 8; var9 = 0x3D106989
      25 [-]: LOADK R11 K9 ; var11 = "ERROR: "
      26 [-]: GETTABLE R19 R1 R5; var19 = var1[var5]
      27 [-]: NAMECALL R19 R19 K10; var20 = var19; var19 = var19[0xE223E2B1]
      28 [-]: CALL R19 2 2 ; var19 = var19(var20)
      29 [-]: MOVE R12 R19 ; var12 = var19
      30 [-]: LOADK R13 K11; var13 = " is too close to "
      31 [-]: GETTABLE R19 R1 R8; var19 = var1[var8]
      32 [-]: NAMECALL R19 R19 K10; var20 = var19; var19 = var19[0xE223E2B1]
      33 [-]: CALL R19 2 2 ; var19 = var19(var20)
      34 [-]: MOVE R14 R19 ; var14 = var19
      35 [-]: LOADK R15 K12; var15 = " in hint "
      36 [-]: NAMECALL R19 R0 K10; var20 = var0; var19 = var0[0xE223E2B1]
      37 [-]: CALL R19 2 2 ; var19 = var19(var20)
      38 [-]: MOVE R16 R19 ; var16 = var19
      39 [-]: LOADK R17 K13; var17 = ". Distance is "
      40 [-]: GETTABLE R18 R1 R5; var18 = var1[var5]
      41 [-]: GETTABLE R20 R1 R8; var20 = var1[var8]
      42 [-]: NAMECALL R18 R18 K14; var19 = var18; var18 = var18[0xBEBAD19F]
      43 [-]: CALL R18 3 2 ; var18 = var18(var19, var20)
      44 [-]: CONCAT R10 R11 R18; var10 = var11 .. var18
      45 [-]: CALL R9 2 1  ; var9(var10)
      46 [-]: LOADB R2 1   ; var2 = true
L 2:  47 [-]: FORNLOOP R6 L1; nforloop end - iterate + goto L1
L 3:  48 [-]: FORNLOOP R3 L0; nforloop end - iterate + goto L0
L 4:  49 [-]: GETIMPORT R4 16; var4 = 0x8689848D
      50 [-]: GETIMPORT R6 16; var6 = 0x8689848D
      51 [-]: LENGTH R5 R6 ; var5 = #var6
      52 [-]: GETTABLE R3 R4 R5; var3 = var4[var5]
      53 [-]: LENGTH R4 R1 ; var4 = #var1
      54 [-]: JUMPIFNOTLT R4 R3 L5; goto L5 if var4 >= var525345
      55 [-]: GETIMPORT R4 8; var4 = 0x3D106989
      56 [-]: LOADK R6 K17 ; var6 = "ERROR: not enough waypoints in "
      57 [-]: NAMECALL R12 R0 K10; var13 = var0; var12 = var0[0xE223E2B1]
      58 [-]: CALL R12 2 2 ; var12 = var12(var13)
      59 [-]: MOVE R7 R12  ; var7 = var12
      60 [-]: LOADK R8 K18 ; var8 = ", only found "
      61 [-]: LENGTH R9 R1 ; var9 = #var1
      62 [-]: LOADK R10 K19; var10 = " out of the max needed "
      63 [-]: MOVE R11 R3  ; var11 = var3
      64 [-]: CONCAT R5 R6 R11; var5 = var6 .. var11
      65 [-]: CALL R4 2 1  ; var4(var5)
      66 [-]: LOADN R4 0   ; var4 = 0
      67 [-]: RETURN R4 1  ; 
L 5:  68 [-]: JUMPIFNOT R2 L6; goto L6 if not var2
      69 [-]: LOADN R4 0   ; var4 = 0
      70 [-]: RETURN R4 1  ; 
L 6:  71 [-]: LOADN R4 1   ; var4 = 1
      72 [-]: RETURN R4 1  ; 


; Name:            
; Defined at line: 1125
; #Upvalues:       11
; #Parameters:     1
; Is_vararg:       0
; Max Stack Size:  5

       0 [-]: GETUPVAL R1 0; var1 = upvalues[0]
       1 [-]: GETUPVAL R3 1; var3 = upvalues[1]
       2 [-]: GETTABLEKS R2 R3 K0; var2 = var3["EXCAVATION"]
       3 [-]: JUMPIFNOTEQ R1 R2 L0; goto L0 if var1 ~= var131388
       4 [-]: GETUPVAL R1 2; var1 = upvalues[2]
       5 [-]: MOVE R2 R0   ; var2 = var0
       6 [-]: CALL R1 2 1  ; var1(var2)
       7 [-]: GETUPVAL R1 3; var1 = upvalues[3]
       8 [-]: GETUPVAL R2 4; var2 = upvalues[4]
       9 [-]: GETUPVAL R3 5; var3 = upvalues[5]
      10 [-]: CALL R1 3 1  ; var1(var2, var3)
      11 [-]: GETUPVAL R1 3; var1 = upvalues[3]
      12 [-]: GETUPVAL R2 6; var2 = upvalues[6]
      13 [-]: GETUPVAL R3 7; var3 = upvalues[7]
      14 [-]: LOADK R4 K1  ; var4 = 0.0099999997764825821
      15 [-]: CALL R1 4 1  ; var1(var2, var3, var4)
      16 [-]: GETUPVAL R1 3; var1 = upvalues[3]
      17 [-]: GETUPVAL R2 8; var2 = upvalues[8]
      18 [-]: GETUPVAL R3 9; var3 = upvalues[9]
      19 [-]: LOADK R4 K1  ; var4 = 0.0099999997764825821
      20 [-]: CALL R1 4 1  ; var1(var2, var3, var4)
L 0:  21 [-]: GETUPVAL R2 10; var2 = upvalues[10]
      22 [-]: ADD R1 R2 R0 ; var1 = var2 + var0
      23 [-]: SETUPVAL R1 10; upvalues[1] = var10
      24 [-]: RETURN R0 0  ; 


; Name:            
; Defined at line: 1133
; #Upvalues:       17
; #Parameters:     1
; Is_vararg:       0
; Max Stack Size:  7

       0 [-]: GETUPVAL R1 0; var1 = upvalues[0]
       1 [-]: MOVE R2 R0   ; var2 = var0
       2 [-]: CALL R1 2 1  ; var1(var2)
       3 [-]: LOADNIL R1   ; var1 = nil
L 0:   4 [-]: NAMECALL R2 R0 K0; var3 = var0; var2 = var0[0xEFE6CAD1]
       5 [-]: CALL R2 2 2  ; var2 = var2(var3)
       6 [-]: LOADN R3 4   ; var3 = 4
       7 [-]: JUMPIFNOTLT R2 R3 L5; goto L5 if var2 >= var66108
L 1:   8 [-]: GETUPVAL R2 1; var2 = upvalues[1]
       9 [-]: NAMECALL R2 R2 K1; var3 = var2; var2 = var2[0x5E895E79]
      10 [-]: CALL R2 2 2  ; var2 = var2(var3)
      11 [-]: JUMPIF R2 L2 ; goto L2 if var2
      12 [-]: GETIMPORT R2 3; var2 = 0xCBD666E1
      13 [-]: LOADN R3 0   ; var3 = 0
      14 [-]: CALL R2 2 1  ; var2(var3)
      15 [-]: JUMPBACK L1  ; goto L1
L 2:  16 [-]: GETIMPORT R2 5; var2 = 0xFFF641AF
      17 [-]: CALL R2 1 2  ; var2 = var2()
      18 [-]: MOVE R1 R2   ; var1 = var2
      19 [-]: MOVE R2 R1   ; var2 = var1
      20 [-]: GETUPVAL R3 2; var3 = upvalues[2]
      21 [-]: GETUPVAL R5 3; var5 = upvalues[3]
      22 [-]: GETTABLEKS R4 R5 K6; var4 = var5["EXCAVATION"]
      23 [-]: JUMPIFNOTEQ R3 R4 L3; goto L3 if var3 ~= var262972
      24 [-]: GETUPVAL R3 4; var3 = upvalues[4]
      25 [-]: MOVE R4 R2   ; var4 = var2
      26 [-]: CALL R3 2 1  ; var3(var4)
      27 [-]: GETUPVAL R3 5; var3 = upvalues[5]
      28 [-]: GETUPVAL R4 6; var4 = upvalues[6]
      29 [-]: GETUPVAL R5 7; var5 = upvalues[7]
      30 [-]: CALL R3 3 1  ; var3(var4, var5)
      31 [-]: GETUPVAL R3 5; var3 = upvalues[5]
      32 [-]: GETUPVAL R4 8; var4 = upvalues[8]
      33 [-]: GETUPVAL R5 9; var5 = upvalues[9]
      34 [-]: LOADK R6 K7  ; var6 = 0.0099999997764825821
      35 [-]: CALL R3 4 1  ; var3(var4, var5, var6)
      36 [-]: GETUPVAL R3 5; var3 = upvalues[5]
      37 [-]: GETUPVAL R4 10; var4 = upvalues[10]
      38 [-]: GETUPVAL R5 11; var5 = upvalues[11]
      39 [-]: LOADK R6 K7  ; var6 = 0.0099999997764825821
      40 [-]: CALL R3 4 1  ; var3(var4, var5, var6)
L 3:  41 [-]: GETUPVAL R4 12; var4 = upvalues[12]
      42 [-]: ADD R3 R4 R2 ; var3 = var4 + var2
      43 [-]: SETUPVAL R3 12; upvalues[3] = var12
      44 [-]: GETUPVAL R2 13; var2 = upvalues[13]
      45 [-]: MOVE R4 R1   ; var4 = var1
      46 [-]: NAMECALL R2 R2 K8; var3 = var2; var2 = var2[0xFAA69527]
      47 [-]: CALL R2 3 1  ; var2(var3, var4)
      48 [-]: NAMECALL R2 R0 K9; var3 = var0; var2 = var0[0xD9531187]
      49 [-]: CALL R2 2 2  ; var2 = var2(var3)
      50 [-]: JUMPIFNOT R2 L4; goto L4 if not var2
      51 [-]: GETUPVAL R3 14; var3 = upvalues[14]
      52 [-]: GETTABLEKS R2 R3 K10; var2 = var3[0xD712B9DB]
      53 [-]: CALL R2 1 1  ; var2()
      54 [-]: GETUPVAL R2 13; var2 = upvalues[13]
      55 [-]: NAMECALL R2 R2 K11; var3 = var2; var2 = var2[0x7076B095]
      56 [-]: CALL R2 2 1  ; var2(var3)
      57 [-]: GETUPVAL R2 15; var2 = upvalues[15]
      58 [-]: LOADN R4 5   ; var4 = 5
      59 [-]: NAMECALL R2 R2 K12; var3 = var2; var2 = var2[0xFE9DC265]
      60 [-]: CALL R2 3 1  ; var2(var3, var4)
      61 [-]: GETIMPORT R2 14; var2 = 0x3D106989
      62 [-]: LOADK R3 K15 ; var3 = "Encounter failed"
      63 [-]: CALL R2 2 1  ; var2(var3)
L 4:  64 [-]: GETIMPORT R2 3; var2 = 0xCBD666E1
      65 [-]: LOADN R3 0   ; var3 = 0
      66 [-]: CALL R2 2 1  ; var2(var3)
      67 [-]: JUMPBACK L0  ; goto L0
L 5:  68 [-]: GETUPVAL R2 16; var2 = upvalues[16]
      69 [-]: CALL R2 1 1  ; var2()
      70 [-]: RETURN R0 0  ; 


; Name:            
; Defined at line: 1152
; #Upvalues:       2
; #Parameters:     1
; Is_vararg:       0
; Max Stack Size:  7

       0 [-]: NAMECALL R1 R0 K0; var2 = var0; var1 = var0[0xBB610E5B]
       1 [-]: CALL R1 2 2  ; var1 = var1(var2)
       2 [-]: FASTCALL1 64 R1 L0; 
       3 [-]: MOVE R3 R1   ; var3 = var1
       4 [-]: GETIMPORT R2 2; var2 = 0x7B998233
       5 [-]: CALL R2 2 2  ; var2 = var2(var3)
L 0:   6 [-]: JUMPIF R2 L3 ; goto L3 if var2
       7 [-]: GETIMPORT R4 4; var4 = gDropshipAvatarType
       8 [-]: NAMECALL R2 R1 K5; var3 = var1; var2 = var1[0xF2DEAF69]
       9 [-]: CALL R2 3 2  ; var2 = var2(var3, var4)
      10 [-]: JUMPIF R2 L3 ; goto L3 if var2
      11 [-]: GETIMPORT R4 7; var4 = gLotusVehicleAvatarType
      12 [-]: NAMECALL R2 R1 K5; var3 = var1; var2 = var1[0xF2DEAF69]
      13 [-]: CALL R2 3 2  ; var2 = var2(var3, var4)
      14 [-]: JUMPIF R2 L3 ; goto L3 if var2
      15 [-]: GETUPVAL R4 0; var4 = upvalues[0]
      16 [-]: NAMECALL R2 R0 K5; var3 = var0; var2 = var0[0xF2DEAF69]
      17 [-]: CALL R2 3 2  ; var2 = var2(var3, var4)
      18 [-]: JUMPIFNOT R2 L1; goto L1 if not var2
      19 [-]: LOADK R3 K8  ; var3 = "DynExcav"
      20 [-]: LOADK R4 K9  ; var4 = ": "
      21 [-]: LOADK R5 K10 ; var5 = "Cell carrier created"
      22 [-]: CONCAT R2 R3 R5; var2 = var3 .. var5
      23 [-]: GETIMPORT R3 12; var3 = 0xD644C2F1
      24 [-]: MOVE R4 R2   ; var4 = var2
      25 [-]: CALL R3 2 1  ; var3(var4)
L 1:  26 [-]: GETIMPORT R2 14; var2 = 0x89326C93
      27 [-]: GETUPVAL R4 1; var4 = upvalues[1]
      28 [-]: NAMECALL R5 R1 K15; var6 = var1; var5 = var1[0xD1586535]
      29 [-]: CALL R5 2 0  ; var5, ... = var5(var6)
      30 [-]: NAMECALL R2 R2 K16; var3 = var2; var2 = var2[0xC7B81E8D]
      31 [-]: CALL R2 0 2  ; var2 = var2(var3, ...)
      32 [-]: FASTCALL1 64 R2 L2; 
      33 [-]: MOVE R4 R2   ; var4 = var2
      34 [-]: GETIMPORT R3 2; var3 = 0x7B998233
      35 [-]: CALL R3 2 2  ; var3 = var3(var4)
L 2:  36 [-]: JUMPIF R3 L3 ; goto L3 if var3
      37 [-]: MOVE R5 R2   ; var5 = var2
      38 [-]: NAMECALL R3 R0 K17; var4 = var0; var3 = var0[0xA64A1F4A]
      39 [-]: CALL R3 3 1  ; var3(var4, var5)
L 3:  40 [-]: RETURN R0 0  ; 


; Name:            
; Defined at line: 1166
; #Upvalues:       5
; #Parameters:     0
; Is_vararg:       0
; Max Stack Size:  10

       0 [-]: GETUPVAL R1 0; var1 = upvalues[0]
       1 [-]: FASTCALL1 64 R1 L0; 
       2 [-]: GETIMPORT R0 1; var0 = 0x7B998233
       3 [-]: CALL R0 2 2  ; var0 = var0(var1)
L 0:   4 [-]: JUMPIF R0 L1 ; goto L1 if var0
       5 [-]: GETUPVAL R0 0; var0 = upvalues[0]
       6 [-]: NAMECALL R0 R0 K2; var1 = var0; var0 = var0[0xEFE6CAD1]
       7 [-]: CALL R0 2 2  ; var0 = var0(var1)
       8 [-]: LOADN R1 4   ; var1 = 4
       9 [-]: JUMPIFLE R1 R0 L1; goto L1 if var1 <= var65596
      10 [-]: GETUPVAL R0 1; var0 = upvalues[1]
      11 [-]: NAMECALL R0 R0 K3; var1 = var0; var0 = var0[0x5E895E79]
      12 [-]: CALL R0 2 2  ; var0 = var0(var1)
      13 [-]: JUMPIF R0 L2 ; goto L2 if var0
L 1:  14 [-]: RETURN R0 0  ; 
L 2:  15 [-]: GETIMPORT R0 5; var0 = 0xBE190284
      16 [-]: GETUPVAL R2 2; var2 = upvalues[2]
      17 [-]: LOADN R3 0   ; var3 = 0
      18 [-]: NAMECALL R0 R0 K6; var1 = var0; var0 = var0[0x0EB34C69]
      19 [-]: CALL R0 4 2  ; var0 = var0(var1, var2, var3)
      20 [-]: GETIMPORT R2 8; var2 = 0xA8CCD011
      21 [-]: GETIMPORT R6 10; var6 = 0xE7F2B02F
      22 [-]: NAMECALL R6 R6 K11; var7 = var6; var6 = var6[0xEBE2F513]
      23 [-]: CALL R6 2 2  ; var6 = var6(var7)
      24 [-]: GETIMPORT R7 13; var7 = 0x9BA7909F
      25 [-]: LOADK R9 K14 ; var9 = "Server.NumVirtualTestClients"
      26 [-]: NAMECALL R7 R7 K15; var8 = var7; var7 = var7[0x8151451D]
      27 [-]: CALL R7 3 2  ; var7 = var7(var8, var9)
      28 [-]: ADD R5 R6 R7 ; var5 = var6 + var7
      29 [-]: FASTCALL2K 18 R5 K16 L3; 
      30 [-]: LOADK R6 K16 ; var6 = 1
      31 [-]: GETIMPORT R4 19; var4 = 0x5BCED4C4[0xB62ECFE0]
      32 [-]: CALL R4 3 2  ; var4 = var4(var5, var6)
L 3:  33 [-]: FASTCALL2K 19 R4 K20 L4; 
      34 [-]: LOADK R5 K20 ; var5 = 4
      35 [-]: GETIMPORT R3 22; var3 = 0x5BCED4C4[0xAC1B386A]
      36 [-]: CALL R3 3 2  ; var3 = var3(var4, var5)
L 4:  37 [-]: GETTABLE R1 R2 R3; var1 = var2[var3]
      38 [-]: GETUPVAL R3 3; var3 = upvalues[3]
      39 [-]: GETTABLEKS R2 R3 K23; var2 = var3[0xF3928F38]
      40 [-]: SUBK R5 R1 K16; var5 = var1 - 1
      41 [-]: FASTCALL2 19 R0 R5 L5; 
      42 [-]: MOVE R4 R0   ; var4 = var0
      43 [-]: GETIMPORT R3 22; var3 = 0x5BCED4C4[0xAC1B386A]
      44 [-]: CALL R3 3 2  ; var3 = var3(var4, var5)
L 5:  45 [-]: MOVE R4 R1   ; var4 = var1
      46 [-]: CALL R2 3 1  ; var2(var3, var4)
      47 [-]: GETUPVAL R2 4; var2 = upvalues[4]
      48 [-]: CALL R2 1 1  ; var2()
      49 [-]: RETURN R0 0  ; 


; Name:            
; Defined at line: 1176
; #Upvalues:       2
; #Parameters:     1
; Is_vararg:       0
; Max Stack Size:  4

       0 [-]: GETUPVAL R1 0; var1 = upvalues[0]
       1 [-]: MOVE R2 R0   ; var2 = var0
       2 [-]: CALL R1 2 2  ; var1 = var1(var2)
       3 [-]: JUMPIFNOT R1 L0; goto L0 if not var1
       4 [-]: GETUPVAL R2 1; var2 = upvalues[1]
       5 [-]: MOVE R3 R1   ; var3 = var1
       6 [-]: CALL R2 2 1  ; var2(var3)
L 0:   7 [-]: RETURN R0 0  ; 


; Name:            
; Defined at line: 1183
; #Upvalues:       3
; #Parameters:     1
; Is_vararg:       0
; Max Stack Size:  10

       0 [-]: NAMECALL R1 R0 K0; var2 = var0; var1 = var0[0x2B54251B]
       1 [-]: CALL R1 2 2  ; var1 = var1(var2)
       2 [-]: GETIMPORT R3 2; var3 = 0xCFC01047
       3 [-]: GETUPVAL R4 0; var4 = upvalues[0]
       4 [-]: CALL R3 2 4  ; var3, var4, var5 = var3(var4)
       5 [-]: FORGPREP_NEXT R3 L1; 
L 0:   6 [-]: GETUPVAL R9 1; var9 = upvalues[1]
       7 [-]: GETTABLE R8 R9 R6; var8 = var9[var6]
       8 [-]: JUMPIFNOTEQ R8 R1 L1; goto L1 if var8 ~= var393774
       9 [-]: MOVE R2 R6   ; var2 = var6
      10 [-]: JUMP L2      ; goto L2
L 1:  11 [-]: FORGLOOP R3 L0 2; 
      12 [-]: LOADNIL R2   ; var2 = nil
L 2:  13 [-]: GETUPVAL R3 2; var3 = upvalues[2]
      14 [-]: MOVE R4 R2   ; var4 = var2
      15 [-]: CALL R3 2 1  ; var3(var4)
      16 [-]: RETURN R0 0  ; 


; Name:            
; Defined at line: 1189
; #Upvalues:       2
; #Parameters:     0
; Is_vararg:       0
; Max Stack Size:  3

       0 [-]: GETUPVAL R1 0; var1 = upvalues[0]
       1 [-]: GETTABLEKS R0 R1 K0; var0 = var1[0x7E8A976A]
       2 [-]: GETUPVAL R1 1; var1 = upvalues[1]
       3 [-]: LOADB R2 1   ; var2 = true
       4 [-]: CALL R0 3 1  ; var0(var1, var2)
       5 [-]: RETURN R0 0  ; 


; Name:            
; Defined at line: 1193
; #Upvalues:       2
; #Parameters:     0
; Is_vararg:       0
; Max Stack Size:  3

       0 [-]: GETUPVAL R1 0; var1 = upvalues[0]
       1 [-]: GETTABLEKS R0 R1 K0; var0 = var1[0x7E8A976A]
       2 [-]: GETUPVAL R1 1; var1 = upvalues[1]
       3 [-]: LOADB R2 0   ; var2 = false
       4 [-]: CALL R0 3 1  ; var0(var1, var2)
       5 [-]: RETURN R0 0  ; 


; Name:            
; Defined at line: 1197
; #Upvalues:       10
; #Parameters:     1
; Is_vararg:       0
; Max Stack Size:  10

       0 [-]: JUMPXEQKN R0 K0 L4 NOT; 
       1 [-]: LOADK R2 K1  ; var2 = "DynExcav"
       2 [-]: LOADK R3 K2  ; var3 = ": "
       3 [-]: LOADK R4 K3  ; var4 = "SKIPPING"
       4 [-]: CONCAT R1 R2 R4; var1 = var2 .. var4
       5 [-]: GETIMPORT R2 5; var2 = 0xD644C2F1
       6 [-]: MOVE R3 R1   ; var3 = var1
       7 [-]: CALL R2 2 1  ; var2(var3)
       8 [-]: GETIMPORT R2 7; var2 = 0x3D106989
       9 [-]: LOADK R3 K3  ; var3 = "SKIPPING"
      10 [-]: CALL R2 2 1  ; var2(var3)
      11 [-]: GETUPVAL R1 0; var1 = upvalues[0]
      12 [-]: GETUPVAL R3 1; var3 = upvalues[1]
      13 [-]: GETTABLEKS R2 R3 K8; var2 = var3["EXCAVATION"]
      14 [-]: JUMPIFNOTEQ R1 R2 L4; goto L4 if var1 ~= var560
      15 [-]: LOADN R2 0   ; var2 = 0
      16 [-]: GETIMPORT R3 10; var3 = 0xCFC01047
      17 [-]: GETUPVAL R4 2; var4 = upvalues[2]
      18 [-]: CALL R3 2 4  ; var3, var4, var5 = var3(var4)
      19 [-]: FORGPREP_NEXT R3 L1; 
L 0:  20 [-]: GETUPVAL R9 3; var9 = upvalues[3]
      21 [-]: GETTABLEKS R8 R9 K11; var8 = var9["A"]
      22 [-]: JUMPIFNOTLE R8 R7 L1; goto L1 if var8 > var131592
      23 [-]: ADDK R2 R2 K0; var2 = var2 + 1
L 1:  24 [-]: FORGLOOP R3 L0 2; 
      25 [-]: MOVE R1 R2   ; var1 = var2
      26 [-]: LOADN R2 0   ; var2 = 0
      27 [-]: JUMPIFNOTLE R1 R2 L2; goto L2 if var1 > var65571
      28 [-]: RETURN R0 0  ; 
L 2:  29 [-]: GETUPVAL R1 4; var1 = upvalues[4]
      30 [-]: CALL R1 1 2  ; var1 = var1()
      31 [-]: GETTABLEN R2 R1 1; var2 = var1[1]
      32 [-]: GETIMPORT R3 7; var3 = 0x3D106989
      33 [-]: LOADK R5 K12 ; var5 = "Excavation completed "
      34 [-]: MOVE R6 R2   ; var6 = var2
      35 [-]: CONCAT R4 R5 R6; var4 = var5 .. var6
      36 [-]: CALL R3 2 1  ; var3(var4)
      37 [-]: GETUPVAL R3 5; var3 = upvalues[5]
      38 [-]: LOADNIL R4   ; var4 = nil
      39 [-]: ORK R4 R4 K0 ; var4 = var4 or 1
      40 [-]: GETIMPORT R5 14; var5 = 0xBE190284
      41 [-]: MOVE R7 R3   ; var7 = var3
      42 [-]: LOADN R8 0   ; var8 = 0
      43 [-]: NAMECALL R5 R5 K15; var6 = var5; var5 = var5[0x0EB34C69]
      44 [-]: CALL R5 4 2  ; var5 = var5(var6, var7, var8)
      45 [-]: ADD R5 R5 R4 ; var5 = var5 + var4
      46 [-]: GETIMPORT R6 14; var6 = 0xBE190284
      47 [-]: MOVE R8 R3   ; var8 = var3
      48 [-]: MOVE R9 R5   ; var9 = var5
      49 [-]: NAMECALL R6 R6 K16; var7 = var6; var6 = var6[0x751F061D]
      50 [-]: CALL R6 4 1  ; var6(var7, var8, var9)
      51 [-]: GETUPVAL R3 6; var3 = upvalues[6]
      52 [-]: MOVE R4 R2   ; var4 = var2
      53 [-]: CALL R3 2 1  ; var3(var4)
      54 [-]: GETUPVAL R3 2; var3 = upvalues[2]
      55 [-]: GETUPVAL R5 3; var5 = upvalues[3]
      56 [-]: GETTABLEKS R4 R5 K17; var4 = var5["COMPLETED"]
      57 [-]: SETTABLE R4 R3 R2; var4[var3] = var2
      58 [-]: GETUPVAL R3 0; var3 = upvalues[0]
      59 [-]: GETUPVAL R5 1; var5 = upvalues[1]
      60 [-]: GETTABLEKS R4 R5 K8; var4 = var5["EXCAVATION"]
      61 [-]: JUMPIFNOTEQ R3 R4 L3; goto L3 if var3 ~= var459580
      62 [-]: GETUPVAL R3 7; var3 = upvalues[7]
      63 [-]: CALL R3 1 1  ; var3()
      64 [-]: GETUPVAL R4 8; var4 = upvalues[8]
      65 [-]: GETTABLEKS R3 R4 K18; var3 = var4[0x9742B85B]
      66 [-]: GETUPVAL R4 9; var4 = upvalues[9]
      67 [-]: GETIMPORT R5 20; var5 = 0x0469F296
      68 [-]: LOADK R6 K21 ; var6 = "DigComplete"
      69 [-]: CALL R5 2 2  ; var5 = var5(var6)
      70 [-]: LOADB R6 0   ; var6 = false
      71 [-]: CALL R3 4 1  ; var3(var4, var5, var6)
L 3:  72 [-]: RETURN R0 0  ; 
L 4:  73 [-]: RETURN R0 0  ; 



