; This file has been disassembled using luadec 2.0.2 by sztupy (modified by Reversive)

; Name:            
; Defined at line: 0
; #Upvalues:       0
; #Parameters:     0
; Is_vararg:       2
; Max Stack Size:  57

  1 [-]: GETGLOBAL R0 K0        ; R0 := 0x2d0fad09
  2 [-]: LOADK     R1 K1        ; R1 := "EE.Interface.Utilities"
  3 [-]: CALL      R0 2 2       ; R0 := R0(R1)
  4 [-]: GETGLOBAL R1 K0        ; R1 := 0x2d0fad09
  5 [-]: LOADK     R2 K2        ; R2 := "Lotus.Scripts.Libs.LandscapeLib"
  6 [-]: CALL      R1 2 2       ; R1 := R1(R2)
  7 [-]: GETGLOBAL R2 K0        ; R2 := 0x2d0fad09
  8 [-]: LOADK     R3 K3        ; R3 := "Lotus.Scripts.Libs.TransmissionSet"
  9 [-]: CALL      R2 2 2       ; R2 := R2(R3)
 10 [-]: GETGLOBAL R3 K0        ; R3 := 0x2d0fad09
 11 [-]: LOADK     R4 K4        ; R4 := "Lotus.Interface.Libs.TimerMgr"
 12 [-]: CALL      R3 2 2       ; R3 := R3(R4)
 13 [-]: GETGLOBAL R4 K0        ; R4 := 0x2d0fad09
 14 [-]: LOADK     R5 K5        ; R5 := "Lotus.Scripts.Libs.ObjectiveText"
 15 [-]: CALL      R4 2 2       ; R4 := R4(R5)
 16 [-]: GETGLOBAL R5 K0        ; R5 := 0x2d0fad09
 17 [-]: LOADK     R6 K6        ; R6 := "Lotus.Scripts.Libs.TableLib"
 18 [-]: CALL      R5 2 2       ; R5 := R5(R6)
 19 [-]: GETGLOBAL R6 K0        ; R6 := 0x2d0fad09
 20 [-]: LOADK     R7 K7        ; R7 := "Lotus.Interface.LotusUtilities"
 21 [-]: CALL      R6 2 2       ; R6 := R6(R7)
 22 [-]: GETGLOBAL R7 K8        ; R7 := 0x88efc25e
 23 [-]: LOADK     R8 K9        ; R8 := "/Lotus/Types/Game/MarkerInfos/DefendMarkerInfo"
 24 [-]: CALL      R7 2 2       ; R7 := R7(R8)
 25 [-]: GETGLOBAL R8 K10       ; R8 := 0x7ed0a956
 26 [-]: LOADK     R9 K11       ; R9 := "/Lotus/Types/Enemies/Orokin/Entrati/EntratiTech/NechroTech/NechroTechAvatar"
 27 [-]: CALL      R8 2 2       ; R8 := R8(R9)
 28 [-]: GETGLOBAL R9 K10       ; R9 := 0x7ed0a956
 29 [-]: LOADK     R10 K12      ; R10 := "/Lotus/Types/Enemies/Orokin/Entrati/EntratiTech/EntratiTechDormantLandscapeAvatar"
 30 [-]: CALL      R9 2 2       ; R9 := R9(R10)
 31 [-]: LOADK     R10 K13      ; R10 := "/Lotus/Language/InfestedMicroplanet/GrineerSurvivorsBonusObjective"
 32 [-]: LOADK     R11 K14      ; R11 := "/Lotus/Language/InfestedMicroplanet/GrineerSurvivorsDefendObjective"
 33 [-]: LOADK     R12 K15      ; R12 := "/Lotus/Language/InfestedMicroplanet/GrineerSurvivorsSpeakToLeaderObjective"
 34 [-]: LOADK     R13 K16      ; R13 := "/Lotus/Language/InfestedMicroplanet/GrineerSurvivorsSquad"
 35 [-]: GETGLOBAL R14 K17      ; R14 := 0x0469f296
 36 [-]: LOADK     R15 K18      ; R15 := "PlayerKills"
 37 [-]: CALL      R14 2 2      ; R14 := R14(R15)
 38 [-]: GETGLOBAL R15 K17      ; R15 := 0x0469f296
 39 [-]: LOADK     R16 K19      ; R16 := "EnemyKills"
 40 [-]: CALL      R15 2 2      ; R15 := R15(R16)
 41 [-]: GETGLOBAL R16 K17      ; R16 := 0x0469f296
 42 [-]: LOADK     R17 K20      ; R17 := "GrineerOvertake"
 43 [-]: CALL      R16 2 2      ; R16 := R16(R17)
 44 [-]: GETGLOBAL R17 K17      ; R17 := 0x0469f296
 45 [-]: LOADK     R18 K21      ; R18 := "PlayerOvertake"
 46 [-]: CALL      R17 2 2      ; R17 := R17(R18)
 47 [-]: GETGLOBAL R18 K17      ; R18 := 0x0469f296
 48 [-]: LOADK     R19 K22      ; R19 := "LeavingCB"
 49 [-]: CALL      R18 2 2      ; R18 := R18(R19)
 50 [-]: GETGLOBAL R19 K17      ; R19 := 0x0469f296
 51 [-]: LOADK     R20 K23      ; R20 := "ReturningCB"
 52 [-]: CALL      R19 2 2      ; R19 := R19(R20)
 53 [-]: GETGLOBAL R20 K17      ; R20 := 0x0469f296
 54 [-]: LOADK     R21 K24      ; R21 := "TENNO"
 55 [-]: CALL      R20 2 2      ; R20 := R20(R21)
 56 [-]: LOADNIL   R21 R23      ; R21 := R22 := R23 := nil
 57 [-]: LOADK     R24 0        ; R24 := 0.000000
 58 [-]: LOADK     R25 0        ; R25 := 0.000000
 59 [-]: LOADNIL   R26 R29      ; R26 := R27 := R28 := R29 := nil
 60 [-]: NEWTABLE  R30 0 0      ; R30 := {}
 61 [-]: LOADNIL   R31 R31      ; R31 := nil
 62 [-]: LOADK     R32 0        ; R32 := 0.000000
 63 [-]: LOADK     R33 1        ; R33 := 1.000000
 64 [-]: LOADK     R34 2        ; R34 := 2.000000
 65 [-]: LOADK     R35 4        ; R35 := 4.000000
 66 [-]: LOADK     R36 5        ; R36 := 5.000000
 67 [-]: NEWTABLE  R37 4 0      ; R37 := {}
 68 [-]: LOADK     R38 30       ; R38 := 30.000000
 69 [-]: LOADK     R39 60       ; R39 := 60.000000
 70 [-]: LOADK     R40 100      ; R40 := 100.000000
 71 [-]: LOADK     R41 125      ; R41 := 125.000000
 72 [-]: SETLIST   R37 4 1      ; R37[(1-1)*FPF+i] := R(37+i), 1 <= i <= 4
 73 [-]: LOADK     R38 30       ; R38 := 30.000000
 74 [-]: LOADK     R39 15       ; R39 := 15.000000
 75 [-]: LOADK     R40 10       ; R40 := 10.000000
 76 [-]: LOADNIL   R41 R41      ; R41 := nil
 77 [-]: NEWTABLE  R42 0 0      ; R42 := {}
 78 [-]: NEWTABLE  R43 0 0      ; R43 := {}
 79 [-]: LOADNIL   R44 R45      ; R44 := R45 := nil
 80 [-]: LOADK     R46 0        ; R46 := 0.000000
 81 [-]: LOADK     R47 0        ; R47 := 0.000000
 82 [-]: CLOSURE   R48 0        ; R48 := closure(Function #1)
 83 [-]: CLOSURE   R49 1        ; R49 := closure(Function #2)
 84 [-]: MOVE      R0 R43       ; R0 := R43
 85 [-]: MOVE      R0 R22       ; R0 := R22
 86 [-]: CLOSURE   R50 2        ; R50 := closure(Function #3)
 87 [-]: MOVE      R0 R1        ; R0 := R1
 88 [-]: MOVE      R0 R22       ; R0 := R22
 89 [-]: MOVE      R0 R41       ; R0 := R41
 90 [-]: MOVE      R0 R7        ; R0 := R7
 91 [-]: MOVE      R0 R29       ; R0 := R29
 92 [-]: MOVE      R0 R35       ; R0 := R35
 93 [-]: CLOSURE   R51 3        ; R51 := closure(Function #4)
 94 [-]: MOVE      R0 R45       ; R0 := R45
 95 [-]: MOVE      R0 R6        ; R0 := R6
 96 [-]: MOVE      R0 R13       ; R0 := R13
 97 [-]: MOVE      R0 R46       ; R0 := R46
 98 [-]: MOVE      R0 R37       ; R0 := R37
 99 [-]: MOVE      R0 R48       ; R0 := R48
100 [-]: MOVE      R0 R47       ; R0 := R47
101 [-]: MOVE      R0 R38       ; R0 := R38
102 [-]: MOVE      R0 R4        ; R0 := R4
103 [-]: MOVE      R0 R41       ; R0 := R41
104 [-]: CLOSURE   R52 4        ; R52 := closure(Function #5)
105 [-]: MOVE      R0 R43       ; R0 := R43
106 [-]: MOVE      R0 R28       ; R0 := R28
107 [-]: CLOSURE   R53 5        ; R53 := closure(Function #6)
108 [-]: MOVE      R0 R29       ; R0 := R29
109 [-]: MOVE      R0 R33       ; R0 := R33
110 [-]: MOVE      R0 R2        ; R0 := R2
111 [-]: MOVE      R0 R27       ; R0 := R27
112 [-]: MOVE      R0 R4        ; R0 := R4
113 [-]: MOVE      R0 R12       ; R0 := R12
114 [-]: MOVE      R0 R34       ; R0 := R34
115 [-]: MOVE      R0 R28       ; R0 := R28
116 [-]: MOVE      R0 R50       ; R0 := R50
117 [-]: MOVE      R0 R35       ; R0 := R35
118 [-]: MOVE      R0 R11       ; R0 := R11
119 [-]: MOVE      R0 R51       ; R0 := R51
120 [-]: MOVE      R0 R36       ; R0 := R36
121 [-]: MOVE      R0 R52       ; R0 := R52
122 [-]: MOVE      R0 R49       ; R0 := R49
123 [-]: CLOSURE   R54 6        ; R54 := closure(Function #7)
124 [-]: MOVE      R0 R21       ; R0 := R21
125 [-]: MOVE      R0 R22       ; R0 := R22
126 [-]: MOVE      R0 R20       ; R0 := R20
127 [-]: CLOSURE   R55 7        ; R55 := closure(Function #8)
128 [-]: MOVE      R0 R21       ; R0 := R21
129 [-]: MOVE      R0 R22       ; R0 := R22
130 [-]: MOVE      R0 R26       ; R0 := R26
131 [-]: MOVE      R0 R23       ; R0 := R23
132 [-]: MOVE      R0 R24       ; R0 := R24
133 [-]: MOVE      R0 R25       ; R0 := R25
134 [-]: MOVE      R0 R27       ; R0 := R27
135 [-]: MOVE      R0 R18       ; R0 := R18
136 [-]: MOVE      R0 R19       ; R0 := R19
137 [-]: MOVE      R0 R30       ; R0 := R30
138 [-]: MOVE      R0 R29       ; R0 := R29
139 [-]: MOVE      R0 R1        ; R0 := R1
140 [-]: MOVE      R0 R53       ; R0 := R53
141 [-]: MOVE      R0 R14       ; R0 := R14
142 [-]: MOVE      R0 R15       ; R0 := R15
143 [-]: MOVE      R0 R28       ; R0 := R28
144 [-]: MOVE      R0 R3        ; R0 := R3
145 [-]: MOVE      R0 R31       ; R0 := R31
146 [-]: MOVE      R0 R41       ; R0 := R41
147 [-]: MOVE      R0 R43       ; R0 := R43
148 [-]: MOVE      R0 R42       ; R0 := R42
149 [-]: MOVE      R0 R20       ; R0 := R20
150 [-]: MOVE      R0 R54       ; R0 := R54
151 [-]: MOVE      R0 R33       ; R0 := R33
152 [-]: MOVE      R0 R44       ; R0 := R44
153 [-]: MOVE      R0 R46       ; R0 := R46
154 [-]: MOVE      R0 R47       ; R0 := R47
155 [-]: MOVE      R0 R4        ; R0 := R4
156 [-]: MOVE      R0 R11       ; R0 := R11
157 [-]: MOVE      R0 R10       ; R0 := R10
158 [-]: MOVE      R0 R0        ; R0 := R0
159 [-]: CLOSURE   R56 8        ; R56 := closure(Function #9)
160 [-]: MOVE      R0 R55       ; R0 := R55
161 [-]: MOVE      R0 R32       ; R0 := R32
162 [-]: MOVE      R0 R29       ; R0 := R29
163 [-]: MOVE      R0 R33       ; R0 := R33
164 [-]: MOVE      R0 R22       ; R0 := R22
165 [-]: MOVE      R0 R41       ; R0 := R41
166 [-]: MOVE      R0 R54       ; R0 := R54
167 [-]: MOVE      R0 R21       ; R0 := R21
168 [-]: MOVE      R0 R23       ; R0 := R23
169 [-]: MOVE      R0 R31       ; R0 := R31
170 [-]: MOVE      R0 R43       ; R0 := R43
171 [-]: MOVE      R0 R42       ; R0 := R42
172 [-]: MOVE      R0 R40       ; R0 := R40
173 [-]: MOVE      R0 R2        ; R0 := R2
174 [-]: MOVE      R0 R27       ; R0 := R27
175 [-]: MOVE      R0 R34       ; R0 := R34
176 [-]: MOVE      R0 R35       ; R0 := R35
177 [-]: MOVE      R0 R36       ; R0 := R36
178 [-]: MOVE      R0 R28       ; R0 := R28
179 [-]: MOVE      R0 R1        ; R0 := R1
180 [-]: MOVE      R0 R18       ; R0 := R18
181 [-]: MOVE      R0 R19       ; R0 := R19
182 [-]: MOVE      R0 R4        ; R0 := R4
183 [-]: MOVE      R0 R45       ; R0 := R45
184 [-]: MOVE      R0 R52       ; R0 := R52
185 [-]: SETGLOBAL R56 K25      ; Start := R56
186 [-]: CLOSURE   R56 9        ; R56 := closure(Function #10)
187 [-]: MOVE      R0 R30       ; R0 := R30
188 [-]: SETGLOBAL R56 K26      ; OnPlayersChanged := R56
189 [-]: CLOSURE   R56 10       ; R56 := closure(Function #11)
190 [-]: MOVE      R0 R1        ; R0 := R1
191 [-]: MOVE      R0 R22       ; R0 := R22
192 [-]: SETGLOBAL R56 K27      ; PlayersLeaving := R56
193 [-]: CLOSURE   R56 11       ; R56 := closure(Function #12)
194 [-]: MOVE      R0 R1        ; R0 := R1
195 [-]: MOVE      R0 R22       ; R0 := R22
196 [-]: SETGLOBAL R56 K28      ; PlayersReturning := R56
197 [-]: CLOSURE   R56 12       ; R56 := closure(Function #13)
198 [-]: MOVE      R0 R8        ; R0 := R8
199 [-]: MOVE      R0 R9        ; R0 := R9
200 [-]: MOVE      R0 R20       ; R0 := R20
201 [-]: MOVE      R0 R44       ; R0 := R44
202 [-]: SETGLOBAL R56 K29      ; OnAgentRegistered := R56
203 [-]: CLOSURE   R56 13       ; R56 := closure(Function #14)
204 [-]: MOVE      R0 R22       ; R0 := R22
205 [-]: MOVE      R0 R29       ; R0 := R29
206 [-]: MOVE      R0 R33       ; R0 := R33
207 [-]: MOVE      R0 R20       ; R0 := R20
208 [-]: MOVE      R0 R41       ; R0 := R41
209 [-]: MOVE      R0 R42       ; R0 := R42
210 [-]: MOVE      R0 R26       ; R0 := R26
211 [-]: MOVE      R0 R35       ; R0 := R35
212 [-]: MOVE      R0 R43       ; R0 := R43
213 [-]: MOVE      R0 R16       ; R0 := R16
214 [-]: MOVE      R0 R47       ; R0 := R47
215 [-]: MOVE      R0 R46       ; R0 := R46
216 [-]: MOVE      R0 R2        ; R0 := R2
217 [-]: MOVE      R0 R27       ; R0 := R27
218 [-]: MOVE      R0 R15       ; R0 := R15
219 [-]: MOVE      R0 R39       ; R0 := R39
220 [-]: MOVE      R0 R4        ; R0 := R4
221 [-]: MOVE      R0 R10       ; R0 := R10
222 [-]: MOVE      R0 R17       ; R0 := R17
223 [-]: MOVE      R0 R14       ; R0 := R14
224 [-]: MOVE      R0 R37       ; R0 := R37
225 [-]: MOVE      R0 R48       ; R0 := R48
226 [-]: MOVE      R0 R38       ; R0 := R38
227 [-]: MOVE      R0 R36       ; R0 := R36
228 [-]: MOVE      R0 R45       ; R0 := R45
229 [-]: SETGLOBAL R56 K30      ; OnDeath := R56
230 [-]: RETURN    R0 1         ; return 


; Function #1:
;
; Name:            
; Defined at line: 80
; #Upvalues:       0
; #Parameters:     0
; Is_vararg:       0
; Max Stack Size:  6

  1 [-]: GETGLOBAL R0 K0        ; R0 := 0x5bced4c4
  2 [-]: GETTABLE  R0 R0 K1     ; R0 := R0[0xac1b386a]
  3 [-]: GETGLOBAL R1 K0        ; R1 := 0x5bced4c4
  4 [-]: GETTABLE  R1 R1 K2     ; R1 := R1[0xb62ecfe0]
  5 [-]: GETGLOBAL R2 K3        ; R2 := 0xe7f2b02f
  6 [-]: SELF      R2 R2 K4     ; R3 := R2; R2 := R2[0xebe2f513]
  7 [-]: CALL      R2 2 2       ; R2 := R2(R3)
  8 [-]: GETGLOBAL R3 K5        ; R3 := 0x9ba7909f
  9 [-]: SELF      R3 R3 K6     ; R4 := R3; R3 := R3[0x8151451d]
 10 [-]: LOADK     R5 K7        ; R5 := "Server.NumVirtualTestClients"
 11 [-]: CALL      R3 3 2       ; R3 := R3(R4,R5)
 12 [-]: ADD       R2 R2 R3     ; R2 := R2 + R3
 13 [-]: LOADK     R3 1         ; R3 := 1.000000
 14 [-]: CALL      R1 3 2       ; R1 := R1(R2,R3)
 15 [-]: LOADK     R2 4         ; R2 := 4.000000
 16 [-]: TAILCALL  R0 3 0       ; R0,... := R0(R1,R2)
 17 [-]: RETURN    R0 0         ; return R0,...
 18 [-]: RETURN    R0 1         ; return 


; Function #2:
;
; Name:            
; Defined at line: 84
; #Upvalues:       2
; #Parameters:     0
; Is_vararg:       0
; Max Stack Size:  7

  1 [-]: LOADK     R0 1         ; R0 := 1.000000
  2 [-]: GETUPVAL  R1 U0        ; R1 := U0
  3 [-]: LEN       R1 R1        ; R1 := # R1
  4 [-]: LOADK     R2 1         ; R2 := 1.000000
  5 [-]: FORPREP   R0 16        ; R0 -= R2; PC := 16
  6 [-]: GETGLOBAL R4 K0        ; R4 := 0x7b998233
  7 [-]: GETUPVAL  R5 U0        ; R5 := U0
  8 [-]: GETTABLE  R5 R5 R3     ; R5 := R5[R3]
  9 [-]: CALL      R4 2 2       ; R4 := R4(R5)
 10 [-]: TEST      R4 1         ; if R4 then PC := 16
 11 [-]: JMP       16           ; PC := 16
 12 [-]: GETUPVAL  R4 U0        ; R4 := U0
 13 [-]: GETTABLE  R4 R4 R3     ; R4 := R4[R3]
 14 [-]: SELF      R4 R4 K1     ; R5 := R4; R4 := R4[0xa2880940]
 15 [-]: CALL      R4 2 1       ; R4(R5)
 16 [-]: FORLOOP   R0 6         ; R0 += R2; if R0 <= R1 then begin PC := 6; R3 := R0 end
 17 [-]: GETUPVAL  R4 U1        ; R4 := U1
 18 [-]: SELF      R4 R4 K2     ; R5 := R4; R4 := R4[0xfe9dc265]
 19 [-]: LOADK     R6 4         ; R6 := 4.000000
 20 [-]: CALL      R4 3 1       ; R4(R5,R6)
 21 [-]: RETURN    R0 1         ; return 


; Function #3:
;
; Name:            
; Defined at line: 93
; #Upvalues:       6
; #Parameters:     0
; Is_vararg:       0
; Max Stack Size:  8

  1 [-]: GETUPVAL  R0 U0        ; R0 := U0
  2 [-]: GETTABLE  R0 R0 K0     ; R0 := R0[0x366089a7]
  3 [-]: GETGLOBAL R1 K1        ; R1 := 0x1f0b5333
  4 [-]: GETUPVAL  R2 U1        ; R2 := U1
  5 [-]: CALL      R0 3 1       ; R0(R1,R2)
  6 [-]: GETUPVAL  R0 U2        ; R0 := U2
  7 [-]: SELF      R0 R0 K2     ; R1 := R0; R0 := R0[0xbb610e5b]
  8 [-]: CALL      R0 2 2       ; R0 := R0(R1)
  9 [-]: SELF      R0 R0 K3     ; R1 := R0; R0 := R0[0x47901f07]
 10 [-]: GETUPVAL  R2 U3        ; R2 := U3
 11 [-]: GETGLOBAL R3 K4        ; R3 := EMPTY_SYMBOL
 12 [-]: GETGLOBAL R4 K5        ; R4 := 0xa421af95
 13 [-]: LOADK     R5 0         ; R5 := 0.000000
 14 [-]: LOADK     R6 1         ; R6 := 1.000000
 15 [-]: LOADK     R7 0         ; R7 := 0.000000
 16 [-]: CALL      R4 4 0       ; R4,... := R4(R5,R6,R7)
 17 [-]: CALL      R0 0 1       ; R0(R1,...)
 18 [-]: GETUPVAL  R0 U4        ; R0 := U4
 19 [-]: SELF      R0 R0 K6     ; R1 := R0; R0 := R0[0x8abff40e]
 20 [-]: GETUPVAL  R2 U5        ; R2 := U5
 21 [-]: CALL      R0 3 1       ; R0(R1,R2)
 22 [-]: RETURN    R0 1         ; return 


; Function #4:
;
; Name:            
; Defined at line: 99
; #Upvalues:       10
; #Parameters:     0
; Is_vararg:       0
; Max Stack Size:  6

  1 [-]: GETGLOBAL R0 K0        ; R0 := _T
  2 [-]: GETTABLE  R0 R0 K1     ; R0 := R0[0x8ee923fe]
  3 [-]: LOADK     R1 K2        ; R1 := "KillTracker"
  4 [-]: GETUPVAL  R2 U1        ; R2 := U1
  5 [-]: GETTABLE  R2 R2 K3     ; R2 := R2["HT_OPPONENT_BAR"]
  6 [-]: LOADNIL   R3 R3        ; R3 := nil
  7 [-]: LOADK     R4 10        ; R4 := 10.000000
  8 [-]: CALL      R0 5 2       ; R0 := R0(R1,R2,R3,R4)
  9 [-]: SETUPVAL  R0 U0        ; U82 := R0
 10 [-]: GETUPVAL  R0 U0        ; R0 := U0
 11 [-]: GETTABLE  R0 R0 K4     ; R0 := R0[0xa849d5ec]
 12 [-]: LOADK     R1 K5        ; R1 := "/Lotus/Language/Menu/Codex_Tenno"
 13 [-]: CALL      R0 2 1       ; R0(R1)
 14 [-]: GETUPVAL  R0 U0        ; R0 := U0
 15 [-]: GETTABLE  R0 R0 K6     ; R0 := R0[0x3780bc35]
 16 [-]: GETUPVAL  R1 U2        ; R1 := U2
 17 [-]: CALL      R0 2 1       ; R0(R1)
 18 [-]: GETUPVAL  R0 U0        ; R0 := U0
 19 [-]: GETTABLE  R0 R0 K7     ; R0 := R0[0x6b560078]
 20 [-]: GETGLOBAL R1 K8        ; R1 := 0x5bced4c4
 21 [-]: GETTABLE  R1 R1 K9     ; R1 := R1[0xac1b386a]
 22 [-]: LOADK     R2 1         ; R2 := 1.000000
 23 [-]: GETUPVAL  R3 U3        ; R3 := U3
 24 [-]: GETUPVAL  R4 U4        ; R4 := U4
 25 [-]: GETUPVAL  R5 U5        ; R5 := U5
 26 [-]: CALL      R5 1 2       ; R5 := R5()
 27 [-]: GETTABLE  R4 R4 R5     ; R4 := R4[R5]
 28 [-]: DIV       R3 R3 R4     ; R3 := R3 / R4
 29 [-]: CALL      R1 3 2       ; R1 := R1(R2,R3)
 30 [-]: GETGLOBAL R2 K8        ; R2 := 0x5bced4c4
 31 [-]: GETTABLE  R2 R2 K9     ; R2 := R2[0xac1b386a]
 32 [-]: LOADK     R3 1         ; R3 := 1.000000
 33 [-]: GETUPVAL  R4 U6        ; R4 := U6
 34 [-]: GETUPVAL  R5 U7        ; R5 := U7
 35 [-]: DIV       R4 R4 R5     ; R4 := R4 / R5
 36 [-]: CALL      R2 3 0       ; R2,... := R2(R3,R4)
 37 [-]: CALL      R0 0 1       ; R0(R1,...)
 38 [-]: GETUPVAL  R0 U0        ; R0 := U0
 39 [-]: GETTABLE  R0 R0 K10    ; R0 := R0[0xb7ae3621]
 40 [-]: LOADK     R1 28        ; R1 := 28.000000
 41 [-]: LOADK     R2 20        ; R2 := 20.000000
 42 [-]: LOADBOOL  R3 1 0       ; R3 := true
 43 [-]: CALL      R0 4 1       ; R0(R1,R2,R3)
 44 [-]: GETUPVAL  R0 U8        ; R0 := U8
 45 [-]: GETTABLE  R0 R0 K11    ; R0 := R0[0x1551aa65]
 46 [-]: GETUPVAL  R1 U9        ; R1 := U9
 47 [-]: SELF      R1 R1 K12    ; R2 := R1; R1 := R1[0xbb610e5b]
 48 [-]: CALL      R1 2 0       ; R1,... := R1(R2)
 49 [-]: CALL      R0 0 1       ; R0(R1,...)
 50 [-]: RETURN    R0 1         ; return 


; Function #5:
;
; Name:            
; Defined at line: 108
; #Upvalues:       2
; #Parameters:     0
; Is_vararg:       0
; Max Stack Size:  18

  1 [-]: LOADK     R0 1         ; R0 := 1.000000
  2 [-]: GETUPVAL  R1 U0        ; R1 := U0
  3 [-]: LEN       R1 R1        ; R1 := # R1
  4 [-]: LOADK     R2 1         ; R2 := 1.000000
  5 [-]: FORPREP   R0 73        ; R0 -= R2; PC := 73
  6 [-]: GETGLOBAL R4 K0        ; R4 := 0x7b998233
  7 [-]: GETUPVAL  R5 U0        ; R5 := U0
  8 [-]: GETTABLE  R5 R5 R3     ; R5 := R5[R3]
  9 [-]: CALL      R4 2 2       ; R4 := R4(R5)
 10 [-]: TEST      R4 1         ; if R4 then PC := 72
 11 [-]: JMP       72           ; PC := 72
 12 [-]: GETUPVAL  R4 U0        ; R4 := U0
 13 [-]: GETTABLE  R4 R4 R3     ; R4 := R4[R3]
 14 [-]: SELF      R4 R4 K1     ; R5 := R4; R4 := R4[0x1ac1655c]
 15 [-]: CALL      R4 2 2       ; R4 := R4(R5)
 16 [-]: SELF      R5 R4 K2     ; R6 := R4; R5 := R4[0xa383de31]
 17 [-]: GETGLOBAL R7 K3        ; R7 := 0x0469f296
 18 [-]: LOADK     R8 K4        ; R8 := "DynamicSurvivorsRetreatInvul"
 19 [-]: CALL      R7 2 2       ; R7 := R7(R8)
 20 [-]: LOADK     R8 25        ; R8 := 25.000000
 21 [-]: LOADK     R9 6         ; R9 := 6.000000
 22 [-]: LOADK     R10 0        ; R10 := 0.000000
 23 [-]: CALL      R5 6 1       ; R5(R6,R7,R8,R9,R10)
 24 [-]: GETUPVAL  R5 U0        ; R5 := U0
 25 [-]: GETTABLE  R5 R5 R3     ; R5 := R5[R3]
 26 [-]: SELF      R5 R5 K6     ; R6 := R5; R5 := R5[0x259b9467]
 27 [-]: LOADK     R7 3         ; R7 := 3.000000
 28 [-]: CALL      R5 3 1       ; R5(R6,R7)
 29 [-]: GETUPVAL  R5 U0        ; R5 := U0
 30 [-]: GETTABLE  R5 R5 R3     ; R5 := R5[R3]
 31 [-]: SELF      R5 R5 K7     ; R6 := R5; R5 := R5[0xc1595bd5]
 32 [-]: GETGLOBAL R7 K8        ; R7 := gBaseMarkerInfoType
 33 [-]: CALL      R5 3 2       ; R5 := R5(R6,R7)
 34 [-]: GETGLOBAL R6 K9        ; R6 := 0xcfc01047
 35 [-]: MOVE      R7 R5        ; R7 := R5
 36 [-]: CALL      R6 2 4       ; R6,R7,R8 := R6(R7)
 37 [-]: JMP       45           ; PC := 45
 38 [-]: GETGLOBAL R11 K0       ; R11 := 0x7b998233
 39 [-]: MOVE      R12 R10      ; R12 := R10
 40 [-]: CALL      R11 2 2      ; R11 := R11(R12)
 41 [-]: TEST      R11 1        ; if R11 then PC := 45
 42 [-]: JMP       45           ; PC := 45
 43 [-]: SELF      R11 R10 K10  ; R12 := R10; R11 := R10[0xa2880940]
 44 [-]: CALL      R11 2 1      ; R11(R12)
 45 [-]: TFORLOOP  R6 2         ; R9,R10 :=  R6(R7,R8); if R9 ~= nil then begin PC = 38; R8 := R9 end
 46 [-]: JMP       38           ; PC := 38
 47 [-]: GETUPVAL  R11 U0       ; R11 := U0
 48 [-]: GETTABLE  R11 R11 R3   ; R11 := R11[R3]
 49 [-]: SELF      R11 R11 K11  ; R12 := R11; R11 := R11[0x16e0b3da]
 50 [-]: GETGLOBAL R13 K12      ; R13 := 0xa4bb8f34
 51 [-]: CALL      R11 3 2      ; R11 := R11(R12,R13)
 52 [-]: TEST      R11 1        ; if R11 then PC := 72
 53 [-]: JMP       72           ; PC := 72
 54 [-]: GETUPVAL  R11 U0       ; R11 := U0
 55 [-]: GETTABLE  R11 R11 R3   ; R11 := R11[R3]
 56 [-]: SELF      R11 R11 K13  ; R12 := R11; R11 := R11[0x5d985c7e]
 57 [-]: GETGLOBAL R13 K14      ; R13 := 0x62b46842
 58 [-]: LOADBOOL  R14 0 0      ; R14 := false
 59 [-]: LOADK     R15 3        ; R15 := 3.000000
 60 [-]: LOADK     R16 1        ; R16 := 1.000000
 61 [-]: LOADBOOL  R17 1 0      ; R17 := true
 62 [-]: CALL      R11 7 1      ; R11(R12,R13,R14,R15,R16,R17)
 63 [-]: GETUPVAL  R11 U1       ; R11 := U1
 64 [-]: SELF      R11 R11 K15  ; R12 := R11; R11 := R11[0xbd2e96ea]
 65 [-]: GETGLOBAL R13 K14      ; R13 := 0x62b46842
 66 [-]: SELF      R13 R13 K16  ; R14 := R13; R13 := R13[0xf0267db4]
 67 [-]: CALL      R13 2 2      ; R13 := R13(R14)
 68 [-]: CLOSURE   R14 0        ; R14 := closure(Function #5.1)
 69 [-]: GETUPVAL  R0 U0        ; R0 := U0
 70 [-]: MOVE      R0 R3        ; R0 := R3
 71 [-]: CALL      R11 4 1      ; R11(R12,R13,R14)
 72 [-]: CLOSE     R3           ; SAVE R3,...
 73 [-]: FORLOOP   R0 6         ; R0 += R2; if R0 <= R1 then begin PC := 6; R3 := R0 end
 74 [-]: RETURN    R0 1         ; return 


; Function #5.1:
;
; Name:            
; Defined at line: 124
; #Upvalues:       2
; #Parameters:     0
; Is_vararg:       0
; Max Stack Size:  7

  1 [-]: GETGLOBAL R0 K0        ; R0 := 0x7b998233
  2 [-]: GETUPVAL  R1 U0        ; R1 := U0
  3 [-]: CALL      R0 2 2       ; R0 := R0(R1)
  4 [-]: TEST      R0 1         ; if R0 then PC := 23
  5 [-]: JMP       23           ; PC := 23
  6 [-]: GETGLOBAL R0 K0        ; R0 := 0x7b998233
  7 [-]: GETUPVAL  R1 U0        ; R1 := U0
  8 [-]: GETUPVAL  R2 U1        ; R2 := U1
  9 [-]: GETTABLE  R1 R1 R2     ; R1 := R1[R2]
 10 [-]: CALL      R0 2 2       ; R0 := R0(R1)
 11 [-]: TEST      R0 1         ; if R0 then PC := 23
 12 [-]: JMP       23           ; PC := 23
 13 [-]: GETUPVAL  R0 U0        ; R0 := U0
 14 [-]: GETUPVAL  R1 U1        ; R1 := U1
 15 [-]: GETTABLE  R0 R0 R1     ; R0 := R0[R1]
 16 [-]: SELF      R0 R0 K1     ; R1 := R0; R0 := R0[0x5d985c7e]
 17 [-]: GETGLOBAL R2 K2        ; R2 := 0xa4bb8f34
 18 [-]: LOADBOOL  R3 0 0       ; R3 := false
 19 [-]: LOADK     R4 3         ; R4 := 3.000000
 20 [-]: LOADK     R5 2         ; R5 := 2.000000
 21 [-]: LOADBOOL  R6 1 0       ; R6 := true
 22 [-]: CALL      R0 7 1       ; R0(R1,R2,R3,R4,R5,R6)
 23 [-]: RETURN    R0 1         ; return 


; Function #6:
;
; Name:            
; Defined at line: 136
; #Upvalues:       15
; #Parameters:     0
; Is_vararg:       0
; Max Stack Size:  5

  1 [-]: GETUPVAL  R0 U0        ; R0 := U0
  2 [-]: SELF      R0 R0 K0     ; R1 := R0; R0 := R0[0x209398c2]
  3 [-]: CALL      R0 2 2       ; R0 := R0(R1)
  4 [-]: GETUPVAL  R1 U1        ; R1 := U1
  5 [-]: EQ        0 R0 R1      ; if R0 ~= R1 then PC := 20
  6 [-]: JMP       20           ; PC := 20
  7 [-]: GETUPVAL  R1 U2        ; R1 := U2
  8 [-]: GETTABLE  R1 R1 K1     ; R1 := R1[0x9742b85b]
  9 [-]: GETUPVAL  R2 U3        ; R2 := U3
 10 [-]: GETGLOBAL R3 K2        ; R3 := 0x0469f296
 11 [-]: LOADK     R4 K3        ; R4 := "Arrival"
 12 [-]: CALL      R3 2 2       ; R3 := R3(R4)
 13 [-]: LOADBOOL  R4 1 0       ; R4 := true
 14 [-]: CALL      R1 4 1       ; R1(R2,R3,R4)
 15 [-]: GETUPVAL  R1 U4        ; R1 := U4
 16 [-]: GETTABLE  R1 R1 K4     ; R1 := R1[0xa1df01d6]
 17 [-]: GETUPVAL  R2 U5        ; R2 := U5
 18 [-]: CALL      R1 2 1       ; R1(R2)
 19 [-]: JMP       49           ; PC := 49
 20 [-]: GETUPVAL  R1 U6        ; R1 := U6
 21 [-]: EQ        0 R0 R1      ; if R0 ~= R1 then PC := 29
 22 [-]: JMP       29           ; PC := 29
 23 [-]: GETUPVAL  R1 U7        ; R1 := U7
 24 [-]: SELF      R1 R1 K5     ; R2 := R1; R1 := R1[0xbd2e96ea]
 25 [-]: LOADK     R3 5         ; R3 := 5.000000
 26 [-]: GETUPVAL  R4 U8        ; R4 := U8
 27 [-]: CALL      R1 4 1       ; R1(R2,R3,R4)
 28 [-]: JMP       49           ; PC := 49
 29 [-]: GETUPVAL  R1 U9        ; R1 := U9
 30 [-]: EQ        0 R0 R1      ; if R0 ~= R1 then PC := 39
 31 [-]: JMP       39           ; PC := 39
 32 [-]: GETUPVAL  R1 U4        ; R1 := U4
 33 [-]: GETTABLE  R1 R1 K4     ; R1 := R1[0xa1df01d6]
 34 [-]: GETUPVAL  R2 U10       ; R2 := U10
 35 [-]: CALL      R1 2 1       ; R1(R2)
 36 [-]: GETUPVAL  R1 U11       ; R1 := U11
 37 [-]: CALL      R1 1 1       ; R1()
 38 [-]: JMP       49           ; PC := 49
 39 [-]: GETUPVAL  R1 U12       ; R1 := U12
 40 [-]: EQ        0 R0 R1      ; if R0 ~= R1 then PC := 49
 41 [-]: JMP       49           ; PC := 49
 42 [-]: GETUPVAL  R1 U13       ; R1 := U13
 43 [-]: CALL      R1 1 1       ; R1()
 44 [-]: GETUPVAL  R1 U7        ; R1 := U7
 45 [-]: SELF      R1 R1 K5     ; R2 := R1; R1 := R1[0xbd2e96ea]
 46 [-]: LOADK     R3 6         ; R3 := 6.000000
 47 [-]: GETUPVAL  R4 U14       ; R4 := U14
 48 [-]: CALL      R1 4 1       ; R1(R2,R3,R4)
 49 [-]: RETURN    R0 1         ; return 


; Function #7:
;
; Name:            
; Defined at line: 155
; #Upvalues:       3
; #Parameters:     2
; Is_vararg:       0
; Max Stack Size:  9

  1 [-]: GETUPVAL  R2 U0        ; R2 := U0
  2 [-]: SELF      R2 R2 K0     ; R3 := R2; R2 := R2[0x2883e796]
  3 [-]: MOVE      R4 R0        ; R4 := R0
  4 [-]: GETUPVAL  R5 U1        ; R5 := U1
  5 [-]: LOADK     R6 15        ; R6 := 15.000000
  6 [-]: GETGLOBAL R7 K1        ; R7 := 0x0469f296
  7 [-]: LOADK     R8 K2        ; R8 := "RandomTeam"
  8 [-]: CALL      R7 2 2       ; R7 := R7(R8)
  9 [-]: MOVE      R8 R1        ; R8 := R1
 10 [-]: CALL      R2 7 2       ; R2 := R2(R3,R4,R5,R6,R7,R8)
 11 [-]: GETGLOBAL R3 K3        ; R3 := 0x7b998233
 12 [-]: MOVE      R4 R2        ; R4 := R2
 13 [-]: CALL      R3 2 2       ; R3 := R3(R4)
 14 [-]: TEST      R3 1         ; if R3 then PC := 30
 15 [-]: JMP       30           ; PC := 30
 16 [-]: SELF      R3 R2 K4     ; R4 := R2; R3 := R2[0xa64a1f4a]
 17 [-]: GETUPVAL  R5 U1        ; R5 := U1
 18 [-]: LOADK     R6 25        ; R6 := 25.000000
 19 [-]: CALL      R3 4 1       ; R3(R4,R5,R6)
 20 [-]: SELF      R3 R2 K5     ; R4 := R2; R3 := R2[0xbb610e5b]
 21 [-]: CALL      R3 2 2       ; R3 := R3(R4)
 22 [-]: SELF      R4 R3 K6     ; R5 := R3; R4 := R3[0x0cca925a]
 23 [-]: GETUPVAL  R6 U2        ; R6 := U2
 24 [-]: CALL      R4 3 1       ; R4(R5,R6)
 25 [-]: GETUPVAL  R4 U1        ; R4 := U1
 26 [-]: SELF      R4 R4 K7     ; R5 := R4; R4 := R4[0x2fb0041c]
 27 [-]: MOVE      R6 R2        ; R6 := R2
 28 [-]: CALL      R4 3 1       ; R4(R5,R6)
 29 [-]: RETURN    R2 2         ; return R2
 30 [-]: LOADNIL   R4 R4        ; R4 := nil
 31 [-]: RETURN    R4 2         ; return R4
 32 [-]: RETURN    R0 1         ; return 


; Function #8:
;
; Name:            
; Defined at line: 170
; #Upvalues:       31
; #Parameters:     1
; Is_vararg:       0
; Max Stack Size:  24

  1 [-]: GETGLOBAL R1 K0        ; R1 := 0x89326c93
  2 [-]: SELF      R1 R1 K1     ; R2 := R1; R1 := R1[0x29ef273d]
  3 [-]: CALL      R1 2 2       ; R1 := R1(R2)
  4 [-]: SELF      R1 R1 K2     ; R2 := R1; R1 := R1[0x66905cb0]
  5 [-]: CALL      R1 2 2       ; R1 := R1(R2)
  6 [-]: SETUPVAL  R1 U0        ; U82 := R0
  7 [-]: GETUPVAL  R1 U0        ; R1 := U0
  8 [-]: SELF      R1 R1 K3     ; R2 := R1; R1 := R1[0xa2d83ed4]
  9 [-]: CALL      R1 2 2       ; R1 := R1(R2)
 10 [-]: TEST      R1 1         ; if R1 then PC := 16
 11 [-]: JMP       16           ; PC := 16
 12 [-]: GETGLOBAL R1 K4        ; R1 := 0xcbd666e1
 13 [-]: LOADK     R2 0         ; R2 := 0.000000
 14 [-]: CALL      R1 2 1       ; R1(R2)
 15 [-]: JMP       7            ; PC := 7
 16 [-]: SETUPVAL  R0 U1        ; U82 := R1
 17 [-]: SELF      R1 R0 K5     ; R2 := R0; R1 := R0[0x891629fa]
 18 [-]: CALL      R1 2 2       ; R1 := R1(R2)
 19 [-]: SETUPVAL  R1 U2        ; U82 := R2
 20 [-]: SELF      R1 R0 K6     ; R2 := R0; R1 := R0[0xd1586535]
 21 [-]: CALL      R1 2 2       ; R1 := R1(R2)
 22 [-]: SETUPVAL  R1 U3        ; U82 := R3
 23 [-]: SELF      R1 R0 K7     ; R2 := R0; R1 := R0[0xc5b92518]
 24 [-]: CALL      R1 2 2       ; R1 := R1(R2)
 25 [-]: SETUPVAL  R1 U4        ; U82 := R4
 26 [-]: SELF      R1 R0 K8     ; R2 := R0; R1 := R0[0x7c97b143]
 27 [-]: CALL      R1 2 2       ; R1 := R1(R2)
 28 [-]: SETUPVAL  R1 U5        ; U82 := R5
 29 [-]: SELF      R1 R0 K9     ; R2 := R0; R1 := R0[0x4c976eda]
 30 [-]: CALL      R1 2 2       ; R1 := R1(R2)
 31 [-]: SELF      R1 R1 K10    ; R2 := R1; R1 := R1[0xe4c355e2]
 32 [-]: CALL      R1 2 2       ; R1 := R1(R2)
 33 [-]: SETUPVAL  R1 U6        ; U82 := R6
 34 [-]: GETGLOBAL R1 K0        ; R1 := 0x89326c93
 35 [-]: SELF      R1 R1 K11    ; R2 := R1; R1 := R1[0xb7d33840]
 36 [-]: LOADK     R3 K12       ; R3 := "OnPlayersChanged"
 37 [-]: CALL      R1 3 1       ; R1(R2,R3)
 38 [-]: GETUPVAL  R1 U1        ; R1 := U1
 39 [-]: SELF      R1 R1 K13    ; R2 := R1; R1 := R1[0xe19c3f44]
 40 [-]: LOADK     R3 K14       ; R3 := "PlayersLeaving"
 41 [-]: GETUPVAL  R4 U7        ; R4 := U7
 42 [-]: CALL      R1 4 1       ; R1(R2,R3,R4)
 43 [-]: GETUPVAL  R1 U1        ; R1 := U1
 44 [-]: SELF      R1 R1 K15    ; R2 := R1; R1 := R1[0x3f86f5a0]
 45 [-]: LOADK     R3 K16       ; R3 := "PlayersReturning"
 46 [-]: GETUPVAL  R4 U8        ; R4 := U8
 47 [-]: CALL      R1 4 1       ; R1(R2,R3,R4)
 48 [-]: GETGLOBAL R1 K0        ; R1 := 0x89326c93
 49 [-]: SELF      R1 R1 K17    ; R2 := R1; R1 := R1[0x7d108ddb]
 50 [-]: CALL      R1 2 2       ; R1 := R1(R2)
 51 [-]: SETUPVAL  R1 U9        ; U82 := R9
 52 [-]: GETUPVAL  R1 U2        ; R1 := U2
 53 [-]: SELF      R1 R1 K18    ; R2 := R1; R1 := R1[0x5b344f44]
 54 [-]: LOADK     R3 K19       ; R3 := "OnAgentRegistered"
 55 [-]: GETGLOBAL R4 K20       ; R4 := 0x0469f296
 56 [-]: LOADK     R5 K21       ; R5 := "Registration"
 57 [-]: CALL      R4 2 0       ; R4,... := R4(R5)
 58 [-]: CALL      R1 0 1       ; R1(R2,...)
 59 [-]: GETUPVAL  R1 U11       ; R1 := U11
 60 [-]: GETTABLE  R1 R1 K22    ; R1 := R1[0xc9013731]
 61 [-]: GETUPVAL  R2 U12       ; R2 := U12
 62 [-]: GETUPVAL  R3 U1        ; R3 := U1
 63 [-]: NEWTABLE  R4 2 0       ; R4 := {}
 64 [-]: GETUPVAL  R5 U13       ; R5 := U13
 65 [-]: GETUPVAL  R6 U14       ; R6 := U14
 66 [-]: SETLIST   R4 2 1       ; R4[(1-1)*FPF+i] := R(4+i), 1 <= i <= 2
 67 [-]: CALL      R1 4 2       ; R1 := R1(R2,R3,R4)
 68 [-]: SETUPVAL  R1 U10       ; U82 := R10
 69 [-]: GETUPVAL  R1 U16       ; R1 := U16
 70 [-]: GETTABLE  R1 R1 K23    ; R1 := R1[0xde474187]
 71 [-]: CALL      R1 1 2       ; R1 := R1()
 72 [-]: SETUPVAL  R1 U15       ; U82 := R15
 73 [-]: GETUPVAL  R1 U11       ; R1 := U11
 74 [-]: GETTABLE  R1 R1 K24    ; R1 := R1[0xa80cf6ff]
 75 [-]: GETUPVAL  R2 U0        ; R2 := U0
 76 [-]: MOVE      R3 R0        ; R3 := R0
 77 [-]: CALL      R1 3 2       ; R1 := R1(R2,R3)
 78 [-]: SETUPVAL  R1 U17       ; U82 := R17
 79 [-]: GETUPVAL  R1 U17       ; R1 := U17
 80 [-]: SETTABLE  R1 K25 K26   ; R1["mIncludeChildHints"] := true
 81 [-]: GETUPVAL  R1 U1        ; R1 := U1
 82 [-]: SELF      R1 R1 K27    ; R2 := R1; R1 := R1[0x50a76235]
 83 [-]: CALL      R1 2 2       ; R1 := R1(R2)
 84 [-]: TEST      R1 0         ; if not R1 then PC := 226
 85 [-]: JMP       226          ; PC := 226
 86 [-]: GETUPVAL  R1 U10       ; R1 := U10
 87 [-]: SELF      R1 R1 K28    ; R2 := R1; R1 := R1[0x209398c2]
 88 [-]: CALL      R1 2 2       ; R1 := R1(R2)
 89 [-]: GETUPVAL  R2 U2        ; R2 := U2
 90 [-]: SELF      R2 R2 K29    ; R3 := R2; R2 := R2[0x22df603c]
 91 [-]: CALL      R2 2 2       ; R2 := R2(R3)
 92 [-]: GETGLOBAL R3 K30       ; R3 := 0xc8802016
 93 [-]: MOVE      R4 R2        ; R4 := R2
 94 [-]: CALL      R3 2 4       ; R3,R4,R5 := R3(R4)
 95 [-]: JMP       173          ; PC := 173
 96 [-]: SELF      R8 R7 K31    ; R9 := R7; R8 := R7[0xbb610e5b]
 97 [-]: CALL      R8 2 2       ; R8 := R8(R9)
 98 [-]: LOADBOOL  R9 0 0       ; R9 := false
 99 [-]: SELF      R10 R7 K32   ; R11 := R7; R10 := R7[0xf2deaf69]
100 [-]: GETGLOBAL R12 K33      ; R12 := 0x93b9146a
101 [-]: CALL      R10 3 2      ; R10 := R10(R11,R12)
102 [-]: TEST      R10 0        ; if not R10 then PC := 135
103 [-]: JMP       135          ; PC := 135
104 [-]: LOADBOOL  R9 1 0       ; R9 := true
105 [-]: SETUPVAL  R7 U18       ; U82 := R18
106 [-]: GETUPVAL  R10 U17      ; R10 := U17
107 [-]: GETTABLE  R10 R10 K34  ; R10 := R10[0xeb80a36f]
108 [-]: GETUPVAL  R11 U18      ; R11 := U18
109 [-]: SELF      R11 R11 K31  ; R12 := R11; R11 := R11[0xbb610e5b]
110 [-]: CALL      R11 2 0      ; R11,... := R11(R12)
111 [-]: CALL      R10 0 1      ; R10(R11,...)
112 [-]: GETUPVAL  R10 U17      ; R10 := U17
113 [-]: GETTABLE  R10 R10 K35  ; R10 := R10[0xb52a11ec]
114 [-]: LOADK     R11 30       ; R11 := 30.000000
115 [-]: CALL      R10 2 1      ; R10(R11)
116 [-]: GETGLOBAL R10 K36      ; R10 := 0x7b998233
117 [-]: GETUPVAL  R11 U18      ; R11 := U18
118 [-]: CALL      R10 2 2      ; R10 := R10(R11)
119 [-]: TEST      R10 1        ; if R10 then PC := 135
120 [-]: JMP       135          ; PC := 135
121 [-]: GETGLOBAL R10 K36      ; R10 := 0x7b998233
122 [-]: GETUPVAL  R11 U18      ; R11 := U18
123 [-]: SELF      R11 R11 K31  ; R12 := R11; R11 := R11[0xbb610e5b]
124 [-]: CALL      R11 2 0      ; R11,... := R11(R12)
125 [-]: CALL      R10 0 2      ; R10 := R10(R11,...)
126 [-]: TEST      R10 1        ; if R10 then PC := 135
127 [-]: JMP       135          ; PC := 135
128 [-]: GETGLOBAL R10 K37      ; R10 := 0x33bdd652
129 [-]: GETTABLE  R10 R10 K38  ; R10 := R10[0x23d5322f]
130 [-]: GETUPVAL  R11 U19      ; R11 := U19
131 [-]: GETUPVAL  R12 U18      ; R12 := U18
132 [-]: SELF      R12 R12 K31  ; R13 := R12; R12 := R12[0xbb610e5b]
133 [-]: CALL      R12 2 0      ; R12,... := R12(R13)
134 [-]: CALL      R10 0 1      ; R10(R11,...)
135 [-]: GETGLOBAL R10 K30      ; R10 := 0xc8802016
136 [-]: GETGLOBAL R11 K39      ; R11 := 0xb96b249e
137 [-]: CALL      R10 2 4      ; R10,R11,R12 := R10(R11)
138 [-]: JMP       162          ; PC := 162
139 [-]: SELF      R15 R7 K32   ; R16 := R7; R15 := R7[0xf2deaf69]
140 [-]: MOVE      R17 R14      ; R17 := R14
141 [-]: CALL      R15 3 2      ; R15 := R15(R16,R17)
142 [-]: TEST      R15 0        ; if not R15 then PC := 162
143 [-]: JMP       162          ; PC := 162
144 [-]: LOADBOOL  R9 1 0       ; R9 := true
145 [-]: GETGLOBAL R15 K37      ; R15 := 0x33bdd652
146 [-]: GETTABLE  R15 R15 K38  ; R15 := R15[0x23d5322f]
147 [-]: GETUPVAL  R16 U20      ; R16 := U20
148 [-]: MOVE      R17 R7       ; R17 := R7
149 [-]: CALL      R15 3 1      ; R15(R16,R17)
150 [-]: GETGLOBAL R15 K36      ; R15 := 0x7b998233
151 [-]: SELF      R16 R7 K31   ; R17 := R7; R16 := R7[0xbb610e5b]
152 [-]: CALL      R16 2 0      ; R16,... := R16(R17)
153 [-]: CALL      R15 0 2      ; R15 := R15(R16,...)
154 [-]: TEST      R15 1        ; if R15 then PC := 162
155 [-]: JMP       162          ; PC := 162
156 [-]: GETGLOBAL R15 K37      ; R15 := 0x33bdd652
157 [-]: GETTABLE  R15 R15 K38  ; R15 := R15[0x23d5322f]
158 [-]: GETUPVAL  R16 U19      ; R16 := U19
159 [-]: SELF      R17 R7 K31   ; R18 := R7; R17 := R7[0xbb610e5b]
160 [-]: CALL      R17 2 0      ; R17,... := R17(R18)
161 [-]: CALL      R15 0 1      ; R15(R16,...)
162 [-]: TFORLOOP  R10 2        ; R13,R14 :=  R10(R11,R12); if R13 ~= nil then begin PC = 139; R12 := R13 end
163 [-]: JMP       139          ; PC := 139
164 [-]: TEST      R9 0         ; if not R9 then PC := 173
165 [-]: JMP       173          ; PC := 173
166 [-]: SELF      R15 R7 K40   ; R16 := R7; R15 := R7[0xa64a1f4a]
167 [-]: GETUPVAL  R17 U1       ; R17 := U1
168 [-]: LOADK     R18 25       ; R18 := 25.000000
169 [-]: CALL      R15 4 1      ; R15(R16,R17,R18)
170 [-]: SELF      R15 R8 K41   ; R16 := R8; R15 := R8[0x0cca925a]
171 [-]: GETUPVAL  R17 U21      ; R17 := U21
172 [-]: CALL      R15 3 1      ; R15(R16,R17)
173 [-]: TFORLOOP  R3 2         ; R6,R7 :=  R3(R4,R5); if R6 ~= nil then begin PC = 96; R5 := R6 end
174 [-]: JMP       96           ; PC := 96
175 [-]: GETGLOBAL R15 K36      ; R15 := 0x7b998233
176 [-]: GETUPVAL  R16 U18      ; R16 := U18
177 [-]: CALL      R15 2 2      ; R15 := R15(R16)
178 [-]: TEST      R15 0        ; if not R15 then PC := 218
179 [-]: JMP       218          ; PC := 218
180 [-]: GETUPVAL  R15 U22      ; R15 := U22
181 [-]: GETGLOBAL R16 K33      ; R16 := 0x93b9146a
182 [-]: GETUPVAL  R17 U0       ; R17 := U0
183 [-]: SELF      R17 R17 K42  ; R18 := R17; R17 := R17[0xc1088746]
184 [-]: GETUPVAL  R19 U3       ; R19 := U3
185 [-]: CALL      R17 3 2      ; R17 := R17(R18,R19)
186 [-]: GETGLOBAL R18 K43      ; R18 := 0x7e3ded28
187 [-]: MUL       R17 R17 R18  ; R17 := R17 * R18
188 [-]: CALL      R15 3 2      ; R15 := R15(R16,R17)
189 [-]: SETUPVAL  R15 U18      ; U82 := R18
190 [-]: GETGLOBAL R15 K36      ; R15 := 0x7b998233
191 [-]: GETUPVAL  R16 U18      ; R16 := U18
192 [-]: CALL      R15 2 2      ; R15 := R15(R16)
193 [-]: TEST      R15 1        ; if R15 then PC := 218
194 [-]: JMP       218          ; PC := 218
195 [-]: GETUPVAL  R15 U18      ; R15 := U18
196 [-]: SELF      R15 R15 K31  ; R16 := R15; R15 := R15[0xbb610e5b]
197 [-]: CALL      R15 2 2      ; R15 := R15(R16)
198 [-]: GETUPVAL  R16 U23      ; R16 := U23
199 [-]: EQ        0 R1 R16     ; if R1 ~= R16 then PC := 210
200 [-]: JMP       210          ; PC := 210
201 [-]: SELF      R16 R15 K44  ; R17 := R15; R16 := R15[0x47901f07]
202 [-]: GETGLOBAL R18 K45      ; R18 := 0xbb76409b
203 [-]: GETGLOBAL R19 K46      ; R19 := EMPTY_SYMBOL
204 [-]: GETGLOBAL R20 K47      ; R20 := 0xa421af95
205 [-]: LOADK     R21 0        ; R21 := 0.000000
206 [-]: LOADK     R22 1        ; R22 := 1.000000
207 [-]: LOADK     R23 0        ; R23 := 0.000000
208 [-]: CALL      R20 4 0      ; R20,... := R20(R21,R22,R23)
209 [-]: CALL      R16 0 1      ; R16(R17,...)
210 [-]: GETUPVAL  R16 U17      ; R16 := U17
211 [-]: SELF      R16 R16 K34  ; R17 := R16; R16 := R16[0xeb80a36f]
212 [-]: MOVE      R18 R15      ; R18 := R15
213 [-]: CALL      R16 3 1      ; R16(R17,R18)
214 [-]: GETUPVAL  R16 U17      ; R16 := U17
215 [-]: SELF      R16 R16 K35  ; R17 := R16; R16 := R16[0xb52a11ec]
216 [-]: LOADK     R18 30       ; R18 := 30.000000
217 [-]: CALL      R16 3 1      ; R16(R17,R18)
218 [-]: GETGLOBAL R16 K0       ; R16 := 0x89326c93
219 [-]: SELF      R16 R16 K48  ; R17 := R16; R16 := R16[0xc7fcada9]
220 [-]: GETGLOBAL R18 K20      ; R18 := 0x0469f296
221 [-]: LOADK     R19 K49      ; R19 := "SurvivorsDefenseVolume"
222 [-]: CALL      R18 2 0      ; R18,... := R18(R19)
223 [-]: CALL      R16 0 2      ; R16 := R16(R17,...)
224 [-]: SETUPVAL  R16 U24      ; U82 := R24
225 [-]: JMP       233          ; PC := 233
226 [-]: GETGLOBAL R16 K0       ; R16 := 0x89326c93
227 [-]: SELF      R16 R16 K50  ; R17 := R16; R16 := R16[0x05909209]
228 [-]: GETGLOBAL R18 K51      ; R18 := 0xa659e774
229 [-]: GETUPVAL  R19 U3       ; R19 := U3
230 [-]: GETGLOBAL R20 K52      ; R20 := ZERO_ROTATION
231 [-]: CALL      R16 5 2      ; R16 := R16(R17,R18,R19,R20)
232 [-]: SETUPVAL  R16 U24      ; U82 := R24
233 [-]: GETGLOBAL R16 K53      ; R16 := 0xbe190284
234 [-]: SELF      R16 R16 K54  ; R17 := R16; R16 := R16[0x0eb34c69]
235 [-]: GETUPVAL  R18 U13      ; R18 := U13
236 [-]: LOADK     R19 0        ; R19 := 0.000000
237 [-]: CALL      R16 4 2      ; R16 := R16(R17,R18,R19)
238 [-]: SETUPVAL  R16 U25      ; U82 := R25
239 [-]: GETGLOBAL R16 K53      ; R16 := 0xbe190284
240 [-]: SELF      R16 R16 K54  ; R17 := R16; R16 := R16[0x0eb34c69]
241 [-]: GETUPVAL  R18 U14      ; R18 := U14
242 [-]: LOADK     R19 0        ; R19 := 0.000000
243 [-]: CALL      R16 4 2      ; R16 := R16(R17,R18,R19)
244 [-]: SETUPVAL  R16 U26      ; U82 := R26
245 [-]: GETGLOBAL R16 K53      ; R16 := 0xbe190284
246 [-]: SELF      R16 R16 K55  ; R17 := R16; R16 := R16[0xe7ef698d]
247 [-]: LOADK     R18 K56      ; R18 := "OnDeath"
248 [-]: CALL      R16 3 1      ; R16(R17,R18)
249 [-]: GETUPVAL  R16 U27      ; R16 := U27
250 [-]: GETTABLE  R16 R16 K57  ; R16 := R16[0xa1df01d6]
251 [-]: GETUPVAL  R17 U28      ; R17 := U28
252 [-]: CALL      R16 2 1      ; R16(R17)
253 [-]: GETUPVAL  R16 U27      ; R16 := U27
254 [-]: GETTABLE  R16 R16 K58  ; R16 := R16[0xa8fbea61]
255 [-]: GETUPVAL  R17 U29      ; R17 := U29
256 [-]: CALL      R16 2 1      ; R16(R17)
257 [-]: GETUPVAL  R16 U1       ; R16 := U1
258 [-]: SELF      R16 R16 K59  ; R17 := R16; R16 := R16[0xabe61691]
259 [-]: CALL      R16 2 2      ; R16 := R16(R17)
260 [-]: GETUPVAL  R17 U10      ; R17 := U10
261 [-]: SELF      R17 R17 K60  ; R18 := R17; R17 := R17[0x8abff40e]
262 [-]: GETUPVAL  R19 U30      ; R19 := U30
263 [-]: GETTABLE  R19 R19 K61  ; R19 := R19[0x06d055f9]
264 [-]: EQ        1 R16 K62    ; if R16 == 0.000000 then PC := 267
265 [-]: JMP       267          ; PC := 267
266 [-]: LOADBOOL  R20 0 1      ; R20 := false; PC := 267
267 [-]: LOADBOOL  R20 1 0      ; R20 := true
268 [-]: GETUPVAL  R21 U23      ; R21 := U23
269 [-]: MOVE      R22 R16      ; R22 := R16
270 [-]: CALL      R19 4 0      ; R19,... := R19(R20,R21,R22)
271 [-]: CALL      R17 0 1      ; R17(R18,...)
272 [-]: SELF      R17 R0 K63   ; R18 := R0; R17 := R0[0xfe9dc265]
273 [-]: LOADK     R19 2        ; R19 := 2.000000
274 [-]: CALL      R17 3 1      ; R17(R18,R19)
275 [-]: SELF      R17 R0 K65   ; R18 := R0; R17 := R0[0x8b28a480]
276 [-]: CALL      R17 2 1      ; R17(R18)
277 [-]: RETURN    R0 1         ; return 


; Function #9:
;
; Name:            
; Defined at line: 262
; #Upvalues:       25
; #Parameters:     1
; Is_vararg:       0
; Max Stack Size:  16

  1 [-]: GETUPVAL  R1 U0        ; R1 := U0
  2 [-]: MOVE      R2 R0        ; R2 := R0
  3 [-]: CALL      R1 2 1       ; R1(R2)
  4 [-]: LOADK     R1 0         ; R1 := 0.000000
  5 [-]: GETUPVAL  R2 U1        ; R2 := U1
  6 [-]: SELF      R3 R0 K0     ; R4 := R0; R3 := R0[0xefe6cad1]
  7 [-]: CALL      R3 2 2       ; R3 := R3(R4)
  8 [-]: LT        0 R3 K2      ; if R3 >= 4.000000 then PC := 191
  9 [-]: JMP       191          ; PC := 191
 10 [-]: GETGLOBAL R3 K3        ; R3 := 0x67652851
 11 [-]: CALL      R3 1 2       ; R3 := R3()
 12 [-]: MOVE      R1 R3        ; R1 := R3
 13 [-]: GETUPVAL  R3 U2        ; R3 := U2
 14 [-]: SELF      R3 R3 K4     ; R4 := R3; R3 := R3[0x209398c2]
 15 [-]: CALL      R3 2 2       ; R3 := R3(R4)
 16 [-]: MOVE      R2 R3        ; R2 := R3
 17 [-]: GETUPVAL  R3 U3        ; R3 := U3
 18 [-]: EQ        0 R2 R3      ; if R2 ~= R3 then PC := 162
 19 [-]: JMP       162          ; PC := 162
 20 [-]: GETUPVAL  R3 U4        ; R3 := U4
 21 [-]: SELF      R3 R3 K5     ; R4 := R3; R3 := R3[0x39e33d94]
 22 [-]: CALL      R3 2 2       ; R3 := R3(R4)
 23 [-]: EQ        0 R3 K6      ; if R3 ~= 0.000000 then PC := 71
 24 [-]: JMP       71           ; PC := 71
 25 [-]: GETUPVAL  R4 U6        ; R4 := U6
 26 [-]: GETGLOBAL R5 K7        ; R5 := 0x93b9146a
 27 [-]: GETUPVAL  R6 U7        ; R6 := U7
 28 [-]: SELF      R6 R6 K8     ; R7 := R6; R6 := R6[0xc1088746]
 29 [-]: GETUPVAL  R8 U8        ; R8 := U8
 30 [-]: CALL      R6 3 2       ; R6 := R6(R7,R8)
 31 [-]: GETGLOBAL R7 K9        ; R7 := 0x7e3ded28
 32 [-]: MUL       R6 R6 R7     ; R6 := R6 * R7
 33 [-]: CALL      R4 3 2       ; R4 := R4(R5,R6)
 34 [-]: SETUPVAL  R4 U5        ; U82 := R5
 35 [-]: GETGLOBAL R4 K10       ; R4 := 0x7b998233
 36 [-]: GETUPVAL  R5 U5        ; R5 := U5
 37 [-]: CALL      R4 2 2       ; R4 := R4(R5)
 38 [-]: TEST      R4 1         ; if R4 then PC := 108
 39 [-]: JMP       108          ; PC := 108
 40 [-]: GETUPVAL  R4 U5        ; R4 := U5
 41 [-]: SELF      R4 R4 K11    ; R5 := R4; R4 := R4[0xbb610e5b]
 42 [-]: CALL      R4 2 2       ; R4 := R4(R5)
 43 [-]: SELF      R5 R4 K12    ; R6 := R4; R5 := R4[0x47901f07]
 44 [-]: GETGLOBAL R7 K13       ; R7 := 0xbb76409b
 45 [-]: GETGLOBAL R8 K14       ; R8 := EMPTY_SYMBOL
 46 [-]: GETGLOBAL R9 K15       ; R9 := 0xa421af95
 47 [-]: LOADK     R10 0        ; R10 := 0.000000
 48 [-]: LOADK     R11 1        ; R11 := 1.000000
 49 [-]: LOADK     R12 0        ; R12 := 0.000000
 50 [-]: CALL      R9 4 0       ; R9,... := R9(R10,R11,R12)
 51 [-]: CALL      R5 0 1       ; R5(R6,...)
 52 [-]: GETUPVAL  R5 U9        ; R5 := U9
 53 [-]: SELF      R5 R5 K16    ; R6 := R5; R5 := R5[0xeb80a36f]
 54 [-]: MOVE      R7 R4        ; R7 := R4
 55 [-]: CALL      R5 3 1       ; R5(R6,R7)
 56 [-]: GETUPVAL  R5 U9        ; R5 := U9
 57 [-]: SELF      R5 R5 K17    ; R6 := R5; R5 := R5[0xb52a11ec]
 58 [-]: LOADK     R7 30        ; R7 := 30.000000
 59 [-]: CALL      R5 3 1       ; R5(R6,R7)
 60 [-]: GETGLOBAL R5 K10       ; R5 := 0x7b998233
 61 [-]: MOVE      R6 R4        ; R6 := R4
 62 [-]: CALL      R5 2 2       ; R5 := R5(R6)
 63 [-]: TEST      R5 1         ; if R5 then PC := 108
 64 [-]: JMP       108          ; PC := 108
 65 [-]: GETGLOBAL R5 K18       ; R5 := 0x33bdd652
 66 [-]: GETTABLE  R5 R5 K19    ; R5 := R5[0x23d5322f]
 67 [-]: GETUPVAL  R6 U10       ; R6 := U10
 68 [-]: MOVE      R7 R4        ; R7 := R4
 69 [-]: CALL      R5 3 1       ; R5(R6,R7)
 70 [-]: JMP       108          ; PC := 108
 71 [-]: GETGLOBAL R5 K20       ; R5 := 0xb96b249e
 72 [-]: LEN       R5 R5        ; R5 := # R5
 73 [-]: ADD       R5 R5 K21    ; R5 := R5 + 1.000000
 74 [-]: LT        0 R3 R5      ; if R3 >= R5 then PC := 108
 75 [-]: JMP       108          ; PC := 108
 76 [-]: GETUPVAL  R5 U6        ; R5 := U6
 77 [-]: GETGLOBAL R6 K20       ; R6 := 0xb96b249e
 78 [-]: GETTABLE  R6 R6 R3     ; R6 := R6[R3]
 79 [-]: GETUPVAL  R7 U7        ; R7 := U7
 80 [-]: SELF      R7 R7 K8     ; R8 := R7; R7 := R7[0xc1088746]
 81 [-]: GETUPVAL  R9 U8        ; R9 := U8
 82 [-]: CALL      R7 3 2       ; R7 := R7(R8,R9)
 83 [-]: GETGLOBAL R8 K22       ; R8 := 0x2e93c8d7
 84 [-]: MUL       R7 R7 R8     ; R7 := R7 * R8
 85 [-]: CALL      R5 3 2       ; R5 := R5(R6,R7)
 86 [-]: GETGLOBAL R6 K10       ; R6 := 0x7b998233
 87 [-]: MOVE      R7 R5        ; R7 := R5
 88 [-]: CALL      R6 2 2       ; R6 := R6(R7)
 89 [-]: TEST      R6 1         ; if R6 then PC := 108
 90 [-]: JMP       108          ; PC := 108
 91 [-]: GETGLOBAL R6 K18       ; R6 := 0x33bdd652
 92 [-]: GETTABLE  R6 R6 K19    ; R6 := R6[0x23d5322f]
 93 [-]: GETUPVAL  R7 U11       ; R7 := U11
 94 [-]: MOVE      R8 R5        ; R8 := R5
 95 [-]: CALL      R6 3 1       ; R6(R7,R8)
 96 [-]: GETGLOBAL R6 K10       ; R6 := 0x7b998233
 97 [-]: SELF      R7 R5 K11    ; R8 := R5; R7 := R5[0xbb610e5b]
 98 [-]: CALL      R7 2 0       ; R7,... := R7(R8)
 99 [-]: CALL      R6 0 2       ; R6 := R6(R7,...)
100 [-]: TEST      R6 1         ; if R6 then PC := 108
101 [-]: JMP       108          ; PC := 108
102 [-]: GETGLOBAL R6 K18       ; R6 := 0x33bdd652
103 [-]: GETTABLE  R6 R6 K19    ; R6 := R6[0x23d5322f]
104 [-]: GETUPVAL  R7 U10       ; R7 := U10
105 [-]: SELF      R8 R5 K11    ; R9 := R5; R8 := R5[0xbb610e5b]
106 [-]: CALL      R8 2 0       ; R8,... := R8(R9)
107 [-]: CALL      R6 0 1       ; R6(R7,...)
108 [-]: LOADNIL   R6 R7        ; R6 := R7 := nil
109 [-]: GETGLOBAL R8 K10       ; R8 := 0x7b998233
110 [-]: GETUPVAL  R9 U5        ; R9 := U5
111 [-]: CALL      R8 2 2       ; R8 := R8(R9)
112 [-]: TEST      R8 1         ; if R8 then PC := 130
113 [-]: JMP       130          ; PC := 130
114 [-]: GETUPVAL  R8 U5        ; R8 := U5
115 [-]: SELF      R8 R8 K11    ; R9 := R8; R8 := R8[0xbb610e5b]
116 [-]: CALL      R8 2 2       ; R8 := R8(R9)
117 [-]: MOVE      R7 R8        ; R7 := R8
118 [-]: GETGLOBAL R8 K10       ; R8 := 0x7b998233
119 [-]: MOVE      R9 R7        ; R9 := R7
120 [-]: CALL      R8 2 2       ; R8 := R8(R9)
121 [-]: TEST      R8 1         ; if R8 then PC := 130
122 [-]: JMP       130          ; PC := 130
123 [-]: GETGLOBAL R8 K23       ; R8 := 0x89326c93
124 [-]: SELF      R8 R8 K24    ; R9 := R8; R8 := R8[0x50a314f9]
125 [-]: SELF      R10 R7 K25   ; R11 := R7; R10 := R7[0xd1586535]
126 [-]: CALL      R10 2 2      ; R10 := R10(R11)
127 [-]: GETUPVAL  R11 U12      ; R11 := U12
128 [-]: CALL      R8 4 2       ; R8 := R8(R9,R10,R11)
129 [-]: MOVE      R6 R8        ; R6 := R8
130 [-]: GETGLOBAL R8 K10       ; R8 := 0x7b998233
131 [-]: MOVE      R9 R6        ; R9 := R6
132 [-]: CALL      R8 2 2       ; R8 := R8(R9)
133 [-]: TEST      R8 1         ; if R8 then PC := 173
134 [-]: JMP       173          ; PC := 173
135 [-]: GETGLOBAL R8 K10       ; R8 := 0x7b998233
136 [-]: MOVE      R9 R7        ; R9 := R7
137 [-]: CALL      R8 2 2       ; R8 := R8(R9)
138 [-]: TEST      R8 1         ; if R8 then PC := 173
139 [-]: JMP       173          ; PC := 173
140 [-]: SELF      R8 R7 K26    ; R9 := R7; R8 := R7[0xc9f6a7d7]
141 [-]: GETGLOBAL R10 K27      ; R10 := gBaseMarkerInfoType
142 [-]: CALL      R8 3 2       ; R8 := R8(R9,R10)
143 [-]: GETGLOBAL R9 K10       ; R9 := 0x7b998233
144 [-]: MOVE      R10 R8       ; R10 := R8
145 [-]: CALL      R9 2 2       ; R9 := R9(R10)
146 [-]: TEST      R9 1         ; if R9 then PC := 150
147 [-]: JMP       150          ; PC := 150
148 [-]: SELF      R9 R8 K28    ; R10 := R8; R9 := R8[0xa2880940]
149 [-]: CALL      R9 2 1       ; R9(R10)
150 [-]: GETUPVAL  R9 U13       ; R9 := U13
151 [-]: GETTABLE  R9 R9 K29    ; R9 := R9[0x9742b85b]
152 [-]: GETUPVAL  R10 U14      ; R10 := U14
153 [-]: GETGLOBAL R11 K30      ; R11 := 0x0469f296
154 [-]: LOADK     R12 K31      ; R12 := "SpeakToLeader"
155 [-]: CALL      R11 2 0      ; R11,... := R11(R12)
156 [-]: CALL      R9 0 1       ; R9(R10,...)
157 [-]: GETUPVAL  R9 U2        ; R9 := U2
158 [-]: SELF      R9 R9 K32    ; R10 := R9; R9 := R9[0x8abff40e]
159 [-]: GETUPVAL  R11 U15      ; R11 := U15
160 [-]: CALL      R9 3 1       ; R9(R10,R11)
161 [-]: JMP       173          ; PC := 173
162 [-]: GETUPVAL  R9 U16       ; R9 := U16
163 [-]: EQ        0 R2 R9      ; if R2 ~= R9 then PC := 170
164 [-]: JMP       170          ; PC := 170
165 [-]: GETUPVAL  R9 U9        ; R9 := U9
166 [-]: SELF      R9 R9 K33    ; R10 := R9; R9 := R9[0xfaa69527]
167 [-]: MOVE      R11 R1       ; R11 := R1
168 [-]: CALL      R9 3 1       ; R9(R10,R11)
169 [-]: JMP       173          ; PC := 173
170 [-]: GETUPVAL  R9 U17       ; R9 := U17
171 [-]: EQ        0 R2 R9      ; if R2 ~= R9 then PC := 173
172 [-]: JMP       173          ; PC := 173
173 [-]: GETUPVAL  R9 U18       ; R9 := U18
174 [-]: SELF      R9 R9 K33    ; R10 := R9; R9 := R9[0xfaa69527]
175 [-]: MOVE      R11 R1       ; R11 := R1
176 [-]: CALL      R9 3 1       ; R9(R10,R11)
177 [-]: SELF      R9 R0 K34    ; R10 := R0; R9 := R0[0xd9531187]
178 [-]: CALL      R9 2 2       ; R9 := R9(R10)
179 [-]: TEST      R9 0         ; if not R9 then PC := 187
180 [-]: JMP       187          ; PC := 187
181 [-]: GETUPVAL  R9 U19       ; R9 := U19
182 [-]: GETTABLE  R9 R9 K35    ; R9 := R9[0xd712b9db]
183 [-]: CALL      R9 1 1       ; R9()
184 [-]: SELF      R9 R0 K36    ; R10 := R0; R9 := R0[0xfe9dc265]
185 [-]: LOADK     R11 5        ; R11 := 5.000000
186 [-]: CALL      R9 3 1       ; R9(R10,R11)
187 [-]: GETGLOBAL R9 K37       ; R9 := 0xcbd666e1
188 [-]: LOADK     R10 0        ; R10 := 0.000000
189 [-]: CALL      R9 2 1       ; R9(R10)
190 [-]: JMP       6            ; PC := 6
191 [-]: GETUPVAL  R9 U4        ; R9 := U4
192 [-]: SELF      R9 R9 K38    ; R10 := R9; R9 := R9[0x3d412e0d]
193 [-]: GETUPVAL  R11 U20      ; R11 := U20
194 [-]: CALL      R9 3 1       ; R9(R10,R11)
195 [-]: GETUPVAL  R9 U4        ; R9 := U4
196 [-]: SELF      R9 R9 K39    ; R10 := R9; R9 := R9[0x136a027d]
197 [-]: GETUPVAL  R11 U21      ; R11 := U21
198 [-]: CALL      R9 3 1       ; R9(R10,R11)
199 [-]: GETUPVAL  R9 U22       ; R9 := U22
200 [-]: GETTABLE  R9 R9 K40    ; R9 := R9[0xf7ebddc8]
201 [-]: CALL      R9 1 1       ; R9()
202 [-]: GETUPVAL  R9 U22       ; R9 := U22
203 [-]: GETTABLE  R9 R9 K41    ; R9 := R9[0xdc3b2033]
204 [-]: CALL      R9 1 1       ; R9()
205 [-]: GETGLOBAL R9 K42       ; R9 := _T
206 [-]: GETTABLE  R9 R9 K43    ; R9 := R9[0x1a41a3c1]
207 [-]: GETUPVAL  R10 U23      ; R10 := U23
208 [-]: CALL      R9 2 1       ; R9(R10)
209 [-]: GETGLOBAL R9 K44       ; R9 := 0xbe190284
210 [-]: SELF      R9 R9 K45    ; R10 := R9; R9 := R9[0xbd710f80]
211 [-]: LOADK     R11 K46      ; R11 := "OnDeath"
212 [-]: CALL      R9 3 1       ; R9(R10,R11)
213 [-]: GETUPVAL  R9 U22       ; R9 := U22
214 [-]: GETTABLE  R9 R9 K47    ; R9 := R9[0xedf59000]
215 [-]: CALL      R9 1 1       ; R9()
216 [-]: GETGLOBAL R9 K10       ; R9 := 0x7b998233
217 [-]: GETUPVAL  R10 U5       ; R10 := U5
218 [-]: CALL      R9 2 2       ; R9 := R9(R10)
219 [-]: TEST      R9 1         ; if R9 then PC := 254
220 [-]: JMP       254          ; PC := 254
221 [-]: GETUPVAL  R9 U24       ; R9 := U24
222 [-]: CALL      R9 1 1       ; R9()
223 [-]: LOADK     R9 3         ; R9 := 3.000000
224 [-]: LT        0 K6 R9      ; if 0.000000 >= R9 then PC := 238
225 [-]: JMP       238          ; PC := 238
226 [-]: GETGLOBAL R10 K37      ; R10 := 0xcbd666e1
227 [-]: LOADK     R11 0        ; R11 := 0.000000
228 [-]: CALL      R10 2 1      ; R10(R11)
229 [-]: GETGLOBAL R10 K3       ; R10 := 0x67652851
230 [-]: CALL      R10 1 2      ; R10 := R10()
231 [-]: SUB       R9 R9 R10    ; R9 := R9 - R10
232 [-]: GETUPVAL  R10 U18      ; R10 := U18
233 [-]: SELF      R10 R10 K33  ; R11 := R10; R10 := R10[0xfaa69527]
234 [-]: GETGLOBAL R12 K3       ; R12 := 0x67652851
235 [-]: CALL      R12 1 0      ; R12,... := R12()
236 [-]: CALL      R10 0 1      ; R10(R11,...)
237 [-]: JMP       224          ; PC := 224
238 [-]: LOADK     R10 1        ; R10 := 1.000000
239 [-]: GETUPVAL  R11 U10      ; R11 := U10
240 [-]: LEN       R11 R11      ; R11 := # R11
241 [-]: LOADK     R12 1        ; R12 := 1.000000
242 [-]: FORPREP   R10 253      ; R10 -= R12; PC := 253
243 [-]: GETGLOBAL R14 K10      ; R14 := 0x7b998233
244 [-]: GETUPVAL  R15 U10      ; R15 := U10
245 [-]: GETTABLE  R15 R15 R13  ; R15 := R15[R13]
246 [-]: CALL      R14 2 2      ; R14 := R14(R15)
247 [-]: TEST      R14 1        ; if R14 then PC := 253
248 [-]: JMP       253          ; PC := 253
249 [-]: GETUPVAL  R14 U10      ; R14 := U10
250 [-]: GETTABLE  R14 R14 R13  ; R14 := R14[R13]
251 [-]: SELF      R14 R14 K28  ; R15 := R14; R14 := R14[0xa2880940]
252 [-]: CALL      R14 2 1      ; R14(R15)
253 [-]: FORLOOP   R10 243      ; R10 += R12; if R10 <= R11 then begin PC := 243; R13 := R10 end
254 [-]: GETUPVAL  R14 U2       ; R14 := U2
255 [-]: SELF      R14 R14 K48  ; R15 := R14; R14 := R14[0x588ed000]
256 [-]: CALL      R14 2 1      ; R14(R15)
257 [-]: RETURN    R0 1         ; return 


; Function #10:
;
; Name:            
; Defined at line: 361
; #Upvalues:       1
; #Parameters:     0
; Is_vararg:       0
; Max Stack Size:  2

  1 [-]: GETGLOBAL R0 K0        ; R0 := 0x89326c93
  2 [-]: SELF      R0 R0 K1     ; R1 := R0; R0 := R0[0x7d108ddb]
  3 [-]: CALL      R0 2 2       ; R0 := R0(R1)
  4 [-]: SETUPVAL  R0 U0        ; U82 := R0
  5 [-]: RETURN    R0 1         ; return 


; Function #11:
;
; Name:            
; Defined at line: 365
; #Upvalues:       2
; #Parameters:     0
; Is_vararg:       0
; Max Stack Size:  3

  1 [-]: GETUPVAL  R0 U0        ; R0 := U0
  2 [-]: GETTABLE  R0 R0 K0     ; R0 := R0[0x7e8a976a]
  3 [-]: GETUPVAL  R1 U1        ; R1 := U1
  4 [-]: LOADBOOL  R2 1 0       ; R2 := true
  5 [-]: CALL      R0 3 1       ; R0(R1,R2)
  6 [-]: RETURN    R0 1         ; return 


; Function #12:
;
; Name:            
; Defined at line: 369
; #Upvalues:       2
; #Parameters:     0
; Is_vararg:       0
; Max Stack Size:  3

  1 [-]: GETUPVAL  R0 U0        ; R0 := U0
  2 [-]: GETTABLE  R0 R0 K0     ; R0 := R0[0x7e8a976a]
  3 [-]: GETUPVAL  R1 U1        ; R1 := U1
  4 [-]: LOADBOOL  R2 0 0       ; R2 := false
  5 [-]: CALL      R0 3 1       ; R0(R1,R2)
  6 [-]: RETURN    R0 1         ; return 


; Function #13:
;
; Name:            
; Defined at line: 373
; #Upvalues:       4
; #Parameters:     1
; Is_vararg:       0
; Max Stack Size:  5

  1 [-]: SELF      R1 R0 K0     ; R2 := R0; R1 := R0[0xbb610e5b]
  2 [-]: CALL      R1 2 2       ; R1 := R1(R2)
  3 [-]: SELF      R2 R1 K1     ; R3 := R1; R2 := R1[0xf2deaf69]
  4 [-]: GETUPVAL  R4 U0        ; R4 := U0
  5 [-]: CALL      R2 3 2       ; R2 := R2(R3,R4)
  6 [-]: TEST      R2 1         ; if R2 then PC := 13
  7 [-]: JMP       13           ; PC := 13
  8 [-]: SELF      R2 R1 K1     ; R3 := R1; R2 := R1[0xf2deaf69]
  9 [-]: GETUPVAL  R4 U1        ; R4 := U1
 10 [-]: CALL      R2 3 2       ; R2 := R2(R3,R4)
 11 [-]: TEST      R2 0         ; if not R2 then PC := 14
 12 [-]: JMP       14           ; PC := 14
 13 [-]: RETURN    R0 1         ; return 
 14 [-]: SELF      R2 R1 K2     ; R3 := R1; R2 := R1[0x808b79e6]
 15 [-]: CALL      R2 2 2       ; R2 := R2(R3)
 16 [-]: GETUPVAL  R3 U2        ; R3 := U2
 17 [-]: EQ        0 R2 R3      ; if R2 ~= R3 then PC := 22
 18 [-]: JMP       22           ; PC := 22
 19 [-]: SELF      R2 R1 K3     ; R3 := R1; R2 := R1[0xefa4e034]
 20 [-]: GETUPVAL  R4 U3        ; R4 := U3
 21 [-]: CALL      R2 3 1       ; R2(R3,R4)
 22 [-]: RETURN    R0 1         ; return 


; Function #14:
;
; Name:            
; Defined at line: 384
; #Upvalues:       25
; #Parameters:     1
; Is_vararg:       0
; Max Stack Size:  22

  1 [-]: GETUPVAL  R1 U0        ; R1 := U0
  2 [-]: SELF      R1 R1 K0     ; R2 := R1; R1 := R1[0xefe6cad1]
  3 [-]: CALL      R1 2 2       ; R1 := R1(R2)
  4 [-]: LE        1 K2 R1      ; if 4.000000 <= R1 then PC := 12
  5 [-]: JMP       12           ; PC := 12
  6 [-]: GETUPVAL  R1 U1        ; R1 := U1
  7 [-]: SELF      R1 R1 K3     ; R2 := R1; R1 := R1[0x209398c2]
  8 [-]: CALL      R1 2 2       ; R1 := R1(R2)
  9 [-]: GETUPVAL  R2 U2        ; R2 := U2
 10 [-]: LT        0 R1 R2      ; if R1 >= R2 then PC := 13
 11 [-]: JMP       13           ; PC := 13
 12 [-]: RETURN    R0 1         ; return 
 13 [-]: SELF      R1 R0 K4     ; R2 := R0; R1 := R0[0x01145f7a]
 14 [-]: CALL      R1 2 2       ; R1 := R1(R2)
 15 [-]: SELF      R2 R1 K5     ; R3 := R1; R2 := R1[0xfa9e477f]
 16 [-]: CALL      R2 2 2       ; R2 := R2(R3)
 17 [-]: GETGLOBAL R3 K6        ; R3 := 0x7b998233
 18 [-]: MOVE      R4 R2        ; R4 := R2
 19 [-]: CALL      R3 2 2       ; R3 := R3(R4)
 20 [-]: TEST      R3 0         ; if not R3 then PC := 23
 21 [-]: JMP       23           ; PC := 23
 22 [-]: RETURN    R0 1         ; return 
 23 [-]: SELF      R3 R2 K7     ; R4 := R2; R3 := R2[0x96a5dceb]
 24 [-]: CALL      R3 2 2       ; R3 := R3(R4)
 25 [-]: GETGLOBAL R4 K6        ; R4 := 0x7b998233
 26 [-]: MOVE      R5 R3        ; R5 := R3
 27 [-]: CALL      R4 2 2       ; R4 := R4(R5)
 28 [-]: TEST      R4 1         ; if R4 then PC := 33
 29 [-]: JMP       33           ; PC := 33
 30 [-]: SELF      R4 R3 K8     ; R5 := R3; R4 := R3[0x891629fa]
 31 [-]: CALL      R4 2 2       ; R4 := R4(R5)
 32 [-]: MOVE      R3 R4        ; R3 := R4
 33 [-]: SELF      R4 R1 K9     ; R5 := R1; R4 := R1[0x808b79e6]
 34 [-]: CALL      R4 2 2       ; R4 := R4(R5)
 35 [-]: GETUPVAL  R5 U3        ; R5 := U3
 36 [-]: EQ        0 R4 R5      ; if R4 ~= R5 then PC := 66
 37 [-]: JMP       66           ; PC := 66
 38 [-]: GETGLOBAL R4 K6        ; R4 := 0x7b998233
 39 [-]: MOVE      R5 R2        ; R5 := R2
 40 [-]: CALL      R4 2 2       ; R4 := R4(R5)
 41 [-]: TEST      R4 1         ; if R4 then PC := 66
 42 [-]: JMP       66           ; PC := 66
 43 [-]: GETUPVAL  R4 U4        ; R4 := U4
 44 [-]: EQ        0 R2 R4      ; if R2 ~= R4 then PC := 51
 45 [-]: JMP       51           ; PC := 51
 46 [-]: GETUPVAL  R4 U0        ; R4 := U0
 47 [-]: SELF      R4 R4 K10    ; R5 := R4; R4 := R4[0xfe9dc265]
 48 [-]: LOADK     R6 5         ; R6 := 5.000000
 49 [-]: CALL      R4 3 1       ; R4(R5,R6)
 50 [-]: JMP       302          ; PC := 302
 51 [-]: GETGLOBAL R4 K11       ; R4 := 0xc8802016
 52 [-]: GETUPVAL  R5 U5        ; R5 := U5
 53 [-]: CALL      R4 2 4       ; R4,R5,R6 := R4(R5)
 54 [-]: JMP       63           ; PC := 63
 55 [-]: EQ        0 R2 R8      ; if R2 ~= R8 then PC := 63
 56 [-]: JMP       63           ; PC := 63
 57 [-]: GETGLOBAL R9 K12       ; R9 := 0x33bdd652
 58 [-]: GETTABLE  R9 R9 K13    ; R9 := R9[0x9c1f3b5a]
 59 [-]: GETUPVAL  R10 U5       ; R10 := U5
 60 [-]: MOVE      R11 R7       ; R11 := R7
 61 [-]: CALL      R9 3 1       ; R9(R10,R11)
 62 [-]: JMP       302          ; PC := 302
 63 [-]: TFORLOOP  R4 2         ; R7,R8 :=  R4(R5,R6); if R7 ~= nil then begin PC = 55; R6 := R7 end
 64 [-]: JMP       55           ; PC := 55
 65 [-]: JMP       302          ; PC := 302
 66 [-]: GETGLOBAL R9 K6        ; R9 := 0x7b998233
 67 [-]: MOVE      R10 R2       ; R10 := R2
 68 [-]: CALL      R9 2 2       ; R9 := R9(R10)
 69 [-]: TEST      R9 1         ; if R9 then PC := 275
 70 [-]: JMP       275          ; PC := 275
 71 [-]: GETUPVAL  R9 U6        ; R9 := U6
 72 [-]: EQ        0 R3 R9      ; if R3 ~= R9 then PC := 275
 73 [-]: JMP       275          ; PC := 275
 74 [-]: GETUPVAL  R9 U1        ; R9 := U1
 75 [-]: SELF      R9 R9 K3     ; R10 := R9; R9 := R9[0x209398c2]
 76 [-]: CALL      R9 2 2       ; R9 := R9(R10)
 77 [-]: GETUPVAL  R10 U7       ; R10 := U7
 78 [-]: EQ        1 R9 R10     ; if R9 == R10 then PC := 81
 79 [-]: JMP       81           ; PC := 81
 80 [-]: RETURN    R0 1         ; return 
 81 [-]: SELF      R9 R0 K14    ; R10 := R0; R9 := R0[0x52de0ed7]
 82 [-]: CALL      R9 2 2       ; R9 := R9(R10)
 83 [-]: GETGLOBAL R10 K6       ; R10 := 0x7b998233
 84 [-]: MOVE      R11 R9       ; R11 := R9
 85 [-]: CALL      R10 2 2      ; R10 := R10(R11)
 86 [-]: TEST      R10 1        ; if R10 then PC := 302
 87 [-]: JMP       302          ; PC := 302
 88 [-]: SELF      R10 R9 K15   ; R11 := R9; R10 := R9[0xf2deaf69]
 89 [-]: GETGLOBAL R12 K16      ; R12 := gBaseAvatarType
 90 [-]: CALL      R10 3 2      ; R10 := R10(R11,R12)
 91 [-]: TEST      R10 0        ; if not R10 then PC := 302
 92 [-]: JMP       302          ; PC := 302
 93 [-]: LOADBOOL  R10 0 0      ; R10 := false
 94 [-]: GETGLOBAL R11 K11      ; R11 := 0xc8802016
 95 [-]: GETUPVAL  R12 U8       ; R12 := U8
 96 [-]: CALL      R11 2 4      ; R11,R12,R13 := R11(R12)
 97 [-]: JMP       102          ; PC := 102
 98 [-]: EQ        0 R9 R15     ; if R9 ~= R15 then PC := 102
 99 [-]: JMP       102          ; PC := 102
100 [-]: LOADBOOL  R10 1 0      ; R10 := true
101 [-]: JMP       104          ; PC := 104
102 [-]: TFORLOOP  R11 2        ; R14,R15 :=  R11(R12,R13); if R14 ~= nil then begin PC = 98; R13 := R14 end
103 [-]: JMP       98           ; PC := 98
104 [-]: TEST      R10 0        ; if not R10 then PC := 154
105 [-]: JMP       154          ; PC := 154
106 [-]: GETGLOBAL R16 K17      ; R16 := 0xbe190284
107 [-]: SELF      R16 R16 K18  ; R17 := R16; R16 := R16[0x0eb34c69]
108 [-]: GETUPVAL  R18 U9       ; R18 := U9
109 [-]: CALL      R16 3 2      ; R16 := R16(R17,R18)
110 [-]: LT        0 R16 K19    ; if R16 >= 1.000000 then PC := 128
111 [-]: JMP       128          ; PC := 128
112 [-]: GETUPVAL  R16 U10      ; R16 := U10
113 [-]: GETUPVAL  R17 U11      ; R17 := U11
114 [-]: EQ        0 R16 R17    ; if R16 ~= R17 then PC := 128
115 [-]: JMP       128          ; PC := 128
116 [-]: GETUPVAL  R16 U12      ; R16 := U12
117 [-]: GETTABLE  R16 R16 K20  ; R16 := R16[0x9742b85b]
118 [-]: GETUPVAL  R17 U13      ; R17 := U13
119 [-]: GETGLOBAL R18 K21      ; R18 := 0x0469f296
120 [-]: LOADK     R19 K22      ; R19 := "GrineerOvertake"
121 [-]: CALL      R18 2 0      ; R18,... := R18(R19)
122 [-]: CALL      R16 0 1      ; R16(R17,...)
123 [-]: GETGLOBAL R16 K17      ; R16 := 0xbe190284
124 [-]: SELF      R16 R16 K23  ; R17 := R16; R16 := R16[0x751f061d]
125 [-]: GETUPVAL  R18 U9       ; R18 := U9
126 [-]: LOADK     R19 1        ; R19 := 1.000000
127 [-]: CALL      R16 4 1      ; R16(R17,R18,R19)
128 [-]: LOADBOOL  R16 0 0      ; R16 := false
129 [-]: TEST      R16 0        ; if not R16 then PC := 137
130 [-]: JMP       137          ; PC := 137
131 [-]: LOADBOOL  R16 0 0      ; R16 := false
132 [-]: TEST      R16 0        ; if not R16 then PC := 137
133 [-]: JMP       137          ; PC := 137
134 [-]: GETUPVAL  R16 U10      ; R16 := U10
135 [-]: ADD       R16 R16 K24  ; R16 := R16 + 5.000000
136 [-]: SETUPVAL  R16 U10      ; U82 := R10
137 [-]: GETUPVAL  R16 U10      ; R16 := U10
138 [-]: ADD       R16 R16 K19  ; R16 := R16 + 1.000000
139 [-]: SETUPVAL  R16 U10      ; U82 := R10
140 [-]: GETGLOBAL R16 K17      ; R16 := 0xbe190284
141 [-]: SELF      R16 R16 K23  ; R17 := R16; R16 := R16[0x751f061d]
142 [-]: GETUPVAL  R18 U14      ; R18 := U14
143 [-]: GETUPVAL  R19 U10      ; R19 := U10
144 [-]: CALL      R16 4 1      ; R16(R17,R18,R19)
145 [-]: GETUPVAL  R16 U10      ; R16 := U10
146 [-]: GETUPVAL  R17 U15      ; R17 := U15
147 [-]: LT        0 R17 R16    ; if R17 >= R16 then PC := 193
148 [-]: JMP       193          ; PC := 193
149 [-]: GETUPVAL  R16 U16      ; R16 := U16
150 [-]: GETTABLE  R16 R16 K25  ; R16 := R16[0x37317859]
151 [-]: GETUPVAL  R17 U17      ; R17 := U17
152 [-]: CALL      R16 2 1      ; R16(R17)
153 [-]: JMP       193          ; PC := 193
154 [-]: GETGLOBAL R16 K17      ; R16 := 0xbe190284
155 [-]: SELF      R16 R16 K18  ; R17 := R16; R16 := R16[0x0eb34c69]
156 [-]: GETUPVAL  R18 U18      ; R18 := U18
157 [-]: CALL      R16 3 2      ; R16 := R16(R17,R18)
158 [-]: LT        0 R16 K19    ; if R16 >= 1.000000 then PC := 176
159 [-]: JMP       176          ; PC := 176
160 [-]: GETUPVAL  R16 U11      ; R16 := U11
161 [-]: GETUPVAL  R17 U10      ; R17 := U10
162 [-]: EQ        0 R16 R17    ; if R16 ~= R17 then PC := 176
163 [-]: JMP       176          ; PC := 176
164 [-]: GETUPVAL  R16 U12      ; R16 := U12
165 [-]: GETTABLE  R16 R16 K20  ; R16 := R16[0x9742b85b]
166 [-]: GETUPVAL  R17 U13      ; R17 := U13
167 [-]: GETGLOBAL R18 K21      ; R18 := 0x0469f296
168 [-]: LOADK     R19 K26      ; R19 := "PlayerOvertake"
169 [-]: CALL      R18 2 0      ; R18,... := R18(R19)
170 [-]: CALL      R16 0 1      ; R16(R17,...)
171 [-]: GETGLOBAL R16 K17      ; R16 := 0xbe190284
172 [-]: SELF      R16 R16 K23  ; R17 := R16; R16 := R16[0x751f061d]
173 [-]: GETUPVAL  R18 U18      ; R18 := U18
174 [-]: LOADK     R19 1        ; R19 := 1.000000
175 [-]: CALL      R16 4 1      ; R16(R17,R18,R19)
176 [-]: LOADBOOL  R16 0 0      ; R16 := false
177 [-]: TEST      R16 0        ; if not R16 then PC := 185
178 [-]: JMP       185          ; PC := 185
179 [-]: LOADBOOL  R16 0 0      ; R16 := false
180 [-]: TEST      R16 0        ; if not R16 then PC := 185
181 [-]: JMP       185          ; PC := 185
182 [-]: GETUPVAL  R16 U11      ; R16 := U11
183 [-]: ADD       R16 R16 K27  ; R16 := R16 + 10.000000
184 [-]: SETUPVAL  R16 U11      ; U82 := R11
185 [-]: GETUPVAL  R16 U11      ; R16 := U11
186 [-]: ADD       R16 R16 K19  ; R16 := R16 + 1.000000
187 [-]: SETUPVAL  R16 U11      ; U82 := R11
188 [-]: GETGLOBAL R16 K17      ; R16 := 0xbe190284
189 [-]: SELF      R16 R16 K23  ; R17 := R16; R16 := R16[0x751f061d]
190 [-]: GETUPVAL  R18 U19      ; R18 := U19
191 [-]: GETUPVAL  R19 U11      ; R19 := U11
192 [-]: CALL      R16 4 1      ; R16(R17,R18,R19)
193 [-]: GETUPVAL  R16 U11      ; R16 := U11
194 [-]: GETUPVAL  R17 U20      ; R17 := U20
195 [-]: GETUPVAL  R18 U21      ; R18 := U21
196 [-]: CALL      R18 1 2      ; R18 := R18()
197 [-]: GETTABLE  R17 R17 R18  ; R17 := R17[R18]
198 [-]: LT        0 R16 R17    ; if R16 >= R17 then PC := 209
199 [-]: JMP       209          ; PC := 209
200 [-]: GETUPVAL  R16 U10      ; R16 := U10
201 [-]: GETUPVAL  R17 U22      ; R17 := U22
202 [-]: LE        0 R17 R16    ; if R17 > R16 then PC := 209
203 [-]: JMP       209          ; PC := 209
204 [-]: GETUPVAL  R16 U0       ; R16 := U0
205 [-]: SELF      R16 R16 K10  ; R17 := R16; R16 := R16[0xfe9dc265]
206 [-]: LOADK     R18 5        ; R18 := 5.000000
207 [-]: CALL      R16 3 1      ; R16(R17,R18)
208 [-]: JMP       249          ; PC := 249
209 [-]: GETUPVAL  R16 U11      ; R16 := U11
210 [-]: GETUPVAL  R17 U20      ; R17 := U20
211 [-]: GETUPVAL  R18 U21      ; R18 := U21
212 [-]: CALL      R18 1 2      ; R18 := R18()
213 [-]: GETTABLE  R17 R17 R18  ; R17 := R17[R18]
214 [-]: LE        0 R17 R16    ; if R17 > R16 then PC := 249
215 [-]: JMP       249          ; PC := 249
216 [-]: GETUPVAL  R16 U10      ; R16 := U10
217 [-]: GETUPVAL  R17 U22      ; R17 := U22
218 [-]: LT        0 R16 R17    ; if R16 >= R17 then PC := 249
219 [-]: JMP       249          ; PC := 249
220 [-]: GETUPVAL  R16 U10      ; R16 := U10
221 [-]: GETUPVAL  R17 U15      ; R17 := U15
222 [-]: LE        0 R16 R17    ; if R16 > R17 then PC := 238
223 [-]: JMP       238          ; PC := 238
224 [-]: GETGLOBAL R16 K28      ; R16 := _T
225 [-]: SETTABLE  R16 K29 K30  ; R16["QualifiedForBountyBonus"] := true
226 [-]: GETUPVAL  R16 U16      ; R16 := U16
227 [-]: GETTABLE  R16 R16 K31  ; R16 := R16[0x0a8ecc31]
228 [-]: GETUPVAL  R17 U17      ; R17 := U17
229 [-]: CALL      R16 2 1      ; R16(R17)
230 [-]: GETUPVAL  R16 U12      ; R16 := U12
231 [-]: GETTABLE  R16 R16 K20  ; R16 := R16[0x9742b85b]
232 [-]: GETUPVAL  R17 U13      ; R17 := U13
233 [-]: GETGLOBAL R18 K21      ; R18 := 0x0469f296
234 [-]: LOADK     R19 K32      ; R19 := "CompleteBonus"
235 [-]: CALL      R18 2 0      ; R18,... := R18(R19)
236 [-]: CALL      R16 0 1      ; R16(R17,...)
237 [-]: JMP       245          ; PC := 245
238 [-]: GETUPVAL  R16 U12      ; R16 := U12
239 [-]: GETTABLE  R16 R16 K20  ; R16 := R16[0x9742b85b]
240 [-]: GETUPVAL  R17 U13      ; R17 := U13
241 [-]: GETGLOBAL R18 K21      ; R18 := 0x0469f296
242 [-]: LOADK     R19 K33      ; R19 := "Complete"
243 [-]: CALL      R18 2 0      ; R18,... := R18(R19)
244 [-]: CALL      R16 0 1      ; R16(R17,...)
245 [-]: GETUPVAL  R16 U1       ; R16 := U1
246 [-]: SELF      R16 R16 K34  ; R17 := R16; R16 := R16[0x8abff40e]
247 [-]: GETUPVAL  R18 U23      ; R18 := U23
248 [-]: CALL      R16 3 1      ; R16(R17,R18)
249 [-]: GETGLOBAL R16 K6       ; R16 := 0x7b998233
250 [-]: GETUPVAL  R17 U24      ; R17 := U24
251 [-]: CALL      R16 2 2      ; R16 := R16(R17)
252 [-]: TEST      R16 1        ; if R16 then PC := 302
253 [-]: JMP       302          ; PC := 302
254 [-]: GETUPVAL  R16 U24      ; R16 := U24
255 [-]: GETTABLE  R16 R16 K35  ; R16 := R16[0x6b560078]
256 [-]: GETGLOBAL R17 K36      ; R17 := 0x5bced4c4
257 [-]: GETTABLE  R17 R17 K37  ; R17 := R17[0xac1b386a]
258 [-]: LOADK     R18 1        ; R18 := 1.000000
259 [-]: GETUPVAL  R19 U11      ; R19 := U11
260 [-]: GETUPVAL  R20 U20      ; R20 := U20
261 [-]: GETUPVAL  R21 U21      ; R21 := U21
262 [-]: CALL      R21 1 2      ; R21 := R21()
263 [-]: GETTABLE  R20 R20 R21  ; R20 := R20[R21]
264 [-]: DIV       R19 R19 R20  ; R19 := R19 / R20
265 [-]: CALL      R17 3 2      ; R17 := R17(R18,R19)
266 [-]: GETGLOBAL R18 K36      ; R18 := 0x5bced4c4
267 [-]: GETTABLE  R18 R18 K37  ; R18 := R18[0xac1b386a]
268 [-]: LOADK     R19 1        ; R19 := 1.000000
269 [-]: GETUPVAL  R20 U10      ; R20 := U10
270 [-]: GETUPVAL  R21 U22      ; R21 := U22
271 [-]: DIV       R20 R20 R21  ; R20 := R20 / R21
272 [-]: CALL      R18 3 0      ; R18,... := R18(R19,R20)
273 [-]: CALL      R16 0 1      ; R16(R17,...)
274 [-]: JMP       302          ; PC := 302
275 [-]: GETGLOBAL R16 K6       ; R16 := 0x7b998233
276 [-]: MOVE      R17 R2       ; R17 := R2
277 [-]: CALL      R16 2 2      ; R16 := R16(R17)
278 [-]: TEST      R16 0        ; if not R16 then PC := 284
279 [-]: JMP       284          ; PC := 284
280 [-]: GETGLOBAL R16 K38      ; R16 := 0xd644c2f1
281 [-]: LOADK     R17 K39      ; R17 := "Null agent"
282 [-]: CALL      R16 2 1      ; R16(R17)
283 [-]: JMP       302          ; PC := 302
284 [-]: GETGLOBAL R16 K6       ; R16 := 0x7b998233
285 [-]: MOVE      R17 R3       ; R17 := R3
286 [-]: CALL      R16 2 2      ; R16 := R16(R17)
287 [-]: TEST      R16 0        ; if not R16 then PC := 293
288 [-]: JMP       293          ; PC := 293
289 [-]: GETGLOBAL R16 K38      ; R16 := 0xd644c2f1
290 [-]: LOADK     R17 K40      ; R17 := "Null enc hint"
291 [-]: CALL      R16 2 1      ; R16(R17)
292 [-]: JMP       302          ; PC := 302
293 [-]: GETGLOBAL R16 K38      ; R16 := 0xd644c2f1
294 [-]: SELF      R17 R3 K41   ; R18 := R3; R17 := R3[0xed4e0128]
295 [-]: CALL      R17 2 2      ; R17 := R17(R18)
296 [-]: LOADK     R18 K42      ; R18 := " != "
297 [-]: GETUPVAL  R19 U6       ; R19 := U6
298 [-]: SELF      R19 R19 K41  ; R20 := R19; R19 := R19[0xed4e0128]
299 [-]: CALL      R19 2 2      ; R19 := R19(R20)
300 [-]: CONCAT    R17 R17 R19  ; R17 := R17 .. R18 .. R19
301 [-]: CALL      R16 2 1      ; R16(R17)
302 [-]: RETURN    R0 1         ; return 


