; Name:            
; Defined at line: 1
; #Upvalues:       0
; #Parameters:     0
; Is_vararg:       1
; Max Stack Size:  33

       1 [-]: GETIMPORT R0 1; var0 = 0x2D0FAD09
       2 [-]: LOADK R1 K2  ; var1 = "EE.Interface.Utilities"
       3 [-]: CALL R0 2 2  ; var0 = var0(var1)
       4 [-]: GETIMPORT R1 4; var1 = 0x0469F296
       5 [-]: LOADK R2 K5  ; var2 = "PurifierTrig"
       6 [-]: CALL R1 2 2  ; var1 = var1(var2)
       7 [-]: GETIMPORT R2 7; var2 = 0x7ED0A956
       8 [-]: LOADK R3 K8  ; var3 = "/Lotus/Types/PickUps/RaidInfestedAntidoteItem"
       9 [-]: CALL R2 2 2  ; var2 = var2(var3)
      10 [-]: GETIMPORT R3 7; var3 = 0x7ED0A956
      11 [-]: LOADK R4 K9  ; var4 = "/Lotus/Types/Enemies/Infested/Vip/J3Golem/BaseTrigDeco"
      12 [-]: CALL R3 2 2  ; var3 = var3(var4)
      13 [-]: GETIMPORT R4 7; var4 = 0x7ED0A956
      14 [-]: LOADK R5 K10 ; var5 = "/Lotus/Types/Enemies/Infested/Vip/J3Golem/J3GolemSpaceAvatar"
      15 [-]: CALL R4 2 2  ; var4 = var4(var5)
      16 [-]: GETIMPORT R5 7; var5 = 0x7ED0A956
      17 [-]: LOADK R6 K11 ; var6 = "/Lotus/Types/Actions/GenericHackButton"
      18 [-]: CALL R5 2 2  ; var5 = var5(var6)
      19 [-]: GETIMPORT R6 7; var6 = 0x7ED0A956
      20 [-]: LOADK R7 K12 ; var7 = "/Lotus/Types/Enemies/Infested/Vip/J3Golem/HitProxies/WeakPointHitProxy"
      21 [-]: CALL R6 2 2  ; var6 = var6(var7)
      22 [-]: GETIMPORT R7 14; var7 = 0xB009BBC6
      23 [-]: LOADK R8 K15 ; var8 = "/Lotus/Animations/Infested/Weakpoint/Spawn_anim.fbx"
      24 [-]: CALL R7 2 2  ; var7 = var7(var8)
      25 [-]: GETIMPORT R8 14; var8 = 0xB009BBC6
      26 [-]: LOADK R9 K16 ; var9 = "/Lotus/Animations/Infested/Weakpoint/Idle_anim.fbx"
      27 [-]: CALL R8 2 2  ; var8 = var8(var9)
      28 [-]: GETIMPORT R9 14; var9 = 0xB009BBC6
      29 [-]: LOADK R10 K17; var10 = "/Lotus/Animations/Infested/Weakpoint/Close_anim.fbx"
      30 [-]: CALL R9 2 2  ; var9 = var9(var10)
      31 [-]: GETIMPORT R10 14; var10 = 0xB009BBC6
      32 [-]: LOADK R11 K18; var11 = "/Lotus/Animations/Infested/Weakpoint/ClosedIdle_anim.fbx"
      33 [-]: CALL R10 2 2 ; var10 = var10(var11)
      34 [-]: GETIMPORT R11 20; var11 = 0x88EFC25E
      35 [-]: LOADK R12 K21; var12 = "/Lotus/Fx/Enemies/J3Golem/GolemWingsWeakSpotB"
      36 [-]: CALL R11 2 2 ; var11 = var11(var12)
      37 [-]: GETIMPORT R12 7; var12 = 0x7ED0A956
      38 [-]: LOADK R13 K22; var13 = "/Lotus/Types/Enemies/Infested/Vip/J3Golem/DevourTeleportTrigger"
      39 [-]: CALL R12 2 2 ; var12 = var12(var13)
      40 [-]: GETIMPORT R13 20; var13 = 0x88EFC25E
      41 [-]: LOADK R14 K23; var14 = "/Lotus/Types/Enemies/Infested/Vip/J3Golem/DevourInvertedTeleportTrigger"
      42 [-]: CALL R13 2 2 ; var13 = var13(var14)
      43 [-]: GETIMPORT R14 14; var14 = 0xB009BBC6
      44 [-]: LOADK R15 K24; var15 = "/Lotus/Animations/Infested/Devourer/Open_anim.fbx"
      45 [-]: CALL R14 2 2 ; var14 = var14(var15)
      46 [-]: GETIMPORT R15 14; var15 = 0xB009BBC6
      47 [-]: LOADK R16 K25; var16 = "/Lotus/Animations/Infested/Devourer/Close_anim.fbx"
      48 [-]: CALL R15 2 2 ; var15 = var15(var16)
      49 [-]: GETIMPORT R16 4; var16 = 0x0469F296
      50 [-]: LOADK R17 K26; var17 = "PurifiedReaction"
      51 [-]: CALL R16 2 2 ; var16 = var16(var17)
      52 [-]: GETIMPORT R17 4; var17 = 0x0469F296
      53 [-]: LOADK R18 K27; var18 = "PurifiedRecover"
      54 [-]: CALL R17 2 2 ; var17 = var17(var18)
      55 [-]: GETIMPORT R18 29; var18 = 0xBE190284
      56 [-]: GETIMPORT R19 4; var19 = 0x0469F296
      57 [-]: LOADK R20 K30; var20 = "RechargeTimer"
      58 [-]: CALL R19 2 2 ; var19 = var19(var20)
      59 [-]: GETIMPORT R20 4; var20 = 0x0469F296
      60 [-]: LOADK R21 K31; var21 = "RechargeLimit"
      61 [-]: CALL R20 2 2 ; var20 = var20(var21)
      62 [-]: GETIMPORT R21 4; var21 = 0x0469F296
      63 [-]: LOADK R22 K32; var22 = "TogglePurifiers"
      64 [-]: CALL R21 2 2 ; var21 = var21(var22)
      65 [-]: GETIMPORT R22 4; var22 = 0x0469F296
      66 [-]: LOADK R23 K33; var23 = "SpaceGolem"
      67 [-]: CALL R22 2 2 ; var22 = var22(var23)
      68 [-]: GETIMPORT R23 4; var23 = 0x0469F296
      69 [-]: LOADK R24 K34; var24 = "SpaceGolemStage"
      70 [-]: CALL R23 2 2 ; var23 = var23(var24)
      71 [-]: NEWTABLE R24 0 3; var24 = {}
      72 [-]: LOADN R25 0  ; var25 = 0
      73 [-]: LOADN R26 1  ; var26 = 1
      74 [-]: LOADN R27 4  ; var27 = 4
      75 [-]: SETLIST R24 R25 3 [1]; var24[1] = var25; var24[2] = var26; var24[3] = var27; var24[4] = var28; 
      76 [-]: DUPCLOSURE R25 K35; 
      77 [-]: DUPCLOSURE R26 K36; 
      78 [-]: DUPCLOSURE R27 K37; 
      79 [-]: LOADNIL R28  ; var28 = nil
      80 [-]: NEWCLOSURE R29 P3; 
      81 [-]: CAPTURE REF R28; 
      82 [-]: DUPCLOSURE R30 K38; 
      83 [-]: CAPTURE VAL R29; 
      84 [-]: SETGLOBAL R30 K39; "PurifierStageCounter" = var30
      85 [-]: DUPCLOSURE R30 K40; 
      86 [-]: SETGLOBAL R30 K41; "PurifierCompleteScript" = var30
      87 [-]: DUPCLOSURE R30 K42; 
      88 [-]: SETGLOBAL R30 K43; "SwitchCounter" = var30
      89 [-]: DUPCLOSURE R30 K44; 
      90 [-]: SETGLOBAL R30 K45; "ArmorStatus" = var30
      91 [-]: DUPCLOSURE R30 K46; 
      92 [-]: SETGLOBAL R30 K47; "SpaceArmorStatus" = var30
      93 [-]: LOADB R30 0  ; var30 = false
      94 [-]: NEWCLOSURE R31 P9; 
      95 [-]: CAPTURE REF R30; 
      96 [-]: SETGLOBAL R31 K48; "OnIncrement" = var31
      97 [-]: NEWCLOSURE R31 P10; 
      98 [-]: CAPTURE REF R18; 
      99 [-]: CAPTURE VAL R21; 
     100 [-]: CAPTURE REF R30; 
     101 [-]: CAPTURE VAL R0; 
     102 [-]: SETGLOBAL R31 K49; "DomeControl" = var31
     103 [-]: DUPCLOSURE R31 K50; 
     104 [-]: NEWCLOSURE R32 P12; 
     105 [-]: CAPTURE REF R18; 
     106 [-]: CAPTURE VAL R6; 
     107 [-]: CAPTURE VAL R23; 
     108 [-]: CAPTURE VAL R1; 
     109 [-]: CAPTURE VAL R9; 
     110 [-]: CAPTURE VAL R10; 
     111 [-]: CAPTURE VAL R7; 
     112 [-]: CAPTURE VAL R8; 
     113 [-]: SETGLOBAL R32 K51; "WeakpointControlNew" = var32
     114 [-]: DUPCLOSURE R32 K52; 
     115 [-]: SETGLOBAL R32 K53; "DevourControl" = var32
     116 [-]: NEWCLOSURE R32 P14; 
     117 [-]: CAPTURE REF R18; 
     118 [-]: CAPTURE VAL R19; 
     119 [-]: CAPTURE VAL R16; 
     120 [-]: CAPTURE VAL R17; 
     121 [-]: SETGLOBAL R32 K54; "GolemControl" = var32
     122 [-]: DUPCLOSURE R32 K55; 
     123 [-]: CAPTURE VAL R1; 
     124 [-]: CAPTURE VAL R3; 
     125 [-]: CAPTURE VAL R31; 
     126 [-]: SETGLOBAL R32 K56; "ConsoleControl" = var32
     127 [-]: DUPCLOSURE R32 K57; 
     128 [-]: CAPTURE VAL R5; 
     129 [-]: SETGLOBAL R32 K58; "OnTouched" = var32
     130 [-]: DUPCLOSURE R32 K59; 
     131 [-]: CAPTURE VAL R1; 
     132 [-]: CAPTURE VAL R3; 
     133 [-]: CAPTURE VAL R31; 
     134 [-]: SETGLOBAL R32 K60; "PurifierMonitor" = var32
     135 [-]: NEWCLOSURE R32 P18; 
     136 [-]: CAPTURE VAL R22; 
     137 [-]: CAPTURE REF R18; 
     138 [-]: CAPTURE VAL R23; 
     139 [-]: CAPTURE VAL R19; 
     140 [-]: CAPTURE VAL R20; 
     141 [-]: CAPTURE VAL R11; 
     142 [-]: SETGLOBAL R32 K61; "GolemButtonMonitor" = var32
     143 [-]: DUPCLOSURE R32 K62; 
     144 [-]: CAPTURE VAL R4; 
     145 [-]: SETGLOBAL R32 K63; "SpacePurifier" = var32
     146 [-]: DUPCLOSURE R32 K64; 
     147 [-]: SETGLOBAL R32 K65; "EnvironmentDamage" = var32
     148 [-]: DUPCLOSURE R32 K66; 
     149 [-]: CAPTURE VAL R12; 
     150 [-]: CAPTURE VAL R13; 
     151 [-]: CAPTURE VAL R14; 
     152 [-]: CAPTURE VAL R15; 
     153 [-]: SETGLOBAL R32 K67; "TeleportAgent" = var32
     154 [-]: DUPCLOSURE R32 K68; 
     155 [-]: SETGLOBAL R32 K69; "EnablePurifier" = var32
     156 [-]: DUPCLOSURE R32 K70; 
     157 [-]: SETGLOBAL R32 K71; "KillDebrisAttachments" = var32
     158 [-]: DUPCLOSURE R32 K72; 
     159 [-]: CAPTURE VAL R2; 
     160 [-]: CAPTURE VAL R24; 
     161 [-]: SETGLOBAL R32 K73; "EvaluateAction" = var32
     162 [-]: CLOSEUPVALS R18; 
     163 [-]: RETURN R0 0  ; 


; Name:            
; Defined at line: 93
; #Upvalues:       0
; #Parameters:     4
; Is_vararg:       0
; Max Stack Size:  13

       0 [-]: LOADNIL R4   ; var4 = nil
       1 [-]: JUMPIFNOTLT R0 R1 L1; goto L1 if var0 >= var67617
       2 [-]: GETIMPORT R8 1; var8 = 0x9BAFFFE3
       3 [-]: LOADN R9 0   ; var9 = 0
       4 [-]: LOADN R10 1  ; var10 = 1
       5 [-]: GETIMPORT R12 3; var12 = 0xAC64F27B
       6 [-]: MUL R11 R2 R12; var11 = var2 * var12
       7 [-]: CALL R8 4 2  ; var8 = var8(var9, var10, var11)
       8 [-]: ADD R7 R0 R8 ; var7 = var0 + var8
       9 [-]: FASTCALL2 19 R1 R7 L0; 
      10 [-]: MOVE R6 R1   ; var6 = var1
      11 [-]: GETIMPORT R5 6; var5 = 0x5BCED4C4[0xAC1B386A]
      12 [-]: CALL R5 3 2  ; var5 = var5(var6, var7)
L 0:  13 [-]: MOVE R4 R5   ; var4 = var5
      14 [-]: RETURN R4 1  ; 
L 1:  15 [-]: GETIMPORT R8 1; var8 = 0x9BAFFFE3
      16 [-]: LOADN R9 0   ; var9 = 0
      17 [-]: LOADN R10 1  ; var10 = 1
      18 [-]: GETIMPORT R12 3; var12 = 0xAC64F27B
      19 [-]: MUL R11 R3 R12; var11 = var3 * var12
      20 [-]: CALL R8 4 2  ; var8 = var8(var9, var10, var11)
      21 [-]: SUB R7 R0 R8 ; var7 = var0 - var8
      22 [-]: FASTCALL2 18 R1 R7 L2; 
      23 [-]: MOVE R6 R1   ; var6 = var1
      24 [-]: GETIMPORT R5 8; var5 = 0x5BCED4C4[0xB62ECFE0]
      25 [-]: CALL R5 3 2  ; var5 = var5(var6, var7)
L 2:  26 [-]: MOVE R4 R5   ; var4 = var5
      27 [-]: RETURN R4 1  ; 


; Name:            
; Defined at line: 106
; #Upvalues:       0
; #Parameters:     2
; Is_vararg:       0
; Max Stack Size:  5

       0 [-]: SUB R4 R0 R1 ; var4 = var0 - var1
       1 [-]: FASTCALL1 2 R4 L0; 
       2 [-]: GETIMPORT R3 2; var3 = 0x5BCED4C4[0xE4A5B3CA]
       3 [-]: CALL R3 2 2  ; var3 = var3(var4)
L 0:   4 [-]: LOADK R4 K3  ; var4 = 0.0099999997764825821
       5 [-]: JUMPIFLT R3 R4 L1; goto L1 if var3 < var16777734
       6 [-]: LOADB R2 0 +1; var2 = false
L 1:   7 [-]: LOADB R2 1   ; var2 = true
L 2:   8 [-]: RETURN R2 1  ; 


; Name:            
; Defined at line: 112
; #Upvalues:       0
; #Parameters:     1
; Is_vararg:       0
; Max Stack Size:  11

       0 [-]: NAMECALL R1 R0 K0; var2 = var0; var1 = var0[0x2B54251B]
       1 [-]: CALL R1 2 2  ; var1 = var1(var2)
       2 [-]: FASTCALL1 64 R1 L0; 
       3 [-]: MOVE R3 R1   ; var3 = var1
       4 [-]: GETIMPORT R2 2; var2 = 0x7B998233
       5 [-]: CALL R2 2 2  ; var2 = var2(var3)
L 0:   6 [-]: JUMPIF R2 L1 ; goto L1 if var2
       7 [-]: GETIMPORT R4 4; var4 = 0x0469F296
       8 [-]: LOADK R5 K5  ; var5 = "BlueClipThreshold"
       9 [-]: CALL R4 2 2  ; var4 = var4(var5)
      10 [-]: LOADN R6 1   ; var6 = 1
      11 [-]: NAMECALL R8 R0 K6; var9 = var0; var8 = var0[0x2E333568]
      12 [-]: CALL R8 2 2  ; var8 = var8(var9)
      13 [-]: NAMECALL R9 R0 K7; var10 = var0; var9 = var0[0xDAB60FC5]
      14 [-]: CALL R9 2 2  ; var9 = var9(var10)
      15 [-]: DIV R7 R8 R9 ; var7 = var8 / var9
      16 [-]: SUB R5 R6 R7 ; var5 = var6 - var7
      17 [-]: NAMECALL R2 R1 K8; var3 = var1; var2 = var1[0x986D2AB8]
      18 [-]: CALL R2 4 1  ; var2(var3, var4, var5)
L 1:  19 [-]: RETURN R0 0  ; 


; Name:            
; Defined at line: 120
; #Upvalues:       1
; #Parameters:     1
; Is_vararg:       0
; Max Stack Size:  7

       0 [-]: GETUPVAL R2 0; var2 = upvalues[0]
       1 [-]: FASTCALL1 64 R2 L0; 
       2 [-]: GETIMPORT R1 1; var1 = 0x7B998233
       3 [-]: CALL R1 2 2  ; var1 = var1(var2)
L 0:   4 [-]: JUMPIF R1 L1 ; goto L1 if var1
       5 [-]: GETUPVAL R1 0; var1 = upvalues[0]
       6 [-]: NAMECALL R1 R1 K2; var2 = var1; var1 = var1[0xF4E253B6]
       7 [-]: CALL R1 2 1  ; var1(var2)
L 1:   8 [-]: NAMECALL R1 R0 K3; var2 = var0; var1 = var0[0x2E333568]
       9 [-]: CALL R1 2 2  ; var1 = var1(var2)
      10 [-]: LOADN R2 0   ; var2 = 0
      11 [-]: JUMPIFNOTLT R2 R1 L2; goto L2 if var2 >= var1744830796
      12 [-]: NAMECALL R1 R0 K3; var2 = var0; var1 = var0[0x2E333568]
      13 [-]: CALL R1 2 2  ; var1 = var1(var2)
      14 [-]: GETIMPORT R3 5; var3 = 0x39B1DCF6
      15 [-]: LENGTH R2 R3 ; var2 = #var3
      16 [-]: JUMPIFNOTLE R1 R2 L2; goto L2 if var1 > var459041
      17 [-]: GETIMPORT R1 7; var1 = 0x89326C93
      18 [-]: GETIMPORT R4 5; var4 = 0x39B1DCF6
      19 [-]: NAMECALL R5 R0 K3; var6 = var0; var5 = var0[0x2E333568]
      20 [-]: CALL R5 2 2  ; var5 = var5(var6)
      21 [-]: GETTABLE R3 R4 R5; var3 = var4[var5]
      22 [-]: NAMECALL R4 R0 K8; var5 = var0; var4 = var0[0xD1586535]
      23 [-]: CALL R4 2 2  ; var4 = var4(var5)
      24 [-]: GETIMPORT R5 10; var5 = 0x00046924
      25 [-]: CALL R5 1 0  ; var5, ... = var5()
      26 [-]: NAMECALL R1 R1 K11; var2 = var1; var1 = var1[0x05909209]
      27 [-]: CALL R1 0 2  ; var1 = var1(var2, ...)
      28 [-]: SETUPVAL R1 0; upvalues[1] = var0
L 2:  29 [-]: RETURN R0 0  ; 


; Name:            
; Defined at line: 130
; #Upvalues:       1
; #Parameters:     1
; Is_vararg:       0
; Max Stack Size:  13

       0 [-]: NAMECALL R1 R0 K0; var2 = var0; var1 = var0[0x2B54251B]
       1 [-]: CALL R1 2 2  ; var1 = var1(var2)
L 0:   2 [-]: FASTCALL1 64 R1 L1; 
       3 [-]: MOVE R3 R1   ; var3 = var1
       4 [-]: GETIMPORT R2 2; var2 = 0x7B998233
       5 [-]: CALL R2 2 2  ; var2 = var2(var3)
L 1:   6 [-]: JUMPIFNOT R2 L2; goto L2 if not var2
       7 [-]: NAMECALL R2 R0 K0; var3 = var0; var2 = var0[0x2B54251B]
       8 [-]: CALL R2 2 2  ; var2 = var2(var3)
       9 [-]: MOVE R1 R2   ; var1 = var2
      10 [-]: GETIMPORT R2 4; var2 = 0xCBD666E1
      11 [-]: LOADN R3 0   ; var3 = 0
      12 [-]: CALL R2 2 1  ; var2(var3)
      13 [-]: JUMPBACK L0  ; goto L0
L 2:  14 [-]: GETIMPORT R4 6; var4 = 0xB0DE66FE
      15 [-]: NAMECALL R2 R1 K7; var3 = var1; var2 = var1[0x0542D42B]
      16 [-]: CALL R2 3 2  ; var2 = var2(var3, var4)
      17 [-]: JUMPIFNOT R2 L3; goto L3 if not var2
      18 [-]: GETIMPORT R2 4; var2 = 0xCBD666E1
      19 [-]: LOADN R3 0   ; var3 = 0
      20 [-]: CALL R2 2 1  ; var2(var3)
      21 [-]: JUMPBACK L2  ; goto L2
L 3:  22 [-]: NAMECALL R2 R0 K0; var3 = var0; var2 = var0[0x2B54251B]
      23 [-]: CALL R2 2 2  ; var2 = var2(var3)
      24 [-]: FASTCALL1 64 R2 L4; 
      25 [-]: MOVE R4 R2   ; var4 = var2
      26 [-]: GETIMPORT R3 2; var3 = 0x7B998233
      27 [-]: CALL R3 2 2  ; var3 = var3(var4)
L 4:  28 [-]: JUMPIF R3 L5 ; goto L5 if var3
      29 [-]: GETIMPORT R5 9; var5 = 0x0469F296
      30 [-]: LOADK R6 K10 ; var6 = "BlueClipThreshold"
      31 [-]: CALL R5 2 2  ; var5 = var5(var6)
      32 [-]: LOADN R7 1   ; var7 = 1
      33 [-]: NAMECALL R9 R0 K11; var10 = var0; var9 = var0[0x2E333568]
      34 [-]: CALL R9 2 2  ; var9 = var9(var10)
      35 [-]: NAMECALL R10 R0 K12; var11 = var0; var10 = var0[0xDAB60FC5]
      36 [-]: CALL R10 2 2 ; var10 = var10(var11)
      37 [-]: DIV R8 R9 R10; var8 = var9 / var10
      38 [-]: SUB R6 R7 R8 ; var6 = var7 - var8
      39 [-]: NAMECALL R3 R2 K13; var4 = var2; var3 = var2[0x986D2AB8]
      40 [-]: CALL R3 4 1  ; var3(var4, var5, var6)
L 5:  41 [-]: NAMECALL R2 R0 K11; var3 = var0; var2 = var0[0x2E333568]
      42 [-]: CALL R2 2 2  ; var2 = var2(var3)
L 6:  43 [-]: FASTCALL1 64 R0 L7; 
      44 [-]: MOVE R4 R0   ; var4 = var0
      45 [-]: GETIMPORT R3 2; var3 = 0x7B998233
      46 [-]: CALL R3 2 2  ; var3 = var3(var4)
L 7:  47 [-]: JUMPIF R3 L13; goto L13 if var3
      48 [-]: GETIMPORT R3 4; var3 = 0xCBD666E1
      49 [-]: LOADN R4 0   ; var4 = 0
      50 [-]: CALL R3 2 1  ; var3(var4)
      51 [-]: NAMECALL R3 R0 K11; var4 = var0; var3 = var0[0x2E333568]
      52 [-]: CALL R3 2 2  ; var3 = var3(var4)
      53 [-]: JUMPIFEQ R2 R3 L12; goto L12 if var2 == var452985676
      54 [-]: NAMECALL R3 R0 K0; var4 = var0; var3 = var0[0x2B54251B]
      55 [-]: CALL R3 2 2  ; var3 = var3(var4)
      56 [-]: FASTCALL1 64 R3 L8; 
      57 [-]: MOVE R5 R3   ; var5 = var3
      58 [-]: GETIMPORT R4 2; var4 = 0x7B998233
      59 [-]: CALL R4 2 2  ; var4 = var4(var5)
L 8:  60 [-]: JUMPIF R4 L9 ; goto L9 if var4
      61 [-]: GETIMPORT R6 9; var6 = 0x0469F296
      62 [-]: LOADK R7 K10 ; var7 = "BlueClipThreshold"
      63 [-]: CALL R6 2 2  ; var6 = var6(var7)
      64 [-]: LOADN R8 1   ; var8 = 1
      65 [-]: NAMECALL R10 R0 K11; var11 = var0; var10 = var0[0x2E333568]
      66 [-]: CALL R10 2 2 ; var10 = var10(var11)
      67 [-]: NAMECALL R11 R0 K12; var12 = var0; var11 = var0[0xDAB60FC5]
      68 [-]: CALL R11 2 2 ; var11 = var11(var12)
      69 [-]: DIV R9 R10 R11; var9 = var10 / var11
      70 [-]: SUB R7 R8 R9 ; var7 = var8 - var9
      71 [-]: NAMECALL R4 R3 K13; var5 = var3; var4 = var3[0x986D2AB8]
      72 [-]: CALL R4 4 1  ; var4(var5, var6, var7)
L 9:  73 [-]: GETIMPORT R3 15; var3 = 0x5108E7AF
      74 [-]: JUMPIFNOT R3 L10; goto L10 if not var3
      75 [-]: GETUPVAL R3 0; var3 = upvalues[0]
      76 [-]: MOVE R4 R0   ; var4 = var0
      77 [-]: CALL R3 2 1  ; var3(var4)
L10:  78 [-]: NAMECALL R3 R0 K11; var4 = var0; var3 = var0[0x2E333568]
      79 [-]: CALL R3 2 2  ; var3 = var3(var4)
      80 [-]: JUMPIFNOTLT R3 R2 L11; goto L11 if var3 >= var1115425
      81 [-]: GETIMPORT R5 17; var5 = 0x11B5D24E
      82 [-]: LOADB R6 0   ; var6 = false
      83 [-]: NAMECALL R3 R0 K18; var4 = var0; var3 = var0[0x659D451F]
      84 [-]: CALL R3 4 1  ; var3(var4, var5, var6)
L11:  85 [-]: NAMECALL R3 R0 K11; var4 = var0; var3 = var0[0x2E333568]
      86 [-]: CALL R3 2 2  ; var3 = var3(var4)
      87 [-]: MOVE R2 R3   ; var2 = var3
L12:  88 [-]: JUMPBACK L6  ; goto L6
L13:  89 [-]: RETURN R0 0  ; 


; Name:            
; Defined at line: 159
; #Upvalues:       0
; #Parameters:     2
; Is_vararg:       0
; Max Stack Size:  6

       0 [-]: GETIMPORT R2 2; var2 = _T["RaidUsedSyringe"]
       1 [-]: JUMPIFNOT R2 L0; goto L0 if not var2
       2 [-]: GETIMPORT R2 2; var2 = _T["RaidUsedSyringe"]
       3 [-]: NAMECALL R3 R1 K3; var4 = var1; var3 = var1[0x5E651723]
       4 [-]: CALL R3 2 2  ; var3 = var3(var4)
       5 [-]: MOVE R4 R0   ; var4 = var0
       6 [-]: CALL R2 3 1  ; var2(var3, var4)
L 0:   7 [-]: GETIMPORT R2 5; var2 = 0x89326C93
       8 [-]: NAMECALL R2 R2 K6; var3 = var2; var2 = var2[0x18D05D30]
       9 [-]: CALL R2 2 2  ; var2 = var2(var3)
      10 [-]: JUMPIFNOT R2 L2; goto L2 if not var2
      11 [-]: GETIMPORT R4 8; var4 = 0x7ED0A956
      12 [-]: LOADK R5 K9  ; var5 = "/Lotus/Types/LevelObjects/Attachments/ActivatePurifierScriptTrigger"
      13 [-]: CALL R4 2 0  ; var4, ... = var4(var5)
      14 [-]: NAMECALL R2 R0 K10; var3 = var0; var2 = var0[0xC9F6A7D7]
      15 [-]: CALL R2 0 2  ; var2 = var2(var3, ...)
      16 [-]: FASTCALL1 64 R2 L1; 
      17 [-]: MOVE R4 R2   ; var4 = var2
      18 [-]: GETIMPORT R3 12; var3 = 0x7B998233
      19 [-]: CALL R3 2 2  ; var3 = var3(var4)
L 1:  20 [-]: JUMPIF R3 L2 ; goto L2 if var3
      21 [-]: LOADK R5 K13 ; var5 = "Execute"
      22 [-]: NAMECALL R3 R2 K14; var4 = var2; var3 = var2[0x8EB2112D]
      23 [-]: CALL R3 3 1  ; var3(var4, var5)
L 2:  24 [-]: RETURN R0 0  ; 


; Name:            
; Defined at line: 173
; #Upvalues:       0
; #Parameters:     2
; Is_vararg:       0
; Max Stack Size:  7

       0 [-]: NAMECALL R2 R0 K0; var3 = var0; var2 = var0[0x2B54251B]
       1 [-]: CALL R2 2 2  ; var2 = var2(var3)
       2 [-]: GETIMPORT R5 2; var5 = gPortCounterType
       3 [-]: NAMECALL R3 R2 K3; var4 = var2; var3 = var2[0xC9F6A7D7]
       4 [-]: CALL R3 3 2  ; var3 = var3(var4, var5)
       5 [-]: LOADK R6 K4  ; var6 = "Increment"
       6 [-]: NAMECALL R4 R3 K5; var5 = var3; var4 = var3[0x8EB2112D]
       7 [-]: CALL R4 3 1  ; var4(var5, var6)
       8 [-]: RETURN R0 0  ; 


; Name:            
; Defined at line: 180
; #Upvalues:       0
; #Parameters:     1
; Is_vararg:       0
; Max Stack Size:  6

       0 [-]: GETIMPORT R3 1; var3 = gPortCounterType
       1 [-]: NAMECALL R1 R0 K2; var2 = var0; var1 = var0[0xC9F6A7D7]
       2 [-]: CALL R1 3 2  ; var1 = var1(var2, var3)
L 0:   3 [-]: FASTCALL1 64 R1 L1; 
       4 [-]: MOVE R3 R1   ; var3 = var1
       5 [-]: GETIMPORT R2 4; var2 = 0x7B998233
       6 [-]: CALL R2 2 2  ; var2 = var2(var3)
L 1:   7 [-]: JUMPIFNOT R2 L2; goto L2 if not var2
       8 [-]: GETIMPORT R2 6; var2 = 0xCBD666E1
       9 [-]: LOADN R3 0   ; var3 = 0
      10 [-]: CALL R2 2 1  ; var2(var3)
      11 [-]: GETIMPORT R4 1; var4 = gPortCounterType
      12 [-]: NAMECALL R2 R0 K2; var3 = var0; var2 = var0[0xC9F6A7D7]
      13 [-]: CALL R2 3 2  ; var2 = var2(var3, var4)
      14 [-]: MOVE R1 R2   ; var1 = var2
      15 [-]: JUMPBACK L0  ; goto L0
L 2:  16 [-]: GETIMPORT R4 8; var4 = 0x079FE2C6
      17 [-]: NAMECALL R2 R1 K9; var3 = var1; var2 = var1[0x80B6C081]
      18 [-]: CALL R2 3 1  ; var2(var3, var4)
      19 [-]: GETIMPORT R2 11; var2 = 0x89326C93
      20 [-]: NAMECALL R2 R2 K12; var3 = var2; var2 = var2[0x18D05D30]
      21 [-]: CALL R2 2 2  ; var2 = var2(var3)
      22 [-]: JUMPIF R2 L3 ; goto L3 if var2
      23 [-]: RETURN R0 0  ; 
L 3:  24 [-]: GETIMPORT R4 14; var4 = 0x8574005C
      25 [-]: NAMECALL R2 R1 K15; var3 = var1; var2 = var1[0xB35F65B4]
      26 [-]: CALL R2 3 1  ; var2(var3, var4)
      27 [-]: GETIMPORT R2 6; var2 = 0xCBD666E1
      28 [-]: LOADN R3 2   ; var3 = 2
      29 [-]: CALL R2 2 1  ; var2(var3)
      30 [-]: LOADNIL R2   ; var2 = nil
      31 [-]: GETIMPORT R3 17; var3 = 0x70C2089F
      32 [-]: JUMPIF R3 L5 ; goto L5 if var3
      33 [-]: GETIMPORT R5 19; var5 = 0xB0DE66FE
      34 [-]: NAMECALL R3 R0 K2; var4 = var0; var3 = var0[0xC9F6A7D7]
      35 [-]: CALL R3 3 2  ; var3 = var3(var4, var5)
      36 [-]: MOVE R2 R3   ; var2 = var3
      37 [-]: FASTCALL1 64 R2 L4; 
      38 [-]: MOVE R4 R2   ; var4 = var2
      39 [-]: GETIMPORT R3 4; var3 = 0x7B998233
      40 [-]: CALL R3 2 2  ; var3 = var3(var4)
L 4:  41 [-]: JUMPIF R3 L5 ; goto L5 if var3
      42 [-]: NAMECALL R3 R2 K20; var4 = var2; var3 = var2[0xA2880940]
      43 [-]: CALL R3 2 1  ; var3(var4)
L 5:  44 [-]: RETURN R0 0  ; 


; Name:            
; Defined at line: 205
; #Upvalues:       0
; #Parameters:     1
; Is_vararg:       0
; Max Stack Size:  10

       0 [-]: GETIMPORT R1 1; var1 = 0xCBD666E1
       1 [-]: LOADN R2 0   ; var2 = 0
       2 [-]: CALL R1 2 1  ; var1(var2)
       3 [-]: GETIMPORT R1 3; var1 = 0x1AC48339
       4 [-]: GETIMPORT R4 5; var4 = 0xB0DE66FE
       5 [-]: NAMECALL R2 R0 K6; var3 = var0; var2 = var0[0xC9F6A7D7]
       6 [-]: CALL R2 3 2  ; var2 = var2(var3, var4)
       7 [-]: GETIMPORT R3 8; var3 = 0x70C2089F
       8 [-]: JUMPIF R3 L0 ; goto L0 if var3
       9 [-]: NAMECALL R3 R2 K9; var4 = var2; var3 = var2[0xA2880940]
      10 [-]: CALL R3 2 1  ; var3(var4)
L 0:  11 [-]: NAMECALL R3 R0 K10; var4 = var0; var3 = var0[0x28E744CF]
      12 [-]: CALL R3 2 2  ; var3 = var3(var4)
      13 [-]: LOADNIL R4   ; var4 = nil
L 1:  14 [-]: FASTCALL1 64 R3 L2; 
      15 [-]: MOVE R6 R3   ; var6 = var3
      16 [-]: GETIMPORT R5 12; var5 = 0x7B998233
      17 [-]: CALL R5 2 2  ; var5 = var5(var6)
L 2:  18 [-]: JUMPIF R5 L7 ; goto L7 if var5
      19 [-]: FASTCALL1 64 R2 L3; 
      20 [-]: MOVE R6 R2   ; var6 = var2
      21 [-]: GETIMPORT R5 12; var5 = 0x7B998233
      22 [-]: CALL R5 2 2  ; var5 = var5(var6)
L 3:  23 [-]: JUMPIFNOT R5 L5; goto L5 if not var5
      24 [-]: FASTCALL1 64 R4 L4; 
      25 [-]: MOVE R6 R4   ; var6 = var4
      26 [-]: GETIMPORT R5 12; var5 = 0x7B998233
      27 [-]: CALL R5 2 2  ; var5 = var5(var6)
L 4:  28 [-]: JUMPIFNOT R5 L5; goto L5 if not var5
      29 [-]: GETIMPORT R7 14; var7 = gPortCounterType
      30 [-]: NAMECALL R5 R0 K6; var6 = var0; var5 = var0[0xC9F6A7D7]
      31 [-]: CALL R5 3 2  ; var5 = var5(var6, var7)
      32 [-]: MOVE R4 R5   ; var4 = var5
      33 [-]: GETIMPORT R7 16; var7 = 0x8574005C
      34 [-]: NAMECALL R5 R4 K17; var6 = var4; var5 = var4[0xB35F65B4]
      35 [-]: CALL R5 3 1  ; var5(var6, var7)
      36 [-]: GETIMPORT R7 19; var7 = 0x079FE2C6
      37 [-]: NAMECALL R5 R4 K20; var6 = var4; var5 = var4[0x80B6C081]
      38 [-]: CALL R5 3 1  ; var5(var6, var7)
L 5:  39 [-]: LOADN R5 0   ; var5 = 0
      40 [-]: JUMPIFNOTLE R1 R5 L6; goto L6 if var1 > var1443105
      41 [-]: GETIMPORT R5 22; var5 = 0x89326C93
      42 [-]: GETIMPORT R7 24; var7 = 0x3CDCE68E
      43 [-]: NAMECALL R8 R3 K25; var9 = var3; var8 = var3[0xD1586535]
      44 [-]: CALL R8 2 2  ; var8 = var8(var9)
      45 [-]: GETIMPORT R9 27; var9 = ZERO_ROTATION
      46 [-]: NAMECALL R5 R5 K28; var6 = var5; var5 = var5[0x05909209]
      47 [-]: CALL R5 5 1  ; var5(var6, var7, var8, var9)
      48 [-]: NAMECALL R5 R3 K9; var6 = var3; var5 = var3[0xA2880940]
      49 [-]: CALL R5 2 1  ; var5(var6)
L 6:  50 [-]: GETIMPORT R5 30; var5 = 0x67652851
      51 [-]: CALL R5 1 2  ; var5 = var5()
      52 [-]: SUB R1 R1 R5 ; var1 = var1 - var5
      53 [-]: GETIMPORT R5 1; var5 = 0xCBD666E1
      54 [-]: LOADN R6 0   ; var6 = 0
      55 [-]: CALL R5 2 1  ; var5(var6)
      56 [-]: JUMPBACK L1  ; goto L1
L 7:  57 [-]: RETURN R0 0  ; 


; Name:            
; Defined at line: 238
; #Upvalues:       1
; #Parameters:     1
; Is_vararg:       0
; Max Stack Size:  2

       0 [-]: LOADB R1 1   ; var1 = true
       1 [-]: SETUPVAL R1 0; upvalues[1] = var0
       2 [-]: RETURN R0 0  ; 


; Name:            
; Defined at line: 242
; #Upvalues:       4
; #Parameters:     1
; Is_vararg:       0
; Max Stack Size:  33

L 0:   0 [-]: GETUPVAL R2 0; var2 = upvalues[0]
       1 [-]: FASTCALL1 64 R2 L1; 
       2 [-]: GETIMPORT R1 1; var1 = 0x7B998233
       3 [-]: CALL R1 2 2  ; var1 = var1(var2)
L 1:   4 [-]: JUMPIFNOT R1 L2; goto L2 if not var1
       5 [-]: GETIMPORT R1 3; var1 = 0xCBD666E1
       6 [-]: LOADN R2 0   ; var2 = 0
       7 [-]: CALL R1 2 1  ; var1(var2)
       8 [-]: GETIMPORT R1 5; var1 = 0xBE190284
       9 [-]: SETUPVAL R1 0; upvalues[1] = var0
      10 [-]: JUMPBACK L0  ; goto L0
L 2:  11 [-]: GETIMPORT R1 3; var1 = 0xCBD666E1
      12 [-]: LOADK R2 K6  ; var2 = 0.10000000149011612
      13 [-]: CALL R1 2 1  ; var1(var2)
      14 [-]: NAMECALL R1 R0 K7; var2 = var0; var1 = var0[0x2B54251B]
      15 [-]: CALL R1 2 2  ; var1 = var1(var2)
L 3:  16 [-]: FASTCALL1 64 R1 L4; 
      17 [-]: MOVE R3 R1   ; var3 = var1
      18 [-]: GETIMPORT R2 1; var2 = 0x7B998233
      19 [-]: CALL R2 2 2  ; var2 = var2(var3)
L 4:  20 [-]: JUMPIFNOT R2 L5; goto L5 if not var2
      21 [-]: GETIMPORT R2 3; var2 = 0xCBD666E1
      22 [-]: LOADN R3 0   ; var3 = 0
      23 [-]: CALL R2 2 1  ; var2(var3)
      24 [-]: NAMECALL R2 R0 K7; var3 = var0; var2 = var0[0x2B54251B]
      25 [-]: CALL R2 2 2  ; var2 = var2(var3)
      26 [-]: MOVE R1 R2   ; var1 = var2
      27 [-]: JUMPBACK L3  ; goto L3
L 5:  28 [-]: GETIMPORT R4 9; var4 = gPortCounterType
      29 [-]: NAMECALL R2 R1 K10; var3 = var1; var2 = var1[0xC9F6A7D7]
      30 [-]: CALL R2 3 2  ; var2 = var2(var3, var4)
L 6:  31 [-]: FASTCALL1 64 R2 L7; 
      32 [-]: MOVE R4 R2   ; var4 = var2
      33 [-]: GETIMPORT R3 1; var3 = 0x7B998233
      34 [-]: CALL R3 2 2  ; var3 = var3(var4)
L 7:  35 [-]: JUMPIFNOT R3 L8; goto L8 if not var3
      36 [-]: GETIMPORT R3 3; var3 = 0xCBD666E1
      37 [-]: LOADN R4 0   ; var4 = 0
      38 [-]: CALL R3 2 1  ; var3(var4)
      39 [-]: GETIMPORT R5 9; var5 = gPortCounterType
      40 [-]: NAMECALL R3 R1 K10; var4 = var1; var3 = var1[0xC9F6A7D7]
      41 [-]: CALL R3 3 2  ; var3 = var3(var4, var5)
      42 [-]: MOVE R2 R3   ; var2 = var3
      43 [-]: JUMPBACK L6  ; goto L6
L 8:  44 [-]: GETIMPORT R3 12; var3 = 0x11A19C5E
      45 [-]: MOVE R4 R2   ; var4 = var2
      46 [-]: LOADK R5 K13 ; var5 = "OnIncrement"
      47 [-]: CALL R3 3 1  ; var3(var4, var5)
      48 [-]: NAMECALL R3 R2 K14; var4 = var2; var3 = var2[0x2E333568]
      49 [-]: CALL R3 2 2  ; var3 = var3(var4)
      50 [-]: MOVE R4 R3   ; var4 = var3
      51 [-]: LOADB R5 0   ; var5 = false
      52 [-]: MOVE R6 R3   ; var6 = var3
L 9:  53 [-]: GETIMPORT R9 16; var9 = 0xB0DE66FE
      54 [-]: NAMECALL R7 R1 K17; var8 = var1; var7 = var1[0x0542D42B]
      55 [-]: CALL R7 3 2  ; var7 = var7(var8, var9)
      56 [-]: JUMPIFNOT R7 L10; goto L10 if not var7
      57 [-]: GETIMPORT R7 3; var7 = 0xCBD666E1
      58 [-]: LOADN R8 0   ; var8 = 0
      59 [-]: CALL R7 2 1  ; var7(var8)
      60 [-]: JUMPBACK L9  ; goto L9
L10:  61 [-]: GETIMPORT R7 3; var7 = 0xCBD666E1
      62 [-]: LOADK R8 K18 ; var8 = 0.5
      63 [-]: CALL R7 2 1  ; var7(var8)
      64 [-]: LOADB R9 1   ; var9 = true
      65 [-]: NAMECALL R7 R0 K19; var8 = var0; var7 = var0[0x768274D6]
      66 [-]: CALL R7 3 1  ; var7(var8, var9)
      67 [-]: NAMECALL R7 R1 K20; var8 = var1; var7 = var1[0x383D2E7D]
      68 [-]: CALL R7 2 1  ; var7(var8)
      69 [-]: NAMECALL R7 R0 K21; var8 = var0; var7 = var0[0x65D389CB]
      70 [-]: CALL R7 2 2  ; var7 = var7(var8)
      71 [-]: MOVE R8 R7   ; var8 = var7
      72 [-]: LOADN R9 0   ; var9 = 0
      73 [-]: LOADN R10 0  ; var10 = 0
      74 [-]: LOADNIL R11  ; var11 = nil
      75 [-]: GETIMPORT R12 23; var12 = 0x2A934C50
      76 [-]: JUMPIF R12 L11; goto L11 if var12
      77 [-]: GETIMPORT R14 25; var14 = 0xECB2A793
      78 [-]: NAMECALL R12 R0 K10; var13 = var0; var12 = var0[0xC9F6A7D7]
      79 [-]: CALL R12 3 2 ; var12 = var12(var13, var14)
      80 [-]: MOVE R11 R12 ; var11 = var12
      81 [-]: JUMP L12     ; goto L12
L11:  82 [-]: GETIMPORT R14 27; var14 = 0x1D31970D
      83 [-]: NAMECALL R12 R0 K10; var13 = var0; var12 = var0[0xC9F6A7D7]
      84 [-]: CALL R12 3 2 ; var12 = var12(var13, var14)
      85 [-]: MOVE R11 R12 ; var11 = var12
L12:  86 [-]: GETIMPORT R14 29; var14 = 0x276FDF68
      87 [-]: NAMECALL R12 R0 K10; var13 = var0; var12 = var0[0xC9F6A7D7]
      88 [-]: CALL R12 3 2 ; var12 = var12(var13, var14)
L13:  89 [-]: FASTCALL1 64 R12 L14; 
      90 [-]: MOVE R14 R12 ; var14 = var12
      91 [-]: GETIMPORT R13 1; var13 = 0x7B998233
      92 [-]: CALL R13 2 2 ; var13 = var13(var14)
L14:  93 [-]: JUMPIFNOT R13 L15; goto L15 if not var13
      94 [-]: GETIMPORT R13 3; var13 = 0xCBD666E1
      95 [-]: LOADN R14 0  ; var14 = 0
      96 [-]: CALL R13 2 1 ; var13(var14)
      97 [-]: GETIMPORT R15 29; var15 = 0x276FDF68
      98 [-]: NAMECALL R13 R0 K10; var14 = var0; var13 = var0[0xC9F6A7D7]
      99 [-]: CALL R13 3 2 ; var13 = var13(var14, var15)
     100 [-]: MOVE R12 R13 ; var12 = var13
     101 [-]: JUMPBACK L13 ; goto L13
L15: 102 [-]: LOADNIL R13  ; var13 = nil
     103 [-]: NAMECALL R14 R12 K30; var15 = var12; var14 = var12[0xDE89CF48]
     104 [-]: CALL R14 2 2 ; var14 = var14(var15)
     105 [-]: MOVE R13 R14 ; var13 = var14
     106 [-]: GETIMPORT R14 32; var14 = 0x89326C93
     107 [-]: GETIMPORT R16 34; var16 = 0xBDE3E984
     108 [-]: NAMECALL R17 R0 K35; var18 = var0; var17 = var0[0xD1586535]
     109 [-]: CALL R17 2 2 ; var17 = var17(var18)
     110 [-]: GETIMPORT R18 37; var18 = ZERO_ROTATION
     111 [-]: NAMECALL R14 R14 K38; var15 = var14; var14 = var14[0x05909209]
     112 [-]: CALL R14 5 1 ; var14(var15, var16, var17, var18)
     113 [-]: GETIMPORT R16 40; var16 = 0x7EDA801D
     114 [-]: GETIMPORT R17 42; var17 = EMPTY_SYMBOL
     115 [-]: NAMECALL R14 R0 K43; var15 = var0; var14 = var0[0x47901F07]
     116 [-]: CALL R14 4 1 ; var14(var15, var16, var17)
     117 [-]: LOADNIL R14  ; var14 = nil
     118 [-]: LOADNIL R15  ; var15 = nil
     119 [-]: LOADN R16 0  ; var16 = 0
     120 [-]: LOADN R17 0  ; var17 = 0
     121 [-]: LOADB R18 0  ; var18 = false
     122 [-]: GETIMPORT R19 32; var19 = 0x89326C93
     123 [-]: NAMECALL R19 R19 K44; var20 = var19; var19 = var19[0x18D05D30]
     124 [-]: CALL R19 2 2 ; var19 = var19(var20)
     125 [-]: JUMPIFNOT R19 L16; goto L16 if not var19
     126 [-]: GETUPVAL R19 0; var19 = upvalues[0]
     127 [-]: GETUPVAL R21 1; var21 = upvalues[1]
     128 [-]: LOADN R22 1  ; var22 = 1
     129 [-]: NAMECALL R19 R19 K45; var20 = var19; var19 = var19[0x751F061D]
     130 [-]: CALL R19 4 1 ; var19(var20, var21, var22)
L16: 131 [-]: FASTCALL1 64 R0 L17; 
     132 [-]: MOVE R20 R0  ; var20 = var0
     133 [-]: GETIMPORT R19 1; var19 = 0x7B998233
     134 [-]: CALL R19 2 2 ; var19 = var19(var20)
L17: 135 [-]: JUMPIF R19 L50; goto L50 if var19
     136 [-]: GETUPVAL R19 0; var19 = upvalues[0]
     137 [-]: GETUPVAL R21 1; var21 = upvalues[1]
     138 [-]: NAMECALL R19 R19 K46; var20 = var19; var19 = var19[0x0EB34C69]
     139 [-]: CALL R19 3 2 ; var19 = var19(var20, var21)
     140 [-]: JUMPXEQKN R19 K47 L18 NOT; 
     141 [-]: NAMECALL R19 R1 K48; var20 = var1; var19 = var1[0xF4E253B6]
     142 [-]: CALL R19 2 1 ; var19(var20)
     143 [-]: LOADK R10 K49; var10 = 3.4028234663852886e+38
     144 [-]: LOADB R18 1  ; var18 = true
     145 [-]: JUMP L19     ; goto L19
L18: 146 [-]: JUMPIFNOT R18 L19; goto L19 if not var18
     147 [-]: LOADB R18 0  ; var18 = false
     148 [-]: LOADN R10 0  ; var10 = 0
     149 [-]: MOVE R21 R6  ; var21 = var6
     150 [-]: NAMECALL R19 R2 K50; var20 = var2; var19 = var2[0xB35F65B4]
     151 [-]: CALL R19 3 1 ; var19(var20, var21)
L19: 152 [-]: FASTCALL1 64 R12 L20; 
     153 [-]: MOVE R20 R12 ; var20 = var12
     154 [-]: GETIMPORT R19 1; var19 = 0x7B998233
     155 [-]: CALL R19 2 2 ; var19 = var19(var20)
L20: 156 [-]: JUMPIFNOT R19 L21; goto L21 if not var19
     157 [-]: GETIMPORT R19 52; var19 = 0x3D106989
     158 [-]: LOADK R20 K53; var20 = "Purifier::DomeControl - safe script trigger doesn't exist, exiting script"
     159 [-]: CALL R19 2 1 ; var19(var20)
     160 [-]: RETURN R0 0  ; 
L21: 161 [-]: JUMPIFNOTLT R6 R3 L23; goto L23 if var6 >= var135996
     162 [-]: GETUPVAL R19 2; var19 = upvalues[2]
     163 [-]: JUMPIFNOT R19 L22; goto L22 if not var19
     164 [-]: LOADN R10 0  ; var10 = 0
     165 [-]: LOADB R19 0  ; var19 = false
     166 [-]: SETUPVAL R19 2; upvalues[19] = var2
     167 [-]: JUMP L23     ; goto L23
L22: 168 [-]: GETIMPORT R19 55; var19 = 0x67652851
     169 [-]: CALL R19 1 2 ; var19 = var19()
     170 [-]: ADD R10 R10 R19; var10 = var10 + var19
L23: 171 [-]: GETUPVAL R20 3; var20 = upvalues[3]
     172 [-]: GETTABLEKS R19 R20 K56; var19 = var20[0x06D055F9]
     173 [-]: LOADB R20 0  ; var20 = false
     174 [-]: LOADN R21 30 ; var21 = 30
     175 [-]: GETIMPORT R22 58; var22 = 0xF21F0C47
     176 [-]: CALL R19 4 2 ; var19 = var19(var20, var21, var22)
     177 [-]: JUMPIFNOTLT R19 R10 L26; goto L26 if var19 >= var1512225
     178 [-]: GETIMPORT R19 23; var19 = 0x2A934C50
     179 [-]: JUMPIF R19 L26; goto L26 if var19
     180 [-]: GETIMPORT R19 32; var19 = 0x89326C93
     181 [-]: NAMECALL R19 R19 K44; var20 = var19; var19 = var19[0x18D05D30]
     182 [-]: CALL R19 2 2 ; var19 = var19(var20)
     183 [-]: JUMPIFNOT R19 L24; goto L24 if not var19
     184 [-]: LOADK R21 K59; var21 = "Decrement"
     185 [-]: NAMECALL R19 R2 K60; var20 = var2; var19 = var2[0x8EB2112D]
     186 [-]: CALL R19 3 1 ; var19(var20, var21)
L24: 187 [-]: MOVE R4 R3   ; var4 = var3
     188 [-]: SUBK R19 R4 K61; var19 = var4 - 1
     189 [-]: JUMPIFNOTLT R6 R19 L25; goto L25 if var6 >= var3805985
     190 [-]: GETIMPORT R19 58; var19 = 0xF21F0C47
     191 [-]: SUBK R10 R19 K62; var10 = var19 - 5
     192 [-]: JUMP L26     ; goto L26
L25: 193 [-]: LOADN R10 0  ; var10 = 0
L26: 194 [-]: NAMECALL R19 R2 K14; var20 = var2; var19 = var2[0x2E333568]
     195 [-]: CALL R19 2 2 ; var19 = var19(var20)
     196 [-]: MOVE R3 R19  ; var3 = var19
     197 [-]: JUMPIF R18 L28; goto L28 if var18
     198 [-]: NAMECALL R19 R2 K63; var20 = var2; var19 = var2[0xDAB60FC5]
     199 [-]: CALL R19 2 2 ; var19 = var19(var20)
     200 [-]: JUMPIFNOTEQ R3 R19 L27; goto L27 if var3 ~= var-1241443508
     201 [-]: NAMECALL R19 R1 K48; var20 = var1; var19 = var1[0xF4E253B6]
     202 [-]: CALL R19 2 1 ; var19(var20)
     203 [-]: JUMP L28     ; goto L28
L27: 204 [-]: NAMECALL R19 R1 K64; var20 = var1; var19 = var1[0xF37943FF]
     205 [-]: CALL R19 2 2 ; var19 = var19(var20)
     206 [-]: JUMPIF R19 L28; goto L28 if var19
     207 [-]: NAMECALL R19 R1 K20; var20 = var1; var19 = var1[0x383D2E7D]
     208 [-]: CALL R19 2 1 ; var19(var20)
L28: 209 [-]: GETIMPORT R19 66; var19 = 0xF2D33C61
     210 [-]: ADDK R20 R3 K61; var20 = var3 + 1
     211 [-]: GETTABLE R14 R19 R20; var14 = var19[var20]
     212 [-]: NAMECALL R19 R0 K21; var20 = var0; var19 = var0[0x65D389CB]
     213 [-]: CALL R19 2 2 ; var19 = var19(var20)
     214 [-]: MOVE R8 R19  ; var8 = var19
     215 [-]: GETIMPORT R19 68; var19 = 0x2008C325
     216 [-]: ADDK R20 R3 K61; var20 = var3 + 1
     217 [-]: GETTABLE R15 R19 R20; var15 = var19[var20]
     218 [-]: NAMECALL R19 R12 K30; var20 = var12; var19 = var12[0xDE89CF48]
     219 [-]: CALL R19 2 2 ; var19 = var19(var20)
     220 [-]: MOVE R17 R19 ; var17 = var19
     221 [-]: JUMPXEQKN R16 K47 L33 NOT; 
     222 [-]: JUMPIFEQ R17 R15 L33; goto L33 if var17 == var1119278
     223 [-]: MOVE R20 R17 ; var20 = var17
     224 [-]: MOVE R21 R15 ; var21 = var15
     225 [-]: SUB R23 R20 R21; var23 = var20 - var21
     226 [-]: FASTCALL1 2 R23 L29; 
     227 [-]: GETIMPORT R22 71; var22 = 0x5BCED4C4[0xE4A5B3CA]
     228 [-]: CALL R22 2 2 ; var22 = var22(var23)
L29: 229 [-]: LOADK R23 K72; var23 = 0.0099999997764825821
     230 [-]: JUMPIFLT R22 R23 L30; goto L30 if var22 < var16782086
     231 [-]: LOADB R19 0 +1; var19 = false
L30: 232 [-]: LOADB R19 1  ; var19 = true
L31: 233 [-]: JUMPIFNOT R19 L32; goto L32 if not var19
     234 [-]: MOVE R13 R15 ; var13 = var15
L32: 235 [-]: MOVE R21 R13 ; var21 = var13
     236 [-]: NAMECALL R19 R11 K73; var20 = var11; var19 = var11[0x5004BE24]
     237 [-]: CALL R19 3 1 ; var19(var20, var21)
     238 [-]: MOVE R21 R13 ; var21 = var13
     239 [-]: NAMECALL R19 R12 K73; var20 = var12; var19 = var12[0x5004BE24]
     240 [-]: CALL R19 3 1 ; var19(var20, var21)
L33: 241 [-]: MOVE R20 R8  ; var20 = var8
     242 [-]: MOVE R21 R14 ; var21 = var14
     243 [-]: SUB R23 R20 R21; var23 = var20 - var21
     244 [-]: FASTCALL1 2 R23 L34; 
     245 [-]: GETIMPORT R22 71; var22 = 0x5BCED4C4[0xE4A5B3CA]
     246 [-]: CALL R22 2 2 ; var22 = var22(var23)
L34: 247 [-]: LOADK R23 K72; var23 = 0.0099999997764825821
     248 [-]: JUMPIFLT R22 R23 L35; goto L35 if var22 < var16782086
     249 [-]: LOADB R19 0 +1; var19 = false
L35: 250 [-]: LOADB R19 1  ; var19 = true
L36: 251 [-]: JUMPIFNOT R19 L37; goto L37 if not var19
     252 [-]: MOVE R8 R14  ; var8 = var14
     253 [-]: MOVE R21 R14 ; var21 = var14
     254 [-]: NAMECALL R19 R0 K74; var20 = var0; var19 = var0[0x2D9BA74F]
     255 [-]: CALL R19 3 1 ; var19(var20, var21)
L37: 256 [-]: JUMPIFNOTEQ R8 R14 L38; goto L38 if var8 ~= var7409964
     257 [-]: JUMPIFEQ R17 R15 L48; goto L48 if var17 == var66822
L38: 258 [-]: LOADB R5 1   ; var5 = true
     259 [-]: GETIMPORT R19 55; var19 = 0x67652851
     260 [-]: CALL R19 1 2 ; var19 = var19()
     261 [-]: SUB R9 R9 R19; var9 = var9 - var19
     262 [-]: LOADN R19 0  ; var19 = 0
     263 [-]: JUMPIFNOTLE R9 R19 L49; goto L49 if var9 > var4985633
     264 [-]: GETIMPORT R19 76; var19 = 0xAC64F27B
     265 [-]: ADD R9 R9 R19; var9 = var9 + var19
     266 [-]: MOVE R20 R8  ; var20 = var8
     267 [-]: MOVE R21 R14 ; var21 = var14
     268 [-]: GETIMPORT R22 78; var22 = 0x14C77C66
     269 [-]: GETIMPORT R23 80; var23 = 0xABB631DC
     270 [-]: LOADNIL R24  ; var24 = nil
     271 [-]: JUMPIFNOTLT R20 R21 L40; goto L40 if var20 >= var5381153
     272 [-]: GETIMPORT R28 82; var28 = 0x9BAFFFE3
     273 [-]: LOADN R29 0  ; var29 = 0
     274 [-]: LOADN R30 1  ; var30 = 1
     275 [-]: GETIMPORT R32 76; var32 = 0xAC64F27B
     276 [-]: MUL R31 R22 R32; var31 = var22 * var32
     277 [-]: CALL R28 4 2 ; var28 = var28(var29, var30, var31)
     278 [-]: ADD R27 R20 R28; var27 = var20 + var28
     279 [-]: FASTCALL2 19 R21 R27 L39; 
     280 [-]: MOVE R26 R21 ; var26 = var21
     281 [-]: GETIMPORT R25 84; var25 = 0x5BCED4C4[0xAC1B386A]
     282 [-]: CALL R25 3 2 ; var25 = var25(var26, var27)
L39: 283 [-]: MOVE R24 R25 ; var24 = var25
     284 [-]: JUMP L42     ; goto L42
L40: 285 [-]: GETIMPORT R28 82; var28 = 0x9BAFFFE3
     286 [-]: LOADN R29 0  ; var29 = 0
     287 [-]: LOADN R30 1  ; var30 = 1
     288 [-]: GETIMPORT R32 76; var32 = 0xAC64F27B
     289 [-]: MUL R31 R23 R32; var31 = var23 * var32
     290 [-]: CALL R28 4 2 ; var28 = var28(var29, var30, var31)
     291 [-]: SUB R27 R20 R28; var27 = var20 - var28
     292 [-]: FASTCALL2 18 R21 R27 L41; 
     293 [-]: MOVE R26 R21 ; var26 = var21
     294 [-]: GETIMPORT R25 86; var25 = 0x5BCED4C4[0xB62ECFE0]
     295 [-]: CALL R25 3 2 ; var25 = var25(var26, var27)
L41: 296 [-]: MOVE R24 R25 ; var24 = var25
L42: 297 [-]: MOVE R19 R24 ; var19 = var24
     298 [-]: MOVE R22 R19 ; var22 = var19
     299 [-]: NAMECALL R20 R0 K74; var21 = var0; var20 = var0[0x2D9BA74F]
     300 [-]: CALL R20 3 1 ; var20(var21, var22)
     301 [-]: MOVE R20 R13 ; var20 = var13
     302 [-]: MOVE R21 R15 ; var21 = var15
     303 [-]: GETIMPORT R22 88; var22 = 0xF384A1C0
     304 [-]: GETIMPORT R23 90; var23 = 0x7CB54246
     305 [-]: LOADNIL R24  ; var24 = nil
     306 [-]: JUMPIFNOTLT R20 R21 L44; goto L44 if var20 >= var5381153
     307 [-]: GETIMPORT R28 82; var28 = 0x9BAFFFE3
     308 [-]: LOADN R29 0  ; var29 = 0
     309 [-]: LOADN R30 1  ; var30 = 1
     310 [-]: GETIMPORT R32 76; var32 = 0xAC64F27B
     311 [-]: MUL R31 R22 R32; var31 = var22 * var32
     312 [-]: CALL R28 4 2 ; var28 = var28(var29, var30, var31)
     313 [-]: ADD R27 R20 R28; var27 = var20 + var28
     314 [-]: FASTCALL2 19 R21 R27 L43; 
     315 [-]: MOVE R26 R21 ; var26 = var21
     316 [-]: GETIMPORT R25 84; var25 = 0x5BCED4C4[0xAC1B386A]
     317 [-]: CALL R25 3 2 ; var25 = var25(var26, var27)
L43: 318 [-]: MOVE R24 R25 ; var24 = var25
     319 [-]: JUMP L46     ; goto L46
L44: 320 [-]: GETIMPORT R28 82; var28 = 0x9BAFFFE3
     321 [-]: LOADN R29 0  ; var29 = 0
     322 [-]: LOADN R30 1  ; var30 = 1
     323 [-]: GETIMPORT R32 76; var32 = 0xAC64F27B
     324 [-]: MUL R31 R23 R32; var31 = var23 * var32
     325 [-]: CALL R28 4 2 ; var28 = var28(var29, var30, var31)
     326 [-]: SUB R27 R20 R28; var27 = var20 - var28
     327 [-]: FASTCALL2 18 R21 R27 L45; 
     328 [-]: MOVE R26 R21 ; var26 = var21
     329 [-]: GETIMPORT R25 86; var25 = 0x5BCED4C4[0xB62ECFE0]
     330 [-]: CALL R25 3 2 ; var25 = var25(var26, var27)
L45: 331 [-]: MOVE R24 R25 ; var24 = var25
L46: 332 [-]: MOVE R13 R24 ; var13 = var24
     333 [-]: JUMPXEQKN R16 K47 L47 NOT; 
     334 [-]: JUMPIFNOTLT R15 R13 L47; goto L47 if var15 >= var331824
     335 [-]: LOADN R16 5  ; var16 = 5
     336 [-]: JUMP L49     ; goto L49
L47: 337 [-]: LOADN R20 0  ; var20 = 0
     338 [-]: JUMPIFNOTLT R20 R16 L49; goto L49 if var20 >= var1024462850
     339 [-]: SUBK R16 R16 K61; var16 = var16 - 1
     340 [-]: JUMP L49     ; goto L49
L48: 341 [-]: LOADB R5 0   ; var5 = false
L49: 342 [-]: GETIMPORT R19 3; var19 = 0xCBD666E1
     343 [-]: LOADN R20 0  ; var20 = 0
     344 [-]: CALL R19 2 1 ; var19(var20)
     345 [-]: JUMPBACK L16 ; goto L16
L50: 346 [-]: RETURN R0 0  ; 


; Name:            
; Defined at line: 408
; #Upvalues:       0
; #Parameters:     2
; Is_vararg:       0
; Max Stack Size:  8

       0 [-]: LOADN R4 1   ; var4 = 1
       1 [-]: LENGTH R2 R0 ; var2 = #var0
       2 [-]: LOADN R3 1   ; var3 = 1
       3 [-]: FORNPREP R2 L3; nforprep start - [escape at L3] -- var2 = iterator
L 0:   4 [-]: GETTABLE R6 R0 R4; var6 = var0[var4]
       5 [-]: FASTCALL1 64 R6 L1; 
       6 [-]: GETIMPORT R5 1; var5 = 0x7B998233
       7 [-]: CALL R5 2 2  ; var5 = var5(var6)
L 1:   8 [-]: JUMPIF R5 L2 ; goto L2 if var5
       9 [-]: GETTABLE R5 R0 R4; var5 = var0[var4]
      10 [-]: MOVE R7 R1   ; var7 = var1
      11 [-]: NAMECALL R5 R5 K2; var6 = var5; var5 = var5[0x13D5D3FB]
      12 [-]: CALL R5 3 2  ; var5 = var5(var6, var7)
      13 [-]: JUMPIFNOT R5 L2; goto L2 if not var5
      14 [-]: LOADB R5 1   ; var5 = true
      15 [-]: RETURN R5 1  ; 
L 2:  16 [-]: FORNLOOP R2 L0; nforloop end - iterate + goto L0
L 3:  17 [-]: LOADB R2 0   ; var2 = false
      18 [-]: RETURN R2 1  ; 


; Name:            
; Defined at line: 419
; #Upvalues:       8
; #Parameters:     1
; Is_vararg:       0
; Max Stack Size:  12

       0 [-]: GETIMPORT R1 1; var1 = 0xCBD666E1
       1 [-]: LOADN R2 2   ; var2 = 2
       2 [-]: CALL R1 2 1  ; var1(var2)
L 0:   3 [-]: GETUPVAL R2 0; var2 = upvalues[0]
       4 [-]: FASTCALL1 64 R2 L1; 
       5 [-]: GETIMPORT R1 3; var1 = 0x7B998233
       6 [-]: CALL R1 2 2  ; var1 = var1(var2)
L 1:   7 [-]: JUMPIFNOT R1 L2; goto L2 if not var1
       8 [-]: GETIMPORT R1 1; var1 = 0xCBD666E1
       9 [-]: LOADN R2 0   ; var2 = 0
      10 [-]: CALL R1 2 1  ; var1(var2)
      11 [-]: GETIMPORT R1 5; var1 = 0xBE190284
      12 [-]: SETUPVAL R1 0; upvalues[1] = var0
      13 [-]: JUMPBACK L0  ; goto L0
L 2:  14 [-]: GETUPVAL R3 1; var3 = upvalues[1]
      15 [-]: NAMECALL R1 R0 K6; var2 = var0; var1 = var0[0xC9F6A7D7]
      16 [-]: CALL R1 3 2  ; var1 = var1(var2, var3)
      17 [-]: NAMECALL R2 R0 K7; var3 = var0; var2 = var0[0xD2715720]
      18 [-]: CALL R2 2 2  ; var2 = var2(var3)
      19 [-]: LOADB R3 0   ; var3 = false
      20 [-]: LOADNIL R4   ; var4 = nil
      21 [-]: LOADN R5 0   ; var5 = 0
      22 [-]: NAMECALL R6 R0 K8; var7 = var0; var6 = var0[0x22DA1852]
      23 [-]: CALL R6 2 2  ; var6 = var6(var7)
      24 [-]: GETIMPORT R7 10; var7 = 0x0469F296
      25 [-]: LOADK R8 K11 ; var8 = "WeakpointTwo"
      26 [-]: CALL R7 2 2  ; var7 = var7(var8)
      27 [-]: JUMPIFNOTEQ R6 R7 L5; goto L5 if var6 ~= var1852
L 3:  28 [-]: GETUPVAL R7 0; var7 = upvalues[0]
      29 [-]: GETUPVAL R9 2; var9 = upvalues[2]
      30 [-]: LOADN R10 1  ; var10 = 1
      31 [-]: NAMECALL R7 R7 K12; var8 = var7; var7 = var7[0x0EB34C69]
      32 [-]: CALL R7 4 2  ; var7 = var7(var8, var9, var10)
      33 [-]: LOADN R8 3   ; var8 = 3
      34 [-]: JUMPIFNOTLT R7 R8 L4; goto L4 if var7 >= var67361
      35 [-]: GETIMPORT R7 1; var7 = 0xCBD666E1
      36 [-]: LOADK R8 K13 ; var8 = 0.5
      37 [-]: CALL R7 2 1  ; var7(var8)
      38 [-]: JUMPBACK L3  ; goto L3
L 4:  39 [-]: GETIMPORT R7 15; var7 = 0x3D106989
      40 [-]: LOADK R8 K16 ; var8 = "Second Weakpoint Activated"
      41 [-]: CALL R7 2 1  ; var7(var8)
      42 [-]: JUMP L9      ; goto L9
L 5:  43 [-]: GETIMPORT R7 10; var7 = 0x0469F296
      44 [-]: LOADK R8 K17 ; var8 = "WeakpointThree"
      45 [-]: CALL R7 2 2  ; var7 = var7(var8)
      46 [-]: JUMPIFNOTEQ R6 R7 L8; goto L8 if var6 ~= var1852
L 6:  47 [-]: GETUPVAL R7 0; var7 = upvalues[0]
      48 [-]: GETUPVAL R9 2; var9 = upvalues[2]
      49 [-]: LOADN R10 1  ; var10 = 1
      50 [-]: NAMECALL R7 R7 K12; var8 = var7; var7 = var7[0x0EB34C69]
      51 [-]: CALL R7 4 2  ; var7 = var7(var8, var9, var10)
      52 [-]: LOADN R8 5   ; var8 = 5
      53 [-]: JUMPIFNOTLT R7 R8 L7; goto L7 if var7 >= var67361
      54 [-]: GETIMPORT R7 1; var7 = 0xCBD666E1
      55 [-]: LOADK R8 K13 ; var8 = 0.5
      56 [-]: CALL R7 2 1  ; var7(var8)
      57 [-]: JUMPBACK L6  ; goto L6
L 7:  58 [-]: GETIMPORT R7 15; var7 = 0x3D106989
      59 [-]: LOADK R8 K18 ; var8 = "Third Weakpoint Activated"
      60 [-]: CALL R7 2 1  ; var7(var8)
      61 [-]: JUMP L9      ; goto L9
L 8:  62 [-]: GETIMPORT R7 15; var7 = 0x3D106989
      63 [-]: LOADK R8 K19 ; var8 = "First Weakpoint Activated"
      64 [-]: CALL R7 2 1  ; var7(var8)
L 9:  65 [-]: FASTCALL1 64 R0 L10; 
      66 [-]: MOVE R8 R0   ; var8 = var0
      67 [-]: GETIMPORT R7 3; var7 = 0x7B998233
      68 [-]: CALL R7 2 2  ; var7 = var7(var8)
L10:  69 [-]: JUMPIF R7 L22; goto L22 if var7
      70 [-]: NAMECALL R7 R0 K7; var8 = var0; var7 = var0[0xD2715720]
      71 [-]: CALL R7 2 2  ; var7 = var7(var8)
      72 [-]: LOADN R8 0   ; var8 = 0
      73 [-]: JUMPIFNOTLT R8 R7 L22; goto L22 if var8 >= var1378081
      74 [-]: GETIMPORT R7 21; var7 = 0x89326C93
      75 [-]: GETUPVAL R9 3; var9 = upvalues[3]
      76 [-]: NAMECALL R10 R0 K22; var11 = var0; var10 = var0[0xD1586535]
      77 [-]: CALL R10 2 0 ; var10, ... = var10(var11)
      78 [-]: NAMECALL R7 R7 K23; var8 = var7; var7 = var7[0xC7B81E8D]
      79 [-]: CALL R7 0 2  ; var7 = var7(var8, ...)
      80 [-]: MOVE R4 R7   ; var4 = var7
      81 [-]: FASTCALL1 64 R4 L11; 
      82 [-]: MOVE R8 R4   ; var8 = var4
      83 [-]: GETIMPORT R7 3; var7 = 0x7B998233
      84 [-]: CALL R7 2 2  ; var7 = var7(var8)
L11:  85 [-]: JUMPIF R7 L21; goto L21 if var7
      86 [-]: MOVE R9 R0   ; var9 = var0
      87 [-]: NAMECALL R7 R4 K24; var8 = var4; var7 = var4[0xBEBAD19F]
      88 [-]: CALL R7 3 2  ; var7 = var7(var8, var9)
      89 [-]: MOVE R5 R7   ; var5 = var7
      90 [-]: NAMECALL R7 R4 K25; var8 = var4; var7 = var4[0xDE89CF48]
      91 [-]: CALL R7 2 2  ; var7 = var7(var8)
      92 [-]: JUMPIFNOTLT R7 R5 L17; goto L17 if var7 >= var50348093
      93 [-]: FASTCALL1 64 R0 L12; 
      94 [-]: MOVE R8 R0   ; var8 = var0
      95 [-]: GETIMPORT R7 3; var7 = 0x7B998233
      96 [-]: CALL R7 2 2  ; var7 = var7(var8)
L12:  97 [-]: JUMPIF R7 L13; goto L13 if var7
      98 [-]: NAMECALL R7 R0 K7; var8 = var0; var7 = var0[0xD2715720]
      99 [-]: CALL R7 2 2  ; var7 = var7(var8)
     100 [-]: LOADN R8 0   ; var8 = 0
     101 [-]: JUMPIFNOTLT R8 R7 L13; goto L13 if var8 >= var133422
     102 [-]: MOVE R9 R2   ; var9 = var2
     103 [-]: NAMECALL R7 R0 K26; var8 = var0; var7 = var0[0x014DB014]
     104 [-]: CALL R7 3 1  ; var7(var8, var9)
L13: 105 [-]: JUMPIFNOT R3 L21; goto L21 if not var3
     106 [-]: GETIMPORT R7 15; var7 = 0x3D106989
     107 [-]: LOADK R8 K27 ; var8 = "                WEAKPOINT HAS BEEN DEACTIVATED!!!"
     108 [-]: CALL R7 2 1  ; var7(var8)
     109 [-]: GETUPVAL R9 4; var9 = upvalues[4]
     110 [-]: LOADB R10 1  ; var10 = true
     111 [-]: LOADB R11 0  ; var11 = false
     112 [-]: NAMECALL R7 R0 K28; var8 = var0; var7 = var0[0x5D985C7E]
     113 [-]: CALL R7 5 1  ; var7(var8, var9, var10, var11)
     114 [-]: GETUPVAL R9 5; var9 = upvalues[5]
     115 [-]: LOADB R10 0  ; var10 = false
     116 [-]: LOADB R11 1  ; var11 = true
     117 [-]: NAMECALL R7 R0 K28; var8 = var0; var7 = var0[0x5D985C7E]
     118 [-]: CALL R7 5 1  ; var7(var8, var9, var10, var11)
     119 [-]: FASTCALL1 64 R1 L14; 
     120 [-]: MOVE R8 R1   ; var8 = var1
     121 [-]: GETIMPORT R7 3; var7 = 0x7B998233
     122 [-]: CALL R7 2 2  ; var7 = var7(var8)
L14: 123 [-]: JUMPIF R7 L15; goto L15 if var7
     124 [-]: NAMECALL R7 R1 K29; var8 = var1; var7 = var1[0xF4E253B6]
     125 [-]: CALL R7 2 1  ; var7(var8)
L15: 126 [-]: GETIMPORT R7 21; var7 = 0x89326C93
     127 [-]: NAMECALL R7 R7 K30; var8 = var7; var7 = var7[0x18D05D30]
     128 [-]: CALL R7 2 2  ; var7 = var7(var8)
     129 [-]: JUMPIFNOT R7 L16; goto L16 if not var7
     130 [-]: NAMECALL R7 R0 K31; var8 = var0; var7 = var0[0xE92524C3]
     131 [-]: CALL R7 2 1  ; var7(var8)
L16: 132 [-]: LOADB R3 0   ; var3 = false
     133 [-]: JUMP L21     ; goto L21
L17: 134 [-]: NAMECALL R7 R4 K25; var8 = var4; var7 = var4[0xDE89CF48]
     135 [-]: CALL R7 2 2  ; var7 = var7(var8)
     136 [-]: JUMPIFNOTLT R5 R7 L21; goto L21 if var5 >= var2294605
     137 [-]: JUMPIF R3 L21; goto L21 if var3
     138 [-]: GETIMPORT R7 15; var7 = 0x3D106989
     139 [-]: LOADK R8 K32 ; var8 = "             WEAKPOINT HAS BEEN ACTIVATED!!"
     140 [-]: CALL R7 2 1  ; var7(var8)
     141 [-]: GETUPVAL R9 6; var9 = upvalues[6]
     142 [-]: LOADB R10 1  ; var10 = true
     143 [-]: LOADB R11 0  ; var11 = false
     144 [-]: NAMECALL R7 R0 K28; var8 = var0; var7 = var0[0x5D985C7E]
     145 [-]: CALL R7 5 1  ; var7(var8, var9, var10, var11)
     146 [-]: GETUPVAL R9 7; var9 = upvalues[7]
     147 [-]: LOADB R10 0  ; var10 = false
     148 [-]: LOADB R11 1  ; var11 = true
     149 [-]: NAMECALL R7 R0 K28; var8 = var0; var7 = var0[0x5D985C7E]
     150 [-]: CALL R7 5 1  ; var7(var8, var9, var10, var11)
     151 [-]: GETIMPORT R7 21; var7 = 0x89326C93
     152 [-]: NAMECALL R7 R7 K30; var8 = var7; var7 = var7[0x18D05D30]
     153 [-]: CALL R7 2 2  ; var7 = var7(var8)
     154 [-]: JUMPIFNOT R7 L18; goto L18 if not var7
     155 [-]: NAMECALL R7 R0 K33; var8 = var0; var7 = var0[0x04347778]
     156 [-]: CALL R7 2 1  ; var7(var8)
L18: 157 [-]: FASTCALL1 64 R1 L19; 
     158 [-]: MOVE R8 R1   ; var8 = var1
     159 [-]: GETIMPORT R7 3; var7 = 0x7B998233
     160 [-]: CALL R7 2 2  ; var7 = var7(var8)
L19: 161 [-]: JUMPIF R7 L20; goto L20 if var7
     162 [-]: NAMECALL R7 R1 K34; var8 = var1; var7 = var1[0x383D2E7D]
     163 [-]: CALL R7 2 1  ; var7(var8)
L20: 164 [-]: LOADB R3 1   ; var3 = true
L21: 165 [-]: GETIMPORT R7 1; var7 = 0xCBD666E1
     166 [-]: LOADK R8 K35 ; var8 = 0.30000001192092896
     167 [-]: CALL R7 2 1  ; var7(var8)
     168 [-]: JUMPBACK L9  ; goto L9
L22: 169 [-]: RETURN R0 0  ; 


; Name:            
; Defined at line: 486
; #Upvalues:       0
; #Parameters:     1
; Is_vararg:       0
; Max Stack Size:  5

       0 [-]: GETIMPORT R1 1; var1 = 0x89326C93
       1 [-]: NAMECALL R1 R1 K2; var2 = var1; var1 = var1[0x18D05D30]
       2 [-]: CALL R1 2 2  ; var1 = var1(var2)
       3 [-]: JUMPIFNOT R1 L0; goto L0 if not var1
       4 [-]: LOADB R3 0   ; var3 = false
       5 [-]: LOADB R4 0   ; var4 = false
       6 [-]: NAMECALL R1 R0 K3; var2 = var0; var1 = var0[0x5710748F]
       7 [-]: CALL R1 4 1  ; var1(var2, var3, var4)
L 0:   8 [-]: RETURN R0 0  ; 


; Name:            
; Defined at line: 492
; #Upvalues:       4
; #Parameters:     1
; Is_vararg:       0
; Max Stack Size:  8

       0 [-]: NAMECALL R1 R0 K0; var2 = var0; var1 = var0[0x5E8B6A40]
       1 [-]: CALL R1 2 2  ; var1 = var1(var2)
       2 [-]: JUMPIFNOT R1 L1; goto L1 if not var1
       3 [-]: GETIMPORT R1 2; var1 = _T
       4 [-]: LOADN R3 0   ; var3 = 0
       5 [-]: GETIMPORT R5 4; var5 = _T["Timer"]
       6 [-]: GETIMPORT R6 6; var6 = 0x79A340EC
       7 [-]: SUB R4 R5 R6 ; var4 = var5 - var6
       8 [-]: FASTCALL2 18 R3 R4 L0; 
       9 [-]: GETIMPORT R2 9; var2 = 0x5BCED4C4[0xB62ECFE0]
      10 [-]: CALL R2 3 2  ; var2 = var2(var3, var4)
L 0:  11 [-]: SETTABLEKS R2 R1 K3; var2["Timer"] = var1
      12 [-]: GETUPVAL R1 0; var1 = upvalues[0]
      13 [-]: GETUPVAL R3 1; var3 = upvalues[1]
      14 [-]: GETIMPORT R4 4; var4 = _T["Timer"]
      15 [-]: NAMECALL R1 R1 K10; var2 = var1; var1 = var1[0x751F061D]
      16 [-]: CALL R1 4 1  ; var1(var2, var3, var4)
      17 [-]: RETURN R0 0  ; 
L 1:  18 [-]: GETUPVAL R1 0; var1 = upvalues[0]
      19 [-]: GETUPVAL R3 1; var3 = upvalues[1]
      20 [-]: LOADN R4 0   ; var4 = 0
      21 [-]: NAMECALL R1 R1 K10; var2 = var1; var1 = var1[0x751F061D]
      22 [-]: CALL R1 4 1  ; var1(var2, var3, var4)
      23 [-]: GETIMPORT R1 2; var1 = _T
      24 [-]: LOADN R2 0   ; var2 = 0
      25 [-]: SETTABLEKS R2 R1 K3; var2["Timer"] = var1
      26 [-]: LOADB R3 1   ; var3 = true
      27 [-]: NAMECALL R1 R0 K11; var2 = var0; var1 = var0[0x113A6664]
      28 [-]: CALL R1 3 1  ; var1(var2, var3)
      29 [-]: GETUPVAL R1 2; var1 = upvalues[2]
      30 [-]: NAMECALL R1 R1 K12; var2 = var1; var1 = var1[0x56C01834]
      31 [-]: CALL R1 2 2  ; var1 = var1(var2)
      32 [-]: JUMPIFNOT R1 L2; goto L2 if not var1
      33 [-]: GETUPVAL R3 2; var3 = upvalues[2]
      34 [-]: NAMECALL R1 R0 K13; var2 = var0; var1 = var0[0xB2532845]
      35 [-]: CALL R1 3 1  ; var1(var2, var3)
L 2:  36 [-]: GETIMPORT R1 15; var1 = 0x0469F296
      37 [-]: LOADK R2 K16 ; var2 = "DoPerch"
      38 [-]: CALL R1 2 2  ; var1 = var1(var2)
      39 [-]: GETIMPORT R2 18; var2 = 0x89326C93
      40 [-]: GETIMPORT R4 15; var4 = 0x0469F296
      41 [-]: LOADK R5 K19 ; var5 = "ExhaustOff"
      42 [-]: CALL R4 2 2  ; var4 = var4(var5)
      43 [-]: NAMECALL R5 R0 K20; var6 = var0; var5 = var0[0xD1586535]
      44 [-]: CALL R5 2 0  ; var5, ... = var5(var6)
      45 [-]: NAMECALL R2 R2 K21; var3 = var2; var2 = var2[0xC7B81E8D]
      46 [-]: CALL R2 0 2  ; var2 = var2(var3, ...)
      47 [-]: GETIMPORT R3 18; var3 = 0x89326C93
      48 [-]: GETIMPORT R5 15; var5 = 0x0469F296
      49 [-]: LOADK R6 K22 ; var6 = "ExhaustOn"
      50 [-]: CALL R5 2 2  ; var5 = var5(var6)
      51 [-]: NAMECALL R6 R0 K20; var7 = var0; var6 = var0[0xD1586535]
      52 [-]: CALL R6 2 0  ; var6, ... = var6(var7)
      53 [-]: NAMECALL R3 R3 K21; var4 = var3; var3 = var3[0xC7B81E8D]
      54 [-]: CALL R3 0 2  ; var3 = var3(var4, ...)
      55 [-]: LOADK R6 K23 ; var6 = "TriggerPort"
      56 [-]: NAMECALL R4 R2 K24; var5 = var2; var4 = var2[0x8EB2112D]
      57 [-]: CALL R4 3 1  ; var4(var5, var6)
      58 [-]: LOADN R6 0   ; var6 = 0
      59 [-]: NAMECALL R4 R0 K25; var5 = var0; var4 = var0[0xF1C72F4A]
      60 [-]: CALL R4 3 1  ; var4(var5, var6)
L 3:  61 [-]: NAMECALL R4 R0 K0; var5 = var0; var4 = var0[0x5E8B6A40]
      62 [-]: CALL R4 2 2  ; var4 = var4(var5)
      63 [-]: JUMPIFNOT R4 L4; goto L4 if not var4
      64 [-]: GETIMPORT R4 27; var4 = 0xCBD666E1
      65 [-]: LOADN R5 0   ; var5 = 0
      66 [-]: CALL R4 2 1  ; var4(var5)
      67 [-]: JUMPBACK L3  ; goto L3
L 4:  68 [-]: GETIMPORT R4 29; var4 = _T["GolemAttached"]
      69 [-]: JUMPIFNOT R4 L7; goto L7 if not var4
      70 [-]: MOVE R6 R1   ; var6 = var1
      71 [-]: NAMECALL R4 R0 K30; var5 = var0; var4 = var0[0xB6A7C46E]
      72 [-]: CALL R4 3 2  ; var4 = var4(var5, var6)
      73 [-]: JUMPIFNOT R4 L7; goto L7 if not var4
      74 [-]: GETUPVAL R4 3; var4 = upvalues[3]
      75 [-]: NAMECALL R4 R4 K12; var5 = var4; var4 = var4[0x56C01834]
      76 [-]: CALL R4 2 2  ; var4 = var4(var5)
      77 [-]: JUMPIFNOT R4 L6; goto L6 if not var4
      78 [-]: GETUPVAL R6 3; var6 = upvalues[3]
      79 [-]: NAMECALL R4 R0 K13; var5 = var0; var4 = var0[0xB2532845]
      80 [-]: CALL R4 3 1  ; var4(var5, var6)
L 5:  81 [-]: GETIMPORT R4 27; var4 = 0xCBD666E1
      82 [-]: LOADN R5 0   ; var5 = 0
      83 [-]: CALL R4 2 1  ; var4(var5)
      84 [-]: GETUPVAL R6 3; var6 = upvalues[3]
      85 [-]: NAMECALL R4 R0 K30; var5 = var0; var4 = var0[0xB6A7C46E]
      86 [-]: CALL R4 3 2  ; var4 = var4(var5, var6)
      87 [-]: JUMPIFNOT R4 L6; goto L6 if not var4
      88 [-]: JUMPBACK L5  ; goto L5
L 6:  89 [-]: LOADK R6 K23 ; var6 = "TriggerPort"
      90 [-]: NAMECALL R4 R3 K24; var5 = var3; var4 = var3[0x8EB2112D]
      91 [-]: CALL R4 3 1  ; var4(var5, var6)
      92 [-]: RETURN R0 0  ; 
L 7:  93 [-]: LOADK R6 K23 ; var6 = "TriggerPort"
      94 [-]: NAMECALL R4 R2 K24; var5 = var2; var4 = var2[0x8EB2112D]
      95 [-]: CALL R4 3 1  ; var4(var5, var6)
      96 [-]: RETURN R0 0  ; 


; Name:            
; Defined at line: 534
; #Upvalues:       3
; #Parameters:     1
; Is_vararg:       0
; Max Stack Size:  9

       0 [-]: GETIMPORT R1 1; var1 = 0x89326C93
       1 [-]: NAMECALL R1 R1 K2; var2 = var1; var1 = var1[0x18D05D30]
       2 [-]: CALL R1 2 2  ; var1 = var1(var2)
       3 [-]: JUMPIFNOT R1 L2; goto L2 if not var1
       4 [-]: GETIMPORT R1 1; var1 = 0x89326C93
       5 [-]: GETIMPORT R3 4; var3 = 0x0469F296
       6 [-]: LOADK R4 K5  ; var4 = "EnableConsole"
       7 [-]: CALL R3 2 2  ; var3 = var3(var4)
       8 [-]: NAMECALL R4 R0 K6; var5 = var0; var4 = var0[0xD1586535]
       9 [-]: CALL R4 2 0  ; var4, ... = var4(var5)
      10 [-]: NAMECALL R1 R1 K7; var2 = var1; var1 = var1[0xC7B81E8D]
      11 [-]: CALL R1 0 2  ; var1 = var1(var2, ...)
      12 [-]: GETIMPORT R2 1; var2 = 0x89326C93
      13 [-]: GETIMPORT R4 4; var4 = 0x0469F296
      14 [-]: LOADK R5 K8  ; var5 = "DisableConsole"
      15 [-]: CALL R4 2 2  ; var4 = var4(var5)
      16 [-]: NAMECALL R5 R0 K6; var6 = var0; var5 = var0[0xD1586535]
      17 [-]: CALL R5 2 0  ; var5, ... = var5(var6)
      18 [-]: NAMECALL R2 R2 K7; var3 = var2; var2 = var2[0xC7B81E8D]
      19 [-]: CALL R2 0 2  ; var2 = var2(var3, ...)
      20 [-]: GETIMPORT R3 1; var3 = 0x89326C93
      21 [-]: GETUPVAL R5 0; var5 = upvalues[0]
      22 [-]: NAMECALL R6 R0 K6; var7 = var0; var6 = var0[0xD1586535]
      23 [-]: CALL R6 2 2  ; var6 = var6(var7)
      24 [-]: LOADN R7 0   ; var7 = 0
      25 [-]: LOADN R8 100 ; var8 = 100
      26 [-]: NAMECALL R3 R3 K9; var4 = var3; var3 = var3[0xF16592C8]
      27 [-]: CALL R3 6 2  ; var3 = var3(var4, var5, var6, var7, var8)
      28 [-]: GETUPVAL R6 1; var6 = upvalues[1]
      29 [-]: NAMECALL R4 R0 K10; var5 = var0; var4 = var0[0xC9F6A7D7]
      30 [-]: CALL R4 3 2  ; var4 = var4(var5, var6)
      31 [-]: LOADB R5 1   ; var5 = true
      32 [-]: LOADK R8 K11 ; var8 = "TriggerPort"
      33 [-]: NAMECALL R6 R1 K12; var7 = var1; var6 = var1[0x8EB2112D]
      34 [-]: CALL R6 3 1  ; var6(var7, var8)
L 0:  35 [-]: JUMPIFNOT R5 L1; goto L1 if not var5
      36 [-]: LOADB R5 0   ; var5 = false
      37 [-]: GETUPVAL R6 2; var6 = upvalues[2]
      38 [-]: MOVE R7 R3   ; var7 = var3
      39 [-]: MOVE R8 R4   ; var8 = var4
      40 [-]: CALL R6 3 2  ; var6 = var6(var7, var8)
      41 [-]: MOVE R5 R6   ; var5 = var6
      42 [-]: GETIMPORT R6 14; var6 = 0xCBD666E1
      43 [-]: LOADN R7 0   ; var7 = 0
      44 [-]: CALL R6 2 1  ; var6(var7)
      45 [-]: JUMPBACK L0  ; goto L0
L 1:  46 [-]: LOADK R8 K11 ; var8 = "TriggerPort"
      47 [-]: NAMECALL R6 R2 K12; var7 = var2; var6 = var2[0x8EB2112D]
      48 [-]: CALL R6 3 1  ; var6(var7, var8)
L 2:  49 [-]: RETURN R0 0  ; 


; Name:            
; Defined at line: 554
; #Upvalues:       1
; #Parameters:     1
; Is_vararg:       0
; Max Stack Size:  7

       0 [-]: NAMECALL R1 R0 K0; var2 = var0; var1 = var0[0xCD73323E]
       1 [-]: CALL R1 2 2  ; var1 = var1(var2)
       2 [-]: NAMECALL R2 R1 K1; var3 = var1; var2 = var1[0x2B54251B]
       3 [-]: CALL R2 2 2  ; var2 = var2(var3)
       4 [-]: FASTCALL1 64 R2 L0; 
       5 [-]: MOVE R4 R2   ; var4 = var2
       6 [-]: GETIMPORT R3 3; var3 = 0x7B998233
       7 [-]: CALL R3 2 2  ; var3 = var3(var4)
L 0:   8 [-]: JUMPIF R3 L2 ; goto L2 if var3
       9 [-]: GETIMPORT R5 5; var5 = gDevourerType
      10 [-]: NAMECALL R3 R2 K6; var4 = var2; var3 = var2[0xF2DEAF69]
      11 [-]: CALL R3 3 2  ; var3 = var3(var4, var5)
      12 [-]: JUMPIFNOT R3 L1; goto L1 if not var3
      13 [-]: GETIMPORT R5 8; var5 = 0x0469F296
      14 [-]: LOADK R6 K9  ; var6 = "DevourControl"
      15 [-]: CALL R5 2 2  ; var5 = var5(var6)
      16 [-]: LOADB R6 0   ; var6 = false
      17 [-]: NAMECALL R3 R2 K10; var4 = var2; var3 = var2[0xD5F7912B]
      18 [-]: CALL R3 4 1  ; var3(var4, var5, var6)
      19 [-]: RETURN R0 0  ; 
L 1:  20 [-]: GETUPVAL R5 0; var5 = upvalues[0]
      21 [-]: NAMECALL R3 R2 K6; var4 = var2; var3 = var2[0xF2DEAF69]
      22 [-]: CALL R3 3 2  ; var3 = var3(var4, var5)
      23 [-]: JUMPIFNOT R3 L3; goto L3 if not var3
      24 [-]: GETIMPORT R5 8; var5 = 0x0469F296
      25 [-]: LOADK R6 K11 ; var6 = "ConsoleControl"
      26 [-]: CALL R5 2 2  ; var5 = var5(var6)
      27 [-]: LOADB R6 0   ; var6 = false
      28 [-]: NAMECALL R3 R2 K10; var4 = var2; var3 = var2[0xD5F7912B]
      29 [-]: CALL R3 4 1  ; var3(var4, var5, var6)
      30 [-]: RETURN R0 0  ; 
L 2:  31 [-]: GETIMPORT R3 13; var3 = 0x3D106989
      32 [-]: LOADK R4 K14 ; var4 = "     parent is null"
      33 [-]: CALL R3 2 1  ; var3(var4)
L 3:  34 [-]: RETURN R0 0  ; 


; Name:            
; Defined at line: 569
; #Upvalues:       3
; #Parameters:     1
; Is_vararg:       0
; Max Stack Size:  11

       0 [-]: GETIMPORT R1 1; var1 = 0x89326C93
       1 [-]: GETUPVAL R3 0; var3 = upvalues[0]
       2 [-]: NAMECALL R1 R1 K2; var2 = var1; var1 = var1[0xC7FCADA9]
       3 [-]: CALL R1 3 2  ; var1 = var1(var2, var3)
       4 [-]: LOADN R4 1   ; var4 = 1
       5 [-]: LENGTH R2 R1 ; var2 = #var1
       6 [-]: LOADN R3 1   ; var3 = 1
       7 [-]: FORNPREP R2 L1; nforprep start - [escape at L1] -- var2 = iterator
L 0:   8 [-]: GETIMPORT R5 4; var5 = 0x11A19C5E
       9 [-]: GETTABLE R6 R1 R4; var6 = var1[var4]
      10 [-]: LOADK R7 K5  ; var7 = "OnTouched"
      11 [-]: CALL R5 3 1  ; var5(var6, var7)
      12 [-]: FORNLOOP R2 L0; nforloop end - iterate + goto L0
L 1:  13 [-]: GETIMPORT R2 1; var2 = 0x89326C93
      14 [-]: GETIMPORT R4 7; var4 = gDevourerType
      15 [-]: NAMECALL R2 R2 K8; var3 = var2; var2 = var2[0xFB669000]
      16 [-]: CALL R2 3 2  ; var2 = var2(var3, var4)
      17 [-]: LOADN R5 1   ; var5 = 1
      18 [-]: LENGTH R3 R2 ; var3 = #var2
      19 [-]: LOADN R4 1   ; var4 = 1
      20 [-]: FORNPREP R3 L5; nforprep start - [escape at L5] -- var3 = iterator
L 2:  21 [-]: GETTABLE R6 R2 R5; var6 = var2[var5]
      22 [-]: FASTCALL1 64 R6 L3; 
      23 [-]: MOVE R8 R6   ; var8 = var6
      24 [-]: GETIMPORT R7 10; var7 = 0x7B998233
      25 [-]: CALL R7 2 2  ; var7 = var7(var8)
L 3:  26 [-]: JUMPIF R7 L4 ; goto L4 if var7
      27 [-]: NAMECALL R7 R6 K11; var8 = var6; var7 = var6[0xF9E80DF1]
      28 [-]: CALL R7 2 2  ; var7 = var7(var8)
      29 [-]: JUMPIFNOT R7 L4; goto L4 if not var7
      30 [-]: NAMECALL R7 R6 K12; var8 = var6; var7 = var6[0x8AFFF5B9]
      31 [-]: CALL R7 2 2  ; var7 = var7(var8)
      32 [-]: JUMPIF R7 L4 ; goto L4 if var7
      33 [-]: GETUPVAL R9 1; var9 = upvalues[1]
      34 [-]: NAMECALL R7 R6 K13; var8 = var6; var7 = var6[0xC9F6A7D7]
      35 [-]: CALL R7 3 2  ; var7 = var7(var8, var9)
      36 [-]: GETUPVAL R8 2; var8 = upvalues[2]
      37 [-]: MOVE R9 R1   ; var9 = var1
      38 [-]: MOVE R10 R7  ; var10 = var7
      39 [-]: CALL R8 3 2  ; var8 = var8(var9, var10)
      40 [-]: JUMPIF R8 L4 ; goto L4 if var8
      41 [-]: NAMECALL R9 R6 K14; var10 = var6; var9 = var6[0xE2E807CC]
      42 [-]: CALL R9 2 1  ; var9(var10)
L 4:  43 [-]: FORNLOOP R3 L2; nforloop end - iterate + goto L2
L 5:  44 [-]: GETIMPORT R3 16; var3 = 0xCBD666E1
      45 [-]: LOADK R4 K17 ; var4 = 0.10000000149011612
      46 [-]: CALL R3 2 1  ; var3(var4)
      47 [-]: JUMPBACK L1  ; goto L1
      48 [-]: RETURN R0 0  ; 


; Name:            
; Defined at line: 595
; #Upvalues:       6
; #Parameters:     1
; Is_vararg:       0
; Max Stack Size:  14

       0 [-]: GETIMPORT R1 1; var1 = 0xCBD666E1
       1 [-]: LOADK R2 K2  ; var2 = 0.10000000149011612
       2 [-]: CALL R1 2 1  ; var1(var2)
       3 [-]: GETIMPORT R1 4; var1 = _T
       4 [-]: LOADN R2 0   ; var2 = 0
       5 [-]: SETTABLEKS R2 R1 K5; var2["Timer"] = var1
       6 [-]: GETIMPORT R1 7; var1 = 0x89326C93
       7 [-]: GETUPVAL R3 0; var3 = upvalues[0]
       8 [-]: NAMECALL R1 R1 K8; var2 = var1; var1 = var1[0x46A0EBF5]
       9 [-]: CALL R1 3 2  ; var1 = var1(var2, var3)
L 0:  10 [-]: FASTCALL1 64 R1 L1; 
      11 [-]: MOVE R3 R1   ; var3 = var1
      12 [-]: GETIMPORT R2 10; var2 = 0x7B998233
      13 [-]: CALL R2 2 2  ; var2 = var2(var3)
L 1:  14 [-]: JUMPIFNOT R2 L2; goto L2 if not var2
      15 [-]: GETIMPORT R2 7; var2 = 0x89326C93
      16 [-]: GETUPVAL R4 0; var4 = upvalues[0]
      17 [-]: NAMECALL R2 R2 K8; var3 = var2; var2 = var2[0x46A0EBF5]
      18 [-]: CALL R2 3 2  ; var2 = var2(var3, var4)
      19 [-]: MOVE R1 R2   ; var1 = var2
      20 [-]: GETIMPORT R2 1; var2 = 0xCBD666E1
      21 [-]: LOADN R3 0   ; var3 = 0
      22 [-]: CALL R2 2 1  ; var2(var3)
      23 [-]: JUMPBACK L0  ; goto L0
L 2:  24 [-]: GETIMPORT R2 7; var2 = 0x89326C93
      25 [-]: GETIMPORT R4 12; var4 = 0x0469F296
      26 [-]: LOADK R5 K13 ; var5 = "ButtonCounter"
      27 [-]: CALL R4 2 0  ; var4, ... = var4(var5)
      28 [-]: NAMECALL R2 R2 K8; var3 = var2; var2 = var2[0x46A0EBF5]
      29 [-]: CALL R2 0 2  ; var2 = var2(var3, ...)
      30 [-]: NAMECALL R3 R2 K14; var4 = var2; var3 = var2[0x2E333568]
      31 [-]: CALL R3 2 2  ; var3 = var3(var4)
      32 [-]: LOADB R4 0   ; var4 = false
      33 [-]: GETIMPORT R5 16; var5 = 0xE9D9F687
      34 [-]: JUMPIFNOT R5 L3; goto L3 if not var5
      35 [-]: GETIMPORT R5 1; var5 = 0xCBD666E1
      36 [-]: GETIMPORT R6 18; var6 = 0xD51C8E5E
      37 [-]: CALL R5 2 1  ; var5(var6)
      38 [-]: GETIMPORT R7 12; var7 = 0x0469F296
      39 [-]: LOADK R8 K19 ; var8 = "GolemControl"
      40 [-]: CALL R7 2 2  ; var7 = var7(var8)
      41 [-]: LOADB R8 0   ; var8 = false
      42 [-]: NAMECALL R5 R1 K20; var6 = var1; var5 = var1[0xD5F7912B]
      43 [-]: CALL R5 4 1  ; var5(var6, var7, var8)
      44 [-]: GETIMPORT R5 1; var5 = 0xCBD666E1
      45 [-]: LOADN R6 1   ; var6 = 1
      46 [-]: CALL R5 2 1  ; var5(var6)
      47 [-]: GETIMPORT R5 4; var5 = _T
      48 [-]: GETIMPORT R7 23; var7 = _T["SpaceGolemStage"]
      49 [-]: ADDK R6 R7 K21; var6 = var7 + 1
      50 [-]: SETTABLEKS R6 R5 K22; var6["SpaceGolemStage"] = var5
      51 [-]: GETUPVAL R5 1; var5 = upvalues[1]
      52 [-]: GETUPVAL R7 2; var7 = upvalues[2]
      53 [-]: GETIMPORT R8 23; var8 = _T["SpaceGolemStage"]
      54 [-]: NAMECALL R5 R5 K24; var6 = var5; var5 = var5[0x751F061D]
      55 [-]: CALL R5 4 1  ; var5(var6, var7, var8)
      56 [-]: GETIMPORT R5 4; var5 = _T
      57 [-]: LOADB R6 0   ; var6 = false
      58 [-]: SETTABLEKS R6 R5 K25; var6["GolemAttached"] = var5
      59 [-]: RETURN R0 0  ; 
L 3:  60 [-]: FASTCALL1 64 R1 L4; 
      61 [-]: MOVE R6 R1   ; var6 = var1
      62 [-]: GETIMPORT R5 10; var5 = 0x7B998233
      63 [-]: CALL R5 2 2  ; var5 = var5(var6)
L 4:  64 [-]: JUMPIF R5 L16; goto L16 if var5
      65 [-]: NAMECALL R5 R1 K26; var6 = var1; var5 = var1[0x5E8B6A40]
      66 [-]: CALL R5 2 2  ; var5 = var5(var6)
      67 [-]: JUMPIFNOT R5 L7; goto L7 if not var5
      68 [-]: GETUPVAL R5 1; var5 = upvalues[1]
      69 [-]: GETUPVAL R7 3; var7 = upvalues[3]
      70 [-]: NAMECALL R5 R5 K27; var6 = var5; var5 = var5[0x0EB34C69]
      71 [-]: CALL R5 3 2  ; var5 = var5(var6, var7)
      72 [-]: GETIMPORT R6 4; var6 = _T
      73 [-]: GETIMPORT R8 28; var8 = _T["Timer"]
      74 [-]: GETIMPORT R9 30; var9 = 0x67652851
      75 [-]: CALL R9 1 2  ; var9 = var9()
      76 [-]: ADD R7 R8 R9 ; var7 = var8 + var9
      77 [-]: SETTABLEKS R7 R6 K5; var7["Timer"] = var6
      78 [-]: GETIMPORT R7 28; var7 = _T["Timer"]
      79 [-]: FASTCALL1 12 R7 L5; 
      80 [-]: GETIMPORT R6 33; var6 = 0x5BCED4C4[0x55F27C30]
      81 [-]: CALL R6 2 2  ; var6 = var6(var7)
L 5:  82 [-]: JUMPIFEQ R6 R5 L6; goto L6 if var6 == var67388
      83 [-]: GETUPVAL R7 1; var7 = upvalues[1]
      84 [-]: GETUPVAL R9 3; var9 = upvalues[3]
      85 [-]: MOVE R10 R6  ; var10 = var6
      86 [-]: NAMECALL R7 R7 K24; var8 = var7; var7 = var7[0x751F061D]
      87 [-]: CALL R7 4 1  ; var7(var8, var9, var10)
L 6:  88 [-]: GETUPVAL R7 1; var7 = upvalues[1]
      89 [-]: GETUPVAL R9 3; var9 = upvalues[3]
      90 [-]: NAMECALL R7 R7 K27; var8 = var7; var7 = var7[0x0EB34C69]
      91 [-]: CALL R7 3 2  ; var7 = var7(var8, var9)
      92 [-]: GETUPVAL R8 1; var8 = upvalues[1]
      93 [-]: GETUPVAL R10 4; var10 = upvalues[4]
      94 [-]: NAMECALL R8 R8 K27; var9 = var8; var8 = var8[0x0EB34C69]
      95 [-]: CALL R8 3 2  ; var8 = var8(var9, var10)
      96 [-]: JUMPIFNOTLT R8 R7 L7; goto L7 if var8 >= var2310
      97 [-]: LOADB R9 0   ; var9 = false
      98 [-]: NAMECALL R7 R1 K34; var8 = var1; var7 = var1[0x113A6664]
      99 [-]: CALL R7 3 1  ; var7(var8, var9)
     100 [-]: GETIMPORT R7 36; var7 = 0x3D106989
     101 [-]: LOADK R9 K37 ; var9 = "purified Timer is "
     102 [-]: GETIMPORT R10 28; var10 = _T["Timer"]
     103 [-]: LOADK R11 K38; var11 = " and the newTime in the hud is "
     104 [-]: MOVE R12 R6  ; var12 = var6
     105 [-]: LOADK R13 K39; var13 = " which should be greater than the recharge limit so bumping hte recharge count"
     106 [-]: CONCAT R8 R9 R13; var8 = var9 .. var13
     107 [-]: CALL R7 2 1  ; var7(var8)
L 7: 108 [-]: NAMECALL R5 R2 K14; var6 = var2; var5 = var2[0x2E333568]
     109 [-]: CALL R5 2 2  ; var5 = var5(var6)
     110 [-]: MOVE R3 R5   ; var3 = var5
     111 [-]: GETIMPORT R5 40; var5 = _T["GolemAttached"]
     112 [-]: JUMPIF R5 L10; goto L10 if var5
     113 [-]: LOADB R7 0   ; var7 = false
     114 [-]: NAMECALL R5 R1 K41; var6 = var1; var5 = var1[0x1D5EEB9A]
     115 [-]: CALL R5 3 1  ; var5(var6, var7)
     116 [-]: GETUPVAL R7 5; var7 = upvalues[5]
     117 [-]: NAMECALL R5 R1 K42; var6 = var1; var5 = var1[0xC9F6A7D7]
     118 [-]: CALL R5 3 2  ; var5 = var5(var6, var7)
     119 [-]: FASTCALL1 64 R5 L8; 
     120 [-]: MOVE R7 R5   ; var7 = var5
     121 [-]: GETIMPORT R6 10; var6 = 0x7B998233
     122 [-]: CALL R6 2 2  ; var6 = var6(var7)
L 8: 123 [-]: JUMPIF R6 L9 ; goto L9 if var6
     124 [-]: NAMECALL R6 R5 K43; var7 = var5; var6 = var5[0x1DB57C6B]
     125 [-]: CALL R6 2 1  ; var6(var7)
L 9: 126 [-]: LOADK R8 K44 ; var8 = "WingsClosed"
     127 [-]: LOADK R9 K45 ; var9 = 1.5
     128 [-]: NAMECALL R6 R1 K46; var7 = var1; var6 = var1[0x21B4C60E]
     129 [-]: CALL R6 4 1  ; var6(var7, var8, var9)
     130 [-]: LOADB R4 0   ; var4 = false
     131 [-]: JUMP L15     ; goto L15
L10: 132 [-]: GETIMPORT R5 48; var5 = 0x0926F628
     133 [-]: JUMPIFNOTEQ R3 R5 L12; goto L12 if var3 ~= var4326477
     134 [-]: JUMPIF R4 L12; goto L12 if var4
     135 [-]: LOADB R7 1   ; var7 = true
     136 [-]: NAMECALL R5 R1 K41; var6 = var1; var5 = var1[0x1D5EEB9A]
     137 [-]: CALL R5 3 1  ; var5(var6, var7)
     138 [-]: GETUPVAL R7 5; var7 = upvalues[5]
     139 [-]: GETIMPORT R8 12; var8 = 0x0469F296
     140 [-]: LOADK R9 K49 ; var9 = "ATT_C1_LEVEL"
     141 [-]: CALL R8 2 2  ; var8 = var8(var9)
     142 [-]: GETIMPORT R9 51; var9 = 0xA421AF95
     143 [-]: LOADN R10 0  ; var10 = 0
     144 [-]: LOADN R11 -1 ; var11 = -1
     145 [-]: LOADN R12 0  ; var12 = 0
     146 [-]: CALL R9 4 0  ; var9, ... = var9(var10, var11, var12)
     147 [-]: NAMECALL R5 R1 K52; var6 = var1; var5 = var1[0x47901F07]
     148 [-]: CALL R5 0 1  ; var5(var6, ...)
     149 [-]: LOADK R7 K53 ; var7 = "WingsOpen"
     150 [-]: LOADK R8 K45 ; var8 = 1.5
     151 [-]: NAMECALL R5 R1 K46; var6 = var1; var5 = var1[0x21B4C60E]
     152 [-]: CALL R5 4 1  ; var5(var6, var7, var8)
     153 [-]: LOADB R4 1   ; var4 = true
     154 [-]: GETIMPORT R5 55; var5 = 0x2A325222
     155 [-]: JUMPIFNOT R5 L11; goto L11 if not var5
     156 [-]: GETIMPORT R7 12; var7 = 0x0469F296
     157 [-]: LOADK R8 K19 ; var8 = "GolemControl"
     158 [-]: CALL R7 2 2  ; var7 = var7(var8)
     159 [-]: LOADB R8 0   ; var8 = false
     160 [-]: NAMECALL R5 R1 K20; var6 = var1; var5 = var1[0xD5F7912B]
     161 [-]: CALL R5 4 1  ; var5(var6, var7, var8)
L11: 162 [-]: GETIMPORT R5 57; var5 = 0x501EE8B2
     163 [-]: JUMPIFNOT R5 L15; goto L15 if not var5
     164 [-]: GETIMPORT R5 1; var5 = 0xCBD666E1
     165 [-]: LOADN R6 2   ; var6 = 2
     166 [-]: CALL R5 2 1  ; var5(var6)
     167 [-]: GETIMPORT R5 4; var5 = _T
     168 [-]: GETIMPORT R7 23; var7 = _T["SpaceGolemStage"]
     169 [-]: ADDK R6 R7 K21; var6 = var7 + 1
     170 [-]: SETTABLEKS R6 R5 K22; var6["SpaceGolemStage"] = var5
     171 [-]: GETUPVAL R5 1; var5 = upvalues[1]
     172 [-]: GETUPVAL R7 2; var7 = upvalues[2]
     173 [-]: GETIMPORT R8 23; var8 = _T["SpaceGolemStage"]
     174 [-]: NAMECALL R5 R5 K24; var6 = var5; var5 = var5[0x751F061D]
     175 [-]: CALL R5 4 1  ; var5(var6, var7, var8)
     176 [-]: GETIMPORT R5 4; var5 = _T
     177 [-]: LOADB R6 0   ; var6 = false
     178 [-]: SETTABLEKS R6 R5 K25; var6["GolemAttached"] = var5
     179 [-]: LOADB R7 0   ; var7 = false
     180 [-]: NAMECALL R5 R1 K34; var6 = var1; var5 = var1[0x113A6664]
     181 [-]: CALL R5 3 1  ; var5(var6, var7)
     182 [-]: JUMP L15     ; goto L15
L12: 183 [-]: GETIMPORT R5 48; var5 = 0x0926F628
     184 [-]: JUMPIFNOTLT R3 R5 L15; goto L15 if var3 >= var1770516
     185 [-]: JUMPIFNOT R4 L15; goto L15 if not var4
     186 [-]: NAMECALL R5 R1 K26; var6 = var1; var5 = var1[0x5E8B6A40]
     187 [-]: CALL R5 2 2  ; var5 = var5(var6)
     188 [-]: JUMPIF R5 L15; goto L15 if var5
     189 [-]: LOADB R7 0   ; var7 = false
     190 [-]: NAMECALL R5 R1 K41; var6 = var1; var5 = var1[0x1D5EEB9A]
     191 [-]: CALL R5 3 1  ; var5(var6, var7)
     192 [-]: GETUPVAL R7 5; var7 = upvalues[5]
     193 [-]: NAMECALL R5 R1 K42; var6 = var1; var5 = var1[0xC9F6A7D7]
     194 [-]: CALL R5 3 2  ; var5 = var5(var6, var7)
     195 [-]: FASTCALL1 64 R5 L13; 
     196 [-]: MOVE R7 R5   ; var7 = var5
     197 [-]: GETIMPORT R6 10; var6 = 0x7B998233
     198 [-]: CALL R6 2 2  ; var6 = var6(var7)
L13: 199 [-]: JUMPIF R6 L14; goto L14 if var6
     200 [-]: NAMECALL R6 R5 K43; var7 = var5; var6 = var5[0x1DB57C6B]
     201 [-]: CALL R6 2 1  ; var6(var7)
L14: 202 [-]: LOADK R8 K44 ; var8 = "WingsClosed"
     203 [-]: LOADK R9 K45 ; var9 = 1.5
     204 [-]: NAMECALL R6 R1 K46; var7 = var1; var6 = var1[0x21B4C60E]
     205 [-]: CALL R6 4 1  ; var6(var7, var8, var9)
     206 [-]: LOADB R4 0   ; var4 = false
L15: 207 [-]: GETIMPORT R5 1; var5 = 0xCBD666E1
     208 [-]: LOADN R6 0   ; var6 = 0
     209 [-]: CALL R5 2 1  ; var5(var6)
     210 [-]: JUMPBACK L3  ; goto L3
L16: 211 [-]: RETURN R0 0  ; 


; Name:            
; Defined at line: 677
; #Upvalues:       1
; #Parameters:     1
; Is_vararg:       0
; Max Stack Size:  8

       0 [-]: NAMECALL R1 R0 K0; var2 = var0; var1 = var0[0x2B54251B]
       1 [-]: CALL R1 2 2  ; var1 = var1(var2)
       2 [-]: NAMECALL R2 R0 K1; var3 = var0; var2 = var0[0xCD73323E]
       3 [-]: CALL R2 2 2  ; var2 = var2(var3)
       4 [-]: NAMECALL R3 R2 K0; var4 = var2; var3 = var2[0x2B54251B]
       5 [-]: CALL R3 2 2  ; var3 = var3(var4)
       6 [-]: GETIMPORT R4 3; var4 = 0x89326C93
       7 [-]: NAMECALL R4 R4 K4; var5 = var4; var4 = var4[0x18D05D30]
       8 [-]: CALL R4 2 2  ; var4 = var4(var5)
       9 [-]: JUMPIF R4 L0 ; goto L0 if var4
      10 [-]: RETURN R0 0  ; 
L 0:  11 [-]: FASTCALL1 64 R3 L1; 
      12 [-]: MOVE R5 R3   ; var5 = var3
      13 [-]: GETIMPORT R4 6; var4 = 0x7B998233
      14 [-]: CALL R4 2 2  ; var4 = var4(var5)
L 1:  15 [-]: JUMPIF R4 L4 ; goto L4 if var4
      16 [-]: GETUPVAL R6 0; var6 = upvalues[0]
      17 [-]: NAMECALL R4 R3 K7; var5 = var3; var4 = var3[0xF2DEAF69]
      18 [-]: CALL R4 3 2  ; var4 = var4(var5, var6)
      19 [-]: JUMPIFNOT R4 L4; goto L4 if not var4
      20 [-]: NAMECALL R4 R3 K8; var5 = var3; var4 = var3[0x4FECD866]
      21 [-]: CALL R4 2 2  ; var4 = var4(var5)
      22 [-]: JUMPXEQKB R4 1 L2 NOT; 
      23 [-]: GETIMPORT R6 10; var6 = 0x0469F296
      24 [-]: LOADK R7 K11 ; var7 = "GolemControl"
      25 [-]: CALL R6 2 2  ; var6 = var6(var7)
      26 [-]: LOADB R7 0   ; var7 = false
      27 [-]: NAMECALL R4 R3 K12; var5 = var3; var4 = var3[0xD5F7912B]
      28 [-]: CALL R4 4 1  ; var4(var5, var6, var7)
L 2:  29 [-]: GETIMPORT R4 14; var4 = 0xCBD666E1
      30 [-]: LOADK R5 K15 ; var5 = 0.20000000298023224
      31 [-]: CALL R4 2 1  ; var4(var5)
      32 [-]: FASTCALL1 64 R1 L3; 
      33 [-]: MOVE R5 R1   ; var5 = var1
      34 [-]: GETIMPORT R4 6; var4 = 0x7B998233
      35 [-]: CALL R4 2 2  ; var4 = var4(var5)
L 3:  36 [-]: JUMPIF R4 L4 ; goto L4 if var4
      37 [-]: NAMECALL R4 R1 K16; var5 = var1; var4 = var1[0x2047CFE7]
      38 [-]: CALL R4 2 2  ; var4 = var4(var5)
      39 [-]: JUMPIF R4 L4 ; goto L4 if var4
      40 [-]: LOADK R6 K17 ; var6 = 50000
      41 [-]: NAMECALL R4 R1 K18; var5 = var1; var4 = var1[0x6E9719EB]
      42 [-]: CALL R4 3 1  ; var4(var5, var6)
L 4:  43 [-]: RETURN R0 0  ; 


; Name:            
; Defined at line: 707
; #Upvalues:       0
; #Parameters:     1
; Is_vararg:       0
; Max Stack Size:  6

       0 [-]: NAMECALL R1 R0 K0; var2 = var0; var1 = var0[0xCD73323E]
       1 [-]: CALL R1 2 2  ; var1 = var1(var2)
       2 [-]: FASTCALL1 64 R1 L0; 
       3 [-]: MOVE R3 R1   ; var3 = var1
       4 [-]: GETIMPORT R2 2; var2 = 0x7B998233
       5 [-]: CALL R2 2 2  ; var2 = var2(var3)
L 0:   6 [-]: JUMPIFNOT R2 L1; goto L1 if not var2
       7 [-]: RETURN R0 0  ; 
L 1:   8 [-]: NAMECALL R2 R1 K3; var3 = var1; var2 = var1[0x2B54251B]
       9 [-]: CALL R2 2 2  ; var2 = var2(var3)
      10 [-]: FASTCALL1 64 R2 L2; 
      11 [-]: MOVE R4 R2   ; var4 = var2
      12 [-]: GETIMPORT R3 2; var3 = 0x7B998233
      13 [-]: CALL R3 2 2  ; var3 = var3(var4)
L 2:  14 [-]: JUMPIF R3 L3 ; goto L3 if var3
      15 [-]: GETIMPORT R5 5; var5 = gDevourerType
      16 [-]: NAMECALL R3 R2 K6; var4 = var2; var3 = var2[0xF2DEAF69]
      17 [-]: CALL R3 3 2  ; var3 = var3(var4, var5)
      18 [-]: JUMPIF R3 L4 ; goto L4 if var3
L 3:  19 [-]: RETURN R0 0  ; 
L 4:  20 [-]: GETIMPORT R4 8; var4 = 0x16B2B58E
      21 [-]: FASTCALL1 64 R4 L5; 
      22 [-]: GETIMPORT R3 2; var3 = 0x7B998233
      23 [-]: CALL R3 2 2  ; var3 = var3(var4)
L 5:  24 [-]: JUMPIF R3 L8 ; goto L8 if var3
L 6:  25 [-]: FASTCALL1 64 R2 L7; 
      26 [-]: MOVE R4 R2   ; var4 = var2
      27 [-]: GETIMPORT R3 2; var3 = 0x7B998233
      28 [-]: CALL R3 2 2  ; var3 = var3(var4)
L 7:  29 [-]: JUMPIF R3 L10; goto L10 if var3
      30 [-]: GETIMPORT R3 8; var3 = 0x16B2B58E
      31 [-]: NAMECALL R3 R3 K9; var4 = var3; var3 = var3[0xF37943FF]
      32 [-]: CALL R3 2 2  ; var3 = var3(var4)
      33 [-]: JUMPIFNOT R3 L10; goto L10 if not var3
      34 [-]: LOADN R5 1   ; var5 = 1
      35 [-]: NAMECALL R3 R2 K10; var4 = var2; var3 = var2[0x6E9719EB]
      36 [-]: CALL R3 3 1  ; var3(var4, var5)
      37 [-]: GETIMPORT R3 12; var3 = 0xCBD666E1
      38 [-]: LOADN R4 2   ; var4 = 2
      39 [-]: CALL R3 2 1  ; var3(var4)
      40 [-]: JUMPBACK L6  ; goto L6
      41 [-]: RETURN R0 0  ; 
L 8:  42 [-]: FASTCALL1 64 R2 L9; 
      43 [-]: MOVE R4 R2   ; var4 = var2
      44 [-]: GETIMPORT R3 2; var3 = 0x7B998233
      45 [-]: CALL R3 2 2  ; var3 = var3(var4)
L 9:  46 [-]: JUMPIF R3 L10; goto L10 if var3
      47 [-]: LOADN R5 1   ; var5 = 1
      48 [-]: NAMECALL R3 R2 K10; var4 = var2; var3 = var2[0x6E9719EB]
      49 [-]: CALL R3 3 1  ; var3(var4, var5)
L10:  50 [-]: RETURN R0 0  ; 


; Name:            
; Defined at line: 730
; #Upvalues:       4
; #Parameters:     0
; Is_vararg:       0
; Max Stack Size:  9

       0 [-]: LOADB R0 0   ; var0 = false
       1 [-]: LOADB R1 0   ; var1 = false
       2 [-]: GETIMPORT R3 1; var3 = 0xEEAC42B2
       3 [-]: FASTCALL1 64 R3 L0; 
       4 [-]: GETIMPORT R2 3; var2 = 0x7B998233
       5 [-]: CALL R2 2 2  ; var2 = var2(var3)
L 0:   6 [-]: JUMPIF R2 L11; goto L11 if var2
       7 [-]: GETIMPORT R3 5; var3 = 0x6C42BBBE
       8 [-]: FASTCALL1 64 R3 L1; 
       9 [-]: GETIMPORT R2 3; var2 = 0x7B998233
      10 [-]: CALL R2 2 2  ; var2 = var2(var3)
L 1:  11 [-]: JUMPIF R2 L11; goto L11 if var2
      12 [-]: GETIMPORT R2 1; var2 = 0xEEAC42B2
      13 [-]: GETUPVAL R4 0; var4 = upvalues[0]
      14 [-]: NAMECALL R2 R2 K6; var3 = var2; var2 = var2[0xC9F6A7D7]
      15 [-]: CALL R2 3 2  ; var2 = var2(var3, var4)
      16 [-]: FASTCALL1 64 R2 L2; 
      17 [-]: MOVE R4 R2   ; var4 = var2
      18 [-]: GETIMPORT R3 3; var3 = 0x7B998233
      19 [-]: CALL R3 2 2  ; var3 = var3(var4)
L 2:  20 [-]: JUMPIFNOT R3 L3; goto L3 if not var3
      21 [-]: GETIMPORT R3 1; var3 = 0xEEAC42B2
      22 [-]: GETUPVAL R5 1; var5 = upvalues[1]
      23 [-]: NAMECALL R3 R3 K6; var4 = var3; var3 = var3[0xC9F6A7D7]
      24 [-]: CALL R3 3 2  ; var3 = var3(var4, var5)
      25 [-]: MOVE R2 R3   ; var2 = var3
L 3:  26 [-]: NAMECALL R3 R2 K7; var4 = var2; var3 = var2[0xF37943FF]
      27 [-]: CALL R3 2 2  ; var3 = var3(var4)
      28 [-]: JUMPIFNOT R3 L4; goto L4 if not var3
      29 [-]: LOADB R0 1   ; var0 = true
L 4:  30 [-]: GETIMPORT R3 5; var3 = 0x6C42BBBE
      31 [-]: GETUPVAL R5 0; var5 = upvalues[0]
      32 [-]: NAMECALL R3 R3 K6; var4 = var3; var3 = var3[0xC9F6A7D7]
      33 [-]: CALL R3 3 2  ; var3 = var3(var4, var5)
      34 [-]: MOVE R2 R3   ; var2 = var3
      35 [-]: FASTCALL1 64 R2 L5; 
      36 [-]: MOVE R4 R2   ; var4 = var2
      37 [-]: GETIMPORT R3 3; var3 = 0x7B998233
      38 [-]: CALL R3 2 2  ; var3 = var3(var4)
L 5:  39 [-]: JUMPIFNOT R3 L6; goto L6 if not var3
      40 [-]: GETIMPORT R3 5; var3 = 0x6C42BBBE
      41 [-]: GETUPVAL R5 1; var5 = upvalues[1]
      42 [-]: NAMECALL R3 R3 K6; var4 = var3; var3 = var3[0xC9F6A7D7]
      43 [-]: CALL R3 3 2  ; var3 = var3(var4, var5)
      44 [-]: MOVE R2 R3   ; var2 = var3
L 6:  45 [-]: NAMECALL R3 R2 K7; var4 = var2; var3 = var2[0xF37943FF]
      46 [-]: CALL R3 2 2  ; var3 = var3(var4)
      47 [-]: JUMPIFNOT R3 L7; goto L7 if not var3
      48 [-]: LOADB R1 1   ; var1 = true
L 7:  49 [-]: JUMPIF R0 L8 ; goto L8 if var0
      50 [-]: GETIMPORT R3 1; var3 = 0xEEAC42B2
      51 [-]: GETUPVAL R5 2; var5 = upvalues[2]
      52 [-]: LOADB R6 0   ; var6 = false
      53 [-]: NAMECALL R3 R3 K8; var4 = var3; var3 = var3[0x5D985C7E]
      54 [-]: CALL R3 4 1  ; var3(var4, var5, var6)
L 8:  55 [-]: JUMPIF R1 L9 ; goto L9 if var1
      56 [-]: GETIMPORT R3 5; var3 = 0x6C42BBBE
      57 [-]: GETUPVAL R5 2; var5 = upvalues[2]
      58 [-]: LOADB R6 0   ; var6 = false
      59 [-]: NAMECALL R3 R3 K8; var4 = var3; var3 = var3[0x5D985C7E]
      60 [-]: CALL R3 4 1  ; var3(var4, var5, var6)
L 9:  61 [-]: GETIMPORT R3 10; var3 = 0x89326C93
      62 [-]: GETIMPORT R5 12; var5 = 0x1F317627
      63 [-]: GETIMPORT R6 1; var6 = 0xEEAC42B2
      64 [-]: NAMECALL R6 R6 K13; var7 = var6; var6 = var6[0xD1586535]
      65 [-]: CALL R6 2 2  ; var6 = var6(var7)
      66 [-]: GETIMPORT R7 1; var7 = 0xEEAC42B2
      67 [-]: NAMECALL R7 R7 K14; var8 = var7; var7 = var7[0xCB3851B8]
      68 [-]: CALL R7 2 0  ; var7, ... = var7(var8)
      69 [-]: NAMECALL R3 R3 K15; var4 = var3; var3 = var3[0x05909209]
      70 [-]: CALL R3 0 1  ; var3(var4, ...)
      71 [-]: GETIMPORT R3 10; var3 = 0x89326C93
      72 [-]: GETIMPORT R5 12; var5 = 0x1F317627
      73 [-]: GETIMPORT R6 5; var6 = 0x6C42BBBE
      74 [-]: NAMECALL R6 R6 K13; var7 = var6; var6 = var6[0xD1586535]
      75 [-]: CALL R6 2 2  ; var6 = var6(var7)
      76 [-]: GETIMPORT R7 5; var7 = 0x6C42BBBE
      77 [-]: NAMECALL R7 R7 K14; var8 = var7; var7 = var7[0xCB3851B8]
      78 [-]: CALL R7 2 0  ; var7, ... = var7(var8)
      79 [-]: NAMECALL R3 R3 K15; var4 = var3; var3 = var3[0x05909209]
      80 [-]: CALL R3 0 1  ; var3(var4, ...)
      81 [-]: JUMPIF R0 L10; goto L10 if var0
      82 [-]: GETIMPORT R3 1; var3 = 0xEEAC42B2
      83 [-]: GETUPVAL R5 3; var5 = upvalues[3]
      84 [-]: LOADB R6 0   ; var6 = false
      85 [-]: NAMECALL R3 R3 K8; var4 = var3; var3 = var3[0x5D985C7E]
      86 [-]: CALL R3 4 1  ; var3(var4, var5, var6)
L10:  87 [-]: JUMPIF R1 L11; goto L11 if var1
      88 [-]: GETIMPORT R3 5; var3 = 0x6C42BBBE
      89 [-]: GETUPVAL R5 3; var5 = upvalues[3]
      90 [-]: LOADB R6 0   ; var6 = false
      91 [-]: NAMECALL R3 R3 K8; var4 = var3; var3 = var3[0x5D985C7E]
      92 [-]: CALL R3 4 1  ; var3(var4, var5, var6)
L11:  93 [-]: RETURN R0 0  ; 


; Name:            
; Defined at line: 777
; #Upvalues:       0
; #Parameters:     0
; Is_vararg:       0
; Max Stack Size:  3

       0 [-]: GETIMPORT R1 1; var1 = 0x389699E6
       1 [-]: FASTCALL1 64 R1 L0; 
       2 [-]: GETIMPORT R0 3; var0 = 0x7B998233
       3 [-]: CALL R0 2 2  ; var0 = var0(var1)
L 0:   4 [-]: JUMPIF R0 L2 ; goto L2 if var0
       5 [-]: GETIMPORT R0 1; var0 = 0x389699E6
       6 [-]: GETIMPORT R2 5; var2 = 0xB0DE66FE
       7 [-]: NAMECALL R0 R0 K6; var1 = var0; var0 = var0[0xC9F6A7D7]
       8 [-]: CALL R0 3 2  ; var0 = var0(var1, var2)
       9 [-]: FASTCALL1 64 R0 L1; 
      10 [-]: MOVE R2 R0   ; var2 = var0
      11 [-]: GETIMPORT R1 3; var1 = 0x7B998233
      12 [-]: CALL R1 2 2  ; var1 = var1(var2)
L 1:  13 [-]: JUMPIF R1 L2 ; goto L2 if var1
      14 [-]: NAMECALL R1 R0 K7; var2 = var0; var1 = var0[0xA2880940]
      15 [-]: CALL R1 2 1  ; var1(var2)
L 2:  16 [-]: RETURN R0 0  ; 


; Name:            
; Defined at line: 786
; #Upvalues:       0
; #Parameters:     1
; Is_vararg:       0
; Max Stack Size:  4

       0 [-]: GETIMPORT R1 1; var1 = 0xCBD666E1
       1 [-]: LOADN R2 1   ; var2 = 1
       2 [-]: CALL R1 2 1  ; var1(var2)
       3 [-]: NAMECALL R1 R0 K2; var2 = var0; var1 = var0[0x2B54251B]
       4 [-]: CALL R1 2 2  ; var1 = var1(var2)
L 0:   5 [-]: FASTCALL1 64 R1 L1; 
       6 [-]: MOVE R3 R1   ; var3 = var1
       7 [-]: GETIMPORT R2 4; var2 = 0x7B998233
       8 [-]: CALL R2 2 2  ; var2 = var2(var3)
L 1:   9 [-]: JUMPIF R2 L2 ; goto L2 if var2
      10 [-]: NAMECALL R2 R0 K2; var3 = var0; var2 = var0[0x2B54251B]
      11 [-]: CALL R2 2 2  ; var2 = var2(var3)
      12 [-]: MOVE R1 R2   ; var1 = var2
      13 [-]: GETIMPORT R2 1; var2 = 0xCBD666E1
      14 [-]: LOADN R3 2   ; var3 = 2
      15 [-]: CALL R2 2 1  ; var2(var3)
      16 [-]: JUMPBACK L0  ; goto L0
L 2:  17 [-]: FASTCALL1 64 R0 L3; 
      18 [-]: MOVE R3 R0   ; var3 = var0
      19 [-]: GETIMPORT R2 4; var2 = 0x7B998233
      20 [-]: CALL R2 2 2  ; var2 = var2(var3)
L 3:  21 [-]: JUMPIF R2 L4 ; goto L4 if var2
      22 [-]: NAMECALL R2 R0 K5; var3 = var0; var2 = var0[0xA2880940]
      23 [-]: CALL R2 2 1  ; var2(var3)
L 4:  24 [-]: RETURN R0 0  ; 


; Name:            
; Defined at line: 801
; #Upvalues:       2
; #Parameters:     2
; Is_vararg:       0
; Max Stack Size:  12

       0 [-]: GETUPVAL R4 0; var4 = upvalues[0]
       1 [-]: NAMECALL R2 R1 K0; var3 = var1; var2 = var1[0x0866B4BD]
       2 [-]: CALL R2 3 2  ; var2 = var2(var3, var4)
       3 [-]: JUMPIFNOT R2 L0; goto L0 if not var2
       4 [-]: LOADB R2 1   ; var2 = true
       5 [-]: RETURN R2 1  ; 
L 0:   6 [-]: NAMECALL R2 R1 K1; var3 = var1; var2 = var1[0x5B89142C]
       7 [-]: CALL R2 2 2  ; var2 = var2(var3)
       8 [-]: FASTCALL1 64 R2 L1; 
       9 [-]: MOVE R4 R2   ; var4 = var2
      10 [-]: GETIMPORT R3 3; var3 = 0x7B998233
      11 [-]: CALL R3 2 2  ; var3 = var3(var4)
L 1:  12 [-]: JUMPIF R3 L5 ; goto L5 if var3
      13 [-]: GETIMPORT R3 5; var3 = 0xC8802016
      14 [-]: GETUPVAL R4 1; var4 = upvalues[1]
      15 [-]: CALL R3 2 4  ; var3, var4, var5 = var3(var4)
      16 [-]: FORGPREP_INEXT R3 L4; 
L 2:  17 [-]: MOVE R10 R7  ; var10 = var7
      18 [-]: NAMECALL R8 R2 K6; var9 = var2; var8 = var2[0xE3A0BBCA]
      19 [-]: CALL R8 3 2  ; var8 = var8(var9, var10)
      20 [-]: FASTCALL1 64 R8 L3; 
      21 [-]: MOVE R10 R8  ; var10 = var8
      22 [-]: GETIMPORT R9 3; var9 = 0x7B998233
      23 [-]: CALL R9 2 2  ; var9 = var9(var10)
L 3:  24 [-]: JUMPIF R9 L4 ; goto L4 if var9
      25 [-]: GETUPVAL R11 0; var11 = upvalues[0]
      26 [-]: NAMECALL R9 R8 K0; var10 = var8; var9 = var8[0x0866B4BD]
      27 [-]: CALL R9 3 2  ; var9 = var9(var10, var11)
      28 [-]: JUMPIFNOT R9 L4; goto L4 if not var9
      29 [-]: LOADB R9 1   ; var9 = true
      30 [-]: RETURN R9 1  ; 
L 4:  31 [-]: FORGLOOP R3 L2 2 [inext]; 
L 5:  32 [-]: LOADB R2 0   ; var2 = false
      33 [-]: RETURN R2 1  ; 



