; This file has been disassembled using luadec 2.0.2 by sztupy (modified by Reversive)

; Name:            
; Defined at line: 0
; #Upvalues:       0
; #Parameters:     0
; Is_vararg:       2
; Max Stack Size:  38

  1 [-]: GETGLOBAL R0 K0        ; R0 := 0x2d0fad09
  2 [-]: LOADK     R1 K1        ; R1 := "Lotus.Scripts.Libs.AbilitiesLib"
  3 [-]: CALL      R0 2 2       ; R0 := R0(R1)
  4 [-]: GETGLOBAL R1 K0        ; R1 := 0x2d0fad09
  5 [-]: LOADK     R2 K2        ; R2 := "Lotus.Powersuits.PowersuitAbilities.PVPLib"
  6 [-]: CALL      R1 2 2       ; R1 := R1(R2)
  7 [-]: GETGLOBAL R2 K0        ; R2 := 0x2d0fad09
  8 [-]: LOADK     R3 K3        ; R3 := "Lotus.Scripts.Effects.EffectsColorUtilities"
  9 [-]: CALL      R2 2 2       ; R2 := R2(R3)
 10 [-]: GETGLOBAL R3 K0        ; R3 := 0x2d0fad09
 11 [-]: LOADK     R4 K4        ; R4 := "EE.Interface.Utilities"
 12 [-]: CALL      R3 2 2       ; R3 := R3(R4)
 13 [-]: CONST     R4 3         ; R4 := 3.000000
 14 [-]: CONST     R5 3         ; R5 := 3.000000
 15 [-]: CONST     R6 1         ; R6 := 1.000000
 16 [-]: CONST     R7 -5        ; R7 := -5.000000
 17 [-]: GETGLOBAL R8 K5        ; R8 := 0xb7cbd06b
 18 [-]: CONST     R9 4         ; R9 := 4.000000
 19 [-]: CONST     R10 8        ; R10 := 8.000000
 20 [-]: CALL      R8 3 2       ; R8 := R8(R9,R10)
 21 [-]: CONST     R9 3         ; R9 := 3.000000
 22 [-]: CONST     R10 9        ; R10 := 9.000000
 23 [-]: CONST     R11 2        ; R11 := 2.000000
 24 [-]: CONST     R12 2        ; R12 := 2.000000
 25 [-]: CONST     R13 1        ; R13 := 1.000000
 26 [-]: CONST     R14 2        ; R14 := 2.000000
 27 [-]: CONST     R15 200      ; R15 := 200.000000
 28 [-]: CONST     R16 2        ; R16 := 2.000000
 29 [-]: CONST     R17 3        ; R17 := 3.000000
 30 [-]: CONST     R18 4        ; R18 := 4.000000
 31 [-]: CONST     R19 0        ; R19 := 0.125000
 32 [-]: GETGLOBAL R20 K6       ; R20 := 0x0469f296
 33 [-]: LOADK     R21 K7       ; R21 := "TintColor3"
 34 [-]: CALL      R20 2 2      ; R20 := R20(R21)
 35 [-]: GETGLOBAL R21 K6       ; R21 := 0x0469f296
 36 [-]: LOADK     R22 K8       ; R22 := "EmissiveMapAtten"
 37 [-]: CALL      R21 2 2      ; R21 := R21(R22)
 38 [-]: GETGLOBAL R22 K6       ; R22 := 0x0469f296
 39 [-]: LOADK     R23 K9       ; R23 := "EmissiveTintColor"
 40 [-]: CALL      R22 2 2      ; R22 := R22(R23)
 41 [-]: GETGLOBAL R23 K6       ; R23 := 0x0469f296
 42 [-]: LOADK     R24 K10      ; R24 := "EmissiveTintColorHi"
 43 [-]: CALL      R23 2 2      ; R23 := R23(R24)
 44 [-]: GETGLOBAL R24 K6       ; R24 := 0x0469f296
 45 [-]: LOADK     R25 K11      ; R25 := "EmissiveTintColorLo"
 46 [-]: CALL      R24 2 2      ; R24 := R24(R25)
 47 [-]: GETGLOBAL R25 K6       ; R25 := 0x0469f296
 48 [-]: LOADK     R26 K12      ; R26 := "EmGreenTintColor"
 49 [-]: CALL      R25 2 2      ; R25 := R25(R26)
 50 [-]: GETGLOBAL R26 K6       ; R26 := 0x0469f296
 51 [-]: LOADK     R27 K13      ; R27 := "EmRedTintColor"
 52 [-]: CALL      R26 2 2      ; R26 := R26(R27)
 53 [-]: CLOSURE   R27 0        ; R27 := closure(Function #1)
 54 [-]: MOVE      R0 R1        ; R0 := R1
 55 [-]: MOVE      R0 R14       ; R0 := R14
 56 [-]: MOVE      R0 R15       ; R0 := R15
 57 [-]: MOVE      R0 R16       ; R0 := R16
 58 [-]: MOVE      R0 R17       ; R0 := R17
 59 [-]: MOVE      R0 R18       ; R0 := R18
 60 [-]: MOVE      R0 R5        ; R0 := R5
 61 [-]: MOVE      R0 R6        ; R0 := R6
 62 [-]: CLOSURE   R28 1        ; R28 := closure(Function #2)
 63 [-]: MOVE      R0 R14       ; R0 := R14
 64 [-]: MOVE      R0 R15       ; R0 := R15
 65 [-]: MOVE      R0 R16       ; R0 := R16
 66 [-]: MOVE      R0 R17       ; R0 := R17
 67 [-]: MOVE      R0 R18       ; R0 := R18
 68 [-]: CLOSURE   R29 2        ; R29 := closure(Function #3)
 69 [-]: MOVE      R0 R19       ; R0 := R19
 70 [-]: CLOSURE   R30 3        ; R30 := closure(Function #4)
 71 [-]: MOVE      R0 R19       ; R0 := R19
 72 [-]: CLOSURE   R31 4        ; R31 := closure(Function #5)
 73 [-]: MOVE      R0 R29       ; R0 := R29
 74 [-]: MOVE      R0 R19       ; R0 := R19
 75 [-]: MOVE      R0 R30       ; R0 := R30
 76 [-]: CLOSURE   R32 5        ; R32 := closure(Function #6)
 77 [-]: MOVE      R0 R27       ; R0 := R27
 78 [-]: MOVE      R0 R14       ; R0 := R14
 79 [-]: MOVE      R0 R15       ; R0 := R15
 80 [-]: MOVE      R0 R16       ; R0 := R16
 81 [-]: MOVE      R0 R17       ; R0 := R17
 82 [-]: MOVE      R0 R18       ; R0 := R18
 83 [-]: MOVE      R0 R28       ; R0 := R28
 84 [-]: MOVE      R0 R5        ; R0 := R5
 85 [-]: MOVE      R0 R31       ; R0 := R31
 86 [-]: SETGLOBAL R32 K14      ; GetAbilityUpgradeLevelInfo := R32
 87 [-]: CLOSURE   R32 6        ; R32 := closure(Function #7)
 88 [-]: MOVE      R0 R29       ; R0 := R29
 89 [-]: MOVE      R0 R3        ; R0 := R3
 90 [-]: MOVE      R0 R19       ; R0 := R19
 91 [-]: SETGLOBAL R32 K15      ; GetAugmentDescriptionInfo := R32
 92 [-]: CLOSURE   R32 7        ; R32 := closure(Function #8)
 93 [-]: MOVE      R0 R27       ; R0 := R27
 94 [-]: MOVE      R0 R5        ; R0 := R5
 95 [-]: SETGLOBAL R32 K16      ; EvaluateAbility := R32
 96 [-]: CLOSURE   R32 8        ; R32 := closure(Function #9)
 97 [-]: SETGLOBAL R32 K17      ; NpcEvaluateAbility := R32
 98 [-]: CLOSURE   R32 9        ; R32 := closure(Function #10)
 99 [-]: MOVE      R0 R1        ; R0 := R1
100 [-]: SETGLOBAL R32 K18      ; InitializeAbility := R32
101 [-]: CLOSURE   R32 10       ; R32 := closure(Function #11)
102 [-]: MOVE      R0 R2        ; R0 := R2
103 [-]: CLOSURE   R33 11       ; R33 := closure(Function #12)
104 [-]: CLOSURE   R34 12       ; R34 := closure(Function #13)
105 [-]: MOVE      R0 R1        ; R0 := R1
106 [-]: MOVE      R0 R9        ; R0 := R9
107 [-]: MOVE      R0 R8        ; R0 := R8
108 [-]: MOVE      R0 R7        ; R0 := R7
109 [-]: MOVE      R0 R33       ; R0 := R33
110 [-]: MOVE      R0 R10       ; R0 := R10
111 [-]: MOVE      R0 R12       ; R0 := R12
112 [-]: MOVE      R0 R11       ; R0 := R11
113 [-]: CLOSURE   R35 13       ; R35 := closure(Function #14)
114 [-]: MOVE      R0 R18       ; R0 := R18
115 [-]: MOVE      R0 R4        ; R0 := R4
116 [-]: MOVE      R0 R19       ; R0 := R19
117 [-]: MOVE      R0 R0        ; R0 := R0
118 [-]: CLOSURE   R36 14       ; R36 := closure(Function #15)
119 [-]: MOVE      R0 R32       ; R0 := R32
120 [-]: MOVE      R0 R22       ; R0 := R22
121 [-]: MOVE      R0 R24       ; R0 := R24
122 [-]: MOVE      R0 R23       ; R0 := R23
123 [-]: MOVE      R0 R25       ; R0 := R25
124 [-]: MOVE      R0 R26       ; R0 := R26
125 [-]: MOVE      R0 R7        ; R0 := R7
126 [-]: CLOSURE   R37 15       ; R37 := closure(Function #16)
127 [-]: MOVE      R0 R0        ; R0 := R0
128 [-]: MOVE      R0 R15       ; R0 := R15
129 [-]: MOVE      R0 R14       ; R0 := R14
130 [-]: MOVE      R0 R34       ; R0 := R34
131 [-]: MOVE      R0 R35       ; R0 := R35
132 [-]: MOVE      R0 R36       ; R0 := R36
133 [-]: SETGLOBAL R37 K19      ; InfestLoop := R37
134 [-]: CLOSURE   R37 16       ; R37 := closure(Function #17)
135 [-]: MOVE      R0 R27       ; R0 := R27
136 [-]: MOVE      R0 R14       ; R0 := R14
137 [-]: MOVE      R0 R15       ; R0 := R15
138 [-]: MOVE      R0 R16       ; R0 := R16
139 [-]: MOVE      R0 R17       ; R0 := R17
140 [-]: MOVE      R0 R18       ; R0 := R18
141 [-]: MOVE      R0 R28       ; R0 := R28
142 [-]: MOVE      R0 R4        ; R0 := R4
143 [-]: MOVE      R0 R29       ; R0 := R29
144 [-]: MOVE      R0 R19       ; R0 := R19
145 [-]: MOVE      R0 R30       ; R0 := R30
146 [-]: MOVE      R0 R5        ; R0 := R5
147 [-]: MOVE      R0 R13       ; R0 := R13
148 [-]: MOVE      R0 R0        ; R0 := R0
149 [-]: MOVE      R0 R8        ; R0 := R8
150 [-]: MOVE      R0 R7        ; R0 := R7
151 [-]: SETGLOBAL R37 K20      ; ActivateAbility := R37
152 [-]: CLOSURE   R37 17       ; R37 := closure(Function #18)
153 [-]: MOVE      R0 R0        ; R0 := R0
154 [-]: SETGLOBAL R37 K21      ; DeactivateAbility := R37
155 [-]: CLOSURE   R37 18       ; R37 := closure(Function #19)
156 [-]: SETGLOBAL R37 K22      ; AllPodsDestroyed := R37
157 [-]: CLOSURE   R37 19       ; R37 := closure(Function #20)
158 [-]: MOVE      R0 R4        ; R0 := R4
159 [-]: MOVE      R0 R27       ; R0 := R27
160 [-]: MOVE      R0 R15       ; R0 := R15
161 [-]: MOVE      R0 R0        ; R0 := R0
162 [-]: MOVE      R0 R14       ; R0 := R14
163 [-]: MOVE      R0 R6        ; R0 := R6
164 [-]: SETGLOBAL R37 K23      ; OnDeath := R37
165 [-]: CLOSURE   R37 20       ; R37 := closure(Function #21)
166 [-]: MOVE      R0 R24       ; R0 := R24
167 [-]: MOVE      R0 R23       ; R0 := R23
168 [-]: MOVE      R0 R20       ; R0 := R20
169 [-]: MOVE      R0 R21       ; R0 := R21
170 [-]: SETGLOBAL R37 K24      ; ColorPods := R37
171 [-]: RETURN    R0 1         ; return 


; Function #1:
;
; Name:            
; Defined at line: 58
; #Upvalues:       8
; #Parameters:     1
; Is_vararg:       0
; Max Stack Size:  2

  1 [-]: GETUPVAL  R1 U0        ; R1 := U0
  2 [-]: GETTABLE  R1 R1 K0     ; R1 := R1[0x32316a21]
  3 [-]: CALL      R1 1 2       ; R1 := R1()
  4 [-]: TEST      R1 1         ; if R1 then PC := 56
  5 [-]: JMP       56           ; PC := 56
  6 [-]: EQ        0 R0 K1      ; if R0 ~= 1.000000 then PC := 19
  7 [-]: JMP       19           ; PC := 19
  8 [-]: CONST     R1 4         ; R1 := 4.000000
  9 [-]: SETUPVAL  R1 U1        ; U82 := R1
 10 [-]: CONST     R1 100       ; R1 := 100.000000
 11 [-]: SETUPVAL  R1 U2        ; U82 := R2
 12 [-]: CONST     R1 25        ; R1 := 25.000000
 13 [-]: SETUPVAL  R1 U3        ; U82 := R3
 14 [-]: CONST     R1 8         ; R1 := 8.000000
 15 [-]: SETUPVAL  R1 U4        ; U82 := R4
 16 [-]: CONST     R1 10        ; R1 := 10.000000
 17 [-]: SETUPVAL  R1 U5        ; U82 := R5
 18 [-]: JMP       109          ; PC := 109
 19 [-]: EQ        0 R0 K2      ; if R0 ~= 2.000000 then PC := 32
 20 [-]: JMP       32           ; PC := 32
 21 [-]: CONST     R1 4         ; R1 := 4.000000
 22 [-]: SETUPVAL  R1 U1        ; U82 := R1
 23 [-]: CONST     R1 110       ; R1 := 110.000000
 24 [-]: SETUPVAL  R1 U2        ; U82 := R2
 25 [-]: CONST     R1 30        ; R1 := 30.000000
 26 [-]: SETUPVAL  R1 U3        ; U82 := R3
 27 [-]: CONST     R1 8         ; R1 := 8.000000
 28 [-]: SETUPVAL  R1 U4        ; U82 := R4
 29 [-]: CONST     R1 13        ; R1 := 13.000000
 30 [-]: SETUPVAL  R1 U5        ; U82 := R5
 31 [-]: JMP       109          ; PC := 109
 32 [-]: EQ        0 R0 K3      ; if R0 ~= 3.000000 then PC := 45
 33 [-]: JMP       45           ; PC := 45
 34 [-]: CONST     R1 4         ; R1 := 4.000000
 35 [-]: SETUPVAL  R1 U1        ; U82 := R1
 36 [-]: CONST     R1 125       ; R1 := 125.000000
 37 [-]: SETUPVAL  R1 U2        ; U82 := R2
 38 [-]: CONST     R1 35        ; R1 := 35.000000
 39 [-]: SETUPVAL  R1 U3        ; U82 := R3
 40 [-]: CONST     R1 8         ; R1 := 8.000000
 41 [-]: SETUPVAL  R1 U4        ; U82 := R4
 42 [-]: CONST     R1 16        ; R1 := 16.000000
 43 [-]: SETUPVAL  R1 U5        ; U82 := R5
 44 [-]: JMP       109          ; PC := 109
 45 [-]: CONST     R1 4         ; R1 := 4.000000
 46 [-]: SETUPVAL  R1 U1        ; U82 := R1
 47 [-]: CONST     R1 150       ; R1 := 150.000000
 48 [-]: SETUPVAL  R1 U2        ; U82 := R2
 49 [-]: CONST     R1 40        ; R1 := 40.000000
 50 [-]: SETUPVAL  R1 U3        ; U82 := R3
 51 [-]: CONST     R1 8         ; R1 := 8.000000
 52 [-]: SETUPVAL  R1 U4        ; U82 := R4
 53 [-]: CONST     R1 20        ; R1 := 20.000000
 54 [-]: SETUPVAL  R1 U5        ; U82 := R5
 55 [-]: JMP       109          ; PC := 109
 56 [-]: CONST     R1 1         ; R1 := 1.000000
 57 [-]: SETUPVAL  R1 U6        ; U82 := R6
 58 [-]: CONST     R1 5         ; R1 := 5.000000
 59 [-]: SETUPVAL  R1 U7        ; U82 := R7
 60 [-]: EQ        0 R0 K1      ; if R0 ~= 1.000000 then PC := 73
 61 [-]: JMP       73           ; PC := 73
 62 [-]: CONST     R1 1         ; R1 := 1.000000
 63 [-]: SETUPVAL  R1 U1        ; U82 := R1
 64 [-]: CONST     R1 140       ; R1 := 140.000000
 65 [-]: SETUPVAL  R1 U2        ; U82 := R2
 66 [-]: CONST     R1 7         ; R1 := 7.000000
 67 [-]: SETUPVAL  R1 U3        ; U82 := R3
 68 [-]: CONST     R1 8         ; R1 := 8.000000
 69 [-]: SETUPVAL  R1 U4        ; U82 := R4
 70 [-]: CONST     R1 7         ; R1 := 7.000000
 71 [-]: SETUPVAL  R1 U5        ; U82 := R5
 72 [-]: JMP       109          ; PC := 109
 73 [-]: EQ        0 R0 K2      ; if R0 ~= 2.000000 then PC := 86
 74 [-]: JMP       86           ; PC := 86
 75 [-]: CONST     R1 2         ; R1 := 2.000000
 76 [-]: SETUPVAL  R1 U1        ; U82 := R1
 77 [-]: CONST     R1 160       ; R1 := 160.000000
 78 [-]: SETUPVAL  R1 U2        ; U82 := R2
 79 [-]: CONST     R1 8         ; R1 := 8.000000
 80 [-]: SETUPVAL  R1 U3        ; U82 := R3
 81 [-]: CONST     R1 8         ; R1 := 8.000000
 82 [-]: SETUPVAL  R1 U4        ; U82 := R4
 83 [-]: CONST     R1 8         ; R1 := 8.000000
 84 [-]: SETUPVAL  R1 U5        ; U82 := R5
 85 [-]: JMP       109          ; PC := 109
 86 [-]: EQ        0 R0 K3      ; if R0 ~= 3.000000 then PC := 99
 87 [-]: JMP       99           ; PC := 99
 88 [-]: CONST     R1 3         ; R1 := 3.000000
 89 [-]: SETUPVAL  R1 U1        ; U82 := R1
 90 [-]: CONST     R1 180       ; R1 := 180.000000
 91 [-]: SETUPVAL  R1 U2        ; U82 := R2
 92 [-]: CONST     R1 9         ; R1 := 9.000000
 93 [-]: SETUPVAL  R1 U3        ; U82 := R3
 94 [-]: CONST     R1 8         ; R1 := 8.000000
 95 [-]: SETUPVAL  R1 U4        ; U82 := R4
 96 [-]: CONST     R1 9         ; R1 := 9.000000
 97 [-]: SETUPVAL  R1 U5        ; U82 := R5
 98 [-]: JMP       109          ; PC := 109
 99 [-]: CONST     R1 4         ; R1 := 4.000000
100 [-]: SETUPVAL  R1 U1        ; U82 := R1
101 [-]: CONST     R1 200       ; R1 := 200.000000
102 [-]: SETUPVAL  R1 U2        ; U82 := R2
103 [-]: CONST     R1 10        ; R1 := 10.000000
104 [-]: SETUPVAL  R1 U3        ; U82 := R3
105 [-]: CONST     R1 8         ; R1 := 8.000000
106 [-]: SETUPVAL  R1 U4        ; U82 := R4
107 [-]: CONST     R1 10        ; R1 := 10.000000
108 [-]: SETUPVAL  R1 U5        ; U82 := R5
109 [-]: RETURN    R0 1         ; return 


; Function #2:
;
; Name:            
; Defined at line: 117
; #Upvalues:       5
; #Parameters:     1
; Is_vararg:       0
; Max Stack Size:  15

  1 [-]: GETUPVAL  R1 U0        ; R1 := U0
  2 [-]: GETGLOBAL R2 K0        ; R2 := 0x34291f5c
  3 [-]: GETTABLE  R2 R2 K1     ; R2 := R2[0x7258f36f]
  4 [-]: GETUPVAL  R3 U1        ; R3 := U1
  5 [-]: CALL      R2 2 2       ; R2 := R2(R3)
  6 [-]: GETUPVAL  R3 U2        ; R3 := U2
  7 [-]: GETUPVAL  R4 U3        ; R4 := U3
  8 [-]: GETUPVAL  R5 U4        ; R5 := U4
  9 [-]: GETGLOBAL R6 K2        ; R6 := 0x7b998233
 10 [-]: MOVE      R7 R0        ; R7 := R0
 11 [-]: CALL      R6 2 2       ; R6 := R6(R7)
 12 [-]: TEST      R6 1         ; if R6 then PC := 53
 13 [-]: JMP       53           ; PC := 53
 14 [-]: SELF      R6 R0 K3     ; R7 := R0; R6 := R0[0xde321e6f]
 15 [-]: CALL      R6 2 2       ; R6 := R6(R7)
 16 [-]: SELF      R7 R6 K4     ; R8 := R6; R7 := R6[0xf7d48ee0]
 17 [-]: CALL      R7 2 2       ; R7 := R7(R8)
 18 [-]: GETGLOBAL R8 K2        ; R8 := 0x7b998233
 19 [-]: MOVE      R9 R7        ; R9 := R7
 20 [-]: CALL      R8 2 2       ; R8 := R8(R9)
 21 [-]: TEST      R8 1         ; if R8 then PC := 53
 22 [-]: JMP       53           ; PC := 53
 23 [-]: SELF      R8 R7 K5     ; R9 := R7; R8 := R7[0xcde10c4a]
 24 [-]: CALL      R8 2 2       ; R8 := R8(R9)
 25 [-]: SELF      R9 R6 K6     ; R10 := R6; R9 := R6[0xe9f54086]
 26 [-]: GETUPVAL  R11 U0       ; R11 := U0
 27 [-]: CONST     R12 9        ; R12 := 9.000000
 28 [-]: MOVE      R13 R8       ; R13 := R8
 29 [-]: MOVE      R14 R7       ; R14 := R7
 30 [-]: CALL      R9 6 2       ; R9 := R9(R10,R11,R12,R13,R14)
 31 [-]: MOVE      R1 R9        ; R1 := R9
 32 [-]: SELF      R9 R6 K8     ; R10 := R6; R9 := R6[0x54ba011d]
 33 [-]: MOVE      R11 R2       ; R11 := R2
 34 [-]: CONST     R12 10       ; R12 := 10.000000
 35 [-]: MOVE      R13 R8       ; R13 := R8
 36 [-]: MOVE      R14 R7       ; R14 := R7
 37 [-]: CALL      R9 6 1       ; R9(R10,R11,R12,R13,R14)
 38 [-]: SELF      R9 R6 K6     ; R10 := R6; R9 := R6[0xe9f54086]
 39 [-]: GETUPVAL  R11 U2       ; R11 := U2
 40 [-]: CONST     R12 3        ; R12 := 3.000000
 41 [-]: MOVE      R13 R8       ; R13 := R8
 42 [-]: MOVE      R14 R7       ; R14 := R7
 43 [-]: CALL      R9 6 2       ; R9 := R9(R10,R11,R12,R13,R14)
 44 [-]: MOVE      R3 R9        ; R3 := R9
 45 [-]: SELF      R9 R6 K6     ; R10 := R6; R9 := R6[0xe9f54086]
 46 [-]: GETUPVAL  R11 U4       ; R11 := U4
 47 [-]: CONST     R12 10       ; R12 := 10.000000
 48 [-]: SELF      R13 R7 K5    ; R14 := R7; R13 := R7[0xcde10c4a]
 49 [-]: CALL      R13 2 2      ; R13 := R13(R14)
 50 [-]: MOVE      R14 R7       ; R14 := R7
 51 [-]: CALL      R9 6 2       ; R9 := R9(R10,R11,R12,R13,R14)
 52 [-]: MOVE      R5 R9        ; R5 := R9
 53 [-]: MOVE      R9 R1        ; R9 := R1
 54 [-]: MOVE      R10 R2       ; R10 := R2
 55 [-]: MOVE      R11 R3       ; R11 := R3
 56 [-]: MOVE      R12 R4       ; R12 := R4
 57 [-]: MOVE      R13 R5       ; R13 := R5
 58 [-]: RETURN    R9 6         ; return R9,R10,R11,R12,R13
 59 [-]: RETURN    R0 1         ; return 


; Function #3:
;
; Name:            
; Defined at line: 144
; #Upvalues:       1
; #Parameters:     2
; Is_vararg:       0
; Max Stack Size:  3

  1 [-]: EQ        0 R1 K1      ; if R1 ~= 1.000000 then PC := 20
  2 [-]: JMP       20           ; PC := 20
  3 [-]: EQ        0 R0 K1      ; if R0 ~= 1.000000 then PC := 8
  4 [-]: JMP       8            ; PC := 8
  5 [-]: LOADK     R2 K2        ; R2 := 0.350000
  6 [-]: SETUPVAL  R2 U0        ; U82 := R0
  7 [-]: JMP       20           ; PC := 20
  8 [-]: EQ        0 R0 K3      ; if R0 ~= 2.000000 then PC := 13
  9 [-]: JMP       13           ; PC := 13
 10 [-]: LOADK     R2 K4        ; R2 := 0.400000
 11 [-]: SETUPVAL  R2 U0        ; U82 := R0
 12 [-]: JMP       20           ; PC := 20
 13 [-]: EQ        0 R0 K5      ; if R0 ~= 3.000000 then PC := 18
 14 [-]: JMP       18           ; PC := 18
 15 [-]: CONST     R2 0         ; R2 := 0.500000
 16 [-]: SETUPVAL  R2 U0        ; U82 := R0
 17 [-]: JMP       20           ; PC := 20
 18 [-]: LOADK     R2 K6        ; R2 := 0.600000
 19 [-]: SETUPVAL  R2 U0        ; U82 := R0
 20 [-]: RETURN    R0 1         ; return 


; Function #4:
;
; Name:            
; Defined at line: 158
; #Upvalues:       1
; #Parameters:     2
; Is_vararg:       0
; Max Stack Size:  11

  1 [-]: SELF      R2 R0 K0     ; R3 := R0; R2 := R0[0xde321e6f]
  2 [-]: CALL      R2 2 2       ; R2 := R2(R3)
  3 [-]: SELF      R3 R2 K1     ; R4 := R2; R3 := R2[0xf7d48ee0]
  4 [-]: CALL      R3 2 2       ; R3 := R3(R4)
  5 [-]: SELF      R4 R3 K2     ; R5 := R3; R4 := R3[0xcde10c4a]
  6 [-]: CALL      R4 2 2       ; R4 := R4(R5)
  7 [-]: EQ        0 R1 K4      ; if R1 ~= 1.000000 then PC := 16
  8 [-]: JMP       16           ; PC := 16
  9 [-]: SELF      R5 R2 K5     ; R6 := R2; R5 := R2[0xe9f54086]
 10 [-]: GETUPVAL  R7 U0        ; R7 := U0
 11 [-]: CONST     R8 10        ; R8 := 10.000000
 12 [-]: MOVE      R9 R4        ; R9 := R4
 13 [-]: MOVE      R10 R3       ; R10 := R3
 14 [-]: TAILCALL  R5 6 0       ; R5,... := R5(R6,R7,R8,R9,R10)
 15 [-]: RETURN    R5 0         ; return R5,...
 16 [-]: LOADNIL   R5 R5        ; R5 := nil
 17 [-]: RETURN    R5 2         ; return R5
 18 [-]: RETURN    R0 1         ; return 


; Function #5:
;
; Name:            
; Defined at line: 170
; #Upvalues:       3
; #Parameters:     1
; Is_vararg:       0
; Max Stack Size:  12

  1 [-]: GETGLOBAL R1 K0        ; R1 := _T
  2 [-]: GETTABLE  R1 R1 K1     ; R1 := R1["AbilityLevelQueryParms"]
  3 [-]: GETTABLE  R1 R1 K2     ; R1 := R1["Avatar"]
  4 [-]: GETGLOBAL R2 K3        ; R2 := 0x7b998233
  5 [-]: MOVE      R3 R1        ; R3 := R1
  6 [-]: CALL      R2 2 2       ; R2 := R2(R3)
  7 [-]: TEST      R2 0         ; if not R2 then PC := 10
  8 [-]: JMP       10           ; PC := 10
  9 [-]: RETURN    R0 1         ; return 
 10 [-]: SELF      R2 R1 K4     ; R3 := R1; R2 := R1[0xde321e6f]
 11 [-]: CALL      R2 2 2       ; R2 := R2(R3)
 12 [-]: SELF      R3 R2 K5     ; R4 := R2; R3 := R2[0xf7d48ee0]
 13 [-]: CALL      R3 2 2       ; R3 := R3(R4)
 14 [-]: GETGLOBAL R4 K3        ; R4 := 0x7b998233
 15 [-]: MOVE      R5 R3        ; R5 := R3
 16 [-]: CALL      R4 2 2       ; R4 := R4(R5)
 17 [-]: TEST      R4 0         ; if not R4 then PC := 20
 18 [-]: JMP       20           ; PC := 20
 19 [-]: RETURN    R0 1         ; return 
 20 [-]: SELF      R4 R3 K6     ; R5 := R3; R4 := R3[0xa2356091]
 21 [-]: GETGLOBAL R6 K0        ; R6 := _T
 22 [-]: GETTABLE  R6 R6 K1     ; R6 := R6["AbilityLevelQueryParms"]
 23 [-]: GETTABLE  R6 R6 K7     ; R6 := R6["Ability"]
 24 [-]: CALL      R4 3 2       ; R4 := R4(R5,R6)
 25 [-]: SELF      R5 R3 K8     ; R6 := R3; R5 := R3[0xd836367c]
 26 [-]: CALL      R5 2 2       ; R5 := R5(R6)
 27 [-]: LE        0 R5 R4      ; if R5 > R4 then PC := 30
 28 [-]: JMP       30           ; PC := 30
 29 [-]: RETURN    R0 1         ; return 
 30 [-]: SELF      R5 R3 K9     ; R6 := R3; R5 := R3[0x5063edc3]
 31 [-]: MOVE      R7 R4        ; R7 := R4
 32 [-]: CALL      R5 3 2       ; R5 := R5(R6,R7)
 33 [-]: LE        0 R5 K10     ; if R5 > 0.000000 then PC := 36
 34 [-]: JMP       36           ; PC := 36
 35 [-]: RETURN    R0 1         ; return 
 36 [-]: SELF      R6 R3 K11    ; R7 := R3; R6 := R3[0x75ecaf0b]
 37 [-]: MOVE      R8 R4        ; R8 := R4
 38 [-]: CALL      R6 3 2       ; R6 := R6(R7,R8)
 39 [-]: GETUPVAL  R7 U0        ; R7 := U0
 40 [-]: MOVE      R8 R5        ; R8 := R5
 41 [-]: MOVE      R9 R6        ; R9 := R6
 42 [-]: CALL      R7 3 1       ; R7(R8,R9)
 43 [-]: EQ        0 R6 K13     ; if R6 ~= 1.000000 then PC := 75
 44 [-]: JMP       75           ; PC := 75
 45 [-]: GETGLOBAL R7 K0        ; R7 := _T
 46 [-]: GETTABLE  R7 R7 K1     ; R7 := R7["AbilityLevelQueryParms"]
 47 [-]: GETTABLE  R7 R7 K14    ; R7 := R7["Modded"]
 48 [-]: TEST      R7 0         ; if not R7 then PC := 55
 49 [-]: JMP       55           ; PC := 55
 50 [-]: GETUPVAL  R7 U2        ; R7 := U2
 51 [-]: MOVE      R8 R1        ; R8 := R1
 52 [-]: MOVE      R9 R6        ; R9 := R6
 53 [-]: CALL      R7 3 2       ; R7 := R7(R8,R9)
 54 [-]: SETUPVAL  R7 U1        ; U82 := R1
 55 [-]: GETGLOBAL R7 K15       ; R7 := 0x33bdd652
 56 [-]: GETTABLE  R7 R7 K16    ; R7 := R7[0x23d5322f]
 57 [-]: MOVE      R8 R0        ; R8 := R0
 58 [-]: NEWTABLE  R9 0 2       ; R9 := {}
 59 [-]: SETTABLE  R9 K17 K18   ; R9["Label"] := "/Lotus/Language/Suits/InfestAbilityAugment1Name"
 60 [-]: SETTABLE  R9 K19 K20   ; R9["Title"] := true
 61 [-]: CALL      R7 3 1       ; R7(R8,R9)
 62 [-]: GETGLOBAL R7 K15       ; R7 := 0x33bdd652
 63 [-]: GETTABLE  R7 R7 K16    ; R7 := R7[0x23d5322f]
 64 [-]: MOVE      R8 R0        ; R8 := R0
 65 [-]: NEWTABLE  R9 0 3       ; R9 := {}
 66 [-]: SETTABLE  R9 K17 K21   ; R9["Label"] := "/Lotus/Language/Labels/AVATAR_SUCCESS_CHANCE"
 67 [-]: GETGLOBAL R10 K23      ; R10 := 0x5bced4c4
 68 [-]: GETTABLE  R10 R10 K24  ; R10 := R10[0x55f27c30]
 69 [-]: GETUPVAL  R11 U1       ; R11 := U1
 70 [-]: MUL       R11 R11 K25  ; R11 := R11 * 100.000000
 71 [-]: CALL      R10 2 2      ; R10 := R10(R11)
 72 [-]: SETTABLE  R9 K22 R10   ; R9["Value"] := R10
 73 [-]: SETTABLE  R9 K26 K27   ; R9["ValueUnit"] := "/Lotus/Language/Game/UNIT_PERCENT"
 74 [-]: CALL      R7 3 1       ; R7(R8,R9)
 75 [-]: RETURN    R0 1         ; return 


; Function #6:
;
; Name:            
; Defined at line: 205
; #Upvalues:       9
; #Parameters:     0
; Is_vararg:       0
; Max Stack Size:  6

  1 [-]: GETGLOBAL R0 K0        ; R0 := _T
  2 [-]: GETTABLE  R0 R0 K1     ; R0 := R0["AbilityLevelQueryParms"]
  3 [-]: GETTABLE  R0 R0 K2     ; R0 := R0["Level"]
  4 [-]: GETUPVAL  R1 U0        ; R1 := U0
  5 [-]: MOVE      R2 R0        ; R2 := R0
  6 [-]: CALL      R1 2 1       ; R1(R2)
  7 [-]: GETGLOBAL R1 K0        ; R1 := _T
  8 [-]: GETTABLE  R1 R1 K1     ; R1 := R1["AbilityLevelQueryParms"]
  9 [-]: GETTABLE  R1 R1 K3     ; R1 := R1["Modded"]
 10 [-]: EQ        0 R1 K4      ; if R1 ~= true then PC := 26
 11 [-]: JMP       26           ; PC := 26
 12 [-]: GETUPVAL  R1 U6        ; R1 := U6
 13 [-]: GETGLOBAL R2 K0        ; R2 := _T
 14 [-]: GETTABLE  R2 R2 K1     ; R2 := R2["AbilityLevelQueryParms"]
 15 [-]: GETTABLE  R2 R2 K5     ; R2 := R2["Avatar"]
 16 [-]: CALL      R1 2 6       ; R1,R2,R3,R4,R5 := R1(R2)
 17 [-]: SETUPVAL  R5 U5        ; U82 := R5
 18 [-]: SETUPVAL  R4 U4        ; U82 := R4
 19 [-]: SETUPVAL  R3 U3        ; U82 := R3
 20 [-]: SETUPVAL  R2 U2        ; U82 := R2
 21 [-]: SETUPVAL  R1 U1        ; U82 := R1
 22 [-]: GETUPVAL  R1 U2        ; R1 := U2
 23 [-]: SELF      R1 R1 K6     ; R2 := R1; R1 := R1[0x838305de]
 24 [-]: CALL      R1 2 2       ; R1 := R1(R2)
 25 [-]: SETUPVAL  R1 U2        ; U82 := R2
 26 [-]: NEWTABLE  R1 0 0       ; R1 := {}
 27 [-]: GETGLOBAL R2 K7        ; R2 := 0x33bdd652
 28 [-]: GETTABLE  R2 R2 K8     ; R2 := R2[0x23d5322f]
 29 [-]: MOVE      R3 R1        ; R3 := R1
 30 [-]: NEWTABLE  R4 0 2       ; R4 := {}
 31 [-]: SETTABLE  R4 K9 K10    ; R4["Label"] := "/Lotus/Language/Game/INFECT_ADAPTATION_COST"
 32 [-]: GETUPVAL  R5 U7        ; R5 := U7
 33 [-]: SETTABLE  R4 K11 R5    ; R4["Value"] := R5
 34 [-]: CALL      R2 3 1       ; R2(R3,R4)
 35 [-]: GETGLOBAL R2 K7        ; R2 := 0x33bdd652
 36 [-]: GETTABLE  R2 R2 K8     ; R2 := R2[0x23d5322f]
 37 [-]: MOVE      R3 R1        ; R3 := R1
 38 [-]: NEWTABLE  R4 0 3       ; R4 := {}
 39 [-]: SETTABLE  R4 K9 K12    ; R4["Label"] := "/Lotus/Language/Labels/WEAPON_EXPLOSION_RADIUS"
 40 [-]: GETUPVAL  R5 U1        ; R5 := U1
 41 [-]: SETTABLE  R4 K11 R5    ; R4["Value"] := R5
 42 [-]: SETTABLE  R4 K13 K14   ; R4["ValueUnit"] := "/Lotus/Language/Game/UNIT_METER"
 43 [-]: CALL      R2 3 1       ; R2(R3,R4)
 44 [-]: GETGLOBAL R2 K7        ; R2 := 0x33bdd652
 45 [-]: GETTABLE  R2 R2 K8     ; R2 := R2[0x23d5322f]
 46 [-]: MOVE      R3 R1        ; R3 := R1
 47 [-]: NEWTABLE  R4 0 3       ; R4 := {}
 48 [-]: SETTABLE  R4 K9 K15    ; R4["Label"] := "/Lotus/Language/Game/MAGGOT_RUPTURE_DAMAGE"
 49 [-]: GETUPVAL  R5 U2        ; R5 := U2
 50 [-]: SETTABLE  R4 K11 R5    ; R4["Value"] := R5
 51 [-]: SETTABLE  R4 K16 K17   ; R4["ValueIcon"] := "<DT_EXPLOSION>"
 52 [-]: CALL      R2 3 1       ; R2(R3,R4)
 53 [-]: GETGLOBAL R2 K7        ; R2 := 0x33bdd652
 54 [-]: GETTABLE  R2 R2 K8     ; R2 := R2[0x23d5322f]
 55 [-]: MOVE      R3 R1        ; R3 := R1
 56 [-]: NEWTABLE  R4 0 3       ; R4 := {}
 57 [-]: SETTABLE  R4 K9 K18    ; R4["Label"] := "/Lotus/Language/Game/ABILITY_RADIUS"
 58 [-]: GETUPVAL  R5 U4        ; R5 := U4
 59 [-]: SETTABLE  R4 K11 R5    ; R4["Value"] := R5
 60 [-]: SETTABLE  R4 K13 K14   ; R4["ValueUnit"] := "/Lotus/Language/Game/UNIT_METER"
 61 [-]: CALL      R2 3 1       ; R2(R3,R4)
 62 [-]: GETGLOBAL R2 K7        ; R2 := 0x33bdd652
 63 [-]: GETTABLE  R2 R2 K8     ; R2 := R2[0x23d5322f]
 64 [-]: MOVE      R3 R1        ; R3 := R1
 65 [-]: NEWTABLE  R4 0 2       ; R4 := {}
 66 [-]: SETTABLE  R4 K9 K19    ; R4["Label"] := "/Lotus/Language/Game/INFEST_HEAL_RATE"
 67 [-]: GETUPVAL  R5 U5        ; R5 := U5
 68 [-]: SETTABLE  R4 K11 R5    ; R4["Value"] := R5
 69 [-]: CALL      R2 3 1       ; R2(R3,R4)
 70 [-]: GETGLOBAL R2 K7        ; R2 := 0x33bdd652
 71 [-]: GETTABLE  R2 R2 K8     ; R2 := R2[0x23d5322f]
 72 [-]: MOVE      R3 R1        ; R3 := R1
 73 [-]: NEWTABLE  R4 0 3       ; R4 := {}
 74 [-]: SETTABLE  R4 K9 K20    ; R4["Label"] := "/Lotus/Language/Game/ABILITY_DURATION"
 75 [-]: GETUPVAL  R5 U3        ; R5 := U3
 76 [-]: SETTABLE  R4 K11 R5    ; R4["Value"] := R5
 77 [-]: SETTABLE  R4 K13 K21   ; R4["ValueUnit"] := "/Lotus/Language/Game/UNIT_SECOND"
 78 [-]: CALL      R2 3 1       ; R2(R3,R4)
 79 [-]: GETUPVAL  R2 U8        ; R2 := U8
 80 [-]: MOVE      R3 R1        ; R3 := R1
 81 [-]: CALL      R2 2 1       ; R2(R3)
 82 [-]: GETGLOBAL R2 K0        ; R2 := _T
 83 [-]: GETTABLE  R2 R2 K1     ; R2 := R2["AbilityLevelQueryParms"]
 84 [-]: GETTABLE  R2 R2 K3     ; R2 := R2["Modded"]
 85 [-]: SETTABLE  R1 K3 R2     ; R1["Modded"] := R2
 86 [-]: GETGLOBAL R2 K0        ; R2 := _T
 87 [-]: SETTABLE  R2 K22 R1    ; R2["AbilityUpgradeLevelInfo"] := R1
 88 [-]: RETURN    R0 1         ; return 


; Function #7:
;
; Name:            
; Defined at line: 228
; #Upvalues:       3
; #Parameters:     2
; Is_vararg:       0
; Max Stack Size:  8

  1 [-]: NEWTABLE  R2 0 0       ; R2 := {}
  2 [-]: GETUPVAL  R3 U0        ; R3 := U0
  3 [-]: MOVE      R4 R0        ; R4 := R0
  4 [-]: MOVE      R5 R1        ; R5 := R1
  5 [-]: CALL      R3 3 1       ; R3(R4,R5)
  6 [-]: EQ        0 R1 K1      ; if R1 ~= 1.000000 then PC := 18
  7 [-]: JMP       18           ; PC := 18
  8 [-]: NEWTABLE  R3 0 1       ; R3 := {}
  9 [-]: GETUPVAL  R4 U1        ; R4 := U1
 10 [-]: GETTABLE  R4 R4 K3     ; R4 := R4[0x1142c7a8]
 11 [-]: GETUPVAL  R5 U2        ; R5 := U2
 12 [-]: MUL       R5 R5 K4     ; R5 := R5 * 100.000000
 13 [-]: CONST     R6 1         ; R6 := 1.000000
 14 [-]: LOADKB    R7 0 0       ; R7 := false
 15 [-]: CALL      R4 4 2       ; R4 := R4(R5,R6,R7)
 16 [-]: SETTABLE  R3 K2 R4     ; R3["CHANCE"] := R4
 17 [-]: MOVE      R2 R3        ; R2 := R3
 18 [-]: GETGLOBAL R3 K5        ; R3 := cjson
 19 [-]: GETTABLE  R3 R3 K6     ; R3 := R3[0xb139d7bc]
 20 [-]: MOVE      R4 R2        ; R4 := R2
 21 [-]: TAILCALL  R3 2 0       ; R3,... := R3(R4)
 22 [-]: RETURN    R3 0         ; return R3,...
 23 [-]: RETURN    R0 1         ; return 


; Function #8:
;
; Name:            
; Defined at line: 241
; #Upvalues:       2
; #Parameters:     3
; Is_vararg:       0
; Max Stack Size:  11

  1 [-]: GETUPVAL  R3 U0        ; R3 := U0
  2 [-]: MOVE      R4 R2        ; R4 := R2
  3 [-]: CALL      R3 2 1       ; R3(R4)
  4 [-]: CONST     R3 0         ; R3 := 0.000000
  5 [-]: GETGLOBAL R4 K0        ; R4 := _T
  6 [-]: GETTABLE  R4 R4 K1     ; R4 := R4["INFESTED_GetStacks"]
  7 [-]: EQ        1 R4 K2      ; if R4 == nil then PC := 14
  8 [-]: JMP       14           ; PC := 14
  9 [-]: GETGLOBAL R4 K0        ; R4 := _T
 10 [-]: GETTABLE  R4 R4 K3     ; R4 := R4[0x85ed3714]
 11 [-]: MOVE      R5 R0        ; R5 := R0
 12 [-]: CALL      R4 2 2       ; R4 := R4(R5)
 13 [-]: MOVE      R3 R4        ; R3 := R4
 14 [-]: GETUPVAL  R4 U1        ; R4 := U1
 15 [-]: LT        0 R3 R4      ; if R3 >= R4 then PC := 45
 16 [-]: JMP       45           ; PC := 45
 17 [-]: GETGLOBAL R4 K0        ; R4 := _T
 18 [-]: GETTABLE  R4 R4 K4     ; R4 := R4["INFESTED_ShowNotEnoughStacks"]
 19 [-]: EQ        1 R4 K2      ; if R4 == nil then PC := 24
 20 [-]: JMP       24           ; PC := 24
 21 [-]: GETGLOBAL R4 K0        ; R4 := _T
 22 [-]: GETTABLE  R4 R4 K5     ; R4 := R4[0x043e1392]
 23 [-]: CALL      R4 1 1       ; R4()
 24 [-]: GETUPVAL  R4 U1        ; R4 := U1
 25 [-]: SUB       R4 R4 R3     ; R4 := R4 - R3
 26 [-]: EQ        0 R4 K6      ; if R4 ~= 1.000000 then PC := 34
 27 [-]: JMP       34           ; PC := 34
 28 [-]: SELF      R5 R1 K7     ; R6 := R1; R5 := R1[0xd7091d77]
 29 [-]: GETGLOBAL R7 K8        ; R7 := 0x0469f296
 30 [-]: LOADK     R8 K9        ; R8 := "/Lotus/Language/Game/InfestedPods_OneMoreStack"
 31 [-]: CALL      R7 2 0       ; R7,... := R7(R8)
 32 [-]: CALL      R5 0 1       ; R5(R6,...)
 33 [-]: JMP       43           ; PC := 43
 34 [-]: SELF      R5 R1 K7     ; R6 := R1; R5 := R1[0xd7091d77]
 35 [-]: GETGLOBAL R7 K8        ; R7 := 0x0469f296
 36 [-]: GETGLOBAL R8 K10       ; R8 := 0x603636ad
 37 [-]: LOADK     R9 K11       ; R9 := "/Lotus/Language/Game/InfestedPods_XMoreStacks"
 38 [-]: NEWTABLE  R10 0 1      ; R10 := {}
 39 [-]: SETTABLE  R10 K12 R4   ; R10["COUNT"] := R4
 40 [-]: CALL      R8 3 0       ; R8,... := R8(R9,R10)
 41 [-]: CALL      R7 0 0       ; R7,... := R7(R8,...)
 42 [-]: CALL      R5 0 1       ; R5(R6,...)
 43 [-]: LOADKB    R5 0 0       ; R5 := false
 44 [-]: RETURN    R5 2         ; return R5
 45 [-]: LOADKB    R5 1 0       ; R5 := true
 46 [-]: RETURN    R5 2         ; return R5
 47 [-]: RETURN    R0 1         ; return 


; Function #9:
;
; Name:            
; Defined at line: 267
; #Upvalues:       0
; #Parameters:     3
; Is_vararg:       0
; Max Stack Size:  7

  1 [-]: SELF      R3 R1 K0     ; R4 := R1; R3 := R1[0xfa9e477f]
  2 [-]: CALL      R3 2 2       ; R3 := R3(R4)
  3 [-]: SELF      R3 R3 K1     ; R4 := R3; R3 := R3[0xa39bb54b]
  4 [-]: CALL      R3 2 2       ; R3 := R3(R4)
  5 [-]: GETTABLE  R4 R3 K2     ; R4 := R3["visible"]
  6 [-]: TEST      R4 0         ; if not R4 then PC := 29
  7 [-]: JMP       29           ; PC := 29
  8 [-]: GETGLOBAL R4 K3        ; R4 := 0x7b998233
  9 [-]: GETTABLE  R5 R3 K4     ; R5 := R3["avatar"]
 10 [-]: CALL      R4 2 2       ; R4 := R4(R5)
 11 [-]: TEST      R4 1         ; if R4 then PC := 29
 12 [-]: JMP       29           ; PC := 29
 13 [-]: GETTABLE  R4 R3 K4     ; R4 := R3["avatar"]
 14 [-]: SELF      R4 R4 K5     ; R5 := R4; R4 := R4[0x73901acf]
 15 [-]: CALL      R4 2 2       ; R4 := R4(R5)
 16 [-]: TEST      R4 1         ; if R4 then PC := 29
 17 [-]: JMP       29           ; PC := 29
 18 [-]: GETTABLE  R4 R3 K6     ; R4 := R3["distanceToTarget"]
 19 [-]: LE        0 K7 R4      ; if 1.000000 > R4 then PC := 29
 20 [-]: JMP       29           ; PC := 29
 21 [-]: GETTABLE  R4 R3 K6     ; R4 := R3["distanceToTarget"]
 22 [-]: LT        0 R4 K8      ; if R4 >= 16.000000 then PC := 29
 23 [-]: JMP       29           ; PC := 29
 24 [-]: SELF      R4 R0 K9     ; R5 := R0; R4 := R0[0x48d05257]
 25 [-]: GETTABLE  R6 R3 K4     ; R6 := R3["avatar"]
 26 [-]: CALL      R4 3 1       ; R4(R5,R6)
 27 [-]: CONST     R4 1         ; R4 := 1.000000
 28 [-]: RETURN    R4 2         ; return R4
 29 [-]: CONST     R4 0         ; R4 := 0.000000
 30 [-]: RETURN    R4 2         ; return R4
 31 [-]: RETURN    R0 1         ; return 


; Function #10:
;
; Name:            
; Defined at line: 284
; #Upvalues:       1
; #Parameters:     2
; Is_vararg:       0
; Max Stack Size:  6

  1 [-]: GETUPVAL  R2 U0        ; R2 := U0
  2 [-]: GETTABLE  R2 R2 K0     ; R2 := R2[0xe4ae0e66]
  3 [-]: CALL      R2 1 2       ; R2 := R2()
  4 [-]: TEST      R2 0         ; if not R2 then PC := 13
  5 [-]: JMP       13           ; PC := 13
  6 [-]: GETGLOBAL R2 K1        ; R2 := 0x6687f6e0
  7 [-]: SELF      R2 R2 K2     ; R3 := R2; R2 := R2[0x3a147087]
  8 [-]: GETGLOBAL R4 K3        ; R4 := 0xbe190284
  9 [-]: SELF      R4 R4 K4     ; R5 := R4; R4 := R4[0xc911409e]
 10 [-]: CALL      R4 2 2       ; R4 := R4(R5)
 11 [-]: ADD       R4 R4 K5     ; R4 := R4 + 100.000000
 12 [-]: CALL      R2 3 1       ; R2(R3,R4)
 13 [-]: RETURN    R0 1         ; return 


; Function #11:
;
; Name:            
; Defined at line: 290
; #Upvalues:       1
; #Parameters:     1
; Is_vararg:       0
; Max Stack Size:  15

  1 [-]: SELF      R1 R0 K0     ; R2 := R0; R1 := R0[0x68d708a7]
  2 [-]: CALL      R1 2 2       ; R1 := R1(R2)
  3 [-]: SELF      R2 R1 K1     ; R3 := R1; R2 := R1[0x8e62760a]
  4 [-]: CONST     R4 0         ; R4 := 0.000000
  5 [-]: CALL      R2 3 2       ; R2 := R2(R3,R4)
  6 [-]: GETGLOBAL R3 K3        ; R3 := 0x60130201
  7 [-]: CONST     R4 100       ; R4 := 100.000000
  8 [-]: CONST     R5 0         ; R5 := 0.000000
  9 [-]: CONST     R6 16        ; R6 := 16.000000
 10 [-]: CONST     R7 255       ; R7 := 255.000000
 11 [-]: CALL      R3 5 2       ; R3 := R3(R4,R5,R6,R7)
 12 [-]: LOADNIL   R4 R6        ; R4 := R5 := R6 := nil
 13 [-]: SELF      R7 R2 K4     ; R8 := R2; R7 := R2[0x697019d0]
 14 [-]: CONST     R9 6         ; R9 := 6.000000
 15 [-]: CALL      R7 3 2       ; R7 := R7(R8,R9)
 16 [-]: TEST      R7 0         ; if not R7 then PC := 19
 17 [-]: JMP       19           ; PC := 19
 18 [-]: GETTABLE  R3 R2 K5     ; R3 := R2["mEnergyColor"]
 19 [-]: SELF      R7 R2 K4     ; R8 := R2; R7 := R2[0x697019d0]
 20 [-]: CONST     R9 0         ; R9 := 0.000000
 21 [-]: CALL      R7 3 2       ; R7 := R7(R8,R9)
 22 [-]: TEST      R7 0         ; if not R7 then PC := 25
 23 [-]: JMP       25           ; PC := 25
 24 [-]: GETTABLE  R4 R2 K6     ; R4 := R2["mTintColor0"]
 25 [-]: SELF      R7 R2 K4     ; R8 := R2; R7 := R2[0x697019d0]
 26 [-]: CONST     R9 1         ; R9 := 1.000000
 27 [-]: CALL      R7 3 2       ; R7 := R7(R8,R9)
 28 [-]: TEST      R7 0         ; if not R7 then PC := 31
 29 [-]: JMP       31           ; PC := 31
 30 [-]: GETTABLE  R5 R2 K7     ; R5 := R2["mTintColor1"]
 31 [-]: SELF      R7 R2 K4     ; R8 := R2; R7 := R2[0x697019d0]
 32 [-]: CONST     R9 2         ; R9 := 2.000000
 33 [-]: CALL      R7 3 2       ; R7 := R7(R8,R9)
 34 [-]: TEST      R7 0         ; if not R7 then PC := 37
 35 [-]: JMP       37           ; PC := 37
 36 [-]: GETTABLE  R6 R2 K8     ; R6 := R2["mTintColor2"]
 37 [-]: NEWTABLE  R7 0 0       ; R7 := {}
 38 [-]: GETGLOBAL R8 K9        ; R8 := 0x33bdd652
 39 [-]: GETTABLE  R8 R8 K10    ; R8 := R8[0x23d5322f]
 40 [-]: MOVE      R9 R7        ; R9 := R7
 41 [-]: GETGLOBAL R10 K11      ; R10 := 0xa421af95
 42 [-]: GETUPVAL  R11 U0       ; R11 := U0
 43 [-]: GETTABLE  R11 R11 K12  ; R11 := R11[0x021dc4be]
 44 [-]: GETTABLE  R12 R3 K13   ; R12 := R3["red"]
 45 [-]: CALL      R11 2 2      ; R11 := R11(R12)
 46 [-]: GETUPVAL  R12 U0       ; R12 := U0
 47 [-]: GETTABLE  R12 R12 K12  ; R12 := R12[0x021dc4be]
 48 [-]: GETTABLE  R13 R3 K14   ; R13 := R3["green"]
 49 [-]: CALL      R12 2 2      ; R12 := R12(R13)
 50 [-]: GETUPVAL  R13 U0       ; R13 := U0
 51 [-]: GETTABLE  R13 R13 K12  ; R13 := R13[0x021dc4be]
 52 [-]: GETTABLE  R14 R3 K15   ; R14 := R3["blue"]
 53 [-]: CALL      R13 2 0      ; R13,... := R13(R14)
 54 [-]: CALL      R10 0 0      ; R10,... := R10(R11,...)
 55 [-]: CALL      R8 0 1       ; R8(R9,...)
 56 [-]: EQ        1 R4 K16     ; if R4 == nil then PC := 76
 57 [-]: JMP       76           ; PC := 76
 58 [-]: GETGLOBAL R8 K9        ; R8 := 0x33bdd652
 59 [-]: GETTABLE  R8 R8 K10    ; R8 := R8[0x23d5322f]
 60 [-]: MOVE      R9 R7        ; R9 := R7
 61 [-]: GETGLOBAL R10 K11      ; R10 := 0xa421af95
 62 [-]: GETUPVAL  R11 U0       ; R11 := U0
 63 [-]: GETTABLE  R11 R11 K12  ; R11 := R11[0x021dc4be]
 64 [-]: GETTABLE  R12 R4 K13   ; R12 := R4["red"]
 65 [-]: CALL      R11 2 2      ; R11 := R11(R12)
 66 [-]: GETUPVAL  R12 U0       ; R12 := U0
 67 [-]: GETTABLE  R12 R12 K12  ; R12 := R12[0x021dc4be]
 68 [-]: GETTABLE  R13 R4 K14   ; R13 := R4["green"]
 69 [-]: CALL      R12 2 2      ; R12 := R12(R13)
 70 [-]: GETUPVAL  R13 U0       ; R13 := U0
 71 [-]: GETTABLE  R13 R13 K12  ; R13 := R13[0x021dc4be]
 72 [-]: GETTABLE  R14 R4 K15   ; R14 := R4["blue"]
 73 [-]: CALL      R13 2 0      ; R13,... := R13(R14)
 74 [-]: CALL      R10 0 0      ; R10,... := R10(R11,...)
 75 [-]: CALL      R8 0 1       ; R8(R9,...)
 76 [-]: EQ        1 R5 K16     ; if R5 == nil then PC := 96
 77 [-]: JMP       96           ; PC := 96
 78 [-]: GETGLOBAL R8 K9        ; R8 := 0x33bdd652
 79 [-]: GETTABLE  R8 R8 K10    ; R8 := R8[0x23d5322f]
 80 [-]: MOVE      R9 R7        ; R9 := R7
 81 [-]: GETGLOBAL R10 K11      ; R10 := 0xa421af95
 82 [-]: GETUPVAL  R11 U0       ; R11 := U0
 83 [-]: GETTABLE  R11 R11 K12  ; R11 := R11[0x021dc4be]
 84 [-]: GETTABLE  R12 R5 K13   ; R12 := R5["red"]
 85 [-]: CALL      R11 2 2      ; R11 := R11(R12)
 86 [-]: GETUPVAL  R12 U0       ; R12 := U0
 87 [-]: GETTABLE  R12 R12 K12  ; R12 := R12[0x021dc4be]
 88 [-]: GETTABLE  R13 R5 K14   ; R13 := R5["green"]
 89 [-]: CALL      R12 2 2      ; R12 := R12(R13)
 90 [-]: GETUPVAL  R13 U0       ; R13 := U0
 91 [-]: GETTABLE  R13 R13 K12  ; R13 := R13[0x021dc4be]
 92 [-]: GETTABLE  R14 R5 K15   ; R14 := R5["blue"]
 93 [-]: CALL      R13 2 0      ; R13,... := R13(R14)
 94 [-]: CALL      R10 0 0      ; R10,... := R10(R11,...)
 95 [-]: CALL      R8 0 1       ; R8(R9,...)
 96 [-]: EQ        1 R6 K16     ; if R6 == nil then PC := 116
 97 [-]: JMP       116          ; PC := 116
 98 [-]: GETGLOBAL R8 K9        ; R8 := 0x33bdd652
 99 [-]: GETTABLE  R8 R8 K10    ; R8 := R8[0x23d5322f]
100 [-]: MOVE      R9 R7        ; R9 := R7
101 [-]: GETGLOBAL R10 K11      ; R10 := 0xa421af95
102 [-]: GETUPVAL  R11 U0       ; R11 := U0
103 [-]: GETTABLE  R11 R11 K12  ; R11 := R11[0x021dc4be]
104 [-]: GETTABLE  R12 R6 K13   ; R12 := R6["red"]
105 [-]: CALL      R11 2 2      ; R11 := R11(R12)
106 [-]: GETUPVAL  R12 U0       ; R12 := U0
107 [-]: GETTABLE  R12 R12 K12  ; R12 := R12[0x021dc4be]
108 [-]: GETTABLE  R13 R6 K14   ; R13 := R6["green"]
109 [-]: CALL      R12 2 2      ; R12 := R12(R13)
110 [-]: GETUPVAL  R13 U0       ; R13 := U0
111 [-]: GETTABLE  R13 R13 K12  ; R13 := R13[0x021dc4be]
112 [-]: GETTABLE  R14 R6 K15   ; R14 := R6["blue"]
113 [-]: CALL      R13 2 0      ; R13,... := R13(R14)
114 [-]: CALL      R10 0 0      ; R10,... := R10(R11,...)
115 [-]: CALL      R8 0 1       ; R8(R9,...)
116 [-]: RETURN    R7 2         ; return R7
117 [-]: RETURN    R0 1         ; return 


; Function #12:
;
; Name:            
; Defined at line: 328
; #Upvalues:       0
; #Parameters:     2
; Is_vararg:       0
; Max Stack Size:  13

  1 [-]: GETGLOBAL R2 K0        ; R2 := 0xc8802016
  2 [-]: GETTABLE  R3 R0 K1     ; R3 := R0["growths"]
  3 [-]: CALL      R2 2 4       ; R2,R3,R4 := R2(R3)
  4 [-]: JMP       13           ; PC := 13
  5 [-]: GETGLOBAL R7 K2        ; R7 := 0x7b998233
  6 [-]: GETTABLE  R8 R6 K3     ; R8 := R6["growth"]
  7 [-]: CALL      R7 2 2       ; R7 := R7(R8)
  8 [-]: TEST      R7 1         ; if R7 then PC := 13
  9 [-]: JMP       13           ; PC := 13
 10 [-]: GETTABLE  R7 R6 K3     ; R7 := R6["growth"]
 11 [-]: SELF      R7 R7 K4     ; R8 := R7; R7 := R7[0xa2880940]
 12 [-]: CALL      R7 2 1       ; R7(R8)
 13 [-]: TFORLOOP  R2 2         ; R5,R6 :=  R2(R3,R4); if R5 ~= nil then begin PC = 5; R4 := R5 end
 14 [-]: JMP       5            ; PC := 5
 15 [-]: GETGLOBAL R7 K5        ; R7 := 0x89326c93
 16 [-]: SELF      R7 R7 K6     ; R8 := R7; R7 := R7[0x05909209]
 17 [-]: GETGLOBAL R9 K7        ; R9 := 0xca684ff9
 18 [-]: GETTABLE  R10 R0 K8    ; R10 := R0["spawnPos"]
 19 [-]: GETGLOBAL R11 K9       ; R11 := ZERO_ROTATION
 20 [-]: MOVE      R12 R1       ; R12 := R1
 21 [-]: CALL      R7 6 1       ; R7(R8,R9,R10,R11,R12)
 22 [-]: GETGLOBAL R7 K2        ; R7 := 0x7b998233
 23 [-]: GETTABLE  R8 R0 K10    ; R8 := R0["pod"]
 24 [-]: CALL      R7 2 2       ; R7 := R7(R8)
 25 [-]: TEST      R7 1         ; if R7 then PC := 30
 26 [-]: JMP       30           ; PC := 30
 27 [-]: GETTABLE  R7 R0 K10    ; R7 := R0["pod"]
 28 [-]: SELF      R7 R7 K4     ; R8 := R7; R7 := R7[0xa2880940]
 29 [-]: CALL      R7 2 1       ; R7(R8)
 30 [-]: RETURN    R0 1         ; return 


; Function #13:
;
; Name:            
; Defined at line: 342
; #Upvalues:       8
; #Parameters:     4
; Is_vararg:       0
; Max Stack Size:  30

  1 [-]: GETGLOBAL R4 K0        ; R4 := 0x89326c93
  2 [-]: SELF      R4 R4 K1     ; R5 := R4; R4 := R4[0x18d05d30]
  3 [-]: CALL      R4 2 2       ; R4 := R4(R5)
  4 [-]: TEST      R4 1         ; if R4 then PC := 7
  5 [-]: JMP       7            ; PC := 7
  6 [-]: RETURN    R0 1         ; return 
  7 [-]: SELF      R4 R1 K2     ; R5 := R1; R4 := R1[0x2d0a291f]
  8 [-]: CALL      R4 2 2       ; R4 := R4(R5)
  9 [-]: CONST     R5 0         ; R5 := 0.000000
 10 [-]: CONST     R6 0         ; R6 := 0.000000
 11 [-]: LOADKB    R7 0 0       ; R7 := false
 12 [-]: GETGLOBAL R8 K3        ; R8 := 0x7b998233
 13 [-]: MOVE      R9 R0        ; R9 := R0
 14 [-]: CALL      R8 2 2       ; R8 := R8(R9)
 15 [-]: TEST      R8 1         ; if R8 then PC := 37
 16 [-]: JMP       37           ; PC := 37
 17 [-]: SELF      R8 R0 K4     ; R9 := R0; R8 := R0[0xca9ea368]
 18 [-]: CALL      R8 2 2       ; R8 := R8(R9)
 19 [-]: MOVE      R5 R8        ; R5 := R8
 20 [-]: SELF      R8 R0 K5     ; R9 := R0; R8 := R0[0x6df09e59]
 21 [-]: CALL      R8 2 2       ; R8 := R8(R9)
 22 [-]: MOVE      R7 R8        ; R7 := R8
 23 [-]: GETGLOBAL R8 K6        ; R8 := _T
 24 [-]: GETTABLE  R8 R8 K7     ; R8 := R8["INFESTED_GetStacks"]
 25 [-]: EQ        1 R8 K8      ; if R8 == nil then PC := 37
 26 [-]: JMP       37           ; PC := 37
 27 [-]: GETUPVAL  R8 U0        ; R8 := U0
 28 [-]: GETTABLE  R8 R8 K9     ; R8 := R8[0x32316a21]
 29 [-]: CALL      R8 1 2       ; R8 := R8()
 30 [-]: TEST      R8 1         ; if R8 then PC := 37
 31 [-]: JMP       37           ; PC := 37
 32 [-]: GETGLOBAL R8 K6        ; R8 := _T
 33 [-]: GETTABLE  R8 R8 K10    ; R8 := R8[0x85ed3714]
 34 [-]: MOVE      R9 R0        ; R9 := R0
 35 [-]: CALL      R8 2 2       ; R8 := R8(R9)
 36 [-]: MOVE      R6 R8        ; R6 := R8
 37 [-]: NEWTABLE  R8 0 0       ; R8 := {}
 38 [-]: NEWTABLE  R9 0 0       ; R9 := {}
 39 [-]: CONST     R10 0        ; R10 := 0.000000
 40 [-]: CONST     R11 0        ; R11 := 0.000000
 41 [-]: GETGLOBAL R12 K11      ; R12 := 0x5bced4c4
 42 [-]: GETTABLE  R12 R12 K12  ; R12 := R12[0xdde5c6a1]
 43 [-]: GETGLOBAL R13 K13      ; R13 := 0x20b7f774
 44 [-]: MOVE      R14 R2       ; R14 := R2
 45 [-]: MOVE      R15 R3       ; R15 := R3
 46 [-]: CALL      R13 3 2      ; R13 := R13(R14,R15)
 47 [-]: GETTABLE  R13 R13 K14  ; R13 := R13["heading"]
 48 [-]: CALL      R12 2 2      ; R12 := R12(R13)
 49 [-]: GETUPVAL  R13 U1       ; R13 := U1
 50 [-]: DIV       R13 K15 R13  ; R13 := 6.283185 / R13
 51 [-]: GETGLOBAL R14 K0       ; R14 := 0x89326c93
 52 [-]: SELF      R14 R14 K16  ; R15 := R14; R14 := R14[0x29ef273d]
 53 [-]: CALL      R14 2 2      ; R14 := R14(R15)
 54 [-]: LOADK     R15 K17      ; R15 := 0.100000
 55 [-]: TEST      R7 0         ; if not R7 then PC := 60
 56 [-]: JMP       60           ; PC := 60
 57 [-]: GETGLOBAL R16 K18      ; R16 := 0x96a19a5c
 58 [-]: TEST      R16 1        ; if R16 then PC := 61
 59 [-]: JMP       61           ; PC := 61
 60 [-]: GETGLOBAL R16 K19      ; R16 := 0xbf369e29
 61 [-]: CONST     R17 1        ; R17 := 1.000000
 62 [-]: GETUPVAL  R18 U1       ; R18 := U1
 63 [-]: CONST     R19 1        ; R19 := 1.000000
 64 [-]: FORPREP   R17 141      ; R17 -= R19; PC := 141
 65 [-]: LT        0 K20 R20    ; if 1.000000 >= R20 then PC := 85
 66 [-]: JMP       85           ; PC := 85
 67 [-]: ADD       R12 R12 R13  ; R12 := R12 + R13
 68 [-]: GETUPVAL  R21 U2       ; R21 := U2
 69 [-]: SELF      R21 R21 K21  ; R22 := R21; R21 := R21[0x96f7a165]
 70 [-]: CALL      R21 2 2      ; R21 := R21(R22)
 71 [-]: GETGLOBAL R22 K22      ; R22 := 0xa421af95
 72 [-]: GETGLOBAL R23 K11      ; R23 := 0x5bced4c4
 73 [-]: GETTABLE  R23 R23 K23  ; R23 := R23[0x3eda26fc]
 74 [-]: MOVE      R24 R12      ; R24 := R12
 75 [-]: CALL      R23 2 2      ; R23 := R23(R24)
 76 [-]: MUL       R23 R21 R23  ; R23 := R21 * R23
 77 [-]: CONST     R24 0        ; R24 := 0.000000
 78 [-]: GETGLOBAL R25 K11      ; R25 := 0x5bced4c4
 79 [-]: GETTABLE  R25 R25 K24  ; R25 := R25[0x00fa6bf1]
 80 [-]: MOVE      R26 R12      ; R26 := R12
 81 [-]: CALL      R25 2 2      ; R25 := R25(R26)
 82 [-]: MUL       R25 R21 R25  ; R25 := R21 * R25
 83 [-]: CALL      R22 4 2      ; R22 := R22(R23,R24,R25)
 84 [-]: ADD       R3 R2 R22    ; R3 := R2 + R22
 85 [-]: EQ        1 R20 K20    ; if R20 == 1.000000 then PC := 95
 86 [-]: JMP       95           ; PC := 95
 87 [-]: SELF      R22 R14 K25  ; R23 := R14; R22 := R14[0x40f8914b]
 88 [-]: MOVE      R24 R3       ; R24 := R3
 89 [-]: CONST     R25 8        ; R25 := 8.000000
 90 [-]: CONST     R26 0        ; R26 := 0.000000
 91 [-]: GETUPVAL  R27 U3       ; R27 := U3
 92 [-]: CALL      R22 6 2      ; R22 := R22(R23,R24,R25,R26,R27)
 93 [-]: TEST      R22 0        ; if not R22 then PC := 141
 94 [-]: JMP       141          ; PC := 141
 95 [-]: GETGLOBAL R22 K0       ; R22 := 0x89326c93
 96 [-]: SELF      R22 R22 K26  ; R23 := R22; R22 := R22[0x05909209]
 97 [-]: MOVE      R24 R16      ; R24 := R16
 98 [-]: MOVE      R25 R3       ; R25 := R3
 99 [-]: GETGLOBAL R26 K27      ; R26 := 0x00046924
100 [-]: GETGLOBAL R27 K28      ; R27 := 0xc163f229
101 [-]: CONST     R28 0        ; R28 := 0.000000
102 [-]: CONST     R29 360      ; R29 := 360.000000
103 [-]: CALL      R27 3 2      ; R27 := R27(R28,R29)
104 [-]: CONST     R28 0        ; R28 := 0.000000
105 [-]: CONST     R29 0        ; R29 := 0.000000
106 [-]: CALL      R26 4 2      ; R26 := R26(R27,R28,R29)
107 [-]: MOVE      R27 R1       ; R27 := R1
108 [-]: CALL      R22 6 2      ; R22 := R22(R23,R24,R25,R26,R27)
109 [-]: GETGLOBAL R23 K3       ; R23 := 0x7b998233
110 [-]: MOVE      R24 R22      ; R24 := R22
111 [-]: CALL      R23 2 2      ; R23 := R23(R24)
112 [-]: TEST      R23 1        ; if R23 then PC := 141
113 [-]: JMP       141          ; PC := 141
114 [-]: GETGLOBAL R23 K29      ; R23 := 0x33bdd652
115 [-]: GETTABLE  R23 R23 K30  ; R23 := R23[0x23d5322f]
116 [-]: MOVE      R24 R8       ; R24 := R8
117 [-]: NEWTABLE  R25 0 7      ; R25 := {}
118 [-]: SETTABLE  R25 K31 R22  ; R25["pod"] := R22
119 [-]: SETTABLE  R25 K32 R15  ; R25["spawnDelay"] := R15
120 [-]: SETTABLE  R25 K33 R3   ; R25["spawnPos"] := R3
121 [-]: GETGLOBAL R26 K35      ; R26 := 0x03ea2485
122 [-]: MOVE      R27 R2       ; R27 := R2
123 [-]: MOVE      R28 R3       ; R28 := R3
124 [-]: CALL      R26 3 2      ; R26 := R26(R27,R28)
125 [-]: SETTABLE  R25 K34 R26  ; R25["radius"] := R26
126 [-]: GETGLOBAL R26 K13      ; R26 := 0x20b7f774
127 [-]: MOVE      R27 R2       ; R27 := R2
128 [-]: MOVE      R28 R3       ; R28 := R3
129 [-]: CALL      R26 3 2      ; R26 := R26(R27,R28)
130 [-]: GETTABLE  R26 R26 K14  ; R26 := R26["heading"]
131 [-]: SETTABLE  R25 K36 R26  ; R25["centerToPod"] := R26
132 [-]: SELF      R26 R22 K38  ; R27 := R22; R26 := R22[0xef8e8f7f]
133 [-]: CALL      R26 2 2      ; R26 := R26(R27)
134 [-]: MUL       R26 R26 K39  ; R26 := R26 * 2.000000
135 [-]: SUB       R26 R26 R3   ; R26 := R26 - R3
136 [-]: SETTABLE  R25 K37 R26  ; R25["nullifierCheckB"] := R26
137 [-]: NEWTABLE  R26 0 0      ; R26 := {}
138 [-]: SETTABLE  R25 K40 R26  ; R25["growths"] := R26
139 [-]: CALL      R23 3 1      ; R23(R24,R25)
140 [-]: ADD       R15 R15 K17  ; R15 := R15 + 0.100000
141 [-]: FORLOOP   R17 65       ; R17 += R19; if R17 <= R18 then begin PC := 65; R20 := R17 end
142 [-]: NEWTABLE  R23 0 2      ; R23 := {}
143 [-]: CLOSURE   R24 0        ; R24 := closure(Function #13.1)
144 [-]: MOVE      R0 R8        ; R0 := R8
145 [-]: GETUPVAL  R0 U4        ; R0 := U4
146 [-]: MOVE      R0 R1        ; R0 := R1
147 [-]: MOVE      R0 R11       ; R0 := R11
148 [-]: MOVE      R0 R9        ; R0 := R9
149 [-]: MOVE      R0 R10       ; R0 := R10
150 [-]: GETUPVAL  R0 U5        ; R0 := U5
151 [-]: MOVE      R0 R2        ; R0 := R2
152 [-]: MOVE      R0 R14       ; R0 := R14
153 [-]: GETUPVAL  R0 U6        ; R0 := U6
154 [-]: GETUPVAL  R0 U7        ; R0 := U7
155 [-]: MOVE      R0 R7        ; R0 := R7
156 [-]: MOVE      R0 R5        ; R0 := R5
157 [-]: MOVE      R0 R4        ; R0 := R4
158 [-]: MOVE      R0 R6        ; R0 := R6
159 [-]: SETTABLE  R23 K41 R24  ; R23["Update"] := R24
160 [-]: CLOSURE   R24 1        ; R24 := closure(Function #13.2)
161 [-]: MOVE      R0 R8        ; R0 := R8
162 [-]: GETUPVAL  R0 U4        ; R0 := U4
163 [-]: MOVE      R0 R1        ; R0 := R1
164 [-]: MOVE      R0 R9        ; R0 := R9
165 [-]: SETTABLE  R23 K42 R24  ; R23["Terminate"] := R24
166 [-]: RETURN    R23 2        ; return R23
167 [-]: RETURN    R0 1         ; return 


; Function #13.1:
;
; Name:            
; Defined at line: 405
; #Upvalues:       15
; #Parameters:     0
; Is_vararg:       0
; Max Stack Size:  44

  1 [-]: GETUPVAL  R0 U0        ; R0 := U0
  2 [-]: LEN       R0 R0        ; R0 := # R0
  3 [-]: CONST     R1 1         ; R1 := 1.000000
  4 [-]: CONST     R2 -1        ; R2 := -1.000000
  5 [-]: FORPREP   R0 28        ; R0 -= R2; PC := 28
  6 [-]: GETUPVAL  R4 U0        ; R4 := U0
  7 [-]: GETTABLE  R4 R4 R3     ; R4 := R4[R3]
  8 [-]: GETTABLE  R4 R4 K0     ; R4 := R4["pod"]
  9 [-]: GETGLOBAL R5 K1        ; R5 := 0x7b998233
 10 [-]: MOVE      R6 R4        ; R6 := R4
 11 [-]: CALL      R5 2 2       ; R5 := R5(R6)
 12 [-]: TEST      R5 1         ; if R5 then PC := 18
 13 [-]: JMP       18           ; PC := 18
 14 [-]: SELF      R5 R4 K2     ; R6 := R4; R5 := R4[0x5c96ca7e]
 15 [-]: CALL      R5 2 2       ; R5 := R5(R6)
 16 [-]: TEST      R5 0         ; if not R5 then PC := 28
 17 [-]: JMP       28           ; PC := 28
 18 [-]: GETUPVAL  R5 U1        ; R5 := U1
 19 [-]: GETUPVAL  R6 U0        ; R6 := U0
 20 [-]: GETTABLE  R6 R6 R3     ; R6 := R6[R3]
 21 [-]: GETUPVAL  R7 U2        ; R7 := U2
 22 [-]: CALL      R5 3 1       ; R5(R6,R7)
 23 [-]: GETGLOBAL R5 K3        ; R5 := 0x33bdd652
 24 [-]: GETTABLE  R5 R5 K4     ; R5 := R5[0x9c1f3b5a]
 25 [-]: GETUPVAL  R6 U0        ; R6 := U0
 26 [-]: MOVE      R7 R3        ; R7 := R3
 27 [-]: CALL      R5 3 1       ; R5(R6,R7)
 28 [-]: FORLOOP   R0 6         ; R0 += R2; if R0 <= R1 then begin PC := 6; R3 := R0 end
 29 [-]: GETUPVAL  R5 U3        ; R5 := U3
 30 [-]: GETGLOBAL R6 K5        ; R6 := 0x67652851
 31 [-]: CALL      R6 1 2       ; R6 := R6()
 32 [-]: SUB       R5 R5 R6     ; R5 := R5 - R6
 33 [-]: SETUPVAL  R5 U3        ; U82 := R3
 34 [-]: GETUPVAL  R5 U3        ; R5 := U3
 35 [-]: LE        0 R5 K6      ; if R5 > 0.000000 then PC := 69
 36 [-]: JMP       69           ; PC := 69
 37 [-]: GETGLOBAL R5 K1        ; R5 := 0x7b998233
 38 [-]: GETGLOBAL R6 K7        ; R6 := 0xbe190284
 39 [-]: CALL      R5 2 2       ; R5 := R5(R6)
 40 [-]: TEST      R5 1         ; if R5 then PC := 67
 41 [-]: JMP       67           ; PC := 67
 42 [-]: GETUPVAL  R5 U0        ; R5 := U0
 43 [-]: LEN       R5 R5        ; R5 := # R5
 44 [-]: CONST     R6 1         ; R6 := 1.000000
 45 [-]: CONST     R7 -1        ; R7 := -1.000000
 46 [-]: FORPREP   R5 66        ; R5 -= R7; PC := 66
 47 [-]: GETUPVAL  R9 U0        ; R9 := U0
 48 [-]: GETTABLE  R9 R9 R8     ; R9 := R9[R8]
 49 [-]: GETGLOBAL R10 K7       ; R10 := 0xbe190284
 50 [-]: SELF      R10 R10 K8   ; R11 := R10; R10 := R10[0xbe973013]
 51 [-]: GETUPVAL  R12 U2       ; R12 := U2
 52 [-]: GETTABLE  R13 R9 K9    ; R13 := R9["spawnPos"]
 53 [-]: GETTABLE  R14 R9 K10   ; R14 := R9["nullifierCheckB"]
 54 [-]: CALL      R10 5 2      ; R10 := R10(R11,R12,R13,R14)
 55 [-]: TEST      R10 0        ; if not R10 then PC := 66
 56 [-]: JMP       66           ; PC := 66
 57 [-]: GETUPVAL  R10 U1       ; R10 := U1
 58 [-]: MOVE      R11 R9       ; R11 := R9
 59 [-]: GETUPVAL  R12 U2       ; R12 := U2
 60 [-]: CALL      R10 3 1      ; R10(R11,R12)
 61 [-]: GETGLOBAL R10 K3       ; R10 := 0x33bdd652
 62 [-]: GETTABLE  R10 R10 K4   ; R10 := R10[0x9c1f3b5a]
 63 [-]: GETUPVAL  R11 U0       ; R11 := U0
 64 [-]: MOVE      R12 R8       ; R12 := R8
 65 [-]: CALL      R10 3 1      ; R10(R11,R12)
 66 [-]: FORLOOP   R5 47        ; R5 += R7; if R5 <= R6 then begin PC := 47; R8 := R5 end
 67 [-]: CONST     R10 0        ; R10 := 0.250000
 68 [-]: SETUPVAL  R10 U3       ; U82 := R3
 69 [-]: LOADKB    R10 1 0      ; R10 := true
 70 [-]: GETGLOBAL R11 K11      ; R11 := 0xc8802016
 71 [-]: GETUPVAL  R12 U0       ; R12 := U0
 72 [-]: CALL      R11 2 4      ; R11,R12,R13 := R11(R12)
 73 [-]: JMP       313          ; PC := 313
 74 [-]: GETTABLE  R16 R15 K12  ; R16 := R15["spawnDelay"]
 75 [-]: GETGLOBAL R17 K5       ; R17 := 0x67652851
 76 [-]: CALL      R17 1 2      ; R17 := R17()
 77 [-]: SUB       R16 R16 R17  ; R16 := R16 - R17
 78 [-]: SETTABLE  R15 K12 R16  ; R15["spawnDelay"] := R16
 79 [-]: GETTABLE  R16 R15 K12  ; R16 := R15["spawnDelay"]
 80 [-]: LE        0 R16 K6     ; if R16 > 0.000000 then PC := 208
 81 [-]: JMP       208          ; PC := 208
 82 [-]: TEST      R10 0        ; if not R10 then PC := 120
 83 [-]: JMP       120          ; PC := 120
 84 [-]: GETUPVAL  R16 U4       ; R16 := U4
 85 [-]: LEN       R16 R16      ; R16 := # R16
 86 [-]: CONST     R17 1        ; R17 := 1.000000
 87 [-]: CONST     R18 -1       ; R18 := -1.000000
 88 [-]: FORPREP   R16 118      ; R16 -= R18; PC := 118
 89 [-]: GETUPVAL  R20 U4       ; R20 := U4
 90 [-]: GETTABLE  R20 R20 R19  ; R20 := R20[R19]
 91 [-]: GETGLOBAL R21 K1       ; R21 := 0x7b998233
 92 [-]: MOVE      R22 R20      ; R22 := R20
 93 [-]: CALL      R21 2 2      ; R21 := R21(R22)
 94 [-]: TEST      R21 0        ; if not R21 then PC := 102
 95 [-]: JMP       102          ; PC := 102
 96 [-]: GETGLOBAL R21 K3       ; R21 := 0x33bdd652
 97 [-]: GETTABLE  R21 R21 K4   ; R21 := R21[0x9c1f3b5a]
 98 [-]: GETUPVAL  R22 U4       ; R22 := U4
 99 [-]: MOVE      R23 R19      ; R23 := R19
100 [-]: CALL      R21 3 1      ; R21(R22,R23)
101 [-]: JMP       118          ; PC := 118
102 [-]: SELF      R21 R20 K13  ; R22 := R20; R21 := R20[0xbb610e5b]
103 [-]: CALL      R21 2 2      ; R21 := R21(R22)
104 [-]: GETGLOBAL R22 K1       ; R22 := 0x7b998233
105 [-]: MOVE      R23 R21      ; R23 := R21
106 [-]: CALL      R22 2 2      ; R22 := R22(R23)
107 [-]: TEST      R22 1        ; if R22 then PC := 113
108 [-]: JMP       113          ; PC := 113
109 [-]: SELF      R22 R21 K14  ; R23 := R21; R22 := R21[0x2047cfe7]
110 [-]: CALL      R22 2 2      ; R22 := R22(R23)
111 [-]: TEST      R22 0        ; if not R22 then PC := 118
112 [-]: JMP       118          ; PC := 118
113 [-]: GETGLOBAL R22 K3       ; R22 := 0x33bdd652
114 [-]: GETTABLE  R22 R22 K4   ; R22 := R22[0x9c1f3b5a]
115 [-]: GETUPVAL  R23 U4       ; R23 := U4
116 [-]: MOVE      R24 R19      ; R24 := R19
117 [-]: CALL      R22 3 1      ; R22(R23,R24)
118 [-]: FORLOOP   R16 89       ; R16 += R18; if R16 <= R17 then begin PC := 89; R19 := R16 end
119 [-]: LOADKB    R10 0 0      ; R10 := false
120 [-]: GETUPVAL  R22 U4       ; R22 := U4
121 [-]: LEN       R22 R22      ; R22 := # R22
122 [-]: GETUPVAL  R23 U5       ; R23 := U5
123 [-]: ADD       R22 R22 R23  ; R22 := R22 + R23
124 [-]: GETUPVAL  R23 U6       ; R23 := U6
125 [-]: LT        0 R22 R23    ; if R22 >= R23 then PC := 206
126 [-]: JMP       206          ; PC := 206
127 [-]: GETGLOBAL R22 K15      ; R22 := 0xc163f229
128 [-]: CONST     R23 1        ; R23 := 1.000000
129 [-]: CONST     R24 3        ; R24 := 3.000000
130 [-]: CALL      R22 3 2      ; R22 := R22(R23,R24)
131 [-]: GETGLOBAL R23 K16      ; R23 := 0x55730e1a
132 [-]: CONST     R24 0        ; R24 := 0.000000
133 [-]: CONST     R25 1        ; R25 := 1.000000
134 [-]: CALL      R23 3 2      ; R23 := R23(R24,R25)
135 [-]: LT        0 K6 R23     ; if 0.000000 >= R23 then PC := 138
136 [-]: JMP       138          ; PC := 138
137 [-]: UNM       R22 R22      ; R22 :=  R22
138 [-]: GETGLOBAL R23 K17      ; R23 := 0x5bced4c4
139 [-]: GETTABLE  R23 R23 K18  ; R23 := R23[0xbf79b942]
140 [-]: GETGLOBAL R24 K17      ; R24 := 0x5bced4c4
141 [-]: GETTABLE  R24 R24 K19  ; R24 := R24[0xd4c1d800]
142 [-]: GETTABLE  R25 R15 K20  ; R25 := R15["radius"]
143 [-]: DIV       R25 R22 R25  ; R25 := R22 / R25
144 [-]: CALL      R24 2 0      ; R24,... := R24(R25)
145 [-]: CALL      R23 0 2      ; R23 := R23(R24,...)
146 [-]: GETUPVAL  R24 U7       ; R24 := U7
147 [-]: GETGLOBAL R25 K21      ; R25 := 0x492c7f2a
148 [-]: GETGLOBAL R26 K22      ; R26 := 0xa421af95
149 [-]: CONST     R27 0        ; R27 := 0.000000
150 [-]: CONST     R28 0        ; R28 := 0.000000
151 [-]: GETTABLE  R29 R15 K20  ; R29 := R15["radius"]
152 [-]: GETGLOBAL R30 K15      ; R30 := 0xc163f229
153 [-]: CONST     R31 0        ; R31 := -0.500000
154 [-]: CONST     R32 1        ; R32 := 1.000000
155 [-]: CALL      R30 3 2      ; R30 := R30(R31,R32)
156 [-]: ADD       R29 R29 R30  ; R29 := R29 + R30
157 [-]: CALL      R26 4 2      ; R26 := R26(R27,R28,R29)
158 [-]: GETGLOBAL R27 K23      ; R27 := 0x00046924
159 [-]: GETTABLE  R28 R15 K24  ; R28 := R15["centerToPod"]
160 [-]: ADD       R28 R28 R23  ; R28 := R28 + R23
161 [-]: CONST     R29 0        ; R29 := 0.000000
162 [-]: CONST     R30 0        ; R30 := 0.000000
163 [-]: CALL      R27 4 0      ; R27,... := R27(R28,R29,R30)
164 [-]: CALL      R25 0 2      ; R25 := R25(R26,...)
165 [-]: ADD       R24 R24 R25  ; R24 := R24 + R25
166 [-]: GETUPVAL  R25 U8       ; R25 := U8
167 [-]: SELF      R25 R25 K25  ; R26 := R25; R25 := R25[0x40f8914b]
168 [-]: MOVE      R27 R24      ; R27 := R24
169 [-]: CONST     R28 3        ; R28 := 3.000000
170 [-]: CONST     R29 0        ; R29 := 0.000000
171 [-]: CONST     R30 -5       ; R30 := -5.000000
172 [-]: CALL      R25 6 2      ; R25 := R25(R26,R27,R28,R29,R30)
173 [-]: TEST      R25 1        ; if R25 then PC := 176
174 [-]: JMP       176          ; PC := 176
175 [-]: GETTABLE  R24 R15 K9   ; R24 := R15["spawnPos"]
176 [-]: GETGLOBAL R25 K26      ; R25 := 0x89326c93
177 [-]: SELF      R25 R25 K27  ; R26 := R25; R25 := R25[0x05909209]
178 [-]: GETGLOBAL R27 K28      ; R27 := 0xff20452d
179 [-]: MOVE      R28 R24      ; R28 := R24
180 [-]: GETGLOBAL R29 K23      ; R29 := 0x00046924
181 [-]: GETGLOBAL R30 K15      ; R30 := 0xc163f229
182 [-]: CONST     R31 0        ; R31 := 0.000000
183 [-]: CONST     R32 360      ; R32 := 360.000000
184 [-]: CALL      R30 3 2      ; R30 := R30(R31,R32)
185 [-]: CONST     R31 0        ; R31 := 0.000000
186 [-]: CONST     R32 0        ; R32 := 0.000000
187 [-]: CALL      R29 4 2      ; R29 := R29(R30,R31,R32)
188 [-]: GETUPVAL  R30 U2       ; R30 := U2
189 [-]: CALL      R25 6 2      ; R25 := R25(R26,R27,R28,R29,R30)
190 [-]: GETGLOBAL R26 K1       ; R26 := 0x7b998233
191 [-]: MOVE      R27 R25      ; R27 := R25
192 [-]: CALL      R26 2 2      ; R26 := R26(R27)
193 [-]: TEST      R26 1        ; if R26 then PC := 206
194 [-]: JMP       206          ; PC := 206
195 [-]: GETGLOBAL R26 K3       ; R26 := 0x33bdd652
196 [-]: GETTABLE  R26 R26 K29  ; R26 := R26[0x23d5322f]
197 [-]: GETTABLE  R27 R15 K30  ; R27 := R15["growths"]
198 [-]: NEWTABLE  R28 0 2      ; R28 := {}
199 [-]: SETTABLE  R28 K31 R25  ; R28["growth"] := R25
200 [-]: GETUPVAL  R29 U9       ; R29 := U9
201 [-]: SETTABLE  R28 K32 R29  ; R28["time"] := R29
202 [-]: CALL      R26 3 1      ; R26(R27,R28)
203 [-]: GETUPVAL  R26 U5       ; R26 := U5
204 [-]: ADD       R26 R26 K33  ; R26 := R26 + 1.000000
205 [-]: SETUPVAL  R26 U5       ; U82 := R5
206 [-]: GETUPVAL  R26 U10      ; R26 := U10
207 [-]: SETTABLE  R15 K12 R26  ; R15["spawnDelay"] := R26
208 [-]: LOADKB    R26 0 0      ; R26 := false
209 [-]: GETTABLE  R27 R15 K30  ; R27 := R15["growths"]
210 [-]: LEN       R27 R27      ; R27 := # R27
211 [-]: CONST     R28 1        ; R28 := 1.000000
212 [-]: CONST     R29 -1       ; R29 := -1.000000
213 [-]: FORPREP   R27 312      ; R27 -= R29; PC := 312
214 [-]: GETTABLE  R31 R15 K30  ; R31 := R15["growths"]
215 [-]: GETTABLE  R31 R31 R30  ; R31 := R31[R30]
216 [-]: GETTABLE  R32 R31 K32  ; R32 := R31["time"]
217 [-]: GETGLOBAL R33 K5       ; R33 := 0x67652851
218 [-]: CALL      R33 1 2      ; R33 := R33()
219 [-]: SUB       R32 R32 R33  ; R32 := R32 - R33
220 [-]: SETTABLE  R31 K32 R32  ; R31["time"] := R32
221 [-]: TEST      R26 1        ; if R26 then PC := 312
222 [-]: JMP       312          ; PC := 312
223 [-]: GETTABLE  R32 R31 K32  ; R32 := R31["time"]
224 [-]: LE        0 R32 K6     ; if R32 > 0.000000 then PC := 312
225 [-]: JMP       312          ; PC := 312
226 [-]: GETTABLE  R32 R31 K31  ; R32 := R31["growth"]
227 [-]: SELF      R33 R32 K34  ; R34 := R32; R33 := R32[0xd1586535]
228 [-]: CALL      R33 2 2      ; R33 := R33(R34)
229 [-]: SELF      R34 R32 K35  ; R35 := R32; R34 := R32[0xcb3851b8]
230 [-]: CALL      R34 2 2      ; R34 := R34(R35)
231 [-]: LOADNIL   R35 R35      ; R35 := nil
232 [-]: GETUPVAL  R36 U11      ; R36 := U11
233 [-]: TEST      R36 0        ; if not R36 then PC := 246
234 [-]: JMP       246          ; PC := 246
235 [-]: GETUPVAL  R36 U8       ; R36 := U8
236 [-]: SELF      R36 R36 K36  ; R37 := R36; R36 := R36[0x6cd833c5]
237 [-]: GETGLOBAL R38 K37      ; R38 := 0x677584c6
238 [-]: MOVE      R39 R33      ; R39 := R33
239 [-]: MOVE      R40 R34      ; R40 := R34
240 [-]: GETGLOBAL R41 K38      ; R41 := EMPTY_SYMBOL
241 [-]: GETUPVAL  R42 U12      ; R42 := U12
242 [-]: LOADKB    R43 1 0      ; R43 := true
243 [-]: CALL      R36 8 2      ; R36 := R36(R37,R38,R39,R40,R41,R42,R43)
244 [-]: MOVE      R35 R36      ; R35 := R36
245 [-]: JMP       256          ; PC := 256
246 [-]: GETUPVAL  R36 U8       ; R36 := U8
247 [-]: SELF      R36 R36 K36  ; R37 := R36; R36 := R36[0x6cd833c5]
248 [-]: GETGLOBAL R38 K39      ; R38 := 0x51fe62f3
249 [-]: MOVE      R39 R33      ; R39 := R33
250 [-]: MOVE      R40 R34      ; R40 := R34
251 [-]: GETGLOBAL R41 K38      ; R41 := EMPTY_SYMBOL
252 [-]: GETUPVAL  R42 U12      ; R42 := U12
253 [-]: LOADKB    R43 1 0      ; R43 := true
254 [-]: CALL      R36 8 2      ; R36 := R36(R37,R38,R39,R40,R41,R42,R43)
255 [-]: MOVE      R35 R36      ; R35 := R36
256 [-]: GETGLOBAL R36 K1       ; R36 := 0x7b998233
257 [-]: MOVE      R37 R35      ; R37 := R35
258 [-]: CALL      R36 2 2      ; R36 := R36(R37)
259 [-]: TEST      R36 1        ; if R36 then PC := 302
260 [-]: JMP       302          ; PC := 302
261 [-]: LOADKB    R26 1 0      ; R26 := true
262 [-]: SELF      R36 R35 K40  ; R37 := R35; R36 := R35[0xa7a16361]
263 [-]: LOADKB    R38 0 0      ; R38 := false
264 [-]: CALL      R36 3 1      ; R36(R37,R38)
265 [-]: SELF      R36 R35 K13  ; R37 := R35; R36 := R35[0xbb610e5b]
266 [-]: CALL      R36 2 2      ; R36 := R36(R37)
267 [-]: GETGLOBAL R37 K1       ; R37 := 0x7b998233
268 [-]: MOVE      R38 R36      ; R38 := R36
269 [-]: CALL      R37 2 2      ; R37 := R37(R38)
270 [-]: TEST      R37 1        ; if R37 then PC := 297
271 [-]: JMP       297          ; PC := 297
272 [-]: SELF      R37 R36 K41  ; R38 := R36; R37 := R36[0x0cca925a]
273 [-]: GETUPVAL  R39 U13      ; R39 := U13
274 [-]: CALL      R37 3 1      ; R37(R38,R39)
275 [-]: SELF      R37 R36 K42  ; R38 := R36; R37 := R36[0xbf5c535d]
276 [-]: GETGLOBAL R39 K43      ; R39 := 0x6687f6e0
277 [-]: CALL      R37 3 1      ; R37(R38,R39)
278 [-]: SELF      R37 R36 K44  ; R38 := R36; R37 := R36[0x74874678]
279 [-]: GETUPVAL  R39 U2       ; R39 := U2
280 [-]: CALL      R37 3 1      ; R37(R38,R39)
281 [-]: SELF      R37 R36 K45  ; R38 := R36; R37 := R36[0xc40eed62]
282 [-]: GETUPVAL  R39 U2       ; R39 := U2
283 [-]: CALL      R37 3 1      ; R37(R38,R39)
284 [-]: SELF      R37 R36 K46  ; R38 := R36; R37 := R36[0x2aae5ec9]
285 [-]: CONST     R39 1        ; R39 := 1.000000
286 [-]: CALL      R37 3 1      ; R37(R38,R39)
287 [-]: GETUPVAL  R37 U14      ; R37 := U14
288 [-]: LT        0 K6 R37     ; if 0.000000 >= R37 then PC := 297
289 [-]: JMP       297          ; PC := 297
290 [-]: SELF      R37 R36 K47  ; R38 := R36; R37 := R36[0xde321e6f]
291 [-]: CALL      R37 2 2      ; R37 := R37(R38)
292 [-]: SELF      R37 R37 K48  ; R38 := R37; R37 := R37[0x5e6704ff]
293 [-]: CONST     R39 10       ; R39 := 10.000000
294 [-]: CONST     R40 3        ; R40 := 3.000000
295 [-]: GETUPVAL  R41 U14      ; R41 := U14
296 [-]: CALL      R37 5 1      ; R37(R38,R39,R40,R41)
297 [-]: GETGLOBAL R37 K3       ; R37 := 0x33bdd652
298 [-]: GETTABLE  R37 R37 K29  ; R37 := R37[0x23d5322f]
299 [-]: GETUPVAL  R38 U4       ; R38 := U4
300 [-]: MOVE      R39 R35      ; R39 := R35
301 [-]: CALL      R37 3 1      ; R37(R38,R39)
302 [-]: SELF      R37 R32 K51  ; R38 := R32; R37 := R32[0xa2880940]
303 [-]: CALL      R37 2 1      ; R37(R38)
304 [-]: GETGLOBAL R37 K3       ; R37 := 0x33bdd652
305 [-]: GETTABLE  R37 R37 K4   ; R37 := R37[0x9c1f3b5a]
306 [-]: GETTABLE  R38 R15 K30  ; R38 := R15["growths"]
307 [-]: MOVE      R39 R30      ; R39 := R30
308 [-]: CALL      R37 3 1      ; R37(R38,R39)
309 [-]: GETUPVAL  R37 U5       ; R37 := U5
310 [-]: SUB       R37 R37 K33  ; R37 := R37 - 1.000000
311 [-]: SETUPVAL  R37 U5       ; U82 := R5
312 [-]: FORLOOP   R27 214      ; R27 += R29; if R27 <= R28 then begin PC := 214; R30 := R27 end
313 [-]: TFORLOOP  R11 2        ; R14,R15 :=  R11(R12,R13); if R14 ~= nil then begin PC = 74; R13 := R14 end
314 [-]: JMP       74           ; PC := 74
315 [-]: GETUPVAL  R37 U0       ; R37 := U0
316 [-]: LEN       R37 R37      ; R37 := # R37
317 [-]: RETURN    R37 2        ; return R37
318 [-]: RETURN    R0 1         ; return 


; Function #13.2:
;
; Name:            
; Defined at line: 528
; #Upvalues:       4
; #Parameters:     0
; Is_vararg:       0
; Max Stack Size:  13

  1 [-]: GETGLOBAL R0 K0        ; R0 := 0xc8802016
  2 [-]: GETUPVAL  R1 U0        ; R1 := U0
  3 [-]: CALL      R0 2 4       ; R0,R1,R2 := R0(R1)
  4 [-]: JMP       9            ; PC := 9
  5 [-]: GETUPVAL  R5 U1        ; R5 := U1
  6 [-]: MOVE      R6 R4        ; R6 := R4
  7 [-]: GETUPVAL  R7 U2        ; R7 := U2
  8 [-]: CALL      R5 3 1       ; R5(R6,R7)
  9 [-]: TFORLOOP  R0 2         ; R3,R4 :=  R0(R1,R2); if R3 ~= nil then begin PC = 5; R2 := R3 end
 10 [-]: JMP       5            ; PC := 5
 11 [-]: GETGLOBAL R5 K0        ; R5 := 0xc8802016
 12 [-]: GETUPVAL  R6 U3        ; R6 := U3
 13 [-]: CALL      R5 2 4       ; R5,R6,R7 := R5(R6)
 14 [-]: JMP       36           ; PC := 36
 15 [-]: GETGLOBAL R10 K1       ; R10 := 0x7b998233
 16 [-]: MOVE      R11 R9       ; R11 := R9
 17 [-]: CALL      R10 2 2      ; R10 := R10(R11)
 18 [-]: TEST      R10 1        ; if R10 then PC := 36
 19 [-]: JMP       36           ; PC := 36
 20 [-]: SELF      R10 R9 K2    ; R11 := R9; R10 := R9[0xbb610e5b]
 21 [-]: CALL      R10 2 2      ; R10 := R10(R11)
 22 [-]: GETGLOBAL R11 K1       ; R11 := 0x7b998233
 23 [-]: MOVE      R12 R10      ; R12 := R10
 24 [-]: CALL      R11 2 2      ; R11 := R11(R12)
 25 [-]: TEST      R11 1        ; if R11 then PC := 36
 26 [-]: JMP       36           ; PC := 36
 27 [-]: SELF      R11 R10 K3   ; R12 := R10; R11 := R10[0x2047cfe7]
 28 [-]: CALL      R11 2 2      ; R11 := R11(R12)
 29 [-]: TEST      R11 1        ; if R11 then PC := 36
 30 [-]: JMP       36           ; PC := 36
 31 [-]: SELF      R11 R10 K4   ; R12 := R10; R11 := R10[0xfb3bba96]
 32 [-]: CALL      R11 2 1      ; R11(R12)
 33 [-]: GETGLOBAL R11 K5       ; R11 := 0xcbd666e1
 34 [-]: CONST     R12 0        ; R12 := 0.000000
 35 [-]: CALL      R11 2 1      ; R11(R12)
 36 [-]: TFORLOOP  R5 2         ; R8,R9 :=  R5(R6,R7); if R8 ~= nil then begin PC = 15; R7 := R8 end
 37 [-]: JMP       15           ; PC := 15
 38 [-]: RETURN    R0 1         ; return 


; Function #14:
;
; Name:            
; Defined at line: 546
; #Upvalues:       4
; #Parameters:     4
; Is_vararg:       0
; Max Stack Size:  17

  1 [-]: GETGLOBAL R4 K0        ; R4 := 0x89326c93
  2 [-]: SELF      R4 R4 K1     ; R5 := R4; R4 := R4[0x18d05d30]
  3 [-]: CALL      R4 2 2       ; R4 := R4(R5)
  4 [-]: TEST      R4 1         ; if R4 then PC := 7
  5 [-]: JMP       7            ; PC := 7
  6 [-]: RETURN    R0 1         ; return 
  7 [-]: GETGLOBAL R4 K2        ; R4 := 0x7b998233
  8 [-]: MOVE      R5 R1        ; R5 := R1
  9 [-]: CALL      R4 2 2       ; R4 := R4(R5)
 10 [-]: TEST      R4 0         ; if not R4 then PC := 13
 11 [-]: JMP       13           ; PC := 13
 12 [-]: RETURN    R0 1         ; return 
 13 [-]: NEWTABLE  R4 0 0       ; R4 := {}
 14 [-]: CONST     R5 0         ; R5 := 0.000000
 15 [-]: GETGLOBAL R6 K3        ; R6 := 0x0469f296
 16 [-]: LOADK     R7 K4        ; R7 := "InfestPodsHeal"
 17 [-]: CALL      R6 2 2       ; R6 := R6(R7)
 18 [-]: GETGLOBAL R7 K3        ; R7 := 0x0469f296
 19 [-]: LOADK     R8 K5        ; R8 := "InfestPodsAugment"
 20 [-]: CALL      R7 2 2       ; R7 := R7(R8)
 21 [-]: GETGLOBAL R8 K6        ; R8 := 0x6687f6e0
 22 [-]: SELF      R8 R8 K7     ; R9 := R8; R8 := R8[0xcde10c4a]
 23 [-]: CALL      R8 2 2       ; R8 := R8(R9)
 24 [-]: GETGLOBAL R9 K8        ; R9 := 0x6c97a788
 25 [-]: GETTABLE  R9 R9 K9     ; R9 := R9[0x608bc054]
 26 [-]: CALL      R9 1 2       ; R9 := R9()
 27 [-]: SETTABLE  R9 K10 R1    ; R9["instigator"] := R1
 28 [-]: GETUPVAL  R10 U0       ; R10 := U0
 29 [-]: SETTABLE  R9 K11 R10   ; R9["buffData"] := R10
 30 [-]: SETTABLE  R9 K12 K13   ; R9["buffType"] := 5.000000
 31 [-]: GETGLOBAL R10 K15      ; R10 := 0x53f6eef3
 32 [-]: SETTABLE  R9 K14 R10   ; R9["abilityType"] := R10
 33 [-]: SELF      R10 R0 K16   ; R11 := R0; R10 := R0[0x5063edc3]
 34 [-]: GETUPVAL  R12 U1       ; R12 := U1
 35 [-]: CALL      R10 3 2      ; R10 := R10(R11,R12)
 36 [-]: SELF      R11 R0 K17   ; R12 := R0; R11 := R0[0x75ecaf0b]
 37 [-]: GETUPVAL  R13 U1       ; R13 := U1
 38 [-]: CALL      R11 3 2      ; R11 := R11(R12,R13)
 39 [-]: LT        0 K18 R10    ; if 0.000000 >= R10 then PC := 43
 40 [-]: JMP       43           ; PC := 43
 41 [-]: EQ        1 R11 K19    ; if R11 == 1.000000 then PC := 44
 42 [-]: JMP       44           ; PC := 44
 43 [-]: LOADKB    R12 0 1      ; R12 := false; PC := 44
 44 [-]: LOADKB    R12 1 0      ; R12 := true
 45 [-]: LOADNIL   R13 R13      ; R13 := nil
 46 [-]: TEST      R12 0        ; if not R12 then PC := 65
 47 [-]: JMP       65           ; PC := 65
 48 [-]: GETGLOBAL R14 K8       ; R14 := 0x6c97a788
 49 [-]: GETTABLE  R14 R14 K9   ; R14 := R14[0x608bc054]
 50 [-]: CALL      R14 1 2      ; R14 := R14()
 51 [-]: MOVE      R13 R14      ; R13 := R14
 52 [-]: SETTABLE  R13 K10 R1   ; R13["instigator"] := R1
 53 [-]: GETGLOBAL R14 K20      ; R14 := 0x5bced4c4
 54 [-]: GETTABLE  R14 R14 K21  ; R14 := R14[0x55f27c30]
 55 [-]: GETUPVAL  R15 U2       ; R15 := U2
 56 [-]: MUL       R15 R15 K22  ; R15 := R15 * 100.000000
 57 [-]: CALL      R14 2 2      ; R14 := R14(R15)
 58 [-]: SETTABLE  R13 K11 R14  ; R13["buffData"] := R14
 59 [-]: SETTABLE  R13 K12 K23  ; R13["buffType"] := 2.000000
 60 [-]: SELF      R14 R0 K24   ; R15 := R0; R14 := R0[0x0688a24b]
 61 [-]: GETUPVAL  R16 U1       ; R16 := U1
 62 [-]: CALL      R14 3 2      ; R14 := R14(R15,R16)
 63 [-]: SETTABLE  R13 K14 R14  ; R13["abilityType"] := R14
 64 [-]: SETTABLE  R13 K25 R11  ; R13["augmentType"] := R11
 65 [-]: NEWTABLE  R14 0 2      ; R14 := {}
 66 [-]: CLOSURE   R15 0        ; R15 := closure(Function #14.1)
 67 [-]: MOVE      R0 R5        ; R0 := R5
 68 [-]: MOVE      R0 R2        ; R0 := R2
 69 [-]: MOVE      R0 R3        ; R0 := R3
 70 [-]: MOVE      R0 R1        ; R0 := R1
 71 [-]: MOVE      R0 R4        ; R0 := R4
 72 [-]: MOVE      R0 R6        ; R0 := R6
 73 [-]: GETUPVAL  R0 U0        ; R0 := U0
 74 [-]: MOVE      R0 R12       ; R0 := R12
 75 [-]: MOVE      R0 R7        ; R0 := R7
 76 [-]: GETUPVAL  R0 U2        ; R0 := U2
 77 [-]: MOVE      R0 R8        ; R0 := R8
 78 [-]: GETUPVAL  R0 U3        ; R0 := U3
 79 [-]: MOVE      R0 R9        ; R0 := R9
 80 [-]: MOVE      R0 R13       ; R0 := R13
 81 [-]: SETTABLE  R14 K26 R15  ; R14["Update"] := R15
 82 [-]: CLOSURE   R15 1        ; R15 := closure(Function #14.2)
 83 [-]: MOVE      R0 R4        ; R0 := R4
 84 [-]: MOVE      R0 R1        ; R0 := R1
 85 [-]: MOVE      R0 R6        ; R0 := R6
 86 [-]: GETUPVAL  R0 U0        ; R0 := U0
 87 [-]: MOVE      R0 R12       ; R0 := R12
 88 [-]: MOVE      R0 R7        ; R0 := R7
 89 [-]: GETUPVAL  R0 U2        ; R0 := U2
 90 [-]: MOVE      R0 R9        ; R0 := R9
 91 [-]: MOVE      R0 R13       ; R0 := R13
 92 [-]: SETTABLE  R14 K27 R15  ; R14["Terminate"] := R15
 93 [-]: RETURN    R14 2        ; return R14
 94 [-]: RETURN    R0 1         ; return 


; Function #14.1:
;
; Name:            
; Defined at line: 581
; #Upvalues:       14
; #Parameters:     0
; Is_vararg:       0
; Max Stack Size:  27

  1 [-]: GETUPVAL  R0 U0        ; R0 := U0
  2 [-]: LE        0 R0 K0      ; if R0 > 0.000000 then PC := 224
  3 [-]: JMP       224          ; PC := 224
  4 [-]: NEWTABLE  R0 0 0       ; R0 := {}
  5 [-]: NEWTABLE  R1 0 0       ; R1 := {}
  6 [-]: NEWTABLE  R2 0 0       ; R2 := {}
  7 [-]: CONST     R3 0         ; R3 := 0.000000
  8 [-]: GETGLOBAL R4 K1        ; R4 := 0x89326c93
  9 [-]: SELF      R4 R4 K2     ; R5 := R4; R4 := R4[0xfb669000]
 10 [-]: GETGLOBAL R6 K3        ; R6 := gLotusAvatarType
 11 [-]: GETUPVAL  R7 U1        ; R7 := U1
 12 [-]: CONST     R8 0         ; R8 := 0.000000
 13 [-]: GETUPVAL  R9 U2        ; R9 := U2
 14 [-]: CALL      R4 6 2       ; R4 := R4(R5,R6,R7,R8,R9)
 15 [-]: GETGLOBAL R5 K4        ; R5 := 0xc8802016
 16 [-]: MOVE      R6 R4        ; R6 := R4
 17 [-]: CALL      R5 2 4       ; R5,R6,R7 := R5(R6)
 18 [-]: JMP       113          ; PC := 113
 19 [-]: SELF      R10 R9 K5    ; R11 := R9; R10 := R9[0xee0bc178]
 20 [-]: GETUPVAL  R12 U3       ; R12 := U3
 21 [-]: CALL      R10 3 2      ; R10 := R10(R11,R12)
 22 [-]: TEST      R10 0        ; if not R10 then PC := 113
 23 [-]: JMP       113          ; PC := 113
 24 [-]: SELF      R10 R9 K6    ; R11 := R9; R10 := R9[0x753a7ea6]
 25 [-]: GETUPVAL  R12 U3       ; R12 := U3
 26 [-]: CALL      R10 3 2      ; R10 := R10(R11,R12)
 27 [-]: TEST      R10 0        ; if not R10 then PC := 113
 28 [-]: JMP       113          ; PC := 113
 29 [-]: GETGLOBAL R10 K7       ; R10 := 0x7b998233
 30 [-]: GETGLOBAL R11 K8       ; R11 := 0x6687f6e0
 31 [-]: CALL      R10 2 2      ; R10 := R10(R11)
 32 [-]: TEST      R10 1        ; if R10 then PC := 113
 33 [-]: JMP       113          ; PC := 113
 34 [-]: GETGLOBAL R10 K8       ; R10 := 0x6687f6e0
 35 [-]: SELF      R10 R10 K9   ; R11 := R10; R10 := R10[0xc05a66cd]
 36 [-]: MOVE      R12 R9       ; R12 := R9
 37 [-]: CALL      R10 3 2      ; R10 := R10(R11,R12)
 38 [-]: TEST      R10 1        ; if R10 then PC := 113
 39 [-]: JMP       113          ; PC := 113
 40 [-]: SELF      R10 R9 K10   ; R11 := R9; R10 := R9[0x388577d5]
 41 [-]: CALL      R10 2 2      ; R10 := R10(R11)
 42 [-]: GETGLOBAL R11 K7       ; R11 := 0x7b998233
 43 [-]: GETUPVAL  R12 U4       ; R12 := U4
 44 [-]: GETTABLE  R12 R12 R10  ; R12 := R12[R10]
 45 [-]: CALL      R11 2 2      ; R11 := R11(R12)
 46 [-]: TEST      R11 0        ; if not R11 then PC := 85
 47 [-]: JMP       85           ; PC := 85
 48 [-]: GETUPVAL  R11 U3       ; R11 := U3
 49 [-]: SELF      R11 R11 K11  ; R12 := R11; R11 := R11[0x6d6734dc]
 50 [-]: MOVE      R13 R9       ; R13 := R9
 51 [-]: CALL      R11 3 2      ; R11 := R11(R12,R13)
 52 [-]: TEST      R11 0        ; if not R11 then PC := 85
 53 [-]: JMP       85           ; PC := 85
 54 [-]: SELF      R11 R9 K12   ; R12 := R9; R11 := R9[0xde321e6f]
 55 [-]: CALL      R11 2 2      ; R11 := R11(R12)
 56 [-]: SELF      R12 R11 K13  ; R13 := R11; R12 := R11[0xeade8050]
 57 [-]: GETUPVAL  R14 U5       ; R14 := U5
 58 [-]: CONST     R15 63       ; R15 := 63.000000
 59 [-]: CONST     R16 0        ; R16 := 0.000000
 60 [-]: GETUPVAL  R17 U6       ; R17 := U6
 61 [-]: CALL      R12 6 1      ; R12(R13,R14,R15,R16,R17)
 62 [-]: GETGLOBAL R12 K16      ; R12 := 0x33bdd652
 63 [-]: GETTABLE  R12 R12 K17  ; R12 := R12[0x23d5322f]
 64 [-]: MOVE      R13 R0       ; R13 := R0
 65 [-]: MOVE      R14 R9       ; R14 := R9
 66 [-]: CALL      R12 3 1      ; R12(R13,R14)
 67 [-]: GETUPVAL  R12 U7       ; R12 := U7
 68 [-]: TEST      R12 0        ; if not R12 then PC := 85
 69 [-]: JMP       85           ; PC := 85
 70 [-]: GETUPVAL  R12 U3       ; R12 := U3
 71 [-]: EQ        0 R9 R12     ; if R9 ~= R12 then PC := 85
 72 [-]: JMP       85           ; PC := 85
 73 [-]: SELF      R12 R11 K13  ; R13 := R11; R12 := R11[0xeade8050]
 74 [-]: GETUPVAL  R14 U8       ; R14 := U8
 75 [-]: CONST     R15 140      ; R15 := 140.000000
 76 [-]: CONST     R16 0        ; R16 := 0.000000
 77 [-]: GETUPVAL  R17 U9       ; R17 := U9
 78 [-]: GETUPVAL  R18 U10      ; R18 := U10
 79 [-]: CALL      R12 7 1      ; R12(R13,R14,R15,R16,R17,R18)
 80 [-]: GETGLOBAL R12 K16      ; R12 := 0x33bdd652
 81 [-]: GETTABLE  R12 R12 K17  ; R12 := R12[0x23d5322f]
 82 [-]: MOVE      R13 R1       ; R13 := R1
 83 [-]: MOVE      R14 R9       ; R14 := R9
 84 [-]: CALL      R12 3 1      ; R12(R13,R14)
 85 [-]: SETTABLE  R2 R10 R9    ; R2[R10] := R9
 86 [-]: GETUPVAL  R12 U4       ; R12 := U4
 87 [-]: SETTABLE  R12 R10 K18  ; R12[R10] := nil
 88 [-]: SELF      R12 R9 K19   ; R13 := R9; R12 := R9[0xfa9e477f]
 89 [-]: CALL      R12 2 2      ; R12 := R12(R13)
 90 [-]: TEST      R12 0        ; if not R12 then PC := 97
 91 [-]: JMP       97           ; PC := 97
 92 [-]: SELF      R13 R12 K20  ; R14 := R12; R13 := R12[0xf2deaf69]
 93 [-]: GETGLOBAL R15 K21      ; R15 := 0x51fe62f3
 94 [-]: CALL      R13 3 2      ; R13 := R13(R14,R15)
 95 [-]: TEST      R13 1        ; if R13 then PC := 113
 96 [-]: JMP       113          ; PC := 113
 97 [-]: GETUPVAL  R13 U0       ; R13 := U0
 98 [-]: ADD       R13 R13 K22  ; R13 := R13 + 0.200000
 99 [-]: GETGLOBAL R14 K23      ; R14 := 0x67652851
100 [-]: CALL      R14 1 2      ; R14 := R14()
101 [-]: ADD       R13 R13 R14  ; R13 := R13 + R14
102 [-]: GETGLOBAL R14 K24      ; R14 := 0x5bced4c4
103 [-]: GETTABLE  R14 R14 K25  ; R14 := R14[0xac1b386a]
104 [-]: GETUPVAL  R15 U6       ; R15 := U6
105 [-]: MUL       R15 R15 R13  ; R15 := R15 * R13
106 [-]: SELF      R16 R9 K26   ; R17 := R9; R16 := R9[0xb40c191a]
107 [-]: CALL      R16 2 2      ; R16 := R16(R17)
108 [-]: SELF      R17 R9 K27   ; R18 := R9; R17 := R9[0xd2715720]
109 [-]: CALL      R17 2 2      ; R17 := R17(R18)
110 [-]: SUB       R16 R16 R17  ; R16 := R16 - R17
111 [-]: CALL      R14 3 2      ; R14 := R14(R15,R16)
112 [-]: ADD       R3 R3 R14    ; R3 := R3 + R14
113 [-]: TFORLOOP  R5 2         ; R8,R9 :=  R5(R6,R7); if R8 ~= nil then begin PC = 19; R7 := R8 end
114 [-]: JMP       19           ; PC := 19
115 [-]: GETUPVAL  R14 U11      ; R14 := U11
116 [-]: GETTABLE  R14 R14 K28  ; R14 := R14[0xe1eecb19]
117 [-]: GETUPVAL  R15 U3       ; R15 := U3
118 [-]: MOVE      R16 R3       ; R16 := R3
119 [-]: CALL      R14 3 1      ; R14(R15,R16)
120 [-]: LEN       R14 R0       ; R14 := # R0
121 [-]: LT        0 K0 R14     ; if 0.000000 >= R14 then PC := 133
122 [-]: JMP       133          ; PC := 133
123 [-]: GETUPVAL  R14 U12      ; R14 := U12
124 [-]: SETTABLE  R14 K29 R0   ; R14["affected"] := R0
125 [-]: GETTABLE  R14 R0 K30   ; R14 := R0[1.000000]
126 [-]: SELF      R14 R14 K31  ; R15 := R14; R14 := R14[0x37e45fb5]
127 [-]: GETUPVAL  R16 U12      ; R16 := U12
128 [-]: LOADKB    R17 1 0      ; R17 := true
129 [-]: LOADKB    R18 1 0      ; R18 := true
130 [-]: CALL      R14 5 1      ; R14(R15,R16,R17,R18)
131 [-]: NEWTABLE  R14 0 0      ; R14 := {}
132 [-]: MOVE      R0 R14       ; R0 := R14
133 [-]: LEN       R14 R1       ; R14 := # R1
134 [-]: LT        0 K0 R14     ; if 0.000000 >= R14 then PC := 146
135 [-]: JMP       146          ; PC := 146
136 [-]: GETUPVAL  R14 U13      ; R14 := U13
137 [-]: SETTABLE  R14 K29 R1   ; R14["affected"] := R1
138 [-]: GETTABLE  R14 R1 K30   ; R14 := R1[1.000000]
139 [-]: SELF      R14 R14 K31  ; R15 := R14; R14 := R14[0x37e45fb5]
140 [-]: GETUPVAL  R16 U13      ; R16 := U13
141 [-]: LOADKB    R17 1 0      ; R17 := true
142 [-]: LOADKB    R18 1 0      ; R18 := true
143 [-]: CALL      R14 5 1      ; R14(R15,R16,R17,R18)
144 [-]: NEWTABLE  R14 0 0      ; R14 := {}
145 [-]: MOVE      R1 R14       ; R1 := R14
146 [-]: GETGLOBAL R14 K32      ; R14 := 0xcfc01047
147 [-]: GETUPVAL  R15 U4       ; R15 := U4
148 [-]: CALL      R14 2 4      ; R14,R15,R16 := R14(R15)
149 [-]: JMP       196          ; PC := 196
150 [-]: GETGLOBAL R19 K7       ; R19 := 0x7b998233
151 [-]: MOVE      R20 R18      ; R20 := R18
152 [-]: CALL      R19 2 2      ; R19 := R19(R20)
153 [-]: TEST      R19 1        ; if R19 then PC := 196
154 [-]: JMP       196          ; PC := 196
155 [-]: SELF      R19 R18 K33  ; R20 := R18; R19 := R18[0x2047cfe7]
156 [-]: CALL      R19 2 2      ; R19 := R19(R20)
157 [-]: TEST      R19 1        ; if R19 then PC := 196
158 [-]: JMP       196          ; PC := 196
159 [-]: GETUPVAL  R19 U3       ; R19 := U3
160 [-]: SELF      R19 R19 K11  ; R20 := R19; R19 := R19[0x6d6734dc]
161 [-]: MOVE      R21 R18      ; R21 := R18
162 [-]: CALL      R19 3 2      ; R19 := R19(R20,R21)
163 [-]: TEST      R19 0        ; if not R19 then PC := 196
164 [-]: JMP       196          ; PC := 196
165 [-]: SELF      R19 R18 K12  ; R20 := R18; R19 := R18[0xde321e6f]
166 [-]: CALL      R19 2 2      ; R19 := R19(R20)
167 [-]: SELF      R20 R19 K34  ; R21 := R19; R20 := R19[0x2722b5c3]
168 [-]: GETUPVAL  R22 U5       ; R22 := U5
169 [-]: CONST     R23 63       ; R23 := 63.000000
170 [-]: CONST     R24 0        ; R24 := 0.000000
171 [-]: GETUPVAL  R25 U6       ; R25 := U6
172 [-]: CALL      R20 6 1      ; R20(R21,R22,R23,R24,R25)
173 [-]: GETGLOBAL R20 K16      ; R20 := 0x33bdd652
174 [-]: GETTABLE  R20 R20 K17  ; R20 := R20[0x23d5322f]
175 [-]: MOVE      R21 R0       ; R21 := R0
176 [-]: MOVE      R22 R18      ; R22 := R18
177 [-]: CALL      R20 3 1      ; R20(R21,R22)
178 [-]: GETUPVAL  R20 U7       ; R20 := U7
179 [-]: TEST      R20 0        ; if not R20 then PC := 196
180 [-]: JMP       196          ; PC := 196
181 [-]: GETUPVAL  R20 U3       ; R20 := U3
182 [-]: EQ        0 R18 R20    ; if R18 ~= R20 then PC := 196
183 [-]: JMP       196          ; PC := 196
184 [-]: SELF      R20 R19 K34  ; R21 := R19; R20 := R19[0x2722b5c3]
185 [-]: GETUPVAL  R22 U8       ; R22 := U8
186 [-]: CONST     R23 140      ; R23 := 140.000000
187 [-]: CONST     R24 0        ; R24 := 0.000000
188 [-]: GETUPVAL  R25 U9       ; R25 := U9
189 [-]: GETUPVAL  R26 U10      ; R26 := U10
190 [-]: CALL      R20 7 1      ; R20(R21,R22,R23,R24,R25,R26)
191 [-]: GETGLOBAL R20 K16      ; R20 := 0x33bdd652
192 [-]: GETTABLE  R20 R20 K17  ; R20 := R20[0x23d5322f]
193 [-]: MOVE      R21 R1       ; R21 := R1
194 [-]: MOVE      R22 R18      ; R22 := R18
195 [-]: CALL      R20 3 1      ; R20(R21,R22)
196 [-]: TFORLOOP  R14 2        ; R17,R18 :=  R14(R15,R16); if R17 ~= nil then begin PC = 150; R16 := R17 end
197 [-]: JMP       150          ; PC := 150
198 [-]: LEN       R20 R0       ; R20 := # R0
199 [-]: LT        0 K0 R20     ; if 0.000000 >= R20 then PC := 209
200 [-]: JMP       209          ; PC := 209
201 [-]: GETUPVAL  R20 U12      ; R20 := U12
202 [-]: SETTABLE  R20 K29 R0   ; R20["affected"] := R0
203 [-]: GETTABLE  R20 R0 K30   ; R20 := R0[1.000000]
204 [-]: SELF      R20 R20 K31  ; R21 := R20; R20 := R20[0x37e45fb5]
205 [-]: GETUPVAL  R22 U12      ; R22 := U12
206 [-]: LOADKB    R23 0 0      ; R23 := false
207 [-]: LOADKB    R24 1 0      ; R24 := true
208 [-]: CALL      R20 5 1      ; R20(R21,R22,R23,R24)
209 [-]: LEN       R20 R1       ; R20 := # R1
210 [-]: LT        0 K0 R20     ; if 0.000000 >= R20 then PC := 220
211 [-]: JMP       220          ; PC := 220
212 [-]: GETUPVAL  R20 U13      ; R20 := U13
213 [-]: SETTABLE  R20 K29 R1   ; R20["affected"] := R1
214 [-]: GETTABLE  R20 R1 K30   ; R20 := R1[1.000000]
215 [-]: SELF      R20 R20 K31  ; R21 := R20; R20 := R20[0x37e45fb5]
216 [-]: GETUPVAL  R22 U13      ; R22 := U13
217 [-]: LOADKB    R23 0 0      ; R23 := false
218 [-]: LOADKB    R24 1 0      ; R24 := true
219 [-]: CALL      R20 5 1      ; R20(R21,R22,R23,R24)
220 [-]: SETUPVAL  R2 U4        ; U82 := R4
221 [-]: GETUPVAL  R20 U0       ; R20 := U0
222 [-]: ADD       R20 R20 K22  ; R20 := R20 + 0.200000
223 [-]: SETUPVAL  R20 U0       ; U82 := R0
224 [-]: GETUPVAL  R20 U0       ; R20 := U0
225 [-]: GETGLOBAL R21 K23      ; R21 := 0x67652851
226 [-]: CALL      R21 1 2      ; R21 := R21()
227 [-]: SUB       R20 R20 R21  ; R20 := R20 - R21
228 [-]: SETUPVAL  R20 U0       ; U82 := R0
229 [-]: RETURN    R0 1         ; return 


; Function #14.2:
;
; Name:            
; Defined at line: 674
; #Upvalues:       9
; #Parameters:     0
; Is_vararg:       0
; Max Stack Size:  16

  1 [-]: NEWTABLE  R0 0 0       ; R0 := {}
  2 [-]: NEWTABLE  R1 0 0       ; R1 := {}
  3 [-]: GETGLOBAL R2 K0        ; R2 := 0xcfc01047
  4 [-]: GETUPVAL  R3 U0        ; R3 := U0
  5 [-]: CALL      R2 2 4       ; R2,R3,R4 := R2(R3)
  6 [-]: JMP       60           ; PC := 60
  7 [-]: GETGLOBAL R7 K1        ; R7 := 0x7b998233
  8 [-]: MOVE      R8 R6        ; R8 := R6
  9 [-]: CALL      R7 2 2       ; R7 := R7(R8)
 10 [-]: TEST      R7 1         ; if R7 then PC := 60
 11 [-]: JMP       60           ; PC := 60
 12 [-]: SELF      R7 R6 K2     ; R8 := R6; R7 := R6[0x2047cfe7]
 13 [-]: CALL      R7 2 2       ; R7 := R7(R8)
 14 [-]: TEST      R7 1         ; if R7 then PC := 60
 15 [-]: JMP       60           ; PC := 60
 16 [-]: GETGLOBAL R7 K1        ; R7 := 0x7b998233
 17 [-]: GETUPVAL  R8 U1        ; R8 := U1
 18 [-]: CALL      R7 2 2       ; R7 := R7(R8)
 19 [-]: TEST      R7 1         ; if R7 then PC := 60
 20 [-]: JMP       60           ; PC := 60
 21 [-]: GETUPVAL  R7 U1        ; R7 := U1
 22 [-]: SELF      R7 R7 K3     ; R8 := R7; R7 := R7[0x6d6734dc]
 23 [-]: MOVE      R9 R6        ; R9 := R6
 24 [-]: CALL      R7 3 2       ; R7 := R7(R8,R9)
 25 [-]: TEST      R7 0         ; if not R7 then PC := 60
 26 [-]: JMP       60           ; PC := 60
 27 [-]: SELF      R7 R6 K4     ; R8 := R6; R7 := R6[0xde321e6f]
 28 [-]: CALL      R7 2 2       ; R7 := R7(R8)
 29 [-]: SELF      R8 R7 K5     ; R9 := R7; R8 := R7[0x2722b5c3]
 30 [-]: GETUPVAL  R10 U2       ; R10 := U2
 31 [-]: CONST     R11 63       ; R11 := 63.000000
 32 [-]: CONST     R12 0        ; R12 := 0.000000
 33 [-]: GETUPVAL  R13 U3       ; R13 := U3
 34 [-]: CALL      R8 6 1       ; R8(R9,R10,R11,R12,R13)
 35 [-]: GETGLOBAL R8 K8        ; R8 := 0x33bdd652
 36 [-]: GETTABLE  R8 R8 K9     ; R8 := R8[0x23d5322f]
 37 [-]: MOVE      R9 R0        ; R9 := R0
 38 [-]: MOVE      R10 R6       ; R10 := R6
 39 [-]: CALL      R8 3 1       ; R8(R9,R10)
 40 [-]: GETUPVAL  R8 U4        ; R8 := U4
 41 [-]: TEST      R8 0         ; if not R8 then PC := 60
 42 [-]: JMP       60           ; PC := 60
 43 [-]: GETUPVAL  R8 U1        ; R8 := U1
 44 [-]: EQ        0 R6 R8      ; if R6 ~= R8 then PC := 60
 45 [-]: JMP       60           ; PC := 60
 46 [-]: SELF      R8 R7 K5     ; R9 := R7; R8 := R7[0x2722b5c3]
 47 [-]: GETUPVAL  R10 U5       ; R10 := U5
 48 [-]: CONST     R11 140      ; R11 := 140.000000
 49 [-]: CONST     R12 0        ; R12 := 0.000000
 50 [-]: GETUPVAL  R13 U6       ; R13 := U6
 51 [-]: GETGLOBAL R14 K10      ; R14 := 0x6687f6e0
 52 [-]: SELF      R14 R14 K11  ; R15 := R14; R14 := R14[0xcde10c4a]
 53 [-]: CALL      R14 2 0      ; R14,... := R14(R15)
 54 [-]: CALL      R8 0 1       ; R8(R9,...)
 55 [-]: GETGLOBAL R8 K8        ; R8 := 0x33bdd652
 56 [-]: GETTABLE  R8 R8 K9     ; R8 := R8[0x23d5322f]
 57 [-]: MOVE      R9 R1        ; R9 := R1
 58 [-]: MOVE      R10 R6       ; R10 := R6
 59 [-]: CALL      R8 3 1       ; R8(R9,R10)
 60 [-]: TFORLOOP  R2 2         ; R5,R6 :=  R2(R3,R4); if R5 ~= nil then begin PC = 7; R4 := R5 end
 61 [-]: JMP       7            ; PC := 7
 62 [-]: LEN       R8 R0        ; R8 := # R0
 63 [-]: LT        0 K12 R8     ; if 0.000000 >= R8 then PC := 73
 64 [-]: JMP       73           ; PC := 73
 65 [-]: GETUPVAL  R8 U7        ; R8 := U7
 66 [-]: SETTABLE  R8 K13 R0    ; R8["affected"] := R0
 67 [-]: GETTABLE  R8 R0 K14    ; R8 := R0[1.000000]
 68 [-]: SELF      R8 R8 K15    ; R9 := R8; R8 := R8[0x37e45fb5]
 69 [-]: GETUPVAL  R10 U7       ; R10 := U7
 70 [-]: LOADKB    R11 0 0      ; R11 := false
 71 [-]: LOADKB    R12 1 0      ; R12 := true
 72 [-]: CALL      R8 5 1       ; R8(R9,R10,R11,R12)
 73 [-]: LEN       R8 R1        ; R8 := # R1
 74 [-]: LT        0 K12 R8     ; if 0.000000 >= R8 then PC := 84
 75 [-]: JMP       84           ; PC := 84
 76 [-]: GETUPVAL  R8 U8        ; R8 := U8
 77 [-]: SETTABLE  R8 K13 R1    ; R8["affected"] := R1
 78 [-]: GETTABLE  R8 R1 K14    ; R8 := R1[1.000000]
 79 [-]: SELF      R8 R8 K15    ; R9 := R8; R8 := R8[0x37e45fb5]
 80 [-]: GETUPVAL  R10 U8       ; R10 := U8
 81 [-]: LOADKB    R11 0 0      ; R11 := false
 82 [-]: LOADKB    R12 1 0      ; R12 := true
 83 [-]: CALL      R8 5 1       ; R8(R9,R10,R11,R12)
 84 [-]: RETURN    R0 1         ; return 


; Function #15:
;
; Name:            
; Defined at line: 709
; #Upvalues:       7
; #Parameters:     3
; Is_vararg:       0
; Max Stack Size:  25

  1 [-]: GETUPVAL  R3 U0        ; R3 := U0
  2 [-]: MOVE      R4 R0        ; R4 := R0
  3 [-]: CALL      R3 2 2       ; R3 := R3(R4)
  4 [-]: GETTABLE  R3 R3 K0     ; R3 := R3[1.000000]
  5 [-]: SELF      R4 R1 K1     ; R5 := R1; R4 := R1[0xd1586535]
  6 [-]: CALL      R4 2 2       ; R4 := R4(R5)
  7 [-]: NEWTABLE  R5 0 0       ; R5 := {}
  8 [-]: GETGLOBAL R6 K2        ; R6 := 0xa421af95
  9 [-]: CALL      R6 1 2       ; R6 := R6()
 10 [-]: NEWTABLE  R7 5 0       ; R7 := {}
 11 [-]: GETUPVAL  R8 U1        ; R8 := U1
 12 [-]: GETUPVAL  R9 U2        ; R9 := U2
 13 [-]: GETUPVAL  R10 U3       ; R10 := U3
 14 [-]: GETUPVAL  R11 U4       ; R11 := U4
 15 [-]: GETUPVAL  R12 U5       ; R12 := U5
 16 [-]: SETLIST   R7 5 1       ; R7[(1-1)*FPF+i] := R(7+i), 1 <= i <= 5
 17 [-]: LOADKB    R8 1 0       ; R8 := true
 18 [-]: CONST     R9 1         ; R9 := 1.000000
 19 [-]: CONST     R10 4        ; R10 := 4.000000
 20 [-]: CONST     R11 10       ; R11 := 10.000000
 21 [-]: NEWTABLE  R12 4 0      ; R12 := {}
 22 [-]: GETGLOBAL R13 K3       ; R13 := gBaseAvatarType
 23 [-]: GETGLOBAL R14 K4       ; R14 := gPickUpType
 24 [-]: GETGLOBAL R15 K5       ; R15 := gRagdollType
 25 [-]: GETGLOBAL R16 K6       ; R16 := gHitProxyType
 26 [-]: SETLIST   R12 4 1      ; R12[(1-1)*FPF+i] := R(12+i), 1 <= i <= 4
 27 [-]: GETGLOBAL R13 K2       ; R13 := 0xa421af95
 28 [-]: CALL      R13 1 2      ; R13 := R13()
 29 [-]: ADD       R13 R4 R13   ; R13 := R4 + R13
 30 [-]: GETGLOBAL R14 K2       ; R14 := 0xa421af95
 31 [-]: CONST     R15 8        ; R15 := 8.000000
 32 [-]: CONST     R16 8        ; R16 := 8.000000
 33 [-]: CONST     R17 8        ; R17 := 8.000000
 34 [-]: CALL      R14 4 2      ; R14 := R14(R15,R16,R17)
 35 [-]: ADD       R14 R4 R14   ; R14 := R4 + R14
 36 [-]: LOADKB    R15 1 0      ; R15 := true
 37 [-]: GETGLOBAL R16 K7       ; R16 := 0x89326c93
 38 [-]: SELF      R16 R16 K8   ; R17 := R16; R16 := R16[0x05909209]
 39 [-]: GETGLOBAL R18 K9       ; R18 := 0xd7a31cbe
 40 [-]: GETGLOBAL R19 K2       ; R19 := 0xa421af95
 41 [-]: CONST     R20 0        ; R20 := 0.000000
 42 [-]: CONST     R21 1        ; R21 := 1.000000
 43 [-]: CONST     R22 0        ; R22 := 0.000000
 44 [-]: CALL      R19 4 2      ; R19 := R19(R20,R21,R22)
 45 [-]: ADD       R19 R4 R19   ; R19 := R4 + R19
 46 [-]: GETGLOBAL R20 K10      ; R20 := 0x00046924
 47 [-]: CONST     R21 0        ; R21 := 0.000000
 48 [-]: CONST     R22 90       ; R22 := 90.000000
 49 [-]: CONST     R23 0        ; R23 := 0.000000
 50 [-]: CALL      R20 4 2      ; R20 := R20(R21,R22,R23)
 51 [-]: MOVE      R21 R0       ; R21 := R0
 52 [-]: MOVE      R22 R1       ; R22 := R1
 53 [-]: CALL      R16 7 2      ; R16 := R16(R17,R18,R19,R20,R21,R22)
 54 [-]: GETGLOBAL R17 K11      ; R17 := 0x7b998233
 55 [-]: MOVE      R18 R16      ; R18 := R16
 56 [-]: CALL      R17 2 2      ; R17 := R17(R18)
 57 [-]: TEST      R17 1        ; if R17 then PC := 64
 58 [-]: JMP       64           ; PC := 64
 59 [-]: SELF      R17 R16 K12  ; R18 := R16; R17 := R16[0xb3c6250f]
 60 [-]: MUL       R19 R2 K13   ; R19 := R2 * 2.100000
 61 [-]: MUL       R20 R2 K13   ; R20 := R2 * 2.100000
 62 [-]: CONST     R21 2        ; R21 := 2.000000
 63 [-]: CALL      R17 5 1      ; R17(R18,R19,R20,R21)
 64 [-]: GETGLOBAL R17 K7       ; R17 := 0x89326c93
 65 [-]: SELF      R17 R17 K8   ; R18 := R17; R17 := R17[0x05909209]
 66 [-]: GETGLOBAL R19 K14      ; R19 := 0x241523bc
 67 [-]: GETGLOBAL R20 K2       ; R20 := 0xa421af95
 68 [-]: CONST     R21 0        ; R21 := 0.000000
 69 [-]: CONST     R22 1        ; R22 := 1.000000
 70 [-]: CONST     R23 0        ; R23 := 0.000000
 71 [-]: CALL      R20 4 2      ; R20 := R20(R21,R22,R23)
 72 [-]: ADD       R20 R4 R20   ; R20 := R4 + R20
 73 [-]: GETGLOBAL R21 K15      ; R21 := ZERO_ROTATION
 74 [-]: MOVE      R22 R0       ; R22 := R0
 75 [-]: MOVE      R23 R1       ; R23 := R1
 76 [-]: CALL      R17 7 2      ; R17 := R17(R18,R19,R20,R21,R22,R23)
 77 [-]: GETGLOBAL R18 K11      ; R18 := 0x7b998233
 78 [-]: MOVE      R19 R17      ; R19 := R17
 79 [-]: CALL      R18 2 2      ; R18 := R18(R19)
 80 [-]: TEST      R18 1        ; if R18 then PC := 92
 81 [-]: JMP       92           ; PC := 92
 82 [-]: SELF      R18 R17 K16  ; R19 := R17; R18 := R17[0x66472bf5]
 83 [-]: CONST     R20 1        ; R20 := 1.000000
 84 [-]: CALL      R18 3 1      ; R18(R19,R20)
 85 [-]: SELF      R18 R17 K17  ; R19 := R17; R18 := R17[0x986d2ab8]
 86 [-]: GETUPVAL  R20 U1       ; R20 := U1
 87 [-]: GETTABLE  R21 R3 K18   ; R21 := R3["x"]
 88 [-]: GETTABLE  R22 R3 K19   ; R22 := R3["y"]
 89 [-]: GETTABLE  R23 R3 K20   ; R23 := R3["z"]
 90 [-]: CONST     R24 1        ; R24 := 1.000000
 91 [-]: CALL      R18 7 1      ; R18(R19,R20,R21,R22,R23,R24)
 92 [-]: GETGLOBAL R18 K7       ; R18 := 0x89326c93
 93 [-]: SELF      R18 R18 K21  ; R19 := R18; R18 := R18[0x29ef273d]
 94 [-]: CALL      R18 2 2      ; R18 := R18(R19)
 95 [-]: NEWTABLE  R19 0 2      ; R19 := {}
 96 [-]: CLOSURE   R20 0        ; R20 := closure(Function #15.1)
 97 [-]: MOVE      R0 R8        ; R0 := R8
 98 [-]: MOVE      R0 R9        ; R0 := R9
 99 [-]: MOVE      R0 R6        ; R0 := R6
100 [-]: MOVE      R0 R4        ; R0 := R4
101 [-]: MOVE      R0 R2        ; R0 := R2
102 [-]: MOVE      R0 R18       ; R0 := R18
103 [-]: GETUPVAL  R0 U6        ; R0 := U6
104 [-]: MOVE      R0 R0        ; R0 := R0
105 [-]: MOVE      R0 R1        ; R0 := R1
106 [-]: MOVE      R0 R5        ; R0 := R5
107 [-]: MOVE      R0 R7        ; R0 := R7
108 [-]: MOVE      R0 R3        ; R0 := R3
109 [-]: MOVE      R0 R16       ; R0 := R16
110 [-]: MOVE      R0 R17       ; R0 := R17
111 [-]: MOVE      R0 R10       ; R0 := R10
112 [-]: MOVE      R0 R11       ; R0 := R11
113 [-]: MOVE      R0 R15       ; R0 := R15
114 [-]: MOVE      R0 R13       ; R0 := R13
115 [-]: MOVE      R0 R14       ; R0 := R14
116 [-]: MOVE      R0 R12       ; R0 := R12
117 [-]: GETUPVAL  R0 U1        ; R0 := U1
118 [-]: GETUPVAL  R0 U2        ; R0 := U2
119 [-]: GETUPVAL  R0 U3        ; R0 := U3
120 [-]: SETTABLE  R19 K22 R20  ; R19["Update"] := R20
121 [-]: CLOSURE   R20 1        ; R20 := closure(Function #15.2)
122 [-]: MOVE      R0 R16       ; R0 := R16
123 [-]: MOVE      R0 R17       ; R0 := R17
124 [-]: MOVE      R0 R5        ; R0 := R5
125 [-]: SETTABLE  R19 K23 R20  ; R19["Terminate"] := R20
126 [-]: RETURN    R19 2        ; return R19
127 [-]: RETURN    R0 1         ; return 


; Function #15.1:
;
; Name:            
; Defined at line: 741
; #Upvalues:       23
; #Parameters:     0
; Is_vararg:       0
; Max Stack Size:  16

  1 [-]: GETUPVAL  R0 U0        ; R0 := U0
  2 [-]: TEST      R0 0         ; if not R0 then PC := 141
  3 [-]: JMP       141          ; PC := 141
  4 [-]: GETUPVAL  R0 U1        ; R0 := U1
  5 [-]: LE        0 R0 K0      ; if R0 > 12.000000 then PC := 121
  6 [-]: JMP       121          ; PC := 121
  7 [-]: GETGLOBAL R0 K1        ; R0 := 0x4232ec01
  8 [-]: LEN       R0 R0        ; R0 := # R0
  9 [-]: LT        0 K2 R0      ; if 0.000000 >= R0 then PC := 87
 10 [-]: JMP       87           ; PC := 87
 11 [-]: GETUPVAL  R0 U3        ; R0 := U3
 12 [-]: GETGLOBAL R1 K3        ; R1 := 0xa421af95
 13 [-]: GETGLOBAL R2 K4        ; R2 := 0xc163f229
 14 [-]: GETUPVAL  R3 U4        ; R3 := U4
 15 [-]: UNM       R3 R3        ; R3 :=  R3
 16 [-]: MUL       R3 R3 K5     ; R3 := R3 * 0.800000
 17 [-]: GETUPVAL  R4 U4        ; R4 := U4
 18 [-]: MUL       R4 R4 K5     ; R4 := R4 * 0.800000
 19 [-]: CALL      R2 3 2       ; R2 := R2(R3,R4)
 20 [-]: CONST     R3 0         ; R3 := 0.000000
 21 [-]: GETGLOBAL R4 K4        ; R4 := 0xc163f229
 22 [-]: GETUPVAL  R5 U4        ; R5 := U4
 23 [-]: UNM       R5 R5        ; R5 :=  R5
 24 [-]: MUL       R5 R5 K5     ; R5 := R5 * 0.800000
 25 [-]: GETUPVAL  R6 U4        ; R6 := U4
 26 [-]: MUL       R6 R6 K5     ; R6 := R6 * 0.800000
 27 [-]: CALL      R4 3 0       ; R4,... := R4(R5,R6)
 28 [-]: CALL      R1 0 2       ; R1 := R1(R2,...)
 29 [-]: ADD       R0 R0 R1     ; R0 := R0 + R1
 30 [-]: SETUPVAL  R0 U2        ; U82 := R2
 31 [-]: GETUPVAL  R0 U5        ; R0 := U5
 32 [-]: SELF      R0 R0 K6     ; R1 := R0; R0 := R0[0x40f8914b]
 33 [-]: GETUPVAL  R2 U2        ; R2 := U2
 34 [-]: CONST     R3 5         ; R3 := 5.000000
 35 [-]: CONST     R4 0         ; R4 := 0.000000
 36 [-]: GETUPVAL  R5 U6        ; R5 := U6
 37 [-]: CALL      R0 6 2       ; R0 := R0(R1,R2,R3,R4,R5)
 38 [-]: TEST      R0 0         ; if not R0 then PC := 87
 39 [-]: JMP       87           ; PC := 87
 40 [-]: GETGLOBAL R0 K7        ; R0 := 0x89326c93
 41 [-]: SELF      R0 R0 K8     ; R1 := R0; R0 := R0[0x05909209]
 42 [-]: GETGLOBAL R2 K1        ; R2 := 0x4232ec01
 43 [-]: GETUPVAL  R3 U1        ; R3 := U1
 44 [-]: GETGLOBAL R4 K1        ; R4 := 0x4232ec01
 45 [-]: LEN       R4 R4        ; R4 := # R4
 46 [-]: MOD       R3 R3 R4     ; R3 := R3 % R4
 47 [-]: ADD       R3 R3 K9     ; R3 := R3 + 1.000000
 48 [-]: GETTABLE  R2 R2 R3     ; R2 := R2[R3]
 49 [-]: GETUPVAL  R3 U2        ; R3 := U2
 50 [-]: GETGLOBAL R4 K10       ; R4 := 0x00046924
 51 [-]: GETGLOBAL R5 K4        ; R5 := 0xc163f229
 52 [-]: CONST     R6 0         ; R6 := 0.000000
 53 [-]: CONST     R7 360       ; R7 := 360.000000
 54 [-]: CALL      R5 3 2       ; R5 := R5(R6,R7)
 55 [-]: CONST     R6 0         ; R6 := 0.000000
 56 [-]: CONST     R7 0         ; R7 := 0.000000
 57 [-]: CALL      R4 4 2       ; R4 := R4(R5,R6,R7)
 58 [-]: GETUPVAL  R5 U7        ; R5 := U7
 59 [-]: GETUPVAL  R6 U8        ; R6 := U8
 60 [-]: CALL      R0 7 2       ; R0 := R0(R1,R2,R3,R4,R5,R6)
 61 [-]: GETGLOBAL R1 K11       ; R1 := 0x7b998233
 62 [-]: MOVE      R2 R0        ; R2 := R0
 63 [-]: CALL      R1 2 2       ; R1 := R1(R2)
 64 [-]: TEST      R1 1         ; if R1 then PC := 87
 65 [-]: JMP       87           ; PC := 87
 66 [-]: GETGLOBAL R1 K12       ; R1 := 0x33bdd652
 67 [-]: GETTABLE  R1 R1 K13    ; R1 := R1[0x23d5322f]
 68 [-]: GETUPVAL  R2 U9        ; R2 := U9
 69 [-]: MOVE      R3 R0        ; R3 := R0
 70 [-]: CALL      R1 3 1       ; R1(R2,R3)
 71 [-]: GETGLOBAL R1 K14       ; R1 := 0xc8802016
 72 [-]: GETUPVAL  R2 U10       ; R2 := U10
 73 [-]: CALL      R1 2 4       ; R1,R2,R3 := R1(R2)
 74 [-]: JMP       85           ; PC := 85
 75 [-]: SELF      R6 R0 K15    ; R7 := R0; R6 := R0[0x986d2ab8]
 76 [-]: MOVE      R8 R5        ; R8 := R5
 77 [-]: GETUPVAL  R9 U11       ; R9 := U11
 78 [-]: GETTABLE  R9 R9 K16    ; R9 := R9["x"]
 79 [-]: GETUPVAL  R10 U11      ; R10 := U11
 80 [-]: GETTABLE  R10 R10 K17  ; R10 := R10["y"]
 81 [-]: GETUPVAL  R11 U11      ; R11 := U11
 82 [-]: GETTABLE  R11 R11 K18  ; R11 := R11["z"]
 83 [-]: CONST     R12 1        ; R12 := 1.000000
 84 [-]: CALL      R6 7 1       ; R6(R7,R8,R9,R10,R11,R12)
 85 [-]: TFORLOOP  R1 2         ; R4,R5 :=  R1(R2,R3); if R4 ~= nil then begin PC = 75; R3 := R4 end
 86 [-]: JMP       75           ; PC := 75
 87 [-]: GETGLOBAL R6 K11       ; R6 := 0x7b998233
 88 [-]: GETUPVAL  R7 U12       ; R7 := U12
 89 [-]: CALL      R6 2 2       ; R6 := R6(R7)
 90 [-]: TEST      R6 1         ; if R6 then PC := 102
 91 [-]: JMP       102          ; PC := 102
 92 [-]: GETUPVAL  R6 U12       ; R6 := U12
 93 [-]: SELF      R6 R6 K19    ; R7 := R6; R6 := R6[0x66472bf5]
 94 [-]: GETGLOBAL R8 K20       ; R8 := 0x5bced4c4
 95 [-]: GETTABLE  R8 R8 K21    ; R8 := R8[0xb62ecfe0]
 96 [-]: LOADK     R9 K22       ; R9 := 0.020000
 97 [-]: GETUPVAL  R10 U1       ; R10 := U1
 98 [-]: DIV       R10 R10 K0   ; R10 := R10 / 12.000000
 99 [-]: SUB       R10 K9 R10   ; R10 := 1.000000 - R10
100 [-]: CALL      R8 3 0       ; R8,... := R8(R9,R10)
101 [-]: CALL      R6 0 1       ; R6(R7,...)
102 [-]: GETGLOBAL R6 K11       ; R6 := 0x7b998233
103 [-]: GETUPVAL  R7 U13       ; R7 := U13
104 [-]: CALL      R6 2 2       ; R6 := R6(R7)
105 [-]: TEST      R6 1         ; if R6 then PC := 117
106 [-]: JMP       117          ; PC := 117
107 [-]: GETUPVAL  R6 U13       ; R6 := U13
108 [-]: SELF      R6 R6 K19    ; R7 := R6; R6 := R6[0x66472bf5]
109 [-]: GETGLOBAL R8 K20       ; R8 := 0x5bced4c4
110 [-]: GETTABLE  R8 R8 K21    ; R8 := R8[0xb62ecfe0]
111 [-]: CONST     R9 0         ; R9 := 0.000000
112 [-]: GETUPVAL  R10 U1       ; R10 := U1
113 [-]: DIV       R10 R10 K0   ; R10 := R10 / 12.000000
114 [-]: SUB       R10 K9 R10   ; R10 := 1.000000 - R10
115 [-]: CALL      R8 3 0       ; R8,... := R8(R9,R10)
116 [-]: CALL      R6 0 1       ; R6(R7,...)
117 [-]: GETUPVAL  R6 U1        ; R6 := U1
118 [-]: ADD       R6 R6 K9     ; R6 := R6 + 1.000000
119 [-]: SETUPVAL  R6 U1        ; U82 := R1
120 [-]: JMP       141          ; PC := 141
121 [-]: GETGLOBAL R6 K11       ; R6 := 0x7b998233
122 [-]: GETUPVAL  R7 U12       ; R7 := U12
123 [-]: CALL      R6 2 2       ; R6 := R6(R7)
124 [-]: TEST      R6 1         ; if R6 then PC := 130
125 [-]: JMP       130          ; PC := 130
126 [-]: GETUPVAL  R6 U12       ; R6 := U12
127 [-]: SELF      R6 R6 K19    ; R7 := R6; R6 := R6[0x66472bf5]
128 [-]: LOADK     R8 K22       ; R8 := 0.020000
129 [-]: CALL      R6 3 1       ; R6(R7,R8)
130 [-]: GETGLOBAL R6 K11       ; R6 := 0x7b998233
131 [-]: GETUPVAL  R7 U13       ; R7 := U13
132 [-]: CALL      R6 2 2       ; R6 := R6(R7)
133 [-]: TEST      R6 1         ; if R6 then PC := 139
134 [-]: JMP       139          ; PC := 139
135 [-]: GETUPVAL  R6 U13       ; R6 := U13
136 [-]: SELF      R6 R6 K19    ; R7 := R6; R6 := R6[0x66472bf5]
137 [-]: CONST     R8 0         ; R8 := 0.000000
138 [-]: CALL      R6 3 1       ; R6(R7,R8)
139 [-]: LOADKB    R6 0 0       ; R6 := false
140 [-]: SETUPVAL  R6 U0        ; U82 := R0
141 [-]: GETUPVAL  R6 U14       ; R6 := U14
142 [-]: LT        0 K2 R6      ; if 0.000000 >= R6 then PC := 291
143 [-]: JMP       291          ; PC := 291
144 [-]: GETUPVAL  R6 U15       ; R6 := U15
145 [-]: LT        0 K2 R6      ; if 0.000000 >= R6 then PC := 291
146 [-]: JMP       291          ; PC := 291
147 [-]: GETUPVAL  R6 U16       ; R6 := U16
148 [-]: TEST      R6 0         ; if not R6 then PC := 189
149 [-]: JMP       189          ; PC := 189
150 [-]: GETUPVAL  R6 U3        ; R6 := U3
151 [-]: GETGLOBAL R7 K3        ; R7 := 0xa421af95
152 [-]: GETGLOBAL R8 K4        ; R8 := 0xc163f229
153 [-]: GETUPVAL  R9 U4        ; R9 := U4
154 [-]: UNM       R9 R9        ; R9 :=  R9
155 [-]: MUL       R9 R9 K23    ; R9 := R9 * 0.600000
156 [-]: GETUPVAL  R10 U4       ; R10 := U4
157 [-]: MUL       R10 R10 K23  ; R10 := R10 * 0.600000
158 [-]: CALL      R8 3 2       ; R8 := R8(R9,R10)
159 [-]: CONST     R9 0         ; R9 := 0.000000
160 [-]: GETGLOBAL R10 K4       ; R10 := 0xc163f229
161 [-]: GETUPVAL  R11 U4       ; R11 := U4
162 [-]: UNM       R11 R11      ; R11 :=  R11
163 [-]: MUL       R11 R11 K23  ; R11 := R11 * 0.600000
164 [-]: GETUPVAL  R12 U4       ; R12 := U4
165 [-]: MUL       R12 R12 K23  ; R12 := R12 * 0.600000
166 [-]: CALL      R10 3 0      ; R10,... := R10(R11,R12)
167 [-]: CALL      R7 0 2       ; R7 := R7(R8,...)
168 [-]: ADD       R6 R6 R7     ; R6 := R6 + R7
169 [-]: SETUPVAL  R6 U2        ; U82 := R2
170 [-]: GETUPVAL  R6 U5        ; R6 := U5
171 [-]: SELF      R6 R6 K6     ; R7 := R6; R6 := R6[0x40f8914b]
172 [-]: GETUPVAL  R8 U2        ; R8 := U2
173 [-]: CONST     R9 8         ; R9 := 8.000000
174 [-]: CONST     R10 0        ; R10 := 0.000000
175 [-]: GETUPVAL  R11 U6       ; R11 := U6
176 [-]: CALL      R6 6 2       ; R6 := R6(R7,R8,R9,R10,R11)
177 [-]: TEST      R6 0         ; if not R6 then PC := 189
178 [-]: JMP       189          ; PC := 189
179 [-]: LOADKB    R6 0 0       ; R6 := false
180 [-]: SETUPVAL  R6 U16       ; U82 := R16
181 [-]: GETUPVAL  R6 U2        ; R6 := U2
182 [-]: GETGLOBAL R7 K3        ; R7 := 0xa421af95
183 [-]: CONST     R8 0         ; R8 := 0.000000
184 [-]: CONST     R9 0         ; R9 := 0.500000
185 [-]: CONST     R10 0        ; R10 := 0.000000
186 [-]: CALL      R7 4 2       ; R7 := R7(R8,R9,R10)
187 [-]: ADD       R6 R6 R7     ; R6 := R6 + R7
188 [-]: SETUPVAL  R6 U17       ; U82 := R17
189 [-]: GETUPVAL  R6 U17       ; R6 := U17
190 [-]: GETGLOBAL R7 K3        ; R7 := 0xa421af95
191 [-]: GETGLOBAL R8 K4        ; R8 := 0xc163f229
192 [-]: GETUPVAL  R9 U4        ; R9 := U4
193 [-]: UNM       R9 R9        ; R9 :=  R9
194 [-]: MUL       R9 R9 K24    ; R9 := R9 * 2.000000
195 [-]: GETUPVAL  R10 U4       ; R10 := U4
196 [-]: MUL       R10 R10 K24  ; R10 := R10 * 2.000000
197 [-]: CALL      R8 3 2       ; R8 := R8(R9,R10)
198 [-]: CONST     R9 12        ; R9 := 12.000000
199 [-]: GETGLOBAL R10 K4       ; R10 := 0xc163f229
200 [-]: GETUPVAL  R11 U4       ; R11 := U4
201 [-]: UNM       R11 R11      ; R11 :=  R11
202 [-]: MUL       R11 R11 K24  ; R11 := R11 * 2.000000
203 [-]: GETUPVAL  R12 U4       ; R12 := U4
204 [-]: MUL       R12 R12 K24  ; R12 := R12 * 2.000000
205 [-]: CALL      R10 3 0      ; R10,... := R10(R11,R12)
206 [-]: CALL      R7 0 2       ; R7 := R7(R8,...)
207 [-]: ADD       R6 R6 R7     ; R6 := R6 + R7
208 [-]: SETUPVAL  R6 U18       ; U82 := R18
209 [-]: GETUPVAL  R6 U16       ; R6 := U16
210 [-]: TEST      R6 1         ; if R6 then PC := 288
211 [-]: JMP       288          ; PC := 288
212 [-]: GETGLOBAL R6 K3        ; R6 := 0xa421af95
213 [-]: CALL      R6 1 2       ; R6 := R6()
214 [-]: GETGLOBAL R7 K7        ; R7 := 0x89326c93
215 [-]: SELF      R7 R7 K25    ; R8 := R7; R7 := R7[0x722cd32c]
216 [-]: GETUPVAL  R9 U17       ; R9 := U17
217 [-]: GETUPVAL  R10 U18      ; R10 := U18
218 [-]: GETUPVAL  R11 U19      ; R11 := U19
219 [-]: LOADNIL   R12 R12      ; R12 := nil
220 [-]: MOVE      R13 R6       ; R13 := R6
221 [-]: CALL      R7 7 2       ; R7 := R7(R8,R9,R10,R11,R12,R13)
222 [-]: TEST      R7 0         ; if not R7 then PC := 288
223 [-]: JMP       288          ; PC := 288
224 [-]: GETGLOBAL R7 K26       ; R7 := 0x20b7f774
225 [-]: GETUPVAL  R8 U2        ; R8 := U2
226 [-]: MOVE      R9 R6        ; R9 := R6
227 [-]: CALL      R7 3 2       ; R7 := R7(R8,R9)
228 [-]: GETGLOBAL R8 K7        ; R8 := 0x89326c93
229 [-]: SELF      R8 R8 K8     ; R9 := R8; R8 := R8[0x05909209]
230 [-]: GETGLOBAL R10 K27      ; R10 := 0xffde2982
231 [-]: GETUPVAL  R11 U2       ; R11 := U2
232 [-]: MOVE      R12 R7       ; R12 := R7
233 [-]: GETUPVAL  R13 U7       ; R13 := U7
234 [-]: GETUPVAL  R14 U8       ; R14 := U8
235 [-]: CALL      R8 7 2       ; R8 := R8(R9,R10,R11,R12,R13,R14)
236 [-]: GETGLOBAL R9 K11       ; R9 := 0x7b998233
237 [-]: MOVE      R10 R8       ; R10 := R8
238 [-]: CALL      R9 2 2       ; R9 := R9(R10)
239 [-]: TEST      R9 1         ; if R9 then PC := 283
240 [-]: JMP       283          ; PC := 283
241 [-]: SELF      R9 R8 K28    ; R10 := R8; R9 := R8[0x2d9ba74f]
242 [-]: GETGLOBAL R11 K29      ; R11 := 0xae2294fa
243 [-]: GETUPVAL  R12 U2       ; R12 := U2
244 [-]: SUB       R12 R6 R12   ; R12 := R6 - R12
245 [-]: CALL      R11 2 2      ; R11 := R11(R12)
246 [-]: DIV       R11 R11 K30  ; R11 := R11 / 10.000000
247 [-]: CALL      R9 3 1       ; R9(R10,R11)
248 [-]: SELF      R9 R8 K15    ; R10 := R8; R9 := R8[0x986d2ab8]
249 [-]: GETUPVAL  R11 U20      ; R11 := U20
250 [-]: GETUPVAL  R12 U11      ; R12 := U11
251 [-]: GETTABLE  R12 R12 K16  ; R12 := R12["x"]
252 [-]: GETUPVAL  R13 U11      ; R13 := U11
253 [-]: GETTABLE  R13 R13 K17  ; R13 := R13["y"]
254 [-]: GETUPVAL  R14 U11      ; R14 := U11
255 [-]: GETTABLE  R14 R14 K18  ; R14 := R14["z"]
256 [-]: CONST     R15 1        ; R15 := 1.000000
257 [-]: CALL      R9 7 1       ; R9(R10,R11,R12,R13,R14,R15)
258 [-]: SELF      R9 R8 K15    ; R10 := R8; R9 := R8[0x986d2ab8]
259 [-]: GETUPVAL  R11 U21      ; R11 := U21
260 [-]: GETUPVAL  R12 U11      ; R12 := U11
261 [-]: GETTABLE  R12 R12 K16  ; R12 := R12["x"]
262 [-]: GETUPVAL  R13 U11      ; R13 := U11
263 [-]: GETTABLE  R13 R13 K17  ; R13 := R13["y"]
264 [-]: GETUPVAL  R14 U11      ; R14 := U11
265 [-]: GETTABLE  R14 R14 K18  ; R14 := R14["z"]
266 [-]: CONST     R15 1        ; R15 := 1.000000
267 [-]: CALL      R9 7 1       ; R9(R10,R11,R12,R13,R14,R15)
268 [-]: SELF      R9 R8 K15    ; R10 := R8; R9 := R8[0x986d2ab8]
269 [-]: GETUPVAL  R11 U22      ; R11 := U22
270 [-]: GETUPVAL  R12 U11      ; R12 := U11
271 [-]: GETTABLE  R12 R12 K16  ; R12 := R12["x"]
272 [-]: GETUPVAL  R13 U11      ; R13 := U11
273 [-]: GETTABLE  R13 R13 K17  ; R13 := R13["y"]
274 [-]: GETUPVAL  R14 U11      ; R14 := U11
275 [-]: GETTABLE  R14 R14 K18  ; R14 := R14["z"]
276 [-]: CONST     R15 1        ; R15 := 1.000000
277 [-]: CALL      R9 7 1       ; R9(R10,R11,R12,R13,R14,R15)
278 [-]: GETGLOBAL R9 K12       ; R9 := 0x33bdd652
279 [-]: GETTABLE  R9 R9 K13    ; R9 := R9[0x23d5322f]
280 [-]: GETUPVAL  R10 U9       ; R10 := U9
281 [-]: MOVE      R11 R8       ; R11 := R8
282 [-]: CALL      R9 3 1       ; R9(R10,R11)
283 [-]: LOADKB    R9 1 0       ; R9 := true
284 [-]: SETUPVAL  R9 U16       ; U82 := R16
285 [-]: GETUPVAL  R9 U14       ; R9 := U14
286 [-]: SUB       R9 R9 K9     ; R9 := R9 - 1.000000
287 [-]: SETUPVAL  R9 U14       ; U82 := R14
288 [-]: GETUPVAL  R9 U15       ; R9 := U15
289 [-]: SUB       R9 R9 K9     ; R9 := R9 - 1.000000
290 [-]: SETUPVAL  R9 U15       ; U82 := R15
291 [-]: RETURN    R0 1         ; return 


; Function #15.2:
;
; Name:            
; Defined at line: 816
; #Upvalues:       3
; #Parameters:     0
; Is_vararg:       0
; Max Stack Size:  9

  1 [-]: CONST     R0 0         ; R0 := 0.000000
  2 [-]: LT        0 R0 K0      ; if R0 >= 1.000000 then PC := 46
  3 [-]: JMP       46           ; PC := 46
  4 [-]: GETGLOBAL R1 K1        ; R1 := 0x7b998233
  5 [-]: GETUPVAL  R2 U0        ; R2 := U0
  6 [-]: CALL      R1 2 2       ; R1 := R1(R2)
  7 [-]: TEST      R1 1         ; if R1 then PC := 14
  8 [-]: JMP       14           ; PC := 14
  9 [-]: GETUPVAL  R1 U0        ; R1 := U0
 10 [-]: SELF      R1 R1 K2     ; R2 := R1; R1 := R1[0x66472bf5]
 11 [-]: MUL       R3 R0 K3     ; R3 := R0 * 0.980000
 12 [-]: ADD       R3 K4 R3     ; R3 := 0.020000 + R3
 13 [-]: CALL      R1 3 1       ; R1(R2,R3)
 14 [-]: GETGLOBAL R1 K1        ; R1 := 0x7b998233
 15 [-]: GETUPVAL  R2 U1        ; R2 := U1
 16 [-]: CALL      R1 2 2       ; R1 := R1(R2)
 17 [-]: TEST      R1 1         ; if R1 then PC := 23
 18 [-]: JMP       23           ; PC := 23
 19 [-]: GETUPVAL  R1 U1        ; R1 := U1
 20 [-]: SELF      R1 R1 K2     ; R2 := R1; R1 := R1[0x66472bf5]
 21 [-]: MOVE      R3 R0        ; R3 := R0
 22 [-]: CALL      R1 3 1       ; R1(R2,R3)
 23 [-]: CONST     R1 1         ; R1 := 1.000000
 24 [-]: GETUPVAL  R2 U2        ; R2 := U2
 25 [-]: LEN       R2 R2        ; R2 := # R2
 26 [-]: CONST     R3 1         ; R3 := 1.000000
 27 [-]: FORPREP   R1 38        ; R1 -= R3; PC := 38
 28 [-]: GETUPVAL  R5 U2        ; R5 := U2
 29 [-]: GETTABLE  R5 R5 R4     ; R5 := R5[R4]
 30 [-]: GETGLOBAL R6 K1        ; R6 := 0x7b998233
 31 [-]: MOVE      R7 R5        ; R7 := R5
 32 [-]: CALL      R6 2 2       ; R6 := R6(R7)
 33 [-]: TEST      R6 1         ; if R6 then PC := 38
 34 [-]: JMP       38           ; PC := 38
 35 [-]: SELF      R6 R5 K2     ; R7 := R5; R6 := R5[0x66472bf5]
 36 [-]: MOVE      R8 R0        ; R8 := R0
 37 [-]: CALL      R6 3 1       ; R6(R7,R8)
 38 [-]: FORLOOP   R1 28        ; R1 += R3; if R1 <= R2 then begin PC := 28; R4 := R1 end
 39 [-]: GETGLOBAL R6 K5        ; R6 := 0xcbd666e1
 40 [-]: CONST     R7 0         ; R7 := 0.000000
 41 [-]: CALL      R6 2 1       ; R6(R7)
 42 [-]: GETGLOBAL R6 K6        ; R6 := 0x67652851
 43 [-]: CALL      R6 1 2       ; R6 := R6()
 44 [-]: ADD       R0 R0 R6     ; R0 := R0 + R6
 45 [-]: JMP       2            ; PC := 2
 46 [-]: RETURN    R0 1         ; return 


; Function #16:
;
; Name:            
; Defined at line: 841
; #Upvalues:       6
; #Parameters:     1
; Is_vararg:       0
; Max Stack Size:  19

  1 [-]: SELF      R1 R0 K0     ; R2 := R0; R1 := R0[0xed324116]
  2 [-]: CALL      R1 2 2       ; R1 := R1(R2)
  3 [-]: SELF      R2 R1 K1     ; R3 := R1; R2 := R1[0x5163741e]
  4 [-]: CALL      R2 2 2       ; R2 := R2(R3)
  5 [-]: SELF      R3 R2 K2     ; R4 := R2; R3 := R2[0x388577d5]
  6 [-]: CALL      R3 2 2       ; R3 := R3(R4)
  7 [-]: GETGLOBAL R4 K3        ; R4 := 0x6687f6e0
  8 [-]: SELF      R4 R4 K4     ; R5 := R4; R4 := R4[0xcde10c4a]
  9 [-]: CALL      R4 2 2       ; R4 := R4(R5)
 10 [-]: GETGLOBAL R5 K5        ; R5 := 0x89326c93
 11 [-]: SELF      R5 R5 K6     ; R6 := R5; R5 := R5[0x18d05d30]
 12 [-]: CALL      R5 2 2       ; R5 := R5(R6)
 13 [-]: GETGLOBAL R6 K7        ; R6 := _T
 14 [-]: GETTABLE  R6 R6 K8     ; R6 := R6["infestPods"]
 15 [-]: GETTABLE  R6 R6 R3     ; R6 := R6[R3]
 16 [-]: GETTABLE  R6 R6 K9     ; R6 := R6["instance"]
 17 [-]: GETGLOBAL R7 K7        ; R7 := _T
 18 [-]: GETTABLE  R7 R7 K8     ; R7 := R7["infestPods"]
 19 [-]: GETTABLE  R7 R7 R3     ; R7 := R7[R3]
 20 [-]: GETTABLE  R7 R7 K10    ; R7 := R7["pos"]
 21 [-]: GETGLOBAL R8 K7        ; R8 := _T
 22 [-]: GETTABLE  R8 R8 K8     ; R8 := R8["infestPods"]
 23 [-]: GETTABLE  R8 R8 R3     ; R8 := R8[R3]
 24 [-]: GETTABLE  R8 R8 K11    ; R8 := R8["radius"]
 25 [-]: GETGLOBAL R9 K7        ; R9 := _T
 26 [-]: GETTABLE  R9 R9 K8     ; R9 := R9["infestPods"]
 27 [-]: GETTABLE  R9 R9 R3     ; R9 := R9[R3]
 28 [-]: GETTABLE  R9 R9 K12    ; R9 := R9["firstPos"]
 29 [-]: GETUPVAL  R10 U0       ; R10 := U0
 30 [-]: GETTABLE  R10 R10 K13  ; R10 := R10[0xf43af54f]
 31 [-]: MOVE      R11 R1       ; R11 := R1
 32 [-]: GETGLOBAL R12 K3       ; R12 := 0x6687f6e0
 33 [-]: NEWTABLE  R13 0 2      ; R13 := {}
 34 [-]: GETUPVAL  R14 U1       ; R14 := U1
 35 [-]: SETTABLE  R13 K14 R14  ; R13["explosionDamage"] := R14
 36 [-]: GETUPVAL  R14 U2       ; R14 := U2
 37 [-]: SETTABLE  R13 K15 R14  ; R13["explosionRadius"] := R14
 38 [-]: CALL      R10 4 1      ; R10(R11,R12,R13)
 39 [-]: GETUPVAL  R10 U3       ; R10 := U3
 40 [-]: MOVE      R11 R1       ; R11 := R1
 41 [-]: MOVE      R12 R2       ; R12 := R2
 42 [-]: SELF      R13 R0 K16   ; R14 := R0; R13 := R0[0xd1586535]
 43 [-]: CALL      R13 2 2      ; R13 := R13(R14)
 44 [-]: MOVE      R14 R9       ; R14 := R9
 45 [-]: CALL      R10 5 2      ; R10 := R10(R11,R12,R13,R14)
 46 [-]: GETUPVAL  R11 U4       ; R11 := U4
 47 [-]: MOVE      R12 R1       ; R12 := R1
 48 [-]: MOVE      R13 R2       ; R13 := R2
 49 [-]: MOVE      R14 R7       ; R14 := R7
 50 [-]: MOVE      R15 R8       ; R15 := R8
 51 [-]: CALL      R11 5 2      ; R11 := R11(R12,R13,R14,R15)
 52 [-]: GETUPVAL  R12 U5       ; R12 := U5
 53 [-]: MOVE      R13 R1       ; R13 := R1
 54 [-]: MOVE      R14 R0       ; R14 := R0
 55 [-]: MOVE      R15 R8       ; R15 := R8
 56 [-]: CALL      R12 4 2      ; R12 := R12(R13,R14,R15)
 57 [-]: GETGLOBAL R13 K17      ; R13 := 0x7b998233
 58 [-]: MOVE      R14 R2       ; R14 := R2
 59 [-]: CALL      R13 2 2      ; R13 := R13(R14)
 60 [-]: TEST      R13 1        ; if R13 then PC := 125
 61 [-]: JMP       125          ; PC := 125
 62 [-]: SELF      R13 R2 K18   ; R14 := R2; R13 := R2[0x2047cfe7]
 63 [-]: CALL      R13 2 2      ; R13 := R13(R14)
 64 [-]: TEST      R13 1        ; if R13 then PC := 125
 65 [-]: JMP       125          ; PC := 125
 66 [-]: GETGLOBAL R13 K7       ; R13 := _T
 67 [-]: GETTABLE  R13 R13 K8   ; R13 := R13["infestPods"]
 68 [-]: TEST      R13 0        ; if not R13 then PC := 125
 69 [-]: JMP       125          ; PC := 125
 70 [-]: GETGLOBAL R13 K7       ; R13 := _T
 71 [-]: GETTABLE  R13 R13 K8   ; R13 := R13["infestPods"]
 72 [-]: GETTABLE  R13 R13 R3   ; R13 := R13[R3]
 73 [-]: TEST      R13 0        ; if not R13 then PC := 125
 74 [-]: JMP       125          ; PC := 125
 75 [-]: GETGLOBAL R13 K7       ; R13 := _T
 76 [-]: GETTABLE  R13 R13 K8   ; R13 := R13["infestPods"]
 77 [-]: GETTABLE  R13 R13 R3   ; R13 := R13[R3]
 78 [-]: GETTABLE  R13 R13 K9   ; R13 := R13["instance"]
 79 [-]: EQ        0 R13 R6     ; if R13 ~= R6 then PC := 125
 80 [-]: JMP       125          ; PC := 125
 81 [-]: GETGLOBAL R13 K7       ; R13 := _T
 82 [-]: GETTABLE  R13 R13 K8   ; R13 := R13["infestPods"]
 83 [-]: GETTABLE  R13 R13 R3   ; R13 := R13[R3]
 84 [-]: GETTABLE  R13 R13 K19  ; R13 := R13["duration"]
 85 [-]: LT        0 K20 R13    ; if 0.000000 >= R13 then PC := 125
 86 [-]: JMP       125          ; PC := 125
 87 [-]: TEST      R5 0         ; if not R5 then PC := 108
 88 [-]: JMP       108          ; PC := 108
 89 [-]: EQ        1 R10 K21    ; if R10 == nil then PC := 95
 90 [-]: JMP       95           ; PC := 95
 91 [-]: GETTABLE  R13 R10 K22  ; R13 := R10[0xfaa69527]
 92 [-]: CALL      R13 1 2      ; R13 := R13()
 93 [-]: LE        0 R13 K20    ; if R13 > 0.000000 then PC := 106
 94 [-]: JMP       106          ; PC := 106
 95 [-]: SELF      R13 R1 K23   ; R14 := R1; R13 := R1[0x3cc932f9]
 96 [-]: GETGLOBAL R15 K3       ; R15 := 0x6687f6e0
 97 [-]: GETGLOBAL R16 K24      ; R16 := 0x0469f296
 98 [-]: LOADK     R17 K25      ; R17 := "PodsDestroyed"
 99 [-]: CALL      R16 2 2      ; R16 := R16(R17)
100 [-]: GETGLOBAL R17 K26      ; R17 := 0x6c97a788
101 [-]: GETTABLE  R17 R17 K27  ; R17 := R17[0x733fc736]
102 [-]: LOADKB    R18 0 0      ; R18 := false
103 [-]: CALL      R17 2 0      ; R17,... := R17(R18)
104 [-]: CALL      R13 0 1      ; R13(R14,...)
105 [-]: JMP       125          ; PC := 125
106 [-]: GETTABLE  R13 R11 K22  ; R13 := R11[0xfaa69527]
107 [-]: CALL      R13 1 1      ; R13()
108 [-]: GETTABLE  R13 R12 K22  ; R13 := R12[0xfaa69527]
109 [-]: CALL      R13 1 1      ; R13()
110 [-]: GETGLOBAL R13 K7       ; R13 := _T
111 [-]: GETTABLE  R13 R13 K8   ; R13 := R13["infestPods"]
112 [-]: GETTABLE  R13 R13 R3   ; R13 := R13[R3]
113 [-]: GETGLOBAL R14 K7       ; R14 := _T
114 [-]: GETTABLE  R14 R14 K8   ; R14 := R14["infestPods"]
115 [-]: GETTABLE  R14 R14 R3   ; R14 := R14[R3]
116 [-]: GETTABLE  R14 R14 K19  ; R14 := R14["duration"]
117 [-]: GETGLOBAL R15 K28      ; R15 := 0x67652851
118 [-]: CALL      R15 1 2      ; R15 := R15()
119 [-]: SUB       R14 R14 R15  ; R14 := R14 - R15
120 [-]: SETTABLE  R13 K19 R14  ; R13["duration"] := R14
121 [-]: GETGLOBAL R13 K29      ; R13 := 0xcbd666e1
122 [-]: CONST     R14 0        ; R14 := 0.000000
123 [-]: CALL      R13 2 1      ; R13(R14)
124 [-]: JMP       57           ; PC := 57
125 [-]: GETGLOBAL R13 K7       ; R13 := _T
126 [-]: GETTABLE  R13 R13 K30  ; R13 := R13["AddAbilityTimer"]
127 [-]: EQ        1 R13 K21    ; if R13 == nil then PC := 142
128 [-]: JMP       142          ; PC := 142
129 [-]: GETGLOBAL R13 K7       ; R13 := _T
130 [-]: GETTABLE  R13 R13 K8   ; R13 := R13["infestPods"]
131 [-]: GETTABLE  R13 R13 R3   ; R13 := R13[R3]
132 [-]: GETTABLE  R13 R13 K9   ; R13 := R13["instance"]
133 [-]: EQ        0 R13 R6     ; if R13 ~= R6 then PC := 142
134 [-]: JMP       142          ; PC := 142
135 [-]: GETGLOBAL R13 K7       ; R13 := _T
136 [-]: GETTABLE  R13 R13 K31  ; R13 := R13[0xcc4ac7a6]
137 [-]: MOVE      R14 R4       ; R14 := R4
138 [-]: MOVE      R15 R2       ; R15 := R2
139 [-]: CONST     R16 0        ; R16 := 0.000000
140 [-]: CONST     R17 0        ; R17 := 0.000000
141 [-]: CALL      R13 5 1      ; R13(R14,R15,R16,R17)
142 [-]: EQ        1 R10 K21    ; if R10 == nil then PC := 146
143 [-]: JMP       146          ; PC := 146
144 [-]: GETTABLE  R13 R10 K32  ; R13 := R10[0x1cb2f429]
145 [-]: CALL      R13 1 1      ; R13()
146 [-]: EQ        1 R11 K21    ; if R11 == nil then PC := 150
147 [-]: JMP       150          ; PC := 150
148 [-]: GETTABLE  R13 R11 K32  ; R13 := R11[0x1cb2f429]
149 [-]: CALL      R13 1 1      ; R13()
150 [-]: GETTABLE  R13 R12 K32  ; R13 := R12[0x1cb2f429]
151 [-]: CALL      R13 1 1      ; R13()
152 [-]: GETGLOBAL R13 K17      ; R13 := 0x7b998233
153 [-]: GETGLOBAL R14 K7       ; R14 := _T
154 [-]: GETTABLE  R14 R14 K8   ; R14 := R14["infestPods"]
155 [-]: CALL      R13 2 2      ; R13 := R13(R14)
156 [-]: TEST      R13 1        ; if R13 then PC := 193
157 [-]: JMP       193          ; PC := 193
158 [-]: GETGLOBAL R13 K17      ; R13 := 0x7b998233
159 [-]: GETGLOBAL R14 K7       ; R14 := _T
160 [-]: GETTABLE  R14 R14 K8   ; R14 := R14["infestPods"]
161 [-]: GETTABLE  R14 R14 R3   ; R14 := R14[R3]
162 [-]: CALL      R13 2 2      ; R13 := R13(R14)
163 [-]: TEST      R13 1        ; if R13 then PC := 193
164 [-]: JMP       193          ; PC := 193
165 [-]: GETGLOBAL R13 K7       ; R13 := _T
166 [-]: GETTABLE  R13 R13 K8   ; R13 := R13["infestPods"]
167 [-]: GETTABLE  R13 R13 R3   ; R13 := R13[R3]
168 [-]: GETTABLE  R13 R13 K9   ; R13 := R13["instance"]
169 [-]: EQ        1 R13 K21    ; if R13 == nil then PC := 177
170 [-]: JMP       177          ; PC := 177
171 [-]: GETGLOBAL R13 K7       ; R13 := _T
172 [-]: GETTABLE  R13 R13 K8   ; R13 := R13["infestPods"]
173 [-]: GETTABLE  R13 R13 R3   ; R13 := R13[R3]
174 [-]: GETTABLE  R13 R13 K9   ; R13 := R13["instance"]
175 [-]: EQ        0 R13 R6     ; if R13 ~= R6 then PC := 193
176 [-]: JMP       193          ; PC := 193
177 [-]: GETGLOBAL R13 K7       ; R13 := _T
178 [-]: GETTABLE  R13 R13 K8   ; R13 := R13["infestPods"]
179 [-]: SETTABLE  R13 R3 K21   ; R13[R3] := nil
180 [-]: GETGLOBAL R13 K33      ; R13 := 0x4ec73e73
181 [-]: GETGLOBAL R14 K7       ; R14 := _T
182 [-]: GETTABLE  R14 R14 K8   ; R14 := R14["infestPods"]
183 [-]: CALL      R13 2 2      ; R13 := R13(R14)
184 [-]: EQ        0 R13 K21    ; if R13 ~= nil then PC := 188
185 [-]: JMP       188          ; PC := 188
186 [-]: GETGLOBAL R13 K7       ; R13 := _T
187 [-]: SETTABLE  R13 K8 K21   ; R13["infestPods"] := nil
188 [-]: GETUPVAL  R13 U0       ; R13 := U0
189 [-]: GETTABLE  R13 R13 K34  ; R13 := R13[0x68d66e6e]
190 [-]: MOVE      R14 R1       ; R14 := R1
191 [-]: GETGLOBAL R15 K3       ; R15 := 0x6687f6e0
192 [-]: CALL      R13 3 1      ; R13(R14,R15)
193 [-]: SELF      R13 R0 K35   ; R14 := R0; R13 := R0[0xa2880940]
194 [-]: CALL      R13 2 1      ; R13(R14)
195 [-]: RETURN    R0 1         ; return 


; Function #17:
;
; Name:            
; Defined at line: 910
; #Upvalues:       16
; #Parameters:     4
; Is_vararg:       0
; Max Stack Size:  26

  1 [-]: GETUPVAL  R4 U0        ; R4 := U0
  2 [-]: MOVE      R5 R3        ; R5 := R3
  3 [-]: CALL      R4 2 1       ; R4(R5)
  4 [-]: GETUPVAL  R4 U6        ; R4 := U6
  5 [-]: MOVE      R5 R1        ; R5 := R1
  6 [-]: CALL      R4 2 6       ; R4,R5,R6,R7,R8 := R4(R5)
  7 [-]: SETUPVAL  R8 U5        ; U82 := R5
  8 [-]: SETUPVAL  R7 U4        ; U82 := R4
  9 [-]: SETUPVAL  R6 U3        ; U82 := R3
 10 [-]: SETUPVAL  R5 U2        ; U82 := R2
 11 [-]: SETUPVAL  R4 U1        ; U82 := R1
 12 [-]: SELF      R4 R0 K0     ; R5 := R0; R4 := R0[0x5063edc3]
 13 [-]: GETUPVAL  R6 U7        ; R6 := U7
 14 [-]: CALL      R4 3 2       ; R4 := R4(R5,R6)
 15 [-]: SELF      R5 R0 K1     ; R6 := R0; R5 := R0[0x75ecaf0b]
 16 [-]: GETUPVAL  R7 U7        ; R7 := U7
 17 [-]: CALL      R5 3 2       ; R5 := R5(R6,R7)
 18 [-]: LT        0 K2 R4      ; if 0.000000 >= R4 then PC := 31
 19 [-]: JMP       31           ; PC := 31
 20 [-]: EQ        0 R5 K4      ; if R5 ~= 1.000000 then PC := 31
 21 [-]: JMP       31           ; PC := 31
 22 [-]: GETUPVAL  R6 U8        ; R6 := U8
 23 [-]: MOVE      R7 R4        ; R7 := R4
 24 [-]: MOVE      R8 R5        ; R8 := R5
 25 [-]: CALL      R6 3 1       ; R6(R7,R8)
 26 [-]: GETUPVAL  R6 U10       ; R6 := U10
 27 [-]: MOVE      R7 R1        ; R7 := R1
 28 [-]: MOVE      R8 R5        ; R8 := R5
 29 [-]: CALL      R6 3 2       ; R6 := R6(R7,R8)
 30 [-]: SETUPVAL  R6 U9        ; U82 := R9
 31 [-]: GETGLOBAL R6 K5        ; R6 := _T
 32 [-]: GETTABLE  R6 R6 K6     ; R6 := R6["INFESTED_AddStacks"]
 33 [-]: EQ        1 R6 K7      ; if R6 == nil then PC := 45
 34 [-]: JMP       45           ; PC := 45
 35 [-]: SELF      R6 R1 K8     ; R7 := R1; R6 := R1[0x35844cf2]
 36 [-]: CALL      R6 2 2       ; R6 := R6(R7)
 37 [-]: TEST      R6 0         ; if not R6 then PC := 45
 38 [-]: JMP       45           ; PC := 45
 39 [-]: GETGLOBAL R6 K5        ; R6 := _T
 40 [-]: GETTABLE  R6 R6 K9     ; R6 := R6[0x67779857]
 41 [-]: MOVE      R7 R0        ; R7 := R0
 42 [-]: GETUPVAL  R8 U11       ; R8 := U11
 43 [-]: UNM       R8 R8        ; R8 :=  R8
 44 [-]: CALL      R6 3 1       ; R6(R7,R8)
 45 [-]: GETGLOBAL R6 K5        ; R6 := _T
 46 [-]: GETTABLE  R6 R6 K10    ; R6 := R6["INFESTED_GetStacks"]
 47 [-]: EQ        1 R6 K7      ; if R6 == nil then PC := 59
 48 [-]: JMP       59           ; PC := 59
 49 [-]: GETUPVAL  R6 U2        ; R6 := U2
 50 [-]: SELF      R6 R6 K11    ; R7 := R6; R6 := R6[0x133d78e8]
 51 [-]: CONST     R8 3         ; R8 := 3.000000
 52 [-]: GETUPVAL  R9 U12       ; R9 := U12
 53 [-]: GETGLOBAL R10 K5       ; R10 := _T
 54 [-]: GETTABLE  R10 R10 K13  ; R10 := R10[0x85ed3714]
 55 [-]: MOVE      R11 R0       ; R11 := R0
 56 [-]: CALL      R10 2 2      ; R10 := R10(R11)
 57 [-]: MUL       R9 R9 R10    ; R9 := R9 * R10
 58 [-]: CALL      R6 4 1       ; R6(R7,R8,R9)
 59 [-]: SELF      R6 R1 K14    ; R7 := R1; R6 := R1[0x47901f07]
 60 [-]: GETGLOBAL R8 K15       ; R8 := 0x17c91a14
 61 [-]: GETGLOBAL R9 K16       ; R9 := 0x0469f296
 62 [-]: LOADK     R10 K17      ; R10 := "GAME_R1_WEAPON1"
 63 [-]: CALL      R9 2 2       ; R9 := R9(R10)
 64 [-]: GETGLOBAL R10 K18      ; R10 := ZERO_VECTOR
 65 [-]: GETGLOBAL R11 K19      ; R11 := ZERO_ROTATION
 66 [-]: MOVE      R12 R0       ; R12 := R0
 67 [-]: CALL      R6 7 1       ; R6(R7,R8,R9,R10,R11,R12)
 68 [-]: SELF      R6 R0 K20    ; R7 := R0; R6 := R0[0x68b88e58]
 69 [-]: LOADKB    R8 1 0       ; R8 := true
 70 [-]: CALL      R6 3 1       ; R6(R7,R8)
 71 [-]: GETUPVAL  R6 U13       ; R6 := U13
 72 [-]: GETTABLE  R6 R6 K21    ; R6 := R6[0xb443c7bd]
 73 [-]: MOVE      R7 R1        ; R7 := R1
 74 [-]: GETGLOBAL R8 K22       ; R8 := 0x99cb4b90
 75 [-]: GETGLOBAL R9 K23       ; R9 := 0x0ed8b456
 76 [-]: LOADK     R10 K24      ; R10 := "InfestCast"
 77 [-]: CALL      R6 5 2       ; R6 := R6(R7,R8,R9,R10)
 78 [-]: TEST      R6 1         ; if R6 then PC := 81
 79 [-]: JMP       81           ; PC := 81
 80 [-]: RETURN    R0 1         ; return 
 81 [-]: SELF      R6 R1 K25    ; R7 := R1; R6 := R1[0xd1586535]
 82 [-]: CALL      R6 2 2       ; R6 := R6(R7)
 83 [-]: CONST     R7 4         ; R7 := 4.000000
 84 [-]: GETGLOBAL R8 K26       ; R8 := 0x5bced4c4
 85 [-]: GETTABLE  R8 R8 K27    ; R8 := R8[0xdde5c6a1]
 86 [-]: SELF      R9 R1 K28    ; R10 := R1; R9 := R1[0xeea7f8c4]
 87 [-]: CALL      R9 2 2       ; R9 := R9(R10)
 88 [-]: GETTABLE  R9 R9 K29    ; R9 := R9["heading"]
 89 [-]: GETGLOBAL R10 K30      ; R10 := 0xc163f229
 90 [-]: CONST     R11 -30      ; R11 := -30.000000
 91 [-]: CONST     R12 30       ; R12 := 30.000000
 92 [-]: CALL      R10 3 2      ; R10 := R10(R11,R12)
 93 [-]: ADD       R9 R9 R10    ; R9 := R9 + R10
 94 [-]: CALL      R8 2 2       ; R8 := R8(R9)
 95 [-]: DIV       R9 K31 R7    ; R9 := 6.283185 / R7
 96 [-]: SELF      R10 R1 K25   ; R11 := R1; R10 := R1[0xd1586535]
 97 [-]: CALL      R10 2 2      ; R10 := R10(R11)
 98 [-]: GETGLOBAL R11 K32      ; R11 := 0xa421af95
 99 [-]: CALL      R11 1 2      ; R11 := R11()
100 [-]: GETGLOBAL R12 K33      ; R12 := 0x89326c93
101 [-]: SELF      R12 R12 K34  ; R13 := R12; R12 := R12[0x29ef273d]
102 [-]: CALL      R12 2 2      ; R12 := R12(R13)
103 [-]: CONST     R13 1        ; R13 := 1.000000
104 [-]: MOVE      R14 R7       ; R14 := R7
105 [-]: CONST     R15 1        ; R15 := 1.000000
106 [-]: FORPREP   R13 139      ; R13 -= R15; PC := 139
107 [-]: GETUPVAL  R17 U14      ; R17 := U14
108 [-]: SELF      R17 R17 K35  ; R18 := R17; R17 := R17[0x96f7a165]
109 [-]: CALL      R17 2 2      ; R17 := R17(R18)
110 [-]: GETTABLE  R18 R10 K36  ; R18 := R10["x"]
111 [-]: GETGLOBAL R19 K26      ; R19 := 0x5bced4c4
112 [-]: GETTABLE  R19 R19 K37  ; R19 := R19[0x3eda26fc]
113 [-]: MOVE      R20 R8       ; R20 := R8
114 [-]: CALL      R19 2 2      ; R19 := R19(R20)
115 [-]: MUL       R19 R17 R19  ; R19 := R17 * R19
116 [-]: ADD       R18 R18 R19  ; R18 := R18 + R19
117 [-]: SETTABLE  R11 K36 R18  ; R11["x"] := R18
118 [-]: GETTABLE  R18 R10 K38  ; R18 := R10["y"]
119 [-]: SETTABLE  R11 K38 R18  ; R11["y"] := R18
120 [-]: GETTABLE  R18 R10 K39  ; R18 := R10["z"]
121 [-]: GETGLOBAL R19 K26      ; R19 := 0x5bced4c4
122 [-]: GETTABLE  R19 R19 K40  ; R19 := R19[0x00fa6bf1]
123 [-]: MOVE      R20 R8       ; R20 := R8
124 [-]: CALL      R19 2 2      ; R19 := R19(R20)
125 [-]: MUL       R19 R17 R19  ; R19 := R17 * R19
126 [-]: ADD       R18 R18 R19  ; R18 := R18 + R19
127 [-]: SETTABLE  R11 K39 R18  ; R11["z"] := R18
128 [-]: SELF      R18 R12 K41  ; R19 := R12; R18 := R12[0x40f8914b]
129 [-]: MOVE      R20 R11      ; R20 := R11
130 [-]: CONST     R21 8        ; R21 := 8.000000
131 [-]: CONST     R22 0        ; R22 := 0.000000
132 [-]: GETUPVAL  R23 U15      ; R23 := U15
133 [-]: CALL      R18 6 2      ; R18 := R18(R19,R20,R21,R22,R23)
134 [-]: TEST      R18 0        ; if not R18 then PC := 138
135 [-]: JMP       138          ; PC := 138
136 [-]: MOVE      R10 R11      ; R10 := R11
137 [-]: JMP       140          ; PC := 140
138 [-]: ADD       R8 R8 R9     ; R8 := R8 + R9
139 [-]: FORLOOP   R13 107      ; R13 += R15; if R13 <= R14 then begin PC := 107; R16 := R13 end
140 [-]: SELF      R18 R0 K20   ; R19 := R0; R18 := R0[0x68b88e58]
141 [-]: LOADKB    R20 0 0      ; R20 := false
142 [-]: CALL      R18 3 1      ; R18(R19,R20)
143 [-]: GETGLOBAL R18 K33      ; R18 := 0x89326c93
144 [-]: SELF      R18 R18 K42  ; R19 := R18; R18 := R18[0x05909209]
145 [-]: GETGLOBAL R20 K43      ; R20 := 0x3d88b2f8
146 [-]: SELF      R21 R1 K44   ; R22 := R1; R21 := R1[0x003c792f]
147 [-]: GETGLOBAL R23 K16      ; R23 := 0x0469f296
148 [-]: LOADK     R24 K17      ; R24 := "GAME_R1_WEAPON1"
149 [-]: CALL      R23 2 0      ; R23,... := R23(R24)
150 [-]: CALL      R21 0 2      ; R21 := R21(R22,...)
151 [-]: GETGLOBAL R22 K19      ; R22 := ZERO_ROTATION
152 [-]: MOVE      R23 R0       ; R23 := R0
153 [-]: CALL      R18 6 1      ; R18(R19,R20,R21,R22,R23)
154 [-]: SELF      R18 R0 K45   ; R19 := R0; R18 := R0[0x0d0482e0]
155 [-]: CALL      R18 2 1      ; R18(R19)
156 [-]: GETGLOBAL R18 K46      ; R18 := 0x7b998233
157 [-]: GETGLOBAL R19 K5       ; R19 := _T
158 [-]: GETTABLE  R19 R19 K47  ; R19 := R19["infestPods"]
159 [-]: CALL      R18 2 2      ; R18 := R18(R19)
160 [-]: TEST      R18 0        ; if not R18 then PC := 165
161 [-]: JMP       165          ; PC := 165
162 [-]: GETGLOBAL R18 K5       ; R18 := _T
163 [-]: NEWTABLE  R19 0 0      ; R19 := {}
164 [-]: SETTABLE  R18 K47 R19  ; R18["infestPods"] := R19
165 [-]: GETGLOBAL R18 K5       ; R18 := _T
166 [-]: GETTABLE  R18 R18 K48  ; R18 := R18[0xcc4ac7a6]
167 [-]: GETGLOBAL R19 K49      ; R19 := 0x6687f6e0
168 [-]: SELF      R19 R19 K50  ; R20 := R19; R19 := R19[0xcde10c4a]
169 [-]: CALL      R19 2 2      ; R19 := R19(R20)
170 [-]: MOVE      R20 R1       ; R20 := R1
171 [-]: GETUPVAL  R21 U3       ; R21 := U3
172 [-]: CONST     R22 0        ; R22 := 0.000000
173 [-]: CALL      R18 5 1      ; R18(R19,R20,R21,R22)
174 [-]: SELF      R18 R1 K51   ; R19 := R1; R18 := R1[0x388577d5]
175 [-]: CALL      R18 2 2      ; R18 := R18(R19)
176 [-]: GETGLOBAL R19 K46      ; R19 := 0x7b998233
177 [-]: GETGLOBAL R20 K5       ; R20 := _T
178 [-]: GETTABLE  R20 R20 K47  ; R20 := R20["infestPods"]
179 [-]: GETTABLE  R20 R20 R18  ; R20 := R20[R18]
180 [-]: CALL      R19 2 2      ; R19 := R19(R20)
181 [-]: TEST      R19 0        ; if not R19 then PC := 191
182 [-]: JMP       191          ; PC := 191
183 [-]: GETGLOBAL R19 K5       ; R19 := _T
184 [-]: GETTABLE  R19 R19 K47  ; R19 := R19["infestPods"]
185 [-]: NEWTABLE  R20 0 2      ; R20 := {}
186 [-]: SETTABLE  R20 K52 K2   ; R20["instance"] := 0.000000
187 [-]: GETUPVAL  R21 U3       ; R21 := U3
188 [-]: SETTABLE  R20 K53 R21  ; R20["duration"] := R21
189 [-]: SETTABLE  R19 R18 R20  ; R19[R18] := R20
190 [-]: JMP       230          ; PC := 230
191 [-]: GETGLOBAL R19 K5       ; R19 := _T
192 [-]: GETTABLE  R19 R19 K47  ; R19 := R19["infestPods"]
193 [-]: GETTABLE  R19 R19 R18  ; R19 := R19[R18]
194 [-]: GETUPVAL  R20 U3       ; R20 := U3
195 [-]: SETTABLE  R19 K53 R20  ; R19["duration"] := R20
196 [-]: GETGLOBAL R19 K54      ; R19 := 0x03ea2485
197 [-]: GETGLOBAL R20 K5       ; R20 := _T
198 [-]: GETTABLE  R20 R20 K47  ; R20 := R20["infestPods"]
199 [-]: GETTABLE  R20 R20 R18  ; R20 := R20[R18]
200 [-]: GETTABLE  R20 R20 K55  ; R20 := R20["pos"]
201 [-]: MOVE      R21 R6       ; R21 := R6
202 [-]: CALL      R19 3 2      ; R19 := R19(R20,R21)
203 [-]: GETGLOBAL R20 K5       ; R20 := _T
204 [-]: GETTABLE  R20 R20 K47  ; R20 := R20["infestPods"]
205 [-]: GETTABLE  R20 R20 R18  ; R20 := R20[R18]
206 [-]: GETTABLE  R20 R20 K56  ; R20 := R20["radius"]
207 [-]: LE        0 R19 R20    ; if R19 > R20 then PC := 210
208 [-]: JMP       210          ; PC := 210
209 [-]: RETURN    R0 1         ; return 
210 [-]: GETGLOBAL R19 K5       ; R19 := _T
211 [-]: GETTABLE  R19 R19 K47  ; R19 := R19["infestPods"]
212 [-]: GETTABLE  R19 R19 R18  ; R19 := R19[R18]
213 [-]: GETTABLE  R19 R19 K52  ; R19 := R19["instance"]
214 [-]: EQ        0 R19 K7     ; if R19 ~= nil then PC := 221
215 [-]: JMP       221          ; PC := 221
216 [-]: GETGLOBAL R19 K5       ; R19 := _T
217 [-]: GETTABLE  R19 R19 K47  ; R19 := R19["infestPods"]
218 [-]: GETTABLE  R19 R19 R18  ; R19 := R19[R18]
219 [-]: SETTABLE  R19 K52 K2   ; R19["instance"] := 0.000000
220 [-]: JMP       230          ; PC := 230
221 [-]: GETGLOBAL R19 K5       ; R19 := _T
222 [-]: GETTABLE  R19 R19 K47  ; R19 := R19["infestPods"]
223 [-]: GETTABLE  R19 R19 R18  ; R19 := R19[R18]
224 [-]: GETGLOBAL R20 K5       ; R20 := _T
225 [-]: GETTABLE  R20 R20 K47  ; R20 := R20["infestPods"]
226 [-]: GETTABLE  R20 R20 R18  ; R20 := R20[R18]
227 [-]: GETTABLE  R20 R20 K52  ; R20 := R20["instance"]
228 [-]: ADD       R20 R20 K4   ; R20 := R20 + 1.000000
229 [-]: SETTABLE  R19 K52 R20  ; R19["instance"] := R20
230 [-]: GETGLOBAL R19 K5       ; R19 := _T
231 [-]: GETTABLE  R19 R19 K47  ; R19 := R19["infestPods"]
232 [-]: GETTABLE  R19 R19 R18  ; R19 := R19[R18]
233 [-]: SETTABLE  R19 K55 R6   ; R19["pos"] := R6
234 [-]: GETGLOBAL R19 K5       ; R19 := _T
235 [-]: GETTABLE  R19 R19 K47  ; R19 := R19["infestPods"]
236 [-]: GETTABLE  R19 R19 R18  ; R19 := R19[R18]
237 [-]: GETUPVAL  R20 U4       ; R20 := U4
238 [-]: SETTABLE  R19 K56 R20  ; R19["radius"] := R20
239 [-]: GETGLOBAL R19 K5       ; R19 := _T
240 [-]: GETTABLE  R19 R19 K47  ; R19 := R19["infestPods"]
241 [-]: GETTABLE  R19 R19 R18  ; R19 := R19[R18]
242 [-]: SETTABLE  R19 K57 R10  ; R19["firstPos"] := R10
243 [-]: GETGLOBAL R19 K33      ; R19 := 0x89326c93
244 [-]: SELF      R19 R19 K42  ; R20 := R19; R19 := R19[0x05909209]
245 [-]: GETGLOBAL R21 K58      ; R21 := 0x4a62ebfe
246 [-]: GETGLOBAL R22 K32      ; R22 := 0xa421af95
247 [-]: CONST     R23 0        ; R23 := 0.000000
248 [-]: CONST     R24 0        ; R24 := 0.500000
249 [-]: CONST     R25 0        ; R25 := 0.000000
250 [-]: CALL      R22 4 2      ; R22 := R22(R23,R24,R25)
251 [-]: ADD       R22 R6 R22   ; R22 := R6 + R22
252 [-]: GETGLOBAL R23 K19      ; R23 := ZERO_ROTATION
253 [-]: MOVE      R24 R0       ; R24 := R0
254 [-]: CALL      R19 6 2      ; R19 := R19(R20,R21,R22,R23,R24)
255 [-]: GETGLOBAL R20 K46      ; R20 := 0x7b998233
256 [-]: MOVE      R21 R19      ; R21 := R19
257 [-]: CALL      R20 2 2      ; R20 := R20(R21)
258 [-]: TEST      R20 1        ; if R20 then PC := 266
259 [-]: JMP       266          ; PC := 266
260 [-]: SELF      R20 R19 K59  ; R21 := R19; R20 := R19[0xd5f7912b]
261 [-]: GETGLOBAL R22 K16      ; R22 := 0x0469f296
262 [-]: LOADK     R23 K60      ; R23 := "InfestLoop"
263 [-]: CALL      R22 2 2      ; R22 := R22(R23)
264 [-]: LOADKB    R23 0 0      ; R23 := false
265 [-]: CALL      R20 4 1      ; R20(R21,R22,R23)
266 [-]: RETURN    R0 1         ; return 


; Function #18:
;
; Name:            
; Defined at line: 996
; #Upvalues:       1
; #Parameters:     4
; Is_vararg:       0
; Max Stack Size:  8

  1 [-]: GETUPVAL  R4 U0        ; R4 := U0
  2 [-]: GETTABLE  R4 R4 K0     ; R4 := R4[0xf847d825]
  3 [-]: MOVE      R5 R1        ; R5 := R1
  4 [-]: GETGLOBAL R6 K1        ; R6 := 0x99cb4b90
  5 [-]: GETGLOBAL R7 K2        ; R7 := 0x0ed8b456
  6 [-]: CALL      R4 4 1       ; R4(R5,R6,R7)
  7 [-]: SELF      R4 R0 K3     ; R5 := R0; R4 := R0[0x68b88e58]
  8 [-]: LOADKB    R6 0 0       ; R6 := false
  9 [-]: CALL      R4 3 1       ; R4(R5,R6)
 10 [-]: RETURN    R0 1         ; return 


; Function #19:
;
; Name:            
; Defined at line: 1001
; #Upvalues:       0
; #Parameters:     2
; Is_vararg:       0
; Max Stack Size:  6

  1 [-]: SELF      R2 R0 K0     ; R3 := R0; R2 := R0[0x5163741e]
  2 [-]: CALL      R2 2 2       ; R2 := R2(R3)
  3 [-]: GETGLOBAL R3 K1        ; R3 := 0x7b998233
  4 [-]: MOVE      R4 R2        ; R4 := R2
  5 [-]: CALL      R3 2 2       ; R3 := R3(R4)
  6 [-]: TEST      R3 1         ; if R3 then PC := 27
  7 [-]: JMP       27           ; PC := 27
  8 [-]: GETGLOBAL R3 K1        ; R3 := 0x7b998233
  9 [-]: GETGLOBAL R4 K2        ; R4 := _T
 10 [-]: GETTABLE  R4 R4 K3     ; R4 := R4["infestPods"]
 11 [-]: CALL      R3 2 2       ; R3 := R3(R4)
 12 [-]: TEST      R3 1         ; if R3 then PC := 27
 13 [-]: JMP       27           ; PC := 27
 14 [-]: SELF      R3 R2 K4     ; R4 := R2; R3 := R2[0x388577d5]
 15 [-]: CALL      R3 2 2       ; R3 := R3(R4)
 16 [-]: GETGLOBAL R4 K1        ; R4 := 0x7b998233
 17 [-]: GETGLOBAL R5 K2        ; R5 := _T
 18 [-]: GETTABLE  R5 R5 K3     ; R5 := R5["infestPods"]
 19 [-]: GETTABLE  R5 R5 R3     ; R5 := R5[R3]
 20 [-]: CALL      R4 2 2       ; R4 := R4(R5)
 21 [-]: TEST      R4 1         ; if R4 then PC := 27
 22 [-]: JMP       27           ; PC := 27
 23 [-]: GETGLOBAL R4 K2        ; R4 := _T
 24 [-]: GETTABLE  R4 R4 K3     ; R4 := R4["infestPods"]
 25 [-]: GETTABLE  R4 R4 R3     ; R4 := R4[R3]
 26 [-]: SETTABLE  R4 K5 K6     ; R4["instance"] := nil
 27 [-]: RETURN    R0 1         ; return 


; Function #20:
;
; Name:            
; Defined at line: 1011
; #Upvalues:       6
; #Parameters:     1
; Is_vararg:       0
; Max Stack Size:  36

  1 [-]: SELF      R1 R0 K0     ; R2 := R0; R1 := R0[0xfa9e477f]
  2 [-]: CALL      R1 2 2       ; R1 := R1(R2)
  3 [-]: GETGLOBAL R2 K1        ; R2 := 0x7b998233
  4 [-]: MOVE      R3 R1        ; R3 := R1
  5 [-]: CALL      R2 2 2       ; R2 := R2(R3)
  6 [-]: TEST      R2 0         ; if not R2 then PC := 9
  7 [-]: JMP       9            ; PC := 9
  8 [-]: RETURN    R0 1         ; return 
  9 [-]: SELF      R2 R0 K2     ; R3 := R0; R2 := R0[0xe4b9db64]
 10 [-]: CALL      R2 2 2       ; R2 := R2(R3)
 11 [-]: GETGLOBAL R3 K1        ; R3 := 0x7b998233
 12 [-]: MOVE      R4 R2        ; R4 := R2
 13 [-]: CALL      R3 2 2       ; R3 := R3(R4)
 14 [-]: TEST      R3 0         ; if not R3 then PC := 17
 15 [-]: JMP       17           ; PC := 17
 16 [-]: RETURN    R0 1         ; return 
 17 [-]: SELF      R3 R2 K3     ; R4 := R2; R3 := R2[0xde321e6f]
 18 [-]: CALL      R3 2 2       ; R3 := R3(R4)
 19 [-]: SELF      R4 R3 K4     ; R5 := R3; R4 := R3[0xf7d48ee0]
 20 [-]: CALL      R4 2 2       ; R4 := R4(R5)
 21 [-]: GETGLOBAL R5 K1        ; R5 := 0x7b998233
 22 [-]: MOVE      R6 R4        ; R6 := R4
 23 [-]: CALL      R5 2 2       ; R5 := R5(R6)
 24 [-]: TEST      R5 0         ; if not R5 then PC := 27
 25 [-]: JMP       27           ; PC := 27
 26 [-]: RETURN    R0 1         ; return 
 27 [-]: GETGLOBAL R5 K5        ; R5 := 0xf5858163
 28 [-]: TEST      R5 0         ; if not R5 then PC := 144
 29 [-]: JMP       144          ; PC := 144
 30 [-]: GETGLOBAL R5 K6        ; R5 := 0x89326c93
 31 [-]: SELF      R5 R5 K7     ; R6 := R5; R5 := R5[0x18d05d30]
 32 [-]: CALL      R5 2 2       ; R5 := R5(R6)
 33 [-]: TEST      R5 1         ; if R5 then PC := 36
 34 [-]: JMP       36           ; PC := 36
 35 [-]: RETURN    R0 1         ; return 
 36 [-]: SELF      R5 R2 K8     ; R6 := R2; R5 := R2[0x388577d5]
 37 [-]: CALL      R5 2 2       ; R5 := R5(R6)
 38 [-]: SELF      R6 R0 K9     ; R7 := R0; R6 := R0[0xf6ebd926]
 39 [-]: CALL      R6 2 2       ; R6 := R6(R7)
 40 [-]: GETGLOBAL R7 K1        ; R7 := 0x7b998233
 41 [-]: GETGLOBAL R8 K10       ; R8 := _T
 42 [-]: GETTABLE  R8 R8 K11    ; R8 := R8["maggotEruption"]
 43 [-]: CALL      R7 2 2       ; R7 := R7(R8)
 44 [-]: TEST      R7 1         ; if R7 then PC := 111
 45 [-]: JMP       111          ; PC := 111
 46 [-]: GETGLOBAL R7 K1        ; R7 := 0x7b998233
 47 [-]: GETGLOBAL R8 K10       ; R8 := _T
 48 [-]: GETTABLE  R8 R8 K11    ; R8 := R8["maggotEruption"]
 49 [-]: GETTABLE  R8 R8 R5     ; R8 := R8[R5]
 50 [-]: CALL      R7 2 2       ; R7 := R7(R8)
 51 [-]: TEST      R7 1         ; if R7 then PC := 111
 52 [-]: JMP       111          ; PC := 111
 53 [-]: GETGLOBAL R7 K10       ; R7 := _T
 54 [-]: GETTABLE  R7 R7 K11    ; R7 := R7["maggotEruption"]
 55 [-]: GETTABLE  R7 R7 R5     ; R7 := R7[R5]
 56 [-]: GETTABLE  R7 R7 K12    ; R7 := R7["dmg"]
 57 [-]: GETGLOBAL R8 K10       ; R8 := _T
 58 [-]: GETTABLE  R8 R8 K11    ; R8 := R8["maggotEruption"]
 59 [-]: GETTABLE  R8 R8 R5     ; R8 := R8[R5]
 60 [-]: GETTABLE  R8 R8 K13    ; R8 := R8["radius"]
 61 [-]: GETGLOBAL R9 K6        ; R9 := 0x89326c93
 62 [-]: SELF      R9 R9 K14    ; R10 := R9; R9 := R9[0xfb669000]
 63 [-]: GETGLOBAL R11 K15      ; R11 := gLotusNpcAvatarType
 64 [-]: MOVE      R12 R6       ; R12 := R6
 65 [-]: CONST     R13 0        ; R13 := 0.000000
 66 [-]: MOVE      R14 R8       ; R14 := R8
 67 [-]: CALL      R9 6 2       ; R9 := R9(R10,R11,R12,R13,R14)
 68 [-]: GETGLOBAL R10 K16      ; R10 := 0x34291f5c
 69 [-]: GETTABLE  R10 R10 K17  ; R10 := R10[0x35c16153]
 70 [-]: CALL      R10 1 2      ; R10 := R10()
 71 [-]: SELF      R11 R10 K18  ; R12 := R10; R11 := R10[0xf4dc3420]
 72 [-]: MOVE      R13 R2       ; R13 := R2
 73 [-]: CALL      R11 3 1      ; R11(R12,R13)
 74 [-]: SELF      R11 R10 K19  ; R12 := R10; R11 := R10[0x1586e35e]
 75 [-]: CONST     R13 12       ; R13 := 12.000000
 76 [-]: CONST     R14 1        ; R14 := 1.000000
 77 [-]: CALL      R11 4 1      ; R11(R12,R13,R14)
 78 [-]: CONST     R11 1        ; R11 := 1.000000
 79 [-]: LEN       R12 R9       ; R12 := # R9
 80 [-]: CONST     R13 1        ; R13 := 1.000000
 81 [-]: FORPREP   R11 110      ; R11 -= R13; PC := 110
 82 [-]: GETGLOBAL R15 K1       ; R15 := 0x7b998233
 83 [-]: GETTABLE  R16 R9 R14   ; R16 := R9[R14]
 84 [-]: CALL      R15 2 2      ; R15 := R15(R16)
 85 [-]: TEST      R15 1        ; if R15 then PC := 110
 86 [-]: JMP       110          ; PC := 110
 87 [-]: GETTABLE  R15 R9 R14   ; R15 := R9[R14]
 88 [-]: SELF      R15 R15 K20  ; R16 := R15; R15 := R15[0x2047cfe7]
 89 [-]: CALL      R15 2 2      ; R15 := R15(R16)
 90 [-]: TEST      R15 1        ; if R15 then PC := 110
 91 [-]: JMP       110          ; PC := 110
 92 [-]: SELF      R15 R0 K21   ; R16 := R0; R15 := R0[0xee0bc178]
 93 [-]: GETTABLE  R17 R9 R14   ; R17 := R9[R14]
 94 [-]: CALL      R15 3 2      ; R15 := R15(R16,R17)
 95 [-]: TEST      R15 1        ; if R15 then PC := 110
 96 [-]: JMP       110          ; PC := 110
 97 [-]: SELF      R15 R10 K22  ; R16 := R10; R15 := R10[0xf326045f]
 98 [-]: GETGLOBAL R17 K16      ; R17 := 0x34291f5c
 99 [-]: GETTABLE  R17 R17 K23  ; R17 := R17[0x7258f36f]
100 [-]: GETTABLE  R18 R9 R14   ; R18 := R9[R14]
101 [-]: SELF      R18 R18 K24  ; R19 := R18; R18 := R18[0xd2715720]
102 [-]: CALL      R18 2 2      ; R18 := R18(R19)
103 [-]: MUL       R18 R7 R18   ; R18 := R7 * R18
104 [-]: CALL      R17 2 0      ; R17,... := R17(R18)
105 [-]: CALL      R15 0 1      ; R15(R16,...)
106 [-]: GETTABLE  R15 R9 R14   ; R15 := R9[R14]
107 [-]: SELF      R15 R15 K25  ; R16 := R15; R15 := R15[0x479483bb]
108 [-]: MOVE      R17 R10      ; R17 := R10
109 [-]: CALL      R15 3 1      ; R15(R16,R17)
110 [-]: FORLOOP   R11 82       ; R11 += R13; if R11 <= R12 then begin PC := 82; R14 := R11 end
111 [-]: GETGLOBAL R15 K6       ; R15 := 0x89326c93
112 [-]: SELF      R15 R15 K26  ; R16 := R15; R15 := R15[0x05909209]
113 [-]: GETGLOBAL R17 K27      ; R17 := 0x946b1bc9
114 [-]: MOVE      R18 R6       ; R18 := R6
115 [-]: SELF      R19 R0 K28   ; R20 := R0; R19 := R0[0x5280b883]
116 [-]: CALL      R19 2 2      ; R19 := R19(R20)
117 [-]: MOVE      R20 R2       ; R20 := R2
118 [-]: CALL      R15 6 2      ; R15 := R15(R16,R17,R18,R19,R20)
119 [-]: GETGLOBAL R16 K10      ; R16 := _T
120 [-]: GETTABLE  R16 R16 K29  ; R16 := R16["StrainMaggots"]
121 [-]: EQ        0 R16 K30    ; if R16 ~= nil then PC := 129
122 [-]: JMP       129          ; PC := 129
123 [-]: GETGLOBAL R16 K10      ; R16 := _T
124 [-]: NEWTABLE  R17 1 0      ; R17 := {}
125 [-]: MOVE      R18 R15      ; R18 := R15
126 [-]: SETLIST   R17 1 1      ; R17[(1-1)*FPF+i] := R(17+i), 1 <= i <= 1
127 [-]: SETTABLE  R16 K29 R17  ; R16["StrainMaggots"] := R17
128 [-]: JMP       135          ; PC := 135
129 [-]: GETGLOBAL R16 K31      ; R16 := 0x33bdd652
130 [-]: GETTABLE  R16 R16 K32  ; R16 := R16[0x23d5322f]
131 [-]: GETGLOBAL R17 K10      ; R17 := _T
132 [-]: GETTABLE  R17 R17 K29  ; R17 := R17["StrainMaggots"]
133 [-]: MOVE      R18 R15      ; R18 := R15
134 [-]: CALL      R16 3 1      ; R16(R17,R18)
135 [-]: SELF      R16 R15 K33  ; R17 := R15; R16 := R15[0x8ff3e684]
136 [-]: LOADKB    R18 0 0      ; R18 := false
137 [-]: LOADKB    R19 1 0      ; R19 := true
138 [-]: LOADKB    R20 0 0      ; R20 := false
139 [-]: GETGLOBAL R21 K34      ; R21 := 0x0c62abf7
140 [-]: CALL      R21 1 2      ; R21 := R21()
141 [-]: ADD       R21 R21 K35  ; R21 := R21 + 0.500000
142 [-]: CALL      R16 6 1      ; R16(R17,R18,R19,R20,R21)
143 [-]: JMP       328          ; PC := 328
144 [-]: GETGLOBAL R16 K36      ; R16 := 0x28338d30
145 [-]: TEST      R16 0        ; if not R16 then PC := 179
146 [-]: JMP       179          ; PC := 179
147 [-]: SELF      R16 R2 K8    ; R17 := R2; R16 := R2[0x388577d5]
148 [-]: CALL      R16 2 2      ; R16 := R16(R17)
149 [-]: GETGLOBAL R17 K1       ; R17 := 0x7b998233
150 [-]: GETGLOBAL R18 K10      ; R18 := _T
151 [-]: GETTABLE  R18 R18 K37  ; R18 := R18["maggotDiedNaturally"]
152 [-]: CALL      R17 2 2      ; R17 := R17(R18)
153 [-]: TEST      R17 1        ; if R17 then PC := 328
154 [-]: JMP       328          ; PC := 328
155 [-]: GETGLOBAL R17 K10      ; R17 := _T
156 [-]: GETTABLE  R17 R17 K37  ; R17 := R17["maggotDiedNaturally"]
157 [-]: GETTABLE  R17 R17 R16  ; R17 := R17[R16]
158 [-]: TEST      R17 1        ; if R17 then PC := 328
159 [-]: JMP       328          ; PC := 328
160 [-]: GETGLOBAL R17 K1       ; R17 := 0x7b998233
161 [-]: GETGLOBAL R18 K10      ; R18 := _T
162 [-]: GETTABLE  R18 R18 K38  ; R18 := R18["maggotDiedEarly"]
163 [-]: CALL      R17 2 2      ; R17 := R17(R18)
164 [-]: TEST      R17 1        ; if R17 then PC := 328
165 [-]: JMP       328          ; PC := 328
166 [-]: GETGLOBAL R17 K10      ; R17 := _T
167 [-]: GETTABLE  R17 R17 K39  ; R17 := R17["MaggotKilledEarly"]
168 [-]: EQ        1 R17 K30    ; if R17 == nil then PC := 328
169 [-]: JMP       328          ; PC := 328
170 [-]: GETGLOBAL R17 K10      ; R17 := _T
171 [-]: GETTABLE  R17 R17 K38  ; R17 := R17["maggotDiedEarly"]
172 [-]: SETTABLE  R17 R16 K40  ; R17[R16] := true
173 [-]: GETGLOBAL R17 K10      ; R17 := _T
174 [-]: GETTABLE  R17 R17 K41  ; R17 := R17[0x0b6972df]
175 [-]: MOVE      R18 R4       ; R18 := R4
176 [-]: MOVE      R19 R2       ; R19 := R2
177 [-]: CALL      R17 3 1      ; R17(R18,R19)
178 [-]: JMP       328          ; PC := 328
179 [-]: SELF      R17 R4 K42   ; R18 := R4; R17 := R4[0xdaddfb73]
180 [-]: GETUPVAL  R19 U0       ; R19 := U0
181 [-]: CALL      R17 3 2      ; R17 := R17(R18,R19)
182 [-]: GETUPVAL  R18 U1       ; R18 := U1
183 [-]: SELF      R19 R4 K43   ; R20 := R4; R19 := R4[0xa776e126]
184 [-]: GETUPVAL  R21 U0       ; R21 := U0
185 [-]: CALL      R19 3 0      ; R19,... := R19(R20,R21)
186 [-]: CALL      R18 0 1      ; R18(R19,...)
187 [-]: GETGLOBAL R18 K16      ; R18 := 0x34291f5c
188 [-]: GETTABLE  R18 R18 K23  ; R18 := R18[0x7258f36f]
189 [-]: GETUPVAL  R19 U2       ; R19 := U2
190 [-]: CALL      R18 2 2      ; R18 := R18(R19)
191 [-]: SETUPVAL  R18 U2       ; U82 := R2
192 [-]: SELF      R18 R0 K44   ; R19 := R0; R18 := R0[0x672ed7b1]
193 [-]: CALL      R18 2 2      ; R18 := R18(R19)
194 [-]: EQ        0 R17 R18    ; if R17 ~= R18 then PC := 210
195 [-]: JMP       210          ; PC := 210
196 [-]: GETUPVAL  R18 U3       ; R18 := U3
197 [-]: GETTABLE  R18 R18 K45  ; R18 := R18[0xb43a6753]
198 [-]: MOVE      R19 R4       ; R19 := R4
199 [-]: MOVE      R20 R17      ; R20 := R17
200 [-]: CALL      R18 3 2      ; R18 := R18(R19,R20)
201 [-]: GETGLOBAL R19 K1       ; R19 := 0x7b998233
202 [-]: MOVE      R20 R18      ; R20 := R18
203 [-]: CALL      R19 2 2      ; R19 := R19(R20)
204 [-]: TEST      R19 1        ; if R19 then PC := 210
205 [-]: JMP       210          ; PC := 210
206 [-]: GETTABLE  R19 R18 K46  ; R19 := R18["explosionDamage"]
207 [-]: GETTABLE  R20 R18 K47  ; R20 := R18["explosionRadius"]
208 [-]: SETUPVAL  R20 U4       ; U82 := R4
209 [-]: SETUPVAL  R19 U2       ; U82 := R2
210 [-]: GETGLOBAL R19 K6       ; R19 := 0x89326c93
211 [-]: SELF      R19 R19 K26  ; R20 := R19; R19 := R19[0x05909209]
212 [-]: GETGLOBAL R21 K48      ; R21 := 0x055e4ffd
213 [-]: SELF      R22 R0 K49   ; R23 := R0; R22 := R0[0xd1586535]
214 [-]: CALL      R22 2 2      ; R22 := R22(R23)
215 [-]: GETGLOBAL R23 K50      ; R23 := ZERO_ROTATION
216 [-]: MOVE      R24 R4       ; R24 := R4
217 [-]: CALL      R19 6 2      ; R19 := R19(R20,R21,R22,R23,R24)
218 [-]: GETGLOBAL R20 K1       ; R20 := 0x7b998233
219 [-]: MOVE      R21 R19      ; R21 := R19
220 [-]: CALL      R20 2 2      ; R20 := R20(R21)
221 [-]: TEST      R20 1        ; if R20 then PC := 227
222 [-]: JMP       227          ; PC := 227
223 [-]: SELF      R20 R19 K51  ; R21 := R19; R20 := R19[0x2d9ba74f]
224 [-]: GETUPVAL  R22 U4       ; R22 := U4
225 [-]: DIV       R22 R22 K52  ; R22 := R22 / 5.000000
226 [-]: CALL      R20 3 1      ; R20(R21,R22)
227 [-]: GETGLOBAL R20 K6       ; R20 := 0x89326c93
228 [-]: SELF      R20 R20 K7   ; R21 := R20; R20 := R20[0x18d05d30]
229 [-]: CALL      R20 2 2      ; R20 := R20(R21)
230 [-]: TEST      R20 1        ; if R20 then PC := 233
231 [-]: JMP       233          ; PC := 233
232 [-]: RETURN    R0 1         ; return 
233 [-]: GETGLOBAL R20 K16      ; R20 := 0x34291f5c
234 [-]: GETTABLE  R20 R20 K17  ; R20 := R20[0x35c16153]
235 [-]: CALL      R20 1 2      ; R20 := R20()
236 [-]: SELF      R21 R20 K22  ; R22 := R20; R21 := R20[0xf326045f]
237 [-]: GETUPVAL  R23 U2       ; R23 := U2
238 [-]: CALL      R21 3 1      ; R21(R22,R23)
239 [-]: SELF      R21 R20 K19  ; R22 := R20; R21 := R20[0x1586e35e]
240 [-]: CONST     R23 7        ; R23 := 7.000000
241 [-]: CONST     R24 1        ; R24 := 1.000000
242 [-]: CALL      R21 4 1      ; R21(R22,R23,R24)
243 [-]: SELF      R21 R20 K53  ; R22 := R20; R21 := R20[0x86cd00cb]
244 [-]: MOVE      R23 R2       ; R23 := R2
245 [-]: CALL      R21 3 1      ; R21(R22,R23)
246 [-]: SELF      R21 R20 K18  ; R22 := R20; R21 := R20[0xf4dc3420]
247 [-]: MOVE      R23 R4       ; R23 := R4
248 [-]: CALL      R21 3 1      ; R21(R22,R23)
249 [-]: CONST     R21 0        ; R21 := 0.000000
250 [-]: GETGLOBAL R22 K1       ; R22 := 0x7b998233
251 [-]: MOVE      R23 R17      ; R23 := R17
252 [-]: CALL      R22 2 2      ; R22 := R22(R23)
253 [-]: TEST      R22 1        ; if R22 then PC := 262
254 [-]: JMP       262          ; PC := 262
255 [-]: SELF      R22 R3 K54   ; R23 := R3; R22 := R3[0xe9f54086]
256 [-]: CONST     R24 0        ; R24 := 0.000000
257 [-]: CONST     R25 140      ; R25 := 140.000000
258 [-]: SELF      R26 R17 K56  ; R27 := R17; R26 := R17[0xcde10c4a]
259 [-]: CALL      R26 2 0      ; R26,... := R26(R27)
260 [-]: CALL      R22 0 2      ; R22 := R22(R23,...)
261 [-]: MOVE      R21 R22      ; R21 := R22
262 [-]: CONST     R22 0        ; R22 := 0.000000
263 [-]: GETGLOBAL R23 K6       ; R23 := 0x89326c93
264 [-]: SELF      R23 R23 K14  ; R24 := R23; R23 := R23[0xfb669000]
265 [-]: GETGLOBAL R25 K57      ; R25 := gBaseAvatarType
266 [-]: SELF      R26 R0 K49   ; R27 := R0; R26 := R0[0xd1586535]
267 [-]: CALL      R26 2 2      ; R26 := R26(R27)
268 [-]: CONST     R27 0        ; R27 := 0.000000
269 [-]: GETUPVAL  R28 U4       ; R28 := U4
270 [-]: CALL      R23 6 2      ; R23 := R23(R24,R25,R26,R27,R28)
271 [-]: GETGLOBAL R24 K58      ; R24 := 0xc8802016
272 [-]: MOVE      R25 R23      ; R25 := R23
273 [-]: CALL      R24 2 4      ; R24,R25,R26 := R24(R25)
274 [-]: JMP       308          ; PC := 308
275 [-]: SELF      R29 R0 K21   ; R30 := R0; R29 := R0[0xee0bc178]
276 [-]: MOVE      R31 R28      ; R31 := R28
277 [-]: CALL      R29 3 2      ; R29 := R29(R30,R31)
278 [-]: TEST      R29 1        ; if R29 then PC := 308
279 [-]: JMP       308          ; PC := 308
280 [-]: SELF      R29 R28 K59  ; R30 := R28; R29 := R28[0xc4dff581]
281 [-]: CONST     R31 0        ; R31 := 0.000000
282 [-]: CALL      R29 3 2      ; R29 := R29(R30,R31)
283 [-]: TEST      R29 1        ; if R29 then PC := 308
284 [-]: JMP       308          ; PC := 308
285 [-]: SELF      R29 R28 K25  ; R30 := R28; R29 := R28[0x479483bb]
286 [-]: MOVE      R31 R20      ; R31 := R20
287 [-]: CALL      R29 3 1      ; R29(R30,R31)
288 [-]: GETUPVAL  R29 U5       ; R29 := U5
289 [-]: ADD       R22 R22 R29  ; R22 := R22 + R29
290 [-]: LT        0 K61 R21    ; if 0.000000 >= R21 then PC := 308
291 [-]: JMP       308          ; PC := 308
292 [-]: GETGLOBAL R29 K62      ; R29 := 0x5bced4c4
293 [-]: GETTABLE  R29 R29 K63  ; R29 := R29[0x55f27c30]
294 [-]: MOVE      R30 R21      ; R30 := R21
295 [-]: CALL      R29 2 2      ; R29 := R29(R30)
296 [-]: GETUPVAL  R30 U5       ; R30 := U5
297 [-]: MUL       R30 R29 R30  ; R30 := R29 * R30
298 [-]: ADD       R22 R22 R30  ; R22 := R22 + R30
299 [-]: GETGLOBAL R30 K64      ; R30 := 0xc163f229
300 [-]: CONST     R31 0        ; R31 := 0.000000
301 [-]: CONST     R32 1        ; R32 := 1.000000
302 [-]: CALL      R30 3 2      ; R30 := R30(R31,R32)
303 [-]: SUB       R31 R21 R29  ; R31 := R21 - R29
304 [-]: LT        0 R30 R31    ; if R30 >= R31 then PC := 308
305 [-]: JMP       308          ; PC := 308
306 [-]: GETUPVAL  R30 U5       ; R30 := U5
307 [-]: ADD       R22 R22 R30  ; R22 := R22 + R30
308 [-]: TFORLOOP  R24 2        ; R27,R28 :=  R24(R25,R26); if R27 ~= nil then begin PC = 275; R26 := R27 end
309 [-]: JMP       275          ; PC := 275
310 [-]: LT        0 K61 R22    ; if 0.000000 >= R22 then PC := 328
311 [-]: JMP       328          ; PC := 328
312 [-]: GETGLOBAL R30 K60      ; R30 := 0x6c97a788
313 [-]: GETTABLE  R30 R30 K65  ; R30 := R30[0x733fc736]
314 [-]: LOADKB    R31 0 0      ; R31 := false
315 [-]: CALL      R30 2 2      ; R30 := R30(R31)
316 [-]: SELF      R31 R30 K66  ; R32 := R30; R31 := R30[0x80925b98]
317 [-]: MOVE      R33 R22      ; R33 := R22
318 [-]: CALL      R31 3 1      ; R31(R32,R33)
319 [-]: SELF      R31 R4 K67   ; R32 := R4; R31 := R4[0xcbae1d7c]
320 [-]: GETGLOBAL R33 K68      ; R33 := 0x7ed0a956
321 [-]: LOADK     R34 K69      ; R34 := "/Lotus/Powersuits/PowersuitAbilities/InfestRuptureAbility"
322 [-]: CALL      R33 2 2      ; R33 := R33(R34)
323 [-]: GETGLOBAL R34 K70      ; R34 := 0x0469f296
324 [-]: LOADK     R35 K71      ; R35 := "AddHits"
325 [-]: CALL      R34 2 2      ; R34 := R34(R35)
326 [-]: MOVE      R35 R30      ; R35 := R30
327 [-]: CALL      R31 5 1      ; R31(R32,R33,R34,R35)
328 [-]: RETURN    R0 1         ; return 


; Function #21:
;
; Name:            
; Defined at line: 1125
; #Upvalues:       4
; #Parameters:     1
; Is_vararg:       0
; Max Stack Size:  8

  1 [-]: GETGLOBAL R1 K0        ; R1 := 0xcbd666e1
  2 [-]: CONST     R2 0         ; R2 := 0.000000
  3 [-]: CALL      R1 2 1       ; R1(R2)
  4 [-]: LOADNIL   R1 R1        ; R1 := nil
  5 [-]: GETGLOBAL R2 K1        ; R2 := 0xdc0d6af8
  6 [-]: TEST      R2 0         ; if not R2 then PC := 28
  7 [-]: JMP       28           ; PC := 28
  8 [-]: GETGLOBAL R2 K0        ; R2 := 0xcbd666e1
  9 [-]: LOADK     R3 K2        ; R3 := 0.100000
 10 [-]: CALL      R2 2 1       ; R2(R3)
 11 [-]: CONST     R2 10        ; R2 := 10.000000
 12 [-]: GETGLOBAL R3 K3        ; R3 := 0x7b998233
 13 [-]: MOVE      R4 R1        ; R4 := R1
 14 [-]: CALL      R3 2 2       ; R3 := R3(R4)
 15 [-]: TEST      R3 0         ; if not R3 then PC := 31
 16 [-]: JMP       31           ; PC := 31
 17 [-]: LT        0 K4 R2      ; if 0.000000 >= R2 then PC := 31
 18 [-]: JMP       31           ; PC := 31
 19 [-]: SELF      R3 R0 K5     ; R4 := R0; R3 := R0[0xe4b9db64]
 20 [-]: CALL      R3 2 2       ; R3 := R3(R4)
 21 [-]: MOVE      R1 R3        ; R1 := R3
 22 [-]: SUB       R2 R2 K6     ; R2 := R2 - 1.000000
 23 [-]: GETGLOBAL R3 K0        ; R3 := 0xcbd666e1
 24 [-]: LOADK     R4 K7        ; R4 := 0.050000
 25 [-]: CALL      R3 2 1       ; R3(R4)
 26 [-]: JMP       12           ; PC := 12
 27 [-]: JMP       31           ; PC := 31
 28 [-]: SELF      R3 R0 K8     ; R4 := R0; R3 := R0[0xed324116]
 29 [-]: CALL      R3 2 2       ; R3 := R3(R4)
 30 [-]: MOVE      R1 R3        ; R1 := R3
 31 [-]: GETGLOBAL R3 K3        ; R3 := 0x7b998233
 32 [-]: MOVE      R4 R1        ; R4 := R1
 33 [-]: CALL      R3 2 2       ; R3 := R3(R4)
 34 [-]: TEST      R3 0         ; if not R3 then PC := 49
 35 [-]: JMP       49           ; PC := 49
 36 [-]: GETGLOBAL R3 K1        ; R3 := 0xdc0d6af8
 37 [-]: TEST      R3 0         ; if not R3 then PC := 48
 38 [-]: JMP       48           ; PC := 48
 39 [-]: SELF      R3 R0 K9     ; R4 := R0; R3 := R0[0x5b65edac]
 40 [-]: GETUPVAL  R5 U0        ; R5 := U0
 41 [-]: CALL      R3 3 1       ; R3(R4,R5)
 42 [-]: SELF      R3 R0 K9     ; R4 := R0; R3 := R0[0x5b65edac]
 43 [-]: GETUPVAL  R5 U1        ; R5 := U1
 44 [-]: CALL      R3 3 1       ; R3(R4,R5)
 45 [-]: SELF      R3 R0 K9     ; R4 := R0; R3 := R0[0x5b65edac]
 46 [-]: GETUPVAL  R5 U2        ; R5 := U2
 47 [-]: CALL      R3 3 1       ; R3(R4,R5)
 48 [-]: RETURN    R0 1         ; return 
 49 [-]: SELF      R3 R0 K10    ; R4 := R0; R3 := R0[0x5ee199f2]
 50 [-]: MOVE      R5 R1        ; R5 := R1
 51 [-]: CALL      R3 3 1       ; R3(R4,R5)
 52 [-]: GETGLOBAL R3 K1        ; R3 := 0xdc0d6af8
 53 [-]: TEST      R3 1         ; if R3 then PC := 56
 54 [-]: JMP       56           ; PC := 56
 55 [-]: RETURN    R0 1         ; return 
 56 [-]: LOADK     R3 K2        ; R3 := 0.100000
 57 [-]: LT        0 R3 K11     ; if R3 >= 2.000000 then PC := 71
 58 [-]: JMP       71           ; PC := 71
 59 [-]: SELF      R4 R0 K12    ; R5 := R0; R4 := R0[0x986d2ab8]
 60 [-]: GETUPVAL  R6 U3        ; R6 := U3
 61 [-]: MUL       R7 R3 K11    ; R7 := R3 * 2.000000
 62 [-]: CALL      R4 4 1       ; R4(R5,R6,R7)
 63 [-]: GETGLOBAL R4 K0        ; R4 := 0xcbd666e1
 64 [-]: CONST     R5 0         ; R5 := 0.000000
 65 [-]: CALL      R4 2 1       ; R4(R5)
 66 [-]: GETGLOBAL R4 K13       ; R4 := 0x67652851
 67 [-]: CALL      R4 1 2       ; R4 := R4()
 68 [-]: MUL       R4 R4 K14    ; R4 := R4 * 4.000000
 69 [-]: ADD       R3 R3 R4     ; R3 := R3 + R4
 70 [-]: JMP       57           ; PC := 57
 71 [-]: RETURN    R0 1         ; return 


