; This file has been disassembled using luadec 2.0.2 by sztupy (modified by Reversive)

; Name:            
; Defined at line: 0
; #Upvalues:       0
; #Parameters:     0
; Is_vararg:       2
; Max Stack Size:  39

  1 [-]: GETGLOBAL R0 K0        ; R0 := 0x2d0fad09
  2 [-]: LOADK     R1 K1        ; R1 := "Lotus.Scripts.Libs.AbilitiesLib"
  3 [-]: CALL      R0 2 2       ; R0 := R0(R1)
  4 [-]: GETGLOBAL R1 K0        ; R1 := 0x2d0fad09
  5 [-]: LOADK     R2 K2        ; R2 := "Lotus.Powersuits.PowersuitAbilities.PVPLib"
  6 [-]: CALL      R1 2 2       ; R1 := R1(R2)
  7 [-]: GETGLOBAL R2 K3        ; R2 := 0x0469f296
  8 [-]: LOADK     R3 K4        ; R3 := "LureAvatar"
  9 [-]: CALL      R2 2 2       ; R2 := R2(R3)
 10 [-]: GETGLOBAL R3 K3        ; R3 := 0x0469f296
 11 [-]: LOADK     R4 K5        ; R4 := "VoidInvuln"
 12 [-]: CALL      R3 2 2       ; R3 := R3(R4)
 13 [-]: LOADK     R4 7         ; R4 := 7.000000
 14 [-]: LOADK     R5 K6        ; R5 := 0.200000
 15 [-]: LOADK     R6 20        ; R6 := 20.000000
 16 [-]: LOADK     R7 0         ; R7 := 0.500000
 17 [-]: LOADK     R8 20        ; R8 := 20.000000
 18 [-]: LOADK     R9 K7        ; R9 := 0.100000
 19 [-]: LOADK     R10 5        ; R10 := 5.000000
 20 [-]: LOADK     R11 K8       ; R11 := 0.050000
 21 [-]: LOADK     R12 4        ; R12 := 4.000000
 22 [-]: LOADK     R13 K9       ; R13 := 0.300000
 23 [-]: LOADK     R14 2        ; R14 := 2.000000
 24 [-]: LOADK     R15 0        ; R15 := 0.000000
 25 [-]: LOADK     R16 25       ; R16 := 25.000000
 26 [-]: LOADK     R17 100      ; R17 := 100.000000
 27 [-]: LOADK     R18 2        ; R18 := 2.000000
 28 [-]: LOADK     R19 5        ; R19 := 5.000000
 29 [-]: LOADK     R20 2        ; R20 := 2.000000
 30 [-]: LOADK     R21 K7       ; R21 := 0.100000
 31 [-]: LOADK     R22 1        ; R22 := 1.000000
 32 [-]: LOADK     R23 8        ; R23 := 8.000000
 33 [-]: LOADK     R24 K7       ; R24 := 0.100000
 34 [-]: MOVE      R25 R5       ; R25 := R5
 35 [-]: LOADK     R26 15       ; R26 := 15.000000
 36 [-]: LOADK     R27 0        ; R27 := 0.500000
 37 [-]: LOADK     R28 12       ; R28 := 12.000000
 38 [-]: LOADK     R29 10       ; R29 := 10.000000
 39 [-]: CLOSURE   R30 0        ; R30 := closure(Function #1)
 40 [-]: MOVE      R0 R1        ; R0 := R1
 41 [-]: MOVE      R0 R17       ; R0 := R17
 42 [-]: MOVE      R0 R18       ; R0 := R18
 43 [-]: MOVE      R0 R19       ; R0 := R19
 44 [-]: MOVE      R0 R20       ; R0 := R20
 45 [-]: MOVE      R0 R21       ; R0 := R21
 46 [-]: MOVE      R0 R22       ; R0 := R22
 47 [-]: MOVE      R0 R23       ; R0 := R23
 48 [-]: CLOSURE   R31 1        ; R31 := closure(Function #2)
 49 [-]: MOVE      R0 R17       ; R0 := R17
 50 [-]: MOVE      R0 R19       ; R0 := R19
 51 [-]: MOVE      R0 R20       ; R0 := R20
 52 [-]: MOVE      R0 R21       ; R0 := R21
 53 [-]: MOVE      R0 R23       ; R0 := R23
 54 [-]: MOVE      R0 R16       ; R0 := R16
 55 [-]: MOVE      R0 R9        ; R0 := R9
 56 [-]: MOVE      R0 R5        ; R0 := R5
 57 [-]: MOVE      R0 R11       ; R0 := R11
 58 [-]: CLOSURE   R32 2        ; R32 := closure(Function #3)
 59 [-]: MOVE      R0 R27       ; R0 := R27
 60 [-]: MOVE      R0 R28       ; R0 := R28
 61 [-]: MOVE      R0 R29       ; R0 := R29
 62 [-]: CLOSURE   R33 3        ; R33 := closure(Function #4)
 63 [-]: MOVE      R0 R26       ; R0 := R26
 64 [-]: MOVE      R0 R27       ; R0 := R27
 65 [-]: MOVE      R0 R28       ; R0 := R28
 66 [-]: MOVE      R0 R29       ; R0 := R29
 67 [-]: CLOSURE   R34 4        ; R34 := closure(Function #5)
 68 [-]: MOVE      R0 R32       ; R0 := R32
 69 [-]: MOVE      R0 R26       ; R0 := R26
 70 [-]: MOVE      R0 R27       ; R0 := R27
 71 [-]: MOVE      R0 R28       ; R0 := R28
 72 [-]: MOVE      R0 R33       ; R0 := R33
 73 [-]: MOVE      R0 R29       ; R0 := R29
 74 [-]: CLOSURE   R35 5        ; R35 := closure(Function #6)
 75 [-]: MOVE      R0 R30       ; R0 := R30
 76 [-]: MOVE      R0 R17       ; R0 := R17
 77 [-]: MOVE      R0 R19       ; R0 := R19
 78 [-]: MOVE      R0 R20       ; R0 := R20
 79 [-]: MOVE      R0 R21       ; R0 := R21
 80 [-]: MOVE      R0 R23       ; R0 := R23
 81 [-]: MOVE      R0 R16       ; R0 := R16
 82 [-]: MOVE      R0 R24       ; R0 := R24
 83 [-]: MOVE      R0 R25       ; R0 := R25
 84 [-]: MOVE      R0 R31       ; R0 := R31
 85 [-]: MOVE      R0 R34       ; R0 := R34
 86 [-]: SETGLOBAL R35 K10      ; GetAbilityUpgradeLevelInfo := R35
 87 [-]: CLOSURE   R35 6        ; R35 := closure(Function #7)
 88 [-]: MOVE      R0 R32       ; R0 := R32
 89 [-]: MOVE      R0 R26       ; R0 := R26
 90 [-]: MOVE      R0 R27       ; R0 := R27
 91 [-]: MOVE      R0 R28       ; R0 := R28
 92 [-]: MOVE      R0 R29       ; R0 := R29
 93 [-]: SETGLOBAL R35 K11      ; GetAugmentDescriptionInfo := R35
 94 [-]: CLOSURE   R35 7        ; R35 := closure(Function #8)
 95 [-]: SETGLOBAL R35 K12      ; NpcEvaluateAbility := R35
 96 [-]: CLOSURE   R35 8        ; R35 := closure(Function #9)
 97 [-]: MOVE      R0 R1        ; R0 := R1
 98 [-]: MOVE      R0 R16       ; R0 := R16
 99 [-]: SETGLOBAL R35 K13      ; InitializeAbility := R35
100 [-]: CLOSURE   R35 9        ; R35 := closure(Function #10)
101 [-]: MOVE      R0 R3        ; R0 := R3
102 [-]: CLOSURE   R36 10       ; R36 := closure(Function #11)
103 [-]: MOVE      R0 R35       ; R0 := R35
104 [-]: MOVE      R0 R2        ; R0 := R2
105 [-]: CLOSURE   R37 11       ; R37 := closure(Function #12)
106 [-]: MOVE      R0 R30       ; R0 := R30
107 [-]: MOVE      R0 R31       ; R0 := R31
108 [-]: MOVE      R0 R1        ; R0 := R1
109 [-]: MOVE      R0 R36       ; R0 := R36
110 [-]: CLOSURE   R38 12       ; R38 := closure(Function #13)
111 [-]: SETGLOBAL R38 K14      ; EvalBusyLoop := R38
112 [-]: CLOSURE   R38 13       ; R38 := closure(Function #14)
113 [-]: MOVE      R0 R16       ; R0 := R16
114 [-]: MOVE      R0 R0        ; R0 := R0
115 [-]: MOVE      R0 R37       ; R0 := R37
116 [-]: MOVE      R0 R1        ; R0 := R1
117 [-]: MOVE      R0 R7        ; R0 := R7
118 [-]: SETGLOBAL R38 K15      ; EvaluateAbility := R38
119 [-]: CLOSURE   R38 14       ; R38 := closure(Function #15)
120 [-]: MOVE      R0 R0        ; R0 := R0
121 [-]: MOVE      R0 R27       ; R0 := R27
122 [-]: MOVE      R0 R28       ; R0 := R28
123 [-]: SETGLOBAL R38 K16      ; DoAugment := R38
124 [-]: CLOSURE   R38 15       ; R38 := closure(Function #16)
125 [-]: MOVE      R0 R30       ; R0 := R30
126 [-]: MOVE      R0 R17       ; R0 := R17
127 [-]: MOVE      R0 R19       ; R0 := R19
128 [-]: MOVE      R0 R20       ; R0 := R20
129 [-]: MOVE      R0 R21       ; R0 := R21
130 [-]: MOVE      R0 R23       ; R0 := R23
131 [-]: MOVE      R0 R24       ; R0 := R24
132 [-]: MOVE      R0 R25       ; R0 := R25
133 [-]: MOVE      R0 R31       ; R0 := R31
134 [-]: MOVE      R0 R32       ; R0 := R32
135 [-]: MOVE      R0 R26       ; R0 := R26
136 [-]: MOVE      R0 R27       ; R0 := R27
137 [-]: MOVE      R0 R28       ; R0 := R28
138 [-]: MOVE      R0 R33       ; R0 := R33
139 [-]: MOVE      R0 R16       ; R0 := R16
140 [-]: MOVE      R0 R7        ; R0 := R7
141 [-]: MOVE      R0 R0        ; R0 := R0
142 [-]: MOVE      R0 R1        ; R0 := R1
143 [-]: MOVE      R0 R6        ; R0 := R6
144 [-]: MOVE      R0 R18       ; R0 := R18
145 [-]: SETGLOBAL R38 K17      ; ActivateAbility := R38
146 [-]: CLOSURE   R38 16       ; R38 := closure(Function #17)
147 [-]: MOVE      R0 R1        ; R0 := R1
148 [-]: SETGLOBAL R38 K18      ; DeactivateAbility := R38
149 [-]: CLOSURE   R38 17       ; R38 := closure(Function #18)
150 [-]: MOVE      R0 R15       ; R0 := R15
151 [-]: MOVE      R0 R1        ; R0 := R1
152 [-]: MOVE      R0 R19       ; R0 := R19
153 [-]: MOVE      R0 R20       ; R0 := R20
154 [-]: MOVE      R0 R21       ; R0 := R21
155 [-]: MOVE      R0 R32       ; R0 := R32
156 [-]: MOVE      R0 R29       ; R0 := R29
157 [-]: MOVE      R0 R33       ; R0 := R33
158 [-]: MOVE      R0 R35       ; R0 := R35
159 [-]: MOVE      R0 R22       ; R0 := R22
160 [-]: MOVE      R0 R18       ; R0 := R18
161 [-]: MOVE      R0 R23       ; R0 := R23
162 [-]: MOVE      R0 R4        ; R0 := R4
163 [-]: MOVE      R0 R10       ; R0 := R10
164 [-]: MOVE      R0 R13       ; R0 := R13
165 [-]: MOVE      R0 R8        ; R0 := R8
166 [-]: MOVE      R0 R25       ; R0 := R25
167 [-]: MOVE      R0 R24       ; R0 := R24
168 [-]: SETGLOBAL R38 K19      ; TrackSpores := R38
169 [-]: CLOSURE   R38 18       ; R38 := closure(Function #19)
170 [-]: MOVE      R0 R15       ; R0 := R15
171 [-]: MOVE      R0 R36       ; R0 := R36
172 [-]: MOVE      R0 R1        ; R0 := R1
173 [-]: MOVE      R0 R14       ; R0 := R14
174 [-]: MOVE      R0 R12       ; R0 := R12
175 [-]: SETGLOBAL R38 K20      ; Grow := R38
176 [-]: CLOSURE   R38 19       ; R38 := closure(Function #20)
177 [-]: SETGLOBAL R38 K21      ; ClientEnd := R38
178 [-]: CLOSURE   R38 20       ; R38 := closure(Function #21)
179 [-]: SETGLOBAL R38 K22      ; ClientDrainStart := R38
180 [-]: CLOSURE   R38 21       ; R38 := closure(Function #22)
181 [-]: SETGLOBAL R38 K23      ; ClientDrainStop := R38
182 [-]: RETURN    R0 1         ; return 


; Function #1:
;
; Name:            
; Defined at line: 59
; #Upvalues:       8
; #Parameters:     1
; Is_vararg:       0
; Max Stack Size:  2

  1 [-]: GETUPVAL  R1 U0        ; R1 := U0
  2 [-]: GETTABLE  R1 R1 K0     ; R1 := R1[0x32316a21]
  3 [-]: CALL      R1 1 2       ; R1 := R1()
  4 [-]: TEST      R1 1         ; if R1 then PC := 72
  5 [-]: JMP       72           ; PC := 72
  6 [-]: EQ        0 R0 K1      ; if R0 ~= 1.000000 then PC := 23
  7 [-]: JMP       23           ; PC := 23
  8 [-]: LOADK     R1 30        ; R1 := 30.000000
  9 [-]: SETUPVAL  R1 U1        ; U82 := 
 10 [-]: LOADK     R1 2         ; R1 := 2.000000
 11 [-]: SETUPVAL  R1 U2        ; U82 := 
 12 [-]: LOADK     R1 6         ; R1 := 6.000000
 13 [-]: SETUPVAL  R1 U3        ; U82 := 
 14 [-]: LOADK     R1 1         ; R1 := 1.000000
 15 [-]: SETUPVAL  R1 U4        ; U82 := 
 16 [-]: LOADK     R1 K2        ; R1 := 0.200000
 17 [-]: SETUPVAL  R1 U5        ; U82 := 
 18 [-]: LOADK     R1 1         ; R1 := 1.000000
 19 [-]: SETUPVAL  R1 U6        ; U82 := 
 20 [-]: LOADK     R1 10        ; R1 := 10.000000
 21 [-]: SETUPVAL  R1 U7        ; U82 := 
 22 [-]: JMP       157          ; PC := 157
 23 [-]: EQ        0 R0 K3      ; if R0 ~= 2.000000 then PC := 40
 24 [-]: JMP       40           ; PC := 40
 25 [-]: LOADK     R1 40        ; R1 := 40.000000
 26 [-]: SETUPVAL  R1 U1        ; U82 := 
 27 [-]: LOADK     R1 2         ; R1 := 2.000000
 28 [-]: SETUPVAL  R1 U2        ; U82 := 
 29 [-]: LOADK     R1 8         ; R1 := 8.000000
 30 [-]: SETUPVAL  R1 U3        ; U82 := 
 31 [-]: LOADK     R1 1         ; R1 := 1.250000
 32 [-]: SETUPVAL  R1 U4        ; U82 := 
 33 [-]: LOADK     R1 K4        ; R1 := 0.300000
 34 [-]: SETUPVAL  R1 U5        ; U82 := 
 35 [-]: LOADK     R1 1         ; R1 := 1.000000
 36 [-]: SETUPVAL  R1 U6        ; U82 := 
 37 [-]: LOADK     R1 12        ; R1 := 12.000000
 38 [-]: SETUPVAL  R1 U7        ; U82 := 
 39 [-]: JMP       157          ; PC := 157
 40 [-]: EQ        0 R0 K5      ; if R0 ~= 3.000000 then PC := 57
 41 [-]: JMP       57           ; PC := 57
 42 [-]: LOADK     R1 50        ; R1 := 50.000000
 43 [-]: SETUPVAL  R1 U1        ; U82 := 
 44 [-]: LOADK     R1 3         ; R1 := 3.000000
 45 [-]: SETUPVAL  R1 U2        ; U82 := 
 46 [-]: LOADK     R1 8         ; R1 := 8.000000
 47 [-]: SETUPVAL  R1 U3        ; U82 := 
 48 [-]: LOADK     R1 1         ; R1 := 1.500000
 49 [-]: SETUPVAL  R1 U4        ; U82 := 
 50 [-]: LOADK     R1 K6        ; R1 := 0.400000
 51 [-]: SETUPVAL  R1 U5        ; U82 := 
 52 [-]: LOADK     R1 1         ; R1 := 1.000000
 53 [-]: SETUPVAL  R1 U6        ; U82 := 
 54 [-]: LOADK     R1 14        ; R1 := 14.000000
 55 [-]: SETUPVAL  R1 U7        ; U82 := 
 56 [-]: JMP       157          ; PC := 157
 57 [-]: LOADK     R1 60        ; R1 := 60.000000
 58 [-]: SETUPVAL  R1 U1        ; U82 := 
 59 [-]: LOADK     R1 3         ; R1 := 3.000000
 60 [-]: SETUPVAL  R1 U2        ; U82 := 
 61 [-]: LOADK     R1 10        ; R1 := 10.000000
 62 [-]: SETUPVAL  R1 U3        ; U82 := 
 63 [-]: LOADK     R1 2         ; R1 := 2.000000
 64 [-]: SETUPVAL  R1 U4        ; U82 := 
 65 [-]: LOADK     R1 0         ; R1 := 0.500000
 66 [-]: SETUPVAL  R1 U5        ; U82 := 
 67 [-]: LOADK     R1 1         ; R1 := 1.000000
 68 [-]: SETUPVAL  R1 U6        ; U82 := 
 69 [-]: LOADK     R1 16        ; R1 := 16.000000
 70 [-]: SETUPVAL  R1 U7        ; U82 := 
 71 [-]: JMP       157          ; PC := 157
 72 [-]: GETUPVAL  R1 U0        ; R1 := U0
 73 [-]: GETTABLE  R1 R1 K7     ; R1 := R1[0xe4ae0e66]
 74 [-]: CALL      R1 1 2       ; R1 := R1()
 75 [-]: TEST      R1 0         ; if not R1 then PC := 92
 76 [-]: JMP       92           ; PC := 92
 77 [-]: LOADK     R1 30        ; R1 := 30.000000
 78 [-]: SETUPVAL  R1 U1        ; U82 := 
 79 [-]: LOADK     R1 1         ; R1 := 1.000000
 80 [-]: SETUPVAL  R1 U2        ; U82 := 
 81 [-]: LOADK     R1 2         ; R1 := 2.000000
 82 [-]: SETUPVAL  R1 U3        ; U82 := 
 83 [-]: LOADK     R1 2         ; R1 := 2.000000
 84 [-]: SETUPVAL  R1 U4        ; U82 := 
 85 [-]: LOADK     R1 0         ; R1 := 0.000000
 86 [-]: SETUPVAL  R1 U5        ; U82 := 
 87 [-]: LOADK     R1 1         ; R1 := 1.000000
 88 [-]: SETUPVAL  R1 U6        ; U82 := 
 89 [-]: LOADK     R1 0         ; R1 := 0.000000
 90 [-]: SETUPVAL  R1 U7        ; U82 := 
 91 [-]: JMP       157          ; PC := 157
 92 [-]: EQ        0 R0 K1      ; if R0 ~= 1.000000 then PC := 109
 93 [-]: JMP       109          ; PC := 109
 94 [-]: LOADK     R1 40        ; R1 := 40.000000
 95 [-]: SETUPVAL  R1 U1        ; U82 := 
 96 [-]: LOADK     R1 1         ; R1 := 1.000000
 97 [-]: SETUPVAL  R1 U2        ; U82 := 
 98 [-]: LOADK     R1 5         ; R1 := 5.000000
 99 [-]: SETUPVAL  R1 U3        ; U82 := 
100 [-]: LOADK     R1 1         ; R1 := 1.000000
101 [-]: SETUPVAL  R1 U4        ; U82 := 
102 [-]: LOADK     R1 1         ; R1 := 1.000000
103 [-]: SETUPVAL  R1 U5        ; U82 := 
104 [-]: LOADK     R1 1         ; R1 := 1.000000
105 [-]: SETUPVAL  R1 U6        ; U82 := 
106 [-]: LOADK     R1 10        ; R1 := 10.000000
107 [-]: SETUPVAL  R1 U7        ; U82 := 
108 [-]: JMP       157          ; PC := 157
109 [-]: EQ        0 R0 K3      ; if R0 ~= 2.000000 then PC := 126
110 [-]: JMP       126          ; PC := 126
111 [-]: LOADK     R1 40        ; R1 := 40.000000
112 [-]: SETUPVAL  R1 U1        ; U82 := 
113 [-]: LOADK     R1 1         ; R1 := 1.000000
114 [-]: SETUPVAL  R1 U2        ; U82 := 
115 [-]: LOADK     R1 10        ; R1 := 10.000000
116 [-]: SETUPVAL  R1 U3        ; U82 := 
117 [-]: LOADK     R1 1         ; R1 := 1.000000
118 [-]: SETUPVAL  R1 U4        ; U82 := 
119 [-]: LOADK     R1 1         ; R1 := 1.000000
120 [-]: SETUPVAL  R1 U5        ; U82 := 
121 [-]: LOADK     R1 1         ; R1 := 1.000000
122 [-]: SETUPVAL  R1 U6        ; U82 := 
123 [-]: LOADK     R1 10        ; R1 := 10.000000
124 [-]: SETUPVAL  R1 U7        ; U82 := 
125 [-]: JMP       157          ; PC := 157
126 [-]: EQ        0 R0 K5      ; if R0 ~= 3.000000 then PC := 143
127 [-]: JMP       143          ; PC := 143
128 [-]: LOADK     R1 40        ; R1 := 40.000000
129 [-]: SETUPVAL  R1 U1        ; U82 := 
130 [-]: LOADK     R1 1         ; R1 := 1.000000
131 [-]: SETUPVAL  R1 U2        ; U82 := 
132 [-]: LOADK     R1 15        ; R1 := 15.000000
133 [-]: SETUPVAL  R1 U3        ; U82 := 
134 [-]: LOADK     R1 1         ; R1 := 1.000000
135 [-]: SETUPVAL  R1 U4        ; U82 := 
136 [-]: LOADK     R1 1         ; R1 := 1.000000
137 [-]: SETUPVAL  R1 U5        ; U82 := 
138 [-]: LOADK     R1 1         ; R1 := 1.000000
139 [-]: SETUPVAL  R1 U6        ; U82 := 
140 [-]: LOADK     R1 10        ; R1 := 10.000000
141 [-]: SETUPVAL  R1 U7        ; U82 := 
142 [-]: JMP       157          ; PC := 157
143 [-]: LOADK     R1 40        ; R1 := 40.000000
144 [-]: SETUPVAL  R1 U1        ; U82 := 
145 [-]: LOADK     R1 1         ; R1 := 1.000000
146 [-]: SETUPVAL  R1 U2        ; U82 := 
147 [-]: LOADK     R1 20        ; R1 := 20.000000
148 [-]: SETUPVAL  R1 U3        ; U82 := 
149 [-]: LOADK     R1 1         ; R1 := 1.000000
150 [-]: SETUPVAL  R1 U4        ; U82 := 
151 [-]: LOADK     R1 1         ; R1 := 1.000000
152 [-]: SETUPVAL  R1 U5        ; U82 := 
153 [-]: LOADK     R1 1         ; R1 := 1.000000
154 [-]: SETUPVAL  R1 U6        ; U82 := 
155 [-]: LOADK     R1 10        ; R1 := 10.000000
156 [-]: SETUPVAL  R1 U7        ; U82 := 
157 [-]: RETURN    R0 1         ; return 


; Function #2:
;
; Name:            
; Defined at line: 141
; #Upvalues:       9
; #Parameters:     1
; Is_vararg:       0
; Max Stack Size:  22

  1 [-]: GETUPVAL  R1 U0        ; R1 := U0
  2 [-]: GETGLOBAL R2 K0        ; R2 := 0x34291f5c
  3 [-]: GETTABLE  R2 R2 K1     ; R2 := R2[0x7258f36f]
  4 [-]: GETUPVAL  R3 U1        ; R3 := U1
  5 [-]: CALL      R2 2 2       ; R2 := R2(R3)
  6 [-]: GETUPVAL  R3 U2        ; R3 := U2
  7 [-]: GETUPVAL  R4 U3        ; R4 := U3
  8 [-]: GETUPVAL  R5 U4        ; R5 := U4
  9 [-]: GETUPVAL  R6 U5        ; R6 := U5
 10 [-]: GETUPVAL  R7 U6        ; R7 := U6
 11 [-]: GETUPVAL  R8 U7        ; R8 := U7
 12 [-]: GETGLOBAL R9 K2        ; R9 := 0x7b998233
 13 [-]: MOVE      R10 R0       ; R10 := R0
 14 [-]: CALL      R9 2 2       ; R9 := R9(R10)
 15 [-]: TEST      R9 1         ; if R9 then PC := 94
 16 [-]: JMP       94           ; PC := 94
 17 [-]: SELF      R9 R0 K3     ; R10 := R0; R9 := R0[0xde321e6f]
 18 [-]: CALL      R9 2 2       ; R9 := R9(R10)
 19 [-]: SELF      R10 R9 K4    ; R11 := R9; R10 := R9[0xf7d48ee0]
 20 [-]: CALL      R10 2 2      ; R10 := R10(R11)
 21 [-]: GETGLOBAL R11 K2       ; R11 := 0x7b998233
 22 [-]: MOVE      R12 R10      ; R12 := R10
 23 [-]: CALL      R11 2 2      ; R11 := R11(R12)
 24 [-]: TEST      R11 1        ; if R11 then PC := 94
 25 [-]: JMP       94           ; PC := 94
 26 [-]: SELF      R11 R10 K5   ; R12 := R10; R11 := R10[0xcde10c4a]
 27 [-]: CALL      R11 2 2      ; R11 := R11(R12)
 28 [-]: SELF      R12 R9 K6    ; R13 := R9; R12 := R9[0xe9f54086]
 29 [-]: GETUPVAL  R14 U0       ; R14 := U0
 30 [-]: LOADK     R15 9        ; R15 := 9.000000
 31 [-]: MOVE      R16 R11      ; R16 := R11
 32 [-]: MOVE      R17 R10      ; R17 := R10
 33 [-]: CALL      R12 6 2      ; R12 := R12(R13,R14,R15,R16,R17)
 34 [-]: MOVE      R1 R12       ; R1 := R12
 35 [-]: SELF      R12 R9 K8    ; R13 := R9; R12 := R9[0x54ba011d]
 36 [-]: MOVE      R14 R2       ; R14 := R2
 37 [-]: LOADK     R15 10       ; R15 := 10.000000
 38 [-]: MOVE      R16 R11      ; R16 := R11
 39 [-]: MOVE      R17 R10      ; R17 := R10
 40 [-]: CALL      R12 6 1      ; R12(R13,R14,R15,R16,R17)
 41 [-]: SELF      R12 R9 K6    ; R13 := R9; R12 := R9[0xe9f54086]
 42 [-]: GETUPVAL  R14 U2       ; R14 := U2
 43 [-]: LOADK     R15 10       ; R15 := 10.000000
 44 [-]: MOVE      R16 R11      ; R16 := R11
 45 [-]: MOVE      R17 R10      ; R17 := R10
 46 [-]: CALL      R12 6 2      ; R12 := R12(R13,R14,R15,R16,R17)
 47 [-]: MOVE      R3 R12       ; R3 := R12
 48 [-]: SELF      R12 R9 K6    ; R13 := R9; R12 := R9[0xe9f54086]
 49 [-]: GETUPVAL  R14 U3       ; R14 := U3
 50 [-]: LOADK     R15 10       ; R15 := 10.000000
 51 [-]: MOVE      R16 R11      ; R16 := R11
 52 [-]: MOVE      R17 R10      ; R17 := R10
 53 [-]: CALL      R12 6 2      ; R12 := R12(R13,R14,R15,R16,R17)
 54 [-]: MOVE      R4 R12       ; R4 := R12
 55 [-]: SELF      R12 R9 K6    ; R13 := R9; R12 := R9[0xe9f54086]
 56 [-]: GETUPVAL  R14 U4       ; R14 := U4
 57 [-]: LOADK     R15 9        ; R15 := 9.000000
 58 [-]: MOVE      R16 R11      ; R16 := R11
 59 [-]: MOVE      R17 R10      ; R17 := R10
 60 [-]: CALL      R12 6 2      ; R12 := R12(R13,R14,R15,R16,R17)
 61 [-]: MOVE      R5 R12       ; R5 := R12
 62 [-]: SELF      R12 R10 K9   ; R13 := R10; R12 := R10[0xf5c3424f]
 63 [-]: GETUPVAL  R14 U5       ; R14 := U5
 64 [-]: CALL      R12 3 2      ; R12 := R12(R13,R14)
 65 [-]: MOVE      R6 R12       ; R6 := R12
 66 [-]: SELF      R12 R9 K6    ; R13 := R9; R12 := R9[0xe9f54086]
 67 [-]: LOADK     R14 1        ; R14 := 1.000000
 68 [-]: LOADK     R15 3        ; R15 := 3.000000
 69 [-]: MOVE      R16 R11      ; R16 := R11
 70 [-]: MOVE      R17 R10      ; R17 := R10
 71 [-]: CALL      R12 6 2      ; R12 := R12(R13,R14,R15,R16,R17)
 72 [-]: SUB       R12 R12 K10  ; R12 := R12 - 1.000000
 73 [-]: GETGLOBAL R13 K11      ; R13 := 0x42dcc9f5
 74 [-]: GETUPVAL  R14 U8       ; R14 := U8
 75 [-]: MUL       R14 R12 R14  ; R14 := R12 * R14
 76 [-]: GETUPVAL  R15 U8       ; R15 := U8
 77 [-]: UNM       R15 R15      ; R15 := ^ R15
 78 [-]: GETUPVAL  R16 U8       ; R16 := U8
 79 [-]: CALL      R13 4 2      ; R13 := R13(R14,R15,R16)
 80 [-]: SUB       R7 R7 R13    ; R7 := R7 - R13
 81 [-]: SELF      R13 R9 K6    ; R14 := R9; R13 := R9[0xe9f54086]
 82 [-]: LOADK     R15 1        ; R15 := 1.000000
 83 [-]: LOADK     R16 10       ; R16 := 10.000000
 84 [-]: MOVE      R17 R11      ; R17 := R11
 85 [-]: MOVE      R18 R10      ; R18 := R10
 86 [-]: CALL      R13 6 2      ; R13 := R13(R14,R15,R16,R17,R18)
 87 [-]: SUB       R13 R13 K10  ; R13 := R13 - 1.000000
 88 [-]: GETGLOBAL R14 K11      ; R14 := 0x42dcc9f5
 89 [-]: MUL       R15 R13 K12  ; R15 := R13 * 0.100000
 90 [-]: LOADK     R16 K13      ; R16 := -0.149900
 91 [-]: LOADK     R17 K14      ; R17 := 0.149900
 92 [-]: CALL      R14 4 2      ; R14 := R14(R15,R16,R17)
 93 [-]: SUB       R8 R8 R14    ; R8 := R8 - R14
 94 [-]: MOVE      R14 R1       ; R14 := R1
 95 [-]: MOVE      R15 R2       ; R15 := R2
 96 [-]: MOVE      R16 R3       ; R16 := R3
 97 [-]: MOVE      R17 R4       ; R17 := R4
 98 [-]: MOVE      R18 R5       ; R18 := R5
 99 [-]: MOVE      R19 R6       ; R19 := R6
100 [-]: MOVE      R20 R7       ; R20 := R7
101 [-]: MOVE      R21 R8       ; R21 := R8
102 [-]: RETURN    R14 9        ; return R14,R15,R16,R17,R18,R19,R20,R21
103 [-]: RETURN    R0 1         ; return 


; Function #3:
;
; Name:            
; Defined at line: 172
; #Upvalues:       3
; #Parameters:     2
; Is_vararg:       0
; Max Stack Size:  3

  1 [-]: EQ        0 R1 K1      ; if R1 ~= 1.000000 then PC := 29
  2 [-]: JMP       29           ; PC := 29
  3 [-]: EQ        0 R0 K1      ; if R0 ~= 1.000000 then PC := 10
  4 [-]: JMP       10           ; PC := 10
  5 [-]: LOADK     R2 0         ; R2 := 0.500000
  6 [-]: SETUPVAL  R2 U0        ; U82 := 
  7 [-]: LOADK     R2 28        ; R2 := 28.000000
  8 [-]: SETUPVAL  R2 U1        ; U82 := 
  9 [-]: JMP       48           ; PC := 48
 10 [-]: EQ        0 R0 K2      ; if R0 ~= 2.000000 then PC := 17
 11 [-]: JMP       17           ; PC := 17
 12 [-]: LOADK     R2 K3        ; R2 := 0.650000
 13 [-]: SETUPVAL  R2 U0        ; U82 := 
 14 [-]: LOADK     R2 32        ; R2 := 32.000000
 15 [-]: SETUPVAL  R2 U1        ; U82 := 
 16 [-]: JMP       48           ; PC := 48
 17 [-]: EQ        0 R0 K4      ; if R0 ~= 3.000000 then PC := 24
 18 [-]: JMP       24           ; PC := 24
 19 [-]: LOADK     R2 K5        ; R2 := 0.800000
 20 [-]: SETUPVAL  R2 U0        ; U82 := 
 21 [-]: LOADK     R2 36        ; R2 := 36.000000
 22 [-]: SETUPVAL  R2 U1        ; U82 := 
 23 [-]: JMP       48           ; PC := 48
 24 [-]: LOADK     R2 1         ; R2 := 1.000000
 25 [-]: SETUPVAL  R2 U0        ; U82 := 
 26 [-]: LOADK     R2 40        ; R2 := 40.000000
 27 [-]: SETUPVAL  R2 U1        ; U82 := 
 28 [-]: JMP       48           ; PC := 48
 29 [-]: EQ        0 R1 K2      ; if R1 ~= 2.000000 then PC := 48
 30 [-]: JMP       48           ; PC := 48
 31 [-]: EQ        0 R0 K1      ; if R0 ~= 1.000000 then PC := 36
 32 [-]: JMP       36           ; PC := 36
 33 [-]: LOADK     R2 10        ; R2 := 10.000000
 34 [-]: SETUPVAL  R2 U2        ; U82 := 
 35 [-]: JMP       48           ; PC := 48
 36 [-]: EQ        0 R0 K2      ; if R0 ~= 2.000000 then PC := 41
 37 [-]: JMP       41           ; PC := 41
 38 [-]: LOADK     R2 20        ; R2 := 20.000000
 39 [-]: SETUPVAL  R2 U2        ; U82 := 
 40 [-]: JMP       48           ; PC := 48
 41 [-]: EQ        0 R0 K4      ; if R0 ~= 3.000000 then PC := 46
 42 [-]: JMP       46           ; PC := 46
 43 [-]: LOADK     R2 30        ; R2 := 30.000000
 44 [-]: SETUPVAL  R2 U2        ; U82 := 
 45 [-]: JMP       48           ; PC := 48
 46 [-]: LOADK     R2 40        ; R2 := 40.000000
 47 [-]: SETUPVAL  R2 U2        ; U82 := 
 48 [-]: RETURN    R0 1         ; return 


; Function #4:
;
; Name:            
; Defined at line: 200
; #Upvalues:       4
; #Parameters:     2
; Is_vararg:       0
; Max Stack Size:  14

  1 [-]: SELF      R2 R0 K0     ; R3 := R0; R2 := R0[0xde321e6f]
  2 [-]: CALL      R2 2 2       ; R2 := R2(R3)
  3 [-]: SELF      R3 R2 K1     ; R4 := R2; R3 := R2[0xf7d48ee0]
  4 [-]: CALL      R3 2 2       ; R3 := R3(R4)
  5 [-]: GETGLOBAL R4 K2        ; R4 := 0x7b998233
  6 [-]: MOVE      R5 R3        ; R5 := R3
  7 [-]: CALL      R4 2 2       ; R4 := R4(R5)
  8 [-]: TEST      R4 1         ; if R4 then PC := 14
  9 [-]: JMP       14           ; PC := 14
 10 [-]: SELF      R4 R3 K3     ; R5 := R3; R4 := R3[0xcde10c4a]
 11 [-]: CALL      R4 2 2       ; R4 := R4(R5)
 12 [-]: TEST      R4 1         ; if R4 then PC := 15
 13 [-]: JMP       15           ; PC := 15
 14 [-]: LOADNIL   R4 R4        ; R4 := nil
 15 [-]: EQ        0 R1 K5      ; if R1 ~= 1.000000 then PC := 40
 16 [-]: JMP       40           ; PC := 40
 17 [-]: SELF      R5 R2 K6     ; R6 := R2; R5 := R2[0xe9f54086]
 18 [-]: GETUPVAL  R7 U0        ; R7 := U0
 19 [-]: LOADK     R8 9         ; R8 := 9.000000
 20 [-]: MOVE      R9 R4        ; R9 := R4
 21 [-]: MOVE      R10 R3       ; R10 := R3
 22 [-]: CALL      R5 6 2       ; R5 := R5(R6,R7,R8,R9,R10)
 23 [-]: SELF      R6 R2 K6     ; R7 := R2; R6 := R2[0xe9f54086]
 24 [-]: GETUPVAL  R8 U1        ; R8 := U1
 25 [-]: LOADK     R9 10        ; R9 := 10.000000
 26 [-]: MOVE      R10 R4       ; R10 := R4
 27 [-]: MOVE      R11 R3       ; R11 := R3
 28 [-]: CALL      R6 6 2       ; R6 := R6(R7,R8,R9,R10,R11)
 29 [-]: SELF      R7 R2 K6     ; R8 := R2; R7 := R2[0xe9f54086]
 30 [-]: GETUPVAL  R9 U2        ; R9 := U2
 31 [-]: LOADK     R10 3        ; R10 := 3.000000
 32 [-]: MOVE      R11 R4       ; R11 := R4
 33 [-]: MOVE      R12 R3       ; R12 := R3
 34 [-]: CALL      R7 6 2       ; R7 := R7(R8,R9,R10,R11,R12)
 35 [-]: MOVE      R8 R5        ; R8 := R5
 36 [-]: MOVE      R9 R6        ; R9 := R6
 37 [-]: MOVE      R10 R7       ; R10 := R7
 38 [-]: RETURN    R8 4         ; return R8,R9,R10
 39 [-]: JMP       49           ; PC := 49
 40 [-]: EQ        0 R1 K8      ; if R1 ~= 2.000000 then PC := 49
 41 [-]: JMP       49           ; PC := 49
 42 [-]: SELF      R8 R2 K6     ; R9 := R2; R8 := R2[0xe9f54086]
 43 [-]: GETUPVAL  R10 U3       ; R10 := U3
 44 [-]: LOADK     R11 9        ; R11 := 9.000000
 45 [-]: MOVE      R12 R4       ; R12 := R4
 46 [-]: MOVE      R13 R3       ; R13 := R3
 47 [-]: CALL      R8 6 2       ; R8 := R8(R9,R10,R11,R12,R13)
 48 [-]: RETURN    R8 2         ; return R8
 49 [-]: LOADNIL   R9 R9        ; R9 := nil
 50 [-]: RETURN    R9 2         ; return R9
 51 [-]: RETURN    R0 1         ; return 


; Function #5:
;
; Name:            
; Defined at line: 218
; #Upvalues:       6
; #Parameters:     1
; Is_vararg:       0
; Max Stack Size:  12

  1 [-]: GETGLOBAL R1 K0        ; R1 := _T
  2 [-]: GETTABLE  R1 R1 K1     ; R1 := R1["AbilityLevelQueryParms"]
  3 [-]: GETTABLE  R1 R1 K2     ; R1 := R1["Avatar"]
  4 [-]: GETGLOBAL R2 K3        ; R2 := 0x7b998233
  5 [-]: MOVE      R3 R1        ; R3 := R1
  6 [-]: CALL      R2 2 2       ; R2 := R2(R3)
  7 [-]: TEST      R2 0         ; if not R2 then PC := 10
  8 [-]: JMP       10           ; PC := 10
  9 [-]: RETURN    R0 1         ; return 
 10 [-]: SELF      R2 R1 K4     ; R3 := R1; R2 := R1[0xde321e6f]
 11 [-]: CALL      R2 2 2       ; R2 := R2(R3)
 12 [-]: SELF      R3 R2 K5     ; R4 := R2; R3 := R2[0xf7d48ee0]
 13 [-]: CALL      R3 2 2       ; R3 := R3(R4)
 14 [-]: GETGLOBAL R4 K3        ; R4 := 0x7b998233
 15 [-]: MOVE      R5 R3        ; R5 := R3
 16 [-]: CALL      R4 2 2       ; R4 := R4(R5)
 17 [-]: TEST      R4 0         ; if not R4 then PC := 20
 18 [-]: JMP       20           ; PC := 20
 19 [-]: RETURN    R0 1         ; return 
 20 [-]: SELF      R4 R3 K6     ; R5 := R3; R4 := R3[0xa2356091]
 21 [-]: GETGLOBAL R6 K0        ; R6 := _T
 22 [-]: GETTABLE  R6 R6 K1     ; R6 := R6["AbilityLevelQueryParms"]
 23 [-]: GETTABLE  R6 R6 K7     ; R6 := R6["Ability"]
 24 [-]: CALL      R4 3 2       ; R4 := R4(R5,R6)
 25 [-]: SELF      R5 R3 K8     ; R6 := R3; R5 := R3[0xd836367c]
 26 [-]: CALL      R5 2 2       ; R5 := R5(R6)
 27 [-]: LE        0 R5 R4      ; if R5 > R4 then PC := 30
 28 [-]: JMP       30           ; PC := 30
 29 [-]: RETURN    R0 1         ; return 
 30 [-]: SELF      R5 R3 K9     ; R6 := R3; R5 := R3[0x5063edc3]
 31 [-]: MOVE      R7 R4        ; R7 := R4
 32 [-]: CALL      R5 3 2       ; R5 := R5(R6,R7)
 33 [-]: LE        0 R5 K10     ; if R5 > 0.000000 then PC := 36
 34 [-]: JMP       36           ; PC := 36
 35 [-]: RETURN    R0 1         ; return 
 36 [-]: SELF      R6 R3 K11    ; R7 := R3; R6 := R3[0x75ecaf0b]
 37 [-]: MOVE      R8 R4        ; R8 := R4
 38 [-]: CALL      R6 3 2       ; R6 := R6(R7,R8)
 39 [-]: GETUPVAL  R7 U0        ; R7 := U0
 40 [-]: MOVE      R8 R5        ; R8 := R5
 41 [-]: MOVE      R9 R6        ; R9 := R6
 42 [-]: CALL      R7 3 1       ; R7(R8,R9)
 43 [-]: EQ        0 R6 K13     ; if R6 ~= 1.000000 then PC := 97
 44 [-]: JMP       97           ; PC := 97
 45 [-]: GETGLOBAL R7 K0        ; R7 := _T
 46 [-]: GETTABLE  R7 R7 K1     ; R7 := R7["AbilityLevelQueryParms"]
 47 [-]: GETTABLE  R7 R7 K14    ; R7 := R7["Modded"]
 48 [-]: TEST      R7 0         ; if not R7 then PC := 57
 49 [-]: JMP       57           ; PC := 57
 50 [-]: GETUPVAL  R7 U4        ; R7 := U4
 51 [-]: MOVE      R8 R1        ; R8 := R1
 52 [-]: MOVE      R9 R6        ; R9 := R6
 53 [-]: CALL      R7 3 4       ; R7,R8,R9 := R7(R8,R9)
 54 [-]: SETUPVAL  R9 U3        ; U82 := 
 55 [-]: SETUPVAL  R8 U2        ; U82 := 
 56 [-]: SETUPVAL  R7 U1        ; U82 := 
 57 [-]: GETGLOBAL R7 K15       ; R7 := 0x33bdd652
 58 [-]: GETTABLE  R7 R7 K16    ; R7 := R7[0x23d5322f]
 59 [-]: MOVE      R8 R0        ; R8 := R0
 60 [-]: NEWTABLE  R9 0 2       ; R9 := {}
 61 [-]: SETTABLE  R9 K17 K18   ; R9["Label"] := "/Lotus/Language/Suits/PoisonAbilityAugment1Name"
 62 [-]: SETTABLE  R9 K19 K20   ; R9["Title"] := true
 63 [-]: CALL      R7 3 1       ; R7(R8,R9)
 64 [-]: GETGLOBAL R7 K15       ; R7 := 0x33bdd652
 65 [-]: GETTABLE  R7 R7 K16    ; R7 := R7[0x23d5322f]
 66 [-]: MOVE      R8 R0        ; R8 := R0
 67 [-]: NEWTABLE  R9 0 3       ; R9 := {}
 68 [-]: SETTABLE  R9 K17 K21   ; R9["Label"] := "/Lotus/Language/Game/ABILITY_RADIUS"
 69 [-]: GETUPVAL  R10 U1       ; R10 := U1
 70 [-]: SETTABLE  R9 K22 R10   ; R9["Value"] := R10
 71 [-]: SETTABLE  R9 K23 K24   ; R9["ValueUnit"] := "/Lotus/Language/Game/UNIT_METER"
 72 [-]: CALL      R7 3 1       ; R7(R8,R9)
 73 [-]: GETGLOBAL R7 K15       ; R7 := 0x33bdd652
 74 [-]: GETTABLE  R7 R7 K16    ; R7 := R7[0x23d5322f]
 75 [-]: MOVE      R8 R0        ; R8 := R0
 76 [-]: NEWTABLE  R9 0 4       ; R9 := {}
 77 [-]: SETTABLE  R9 K17 K25   ; R9["Label"] := "/Lotus/Language/Game/EXTRA_DAMAGE"
 78 [-]: GETGLOBAL R10 K26      ; R10 := 0x5bced4c4
 79 [-]: GETTABLE  R10 R10 K27  ; R10 := R10[0x55f27c30]
 80 [-]: GETUPVAL  R11 U2       ; R11 := U2
 81 [-]: MUL       R11 R11 K28  ; R11 := R11 * 100.000000
 82 [-]: CALL      R10 2 2      ; R10 := R10(R11)
 83 [-]: SETTABLE  R9 K22 R10   ; R9["Value"] := R10
 84 [-]: SETTABLE  R9 K29 K30   ; R9["ValueIcon"] := "<DT_CORROSIVE>"
 85 [-]: SETTABLE  R9 K23 K31   ; R9["ValueUnit"] := "/Lotus/Language/Game/UNIT_PERCENT"
 86 [-]: CALL      R7 3 1       ; R7(R8,R9)
 87 [-]: GETGLOBAL R7 K15       ; R7 := 0x33bdd652
 88 [-]: GETTABLE  R7 R7 K16    ; R7 := R7[0x23d5322f]
 89 [-]: MOVE      R8 R0        ; R8 := R0
 90 [-]: NEWTABLE  R9 0 3       ; R9 := {}
 91 [-]: SETTABLE  R9 K17 K32   ; R9["Label"] := "/Lotus/Language/Game/ABILITY_DURATION"
 92 [-]: GETUPVAL  R10 U3       ; R10 := U3
 93 [-]: SETTABLE  R9 K22 R10   ; R9["Value"] := R10
 94 [-]: SETTABLE  R9 K23 K33   ; R9["ValueUnit"] := "/Lotus/Language/Game/UNIT_SECOND"
 95 [-]: CALL      R7 3 1       ; R7(R8,R9)
 96 [-]: JMP       125          ; PC := 125
 97 [-]: EQ        0 R6 K34     ; if R6 ~= 2.000000 then PC := 125
 98 [-]: JMP       125          ; PC := 125
 99 [-]: GETGLOBAL R7 K0        ; R7 := _T
100 [-]: GETTABLE  R7 R7 K1     ; R7 := R7["AbilityLevelQueryParms"]
101 [-]: GETTABLE  R7 R7 K14    ; R7 := R7["Modded"]
102 [-]: TEST      R7 0         ; if not R7 then PC := 109
103 [-]: JMP       109          ; PC := 109
104 [-]: GETUPVAL  R7 U4        ; R7 := U4
105 [-]: MOVE      R8 R1        ; R8 := R1
106 [-]: MOVE      R9 R6        ; R9 := R6
107 [-]: CALL      R7 3 2       ; R7 := R7(R8,R9)
108 [-]: SETUPVAL  R7 U5        ; U82 := 
109 [-]: GETGLOBAL R7 K15       ; R7 := 0x33bdd652
110 [-]: GETTABLE  R7 R7 K16    ; R7 := R7[0x23d5322f]
111 [-]: MOVE      R8 R0        ; R8 := R0
112 [-]: NEWTABLE  R9 0 2       ; R9 := {}
113 [-]: SETTABLE  R9 K17 K35   ; R9["Label"] := "/Lotus/Language/Suits/PoisonAbilityAugment2Name"
114 [-]: SETTABLE  R9 K19 K20   ; R9["Title"] := true
115 [-]: CALL      R7 3 1       ; R7(R8,R9)
116 [-]: GETGLOBAL R7 K15       ; R7 := 0x33bdd652
117 [-]: GETTABLE  R7 R7 K16    ; R7 := R7[0x23d5322f]
118 [-]: MOVE      R8 R0        ; R8 := R0
119 [-]: NEWTABLE  R9 0 3       ; R9 := {}
120 [-]: SETTABLE  R9 K17 K21   ; R9["Label"] := "/Lotus/Language/Game/ABILITY_RADIUS"
121 [-]: GETUPVAL  R10 U5       ; R10 := U5
122 [-]: SETTABLE  R9 K22 R10   ; R9["Value"] := R10
123 [-]: SETTABLE  R9 K23 K24   ; R9["ValueUnit"] := "/Lotus/Language/Game/UNIT_METER"
124 [-]: CALL      R7 3 1       ; R7(R8,R9)
125 [-]: RETURN    R0 1         ; return 


; Function #6:
;
; Name:            
; Defined at line: 263
; #Upvalues:       11
; #Parameters:     0
; Is_vararg:       0
; Max Stack Size:  8

  1 [-]: GETUPVAL  R0 U0        ; R0 := U0
  2 [-]: GETGLOBAL R1 K0        ; R1 := _T
  3 [-]: GETTABLE  R1 R1 K1     ; R1 := R1["AbilityLevelQueryParms"]
  4 [-]: GETTABLE  R1 R1 K2     ; R1 := R1["Level"]
  5 [-]: CALL      R0 2 1       ; R0(R1)
  6 [-]: GETGLOBAL R0 K0        ; R0 := _T
  7 [-]: GETTABLE  R0 R0 K1     ; R0 := R0["AbilityLevelQueryParms"]
  8 [-]: GETTABLE  R0 R0 K3     ; R0 := R0["Modded"]
  9 [-]: EQ        0 R0 K4      ; if R0 ~= true then PC := 28
 10 [-]: JMP       28           ; PC := 28
 11 [-]: GETUPVAL  R0 U9        ; R0 := U9
 12 [-]: GETGLOBAL R1 K0        ; R1 := _T
 13 [-]: GETTABLE  R1 R1 K1     ; R1 := R1["AbilityLevelQueryParms"]
 14 [-]: GETTABLE  R1 R1 K5     ; R1 := R1["Avatar"]
 15 [-]: CALL      R0 2 9       ; R0,R1,R2,R3,R4,R5,R6,R7 := R0(R1)
 16 [-]: SETUPVAL  R7 U8        ; U82 := 
 17 [-]: SETUPVAL  R6 U7        ; U82 := 
 18 [-]: SETUPVAL  R5 U6        ; U82 := 
 19 [-]: SETUPVAL  R4 U5        ; U82 := 
 20 [-]: SETUPVAL  R3 U4        ; U82 := 
 21 [-]: SETUPVAL  R2 U3        ; U82 := 
 22 [-]: SETUPVAL  R1 U2        ; U82 := 
 23 [-]: SETUPVAL  R0 U1        ; U82 := 
 24 [-]: GETUPVAL  R0 U2        ; R0 := U2
 25 [-]: SELF      R0 R0 K6     ; R1 := R0; R0 := R0[0x838305de]
 26 [-]: CALL      R0 2 2       ; R0 := R0(R1)
 27 [-]: SETUPVAL  R0 U2        ; U82 := 
 28 [-]: NEWTABLE  R0 0 0       ; R0 := {}
 29 [-]: GETGLOBAL R1 K7        ; R1 := 0x33bdd652
 30 [-]: GETTABLE  R1 R1 K8     ; R1 := R1[0x23d5322f]
 31 [-]: MOVE      R2 R0        ; R2 := R0
 32 [-]: NEWTABLE  R3 0 3       ; R3 := {}
 33 [-]: SETTABLE  R3 K9 K10    ; R3["Label"] := "/Lotus/Language/Labels/WEAPON_RANGE"
 34 [-]: GETUPVAL  R4 U1        ; R4 := U1
 35 [-]: SETTABLE  R3 K11 R4    ; R3["Value"] := R4
 36 [-]: SETTABLE  R3 K12 K13   ; R3["ValueUnit"] := "/Lotus/Language/Game/UNIT_METER"
 37 [-]: CALL      R1 3 1       ; R1(R2,R3)
 38 [-]: GETGLOBAL R1 K7        ; R1 := 0x33bdd652
 39 [-]: GETTABLE  R1 R1 K8     ; R1 := R1[0x23d5322f]
 40 [-]: MOVE      R2 R0        ; R2 := R0
 41 [-]: NEWTABLE  R3 0 3       ; R3 := {}
 42 [-]: SETTABLE  R3 K9 K14    ; R3["Label"] := "/Lotus/Language/Game/DPS"
 43 [-]: GETUPVAL  R4 U2        ; R4 := U2
 44 [-]: SETTABLE  R3 K11 R4    ; R3["Value"] := R4
 45 [-]: SETTABLE  R3 K15 K16   ; R3["ValueIcon"] := "<DT_CORROSIVE>"
 46 [-]: CALL      R1 3 1       ; R1(R2,R3)
 47 [-]: GETGLOBAL R1 K7        ; R1 := 0x33bdd652
 48 [-]: GETTABLE  R1 R1 K8     ; R1 := R1[0x23d5322f]
 49 [-]: MOVE      R2 R0        ; R2 := R0
 50 [-]: NEWTABLE  R3 0 3       ; R3 := {}
 51 [-]: SETTABLE  R3 K9 K17    ; R3["Label"] := "/Lotus/Language/Game/GROWTH_RATE"
 52 [-]: GETUPVAL  R4 U3        ; R4 := U3
 53 [-]: SETTABLE  R3 K11 R4    ; R3["Value"] := R4
 54 [-]: SETTABLE  R3 K15 K16   ; R3["ValueIcon"] := "<DT_CORROSIVE>"
 55 [-]: CALL      R1 3 1       ; R1(R2,R3)
 56 [-]: GETGLOBAL R1 K7        ; R1 := 0x33bdd652
 57 [-]: GETTABLE  R1 R1 K8     ; R1 := R1[0x23d5322f]
 58 [-]: MOVE      R2 R0        ; R2 := R0
 59 [-]: NEWTABLE  R3 0 3       ; R3 := {}
 60 [-]: SETTABLE  R3 K9 K18    ; R3["Label"] := "/Lotus/Language/Labels/WEAPON_PROC_CHANCE"
 61 [-]: GETGLOBAL R4 K19       ; R4 := 0x5bced4c4
 62 [-]: GETTABLE  R4 R4 K20    ; R4 := R4[0x55f27c30]
 63 [-]: GETUPVAL  R5 U4        ; R5 := U4
 64 [-]: MUL       R5 R5 K21    ; R5 := R5 * 100.000000
 65 [-]: CALL      R4 2 2       ; R4 := R4(R5)
 66 [-]: SETTABLE  R3 K11 R4    ; R3["Value"] := R4
 67 [-]: SETTABLE  R3 K12 K22   ; R3["ValueUnit"] := "/Lotus/Language/Game/UNIT_PERCENT"
 68 [-]: CALL      R1 3 1       ; R1(R2,R3)
 69 [-]: GETGLOBAL R1 K7        ; R1 := 0x33bdd652
 70 [-]: GETTABLE  R1 R1 K8     ; R1 := R1[0x23d5322f]
 71 [-]: MOVE      R2 R0        ; R2 := R0
 72 [-]: NEWTABLE  R3 0 3       ; R3 := {}
 73 [-]: SETTABLE  R3 K9 K23    ; R3["Label"] := "/Lotus/Language/Game/SPREAD_RADIUS_NO_UNIT"
 74 [-]: GETUPVAL  R4 U5        ; R4 := U5
 75 [-]: SETTABLE  R3 K11 R4    ; R3["Value"] := R4
 76 [-]: SETTABLE  R3 K12 K13   ; R3["ValueUnit"] := "/Lotus/Language/Game/UNIT_METER"
 77 [-]: CALL      R1 3 1       ; R1(R2,R3)
 78 [-]: GETGLOBAL R1 K7        ; R1 := 0x33bdd652
 79 [-]: GETTABLE  R1 R1 K8     ; R1 := R1[0x23d5322f]
 80 [-]: MOVE      R2 R0        ; R2 := R0
 81 [-]: NEWTABLE  R3 0 4       ; R3 := {}
 82 [-]: SETTABLE  R3 K9 K24    ; R3["Label"] := "/Lotus/Language/Game/DECAY_RATE"
 83 [-]: GETGLOBAL R4 K19       ; R4 := 0x5bced4c4
 84 [-]: GETTABLE  R4 R4 K20    ; R4 := R4[0x55f27c30]
 85 [-]: GETUPVAL  R5 U7        ; R5 := U7
 86 [-]: MUL       R5 R5 K21    ; R5 := R5 * 100.000000
 87 [-]: CALL      R4 2 2       ; R4 := R4(R5)
 88 [-]: SETTABLE  R3 K11 R4    ; R3["Value"] := R4
 89 [-]: SETTABLE  R3 K12 K22   ; R3["ValueUnit"] := "/Lotus/Language/Game/UNIT_PERCENT"
 90 [-]: SETTABLE  R3 K25 K4    ; R3["SmallerIsBetter"] := true
 91 [-]: CALL      R1 3 1       ; R1(R2,R3)
 92 [-]: GETGLOBAL R1 K7        ; R1 := 0x33bdd652
 93 [-]: GETTABLE  R1 R1 K8     ; R1 := R1[0x23d5322f]
 94 [-]: MOVE      R2 R0        ; R2 := R0
 95 [-]: NEWTABLE  R3 0 4       ; R3 := {}
 96 [-]: SETTABLE  R3 K9 K26    ; R3["Label"] := "/Lotus/Language/Game/RESET_DECAY"
 97 [-]: GETGLOBAL R4 K19       ; R4 := 0x5bced4c4
 98 [-]: GETTABLE  R4 R4 K20    ; R4 := R4[0x55f27c30]
 99 [-]: GETUPVAL  R5 U8        ; R5 := U8
100 [-]: MUL       R5 R5 K21    ; R5 := R5 * 100.000000
101 [-]: CALL      R4 2 2       ; R4 := R4(R5)
102 [-]: SETTABLE  R3 K11 R4    ; R3["Value"] := R4
103 [-]: SETTABLE  R3 K12 K22   ; R3["ValueUnit"] := "/Lotus/Language/Game/UNIT_PERCENT"
104 [-]: SETTABLE  R3 K25 K4    ; R3["SmallerIsBetter"] := true
105 [-]: CALL      R1 3 1       ; R1(R2,R3)
106 [-]: GETUPVAL  R1 U10       ; R1 := U10
107 [-]: MOVE      R2 R0        ; R2 := R0
108 [-]: CALL      R1 2 1       ; R1(R2)
109 [-]: GETGLOBAL R1 K0        ; R1 := _T
110 [-]: GETTABLE  R1 R1 K1     ; R1 := R1["AbilityLevelQueryParms"]
111 [-]: GETTABLE  R1 R1 K3     ; R1 := R1["Modded"]
112 [-]: SETTABLE  R0 K3 R1     ; R0["Modded"] := R1
113 [-]: GETUPVAL  R1 U6        ; R1 := U6
114 [-]: SETTABLE  R0 K27 R1    ; R0[0x63c599b8] := R1
115 [-]: GETGLOBAL R1 K0        ; R1 := _T
116 [-]: SETTABLE  R1 K28 R0    ; R1[0x6687f6e0] := R0
117 [-]: RETURN    R0 1         ; return 


; Function #7:
;
; Name:            
; Defined at line: 287
; #Upvalues:       5
; #Parameters:     2
; Is_vararg:       0
; Max Stack Size:  6

  1 [-]: NEWTABLE  R2 0 0       ; R2 := {}
  2 [-]: GETUPVAL  R3 U0        ; R3 := U0
  3 [-]: MOVE      R4 R0        ; R4 := R0
  4 [-]: MOVE      R5 R1        ; R5 := R1
  5 [-]: CALL      R3 3 1       ; R3(R4,R5)
  6 [-]: EQ        0 R1 K1      ; if R1 ~= 1.000000 then PC := 21
  7 [-]: JMP       21           ; PC := 21
  8 [-]: NEWTABLE  R3 0 3       ; R3 := {}
  9 [-]: GETUPVAL  R4 U1        ; R4 := U1
 10 [-]: SETTABLE  R3 K2 R4     ; R3["RADIUS"] := R4
 11 [-]: GETGLOBAL R4 K4        ; R4 := 0x5bced4c4
 12 [-]: GETTABLE  R4 R4 K5     ; R4 := R4[0x55f27c30]
 13 [-]: GETUPVAL  R5 U2        ; R5 := U2
 14 [-]: MUL       R5 R5 K6     ; R5 := R5 * 100.000000
 15 [-]: CALL      R4 2 2       ; R4 := R4(R5)
 16 [-]: SETTABLE  R3 K3 R4     ; R3["DAMAGE_INCREASE"] := R4
 17 [-]: GETUPVAL  R4 U3        ; R4 := U3
 18 [-]: SETTABLE  R3 K7 R4     ; R3["DURATION"] := R4
 19 [-]: MOVE      R2 R3        ; R2 := R3
 20 [-]: JMP       27           ; PC := 27
 21 [-]: EQ        0 R1 K8      ; if R1 ~= 2.000000 then PC := 27
 22 [-]: JMP       27           ; PC := 27
 23 [-]: NEWTABLE  R3 0 1       ; R3 := {}
 24 [-]: GETUPVAL  R4 U4        ; R4 := U4
 25 [-]: SETTABLE  R3 K2 R4     ; R3["RADIUS"] := R4
 26 [-]: MOVE      R2 R3        ; R2 := R3
 27 [-]: GETGLOBAL R3 K9        ; R3 := cjson
 28 [-]: GETTABLE  R3 R3 K10    ; R3 := R3[0xb139d7bc]
 29 [-]: MOVE      R4 R2        ; R4 := R2
 30 [-]: TAILCALL  R3 2 0       ; R3,... := R3(R4)
 31 [-]: RETURN    R3 0         ; return R3,...
 32 [-]: RETURN    R0 1         ; return 


; Function #8:
;
; Name:            
; Defined at line: 306
; #Upvalues:       0
; #Parameters:     2
; Is_vararg:       0
; Max Stack Size:  10

  1 [-]: SELF      R2 R1 K0     ; R3 := R1; R2 := R1[0xfa9e477f]
  2 [-]: CALL      R2 2 2       ; R2 := R2(R3)
  3 [-]: SELF      R3 R2 K1     ; R4 := R2; R3 := R2[0x5f45b081]
  4 [-]: CALL      R3 2 2       ; R3 := R3(R4)
  5 [-]: TEST      R3 0         ; if not R3 then PC := 12
  6 [-]: JMP       12           ; PC := 12
  7 [-]: SELF      R3 R1 K2     ; R4 := R1; R3 := R1[0x0e46e45b]
  8 [-]: LOADK     R5 15        ; R5 := 15.000000
  9 [-]: CALL      R3 3 2       ; R3 := R3(R4,R5)
 10 [-]: TEST      R3 0         ; if not R3 then PC := 14
 11 [-]: JMP       14           ; PC := 14
 12 [-]: LOADK     R3 0         ; R3 := 0.000000
 13 [-]: RETURN    R3 2         ; return R3
 14 [-]: LOADK     R3 0         ; R3 := 0.000000
 15 [-]: SELF      R4 R1 K0     ; R5 := R1; R4 := R1[0xfa9e477f]
 16 [-]: CALL      R4 2 2       ; R4 := R4(R5)
 17 [-]: SELF      R4 R4 K4     ; R5 := R4; R4 := R4[0xa39bb54b]
 18 [-]: CALL      R4 2 2       ; R4 := R4(R5)
 19 [-]: GETTABLE  R5 R4 K5     ; R5 := R4["visible"]
 20 [-]: TEST      R5 0         ; if not R5 then PC := 53
 21 [-]: JMP       53           ; PC := 53
 22 [-]: GETGLOBAL R5 K6        ; R5 := 0x7b998233
 23 [-]: GETTABLE  R6 R4 K7     ; R6 := R4["avatar"]
 24 [-]: CALL      R5 2 2       ; R5 := R5(R6)
 25 [-]: TEST      R5 1         ; if R5 then PC := 53
 26 [-]: JMP       53           ; PC := 53
 27 [-]: GETTABLE  R5 R4 K7     ; R5 := R4["avatar"]
 28 [-]: SELF      R5 R5 K8     ; R6 := R5; R5 := R5[0x73901acf]
 29 [-]: CALL      R5 2 2       ; R5 := R5(R6)
 30 [-]: TEST      R5 1         ; if R5 then PC := 53
 31 [-]: JMP       53           ; PC := 53
 32 [-]: SELF      R5 R0 K9     ; R6 := R0; R5 := R0[0x48d05257]
 33 [-]: GETTABLE  R7 R4 K7     ; R7 := R4["avatar"]
 34 [-]: CALL      R5 3 1       ; R5(R6,R7)
 35 [-]: NEWTABLE  R5 1 0       ; R5 := {}
 36 [-]: GETGLOBAL R6 K10       ; R6 := gLotusAvatarType
 37 [-]: SETLIST   R5 1 1       ; R5[(1-1)*FPF+i] := R(5+i), 1 <= i <= 1
 38 [-]: SELF      R6 R1 K0     ; R7 := R1; R6 := R1[0xfa9e477f]
 39 [-]: CALL      R6 2 2       ; R6 := R6(R7)
 40 [-]: SELF      R6 R6 K11    ; R7 := R6; R6 := R6[0xe11a16c7]
 41 [-]: LOADK     R8 15        ; R8 := 15.000000
 42 [-]: MOVE      R9 R5        ; R9 := R5
 43 [-]: CALL      R6 4 2       ; R6 := R6(R7,R8,R9)
 44 [-]: LE        0 R6 K12     ; if R6 > 2.000000 then PC := 52
 45 [-]: JMP       52           ; PC := 52
 46 [-]: GETTABLE  R7 R4 K7     ; R7 := R4["avatar"]
 47 [-]: SELF      R7 R7 K13    ; R8 := R7; R7 := R7[0xc8442850]
 48 [-]: CALL      R7 2 2       ; R7 := R7(R8)
 49 [-]: MUL       R7 R7 K14    ; R7 := R7 * 0.800000
 50 [-]: SUB       R3 K15 R7    ; R3 := 1.000000 - R7
 51 [-]: JMP       53           ; PC := 53
 52 [-]: LOADK     R3 1         ; R3 := 1.000000
 53 [-]: RETURN    R3 2         ; return R3
 54 [-]: RETURN    R0 1         ; return 


; Function #9:
;
; Name:            
; Defined at line: 333
; #Upvalues:       2
; #Parameters:     2
; Is_vararg:       0
; Max Stack Size:  6

  1 [-]: GETUPVAL  R2 U0        ; R2 := U0
  2 [-]: GETTABLE  R2 R2 K0     ; R2 := R2[0xe4ae0e66]
  3 [-]: CALL      R2 1 2       ; R2 := R2()
  4 [-]: TEST      R2 0         ; if not R2 then PC := 13
  5 [-]: JMP       13           ; PC := 13
  6 [-]: GETGLOBAL R2 K1        ; R2 := 0x6687f6e0
  7 [-]: SELF      R2 R2 K2     ; R3 := R2; R2 := R2[0x3a147087]
  8 [-]: GETGLOBAL R4 K3        ; R4 := 0xbe190284
  9 [-]: SELF      R4 R4 K4     ; R5 := R4; R4 := R4[0xc911409e]
 10 [-]: CALL      R4 2 0       ; R4,... := R4(R5)
 11 [-]: CALL      R2 0 1       ; R2(R3,...)
 12 [-]: JMP       22           ; PC := 22
 13 [-]: GETUPVAL  R2 U0        ; R2 := U0
 14 [-]: GETTABLE  R2 R2 K5     ; R2 := R2[0x32316a21]
 15 [-]: CALL      R2 1 2       ; R2 := R2()
 16 [-]: TEST      R2 0         ; if not R2 then PC := 22
 17 [-]: JMP       22           ; PC := 22
 18 [-]: GETGLOBAL R2 K1        ; R2 := 0x6687f6e0
 19 [-]: SELF      R2 R2 K2     ; R3 := R2; R2 := R2[0x3a147087]
 20 [-]: GETUPVAL  R4 U1        ; R4 := U1
 21 [-]: CALL      R2 3 1       ; R2(R3,R4)
 22 [-]: RETURN    R0 1         ; return 


; Function #10:
;
; Name:            
; Defined at line: 341
; #Upvalues:       1
; #Parameters:     2
; Is_vararg:       0
; Max Stack Size:  11

  1 [-]: GETGLOBAL R2 K0        ; R2 := 0x7b998233
  2 [-]: MOVE      R3 R1        ; R3 := R1
  3 [-]: CALL      R2 2 2       ; R2 := R2(R3)
  4 [-]: TEST      R2 1         ; if R2 then PC := 11
  5 [-]: JMP       11           ; PC := 11
  6 [-]: SELF      R2 R1 K1     ; R3 := R1; R2 := R1[0xee0bc178]
  7 [-]: MOVE      R4 R0        ; R4 := R0
  8 [-]: CALL      R2 3 2       ; R2 := R2(R3,R4)
  9 [-]: TEST      R2 0         ; if not R2 then PC := 13
 10 [-]: JMP       13           ; PC := 13
 11 [-]: LOADBOOL  R2 0 0       ; R2 := false
 12 [-]: RETURN    R2 2         ; return R2
 13 [-]: SELF      R2 R1 K2     ; R3 := R1; R2 := R1[0x1ac1655c]
 14 [-]: CALL      R2 2 2       ; R2 := R2(R3)
 15 [-]: SELF      R3 R2 K3     ; R4 := R2; R3 := R2[0x68d1b91d]
 16 [-]: CALL      R3 2 2       ; R3 := R3(R4)
 17 [-]: TEST      R3 0         ; if not R3 then PC := 24
 18 [-]: JMP       24           ; PC := 24
 19 [-]: SELF      R3 R2 K4     ; R4 := R2; R3 := R2[0x8733746a]
 20 [-]: GETUPVAL  R5 U0        ; R5 := U0
 21 [-]: CALL      R3 3 2       ; R3 := R3(R4,R5)
 22 [-]: TEST      R3 0         ; if not R3 then PC := 32
 23 [-]: JMP       32           ; PC := 32
 24 [-]: SELF      R3 R2 K5     ; R4 := R2; R3 := R2[0xa53cf701]
 25 [-]: CALL      R3 2 2       ; R3 := R3(R4)
 26 [-]: TEST      R3 1         ; if R3 then PC := 32
 27 [-]: JMP       32           ; PC := 32
 28 [-]: SELF      R3 R2 K6     ; R4 := R2; R3 := R2[0x73901acf]
 29 [-]: CALL      R3 2 2       ; R3 := R3(R4)
 30 [-]: TEST      R3 0         ; if not R3 then PC := 34
 31 [-]: JMP       34           ; PC := 34
 32 [-]: LOADBOOL  R3 0 0       ; R3 := false
 33 [-]: RETURN    R3 2         ; return R3
 34 [-]: SELF      R3 R2 K7     ; R4 := R2; R3 := R2[0xb6bcca02]
 35 [-]: CALL      R3 2 2       ; R3 := R3(R4)
 36 [-]: GETGLOBAL R4 K0        ; R4 := 0x7b998233
 37 [-]: MOVE      R5 R3        ; R5 := R3
 38 [-]: CALL      R4 2 2       ; R4 := R4(R5)
 39 [-]: TEST      R4 1         ; if R4 then PC := 45
 40 [-]: JMP       45           ; PC := 45
 41 [-]: EQ        1 R3 R0      ; if R3 == R0 then PC := 45
 42 [-]: JMP       45           ; PC := 45
 43 [-]: LOADBOOL  R4 0 0       ; R4 := false
 44 [-]: RETURN    R4 2         ; return R4
 45 [-]: SELF      R4 R1 K8     ; R5 := R1; R4 := R1[0xde321e6f]
 46 [-]: CALL      R4 2 2       ; R4 := R4(R5)
 47 [-]: SELF      R4 R4 K9     ; R5 := R4; R4 := R4[0xe9f54086]
 48 [-]: LOADK     R6 100       ; R6 := 100.000000
 49 [-]: LOADK     R7 33        ; R7 := 33.000000
 50 [-]: LOADNIL   R8 R9        ; R8 := R9 := nil
 51 [-]: LOADK     R10 12       ; R10 := 12.000000
 52 [-]: CALL      R4 7 2       ; R4 := R4(R5,R6,R7,R8,R9,R10)
 53 [-]: LE        0 R4 K12     ; if R4 > 0.000000 then PC := 57
 54 [-]: JMP       57           ; PC := 57
 55 [-]: LOADBOOL  R4 0 0       ; R4 := false
 56 [-]: RETURN    R4 2         ; return R4
 57 [-]: LOADBOOL  R4 1 0       ; R4 := true
 58 [-]: RETURN    R4 2         ; return R4
 59 [-]: RETURN    R0 1         ; return 


; Function #11:
;
; Name:            
; Defined at line: 364
; #Upvalues:       2
; #Parameters:     2
; Is_vararg:       0
; Max Stack Size:  5

  1 [-]: GETUPVAL  R2 U0        ; R2 := U0
  2 [-]: MOVE      R3 R0        ; R3 := R0
  3 [-]: MOVE      R4 R1        ; R4 := R1
  4 [-]: CALL      R2 3 2       ; R2 := R2(R3,R4)
  5 [-]: TEST      R2 1         ; if R2 then PC := 9
  6 [-]: JMP       9            ; PC := 9
  7 [-]: LOADBOOL  R2 0 0       ; R2 := false
  8 [-]: RETURN    R2 2         ; return R2
  9 [-]: SELF      R2 R1 K0     ; R3 := R1; R2 := R1[0x08db51de]
 10 [-]: GETUPVAL  R4 U1        ; R4 := U1
 11 [-]: CALL      R2 3 2       ; R2 := R2(R3,R4)
 12 [-]: NOT       R2 R2        ; R2 := not R2
 13 [-]: RETURN    R2 2         ; return R2
 14 [-]: RETURN    R0 1         ; return 


; Function #12:
;
; Name:            
; Defined at line: 372
; #Upvalues:       4
; #Parameters:     3
; Is_vararg:       0
; Max Stack Size:  17

  1 [-]: SELF      R3 R1 K0     ; R4 := R1; R3 := R1[0xde321e6f]
  2 [-]: CALL      R3 2 2       ; R3 := R3(R4)
  3 [-]: LOADNIL   R4 R4        ; R4 := nil
  4 [-]: GETUPVAL  R5 U0        ; R5 := U0
  5 [-]: MOVE      R6 R2        ; R6 := R2
  6 [-]: CALL      R5 2 1       ; R5(R6)
  7 [-]: GETUPVAL  R5 U1        ; R5 := U1
  8 [-]: MOVE      R6 R1        ; R6 := R1
  9 [-]: CALL      R5 2 2       ; R5 := R5(R6)
 10 [-]: GETGLOBAL R6 K1        ; R6 := 0x7b998233
 11 [-]: SELF      R7 R1 K2     ; R8 := R1; R7 := R1[0xfa9e477f]
 12 [-]: CALL      R7 2 0       ; R7,... := R7(R8)
 13 [-]: CALL      R6 0 2       ; R6 := R6(R7,...)
 14 [-]: TEST      R6 0         ; if not R6 then PC := 85
 15 [-]: JMP       85           ; PC := 85
 16 [-]: SELF      R6 R3 K3     ; R7 := R3; R6 := R3[0x7c09e541]
 17 [-]: CALL      R6 2 2       ; R6 := R6(R7)
 18 [-]: MOVE      R4 R6        ; R4 := R6
 19 [-]: GETGLOBAL R6 K1        ; R6 := 0x7b998233
 20 [-]: MOVE      R7 R4        ; R7 := R4
 21 [-]: CALL      R6 2 2       ; R6 := R6(R7)
 22 [-]: TEST      R6 1         ; if R6 then PC := 29
 23 [-]: JMP       29           ; PC := 29
 24 [-]: SELF      R6 R4 K4     ; R7 := R4; R6 := R4[0xf2deaf69]
 25 [-]: GETGLOBAL R8 K5        ; R8 := gLotusAvatarType
 26 [-]: CALL      R6 3 2       ; R6 := R6(R7,R8)
 27 [-]: TEST      R6 1         ; if R6 then PC := 90
 28 [-]: JMP       90           ; PC := 90
 29 [-]: LOADNIL   R6 R6        ; R6 := nil
 30 [-]: GETUPVAL  R7 U2        ; R7 := U2
 31 [-]: GETTABLE  R7 R7 K6     ; R7 := R7[0x32316a21]
 32 [-]: CALL      R7 1 2       ; R7 := R7()
 33 [-]: TEST      R7 0         ; if not R7 then PC := 49
 34 [-]: JMP       49           ; PC := 49
 35 [-]: SELF      R7 R1 K7     ; R8 := R1; R7 := R1[0x80846b00]
 36 [-]: LOADK     R9 1         ; R9 := 1.000000
 37 [-]: MOVE      R10 R5       ; R10 := R5
 38 [-]: GETUPVAL  R11 U2       ; R11 := U2
 39 [-]: GETTABLE  R11 R11 K8   ; R11 := R11[0xfbdcfe72]
 40 [-]: GETGLOBAL R12 K9       ; R12 := 0x19849b93
 41 [-]: MOVE      R13 R1       ; R13 := R1
 42 [-]: MOVE      R14 R0       ; R14 := R0
 43 [-]: CALL      R11 4 2      ; R11 := R11(R12,R13,R14)
 44 [-]: LOADBOOL  R12 1 0      ; R12 := true
 45 [-]: LOADBOOL  R13 1 0      ; R13 := true
 46 [-]: CALL      R7 7 2       ; R7 := R7(R8,R9,R10,R11,R12,R13)
 47 [-]: MOVE      R6 R7        ; R6 := R7
 48 [-]: JMP       57           ; PC := 57
 49 [-]: SELF      R7 R1 K7     ; R8 := R1; R7 := R1[0x80846b00]
 50 [-]: LOADK     R9 1         ; R9 := 1.000000
 51 [-]: MOVE      R10 R5       ; R10 := R5
 52 [-]: LOADK     R11 1        ; R11 := 1.000000
 53 [-]: LOADBOOL  R12 1 0      ; R12 := true
 54 [-]: LOADBOOL  R13 1 0      ; R13 := true
 55 [-]: CALL      R7 7 2       ; R7 := R7(R8,R9,R10,R11,R12,R13)
 56 [-]: MOVE      R6 R7        ; R6 := R7
 57 [-]: GETGLOBAL R7 K10       ; R7 := 0xf6c6e505
 58 [-]: SELF      R8 R1 K11    ; R9 := R1; R8 := R1[0xeea7f8c4]
 59 [-]: CALL      R8 2 0       ; R8,... := R8(R9)
 60 [-]: CALL      R7 0 2       ; R7 := R7(R8,...)
 61 [-]: GETGLOBAL R8 K12       ; R8 := 0xc8802016
 62 [-]: MOVE      R9 R6        ; R9 := R6
 63 [-]: CALL      R8 2 4       ; R8,R9,R10 := R8(R9)
 64 [-]: JMP       82           ; PC := 82
 65 [-]: SELF      R13 R12 K13  ; R14 := R12; R13 := R12[0xee0bc178]
 66 [-]: MOVE      R15 R1       ; R15 := R1
 67 [-]: CALL      R13 3 2      ; R13 := R13(R14,R15)
 68 [-]: TEST      R13 1        ; if R13 then PC := 82
 69 [-]: JMP       82           ; PC := 82
 70 [-]: GETGLOBAL R13 K14      ; R13 := 0x4fd57545
 71 [-]: SELF      R14 R12 K15  ; R15 := R12; R14 := R12[0xd1586535]
 72 [-]: CALL      R14 2 2      ; R14 := R14(R15)
 73 [-]: SELF      R15 R1 K15   ; R16 := R1; R15 := R1[0xd1586535]
 74 [-]: CALL      R15 2 2      ; R15 := R15(R16)
 75 [-]: SUB       R14 R14 R15  ; R14 := R14 - R15
 76 [-]: MOVE      R15 R7       ; R15 := R7
 77 [-]: CALL      R13 3 2      ; R13 := R13(R14,R15)
 78 [-]: LT        0 K16 R13    ; if 0.000000 >= R13 then PC := 82
 79 [-]: JMP       82           ; PC := 82
 80 [-]: MOVE      R4 R12       ; R4 := R12
 81 [-]: JMP       90           ; PC := 90
 82 [-]: TFORLOOP  R8 2         ; R11,R12 :=  R8(R9,R10); if R11 ~= nil then begin PC = 65; R10 := R11 end
 83 [-]: JMP       65           ; PC := 65
 84 [-]: JMP       90           ; PC := 90
 85 [-]: SELF      R13 R1 K2    ; R14 := R1; R13 := R1[0xfa9e477f]
 86 [-]: CALL      R13 2 2      ; R13 := R13(R14)
 87 [-]: SELF      R13 R13 K17  ; R14 := R13; R13 := R13[0xf5527472]
 88 [-]: CALL      R13 2 2      ; R13 := R13(R14)
 89 [-]: MOVE      R4 R13       ; R4 := R13
 90 [-]: GETGLOBAL R13 K1       ; R13 := 0x7b998233
 91 [-]: MOVE      R14 R4       ; R14 := R4
 92 [-]: CALL      R13 2 2      ; R13 := R13(R14)
 93 [-]: TEST      R13 1        ; if R13 then PC := 114
 94 [-]: JMP       114          ; PC := 114
 95 [-]: SELF      R13 R4 K4    ; R14 := R4; R13 := R4[0xf2deaf69]
 96 [-]: GETGLOBAL R15 K5       ; R15 := gLotusAvatarType
 97 [-]: CALL      R13 3 2      ; R13 := R13(R14,R15)
 98 [-]: TEST      R13 0        ; if not R13 then PC := 114
 99 [-]: JMP       114          ; PC := 114
100 [-]: SELF      R13 R4 K18   ; R14 := R4; R13 := R4[0x2047cfe7]
101 [-]: CALL      R13 2 2      ; R13 := R13(R14)
102 [-]: TEST      R13 1        ; if R13 then PC := 114
103 [-]: JMP       114          ; PC := 114
104 [-]: SELF      R13 R4 K19   ; R14 := R4; R13 := R4[0xc4dff581]
105 [-]: LOADK     R15 0        ; R15 := 0.000000
106 [-]: CALL      R13 3 2      ; R13 := R13(R14,R15)
107 [-]: TEST      R13 1        ; if R13 then PC := 114
108 [-]: JMP       114          ; PC := 114
109 [-]: SELF      R13 R4 K21   ; R14 := R4; R13 := R4[0x753a7ea6]
110 [-]: MOVE      R15 R1       ; R15 := R1
111 [-]: CALL      R13 3 2      ; R13 := R13(R14,R15)
112 [-]: TEST      R13 1        ; if R13 then PC := 119
113 [-]: JMP       119          ; PC := 119
114 [-]: LOADNIL   R13 R13      ; R13 := nil
115 [-]: GETGLOBAL R14 K22      ; R14 := 0x0469f296
116 [-]: LOADK     R15 K23      ; R15 := "/Lotus/Language/Game/AbilityErrorInvalidTarget"
117 [-]: CALL      R14 2 0      ; R14,... := R14(R15)
118 [-]: RETURN    R13 0        ; return R13,...
119 [-]: GETUPVAL  R13 U3       ; R13 := U3
120 [-]: MOVE      R14 R1       ; R14 := R1
121 [-]: MOVE      R15 R4       ; R15 := R4
122 [-]: CALL      R13 3 2      ; R13 := R13(R14,R15)
123 [-]: TEST      R13 1        ; if R13 then PC := 130
124 [-]: JMP       130          ; PC := 130
125 [-]: LOADNIL   R13 R13      ; R13 := nil
126 [-]: GETGLOBAL R14 K22      ; R14 := 0x0469f296
127 [-]: LOADK     R15 K23      ; R15 := "/Lotus/Language/Game/AbilityErrorInvalidTarget"
128 [-]: CALL      R14 2 0      ; R14,... := R14(R15)
129 [-]: RETURN    R13 0        ; return R13,...
130 [-]: SELF      R13 R4 K13   ; R14 := R4; R13 := R4[0xee0bc178]
131 [-]: MOVE      R15 R1       ; R15 := R1
132 [-]: CALL      R13 3 2      ; R13 := R13(R14,R15)
133 [-]: TEST      R13 0        ; if not R13 then PC := 140
134 [-]: JMP       140          ; PC := 140
135 [-]: LOADNIL   R13 R13      ; R13 := nil
136 [-]: GETGLOBAL R14 K22      ; R14 := 0x0469f296
137 [-]: LOADK     R15 K23      ; R15 := "/Lotus/Language/Game/AbilityErrorInvalidTarget"
138 [-]: CALL      R14 2 0      ; R14,... := R14(R15)
139 [-]: RETURN    R13 0        ; return R13,...
140 [-]: SELF      R13 R4 K24   ; R14 := R4; R13 := R4[0xbebad19f]
141 [-]: MOVE      R15 R1       ; R15 := R1
142 [-]: CALL      R13 3 2      ; R13 := R13(R14,R15)
143 [-]: LT        0 R5 R13     ; if R5 >= R13 then PC := 150
144 [-]: JMP       150          ; PC := 150
145 [-]: LOADNIL   R14 R14      ; R14 := nil
146 [-]: GETGLOBAL R15 K22      ; R15 := 0x0469f296
147 [-]: LOADK     R16 K25      ; R16 := "/Lotus/Language/Game/AbilityErrorOutOfRange"
148 [-]: CALL      R15 2 0      ; R15,... := R15(R16)
149 [-]: RETURN    R14 0        ; return R14,...
150 [-]: RETURN    R4 2         ; return R4
151 [-]: RETURN    R0 1         ; return 


; Function #13:
;
; Name:            
; Defined at line: 431
; #Upvalues:       0
; #Parameters:     1
; Is_vararg:       0
; Max Stack Size:  7

  1 [-]: SELF      R1 R0 K0     ; R2 := R0; R1 := R0[0xde321e6f]
  2 [-]: CALL      R1 2 2       ; R1 := R1(R2)
  3 [-]: SELF      R1 R1 K1     ; R2 := R1; R1 := R1[0xf7d48ee0]
  4 [-]: CALL      R1 2 2       ; R1 := R1(R2)
  5 [-]: LOADK     R2 K2        ; R2 := 0.200000
  6 [-]: SELF      R3 R1 K3     ; R4 := R1; R3 := R1[0x73712b9c]
  7 [-]: GETGLOBAL R5 K4        ; R5 := 0x6687f6e0
  8 [-]: CALL      R3 3 2       ; R3 := R3(R4,R5)
  9 [-]: LT        0 K5 R2      ; if 0.000000 >= R2 then PC := 39
 10 [-]: JMP       39           ; PC := 39
 11 [-]: GETGLOBAL R4 K6        ; R4 := 0x7b998233
 12 [-]: GETGLOBAL R5 K4        ; R5 := 0x6687f6e0
 13 [-]: CALL      R4 2 2       ; R4 := R4(R5)
 14 [-]: TEST      R4 1         ; if R4 then PC := 39
 15 [-]: JMP       39           ; PC := 39
 16 [-]: GETGLOBAL R4 K4        ; R4 := 0x6687f6e0
 17 [-]: SELF      R4 R4 K7     ; R5 := R4; R4 := R4[0x2f189c42]
 18 [-]: CALL      R4 2 2       ; R4 := R4(R5)
 19 [-]: TEST      R4 0         ; if not R4 then PC := 39
 20 [-]: JMP       39           ; PC := 39
 21 [-]: GETGLOBAL R4 K6        ; R4 := 0x7b998233
 22 [-]: MOVE      R5 R1        ; R5 := R1
 23 [-]: CALL      R4 2 2       ; R4 := R4(R5)
 24 [-]: TEST      R4 1         ; if R4 then PC := 39
 25 [-]: JMP       39           ; PC := 39
 26 [-]: SELF      R4 R1 K8     ; R5 := R1; R4 := R1[0xb720de27]
 27 [-]: MOVE      R6 R3        ; R6 := R3
 28 [-]: CALL      R4 3 2       ; R4 := R4(R5,R6)
 29 [-]: TEST      R4 1         ; if R4 then PC := 32
 30 [-]: JMP       32           ; PC := 32
 31 [-]: JMP       39           ; PC := 39
 32 [-]: GETGLOBAL R4 K9        ; R4 := 0xcbd666e1
 33 [-]: LOADK     R5 0         ; R5 := 0.000000
 34 [-]: CALL      R4 2 1       ; R4(R5)
 35 [-]: GETGLOBAL R4 K10       ; R4 := 0x67652851
 36 [-]: CALL      R4 1 2       ; R4 := R4()
 37 [-]: SUB       R2 R2 R4     ; R2 := R2 - R4
 38 [-]: JMP       9            ; PC := 9
 39 [-]: RETURN    R0 1         ; return 


; Function #14:
;
; Name:            
; Defined at line: 446
; #Upvalues:       5
; #Parameters:     3
; Is_vararg:       0
; Max Stack Size:  11

  1 [-]: SELF      R3 R0 K0     ; R4 := R0; R3 := R0[0x5063edc3]
  2 [-]: CALL      R3 2 2       ; R3 := R3(R4)
  3 [-]: LT        0 K1 R3      ; if 0.000000 >= R3 then PC := 58
  4 [-]: JMP       58           ; PC := 58
  5 [-]: SELF      R3 R0 K2     ; R4 := R0; R3 := R0[0x75ecaf0b]
  6 [-]: CALL      R3 2 2       ; R3 := R3(R4)
  7 [-]: EQ        0 R3 K4      ; if R3 ~= 1.000000 then PC := 58
  8 [-]: JMP       58           ; PC := 58
  9 [-]: SELF      R3 R1 K5     ; R4 := R1; R3 := R1[0xd5f7912b]
 10 [-]: GETGLOBAL R5 K6        ; R5 := 0x0469f296
 11 [-]: LOADK     R6 K7        ; R6 := "EvalBusyLoop"
 12 [-]: CALL      R5 2 2       ; R5 := R5(R6)
 13 [-]: LOADBOOL  R6 1 0       ; R6 := true
 14 [-]: CALL      R3 4 1       ; R3(R4,R5,R6)
 15 [-]: GETGLOBAL R3 K8        ; R3 := 0x7b998233
 16 [-]: MOVE      R4 R0        ; R4 := R0
 17 [-]: CALL      R3 2 2       ; R3 := R3(R4)
 18 [-]: TEST      R3 0         ; if not R3 then PC := 22
 19 [-]: JMP       22           ; PC := 22
 20 [-]: LOADBOOL  R3 0 0       ; R3 := false
 21 [-]: RETURN    R3 2         ; return R3
 22 [-]: SELF      R3 R0 K9     ; R4 := R0; R3 := R0[0xf5c3424f]
 23 [-]: GETUPVAL  R5 U0        ; R5 := U0
 24 [-]: CALL      R3 3 2       ; R3 := R3(R4,R5)
 25 [-]: SELF      R4 R0 K10    ; R5 := R0; R4 := R0[0x58a4d5ac]
 26 [-]: CALL      R4 2 2       ; R4 := R4(R5)
 27 [-]: LT        0 R4 R3      ; if R4 >= R3 then PC := 46
 28 [-]: JMP       46           ; PC := 46
 29 [-]: GETUPVAL  R3 U1        ; R3 := U1
 30 [-]: GETTABLE  R3 R3 K11    ; R3 := R3[0x94419417]
 31 [-]: MOVE      R4 R1        ; R4 := R1
 32 [-]: LOADBOOL  R5 0 0       ; R5 := false
 33 [-]: CALL      R3 3 2       ; R3 := R3(R4,R5)
 34 [-]: TEST      R3 1         ; if R3 then PC := 46
 35 [-]: JMP       46           ; PC := 46
 36 [-]: LOADBOOL  R3 1 0       ; R3 := true
 37 [-]: TEST      R3 1         ; if R3 then PC := 39
 38 [-]: JMP       39           ; PC := 39
 39 [-]: SELF      R3 R1 K12    ; R4 := R1; R3 := R1[0xd7091d77]
 40 [-]: GETGLOBAL R5 K6        ; R5 := 0x0469f296
 41 [-]: LOADK     R6 K13       ; R6 := "/Lotus/Language/Game/AbilityNeedMoreEnergy"
 42 [-]: CALL      R5 2 0       ; R5,... := R5(R6)
 43 [-]: CALL      R3 0 1       ; R3(R4,...)
 44 [-]: LOADBOOL  R3 0 0       ; R3 := false
 45 [-]: RETURN    R3 2         ; return R3
 46 [-]: SELF      R3 R0 K14    ; R4 := R0; R3 := R0[0xb720de27]
 47 [-]: SELF      R5 R0 K15    ; R6 := R0; R5 := R0[0x73712b9c]
 48 [-]: GETGLOBAL R7 K16       ; R7 := 0x6687f6e0
 49 [-]: CALL      R5 3 0       ; R5,... := R5(R6,R7)
 50 [-]: CALL      R3 0 2       ; R3 := R3(R4,...)
 51 [-]: TEST      R3 0         ; if not R3 then PC := 58
 52 [-]: JMP       58           ; PC := 58
 53 [-]: SELF      R3 R0 K17    ; R4 := R0; R3 := R0[0x48d05257]
 54 [-]: MOVE      R5 R1        ; R5 := R1
 55 [-]: CALL      R3 3 1       ; R3(R4,R5)
 56 [-]: LOADBOOL  R3 1 0       ; R3 := true
 57 [-]: RETURN    R3 2         ; return R3
 58 [-]: GETUPVAL  R3 U2        ; R3 := U2
 59 [-]: MOVE      R4 R0        ; R4 := R0
 60 [-]: MOVE      R5 R1        ; R5 := R1
 61 [-]: MOVE      R6 R2        ; R6 := R2
 62 [-]: CALL      R3 4 3       ; R3,R4 := R3(R4,R5,R6)
 63 [-]: GETUPVAL  R5 U3        ; R5 := U3
 64 [-]: GETTABLE  R5 R5 K18    ; R5 := R5[0x32316a21]
 65 [-]: CALL      R5 1 2       ; R5 := R5()
 66 [-]: TEST      R5 1         ; if R5 then PC := 106
 67 [-]: JMP       106          ; PC := 106
 68 [-]: SELF      R5 R1 K19    ; R6 := R1; R5 := R1[0x388577d5]
 69 [-]: CALL      R5 2 2       ; R5 := R5(R6)
 70 [-]: GETUPVAL  R6 U0        ; R6 := U0
 71 [-]: GETGLOBAL R7 K20       ; R7 := _T
 72 [-]: GETTABLE  R7 R7 K21    ; R7 := R7["sporesAbility"]
 73 [-]: EQ        1 R7 K22     ; if R7 == nil then PC := 82
 74 [-]: JMP       82           ; PC := 82
 75 [-]: GETGLOBAL R7 K20       ; R7 := _T
 76 [-]: GETTABLE  R7 R7 K21    ; R7 := R7["sporesAbility"]
 77 [-]: GETTABLE  R7 R7 R5     ; R7 := R7[R5]
 78 [-]: EQ        1 R7 K22     ; if R7 == nil then PC := 82
 79 [-]: JMP       82           ; PC := 82
 80 [-]: GETUPVAL  R7 U4        ; R7 := U4
 81 [-]: MUL       R6 R6 R7     ; R6 := R6 * R7
 82 [-]: SELF      R7 R0 K9     ; R8 := R0; R7 := R0[0xf5c3424f]
 83 [-]: MOVE      R9 R6        ; R9 := R6
 84 [-]: CALL      R7 3 2       ; R7 := R7(R8,R9)
 85 [-]: SELF      R8 R0 K10    ; R9 := R0; R8 := R0[0x58a4d5ac]
 86 [-]: CALL      R8 2 2       ; R8 := R8(R9)
 87 [-]: LT        0 R8 R7      ; if R8 >= R7 then PC := 106
 88 [-]: JMP       106          ; PC := 106
 89 [-]: GETUPVAL  R7 U1        ; R7 := U1
 90 [-]: GETTABLE  R7 R7 K11    ; R7 := R7[0x94419417]
 91 [-]: MOVE      R8 R1        ; R8 := R1
 92 [-]: LOADBOOL  R9 0 0       ; R9 := false
 93 [-]: CALL      R7 3 2       ; R7 := R7(R8,R9)
 94 [-]: TEST      R7 1         ; if R7 then PC := 106
 95 [-]: JMP       106          ; PC := 106
 96 [-]: LOADBOOL  R7 1 0       ; R7 := true
 97 [-]: TEST      R7 1         ; if R7 then PC := 99
 98 [-]: JMP       99           ; PC := 99
 99 [-]: SELF      R7 R1 K12    ; R8 := R1; R7 := R1[0xd7091d77]
100 [-]: GETGLOBAL R9 K6        ; R9 := 0x0469f296
101 [-]: LOADK     R10 K13      ; R10 := "/Lotus/Language/Game/AbilityNeedMoreEnergy"
102 [-]: CALL      R9 2 0       ; R9,... := R9(R10)
103 [-]: CALL      R7 0 1       ; R7(R8,...)
104 [-]: LOADBOOL  R7 0 0       ; R7 := false
105 [-]: RETURN    R7 2         ; return R7
106 [-]: EQ        0 R3 K22     ; if R3 ~= nil then PC := 123
107 [-]: JMP       123          ; PC := 123
108 [-]: GETUPVAL  R7 U3        ; R7 := U3
109 [-]: GETTABLE  R7 R7 K18    ; R7 := R7[0x32316a21]
110 [-]: CALL      R7 1 2       ; R7 := R7()
111 [-]: TEST      R7 0         ; if not R7 then PC := 116
112 [-]: JMP       116          ; PC := 116
113 [-]: LOADBOOL  R7 1 0       ; R7 := true
114 [-]: RETURN    R7 2         ; return R7
115 [-]: JMP       123          ; PC := 123
116 [-]: EQ        1 R4 K22     ; if R4 == nil then PC := 121
117 [-]: JMP       121          ; PC := 121
118 [-]: SELF      R7 R1 K12    ; R8 := R1; R7 := R1[0xd7091d77]
119 [-]: MOVE      R9 R4        ; R9 := R4
120 [-]: CALL      R7 3 1       ; R7(R8,R9)
121 [-]: LOADBOOL  R7 0 0       ; R7 := false
122 [-]: RETURN    R7 2         ; return R7
123 [-]: SELF      R7 R0 K17    ; R8 := R0; R7 := R0[0x48d05257]
124 [-]: MOVE      R9 R3        ; R9 := R3
125 [-]: CALL      R7 3 1       ; R7(R8,R9)
126 [-]: LOADBOOL  R7 1 0       ; R7 := true
127 [-]: RETURN    R7 2         ; return R7
128 [-]: RETURN    R0 1         ; return 


; Function #15:
;
; Name:            
; Defined at line: 506
; #Upvalues:       3
; #Parameters:     1
; Is_vararg:       0
; Max Stack Size:  8

  1 [-]: GETUPVAL  R1 U0        ; R1 := U0
  2 [-]: GETTABLE  R1 R1 K0     ; R1 := R1[0x63c599b8]
  3 [-]: MOVE      R2 R0        ; R2 := R0
  4 [-]: GETGLOBAL R3 K1        ; R3 := 0x6687f6e0
  5 [-]: LOADK     R4 12        ; R4 := 12.000000
  6 [-]: GETUPVAL  R5 U1        ; R5 := U1
  7 [-]: GETUPVAL  R6 U2        ; R6 := U2
  8 [-]: GETGLOBAL R7 K3        ; R7 := 0x9db9203f
  9 [-]: CALL      R1 7 1       ; R1(R2,R3,R4,R5,R6,R7)
 10 [-]: RETURN    R0 1         ; return 


; Function #16:
;
; Name:            
; Defined at line: 510
; #Upvalues:       20
; #Parameters:     4
; Is_vararg:       0
; Max Stack Size:  33

  1 [-]: GETUPVAL  R4 U0        ; R4 := U0
  2 [-]: MOVE      R5 R3        ; R5 := R3
  3 [-]: CALL      R4 2 1       ; R4(R5)
  4 [-]: LOADNIL   R4 R4        ; R4 := nil
  5 [-]: GETUPVAL  R5 U8        ; R5 := U8
  6 [-]: MOVE      R6 R1        ; R6 := R1
  7 [-]: CALL      R5 2 9       ; R5,R6,R7,R8,R9,R10,R11,R12 := R5(R6)
  8 [-]: SETUPVAL  R12 U7       ; U82 := 
  9 [-]: SETUPVAL  R11 U6       ; U82 := 
 10 [-]: MOVE      R4 R10       ; R4 := R10
 11 [-]: SETUPVAL  R9 U5        ; U82 := 
 12 [-]: SETUPVAL  R8 U4        ; U82 := 
 13 [-]: SETUPVAL  R7 U3        ; U82 := 
 14 [-]: SETUPVAL  R6 U2        ; U82 := 
 15 [-]: SETUPVAL  R5 U1        ; U82 := 
 16 [-]: SELF      R5 R0 K0     ; R6 := R0; R5 := R0[0x5063edc3]
 17 [-]: CALL      R5 2 2       ; R5 := R5(R6)
 18 [-]: SELF      R6 R0 K1     ; R7 := R0; R6 := R0[0x75ecaf0b]
 19 [-]: CALL      R6 2 2       ; R6 := R6(R7)
 20 [-]: LT        0 K2 R5      ; if 0.000000 >= R5 then PC := 24
 21 [-]: JMP       24           ; PC := 24
 22 [-]: EQ        1 R6 K4      ; if R6 == 1.000000 then PC := 25
 23 [-]: JMP       25           ; PC := 25
 24 [-]: LOADBOOL  R7 0 1       ; R7 := false; PC := 25
 25 [-]: LOADBOOL  R7 1 0       ; R7 := true
 26 [-]: TEST      R7 0         ; if not R7 then PC := 39
 27 [-]: JMP       39           ; PC := 39
 28 [-]: GETUPVAL  R8 U9        ; R8 := U9
 29 [-]: MOVE      R9 R5        ; R9 := R5
 30 [-]: MOVE      R10 R6       ; R10 := R6
 31 [-]: CALL      R8 3 1       ; R8(R9,R10)
 32 [-]: GETUPVAL  R8 U13       ; R8 := U13
 33 [-]: MOVE      R9 R1        ; R9 := R1
 34 [-]: MOVE      R10 R6       ; R10 := R6
 35 [-]: CALL      R8 3 4       ; R8,R9,R10 := R8(R9,R10)
 36 [-]: SETUPVAL  R10 U12      ; U82 := 
 37 [-]: SETUPVAL  R9 U11       ; U82 := 
 38 [-]: SETUPVAL  R8 U10       ; U82 := 

 39 [-]: SELF      R8 R1 K5     ; R9 := R1; R8 := R1[0xeea7f8c4]
 40 [-]: CALL      R8 2 2       ; R8 := R8(R9)
 41 [-]: SELF      R9 R1 K6     ; R10 := R1; R9 := R1[0xc69299ed]
 42 [-]: CALL      R9 2 2       ; R9 := R9(R10)
 43 [-]: LE        0 R9 K4      ; if R9 > 1.000000 then PC := 50
 44 [-]: JMP       50           ; PC := 50
 45 [-]: SELF      R9 R1 K7     ; R10 := R1; R9 := R1[0x020d4331]
 46 [-]: CALL      R9 2 2       ; R9 := R9(R10)
 47 [-]: SELF      R9 R9 K8     ; R10 := R9; R9 := R9[0x553549e8]
 48 [-]: MOVE      R11 R8       ; R11 := R8
 49 [-]: CALL      R9 3 1       ; R9(R10,R11)
 50 [-]: SELF      R9 R1 K9     ; R10 := R1; R9 := R1[0x47901f07]
 51 [-]: GETGLOBAL R11 K10      ; R11 := 0x86f0e8bf
 52 [-]: GETGLOBAL R12 K11      ; R12 := EMPTY_SYMBOL
 53 [-]: CALL      R9 4 1       ; R9(R10,R11,R12)
 54 [-]: SELF      R9 R1 K12    ; R10 := R1; R9 := R1[0x388577d5]
 55 [-]: CALL      R9 2 2       ; R9 := R9(R10)
 56 [-]: GETUPVAL  R10 U14      ; R10 := U14
 57 [-]: TEST      R7 1         ; if R7 then PC := 70
 58 [-]: JMP       70           ; PC := 70
 59 [-]: GETGLOBAL R11 K13      ; R11 := _T
 60 [-]: GETTABLE  R11 R11 K14  ; R11 := R11["sporesAbility"]
 61 [-]: EQ        1 R11 K15    ; if R11 == nil then PC := 70
 62 [-]: JMP       70           ; PC := 70
 63 [-]: GETGLOBAL R11 K13      ; R11 := _T
 64 [-]: GETTABLE  R11 R11 K14  ; R11 := R11["sporesAbility"]
 65 [-]: GETTABLE  R11 R11 R9   ; R11 := R11[R9]
 66 [-]: EQ        1 R11 K15    ; if R11 == nil then PC := 70
 67 [-]: JMP       70           ; PC := 70
 68 [-]: GETUPVAL  R11 U15      ; R11 := U15
 69 [-]: MUL       R10 R10 R11  ; R10 := R10 * R11
 70 [-]: GETUPVAL  R11 U16      ; R11 := U16
 71 [-]: GETTABLE  R11 R11 K16  ; R11 := R11[0x94419417]
 72 [-]: MOVE      R12 R1       ; R12 := R1
 73 [-]: LOADBOOL  R13 0 0      ; R13 := false
 74 [-]: CALL      R11 3 2      ; R11 := R11(R12,R13)
 75 [-]: TEST      R11 1        ; if R11 then PC := 81
 76 [-]: JMP       81           ; PC := 81
 77 [-]: GETGLOBAL R11 K17      ; R11 := 0x6687f6e0
 78 [-]: SELF      R11 R11 K18  ; R12 := R11; R11 := R11[0x3a147087]
 79 [-]: MOVE      R13 R10      ; R13 := R10
 80 [-]: CALL      R11 3 1      ; R11(R12,R13)
 81 [-]: GETGLOBAL R11 K17      ; R11 := 0x6687f6e0
 82 [-]: SELF      R11 R11 K19  ; R12 := R11; R11 := R11[0x7e627183]
 83 [-]: CALL      R11 2 2      ; R11 := R11(R12)
 84 [-]: SELF      R12 R0 K20   ; R13 := R0; R12 := R0[0x68b88e58]
 85 [-]: LOADBOOL  R14 1 0      ; R14 := true
 86 [-]: CALL      R12 3 1      ; R12(R13,R14)
 87 [-]: GETUPVAL  R12 U16      ; R12 := U16
 88 [-]: GETTABLE  R12 R12 K21  ; R12 := R12[0x5c445da6]
 89 [-]: MOVE      R13 R0       ; R13 := R0
 90 [-]: GETGLOBAL R14 K22      ; R14 := 0x0ed8b456
 91 [-]: LOADK     R15 K23      ; R15 := "Poison"
 92 [-]: LOADBOOL  R16 0 0      ; R16 := false
 93 [-]: LOADK     R17 2        ; R17 := 2.000000
 94 [-]: LOADK     R18 1        ; R18 := 1.000000
 95 [-]: LOADBOOL  R19 0 0      ; R19 := false
 96 [-]: CALL      R12 8 1      ; R12(R13,R14,R15,R16,R17,R18,R19)
 97 [-]: SELF      R12 R0 K20   ; R13 := R0; R12 := R0[0x68b88e58]
 98 [-]: LOADBOOL  R14 0 0      ; R14 := false
 99 [-]: CALL      R12 3 1      ; R12(R13,R14)
100 [-]: GETUPVAL  R12 U17      ; R12 := U17
101 [-]: GETTABLE  R12 R12 K25  ; R12 := R12[0x32316a21]
102 [-]: CALL      R12 1 2      ; R12 := R12()
103 [-]: TEST      R12 1        ; if R12 then PC := 109
104 [-]: JMP       109          ; PC := 109
105 [-]: GETGLOBAL R12 K17      ; R12 := 0x6687f6e0
106 [-]: SELF      R12 R12 K18  ; R13 := R12; R12 := R12[0x3a147087]
107 [-]: LOADK     R14 0        ; R14 := 0.000000
108 [-]: CALL      R12 3 1      ; R12(R13,R14)
109 [-]: TEST      R7 0         ; if not R7 then PC := 176
110 [-]: JMP       176          ; PC := 176
111 [-]: EQ        0 R2 R1      ; if R2 ~= R1 then PC := 176
112 [-]: JMP       176          ; PC := 176
113 [-]: SELF      R12 R1 K26   ; R13 := R1; R12 := R1[0xf6ebd926]
114 [-]: CALL      R12 2 2      ; R12 := R12(R13)
115 [-]: GETGLOBAL R13 K27      ; R13 := 0x89326c93
116 [-]: SELF      R13 R13 K28  ; R14 := R13; R13 := R13[0x05909209]
117 [-]: GETGLOBAL R15 K29      ; R15 := 0x18b6fc3f
118 [-]: MOVE      R16 R12      ; R16 := R12
119 [-]: GETGLOBAL R17 K30      ; R17 := ZERO_ROTATION
120 [-]: MOVE      R18 R0       ; R18 := R0
121 [-]: CALL      R13 6 2      ; R13 := R13(R14,R15,R16,R17,R18)
122 [-]: GETGLOBAL R14 K31      ; R14 := 0x7b998233
123 [-]: MOVE      R15 R13      ; R15 := R13
124 [-]: CALL      R14 2 2      ; R14 := R14(R15)
125 [-]: TEST      R14 1        ; if R14 then PC := 131
126 [-]: JMP       131          ; PC := 131
127 [-]: SELF      R14 R13 K32  ; R15 := R13; R14 := R13[0x7679029b]
128 [-]: GETUPVAL  R16 U10      ; R16 := U10
129 [-]: MUL       R16 R16 K33  ; R16 := R16 * 0.800000
130 [-]: CALL      R14 3 1      ; R14(R15,R16)
131 [-]: GETGLOBAL R14 K27      ; R14 := 0x89326c93
132 [-]: SELF      R14 R14 K34  ; R15 := R14; R14 := R14[0x18d05d30]
133 [-]: CALL      R14 2 2      ; R14 := R14(R15)
134 [-]: TEST      R14 0        ; if not R14 then PC := 175
135 [-]: JMP       175          ; PC := 175
136 [-]: GETGLOBAL R14 K35      ; R14 := 0x0469f296
137 [-]: LOADK     R15 K36      ; R15 := "DoAugment"
138 [-]: CALL      R14 2 2      ; R14 := R14(R15)
139 [-]: GETGLOBAL R15 K27      ; R15 := 0x89326c93
140 [-]: SELF      R15 R15 K37  ; R16 := R15; R15 := R15[0xfb669000]
141 [-]: GETGLOBAL R17 K38      ; R17 := gLotusAvatarType
142 [-]: MOVE      R18 R12      ; R18 := R12
143 [-]: LOADK     R19 0        ; R19 := 0.000000
144 [-]: GETUPVAL  R20 U10      ; R20 := U10
145 [-]: CALL      R15 6 2      ; R15 := R15(R16,R17,R18,R19,R20)
146 [-]: GETGLOBAL R16 K39      ; R16 := 0xc8802016
147 [-]: MOVE      R17 R15      ; R17 := R15
148 [-]: CALL      R16 2 4      ; R16,R17,R18 := R16(R17)
149 [-]: JMP       173          ; PC := 173
150 [-]: SELF      R21 R20 K40  ; R22 := R20; R21 := R20[0xee0bc178]
151 [-]: MOVE      R23 R1       ; R23 := R1
152 [-]: CALL      R21 3 2      ; R21 := R21(R22,R23)
153 [-]: TEST      R21 0        ; if not R21 then PC := 173
154 [-]: JMP       173          ; PC := 173
155 [-]: SELF      R21 R20 K41  ; R22 := R20; R21 := R20[0x753a7ea6]
156 [-]: MOVE      R23 R1       ; R23 := R1
157 [-]: CALL      R21 3 2      ; R21 := R21(R22,R23)
158 [-]: TEST      R21 0        ; if not R21 then PC := 173
159 [-]: JMP       173          ; PC := 173
160 [-]: GETGLOBAL R21 K31      ; R21 := 0x7b998233
161 [-]: SELF      R22 R20 K42  ; R23 := R20; R22 := R20[0xde321e6f]
162 [-]: CALL      R22 2 2      ; R22 := R22(R23)
163 [-]: SELF      R22 R22 K43  ; R23 := R22; R22 := R22[0x881b6b90]
164 [-]: LOADK     R24 0        ; R24 := 0.000000
165 [-]: CALL      R22 3 0      ; R22,... := R22(R23,R24)
166 [-]: CALL      R21 0 2      ; R21 := R21(R22,...)
167 [-]: TEST      R21 1        ; if R21 then PC := 173
168 [-]: JMP       173          ; PC := 173
169 [-]: SELF      R21 R20 K44  ; R22 := R20; R21 := R20[0xd5f7912b]
170 [-]: MOVE      R23 R14      ; R23 := R14
171 [-]: LOADBOOL  R24 0 0      ; R24 := false
172 [-]: CALL      R21 4 1      ; R21(R22,R23,R24)
173 [-]: TFORLOOP  R16 2        ; R19,R20 :=  R16(R17,R18); if R19 ~= nil then begin PC = 150; R18 := R19 end
174 [-]: JMP       150          ; PC := 150
175 [-]: RETURN    R0 1         ; return 
176 [-]: LOADBOOL  R21 0 0      ; R21 := false
177 [-]: GETGLOBAL R22 K31      ; R22 := 0x7b998233
178 [-]: MOVE      R23 R2       ; R23 := R2
179 [-]: CALL      R22 2 2      ; R22 := R22(R23)
180 [-]: TEST      R22 1        ; if R22 then PC := 186
181 [-]: JMP       186          ; PC := 186
182 [-]: SELF      R22 R2 K45   ; R23 := R2; R22 := R2[0x2047cfe7]
183 [-]: CALL      R22 2 2      ; R22 := R22(R23)
184 [-]: TEST      R22 0        ; if not R22 then PC := 201
185 [-]: JMP       201          ; PC := 201
186 [-]: GETGLOBAL R22 K27      ; R22 := 0x89326c93
187 [-]: SELF      R22 R22 K34  ; R23 := R22; R22 := R22[0x18d05d30]
188 [-]: CALL      R22 2 2      ; R22 := R22(R23)
189 [-]: TEST      R22 0        ; if not R22 then PC := 199
190 [-]: JMP       199          ; PC := 199
191 [-]: GETUPVAL  R22 U17      ; R22 := U17
192 [-]: GETTABLE  R22 R22 K25  ; R22 := R22[0x32316a21]
193 [-]: CALL      R22 1 2      ; R22 := R22()
194 [-]: TEST      R22 1        ; if R22 then PC := 199
195 [-]: JMP       199          ; PC := 199
196 [-]: SELF      R22 R0 K46   ; R23 := R0; R22 := R0[0xfc80301e]
197 [-]: MOVE      R24 R11      ; R24 := R11
198 [-]: CALL      R22 3 1      ; R22(R23,R24)
199 [-]: LOADBOOL  R21 1 0      ; R21 := true
200 [-]: JMP       214          ; PC := 214
201 [-]: SELF      R22 R2 K47   ; R23 := R2; R22 := R2[0xc4dff581]
202 [-]: LOADK     R24 0        ; R24 := 0.000000
203 [-]: CALL      R22 3 2      ; R22 := R22(R23,R24)
204 [-]: TEST      R22 0        ; if not R22 then PC := 214
205 [-]: JMP       214          ; PC := 214
206 [-]: SELF      R22 R1 K48   ; R23 := R1; R22 := R1[0xa5e492d4]
207 [-]: CALL      R22 2 2      ; R22 := R22(R23)
208 [-]: TEST      R22 0        ; if not R22 then PC := 213
209 [-]: JMP       213          ; PC := 213
210 [-]: SELF      R22 R2 K49   ; R23 := R2; R22 := R2[0x0dd961c5]
211 [-]: MOVE      R24 R1       ; R24 := R1
212 [-]: CALL      R22 3 1      ; R22(R23,R24)
213 [-]: LOADBOOL  R21 1 0      ; R21 := true
214 [-]: TEST      R21 0        ; if not R21 then PC := 241
215 [-]: JMP       241          ; PC := 241
216 [-]: GETGLOBAL R22 K27      ; R22 := 0x89326c93
217 [-]: SELF      R22 R22 K34  ; R23 := R22; R22 := R22[0x18d05d30]
218 [-]: CALL      R22 2 2      ; R22 := R22(R23)
219 [-]: TEST      R22 0        ; if not R22 then PC := 240
220 [-]: JMP       240          ; PC := 240
221 [-]: GETGLOBAL R22 K13      ; R22 := _T
222 [-]: GETTABLE  R22 R22 K14  ; R22 := R22["sporesAbility"]
223 [-]: EQ        1 R22 K15    ; if R22 == nil then PC := 230
224 [-]: JMP       230          ; PC := 230
225 [-]: GETGLOBAL R22 K13      ; R22 := _T
226 [-]: GETTABLE  R22 R22 K14  ; R22 := R22["sporesAbility"]
227 [-]: GETTABLE  R22 R22 R9   ; R22 := R22[R9]
228 [-]: EQ        0 R22 K15    ; if R22 ~= nil then PC := 240
229 [-]: JMP       240          ; PC := 240
230 [-]: SELF      R22 R0 K50   ; R23 := R0; R22 := R0[0x3cc932f9]
231 [-]: GETGLOBAL R24 K17      ; R24 := 0x6687f6e0
232 [-]: GETGLOBAL R25 K35      ; R25 := 0x0469f296
233 [-]: LOADK     R26 K51      ; R26 := "ClientEnd"
234 [-]: CALL      R25 2 2      ; R25 := R25(R26)
235 [-]: GETGLOBAL R26 K3       ; R26 := 0x6c97a788
236 [-]: GETTABLE  R26 R26 K52  ; R26 := R26[0x733fc736]
237 [-]: LOADBOOL  R27 0 0      ; R27 := false
238 [-]: CALL      R26 2 0      ; R26,... := R26(R27)
239 [-]: CALL      R22 0 1      ; R22(R23,...)
240 [-]: RETURN    R0 1         ; return 
241 [-]: GETGLOBAL R22 K13      ; R22 := _T
242 [-]: GETTABLE  R22 R22 K14  ; R22 := R22["sporesAbility"]
243 [-]: EQ        0 R22 K15    ; if R22 ~= nil then PC := 248
244 [-]: JMP       248          ; PC := 248
245 [-]: GETGLOBAL R22 K13      ; R22 := _T
246 [-]: NEWTABLE  R23 0 0      ; R23 := {}
247 [-]: SETTABLE  R22 K14 R23  ; R22["sporesAbility"] := R23
248 [-]: LOADBOOL  R22 0 0      ; R22 := false
249 [-]: GETGLOBAL R23 K13      ; R23 := _T
250 [-]: GETTABLE  R23 R23 K14  ; R23 := R23["sporesAbility"]
251 [-]: GETTABLE  R23 R23 R9   ; R23 := R23[R9]
252 [-]: EQ        0 R23 K15    ; if R23 ~= nil then PC := 266
253 [-]: JMP       266          ; PC := 266
254 [-]: GETGLOBAL R23 K13      ; R23 := _T
255 [-]: GETTABLE  R23 R23 K14  ; R23 := R23["sporesAbility"]
256 [-]: NEWTABLE  R24 0 4      ; R24 := {}
257 [-]: SETTABLE  R24 K53 K2   ; R24["damage"] := 0.000000
258 [-]: NEWTABLE  R25 0 0      ; R25 := {}
259 [-]: SETTABLE  R24 K54 R25  ; R24["sporesInfo"] := R25
260 [-]: SETTABLE  R24 K55 K2   ; R24["aliveTime"] := 0.000000
261 [-]: NEWTABLE  R25 0 0      ; R25 := {}
262 [-]: SETTABLE  R24 K56 R25  ; R24["spreadOnDeath"] := R25
263 [-]: SETTABLE  R23 R9 R24   ; R23[R9] := R24
264 [-]: LOADBOOL  R22 1 0      ; R22 := true
265 [-]: JMP       311          ; PC := 311
266 [-]: GETGLOBAL R23 K13      ; R23 := _T
267 [-]: GETTABLE  R23 R23 K14  ; R23 := R23["sporesAbility"]
268 [-]: GETTABLE  R23 R23 R9   ; R23 := R23[R9]
269 [-]: GETTABLE  R23 R23 K57  ; R23 := R23["drain"]
270 [-]: TEST      R23 1        ; if R23 then PC := 311
271 [-]: JMP       311          ; PC := 311
272 [-]: GETGLOBAL R23 K58      ; R23 := 0x5bced4c4
273 [-]: GETTABLE  R23 R23 K59  ; R23 := R23[0xb62ecfe0]
274 [-]: GETUPVAL  R24 U18      ; R24 := U18
275 [-]: GETGLOBAL R25 K13      ; R25 := _T
276 [-]: GETTABLE  R25 R25 K14  ; R25 := R25["sporesAbility"]
277 [-]: GETTABLE  R25 R25 R9   ; R25 := R25[R9]
278 [-]: GETTABLE  R25 R25 K53  ; R25 := R25["damage"]
279 [-]: GETUPVAL  R26 U7       ; R26 := U7
280 [-]: MUL       R25 R25 R26  ; R25 := R25 * R26
281 [-]: CALL      R23 3 2      ; R23 := R23(R24,R25)
282 [-]: GETGLOBAL R24 K13      ; R24 := _T
283 [-]: GETTABLE  R24 R24 K14  ; R24 := R24["sporesAbility"]
284 [-]: GETTABLE  R24 R24 R9   ; R24 := R24[R9]
285 [-]: GETGLOBAL R25 K58      ; R25 := 0x5bced4c4
286 [-]: GETTABLE  R25 R25 K59  ; R25 := R25[0xb62ecfe0]
287 [-]: LOADK     R26 0        ; R26 := 0.000000
288 [-]: GETGLOBAL R27 K13      ; R27 := _T
289 [-]: GETTABLE  R27 R27 K14  ; R27 := R27["sporesAbility"]
290 [-]: GETTABLE  R27 R27 R9   ; R27 := R27[R9]
291 [-]: GETTABLE  R27 R27 K53  ; R27 := R27["damage"]
292 [-]: SUB       R27 R27 R23  ; R27 := R27 - R23
293 [-]: CALL      R25 3 2      ; R25 := R25(R26,R27)
294 [-]: SETTABLE  R24 K53 R25  ; R24["damage"] := R25
295 [-]: GETGLOBAL R24 K13      ; R24 := _T
296 [-]: GETTABLE  R24 R24 K60  ; R24 := R24["SARYN_ShowSpore"]
297 [-]: EQ        1 R24 K15    ; if R24 == nil then PC := 311
298 [-]: JMP       311          ; PC := 311
299 [-]: GETUPVAL  R24 U17      ; R24 := U17
300 [-]: GETTABLE  R24 R24 K25  ; R24 := R24[0x32316a21]
301 [-]: CALL      R24 1 2      ; R24 := R24()
302 [-]: TEST      R24 1        ; if R24 then PC := 311
303 [-]: JMP       311          ; PC := 311
304 [-]: GETGLOBAL R24 K13      ; R24 := _T
305 [-]: GETTABLE  R24 R24 K61  ; R24 := R24[0xaf5bf978]
306 [-]: GETGLOBAL R25 K13      ; R25 := _T
307 [-]: GETTABLE  R25 R25 K14  ; R25 := R25["sporesAbility"]
308 [-]: GETTABLE  R25 R25 R9   ; R25 := R25[R9]
309 [-]: GETTABLE  R25 R25 K53  ; R25 := R25["damage"]
310 [-]: CALL      R24 2 1      ; R24(R25)
311 [-]: GETGLOBAL R24 K13      ; R24 := _T
312 [-]: GETTABLE  R24 R24 K14  ; R24 := R24["sporesAbility"]
313 [-]: GETTABLE  R24 R24 R9   ; R24 := R24[R9]
314 [-]: GETTABLE  R24 R24 K56  ; R24 := R24["spreadOnDeath"]
315 [-]: SELF      R25 R2 K12   ; R26 := R2; R25 := R2[0x388577d5]
316 [-]: CALL      R25 2 2      ; R25 := R25(R26)
317 [-]: SETTABLE  R24 R25 K62  ; R24[R25] := true
318 [-]: GETGLOBAL R24 K27      ; R24 := 0x89326c93
319 [-]: SELF      R24 R24 K34  ; R25 := R24; R24 := R24[0x18d05d30]
320 [-]: CALL      R24 2 2      ; R24 := R24(R25)
321 [-]: TEST      R24 0        ; if not R24 then PC := 338
322 [-]: JMP       338          ; PC := 338
323 [-]: GETGLOBAL R24 K63      ; R24 := 0xd7f04970
324 [-]: GETUPVAL  R25 U17      ; R25 := U17
325 [-]: GETTABLE  R25 R25 K25  ; R25 := R25[0x32316a21]
326 [-]: CALL      R25 1 2      ; R25 := R25()
327 [-]: TEST      R25 0        ; if not R25 then PC := 330
328 [-]: JMP       330          ; PC := 330
329 [-]: GETGLOBAL R24 K64      ; R24 := 0xec8fb596
330 [-]: SELF      R25 R2 K65   ; R26 := R2; R25 := R2[0x34dc1236]
331 [-]: MOVE      R27 R24      ; R27 := R24
332 [-]: LOADNIL   R28 R28      ; R28 := nil
333 [-]: GETUPVAL  R29 U19      ; R29 := U19
334 [-]: LOADK     R30 12       ; R30 := 12.000000
335 [-]: LOADK     R31 0        ; R31 := 0.000000
336 [-]: MOVE      R32 R1       ; R32 := R1
337 [-]: CALL      R25 8 1      ; R25(R26,R27,R28,R29,R30,R31,R32)
338 [-]: TEST      R22 0        ; if not R22 then PC := 346
339 [-]: JMP       346          ; PC := 346
340 [-]: SELF      R25 R1 K44   ; R26 := R1; R25 := R1[0xd5f7912b]
341 [-]: GETGLOBAL R27 K35      ; R27 := 0x0469f296
342 [-]: LOADK     R28 K66      ; R28 := "TrackSpores"
343 [-]: CALL      R27 2 2      ; R27 := R27(R28)
344 [-]: LOADBOOL  R28 0 0      ; R28 := false
345 [-]: CALL      R25 4 1      ; R25(R26,R27,R28)
346 [-]: GETGLOBAL R25 K27      ; R25 := 0x89326c93
347 [-]: SELF      R25 R25 K67  ; R26 := R25; R25 := R25[0x659d451f]
348 [-]: GETGLOBAL R27 K68      ; R27 := 0x7e11dde2
349 [-]: SELF      R28 R2 K69   ; R29 := R2; R28 := R2[0xef8e8f7f]
350 [-]: CALL      R28 2 2      ; R28 := R28(R29)
351 [-]: LOADBOOL  R29 0 0      ; R29 := false
352 [-]: LOADK     R30 0        ; R30 := 0.000000
353 [-]: MOVE      R31 R1       ; R31 := R1
354 [-]: MOVE      R32 R2       ; R32 := R2
355 [-]: CALL      R25 8 1      ; R25(R26,R27,R28,R29,R30,R31,R32)
356 [-]: GETGLOBAL R25 K13      ; R25 := _T
357 [-]: GETTABLE  R25 R25 K14  ; R25 := R25["sporesAbility"]
358 [-]: EQ        1 R25 K15    ; if R25 == nil then PC := 380
359 [-]: JMP       380          ; PC := 380
360 [-]: GETGLOBAL R25 K13      ; R25 := _T
361 [-]: GETTABLE  R25 R25 K14  ; R25 := R25["sporesAbility"]
362 [-]: GETTABLE  R25 R25 R9   ; R25 := R25[R9]
363 [-]: EQ        1 R25 K15    ; if R25 == nil then PC := 380
364 [-]: JMP       380          ; PC := 380
365 [-]: GETGLOBAL R25 K31      ; R25 := 0x7b998233
366 [-]: MOVE      R26 R1       ; R26 := R1
367 [-]: CALL      R25 2 2      ; R25 := R25(R26)
368 [-]: TEST      R25 1        ; if R25 then PC := 380
369 [-]: JMP       380          ; PC := 380
370 [-]: SELF      R25 R1 K70   ; R26 := R1; R25 := R1[0x16e0b3da]
371 [-]: GETGLOBAL R27 K22      ; R27 := 0x0ed8b456
372 [-]: CALL      R25 3 2      ; R25 := R25(R26,R27)
373 [-]: TEST      R25 1        ; if R25 then PC := 376
374 [-]: JMP       376          ; PC := 376
375 [-]: JMP       380          ; PC := 380
376 [-]: GETGLOBAL R25 K71      ; R25 := 0xcbd666e1
377 [-]: LOADK     R26 0        ; R26 := 0.000000
378 [-]: CALL      R25 2 1      ; R25(R26)
379 [-]: JMP       356          ; PC := 356
380 [-]: SELF      R25 R0 K72   ; R26 := R0; R25 := R0[0x0d0482e0]
381 [-]: CALL      R25 2 1      ; R25(R26)
382 [-]: GETGLOBAL R25 K13      ; R25 := _T
383 [-]: GETTABLE  R25 R25 K14  ; R25 := R25["sporesAbility"]
384 [-]: EQ        1 R25 K15    ; if R25 == nil then PC := 395
385 [-]: JMP       395          ; PC := 395
386 [-]: GETGLOBAL R25 K13      ; R25 := _T
387 [-]: GETTABLE  R25 R25 K14  ; R25 := R25["sporesAbility"]
388 [-]: GETTABLE  R25 R25 R9   ; R25 := R25[R9]
389 [-]: EQ        1 R25 K15    ; if R25 == nil then PC := 395
390 [-]: JMP       395          ; PC := 395
391 [-]: GETGLOBAL R25 K71      ; R25 := 0xcbd666e1
392 [-]: LOADK     R26 1        ; R26 := 1.000000
393 [-]: CALL      R25 2 1      ; R25(R26)
394 [-]: JMP       382          ; PC := 382
395 [-]: RETURN    R0 1         ; return 


; Function #17:
;
; Name:            
; Defined at line: 647
; #Upvalues:       1
; #Parameters:     2
; Is_vararg:       0
; Max Stack Size:  5

  1 [-]: GETUPVAL  R2 U0        ; R2 := U0
  2 [-]: GETTABLE  R2 R2 K0     ; R2 := R2[0x32316a21]
  3 [-]: CALL      R2 1 2       ; R2 := R2()
  4 [-]: TEST      R2 1         ; if R2 then PC := 10
  5 [-]: JMP       10           ; PC := 10
  6 [-]: GETGLOBAL R2 K1        ; R2 := 0x6687f6e0
  7 [-]: SELF      R2 R2 K2     ; R3 := R2; R2 := R2[0x3a147087]
  8 [-]: LOADK     R4 0         ; R4 := 0.000000
  9 [-]: CALL      R2 3 1       ; R2(R3,R4)
 10 [-]: GETGLOBAL R2 K3        ; R2 := 0x7b998233
 11 [-]: MOVE      R3 R1        ; R3 := R1
 12 [-]: CALL      R2 2 2       ; R2 := R2(R3)
 13 [-]: TEST      R2 1         ; if R2 then PC := 24
 14 [-]: JMP       24           ; PC := 24
 15 [-]: SELF      R2 R1 K4     ; R3 := R1; R2 := R1[0x16e0b3da]
 16 [-]: GETGLOBAL R4 K5        ; R4 := 0x0ed8b456
 17 [-]: CALL      R2 3 2       ; R2 := R2(R3,R4)
 18 [-]: TEST      R2 0         ; if not R2 then PC := 24
 19 [-]: JMP       24           ; PC := 24
 20 [-]: GETGLOBAL R2 K6        ; R2 := 0xcbd666e1
 21 [-]: LOADK     R3 0         ; R3 := 0.000000
 22 [-]: CALL      R2 2 1       ; R2(R3)
 23 [-]: JMP       10           ; PC := 10
 24 [-]: GETGLOBAL R2 K6        ; R2 := 0xcbd666e1
 25 [-]: LOADK     R3 0         ; R3 := 0.000000
 26 [-]: CALL      R2 2 1       ; R2(R3)
 27 [-]: RETURN    R0 1         ; return 


; Function #18:
;
; Name:            
; Defined at line: 658
; #Upvalues:       18
; #Parameters:     1
; Is_vararg:       0
; Max Stack Size:  80

  1 [-]: GETGLOBAL R2 K0        ; R2 := 0x7b998233
  2 [-]: MOVE      R3 R1        ; R3 := R1
  3 [-]: CALL      R2 2 2       ; R2 := R2(R3)
  4 [-]: TEST      R2 0         ; if not R2 then PC := 20
  5 [-]: JMP       20           ; PC := 20
  6 [-]: SELF      R2 R0 K1     ; R3 := R0; R2 := R0[0xde321e6f]
  7 [-]: CALL      R2 2 2       ; R2 := R2(R3)
  8 [-]: SELF      R2 R2 K2     ; R3 := R2; R2 := R2[0xf7d48ee0]
  9 [-]: CALL      R2 2 2       ; R2 := R2(R3)
 10 [-]: MOVE      R1 R2        ; R1 := R2
 11 [-]: GETGLOBAL R2 K0        ; R2 := 0x7b998233
 12 [-]: MOVE      R3 R1        ; R3 := R1
 13 [-]: CALL      R2 2 2       ; R2 := R2(R3)
 14 [-]: TEST      R2 0         ; if not R2 then PC := 1
 15 [-]: JMP       1            ; PC := 1
 16 [-]: GETGLOBAL R2 K3        ; R2 := 0xcbd666e1
 17 [-]: LOADK     R3 0         ; R3 := 0.000000
 18 [-]: CALL      R2 2 1       ; R2(R3)
 19 [-]: JMP       1            ; PC := 1
 20 [-]: SELF      R2 R1 K4     ; R3 := R1; R2 := R1[0xdaddfb73]
 21 [-]: GETUPVAL  R4 U0        ; R4 := U0
 22 [-]: CALL      R2 3 2       ; R2 := R2(R3,R4)
 23 [-]: SELF      R3 R0 K5     ; R4 := R0; R3 := R0[0x388577d5]
 24 [-]: CALL      R3 2 2       ; R3 := R3(R4)
 25 [-]: SELF      R4 R0 K1     ; R5 := R0; R4 := R0[0xde321e6f]
 26 [-]: CALL      R4 2 2       ; R4 := R4(R5)
 27 [-]: SELF      R5 R0 K6     ; R6 := R0; R5 := R0[0xa5e492d4]
 28 [-]: CALL      R5 2 2       ; R5 := R5(R6)
 29 [-]: TEST      R5 0         ; if not R5 then PC := 34
 30 [-]: JMP       34           ; PC := 34
 31 [-]: SELF      R5 R4 K7     ; R6 := R4; R5 := R4[0x890379f5]
 32 [-]: CALL      R5 2 2       ; R5 := R5(R6)
 33 [-]: NOT       R5 R5        ; R5 := not R5
 34 [-]: SELF      R6 R0 K8     ; R7 := R0; R6 := R0[0xf80fae85]
 35 [-]: CALL      R6 2 2       ; R6 := R6(R7)
 36 [-]: GETGLOBAL R7 K9        ; R7 := 0x89326c93
 37 [-]: SELF      R7 R7 K10    ; R8 := R7; R7 := R7[0x18d05d30]
 38 [-]: CALL      R7 2 2       ; R7 := R7(R8)
 39 [-]: GETUPVAL  R8 U1        ; R8 := U1
 40 [-]: GETTABLE  R8 R8 K11    ; R8 := R8[0x32316a21]
 41 [-]: CALL      R8 1 2       ; R8 := R8()
 42 [-]: GETUPVAL  R9 U1        ; R9 := U1
 43 [-]: GETTABLE  R9 R9 K12    ; R9 := R9[0xe4ae0e66]
 44 [-]: CALL      R9 1 2       ; R9 := R9()
 45 [-]: GETGLOBAL R10 K13      ; R10 := 0x0469f296
 46 [-]: LOADK     R11 K14      ; R11 := "PoisonDM"
 47 [-]: CALL      R10 2 2      ; R10 := R10(R11)
 48 [-]: GETGLOBAL R11 K15      ; R11 := _T
 49 [-]: GETTABLE  R11 R11 K16  ; R11 := R11["sporesAbility"]
 50 [-]: GETTABLE  R11 R11 R3   ; R11 := R11[R3]
 51 [-]: LOADBOOL  R12 0 0      ; R12 := false
 52 [-]: LOADBOOL  R13 0 0      ; R13 := false
 53 [-]: LOADBOOL  R14 1 0      ; R14 := true
 54 [-]: GETGLOBAL R15 K13      ; R15 := 0x0469f296
 55 [-]: LOADK     R16 K17      ; R16 := "ClientDrainStart"
 56 [-]: CALL      R15 2 2      ; R15 := R15(R16)
 57 [-]: GETGLOBAL R16 K13      ; R16 := 0x0469f296
 58 [-]: LOADK     R17 K18      ; R17 := "ClientDrainStop"
 59 [-]: CALL      R16 2 2      ; R16 := R16(R17)
 60 [-]: LOADK     R17 0        ; R17 := 0.000000
 61 [-]: LOADK     R18 0        ; R18 := 0.000000
 62 [-]: LOADK     R19 0        ; R19 := 0.000000
 63 [-]: GETGLOBAL R20 K19      ; R20 := 0xd7f04970
 64 [-]: GETUPVAL  R21 U1       ; R21 := U1
 65 [-]: GETTABLE  R21 R21 K11  ; R21 := R21[0x32316a21]
 66 [-]: CALL      R21 1 2      ; R21 := R21()
 67 [-]: TEST      R21 0        ; if not R21 then PC := 70
 68 [-]: JMP       70           ; PC := 70
 69 [-]: GETGLOBAL R20 K20      ; R20 := 0xec8fb596
 70 [-]: GETUPVAL  R21 U2       ; R21 := U2
 71 [-]: SELF      R21 R21 K22  ; R22 := R21; R21 := R21[0x111f713c]
 72 [-]: CALL      R21 2 2      ; R21 := R21(R22)
 73 [-]: GETUPVAL  R22 U3       ; R22 := U3
 74 [-]: SUB       R21 R21 R22  ; R21 := R21 - R22
 75 [-]: SETTABLE  R11 K21 R21  ; R11["damage"] := R21
 76 [-]: GETGLOBAL R21 K23      ; R21 := 0x34291f5c
 77 [-]: GETTABLE  R21 R21 K24  ; R21 := R21[0x35c16153]
 78 [-]: CALL      R21 1 2      ; R21 := R21()
 79 [-]: GETUPVAL  R22 U4       ; R22 := U4
 80 [-]: SETTABLE  R21 K25 R22  ; R21["baseProcChance"] := R22
 81 [-]: SETTABLE  R21 K26 K27  ; R21["hitType"] := 5.000000
 82 [-]: SELF      R22 R21 K28  ; R23 := R21; R22 := R21[0x1586e35e]
 83 [-]: LOADK     R24 12       ; R24 := 12.000000
 84 [-]: LOADK     R25 1        ; R25 := 1.000000
 85 [-]: CALL      R22 4 1      ; R22(R23,R24,R25)
 86 [-]: SELF      R22 R21 K29  ; R23 := R21; R22 := R21[0xca73dd2a]
 87 [-]: LOADK     R24 0        ; R24 := 0.000000
 88 [-]: CALL      R22 3 1      ; R22(R23,R24)
 89 [-]: SELF      R22 R21 K30  ; R23 := R21; R22 := R21[0x86cd00cb]
 90 [-]: MOVE      R24 R0       ; R24 := R0
 91 [-]: CALL      R22 3 1      ; R22(R23,R24)
 92 [-]: SELF      R22 R21 K31  ; R23 := R21; R22 := R21[0xf4dc3420]
 93 [-]: MOVE      R24 R1       ; R24 := R1
 94 [-]: CALL      R22 3 1      ; R22(R23,R24)
 95 [-]: SELF      R22 R1 K32   ; R23 := R1; R22 := R1[0x5063edc3]
 96 [-]: GETUPVAL  R24 U0       ; R24 := U0
 97 [-]: CALL      R22 3 2      ; R22 := R22(R23,R24)
 98 [-]: SELF      R23 R1 K33   ; R24 := R1; R23 := R1[0x75ecaf0b]
 99 [-]: GETUPVAL  R25 U0       ; R25 := U0
100 [-]: CALL      R23 3 2      ; R23 := R23(R24,R25)
101 [-]: TESTSET   R24 R6 0     ; if not R6 then PC := 109 else R24 := R6
102 [-]: JMP       109          ; PC := 109
103 [-]: LT        0 K34 R22    ; if 0.000000 >= R22 then PC := 107
104 [-]: JMP       107          ; PC := 107
105 [-]: EQ        1 R23 K36    ; if R23 == 2.000000 then PC := 108
106 [-]: JMP       108          ; PC := 108
107 [-]: LOADBOOL  R24 0 1      ; R24 := false; PC := 108
108 [-]: LOADBOOL  R24 1 0      ; R24 := true
109 [-]: TEST      R24 0        ; if not R24 then PC := 124
110 [-]: JMP       124          ; PC := 124
111 [-]: GETUPVAL  R25 U5       ; R25 := U5
112 [-]: MOVE      R26 R22      ; R26 := R22
113 [-]: MOVE      R27 R23      ; R27 := R23
114 [-]: CALL      R25 3 1      ; R25(R26,R27)
115 [-]: GETUPVAL  R25 U7       ; R25 := U7
116 [-]: MOVE      R26 R0       ; R26 := R0
117 [-]: MOVE      R27 R23      ; R27 := R23
118 [-]: CALL      R25 3 2      ; R25 := R25(R26,R27)
119 [-]: SETUPVAL  R25 U6       ; U82 := 
120 [-]: GETUPVAL  R25 U6       ; R25 := U6
121 [-]: GETUPVAL  R26 U6       ; R26 := U6
122 [-]: MUL       R25 R25 R26  ; R25 := R25 * R26
123 [-]: SETUPVAL  R25 U6       ; U82 := 
124 [-]: TEST      R5 0         ; if not R5 then PC := 151
125 [-]: JMP       151          ; PC := 151
126 [-]: GETGLOBAL R25 K15      ; R25 := _T
127 [-]: GETTABLE  R25 R25 K37  ; R25 := R25[0xa647617f]
128 [-]: GETUPVAL  R26 U0       ; R26 := U0
129 [-]: LOADBOOL  R27 1 0      ; R27 := true
130 [-]: CALL      R25 3 1      ; R25(R26,R27)
131 [-]: GETGLOBAL R25 K15      ; R25 := _T
132 [-]: GETTABLE  R25 R25 K38  ; R25 := R25["SARYN_ShowSpore"]
133 [-]: EQ        1 R25 K39    ; if R25 == nil then PC := 151
134 [-]: JMP       151          ; PC := 151
135 [-]: TEST      R8 1         ; if R8 then PC := 151
136 [-]: JMP       151          ; PC := 151
137 [-]: GETGLOBAL R25 K15      ; R25 := _T
138 [-]: GETTABLE  R25 R25 K40  ; R25 := R25[0xb27d8356]
139 [-]: LOADBOOL  R26 1 0      ; R26 := true
140 [-]: CALL      R25 2 1      ; R25(R26)
141 [-]: GETGLOBAL R25 K15      ; R25 := _T
142 [-]: GETTABLE  R25 R25 K41  ; R25 := R25[0xaf5bf978]
143 [-]: GETUPVAL  R26 U2       ; R26 := U2
144 [-]: SELF      R26 R26 K42  ; R27 := R26; R26 := R26[0x838305de]
145 [-]: CALL      R26 2 0      ; R26,... := R26(R27)
146 [-]: CALL      R25 0 1      ; R25(R26,...)
147 [-]: GETGLOBAL R25 K15      ; R25 := _T
148 [-]: GETTABLE  R25 R25 K43  ; R25 := R25[0xd6aaf3b4]
149 [-]: LOADK     R26 0        ; R26 := 0.000000
150 [-]: CALL      R25 2 1      ; R25(R26)
151 [-]: GETGLOBAL R25 K44      ; R25 := 0x55156ff7
152 [-]: CALL      R25 1 2      ; R25 := R25()
153 [-]: GETGLOBAL R26 K0       ; R26 := 0x7b998233
154 [-]: MOVE      R27 R0       ; R27 := R0
155 [-]: CALL      R26 2 2      ; R26 := R26(R27)
156 [-]: TESTSET   R13 R26 1    ; if R26 then PC := 171 else R13 := R26
157 [-]: JMP       171          ; PC := 171
158 [-]: SELF      R26 R0 K45   ; R27 := R0; R26 := R0[0x2047cfe7]
159 [-]: CALL      R26 2 2      ; R26 := R26(R27)
160 [-]: TESTSET   R13 R26 1    ; if R26 then PC := 171 else R13 := R26
161 [-]: JMP       171          ; PC := 171
162 [-]: GETGLOBAL R26 K0       ; R26 := 0x7b998233
163 [-]: MOVE      R27 R1       ; R27 := R1
164 [-]: CALL      R26 2 2      ; R26 := R26(R27)
165 [-]: TESTSET   R13 R26 1    ; if R26 then PC := 171 else R13 := R26
166 [-]: JMP       171          ; PC := 171
167 [-]: GETGLOBAL R26 K0       ; R26 := 0x7b998233
168 [-]: GETGLOBAL R27 K46      ; R27 := 0x6687f6e0
169 [-]: CALL      R26 2 2      ; R26 := R26(R27)
170 [-]: MOVE      R13 R26      ; R13 := R26
171 [-]: GETGLOBAL R26 K47      ; R26 := 0x67652851
172 [-]: CALL      R26 1 2      ; R26 := R26()
173 [-]: SUB       R18 R18 R26  ; R18 := R18 - R26
174 [-]: LE        0 R18 K34    ; if R18 > 0.000000 then PC := 178
175 [-]: JMP       178          ; PC := 178
176 [-]: LOADK     R17 0        ; R17 := 0.000000
177 [-]: ADD       R18 R18 K48  ; R18 := R18 + 1.000000
178 [-]: GETGLOBAL R26 K49      ; R26 := 0xcfc01047
179 [-]: GETTABLE  R27 R11 K50  ; R27 := R11["sporesInfo"]
180 [-]: CALL      R26 2 4      ; R26,R27,R28 := R26(R27)
181 [-]: JMP       626          ; PC := 626
182 [-]: GETTABLE  R31 R30 K51  ; R31 := R30["avatar"]
183 [-]: GETTABLE  R32 R30 K52  ; R32 := R30["spores"]
184 [-]: MOVE      R33 R13      ; R33 := R13
185 [-]: MOVE      R34 R33      ; R34 := R33
186 [-]: TEST      R33 1        ; if R33 then PC := 290
187 [-]: JMP       290          ; PC := 290
188 [-]: TEST      R8 0         ; if not R8 then PC := 200
189 [-]: JMP       200          ; PC := 200
190 [-]: GETTABLE  R35 R30 K53  ; R35 := R30["tickCount"]
191 [-]: EQ        1 R35 K39    ; if R35 == nil then PC := 200
192 [-]: JMP       200          ; PC := 200
193 [-]: GETTABLE  R35 R30 K53  ; R35 := R30["tickCount"]
194 [-]: LE        0 R35 K34    ; if R35 > 0.000000 then PC := 200
195 [-]: JMP       200          ; PC := 200
196 [-]: LOADBOOL  R35 1 0      ; R35 := true
197 [-]: LOADBOOL  R34 1 0      ; R34 := true
198 [-]: MOVE      R33 R35      ; R33 := R35
199 [-]: JMP       276          ; PC := 276
200 [-]: GETUPVAL  R35 U8       ; R35 := U8
201 [-]: MOVE      R36 R0       ; R36 := R0
202 [-]: MOVE      R37 R31      ; R37 := R31
203 [-]: CALL      R35 3 2      ; R35 := R35(R36,R37)
204 [-]: TEST      R35 1        ; if R35 then PC := 210
205 [-]: JMP       210          ; PC := 210
206 [-]: LOADBOOL  R35 1 0      ; R35 := true
207 [-]: MOVE      R34 R7       ; R34 := R7
208 [-]: MOVE      R33 R35      ; R33 := R35
209 [-]: JMP       276          ; PC := 276
210 [-]: GETGLOBAL R35 K0       ; R35 := 0x7b998233
211 [-]: MOVE      R36 R31      ; R36 := R31
212 [-]: CALL      R35 2 2      ; R35 := R35(R36)
213 [-]: TEST      R35 0        ; if not R35 then PC := 219
214 [-]: JMP       219          ; PC := 219
215 [-]: LOADBOOL  R35 1 0      ; R35 := true
216 [-]: LOADBOOL  R34 1 0      ; R34 := true
217 [-]: MOVE      R33 R35      ; R33 := R35
218 [-]: JMP       276          ; PC := 276
219 [-]: SELF      R35 R31 K45  ; R36 := R31; R35 := R31[0x2047cfe7]
220 [-]: CALL      R35 2 2      ; R35 := R35(R36)
221 [-]: MOVE      R33 R35      ; R33 := R35
222 [-]: SELF      R35 R31 K54  ; R36 := R31; R35 := R31[0xc4dff581]
223 [-]: LOADK     R37 0        ; R37 := 0.000000
224 [-]: CALL      R35 3 2      ; R35 := R35(R36,R37)
225 [-]: MOVE      R34 R35      ; R34 := R35
226 [-]: TEST      R7 0         ; if not R7 then PC := 276
227 [-]: JMP       276          ; PC := 276
228 [-]: TEST      R33 0        ; if not R33 then PC := 276
229 [-]: JMP       276          ; PC := 276
230 [-]: TEST      R34 1        ; if R34 then PC := 276
231 [-]: JMP       276          ; PC := 276
232 [-]: GETTABLE  R35 R11 K55  ; R35 := R11["spreadOnDeath"]
233 [-]: SELF      R36 R31 K5   ; R37 := R31; R36 := R31[0x388577d5]
234 [-]: CALL      R36 2 2      ; R36 := R36(R37)
235 [-]: GETTABLE  R35 R35 R36  ; R35 := R35[R36]
236 [-]: TEST      R35 1        ; if R35 then PC := 276
237 [-]: JMP       276          ; PC := 276
238 [-]: SELF      R35 R31 K56  ; R36 := R31; R35 := R31[0x1ac1655c]
239 [-]: CALL      R35 2 2      ; R35 := R35(R36)
240 [-]: SELF      R35 R35 K57  ; R36 := R35; R35 := R35[0xd2d1302f]
241 [-]: CALL      R35 2 2      ; R35 := R35(R36)
242 [-]: GETTABLE  R36 R35 K26  ; R36 := R35["hitType"]
243 [-]: EQ        0 R36 K27    ; if R36 ~= 5.000000 then PC := 276
244 [-]: JMP       276          ; PC := 276
245 [-]: SELF      R36 R35 K58  ; R37 := R35; R36 := R35[0x52de0ed7]
246 [-]: CALL      R36 2 2      ; R36 := R36(R37)
247 [-]: EQ        0 R36 R0     ; if R36 ~= R0 then PC := 276
248 [-]: JMP       276          ; PC := 276
249 [-]: SELF      R36 R35 K59  ; R37 := R35; R36 := R35[0x14a55974]
250 [-]: CALL      R36 2 2      ; R36 := R36(R37)
251 [-]: EQ        0 R36 R1     ; if R36 ~= R1 then PC := 276
252 [-]: JMP       276          ; PC := 276
253 [-]: SELF      R36 R35 K60  ; R37 := R35; R36 := R35[0x56b2aae2]
254 [-]: LOADK     R38 12       ; R38 := 12.000000
255 [-]: CALL      R36 3 2      ; R36 := R36(R37,R38)
256 [-]: EQ        0 R36 K48    ; if R36 ~= 1.000000 then PC := 276
257 [-]: JMP       276          ; PC := 276
258 [-]: SELF      R36 R31 K61  ; R37 := R31; R36 := R31[0x0542d42b]
259 [-]: GETGLOBAL R38 K62      ; R38 := 0x2f27aa32
260 [-]: CALL      R36 3 2      ; R36 := R36(R37,R38)
261 [-]: TEST      R36 1        ; if R36 then PC := 276
262 [-]: JMP       276          ; PC := 276
263 [-]: SELF      R36 R31 K63  ; R37 := R31; R36 := R31[0xb3ed31dd]
264 [-]: CALL      R36 2 2      ; R36 := R36(R37)
265 [-]: GETGLOBAL R37 K0       ; R37 := 0x7b998233
266 [-]: MOVE      R38 R36      ; R38 := R36
267 [-]: CALL      R37 2 2      ; R37 := R37(R38)
268 [-]: TEST      R37 1        ; if R37 then PC := 275
269 [-]: JMP       275          ; PC := 275
270 [-]: SELF      R37 R36 K61  ; R38 := R36; R37 := R36[0x0542d42b]
271 [-]: GETGLOBAL R39 K62      ; R39 := 0x2f27aa32
272 [-]: CALL      R37 3 2      ; R37 := R37(R38,R39)
273 [-]: TEST      R37 1        ; if R37 then PC := 276
274 [-]: JMP       276          ; PC := 276
275 [-]: LOADBOOL  R34 1 0      ; R34 := true
276 [-]: TEST      R9 0         ; if not R9 then PC := 290
277 [-]: JMP       290          ; PC := 290
278 [-]: GETTABLE  R37 R11 K64  ; R37 := R11["aliveTime"]
279 [-]: GETGLOBAL R38 K47      ; R38 := 0x67652851
280 [-]: CALL      R38 1 2      ; R38 := R38()
281 [-]: ADD       R37 R37 R38  ; R37 := R37 + R38
282 [-]: SETTABLE  R11 K64 R37  ; R11["aliveTime"] := R37
283 [-]: GETTABLE  R37 R11 K64  ; R37 := R11["aliveTime"]
284 [-]: GETGLOBAL R38 K65      ; R38 := 0xcc67df75
285 [-]: LT        0 R38 R37    ; if R38 >= R37 then PC := 290
286 [-]: JMP       290          ; PC := 290
287 [-]: LOADBOOL  R37 1 0      ; R37 := true
288 [-]: LOADBOOL  R34 1 0      ; R34 := true
289 [-]: MOVE      R33 R37      ; R33 := R37
290 [-]: LOADK     R37 0        ; R37 := 0.000000
291 [-]: NEWTABLE  R38 0 0      ; R38 := {}
292 [-]: LEN       R39 R32      ; R39 := # R32
293 [-]: LOADK     R40 1        ; R40 := 1.000000
294 [-]: LOADK     R41 -1       ; R41 := -1.000000
295 [-]: FORPREP   R39 343      ; R39 -= R41; PC := 343
296 [-]: GETTABLE  R43 R32 R42  ; R43 := R32[R42]
297 [-]: GETGLOBAL R44 K0       ; R44 := 0x7b998233
298 [-]: MOVE      R45 R43      ; R45 := R43
299 [-]: CALL      R44 2 2      ; R44 := R44(R45)
300 [-]: TEST      R44 0        ; if not R44 then PC := 309
301 [-]: JMP       309          ; PC := 309
302 [-]: GETGLOBAL R44 K66      ; R44 := 0x33bdd652
303 [-]: GETTABLE  R44 R44 K67  ; R44 := R44[0x9c1f3b5a]
304 [-]: MOVE      R45 R32      ; R45 := R32
305 [-]: MOVE      R46 R42      ; R46 := R42
306 [-]: CALL      R44 3 1      ; R44(R45,R46)
307 [-]: ADD       R37 R37 K48  ; R37 := R37 + 1.000000
308 [-]: JMP       343          ; PC := 343
309 [-]: SELF      R44 R43 K68  ; R45 := R43; R44 := R43[0xd2715720]
310 [-]: CALL      R44 2 2      ; R44 := R44(R45)
311 [-]: LE        0 R44 K34    ; if R44 > 0.000000 then PC := 324
312 [-]: JMP       324          ; PC := 324
313 [-]: GETGLOBAL R44 K66      ; R44 := 0x33bdd652
314 [-]: GETTABLE  R44 R44 K67  ; R44 := R44[0x9c1f3b5a]
315 [-]: MOVE      R45 R32      ; R45 := R32
316 [-]: MOVE      R46 R42      ; R46 := R42
317 [-]: CALL      R44 3 1      ; R44(R45,R46)
318 [-]: SELF      R44 R43 K69  ; R45 := R43; R44 := R43[0x5c96ca7e]
319 [-]: CALL      R44 2 2      ; R44 := R44(R45)
320 [-]: TEST      R44 0        ; if not R44 then PC := 343
321 [-]: JMP       343          ; PC := 343
322 [-]: ADD       R37 R37 K48  ; R37 := R37 + 1.000000
323 [-]: JMP       343          ; PC := 343
324 [-]: TEST      R8 1         ; if R8 then PC := 332
325 [-]: JMP       332          ; PC := 332
326 [-]: SELF      R44 R43 K69  ; R45 := R43; R44 := R43[0x5c96ca7e]
327 [-]: CALL      R44 2 2      ; R44 := R44(R45)
328 [-]: TEST      R44 1        ; if R44 then PC := 332
329 [-]: JMP       332          ; PC := 332
330 [-]: LOADBOOL  R34 1 0      ; R34 := true
331 [-]: JMP       343          ; PC := 343
332 [-]: SELF      R44 R43 K68  ; R45 := R43; R44 := R43[0xd2715720]
333 [-]: CALL      R44 2 2      ; R44 := R44(R45)
334 [-]: SELF      R45 R43 K70  ; R46 := R43; R45 := R43[0x8fc72941]
335 [-]: CALL      R45 2 2      ; R45 := R45(R46)
336 [-]: LT        0 R44 R45    ; if R44 >= R45 then PC := 343
337 [-]: JMP       343          ; PC := 343
338 [-]: GETGLOBAL R44 K66      ; R44 := 0x33bdd652
339 [-]: GETTABLE  R44 R44 K71  ; R44 := R44[0x23d5322f]
340 [-]: MOVE      R45 R38      ; R45 := R38
341 [-]: MOVE      R46 R43      ; R46 := R43
342 [-]: CALL      R44 3 1      ; R44(R45,R46)
343 [-]: FORLOOP   R39 296      ; R39 += R41; if R39 <= R40 then begin PC := 296; R42 := R39 end
344 [-]: TEST      R33 1        ; if R33 then PC := 348
345 [-]: JMP       348          ; PC := 348
346 [-]: TEST      R34 0        ; if not R34 then PC := 377
347 [-]: JMP       377          ; PC := 377
348 [-]: GETGLOBAL R44 K72      ; R44 := 0xc8802016
349 [-]: MOVE      R45 R32      ; R45 := R32
350 [-]: CALL      R44 2 4      ; R44,R45,R46 := R44(R45)
351 [-]: JMP       370          ; PC := 370
352 [-]: GETGLOBAL R49 K0       ; R49 := 0x7b998233
353 [-]: MOVE      R50 R48      ; R50 := R48
354 [-]: CALL      R49 2 2      ; R49 := R49(R50)
355 [-]: TEST      R49 1        ; if R49 then PC := 370
356 [-]: JMP       370          ; PC := 370
357 [-]: TEST      R33 0        ; if not R33 then PC := 365
358 [-]: JMP       365          ; PC := 365
359 [-]: TEST      R7 0         ; if not R7 then PC := 363
360 [-]: JMP       363          ; PC := 363
361 [-]: SELF      R49 R48 K73  ; R50 := R48; R49 := R48[0xa2880940]
362 [-]: CALL      R49 2 1      ; R49(R50)
363 [-]: ADD       R37 R37 K48  ; R37 := R37 + 1.000000
364 [-]: JMP       370          ; PC := 370
365 [-]: SELF      R49 R48 K74  ; R50 := R48; R49 := R48[0xe92524c3]
366 [-]: CALL      R49 2 1      ; R49(R50)
367 [-]: SELF      R49 R48 K75  ; R50 := R48; R49 := R48[0x1db57c6b]
368 [-]: LOADBOOL  R51 0 0      ; R51 := false
369 [-]: CALL      R49 3 1      ; R49(R50,R51)
370 [-]: TFORLOOP  R44 2        ; R47,R48 :=  R44(R45,R46); if R47 ~= nil then begin PC = 352; R46 := R47 end
371 [-]: JMP       352          ; PC := 352
372 [-]: LOADNIL   R32 R32      ; R32 := nil
373 [-]: GETGLOBAL R49 K15      ; R49 := _T
374 [-]: GETTABLE  R49 R49 K76  ; R49 := R49["sporesCount"]
375 [-]: SETTABLE  R49 R29 R37  ; R49[R29] := R37
376 [-]: JMP       428          ; PC := 428
377 [-]: LOADBOOL  R14 1 0      ; R14 := true
378 [-]: TEST      R7 0         ; if not R7 then PC := 393
379 [-]: JMP       393          ; PC := 393
380 [-]: GETTABLE  R49 R11 K77  ; R49 := R11["drain"]
381 [-]: TEST      R49 0        ; if not R49 then PC := 428
382 [-]: JMP       428          ; PC := 428
383 [-]: SELF      R49 R1 K78   ; R50 := R1; R49 := R1[0x3cc932f9]
384 [-]: GETGLOBAL R51 K46      ; R51 := 0x6687f6e0
385 [-]: MOVE      R52 R16      ; R52 := R16
386 [-]: GETGLOBAL R53 K35      ; R53 := 0x6c97a788
387 [-]: GETTABLE  R53 R53 K79  ; R53 := R53[0x733fc736]
388 [-]: LOADBOOL  R54 0 0      ; R54 := false
389 [-]: CALL      R53 2 0      ; R53,... := R53(R54)
390 [-]: CALL      R49 0 1      ; R49(R50,...)
391 [-]: SETTABLE  R11 K77 K39  ; R11["drain"] := nil
392 [-]: JMP       428          ; PC := 428
393 [-]: SELF      R49 R31 K63  ; R50 := R31; R49 := R31[0xb3ed31dd]
394 [-]: CALL      R49 2 2      ; R49 := R49(R50)
395 [-]: GETGLOBAL R50 K0       ; R50 := 0x7b998233
396 [-]: MOVE      R51 R49      ; R51 := R49
397 [-]: CALL      R50 2 2      ; R50 := R50(R51)
398 [-]: TEST      R50 1        ; if R50 then PC := 428
399 [-]: JMP       428          ; PC := 428
400 [-]: GETGLOBAL R50 K72      ; R50 := 0xc8802016
401 [-]: MOVE      R51 R32      ; R51 := R32
402 [-]: CALL      R50 2 4      ; R50,R51,R52 := R50(R51)
403 [-]: JMP       426          ; PC := 426
404 [-]: GETGLOBAL R55 K0       ; R55 := 0x7b998233
405 [-]: MOVE      R56 R54      ; R56 := R54
406 [-]: CALL      R55 2 2      ; R55 := R55(R56)
407 [-]: TEST      R55 1        ; if R55 then PC := 426
408 [-]: JMP       426          ; PC := 426
409 [-]: GETGLOBAL R55 K0       ; R55 := 0x7b998233
410 [-]: SELF      R56 R54 K80  ; R57 := R54; R56 := R54[0x2b54251b]
411 [-]: CALL      R56 2 0      ; R56,... := R56(R57)
412 [-]: CALL      R55 0 2      ; R55 := R55(R56,...)
413 [-]: TEST      R55 0        ; if not R55 then PC := 426
414 [-]: JMP       426          ; PC := 426
415 [-]: SELF      R55 R54 K81  ; R56 := R54; R55 := R54[0xb6b094b2]
416 [-]: MOVE      R57 R49      ; R57 := R49
417 [-]: SELF      R58 R54 K82  ; R59 := R54; R58 := R54[0x6162d901]
418 [-]: CALL      R58 2 0      ; R58,... := R58(R59)
419 [-]: CALL      R55 0 1      ; R55(R56,...)
420 [-]: SELF      R55 R54 K83  ; R56 := R54; R55 := R54[0xe28aa928]
421 [-]: SELF      R57 R54 K84  ; R58 := R54; R57 := R54[0x89531483]
422 [-]: CALL      R57 2 2      ; R57 := R57(R58)
423 [-]: SELF      R58 R54 K85  ; R59 := R54; R58 := R54[0xc6ddbc86]
424 [-]: CALL      R58 2 0      ; R58,... := R58(R59)
425 [-]: CALL      R55 0 1      ; R55(R56,...)
426 [-]: TFORLOOP  R50 2        ; R53,R54 :=  R50(R51,R52); if R53 ~= nil then begin PC = 404; R52 := R53 end
427 [-]: JMP       404          ; PC := 404
428 [-]: LT        1 K34 R37    ; if 0.000000 < R37 then PC := 433
429 [-]: JMP       433          ; PC := 433
430 [-]: LEN       R55 R38      ; R55 := # R38
431 [-]: LT        0 K34 R55    ; if 0.000000 >= R55 then PC := 472
432 [-]: JMP       472          ; PC := 472
433 [-]: GETGLOBAL R55 K15      ; R55 := _T
434 [-]: GETTABLE  R55 R55 K76  ; R55 := R55["sporesCount"]
435 [-]: GETTABLE  R55 R55 R29  ; R55 := R55[R29]
436 [-]: EQ        1 R55 K39    ; if R55 == nil then PC := 445
437 [-]: JMP       445          ; PC := 445
438 [-]: GETGLOBAL R55 K15      ; R55 := _T
439 [-]: GETTABLE  R55 R55 K76  ; R55 := R55["sporesCount"]
440 [-]: GETGLOBAL R56 K15      ; R56 := _T
441 [-]: GETTABLE  R56 R56 K76  ; R56 := R56["sporesCount"]
442 [-]: GETTABLE  R56 R56 R29  ; R56 := R56[R29]
443 [-]: SUB       R56 R56 R37  ; R56 := R56 - R37
444 [-]: SETTABLE  R55 R29 R56  ; R55[R29] := R56
445 [-]: TEST      R7 0         ; if not R7 then PC := 472
446 [-]: JMP       472          ; PC := 472
447 [-]: GETTABLE  R55 R11 K86  ; R55 := R11["burst"]
448 [-]: TEST      R55 1        ; if R55 then PC := 472
449 [-]: JMP       472          ; PC := 472
450 [-]: GETGLOBAL R55 K0       ; R55 := 0x7b998233
451 [-]: MOVE      R56 R31      ; R56 := R31
452 [-]: CALL      R55 2 2      ; R55 := R55(R56)
453 [-]: TEST      R55 1        ; if R55 then PC := 472
454 [-]: JMP       472          ; PC := 472
455 [-]: TEST      R34 1        ; if R34 then PC := 472
456 [-]: JMP       472          ; PC := 472
457 [-]: TEST      R33 0        ; if not R33 then PC := 461
458 [-]: JMP       461          ; PC := 461
459 [-]: LOADK     R37 1        ; R37 := 1.000000
460 [-]: LOADNIL   R38 R38      ; R38 := nil
461 [-]: SELF      R55 R31 K87  ; R56 := R31; R55 := R31[0x34dc1236]
462 [-]: MOVE      R57 R20      ; R57 := R20
463 [-]: MOVE      R58 R38      ; R58 := R38
464 [-]: GETUPVAL  R59 U9       ; R59 := U9
465 [-]: LEN       R60 R38      ; R60 := # R38
466 [-]: ADD       R60 R37 R60  ; R60 := R37 + R60
467 [-]: MUL       R59 R59 R60  ; R59 := R59 * R60
468 [-]: GETUPVAL  R60 U10      ; R60 := U10
469 [-]: GETUPVAL  R61 U11      ; R61 := U11
470 [-]: MOVE      R62 R0       ; R62 := R0
471 [-]: CALL      R55 8 1      ; R55(R56,R57,R58,R59,R60,R61,R62)
472 [-]: GETTABLE  R55 R30 K88  ; R55 := R30["damageTime"]
473 [-]: LE        0 R55 R25    ; if R55 > R25 then PC := 587
474 [-]: JMP       587          ; PC := 587
475 [-]: GETGLOBAL R55 K0       ; R55 := 0x7b998233
476 [-]: MOVE      R56 R31      ; R56 := R31
477 [-]: CALL      R55 2 2      ; R55 := R55(R56)
478 [-]: TEST      R55 1        ; if R55 then PC := 587
479 [-]: JMP       587          ; PC := 587
480 [-]: LEN       R55 R32      ; R55 := # R32
481 [-]: LT        0 K34 R55    ; if 0.000000 >= R55 then PC := 579
482 [-]: JMP       579          ; PC := 579
483 [-]: TEST      R33 1        ; if R33 then PC := 579
484 [-]: JMP       579          ; PC := 579
485 [-]: TEST      R24 0        ; if not R24 then PC := 516
486 [-]: JMP       516          ; PC := 516
487 [-]: SELF      R56 R31 K89  ; R57 := R31; R56 := R31[0x9b2e6c87]
488 [-]: MOVE      R58 R0       ; R58 := R0
489 [-]: CALL      R56 3 2      ; R56 := R56(R57,R58)
490 [-]: GETUPVAL  R57 U6       ; R57 := U6
491 [-]: LE        0 R56 R57    ; if R56 > R57 then PC := 507
492 [-]: JMP       507          ; PC := 507
493 [-]: GETGLOBAL R56 K0       ; R56 := 0x7b998233
494 [-]: GETTABLE  R57 R30 K90  ; R57 := R30["augmentMarker"]
495 [-]: CALL      R56 2 2      ; R56 := R56(R57)
496 [-]: TEST      R56 0        ; if not R56 then PC := 516
497 [-]: JMP       516          ; PC := 516
498 [-]: SELF      R56 R31 K91  ; R57 := R31; R56 := R31[0x47901f07]
499 [-]: GETGLOBAL R58 K92      ; R58 := 0x0bae6aab
500 [-]: GETGLOBAL R59 K93      ; R59 := EMPTY_SYMBOL
501 [-]: GETGLOBAL R60 K94      ; R60 := ZERO_VECTOR
502 [-]: GETGLOBAL R61 K95      ; R61 := ZERO_ROTATION
503 [-]: MOVE      R62 R0       ; R62 := R0
504 [-]: CALL      R56 7 2      ; R56 := R56(R57,R58,R59,R60,R61,R62)
505 [-]: SETTABLE  R30 K90 R56  ; R30["augmentMarker"] := R56
506 [-]: JMP       516          ; PC := 516
507 [-]: GETGLOBAL R56 K0       ; R56 := 0x7b998233
508 [-]: GETTABLE  R57 R30 K90  ; R57 := R30["augmentMarker"]
509 [-]: CALL      R56 2 2      ; R56 := R56(R57)
510 [-]: TEST      R56 1        ; if R56 then PC := 516
511 [-]: JMP       516          ; PC := 516
512 [-]: GETTABLE  R56 R30 K90  ; R56 := R30["augmentMarker"]
513 [-]: SELF      R56 R56 K73  ; R57 := R56; R56 := R56[0xa2880940]
514 [-]: CALL      R56 2 1      ; R56(R57)
515 [-]: SETTABLE  R30 K90 K39  ; R30["augmentMarker"] := nil
516 [-]: GETGLOBAL R56 K9       ; R56 := 0x89326c93
517 [-]: SELF      R56 R56 K96  ; R57 := R56; R56 := R56[0x659d451f]
518 [-]: GETGLOBAL R58 K97      ; R58 := 0x599c95a9
519 [-]: SELF      R59 R31 K98  ; R60 := R31; R59 := R31[0xef8e8f7f]
520 [-]: CALL      R59 2 2      ; R59 := R59(R60)
521 [-]: LOADBOOL  R60 0 0      ; R60 := false
522 [-]: LOADK     R61 0        ; R61 := 0.000000
523 [-]: MOVE      R62 R0       ; R62 := R0
524 [-]: MOVE      R63 R31      ; R63 := R31
525 [-]: CALL      R56 8 1      ; R56(R57,R58,R59,R60,R61,R62,R63)
526 [-]: SELF      R56 R2 K99   ; R57 := R2; R56 := R2[0x30f46140]
527 [-]: CALL      R56 2 2      ; R56 := R56(R57)
528 [-]: TEST      R56 1        ; if R56 then PC := 546
529 [-]: JMP       546          ; PC := 546
530 [-]: GETGLOBAL R56 K100     ; R56 := 0x5bced4c4
531 [-]: GETTABLE  R56 R56 K101 ; R56 := R56[0xac1b386a]
532 [-]: GETUPVAL  R57 U3       ; R57 := U3
533 [-]: GETUPVAL  R58 U12      ; R58 := U12
534 [-]: GETUPVAL  R59 U3       ; R59 := U3
535 [-]: MUL       R58 R58 R59  ; R58 := R58 * R59
536 [-]: SUB       R58 R58 R17  ; R58 := R58 - R17
537 [-]: CALL      R56 3 2      ; R56 := R56(R57,R58)
538 [-]: ADD       R17 R17 R56  ; R17 := R17 + R56
539 [-]: GETGLOBAL R57 K100     ; R57 := 0x5bced4c4
540 [-]: GETTABLE  R57 R57 K101 ; R57 := R57[0xac1b386a]
541 [-]: LOADK     R58 K102     ; R58 := 100000.000000
542 [-]: GETTABLE  R59 R11 K21  ; R59 := R11["damage"]
543 [-]: ADD       R59 R59 R56  ; R59 := R59 + R56
544 [-]: CALL      R57 3 2      ; R57 := R57(R58,R59)
545 [-]: SETTABLE  R11 K21 R57  ; R11["damage"] := R57
546 [-]: GETGLOBAL R57 K23      ; R57 := 0x34291f5c
547 [-]: GETTABLE  R57 R57 K103 ; R57 := R57[0x7258f36f]
548 [-]: GETTABLE  R58 R11 K21  ; R58 := R11["damage"]
549 [-]: CALL      R57 2 2      ; R57 := R57(R58)
550 [-]: SELF      R58 R57 K104 ; R59 := R57; R58 := R57[0xe4c4dc01]
551 [-]: GETUPVAL  R60 U2       ; R60 := U2
552 [-]: CALL      R58 3 1      ; R58(R59,R60)
553 [-]: TEST      R6 0         ; if not R6 then PC := 566
554 [-]: JMP       566          ; PC := 566
555 [-]: SELF      R58 R21 K105 ; R59 := R21; R58 := R21[0xf326045f]
556 [-]: MOVE      R60 R57      ; R60 := R57
557 [-]: CALL      R58 3 1      ; R58(R59,R60)
558 [-]: LOADK     R58 1        ; R58 := 1.000000
559 [-]: MOVE      R59 R55      ; R59 := R55
560 [-]: LOADK     R60 1        ; R60 := 1.000000
561 [-]: FORPREP   R58 565      ; R58 -= R60; PC := 565
562 [-]: SELF      R62 R31 K106 ; R63 := R31; R62 := R31[0x479483bb]
563 [-]: MOVE      R64 R21      ; R64 := R21
564 [-]: CALL      R62 3 1      ; R62(R63,R64)
565 [-]: FORLOOP   R58 562      ; R58 += R60; if R58 <= R59 then begin PC := 562; R61 := R58 end
566 [-]: GETGLOBAL R62 K15      ; R62 := _T
567 [-]: GETTABLE  R62 R62 K107 ; R62 := R62["SARYN_SetSporeDamage"]
568 [-]: EQ        1 R62 K39    ; if R62 == nil then PC := 579
569 [-]: JMP       579          ; PC := 579
570 [-]: TEST      R5 0         ; if not R5 then PC := 579
571 [-]: JMP       579          ; PC := 579
572 [-]: TEST      R8 1         ; if R8 then PC := 579
573 [-]: JMP       579          ; PC := 579
574 [-]: GETGLOBAL R62 K15      ; R62 := _T
575 [-]: GETTABLE  R62 R62 K41  ; R62 := R62[0xaf5bf978]
576 [-]: SELF      R63 R57 K42  ; R64 := R57; R63 := R57[0x838305de]
577 [-]: CALL      R63 2 0      ; R63,... := R63(R64)
578 [-]: CALL      R62 0 1      ; R62(R63,...)
579 [-]: ADD       R62 R25 K48  ; R62 := R25 + 1.000000
580 [-]: SETTABLE  R30 K88 R62  ; R30["damageTime"] := R62
581 [-]: GETTABLE  R62 R30 K53  ; R62 := R30["tickCount"]
582 [-]: EQ        1 R62 K39    ; if R62 == nil then PC := 587
583 [-]: JMP       587          ; PC := 587
584 [-]: GETTABLE  R62 R30 K53  ; R62 := R30["tickCount"]
585 [-]: SUB       R62 R62 K48  ; R62 := R62 - 1.000000
586 [-]: SETTABLE  R30 K53 R62  ; R30["tickCount"] := R62
587 [-]: GETGLOBAL R62 K15      ; R62 := _T
588 [-]: GETTABLE  R62 R62 K76  ; R62 := R62["sporesCount"]
589 [-]: GETTABLE  R62 R62 R29  ; R62 := R62[R29]
590 [-]: EQ        0 R62 K34    ; if R62 ~= 0.000000 then PC := 606
591 [-]: JMP       606          ; PC := 606
592 [-]: GETGLOBAL R62 K0       ; R62 := 0x7b998233
593 [-]: MOVE      R63 R31      ; R63 := R31
594 [-]: CALL      R62 2 2      ; R62 := R62(R63)
595 [-]: TEST      R62 1        ; if R62 then PC := 602
596 [-]: JMP       602          ; PC := 602
597 [-]: SELF      R62 R31 K56  ; R63 := R31; R62 := R31[0x1ac1655c]
598 [-]: CALL      R62 2 2      ; R62 := R62(R63)
599 [-]: SELF      R62 R62 K108 ; R63 := R62; R62 := R62[0x55481e0d]
600 [-]: MOVE      R64 R10      ; R64 := R10
601 [-]: CALL      R62 3 1      ; R62(R63,R64)
602 [-]: GETGLOBAL R62 K15      ; R62 := _T
603 [-]: GETTABLE  R62 R62 K76  ; R62 := R62["sporesCount"]
604 [-]: SETTABLE  R62 R29 K39  ; R62[R29] := nil
605 [-]: LOADNIL   R32 R32      ; R32 := nil
606 [-]: LEN       R62 R32      ; R62 := # R32
607 [-]: EQ        0 R62 K34    ; if R62 ~= 0.000000 then PC := 626
608 [-]: JMP       626          ; PC := 626
609 [-]: GETGLOBAL R62 K0       ; R62 := 0x7b998233
610 [-]: GETTABLE  R63 R30 K90  ; R63 := R30["augmentMarker"]
611 [-]: CALL      R62 2 2      ; R62 := R62(R63)
612 [-]: TEST      R62 1        ; if R62 then PC := 617
613 [-]: JMP       617          ; PC := 617
614 [-]: GETTABLE  R62 R30 K90  ; R62 := R30["augmentMarker"]
615 [-]: SELF      R62 R62 K73  ; R63 := R62; R62 := R62[0xa2880940]
616 [-]: CALL      R62 2 1      ; R62(R63)
617 [-]: GETTABLE  R62 R11 K50  ; R62 := R11["sporesInfo"]
618 [-]: SETTABLE  R62 R29 K39  ; R62[R29] := nil
619 [-]: GETGLOBAL R62 K109     ; R62 := 0x4ec73e73
620 [-]: GETTABLE  R63 R11 K50  ; R63 := R11["sporesInfo"]
621 [-]: CALL      R62 2 2      ; R62 := R62(R63)
622 [-]: EQ        0 R62 K39    ; if R62 ~= nil then PC := 626
623 [-]: JMP       626          ; PC := 626
624 [-]: NEWTABLE  R62 0 0      ; R62 := {}
625 [-]: SETTABLE  R11 K50 R62  ; R11["sporesInfo"] := R62
626 [-]: TFORLOOP  R26 2        ; R29,R30 :=  R26(R27,R28); if R29 ~= nil then begin PC = 182; R28 := R29 end
627 [-]: JMP       182          ; PC := 182
628 [-]: GETTABLE  R62 R11 K86  ; R62 := R11["burst"]
629 [-]: TEST      R62 1        ; if R62 then PC := 823
630 [-]: JMP       823          ; PC := 823
631 [-]: TEST      R13 0        ; if not R13 then PC := 634
632 [-]: JMP       634          ; PC := 634
633 [-]: JMP       823          ; PC := 823
634 [-]: TEST      R7 0         ; if not R7 then PC := 641
635 [-]: JMP       641          ; PC := 641
636 [-]: GETGLOBAL R62 K109     ; R62 := 0x4ec73e73
637 [-]: GETTABLE  R63 R11 K50  ; R63 := R11["sporesInfo"]
638 [-]: CALL      R62 2 2      ; R62 := R62(R63)
639 [-]: EQ        1 R62 K39    ; if R62 == nil then PC := 644
640 [-]: JMP       644          ; PC := 644
641 [-]: GETTABLE  R62 R11 K77  ; R62 := R11["drain"]
642 [-]: JMP       645          ; PC := 645
643 [-]: LOADBOOL  R62 0 1      ; R62 := false; PC := 644
644 [-]: LOADBOOL  R62 1 0      ; R62 := true
645 [-]: TEST      R62 1        ; if R62 then PC := 651
646 [-]: JMP       651          ; PC := 651
647 [-]: SELF      R63 R2 K99   ; R64 := R2; R63 := R2[0x30f46140]
648 [-]: CALL      R63 2 2      ; R63 := R63(R64)
649 [-]: TEST      R63 0        ; if not R63 then PC := 749
650 [-]: JMP       749          ; PC := 749
651 [-]: SETTABLE  R11 K77 R62  ; R11["drain"] := R62
652 [-]: GETGLOBAL R63 K47      ; R63 := 0x67652851
653 [-]: CALL      R63 1 2      ; R63 := R63()
654 [-]: SUB       R19 R19 R63  ; R19 := R19 - R63
655 [-]: LE        0 R19 K34    ; if R19 > 0.000000 then PC := 750
656 [-]: JMP       750          ; PC := 750
657 [-]: SELF      R63 R2 K99   ; R64 := R2; R63 := R2[0x30f46140]
658 [-]: CALL      R63 2 2      ; R63 := R63(R64)
659 [-]: TEST      R63 0        ; if not R63 then PC := 676
660 [-]: JMP       676          ; PC := 676
661 [-]: GETGLOBAL R63 K100     ; R63 := 0x5bced4c4
662 [-]: GETTABLE  R63 R63 K110 ; R63 := R63[0xb62ecfe0]
663 [-]: GETUPVAL  R64 U13      ; R64 := U13
664 [-]: GETTABLE  R65 R11 K21  ; R65 := R11["damage"]
665 [-]: GETUPVAL  R66 U14      ; R66 := U14
666 [-]: MUL       R65 R65 R66  ; R65 := R65 * R66
667 [-]: CALL      R63 3 2      ; R63 := R63(R64,R65)
668 [-]: GETGLOBAL R64 K100     ; R64 := 0x5bced4c4
669 [-]: GETTABLE  R64 R64 K110 ; R64 := R64[0xb62ecfe0]
670 [-]: LOADK     R65 0        ; R65 := 0.000000
671 [-]: GETTABLE  R66 R11 K21  ; R66 := R11["damage"]
672 [-]: SUB       R66 R66 R63  ; R66 := R66 - R63
673 [-]: CALL      R64 3 2      ; R64 := R64(R65,R66)
674 [-]: SETTABLE  R11 K21 R64  ; R11["damage"] := R64
675 [-]: JMP       718          ; PC := 718
676 [-]: TEST      R14 0        ; if not R14 then PC := 704
677 [-]: JMP       704          ; PC := 704
678 [-]: GETGLOBAL R64 K100     ; R64 := 0x5bced4c4
679 [-]: GETTABLE  R64 R64 K110 ; R64 := R64[0xb62ecfe0]
680 [-]: GETUPVAL  R65 U15      ; R65 := U15
681 [-]: GETTABLE  R66 R11 K21  ; R66 := R11["damage"]
682 [-]: GETUPVAL  R67 U16      ; R67 := U16
683 [-]: MUL       R66 R66 R67  ; R66 := R66 * R67
684 [-]: CALL      R64 3 2      ; R64 := R64(R65,R66)
685 [-]: GETGLOBAL R65 K100     ; R65 := 0x5bced4c4
686 [-]: GETTABLE  R65 R65 K110 ; R65 := R65[0xb62ecfe0]
687 [-]: LOADK     R66 0        ; R66 := 0.000000
688 [-]: GETTABLE  R67 R11 K21  ; R67 := R11["damage"]
689 [-]: SUB       R67 R67 R64  ; R67 := R67 - R64
690 [-]: CALL      R65 3 2      ; R65 := R65(R66,R67)
691 [-]: SETTABLE  R11 K21 R65  ; R11["damage"] := R65
692 [-]: LOADBOOL  R14 0 0      ; R14 := false
693 [-]: TEST      R7 0         ; if not R7 then PC := 718
694 [-]: JMP       718          ; PC := 718
695 [-]: SELF      R65 R1 K78   ; R66 := R1; R65 := R1[0x3cc932f9]
696 [-]: GETGLOBAL R67 K46      ; R67 := 0x6687f6e0
697 [-]: MOVE      R68 R15      ; R68 := R15
698 [-]: GETGLOBAL R69 K35      ; R69 := 0x6c97a788
699 [-]: GETTABLE  R69 R69 K79  ; R69 := R69[0x733fc736]
700 [-]: LOADBOOL  R70 0 0      ; R70 := false
701 [-]: CALL      R69 2 0      ; R69,... := R69(R70)
702 [-]: CALL      R65 0 1      ; R65(R66,...)
703 [-]: JMP       718          ; PC := 718
704 [-]: GETGLOBAL R65 K100     ; R65 := 0x5bced4c4
705 [-]: GETTABLE  R65 R65 K110 ; R65 := R65[0xb62ecfe0]
706 [-]: GETUPVAL  R66 U13      ; R66 := U13
707 [-]: GETTABLE  R67 R11 K21  ; R67 := R11["damage"]
708 [-]: GETUPVAL  R68 U17      ; R68 := U17
709 [-]: MUL       R67 R67 R68  ; R67 := R67 * R68
710 [-]: CALL      R65 3 2      ; R65 := R65(R66,R67)
711 [-]: GETGLOBAL R66 K100     ; R66 := 0x5bced4c4
712 [-]: GETTABLE  R66 R66 K110 ; R66 := R66[0xb62ecfe0]
713 [-]: LOADK     R67 0        ; R67 := 0.000000
714 [-]: GETTABLE  R68 R11 K21  ; R68 := R11["damage"]
715 [-]: SUB       R68 R68 R65  ; R68 := R68 - R65
716 [-]: CALL      R66 3 2      ; R66 := R66(R67,R68)
717 [-]: SETTABLE  R11 K21 R66  ; R11["damage"] := R66
718 [-]: GETGLOBAL R66 K15      ; R66 := _T
719 [-]: GETTABLE  R66 R66 K107 ; R66 := R66["SARYN_SetSporeDamage"]
720 [-]: EQ        1 R66 K39    ; if R66 == nil then PC := 738
721 [-]: JMP       738          ; PC := 738
722 [-]: TEST      R5 0         ; if not R5 then PC := 738
723 [-]: JMP       738          ; PC := 738
724 [-]: TEST      R8 1         ; if R8 then PC := 738
725 [-]: JMP       738          ; PC := 738
726 [-]: GETGLOBAL R66 K23      ; R66 := 0x34291f5c
727 [-]: GETTABLE  R66 R66 K103 ; R66 := R66[0x7258f36f]
728 [-]: GETTABLE  R67 R11 K21  ; R67 := R11["damage"]
729 [-]: CALL      R66 2 2      ; R66 := R66(R67)
730 [-]: SELF      R67 R66 K104 ; R68 := R66; R67 := R66[0xe4c4dc01]
731 [-]: GETUPVAL  R69 U2       ; R69 := U2
732 [-]: CALL      R67 3 1      ; R67(R68,R69)
733 [-]: GETGLOBAL R67 K15      ; R67 := _T
734 [-]: GETTABLE  R67 R67 K41  ; R67 := R67[0xaf5bf978]
735 [-]: SELF      R68 R66 K42  ; R69 := R66; R68 := R66[0x838305de]
736 [-]: CALL      R68 2 0      ; R68,... := R68(R69)
737 [-]: CALL      R67 0 1      ; R67(R68,...)
738 [-]: GETTABLE  R67 R11 K21  ; R67 := R11["damage"]
739 [-]: GETUPVAL  R68 U2       ; R68 := U2
740 [-]: SELF      R68 R68 K22  ; R69 := R68; R68 := R68[0x111f713c]
741 [-]: CALL      R68 2 2      ; R68 := R68(R69)
742 [-]: LT        0 R67 R68    ; if R67 >= R68 then PC := 747
743 [-]: JMP       747          ; PC := 747
744 [-]: TEST      R62 0        ; if not R62 then PC := 747
745 [-]: JMP       747          ; PC := 747
746 [-]: JMP       823          ; PC := 823
747 [-]: ADD       R19 R19 K111 ; R19 := R19 + 0.500000
748 [-]: JMP       750          ; PC := 750
749 [-]: LOADK     R19 0        ; R19 := 0.000000
750 [-]: GETGLOBAL R67 K0       ; R67 := 0x7b998233
751 [-]: MOVE      R68 R0       ; R68 := R0
752 [-]: CALL      R67 2 2      ; R67 := R67(R68)
753 [-]: TEST      R67 1        ; if R67 then PC := 771
754 [-]: JMP       771          ; PC := 771
755 [-]: SELF      R67 R0 K6    ; R68 := R0; R67 := R0[0xa5e492d4]
756 [-]: CALL      R67 2 2      ; R67 := R67(R68)
757 [-]: TEST      R67 0        ; if not R67 then PC := 762
758 [-]: JMP       762          ; PC := 762
759 [-]: SELF      R67 R4 K7    ; R68 := R4; R67 := R4[0x890379f5]
760 [-]: CALL      R67 2 2      ; R67 := R67(R68)
761 [-]: NOT       R67 R67      ; R67 := not R67
762 [-]: EQ        1 R5 R67     ; if R5 == R67 then PC := 771
763 [-]: JMP       771          ; PC := 771
764 [-]: NOT       R5 R5        ; R5 := not R5
765 [-]: GETGLOBAL R67 K15      ; R67 := _T
766 [-]: GETTABLE  R67 R67 K37  ; R67 := R67[0xa647617f]
767 [-]: GETUPVAL  R68 U0       ; R68 := U0
768 [-]: MOVE      R69 R5       ; R69 := R5
769 [-]: CALL      R67 3 1      ; R67(R68,R69)
770 [-]: LOADBOOL  R12 1 0      ; R12 := true
771 [-]: TEST      R5 0         ; if not R5 then PC := 819
772 [-]: JMP       819          ; PC := 819
773 [-]: TEST      R8 1         ; if R8 then PC := 819
774 [-]: JMP       819          ; PC := 819
775 [-]: GETGLOBAL R67 K15      ; R67 := _T
776 [-]: GETTABLE  R67 R67 K112 ; R67 := R67["SARYN_SetInfected"]
777 [-]: EQ        1 R67 K39    ; if R67 == nil then PC := 819
778 [-]: JMP       819          ; PC := 819
779 [-]: LOADK     R67 0        ; R67 := 0.000000
780 [-]: GETGLOBAL R68 K49      ; R68 := 0xcfc01047
781 [-]: GETTABLE  R69 R11 K50  ; R69 := R11["sporesInfo"]
782 [-]: CALL      R68 2 4      ; R68,R69,R70 := R68(R69)
783 [-]: JMP       794          ; PC := 794
784 [-]: GETGLOBAL R73 K0       ; R73 := 0x7b998233
785 [-]: GETTABLE  R74 R72 K51  ; R74 := R72["avatar"]
786 [-]: CALL      R73 2 2      ; R73 := R73(R74)
787 [-]: TEST      R73 1        ; if R73 then PC := 794
788 [-]: JMP       794          ; PC := 794
789 [-]: GETTABLE  R73 R72 K52  ; R73 := R72["spores"]
790 [-]: LEN       R73 R73      ; R73 := # R73
791 [-]: LT        0 K34 R73    ; if 0.000000 >= R73 then PC := 794
792 [-]: JMP       794          ; PC := 794
793 [-]: ADD       R67 R67 K48  ; R67 := R67 + 1.000000
794 [-]: TFORLOOP  R68 2        ; R71,R72 :=  R68(R69,R70); if R71 ~= nil then begin PC = 784; R70 := R71 end
795 [-]: JMP       784          ; PC := 784
796 [-]: GETGLOBAL R73 K15      ; R73 := _T
797 [-]: GETTABLE  R73 R73 K43  ; R73 := R73[0xd6aaf3b4]
798 [-]: MOVE      R74 R67      ; R74 := R67
799 [-]: CALL      R73 2 1      ; R73(R74)
800 [-]: TEST      R12 0        ; if not R12 then PC := 819
801 [-]: JMP       819          ; PC := 819
802 [-]: GETGLOBAL R73 K15      ; R73 := _T
803 [-]: GETTABLE  R73 R73 K40  ; R73 := R73[0xb27d8356]
804 [-]: LOADBOOL  R74 1 0      ; R74 := true
805 [-]: CALL      R73 2 1      ; R73(R74)
806 [-]: GETGLOBAL R73 K23      ; R73 := 0x34291f5c
807 [-]: GETTABLE  R73 R73 K103 ; R73 := R73[0x7258f36f]
808 [-]: GETTABLE  R74 R11 K21  ; R74 := R11["damage"]
809 [-]: CALL      R73 2 2      ; R73 := R73(R74)
810 [-]: SELF      R74 R73 K104 ; R75 := R73; R74 := R73[0xe4c4dc01]
811 [-]: GETUPVAL  R76 U2       ; R76 := U2
812 [-]: CALL      R74 3 1      ; R74(R75,R76)
813 [-]: GETGLOBAL R74 K15      ; R74 := _T
814 [-]: GETTABLE  R74 R74 K41  ; R74 := R74[0xaf5bf978]
815 [-]: SELF      R75 R73 K42  ; R76 := R73; R75 := R73[0x838305de]
816 [-]: CALL      R75 2 0      ; R75,... := R75(R76)
817 [-]: CALL      R74 0 1      ; R74(R75,...)
818 [-]: LOADBOOL  R12 0 0      ; R12 := false
819 [-]: GETGLOBAL R74 K3       ; R74 := 0xcbd666e1
820 [-]: LOADK     R75 0        ; R75 := 0.000000
821 [-]: CALL      R74 2 1      ; R74(R75)
822 [-]: JMP       151          ; PC := 151
823 [-]: TEST      R5 0         ; if not R5 then PC := 840
824 [-]: JMP       840          ; PC := 840
825 [-]: GETGLOBAL R74 K15      ; R74 := _T
826 [-]: GETTABLE  R74 R74 K37  ; R74 := R74[0xa647617f]
827 [-]: GETUPVAL  R75 U0       ; R75 := U0
828 [-]: LOADBOOL  R76 0 0      ; R76 := false
829 [-]: CALL      R74 3 1      ; R74(R75,R76)
830 [-]: GETGLOBAL R74 K15      ; R74 := _T
831 [-]: GETTABLE  R74 R74 K38  ; R74 := R74["SARYN_ShowSpore"]
832 [-]: EQ        1 R74 K39    ; if R74 == nil then PC := 840
833 [-]: JMP       840          ; PC := 840
834 [-]: TEST      R8 1         ; if R8 then PC := 840
835 [-]: JMP       840          ; PC := 840
836 [-]: GETGLOBAL R74 K15      ; R74 := _T
837 [-]: GETTABLE  R74 R74 K40  ; R74 := R74[0xb27d8356]
838 [-]: LOADBOOL  R75 0 0      ; R75 := false
839 [-]: CALL      R74 2 1      ; R74(R75)
840 [-]: TEST      R7 0         ; if not R7 then PC := 864
841 [-]: JMP       864          ; PC := 864
842 [-]: GETGLOBAL R74 K0       ; R74 := 0x7b998233
843 [-]: MOVE      R75 R1       ; R75 := R1
844 [-]: CALL      R74 2 2      ; R74 := R74(R75)
845 [-]: TEST      R74 1        ; if R74 then PC := 864
846 [-]: JMP       864          ; PC := 864
847 [-]: GETGLOBAL R74 K0       ; R74 := 0x7b998233
848 [-]: GETGLOBAL R75 K46      ; R75 := 0x6687f6e0
849 [-]: CALL      R74 2 2      ; R74 := R74(R75)
850 [-]: TEST      R74 1        ; if R74 then PC := 864
851 [-]: JMP       864          ; PC := 864
852 [-]: TEST      R13 1        ; if R13 then PC := 864
853 [-]: JMP       864          ; PC := 864
854 [-]: SELF      R74 R1 K78   ; R75 := R1; R74 := R1[0x3cc932f9]
855 [-]: GETGLOBAL R76 K46      ; R76 := 0x6687f6e0
856 [-]: GETGLOBAL R77 K13      ; R77 := 0x0469f296
857 [-]: LOADK     R78 K113     ; R78 := "ClientEnd"
858 [-]: CALL      R77 2 2      ; R77 := R77(R78)
859 [-]: GETGLOBAL R78 K35      ; R78 := 0x6c97a788
860 [-]: GETTABLE  R78 R78 K79  ; R78 := R78[0x733fc736]
861 [-]: LOADBOOL  R79 0 0      ; R79 := false
862 [-]: CALL      R78 2 0      ; R78,... := R78(R79)
863 [-]: CALL      R74 0 1      ; R74(R75,...)
864 [-]: GETGLOBAL R74 K15      ; R74 := _T
865 [-]: GETTABLE  R74 R74 K16  ; R74 := R74["sporesAbility"]
866 [-]: SETTABLE  R74 R3 K39   ; R74[R3] := nil
867 [-]: GETGLOBAL R74 K109     ; R74 := 0x4ec73e73
868 [-]: GETGLOBAL R75 K15      ; R75 := _T
869 [-]: GETTABLE  R75 R75 K16  ; R75 := R75["sporesAbility"]
870 [-]: CALL      R74 2 2      ; R74 := R74(R75)
871 [-]: EQ        0 R74 K39    ; if R74 ~= nil then PC := 875
872 [-]: JMP       875          ; PC := 875
873 [-]: GETGLOBAL R74 K15      ; R74 := _T
874 [-]: SETTABLE  R74 K16 K39  ; R74["sporesAbility"] := nil
875 [-]: RETURN    R0 1         ; return 


; Function #19:
;
; Name:            
; Defined at line: 1015
; #Upvalues:       5
; #Parameters:     1
; Is_vararg:       0
; Max Stack Size:  16

  1 [-]: SELF      R1 R0 K0     ; R2 := R0; R1 := R0[0xed324116]
  2 [-]: CALL      R1 2 2       ; R1 := R1(R2)
  3 [-]: GETGLOBAL R2 K1        ; R2 := 0x7b998233
  4 [-]: MOVE      R3 R1        ; R3 := R1
  5 [-]: CALL      R2 2 2       ; R2 := R2(R3)
  6 [-]: TEST      R2 1         ; if R2 then PC := 12
  7 [-]: JMP       12           ; PC := 12
  8 [-]: SELF      R2 R1 K2     ; R3 := R1; R2 := R1[0x2047cfe7]
  9 [-]: CALL      R2 2 2       ; R2 := R2(R3)
 10 [-]: TEST      R2 0         ; if not R2 then PC := 17
 11 [-]: JMP       17           ; PC := 17
 12 [-]: GETGLOBAL R2 K3        ; R2 := 0x89326c93
 13 [-]: SELF      R2 R2 K4     ; R3 := R2; R2 := R2[0x59c96e77]
 14 [-]: MOVE      R4 R0        ; R4 := R0
 15 [-]: CALL      R2 3 1       ; R2(R3,R4)
 16 [-]: RETURN    R0 1         ; return 
 17 [-]: SELF      R2 R1 K5     ; R3 := R1; R2 := R1[0xde321e6f]
 18 [-]: CALL      R2 2 2       ; R2 := R2(R3)
 19 [-]: SELF      R2 R2 K6     ; R3 := R2; R2 := R2[0xf7d48ee0]
 20 [-]: CALL      R2 2 2       ; R2 := R2(R3)
 21 [-]: GETGLOBAL R3 K1        ; R3 := 0x7b998233
 22 [-]: MOVE      R4 R2        ; R4 := R2
 23 [-]: CALL      R3 2 2       ; R3 := R3(R4)
 24 [-]: TEST      R3 0         ; if not R3 then PC := 31
 25 [-]: JMP       31           ; PC := 31
 26 [-]: GETGLOBAL R3 K3        ; R3 := 0x89326c93
 27 [-]: SELF      R3 R3 K4     ; R4 := R3; R3 := R3[0x59c96e77]
 28 [-]: MOVE      R5 R0        ; R5 := R0
 29 [-]: CALL      R3 3 1       ; R3(R4,R5)
 30 [-]: RETURN    R0 1         ; return 
 31 [-]: SELF      R3 R2 K7     ; R4 := R2; R3 := R2[0xdaddfb73]
 32 [-]: GETUPVAL  R5 U0        ; R5 := U0
 33 [-]: CALL      R3 3 2       ; R3 := R3(R4,R5)
 34 [-]: GETGLOBAL R4 K1        ; R4 := 0x7b998233
 35 [-]: MOVE      R5 R3        ; R5 := R3
 36 [-]: CALL      R4 2 2       ; R4 := R4(R5)
 37 [-]: TEST      R4 0         ; if not R4 then PC := 44
 38 [-]: JMP       44           ; PC := 44
 39 [-]: GETGLOBAL R4 K3        ; R4 := 0x89326c93
 40 [-]: SELF      R4 R4 K4     ; R5 := R4; R4 := R4[0x59c96e77]
 41 [-]: MOVE      R6 R0        ; R6 := R0
 42 [-]: CALL      R4 3 1       ; R4(R5,R6)
 43 [-]: RETURN    R0 1         ; return 
 44 [-]: GETGLOBAL R4 K3        ; R4 := 0x89326c93
 45 [-]: SELF      R4 R4 K8     ; R5 := R4; R4 := R4[0x21dbe06c]
 46 [-]: GETGLOBAL R6 K9        ; R6 := 0x4d41bf8c
 47 [-]: SELF      R7 R0 K10    ; R8 := R0; R7 := R0[0xd1586535]
 48 [-]: CALL      R7 2 2       ; R7 := R7(R8)
 49 [-]: GETGLOBAL R8 K11       ; R8 := ZERO_ROTATION
 50 [-]: MOVE      R9 R2        ; R9 := R2
 51 [-]: CALL      R4 6 1       ; R4(R5,R6,R7,R8,R9)
 52 [-]: NEWTABLE  R4 5 0       ; R4 := {}
 53 [-]: LOADK     R5 K12       ; R5 := 0.360000
 54 [-]: LOADK     R6 K13       ; R6 := 0.400000
 55 [-]: LOADK     R7 K13       ; R7 := 0.400000
 56 [-]: LOADK     R8 K12       ; R8 := 0.360000
 57 [-]: LOADK     R9 K12       ; R9 := 0.360000
 58 [-]: SETLIST   R4 5 1       ; R4[(1-1)*FPF+i] := R(4+i), 1 <= i <= 5
 59 [-]: SELF      R5 R3 K14    ; R6 := R3; R5 := R3[0x0c5e62f9]
 60 [-]: LOADK     R7 1         ; R7 := 1.000000
 61 [-]: LEN       R8 R4        ; R8 := # R4
 62 [-]: CALL      R5 4 2       ; R5 := R5(R6,R7,R8)
 63 [-]: SELF      R6 R0 K15    ; R7 := R0; R6 := R0[0x2b54251b]
 64 [-]: CALL      R6 2 2       ; R6 := R6(R7)
 65 [-]: GETGLOBAL R7 K1        ; R7 := 0x7b998233
 66 [-]: MOVE      R8 R6        ; R8 := R6
 67 [-]: CALL      R7 2 2       ; R7 := R7(R8)
 68 [-]: TEST      R7 0         ; if not R7 then PC := 80
 69 [-]: JMP       80           ; PC := 80
 70 [-]: GETGLOBAL R7 K16       ; R7 := 0xcbd666e1
 71 [-]: LOADK     R8 0         ; R8 := 0.000000
 72 [-]: CALL      R7 2 1       ; R7(R8)
 73 [-]: SELF      R7 R0 K15    ; R8 := R0; R7 := R0[0x2b54251b]
 74 [-]: CALL      R7 2 2       ; R7 := R7(R8)
 75 [-]: MOVE      R6 R7        ; R6 := R7
 76 [-]: SELF      R7 R0 K17    ; R8 := R0; R7 := R0[0x7679029b]
 77 [-]: GETTABLE  R9 R4 R5     ; R9 := R4[R5]
 78 [-]: CALL      R7 3 1       ; R7(R8,R9)
 79 [-]: JMP       65           ; PC := 65
 80 [-]: SELF      R7 R6 K18    ; R8 := R6; R7 := R6[0xf2deaf69]
 81 [-]: GETGLOBAL R9 K19       ; R9 := gRagdollType
 82 [-]: CALL      R7 3 2       ; R7 := R7(R8,R9)
 83 [-]: TEST      R7 0         ; if not R7 then PC := 88
 84 [-]: JMP       88           ; PC := 88
 85 [-]: SELF      R7 R6 K20    ; R8 := R6; R7 := R6[0x5163741e]
 86 [-]: CALL      R7 2 2       ; R7 := R7(R8)
 87 [-]: MOVE      R6 R7        ; R6 := R7
 88 [-]: SELF      R7 R6 K18    ; R8 := R6; R7 := R6[0xf2deaf69]
 89 [-]: GETGLOBAL R9 K21       ; R9 := gBaseAvatarType
 90 [-]: CALL      R7 3 2       ; R7 := R7(R8,R9)
 91 [-]: TEST      R7 0         ; if not R7 then PC := 99
 92 [-]: JMP       99           ; PC := 99
 93 [-]: GETUPVAL  R7 U1        ; R7 := U1
 94 [-]: MOVE      R8 R1        ; R8 := R1
 95 [-]: MOVE      R9 R6        ; R9 := R6
 96 [-]: CALL      R7 3 2       ; R7 := R7(R8,R9)
 97 [-]: TEST      R7 1         ; if R7 then PC := 104
 98 [-]: JMP       104          ; PC := 104
 99 [-]: GETGLOBAL R7 K3        ; R7 := 0x89326c93
100 [-]: SELF      R7 R7 K4     ; R8 := R7; R7 := R7[0x59c96e77]
101 [-]: MOVE      R9 R0        ; R9 := R0
102 [-]: CALL      R7 3 1       ; R7(R8,R9)
103 [-]: RETURN    R0 1         ; return 
104 [-]: SELF      R7 R1 K22    ; R8 := R1; R7 := R1[0x388577d5]
105 [-]: CALL      R7 2 2       ; R7 := R7(R8)
106 [-]: GETGLOBAL R8 K23       ; R8 := _T
107 [-]: GETTABLE  R8 R8 K24    ; R8 := R8["sporesAbility"]
108 [-]: EQ        1 R8 K25     ; if R8 == nil then PC := 115
109 [-]: JMP       115          ; PC := 115
110 [-]: GETGLOBAL R8 K23       ; R8 := _T
111 [-]: GETTABLE  R8 R8 K24    ; R8 := R8["sporesAbility"]
112 [-]: GETTABLE  R8 R8 R7     ; R8 := R8[R7]
113 [-]: EQ        0 R8 K25     ; if R8 ~= nil then PC := 120
114 [-]: JMP       120          ; PC := 120
115 [-]: GETGLOBAL R8 K3        ; R8 := 0x89326c93
116 [-]: SELF      R8 R8 K4     ; R9 := R8; R8 := R8[0x59c96e77]
117 [-]: MOVE      R10 R0       ; R10 := R0
118 [-]: CALL      R8 3 1       ; R8(R9,R10)
119 [-]: RETURN    R0 1         ; return 
120 [-]: SELF      R8 R6 K22    ; R9 := R6; R8 := R6[0x388577d5]
121 [-]: CALL      R8 2 2       ; R8 := R8(R9)
122 [-]: GETGLOBAL R9 K23       ; R9 := _T
123 [-]: GETTABLE  R9 R9 K24    ; R9 := R9["sporesAbility"]
124 [-]: GETTABLE  R9 R9 R7     ; R9 := R9[R7]
125 [-]: GETTABLE  R9 R9 K26    ; R9 := R9["sporesInfo"]
126 [-]: GETTABLE  R9 R9 R8     ; R9 := R9[R8]
127 [-]: EQ        0 R9 K25     ; if R9 ~= nil then PC := 158
128 [-]: JMP       158          ; PC := 158
129 [-]: GETGLOBAL R9 K23       ; R9 := _T
130 [-]: GETTABLE  R9 R9 K24    ; R9 := R9["sporesAbility"]
131 [-]: GETTABLE  R9 R9 R7     ; R9 := R9[R7]
132 [-]: GETTABLE  R9 R9 K26    ; R9 := R9["sporesInfo"]
133 [-]: NEWTABLE  R10 0 3      ; R10 := {}
134 [-]: SETTABLE  R10 K27 R6   ; R10["avatar"] := R6
135 [-]: GETGLOBAL R11 K29      ; R11 := 0x55156ff7
136 [-]: CALL      R11 1 2      ; R11 := R11()
137 [-]: SELF      R12 R3 K30   ; R13 := R3; R12 := R3[0xdd6e4cf8]
138 [-]: LOADK     R14 0        ; R14 := 0.000000
139 [-]: LOADK     R15 1        ; R15 := 1.000000
140 [-]: CALL      R12 4 2      ; R12 := R12(R13,R14,R15)
141 [-]: ADD       R11 R11 R12  ; R11 := R11 + R12
142 [-]: SETTABLE  R10 K28 R11  ; R10["damageTime"] := R11
143 [-]: NEWTABLE  R11 0 0      ; R11 := {}
144 [-]: SETTABLE  R10 K31 R11  ; R10["spores"] := R11
145 [-]: SETTABLE  R9 R8 R10    ; R9[R8] := R10
146 [-]: GETUPVAL  R9 U2        ; R9 := U2
147 [-]: GETTABLE  R9 R9 K32    ; R9 := R9[0x32316a21]
148 [-]: CALL      R9 1 2       ; R9 := R9()
149 [-]: TEST      R9 0         ; if not R9 then PC := 158
150 [-]: JMP       158          ; PC := 158
151 [-]: GETGLOBAL R9 K23       ; R9 := _T
152 [-]: GETTABLE  R9 R9 K24    ; R9 := R9["sporesAbility"]
153 [-]: GETTABLE  R9 R9 R7     ; R9 := R9[R7]
154 [-]: GETTABLE  R9 R9 K26    ; R9 := R9["sporesInfo"]
155 [-]: GETTABLE  R9 R9 R8     ; R9 := R9[R8]
156 [-]: GETUPVAL  R10 U3       ; R10 := U3
157 [-]: SETTABLE  R9 K33 R10   ; R9["tickCount"] := R10
158 [-]: GETGLOBAL R9 K34       ; R9 := 0x33bdd652
159 [-]: GETTABLE  R9 R9 K35    ; R9 := R9[0x23d5322f]
160 [-]: GETGLOBAL R10 K23      ; R10 := _T
161 [-]: GETTABLE  R10 R10 K24  ; R10 := R10["sporesAbility"]
162 [-]: GETTABLE  R10 R10 R7   ; R10 := R10[R7]
163 [-]: GETTABLE  R10 R10 K26  ; R10 := R10["sporesInfo"]
164 [-]: GETTABLE  R10 R10 R8   ; R10 := R10[R8]
165 [-]: GETTABLE  R10 R10 K31  ; R10 := R10["spores"]
166 [-]: MOVE      R11 R0       ; R11 := R0
167 [-]: CALL      R9 3 1       ; R9(R10,R11)
168 [-]: GETGLOBAL R9 K23       ; R9 := _T
169 [-]: GETTABLE  R9 R9 K36    ; R9 := R9["sporesCount"]
170 [-]: EQ        0 R9 K25     ; if R9 ~= nil then PC := 175
171 [-]: JMP       175          ; PC := 175
172 [-]: GETGLOBAL R9 K23       ; R9 := _T
173 [-]: NEWTABLE  R10 0 0      ; R10 := {}
174 [-]: SETTABLE  R9 K36 R10   ; R9["sporesCount"] := R10
175 [-]: GETGLOBAL R9 K23       ; R9 := _T
176 [-]: GETTABLE  R9 R9 K36    ; R9 := R9["sporesCount"]
177 [-]: GETTABLE  R9 R9 R8     ; R9 := R9[R8]
178 [-]: EQ        0 R9 K25     ; if R9 ~= nil then PC := 194
179 [-]: JMP       194          ; PC := 194
180 [-]: GETGLOBAL R9 K23       ; R9 := _T
181 [-]: GETTABLE  R9 R9 K36    ; R9 := R9["sporesCount"]
182 [-]: SETTABLE  R9 R8 K37    ; R9[R8] := 0.000000
183 [-]: SELF      R9 R6 K38    ; R10 := R6; R9 := R6[0x1ac1655c]
184 [-]: CALL      R9 2 2       ; R9 := R9(R10)
185 [-]: SELF      R9 R9 K39    ; R10 := R9; R9 := R9[0xeb3c14da]
186 [-]: GETGLOBAL R11 K40      ; R11 := 0x0469f296
187 [-]: LOADK     R12 K41      ; R12 := "PoisonDM"
188 [-]: CALL      R11 2 2      ; R11 := R11(R12)
189 [-]: LOADK     R12 11       ; R12 := 11.000000
190 [-]: LOADK     R13 6        ; R13 := 6.000000
191 [-]: LOADK     R14 7        ; R14 := 7.000000
192 [-]: GETUPVAL  R15 U4       ; R15 := U4
193 [-]: CALL      R9 7 1       ; R9(R10,R11,R12,R13,R14,R15)
194 [-]: GETGLOBAL R9 K23       ; R9 := _T
195 [-]: GETTABLE  R9 R9 K36    ; R9 := R9["sporesCount"]
196 [-]: GETGLOBAL R10 K23      ; R10 := _T
197 [-]: GETTABLE  R10 R10 K36  ; R10 := R10["sporesCount"]
198 [-]: GETTABLE  R10 R10 R8   ; R10 := R10[R8]
199 [-]: ADD       R10 R10 K43  ; R10 := R10 + 1.000000
200 [-]: SETTABLE  R9 R8 R10    ; R9[R8] := R10
201 [-]: GETGLOBAL R9 K16       ; R9 := 0xcbd666e1
202 [-]: LOADK     R10 0        ; R10 := 0.000000
203 [-]: CALL      R9 2 1       ; R9(R10)
204 [-]: SELF      R9 R0 K17    ; R10 := R0; R9 := R0[0x7679029b]
205 [-]: GETTABLE  R11 R4 R5    ; R11 := R4[R5]
206 [-]: CALL      R9 3 1       ; R9(R10,R11)
207 [-]: RETURN    R0 1         ; return 


; Function #20:
;
; Name:            
; Defined at line: 1088
; #Upvalues:       0
; #Parameters:     2
; Is_vararg:       0
; Max Stack Size:  4

  1 [-]: GETGLOBAL R2 K0        ; R2 := _T
  2 [-]: GETTABLE  R2 R2 K1     ; R2 := R2["sporesAbility"]
  3 [-]: EQ        0 R2 K2      ; if R2 ~= nil then PC := 6
  4 [-]: JMP       6            ; PC := 6
  5 [-]: RETURN    R0 1         ; return 
  6 [-]: SELF      R2 R0 K3     ; R3 := R0; R2 := R0[0x5163741e]
  7 [-]: CALL      R2 2 2       ; R2 := R2(R3)
  8 [-]: SELF      R2 R2 K4     ; R3 := R2; R2 := R2[0x388577d5]
  9 [-]: CALL      R2 2 2       ; R2 := R2(R3)
 10 [-]: GETGLOBAL R3 K0        ; R3 := _T
 11 [-]: GETTABLE  R3 R3 K1     ; R3 := R3["sporesAbility"]
 12 [-]: GETTABLE  R3 R3 R2     ; R3 := R3[R2]
 13 [-]: EQ        0 R3 K2      ; if R3 ~= nil then PC := 16
 14 [-]: JMP       16           ; PC := 16
 15 [-]: RETURN    R0 1         ; return 
 16 [-]: GETGLOBAL R3 K0        ; R3 := _T
 17 [-]: GETTABLE  R3 R3 K1     ; R3 := R3["sporesAbility"]
 18 [-]: GETTABLE  R3 R3 R2     ; R3 := R3[R2]
 19 [-]: SETTABLE  R3 K5 K6     ; R3["burst"] := true
 20 [-]: RETURN    R0 1         ; return 


; Function #21:
;
; Name:            
; Defined at line: 1101
; #Upvalues:       0
; #Parameters:     2
; Is_vararg:       0
; Max Stack Size:  4

  1 [-]: GETGLOBAL R2 K0        ; R2 := _T
  2 [-]: GETTABLE  R2 R2 K1     ; R2 := R2["sporesAbility"]
  3 [-]: EQ        0 R2 K2      ; if R2 ~= nil then PC := 6
  4 [-]: JMP       6            ; PC := 6
  5 [-]: RETURN    R0 1         ; return 
  6 [-]: SELF      R2 R0 K3     ; R3 := R0; R2 := R0[0x5163741e]
  7 [-]: CALL      R2 2 2       ; R2 := R2(R3)
  8 [-]: SELF      R2 R2 K4     ; R3 := R2; R2 := R2[0x388577d5]
  9 [-]: CALL      R2 2 2       ; R2 := R2(R3)
 10 [-]: GETGLOBAL R3 K0        ; R3 := _T
 11 [-]: GETTABLE  R3 R3 K1     ; R3 := R3["sporesAbility"]
 12 [-]: GETTABLE  R3 R3 R2     ; R3 := R3[R2]
 13 [-]: EQ        0 R3 K2      ; if R3 ~= nil then PC := 16
 14 [-]: JMP       16           ; PC := 16
 15 [-]: RETURN    R0 1         ; return 
 16 [-]: GETGLOBAL R3 K0        ; R3 := _T
 17 [-]: GETTABLE  R3 R3 K1     ; R3 := R3["sporesAbility"]
 18 [-]: GETTABLE  R3 R3 R2     ; R3 := R3[R2]
 19 [-]: SETTABLE  R3 K5 K6     ; R3["drain"] := true
 20 [-]: RETURN    R0 1         ; return 


; Function #22:
;
; Name:            
; Defined at line: 1114
; #Upvalues:       0
; #Parameters:     2
; Is_vararg:       0
; Max Stack Size:  4

  1 [-]: GETGLOBAL R2 K0        ; R2 := _T
  2 [-]: GETTABLE  R2 R2 K1     ; R2 := R2["sporesAbility"]
  3 [-]: EQ        0 R2 K2      ; if R2 ~= nil then PC := 6
  4 [-]: JMP       6            ; PC := 6
  5 [-]: RETURN    R0 1         ; return 
  6 [-]: SELF      R2 R0 K3     ; R3 := R0; R2 := R0[0x5163741e]
  7 [-]: CALL      R2 2 2       ; R2 := R2(R3)
  8 [-]: SELF      R2 R2 K4     ; R3 := R2; R2 := R2[0x388577d5]
  9 [-]: CALL      R2 2 2       ; R2 := R2(R3)
 10 [-]: GETGLOBAL R3 K0        ; R3 := _T
 11 [-]: GETTABLE  R3 R3 K1     ; R3 := R3["sporesAbility"]
 12 [-]: GETTABLE  R3 R3 R2     ; R3 := R3[R2]
 13 [-]: EQ        0 R3 K2      ; if R3 ~= nil then PC := 16
 14 [-]: JMP       16           ; PC := 16
 15 [-]: RETURN    R0 1         ; return 
 16 [-]: GETGLOBAL R3 K0        ; R3 := _T
 17 [-]: GETTABLE  R3 R3 K1     ; R3 := R3["sporesAbility"]
 18 [-]: GETTABLE  R3 R3 R2     ; R3 := R3[R2]
 19 [-]: SETTABLE  R3 K5 K2     ; R3["drain"] := nil
 20 [-]: RETURN    R0 1         ; return 


