; This file has been disassembled using luadec 2.0.2 by sztupy (modified by Reversive)

; Name:            
; Defined at line: 0
; #Upvalues:       0
; #Parameters:     0
; Is_vararg:       2
; Max Stack Size:  25

  1 [-]: GETGLOBAL R0 K0        ; R0 := 0x2d0fad09
  2 [-]: LOADK     R1 K1        ; R1 := "Lotus.Scripts.Libs.AbilitiesLib"
  3 [-]: CALL      R0 2 2       ; R0 := R0(R1)
  4 [-]: GETGLOBAL R1 K0        ; R1 := 0x2d0fad09
  5 [-]: LOADK     R2 K2        ; R2 := "Lotus.Powersuits.PowersuitAbilities.PVPLib"
  6 [-]: CALL      R1 2 2       ; R1 := R1(R2)
  7 [-]: CONST     R2 100       ; R2 := 100.000000
  8 [-]: CONST     R3 100       ; R3 := 100.000000
  9 [-]: CONST     R4 3         ; R4 := 3.000000
 10 [-]: CONST     R5 10        ; R5 := 10.000000
 11 [-]: CONST     R6 10        ; R6 := 10.000000
 12 [-]: CONST     R7 25        ; R7 := 25.000000
 13 [-]: LOADK     R8 K3        ; R8 := 0.100000
 14 [-]: CONST     R9 5         ; R9 := 5.000000
 15 [-]: CONST     R10 1        ; R10 := 1.250000
 16 [-]: CONST     R11 5        ; R11 := 5.000000
 17 [-]: CONST     R12 2        ; R12 := 2.000000
 18 [-]: CLOSURE   R13 0        ; R13 := closure(Function #1)
 19 [-]: MOVE      R0 R1        ; R0 := R1
 20 [-]: MOVE      R0 R5        ; R0 := R5
 21 [-]: MOVE      R0 R6        ; R0 := R6
 22 [-]: MOVE      R0 R7        ; R0 := R7
 23 [-]: CLOSURE   R14 1        ; R14 := closure(Function #2)
 24 [-]: MOVE      R0 R5        ; R0 := R5
 25 [-]: MOVE      R0 R6        ; R0 := R6
 26 [-]: MOVE      R0 R7        ; R0 := R7
 27 [-]: CLOSURE   R15 2        ; R15 := closure(Function #3)
 28 [-]: MOVE      R0 R9        ; R0 := R9
 29 [-]: MOVE      R0 R10       ; R0 := R10
 30 [-]: CLOSURE   R16 3        ; R16 := closure(Function #4)
 31 [-]: MOVE      R0 R15       ; R0 := R15
 32 [-]: MOVE      R0 R9        ; R0 := R9
 33 [-]: MOVE      R0 R10       ; R0 := R10
 34 [-]: CLOSURE   R17 4        ; R17 := closure(Function #5)
 35 [-]: MOVE      R0 R13       ; R0 := R13
 36 [-]: MOVE      R0 R5        ; R0 := R5
 37 [-]: MOVE      R0 R6        ; R0 := R6
 38 [-]: MOVE      R0 R7        ; R0 := R7
 39 [-]: MOVE      R0 R14       ; R0 := R14
 40 [-]: MOVE      R0 R15       ; R0 := R15
 41 [-]: MOVE      R0 R9        ; R0 := R9
 42 [-]: MOVE      R0 R10       ; R0 := R10
 43 [-]: MOVE      R0 R16       ; R0 := R16
 44 [-]: SETGLOBAL R17 K4       ; GetAbilityUpgradeLevelInfo := R17
 45 [-]: CLOSURE   R17 5        ; R17 := closure(Function #6)
 46 [-]: MOVE      R0 R15       ; R0 := R15
 47 [-]: MOVE      R0 R9        ; R0 := R9
 48 [-]: MOVE      R0 R10       ; R0 := R10
 49 [-]: SETGLOBAL R17 K5       ; GetAugmentDescriptionInfo := R17
 50 [-]: CLOSURE   R17 6        ; R17 := closure(Function #7)
 51 [-]: MOVE      R0 R1        ; R0 := R1
 52 [-]: MOVE      R0 R2        ; R0 := R2
 53 [-]: SETGLOBAL R17 K6       ; InitializeAbility := R17
 54 [-]: CLOSURE   R17 7        ; R17 := closure(Function #8)
 55 [-]: SETGLOBAL R17 K7       ; NpcEvaluateAbility := R17
 56 [-]: GETGLOBAL R17 K8       ; R17 := 0x0469f296
 57 [-]: LOADK     R18 K9       ; R18 := "Light"
 58 [-]: CALL      R17 2 2      ; R17 := R17(R18)
 59 [-]: GETGLOBAL R18 K8       ; R18 := 0x0469f296
 60 [-]: LOADK     R19 K10      ; R19 := "LightFixture"
 61 [-]: CALL      R18 2 2      ; R18 := R18(R19)
 62 [-]: GETGLOBAL R19 K8       ; R19 := 0x0469f296
 63 [-]: LOADK     R20 K11      ; R20 := "LightFixtureTemplate"
 64 [-]: CALL      R19 2 2      ; R19 := R19(R20)
 65 [-]: GETGLOBAL R20 K8       ; R20 := 0x0469f296
 66 [-]: LOADK     R21 K12      ; R21 := "LightFlare"
 67 [-]: CALL      R20 2 2      ; R20 := R20(R21)
 68 [-]: CLOSURE   R21 8        ; R21 := closure(Function #9)
 69 [-]: MOVE      R0 R17       ; R0 := R17
 70 [-]: MOVE      R0 R18       ; R0 := R18
 71 [-]: MOVE      R0 R19       ; R0 := R19
 72 [-]: MOVE      R0 R20       ; R0 := R20
 73 [-]: CLOSURE   R22 9        ; R22 := closure(Function #10)
 74 [-]: MOVE      R0 R19       ; R0 := R19
 75 [-]: MOVE      R0 R17       ; R0 := R17
 76 [-]: MOVE      R0 R20       ; R0 := R20
 77 [-]: CLOSURE   R23 10       ; R23 := closure(Function #11)
 78 [-]: MOVE      R0 R1        ; R0 := R1
 79 [-]: MOVE      R0 R4        ; R0 := R4
 80 [-]: MOVE      R0 R21       ; R0 := R21
 81 [-]: MOVE      R0 R22       ; R0 := R22
 82 [-]: MOVE      R0 R8        ; R0 := R8
 83 [-]: MOVE      R0 R12       ; R0 := R12
 84 [-]: MOVE      R0 R11       ; R0 := R11
 85 [-]: MOVE      R0 R0        ; R0 := R0
 86 [-]: CLOSURE   R24 11       ; R24 := closure(Function #12)
 87 [-]: MOVE      R0 R23       ; R0 := R23
 88 [-]: MOVE      R0 R5        ; R0 := R5
 89 [-]: MOVE      R0 R6        ; R0 := R6
 90 [-]: MOVE      R0 R9        ; R0 := R9
 91 [-]: SETGLOBAL R24 K13      ; DoQuake := R24
 92 [-]: CLOSURE   R24 12       ; R24 := closure(Function #13)
 93 [-]: MOVE      R0 R13       ; R0 := R13
 94 [-]: MOVE      R0 R5        ; R0 := R5
 95 [-]: MOVE      R0 R6        ; R0 := R6
 96 [-]: MOVE      R0 R14       ; R0 := R14
 97 [-]: MOVE      R0 R15       ; R0 := R15
 98 [-]: MOVE      R0 R10       ; R0 := R10
 99 [-]: MOVE      R0 R1        ; R0 := R1
100 [-]: MOVE      R0 R0        ; R0 := R0
101 [-]: MOVE      R0 R7        ; R0 := R7
102 [-]: MOVE      R0 R23       ; R0 := R23
103 [-]: SETGLOBAL R24 K14      ; ActivateAbility := R24
104 [-]: CLOSURE   R24 13       ; R24 := closure(Function #14)
105 [-]: MOVE      R0 R0        ; R0 := R0
106 [-]: MOVE      R0 R1        ; R0 := R1
107 [-]: MOVE      R0 R2        ; R0 := R2
108 [-]: SETGLOBAL R24 K15      ; DeactivateAbility := R24
109 [-]: CLOSURE   R24 14       ; R24 := closure(Function #15)
110 [-]: MOVE      R0 R4        ; R0 := R4
111 [-]: MOVE      R0 R3        ; R0 := R3
112 [-]: SETGLOBAL R24 K16      ; SetAugmentECost := R24
113 [-]: CLOSURE   R24 15       ; R24 := closure(Function #16)
114 [-]: MOVE      R0 R4        ; R0 := R4
115 [-]: SETGLOBAL R24 K17      ; UnsetAugmentECost := R24
116 [-]: RETURN    R0 1         ; return 


; Function #1:
;
; Name:            
; Defined at line: 35
; #Upvalues:       4
; #Parameters:     1
; Is_vararg:       0
; Max Stack Size:  2

  1 [-]: GETUPVAL  R1 U0        ; R1 := U0
  2 [-]: GETTABLE  R1 R1 K0     ; R1 := R1[0x32316a21]
  3 [-]: CALL      R1 1 2       ; R1 := R1()
  4 [-]: TEST      R1 1         ; if R1 then PC := 40
  5 [-]: JMP       40           ; PC := 40
  6 [-]: EQ        0 R0 K1      ; if R0 ~= 1.000000 then PC := 15
  7 [-]: JMP       15           ; PC := 15
  8 [-]: CONST     R1 12        ; R1 := 12.000000
  9 [-]: SETUPVAL  R1 U1        ; U82 := R1
 10 [-]: CONST     R1 125       ; R1 := 125.000000
 11 [-]: SETUPVAL  R1 U2        ; U82 := R2
 12 [-]: CONST     R1 25        ; R1 := 25.000000
 13 [-]: SETUPVAL  R1 U3        ; U82 := R3
 14 [-]: JMP       73           ; PC := 73
 15 [-]: EQ        0 R0 K2      ; if R0 ~= 2.000000 then PC := 24
 16 [-]: JMP       24           ; PC := 24
 17 [-]: CONST     R1 15        ; R1 := 15.000000
 18 [-]: SETUPVAL  R1 U1        ; U82 := R1
 19 [-]: CONST     R1 150       ; R1 := 150.000000
 20 [-]: SETUPVAL  R1 U2        ; U82 := R2
 21 [-]: CONST     R1 18        ; R1 := 18.000000
 22 [-]: SETUPVAL  R1 U3        ; U82 := R3
 23 [-]: JMP       73           ; PC := 73
 24 [-]: EQ        0 R0 K3      ; if R0 ~= 3.000000 then PC := 33
 25 [-]: JMP       33           ; PC := 33
 26 [-]: CONST     R1 18        ; R1 := 18.000000
 27 [-]: SETUPVAL  R1 U1        ; U82 := R1
 28 [-]: CONST     R1 175       ; R1 := 175.000000
 29 [-]: SETUPVAL  R1 U2        ; U82 := R2
 30 [-]: CONST     R1 15        ; R1 := 15.000000
 31 [-]: SETUPVAL  R1 U3        ; U82 := R3
 32 [-]: JMP       73           ; PC := 73
 33 [-]: CONST     R1 20        ; R1 := 20.000000
 34 [-]: SETUPVAL  R1 U1        ; U82 := R1
 35 [-]: CONST     R1 200       ; R1 := 200.000000
 36 [-]: SETUPVAL  R1 U2        ; U82 := R2
 37 [-]: CONST     R1 12        ; R1 := 12.000000
 38 [-]: SETUPVAL  R1 U3        ; U82 := R3
 39 [-]: JMP       73           ; PC := 73
 40 [-]: EQ        0 R0 K1      ; if R0 ~= 1.000000 then PC := 49
 41 [-]: JMP       49           ; PC := 49
 42 [-]: CONST     R1 4         ; R1 := 4.000000
 43 [-]: SETUPVAL  R1 U1        ; U82 := R1
 44 [-]: CONST     R1 240       ; R1 := 240.000000
 45 [-]: SETUPVAL  R1 U2        ; U82 := R2
 46 [-]: CONST     R1 20        ; R1 := 20.000000
 47 [-]: SETUPVAL  R1 U3        ; U82 := R3
 48 [-]: JMP       73           ; PC := 73
 49 [-]: EQ        0 R0 K2      ; if R0 ~= 2.000000 then PC := 58
 50 [-]: JMP       58           ; PC := 58
 51 [-]: CONST     R1 5         ; R1 := 5.000000
 52 [-]: SETUPVAL  R1 U1        ; U82 := R1
 53 [-]: CONST     R1 260       ; R1 := 260.000000
 54 [-]: SETUPVAL  R1 U2        ; U82 := R2
 55 [-]: CONST     R1 20        ; R1 := 20.000000
 56 [-]: SETUPVAL  R1 U3        ; U82 := R3
 57 [-]: JMP       73           ; PC := 73
 58 [-]: EQ        0 R0 K3      ; if R0 ~= 3.000000 then PC := 67
 59 [-]: JMP       67           ; PC := 67
 60 [-]: CONST     R1 6         ; R1 := 6.000000
 61 [-]: SETUPVAL  R1 U1        ; U82 := R1
 62 [-]: CONST     R1 280       ; R1 := 280.000000
 63 [-]: SETUPVAL  R1 U2        ; U82 := R2
 64 [-]: CONST     R1 20        ; R1 := 20.000000
 65 [-]: SETUPVAL  R1 U3        ; U82 := R3
 66 [-]: JMP       73           ; PC := 73
 67 [-]: CONST     R1 7         ; R1 := 7.000000
 68 [-]: SETUPVAL  R1 U1        ; U82 := R1
 69 [-]: CONST     R1 300       ; R1 := 300.000000
 70 [-]: SETUPVAL  R1 U2        ; U82 := R2
 71 [-]: CONST     R1 20        ; R1 := 20.000000
 72 [-]: SETUPVAL  R1 U3        ; U82 := R3
 73 [-]: RETURN    R0 1         ; return 


; Function #2:
;
; Name:            
; Defined at line: 75
; #Upvalues:       3
; #Parameters:     1
; Is_vararg:       0
; Max Stack Size:  13

  1 [-]: GETUPVAL  R1 U0        ; R1 := U0
  2 [-]: GETGLOBAL R2 K0        ; R2 := 0x34291f5c
  3 [-]: GETTABLE  R2 R2 K1     ; R2 := R2[0x7258f36f]
  4 [-]: GETUPVAL  R3 U1        ; R3 := U1
  5 [-]: CALL      R2 2 2       ; R2 := R2(R3)
  6 [-]: GETUPVAL  R3 U2        ; R3 := U2
  7 [-]: GETGLOBAL R4 K2        ; R4 := 0x7b998233
  8 [-]: MOVE      R5 R0        ; R5 := R0
  9 [-]: CALL      R4 2 2       ; R4 := R4(R5)
 10 [-]: TEST      R4 1         ; if R4 then PC := 40
 11 [-]: JMP       40           ; PC := 40
 12 [-]: SELF      R4 R0 K3     ; R5 := R0; R4 := R0[0xde321e6f]
 13 [-]: CALL      R4 2 2       ; R4 := R4(R5)
 14 [-]: SELF      R5 R4 K4     ; R6 := R4; R5 := R4[0xf7d48ee0]
 15 [-]: CALL      R5 2 2       ; R5 := R5(R6)
 16 [-]: GETGLOBAL R6 K2        ; R6 := 0x7b998233
 17 [-]: MOVE      R7 R5        ; R7 := R5
 18 [-]: CALL      R6 2 2       ; R6 := R6(R7)
 19 [-]: TEST      R6 1         ; if R6 then PC := 40
 20 [-]: JMP       40           ; PC := 40
 21 [-]: SELF      R6 R5 K5     ; R7 := R5; R6 := R5[0xcde10c4a]
 22 [-]: CALL      R6 2 2       ; R6 := R6(R7)
 23 [-]: SELF      R7 R4 K6     ; R8 := R4; R7 := R4[0xe9f54086]
 24 [-]: GETUPVAL  R9 U0        ; R9 := U0
 25 [-]: CONST     R10 9        ; R10 := 9.000000
 26 [-]: MOVE      R11 R6       ; R11 := R6
 27 [-]: MOVE      R12 R5       ; R12 := R5
 28 [-]: CALL      R7 6 2       ; R7 := R7(R8,R9,R10,R11,R12)
 29 [-]: MOVE      R1 R7        ; R1 := R7
 30 [-]: SELF      R7 R4 K8     ; R8 := R4; R7 := R4[0x54ba011d]
 31 [-]: MOVE      R9 R2        ; R9 := R2
 32 [-]: CONST     R10 10       ; R10 := 10.000000
 33 [-]: MOVE      R11 R6       ; R11 := R6
 34 [-]: MOVE      R12 R5       ; R12 := R5
 35 [-]: CALL      R7 6 1       ; R7(R8,R9,R10,R11,R12)
 36 [-]: SELF      R7 R5 K9     ; R8 := R5; R7 := R5[0xb418b348]
 37 [-]: GETUPVAL  R9 U2        ; R9 := U2
 38 [-]: CALL      R7 3 2       ; R7 := R7(R8,R9)
 39 [-]: MOVE      R3 R7        ; R3 := R7
 40 [-]: MOVE      R7 R1        ; R7 := R1
 41 [-]: MOVE      R8 R2        ; R8 := R2
 42 [-]: MOVE      R9 R3        ; R9 := R3
 43 [-]: RETURN    R7 4         ; return R7,R8,R9
 44 [-]: RETURN    R0 1         ; return 


; Function #3:
;
; Name:            
; Defined at line: 94
; #Upvalues:       2
; #Parameters:     2
; Is_vararg:       0
; Max Stack Size:  3

  1 [-]: EQ        0 R1 K1      ; if R1 ~= 1.000000 then PC := 28
  2 [-]: JMP       28           ; PC := 28
  3 [-]: EQ        0 R0 K1      ; if R0 ~= 1.000000 then PC := 10
  4 [-]: JMP       10           ; PC := 10
  5 [-]: CONST     R2 10        ; R2 := 10.000000
  6 [-]: SETUPVAL  R2 U0        ; U82 := R0
  7 [-]: CONST     R2 1         ; R2 := 1.250000
  8 [-]: SETUPVAL  R2 U1        ; U82 := R1
  9 [-]: JMP       28           ; PC := 28
 10 [-]: EQ        0 R0 K2      ; if R0 ~= 2.000000 then PC := 17
 11 [-]: JMP       17           ; PC := 17
 12 [-]: CONST     R2 12        ; R2 := 12.000000
 13 [-]: SETUPVAL  R2 U0        ; U82 := R0
 14 [-]: CONST     R2 1         ; R2 := 1.500000
 15 [-]: SETUPVAL  R2 U1        ; U82 := R1
 16 [-]: JMP       28           ; PC := 28
 17 [-]: EQ        0 R0 K3      ; if R0 ~= 3.000000 then PC := 24
 18 [-]: JMP       24           ; PC := 24
 19 [-]: CONST     R2 15        ; R2 := 15.000000
 20 [-]: SETUPVAL  R2 U0        ; U82 := R0
 21 [-]: LOADK     R2 K4        ; R2 := 1.600000
 22 [-]: SETUPVAL  R2 U1        ; U82 := R1
 23 [-]: JMP       28           ; PC := 28
 24 [-]: CONST     R2 20        ; R2 := 20.000000
 25 [-]: SETUPVAL  R2 U0        ; U82 := R0
 26 [-]: CONST     R2 1         ; R2 := 1.750000
 27 [-]: SETUPVAL  R2 U1        ; U82 := R1
 28 [-]: RETURN    R0 1         ; return 


; Function #4:
;
; Name:            
; Defined at line: 112
; #Upvalues:       3
; #Parameters:     1
; Is_vararg:       0
; Max Stack Size:  11

  1 [-]: GETGLOBAL R1 K0        ; R1 := _T
  2 [-]: GETTABLE  R1 R1 K1     ; R1 := R1["AbilityLevelQueryParms"]
  3 [-]: GETTABLE  R1 R1 K2     ; R1 := R1["Avatar"]
  4 [-]: GETGLOBAL R2 K3        ; R2 := 0x7b998233
  5 [-]: MOVE      R3 R1        ; R3 := R1
  6 [-]: CALL      R2 2 2       ; R2 := R2(R3)
  7 [-]: TEST      R2 0         ; if not R2 then PC := 10
  8 [-]: JMP       10           ; PC := 10
  9 [-]: RETURN    R0 1         ; return 
 10 [-]: SELF      R2 R1 K4     ; R3 := R1; R2 := R1[0xde321e6f]
 11 [-]: CALL      R2 2 2       ; R2 := R2(R3)
 12 [-]: SELF      R3 R2 K5     ; R4 := R2; R3 := R2[0xf7d48ee0]
 13 [-]: CALL      R3 2 2       ; R3 := R3(R4)
 14 [-]: GETGLOBAL R4 K3        ; R4 := 0x7b998233
 15 [-]: MOVE      R5 R3        ; R5 := R3
 16 [-]: CALL      R4 2 2       ; R4 := R4(R5)
 17 [-]: TEST      R4 0         ; if not R4 then PC := 20
 18 [-]: JMP       20           ; PC := 20
 19 [-]: RETURN    R0 1         ; return 
 20 [-]: SELF      R4 R3 K6     ; R5 := R3; R4 := R3[0xa2356091]
 21 [-]: GETGLOBAL R6 K0        ; R6 := _T
 22 [-]: GETTABLE  R6 R6 K1     ; R6 := R6["AbilityLevelQueryParms"]
 23 [-]: GETTABLE  R6 R6 K7     ; R6 := R6["Ability"]
 24 [-]: CALL      R4 3 2       ; R4 := R4(R5,R6)
 25 [-]: SELF      R5 R3 K8     ; R6 := R3; R5 := R3[0xd836367c]
 26 [-]: CALL      R5 2 2       ; R5 := R5(R6)
 27 [-]: LE        0 R5 R4      ; if R5 > R4 then PC := 30
 28 [-]: JMP       30           ; PC := 30
 29 [-]: RETURN    R0 1         ; return 
 30 [-]: SELF      R5 R3 K9     ; R6 := R3; R5 := R3[0x5063edc3]
 31 [-]: MOVE      R7 R4        ; R7 := R4
 32 [-]: CALL      R5 3 2       ; R5 := R5(R6,R7)
 33 [-]: LE        0 R5 K10     ; if R5 > 0.000000 then PC := 36
 34 [-]: JMP       36           ; PC := 36
 35 [-]: RETURN    R0 1         ; return 
 36 [-]: SELF      R6 R3 K11    ; R7 := R3; R6 := R3[0x75ecaf0b]
 37 [-]: MOVE      R8 R4        ; R8 := R4
 38 [-]: CALL      R6 3 2       ; R6 := R6(R7,R8)
 39 [-]: GETUPVAL  R7 U0        ; R7 := U0
 40 [-]: MOVE      R8 R5        ; R8 := R5
 41 [-]: MOVE      R9 R6        ; R9 := R6
 42 [-]: CALL      R7 3 1       ; R7(R8,R9)
 43 [-]: EQ        0 R6 K13     ; if R6 ~= 1.000000 then PC := 70
 44 [-]: JMP       70           ; PC := 70
 45 [-]: GETGLOBAL R7 K14       ; R7 := 0x33bdd652
 46 [-]: GETTABLE  R7 R7 K15    ; R7 := R7[0x23d5322f]
 47 [-]: MOVE      R8 R0        ; R8 := R0
 48 [-]: NEWTABLE  R9 0 2       ; R9 := {}
 49 [-]: SETTABLE  R9 K16 K17   ; R9["Label"] := "/Lotus/Language/Suits/SoundquakeAbilityAugment1Name"
 50 [-]: SETTABLE  R9 K18 K19   ; R9["Title"] := true
 51 [-]: CALL      R7 3 1       ; R7(R8,R9)
 52 [-]: GETGLOBAL R7 K14       ; R7 := 0x33bdd652
 53 [-]: GETTABLE  R7 R7 K15    ; R7 := R7[0x23d5322f]
 54 [-]: MOVE      R8 R0        ; R8 := R0
 55 [-]: NEWTABLE  R9 0 3       ; R9 := {}
 56 [-]: SETTABLE  R9 K16 K20   ; R9["Label"] := "/Lotus/Language/Game/DAMAGE"
 57 [-]: GETUPVAL  R10 U1       ; R10 := U1
 58 [-]: SETTABLE  R9 K21 R10   ; R9["Value"] := R10
 59 [-]: SETTABLE  R9 K22 K23   ; R9["ValueUnit"] := "/Lotus/Language/Game/UNIT_MULTIPLIER"
 60 [-]: CALL      R7 3 1       ; R7(R8,R9)
 61 [-]: GETGLOBAL R7 K14       ; R7 := 0x33bdd652
 62 [-]: GETTABLE  R7 R7 K15    ; R7 := R7[0x23d5322f]
 63 [-]: MOVE      R8 R0        ; R8 := R0
 64 [-]: NEWTABLE  R9 0 3       ; R9 := {}
 65 [-]: SETTABLE  R9 K16 K24   ; R9["Label"] := "/Lotus/Language/Game/ABILITY_RADIUS"
 66 [-]: GETUPVAL  R10 U2       ; R10 := U2
 67 [-]: SETTABLE  R9 K21 R10   ; R9["Value"] := R10
 68 [-]: SETTABLE  R9 K22 K23   ; R9["ValueUnit"] := "/Lotus/Language/Game/UNIT_MULTIPLIER"
 69 [-]: CALL      R7 3 1       ; R7(R8,R9)
 70 [-]: RETURN    R0 1         ; return 


; Function #5:
;
; Name:            
; Defined at line: 144
; #Upvalues:       9
; #Parameters:     0
; Is_vararg:       0
; Max Stack Size:  9

  1 [-]: GETUPVAL  R0 U0        ; R0 := U0
  2 [-]: GETGLOBAL R1 K0        ; R1 := _T
  3 [-]: GETTABLE  R1 R1 K1     ; R1 := R1["AbilityLevelQueryParms"]
  4 [-]: GETTABLE  R1 R1 K2     ; R1 := R1["Level"]
  5 [-]: CALL      R0 2 1       ; R0(R1)
  6 [-]: GETGLOBAL R0 K0        ; R0 := _T
  7 [-]: GETTABLE  R0 R0 K1     ; R0 := R0["AbilityLevelQueryParms"]
  8 [-]: GETTABLE  R0 R0 K3     ; R0 := R0["Modded"]
  9 [-]: EQ        0 R0 K4      ; if R0 ~= true then PC := 78
 10 [-]: JMP       78           ; PC := 78
 11 [-]: GETUPVAL  R0 U4        ; R0 := U4
 12 [-]: GETGLOBAL R1 K0        ; R1 := _T
 13 [-]: GETTABLE  R1 R1 K1     ; R1 := R1["AbilityLevelQueryParms"]
 14 [-]: GETTABLE  R1 R1 K5     ; R1 := R1["Avatar"]
 15 [-]: CALL      R0 2 4       ; R0,R1,R2 := R0(R1)
 16 [-]: SETUPVAL  R2 U3        ; U82 := R3
 17 [-]: SETUPVAL  R1 U2        ; U82 := R2
 18 [-]: SETUPVAL  R0 U1        ; U82 := R1
 19 [-]: GETUPVAL  R0 U2        ; R0 := U2
 20 [-]: SELF      R0 R0 K6     ; R1 := R0; R0 := R0[0x838305de]
 21 [-]: CALL      R0 2 2       ; R0 := R0(R1)
 22 [-]: SETUPVAL  R0 U2        ; U82 := R2
 23 [-]: GETGLOBAL R0 K7        ; R0 := 0x7b998233
 24 [-]: GETGLOBAL R1 K0        ; R1 := _T
 25 [-]: GETTABLE  R1 R1 K1     ; R1 := R1["AbilityLevelQueryParms"]
 26 [-]: GETTABLE  R1 R1 K5     ; R1 := R1["Avatar"]
 27 [-]: CALL      R0 2 2       ; R0 := R0(R1)
 28 [-]: TEST      R0 1         ; if R0 then PC := 78
 29 [-]: JMP       78           ; PC := 78
 30 [-]: GETGLOBAL R0 K7        ; R0 := 0x7b998233
 31 [-]: GETGLOBAL R1 K0        ; R1 := _T
 32 [-]: GETTABLE  R1 R1 K1     ; R1 := R1["AbilityLevelQueryParms"]
 33 [-]: GETTABLE  R1 R1 K8     ; R1 := R1["Ability"]
 34 [-]: CALL      R0 2 2       ; R0 := R0(R1)
 35 [-]: TEST      R0 1         ; if R0 then PC := 78
 36 [-]: JMP       78           ; PC := 78
 37 [-]: GETGLOBAL R0 K0        ; R0 := _T
 38 [-]: GETTABLE  R0 R0 K1     ; R0 := R0["AbilityLevelQueryParms"]
 39 [-]: GETTABLE  R0 R0 K5     ; R0 := R0["Avatar"]
 40 [-]: SELF      R0 R0 K9     ; R1 := R0; R0 := R0[0xde321e6f]
 41 [-]: CALL      R0 2 2       ; R0 := R0(R1)
 42 [-]: SELF      R0 R0 K10    ; R1 := R0; R0 := R0[0xf7d48ee0]
 43 [-]: CALL      R0 2 2       ; R0 := R0(R1)
 44 [-]: GETGLOBAL R1 K7        ; R1 := 0x7b998233
 45 [-]: MOVE      R2 R0        ; R2 := R0
 46 [-]: CALL      R1 2 2       ; R1 := R1(R2)
 47 [-]: TEST      R1 1         ; if R1 then PC := 78
 48 [-]: JMP       78           ; PC := 78
 49 [-]: SELF      R1 R0 K11    ; R2 := R0; R1 := R0[0xa2356091]
 50 [-]: GETGLOBAL R3 K0        ; R3 := _T
 51 [-]: GETTABLE  R3 R3 K1     ; R3 := R3["AbilityLevelQueryParms"]
 52 [-]: GETTABLE  R3 R3 K8     ; R3 := R3["Ability"]
 53 [-]: CALL      R1 3 2       ; R1 := R1(R2,R3)
 54 [-]: SELF      R2 R0 K12    ; R3 := R0; R2 := R0[0x5063edc3]
 55 [-]: MOVE      R4 R1        ; R4 := R1
 56 [-]: CALL      R2 3 2       ; R2 := R2(R3,R4)
 57 [-]: SELF      R3 R0 K13    ; R4 := R0; R3 := R0[0x75ecaf0b]
 58 [-]: MOVE      R5 R1        ; R5 := R1
 59 [-]: CALL      R3 3 2       ; R3 := R3(R4,R5)
 60 [-]: LT        0 K14 R2     ; if 0.000000 >= R2 then PC := 78
 61 [-]: JMP       78           ; PC := 78
 62 [-]: EQ        0 R3 K16     ; if R3 ~= 1.000000 then PC := 78
 63 [-]: JMP       78           ; PC := 78
 64 [-]: GETUPVAL  R4 U5        ; R4 := U5
 65 [-]: MOVE      R5 R2        ; R5 := R2
 66 [-]: MOVE      R6 R3        ; R6 := R3
 67 [-]: CALL      R4 3 1       ; R4(R5,R6)
 68 [-]: GETUPVAL  R4 U2        ; R4 := U2
 69 [-]: GETUPVAL  R5 U6        ; R5 := U6
 70 [-]: MUL       R4 R4 R5     ; R4 := R4 * R5
 71 [-]: SETUPVAL  R4 U2        ; U82 := R2
 72 [-]: GETUPVAL  R4 U1        ; R4 := U1
 73 [-]: GETUPVAL  R5 U7        ; R5 := U7
 74 [-]: MUL       R4 R4 R5     ; R4 := R4 * R5
 75 [-]: SETUPVAL  R4 U1        ; U82 := R1
 76 [-]: CONST     R4 0         ; R4 := 0.000000
 77 [-]: SETUPVAL  R4 U3        ; U82 := R3
 78 [-]: NEWTABLE  R4 0 0       ; R4 := {}
 79 [-]: GETGLOBAL R5 K17       ; R5 := 0x33bdd652
 80 [-]: GETTABLE  R5 R5 K18    ; R5 := R5[0x23d5322f]
 81 [-]: MOVE      R6 R4        ; R6 := R4
 82 [-]: NEWTABLE  R7 0 4       ; R7 := {}
 83 [-]: SETTABLE  R7 K19 K20   ; R7["Label"] := "/Lotus/Language/Game/EnergyPerSec"
 84 [-]: GETUPVAL  R8 U3        ; R8 := U3
 85 [-]: SETTABLE  R7 K21 R8    ; R7["Value"] := R8
 86 [-]: SETTABLE  R7 K22 K23   ; R7["ValueIcon"] := "<ENERGY>"
 87 [-]: SETTABLE  R7 K24 K4    ; R7["SmallerIsBetter"] := true
 88 [-]: CALL      R5 3 1       ; R5(R6,R7)
 89 [-]: GETGLOBAL R5 K17       ; R5 := 0x33bdd652
 90 [-]: GETTABLE  R5 R5 K18    ; R5 := R5[0x23d5322f]
 91 [-]: MOVE      R6 R4        ; R6 := R4
 92 [-]: NEWTABLE  R7 0 3       ; R7 := {}
 93 [-]: SETTABLE  R7 K19 K25   ; R7["Label"] := "/Lotus/Language/Game/ABILITY_RADIUS"
 94 [-]: GETUPVAL  R8 U1        ; R8 := U1
 95 [-]: SETTABLE  R7 K21 R8    ; R7["Value"] := R8
 96 [-]: SETTABLE  R7 K26 K27   ; R7["ValueUnit"] := "/Lotus/Language/Game/UNIT_METER"
 97 [-]: CALL      R5 3 1       ; R5(R6,R7)
 98 [-]: GETGLOBAL R5 K17       ; R5 := 0x33bdd652
 99 [-]: GETTABLE  R5 R5 K18    ; R5 := R5[0x23d5322f]
100 [-]: MOVE      R6 R4        ; R6 := R4
101 [-]: NEWTABLE  R7 0 3       ; R7 := {}
102 [-]: SETTABLE  R7 K19 K28   ; R7["Label"] := "/Lotus/Language/Game/DPS"
103 [-]: GETUPVAL  R8 U2        ; R8 := U2
104 [-]: SETTABLE  R7 K21 R8    ; R7["Value"] := R8
105 [-]: SETTABLE  R7 K22 K29   ; R7["ValueIcon"] := "<DT_EXPLOSION>"
106 [-]: CALL      R5 3 1       ; R5(R6,R7)
107 [-]: GETUPVAL  R5 U8        ; R5 := U8
108 [-]: MOVE      R6 R4        ; R6 := R4
109 [-]: CALL      R5 2 1       ; R5(R6)
110 [-]: GETGLOBAL R5 K0        ; R5 := _T
111 [-]: GETTABLE  R5 R5 K1     ; R5 := R5["AbilityLevelQueryParms"]
112 [-]: GETTABLE  R5 R5 K3     ; R5 := R5["Modded"]
113 [-]: SETTABLE  R4 K3 R5     ; R4["Modded"] := R5
114 [-]: GETGLOBAL R5 K0        ; R5 := _T
115 [-]: SETTABLE  R5 K30 R4    ; R5["AbilityUpgradeLevelInfo"] := R4
116 [-]: RETURN    R0 1         ; return 


; Function #6:
;
; Name:            
; Defined at line: 178
; #Upvalues:       3
; #Parameters:     2
; Is_vararg:       0
; Max Stack Size:  6

  1 [-]: NEWTABLE  R2 0 0       ; R2 := {}
  2 [-]: GETUPVAL  R3 U0        ; R3 := U0
  3 [-]: MOVE      R4 R0        ; R4 := R0
  4 [-]: MOVE      R5 R1        ; R5 := R1
  5 [-]: CALL      R3 3 1       ; R3(R4,R5)
  6 [-]: EQ        0 R1 K1      ; if R1 ~= 1.000000 then PC := 14
  7 [-]: JMP       14           ; PC := 14
  8 [-]: NEWTABLE  R3 0 2       ; R3 := {}
  9 [-]: GETUPVAL  R4 U1        ; R4 := U1
 10 [-]: SETTABLE  R3 K2 R4     ; R3["DAMAGE_MULT"] := R4
 11 [-]: GETUPVAL  R4 U2        ; R4 := U2
 12 [-]: SETTABLE  R3 K3 R4     ; R3["RANGE_MULT"] := R4
 13 [-]: MOVE      R2 R3        ; R2 := R3
 14 [-]: GETGLOBAL R3 K4        ; R3 := cjson
 15 [-]: GETTABLE  R3 R3 K5     ; R3 := R3[0xb139d7bc]
 16 [-]: MOVE      R4 R2        ; R4 := R2
 17 [-]: TAILCALL  R3 2 0       ; R3,... := R3(R4)
 18 [-]: RETURN    R3 0         ; return R3,...
 19 [-]: RETURN    R0 1         ; return 


; Function #7:
;
; Name:            
; Defined at line: 192
; #Upvalues:       2
; #Parameters:     2
; Is_vararg:       0
; Max Stack Size:  6

  1 [-]: GETUPVAL  R2 U0        ; R2 := U0
  2 [-]: GETTABLE  R2 R2 K0     ; R2 := R2[0x32316a21]
  3 [-]: CALL      R2 1 2       ; R2 := R2()
  4 [-]: TEST      R2 0         ; if not R2 then PC := 23
  5 [-]: JMP       23           ; PC := 23
  6 [-]: GETUPVAL  R2 U0        ; R2 := U0
  7 [-]: GETTABLE  R2 R2 K1     ; R2 := R2[0xe4ae0e66]
  8 [-]: CALL      R2 1 2       ; R2 := R2()
  9 [-]: TEST      R2 0         ; if not R2 then PC := 19
 10 [-]: JMP       19           ; PC := 19
 11 [-]: GETGLOBAL R2 K2        ; R2 := 0x6687f6e0
 12 [-]: SELF      R2 R2 K3     ; R3 := R2; R2 := R2[0x3a147087]
 13 [-]: GETGLOBAL R4 K4        ; R4 := 0xbe190284
 14 [-]: SELF      R4 R4 K5     ; R5 := R4; R4 := R4[0xc911409e]
 15 [-]: CALL      R4 2 2       ; R4 := R4(R5)
 16 [-]: ADD       R4 R4 K6     ; R4 := R4 + 100.000000
 17 [-]: CALL      R2 3 1       ; R2(R3,R4)
 18 [-]: JMP       23           ; PC := 23
 19 [-]: GETGLOBAL R2 K2        ; R2 := 0x6687f6e0
 20 [-]: SELF      R2 R2 K3     ; R3 := R2; R2 := R2[0x3a147087]
 21 [-]: GETUPVAL  R4 U1        ; R4 := U1
 22 [-]: CALL      R2 3 1       ; R2(R3,R4)
 23 [-]: RETURN    R0 1         ; return 


; Function #8:
;
; Name:            
; Defined at line: 202
; #Upvalues:       0
; #Parameters:     2
; Is_vararg:       0
; Max Stack Size:  16

  1 [-]: CONST     R2 0         ; R2 := 0.000000
  2 [-]: SELF      R3 R1 K0     ; R4 := R1; R3 := R1[0xfa9e477f]
  3 [-]: CALL      R3 2 2       ; R3 := R3(R4)
  4 [-]: SELF      R3 R3 K1     ; R4 := R3; R3 := R3[0xc0e06c5c]
  5 [-]: CALL      R3 2 2       ; R3 := R3(R4)
  6 [-]: CONST     R4 5         ; R4 := 5.000000
  7 [-]: CONST     R5 12        ; R5 := 12.000000
  8 [-]: SELF      R6 R1 K2     ; R7 := R1; R6 := R1[0xf6ebd926]
  9 [-]: CALL      R6 2 2       ; R6 := R6(R7)
 10 [-]: GETTABLE  R7 R6 K3     ; R7 := R6["y"]
 11 [-]: CONST     R8 1         ; R8 := 1.000000
 12 [-]: LEN       R9 R3        ; R9 := # R3
 13 [-]: CONST     R10 1        ; R10 := 1.000000
 14 [-]: FORPREP   R8 45        ; R8 -= R10; PC := 45
 15 [-]: GETTABLE  R12 R3 R11   ; R12 := R3[R11]
 16 [-]: GETTABLE  R12 R12 K4   ; R12 := R12["visible"]
 17 [-]: TEST      R12 0        ; if not R12 then PC := 45
 18 [-]: JMP       45           ; PC := 45
 19 [-]: GETTABLE  R12 R3 R11   ; R12 := R3[R11]
 20 [-]: SELF      R12 R12 K5   ; R13 := R12; R12 := R12[0x37e4785a]
 21 [-]: CALL      R12 2 2      ; R12 := R12(R13)
 22 [-]: TEST      R12 0        ; if not R12 then PC := 45
 23 [-]: JMP       45           ; PC := 45
 24 [-]: GETTABLE  R12 R3 R11   ; R12 := R3[R11]
 25 [-]: GETTABLE  R12 R12 K6   ; R12 := R12["distanceToTarget"]
 26 [-]: LE        0 R4 R12     ; if R4 > R12 then PC := 45
 27 [-]: JMP       45           ; PC := 45
 28 [-]: LE        0 R12 R5     ; if R12 > R5 then PC := 45
 29 [-]: JMP       45           ; PC := 45
 30 [-]: GETTABLE  R13 R3 R11   ; R13 := R3[R11]
 31 [-]: GETTABLE  R13 R13 K7   ; R13 := R13["avatar"]
 32 [-]: SELF      R13 R13 K2   ; R14 := R13; R13 := R13[0xf6ebd926]
 33 [-]: CALL      R13 2 2      ; R13 := R13(R14)
 34 [-]: GETTABLE  R14 R13 K3   ; R14 := R13["y"]
 35 [-]: SUB       R14 R14 R7   ; R14 := R14 - R7
 36 [-]: LE        0 R14 K8     ; if R14 > 2.500000 then PC := 45
 37 [-]: JMP       45           ; PC := 45
 38 [-]: SUB       R14 R12 R4   ; R14 := R12 - R4
 39 [-]: SUB       R15 R5 R4    ; R15 := R5 - R4
 40 [-]: DIV       R14 R14 R15  ; R14 := R14 / R15
 41 [-]: SUB       R14 K9 R14   ; R14 := 1.000000 - R14
 42 [-]: LEN       R15 R3       ; R15 := # R3
 43 [-]: DIV       R14 R14 R15  ; R14 := R14 / R15
 44 [-]: ADD       R2 R2 R14    ; R2 := R2 + R14
 45 [-]: FORLOOP   R8 15        ; R8 += R10; if R8 <= R9 then begin PC := 15; R11 := R8 end
 46 [-]: RETURN    R2 2         ; return R2
 47 [-]: RETURN    R0 1         ; return 


; Function #9:
;
; Name:            
; Defined at line: 234
; #Upvalues:       4
; #Parameters:     6
; Is_vararg:       0
; Max Stack Size:  12

  1 [-]: GETGLOBAL R6 K0        ; R6 := 0x89326c93
  2 [-]: SELF      R6 R6 K1     ; R7 := R6; R6 := R6[0xf16592c8]
  3 [-]: GETUPVAL  R8 U0        ; R8 := U0
  4 [-]: MOVE      R9 R1        ; R9 := R1
  5 [-]: CONST     R10 0        ; R10 := 0.000000
  6 [-]: MOVE      R11 R0       ; R11 := R0
  7 [-]: CALL      R6 6 2       ; R6 := R6(R7,R8,R9,R10,R11)
  8 [-]: MOVE      R2 R6        ; R2 := R6
  9 [-]: GETGLOBAL R6 K0        ; R6 := 0x89326c93
 10 [-]: SELF      R6 R6 K1     ; R7 := R6; R6 := R6[0xf16592c8]
 11 [-]: GETUPVAL  R8 U1        ; R8 := U1
 12 [-]: MOVE      R9 R1        ; R9 := R1
 13 [-]: CONST     R10 0        ; R10 := 0.000000
 14 [-]: MOVE      R11 R0       ; R11 := R0
 15 [-]: CALL      R6 6 2       ; R6 := R6(R7,R8,R9,R10,R11)
 16 [-]: MOVE      R3 R6        ; R3 := R6
 17 [-]: GETGLOBAL R6 K0        ; R6 := 0x89326c93
 18 [-]: SELF      R6 R6 K1     ; R7 := R6; R6 := R6[0xf16592c8]
 19 [-]: GETUPVAL  R8 U2        ; R8 := U2
 20 [-]: MOVE      R9 R1        ; R9 := R1
 21 [-]: CONST     R10 0        ; R10 := 0.000000
 22 [-]: MOVE      R11 R0       ; R11 := R0
 23 [-]: CALL      R6 6 2       ; R6 := R6(R7,R8,R9,R10,R11)
 24 [-]: MOVE      R4 R6        ; R4 := R6
 25 [-]: GETGLOBAL R6 K0        ; R6 := 0x89326c93
 26 [-]: SELF      R6 R6 K1     ; R7 := R6; R6 := R6[0xf16592c8]
 27 [-]: GETUPVAL  R8 U3        ; R8 := U3
 28 [-]: MOVE      R9 R1        ; R9 := R1
 29 [-]: CONST     R10 0        ; R10 := 0.000000
 30 [-]: MOVE      R11 R0       ; R11 := R0
 31 [-]: CALL      R6 6 2       ; R6 := R6(R7,R8,R9,R10,R11)
 32 [-]: MOVE      R5 R6        ; R5 := R6
 33 [-]: RETURN    R0 1         ; return 


; Function #10:
;
; Name:            
; Defined at line: 241
; #Upvalues:       3
; #Parameters:     6
; Is_vararg:       0
; Max Stack Size:  29

  1 [-]: GETGLOBAL R6 K0        ; R6 := 0x7b998233
  2 [-]: MOVE      R7 R4        ; R7 := R4
  3 [-]: CALL      R6 2 2       ; R6 := R6(R7)
  4 [-]: TEST      R6 1         ; if R6 then PC := 38
  5 [-]: JMP       38           ; PC := 38
  6 [-]: GETGLOBAL R6 K1        ; R6 := 0xcfc01047
  7 [-]: MOVE      R7 R4        ; R7 := R4
  8 [-]: CALL      R6 2 4       ; R6,R7,R8 := R6(R7)
  9 [-]: JMP       36           ; PC := 36
 10 [-]: GETGLOBAL R11 K0       ; R11 := 0x7b998233
 11 [-]: MOVE      R12 R10      ; R12 := R10
 12 [-]: CALL      R11 2 2      ; R11 := R11(R12)
 13 [-]: TEST      R11 1        ; if R11 then PC := 36
 14 [-]: JMP       36           ; PC := 36
 15 [-]: SELF      R11 R10 K2   ; R12 := R10; R11 := R10[0x08db51de]
 16 [-]: GETUPVAL  R13 U0       ; R13 := U0
 17 [-]: CALL      R11 3 2      ; R11 := R11(R12,R13)
 18 [-]: TEST      R11 0        ; if not R11 then PC := 36
 19 [-]: JMP       36           ; PC := 36
 20 [-]: SELF      R11 R10 K3   ; R12 := R10; R11 := R10[0x1f420a3a]
 21 [-]: MOVE      R13 R1       ; R13 := R1
 22 [-]: CALL      R11 3 2      ; R11 := R11(R12,R13)
 23 [-]: LE        0 R11 R0     ; if R11 > R0 then PC := 36
 24 [-]: JMP       36           ; PC := 36
 25 [-]: SELF      R11 R10 K4   ; R12 := R10; R11 := R10[0x986d2ab8]
 26 [-]: GETGLOBAL R13 K5       ; R13 := 0x6c97a788
 27 [-]: GETTABLE  R13 R13 K6   ; R13 := R13["EMISSIVE_MAP_ATTEN"]
 28 [-]: CONST     R14 0        ; R14 := 0.000000
 29 [-]: CALL      R11 4 1      ; R11(R12,R13,R14)
 30 [-]: SELF      R11 R10 K7   ; R12 := R10; R11 := R10[0xa2880940]
 31 [-]: CALL      R11 2 1      ; R11(R12)
 32 [-]: SELF      R11 R10 K8   ; R12 := R10; R11 := R10[0x3273ba96]
 33 [-]: GETGLOBAL R13 K9       ; R13 := EMPTY_SYMBOL
 34 [-]: CALL      R11 3 1      ; R11(R12,R13)
 35 [-]: SETTABLE  R4 R9 K10    ; R4[R9] := nil
 36 [-]: TFORLOOP  R6 2         ; R9,R10 :=  R6(R7,R8); if R9 ~= nil then begin PC = 10; R8 := R9 end
 37 [-]: JMP       10           ; PC := 10
 38 [-]: GETGLOBAL R11 K0       ; R11 := 0x7b998233
 39 [-]: MOVE      R12 R3       ; R12 := R3
 40 [-]: CALL      R11 2 2      ; R11 := R11(R12)
 41 [-]: TEST      R11 1        ; if R11 then PC := 81
 42 [-]: JMP       81           ; PC := 81
 43 [-]: GETGLOBAL R11 K1       ; R11 := 0xcfc01047
 44 [-]: MOVE      R12 R3       ; R12 := R3
 45 [-]: CALL      R11 2 4      ; R11,R12,R13 := R11(R12)
 46 [-]: JMP       79           ; PC := 79
 47 [-]: GETGLOBAL R16 K0       ; R16 := 0x7b998233
 48 [-]: MOVE      R17 R15      ; R17 := R15
 49 [-]: CALL      R16 2 2      ; R16 := R16(R17)
 50 [-]: TEST      R16 1        ; if R16 then PC := 79
 51 [-]: JMP       79           ; PC := 79
 52 [-]: SELF      R16 R15 K2   ; R17 := R15; R16 := R15[0x08db51de]
 53 [-]: GETUPVAL  R18 U0       ; R18 := U0
 54 [-]: CALL      R16 3 2      ; R16 := R16(R17,R18)
 55 [-]: TEST      R16 0        ; if not R16 then PC := 79
 56 [-]: JMP       79           ; PC := 79
 57 [-]: SELF      R16 R15 K3   ; R17 := R15; R16 := R15[0x1f420a3a]
 58 [-]: MOVE      R18 R1       ; R18 := R1
 59 [-]: CALL      R16 3 2      ; R16 := R16(R17,R18)
 60 [-]: LE        0 R16 R0     ; if R16 > R0 then PC := 79
 61 [-]: JMP       79           ; PC := 79
 62 [-]: SELF      R16 R15 K4   ; R17 := R15; R16 := R15[0x986d2ab8]
 63 [-]: GETGLOBAL R18 K5       ; R18 := 0x6c97a788
 64 [-]: GETTABLE  R18 R18 K6   ; R18 := R18["EMISSIVE_MAP_ATTEN"]
 65 [-]: CONST     R19 0        ; R19 := 0.000000
 66 [-]: CALL      R16 4 1      ; R16(R17,R18,R19)
 67 [-]: GETGLOBAL R16 K11      ; R16 := 0x89326c93
 68 [-]: SELF      R16 R16 K12  ; R17 := R16; R16 := R16[0x05909209]
 69 [-]: GETGLOBAL R18 K13      ; R18 := 0xee216a05
 70 [-]: SELF      R19 R15 K14  ; R20 := R15; R19 := R15[0xd1586535]
 71 [-]: CALL      R19 2 2      ; R19 := R19(R20)
 72 [-]: SELF      R20 R15 K15  ; R21 := R15; R20 := R15[0xcb3851b8]
 73 [-]: CALL      R20 2 0      ; R20,... := R20(R21)
 74 [-]: CALL      R16 0 1      ; R16(R17,...)
 75 [-]: SELF      R16 R15 K8   ; R17 := R15; R16 := R15[0x3273ba96]
 76 [-]: GETGLOBAL R18 K9       ; R18 := EMPTY_SYMBOL
 77 [-]: CALL      R16 3 1      ; R16(R17,R18)
 78 [-]: SETTABLE  R3 R14 K10   ; R3[R14] := nil
 79 [-]: TFORLOOP  R11 2        ; R14,R15 :=  R11(R12,R13); if R14 ~= nil then begin PC = 47; R13 := R14 end
 80 [-]: JMP       47           ; PC := 47
 81 [-]: GETGLOBAL R16 K0       ; R16 := 0x7b998233
 82 [-]: MOVE      R17 R2       ; R17 := R2
 83 [-]: CALL      R16 2 2      ; R16 := R16(R17)
 84 [-]: TEST      R16 1        ; if R16 then PC := 114
 85 [-]: JMP       114          ; PC := 114
 86 [-]: GETGLOBAL R16 K1       ; R16 := 0xcfc01047
 87 [-]: MOVE      R17 R2       ; R17 := R2
 88 [-]: CALL      R16 2 4      ; R16,R17,R18 := R16(R17)
 89 [-]: JMP       112          ; PC := 112
 90 [-]: GETGLOBAL R21 K0       ; R21 := 0x7b998233
 91 [-]: MOVE      R22 R20      ; R22 := R20
 92 [-]: CALL      R21 2 2      ; R21 := R21(R22)
 93 [-]: TEST      R21 1        ; if R21 then PC := 112
 94 [-]: JMP       112          ; PC := 112
 95 [-]: SELF      R21 R20 K2   ; R22 := R20; R21 := R20[0x08db51de]
 96 [-]: GETUPVAL  R23 U1       ; R23 := U1
 97 [-]: CALL      R21 3 2      ; R21 := R21(R22,R23)
 98 [-]: TEST      R21 0        ; if not R21 then PC := 112
 99 [-]: JMP       112          ; PC := 112
100 [-]: SELF      R21 R20 K3   ; R22 := R20; R21 := R20[0x1f420a3a]
101 [-]: MOVE      R23 R1       ; R23 := R1
102 [-]: CALL      R21 3 2      ; R21 := R21(R22,R23)
103 [-]: LE        0 R21 R0     ; if R21 > R0 then PC := 112
104 [-]: JMP       112          ; PC := 112
105 [-]: SELF      R21 R20 K16  ; R22 := R20; R21 := R20[0x8eb2112d]
106 [-]: LOADK     R23 K17      ; R23 := "TurnOff"
107 [-]: CALL      R21 3 1      ; R21(R22,R23)
108 [-]: SELF      R21 R20 K8   ; R22 := R20; R21 := R20[0x3273ba96]
109 [-]: GETGLOBAL R23 K9       ; R23 := EMPTY_SYMBOL
110 [-]: CALL      R21 3 1      ; R21(R22,R23)
111 [-]: SETTABLE  R2 R19 K10   ; R2[R19] := nil
112 [-]: TFORLOOP  R16 2        ; R19,R20 :=  R16(R17,R18); if R19 ~= nil then begin PC = 90; R18 := R19 end
113 [-]: JMP       90           ; PC := 90
114 [-]: GETGLOBAL R21 K0       ; R21 := 0x7b998233
115 [-]: MOVE      R22 R5       ; R22 := R5
116 [-]: CALL      R21 2 2      ; R21 := R21(R22)
117 [-]: TEST      R21 1        ; if R21 then PC := 147
118 [-]: JMP       147          ; PC := 147
119 [-]: GETGLOBAL R21 K1       ; R21 := 0xcfc01047
120 [-]: MOVE      R22 R5       ; R22 := R5
121 [-]: CALL      R21 2 4      ; R21,R22,R23 := R21(R22)
122 [-]: JMP       145          ; PC := 145
123 [-]: GETGLOBAL R26 K0       ; R26 := 0x7b998233
124 [-]: MOVE      R27 R25      ; R27 := R25
125 [-]: CALL      R26 2 2      ; R26 := R26(R27)
126 [-]: TEST      R26 1        ; if R26 then PC := 145
127 [-]: JMP       145          ; PC := 145
128 [-]: SELF      R26 R25 K2   ; R27 := R25; R26 := R25[0x08db51de]
129 [-]: GETUPVAL  R28 U2       ; R28 := U2
130 [-]: CALL      R26 3 2      ; R26 := R26(R27,R28)
131 [-]: TEST      R26 0        ; if not R26 then PC := 145
132 [-]: JMP       145          ; PC := 145
133 [-]: SELF      R26 R25 K3   ; R27 := R25; R26 := R25[0x1f420a3a]
134 [-]: MOVE      R28 R1       ; R28 := R1
135 [-]: CALL      R26 3 2      ; R26 := R26(R27,R28)
136 [-]: LE        0 R26 R0     ; if R26 > R0 then PC := 145
137 [-]: JMP       145          ; PC := 145
138 [-]: SELF      R26 R25 K16  ; R27 := R25; R26 := R25[0x8eb2112d]
139 [-]: LOADK     R28 K18      ; R28 := "Disable"
140 [-]: CALL      R26 3 1      ; R26(R27,R28)
141 [-]: SELF      R26 R25 K8   ; R27 := R25; R26 := R25[0x3273ba96]
142 [-]: GETGLOBAL R28 K9       ; R28 := EMPTY_SYMBOL
143 [-]: CALL      R26 3 1      ; R26(R27,R28)
144 [-]: SETTABLE  R5 R24 K10   ; R5[R24] := nil
145 [-]: TFORLOOP  R21 2        ; R24,R25 :=  R21(R22,R23); if R24 ~= nil then begin PC = 123; R23 := R24 end
146 [-]: JMP       123          ; PC := 123
147 [-]: RETURN    R0 1         ; return 


; Function #11:
;
; Name:            
; Defined at line: 301
; #Upvalues:       8
; #Parameters:     5
; Is_vararg:       0
; Max Stack Size:  48

  1 [-]: CONST     R5 5         ; R5 := 5.000000
  2 [-]: CONST     R6 0         ; R6 := 0.000000
  3 [-]: CONST     R7 1         ; R7 := 1.000000
  4 [-]: SELF      R8 R1 K0     ; R9 := R1; R8 := R1[0xf6ebd926]
  5 [-]: CALL      R8 2 2       ; R8 := R8(R9)
  6 [-]: NEWTABLE  R9 0 0       ; R9 := {}
  7 [-]: GETUPVAL  R10 U0       ; R10 := U0
  8 [-]: GETTABLE  R10 R10 K1   ; R10 := R10[0x32316a21]
  9 [-]: CALL      R10 1 2      ; R10 := R10()
 10 [-]: SELF      R11 R0 K2    ; R12 := R0; R11 := R0[0x5063edc3]
 11 [-]: GETUPVAL  R13 U1       ; R13 := U1
 12 [-]: CALL      R11 3 2      ; R11 := R11(R12,R13)
 13 [-]: SELF      R12 R0 K3    ; R13 := R0; R12 := R0[0x75ecaf0b]
 14 [-]: GETUPVAL  R14 U1       ; R14 := U1
 15 [-]: CALL      R12 3 2      ; R12 := R12(R13,R14)
 16 [-]: LT        0 K4 R11     ; if 0.000000 >= R11 then PC := 20
 17 [-]: JMP       20           ; PC := 20
 18 [-]: EQ        1 R12 K6     ; if R12 == 1.000000 then PC := 21
 19 [-]: JMP       21           ; PC := 21
 20 [-]: LOADKB    R13 0 1      ; R13 := false; PC := 21
 21 [-]: LOADKB    R13 1 0      ; R13 := true
 22 [-]: SELF      R14 R1 K7    ; R15 := R1; R14 := R1[0x35844cf2]
 23 [-]: CALL      R14 2 2      ; R14 := R14(R15)
 24 [-]: TEST      R14 1        ; if R14 then PC := 30
 25 [-]: JMP       30           ; PC := 30
 26 [-]: SELF      R14 R3 K8    ; R15 := R3; R14 := R3[0x133d78e8]
 27 [-]: CONST     R16 2        ; R16 := 2.000000
 28 [-]: LOADK     R17 K10      ; R17 := 0.333333
 29 [-]: CALL      R14 4 1      ; R14(R15,R16,R17)
 30 [-]: GETGLOBAL R14 K11      ; R14 := 0x89326c93
 31 [-]: SELF      R14 R14 K12  ; R15 := R14; R14 := R14[0x18d05d30]
 32 [-]: CALL      R14 2 2      ; R14 := R14(R15)
 33 [-]: TEST      R14 0        ; if not R14 then PC := 66
 34 [-]: JMP       66           ; PC := 66
 35 [-]: GETGLOBAL R14 K9       ; R14 := 0x34291f5c
 36 [-]: GETTABLE  R14 R14 K13  ; R14 := R14[0x5cb2adf8]
 37 [-]: CALL      R14 1 2      ; R14 := R14()
 38 [-]: SELF      R15 R14 K14  ; R16 := R14; R15 := R14[0x86cd00cb]
 39 [-]: MOVE      R17 R1       ; R17 := R1
 40 [-]: CALL      R15 3 1      ; R15(R16,R17)
 41 [-]: SELF      R15 R14 K15  ; R16 := R14; R15 := R14[0x618938f0]
 42 [-]: MOVE      R17 R8       ; R17 := R8
 43 [-]: CALL      R15 3 1      ; R15(R16,R17)
 44 [-]: SELF      R15 R14 K16  ; R16 := R14; R15 := R14[0xf326045f]
 45 [-]: MOVE      R17 R3       ; R17 := R3
 46 [-]: CALL      R15 3 1      ; R15(R16,R17)
 47 [-]: SETTABLE  R14 K17 K18  ; R14["radius"] := 5.000000
 48 [-]: SELF      R15 R14 K19  ; R16 := R14; R15 := R14[0xcdb40c41]
 49 [-]: CONST     R17 50       ; R17 := 50.000000
 50 [-]: CALL      R15 3 1      ; R15(R16,R17)
 51 [-]: SELF      R15 R14 K20  ; R16 := R14; R15 := R14[0x1586e35e]
 52 [-]: CONST     R17 7        ; R17 := 7.000000
 53 [-]: CONST     R18 1        ; R18 := 1.000000
 54 [-]: CALL      R15 4 1      ; R15(R16,R17,R18)
 55 [-]: SELF      R15 R14 K21  ; R16 := R14; R15 := R14[0xf4dc3420]
 56 [-]: MOVE      R17 R0       ; R17 := R0
 57 [-]: CALL      R15 3 1      ; R15(R16,R17)
 58 [-]: SETTABLE  R14 K22 K23  ; R14["checkForCover"] := true
 59 [-]: SETTABLE  R14 K24 K25  ; R14["staticCoverOnly"] := false
 60 [-]: SETTABLE  R14 K26 K6   ; R14["fallOff"] := 1.000000
 61 [-]: SETTABLE  R14 K27 K23  ; R14["hostAuthoritative"] := true
 62 [-]: GETGLOBAL R15 K11      ; R15 := 0x89326c93
 63 [-]: SELF      R15 R15 K28  ; R16 := R15; R15 := R15[0x97dcff30]
 64 [-]: MOVE      R17 R14      ; R17 := R14
 65 [-]: CALL      R15 3 1      ; R15(R16,R17)
 66 [-]: LOADNIL   R15 R16      ; R15 := R16 := nil
 67 [-]: CONST     R17 0        ; R17 := 0.000000
 68 [-]: TEST      R13 0        ; if not R13 then PC := 92
 69 [-]: JMP       92           ; PC := 92
 70 [-]: CONST     R17 -800     ; R17 := -800.000000
 71 [-]: GETGLOBAL R18 K11      ; R18 := 0x89326c93
 72 [-]: SELF      R18 R18 K29  ; R19 := R18; R18 := R18[0x05909209]
 73 [-]: GETGLOBAL R20 K30      ; R20 := 0x76ecb54a
 74 [-]: MOVE      R21 R8       ; R21 := R8
 75 [-]: GETGLOBAL R22 K31      ; R22 := ZERO_ROTATION
 76 [-]: MOVE      R23 R1       ; R23 := R1
 77 [-]: CALL      R18 6 2      ; R18 := R18(R19,R20,R21,R22,R23)
 78 [-]: MOVE      R15 R18      ; R15 := R18
 79 [-]: SELF      R18 R1 K32   ; R19 := R1; R18 := R1[0xa5e492d4]
 80 [-]: CALL      R18 2 2      ; R18 := R18(R19)
 81 [-]: TEST      R18 0        ; if not R18 then PC := 112
 82 [-]: JMP       112          ; PC := 112
 83 [-]: GETGLOBAL R18 K11      ; R18 := 0x89326c93
 84 [-]: SELF      R18 R18 K29  ; R19 := R18; R18 := R18[0x05909209]
 85 [-]: GETGLOBAL R20 K33      ; R20 := 0x723d515a
 86 [-]: MOVE      R21 R8       ; R21 := R8
 87 [-]: GETGLOBAL R22 K31      ; R22 := ZERO_ROTATION
 88 [-]: MOVE      R23 R0       ; R23 := R0
 89 [-]: CALL      R18 6 2      ; R18 := R18(R19,R20,R21,R22,R23)
 90 [-]: MOVE      R16 R18      ; R16 := R18
 91 [-]: JMP       112          ; PC := 112
 92 [-]: SELF      R18 R1 K34   ; R19 := R1; R18 := R1[0x47901f07]
 93 [-]: GETGLOBAL R20 K35      ; R20 := 0x945f9957
 94 [-]: GETGLOBAL R21 K36      ; R21 := EMPTY_SYMBOL
 95 [-]: GETGLOBAL R22 K37      ; R22 := ZERO_VECTOR
 96 [-]: GETGLOBAL R23 K31      ; R23 := ZERO_ROTATION
 97 [-]: MOVE      R24 R1       ; R24 := R1
 98 [-]: CALL      R18 7 2      ; R18 := R18(R19,R20,R21,R22,R23,R24)
 99 [-]: MOVE      R15 R18      ; R15 := R18
100 [-]: SELF      R18 R1 K32   ; R19 := R1; R18 := R1[0xa5e492d4]
101 [-]: CALL      R18 2 2      ; R18 := R18(R19)
102 [-]: TEST      R18 0        ; if not R18 then PC := 112
103 [-]: JMP       112          ; PC := 112
104 [-]: SELF      R18 R1 K34   ; R19 := R1; R18 := R1[0x47901f07]
105 [-]: GETGLOBAL R20 K33      ; R20 := 0x723d515a
106 [-]: GETGLOBAL R21 K36      ; R21 := EMPTY_SYMBOL
107 [-]: GETGLOBAL R22 K37      ; R22 := ZERO_VECTOR
108 [-]: GETGLOBAL R23 K31      ; R23 := ZERO_ROTATION
109 [-]: MOVE      R24 R0       ; R24 := R0
110 [-]: CALL      R18 7 2      ; R18 := R18(R19,R20,R21,R22,R23,R24)
111 [-]: MOVE      R16 R18      ; R16 := R18
112 [-]: LOADNIL   R18 R21      ; R18 := R19 := R20 := R21 := nil
113 [-]: GETUPVAL  R22 U2       ; R22 := U2
114 [-]: MOVE      R23 R2       ; R23 := R2
115 [-]: MOVE      R24 R8       ; R24 := R8
116 [-]: MOVE      R25 R18      ; R25 := R18
117 [-]: MOVE      R26 R19      ; R26 := R19
118 [-]: MOVE      R27 R20      ; R27 := R20
119 [-]: MOVE      R28 R21      ; R28 := R21
120 [-]: CALL      R22 7 1      ; R22(R23,R24,R25,R26,R27,R28)
121 [-]: GETGLOBAL R22 K9       ; R22 := 0x34291f5c
122 [-]: GETTABLE  R22 R22 K38  ; R22 := R22[0x35c16153]
123 [-]: CALL      R22 1 2      ; R22 := R22()
124 [-]: SELF      R23 R22 K20  ; R24 := R22; R23 := R22[0x1586e35e]
125 [-]: CONST     R25 7        ; R25 := 7.000000
126 [-]: CONST     R26 1        ; R26 := 1.000000
127 [-]: CALL      R23 4 1      ; R23(R24,R25,R26)
128 [-]: SELF      R23 R22 K14  ; R24 := R22; R23 := R22[0x86cd00cb]
129 [-]: MOVE      R25 R1       ; R25 := R1
130 [-]: CALL      R23 3 1      ; R23(R24,R25)
131 [-]: SELF      R23 R22 K21  ; R24 := R22; R23 := R22[0xf4dc3420]
132 [-]: MOVE      R25 R0       ; R25 := R0
133 [-]: CALL      R23 3 1      ; R23(R24,R25)
134 [-]: SELF      R23 R22 K39  ; R24 := R22; R23 := R22[0xca73dd2a]
135 [-]: CONST     R25 0        ; R25 := 0.000000
136 [-]: CALL      R23 3 1      ; R23(R24,R25)
137 [-]: SELF      R23 R22 K40  ; R24 := R22; R23 := R22[0xfc0e440a]
138 [-]: CONST     R25 20       ; R25 := 20.000000
139 [-]: MOVE      R26 R13      ; R26 := R13
140 [-]: CALL      R23 4 1      ; R23(R24,R25,R26)
141 [-]: SELF      R23 R22 K41  ; R24 := R22; R23 := R22[0xe18620d2]
142 [-]: GETGLOBAL R25 K42      ; R25 := 0x5353cdba
143 [-]: CALL      R23 3 1      ; R23(R24,R25)
144 [-]: LOADNIL   R23 R23      ; R23 := nil
145 [-]: CONST     R24 1        ; R24 := 1.000000
146 [-]: TEST      R10 0        ; if not R10 then PC := 158
147 [-]: JMP       158          ; PC := 158
148 [-]: NEWTABLE  R25 3 0      ; R25 := {}
149 [-]: CONST     R26 17       ; R26 := 17.000000
150 [-]: CONST     R27 20       ; R27 := 20.000000
151 [-]: CONST     R28 17       ; R28 := 17.000000
152 [-]: SETLIST   R25 3 1      ; R25[(1-1)*FPF+i] := R(25+i), 1 <= i <= 3
153 [-]: MOVE      R23 R25      ; R23 := R25
154 [-]: SELF      R25 R22 K40  ; R26 := R22; R25 := R22[0xfc0e440a]
155 [-]: GETTABLE  R27 R23 R24  ; R27 := R23[R24]
156 [-]: LOADKB    R28 1 0      ; R28 := true
157 [-]: CALL      R25 4 1      ; R25(R26,R27,R28)
158 [-]: GETGLOBAL R25 K43      ; R25 := 0x0469f296
159 [-]: LOADK     R26 K44      ; R26 := "DECREE_SONICQUAKE"
160 [-]: CALL      R25 2 2      ; R25 := R25(R26)
161 [-]: CONST     R26 0        ; R26 := 0.000000
162 [-]: NEWTABLE  R27 0 0      ; R27 := {}
163 [-]: LOADKB    R28 0 0      ; R28 := false
164 [-]: GETGLOBAL R29 K45      ; R29 := 0x7b998233
165 [-]: MOVE      R30 R1       ; R30 := R1
166 [-]: CALL      R29 2 2      ; R29 := R29(R30)
167 [-]: TEST      R29 1        ; if R29 then PC := 447
168 [-]: JMP       447          ; PC := 447
169 [-]: SELF      R29 R1 K46   ; R30 := R1; R29 := R1[0x73901acf]
170 [-]: CALL      R29 2 2      ; R29 := R29(R30)
171 [-]: TEST      R29 1        ; if R29 then PC := 447
172 [-]: JMP       447          ; PC := 447
173 [-]: SELF      R29 R1 K47   ; R30 := R1; R29 := R1[0x2047cfe7]
174 [-]: CALL      R29 2 2      ; R29 := R29(R30)
175 [-]: TEST      R29 1        ; if R29 then PC := 447
176 [-]: JMP       447          ; PC := 447
177 [-]: GETGLOBAL R29 K45      ; R29 := 0x7b998233
178 [-]: GETGLOBAL R30 K48      ; R30 := 0x6687f6e0
179 [-]: CALL      R29 2 2      ; R29 := R29(R30)
180 [-]: TEST      R29 1        ; if R29 then PC := 447
181 [-]: JMP       447          ; PC := 447
182 [-]: GETGLOBAL R29 K48      ; R29 := 0x6687f6e0
183 [-]: SELF      R29 R29 K49  ; R30 := R29; R29 := R29[0x30f46140]
184 [-]: CALL      R29 2 2      ; R29 := R29(R30)
185 [-]: TEST      R29 1        ; if R29 then PC := 447
186 [-]: JMP       447          ; PC := 447
187 [-]: TEST      R13 1        ; if R13 then PC := 192
188 [-]: JMP       192          ; PC := 192
189 [-]: SELF      R29 R1 K0    ; R30 := R1; R29 := R1[0xf6ebd926]
190 [-]: CALL      R29 2 2      ; R29 := R29(R30)
191 [-]: MOVE      R8 R29       ; R8 := R29
192 [-]: LE        0 R26 K4     ; if R26 > 0.000000 then PC := 203
193 [-]: JMP       203          ; PC := 203
194 [-]: GETGLOBAL R29 K11      ; R29 := 0x89326c93
195 [-]: SELF      R29 R29 K50  ; R30 := R29; R29 := R29[0xfb669000]
196 [-]: GETGLOBAL R31 K51      ; R31 := gBaseAvatarType
197 [-]: MOVE      R32 R8       ; R32 := R8
198 [-]: CONST     R33 0        ; R33 := 0.000000
199 [-]: MOVE      R34 R5       ; R34 := R5
200 [-]: CALL      R29 6 2      ; R29 := R29(R30,R31,R32,R33,R34)
201 [-]: MOVE      R9 R29       ; R9 := R29
202 [-]: ADD       R26 R26 K52  ; R26 := R26 + 0.200000
203 [-]: LT        0 R6 R5      ; if R6 >= R5 then PC := 213
204 [-]: JMP       213          ; PC := 213
205 [-]: GETUPVAL  R29 U3       ; R29 := U3
206 [-]: MOVE      R30 R5       ; R30 := R5
207 [-]: MOVE      R31 R8       ; R31 := R8
208 [-]: MOVE      R32 R18      ; R32 := R18
209 [-]: MOVE      R33 R19      ; R33 := R19
210 [-]: MOVE      R34 R20      ; R34 := R20
211 [-]: MOVE      R35 R21      ; R35 := R21
212 [-]: CALL      R29 7 1      ; R29(R30,R31,R32,R33,R34,R35)
213 [-]: GETGLOBAL R29 K53      ; R29 := 0x55156ff7
214 [-]: CALL      R29 1 2      ; R29 := R29()
215 [-]: GETGLOBAL R30 K54      ; R30 := 0xc8802016
216 [-]: MOVE      R31 R9       ; R31 := R9
217 [-]: CALL      R30 2 4      ; R30,R31,R32 := R30(R31)
218 [-]: JMP       332          ; PC := 332
219 [-]: GETGLOBAL R35 K45      ; R35 := 0x7b998233
220 [-]: MOVE      R36 R34      ; R36 := R34
221 [-]: CALL      R35 2 2      ; R35 := R35(R36)
222 [-]: TEST      R35 1        ; if R35 then PC := 332
223 [-]: JMP       332          ; PC := 332
224 [-]: SELF      R35 R1 K55   ; R36 := R1; R35 := R1[0xee0bc178]
225 [-]: MOVE      R37 R34      ; R37 := R34
226 [-]: CALL      R35 3 2      ; R35 := R35(R36,R37)
227 [-]: TEST      R35 1        ; if R35 then PC := 332
228 [-]: JMP       332          ; PC := 332
229 [-]: SELF      R35 R34 K56  ; R36 := R34; R35 := R34[0xc4dff581]
230 [-]: CONST     R37 0        ; R37 := 0.000000
231 [-]: CALL      R35 3 2      ; R35 := R35(R36,R37)
232 [-]: TEST      R35 1        ; if R35 then PC := 332
233 [-]: JMP       332          ; PC := 332
234 [-]: GETGLOBAL R35 K45      ; R35 := 0x7b998233
235 [-]: SELF      R36 R34 K57  ; R37 := R34; R36 := R34[0x5e651723]
236 [-]: CALL      R36 2 0      ; R36,... := R36(R37)
237 [-]: CALL      R35 0 2      ; R35 := R35(R36,...)
238 [-]: TEST      R35 0        ; if not R35 then PC := 267
239 [-]: JMP       267          ; PC := 267
240 [-]: SELF      R35 R34 K58  ; R36 := R34; R35 := R34[0xf2deaf69]
241 [-]: GETGLOBAL R37 K59      ; R37 := gLotusNpcAvatarType
242 [-]: CALL      R35 3 2      ; R35 := R35(R36,R37)
243 [-]: TEST      R35 0        ; if not R35 then PC := 267
244 [-]: JMP       267          ; PC := 267
245 [-]: SELF      R35 R34 K60  ; R36 := R34; R35 := R34[0x444ae2c8]
246 [-]: CALL      R35 2 2      ; R35 := R35(R36)
247 [-]: TEST      R35 1        ; if R35 then PC := 267
248 [-]: JMP       267          ; PC := 267
249 [-]: SELF      R35 R34 K56  ; R36 := R34; R35 := R34[0xc4dff581]
250 [-]: CONST     R37 8        ; R37 := 8.000000
251 [-]: CALL      R35 3 2      ; R35 := R35(R36,R37)
252 [-]: TEST      R35 1        ; if R35 then PC := 267
253 [-]: JMP       267          ; PC := 267
254 [-]: TEST      R13 1        ; if R13 then PC := 267
255 [-]: JMP       267          ; PC := 267
256 [-]: SELF      R35 R34 K61  ; R36 := R34; R35 := R34[0x0f89a4d4]
257 [-]: MOVE      R37 R25      ; R37 := R25
258 [-]: LOADKB    R38 0 0      ; R38 := false
259 [-]: CONST     R39 4        ; R39 := 4.000000
260 [-]: CONST     R40 1        ; R40 := 1.000000
261 [-]: LOADKB    R41 1 0      ; R41 := true
262 [-]: GETGLOBAL R42 K62      ; R42 := 0x55730e1a
263 [-]: CONST     R43 0        ; R43 := 0.000000
264 [-]: CONST     R44 3        ; R44 := 3.000000
265 [-]: CALL      R42 3 0      ; R42,... := R42(R43,R44)
266 [-]: CALL      R35 0 1      ; R35(R36,...)
267 [-]: GETGLOBAL R35 K11      ; R35 := 0x89326c93
268 [-]: SELF      R35 R35 K12  ; R36 := R35; R35 := R35[0x18d05d30]
269 [-]: CALL      R35 2 2      ; R35 := R35(R36)
270 [-]: TEST      R35 0        ; if not R35 then PC := 332
271 [-]: JMP       332          ; PC := 332
272 [-]: SELF      R35 R34 K63  ; R36 := R34; R35 := R34[0x388577d5]
273 [-]: CALL      R35 2 2      ; R35 := R35(R36)
274 [-]: GETTABLE  R36 R27 R35  ; R36 := R27[R35]
275 [-]: EQ        1 R36 K64    ; if R36 == nil then PC := 280
276 [-]: JMP       280          ; PC := 280
277 [-]: GETTABLE  R36 R27 R35  ; R36 := R27[R35]
278 [-]: LE        0 R36 R29    ; if R36 > R29 then PC := 332
279 [-]: JMP       332          ; PC := 332
280 [-]: SELF      R36 R3 K65   ; R37 := R3; R36 := R3[0x111f713c]
281 [-]: CALL      R36 2 2      ; R36 := R36(R37)
282 [-]: MUL       R36 R36 R4   ; R36 := R36 * R4
283 [-]: TEST      R13 0        ; if not R13 then PC := 294
284 [-]: JMP       294          ; PC := 294
285 [-]: SELF      R37 R1 K66   ; R38 := R1; R37 := R1[0xbebad19f]
286 [-]: MOVE      R39 R34      ; R39 := R34
287 [-]: CALL      R37 3 2      ; R37 := R37(R38,R39)
288 [-]: GETGLOBAL R38 K67      ; R38 := 0x9bafffe3
289 [-]: CONST     R39 1        ; R39 := 1.000000
290 [-]: GETUPVAL  R40 U4       ; R40 := U4
291 [-]: DIV       R41 R37 R5   ; R41 := R37 / R5
292 [-]: CALL      R38 4 2      ; R38 := R38(R39,R40,R41)
293 [-]: MUL       R36 R36 R38  ; R36 := R36 * R38
294 [-]: TEST      R10 0        ; if not R10 then PC := 311
295 [-]: JMP       311          ; PC := 311
296 [-]: SELF      R38 R34 K68  ; R39 := R34; R38 := R34[0x0e46e45b]
297 [-]: CONST     R40 15       ; R40 := 15.000000
298 [-]: CALL      R38 3 2      ; R38 := R38(R39,R40)
299 [-]: TEST      R38 0        ; if not R38 then PC := 307
300 [-]: JMP       307          ; PC := 307
301 [-]: DIV       R36 R36 K69  ; R36 := R36 / 2.000000
302 [-]: SELF      R38 R22 K40  ; R39 := R22; R38 := R22[0xfc0e440a]
303 [-]: GETTABLE  R40 R23 R24  ; R40 := R23[R24]
304 [-]: LOADKB    R41 0 0      ; R41 := false
305 [-]: CALL      R38 4 1      ; R38(R39,R40,R41)
306 [-]: JMP       311          ; PC := 311
307 [-]: SELF      R38 R22 K40  ; R39 := R22; R38 := R22[0xfc0e440a]
308 [-]: GETTABLE  R40 R23 R24  ; R40 := R23[R24]
309 [-]: LOADKB    R41 1 0      ; R41 := true
310 [-]: CALL      R38 4 1      ; R38(R39,R40,R41)
311 [-]: GETGLOBAL R38 K9       ; R38 := 0x34291f5c
312 [-]: GETTABLE  R38 R38 K70  ; R38 := R38[0x7258f36f]
313 [-]: MOVE      R39 R36      ; R39 := R36
314 [-]: CALL      R38 2 2      ; R38 := R38(R39)
315 [-]: MOVE      R36 R38      ; R36 := R38
316 [-]: SELF      R38 R36 K71  ; R39 := R36; R38 := R36[0xe4c4dc01]
317 [-]: MOVE      R40 R3       ; R40 := R3
318 [-]: CALL      R38 3 1      ; R38(R39,R40)
319 [-]: SELF      R38 R22 K16  ; R39 := R22; R38 := R22[0xf326045f]
320 [-]: MOVE      R40 R36      ; R40 := R36
321 [-]: CALL      R38 3 1      ; R38(R39,R40)
322 [-]: SELF      R38 R34 K72  ; R39 := R34; R38 := R34[0x479483bb]
323 [-]: MOVE      R40 R22      ; R40 := R22
324 [-]: MOVE      R41 R17      ; R41 := R17
325 [-]: CALL      R38 4 1      ; R38(R39,R40,R41)
326 [-]: TEST      R13 0        ; if not R13 then PC := 330
327 [-]: JMP       330          ; PC := 330
328 [-]: SETTABLE  R27 R35 K73  ; R27[R35] := 340282346638528859811704183484516925440.000000
329 [-]: JMP       332          ; PC := 332
330 [-]: ADD       R38 R29 K6   ; R38 := R29 + 1.000000
331 [-]: SETTABLE  R27 R35 R38  ; R27[R35] := R38
332 [-]: TFORLOOP  R30 2        ; R33,R34 :=  R30(R31,R32); if R33 ~= nil then begin PC = 219; R32 := R33 end
333 [-]: JMP       219          ; PC := 219
334 [-]: TEST      R13 0        ; if not R13 then PC := 340
335 [-]: JMP       340          ; PC := 340
336 [-]: LE        0 R2 R6      ; if R2 > R6 then PC := 400
337 [-]: JMP       400          ; PC := 400
338 [-]: JMP       447          ; PC := 447
339 [-]: JMP       400          ; PC := 400
340 [-]: SELF      R38 R1 K32   ; R39 := R1; R38 := R1[0xa5e492d4]
341 [-]: CALL      R38 2 2      ; R38 := R38(R39)
342 [-]: EQ        1 R28 R38    ; if R28 == R38 then PC := 386
343 [-]: JMP       386          ; PC := 386
344 [-]: NOT       R28 R28      ; R28 :=  R28
345 [-]: TEST      R28 0        ; if not R28 then PC := 376
346 [-]: JMP       376          ; PC := 376
347 [-]: GETGLOBAL R38 K74      ; R38 := _T
348 [-]: GETTABLE  R38 R38 K75  ; R38 := R38[0xa647617f]
349 [-]: CONST     R39 3        ; R39 := 3.000000
350 [-]: LOADKB    R40 1 0      ; R40 := true
351 [-]: CALL      R38 3 1      ; R38(R39,R40)
352 [-]: SELF      R38 R1 K76   ; R39 := R1; R38 := R1[0x0b4bcfb6]
353 [-]: CALL      R38 2 2      ; R38 := R38(R39)
354 [-]: GETGLOBAL R39 K45      ; R39 := 0x7b998233
355 [-]: MOVE      R40 R38      ; R40 := R38
356 [-]: CALL      R39 2 2      ; R39 := R39(R40)
357 [-]: TEST      R39 1        ; if R39 then PC := 365
358 [-]: JMP       365          ; PC := 365
359 [-]: SELF      R39 R38 K77  ; R40 := R38; R39 := R38[0x758c046d]
360 [-]: GETGLOBAL R41 K78      ; R41 := 0xb37905d5
361 [-]: CONST     R42 1        ; R42 := 1.000000
362 [-]: CONST     R43 -1       ; R43 := -1.000000
363 [-]: CONST     R44 1        ; R44 := 1.000000
364 [-]: CALL      R39 6 1      ; R39(R40,R41,R42,R43,R44)
365 [-]: GETGLOBAL R39 K11      ; R39 := 0x89326c93
366 [-]: SELF      R39 R39 K79  ; R40 := R39; R39 := R39[0x7c1a0374]
367 [-]: CALL      R39 2 2      ; R39 := R39(R40)
368 [-]: GETTABLE  R39 R39 K80  ; R39 := R39["postProcess"]
369 [-]: SELF      R40 R39 K81  ; R41 := R39; R40 := R39[0xf038ec0b]
370 [-]: GETUPVAL  R42 U5       ; R42 := U5
371 [-]: CALL      R40 3 1      ; R40(R41,R42)
372 [-]: SELF      R40 R39 K82  ; R41 := R39; R40 := R39[0xc7bdb630]
373 [-]: GETUPVAL  R42 U6       ; R42 := U6
374 [-]: CALL      R40 3 1      ; R40(R41,R42)
375 [-]: JMP       386          ; PC := 386
376 [-]: GETGLOBAL R40 K11      ; R40 := 0x89326c93
377 [-]: SELF      R40 R40 K79  ; R41 := R40; R40 := R40[0x7c1a0374]
378 [-]: CALL      R40 2 2      ; R40 := R40(R41)
379 [-]: GETTABLE  R40 R40 K80  ; R40 := R40["postProcess"]
380 [-]: SELF      R41 R40 K81  ; R42 := R40; R41 := R40[0xf038ec0b]
381 [-]: CONST     R43 1        ; R43 := 1.000000
382 [-]: CALL      R41 3 1      ; R41(R42,R43)
383 [-]: SELF      R41 R40 K82  ; R42 := R40; R41 := R40[0xc7bdb630]
384 [-]: CONST     R43 0        ; R43 := 0.000000
385 [-]: CALL      R41 3 1      ; R41(R42,R43)
386 [-]: SELF      R41 R1 K83   ; R42 := R1; R41 := R1[0x16e0b3da]
387 [-]: GETGLOBAL R43 K84      ; R43 := 0x66c01afd
388 [-]: CALL      R41 3 2      ; R41 := R41(R42,R43)
389 [-]: TEST      R41 1        ; if R41 then PC := 400
390 [-]: JMP       400          ; PC := 400
391 [-]: GETUPVAL  R41 U7       ; R41 := U7
392 [-]: GETTABLE  R41 R41 K85  ; R41 := R41[0x54697cb5]
393 [-]: MOVE      R42 R0       ; R42 := R0
394 [-]: GETGLOBAL R43 K84      ; R43 := 0x66c01afd
395 [-]: LOADKB    R44 0 0      ; R44 := false
396 [-]: CONST     R45 2        ; R45 := 2.000000
397 [-]: CONST     R46 2        ; R46 := 2.000000
398 [-]: LOADKB    R47 1 0      ; R47 := true
399 [-]: CALL      R41 7 1      ; R41(R42,R43,R44,R45,R46,R47)
400 [-]: MOVE      R6 R5        ; R6 := R5
401 [-]: GETGLOBAL R41 K86      ; R41 := 0x5bced4c4
402 [-]: GETTABLE  R41 R41 K87  ; R41 := R41[0xac1b386a]
403 [-]: MOVE      R42 R2       ; R42 := R2
404 [-]: GETGLOBAL R43 K88      ; R43 := 0x67652851
405 [-]: CALL      R43 1 2      ; R43 := R43()
406 [-]: MUL       R43 R43 K89  ; R43 := R43 * 20.000000
407 [-]: ADD       R43 R5 R43   ; R43 := R5 + R43
408 [-]: CALL      R41 3 2      ; R41 := R41(R42,R43)
409 [-]: MOVE      R5 R41       ; R5 := R41
410 [-]: GETGLOBAL R41 K45      ; R41 := 0x7b998233
411 [-]: MOVE      R42 R16      ; R42 := R16
412 [-]: CALL      R41 2 2      ; R41 := R41(R42)
413 [-]: TEST      R41 1        ; if R41 then PC := 418
414 [-]: JMP       418          ; PC := 418
415 [-]: SELF      R41 R16 K90  ; R42 := R16; R41 := R16[0x2d9ba74f]
416 [-]: DIV       R43 R5 K18   ; R43 := R5 / 5.000000
417 [-]: CALL      R41 3 1      ; R41(R42,R43)
418 [-]: LE        0 K6 R7      ; if 1.000000 > R7 then PC := 434
419 [-]: JMP       434          ; PC := 434
420 [-]: SUB       R7 R7 K6     ; R7 := R7 - 1.000000
421 [-]: EQ        1 R23 K64    ; if R23 == nil then PC := 434
422 [-]: JMP       434          ; PC := 434
423 [-]: SELF      R41 R22 K40  ; R42 := R22; R41 := R22[0xfc0e440a]
424 [-]: GETTABLE  R43 R23 R24  ; R43 := R23[R24]
425 [-]: LOADKB    R44 0 0      ; R44 := false
426 [-]: CALL      R41 4 1      ; R41(R42,R43,R44)
427 [-]: LEN       R41 R23      ; R41 := # R23
428 [-]: MOD       R41 R24 R41  ; R41 := R24 % R41
429 [-]: ADD       R24 R41 K6   ; R24 := R41 + 1.000000
430 [-]: SELF      R41 R22 K40  ; R42 := R22; R41 := R22[0xfc0e440a]
431 [-]: GETTABLE  R43 R23 R24  ; R43 := R23[R24]
432 [-]: LOADKB    R44 1 0      ; R44 := true
433 [-]: CALL      R41 4 1      ; R41(R42,R43,R44)
434 [-]: GETGLOBAL R41 K91      ; R41 := 0xcbd666e1
435 [-]: CONST     R42 0        ; R42 := 0.000000
436 [-]: CALL      R41 2 1      ; R41(R42)
437 [-]: GETGLOBAL R41 K88      ; R41 := 0x67652851
438 [-]: CALL      R41 1 2      ; R41 := R41()
439 [-]: ADD       R7 R7 R41    ; R7 := R7 + R41
440 [-]: SUB       R26 R26 R41  ; R26 := R26 - R41
441 [-]: TEST      R13 0        ; if not R13 then PC := 164
442 [-]: JMP       164          ; PC := 164
443 [-]: LE        0 R2 R5      ; if R2 > R5 then PC := 164
444 [-]: JMP       164          ; PC := 164
445 [-]: CONST     R26 0        ; R26 := 0.000000
446 [-]: JMP       164          ; PC := 164
447 [-]: TEST      R13 0        ; if not R13 then PC := 463
448 [-]: JMP       463          ; PC := 463
449 [-]: GETGLOBAL R42 K45      ; R42 := 0x7b998233
450 [-]: MOVE      R43 R15      ; R43 := R15
451 [-]: CALL      R42 2 2      ; R42 := R42(R43)
452 [-]: TEST      R42 1        ; if R42 then PC := 456
453 [-]: JMP       456          ; PC := 456
454 [-]: SELF      R42 R15 K92  ; R43 := R15; R42 := R15[0xa2880940]
455 [-]: CALL      R42 2 1      ; R42(R43)
456 [-]: GETGLOBAL R42 K45      ; R42 := 0x7b998233
457 [-]: MOVE      R43 R16      ; R43 := R16
458 [-]: CALL      R42 2 2      ; R42 := R42(R43)
459 [-]: TEST      R42 1        ; if R42 then PC := 463
460 [-]: JMP       463          ; PC := 463
461 [-]: SELF      R42 R16 K93  ; R43 := R16; R42 := R16[0x1db57c6b]
462 [-]: CALL      R42 2 1      ; R42(R43)
463 [-]: RETURN    R0 1         ; return 


; Function #12:
;
; Name:            
; Defined at line: 525
; #Upvalues:       4
; #Parameters:     1
; Is_vararg:       0
; Max Stack Size:  7

  1 [-]: GETUPVAL  R1 U0        ; R1 := U0
  2 [-]: SELF      R2 R0 K0     ; R3 := R0; R2 := R0[0xde321e6f]
  3 [-]: CALL      R2 2 2       ; R2 := R2(R3)
  4 [-]: SELF      R2 R2 K1     ; R3 := R2; R2 := R2[0xf7d48ee0]
  5 [-]: CALL      R2 2 2       ; R2 := R2(R3)
  6 [-]: MOVE      R3 R0        ; R3 := R0
  7 [-]: GETUPVAL  R4 U1        ; R4 := U1
  8 [-]: GETUPVAL  R5 U2        ; R5 := U2
  9 [-]: GETUPVAL  R6 U3        ; R6 := U3
 10 [-]: CALL      R1 6 1       ; R1(R2,R3,R4,R5,R6)
 11 [-]: RETURN    R0 1         ; return 


; Function #13:
;
; Name:            
; Defined at line: 529
; #Upvalues:       10
; #Parameters:     4
; Is_vararg:       0
; Max Stack Size:  17

  1 [-]: GETUPVAL  R4 U0        ; R4 := U0
  2 [-]: MOVE      R5 R3        ; R5 := R3
  3 [-]: CALL      R4 2 1       ; R4(R5)
  4 [-]: GETUPVAL  R4 U3        ; R4 := U3
  5 [-]: MOVE      R5 R1        ; R5 := R1
  6 [-]: CALL      R4 2 3       ; R4,R5 := R4(R5)
  7 [-]: SETUPVAL  R5 U2        ; U82 := R2
  8 [-]: SETUPVAL  R4 U1        ; U82 := R1
  9 [-]: SELF      R4 R0 K0     ; R5 := R0; R4 := R0[0x5063edc3]
 10 [-]: CALL      R4 2 2       ; R4 := R4(R5)
 11 [-]: SELF      R5 R0 K1     ; R6 := R0; R5 := R0[0x75ecaf0b]
 12 [-]: CALL      R5 2 2       ; R5 := R5(R6)
 13 [-]: LT        0 K2 R4      ; if 0.000000 >= R4 then PC := 17
 14 [-]: JMP       17           ; PC := 17
 15 [-]: EQ        1 R5 K4      ; if R5 == 1.000000 then PC := 18
 16 [-]: JMP       18           ; PC := 18
 17 [-]: LOADKB    R6 0 1       ; R6 := false; PC := 18
 18 [-]: LOADKB    R6 1 0       ; R6 := true
 19 [-]: TEST      R6 0         ; if not R6 then PC := 29
 20 [-]: JMP       29           ; PC := 29
 21 [-]: GETUPVAL  R7 U4        ; R7 := U4
 22 [-]: MOVE      R8 R4        ; R8 := R4
 23 [-]: MOVE      R9 R5        ; R9 := R5
 24 [-]: CALL      R7 3 1       ; R7(R8,R9)
 25 [-]: GETUPVAL  R7 U1        ; R7 := U1
 26 [-]: GETUPVAL  R8 U5        ; R8 := U5
 27 [-]: MUL       R7 R7 R8     ; R7 := R7 * R8
 28 [-]: SETUPVAL  R7 U1        ; U82 := R1
 29 [-]: SELF      R7 R0 K5     ; R8 := R0; R7 := R0[0xf0ae08d4]
 30 [-]: CONST     R9 0         ; R9 := 0.000000
 31 [-]: CALL      R7 3 1       ; R7(R8,R9)
 32 [-]: GETUPVAL  R7 U6        ; R7 := U6
 33 [-]: GETTABLE  R7 R7 K6     ; R7 := R7[0x32316a21]
 34 [-]: CALL      R7 1 2       ; R7 := R7()
 35 [-]: TEST      R7 0         ; if not R7 then PC := 48
 36 [-]: JMP       48           ; PC := 48
 37 [-]: GETGLOBAL R7 K7        ; R7 := 0x6687f6e0
 38 [-]: SELF      R7 R7 K8     ; R8 := R7; R7 := R7[0x3a147087]
 39 [-]: GETGLOBAL R9 K9        ; R9 := 0xb009bbc6
 40 [-]: GETGLOBAL R10 K7       ; R10 := 0x6687f6e0
 41 [-]: SELF      R10 R10 K10  ; R11 := R10; R10 := R10[0xcde10c4a]
 42 [-]: CALL      R10 2 0      ; R10,... := R10(R11)
 43 [-]: CALL      R9 0 2       ; R9 := R9(R10,...)
 44 [-]: SELF      R9 R9 K11    ; R10 := R9; R9 := R9[0x7e627183]
 45 [-]: LOADKB    R11 0 0      ; R11 := false
 46 [-]: CALL      R9 3 0       ; R9,... := R9(R10,R11)
 47 [-]: CALL      R7 0 1       ; R7(R8,...)
 48 [-]: SELF      R7 R1 K12    ; R8 := R1; R7 := R1[0x47901f07]
 49 [-]: GETGLOBAL R9 K13       ; R9 := 0x17c91a14
 50 [-]: GETGLOBAL R10 K14      ; R10 := EMPTY_SYMBOL
 51 [-]: GETGLOBAL R11 K15      ; R11 := ZERO_VECTOR
 52 [-]: GETGLOBAL R12 K16      ; R12 := ZERO_ROTATION
 53 [-]: MOVE      R13 R0       ; R13 := R0
 54 [-]: CALL      R7 7 1       ; R7(R8,R9,R10,R11,R12,R13)
 55 [-]: SELF      R7 R0 K17    ; R8 := R0; R7 := R0[0x68b88e58]
 56 [-]: LOADKB    R9 1 0       ; R9 := true
 57 [-]: CALL      R7 3 1       ; R7(R8,R9)
 58 [-]: GETUPVAL  R7 U7        ; R7 := U7
 59 [-]: GETTABLE  R7 R7 K18    ; R7 := R7[0xb443c7bd]
 60 [-]: MOVE      R8 R1        ; R8 := R1
 61 [-]: GETGLOBAL R9 K19       ; R9 := 0x99cb4b90
 62 [-]: GETGLOBAL R10 K20      ; R10 := 0x0ed8b456
 63 [-]: LOADK     R11 K21      ; R11 := "Quake"
 64 [-]: CALL      R7 5 2       ; R7 := R7(R8,R9,R10,R11)
 65 [-]: TEST      R7 1         ; if R7 then PC := 68
 66 [-]: JMP       68           ; PC := 68
 67 [-]: RETURN    R0 1         ; return 
 68 [-]: SELF      R7 R0 K17    ; R8 := R0; R7 := R0[0x68b88e58]
 69 [-]: LOADKB    R9 0 0       ; R9 := false
 70 [-]: CALL      R7 3 1       ; R7(R8,R9)
 71 [-]: TEST      R6 0         ; if not R6 then PC := 80
 72 [-]: JMP       80           ; PC := 80
 73 [-]: SELF      R7 R1 K22    ; R8 := R1; R7 := R1[0xd5f7912b]
 74 [-]: GETGLOBAL R9 K23       ; R9 := 0x0469f296
 75 [-]: LOADK     R10 K24      ; R10 := "DoQuake"
 76 [-]: CALL      R9 2 2       ; R9 := R9(R10)
 77 [-]: LOADKB    R10 0 0      ; R10 := false
 78 [-]: CALL      R7 4 1       ; R7(R8,R9,R10)
 79 [-]: JMP       137          ; PC := 137
 80 [-]: SELF      R7 R1 K25    ; R8 := R1; R7 := R1[0xc9f6a7d7]
 81 [-]: GETGLOBAL R9 K26       ; R9 := 0x14ce30d0
 82 [-]: CALL      R7 3 2       ; R7 := R7(R8,R9)
 83 [-]: GETGLOBAL R8 K27       ; R8 := 0x7b998233
 84 [-]: MOVE      R9 R7        ; R9 := R7
 85 [-]: CALL      R8 2 2       ; R8 := R8(R9)
 86 [-]: TEST      R8 1         ; if R8 then PC := 94
 87 [-]: JMP       94           ; PC := 94
 88 [-]: SELF      R8 R7 K28    ; R9 := R7; R8 := R7[0x22c9fbaf]
 89 [-]: GETGLOBAL R10 K29      ; R10 := 0xb7cbd06b
 90 [-]: LOADK     R11 K30      ; R11 := 0.000100
 91 [-]: CONST     R12 2        ; R12 := 2.500000
 92 [-]: CALL      R10 3 0      ; R10,... := R10(R11,R12)
 93 [-]: CALL      R8 0 1       ; R8(R9,...)
 94 [-]: SELF      R8 R0 K31    ; R9 := R0; R8 := R0[0x68d708a7]
 95 [-]: CALL      R8 2 2       ; R8 := R8(R9)
 96 [-]: SELF      R9 R8 K32    ; R10 := R8; R9 := R8[0x2540510f]
 97 [-]: CONST     R11 7        ; R11 := 7.000000
 98 [-]: CALL      R9 3 2       ; R9 := R9(R10,R11)
 99 [-]: GETGLOBAL R10 K27      ; R10 := 0x7b998233
100 [-]: MOVE      R11 R9       ; R11 := R9
101 [-]: CALL      R10 2 2      ; R10 := R10(R11)
102 [-]: TEST      R10 1        ; if R10 then PC := 116
103 [-]: JMP       116          ; PC := 116
104 [-]: SELF      R10 R9 K33   ; R11 := R9; R10 := R9[0xf2deaf69]
105 [-]: GETGLOBAL R12 K34      ; R12 := 0xefa2c420
106 [-]: CALL      R10 3 2      ; R10 := R10(R11,R12)
107 [-]: TEST      R10 0        ; if not R10 then PC := 116
108 [-]: JMP       116          ; PC := 116
109 [-]: SELF      R10 R1 K12   ; R11 := R1; R10 := R1[0x47901f07]
110 [-]: GETGLOBAL R12 K35      ; R12 := 0x8e6a4a0c
111 [-]: GETGLOBAL R13 K14      ; R13 := EMPTY_SYMBOL
112 [-]: GETGLOBAL R14 K15      ; R14 := ZERO_VECTOR
113 [-]: GETGLOBAL R15 K16      ; R15 := ZERO_ROTATION
114 [-]: MOVE      R16 R0       ; R16 := R0
115 [-]: CALL      R10 7 1      ; R10(R11,R12,R13,R14,R15,R16)
116 [-]: GETUPVAL  R10 U7       ; R10 := U7
117 [-]: GETTABLE  R10 R10 K36  ; R10 := R10[0xe2905027]
118 [-]: MOVE      R11 R1       ; R11 := R1
119 [-]: LOADKB    R12 1 0      ; R12 := true
120 [-]: CALL      R10 3 1      ; R10(R11,R12)
121 [-]: SELF      R10 R0 K5    ; R11 := R0; R10 := R0[0xf0ae08d4]
122 [-]: GETUPVAL  R12 U8       ; R12 := U8
123 [-]: CALL      R10 3 1      ; R10(R11,R12)
124 [-]: SELF      R10 R0 K37   ; R11 := R0; R10 := R0[0x6a4e4088]
125 [-]: CALL      R10 2 1      ; R10(R11)
126 [-]: SELF      R10 R0 K38   ; R11 := R0; R10 := R0[0x79f6af86]
127 [-]: LOADKB    R12 1 0      ; R12 := true
128 [-]: CALL      R10 3 1      ; R10(R11,R12)
129 [-]: GETUPVAL  R10 U9       ; R10 := U9
130 [-]: MOVE      R11 R0       ; R11 := R0
131 [-]: MOVE      R12 R1       ; R12 := R1
132 [-]: GETUPVAL  R13 U1       ; R13 := U1
133 [-]: GETUPVAL  R14 U2       ; R14 := U2
134 [-]: CONST     R15 1        ; R15 := 1.000000
135 [-]: CONST     R16 -1       ; R16 := -1.000000
136 [-]: CALL      R10 7 1      ; R10(R11,R12,R13,R14,R15,R16)
137 [-]: RETURN    R0 1         ; return 


; Function #14:
;
; Name:            
; Defined at line: 581
; #Upvalues:       3
; #Parameters:     2
; Is_vararg:       0
; Max Stack Size:  18

  1 [-]: GETUPVAL  R2 U0        ; R2 := U0
  2 [-]: GETTABLE  R2 R2 K0     ; R2 := R2[0xf847d825]
  3 [-]: MOVE      R3 R1        ; R3 := R1
  4 [-]: GETGLOBAL R4 K1        ; R4 := 0x99cb4b90
  5 [-]: GETGLOBAL R5 K2        ; R5 := 0x0ed8b456
  6 [-]: CALL      R2 4 1       ; R2(R3,R4,R5)
  7 [-]: GETUPVAL  R2 U0        ; R2 := U0
  8 [-]: GETTABLE  R2 R2 K3     ; R2 := R2[0xe2905027]
  9 [-]: MOVE      R3 R1        ; R3 := R1
 10 [-]: LOADKB    R4 0 0       ; R4 := false
 11 [-]: CALL      R2 3 1       ; R2(R3,R4)
 12 [-]: GETUPVAL  R2 U1        ; R2 := U1
 13 [-]: GETTABLE  R2 R2 K4     ; R2 := R2[0x32316a21]
 14 [-]: CALL      R2 1 2       ; R2 := R2()
 15 [-]: TEST      R2 0         ; if not R2 then PC := 21
 16 [-]: JMP       21           ; PC := 21
 17 [-]: GETGLOBAL R2 K5        ; R2 := 0x6687f6e0
 18 [-]: SELF      R2 R2 K6     ; R3 := R2; R2 := R2[0x3a147087]
 19 [-]: GETUPVAL  R4 U2        ; R4 := U2
 20 [-]: CALL      R2 3 1       ; R2(R3,R4)
 21 [-]: SELF      R2 R0 K7     ; R3 := R0; R2 := R0[0x5063edc3]
 22 [-]: CALL      R2 2 2       ; R2 := R2(R3)
 23 [-]: SELF      R3 R0 K8     ; R4 := R0; R3 := R0[0x75ecaf0b]
 24 [-]: CALL      R3 2 2       ; R3 := R3(R4)
 25 [-]: LT        0 K9 R2      ; if 0.000000 >= R2 then PC := 29
 26 [-]: JMP       29           ; PC := 29
 27 [-]: EQ        1 R3 K11     ; if R3 == 1.000000 then PC := 30
 28 [-]: JMP       30           ; PC := 30
 29 [-]: LOADKB    R4 0 1       ; R4 := false; PC := 30
 30 [-]: LOADKB    R4 1 0       ; R4 := true
 31 [-]: TEST      R4 1         ; if R4 then PC := 110
 32 [-]: JMP       110          ; PC := 110
 33 [-]: SELF      R5 R1 K12    ; R6 := R1; R5 := R1[0xc9f6a7d7]
 34 [-]: GETGLOBAL R7 K13       ; R7 := 0x945f9957
 35 [-]: CALL      R5 3 2       ; R5 := R5(R6,R7)
 36 [-]: GETGLOBAL R6 K14       ; R6 := 0x7b998233
 37 [-]: MOVE      R7 R5        ; R7 := R5
 38 [-]: CALL      R6 2 2       ; R6 := R6(R7)
 39 [-]: TEST      R6 1         ; if R6 then PC := 43
 40 [-]: JMP       43           ; PC := 43
 41 [-]: SELF      R6 R5 K15    ; R7 := R5; R6 := R5[0xa2880940]
 42 [-]: CALL      R6 2 1       ; R6(R7)
 43 [-]: SELF      R6 R1 K12    ; R7 := R1; R6 := R1[0xc9f6a7d7]
 44 [-]: GETGLOBAL R8 K16       ; R8 := 0x723d515a
 45 [-]: CALL      R6 3 2       ; R6 := R6(R7,R8)
 46 [-]: GETGLOBAL R7 K14       ; R7 := 0x7b998233
 47 [-]: MOVE      R8 R6        ; R8 := R6
 48 [-]: CALL      R7 2 2       ; R7 := R7(R8)
 49 [-]: TEST      R7 1         ; if R7 then PC := 53
 50 [-]: JMP       53           ; PC := 53
 51 [-]: SELF      R7 R6 K17    ; R8 := R6; R7 := R6[0x1db57c6b]
 52 [-]: CALL      R7 2 1       ; R7(R8)
 53 [-]: SELF      R7 R1 K12    ; R8 := R1; R7 := R1[0xc9f6a7d7]
 54 [-]: GETGLOBAL R9 K18       ; R9 := 0x8e6a4a0c
 55 [-]: CALL      R7 3 2       ; R7 := R7(R8,R9)
 56 [-]: GETGLOBAL R8 K14       ; R8 := 0x7b998233
 57 [-]: MOVE      R9 R7        ; R9 := R7
 58 [-]: CALL      R8 2 2       ; R8 := R8(R9)
 59 [-]: TEST      R8 1         ; if R8 then PC := 63
 60 [-]: JMP       63           ; PC := 63
 61 [-]: SELF      R8 R7 K15    ; R9 := R7; R8 := R7[0xa2880940]
 62 [-]: CALL      R8 2 1       ; R8(R9)
 63 [-]: SELF      R8 R1 K12    ; R9 := R1; R8 := R1[0xc9f6a7d7]
 64 [-]: GETGLOBAL R10 K19      ; R10 := 0x14ce30d0
 65 [-]: CALL      R8 3 2       ; R8 := R8(R9,R10)
 66 [-]: GETGLOBAL R9 K14       ; R9 := 0x7b998233
 67 [-]: MOVE      R10 R8       ; R10 := R8
 68 [-]: CALL      R9 2 2       ; R9 := R9(R10)
 69 [-]: TEST      R9 1         ; if R9 then PC := 77
 70 [-]: JMP       77           ; PC := 77
 71 [-]: SELF      R9 R8 K20    ; R10 := R8; R9 := R8[0x22c9fbaf]
 72 [-]: GETGLOBAL R11 K21      ; R11 := 0xb7cbd06b
 73 [-]: LOADK     R12 K22      ; R12 := 0.000100
 74 [-]: CONST     R13 0        ; R13 := 0.500000
 75 [-]: CALL      R11 3 0      ; R11,... := R11(R12,R13)
 76 [-]: CALL      R9 0 1       ; R9(R10,...)
 77 [-]: SELF      R9 R1 K23    ; R10 := R1; R9 := R1[0xa5e492d4]
 78 [-]: CALL      R9 2 2       ; R9 := R9(R10)
 79 [-]: TEST      R9 0         ; if not R9 then PC := 96
 80 [-]: JMP       96           ; PC := 96
 81 [-]: GETGLOBAL R9 K24       ; R9 := _T
 82 [-]: GETTABLE  R9 R9 K25    ; R9 := R9[0xa647617f]
 83 [-]: CONST     R10 3        ; R10 := 3.000000
 84 [-]: LOADKB    R11 0 0      ; R11 := false
 85 [-]: CALL      R9 3 1       ; R9(R10,R11)
 86 [-]: SELF      R9 R1 K26    ; R10 := R1; R9 := R1[0x0b4bcfb6]
 87 [-]: CALL      R9 2 2       ; R9 := R9(R10)
 88 [-]: GETGLOBAL R10 K14      ; R10 := 0x7b998233
 89 [-]: MOVE      R11 R9       ; R11 := R9
 90 [-]: CALL      R10 2 2      ; R10 := R10(R11)
 91 [-]: TEST      R10 1        ; if R10 then PC := 96
 92 [-]: JMP       96           ; PC := 96
 93 [-]: SELF      R10 R9 K27   ; R11 := R9; R10 := R9[0xbd5007d9]
 94 [-]: GETGLOBAL R12 K28      ; R12 := 0xb37905d5
 95 [-]: CALL      R10 3 1      ; R10(R11,R12)
 96 [-]: SELF      R10 R1 K29   ; R11 := R1; R10 := R1[0xf80fae85]
 97 [-]: CALL      R10 2 2      ; R10 := R10(R11)
 98 [-]: TEST      R10 0        ; if not R10 then PC := 110
 99 [-]: JMP       110          ; PC := 110
100 [-]: GETGLOBAL R10 K30      ; R10 := 0x89326c93
101 [-]: SELF      R10 R10 K31  ; R11 := R10; R10 := R10[0x7c1a0374]
102 [-]: CALL      R10 2 2      ; R10 := R10(R11)
103 [-]: GETTABLE  R10 R10 K32  ; R10 := R10["postProcess"]
104 [-]: SELF      R11 R10 K33  ; R12 := R10; R11 := R10[0xf038ec0b]
105 [-]: CONST     R13 1        ; R13 := 1.000000
106 [-]: CALL      R11 3 1      ; R11(R12,R13)
107 [-]: SELF      R11 R10 K34  ; R12 := R10; R11 := R10[0xc7bdb630]
108 [-]: CONST     R13 0        ; R13 := 0.000000
109 [-]: CALL      R11 3 1      ; R11(R12,R13)
110 [-]: GETGLOBAL R11 K14      ; R11 := 0x7b998233
111 [-]: MOVE      R12 R1       ; R12 := R1
112 [-]: CALL      R11 2 2      ; R11 := R11(R12)
113 [-]: TEST      R11 1        ; if R11 then PC := 144
114 [-]: JMP       144          ; PC := 144
115 [-]: SELF      R11 R1 K35   ; R12 := R1; R11 := R1[0x73901acf]
116 [-]: CALL      R11 2 2      ; R11 := R11(R12)
117 [-]: TEST      R11 1        ; if R11 then PC := 144
118 [-]: JMP       144          ; PC := 144
119 [-]: SELF      R11 R1 K36   ; R12 := R1; R11 := R1[0x2047cfe7]
120 [-]: CALL      R11 2 2      ; R11 := R11(R12)
121 [-]: TEST      R11 1        ; if R11 then PC := 144
122 [-]: JMP       144          ; PC := 144
123 [-]: GETGLOBAL R11 K14      ; R11 := 0x7b998233
124 [-]: SELF      R12 R1 K37   ; R13 := R1; R12 := R1[0x5e651723]
125 [-]: CALL      R12 2 0      ; R12,... := R12(R13)
126 [-]: CALL      R11 0 2      ; R11 := R11(R12,...)
127 [-]: TEST      R11 0        ; if not R11 then PC := 137
128 [-]: JMP       137          ; PC := 137
129 [-]: SELF      R11 R1 K38   ; R12 := R1; R11 := R1[0x5d985c7e]
130 [-]: GETGLOBAL R13 K39      ; R13 := 0x701f5e21
131 [-]: LOADKB    R14 1 0      ; R14 := true
132 [-]: CONST     R15 2        ; R15 := 2.000000
133 [-]: CONST     R16 1        ; R16 := 1.000000
134 [-]: LOADKB    R17 1 0      ; R17 := true
135 [-]: CALL      R11 7 1      ; R11(R12,R13,R14,R15,R16,R17)
136 [-]: JMP       144          ; PC := 144
137 [-]: SELF      R11 R1 K41   ; R12 := R1; R11 := R1[0x7027c544]
138 [-]: GETGLOBAL R13 K39      ; R13 := 0x701f5e21
139 [-]: LOADKB    R14 1 0      ; R14 := true
140 [-]: CONST     R15 2        ; R15 := 2.000000
141 [-]: CONST     R16 1        ; R16 := 1.000000
142 [-]: LOADKB    R17 1 0      ; R17 := true
143 [-]: CALL      R11 7 1      ; R11(R12,R13,R14,R15,R16,R17)
144 [-]: RETURN    R0 1         ; return 


; Function #15:
;
; Name:            
; Defined at line: 638
; #Upvalues:       2
; #Parameters:     2
; Is_vararg:       0
; Max Stack Size:  6

  1 [-]: GETGLOBAL R2 K0        ; R2 := 0x7b998233
  2 [-]: MOVE      R3 R1        ; R3 := R1
  3 [-]: CALL      R2 2 2       ; R2 := R2(R3)
  4 [-]: TEST      R2 1         ; if R2 then PC := 17
  5 [-]: JMP       17           ; PC := 17
  6 [-]: SELF      R2 R1 K1     ; R3 := R1; R2 := R1[0xdaddfb73]
  7 [-]: GETUPVAL  R4 U0        ; R4 := U0
  8 [-]: CALL      R2 3 2       ; R2 := R2(R3,R4)
  9 [-]: GETGLOBAL R3 K0        ; R3 := 0x7b998233
 10 [-]: MOVE      R4 R2        ; R4 := R2
 11 [-]: CALL      R3 2 2       ; R3 := R3(R4)
 12 [-]: TEST      R3 1         ; if R3 then PC := 17
 13 [-]: JMP       17           ; PC := 17
 14 [-]: SELF      R3 R2 K2     ; R4 := R2; R3 := R2[0x3a147087]
 15 [-]: GETUPVAL  R5 U1        ; R5 := U1
 16 [-]: CALL      R3 3 1       ; R3(R4,R5)
 17 [-]: RETURN    R0 1         ; return 


; Function #16:
;
; Name:            
; Defined at line: 647
; #Upvalues:       1
; #Parameters:     2
; Is_vararg:       0
; Max Stack Size:  8

  1 [-]: GETGLOBAL R2 K0        ; R2 := 0x7b998233
  2 [-]: MOVE      R3 R1        ; R3 := R1
  3 [-]: CALL      R2 2 2       ; R2 := R2(R3)
  4 [-]: TEST      R2 1         ; if R2 then PC := 23
  5 [-]: JMP       23           ; PC := 23
  6 [-]: SELF      R2 R1 K1     ; R3 := R1; R2 := R1[0xdaddfb73]
  7 [-]: GETUPVAL  R4 U0        ; R4 := U0
  8 [-]: CALL      R2 3 2       ; R2 := R2(R3,R4)
  9 [-]: GETGLOBAL R3 K0        ; R3 := 0x7b998233
 10 [-]: MOVE      R4 R2        ; R4 := R2
 11 [-]: CALL      R3 2 2       ; R3 := R3(R4)
 12 [-]: TEST      R3 1         ; if R3 then PC := 23
 13 [-]: JMP       23           ; PC := 23
 14 [-]: SELF      R3 R2 K2     ; R4 := R2; R3 := R2[0x3a147087]
 15 [-]: GETGLOBAL R5 K3        ; R5 := 0xb009bbc6
 16 [-]: SELF      R6 R2 K4     ; R7 := R2; R6 := R2[0xcde10c4a]
 17 [-]: CALL      R6 2 0       ; R6,... := R6(R7)
 18 [-]: CALL      R5 0 2       ; R5 := R5(R6,...)
 19 [-]: SELF      R5 R5 K5     ; R6 := R5; R5 := R5[0x7e627183]
 20 [-]: LOADKB    R7 0 0       ; R7 := false
 21 [-]: CALL      R5 3 0       ; R5,... := R5(R6,R7)
 22 [-]: CALL      R3 0 1       ; R3(R4,...)
 23 [-]: RETURN    R0 1         ; return 


