; This file has been disassembled using luadec 2.0.2 by sztupy (modified by Reversive)

; Name:            
; Defined at line: 0
; #Upvalues:       0
; #Parameters:     0
; Is_vararg:       2
; Max Stack Size:  23

  1 [-]: GETGLOBAL R0 K0        ; R0 := 0x0469f296
  2 [-]: LOADK     R1 K1        ; R1 := "WellOfLifeAtten"
  3 [-]: CALL      R0 2 2       ; R0 := R0(R1)
  4 [-]: GETGLOBAL R1 K2        ; R1 := 0x2d0fad09
  5 [-]: LOADK     R2 K3        ; R2 := "Lotus.Scripts.Libs.AbilitiesLib"
  6 [-]: CALL      R1 2 2       ; R1 := R1(R2)
  7 [-]: GETGLOBAL R2 K2        ; R2 := 0x2d0fad09
  8 [-]: LOADK     R3 K4        ; R3 := "Lotus.Powersuits.PowersuitAbilities.PVPLib"
  9 [-]: CALL      R2 2 2       ; R2 := R2(R3)
 10 [-]: GETGLOBAL R3 K0        ; R3 := 0x0469f296
 11 [-]: LOADK     R4 K5        ; R4 := "WellOfLifeII"
 12 [-]: CALL      R3 2 2       ; R3 := R3(R4)
 13 [-]: CONST     R4 1         ; R4 := 1.000000
 14 [-]: LOADK     R5 K6        ; R5 := 0.100000
 15 [-]: CONST     R6 100       ; R6 := 100.000000
 16 [-]: CONST     R7 7         ; R7 := 7.000000
 17 [-]: LOADK     R8 K7        ; R8 := 0.300000
 18 [-]: CONST     R9 5         ; R9 := 5.000000
 19 [-]: CONST     R10 25       ; R10 := 25.000000
 20 [-]: CONST     R11 1        ; R11 := 1.000000
 21 [-]: LOADK     R12 K6       ; R12 := 0.100000
 22 [-]: CLOSURE   R13 0        ; R13 := closure(Function #1)
 23 [-]: MOVE      R0 R2        ; R0 := R2
 24 [-]: MOVE      R0 R6        ; R0 := R6
 25 [-]: MOVE      R0 R7        ; R0 := R7
 26 [-]: MOVE      R0 R8        ; R0 := R8
 27 [-]: MOVE      R0 R9        ; R0 := R9
 28 [-]: MOVE      R0 R10       ; R0 := R10
 29 [-]: CLOSURE   R14 1        ; R14 := closure(Function #2)
 30 [-]: MOVE      R0 R6        ; R0 := R6
 31 [-]: MOVE      R0 R8        ; R0 := R8
 32 [-]: MOVE      R0 R7        ; R0 := R7
 33 [-]: MOVE      R0 R9        ; R0 := R9
 34 [-]: MOVE      R0 R10       ; R0 := R10
 35 [-]: CLOSURE   R15 2        ; R15 := closure(Function #3)
 36 [-]: MOVE      R0 R11       ; R0 := R11
 37 [-]: MOVE      R0 R12       ; R0 := R12
 38 [-]: CLOSURE   R16 3        ; R16 := closure(Function #4)
 39 [-]: MOVE      R0 R15       ; R0 := R15
 40 [-]: MOVE      R0 R11       ; R0 := R11
 41 [-]: MOVE      R0 R12       ; R0 := R12
 42 [-]: CLOSURE   R17 4        ; R17 := closure(Function #5)
 43 [-]: MOVE      R0 R13       ; R0 := R13
 44 [-]: MOVE      R0 R6        ; R0 := R6
 45 [-]: MOVE      R0 R8        ; R0 := R8
 46 [-]: MOVE      R0 R7        ; R0 := R7
 47 [-]: MOVE      R0 R9        ; R0 := R9
 48 [-]: MOVE      R0 R10       ; R0 := R10
 49 [-]: MOVE      R0 R14       ; R0 := R14
 50 [-]: MOVE      R0 R16       ; R0 := R16
 51 [-]: SETGLOBAL R17 K8       ; GetAbilityUpgradeLevelInfo := R17
 52 [-]: CLOSURE   R17 5        ; R17 := closure(Function #6)
 53 [-]: MOVE      R0 R15       ; R0 := R15
 54 [-]: MOVE      R0 R11       ; R0 := R11
 55 [-]: MOVE      R0 R12       ; R0 := R12
 56 [-]: SETGLOBAL R17 K9       ; GetAugmentDescriptionInfo := R17
 57 [-]: CLOSURE   R17 6        ; R17 := closure(Function #7)
 58 [-]: MOVE      R0 R3        ; R0 := R3
 59 [-]: CLOSURE   R18 7        ; R18 := closure(Function #8)
 60 [-]: MOVE      R0 R3        ; R0 := R3
 61 [-]: CLOSURE   R19 8        ; R19 := closure(Function #9)
 62 [-]: MOVE      R0 R13       ; R0 := R13
 63 [-]: MOVE      R0 R14       ; R0 := R14
 64 [-]: MOVE      R0 R2        ; R0 := R2
 65 [-]: CLOSURE   R20 9        ; R20 := closure(Function #10)
 66 [-]: MOVE      R0 R19       ; R0 := R19
 67 [-]: MOVE      R0 R2        ; R0 := R2
 68 [-]: SETGLOBAL R20 K10      ; EvaluateAbility := R20
 69 [-]: CLOSURE   R20 10       ; R20 := closure(Function #11)
 70 [-]: SETGLOBAL R20 K11      ; NpcEvaluateAbility := R20
 71 [-]: CLOSURE   R20 11       ; R20 := closure(Function #12)
 72 [-]: MOVE      R0 R2        ; R0 := R2
 73 [-]: SETGLOBAL R20 K12      ; InitializeAbility := R20
 74 [-]: CLOSURE   R20 12       ; R20 := closure(Function #13)
 75 [-]: CLOSURE   R21 13       ; R21 := closure(Function #14)
 76 [-]: MOVE      R0 R1        ; R0 := R1
 77 [-]: CLOSURE   R22 14       ; R22 := closure(Function #15)
 78 [-]: MOVE      R0 R13       ; R0 := R13
 79 [-]: MOVE      R0 R14       ; R0 := R14
 80 [-]: MOVE      R0 R1        ; R0 := R1
 81 [-]: MOVE      R0 R2        ; R0 := R2
 82 [-]: MOVE      R0 R17       ; R0 := R17
 83 [-]: MOVE      R0 R0        ; R0 := R0
 84 [-]: MOVE      R0 R21       ; R0 := R21
 85 [-]: SETGLOBAL R22 K13      ; ActivateAbility := R22
 86 [-]: CLOSURE   R22 15       ; R22 := closure(Function #16)
 87 [-]: MOVE      R0 R18       ; R0 := R18
 88 [-]: MOVE      R0 R15       ; R0 := R15
 89 [-]: MOVE      R0 R11       ; R0 := R11
 90 [-]: MOVE      R0 R20       ; R0 := R20
 91 [-]: MOVE      R0 R12       ; R0 := R12
 92 [-]: MOVE      R0 R1        ; R0 := R1
 93 [-]: MOVE      R0 R21       ; R0 := R21
 94 [-]: SETGLOBAL R22 K14      ; DeactivateAbility := R22
 95 [-]: CLOSURE   R22 16       ; R22 := closure(Function #17)
 96 [-]: MOVE      R0 R21       ; R0 := R21
 97 [-]: MOVE      R0 R1        ; R0 := R1
 98 [-]: MOVE      R0 R4        ; R0 := R4
 99 [-]: SETGLOBAL R22 K15      ; OnProcBlock := R22
100 [-]: CLOSURE   R22 17       ; R22 := closure(Function #18)
101 [-]: MOVE      R0 R5        ; R0 := R5
102 [-]: SETGLOBAL R22 K16      ; ProjHit := R22
103 [-]: RETURN    R0 1         ; return 


; Function #1:
;
; Name:            
; Defined at line: 30
; #Upvalues:       6
; #Parameters:     1
; Is_vararg:       0
; Max Stack Size:  2

  1 [-]: GETUPVAL  R1 U0        ; R1 := U0
  2 [-]: GETTABLE  R1 R1 K0     ; R1 := R1[0x32316a21]
  3 [-]: CALL      R1 1 2       ; R1 := R1()
  4 [-]: TEST      R1 1         ; if R1 then PC := 56
  5 [-]: JMP       56           ; PC := 56
  6 [-]: EQ        0 R0 K1      ; if R0 ~= 1.000000 then PC := 19
  7 [-]: JMP       19           ; PC := 19
  8 [-]: CONST     R1 100       ; R1 := 100.000000
  9 [-]: SETUPVAL  R1 U1        ; U82 := R1
 10 [-]: CONST     R1 7         ; R1 := 7.000000
 11 [-]: SETUPVAL  R1 U2        ; U82 := R2
 12 [-]: LOADK     R1 K2        ; R1 := 0.002500
 13 [-]: SETUPVAL  R1 U3        ; U82 := R3
 14 [-]: CONST     R1 15        ; R1 := 15.000000
 15 [-]: SETUPVAL  R1 U4        ; U82 := R4
 16 [-]: CONST     R1 25        ; R1 := 25.000000
 17 [-]: SETUPVAL  R1 U5        ; U82 := R5
 18 [-]: JMP       101          ; PC := 101
 19 [-]: EQ        0 R0 K3      ; if R0 ~= 2.000000 then PC := 32
 20 [-]: JMP       32           ; PC := 32
 21 [-]: CONST     R1 100       ; R1 := 100.000000
 22 [-]: SETUPVAL  R1 U1        ; U82 := R1
 23 [-]: CONST     R1 9         ; R1 := 9.000000
 24 [-]: SETUPVAL  R1 U2        ; U82 := R2
 25 [-]: LOADK     R1 K4        ; R1 := 0.005000
 26 [-]: SETUPVAL  R1 U3        ; U82 := R3
 27 [-]: CONST     R1 15        ; R1 := 15.000000
 28 [-]: SETUPVAL  R1 U4        ; U82 := R4
 29 [-]: CONST     R1 50        ; R1 := 50.000000
 30 [-]: SETUPVAL  R1 U5        ; U82 := R5
 31 [-]: JMP       101          ; PC := 101
 32 [-]: EQ        0 R0 K5      ; if R0 ~= 3.000000 then PC := 45
 33 [-]: JMP       45           ; PC := 45
 34 [-]: CONST     R1 100       ; R1 := 100.000000
 35 [-]: SETUPVAL  R1 U1        ; U82 := R1
 36 [-]: CONST     R1 10        ; R1 := 10.000000
 37 [-]: SETUPVAL  R1 U2        ; U82 := R2
 38 [-]: LOADK     R1 K6        ; R1 := 0.007500
 39 [-]: SETUPVAL  R1 U3        ; U82 := R3
 40 [-]: CONST     R1 15        ; R1 := 15.000000
 41 [-]: SETUPVAL  R1 U4        ; U82 := R4
 42 [-]: CONST     R1 75        ; R1 := 75.000000
 43 [-]: SETUPVAL  R1 U5        ; U82 := R5
 44 [-]: JMP       101          ; PC := 101
 45 [-]: CONST     R1 100       ; R1 := 100.000000
 46 [-]: SETUPVAL  R1 U1        ; U82 := R1
 47 [-]: CONST     R1 12        ; R1 := 12.000000
 48 [-]: SETUPVAL  R1 U2        ; U82 := R2
 49 [-]: LOADK     R1 K7        ; R1 := 0.010000
 50 [-]: SETUPVAL  R1 U3        ; U82 := R3
 51 [-]: CONST     R1 15        ; R1 := 15.000000
 52 [-]: SETUPVAL  R1 U4        ; U82 := R4
 53 [-]: CONST     R1 100       ; R1 := 100.000000
 54 [-]: SETUPVAL  R1 U5        ; U82 := R5
 55 [-]: JMP       101          ; PC := 101
 56 [-]: GETUPVAL  R1 U0        ; R1 := U0
 57 [-]: GETTABLE  R1 R1 K8     ; R1 := R1[0xe4ae0e66]
 58 [-]: CALL      R1 1 2       ; R1 := R1()
 59 [-]: TEST      R1 0         ; if not R1 then PC := 68
 60 [-]: JMP       68           ; PC := 68
 61 [-]: CONST     R1 10        ; R1 := 10.000000
 62 [-]: SETUPVAL  R1 U1        ; U82 := R1
 63 [-]: CONST     R1 20        ; R1 := 20.000000
 64 [-]: SETUPVAL  R1 U2        ; U82 := R2
 65 [-]: CONST     R1 1         ; R1 := 1.000000
 66 [-]: SETUPVAL  R1 U3        ; U82 := R3
 67 [-]: JMP       101          ; PC := 101
 68 [-]: EQ        0 R0 K1      ; if R0 ~= 1.000000 then PC := 77
 69 [-]: JMP       77           ; PC := 77
 70 [-]: CONST     R1 60        ; R1 := 60.000000
 71 [-]: SETUPVAL  R1 U1        ; U82 := R1
 72 [-]: CONST     R1 7         ; R1 := 7.000000
 73 [-]: SETUPVAL  R1 U2        ; U82 := R2
 74 [-]: LOADK     R1 K9        ; R1 := 0.120000
 75 [-]: SETUPVAL  R1 U3        ; U82 := R3
 76 [-]: JMP       101          ; PC := 101
 77 [-]: EQ        0 R0 K3      ; if R0 ~= 2.000000 then PC := 86
 78 [-]: JMP       86           ; PC := 86
 79 [-]: CONST     R1 60        ; R1 := 60.000000
 80 [-]: SETUPVAL  R1 U1        ; U82 := R1
 81 [-]: CONST     R1 8         ; R1 := 8.000000
 82 [-]: SETUPVAL  R1 U2        ; U82 := R2
 83 [-]: LOADK     R1 K10       ; R1 := 0.160000
 84 [-]: SETUPVAL  R1 U3        ; U82 := R3
 85 [-]: JMP       101          ; PC := 101
 86 [-]: EQ        0 R0 K5      ; if R0 ~= 3.000000 then PC := 95
 87 [-]: JMP       95           ; PC := 95
 88 [-]: CONST     R1 60        ; R1 := 60.000000
 89 [-]: SETUPVAL  R1 U1        ; U82 := R1
 90 [-]: CONST     R1 9         ; R1 := 9.000000
 91 [-]: SETUPVAL  R1 U2        ; U82 := R2
 92 [-]: LOADK     R1 K11       ; R1 := 0.180000
 93 [-]: SETUPVAL  R1 U3        ; U82 := R3
 94 [-]: JMP       101          ; PC := 101
 95 [-]: CONST     R1 60        ; R1 := 60.000000
 96 [-]: SETUPVAL  R1 U1        ; U82 := R1
 97 [-]: CONST     R1 10        ; R1 := 10.000000
 98 [-]: SETUPVAL  R1 U2        ; U82 := R2
 99 [-]: LOADK     R1 K12       ; R1 := 0.200000
100 [-]: SETUPVAL  R1 U3        ; U82 := R3
101 [-]: RETURN    R0 1         ; return 


; Function #2:
;
; Name:            
; Defined at line: 84
; #Upvalues:       5
; #Parameters:     1
; Is_vararg:       0
; Max Stack Size:  15

  1 [-]: GETUPVAL  R1 U0        ; R1 := U0
  2 [-]: GETUPVAL  R2 U1        ; R2 := U1
  3 [-]: GETUPVAL  R3 U2        ; R3 := U2
  4 [-]: GETUPVAL  R4 U3        ; R4 := U3
  5 [-]: GETUPVAL  R5 U4        ; R5 := U4
  6 [-]: GETGLOBAL R6 K0        ; R6 := 0x7b998233
  7 [-]: MOVE      R7 R0        ; R7 := R0
  8 [-]: CALL      R6 2 2       ; R6 := R6(R7)
  9 [-]: TEST      R6 1         ; if R6 then PC := 57
 10 [-]: JMP       57           ; PC := 57
 11 [-]: SELF      R6 R0 K1     ; R7 := R0; R6 := R0[0xde321e6f]
 12 [-]: CALL      R6 2 2       ; R6 := R6(R7)
 13 [-]: SELF      R7 R6 K2     ; R8 := R6; R7 := R6[0xf7d48ee0]
 14 [-]: CALL      R7 2 2       ; R7 := R7(R8)
 15 [-]: GETGLOBAL R8 K0        ; R8 := 0x7b998233
 16 [-]: MOVE      R9 R7        ; R9 := R7
 17 [-]: CALL      R8 2 2       ; R8 := R8(R9)
 18 [-]: TEST      R8 1         ; if R8 then PC := 57
 19 [-]: JMP       57           ; PC := 57
 20 [-]: SELF      R8 R7 K3     ; R9 := R7; R8 := R7[0xcde10c4a]
 21 [-]: CALL      R8 2 2       ; R8 := R8(R9)
 22 [-]: SELF      R9 R6 K4     ; R10 := R6; R9 := R6[0xe9f54086]
 23 [-]: GETUPVAL  R11 U0       ; R11 := U0
 24 [-]: CONST     R12 9        ; R12 := 9.000000
 25 [-]: MOVE      R13 R8       ; R13 := R8
 26 [-]: MOVE      R14 R7       ; R14 := R7
 27 [-]: CALL      R9 6 2       ; R9 := R9(R10,R11,R12,R13,R14)
 28 [-]: MOVE      R1 R9        ; R1 := R9
 29 [-]: SELF      R9 R6 K4     ; R10 := R6; R9 := R6[0xe9f54086]
 30 [-]: GETUPVAL  R11 U1       ; R11 := U1
 31 [-]: CONST     R12 10       ; R12 := 10.000000
 32 [-]: MOVE      R13 R8       ; R13 := R8
 33 [-]: MOVE      R14 R7       ; R14 := R7
 34 [-]: CALL      R9 6 2       ; R9 := R9(R10,R11,R12,R13,R14)
 35 [-]: MOVE      R2 R9        ; R2 := R9
 36 [-]: SELF      R9 R6 K4     ; R10 := R6; R9 := R6[0xe9f54086]
 37 [-]: GETUPVAL  R11 U2       ; R11 := U2
 38 [-]: CONST     R12 3        ; R12 := 3.000000
 39 [-]: MOVE      R13 R8       ; R13 := R8
 40 [-]: MOVE      R14 R7       ; R14 := R7
 41 [-]: CALL      R9 6 2       ; R9 := R9(R10,R11,R12,R13,R14)
 42 [-]: MOVE      R3 R9        ; R3 := R9
 43 [-]: SELF      R9 R6 K4     ; R10 := R6; R9 := R6[0xe9f54086]
 44 [-]: GETUPVAL  R11 U3       ; R11 := U3
 45 [-]: CONST     R12 9        ; R12 := 9.000000
 46 [-]: MOVE      R13 R8       ; R13 := R8
 47 [-]: MOVE      R14 R7       ; R14 := R7
 48 [-]: CALL      R9 6 2       ; R9 := R9(R10,R11,R12,R13,R14)
 49 [-]: MOVE      R4 R9        ; R4 := R9
 50 [-]: SELF      R9 R6 K4     ; R10 := R6; R9 := R6[0xe9f54086]
 51 [-]: GETUPVAL  R11 U4       ; R11 := U4
 52 [-]: CONST     R12 10       ; R12 := 10.000000
 53 [-]: MOVE      R13 R8       ; R13 := R8
 54 [-]: MOVE      R14 R7       ; R14 := R7
 55 [-]: CALL      R9 6 2       ; R9 := R9(R10,R11,R12,R13,R14)
 56 [-]: MOVE      R5 R9        ; R5 := R9
 57 [-]: MOVE      R9 R1        ; R9 := R1
 58 [-]: MOVE      R10 R2       ; R10 := R2
 59 [-]: MOVE      R11 R3       ; R11 := R3
 60 [-]: MOVE      R12 R4       ; R12 := R4
 61 [-]: MOVE      R13 R5       ; R13 := R5
 62 [-]: RETURN    R9 6         ; return R9,R10,R11,R12,R13
 63 [-]: RETURN    R0 1         ; return 


; Function #3:
;
; Name:            
; Defined at line: 107
; #Upvalues:       2
; #Parameters:     2
; Is_vararg:       0
; Max Stack Size:  3

  1 [-]: EQ        0 R1 K1      ; if R1 ~= 1.000000 then PC := 28
  2 [-]: JMP       28           ; PC := 28
  3 [-]: EQ        0 R0 K1      ; if R0 ~= 1.000000 then PC := 10
  4 [-]: JMP       10           ; PC := 10
  5 [-]: CONST     R2 1         ; R2 := 1.000000
  6 [-]: SETUPVAL  R2 U0        ; U82 := R0
  7 [-]: CONST     R2 1         ; R2 := 1.000000
  8 [-]: SETUPVAL  R2 U1        ; U82 := R1
  9 [-]: JMP       28           ; PC := 28
 10 [-]: EQ        0 R0 K2      ; if R0 ~= 2.000000 then PC := 17
 11 [-]: JMP       17           ; PC := 17
 12 [-]: CONST     R2 2         ; R2 := 2.000000
 13 [-]: SETUPVAL  R2 U0        ; U82 := R0
 14 [-]: CONST     R2 1         ; R2 := 1.000000
 15 [-]: SETUPVAL  R2 U1        ; U82 := R1
 16 [-]: JMP       28           ; PC := 28
 17 [-]: EQ        0 R0 K3      ; if R0 ~= 3.000000 then PC := 24
 18 [-]: JMP       24           ; PC := 24
 19 [-]: CONST     R2 3         ; R2 := 3.000000
 20 [-]: SETUPVAL  R2 U0        ; U82 := R0
 21 [-]: CONST     R2 1         ; R2 := 1.000000
 22 [-]: SETUPVAL  R2 U1        ; U82 := R1
 23 [-]: JMP       28           ; PC := 28
 24 [-]: CONST     R2 4         ; R2 := 4.000000
 25 [-]: SETUPVAL  R2 U0        ; U82 := R0
 26 [-]: CONST     R2 1         ; R2 := 1.000000
 27 [-]: SETUPVAL  R2 U1        ; U82 := R1
 28 [-]: RETURN    R0 1         ; return 


; Function #4:
;
; Name:            
; Defined at line: 125
; #Upvalues:       3
; #Parameters:     3
; Is_vararg:       0
; Max Stack Size:  13

  1 [-]: GETGLOBAL R3 K0        ; R3 := 0x7b998233
  2 [-]: MOVE      R4 R1        ; R4 := R1
  3 [-]: CALL      R3 2 2       ; R3 := R3(R4)
  4 [-]: TEST      R3 0         ; if not R3 then PC := 7
  5 [-]: JMP       7            ; PC := 7
  6 [-]: RETURN    R0 1         ; return 
  7 [-]: SELF      R3 R1 K1     ; R4 := R1; R3 := R1[0xde321e6f]
  8 [-]: CALL      R3 2 2       ; R3 := R3(R4)
  9 [-]: SELF      R4 R3 K2     ; R5 := R3; R4 := R3[0xf7d48ee0]
 10 [-]: CALL      R4 2 2       ; R4 := R4(R5)
 11 [-]: GETGLOBAL R5 K0        ; R5 := 0x7b998233
 12 [-]: MOVE      R6 R4        ; R6 := R4
 13 [-]: CALL      R5 2 2       ; R5 := R5(R6)
 14 [-]: TEST      R5 0         ; if not R5 then PC := 17
 15 [-]: JMP       17           ; PC := 17
 16 [-]: RETURN    R0 1         ; return 
 17 [-]: SELF      R5 R4 K3     ; R6 := R4; R5 := R4[0xa2356091]
 18 [-]: MOVE      R7 R2        ; R7 := R2
 19 [-]: CALL      R5 3 2       ; R5 := R5(R6,R7)
 20 [-]: SELF      R6 R4 K4     ; R7 := R4; R6 := R4[0xd836367c]
 21 [-]: CALL      R6 2 2       ; R6 := R6(R7)
 22 [-]: LE        0 R6 R5      ; if R6 > R5 then PC := 25
 23 [-]: JMP       25           ; PC := 25
 24 [-]: RETURN    R0 1         ; return 
 25 [-]: SELF      R6 R4 K5     ; R7 := R4; R6 := R4[0x5063edc3]
 26 [-]: MOVE      R8 R5        ; R8 := R5
 27 [-]: CALL      R6 3 2       ; R6 := R6(R7,R8)
 28 [-]: LE        0 R6 K6      ; if R6 > 0.000000 then PC := 31
 29 [-]: JMP       31           ; PC := 31
 30 [-]: RETURN    R0 1         ; return 
 31 [-]: SELF      R7 R4 K7     ; R8 := R4; R7 := R4[0x75ecaf0b]
 32 [-]: MOVE      R9 R5        ; R9 := R5
 33 [-]: CALL      R7 3 2       ; R7 := R7(R8,R9)
 34 [-]: GETUPVAL  R8 U0        ; R8 := U0
 35 [-]: MOVE      R9 R6        ; R9 := R6
 36 [-]: MOVE      R10 R7       ; R10 := R7
 37 [-]: CALL      R8 3 1       ; R8(R9,R10)
 38 [-]: EQ        0 R7 K9      ; if R7 ~= 1.000000 then PC := 68
 39 [-]: JMP       68           ; PC := 68
 40 [-]: GETGLOBAL R8 K10       ; R8 := 0x33bdd652
 41 [-]: GETTABLE  R8 R8 K11    ; R8 := R8[0x23d5322f]
 42 [-]: MOVE      R9 R0        ; R9 := R0
 43 [-]: NEWTABLE  R10 0 2      ; R10 := {}
 44 [-]: SETTABLE  R10 K12 K13  ; R10["Label"] := "/Lotus/Language/Suits/WellOfLifeAbilityAugment1Name"
 45 [-]: SETTABLE  R10 K14 K15  ; R10["Title"] := true
 46 [-]: CALL      R8 3 1       ; R8(R9,R10)
 47 [-]: GETGLOBAL R8 K10       ; R8 := 0x33bdd652
 48 [-]: GETTABLE  R8 R8 K11    ; R8 := R8[0x23d5322f]
 49 [-]: MOVE      R9 R0        ; R9 := R0
 50 [-]: NEWTABLE  R10 0 2      ; R10 := {}
 51 [-]: SETTABLE  R10 K12 K16  ; R10["Label"] := "/Lotus/Language/Game/HEALTH_ORB_DROP_NO_UNIT"
 52 [-]: GETUPVAL  R11 U1       ; R11 := U1
 53 [-]: SETTABLE  R10 K17 R11  ; R10["Value"] := R11
 54 [-]: CALL      R8 3 1       ; R8(R9,R10)
 55 [-]: GETGLOBAL R8 K10       ; R8 := 0x33bdd652
 56 [-]: GETTABLE  R8 R8 K11    ; R8 := R8[0x23d5322f]
 57 [-]: MOVE      R9 R0        ; R9 := R0
 58 [-]: NEWTABLE  R10 0 3      ; R10 := {}
 59 [-]: SETTABLE  R10 K12 K18  ; R10["Label"] := "/Lotus/Language/Game/ENERGY_ORB_DROP_NO_UNIT"
 60 [-]: GETGLOBAL R11 K19      ; R11 := 0x5bced4c4
 61 [-]: GETTABLE  R11 R11 K20  ; R11 := R11[0x55f27c30]
 62 [-]: GETUPVAL  R12 U2       ; R12 := U2
 63 [-]: MUL       R12 R12 K21  ; R12 := R12 * 100.000000
 64 [-]: CALL      R11 2 2      ; R11 := R11(R12)
 65 [-]: SETTABLE  R10 K17 R11  ; R10["Value"] := R11
 66 [-]: SETTABLE  R10 K22 K23  ; R10["ValueUnit"] := "/Lotus/Language/Game/UNIT_PERCENT"
 67 [-]: CALL      R8 3 1       ; R8(R9,R10)
 68 [-]: RETURN    R0 1         ; return 


; Function #5:
;
; Name:            
; Defined at line: 156
; #Upvalues:       8
; #Parameters:     0
; Is_vararg:       0
; Max Stack Size:  5

  1 [-]: GETUPVAL  R0 U0        ; R0 := U0
  2 [-]: GETGLOBAL R1 K0        ; R1 := _T
  3 [-]: GETTABLE  R1 R1 K1     ; R1 := R1["AbilityLevelQueryParms"]
  4 [-]: GETTABLE  R1 R1 K2     ; R1 := R1["Level"]
  5 [-]: CALL      R0 2 1       ; R0(R1)
  6 [-]: GETGLOBAL R0 K0        ; R0 := _T
  7 [-]: GETTABLE  R0 R0 K1     ; R0 := R0["AbilityLevelQueryParms"]
  8 [-]: GETTABLE  R0 R0 K3     ; R0 := R0["Modded"]
  9 [-]: EQ        0 R0 K4      ; if R0 ~= true then PC := 21
 10 [-]: JMP       21           ; PC := 21
 11 [-]: GETUPVAL  R0 U6        ; R0 := U6
 12 [-]: GETGLOBAL R1 K0        ; R1 := _T
 13 [-]: GETTABLE  R1 R1 K1     ; R1 := R1["AbilityLevelQueryParms"]
 14 [-]: GETTABLE  R1 R1 K5     ; R1 := R1["Avatar"]
 15 [-]: CALL      R0 2 6       ; R0,R1,R2,R3,R4 := R0(R1)
 16 [-]: SETUPVAL  R4 U5        ; U82 := R5
 17 [-]: SETUPVAL  R3 U4        ; U82 := R4
 18 [-]: SETUPVAL  R2 U3        ; U82 := R3
 19 [-]: SETUPVAL  R1 U2        ; U82 := R2
 20 [-]: SETUPVAL  R0 U1        ; U82 := R1
 21 [-]: NEWTABLE  R0 0 0       ; R0 := {}
 22 [-]: GETGLOBAL R1 K6        ; R1 := 0x33bdd652
 23 [-]: GETTABLE  R1 R1 K7     ; R1 := R1[0x23d5322f]
 24 [-]: MOVE      R2 R0        ; R2 := R0
 25 [-]: NEWTABLE  R3 0 3       ; R3 := {}
 26 [-]: SETTABLE  R3 K8 K9     ; R3["Label"] := "/Lotus/Language/Labels/WEAPON_RANGE"
 27 [-]: GETUPVAL  R4 U1        ; R4 := U1
 28 [-]: SETTABLE  R3 K10 R4    ; R3["Value"] := R4
 29 [-]: SETTABLE  R3 K11 K12   ; R3["ValueUnit"] := "/Lotus/Language/Game/UNIT_METER"
 30 [-]: CALL      R1 3 1       ; R1(R2,R3)
 31 [-]: GETGLOBAL R1 K6        ; R1 := 0x33bdd652
 32 [-]: GETTABLE  R1 R1 K7     ; R1 := R1[0x23d5322f]
 33 [-]: MOVE      R2 R0        ; R2 := R0
 34 [-]: NEWTABLE  R3 0 3       ; R3 := {}
 35 [-]: SETTABLE  R3 K8 K13    ; R3["Label"] := "/Lotus/Language/Menu/DURATION"
 36 [-]: GETUPVAL  R4 U3        ; R4 := U3
 37 [-]: SETTABLE  R3 K10 R4    ; R3["Value"] := R4
 38 [-]: SETTABLE  R3 K11 K14   ; R3["ValueUnit"] := "/Lotus/Language/Game/UNIT_SECOND"
 39 [-]: CALL      R1 3 1       ; R1(R2,R3)
 40 [-]: GETGLOBAL R1 K6        ; R1 := 0x33bdd652
 41 [-]: GETTABLE  R1 R1 K7     ; R1 := R1[0x23d5322f]
 42 [-]: MOVE      R2 R0        ; R2 := R0
 43 [-]: NEWTABLE  R3 0 3       ; R3 := {}
 44 [-]: SETTABLE  R3 K8 K15    ; R3["Label"] := "/Lotus/Language/Game/ABILITY_RADIUS"
 45 [-]: GETUPVAL  R4 U4        ; R4 := U4
 46 [-]: SETTABLE  R3 K10 R4    ; R3["Value"] := R4
 47 [-]: SETTABLE  R3 K11 K12   ; R3["ValueUnit"] := "/Lotus/Language/Game/UNIT_METER"
 48 [-]: CALL      R1 3 1       ; R1(R2,R3)
 49 [-]: GETGLOBAL R1 K6        ; R1 := 0x33bdd652
 50 [-]: GETTABLE  R1 R1 K7     ; R1 := R1[0x23d5322f]
 51 [-]: MOVE      R2 R0        ; R2 := R0
 52 [-]: NEWTABLE  R3 0 2       ; R3 := {}
 53 [-]: SETTABLE  R3 K8 K16    ; R3["Label"] := "/Lotus/Language/Game/HEALTH_PER_SEC"
 54 [-]: GETUPVAL  R4 U5        ; R4 := U5
 55 [-]: SETTABLE  R3 K10 R4    ; R3["Value"] := R4
 56 [-]: CALL      R1 3 1       ; R1(R2,R3)
 57 [-]: GETGLOBAL R1 K6        ; R1 := 0x33bdd652
 58 [-]: GETTABLE  R1 R1 K7     ; R1 := R1[0x23d5322f]
 59 [-]: MOVE      R2 R0        ; R2 := R0
 60 [-]: NEWTABLE  R3 0 3       ; R3 := {}
 61 [-]: SETTABLE  R3 K8 K17    ; R3["Label"] := "/Lotus/Language/Labels/WEAPON_LIFE_STEAL"
 62 [-]: GETUPVAL  R4 U2        ; R4 := U2
 63 [-]: MUL       R4 K18 R4    ; R4 := 100.000000 * R4
 64 [-]: SETTABLE  R3 K10 R4    ; R3["Value"] := R4
 65 [-]: SETTABLE  R3 K11 K19   ; R3["ValueUnit"] := "/Lotus/Language/Game/UNIT_PERCENT"
 66 [-]: CALL      R1 3 1       ; R1(R2,R3)
 67 [-]: GETUPVAL  R1 U7        ; R1 := U7
 68 [-]: MOVE      R2 R0        ; R2 := R0
 69 [-]: GETGLOBAL R3 K0        ; R3 := _T
 70 [-]: GETTABLE  R3 R3 K1     ; R3 := R3["AbilityLevelQueryParms"]
 71 [-]: GETTABLE  R3 R3 K5     ; R3 := R3["Avatar"]
 72 [-]: GETGLOBAL R4 K0        ; R4 := _T
 73 [-]: GETTABLE  R4 R4 K1     ; R4 := R4["AbilityLevelQueryParms"]
 74 [-]: GETTABLE  R4 R4 K20    ; R4 := R4["Ability"]
 75 [-]: CALL      R1 4 1       ; R1(R2,R3,R4)
 76 [-]: GETGLOBAL R1 K0        ; R1 := _T
 77 [-]: GETTABLE  R1 R1 K1     ; R1 := R1["AbilityLevelQueryParms"]
 78 [-]: GETTABLE  R1 R1 K3     ; R1 := R1["Modded"]
 79 [-]: SETTABLE  R0 K3 R1     ; R0["Modded"] := R1
 80 [-]: GETGLOBAL R1 K0        ; R1 := _T
 81 [-]: SETTABLE  R1 K21 R0    ; R1["AbilityUpgradeLevelInfo"] := R0
 82 [-]: RETURN    R0 1         ; return 


; Function #6:
;
; Name:            
; Defined at line: 176
; #Upvalues:       3
; #Parameters:     2
; Is_vararg:       0
; Max Stack Size:  6

  1 [-]: NEWTABLE  R2 0 0       ; R2 := {}
  2 [-]: GETUPVAL  R3 U0        ; R3 := U0
  3 [-]: MOVE      R4 R0        ; R4 := R0
  4 [-]: MOVE      R5 R1        ; R5 := R1
  5 [-]: CALL      R3 3 1       ; R3(R4,R5)
  6 [-]: EQ        0 R1 K1      ; if R1 ~= 1.000000 then PC := 18
  7 [-]: JMP       18           ; PC := 18
  8 [-]: NEWTABLE  R3 0 2       ; R3 := {}
  9 [-]: GETUPVAL  R4 U1        ; R4 := U1
 10 [-]: SETTABLE  R3 K2 R4     ; R3["HEALTH_ORBS"] := R4
 11 [-]: GETGLOBAL R4 K4        ; R4 := 0x5bced4c4
 12 [-]: GETTABLE  R4 R4 K5     ; R4 := R4[0x55f27c30]
 13 [-]: GETUPVAL  R5 U2        ; R5 := U2
 14 [-]: MUL       R5 R5 K6     ; R5 := R5 * 100.000000
 15 [-]: CALL      R4 2 2       ; R4 := R4(R5)
 16 [-]: SETTABLE  R3 K3 R4     ; R3["ENERGY_ORB_CHANCE"] := R4
 17 [-]: MOVE      R2 R3        ; R2 := R3
 18 [-]: GETGLOBAL R3 K7        ; R3 := cjson
 19 [-]: GETTABLE  R3 R3 K8     ; R3 := R3[0xb139d7bc]
 20 [-]: MOVE      R4 R2        ; R4 := R2
 21 [-]: TAILCALL  R3 2 0       ; R3,... := R3(R4)
 22 [-]: RETURN    R3 0         ; return R3,...
 23 [-]: RETURN    R0 1         ; return 


; Function #7:
;
; Name:            
; Defined at line: 191
; #Upvalues:       1
; #Parameters:     1
; Is_vararg:       0
; Max Stack Size:  9

  1 [-]: GETGLOBAL R1 K0        ; R1 := 0x7b998233
  2 [-]: MOVE      R2 R0        ; R2 := R0
  3 [-]: CALL      R1 2 2       ; R1 := R1(R2)
  4 [-]: TEST      R1 1         ; if R1 then PC := 35
  5 [-]: JMP       35           ; PC := 35
  6 [-]: SELF      R1 R0 K1     ; R2 := R0; R1 := R0[0x1ac1655c]
  7 [-]: CALL      R1 2 2       ; R1 := R1(R2)
  8 [-]: SELF      R2 R1 K2     ; R3 := R1; R2 := R1[0xaa0faa2c]
  9 [-]: CONST     R4 5         ; R4 := 5.000000
 10 [-]: GETUPVAL  R5 U0        ; R5 := U0
 11 [-]: CALL      R2 4 1       ; R2(R3,R4,R5)
 12 [-]: SELF      R2 R1 K2     ; R3 := R1; R2 := R1[0xaa0faa2c]
 13 [-]: CONST     R4 6         ; R4 := 6.000000
 14 [-]: GETUPVAL  R5 U0        ; R5 := U0
 15 [-]: CALL      R2 4 1       ; R2(R3,R4,R5)
 16 [-]: SELF      R2 R1 K2     ; R3 := R1; R2 := R1[0xaa0faa2c]
 17 [-]: CONST     R4 3         ; R4 := 3.000000
 18 [-]: GETUPVAL  R5 U0        ; R5 := U0
 19 [-]: CALL      R2 4 1       ; R2(R3,R4,R5)
 20 [-]: SELF      R2 R1 K2     ; R3 := R1; R2 := R1[0xaa0faa2c]
 21 [-]: CONST     R4 4         ; R4 := 4.000000
 22 [-]: GETUPVAL  R5 U0        ; R5 := U0
 23 [-]: CALL      R2 4 1       ; R2(R3,R4,R5)
 24 [-]: SELF      R2 R1 K2     ; R3 := R1; R2 := R1[0xaa0faa2c]
 25 [-]: CONST     R4 9         ; R4 := 9.000000
 26 [-]: GETUPVAL  R5 U0        ; R5 := U0
 27 [-]: CALL      R2 4 1       ; R2(R3,R4,R5)
 28 [-]: SELF      R2 R1 K4     ; R3 := R1; R2 := R1[0xeb3c14da]
 29 [-]: GETUPVAL  R4 U0        ; R4 := U0
 30 [-]: CONST     R5 25        ; R5 := 25.000000
 31 [-]: CONST     R6 6         ; R6 := 6.000000
 32 [-]: CONST     R7 0         ; R7 := 0.000000
 33 [-]: CONST     R8 0         ; R8 := 0.000000
 34 [-]: CALL      R2 7 1       ; R2(R3,R4,R5,R6,R7,R8)
 35 [-]: RETURN    R0 1         ; return 


; Function #8:
;
; Name:            
; Defined at line: 203
; #Upvalues:       1
; #Parameters:     1
; Is_vararg:       0
; Max Stack Size:  6

  1 [-]: GETGLOBAL R1 K0        ; R1 := 0x7b998233
  2 [-]: MOVE      R2 R0        ; R2 := R0
  3 [-]: CALL      R1 2 2       ; R1 := R1(R2)
  4 [-]: TEST      R1 1         ; if R1 then PC := 31
  5 [-]: JMP       31           ; PC := 31
  6 [-]: SELF      R1 R0 K1     ; R2 := R0; R1 := R0[0x1ac1655c]
  7 [-]: CALL      R1 2 2       ; R1 := R1(R2)
  8 [-]: SELF      R2 R1 K2     ; R3 := R1; R2 := R1[0x0f68c2b7]
  9 [-]: CONST     R4 5         ; R4 := 5.000000
 10 [-]: GETUPVAL  R5 U0        ; R5 := U0
 11 [-]: CALL      R2 4 1       ; R2(R3,R4,R5)
 12 [-]: SELF      R2 R1 K2     ; R3 := R1; R2 := R1[0x0f68c2b7]
 13 [-]: CONST     R4 6         ; R4 := 6.000000
 14 [-]: GETUPVAL  R5 U0        ; R5 := U0
 15 [-]: CALL      R2 4 1       ; R2(R3,R4,R5)
 16 [-]: SELF      R2 R1 K2     ; R3 := R1; R2 := R1[0x0f68c2b7]
 17 [-]: CONST     R4 3         ; R4 := 3.000000
 18 [-]: GETUPVAL  R5 U0        ; R5 := U0
 19 [-]: CALL      R2 4 1       ; R2(R3,R4,R5)
 20 [-]: SELF      R2 R1 K2     ; R3 := R1; R2 := R1[0x0f68c2b7]
 21 [-]: CONST     R4 4         ; R4 := 4.000000
 22 [-]: GETUPVAL  R5 U0        ; R5 := U0
 23 [-]: CALL      R2 4 1       ; R2(R3,R4,R5)
 24 [-]: SELF      R2 R1 K2     ; R3 := R1; R2 := R1[0x0f68c2b7]
 25 [-]: CONST     R4 9         ; R4 := 9.000000
 26 [-]: GETUPVAL  R5 U0        ; R5 := U0
 27 [-]: CALL      R2 4 1       ; R2(R3,R4,R5)
 28 [-]: SELF      R2 R1 K4     ; R3 := R1; R2 := R1[0x55481e0d]
 29 [-]: GETUPVAL  R4 U0        ; R4 := U0
 30 [-]: CALL      R2 3 1       ; R2(R3,R4)
 31 [-]: RETURN    R0 1         ; return 


; Function #9:
;
; Name:            
; Defined at line: 215
; #Upvalues:       3
; #Parameters:     3
; Is_vararg:       0
; Max Stack Size:  16

  1 [-]: SELF      R3 R0 K0     ; R4 := R0; R3 := R0[0xde321e6f]
  2 [-]: CALL      R3 2 2       ; R3 := R3(R4)
  3 [-]: SELF      R4 R3 K1     ; R5 := R3; R4 := R3[0x7c09e541]
  4 [-]: CALL      R4 2 2       ; R4 := R4(R5)
  5 [-]: GETUPVAL  R5 U0        ; R5 := U0
  6 [-]: MOVE      R6 R1        ; R6 := R1
  7 [-]: CALL      R5 2 1       ; R5(R6)
  8 [-]: GETUPVAL  R5 U1        ; R5 := U1
  9 [-]: MOVE      R6 R0        ; R6 := R0
 10 [-]: CALL      R5 2 2       ; R5 := R5(R6)
 11 [-]: GETGLOBAL R6 K2        ; R6 := 0x7b998233
 12 [-]: SELF      R7 R0 K3     ; R8 := R0; R7 := R0[0xfa9e477f]
 13 [-]: CALL      R7 2 0       ; R7,... := R7(R8)
 14 [-]: CALL      R6 0 2       ; R6 := R6(R7,...)
 15 [-]: TEST      R6 1         ; if R6 then PC := 31
 16 [-]: JMP       31           ; PC := 31
 17 [-]: SELF      R6 R0 K3     ; R7 := R0; R6 := R0[0xfa9e477f]
 18 [-]: CALL      R6 2 2       ; R6 := R6(R7)
 19 [-]: SELF      R6 R6 K4     ; R7 := R6; R6 := R6[0xa39bb54b]
 20 [-]: CALL      R6 2 2       ; R6 := R6(R7)
 21 [-]: GETTABLE  R7 R6 K5     ; R7 := R6["visible"]
 22 [-]: TEST      R7 0         ; if not R7 then PC := 75
 23 [-]: JMP       75           ; PC := 75
 24 [-]: GETGLOBAL R7 K2        ; R7 := 0x7b998233
 25 [-]: GETTABLE  R8 R6 K6     ; R8 := R6["entity"]
 26 [-]: CALL      R7 2 2       ; R7 := R7(R8)
 27 [-]: TEST      R7 1         ; if R7 then PC := 75
 28 [-]: JMP       75           ; PC := 75
 29 [-]: GETTABLE  R4 R6 K6     ; R4 := R6["entity"]
 30 [-]: JMP       75           ; PC := 75
 31 [-]: GETGLOBAL R7 K2        ; R7 := 0x7b998233
 32 [-]: MOVE      R8 R4        ; R8 := R4
 33 [-]: CALL      R7 2 2       ; R7 := R7(R8)
 34 [-]: TEST      R7 1         ; if R7 then PC := 41
 35 [-]: JMP       41           ; PC := 41
 36 [-]: SELF      R7 R4 K7     ; R8 := R4; R7 := R4[0xf2deaf69]
 37 [-]: GETGLOBAL R9 K8        ; R9 := gBaseAvatarType
 38 [-]: CALL      R7 3 2       ; R7 := R7(R8,R9)
 39 [-]: TEST      R7 1         ; if R7 then PC := 75
 40 [-]: JMP       75           ; PC := 75
 41 [-]: LOADNIL   R7 R7        ; R7 := nil
 42 [-]: GETUPVAL  R8 U2        ; R8 := U2
 43 [-]: GETTABLE  R8 R8 K9     ; R8 := R8[0x32316a21]
 44 [-]: CALL      R8 1 2       ; R8 := R8()
 45 [-]: TEST      R8 0         ; if not R8 then PC := 61
 46 [-]: JMP       61           ; PC := 61
 47 [-]: SELF      R8 R0 K10    ; R9 := R0; R8 := R0[0x80846b00]
 48 [-]: CONST     R10 1        ; R10 := 1.000000
 49 [-]: MOVE      R11 R5       ; R11 := R5
 50 [-]: GETUPVAL  R12 U2       ; R12 := U2
 51 [-]: GETTABLE  R12 R12 K11  ; R12 := R12[0xfbdcfe72]
 52 [-]: GETGLOBAL R13 K12      ; R13 := 0x19849b93
 53 [-]: MOVE      R14 R0       ; R14 := R0
 54 [-]: MOVE      R15 R2       ; R15 := R2
 55 [-]: CALL      R12 4 2      ; R12 := R12(R13,R14,R15)
 56 [-]: LOADKB    R13 0 0      ; R13 := false
 57 [-]: LOADKB    R14 1 0      ; R14 := true
 58 [-]: CALL      R8 7 2       ; R8 := R8(R9,R10,R11,R12,R13,R14)
 59 [-]: MOVE      R7 R8        ; R7 := R8
 60 [-]: JMP       69           ; PC := 69
 61 [-]: SELF      R8 R0 K10    ; R9 := R0; R8 := R0[0x80846b00]
 62 [-]: CONST     R10 1        ; R10 := 1.000000
 63 [-]: MOVE      R11 R5       ; R11 := R5
 64 [-]: CONST     R12 1        ; R12 := 1.000000
 65 [-]: LOADKB    R13 0 0      ; R13 := false
 66 [-]: LOADKB    R14 1 0      ; R14 := true
 67 [-]: CALL      R8 7 2       ; R8 := R8(R9,R10,R11,R12,R13,R14)
 68 [-]: MOVE      R7 R8        ; R7 := R8
 69 [-]: GETGLOBAL R8 K2        ; R8 := 0x7b998233
 70 [-]: MOVE      R9 R7        ; R9 := R7
 71 [-]: CALL      R8 2 2       ; R8 := R8(R9)
 72 [-]: TEST      R8 1         ; if R8 then PC := 75
 73 [-]: JMP       75           ; PC := 75
 74 [-]: GETTABLE  R4 R7 K13    ; R4 := R7[1.000000]
 75 [-]: GETGLOBAL R8 K2        ; R8 := 0x7b998233
 76 [-]: MOVE      R9 R4        ; R9 := R4
 77 [-]: CALL      R8 2 2       ; R8 := R8(R9)
 78 [-]: TEST      R8 1         ; if R8 then PC := 94
 79 [-]: JMP       94           ; PC := 94
 80 [-]: SELF      R8 R4 K7     ; R9 := R4; R8 := R4[0xf2deaf69]
 81 [-]: GETGLOBAL R10 K8       ; R10 := gBaseAvatarType
 82 [-]: CALL      R8 3 2       ; R8 := R8(R9,R10)
 83 [-]: TEST      R8 0         ; if not R8 then PC := 94
 84 [-]: JMP       94           ; PC := 94
 85 [-]: SELF      R8 R4 K14    ; R9 := R4; R8 := R4[0x2047cfe7]
 86 [-]: CALL      R8 2 2       ; R8 := R8(R9)
 87 [-]: TEST      R8 1         ; if R8 then PC := 94
 88 [-]: JMP       94           ; PC := 94
 89 [-]: SELF      R8 R4 K15    ; R9 := R4; R8 := R4[0xc4dff581]
 90 [-]: CONST     R10 4        ; R10 := 4.000000
 91 [-]: CALL      R8 3 2       ; R8 := R8(R9,R10)
 92 [-]: TEST      R8 0         ; if not R8 then PC := 99
 93 [-]: JMP       99           ; PC := 99
 94 [-]: LOADNIL   R8 R8        ; R8 := nil
 95 [-]: GETGLOBAL R9 K17       ; R9 := 0x0469f296
 96 [-]: LOADK     R10 K18      ; R10 := "/Lotus/Language/Game/AbilityErrorInvalidTarget"
 97 [-]: CALL      R9 2 0       ; R9,... := R9(R10)
 98 [-]: RETURN    R8 0         ; return R8,...
 99 [-]: SELF      R8 R4 K19    ; R9 := R4; R8 := R4[0xbebad19f]
100 [-]: MOVE      R10 R0       ; R10 := R0
101 [-]: CALL      R8 3 2       ; R8 := R8(R9,R10)
102 [-]: LT        0 R5 R8      ; if R5 >= R8 then PC := 109
103 [-]: JMP       109          ; PC := 109
104 [-]: LOADNIL   R9 R9        ; R9 := nil
105 [-]: GETGLOBAL R10 K17      ; R10 := 0x0469f296
106 [-]: LOADK     R11 K20      ; R11 := "/Lotus/Language/Game/AbilityErrorOutOfRange"
107 [-]: CALL      R10 2 0      ; R10,... := R10(R11)
108 [-]: RETURN    R9 0         ; return R9,...
109 [-]: GETUPVAL  R9 U2        ; R9 := U2
110 [-]: GETTABLE  R9 R9 K9     ; R9 := R9[0x32316a21]
111 [-]: CALL      R9 1 2       ; R9 := R9()
112 [-]: TEST      R9 0         ; if not R9 then PC := 122
113 [-]: JMP       122          ; PC := 122
114 [-]: GETUPVAL  R9 U2        ; R9 := U2
115 [-]: GETTABLE  R9 R9 K21    ; R9 := R9[0xfabc505b]
116 [-]: MOVE      R10 R0       ; R10 := R0
117 [-]: MOVE      R11 R4       ; R11 := R4
118 [-]: CALL      R9 3 2       ; R9 := R9(R10,R11)
119 [-]: TEST      R9 0         ; if not R9 then PC := 122
120 [-]: JMP       122          ; PC := 122
121 [-]: RETURN    R4 2         ; return R4
122 [-]: SELF      R9 R4 K22    ; R10 := R4; R9 := R4[0xee0bc178]
123 [-]: MOVE      R11 R0       ; R11 := R0
124 [-]: CALL      R9 3 2       ; R9 := R9(R10,R11)
125 [-]: TEST      R9 0         ; if not R9 then PC := 132
126 [-]: JMP       132          ; PC := 132
127 [-]: LOADNIL   R9 R9        ; R9 := nil
128 [-]: GETGLOBAL R10 K17      ; R10 := 0x0469f296
129 [-]: LOADK     R11 K18      ; R11 := "/Lotus/Language/Game/AbilityErrorInvalidTarget"
130 [-]: CALL      R10 2 0      ; R10,... := R10(R11)
131 [-]: RETURN    R9 0         ; return R9,...
132 [-]: GETGLOBAL R9 K2        ; R9 := 0x7b998233
133 [-]: SELF      R10 R4 K23   ; R11 := R4; R10 := R4[0x5e651723]
134 [-]: CALL      R10 2 0      ; R10,... := R10(R11)
135 [-]: CALL      R9 0 2       ; R9 := R9(R10,...)
136 [-]: TEST      R9 1         ; if R9 then PC := 143
137 [-]: JMP       143          ; PC := 143
138 [-]: LOADNIL   R9 R9        ; R9 := nil
139 [-]: GETGLOBAL R10 K17      ; R10 := 0x0469f296
140 [-]: LOADK     R11 K18      ; R11 := "/Lotus/Language/Game/AbilityErrorInvalidTarget"
141 [-]: CALL      R10 2 0      ; R10,... := R10(R11)
142 [-]: RETURN    R9 0         ; return R9,...
143 [-]: SELF      R9 R4 K24    ; R10 := R4; R9 := R4[0x1ac1655c]
144 [-]: CALL      R9 2 2       ; R9 := R9(R10)
145 [-]: SELF      R9 R9 K25    ; R10 := R9; R9 := R9[0x68d1b91d]
146 [-]: CALL      R9 2 2       ; R9 := R9(R10)
147 [-]: TEST      R9 0         ; if not R9 then PC := 154
148 [-]: JMP       154          ; PC := 154
149 [-]: LOADNIL   R9 R9        ; R9 := nil
150 [-]: GETGLOBAL R10 K17      ; R10 := 0x0469f296
151 [-]: LOADK     R11 K18      ; R11 := "/Lotus/Language/Game/AbilityErrorInvalidTarget"
152 [-]: CALL      R10 2 0      ; R10,... := R10(R11)
153 [-]: RETURN    R9 0         ; return R9,...
154 [-]: RETURN    R4 2         ; return R4
155 [-]: RETURN    R0 1         ; return 


; Function #10:
;
; Name:            
; Defined at line: 279
; #Upvalues:       2
; #Parameters:     3
; Is_vararg:       0
; Max Stack Size:  11

  1 [-]: GETUPVAL  R3 U0        ; R3 := U0
  2 [-]: MOVE      R4 R1        ; R4 := R1
  3 [-]: MOVE      R5 R2        ; R5 := R2
  4 [-]: MOVE      R6 R0        ; R6 := R0
  5 [-]: CALL      R3 4 3       ; R3,R4 := R3(R4,R5,R6)
  6 [-]: EQ        0 R3 K0      ; if R3 ~= nil then PC := 28
  7 [-]: JMP       28           ; PC := 28
  8 [-]: GETUPVAL  R5 U1        ; R5 := U1
  9 [-]: GETTABLE  R5 R5 K1     ; R5 := R5[0x32316a21]
 10 [-]: CALL      R5 1 2       ; R5 := R5()
 11 [-]: TEST      R5 0         ; if not R5 then PC := 16
 12 [-]: JMP       16           ; PC := 16
 13 [-]: LOADKB    R5 1 0       ; R5 := true
 14 [-]: RETURN    R5 2         ; return R5
 15 [-]: JMP       33           ; PC := 33
 16 [-]: SELF      R5 R1 K2     ; R6 := R1; R5 := R1[0x659d451f]
 17 [-]: GETGLOBAL R7 K3        ; R7 := 0xe144cbfd
 18 [-]: LOADKB    R8 0 0       ; R8 := false
 19 [-]: CONST     R9 0         ; R9 := 0.000000
 20 [-]: LOADKB    R10 0 0      ; R10 := false
 21 [-]: CALL      R5 6 1       ; R5(R6,R7,R8,R9,R10)
 22 [-]: SELF      R5 R1 K4     ; R6 := R1; R5 := R1[0xd7091d77]
 23 [-]: MOVE      R7 R4        ; R7 := R4
 24 [-]: CALL      R5 3 1       ; R5(R6,R7)
 25 [-]: LOADKB    R5 0 0       ; R5 := false
 26 [-]: RETURN    R5 2         ; return R5
 27 [-]: JMP       33           ; PC := 33
 28 [-]: SELF      R5 R0 K5     ; R6 := R0; R5 := R0[0x48d05257]
 29 [-]: MOVE      R7 R3        ; R7 := R3
 30 [-]: CALL      R5 3 1       ; R5(R6,R7)
 31 [-]: LOADKB    R5 1 0       ; R5 := true
 32 [-]: RETURN    R5 2         ; return R5
 33 [-]: RETURN    R0 1         ; return 


; Function #11:
;
; Name:            
; Defined at line: 297
; #Upvalues:       0
; #Parameters:     2
; Is_vararg:       0
; Max Stack Size:  11

  1 [-]: SELF      R2 R1 K0     ; R3 := R1; R2 := R1[0xd4f67d6e]
  2 [-]: CALL      R2 2 2       ; R2 := R2(R3)
  3 [-]: GETGLOBAL R3 K1        ; R3 := 0x7b998233
  4 [-]: MOVE      R4 R2        ; R4 := R2
  5 [-]: CALL      R3 2 2       ; R3 := R3(R4)
  6 [-]: TEST      R3 1         ; if R3 then PC := 20
  7 [-]: JMP       20           ; PC := 20
  8 [-]: SELF      R3 R2 K2     ; R4 := R2; R3 := R2[0x1ac1655c]
  9 [-]: CALL      R3 2 2       ; R3 := R3(R4)
 10 [-]: SELF      R3 R3 K3     ; R4 := R3; R3 := R3[0xd29b845d]
 11 [-]: CALL      R3 2 2       ; R3 := R3(R4)
 12 [-]: SELF      R4 R2 K4     ; R5 := R2; R4 := R2[0xc8442850]
 13 [-]: CALL      R4 2 2       ; R4 := R4(R5)
 14 [-]: LT        1 R3 K5      ; if R3 < 0.500000 then PC := 18
 15 [-]: JMP       18           ; PC := 18
 16 [-]: LT        0 R4 K6      ; if R4 >= 0.800000 then PC := 20
 17 [-]: JMP       20           ; PC := 20
 18 [-]: LOADK     R5 K6        ; R5 := 0.800000
 19 [-]: RETURN    R5 2         ; return R5
 20 [-]: SELF      R5 R1 K2     ; R6 := R1; R5 := R1[0x1ac1655c]
 21 [-]: CALL      R5 2 2       ; R5 := R5(R6)
 22 [-]: SELF      R5 R5 K3     ; R6 := R5; R5 := R5[0xd29b845d]
 23 [-]: CALL      R5 2 2       ; R5 := R5(R6)
 24 [-]: SELF      R6 R1 K4     ; R7 := R1; R6 := R1[0xc8442850]
 25 [-]: CALL      R6 2 2       ; R6 := R6(R7)
 26 [-]: LT        1 K7 R5      ; if 0.250000 < R5 then PC := 30
 27 [-]: JMP       30           ; PC := 30
 28 [-]: LT        0 K5 R6      ; if 0.500000 >= R6 then PC := 32
 29 [-]: JMP       32           ; PC := 32
 30 [-]: CONST     R7 0         ; R7 := 0.000000
 31 [-]: RETURN    R7 2         ; return R7
 32 [-]: SELF      R7 R1 K8     ; R8 := R1; R7 := R1[0xfa9e477f]
 33 [-]: CALL      R7 2 2       ; R7 := R7(R8)
 34 [-]: SELF      R7 R7 K9     ; R8 := R7; R7 := R7[0xa39bb54b]
 35 [-]: CALL      R7 2 2       ; R7 := R7(R8)
 36 [-]: GETTABLE  R8 R7 K10    ; R8 := R7["visible"]
 37 [-]: TEST      R8 0         ; if not R8 then PC := 48
 38 [-]: JMP       48           ; PC := 48
 39 [-]: SELF      R8 R7 K11    ; R9 := R7; R8 := R7[0x37e4785a]
 40 [-]: CALL      R8 2 2       ; R8 := R8(R9)
 41 [-]: TEST      R8 0         ; if not R8 then PC := 48
 42 [-]: JMP       48           ; PC := 48
 43 [-]: SELF      R8 R0 K12    ; R9 := R0; R8 := R0[0x48d05257]
 44 [-]: GETTABLE  R10 R7 K13   ; R10 := R7["avatar"]
 45 [-]: CALL      R8 3 1       ; R8(R9,R10)
 46 [-]: LOADK     R8 K6        ; R8 := 0.800000
 47 [-]: RETURN    R8 2         ; return R8
 48 [-]: CONST     R8 0         ; R8 := 0.000000
 49 [-]: RETURN    R8 2         ; return R8
 50 [-]: RETURN    R0 1         ; return 


; Function #12:
;
; Name:            
; Defined at line: 324
; #Upvalues:       1
; #Parameters:     2
; Is_vararg:       0
; Max Stack Size:  6

  1 [-]: GETUPVAL  R2 U0        ; R2 := U0
  2 [-]: GETTABLE  R2 R2 K0     ; R2 := R2[0xe4ae0e66]
  3 [-]: CALL      R2 1 2       ; R2 := R2()
  4 [-]: TEST      R2 0         ; if not R2 then PC := 12
  5 [-]: JMP       12           ; PC := 12
  6 [-]: GETGLOBAL R2 K1        ; R2 := 0x6687f6e0
  7 [-]: SELF      R2 R2 K2     ; R3 := R2; R2 := R2[0x3a147087]
  8 [-]: GETGLOBAL R4 K3        ; R4 := 0xbe190284
  9 [-]: SELF      R4 R4 K4     ; R5 := R4; R4 := R4[0xc911409e]
 10 [-]: CALL      R4 2 0       ; R4,... := R4(R5)
 11 [-]: CALL      R2 0 1       ; R2(R3,...)
 12 [-]: RETURN    R0 1         ; return 


; Function #13:
;
; Name:            
; Defined at line: 330
; #Upvalues:       0
; #Parameters:     4
; Is_vararg:       0
; Max Stack Size:  12

  1 [-]: GETGLOBAL R4 K0        ; R4 := 0x89326c93
  2 [-]: SELF      R4 R4 K1     ; R5 := R4; R4 := R4[0x05909209]
  3 [-]: MOVE      R6 R0        ; R6 := R0
  4 [-]: MOVE      R7 R1        ; R7 := R1
  5 [-]: GETGLOBAL R8 K2        ; R8 := ZERO_ROTATION
  6 [-]: CALL      R4 5 2       ; R4 := R4(R5,R6,R7,R8)
  7 [-]: SELF      R5 R4 K3     ; R6 := R4; R5 := R4[0xa9365339]
  8 [-]: MOVE      R7 R2        ; R7 := R2
  9 [-]: CALL      R5 3 1       ; R5(R6,R7)
 10 [-]: GETGLOBAL R5 K4        ; R5 := 0x7b998233
 11 [-]: MOVE      R6 R3        ; R6 := R3
 12 [-]: CALL      R5 2 2       ; R5 := R5(R6)
 13 [-]: TEST      R5 1         ; if R5 then PC := 19
 14 [-]: JMP       19           ; PC := 19
 15 [-]: SELF      R5 R4 K5     ; R6 := R4; R5 := R4[0xf4dc3420]
 16 [-]: SELF      R7 R3 K6     ; R8 := R3; R7 := R3[0x5e651723]
 17 [-]: CALL      R7 2 0       ; R7,... := R7(R8)
 18 [-]: CALL      R5 0 1       ; R5(R6,...)
 19 [-]: GETGLOBAL R5 K7        ; R5 := 0xa421af95
 20 [-]: CONST     R6 0         ; R6 := 0.000000
 21 [-]: CONST     R7 1         ; R7 := 1.000000
 22 [-]: CONST     R8 0         ; R8 := 0.000000
 23 [-]: CALL      R5 4 2       ; R5 := R5(R6,R7,R8)
 24 [-]: GETGLOBAL R6 K7        ; R6 := 0xa421af95
 25 [-]: GETGLOBAL R7 K8        ; R7 := 0xc163f229
 26 [-]: CONST     R8 0         ; R8 := 0.000000
 27 [-]: CONST     R9 2         ; R9 := 2.000000
 28 [-]: CALL      R7 3 2       ; R7 := R7(R8,R9)
 29 [-]: SUB       R7 R7 K9     ; R7 := R7 - 1.000000
 30 [-]: CONST     R8 0         ; R8 := 0.000000
 31 [-]: GETGLOBAL R9 K8        ; R9 := 0xc163f229
 32 [-]: CONST     R10 0        ; R10 := 0.000000
 33 [-]: CONST     R11 2        ; R11 := 2.000000
 34 [-]: CALL      R9 3 2       ; R9 := R9(R10,R11)
 35 [-]: SUB       R9 R9 K9     ; R9 := R9 - 1.000000
 36 [-]: CALL      R6 4 2       ; R6 := R6(R7,R8,R9)
 37 [-]: GETGLOBAL R7 K10       ; R7 := 0xc2892f65
 38 [-]: MOVE      R8 R6        ; R8 := R6
 39 [-]: CALL      R7 2 1       ; R7(R8)
 40 [-]: GETGLOBAL R7 K8        ; R7 := 0xc163f229
 41 [-]: CONST     R8 5         ; R8 := 5.000000
 42 [-]: CONST     R9 10        ; R9 := 10.000000
 43 [-]: CALL      R7 3 2       ; R7 := R7(R8,R9)
 44 [-]: MUL       R7 R5 R7     ; R7 := R5 * R7
 45 [-]: GETGLOBAL R8 K8        ; R8 := 0xc163f229
 46 [-]: CONST     R9 1         ; R9 := 1.000000
 47 [-]: CONST     R10 2        ; R10 := 2.000000
 48 [-]: CALL      R8 3 2       ; R8 := R8(R9,R10)
 49 [-]: MUL       R8 R6 R8     ; R8 := R6 * R8
 50 [-]: ADD       R7 R7 R8     ; R7 := R7 + R8
 51 [-]: SELF      R8 R4 K11    ; R9 := R4; R8 := R4[0xc5b6a2d5]
 52 [-]: MOVE      R10 R7       ; R10 := R7
 53 [-]: CALL      R8 3 1       ; R8(R9,R10)
 54 [-]: SELF      R8 R4 K12    ; R9 := R4; R8 := R4[0xef23c099]
 55 [-]: MOVE      R10 R7       ; R10 := R7
 56 [-]: CALL      R8 3 1       ; R8(R9,R10)
 57 [-]: RETURN    R0 1         ; return 


; Function #14:
;
; Name:            
; Defined at line: 344
; #Upvalues:       1
; #Parameters:     2
; Is_vararg:       0
; Max Stack Size:  8

  1 [-]: GETGLOBAL R2 K0        ; R2 := 0x89326c93
  2 [-]: SELF      R2 R2 K1     ; R3 := R2; R2 := R2[0x18d05d30]
  3 [-]: CALL      R2 2 2       ; R2 := R2(R3)
  4 [-]: TEST      R2 0         ; if not R2 then PC := 30
  5 [-]: JMP       30           ; PC := 30
  6 [-]: SELF      R2 R0 K2     ; R3 := R0; R2 := R0[0xde321e6f]
  7 [-]: CALL      R2 2 2       ; R2 := R2(R3)
  8 [-]: SELF      R2 R2 K3     ; R3 := R2; R2 := R2[0xf7d48ee0]
  9 [-]: CALL      R2 2 2       ; R2 := R2(R3)
 10 [-]: GETGLOBAL R3 K4        ; R3 := 0x7b998233
 11 [-]: MOVE      R4 R2        ; R4 := R2
 12 [-]: CALL      R3 2 2       ; R3 := R3(R4)
 13 [-]: TEST      R3 1         ; if R3 then PC := 30
 14 [-]: JMP       30           ; PC := 30
 15 [-]: TEST      R1 0         ; if not R1 then PC := 24
 16 [-]: JMP       24           ; PC := 24
 17 [-]: SELF      R3 R2 K5     ; R4 := R2; R3 := R2[0x9c27a26d]
 18 [-]: GETGLOBAL R5 K6        ; R5 := 0x6687f6e0
 19 [-]: GETGLOBAL R6 K7        ; R6 := 0x0469f296
 20 [-]: LOADK     R7 K8        ; R7 := "OnProcBlock"
 21 [-]: CALL      R6 2 0       ; R6,... := R6(R7)
 22 [-]: CALL      R3 0 1       ; R3(R4,...)
 23 [-]: JMP       30           ; PC := 30
 24 [-]: SELF      R3 R2 K9     ; R4 := R2; R3 := R2[0x56a4f3d7]
 25 [-]: GETGLOBAL R5 K6        ; R5 := 0x6687f6e0
 26 [-]: GETGLOBAL R6 K7        ; R6 := 0x0469f296
 27 [-]: LOADK     R7 K8        ; R7 := "OnProcBlock"
 28 [-]: CALL      R6 2 0       ; R6,... := R6(R7)
 29 [-]: CALL      R3 0 1       ; R3(R4,...)
 30 [-]: GETUPVAL  R3 U0        ; R3 := U0
 31 [-]: GETTABLE  R3 R3 K10    ; R3 := R3[0x8c971f40]
 32 [-]: MOVE      R4 R0        ; R4 := R0
 33 [-]: MOVE      R5 R1        ; R5 := R1
 34 [-]: CALL      R3 3 1       ; R3(R4,R5)
 35 [-]: RETURN    R0 1         ; return 


; Function #15:
;
; Name:            
; Defined at line: 360
; #Upvalues:       7
; #Parameters:     4
; Is_vararg:       0
; Max Stack Size:  48

  1 [-]: GETUPVAL  R4 U0        ; R4 := U0
  2 [-]: MOVE      R5 R3        ; R5 := R3
  3 [-]: CALL      R4 2 1       ; R4(R5)
  4 [-]: GETUPVAL  R4 U1        ; R4 := U1
  5 [-]: MOVE      R5 R1        ; R5 := R1
  6 [-]: CALL      R4 2 6       ; R4,R5,R6,R7,R8 := R4(R5)
  7 [-]: SELF      R9 R1 K0     ; R10 := R1; R9 := R1[0xeea7f8c4]
  8 [-]: CALL      R9 2 2       ; R9 := R9(R10)
  9 [-]: CONST     R10 1        ; R10 := 1.000000
 10 [-]: SELF      R11 R1 K1    ; R12 := R1; R11 := R1[0x020d4331]
 11 [-]: CALL      R11 2 2      ; R11 := R11(R12)
 12 [-]: SELF      R11 R11 K2   ; R12 := R11; R11 := R11[0x553549e8]
 13 [-]: MOVE      R13 R9       ; R13 := R9
 14 [-]: CALL      R11 3 1      ; R11(R12,R13)
 15 [-]: GETGLOBAL R11 K3       ; R11 := 0x6687f6e0
 16 [-]: SELF      R11 R11 K4   ; R12 := R11; R11 := R11[0x7e627183]
 17 [-]: CALL      R11 2 2      ; R11 := R11(R12)
 18 [-]: SELF      R12 R1 K5    ; R13 := R1; R12 := R1[0x47901f07]
 19 [-]: SELF      R14 R0 K6    ; R15 := R0; R14 := R0[0xbc4ebb44]
 20 [-]: GETGLOBAL R16 K7       ; R16 := 0x0469f296
 21 [-]: LOADK     R17 K8       ; R17 := "WellCast"
 22 [-]: CALL      R16 2 0      ; R16,... := R16(R17)
 23 [-]: CALL      R14 0 2      ; R14 := R14(R15,...)
 24 [-]: GETGLOBAL R15 K9       ; R15 := EMPTY_SYMBOL
 25 [-]: GETGLOBAL R16 K10      ; R16 := ZERO_VECTOR
 26 [-]: GETGLOBAL R17 K11      ; R17 := ZERO_ROTATION
 27 [-]: MOVE      R18 R0       ; R18 := R0
 28 [-]: CALL      R12 7 1      ; R12(R13,R14,R15,R16,R17,R18)
 29 [-]: GETUPVAL  R12 U2       ; R12 := U2
 30 [-]: GETTABLE  R12 R12 K12  ; R12 := R12[0x54697cb5]
 31 [-]: MOVE      R13 R0       ; R13 := R0
 32 [-]: GETGLOBAL R14 K13      ; R14 := 0x0ed8b456
 33 [-]: LOADKB    R15 1 0      ; R15 := true
 34 [-]: CONST     R16 2        ; R16 := 2.000000
 35 [-]: CONST     R17 1        ; R17 := 1.000000
 36 [-]: LOADKB    R18 1 0      ; R18 := true
 37 [-]: CALL      R12 7 1      ; R12(R13,R14,R15,R16,R17,R18)
 38 [-]: SELF      R12 R1 K15   ; R13 := R1; R12 := R1[0x659d451f]
 39 [-]: GETGLOBAL R14 K16      ; R14 := 0x520e413d
 40 [-]: LOADKB    R15 0 0      ; R15 := false
 41 [-]: CONST     R16 0        ; R16 := 0.000000
 42 [-]: LOADKB    R17 1 0      ; R17 := true
 43 [-]: CALL      R12 6 1      ; R12(R13,R14,R15,R16,R17)
 44 [-]: SELF      R12 R1 K5    ; R13 := R1; R12 := R1[0x47901f07]
 45 [-]: SELF      R14 R0 K6    ; R15 := R0; R14 := R0[0xbc4ebb44]
 46 [-]: GETGLOBAL R16 K7       ; R16 := 0x0469f296
 47 [-]: LOADK     R17 K17      ; R17 := "WellCastBurst"
 48 [-]: CALL      R16 2 0      ; R16,... := R16(R17)
 49 [-]: CALL      R14 0 2      ; R14 := R14(R15,...)
 50 [-]: GETGLOBAL R15 K7       ; R15 := 0x0469f296
 51 [-]: LOADK     R16 K18      ; R16 := "GAME_L1_WEAPON1"
 52 [-]: CALL      R15 2 2      ; R15 := R15(R16)
 53 [-]: GETGLOBAL R16 K10      ; R16 := ZERO_VECTOR
 54 [-]: GETGLOBAL R17 K11      ; R17 := ZERO_ROTATION
 55 [-]: MOVE      R18 R0       ; R18 := R0
 56 [-]: CALL      R12 7 1      ; R12(R13,R14,R15,R16,R17,R18)
 57 [-]: SELF      R12 R0 K19   ; R13 := R0; R12 := R0[0x0d0482e0]
 58 [-]: CALL      R12 2 1      ; R12(R13)
 59 [-]: SELF      R12 R0 K20   ; R13 := R0; R12 := R0[0x6a4e4088]
 60 [-]: CALL      R12 2 1      ; R12(R13)
 61 [-]: GETGLOBAL R12 K21      ; R12 := 0x7b998233
 62 [-]: MOVE      R13 R2       ; R13 := R2
 63 [-]: CALL      R12 2 2      ; R12 := R12(R13)
 64 [-]: TEST      R12 1        ; if R12 then PC := 74
 65 [-]: JMP       74           ; PC := 74
 66 [-]: SELF      R12 R2 K22   ; R13 := R2; R12 := R2[0x73901acf]
 67 [-]: CALL      R12 2 2      ; R12 := R12(R13)
 68 [-]: TEST      R12 1        ; if R12 then PC := 74
 69 [-]: JMP       74           ; PC := 74
 70 [-]: SELF      R12 R2 K23   ; R13 := R2; R12 := R2[0x2047cfe7]
 71 [-]: CALL      R12 2 2      ; R12 := R12(R13)
 72 [-]: TEST      R12 0        ; if not R12 then PC := 89
 73 [-]: JMP       89           ; PC := 89
 74 [-]: GETGLOBAL R12 K24      ; R12 := 0x89326c93
 75 [-]: SELF      R12 R12 K25  ; R13 := R12; R12 := R12[0x18d05d30]
 76 [-]: CALL      R12 2 2      ; R12 := R12(R13)
 77 [-]: TEST      R12 0        ; if not R12 then PC := 87
 78 [-]: JMP       87           ; PC := 87
 79 [-]: GETUPVAL  R12 U3       ; R12 := U3
 80 [-]: GETTABLE  R12 R12 K26  ; R12 := R12[0x32316a21]
 81 [-]: CALL      R12 1 2      ; R12 := R12()
 82 [-]: TEST      R12 1        ; if R12 then PC := 87
 83 [-]: JMP       87           ; PC := 87
 84 [-]: SELF      R12 R0 K27   ; R13 := R0; R12 := R0[0xfc80301e]
 85 [-]: MOVE      R14 R11      ; R14 := R11
 86 [-]: CALL      R12 3 1      ; R12(R13,R14)
 87 [-]: LOADKB    R12 1 0      ; R12 := true
 88 [-]: RETURN    R12 2        ; return R12
 89 [-]: GETGLOBAL R12 K21      ; R12 := 0x7b998233
 90 [-]: GETGLOBAL R13 K28      ; R13 := _T
 91 [-]: GETTABLE  R13 R13 K29  ; R13 := R13["wellOfLifeLeech"]
 92 [-]: CALL      R12 2 2      ; R12 := R12(R13)
 93 [-]: TEST      R12 0        ; if not R12 then PC := 98
 94 [-]: JMP       98           ; PC := 98
 95 [-]: GETGLOBAL R12 K28      ; R12 := _T
 96 [-]: NEWTABLE  R13 0 0      ; R13 := {}
 97 [-]: SETTABLE  R12 K29 R13  ; R12["wellOfLifeLeech"] := R13
 98 [-]: GETGLOBAL R12 K24      ; R12 := 0x89326c93
 99 [-]: SELF      R12 R12 K25  ; R13 := R12; R12 := R12[0x18d05d30]
100 [-]: CALL      R12 2 2      ; R12 := R12(R13)
101 [-]: TEST      R12 0        ; if not R12 then PC := 119
102 [-]: JMP       119          ; PC := 119
103 [-]: SELF      R12 R2 K30   ; R13 := R2; R12 := R2[0x1ac1655c]
104 [-]: CALL      R12 2 2      ; R12 := R12(R13)
105 [-]: GETGLOBAL R13 K28      ; R13 := _T
106 [-]: GETTABLE  R13 R13 K29  ; R13 := R13["wellOfLifeLeech"]
107 [-]: SELF      R14 R1 K31   ; R15 := R1; R14 := R1[0x388577d5]
108 [-]: CALL      R14 2 2      ; R14 := R14(R15)
109 [-]: SELF      R15 R12 K32  ; R16 := R12; R15 := R12[0xd323c0f0]
110 [-]: MOVE      R17 R1       ; R17 := R1
111 [-]: MOVE      R18 R5       ; R18 := R5
112 [-]: CONST     R19 0        ; R19 := 0.000000
113 [-]: MOVE      R20 R7       ; R20 := R7
114 [-]: CALL      R15 6 2      ; R15 := R15(R16,R17,R18,R19,R20)
115 [-]: SETTABLE  R13 R14 R15  ; R13[R14] := R15
116 [-]: SELF      R13 R12 K33  ; R14 := R12; R13 := R12[0xd8b8c436]
117 [-]: LOADKB    R15 1 0      ; R15 := true
118 [-]: CALL      R13 3 1      ; R13(R14,R15)
119 [-]: GETUPVAL  R13 U4       ; R13 := U4
120 [-]: MOVE      R14 R2       ; R14 := R2
121 [-]: CALL      R13 2 1      ; R13(R14)
122 [-]: SELF      R13 R2 K5    ; R14 := R2; R13 := R2[0x47901f07]
123 [-]: SELF      R15 R0 K6    ; R16 := R0; R15 := R0[0xbc4ebb44]
124 [-]: GETGLOBAL R17 K7       ; R17 := 0x0469f296
125 [-]: LOADK     R18 K34      ; R18 := "WellAttach"
126 [-]: CALL      R17 2 0      ; R17,... := R17(R18)
127 [-]: CALL      R15 0 2      ; R15 := R15(R16,...)
128 [-]: GETGLOBAL R16 K9       ; R16 := EMPTY_SYMBOL
129 [-]: GETGLOBAL R17 K10      ; R17 := ZERO_VECTOR
130 [-]: GETGLOBAL R18 K11      ; R18 := ZERO_ROTATION
131 [-]: MOVE      R19 R0       ; R19 := R0
132 [-]: CALL      R13 7 1      ; R13(R14,R15,R16,R17,R18,R19)
133 [-]: SELF      R13 R0 K35   ; R14 := R0; R13 := R0[0x6df09e59]
134 [-]: CALL      R13 2 2      ; R13 := R13(R14)
135 [-]: TEST      R13 0        ; if not R13 then PC := 150
136 [-]: JMP       150          ; PC := 150
137 [-]: SELF      R13 R2 K5    ; R14 := R2; R13 := R2[0x47901f07]
138 [-]: SELF      R15 R0 K6    ; R16 := R0; R15 := R0[0xbc4ebb44]
139 [-]: GETGLOBAL R17 K7       ; R17 := 0x0469f296
140 [-]: LOADK     R18 K36      ; R18 := "PrimeAttachEffect"
141 [-]: CALL      R17 2 0      ; R17,... := R17(R18)
142 [-]: CALL      R15 0 2      ; R15 := R15(R16,...)
143 [-]: GETGLOBAL R16 K7       ; R16 := 0x0469f296
144 [-]: LOADK     R17 K37      ; R17 := "GAME_C1_HIP1"
145 [-]: CALL      R16 2 2      ; R16 := R16(R17)
146 [-]: GETGLOBAL R17 K10      ; R17 := ZERO_VECTOR
147 [-]: GETGLOBAL R18 K11      ; R18 := ZERO_ROTATION
148 [-]: MOVE      R19 R0       ; R19 := R0
149 [-]: CALL      R13 7 1      ; R13(R14,R15,R16,R17,R18,R19)
150 [-]: SELF      R13 R2 K5    ; R14 := R2; R13 := R2[0x47901f07]
151 [-]: GETGLOBAL R15 K38      ; R15 := 0x723d515a
152 [-]: GETGLOBAL R16 K9       ; R16 := EMPTY_SYMBOL
153 [-]: GETGLOBAL R17 K10      ; R17 := ZERO_VECTOR
154 [-]: GETGLOBAL R18 K11      ; R18 := ZERO_ROTATION
155 [-]: MOVE      R19 R0       ; R19 := R0
156 [-]: CALL      R13 7 2      ; R13 := R13(R14,R15,R16,R17,R18,R19)
157 [-]: GETGLOBAL R14 K21      ; R14 := 0x7b998233
158 [-]: MOVE      R15 R13      ; R15 := R13
159 [-]: CALL      R14 2 2      ; R14 := R14(R15)
160 [-]: TEST      R14 1        ; if R14 then PC := 165
161 [-]: JMP       165          ; PC := 165
162 [-]: SELF      R14 R13 K39  ; R15 := R13; R14 := R13[0x7679029b]
163 [-]: DIV       R16 R7 K40   ; R16 := R7 / 1.250000
164 [-]: CALL      R14 3 1      ; R14(R15,R16)
165 [-]: SELF      R14 R2 K41   ; R15 := R2; R14 := R2[0xf2deaf69]
166 [-]: GETGLOBAL R16 K42      ; R16 := gLotusNpcAvatarType
167 [-]: CALL      R14 3 2      ; R14 := R14(R15,R16)
168 [-]: TEST      R14 0        ; if not R14 then PC := 181
169 [-]: JMP       181          ; PC := 181
170 [-]: SELF      R14 R2 K43   ; R15 := R2; R14 := R2[0x278b099d]
171 [-]: CALL      R14 2 2      ; R14 := R14(R15)
172 [-]: TEST      R14 1        ; if R14 then PC := 179
173 [-]: JMP       179          ; PC := 179
174 [-]: SELF      R14 R2 K41   ; R15 := R2; R14 := R2[0xf2deaf69]
175 [-]: GETGLOBAL R16 K44      ; R16 := gLotusBossNpcAvatarType
176 [-]: CALL      R14 3 2      ; R14 := R14(R15,R16)
177 [-]: NOT       R14 R14      ; R14 :=  R14
178 [-]: JMP       181          ; PC := 181
179 [-]: LOADKB    R14 0 1      ; R14 := false; PC := 180
180 [-]: LOADKB    R14 1 0      ; R14 := true
181 [-]: TEST      R14 0        ; if not R14 then PC := 193
182 [-]: JMP       193          ; PC := 193
183 [-]: SELF      R15 R2 K45   ; R16 := R2; R15 := R2[0x0f89a4d4]
184 [-]: GETGLOBAL R17 K7       ; R17 := 0x0469f296
185 [-]: LOADK     R18 K46      ; R18 := "STASIS_START"
186 [-]: CALL      R17 2 2      ; R17 := R17(R18)
187 [-]: LOADKB    R18 0 0      ; R18 := false
188 [-]: CONST     R19 3        ; R19 := 3.000000
189 [-]: CONST     R20 3        ; R20 := 3.000000
190 [-]: LOADKB    R21 1 0      ; R21 := true
191 [-]: MOVE      R22 R10      ; R22 := R10
192 [-]: CALL      R15 8 1      ; R15(R16,R17,R18,R19,R20,R21,R22)
193 [-]: SELF      R15 R0 K47   ; R16 := R0; R15 := R0[0x79f6af86]
194 [-]: LOADKB    R17 1 0      ; R17 := true
195 [-]: CALL      R15 3 1      ; R15(R16,R17)
196 [-]: SELF      R15 R2 K48   ; R16 := R2; R15 := R2[0xb61e5a1a]
197 [-]: GETUPVAL  R17 U5       ; R17 := U5
198 [-]: MOVE      R18 R6       ; R18 := R6
199 [-]: CALL      R15 4 2      ; R15 := R15(R16,R17,R18)
200 [-]: MOVE      R6 R15       ; R6 := R15
201 [-]: CONST     R15 0        ; R15 := 0.000000
202 [-]: CONST     R16 0        ; R16 := 0.000000
203 [-]: NEWTABLE  R17 0 0      ; R17 := {}
204 [-]: NEWTABLE  R18 0 2      ; R18 := {}
205 [-]: SETTABLE  R18 K49 R2   ; R18["target"] := R2
206 [-]: SETTABLE  R18 K50 R17  ; R18["hotAvatars"] := R17
207 [-]: GETUPVAL  R19 U2       ; R19 := U2
208 [-]: GETTABLE  R19 R19 K51  ; R19 := R19[0xf43af54f]
209 [-]: MOVE      R20 R0       ; R20 := R0
210 [-]: GETGLOBAL R21 K3       ; R21 := 0x6687f6e0
211 [-]: MOVE      R22 R18      ; R22 := R18
212 [-]: CALL      R19 4 1      ; R19(R20,R21,R22)
213 [-]: GETGLOBAL R19 K28      ; R19 := _T
214 [-]: GETTABLE  R19 R19 K52  ; R19 := R19[0xcc4ac7a6]
215 [-]: GETGLOBAL R20 K3       ; R20 := 0x6687f6e0
216 [-]: SELF      R20 R20 K53  ; R21 := R20; R20 := R20[0xcde10c4a]
217 [-]: CALL      R20 2 2      ; R20 := R20(R21)
218 [-]: MOVE      R21 R1       ; R21 := R1
219 [-]: MOVE      R22 R6       ; R22 := R6
220 [-]: CONST     R23 0        ; R23 := 0.000000
221 [-]: CALL      R19 5 1      ; R19(R20,R21,R22,R23)
222 [-]: GETGLOBAL R19 K21      ; R19 := 0x7b998233
223 [-]: MOVE      R20 R2       ; R20 := R2
224 [-]: CALL      R19 2 2      ; R19 := R19(R20)
225 [-]: TEST      R19 1        ; if R19 then PC := 375
226 [-]: JMP       375          ; PC := 375
227 [-]: SELF      R19 R2 K23   ; R20 := R2; R19 := R2[0x2047cfe7]
228 [-]: CALL      R19 2 2      ; R19 := R19(R20)
229 [-]: TEST      R19 1        ; if R19 then PC := 375
230 [-]: JMP       375          ; PC := 375
231 [-]: LT        0 K54 R6     ; if 0.000000 >= R6 then PC := 375
232 [-]: JMP       375          ; PC := 375
233 [-]: SELF      R19 R2 K55   ; R20 := R2; R19 := R2[0xc4dff581]
234 [-]: CONST     R21 4        ; R21 := 4.000000
235 [-]: CALL      R19 3 2      ; R19 := R19(R20,R21)
236 [-]: TEST      R19 1        ; if R19 then PC := 375
237 [-]: JMP       375          ; PC := 375
238 [-]: GETGLOBAL R19 K24      ; R19 := 0x89326c93
239 [-]: SELF      R19 R19 K25  ; R20 := R19; R19 := R19[0x18d05d30]
240 [-]: CALL      R19 2 2      ; R19 := R19(R20)
241 [-]: TEST      R19 0        ; if not R19 then PC := 350
242 [-]: JMP       350          ; PC := 350
243 [-]: GETGLOBAL R19 K57      ; R19 := 0x67652851
244 [-]: CALL      R19 1 2      ; R19 := R19()
245 [-]: SUB       R16 R16 R19  ; R16 := R16 - R19
246 [-]: LE        0 R16 K54    ; if R16 > 0.000000 then PC := 309
247 [-]: JMP       309          ; PC := 309
248 [-]: CONST     R16 0        ; R16 := 0.500000
249 [-]: GETGLOBAL R19 K24      ; R19 := 0x89326c93
250 [-]: SELF      R19 R19 K58  ; R20 := R19; R19 := R19[0xfb669000]
251 [-]: GETGLOBAL R21 K59      ; R21 := gBaseAvatarType
252 [-]: SELF      R22 R2 K60   ; R23 := R2; R22 := R2[0xef8e8f7f]
253 [-]: CALL      R22 2 2      ; R22 := R22(R23)
254 [-]: CONST     R23 0        ; R23 := 0.000000
255 [-]: MOVE      R24 R7       ; R24 := R7
256 [-]: CALL      R19 6 2      ; R19 := R19(R20,R21,R22,R23,R24)
257 [-]: NEWTABLE  R20 0 0      ; R20 := {}
258 [-]: GETGLOBAL R21 K61      ; R21 := 0xc8802016
259 [-]: MOVE      R22 R19      ; R22 := R19
260 [-]: CALL      R21 2 4      ; R21,R22,R23 := R21(R22)
261 [-]: JMP       290          ; PC := 290
262 [-]: SELF      R26 R1 K62   ; R27 := R1; R26 := R1[0x6d6734dc]
263 [-]: MOVE      R28 R25      ; R28 := R25
264 [-]: CALL      R26 3 2      ; R26 := R26(R27,R28)
265 [-]: TEST      R26 0        ; if not R26 then PC := 290
266 [-]: JMP       290          ; PC := 290
267 [-]: SELF      R26 R25 K63  ; R27 := R25; R26 := R25[0x753a7ea6]
268 [-]: MOVE      R28 R1       ; R28 := R1
269 [-]: CALL      R26 3 2      ; R26 := R26(R27,R28)
270 [-]: TEST      R26 0        ; if not R26 then PC := 290
271 [-]: JMP       290          ; PC := 290
272 [-]: GETGLOBAL R26 K3       ; R26 := 0x6687f6e0
273 [-]: SELF      R26 R26 K64  ; R27 := R26; R26 := R26[0xc05a66cd]
274 [-]: MOVE      R28 R25      ; R28 := R25
275 [-]: CALL      R26 3 2      ; R26 := R26(R27,R28)
276 [-]: TEST      R26 1        ; if R26 then PC := 290
277 [-]: JMP       290          ; PC := 290
278 [-]: SELF      R26 R25 K31  ; R27 := R25; R26 := R25[0x388577d5]
279 [-]: CALL      R26 2 2      ; R26 := R26(R27)
280 [-]: GETTABLE  R27 R17 R26  ; R27 := R17[R26]
281 [-]: TEST      R27 1        ; if R27 then PC := 288
282 [-]: JMP       288          ; PC := 288
283 [-]: GETUPVAL  R27 U6       ; R27 := U6
284 [-]: MOVE      R28 R25      ; R28 := R25
285 [-]: LOADKB    R29 1 0      ; R29 := true
286 [-]: CALL      R27 3 1      ; R27(R28,R29)
287 [-]: JMP       289          ; PC := 289
288 [-]: SETTABLE  R17 R26 K65  ; R17[R26] := nil
289 [-]: SETTABLE  R20 R26 R25  ; R20[R26] := R25
290 [-]: TFORLOOP  R21 2        ; R24,R25 :=  R21(R22,R23); if R24 ~= nil then begin PC = 262; R23 := R24 end
291 [-]: JMP       262          ; PC := 262
292 [-]: GETGLOBAL R27 K66      ; R27 := 0xcfc01047
293 [-]: MOVE      R28 R17      ; R28 := R17
294 [-]: CALL      R27 2 4      ; R27,R28,R29 := R27(R28)
295 [-]: JMP       305          ; PC := 305
296 [-]: GETGLOBAL R32 K21      ; R32 := 0x7b998233
297 [-]: MOVE      R33 R31      ; R33 := R31
298 [-]: CALL      R32 2 2      ; R32 := R32(R33)
299 [-]: TEST      R32 1        ; if R32 then PC := 305
300 [-]: JMP       305          ; PC := 305
301 [-]: GETUPVAL  R32 U6       ; R32 := U6
302 [-]: MOVE      R33 R31      ; R33 := R31
303 [-]: LOADKB    R34 0 0      ; R34 := false
304 [-]: CALL      R32 3 1      ; R32(R33,R34)
305 [-]: TFORLOOP  R27 2        ; R30,R31 :=  R27(R28,R29); if R30 ~= nil then begin PC = 296; R29 := R30 end
306 [-]: JMP       296          ; PC := 296
307 [-]: MOVE      R17 R20      ; R17 := R20
308 [-]: SETTABLE  R18 K50 R17  ; R18["hotAvatars"] := R17
309 [-]: GETGLOBAL R32 K57      ; R32 := 0x67652851
310 [-]: CALL      R32 1 2      ; R32 := R32()
311 [-]: MUL       R32 R8 R32   ; R32 := R8 * R32
312 [-]: ADD       R15 R15 R32  ; R15 := R15 + R32
313 [-]: LE        0 K67 R15    ; if 1.000000 > R15 then PC := 350
314 [-]: JMP       350          ; PC := 350
315 [-]: GETGLOBAL R32 K68      ; R32 := 0x5bced4c4
316 [-]: GETTABLE  R32 R32 K69  ; R32 := R32[0x55f27c30]
317 [-]: MOVE      R33 R15      ; R33 := R15
318 [-]: CALL      R32 2 2      ; R32 := R32(R33)
319 [-]: SUB       R15 R15 R32  ; R15 := R15 - R32
320 [-]: CONST     R33 0        ; R33 := 0.000000
321 [-]: GETGLOBAL R34 K66      ; R34 := 0xcfc01047
322 [-]: MOVE      R35 R17      ; R35 := R17
323 [-]: CALL      R34 2 4      ; R34,R35,R36 := R34(R35)
324 [-]: JMP       341          ; PC := 341
325 [-]: GETGLOBAL R39 K21      ; R39 := 0x7b998233
326 [-]: MOVE      R40 R38      ; R40 := R38
327 [-]: CALL      R39 2 2      ; R39 := R39(R40)
328 [-]: TEST      R39 1        ; if R39 then PC := 341
329 [-]: JMP       341          ; PC := 341
330 [-]: SELF      R39 R38 K70  ; R40 := R38; R39 := R38[0xd2715720]
331 [-]: CALL      R39 2 2      ; R39 := R39(R40)
332 [-]: SELF      R40 R1 K71   ; R41 := R1; R40 := R1[0x1f135de0]
333 [-]: MOVE      R42 R38      ; R42 := R38
334 [-]: MOVE      R43 R32      ; R43 := R32
335 [-]: MOVE      R44 R1       ; R44 := R1
336 [-]: CALL      R40 5 1      ; R40(R41,R42,R43,R44)
337 [-]: SELF      R40 R38 K70  ; R41 := R38; R40 := R38[0xd2715720]
338 [-]: CALL      R40 2 2      ; R40 := R40(R41)
339 [-]: ADD       R40 R33 R40  ; R40 := R33 + R40
340 [-]: SUB       R33 R40 R39  ; R33 := R40 - R39
341 [-]: TFORLOOP  R34 2        ; R37,R38 :=  R34(R35,R36); if R37 ~= nil then begin PC = 325; R36 := R37 end
342 [-]: JMP       325          ; PC := 325
343 [-]: LT        0 K54 R33    ; if 0.000000 >= R33 then PC := 350
344 [-]: JMP       350          ; PC := 350
345 [-]: GETUPVAL  R40 U2       ; R40 := U2
346 [-]: GETTABLE  R40 R40 K72  ; R40 := R40[0xe1eecb19]
347 [-]: MOVE      R41 R1       ; R41 := R1
348 [-]: MOVE      R42 R33      ; R42 := R33
349 [-]: CALL      R40 3 1      ; R40(R41,R42)
350 [-]: TEST      R14 0        ; if not R14 then PC := 368
351 [-]: JMP       368          ; PC := 368
352 [-]: SELF      R40 R2 K73   ; R41 := R2; R40 := R2[0x444ae2c8]
353 [-]: GETGLOBAL R42 K9       ; R42 := EMPTY_SYMBOL
354 [-]: LOADKB    R43 0 0      ; R43 := false
355 [-]: CALL      R40 4 2      ; R40 := R40(R41,R42,R43)
356 [-]: TEST      R40 1        ; if R40 then PC := 368
357 [-]: JMP       368          ; PC := 368
358 [-]: SELF      R40 R2 K45   ; R41 := R2; R40 := R2[0x0f89a4d4]
359 [-]: GETGLOBAL R42 K7       ; R42 := 0x0469f296
360 [-]: LOADK     R43 K74      ; R43 := "STASIS_LOOP"
361 [-]: CALL      R42 2 2      ; R42 := R42(R43)
362 [-]: LOADKB    R43 0 0      ; R43 := false
363 [-]: CONST     R44 3        ; R44 := 3.000000
364 [-]: CONST     R45 2        ; R45 := 2.000000
365 [-]: LOADKB    R46 1 0      ; R46 := true
366 [-]: MOVE      R47 R10      ; R47 := R10
367 [-]: CALL      R40 8 1      ; R40(R41,R42,R43,R44,R45,R46,R47)
368 [-]: GETGLOBAL R40 K57      ; R40 := 0x67652851
369 [-]: CALL      R40 1 2      ; R40 := R40()
370 [-]: SUB       R6 R6 R40    ; R6 := R6 - R40
371 [-]: GETGLOBAL R40 K75      ; R40 := 0xcbd666e1
372 [-]: CONST     R41 0        ; R41 := 0.000000
373 [-]: CALL      R40 2 1      ; R40(R41)
374 [-]: JMP       222          ; PC := 222
375 [-]: RETURN    R0 1         ; return 


; Function #16:
;
; Name:            
; Defined at line: 494
; #Upvalues:       7
; #Parameters:     3
; Is_vararg:       0
; Max Stack Size:  24

  1 [-]: GETGLOBAL R3 K0        ; R3 := _T
  2 [-]: GETTABLE  R3 R3 K1     ; R3 := R3[0xcc4ac7a6]
  3 [-]: GETGLOBAL R4 K2        ; R4 := 0x6687f6e0
  4 [-]: SELF      R4 R4 K3     ; R5 := R4; R4 := R4[0xcde10c4a]
  5 [-]: CALL      R4 2 2       ; R4 := R4(R5)
  6 [-]: MOVE      R5 R1        ; R5 := R1
  7 [-]: CONST     R6 0         ; R6 := 0.000000
  8 [-]: CONST     R7 0         ; R7 := 0.000000
  9 [-]: CALL      R3 5 1       ; R3(R4,R5,R6,R7)
 10 [-]: CONST     R3 1         ; R3 := 1.000000
 11 [-]: GETGLOBAL R4 K4        ; R4 := 0x7b998233
 12 [-]: MOVE      R5 R2        ; R5 := R2
 13 [-]: CALL      R4 2 2       ; R4 := R4(R5)
 14 [-]: TEST      R4 1         ; if R4 then PC := 44
 15 [-]: JMP       44           ; PC := 44
 16 [-]: SELF      R4 R2 K5     ; R5 := R2; R4 := R2[0xf2deaf69]
 17 [-]: GETGLOBAL R6 K6        ; R6 := gLotusNpcAvatarType
 18 [-]: CALL      R4 3 2       ; R4 := R4(R5,R6)
 19 [-]: TEST      R4 0         ; if not R4 then PC := 44
 20 [-]: JMP       44           ; PC := 44
 21 [-]: SELF      R4 R2 K7     ; R5 := R2; R4 := R2[0x444ae2c8]
 22 [-]: CALL      R4 2 2       ; R4 := R4(R5)
 23 [-]: TEST      R4 0         ; if not R4 then PC := 44
 24 [-]: JMP       44           ; PC := 44
 25 [-]: SELF      R4 R2 K8     ; R5 := R2; R4 := R2[0x278b099d]
 26 [-]: CALL      R4 2 2       ; R4 := R4(R5)
 27 [-]: TEST      R4 1         ; if R4 then PC := 44
 28 [-]: JMP       44           ; PC := 44
 29 [-]: SELF      R4 R2 K5     ; R5 := R2; R4 := R2[0xf2deaf69]
 30 [-]: GETGLOBAL R6 K9        ; R6 := gLotusBossNpcAvatarType
 31 [-]: CALL      R4 3 2       ; R4 := R4(R5,R6)
 32 [-]: TEST      R4 1         ; if R4 then PC := 44
 33 [-]: JMP       44           ; PC := 44
 34 [-]: SELF      R4 R2 K10    ; R5 := R2; R4 := R2[0x0f89a4d4]
 35 [-]: GETGLOBAL R6 K11       ; R6 := 0x0469f296
 36 [-]: LOADK     R7 K12       ; R7 := "STASIS_END"
 37 [-]: CALL      R6 2 2       ; R6 := R6(R7)
 38 [-]: LOADKB    R7 0 0       ; R7 := false
 39 [-]: CONST     R8 3         ; R8 := 3.000000
 40 [-]: CONST     R9 1         ; R9 := 1.000000
 41 [-]: LOADKB    R10 1 0      ; R10 := true
 42 [-]: MOVE      R11 R3       ; R11 := R3
 43 [-]: CALL      R4 8 1       ; R4(R5,R6,R7,R8,R9,R10,R11)
 44 [-]: SELF      R4 R1 K14    ; R5 := R1; R4 := R1[0x388577d5]
 45 [-]: CALL      R4 2 2       ; R4 := R4(R5)
 46 [-]: GETGLOBAL R5 K15       ; R5 := 0x89326c93
 47 [-]: SELF      R5 R5 K16    ; R6 := R5; R5 := R5[0x18d05d30]
 48 [-]: CALL      R5 2 2       ; R5 := R5(R6)
 49 [-]: TEST      R5 0         ; if not R5 then PC := 81
 50 [-]: JMP       81           ; PC := 81
 51 [-]: GETGLOBAL R5 K4        ; R5 := 0x7b998233
 52 [-]: MOVE      R6 R2        ; R6 := R2
 53 [-]: CALL      R5 2 2       ; R5 := R5(R6)
 54 [-]: TEST      R5 1         ; if R5 then PC := 81
 55 [-]: JMP       81           ; PC := 81
 56 [-]: GETGLOBAL R5 K4        ; R5 := 0x7b998233
 57 [-]: GETGLOBAL R6 K0        ; R6 := _T
 58 [-]: GETTABLE  R6 R6 K17    ; R6 := R6["wellOfLifeLeech"]
 59 [-]: CALL      R5 2 2       ; R5 := R5(R6)
 60 [-]: TEST      R5 1         ; if R5 then PC := 81
 61 [-]: JMP       81           ; PC := 81
 62 [-]: GETGLOBAL R5 K4        ; R5 := 0x7b998233
 63 [-]: GETGLOBAL R6 K0        ; R6 := _T
 64 [-]: GETTABLE  R6 R6 K17    ; R6 := R6["wellOfLifeLeech"]
 65 [-]: GETTABLE  R6 R6 R4     ; R6 := R6[R4]
 66 [-]: CALL      R5 2 2       ; R5 := R5(R6)
 67 [-]: TEST      R5 1         ; if R5 then PC := 81
 68 [-]: JMP       81           ; PC := 81
 69 [-]: SELF      R5 R2 K18    ; R6 := R2; R5 := R2[0x1ac1655c]
 70 [-]: CALL      R5 2 2       ; R5 := R5(R6)
 71 [-]: SELF      R5 R5 K19    ; R6 := R5; R5 := R5[0x01128051]
 72 [-]: GETGLOBAL R7 K0        ; R7 := _T
 73 [-]: GETTABLE  R7 R7 K17    ; R7 := R7["wellOfLifeLeech"]
 74 [-]: GETTABLE  R7 R7 R4     ; R7 := R7[R4]
 75 [-]: CALL      R5 3 1       ; R5(R6,R7)
 76 [-]: GETGLOBAL R5 K0        ; R5 := _T
 77 [-]: GETTABLE  R5 R5 K17    ; R5 := R5["wellOfLifeLeech"]
 78 [-]: SELF      R6 R1 K14    ; R7 := R1; R6 := R1[0x388577d5]
 79 [-]: CALL      R6 2 2       ; R6 := R6(R7)
 80 [-]: SETTABLE  R5 R6 K20    ; R5[R6] := nil
 81 [-]: GETGLOBAL R5 K4        ; R5 := 0x7b998233
 82 [-]: MOVE      R6 R2        ; R6 := R2
 83 [-]: CALL      R5 2 2       ; R5 := R5(R6)
 84 [-]: TEST      R5 1         ; if R5 then PC := 203
 85 [-]: JMP       203          ; PC := 203
 86 [-]: GETUPVAL  R5 U0        ; R5 := U0
 87 [-]: MOVE      R6 R2        ; R6 := R2
 88 [-]: CALL      R5 2 1       ; R5(R6)
 89 [-]: SELF      R5 R2 K21    ; R6 := R2; R5 := R2[0xad10e5bc]
 90 [-]: SELF      R7 R0 K22    ; R8 := R0; R7 := R0[0xbc4ebb44]
 91 [-]: GETGLOBAL R9 K11       ; R9 := 0x0469f296
 92 [-]: LOADK     R10 K23      ; R10 := "WellAttach"
 93 [-]: CALL      R9 2 0       ; R9,... := R9(R10)
 94 [-]: CALL      R7 0 0       ; R7,... := R7(R8,...)
 95 [-]: CALL      R5 0 1       ; R5(R6,...)
 96 [-]: SELF      R5 R2 K21    ; R6 := R2; R5 := R2[0xad10e5bc]
 97 [-]: SELF      R7 R0 K22    ; R8 := R0; R7 := R0[0xbc4ebb44]
 98 [-]: GETGLOBAL R9 K11       ; R9 := 0x0469f296
 99 [-]: LOADK     R10 K24      ; R10 := "PrimeAttachEffect"
100 [-]: CALL      R9 2 0       ; R9,... := R9(R10)
101 [-]: CALL      R7 0 0       ; R7,... := R7(R8,...)
102 [-]: CALL      R5 0 1       ; R5(R6,...)
103 [-]: SELF      R5 R2 K25    ; R6 := R2; R5 := R2[0xc9f6a7d7]
104 [-]: GETGLOBAL R7 K26       ; R7 := 0x723d515a
105 [-]: CALL      R5 3 2       ; R5 := R5(R6,R7)
106 [-]: GETGLOBAL R6 K4        ; R6 := 0x7b998233
107 [-]: MOVE      R7 R5        ; R7 := R5
108 [-]: CALL      R6 2 2       ; R6 := R6(R7)
109 [-]: TEST      R6 1         ; if R6 then PC := 113
110 [-]: JMP       113          ; PC := 113
111 [-]: SELF      R6 R5 K27    ; R7 := R5; R6 := R5[0x1db57c6b]
112 [-]: CALL      R6 2 1       ; R6(R7)
113 [-]: SELF      R6 R2 K28    ; R7 := R2; R6 := R2[0x47901f07]
114 [-]: SELF      R8 R0 K22    ; R9 := R0; R8 := R0[0xbc4ebb44]
115 [-]: GETGLOBAL R10 K11      ; R10 := 0x0469f296
116 [-]: LOADK     R11 K29      ; R11 := "WellEnd"
117 [-]: CALL      R10 2 0      ; R10,... := R10(R11)
118 [-]: CALL      R8 0 2       ; R8 := R8(R9,...)
119 [-]: GETGLOBAL R9 K30       ; R9 := EMPTY_SYMBOL
120 [-]: GETGLOBAL R10 K31      ; R10 := ZERO_VECTOR
121 [-]: GETGLOBAL R11 K32      ; R11 := ZERO_ROTATION
122 [-]: MOVE      R12 R0       ; R12 := R0
123 [-]: CALL      R6 7 1       ; R6(R7,R8,R9,R10,R11,R12)
124 [-]: GETGLOBAL R6 K15       ; R6 := 0x89326c93
125 [-]: SELF      R6 R6 K16    ; R7 := R6; R6 := R6[0x18d05d30]
126 [-]: CALL      R6 2 2       ; R6 := R6(R7)
127 [-]: TEST      R6 0         ; if not R6 then PC := 203
128 [-]: JMP       203          ; PC := 203
129 [-]: SELF      R6 R2 K18    ; R7 := R2; R6 := R2[0x1ac1655c]
130 [-]: CALL      R6 2 2       ; R6 := R6(R7)
131 [-]: SELF      R7 R6 K33    ; R8 := R6; R7 := R6[0x7a57291d]
132 [-]: CALL      R7 2 2       ; R7 := R7(R8)
133 [-]: SELF      R8 R6 K34    ; R9 := R6; R8 := R6[0xd8b8c436]
134 [-]: LOADKB    R10 0 0      ; R10 := false
135 [-]: CALL      R8 3 1       ; R8(R9,R10)
136 [-]: SELF      R8 R7 K35    ; R9 := R7; R8 := R7[0x022ce583]
137 [-]: CALL      R8 2 2       ; R8 := R8(R9)
138 [-]: SELF      R8 R8 K36    ; R9 := R8; R8 := R8[0x111f713c]
139 [-]: CALL      R8 2 2       ; R8 := R8(R9)
140 [-]: LT        0 K37 R8     ; if 0.000000 >= R8 then PC := 203
141 [-]: JMP       203          ; PC := 203
142 [-]: SELF      R8 R2 K38    ; R9 := R2; R8 := R2[0xef8e8f7f]
143 [-]: CALL      R8 2 2       ; R8 := R8(R9)
144 [-]: SELF      R9 R7 K39    ; R10 := R7; R9 := R7[0x86cd00cb]
145 [-]: MOVE      R11 R1       ; R11 := R1
146 [-]: CALL      R9 3 1       ; R9(R10,R11)
147 [-]: SELF      R9 R7 K40    ; R10 := R7; R9 := R7[0xf4dc3420]
148 [-]: MOVE      R11 R0       ; R11 := R0
149 [-]: CALL      R9 3 1       ; R9(R10,R11)
150 [-]: SELF      R9 R2 K41    ; R10 := R2; R9 := R2[0x479483bb]
151 [-]: MOVE      R11 R7       ; R11 := R7
152 [-]: CALL      R9 3 1       ; R9(R10,R11)
153 [-]: GETGLOBAL R9 K4        ; R9 := 0x7b998233
154 [-]: MOVE      R10 R2       ; R10 := R2
155 [-]: CALL      R9 2 2       ; R9 := R9(R10)
156 [-]: TEST      R9 1         ; if R9 then PC := 167
157 [-]: JMP       167          ; PC := 167
158 [-]: SELF      R9 R2 K42    ; R10 := R2; R9 := R2[0x2047cfe7]
159 [-]: CALL      R9 2 2       ; R9 := R9(R10)
160 [-]: TEST      R9 0         ; if not R9 then PC := 203
161 [-]: JMP       203          ; PC := 203
162 [-]: SELF      R9 R2 K43    ; R10 := R2; R9 := R2[0xc4dff581]
163 [-]: CONST     R11 0        ; R11 := 0.000000
164 [-]: CALL      R9 3 2       ; R9 := R9(R10,R11)
165 [-]: TEST      R9 1         ; if R9 then PC := 203
166 [-]: JMP       203          ; PC := 203
167 [-]: SELF      R9 R0 K45    ; R10 := R0; R9 := R0[0x5063edc3]
168 [-]: CALL      R9 2 2       ; R9 := R9(R10)
169 [-]: SELF      R10 R0 K46   ; R11 := R0; R10 := R0[0x75ecaf0b]
170 [-]: CALL      R10 2 2      ; R10 := R10(R11)
171 [-]: LT        0 K37 R9     ; if 0.000000 >= R9 then PC := 203
172 [-]: JMP       203          ; PC := 203
173 [-]: EQ        0 R10 K47    ; if R10 ~= 1.000000 then PC := 203
174 [-]: JMP       203          ; PC := 203
175 [-]: GETUPVAL  R11 U1       ; R11 := U1
176 [-]: MOVE      R12 R9       ; R12 := R9
177 [-]: MOVE      R13 R10      ; R13 := R10
178 [-]: CALL      R11 3 1      ; R11(R12,R13)
179 [-]: CONST     R11 1        ; R11 := 1.000000
180 [-]: GETUPVAL  R12 U2       ; R12 := U2
181 [-]: CONST     R13 1        ; R13 := 1.000000
182 [-]: FORPREP   R11 189      ; R11 -= R13; PC := 189
183 [-]: GETUPVAL  R15 U3       ; R15 := U3
184 [-]: GETGLOBAL R16 K48      ; R16 := 0x446637b1
185 [-]: MOVE      R17 R8       ; R17 := R8
186 [-]: MOVE      R18 R2       ; R18 := R2
187 [-]: MOVE      R19 R1       ; R19 := R1
188 [-]: CALL      R15 5 1      ; R15(R16,R17,R18,R19)
189 [-]: FORLOOP   R11 183      ; R11 += R13; if R11 <= R12 then begin PC := 183; R14 := R11 end
190 [-]: GETGLOBAL R15 K49      ; R15 := 0xc163f229
191 [-]: CONST     R16 0        ; R16 := 0.000000
192 [-]: CONST     R17 1        ; R17 := 1.000000
193 [-]: CALL      R15 3 2      ; R15 := R15(R16,R17)
194 [-]: GETUPVAL  R16 U4       ; R16 := U4
195 [-]: LE        0 R15 R16    ; if R15 > R16 then PC := 203
196 [-]: JMP       203          ; PC := 203
197 [-]: GETUPVAL  R15 U3       ; R15 := U3
198 [-]: GETGLOBAL R16 K50      ; R16 := 0x29e88d13
199 [-]: MOVE      R17 R8       ; R17 := R8
200 [-]: MOVE      R18 R2       ; R18 := R2
201 [-]: MOVE      R19 R1       ; R19 := R1
202 [-]: CALL      R15 5 1      ; R15(R16,R17,R18,R19)
203 [-]: GETUPVAL  R15 U5       ; R15 := U5
204 [-]: GETTABLE  R15 R15 K51  ; R15 := R15[0xb43a6753]
205 [-]: MOVE      R16 R0       ; R16 := R0
206 [-]: GETGLOBAL R17 K2       ; R17 := 0x6687f6e0
207 [-]: LOADKB    R18 1 0      ; R18 := true
208 [-]: CALL      R15 4 2      ; R15 := R15(R16,R17,R18)
209 [-]: TEST      R15 0        ; if not R15 then PC := 226
210 [-]: JMP       226          ; PC := 226
211 [-]: GETGLOBAL R16 K52      ; R16 := 0xcfc01047
212 [-]: GETTABLE  R17 R15 K53  ; R17 := R15["hotAvatars"]
213 [-]: CALL      R16 2 4      ; R16,R17,R18 := R16(R17)
214 [-]: JMP       224          ; PC := 224
215 [-]: GETGLOBAL R21 K4       ; R21 := 0x7b998233
216 [-]: MOVE      R22 R20      ; R22 := R20
217 [-]: CALL      R21 2 2      ; R21 := R21(R22)
218 [-]: TEST      R21 1        ; if R21 then PC := 224
219 [-]: JMP       224          ; PC := 224
220 [-]: GETUPVAL  R21 U6       ; R21 := U6
221 [-]: MOVE      R22 R20      ; R22 := R20
222 [-]: LOADKB    R23 0 0      ; R23 := false
223 [-]: CALL      R21 3 1      ; R21(R22,R23)
224 [-]: TFORLOOP  R16 2        ; R19,R20 :=  R16(R17,R18); if R19 ~= nil then begin PC = 215; R18 := R19 end
225 [-]: JMP       215          ; PC := 215
226 [-]: RETURN    R0 1         ; return 


; Function #17:
;
; Name:            
; Defined at line: 566
; #Upvalues:       3
; #Parameters:     2
; Is_vararg:       0
; Max Stack Size:  19

  1 [-]: SELF      R2 R0 K0     ; R3 := R0; R2 := R0[0x5163741e]
  2 [-]: CALL      R2 2 2       ; R2 := R2(R3)
  3 [-]: GETGLOBAL R3 K1        ; R3 := 0x7b998233
  4 [-]: GETGLOBAL R4 K2        ; R4 := 0x6687f6e0
  5 [-]: CALL      R3 2 2       ; R3 := R3(R4)
  6 [-]: TEST      R3 0         ; if not R3 then PC := 13
  7 [-]: JMP       13           ; PC := 13
  8 [-]: GETUPVAL  R3 U0        ; R3 := U0
  9 [-]: MOVE      R4 R2        ; R4 := R2
 10 [-]: LOADKB    R5 0 0       ; R5 := false
 11 [-]: CALL      R3 3 1       ; R3(R4,R5)
 12 [-]: RETURN    R0 1         ; return 
 13 [-]: GETGLOBAL R3 K3        ; R3 := 0x0469f296
 14 [-]: LOADK     R4 K4        ; R4 := "OnProcBlock"
 15 [-]: CALL      R3 2 2       ; R3 := R3(R4)
 16 [-]: SELF      R4 R0 K5     ; R5 := R0; R4 := R0[0x3248ee76]
 17 [-]: GETGLOBAL R6 K2        ; R6 := 0x6687f6e0
 18 [-]: MOVE      R7 R3        ; R7 := R3
 19 [-]: LOADKB    R8 0 0       ; R8 := false
 20 [-]: CALL      R4 5 1       ; R4(R5,R6,R7,R8)
 21 [-]: GETUPVAL  R4 U1        ; R4 := U1
 22 [-]: GETTABLE  R4 R4 K6     ; R4 := R4[0xb43a6753]
 23 [-]: GETGLOBAL R5 K2        ; R5 := 0x6687f6e0
 24 [-]: SELF      R5 R5 K7     ; R6 := R5; R5 := R5[0x3f703537]
 25 [-]: CALL      R5 2 2       ; R5 := R5(R6)
 26 [-]: GETGLOBAL R6 K2        ; R6 := 0x6687f6e0
 27 [-]: CALL      R4 3 2       ; R4 := R4(R5,R6)
 28 [-]: TEST      R4 0         ; if not R4 then PC := 35
 29 [-]: JMP       35           ; PC := 35
 30 [-]: GETGLOBAL R5 K1        ; R5 := 0x7b998233
 31 [-]: GETTABLE  R6 R4 K8     ; R6 := R4["target"]
 32 [-]: CALL      R5 2 2       ; R5 := R5(R6)
 33 [-]: TEST      R5 0         ; if not R5 then PC := 36
 34 [-]: JMP       36           ; PC := 36
 35 [-]: RETURN    R0 1         ; return 
 36 [-]: SELF      R5 R2 K9     ; R6 := R2; R5 := R2[0x003c792f]
 37 [-]: GETGLOBAL R7 K3        ; R7 := 0x0469f296
 38 [-]: LOADK     R8 K10       ; R8 := "GAME_C1_HIP1"
 39 [-]: CALL      R7 2 0       ; R7,... := R7(R8)
 40 [-]: CALL      R5 0 2       ; R5 := R5(R6,...)
 41 [-]: GETGLOBAL R6 K11       ; R6 := 0x00046924
 42 [-]: GETGLOBAL R7 K12       ; R7 := 0x20b7f774
 43 [-]: MOVE      R8 R5        ; R8 := R5
 44 [-]: GETTABLE  R9 R4 K8     ; R9 := R4["target"]
 45 [-]: SELF      R9 R9 K13    ; R10 := R9; R9 := R9[0xd1586535]
 46 [-]: CALL      R9 2 0       ; R9,... := R9(R10)
 47 [-]: CALL      R7 0 2       ; R7 := R7(R8,...)
 48 [-]: GETTABLE  R7 R7 K14    ; R7 := R7["heading"]
 49 [-]: GETGLOBAL R8 K15       ; R8 := 0x5bced4c4
 50 [-]: GETTABLE  R8 R8 K16    ; R8 := R8[0x3630e649]
 51 [-]: CONST     R9 -60       ; R9 := -60.000000
 52 [-]: CONST     R10 -40      ; R10 := -40.000000
 53 [-]: CALL      R8 3 2       ; R8 := R8(R9,R10)
 54 [-]: CONST     R9 0         ; R9 := 0.000000
 55 [-]: CALL      R6 4 2       ; R6 := R6(R7,R8,R9)
 56 [-]: GETGLOBAL R7 K17       ; R7 := 0x89326c93
 57 [-]: SELF      R7 R7 K18    ; R8 := R7; R7 := R7[0x05909209]
 58 [-]: GETGLOBAL R9 K19       ; R9 := 0xd8911fcc
 59 [-]: MOVE      R10 R5       ; R10 := R5
 60 [-]: MOVE      R11 R6       ; R11 := R6
 61 [-]: MOVE      R12 R2       ; R12 := R2
 62 [-]: CALL      R7 6 2       ; R7 := R7(R8,R9,R10,R11,R12)
 63 [-]: GETGLOBAL R8 K2        ; R8 := 0x6687f6e0
 64 [-]: SELF      R8 R8 K7     ; R9 := R8; R8 := R8[0x3f703537]
 65 [-]: CALL      R8 2 2       ; R8 := R8(R9)
 66 [-]: GETGLOBAL R9 K1        ; R9 := 0x7b998233
 67 [-]: MOVE      R10 R7       ; R10 := R7
 68 [-]: CALL      R9 2 2       ; R9 := R9(R10)
 69 [-]: TEST      R9 1         ; if R9 then PC := 80
 70 [-]: JMP       80           ; PC := 80
 71 [-]: SELF      R9 R7 K20    ; R10 := R7; R9 := R7[0x263a3cc2]
 72 [-]: MOVE      R11 R2       ; R11 := R2
 73 [-]: CALL      R9 3 1       ; R9(R10,R11)
 74 [-]: SELF      R9 R7 K21    ; R10 := R7; R9 := R7[0xfe447379]
 75 [-]: MOVE      R11 R8       ; R11 := R8
 76 [-]: CALL      R9 3 1       ; R9(R10,R11)
 77 [-]: SELF      R9 R7 K22    ; R10 := R7; R9 := R7[0x419785d7]
 78 [-]: GETTABLE  R11 R4 K8    ; R11 := R4["target"]
 79 [-]: CALL      R9 3 1       ; R9(R10,R11)
 80 [-]: CONST     R9 1         ; R9 := 1.000000
 81 [-]: CONST     R10 3        ; R10 := 3.000000
 82 [-]: CONST     R11 1        ; R11 := 1.000000
 83 [-]: FORPREP   R9 103       ; R9 -= R11; PC := 103
 84 [-]: GETGLOBAL R13 K17      ; R13 := 0x89326c93
 85 [-]: SELF      R13 R13 K18  ; R14 := R13; R13 := R13[0x05909209]
 86 [-]: GETGLOBAL R15 K23      ; R15 := 0x5633f0a6
 87 [-]: MOVE      R16 R5       ; R16 := R5
 88 [-]: GETGLOBAL R17 K24      ; R17 := ZERO_ROTATION
 89 [-]: MOVE      R18 R8       ; R18 := R8
 90 [-]: CALL      R13 6 2      ; R13 := R13(R14,R15,R16,R17,R18)
 91 [-]: GETGLOBAL R14 K1       ; R14 := 0x7b998233
 92 [-]: MOVE      R15 R13      ; R15 := R13
 93 [-]: CALL      R14 2 2      ; R14 := R14(R15)
 94 [-]: TEST      R14 1        ; if R14 then PC := 103
 95 [-]: JMP       103          ; PC := 103
 96 [-]: SELF      R14 R13 K25  ; R15 := R13; R14 := R13[0x5b7a8013]
 97 [-]: GETTABLE  R16 R4 K8    ; R16 := R4["target"]
 98 [-]: GETGLOBAL R17 K3       ; R17 := 0x0469f296
 99 [-]: LOADK     R18 K26      ; R18 := "GAME_C1_SPINE2"
100 [-]: CALL      R17 2 2      ; R17 := R17(R18)
101 [-]: CONST     R18 0        ; R18 := 0.750000
102 [-]: CALL      R14 5 1      ; R14(R15,R16,R17,R18)
103 [-]: FORLOOP   R9 84        ; R9 += R11; if R9 <= R10 then begin PC := 84; R12 := R9 end
104 [-]: GETGLOBAL R14 K27      ; R14 := 0xcbd666e1
105 [-]: GETUPVAL  R15 U2       ; R15 := U2
106 [-]: CALL      R14 2 1      ; R14(R15)
107 [-]: GETGLOBAL R14 K1       ; R14 := 0x7b998233
108 [-]: GETGLOBAL R15 K2       ; R15 := 0x6687f6e0
109 [-]: CALL      R14 2 2      ; R14 := R14(R15)
110 [-]: TEST      R14 1        ; if R14 then PC := 117
111 [-]: JMP       117          ; PC := 117
112 [-]: SELF      R14 R0 K5    ; R15 := R0; R14 := R0[0x3248ee76]
113 [-]: GETGLOBAL R16 K2       ; R16 := 0x6687f6e0
114 [-]: MOVE      R17 R3       ; R17 := R3
115 [-]: LOADKB    R18 1 0      ; R18 := true
116 [-]: CALL      R14 5 1      ; R14(R15,R16,R17,R18)
117 [-]: RETURN    R0 1         ; return 


; Function #18:
;
; Name:            
; Defined at line: 607
; #Upvalues:       1
; #Parameters:     2
; Is_vararg:       0
; Max Stack Size:  11

  1 [-]: GETGLOBAL R2 K0        ; R2 := 0x89326c93
  2 [-]: SELF      R2 R2 K1     ; R3 := R2; R2 := R2[0x18d05d30]
  3 [-]: CALL      R2 2 2       ; R2 := R2(R3)
  4 [-]: TEST      R2 0         ; if not R2 then PC := 15
  5 [-]: JMP       15           ; PC := 15
  6 [-]: GETGLOBAL R2 K2        ; R2 := 0x7b998233
  7 [-]: MOVE      R3 R1        ; R3 := R1
  8 [-]: CALL      R2 2 2       ; R2 := R2(R3)
  9 [-]: TEST      R2 1         ; if R2 then PC := 15
 10 [-]: JMP       15           ; PC := 15
 11 [-]: SELF      R2 R0 K3     ; R3 := R0; R2 := R0[0xf5527472]
 12 [-]: CALL      R2 2 2       ; R2 := R2(R3)
 13 [-]: EQ        1 R1 R2      ; if R1 == R2 then PC := 16
 14 [-]: JMP       16           ; PC := 16
 15 [-]: RETURN    R0 1         ; return 
 16 [-]: SELF      R2 R1 K4     ; R3 := R1; R2 := R1[0x1ac1655c]
 17 [-]: CALL      R2 2 2       ; R2 := R2(R3)
 18 [-]: SELF      R3 R1 K5     ; R4 := R1; R3 := R1[0xb40c191a]
 19 [-]: CALL      R3 2 2       ; R3 := R3(R4)
 20 [-]: GETUPVAL  R4 U0        ; R4 := U0
 21 [-]: MUL       R3 R3 R4     ; R3 := R3 * R4
 22 [-]: SELF      R4 R1 K6     ; R5 := R1; R4 := R1[0xd2715720]
 23 [-]: CALL      R4 2 2       ; R4 := R4(R5)
 24 [-]: SELF      R5 R2 K7     ; R6 := R2; R5 := R2[0xfe9ed1e0]
 25 [-]: CALL      R5 2 2       ; R5 := R5(R6)
 26 [-]: SUB       R6 R4 R5     ; R6 := R4 - R5
 27 [-]: LT        0 R3 R6      ; if R3 >= R6 then PC := 33
 28 [-]: JMP       33           ; PC := 33
 29 [-]: SELF      R6 R1 K8     ; R7 := R1; R6 := R1[0x014db014]
 30 [-]: SUB       R8 R4 R3     ; R8 := R4 - R3
 31 [-]: CALL      R6 3 1       ; R6(R7,R8)
 32 [-]: JMP       56           ; PC := 56
 33 [-]: SELF      R6 R2 K9     ; R7 := R2; R6 := R2[0xd8b8c436]
 34 [-]: LOADKB    R8 0 0       ; R8 := false
 35 [-]: CALL      R6 3 1       ; R6(R7,R8)
 36 [-]: GETGLOBAL R6 K10       ; R6 := 0x34291f5c
 37 [-]: GETTABLE  R6 R6 K11    ; R6 := R6[0x35c16153]
 38 [-]: CALL      R6 1 2       ; R6 := R6()
 39 [-]: SETTABLE  R6 K12 R3    ; R6["baseAmount"] := R3
 40 [-]: SELF      R7 R6 K13    ; R8 := R6; R7 := R6[0x1586e35e]
 41 [-]: CONST     R9 17        ; R9 := 17.000000
 42 [-]: CONST     R10 1        ; R10 := 1.000000
 43 [-]: CALL      R7 4 1       ; R7(R8,R9,R10)
 44 [-]: SELF      R7 R6 K14    ; R8 := R6; R7 := R6[0x86cd00cb]
 45 [-]: SELF      R9 R0 K15    ; R10 := R0; R9 := R0[0xcd73323e]
 46 [-]: CALL      R9 2 0       ; R9,... := R9(R10)
 47 [-]: CALL      R7 0 1       ; R7(R8,...)
 48 [-]: SELF      R7 R6 K16    ; R8 := R6; R7 := R6[0xf4dc3420]
 49 [-]: SELF      R9 R0 K17    ; R10 := R0; R9 := R0[0x71c3065d]
 50 [-]: CALL      R9 2 0       ; R9,... := R9(R10)
 51 [-]: CALL      R7 0 1       ; R7(R8,...)
 52 [-]: SETTABLE  R6 K18 K19   ; R6["instantKill"] := true
 53 [-]: SELF      R7 R1 K20    ; R8 := R1; R7 := R1[0x479483bb]
 54 [-]: MOVE      R9 R6        ; R9 := R6
 55 [-]: CALL      R7 3 1       ; R7(R8,R9)
 56 [-]: RETURN    R0 1         ; return 


